{
  "type": "Feature",
  "properties": {
    "gn:admin1_code":"19.0",
    "gn:asciiname":"Yangshanling",
    "gn:country_code":"CN",
    "gn:dem":263,
    "gn:feature_class":"P",
    "gn:feature_code":"PPL",
    "gn:name":"Yangshanling",
    "gn:population":0,
    "gn:timezone":"Asia/Shanghai",
    "iso:country":"CN",
    "name:zho_x_preferred":[
        "\u7f8a\u5c71\u5cad"
    ],
    "wof:name":"Yangshanling",
    "wof:placetype":"locality"
},
  "geometry": {"coordinates":[120.76300000000001,41.3633],"type":"Point"}
}