{
  "type": "Feature",
  "properties": {
    "gn:admin1_code":"10.0",
    "gn:asciiname":"Yingtou",
    "gn:country_code":"CN",
    "gn:dem":247,
    "gn:feature_class":"P",
    "gn:feature_code":"PPL",
    "gn:name":"Yingtou",
    "gn:population":0,
    "gn:timezone":"Asia/Shanghai",
    "iso:country":"CN",
    "name:und_x_variant":[
        "Ying-t\u2019ou-chen",
        "Yingtou"
    ],
    "name:zho_x_preferred":[
        "\u8425\u5934"
    ],
    "wof:name":"Yingtou",
    "wof:placetype":"locality"
},
  "geometry": {"coordinates":[114.13200000000001,37.0559],"type":"Point"}
}