{
  "type": "Feature",
  "properties": {
    "gn:admin1_code":"15.0",
    "gn:asciiname":"Xiaoguan",
    "gn:country_code":"CN",
    "gn:dem":2108,
    "gn:feature_class":"P",
    "gn:feature_code":"PPL",
    "gn:name":"Xiaoguan",
    "gn:population":0,
    "gn:timezone":"Asia/Shanghai",
    "iso:country":"CN",
    "name:und_x_variant":[
        "\u5c0f\u5173"
    ],
    "name:zho_x_preferred":[
        "\u5c0f\u5173"
    ],
    "wof:name":"Xiaoguan",
    "wof:placetype":"locality"
},
  "geometry": {"coordinates":[104.82762,34.01439],"type":"Point"}
}