{
  "type": "Feature",
  "properties": {
    "gn:admin1_code":"32.0",
    "gn:asciiname":"Xiaoshidang",
    "gn:country_code":"CN",
    "gn:dem":356,
    "gn:feature_class":"P",
    "gn:feature_code":"PPL",
    "gn:name":"Xiaoshidang",
    "gn:population":0,
    "gn:timezone":"Asia/Shanghai",
    "iso:country":"CN",
    "name:zho_x_preferred":[
        "\u5c0f\u77f3\u51fc"
    ],
    "wof:name":"Xiaoshidang",
    "wof:placetype":"locality"
},
  "geometry": {"coordinates":[107.259,30.9245],"type":"Point"}
}