{
  "type": "Feature",
  "properties": {
    "gn:admin1_code":"32.0",
    "gn:asciiname":"Shiwei",
    "gn:country_code":"CN",
    "gn:dem":861,
    "gn:feature_class":"P",
    "gn:feature_code":"PPL",
    "gn:name":"Shiwei",
    "gn:population":0,
    "gn:timezone":"Asia/Shanghai",
    "iso:country":"CN",
    "name:aze_x_preferred":[
        "\u015eiveyl\u0259r"
    ],
    "name:bul_x_preferred":[
        "\u0428\u044a\u0443\u0435\u0439"
    ],
    "name:mon_x_preferred":[
        "\u0428\u0438\u0432\u044d\u0439"
    ],
    "name:rus_x_preferred":[
        "\u0428\u0438\u0432\u044d\u0439"
    ],
    "name:szl_x_preferred":[
        "Siy\u0142eje"
    ],
    "name:ukr_x_preferred":[
        "\u0428\u0438\u0432\u0435\u0439"
    ],
    "name:und_x_variant":[
        "\u77f3\u6845"
    ],
    "wof:name":"Shiwei",
    "wof:placetype":"locality"
},
  "geometry": {"coordinates":[106.29874,32.17726],"type":"Point"}
}