{
  "type": "Feature",
  "properties": {
    "gn:admin1_code":"15.0",
    "gn:asciiname":"Zhenshan",
    "gn:country_code":"CN",
    "gn:dem":2328,
    "gn:feature_class":"P",
    "gn:feature_code":"PPL",
    "gn:name":"Zhenshan",
    "gn:population":0,
    "gn:timezone":"Asia/Shanghai",
    "iso:country":"CN",
    "name:und_x_variant":[
        "\u73cd\u5c71"
    ],
    "name:zho_x_preferred":[
        "\u73cd\u5c71"
    ],
    "wof:name":"Zhenshan",
    "wof:placetype":"locality"
},
  "geometry": {"coordinates":[104.89197,33.5412],"type":"Point"}
}