{
  "type": "Feature",
  "properties": {
    "gn:admin1_code":"31.0",
    "gn:asciiname":"Dayong",
    "gn:country_code":"CN",
    "gn:dem":119,
    "gn:feature_class":"P",
    "gn:feature_code":"PPL",
    "gn:name":"Dayong",
    "gn:population":0,
    "gn:timezone":"Asia/Shanghai",
    "iso:country":"CN",
    "name:zho_x_preferred":[
        "Dayong"
    ],
    "name:zho_x_variant":[
        "\u5927\u52c7"
    ],
    "wof:name":"Dayong",
    "wof:placetype":"locality"
},
  "geometry": {"coordinates":[110.56702,19.44803],"type":"Point"}
}