{
  "type": "Feature",
  "properties": {
    "gn:admin1_code":"1.0",
    "gn:asciiname":"Takeng",
    "gn:country_code":"CN",
    "gn:dem":311,
    "gn:feature_class":"P",
    "gn:feature_code":"PPL",
    "gn:name":"Takeng",
    "gn:population":0,
    "gn:timezone":"Asia/Shanghai",
    "iso:country":"CN",
    "name:zho_x_preferred":[
        "\u5854\u5751"
    ],
    "wof:name":"Takeng",
    "wof:placetype":"locality"
},
  "geometry": {"coordinates":[118.73156000000002,29.77305],"type":"Point"}
}