{
  "type": "Feature",
  "properties": {
    "gn:admin1_code":"19.0",
    "gn:asciiname":"Yinzhuangzicun",
    "gn:country_code":"CN",
    "gn:dem":87,
    "gn:feature_class":"P",
    "gn:feature_code":"PPL",
    "gn:name":"Yinzhuangzicun",
    "gn:population":0,
    "gn:timezone":"Asia/Shanghai",
    "iso:country":"CN",
    "name:zho_x_preferred":[
        "\u94f6\u5e84\u5b50\u6751"
    ],
    "wof:name":"Yinzhuangzicun",
    "wof:placetype":"locality"
},
  "geometry": {"coordinates":[120.042,40.311],"type":"Point"}
}