{
  "type": "Feature",
  "properties": {
    "gn:admin1_code":"32.0",
    "gn:asciiname":"Wangjia Citang",
    "gn:country_code":"CN",
    "gn:dem":452,
    "gn:feature_class":"P",
    "gn:feature_code":"PPL",
    "gn:name":"Wangjia Citang",
    "gn:population":0,
    "gn:timezone":"Asia/Shanghai",
    "iso:country":"CN",
    "name:zho_x_preferred":[
        "\u738b\u5bb6\u7960\u5802"
    ],
    "wof:name":"Wangjia Citang",
    "wof:placetype":"locality"
},
  "geometry": {"coordinates":[105.22499999999999,30.9729],"type":"Point"}
}