{
  "type": "Feature",
  "properties": {
    "gn:admin1_code":"29.0",
    "gn:asciiname":"Xiaheiwan",
    "gn:country_code":"CN",
    "gn:dem":2360,
    "gn:feature_class":"P",
    "gn:feature_code":"PPL",
    "gn:name":"Xiaheiwan",
    "gn:population":0,
    "gn:timezone":"Asia/Shanghai",
    "iso:country":"CN",
    "name:zho_x_preferred":[
        "\u4e0b\u9ed1\u6e7e"
    ],
    "wof:name":"Xiaheiwan",
    "wof:placetype":"locality"
},
  "geometry": {"coordinates":[99.9327,26.2653],"type":"Point"}
}