{
  "type": "Feature",
  "properties": {
    "gn:admin1_code":"14.0",
    "gn:asciiname":"Delalin",
    "gn:country_code":"CN",
    "gn:dem":4004,
    "gn:feature_class":"P",
    "gn:feature_code":"PPL",
    "gn:name":"Delalin",
    "gn:population":0,
    "gn:timezone":"Asia/Shanghai",
    "iso:country":"CN",
    "name:zho_x_preferred":[
        "\u5fb7\u62c9\u6797"
    ],
    "wof:name":"Delalin",
    "wof:placetype":"locality"
},
  "geometry": {"coordinates":[81.1554,30.3318],"type":"Point"}
}