{
  "type": "Feature",
  "properties": {
    "gn:admin1_code":"4.0",
    "gn:asciiname":"Daliuzhuang",
    "gn:country_code":"CN",
    "gn:dem":4,
    "gn:feature_class":"P",
    "gn:feature_code":"PPL",
    "gn:name":"Daliuzhuang",
    "gn:population":0,
    "gn:timezone":"Asia/Shanghai",
    "iso:country":"CN",
    "name:zho_x_preferred":[
        "Daliuzhuang"
    ],
    "name:zho_x_variant":[
        "\u5927\u5218\u5e84"
    ],
    "wof:name":"Daliuzhuang",
    "wof:placetype":"locality"
},
  "geometry": {"coordinates":[119.25503999999999,34.34087],"type":"Point"}
}