{
  "type": "Feature",
  "properties": {
    "gn:admin1_code":"26.0",
    "gn:asciiname":"Jiandongcun",
    "gn:country_code":"CN",
    "gn:dem":672,
    "gn:feature_class":"P",
    "gn:feature_code":"PPL",
    "gn:name":"Jiandongcun",
    "gn:population":0,
    "gn:timezone":"Asia/Shanghai",
    "iso:country":"CN",
    "name:zho_x_preferred":[
        "\u6da7\u4e1c\u6751"
    ],
    "wof:name":"Jiandongcun",
    "wof:placetype":"locality"
},
  "geometry": {"coordinates":[110.44163,35.70442],"type":"Point"}
}