{
  "type": "Feature",
  "properties": {
    "gn:admin1_code":"1.0",
    "gn:asciiname":"Zhenjuncun",
    "gn:country_code":"CN",
    "gn:dem":92,
    "gn:feature_class":"P",
    "gn:feature_code":"PPL",
    "gn:name":"Zhenjuncun",
    "gn:population":0,
    "gn:timezone":"Asia/Shanghai",
    "iso:country":"CN",
    "name:zho_x_preferred":[
        "\u771f\u541b\u6751"
    ],
    "wof:name":"Zhenjuncun",
    "wof:placetype":"locality"
},
  "geometry": {"coordinates":[115.98511000000001,30.54572000000001],"type":"Point"}
}