{
  "type": "Feature",
  "properties": {
    "gn:admin1_code":"26.0",
    "gn:asciiname":"Yaoyacun",
    "gn:country_code":"CN",
    "gn:dem":1133,
    "gn:feature_class":"P",
    "gn:feature_code":"PPL",
    "gn:name":"Yaoyacun",
    "gn:population":0,
    "gn:timezone":"Asia/Shanghai",
    "iso:country":"CN",
    "name:zho_x_preferred":[
        "\u8170\u5d16\u6751"
    ],
    "wof:name":"Yaoyacun",
    "wof:placetype":"locality"
},
  "geometry": {"coordinates":[107.30968,34.92883],"type":"Point"}
}