{
  "type": "Feature",
  "properties": {
    "gn:admin1_code":"32.0",
    "gn:asciiname":"Shangluanshanzi",
    "gn:country_code":"CN",
    "gn:dem":1469,
    "gn:feature_class":"P",
    "gn:feature_code":"PPL",
    "gn:name":"Shangluanshanzi",
    "gn:population":0,
    "gn:timezone":"Asia/Shanghai",
    "iso:country":"CN",
    "name:zho_x_preferred":[
        "\u4e0a\u4e71\u5c71\u5b50"
    ],
    "wof:name":"Shangluanshanzi",
    "wof:placetype":"locality"
},
  "geometry": {"coordinates":[103.483,28.8117],"type":"Point"}
}