{
  "type": "Feature",
  "properties": {
    "gn:admin1_code":"14.0",
    "gn:asciiname":"Duo'ersuocun",
    "gn:country_code":"CN",
    "gn:dem":4593,
    "gn:feature_class":"P",
    "gn:feature_code":"PPL",
    "gn:name":"Duo\u2019ersuocun",
    "gn:population":0,
    "gn:timezone":"Asia/Urumqi",
    "iso:country":"CN",
    "name:und_x_variant":[
        "Duo\u2019ersuocun"
    ],
    "name:zho_x_preferred":[
        "\u591a\u5c14\u7d22\u6751"
    ],
    "wof:name":"Duo'ersuocun",
    "wof:placetype":"locality"
},
  "geometry": {"coordinates":[92.39328,31.65111],"type":"Point"}
}