{
  "type": "Feature",
  "properties": {
    "gn:admin1_code":"1.0",
    "gn:asciiname":"Shujiawu",
    "gn:country_code":"CN",
    "gn:dem":220,
    "gn:feature_class":"P",
    "gn:feature_code":"PPL",
    "gn:name":"Shujiawu",
    "gn:population":0,
    "gn:timezone":"Asia/Shanghai",
    "iso:country":"CN",
    "name:zho_x_preferred":[
        "\u8212\u5bb6\u575e"
    ],
    "wof:name":"Shujiawu",
    "wof:placetype":"locality"
},
  "geometry": {"coordinates":[117.50909,29.9286],"type":"Point"}
}