{
  "type": "Feature",
  "properties": {
    "gn:admin1_code":"18",
    "gn:asciiname":"Weisuoming",
    "gn:country_code":"CN",
    "gn:dem":2022,
    "gn:feature_class":"P",
    "gn:feature_code":"PPL",
    "gn:name":"Weisuoming",
    "gn:population":0,
    "gn:timezone":"Asia/Shanghai",
    "iso:country":"CN",
    "name:zho_x_preferred":[
        "\u5a01\u68ad\u660e"
    ],
    "wof:name":"Weisuoming",
    "wof:placetype":"locality"
},
  "geometry": {"coordinates":[104.50700000000001,27.1925],"type":"Point"}
}