{
  "type": "Feature",
  "properties": {
    "gn:admin1_code":"7.0",
    "gn:asciiname":"Caoyang",
    "gn:country_code":"CN",
    "gn:dem":302,
    "gn:feature_class":"P",
    "gn:feature_code":"PPL",
    "gn:name":"Caoyang",
    "gn:population":0,
    "gn:timezone":"Asia/Shanghai",
    "iso:country":"CN",
    "name:zho_x_preferred":[
        "Caoyang"
    ],
    "name:zho_x_variant":[
        "\u66f9\u6d0b"
    ],
    "wof:name":"Caoyang",
    "wof:placetype":"locality"
},
  "geometry": {"coordinates":[118.76000000000001,26.54861],"type":"Point"}
}