{
  "type": "Feature",
  "properties": {
    "gn:admin1_code":"2.0",
    "gn:asciiname":"Wangfeng",
    "gn:country_code":"CN",
    "gn:dem":83,
    "gn:feature_class":"P",
    "gn:feature_code":"PPL",
    "gn:name":"Wangfeng",
    "gn:population":0,
    "gn:timezone":"Asia/Shanghai",
    "iso:country":"CN",
    "name:zho_x_preferred":[
        "\u738b\u5cf0"
    ],
    "name:zho_x_variant":[
        "\u738b\u5949\u9547"
    ],
    "wof:name":"Wangfeng",
    "wof:placetype":"locality"
},
  "geometry": {"coordinates":[120.25515,29.30196],"type":"Point"}
}