{
  "type": "Feature",
  "properties": {
    "gn:admin1_code":"16.0",
    "gn:asciiname":"Beitouwan",
    "gn:country_code":"CN",
    "gn:dem":315,
    "gn:feature_class":"P",
    "gn:feature_code":"PPL",
    "gn:name":"Beitouwan",
    "gn:population":0,
    "gn:timezone":"Asia/Shanghai",
    "iso:country":"CN",
    "name:zho_x_preferred":[
        "\u7891\u5934\u6e7e"
    ],
    "wof:name":"Beitouwan",
    "wof:placetype":"locality"
},
  "geometry": {"coordinates":[110.553,22.6096],"type":"Point"}
}