{
  "type": "Feature",
  "properties": {
    "gn:admin1_code":"02",
    "gn:asciiname":"Dingtian",
    "gn:country_code":"CN",
    "gn:dem":7,
    "gn:feature_class":"P",
    "gn:feature_code":"PPL",
    "gn:name":"Dingtian",
    "gn:population":0,
    "gn:timezone":"Asia/Shanghai",
    "iso:country":"CN",
    "name:zho_x_preferred":[
        "Ting-t\u2019ien"
    ],
    "name:zho_x_variant":[
        "\u6c40\u7530"
    ],
    "wof:name":"Dingtian",
    "wof:placetype":"locality"
},
  "geometry": {"coordinates":[120.69783,27.79865],"type":"Point"}
}