{
  "type": "Feature",
  "properties": {
    "gn:admin1_code":"4.0",
    "gn:asciiname":"Guojiadai",
    "gn:country_code":"CN",
    "gn:dem":3,
    "gn:feature_class":"P",
    "gn:feature_code":"PPL",
    "gn:name":"Guojiadai",
    "gn:population":0,
    "gn:timezone":"Asia/Shanghai",
    "iso:country":"CN",
    "name:und_x_variant":[
        "\u90ed\u5bb6\u5788"
    ],
    "name:zho_x_preferred":[
        "\u90ed\u5bb6\u5788"
    ],
    "wof:name":"Guojiadai",
    "wof:placetype":"locality"
},
  "geometry": {"coordinates":[120.29002,32.10191],"type":"Point"}
}