{
  "type": "Feature",
  "properties": {
    "gn:admin1_code":"16.0",
    "gn:asciiname":"Li'an",
    "gn:country_code":"CN",
    "gn:dem":53,
    "gn:feature_class":"P",
    "gn:feature_code":"PPL",
    "gn:name":"Li\u2019an",
    "gn:population":0,
    "gn:timezone":"Asia/Shanghai",
    "iso:country":"CN",
    "name:und_x_variant":[
        "Li\u2019an"
    ],
    "name:zho_x_preferred":[
        "\u793c\u5cb8"
    ],
    "wof:name":"Li'an",
    "wof:placetype":"locality"
},
  "geometry": {"coordinates":[111.56699999999999,23.8172],"type":"Point"}
}