{
  "type": "Feature",
  "properties": {
    "gn:admin1_code":"30.0",
    "gn:asciiname":"Xianyancun",
    "gn:country_code":"CN",
    "gn:dem":21,
    "gn:feature_class":"P",
    "gn:feature_code":"PPL",
    "gn:name":"Xianyancun",
    "gn:population":0,
    "gn:timezone":"Asia/Shanghai",
    "iso:country":"CN",
    "name:zho_x_preferred":[
        "\u4ed9\u5ca9\u6751"
    ],
    "wof:name":"Xianyancun",
    "wof:placetype":"locality"
},
  "geometry": {"coordinates":[116.78555,23.62561],"type":"Point"}
}