{
  "type": "Feature",
  "properties": {
    "gn:admin1_code":"2.0",
    "gn:asciiname":"Hufasi",
    "gn:country_code":"CN",
    "gn:dem":10,
    "gn:feature_class":"P",
    "gn:feature_code":"PPL",
    "gn:name":"Hufasi",
    "gn:population":0,
    "gn:timezone":"Asia/Shanghai",
    "iso:country":"CN",
    "name:und_x_variant":[
        "\u62a4\u6cd5\u5bfa"
    ],
    "wof:name":"Hufasi",
    "wof:placetype":"locality"
},
  "geometry": {"coordinates":[119.73943,30.88033],"type":"Point"}
}