{
  "type": "Feature",
  "properties": {
    "gn:admin1_code":"11",
    "gn:asciiname":"Shiyan",
    "gn:country_code":"CN",
    "gn:dem":332,
    "gn:feature_class":"P",
    "gn:feature_code":"PPL",
    "gn:name":"Shiyan",
    "gn:population":0,
    "gn:timezone":"Asia/Shanghai",
    "iso:country":"CN",
    "name:zho_x_preferred":[
        "\u77f3\u71d5"
    ],
    "wof:name":"Shiyan",
    "wof:placetype":"locality"
},
  "geometry": {"coordinates":[110.90111,27.20167],"type":"Point"}
}