{
  "type": "Feature",
  "properties": {
    "gn:admin1_code":"11",
    "gn:asciiname":"Shiyan",
    "gn:country_code":"CN",
    "gn:dem":332,
    "gn:feature_class":"P",
    "gn:feature_code":"PPL",
    "gn:name":"Shiyan",
    "gn:population":0,
    "gn:timezone":"Asia/Shanghai",
    "iso:country":"CN",
    "name:ara_x_preferred":[
        "\u0634\u064a\u0627\u0646"
    ],
    "name:bul_x_preferred":[
        "\u0428\u044a\u0439\u0435\u043d"
    ],
    "name:cdo_x_preferred":[
        "S\u0115k-i\u0113ng"
    ],
    "name:ceb_x_preferred":[
        "Shiyan"
    ],
    "name:ces_x_preferred":[
        "\u0160\u2019-jen"
    ],
    "name:dan_x_preferred":[
        "Shiyan"
    ],
    "name:deu_x_preferred":[
        "Shiyan"
    ],
    "name:eus_x_preferred":[
        "Shiyan"
    ],
    "name:fas_x_preferred":[
        "\u0634\u06cc\u06cc\u0627\u0646"
    ],
    "name:fin_x_preferred":[
        "Shiyan"
    ],
    "name:fra_x_preferred":[
        "Shiyan"
    ],
    "name:ita_x_preferred":[
        "Shiyan"
    ],
    "name:jpn_x_preferred":[
        "\u5341\u5830\u5e02"
    ],
    "name:kik_x_preferred":[
        "Shiyan"
    ],
    "name:kor_x_preferred":[
        "\uc2a4\uc60c\uc2dc"
    ],
    "name:mlg_x_preferred":[
        "Shiyan"
    ],
    "name:nld_x_preferred":[
        "Shiyan"
    ],
    "name:nno_x_preferred":[
        "Shiyan"
    ],
    "name:nor_x_preferred":[
        "Shiyan"
    ],
    "name:pam_x_preferred":[
        "Shiyan"
    ],
    "name:pol_x_preferred":[
        "Shiyan"
    ],
    "name:rus_x_preferred":[
        "\u0428\u0438\u044f\u043d\u044c"
    ],
    "name:spa_x_preferred":[
        "Shiyan"
    ],
    "name:srp_x_preferred":[
        "\u0428\u0438\u0458\u0435\u043d"
    ],
    "name:swe_x_preferred":[
        "Shiyan"
    ],
    "name:tgl_x_preferred":[
        "Shiyan"
    ],
    "name:tur_x_preferred":[
        "Shiyan"
    ],
    "name:urd_x_preferred":[
        "\u0634\u06cc\u06cc\u0627\u0646"
    ],
    "name:vie_x_preferred":[
        "Th\u1eadp Y\u1ec3n"
    ],
    "name:war_x_preferred":[
        "Shiyan"
    ],
    "name:zho_x_preferred":[
        "\u77f3\u71d5"
    ],
    "name:zho_x_variant":[
        "\u5341\u5830\u5e02"
    ],
    "wof:name":"Shiyan",
    "wof:placetype":"locality"
},
  "geometry": {"coordinates":[110.90111,27.20167],"type":"Point"}
}