{
  "type": "Feature",
  "properties": {
    "gn:admin1_code":"29.0",
    "gn:asciiname":"Zhongzhai",
    "gn:country_code":"CN",
    "gn:dem":1603,
    "gn:feature_class":"P",
    "gn:feature_code":"PPL",
    "gn:name":"Zhongzhai",
    "gn:population":0,
    "gn:timezone":"Asia/Shanghai",
    "iso:country":"CN",
    "name:zho_x_preferred":[
        "\u4e2d\u5be8"
    ],
    "name:zho_x_variant":[
        "\u4e2d\u5be8\u9547"
    ],
    "wof:name":"Zhongzhai",
    "wof:placetype":"locality"
},
  "geometry": {"coordinates":[97.7565,24.3856],"type":"Point"}
}