{
  "type": "Feature",
  "properties": {
    "gn:admin1_code":"11",
    "gn:asciiname":"Lizigang",
    "gn:country_code":"CN",
    "gn:dem":299,
    "gn:feature_class":"P",
    "gn:feature_code":"PPL",
    "gn:name":"Lizigang",
    "gn:population":0,
    "gn:timezone":"Asia/Shanghai",
    "iso:country":"CN",
    "name:zho_x_preferred":[
        "\u6817\u5b50\u6e2f"
    ],
    "wof:name":"Lizigang",
    "wof:placetype":"locality"
},
  "geometry": {"coordinates":[112.26091,27.80178],"type":"Point"}
}