{
  "type": "Feature",
  "properties": {
    "gn:admin1_code":"29.0",
    "gn:asciiname":"Ciba",
    "gn:country_code":"CN",
    "gn:dem":1755,
    "gn:feature_class":"P",
    "gn:feature_code":"PPL",
    "gn:name":"Ciba",
    "gn:population":0,
    "gn:timezone":"Asia/Shanghai",
    "iso:country":"CN",
    "name:ceb_x_preferred":[
        "Ciba"
    ],
    "name:deu_x_preferred":[
        "Ciba"
    ],
    "name:epo_x_preferred":[
        "Ciba"
    ],
    "name:hun_x_preferred":[
        "Ciba"
    ],
    "name:ron_x_preferred":[
        "Ciba"
    ],
    "name:swe_x_preferred":[
        "Ciba"
    ],
    "name:zho_x_preferred":[
        "\u8328\u82ad"
    ],
    "wof:name":"Ciba",
    "wof:placetype":"locality"
},
  "geometry": {"coordinates":[100.416,25.3719],"type":"Point"}
}