{
  "type": "Feature",
  "properties": {
    "gn:admin1_code":"15.0",
    "gn:asciiname":"Bazhiyao",
    "gn:country_code":"CN",
    "gn:dem":1563,
    "gn:feature_class":"P",
    "gn:feature_code":"PPL",
    "gn:name":"Bazhiyao",
    "gn:population":0,
    "gn:timezone":"Asia/Shanghai",
    "iso:country":"CN",
    "name:zho_x_preferred":[
        "\u516b\u53ea\u7a91"
    ],
    "wof:name":"Bazhiyao",
    "wof:placetype":"locality"
},
  "geometry": {"coordinates":[108.47799999999999,35.6296],"type":"Point"}
}