{
  "type": "Feature",
  "properties": {
    "gn:admin1_code":"30",
    "gn:asciiname":"Chaoyangshifan Nongchang",
    "gn:country_code":"CN",
    "gn:dem":8,
    "gn:feature_class":"P",
    "gn:feature_code":"PPLF",
    "gn:name":"Chaoyangshifan Nongchang",
    "gn:population":0,
    "gn:timezone":"Asia/Shanghai",
    "iso:country":"CN",
    "wof:name":"Chaoyangshifan Nongchang",
    "wof:placetype":"locality"
},
  "geometry": {"coordinates":[116.50848999999999,23.26219],"type":"Point"}
}