{
  "type": "Feature",
  "properties": {
    "gn:admin1_code":"14",
    "gn:asciiname":"Pule",
    "gn:country_code":"CN",
    "gn:dem":4724,
    "gn:feature_class":"P",
    "gn:feature_code":"PPL",
    "gn:name":"Pule",
    "gn:population":0,
    "gn:timezone":"Asia/Urumqi",
    "iso:country":"CN",
    "name:zho_x_preferred":[
        "\u6251\u52d2"
    ],
    "wof:name":"Pule",
    "wof:placetype":"locality"
},
  "geometry": {"coordinates":[88.80799999999998,28.6742],"type":"Point"}
}