{
  "type": "Feature",
  "properties": {
    "gn:admin1_code":"26.0",
    "gn:asciiname":"Neiyuancun",
    "gn:country_code":"CN",
    "gn:dem":473,
    "gn:feature_class":"P",
    "gn:feature_code":"PPL",
    "gn:name":"Neiyuancun",
    "gn:population":0,
    "gn:timezone":"Asia/Shanghai",
    "iso:country":"CN",
    "name:zho_x_preferred":[
        "\u5185\u82d1\u6751"
    ],
    "wof:name":"Neiyuancun",
    "wof:placetype":"locality"
},
  "geometry": {"coordinates":[108.85683,34.05548],"type":"Point"}
}