{
  "type": "Feature",
  "properties": {
    "gn:admin1_code":"31.0",
    "gn:asciiname":"Xionghe",
    "gn:country_code":"CN",
    "gn:dem":44,
    "gn:feature_class":"P",
    "gn:feature_code":"PPL",
    "gn:name":"Xionghe",
    "gn:population":0,
    "gn:timezone":"Asia/Shanghai",
    "iso:country":"CN",
    "name:zho_x_preferred":[
        "\u96c4\u8d6b"
    ],
    "wof:name":"Xionghe",
    "wof:placetype":"locality"
},
  "geometry": {"coordinates":[110.35375999999999,19.89506],"type":"Point"}
}