{
  "type": "Feature",
  "properties": {
    "gn:admin1_code":"8.0",
    "gn:asciiname":"Dongfanghong Linchang",
    "gn:country_code":"CN",
    "gn:dem":407,
    "gn:feature_class":"P",
    "gn:feature_code":"PPLF",
    "gn:name":"Dongfanghong Linchang",
    "gn:population":0,
    "gn:timezone":"Asia/Shanghai",
    "iso:country":"CN",
    "name:zho_x_preferred":[
        "\u4e1c\u65b9\u7ea2\u6797\u573a"
    ],
    "wof:name":"Dongfanghong Linchang",
    "wof:placetype":"locality"
},
  "geometry": {"coordinates":[127.62102,48.10626],"type":"Point"}
}