{
  "type": "Feature",
  "properties": {
    "gn:admin1_code":"24.0",
    "gn:asciiname":"Weipingbu",
    "gn:country_code":"CN",
    "gn:dem":1391,
    "gn:feature_class":"P",
    "gn:feature_code":"PPL",
    "gn:name":"Weipingbu",
    "gn:population":0,
    "gn:timezone":"Asia/Shanghai",
    "iso:country":"CN",
    "name:und_x_variant":[
        "Wei-p\u2019ing-Pao",
        "Weipingbu",
        "\u5a01\u576a\u5821"
    ],
    "wof:name":"Weipingbu",
    "wof:placetype":"locality"
},
  "geometry": {"coordinates":[112.26554,39.87868],"type":"Point"}
}