{
  "type": "Feature",
  "properties": {
    "gn:admin1_code":"13.0",
    "gn:asciiname":"Yakule",
    "gn:country_code":"CN",
    "gn:dem":1169,
    "gn:feature_class":"P",
    "gn:feature_code":"PPL",
    "gn:name":"Yakule",
    "gn:population":0,
    "gn:timezone":"Asia/Shanghai",
    "iso:country":"CN",
    "name:zho_x_preferred":[
        "\u4e9a\u5e93\u52d2"
    ],
    "wof:name":"Yakule",
    "wof:placetype":"locality"
},
  "geometry": {"coordinates":[77.66146999999999,39.08172],"type":"Point"}
}