{
  "type": "Feature",
  "properties": {
    "gn:admin1_code":"15.0",
    "gn:asciiname":"Huaizhuangzi",
    "gn:country_code":"CN",
    "gn:dem":1499,
    "gn:feature_class":"P",
    "gn:feature_code":"PPL",
    "gn:name":"Huaizhuangzi",
    "gn:population":0,
    "gn:timezone":"Asia/Shanghai",
    "iso:country":"CN",
    "name:zho_x_preferred":[
        "\u69d0\u5e84\u5b50"
    ],
    "wof:name":"Huaizhuangzi",
    "wof:placetype":"locality"
},
  "geometry": {"coordinates":[108.53100000000001,35.3209],"type":"Point"}
}