{
  "type": "Feature",
  "properties": {
    "gn:admin1_code":"16.0",
    "gn:asciiname":"Wujing",
    "gn:country_code":"CN",
    "gn:dem":45,
    "gn:feature_class":"P",
    "gn:feature_code":"PPL",
    "gn:name":"Wujing",
    "gn:population":0,
    "gn:timezone":"Asia/Shanghai",
    "iso:country":"CN",
    "name:deu_x_preferred":[
        "Wujing"
    ],
    "name:swe_x_preferred":[
        "Wujing"
    ],
    "name:zho_x_preferred":[
        "\u6b66\u9756"
    ],
    "wof:name":"Wujing",
    "wof:placetype":"locality"
},
  "geometry": {"coordinates":[110.119,23.5593],"type":"Point"}
}