{
  "type": "Feature",
  "properties": {
    "gn:admin1_code":"10.0",
    "gn:asciiname":"Lilingju",
    "gn:country_code":"CN",
    "gn:dem":9,
    "gn:feature_class":"P",
    "gn:feature_code":"PPL",
    "gn:name":"Lilingju",
    "gn:population":0,
    "gn:timezone":"Asia/Shanghai",
    "iso:country":"CN",
    "name:zho_x_preferred":[
        "\u674e\u96f6\u5de8"
    ],
    "wof:name":"Lilingju",
    "wof:placetype":"locality"
},
  "geometry": {"coordinates":[116.508,38.6064],"type":"Point"}
}