{
  "type": "Feature",
  "properties": {
    "gn:admin1_code":"30.0",
    "gn:asciiname":"Qiankeng",
    "gn:country_code":"CN",
    "gn:dem":259,
    "gn:feature_class":"P",
    "gn:feature_code":"PPL",
    "gn:name":"Qiankeng",
    "gn:population":0,
    "gn:timezone":"Asia/Shanghai",
    "iso:country":"CN",
    "name:und_x_variant":[
        "\u831c\u5751"
    ],
    "name:zho_x_preferred":[
        "\u831c\u5751"
    ],
    "wof:name":"Qiankeng",
    "wof:placetype":"locality"
},
  "geometry": {"coordinates":[115.20732,23.65833],"type":"Point"}
}