{
  "type": "Feature",
  "properties": {
    "gn:admin1_code":"30.0",
    "gn:asciiname":"Yangqiaotou",
    "gn:country_code":"CN",
    "gn:dem":116,
    "gn:feature_class":"P",
    "gn:feature_code":"PPL",
    "gn:name":"Yangqiaotou",
    "gn:population":0,
    "gn:timezone":"Asia/Shanghai",
    "iso:country":"CN",
    "name:zho_x_preferred":[
        "\u6768\u6865\u5934"
    ],
    "wof:name":"Yangqiaotou",
    "wof:placetype":"locality"
},
  "geometry": {"coordinates":[113.68429999999999,23.89503],"type":"Point"}
}