{
  "type": "Feature",
  "properties": {
    "gn:admin1_code":"3.0",
    "gn:asciiname":"Dunshangliujia",
    "gn:country_code":"CN",
    "gn:dem":58,
    "gn:feature_class":"P",
    "gn:feature_code":"PPL",
    "gn:name":"Dunshangliujia",
    "gn:population":0,
    "gn:timezone":"Asia/Shanghai",
    "iso:country":"CN",
    "name:und_x_variant":[
        "\u58a9\u4e0a\u5218\u5bb6"
    ],
    "wof:name":"Dunshangliujia",
    "wof:placetype":"locality"
},
  "geometry": {"coordinates":[116.80757,28.55679],"type":"Point"}
}