{
  "type": "Feature",
  "properties": {
    "gn:admin1_code":"14.0",
    "gn:asciiname":"Gubo",
    "gn:country_code":"CN",
    "gn:dem":4044,
    "gn:feature_class":"P",
    "gn:feature_code":"PPL",
    "gn:name":"Gubo",
    "gn:population":0,
    "gn:timezone":"Asia/Urumqi",
    "iso:country":"CN",
    "name:zho_x_preferred":[
        "\u56fa\u6ce2"
    ],
    "wof:name":"Gubo",
    "wof:placetype":"locality"
},
  "geometry": {"coordinates":[92.08553999999999,29.0459],"type":"Point"}
}