{
  "type": "Feature",
  "properties": {
    "gn:admin1_code":"8.0",
    "gn:asciiname":"Aihuacun",
    "gn:country_code":"CN",
    "gn:dem":181,
    "gn:feature_class":"P",
    "gn:feature_code":"PPL",
    "gn:name":"Aihuacun",
    "gn:population":0,
    "gn:timezone":"Asia/Shanghai",
    "iso:country":"CN",
    "name:zho_x_preferred":[
        "\u7231\u534e\u6751"
    ],
    "wof:name":"Aihuacun",
    "wof:placetype":"locality"
},
  "geometry": {"coordinates":[126.60102999999999,47.60703],"type":"Point"}
}