{
  "type": "Feature",
  "properties": {
    "gn:admin1_code":"31",
    "gn:asciiname":"Bishi",
    "gn:country_code":"CN",
    "gn:dem":55,
    "gn:feature_class":"P",
    "gn:feature_code":"PPL",
    "gn:name":"Bishi",
    "gn:population":0,
    "gn:timezone":"Asia/Shanghai",
    "iso:country":"CN",
    "name:ceb_x_preferred":[
        "Bishi"
    ],
    "name:deu_x_preferred":[
        "Bishi"
    ],
    "name:und_x_variant":[
        "\u5fc5\u77f3"
    ],
    "wof:name":"Bishi",
    "wof:placetype":"locality"
},
  "geometry": {"coordinates":[110.247,19.7807],"type":"Point"}
}