{
  "type": "Feature",
  "properties": {
    "gn:admin1_code":"14.0",
    "gn:asciiname":"Baguo",
    "gn:country_code":"CN",
    "gn:dem":4584,
    "gn:feature_class":"P",
    "gn:feature_code":"PPL",
    "gn:name":"Baguo",
    "gn:population":0,
    "gn:timezone":"Asia/Urumqi",
    "iso:country":"CN",
    "name:zho_x_preferred":[
        "\u5df4\u679c"
    ],
    "wof:name":"Baguo",
    "wof:placetype":"locality"
},
  "geometry": {"coordinates":[90.60211,30.16625],"type":"Point"}
}