{
  "type": "Feature",
  "properties": {
    "gn:admin1_code":"1.0",
    "gn:asciiname":"Daxuwan",
    "gn:country_code":"CN",
    "gn:dem":5,
    "gn:feature_class":"P",
    "gn:feature_code":"PPL",
    "gn:name":"Daxuwan",
    "gn:population":0,
    "gn:timezone":"Asia/Shanghai",
    "iso:country":"CN",
    "name:zho_x_preferred":[
        "\u5927\u5729\u6e7e"
    ],
    "wof:name":"Daxuwan",
    "wof:placetype":"locality"
},
  "geometry": {"coordinates":[118.14,31.43402],"type":"Point"}
}