{
  "type": "Feature",
  "properties": {
    "gn:admin1_code":"30.0",
    "gn:asciiname":"Mizailong",
    "gn:country_code":"CN",
    "gn:dem":73,
    "gn:feature_class":"P",
    "gn:feature_code":"PPL",
    "gn:name":"Mizailong",
    "gn:population":0,
    "gn:timezone":"Asia/Shanghai",
    "iso:country":"CN",
    "name:zho_x_preferred":[
        "\u871c\u4ed4\u7b3c"
    ],
    "wof:name":"Mizailong",
    "wof:placetype":"locality"
},
  "geometry": {"coordinates":[113.15477,23.56326],"type":"Point"}
}