{
  "type": "Feature",
  "properties": {
    "gn:admin1_code":"33.0",
    "gn:asciiname":"Lijia",
    "gn:country_code":"CN",
    "gn:dem":306,
    "gn:feature_class":"P",
    "gn:feature_code":"PPL",
    "gn:name":"Lijia",
    "gn:population":0,
    "gn:timezone":"Asia/Shanghai",
    "iso:country":"CN",
    "name:deu_x_preferred":[
        "Lijia"
    ],
    "name:zho_x_preferred":[
        "\u9ece\u5bb6"
    ],
    "wof:name":"Lijia",
    "wof:placetype":"locality"
},
  "geometry": {"coordinates":[106.65364,29.76515],"type":"Point"}
}