{
  "type": "Feature",
  "properties": {
    "gn:admin1_code":"25",
    "gn:asciiname":"Puzhaosi",
    "gn:country_code":"CN",
    "gn:dem":253,
    "gn:feature_class":"P",
    "gn:feature_code":"PPL",
    "gn:name":"Puzhaosi",
    "gn:population":0,
    "gn:timezone":"Asia/Shanghai",
    "iso:country":"CN",
    "name:zho_x_preferred":[
        "\u666e\u7167\u5bfa"
    ],
    "wof:name":"Puzhaosi",
    "wof:placetype":"locality"
},
  "geometry": {"coordinates":[117.107,36.21],"type":"Point"}
}