{
  "type": "Feature",
  "properties": {
    "gn:admin1_code":"16",
    "gn:asciiname":"Yinshandong",
    "gn:country_code":"CN",
    "gn:dem":281,
    "gn:feature_class":"P",
    "gn:feature_code":"PPL",
    "gn:name":"Yinshandong",
    "gn:population":0,
    "gn:timezone":"Asia/Shanghai",
    "iso:country":"CN",
    "name:zho_x_preferred":[
        "\u94f6\u5c71\u6d1e"
    ],
    "wof:name":"Yinshandong",
    "wof:placetype":"locality"
},
  "geometry": {"coordinates":[110.645,25.4997],"type":"Point"}
}