{
  "type": "Feature",
  "properties": {
    "gn:admin1_code":"15.0",
    "gn:asciiname":"Shanggou",
    "gn:country_code":"CN",
    "gn:dem":1254,
    "gn:feature_class":"P",
    "gn:feature_code":"PPL",
    "gn:name":"Shanggou",
    "gn:population":0,
    "gn:timezone":"Asia/Shanghai",
    "iso:country":"CN",
    "name:und_x_variant":[
        "\u5c1a\u6c9f"
    ],
    "name:zho_x_preferred":[
        "\u5c1a\u6c9f"
    ],
    "wof:name":"Shanggou",
    "wof:placetype":"locality"
},
  "geometry": {"coordinates":[104.83978999999999,32.90474],"type":"Point"}
}