{
  "type": "Feature",
  "properties": {
    "gn:admin1_code":"8.0",
    "gn:asciiname":"Duobaoshan Tongkuang",
    "gn:country_code":"CN",
    "gn:dem":418,
    "gn:feature_class":"P",
    "gn:feature_code":"PPLF",
    "gn:name":"Duobaoshan Tongkuang",
    "gn:population":0,
    "gn:timezone":"Asia/Shanghai",
    "iso:country":"CN",
    "name:zho_x_preferred":[
        "\u591a\u5b9d\u5c71\u94dc\u77ff"
    ],
    "wof:name":"Duobaoshan Tongkuang",
    "wof:placetype":"locality"
},
  "geometry": {"coordinates":[125.66013,50.36548],"type":"Point"}
}