{
  "type": "Feature",
  "properties": {
    "gn:admin1_code":"11.0",
    "gn:asciiname":"Datianba",
    "gn:country_code":"CN",
    "gn:dem":893,
    "gn:feature_class":"P",
    "gn:feature_code":"PPL",
    "gn:name":"Datianba",
    "gn:population":0,
    "gn:timezone":"Asia/Shanghai",
    "iso:country":"CN",
    "name:zho_x_preferred":[
        "\u5927\u7530\u575d"
    ],
    "wof:name":"Datianba",
    "wof:placetype":"locality"
},
  "geometry": {"coordinates":[110.62215,26.6103],"type":"Point"}
}