{
  "type": "Feature",
  "properties": {
    "gn:admin1_code":"19.0",
    "gn:asciiname":"Qiandayuhe",
    "gn:country_code":"CN",
    "gn:dem":7,
    "gn:feature_class":"P",
    "gn:feature_code":"PPL",
    "gn:name":"Qiandayuhe",
    "gn:population":0,
    "gn:timezone":"Asia/Shanghai",
    "iso:country":"CN",
    "name:zho_x_preferred":[
        "\u524d\u5927\u9c7c\u6cb3"
    ],
    "wof:name":"Qiandayuhe",
    "wof:placetype":"locality"
},
  "geometry": {"coordinates":[122.639,41.1483],"type":"Point"}
}