{
  "type": "Feature",
  "properties": {
    "gn:admin1_code":"05",
    "gn:asciiname":"Wukeshu",
    "gn:cc2":"CN",
    "gn:country_code":"CN",
    "gn:dem":173,
    "gn:feature_class":"P",
    "gn:feature_code":"PPL",
    "gn:name":"Wukeshu",
    "gn:population":0,
    "gn:timezone":"Asia/Shanghai",
    "iso:country":"CN",
    "name:und_x_variant":[
        "Wu-k\u2019o-shu-ts\u2019un",
        "Wo-k\u2019o-shu",
        "Wukeshu"
    ],
    "wof:name":"Wukeshu",
    "wof:placetype":"locality"
},
  "geometry": {"coordinates":[126.09999999999999,44.78333],"type":"Point"}
}