{
  "type": "Feature",
  "properties": {
    "gn:admin1_code":"9.0",
    "gn:asciiname":"Qianzhangjin",
    "gn:country_code":"CN",
    "gn:dem":72,
    "gn:feature_class":"P",
    "gn:feature_code":"PPL",
    "gn:name":"Qianzhangjin",
    "gn:population":0,
    "gn:timezone":"Asia/Shanghai",
    "iso:country":"CN",
    "name:zho_x_preferred":[
        "\u524d\u5f20\u8fd1"
    ],
    "wof:name":"Qianzhangjin",
    "wof:placetype":"locality"
},
  "geometry": {"coordinates":[114.22503,35.60234000000001],"type":"Point"}
}