{
  "type": "Feature",
  "properties": {
    "gn:admin1_code":"24.0",
    "gn:asciiname":"Houyuanji",
    "gn:country_code":"CN",
    "gn:dem":968,
    "gn:feature_class":"P",
    "gn:feature_code":"PPL",
    "gn:name":"Houyuanji",
    "gn:population":0,
    "gn:timezone":"Asia/Shanghai",
    "iso:country":"CN",
    "name:zho_x_preferred":[
        "\u540e\u5143\u5409"
    ],
    "wof:name":"Houyuanji",
    "wof:placetype":"locality"
},
  "geometry": {"coordinates":[113.48376,38.09563],"type":"Point"}
}