{
  "type": "Feature",
  "properties": {
    "gn:admin1_code":"07",
    "gn:asciiname":"Caolongzai",
    "gn:country_code":"CN",
    "gn:dem":384,
    "gn:feature_class":"P",
    "gn:feature_code":"PPL",
    "gn:name":"Caolongzai",
    "gn:population":0,
    "gn:timezone":"Asia/Shanghai",
    "iso:country":"CN",
    "name:zho_x_preferred":[
        "\u8349\u5784\u4ed4"
    ],
    "wof:name":"Caolongzai",
    "wof:placetype":"locality"
},
  "geometry": {"coordinates":[118.33306,25.34194],"type":"Point"}
}