{
  "type": "Feature",
  "properties": {
    "gn:admin1_code":"16.0",
    "gn:asciiname":"Shankou",
    "gn:country_code":"CN",
    "gn:dem":1010,
    "gn:feature_class":"P",
    "gn:feature_code":"PPL",
    "gn:name":"Shankou",
    "gn:population":0,
    "gn:timezone":"Asia/Shanghai",
    "iso:country":"CN",
    "name:deu_x_preferred":[
        "Shankou"
    ],
    "name:zho_x_preferred":[
        "\u5c71\u53e3"
    ],
    "wof:name":"Shankou",
    "wof:placetype":"locality"
},
  "geometry": {"coordinates":[107.123,25.1086],"type":"Point"}
}