{
  "type": "Feature",
  "properties": {
    "gn:admin1_code":"15.0",
    "gn:asciiname":"Qiaoyang",
    "gn:country_code":"CN",
    "gn:dem":2265,
    "gn:feature_class":"P",
    "gn:feature_code":"PPL",
    "gn:name":"Qiaoyang",
    "gn:population":0,
    "gn:timezone":"Asia/Shanghai",
    "iso:country":"CN",
    "name:zho_x_preferred":[
        "\u4e54\u9633"
    ],
    "wof:name":"Qiaoyang",
    "wof:placetype":"locality"
},
  "geometry": {"coordinates":[104.196,35.0393],"type":"Point"}
}