{
  "type": "Feature",
  "properties": {
    "gn:admin1_code":"26.0",
    "gn:asciiname":"Xingzhaicun",
    "gn:country_code":"CN",
    "gn:dem":1017,
    "gn:feature_class":"P",
    "gn:feature_code":"PPL",
    "gn:name":"Xingzhaicun",
    "gn:population":0,
    "gn:timezone":"Asia/Shanghai",
    "iso:country":"CN",
    "name:zho_x_preferred":[
        "\u5174\u5be8\u6751"
    ],
    "wof:name":"Xingzhaicun",
    "wof:placetype":"locality"
},
  "geometry": {"coordinates":[110.83338000000001,38.84418],"type":"Point"}
}