{
  "type": "Feature",
  "properties": {
    "gn:admin1_code":"26.0",
    "gn:asciiname":"Yuanjiacun",
    "gn:country_code":"CN",
    "gn:dem":411,
    "gn:feature_class":"P",
    "gn:feature_code":"PPL",
    "gn:name":"Yuanjiacun",
    "gn:population":0,
    "gn:timezone":"Asia/Shanghai",
    "iso:country":"CN",
    "name:zho_x_preferred":[
        "\u5143\u9a7e\u6751"
    ],
    "wof:name":"Yuanjiacun",
    "wof:placetype":"locality"
},
  "geometry": {"coordinates":[108.54416000000001,34.15574],"type":"Point"}
}