{
  "type": "Feature",
  "properties": {
    "gn:admin1_code":"18",
    "gn:asciiname":"Shangyuan",
    "gn:country_code":"CN",
    "gn:dem":734,
    "gn:feature_class":"P",
    "gn:feature_code":"PPL",
    "gn:name":"Shangyuan",
    "gn:population":0,
    "gn:timezone":"Asia/Shanghai",
    "iso:country":"CN",
    "name:zho_x_preferred":[
        "\u4e0a\u56ed"
    ],
    "name:zho_x_variant":[
        "\u4e0a\u5143"
    ],
    "wof:name":"Shangyuan",
    "wof:placetype":"locality"
},
  "geometry": {"coordinates":[108.06100000000001,27.2879],"type":"Point"}
}