{
  "type": "Feature",
  "properties": {
    "gn:admin1_code":"10.0",
    "gn:asciiname":"Donglongmen",
    "gn:country_code":"CN",
    "gn:dem":749,
    "gn:feature_class":"P",
    "gn:feature_code":"PPL",
    "gn:name":"Donglongmen",
    "gn:population":0,
    "gn:timezone":"Asia/Shanghai",
    "iso:country":"CN",
    "name:zho_x_preferred":[
        "\u4e1c\u9f99\u95e8"
    ],
    "wof:name":"Donglongmen",
    "wof:placetype":"locality"
},
  "geometry": {"coordinates":[115.09256999999999,39.36374],"type":"Point"}
}