{
  "type": "Feature",
  "properties": {
    "gn:admin1_code":"19.0",
    "gn:asciiname":"Beikou",
    "gn:country_code":"CN",
    "gn:dem":169,
    "gn:feature_class":"P",
    "gn:feature_code":"PPL",
    "gn:name":"Beikou",
    "gn:population":0,
    "gn:timezone":"Asia/Shanghai",
    "iso:country":"CN",
    "name:und_x_variant":[
        "\u5317\u53e3"
    ],
    "name:zho_x_preferred":[
        "\u5317\u53e3"
    ],
    "wof:name":"Beikou",
    "wof:placetype":"locality"
},
  "geometry": {"coordinates":[122.2713,39.80162],"type":"Point"}
}