{
  "type": "Feature",
  "properties": {
    "gn:admin1_code":"29.0",
    "gn:asciiname":"Shiziyuan",
    "gn:country_code":"CN",
    "gn:dem":1487,
    "gn:feature_class":"P",
    "gn:feature_code":"PPL",
    "gn:name":"Shiziyuan",
    "gn:population":0,
    "gn:timezone":"Asia/Shanghai",
    "iso:country":"CN",
    "name:zho_x_preferred":[
        "\u67ff\u5b50\u56ed"
    ],
    "wof:name":"Shiziyuan",
    "wof:placetype":"locality"
},
  "geometry": {"coordinates":[99.1721,24.8113],"type":"Point"}
}