{
  "type": "Feature",
  "properties": {
    "gn:admin1_code":"32.0",
    "gn:asciiname":"Rongxu",
    "gn:country_code":"CN",
    "gn:dem":3378,
    "gn:feature_class":"P",
    "gn:feature_code":"PPL",
    "gn:name":"Rongxu",
    "gn:population":0,
    "gn:timezone":"Asia/Shanghai",
    "iso:country":"CN",
    "name:zho_x_preferred":[
        "\u7ed2\u9700"
    ],
    "wof:name":"Rongxu",
    "wof:placetype":"locality"
},
  "geometry": {"coordinates":[98.87381000000001,31.13826],"type":"Point"}
}