{
  "type": "Feature",
  "properties": {
    "gn:admin1_code":"8.0",
    "gn:asciiname":"Qiandaying",
    "gn:country_code":"CN",
    "gn:dem":153,
    "gn:feature_class":"P",
    "gn:feature_code":"PPL",
    "gn:name":"Qiandaying",
    "gn:population":0,
    "gn:timezone":"Asia/Shanghai",
    "iso:country":"CN",
    "name:zho_x_preferred":[
        "\u524d\u8fbe\u8425"
    ],
    "wof:name":"Qiandaying",
    "wof:placetype":"locality"
},
  "geometry": {"coordinates":[127.47183,46.13008],"type":"Point"}
}