{
  "type": "Feature",
  "properties": {
    "gn:admin1_code":"10",
    "gn:asciiname":"Huangmenzi",
    "gn:country_code":"CN",
    "gn:dem":345,
    "gn:feature_class":"P",
    "gn:feature_code":"PPL",
    "gn:name":"Huangmenzi",
    "gn:population":0,
    "gn:timezone":"Asia/Shanghai",
    "iso:country":"CN",
    "name:zho_x_preferred":[
        "\u9ec4\u95e8\u5b50"
    ],
    "wof:name":"Huangmenzi",
    "wof:placetype":"locality"
},
  "geometry": {"coordinates":[117.81189999999999,40.37796],"type":"Point"}
}