{
  "type": "Feature",
  "properties": {
    "gn:admin1_code":"9.0",
    "gn:asciiname":"Tiechiman",
    "gn:country_code":"CN",
    "gn:dem":995,
    "gn:feature_class":"P",
    "gn:feature_code":"PPL",
    "gn:name":"Tiechiman",
    "gn:population":0,
    "gn:timezone":"Asia/Shanghai",
    "iso:country":"CN",
    "name:zho_x_preferred":[
        "\u94c1\u5c3a\u5881"
    ],
    "wof:name":"Tiechiman",
    "wof:placetype":"locality"
},
  "geometry": {"coordinates":[111.40363000000001,33.51091],"type":"Point"}
}