{
  "type": "Feature",
  "properties": {
    "gn:admin1_code":"5.0",
    "gn:asciiname":"Houlianzhubu",
    "gn:country_code":"CN",
    "gn:dem":176,
    "gn:feature_class":"P",
    "gn:feature_code":"PPL",
    "gn:name":"Houlianzhubu",
    "gn:population":0,
    "gn:timezone":"Asia/Shanghai",
    "iso:country":"CN",
    "name:zho_x_preferred":[
        "\u540e\u8054\u73e0\u5821"
    ],
    "wof:name":"Houlianzhubu",
    "wof:placetype":"locality"
},
  "geometry": {"coordinates":[123.83492,43.91398],"type":"Point"}
}