{
  "type": "Feature",
  "properties": {
    "gn:admin1_code":"3.0",
    "gn:asciiname":"Chengxi",
    "gn:country_code":"CN",
    "gn:dem":67,
    "gn:feature_class":"P",
    "gn:feature_code":"PPL",
    "gn:name":"Chengxi",
    "gn:population":0,
    "gn:timezone":"Asia/Shanghai",
    "iso:country":"CN",
    "name:und_x_variant":[
        "\u57ce\u6eaa"
    ],
    "wof:name":"Chengxi",
    "wof:placetype":"locality"
},
  "geometry": {"coordinates":[115.50775,27.67326],"type":"Point"}
}