{
  "type": "Feature",
  "properties": {
    "gn:admin1_code":"32.0",
    "gn:asciiname":"Miaogao",
    "gn:country_code":"CN",
    "gn:dem":374,
    "gn:feature_class":"P",
    "gn:feature_code":"PPL",
    "gn:name":"Miaogao",
    "gn:population":0,
    "gn:timezone":"Asia/Shanghai",
    "iso:country":"CN",
    "name:zho_x_preferred":[
        "\u5999\u9ad8"
    ],
    "wof:name":"Miaogao",
    "wof:placetype":"locality"
},
  "geometry": {"coordinates":[106.15398999999999,31.56722],"type":"Point"}
}