{
  "type": "Feature",
  "properties": {
    "gn:admin1_code":"30.0",
    "gn:asciiname":"Banling",
    "gn:country_code":"CN",
    "gn:dem":905,
    "gn:feature_class":"P",
    "gn:feature_code":"PPL",
    "gn:name":"Banling",
    "gn:population":0,
    "gn:timezone":"Asia/Shanghai",
    "iso:country":"CN",
    "name:zho_x_preferred":[
        "Banling"
    ],
    "name:zho_x_variant":[
        "\u534a\u5cad"
    ],
    "wof:name":"Banling",
    "wof:placetype":"locality"
},
  "geometry": {"coordinates":[113.25158999999999,24.91682],"type":"Point"}
}