{
  "type": "Feature",
  "properties": {
    "gn:admin1_code":"9.0",
    "gn:asciiname":"Nianfangzhuang",
    "gn:country_code":"CN",
    "gn:dem":201,
    "gn:feature_class":"P",
    "gn:feature_code":"PPL",
    "gn:name":"Nianfangzhuang",
    "gn:population":0,
    "gn:timezone":"Asia/Shanghai",
    "iso:country":"CN",
    "name:und_x_variant":[
        "\u78be\u574a\u5e84",
        "Nianfangzhuang"
    ],
    "wof:name":"Nianfangzhuang",
    "wof:placetype":"locality"
},
  "geometry": {"coordinates":[112.22322,33.04693],"type":"Point"}
}