{
  "type": "Feature",
  "properties": {
    "gn:admin1_code":"10",
    "gn:asciiname":"Qicun",
    "gn:cc2":"CN",
    "gn:country_code":"CN",
    "gn:dem":210,
    "gn:feature_class":"P",
    "gn:feature_code":"PPL",
    "gn:name":"Qicun",
    "gn:population":0,
    "gn:timezone":"Asia/Shanghai",
    "iso:country":"CN",
    "name:und_x_variant":[
        "Ch\u2019i-ts\u2019un",
        "Qicun"
    ],
    "wof:name":"Qicun",
    "wof:placetype":"locality"
},
  "geometry": {"coordinates":[114.29306,36.93528],"type":"Point"}
}