{
  "type": "Feature",
  "properties": {
    "gn:admin1_code":"13.0",
    "gn:asciiname":"Julu'ai",
    "gn:country_code":"CN",
    "gn:dem":2740,
    "gn:feature_class":"P",
    "gn:feature_code":"PPL",
    "gn:name":"Julu\u2019ai",
    "gn:population":0,
    "gn:timezone":"Asia/Urumqi",
    "iso:country":"CN",
    "name:und_x_variant":[
        "Julu\u2019ai"
    ],
    "name:zho_x_preferred":[
        "\u5de8\u9c81\u827e"
    ],
    "wof:name":"Julu'ai",
    "wof:placetype":"locality"
},
  "geometry": {"coordinates":[86.29308,37.79952],"type":"Point"}
}