{
  "type": "Feature",
  "properties": {
    "gn:admin1_code":"15.0",
    "gn:asciiname":"Sidaogou",
    "gn:country_code":"CN",
    "gn:dem":1408,
    "gn:feature_class":"P",
    "gn:feature_code":"PPL",
    "gn:name":"Sidaogou",
    "gn:population":0,
    "gn:timezone":"Asia/Urumqi",
    "iso:country":"CN",
    "name:zho_x_preferred":[
        "\u56db\u9053\u6c9f"
    ],
    "wof:name":"Sidaogou",
    "wof:placetype":"locality"
},
  "geometry": {"coordinates":[96.85420000000001,40.4783],"type":"Point"}
}