{
  "type": "Feature",
  "properties": {
    "gn:admin1_code":"04",
    "gn:asciiname":"Jianghai Nongchang",
    "gn:country_code":"CN",
    "gn:dem":3,
    "gn:feature_class":"P",
    "gn:feature_code":"PPLF",
    "gn:name":"Jianghai Nongchang",
    "gn:population":0,
    "gn:timezone":"Asia/Shanghai",
    "iso:country":"CN",
    "name:und_x_variant":[
        "\u6c5f\u6d77\u519c\u573a"
    ],
    "wof:name":"Jianghai Nongchang",
    "wof:placetype":"locality"
},
  "geometry": {"coordinates":[121.78383999999998,31.70557],"type":"Point"}
}