{
  "type": "Feature",
  "properties": {
    "gn:admin1_code":"29.0",
    "gn:asciiname":"Cangjue",
    "gn:country_code":"CN",
    "gn:dem":1911,
    "gn:feature_class":"P",
    "gn:feature_code":"PPL",
    "gn:name":"Cangjue",
    "gn:population":0,
    "gn:timezone":"Asia/Shanghai",
    "iso:country":"CN",
    "name:zho_x_preferred":[
        "\u4ed3\u89c9"
    ],
    "wof:name":"Cangjue",
    "wof:placetype":"locality"
},
  "geometry": {"coordinates":[99.52030000000001,27.5995],"type":"Point"}
}