{
  "type": "Feature",
  "properties": {
    "gn:admin1_code":"11.0",
    "gn:asciiname":"Tinggongci",
    "gn:country_code":"CN",
    "gn:dem":76,
    "gn:feature_class":"P",
    "gn:feature_code":"PPL",
    "gn:name":"Tinggongci",
    "gn:population":0,
    "gn:timezone":"Asia/Shanghai",
    "iso:country":"CN",
    "name:zho_x_preferred":[
        "\u5ef7\u516c\u7960"
    ],
    "wof:name":"Tinggongci",
    "wof:placetype":"locality"
},
  "geometry": {"coordinates":[113.39185000000001,27.59998],"type":"Point"}
}