{
  "type": "Feature",
  "properties": {
    "gn:admin1_code":"3.0",
    "gn:asciiname":"Maoling",
    "gn:country_code":"CN",
    "gn:dem":241,
    "gn:feature_class":"P",
    "gn:feature_code":"PPL",
    "gn:name":"Maoling",
    "gn:population":0,
    "gn:timezone":"Asia/Shanghai",
    "iso:country":"CN",
    "name:deu_x_preferred":[
        "Maoling-Mausoleum"
    ],
    "name:nor_x_preferred":[
        "Maolingmausoleet"
    ],
    "name:swe_x_preferred":[
        "Maoling"
    ],
    "name:und_x_variant":[
        "\u5e3d\u5cad"
    ],
    "name:zho_x_preferred":[
        "\u6c49\u8302\u9675"
    ],
    "wof:name":"Maoling",
    "wof:placetype":"locality"
},
  "geometry": {"coordinates":[114.88131,27.55971],"type":"Point"}
}