{
  "type": "Feature",
  "properties": {
    "gn:admin1_code":"16.0",
    "gn:asciiname":"Qiming",
    "gn:country_code":"CN",
    "gn:dem":106,
    "gn:feature_class":"P",
    "gn:feature_code":"PPL",
    "gn:name":"Qiming",
    "gn:population":0,
    "gn:timezone":"Asia/Shanghai",
    "iso:country":"CN",
    "name:zho_x_preferred":[
        "\u542f\u660e"
    ],
    "wof:name":"Qiming",
    "wof:placetype":"locality"
},
  "geometry": {"coordinates":[109.22199999999999,23.2087],"type":"Point"}
}