{
  "type": "Feature",
  "properties": {
    "gn:admin1_code":"16.0",
    "gn:asciiname":"Caile",
    "gn:country_code":"CN",
    "gn:dem":753,
    "gn:feature_class":"P",
    "gn:feature_code":"PPL",
    "gn:name":"Caile",
    "gn:population":0,
    "gn:timezone":"Asia/Shanghai",
    "iso:country":"CN",
    "name:zho_x_preferred":[
        "\u624d\u4e50"
    ],
    "wof:name":"Caile",
    "wof:placetype":"locality"
},
  "geometry": {"coordinates":[108.538,25.0066],"type":"Point"}
}