{
  "type": "Feature",
  "properties": {
    "gn:admin1_code":"16.0",
    "gn:asciiname":"Longnei",
    "gn:country_code":"CN",
    "gn:dem":913,
    "gn:feature_class":"P",
    "gn:feature_code":"PPL",
    "gn:name":"Longnei",
    "gn:population":0,
    "gn:timezone":"Asia/Shanghai",
    "iso:country":"CN",
    "name:zho_x_preferred":[
        "\u9686\u5185"
    ],
    "wof:name":"Longnei",
    "wof:placetype":"locality"
},
  "geometry": {"coordinates":[105.355,24.7302],"type":"Point"}
}