{
  "type": "Feature",
  "properties": {
    "gn:admin1_code":"33",
    "gn:asciiname":"Tuxiang",
    "gn:country_code":"CN",
    "gn:dem":842,
    "gn:feature_class":"P",
    "gn:feature_code":"PPLA4",
    "gn:name":"Tuxiang",
    "gn:population":0,
    "gn:timezone":"Asia/Shanghai",
    "iso:country":"CN",
    "name:und_x_variant":[
        "T\u2019u-hsiang",
        "T\u2019u-hsiang-pa",
        "Tuxiang",
        "Tuxiang Zhen",
        "Xiongjiabang"
    ],
    "name:zho_x_preferred":[
        "\u5410\u7965"
    ],
    "name:zho_x_variant":[
        "\u5410\u7965\u9547",
        "\u718a\u5bb6\u585d"
    ],
    "wof:name":"Tuxiang",
    "wof:placetype":"locality"
},
  "geometry": {"coordinates":[109.15555999999999,30.71293],"type":"Point"}
}