{
  "type": "Feature",
  "properties": {
    "gn:admin1_code":"14.0",
    "gn:asciiname":"Siqing",
    "gn:country_code":"CN",
    "gn:dem":4207,
    "gn:feature_class":"P",
    "gn:feature_code":"PPL",
    "gn:name":"Siqing",
    "gn:population":0,
    "gn:timezone":"Asia/Urumqi",
    "iso:country":"CN",
    "name:zho_x_preferred":[
        "\u79c1\u9752"
    ],
    "wof:name":"Siqing",
    "wof:placetype":"locality"
},
  "geometry": {"coordinates":[94.07568000000001,29.47002],"type":"Point"}
}