{
  "type": "Feature",
  "properties": {
    "gn:admin1_code":"32.0",
    "gn:asciiname":"Azidu",
    "gn:country_code":"CN",
    "gn:dem":2364,
    "gn:feature_class":"P",
    "gn:feature_code":"PPL",
    "gn:name":"Azidu",
    "gn:population":0,
    "gn:timezone":"Asia/Shanghai",
    "iso:country":"CN",
    "name:zho_x_preferred":[
        "\u963f\u5b50\u90fd"
    ],
    "wof:name":"Azidu",
    "wof:placetype":"locality"
},
  "geometry": {"coordinates":[103.029,27.795],"type":"Point"}
}