{
  "type": "Feature",
  "properties": {
    "gn:admin1_code":"9.0",
    "gn:asciiname":"Xionglou",
    "gn:country_code":"CN",
    "gn:dem":44,
    "gn:feature_class":"P",
    "gn:feature_code":"PPL",
    "gn:name":"Xionglou",
    "gn:population":0,
    "gn:timezone":"Asia/Shanghai",
    "iso:country":"CN",
    "name:zho_x_preferred":[
        "\u718a\u697c"
    ],
    "wof:name":"Xionglou",
    "wof:placetype":"locality"
},
  "geometry": {"coordinates":[114.96748999999998,32.92065],"type":"Point"}
}