{
  "type": "Feature",
  "properties": {
    "gn:admin1_code":"11.0",
    "gn:asciiname":"Miboku",
    "gn:country_code":"CN",
    "gn:dem":439,
    "gn:feature_class":"P",
    "gn:feature_code":"PPL",
    "gn:name":"Miboku",
    "gn:population":0,
    "gn:timezone":"Asia/Shanghai",
    "iso:country":"CN",
    "name:zho_x_preferred":[
        "\u7c73\u62e8\u67af"
    ],
    "wof:name":"Miboku",
    "wof:placetype":"locality"
},
  "geometry": {"coordinates":[109.7025,29.23024],"type":"Point"}
}