{
  "type": "Feature",
  "properties": {
    "gn:admin1_code":"32.0",
    "gn:asciiname":"Haoba",
    "gn:country_code":"CN",
    "gn:dem":813,
    "gn:feature_class":"P",
    "gn:feature_code":"PPL",
    "gn:name":"Haoba",
    "gn:population":0,
    "gn:timezone":"Asia/Shanghai",
    "iso:country":"CN",
    "name:zho_x_preferred":[
        "\u84bf\u575d"
    ],
    "wof:name":"Haoba",
    "wof:placetype":"locality"
},
  "geometry": {"coordinates":[105.971,32.7702],"type":"Point"}
}