{
  "type": "Feature",
  "properties": {
    "gn:admin1_code":"24",
    "gn:asciiname":"Nanjingzhuang",
    "gn:country_code":"CN",
    "gn:dem":1445,
    "gn:feature_class":"P",
    "gn:feature_code":"PPL",
    "gn:name":"Nanjingzhuang",
    "gn:population":0,
    "gn:timezone":"Asia/Shanghai",
    "iso:country":"CN",
    "name:und_x_variant":[
        "Nan-ching-chuang",
        "Nanjingzhuang",
        "\u5357\u4eac\u5e84"
    ],
    "wof:name":"Nanjingzhuang",
    "wof:placetype":"locality"
},
  "geometry": {"coordinates":[112.70753999999999,39.93446],"type":"Point"}
}