{
  "type": "Feature",
  "properties": {
    "gn:admin1_code":"3",
    "gn:asciiname":"Dongnao",
    "gn:country_code":"CN",
    "gn:dem":559,
    "gn:feature_class":"P",
    "gn:feature_code":"PPL",
    "gn:name":"Dongnao",
    "gn:population":0,
    "gn:timezone":"Asia/Shanghai",
    "iso:country":"CN",
    "name:zho_x_preferred":[
        "\u51bb\u8111"
    ],
    "wof:name":"Dongnao",
    "wof:placetype":"locality"
},
  "geometry": {"coordinates":[114.313,26.0282],"type":"Point"}
}