{
  "type": "Feature",
  "properties": {
    "gn:admin1_code":"4.0",
    "gn:asciiname":"Qianxiang",
    "gn:country_code":"CN",
    "gn:dem":2,
    "gn:feature_class":"P",
    "gn:feature_code":"PPL",
    "gn:name":"Qianxiang",
    "gn:population":0,
    "gn:timezone":"Asia/Shanghai",
    "iso:country":"CN",
    "name:zho_x_preferred":[
        "Qianxiang"
    ],
    "name:zho_x_variant":[
        "\u524d\u5df7"
    ],
    "wof:name":"Qianxiang",
    "wof:placetype":"locality"
},
  "geometry": {"coordinates":[119.75876,33.65516],"type":"Point"}
}