{
  "type": "Feature",
  "properties": {
    "gn:admin1_code":"05",
    "gn:asciiname":"Choushui",
    "gn:country_code":"CN",
    "gn:dem":503,
    "gn:feature_class":"P",
    "gn:feature_code":"PPLA4",
    "gn:name":"Choushui",
    "gn:population":0,
    "gn:timezone":"Asia/Shanghai",
    "iso:country":"CN",
    "name:und_x_variant":[
        "Ch\u2019ou-shui-ho",
        "Choushui",
        "\u62bd\u6c34",
        "Choushui Xiang",
        "\u62bd\u6c34\u4e61"
    ],
    "wof:name":"Choushui",
    "wof:placetype":"locality"
},
  "geometry": {"coordinates":[127.07626999999999,42.39463],"type":"Point"}
}