{
  "type": "Feature",
  "properties": {
    "gn:admin1_code":"15.0",
    "gn:asciiname":"Jiucai",
    "gn:country_code":"CN",
    "gn:dem":2525,
    "gn:feature_class":"P",
    "gn:feature_code":"PPL",
    "gn:name":"Jiucai",
    "gn:population":0,
    "gn:timezone":"Asia/Shanghai",
    "iso:country":"CN",
    "name:und_x_variant":[
        "\u97ed\u83dc",
        "Jiucaicun",
        "\u97ed\u83dc\u6751"
    ],
    "wof:name":"Jiucai",
    "wof:placetype":"locality"
},
  "geometry": {"coordinates":[103.88891,34.63293],"type":"Point"}
}