{
  "type": "Feature",
  "properties": {
    "gn:admin1_code":"24.0",
    "gn:asciiname":"Dafengtou",
    "gn:country_code":"CN",
    "gn:dem":1057,
    "gn:feature_class":"P",
    "gn:feature_code":"PPL",
    "gn:name":"Dafengtou",
    "gn:population":0,
    "gn:timezone":"Asia/Shanghai",
    "iso:country":"CN",
    "name:zho_x_preferred":[
        "\u5927\u5cf0\u5934"
    ],
    "wof:name":"Dafengtou",
    "wof:placetype":"locality"
},
  "geometry": {"coordinates":[113.04468,35.60305],"type":"Point"}
}