{
  "type": "Feature",
  "properties": {
    "gn:admin1_code":"7.0",
    "gn:asciiname":"Zhoujiashan",
    "gn:country_code":"CN",
    "gn:dem":776,
    "gn:feature_class":"P",
    "gn:feature_code":"PPL",
    "gn:name":"Zhoujiashan",
    "gn:population":0,
    "gn:timezone":"Asia/Shanghai",
    "iso:country":"CN",
    "name:zho_x_preferred":[
        "\u5468\u4f73\u5c71"
    ],
    "wof:name":"Zhoujiashan",
    "wof:placetype":"locality"
},
  "geometry": {"coordinates":[118.88273999999998,26.85024],"type":"Point"}
}