{
  "type": "Feature",
  "properties": {
    "gn:admin1_code":"18.0",
    "gn:asciiname":"Lamai",
    "gn:country_code":"CN",
    "gn:dem":804,
    "gn:feature_class":"P",
    "gn:feature_code":"PPL",
    "gn:name":"Lamai",
    "gn:population":0,
    "gn:timezone":"Asia/Shanghai",
    "iso:country":"CN",
    "name:ben_x_preferred":[
        "\u09b2\u09be\u09ae\u09be\u0987"
    ],
    "name:bpy_x_preferred":[
        "\u09b2\u09be\u09ae\u09be\u0987"
    ],
    "name:ceb_x_preferred":[
        "Lamai"
    ],
    "name:ita_x_preferred":[
        "Lamlai"
    ],
    "name:msa_x_preferred":[
        "Lamai"
    ],
    "name:new_x_preferred":[
        "\u0932\u092e\u0908"
    ],
    "name:nld_x_preferred":[
        "Lamai"
    ],
    "name:por_x_preferred":[
        "Lamai"
    ],
    "name:swe_x_preferred":[
        "Lamai"
    ],
    "name:urd_x_preferred":[
        "\u0644\u0627\u0645\u0627\u06cc"
    ],
    "name:vie_x_preferred":[
        "Lamai"
    ],
    "name:zho_x_preferred":[
        "\u62c9\u9ea6"
    ],
    "wof:name":"Lamai",
    "wof:placetype":"locality"
},
  "geometry": {"coordinates":[107.258,25.8971],"type":"Point"}
}