{
  "type": "Feature",
  "properties": {
    "gn:admin1_code":"02",
    "gn:asciiname":"Tanhu",
    "gn:country_code":"CN",
    "gn:dem":15,
    "gn:feature_class":"P",
    "gn:feature_code":"PPL",
    "gn:name":"Tanhu",
    "gn:population":0,
    "gn:timezone":"Asia/Shanghai",
    "iso:country":"CN",
    "name:und_x_variant":[
        "\u6ee9\u6d52"
    ],
    "wof:name":"Tanhu",
    "wof:placetype":"locality"
},
  "geometry": {"coordinates":[121.62649999999999,30.61266],"type":"Point"}
}