{
  "type": "Feature",
  "properties": {
    "gn:admin1_code":"13.0",
    "gn:asciiname":"Layibu Lake",
    "gn:country_code":"CN",
    "gn:dem":1373,
    "gn:feature_class":"P",
    "gn:feature_code":"PPL",
    "gn:name":"Layibu Lake",
    "gn:population":0,
    "gn:timezone":"Asia/Shanghai",
    "iso:country":"CN",
    "name:und_x_variant":[
        "\u62c9\u4f9d\u5e03\u62c9\u514b"
    ],
    "wof:name":"Layibu Lake",
    "wof:placetype":"locality"
},
  "geometry": {"coordinates":[76.16515,38.79686],"type":"Point"}
}