{
  "type": "Feature",
  "properties": {
    "gn:admin1_code":"32.0",
    "gn:asciiname":"Sanqing",
    "gn:country_code":"CN",
    "gn:dem":533,
    "gn:feature_class":"P",
    "gn:feature_code":"PPL",
    "gn:name":"Sanqing",
    "gn:population":0,
    "gn:timezone":"Asia/Shanghai",
    "iso:country":"CN",
    "name:zho_x_preferred":[
        "\u4e09\u6e05"
    ],
    "wof:name":"Sanqing",
    "wof:placetype":"locality"
},
  "geometry": {"coordinates":[105.36499999999999,31.9355],"type":"Point"}
}