{
  "type": "Feature",
  "properties": {
    "gn:admin1_code":"1.0",
    "gn:asciiname":"Songyuancun",
    "gn:country_code":"CN",
    "gn:dem":17,
    "gn:feature_class":"P",
    "gn:feature_code":"PPL",
    "gn:name":"Songyuancun",
    "gn:population":0,
    "gn:timezone":"Asia/Shanghai",
    "iso:country":"CN",
    "name:zho_x_preferred":[
        "\u677e\u56ed\u6751"
    ],
    "wof:name":"Songyuancun",
    "wof:placetype":"locality"
},
  "geometry": {"coordinates":[117.37267,30.7377],"type":"Point"}
}