{
  "type": "Feature",
  "properties": {
    "gn:admin1_code":"9.0",
    "gn:asciiname":"Xihezhai",
    "gn:country_code":"CN",
    "gn:dem":217,
    "gn:feature_class":"P",
    "gn:feature_code":"PPL",
    "gn:name":"Xihezhai",
    "gn:population":0,
    "gn:timezone":"Asia/Shanghai",
    "iso:country":"CN",
    "name:und_x_variant":[
        "\u897f\u4f55\u5be8",
        "Xihezhai"
    ],
    "wof:name":"Xihezhai",
    "wof:placetype":"locality"
},
  "geometry": {"coordinates":[112.89490000000001,33.97746],"type":"Point"}
}