{
  "type": "Feature",
  "properties": {
    "gn:admin1_code":"8.0",
    "gn:asciiname":"Changyuancun",
    "gn:country_code":"CN",
    "gn:dem":199,
    "gn:feature_class":"P",
    "gn:feature_code":"PPL",
    "gn:name":"Changyuancun",
    "gn:population":0,
    "gn:timezone":"Asia/Shanghai",
    "iso:country":"CN",
    "name:zho_x_preferred":[
        "\u957f\u8fdc\u6751"
    ],
    "wof:name":"Changyuancun",
    "wof:placetype":"locality"
},
  "geometry": {"coordinates":[124.52630000000001,47.98556],"type":"Point"}
}