{
  "type": "Feature",
  "properties": {
    "gn:admin1_code":"11.0",
    "gn:asciiname":"Songjiahe",
    "gn:country_code":"CN",
    "gn:dem":36,
    "gn:feature_class":"P",
    "gn:feature_code":"PPL",
    "gn:name":"Songjiahe",
    "gn:population":0,
    "gn:timezone":"Asia/Shanghai",
    "iso:country":"CN",
    "name:zho_x_preferred":[
        "Songjiahe"
    ],
    "name:zho_x_variant":[
        "\u5b8b\u5bb6\u6cb3"
    ],
    "wof:name":"Songjiahe",
    "wof:placetype":"locality"
},
  "geometry": {"coordinates":[111.64481000000001,28.96603],"type":"Point"}
}