{
  "type": "Feature",
  "properties": {
    "gn:admin1_code":"5.0",
    "gn:asciiname":"Taipingchuancun",
    "gn:country_code":"CN",
    "gn:dem":577,
    "gn:feature_class":"P",
    "gn:feature_code":"PPL",
    "gn:name":"Taipingchuancun",
    "gn:population":0,
    "gn:timezone":"Asia/Shanghai",
    "iso:country":"CN",
    "name:zho_x_preferred":[
        "\u592a\u5e73\u5ddd\u6751"
    ],
    "wof:name":"Taipingchuancun",
    "wof:placetype":"locality"
},
  "geometry": {"coordinates":[128.42441000000002,43.23107],"type":"Point"}
}