{
  "type": "Feature",
  "properties": {
    "gn:admin1_code":"2.0",
    "gn:asciiname":"Shangzhoujia",
    "gn:country_code":"CN",
    "gn:dem":216,
    "gn:feature_class":"P",
    "gn:feature_code":"PPL",
    "gn:name":"Shangzhoujia",
    "gn:population":0,
    "gn:timezone":"Asia/Shanghai",
    "iso:country":"CN",
    "name:zho_x_preferred":[
        "\u4e0a\u5468\u5bb6"
    ],
    "wof:name":"Shangzhoujia",
    "wof:placetype":"locality"
},
  "geometry": {"coordinates":[120.55332,29.90174],"type":"Point"}
}