{
  "type": "Feature",
  "properties": {
    "gn:admin1_code":"25",
    "gn:asciiname":"Xisunjiazhuang",
    "gn:country_code":"CN",
    "gn:dem":10,
    "gn:feature_class":"P",
    "gn:feature_code":"PPL",
    "gn:name":"Xisunjiazhuang",
    "gn:population":0,
    "gn:timezone":"Asia/Shanghai",
    "iso:country":"CN",
    "name:zho_x_preferred":[
        "\u897f\u5b59\u5bb6\u5e84"
    ],
    "wof:name":"Xisunjiazhuang",
    "wof:placetype":"locality"
},
  "geometry": {"coordinates":[119.724,36.7221],"type":"Point"}
}