{
  "type": "Feature",
  "properties": {
    "gn:admin1_code":"02",
    "gn:asciiname":"Yongzhongjiedao",
    "gn:country_code":"CN",
    "gn:dem":14,
    "gn:feature_class":"P",
    "gn:feature_code":"PPL",
    "gn:name":"Yongzhongjiedao",
    "gn:population":0,
    "gn:timezone":"Asia/Shanghai",
    "iso:country":"CN",
    "name:und_x_variant":[
        "Siqianjie",
        "Yongzhongzhen",
        "Yongchangzhen",
        "Yongzhongjiedao"
    ],
    "name:zho_x_preferred":[
        "Ssu-ch\u2019ien-chieh"
    ],
    "name:zho_x_variant":[
        "\u6c38\u4e2d\u8857\u9053"
    ],
    "wof:name":"Yongzhongjiedao",
    "wof:placetype":"locality"
},
  "geometry": {"coordinates":[120.82227,27.92434],"type":"Point"}
}