{
  "type": "Feature",
  "properties": {
    "gn:admin1_code":"12.0",
    "gn:asciiname":"Liantonghu Dadui",
    "gn:country_code":"CN",
    "gn:dem":19,
    "gn:feature_class":"P",
    "gn:feature_code":"PPLF",
    "gn:name":"Liantonghu Dadui",
    "gn:population":0,
    "gn:timezone":"Asia/Shanghai",
    "iso:country":"CN",
    "name:und_x_variant":[
        "\u8fde\u901a\u6e56\u5927\u961f"
    ],
    "wof:name":"Liantonghu Dadui",
    "wof:placetype":"locality"
},
  "geometry": {"coordinates":[114.06216999999999,30.69852],"type":"Point"}
}