{
  "type": "Feature",
  "properties": {
    "gn:admin1_code":"10.0",
    "gn:asciiname":"Guanfengdui",
    "gn:country_code":"CN",
    "gn:dem":7,
    "gn:feature_class":"P",
    "gn:feature_code":"PPL",
    "gn:name":"Guanfengdui",
    "gn:population":0,
    "gn:timezone":"Asia/Shanghai",
    "iso:country":"CN",
    "name:zho_x_preferred":[
        "\u89c2\u98ce\u5806"
    ],
    "wof:name":"Guanfengdui",
    "wof:placetype":"locality"
},
  "geometry": {"coordinates":[117.64775,39.59233],"type":"Point"}
}