{
  "type": "Feature",
  "properties": {
    "gn:admin1_code":"25.0",
    "gn:asciiname":"Miaozikuangcun",
    "gn:country_code":"CN",
    "gn:dem":101,
    "gn:feature_class":"P",
    "gn:feature_code":"PPL",
    "gn:name":"Miaozikuangcun",
    "gn:population":0,
    "gn:timezone":"Asia/Shanghai",
    "iso:country":"CN",
    "name:zho_x_preferred":[
        "\u5e99\u5b50\u593c\u6751"
    ],
    "wof:name":"Miaozikuangcun",
    "wof:placetype":"locality"
},
  "geometry": {"coordinates":[120.45461,37.13532],"type":"Point"}
}