{
  "type": "Feature",
  "properties": {
    "gn:admin1_code":"33.0",
    "gn:asciiname":"Sunhe",
    "gn:country_code":"CN",
    "gn:dem":272,
    "gn:feature_class":"P",
    "gn:feature_code":"PPL",
    "gn:name":"Sunhe",
    "gn:population":0,
    "gn:timezone":"Asia/Shanghai",
    "iso:country":"CN",
    "name:zho_x_preferred":[
        "\u5b59\u6cb3"
    ],
    "wof:name":"Sunhe",
    "wof:placetype":"locality"
},
  "geometry": {"coordinates":[106.21720000000001,29.42937],"type":"Point"}
}