{
  "type": "Feature",
  "properties": {
    "gn:admin1_code":"24.0",
    "gn:asciiname":"Wujiagou",
    "gn:country_code":"CN",
    "gn:dem":1591,
    "gn:feature_class":"P",
    "gn:feature_code":"PPL",
    "gn:name":"Wujiagou",
    "gn:population":0,
    "gn:timezone":"Asia/Shanghai",
    "iso:country":"CN",
    "name:und_x_variant":[
        "\u6b66\u5bb6\u6c9f"
    ],
    "wof:name":"Wujiagou",
    "wof:placetype":"locality"
},
  "geometry": {"coordinates":[112.23685,39.71934],"type":"Point"}
}