{
  "type": "Feature",
  "properties": {
    "gn:admin1_code":"11.0",
    "gn:asciiname":"Shuizhuyuan",
    "gn:country_code":"CN",
    "gn:dem":731,
    "gn:feature_class":"P",
    "gn:feature_code":"PPL",
    "gn:name":"Shuizhuyuan",
    "gn:population":0,
    "gn:timezone":"Asia/Shanghai",
    "iso:country":"CN",
    "name:zho_x_preferred":[
        "\u6c34\u7af9\u56ed"
    ],
    "wof:name":"Shuizhuyuan",
    "wof:placetype":"locality"
},
  "geometry": {"coordinates":[110.11098,29.69271],"type":"Point"}
}