{
  "type": "Feature",
  "properties": {
    "gn:admin1_code":"30",
    "gn:asciiname":"Getengwo",
    "gn:country_code":"CN",
    "gn:dem":588,
    "gn:feature_class":"P",
    "gn:feature_code":"PPL",
    "gn:name":"Getengwo",
    "gn:population":0,
    "gn:timezone":"Asia/Shanghai",
    "iso:country":"CN",
    "name:zho_x_preferred":[
        "\u845b\u85e4\u7a9d"
    ],
    "wof:name":"Getengwo",
    "wof:placetype":"locality"
},
  "geometry": {"coordinates":[116.00193,24.71977],"type":"Point"}
}