{
  "type": "Feature",
  "properties": {
    "gn:admin1_code":"32",
    "gn:asciiname":"Heiyantou",
    "gn:country_code":"CN",
    "gn:dem":246,
    "gn:feature_class":"P",
    "gn:feature_code":"PPL",
    "gn:name":"Heiyantou",
    "gn:population":0,
    "gn:timezone":"Asia/Shanghai",
    "iso:country":"CN",
    "name:zho_x_preferred":[
        "\u9ed1\u5ca9\u5934"
    ],
    "wof:name":"Heiyantou",
    "wof:placetype":"locality"
},
  "geometry": {"coordinates":[106.61157,30.3536],"type":"Point"}
}