{
  "type": "Feature",
  "properties": {
    "gn:admin1_code":"16",
    "gn:asciiname":"Meizizhou",
    "gn:country_code":"CN",
    "gn:dem":125,
    "gn:feature_class":"P",
    "gn:feature_code":"PPL",
    "gn:name":"Meizizhou",
    "gn:population":0,
    "gn:timezone":"Asia/Shanghai",
    "iso:country":"CN",
    "name:zho_x_preferred":[
        "\u6885\u5b50\u6d32"
    ],
    "wof:name":"Meizizhou",
    "wof:placetype":"locality"
},
  "geometry": {"coordinates":[110.559,24.6132],"type":"Point"}
}