{
  "type": "Feature",
  "properties": {
    "gn:admin1_code":"19.0",
    "gn:asciiname":"Luanchuangou",
    "gn:country_code":"CN",
    "gn:dem":559,
    "gn:feature_class":"P",
    "gn:feature_code":"PPL",
    "gn:name":"Luanchuangou",
    "gn:population":0,
    "gn:timezone":"Asia/Shanghai",
    "iso:country":"CN",
    "name:und_x_variant":[
        "\u4e71\u693d\u6c9f"
    ],
    "wof:name":"Luanchuangou",
    "wof:placetype":"locality"
},
  "geometry": {"coordinates":[124.68783000000001,41.46018],"type":"Point"}
}