{
  "type": "Feature",
  "properties": {
    "gn:admin1_code":"1.0",
    "gn:asciiname":"Pushuicun",
    "gn:country_code":"CN",
    "gn:dem":9,
    "gn:feature_class":"P",
    "gn:feature_code":"PPL",
    "gn:name":"Pushuicun",
    "gn:population":0,
    "gn:timezone":"Asia/Shanghai",
    "iso:country":"CN",
    "name:zho_x_preferred":[
        "\u6fee\u6c34\u6751"
    ],
    "wof:name":"Pushuicun",
    "wof:placetype":"locality"
},
  "geometry": {"coordinates":[118.24176,31.34274000000001],"type":"Point"}
}