{
  "type": "Feature",
  "properties": {
    "gn:admin1_code":"9.0",
    "gn:asciiname":"Baimakeng",
    "gn:country_code":"CN",
    "gn:dem":755,
    "gn:feature_class":"P",
    "gn:feature_code":"PPL",
    "gn:name":"Baimakeng",
    "gn:population":0,
    "gn:timezone":"Asia/Shanghai",
    "iso:country":"CN",
    "name:und_x_variant":[
        "\u767d\u9a6c\u5751",
        "Baimakeng"
    ],
    "wof:name":"Baimakeng",
    "wof:placetype":"locality"
},
  "geometry": {"coordinates":[112.02084000000001,33.32278],"type":"Point"}
}