{
  "type": "Feature",
  "properties": {
    "gn:admin1_code":"3.0",
    "gn:asciiname":"Yangshanli",
    "gn:country_code":"CN",
    "gn:dem":344,
    "gn:feature_class":"P",
    "gn:feature_code":"PPL",
    "gn:name":"Yangshanli",
    "gn:population":0,
    "gn:timezone":"Asia/Shanghai",
    "iso:country":"CN",
    "name:und_x_variant":[
        "\u6768\u5c71\u91cc"
    ],
    "wof:name":"Yangshanli",
    "wof:placetype":"locality"
},
  "geometry": {"coordinates":[115.48729,29.50354],"type":"Point"}
}