{
  "type": "Feature",
  "properties": {
    "gn:admin1_code":"5.0",
    "gn:asciiname":"Fujiatun",
    "gn:country_code":"CN",
    "gn:dem":249,
    "gn:feature_class":"P",
    "gn:feature_code":"PPL",
    "gn:name":"Fujiatun",
    "gn:population":0,
    "gn:timezone":"Asia/Shanghai",
    "iso:country":"CN",
    "name:zho_x_preferred":[
        "\u5bcc\u5bb6\u5c6f"
    ],
    "wof:name":"Fujiatun",
    "wof:placetype":"locality"
},
  "geometry": {"coordinates":[125.11653,43.36947],"type":"Point"}
}