{
  "type": "Feature",
  "properties": {
    "gn:admin1_code":"3.0",
    "gn:asciiname":"Niuguyuan",
    "gn:country_code":"CN",
    "gn:dem":273,
    "gn:feature_class":"P",
    "gn:feature_code":"PPL",
    "gn:name":"Niuguyuan",
    "gn:population":0,
    "gn:timezone":"Asia/Shanghai",
    "iso:country":"CN",
    "name:und_x_variant":[
        "\u725b\u726f\u8fdc"
    ],
    "wof:name":"Niuguyuan",
    "wof:placetype":"locality"
},
  "geometry": {"coordinates":[115.79506000000001,25.32608],"type":"Point"}
}