{
  "type": "Feature",
  "properties": {
    "gn:admin1_code":"30.0",
    "gn:asciiname":"Jianjiacun",
    "gn:country_code":"CN",
    "gn:dem":167,
    "gn:feature_class":"P",
    "gn:feature_code":"PPL",
    "gn:name":"Jianjiacun",
    "gn:population":0,
    "gn:timezone":"Asia/Shanghai",
    "iso:country":"CN",
    "name:zho_x_preferred":[
        "\u517c\u846d\u6751"
    ],
    "wof:name":"Jianjiacun",
    "wof:placetype":"locality"
},
  "geometry": {"coordinates":[116.54751,24.23752],"type":"Point"}
}