{
  "type": "Feature",
  "properties": {
    "gn:admin1_code":"9.0",
    "gn:asciiname":"Fengweizi",
    "gn:country_code":"CN",
    "gn:dem":45,
    "gn:feature_class":"P",
    "gn:feature_code":"PPL",
    "gn:name":"Fengweizi",
    "gn:population":0,
    "gn:timezone":"Asia/Shanghai",
    "iso:country":"CN",
    "name:zho_x_preferred":[
        "\u51af\u56f4\u5b50"
    ],
    "wof:name":"Fengweizi",
    "wof:placetype":"locality"
},
  "geometry": {"coordinates":[114.81126999999999,32.68915],"type":"Point"}
}