{
  "type": "Feature",
  "properties": {
    "gn:admin1_code":"29.0",
    "gn:asciiname":"Zichala",
    "gn:country_code":"CN",
    "gn:dem":2092,
    "gn:feature_class":"P",
    "gn:feature_code":"PPL",
    "gn:name":"Zichala",
    "gn:population":0,
    "gn:timezone":"Asia/Shanghai",
    "iso:country":"CN",
    "name:zho_x_preferred":[
        "\u5b50\u5dee\u62c9"
    ],
    "wof:name":"Zichala",
    "wof:placetype":"locality"
},
  "geometry": {"coordinates":[101.06100000000001,26.8048],"type":"Point"}
}