{
  "type": "Feature",
  "properties": {
    "gn:admin1_code":"25.0",
    "gn:asciiname":"Dajincunxicun",
    "gn:country_code":"CN",
    "gn:dem":43,
    "gn:feature_class":"P",
    "gn:feature_code":"PPL",
    "gn:name":"Dajincunxicun",
    "gn:population":0,
    "gn:timezone":"Asia/Shanghai",
    "iso:country":"CN",
    "name:zho_x_preferred":[
        "\u5927\u8fd1\u6751\u897f\u6751"
    ],
    "wof:name":"Dajincunxicun",
    "wof:placetype":"locality"
},
  "geometry": {"coordinates":[115.50309,36.54736],"type":"Point"}
}