{
  "type": "Feature",
  "properties": {
    "gn:admin1_code":"18",
    "gn:asciiname":"Xiaokeli",
    "gn:country_code":"CN",
    "gn:dem":1306,
    "gn:feature_class":"P",
    "gn:feature_code":"PPL",
    "gn:name":"Xiaokeli",
    "gn:population":0,
    "gn:timezone":"Asia/Shanghai",
    "iso:country":"CN",
    "name:zho_x_preferred":[
        "\u5c0f\u514b\u91cc"
    ],
    "wof:name":"Xiaokeli",
    "wof:placetype":"locality"
},
  "geometry": {"coordinates":[106.837,26.2179],"type":"Point"}
}