{
  "type": "Feature",
  "properties": {
    "gn:admin1_code":"26.0",
    "gn:asciiname":"Anzitoucun",
    "gn:country_code":"CN",
    "gn:dem":1127,
    "gn:feature_class":"P",
    "gn:feature_code":"PPL",
    "gn:name":"Anzitoucun",
    "gn:population":0,
    "gn:timezone":"Asia/Shanghai",
    "iso:country":"CN",
    "name:zho_x_preferred":[
        "\u5b89\u5b50\u5934\u6751"
    ],
    "wof:name":"Anzitoucun",
    "wof:placetype":"locality"
},
  "geometry": {"coordinates":[109.29753999999998,35.84058],"type":"Point"}
}