{
  "type": "Feature",
  "properties": {
    "gn:admin1_code":"33.0",
    "gn:asciiname":"Haitang",
    "gn:country_code":"CN",
    "gn:dem":396,
    "gn:feature_class":"P",
    "gn:feature_code":"PPLA4",
    "gn:name":"Haitang",
    "gn:population":0,
    "gn:timezone":"Asia/Shanghai",
    "iso:country":"CN",
    "name:und_x_variant":[
        "Haitang Zhen"
    ],
    "name:zho_x_preferred":[
        "\u6d77\u68e0"
    ],
    "name:zho_x_variant":[
        "\u6d77\u68e0\u9547"
    ],
    "wof:name":"Haitang",
    "wof:placetype":"locality"
},
  "geometry": {"coordinates":[107.22991,30.17173],"type":"Point"}
}