{
  "type": "Feature",
  "properties": {
    "gn:admin1_code":"15.0",
    "gn:asciiname":"Xingwang",
    "gn:country_code":"CN",
    "gn:dem":2155,
    "gn:feature_class":"P",
    "gn:feature_code":"PPL",
    "gn:name":"Xingwang",
    "gn:population":0,
    "gn:timezone":"Asia/Shanghai",
    "iso:country":"CN",
    "name:und_x_variant":[
        "\u5174\u65fa"
    ],
    "wof:name":"Xingwang",
    "wof:placetype":"locality"
},
  "geometry": {"coordinates":[105.00306999999999,35.2465],"type":"Point"}
}