{
  "type": "Feature",
  "properties": {
    "gn:admin1_code":"10",
    "gn:asciiname":"Xishuiyuli",
    "gn:country_code":"CN",
    "gn:dem":295,
    "gn:feature_class":"P",
    "gn:feature_code":"PPL",
    "gn:name":"Xishuiyuli",
    "gn:population":0,
    "gn:timezone":"Asia/Shanghai",
    "iso:country":"CN",
    "name:zho_x_preferred":[
        "\u897f\u6c34\u5cea\u91cc"
    ],
    "wof:name":"Xishuiyuli",
    "wof:placetype":"locality"
},
  "geometry": {"coordinates":[118.3223,40.32712],"type":"Point"}
}