{
  "type": "Feature",
  "properties": {
    "gn:admin1_code":"16.0",
    "gn:asciiname":"Rongchang",
    "gn:country_code":"CN",
    "gn:dem":834,
    "gn:feature_class":"P",
    "gn:feature_code":"PPL",
    "gn:name":"Rongchang",
    "gn:population":0,
    "gn:timezone":"Asia/Shanghai",
    "iso:country":"CN",
    "name:zho_x_preferred":[
        "\u8363\u573a"
    ],
    "wof:name":"Rongchang",
    "wof:placetype":"locality"
},
  "geometry": {"coordinates":[107.36199999999999,25.3891],"type":"Point"}
}