{
  "type": "Feature",
  "properties": {
    "gn:admin1_code":"29.0",
    "gn:asciiname":"Gezuo",
    "gn:country_code":"CN",
    "gn:dem":3113,
    "gn:feature_class":"P",
    "gn:feature_code":"PPL",
    "gn:name":"Gezuo",
    "gn:population":0,
    "gn:timezone":"Asia/Shanghai",
    "iso:country":"CN",
    "name:zho_x_preferred":[
        "\u5404\u5de6"
    ],
    "wof:name":"Gezuo",
    "wof:placetype":"locality"
},
  "geometry": {"coordinates":[100.584,27.7897],"type":"Point"}
}