{
  "type": "Feature",
  "properties": {
    "gn:admin1_code":"32.0",
    "gn:asciiname":"Pengzigou",
    "gn:country_code":"CN",
    "gn:dem":445,
    "gn:feature_class":"P",
    "gn:feature_code":"PPL",
    "gn:name":"Pengzigou",
    "gn:population":0,
    "gn:timezone":"Asia/Shanghai",
    "iso:country":"CN",
    "name:zho_x_preferred":[
        "\u68da\u5b50\u6c9f"
    ],
    "wof:name":"Pengzigou",
    "wof:placetype":"locality"
},
  "geometry": {"coordinates":[104.41200000000001,30.2273],"type":"Point"}
}