{
  "type": "Feature",
  "properties": {
    "gn:admin1_code":"33.0",
    "gn:asciiname":"Chagouzi",
    "gn:country_code":"CN",
    "gn:dem":1677,
    "gn:feature_class":"P",
    "gn:feature_code":"PPL",
    "gn:name":"Chagouzi",
    "gn:population":0,
    "gn:timezone":"Asia/Shanghai",
    "iso:country":"CN",
    "name:zho_x_preferred":[
        "\u5c94\u6c9f\u5b50"
    ],
    "wof:name":"Chagouzi",
    "wof:placetype":"locality"
},
  "geometry": {"coordinates":[109.24427,31.78868],"type":"Point"}
}