{
  "type": "Feature",
  "properties": {
    "gn:admin1_code":"29",
    "gn:asciiname":"Caozidi",
    "gn:country_code":"CN",
    "gn:dem":1731,
    "gn:feature_class":"P",
    "gn:feature_code":"PPL",
    "gn:name":"Caozidi",
    "gn:population":0,
    "gn:timezone":"Asia/Shanghai",
    "iso:country":"CN",
    "name:zho_x_preferred":[
        "\u8349\u5b50\u5730"
    ],
    "wof:name":"Caozidi",
    "wof:placetype":"locality"
},
  "geometry": {"coordinates":[101.033,24.6822],"type":"Point"}
}