{
  "type": "Feature",
  "properties": {
    "gn:admin1_code":"29.0",
    "gn:asciiname":"Hongmaoshu",
    "gn:country_code":"CN",
    "gn:dem":1075,
    "gn:feature_class":"P",
    "gn:feature_code":"PPL",
    "gn:name":"Hongmaoshu",
    "gn:population":0,
    "gn:timezone":"Asia/Shanghai",
    "iso:country":"CN",
    "name:zho_x_preferred":[
        "\u7ea2\u6bdb\u6811"
    ],
    "wof:name":"Hongmaoshu",
    "wof:placetype":"locality"
},
  "geometry": {"coordinates":[101.245,24.0441],"type":"Point"}
}