{
  "type": "Feature",
  "properties": {
    "gn:admin1_code":"21.0",
    "gn:asciiname":"Liujiawannao",
    "gn:country_code":"CN",
    "gn:dem":1735,
    "gn:feature_class":"P",
    "gn:feature_code":"PPL",
    "gn:name":"Liujiawannao",
    "gn:population":0,
    "gn:timezone":"Asia/Shanghai",
    "iso:country":"CN",
    "name:zho_x_preferred":[
        "\u5218\u5bb6\u6e7e\u8111"
    ],
    "wof:name":"Liujiawannao",
    "wof:placetype":"locality"
},
  "geometry": {"coordinates":[106.39527,36.12204000000001],"type":"Point"}
}