{
  "type": "Feature",
  "properties": {
    "gn:admin1_code":"9.0",
    "gn:asciiname":"Laoxiezhuang",
    "gn:country_code":"CN",
    "gn:dem":90,
    "gn:feature_class":"P",
    "gn:feature_code":"PPL",
    "gn:name":"Laoxiezhuang",
    "gn:population":0,
    "gn:timezone":"Asia/Shanghai",
    "iso:country":"CN",
    "name:zho_x_preferred":[
        "\u8001\u8c22\u5e84"
    ],
    "wof:name":"Laoxiezhuang",
    "wof:placetype":"locality"
},
  "geometry": {"coordinates":[114.23479,33.25037],"type":"Point"}
}