{
  "type": "Feature",
  "properties": {
    "gn:admin1_code":"7.0",
    "gn:asciiname":"Fuxi",
    "gn:country_code":"CN",
    "gn:dem":449,
    "gn:feature_class":"P",
    "gn:feature_code":"PPL",
    "gn:name":"Fuxi",
    "gn:population":0,
    "gn:timezone":"Asia/Shanghai",
    "iso:country":"CN",
    "name:zho_x_preferred":[
        "\u6577\u9521"
    ],
    "wof:name":"Fuxi",
    "wof:placetype":"locality"
},
  "geometry": {"coordinates":[118.55455000000001,26.90288],"type":"Point"}
}