{
  "type": "Feature",
  "properties": {
    "gn:admin1_code":"30.0",
    "gn:asciiname":"Guantoudong",
    "gn:country_code":"CN",
    "gn:dem":495,
    "gn:feature_class":"P",
    "gn:feature_code":"PPL",
    "gn:name":"Guantoudong",
    "gn:population":0,
    "gn:timezone":"Asia/Shanghai",
    "iso:country":"CN",
    "name:zho_x_preferred":[
        "Guantoudong"
    ],
    "name:zho_x_variant":[
        "\u89c2\u5934\u6d1e"
    ],
    "wof:name":"Guantoudong",
    "wof:placetype":"locality"
},
  "geometry": {"coordinates":[112.59721999999999,25.10083],"type":"Point"}
}