{
  "type": "Feature",
  "properties": {
    "gn:admin1_code":"25.0",
    "gn:asciiname":"Xizhulu",
    "gn:country_code":"CN",
    "gn:dem":49,
    "gn:feature_class":"P",
    "gn:feature_code":"PPL",
    "gn:name":"Xizhulu",
    "gn:population":0,
    "gn:timezone":"Asia/Shanghai",
    "iso:country":"CN",
    "name:zho_x_preferred":[
        "\u897f\u8bf8\u9e93"
    ],
    "wof:name":"Xizhulu",
    "wof:placetype":"locality"
},
  "geometry": {"coordinates":[120.81322,36.87855],"type":"Point"}
}