{
  "type": "Feature",
  "properties": {
    "gn:admin1_code":"19.0",
    "gn:asciiname":"Houdaqian",
    "gn:country_code":"CN",
    "gn:dem":9,
    "gn:feature_class":"P",
    "gn:feature_code":"PPL",
    "gn:name":"Houdaqian",
    "gn:population":0,
    "gn:timezone":"Asia/Shanghai",
    "iso:country":"CN",
    "name:zho_x_preferred":[
        "\u540e\u5927\u6b20"
    ],
    "name:zho_x_variant":[
        "\u540e\u5927\u5811"
    ],
    "wof:name":"Houdaqian",
    "wof:placetype":"locality"
},
  "geometry": {"coordinates":[122.562,41.2418],"type":"Point"}
}