{
  "type": "Feature",
  "properties": {
    "gn:admin1_code":"25.0",
    "gn:asciiname":"Tunling",
    "gn:cc2":"CN",
    "gn:country_code":"CN",
    "gn:dem":28,
    "gn:feature_class":"P",
    "gn:feature_code":"PPL",
    "gn:name":"Tunling",
    "gn:population":0,
    "gn:timezone":"Asia/Shanghai",
    "iso:country":"CN",
    "name:zho_x_preferred":[
        "\u5c6f\u5cad"
    ],
    "wof:name":"Tunling",
    "wof:placetype":"locality"
},
  "geometry": {"coordinates":[119.51052,35.50275],"type":"Point"}
}