{
  "type": "Feature",
  "properties": {
    "gn:admin1_code":"14.0",
    "gn:asciiname":"Yaimai",
    "gn:country_code":"CN",
    "gn:dem":4604,
    "gn:feature_class":"P",
    "gn:feature_code":"PPL",
    "gn:name":"Yaimai",
    "gn:population":0,
    "gn:timezone":"Asia/Urumqi",
    "iso:country":"CN",
    "name:bod_x_preferred":[
        "Yaimai"
    ],
    "name:zho_x_preferred":[
        "Yimai"
    ],
    "name:zho_x_variant":[
        "\u4f0a\u9ea6"
    ],
    "wof:name":"Yaimai",
    "wof:placetype":"locality"
},
  "geometry": {"coordinates":[96.602,31.402],"type":"Point"}
}