{
  "type": "Feature",
  "properties": {
    "gn:admin1_code":"4.0",
    "gn:asciiname":"Huji",
    "gn:country_code":"CN",
    "gn:dem":6,
    "gn:feature_class":"P",
    "gn:feature_code":"PPL",
    "gn:name":"Huji",
    "gn:population":0,
    "gn:timezone":"Asia/Shanghai",
    "iso:country":"CN",
    "name:ceb_x_preferred":[
        "Huji"
    ],
    "name:swe_x_preferred":[
        "Huji"
    ],
    "wof:name":"Huji",
    "wof:placetype":"locality"
},
  "geometry": {"coordinates":[120.38056,32.53611],"type":"Point"}
}