{
  "type": "Feature",
  "properties": {
    "gn:admin1_code":"25",
    "gn:asciiname":"Dengyoufang",
    "gn:country_code":"CN",
    "gn:dem":51,
    "gn:feature_class":"P",
    "gn:feature_code":"PPL",
    "gn:name":"Dengyoufang",
    "gn:population":0,
    "gn:timezone":"Asia/Shanghai",
    "iso:country":"CN",
    "name:zho_x_preferred":[
        "\u9093\u6cb9\u574a"
    ],
    "wof:name":"Dengyoufang",
    "wof:placetype":"locality"
},
  "geometry": {"coordinates":[115.60581999999999,35.08095],"type":"Point"}
}