{
  "type": "Feature",
  "properties": {
    "gn:admin1_code":"14.0",
    "gn:asciiname":"Tama Muchang",
    "gn:country_code":"CN",
    "gn:dem":3400,
    "gn:feature_class":"P",
    "gn:feature_code":"PPLF",
    "gn:name":"Tama Muchang",
    "gn:population":0,
    "gn:timezone":"Asia/Urumqi",
    "iso:country":"CN",
    "name:zho_x_preferred":[
        "\u5854\u9a6c\u7267\u573a"
    ],
    "wof:name":"Tama Muchang",
    "wof:placetype":"locality"
},
  "geometry": {"coordinates":[94.39924000000001,29.21356],"type":"Point"}
}