{
  "type": "Feature",
  "properties": {
    "gn:admin1_code":"12.0",
    "gn:asciiname":"Fengxiangmen",
    "gn:country_code":"CN",
    "gn:dem":25,
    "gn:feature_class":"P",
    "gn:feature_code":"PPL",
    "gn:name":"Fengxiangmen",
    "gn:population":0,
    "gn:timezone":"Asia/Shanghai",
    "iso:country":"CN",
    "name:zho_x_preferred":[
        "Fengxiangmen"
    ],
    "name:zho_x_variant":[
        "\u51af\u76f8\u95e8"
    ],
    "wof:name":"Fengxiangmen",
    "wof:placetype":"locality"
},
  "geometry": {"coordinates":[115.2704,29.91872],"type":"Point"}
}