{
  "type": "Feature",
  "properties": {
    "gn:admin1_code":"14.0",
    "gn:asciiname":"Chongdacun",
    "gn:country_code":"CN",
    "gn:dem":3941,
    "gn:feature_class":"P",
    "gn:feature_code":"PPL",
    "gn:name":"Chongdacun",
    "gn:population":0,
    "gn:timezone":"Asia/Urumqi",
    "iso:country":"CN",
    "name:zho_x_preferred":[
        "\u51b2\u8fbe\u6751"
    ],
    "wof:name":"Chongdacun",
    "wof:placetype":"locality"
},
  "geometry": {"coordinates":[92.06032,29.24946],"type":"Point"}
}