{
  "type": "Feature",
  "properties": {
    "gn:admin1_code":"25.0",
    "gn:asciiname":"Xiaxujia",
    "gn:country_code":"CN",
    "gn:dem":164,
    "gn:feature_class":"P",
    "gn:feature_code":"PPL",
    "gn:name":"Xiaxujia",
    "gn:population":0,
    "gn:timezone":"Asia/Shanghai",
    "iso:country":"CN",
    "name:zho_x_preferred":[
        "\u4e0b\u5f90\u5bb6"
    ],
    "wof:name":"Xiaxujia",
    "wof:placetype":"locality"
},
  "geometry": {"coordinates":[120.08883,37.03288],"type":"Point"}
}