{
  "type": "Feature",
  "properties": {
    "gn:admin1_code":"4.0",
    "gn:asciiname":"Jiejia",
    "gn:country_code":"CN",
    "gn:dem":26,
    "gn:feature_class":"P",
    "gn:feature_code":"PPL",
    "gn:name":"Jiejia",
    "gn:population":0,
    "gn:timezone":"Asia/Shanghai",
    "iso:country":"CN",
    "name:zho_x_preferred":[
        "\u89e3\u5bb6"
    ],
    "wof:name":"Jiejia",
    "wof:placetype":"locality"
},
  "geometry": {"coordinates":[119.60269,32.06015],"type":"Point"}
}