{
  "type": "Feature",
  "properties": {
    "gn:admin1_code":"11.0",
    "gn:asciiname":"Xiling",
    "gn:cc2":"CN",
    "gn:country_code":"CN",
    "gn:dem":90,
    "gn:feature_class":"P",
    "gn:feature_code":"PPL",
    "gn:name":"Xiling",
    "gn:population":0,
    "gn:timezone":"Asia/Shanghai",
    "iso:country":"CN",
    "name:und_x_variant":[
        "Hsi-ling-hs\u00fc",
        "Xilingxu",
        "Xiling"
    ],
    "wof:name":"Xiling",
    "wof:placetype":"locality"
},
  "geometry": {"coordinates":[112.58417,26.27528],"type":"Point"}
}