{
  "type": "Feature",
  "properties": {
    "gn:admin1_code":"2.0",
    "gn:asciiname":"Juxia",
    "gn:country_code":"CN",
    "gn:dem":977,
    "gn:feature_class":"P",
    "gn:feature_code":"PPL",
    "gn:name":"Juxia",
    "gn:population":0,
    "gn:timezone":"Asia/Shanghai",
    "iso:country":"CN",
    "name:deu_x_preferred":[
        "Juxia"
    ],
    "name:fra_x_preferred":[
        "Juxia"
    ],
    "name:ita_x_preferred":[
        "Juxia"
    ],
    "name:por_x_preferred":[
        "Juxia"
    ],
    "name:spa_x_preferred":[
        "Juxia"
    ],
    "name:vie_x_preferred":[
        "Juxia"
    ],
    "name:zho_x_preferred":[
        "\u5c40\u4e0b"
    ],
    "wof:name":"Juxia",
    "wof:placetype":"locality"
},
  "geometry": {"coordinates":[118.8553,28.07592],"type":"Point"}
}