{
  "type": "Feature",
  "properties": {
    "gn:admin1_code":"26.0",
    "gn:asciiname":"Dai'ancun",
    "gn:country_code":"CN",
    "gn:dem":1274,
    "gn:feature_class":"P",
    "gn:feature_code":"PPL",
    "gn:name":"Dai\u2019ancun",
    "gn:population":0,
    "gn:timezone":"Asia/Shanghai",
    "iso:country":"CN",
    "name:und_x_variant":[
        "Dai\u2019ancun"
    ],
    "name:zho_x_preferred":[
        "\u4ee3\u5b89\u6751"
    ],
    "wof:name":"Dai'ancun",
    "wof:placetype":"locality"
},
  "geometry": {"coordinates":[109.33215,31.84975],"type":"Point"}
}