{
  "type": "Feature",
  "properties": {
    "gn:admin1_code":"21.0",
    "gn:asciiname":"Xiaheiling",
    "gn:country_code":"CN",
    "gn:dem":1636,
    "gn:feature_class":"P",
    "gn:feature_code":"PPL",
    "gn:name":"Xiaheiling",
    "gn:population":0,
    "gn:timezone":"Asia/Shanghai",
    "iso:country":"CN",
    "name:und_x_variant":[
        "\u4e0b\u9ed1\u5cad"
    ],
    "name:zho_x_preferred":[
        "\u4e0b\u9ed1\u5cad"
    ],
    "wof:name":"Xiaheiling",
    "wof:placetype":"locality"
},
  "geometry": {"coordinates":[106.05517999999999,36.61077],"type":"Point"}
}