{
  "type": "Feature",
  "properties": {
    "gn:admin1_code":"10.0",
    "gn:asciiname":"Danggezhuang",
    "gn:country_code":"CN",
    "gn:dem":27,
    "gn:feature_class":"P",
    "gn:feature_code":"PPL",
    "gn:name":"Danggezhuang",
    "gn:population":0,
    "gn:timezone":"Asia/Shanghai",
    "iso:country":"CN",
    "name:zho_x_preferred":[
        "\u515a\u5404\u5e84"
    ],
    "wof:name":"Danggezhuang",
    "wof:placetype":"locality"
},
  "geometry": {"coordinates":[118.9157,39.6701],"type":"Point"}
}