{
  "type": "Feature",
  "properties": {
    "gn:admin1_code":"32.0",
    "gn:asciiname":"Baihe",
    "gn:country_code":"CN",
    "gn:dem":315,
    "gn:feature_class":"P",
    "gn:feature_code":"PPL",
    "gn:name":"Baihe",
    "gn:population":0,
    "gn:timezone":"Asia/Shanghai",
    "iso:country":"CN",
    "name:deu_x_preferred":[
        "Baihe"
    ],
    "name:nor_x_preferred":[
        "Baihe"
    ],
    "name:zho_x_preferred":[
        "\u767e\u548c"
    ],
    "wof:name":"Baihe",
    "wof:placetype":"locality"
},
  "geometry": {"coordinates":[105.71432,29.042],"type":"Point"}
}