{
  "type": "Feature",
  "properties": {
    "gn:admin1_code":"29.0",
    "gn:asciiname":"Jindan Shangcun",
    "gn:country_code":"CN",
    "gn:dem":2069,
    "gn:feature_class":"P",
    "gn:feature_code":"PPL",
    "gn:name":"Jindan Shangcun",
    "gn:population":0,
    "gn:timezone":"Asia/Shanghai",
    "iso:country":"CN",
    "name:zho_x_preferred":[
        "\u91d1\u65e6\u4e0a\u6751"
    ],
    "wof:name":"Jindan Shangcun",
    "wof:placetype":"locality"
},
  "geometry": {"coordinates":[100.785,25.7629],"type":"Point"}
}