{
  "type": "Feature",
  "properties": {
    "gn:admin1_code":"5.0",
    "gn:asciiname":"Xiyangyishan",
    "gn:country_code":"CN",
    "gn:dem":192,
    "gn:feature_class":"P",
    "gn:feature_code":"PPL",
    "gn:name":"Xiyangyishan",
    "gn:population":0,
    "gn:timezone":"Asia/Shanghai",
    "iso:country":"CN",
    "name:zho_x_preferred":[
        "\u897f\u7f8a\u4f9d\u5c71"
    ],
    "wof:name":"Xiyangyishan",
    "wof:placetype":"locality"
},
  "geometry": {"coordinates":[124.07544,44.12771],"type":"Point"}
}