{
  "type": "Feature",
  "properties": {
    "gn:admin1_code":"15.0",
    "gn:asciiname":"Guojiatan",
    "gn:country_code":"CN",
    "gn:dem":1503,
    "gn:feature_class":"P",
    "gn:feature_code":"PPL",
    "gn:name":"Guojiatan",
    "gn:population":0,
    "gn:timezone":"Asia/Shanghai",
    "iso:country":"CN",
    "name:und_x_variant":[
        "\u90ed\u5bb6\u6ee9"
    ],
    "wof:name":"Guojiatan",
    "wof:placetype":"locality"
},
  "geometry": {"coordinates":[107.01388,36.75648],"type":"Point"}
}