{
  "type": "Feature",
  "properties": {
    "gn:admin1_code":"11.0",
    "gn:asciiname":"Hubeitang",
    "gn:country_code":"CN",
    "gn:dem":300,
    "gn:feature_class":"P",
    "gn:feature_code":"PPL",
    "gn:name":"Hubeitang",
    "gn:population":0,
    "gn:timezone":"Asia/Shanghai",
    "iso:country":"CN",
    "name:zho_x_preferred":[
        "\u6e56\u5317\u5858"
    ],
    "wof:name":"Hubeitang",
    "wof:placetype":"locality"
},
  "geometry": {"coordinates":[110.65873000000001,27.11392],"type":"Point"}
}