{
  "type": "Feature",
  "properties": {
    "gn:admin1_code":"16.0",
    "gn:asciiname":"Zhilong Kuangqu",
    "gn:country_code":"CN",
    "gn:dem":109,
    "gn:feature_class":"P",
    "gn:feature_code":"PPL",
    "gn:name":"Zhilong Kuangqu",
    "gn:population":0,
    "gn:timezone":"Asia/Shanghai",
    "iso:country":"CN",
    "name:zho_x_preferred":[
        "\u5fd7\u9686\u77ff\u533a"
    ],
    "wof:name":"Zhilong Kuangqu",
    "wof:placetype":"locality"
},
  "geometry": {"coordinates":[110.95999999999999,23.8933],"type":"Point"}
}