{
  "type": "Feature",
  "properties": {
    "gn:admin1_code":"18",
    "gn:asciiname":"Luoshejia",
    "gn:country_code":"CN",
    "gn:dem":2079,
    "gn:feature_class":"P",
    "gn:feature_code":"PPL",
    "gn:name":"Luoshejia",
    "gn:population":0,
    "gn:timezone":"Asia/Shanghai",
    "iso:country":"CN",
    "name:zho_x_preferred":[
        "\u502e\u820d\u621b"
    ],
    "wof:name":"Luoshejia",
    "wof:placetype":"locality"
},
  "geometry": {"coordinates":[104.896,26.2779],"type":"Point"}
}