{
  "type": "Feature",
  "properties": {
    "gn:admin1_code":"3.0",
    "gn:asciiname":"Maolin",
    "gn:country_code":"CN",
    "gn:dem":49,
    "gn:feature_class":"P",
    "gn:feature_code":"PPL",
    "gn:name":"Maolin",
    "gn:population":0,
    "gn:timezone":"Asia/Shanghai",
    "iso:country":"CN",
    "name:und_x_variant":[
        "\u8302\u6797"
    ],
    "wof:name":"Maolin",
    "wof:placetype":"locality"
},
  "geometry": {"coordinates":[115.38554999999999,28.11584],"type":"Point"}
}