{
  "type": "Feature",
  "properties": {
    "gn:admin1_code":"26.0",
    "gn:asciiname":"Chenggu Xian",
    "gn:country_code":"CN",
    "gn:dem":485,
    "gn:feature_class":"P",
    "gn:feature_code":"PPL",
    "gn:name":"Chenggu Xian",
    "gn:population":0,
    "gn:timezone":"Asia/Shanghai",
    "iso:country":"CN",
    "name:und_x_variant":[
        "\u57ce\u56fa\u53bf"
    ],
    "wof:name":"Chenggu Xian",
    "wof:placetype":"locality"
},
  "geometry": {"coordinates":[107.32577999999999,33.15416],"type":"Point"}
}