{
  "type": "Feature",
  "properties": {
    "gn:admin1_code":"22.0",
    "gn:asciiname":"Xiaolianghou Xigou",
    "gn:country_code":"CN",
    "gn:dem":649,
    "gn:feature_class":"P",
    "gn:feature_code":"PPL",
    "gn:name":"Xiaolianghou Xigou",
    "gn:population":0,
    "gn:timezone":"Asia/Shanghai",
    "iso:country":"CN",
    "name:zho_x_preferred":[
        "\u5c0f\u6881\u540e\u897f\u6c9f"
    ],
    "wof:name":"Xiaolianghou Xigou",
    "wof:placetype":"locality"
},
  "geometry": {"coordinates":[116.51922,40.85297],"type":"Point"}
}