{
  "type": "Feature",
  "properties": {
    "gn:admin1_code":"12.0",
    "gn:asciiname":"Shangjietou",
    "gn:country_code":"CN",
    "gn:dem":30,
    "gn:feature_class":"P",
    "gn:feature_code":"PPL",
    "gn:name":"Shangjietou",
    "gn:population":0,
    "gn:timezone":"Asia/Shanghai",
    "iso:country":"CN",
    "name:und_x_variant":[
        "\u4e0a\u8857\u5934"
    ],
    "wof:name":"Shangjietou",
    "wof:placetype":"locality"
},
  "geometry": {"coordinates":[114.53775,30.86904],"type":"Point"}
}