{
  "type": "Feature",
  "properties": {
    "gn:admin1_code":"1.0",
    "gn:asciiname":"Liupeng",
    "gn:country_code":"CN",
    "gn:dem":8,
    "gn:feature_class":"P",
    "gn:feature_code":"PPL",
    "gn:name":"Liupeng",
    "gn:population":0,
    "gn:timezone":"Asia/Shanghai",
    "iso:country":"CN",
    "name:zho_x_preferred":[
        "\u516d\u68da"
    ],
    "wof:name":"Liupeng",
    "wof:placetype":"locality"
},
  "geometry": {"coordinates":[118.11154999999999,31.29312],"type":"Point"}
}