{
  "type": "Feature",
  "properties": {
    "gn:admin1_code":"9.0",
    "gn:asciiname":"Taicang",
    "gn:country_code":"CN",
    "gn:dem":162,
    "gn:feature_class":"P",
    "gn:feature_code":"PPL",
    "gn:name":"Taicang",
    "gn:population":0,
    "gn:timezone":"Asia/Shanghai",
    "iso:country":"CN",
    "name:ces_x_preferred":[
        "Tchaj-cchang"
    ],
    "name:cym_x_preferred":[
        "Taicang"
    ],
    "name:deu_x_preferred":[
        "Taicang"
    ],
    "name:fas_x_preferred":[
        "\u062a\u0627\u06cc\u06a9\u0627\u0646\u06af"
    ],
    "name:fra_x_preferred":[
        "Taicang"
    ],
    "name:ita_x_preferred":[
        "Taicang"
    ],
    "name:jpn_x_preferred":[
        "\u592a\u5009\u5e02"
    ],
    "name:kik_x_preferred":[
        "Taicang"
    ],
    "name:kor_x_preferred":[
        "\ud0c0\uc774\ucc3d\uc2dc"
    ],
    "name:nld_x_preferred":[
        "Taicang"
    ],
    "name:nor_x_preferred":[
        "Taicang"
    ],
    "name:pol_x_preferred":[
        "Taicang"
    ],
    "name:rus_x_preferred":[
        "\u0422\u0430\u0439\u0446\u0430\u043d"
    ],
    "name:spa_x_preferred":[
        "Taicang"
    ],
    "name:swe_x_preferred":[
        "Taicang"
    ],
    "name:tgl_x_preferred":[
        "Taicang"
    ],
    "name:urd_x_preferred":[
        "\u062a\u0627\u06cc\u06a9\u0627\u0646\u06af"
    ],
    "name:vie_x_preferred":[
        "Th\u00e1i Th\u01b0\u01a1ng"
    ],
    "name:zho_x_preferred":[
        "\u592a\u4ed3"
    ],
    "name:zho_x_variant":[
        "\u592a\u4ed3\u5e02"
    ],
    "wof:name":"Taicang",
    "wof:placetype":"locality"
},
  "geometry": {"coordinates":[112.55240999999999,34.75251],"type":"Point"}
}