{
  "type": "Feature",
  "properties": {
    "gn:admin1_code":"7.0",
    "gn:asciiname":"Weifangcun",
    "gn:country_code":"CN",
    "gn:dem":390,
    "gn:feature_class":"P",
    "gn:feature_code":"PPL",
    "gn:name":"Weifangcun",
    "gn:population":0,
    "gn:timezone":"Asia/Shanghai",
    "iso:country":"CN",
    "name:und_x_variant":[
        "\u9b4f\u574a\u6751"
    ],
    "name:zho_x_preferred":[
        "\u9b4f\u574a\u6751"
    ],
    "wof:name":"Weifangcun",
    "wof:placetype":"locality"
},
  "geometry": {"coordinates":[117.29446000000002,26.09395],"type":"Point"}
}