{
  "type": "Feature",
  "properties": {
    "gn:admin1_code":"14.0",
    "gn:asciiname":"Jiangba",
    "gn:country_code":"CN",
    "gn:dem":2965,
    "gn:feature_class":"P",
    "gn:feature_code":"PPL",
    "gn:name":"Jiangba",
    "gn:population":0,
    "gn:timezone":"Asia/Urumqi",
    "iso:country":"CN",
    "name:zho_x_preferred":[
        "\u964d\u5df4"
    ],
    "wof:name":"Jiangba",
    "wof:placetype":"locality"
},
  "geometry": {"coordinates":[94.88849,29.55275],"type":"Point"}
}