{
  "type": "Feature",
  "properties": {
    "gn:admin1_code":"6.0",
    "gn:asciiname":"Jangcang",
    "gn:country_code":"CN",
    "gn:dem":3756,
    "gn:feature_class":"P",
    "gn:feature_code":"PPL",
    "gn:name":"Jangcang",
    "gn:population":0,
    "gn:timezone":"Asia/Shanghai",
    "iso:country":"CN",
    "wof:name":"Jangcang",
    "wof:placetype":"locality"
},
  "geometry": {"coordinates":[99.66667,38.03333],"type":"Point"}
}