{
  "type": "Feature",
  "properties": {
    "gn:admin1_code":"30",
    "gn:asciiname":"Pingbu",
    "gn:country_code":"CN",
    "gn:dem":6,
    "gn:feature_class":"P",
    "gn:feature_code":"PPL",
    "gn:name":"Pingbu",
    "gn:population":0,
    "gn:timezone":"Asia/Urumqi",
    "iso:country":"CN",
    "name:zho_x_preferred":[
        "\u5e73\u6b65"
    ],
    "wof:name":"Pingbu",
    "wof:placetype":"locality"
},
  "geometry": {"coordinates":[109.86599,20.56462],"type":"Point"}
}