{
  "type": "Feature",
  "properties": {
    "gn:admin1_code":"32.0",
    "gn:asciiname":"Xiangzhang",
    "gn:country_code":"CN",
    "gn:dem":372,
    "gn:feature_class":"P",
    "gn:feature_code":"PPL",
    "gn:name":"Xiangzhang",
    "gn:population":0,
    "gn:timezone":"Asia/Shanghai",
    "iso:country":"CN",
    "name:zho_x_preferred":[
        "\u9999\u6a1f"
    ],
    "wof:name":"Xiangzhang",
    "wof:placetype":"locality"
},
  "geometry": {"coordinates":[105.30500000000001,30.8848],"type":"Point"}
}