{
  "type": "Feature",
  "properties": {
    "gn:admin1_code":"25.0",
    "gn:asciiname":"Longwantou",
    "gn:country_code":"CN",
    "gn:dem":176,
    "gn:feature_class":"P",
    "gn:feature_code":"PPL",
    "gn:name":"Longwantou",
    "gn:population":0,
    "gn:timezone":"Asia/Shanghai",
    "iso:country":"CN",
    "name:zho_x_preferred":[
        "\u9f99\u6e7e\u5934"
    ],
    "wof:name":"Longwantou",
    "wof:placetype":"locality"
},
  "geometry": {"coordinates":[119.46747000000001,35.81395999999999],"type":"Point"}
}