{
  "type": "Feature",
  "properties": {
    "gn:admin1_code":"5.0",
    "gn:asciiname":"Yijiacun",
    "gn:country_code":"CN",
    "gn:dem":209,
    "gn:feature_class":"P",
    "gn:feature_code":"PPL",
    "gn:name":"Yijiacun",
    "gn:population":0,
    "gn:timezone":"Asia/Shanghai",
    "iso:country":"CN",
    "name:zho_x_preferred":[
        "\u8863\u5bb6\u6751"
    ],
    "wof:name":"Yijiacun",
    "wof:placetype":"locality"
},
  "geometry": {"coordinates":[125.22936,43.96454],"type":"Point"}
}