{
  "type": "Feature",
  "properties": {
    "gn:admin1_code":"16.0",
    "gn:asciiname":"Baijiucun",
    "gn:country_code":"CN",
    "gn:dem":703,
    "gn:feature_class":"P",
    "gn:feature_code":"PPL",
    "gn:name":"Baijiucun",
    "gn:population":0,
    "gn:timezone":"Asia/Shanghai",
    "iso:country":"CN",
    "name:zho_x_preferred":[
        "\u767e\u4e5d\u6751"
    ],
    "wof:name":"Baijiucun",
    "wof:placetype":"locality"
},
  "geometry": {"coordinates":[107.06100000000001,24.0916],"type":"Point"}
}