{
  "type": "Feature",
  "properties": {
    "gn:admin1_code":"7.0",
    "gn:asciiname":"Lihuanglian",
    "gn:country_code":"CN",
    "gn:dem":614,
    "gn:feature_class":"P",
    "gn:feature_code":"PPL",
    "gn:name":"Lihuanglian",
    "gn:population":0,
    "gn:timezone":"Asia/Shanghai",
    "iso:country":"CN",
    "name:zho_x_preferred":[
        "\u91cc\u9ec4\u8fde"
    ],
    "wof:name":"Lihuanglian",
    "wof:placetype":"locality"
},
  "geometry": {"coordinates":[118.60826000000002,26.55397],"type":"Point"}
}