{
  "type": "Feature",
  "properties": {
    "gn:admin1_code":"4.0",
    "gn:asciiname":"Guanhecun",
    "gn:country_code":"CN",
    "gn:dem":5,
    "gn:feature_class":"P",
    "gn:feature_code":"PPL",
    "gn:name":"Guanhecun",
    "gn:population":0,
    "gn:timezone":"Asia/Shanghai",
    "iso:country":"CN",
    "name:und_x_variant":[
        "Guanhe"
    ],
    "name:zho_x_preferred":[
        "\u5b98\u6cb3\u6751"
    ],
    "wof:name":"Guanhecun",
    "wof:placetype":"locality"
},
  "geometry": {"coordinates":[119.0705,34.92511],"type":"Point"}
}