{
  "type": "Feature",
  "properties": {
    "gn:admin1_code":"02",
    "gn:asciiname":"Dongcun",
    "gn:country_code":"CN",
    "gn:dem":48,
    "gn:feature_class":"P",
    "gn:feature_code":"PPL",
    "gn:name":"Dongcun",
    "gn:population":0,
    "gn:timezone":"Asia/Shanghai",
    "iso:country":"CN",
    "name:und_x_variant":[
        "Tung-ts\u2019un",
        "Dongcun"
    ],
    "name:zho_x_preferred":[
        "\u4e1c\u6751"
    ],
    "wof:name":"Dongcun",
    "wof:placetype":"locality"
},
  "geometry": {"coordinates":[120.78845,28.25929],"type":"Point"}
}