{
  "type": "Feature",
  "properties": {
    "gn:admin1_code":"03",
    "gn:asciiname":"Furong",
    "gn:country_code":"CN",
    "gn:dem":139,
    "gn:feature_class":"P",
    "gn:feature_code":"PPLA3",
    "gn:name":"Furong",
    "gn:population":0,
    "gn:timezone":"Asia/Shanghai",
    "iso:country":"CN",
    "name:ces_x_preferred":[
        "Wan-an"
    ],
    "name:deu_x_preferred":[
        "Wan\u2019an"
    ],
    "name:fas_x_preferred":[
        "\u0634\u0647\u0631\u0633\u062a\u0627\u0646 \u0648\u0627\u0646\u0627\u0646"
    ],
    "name:jpn_x_preferred":[
        "\u4e07\u5b89\u770c"
    ],
    "name:kor_x_preferred":[
        "\uc644\uc548\ud604"
    ],
    "name:nor_x_preferred":[
        "Wan'an"
    ],
    "name:swe_x_preferred":[
        "Wan'an"
    ],
    "name:und_x_variant":[
        "Wan-an-hsien-ch\u2019eng",
        "Wan-an-hsien",
        "Furong",
        "Wan\u2019an Xian"
    ],
    "name:vie_x_preferred":[
        "V\u1ea1n An"
    ],
    "name:zho_x_preferred":[
        "\u8299\u84c9"
    ],
    "name:zho_x_variant":[
        "\u4e07\u5b89\u53bf"
    ],
    "wof:name":"Furong",
    "wof:placetype":"locality"
},
  "geometry": {"coordinates":[114.76667,26.45],"type":"Point"}
}