{
  "type": "Feature",
  "properties": {
    "gn:admin1_code":"31",
    "gn:asciiname":"Yaba",
    "gn:country_code":"CN",
    "gn:dem":266,
    "gn:feature_class":"P",
    "gn:feature_code":"PPL",
    "gn:name":"Yaba",
    "gn:population":0,
    "gn:timezone":"Asia/Shanghai",
    "iso:country":"CN",
    "name:ceb_x_preferred":[
        "Yaba"
    ],
    "name:deu_x_preferred":[
        "Yaba"
    ],
    "name:est_x_preferred":[
        "Yaba"
    ],
    "name:fra_x_preferred":[
        "Yaba"
    ],
    "name:swe_x_preferred":[
        "Yaba"
    ],
    "name:und_x_variant":[
        "\u7259\u575d",
        "Dazhangcun"
    ],
    "wof:name":"Yaba",
    "wof:placetype":"locality"
},
  "geometry": {"coordinates":[109.4092,19.12859],"type":"Point"}
}