{
  "type": "Feature",
  "properties": {
    "gn:admin1_code":"29.0",
    "gn:asciiname":"Dongde",
    "gn:country_code":"CN",
    "gn:dem":2212,
    "gn:feature_class":"P",
    "gn:feature_code":"PPL",
    "gn:name":"Dongde",
    "gn:population":0,
    "gn:timezone":"Asia/Shanghai",
    "iso:country":"CN",
    "name:und_x_variant":[
        "\u8463\u5f97"
    ],
    "wof:name":"Dongde",
    "wof:placetype":"locality"
},
  "geometry": {"coordinates":[103.49451999999999,26.08234],"type":"Point"}
}