{
  "type": "Feature",
  "properties": {
    "gn:admin1_code":"15.0",
    "gn:asciiname":"Talasi",
    "gn:country_code":"CN",
    "gn:dem":2346,
    "gn:feature_class":"P",
    "gn:feature_code":"PPL",
    "gn:name":"Talasi",
    "gn:population":0,
    "gn:timezone":"Asia/Shanghai",
    "iso:country":"CN",
    "name:und_x_variant":[
        "\u5854\u5587\u5bfa"
    ],
    "wof:name":"Talasi",
    "wof:placetype":"locality"
},
  "geometry": {"coordinates":[104.96355,34.5786],"type":"Point"}
}