{
  "type": "Feature",
  "properties": {
    "gn:admin1_code":"9.0",
    "gn:asciiname":"Shangluying",
    "gn:country_code":"CN",
    "gn:dem":250,
    "gn:feature_class":"P",
    "gn:feature_code":"PPL",
    "gn:name":"Shangl\u00fcying",
    "gn:population":0,
    "gn:timezone":"Asia/Shanghai",
    "iso:country":"CN",
    "name:und_x_variant":[
        "Shangl\u00fcying"
    ],
    "name:zho_x_preferred":[
        "\u4e0a\u5415\u8425"
    ],
    "wof:name":"Shangluying",
    "wof:placetype":"locality"
},
  "geometry": {"coordinates":[111.75932,33.22085],"type":"Point"}
}