{
  "type": "Feature",
  "properties": {
    "gn:admin1_code":"25",
    "gn:asciiname":"Nanxuye",
    "gn:country_code":"CN",
    "gn:dem":172,
    "gn:feature_class":"P",
    "gn:feature_code":"PPL",
    "gn:name":"Nanxuye",
    "gn:population":0,
    "gn:timezone":"Asia/Shanghai",
    "iso:country":"CN",
    "name:zho_x_preferred":[
        "\u5357\u5f90\u51b6"
    ],
    "wof:name":"Nanxuye",
    "wof:placetype":"locality"
},
  "geometry": {"coordinates":[117.444,36.1215],"type":"Point"}
}