{
  "type": "Feature",
  "properties": {
    "gn:admin1_code":"30.0",
    "gn:asciiname":"Tanglangjing",
    "gn:country_code":"CN",
    "gn:dem":518,
    "gn:feature_class":"P",
    "gn:feature_code":"PPL",
    "gn:name":"Tanglangjing",
    "gn:population":0,
    "gn:timezone":"Asia/Shanghai",
    "iso:country":"CN",
    "name:zho_x_preferred":[
        "Tanglangjing"
    ],
    "name:zho_x_variant":[
        "\u87b3\u8782\u8ff3"
    ],
    "wof:name":"Tanglangjing",
    "wof:placetype":"locality"
},
  "geometry": {"coordinates":[112.78194000000001,24.57389],"type":"Point"}
}