{
  "type": "Feature",
  "properties": {
    "gn:admin1_code":"29.0",
    "gn:asciiname":"Dazhupeng",
    "gn:country_code":"CN",
    "gn:dem":1488,
    "gn:feature_class":"P",
    "gn:feature_code":"PPL",
    "gn:name":"Dazhupeng",
    "gn:population":0,
    "gn:timezone":"Asia/Shanghai",
    "iso:country":"CN",
    "name:zho_x_preferred":[
        "\u5927\u7af9\u68da"
    ],
    "wof:name":"Dazhupeng",
    "wof:placetype":"locality"
},
  "geometry": {"coordinates":[103.803,23.0718],"type":"Point"}
}