{
  "type": "Feature",
  "properties": {
    "gn:admin1_code":"11.0",
    "gn:asciiname":"Zhaixichong",
    "gn:country_code":"CN",
    "gn:dem":431,
    "gn:feature_class":"P",
    "gn:feature_code":"PPL",
    "gn:name":"Zhaixichong",
    "gn:population":0,
    "gn:timezone":"Asia/Shanghai",
    "iso:country":"CN",
    "name:zho_x_preferred":[
        "\u5be8\u6eaa\u51b2"
    ],
    "wof:name":"Zhaixichong",
    "wof:placetype":"locality"
},
  "geometry": {"coordinates":[109.27949,27.32263],"type":"Point"}
}