{
  "type": "Feature",
  "properties": {
    "gn:admin1_code":"18",
    "gn:asciiname":"Suiyangshan",
    "gn:country_code":"CN",
    "gn:dem":801,
    "gn:feature_class":"P",
    "gn:feature_code":"PPL",
    "gn:name":"Suiyangshan",
    "gn:population":0,
    "gn:timezone":"Asia/Shanghai",
    "iso:country":"CN",
    "name:zho_x_preferred":[
        "\u968f\u9633\u5c71"
    ],
    "wof:name":"Suiyangshan",
    "wof:placetype":"locality"
},
  "geometry": {"coordinates":[107.645,27.9505],"type":"Point"}
}