{
  "type": "Feature",
  "properties": {
    "gn:admin1_code":"22.0",
    "gn:asciiname":"Sandaoliangcun",
    "gn:country_code":"CN",
    "gn:dem":572,
    "gn:feature_class":"P",
    "gn:feature_code":"PPL",
    "gn:name":"Sandaoliangcun",
    "gn:population":0,
    "gn:timezone":"Asia/Shanghai",
    "iso:country":"CN",
    "name:zho_x_preferred":[
        "\u4e09\u9053\u6881\u6751"
    ],
    "wof:name":"Sandaoliangcun",
    "wof:placetype":"locality"
},
  "geometry": {"coordinates":[116.38934999999999,40.71078],"type":"Point"}
}