{
  "type": "Feature",
  "properties": {
    "gn:admin1_code":"1.0",
    "gn:asciiname":"Licuicun",
    "gn:country_code":"CN",
    "gn:dem":33,
    "gn:feature_class":"P",
    "gn:feature_code":"PPL",
    "gn:name":"Licuicun",
    "gn:population":0,
    "gn:timezone":"Asia/Shanghai",
    "iso:country":"CN",
    "name:zho_x_preferred":[
        "\u674e\u7fe0\u6751"
    ],
    "wof:name":"Licuicun",
    "wof:placetype":"locality"
},
  "geometry": {"coordinates":[115.34692,33.07471],"type":"Point"}
}