{
  "type": "Feature",
  "properties": {
    "gn:admin1_code":"5.0",
    "gn:asciiname":"Xinchangningping",
    "gn:country_code":"CN",
    "gn:dem":554,
    "gn:feature_class":"P",
    "gn:feature_code":"PPL",
    "gn:name":"Xinchangningping",
    "gn:population":0,
    "gn:timezone":"Asia/Shanghai",
    "iso:country":"CN",
    "name:und_x_variant":[
        "\u65b0\u957f\u5b81\u576a"
    ],
    "wof:name":"Xinchangningping",
    "wof:placetype":"locality"
},
  "geometry": {"coordinates":[128.89819,42.60448],"type":"Point"}
}