{
  "type": "Feature",
  "properties": {
    "gn:admin1_code":"4.0",
    "gn:asciiname":"Fajiaodian",
    "gn:country_code":"CN",
    "gn:dem":3,
    "gn:feature_class":"P",
    "gn:feature_code":"PPL",
    "gn:name":"Fajiaodian",
    "gn:population":0,
    "gn:timezone":"Asia/Shanghai",
    "iso:country":"CN",
    "name:und_x_variant":[
        "\u53d1\u89d2\u6bbf"
    ],
    "wof:name":"Fajiaodian",
    "wof:placetype":"locality"
},
  "geometry": {"coordinates":[120.90665,32.1694],"type":"Point"}
}