{
  "type": "Feature",
  "properties": {
    "gn:admin1_code":"25",
    "gn:asciiname":"Zhanzi Yicun",
    "gn:country_code":"CN",
    "gn:dem":5,
    "gn:feature_class":"P",
    "gn:feature_code":"PPL",
    "gn:name":"Zhanzi Yicun",
    "gn:population":0,
    "gn:timezone":"Asia/Shanghai",
    "iso:country":"CN",
    "name:zho_x_preferred":[
        "\u6808\u5b50\u4e00\u6751"
    ],
    "wof:name":"Zhanzi Yicun",
    "wof:placetype":"locality"
},
  "geometry": {"coordinates":[119.387,35.2393],"type":"Point"}
}