{
  "type": "Feature",
  "properties": {
    "gn:admin1_code":"20.0",
    "gn:asciiname":"Dudaigou",
    "gn:country_code":"CN",
    "gn:dem":291,
    "gn:feature_class":"P",
    "gn:feature_code":"PPL",
    "gn:name":"Dudaigou",
    "gn:population":0,
    "gn:timezone":"Asia/Shanghai",
    "iso:country":"CN",
    "name:zho_x_preferred":[
        "\u675c\u4ee3\u6c9f"
    ],
    "wof:name":"Dudaigou",
    "wof:placetype":"locality"
},
  "geometry": {"coordinates":[123.59989,48.75552],"type":"Point"}
}