{
  "type": "Feature",
  "properties": {
    "gn:admin1_code":"33.0",
    "gn:asciiname":"Chensanfang",
    "gn:country_code":"CN",
    "gn:dem":343,
    "gn:feature_class":"P",
    "gn:feature_code":"PPL",
    "gn:name":"Chensanfang",
    "gn:population":0,
    "gn:timezone":"Asia/Shanghai",
    "iso:country":"CN",
    "name:zho_x_preferred":[
        "\u9648\u4e09\u623f"
    ],
    "wof:name":"Chensanfang",
    "wof:placetype":"locality"
},
  "geometry": {"coordinates":[106.917,28.9357],"type":"Point"}
}