{
  "type": "Feature",
  "properties": {
    "gn:admin1_code":"29.0",
    "gn:asciiname":"Yiweijie",
    "gn:country_code":"CN",
    "gn:dem":590,
    "gn:feature_class":"P",
    "gn:feature_code":"PPL",
    "gn:name":"Yiweijie",
    "gn:population":0,
    "gn:timezone":"Asia/Shanghai",
    "iso:country":"CN",
    "name:zho_x_preferred":[
        "\u5b9c\u5c09\u8857"
    ],
    "wof:name":"Yiweijie",
    "wof:placetype":"locality"
},
  "geometry": {"coordinates":[100.833,21.9924],"type":"Point"}
}