{
  "type": "Feature",
  "properties": {
    "gn:admin1_code":"5.0",
    "gn:asciiname":"Wenjia Hekoucun",
    "gn:country_code":"CN",
    "gn:dem":174,
    "gn:feature_class":"P",
    "gn:feature_code":"PPL",
    "gn:name":"Wenjia Hekoucun",
    "gn:population":0,
    "gn:timezone":"Asia/Shanghai",
    "iso:country":"CN",
    "name:zho_x_preferred":[
        "\u6e29\u5bb6\u6cb3\u53e3\u6751"
    ],
    "wof:name":"Wenjia Hekoucun",
    "wof:placetype":"locality"
},
  "geometry": {"coordinates":[124.68528000000001,43.5097],"type":"Point"}
}