{
  "type": "Feature",
  "properties": {
    "gn:admin1_code":"3.0",
    "gn:asciiname":"Guantoubei",
    "gn:country_code":"CN",
    "gn:dem":208,
    "gn:feature_class":"P",
    "gn:feature_code":"PPL",
    "gn:name":"Guantoubei",
    "gn:population":0,
    "gn:timezone":"Asia/Shanghai",
    "iso:country":"CN",
    "name:und_x_variant":[
        "\u704c\u5934\u9642"
    ],
    "wof:name":"Guantoubei",
    "wof:placetype":"locality"
},
  "geometry": {"coordinates":[116.28792,26.18638],"type":"Point"}
}