{
  "type": "Feature",
  "properties": {
    "gn:admin1_code":"31.0",
    "gn:asciiname":"Yezhuang",
    "gn:country_code":"CN",
    "gn:dem":2,
    "gn:feature_class":"P",
    "gn:feature_code":"PPL",
    "gn:name":"Yezhuang",
    "gn:population":0,
    "gn:timezone":"Asia/Shanghai",
    "iso:country":"CN",
    "name:und_x_variant":[
        "\u6930\u5e84"
    ],
    "wof:name":"Yezhuang",
    "wof:placetype":"locality"
},
  "geometry": {"coordinates":[109.48519,18.20655],"type":"Point"}
}