{
  "type": "Feature",
  "properties": {
    "gn:admin1_code":"26.0",
    "gn:asciiname":"Guojiashan",
    "gn:country_code":"CN",
    "gn:dem":1292,
    "gn:feature_class":"P",
    "gn:feature_code":"PPL",
    "gn:name":"Guojiashan",
    "gn:population":0,
    "gn:timezone":"Asia/Shanghai",
    "iso:country":"CN",
    "name:zho_x_preferred":[
        "\u90ed\u5bb6\u5c71"
    ],
    "wof:name":"Guojiashan",
    "wof:placetype":"locality"
},
  "geometry": {"coordinates":[106.83786000000001,35.03252],"type":"Point"}
}