{
  "type": "Feature",
  "properties": {
    "gn:admin1_code":"14.0",
    "gn:asciiname":"Zuobude",
    "gn:country_code":"CN",
    "gn:dem":4335,
    "gn:feature_class":"P",
    "gn:feature_code":"PPLA4",
    "gn:name":"Zuobude",
    "gn:population":0,
    "gn:timezone":"Asia/Urumqi",
    "iso:country":"CN",
    "name:bod_x_preferred":[
        "Zhobd\u00ea"
    ],
    "name:zho_x_preferred":[
        "Zuobude"
    ],
    "name:zho_x_variant":[
        "\u5de6\u5e03\u5fb7",
        "Zuobude Xiang",
        "\u5de6\u5e03\u5fb7\u4e61"
    ],
    "wof:name":"Zuobude",
    "wof:placetype":"locality"
},
  "geometry": {"coordinates":[86.303,28.003],"type":"Point"}
}