{
  "type": "Feature",
  "properties": {
    "gn:admin1_code":"6.0",
    "gn:asciiname":"Jiajiang Gencai",
    "gn:country_code":"CN",
    "gn:dem":4204,
    "gn:feature_class":"P",
    "gn:feature_code":"PPL",
    "gn:name":"Jiajiang Gencai",
    "gn:population":0,
    "gn:timezone":"Asia/Urumqi",
    "iso:country":"CN",
    "name:zho_x_preferred":[
        "\u52a0\u6c5f\u6839\u624d"
    ],
    "wof:name":"Jiajiang Gencai",
    "wof:placetype":"locality"
},
  "geometry": {"coordinates":[96.23945000000001,32.13244],"type":"Point"}
}