{
  "type": "Feature",
  "properties": {
    "gn:admin1_code":"30.0",
    "gn:asciiname":"Bipucun",
    "gn:country_code":"CN",
    "gn:dem":23,
    "gn:feature_class":"P",
    "gn:feature_code":"PPL",
    "gn:name":"Bipucun",
    "gn:population":0,
    "gn:timezone":"Asia/Shanghai",
    "iso:country":"CN",
    "name:zho_x_preferred":[
        "\u7b14\u57d4\u6751"
    ],
    "wof:name":"Bipucun",
    "wof:placetype":"locality"
},
  "geometry": {"coordinates":[116.51675,23.67798],"type":"Point"}
}