{
  "type": "Feature",
  "properties": {
    "gn:admin1_code":"25.0",
    "gn:asciiname":"Lusucun",
    "gn:country_code":"CN",
    "gn:dem":17,
    "gn:feature_class":"P",
    "gn:feature_code":"PPL",
    "gn:name":"Lusucun",
    "gn:population":0,
    "gn:timezone":"Asia/Shanghai",
    "iso:country":"CN",
    "name:zho_x_preferred":[
        "\u8def\u5bbf\u6751"
    ],
    "wof:name":"Lusucun",
    "wof:placetype":"locality"
},
  "geometry": {"coordinates":[119.97423999999999,37.2919],"type":"Point"}
}