{
  "type": "Feature",
  "properties": {
    "gn:admin1_code":"5.0",
    "gn:asciiname":"Gangjiecun",
    "gn:country_code":"CN",
    "gn:dem":215,
    "gn:feature_class":"P",
    "gn:feature_code":"PPL",
    "gn:name":"Gangjiecun",
    "gn:population":0,
    "gn:timezone":"Asia/Shanghai",
    "iso:country":"CN",
    "name:zho_x_preferred":[
        "\u5c97\u8857\u6751"
    ],
    "wof:name":"Gangjiecun",
    "wof:placetype":"locality"
},
  "geometry": {"coordinates":[127.05462,44.54244],"type":"Point"}
}