{
  "type": "Feature",
  "properties": {
    "gn:admin1_code":"32.0",
    "gn:asciiname":"Jinbaochang",
    "gn:country_code":"CN",
    "gn:dem":466,
    "gn:feature_class":"P",
    "gn:feature_code":"PPL",
    "gn:name":"Jinbaochang",
    "gn:population":0,
    "gn:timezone":"Asia/Shanghai",
    "iso:country":"CN",
    "name:zho_x_preferred":[
        "\u8fdb\u5b9d\u573a"
    ],
    "wof:name":"Jinbaochang",
    "wof:placetype":"locality"
},
  "geometry": {"coordinates":[105.98345999999999,28.85193],"type":"Point"}
}