{
  "type": "Feature",
  "properties": {
    "gn:admin1_code":"32.0",
    "gn:asciiname":"Luantianwan",
    "gn:country_code":"CN",
    "gn:dem":519,
    "gn:feature_class":"P",
    "gn:feature_code":"PPL",
    "gn:name":"Luantianwan",
    "gn:population":0,
    "gn:timezone":"Asia/Shanghai",
    "iso:country":"CN",
    "name:zho_x_preferred":[
        "\u4e71\u7530\u6e7e"
    ],
    "wof:name":"Luantianwan",
    "wof:placetype":"locality"
},
  "geometry": {"coordinates":[106.69846,31.72267],"type":"Point"}
}