{
  "type": "Feature",
  "properties": {
    "gn:admin1_code":"15.0",
    "gn:asciiname":"Shangxiang",
    "gn:country_code":"CN",
    "gn:dem":1549,
    "gn:feature_class":"P",
    "gn:feature_code":"PPL",
    "gn:name":"Shangxiang",
    "gn:population":0,
    "gn:timezone":"Asia/Shanghai",
    "iso:country":"CN",
    "name:und_x_variant":[
        "\u4e0a\u5df7"
    ],
    "wof:name":"Shangxiang",
    "wof:placetype":"locality"
},
  "geometry": {"coordinates":[105.40985000000001,33.86935],"type":"Point"}
}