{
  "type": "Feature",
  "properties": {
    "gn:admin1_code":"26.0",
    "gn:asciiname":"Weijia",
    "gn:country_code":"CN",
    "gn:dem":1495,
    "gn:feature_class":"P",
    "gn:feature_code":"PPL",
    "gn:name":"Weijia",
    "gn:population":0,
    "gn:timezone":"Asia/Shanghai",
    "iso:country":"CN",
    "name:und_x_variant":[
        "\u9b4f\u5bb6"
    ],
    "wof:name":"Weijia",
    "wof:placetype":"locality"
},
  "geometry": {"coordinates":[106.77825,34.05985],"type":"Point"}
}