{
  "type": "Feature",
  "properties": {
    "gn:admin1_code":"14.0",
    "gn:asciiname":"Gamotong",
    "gn:country_code":"CN",
    "gn:dem":3265,
    "gn:feature_class":"P",
    "gn:feature_code":"PPL",
    "gn:name":"Gamotong",
    "gn:population":0,
    "gn:timezone":"Asia/Urumqi",
    "iso:country":"CN",
    "name:zho_x_preferred":[
        "\u560e\u83ab\u901a"
    ],
    "wof:name":"Gamotong",
    "wof:placetype":"locality"
},
  "geometry": {"coordinates":[97.17869,31.16764],"type":"Point"}
}