{
  "type": "Feature",
  "properties": {
    "gn:admin1_code":"29.0",
    "gn:asciiname":"Jiujingshi",
    "gn:country_code":"CN",
    "gn:dem":1552,
    "gn:feature_class":"P",
    "gn:feature_code":"PPL",
    "gn:name":"Jiujingshi",
    "gn:population":0,
    "gn:timezone":"Asia/Shanghai",
    "iso:country":"CN",
    "name:zho_x_preferred":[
        "\u65e7\u51c0\u77f3"
    ],
    "wof:name":"Jiujingshi",
    "wof:placetype":"locality"
},
  "geometry": {"coordinates":[101.727,25.6593],"type":"Point"}
}