{
  "type": "Feature",
  "properties": {
    "gn:admin1_code":"10.0",
    "gn:asciiname":"Xiwangqi",
    "gn:country_code":"CN",
    "gn:dem":32,
    "gn:feature_class":"P",
    "gn:feature_code":"PPL",
    "gn:name":"Xiwangqi",
    "gn:population":0,
    "gn:timezone":"Asia/Shanghai",
    "iso:country":"CN",
    "name:zho_x_preferred":[
        "\u897f\u738b\u5947"
    ],
    "wof:name":"Xiwangqi",
    "wof:placetype":"locality"
},
  "geometry": {"coordinates":[115.34,38.3665],"type":"Point"}
}