{
  "type": "Feature",
  "properties": {
    "gn:admin1_code":"31",
    "gn:asciiname":"Lizhigou",
    "gn:country_code":"CN",
    "gn:dem":13,
    "gn:feature_class":"P",
    "gn:feature_code":"PPL",
    "gn:name":"Lizhigou",
    "gn:population":0,
    "gn:timezone":"Asia/Shanghai",
    "iso:country":"CN",
    "name:und_x_variant":[
        "\u8354\u679d\u6c9f"
    ],
    "wof:name":"Lizhigou",
    "wof:placetype":"locality"
},
  "geometry": {"coordinates":[109.532,18.2986],"type":"Point"}
}