{
  "type": "Feature",
  "properties": {
    "gn:admin1_code":"6.0",
    "gn:asciiname":"Bami",
    "gn:country_code":"CN",
    "gn:dem":3755,
    "gn:feature_class":"P",
    "gn:feature_code":"PPL",
    "gn:name":"Bami",
    "gn:population":0,
    "gn:timezone":"Asia/Urumqi",
    "iso:country":"CN",
    "name:zho_x_preferred":[
        "\u5df4\u7c73"
    ],
    "wof:name":"Bami",
    "wof:placetype":"locality"
},
  "geometry": {"coordinates":[96.42871,32.19166],"type":"Point"}
}