{
  "type": "Feature",
  "properties": {
    "gn:admin1_code":"7",
    "gn:asciiname":"Kengtou",
    "gn:country_code":"CN",
    "gn:dem":547,
    "gn:feature_class":"P",
    "gn:feature_code":"PPL",
    "gn:name":"Kengtou",
    "gn:population":0,
    "gn:timezone":"Asia/Shanghai",
    "iso:country":"CN",
    "name:und_x_variant":[
        "\u5751\u5934"
    ],
    "wof:name":"Kengtou",
    "wof:placetype":"locality"
},
  "geometry": {"coordinates":[118.21138999999999,26.07833],"type":"Point"}
}