{
  "type": "Feature",
  "properties": {
    "iso:country":"CN",
    "qs:name":"\u963f\u575d",
    "qs:name_adm0":"\u4e2d\u570b",
    "qs:name_adm1":"\u56db\u5ddd\u7701",
    "qs:photos":490,
    "qs:photos_1k":99,
    "qs:photos_9k":2,
    "qs:photos_9r":5,
    "qs:photos_all":490,
    "qs:photos_sr":7,
    "qs:placetype":"Town",
    "qs:pop_sr":"0",
    "wof:name":"\u963f\u575d",
    "wof:placetype":"locality"
},
  "geometry": {"coordinates":[101.700782,32.907118],"type":"Point"}
}