{
  "type": "Feature",
  "properties": {
    "gn:admin1_code":"16.0",
    "gn:asciiname":"Wei'e",
    "gn:country_code":"CN",
    "gn:dem":754,
    "gn:feature_class":"P",
    "gn:feature_code":"PPL",
    "gn:name":"Wei\u2019e",
    "gn:population":0,
    "gn:timezone":"Asia/Shanghai",
    "iso:country":"CN",
    "name:und_x_variant":[
        "Wei\u2019e"
    ],
    "name:zho_x_preferred":[
        "\u6e2d\u989d"
    ],
    "wof:name":"Wei'e",
    "wof:placetype":"locality"
},
  "geometry": {"coordinates":[106.14400000000001,24.3162],"type":"Point"}
}