{
  "type": "Feature",
  "properties": {
    "gn:admin1_code":"29.0",
    "gn:asciiname":"Maidichong",
    "gn:country_code":"CN",
    "gn:dem":2062,
    "gn:feature_class":"P",
    "gn:feature_code":"PPL",
    "gn:name":"Maidichong",
    "gn:population":0,
    "gn:timezone":"Asia/Shanghai",
    "iso:country":"CN",
    "name:zho_x_preferred":[
        "\u9ea6\u5730\u51b2"
    ],
    "wof:name":"Maidichong",
    "wof:placetype":"locality"
},
  "geometry": {"coordinates":[103.697,25.772],"type":"Point"}
}