{
  "type": "Feature",
  "properties": {
    "gn:admin1_code":"16",
    "gn:asciiname":"Nawancun",
    "gn:country_code":"CN",
    "gn:dem":368,
    "gn:feature_class":"P",
    "gn:feature_code":"PPL",
    "gn:name":"Nawancun",
    "gn:population":0,
    "gn:timezone":"Asia/Shanghai",
    "iso:country":"CN",
    "name:und_x_variant":[
        "Na-wu-ts\u2019un",
        "Nawancun"
    ],
    "name:zho_x_preferred":[
        "\u90a3\u4e07\u6751"
    ],
    "wof:name":"Nawancun",
    "wof:placetype":"locality"
},
  "geometry": {"coordinates":[105.90600000000001,23.0618],"type":"Point"}
}