{
  "type": "Feature",
  "properties": {
    "gn:admin1_code":"19.0",
    "gn:asciiname":"Shitoushancun",
    "gn:country_code":"CN",
    "gn:dem":70,
    "gn:feature_class":"P",
    "gn:feature_code":"PPL",
    "gn:name":"Shitoushancun",
    "gn:population":0,
    "gn:timezone":"Asia/Shanghai",
    "iso:country":"CN",
    "name:zho_x_preferred":[
        "\u77f3\u5934\u5c71\u6751"
    ],
    "wof:name":"Shitoushancun",
    "wof:placetype":"locality"
},
  "geometry": {"coordinates":[122.678,42.3178],"type":"Point"}
}