{
  "type": "Feature",
  "properties": {
    "gn:admin1_code":"32.0",
    "gn:asciiname":"Hongwuyue",
    "gn:country_code":"CN",
    "gn:dem":1993,
    "gn:feature_class":"P",
    "gn:feature_code":"PPL",
    "gn:name":"Hongwuyue",
    "gn:population":0,
    "gn:timezone":"Asia/Shanghai",
    "iso:country":"CN",
    "name:zho_x_preferred":[
        "\u7ea2\u4e94\u6708"
    ],
    "wof:name":"Hongwuyue",
    "wof:placetype":"locality"
},
  "geometry": {"coordinates":[101.98999999999999,30.9547],"type":"Point"}
}