{
  "type": "Feature",
  "properties": {
    "gn:admin1_code":"14.0",
    "gn:asciiname":"Xaga",
    "gn:country_code":"CN",
    "gn:dem":4651,
    "gn:feature_class":"P",
    "gn:feature_code":"PPL",
    "gn:name":"Xaga",
    "gn:population":0,
    "gn:timezone":"Asia/Urumqi",
    "iso:country":"CN",
    "name:msa_x_preferred":[
        "Xaga"
    ],
    "wof:name":"Xaga",
    "wof:placetype":"locality"
},
  "geometry": {"coordinates":[85.76666999999998,28.76667],"type":"Point"}
}