{
  "type": "Feature",
  "properties": {
    "gn:admin1_code":"12.0",
    "gn:asciiname":"Chenjiacao",
    "gn:country_code":"CN",
    "gn:dem":1371,
    "gn:feature_class":"P",
    "gn:feature_code":"PPL",
    "gn:name":"Chenjiacao",
    "gn:population":0,
    "gn:timezone":"Asia/Shanghai",
    "iso:country":"CN",
    "name:zho_x_preferred":[
        "Chenjiacao"
    ],
    "name:zho_x_variant":[
        "\u9648\u5bb6\u69fd"
    ],
    "wof:name":"Chenjiacao",
    "wof:placetype":"locality"
},
  "geometry": {"coordinates":[109.56480999999999,29.75898],"type":"Point"}
}