{
  "type": "Feature",
  "properties": {
    "gn:admin1_code":"19.0",
    "gn:asciiname":"Baoshigou",
    "gn:country_code":"CN",
    "gn:dem":137,
    "gn:feature_class":"P",
    "gn:feature_code":"PPL",
    "gn:name":"Baoshigou",
    "gn:population":0,
    "gn:timezone":"Asia/Shanghai",
    "iso:country":"CN",
    "name:zho_x_preferred":[
        "\u5b9d\u77f3\u6c9f"
    ],
    "wof:name":"Baoshigou",
    "wof:placetype":"locality"
},
  "geometry": {"coordinates":[123.73399999999999,41.9572],"type":"Point"}
}