{
  "type": "Feature",
  "properties": {
    "gn:admin1_code":"14.0",
    "gn:asciiname":"Rishucun",
    "gn:country_code":"CN",
    "gn:dem":3840,
    "gn:feature_class":"P",
    "gn:feature_code":"PPL",
    "gn:name":"Rishucun",
    "gn:population":0,
    "gn:timezone":"Asia/Urumqi",
    "iso:country":"CN",
    "name:zho_x_preferred":[
        "\u65e5\u7f72\u6751"
    ],
    "wof:name":"Rishucun",
    "wof:placetype":"locality"
},
  "geometry": {"coordinates":[91.87255999999999,29.01177],"type":"Point"}
}