{
  "type": "Feature",
  "properties": {
    "gn:admin1_code":"18",
    "gn:asciiname":"Lingyi",
    "gn:country_code":"CN",
    "gn:dem":1306,
    "gn:feature_class":"P",
    "gn:feature_code":"PPL",
    "gn:name":"Lingyi",
    "gn:population":0,
    "gn:timezone":"Asia/Shanghai",
    "iso:country":"CN",
    "name:zho_x_preferred":[
        "\u53e6\u5df2"
    ],
    "wof:name":"Lingyi",
    "wof:placetype":"locality"
},
  "geometry": {"coordinates":[106.51300000000001,26.114],"type":"Point"}
}