{
  "type": "Feature",
  "properties": {
    "gn:admin1_code":"14.0",
    "gn:asciiname":"Shamaicun",
    "gn:country_code":"CN",
    "gn:dem":3217,
    "gn:feature_class":"P",
    "gn:feature_code":"PPL",
    "gn:name":"Shamaicun",
    "gn:population":0,
    "gn:timezone":"Asia/Urumqi",
    "iso:country":"CN",
    "name:zho_x_preferred":[
        "\u6c99\u9ea6\u6751"
    ],
    "wof:name":"Shamaicun",
    "wof:placetype":"locality"
},
  "geometry": {"coordinates":[97.55809000000001,29.46327],"type":"Point"}
}