{
  "type": "Feature",
  "properties": {
    "gn:admin1_code":"30",
    "gn:asciiname":"Gonghou",
    "gn:country_code":"CN",
    "gn:dem":431,
    "gn:feature_class":"P",
    "gn:feature_code":"PPL",
    "gn:name":"Gonghou",
    "gn:population":0,
    "gn:timezone":"Asia/Shanghai",
    "iso:country":"CN",
    "name:zho_x_preferred":[
        "\u5bab\u540e"
    ],
    "wof:name":"Gonghou",
    "wof:placetype":"locality"
},
  "geometry": {"coordinates":[116.69208,23.95451],"type":"Point"}
}