{
  "type": "Feature",
  "properties": {
    "gn:admin1_code":"07",
    "gn:asciiname":"Cheyang",
    "gn:country_code":"CN",
    "gn:dem":22,
    "gn:feature_class":"P",
    "gn:feature_code":"PPL",
    "gn:name":"Cheyang",
    "gn:population":0,
    "gn:timezone":"Asia/Shanghai",
    "iso:country":"CN",
    "name:zho_x_preferred":[
        "\u8f66\u6d0b"
    ],
    "wof:name":"Cheyang",
    "wof:placetype":"locality"
},
  "geometry": {"coordinates":[120.14754000000001,27.18984],"type":"Point"}
}