{
  "type": "Feature",
  "properties": {
    "gn:admin1_code":"9",
    "gn:asciiname":"Beiyue",
    "gn:country_code":"CN",
    "gn:dem":52,
    "gn:feature_class":"P",
    "gn:feature_code":"PPL",
    "gn:name":"Beiyue",
    "gn:population":0,
    "gn:timezone":"Asia/Shanghai",
    "iso:country":"CN",
    "name:zho_x_preferred":[
        "\u5317\u5cb3"
    ],
    "wof:name":"Beiyue",
    "wof:placetype":"locality"
},
  "geometry": {"coordinates":[115.11055,35.99054],"type":"Point"}
}