{
  "type": "Feature",
  "properties": {
    "gn:admin1_code":"18",
    "gn:asciiname":"Beiji",
    "gn:country_code":"CN",
    "gn:dem":977,
    "gn:feature_class":"P",
    "gn:feature_code":"PPL",
    "gn:name":"Beiji",
    "gn:population":0,
    "gn:timezone":"Asia/Shanghai",
    "iso:country":"CN",
    "name:zho_x_preferred":[
        "\u5317\u57fa"
    ],
    "wof:name":"Beiji",
    "wof:placetype":"locality"
},
  "geometry": {"coordinates":[107.44199999999999,29.0764],"type":"Point"}
}