{
  "type": "Feature",
  "properties": {
    "gn:admin1_code":"33.0",
    "gn:asciiname":"Minian",
    "gn:country_code":"CN",
    "gn:dem":1013,
    "gn:feature_class":"P",
    "gn:feature_code":"PPL",
    "gn:name":"Minian",
    "gn:population":0,
    "gn:timezone":"Asia/Shanghai",
    "iso:country":"CN",
    "name:zho_x_preferred":[
        "\u871c\u917f"
    ],
    "wof:name":"Minian",
    "wof:placetype":"locality"
},
  "geometry": {"coordinates":[108.22301000000002,30.21293],"type":"Point"}
}