{
  "type": "Feature",
  "properties": {
    "gn:admin1_code":"18.0",
    "gn:asciiname":"Houzi'ao",
    "gn:country_code":"CN",
    "gn:dem":975,
    "gn:feature_class":"P",
    "gn:feature_code":"PPL",
    "gn:name":"Houzi\u2019ao",
    "gn:population":0,
    "gn:timezone":"Asia/Shanghai",
    "iso:country":"CN",
    "name:und_x_variant":[
        "Houzi\u2019ao"
    ],
    "name:zho_x_preferred":[
        "\u7334\u5b50\u5773"
    ],
    "wof:name":"Houzi'ao",
    "wof:placetype":"locality"
},
  "geometry": {"coordinates":[108.051,26.6466],"type":"Point"}
}