{
  "type": "Feature",
  "properties": {
    "gn:admin1_code":"12.0",
    "gn:asciiname":"Dayanwan",
    "gn:country_code":"CN",
    "gn:dem":1351,
    "gn:feature_class":"P",
    "gn:feature_code":"PPL",
    "gn:name":"Dayanwan",
    "gn:population":0,
    "gn:timezone":"Asia/Shanghai",
    "iso:country":"CN",
    "name:zho_x_preferred":[
        "\u5927\u5ca9\u6e7e"
    ],
    "wof:name":"Dayanwan",
    "wof:placetype":"locality"
},
  "geometry": {"coordinates":[108.61753,30.31014],"type":"Point"}
}