{
  "type": "Feature",
  "properties": {
    "gn:admin1_code":"18",
    "gn:asciiname":"Gaoshikan",
    "gn:country_code":"CN",
    "gn:dem":1331,
    "gn:feature_class":"P",
    "gn:feature_code":"PPL",
    "gn:name":"Gaoshikan",
    "gn:population":0,
    "gn:timezone":"Asia/Shanghai",
    "iso:country":"CN",
    "name:zho_x_preferred":[
        "\u9ad8\u77f3\u574e"
    ],
    "wof:name":"Gaoshikan",
    "wof:placetype":"locality"
},
  "geometry": {"coordinates":[106.28100000000001,27.0705],"type":"Point"}
}