{
  "type": "Feature",
  "properties": {
    "gn:admin1_code":"19.0",
    "gn:asciiname":"Luodaotun",
    "gn:country_code":"CN",
    "gn:dem":6,
    "gn:feature_class":"P",
    "gn:feature_code":"PPL",
    "gn:name":"Luodaotun",
    "gn:population":0,
    "gn:timezone":"Asia/Shanghai",
    "iso:country":"CN",
    "name:zho_x_preferred":[
        "\u7f57\u5c9b\u5c6f"
    ],
    "wof:name":"Luodaotun",
    "wof:placetype":"locality"
},
  "geometry": {"coordinates":[121.274,39.4257],"type":"Point"}
}