{
  "type": "Feature",
  "properties": {
    "gn:admin1_code":"30.0",
    "gn:asciiname":"Shanjiacun",
    "gn:country_code":"CN",
    "gn:dem":11,
    "gn:feature_class":"P",
    "gn:feature_code":"PPL",
    "gn:name":"Shanjiacun",
    "gn:population":0,
    "gn:timezone":"Asia/Shanghai",
    "iso:country":"CN",
    "name:zho_x_preferred":[
        "\u5c71\u5bb6\u6751"
    ],
    "wof:name":"Shanjiacun",
    "wof:placetype":"locality"
},
  "geometry": {"coordinates":[116.26173,23.28506],"type":"Point"}
}