{
  "type": "Feature",
  "properties": {
    "gn:admin1_code":"15.0",
    "gn:asciiname":"Xipo Majia",
    "gn:country_code":"CN",
    "gn:dem":1466,
    "gn:feature_class":"P",
    "gn:feature_code":"PPL",
    "gn:name":"Xipo Majia",
    "gn:population":0,
    "gn:timezone":"Asia/Shanghai",
    "iso:country":"CN",
    "name:zho_x_preferred":[
        "\u897f\u5761\u9a6c\u5bb6"
    ],
    "wof:name":"Xipo Majia",
    "wof:placetype":"locality"
},
  "geometry": {"coordinates":[104.745,36.4216],"type":"Point"}
}