{
  "type": "Feature",
  "properties": {
    "gn:admin1_code":"30.0",
    "gn:asciiname":"Tiantouhecun",
    "gn:country_code":"CN",
    "gn:dem":12,
    "gn:feature_class":"P",
    "gn:feature_code":"PPL",
    "gn:name":"Tiantouhecun",
    "gn:population":0,
    "gn:timezone":"Asia/Shanghai",
    "iso:country":"CN",
    "name:zho_x_preferred":[
        "\u7530\u5934\u4f55\u6751"
    ],
    "wof:name":"Tiantouhecun",
    "wof:placetype":"locality"
},
  "geometry": {"coordinates":[116.62871,23.61144],"type":"Point"}
}