{
  "type": "Feature",
  "properties": {
    "gn:admin1_code":"3.0",
    "gn:asciiname":"Fanshen",
    "gn:country_code":"CN",
    "gn:dem":33,
    "gn:feature_class":"P",
    "gn:feature_code":"PPL",
    "gn:name":"Fanshen",
    "gn:population":0,
    "gn:timezone":"Asia/Shanghai",
    "iso:country":"CN",
    "name:und_x_variant":[
        "\u7ffb\u8eab"
    ],
    "wof:name":"Fanshen",
    "wof:placetype":"locality"
},
  "geometry": {"coordinates":[115.97659,29.38227],"type":"Point"}
}