{
  "type": "Feature",
  "properties": {
    "gn:admin1_code":"12.0",
    "gn:asciiname":"Xiliuxi",
    "gn:country_code":"CN",
    "gn:dem":852,
    "gn:feature_class":"P",
    "gn:feature_code":"PPL",
    "gn:name":"Xiliuxi",
    "gn:population":0,
    "gn:timezone":"Asia/Shanghai",
    "iso:country":"CN",
    "name:zho_x_preferred":[
        "Xiliuxi"
    ],
    "name:zho_x_variant":[
        "\u897f\u6d41\u6eaa"
    ],
    "wof:name":"Xiliuxi",
    "wof:placetype":"locality"
},
  "geometry": {"coordinates":[110.99686,30.10172],"type":"Point"}
}