{
  "type": "Feature",
  "properties": {
    "gn:admin1_code":"9.0",
    "gn:asciiname":"Mowangzhuang",
    "gn:country_code":"CN",
    "gn:dem":40,
    "gn:feature_class":"P",
    "gn:feature_code":"PPL",
    "gn:name":"Mowangzhuang",
    "gn:population":0,
    "gn:timezone":"Asia/Shanghai",
    "iso:country":"CN",
    "name:zho_x_preferred":[
        "\u78e8\u738b\u5e84"
    ],
    "wof:name":"Mowangzhuang",
    "wof:placetype":"locality"
},
  "geometry": {"coordinates":[115.54770000000001,33.64344000000001],"type":"Point"}
}