{
  "type": "Feature",
  "properties": {
    "gn:admin1_code":"5.0",
    "gn:asciiname":"Haoli",
    "gn:country_code":"CN",
    "gn:dem":175,
    "gn:feature_class":"P",
    "gn:feature_code":"PPL",
    "gn:name":"Haoli",
    "gn:population":0,
    "gn:timezone":"Asia/Shanghai",
    "iso:country":"CN",
    "name:zho_x_preferred":[
        "\u58d5\u91cc"
    ],
    "wof:name":"Haoli",
    "wof:placetype":"locality"
},
  "geometry": {"coordinates":[124.74051,43.7677],"type":"Point"}
}