{
  "type": "Feature",
  "properties": {
    "gn:admin1_code":"16.0",
    "gn:asciiname":"Xiaoshan Xincun",
    "gn:country_code":"CN",
    "gn:dem":86,
    "gn:feature_class":"P",
    "gn:feature_code":"PPL",
    "gn:name":"Xiaoshan Xincun",
    "gn:population":0,
    "gn:timezone":"Asia/Shanghai",
    "iso:country":"CN",
    "name:zho_x_preferred":[
        "\u5c0f\u5c71\u65b0\u6751"
    ],
    "wof:name":"Xiaoshan Xincun",
    "wof:placetype":"locality"
},
  "geometry": {"coordinates":[109.274,23.8573],"type":"Point"}
}