{
  "type": "Feature",
  "properties": {
    "gn:admin1_code":"11",
    "gn:asciiname":"Jintianwan",
    "gn:country_code":"CN",
    "gn:dem":472,
    "gn:feature_class":"P",
    "gn:feature_code":"PPL",
    "gn:name":"Jintianwan",
    "gn:population":0,
    "gn:timezone":"Asia/Shanghai",
    "iso:country":"CN",
    "name:zho_x_preferred":[
        "\u7981\u7530\u6e7e"
    ],
    "wof:name":"Jintianwan",
    "wof:placetype":"locality"
},
  "geometry": {"coordinates":[111.45274999999999,27.91174],"type":"Point"}
}