{
  "type": "Feature",
  "properties": {
    "gn:admin1_code":"18.0",
    "gn:asciiname":"Jiashao",
    "gn:country_code":"CN",
    "gn:dem":668,
    "gn:feature_class":"P",
    "gn:feature_code":"PPL",
    "gn:name":"Jiashao",
    "gn:population":0,
    "gn:timezone":"Asia/Shanghai",
    "iso:country":"CN",
    "name:zho_x_preferred":[
        "\u7532\u5c11"
    ],
    "wof:name":"Jiashao",
    "wof:placetype":"locality"
},
  "geometry": {"coordinates":[108.005,25.6618],"type":"Point"}
}