{
  "type": "Feature",
  "properties": {
    "gn:admin1_code":"12.0",
    "gn:asciiname":"Shuangmiaowan",
    "gn:country_code":"CN",
    "gn:dem":715,
    "gn:feature_class":"P",
    "gn:feature_code":"PPL",
    "gn:name":"Shuangmiaowan",
    "gn:population":0,
    "gn:timezone":"Asia/Shanghai",
    "iso:country":"CN",
    "name:zho_x_preferred":[
        "\u53cc\u5e99\u6e7e"
    ],
    "wof:name":"Shuangmiaowan",
    "wof:placetype":"locality"
},
  "geometry": {"coordinates":[110.87642,32.0981],"type":"Point"}
}