{
  "type": "Feature",
  "properties": {
    "gn:admin1_code":"15.0",
    "gn:asciiname":"Baidian",
    "gn:country_code":"CN",
    "gn:dem":1179,
    "gn:feature_class":"P",
    "gn:feature_code":"PPL",
    "gn:name":"Baidian",
    "gn:population":0,
    "gn:timezone":"Asia/Shanghai",
    "iso:country":"CN",
    "name:zho_x_preferred":[
        "\u767d\u5e97"
    ],
    "wof:name":"Baidian",
    "wof:placetype":"locality"
},
  "geometry": {"coordinates":[107.857,35.3143],"type":"Point"}
}