{
  "type": "Feature",
  "properties": {
    "gn:admin1_code":"9.0",
    "gn:asciiname":"Huangmogou",
    "gn:country_code":"CN",
    "gn:dem":1016,
    "gn:feature_class":"P",
    "gn:feature_code":"PPL",
    "gn:name":"Huangmogou",
    "gn:population":0,
    "gn:timezone":"Asia/Shanghai",
    "iso:country":"CN",
    "name:zho_x_preferred":[
        "\u6643\u78e8\u6c9f"
    ],
    "wof:name":"Huangmogou",
    "wof:placetype":"locality"
},
  "geometry": {"coordinates":[111.95721,33.47219],"type":"Point"}
}