{
  "type": "Feature",
  "properties": {
    "gn:admin1_code":"1.0",
    "gn:asciiname":"Liuxingcun",
    "gn:country_code":"CN",
    "gn:dem":63,
    "gn:feature_class":"P",
    "gn:feature_code":"PPL",
    "gn:name":"Liuxingcun",
    "gn:population":0,
    "gn:timezone":"Asia/Shanghai",
    "iso:country":"CN",
    "name:zho_x_preferred":[
        "\u5218\u5174\u6751"
    ],
    "wof:name":"Liuxingcun",
    "wof:placetype":"locality"
},
  "geometry": {"coordinates":[117.39648,32.36493],"type":"Point"}
}