{
  "type": "Feature",
  "properties": {
    "gn:admin1_code":"1.0",
    "gn:asciiname":"Tiankoucun",
    "gn:country_code":"CN",
    "gn:dem":29,
    "gn:feature_class":"P",
    "gn:feature_code":"PPL",
    "gn:name":"Tiankoucun",
    "gn:population":0,
    "gn:timezone":"Asia/Shanghai",
    "iso:country":"CN",
    "name:zho_x_preferred":[
        "\u7530\u53e3\u6751"
    ],
    "wof:name":"Tiankoucun",
    "wof:placetype":"locality"
},
  "geometry": {"coordinates":[117.44611,33.93372],"type":"Point"}
}