{
  "type": "Feature",
  "properties": {
    "gn:admin1_code":"10",
    "gn:asciiname":"Youzhou",
    "gn:country_code":"CN",
    "gn:dem":416,
    "gn:feature_class":"P",
    "gn:feature_code":"PPL",
    "gn:name":"Youzhou",
    "gn:population":0,
    "gn:timezone":"Asia/Shanghai",
    "iso:country":"CN",
    "name:und_x_variant":[
        "Yu-chou",
        "Youzhou",
        "\u5e7d\u5dde"
    ],
    "wof:name":"Youzhou",
    "wof:placetype":"locality"
},
  "geometry": {"coordinates":[115.68087,40.15511],"type":"Point"}
}