{
  "type": "Feature",
  "properties": {
    "gn:admin1_code":"3",
    "gn:asciiname":"Xiakouba",
    "gn:country_code":"CN",
    "gn:dem":149,
    "gn:feature_class":"P",
    "gn:feature_code":"PPL",
    "gn:name":"Xiakouba",
    "gn:population":0,
    "gn:timezone":"Asia/Shanghai",
    "iso:country":"CN",
    "name:zho_x_preferred":[
        "\u4e0b\u53e3\u575d"
    ],
    "wof:name":"Xiakouba",
    "wof:placetype":"locality"
},
  "geometry": {"coordinates":[114.682,25.7143],"type":"Point"}
}