{
  "type": "Feature",
  "properties": {
    "gn:admin1_code":"32.0",
    "gn:asciiname":"Shiqidaoguai",
    "gn:country_code":"CN",
    "gn:dem":1769,
    "gn:feature_class":"P",
    "gn:feature_code":"PPL",
    "gn:name":"Shiqidaoguai",
    "gn:population":0,
    "gn:timezone":"Asia/Shanghai",
    "iso:country":"CN",
    "name:zho_x_preferred":[
        "\u5341\u4e03\u9053\u62d0"
    ],
    "wof:name":"Shiqidaoguai",
    "wof:placetype":"locality"
},
  "geometry": {"coordinates":[102.12766999999999,30.35142],"type":"Point"}
}