{
  "type": "Feature",
  "properties": {
    "gn:admin1_code":"2.0",
    "gn:asciiname":"Gaobaitang",
    "gn:country_code":"CN",
    "gn:dem":240,
    "gn:feature_class":"P",
    "gn:feature_code":"PPL",
    "gn:name":"Gaobaitang",
    "gn:population":0,
    "gn:timezone":"Asia/Shanghai",
    "iso:country":"CN",
    "name:und_x_variant":[
        "\u9ad8\u767d\u5858"
    ],
    "wof:name":"Gaobaitang",
    "wof:placetype":"locality"
},
  "geometry": {"coordinates":[119.55365999999999,30.18159],"type":"Point"}
}