{
  "type": "Feature",
  "properties": {
    "gn:admin1_code":"25.0",
    "gn:asciiname":"Yinji",
    "gn:cc2":"CN",
    "gn:country_code":"CN",
    "gn:dem":32,
    "gn:feature_class":"P",
    "gn:feature_code":"PPL",
    "gn:name":"Yinji",
    "gn:population":0,
    "gn:timezone":"Asia/Shanghai",
    "iso:country":"CN",
    "name:und_x_variant":[
        "I-chi",
        "Yinji"
    ],
    "wof:name":"Yinji",
    "wof:placetype":"locality"
},
  "geometry": {"coordinates":[116.31889,36.90111],"type":"Point"}
}