{
  "type": "Feature",
  "properties": {
    "gn:admin1_code":"15.0",
    "gn:asciiname":"Shengjiawan",
    "gn:country_code":"CN",
    "gn:dem":1937,
    "gn:feature_class":"P",
    "gn:feature_code":"PPL",
    "gn:name":"Shengjiawan",
    "gn:population":0,
    "gn:timezone":"Asia/Shanghai",
    "iso:country":"CN",
    "name:zho_x_preferred":[
        "\u751f\u5bb6\u6e7e"
    ],
    "wof:name":"Shengjiawan",
    "wof:placetype":"locality"
},
  "geometry": {"coordinates":[106.622,35.4077],"type":"Point"}
}