{
  "type": "Feature",
  "properties": {
    "gn:admin1_code":"2",
    "gn:asciiname":"Jiadi",
    "gn:country_code":"CN",
    "gn:dem":528,
    "gn:feature_class":"P",
    "gn:feature_code":"PPLA4",
    "gn:name":"Jiadi",
    "gn:population":0,
    "gn:timezone":"Asia/Shanghai",
    "iso:country":"CN",
    "name:und_x_variant":[
        "\u5bb6\u5730",
        "Jiadi",
        "Jiadi Xiang"
    ],
    "wof:name":"Jiadi",
    "wof:placetype":"locality"
},
  "geometry": {"coordinates":[119.52172,27.71839000000001],"type":"Point"}
}