{
  "type": "Feature",
  "properties": {
    "gn:admin1_code":"32.0",
    "gn:asciiname":"Manzhen",
    "gn:country_code":"CN",
    "gn:dem":3611,
    "gn:feature_class":"P",
    "gn:feature_code":"PPL",
    "gn:name":"Manzhen",
    "gn:population":0,
    "gn:timezone":"Asia/Shanghai",
    "iso:country":"CN",
    "name:zho_x_preferred":[
        "\u6ee1\u771f"
    ],
    "wof:name":"Manzhen",
    "wof:placetype":"locality"
},
  "geometry": {"coordinates":[97.4393,32.7071],"type":"Point"}
}