{
  "type": "Feature",
  "properties": {
    "gn:admin1_code":"29.0",
    "gn:asciiname":"Heiqing",
    "gn:country_code":"CN",
    "gn:dem":1955,
    "gn:feature_class":"P",
    "gn:feature_code":"PPL",
    "gn:name":"Heiqing",
    "gn:population":0,
    "gn:timezone":"Asia/Shanghai",
    "iso:country":"CN",
    "name:zho_x_preferred":[
        "\u9ed1\u7b90"
    ],
    "wof:name":"Heiqing",
    "wof:placetype":"locality"
},
  "geometry": {"coordinates":[103.458,25.6024],"type":"Point"}
}