{
  "type": "Feature",
  "properties": {
    "gn:admin1_code":"4.0",
    "gn:asciiname":"Xupingloucun",
    "gn:country_code":"CN",
    "gn:dem":45,
    "gn:feature_class":"P",
    "gn:feature_code":"PPL",
    "gn:name":"Xupingloucun",
    "gn:population":0,
    "gn:timezone":"Asia/Shanghai",
    "iso:country":"CN",
    "name:zho_x_preferred":[
        "\u5f90\u5e73\u697c\u6751"
    ],
    "wof:name":"Xupingloucun",
    "wof:placetype":"locality"
},
  "geometry": {"coordinates":[116.83069,34.4613],"type":"Point"}
}