{
  "type": "Feature",
  "properties": {
    "gn:admin1_code":"8.0",
    "gn:asciiname":"Changfengcun",
    "gn:country_code":"CN",
    "gn:dem":355,
    "gn:feature_class":"P",
    "gn:feature_code":"PPL",
    "gn:name":"Changfengcun",
    "gn:population":0,
    "gn:timezone":"Asia/Shanghai",
    "iso:country":"CN",
    "name:zho_x_preferred":[
        "\u957f\u4e30\u6751"
    ],
    "wof:name":"Changfengcun",
    "wof:placetype":"locality"
},
  "geometry": {"coordinates":[130.27638000000002,45.17215],"type":"Point"}
}