{
  "type": "Feature",
  "properties": {
    "gn:admin1_code":"32.0",
    "gn:asciiname":"Huangmaochong",
    "gn:country_code":"CN",
    "gn:dem":365,
    "gn:feature_class":"P",
    "gn:feature_code":"PPL",
    "gn:name":"Huangmaochong",
    "gn:population":0,
    "gn:timezone":"Asia/Shanghai",
    "iso:country":"CN",
    "name:zho_x_preferred":[
        "\u9ec4\u6bdb\u51b2"
    ],
    "wof:name":"Huangmaochong",
    "wof:placetype":"locality"
},
  "geometry": {"coordinates":[104.60299999999999,28.9276],"type":"Point"}
}