{
  "type": "Feature",
  "properties": {
    "gn:admin1_code":"7.0",
    "gn:asciiname":"Chencuocun",
    "gn:country_code":"CN",
    "gn:dem":223,
    "gn:feature_class":"P",
    "gn:feature_code":"PPL",
    "gn:name":"Chencuocun",
    "gn:population":0,
    "gn:timezone":"Asia/Shanghai",
    "iso:country":"CN",
    "name:zho_x_preferred":[
        "\u9648\u539d\u6751"
    ],
    "wof:name":"Chencuocun",
    "wof:placetype":"locality"
},
  "geometry": {"coordinates":[117.38226,26.58374],"type":"Point"}
}