{
  "type": "Feature",
  "properties": {
    "gn:admin1_code":"10",
    "gn:asciiname":"Sanchakou",
    "gn:country_code":"CN",
    "gn:dem":693,
    "gn:feature_class":"P",
    "gn:feature_code":"PPL",
    "gn:name":"Sanchakou",
    "gn:population":0,
    "gn:timezone":"Asia/Shanghai",
    "iso:country":"CN",
    "name:zho_x_preferred":[
        "\u4e09\u5c94\u53e3"
    ],
    "wof:name":"Sanchakou",
    "wof:placetype":"locality"
},
  "geometry": {"coordinates":[117.08459000000001,41.15916],"type":"Point"}
}