{
  "type": "Feature",
  "properties": {
    "gn:admin1_code":"30",
    "gn:asciiname":"Shikengwei",
    "gn:country_code":"CN",
    "gn:dem":209,
    "gn:feature_class":"P",
    "gn:feature_code":"PPL",
    "gn:name":"Shikengwei",
    "gn:population":0,
    "gn:timezone":"Asia/Shanghai",
    "iso:country":"CN",
    "name:zho_x_preferred":[
        "\u77f3\u5751\u5729"
    ],
    "wof:name":"Shikengwei",
    "wof:placetype":"locality"
},
  "geometry": {"coordinates":[115.5624,24.24341],"type":"Point"}
}