{
  "type": "Feature",
  "properties": {
    "gn:admin1_code":"15.0",
    "gn:asciiname":"Dazhangzi",
    "gn:country_code":"CN",
    "gn:dem":1645,
    "gn:feature_class":"P",
    "gn:feature_code":"PPL",
    "gn:name":"Dazhangzi",
    "gn:population":0,
    "gn:timezone":"Asia/Shanghai",
    "iso:country":"CN",
    "name:und_x_variant":[
        "\u5927\u638c\u5b50"
    ],
    "wof:name":"Dazhangzi",
    "wof:placetype":"locality"
},
  "geometry": {"coordinates":[106.97261,36.8162],"type":"Point"}
}