{
  "type": "Feature",
  "properties": {
    "gn:admin1_code":"19.0",
    "gn:asciiname":"Peijia Wobu",
    "gn:country_code":"CN",
    "gn:dem":93,
    "gn:feature_class":"P",
    "gn:feature_code":"PPL",
    "gn:name":"Peijia Wobu",
    "gn:population":0,
    "gn:timezone":"Asia/Shanghai",
    "iso:country":"CN",
    "name:zho_x_preferred":[
        "\u88f4\u5bb6\u7a9d\u5821"
    ],
    "wof:name":"Peijia Wobu",
    "wof:placetype":"locality"
},
  "geometry": {"coordinates":[123.268,42.8048],"type":"Point"}
}