{
  "type": "Feature",
  "properties": {
    "gn:admin1_code":"29.0",
    "gn:asciiname":"Lengshuigou",
    "gn:country_code":"CN",
    "gn:dem":2027,
    "gn:feature_class":"P",
    "gn:feature_code":"PPL",
    "gn:name":"Lengshuigou",
    "gn:population":0,
    "gn:timezone":"Asia/Shanghai",
    "iso:country":"CN",
    "name:zho_x_preferred":[
        "\u51b7\u6c34\u6c9f"
    ],
    "wof:name":"Lengshuigou",
    "wof:placetype":"locality"
},
  "geometry": {"coordinates":[103.675,24.8367],"type":"Point"}
}