{
  "type": "Feature",
  "properties": {
    "gn:admin1_code":"4.0",
    "gn:asciiname":"Jianghan",
    "gn:country_code":"CN",
    "gn:dem":21,
    "gn:feature_class":"P",
    "gn:feature_code":"PPL",
    "gn:name":"Jianghan",
    "gn:population":0,
    "gn:timezone":"Asia/Shanghai",
    "iso:country":"CN",
    "name:zho_x_preferred":[
        "\u6c5f\u97e9"
    ],
    "name:zho_x_variant":[
        "\u6c5f\u6c49"
    ],
    "wof:name":"Jianghan",
    "wof:placetype":"locality"
},
  "geometry": {"coordinates":[118.208,33.6957],"type":"Point"}
}