{
  "type": "Feature",
  "properties": {
    "gn:admin1_code":"04",
    "gn:asciiname":"Qiaolin",
    "gn:country_code":"CN",
    "gn:dem":21,
    "gn:feature_class":"P",
    "gn:feature_code":"PPLA4",
    "gn:name":"Qiaolin",
    "gn:population":0,
    "gn:timezone":"Asia/Shanghai",
    "iso:country":"CN",
    "name:und_x_variant":[
        "Ch\u2019iao-lin",
        "Ch\u2019iao-lin-chen",
        "Qiaolin",
        "Qiaolin Zhen"
    ],
    "name:zho_x_preferred":[
        "\u6865\u6797"
    ],
    "wof:name":"Qiaolin",
    "wof:placetype":"locality"
},
  "geometry": {"coordinates":[118.5265,31.94673],"type":"Point"}
}