{
  "type": "Feature",
  "properties": {
    "gn:admin1_code":"9",
    "gn:asciiname":"Niemiao",
    "gn:country_code":"CN",
    "gn:dem":39,
    "gn:feature_class":"P",
    "gn:feature_code":"PPL",
    "gn:name":"Niemiao",
    "gn:population":0,
    "gn:timezone":"Asia/Shanghai",
    "iso:country":"CN",
    "name:zho_x_preferred":[
        "\u8042\u5e99"
    ],
    "wof:name":"Niemiao",
    "wof:placetype":"locality"
},
  "geometry": {"coordinates":[116.398,34.1079],"type":"Point"}
}