{
  "type": "Feature",
  "properties": {
    "gn:admin1_code":"16",
    "gn:asciiname":"Honghuaqi",
    "gn:country_code":"CN",
    "gn:dem":837,
    "gn:feature_class":"P",
    "gn:feature_code":"PPL",
    "gn:name":"Honghuaqi",
    "gn:population":0,
    "gn:timezone":"Asia/Shanghai",
    "iso:country":"CN",
    "name:zho_x_preferred":[
        "\u7ea2\u82b1\u5c90"
    ],
    "wof:name":"Honghuaqi",
    "wof:placetype":"locality"
},
  "geometry": {"coordinates":[110.77800000000001,25.326],"type":"Point"}
}