{
  "type": "Feature",
  "properties": {
    "gn:admin1_code":"1.0",
    "gn:asciiname":"Dongfengcun",
    "gn:country_code":"CN",
    "gn:dem":37,
    "gn:feature_class":"P",
    "gn:feature_code":"PPL",
    "gn:name":"Dongfengcun",
    "gn:population":0,
    "gn:timezone":"Asia/Shanghai",
    "iso:country":"CN",
    "name:zho_x_preferred":[
        "\u4e1c\u98ce\u6751"
    ],
    "wof:name":"Dongfengcun",
    "wof:placetype":"locality"
},
  "geometry": {"coordinates":[116.47238,31.82979000000001],"type":"Point"}
}