{
  "type": "Feature",
  "properties": {
    "gn:admin1_code":"18.0",
    "gn:asciiname":"Gaobatian",
    "gn:country_code":"CN",
    "gn:dem":574,
    "gn:feature_class":"P",
    "gn:feature_code":"PPL",
    "gn:name":"Gaobatian",
    "gn:population":0,
    "gn:timezone":"Asia/Shanghai",
    "iso:country":"CN",
    "name:zho_x_preferred":[
        "\u9ad8\u575d\u7530"
    ],
    "wof:name":"Gaobatian",
    "wof:placetype":"locality"
},
  "geometry": {"coordinates":[109.06,27.6872],"type":"Point"}
}