{
  "type": "Feature",
  "properties": {
    "gn:admin1_code":"32.0",
    "gn:asciiname":"Laotangfang",
    "gn:country_code":"CN",
    "gn:dem":346,
    "gn:feature_class":"P",
    "gn:feature_code":"PPL",
    "gn:name":"Laotangfang",
    "gn:population":0,
    "gn:timezone":"Asia/Shanghai",
    "iso:country":"CN",
    "name:zho_x_preferred":[
        "\u8001\u7cd6\u574a"
    ],
    "wof:name":"Laotangfang",
    "wof:placetype":"locality"
},
  "geometry": {"coordinates":[104.985,29.8481],"type":"Point"}
}