{
  "type": "Feature",
  "properties": {
    "gn:admin1_code":"3.0",
    "gn:asciiname":"Shegongshu",
    "gn:country_code":"CN",
    "gn:dem":80,
    "gn:feature_class":"P",
    "gn:feature_code":"PPL",
    "gn:name":"Shegongshu",
    "gn:population":0,
    "gn:timezone":"Asia/Shanghai",
    "iso:country":"CN",
    "name:und_x_variant":[
        "\u793e\u516c\u6811"
    ],
    "wof:name":"Shegongshu",
    "wof:placetype":"locality"
},
  "geometry": {"coordinates":[116.81922,29.89993],"type":"Point"}
}