{
  "type": "Feature",
  "properties": {
    "gn:admin1_code":"29.0",
    "gn:asciiname":"Galu",
    "gn:country_code":"CN",
    "gn:dem":1947,
    "gn:feature_class":"P",
    "gn:feature_code":"PPL",
    "gn:name":"Galu",
    "gn:population":0,
    "gn:timezone":"Asia/Shanghai",
    "iso:country":"CN",
    "name:zho_x_preferred":[
        "\u560e\u565c"
    ],
    "wof:name":"Galu",
    "wof:placetype":"locality"
},
  "geometry": {"coordinates":[104.16800000000001,27.3357],"type":"Point"}
}