{
  "type": "Feature",
  "properties": {
    "gn:admin1_code":"25",
    "gn:asciiname":"Huibei",
    "gn:country_code":"CN",
    "gn:dem":67,
    "gn:feature_class":"P",
    "gn:feature_code":"PPL",
    "gn:name":"Huibei",
    "gn:population":0,
    "gn:timezone":"Asia/Shanghai",
    "iso:country":"CN",
    "name:zho_x_preferred":[
        "\u6c47\u5317"
    ],
    "wof:name":"Huibei",
    "wof:placetype":"locality"
},
  "geometry": {"coordinates":[116.55200000000001,36.1879],"type":"Point"}
}