{
  "type": "Feature",
  "properties": {
    "gn:admin1_code":"31.0",
    "gn:asciiname":"Shiyakou",
    "gn:country_code":"CN",
    "gn:dem":558,
    "gn:feature_class":"P",
    "gn:feature_code":"PPL",
    "gn:name":"Shiyakou",
    "gn:population":0,
    "gn:timezone":"Asia/Shanghai",
    "iso:country":"CN",
    "name:und_x_variant":[
        "\u4ec0\u7259\u53e3"
    ],
    "wof:name":"Shiyakou",
    "wof:placetype":"locality"
},
  "geometry": {"coordinates":[109.64521000000001,18.8984],"type":"Point"}
}