{
  "type": "Feature",
  "properties": {
    "gn:admin1_code":"11.0",
    "gn:asciiname":"Huozhuan Wuchang",
    "gn:country_code":"CN",
    "gn:dem":298,
    "gn:feature_class":"P",
    "gn:feature_code":"PPL",
    "gn:name":"Huozhuan Wuchang",
    "gn:population":0,
    "gn:timezone":"Asia/Shanghai",
    "iso:country":"CN",
    "name:zho_x_preferred":[
        "\u706b\u7816\u5c4b\u573a"
    ],
    "wof:name":"Huozhuan Wuchang",
    "wof:placetype":"locality"
},
  "geometry": {"coordinates":[110.74542,27.00972],"type":"Point"}
}