{
  "type": "Feature",
  "properties": {
    "gn:admin1_code":"18.0",
    "gn:asciiname":"Xiaokaizhou",
    "gn:country_code":"CN",
    "gn:dem":1006,
    "gn:feature_class":"P",
    "gn:feature_code":"PPL",
    "gn:name":"Xiaokaizhou",
    "gn:population":0,
    "gn:timezone":"Asia/Shanghai",
    "iso:country":"CN",
    "name:zho_x_preferred":[
        "\u5c0f\u5f00\u6d32"
    ],
    "wof:name":"Xiaokaizhou",
    "wof:placetype":"locality"
},
  "geometry": {"coordinates":[107.285,27.2287],"type":"Point"}
}