{
  "type": "Feature",
  "properties": {
    "gn:admin1_code":"29.0",
    "gn:asciiname":"Zengming",
    "gn:country_code":"CN",
    "gn:dem":1958,
    "gn:feature_class":"P",
    "gn:feature_code":"PPL",
    "gn:name":"Zengming",
    "gn:population":0,
    "gn:timezone":"Asia/Shanghai",
    "iso:country":"CN",
    "name:zho_x_preferred":[
        "\u589e\u660e"
    ],
    "wof:name":"Zengming",
    "wof:placetype":"locality"
},
  "geometry": {"coordinates":[100.425,26.8117],"type":"Point"}
}