{
  "type": "Feature",
  "properties": {
    "gn:admin1_code":"11",
    "gn:asciiname":"Chashi",
    "gn:country_code":"CN",
    "gn:dem":86,
    "gn:feature_class":"P",
    "gn:feature_code":"PPL",
    "gn:name":"Chashi",
    "gn:population":0,
    "gn:timezone":"Asia/Shanghai",
    "iso:country":"CN",
    "name:jpn_x_preferred":[
        "\u30c1\u30e3\u30b7"
    ],
    "wof:name":"Chashi",
    "wof:placetype":"locality"
},
  "geometry": {"coordinates":[112.75111,26.76639],"type":"Point"}
}