{
  "type": "Feature",
  "properties": {
    "gn:admin1_code":"12.0",
    "gn:asciiname":"Xingjiawan",
    "gn:country_code":"CN",
    "gn:dem":25,
    "gn:feature_class":"P",
    "gn:feature_code":"PPL",
    "gn:name":"Xingjiawan",
    "gn:population":0,
    "gn:timezone":"Asia/Shanghai",
    "iso:country":"CN",
    "name:und_x_variant":[
        "\u5211\u5bb6\u5846"
    ],
    "wof:name":"Xingjiawan",
    "wof:placetype":"locality"
},
  "geometry": {"coordinates":[114.94356000000001,30.41924],"type":"Point"}
}