{
  "type": "Feature",
  "properties": {
    "gn:admin1_code":"32.0",
    "gn:asciiname":"Dayangan",
    "gn:country_code":"CN",
    "gn:dem":1081,
    "gn:feature_class":"P",
    "gn:feature_code":"PPL",
    "gn:name":"Dayangan",
    "gn:population":0,
    "gn:timezone":"Asia/Shanghai",
    "iso:country":"CN",
    "name:zho_x_preferred":[
        "\u5927\u5ca9\u77f8"
    ],
    "wof:name":"Dayangan",
    "wof:placetype":"locality"
},
  "geometry": {"coordinates":[103.99751000000001,28.67757000000001],"type":"Point"}
}