{
  "type": "Feature",
  "properties": {
    "gn:admin1_code":"14.0",
    "gn:asciiname":"Bomu",
    "gn:country_code":"CN",
    "gn:dem":4705,
    "gn:feature_class":"P",
    "gn:feature_code":"PPL",
    "gn:name":"Bomu",
    "gn:population":0,
    "gn:timezone":"Asia/Urumqi",
    "iso:country":"CN",
    "name:ceb_x_preferred":[
        "Bomu"
    ],
    "name:fra_x_preferred":[
        "Bomu"
    ],
    "name:swe_x_preferred":[
        "Bomu"
    ],
    "name:zho_x_preferred":[
        "\u6ce2\u6728"
    ],
    "wof:name":"Bomu",
    "wof:placetype":"locality"
},
  "geometry": {"coordinates":[85.8492,28.8351],"type":"Point"}
}