{
  "type": "Feature",
  "properties": {
    "gn:admin1_code":"14.0",
    "gn:asciiname":"Bomu",
    "gn:country_code":"CN",
    "gn:dem":4705,
    "gn:feature_class":"P",
    "gn:feature_code":"PPL",
    "gn:name":"Bomu",
    "gn:population":0,
    "gn:timezone":"Asia/Urumqi",
    "iso:country":"CN",
    "name:ara_x_preferred":[
        "\u0628\u0648\u0645\u0648"
    ],
    "name:ben_x_preferred":[
        "\u09ac\u09cb\u09ae\u09c1"
    ],
    "name:ceb_x_preferred":[
        "Bomu"
    ],
    "name:ell_x_preferred":[
        "\u039c\u03c0\u03cc\u03bc\u03bf\u03c5"
    ],
    "name:fas_x_preferred":[
        "\u0628\u0648\u0645\u0648"
    ],
    "name:fra_x_preferred":[
        "Bomu"
    ],
    "name:heb_x_preferred":[
        "\u05d1\u05d5\u05de\u05d5"
    ],
    "name:ind_x_preferred":[
        "Bomu"
    ],
    "name:kor_x_preferred":[
        "\ubcf4\ubb34"
    ],
    "name:swe_x_preferred":[
        "Bomu"
    ],
    "name:tur_x_preferred":[
        "Bomu"
    ],
    "name:urd_x_preferred":[
        "\u0628\u0648\u0645\u0648"
    ],
    "name:zho_x_preferred":[
        "\u6ce2\u6728"
    ],
    "wof:name":"Bomu",
    "wof:placetype":"locality"
},
  "geometry": {"coordinates":[85.8492,28.8351],"type":"Point"}
}