{
  "type": "Feature",
  "properties": {
    "gn:admin1_code":"4.0",
    "gn:asciiname":"Kanjialing",
    "gn:country_code":"CN",
    "gn:dem":41,
    "gn:feature_class":"P",
    "gn:feature_code":"PPL",
    "gn:name":"Kanjialing",
    "gn:population":0,
    "gn:timezone":"Asia/Shanghai",
    "iso:country":"CN",
    "name:zho_x_preferred":[
        "\u961a\u5bb6\u5cad"
    ],
    "wof:name":"Kanjialing",
    "wof:placetype":"locality"
},
  "geometry": {"coordinates":[118.97799999999999,34.9644],"type":"Point"}
}