{
  "type": "Feature",
  "properties": {
    "gn:admin1_code":"32.0",
    "gn:asciiname":"Baohua Wuji",
    "gn:country_code":"CN",
    "gn:dem":413,
    "gn:feature_class":"P",
    "gn:feature_code":"PPL",
    "gn:name":"Baohua Wuji",
    "gn:population":0,
    "gn:timezone":"Asia/Shanghai",
    "iso:country":"CN",
    "name:zho_x_preferred":[
        "\u7206\u82b1\u5c4b\u57fa"
    ],
    "wof:name":"Baohua Wuji",
    "wof:placetype":"locality"
},
  "geometry": {"coordinates":[104.76600000000001,29.9793],"type":"Point"}
}