{
  "type": "Feature",
  "properties": {
    "gn:admin1_code":"32.0",
    "gn:asciiname":"Guanji",
    "gn:country_code":"CN",
    "gn:dem":2659,
    "gn:feature_class":"P",
    "gn:feature_code":"PPL",
    "gn:name":"Guanji",
    "gn:population":0,
    "gn:timezone":"Asia/Shanghai",
    "iso:country":"CN",
    "name:zho_x_preferred":[
        "\u5173\u673a"
    ],
    "wof:name":"Guanji",
    "wof:placetype":"locality"
},
  "geometry": {"coordinates":[101.163,28.858],"type":"Point"}
}