{
  "type": "Feature",
  "properties": {
    "gn:admin1_code":"30.0",
    "gn:asciiname":"Wanzai",
    "gn:country_code":"CN",
    "gn:dem":74,
    "gn:feature_class":"P",
    "gn:feature_code":"PPL",
    "gn:name":"Wanzai",
    "gn:population":0,
    "gn:timezone":"Asia/Urumqi",
    "iso:country":"CN",
    "name:zho_x_preferred":[
        "\u6e7e\u4ed4"
    ],
    "wof:name":"Wanzai",
    "wof:placetype":"locality"
},
  "geometry": {"coordinates":[110.20659999999999,20.41405],"type":"Point"}
}