{
  "type": "Feature",
  "properties": {
    "gn:admin1_code":"10.0",
    "gn:asciiname":"Houyuhang",
    "gn:country_code":"CN",
    "gn:dem":14,
    "gn:feature_class":"P",
    "gn:feature_code":"PPL",
    "gn:name":"Houyuhang",
    "gn:population":0,
    "gn:timezone":"Asia/Shanghai",
    "iso:country":"CN",
    "name:zho_x_preferred":[
        "\u540e\u6986\u676d"
    ],
    "wof:name":"Houyuhang",
    "wof:placetype":"locality"
},
  "geometry": {"coordinates":[116.324,38.5142],"type":"Point"}
}