{
  "type": "Feature",
  "properties": {
    "gn:admin1_code":"9",
    "gn:asciiname":"Shuikengliu",
    "gn:country_code":"CN",
    "gn:dem":57,
    "gn:feature_class":"P",
    "gn:feature_code":"PPL",
    "gn:name":"Shuikengliu",
    "gn:population":0,
    "gn:timezone":"Asia/Shanghai",
    "iso:country":"CN",
    "name:zho_x_preferred":[
        "\u6c34\u5751\u5218"
    ],
    "wof:name":"Shuikengliu",
    "wof:placetype":"locality"
},
  "geometry": {"coordinates":[114.879,34.3064],"type":"Point"}
}