{
  "type": "Feature",
  "properties": {
    "gn:admin1_code":"15.0",
    "gn:asciiname":"Zhenquanzizhuang",
    "gn:country_code":"CN",
    "gn:dem":2272,
    "gn:feature_class":"P",
    "gn:feature_code":"PPL",
    "gn:name":"Zhenquanzizhuang",
    "gn:population":0,
    "gn:timezone":"Asia/Shanghai",
    "iso:country":"CN",
    "name:und_x_variant":[
        "\u73cd\u6cc9\u5b50\u5e84"
    ],
    "name:zho_x_preferred":[
        "\u73cd\u6cc9\u5b50\u5e84"
    ],
    "wof:name":"Zhenquanzizhuang",
    "wof:placetype":"locality"
},
  "geometry": {"coordinates":[104.58148,34.01521],"type":"Point"}
}