{
  "type": "Feature",
  "properties": {
    "gn:admin1_code":"29.0",
    "gn:asciiname":"Jiale",
    "gn:country_code":"CN",
    "gn:dem":1791,
    "gn:feature_class":"P",
    "gn:feature_code":"PPL",
    "gn:name":"Jiale",
    "gn:population":0,
    "gn:timezone":"Asia/Shanghai",
    "iso:country":"CN",
    "name:zho_x_preferred":[
        "\u5609\u4e50"
    ],
    "wof:name":"Jiale",
    "wof:placetype":"locality"
},
  "geometry": {"coordinates":[103.752,24.59800000000001],"type":"Point"}
}