{
  "type": "Feature",
  "properties": {
    "gn:admin1_code":"14.0",
    "gn:asciiname":"Lulingka",
    "gn:country_code":"CN",
    "gn:dem":4437,
    "gn:feature_class":"P",
    "gn:feature_code":"PPL",
    "gn:name":"Lulingka",
    "gn:population":0,
    "gn:timezone":"Asia/Urumqi",
    "iso:country":"CN",
    "name:zho_x_preferred":[
        "\u5362\u4ee4\u5361"
    ],
    "wof:name":"Lulingka",
    "wof:placetype":"locality"
},
  "geometry": {"coordinates":[94.22004,31.43312],"type":"Point"}
}