{
  "type": "Feature",
  "properties": {
    "gn:admin1_code":"12.0",
    "gn:asciiname":"Xinwuzhu",
    "gn:country_code":"CN",
    "gn:dem":70,
    "gn:feature_class":"P",
    "gn:feature_code":"PPL",
    "gn:name":"Xinwuzhu",
    "gn:population":0,
    "gn:timezone":"Asia/Shanghai",
    "iso:country":"CN",
    "name:zho_x_preferred":[
        "Xinwuzhu"
    ],
    "name:zho_x_variant":[
        "\u65b0\u5c4b\u6731"
    ],
    "wof:name":"Xinwuzhu",
    "wof:placetype":"locality"
},
  "geometry": {"coordinates":[114.47753,29.82509000000001],"type":"Point"}
}