{
  "type": "Feature",
  "properties": {
    "gn:admin1_code":"15.0",
    "gn:asciiname":"Liyaoxian",
    "gn:country_code":"CN",
    "gn:dem":1485,
    "gn:feature_class":"P",
    "gn:feature_code":"PPL",
    "gn:name":"Liyaoxian",
    "gn:population":0,
    "gn:timezone":"Asia/Shanghai",
    "iso:country":"CN",
    "name:und_x_variant":[
        "\u674e\u5d3e\u5c98"
    ],
    "wof:name":"Liyaoxian",
    "wof:placetype":"locality"
},
  "geometry": {"coordinates":[107.23248,36.34308],"type":"Point"}
}