{
  "type": "Feature",
  "properties": {
    "gn:admin1_code":"3.0",
    "gn:asciiname":"Shanggaoping",
    "gn:country_code":"CN",
    "gn:dem":368,
    "gn:feature_class":"P",
    "gn:feature_code":"PPL",
    "gn:name":"Shanggaoping",
    "gn:population":0,
    "gn:timezone":"Asia/Shanghai",
    "iso:country":"CN",
    "name:und_x_variant":[
        "\u4e0a\u9ad8\u576a"
    ],
    "wof:name":"Shanggaoping",
    "wof:placetype":"locality"
},
  "geometry": {"coordinates":[115.98909999999999,27.36116],"type":"Point"}
}