{
  "type": "Feature",
  "properties": {
    "gn:admin1_code":"15.0",
    "gn:asciiname":"Wenshu",
    "gn:country_code":"CN",
    "gn:dem":1585,
    "gn:feature_class":"P",
    "gn:feature_code":"PPLA4",
    "gn:name":"Wenshu",
    "gn:population":0,
    "gn:timezone":"Asia/Shanghai",
    "iso:country":"CN",
    "name:und_x_variant":[
        "Wenshu Zhen"
    ],
    "name:zho_x_preferred":[
        "\u6587\u6b8a"
    ],
    "name:zho_x_variant":[
        "\u6587\u6b8a\u9547"
    ],
    "wof:name":"Wenshu",
    "wof:placetype":"locality"
},
  "geometry": {"coordinates":[98.37221,39.69378],"type":"Point"}
}