{
  "type": "Feature",
  "properties": {
    "gn:admin1_code":"26.0",
    "gn:asciiname":"Anjiapo",
    "gn:country_code":"CN",
    "gn:dem":1361,
    "gn:feature_class":"P",
    "gn:feature_code":"PPL",
    "gn:name":"Anjiapo",
    "gn:population":0,
    "gn:timezone":"Asia/Shanghai",
    "iso:country":"CN",
    "name:und_x_variant":[
        "\u5b89\u5bb6\u5761"
    ],
    "wof:name":"Anjiapo",
    "wof:placetype":"locality"
},
  "geometry": {"coordinates":[106.35827999999999,32.77831],"type":"Point"}
}