{
  "type": "Feature",
  "properties": {
    "gn:admin1_code":"02",
    "gn:asciiname":"Dashawan",
    "gn:country_code":"CN",
    "gn:dem":101,
    "gn:feature_class":"P",
    "gn:feature_code":"PPL",
    "gn:name":"Dashawan",
    "gn:population":0,
    "gn:timezone":"Asia/Shanghai",
    "iso:country":"CN",
    "name:und_x_variant":[
        "Ta-sha-wan",
        "Dashawan",
        "\u5927\u6c99\u7897"
    ],
    "wof:name":"Dashawan",
    "wof:placetype":"locality"
},
  "geometry": {"coordinates":[122.43056,30.41511],"type":"Point"}
}