{
  "type": "Feature",
  "properties": {
    "gn:admin1_code":"12.0",
    "gn:asciiname":"Badouping",
    "gn:country_code":"CN",
    "gn:dem":318,
    "gn:feature_class":"P",
    "gn:feature_code":"PPL",
    "gn:name":"Badouping",
    "gn:population":0,
    "gn:timezone":"Asia/Shanghai",
    "iso:country":"CN",
    "name:zho_x_preferred":[
        "\u516b\u6597\u576a"
    ],
    "wof:name":"Badouping",
    "wof:placetype":"locality"
},
  "geometry": {"coordinates":[111.33428000000001,31.52115],"type":"Point"}
}