{
  "type": "Feature",
  "properties": {
    "gn:admin1_code":"32.0",
    "gn:asciiname":"Song'eryan",
    "gn:country_code":"CN",
    "gn:dem":346,
    "gn:feature_class":"P",
    "gn:feature_code":"PPL",
    "gn:name":"Song\u2019eryan",
    "gn:population":0,
    "gn:timezone":"Asia/Shanghai",
    "iso:country":"CN",
    "name:und_x_variant":[
        "Song\u2019eryan"
    ],
    "name:zho_x_preferred":[
        "\u5b8b\u513f\u5ca9"
    ],
    "wof:name":"Song'eryan",
    "wof:placetype":"locality"
},
  "geometry": {"coordinates":[104.568,28.5488],"type":"Point"}
}