{
  "type": "Feature",
  "properties": {
    "gn:admin1_code":"22",
    "gn:asciiname":"Longmentai",
    "gn:country_code":"CN",
    "gn:dem":630,
    "gn:feature_class":"P",
    "gn:feature_code":"PPL",
    "gn:name":"Longmentai",
    "gn:population":0,
    "gn:timezone":"Asia/Shanghai",
    "iso:country":"CN",
    "name:zho_x_preferred":[
        "\u9f99\u95e8\u53f0"
    ],
    "wof:name":"Longmentai",
    "wof:placetype":"locality"
},
  "geometry": {"coordinates":[115.62663999999999,39.75807],"type":"Point"}
}