{
  "type": "Feature",
  "properties": {
    "gn:admin1_code":"20.0",
    "gn:asciiname":"Kumu Erken",
    "gn:country_code":"CN",
    "gn:dem":269,
    "gn:feature_class":"P",
    "gn:feature_code":"PPL",
    "gn:name":"Kumu Erken",
    "gn:population":0,
    "gn:timezone":"Asia/Shanghai",
    "iso:country":"CN",
    "name:zho_x_preferred":[
        "\u5e93\u6728\u5c14\u80af"
    ],
    "wof:name":"Kumu Erken",
    "wof:placetype":"locality"
},
  "geometry": {"coordinates":[124.58977,49.16886],"type":"Point"}
}