{
  "type": "Feature",
  "properties": {
    "gn:admin1_code":"16.0",
    "gn:asciiname":"Dongshan",
    "gn:country_code":"CN",
    "gn:dem":53,
    "gn:feature_class":"P",
    "gn:feature_code":"PPL",
    "gn:name":"Dongshan",
    "gn:population":0,
    "gn:timezone":"Asia/Shanghai",
    "iso:country":"CN",
    "name:ceb_x_preferred":[
        "Dongshan"
    ],
    "name:deu_x_preferred":[
        "Dongshan"
    ],
    "name:eus_x_preferred":[
        "Dongshan"
    ],
    "name:fra_x_preferred":[
        "Dongshan"
    ],
    "name:nor_x_preferred":[
        "Dongshan"
    ],
    "name:rus_x_preferred":[
        "\u0414\u0443\u043d\u0448\u0430\u043d\u044c"
    ],
    "name:spa_x_preferred":[
        "Dongshan"
    ],
    "name:swe_x_preferred":[
        "Dongshan"
    ],
    "name:zho_x_preferred":[
        "\u4e1c\u5c71"
    ],
    "wof:name":"Dongshan",
    "wof:placetype":"locality"
},
  "geometry": {"coordinates":[109.705,23.1136],"type":"Point"}
}