{
  "type": "Feature",
  "properties": {
    "gn:admin1_code":"19.0",
    "gn:asciiname":"Beidaling",
    "gn:country_code":"CN",
    "gn:dem":350,
    "gn:feature_class":"P",
    "gn:feature_code":"PPL",
    "gn:name":"Beidaling",
    "gn:population":0,
    "gn:timezone":"Asia/Shanghai",
    "iso:country":"CN",
    "name:zho_x_preferred":[
        "\u5317\u5927\u5cad"
    ],
    "wof:name":"Beidaling",
    "wof:placetype":"locality"
},
  "geometry": {"coordinates":[123.965,41.551],"type":"Point"}
}