{
  "type": "Feature",
  "properties": {
    "gn:admin1_code":"3.0",
    "gn:asciiname":"Baishiling",
    "gn:country_code":"CN",
    "gn:dem":117,
    "gn:feature_class":"P",
    "gn:feature_code":"PPL",
    "gn:name":"Baishiling",
    "gn:population":0,
    "gn:timezone":"Asia/Shanghai",
    "iso:country":"CN",
    "name:und_x_variant":[
        "\u767d\u77f3\u5cad"
    ],
    "wof:name":"Baishiling",
    "wof:placetype":"locality"
},
  "geometry": {"coordinates":[116.62372000000001,27.31914],"type":"Point"}
}