{
  "type": "Feature",
  "properties": {
    "gn:admin1_code":"5.0",
    "gn:asciiname":"Shitouhezi",
    "gn:country_code":"CN",
    "gn:dem":874,
    "gn:feature_class":"P",
    "gn:feature_code":"PPL",
    "gn:name":"Shitouhezi",
    "gn:population":0,
    "gn:timezone":"Asia/Shanghai",
    "iso:country":"CN",
    "name:und_x_variant":[
        "\u77f3\u5934\u6cb3\u5b50"
    ],
    "wof:name":"Shitouhezi",
    "wof:placetype":"locality"
},
  "geometry": {"coordinates":[127.03816,41.87617],"type":"Point"}
}