{
  "type": "Feature",
  "properties": {
    "gn:admin1_code":"2.0",
    "gn:asciiname":"Xianyan",
    "gn:country_code":"CN",
    "gn:dem":194,
    "gn:feature_class":"P",
    "gn:feature_code":"PPL",
    "gn:name":"Xianyan",
    "gn:population":0,
    "gn:timezone":"Asia/Shanghai",
    "iso:country":"CN",
    "name:zho_x_preferred":[
        "\u4ed9\u5ca9"
    ],
    "wof:name":"Xianyan",
    "wof:placetype":"locality"
},
  "geometry": {"coordinates":[120.48763999999998,27.22265],"type":"Point"}
}