{
  "type": "Feature",
  "properties": {
    "gn:admin1_code":"6.0",
    "gn:asciiname":"Wenqun",
    "gn:country_code":"CN",
    "gn:dem":3488,
    "gn:feature_class":"P",
    "gn:feature_code":"PPL",
    "gn:name":"Wenqun",
    "gn:population":0,
    "gn:timezone":"Asia/Shanghai",
    "iso:country":"CN",
    "name:zho_x_preferred":[
        "\u6587\u7fa4"
    ],
    "wof:name":"Wenqun",
    "wof:placetype":"locality"
},
  "geometry": {"coordinates":[101.39673999999999,34.61912],"type":"Point"}
}