{
  "type": "Feature",
  "properties": {
    "gn:admin1_code":"19.0",
    "gn:asciiname":"Gaojiatun",
    "gn:country_code":"CN",
    "gn:dem":63,
    "gn:feature_class":"P",
    "gn:feature_code":"PPL",
    "gn:name":"Gaojiatun",
    "gn:population":0,
    "gn:timezone":"Asia/Shanghai",
    "iso:country":"CN",
    "name:und_x_variant":[
        "\u9ad8\u5bb6\u5c6f"
    ],
    "name:zho_x_preferred":[
        "\u9ad8\u5bb6\u5c6f"
    ],
    "wof:name":"Gaojiatun",
    "wof:placetype":"locality"
},
  "geometry": {"coordinates":[121.28672,41.53199],"type":"Point"}
}