{
  "type": "Feature",
  "properties": {
    "gn:admin1_code":"16.0",
    "gn:asciiname":"Wanggan Xincun",
    "gn:country_code":"CN",
    "gn:dem":86,
    "gn:feature_class":"P",
    "gn:feature_code":"PPL",
    "gn:name":"Wanggan Xincun",
    "gn:population":0,
    "gn:timezone":"Asia/Shanghai",
    "iso:country":"CN",
    "name:zho_x_preferred":[
        "\u65fa\u611f\u65b0\u6751"
    ],
    "wof:name":"Wanggan Xincun",
    "wof:placetype":"locality"
},
  "geometry": {"coordinates":[109.101,22.8899],"type":"Point"}
}