{
  "type": "Feature",
  "properties": {
    "gn:admin1_code":"9.0",
    "gn:asciiname":"Nan'angou",
    "gn:country_code":"CN",
    "gn:dem":520,
    "gn:feature_class":"P",
    "gn:feature_code":"PPL",
    "gn:name":"Nan\u2019angou",
    "gn:population":0,
    "gn:timezone":"Asia/Shanghai",
    "iso:country":"CN",
    "name:und_x_variant":[
        "Nan\u2019angou"
    ],
    "name:zho_x_preferred":[
        "\u5357\u5b89\u6c9f"
    ],
    "wof:name":"Nan'angou",
    "wof:placetype":"locality"
},
  "geometry": {"coordinates":[111.49682,34.29417],"type":"Point"}
}