{
  "type": "Feature",
  "properties": {
    "gn:admin1_code":"26.0",
    "gn:asciiname":"Yaoxianli",
    "gn:country_code":"CN",
    "gn:dem":1724,
    "gn:feature_class":"P",
    "gn:feature_code":"PPL",
    "gn:name":"Yaoxianli",
    "gn:population":0,
    "gn:timezone":"Asia/Shanghai",
    "iso:country":"CN",
    "name:zho_x_preferred":[
        "\u8981\u5c98\u91cc"
    ],
    "wof:name":"Yaoxianli",
    "wof:placetype":"locality"
},
  "geometry": {"coordinates":[106.52068,34.62151],"type":"Point"}
}