{
  "type": "Feature",
  "properties": {
    "gn:admin1_code":"8.0",
    "gn:asciiname":"Nenan Shidui",
    "gn:country_code":"CN",
    "gn:dem":210,
    "gn:feature_class":"P",
    "gn:feature_code":"PPLF",
    "gn:name":"Nenan Shidui",
    "gn:population":0,
    "gn:timezone":"Asia/Shanghai",
    "iso:country":"CN",
    "name:zho_x_preferred":[
        "\u8bb7\u5357\u5341\u961f"
    ],
    "wof:name":"Nenan Shidui",
    "wof:placetype":"locality"
},
  "geometry": {"coordinates":[125.17718000000001,48.44891],"type":"Point"}
}