{
  "type": "Feature",
  "properties": {
    "gn:admin1_code":"3.0",
    "gn:asciiname":"Liuzhaqiao Lijia",
    "gn:country_code":"CN",
    "gn:dem":24,
    "gn:feature_class":"P",
    "gn:feature_code":"PPL",
    "gn:name":"Liuzhaqiao Lijia",
    "gn:population":0,
    "gn:timezone":"Asia/Shanghai",
    "iso:country":"CN",
    "name:und_x_variant":[
        "\u516d\u95f8\u6865\u674e\u5bb6"
    ],
    "wof:name":"Liuzhaqiao Lijia",
    "wof:placetype":"locality"
},
  "geometry": {"coordinates":[116.80525,28.45782],"type":"Point"}
}