{
  "type": "Feature",
  "properties": {
    "gn:admin1_code":"5.0",
    "gn:asciiname":"Yaojie Niuquan",
    "gn:country_code":"CN",
    "gn:dem":169,
    "gn:feature_class":"P",
    "gn:feature_code":"PPL",
    "gn:name":"Yaojie Niuquan",
    "gn:population":0,
    "gn:timezone":"Asia/Shanghai",
    "iso:country":"CN",
    "name:zho_x_preferred":[
        "\u8170\u8857\u725b\u5708"
    ],
    "wof:name":"Yaojie Niuquan",
    "wof:placetype":"locality"
},
  "geometry": {"coordinates":[123.90383,44.37477],"type":"Point"}
}