{
  "type": "Feature",
  "properties": {
    "gn:admin1_code":"3",
    "gn:asciiname":"Yangyatang",
    "gn:country_code":"CN",
    "gn:dem":414,
    "gn:feature_class":"P",
    "gn:feature_code":"PPL",
    "gn:name":"Yangyatang",
    "gn:population":0,
    "gn:timezone":"Asia/Shanghai",
    "iso:country":"CN",
    "name:zho_x_preferred":[
        "\u6d0b\u7259\u5858"
    ],
    "wof:name":"Yangyatang",
    "wof:placetype":"locality"
},
  "geometry": {"coordinates":[114.488,26.1055],"type":"Point"}
}