{
  "type": "Feature",
  "properties": {
    "gn:admin1_code":"30.0",
    "gn:asciiname":"Changshan",
    "gn:country_code":"CN",
    "gn:dem":457,
    "gn:feature_class":"P",
    "gn:feature_code":"PPL",
    "gn:name":"Changshan",
    "gn:population":0,
    "gn:timezone":"Asia/Shanghai",
    "iso:country":"CN",
    "name:ita_x_preferred":[
        "Changshan"
    ],
    "name:kor_x_preferred":[
        "\ucc3d\ud30c\uc624"
    ],
    "name:msa_x_preferred":[
        "Changshan"
    ],
    "name:swe_x_preferred":[
        "Cheongsam"
    ],
    "name:zho_x_preferred":[
        "Changshan"
    ],
    "name:zho_x_variant":[
        "\u957f\u5c71"
    ],
    "wof:name":"Changshan",
    "wof:placetype":"locality"
},
  "geometry": {"coordinates":[113.00936000000002,24.59054],"type":"Point"}
}