{
  "type": "Feature",
  "properties": {
    "gn:admin1_code":"12.0",
    "gn:asciiname":"Bajiatai",
    "gn:country_code":"CN",
    "gn:dem":906,
    "gn:feature_class":"P",
    "gn:feature_code":"PPL",
    "gn:name":"Bajiatai",
    "gn:population":0,
    "gn:timezone":"Asia/Shanghai",
    "iso:country":"CN",
    "name:zho_x_preferred":[
        "\u516b\u5bb6\u53f0"
    ],
    "wof:name":"Bajiatai",
    "wof:placetype":"locality"
},
  "geometry": {"coordinates":[108.81095000000001,29.87227],"type":"Point"}
}