{
  "type": "Feature",
  "properties": {
    "gn:admin1_code":"8.0",
    "gn:asciiname":"Shengli Linchang",
    "gn:country_code":"CN",
    "gn:dem":374,
    "gn:feature_class":"P",
    "gn:feature_code":"PPLF",
    "gn:name":"Shengli Linchang",
    "gn:population":0,
    "gn:timezone":"Asia/Shanghai",
    "iso:country":"CN",
    "name:zho_x_preferred":[
        "\u80dc\u5229\u6797\u573a"
    ],
    "wof:name":"Shengli Linchang",
    "wof:placetype":"locality"
},
  "geometry": {"coordinates":[127.57595000000001,48.97629000000001],"type":"Point"}
}