{
  "type": "Feature",
  "properties": {
    "gn:admin1_code":"18",
    "gn:asciiname":"Laohaodong",
    "gn:country_code":"CN",
    "gn:dem":1274,
    "gn:feature_class":"P",
    "gn:feature_code":"PPL",
    "gn:name":"Laohaodong",
    "gn:population":0,
    "gn:timezone":"Asia/Shanghai",
    "iso:country":"CN",
    "name:zho_x_preferred":[
        "\u8001\u597d\u6d1e"
    ],
    "wof:name":"Laohaodong",
    "wof:placetype":"locality"
},
  "geometry": {"coordinates":[106.94,26.8651],"type":"Point"}
}