{
  "type": "Feature",
  "properties": {
    "gn:admin1_code":"11.0",
    "gn:asciiname":"Huangdianxi",
    "gn:country_code":"CN",
    "gn:dem":112,
    "gn:feature_class":"P",
    "gn:feature_code":"PPL",
    "gn:name":"Huangdianxi",
    "gn:population":0,
    "gn:timezone":"Asia/Shanghai",
    "iso:country":"CN",
    "name:zho_x_preferred":[
        "\u9ec4\u6bbf\u6eaa"
    ],
    "wof:name":"Huangdianxi",
    "wof:placetype":"locality"
},
  "geometry": {"coordinates":[111.48649,28.68102],"type":"Point"}
}