{
  "type": "Feature",
  "properties": {
    "gn:admin1_code":"5.0",
    "gn:asciiname":"Qinggouzi",
    "gn:country_code":"CN",
    "gn:dem":606,
    "gn:feature_class":"P",
    "gn:feature_code":"PPL",
    "gn:name":"Qinggouzi",
    "gn:population":0,
    "gn:timezone":"Asia/Shanghai",
    "iso:country":"CN",
    "name:und_x_variant":[
        "\u6e05\u6c9f\u5b50"
    ],
    "wof:name":"Qinggouzi",
    "wof:placetype":"locality"
},
  "geometry": {"coordinates":[128.44288,42.94208],"type":"Point"}
}