{
  "type": "Feature",
  "properties": {
    "gn:admin1_code":"8.0",
    "gn:asciiname":"Jiangbaochang",
    "gn:country_code":"CN",
    "gn:dem":153,
    "gn:feature_class":"P",
    "gn:feature_code":"PPL",
    "gn:name":"Jiangbaochang",
    "gn:population":0,
    "gn:timezone":"Asia/Shanghai",
    "iso:country":"CN",
    "name:zho_x_preferred":[
        "\u59dc\u4fdd\u957f"
    ],
    "wof:name":"Jiangbaochang",
    "wof:placetype":"locality"
},
  "geometry": {"coordinates":[124.96787999999999,47.12369],"type":"Point"}
}