{
  "type": "Feature",
  "properties": {
    "gn:admin1_code":"2.0",
    "gn:asciiname":"Xiaofeng",
    "gn:cc2":"CN",
    "gn:country_code":"CN",
    "gn:dem":67,
    "gn:feature_class":"P",
    "gn:feature_code":"PPL",
    "gn:name":"Xiaofeng",
    "gn:population":0,
    "gn:timezone":"Asia/Shanghai",
    "iso:country":"CN",
    "name:und_x_variant":[
        "Siaofenghsien",
        "Hsiao-feng-hsien-ch\u2019eng",
        "Siaofeng",
        "Feng-ch\u2019eng",
        "Hsiao-feng-hsien",
        "Hsiao-feng",
        "Xiaofeng",
        "\u5b5d\u4e30"
    ],
    "wof:name":"Xiaofeng",
    "wof:placetype":"locality"
},
  "geometry": {"coordinates":[119.54806000000001,30.58972],"type":"Point"}
}