{
  "type": "Feature",
  "properties": {
    "gn:admin1_code":"04",
    "gn:asciiname":"Shenjiaqiao",
    "gn:cc2":"CN",
    "gn:country_code":"CN",
    "gn:dem":6,
    "gn:feature_class":"P",
    "gn:feature_code":"PPL",
    "gn:name":"Shenjiaqiao",
    "gn:population":0,
    "gn:timezone":"Asia/Shanghai",
    "iso:country":"CN",
    "name:und_x_variant":[
        "Shen-chia-ch\u2019iao",
        "Shenjiaqiao",
        "\u6c88\u5bb6\u6865"
    ],
    "wof:name":"Shenjiaqiao",
    "wof:placetype":"locality"
},
  "geometry": {"coordinates":[120.70583000000001,32.24028],"type":"Point"}
}