{
  "type": "Feature",
  "properties": {
    "gn:admin1_code":"30.0",
    "gn:asciiname":"Xiaoyuankeng",
    "gn:country_code":"CN",
    "gn:dem":202,
    "gn:feature_class":"P",
    "gn:feature_code":"PPL",
    "gn:name":"Xiaoyuankeng",
    "gn:population":0,
    "gn:timezone":"Asia/Shanghai",
    "iso:country":"CN",
    "name:zho_x_preferred":[
        "\u5c0f\u5143\u5751"
    ],
    "wof:name":"Xiaoyuankeng",
    "wof:placetype":"locality"
},
  "geometry": {"coordinates":[114.21514000000001,23.45334],"type":"Point"}
}