{
  "type": "Feature",
  "properties": {
    "gn:admin1_code":"3.0",
    "gn:asciiname":"Exing",
    "gn:country_code":"CN",
    "gn:dem":188,
    "gn:feature_class":"P",
    "gn:feature_code":"PPL",
    "gn:name":"Exing",
    "gn:population":0,
    "gn:timezone":"Asia/Shanghai",
    "iso:country":"CN",
    "name:und_x_variant":[
        "\u9e45\u5f62"
    ],
    "wof:name":"Exing",
    "wof:placetype":"locality"
},
  "geometry": {"coordinates":[115.84529000000001,26.37325],"type":"Point"}
}