{
  "type": "Feature",
  "properties": {
    "gn:admin1_code":"32.0",
    "gn:asciiname":"Sanjiao",
    "gn:country_code":"CN",
    "gn:dem":409,
    "gn:feature_class":"P",
    "gn:feature_code":"PPL",
    "gn:name":"Sanjiao",
    "gn:population":0,
    "gn:timezone":"Asia/Shanghai",
    "iso:country":"CN",
    "name:ceb_x_preferred":[
        "Sanjiao"
    ],
    "name:deu_x_preferred":[
        "Sanjiao"
    ],
    "name:swe_x_preferred":[
        "Sanjiao"
    ],
    "name:zho_x_preferred":[
        "\u4e09\u86df"
    ],
    "wof:name":"Sanjiao",
    "wof:placetype":"locality"
},
  "geometry": {"coordinates":[106.40452999999999,31.60089],"type":"Point"}
}