{
  "type": "Feature",
  "properties": {
    "gn:admin1_code":"9.0",
    "gn:asciiname":"Beiguozhuang",
    "gn:country_code":"CN",
    "gn:dem":361,
    "gn:feature_class":"P",
    "gn:feature_code":"PPL",
    "gn:name":"Beiguozhuang",
    "gn:population":0,
    "gn:timezone":"Asia/Shanghai",
    "iso:country":"CN",
    "name:zho_x_preferred":[
        "\u5317\u90ed\u5e84"
    ],
    "wof:name":"Beiguozhuang",
    "wof:placetype":"locality"
},
  "geometry": {"coordinates":[112.69073,34.27972],"type":"Point"}
}