{
  "type": "Feature",
  "properties": {
    "gn:admin1_code":"18.0",
    "gn:asciiname":"Xingzhu",
    "gn:country_code":"CN",
    "gn:dem":592,
    "gn:feature_class":"P",
    "gn:feature_code":"PPL",
    "gn:name":"Xingzhu",
    "gn:population":0,
    "gn:timezone":"Asia/Shanghai",
    "iso:country":"CN",
    "name:zho_x_preferred":[
        "\u661f\u7af9"
    ],
    "wof:name":"Xingzhu",
    "wof:placetype":"locality"
},
  "geometry": {"coordinates":[107.89400000000001,27.8011],"type":"Point"}
}