{
  "type": "Feature",
  "properties": {
    "gn:admin1_code":"02",
    "gn:asciiname":"Fangshan",
    "gn:country_code":"CN",
    "gn:dem":139,
    "gn:feature_class":"P",
    "gn:feature_code":"PPLA4",
    "gn:name":"Fangshan",
    "gn:population":0,
    "gn:timezone":"Asia/Shanghai",
    "iso:country":"CN",
    "name:und_x_variant":[
        "Shiqian",
        "Fangshan",
        "Fangshan Xiang"
    ],
    "name:zho_x_preferred":[
        "Hs\u00fc-ch\u2019ien"
    ],
    "name:zho_x_variant":[
        "\u65b9\u5c71",
        "\u65b9\u5c71\u4e61"
    ],
    "wof:name":"Fangshan",
    "wof:placetype":"locality"
},
  "geometry": {"coordinates":[120.3135,28.0236],"type":"Point"}
}