{
  "type": "Feature",
  "properties": {
    "gn:admin1_code":"4.0",
    "gn:asciiname":"Peide",
    "gn:country_code":"CN",
    "gn:dem":6,
    "gn:feature_class":"P",
    "gn:feature_code":"PPL",
    "gn:name":"Peide",
    "gn:population":0,
    "gn:timezone":"Asia/Shanghai",
    "iso:country":"CN",
    "name:und_x_variant":[
        "\u57f9\u5fb7"
    ],
    "wof:name":"Peide",
    "wof:placetype":"locality"
},
  "geometry": {"coordinates":[121.30903000000001,32.29216],"type":"Point"}
}