{
  "type": "Feature",
  "properties": {
    "gn:admin1_code":"32.0",
    "gn:asciiname":"Ziku",
    "gn:country_code":"CN",
    "gn:dem":473,
    "gn:feature_class":"P",
    "gn:feature_code":"PPL",
    "gn:name":"Ziku",
    "gn:population":0,
    "gn:timezone":"Asia/Shanghai",
    "iso:country":"CN",
    "name:zho_x_preferred":[
        "\u5b57\u5e93"
    ],
    "wof:name":"Ziku",
    "wof:placetype":"locality"
},
  "geometry": {"coordinates":[104.73651,31.22421],"type":"Point"}
}