{
  "type": "Feature",
  "properties": {
    "gn:admin1_code":"2",
    "gn:asciiname":"Zhangjiayuan",
    "gn:country_code":"CN",
    "gn:dem":385,
    "gn:feature_class":"P",
    "gn:feature_code":"PPL",
    "gn:name":"Zhangjiayuan",
    "gn:population":0,
    "gn:timezone":"Asia/Shanghai",
    "iso:country":"CN",
    "name:zho_x_preferred":[
        "\u5f20\u5bb6\u6e90"
    ],
    "wof:name":"Zhangjiayuan",
    "wof:placetype":"locality"
},
  "geometry": {"coordinates":[118.58986000000002,28.53393],"type":"Point"}
}