{
  "type": "Feature",
  "properties": {
    "gn:admin1_code":"11",
    "gn:asciiname":"Laohekou",
    "gn:country_code":"CN",
    "gn:dem":30,
    "gn:feature_class":"P",
    "gn:feature_code":"PPL",
    "gn:name":"Laohekou",
    "gn:population":0,
    "gn:timezone":"Asia/Shanghai",
    "iso:country":"CN",
    "name:ceb_x_preferred":[
        "Laohekou Shi"
    ],
    "name:deu_x_preferred":[
        "Laohekou"
    ],
    "name:fra_x_preferred":[
        "Laohekou"
    ],
    "name:ita_x_preferred":[
        "Laohekou"
    ],
    "name:jpn_x_preferred":[
        "\u8001\u6cb3\u53e3\u5e02"
    ],
    "name:kik_x_preferred":[
        "Laohekou"
    ],
    "name:kor_x_preferred":[
        "\ub77c\uc624\ud5c8\ucee4\uc6b0\uc2dc"
    ],
    "name:mlg_x_preferred":[
        "Laohekou"
    ],
    "name:nor_x_preferred":[
        "Laohekou"
    ],
    "name:pam_x_preferred":[
        "Laohekou"
    ],
    "name:pol_x_preferred":[
        "Laohekou"
    ],
    "name:srp_x_preferred":[
        "\u041b\u0430\u043e\u0445\u0435\u043a\u043e\u0443"
    ],
    "name:swe_x_preferred":[
        "Laohekou"
    ],
    "name:urd_x_preferred":[
        "\u0644\u0627\u0648\u06c1\u06cc\u06a9\u0648"
    ],
    "name:war_x_preferred":[
        "Laohekou"
    ],
    "name:zho_x_preferred":[
        "\u8001\u6cb3\u53e3\u5e02"
    ],
    "wof:name":"Laohekou",
    "wof:placetype":"locality"
},
  "geometry": {"coordinates":[112.67833,29.46472],"type":"Point"}
}