{
  "type": "Feature",
  "properties": {
    "gn:admin1_code":"02",
    "gn:asciiname":"Maqiao",
    "gn:country_code":"CN",
    "gn:dem":8,
    "gn:feature_class":"P",
    "gn:feature_code":"PPLA4",
    "gn:name":"Maqiao",
    "gn:population":0,
    "gn:timezone":"Asia/Shanghai",
    "iso:country":"CN",
    "name:und_x_variant":[
        "Ma-ch\u2019iao-chen",
        "Maqiao",
        "\u9a6c\u6865",
        "Maqiao Zhen",
        "Maqiao Jiedao",
        "\u9a6c\u6865\u9547",
        "\u9a6c\u6865\u8857\u9053"
    ],
    "wof:name":"Maqiao",
    "wof:placetype":"locality"
},
  "geometry": {"coordinates":[120.69792,30.46449],"type":"Point"}
}