{
  "type": "Feature",
  "properties": {
    "gn:admin1_code":"12.0",
    "gn:asciiname":"Shangguanlao",
    "gn:country_code":"CN",
    "gn:dem":35,
    "gn:feature_class":"P",
    "gn:feature_code":"PPL",
    "gn:name":"Shangguanlao",
    "gn:population":0,
    "gn:timezone":"Asia/Shanghai",
    "iso:country":"CN",
    "name:zho_x_preferred":[
        "\u4e0a\u5173\u8001"
    ],
    "wof:name":"Shangguanlao",
    "wof:placetype":"locality"
},
  "geometry": {"coordinates":[112.60783000000001,29.71692],"type":"Point"}
}