{
  "type": "Feature",
  "properties": {
    "gn:admin1_code":"31.0",
    "gn:asciiname":"Rulin",
    "gn:country_code":"CN",
    "gn:dem":20,
    "gn:feature_class":"P",
    "gn:feature_code":"PPL",
    "gn:name":"Rulin",
    "gn:population":0,
    "gn:timezone":"Asia/Shanghai",
    "iso:country":"CN",
    "name:zho_x_preferred":[
        "\u5112\u6797"
    ],
    "name:zho_x_variant":[
        "\u5112\u6797\u9547"
    ],
    "wof:name":"Rulin",
    "wof:placetype":"locality"
},
  "geometry": {"coordinates":[110.41297,19.83461],"type":"Point"}
}