{
  "type": "Feature",
  "properties": {
    "gn:admin1_code":"19.0",
    "gn:asciiname":"Zhanggangtuncun",
    "gn:country_code":"CN",
    "gn:dem":98,
    "gn:feature_class":"P",
    "gn:feature_code":"PPL",
    "gn:name":"Zhanggangtuncun",
    "gn:population":0,
    "gn:timezone":"Asia/Shanghai",
    "iso:country":"CN",
    "name:zho_x_preferred":[
        "\u5f20\u6760\u5c6f\u6751"
    ],
    "wof:name":"Zhanggangtuncun",
    "wof:placetype":"locality"
},
  "geometry": {"coordinates":[120.88200000000001,41.2888],"type":"Point"}
}