{
  "type": "Feature",
  "properties": {
    "gn:admin1_code":"18",
    "gn:asciiname":"Datuola",
    "gn:country_code":"CN",
    "gn:dem":1443,
    "gn:feature_class":"P",
    "gn:feature_code":"PPL",
    "gn:name":"Datuola",
    "gn:population":0,
    "gn:timezone":"Asia/Shanghai",
    "iso:country":"CN",
    "name:zho_x_preferred":[
        "\u5927\u62d6\u62c9"
    ],
    "wof:name":"Datuola",
    "wof:placetype":"locality"
},
  "geometry": {"coordinates":[104.68899999999999,24.9715],"type":"Point"}
}