{
  "type": "Feature",
  "properties": {
    "gn:admin1_code":"21.0",
    "gn:asciiname":"Buluoquan",
    "gn:country_code":"CN",
    "gn:dem":2218,
    "gn:feature_class":"P",
    "gn:feature_code":"PPL",
    "gn:name":"Buluoquan",
    "gn:population":0,
    "gn:timezone":"Asia/Shanghai",
    "iso:country":"CN",
    "name:zho_x_preferred":[
        "\u535c\u7f57\u6cc9"
    ],
    "wof:name":"Buluoquan",
    "wof:placetype":"locality"
},
  "geometry": {"coordinates":[105.524,36.2942],"type":"Point"}
}