{
  "type": "Feature",
  "properties": {
    "gn:admin1_code":"12.0",
    "gn:asciiname":"Jianlouwu",
    "gn:country_code":"CN",
    "gn:dem":85,
    "gn:feature_class":"P",
    "gn:feature_code":"PPL",
    "gn:name":"Jianlouwu",
    "gn:population":0,
    "gn:timezone":"Asia/Shanghai",
    "iso:country":"CN",
    "name:zho_x_preferred":[
        "\u5efa\u697c\u5c4b"
    ],
    "wof:name":"Jianlouwu",
    "wof:placetype":"locality"
},
  "geometry": {"coordinates":[113.80944,29.63057],"type":"Point"}
}