{
  "type": "Feature",
  "properties": {
    "gn:admin1_code":"3.0",
    "gn:asciiname":"Waiping",
    "gn:country_code":"CN",
    "gn:dem":199,
    "gn:feature_class":"P",
    "gn:feature_code":"PPL",
    "gn:name":"Waiping",
    "gn:population":0,
    "gn:timezone":"Asia/Shanghai",
    "iso:country":"CN",
    "name:und_x_variant":[
        "\u5916\u576a"
    ],
    "wof:name":"Waiping",
    "wof:placetype":"locality"
},
  "geometry": {"coordinates":[114.84032999999999,29.31851],"type":"Point"}
}