{
  "type": "Feature",
  "properties": {
    "gn:admin1_code":"16",
    "gn:asciiname":"Nonggang",
    "gn:country_code":"CN",
    "gn:dem":192,
    "gn:feature_class":"P",
    "gn:feature_code":"PPL",
    "gn:name":"Nonggang",
    "gn:population":0,
    "gn:timezone":"Asia/Shanghai",
    "iso:country":"CN",
    "name:zho_x_preferred":[
        "\u5f04\u5c97"
    ],
    "wof:name":"Nonggang",
    "wof:placetype":"locality"
},
  "geometry": {"coordinates":[106.977,22.5093],"type":"Point"}
}