{
  "type": "Feature",
  "properties": {
    "gn:admin1_code":"5.0",
    "gn:asciiname":"Tianjiashihao",
    "gn:country_code":"CN",
    "gn:dem":189,
    "gn:feature_class":"P",
    "gn:feature_code":"PPL",
    "gn:name":"Tianjiashihao",
    "gn:population":0,
    "gn:timezone":"Asia/Shanghai",
    "iso:country":"CN",
    "name:zho_x_preferred":[
        "\u7530\u5bb6\u5341\u53f7"
    ],
    "wof:name":"Tianjiashihao",
    "wof:placetype":"locality"
},
  "geometry": {"coordinates":[126.40658000000001,45.0594],"type":"Point"}
}