{
  "type": "Feature",
  "properties": {
    "gn:admin1_code":"6.0",
    "gn:asciiname":"Namsai",
    "gn:country_code":"CN",
    "gn:dem":3966,
    "gn:feature_class":"P",
    "gn:feature_code":"PPLA4",
    "gn:name":"Namsai",
    "gn:population":0,
    "gn:timezone":"Asia/Urumqi",
    "iso:country":"CN",
    "name:mon_x_preferred":[
        "Namsai"
    ],
    "name:und_x_variant":[
        "Angsai",
        "Angsai Xiang",
        "Dieniga"
    ],
    "name:zho_x_preferred":[
        "\u6602\u8d5b"
    ],
    "name:zho_x_variant":[
        "\u6602\u8d5b\u4e61",
        "\u8dcc\u5c3c\u560e"
    ],
    "wof:name":"Namsai",
    "wof:placetype":"locality"
},
  "geometry": {"coordinates":[95.61479,32.78552],"type":"Point"}
}