{
  "type": "Feature",
  "properties": {
    "gn:admin1_code":"2.0",
    "gn:asciiname":"Gengdu",
    "gn:country_code":"CN",
    "gn:dem":812,
    "gn:feature_class":"P",
    "gn:feature_code":"PPL",
    "gn:name":"Gengdu",
    "gn:population":0,
    "gn:timezone":"Asia/Shanghai",
    "iso:country":"CN",
    "name:zho_x_preferred":[
        "\u8015\u8bfb"
    ],
    "wof:name":"Gengdu",
    "wof:placetype":"locality"
},
  "geometry": {"coordinates":[120.59686000000001,28.84912000000001],"type":"Point"}
}