{
  "type": "Feature",
  "properties": {
    "gn:admin1_code":"29.0",
    "gn:asciiname":"Huangchong",
    "gn:country_code":"CN",
    "gn:dem":2161,
    "gn:feature_class":"P",
    "gn:feature_code":"PPL",
    "gn:name":"Huangchong",
    "gn:population":0,
    "gn:timezone":"Asia/Shanghai",
    "iso:country":"CN",
    "name:zho_x_preferred":[
        "\u8352\u51b2"
    ],
    "wof:name":"Huangchong",
    "wof:placetype":"locality"
},
  "geometry": {"coordinates":[103.392,26.5356],"type":"Point"}
}