{
  "type": "Feature",
  "properties": {
    "gn:admin1_code":"5.0",
    "gn:asciiname":"Xia'erguliucun",
    "gn:country_code":"CN",
    "gn:dem":495,
    "gn:feature_class":"P",
    "gn:feature_code":"PPL",
    "gn:name":"Xia\u2019erguliucun",
    "gn:population":0,
    "gn:timezone":"Asia/Shanghai",
    "iso:country":"CN",
    "name:und_x_variant":[
        "Xia\u2019erguliucun"
    ],
    "name:zho_x_preferred":[
        "\u4e0b\u4e8c\u80a1\u6d41\u6751"
    ],
    "wof:name":"Xia'erguliucun",
    "wof:placetype":"locality"
},
  "geometry": {"coordinates":[127.47714999999999,41.47233],"type":"Point"}
}