{
  "type": "Feature",
  "properties": {
    "gn:admin1_code":"4.0",
    "gn:asciiname":"Nanbao",
    "gn:country_code":"CN",
    "gn:dem":1,
    "gn:feature_class":"P",
    "gn:feature_code":"PPL",
    "gn:name":"Nanbao",
    "gn:population":0,
    "gn:timezone":"Asia/Shanghai",
    "iso:country":"CN",
    "name:ceb_x_preferred":[
        "Nanbao"
    ],
    "name:swe_x_preferred":[
        "Nanbao"
    ],
    "wof:name":"Nanbao",
    "wof:placetype":"locality"
},
  "geometry": {"coordinates":[119.95,33.175],"type":"Point"}
}