{
  "type": "Feature",
  "properties": {
    "gn:admin1_code":"26.0",
    "gn:asciiname":"Chenjincun",
    "gn:country_code":"CN",
    "gn:dem":565,
    "gn:feature_class":"P",
    "gn:feature_code":"PPL",
    "gn:name":"Chenjincun",
    "gn:population":0,
    "gn:timezone":"Asia/Shanghai",
    "iso:country":"CN",
    "name:zho_x_preferred":[
        "\u9648\u9773\u6751"
    ],
    "wof:name":"Chenjincun",
    "wof:placetype":"locality"
},
  "geometry": {"coordinates":[108.40347,34.46841],"type":"Point"}
}