{
  "type": "Feature",
  "properties": {
    "gn:admin1_code":"11",
    "gn:asciiname":"Nanyang",
    "gn:country_code":"CN",
    "gn:dem":129,
    "gn:feature_class":"P",
    "gn:feature_code":"PPL",
    "gn:name":"Nanyang",
    "gn:population":0,
    "gn:timezone":"Asia/Shanghai",
    "iso:country":"CN",
    "name:ceb_x_preferred":[
        "Nanyang"
    ],
    "name:deu_x_preferred":[
        "Nanyang"
    ],
    "name:heb_x_preferred":[
        "\u05e0\u05e0\u05d9\u05d0\u05e0\u05d2"
    ],
    "name:hun_x_preferred":[
        "Nanjang"
    ],
    "name:mlg_x_preferred":[
        "Nanyang"
    ],
    "name:nor_x_preferred":[
        "Nanyang"
    ],
    "name:swe_x_preferred":[
        "Nanyang"
    ],
    "name:vie_x_preferred":[
        "Nam D\u01b0\u01a1ng"
    ],
    "wof:name":"Nanyang",
    "wof:placetype":"locality"
},
  "geometry": {"coordinates":[112.97028,26.34917],"type":"Point"}
}