{
  "type": "Feature",
  "properties": {
    "gn:admin1_code":"8.0",
    "gn:asciiname":"Dongdaolin",
    "gn:country_code":"CN",
    "gn:dem":54,
    "gn:feature_class":"P",
    "gn:feature_code":"PPL",
    "gn:name":"Dongdaolin",
    "gn:population":0,
    "gn:timezone":"Asia/Shanghai",
    "iso:country":"CN",
    "name:zho_x_preferred":[
        "\u4e1c\u9053\u6797"
    ],
    "wof:name":"Dongdaolin",
    "wof:placetype":"locality"
},
  "geometry": {"coordinates":[134.20809,47.50388],"type":"Point"}
}