{
  "type": "Feature",
  "properties": {
    "gn:admin1_code":"10.0",
    "gn:asciiname":"Tangyingsi",
    "gn:country_code":"CN",
    "gn:dem":1644,
    "gn:feature_class":"P",
    "gn:feature_code":"PPL",
    "gn:name":"Tangyingsi",
    "gn:population":0,
    "gn:timezone":"Asia/Shanghai",
    "iso:country":"CN",
    "name:zho_x_preferred":[
        "\u6c64\u5e94\u5bfa"
    ],
    "wof:name":"Tangyingsi",
    "wof:placetype":"locality"
},
  "geometry": {"coordinates":[115.05128000000001,39.91507],"type":"Point"}
}