{
  "type": "Feature",
  "properties": {
    "gn:admin1_code":"07",
    "gn:asciiname":"Guanbei",
    "gn:cc2":"CN",
    "gn:country_code":"CN",
    "gn:dem":114,
    "gn:feature_class":"P",
    "gn:feature_code":"PPL",
    "gn:name":"Guanbei",
    "gn:population":0,
    "gn:timezone":"Asia/Shanghai",
    "iso:country":"CN",
    "name:und_x_variant":[
        "Kuan-pei",
        "Guanbei"
    ],
    "name:zho_x_preferred":[
        "\u5b98\u9642\u9547"
    ],
    "wof:name":"Guanbei",
    "wof:placetype":"locality"
},
  "geometry": {"coordinates":[117.06917,24.01833],"type":"Point"}
}