{
  "type": "Feature",
  "properties": {
    "gn:admin1_code":"30.0",
    "gn:asciiname":"Jiantang",
    "gn:country_code":"CN",
    "gn:dem":408,
    "gn:feature_class":"P",
    "gn:feature_code":"PPL",
    "gn:name":"Jiantang",
    "gn:population":0,
    "gn:timezone":"Asia/Shanghai",
    "iso:country":"CN",
    "name:zho_x_preferred":[
        "\u5efa\u68e0"
    ],
    "name:zho_x_variant":[
        "\u5efa\u5858\u9547"
    ],
    "wof:name":"Jiantang",
    "wof:placetype":"locality"
},
  "geometry": {"coordinates":[112.97472,24.49278],"type":"Point"}
}