{
  "type": "Feature",
  "properties": {
    "gn:admin1_code":"30.0",
    "gn:asciiname":"Xiasandu",
    "gn:country_code":"CN",
    "gn:dem":53,
    "gn:feature_class":"P",
    "gn:feature_code":"PPL",
    "gn:name":"Xiasandu",
    "gn:population":0,
    "gn:timezone":"Asia/Shanghai",
    "iso:country":"CN",
    "name:zho_x_preferred":[
        "\u4e0b\u4e09\u90fd"
    ],
    "wof:name":"Xiasandu",
    "wof:placetype":"locality"
},
  "geometry": {"coordinates":[113.49115999999999,24.70393],"type":"Point"}
}