{
  "type": "Feature",
  "properties": {
    "gn:admin1_code":"24",
    "gn:asciiname":"Zhuangjiadian",
    "gn:country_code":"CN",
    "gn:dem":1399,
    "gn:feature_class":"P",
    "gn:feature_code":"PPL",
    "gn:name":"Zhuangjiadian",
    "gn:population":0,
    "gn:timezone":"Asia/Shanghai",
    "iso:country":"CN",
    "name:und_x_variant":[
        "Chuang-chia-tien",
        "Zhuangjiadian",
        "\u5e84\u5bb6\u5e97"
    ],
    "wof:name":"Zhuangjiadian",
    "wof:placetype":"locality"
},
  "geometry": {"coordinates":[112.81453999999999,39.84911],"type":"Point"}
}