{
  "type": "Feature",
  "properties": {
    "gn:admin1_code":"19",
    "gn:asciiname":"Nanzamu",
    "gn:country_code":"CN",
    "gn:dem":141,
    "gn:feature_class":"P",
    "gn:feature_code":"PPLA4",
    "gn:name":"Nanzamu",
    "gn:population":0,
    "gn:timezone":"Asia/Shanghai",
    "iso:country":"CN",
    "name:und_x_variant":[
        "Nan-tsa-mu-huo-lo",
        "Nan-cha-mu-huo-lo",
        "Nan-tsa-mu",
        "Nanzamu",
        "\u5357\u6742\u6728",
        "Nanzamu Zhen",
        "\u5357\u6742\u6728\u9547"
    ],
    "wof:name":"Nanzamu",
    "wof:placetype":"locality"
},
  "geometry": {"coordinates":[124.41101,41.96927],"type":"Point"}
}