{
  "type": "Feature",
  "properties": {
    "gn:admin1_code":"29.0",
    "gn:asciiname":"Shipopo",
    "gn:country_code":"CN",
    "gn:dem":1731,
    "gn:feature_class":"P",
    "gn:feature_code":"PPL",
    "gn:name":"Shipopo",
    "gn:population":0,
    "gn:timezone":"Asia/Shanghai",
    "iso:country":"CN",
    "name:zho_x_preferred":[
        "\u77f3\u5761\u5761"
    ],
    "wof:name":"Shipopo",
    "wof:placetype":"locality"
},
  "geometry": {"coordinates":[101.56399999999999,25.7279],"type":"Point"}
}