{
  "type": "Feature",
  "properties": {
    "gn:admin1_code":"32.0",
    "gn:asciiname":"Dachaoyuan",
    "gn:country_code":"CN",
    "gn:dem":2105,
    "gn:feature_class":"P",
    "gn:feature_code":"PPL",
    "gn:name":"Dachaoyuan",
    "gn:population":0,
    "gn:timezone":"Asia/Shanghai",
    "iso:country":"CN",
    "name:zho_x_preferred":[
        "\u5927\u6f6e\u5143"
    ],
    "wof:name":"Dachaoyuan",
    "wof:placetype":"locality"
},
  "geometry": {"coordinates":[102.512,27.3093],"type":"Point"}
}