{
  "type": "Feature",
  "properties": {
    "gn:admin1_code":"30.0",
    "gn:asciiname":"Fuxicun",
    "gn:country_code":"CN",
    "gn:dem":171,
    "gn:feature_class":"P",
    "gn:feature_code":"PPL",
    "gn:name":"Fuxicun",
    "gn:population":0,
    "gn:timezone":"Asia/Shanghai",
    "iso:country":"CN",
    "name:zho_x_preferred":[
        "\u798f\u6eaa\u6751"
    ],
    "wof:name":"Fuxicun",
    "wof:placetype":"locality"
},
  "geometry": {"coordinates":[116.84781,24.3146],"type":"Point"}
}