{
  "type": "Feature",
  "properties": {
    "gn:admin1_code":"11.0",
    "gn:asciiname":"Zhutailing",
    "gn:country_code":"CN",
    "gn:dem":163,
    "gn:feature_class":"P",
    "gn:feature_code":"PPL",
    "gn:name":"Zhutailing",
    "gn:population":0,
    "gn:timezone":"Asia/Shanghai",
    "iso:country":"CN",
    "name:zho_x_preferred":[
        "\u7af9\u53f0\u5cad"
    ],
    "wof:name":"Zhutailing",
    "wof:placetype":"locality"
},
  "geometry": {"coordinates":[113.11123000000001,27.27239],"type":"Point"}
}