{
  "type": "Feature",
  "properties": {
    "gn:admin1_code":"22.0",
    "gn:asciiname":"Ketoucun",
    "gn:country_code":"CN",
    "gn:dem":29,
    "gn:feature_class":"P",
    "gn:feature_code":"PPL",
    "gn:name":"Ketoucun",
    "gn:population":0,
    "gn:timezone":"Asia/Shanghai",
    "iso:country":"CN",
    "name:zho_x_preferred":[
        "\u514b\u5934\u6751"
    ],
    "wof:name":"Ketoucun",
    "wof:placetype":"locality"
},
  "geometry": {"coordinates":[117.08332,40.09611],"type":"Point"}
}