{
  "type": "Feature",
  "properties": {
    "gn:admin1_code":"10.0",
    "gn:asciiname":"Xuyangzhuang",
    "gn:country_code":"CN",
    "gn:dem":46,
    "gn:feature_class":"P",
    "gn:feature_code":"PPL",
    "gn:name":"Xuyangzhuang",
    "gn:population":0,
    "gn:timezone":"Asia/Shanghai",
    "iso:country":"CN",
    "name:und_x_variant":[
        "Hs\u00fc-chuang",
        "Xuzhuang",
        "Xuyangzhuang",
        "Xuyang"
    ],
    "name:zho_x_preferred":[
        "\u5f90\u6768\u5e84"
    ],
    "name:zho_x_variant":[
        "\u5f90\u6768"
    ],
    "wof:name":"Xuyangzhuang",
    "wof:placetype":"locality"
},
  "geometry": {"coordinates":[115.27714,36.38321],"type":"Point"}
}