{
  "type": "Feature",
  "properties": {
    "gn:admin1_code":"21.0",
    "gn:asciiname":"Huasan Dadui",
    "gn:country_code":"CN",
    "gn:dem":1122,
    "gn:feature_class":"P",
    "gn:feature_code":"PPLF",
    "gn:name":"Huasan Dadui",
    "gn:population":0,
    "gn:timezone":"Asia/Shanghai",
    "iso:country":"CN",
    "name:zho_x_preferred":[
        "\u534e\u4e09\u5927\u961f"
    ],
    "wof:name":"Huasan Dadui",
    "wof:placetype":"locality"
},
  "geometry": {"coordinates":[106.19199999999999,38.024],"type":"Point"}
}