{
  "type": "Feature",
  "properties": {
    "gn:admin1_code":"19.0",
    "gn:asciiname":"Houyuantai",
    "gn:country_code":"CN",
    "gn:dem":54,
    "gn:feature_class":"P",
    "gn:feature_code":"PPL",
    "gn:name":"Houyuantai",
    "gn:population":0,
    "gn:timezone":"Asia/Shanghai",
    "iso:country":"CN",
    "name:und_x_variant":[
        "\u540e\u5143\u53f0"
    ],
    "name:zho_x_preferred":[
        "\u540e\u5143\u53f0"
    ],
    "wof:name":"Houyuantai",
    "wof:placetype":"locality"
},
  "geometry": {"coordinates":[122.06775,39.64098],"type":"Point"}
}