{
  "type": "Feature",
  "properties": {
    "gn:admin1_code":"29.0",
    "gn:asciiname":"Laimu",
    "gn:country_code":"CN",
    "gn:dem":1002,
    "gn:feature_class":"P",
    "gn:feature_code":"PPL",
    "gn:name":"Laimu",
    "gn:population":0,
    "gn:timezone":"Asia/Shanghai",
    "iso:country":"CN",
    "name:zho_x_preferred":[
        "\u8d56\u6728"
    ],
    "wof:name":"Laimu",
    "wof:placetype":"locality"
},
  "geometry": {"coordinates":[98.31870000000001,24.3618],"type":"Point"}
}