{
  "type": "Feature",
  "properties": {
    "gn:admin1_code":"5.0",
    "gn:asciiname":"Sanmen Zhangjia",
    "gn:country_code":"CN",
    "gn:dem":296,
    "gn:feature_class":"P",
    "gn:feature_code":"PPL",
    "gn:name":"Sanmen Zhangjia",
    "gn:population":0,
    "gn:timezone":"Asia/Shanghai",
    "iso:country":"CN",
    "name:zho_x_preferred":[
        "\u4e09\u95e8\u5f20\u5bb6"
    ],
    "wof:name":"Sanmen Zhangjia",
    "wof:placetype":"locality"
},
  "geometry": {"coordinates":[125.08635,42.99634],"type":"Point"}
}