{
  "type": "Feature",
  "properties": {
    "gn:admin1_code":"32.0",
    "gn:asciiname":"Dagalong",
    "gn:country_code":"CN",
    "gn:dem":2841,
    "gn:feature_class":"P",
    "gn:feature_code":"PPL",
    "gn:name":"Dagalong",
    "gn:population":0,
    "gn:timezone":"Asia/Shanghai",
    "iso:country":"CN",
    "name:zho_x_preferred":[
        "\u8fbe\u560e\u9686"
    ],
    "wof:name":"Dagalong",
    "wof:placetype":"locality"
},
  "geometry": {"coordinates":[99.0609,29.5845],"type":"Point"}
}