{
  "type": "Feature",
  "properties": {
    "gn:admin1_code":"7.0",
    "gn:asciiname":"Lingbian",
    "gn:country_code":"CN",
    "gn:dem":688,
    "gn:feature_class":"P",
    "gn:feature_code":"PPL",
    "gn:name":"Lingbian",
    "gn:population":0,
    "gn:timezone":"Asia/Shanghai",
    "iso:country":"CN",
    "name:zho_x_preferred":[
        "Lingbian"
    ],
    "name:zho_x_variant":[
        "\u5cad\u8fb9"
    ],
    "wof:name":"Lingbian",
    "wof:placetype":"locality"
},
  "geometry": {"coordinates":[118.77822999999999,26.35305],"type":"Point"}
}