{
  "type": "Feature",
  "properties": {
    "gn:admin1_code":"9.0",
    "gn:asciiname":"Dongniuzhuang",
    "gn:country_code":"CN",
    "gn:dem":232,
    "gn:feature_class":"P",
    "gn:feature_code":"PPL",
    "gn:name":"Dongniuzhuang",
    "gn:population":0,
    "gn:timezone":"Asia/Shanghai",
    "iso:country":"CN",
    "name:zho_x_preferred":[
        "\u4e1c\u725b\u5e84"
    ],
    "wof:name":"Dongniuzhuang",
    "wof:placetype":"locality"
},
  "geometry": {"coordinates":[112.52969,34.48359],"type":"Point"}
}