{
  "type": "Feature",
  "properties": {
    "gn:admin1_code":"3.0",
    "gn:asciiname":"Zhuxi",
    "gn:country_code":"CN",
    "gn:dem":82,
    "gn:feature_class":"P",
    "gn:feature_code":"PPL",
    "gn:name":"Zhuxi",
    "gn:population":0,
    "gn:timezone":"Asia/Shanghai",
    "iso:country":"CN",
    "name:ceb_x_preferred":[
        "Zhuxi"
    ],
    "name:nor_x_preferred":[
        "Zhuxi"
    ],
    "name:zho_x_preferred":[
        "\u7af9\u6eaa"
    ],
    "wof:name":"Zhuxi",
    "wof:placetype":"locality"
},
  "geometry": {"coordinates":[115.114,28.5321],"type":"Point"}
}