{
  "type": "Feature",
  "properties": {
    "gn:admin1_code":"14.0",
    "gn:asciiname":"Zakor",
    "gn:country_code":"CN",
    "gn:dem":4083,
    "gn:feature_class":"P",
    "gn:feature_code":"PPL",
    "gn:name":"Zakor",
    "gn:population":0,
    "gn:timezone":"Asia/Urumqi",
    "iso:country":"CN",
    "name:bod_x_preferred":[
        "Zakor"
    ],
    "name:zho_x_preferred":[
        "Zaguo"
    ],
    "name:zho_x_variant":[
        "\u6742\u679c",
        "Remulang Gongshe",
        "\u60f9\u6728\u6717\u516c\u793e"
    ],
    "wof:name":"Zakor",
    "wof:placetype":"locality"
},
  "geometry": {"coordinates":[91.90300000000001,28.903],"type":"Point"}
}