{
  "type": "Feature",
  "properties": {
    "gn:admin1_code":"09",
    "gn:asciiname":"Taiqiu",
    "gn:cc2":"CN",
    "gn:country_code":"CN",
    "gn:dem":40,
    "gn:feature_class":"P",
    "gn:feature_code":"PPL",
    "gn:name":"Taiqiu",
    "gn:population":0,
    "gn:timezone":"Asia/Shanghai",
    "iso:country":"CN",
    "name:und_x_variant":[
        "Ta-ch\u2019iu-chi",
        "Taiqiu"
    ],
    "wof:name":"Taiqiu",
    "wof:placetype":"locality"
},
  "geometry": {"coordinates":[116.29056,34.1075],"type":"Point"}
}