{
  "type": "Feature",
  "properties": {
    "gn:admin1_code":"21",
    "gn:asciiname":"Baitougangzi",
    "gn:cc2":"CN",
    "gn:country_code":"CN",
    "gn:dem":1171,
    "gn:feature_class":"P",
    "gn:feature_code":"PPL",
    "gn:name":"Baitougangzi",
    "gn:population":0,
    "gn:timezone":"Asia/Shanghai",
    "iso:country":"CN",
    "name:und_x_variant":[
        "Pai-t\u2019ou-kang-tzu",
        "Baitougangzi"
    ],
    "wof:name":"Baitougangzi",
    "wof:placetype":"locality"
},
  "geometry": {"coordinates":[106.35333,37.81889],"type":"Point"}
}