{
  "type": "Feature",
  "properties": {
    "gn:admin1_code":"25",
    "gn:asciiname":"Beijianxing Xicun",
    "gn:country_code":"CN",
    "gn:dem":59,
    "gn:feature_class":"P",
    "gn:feature_code":"PPL",
    "gn:name":"Beijianxing Xicun",
    "gn:population":0,
    "gn:timezone":"Asia/Shanghai",
    "iso:country":"CN",
    "name:zho_x_preferred":[
        "\u5317\u6e10\u5174\u897f\u6751"
    ],
    "wof:name":"Beijianxing Xicun",
    "wof:placetype":"locality"
},
  "geometry": {"coordinates":[116.917,35.4098],"type":"Point"}
}