{
  "type": "Feature",
  "properties": {
    "gn:admin1_code":"25",
    "gn:asciiname":"Shangyandian",
    "gn:country_code":"CN",
    "gn:dem":219,
    "gn:feature_class":"P",
    "gn:feature_code":"PPL",
    "gn:name":"Shangyandian",
    "gn:population":0,
    "gn:timezone":"Asia/Shanghai",
    "iso:country":"CN",
    "name:zho_x_preferred":[
        "\u4e0a\u76d0\u5e97"
    ],
    "wof:name":"Shangyandian",
    "wof:placetype":"locality"
},
  "geometry": {"coordinates":[117.54000000000001,35.829],"type":"Point"}
}