{
  "type": "Feature",
  "properties": {
    "gn:admin1_code":"11.0",
    "gn:asciiname":"Dalitang",
    "gn:country_code":"CN",
    "gn:dem":175,
    "gn:feature_class":"P",
    "gn:feature_code":"PPL",
    "gn:name":"Dalitang",
    "gn:population":0,
    "gn:timezone":"Asia/Shanghai",
    "iso:country":"CN",
    "name:zho_x_preferred":[
        "\u5927\u91cc\u5858"
    ],
    "wof:name":"Dalitang",
    "wof:placetype":"locality"
},
  "geometry": {"coordinates":[111.50454999999999,26.36608],"type":"Point"}
}