{
  "type": "Feature",
  "properties": {
    "gn:admin1_code":"24",
    "gn:asciiname":"Chengou",
    "gn:country_code":"CN",
    "gn:dem":882,
    "gn:feature_class":"P",
    "gn:feature_code":"PPL",
    "gn:name":"Chengou",
    "gn:population":0,
    "gn:timezone":"Asia/Shanghai",
    "iso:country":"CN",
    "name:und_x_variant":[
        "Ch\u2019en-kou",
        "Chengou"
    ],
    "name:zho_x_preferred":[
        "\u9648\u6c9f"
    ],
    "wof:name":"Chengou",
    "wof:placetype":"locality"
},
  "geometry": {"coordinates":[112.8134,35.57952],"type":"Point"}
}