{
  "type": "Feature",
  "properties": {
    "gn:admin1_code":"14",
    "gn:asciiname":"Dongra",
    "gn:country_code":"CN",
    "gn:dem":4832,
    "gn:feature_class":"P",
    "gn:feature_code":"PPL",
    "gn:name":"Dongra",
    "gn:population":0,
    "gn:timezone":"Asia/Urumqi",
    "iso:country":"CN",
    "name:bod_x_preferred":[
        "\u0f66\u0f9f\u0f7c\u0f44\u0f0b\u0f62\u0fad"
    ],
    "name:und_x_variant":[
        "Dongla"
    ],
    "name:zho_x_preferred":[
        "\u4e1c\u62c9"
    ],
    "wof:name":"Dongra",
    "wof:placetype":"locality"
},
  "geometry": {"coordinates":[90.80235,29.03456],"type":"Point"}
}