{
  "type": "Feature",
  "properties": {
    "gn:admin1_code":"30.0",
    "gn:asciiname":"Guanyin",
    "gn:country_code":"CN",
    "gn:dem":171,
    "gn:feature_class":"P",
    "gn:feature_code":"PPL",
    "gn:name":"Guanyin",
    "gn:population":0,
    "gn:timezone":"Asia/Shanghai",
    "iso:country":"CN",
    "name:zho_x_preferred":[
        "Guanyin"
    ],
    "name:zho_x_variant":[
        "\u89c2\u97f3"
    ],
    "wof:name":"Guanyin",
    "wof:placetype":"locality"
},
  "geometry": {"coordinates":[112.74833,23.80694],"type":"Point"}
}