{
  "type": "Feature",
  "properties": {
    "gn:admin1_code":"14.0",
    "gn:asciiname":"Tangga",
    "gn:country_code":"CN",
    "gn:dem":4152,
    "gn:feature_class":"P",
    "gn:feature_code":"PPL",
    "gn:name":"Tangga",
    "gn:population":0,
    "gn:timezone":"Asia/Urumqi",
    "iso:country":"CN",
    "name:zho_x_preferred":[
        "\u5858\u560e"
    ],
    "wof:name":"Tangga",
    "wof:placetype":"locality"
},
  "geometry": {"coordinates":[87.303,29.1196],"type":"Point"}
}