{
  "type": "Feature",
  "properties": {
    "gn:admin1_code":"26.0",
    "gn:asciiname":"Ganjintoucun",
    "gn:country_code":"CN",
    "gn:dem":1191,
    "gn:feature_class":"P",
    "gn:feature_code":"PPL",
    "gn:name":"Ganjintoucun",
    "gn:population":0,
    "gn:timezone":"Asia/Shanghai",
    "iso:country":"CN",
    "name:zho_x_preferred":[
        "\u7518\u6d25\u5934\u6751"
    ],
    "wof:name":"Ganjintoucun",
    "wof:placetype":"locality"
},
  "geometry": {"coordinates":[108.04697,35.20824],"type":"Point"}
}