{
  "type": "Feature",
  "properties": {
    "gn:admin1_code":"33.0",
    "gn:asciiname":"Shaolou",
    "gn:country_code":"CN",
    "gn:dem":320,
    "gn:feature_class":"P",
    "gn:feature_code":"PPL",
    "gn:name":"Shaolou",
    "gn:population":0,
    "gn:timezone":"Asia/Shanghai",
    "iso:country":"CN",
    "name:zho_x_preferred":[
        "\u54e8\u697c"
    ],
    "wof:name":"Shaolou",
    "wof:placetype":"locality"
},
  "geometry": {"coordinates":[105.92658,30.07116],"type":"Point"}
}