{
  "type": "Feature",
  "properties": {
    "gn:admin1_code":"14.0",
    "gn:asciiname":"Laji",
    "gn:country_code":"CN",
    "gn:dem":4330,
    "gn:feature_class":"P",
    "gn:feature_code":"PPL",
    "gn:name":"Laji",
    "gn:population":0,
    "gn:timezone":"Asia/Shanghai",
    "iso:country":"CN",
    "name:zho_x_preferred":[
        "\u62c9\u5409"
    ],
    "wof:name":"Laji",
    "wof:placetype":"locality"
},
  "geometry": {"coordinates":[79.91115000000001,33.18209],"type":"Point"}
}