{
  "type": "Feature",
  "properties": {
    "gn:admin1_code":"3.0",
    "gn:asciiname":"Zuojia Fangxinju",
    "gn:country_code":"CN",
    "gn:dem":36,
    "gn:feature_class":"P",
    "gn:feature_code":"PPL",
    "gn:name":"Zuojia Fangxinju",
    "gn:population":0,
    "gn:timezone":"Asia/Shanghai",
    "iso:country":"CN",
    "name:und_x_variant":[
        "\u5de6\u5bb6\u574a\u65b0\u5c45"
    ],
    "wof:name":"Zuojia Fangxinju",
    "wof:placetype":"locality"
},
  "geometry": {"coordinates":[115.42059,28.49621],"type":"Point"}
}