{
  "type": "Feature",
  "properties": {
    "gn:admin1_code":"16",
    "gn:asciiname":"Jinshanli",
    "gn:country_code":"CN",
    "gn:dem":187,
    "gn:feature_class":"P",
    "gn:feature_code":"PPL",
    "gn:name":"Jinshanli",
    "gn:population":0,
    "gn:timezone":"Asia/Shanghai",
    "iso:country":"CN",
    "name:zho_x_preferred":[
        "\u7981\u5c71\u91cc"
    ],
    "wof:name":"Jinshanli",
    "wof:placetype":"locality"
},
  "geometry": {"coordinates":[110.94499999999999,25.9833],"type":"Point"}
}