{
  "type": "Feature",
  "properties": {
    "gn:admin1_code":"8.0",
    "gn:asciiname":"Dongmingcun",
    "gn:country_code":"CN",
    "gn:dem":115,
    "gn:feature_class":"P",
    "gn:feature_code":"PPL",
    "gn:name":"Dongmingcun",
    "gn:population":0,
    "gn:timezone":"Asia/Shanghai",
    "iso:country":"CN",
    "name:zho_x_preferred":[
        "\u4e1c\u660e\u6751"
    ],
    "wof:name":"Dongmingcun",
    "wof:placetype":"locality"
},
  "geometry": {"coordinates":[131.92781000000002,45.56973],"type":"Point"}
}