{
  "type": "Feature",
  "properties": {
    "gn:admin1_code":"9",
    "gn:asciiname":"Dongliubei",
    "gn:country_code":"CN",
    "gn:dem":300,
    "gn:feature_class":"P",
    "gn:feature_code":"PPL",
    "gn:name":"Dongliubei",
    "gn:population":0,
    "gn:timezone":"Asia/Shanghai",
    "iso:country":"CN",
    "name:zho_x_preferred":[
        "\u4e1c\u5218\u7891"
    ],
    "wof:name":"Dongliubei",
    "wof:placetype":"locality"
},
  "geometry": {"coordinates":[113.1951,34.40338],"type":"Point"}
}