{
  "type": "Feature",
  "properties": {
    "gn:admin1_code":"32.0",
    "gn:asciiname":"Mocaotian",
    "gn:country_code":"CN",
    "gn:dem":1576,
    "gn:feature_class":"P",
    "gn:feature_code":"PPL",
    "gn:name":"Mocaotian",
    "gn:population":0,
    "gn:timezone":"Asia/Shanghai",
    "iso:country":"CN",
    "name:zho_x_preferred":[
        "\u78e8\u69fd\u7530"
    ],
    "wof:name":"Mocaotian",
    "wof:placetype":"locality"
},
  "geometry": {"coordinates":[102.14959,26.77884],"type":"Point"}
}