{
  "type": "Feature",
  "properties": {
    "gn:admin1_code":"14.0",
    "gn:asciiname":"Renqinggang",
    "gn:country_code":"CN",
    "gn:dem":3477,
    "gn:feature_class":"P",
    "gn:feature_code":"PPLF",
    "gn:name":"Renqinggang",
    "gn:population":0,
    "gn:timezone":"Asia/Urumqi",
    "iso:country":"CN",
    "name:bod_x_preferred":[
        "Rinq\u00eangang"
    ],
    "name:zho_x_preferred":[
        "Renqinggang"
    ],
    "name:zho_x_variant":[
        "\u4ec1\u9752\u5c97",
        "Xiayadong Qu",
        "\u4e0b\u4e9a\u4e1c\u533a"
    ],
    "wof:name":"Renqinggang",
    "wof:placetype":"locality"
},
  "geometry": {"coordinates":[88.91,27.41],"type":"Point"}
}