{
  "type": "Feature",
  "properties": {
    "gn:admin1_code":"13",
    "gn:asciiname":"Moyidong Qiongkanerzi",
    "gn:country_code":"CN",
    "gn:dem":478,
    "gn:feature_class":"P",
    "gn:feature_code":"PPL",
    "gn:name":"Moyidong Qiongkanerzi",
    "gn:population":0,
    "gn:timezone":"Asia/Urumqi",
    "iso:country":"CN",
    "name:und_x_variant":[
        "\u83ab\u4f9d\u51ac\u743c\u574e\u513f\u5b5c"
    ],
    "wof:name":"Moyidong Qiongkanerzi",
    "wof:placetype":"locality"
},
  "geometry": {"coordinates":[90.68237000000001,43.00366],"type":"Point"}
}