{
  "type": "Feature",
  "properties": {
    "gn:admin1_code":"20",
    "gn:asciiname":"Xil",
    "gn:cc2":"CN",
    "gn:country_code":"CN",
    "gn:dem":987,
    "gn:feature_class":"P",
    "gn:feature_code":"PPL",
    "gn:name":"Xil",
    "gn:population":0,
    "gn:timezone":"Asia/Shanghai",
    "iso:country":"CN",
    "name:und_x_variant":[
        "Hsi-li",
        "Xil"
    ],
    "wof:name":"Xil",
    "wof:placetype":"locality"
},
  "geometry": {"coordinates":[112.13861,43.46972],"type":"Point"}
}