{
  "type": "Feature",
  "properties": {
    "gn:admin1_code":"30",
    "gn:asciiname":"Huguang",
    "gn:country_code":"CN",
    "gn:dem":30,
    "gn:feature_class":"P",
    "gn:feature_code":"PPLA4",
    "gn:name":"Huguang",
    "gn:population":0,
    "gn:timezone":"Asia/Urumqi",
    "iso:country":"CN",
    "name:ces_x_preferred":[
        "Chu-kuang"
    ],
    "name:fra_x_preferred":[
        "Huguang"
    ],
    "name:ind_x_preferred":[
        "Huguang"
    ],
    "name:jpn_x_preferred":[
        "\u6e56\u5e83\u7701"
    ],
    "name:nor_x_preferred":[
        "Huguang"
    ],
    "name:pol_x_preferred":[
        "Huguang"
    ],
    "name:rus_x_preferred":[
        "\u0425\u0443\u0433\u0443\u0430\u043d"
    ],
    "name:swe_x_preferred":[
        "Huguang"
    ],
    "name:und_x_variant":[
        "Huguang Zhen",
        "\u6e56\u5149\u9547"
    ],
    "name:zho_x_preferred":[
        "\u6e56\u5149"
    ],
    "wof:name":"Huguang",
    "wof:placetype":"locality"
},
  "geometry": {"coordinates":[110.28872,21.12582],"type":"Point"}
}