{
  "type": "Feature",
  "properties": {
    "gn:admin1_code":"24.0",
    "gn:asciiname":"Dongyuan",
    "gn:country_code":"CN",
    "gn:dem":432,
    "gn:feature_class":"P",
    "gn:feature_code":"PPL",
    "gn:name":"Dongyuan",
    "gn:population":0,
    "gn:timezone":"Asia/Shanghai",
    "iso:country":"CN",
    "name:ceb_x_preferred":[
        "Dongyuan"
    ],
    "name:deu_x_preferred":[
        "Dongyuan"
    ],
    "name:nor_x_preferred":[
        "Dongyuan"
    ],
    "name:und_x_variant":[
        "\u4e1c\u9662"
    ],
    "name:zho_x_preferred":[
        "\u4e1c\u9662"
    ],
    "wof:name":"Dongyuan",
    "wof:placetype":"locality"
},
  "geometry": {"coordinates":[111.3779,35.99533],"type":"Point"}
}