{
  "type": "Feature",
  "properties": {
    "gn:admin1_code":"16.0",
    "gn:asciiname":"Shiyanshan",
    "gn:country_code":"CN",
    "gn:dem":302,
    "gn:feature_class":"P",
    "gn:feature_code":"PPL",
    "gn:name":"Shiyanshan",
    "gn:population":0,
    "gn:timezone":"Asia/Shanghai",
    "iso:country":"CN",
    "name:zho_x_preferred":[
        "\u77f3\u773c\u5c71"
    ],
    "wof:name":"Shiyanshan",
    "wof:placetype":"locality"
},
  "geometry": {"coordinates":[111.27800000000001,24.993],"type":"Point"}
}