{
  "type": "Feature",
  "properties": {
    "gn:admin1_code":"25",
    "gn:asciiname":"Niujia",
    "gn:country_code":"CN",
    "gn:dem":9,
    "gn:feature_class":"P",
    "gn:feature_code":"PPL",
    "gn:name":"Niujia",
    "gn:population":0,
    "gn:timezone":"Asia/Shanghai",
    "iso:country":"CN",
    "name:zho_x_preferred":[
        "\u725b\u5bb6"
    ],
    "wof:name":"Niujia",
    "wof:placetype":"locality"
},
  "geometry": {"coordinates":[118.30938999999999,37.41329],"type":"Point"}
}