{
  "type": "Feature",
  "properties": {
    "gn:admin1_code":"21.0",
    "gn:asciiname":"Anqiaobu",
    "gn:country_code":"CN",
    "gn:dem":2095,
    "gn:feature_class":"P",
    "gn:feature_code":"PPL",
    "gn:name":"Anqiaobu",
    "gn:population":0,
    "gn:timezone":"Asia/Shanghai",
    "iso:country":"CN",
    "name:zho_x_preferred":[
        "\u5b89\u6865\u5821"
    ],
    "wof:name":"Anqiaobu",
    "wof:placetype":"locality"
},
  "geometry": {"coordinates":[105.586,36.5194],"type":"Point"}
}