{
  "type": "Feature",
  "properties": {
    "gn:admin1_code":"9.0",
    "gn:asciiname":"Nanhujia",
    "gn:country_code":"CN",
    "gn:dem":157,
    "gn:feature_class":"P",
    "gn:feature_code":"PPL",
    "gn:name":"Nanhujia",
    "gn:population":0,
    "gn:timezone":"Asia/Shanghai",
    "iso:country":"CN",
    "name:zho_x_preferred":[
        "\u5357\u80e1\u5bb6"
    ],
    "wof:name":"Nanhujia",
    "wof:placetype":"locality"
},
  "geometry": {"coordinates":[114.73353,31.57789],"type":"Point"}
}