{
  "type": "Feature",
  "properties": {
    "gn:admin1_code":"29.0",
    "gn:asciiname":"Dahebian",
    "gn:country_code":"CN",
    "gn:dem":1082,
    "gn:feature_class":"P",
    "gn:feature_code":"PPL",
    "gn:name":"Dahebian",
    "gn:population":0,
    "gn:timezone":"Asia/Shanghai",
    "iso:country":"CN",
    "name:zho_x_preferred":[
        "\u5927\u6cb3\u8fb9"
    ],
    "wof:name":"Dahebian",
    "wof:placetype":"locality"
},
  "geometry": {"coordinates":[100.44,23.6839],"type":"Point"}
}