{
  "type": "Feature",
  "properties": {
    "gn:admin1_code":"3.0",
    "gn:asciiname":"Junzili",
    "gn:country_code":"CN",
    "gn:dem":208,
    "gn:feature_class":"P",
    "gn:feature_code":"PPL",
    "gn:name":"Junzili",
    "gn:population":0,
    "gn:timezone":"Asia/Shanghai",
    "iso:country":"CN",
    "name:und_x_variant":[
        "\u541b\u5b50\u91cc"
    ],
    "wof:name":"Junzili",
    "wof:placetype":"locality"
},
  "geometry": {"coordinates":[116.98981999999999,27.23039],"type":"Point"}
}