{
  "type": "Feature",
  "properties": {
    "gn:admin1_code":"5.0",
    "gn:asciiname":"Xihuojiatun",
    "gn:country_code":"CN",
    "gn:dem":159,
    "gn:feature_class":"P",
    "gn:feature_code":"PPL",
    "gn:name":"Xihuojiatun",
    "gn:population":0,
    "gn:timezone":"Asia/Shanghai",
    "iso:country":"CN",
    "name:zho_x_preferred":[
        "\u897f\u970d\u5bb6\u5c6f"
    ],
    "wof:name":"Xihuojiatun",
    "wof:placetype":"locality"
},
  "geometry": {"coordinates":[124.28592999999999,43.56774],"type":"Point"}
}