{
  "type": "Feature",
  "properties": {
    "gn:admin1_code":"2.0",
    "gn:asciiname":"Xiadanxi",
    "gn:country_code":"CN",
    "gn:dem":245,
    "gn:feature_class":"P",
    "gn:feature_code":"PPL",
    "gn:name":"Xiadanxi",
    "gn:population":0,
    "gn:timezone":"Asia/Shanghai",
    "iso:country":"CN",
    "name:zho_x_preferred":[
        "\u4e0b\u4e39\u6eaa"
    ],
    "wof:name":"Xiadanxi",
    "wof:placetype":"locality"
},
  "geometry": {"coordinates":[120.87012,29.30079000000001],"type":"Point"}
}