{
  "type": "Feature",
  "properties": {
    "gn:admin1_code":"32.0",
    "gn:asciiname":"Mawo",
    "gn:country_code":"CN",
    "gn:dem":3244,
    "gn:feature_class":"P",
    "gn:feature_code":"PPL",
    "gn:name":"Mawo",
    "gn:population":0,
    "gn:timezone":"Asia/Shanghai",
    "iso:country":"CN",
    "name:zho_x_preferred":[
        "\u9ebb\u7a9d"
    ],
    "wof:name":"Mawo",
    "wof:placetype":"locality"
},
  "geometry": {"coordinates":[101.82548,28.9602],"type":"Point"}
}