{
  "type": "Feature",
  "properties": {
    "gn:admin1_code":"8.0",
    "gn:asciiname":"Yonghecun",
    "gn:country_code":"CN",
    "gn:dem":57,
    "gn:feature_class":"P",
    "gn:feature_code":"PPL",
    "gn:name":"Yonghecun",
    "gn:population":0,
    "gn:timezone":"Asia/Shanghai",
    "iso:country":"CN",
    "name:zho_x_preferred":[
        "\u6c38\u548c\u6751"
    ],
    "wof:name":"Yonghecun",
    "wof:placetype":"locality"
},
  "geometry": {"coordinates":[133.60442,46.14925],"type":"Point"}
}