{
  "type": "Feature",
  "properties": {
    "gn:admin1_code":"26.0",
    "gn:asciiname":"Yangtianzhai",
    "gn:country_code":"CN",
    "gn:dem":341,
    "gn:feature_class":"P",
    "gn:feature_code":"PPL",
    "gn:name":"Yangtianzhai",
    "gn:population":0,
    "gn:timezone":"Asia/Shanghai",
    "iso:country":"CN",
    "name:zho_x_preferred":[
        "\u6837\u7530\u5be8"
    ],
    "wof:name":"Yangtianzhai",
    "wof:placetype":"locality"
},
  "geometry": {"coordinates":[109.67134,34.52411],"type":"Point"}
}