{
  "type": "Feature",
  "properties": {
    "gn:admin1_code":"15.0",
    "gn:asciiname":"Xifenzhi",
    "gn:country_code":"CN",
    "gn:dem":1701,
    "gn:feature_class":"P",
    "gn:feature_code":"PPL",
    "gn:name":"Xifenzhi",
    "gn:population":0,
    "gn:timezone":"Asia/Shanghai",
    "iso:country":"CN",
    "name:zho_x_preferred":[
        "\u897f\u5206\u652f"
    ],
    "wof:name":"Xifenzhi",
    "wof:placetype":"locality"
},
  "geometry": {"coordinates":[103.70399999999999,37.5953],"type":"Point"}
}