{
  "type": "Feature",
  "properties": {
    "gn:admin1_code":"12.0",
    "gn:asciiname":"Fanqiying",
    "gn:country_code":"CN",
    "gn:dem":58,
    "gn:feature_class":"P",
    "gn:feature_code":"PPL",
    "gn:name":"Fanqiying",
    "gn:population":0,
    "gn:timezone":"Asia/Shanghai",
    "iso:country":"CN",
    "name:zho_x_preferred":[
        "\u8303\u65d7\u8425"
    ],
    "wof:name":"Fanqiying",
    "wof:placetype":"locality"
},
  "geometry": {"coordinates":[112.34117999999999,31.7318],"type":"Point"}
}