{
  "type": "Feature",
  "properties": {
    "gn:admin1_code":"14.0",
    "gn:asciiname":"Bumeicun",
    "gn:country_code":"CN",
    "gn:dem":3651,
    "gn:feature_class":"P",
    "gn:feature_code":"PPL",
    "gn:name":"Bumeicun",
    "gn:population":0,
    "gn:timezone":"Asia/Urumqi",
    "iso:country":"CN",
    "name:zho_x_preferred":[
        "\u5e03\u7f8e\u6751"
    ],
    "wof:name":"Bumeicun",
    "wof:placetype":"locality"
},
  "geometry": {"coordinates":[91.6806,29.30718],"type":"Point"}
}