{
  "type": "Feature",
  "properties": {
    "gn:admin1_code":"26.0",
    "gn:asciiname":"Gongjiagou",
    "gn:country_code":"CN",
    "gn:dem":1227,
    "gn:feature_class":"P",
    "gn:feature_code":"PPL",
    "gn:name":"Gongjiagou",
    "gn:population":0,
    "gn:timezone":"Asia/Shanghai",
    "iso:country":"CN",
    "name:und_x_variant":[
        "\u5de9\u5bb6\u6c9f"
    ],
    "wof:name":"Gongjiagou",
    "wof:placetype":"locality"
},
  "geometry": {"coordinates":[105.87087,33.33535999999999],"type":"Point"}
}