{
  "type": "Feature",
  "properties": {
    "gn:admin1_code":"25.0",
    "gn:asciiname":"Cenlijiacun",
    "gn:country_code":"CN",
    "gn:dem":12,
    "gn:feature_class":"P",
    "gn:feature_code":"PPL",
    "gn:name":"Cenlijiacun",
    "gn:population":0,
    "gn:timezone":"Asia/Shanghai",
    "iso:country":"CN",
    "name:zho_x_preferred":[
        "\u5c91\u674e\u5bb6\u6751"
    ],
    "wof:name":"Cenlijiacun",
    "wof:placetype":"locality"
},
  "geometry": {"coordinates":[119.82701000000002,36.63618],"type":"Point"}
}