{
  "type": "Feature",
  "properties": {
    "gn:admin1_code":"7.0",
    "gn:asciiname":"Neitianliaokeng",
    "gn:country_code":"CN",
    "gn:dem":415,
    "gn:feature_class":"P",
    "gn:feature_code":"PPL",
    "gn:name":"Neitianliaokeng",
    "gn:population":0,
    "gn:timezone":"Asia/Shanghai",
    "iso:country":"CN",
    "name:zho_x_preferred":[
        "\u5185\u7530\u5bee\u5751"
    ],
    "wof:name":"Neitianliaokeng",
    "wof:placetype":"locality"
},
  "geometry": {"coordinates":[116.22857,25.60438],"type":"Point"}
}