{
  "type": "Feature",
  "properties": {
    "gn:admin1_code":"9.0",
    "gn:asciiname":"Penguocun",
    "gn:country_code":"CN",
    "gn:dem":124,
    "gn:feature_class":"P",
    "gn:feature_code":"PPL",
    "gn:name":"Penguocun",
    "gn:population":0,
    "gn:timezone":"Asia/Shanghai",
    "iso:country":"CN",
    "name:zho_x_preferred":[
        "\u76c6\u90ed\u6751"
    ],
    "wof:name":"Penguocun",
    "wof:placetype":"locality"
},
  "geometry": {"coordinates":[113.03661,33.78713],"type":"Point"}
}