{
  "type": "Feature",
  "properties": {
    "gn:admin1_code":"32.0",
    "gn:asciiname":"Xiangjiazui",
    "gn:country_code":"CN",
    "gn:dem":662,
    "gn:feature_class":"P",
    "gn:feature_code":"PPL",
    "gn:name":"Xiangjiazui",
    "gn:population":0,
    "gn:timezone":"Asia/Shanghai",
    "iso:country":"CN",
    "name:zho_x_preferred":[
        "\u54cd\u5bb6\u5480"
    ],
    "wof:name":"Xiangjiazui",
    "wof:placetype":"locality"
},
  "geometry": {"coordinates":[104.33925000000001,29.58189],"type":"Point"}
}