{
  "type": "Feature",
  "properties": {
    "gn:admin1_code":"32",
    "gn:asciiname":"Mai'erma",
    "gn:country_code":"CN",
    "gn:dem":3503,
    "gn:feature_class":"P",
    "gn:feature_code":"PPL",
    "gn:name":"Mai\u2019erma",
    "gn:population":0,
    "gn:timezone":"Asia/Shanghai",
    "iso:country":"CN",
    "name:und_x_variant":[
        "M\u00earuma"
    ],
    "name:zho_x_preferred":[
        "\u9ea6\u5c14\u739b"
    ],
    "name:zho_x_variant":[
        "Mai\u2019erma"
    ],
    "wof:name":"Mai'erma",
    "wof:placetype":"locality"
},
  "geometry": {"coordinates":[101.96917000000001,32.87733],"type":"Point"}
}