{
  "type": "Feature",
  "properties": {
    "gn:admin1_code":"14",
    "gn:asciiname":"Qianggedang",
    "gn:country_code":"CN",
    "gn:dem":3410,
    "gn:feature_class":"P",
    "gn:feature_code":"PPL",
    "gn:name":"Qianggedang",
    "gn:population":0,
    "gn:timezone":"Asia/Urumqi",
    "iso:country":"CN",
    "name:zho_x_preferred":[
        "\u67aa\u683c\u6321"
    ],
    "wof:name":"Qianggedang",
    "wof:placetype":"locality"
},
  "geometry": {"coordinates":[88.90389999999999,27.4119],"type":"Point"}
}