{
  "type": "Feature",
  "properties": {
    "gn:admin1_code":"30.0",
    "gn:asciiname":"Baowu",
    "gn:country_code":"CN",
    "gn:dem":192,
    "gn:feature_class":"P",
    "gn:feature_code":"PPL",
    "gn:name":"Baowu",
    "gn:population":0,
    "gn:timezone":"Asia/Shanghai",
    "iso:country":"CN",
    "name:zho_x_preferred":[
        "Baowu"
    ],
    "name:zho_x_variant":[
        "\u5305\u5c4b"
    ],
    "wof:name":"Baowu",
    "wof:placetype":"locality"
},
  "geometry": {"coordinates":[114.08965999999999,24.53543],"type":"Point"}
}