{
  "type": "Feature",
  "properties": {
    "gn:admin1_code":"0.0",
    "gn:asciiname":"Mo-lang-p'o",
    "gn:country_code":"CN",
    "gn:dem":1020,
    "gn:feature_class":"P",
    "gn:feature_code":"PPL",
    "gn:name":"Mo-lang-p\u2019o",
    "gn:population":0,
    "gn:timezone":"Asia/Shanghai",
    "iso:country":"CN",
    "wof:name":"Mo-lang-p'o",
    "wof:placetype":"locality"
},
  "geometry": {"coordinates":[101.91133000000001,23.56114],"type":"Point"}
}