{
  "type": "Feature",
  "properties": {
    "gn:admin1_code":"4.0",
    "gn:asciiname":"Oumin Wuzu",
    "gn:country_code":"CN",
    "gn:dem":-2,
    "gn:feature_class":"P",
    "gn:feature_code":"PPLF",
    "gn:name":"Oumin Wuzu",
    "gn:population":0,
    "gn:timezone":"Asia/Shanghai",
    "iso:country":"CN",
    "name:zho_x_preferred":[
        "\u8026\u6c11\u4e94\u7ec4"
    ],
    "wof:name":"Oumin Wuzu",
    "wof:placetype":"locality"
},
  "geometry": {"coordinates":[120.175,33.8667],"type":"Point"}
}