{
  "type": "Feature",
  "properties": {
    "gn:admin1_code":"29.0",
    "gn:asciiname":"Agui",
    "gn:country_code":"CN",
    "gn:dem":2157,
    "gn:feature_class":"P",
    "gn:feature_code":"PPL",
    "gn:name":"Agui",
    "gn:population":0,
    "gn:timezone":"Asia/Shanghai",
    "iso:country":"CN",
    "name:fra_x_preferred":[
        "Agui"
    ],
    "name:jpn_x_preferred":[
        "\u30a2\u30b0\u30a4"
    ],
    "name:rus_x_preferred":[
        "\u0410\u0433\u0443\u0439"
    ],
    "name:tha_x_preferred":[
        "\u0e2d\u0e32\u0e01\u0e38\u0e49\u0e22"
    ],
    "name:vie_x_preferred":[
        "A Qu\u1ebf"
    ],
    "name:zho_x_preferred":[
        "\u963f\u8d35"
    ],
    "wof:name":"Agui",
    "wof:placetype":"locality"
},
  "geometry": {"coordinates":[104.16200000000001,25.116],"type":"Point"}
}