{
  "type": "Feature",
  "properties": {
    "gn:admin1_code":"29.0",
    "gn:asciiname":"Agui",
    "gn:country_code":"CN",
    "gn:dem":2157,
    "gn:feature_class":"P",
    "gn:feature_code":"PPL",
    "gn:name":"Agui",
    "gn:population":0,
    "gn:timezone":"Asia/Shanghai",
    "iso:country":"CN",
    "name:zho_x_preferred":[
        "\u963f\u8d35"
    ],
    "wof:name":"Agui",
    "wof:placetype":"locality"
},
  "geometry": {"coordinates":[104.16200000000001,25.116],"type":"Point"}
}