{
  "type": "Feature",
  "properties": {
    "gn:admin1_code":"30",
    "gn:asciiname":"Dapo",
    "gn:country_code":"CN",
    "gn:dem":43,
    "gn:feature_class":"P",
    "gn:feature_code":"PPL",
    "gn:name":"Dapo",
    "gn:population":0,
    "gn:timezone":"Asia/Urumqi",
    "iso:country":"CN",
    "name:zho_x_preferred":[
        "\u5927\u5761"
    ],
    "wof:name":"Dapo",
    "wof:placetype":"locality"
},
  "geometry": {"coordinates":[110.55923,21.9525],"type":"Point"}
}