{
  "type": "Feature",
  "properties": {
    "gn:admin1_code":"32.0",
    "gn:asciiname":"Eduo",
    "gn:country_code":"CN",
    "gn:dem":2877,
    "gn:feature_class":"P",
    "gn:feature_code":"PPL",
    "gn:name":"Eduo",
    "gn:population":0,
    "gn:timezone":"Asia/Shanghai",
    "iso:country":"CN",
    "name:zho_x_preferred":[
        "\u4fc4\u591a"
    ],
    "wof:name":"Eduo",
    "wof:placetype":"locality"
},
  "geometry": {"coordinates":[103.12971,32.29026],"type":"Point"}
}