{
  "type": "Feature",
  "properties": {
    "gn:admin1_code":"10.0",
    "gn:asciiname":"Canshakou",
    "gn:country_code":"CN",
    "gn:dem":5,
    "gn:feature_class":"P",
    "gn:feature_code":"PPL",
    "gn:name":"Canshakou",
    "gn:population":0,
    "gn:timezone":"Asia/Shanghai",
    "iso:country":"CN",
    "name:zho_x_preferred":[
        "\u8695\u6c99\u53e3"
    ],
    "wof:name":"Canshakou",
    "wof:placetype":"locality"
},
  "geometry": {"coordinates":[118.62076,39.22853],"type":"Point"}
}