{
  "type": "Feature",
  "properties": {
    "gn:admin1_code":"16.0",
    "gn:asciiname":"Naba",
    "gn:country_code":"CN",
    "gn:dem":139,
    "gn:feature_class":"P",
    "gn:feature_code":"PPL",
    "gn:name":"Naba",
    "gn:population":0,
    "gn:timezone":"Asia/Shanghai",
    "iso:country":"CN",
    "name:ceb_x_preferred":[
        "Naba"
    ],
    "name:fra_x_preferred":[
        "Naba"
    ],
    "name:spa_x_preferred":[
        "Naba"
    ],
    "name:swe_x_preferred":[
        "Naba"
    ],
    "name:zho_x_preferred":[
        "\u90a3\u5df4"
    ],
    "wof:name":"Naba",
    "wof:placetype":"locality"
},
  "geometry": {"coordinates":[107.938,22.3209],"type":"Point"}
}