{
  "type": "Feature",
  "properties": {
    "gn:admin1_code":"15.0",
    "gn:asciiname":"Yongfengbu Dongcun",
    "gn:country_code":"CN",
    "gn:dem":1710,
    "gn:feature_class":"P",
    "gn:feature_code":"PPL",
    "gn:name":"Yongfengbu Dongcun",
    "gn:population":0,
    "gn:timezone":"Asia/Shanghai",
    "iso:country":"CN",
    "name:zho_x_preferred":[
        "\u6c38\u4e30\u5821\u4e1c\u6751"
    ],
    "wof:name":"Yongfengbu Dongcun",
    "wof:placetype":"locality"
},
  "geometry": {"coordinates":[103.03700000000001,37.6685],"type":"Point"}
}