{
  "type": "Feature",
  "properties": {
    "gn:admin1_code":"25",
    "gn:asciiname":"Danuanyu",
    "gn:country_code":"CN",
    "gn:dem":281,
    "gn:feature_class":"P",
    "gn:feature_code":"PPL",
    "gn:name":"Danuanyu",
    "gn:population":0,
    "gn:timezone":"Asia/Shanghai",
    "iso:country":"CN",
    "name:zho_x_preferred":[
        "\u5927\u6696\u5cea"
    ],
    "wof:name":"Danuanyu",
    "wof:placetype":"locality"
},
  "geometry": {"coordinates":[118.505,35.9953],"type":"Point"}
}