{
  "type": "Feature",
  "properties": {
    "gn:admin1_code":"3.0",
    "gn:asciiname":"Lingbei",
    "gn:country_code":"CN",
    "gn:dem":107,
    "gn:feature_class":"P",
    "gn:feature_code":"PPL",
    "gn:name":"Lingbei",
    "gn:population":0,
    "gn:timezone":"Asia/Shanghai",
    "iso:country":"CN",
    "name:und_x_variant":[
        "\u5cad\u80cc"
    ],
    "wof:name":"Lingbei",
    "wof:placetype":"locality"
},
  "geometry": {"coordinates":[115.55672,27.76748],"type":"Point"}
}