{
  "type": "Feature",
  "properties": {
    "gn:admin1_code":"24.0",
    "gn:asciiname":"Luoliwan",
    "gn:country_code":"CN",
    "gn:dem":1029,
    "gn:feature_class":"P",
    "gn:feature_code":"PPL",
    "gn:name":"Luoliwan",
    "gn:population":0,
    "gn:timezone":"Asia/Shanghai",
    "iso:country":"CN",
    "name:und_x_variant":[
        "\u843d\u91cc\u6e7e"
    ],
    "name:zho_x_preferred":[
        "\u843d\u91cc\u6e7e"
    ],
    "wof:name":"Luoliwan",
    "wof:placetype":"locality"
},
  "geometry": {"coordinates":[113.21122,39.98207],"type":"Point"}
}