{
  "type": "Feature",
  "properties": {
    "gn:admin1_code":"10",
    "gn:asciiname":"Wushiqihao",
    "gn:country_code":"CN",
    "gn:dem":1189,
    "gn:feature_class":"P",
    "gn:feature_code":"PPLF",
    "gn:name":"Wushiqihao",
    "gn:population":0,
    "gn:timezone":"Asia/Shanghai",
    "iso:country":"CN",
    "name:und_x_variant":[
        "Wu-shih-ch\u2019i-hao"
    ],
    "name:zho_x_preferred":[
        "\u4e94\u5341\u4e03\u53f7"
    ],
    "wof:name":"Wushiqihao",
    "wof:placetype":"locality"
},
  "geometry": {"coordinates":[117.3075,42.1275],"type":"Point"}
}