{
  "type": "Feature",
  "properties": {
    "gn:admin1_code":"14.0",
    "gn:asciiname":"Niewocun",
    "gn:country_code":"CN",
    "gn:dem":3768,
    "gn:feature_class":"P",
    "gn:feature_code":"PPL",
    "gn:name":"Niewocun",
    "gn:population":0,
    "gn:timezone":"Asia/Urumqi",
    "iso:country":"CN",
    "name:zho_x_preferred":[
        "\u8042\u7a9d\u6751"
    ],
    "wof:name":"Niewocun",
    "wof:placetype":"locality"
},
  "geometry": {"coordinates":[97.51090000000001,30.78584],"type":"Point"}
}