{
  "type": "Feature",
  "properties": {
    "gn:admin1_code":"4.0",
    "gn:asciiname":"Huchengcun",
    "gn:country_code":"CN",
    "gn:dem":-1,
    "gn:feature_class":"P",
    "gn:feature_code":"PPL",
    "gn:name":"Huchengcun",
    "gn:population":0,
    "gn:timezone":"Asia/Shanghai",
    "iso:country":"CN",
    "name:zho_x_preferred":[
        "\u6e56\u6210\u6751"
    ],
    "wof:name":"Huchengcun",
    "wof:placetype":"locality"
},
  "geometry": {"coordinates":[119.74847,33.52368],"type":"Point"}
}