{
  "type": "Feature",
  "properties": {
    "gn:admin1_code":"11.0",
    "gn:asciiname":"Kangxi",
    "gn:country_code":"CN",
    "gn:dem":218,
    "gn:feature_class":"P",
    "gn:feature_code":"PPL",
    "gn:name":"Kangxi",
    "gn:population":0,
    "gn:timezone":"Asia/Shanghai",
    "iso:country":"CN",
    "name:zho_x_preferred":[
        "\u5eb7\u6eaa"
    ],
    "wof:name":"Kangxi",
    "wof:placetype":"locality"
},
  "geometry": {"coordinates":[109.75432000000001,27.1594],"type":"Point"}
}