{
  "type": "Feature",
  "properties": {
    "gn:admin1_code":"04",
    "gn:asciiname":"Wanpingcun",
    "gn:country_code":"CN",
    "gn:dem":4,
    "gn:feature_class":"P",
    "gn:feature_code":"PPL",
    "gn:name":"Wanpingcun",
    "gn:population":0,
    "gn:timezone":"Asia/Shanghai",
    "iso:country":"CN",
    "name:zho_x_preferred":[
        "\u5b9b\u5e73\u6751"
    ],
    "wof:name":"Wanpingcun",
    "wof:placetype":"locality"
},
  "geometry": {"coordinates":[121.36548000000001,32.0061],"type":"Point"}
}