{
  "type": "Feature",
  "properties": {
    "gn:admin1_code":"32.0",
    "gn:asciiname":"Oujia Wanzi",
    "gn:country_code":"CN",
    "gn:dem":1730,
    "gn:feature_class":"P",
    "gn:feature_code":"PPL",
    "gn:name":"Oujia Wanzi",
    "gn:population":0,
    "gn:timezone":"Asia/Shanghai",
    "iso:country":"CN",
    "name:zho_x_preferred":[
        "\u6b27\u5bb6\u6e7e\u5b50"
    ],
    "wof:name":"Oujia Wanzi",
    "wof:placetype":"locality"
},
  "geometry": {"coordinates":[101.538,28.0611],"type":"Point"}
}