{
  "type": "Feature",
  "properties": {
    "gn:admin1_code":"24.0",
    "gn:asciiname":"Zhujiayucun",
    "gn:country_code":"CN",
    "gn:dem":1069,
    "gn:feature_class":"P",
    "gn:feature_code":"PPL",
    "gn:name":"Zhujiayucun",
    "gn:population":0,
    "gn:timezone":"Asia/Shanghai",
    "iso:country":"CN",
    "name:zho_x_preferred":[
        "\u6731\u5bb6\u5cea\u6751"
    ],
    "wof:name":"Zhujiayucun",
    "wof:placetype":"locality"
},
  "geometry": {"coordinates":[110.90738,36.8023],"type":"Point"}
}