{
  "type": "Feature",
  "properties": {
    "gn:admin1_code":"30.0",
    "gn:asciiname":"Daqun",
    "gn:country_code":"CN",
    "gn:dem":190,
    "gn:feature_class":"P",
    "gn:feature_code":"PPL",
    "gn:name":"Daqun",
    "gn:population":0,
    "gn:timezone":"Asia/Shanghai",
    "iso:country":"CN",
    "name:zho_x_preferred":[
        "Daqun"
    ],
    "name:zho_x_variant":[
        "\u5927\u7fa4"
    ],
    "wof:name":"Daqun",
    "wof:placetype":"locality"
},
  "geometry": {"coordinates":[115.13056,24.16806],"type":"Point"}
}