{
  "type": "Feature",
  "properties": {
    "gn:admin1_code":"26.0",
    "gn:asciiname":"Ertaizi",
    "gn:country_code":"CN",
    "gn:dem":1249,
    "gn:feature_class":"P",
    "gn:feature_code":"PPL",
    "gn:name":"Ertaizi",
    "gn:population":0,
    "gn:timezone":"Asia/Shanghai",
    "iso:country":"CN",
    "name:und_x_variant":[
        "\u4e8c\u53f0\u5b50"
    ],
    "wof:name":"Ertaizi",
    "wof:placetype":"locality"
},
  "geometry": {"coordinates":[106.63227000000001,33.30376],"type":"Point"}
}