{
  "type": "Feature",
  "properties": {
    "gn:admin1_code":"32.0",
    "gn:asciiname":"Hesiba",
    "gn:country_code":"CN",
    "gn:dem":376,
    "gn:feature_class":"P",
    "gn:feature_code":"PPL",
    "gn:name":"Hesiba",
    "gn:population":0,
    "gn:timezone":"Asia/Shanghai",
    "iso:country":"CN",
    "name:zho_x_preferred":[
        "\u6cb3\u6cd7\u575d"
    ],
    "wof:name":"Hesiba",
    "wof:placetype":"locality"
},
  "geometry": {"coordinates":[105.73,31.2059],"type":"Point"}
}