{
  "type": "Feature",
  "properties": {
    "gn:admin1_code":"26.0",
    "gn:asciiname":"Dengdengya",
    "gn:country_code":"CN",
    "gn:dem":754,
    "gn:feature_class":"P",
    "gn:feature_code":"PPL",
    "gn:name":"Dengdengya",
    "gn:population":0,
    "gn:timezone":"Asia/Shanghai",
    "iso:country":"CN",
    "name:und_x_variant":[
        "\u767b\u8e6c\u57ad"
    ],
    "wof:name":"Dengdengya",
    "wof:placetype":"locality"
},
  "geometry": {"coordinates":[106.0371,33.11512],"type":"Point"}
}