{
  "type": "Feature",
  "properties": {
    "gn:admin1_code":"15.0",
    "gn:asciiname":"Manyuan",
    "gn:country_code":"CN",
    "gn:dem":1545,
    "gn:feature_class":"P",
    "gn:feature_code":"PPL",
    "gn:name":"Manyuan",
    "gn:population":0,
    "gn:timezone":"Asia/Shanghai",
    "iso:country":"CN",
    "name:und_x_variant":[
        "\u6f2b\u586c"
    ],
    "wof:name":"Manyuan",
    "wof:placetype":"locality"
},
  "geometry": {"coordinates":[107.37166999999999,36.63],"type":"Point"}
}