{
  "type": "Feature",
  "properties": {
    "gn:admin1_code":"19.0",
    "gn:asciiname":"Huoshi",
    "gn:country_code":"CN",
    "gn:dem":6,
    "gn:feature_class":"P",
    "gn:feature_code":"PPL",
    "gn:name":"Huoshi",
    "gn:population":0,
    "gn:timezone":"Asia/Shanghai",
    "iso:country":"CN",
    "name:und_x_variant":[
        "\u4f19\u98df"
    ],
    "name:zho_x_preferred":[
        "\u4f19\u98df"
    ],
    "wof:name":"Huoshi",
    "wof:placetype":"locality"
},
  "geometry": {"coordinates":[122.883,39.6171],"type":"Point"}
}