{
  "type": "Feature",
  "properties": {
    "gn:admin1_code":"1.0",
    "gn:asciiname":"Chakeng",
    "gn:country_code":"CN",
    "gn:dem":251,
    "gn:feature_class":"P",
    "gn:feature_code":"PPL",
    "gn:name":"Chakeng",
    "gn:population":0,
    "gn:timezone":"Asia/Shanghai",
    "iso:country":"CN",
    "name:zho_x_preferred":[
        "\u67e5\u5751"
    ],
    "wof:name":"Chakeng",
    "wof:placetype":"locality"
},
  "geometry": {"coordinates":[117.81774,29.77982],"type":"Point"}
}