{
  "type": "Feature",
  "properties": {
    "gn:admin1_code":"29.0",
    "gn:asciiname":"Haishao",
    "gn:country_code":"CN",
    "gn:dem":1628,
    "gn:feature_class":"P",
    "gn:feature_code":"PPL",
    "gn:name":"Haishao",
    "gn:population":0,
    "gn:timezone":"Asia/Shanghai",
    "iso:country":"CN",
    "name:zho_x_preferred":[
        "\u6d77\u7a0d"
    ],
    "wof:name":"Haishao",
    "wof:placetype":"locality"
},
  "geometry": {"coordinates":[100.666,25.6802],"type":"Point"}
}