{
  "type": "Feature",
  "properties": {
    "gn:admin1_code":"32.0",
    "gn:asciiname":"Dayanjing",
    "gn:country_code":"CN",
    "gn:dem":2085,
    "gn:feature_class":"P",
    "gn:feature_code":"PPL",
    "gn:name":"Dayanjing",
    "gn:population":0,
    "gn:timezone":"Asia/Shanghai",
    "iso:country":"CN",
    "name:zho_x_preferred":[
        "\u5927\u76d0\u4e95"
    ],
    "wof:name":"Dayanjing",
    "wof:placetype":"locality"
},
  "geometry": {"coordinates":[102.26000000000001,28.7334],"type":"Point"}
}