{
  "type": "Feature",
  "properties": {
    "gn:admin1_code":"25",
    "gn:asciiname":"Maliangzhuang",
    "gn:country_code":"CN",
    "gn:dem":28,
    "gn:feature_class":"P",
    "gn:feature_code":"PPL",
    "gn:name":"Maliangzhuang",
    "gn:population":0,
    "gn:timezone":"Asia/Shanghai",
    "iso:country":"CN",
    "name:zho_x_preferred":[
        "\u9a6c\u7cae\u5e84"
    ],
    "wof:name":"Maliangzhuang",
    "wof:placetype":"locality"
},
  "geometry": {"coordinates":[116.09099999999999,37.1839],"type":"Point"}
}