{
  "type": "Feature",
  "properties": {
    "gn:admin1_code":"33.0",
    "gn:asciiname":"Shuijingwan",
    "gn:country_code":"CN",
    "gn:dem":696,
    "gn:feature_class":"P",
    "gn:feature_code":"PPL",
    "gn:name":"Shuijingwan",
    "gn:population":0,
    "gn:timezone":"Asia/Shanghai",
    "iso:country":"CN",
    "name:zho_x_preferred":[
        "\u6c34\u4e95\u6e7e"
    ],
    "wof:name":"Shuijingwan",
    "wof:placetype":"locality"
},
  "geometry": {"coordinates":[107.78237,30.11558],"type":"Point"}
}