{
  "type": "Feature",
  "properties": {
    "gn:country":"CN",
    "gn:fcode":"PPL",
    "gn:population":1114,
    "iso:country":"CN",
    "name:und_x_variant":[
        "Jun-song"
    ],
    "name:zho_x_preferred":[
        "\u6da6\u677e"
    ],
    "qs:name":"Runsonglaozhai",
    "qs:photos_9r":0,
    "qs:photos_sr":0,
    "qs:pop_sr":"3",
    "wof:name":"Runsonglaozhai",
    "wof:placetype":"locality",
    "wof:population":1114
},
  "geometry": {"coordinates":[109.09528,26.86889],"type":"Point"}
}