{
  "type": "Feature",
  "properties": {
    "gn:admin1_code":"20.0",
    "gn:asciiname":"Yilongyong",
    "gn:country_code":"CN",
    "gn:dem":403,
    "gn:feature_class":"P",
    "gn:feature_code":"PPLA4",
    "gn:name":"Yilongyong",
    "gn:population":0,
    "gn:timezone":"Asia/Shanghai",
    "iso:country":"CN",
    "name:und_x_variant":[
        "Yilongyong Zhen"
    ],
    "name:zho_x_preferred":[
        "\u4e49\u9686\u6c38"
    ],
    "name:zho_x_variant":[
        "\u4e49\u9686\u6c38\u9547"
    ],
    "wof:name":"Yilongyong",
    "wof:placetype":"locality"
},
  "geometry": {"coordinates":[120.64755,42.63983],"type":"Point"}
}