{
  "type": "Feature",
  "properties": {
    "gn:admin1_code":"20.0",
    "gn:asciiname":"Chaoyanggou",
    "gn:country_code":"CN",
    "gn:dem":331,
    "gn:feature_class":"P",
    "gn:feature_code":"PPL",
    "gn:name":"Chaoyanggou",
    "gn:population":0,
    "gn:timezone":"Asia/Shanghai",
    "iso:country":"CN",
    "name:zho_x_preferred":[
        "\u671d\u9633\u6c9f"
    ],
    "wof:name":"Chaoyanggou",
    "wof:placetype":"locality"
},
  "geometry": {"coordinates":[124.32975999999999,50.02592],"type":"Point"}
}