{
  "type": "Feature",
  "properties": {
    "gn:admin1_code":"8.0",
    "gn:asciiname":"Shuangsheng",
    "gn:country_code":"CN",
    "gn:dem":248,
    "gn:feature_class":"P",
    "gn:feature_code":"PPL",
    "gn:name":"Shuangsheng",
    "gn:population":0,
    "gn:timezone":"Asia/Shanghai",
    "iso:country":"CN",
    "name:zho_x_preferred":[
        "\u53cc\u80dc"
    ],
    "wof:name":"Shuangsheng",
    "wof:placetype":"locality"
},
  "geometry": {"coordinates":[125.87358999999999,47.06801],"type":"Point"}
}