{
  "type": "Feature",
  "properties": {
    "gn:admin1_code":"15",
    "gn:asciiname":"Wangdizhuang",
    "gn:country_code":"CN",
    "gn:dem":1518,
    "gn:feature_class":"P",
    "gn:feature_code":"PPL",
    "gn:name":"Wangdizhuang",
    "gn:population":0,
    "gn:timezone":"Asia/Shanghai",
    "iso:country":"CN",
    "name:zho_x_preferred":[
        "\u738b\u5730\u5e84"
    ],
    "wof:name":"Wangdizhuang",
    "wof:placetype":"locality"
},
  "geometry": {"coordinates":[107.169,35.9053],"type":"Point"}
}