{
  "type": "Feature",
  "properties": {
    "gn:admin1_code":"3",
    "gn:asciiname":"Huzhuaping",
    "gn:country_code":"CN",
    "gn:dem":294,
    "gn:feature_class":"P",
    "gn:feature_code":"PPL",
    "gn:name":"Huzhuaping",
    "gn:population":0,
    "gn:timezone":"Asia/Shanghai",
    "iso:country":"CN",
    "name:zho_x_preferred":[
        "\u864e\u722a\u576a"
    ],
    "wof:name":"Huzhuaping",
    "wof:placetype":"locality"
},
  "geometry": {"coordinates":[113.904,26.6962],"type":"Point"}
}