{
  "type": "Feature",
  "properties": {
    "gn:admin1_code":"19.0",
    "gn:asciiname":"Shang'ailingao",
    "gn:country_code":"CN",
    "gn:dem":289,
    "gn:feature_class":"P",
    "gn:feature_code":"PPL",
    "gn:name":"Shang\u2019ailingao",
    "gn:population":0,
    "gn:timezone":"Asia/Shanghai",
    "iso:country":"CN",
    "name:und_x_variant":[
        "Shang\u2019ailingao"
    ],
    "name:zho_x_preferred":[
        "\u4e0a\u827e\u6797\u768b"
    ],
    "wof:name":"Shang'ailingao",
    "wof:placetype":"locality"
},
  "geometry": {"coordinates":[121.161,41.8914],"type":"Point"}
}