{
  "type": "Feature",
  "properties": {
    "gn:admin1_code":"32.0",
    "gn:asciiname":"Zhilazong",
    "gn:country_code":"CN",
    "gn:dem":3643,
    "gn:feature_class":"P",
    "gn:feature_code":"PPL",
    "gn:name":"Zhilazong",
    "gn:population":0,
    "gn:timezone":"Asia/Shanghai",
    "iso:country":"CN",
    "name:zho_x_preferred":[
        "\u652f\u62c9\u5b97"
    ],
    "wof:name":"Zhilazong",
    "wof:placetype":"locality"
},
  "geometry": {"coordinates":[99.47110000000001,29.1852],"type":"Point"}
}