{
  "type": "Feature",
  "properties": {
    "gn:admin1_code":"16.0",
    "gn:asciiname":"Yangbei",
    "gn:country_code":"CN",
    "gn:dem":72,
    "gn:feature_class":"P",
    "gn:feature_code":"PPL",
    "gn:name":"Yangbei",
    "gn:population":0,
    "gn:timezone":"Asia/Shanghai",
    "iso:country":"CN",
    "name:zho_x_preferred":[
        "\u6d0b\u9642"
    ],
    "wof:name":"Yangbei",
    "wof:placetype":"locality"
},
  "geometry": {"coordinates":[109.967,22.9461],"type":"Point"}
}