{
  "type": "Feature",
  "properties": {
    "gn:admin1_code":"16.0",
    "gn:asciiname":"Xinbanwei",
    "gn:country_code":"CN",
    "gn:dem":251,
    "gn:feature_class":"P",
    "gn:feature_code":"PPL",
    "gn:name":"Xinbanwei",
    "gn:population":0,
    "gn:timezone":"Asia/Shanghai",
    "iso:country":"CN",
    "name:zho_x_preferred":[
        "\u65b0\u677f\u56f4"
    ],
    "wof:name":"Xinbanwei",
    "wof:placetype":"locality"
},
  "geometry": {"coordinates":[108.869,24.3537],"type":"Point"}
}