{
  "type": "Feature",
  "properties": {
    "gn:admin1_code":"31.0",
    "gn:asciiname":"Chaogang",
    "gn:country_code":"CN",
    "gn:dem":6,
    "gn:feature_class":"P",
    "gn:feature_code":"PPL",
    "gn:name":"Chaogang",
    "gn:population":0,
    "gn:timezone":"Asia/Shanghai",
    "iso:country":"CN",
    "name:zho_x_preferred":[
        "\u6f6e\u6e2f"
    ],
    "wof:name":"Chaogang",
    "wof:placetype":"locality"
},
  "geometry": {"coordinates":[110.45746,18.8527],"type":"Point"}
}