{
  "type": "Feature",
  "properties": {
    "gn:admin1_code":"3.0",
    "gn:asciiname":"Shangbanling",
    "gn:country_code":"CN",
    "gn:dem":203,
    "gn:feature_class":"P",
    "gn:feature_code":"PPL",
    "gn:name":"Shangbanling",
    "gn:population":0,
    "gn:timezone":"Asia/Shanghai",
    "iso:country":"CN",
    "name:und_x_variant":[
        "\u4e0a\u534a\u5cad"
    ],
    "wof:name":"Shangbanling",
    "wof:placetype":"locality"
},
  "geometry": {"coordinates":[115.83205,25.63422000000001],"type":"Point"}
}