{
  "type": "Feature",
  "properties": {
    "gn:admin1_code":"30.0",
    "gn:asciiname":"Houdong",
    "gn:country_code":"CN",
    "gn:dem":132,
    "gn:feature_class":"P",
    "gn:feature_code":"PPL",
    "gn:name":"Houdong",
    "gn:population":0,
    "gn:timezone":"Asia/Shanghai",
    "iso:country":"CN",
    "name:und_x_variant":[
        "\u539a\u6d1e"
    ],
    "name:zho_x_preferred":[
        "\u539a\u6d1e"
    ],
    "wof:name":"Houdong",
    "wof:placetype":"locality"
},
  "geometry": {"coordinates":[114.43384,23.88434],"type":"Point"}
}