{
  "type": "Feature",
  "properties": {
    "gn:admin1_code":"16.0",
    "gn:asciiname":"Xinmei",
    "gn:country_code":"CN",
    "gn:dem":648,
    "gn:feature_class":"P",
    "gn:feature_code":"PPL",
    "gn:name":"Xinmei",
    "gn:population":0,
    "gn:timezone":"Asia/Shanghai",
    "iso:country":"CN",
    "name:zho_x_preferred":[
        "\u65b0\u7f8e"
    ],
    "wof:name":"Xinmei",
    "wof:placetype":"locality"
},
  "geometry": {"coordinates":[106.65900000000001,23.5611],"type":"Point"}
}