{
  "type": "Feature",
  "properties": {
    "gn:admin1_code":"31.0",
    "gn:asciiname":"Baishamen",
    "gn:country_code":"CN",
    "gn:dem":7,
    "gn:feature_class":"P",
    "gn:feature_code":"PPL",
    "gn:name":"Baishamen",
    "gn:population":0,
    "gn:timezone":"Asia/Shanghai",
    "iso:country":"CN",
    "name:zho_x_preferred":[
        "\u767d\u6c99\u95e8"
    ],
    "wof:name":"Baishamen",
    "wof:placetype":"locality"
},
  "geometry": {"coordinates":[110.33542,20.06661],"type":"Point"}
}