{
  "type": "Feature",
  "properties": {
    "gn:admin1_code":"32.0",
    "gn:asciiname":"Alaiwu",
    "gn:country_code":"CN",
    "gn:dem":1981,
    "gn:feature_class":"P",
    "gn:feature_code":"PPL",
    "gn:name":"Alaiwu",
    "gn:population":0,
    "gn:timezone":"Asia/Shanghai",
    "iso:country":"CN",
    "name:zho_x_preferred":[
        "\u963f\u6765\u543e"
    ],
    "wof:name":"Alaiwu",
    "wof:placetype":"locality"
},
  "geometry": {"coordinates":[102.621,28.6032],"type":"Point"}
}