{
  "type": "Feature",
  "properties": {
    "gn:admin1_code":"30.0",
    "gn:asciiname":"Longgeng",
    "gn:country_code":"CN",
    "gn:dem":177,
    "gn:feature_class":"P",
    "gn:feature_code":"PPL",
    "gn:name":"Longgeng",
    "gn:population":0,
    "gn:timezone":"Asia/Shanghai",
    "iso:country":"CN",
    "name:zho_x_preferred":[
        "Longgeng"
    ],
    "name:zho_x_variant":[
        "\u9f99\u9888"
    ],
    "wof:name":"Longgeng",
    "wof:placetype":"locality"
},
  "geometry": {"coordinates":[114.99666999999999,24.1926],"type":"Point"}
}