{
  "type": "Feature",
  "properties": {
    "gn:admin1_code":"16.0",
    "gn:asciiname":"Wailonghei",
    "gn:country_code":"CN",
    "gn:dem":266,
    "gn:feature_class":"P",
    "gn:feature_code":"PPL",
    "gn:name":"Wailonghei",
    "gn:population":0,
    "gn:timezone":"Asia/Shanghai",
    "iso:country":"CN",
    "name:zho_x_preferred":[
        "\u5916\u9f99\u9ed1"
    ],
    "wof:name":"Wailonghei",
    "wof:placetype":"locality"
},
  "geometry": {"coordinates":[108.553,24.3041],"type":"Point"}
}