{
  "type": "Feature",
  "properties": {
    "gn:admin1_code":"32.0",
    "gn:asciiname":"Wayaotou",
    "gn:country_code":"CN",
    "gn:dem":660,
    "gn:feature_class":"P",
    "gn:feature_code":"PPL",
    "gn:name":"Wayaotou",
    "gn:population":0,
    "gn:timezone":"Asia/Shanghai",
    "iso:country":"CN",
    "name:zho_x_preferred":[
        "\u74e6\u7a91\u5934"
    ],
    "wof:name":"Wayaotou",
    "wof:placetype":"locality"
},
  "geometry": {"coordinates":[105.79212,28.6204],"type":"Point"}
}