{
  "type": "Feature",
  "properties": {
    "gn:admin1_code":"11.0",
    "gn:asciiname":"Qiumufeng",
    "gn:country_code":"CN",
    "gn:dem":1015,
    "gn:feature_class":"P",
    "gn:feature_code":"PPL",
    "gn:name":"Qiumufeng",
    "gn:population":0,
    "gn:timezone":"Asia/Shanghai",
    "iso:country":"CN",
    "name:zho_x_preferred":[
        "\u79cb\u6728\u5cf0"
    ],
    "wof:name":"Qiumufeng",
    "wof:placetype":"locality"
},
  "geometry": {"coordinates":[110.67511,29.97918],"type":"Point"}
}