{
  "type": "Feature",
  "properties": {
    "gn:admin1_code":"18",
    "gn:asciiname":"Datian",
    "gn:country_code":"CN",
    "gn:dem":872,
    "gn:feature_class":"P",
    "gn:feature_code":"PPL",
    "gn:name":"Datian",
    "gn:population":0,
    "gn:timezone":"Asia/Shanghai",
    "iso:country":"CN",
    "name:ceb_x_preferred":[
        "Datian"
    ],
    "name:deu_x_preferred":[
        "Datian"
    ],
    "name:vie_x_preferred":[
        "\u0110\u1ea1i \u0110i\u1ec1n"
    ],
    "name:zho_x_preferred":[
        "\u5927\u7530"
    ],
    "wof:name":"Datian",
    "wof:placetype":"locality"
},
  "geometry": {"coordinates":[106.83499999999999,25.2404],"type":"Point"}
}