{
  "type": "Feature",
  "properties": {
    "gn:admin1_code":"18",
    "gn:asciiname":"Xinmin",
    "gn:country_code":"CN",
    "gn:dem":734,
    "gn:feature_class":"P",
    "gn:feature_code":"PPL",
    "gn:name":"Xinmin",
    "gn:population":0,
    "gn:timezone":"Asia/Shanghai",
    "iso:country":"CN",
    "wof:name":"Xinmin",
    "wof:placetype":"locality"
},
  "geometry": {"coordinates":[108.70471999999999,25.88861],"type":"Point"}
}