{
  "type": "Feature",
  "properties": {
    "gn:admin1_code":"02",
    "gn:asciiname":"Gujiaqiao",
    "gn:country_code":"CN",
    "gn:dem":8,
    "gn:feature_class":"P",
    "gn:feature_code":"PPL",
    "gn:name":"Gujiaqiao",
    "gn:population":0,
    "gn:timezone":"Asia/Shanghai",
    "iso:country":"CN",
    "name:und_x_variant":[
        "\u987e\u5bb6\u6865"
    ],
    "wof:name":"Gujiaqiao",
    "wof:placetype":"locality"
},
  "geometry": {"coordinates":[121.03421000000002,30.76373],"type":"Point"}
}