{
  "type": "Feature",
  "properties": {
    "gn:admin1_code":"1.0",
    "gn:asciiname":"Weitang",
    "gn:country_code":"CN",
    "gn:dem":26,
    "gn:feature_class":"P",
    "gn:feature_code":"PPL",
    "gn:name":"Weitang",
    "gn:population":0,
    "gn:timezone":"Asia/Shanghai",
    "iso:country":"CN",
    "name:und_x_variant":[
        "\u9b4f\u5858",
        "\u9b4f\u5858\u6751"
    ],
    "name:zho_x_preferred":[
        "Weitangcun"
    ],
    "wof:name":"Weitang",
    "wof:placetype":"locality"
},
  "geometry": {"coordinates":[119.02087,30.97115],"type":"Point"}
}