{
  "type": "Feature",
  "properties": {
    "gn:admin1_code":"29.0",
    "gn:asciiname":"Daba",
    "gn:country_code":"CN",
    "gn:dem":2719,
    "gn:feature_class":"P",
    "gn:feature_code":"PPL",
    "gn:name":"Daba",
    "gn:population":0,
    "gn:timezone":"Asia/Shanghai",
    "iso:country":"CN",
    "name:und_x_variant":[
        "\u5927\u575d"
    ],
    "wof:name":"Daba",
    "wof:placetype":"locality"
},
  "geometry": {"coordinates":[103.45699999999999,26.27414000000001],"type":"Point"}
}