{
  "type": "Feature",
  "properties": {
    "gn:admin1_code":"25.0",
    "gn:asciiname":"Qiangou",
    "gn:cc2":"CN",
    "gn:country_code":"CN",
    "gn:dem":53,
    "gn:feature_class":"P",
    "gn:feature_code":"PPL",
    "gn:name":"Qiangou",
    "gn:population":0,
    "gn:timezone":"Asia/Shanghai",
    "iso:country":"CN",
    "name:zho_x_preferred":[
        "\u524d\u6c9f"
    ],
    "wof:name":"Qiangou",
    "wof:placetype":"locality"
},
  "geometry": {"coordinates":[119.92863,35.97285],"type":"Point"}
}