{
  "type": "Feature",
  "properties": {
    "gn:admin1_code":"01",
    "gn:asciiname":"Huangnihe",
    "gn:cc2":"CN",
    "gn:country_code":"CN",
    "gn:dem":16,
    "gn:feature_class":"P",
    "gn:feature_code":"PPL",
    "gn:name":"Huangnihe",
    "gn:population":0,
    "gn:timezone":"Asia/Shanghai",
    "iso:country":"CN",
    "name:und_x_variant":[
        "Ni-ho",
        "Huang-ni-ho",
        "Huangnihe"
    ],
    "wof:name":"Huangnihe",
    "wof:placetype":"locality"
},
  "geometry": {"coordinates":[117.31833,31.08889000000001],"type":"Point"}
}