{
  "type": "Feature",
  "properties": {
    "gn:admin1_code":"16.0",
    "gn:asciiname":"Wuxu",
    "gn:cc2":"CN",
    "gn:country_code":"CN",
    "gn:dem":133,
    "gn:feature_class":"P",
    "gn:feature_code":"PPL",
    "gn:name":"Wuxu",
    "gn:population":0,
    "gn:timezone":"Asia/Shanghai",
    "iso:country":"CN",
    "name:und_x_variant":[
        "Wu-hs\u00fc",
        "Wu-sun-hsu",
        "Wu-ts\u2019un-hs\u00fc",
        "Wu-ts\u2019un",
        "Wutsunyu",
        "Wuyu",
        "Wuxu"
    ],
    "wof:name":"Wuxu",
    "wof:placetype":"locality"
},
  "geometry": {"coordinates":[108.21666999999999,22.65],"type":"Point"}
}