{
  "type": "Feature",
  "properties": {
    "gn:admin1_code":"14.0",
    "gn:asciiname":"Bilincun",
    "gn:country_code":"CN",
    "gn:dem":3709,
    "gn:feature_class":"P",
    "gn:feature_code":"PPL",
    "gn:name":"Bilincun",
    "gn:population":0,
    "gn:timezone":"Asia/Urumqi",
    "iso:country":"CN",
    "name:zho_x_preferred":[
        "\u6bd4\u6797\u6751"
    ],
    "wof:name":"Bilincun",
    "wof:placetype":"locality"
},
  "geometry": {"coordinates":[92.81122999999999,28.88282],"type":"Point"}
}