{
  "type": "Feature",
  "properties": {
    "gn:admin1_code":"5.0",
    "gn:asciiname":"Qingshui Quanzicun",
    "gn:country_code":"CN",
    "gn:dem":196,
    "gn:feature_class":"P",
    "gn:feature_code":"PPL",
    "gn:name":"Qingshui Quanzicun",
    "gn:population":0,
    "gn:timezone":"Asia/Shanghai",
    "iso:country":"CN",
    "name:zho_x_preferred":[
        "\u6e05\u6c34\u6cc9\u5b50\u6751"
    ],
    "wof:name":"Qingshui Quanzicun",
    "wof:placetype":"locality"
},
  "geometry": {"coordinates":[125.90425999999999,43.87263],"type":"Point"}
}