{
  "type": "Feature",
  "properties": {
    "gn:admin1_code":"16",
    "gn:asciiname":"Shanhuashui",
    "gn:country_code":"CN",
    "gn:dem":961,
    "gn:feature_class":"P",
    "gn:feature_code":"PPL",
    "gn:name":"Shanhuashui",
    "gn:population":0,
    "gn:timezone":"Asia/Shanghai",
    "iso:country":"CN",
    "name:zho_x_preferred":[
        "\u5c71\u82b1\u6c34"
    ],
    "wof:name":"Shanhuashui",
    "wof:placetype":"locality"
},
  "geometry": {"coordinates":[110.765,26.1043],"type":"Point"}
}