{
  "type": "Feature",
  "properties": {
    "gn:admin1_code":"32",
    "gn:asciiname":"Chengzishan",
    "gn:country_code":"CN",
    "gn:dem":1311,
    "gn:feature_class":"P",
    "gn:feature_code":"PPL",
    "gn:name":"Chengzishan",
    "gn:population":0,
    "gn:timezone":"Asia/Shanghai",
    "iso:country":"CN",
    "wof:name":"Chengzishan",
    "wof:placetype":"locality"
},
  "geometry": {"coordinates":[107.32472,32.47389],"type":"Point"}
}