{
  "type": "Feature",
  "properties": {
    "gn:admin1_code":"15.0",
    "gn:asciiname":"Gaoshangzui",
    "gn:country_code":"CN",
    "gn:dem":1922,
    "gn:feature_class":"P",
    "gn:feature_code":"PPL",
    "gn:name":"Gaoshangzui",
    "gn:population":0,
    "gn:timezone":"Asia/Shanghai",
    "iso:country":"CN",
    "name:zho_x_preferred":[
        "\u9ad8\u4e0a\u5634"
    ],
    "wof:name":"Gaoshangzui",
    "wof:placetype":"locality"
},
  "geometry": {"coordinates":[104.791,35.5589],"type":"Point"}
}