{
  "type": "Feature",
  "properties": {
    "gn:admin1_code":"32.0",
    "gn:asciiname":"Mapingzi",
    "gn:country_code":"CN",
    "gn:dem":2301,
    "gn:feature_class":"P",
    "gn:feature_code":"PPL",
    "gn:name":"Mapingzi",
    "gn:population":0,
    "gn:timezone":"Asia/Shanghai",
    "iso:country":"CN",
    "name:zho_x_preferred":[
        "\u9a6c\u576a\u5b50"
    ],
    "wof:name":"Mapingzi",
    "wof:placetype":"locality"
},
  "geometry": {"coordinates":[102.01272,26.74174],"type":"Point"}
}