{
  "type": "Feature",
  "properties": {
    "gn:admin1_code":"8.0",
    "gn:asciiname":"Sheng'ancun",
    "gn:country_code":"CN",
    "gn:dem":178,
    "gn:feature_class":"P",
    "gn:feature_code":"PPL",
    "gn:name":"Sheng\u2019ancun",
    "gn:population":0,
    "gn:timezone":"Asia/Shanghai",
    "iso:country":"CN",
    "name:und_x_variant":[
        "Sheng\u2019ancun"
    ],
    "name:zho_x_preferred":[
        "\u80dc\u5b89\u6751"
    ],
    "wof:name":"Sheng'ancun",
    "wof:placetype":"locality"
},
  "geometry": {"coordinates":[125.45734,46.20334],"type":"Point"}
}