{
  "type": "Feature",
  "properties": {
    "gn:admin1_code":"1.0",
    "gn:asciiname":"Wenxucun",
    "gn:country_code":"CN",
    "gn:dem":31,
    "gn:feature_class":"P",
    "gn:feature_code":"PPL",
    "gn:name":"Wenxucun",
    "gn:population":0,
    "gn:timezone":"Asia/Shanghai",
    "iso:country":"CN",
    "name:zho_x_preferred":[
        "\u6587\u5729\u6751"
    ],
    "wof:name":"Wenxucun",
    "wof:placetype":"locality"
},
  "geometry": {"coordinates":[116.57223,32.0406],"type":"Point"}
}