{
  "type": "Feature",
  "properties": {
    "gn:admin1_code":"21.0",
    "gn:asciiname":"Pujiashan",
    "gn:country_code":"CN",
    "gn:dem":1842,
    "gn:feature_class":"P",
    "gn:feature_code":"PPL",
    "gn:name":"Pujiashan",
    "gn:population":0,
    "gn:timezone":"Asia/Shanghai",
    "iso:country":"CN",
    "name:zho_x_preferred":[
        "\u8386\u5bb6\u5c71"
    ],
    "wof:name":"Pujiashan",
    "wof:placetype":"locality"
},
  "geometry": {"coordinates":[105.88800000000001,36.4361],"type":"Point"}
}