{
  "type": "Feature",
  "properties": {
    "gn:admin1_code":"32.0",
    "gn:asciiname":"Baxia",
    "gn:country_code":"CN",
    "gn:dem":3406,
    "gn:feature_class":"P",
    "gn:feature_code":"PPL",
    "gn:name":"Baxia",
    "gn:population":0,
    "gn:timezone":"Asia/Shanghai",
    "iso:country":"CN",
    "name:zho_x_preferred":[
        "\u5df4\u590f"
    ],
    "wof:name":"Baxia",
    "wof:placetype":"locality"
},
  "geometry": {"coordinates":[100.878,29.403],"type":"Point"}
}