{
  "type": "Feature",
  "properties": {
    "gn:admin1_code":"8.0",
    "gn:asciiname":"Weiguo",
    "gn:country_code":"CN",
    "gn:dem":197,
    "gn:feature_class":"P",
    "gn:feature_code":"PPLA4",
    "gn:name":"Weiguo",
    "gn:population":0,
    "gn:timezone":"Asia/Shanghai",
    "iso:country":"CN",
    "name:und_x_variant":[
        "Weiguo Xiang"
    ],
    "name:zho_x_preferred":[
        "\u536b\u56fd"
    ],
    "name:zho_x_variant":[
        "\u536b\u56fd\u4e61"
    ],
    "wof:name":"Weiguo",
    "wof:placetype":"locality"
},
  "geometry": {"coordinates":[127.81014999999999,46.89425],"type":"Point"}
}