{
  "type": "Feature",
  "properties": {
    "gn:admin1_code":"30",
    "gn:asciiname":"Gangdi",
    "gn:country_code":"CN",
    "gn:dem":3,
    "gn:feature_class":"P",
    "gn:feature_code":"PPL",
    "gn:name":"Gangdi",
    "gn:population":0,
    "gn:timezone":"Asia/Shanghai",
    "iso:country":"CN",
    "wof:name":"Gangdi",
    "wof:placetype":"locality"
},
  "geometry": {"coordinates":[116.45667,23.43306],"type":"Point"}
}