{
  "type": "Feature",
  "properties": {
    "gn:admin1_code":"29.0",
    "gn:asciiname":"Xugongqing Shangcun",
    "gn:country_code":"CN",
    "gn:dem":2638,
    "gn:feature_class":"P",
    "gn:feature_code":"PPL",
    "gn:name":"Xugongqing Shangcun",
    "gn:population":0,
    "gn:timezone":"Asia/Shanghai",
    "iso:country":"CN",
    "name:zho_x_preferred":[
        "\u8bb8\u8d21\u7b90\u4e0a\u6751"
    ],
    "wof:name":"Xugongqing Shangcun",
    "wof:placetype":"locality"
},
  "geometry": {"coordinates":[99.3683,27.6383],"type":"Point"}
}