{
  "type": "Feature",
  "properties": {
    "gn:admin1_code":"15.0",
    "gn:asciiname":"Huluba",
    "gn:country_code":"CN",
    "gn:dem":903,
    "gn:feature_class":"P",
    "gn:feature_code":"PPL",
    "gn:name":"Huluba",
    "gn:population":0,
    "gn:timezone":"Asia/Shanghai",
    "iso:country":"CN",
    "name:und_x_variant":[
        "\u846b\u82a6\u575d"
    ],
    "wof:name":"Huluba",
    "wof:placetype":"locality"
},
  "geometry": {"coordinates":[106.14848000000001,33.87065],"type":"Point"}
}