{
  "type": "Feature",
  "properties": {
    "gn:admin1_code":"32.0",
    "gn:asciiname":"Xinwuba",
    "gn:country_code":"CN",
    "gn:dem":352,
    "gn:feature_class":"P",
    "gn:feature_code":"PPL",
    "gn:name":"Xinwuba",
    "gn:population":0,
    "gn:timezone":"Asia/Shanghai",
    "iso:country":"CN",
    "name:zho_x_preferred":[
        "\u65b0\u5c4b\u575d"
    ],
    "wof:name":"Xinwuba",
    "wof:placetype":"locality"
},
  "geometry": {"coordinates":[104.336,29.152],"type":"Point"}
}