{
  "type": "Feature",
  "properties": {
    "gn:admin1_code":"22.0",
    "gn:asciiname":"Panglicun",
    "gn:country_code":"CN",
    "gn:dem":40,
    "gn:feature_class":"P",
    "gn:feature_code":"PPL",
    "gn:name":"Panglicun",
    "gn:population":0,
    "gn:timezone":"Asia/Shanghai",
    "iso:country":"CN",
    "name:zho_x_preferred":[
        "\u5e9e\u91cc\u6751"
    ],
    "wof:name":"Panglicun",
    "wof:placetype":"locality"
},
  "geometry": {"coordinates":[116.87299,40.13869],"type":"Point"}
}