{
  "type": "Feature",
  "properties": {
    "gn:admin1_code":"10.0",
    "gn:asciiname":"Cimihua",
    "gn:country_code":"CN",
    "gn:dem":1126,
    "gn:feature_class":"P",
    "gn:feature_code":"PPL",
    "gn:name":"Cimihua",
    "gn:population":0,
    "gn:timezone":"Asia/Shanghai",
    "iso:country":"CN",
    "name:zho_x_preferred":[
        "\u523a\u7c73\u82b1"
    ],
    "wof:name":"Cimihua",
    "wof:placetype":"locality"
},
  "geometry": {"coordinates":[114.86184,39.43421],"type":"Point"}
}