{
  "type": "Feature",
  "properties": {
    "gn:admin1_code":"29.0",
    "gn:asciiname":"Jiudiji",
    "gn:country_code":"CN",
    "gn:dem":1767,
    "gn:feature_class":"P",
    "gn:feature_code":"PPL",
    "gn:name":"Jiudiji",
    "gn:population":0,
    "gn:timezone":"Asia/Shanghai",
    "iso:country":"CN",
    "name:zho_x_preferred":[
        "\u65e7\u5730\u57fa"
    ],
    "wof:name":"Jiudiji",
    "wof:placetype":"locality"
},
  "geometry": {"coordinates":[100.22499999999999,24.629],"type":"Point"}
}