{
  "type": "Feature",
  "properties": {
    "gn:admin1_code":"9.0",
    "gn:asciiname":"Shangyingou",
    "gn:country_code":"CN",
    "gn:dem":164,
    "gn:feature_class":"P",
    "gn:feature_code":"PPL",
    "gn:name":"Shangyingou",
    "gn:population":0,
    "gn:timezone":"Asia/Shanghai",
    "iso:country":"CN",
    "name:zho_x_preferred":[
        "\u4e0a\u5c39\u6c9f"
    ],
    "wof:name":"Shangyingou",
    "wof:placetype":"locality"
},
  "geometry": {"coordinates":[111.66725,32.79528],"type":"Point"}
}