{
  "type": "Feature",
  "properties": {
    "gn:admin1_code":"16.0",
    "gn:asciiname":"Liangqiao",
    "gn:country_code":"CN",
    "gn:dem":192,
    "gn:feature_class":"P",
    "gn:feature_code":"PPL",
    "gn:name":"Liangqiao",
    "gn:population":0,
    "gn:timezone":"Asia/Shanghai",
    "iso:country":"CN",
    "name:zho_x_preferred":[
        "\u826f\u6865"
    ],
    "wof:name":"Liangqiao",
    "wof:placetype":"locality"
},
  "geometry": {"coordinates":[108.40000000000001,24.7245],"type":"Point"}
}