{
  "type": "Feature",
  "properties": {
    "gn:admin1_code":"12.0",
    "gn:asciiname":"Liujiahekou",
    "gn:country_code":"CN",
    "gn:dem":26,
    "gn:feature_class":"P",
    "gn:feature_code":"PPL",
    "gn:name":"Liujiahekou",
    "gn:population":0,
    "gn:timezone":"Asia/Shanghai",
    "iso:country":"CN",
    "name:zho_x_preferred":[
        "\u5218\u5bb6\u6cb3\u53e3"
    ],
    "wof:name":"Liujiahekou",
    "wof:placetype":"locality"
},
  "geometry": {"coordinates":[113.29501999999999,30.34918],"type":"Point"}
}