{
  "type": "Feature",
  "properties": {
    "gn:admin1_code":"29",
    "gn:asciiname":"Yiliucun",
    "gn:country_code":"CN",
    "gn:dem":1975,
    "gn:feature_class":"P",
    "gn:feature_code":"PPL",
    "gn:name":"Yiliucun",
    "gn:population":0,
    "gn:timezone":"Asia/Shanghai",
    "iso:country":"CN",
    "name:und_x_variant":[
        "Yiliujie",
        "Yiliujie Xiang",
        "\u4e00\u516d\u8857\u4e61",
        "Yiliucun"
    ],
    "name:zho_x_preferred":[
        "\u4e00\u516d\u6751"
    ],
    "name:zho_x_variant":[
        "\u4e00\u516d\u8857"
    ],
    "wof:name":"Yiliucun",
    "wof:placetype":"locality"
},
  "geometry": {"coordinates":[102.32162,24.5805],"type":"Point"}
}