{
  "type": "Feature",
  "properties": {
    "gn:admin1_code":"3.0",
    "gn:asciiname":"Shiwozi",
    "gn:country_code":"CN",
    "gn:dem":76,
    "gn:feature_class":"P",
    "gn:feature_code":"PPL",
    "gn:name":"Shiwozi",
    "gn:population":0,
    "gn:timezone":"Asia/Shanghai",
    "iso:country":"CN",
    "name:und_x_variant":[
        "\u77f3\u7a9d\u5b50"
    ],
    "wof:name":"Shiwozi",
    "wof:placetype":"locality"
},
  "geometry": {"coordinates":[115.46351,27.19481],"type":"Point"}
}