{
  "type": "Feature",
  "properties": {
    "gn:admin1_code":"22.0",
    "gn:asciiname":"Chazigoucun",
    "gn:country_code":"CN",
    "gn:dem":318,
    "gn:feature_class":"P",
    "gn:feature_code":"PPL",
    "gn:name":"Chazigoucun",
    "gn:population":0,
    "gn:timezone":"Asia/Shanghai",
    "iso:country":"CN",
    "name:zho_x_preferred":[
        "\u67e5\u5b50\u6c9f\u6751"
    ],
    "wof:name":"Chazigoucun",
    "wof:placetype":"locality"
},
  "geometry": {"coordinates":[117.04819999999999,40.4314],"type":"Point"}
}