{
  "type": "Feature",
  "properties": {
    "gn:admin1_code":"30",
    "gn:asciiname":"Jiuhe",
    "gn:country_code":"CN",
    "gn:dem":102,
    "gn:feature_class":"P",
    "gn:feature_code":"PPLA4",
    "gn:name":"Jiuhe",
    "gn:population":0,
    "gn:timezone":"Asia/Shanghai",
    "iso:country":"CN",
    "name:und_x_variant":[
        "Chiu-ho-hs\u00fc",
        "Chiu-ho-shih",
        "Chiu-ho",
        "Jiuhe",
        "\u4e5d\u548c",
        "Jiuhe Zhen",
        "\u4e5d\u548c\u9547"
    ],
    "wof:name":"Jiuhe",
    "wof:placetype":"locality"
},
  "geometry": {"coordinates":[115.06082000000001,23.49563],"type":"Point"}
}