{
  "type": "Feature",
  "properties": {
    "gn:admin1_code":"26.0",
    "gn:asciiname":"Huatiangou",
    "gn:country_code":"CN",
    "gn:dem":1434,
    "gn:feature_class":"P",
    "gn:feature_code":"PPL",
    "gn:name":"Huatiangou",
    "gn:population":0,
    "gn:timezone":"Asia/Shanghai",
    "iso:country":"CN",
    "name:zho_x_preferred":[
        "\u5316\u5929\u6c9f"
    ],
    "wof:name":"Huatiangou",
    "wof:placetype":"locality"
},
  "geometry": {"coordinates":[109.5416,33.75009],"type":"Point"}
}