{
  "type": "Feature",
  "properties": {
    "gn:admin1_code":"16.0",
    "gn:asciiname":"Jiuzhiben",
    "gn:country_code":"CN",
    "gn:dem":529,
    "gn:feature_class":"P",
    "gn:feature_code":"PPL",
    "gn:name":"Jiuzhiben",
    "gn:population":0,
    "gn:timezone":"Asia/Shanghai",
    "iso:country":"CN",
    "name:zho_x_preferred":[
        "\u65e7\u5cd9\u672c"
    ],
    "wof:name":"Jiuzhiben",
    "wof:placetype":"locality"
},
  "geometry": {"coordinates":[107.279,21.781],"type":"Point"}
}