{
  "type": "Feature",
  "properties": {
    "gn:admin1_code":"32.0",
    "gn:asciiname":"Jiemu",
    "gn:country_code":"CN",
    "gn:dem":2881,
    "gn:feature_class":"P",
    "gn:feature_code":"PPL",
    "gn:name":"Jiemu",
    "gn:population":0,
    "gn:timezone":"Asia/Shanghai",
    "iso:country":"CN",
    "name:zho_x_preferred":[
        "\u7ed3\u6728"
    ],
    "wof:name":"Jiemu",
    "wof:placetype":"locality"
},
  "geometry": {"coordinates":[102.04000000000001,31.3698],"type":"Point"}
}