{
  "type": "Feature",
  "properties": {
    "gn:admin1_code":"32.0",
    "gn:asciiname":"Wangqinggong",
    "gn:country_code":"CN",
    "gn:dem":381,
    "gn:feature_class":"P",
    "gn:feature_code":"PPL",
    "gn:name":"Wangqinggong",
    "gn:population":0,
    "gn:timezone":"Asia/Shanghai",
    "iso:country":"CN",
    "name:zho_x_preferred":[
        "\u738b\u6e05\u5bab"
    ],
    "wof:name":"Wangqinggong",
    "wof:placetype":"locality"
},
  "geometry": {"coordinates":[105.577,28.9107],"type":"Point"}
}