{
  "type": "Feature",
  "properties": {
    "gn:admin1_code":"12.0",
    "gn:asciiname":"Sanxiaowan",
    "gn:country_code":"CN",
    "gn:dem":871,
    "gn:feature_class":"P",
    "gn:feature_code":"PPL",
    "gn:name":"Sanxiaowan",
    "gn:population":0,
    "gn:timezone":"Asia/Shanghai",
    "iso:country":"CN",
    "name:zho_x_preferred":[
        "\u4e09\u5b5d\u6e7e"
    ],
    "wof:name":"Sanxiaowan",
    "wof:placetype":"locality"
},
  "geometry": {"coordinates":[110.37914000000001,31.11816],"type":"Point"}
}