{
  "type": "Feature",
  "properties": {
    "gn:admin1_code":"29.0",
    "gn:asciiname":"Dasuoniang",
    "gn:country_code":"CN",
    "gn:dem":1152,
    "gn:feature_class":"P",
    "gn:feature_code":"PPL",
    "gn:name":"Dasuoniang",
    "gn:population":0,
    "gn:timezone":"Asia/Shanghai",
    "iso:country":"CN",
    "name:zho_x_preferred":[
        "\u5927\u6240\u5a18"
    ],
    "wof:name":"Dasuoniang",
    "wof:placetype":"locality"
},
  "geometry": {"coordinates":[101.596,23.2242],"type":"Point"}
}