{
  "type": "Feature",
  "properties": {
    "gn:admin1_code":"15.0",
    "gn:asciiname":"Gedaling",
    "gn:country_code":"CN",
    "gn:dem":1418,
    "gn:feature_class":"P",
    "gn:feature_code":"PPL",
    "gn:name":"Gedaling",
    "gn:population":0,
    "gn:timezone":"Asia/Shanghai",
    "iso:country":"CN",
    "name:und_x_variant":[
        "\u7599\u7629\u5cad"
    ],
    "wof:name":"Gedaling",
    "wof:placetype":"locality"
},
  "geometry": {"coordinates":[105.57210000000001,33.14395],"type":"Point"}
}