{
  "type": "Feature",
  "properties": {
    "gn:admin1_code":"24.0",
    "gn:asciiname":"Hougangcun",
    "gn:country_code":"CN",
    "gn:dem":1082,
    "gn:feature_class":"P",
    "gn:feature_code":"PPL",
    "gn:name":"Hougangcun",
    "gn:population":0,
    "gn:timezone":"Asia/Shanghai",
    "iso:country":"CN",
    "name:zho_x_preferred":[
        "\u540e\u5c97\u6751"
    ],
    "wof:name":"Hougangcun",
    "wof:placetype":"locality"
},
  "geometry": {"coordinates":[113.21944000000001,38.74503],"type":"Point"}
}