{
  "type": "Feature",
  "properties": {
    "gn:admin1_code":"33.0",
    "gn:asciiname":"Yuanjia Dianzi",
    "gn:country_code":"CN",
    "gn:dem":405,
    "gn:feature_class":"P",
    "gn:feature_code":"PPL",
    "gn:name":"Yuanjia Dianzi",
    "gn:population":0,
    "gn:timezone":"Asia/Shanghai",
    "iso:country":"CN",
    "name:zho_x_preferred":[
        "\u8881\u5bb6\u5e97\u5b50"
    ],
    "wof:name":"Yuanjia Dianzi",
    "wof:placetype":"locality"
},
  "geometry": {"coordinates":[107.37961,30.23153],"type":"Point"}
}