{
  "type": "Feature",
  "properties": {
    "gn:admin1_code":"15.0",
    "gn:asciiname":"Baiyin",
    "gn:country_code":"CN",
    "gn:dem":2168,
    "gn:feature_class":"P",
    "gn:feature_code":"PPLA4",
    "gn:name":"Baiyin",
    "gn:population":0,
    "gn:timezone":"Asia/Shanghai",
    "iso:country":"CN",
    "name:ara_x_preferred":[
        "\u0628\u0627\u064a\u064a\u0646"
    ],
    "name:cdo_x_preferred":[
        "B\u0103h-ng\u1e73\u0300ng"
    ],
    "name:ceb_x_preferred":[
        "Baiyin"
    ],
    "name:ces_x_preferred":[
        "Paj-jin"
    ],
    "name:dan_x_preferred":[
        "Baiyin"
    ],
    "name:deu_x_preferred":[
        "Baiyin"
    ],
    "name:est_x_preferred":[
        "Baiyin"
    ],
    "name:eus_x_preferred":[
        "Baiyin"
    ],
    "name:fas_x_preferred":[
        "\u0628\u0627\u06cc\u06cc\u0646"
    ],
    "name:fin_x_preferred":[
        "Baiyin"
    ],
    "name:fra_x_preferred":[
        "Baiyin"
    ],
    "name:hye_x_preferred":[
        "\u0532\u0561\u0575\u056b\u0576"
    ],
    "name:ita_x_preferred":[
        "Baiyin"
    ],
    "name:jpn_x_preferred":[
        "\u767d\u9280\u5e02"
    ],
    "name:kik_x_preferred":[
        "Baiyin"
    ],
    "name:kor_x_preferred":[
        "\ubc14\uc774\uc778\uc2dc"
    ],
    "name:mlg_x_preferred":[
        "Baiyin"
    ],
    "name:nld_x_preferred":[
        "Baiyin"
    ],
    "name:nno_x_preferred":[
        "Baiyin"
    ],
    "name:nor_x_preferred":[
        "Baiyin"
    ],
    "name:pam_x_preferred":[
        "Baiyin"
    ],
    "name:pnb_x_preferred":[
        "\u0628\u0627\u0626\u06cc \u06cc\u0646"
    ],
    "name:pol_x_preferred":[
        "Baiyin"
    ],
    "name:rus_x_preferred":[
        "\u0411\u0430\u0439\u0438\u043d\u044c"
    ],
    "name:sco_x_preferred":[
        "Baiyin"
    ],
    "name:spa_x_preferred":[
        "Baiyin"
    ],
    "name:swe_x_preferred":[
        "Baiyin"
    ],
    "name:tgl_x_preferred":[
        "Baiyin"
    ],
    "name:tur_x_preferred":[
        "Baiyin"
    ],
    "name:und_x_variant":[
        "Baiyin Mengguzu Xiang"
    ],
    "name:urd_x_preferred":[
        "\u0628\u0627\u0626\u06cc\u06cc\u0646"
    ],
    "name:vie_x_preferred":[
        "B\u1ea1ch Ng\u00e2n"
    ],
    "name:war_x_preferred":[
        "Baiyin"
    ],
    "name:wuu_x_preferred":[
        "\u767d\u94f6\u5e02"
    ],
    "name:zho_x_preferred":[
        "\u767d\u94f6"
    ],
    "name:zho_x_variant":[
        "\u767d\u94f6\u8499\u53e4\u65cf\u4e61",
        "\u767d\u94f6\u5e02"
    ],
    "wof:name":"Baiyin",
    "wof:placetype":"locality"
},
  "geometry": {"coordinates":[99.88851,38.91824],"type":"Point"}
}