{
  "type": "Feature",
  "properties": {
    "gn:country":"CN",
    "gn:fcode":"PPL",
    "gn:population":385,
    "iso:country":"CN",
    "name:nor_x_preferred":[
        "Shimenkan-demningen"
    ],
    "name:ukr_x_preferred":[
        "\u0413\u0415\u0421 \u0428\u0438\u043c\u0435\u043d\u043a\u0430\u043d"
    ],
    "name:und_x_variant":[
        "Shih-k\u2019an-men"
    ],
    "name:zho_x_preferred":[
        "\u77f3\u95e8\u574e"
    ],
    "qs:name":"Shimenkan",
    "qs:photos_9r":0,
    "qs:photos_sr":0,
    "qs:pop_sr":"2",
    "wd:wordcount":163,
    "wof:name":"Shimenkan",
    "wof:placetype":"locality",
    "wof:population":385
},
  "geometry": {"coordinates":[106.76443999999999,28.10556],"type":"Point"}
}