{
  "type": "Feature",
  "properties": {
    "gn:admin1_code":"19.0",
    "gn:asciiname":"Wangguanzhaicun",
    "gn:country_code":"CN",
    "gn:dem":15,
    "gn:feature_class":"P",
    "gn:feature_code":"PPL",
    "gn:name":"Wangguanzhaicun",
    "gn:population":0,
    "gn:timezone":"Asia/Shanghai",
    "iso:country":"CN",
    "name:zho_x_preferred":[
        "\u738b\u5b98\u5be8\u6751"
    ],
    "wof:name":"Wangguanzhaicun",
    "wof:placetype":"locality"
},
  "geometry": {"coordinates":[121.82899999999999,39.0603],"type":"Point"}
}