{
  "type": "Feature",
  "properties": {
    "gn:admin1_code":"4.0",
    "gn:asciiname":"Shenhecun",
    "gn:country_code":"CN",
    "gn:dem":3,
    "gn:feature_class":"P",
    "gn:feature_code":"PPL",
    "gn:name":"Shenhecun",
    "gn:population":0,
    "gn:timezone":"Asia/Shanghai",
    "iso:country":"CN",
    "name:zho_x_preferred":[
        "\u6c88\u6cb3\u6751"
    ],
    "wof:name":"Shenhecun",
    "wof:placetype":"locality"
},
  "geometry": {"coordinates":[120.52786999999999,32.82332],"type":"Point"}
}