{
  "type": "Feature",
  "properties": {
    "gn:admin1_code":"16.0",
    "gn:asciiname":"Qishe",
    "gn:country_code":"CN",
    "gn:dem":1093,
    "gn:feature_class":"P",
    "gn:feature_code":"PPL",
    "gn:name":"Qishe",
    "gn:population":0,
    "gn:timezone":"Asia/Shanghai",
    "iso:country":"CN",
    "name:zho_x_preferred":[
        "\u4e03\u8bbe"
    ],
    "wof:name":"Qishe",
    "wof:placetype":"locality"
},
  "geometry": {"coordinates":[106.68600000000001,24.9195],"type":"Point"}
}