{
  "type": "Feature",
  "properties": {
    "gn:admin1_code":"16.0",
    "gn:asciiname":"Yanping",
    "gn:country_code":"CN",
    "gn:dem":45,
    "gn:feature_class":"P",
    "gn:feature_code":"PPL",
    "gn:name":"Yanping",
    "gn:population":0,
    "gn:timezone":"Asia/Shanghai",
    "iso:country":"CN",
    "name:ceb_x_preferred":[
        "Yanping"
    ],
    "name:zho_x_preferred":[
        "\u71d5\u576a"
    ],
    "wof:name":"Yanping",
    "wof:placetype":"locality"
},
  "geometry": {"coordinates":[109.072,22.0914],"type":"Point"}
}