{
  "type": "Feature",
  "properties": {
    "gn:admin1_code":"15.0",
    "gn:asciiname":"Chengjiazhuang",
    "gn:country_code":"CN",
    "gn:dem":1460,
    "gn:feature_class":"P",
    "gn:feature_code":"PPL",
    "gn:name":"Chengjiazhuang",
    "gn:population":0,
    "gn:timezone":"Asia/Shanghai",
    "iso:country":"CN",
    "name:zho_x_preferred":[
        "\u7a0b\u5bb6\u5e84"
    ],
    "wof:name":"Chengjiazhuang",
    "wof:placetype":"locality"
},
  "geometry": {"coordinates":[98.6413,39.6428],"type":"Point"}
}