{
  "type": "Feature",
  "properties": {
    "gn:admin1_code":"3.0",
    "gn:asciiname":"Guanmei",
    "gn:country_code":"CN",
    "gn:dem":89,
    "gn:feature_class":"P",
    "gn:feature_code":"PPL",
    "gn:name":"Guanmei",
    "gn:population":0,
    "gn:timezone":"Asia/Shanghai",
    "iso:country":"CN",
    "name:und_x_variant":[
        "\u89c2\u7f8e"
    ],
    "wof:name":"Guanmei",
    "wof:placetype":"locality"
},
  "geometry": {"coordinates":[115.62212,29.0446],"type":"Point"}
}