{
  "type": "Feature",
  "properties": {
    "gn:admin1_code":"32.0",
    "gn:asciiname":"Longtanzi",
    "gn:country_code":"CN",
    "gn:dem":376,
    "gn:feature_class":"P",
    "gn:feature_code":"PPL",
    "gn:name":"Longtanzi",
    "gn:population":0,
    "gn:timezone":"Asia/Shanghai",
    "iso:country":"CN",
    "name:zho_x_preferred":[
        "\u9f99\u6f6d\u5b50"
    ],
    "wof:name":"Longtanzi",
    "wof:placetype":"locality"
},
  "geometry": {"coordinates":[105.54040000000001,31.10943],"type":"Point"}
}