{
  "type": "Feature",
  "properties": {
    "gn:admin1_code":"10.0",
    "gn:asciiname":"Chengjiaozhuang",
    "gn:country_code":"CN",
    "gn:dem":79,
    "gn:feature_class":"P",
    "gn:feature_code":"PPL",
    "gn:name":"Chengjiaozhuang",
    "gn:population":0,
    "gn:timezone":"Asia/Shanghai",
    "iso:country":"CN",
    "name:zho_x_preferred":[
        "\u57ce\u89d2\u5e84"
    ],
    "wof:name":"Chengjiaozhuang",
    "wof:placetype":"locality"
},
  "geometry": {"coordinates":[119.06632999999999,40.02153],"type":"Point"}
}