{
  "type": "Feature",
  "properties": {
    "gn:admin1_code":"18",
    "gn:asciiname":"Wozituo",
    "gn:country_code":"CN",
    "gn:dem":937,
    "gn:feature_class":"P",
    "gn:feature_code":"PPL",
    "gn:name":"Wozituo",
    "gn:population":0,
    "gn:timezone":"Asia/Shanghai",
    "iso:country":"CN",
    "name:zho_x_preferred":[
        "\u7a9d\u5b50\u5768"
    ],
    "wof:name":"Wozituo",
    "wof:placetype":"locality"
},
  "geometry": {"coordinates":[107.967,28.9493],"type":"Point"}
}