{
  "type": "Feature",
  "properties": {
    "gn:admin1_code":"5.0",
    "gn:asciiname":"Tongling Wobucun",
    "gn:country_code":"CN",
    "gn:dem":155,
    "gn:feature_class":"P",
    "gn:feature_code":"PPL",
    "gn:name":"Tongling Wobucun",
    "gn:population":0,
    "gn:timezone":"Asia/Shanghai",
    "iso:country":"CN",
    "name:zho_x_preferred":[
        "\u7edf\u9886\u7a9d\u5821\u6751"
    ],
    "wof:name":"Tongling Wobucun",
    "wof:placetype":"locality"
},
  "geometry": {"coordinates":[123.95223,44.64507],"type":"Point"}
}