{
  "type": "Feature",
  "properties": {
    "gn:admin1_code":"15.0",
    "gn:asciiname":"Risai",
    "gn:country_code":"CN",
    "gn:dem":3136,
    "gn:feature_class":"P",
    "gn:feature_code":"PPL",
    "gn:name":"Risai",
    "gn:population":0,
    "gn:timezone":"Asia/Shanghai",
    "iso:country":"CN",
    "name:und_x_variant":[
        "\u65e5\u8d5b"
    ],
    "wof:name":"Risai",
    "wof:placetype":"locality"
},
  "geometry": {"coordinates":[102.99458,35.01311],"type":"Point"}
}