{
  "type": "Feature",
  "properties": {
    "gn:admin1_code":"29.0",
    "gn:asciiname":"Baizhilang",
    "gn:country_code":"CN",
    "gn:dem":2532,
    "gn:feature_class":"P",
    "gn:feature_code":"PPL",
    "gn:name":"Baizhilang",
    "gn:population":0,
    "gn:timezone":"Asia/Shanghai",
    "iso:country":"CN",
    "name:zho_x_preferred":[
        "\u767d\u76f4\u6d6a"
    ],
    "wof:name":"Baizhilang",
    "wof:placetype":"locality"
},
  "geometry": {"coordinates":[99.0504,27.6512],"type":"Point"}
}