{
  "type": "Feature",
  "properties": {
    "gn:admin1_code":"19.0",
    "gn:asciiname":"Xialingdaogou",
    "gn:country_code":"CN",
    "gn:dem":179,
    "gn:feature_class":"P",
    "gn:feature_code":"PPL",
    "gn:name":"Xialingdaogou",
    "gn:population":0,
    "gn:timezone":"Asia/Shanghai",
    "iso:country":"CN",
    "name:und_x_variant":[
        "\u4e0b\u5cad\u9053\u6c9f"
    ],
    "name:zho_x_preferred":[
        "\u4e0b\u5cad\u9053\u6c9f"
    ],
    "wof:name":"Xialingdaogou",
    "wof:placetype":"locality"
},
  "geometry": {"coordinates":[125.29443999999999,40.68271],"type":"Point"}
}