{
  "type": "Feature",
  "properties": {
    "gn:admin1_code":"14.0",
    "gn:asciiname":"Kadoi",
    "gn:country_code":"CN",
    "gn:dem":3717,
    "gn:feature_class":"P",
    "gn:feature_code":"PPL",
    "gn:name":"Kadoi",
    "gn:population":0,
    "gn:timezone":"Asia/Urumqi",
    "iso:country":"CN",
    "name:bod_x_preferred":[
        "Kadoi"
    ],
    "name:zho_x_preferred":[
        "Kadui"
    ],
    "name:zho_x_variant":[
        "\u5361\u5806"
    ],
    "wof:name":"Kadoi",
    "wof:placetype":"locality"
},
  "geometry": {"coordinates":[97.11815,30.8537],"type":"Point"}
}