{
  "type": "Feature",
  "properties": {
    "gn:admin1_code":"3.0",
    "gn:asciiname":"Baimilong",
    "gn:country_code":"CN",
    "gn:dem":234,
    "gn:feature_class":"P",
    "gn:feature_code":"PPL",
    "gn:name":"Baimilong",
    "gn:population":0,
    "gn:timezone":"Asia/Shanghai",
    "iso:country":"CN",
    "name:zho_x_preferred":[
        "\u767d\u7c73\u5784"
    ],
    "wof:name":"Baimilong",
    "wof:placetype":"locality"
},
  "geometry": {"coordinates":[117.09078999999998,27.79033],"type":"Point"}
}