{
  "type": "Feature",
  "properties": {
    "gn:admin1_code":"32.0",
    "gn:asciiname":"Wali",
    "gn:country_code":"CN",
    "gn:dem":3191,
    "gn:feature_class":"P",
    "gn:feature_code":"PPL",
    "gn:name":"Wali",
    "gn:population":0,
    "gn:timezone":"Asia/Shanghai",
    "iso:country":"CN",
    "name:zho_x_preferred":[
        "\u5a03\u91cc"
    ],
    "wof:name":"Wali",
    "wof:placetype":"locality"
},
  "geometry": {"coordinates":[100.309,30.4394],"type":"Point"}
}