{
  "type": "Feature",
  "properties": {
    "gn:admin1_code":"32.0",
    "gn:asciiname":"Wali",
    "gn:country_code":"CN",
    "gn:dem":3191,
    "gn:feature_class":"P",
    "gn:feature_code":"PPL",
    "gn:name":"Wali",
    "gn:population":0,
    "gn:timezone":"Asia/Shanghai",
    "iso:country":"CN",
    "name:ara_x_preferred":[
        "\u0648\u0644\u064a"
    ],
    "name:aze_x_preferred":[
        "\u018fl-V\u0259li"
    ],
    "name:ben_x_preferred":[
        "\u0993\u09af\u09bc\u09be\u09b2\u09bf"
    ],
    "name:bul_x_preferred":[
        "\u0412\u0430\u043b\u0438\u044f"
    ],
    "name:cat_x_preferred":[
        "Val\u00ed"
    ],
    "name:deu_x_preferred":[
        "Wal\u012b"
    ],
    "name:epo_x_preferred":[
        "\u016calio"
    ],
    "name:fas_x_preferred":[
        "\u0648\u0644\u06cc"
    ],
    "name:fra_x_preferred":[
        "Wali"
    ],
    "name:heb_x_preferred":[
        "\u05d5\u05dc\u05d9"
    ],
    "name:ind_x_preferred":[
        "Wali"
    ],
    "name:ita_x_preferred":[
        "Wali"
    ],
    "name:lav_x_preferred":[
        "Vali"
    ],
    "name:mkd_x_preferred":[
        "\u0412\u0430\u043b\u0438\u0458\u0430"
    ],
    "name:msa_x_preferred":[
        "Wali"
    ],
    "name:nld_x_preferred":[
        "Wali"
    ],
    "name:pol_x_preferred":[
        "Wali"
    ],
    "name:por_x_preferred":[
        "Uale"
    ],
    "name:ron_x_preferred":[
        "Wali"
    ],
    "name:rus_x_preferred":[
        "\u0412\u0430\u043b\u0438"
    ],
    "name:spa_x_preferred":[
        "Val\u00ed"
    ],
    "name:sqi_x_preferred":[
        "Evlija"
    ],
    "name:srp_x_preferred":[
        "\u0412\u0430\u043b\u0438\u0458\u0430"
    ],
    "name:swa_x_preferred":[
        "Liwali"
    ],
    "name:swe_x_preferred":[
        "Vali"
    ],
    "name:tur_x_preferred":[
        "Vel\u00ee"
    ],
    "name:ukr_x_preferred":[
        "\u0412\u0430\u043b\u0456"
    ],
    "name:urd_x_preferred":[
        "\u0648\u0644\u06cc"
    ],
    "name:zho_x_preferred":[
        "\u5a03\u91cc"
    ],
    "name:zho_x_variant":[
        "\u74e6\u5229"
    ],
    "wof:name":"Wali",
    "wof:placetype":"locality"
},
  "geometry": {"coordinates":[100.309,30.4394],"type":"Point"}
}