{
  "type": "Feature",
  "properties": {
    "gn:admin1_code":"32.0",
    "gn:asciiname":"Huadiao",
    "gn:country_code":"CN",
    "gn:dem":2352,
    "gn:feature_class":"P",
    "gn:feature_code":"PPL",
    "gn:name":"Huadiao",
    "gn:population":0,
    "gn:timezone":"Asia/Shanghai",
    "iso:country":"CN",
    "name:zho_x_preferred":[
        "\u82b1\u7889"
    ],
    "wof:name":"Huadiao",
    "wof:placetype":"locality"
},
  "geometry": {"coordinates":[101.44499999999999,27.44400000000001],"type":"Point"}
}