{
  "type": "Feature",
  "properties": {
    "gn:admin1_code":"4.0",
    "gn:asciiname":"Lianghecun",
    "gn:country_code":"CN",
    "gn:dem":-2,
    "gn:feature_class":"P",
    "gn:feature_code":"PPL",
    "gn:name":"Lianghecun",
    "gn:population":0,
    "gn:timezone":"Asia/Shanghai",
    "iso:country":"CN",
    "name:zho_x_preferred":[
        "\u4e24\u6cb3\u6751"
    ],
    "wof:name":"Lianghecun",
    "wof:placetype":"locality"
},
  "geometry": {"coordinates":[119.8869,33.79108],"type":"Point"}
}