{
  "type": "Feature",
  "properties": {
    "gn:admin1_code":"30.0",
    "gn:asciiname":"Shuanggan Nongchang",
    "gn:country_code":"CN",
    "gn:dem":79,
    "gn:feature_class":"P",
    "gn:feature_code":"PPLF",
    "gn:name":"Shuanggan Nongchang",
    "gn:population":0,
    "gn:timezone":"Asia/Shanghai",
    "iso:country":"CN",
    "name:zho_x_preferred":[
        "\u53cc\u7518\u519c\u573a"
    ],
    "wof:name":"Shuanggan Nongchang",
    "wof:placetype":"locality"
},
  "geometry": {"coordinates":[112.05105,24.08286],"type":"Point"}
}