{
  "type": "Feature",
  "properties": {
    "gn:admin1_code":"4.0",
    "gn:asciiname":"Shangnong Erdui",
    "gn:country_code":"CN",
    "gn:dem":2,
    "gn:feature_class":"P",
    "gn:feature_code":"PPLF",
    "gn:name":"Shangnong Erdui",
    "gn:population":0,
    "gn:timezone":"Asia/Shanghai",
    "iso:country":"CN",
    "name:und_x_variant":[
        "\u4e0a\u519c\u4e8c\u961f"
    ],
    "wof:name":"Shangnong Erdui",
    "wof:placetype":"locality"
},
  "geometry": {"coordinates":[120.51694000000001,33.35415],"type":"Point"}
}