{
  "type": "Feature",
  "properties": {
    "gn:admin1_code":"30",
    "gn:asciiname":"Jiantou",
    "gn:country_code":"CN",
    "gn:dem":61,
    "gn:feature_class":"P",
    "gn:feature_code":"PPL",
    "gn:name":"Jiantou",
    "gn:population":0,
    "gn:timezone":"Asia/Shanghai",
    "iso:country":"CN",
    "name:zho_x_preferred":[
        "\u7b80\u5934"
    ],
    "wof:name":"Jiantou",
    "wof:placetype":"locality"
},
  "geometry": {"coordinates":[116.50104,24.36042],"type":"Point"}
}