{
  "type": "Feature",
  "properties": {
    "gn:admin1_code":"32.0",
    "gn:asciiname":"Puchao",
    "gn:country_code":"CN",
    "gn:dem":319,
    "gn:feature_class":"P",
    "gn:feature_code":"PPL",
    "gn:name":"Puchao",
    "gn:population":0,
    "gn:timezone":"Asia/Shanghai",
    "iso:country":"CN",
    "name:zho_x_preferred":[
        "\u666e\u6f6e"
    ],
    "wof:name":"Puchao",
    "wof:placetype":"locality"
},
  "geometry": {"coordinates":[105.29600000000001,28.8448],"type":"Point"}
}