{
  "type": "Feature",
  "properties": {
    "gn:admin1_code":"2.0",
    "gn:asciiname":"Fangdi",
    "gn:country_code":"CN",
    "gn:dem":97,
    "gn:feature_class":"P",
    "gn:feature_code":"PPL",
    "gn:name":"Fangdi",
    "gn:population":0,
    "gn:timezone":"Asia/Shanghai",
    "iso:country":"CN",
    "name:und_x_variant":[
        "\u82b3\u5730",
        "Fangdi"
    ],
    "wof:name":"Fangdi",
    "wof:placetype":"locality"
},
  "geometry": {"coordinates":[119.95465,29.50154],"type":"Point"}
}