{
  "type": "Feature",
  "properties": {
    "gn:admin1_code":"15.0",
    "gn:asciiname":"Wutongquan",
    "gn:country_code":"CN",
    "gn:dem":1723,
    "gn:feature_class":"P",
    "gn:feature_code":"PPL",
    "gn:name":"Wutongquan",
    "gn:population":0,
    "gn:timezone":"Asia/Shanghai",
    "iso:country":"CN",
    "name:zho_x_preferred":[
        "\u68a7\u6850\u6cc9"
    ],
    "wof:name":"Wutongquan",
    "wof:placetype":"locality"
},
  "geometry": {"coordinates":[99.6392,39.2463],"type":"Point"}
}