{
  "type": "Feature",
  "properties": {
    "gn:admin1_code":"26",
    "gn:asciiname":"Fujia",
    "gn:country_code":"CN",
    "gn:dem":413,
    "gn:feature_class":"P",
    "gn:feature_code":"PPL",
    "gn:name":"Fujia",
    "gn:population":0,
    "gn:timezone":"Asia/Shanghai",
    "iso:country":"CN",
    "name:und_x_variant":[
        "Fujiacun"
    ],
    "name:zho_x_preferred":[
        "\u4ed8\u5bb6"
    ],
    "wof:name":"Fujia",
    "wof:placetype":"locality"
},
  "geometry": {"coordinates":[108.78028,34.5475],"type":"Point"}
}