{
  "type": "Feature",
  "properties": {
    "gn:admin1_code":"08",
    "gn:asciiname":"Dahaozi",
    "gn:country_code":"CN",
    "gn:dem":144,
    "gn:feature_class":"P",
    "gn:feature_code":"PPL",
    "gn:name":"Dahaozi",
    "gn:population":0,
    "gn:timezone":"Asia/Shanghai",
    "iso:country":"CN",
    "name:und_x_variant":[
        "Ta-hao-tzu",
        "Dahaozi"
    ],
    "name:zho_x_preferred":[
        "\u5927\u84bf\u5b50"
    ],
    "wof:name":"Dahaozi",
    "wof:placetype":"locality"
},
  "geometry": {"coordinates":[124.15988,47.00128],"type":"Point"}
}