{
  "type": "Feature",
  "properties": {
    "gn:admin1_code":"20.0",
    "gn:asciiname":"Lihaidaigou",
    "gn:country_code":"CN",
    "gn:dem":1562,
    "gn:feature_class":"P",
    "gn:feature_code":"PPL",
    "gn:name":"Lihaidaigou",
    "gn:population":0,
    "gn:timezone":"Asia/Shanghai",
    "iso:country":"CN",
    "name:und_x_variant":[
        "\u674e\u6d77\u4ee3\u6c9f"
    ],
    "wof:name":"Lihaidaigou",
    "wof:placetype":"locality"
},
  "geometry": {"coordinates":[113.12248999999998,41.34103],"type":"Point"}
}