{
  "type": "Feature",
  "properties": {
    "gn:admin1_code":"22",
    "gn:asciiname":"Qizhuang",
    "gn:country_code":"CN",
    "gn:dem":93,
    "gn:feature_class":"P",
    "gn:feature_code":"PPL",
    "gn:name":"Qizhuang",
    "gn:population":0,
    "gn:timezone":"Asia/Shanghai",
    "iso:country":"CN",
    "name:zho_x_preferred":[
        "\u5c90\u5e84"
    ],
    "wof:name":"Qizhuang",
    "wof:placetype":"locality"
},
  "geometry": {"coordinates":[116.52408,40.32248],"type":"Point"}
}