{
  "type": "Feature",
  "properties": {
    "gn:admin1_code":"19.0",
    "gn:asciiname":"Fengyuancun",
    "gn:country_code":"CN",
    "gn:dem":98,
    "gn:feature_class":"P",
    "gn:feature_code":"PPL",
    "gn:name":"Fengyuancun",
    "gn:population":0,
    "gn:timezone":"Asia/Shanghai",
    "iso:country":"CN",
    "name:zho_x_preferred":[
        "\u4e30\u6e90\u6751"
    ],
    "wof:name":"Fengyuancun",
    "wof:placetype":"locality"
},
  "geometry": {"coordinates":[123.83047000000001,42.96464],"type":"Point"}
}