{
  "type": "Feature",
  "properties": {
    "gn:admin1_code":"18",
    "gn:asciiname":"Bawancun",
    "gn:country_code":"CN",
    "gn:dem":806,
    "gn:feature_class":"P",
    "gn:feature_code":"PPL",
    "gn:name":"Bawancun",
    "gn:population":0,
    "gn:timezone":"Asia/Shanghai",
    "iso:country":"CN",
    "name:zho_x_preferred":[
        "\u575d\u4e07\u6751"
    ],
    "wof:name":"Bawancun",
    "wof:placetype":"locality"
},
  "geometry": {"coordinates":[104.68600000000001,24.6646],"type":"Point"}
}