{
  "type": "Feature",
  "properties": {
    "gn:admin1_code":"30.0",
    "gn:asciiname":"Foziwei",
    "gn:country_code":"CN",
    "gn:dem":194,
    "gn:feature_class":"P",
    "gn:feature_code":"PPL",
    "gn:name":"Foziwei",
    "gn:population":0,
    "gn:timezone":"Asia/Shanghai",
    "iso:country":"CN",
    "name:zho_x_preferred":[
        "\u4f5b\u5b50\u56f4"
    ],
    "wof:name":"Foziwei",
    "wof:placetype":"locality"
},
  "geometry": {"coordinates":[113.57778,24.11556],"type":"Point"}
}