{
  "type": "Feature",
  "properties": {
    "gn:admin1_code":"29.0",
    "gn:asciiname":"Weijiaqing",
    "gn:country_code":"CN",
    "gn:dem":2062,
    "gn:feature_class":"P",
    "gn:feature_code":"PPL",
    "gn:name":"Weijiaqing",
    "gn:population":0,
    "gn:timezone":"Asia/Shanghai",
    "iso:country":"CN",
    "name:zho_x_preferred":[
        "\u56f4\u5bb6\u7b90"
    ],
    "wof:name":"Weijiaqing",
    "wof:placetype":"locality"
},
  "geometry": {"coordinates":[103.41500000000001,26.5624],"type":"Point"}
}