{
  "type": "Feature",
  "properties": {
    "gn:admin1_code":"14.0",
    "gn:asciiname":"Nianxueka",
    "gn:country_code":"CN",
    "gn:dem":3711,
    "gn:feature_class":"P",
    "gn:feature_code":"PPL",
    "gn:name":"Nianxueka",
    "gn:population":0,
    "gn:timezone":"Asia/Urumqi",
    "iso:country":"CN",
    "name:zho_x_preferred":[
        "\u5e74\u96ea\u5361"
    ],
    "wof:name":"Nianxueka",
    "wof:placetype":"locality"
},
  "geometry": {"coordinates":[94.45932000000001,31.24956],"type":"Point"}
}