{
  "type": "Feature",
  "properties": {
    "gn:admin1_code":"15.0",
    "gn:asciiname":"Yangjiazhuang",
    "gn:country_code":"CN",
    "gn:dem":1676,
    "gn:feature_class":"P",
    "gn:feature_code":"PPL",
    "gn:name":"Yangjiazhuang",
    "gn:population":0,
    "gn:timezone":"Asia/Shanghai",
    "iso:country":"CN",
    "name:und_x_variant":[
        "\u6768\u5bb6\u5e84"
    ],
    "wof:name":"Yangjiazhuang",
    "wof:placetype":"locality"
},
  "geometry": {"coordinates":[105.22824,33.86554],"type":"Point"}
}