{
  "type": "Feature",
  "properties": {
    "gn:admin1_code":"26.0",
    "gn:asciiname":"Jinhuacun",
    "gn:country_code":"CN",
    "gn:dem":449,
    "gn:feature_class":"P",
    "gn:feature_code":"PPL",
    "gn:name":"Jinhuacun",
    "gn:population":0,
    "gn:timezone":"Asia/Shanghai",
    "iso:country":"CN",
    "name:zho_x_preferred":[
        "\u91d1\u534e\u6751"
    ],
    "wof:name":"Jinhuacun",
    "wof:placetype":"locality"
},
  "geometry": {"coordinates":[109.03158999999999,32.77079000000001],"type":"Point"}
}