{
  "type": "Feature",
  "properties": {
    "gn:admin1_code":"25",
    "gn:asciiname":"Botou",
    "gn:cc2":"CN",
    "gn:country_code":"CN",
    "gn:dem":6,
    "gn:feature_class":"P",
    "gn:feature_code":"PPL",
    "gn:name":"Botou",
    "gn:population":0,
    "gn:timezone":"Asia/Shanghai",
    "iso:country":"CN",
    "name:ara_x_preferred":[
        "\u0628\u0648\u062a\u0648\u0648"
    ],
    "name:ceb_x_preferred":[
        "Botou Shi"
    ],
    "name:deu_x_preferred":[
        "Botou"
    ],
    "name:fra_x_preferred":[
        "Botou"
    ],
    "name:ita_x_preferred":[
        "Botou"
    ],
    "name:jpn_x_preferred":[
        "\u6cca\u982d\u5e02"
    ],
    "name:kik_x_preferred":[
        "Botou"
    ],
    "name:kor_x_preferred":[
        "\ubcf4\ud130\uc6b0\uc2dc"
    ],
    "name:mlg_x_preferred":[
        "Botou"
    ],
    "name:nor_x_preferred":[
        "Botou"
    ],
    "name:pam_x_preferred":[
        "Botou"
    ],
    "name:rus_x_preferred":[
        "\u0411\u043e\u0442\u043e\u0443"
    ],
    "name:swe_x_preferred":[
        "Botou"
    ],
    "name:und_x_variant":[
        "Po-t\u2019ou-chen",
        "Chu-t\u2019ou-chen",
        "Potowchen",
        "Po-t\u2019ou",
        "Botou"
    ],
    "name:urd_x_preferred":[
        "\u0628\u0648\u062a\u0648\u0648"
    ],
    "name:vie_x_preferred":[
        "B\u1ea1c \u0110\u1ea7u"
    ],
    "name:zho_x_preferred":[
        "\u6cca\u5934\u5e02"
    ],
    "wof:name":"Botou",
    "wof:placetype":"locality"
},
  "geometry": {"coordinates":[117.56889,38.04222],"type":"Point"}
}