{
  "type": "Feature",
  "properties": {
    "gn:admin1_code":"19.0",
    "gn:asciiname":"Luanshijian",
    "gn:country_code":"CN",
    "gn:dem":295,
    "gn:feature_class":"P",
    "gn:feature_code":"PPL",
    "gn:name":"Luanshijian",
    "gn:population":0,
    "gn:timezone":"Asia/Shanghai",
    "iso:country":"CN",
    "name:und_x_variant":[
        "\u4e71\u77f3\u6da7"
    ],
    "wof:name":"Luanshijian",
    "wof:placetype":"locality"
},
  "geometry": {"coordinates":[123.05586,40.57962],"type":"Point"}
}