{
  "type": "Feature",
  "properties": {
    "gn:admin1_code":"29.0",
    "gn:asciiname":"Henkan",
    "gn:country_code":"CN",
    "gn:dem":1011,
    "gn:feature_class":"P",
    "gn:feature_code":"PPL",
    "gn:name":"Henkan",
    "gn:population":0,
    "gn:timezone":"Asia/Shanghai",
    "iso:country":"CN",
    "name:zho_x_preferred":[
        "\u5f88\u574e"
    ],
    "wof:name":"Henkan",
    "wof:placetype":"locality"
},
  "geometry": {"coordinates":[103.96299999999999,24.4496],"type":"Point"}
}