{
  "type": "Feature",
  "properties": {
    "gn:admin1_code":"29",
    "gn:asciiname":"Baichimi",
    "gn:country_code":"CN",
    "gn:dem":2144,
    "gn:feature_class":"P",
    "gn:feature_code":"PPL",
    "gn:name":"Baichimi",
    "gn:population":0,
    "gn:timezone":"Asia/Shanghai",
    "iso:country":"CN",
    "name:zho_x_preferred":[
        "\u767d\u5c3a\u54aa"
    ],
    "wof:name":"Baichimi",
    "wof:placetype":"locality"
},
  "geometry": {"coordinates":[101.336,24.9727],"type":"Point"}
}