{
  "type": "Feature",
  "properties": {
    "gn:admin1_code":"11",
    "gn:asciiname":"Yantianpo",
    "gn:country_code":"CN",
    "gn:dem":168,
    "gn:feature_class":"P",
    "gn:feature_code":"PPL",
    "gn:name":"Yantianpo",
    "gn:population":0,
    "gn:timezone":"Asia/Shanghai",
    "iso:country":"CN",
    "name:zho_x_preferred":[
        "\u5ca9\u7530\u5761"
    ],
    "wof:name":"Yantianpo",
    "wof:placetype":"locality"
},
  "geometry": {"coordinates":[109.71203,27.86946],"type":"Point"}
}