{
  "type": "Feature",
  "properties": {
    "gn:admin1_code":"11",
    "gn:asciiname":"Dalei",
    "gn:country_code":"CN",
    "gn:dem":626,
    "gn:feature_class":"P",
    "gn:feature_code":"PPL",
    "gn:name":"Dalei",
    "gn:population":0,
    "gn:timezone":"Asia/Shanghai",
    "iso:country":"CN",
    "name:und_x_variant":[
        "\u5927\u6f2f",
        "Dalei"
    ],
    "wof:name":"Dalei",
    "wof:placetype":"locality"
},
  "geometry": {"coordinates":[111.95111,25.76583],"type":"Point"}
}