{
  "type": "Feature",
  "properties": {
    "gn:admin1_code":"30.0",
    "gn:asciiname":"Chengchun",
    "gn:country_code":"CN",
    "gn:dem":20,
    "gn:feature_class":"P",
    "gn:feature_code":"PPL",
    "gn:name":"Chengchun",
    "gn:population":0,
    "gn:timezone":"Asia/Shanghai",
    "iso:country":"CN",
    "name:zho_x_preferred":[
        "\u6210\u6625"
    ],
    "wof:name":"Chengchun",
    "wof:placetype":"locality"
},
  "geometry": {"coordinates":[112.41128,22.3655],"type":"Point"}
}