{
  "type": "Feature",
  "properties": {
    "gn:admin1_code":"02",
    "gn:asciiname":"Haicheng",
    "gn:country_code":"CN",
    "gn:dem":6,
    "gn:feature_class":"P",
    "gn:feature_code":"PPL",
    "gn:name":"Haicheng",
    "gn:population":0,
    "gn:timezone":"Asia/Shanghai",
    "iso:country":"CN",
    "name:ceb_x_preferred":[
        "Haicheng"
    ],
    "name:deu_x_preferred":[
        "Haicheng"
    ],
    "name:fra_x_preferred":[
        "Haicheng"
    ],
    "name:nor_x_preferred":[
        "Haicheng"
    ],
    "name:swe_x_preferred":[
        "Haicheng"
    ],
    "wof:name":"Haicheng",
    "wof:placetype":"locality"
},
  "geometry": {"coordinates":[120.58611000000001,27.52222],"type":"Point"}
}