{
  "type": "Feature",
  "properties": {
    "gn:admin1_code":"15.0",
    "gn:asciiname":"Puwan",
    "gn:country_code":"CN",
    "gn:dem":1967,
    "gn:feature_class":"P",
    "gn:feature_code":"PPL",
    "gn:name":"Puwan",
    "gn:population":0,
    "gn:timezone":"Asia/Shanghai",
    "iso:country":"CN",
    "name:und_x_variant":[
        "\u6d66\u6e7e"
    ],
    "wof:name":"Puwan",
    "wof:placetype":"locality"
},
  "geometry": {"coordinates":[105.00095,35.20557],"type":"Point"}
}