{
  "type": "Feature",
  "properties": {
    "gn:admin1_code":"11.0",
    "gn:asciiname":"Yueliangping",
    "gn:country_code":"CN",
    "gn:dem":224,
    "gn:feature_class":"P",
    "gn:feature_code":"PPL",
    "gn:name":"Yueliangping",
    "gn:population":0,
    "gn:timezone":"Asia/Shanghai",
    "iso:country":"CN",
    "name:zho_x_preferred":[
        "Yueliangping"
    ],
    "name:zho_x_variant":[
        "\u6708\u4eae\u576a"
    ],
    "wof:name":"Yueliangping",
    "wof:placetype":"locality"
},
  "geometry": {"coordinates":[110.59695000000001,29.22491],"type":"Point"}
}