{
  "type": "Feature",
  "properties": {
    "gn:admin1_code":"10",
    "gn:asciiname":"Rongcheng",
    "gn:cc2":"CN",
    "gn:country_code":"CN",
    "gn:dem":18,
    "gn:feature_class":"P",
    "gn:feature_code":"PPL",
    "gn:name":"Rongcheng",
    "gn:population":0,
    "gn:timezone":"Asia/Shanghai",
    "iso:country":"CN",
    "name:ceb_x_preferred":[
        "Rongcheng"
    ],
    "name:deu_x_preferred":[
        "Rongcheng"
    ],
    "name:fra_x_preferred":[
        "Rongcheng"
    ],
    "name:nor_x_preferred":[
        "Rongcheng"
    ],
    "name:pol_x_preferred":[
        "Rongcheng"
    ],
    "name:rus_x_preferred":[
        "\u0416\u0443\u043d\u0447\u044d\u043d"
    ],
    "name:swe_x_preferred":[
        "Rongcheng"
    ],
    "name:und_x_variant":[
        "Jung-ch\u2019eng-ch\u2019eng-kuan",
        "Zhunchen\u2019",
        "Jung-ch\u2019eng",
        "Jung-ch\u2019eng-hsien"
    ],
    "wof:name":"Rongcheng",
    "wof:placetype":"locality"
},
  "geometry": {"coordinates":[115.86028,39.0525],"type":"Point"}
}