{
  "type": "Feature",
  "properties": {
    "gn:admin1_code":"5.0",
    "gn:asciiname":"Huoshao Dingzi",
    "gn:country_code":"CN",
    "gn:dem":612,
    "gn:feature_class":"P",
    "gn:feature_code":"PPL",
    "gn:name":"Huoshao Dingzi",
    "gn:population":0,
    "gn:timezone":"Asia/Shanghai",
    "iso:country":"CN",
    "name:zho_x_preferred":[
        "\u706b\u70e7\u9876\u5b50"
    ],
    "wof:name":"Huoshao Dingzi",
    "wof:placetype":"locality"
},
  "geometry": {"coordinates":[126.70853,42.38389],"type":"Point"}
}