{
  "type": "Feature",
  "properties": {
    "gn:admin1_code":"32.0",
    "gn:asciiname":"Guadiyan",
    "gn:country_code":"CN",
    "gn:dem":1881,
    "gn:feature_class":"P",
    "gn:feature_code":"PPL",
    "gn:name":"Guadiyan",
    "gn:population":0,
    "gn:timezone":"Asia/Shanghai",
    "iso:country":"CN",
    "name:zho_x_preferred":[
        "\u74dc\u5730\u5ca9"
    ],
    "wof:name":"Guadiyan",
    "wof:placetype":"locality"
},
  "geometry": {"coordinates":[104.13844,33.07352],"type":"Point"}
}