{
  "type": "Feature",
  "properties": {
    "gn:admin1_code":"30.0",
    "gn:asciiname":"Baishizhang",
    "gn:country_code":"CN",
    "gn:dem":272,
    "gn:feature_class":"P",
    "gn:feature_code":"PPL",
    "gn:name":"Baishizhang",
    "gn:population":0,
    "gn:timezone":"Asia/Shanghai",
    "iso:country":"CN",
    "name:zho_x_preferred":[
        "Baishizhang"
    ],
    "name:zho_x_variant":[
        "\u767d\u77f3\u5d82"
    ],
    "wof:name":"Baishizhang",
    "wof:placetype":"locality"
},
  "geometry": {"coordinates":[114.91454,24.05474],"type":"Point"}
}