{
  "type": "Feature",
  "properties": {
    "gn:admin1_code":"33.0",
    "gn:asciiname":"Shangwangwutuo",
    "gn:country_code":"CN",
    "gn:dem":623,
    "gn:feature_class":"P",
    "gn:feature_code":"PPL",
    "gn:name":"Shangwangwutuo",
    "gn:population":0,
    "gn:timezone":"Asia/Shanghai",
    "iso:country":"CN",
    "name:zho_x_preferred":[
        "\u4e0a\u738b\u6b66\u5768"
    ],
    "wof:name":"Shangwangwutuo",
    "wof:placetype":"locality"
},
  "geometry": {"coordinates":[108.54218,28.73881],"type":"Point"}
}