{
  "type": "Feature",
  "properties": {
    "gn:admin1_code":"16.0",
    "gn:asciiname":"Jinge",
    "gn:country_code":"CN",
    "gn:dem":241,
    "gn:feature_class":"P",
    "gn:feature_code":"PPL",
    "gn:name":"Jinge",
    "gn:population":0,
    "gn:timezone":"Asia/Shanghai",
    "iso:country":"CN",
    "name:zho_x_preferred":[
        "\u9526\u9601"
    ],
    "wof:name":"Jinge",
    "wof:placetype":"locality"
},
  "geometry": {"coordinates":[106.956,22.5808],"type":"Point"}
}