{
  "type": "Feature",
  "properties": {
    "gn:admin1_code":"20.0",
    "gn:asciiname":"Hulai",
    "gn:country_code":"CN",
    "gn:dem":776,
    "gn:feature_class":"P",
    "gn:feature_code":"PPL",
    "gn:name":"Hulai",
    "gn:population":0,
    "gn:timezone":"Asia/Shanghai",
    "iso:country":"CN",
    "name:zho_x_preferred":[
        "\u547c\u8d56"
    ],
    "wof:name":"Hulai",
    "wof:placetype":"locality"
},
  "geometry": {"coordinates":[119.45587,48.37268],"type":"Point"}
}