{
  "type": "Feature",
  "properties": {
    "gn:admin1_code":"7.0",
    "gn:asciiname":"Jiaojing",
    "gn:country_code":"CN",
    "gn:dem":718,
    "gn:feature_class":"P",
    "gn:feature_code":"PPL",
    "gn:name":"Jiaojing",
    "gn:population":0,
    "gn:timezone":"Asia/Shanghai",
    "iso:country":"CN",
    "name:zho_x_preferred":[
        "\u89d2\u4e95"
    ],
    "wof:name":"Jiaojing",
    "wof:placetype":"locality"
},
  "geometry": {"coordinates":[118.8415,27.25321],"type":"Point"}
}