{
  "type": "Feature",
  "properties": {
    "gn:admin1_code":"32.0",
    "gn:asciiname":"Ani'adi",
    "gn:country_code":"CN",
    "gn:dem":2007,
    "gn:feature_class":"P",
    "gn:feature_code":"PPL",
    "gn:name":"Ani\u2019adi",
    "gn:population":0,
    "gn:timezone":"Asia/Shanghai",
    "iso:country":"CN",
    "name:und_x_variant":[
        "Ani\u2019adi"
    ],
    "name:zho_x_preferred":[
        "\u963f\u6ce5\u963f\u5e95"
    ],
    "wof:name":"Ani'adi",
    "wof:placetype":"locality"
},
  "geometry": {"coordinates":[102.754,29.1141],"type":"Point"}
}