{
  "type": "Feature",
  "properties": {
    "gn:admin1_code":"19",
    "gn:asciiname":"Xinmintun",
    "gn:cc2":"CN",
    "gn:country_code":"CN",
    "gn:dem":363,
    "gn:feature_class":"P",
    "gn:feature_code":"PPL",
    "gn:name":"Xinmintun",
    "gn:population":0,
    "gn:timezone":"Asia/Shanghai",
    "iso:country":"CN",
    "name:und_x_variant":[
        "Hsin-li-t\u2019un",
        "Xinmintun",
        "Xinmintuncun"
    ],
    "name:zho_x_preferred":[
        "\u65b0\u6c11\u5c6f\u6751"
    ],
    "wof:name":"Xinmintun",
    "wof:placetype":"locality"
},
  "geometry": {"coordinates":[125.06694,42.21139],"type":"Point"}
}