{
  "type": "Feature",
  "properties": {
    "gn:admin1_code":"15.0",
    "gn:asciiname":"Caochuan",
    "gn:country_code":"CN",
    "gn:dem":2161,
    "gn:feature_class":"P",
    "gn:feature_code":"PPL",
    "gn:name":"Caochuan",
    "gn:population":0,
    "gn:timezone":"Asia/Shanghai",
    "iso:country":"CN",
    "name:zho_x_preferred":[
        "\u8349\u5ddd"
    ],
    "wof:name":"Caochuan",
    "wof:placetype":"locality"
},
  "geometry": {"coordinates":[105.116,34.5545],"type":"Point"}
}