{
  "type": "Feature",
  "properties": {
    "gn:admin1_code":"15.0",
    "gn:asciiname":"Duojia",
    "gn:country_code":"CN",
    "gn:dem":2282,
    "gn:feature_class":"P",
    "gn:feature_code":"PPL",
    "gn:name":"Duojia",
    "gn:population":0,
    "gn:timezone":"Asia/Shanghai",
    "iso:country":"CN",
    "name:und_x_variant":[
        "\u6735\u5bb6"
    ],
    "wof:name":"Duojia",
    "wof:placetype":"locality"
},
  "geometry": {"coordinates":[102.95699999999999,35.8772],"type":"Point"}
}