{
  "type": "Feature",
  "properties": {
    "gn:admin1_code":"3",
    "gn:asciiname":"Taoshupai",
    "gn:country_code":"CN",
    "gn:dem":410,
    "gn:feature_class":"P",
    "gn:feature_code":"PPL",
    "gn:name":"Taoshupai",
    "gn:population":0,
    "gn:timezone":"Asia/Shanghai",
    "iso:country":"CN",
    "name:zho_x_preferred":[
        "\u6843\u6811\u6392"
    ],
    "wof:name":"Taoshupai",
    "wof:placetype":"locality"
},
  "geometry": {"coordinates":[114.70699999999999,26.04],"type":"Point"}
}