{
  "type": "Feature",
  "properties": {
    "gn:admin1_code":"32.0",
    "gn:asciiname":"Lujia'ao",
    "gn:country_code":"CN",
    "gn:dem":1877,
    "gn:feature_class":"P",
    "gn:feature_code":"PPL",
    "gn:name":"Lujia\u2019ao",
    "gn:population":0,
    "gn:timezone":"Asia/Shanghai",
    "iso:country":"CN",
    "name:und_x_variant":[
        "Lujia\u2019ao"
    ],
    "name:zho_x_preferred":[
        "\u5362\u5bb6\u51f9"
    ],
    "wof:name":"Lujia'ao",
    "wof:placetype":"locality"
},
  "geometry": {"coordinates":[102.217,26.6485],"type":"Point"}
}