{
  "type": "Feature",
  "properties": {
    "gn:admin1_code":"8.0",
    "gn:asciiname":"Sanrenban Sidui",
    "gn:country_code":"CN",
    "gn:dem":108,
    "gn:feature_class":"P",
    "gn:feature_code":"PPLF",
    "gn:name":"Sanrenban Sidui",
    "gn:population":0,
    "gn:timezone":"Asia/Shanghai",
    "iso:country":"CN",
    "name:zho_x_preferred":[
        "\u4e09\u4eba\u73ed\u56db\u961f"
    ],
    "wof:name":"Sanrenban Sidui",
    "wof:placetype":"locality"
},
  "geometry": {"coordinates":[132.03149999999999,45.62428],"type":"Point"}
}