{
  "type": "Feature",
  "properties": {
    "gn:admin1_code":"4.0",
    "gn:asciiname":"Qigecun",
    "gn:country_code":"CN",
    "gn:dem":42,
    "gn:feature_class":"P",
    "gn:feature_code":"PPL",
    "gn:name":"Qigecun",
    "gn:population":0,
    "gn:timezone":"Asia/Shanghai",
    "iso:country":"CN",
    "name:zho_x_preferred":[
        "\u9f50\u9601\u6751"
    ],
    "wof:name":"Qigecun",
    "wof:placetype":"locality"
},
  "geometry": {"coordinates":[116.8537,34.54327],"type":"Point"}
}