{
  "type": "Feature",
  "properties": {
    "gn:admin1_code":"15.0",
    "gn:asciiname":"Shijiadi",
    "gn:country_code":"CN",
    "gn:dem":1808,
    "gn:feature_class":"P",
    "gn:feature_code":"PPL",
    "gn:name":"Shijiadi",
    "gn:population":0,
    "gn:timezone":"Asia/Shanghai",
    "iso:country":"CN",
    "name:zho_x_preferred":[
        "\u53f2\u5bb6\u5730"
    ],
    "wof:name":"Shijiadi",
    "wof:placetype":"locality"
},
  "geometry": {"coordinates":[99.0462,39.3067],"type":"Point"}
}