{
  "type": "Feature",
  "properties": {
    "gn:admin1_code":"8.0",
    "gn:asciiname":"Tuanjietun",
    "gn:country_code":"CN",
    "gn:dem":193,
    "gn:feature_class":"P",
    "gn:feature_code":"PPL",
    "gn:name":"Tuanjietun",
    "gn:population":0,
    "gn:timezone":"Asia/Shanghai",
    "iso:country":"CN",
    "name:zho_x_preferred":[
        "\u56e2\u7ed3\u5c6f"
    ],
    "wof:name":"Tuanjietun",
    "wof:placetype":"locality"
},
  "geometry": {"coordinates":[124.59893,48.59748],"type":"Point"}
}