{
  "type": "Feature",
  "properties": {
    "gn:admin1_code":"12.0",
    "gn:asciiname":"Xiaohekou",
    "gn:cc2":"CN",
    "gn:country_code":"CN",
    "gn:dem":451,
    "gn:feature_class":"P",
    "gn:feature_code":"PPL",
    "gn:name":"Xiaohekou",
    "gn:population":0,
    "gn:timezone":"Asia/Shanghai",
    "iso:country":"CN",
    "name:und_x_variant":[
        "Hsiao-ho-k\u2019ou",
        "Xiaohekou"
    ],
    "wof:name":"Xiaohekou",
    "wof:placetype":"locality"
},
  "geometry": {"coordinates":[109.81667,32.31667],"type":"Point"}
}