{
  "type": "Feature",
  "properties": {
    "gn:admin1_code":"32.0",
    "gn:asciiname":"Xiaowan",
    "gn:country_code":"CN",
    "gn:dem":334,
    "gn:feature_class":"P",
    "gn:feature_code":"PPL",
    "gn:name":"Xiaowan",
    "gn:population":0,
    "gn:timezone":"Asia/Shanghai",
    "iso:country":"CN",
    "name:zho_x_preferred":[
        "\u8096\u6e7e"
    ],
    "wof:name":"Xiaowan",
    "wof:placetype":"locality"
},
  "geometry": {"coordinates":[105.15900000000001,29.7184],"type":"Point"}
}