{
  "type": "Feature",
  "properties": {
    "gn:admin1_code":"30.0",
    "gn:asciiname":"Xishengli",
    "gn:country_code":"CN",
    "gn:dem":12,
    "gn:feature_class":"P",
    "gn:feature_code":"PPL",
    "gn:name":"Xishengli",
    "gn:population":0,
    "gn:timezone":"Asia/Shanghai",
    "iso:country":"CN",
    "name:zho_x_preferred":[
        "\u897f\u76db\u91cc"
    ],
    "wof:name":"Xishengli",
    "wof:placetype":"locality"
},
  "geometry": {"coordinates":[112.49636,22.21186],"type":"Point"}
}