{
  "type": "Feature",
  "properties": {
    "gn:admin1_code":"5.0",
    "gn:asciiname":"Xijijia Yingzi",
    "gn:country_code":"CN",
    "gn:dem":126,
    "gn:feature_class":"P",
    "gn:feature_code":"PPL",
    "gn:name":"Xijijia Yingzi",
    "gn:population":0,
    "gn:timezone":"Asia/Shanghai",
    "iso:country":"CN",
    "name:zho_x_preferred":[
        "\u897f\u7eaa\u5bb6\u8425\u5b50"
    ],
    "wof:name":"Xijijia Yingzi",
    "wof:placetype":"locality"
},
  "geometry": {"coordinates":[123.87897,43.46802],"type":"Point"}
}