{
  "type": "Feature",
  "properties": {
    "gn:admin1_code":"29.0",
    "gn:asciiname":"Lulian",
    "gn:country_code":"CN",
    "gn:dem":1507,
    "gn:feature_class":"P",
    "gn:feature_code":"PPL",
    "gn:name":"L\u00fclian",
    "gn:population":0,
    "gn:timezone":"Asia/Shanghai",
    "iso:country":"CN",
    "name:und_x_variant":[
        "L\u00fclian"
    ],
    "name:zho_x_preferred":[
        "\u5415\u8fde"
    ],
    "wof:name":"Lulian",
    "wof:placetype":"locality"
},
  "geometry": {"coordinates":[97.9388,24.4314],"type":"Point"}
}