{
  "type": "Feature",
  "properties": {
    "gn:admin1_code":"33",
    "gn:asciiname":"Lianghui",
    "gn:country_code":"CN",
    "gn:dem":216,
    "gn:feature_class":"P",
    "gn:feature_code":"PPLA4",
    "gn:name":"Lianghui",
    "gn:population":0,
    "gn:timezone":"Asia/Shanghai",
    "iso:country":"CN",
    "name:und_x_variant":[
        "Lianghui Xiang",
        "Xingcangku"
    ],
    "name:zho_x_preferred":[
        "\u4e24\u6c47"
    ],
    "name:zho_x_variant":[
        "\u4e24\u6c47\u4e61",
        "\u65b0\u4ed3\u5e93"
    ],
    "wof:name":"Lianghui",
    "wof:placetype":"locality"
},
  "geometry": {"coordinates":[107.10048,29.63526],"type":"Point"}
}