{
  "type": "Feature",
  "properties": {
    "gn:admin1_code":"26.0",
    "gn:asciiname":"Bazhouying",
    "gn:country_code":"CN",
    "gn:dem":1255,
    "gn:feature_class":"P",
    "gn:feature_code":"PPL",
    "gn:name":"Bazhouying",
    "gn:population":0,
    "gn:timezone":"Asia/Shanghai",
    "iso:country":"CN",
    "name:zho_x_preferred":[
        "\u516b\u5dde\u8425"
    ],
    "wof:name":"Bazhouying",
    "wof:placetype":"locality"
},
  "geometry": {"coordinates":[107.75588999999999,32.85049],"type":"Point"}
}