{
  "type": "Feature",
  "properties": {
    "gn:admin1_code":"14.0",
    "gn:asciiname":"Sabalongcun",
    "gn:country_code":"CN",
    "gn:dem":4439,
    "gn:feature_class":"P",
    "gn:feature_code":"PPL",
    "gn:name":"Sabalongcun",
    "gn:population":0,
    "gn:timezone":"Asia/Urumqi",
    "iso:country":"CN",
    "name:zho_x_preferred":[
        "\u8428\u5df4\u9686\u6751"
    ],
    "wof:name":"Sabalongcun",
    "wof:placetype":"locality"
},
  "geometry": {"coordinates":[92.88567999999999,31.6815],"type":"Point"}
}