{
  "type": "Feature",
  "properties": {
    "gn:admin1_code":"14.0",
    "gn:asciiname":"Puxar",
    "gn:country_code":"CN",
    "gn:dem":3896,
    "gn:feature_class":"P",
    "gn:feature_code":"PPLF",
    "gn:name":"Puxar",
    "gn:population":0,
    "gn:timezone":"Asia/Urumqi",
    "iso:country":"CN",
    "name:bod_x_preferred":[
        "Puxar"
    ],
    "name:zho_x_preferred":[
        "Puxia"
    ],
    "name:zho_x_variant":[
        "\u666e\u4e0b"
    ],
    "wof:name":"Puxar",
    "wof:placetype":"locality"
},
  "geometry": {"coordinates":[91.10599999999999,29.106],"type":"Point"}
}