{
  "type": "Feature",
  "properties": {
    "gn:admin1_code":"19.0",
    "gn:asciiname":"Yanghu Nangou",
    "gn:country_code":"CN",
    "gn:dem":213,
    "gn:feature_class":"P",
    "gn:feature_code":"PPL",
    "gn:name":"Yanghu Nangou",
    "gn:population":0,
    "gn:timezone":"Asia/Shanghai",
    "iso:country":"CN",
    "name:und_x_variant":[
        "\u6d0b\u6e56\u5357\u6c9f"
    ],
    "wof:name":"Yanghu Nangou",
    "wof:placetype":"locality"
},
  "geometry": {"coordinates":[124.11308,41.70228],"type":"Point"}
}