{
  "type": "Feature",
  "properties": {
    "gn:admin1_code":"30",
    "gn:asciiname":"Yinzhan",
    "gn:country_code":"CN",
    "gn:dem":49,
    "gn:feature_class":"P",
    "gn:feature_code":"PPL",
    "gn:name":"Yinzhan",
    "gn:population":0,
    "gn:timezone":"Asia/Shanghai",
    "iso:country":"CN",
    "name:und_x_variant":[
        "\u94f6\u76cf"
    ],
    "name:zho_x_preferred":[
        "\u94f6\u76cf"
    ],
    "wof:name":"Yinzhan",
    "wof:placetype":"locality"
},
  "geometry": {"coordinates":[113.14278,23.55667],"type":"Point"}
}