{
  "type": "Feature",
  "properties": {
    "gn:admin1_code":"10",
    "gn:asciiname":"Ximiaogong",
    "gn:country_code":"CN",
    "gn:dem":947,
    "gn:feature_class":"P",
    "gn:feature_code":"PPL",
    "gn:name":"Ximiaogong",
    "gn:population":0,
    "gn:timezone":"Asia/Shanghai",
    "iso:country":"CN",
    "name:zho_x_preferred":[
        "\u897f\u5e99\u5bab"
    ],
    "wof:name":"Ximiaogong",
    "wof:placetype":"locality"
},
  "geometry": {"coordinates":[117.31923,41.70431],"type":"Point"}
}