{
  "type": "Feature",
  "properties": {
    "gn:admin1_code":"01",
    "gn:asciiname":"Guantang",
    "gn:cc2":"CN",
    "gn:country_code":"CN",
    "gn:dem":40,
    "gn:feature_class":"P",
    "gn:feature_code":"PPL",
    "gn:name":"Guantang",
    "gn:population":0,
    "gn:timezone":"Asia/Shanghai",
    "iso:country":"CN",
    "name:und_x_variant":[
        "Kuan-t\u2019ang",
        "Guantangji",
        "Kuan-t\u2019ang-chi",
        "Kuan-yin-t\u2019ang",
        "Guantang"
    ],
    "wof:name":"Guantang",
    "wof:placetype":"locality"
},
  "geometry": {"coordinates":[116.00943999999998,33.80083],"type":"Point"}
}