{
  "type": "Feature",
  "properties": {
    "gn:admin1_code":"9.0",
    "gn:asciiname":"Dongliuyuan",
    "gn:country_code":"CN",
    "gn:dem":70,
    "gn:feature_class":"P",
    "gn:feature_code":"PPL",
    "gn:name":"Dongliuyuan",
    "gn:population":0,
    "gn:timezone":"Asia/Shanghai",
    "iso:country":"CN",
    "name:zho_x_preferred":[
        "\u4e1c\u67f3\u56ed"
    ],
    "wof:name":"Dongliuyuan",
    "wof:placetype":"locality"
},
  "geometry": {"coordinates":[114.55148,35.16457],"type":"Point"}
}