{
  "type": "Feature",
  "properties": {
    "gn:admin1_code":"26.0",
    "gn:asciiname":"Xuezhuang",
    "gn:country_code":"CN",
    "gn:dem":1110,
    "gn:feature_class":"P",
    "gn:feature_code":"PPL",
    "gn:name":"Xuezhuang",
    "gn:population":0,
    "gn:timezone":"Asia/Shanghai",
    "iso:country":"CN",
    "name:zho_x_preferred":[
        "\u859b\u5e84"
    ],
    "wof:name":"Xuezhuang",
    "wof:placetype":"locality"
},
  "geometry": {"coordinates":[108.80752,36.08307],"type":"Point"}
}