{
  "type": "Feature",
  "properties": {
    "gn:admin1_code":"29.0",
    "gn:asciiname":"Yumaideng",
    "gn:country_code":"CN",
    "gn:dem":1888,
    "gn:feature_class":"P",
    "gn:feature_code":"PPL",
    "gn:name":"Yumaideng",
    "gn:population":0,
    "gn:timezone":"Asia/Shanghai",
    "iso:country":"CN",
    "name:zho_x_preferred":[
        "\u7389\u9ea6\u767b"
    ],
    "wof:name":"Yumaideng",
    "wof:placetype":"locality"
},
  "geometry": {"coordinates":[104.48699999999999,25.3509],"type":"Point"}
}