{
  "type": "Feature",
  "properties": {
    "gn:admin1_code":"24",
    "gn:asciiname":"Niucun",
    "gn:cc2":"CN",
    "gn:country_code":"CN",
    "gn:dem":974,
    "gn:feature_class":"P",
    "gn:feature_code":"PPL",
    "gn:name":"Niucun",
    "gn:population":0,
    "gn:timezone":"Asia/Shanghai",
    "iso:country":"CN",
    "name:und_x_variant":[
        "Niu-ts\u2019un-chen",
        "Niu-ts\u2019un",
        "Niucun"
    ],
    "wof:name":"Niucun",
    "wof:placetype":"locality"
},
  "geometry": {"coordinates":[113.50888999999999,38.09417],"type":"Point"}
}