{
  "type": "Feature",
  "properties": {
    "gn:admin1_code":"6.0",
    "gn:asciiname":"Niangzhuang",
    "gn:country_code":"CN",
    "gn:dem":2951,
    "gn:feature_class":"P",
    "gn:feature_code":"PPL",
    "gn:name":"Niangzhuang",
    "gn:population":0,
    "gn:timezone":"Asia/Shanghai",
    "iso:country":"CN",
    "name:und_x_variant":[
        "\u5a18\u5e84"
    ],
    "wof:name":"Niangzhuang",
    "wof:placetype":"locality"
},
  "geometry": {"coordinates":[102.14336,35.56345],"type":"Point"}
}