{
  "type": "Feature",
  "properties": {
    "gn:admin1_code":"29.0",
    "gn:asciiname":"Dahuofang",
    "gn:country_code":"CN",
    "gn:dem":2182,
    "gn:feature_class":"P",
    "gn:feature_code":"PPL",
    "gn:name":"Dahuofang",
    "gn:population":0,
    "gn:timezone":"Asia/Shanghai",
    "iso:country":"CN",
    "name:zho_x_preferred":[
        "\u5927\u706b\u623f"
    ],
    "wof:name":"Dahuofang",
    "wof:placetype":"locality"
},
  "geometry": {"coordinates":[99.172,23.7842],"type":"Point"}
}