{
  "type": "Feature",
  "properties": {
    "gn:admin1_code":"24.0",
    "gn:asciiname":"Zhuwei",
    "gn:country_code":"CN",
    "gn:dem":1238,
    "gn:feature_class":"P",
    "gn:feature_code":"PPL",
    "gn:name":"Zhuwei",
    "gn:population":0,
    "gn:timezone":"Asia/Shanghai",
    "iso:country":"CN",
    "name:zho_x_preferred":[
        "\u732a\u5c3e"
    ],
    "wof:name":"Zhuwei",
    "wof:placetype":"locality"
},
  "geometry": {"coordinates":[113.27593,35.65441],"type":"Point"}
}