{
  "type": "Feature",
  "properties": {
    "gn:admin1_code":"32.0",
    "gn:asciiname":"Menggeluo",
    "gn:country_code":"CN",
    "gn:dem":3246,
    "gn:feature_class":"P",
    "gn:feature_code":"PPL",
    "gn:name":"Menggeluo",
    "gn:population":0,
    "gn:timezone":"Asia/Shanghai",
    "iso:country":"CN",
    "name:zho_x_preferred":[
        "\u8499\u683c\u6d1b"
    ],
    "wof:name":"Menggeluo",
    "wof:placetype":"locality"
},
  "geometry": {"coordinates":[102.18899999999999,32.1773],"type":"Point"}
}