{
  "type": "Feature",
  "properties": {
    "gn:admin1_code":"20",
    "gn:asciiname":"Hatan Tohoi",
    "gn:country_code":"CN",
    "gn:dem":1039,
    "gn:feature_class":"P",
    "gn:feature_code":"PPL",
    "gn:name":"Hatan Tohoi",
    "gn:population":0,
    "gn:timezone":"Asia/Shanghai",
    "iso:country":"CN",
    "wof:name":"Hatan Tohoi",
    "wof:placetype":"locality"
},
  "geometry": {"coordinates":[106.58333,40.56667],"type":"Point"}
}