{
  "type": "Feature",
  "properties": {
    "gn:admin1_code":"32.0",
    "gn:asciiname":"Baozuozui",
    "gn:country_code":"CN",
    "gn:dem":383,
    "gn:feature_class":"P",
    "gn:feature_code":"PPL",
    "gn:name":"Baozuozui",
    "gn:population":0,
    "gn:timezone":"Asia/Shanghai",
    "iso:country":"CN",
    "name:zho_x_preferred":[
        "\u5b9d\u5ea7\u5634"
    ],
    "wof:name":"Baozuozui",
    "wof:placetype":"locality"
},
  "geometry": {"coordinates":[105.02800000000001,29.7973],"type":"Point"}
}