{
  "type": "Feature",
  "properties": {
    "gn:admin1_code":"32.0",
    "gn:asciiname":"Jiucun",
    "gn:country_code":"CN",
    "gn:dem":2065,
    "gn:feature_class":"P",
    "gn:feature_code":"PPL",
    "gn:name":"Jiucun",
    "gn:population":0,
    "gn:timezone":"Asia/Shanghai",
    "iso:country":"CN",
    "name:zho_x_preferred":[
        "\u65e7\u6751"
    ],
    "wof:name":"Jiucun",
    "wof:placetype":"locality"
},
  "geometry": {"coordinates":[102.283,26.2682],"type":"Point"}
}