{
  "type": "Feature",
  "properties": {
    "gn:admin1_code":"4.0",
    "gn:asciiname":"Yuduo",
    "gn:country_code":"CN",
    "gn:dem":6,
    "gn:feature_class":"P",
    "gn:feature_code":"PPLA4",
    "gn:name":"Yuduo",
    "gn:population":0,
    "gn:timezone":"Asia/Shanghai",
    "iso:country":"CN",
    "name:und_x_variant":[
        "Yujiaduo",
        "\u4fde\u5bb6\u579b",
        "Yuduo",
        "Yuduo Zhen",
        "\u4fde\u579b",
        "\u4fde\u579b\u9547"
    ],
    "wof:name":"Yuduo",
    "wof:placetype":"locality"
},
  "geometry": {"coordinates":[120.01282999999999,32.64077],"type":"Point"}
}