{
  "type": "Feature",
  "properties": {
    "gn:admin1_code":"14.0",
    "gn:asciiname":"Baiduicun",
    "gn:country_code":"CN",
    "gn:dem":3613,
    "gn:feature_class":"P",
    "gn:feature_code":"PPL",
    "gn:name":"Baiduicun",
    "gn:population":0,
    "gn:timezone":"Asia/Urumqi",
    "iso:country":"CN",
    "name:zho_x_preferred":[
        "\u767e\u5806\u6751"
    ],
    "wof:name":"Baiduicun",
    "wof:placetype":"locality"
},
  "geometry": {"coordinates":[90.95755,29.49043],"type":"Point"}
}