{
  "type": "Feature",
  "properties": {
    "gn:admin1_code":"16",
    "gn:asciiname":"Shinan",
    "gn:country_code":"CN",
    "gn:dem":123,
    "gn:feature_class":"P",
    "gn:feature_code":"PPLA3",
    "gn:name":"Shinan",
    "gn:population":0,
    "gn:timezone":"Asia/Shanghai",
    "iso:country":"CN",
    "name:und_x_variant":[
        "Shih-nan",
        "Shinan",
        "Shinan Zhen"
    ],
    "name:zho_x_preferred":[
        "\u77f3\u5357"
    ],
    "name:zho_x_variant":[
        "\u77f3\u5357\u9547"
    ],
    "wof:name":"Shinan",
    "wof:placetype":"locality"
},
  "geometry": {"coordinates":[109.87428,22.7439],"type":"Point"}
}