{
  "type": "Feature",
  "properties": {
    "gn:admin1_code":"29.0",
    "gn:asciiname":"Jinshan Maidi",
    "gn:country_code":"CN",
    "gn:dem":2148,
    "gn:feature_class":"P",
    "gn:feature_code":"PPL",
    "gn:name":"Jinshan Maidi",
    "gn:population":0,
    "gn:timezone":"Asia/Shanghai",
    "iso:country":"CN",
    "name:zho_x_preferred":[
        "\u91d1\u5c71\u9ea6\u5730"
    ],
    "wof:name":"Jinshan Maidi",
    "wof:placetype":"locality"
},
  "geometry": {"coordinates":[101.78400000000001,25.2419],"type":"Point"}
}