{
  "type": "Feature",
  "properties": {
    "gn:admin1_code":"1.0",
    "gn:asciiname":"Chaigangcun",
    "gn:country_code":"CN",
    "gn:dem":25,
    "gn:feature_class":"P",
    "gn:feature_code":"PPL",
    "gn:name":"Chaigangcun",
    "gn:population":0,
    "gn:timezone":"Asia/Shanghai",
    "iso:country":"CN",
    "name:zho_x_preferred":[
        "\u67f4\u5c97\u6751"
    ],
    "wof:name":"Chaigangcun",
    "wof:placetype":"locality"
},
  "geometry": {"coordinates":[116.58262999999999,32.51781],"type":"Point"}
}