{
  "type": "Feature",
  "properties": {
    "gn:admin1_code":"18",
    "gn:asciiname":"Nama",
    "gn:country_code":"CN",
    "gn:dem":1255,
    "gn:feature_class":"P",
    "gn:feature_code":"PPL",
    "gn:name":"Nama",
    "gn:population":0,
    "gn:timezone":"Asia/Shanghai",
    "iso:country":"CN",
    "name:ceb_x_preferred":[
        "Nama"
    ],
    "name:deu_x_preferred":[
        "Nama"
    ],
    "name:ell_x_preferred":[
        "\u039d\u03ac\u03bc\u03b1"
    ],
    "name:fin_x_preferred":[
        "Nama"
    ],
    "name:fra_x_preferred":[
        "Nama"
    ],
    "name:nld_x_preferred":[
        "Nama"
    ],
    "name:pol_x_preferred":[
        "Nama"
    ],
    "name:por_x_preferred":[
        "Nama"
    ],
    "name:swe_x_preferred":[
        "Nama"
    ],
    "name:zho_x_preferred":[
        "\u7eb3\u9a82"
    ],
    "wof:name":"Nama",
    "wof:placetype":"locality"
},
  "geometry": {"coordinates":[105.51600000000001,26.1207],"type":"Point"}
}