{
  "type": "Feature",
  "properties": {
    "gn:admin1_code":"9",
    "gn:asciiname":"Gaocaiyuan",
    "gn:country_code":"CN",
    "gn:dem":48,
    "gn:feature_class":"P",
    "gn:feature_code":"PPL",
    "gn:name":"Gaocaiyuan",
    "gn:population":0,
    "gn:timezone":"Asia/Shanghai",
    "iso:country":"CN",
    "name:zho_x_preferred":[
        "\u9ad8\u83dc\u56ed"
    ],
    "wof:name":"Gaocaiyuan",
    "wof:placetype":"locality"
},
  "geometry": {"coordinates":[115.56346000000001,35.855],"type":"Point"}
}