{
  "type": "Feature",
  "properties": {
    "gn:admin1_code":"11.0",
    "gn:asciiname":"Laixi",
    "gn:country_code":"CN",
    "gn:dem":604,
    "gn:feature_class":"P",
    "gn:feature_code":"PPL",
    "gn:name":"Laixi",
    "gn:population":0,
    "gn:timezone":"Asia/Shanghai",
    "iso:country":"CN",
    "name:ceb_x_preferred":[
        "Laixi"
    ],
    "name:deu_x_preferred":[
        "Laixi"
    ],
    "name:fra_x_preferred":[
        "Laixi"
    ],
    "name:ita_x_preferred":[
        "Laixi"
    ],
    "name:jpn_x_preferred":[
        "\u83b1\u897f\u5e02"
    ],
    "name:kik_x_preferred":[
        "Laixi"
    ],
    "name:kor_x_preferred":[
        "\ub77c\uc774\uc2dc\uc2dc"
    ],
    "name:mlg_x_preferred":[
        "Laixi"
    ],
    "name:nor_x_preferred":[
        "Laixi"
    ],
    "name:rus_x_preferred":[
        "\u041b\u0430\u0439\u0441\u0438"
    ],
    "name:swe_x_preferred":[
        "Laixi"
    ],
    "name:urd_x_preferred":[
        "\u0644\u0627\u0626\u0634\u06cc"
    ],
    "name:vie_x_preferred":[
        "Lai T\u00e2y"
    ],
    "name:zho_x_preferred":[
        "\u6d9e\u6eaa"
    ],
    "name:zho_x_variant":[
        "\u83b1\u897f\u5e02"
    ],
    "wof:name":"Laixi",
    "wof:placetype":"locality"
},
  "geometry": {"coordinates":[109.39122999999999,27.30942000000001],"type":"Point"}
}