{
  "type": "Feature",
  "properties": {
    "gn:admin1_code":"11.0",
    "gn:asciiname":"Laixi",
    "gn:country_code":"CN",
    "gn:dem":604,
    "gn:feature_class":"P",
    "gn:feature_code":"PPL",
    "gn:name":"Laixi",
    "gn:population":0,
    "gn:timezone":"Asia/Shanghai",
    "iso:country":"CN",
    "name:zho_x_preferred":[
        "\u6d9e\u6eaa"
    ],
    "wof:name":"Laixi",
    "wof:placetype":"locality"
},
  "geometry": {"coordinates":[109.39122999999999,27.30942000000001],"type":"Point"}
}