{
  "type": "Feature",
  "properties": {
    "gn:admin1_code":"29.0",
    "gn:asciiname":"Michu",
    "gn:country_code":"CN",
    "gn:dem":1333,
    "gn:feature_class":"P",
    "gn:feature_code":"PPL",
    "gn:name":"Michu",
    "gn:population":0,
    "gn:timezone":"Asia/Shanghai",
    "iso:country":"CN",
    "name:ara_x_preferred":[
        "\u0645\u064a\u062a\u0634\u0648"
    ],
    "name:ast_x_preferred":[
        "Michu"
    ],
    "name:azb_x_preferred":[
        "\u0645\u06cc\u0686\u0648"
    ],
    "name:bul_x_preferred":[
        "\u041c\u0438\u0447\u0443"
    ],
    "name:cat_x_preferred":[
        "Michu"
    ],
    "name:ces_x_preferred":[
        "Michu"
    ],
    "name:dan_x_preferred":[
        "Michu"
    ],
    "name:deu_x_preferred":[
        "Michu"
    ],
    "name:fas_x_preferred":[
        "\u0645\u06cc\u0686\u0648"
    ],
    "name:fin_x_preferred":[
        "Michu"
    ],
    "name:fra_x_preferred":[
        "Michu"
    ],
    "name:hun_x_preferred":[
        "Michu"
    ],
    "name:hye_x_preferred":[
        "\u0544\u056b\u0579\u0578\u0582"
    ],
    "name:ita_x_preferred":[
        "Michu"
    ],
    "name:jpn_x_preferred":[
        "\u30df\u30b2\u30eb\u30fb\u30da\u30ec\u30b9\u30fb\u30af\u30a8\u30b9\u30bf"
    ],
    "name:mkd_x_preferred":[
        "\u041c\u0438\u0447\u0443"
    ],
    "name:msa_x_preferred":[
        "Michu"
    ],
    "name:nld_x_preferred":[
        "Michu"
    ],
    "name:pol_x_preferred":[
        "Michu"
    ],
    "name:por_x_preferred":[
        "Michu"
    ],
    "name:rus_x_preferred":[
        "\u041c\u0438\u0447\u0443"
    ],
    "name:spa_x_preferred":[
        "Michu"
    ],
    "name:swe_x_preferred":[
        "Michu"
    ],
    "name:tgk_x_preferred":[
        "\u041c\u0438\u043a\u0443"
    ],
    "name:tha_x_preferred":[
        "\u0e21\u0e34\u0e0a\u0e39"
    ],
    "name:tur_x_preferred":[
        "Michu"
    ],
    "name:vie_x_preferred":[
        "Michu"
    ],
    "name:zho_x_preferred":[
        "\u54aa\u521d"
    ],
    "wof:name":"Michu",
    "wof:placetype":"locality"
},
  "geometry": {"coordinates":[102.124,23.1517],"type":"Point"}
}