{
  "type": "Feature",
  "properties": {
    "gn:admin1_code":"30.0",
    "gn:asciiname":"Butouwei",
    "gn:country_code":"CN",
    "gn:dem":19,
    "gn:feature_class":"P",
    "gn:feature_code":"PPL",
    "gn:name":"Butouwei",
    "gn:population":0,
    "gn:timezone":"Asia/Shanghai",
    "iso:country":"CN",
    "name:zho_x_preferred":[
        "\u6b65\u5934\u5c3e"
    ],
    "wof:name":"Butouwei",
    "wof:placetype":"locality"
},
  "geometry": {"coordinates":[113.34314999999999,22.31748],"type":"Point"}
}