{
  "type": "Feature",
  "properties": {
    "gn:admin1_code":"8.0",
    "gn:asciiname":"Zilicun",
    "gn:country_code":"CN",
    "gn:dem":269,
    "gn:feature_class":"P",
    "gn:feature_code":"PPL",
    "gn:name":"Zilicun",
    "gn:population":0,
    "gn:timezone":"Asia/Shanghai",
    "iso:country":"CN",
    "name:zho_x_preferred":[
        "\u81ea\u7acb\u6751"
    ],
    "wof:name":"Zilicun",
    "wof:placetype":"locality"
},
  "geometry": {"coordinates":[126.41186,48.27096],"type":"Point"}
}