{
  "type": "Feature",
  "properties": {
    "gn:admin1_code":"5.0",
    "gn:asciiname":"Bijiadiancun",
    "gn:country_code":"CN",
    "gn:dem":179,
    "gn:feature_class":"P",
    "gn:feature_code":"PPL",
    "gn:name":"Bijiadiancun",
    "gn:population":0,
    "gn:timezone":"Asia/Shanghai",
    "iso:country":"CN",
    "name:zho_x_preferred":[
        "\u6bd5\u5bb6\u5e97\u6751"
    ],
    "wof:name":"Bijiadiancun",
    "wof:placetype":"locality"
},
  "geometry": {"coordinates":[125.07787999999999,44.34969],"type":"Point"}
}