{
  "type": "Feature",
  "properties": {
    "gn:admin1_code":"16.0",
    "gn:asciiname":"Lile",
    "gn:country_code":"CN",
    "gn:dem":907,
    "gn:feature_class":"P",
    "gn:feature_code":"PPL",
    "gn:name":"Lile",
    "gn:population":0,
    "gn:timezone":"Asia/Shanghai",
    "iso:country":"CN",
    "name:zho_x_preferred":[
        "\u5229\u4e50"
    ],
    "wof:name":"Lile",
    "wof:placetype":"locality"
},
  "geometry": {"coordinates":[107.72499999999999,25.0462],"type":"Point"}
}