{
  "type": "Feature",
  "properties": {
    "gn:admin1_code":"4.0",
    "gn:asciiname":"Zhouchencun",
    "gn:country_code":"CN",
    "gn:dem":7,
    "gn:feature_class":"P",
    "gn:feature_code":"PPL",
    "gn:name":"Zhouchencun",
    "gn:population":0,
    "gn:timezone":"Asia/Shanghai",
    "iso:country":"CN",
    "name:zho_x_preferred":[
        "\u5468\u9648\u6751"
    ],
    "wof:name":"Zhouchencun",
    "wof:placetype":"locality"
},
  "geometry": {"coordinates":[119.06207000000001,33.50232],"type":"Point"}
}