{
  "type": "Feature",
  "properties": {
    "gn:admin1_code":"16.0",
    "gn:asciiname":"Dushan",
    "gn:country_code":"CN",
    "gn:dem":181,
    "gn:feature_class":"P",
    "gn:feature_code":"PPL",
    "gn:name":"Dushan",
    "gn:population":0,
    "gn:timezone":"Asia/Shanghai",
    "iso:country":"CN",
    "name:ceb_x_preferred":[
        "Dushan"
    ],
    "name:deu_x_preferred":[
        "Dushan"
    ],
    "name:zho_x_preferred":[
        "\u72ec\u5c71"
    ],
    "wof:name":"Dushan",
    "wof:placetype":"locality"
},
  "geometry": {"coordinates":[107.669,22.2707],"type":"Point"}
}