{
  "type": "Feature",
  "properties": {
    "gn:admin1_code":"15.0",
    "gn:asciiname":"Shangtanzi",
    "gn:country_code":"CN",
    "gn:dem":1482,
    "gn:feature_class":"P",
    "gn:feature_code":"PPL",
    "gn:name":"Shangtanzi",
    "gn:population":0,
    "gn:timezone":"Asia/Shanghai",
    "iso:country":"CN",
    "name:zho_x_preferred":[
        "\u4e0a\u6ee9\u5b50"
    ],
    "wof:name":"Shangtanzi",
    "wof:placetype":"locality"
},
  "geometry": {"coordinates":[105.413,34.8035],"type":"Point"}
}