{
  "type": "Feature",
  "properties": {
    "gn:admin1_code":"4.0",
    "gn:asciiname":"Jiangliyuancun",
    "gn:country_code":"CN",
    "gn:dem":43,
    "gn:feature_class":"P",
    "gn:feature_code":"PPL",
    "gn:name":"Jiangliyuancun",
    "gn:population":0,
    "gn:timezone":"Asia/Shanghai",
    "iso:country":"CN",
    "name:und_x_variant":[
        "Jiangliyuan"
    ],
    "name:zho_x_preferred":[
        "\u59dc\u68a8\u56ed\u6751"
    ],
    "wof:name":"Jiangliyuancun",
    "wof:placetype":"locality"
},
  "geometry": {"coordinates":[116.78192,34.64911],"type":"Point"}
}