{
  "type": "Feature",
  "properties": {
    "gn:admin1_code":"32.0",
    "gn:asciiname":"Paotouwan",
    "gn:country_code":"CN",
    "gn:dem":317,
    "gn:feature_class":"P",
    "gn:feature_code":"PPL",
    "gn:name":"Paotouwan",
    "gn:population":0,
    "gn:timezone":"Asia/Shanghai",
    "iso:country":"CN",
    "name:zho_x_preferred":[
        "\u70ae\u5934\u6e7e"
    ],
    "wof:name":"Paotouwan",
    "wof:placetype":"locality"
},
  "geometry": {"coordinates":[104.955,28.9491],"type":"Point"}
}