{
  "type": "Feature",
  "properties": {
    "gn:admin1_code":"25.0",
    "gn:asciiname":"Lequancun",
    "gn:country_code":"CN",
    "gn:dem":126,
    "gn:feature_class":"P",
    "gn:feature_code":"PPL",
    "gn:name":"Lequancun",
    "gn:population":0,
    "gn:timezone":"Asia/Shanghai",
    "iso:country":"CN",
    "name:zho_x_preferred":[
        "\u4e50\u754e\u6751"
    ],
    "wof:name":"Lequancun",
    "wof:placetype":"locality"
},
  "geometry": {"coordinates":[121.12233999999999,36.87596],"type":"Point"}
}