{
  "type": "Feature",
  "properties": {
    "gn:admin1_code":"2",
    "gn:asciiname":"Xiashanwu",
    "gn:country_code":"CN",
    "gn:dem":122,
    "gn:feature_class":"P",
    "gn:feature_code":"PPL",
    "gn:name":"Xiashanwu",
    "gn:population":0,
    "gn:timezone":"Asia/Shanghai",
    "iso:country":"CN",
    "name:zho_x_preferred":[
        "\u4e0b\u5c71\u575e"
    ],
    "wof:name":"Xiashanwu",
    "wof:placetype":"locality"
},
  "geometry": {"coordinates":[120.30154,29.51567],"type":"Point"}
}