{
  "type": "Feature",
  "properties": {
    "gn:country":"CN",
    "gn:fcode":"PPL",
    "gn:pop":420,
    "iso:country":"CN",
    "name:zho_x_preferred":[
        "\u90ed\u516c\u576a"
    ],
    "qs:name":"Guogongping",
    "qs:photos_9r":0,
    "qs:photos_sr":0,
    "qs:pop_sr":"2",
    "wof:name":"Guogongping",
    "wof:placetype":"locality",
    "wof:population":420
},
  "geometry": {"coordinates":[109.46693999999999,27.72333],"type":"Point"}
}