{
  "type": "Feature",
  "properties": {
    "gn:admin1_code":"12.0",
    "gn:asciiname":"Daoshidian",
    "gn:country_code":"CN",
    "gn:dem":64,
    "gn:feature_class":"P",
    "gn:feature_code":"PPL",
    "gn:name":"Daoshidian",
    "gn:population":0,
    "gn:timezone":"Asia/Shanghai",
    "iso:country":"CN",
    "name:zho_x_preferred":[
        "\u9053\u58eb\u5e97"
    ],
    "wof:name":"Daoshidian",
    "wof:placetype":"locality"
},
  "geometry": {"coordinates":[114.02464000000001,31.01305],"type":"Point"}
}