{
  "type": "Feature",
  "properties": {
    "gn:admin1_code":"14.0",
    "gn:asciiname":"Jiangningcun",
    "gn:country_code":"CN",
    "gn:dem":4561,
    "gn:feature_class":"P",
    "gn:feature_code":"PPL",
    "gn:name":"Jiangningcun",
    "gn:population":0,
    "gn:timezone":"Asia/Urumqi",
    "iso:country":"CN",
    "name:zho_x_preferred":[
        "\u6c5f\u5b81\u6751"
    ],
    "wof:name":"Jiangningcun",
    "wof:placetype":"locality"
},
  "geometry": {"coordinates":[93.09560999999999,31.94804],"type":"Point"}
}