{
  "type": "Feature",
  "properties": {
    "gn:admin1_code":"19.0",
    "gn:asciiname":"Huitun",
    "gn:country_code":"CN",
    "gn:dem":22,
    "gn:feature_class":"P",
    "gn:feature_code":"PPL",
    "gn:name":"Huitun",
    "gn:population":0,
    "gn:timezone":"Asia/Shanghai",
    "iso:country":"CN",
    "name:und_x_variant":[
        "\u60e0\u5c6f"
    ],
    "wof:name":"Huitun",
    "wof:placetype":"locality"
},
  "geometry": {"coordinates":[122.23793000000001,40.37562],"type":"Point"}
}