{
  "type": "Feature",
  "properties": {
    "gn:admin1_code":"15.0",
    "gn:asciiname":"Yangjia Xianzi",
    "gn:country_code":"CN",
    "gn:dem":2062,
    "gn:feature_class":"P",
    "gn:feature_code":"PPL",
    "gn:name":"Yangjia Xianzi",
    "gn:population":0,
    "gn:timezone":"Asia/Shanghai",
    "iso:country":"CN",
    "name:zho_x_preferred":[
        "\u6768\u5bb6\u5c98\u5b50"
    ],
    "wof:name":"Yangjia Xianzi",
    "wof:placetype":"locality"
},
  "geometry": {"coordinates":[103.54600000000001,36.6097],"type":"Point"}
}