{
  "type": "Feature",
  "properties": {
    "gn:admin1_code":"24",
    "gn:asciiname":"Daxigouzhang",
    "gn:country_code":"CN",
    "gn:dem":2087,
    "gn:feature_class":"P",
    "gn:feature_code":"PPL",
    "gn:name":"Daxigouzhang",
    "gn:population":0,
    "gn:timezone":"Asia/Shanghai",
    "iso:country":"CN",
    "wof:name":"Daxigouzhang",
    "wof:placetype":"locality"
},
  "geometry": {"coordinates":[113.67083,39.56889],"type":"Point"}
}