{
  "type": "Feature",
  "properties": {
    "gn:admin1_code":"11",
    "gn:asciiname":"Yongxingnonglinkenzhichang",
    "gn:country_code":"CN",
    "gn:dem":249,
    "gn:feature_class":"P",
    "gn:feature_code":"PPL",
    "gn:name":"Yongxingnonglinkenzhichang",
    "gn:population":0,
    "gn:timezone":"Asia/Shanghai",
    "iso:country":"CN",
    "wof:name":"Yongxingnonglinkenzhichang",
    "wof:placetype":"locality"
},
  "geometry": {"coordinates":[113.3475,26.22917],"type":"Point"}
}