{
  "type": "Feature",
  "properties": {
    "gn:admin1_code":"25",
    "gn:asciiname":"Xiajiazhuang",
    "gn:country_code":"CN",
    "gn:dem":177,
    "gn:feature_class":"P",
    "gn:feature_code":"PPL",
    "gn:name":"Xiajiazhuang",
    "gn:population":0,
    "gn:timezone":"Asia/Shanghai",
    "iso:country":"CN",
    "name:zho_x_preferred":[
        "\u590f\u5bb6\u5e84"
    ],
    "wof:name":"Xiajiazhuang",
    "wof:placetype":"locality"
},
  "geometry": {"coordinates":[116.90900000000001,36.2214],"type":"Point"}
}