{
  "type": "Feature",
  "properties": {
    "gn:admin1_code":"4.0",
    "gn:asciiname":"Yantoukou",
    "gn:country_code":"CN",
    "gn:dem":3,
    "gn:feature_class":"P",
    "gn:feature_code":"PPL",
    "gn:name":"Yantoukou",
    "gn:population":0,
    "gn:timezone":"Asia/Shanghai",
    "iso:country":"CN",
    "name:und_x_variant":[
        "\u96c1\u5934\u53e3"
    ],
    "wof:name":"Yantoukou",
    "wof:placetype":"locality"
},
  "geometry": {"coordinates":[121.08707,32.22056],"type":"Point"}
}