{
  "type": "Feature",
  "properties": {
    "gn:admin1_code":"11",
    "gn:asciiname":"Tuoli",
    "gn:country_code":"CN",
    "gn:dem":282,
    "gn:feature_class":"P",
    "gn:feature_code":"PPL",
    "gn:name":"Tuoli",
    "gn:population":0,
    "gn:timezone":"Asia/Shanghai",
    "iso:country":"CN",
    "name:zho_x_preferred":[
        "\u5768\u91cc"
    ],
    "wof:name":"Tuoli",
    "wof:placetype":"locality"
},
  "geometry": {"coordinates":[110.42393,27.83573],"type":"Point"}
}