{
  "type": "Feature",
  "properties": {
    "gn:admin1_code":"32.0",
    "gn:asciiname":"Mushui",
    "gn:country_code":"CN",
    "gn:dem":919,
    "gn:feature_class":"P",
    "gn:feature_code":"PPL",
    "gn:name":"Mushui",
    "gn:population":0,
    "gn:timezone":"Asia/Shanghai",
    "iso:country":"CN",
    "name:zho_x_preferred":[
        "\u6c90\u6c34"
    ],
    "wof:name":"Mushui",
    "wof:placetype":"locality"
},
  "geometry": {"coordinates":[105.22199999999999,32.3089],"type":"Point"}
}