{
  "type": "Feature",
  "properties": {
    "gn:admin1_code":"29",
    "gn:asciiname":"Yaozhanjie",
    "gn:country_code":"CN",
    "gn:dem":1780,
    "gn:feature_class":"P",
    "gn:feature_code":"PPL",
    "gn:name":"Yaozhanjie",
    "gn:population":0,
    "gn:timezone":"Asia/Shanghai",
    "iso:country":"CN",
    "name:zho_x_preferred":[
        "\u8170\u7ad9\u8857"
    ],
    "wof:name":"Yaozhanjie",
    "wof:placetype":"locality"
},
  "geometry": {"coordinates":[101.642,25.0924],"type":"Point"}
}