{
  "type": "Feature",
  "properties": {
    "gn:admin1_code":"32.0",
    "gn:asciiname":"Shaijin",
    "gn:country_code":"CN",
    "gn:dem":320,
    "gn:feature_class":"P",
    "gn:feature_code":"PPL",
    "gn:name":"Shaijin",
    "gn:population":0,
    "gn:timezone":"Asia/Shanghai",
    "iso:country":"CN",
    "name:zho_x_preferred":[
        "\u6652\u91d1"
    ],
    "wof:name":"Shaijin",
    "wof:placetype":"locality"
},
  "geometry": {"coordinates":[107.17100000000001,30.2891],"type":"Point"}
}