{
  "type": "Feature",
  "properties": {
    "gn:admin1_code":"12.0",
    "gn:asciiname":"Yangjiaozhai",
    "gn:country_code":"CN",
    "gn:dem":1215,
    "gn:feature_class":"P",
    "gn:feature_code":"PPL",
    "gn:name":"Yangjiaozhai",
    "gn:population":0,
    "gn:timezone":"Asia/Shanghai",
    "iso:country":"CN",
    "name:zho_x_preferred":[
        "\u7f8a\u89d2\u5be8"
    ],
    "wof:name":"Yangjiaozhai",
    "wof:placetype":"locality"
},
  "geometry": {"coordinates":[110.91613,31.169],"type":"Point"}
}