{
  "type": "Feature",
  "properties": {
    "gn:admin1_code":"9",
    "gn:asciiname":"Huanglongtan",
    "gn:country_code":"CN",
    "gn:dem":360,
    "gn:feature_class":"P",
    "gn:feature_code":"PPL",
    "gn:name":"Huanglongtan",
    "gn:population":0,
    "gn:timezone":"Asia/Shanghai",
    "iso:country":"CN",
    "name:und_x_variant":[
        "\u9ec4\u9f99\u6f6d",
        "Huanglongtan"
    ],
    "wof:name":"Huanglongtan",
    "wof:placetype":"locality"
},
  "geometry": {"coordinates":[112.15170000000001,33.42321],"type":"Point"}
}