{
  "type": "Feature",
  "properties": {
    "gn:admin1_code":"29.0",
    "gn:asciiname":"Shangyakou",
    "gn:country_code":"CN",
    "gn:dem":2140,
    "gn:feature_class":"P",
    "gn:feature_code":"PPL",
    "gn:name":"Shangyakou",
    "gn:population":0,
    "gn:timezone":"Asia/Shanghai",
    "iso:country":"CN",
    "name:und_x_variant":[
        "\u4e0a\u57ad\u53e3"
    ],
    "wof:name":"Shangyakou",
    "wof:placetype":"locality"
},
  "geometry": {"coordinates":[102.4725,25.42945],"type":"Point"}
}