{
  "type": "Feature",
  "properties": {
    "gn:admin1_code":"19.0",
    "gn:asciiname":"Xinhuangdigou",
    "gn:country_code":"CN",
    "gn:dem":184,
    "gn:feature_class":"P",
    "gn:feature_code":"PPL",
    "gn:name":"Xinhuangdigou",
    "gn:population":0,
    "gn:timezone":"Asia/Shanghai",
    "iso:country":"CN",
    "name:zho_x_preferred":[
        "\u65b0\u8352\u5730\u6c9f"
    ],
    "wof:name":"Xinhuangdigou",
    "wof:placetype":"locality"
},
  "geometry": {"coordinates":[121.00761,41.62339],"type":"Point"}
}