{
  "type": "Feature",
  "properties": {
    "gn:admin1_code":"24.0",
    "gn:asciiname":"Xijiazhai",
    "gn:country_code":"CN",
    "gn:dem":1201,
    "gn:feature_class":"P",
    "gn:feature_code":"PPL",
    "gn:name":"Xijiazhai",
    "gn:population":0,
    "gn:timezone":"Asia/Shanghai",
    "iso:country":"CN",
    "name:und_x_variant":[
        "\u897f\u5bb6\u5be8"
    ],
    "wof:name":"Xijiazhai",
    "wof:placetype":"locality"
},
  "geometry": {"coordinates":[112.44767,39.46295],"type":"Point"}
}