{
  "type": "Feature",
  "properties": {
    "gn:admin1_code":"32.0",
    "gn:asciiname":"Xingzigou",
    "gn:country_code":"CN",
    "gn:dem":329,
    "gn:feature_class":"P",
    "gn:feature_code":"PPL",
    "gn:name":"Xingzigou",
    "gn:population":0,
    "gn:timezone":"Asia/Shanghai",
    "iso:country":"CN",
    "name:zho_x_preferred":[
        "\u661f\u5b50\u6c9f"
    ],
    "wof:name":"Xingzigou",
    "wof:placetype":"locality"
},
  "geometry": {"coordinates":[105.223,30.2693],"type":"Point"}
}