{
  "type": "Feature",
  "properties": {
    "gn:admin1_code":"3.0",
    "gn:asciiname":"Saozhougang Liujia",
    "gn:country_code":"CN",
    "gn:dem":22,
    "gn:feature_class":"P",
    "gn:feature_code":"PPL",
    "gn:name":"Saozhougang Liujia",
    "gn:population":0,
    "gn:timezone":"Asia/Shanghai",
    "iso:country":"CN",
    "name:und_x_variant":[
        "\u626b\u5e1a\u5c97\u5218\u5bb6"
    ],
    "wof:name":"Saozhougang Liujia",
    "wof:placetype":"locality"
},
  "geometry": {"coordinates":[116.16743999999998,28.40059],"type":"Point"}
}