{
  "type": "Feature",
  "properties": {
    "gn:admin1_code":"1.0",
    "gn:asciiname":"Chenliucun",
    "gn:country_code":"CN",
    "gn:dem":34,
    "gn:feature_class":"P",
    "gn:feature_code":"PPL",
    "gn:name":"Chenliucun",
    "gn:population":0,
    "gn:timezone":"Asia/Shanghai",
    "iso:country":"CN",
    "name:zho_x_preferred":[
        "\u9648\u5218\u6751"
    ],
    "wof:name":"Chenliucun",
    "wof:placetype":"locality"
},
  "geometry": {"coordinates":[115.73932000000001,33.4811],"type":"Point"}
}