{
  "type": "Feature",
  "properties": {
    "gn:admin1_code":"14.0",
    "gn:asciiname":"Longrelong",
    "gn:country_code":"CN",
    "gn:dem":4188,
    "gn:feature_class":"P",
    "gn:feature_code":"PPL",
    "gn:name":"Longrelong",
    "gn:population":0,
    "gn:timezone":"Asia/Urumqi",
    "iso:country":"CN",
    "name:zho_x_preferred":[
        "\u62e2\u70ed\u62e2"
    ],
    "wof:name":"Longrelong",
    "wof:placetype":"locality"
},
  "geometry": {"coordinates":[95.41593,30.83431],"type":"Point"}
}