{
  "type": "Feature",
  "properties": {
    "gn:admin1_code":"11",
    "gn:asciiname":"Zhouping",
    "gn:country_code":"CN",
    "gn:dem":316,
    "gn:feature_class":"P",
    "gn:feature_code":"PPL",
    "gn:name":"Zhouping",
    "gn:population":0,
    "gn:timezone":"Asia/Shanghai",
    "iso:country":"CN",
    "wof:name":"Zhouping",
    "wof:placetype":"locality"
},
  "geometry": {"coordinates":[109.62472,27.37389000000001],"type":"Point"}
}