{
  "type": "Feature",
  "properties": {
    "gn:admin1_code":"19.0",
    "gn:asciiname":"Menlou",
    "gn:country_code":"CN",
    "gn:dem":132,
    "gn:feature_class":"P",
    "gn:feature_code":"PPL",
    "gn:name":"Menlou",
    "gn:population":0,
    "gn:timezone":"Asia/Shanghai",
    "iso:country":"CN",
    "name:zho_x_preferred":[
        "\u95e8\u697c"
    ],
    "wof:name":"Menlou",
    "wof:placetype":"locality"
},
  "geometry": {"coordinates":[124.08087999999999,42.39671],"type":"Point"}
}