{
  "type": "Feature",
  "properties": {
    "gn:admin1_code":"18.0",
    "gn:asciiname":"Layan",
    "gn:country_code":"CN",
    "gn:dem":587,
    "gn:feature_class":"P",
    "gn:feature_code":"PPL",
    "gn:name":"Layan",
    "gn:population":0,
    "gn:timezone":"Asia/Shanghai",
    "iso:country":"CN",
    "name:zho_x_preferred":[
        "\u814a\u5ca9"
    ],
    "wof:name":"Layan",
    "wof:placetype":"locality"
},
  "geometry": {"coordinates":[108.745,27.4847],"type":"Point"}
}