{
  "type": "Feature",
  "properties": {
    "gn:admin1_code":"30",
    "gn:asciiname":"Wankeng",
    "gn:country_code":"CN",
    "gn:dem":125,
    "gn:feature_class":"P",
    "gn:feature_code":"PPL",
    "gn:name":"Wankeng",
    "gn:population":0,
    "gn:timezone":"Asia/Shanghai",
    "iso:country":"CN",
    "name:zho_x_preferred":[
        "\u7897\u5751"
    ],
    "wof:name":"Wankeng",
    "wof:placetype":"locality"
},
  "geometry": {"coordinates":[111.51848,22.12098],"type":"Point"}
}