{
  "type": "Feature",
  "properties": {
    "gn:admin1_code":"18.0",
    "gn:asciiname":"Geyi Shangzhai",
    "gn:country_code":"CN",
    "gn:dem":832,
    "gn:feature_class":"P",
    "gn:feature_code":"PPL",
    "gn:name":"Geyi Shangzhai",
    "gn:population":0,
    "gn:timezone":"Asia/Shanghai",
    "iso:country":"CN",
    "name:zho_x_preferred":[
        "\u683c\u76ca\u4e0a\u5be8"
    ],
    "wof:name":"Geyi Shangzhai",
    "wof:placetype":"locality"
},
  "geometry": {"coordinates":[108.23099999999999,26.2453],"type":"Point"}
}