{
  "type": "Feature",
  "properties": {
    "gn:admin1_code":"04",
    "gn:asciiname":"Touxing",
    "gn:country_code":"CN",
    "gn:dem":2,
    "gn:feature_class":"P",
    "gn:feature_code":"PPL",
    "gn:name":"Touxing",
    "gn:population":0,
    "gn:timezone":"Asia/Shanghai",
    "iso:country":"CN",
    "name:und_x_variant":[
        "T\u2019ou-hsing-chen",
        "Touxingzhen",
        "Touxing",
        "\u5934\u5174",
        "\u5934\u5174\u9547"
    ],
    "wof:name":"Touxing",
    "wof:placetype":"locality"
},
  "geometry": {"coordinates":[121.63402000000001,31.79941],"type":"Point"}
}