{
  "type": "Feature",
  "properties": {
    "gn:admin1_code":"12",
    "gn:asciiname":"Xuejialiang",
    "gn:country_code":"CN",
    "gn:dem":883,
    "gn:feature_class":"P",
    "gn:feature_code":"PPL",
    "gn:name":"Xuejialiang",
    "gn:population":0,
    "gn:timezone":"Asia/Shanghai",
    "iso:country":"CN",
    "wof:name":"Xuejialiang",
    "wof:placetype":"locality"
},
  "geometry": {"coordinates":[110.28222,32.1925],"type":"Point"}
}