{
  "type": "Feature",
  "properties": {
    "gn:admin1_code":"3.0",
    "gn:asciiname":"Niukengshan",
    "gn:country_code":"CN",
    "gn:dem":267,
    "gn:feature_class":"P",
    "gn:feature_code":"PPL",
    "gn:name":"Niukengshan",
    "gn:population":0,
    "gn:timezone":"Asia/Shanghai",
    "iso:country":"CN",
    "name:und_x_variant":[
        "\u725b\u5751\u5c71"
    ],
    "wof:name":"Niukengshan",
    "wof:placetype":"locality"
},
  "geometry": {"coordinates":[117.9577,29.4499],"type":"Point"}
}