{
  "type": "Feature",
  "properties": {
    "gn:admin1_code":"01",
    "gn:asciiname":"Modian",
    "gn:cc2":"CN",
    "gn:country_code":"CN",
    "gn:dem":45,
    "gn:feature_class":"P",
    "gn:feature_code":"PPL",
    "gn:name":"Modian",
    "gn:population":0,
    "gn:timezone":"Asia/Shanghai",
    "iso:country":"CN",
    "name:und_x_variant":[
        "Mo-tien-tzu",
        "Modianzi",
        "Modian"
    ],
    "wof:name":"Modian",
    "wof:placetype":"locality"
},
  "geometry": {"coordinates":[117.37333,31.94333],"type":"Point"}
}