{
  "type": "Feature",
  "properties": {
    "gn:admin1_code":"18",
    "gn:asciiname":"Dibang",
    "gn:country_code":"CN",
    "gn:dem":1109,
    "gn:feature_class":"P",
    "gn:feature_code":"PPL",
    "gn:name":"Dibang",
    "gn:population":0,
    "gn:timezone":"Asia/Shanghai",
    "iso:country":"CN",
    "name:zho_x_preferred":[
        "\u62b5\u699c"
    ],
    "wof:name":"Dibang",
    "wof:placetype":"locality"
},
  "geometry": {"coordinates":[106.66200000000001,25.54300000000001],"type":"Point"}
}