{
  "type": "Feature",
  "properties": {
    "gn:admin1_code":"25",
    "gn:asciiname":"Kangzhai",
    "gn:country_code":"CN",
    "gn:dem":208,
    "gn:feature_class":"P",
    "gn:feature_code":"PPL",
    "gn:name":"Kangzhai",
    "gn:population":0,
    "gn:timezone":"Asia/Shanghai",
    "iso:country":"CN",
    "name:zho_x_preferred":[
        "\u5eb7\u5b85"
    ],
    "wof:name":"Kangzhai",
    "wof:placetype":"locality"
},
  "geometry": {"coordinates":[117.53700000000001,34.9933],"type":"Point"}
}