{
  "type": "Feature",
  "properties": {
    "gn:admin1_code":"15.0",
    "gn:asciiname":"Gongji",
    "gn:country_code":"CN",
    "gn:dem":1132,
    "gn:feature_class":"P",
    "gn:feature_code":"PPLA4",
    "gn:name":"Gongji",
    "gn:population":0,
    "gn:timezone":"Asia/Shanghai",
    "iso:country":"CN",
    "name:und_x_variant":[
        "\u5de9\u96c6"
    ],
    "wof:name":"Gongji",
    "wof:placetype":"locality"
},
  "geometry": {"coordinates":[105.52597,33.45038],"type":"Point"}
}