{
  "type": "Feature",
  "properties": {
    "gn:admin1_code":"14.0",
    "gn:asciiname":"Yangba",
    "gn:country_code":"CN",
    "gn:dem":3927,
    "gn:feature_class":"P",
    "gn:feature_code":"PPLF",
    "gn:name":"Yangba",
    "gn:population":0,
    "gn:timezone":"Asia/Urumqi",
    "iso:country":"CN",
    "name:bod_x_preferred":[
        "Yangba"
    ],
    "name:zho_x_preferred":[
        "\u592e\u5df4"
    ],
    "wof:name":"Yangba",
    "wof:placetype":"locality"
},
  "geometry": {"coordinates":[96.402,30.402],"type":"Point"}
}