{
  "type": "Feature",
  "properties": {
    "gn:admin1_code":"32.0",
    "gn:asciiname":"Yincheng",
    "gn:country_code":"CN",
    "gn:dem":514,
    "gn:feature_class":"P",
    "gn:feature_code":"PPL",
    "gn:name":"Yincheng",
    "gn:population":0,
    "gn:timezone":"Asia/Shanghai",
    "iso:country":"CN",
    "name:zho_x_preferred":[
        "\u5c39\u6210"
    ],
    "wof:name":"Yincheng",
    "wof:placetype":"locality"
},
  "geometry": {"coordinates":[106.399,31.6856],"type":"Point"}
}