{
  "type": "Feature",
  "properties": {
    "gn:admin1_code":"14.0",
    "gn:asciiname":"Qudang",
    "gn:country_code":"CN",
    "gn:dem":4688,
    "gn:feature_class":"P",
    "gn:feature_code":"PPLF",
    "gn:name":"Qudang",
    "gn:population":0,
    "gn:timezone":"Asia/Urumqi",
    "iso:country":"CN",
    "name:bod_x_preferred":[
        "Qud\u00eang"
    ],
    "name:zho_x_preferred":[
        "Qudang"
    ],
    "name:zho_x_variant":[
        "\u66f2\u5f53",
        "Kada Qu",
        "\u5361\u8fbe\u533a"
    ],
    "wof:name":"Qudang",
    "wof:placetype":"locality"
},
  "geometry": {"coordinates":[87.301,28.101],"type":"Point"}
}