{
  "type": "Feature",
  "properties": {
    "gn:admin1_code":"9.0",
    "gn:asciiname":"Zhangzhai",
    "gn:country_code":"CN",
    "gn:dem":154,
    "gn:feature_class":"P",
    "gn:feature_code":"PPL",
    "gn:name":"Zhangzhai",
    "gn:population":0,
    "gn:timezone":"Asia/Shanghai",
    "iso:country":"CN",
    "name:und_x_variant":[
        "\u5f20\u5be8"
    ],
    "name:zho_x_preferred":[
        "\u5f20\u5be8"
    ],
    "wof:name":"Zhangzhai",
    "wof:placetype":"locality"
},
  "geometry": {"coordinates":[113.09318,33.32281],"type":"Point"}
}