{
  "type": "Feature",
  "properties": {
    "gn:admin1_code":"5.0",
    "gn:asciiname":"Jixiangcun",
    "gn:country_code":"CN",
    "gn:dem":211,
    "gn:feature_class":"P",
    "gn:feature_code":"PPL",
    "gn:name":"Jixiangcun",
    "gn:population":0,
    "gn:timezone":"Asia/Shanghai",
    "iso:country":"CN",
    "name:zho_x_preferred":[
        "\u5409\u7965\u6751"
    ],
    "wof:name":"Jixiangcun",
    "wof:placetype":"locality"
},
  "geometry": {"coordinates":[125.60290999999999,44.0726],"type":"Point"}
}