{
  "type": "Feature",
  "properties": {
    "gn:admin1_code":"1.0",
    "gn:asciiname":"Daimiaocun",
    "gn:country_code":"CN",
    "gn:dem":29,
    "gn:feature_class":"P",
    "gn:feature_code":"PPL",
    "gn:name":"Daimiaocun",
    "gn:population":0,
    "gn:timezone":"Asia/Shanghai",
    "iso:country":"CN",
    "name:zho_x_preferred":[
        "\u6234\u5e99\u6751"
    ],
    "wof:name":"Daimiaocun",
    "wof:placetype":"locality"
},
  "geometry": {"coordinates":[116.74458,33.64568],"type":"Point"}
}