{
  "type": "Feature",
  "properties": {
    "gn:admin1_code":"18",
    "gn:asciiname":"Wengzhao",
    "gn:country_code":"CN",
    "gn:dem":1216,
    "gn:feature_class":"P",
    "gn:feature_code":"PPL",
    "gn:name":"Wengzhao",
    "gn:population":0,
    "gn:timezone":"Asia/Shanghai",
    "iso:country":"CN",
    "name:zho_x_preferred":[
        "\u7fc1\u62db"
    ],
    "wof:name":"Wengzhao",
    "wof:placetype":"locality"
},
  "geometry": {"coordinates":[106.79900000000001,26.4595],"type":"Point"}
}