{
  "type": "Feature",
  "properties": {
    "gn:admin1_code":"30.0",
    "gn:asciiname":"Liantang",
    "gn:country_code":"CN",
    "gn:dem":95,
    "gn:feature_class":"P",
    "gn:feature_code":"PPL",
    "gn:name":"Liantang",
    "gn:population":0,
    "gn:timezone":"Asia/Shanghai",
    "iso:country":"CN",
    "name:zho_x_preferred":[
        "Liantang"
    ],
    "name:zho_x_variant":[
        "\u7ec3\u5858"
    ],
    "wof:name":"Liantang",
    "wof:placetype":"locality"
},
  "geometry": {"coordinates":[113.3725,25.1275],"type":"Point"}
}