{
  "type": "Feature",
  "properties": {
    "gn:admin1_code":"16.0",
    "gn:asciiname":"Mengtong",
    "gn:country_code":"CN",
    "gn:dem":559,
    "gn:feature_class":"P",
    "gn:feature_code":"PPL",
    "gn:name":"Mengtong",
    "gn:population":0,
    "gn:timezone":"Asia/Shanghai",
    "iso:country":"CN",
    "name:zho_x_preferred":[
        "\u5b5f\u540c"
    ],
    "wof:name":"Mengtong",
    "wof:placetype":"locality"
},
  "geometry": {"coordinates":[108.34099999999999,25.1392],"type":"Point"}
}