{
  "type": "Feature",
  "properties": {
    "gn:admin1_code":"15.0",
    "gn:asciiname":"Zaoyang",
    "gn:country_code":"CN",
    "gn:dem":1576,
    "gn:feature_class":"P",
    "gn:feature_code":"PPL",
    "gn:name":"Zaoyang",
    "gn:population":0,
    "gn:timezone":"Asia/Shanghai",
    "iso:country":"CN",
    "name:zho_x_preferred":[
        "\u65e9\u9633"
    ],
    "wof:name":"Zaoyang",
    "wof:placetype":"locality"
},
  "geometry": {"coordinates":[105.42700000000001,34.174],"type":"Point"}
}