{
  "type": "Feature",
  "properties": {
    "gn:admin1_code":"31.0",
    "gn:asciiname":"Nanbang",
    "gn:country_code":"CN",
    "gn:dem":228,
    "gn:feature_class":"P",
    "gn:feature_code":"PPL",
    "gn:name":"Nanbang",
    "gn:population":0,
    "gn:timezone":"Asia/Shanghai",
    "iso:country":"CN",
    "name:zho_x_preferred":[
        "\u5357\u5e2e"
    ],
    "wof:name":"Nanbang",
    "wof:placetype":"locality"
},
  "geometry": {"coordinates":[109.50172000000001,19.2227],"type":"Point"}
}