{
  "type": "Feature",
  "properties": {
    "gn:admin1_code":"3.0",
    "gn:asciiname":"Qiaoshang Lijia",
    "gn:country_code":"CN",
    "gn:dem":51,
    "gn:feature_class":"P",
    "gn:feature_code":"PPL",
    "gn:name":"Qiaoshang Lijia",
    "gn:population":0,
    "gn:timezone":"Asia/Shanghai",
    "iso:country":"CN",
    "name:und_x_variant":[
        "\u6865\u4e0a\u674e\u5bb6"
    ],
    "wof:name":"Qiaoshang Lijia",
    "wof:placetype":"locality"
},
  "geometry": {"coordinates":[116.62226,28.42252],"type":"Point"}
}