{
  "type": "Feature",
  "properties": {
    "gn:admin1_code":"32.0",
    "gn:asciiname":"Lianghe",
    "gn:country_code":"CN",
    "gn:dem":1991,
    "gn:feature_class":"P",
    "gn:feature_code":"PPL",
    "gn:name":"Lianghe",
    "gn:population":0,
    "gn:timezone":"Asia/Shanghai",
    "iso:country":"CN",
    "name:zho_x_preferred":[
        "\u4e24\u6cb3"
    ],
    "wof:name":"Lianghe",
    "wof:placetype":"locality"
},
  "geometry": {"coordinates":[102.65680999999999,29.08508],"type":"Point"}
}