{
  "type": "Feature",
  "properties": {
    "gn:admin1_code":"25",
    "gn:asciiname":"Zhangdong",
    "gn:country_code":"CN",
    "gn:dem":41,
    "gn:feature_class":"P",
    "gn:feature_code":"PPL",
    "gn:name":"Zhangdong",
    "gn:population":0,
    "gn:timezone":"Asia/Shanghai",
    "iso:country":"CN",
    "name:ara_x_preferred":[
        "\u062c\u0627\u0646\u063a\u062f\u0648\u0646\u063a"
    ],
    "name:msa_x_preferred":[
        "Zhangdong"
    ],
    "name:zho_x_preferred":[
        "\u5f20\u4e1c"
    ],
    "wof:name":"Zhangdong",
    "wof:placetype":"locality"
},
  "geometry": {"coordinates":[116.70399999999999,35.2941],"type":"Point"}
}