{
  "type": "Feature",
  "properties": {
    "gn:admin1_code":"15.0",
    "gn:asciiname":"Mazongshan",
    "gn:country_code":"CN",
    "gn:dem":1749,
    "gn:feature_class":"P",
    "gn:feature_code":"PPLA4",
    "gn:name":"Mazongshan",
    "gn:population":0,
    "gn:timezone":"Asia/Urumqi",
    "iso:country":"CN",
    "name:und_x_variant":[
        "Mazongshan Zhen"
    ],
    "name:zho_x_preferred":[
        "\u9a6c\u9b03\u5c71"
    ],
    "name:zho_x_variant":[
        "\u9a6c\u9b03\u5c71\u9547"
    ],
    "wof:name":"Mazongshan",
    "wof:placetype":"locality"
},
  "geometry": {"coordinates":[97.02655,41.80885],"type":"Point"}
}