{
  "type": "Feature",
  "properties": {
    "gn:admin1_code":"18",
    "gn:asciiname":"Huajiaolin",
    "gn:country_code":"CN",
    "gn:dem":1062,
    "gn:feature_class":"P",
    "gn:feature_code":"PPL",
    "gn:name":"Huajiaolin",
    "gn:population":0,
    "gn:timezone":"Asia/Shanghai",
    "iso:country":"CN",
    "name:zho_x_preferred":[
        "\u82b1\u6912\u6797"
    ],
    "wof:name":"Huajiaolin",
    "wof:placetype":"locality"
},
  "geometry": {"coordinates":[107.80800000000001,28.1397],"type":"Point"}
}