{
  "type": "Feature",
  "properties": {
    "gn:admin1_code":"7",
    "gn:asciiname":"Houlou",
    "gn:country_code":"CN",
    "gn:dem":803,
    "gn:feature_class":"P",
    "gn:feature_code":"PPL",
    "gn:name":"Houlou",
    "gn:population":0,
    "gn:timezone":"Asia/Shanghai",
    "iso:country":"CN",
    "name:und_x_variant":[
        "\u540e\u697c",
        "Houlou"
    ],
    "wof:name":"Houlou",
    "wof:placetype":"locality"
},
  "geometry": {"coordinates":[119.81270000000001,27.25892],"type":"Point"}
}