{
  "type": "Feature",
  "properties": {
    "gn:admin1_code":"18",
    "gn:asciiname":"Wangfeng",
    "gn:country_code":"CN",
    "gn:dem":1593,
    "gn:feature_class":"P",
    "gn:feature_code":"PPL",
    "gn:name":"Wangfeng",
    "gn:population":0,
    "gn:timezone":"Asia/Shanghai",
    "iso:country":"CN",
    "name:zho_x_preferred":[
        "\u738b\u4e30"
    ],
    "name:zho_x_variant":[
        "\u738b\u5949\u9547"
    ],
    "wof:name":"Wangfeng",
    "wof:placetype":"locality"
},
  "geometry": {"coordinates":[105.205,27.2063],"type":"Point"}
}