{
  "type": "Feature",
  "properties": {
    "gn:admin1_code":"33.0",
    "gn:asciiname":"Tanziba",
    "gn:country_code":"CN",
    "gn:dem":1898,
    "gn:feature_class":"P",
    "gn:feature_code":"PPL",
    "gn:name":"Tanziba",
    "gn:population":0,
    "gn:timezone":"Asia/Shanghai",
    "iso:country":"CN",
    "name:zho_x_preferred":[
        "\u6f6d\u5b50\u575d"
    ],
    "wof:name":"Tanziba",
    "wof:placetype":"locality"
},
  "geometry": {"coordinates":[109.01733,31.92922],"type":"Point"}
}