{
  "type": "Feature",
  "properties": {
    "gn:admin1_code":"6.0",
    "gn:asciiname":"Sulongzhu",
    "gn:country_code":"CN",
    "gn:dem":1987,
    "gn:feature_class":"P",
    "gn:feature_code":"PPL",
    "gn:name":"Sulongzhu",
    "gn:population":0,
    "gn:timezone":"Asia/Shanghai",
    "iso:country":"CN",
    "name:und_x_variant":[
        "\u82cf\u9f99\u73e0"
    ],
    "wof:name":"Sulongzhu",
    "wof:placetype":"locality"
},
  "geometry": {"coordinates":[102.10682,35.82060999999999],"type":"Point"}
}