{
  "type": "Feature",
  "properties": {
    "gn:admin1_code":"32.0",
    "gn:asciiname":"Ge'nang",
    "gn:country_code":"CN",
    "gn:dem":4073,
    "gn:feature_class":"P",
    "gn:feature_code":"PPL",
    "gn:name":"Ge\u2019nang",
    "gn:population":0,
    "gn:timezone":"Asia/Shanghai",
    "iso:country":"CN",
    "name:zho_x_preferred":[
        "\u683c\u56ca"
    ],
    "name:zho_x_variant":[
        "Ge\u2019nang"
    ],
    "wof:name":"Ge'nang",
    "wof:placetype":"locality"
},
  "geometry": {"coordinates":[101.04022999999999,32.58384],"type":"Point"}
}