{
  "type": "Feature",
  "properties": {
    "gn:admin1_code":"24",
    "gn:asciiname":"Madaotou",
    "gn:country_code":"CN",
    "gn:dem":1540,
    "gn:feature_class":"P",
    "gn:feature_code":"PPLA4",
    "gn:name":"Madaotou",
    "gn:population":0,
    "gn:timezone":"Asia/Shanghai",
    "iso:country":"CN",
    "name:und_x_variant":[
        "Ma-tao-t\u2019ou",
        "Madaotou",
        "\u9a6c\u9053\u5934",
        "Madaotou Xiang",
        "\u9a6c\u9053\u5934\u4e61"
    ],
    "wof:name":"Madaotou",
    "wof:placetype":"locality"
},
  "geometry": {"coordinates":[112.76861,39.87611],"type":"Point"}
}