{
  "type": "Feature",
  "properties": {
    "gn:admin1_code":"5.0",
    "gn:asciiname":"Heiweizicun",
    "gn:country_code":"CN",
    "gn:dem":365,
    "gn:feature_class":"P",
    "gn:feature_code":"PPL",
    "gn:name":"Heiweizicun",
    "gn:population":0,
    "gn:timezone":"Asia/Shanghai",
    "iso:country":"CN",
    "name:zho_x_preferred":[
        "\u9ed1\u5d34\u5b50\u6751"
    ],
    "wof:name":"Heiweizicun",
    "wof:placetype":"locality"
},
  "geometry": {"coordinates":[125.88421,42.37334],"type":"Point"}
}