{
  "type": "Feature",
  "properties": {
    "gn:admin1_code":"19.0",
    "gn:asciiname":"Liumu Jianggou",
    "gn:country_code":"CN",
    "gn:dem":229,
    "gn:feature_class":"P",
    "gn:feature_code":"PPL",
    "gn:name":"Liumu Jianggou",
    "gn:population":0,
    "gn:timezone":"Asia/Shanghai",
    "iso:country":"CN",
    "name:und_x_variant":[
        "\u67f3\u6728\u5320\u6c9f"
    ],
    "name:zho_x_preferred":[
        "\u67f3\u6728\u5320\u6c9f"
    ],
    "wof:name":"Liumu Jianggou",
    "wof:placetype":"locality"
},
  "geometry": {"coordinates":[120.58947000000001,41.36208],"type":"Point"}
}