{
  "type": "Feature",
  "properties": {
    "gn:admin1_code":"14.0",
    "gn:asciiname":"Charang",
    "gn:country_code":"CN",
    "gn:dem":4696,
    "gn:feature_class":"P",
    "gn:feature_code":"PPL",
    "gn:name":"Charang",
    "gn:population":0,
    "gn:timezone":"Asia/Urumqi",
    "iso:country":"CN",
    "name:zho_x_preferred":[
        "\u5bdf\u8ba9"
    ],
    "wof:name":"Charang",
    "wof:placetype":"locality"
},
  "geometry": {"coordinates":[85.07600000000002,29.6605],"type":"Point"}
}