{
  "type": "Feature",
  "properties": {
    "gn:admin1_code":"8.0",
    "gn:asciiname":"Yongsheng Liudui",
    "gn:country_code":"CN",
    "gn:dem":146,
    "gn:feature_class":"P",
    "gn:feature_code":"PPLF",
    "gn:name":"Yongsheng Liudui",
    "gn:population":0,
    "gn:timezone":"Asia/Shanghai",
    "iso:country":"CN",
    "name:zho_x_preferred":[
        "\u6c38\u80dc\u516d\u961f"
    ],
    "wof:name":"Yongsheng Liudui",
    "wof:placetype":"locality"
},
  "geometry": {"coordinates":[123.53449999999999,47.04403],"type":"Point"}
}