{
  "type": "Feature",
  "properties": {
    "gn:admin1_code":"26.0",
    "gn:asciiname":"Shuanggumu",
    "gn:country_code":"CN",
    "gn:dem":593,
    "gn:feature_class":"P",
    "gn:feature_code":"PPL",
    "gn:name":"Shuanggumu",
    "gn:population":0,
    "gn:timezone":"Asia/Shanghai",
    "iso:country":"CN",
    "name:und_x_variant":[
        "\u53cc\u59d1\u5893"
    ],
    "wof:name":"Shuanggumu",
    "wof:placetype":"locality"
},
  "geometry": {"coordinates":[107.70009,33.35551],"type":"Point"}
}