{
  "type": "Feature",
  "properties": {
    "gn:admin1_code":"8.0",
    "gn:asciiname":"Toudaocun",
    "gn:country_code":"CN",
    "gn:dem":229,
    "gn:feature_class":"P",
    "gn:feature_code":"PPL",
    "gn:name":"Toudaocun",
    "gn:population":0,
    "gn:timezone":"Asia/Shanghai",
    "iso:country":"CN",
    "name:zho_x_preferred":[
        "\u5934\u9053\u6751"
    ],
    "wof:name":"Toudaocun",
    "wof:placetype":"locality"
},
  "geometry": {"coordinates":[129.61365000000001,44.85299000000001],"type":"Point"}
}