{
  "type": "Feature",
  "properties": {
    "gn:admin1_code":"16.0",
    "gn:asciiname":"Pangu",
    "gn:country_code":"CN",
    "gn:dem":39,
    "gn:feature_class":"P",
    "gn:feature_code":"PPL",
    "gn:name":"Pangu",
    "gn:population":0,
    "gn:timezone":"Asia/Shanghai",
    "iso:country":"CN",
    "name:ara_x_preferred":[
        "\u0628\u0627\u0646 \u0643\u0648"
    ],
    "name:cat_x_preferred":[
        "Pangu"
    ],
    "name:ces_x_preferred":[
        "Pangu"
    ],
    "name:cym_x_preferred":[
        "Pangu"
    ],
    "name:deu_x_preferred":[
        "Pangu"
    ],
    "name:fas_x_preferred":[
        "\u067e\u0627\u0646\u06af\u0648"
    ],
    "name:fra_x_preferred":[
        "Pangu"
    ],
    "name:hak_x_preferred":[
        "Ph\u00e0n-k\u00fa"
    ],
    "name:hun_x_preferred":[
        "Pan-ku"
    ],
    "name:ind_x_preferred":[
        "Pangu"
    ],
    "name:ita_x_preferred":[
        "Pangu"
    ],
    "name:kor_x_preferred":[
        "\ubc18\uace0"
    ],
    "name:nld_x_preferred":[
        "Pangu"
    ],
    "name:nor_x_preferred":[
        "Pangu"
    ],
    "name:pol_x_preferred":[
        "Pangu"
    ],
    "name:por_x_preferred":[
        "Pan Ku"
    ],
    "name:ron_x_preferred":[
        "Pan ku"
    ],
    "name:rus_x_preferred":[
        "\u041f\u0430\u043d\u044c\u0433\u0443"
    ],
    "name:spa_x_preferred":[
        "Pangu"
    ],
    "name:swe_x_preferred":[
        "Pangu"
    ],
    "name:tam_x_preferred":[
        "\u0baa\u0ba9\u0bcd\u0b95\u0bc1"
    ],
    "name:tha_x_preferred":[
        "\u0e1c\u0e32\u0e19\u0e01\u0e39\u0e48"
    ],
    "name:tur_x_preferred":[
        "Pan Gu"
    ],
    "name:ukr_x_preferred":[
        "\u041f\u0430\u043d\u044c-\u0433\u0443"
    ],
    "name:vie_x_preferred":[
        "B\u00e0n C\u1ed5"
    ],
    "name:zho_x_preferred":[
        "\u87e0\u53e4"
    ],
    "wof:name":"Pangu",
    "wof:placetype":"locality"
},
  "geometry": {"coordinates":[110.741,23.5475],"type":"Point"}
}