{
  "type": "Feature",
  "properties": {
    "gn:admin1_code":"6.0",
    "gn:asciiname":"Ri'a Jida",
    "gn:country_code":"CN",
    "gn:dem":4110,
    "gn:feature_class":"P",
    "gn:feature_code":"PPL",
    "gn:name":"Ri\u2019a Jida",
    "gn:population":0,
    "gn:timezone":"Asia/Urumqi",
    "iso:country":"CN",
    "name:und_x_variant":[
        "Ri\u2019a Jida"
    ],
    "name:zho_x_preferred":[
        "\u65e5\u963f\u7ed9\u8fbe"
    ],
    "wof:name":"Ri'a Jida",
    "wof:placetype":"locality"
},
  "geometry": {"coordinates":[96.25296,32.66859],"type":"Point"}
}