{
  "type": "Feature",
  "properties": {
    "gn:admin1_code":"32.0",
    "gn:asciiname":"Wanlongzui",
    "gn:country_code":"CN",
    "gn:dem":372,
    "gn:feature_class":"P",
    "gn:feature_code":"PPL",
    "gn:name":"Wanlongzui",
    "gn:population":0,
    "gn:timezone":"Asia/Shanghai",
    "iso:country":"CN",
    "name:zho_x_preferred":[
        "\u4e07\u9f99\u5480"
    ],
    "wof:name":"Wanlongzui",
    "wof:placetype":"locality"
},
  "geometry": {"coordinates":[104.446,30.0551],"type":"Point"}
}