{
  "type": "Feature",
  "properties": {
    "gn:admin1_code":"32.0",
    "gn:asciiname":"Amituofo",
    "gn:country_code":"CN",
    "gn:dem":513,
    "gn:feature_class":"P",
    "gn:feature_code":"PPL",
    "gn:name":"Amituofo",
    "gn:population":0,
    "gn:timezone":"Asia/Shanghai",
    "iso:country":"CN",
    "name:zho_x_preferred":[
        "\u963f\u5f25\u9640\u4f5b"
    ],
    "wof:name":"Amituofo",
    "wof:placetype":"locality"
},
  "geometry": {"coordinates":[103.97499999999999,30.304],"type":"Point"}
}