{
  "type": "Feature",
  "properties": {
    "gn:admin1_code":"5.0",
    "gn:asciiname":"Houxingtun",
    "gn:country_code":"CN",
    "gn:dem":183,
    "gn:feature_class":"P",
    "gn:feature_code":"PPL",
    "gn:name":"Houxingtun",
    "gn:population":0,
    "gn:timezone":"Asia/Shanghai",
    "iso:country":"CN",
    "name:zho_x_preferred":[
        "\u540e\u5174\u5c6f"
    ],
    "wof:name":"Houxingtun",
    "wof:placetype":"locality"
},
  "geometry": {"coordinates":[126.55629,44.92334],"type":"Point"}
}