{
  "type": "Feature",
  "properties": {
    "gn:admin1_code":"11.0",
    "gn:asciiname":"Dujiatai",
    "gn:country_code":"CN",
    "gn:dem":176,
    "gn:feature_class":"P",
    "gn:feature_code":"PPL",
    "gn:name":"Dujiatai",
    "gn:population":0,
    "gn:timezone":"Asia/Shanghai",
    "iso:country":"CN",
    "name:zho_x_preferred":[
        "Dujiatai"
    ],
    "name:zho_x_variant":[
        "\u675c\u5bb6\u53f0"
    ],
    "wof:name":"Dujiatai",
    "wof:placetype":"locality"
},
  "geometry": {"coordinates":[111.54955,29.88677],"type":"Point"}
}