{
  "type": "Feature",
  "properties": {
    "gn:admin1_code":"16.0",
    "gn:asciiname":"Shirendao",
    "gn:country_code":"CN",
    "gn:dem":63,
    "gn:feature_class":"P",
    "gn:feature_code":"PPL",
    "gn:name":"Shirendao",
    "gn:population":0,
    "gn:timezone":"Asia/Shanghai",
    "iso:country":"CN",
    "name:zho_x_preferred":[
        "\u77f3\u4eba\u5c9b"
    ],
    "wof:name":"Shirendao",
    "wof:placetype":"locality"
},
  "geometry": {"coordinates":[110.79600000000001,24.0873],"type":"Point"}
}