{
  "type": "Feature",
  "properties": {
    "gn:admin1_code":"1.0",
    "gn:asciiname":"Pangqiaocun",
    "gn:country_code":"CN",
    "gn:dem":30,
    "gn:feature_class":"P",
    "gn:feature_code":"PPL",
    "gn:name":"Pangqiaocun",
    "gn:population":0,
    "gn:timezone":"Asia/Shanghai",
    "iso:country":"CN",
    "name:zho_x_preferred":[
        "\u5e9e\u6865\u6751"
    ],
    "wof:name":"Pangqiaocun",
    "wof:placetype":"locality"
},
  "geometry": {"coordinates":[115.95027,33.2557],"type":"Point"}
}