{
  "type": "Feature",
  "properties": {
    "gn:admin1_code":"18.0",
    "gn:asciiname":"Lamaozhai",
    "gn:country_code":"CN",
    "gn:dem":1047,
    "gn:feature_class":"P",
    "gn:feature_code":"PPL",
    "gn:name":"Lamaozhai",
    "gn:population":0,
    "gn:timezone":"Asia/Shanghai",
    "iso:country":"CN",
    "name:zho_x_preferred":[
        "\u62c9\u8302\u5be8"
    ],
    "wof:name":"Lamaozhai",
    "wof:placetype":"locality"
},
  "geometry": {"coordinates":[107.443,25.8144],"type":"Point"}
}