{
  "type": "Feature",
  "properties": {
    "gn:admin1_code":"14.0",
    "gn:asciiname":"Jiamu",
    "gn:country_code":"CN",
    "gn:dem":4148,
    "gn:feature_class":"P",
    "gn:feature_code":"PPL",
    "gn:name":"Jiamu",
    "gn:population":0,
    "gn:timezone":"Asia/Urumqi",
    "iso:country":"CN",
    "name:zho_x_preferred":[
        "\u52a0\u6728"
    ],
    "wof:name":"Jiamu",
    "wof:placetype":"locality"
},
  "geometry": {"coordinates":[85.3168,28.8372],"type":"Point"}
}