{
  "type": "Feature",
  "properties": {
    "gn:admin1_code":"24",
    "gn:asciiname":"Dongshuitou",
    "gn:country_code":"CN",
    "gn:dem":1191,
    "gn:feature_class":"P",
    "gn:feature_code":"PPL",
    "gn:name":"Dongshuitou",
    "gn:population":0,
    "gn:timezone":"Asia/Shanghai",
    "iso:country":"CN",
    "name:und_x_variant":[
        "Tung-shui-t\u2019ou",
        "Dongshuitou"
    ],
    "name:zho_x_preferred":[
        "\u4e1c\u6c34\u5934"
    ],
    "wof:name":"Dongshuitou",
    "wof:placetype":"locality"
},
  "geometry": {"coordinates":[113.77313999999998,40.13897],"type":"Point"}
}