{
  "type": "Feature",
  "properties": {
    "gn:admin1_code":"5.0",
    "gn:asciiname":"Dongshengcun",
    "gn:country_code":"CN",
    "gn:dem":277,
    "gn:feature_class":"P",
    "gn:feature_code":"PPL",
    "gn:name":"Dongshengcun",
    "gn:population":0,
    "gn:timezone":"Asia/Shanghai",
    "iso:country":"CN",
    "name:zho_x_preferred":[
        "\u4e1c\u5347\u6751"
    ],
    "wof:name":"Dongshengcun",
    "wof:placetype":"locality"
},
  "geometry": {"coordinates":[125.52330000000001,43.7934],"type":"Point"}
}