{
  "type": "Feature",
  "properties": {
    "gn:admin1_code":"9.0",
    "gn:asciiname":"Dongwangying",
    "gn:country_code":"CN",
    "gn:dem":54,
    "gn:feature_class":"P",
    "gn:feature_code":"PPL",
    "gn:name":"Dongwangying",
    "gn:population":0,
    "gn:timezone":"Asia/Shanghai",
    "iso:country":"CN",
    "name:zho_x_preferred":[
        "\u4e1c\u738b\u8425"
    ],
    "wof:name":"Dongwangying",
    "wof:placetype":"locality"
},
  "geometry": {"coordinates":[114.62907,33.7116],"type":"Point"}
}