{
  "type": "Feature",
  "properties": {
    "gn:admin1_code":"10",
    "gn:asciiname":"Dongpingtai",
    "gn:country_code":"CN",
    "gn:dem":168,
    "gn:feature_class":"P",
    "gn:feature_code":"PPL",
    "gn:name":"Dongpingtai",
    "gn:population":0,
    "gn:timezone":"Asia/Shanghai",
    "iso:country":"CN",
    "name:zho_x_preferred":[
        "\u4e1c\u5e73\u53f0"
    ],
    "wof:name":"Dongpingtai",
    "wof:placetype":"locality"
},
  "geometry": {"coordinates":[118.12456,40.0356],"type":"Point"}
}