{
  "type": "Feature",
  "properties": {
    "gn:admin1_code":"29.0",
    "gn:asciiname":"Chushui",
    "gn:country_code":"CN",
    "gn:dem":2301,
    "gn:feature_class":"P",
    "gn:feature_code":"PPL",
    "gn:name":"Chushui",
    "gn:population":0,
    "gn:timezone":"Asia/Shanghai",
    "iso:country":"CN",
    "name:und_x_variant":[
        "\u51fa\u6c34"
    ],
    "wof:name":"Chushui",
    "wof:placetype":"locality"
},
  "geometry": {"coordinates":[103.91876999999999,27.66183],"type":"Point"}
}