{
  "type": "Feature",
  "properties": {
    "gn:admin1_code":"24",
    "gn:asciiname":"Shijiudun",
    "gn:cc2":"CN",
    "gn:country_code":"CN",
    "gn:dem":1421,
    "gn:feature_class":"P",
    "gn:feature_code":"PPL",
    "gn:name":"Shijiudun",
    "gn:population":0,
    "gn:timezone":"Asia/Shanghai",
    "iso:country":"CN",
    "name:und_x_variant":[
        "Shih-chiu-liang",
        "Shijiudun"
    ],
    "wof:name":"Shijiudun",
    "wof:placetype":"locality"
},
  "geometry": {"coordinates":[113.62833000000001,40.39556],"type":"Point"}
}