{
  "type": "Feature",
  "properties": {
    "gn:admin1_code":"18",
    "gn:asciiname":"Zhuangzitai",
    "gn:country_code":"CN",
    "gn:dem":829,
    "gn:feature_class":"P",
    "gn:feature_code":"PPL",
    "gn:name":"Zhuangzitai",
    "gn:population":0,
    "gn:timezone":"Asia/Shanghai",
    "iso:country":"CN",
    "name:zho_x_preferred":[
        "\u5e84\u5b50\u53f0"
    ],
    "wof:name":"Zhuangzitai",
    "wof:placetype":"locality"
},
  "geometry": {"coordinates":[107.822,28.545],"type":"Point"}
}