{
  "type": "Feature",
  "properties": {
    "gn:admin1_code":"11.0",
    "gn:asciiname":"Gaotouwu",
    "gn:country_code":"CN",
    "gn:dem":208,
    "gn:feature_class":"P",
    "gn:feature_code":"PPL",
    "gn:name":"Gaotouwu",
    "gn:population":0,
    "gn:timezone":"Asia/Shanghai",
    "iso:country":"CN",
    "name:zho_x_preferred":[
        "\u9ad8\u5934\u5c4b"
    ],
    "wof:name":"Gaotouwu",
    "wof:placetype":"locality"
},
  "geometry": {"coordinates":[110.69145,28.57919],"type":"Point"}
}