{
  "type": "Feature",
  "properties": {
    "gn:admin1_code":"5.0",
    "gn:asciiname":"Dongwazi",
    "gn:country_code":"CN",
    "gn:dem":158,
    "gn:feature_class":"P",
    "gn:feature_code":"PPL",
    "gn:name":"Dongwazi",
    "gn:population":0,
    "gn:timezone":"Asia/Shanghai",
    "iso:country":"CN",
    "name:zho_x_preferred":[
        "\u4e1c\u6d3c\u5b50"
    ],
    "wof:name":"Dongwazi",
    "wof:placetype":"locality"
},
  "geometry": {"coordinates":[123.84484999999999,43.80762],"type":"Point"}
}