{
  "type": "Feature",
  "properties": {
    "gn:admin1_code":"30",
    "gn:asciiname":"Nahuo",
    "gn:country_code":"CN",
    "gn:dem":74,
    "gn:feature_class":"P",
    "gn:feature_code":"PPLA4",
    "gn:name":"Nahuo",
    "gn:population":0,
    "gn:timezone":"Asia/Urumqi",
    "iso:country":"CN",
    "name:und_x_variant":[
        "Nahuo Zhen",
        "\u90a3\u970d\u9547"
    ],
    "name:zho_x_preferred":[
        "\u90a3\u970d"
    ],
    "wof:name":"Nahuo",
    "wof:placetype":"locality"
},
  "geometry": {"coordinates":[111.23862,21.89092],"type":"Point"}
}