{
  "type": "Feature",
  "properties": {
    "gn:admin1_code":"25",
    "gn:asciiname":"Hongmiaozhuang",
    "gn:country_code":"CN",
    "gn:dem":52,
    "gn:feature_class":"P",
    "gn:feature_code":"PPL",
    "gn:name":"Hongmiaozhuang",
    "gn:population":0,
    "gn:timezone":"Asia/Shanghai",
    "iso:country":"CN",
    "name:zho_x_preferred":[
        "\u7ea2\u5e99\u5e84"
    ],
    "wof:name":"Hongmiaozhuang",
    "wof:placetype":"locality"
},
  "geometry": {"coordinates":[115.79300000000001,34.7348],"type":"Point"}
}