{
  "type": "Feature",
  "properties": {
    "gn:admin1_code":"30",
    "gn:asciiname":"Yangxinlou",
    "gn:country_code":"CN",
    "gn:dem":124,
    "gn:feature_class":"P",
    "gn:feature_code":"PPL",
    "gn:name":"Yangxinlou",
    "gn:population":0,
    "gn:timezone":"Asia/Shanghai",
    "iso:country":"CN",
    "name:zho_x_preferred":[
        "\u6d0b\u5fc3\u697c"
    ],
    "wof:name":"Yangxinlou",
    "wof:placetype":"locality"
},
  "geometry": {"coordinates":[116.91897,23.92856],"type":"Point"}
}