{
  "type": "Feature",
  "properties": {
    "gn:admin1_code":"2.0",
    "gn:asciiname":"Daxizhuang",
    "gn:country_code":"CN",
    "gn:dem":9,
    "gn:feature_class":"P",
    "gn:feature_code":"PPL",
    "gn:name":"Daxizhuang",
    "gn:population":0,
    "gn:timezone":"Asia/Shanghai",
    "iso:country":"CN",
    "name:und_x_variant":[
        "\u5927\u897f\u5e84"
    ],
    "wof:name":"Daxizhuang",
    "wof:placetype":"locality"
},
  "geometry": {"coordinates":[120.45538000000001,30.12141],"type":"Point"}
}