{
  "type": "Feature",
  "properties": {
    "gn:admin1_code":"30",
    "gn:asciiname":"Shanglan",
    "gn:country_code":"CN",
    "gn:dem":181,
    "gn:feature_class":"P",
    "gn:feature_code":"PPL",
    "gn:name":"Shanglan",
    "gn:population":0,
    "gn:timezone":"Asia/Shanghai",
    "iso:country":"CN",
    "name:und_x_variant":[
        "\u4e0a\u84dd"
    ],
    "wof:name":"Shanglan",
    "wof:placetype":"locality"
},
  "geometry": {"coordinates":[114.91512,24.08459],"type":"Point"}
}