{
  "type": "Feature",
  "properties": {
    "gn:admin1_code":"5.0",
    "gn:asciiname":"Yonglicun",
    "gn:country_code":"CN",
    "gn:dem":197,
    "gn:feature_class":"P",
    "gn:feature_code":"PPL",
    "gn:name":"Yonglicun",
    "gn:population":0,
    "gn:timezone":"Asia/Shanghai",
    "iso:country":"CN",
    "name:zho_x_preferred":[
        "\u6c38\u5229\u6751"
    ],
    "wof:name":"Yonglicun",
    "wof:placetype":"locality"
},
  "geometry": {"coordinates":[125.94237,44.88384],"type":"Point"}
}