{
  "type": "Feature",
  "properties": {
    "gn:admin1_code":"29.0",
    "gn:asciiname":"Reshuichang",
    "gn:country_code":"CN",
    "gn:dem":1998,
    "gn:feature_class":"P",
    "gn:feature_code":"PPL",
    "gn:name":"Reshuichang",
    "gn:population":0,
    "gn:timezone":"Asia/Shanghai",
    "iso:country":"CN",
    "name:zho_x_preferred":[
        "\u70ed\u6c34\u573a"
    ],
    "wof:name":"Reshuichang",
    "wof:placetype":"locality"
},
  "geometry": {"coordinates":[99.3297,26.0134],"type":"Point"}
}