{
  "type": "Feature",
  "properties": {
    "gn:admin1_code":"03",
    "gn:asciiname":"Qingxi",
    "gn:country_code":"CN",
    "gn:dem":530,
    "gn:feature_class":"P",
    "gn:feature_code":"PPLA4",
    "gn:name":"Qingxi",
    "gn:population":0,
    "gn:timezone":"Asia/Shanghai",
    "iso:country":"CN",
    "name:ceb_x_preferred":[
        "Qingxi"
    ],
    "name:deu_x_preferred":[
        "Qingxi"
    ],
    "name:swe_x_preferred":[
        "Qingxi"
    ],
    "name:und_x_variant":[
        "Ch\u2019ing-ch\u2019i",
        "Ch\u2019ing-ch\u2019i-hs\u00fc",
        "\u6e05\u6eaa",
        "Qingxi Xiang",
        "\u6e05\u6eaa\u4e61"
    ],
    "wof:name":"Qingxi",
    "wof:placetype":"locality"
},
  "geometry": {"coordinates":[115.61391999999999,25.22949],"type":"Point"}
}