{
  "type": "Feature",
  "properties": {
    "gn:admin1_code":"32.0",
    "gn:asciiname":"Ma'erdang",
    "gn:country_code":"CN",
    "gn:dem":3070,
    "gn:feature_class":"P",
    "gn:feature_code":"PPL",
    "gn:name":"Ma\u2019erdang",
    "gn:population":0,
    "gn:timezone":"Asia/Shanghai",
    "iso:country":"CN",
    "name:und_x_variant":[
        "Ma\u2019erdang"
    ],
    "name:zho_x_preferred":[
        "\u9a6c\u5c14\u51fc"
    ],
    "wof:name":"Ma'erdang",
    "wof:placetype":"locality"
},
  "geometry": {"coordinates":[102.51000000000001,31.4295],"type":"Point"}
}