{
  "type": "Feature",
  "properties": {
    "gn:admin1_code":"26.0",
    "gn:asciiname":"Dahaizegou",
    "gn:country_code":"CN",
    "gn:dem":1103,
    "gn:feature_class":"P",
    "gn:feature_code":"PPL",
    "gn:name":"Dahaizegou",
    "gn:population":0,
    "gn:timezone":"Asia/Shanghai",
    "iso:country":"CN",
    "name:zho_x_preferred":[
        "\u5927\u6d77\u5219\u6c9f"
    ],
    "wof:name":"Dahaizegou",
    "wof:placetype":"locality"
},
  "geometry": {"coordinates":[109.14999,37.98281],"type":"Point"}
}