{
  "type": "Feature",
  "properties": {
    "gn:admin1_code":"2.0",
    "gn:asciiname":"Wanzhong",
    "gn:country_code":"CN",
    "gn:dem":11,
    "gn:feature_class":"P",
    "gn:feature_code":"PPL",
    "gn:name":"Wanzhong",
    "gn:population":0,
    "gn:timezone":"Asia/Shanghai",
    "iso:country":"CN",
    "name:und_x_variant":[
        "\u4e07\u4f17"
    ],
    "wof:name":"Wanzhong",
    "wof:placetype":"locality"
},
  "geometry": {"coordinates":[120.11445000000001,30.07381],"type":"Point"}
}