{
  "type": "Feature",
  "properties": {
    "gn:admin1_code":"32.0",
    "gn:asciiname":"Gaobanqiao",
    "gn:country_code":"CN",
    "gn:dem":565,
    "gn:feature_class":"P",
    "gn:feature_code":"PPL",
    "gn:name":"Gaobanqiao",
    "gn:population":0,
    "gn:timezone":"Asia/Shanghai",
    "iso:country":"CN",
    "name:zho_x_preferred":[
        "\u9ad8\u677f\u6865"
    ],
    "wof:name":"Gaobanqiao",
    "wof:placetype":"locality"
},
  "geometry": {"coordinates":[104.779,31.8603],"type":"Point"}
}