{
  "type": "Feature",
  "properties": {
    "gn:admin1_code":"29.0",
    "gn:asciiname":"Qianqiucun",
    "gn:country_code":"CN",
    "gn:dem":1674,
    "gn:feature_class":"P",
    "gn:feature_code":"PPL",
    "gn:name":"Qianqiucun",
    "gn:population":0,
    "gn:timezone":"Asia/Shanghai",
    "iso:country":"CN",
    "name:zho_x_preferred":[
        "\u5343\u79cb\u6751"
    ],
    "wof:name":"Qianqiucun",
    "wof:placetype":"locality"
},
  "geometry": {"coordinates":[105.071,27.5299],"type":"Point"}
}