{
  "type": "Feature",
  "properties": {
    "gn:admin1_code":"4.0",
    "gn:asciiname":"Hebei",
    "gn:country_code":"CN",
    "gn:dem":2,
    "gn:feature_class":"P",
    "gn:feature_code":"PPL",
    "gn:name":"Hebei",
    "gn:population":0,
    "gn:timezone":"Asia/Shanghai",
    "iso:country":"CN",
    "name:zho_x_preferred":[
        "Hebei"
    ],
    "name:zho_x_variant":[
        "\u6cb3\u5317"
    ],
    "wof:name":"Hebei",
    "wof:placetype":"locality"
},
  "geometry": {"coordinates":[119.6001,33.39942],"type":"Point"}
}