{
  "type": "Feature",
  "properties": {
    "gn:admin1_code":"4.0",
    "gn:asciiname":"Shiyu Gaodian",
    "gn:country_code":"CN",
    "gn:dem":4,
    "gn:feature_class":"P",
    "gn:feature_code":"PPL",
    "gn:name":"Shiyu Gaodian",
    "gn:population":0,
    "gn:timezone":"Asia/Shanghai",
    "iso:country":"CN",
    "name:zho_x_preferred":[
        "Shiyu Gaodian"
    ],
    "name:zho_x_variant":[
        "\u65bd\u88d5\u9ad8\u5e97"
    ],
    "wof:name":"Shiyu Gaodian",
    "wof:placetype":"locality"
},
  "geometry": {"coordinates":[121.496,31.88299],"type":"Point"}
}