{
  "type": "Feature",
  "properties": {
    "gn:admin1_code":"15.0",
    "gn:asciiname":"Xigong",
    "gn:country_code":"CN",
    "gn:dem":2965,
    "gn:feature_class":"P",
    "gn:feature_code":"PPL",
    "gn:name":"Xigong",
    "gn:population":0,
    "gn:timezone":"Asia/Shanghai",
    "iso:country":"CN",
    "name:und_x_variant":[
        "\u897f\u529f"
    ],
    "wof:name":"Xigong",
    "wof:placetype":"locality"
},
  "geometry": {"coordinates":[103.12527,34.52038],"type":"Point"}
}