{
  "type": "Feature",
  "properties": {
    "gn:admin1_code":"19.0",
    "gn:asciiname":"Qiansancha",
    "gn:country_code":"CN",
    "gn:dem":56,
    "gn:feature_class":"P",
    "gn:feature_code":"PPL",
    "gn:name":"Qiansancha",
    "gn:population":0,
    "gn:timezone":"Asia/Shanghai",
    "iso:country":"CN",
    "name:und_x_variant":[
        "\u524d\u4e09\u5c94"
    ],
    "wof:name":"Qiansancha",
    "wof:placetype":"locality"
},
  "geometry": {"coordinates":[123.41506,40.22711],"type":"Point"}
}