{
  "type": "Feature",
  "properties": {
    "gn:admin1_code":"13",
    "gn:asciiname":"Kaladun",
    "gn:country_code":"CN",
    "gn:dem":1282,
    "gn:feature_class":"P",
    "gn:feature_code":"PPL",
    "gn:name":"Kaladun",
    "gn:population":0,
    "gn:timezone":"Asia/Shanghai",
    "iso:country":"CN",
    "name:und_x_variant":[
        "\u5580\u62c9\u58a9"
    ],
    "wof:name":"Kaladun",
    "wof:placetype":"locality"
},
  "geometry": {"coordinates":[77.30225,38.09035],"type":"Point"}
}