{
  "type": "Feature",
  "properties": {
    "gn:admin1_code":"16.0",
    "gn:asciiname":"Lawancun",
    "gn:country_code":"CN",
    "gn:dem":204,
    "gn:feature_class":"P",
    "gn:feature_code":"PPL",
    "gn:name":"Lawancun",
    "gn:population":0,
    "gn:timezone":"Asia/Shanghai",
    "iso:country":"CN",
    "name:zho_x_preferred":[
        "\u62c9\u4e07\u6751"
    ],
    "wof:name":"Lawancun",
    "wof:placetype":"locality"
},
  "geometry": {"coordinates":[107.66500000000001,23.9682],"type":"Point"}
}