{
  "type": "Feature",
  "properties": {
    "gn:admin1_code":"1.0",
    "gn:asciiname":"Renmin",
    "gn:country_code":"CN",
    "gn:dem":11,
    "gn:feature_class":"P",
    "gn:feature_code":"PPL",
    "gn:name":"Renmin",
    "gn:population":0,
    "gn:timezone":"Asia/Shanghai",
    "iso:country":"CN",
    "name:zho_x_preferred":[
        "\u4eba\u6c11"
    ],
    "wof:name":"Renmin",
    "wof:placetype":"locality"
},
  "geometry": {"coordinates":[118.36038000000001,31.82965],"type":"Point"}
}