{
  "type": "Feature",
  "properties": {
    "gn:admin1_code":"7.0",
    "gn:asciiname":"Liuban",
    "gn:country_code":"CN",
    "gn:dem":175,
    "gn:feature_class":"P",
    "gn:feature_code":"PPL",
    "gn:name":"Liuban",
    "gn:population":0,
    "gn:timezone":"Asia/Shanghai",
    "iso:country":"CN",
    "name:und_x_variant":[
        "\u5218\u5742"
    ],
    "name:zho_x_preferred":[
        "\u5218\u5742"
    ],
    "wof:name":"Liuban",
    "wof:placetype":"locality"
},
  "geometry": {"coordinates":[118.33508999999999,26.3072],"type":"Point"}
}