{
  "type": "Feature",
  "properties": {
    "gn:admin1_code":"4.0",
    "gn:asciiname":"Shiduancun",
    "gn:country_code":"CN",
    "gn:dem":36,
    "gn:feature_class":"P",
    "gn:feature_code":"PPL",
    "gn:name":"Shiduancun",
    "gn:population":0,
    "gn:timezone":"Asia/Shanghai",
    "iso:country":"CN",
    "name:zho_x_preferred":[
        "\u62fe\u6bb5\u6751"
    ],
    "wof:name":"Shiduancun",
    "wof:placetype":"locality"
},
  "geometry": {"coordinates":[117.12220000000001,34.51016],"type":"Point"}
}