{
  "type": "Feature",
  "properties": {
    "gn:admin1_code":"13.0",
    "gn:asciiname":"Saybag",
    "gn:cc2":"CN",
    "gn:country_code":"CN",
    "gn:dem":1362,
    "gn:feature_class":"P",
    "gn:feature_code":"PPL",
    "gn:name":"Saybag",
    "gn:population":0,
    "gn:timezone":"Asia/Shanghai",
    "iso:country":"CN",
    "name:uig_x_preferred":[
        "Sayba\u01a3"
    ],
    "name:uig_x_variant":[
        "Saybagh",
        "\u0633\u0627\u064a\u0628\u0627\u063a",
        "\u0421\u0430\u0439\u0431\u0430\u0493"
    ],
    "name:und_x_variant":[
        "Saybag Xiang",
        "Saybag"
    ],
    "wof:name":"Saybag",
    "wof:placetype":"locality"
},
  "geometry": {"coordinates":[79.65833000000001,37.14972],"type":"Point"}
}