{
  "type": "Feature",
  "properties": {
    "gn:admin1_code":"24.0",
    "gn:asciiname":"Baisencun",
    "gn:country_code":"CN",
    "gn:dem":768,
    "gn:feature_class":"P",
    "gn:feature_code":"PPL",
    "gn:name":"Baisencun",
    "gn:population":0,
    "gn:timezone":"Asia/Shanghai",
    "iso:country":"CN",
    "name:zho_x_preferred":[
        "\u67cf\u68ee\u6751"
    ],
    "wof:name":"Baisencun",
    "wof:placetype":"locality"
},
  "geometry": {"coordinates":[112.29255999999999,37.29182],"type":"Point"}
}