{
  "type": "Feature",
  "properties": {
    "gn:admin1_code":"9.0",
    "gn:asciiname":"Shuitahe Yijie",
    "gn:country_code":"CN",
    "gn:dem":60,
    "gn:feature_class":"P",
    "gn:feature_code":"PPL",
    "gn:name":"Shuitahe Yijie",
    "gn:population":0,
    "gn:timezone":"Asia/Shanghai",
    "iso:country":"CN",
    "name:zho_x_preferred":[
        "\u6c34\u5854\u6cb3\u4e00\u8857"
    ],
    "wof:name":"Shuitahe Yijie",
    "wof:placetype":"locality"
},
  "geometry": {"coordinates":[114.62983,35.901],"type":"Point"}
}