{
  "type": "Feature",
  "properties": {
    "gn:admin1_code":"2.0",
    "gn:asciiname":"Shangzhangcun",
    "gn:country_code":"CN",
    "gn:dem":300,
    "gn:feature_class":"P",
    "gn:feature_code":"PPL",
    "gn:name":"Shangzhangcun",
    "gn:population":0,
    "gn:timezone":"Asia/Shanghai",
    "iso:country":"CN",
    "name:und_x_variant":[
        "\u4e0a\u5f20\u6751",
        "Shangzhangcun"
    ],
    "wof:name":"Shangzhangcun",
    "wof:placetype":"locality"
},
  "geometry": {"coordinates":[119.66248,27.95818],"type":"Point"}
}