{
  "type": "Feature",
  "properties": {
    "gn:admin1_code":"29.0",
    "gn:asciiname":"Luomeicheng",
    "gn:country_code":"CN",
    "gn:dem":1547,
    "gn:feature_class":"P",
    "gn:feature_code":"PPL",
    "gn:name":"Luomeicheng",
    "gn:population":0,
    "gn:timezone":"Asia/Shanghai",
    "iso:country":"CN",
    "name:zho_x_preferred":[
        "\u7f57\u59b9\u57ce"
    ],
    "wof:name":"Luomeicheng",
    "wof:placetype":"locality"
},
  "geometry": {"coordinates":[98.6255,25.3228],"type":"Point"}
}