{
  "type": "Feature",
  "properties": {
    "gn:admin1_code":"32.0",
    "gn:asciiname":"Simianshan",
    "gn:country_code":"CN",
    "gn:dem":327,
    "gn:feature_class":"P",
    "gn:feature_code":"PPL",
    "gn:name":"Simianshan",
    "gn:population":0,
    "gn:timezone":"Asia/Shanghai",
    "iso:country":"CN",
    "name:zho_x_preferred":[
        "\u56db\u9762\u5c71"
    ],
    "wof:name":"Simianshan",
    "wof:placetype":"locality"
},
  "geometry": {"coordinates":[105.1597,28.81175],"type":"Point"}
}