{
  "type": "Feature",
  "properties": {
    "gn:admin1_code":"26.0",
    "gn:asciiname":"Zhonglousi",
    "gn:country_code":"CN",
    "gn:dem":895,
    "gn:feature_class":"P",
    "gn:feature_code":"PPL",
    "gn:name":"Zhonglousi",
    "gn:population":0,
    "gn:timezone":"Asia/Shanghai",
    "iso:country":"CN",
    "name:und_x_variant":[
        "\u949f\u697c\u5bfa"
    ],
    "wof:name":"Zhonglousi",
    "wof:placetype":"locality"
},
  "geometry": {"coordinates":[107.17238999999999,34.43857],"type":"Point"}
}