{
  "type": "Feature",
  "properties": {
    "gn:admin1_code":"9.0",
    "gn:asciiname":"Shunhejie Nancun",
    "gn:country_code":"CN",
    "gn:dem":86,
    "gn:feature_class":"P",
    "gn:feature_code":"PPL",
    "gn:name":"Shunhejie Nancun",
    "gn:population":0,
    "gn:timezone":"Asia/Shanghai",
    "iso:country":"CN",
    "name:zho_x_preferred":[
        "\u987a\u6cb3\u8857\u5357\u6751"
    ],
    "wof:name":"Shunhejie Nancun",
    "wof:placetype":"locality"
},
  "geometry": {"coordinates":[114.26036999999999,34.93074],"type":"Point"}
}