{
  "type": "Feature",
  "properties": {
    "gn:admin1_code":"25.0",
    "gn:asciiname":"Xumeng",
    "gn:cc2":"CN",
    "gn:country_code":"CN",
    "gn:dem":94,
    "gn:feature_class":"P",
    "gn:feature_code":"PPL",
    "gn:name":"Xumeng",
    "gn:population":0,
    "gn:timezone":"Asia/Shanghai",
    "iso:country":"CN",
    "name:und_x_variant":[
        "Hs\u00fc-meng",
        "Xumeng"
    ],
    "wof:name":"Xumeng",
    "wof:placetype":"locality"
},
  "geometry": {"coordinates":[119.32083,35.86222],"type":"Point"}
}