{
  "type": "Feature",
  "properties": {
    "gn:admin1_code":"4.0",
    "gn:asciiname":"Magangcun",
    "gn:country_code":"CN",
    "gn:dem":3,
    "gn:feature_class":"P",
    "gn:feature_code":"PPL",
    "gn:name":"Magangcun",
    "gn:population":0,
    "gn:timezone":"Asia/Shanghai",
    "iso:country":"CN",
    "name:zho_x_preferred":[
        "\u9a6c\u6e2f\u6751"
    ],
    "wof:name":"Magangcun",
    "wof:placetype":"locality"
},
  "geometry": {"coordinates":[120.40649000000001,33.09967],"type":"Point"}
}