{
  "type": "Feature",
  "properties": {
    "gn:admin1_code":"32.0",
    "gn:asciiname":"Houyupu",
    "gn:country_code":"CN",
    "gn:dem":1159,
    "gn:feature_class":"P",
    "gn:feature_code":"PPL",
    "gn:name":"Houyupu",
    "gn:population":0,
    "gn:timezone":"Asia/Shanghai",
    "iso:country":"CN",
    "name:zho_x_preferred":[
        "\u5019\u7389\u666e"
    ],
    "wof:name":"Houyupu",
    "wof:placetype":"locality"
},
  "geometry": {"coordinates":[102.73099999999999,28.9426],"type":"Point"}
}