{
  "type": "Feature",
  "properties": {
    "gn:admin1_code":"30",
    "gn:asciiname":"Zhangdaocun",
    "gn:country_code":"CN",
    "gn:dem":57,
    "gn:feature_class":"P",
    "gn:feature_code":"PPL",
    "gn:name":"Zhangdaocun",
    "gn:population":0,
    "gn:timezone":"Asia/Urumqi",
    "iso:country":"CN",
    "name:zho_x_preferred":[
        "\u7ae0\u9053\u6751"
    ],
    "wof:name":"Zhangdaocun",
    "wof:placetype":"locality"
},
  "geometry": {"coordinates":[110.63981,22.04657000000001],"type":"Point"}
}