{
  "type": "Feature",
  "properties": {
    "gn:admin1_code":"29.0",
    "gn:asciiname":"Zeni",
    "gn:country_code":"CN",
    "gn:dem":1349,
    "gn:feature_class":"P",
    "gn:feature_code":"PPL",
    "gn:name":"Zeni",
    "gn:population":0,
    "gn:timezone":"Asia/Shanghai",
    "iso:country":"CN",
    "name:ita_x_preferred":[
        "Zeni"
    ],
    "name:jpn_x_preferred":[
        "\u92ad"
    ],
    "name:vie_x_preferred":[
        "Ti\u1ec1n"
    ],
    "name:zho_x_preferred":[
        "\u6cfd\u5c3c"
    ],
    "name:zho_x_variant":[
        "\u9322"
    ],
    "wof:name":"Zeni",
    "wof:placetype":"locality"
},
  "geometry": {"coordinates":[102.709,22.8837],"type":"Point"}
}