{
  "type": "Feature",
  "properties": {
    "gn:admin1_code":"30.0",
    "gn:asciiname":"Xingfuxin",
    "gn:country_code":"CN",
    "gn:dem":31,
    "gn:feature_class":"P",
    "gn:feature_code":"PPL",
    "gn:name":"Xingfuxin",
    "gn:population":0,
    "gn:timezone":"Asia/Shanghai",
    "iso:country":"CN",
    "name:zho_x_preferred":[
        "\u5e78\u798f\u65b0"
    ],
    "wof:name":"Xingfuxin",
    "wof:placetype":"locality"
},
  "geometry": {"coordinates":[113.06562,22.58702000000001],"type":"Point"}
}