{
  "type": "Feature",
  "properties": {
    "gn:admin1_code":"7.0",
    "gn:asciiname":"Zhaoshajia",
    "gn:country_code":"CN",
    "gn:dem":275,
    "gn:feature_class":"P",
    "gn:feature_code":"PPL",
    "gn:name":"Zhaoshajia",
    "gn:population":0,
    "gn:timezone":"Asia/Shanghai",
    "iso:country":"CN",
    "name:zho_x_preferred":[
        "\u62db\u6c99\u7532"
    ],
    "wof:name":"Zhaoshajia",
    "wof:placetype":"locality"
},
  "geometry": {"coordinates":[118.68084,27.58331],"type":"Point"}
}