{
  "type": "Feature",
  "properties": {
    "gn:admin1_code":"9.0",
    "gn:asciiname":"Wulishan",
    "gn:country_code":"CN",
    "gn:dem":191,
    "gn:feature_class":"P",
    "gn:feature_code":"PPL",
    "gn:name":"Wulishan",
    "gn:population":0,
    "gn:timezone":"Asia/Shanghai",
    "iso:country":"CN",
    "name:zho_x_preferred":[
        "\u4e94\u91cc\u5c71"
    ],
    "wof:name":"Wulishan",
    "wof:placetype":"locality"
},
  "geometry": {"coordinates":[115.27766,31.46493],"type":"Point"}
}