{
  "type": "Feature",
  "properties": {
    "gn:admin1_code":"30.0",
    "gn:asciiname":"Baigangxin",
    "gn:country_code":"CN",
    "gn:dem":9,
    "gn:feature_class":"P",
    "gn:feature_code":"PPL",
    "gn:name":"Baigangxin",
    "gn:population":0,
    "gn:timezone":"Asia/Shanghai",
    "iso:country":"CN",
    "name:und_x_variant":[
        "Baigangxincun",
        "Baigangxin",
        "\u767d\u5c97\u65b0"
    ],
    "name:zho_x_preferred":[
        "\u767d\u5c97\u65b0\u6751"
    ],
    "wof:name":"Baigangxin",
    "wof:placetype":"locality"
},
  "geometry": {"coordinates":[112.80373,22.15587],"type":"Point"}
}