{
  "type": "Feature",
  "properties": {
    "gn:admin1_code":"32.0",
    "gn:asciiname":"Decha",
    "gn:country_code":"CN",
    "gn:dem":3910,
    "gn:feature_class":"P",
    "gn:feature_code":"PPL",
    "gn:name":"Decha",
    "gn:population":0,
    "gn:timezone":"Asia/Shanghai",
    "iso:country":"CN",
    "name:ceb_x_preferred":[
        "Decha"
    ],
    "name:fra_x_preferred":[
        "Decha"
    ],
    "name:swe_x_preferred":[
        "Decha"
    ],
    "name:zho_x_preferred":[
        "\u5fb7\u5dee"
    ],
    "wof:name":"Decha",
    "wof:placetype":"locality"
},
  "geometry": {"coordinates":[101.34399999999999,29.9551],"type":"Point"}
}