{
  "type": "Feature",
  "properties": {
    "gn:admin1_code":"9.0",
    "gn:asciiname":"Sanlihe",
    "gn:country_code":"CN",
    "gn:dem":135,
    "gn:feature_class":"P",
    "gn:feature_code":"PPL",
    "gn:name":"Sanlihe",
    "gn:population":0,
    "gn:timezone":"Asia/Shanghai",
    "iso:country":"CN",
    "name:und_x_variant":[
        "\u4e09\u91cc\u6cb3"
    ],
    "name:zho_x_preferred":[
        "\u4e09\u91cc\u6cb3"
    ],
    "wof:name":"Sanlihe",
    "wof:placetype":"locality"
},
  "geometry": {"coordinates":[113.24535,33.35683],"type":"Point"}
}