{
  "type": "Feature",
  "properties": {
    "gn:admin1_code":"30.0",
    "gn:asciiname":"Rendie",
    "gn:country_code":"CN",
    "gn:dem":408,
    "gn:feature_class":"P",
    "gn:feature_code":"PPL",
    "gn:name":"Rendie",
    "gn:population":0,
    "gn:timezone":"Asia/Shanghai",
    "iso:country":"CN",
    "name:zho_x_preferred":[
        "Rendie"
    ],
    "name:zho_x_variant":[
        "\u4ec1\u8776"
    ],
    "wof:name":"Rendie",
    "wof:placetype":"locality"
},
  "geometry": {"coordinates":[112.39972,24.66778],"type":"Point"}
}