{
  "type": "Feature",
  "properties": {
    "gn:admin1_code":"32.0",
    "gn:asciiname":"Xunlong",
    "gn:country_code":"CN",
    "gn:dem":401,
    "gn:feature_class":"P",
    "gn:feature_code":"PPL",
    "gn:name":"Xunlong",
    "gn:population":0,
    "gn:timezone":"Asia/Shanghai",
    "iso:country":"CN",
    "name:zho_x_preferred":[
        "\u9a6f\u9f99"
    ],
    "wof:name":"Xunlong",
    "wof:placetype":"locality"
},
  "geometry": {"coordinates":[105.08969999999999,30.0376],"type":"Point"}
}