{
  "type": "Feature",
  "properties": {
    "gn:admin1_code":"15.0",
    "gn:asciiname":"Xiacaochuan",
    "gn:country_code":"CN",
    "gn:dem":2565,
    "gn:feature_class":"P",
    "gn:feature_code":"PPL",
    "gn:name":"Xiacaochuan",
    "gn:population":0,
    "gn:timezone":"Asia/Shanghai",
    "iso:country":"CN",
    "name:zho_x_preferred":[
        "\u4e0b\u8349\u5ddd"
    ],
    "wof:name":"Xiacaochuan",
    "wof:placetype":"locality"
},
  "geometry": {"coordinates":[104.83753,33.65499000000001],"type":"Point"}
}