{
  "type": "Feature",
  "properties": {
    "gn:admin1_code":"11.0",
    "gn:asciiname":"Xieya",
    "gn:country_code":"CN",
    "gn:dem":883,
    "gn:feature_class":"P",
    "gn:feature_code":"PPL",
    "gn:name":"Xieya",
    "gn:population":0,
    "gn:timezone":"Asia/Shanghai",
    "iso:country":"CN",
    "name:zho_x_preferred":[
        "\u4e9b\u57ad"
    ],
    "wof:name":"Xieya",
    "wof:placetype":"locality"
},
  "geometry": {"coordinates":[109.79861,29.57259],"type":"Point"}
}