{
  "type": "Feature",
  "properties": {
    "gn:admin1_code":"8.0",
    "gn:asciiname":"Yanjun Yidui",
    "gn:country_code":"CN",
    "gn:dem":76,
    "gn:feature_class":"P",
    "gn:feature_code":"PPLF",
    "gn:name":"Yanjun Yidui",
    "gn:population":0,
    "gn:timezone":"Asia/Shanghai",
    "iso:country":"CN",
    "name:zho_x_preferred":[
        "\u5ef6\u519b\u4e00\u961f"
    ],
    "wof:name":"Yanjun Yidui",
    "wof:placetype":"locality"
},
  "geometry": {"coordinates":[130.91436999999999,47.64377],"type":"Point"}
}