{
  "type": "Feature",
  "properties": {
    "gn:admin1_code":"8.0",
    "gn:asciiname":"Xiangqian Sandui",
    "gn:country_code":"CN",
    "gn:dem":150,
    "gn:feature_class":"P",
    "gn:feature_code":"PPLF",
    "gn:name":"Xiangqian Sandui",
    "gn:population":0,
    "gn:timezone":"Asia/Shanghai",
    "iso:country":"CN",
    "name:zho_x_preferred":[
        "\u5411\u524d\u4e09\u961f"
    ],
    "wof:name":"Xiangqian Sandui",
    "wof:placetype":"locality"
},
  "geometry": {"coordinates":[124.94711,46.93687],"type":"Point"}
}