{
  "type": "Feature",
  "properties": {
    "gn:admin1_code":"3.0",
    "gn:asciiname":"Magudong",
    "gn:country_code":"CN",
    "gn:dem":309,
    "gn:feature_class":"P",
    "gn:feature_code":"PPL",
    "gn:name":"Magudong",
    "gn:population":0,
    "gn:timezone":"Asia/Shanghai",
    "iso:country":"CN",
    "name:und_x_variant":[
        "\u9a6c\u53e4\u6d1e"
    ],
    "wof:name":"Magudong",
    "wof:placetype":"locality"
},
  "geometry": {"coordinates":[114.87994,24.969],"type":"Point"}
}