{
  "type": "Feature",
  "properties": {
    "gn:admin1_code":"4.0",
    "gn:asciiname":"Yingzhanjing",
    "gn:country_code":"CN",
    "gn:dem":4,
    "gn:feature_class":"P",
    "gn:feature_code":"PPL",
    "gn:name":"Yingzhanjing",
    "gn:population":0,
    "gn:timezone":"Asia/Shanghai",
    "iso:country":"CN",
    "name:zho_x_preferred":[
        "Yingzhanjing"
    ],
    "name:zho_x_variant":[
        "\u8425\u65a9\u6cfe"
    ],
    "wof:name":"Yingzhanjing",
    "wof:placetype":"locality"
},
  "geometry": {"coordinates":[121.39324000000001,31.99563],"type":"Point"}
}