{
  "type": "Feature",
  "properties": {
    "gn:admin1_code":"8.0",
    "gn:asciiname":"Duiqingshancun",
    "gn:country_code":"CN",
    "gn:dem":112,
    "gn:feature_class":"P",
    "gn:feature_code":"PPL",
    "gn:name":"Duiqingshancun",
    "gn:population":0,
    "gn:timezone":"Asia/Shanghai",
    "iso:country":"CN",
    "name:zho_x_preferred":[
        "\u5bf9\u9752\u5c71\u6751"
    ],
    "wof:name":"Duiqingshancun",
    "wof:placetype":"locality"
},
  "geometry": {"coordinates":[129.44311999999999,46.23793],"type":"Point"}
}