{
  "type": "Feature",
  "properties": {
    "gn:admin1_code":"10",
    "gn:asciiname":"Qianyingzi",
    "gn:country_code":"CN",
    "gn:dem":479,
    "gn:feature_class":"P",
    "gn:feature_code":"PPL",
    "gn:name":"Qianyingzi",
    "gn:population":0,
    "gn:timezone":"Asia/Shanghai",
    "iso:country":"CN",
    "name:zho_x_preferred":[
        "\u524d\u8425\u5b50"
    ],
    "wof:name":"Qianyingzi",
    "wof:placetype":"locality"
},
  "geometry": {"coordinates":[119.22083000000001,41.28151],"type":"Point"}
}