{
  "type": "Feature",
  "properties": {
    "gn:admin1_code":"9.0",
    "gn:asciiname":"Quancaiping",
    "gn:country_code":"CN",
    "gn:dem":570,
    "gn:feature_class":"P",
    "gn:feature_code":"PPL",
    "gn:name":"Quancaiping",
    "gn:population":0,
    "gn:timezone":"Asia/Shanghai",
    "iso:country":"CN",
    "name:zho_x_preferred":[
        "\u8343\u83dc\u576a"
    ],
    "wof:name":"Quancaiping",
    "wof:placetype":"locality"
},
  "geometry": {"coordinates":[112.00429,33.50835],"type":"Point"}
}