{
  "type": "Feature",
  "properties": {
    "gn:admin1_code":"1.0",
    "gn:asciiname":"Longtan",
    "gn:country_code":"CN",
    "gn:dem":9,
    "gn:feature_class":"P",
    "gn:feature_code":"PPL",
    "gn:name":"Longtan",
    "gn:population":0,
    "gn:timezone":"Asia/Shanghai",
    "iso:country":"CN",
    "name:ceb_x_preferred":[
        "Longtan"
    ],
    "name:deu_x_preferred":[
        "Longtan"
    ],
    "name:fra_x_preferred":[
        "Longtan"
    ],
    "name:zho_x_preferred":[
        "\u9f99\u6f6d"
    ],
    "wof:name":"Longtan",
    "wof:placetype":"locality"
},
  "geometry": {"coordinates":[118.40646,31.08478],"type":"Point"}
}