{
  "type": "Feature",
  "properties": {
    "gn:admin1_code":"32.0",
    "gn:asciiname":"Shipaolou",
    "gn:country_code":"CN",
    "gn:dem":416,
    "gn:feature_class":"P",
    "gn:feature_code":"PPL",
    "gn:name":"Shipaolou",
    "gn:population":0,
    "gn:timezone":"Asia/Shanghai",
    "iso:country":"CN",
    "name:zho_x_preferred":[
        "\u77f3\u70ae\u697c"
    ],
    "wof:name":"Shipaolou",
    "wof:placetype":"locality"
},
  "geometry": {"coordinates":[104.73099999999999,30.4912],"type":"Point"}
}