{
  "type": "Feature",
  "properties": {
    "gn:admin1_code":"25",
    "gn:asciiname":"Beihuoling",
    "gn:country_code":"CN",
    "gn:dem":57,
    "gn:feature_class":"P",
    "gn:feature_code":"PPL",
    "gn:name":"Beihuoling",
    "gn:population":0,
    "gn:timezone":"Asia/Shanghai",
    "iso:country":"CN",
    "name:zho_x_preferred":[
        "\u5317\u970d\u9675"
    ],
    "wof:name":"Beihuoling",
    "wof:placetype":"locality"
},
  "geometry": {"coordinates":[118.617,36.6939],"type":"Point"}
}