{
  "type": "Feature",
  "properties": {
    "gn:admin1_code":"3.0",
    "gn:asciiname":"Lannikeng",
    "gn:country_code":"CN",
    "gn:dem":878,
    "gn:feature_class":"P",
    "gn:feature_code":"PPL",
    "gn:name":"Lannikeng",
    "gn:population":0,
    "gn:timezone":"Asia/Shanghai",
    "iso:country":"CN",
    "name:und_x_variant":[
        "\u70c2\u6ce5\u5751"
    ],
    "wof:name":"Lannikeng",
    "wof:placetype":"locality"
},
  "geometry": {"coordinates":[115.87358999999999,26.93598],"type":"Point"}
}