{
  "type": "Feature",
  "properties": {
    "gn:admin1_code":"29.0",
    "gn:asciiname":"Shulintou",
    "gn:country_code":"CN",
    "gn:dem":1639,
    "gn:feature_class":"P",
    "gn:feature_code":"PPL",
    "gn:name":"Shulintou",
    "gn:population":0,
    "gn:timezone":"Asia/Shanghai",
    "iso:country":"CN",
    "name:zho_x_preferred":[
        "\u6811\u6797\u5934"
    ],
    "wof:name":"Shulintou",
    "wof:placetype":"locality"
},
  "geometry": {"coordinates":[104.639,25.1198],"type":"Point"}
}