{
  "type": "Feature",
  "properties": {
    "gn:admin1_code":"7",
    "gn:asciiname":"Guodun",
    "gn:country_code":"CN",
    "gn:dem":5,
    "gn:feature_class":"P",
    "gn:feature_code":"PPL",
    "gn:name":"Guodun",
    "gn:population":0,
    "gn:timezone":"Asia/Shanghai",
    "iso:country":"CN",
    "name:und_x_variant":[
        "\u90ed\u58a9"
    ],
    "name:zho_x_preferred":[
        "\u90ed\u58a9"
    ],
    "wof:name":"Guodun",
    "wof:placetype":"locality"
},
  "geometry": {"coordinates":[117.37139000000001,23.935],"type":"Point"}
}