{
  "type": "Feature",
  "properties": {
    "gn:admin1_code":"19.0",
    "gn:asciiname":"Gaowafangcun",
    "gn:country_code":"CN",
    "gn:dem":45,
    "gn:feature_class":"P",
    "gn:feature_code":"PPL",
    "gn:name":"Gaowafangcun",
    "gn:population":0,
    "gn:timezone":"Asia/Shanghai",
    "iso:country":"CN",
    "name:zho_x_preferred":[
        "\u9ad8\u74e6\u623f\u6751"
    ],
    "wof:name":"Gaowafangcun",
    "wof:placetype":"locality"
},
  "geometry": {"coordinates":[122.277,39.6025],"type":"Point"}
}