{
  "type": "Feature",
  "properties": {
    "gn:admin1_code":"3.0",
    "gn:asciiname":"Fenjiwo",
    "gn:country_code":"CN",
    "gn:dem":455,
    "gn:feature_class":"P",
    "gn:feature_code":"PPL",
    "gn:name":"Fenjiwo",
    "gn:population":0,
    "gn:timezone":"Asia/Shanghai",
    "iso:country":"CN",
    "name:und_x_variant":[
        "\u7caa\u7b95\u7a9d"
    ],
    "wof:name":"Fenjiwo",
    "wof:placetype":"locality"
},
  "geometry": {"coordinates":[115.87463,25.33704],"type":"Point"}
}