{
  "type": "Feature",
  "properties": {
    "gn:admin1_code":"25.0",
    "gn:asciiname":"Beichengzi",
    "gn:country_code":"CN",
    "gn:dem":34,
    "gn:feature_class":"P",
    "gn:feature_code":"PPL",
    "gn:name":"Beichengzi",
    "gn:population":0,
    "gn:timezone":"Asia/Shanghai",
    "iso:country":"CN",
    "name:zho_x_preferred":[
        "\u5317\u57ce\u5b50"
    ],
    "wof:name":"Beichengzi",
    "wof:placetype":"locality"
},
  "geometry": {"coordinates":[120.23576,36.71131],"type":"Point"}
}