{
  "type": "Feature",
  "properties": {
    "gn:admin1_code":"32.0",
    "gn:asciiname":"Caijiaba",
    "gn:country_code":"CN",
    "gn:dem":842,
    "gn:feature_class":"P",
    "gn:feature_code":"PPL",
    "gn:name":"Caijiaba",
    "gn:population":0,
    "gn:timezone":"Asia/Shanghai",
    "iso:country":"CN",
    "name:zho_x_preferred":[
        "\u8521\u5bb6\u575d"
    ],
    "wof:name":"Caijiaba",
    "wof:placetype":"locality"
},
  "geometry": {"coordinates":[105.00491,32.17554000000001],"type":"Point"}
}