{
  "type": "Feature",
  "properties": {
    "gn:admin1_code":"32.0",
    "gn:asciiname":"Zhaojia Youfang",
    "gn:country_code":"CN",
    "gn:dem":422,
    "gn:feature_class":"P",
    "gn:feature_code":"PPL",
    "gn:name":"Zhaojia Youfang",
    "gn:population":0,
    "gn:timezone":"Asia/Shanghai",
    "iso:country":"CN",
    "name:zho_x_preferred":[
        "\u8d75\u5bb6\u6cb9\u623f"
    ],
    "wof:name":"Zhaojia Youfang",
    "wof:placetype":"locality"
},
  "geometry": {"coordinates":[104.97008,31.16501],"type":"Point"}
}