{
  "type": "Feature",
  "properties": {
    "gn:admin1_code":"9.0",
    "gn:asciiname":"Daiwa",
    "gn:country_code":"CN",
    "gn:dem":58,
    "gn:feature_class":"P",
    "gn:feature_code":"PPL",
    "gn:name":"Daiwa",
    "gn:population":0,
    "gn:timezone":"Asia/Shanghai",
    "iso:country":"CN",
    "name:vie_x_preferred":[
        "Daiwa"
    ],
    "name:zho_x_preferred":[
        "\u6234\u6d3c"
    ],
    "wof:name":"Daiwa",
    "wof:placetype":"locality"
},
  "geometry": {"coordinates":[114.47328,33.92262],"type":"Point"}
}