{
  "type": "Feature",
  "properties": {
    "gn:admin1_code":"3",
    "gn:asciiname":"Qingcaosheng",
    "gn:country_code":"CN",
    "gn:dem":341,
    "gn:feature_class":"P",
    "gn:feature_code":"PPL",
    "gn:name":"Qingcaosheng",
    "gn:population":0,
    "gn:timezone":"Asia/Shanghai",
    "iso:country":"CN",
    "name:zho_x_preferred":[
        "\u9752\u8349\u5d4a"
    ],
    "wof:name":"Qingcaosheng",
    "wof:placetype":"locality"
},
  "geometry": {"coordinates":[114.16,25.4453],"type":"Point"}
}