{
  "type": "Feature",
  "properties": {
    "gn:admin1_code":"30.0",
    "gn:asciiname":"Heshakeng",
    "gn:country_code":"CN",
    "gn:dem":51,
    "gn:feature_class":"P",
    "gn:feature_code":"PPL",
    "gn:name":"Heshakeng",
    "gn:population":0,
    "gn:timezone":"Asia/Shanghai",
    "iso:country":"CN",
    "name:und_x_variant":[
        "\u79be\u6c99\u5751"
    ],
    "name:zho_x_preferred":[
        "\u79be\u6c99\u5751"
    ],
    "wof:name":"Heshakeng",
    "wof:placetype":"locality"
},
  "geometry": {"coordinates":[114.73583000000001,23.56638],"type":"Point"}
}