{
  "type": "Feature",
  "properties": {
    "gn:admin1_code":"29.0",
    "gn:asciiname":"Yuji",
    "gn:country_code":"CN",
    "gn:dem":1890,
    "gn:feature_class":"P",
    "gn:feature_code":"PPL",
    "gn:name":"Yuji",
    "gn:population":0,
    "gn:timezone":"Asia/Shanghai",
    "iso:country":"CN",
    "name:ind_x_preferred":[
        "Yuji"
    ],
    "name:ita_x_preferred":[
        "Yuji"
    ],
    "name:zho_x_preferred":[
        "\u9c7c\u810a"
    ],
    "wof:name":"Yuji",
    "wof:placetype":"locality"
},
  "geometry": {"coordinates":[103.709,27.5276],"type":"Point"}
}