{
  "type": "Feature",
  "properties": {
    "gn:admin1_code":"29.0",
    "gn:asciiname":"Liangzizhai",
    "gn:country_code":"CN",
    "gn:dem":1942,
    "gn:feature_class":"P",
    "gn:feature_code":"PPL",
    "gn:name":"Liangzizhai",
    "gn:population":0,
    "gn:timezone":"Asia/Shanghai",
    "iso:country":"CN",
    "name:zho_x_preferred":[
        "\u6881\u5b50\u5be8"
    ],
    "wof:name":"Liangzizhai",
    "wof:placetype":"locality"
},
  "geometry": {"coordinates":[99.6818,23.6315],"type":"Point"}
}