{
  "type": "Feature",
  "properties": {
    "gn:admin1_code":"14.0",
    "gn:asciiname":"Nasu",
    "gn:country_code":"CN",
    "gn:dem":4240,
    "gn:feature_class":"P",
    "gn:feature_code":"PPL",
    "gn:name":"Nasu",
    "gn:population":0,
    "gn:timezone":"Asia/Urumqi",
    "iso:country":"CN",
    "name:ceb_x_preferred":[
        "Nasu"
    ],
    "name:ces_x_preferred":[
        "Nasu"
    ],
    "name:deu_x_preferred":[
        "Nasu"
    ],
    "name:ita_x_preferred":[
        "Nasu"
    ],
    "name:jpn_x_preferred":[
        "\u30ca\u30b9"
    ],
    "name:nld_x_preferred":[
        "Nasu"
    ],
    "name:rus_x_preferred":[
        "\u041d\u0430\u0441\u0443"
    ],
    "name:scn_x_preferred":[
        "Nasu"
    ],
    "name:slk_x_preferred":[
        "Nasu"
    ],
    "name:ukr_x_preferred":[
        "\u041d\u0430\u0441\u0443"
    ],
    "name:zho_x_preferred":[
        "\u90a3\u82cf"
    ],
    "wof:name":"Nasu",
    "wof:placetype":"locality"
},
  "geometry": {"coordinates":[85.31059999999999,28.657],"type":"Point"}
}