{
  "type": "Feature",
  "properties": {
    "gn:admin1_code":"14.0",
    "gn:asciiname":"Nasu",
    "gn:country_code":"CN",
    "gn:dem":4240,
    "gn:feature_class":"P",
    "gn:feature_code":"PPL",
    "gn:name":"Nasu",
    "gn:population":0,
    "gn:timezone":"Asia/Urumqi",
    "iso:country":"CN",
    "name:zho_x_preferred":[
        "\u90a3\u82cf"
    ],
    "wof:name":"Nasu",
    "wof:placetype":"locality"
},
  "geometry": {"coordinates":[85.31059999999999,28.657],"type":"Point"}
}