{
  "type": "Feature",
  "properties": {
    "gn:admin1_code":"32.0",
    "gn:asciiname":"Sanwuqiao",
    "gn:country_code":"CN",
    "gn:dem":597,
    "gn:feature_class":"P",
    "gn:feature_code":"PPL",
    "gn:name":"Sanwuqiao",
    "gn:population":0,
    "gn:timezone":"Asia/Shanghai",
    "iso:country":"CN",
    "name:zho_x_preferred":[
        "\u4e09\u5c4b\u6865"
    ],
    "wof:name":"Sanwuqiao",
    "wof:placetype":"locality"
},
  "geometry": {"coordinates":[104.38366000000001,28.59108],"type":"Point"}
}