{
  "type": "Feature",
  "properties": {
    "gn:admin1_code":"16.0",
    "gn:asciiname":"Wuwu Xincun",
    "gn:country_code":"CN",
    "gn:dem":51,
    "gn:feature_class":"P",
    "gn:feature_code":"PPL",
    "gn:name":"Wuwu Xincun",
    "gn:population":0,
    "gn:timezone":"Asia/Shanghai",
    "iso:country":"CN",
    "name:zho_x_preferred":[
        "\u4f0d\u5c4b\u65b0\u6751"
    ],
    "wof:name":"Wuwu Xincun",
    "wof:placetype":"locality"
},
  "geometry": {"coordinates":[109.631,23.0284],"type":"Point"}
}