{
  "type": "Feature",
  "properties": {
    "gn:admin1_code":"10",
    "gn:asciiname":"Xiaohei Laopogou",
    "gn:country_code":"CN",
    "gn:dem":1105,
    "gn:feature_class":"P",
    "gn:feature_code":"PPL",
    "gn:name":"Xiaohei Laopogou",
    "gn:population":0,
    "gn:timezone":"Asia/Shanghai",
    "iso:country":"CN",
    "name:zho_x_preferred":[
        "\u5c0f\u9ed1\u8001\u5a46\u6c9f"
    ],
    "wof:name":"Xiaohei Laopogou",
    "wof:placetype":"locality"
},
  "geometry": {"coordinates":[117.96894,42.03758],"type":"Point"}
}