{
  "type": "Feature",
  "properties": {
    "gn:country":"CN",
    "gn:fcode":"ADM3",
    "gn:pop":0,
    "iso:country":"CN",
    "name:unk_x_variant":[
        "Mei Hsien"
    ],
    "name:zho_x_preferred":[
        "\u6885\u53bf"
    ],
    "qs:name":"Mei Xian",
    "qs:photos_9r":0,
    "qs:photos_sr":0,
    "qs:pop_sr":"0",
    "wd:wordcount":47,
    "wof:name":"Mei Xian",
    "wof:placetype":"localadmin",
    "wof:population":0
},
  "geometry": {"coordinates":[116.02394,24.22413],"type":"Point"}
}