{
  "type": "Feature",
  "properties": {
    "gn:country":"CN",
    "gn:fcode":"ADM3",
    "gn:population":0,
    "iso:country":"CN",
    "name:deu_x_preferred":[
        "Mei"
    ],
    "name:fas_x_preferred":[
        "\u0634\u0647\u0631\u0633\u062a\u0627\u0646 \u0645\u06cc"
    ],
    "name:ind_x_preferred":[
        "Kabupaten Mei"
    ],
    "name:kor_x_preferred":[
        "\uba54\uc774\ud604"
    ],
    "name:nor_x_preferred":[
        "Mei"
    ],
    "name:rus_x_preferred":[
        "\u041c\u044d\u0439\u0441\u044f\u043d\u044c"
    ],
    "name:swe_x_preferred":[
        "Mei"
    ],
    "name:tgl_x_preferred":[
        "Kondado ng Mei"
    ],
    "name:und_x_variant":[
        "Mei Hsien"
    ],
    "name:vie_x_preferred":[
        "My"
    ],
    "name:zho_x_preferred":[
        "\u6885\u53bf"
    ],
    "qs:name":"Mei Xian",
    "qs:photos_9r":0,
    "qs:photos_sr":0,
    "qs:pop_sr":"0",
    "wd:wordcount":47,
    "wof:name":"Mei Xian",
    "wof:placetype":"localadmin",
    "wof:population":0
},
  "geometry": {"coordinates":[116.02394,24.22413],"type":"Point"}
}