{
  "type": "Feature",
  "properties": {
    "gn:admin1_code":"12.0",
    "gn:asciiname":"Xiaojiayan",
    "gn:country_code":"CN",
    "gn:dem":34,
    "gn:feature_class":"P",
    "gn:feature_code":"PPL",
    "gn:name":"Xiaojiayan",
    "gn:population":0,
    "gn:timezone":"Asia/Shanghai",
    "iso:country":"CN",
    "name:und_x_variant":[
        "\u8096\u5bb6\u5830"
    ],
    "wof:name":"Xiaojiayan",
    "wof:placetype":"locality"
},
  "geometry": {"coordinates":[114.8099,30.19992],"type":"Point"}
}