{
  "type": "Feature",
  "properties": {
    "gn:admin1_code":"30",
    "gn:asciiname":"Dengfang",
    "gn:country_code":"CN",
    "gn:dem":181,
    "gn:feature_class":"P",
    "gn:feature_code":"PPLA4",
    "gn:name":"Dengfang",
    "gn:population":0,
    "gn:timezone":"Asia/Shanghai",
    "iso:country":"CN",
    "name:und_x_variant":[
        "Dengfang Zhen",
        "\u9093\u574a\u9547"
    ],
    "name:zho_x_preferred":[
        "\u9093\u574a"
    ],
    "wof:name":"Dengfang",
    "wof:placetype":"locality"
},
  "geometry": {"coordinates":[114.44267000000001,25.26258],"type":"Point"}
}