{
  "type": "Feature",
  "properties": {
    "gn:admin1_code":"22.0",
    "gn:asciiname":"Beiliucun",
    "gn:country_code":"CN",
    "gn:dem":129,
    "gn:feature_class":"P",
    "gn:feature_code":"PPL",
    "gn:name":"Beiliucun",
    "gn:population":0,
    "gn:timezone":"Asia/Shanghai",
    "iso:country":"CN",
    "name:zho_x_preferred":[
        "\u5317\u6d41\u6751"
    ],
    "wof:name":"Beiliucun",
    "wof:placetype":"locality"
},
  "geometry": {"coordinates":[116.06168999999998,40.17049],"type":"Point"}
}