{
  "type": "Feature",
  "properties": {
    "gn:admin1_code":"18.0",
    "gn:asciiname":"Pingdiying",
    "gn:country_code":"CN",
    "gn:dem":520,
    "gn:feature_class":"P",
    "gn:feature_code":"PPL",
    "gn:name":"Pingdiying",
    "gn:population":0,
    "gn:timezone":"Asia/Shanghai",
    "iso:country":"CN",
    "name:zho_x_preferred":[
        "\u5e73\u5730\u8425"
    ],
    "wof:name":"Pingdiying",
    "wof:placetype":"locality"
},
  "geometry": {"coordinates":[108.33199999999999,26.8486],"type":"Point"}
}