{
  "type": "Feature",
  "properties": {
    "gn:admin1_code":"15.0",
    "gn:asciiname":"Chejiagou",
    "gn:country_code":"CN",
    "gn:dem":1000,
    "gn:feature_class":"P",
    "gn:feature_code":"PPL",
    "gn:name":"Chejiagou",
    "gn:population":0,
    "gn:timezone":"Asia/Shanghai",
    "iso:country":"CN",
    "name:zho_x_preferred":[
        "\u8f66\u5bb6\u6c9f"
    ],
    "wof:name":"Chejiagou",
    "wof:placetype":"locality"
},
  "geometry": {"coordinates":[107.961,35.2497],"type":"Point"}
}