{
  "type": "Feature",
  "properties": {
    "gn:admin1_code":"24.0",
    "gn:asciiname":"Hejialing",
    "gn:country_code":"CN",
    "gn:dem":1231,
    "gn:feature_class":"P",
    "gn:feature_code":"PPL",
    "gn:name":"Hejialing",
    "gn:population":0,
    "gn:timezone":"Asia/Shanghai",
    "iso:country":"CN",
    "name:zho_x_preferred":[
        "\u8d3a\u5bb6\u5cad"
    ],
    "wof:name":"Hejialing",
    "wof:placetype":"locality"
},
  "geometry": {"coordinates":[110.97403,38.15386],"type":"Point"}
}