{
  "type": "Feature",
  "properties": {
    "gn:admin1_code":"10.0",
    "gn:asciiname":"Nanjiangshi",
    "gn:country_code":"CN",
    "gn:dem":821,
    "gn:feature_class":"P",
    "gn:feature_code":"PPL",
    "gn:name":"Nanjiangshi",
    "gn:population":0,
    "gn:timezone":"Asia/Shanghai",
    "iso:country":"CN",
    "name:zho_x_preferred":[
        "\u5357\u5c06\u77f3"
    ],
    "wof:name":"Nanjiangshi",
    "wof:placetype":"locality"
},
  "geometry": {"coordinates":[115.3634,39.89513],"type":"Point"}
}