{
  "type": "Feature",
  "properties": {
    "gn:admin1_code":"16.0",
    "gn:asciiname":"Daming",
    "gn:country_code":"CN",
    "gn:dem":110,
    "gn:feature_class":"P",
    "gn:feature_code":"PPL",
    "gn:name":"Daming",
    "gn:population":0,
    "gn:timezone":"Asia/Shanghai",
    "iso:country":"CN",
    "name:ceb_x_preferred":[
        "Daming"
    ],
    "name:ces_x_preferred":[
        "Ta-ming"
    ],
    "name:deu_x_preferred":[
        "Daming"
    ],
    "name:nor_x_preferred":[
        "Daming"
    ],
    "name:swe_x_preferred":[
        "Daming"
    ],
    "name:zho_x_preferred":[
        "\u5927\u660e"
    ],
    "wof:name":"Daming",
    "wof:placetype":"locality"
},
  "geometry": {"coordinates":[109.815,24.6279],"type":"Point"}
}