{
  "type": "Feature",
  "properties": {
    "gn:admin1_code":"6.0",
    "gn:asciiname":"Nabzain",
    "gn:country_code":"CN",
    "gn:dem":3830,
    "gn:feature_class":"P",
    "gn:feature_code":"PPL",
    "gn:name":"Nabzain",
    "gn:population":0,
    "gn:timezone":"Asia/Urumqi",
    "iso:country":"CN",
    "wof:name":"Nabzain",
    "wof:placetype":"locality"
},
  "geometry": {"coordinates":[98.05,38.58333],"type":"Point"}
}