{
  "type": "Feature",
  "properties": {
    "gn:admin1_code":"03",
    "gn:asciiname":"Chengjiang",
    "gn:country_code":"CN",
    "gn:dem":58,
    "gn:feature_class":"P",
    "gn:feature_code":"PPLA3",
    "gn:name":"Chengjiang",
    "gn:population":0,
    "gn:timezone":"Asia/Shanghai",
    "iso:country":"CN",
    "name:und_x_variant":[
        "Taihe",
        "T\u2019ai-ho",
        "T\u2019ai-ho-hsien",
        "T\u2019ai-ho-hsien-ch\u2019eng",
        "Chengjiang",
        "Taihe Xian"
    ],
    "name:zho_x_preferred":[
        "\u6f84\u6c5f"
    ],
    "name:zho_x_variant":[
        "\u6cf0\u548c\u53bf"
    ],
    "wof:name":"Chengjiang",
    "wof:placetype":"locality"
},
  "geometry": {"coordinates":[114.89978000000001,26.80171],"type":"Point"}
}