{
  "type": "Feature",
  "properties": {
    "gn:admin1_code":"29",
    "gn:asciiname":"Shangzhewo",
    "gn:country_code":"CN",
    "gn:dem":2048,
    "gn:feature_class":"P",
    "gn:feature_code":"PPL",
    "gn:name":"Shangzhewo",
    "gn:population":0,
    "gn:timezone":"Asia/Shanghai",
    "iso:country":"CN",
    "name:zho_x_preferred":[
        "\u4e0a\u8005\u7a9d"
    ],
    "wof:name":"Shangzhewo",
    "wof:placetype":"locality"
},
  "geometry": {"coordinates":[101.825,24.5429],"type":"Point"}
}