{
  "type": "Feature",
  "properties": {
    "gn:admin1_code":"14.0",
    "gn:asciiname":"Baitangcun",
    "gn:country_code":"CN",
    "gn:dem":4168,
    "gn:feature_class":"P",
    "gn:feature_code":"PPL",
    "gn:name":"Baitangcun",
    "gn:population":0,
    "gn:timezone":"Asia/Urumqi",
    "iso:country":"CN",
    "name:zho_x_preferred":[
        "\u767d\u5858\u6751"
    ],
    "wof:name":"Baitangcun",
    "wof:placetype":"locality"
},
  "geometry": {"coordinates":[93.53294,32.11883],"type":"Point"}
}