{
  "type": "Feature",
  "properties": {
    "gn:admin1_code":"7.0",
    "gn:asciiname":"Cunhou",
    "gn:country_code":"CN",
    "gn:dem":257,
    "gn:feature_class":"P",
    "gn:feature_code":"PPL",
    "gn:name":"Cunhou",
    "gn:population":0,
    "gn:timezone":"Asia/Shanghai",
    "iso:country":"CN",
    "name:zho_x_preferred":[
        "\u6751\u540e"
    ],
    "wof:name":"Cunhou",
    "wof:placetype":"locality"
},
  "geometry": {"coordinates":[118.91437000000001,26.42136],"type":"Point"}
}