{
  "type": "Feature",
  "properties": {
    "gn:admin1_code":"12.0",
    "gn:asciiname":"Lianhuadi",
    "gn:country_code":"CN",
    "gn:dem":104,
    "gn:feature_class":"P",
    "gn:feature_code":"PPL",
    "gn:name":"Lianhuadi",
    "gn:population":0,
    "gn:timezone":"Asia/Shanghai",
    "iso:country":"CN",
    "name:zho_x_preferred":[
        "Lianhuadi"
    ],
    "name:zho_x_variant":[
        "\u83b2\u82b1\u5730"
    ],
    "wof:name":"Lianhuadi",
    "wof:placetype":"locality"
},
  "geometry": {"coordinates":[115.46468,30.82244],"type":"Point"}
}