{
  "type": "Feature",
  "properties": {
    "gn:admin1_code":"16.0",
    "gn:asciiname":"Ping'an",
    "gn:country_code":"CN",
    "gn:dem":1057,
    "gn:feature_class":"P",
    "gn:feature_code":"PPL",
    "gn:name":"Ping\u2019an",
    "gn:population":0,
    "gn:timezone":"Asia/Shanghai",
    "iso:country":"CN",
    "name:und_x_variant":[
        "Ping\u2019an"
    ],
    "name:zho_x_preferred":[
        "\u5e73\u5b89"
    ],
    "wof:name":"Ping'an",
    "wof:placetype":"locality"
},
  "geometry": {"coordinates":[105.12,24.7095],"type":"Point"}
}