{
  "type": "Feature",
  "properties": {
    "gn:admin1_code":"3.0",
    "gn:asciiname":"Qiutian",
    "gn:country_code":"CN",
    "gn:dem":44,
    "gn:feature_class":"P",
    "gn:feature_code":"PPL",
    "gn:name":"Qiutian",
    "gn:population":0,
    "gn:timezone":"Asia/Shanghai",
    "iso:country":"CN",
    "name:und_x_variant":[
        "\u79cb\u7530"
    ],
    "wof:name":"Qiutian",
    "wof:placetype":"locality"
},
  "geometry": {"coordinates":[115.14278,27.52961],"type":"Point"}
}