{
  "type": "Feature",
  "properties": {
    "gn:admin1_code":"16.0",
    "gn:asciiname":"Jiemutang",
    "gn:country_code":"CN",
    "gn:dem":181,
    "gn:feature_class":"P",
    "gn:feature_code":"PPL",
    "gn:name":"Jiemutang",
    "gn:population":0,
    "gn:timezone":"Asia/Shanghai",
    "iso:country":"CN",
    "name:zho_x_preferred":[
        "\u754c\u6728\u5858"
    ],
    "wof:name":"Jiemutang",
    "wof:placetype":"locality"
},
  "geometry": {"coordinates":[110.825,24.7176],"type":"Point"}
}