{
  "type": "Feature",
  "properties": {
    "gn:admin1_code":"15.0",
    "gn:asciiname":"Zhouyuan",
    "gn:country_code":"CN",
    "gn:dem":1546,
    "gn:feature_class":"P",
    "gn:feature_code":"PPL",
    "gn:name":"Zhouyuan",
    "gn:population":0,
    "gn:timezone":"Asia/Shanghai",
    "iso:country":"CN",
    "name:und_x_variant":[
        "\u5468\u586c"
    ],
    "wof:name":"Zhouyuan",
    "wof:placetype":"locality"
},
  "geometry": {"coordinates":[107.20990999999999,36.5832],"type":"Point"}
}