{
  "type": "Feature",
  "properties": {
    "gn:admin1_code":"4.0",
    "gn:asciiname":"Zhouzhuang",
    "gn:country_code":"CN",
    "gn:dem":0,
    "gn:feature_class":"P",
    "gn:feature_code":"PPL",
    "gn:name":"Zhouzhuang",
    "gn:population":0,
    "gn:timezone":"Asia/Shanghai",
    "iso:country":"CN",
    "name:zho_x_preferred":[
        "\u5468\u5e84"
    ],
    "wof:name":"Zhouzhuang",
    "wof:placetype":"locality"
},
  "geometry": {"coordinates":[119.80114,33.66485],"type":"Point"}
}