{
  "type": "Feature",
  "properties": {
    "gn:admin1_code":"4.0",
    "gn:asciiname":"Liuqiaocun",
    "gn:country_code":"CN",
    "gn:dem":44,
    "gn:feature_class":"P",
    "gn:feature_code":"PPL",
    "gn:name":"Liuqiaocun",
    "gn:population":0,
    "gn:timezone":"Asia/Shanghai",
    "iso:country":"CN",
    "name:zho_x_preferred":[
        "\u516d\u6865\u6751"
    ],
    "wof:name":"Liuqiaocun",
    "wof:placetype":"locality"
},
  "geometry": {"coordinates":[118.51788000000001,32.88153],"type":"Point"}
}