{
  "type": "Feature",
  "properties": {
    "gn:admin1_code":"24",
    "gn:asciiname":"Huanghuatan",
    "gn:country_code":"CN",
    "gn:dem":1588,
    "gn:feature_class":"P",
    "gn:feature_code":"PPLA4",
    "gn:name":"Huanghuatan",
    "gn:population":0,
    "gn:timezone":"Asia/Shanghai",
    "iso:country":"CN",
    "name:und_x_variant":[
        "\u9ec4\u82b1\u6ee9",
        "Huanghuatan Xiang",
        "\u9ec4\u82b1\u6ee9\u4e61"
    ],
    "wof:name":"Huanghuatan",
    "wof:placetype":"locality"
},
  "geometry": {"coordinates":[113.84193999999999,39.65361],"type":"Point"}
}