{
  "type": "Feature",
  "properties": {
    "gn:admin1_code":"19.0",
    "gn:asciiname":"Zhangjia Wazi",
    "gn:country_code":"CN",
    "gn:dem":140,
    "gn:feature_class":"P",
    "gn:feature_code":"PPL",
    "gn:name":"Zhangjia Wazi",
    "gn:population":0,
    "gn:timezone":"Asia/Shanghai",
    "iso:country":"CN",
    "name:zho_x_preferred":[
        "\u5f20\u5bb6\u6d3c\u5b50"
    ],
    "wof:name":"Zhangjia Wazi",
    "wof:placetype":"locality"
},
  "geometry": {"coordinates":[121.97499999999999,41.9798],"type":"Point"}
}