{
  "type": "Feature",
  "properties": {
    "gn:admin1_code":"29.0",
    "gn:asciiname":"Qingmen",
    "gn:country_code":"CN",
    "gn:dem":2542,
    "gn:feature_class":"P",
    "gn:feature_code":"PPL",
    "gn:name":"Qingmen",
    "gn:population":0,
    "gn:timezone":"Asia/Shanghai",
    "iso:country":"CN",
    "name:und_x_variant":[
        "\u7b90\u95e8"
    ],
    "wof:name":"Qingmen",
    "wof:placetype":"locality"
},
  "geometry": {"coordinates":[103.31573,26.12619],"type":"Point"}
}