{
  "type": "Feature",
  "properties": {
    "gn:admin1_code":"02",
    "gn:asciiname":"Yanjiaoshan",
    "gn:country_code":"CN",
    "gn:dem":263,
    "gn:feature_class":"P",
    "gn:feature_code":"PPL",
    "gn:name":"Yanjiaoshan",
    "gn:population":0,
    "gn:timezone":"Asia/Shanghai",
    "iso:country":"CN",
    "name:zho_x_preferred":[
        "\u5ca9\u89d2\u5c71"
    ],
    "wof:name":"Yanjiaoshan",
    "wof:placetype":"locality"
},
  "geometry": {"coordinates":[120.4855,28.01825],"type":"Point"}
}