{
  "type": "Feature",
  "properties": {
    "gn:admin1_code":"24.0",
    "gn:asciiname":"Yannicun",
    "gn:country_code":"CN",
    "gn:dem":927,
    "gn:feature_class":"P",
    "gn:feature_code":"PPL",
    "gn:name":"Yannicun",
    "gn:population":0,
    "gn:timezone":"Asia/Shanghai",
    "iso:country":"CN",
    "name:zho_x_preferred":[
        "\u7814\u6ce5\u6751"
    ],
    "wof:name":"Yannicun",
    "wof:placetype":"locality"
},
  "geometry": {"coordinates":[112.63733000000001,37.3686],"type":"Point"}
}