{
  "type": "Feature",
  "properties": {
    "gn:admin1_code":"07",
    "gn:asciiname":"Xiayuantian",
    "gn:country_code":"CN",
    "gn:dem":253,
    "gn:feature_class":"P",
    "gn:feature_code":"PPL",
    "gn:name":"Xiayuantian",
    "gn:population":0,
    "gn:timezone":"Asia/Shanghai",
    "iso:country":"CN",
    "name:zho_x_preferred":[
        "\u4e0b\u56ed\u7530"
    ],
    "name:zho_x_variant":[
        "\u4e0b\u5706\u7530"
    ],
    "wof:name":"Xiayuantian",
    "wof:placetype":"locality"
},
  "geometry": {"coordinates":[116.12997,24.90441],"type":"Point"}
}