{
  "type": "Feature",
  "properties": {
    "gn:admin1_code":"3",
    "gn:asciiname":"Tianxianglu",
    "gn:country_code":"CN",
    "gn:dem":173,
    "gn:feature_class":"P",
    "gn:feature_code":"PPL",
    "gn:name":"Tianxianglu",
    "gn:population":0,
    "gn:timezone":"Asia/Shanghai",
    "iso:country":"CN",
    "name:zho_x_preferred":[
        "\u5929\u9999\u7089"
    ],
    "wof:name":"Tianxianglu",
    "wof:placetype":"locality"
},
  "geometry": {"coordinates":[114.64700000000001,25.5701],"type":"Point"}
}