{
  "type": "Feature",
  "properties": {
    "gn:admin1_code":"26.0",
    "gn:asciiname":"Dianzigou",
    "gn:country_code":"CN",
    "gn:dem":596,
    "gn:feature_class":"P",
    "gn:feature_code":"PPL",
    "gn:name":"Dianzigou",
    "gn:population":0,
    "gn:timezone":"Asia/Shanghai",
    "iso:country":"CN",
    "name:und_x_variant":[
        "\u5e97\u5b50\u6c9f"
    ],
    "wof:name":"Dianzigou",
    "wof:placetype":"locality"
},
  "geometry": {"coordinates":[107.71681,33.23524],"type":"Point"}
}