{
  "type": "Feature",
  "properties": {
    "gn:admin1_code":"16.0",
    "gn:asciiname":"Weilao",
    "gn:country_code":"CN",
    "gn:dem":1215,
    "gn:feature_class":"P",
    "gn:feature_code":"PPL",
    "gn:name":"Weilao",
    "gn:population":0,
    "gn:timezone":"Asia/Shanghai",
    "iso:country":"CN",
    "name:zho_x_preferred":[
        "\u4f1f\u8001"
    ],
    "wof:name":"Weilao",
    "wof:placetype":"locality"
},
  "geometry": {"coordinates":[105.30200000000001,24.7137],"type":"Point"}
}