{
  "type": "Feature",
  "properties": {
    "gn:admin1_code":"11.0",
    "gn:asciiname":"Muzixi",
    "gn:country_code":"CN",
    "gn:dem":200,
    "gn:feature_class":"P",
    "gn:feature_code":"PPL",
    "gn:name":"Muzixi",
    "gn:population":0,
    "gn:timezone":"Asia/Shanghai",
    "iso:country":"CN",
    "name:zho_x_preferred":[
        "\u6728\u5b50\u6eaa"
    ],
    "wof:name":"Muzixi",
    "wof:placetype":"locality"
},
  "geometry": {"coordinates":[109.63567999999999,27.90146],"type":"Point"}
}