{
  "type": "Feature",
  "properties": {
    "gn:admin1_code":"8.0",
    "gn:asciiname":"Dougouzi",
    "gn:country_code":"CN",
    "gn:dem":262,
    "gn:feature_class":"P",
    "gn:feature_code":"PPL",
    "gn:name":"Dougouzi",
    "gn:population":0,
    "gn:timezone":"Asia/Shanghai",
    "iso:country":"CN",
    "name:zho_x_preferred":[
        "\u6597\u6c9f\u5b50"
    ],
    "wof:name":"Dougouzi",
    "wof:placetype":"locality"
},
  "geometry": {"coordinates":[129.52090000000001,44.33321],"type":"Point"}
}