{
  "type": "Feature",
  "properties": {
    "gn:admin1_code":"12.0",
    "gn:asciiname":"Luojia Tiankeng",
    "gn:country_code":"CN",
    "gn:dem":194,
    "gn:feature_class":"P",
    "gn:feature_code":"PPL",
    "gn:name":"Luojia Tiankeng",
    "gn:population":0,
    "gn:timezone":"Asia/Shanghai",
    "iso:country":"CN",
    "name:zho_x_preferred":[
        "Luojia Tiankeng"
    ],
    "name:zho_x_variant":[
        "\u7f57\u5bb6\u5929\u5751"
    ],
    "wof:name":"Luojia Tiankeng",
    "wof:placetype":"locality"
},
  "geometry": {"coordinates":[111.53901,30.2009],"type":"Point"}
}