{
  "type": "Feature",
  "properties": {
    "gn:admin1_code":"32.0",
    "gn:asciiname":"Heiyuanzi",
    "gn:country_code":"CN",
    "gn:dem":456,
    "gn:feature_class":"P",
    "gn:feature_code":"PPL",
    "gn:name":"Heiyuanzi",
    "gn:population":0,
    "gn:timezone":"Asia/Shanghai",
    "iso:country":"CN",
    "name:zho_x_preferred":[
        "\u9ed1\u9662\u5b50"
    ],
    "wof:name":"Heiyuanzi",
    "wof:placetype":"locality"
},
  "geometry": {"coordinates":[103.65000000000001,30.0859],"type":"Point"}
}