{
  "type": "Feature",
  "properties": {
    "gn:admin1_code":"20.0",
    "gn:asciiname":"Gouzhangzi",
    "gn:country_code":"CN",
    "gn:dem":1846,
    "gn:feature_class":"P",
    "gn:feature_code":"PPL",
    "gn:name":"Gouzhangzi",
    "gn:population":0,
    "gn:timezone":"Asia/Shanghai",
    "iso:country":"CN",
    "name:und_x_variant":[
        "\u6c9f\u638c\u5b50"
    ],
    "wof:name":"Gouzhangzi",
    "wof:placetype":"locality"
},
  "geometry": {"coordinates":[112.25867,41.32754],"type":"Point"}
}