{
  "type": "Feature",
  "properties": {
    "gn:admin1_code":"7",
    "gn:asciiname":"Yeshou",
    "gn:country_code":"CN",
    "gn:dem":991,
    "gn:feature_class":"P",
    "gn:feature_code":"PPL",
    "gn:name":"Yeshou",
    "gn:population":0,
    "gn:timezone":"Asia/Shanghai",
    "iso:country":"CN",
    "name:und_x_variant":[
        "\u53f6\u9996",
        "Yeshou"
    ],
    "wof:name":"Yeshou",
    "wof:placetype":"locality"
},
  "geometry": {"coordinates":[119.79467,27.19638],"type":"Point"}
}