{
  "type": "Feature",
  "properties": {
    "gn:admin1_code":"25",
    "gn:asciiname":"Xixiaoyou",
    "gn:country_code":"CN",
    "gn:dem":76,
    "gn:feature_class":"P",
    "gn:feature_code":"PPL",
    "gn:name":"Xixiaoyou",
    "gn:population":0,
    "gn:timezone":"Asia/Shanghai",
    "iso:country":"CN",
    "name:zho_x_preferred":[
        "\u897f\u5b5d\u53cb"
    ],
    "wof:name":"Xixiaoyou",
    "wof:placetype":"locality"
},
  "geometry": {"coordinates":[118.39400000000001,35.1924],"type":"Point"}
}