{
  "type": "Feature",
  "properties": {
    "gn:admin1_code":"26",
    "gn:asciiname":"Liujia",
    "gn:country_code":"CN",
    "gn:dem":482,
    "gn:feature_class":"P",
    "gn:feature_code":"PPL",
    "gn:name":"Liujia",
    "gn:population":0,
    "gn:timezone":"Asia/Shanghai",
    "iso:country":"CN",
    "name:ceb_x_preferred":[
        "Liujia"
    ],
    "name:deu_x_preferred":[
        "Liujia"
    ],
    "name:swe_x_preferred":[
        "Liujia"
    ],
    "name:und_x_variant":[
        "\u5218\u5bb6"
    ],
    "name:zho_x_preferred":[
        "\u5218\u5bb6"
    ],
    "wof:name":"Liujia",
    "wof:placetype":"locality"
},
  "geometry": {"coordinates":[108.51278000000001,34.32639],"type":"Point"}
}