{
  "type": "Feature",
  "properties": {
    "gn:admin1_code":"25",
    "gn:asciiname":"Guoshuikeng",
    "gn:country_code":"CN",
    "gn:dem":53,
    "gn:feature_class":"P",
    "gn:feature_code":"PPL",
    "gn:name":"Guoshuikeng",
    "gn:population":0,
    "gn:timezone":"Asia/Shanghai",
    "iso:country":"CN",
    "name:zho_x_preferred":[
        "\u90ed\u6c34\u5751"
    ],
    "wof:name":"Guoshuikeng",
    "wof:placetype":"locality"
},
  "geometry": {"coordinates":[115.63200000000001,35.3947],"type":"Point"}
}