{
  "type": "Feature",
  "properties": {
    "gn:admin1_code":"18.0",
    "gn:asciiname":"Xiaodiyan",
    "gn:country_code":"CN",
    "gn:dem":628,
    "gn:feature_class":"P",
    "gn:feature_code":"PPL",
    "gn:name":"Xiaodiyan",
    "gn:population":0,
    "gn:timezone":"Asia/Shanghai",
    "iso:country":"CN",
    "name:zho_x_preferred":[
        "\u5c0f\u5730\u773c"
    ],
    "wof:name":"Xiaodiyan",
    "wof:placetype":"locality"
},
  "geometry": {"coordinates":[109.18600000000001,28.3893],"type":"Point"}
}