{
  "type": "Feature",
  "properties": {
    "gn:admin1_code":"26.0",
    "gn:asciiname":"Wangzhuangcun",
    "gn:country_code":"CN",
    "gn:dem":661,
    "gn:feature_class":"P",
    "gn:feature_code":"PPL",
    "gn:name":"Wangzhuangcun",
    "gn:population":0,
    "gn:timezone":"Asia/Shanghai",
    "iso:country":"CN",
    "name:und_x_variant":[
        "\u738b\u5e84\u6751"
    ],
    "wof:name":"Wangzhuangcun",
    "wof:placetype":"locality"
},
  "geometry": {"coordinates":[107.60572999999999,33.31547],"type":"Point"}
}