{
  "type": "Feature",
  "properties": {
    "gn:admin1_code":"7",
    "gn:asciiname":"Qitouding",
    "gn:country_code":"CN",
    "gn:dem":635,
    "gn:feature_class":"P",
    "gn:feature_code":"PPL",
    "gn:name":"Qitouding",
    "gn:population":0,
    "gn:timezone":"Asia/Shanghai",
    "iso:country":"CN",
    "name:zho_x_preferred":[
        "\u5c90\u5934\u9876"
    ],
    "wof:name":"Qitouding",
    "wof:placetype":"locality"
},
  "geometry": {"coordinates":[119.03994,25.81276],"type":"Point"}
}