{
  "type": "Feature",
  "properties": {
    "gn:admin1_code":"33.0",
    "gn:asciiname":"Xiadongqiao",
    "gn:country_code":"CN",
    "gn:dem":686,
    "gn:feature_class":"P",
    "gn:feature_code":"PPL",
    "gn:name":"Xiadongqiao",
    "gn:population":0,
    "gn:timezone":"Asia/Shanghai",
    "iso:country":"CN",
    "name:zho_x_preferred":[
        "\u4e0b\u6d1e\u6865"
    ],
    "wof:name":"Xiadongqiao",
    "wof:placetype":"locality"
},
  "geometry": {"coordinates":[109.82416000000001,31.1557],"type":"Point"}
}