{
  "type": "Feature",
  "properties": {
    "gn:admin1_code":"11",
    "gn:asciiname":"Hezhailing",
    "gn:country_code":"CN",
    "gn:dem":257,
    "gn:feature_class":"P",
    "gn:feature_code":"PPL",
    "gn:name":"Hezhailing",
    "gn:population":0,
    "gn:timezone":"Asia/Shanghai",
    "iso:country":"CN",
    "name:und_x_variant":[
        "\u8d3a\u5be8\u5cad",
        "Hezhailing"
    ],
    "wof:name":"Hezhailing",
    "wof:placetype":"locality"
},
  "geometry": {"coordinates":[112.28278,26.00889],"type":"Point"}
}