{
  "type": "Feature",
  "properties": {
    "gn:admin1_code":"29.0",
    "gn:asciiname":"Dazhongshan",
    "gn:country_code":"CN",
    "gn:dem":1794,
    "gn:feature_class":"P",
    "gn:feature_code":"PPL",
    "gn:name":"Dazhongshan",
    "gn:population":0,
    "gn:timezone":"Asia/Shanghai",
    "iso:country":"CN",
    "name:zho_x_preferred":[
        "\u5927\u5fe0\u5c71"
    ],
    "wof:name":"Dazhongshan",
    "wof:placetype":"locality"
},
  "geometry": {"coordinates":[99.8348,23.7169],"type":"Point"}
}