{
  "type": "Feature",
  "properties": {
    "gn:admin1_code":"11.0",
    "gn:asciiname":"Shijiafu",
    "gn:country_code":"CN",
    "gn:dem":418,
    "gn:feature_class":"P",
    "gn:feature_code":"PPL",
    "gn:name":"Shijiafu",
    "gn:population":0,
    "gn:timezone":"Asia/Shanghai",
    "iso:country":"CN",
    "name:zho_x_preferred":[
        "Shijiafu"
    ],
    "name:zho_x_variant":[
        "\u5341\u5bb6\u7b26"
    ],
    "wof:name":"Shijiafu",
    "wof:placetype":"locality"
},
  "geometry": {"coordinates":[110.62615,28.93088],"type":"Point"}
}