{
  "type": "Feature",
  "properties": {
    "gn:admin1_code":"29.0",
    "gn:asciiname":"Chaozhizhai",
    "gn:country_code":"CN",
    "gn:dem":1685,
    "gn:feature_class":"P",
    "gn:feature_code":"PPL",
    "gn:name":"Chaozhizhai",
    "gn:population":0,
    "gn:timezone":"Asia/Shanghai",
    "iso:country":"CN",
    "name:zho_x_preferred":[
        "\u6284\u7eb8\u5be8"
    ],
    "wof:name":"Chaozhizhai",
    "wof:placetype":"locality"
},
  "geometry": {"coordinates":[99.575,24.7097],"type":"Point"}
}