{
  "type": "Feature",
  "properties": {
    "gn:admin1_code":"3.0",
    "gn:asciiname":"Xiangjiazui",
    "gn:country_code":"CN",
    "gn:dem":22,
    "gn:feature_class":"P",
    "gn:feature_code":"PPL",
    "gn:name":"Xiangjiazui",
    "gn:population":0,
    "gn:timezone":"Asia/Shanghai",
    "iso:country":"CN",
    "name:und_x_variant":[
        "\u5411\u5bb6\u5480"
    ],
    "wof:name":"Xiangjiazui",
    "wof:placetype":"locality"
},
  "geometry": {"coordinates":[116.29080999999999,29.45122000000001],"type":"Point"}
}