{
  "type": "Feature",
  "properties": {
    "gn:admin1_code":"2.0",
    "gn:asciiname":"Yulin",
    "gn:country_code":"CN",
    "gn:dem":94,
    "gn:feature_class":"P",
    "gn:feature_code":"PPL",
    "gn:name":"Yulin",
    "gn:population":0,
    "gn:timezone":"Asia/Shanghai",
    "iso:country":"CN",
    "name:zho_x_preferred":[
        "\u6986\u6797"
    ],
    "wof:name":"Yulin",
    "wof:placetype":"locality"
},
  "geometry": {"coordinates":[121.23233,29.60074],"type":"Point"}
}