{
  "type": "Feature",
  "properties": {
    "gn:admin1_code":"10",
    "gn:asciiname":"Xinbao'an",
    "gn:country_code":"CN",
    "gn:dem":503,
    "gn:feature_class":"P",
    "gn:feature_code":"PPL",
    "gn:name":"Xinbao\u2019an",
    "gn:population":0,
    "gn:timezone":"Asia/Shanghai",
    "iso:country":"CN",
    "name:und_x_variant":[
        "Hsin-pao-an",
        "Hsin-an-pao",
        "Xinbao\u2019an"
    ],
    "wof:name":"Xinbao'an",
    "wof:placetype":"locality"
},
  "geometry": {"coordinates":[115.40528,40.43167],"type":"Point"}
}