{
  "type": "Feature",
  "properties": {
    "gn:admin1_code":"8.0",
    "gn:asciiname":"Bayiwuliuerbudui Nongchang Sanlian",
    "gn:country_code":"CN",
    "gn:dem":348,
    "gn:feature_class":"P",
    "gn:feature_code":"PPLF",
    "gn:name":"Bayiwuliuerbudui Nongchang Sanlian",
    "gn:population":0,
    "gn:timezone":"Asia/Shanghai",
    "iso:country":"CN",
    "name:zho_x_preferred":[
        "\u516b\u4e00\u4e94\u516d\u4e8c\u90e8\u961f\u519c\u573a\u4e09\u8fde"
    ],
    "wof:name":"Bayiwuliuerbudui Nongchang Sanlian",
    "wof:placetype":"locality"
},
  "geometry": {"coordinates":[127.25054,48.12631],"type":"Point"}
}