{
  "type": "Feature",
  "properties": {
    "gn:admin1_code":"2.0",
    "gn:asciiname":"Xibianjin",
    "gn:country_code":"CN",
    "gn:dem":51,
    "gn:feature_class":"P",
    "gn:feature_code":"PPL",
    "gn:name":"Xibianjin",
    "gn:population":0,
    "gn:timezone":"Asia/Shanghai",
    "iso:country":"CN",
    "name:zho_x_preferred":[
        "\u6eaa\u8fb9\u91d1"
    ],
    "wof:name":"Xibianjin",
    "wof:placetype":"locality"
},
  "geometry": {"coordinates":[119.85832000000001,29.15083],"type":"Point"}
}