{
  "type": "Feature",
  "properties": {
    "gn:admin1_code":"30",
    "gn:asciiname":"Yangjia",
    "gn:country_code":"CN",
    "gn:dem":16,
    "gn:feature_class":"P",
    "gn:feature_code":"PPLA4",
    "gn:name":"Yangjia",
    "gn:population":0,
    "gn:timezone":"Asia/Urumqi",
    "iso:country":"CN",
    "name:und_x_variant":[
        "Yangjia Zhen",
        "\u6768\u5bb6\u9547"
    ],
    "name:zho_x_preferred":[
        "\u6768\u5bb6"
    ],
    "wof:name":"Yangjia",
    "wof:placetype":"locality"
},
  "geometry": {"coordinates":[109.96031000000001,20.89802],"type":"Point"}
}