{
  "type": "Feature",
  "properties": {
    "gn:admin1_code":"5.0",
    "gn:asciiname":"Liudingshancun",
    "gn:country_code":"CN",
    "gn:dem":503,
    "gn:feature_class":"P",
    "gn:feature_code":"PPL",
    "gn:name":"Liudingshancun",
    "gn:population":0,
    "gn:timezone":"Asia/Shanghai",
    "iso:country":"CN",
    "name:zho_x_preferred":[
        "\u516d\u9876\u5c71\u6751"
    ],
    "wof:name":"Liudingshancun",
    "wof:placetype":"locality"
},
  "geometry": {"coordinates":[128.21860000000001,43.32656],"type":"Point"}
}