{
  "type": "Feature",
  "properties": {
    "gn:admin1_code":"33",
    "gn:asciiname":"Gaoyang",
    "gn:country_code":"CN",
    "gn:dem":210,
    "gn:feature_class":"P",
    "gn:feature_code":"PPLA4",
    "gn:name":"Gaoyang",
    "gn:population":0,
    "gn:timezone":"Asia/Shanghai",
    "iso:country":"CN",
    "name:ceb_x_preferred":[
        "Gaoyang"
    ],
    "name:deu_x_preferred":[
        "Gaoyang"
    ],
    "name:fra_x_preferred":[
        "Gaoyang"
    ],
    "name:nor_x_preferred":[
        "Gaoyang"
    ],
    "name:und_x_variant":[
        "Gaoyang Zhen"
    ],
    "name:zho_x_preferred":[
        "\u9ad8\u9633"
    ],
    "name:zho_x_variant":[
        "\u9ad8\u9633\u9547"
    ],
    "wof:name":"Gaoyang",
    "wof:placetype":"locality"
},
  "geometry": {"coordinates":[108.67912,31.09939],"type":"Point"}
}