{
  "type": "Feature",
  "properties": {
    "gn:admin1_code":"01",
    "gn:asciiname":"Longgang",
    "gn:country_code":"CN",
    "gn:dem":12,
    "gn:feature_class":"P",
    "gn:feature_code":"PPL",
    "gn:name":"Longgang",
    "gn:population":0,
    "gn:timezone":"Asia/Shanghai",
    "iso:country":"CN",
    "name:ceb_x_preferred":[
        "Longgang"
    ],
    "name:deu_x_preferred":[
        "Longgang"
    ],
    "name:fra_x_preferred":[
        "Longgang"
    ],
    "name:kor_x_preferred":[
        "\ub8fd\uac15\uad6c"
    ],
    "name:mlg_x_preferred":[
        "Longgang"
    ],
    "name:nor_x_preferred":[
        "Longgang"
    ],
    "name:pol_x_preferred":[
        "Longgang"
    ],
    "name:und_x_variant":[
        "Lung-kang",
        "Lung-kang-chen",
        "Longgang"
    ],
    "name:zho_x_preferred":[
        "\u9f99\u5c97"
    ],
    "wof:name":"Longgang",
    "wof:placetype":"locality"
},
  "geometry": {"coordinates":[119.04489,32.88272],"type":"Point"}
}