{
  "type": "Feature",
  "properties": {
    "gn:admin1_code":"19.0",
    "gn:asciiname":"Nanguancun",
    "gn:country_code":"CN",
    "gn:dem":77,
    "gn:feature_class":"P",
    "gn:feature_code":"PPL",
    "gn:name":"Nanguancun",
    "gn:population":0,
    "gn:timezone":"Asia/Shanghai",
    "iso:country":"CN",
    "name:zho_x_preferred":[
        "\u5357\u5173\u6751"
    ],
    "wof:name":"Nanguancun",
    "wof:placetype":"locality"
},
  "geometry": {"coordinates":[124.06682000000001,42.57362],"type":"Point"}
}