{
  "type": "Feature",
  "properties": {
    "gn:admin1_code":"30",
    "gn:asciiname":"Huangdonghe",
    "gn:country_code":"CN",
    "gn:dem":195,
    "gn:feature_class":"P",
    "gn:feature_code":"PPL",
    "gn:name":"Huangdonghe",
    "gn:population":0,
    "gn:timezone":"Asia/Shanghai",
    "iso:country":"CN",
    "name:zho_x_preferred":[
        "\u9ec4\u578c\u6cb3"
    ],
    "wof:name":"Huangdonghe",
    "wof:placetype":"locality"
},
  "geometry": {"coordinates":[111.45735999999999,22.19267],"type":"Point"}
}