{
  "type": "Feature",
  "properties": {
    "gn:admin1_code":"11.0",
    "gn:asciiname":"Liuhu",
    "gn:country_code":"CN",
    "gn:dem":429,
    "gn:feature_class":"P",
    "gn:feature_code":"PPL",
    "gn:name":"Liuhu",
    "gn:population":0,
    "gn:timezone":"Asia/Shanghai",
    "iso:country":"CN",
    "name:zho_x_preferred":[
        "\u516d\u6e56"
    ],
    "wof:name":"Liuhu",
    "wof:placetype":"locality"
},
  "geometry": {"coordinates":[109.40783999999999,28.89409],"type":"Point"}
}