{
  "type": "Feature",
  "properties": {
    "gn:admin1_code":"8.0",
    "gn:asciiname":"Zhangdakeng",
    "gn:country_code":"CN",
    "gn:dem":272,
    "gn:feature_class":"P",
    "gn:feature_code":"PPL",
    "gn:name":"Zhangdakeng",
    "gn:population":0,
    "gn:timezone":"Asia/Shanghai",
    "iso:country":"CN",
    "name:zho_x_preferred":[
        "\u5f20\u5927\u5751"
    ],
    "wof:name":"Zhangdakeng",
    "wof:placetype":"locality"
},
  "geometry": {"coordinates":[125.18261,48.12759000000001],"type":"Point"}
}