{
  "type": "Feature",
  "properties": {
    "gn:admin1_code":"29.0",
    "gn:asciiname":"Paleng",
    "gn:country_code":"CN",
    "gn:dem":1290,
    "gn:feature_class":"P",
    "gn:feature_code":"PPL",
    "gn:name":"Paleng",
    "gn:population":0,
    "gn:timezone":"Asia/Shanghai",
    "iso:country":"CN",
    "name:zho_x_preferred":[
        "\u5e15\u51b7"
    ],
    "wof:name":"Paleng",
    "wof:placetype":"locality"
},
  "geometry": {"coordinates":[100.59399999999999,21.5988],"type":"Point"}
}