{
  "type": "Feature",
  "properties": {
    "gn:admin1_code":"02",
    "gn:asciiname":"Chih-hui-miao",
    "gn:cc2":"CN",
    "gn:country_code":"CN",
    "gn:dem":7,
    "gn:feature_class":"P",
    "gn:feature_code":"PPL",
    "gn:name":"Chih-hui-miao",
    "gn:population":0,
    "gn:timezone":"Asia/Shanghai",
    "iso:country":"CN",
    "name:und_x_variant":[
        "Chih-hui-maio",
        "Chih-hui-miao"
    ],
    "wof:name":"Chih-hui-miao",
    "wof:placetype":"locality"
},
  "geometry": {"coordinates":[121.12528,30.21083],"type":"Point"}
}