{
  "type": "Feature",
  "properties": {
    "gn:admin1_code":"19.0",
    "gn:asciiname":"Qianyaobucun",
    "gn:country_code":"CN",
    "gn:dem":79,
    "gn:feature_class":"P",
    "gn:feature_code":"PPL",
    "gn:name":"Qianyaobucun",
    "gn:population":0,
    "gn:timezone":"Asia/Shanghai",
    "iso:country":"CN",
    "name:zho_x_preferred":[
        "\u524d\u8170\u5821\u6751"
    ],
    "wof:name":"Qianyaobucun",
    "wof:placetype":"locality"
},
  "geometry": {"coordinates":[123.60899999999999,42.0374],"type":"Point"}
}