{
  "type": "Feature",
  "properties": {
    "gn:admin1_code":"15.0",
    "gn:asciiname":"Mujiagou",
    "gn:country_code":"CN",
    "gn:dem":1156,
    "gn:feature_class":"P",
    "gn:feature_code":"PPL",
    "gn:name":"Mujiagou",
    "gn:population":0,
    "gn:timezone":"Asia/Shanghai",
    "iso:country":"CN",
    "name:zho_x_preferred":[
        "\u7267\u5bb6\u6c9f"
    ],
    "wof:name":"Mujiagou",
    "wof:placetype":"locality"
},
  "geometry": {"coordinates":[108.092,35.9851],"type":"Point"}
}