{
  "type": "Feature",
  "properties": {
    "gn:admin1_code":"9.0",
    "gn:asciiname":"Housangyuan",
    "gn:country_code":"CN",
    "gn:dem":84,
    "gn:feature_class":"P",
    "gn:feature_code":"PPL",
    "gn:name":"Housangyuan",
    "gn:population":0,
    "gn:timezone":"Asia/Shanghai",
    "iso:country":"CN",
    "name:zho_x_preferred":[
        "\u540e\u6851\u56ed"
    ],
    "wof:name":"Housangyuan",
    "wof:placetype":"locality"
},
  "geometry": {"coordinates":[114.34376,34.9596],"type":"Point"}
}