{
  "type": "Feature",
  "properties": {
    "gn:admin1_code":"14.0",
    "gn:asciiname":"Shenmucun",
    "gn:country_code":"CN",
    "gn:dem":3125,
    "gn:feature_class":"P",
    "gn:feature_code":"PPL",
    "gn:name":"Shenmucun",
    "gn:population":0,
    "gn:timezone":"Asia/Urumqi",
    "iso:country":"CN",
    "name:zho_x_preferred":[
        "\u7533\u6728\u6751"
    ],
    "wof:name":"Shenmucun",
    "wof:placetype":"locality"
},
  "geometry": {"coordinates":[93.08789,29.10172],"type":"Point"}
}