{
  "type": "Feature",
  "properties": {
    "gn:admin1_code":"26.0",
    "gn:asciiname":"Zuitoucun",
    "gn:country_code":"CN",
    "gn:dem":1092,
    "gn:feature_class":"P",
    "gn:feature_code":"PPL",
    "gn:name":"Zuitoucun",
    "gn:population":0,
    "gn:timezone":"Asia/Shanghai",
    "iso:country":"CN",
    "name:zho_x_preferred":[
        "\u5480\u5934\u6751"
    ],
    "wof:name":"Zuitoucun",
    "wof:placetype":"locality"
},
  "geometry": {"coordinates":[108.1567,34.93829],"type":"Point"}
}