{
  "type": "Feature",
  "properties": {
    "gn:admin1_code":"24.0",
    "gn:asciiname":"Yangjian",
    "gn:cc2":"CN",
    "gn:country_code":"CN",
    "gn:dem":1230,
    "gn:feature_class":"P",
    "gn:feature_code":"PPL",
    "gn:name":"Yangjian",
    "gn:population":0,
    "gn:timezone":"Asia/Shanghai",
    "iso:country":"CN",
    "name:und_x_variant":[
        "Yang-chien",
        "Yangjian"
    ],
    "name:zho_x_preferred":[
        "\u7f8a\u5c16\u9547"
    ],
    "wof:name":"Yangjian",
    "wof:placetype":"locality"
},
  "geometry": {"coordinates":[112.46666999999999,39.45],"type":"Point"}
}