{
  "type": "Feature",
  "properties": {
    "gn:admin1_code":"25",
    "gn:asciiname":"Poli",
    "gn:country_code":"CN",
    "gn:dem":147,
    "gn:feature_class":"P",
    "gn:feature_code":"PPL",
    "gn:name":"Poli",
    "gn:population":0,
    "gn:timezone":"Asia/Shanghai",
    "iso:country":"CN",
    "name:ceb_x_preferred":[
        "Poli"
    ],
    "name:deu_x_preferred":[
        "Poli"
    ],
    "name:ell_x_preferred":[
        "\u03a0\u03cc\u03bb\u03b7"
    ],
    "name:fin_x_preferred":[
        "Poli"
    ],
    "name:fra_x_preferred":[
        "Poli"
    ],
    "name:ita_x_preferred":[
        "Poli"
    ],
    "name:nld_x_preferred":[
        "Poli"
    ],
    "name:pol_x_preferred":[
        "Poli"
    ],
    "name:por_x_preferred":[
        "Poli"
    ],
    "name:rus_x_preferred":[
        "\u041f\u043e\u043b\u0438"
    ],
    "name:sco_x_preferred":[
        "Poli"
    ],
    "name:spa_x_preferred":[
        "Poli"
    ],
    "name:srp_x_preferred":[
        "Poli"
    ],
    "name:swe_x_preferred":[
        "Poli"
    ],
    "name:zho_x_preferred":[
        "\u5761\u91cc"
    ],
    "wof:name":"Poli",
    "wof:placetype":"locality"
},
  "geometry": {"coordinates":[117.511,35.9452],"type":"Point"}
}