{
  "type": "Feature",
  "properties": {
    "gn:admin1_code":"19.0",
    "gn:asciiname":"Honghualingcun",
    "gn:country_code":"CN",
    "gn:dem":84,
    "gn:feature_class":"P",
    "gn:feature_code":"PPL",
    "gn:name":"Honghualingcun",
    "gn:population":0,
    "gn:timezone":"Asia/Shanghai",
    "iso:country":"CN",
    "name:zho_x_preferred":[
        "\u7ea2\u82b1\u5cad\u6751"
    ],
    "wof:name":"Honghualingcun",
    "wof:placetype":"locality"
},
  "geometry": {"coordinates":[123.28100000000001,42.4193],"type":"Point"}
}