{
  "type": "Feature",
  "properties": {
    "gn:admin1_code":"14.0",
    "gn:asciiname":"Qukacun",
    "gn:country_code":"CN",
    "gn:dem":3779,
    "gn:feature_class":"P",
    "gn:feature_code":"PPL",
    "gn:name":"Qukacun",
    "gn:population":0,
    "gn:timezone":"Asia/Urumqi",
    "iso:country":"CN",
    "name:zho_x_preferred":[
        "\u66f2\u5361\u6751"
    ],
    "wof:name":"Qukacun",
    "wof:placetype":"locality"
},
  "geometry": {"coordinates":[98.36548000000001,30.653],"type":"Point"}
}