{
  "type": "Feature",
  "properties": {
    "gn:admin1_code":"30",
    "gn:asciiname":"Huangqiang",
    "gn:country_code":"CN",
    "gn:dem":17,
    "gn:feature_class":"P",
    "gn:feature_code":"PPLA4",
    "gn:name":"Huangqiang",
    "gn:population":0,
    "gn:timezone":"Asia/Shanghai",
    "iso:country":"CN",
    "name:und_x_variant":[
        "Huangqiang Zhen",
        "\u9ec4\u7f8c\u9547"
    ],
    "name:zho_x_preferred":[
        "\u9ec4\u7f8c"
    ],
    "wof:name":"Huangqiang",
    "wof:placetype":"locality"
},
  "geometry": {"coordinates":[115.41861000000002,23.15137],"type":"Point"}
}