{
  "type": "Feature",
  "properties": {
    "gn:admin1_code":"18.0",
    "gn:asciiname":"Zhanliang",
    "gn:country_code":"CN",
    "gn:dem":941,
    "gn:feature_class":"P",
    "gn:feature_code":"PPL",
    "gn:name":"Zhanliang",
    "gn:population":0,
    "gn:timezone":"Asia/Shanghai",
    "iso:country":"CN",
    "name:zho_x_preferred":[
        "\u5c55\u4eae"
    ],
    "wof:name":"Zhanliang",
    "wof:placetype":"locality"
},
  "geometry": {"coordinates":[108.535,26.7256],"type":"Point"}
}