{
  "type": "Feature",
  "properties": {
    "gn:admin1_code":"14.0",
    "gn:asciiname":"Galie",
    "gn:country_code":"CN",
    "gn:dem":4253,
    "gn:feature_class":"P",
    "gn:feature_code":"PPL",
    "gn:name":"Galie",
    "gn:population":0,
    "gn:timezone":"Asia/Urumqi",
    "iso:country":"CN",
    "name:zho_x_preferred":[
        "\u5c15\u5217"
    ],
    "wof:name":"Galie",
    "wof:placetype":"locality"
},
  "geometry": {"coordinates":[96.23694,30.97459000000001],"type":"Point"}
}