{
  "type": "Feature",
  "properties": {
    "gn:admin1_code":"12.0",
    "gn:asciiname":"Beimenhe",
    "gn:country_code":"CN",
    "gn:dem":108,
    "gn:feature_class":"P",
    "gn:feature_code":"PPL",
    "gn:name":"Beimenhe",
    "gn:population":0,
    "gn:timezone":"Asia/Shanghai",
    "iso:country":"CN",
    "name:zho_x_preferred":[
        "\u5317\u95e8\u6cb3"
    ],
    "wof:name":"Beimenhe",
    "wof:placetype":"locality"
},
  "geometry": {"coordinates":[111.62208,31.07549],"type":"Point"}
}