{
  "type": "Feature",
  "properties": {
    "gn:admin1_code":"14.0",
    "gn:asciiname":"Qianjin",
    "gn:country_code":"CN",
    "gn:dem":4014,
    "gn:feature_class":"P",
    "gn:feature_code":"PPLF",
    "gn:name":"Qianjin",
    "gn:population":0,
    "gn:timezone":"Asia/Urumqi",
    "iso:country":"CN",
    "name:bod_x_preferred":[
        "D\u00fcn\u2019gyoi"
    ],
    "name:ceb_x_preferred":[
        "Qianjin"
    ],
    "name:deu_x_preferred":[
        "Qianjin"
    ],
    "name:eus_x_preferred":[
        "Qianjin"
    ],
    "name:kor_x_preferred":[
        "\uccb8\uc9c4\uad6c"
    ],
    "name:rus_x_preferred":[
        "\u0426\u044f\u043d\u044c\u0446\u0437\u0438\u043d\u044c"
    ],
    "name:zho_x_preferred":[
        "Qianjin"
    ],
    "name:zho_x_variant":[
        "\u524d\u8fdb",
        "Manixika",
        "\u9a6c\u5c3c\u6eaa\u5361"
    ],
    "wof:name":"Qianjin",
    "wof:placetype":"locality"
},
  "geometry": {"coordinates":[92.70099999999999,29.001],"type":"Point"}
}