{
  "type": "Feature",
  "properties": {
    "gn:admin1_code":"30.0",
    "gn:asciiname":"Jian'ancun",
    "gn:country_code":"CN",
    "gn:dem":122,
    "gn:feature_class":"P",
    "gn:feature_code":"PPL",
    "gn:name":"Jian\u2019ancun",
    "gn:population":0,
    "gn:timezone":"Asia/Shanghai",
    "iso:country":"CN",
    "name:und_x_variant":[
        "Jian\u2019ancun"
    ],
    "name:zho_x_preferred":[
        "\u5efa\u5b89\u6751"
    ],
    "wof:name":"Jian'ancun",
    "wof:placetype":"locality"
},
  "geometry": {"coordinates":[116.14102,23.94771],"type":"Point"}
}