{
  "type": "Feature",
  "properties": {
    "gn:admin1_code":"26.0",
    "gn:asciiname":"Caojia Yuanzicun",
    "gn:country_code":"CN",
    "gn:dem":901,
    "gn:feature_class":"P",
    "gn:feature_code":"PPL",
    "gn:name":"Caojia Yuanzicun",
    "gn:population":0,
    "gn:timezone":"Asia/Shanghai",
    "iso:country":"CN",
    "name:zho_x_preferred":[
        "\u66f9\u5bb6\u9662\u5b50\u6751"
    ],
    "wof:name":"Caojia Yuanzicun",
    "wof:placetype":"locality"
},
  "geometry": {"coordinates":[108.61507,33.67067],"type":"Point"}
}