{
  "type": "Feature",
  "properties": {
    "gn:admin1_code":"16.0",
    "gn:asciiname":"Dipodi",
    "gn:country_code":"CN",
    "gn:dem":24,
    "gn:feature_class":"P",
    "gn:feature_code":"PPL",
    "gn:name":"Dipodi",
    "gn:population":0,
    "gn:timezone":"Asia/Shanghai",
    "iso:country":"CN",
    "name:zho_x_preferred":[
        "\u4f4e\u5761\u5e95"
    ],
    "wof:name":"Dipodi",
    "wof:placetype":"locality"
},
  "geometry": {"coordinates":[109.381,21.8338],"type":"Point"}
}