{
  "type": "Feature",
  "properties": {
    "gn:admin1_code":"11.0",
    "gn:asciiname":"Jigongtang",
    "gn:country_code":"CN",
    "gn:dem":319,
    "gn:feature_class":"P",
    "gn:feature_code":"PPL",
    "gn:name":"Jigongtang",
    "gn:population":0,
    "gn:timezone":"Asia/Shanghai",
    "iso:country":"CN",
    "name:zho_x_preferred":[
        "\u9e21\u516c\u5858"
    ],
    "wof:name":"Jigongtang",
    "wof:placetype":"locality"
},
  "geometry": {"coordinates":[111.7462,27.3594],"type":"Point"}
}