{
  "type": "Feature",
  "properties": {
    "gn:admin1_code":"3.0",
    "gn:asciiname":"Xiexi",
    "gn:country_code":"CN",
    "gn:dem":96,
    "gn:feature_class":"P",
    "gn:feature_code":"PPL",
    "gn:name":"Xiexi",
    "gn:population":0,
    "gn:timezone":"Asia/Shanghai",
    "iso:country":"CN",
    "name:zho_x_preferred":[
        "\u659c\u6eaa"
    ],
    "wof:name":"Xiexi",
    "wof:placetype":"locality"
},
  "geometry": {"coordinates":[117.90045000000001,28.44672000000001],"type":"Point"}
}