{
  "type": "Feature",
  "properties": {
    "gn:admin1_code":"12.0",
    "gn:asciiname":"Huazidian",
    "gn:country_code":"CN",
    "gn:dem":63,
    "gn:feature_class":"P",
    "gn:feature_code":"PPL",
    "gn:name":"Huazidian",
    "gn:population":0,
    "gn:timezone":"Asia/Shanghai",
    "iso:country":"CN",
    "name:zho_x_preferred":[
        "\u82b1\u5b50\u5e97"
    ],
    "wof:name":"Huazidian",
    "wof:placetype":"locality"
},
  "geometry": {"coordinates":[113.63612000000001,31.26375],"type":"Point"}
}