{
  "type": "Feature",
  "properties": {
    "gn:admin1_code":"29",
    "gn:asciiname":"Takedie",
    "gn:country_code":"CN",
    "gn:dem":1346,
    "gn:feature_class":"P",
    "gn:feature_code":"PPL",
    "gn:name":"Takedie",
    "gn:population":0,
    "gn:timezone":"Asia/Shanghai",
    "iso:country":"CN",
    "name:zho_x_preferred":[
        "\u5b83\u79d1\u57a4"
    ],
    "wof:name":"Takedie",
    "wof:placetype":"locality"
},
  "geometry": {"coordinates":[102.164,23.6288],"type":"Point"}
}