{
  "type": "Feature",
  "properties": {
    "gn:admin1_code":"5.0",
    "gn:asciiname":"Huashu Zuizi Nangou",
    "gn:country_code":"CN",
    "gn:dem":219,
    "gn:feature_class":"P",
    "gn:feature_code":"PPL",
    "gn:name":"Huashu Zuizi Nangou",
    "gn:population":0,
    "gn:timezone":"Asia/Shanghai",
    "iso:country":"CN",
    "name:zho_x_preferred":[
        "\u6866\u6811\u5480\u5b50\u5357\u6c9f"
    ],
    "wof:name":"Huashu Zuizi Nangou",
    "wof:placetype":"locality"
},
  "geometry": {"coordinates":[126.60720000000001,44.12864],"type":"Point"}
}