{
  "type": "Feature",
  "properties": {
    "gn:admin1_code":"24.0",
    "gn:asciiname":"Shanshangcun",
    "gn:country_code":"CN",
    "gn:dem":1022,
    "gn:feature_class":"P",
    "gn:feature_code":"PPL",
    "gn:name":"Shanshangcun",
    "gn:population":0,
    "gn:timezone":"Asia/Shanghai",
    "iso:country":"CN",
    "name:zho_x_preferred":[
        "\u5c71\u4e0a\u6751"
    ],
    "wof:name":"Shanshangcun",
    "wof:placetype":"locality"
},
  "geometry": {"coordinates":[114.06252000000001,37.65797],"type":"Point"}
}