{
  "type": "Feature",
  "properties": {
    "gn:admin1_code":"3.0",
    "gn:asciiname":"Yujia",
    "gn:country_code":"CN",
    "gn:dem":150,
    "gn:feature_class":"P",
    "gn:feature_code":"PPL",
    "gn:name":"Yujia",
    "gn:population":0,
    "gn:timezone":"Asia/Shanghai",
    "iso:country":"CN",
    "name:und_x_variant":[
        "\u55bb\u5bb6"
    ],
    "wof:name":"Yujia",
    "wof:placetype":"locality"
},
  "geometry": {"coordinates":[116.82986,27.20707],"type":"Point"}
}