{
  "type": "Feature",
  "properties": {
    "gn:admin1_code":"13",
    "gn:asciiname":"Huletuo Gelake",
    "gn:country_code":"CN",
    "gn:dem":329,
    "gn:feature_class":"P",
    "gn:feature_code":"PPL",
    "gn:name":"Huletuo Gelake",
    "gn:population":0,
    "gn:timezone":"Asia/Urumqi",
    "iso:country":"CN",
    "name:zho_x_preferred":[
        "\u80e1\u52d2\u6258\u683c\u62c9\u514b"
    ],
    "wof:name":"Huletuo Gelake",
    "wof:placetype":"locality"
},
  "geometry": {"coordinates":[92.64152,42.81797],"type":"Point"}
}