{
  "type": "Feature",
  "properties": {
    "gn:admin1_code":"9.0",
    "gn:asciiname":"Fenxindian",
    "gn:country_code":"CN",
    "gn:dem":90,
    "gn:feature_class":"P",
    "gn:feature_code":"PPL",
    "gn:name":"Fenxindian",
    "gn:population":0,
    "gn:timezone":"Asia/Shanghai",
    "iso:country":"CN",
    "name:zho_x_preferred":[
        "\u5206\u65b0\u5e97"
    ],
    "wof:name":"Fenxindian",
    "wof:placetype":"locality"
},
  "geometry": {"coordinates":[114.52200000000001,31.83225],"type":"Point"}
}