{
  "type": "Feature",
  "properties": {
    "gn:admin1_code":"26.0",
    "gn:asciiname":"Zhujiabacun",
    "gn:country_code":"CN",
    "gn:dem":677,
    "gn:feature_class":"P",
    "gn:feature_code":"PPL",
    "gn:name":"Zhujiabacun",
    "gn:population":0,
    "gn:timezone":"Asia/Shanghai",
    "iso:country":"CN",
    "name:und_x_variant":[
        "Chu-chia-pa",
        "Zhujiaba",
        "Zhujiabacun"
    ],
    "name:zho_x_preferred":[
        "\u6731\u5bb6\u575d\u6751"
    ],
    "wof:name":"Zhujiabacun",
    "wof:placetype":"locality"
},
  "geometry": {"coordinates":[107.17228,32.4964],"type":"Point"}
}