{
  "type": "Feature",
  "properties": {
    "gn:admin1_code":"24.0",
    "gn:asciiname":"Dahuangpo",
    "gn:country_code":"CN",
    "gn:dem":997,
    "gn:feature_class":"P",
    "gn:feature_code":"PPL",
    "gn:name":"Dahuangpo",
    "gn:population":0,
    "gn:timezone":"Asia/Shanghai",
    "iso:country":"CN",
    "name:zho_x_preferred":[
        "\u5927\u9ec4\u5761"
    ],
    "wof:name":"Dahuangpo",
    "wof:placetype":"locality"
},
  "geometry": {"coordinates":[111.1164,39.01095],"type":"Point"}
}