{
  "type": "Feature",
  "properties": {
    "gn:admin1_code":"29.0",
    "gn:asciiname":"Kangnong",
    "gn:country_code":"CN",
    "gn:dem":1372,
    "gn:feature_class":"P",
    "gn:feature_code":"PPL",
    "gn:name":"Kangnong",
    "gn:population":0,
    "gn:timezone":"Asia/Shanghai",
    "iso:country":"CN",
    "name:zho_x_preferred":[
        "\u6297\u5f04"
    ],
    "wof:name":"Kangnong",
    "wof:placetype":"locality"
},
  "geometry": {"coordinates":[100.265,23.3522],"type":"Point"}
}