{
  "type": "Feature",
  "properties": {
    "gn:admin1_code":"8.0",
    "gn:asciiname":"Yongxing Erdui",
    "gn:country_code":"CN",
    "gn:dem":267,
    "gn:feature_class":"P",
    "gn:feature_code":"PPLF",
    "gn:name":"Yongxing Erdui",
    "gn:population":0,
    "gn:timezone":"Asia/Shanghai",
    "iso:country":"CN",
    "name:zho_x_preferred":[
        "\u6c38\u5174\u4e8c\u961f"
    ],
    "wof:name":"Yongxing Erdui",
    "wof:placetype":"locality"
},
  "geometry": {"coordinates":[125.44378,48.64704],"type":"Point"}
}