{
  "type": "Feature",
  "properties": {
    "gn:admin1_code":"16",
    "gn:asciiname":"Tanli",
    "gn:cc2":"CN",
    "gn:country_code":"CN",
    "gn:dem":162,
    "gn:feature_class":"P",
    "gn:feature_code":"PPL",
    "gn:name":"Tanli",
    "gn:population":0,
    "gn:timezone":"Asia/Shanghai",
    "iso:country":"CN",
    "name:und_x_variant":[
        "T\u2019an-li-san-ts\u2019un",
        "Tanli"
    ],
    "wof:name":"Tanli",
    "wof:placetype":"locality"
},
  "geometry": {"coordinates":[108.36556000000002,23.33167000000001],"type":"Point"}
}