{
  "type": "Feature",
  "properties": {
    "gn:admin1_code":"9",
    "gn:asciiname":"Zhonglou",
    "gn:country_code":"CN",
    "gn:dem":69,
    "gn:feature_class":"P",
    "gn:feature_code":"PPL",
    "gn:name":"Zhonglou",
    "gn:population":0,
    "gn:timezone":"Asia/Shanghai",
    "iso:country":"CN",
    "name:zho_x_preferred":[
        "\u4ef2\u697c"
    ],
    "wof:name":"Zhonglou",
    "wof:placetype":"locality"
},
  "geometry": {"coordinates":[115.39100000000001,34.6618],"type":"Point"}
}