{
  "type": "Feature",
  "properties": {
    "gn:admin1_code":"25",
    "gn:asciiname":"Liubaixin",
    "gn:country_code":"CN",
    "gn:dem":23,
    "gn:feature_class":"P",
    "gn:feature_code":"PPL",
    "gn:name":"Liubaixin",
    "gn:population":0,
    "gn:timezone":"Asia/Shanghai",
    "iso:country":"CN",
    "name:zho_x_preferred":[
        "\u5218\u767e\u8f9b"
    ],
    "wof:name":"Liubaixin",
    "wof:placetype":"locality"
},
  "geometry": {"coordinates":[116.741,37.0799],"type":"Point"}
}