{
  "type": "Feature",
  "properties": {
    "gn:admin1_code":"12",
    "gn:asciiname":"Hougang",
    "gn:country_code":"CN",
    "gn:dem":34,
    "gn:feature_class":"P",
    "gn:feature_code":"PPLA4",
    "gn:name":"Hougang",
    "gn:population":0,
    "gn:timezone":"Asia/Shanghai",
    "iso:country":"CN",
    "name:fas_x_preferred":[
        "\u0647\u0648\u06af\u0627\u0646\u06af"
    ],
    "name:fin_x_preferred":[
        "Hougang"
    ],
    "name:ind_x_preferred":[
        "Hougang"
    ],
    "name:und_x_variant":[
        "Hou-Kang",
        "Hougang",
        "\u540e\u6e2f",
        "Hougang Zhen",
        "\u540e\u6e2f\u9547"
    ],
    "wof:name":"Hougang",
    "wof:placetype":"locality"
},
  "geometry": {"coordinates":[112.38388999999999,30.51722],"type":"Point"}
}