{
  "type": "Feature",
  "properties": {
    "gn:admin1_code":"14.0",
    "gn:asciiname":"Xiarumai",
    "gn:country_code":"CN",
    "gn:dem":4576,
    "gn:feature_class":"P",
    "gn:feature_code":"PPL",
    "gn:name":"Xiarumai",
    "gn:population":0,
    "gn:timezone":"Asia/Urumqi",
    "iso:country":"CN",
    "name:zho_x_preferred":[
        "\u590f\u5982\u9ea6"
    ],
    "wof:name":"Xiarumai",
    "wof:placetype":"locality"
},
  "geometry": {"coordinates":[91.86566000000001,28.57382],"type":"Point"}
}