{
  "type": "Feature",
  "properties": {
    "gn:admin1_code":"3",
    "gn:asciiname":"Laowuxia",
    "gn:country_code":"CN",
    "gn:dem":265,
    "gn:feature_class":"P",
    "gn:feature_code":"PPL",
    "gn:name":"Laowuxia",
    "gn:population":0,
    "gn:timezone":"Asia/Shanghai",
    "iso:country":"CN",
    "name:zho_x_preferred":[
        "\u8001\u5c4b\u4e0b"
    ],
    "wof:name":"Laowuxia",
    "wof:placetype":"locality"
},
  "geometry": {"coordinates":[114.64400000000001,25.3604],"type":"Point"}
}