{
  "type": "Feature",
  "properties": {
    "gn:admin1_code":"7.0",
    "gn:asciiname":"Chigoupai",
    "gn:country_code":"CN",
    "gn:dem":338,
    "gn:feature_class":"P",
    "gn:feature_code":"PPL",
    "gn:name":"Chigoupai",
    "gn:population":0,
    "gn:timezone":"Asia/Shanghai",
    "iso:country":"CN",
    "name:zho_x_preferred":[
        "\u8d64\u52fe\u6392"
    ],
    "wof:name":"Chigoupai",
    "wof:placetype":"locality"
},
  "geometry": {"coordinates":[116.28570000000001,25.17637],"type":"Point"}
}