{
  "type": "Feature",
  "properties": {
    "gn:admin1_code":"12.0",
    "gn:asciiname":"Shapo",
    "gn:country_code":"CN",
    "gn:dem":1016,
    "gn:feature_class":"P",
    "gn:feature_code":"PPL",
    "gn:name":"Shapo",
    "gn:population":0,
    "gn:timezone":"Asia/Shanghai",
    "iso:country":"CN",
    "name:zho_x_preferred":[
        "\u6c99\u5761"
    ],
    "wof:name":"Shapo",
    "wof:placetype":"locality"
},
  "geometry": {"coordinates":[110.82571000000002,30.36666],"type":"Point"}
}