{
  "type": "Feature",
  "properties": {
    "gn:admin1_code":"4.0",
    "gn:asciiname":"Yunshan",
    "gn:country_code":"CN",
    "gn:dem":29,
    "gn:feature_class":"P",
    "gn:feature_code":"PPL",
    "gn:name":"Yunshan",
    "gn:population":0,
    "gn:timezone":"Asia/Shanghai",
    "iso:country":"CN",
    "name:zho_x_preferred":[
        "\u4e91\u5c71"
    ],
    "wof:name":"Yunshan",
    "wof:placetype":"locality"
},
  "geometry": {"coordinates":[118.85883,32.97666],"type":"Point"}
}