{
  "type": "Feature",
  "properties": {
    "gn:admin1_code":"18",
    "gn:asciiname":"Duoyuqing",
    "gn:country_code":"CN",
    "gn:dem":1114,
    "gn:feature_class":"P",
    "gn:feature_code":"PPL",
    "gn:name":"Duoyuqing",
    "gn:population":0,
    "gn:timezone":"Asia/Shanghai",
    "iso:country":"CN",
    "name:zho_x_preferred":[
        "\u8eb2\u96e8\u7b90"
    ],
    "wof:name":"Duoyuqing",
    "wof:placetype":"locality"
},
  "geometry": {"coordinates":[105.64700000000001,25.7927],"type":"Point"}
}