{
  "type": "Feature",
  "properties": {
    "gn:admin1_code":"25",
    "gn:asciiname":"Xizhangzhuang",
    "gn:country_code":"CN",
    "gn:dem":149,
    "gn:feature_class":"P",
    "gn:feature_code":"PPL",
    "gn:name":"Xizhangzhuang",
    "gn:population":0,
    "gn:timezone":"Asia/Shanghai",
    "iso:country":"CN",
    "name:zho_x_preferred":[
        "\u897f\u5f20\u5e84"
    ],
    "wof:name":"Xizhangzhuang",
    "wof:placetype":"locality"
},
  "geometry": {"coordinates":[117.20699999999999,36.2069],"type":"Point"}
}