{
  "type": "Feature",
  "properties": {
    "gn:admin1_code":"25",
    "gn:asciiname":"Zhangpolou",
    "gn:country_code":"CN",
    "gn:dem":49,
    "gn:feature_class":"P",
    "gn:feature_code":"PPL",
    "gn:name":"Zhangpolou",
    "gn:population":0,
    "gn:timezone":"Asia/Shanghai",
    "iso:country":"CN",
    "name:zho_x_preferred":[
        "\u5f20\u5761\u697c"
    ],
    "wof:name":"Zhangpolou",
    "wof:placetype":"locality"
},
  "geometry": {"coordinates":[115.76688,35.14548],"type":"Point"}
}