{
  "type": "Feature",
  "properties": {
    "gn:admin1_code":"15.0",
    "gn:asciiname":"Wuxing Jiudui",
    "gn:country_code":"CN",
    "gn:dem":1242,
    "gn:feature_class":"P",
    "gn:feature_code":"PPLF",
    "gn:name":"Wuxing Jiudui",
    "gn:population":0,
    "gn:timezone":"Asia/Shanghai",
    "iso:country":"CN",
    "name:zho_x_preferred":[
        "\u4e94\u661f\u4e5d\u961f"
    ],
    "wof:name":"Wuxing Jiudui",
    "wof:placetype":"locality"
},
  "geometry": {"coordinates":[99.03060000000001,40.0716],"type":"Point"}
}