{
  "type": "Feature",
  "properties": {
    "gn:admin1_code":"4.0",
    "gn:asciiname":"Qingfengyao",
    "gn:country_code":"CN",
    "gn:dem":4,
    "gn:feature_class":"P",
    "gn:feature_code":"PPL",
    "gn:name":"Qingfengyao",
    "gn:population":0,
    "gn:timezone":"Asia/Shanghai",
    "iso:country":"CN",
    "name:zho_x_preferred":[
        "Qingfengyao"
    ],
    "name:zho_x_variant":[
        "\u5e86\u4e30\u7a91"
    ],
    "wof:name":"Qingfengyao",
    "wof:placetype":"locality"
},
  "geometry": {"coordinates":[121.41092999999999,32.15916],"type":"Point"}
}