{
  "type": "Feature",
  "properties": {
    "gn:admin1_code":"19.0",
    "gn:asciiname":"Bayintai",
    "gn:country_code":"CN",
    "gn:dem":23,
    "gn:feature_class":"P",
    "gn:feature_code":"PPL",
    "gn:name":"Bayintai",
    "gn:population":0,
    "gn:timezone":"Asia/Shanghai",
    "iso:country":"CN",
    "name:und_x_variant":[
        "\u516b\u97f3\u53f0"
    ],
    "name:zho_x_preferred":[
        "\u516b\u97f3\u53f0"
    ],
    "wof:name":"Bayintai",
    "wof:placetype":"locality"
},
  "geometry": {"coordinates":[122.98968000000001,41.58464],"type":"Point"}
}