{
  "type": "Feature",
  "properties": {
    "gn:admin1_code":"29.0",
    "gn:asciiname":"Huazhuqing",
    "gn:country_code":"CN",
    "gn:dem":1643,
    "gn:feature_class":"P",
    "gn:feature_code":"PPL",
    "gn:name":"Huazhuqing",
    "gn:population":0,
    "gn:timezone":"Asia/Shanghai",
    "iso:country":"CN",
    "name:zho_x_preferred":[
        "\u6ed1\u7af9\u7b90"
    ],
    "wof:name":"Huazhuqing",
    "wof:placetype":"locality"
},
  "geometry": {"coordinates":[101.386,23.3459],"type":"Point"}
}