{
  "type": "Feature",
  "properties": {
    "gn:admin1_code":"15.0",
    "gn:asciiname":"Cangtoushan",
    "gn:country_code":"CN",
    "gn:dem":1988,
    "gn:feature_class":"P",
    "gn:feature_code":"PPL",
    "gn:name":"Cangtoushan",
    "gn:population":0,
    "gn:timezone":"Asia/Shanghai",
    "iso:country":"CN",
    "name:und_x_variant":[
        "\u4ed3\u5934\u5c71"
    ],
    "wof:name":"Cangtoushan",
    "wof:placetype":"locality"
},
  "geometry": {"coordinates":[105.14426,33.53818],"type":"Point"}
}