{
  "type": "Feature",
  "properties": {
    "gn:admin1_code":"19.0",
    "gn:asciiname":"Jiaojia Buzi",
    "gn:country_code":"CN",
    "gn:dem":265,
    "gn:feature_class":"P",
    "gn:feature_code":"PPL",
    "gn:name":"Jiaojia Buzi",
    "gn:population":0,
    "gn:timezone":"Asia/Shanghai",
    "iso:country":"CN",
    "name:und_x_variant":[
        "Jiaojiabaozi",
        "Jiaojia Buzi"
    ],
    "name:zho_x_preferred":[
        "\u6559\u5bb6\u5821\u5b50"
    ],
    "wof:name":"Jiaojia Buzi",
    "wof:placetype":"locality"
},
  "geometry": {"coordinates":[123.7895,40.77945],"type":"Point"}
}