{
  "type": "Feature",
  "properties": {
    "gn:admin1_code":"1.0",
    "gn:asciiname":"Caojiahecun",
    "gn:country_code":"CN",
    "gn:dem":348,
    "gn:feature_class":"P",
    "gn:feature_code":"PPL",
    "gn:name":"Caojiahecun",
    "gn:population":0,
    "gn:timezone":"Asia/Shanghai",
    "iso:country":"CN",
    "name:zho_x_preferred":[
        "\u66f9\u5bb6\u6cb3\u6751"
    ],
    "wof:name":"Caojiahecun",
    "wof:placetype":"locality"
},
  "geometry": {"coordinates":[116.31999999999999,31.34828],"type":"Point"}
}