{
  "type": "Feature",
  "properties": {
    "gn:admin1_code":"29.0",
    "gn:asciiname":"Dawazhe",
    "gn:country_code":"CN",
    "gn:dem":1873,
    "gn:feature_class":"P",
    "gn:feature_code":"PPL",
    "gn:name":"Dawazhe",
    "gn:population":0,
    "gn:timezone":"Asia/Shanghai",
    "iso:country":"CN",
    "name:zho_x_preferred":[
        "\u5927\u74e6\u6298"
    ],
    "wof:name":"Dawazhe",
    "wof:placetype":"locality"
},
  "geometry": {"coordinates":[100.548,24.9814],"type":"Point"}
}