{
  "type": "Feature",
  "properties": {
    "gn:admin1_code":"30",
    "gn:asciiname":"Dongyangwei",
    "gn:country_code":"CN",
    "gn:dem":40,
    "gn:feature_class":"P",
    "gn:feature_code":"PPL",
    "gn:name":"Dongyangwei",
    "gn:population":0,
    "gn:timezone":"Asia/Urumqi",
    "iso:country":"CN",
    "name:zho_x_preferred":[
        "\u4e1c\u6d0b\u5c3e"
    ],
    "wof:name":"Dongyangwei",
    "wof:placetype":"locality"
},
  "geometry": {"coordinates":[110.02248,20.96912],"type":"Point"}
}