{
  "type": "Feature",
  "properties": {
    "gn:admin1_code":"04",
    "gn:asciiname":"Hangxiang",
    "gn:country_code":"CN",
    "gn:dem":19,
    "gn:feature_class":"P",
    "gn:feature_code":"PPL",
    "gn:name":"Hangxiang",
    "gn:population":0,
    "gn:timezone":"Asia/Shanghai",
    "iso:country":"CN",
    "name:und_x_variant":[
        "Hsing-hsiang-chen",
        "Hang-hsiang",
        "Hang-hsiang-chen",
        "Hangxiang"
    ],
    "wof:name":"Hangxiang",
    "wof:placetype":"locality"
},
  "geometry": {"coordinates":[119.28937000000001,31.96596],"type":"Point"}
}