{
  "type": "Feature",
  "properties": {
    "gn:admin1_code":"19.0",
    "gn:asciiname":"Shazigang",
    "gn:country_code":"CN",
    "gn:dem":222,
    "gn:feature_class":"P",
    "gn:feature_code":"PPL",
    "gn:name":"Shazigang",
    "gn:population":0,
    "gn:timezone":"Asia/Shanghai",
    "iso:country":"CN",
    "name:und_x_variant":[
        "\u6c99\u5b50\u5c97"
    ],
    "name:zho_x_preferred":[
        "\u6c99\u5b50\u5c97"
    ],
    "wof:name":"Shazigang",
    "wof:placetype":"locality"
},
  "geometry": {"coordinates":[123.39879999999999,40.71943],"type":"Point"}
}