{
  "type": "Feature",
  "properties": {
    "gn:admin1_code":"16.0",
    "gn:asciiname":"Mahua",
    "gn:country_code":"CN",
    "gn:dem":862,
    "gn:feature_class":"P",
    "gn:feature_code":"PPL",
    "gn:name":"Mahua",
    "gn:population":0,
    "gn:timezone":"Asia/Shanghai",
    "iso:country":"CN",
    "name:zho_x_preferred":[
        "\u9a6c\u5316"
    ],
    "wof:name":"Mahua",
    "wof:placetype":"locality"
},
  "geometry": {"coordinates":[106.155,23.3594],"type":"Point"}
}