{
  "type": "Feature",
  "properties": {
    "gn:admin1_code":"2.0",
    "gn:asciiname":"Jinchangluo",
    "gn:country_code":"CN",
    "gn:dem":379,
    "gn:feature_class":"P",
    "gn:feature_code":"PPL",
    "gn:name":"Jinchangluo",
    "gn:population":0,
    "gn:timezone":"Asia/Shanghai",
    "iso:country":"CN",
    "name:zho_x_preferred":[
        "\u91d1\u83d6\u7f57"
    ],
    "wof:name":"Jinchangluo",
    "wof:placetype":"locality"
},
  "geometry": {"coordinates":[120.30783,28.20464],"type":"Point"}
}