{
  "type": "Feature",
  "properties": {
    "gn:admin1_code":"26.0",
    "gn:asciiname":"Diaozhongcun",
    "gn:country_code":"CN",
    "gn:dem":932,
    "gn:feature_class":"P",
    "gn:feature_code":"PPL",
    "gn:name":"Diaozhongcun",
    "gn:population":0,
    "gn:timezone":"Asia/Shanghai",
    "iso:country":"CN",
    "name:zho_x_preferred":[
        "\u540a\u949f\u6751"
    ],
    "wof:name":"Diaozhongcun",
    "wof:placetype":"locality"
},
  "geometry": {"coordinates":[108.16030000000001,32.58807],"type":"Point"}
}