{
  "type": "Feature",
  "properties": {
    "gn:admin1_code":"11.0",
    "gn:asciiname":"Gushurong",
    "gn:country_code":"CN",
    "gn:dem":270,
    "gn:feature_class":"P",
    "gn:feature_code":"PPL",
    "gn:name":"Gushurong",
    "gn:population":0,
    "gn:timezone":"Asia/Shanghai",
    "iso:country":"CN",
    "name:zho_x_preferred":[
        "\u53e4\u6811\u6eb6"
    ],
    "wof:name":"Gushurong",
    "wof:placetype":"locality"
},
  "geometry": {"coordinates":[110.23066,28.08415],"type":"Point"}
}