{
  "type": "Feature",
  "properties": {
    "gn:admin1_code":"29.0",
    "gn:asciiname":"Wozichang",
    "gn:country_code":"CN",
    "gn:dem":985,
    "gn:feature_class":"P",
    "gn:feature_code":"PPL",
    "gn:name":"Wozichang",
    "gn:population":0,
    "gn:timezone":"Asia/Shanghai",
    "iso:country":"CN",
    "name:zho_x_preferred":[
        "\u7a9d\u5b50\u573a"
    ],
    "wof:name":"Wozichang",
    "wof:placetype":"locality"
},
  "geometry": {"coordinates":[104.059,28.3072],"type":"Point"}
}