{
  "type": "Feature",
  "properties": {
    "gn:admin1_code":"8.0",
    "gn:asciiname":"Liqibei",
    "gn:country_code":"CN",
    "gn:dem":124,
    "gn:feature_class":"P",
    "gn:feature_code":"PPL",
    "gn:name":"Liqibei",
    "gn:population":0,
    "gn:timezone":"Asia/Shanghai",
    "iso:country":"CN",
    "name:zho_x_preferred":[
        "\u7acb\u65d7\u7891"
    ],
    "wof:name":"Liqibei",
    "wof:placetype":"locality"
},
  "geometry": {"coordinates":[125.82353999999999,45.59596],"type":"Point"}
}