{
  "type": "Feature",
  "properties": {
    "gn:admin1_code":"3.0",
    "gn:asciiname":"Dazhuang",
    "gn:country_code":"CN",
    "gn:dem":95,
    "gn:feature_class":"P",
    "gn:feature_code":"PPL",
    "gn:name":"Dazhuang",
    "gn:population":0,
    "gn:timezone":"Asia/Shanghai",
    "iso:country":"CN",
    "name:ceb_x_preferred":[
        "Dazhuang"
    ],
    "name:deu_x_preferred":[
        "Dazhuang"
    ],
    "name:swe_x_preferred":[
        "Dazhuang"
    ],
    "name:und_x_variant":[
        "\u5927\u5e84"
    ],
    "wof:name":"Dazhuang",
    "wof:placetype":"locality"
},
  "geometry": {"coordinates":[114.44753,27.76842000000001],"type":"Point"}
}