{
  "type": "Feature",
  "properties": {
    "gn:admin1_code":"29.0",
    "gn:asciiname":"Lizhishu",
    "gn:country_code":"CN",
    "gn:dem":1300,
    "gn:feature_class":"P",
    "gn:feature_code":"PPL",
    "gn:name":"Lizhishu",
    "gn:population":0,
    "gn:timezone":"Asia/Shanghai",
    "iso:country":"CN",
    "name:zho_x_preferred":[
        "\u674e\u652f\u6811"
    ],
    "wof:name":"Lizhishu",
    "wof:placetype":"locality"
},
  "geometry": {"coordinates":[101.253,23.4479],"type":"Point"}
}