{
  "type": "Feature",
  "properties": {
    "gn:admin1_code":"15.0",
    "gn:asciiname":"Zhujia Tunzhuang",
    "gn:country_code":"CN",
    "gn:dem":1322,
    "gn:feature_class":"P",
    "gn:feature_code":"PPL",
    "gn:name":"Zhujia Tunzhuang",
    "gn:population":0,
    "gn:timezone":"Asia/Shanghai",
    "iso:country":"CN",
    "name:zho_x_preferred":[
        "\u6731\u5bb6\u5c6f\u5e84"
    ],
    "wof:name":"Zhujia Tunzhuang",
    "wof:placetype":"locality"
},
  "geometry": {"coordinates":[108.164,35.4564],"type":"Point"}
}