{
  "type": "Feature",
  "properties": {
    "gn:admin1_code":"1.0",
    "gn:asciiname":"Xiyuan",
    "gn:country_code":"CN",
    "gn:dem":51,
    "gn:feature_class":"P",
    "gn:feature_code":"PPL",
    "gn:name":"Xiyuan",
    "gn:population":0,
    "gn:timezone":"Asia/Shanghai",
    "iso:country":"CN",
    "name:zho_x_preferred":[
        "\u516c\u5143"
    ],
    "wof:name":"Xiyuan",
    "wof:placetype":"locality"
},
  "geometry": {"coordinates":[117.05670000000001,31.19128],"type":"Point"}
}