{
  "type": "Feature",
  "properties": {
    "gn:admin1_code":"19.0",
    "gn:asciiname":"Wolongquanzi",
    "gn:country_code":"CN",
    "gn:dem":2,
    "gn:feature_class":"P",
    "gn:feature_code":"PPL",
    "gn:name":"Wolongquanzi",
    "gn:population":0,
    "gn:timezone":"Asia/Shanghai",
    "iso:country":"CN",
    "name:zho_x_preferred":[
        "\u5367\u9f99\u5708\u5b50"
    ],
    "wof:name":"Wolongquanzi",
    "wof:placetype":"locality"
},
  "geometry": {"coordinates":[121.92440000000001,41.22565],"type":"Point"}
}