{
  "type": "Feature",
  "properties": {
    "gn:admin1_code":"30.0",
    "gn:asciiname":"Xiamafang",
    "gn:country_code":"CN",
    "gn:dem":7,
    "gn:feature_class":"P",
    "gn:feature_code":"PPL",
    "gn:name":"Xiamafang",
    "gn:population":0,
    "gn:timezone":"Asia/Shanghai",
    "iso:country":"CN",
    "name:zho_x_preferred":[
        "\u4e0b\u9ebb\u653e"
    ],
    "wof:name":"Xiamafang",
    "wof:placetype":"locality"
},
  "geometry": {"coordinates":[111.89252999999999,21.91489],"type":"Point"}
}