{
  "type": "Feature",
  "properties": {
    "gn:admin1_code":"26.0",
    "gn:asciiname":"Baonanxiang",
    "gn:country_code":"CN",
    "gn:dem":514,
    "gn:feature_class":"P",
    "gn:feature_code":"PPL",
    "gn:name":"Baonanxiang",
    "gn:population":0,
    "gn:timezone":"Asia/Shanghai",
    "iso:country":"CN",
    "name:und_x_variant":[
        "\u4fdd\u5357\u4e61"
    ],
    "wof:name":"Baonanxiang",
    "wof:placetype":"locality"
},
  "geometry": {"coordinates":[109.65971999999999,35.00808],"type":"Point"}
}