{
  "type": "Feature",
  "properties": {
    "gn:admin1_code":"6.0",
    "gn:asciiname":"Jilai",
    "gn:country_code":"CN",
    "gn:dem":3946,
    "gn:feature_class":"P",
    "gn:feature_code":"PPL",
    "gn:name":"Jilai",
    "gn:population":0,
    "gn:timezone":"Asia/Urumqi",
    "iso:country":"CN",
    "name:zho_x_preferred":[
        "\u5409\u6765"
    ],
    "wof:name":"Jilai",
    "wof:placetype":"locality"
},
  "geometry": {"coordinates":[95.78261999999999,32.11736],"type":"Point"}
}