{
  "type": "Feature",
  "properties": {
    "gn:admin1_code":"29.0",
    "gn:asciiname":"Xinglongzhai",
    "gn:country_code":"CN",
    "gn:dem":1365,
    "gn:feature_class":"P",
    "gn:feature_code":"PPL",
    "gn:name":"Xinglongzhai",
    "gn:population":0,
    "gn:timezone":"Asia/Shanghai",
    "iso:country":"CN",
    "name:zho_x_preferred":[
        "\u5174\u9686\u5be8"
    ],
    "wof:name":"Xinglongzhai",
    "wof:placetype":"locality"
},
  "geometry": {"coordinates":[98.2736,24.6634],"type":"Point"}
}