{
  "type": "Feature",
  "properties": {
    "gn:admin1_code":"3.0",
    "gn:asciiname":"Songshulin",
    "gn:country_code":"CN",
    "gn:dem":569,
    "gn:feature_class":"P",
    "gn:feature_code":"PPL",
    "gn:name":"Songshulin",
    "gn:population":0,
    "gn:timezone":"Asia/Shanghai",
    "iso:country":"CN",
    "name:und_x_variant":[
        "\u677e\u6811\u6797"
    ],
    "wof:name":"Songshulin",
    "wof:placetype":"locality"
},
  "geometry": {"coordinates":[116.02346,29.61424],"type":"Point"}
}