{
  "type": "Feature",
  "properties": {
    "gn:admin1_code":"15.0",
    "gn:asciiname":"Xiaba",
    "gn:country_code":"CN",
    "gn:dem":896,
    "gn:feature_class":"P",
    "gn:feature_code":"PPL",
    "gn:name":"Xiaba",
    "gn:population":0,
    "gn:timezone":"Asia/Shanghai",
    "iso:country":"CN",
    "name:und_x_variant":[
        "\u4e0b\u575d"
    ],
    "wof:name":"Xiaba",
    "wof:placetype":"locality"
},
  "geometry": {"coordinates":[105.76026,32.99766],"type":"Point"}
}