{
  "type": "Feature",
  "properties": {
    "gn:admin1_code":"1.0",
    "gn:asciiname":"Tanlincun",
    "gn:country_code":"CN",
    "gn:dem":54,
    "gn:feature_class":"P",
    "gn:feature_code":"PPL",
    "gn:name":"Tanlincun",
    "gn:population":0,
    "gn:timezone":"Asia/Shanghai",
    "iso:country":"CN",
    "name:zho_x_preferred":[
        "\u6a80\u6797\u6751"
    ],
    "wof:name":"Tanlincun",
    "wof:placetype":"locality"
},
  "geometry": {"coordinates":[117.40586,30.34746],"type":"Point"}
}