{
  "type": "Feature",
  "properties": {
    "gn:admin1_code":"32.0",
    "gn:asciiname":"Ansigou",
    "gn:country_code":"CN",
    "gn:dem":475,
    "gn:feature_class":"P",
    "gn:feature_code":"PPL",
    "gn:name":"Ansigou",
    "gn:population":0,
    "gn:timezone":"Asia/Shanghai",
    "iso:country":"CN",
    "name:zho_x_preferred":[
        "\u978d\u5bfa\u6c9f"
    ],
    "wof:name":"Ansigou",
    "wof:placetype":"locality"
},
  "geometry": {"coordinates":[105.01096,30.94332],"type":"Point"}
}