{
  "type": "Feature",
  "properties": {
    "gn:admin1_code":"15.0",
    "gn:asciiname":"Ruolong",
    "gn:country_code":"CN",
    "gn:dem":2544,
    "gn:feature_class":"P",
    "gn:feature_code":"PPL",
    "gn:name":"Ruolong",
    "gn:population":0,
    "gn:timezone":"Asia/Shanghai",
    "iso:country":"CN",
    "name:und_x_variant":[
        "\u82e5\u9f99"
    ],
    "wof:name":"Ruolong",
    "wof:placetype":"locality"
},
  "geometry": {"coordinates":[103.68061,34.5198],"type":"Point"}
}