{
  "type": "Feature",
  "properties": {
    "gn:admin1_code":"12.0",
    "gn:asciiname":"Banzhuwan",
    "gn:country_code":"CN",
    "gn:dem":1057,
    "gn:feature_class":"P",
    "gn:feature_code":"PPL",
    "gn:name":"Banzhuwan",
    "gn:population":0,
    "gn:timezone":"Asia/Shanghai",
    "iso:country":"CN",
    "name:zho_x_preferred":[
        "Banzhuwan"
    ],
    "name:zho_x_variant":[
        "\u6591\u7af9\u6e7e"
    ],
    "wof:name":"Banzhuwan",
    "wof:placetype":"locality"
},
  "geometry": {"coordinates":[110.11577,30.07188],"type":"Point"}
}