{
  "type": "Feature",
  "properties": {
    "gn:admin1_code":"03",
    "gn:asciiname":"Haikou",
    "gn:country_code":"CN",
    "gn:dem":64,
    "gn:feature_class":"P",
    "gn:feature_code":"PPLA4",
    "gn:name":"Haikou",
    "gn:population":0,
    "gn:timezone":"Asia/Shanghai",
    "iso:country":"CN",
    "name:und_x_variant":[
        "Hai-k\u2019ou-shih",
        "Haikou",
        "\u6d77\u53e3",
        "Haikou Zhen",
        "\u6d77\u53e3\u9547"
    ],
    "wof:name":"Haikou",
    "wof:placetype":"locality"
},
  "geometry": {"coordinates":[117.80736,29.10682000000001],"type":"Point"}
}