{
  "type": "Feature",
  "properties": {
    "gn:admin1_code":"32",
    "gn:asciiname":"Mosuoying",
    "gn:cc2":"CN",
    "gn:country_code":"CN",
    "gn:dem":1269,
    "gn:feature_class":"P",
    "gn:feature_code":"PPL",
    "gn:name":"Mosuoying",
    "gn:population":0,
    "gn:timezone":"Asia/Shanghai",
    "iso:country":"CN",
    "name:und_x_variant":[
        "Mo-so-ying",
        "Mosuoying"
    ],
    "wof:name":"Mosuoying",
    "wof:placetype":"locality"
},
  "geometry": {"coordinates":[102.25028,27.06778],"type":"Point"}
}