{
  "type": "Feature",
  "properties": {
    "gn:admin1_code":"11.0",
    "gn:asciiname":"Zhuangchaibu",
    "gn:country_code":"CN",
    "gn:dem":58,
    "gn:feature_class":"P",
    "gn:feature_code":"PPL",
    "gn:name":"Zhuangchaibu",
    "gn:population":0,
    "gn:timezone":"Asia/Shanghai",
    "iso:country":"CN",
    "name:zho_x_preferred":[
        "\u88c5\u67f4\u57e0"
    ],
    "wof:name":"Zhuangchaibu",
    "wof:placetype":"locality"
},
  "geometry": {"coordinates":[112.10442,28.56642],"type":"Point"}
}