{
  "type": "Feature",
  "properties": {
    "gn:admin1_code":"14.0",
    "gn:asciiname":"Guote",
    "gn:country_code":"CN",
    "gn:dem":3723,
    "gn:feature_class":"P",
    "gn:feature_code":"PPL",
    "gn:name":"Guote",
    "gn:population":0,
    "gn:timezone":"Asia/Urumqi",
    "iso:country":"CN",
    "name:zho_x_preferred":[
        "\u679c\u7279"
    ],
    "wof:name":"Guote",
    "wof:placetype":"locality"
},
  "geometry": {"coordinates":[97.08138,31.60473],"type":"Point"}
}