{
  "type": "Feature",
  "properties": {
    "gn:admin1_code":"5.0",
    "gn:asciiname":"Beijiushan",
    "gn:country_code":"CN",
    "gn:dem":250,
    "gn:feature_class":"P",
    "gn:feature_code":"PPL",
    "gn:name":"Beijiushan",
    "gn:population":0,
    "gn:timezone":"Asia/Shanghai",
    "iso:country":"CN",
    "name:zho_x_preferred":[
        "\u5317\u4e5d\u5c71"
    ],
    "wof:name":"Beijiushan",
    "wof:placetype":"locality"
},
  "geometry": {"coordinates":[127.00136999999999,44.41816],"type":"Point"}
}