{
  "type": "Feature",
  "properties": {
    "gn:admin1_code":"29.0",
    "gn:asciiname":"Dasongshan",
    "gn:country_code":"CN",
    "gn:dem":2123,
    "gn:feature_class":"P",
    "gn:feature_code":"PPL",
    "gn:name":"Dasongshan",
    "gn:population":0,
    "gn:timezone":"Asia/Shanghai",
    "iso:country":"CN",
    "name:zho_x_preferred":[
        "\u5927\u677e\u5c71"
    ],
    "wof:name":"Dasongshan",
    "wof:placetype":"locality"
},
  "geometry": {"coordinates":[103.907,26.2372],"type":"Point"}
}