{
  "type": "Feature",
  "properties": {
    "gn:admin1_code":"10.0",
    "gn:asciiname":"Fumazhai",
    "gn:country_code":"CN",
    "gn:dem":33,
    "gn:feature_class":"P",
    "gn:feature_code":"PPL",
    "gn:name":"Fumazhai",
    "gn:population":0,
    "gn:timezone":"Asia/Shanghai",
    "iso:country":"CN",
    "name:zho_x_preferred":[
        "\u9a78\u9a6c\u5be8"
    ],
    "wof:name":"Fumazhai",
    "wof:placetype":"locality"
},
  "geometry": {"coordinates":[119.32855000000001,39.945],"type":"Point"}
}