{
  "type": "Feature",
  "properties": {
    "gn:admin1_code":"13",
    "gn:asciiname":"Ku'erma",
    "gn:country_code":"CN",
    "gn:dem":1030,
    "gn:feature_class":"P",
    "gn:feature_code":"PPL",
    "gn:name":"Ku\u2019erma",
    "gn:population":0,
    "gn:timezone":"Asia/Shanghai",
    "iso:country":"CN",
    "name:und_x_variant":[
        "Ku\u2019erma",
        "\u5e93\u5c14\u739b"
    ],
    "wof:name":"Ku'erma",
    "wof:placetype":"locality"
},
  "geometry": {"coordinates":[80.75577,40.47589],"type":"Point"}
}