{
  "type": "Feature",
  "properties": {
    "gn:admin1_code":"29.0",
    "gn:asciiname":"Taiping",
    "gn:country_code":"CN",
    "gn:dem":956,
    "gn:feature_class":"P",
    "gn:feature_code":"PPL",
    "gn:name":"Taiping",
    "gn:population":0,
    "gn:timezone":"Asia/Shanghai",
    "iso:country":"CN",
    "name:ceb_x_preferred":[
        "Taiping"
    ],
    "name:deu_x_preferred":[
        "Taiping"
    ],
    "name:fra_x_preferred":[
        "Taiping"
    ],
    "name:hun_x_preferred":[
        "Taiping"
    ],
    "name:ind_x_preferred":[
        "Taiping"
    ],
    "name:msa_x_preferred":[
        "Taiping"
    ],
    "name:nld_x_preferred":[
        "Taiping"
    ],
    "name:rus_x_preferred":[
        "\u0422\u0430\u0439\u043f\u0438\u043d"
    ],
    "name:swe_x_preferred":[
        "Taiping"
    ],
    "name:und_x_variant":[
        "\u592a\u5e73"
    ],
    "wof:name":"Taiping",
    "wof:placetype":"locality"
},
  "geometry": {"coordinates":[103.10157,26.37639],"type":"Point"}
}