{
  "type": "Feature",
  "properties": {
    "gn:admin1_code":"11.0",
    "gn:asciiname":"Tanggongmiao",
    "gn:country_code":"CN",
    "gn:dem":153,
    "gn:feature_class":"P",
    "gn:feature_code":"PPL",
    "gn:name":"Tanggongmiao",
    "gn:population":0,
    "gn:timezone":"Asia/Shanghai",
    "iso:country":"CN",
    "name:zho_x_preferred":[
        "\u5510\u516c\u5e99"
    ],
    "wof:name":"Tanggongmiao",
    "wof:placetype":"locality"
},
  "geometry": {"coordinates":[113.16078,26.24893],"type":"Point"}
}