{
  "type": "Feature",
  "properties": {
    "gn:admin1_code":"05",
    "gn:asciiname":"Wanfa",
    "gn:cc2":"CN",
    "gn:country_code":"CN",
    "gn:dem":189,
    "gn:feature_class":"P",
    "gn:feature_code":"PPL",
    "gn:name":"Wanfa",
    "gn:population":0,
    "gn:timezone":"Asia/Shanghai",
    "iso:country":"CN",
    "name:und_x_variant":[
        "Wan-fa-chieh",
        "Wanfa"
    ],
    "wof:name":"Wanfa",
    "wof:placetype":"locality"
},
  "geometry": {"coordinates":[125.53333000000001,45.06667],"type":"Point"}
}