{
  "type": "Feature",
  "properties": {
    "gn:admin1_code":"4.0",
    "gn:asciiname":"Dashenjia",
    "gn:country_code":"CN",
    "gn:dem":8,
    "gn:feature_class":"P",
    "gn:feature_code":"PPL",
    "gn:name":"Dashenjia",
    "gn:population":0,
    "gn:timezone":"Asia/Shanghai",
    "iso:country":"CN",
    "name:zho_x_preferred":[
        "\u5927\u6c88\u5bb6"
    ],
    "wof:name":"Dashenjia",
    "wof:placetype":"locality"
},
  "geometry": {"coordinates":[119.76591999999999,31.63271],"type":"Point"}
}