{
  "type": "Feature",
  "properties": {
    "gn:admin1_code":"11.0",
    "gn:asciiname":"Baidouxi",
    "gn:country_code":"CN",
    "gn:dem":191,
    "gn:feature_class":"P",
    "gn:feature_code":"PPL",
    "gn:name":"Baidouxi",
    "gn:population":0,
    "gn:timezone":"Asia/Shanghai",
    "iso:country":"CN",
    "name:zho_x_preferred":[
        "\u767d\u6597\u6eaa"
    ],
    "wof:name":"Baidouxi",
    "wof:placetype":"locality"
},
  "geometry": {"coordinates":[110.56309,28.63738],"type":"Point"}
}