{
  "type": "Feature",
  "properties": {
    "gn:admin1_code":"07",
    "gn:asciiname":"Duobaoshi",
    "gn:country_code":"CN",
    "gn:dem":391,
    "gn:feature_class":"P",
    "gn:feature_code":"PPL",
    "gn:name":"Duobaoshi",
    "gn:population":0,
    "gn:timezone":"Asia/Shanghai",
    "iso:country":"CN",
    "name:zho_x_preferred":[
        "\u591a\u5b9d\u77f3"
    ],
    "wof:name":"Duobaoshi",
    "wof:placetype":"locality"
},
  "geometry": {"coordinates":[116.36835000000001,24.84166],"type":"Point"}
}