{
  "type": "Feature",
  "properties": {
    "gn:admin1_code":"3.0",
    "gn:asciiname":"Beixi",
    "gn:country_code":"CN",
    "gn:dem":211,
    "gn:feature_class":"P",
    "gn:feature_code":"PPL",
    "gn:name":"Beixi",
    "gn:population":0,
    "gn:timezone":"Asia/Shanghai",
    "iso:country":"CN",
    "name:zho_x_preferred":[
        "\u9642\u6eaa"
    ],
    "wof:name":"Beixi",
    "wof:placetype":"locality"
},
  "geometry": {"coordinates":[115.56100000000001,26.3987],"type":"Point"}
}