{
  "type": "Feature",
  "properties": {
    "gn:admin1_code":"12.0",
    "gn:asciiname":"Shizitan",
    "gn:country_code":"CN",
    "gn:dem":489,
    "gn:feature_class":"P",
    "gn:feature_code":"PPL",
    "gn:name":"Shizitan",
    "gn:population":0,
    "gn:timezone":"Asia/Shanghai",
    "iso:country":"CN",
    "name:zho_x_preferred":[
        "\u72ee\u5b50\u6f6d"
    ],
    "wof:name":"Shizitan",
    "wof:placetype":"locality"
},
  "geometry": {"coordinates":[110.82572999999999,32.06953],"type":"Point"}
}