{
  "type": "Feature",
  "properties": {
    "gn:admin1_code":"16",
    "gn:asciiname":"Qingjiangtian",
    "gn:country_code":"CN",
    "gn:dem":242,
    "gn:feature_class":"P",
    "gn:feature_code":"PPL",
    "gn:name":"Qingjiangtian",
    "gn:population":0,
    "gn:timezone":"Asia/Shanghai",
    "iso:country":"CN",
    "name:zho_x_preferred":[
        "\u6e05\u6c5f\u7530"
    ],
    "wof:name":"Qingjiangtian",
    "wof:placetype":"locality"
},
  "geometry": {"coordinates":[110.504,25.3502],"type":"Point"}
}