{
  "type": "Feature",
  "properties": {
    "gn:admin1_code":"12.0",
    "gn:asciiname":"Liangjiazhai",
    "gn:country_code":"CN",
    "gn:dem":172,
    "gn:feature_class":"P",
    "gn:feature_code":"PPL",
    "gn:name":"Liangjiazhai",
    "gn:population":0,
    "gn:timezone":"Asia/Shanghai",
    "iso:country":"CN",
    "name:zho_x_preferred":[
        "\u6881\u5bb6\u5be8"
    ],
    "wof:name":"Liangjiazhai",
    "wof:placetype":"locality"
},
  "geometry": {"coordinates":[111.05915,32.53933],"type":"Point"}
}