{
  "type": "Feature",
  "properties": {
    "gn:admin1_code":"14",
    "gn:asciiname":"Jiuruo",
    "gn:country_code":"CN",
    "gn:dem":4063,
    "gn:feature_class":"P",
    "gn:feature_code":"PPL",
    "gn:name":"Jiuruo",
    "gn:population":0,
    "gn:timezone":"Asia/Urumqi",
    "iso:country":"CN",
    "name:zho_x_preferred":[
        "\u4e45\u82e5"
    ],
    "wof:name":"Jiuruo",
    "wof:placetype":"locality"
},
  "geometry": {"coordinates":[88.2735,29.4146],"type":"Point"}
}