{
  "type": "Feature",
  "properties": {
    "gn:admin1_code":"19.0",
    "gn:asciiname":"Xiheyancun",
    "gn:country_code":"CN",
    "gn:dem":17,
    "gn:feature_class":"P",
    "gn:feature_code":"PPL",
    "gn:name":"Xiheyancun",
    "gn:population":0,
    "gn:timezone":"Asia/Shanghai",
    "iso:country":"CN",
    "name:zho_x_preferred":[
        "\u7ec6\u6cb3\u6cbf\u6751"
    ],
    "wof:name":"Xiheyancun",
    "wof:placetype":"locality"
},
  "geometry": {"coordinates":[122.77670999999999,41.59479],"type":"Point"}
}