{
  "type": "Feature",
  "properties": {
    "gn:admin1_code":"12.0",
    "gn:asciiname":"Hengdian",
    "gn:country_code":"CN",
    "gn:dem":240,
    "gn:feature_class":"P",
    "gn:feature_code":"PPL",
    "gn:name":"Hengdian",
    "gn:population":0,
    "gn:timezone":"Asia/Shanghai",
    "iso:country":"CN",
    "name:swe_x_preferred":[
        "Hengdian"
    ],
    "name:zho_x_preferred":[
        "\u6a2a\u5e97"
    ],
    "wof:name":"Hengdian",
    "wof:placetype":"locality"
},
  "geometry": {"coordinates":[111.75555,31.10756],"type":"Point"}
}