{
  "type": "Feature",
  "properties": {
    "gn:admin1_code":"24.0",
    "gn:asciiname":"Wangxuezhuangcun",
    "gn:country_code":"CN",
    "gn:dem":531,
    "gn:feature_class":"P",
    "gn:feature_code":"PPL",
    "gn:name":"Wangxuezhuangcun",
    "gn:population":0,
    "gn:timezone":"Asia/Shanghai",
    "iso:country":"CN",
    "name:zho_x_preferred":[
        "\u738b\u859b\u5e84\u6751"
    ],
    "wof:name":"Wangxuezhuangcun",
    "wof:placetype":"locality"
},
  "geometry": {"coordinates":[110.85408,35.25142],"type":"Point"}
}