{
  "type": "Feature",
  "properties": {
    "gn:admin1_code":"3.0",
    "gn:asciiname":"Yaocun",
    "gn:country_code":"CN",
    "gn:dem":251,
    "gn:feature_class":"P",
    "gn:feature_code":"PPL",
    "gn:name":"Yaocun",
    "gn:population":0,
    "gn:timezone":"Asia/Shanghai",
    "iso:country":"CN",
    "name:und_x_variant":[
        "\u7a91\u6751"
    ],
    "wof:name":"Yaocun",
    "wof:placetype":"locality"
},
  "geometry": {"coordinates":[114.79173,28.902],"type":"Point"}
}