{
  "type": "Feature",
  "properties": {
    "gn:admin1_code":"10",
    "gn:asciiname":"T'ien-chia-ying-tzu",
    "gn:country_code":"CN",
    "gn:dem":1268,
    "gn:feature_class":"P",
    "gn:feature_code":"PPL",
    "gn:name":"T\u2019ien-chia-ying-tzu",
    "gn:population":0,
    "gn:timezone":"Asia/Shanghai",
    "iso:country":"CN",
    "wof:name":"T'ien-chia-ying-tzu",
    "wof:placetype":"locality"
},
  "geometry": {"coordinates":[116.23222,41.36167],"type":"Point"}
}