{
  "type": "Feature",
  "properties": {
    "gn:admin1_code":"19.0",
    "gn:asciiname":"Xixiaomozi",
    "gn:country_code":"CN",
    "gn:dem":7,
    "gn:feature_class":"P",
    "gn:feature_code":"PPL",
    "gn:name":"Xixiaomozi",
    "gn:population":0,
    "gn:timezone":"Asia/Shanghai",
    "iso:country":"CN",
    "name:und_x_variant":[
        "\u897f\u5c0f\u78e8\u5b50"
    ],
    "name:zho_x_preferred":[
        "\u897f\u5c0f\u78e8\u5b50"
    ],
    "wof:name":"Xixiaomozi",
    "wof:placetype":"locality"
},
  "geometry": {"coordinates":[121.3515,38.98734],"type":"Point"}
}