{
  "type": "Feature",
  "properties": {
    "gn:admin1_code":"1.0",
    "gn:asciiname":"Baohecun",
    "gn:country_code":"CN",
    "gn:dem":47,
    "gn:feature_class":"P",
    "gn:feature_code":"PPL",
    "gn:name":"Baohecun",
    "gn:population":0,
    "gn:timezone":"Asia/Shanghai",
    "iso:country":"CN",
    "name:zho_x_preferred":[
        "\u9c8d\u6cb3\u6751"
    ],
    "wof:name":"Baohecun",
    "wof:placetype":"locality"
},
  "geometry": {"coordinates":[116.85657999999999,31.87336],"type":"Point"}
}