{
  "type": "Feature",
  "properties": {
    "gn:admin1_code":"26.0",
    "gn:asciiname":"Leijiadongcun",
    "gn:country_code":"CN",
    "gn:dem":419,
    "gn:feature_class":"P",
    "gn:feature_code":"PPL",
    "gn:name":"Leijiadongcun",
    "gn:population":0,
    "gn:timezone":"Asia/Shanghai",
    "iso:country":"CN",
    "name:zho_x_preferred":[
        "\u96f7\u5bb6\u6d1e\u6751"
    ],
    "wof:name":"Leijiadongcun",
    "wof:placetype":"locality"
},
  "geometry": {"coordinates":[110.46716000000001,33.46133],"type":"Point"}
}