{
  "type": "Feature",
  "properties": {
    "gn:admin1_code":"32.0",
    "gn:asciiname":"Riji",
    "gn:country_code":"CN",
    "gn:dem":3034,
    "gn:feature_class":"P",
    "gn:feature_code":"PPL",
    "gn:name":"Riji",
    "gn:population":0,
    "gn:timezone":"Asia/Shanghai",
    "iso:country":"CN",
    "name:zho_x_preferred":[
        "\u65e5\u57fa"
    ],
    "wof:name":"Riji",
    "wof:placetype":"locality"
},
  "geometry": {"coordinates":[101.17100000000001,30.07],"type":"Point"}
}