{
  "type": "Feature",
  "properties": {
    "gn:admin1_code":"5.0",
    "gn:asciiname":"Housandao Linzi",
    "gn:country_code":"CN",
    "gn:dem":230,
    "gn:feature_class":"P",
    "gn:feature_code":"PPL",
    "gn:name":"Housandao Linzi",
    "gn:population":0,
    "gn:timezone":"Asia/Shanghai",
    "iso:country":"CN",
    "name:zho_x_preferred":[
        "\u540e\u4e09\u9053\u6797\u5b50"
    ],
    "wof:name":"Housandao Linzi",
    "wof:placetype":"locality"
},
  "geometry": {"coordinates":[125.99074,44.25285],"type":"Point"}
}