{
  "type": "Feature",
  "properties": {
    "gn:admin1_code":"32.0",
    "gn:asciiname":"Zuobi",
    "gn:country_code":"CN",
    "gn:dem":2304,
    "gn:feature_class":"P",
    "gn:feature_code":"PPL",
    "gn:name":"Zuobi",
    "gn:population":0,
    "gn:timezone":"Asia/Shanghai",
    "iso:country":"CN",
    "name:zho_x_preferred":[
        "\u5de6\u6bd4"
    ],
    "wof:name":"Zuobi",
    "wof:placetype":"locality"
},
  "geometry": {"coordinates":[101.94,30.8578],"type":"Point"}
}