{
  "type": "Feature",
  "properties": {
    "gn:admin1_code":"33.0",
    "gn:asciiname":"Dafenshan",
    "gn:country_code":"CN",
    "gn:dem":374,
    "gn:feature_class":"P",
    "gn:feature_code":"PPL",
    "gn:name":"Dafenshan",
    "gn:population":0,
    "gn:timezone":"Asia/Shanghai",
    "iso:country":"CN",
    "name:zho_x_preferred":[
        "\u5927\u575f\u5c71"
    ],
    "wof:name":"Dafenshan",
    "wof:placetype":"locality"
},
  "geometry": {"coordinates":[108.95349,28.44283],"type":"Point"}
}