{
  "type": "Feature",
  "properties": {
    "gn:admin1_code":"16.0",
    "gn:asciiname":"Poyuan",
    "gn:country_code":"CN",
    "gn:dem":531,
    "gn:feature_class":"P",
    "gn:feature_code":"PPL",
    "gn:name":"Poyuan",
    "gn:population":0,
    "gn:timezone":"Asia/Shanghai",
    "iso:country":"CN",
    "name:zho_x_preferred":[
        "\u5761\u5143"
    ],
    "wof:name":"Poyuan",
    "wof:placetype":"locality"
},
  "geometry": {"coordinates":[106.97,23.1721],"type":"Point"}
}