{
  "type": "Feature",
  "properties": {
    "gn:admin1_code":"19.0",
    "gn:asciiname":"Qiancailiyingzi",
    "gn:country_code":"CN",
    "gn:dem":110,
    "gn:feature_class":"P",
    "gn:feature_code":"PPL",
    "gn:name":"Qiancailiyingzi",
    "gn:population":0,
    "gn:timezone":"Asia/Shanghai",
    "iso:country":"CN",
    "name:zho_x_preferred":[
        "\u524d\u624d\u91cc\u8425\u5b50"
    ],
    "wof:name":"Qiancailiyingzi",
    "wof:placetype":"locality"
},
  "geometry": {"coordinates":[121.58,41.791],"type":"Point"}
}