{
  "type": "Feature",
  "properties": {
    "gn:admin1_code":"30.0",
    "gn:asciiname":"Jingduli",
    "gn:country_code":"CN",
    "gn:dem":223,
    "gn:feature_class":"P",
    "gn:feature_code":"PPL",
    "gn:name":"Jingduli",
    "gn:population":0,
    "gn:timezone":"Asia/Shanghai",
    "iso:country":"CN",
    "name:zho_x_preferred":[
        "Jingduli"
    ],
    "name:zho_x_variant":[
        "\u5f84\u809a\u91cc"
    ],
    "wof:name":"Jingduli",
    "wof:placetype":"locality"
},
  "geometry": {"coordinates":[115.25444,24.49583],"type":"Point"}
}