{
  "type": "Feature",
  "properties": {
    "gn:admin1_code":"11",
    "gn:asciiname":"Baosi'ao",
    "gn:country_code":"CN",
    "gn:dem":549,
    "gn:feature_class":"P",
    "gn:feature_code":"PPL",
    "gn:name":"Baosi\u2019ao",
    "gn:population":0,
    "gn:timezone":"Asia/Shanghai",
    "iso:country":"CN",
    "name:und_x_variant":[
        "Baosi\u2019ao"
    ],
    "name:zho_x_preferred":[
        "\u5b9d\u56db\u5773"
    ],
    "wof:name":"Baosi'ao",
    "wof:placetype":"locality"
},
  "geometry": {"coordinates":[111.44492,27.82714],"type":"Point"}
}