{
  "type": "Feature",
  "properties": {
    "gn:admin1_code":"18.0",
    "gn:asciiname":"Xinglong",
    "gn:country_code":"CN",
    "gn:dem":887,
    "gn:feature_class":"P",
    "gn:feature_code":"PPL",
    "gn:name":"Xinglong",
    "gn:population":0,
    "gn:timezone":"Asia/Shanghai",
    "iso:country":"CN",
    "wof:name":"Xinglong",
    "wof:placetype":"locality"
},
  "geometry": {"coordinates":[107.23333,27.98333],"type":"Point"}
}