{
  "type": "Feature",
  "properties": {
    "gn:admin1_code":"15.0",
    "gn:asciiname":"Qianjian",
    "gn:country_code":"CN",
    "gn:dem":1593,
    "gn:feature_class":"P",
    "gn:feature_code":"PPL",
    "gn:name":"Qianjian",
    "gn:population":0,
    "gn:timezone":"Asia/Shanghai",
    "iso:country":"CN",
    "name:und_x_variant":[
        "\u524d\u7877"
    ],
    "wof:name":"Qianjian",
    "wof:placetype":"locality"
},
  "geometry": {"coordinates":[107.29485,36.69011],"type":"Point"}
}