{
  "type": "Feature",
  "properties": {
    "gn:admin1_code":"3.0",
    "gn:asciiname":"Tudijiao",
    "gn:country_code":"CN",
    "gn:dem":191,
    "gn:feature_class":"P",
    "gn:feature_code":"PPL",
    "gn:name":"Tudijiao",
    "gn:population":0,
    "gn:timezone":"Asia/Shanghai",
    "iso:country":"CN",
    "name:und_x_variant":[
        "\u571f\u5730\u89d2"
    ],
    "wof:name":"Tudijiao",
    "wof:placetype":"locality"
},
  "geometry": {"coordinates":[115.96046,26.31676],"type":"Point"}
}