{
  "type": "Feature",
  "properties": {
    "gn:admin1_code":"2.0",
    "gn:asciiname":"Wuchang",
    "gn:country_code":"CN",
    "gn:dem":7,
    "gn:feature_class":"P",
    "gn:feature_code":"PPL",
    "gn:name":"Wuchang",
    "gn:population":0,
    "gn:timezone":"Asia/Shanghai",
    "iso:country":"CN",
    "name:und_x_variant":[
        "\u4e94\u5e38",
        "Wuchangxiang",
        "\u4e94\u5e38\u4e61"
    ],
    "wof:name":"Wuchang",
    "wof:placetype":"locality"
},
  "geometry": {"coordinates":[120.03524,30.26259000000001],"type":"Point"}
}