{
  "type": "Feature",
  "properties": {
    "gn:admin1_code":"26.0",
    "gn:asciiname":"Taopingcun",
    "gn:country_code":"CN",
    "gn:dem":1618,
    "gn:feature_class":"P",
    "gn:feature_code":"PPL",
    "gn:name":"Taopingcun",
    "gn:population":0,
    "gn:timezone":"Asia/Shanghai",
    "iso:country":"CN",
    "name:zho_x_preferred":[
        "\u6843\u576a\u6751"
    ],
    "wof:name":"Taopingcun",
    "wof:placetype":"locality"
},
  "geometry": {"coordinates":[110.10747000000001,34.40835],"type":"Point"}
}