{
  "type": "Feature",
  "properties": {
    "gn:admin1_code":"5.0",
    "gn:asciiname":"Quandebu",
    "gn:country_code":"CN",
    "gn:dem":240,
    "gn:feature_class":"P",
    "gn:feature_code":"PPL",
    "gn:name":"Quandebu",
    "gn:population":0,
    "gn:timezone":"Asia/Shanghai",
    "iso:country":"CN",
    "name:zho_x_preferred":[
        "\u5168\u5fb7\u5821"
    ],
    "wof:name":"Quandebu",
    "wof:placetype":"locality"
},
  "geometry": {"coordinates":[126.99484,44.50482],"type":"Point"}
}