{
  "type": "Feature",
  "properties": {
    "gn:admin1_code":"26.0",
    "gn:asciiname":"Qujiacun",
    "gn:country_code":"CN",
    "gn:dem":349,
    "gn:feature_class":"P",
    "gn:feature_code":"PPL",
    "gn:name":"Qujiacun",
    "gn:population":0,
    "gn:timezone":"Asia/Shanghai",
    "iso:country":"CN",
    "name:zho_x_preferred":[
        "\u5c48\u5bb6\u6751"
    ],
    "wof:name":"Qujiacun",
    "wof:placetype":"locality"
},
  "geometry": {"coordinates":[110.06690999999999,34.56594],"type":"Point"}
}