{
  "type": "Feature",
  "properties": {
    "gn:admin1_code":"7.0",
    "gn:asciiname":"Chentian",
    "gn:country_code":"CN",
    "gn:dem":499,
    "gn:feature_class":"P",
    "gn:feature_code":"PPL",
    "gn:name":"Chentian",
    "gn:population":0,
    "gn:timezone":"Asia/Shanghai",
    "iso:country":"CN",
    "name:zho_x_preferred":[
        "\u9648\u7530"
    ],
    "wof:name":"Chentian",
    "wof:placetype":"locality"
},
  "geometry": {"coordinates":[116.20589,25.07288],"type":"Point"}
}