{
  "type": "Feature",
  "properties": {
    "gn:admin1_code":"30",
    "gn:asciiname":"Wentang",
    "gn:country_code":"CN",
    "gn:dem":136,
    "gn:feature_class":"P",
    "gn:feature_code":"PPL",
    "gn:name":"Wentang",
    "gn:population":0,
    "gn:timezone":"Asia/Shanghai",
    "iso:country":"CN",
    "name:zho_x_preferred":[
        "\u6c76\u5858"
    ],
    "wof:name":"Wentang",
    "wof:placetype":"locality"
},
  "geometry": {"coordinates":[112.29116,24.02987000000001],"type":"Point"}
}