{
  "type": "Feature",
  "properties": {
    "gn:admin1_code":"3.0",
    "gn:asciiname":"Laozhushan",
    "gn:country_code":"CN",
    "gn:dem":239,
    "gn:feature_class":"P",
    "gn:feature_code":"PPL",
    "gn:name":"Laozhushan",
    "gn:population":0,
    "gn:timezone":"Asia/Shanghai",
    "iso:country":"CN",
    "name:und_x_variant":[
        "\u8001\u732a\u5c71"
    ],
    "wof:name":"Laozhushan",
    "wof:placetype":"locality"
},
  "geometry": {"coordinates":[114.28852999999999,28.83244],"type":"Point"}
}