{
  "type": "Feature",
  "properties": {
    "gn:admin1_code":"25",
    "gn:asciiname":"Tankouji",
    "gn:country_code":"CN",
    "gn:dem":35,
    "gn:feature_class":"P",
    "gn:feature_code":"PPL",
    "gn:name":"Tankouji",
    "gn:population":0,
    "gn:timezone":"Asia/Shanghai",
    "iso:country":"CN",
    "name:zho_x_preferred":[
        "\u8c2d\u53e3\u96c6"
    ],
    "wof:name":"Tankouji",
    "wof:placetype":"locality"
},
  "geometry": {"coordinates":[116.452,35.2027],"type":"Point"}
}