{
  "type": "Feature",
  "properties": {
    "gn:admin1_code":"15.0",
    "gn:asciiname":"Zhaojiawa",
    "gn:country_code":"CN",
    "gn:dem":1431,
    "gn:feature_class":"P",
    "gn:feature_code":"PPL",
    "gn:name":"Zhaojiawa",
    "gn:population":0,
    "gn:timezone":"Asia/Shanghai",
    "iso:country":"CN",
    "name:zho_x_preferred":[
        "\u8d75\u5bb6\u6d3c"
    ],
    "wof:name":"Zhaojiawa",
    "wof:placetype":"locality"
},
  "geometry": {"coordinates":[107.17400000000001,35.266],"type":"Point"}
}