{
  "type": "Feature",
  "properties": {
    "gn:admin1_code":"1.0",
    "gn:asciiname":"Xinmingcun",
    "gn:country_code":"CN",
    "gn:dem":184,
    "gn:feature_class":"P",
    "gn:feature_code":"PPL",
    "gn:name":"Xinmingcun",
    "gn:population":0,
    "gn:timezone":"Asia/Shanghai",
    "iso:country":"CN",
    "name:zho_x_preferred":[
        "\u65b0\u660e\u6751"
    ],
    "wof:name":"Xinmingcun",
    "wof:placetype":"locality"
},
  "geometry": {"coordinates":[118.25843999999999,30.35023],"type":"Point"}
}