{
  "type": "Feature",
  "properties": {
    "gn:admin1_code":"3.0",
    "gn:asciiname":"Yangdikeng",
    "gn:country_code":"CN",
    "gn:dem":535,
    "gn:feature_class":"P",
    "gn:feature_code":"PPL",
    "gn:name":"Yangdikeng",
    "gn:population":0,
    "gn:timezone":"Asia/Shanghai",
    "iso:country":"CN",
    "name:und_x_variant":[
        "\u6d0b\u5730\u5751"
    ],
    "wof:name":"Yangdikeng",
    "wof:placetype":"locality"
},
  "geometry": {"coordinates":[115.74447000000001,24.74744],"type":"Point"}
}