{
  "type": "Feature",
  "properties": {
    "gn:admin1_code":"3.0",
    "gn:asciiname":"Yanggangtou",
    "gn:country_code":"CN",
    "gn:dem":414,
    "gn:feature_class":"P",
    "gn:feature_code":"PPL",
    "gn:name":"Yanggangtou",
    "gn:population":0,
    "gn:timezone":"Asia/Shanghai",
    "iso:country":"CN",
    "name:zho_x_preferred":[
        "\u9633\u5c97\u5934"
    ],
    "wof:name":"Yanggangtou",
    "wof:placetype":"locality"
},
  "geometry": {"coordinates":[117.94073,28.97579],"type":"Point"}
}