{
  "type": "Feature",
  "properties": {
    "gn:admin1_code":"25",
    "gn:asciiname":"Beixucun",
    "gn:country_code":"CN",
    "gn:dem":124,
    "gn:feature_class":"P",
    "gn:feature_code":"PPL",
    "gn:name":"Beixucun",
    "gn:population":0,
    "gn:timezone":"Asia/Shanghai",
    "iso:country":"CN",
    "name:zho_x_preferred":[
        "\u5317\u8bb8\u6751"
    ],
    "wof:name":"Beixucun",
    "wof:placetype":"locality"
},
  "geometry": {"coordinates":[117.16800000000001,36.1273],"type":"Point"}
}