{
  "type": "Feature",
  "properties": {
    "gn:admin1_code":"19.0",
    "gn:asciiname":"Xiaolantuocun",
    "gn:country_code":"CN",
    "gn:dem":6,
    "gn:feature_class":"P",
    "gn:feature_code":"PPL",
    "gn:name":"Xiaolantuocun",
    "gn:population":0,
    "gn:timezone":"Asia/Shanghai",
    "iso:country":"CN",
    "name:zho_x_preferred":[
        "\u8096\u5170\u5768\u6751"
    ],
    "wof:name":"Xiaolantuocun",
    "wof:placetype":"locality"
},
  "geometry": {"coordinates":[122.77878,41.43384],"type":"Point"}
}