{
  "type": "Feature",
  "properties": {
    "gn:admin1_code":"3.0",
    "gn:asciiname":"Zhongxinkeng",
    "gn:country_code":"CN",
    "gn:dem":276,
    "gn:feature_class":"P",
    "gn:feature_code":"PPL",
    "gn:name":"Zhongxinkeng",
    "gn:population":0,
    "gn:timezone":"Asia/Shanghai",
    "iso:country":"CN",
    "name:und_x_variant":[
        "\u4e2d\u5fc3\u5751"
    ],
    "wof:name":"Zhongxinkeng",
    "wof:placetype":"locality"
},
  "geometry": {"coordinates":[115.66164999999999,24.92974],"type":"Point"}
}