{
  "type": "Feature",
  "properties": {
    "gn:admin1_code":"11.0",
    "gn:asciiname":"Dajia'ao",
    "gn:country_code":"CN",
    "gn:dem":200,
    "gn:feature_class":"P",
    "gn:feature_code":"PPL",
    "gn:name":"Dajia\u2019ao",
    "gn:population":0,
    "gn:timezone":"Asia/Shanghai",
    "iso:country":"CN",
    "name:und_x_variant":[
        "Dajia\u2019ao"
    ],
    "name:zho_x_preferred":[
        "\u5927\u5bb6\u5773"
    ],
    "wof:name":"Dajia'ao",
    "wof:placetype":"locality"
},
  "geometry": {"coordinates":[113.75664,28.15772],"type":"Point"}
}