{
  "type": "Feature",
  "properties": {
    "gn:admin1_code":"1.0",
    "gn:asciiname":"Datuzhuangcun",
    "gn:country_code":"CN",
    "gn:dem":43,
    "gn:feature_class":"P",
    "gn:feature_code":"PPL",
    "gn:name":"Datuzhuangcun",
    "gn:population":0,
    "gn:timezone":"Asia/Shanghai",
    "iso:country":"CN",
    "name:zho_x_preferred":[
        "\u5927\u6d82\u5e84\u6751"
    ],
    "wof:name":"Datuzhuangcun",
    "wof:placetype":"locality"
},
  "geometry": {"coordinates":[115.03637999999999,33.08147],"type":"Point"}
}