{
  "type": "Feature",
  "properties": {
    "gn:admin1_code":"15.0",
    "gn:asciiname":"Dianwang",
    "gn:country_code":"CN",
    "gn:dem":1399,
    "gn:feature_class":"P",
    "gn:feature_code":"PPL",
    "gn:name":"Dianwang",
    "gn:population":0,
    "gn:timezone":"Asia/Shanghai",
    "iso:country":"CN",
    "name:zho_x_preferred":[
        "\u5e97\u6c6a"
    ],
    "wof:name":"Dianwang",
    "wof:placetype":"locality"
},
  "geometry": {"coordinates":[107.065,35.9814],"type":"Point"}
}