{
  "type": "Feature",
  "properties": {
    "gn:admin1_code":"19.0",
    "gn:asciiname":"Liyingjiang Wobucun",
    "gn:country_code":"CN",
    "gn:dem":87,
    "gn:feature_class":"P",
    "gn:feature_code":"PPL",
    "gn:name":"Liyingjiang Wobucun",
    "gn:population":0,
    "gn:timezone":"Asia/Shanghai",
    "iso:country":"CN",
    "name:und_x_variant":[
        "Liyingjiangwobucun",
        "Liyingjiang Wobucun"
    ],
    "name:zho_x_preferred":[
        "\u674e\u5f71\u5320\u7a9d\u5821\u6751"
    ],
    "wof:name":"Liyingjiang Wobucun",
    "wof:placetype":"locality"
},
  "geometry": {"coordinates":[123.19132,42.63902],"type":"Point"}
}