{
  "type": "Feature",
  "properties": {
    "gn:admin1_code":"32.0",
    "gn:asciiname":"Zhujiaba",
    "gn:country_code":"CN",
    "gn:dem":2438,
    "gn:feature_class":"P",
    "gn:feature_code":"PPL",
    "gn:name":"Zhujiaba",
    "gn:population":0,
    "gn:timezone":"Asia/Shanghai",
    "iso:country":"CN",
    "name:zho_x_preferred":[
        "\u6731\u5bb6\u575d"
    ],
    "wof:name":"Zhujiaba",
    "wof:placetype":"locality"
},
  "geometry": {"coordinates":[103.98339,33.39458],"type":"Point"}
}