{
  "type": "Feature",
  "properties": {
    "gn:admin1_code":"6.0",
    "gn:asciiname":"Sainake",
    "gn:country_code":"CN",
    "gn:dem":3938,
    "gn:feature_class":"P",
    "gn:feature_code":"PPL",
    "gn:name":"Sainake",
    "gn:population":0,
    "gn:timezone":"Asia/Urumqi",
    "iso:country":"CN",
    "name:zho_x_preferred":[
        "\u8d5b\u7eb3\u514b"
    ],
    "wof:name":"Sainake",
    "wof:placetype":"locality"
},
  "geometry": {"coordinates":[96.5448,32.6266],"type":"Point"}
}