{
  "type": "Feature",
  "properties": {
    "gn:admin1_code":"14.0",
    "gn:asciiname":"Langbacun",
    "gn:country_code":"CN",
    "gn:dem":4073,
    "gn:feature_class":"P",
    "gn:feature_code":"PPL",
    "gn:name":"Langbacun",
    "gn:population":0,
    "gn:timezone":"Asia/Urumqi",
    "iso:country":"CN",
    "name:zho_x_preferred":[
        "\u90ce\u5df4\u6751"
    ],
    "wof:name":"Langbacun",
    "wof:placetype":"locality"
},
  "geometry": {"coordinates":[90.6884,29.93034],"type":"Point"}
}