{
  "type": "Feature",
  "properties": {
    "gn:admin1_code":"16.0",
    "gn:asciiname":"Nonggongwan",
    "gn:country_code":"CN",
    "gn:dem":711,
    "gn:feature_class":"P",
    "gn:feature_code":"PPL",
    "gn:name":"Nonggongwan",
    "gn:population":0,
    "gn:timezone":"Asia/Shanghai",
    "iso:country":"CN",
    "name:zho_x_preferred":[
        "\u5f04\u516c\u6e7e"
    ],
    "wof:name":"Nonggongwan",
    "wof:placetype":"locality"
},
  "geometry": {"coordinates":[107.44,24.2851],"type":"Point"}
}