{
  "type": "Feature",
  "properties": {
    "gn:country":"CN",
    "gn:fcode":"PPLA3",
    "gn:population":77633,
    "iso:country":"CN",
    "name:deu_x_preferred":[
        "Huangmei"
    ],
    "name:eng_x_preferred":[
        "Huangmei County"
    ],
    "name:eus_x_preferred":[
        "Huangmei Konderria"
    ],
    "name:fas_x_preferred":[
        "\u0634\u0647\u0631\u0633\u062a\u0627\u0646 \u0647\u0648\u0627\u0646\u06af\u0645\u06cc"
    ],
    "name:gan_x_preferred":[
        "\u9ec4\u6885\u53bf"
    ],
    "name:jpn_x_preferred":[
        "\u9ec4\u6885\u770c"
    ],
    "name:kor_x_preferred":[
        "\ud669\uba54\uc774\ud604"
    ],
    "name:mlg_x_preferred":[
        "Huangmei"
    ],
    "name:nan_x_preferred":[
        "N\u0302g-m\u00fbi-ko\u0101n"
    ],
    "name:nld_x_preferred":[
        "Huangmei"
    ],
    "name:nob_x_preferred":[
        "Huangmei"
    ],
    "name:pol_x_preferred":[
        "Huangmei"
    ],
    "name:rus_x_preferred":[
        "\u0425\u0443\u0430\u043d\u043c\u044d\u0439"
    ],
    "name:spa_x_preferred":[
        "Huangmei"
    ],
    "name:swe_x_preferred":[
        "Huangmei"
    ],
    "name:und_x_variant":[
        "Huang-mei-hsien"
    ],
    "name:vie_x_preferred":[
        "Ho\u00e0ng Mai"
    ],
    "name:wuu_x_preferred":[
        "\u9ec4\u6885\u53bf"
    ],
    "name:yue_x_preferred":[
        "\u9ec3\u6885"
    ],
    "name:zho_x_preferred":[
        "\u9ec4\u6885\u53bf"
    ],
    "qs:name":"\u9ec4\u6885\u53bf",
    "qs:name_adm0":"\u4e2d\u570b",
    "qs:name_adm1":"\u6e56\u5317\u7701",
    "qs:photos":14,
    "qs:photos_1k":3,
    "qs:photos_9k":1,
    "qs:photos_9r":1,
    "qs:photos_all":14,
    "qs:photos_sr":1,
    "qs:placetype":"LocalAdmin",
    "qs:pop_sr":"8",
    "wd:wordcount":125,
    "wof:name":"\u9ec4\u6885\u53bf",
    "wof:placetype":"localadmin",
    "wof:population":77633
},
  "geometry": {"coordinates":[116.02495999999999,30.19235],"type":"Point"}
}