{
  "type": "Feature",
  "properties": {
    "gn:country":"CN",
    "gn:fcode":"PPLA3",
    "gn:pop":77633,
    "iso:country":"CN",
    "name:unk_x_variant":[
        "Huang-mei-hsien"
    ],
    "qs:name":"\u9ec4\u6885\u53bf",
    "qs:name_adm0":"\u4e2d\u570b",
    "qs:name_adm1":"\u6e56\u5317\u7701",
    "qs:photos":14,
    "qs:photos_1k":3,
    "qs:photos_9k":1,
    "qs:photos_9r":1,
    "qs:photos_all":14,
    "qs:photos_sr":1,
    "qs:placetype":"LocalAdmin",
    "qs:pop_sr":"8",
    "wd:wordcount":125,
    "wof:name":"\u9ec4\u6885\u53bf",
    "wof:placetype":"localadmin",
    "wof:population":77633
},
  "geometry": {"coordinates":[116.02495999999999,30.19235],"type":"Point"}
}