{
  "type": "Feature",
  "properties": {
    "gn:admin1_code":"3.0",
    "gn:asciiname":"Wangjiadun",
    "gn:country_code":"CN",
    "gn:dem":17,
    "gn:feature_class":"P",
    "gn:feature_code":"PPL",
    "gn:name":"Wangjiadun",
    "gn:population":0,
    "gn:timezone":"Asia/Shanghai",
    "iso:country":"CN",
    "name:und_x_variant":[
        "\u738b\u5bb6\u58a9"
    ],
    "wof:name":"Wangjiadun",
    "wof:placetype":"locality"
},
  "geometry": {"coordinates":[115.96612,29.00778],"type":"Point"}
}