{
  "type": "Feature",
  "properties": {
    "gn:admin1_code":"8.0",
    "gn:asciiname":"Zhangbaodongtun",
    "gn:country_code":"CN",
    "gn:dem":265,
    "gn:feature_class":"P",
    "gn:feature_code":"PPL",
    "gn:name":"Zhangbaodongtun",
    "gn:population":0,
    "gn:timezone":"Asia/Shanghai",
    "iso:country":"CN",
    "name:zho_x_preferred":[
        "\u5f20\u4fdd\u8463\u5c6f"
    ],
    "wof:name":"Zhangbaodongtun",
    "wof:placetype":"locality"
},
  "geometry": {"coordinates":[125.78005,48.10645],"type":"Point"}
}