{
  "type": "Feature",
  "properties": {
    "gn:admin1_code":"32.0",
    "gn:asciiname":"Mushi",
    "gn:country_code":"CN",
    "gn:dem":3320,
    "gn:feature_class":"P",
    "gn:feature_code":"PPL",
    "gn:name":"Mushi",
    "gn:population":0,
    "gn:timezone":"Asia/Shanghai",
    "iso:country":"CN",
    "name:ceb_x_preferred":[
        "Mushi"
    ],
    "name:spa_x_preferred":[
        "Mushi"
    ],
    "name:swe_x_preferred":[
        "Mushi"
    ],
    "name:zho_x_preferred":[
        "\u6728\u77f3"
    ],
    "wof:name":"Mushi",
    "wof:placetype":"locality"
},
  "geometry": {"coordinates":[103.738,32.4793],"type":"Point"}
}