{
  "type": "Feature",
  "properties": {
    "gn:admin1_code":"05",
    "gn:asciiname":"Dapuchaihe",
    "gn:country_code":"CN",
    "gn:dem":563,
    "gn:feature_class":"P",
    "gn:feature_code":"PPLA4",
    "gn:name":"Dapuchaihe",
    "gn:population":0,
    "gn:timezone":"Asia/Shanghai",
    "iso:country":"CN",
    "name:und_x_variant":[
        "Ta-p\u2019u-ch\u2019ai-ho",
        "Dapuchaihe Zhen",
        "Ta-pu-ts\u2019ai-ho",
        "Dapuchaihe",
        "\u5927\u84b2\u67f4\u6cb3",
        "\u5927\u84b2\u67f4\u6cb3\u9547"
    ],
    "wof:name":"Dapuchaihe",
    "wof:placetype":"locality"
},
  "geometry": {"coordinates":[128.03048999999999,42.87973],"type":"Point"}
}