{
  "type": "Feature",
  "properties": {
    "gn:admin1_code":"5.0",
    "gn:asciiname":"Wangda Fangzi",
    "gn:country_code":"CN",
    "gn:dem":189,
    "gn:feature_class":"P",
    "gn:feature_code":"PPL",
    "gn:name":"Wangda Fangzi",
    "gn:population":0,
    "gn:timezone":"Asia/Shanghai",
    "iso:country":"CN",
    "name:zho_x_preferred":[
        "\u738b\u5927\u623f\u5b50"
    ],
    "wof:name":"Wangda Fangzi",
    "wof:placetype":"locality"
},
  "geometry": {"coordinates":[124.9203,44.04072],"type":"Point"}
}