{
  "type": "Feature",
  "properties": {
    "gn:admin1_code":"26.0",
    "gn:asciiname":"Liandaowancun",
    "gn:country_code":"CN",
    "gn:dem":1258,
    "gn:feature_class":"P",
    "gn:feature_code":"PPL",
    "gn:name":"Liandaowancun",
    "gn:population":0,
    "gn:timezone":"Asia/Shanghai",
    "iso:country":"CN",
    "name:zho_x_preferred":[
        "\u9570\u5200\u6e7e\u6751"
    ],
    "wof:name":"Liandaowancun",
    "wof:placetype":"locality"
},
  "geometry": {"coordinates":[108.98022,37.20874],"type":"Point"}
}