{
  "type": "Feature",
  "properties": {
    "gn:admin1_code":"7.0",
    "gn:asciiname":"Youxi",
    "gn:country_code":"CN",
    "gn:dem":454,
    "gn:feature_class":"P",
    "gn:feature_code":"PPL",
    "gn:name":"Youxi",
    "gn:population":0,
    "gn:timezone":"Asia/Shanghai",
    "iso:country":"CN",
    "name:zho_x_preferred":[
        "\u5c24\u6eaa"
    ],
    "wof:name":"Youxi",
    "wof:placetype":"locality"
},
  "geometry": {"coordinates":[119.36612,27.36742000000001],"type":"Point"}
}