{
  "type": "Feature",
  "properties": {
    "gn:admin1_code":"30.0",
    "gn:asciiname":"Hengshanwo",
    "gn:country_code":"CN",
    "gn:dem":9,
    "gn:feature_class":"P",
    "gn:feature_code":"PPL",
    "gn:name":"Hengshanwo",
    "gn:population":0,
    "gn:timezone":"Asia/Shanghai",
    "iso:country":"CN",
    "name:zho_x_preferred":[
        "\u6a2a\u5c71\u6da1"
    ],
    "wof:name":"Hengshanwo",
    "wof:placetype":"locality"
},
  "geometry": {"coordinates":[112.89933000000001,23.28912],"type":"Point"}
}