{
  "type": "Feature",
  "properties": {
    "gn:admin1_code":"11.0",
    "gn:asciiname":"Ruiyingsi",
    "gn:country_code":"CN",
    "gn:dem":221,
    "gn:feature_class":"P",
    "gn:feature_code":"PPL",
    "gn:name":"Ruiyingsi",
    "gn:population":0,
    "gn:timezone":"Asia/Shanghai",
    "iso:country":"CN",
    "name:zho_x_preferred":[
        "\u745e\u6620\u5bfa"
    ],
    "wof:name":"Ruiyingsi",
    "wof:placetype":"locality"
},
  "geometry": {"coordinates":[113.44193,27.84077000000001],"type":"Point"}
}