{
  "type": "Feature",
  "properties": {
    "gn:admin1_code":"2.0",
    "gn:asciiname":"Luosiyan",
    "gn:country_code":"CN",
    "gn:dem":194,
    "gn:feature_class":"P",
    "gn:feature_code":"PPL",
    "gn:name":"Luosiyan",
    "gn:population":0,
    "gn:timezone":"Asia/Shanghai",
    "iso:country":"CN",
    "name:zho_x_preferred":[
        "\u87ba\u86f3\u5ca9"
    ],
    "wof:name":"Luosiyan",
    "wof:placetype":"locality"
},
  "geometry": {"coordinates":[120.17021,28.66463],"type":"Point"}
}