{
  "type": "Feature",
  "properties": {
    "gn:admin1_code":"30",
    "gn:asciiname":"Gaopu",
    "gn:country_code":"CN",
    "gn:dem":39,
    "gn:feature_class":"P",
    "gn:feature_code":"PPL",
    "gn:name":"Gaopu",
    "gn:population":0,
    "gn:timezone":"Asia/Shanghai",
    "iso:country":"CN",
    "name:und_x_variant":[
        "Kao-ch\u2019iao",
        "Gaoqiao",
        "Gaopu"
    ],
    "name:zho_x_preferred":[
        "\u9ad8\u57d4"
    ],
    "wof:name":"Gaopu",
    "wof:placetype":"locality"
},
  "geometry": {"coordinates":[113.25641,23.64841],"type":"Point"}
}