{
  "type": "Feature",
  "properties": {
    "gn:admin1_code":"29.0",
    "gn:asciiname":"Yibucun",
    "gn:country_code":"CN",
    "gn:dem":1506,
    "gn:feature_class":"P",
    "gn:feature_code":"PPL",
    "gn:name":"Yibucun",
    "gn:population":0,
    "gn:timezone":"Asia/Shanghai",
    "iso:country":"CN",
    "name:zho_x_preferred":[
        "\u4ee5\u5821\u6751"
    ],
    "wof:name":"Yibucun",
    "wof:placetype":"locality"
},
  "geometry": {"coordinates":[105.178,27.6378],"type":"Point"}
}