{
  "type": "Feature",
  "properties": {
    "gn:admin1_code":"1.0",
    "gn:asciiname":"Suyingcun",
    "gn:country_code":"CN",
    "gn:dem":41,
    "gn:feature_class":"P",
    "gn:feature_code":"PPL",
    "gn:name":"Suyingcun",
    "gn:population":0,
    "gn:timezone":"Asia/Shanghai",
    "iso:country":"CN",
    "name:und_x_variant":[
        "Suying"
    ],
    "name:zho_x_preferred":[
        "\u82cf\u8425\u6751"
    ],
    "wof:name":"Suyingcun",
    "wof:placetype":"locality"
},
  "geometry": {"coordinates":[115.15000000000001,33.01667],"type":"Point"}
}