{
  "type": "Feature",
  "properties": {
    "gn:admin1_code":"26",
    "gn:asciiname":"Mujianghekou",
    "gn:cc2":"CN",
    "gn:country_code":"CN",
    "gn:dem":1197,
    "gn:feature_class":"P",
    "gn:feature_code":"PPL",
    "gn:name":"Mujianghekou",
    "gn:population":0,
    "gn:timezone":"Asia/Shanghai",
    "iso:country":"CN",
    "name:und_x_variant":[
        "Mu-chiang-ho",
        "Mujianghe",
        "Mu-chia-ho",
        "Mujianghekou"
    ],
    "wof:name":"Mujianghekou",
    "wof:placetype":"locality"
},
  "geometry": {"coordinates":[108.14556,33.96056],"type":"Point"}
}