{
  "type": "Feature",
  "properties": {
    "gn:admin1_code":"21.0",
    "gn:asciiname":"Yanghongqiao Sandui",
    "gn:country_code":"CN",
    "gn:dem":1118,
    "gn:feature_class":"P",
    "gn:feature_code":"PPLF",
    "gn:name":"Yanghongqiao Sandui",
    "gn:population":0,
    "gn:timezone":"Asia/Shanghai",
    "iso:country":"CN",
    "name:zho_x_preferred":[
        "\u6768\u6d2a\u6865\u4e09\u961f"
    ],
    "wof:name":"Yanghongqiao Sandui",
    "wof:placetype":"locality"
},
  "geometry": {"coordinates":[106.26600000000001,38.1101],"type":"Point"}
}