{
  "type": "Feature",
  "properties": {
    "gn:admin1_code":"29.0",
    "gn:asciiname":"Xialongmen",
    "gn:country_code":"CN",
    "gn:dem":2150,
    "gn:feature_class":"P",
    "gn:feature_code":"PPL",
    "gn:name":"Xialongmen",
    "gn:population":0,
    "gn:timezone":"Asia/Shanghai",
    "iso:country":"CN",
    "name:zho_x_preferred":[
        "\u4e0b\u9f99\u95e8"
    ],
    "wof:name":"Xialongmen",
    "wof:placetype":"locality"
},
  "geometry": {"coordinates":[99.9498,26.0662],"type":"Point"}
}