{
  "type": "Feature",
  "properties": {
    "gn:admin1_code":"18",
    "gn:asciiname":"Daqiaohe",
    "gn:country_code":"CN",
    "gn:dem":1338,
    "gn:feature_class":"P",
    "gn:feature_code":"PPL",
    "gn:name":"Daqiaohe",
    "gn:population":0,
    "gn:timezone":"Asia/Shanghai",
    "iso:country":"CN",
    "name:zho_x_preferred":[
        "\u5927\u6865\u6cb3"
    ],
    "wof:name":"Daqiaohe",
    "wof:placetype":"locality"
},
  "geometry": {"coordinates":[105.181,25.4552],"type":"Point"}
}