{
  "type": "Feature",
  "properties": {
    "gn:admin1_code":"9.0",
    "gn:asciiname":"Lijia'ao",
    "gn:country_code":"CN",
    "gn:dem":558,
    "gn:feature_class":"P",
    "gn:feature_code":"PPL",
    "gn:name":"Lijia\u2019ao",
    "gn:population":0,
    "gn:timezone":"Asia/Shanghai",
    "iso:country":"CN",
    "name:und_x_variant":[
        "Lijia\u2019ao"
    ],
    "name:zho_x_preferred":[
        "\u674e\u5bb6\u51f9"
    ],
    "wof:name":"Lijia'ao",
    "wof:placetype":"locality"
},
  "geometry": {"coordinates":[111.11177000000001,34.70678],"type":"Point"}
}