{
  "type": "Feature",
  "properties": {
    "gn:admin1_code":"11.0",
    "gn:asciiname":"Qiaoxiacun",
    "gn:country_code":"CN",
    "gn:dem":88,
    "gn:feature_class":"P",
    "gn:feature_code":"PPL",
    "gn:name":"Qiaoxiacun",
    "gn:population":0,
    "gn:timezone":"Asia/Shanghai",
    "iso:country":"CN",
    "name:zho_x_preferred":[
        "\u4e54\u4e0b\u6751"
    ],
    "wof:name":"Qiaoxiacun",
    "wof:placetype":"locality"
},
  "geometry": {"coordinates":[113.41531999999999,26.94485],"type":"Point"}
}