{
  "type": "Feature",
  "properties": {
    "gn:admin1_code":"25",
    "gn:asciiname":"Damanying",
    "gn:country_code":"CN",
    "gn:dem":66,
    "gn:feature_class":"P",
    "gn:feature_code":"PPL",
    "gn:name":"Damanying",
    "gn:population":0,
    "gn:timezone":"Asia/Shanghai",
    "iso:country":"CN",
    "name:zho_x_preferred":[
        "\u5927\u6ee1\u8425"
    ],
    "wof:name":"Damanying",
    "wof:placetype":"locality"
},
  "geometry": {"coordinates":[116.83799999999999,35.7079],"type":"Point"}
}