{
  "type": "Feature",
  "properties": {
    "gn:admin1_code":"2.0",
    "gn:asciiname":"Qishang",
    "gn:country_code":"CN",
    "gn:dem":225,
    "gn:feature_class":"P",
    "gn:feature_code":"PPL",
    "gn:name":"Qishang",
    "gn:population":0,
    "gn:timezone":"Asia/Shanghai",
    "iso:country":"CN",
    "name:zho_x_preferred":[
        "\u78dc\u4e0a"
    ],
    "wof:name":"Qishang",
    "wof:placetype":"locality"
},
  "geometry": {"coordinates":[119.20423999999998,28.87887000000001],"type":"Point"}
}