{
  "type": "Feature",
  "properties": {
    "gn:admin1_code":"8.0",
    "gn:asciiname":"Gaoshanqiaodi Yingzi",
    "gn:country_code":"CN",
    "gn:dem":203,
    "gn:feature_class":"P",
    "gn:feature_code":"PPL",
    "gn:name":"Gaoshanqiaodi Yingzi",
    "gn:population":0,
    "gn:timezone":"Asia/Shanghai",
    "iso:country":"CN",
    "name:zho_x_preferred":[
        "\u9ad8\u5c71\u6865\u5730\u8425\u5b50"
    ],
    "wof:name":"Gaoshanqiaodi Yingzi",
    "wof:placetype":"locality"
},
  "geometry": {"coordinates":[127.21392,50.23316],"type":"Point"}
}