{
  "type": "Feature",
  "properties": {
    "gn:admin1_code":"02",
    "gn:asciiname":"Weipingtou",
    "gn:country_code":"CN",
    "gn:dem":341,
    "gn:feature_class":"P",
    "gn:feature_code":"PPL",
    "gn:name":"Weipingtou",
    "gn:population":0,
    "gn:timezone":"Asia/Shanghai",
    "iso:country":"CN",
    "name:zho_x_preferred":[
        "\u56f4\u576a\u5934"
    ],
    "wof:name":"Weipingtou",
    "wof:placetype":"locality"
},
  "geometry": {"coordinates":[120.49088,27.99341],"type":"Point"}
}