{
  "type": "Feature",
  "properties": {
    "gn:admin1_code":"29.0",
    "gn:asciiname":"Laozhouzhai",
    "gn:country_code":"CN",
    "gn:dem":1515,
    "gn:feature_class":"P",
    "gn:feature_code":"PPL",
    "gn:name":"Laozhouzhai",
    "gn:population":0,
    "gn:timezone":"Asia/Shanghai",
    "iso:country":"CN",
    "name:zho_x_preferred":[
        "\u8001\u5468\u5be8"
    ],
    "wof:name":"Laozhouzhai",
    "wof:placetype":"locality"
},
  "geometry": {"coordinates":[100.253,22.7719],"type":"Point"}
}