{
  "type": "Feature",
  "properties": {
    "gn:admin1_code":"18",
    "gn:asciiname":"Jiwotian",
    "gn:country_code":"CN",
    "gn:dem":1408,
    "gn:feature_class":"P",
    "gn:feature_code":"PPL",
    "gn:name":"Jiwotian",
    "gn:population":0,
    "gn:timezone":"Asia/Shanghai",
    "iso:country":"CN",
    "name:zho_x_preferred":[
        "\u9e21\u7a9d\u7530"
    ],
    "wof:name":"Jiwotian",
    "wof:placetype":"locality"
},
  "geometry": {"coordinates":[105.267,25.4806],"type":"Point"}
}