{
  "type": "Feature",
  "properties": {
    "gn:admin1_code":"32.0",
    "gn:asciiname":"Erkazi",
    "gn:country_code":"CN",
    "gn:dem":2634,
    "gn:feature_class":"P",
    "gn:feature_code":"PPL",
    "gn:name":"Erkazi",
    "gn:population":0,
    "gn:timezone":"Asia/Shanghai",
    "iso:country":"CN",
    "name:zho_x_preferred":[
        "\u4e8c\u5361\u5b50"
    ],
    "wof:name":"Erkazi",
    "wof:placetype":"locality"
},
  "geometry": {"coordinates":[101.736,30.7958],"type":"Point"}
}