{
  "type": "Feature",
  "properties": {
    "gn:admin1_code":"11.0",
    "gn:asciiname":"Guancuntang",
    "gn:country_code":"CN",
    "gn:dem":330,
    "gn:feature_class":"P",
    "gn:feature_code":"PPL",
    "gn:name":"Guancuntang",
    "gn:population":0,
    "gn:timezone":"Asia/Shanghai",
    "iso:country":"CN",
    "name:zho_x_preferred":[
        "\u5173\u5bf8\u5858"
    ],
    "wof:name":"Guancuntang",
    "wof:placetype":"locality"
},
  "geometry": {"coordinates":[110.57258,27.82913],"type":"Point"}
}