{
  "type": "Feature",
  "properties": {
    "gn:admin1_code":"21.0",
    "gn:asciiname":"Qiaojiazhuang",
    "gn:country_code":"CN",
    "gn:dem":1130,
    "gn:feature_class":"P",
    "gn:feature_code":"PPL",
    "gn:name":"Qiaojiazhuang",
    "gn:population":0,
    "gn:timezone":"Asia/Shanghai",
    "iso:country":"CN",
    "name:zho_x_preferred":[
        "\u4e54\u5bb6\u5e84"
    ],
    "wof:name":"Qiaojiazhuang",
    "wof:placetype":"locality"
},
  "geometry": {"coordinates":[106.03400000000001,38.1433],"type":"Point"}
}