{
  "type": "Feature",
  "properties": {
    "gn:admin1_code":"15.0",
    "gn:asciiname":"Yanjiayao",
    "gn:country_code":"CN",
    "gn:dem":2087,
    "gn:feature_class":"P",
    "gn:feature_code":"PPL",
    "gn:name":"Yanjiayao",
    "gn:population":0,
    "gn:timezone":"Asia/Shanghai",
    "iso:country":"CN",
    "name:zho_x_preferred":[
        "\u960e\u5bb6\u7a91"
    ],
    "wof:name":"Yanjiayao",
    "wof:placetype":"locality"
},
  "geometry": {"coordinates":[103.747,37.2383],"type":"Point"}
}