{
  "type": "Feature",
  "properties": {
    "gn:admin1_code":"18",
    "gn:asciiname":"Lugong",
    "gn:country_code":"CN",
    "gn:dem":1124,
    "gn:feature_class":"P",
    "gn:feature_code":"PPL",
    "gn:name":"Lugong",
    "gn:population":0,
    "gn:timezone":"Asia/Shanghai",
    "iso:country":"CN",
    "name:zho_x_preferred":[
        "\u9c81\u8d21"
    ],
    "wof:name":"Lugong",
    "wof:placetype":"locality"
},
  "geometry": {"coordinates":[105.337,25.0453],"type":"Point"}
}