{
  "type": "Feature",
  "properties": {
    "iso:country":"CN",
    "name:kaz_x_preferred":[
        "\u041a\u04e9\u043a\u0442\u043e\u0493\u0430\u0439"
    ],
    "name:rus_x_preferred":[
        "\u041a\u0451\u043a\u0442\u043e\u043a\u0430\u0439"
    ],
    "name:uig_x_preferred":[
        "\u0643\u06c6\u0643\u062a\u0648\u0642\u0627\u064a \u0628\u0627\u0632\u0649\u0631\u0649"
    ],
    "name:zho_x_preferred":[
        "\u53ef\u53ef\u6258\u6d77\u9547"
    ],
    "ne:ADM0CAP":0.0,
    "ne:ADM0NAME":"China",
    "ne:ADM0_A3":"CHN",
    "ne:ADM1NAME":"Xinjiang Uygur",
    "ne:ADMIN1_COD":0,
    "ne:CAPALT":0,
    "ne:CHANGED":0,
    "ne:CHECKME":0,
    "ne:COMPARE":0,
    "ne:DIFFASCII":0,
    "ne:ELEVATION":0.0,
    "ne:FEATURECLA":"Populated place",
    "ne:GEONAMEID":-1,
    "ne:GEONAMESNO":"No GeoNames match due to small population, not in GeoNames, or poor NEV placement.",
    "ne:GN_POP":0,
    "ne:GTOPO30":0.0,
    "ne:ISO_A2":"CN",
    "ne:LABELRANK":1,
    "ne:LATITUDE":47.000373,
    "ne:LONGITUDE":89.466621,
    "ne:LS_MATCH":0,
    "ne:LS_NAME":"Fuyun",
    "ne:MAX_AREAKM":0.0,
    "ne:MAX_AREAMI":0.0,
    "ne:MAX_BBXMAX":0.0,
    "ne:MAX_BBXMIN":0.0,
    "ne:MAX_BBYMAX":0.0,
    "ne:MAX_BBYMIN":0.0,
    "ne:MAX_NATSCA":0.0,
    "ne:MAX_PERKM":0.0,
    "ne:MAX_PERMI":0.0,
    "ne:MAX_POP10":0,
    "ne:MAX_POP20":0,
    "ne:MAX_POP300":0,
    "ne:MAX_POP310":0,
    "ne:MAX_POP50":0,
    "ne:MEAN_BBXC":0.0,
    "ne:MEAN_BBYC":0.0,
    "ne:MEGACITY":0,
    "ne:MIN_AREAKM":0.0,
    "ne:MIN_AREAMI":0.0,
    "ne:MIN_BBXMAX":0.0,
    "ne:MIN_BBXMIN":0.0,
    "ne:MIN_BBYMAX":0.0,
    "ne:MIN_BBYMIN":0.0,
    "ne:MIN_PERKM":0.0,
    "ne:MIN_PERMI":0.0,
    "ne:NAME":"Koktokay",
    "ne:NAMEASCII":"Koktokay",
    "ne:NAMEDIFF":0,
    "ne:NAMEPAR":"Fuyun",
    "ne:NATSCALE":20,
    "ne:POP1950":0,
    "ne:POP1955":0,
    "ne:POP1960":0,
    "ne:POP1965":0,
    "ne:POP1970":0,
    "ne:POP1975":0,
    "ne:POP1980":0,
    "ne:POP1985":0,
    "ne:POP1990":0,
    "ne:POP1995":0,
    "ne:POP2000":0,
    "ne:POP2005":0,
    "ne:POP2010":0,
    "ne:POP2015":0,
    "ne:POP2020":0,
    "ne:POP2025":0,
    "ne:POP2050":0,
    "ne:POP_MAX":80000,
    "ne:POP_MIN":40000,
    "ne:POP_OTHER":0,
    "ne:RANK_MAX":8,
    "ne:RANK_MIN":7,
    "ne:SCALERANK":7,
    "ne:SOV0NAME":"China",
    "ne:SOV_A3":"CHN",
    "ne:UN_FID":0,
    "ne:UN_LAT":0.0,
    "ne:UN_LONG":0.0,
    "ne:WORLDCITY":0,
    "ne:min_zoom":6.1,
    "wof:name":"Koktokay",
    "wof:placetype":"locality"
},
  "geometry": {"coordinates":[89.46662145890434,47.00037274076431],"type":"Point"}
}