{
  "type": "Feature",
  "properties": {
    "gn:admin1_code":"31.0",
    "gn:asciiname":"Xingshi",
    "gn:country_code":"CN",
    "gn:dem":63,
    "gn:feature_class":"P",
    "gn:feature_code":"PPL",
    "gn:name":"Xingshi",
    "gn:population":0,
    "gn:timezone":"Asia/Shanghai",
    "iso:country":"CN",
    "name:zho_x_preferred":[
        "\u5174\u8bd7"
    ],
    "wof:name":"Xingshi",
    "wof:placetype":"locality"
},
  "geometry": {"coordinates":[110.19943000000001,19.50174],"type":"Point"}
}