{
  "type": "Feature",
  "properties": {
    "gn:admin1_code":"02",
    "gn:asciiname":"Qianyantoucun",
    "gn:country_code":"CN",
    "gn:dem":14,
    "gn:feature_class":"P",
    "gn:feature_code":"PPL",
    "gn:name":"Qianyantoucun",
    "gn:population":0,
    "gn:timezone":"Asia/Shanghai",
    "iso:country":"CN",
    "name:und_x_variant":[
        "Ch\u2019ien-yen-t\u2019ou",
        "Qianyantou",
        "Qianyantoucun"
    ],
    "name:zho_x_preferred":[
        "\u524d\u5830\u5934"
    ],
    "name:zho_x_variant":[
        "\u524d\u5830\u5934\u6751"
    ],
    "wof:name":"Qianyantoucun",
    "wof:placetype":"locality"
},
  "geometry": {"coordinates":[121.67151,29.7958],"type":"Point"}
}