{
  "type": "Feature",
  "properties": {
    "gn:admin1_code":"16.0",
    "gn:asciiname":"Kenchou",
    "gn:country_code":"CN",
    "gn:dem":253,
    "gn:feature_class":"P",
    "gn:feature_code":"PPL",
    "gn:name":"Kenchou",
    "gn:population":0,
    "gn:timezone":"Asia/Shanghai",
    "iso:country":"CN",
    "name:zho_x_preferred":[
        "\u80af\u4ec7"
    ],
    "wof:name":"Kenchou",
    "wof:placetype":"locality"
},
  "geometry": {"coordinates":[107.879,24.8446],"type":"Point"}
}