{
  "type": "Feature",
  "properties": {
    "gn:admin1_code":"9.0",
    "gn:asciiname":"Lilaozhuang",
    "gn:country_code":"CN",
    "gn:dem":204,
    "gn:feature_class":"P",
    "gn:feature_code":"PPL",
    "gn:name":"Lilaozhuang",
    "gn:population":0,
    "gn:timezone":"Asia/Shanghai",
    "iso:country":"CN",
    "name:und_x_variant":[
        "\u674e\u8001\u5e84",
        "Lilaozhuang"
    ],
    "wof:name":"Lilaozhuang",
    "wof:placetype":"locality"
},
  "geometry": {"coordinates":[112.27742000000001,33.05183],"type":"Point"}
}