{
  "type": "Feature",
  "properties": {
    "gn:admin1_code":"15.0",
    "gn:asciiname":"Wanli",
    "gn:country_code":"CN",
    "gn:dem":1538,
    "gn:feature_class":"P",
    "gn:feature_code":"PPL",
    "gn:name":"Wanli",
    "gn:population":0,
    "gn:timezone":"Asia/Shanghai",
    "iso:country":"CN",
    "name:zho_x_preferred":[
        "\u6e7e\u91cc"
    ],
    "wof:name":"Wanli",
    "wof:placetype":"locality"
},
  "geometry": {"coordinates":[108.497,35.5461],"type":"Point"}
}