{
  "type": "Feature",
  "properties": {
    "gn:admin1_code":"15.0",
    "gn:asciiname":"Baitiegou",
    "gn:country_code":"CN",
    "gn:dem":1933,
    "gn:feature_class":"P",
    "gn:feature_code":"PPL",
    "gn:name":"Baitiegou",
    "gn:population":0,
    "gn:timezone":"Asia/Shanghai",
    "iso:country":"CN",
    "name:und_x_variant":[
        "\u767d\u94c1\u6c9f"
    ],
    "wof:name":"Baitiegou",
    "wof:placetype":"locality"
},
  "geometry": {"coordinates":[104.94098,34.5173],"type":"Point"}
}