{
  "type": "Feature",
  "properties": {
    "gn:admin1_code":"08",
    "gn:asciiname":"Housanhetun",
    "gn:country_code":"CN",
    "gn:dem":175,
    "gn:feature_class":"P",
    "gn:feature_code":"PPL",
    "gn:name":"Housanhetun",
    "gn:population":0,
    "gn:timezone":"Asia/Shanghai",
    "iso:country":"CN",
    "name:und_x_variant":[
        "Hou-san-ho-t\u2019un",
        "Housanhetun"
    ],
    "name:zho_x_preferred":[
        "\u540e\u4e09\u5408\u5c6f"
    ],
    "wof:name":"Housanhetun",
    "wof:placetype":"locality"
},
  "geometry": {"coordinates":[124.64606999999999,47.90334],"type":"Point"}
}