{
  "type": "Feature",
  "properties": {
    "gn:admin1_code":"14.0",
    "gn:asciiname":"Longdongka",
    "gn:country_code":"CN",
    "gn:dem":4267,
    "gn:feature_class":"P",
    "gn:feature_code":"PPL",
    "gn:name":"Longdongka",
    "gn:population":0,
    "gn:timezone":"Asia/Urumqi",
    "iso:country":"CN",
    "name:zho_x_preferred":[
        "\u9647\u51ac\u5361"
    ],
    "wof:name":"Longdongka",
    "wof:placetype":"locality"
},
  "geometry": {"coordinates":[95.00182,31.62],"type":"Point"}
}