{
  "type": "Feature",
  "properties": {
    "gn:admin1_code":"9.0",
    "gn:asciiname":"Dongzhangzhuang",
    "gn:country_code":"CN",
    "gn:dem":205,
    "gn:feature_class":"P",
    "gn:feature_code":"PPL",
    "gn:name":"Dongzhangzhuang",
    "gn:population":0,
    "gn:timezone":"Asia/Shanghai",
    "iso:country":"CN",
    "name:zho_x_preferred":[
        "\u4e1c\u5f20\u5e84"
    ],
    "wof:name":"Dongzhangzhuang",
    "wof:placetype":"locality"
},
  "geometry": {"coordinates":[112.46268000000001,35.08184],"type":"Point"}
}