{
  "type": "Feature",
  "properties": {
    "gn:admin1_code":"9.0",
    "gn:asciiname":"Qinlaozhuang",
    "gn:country_code":"CN",
    "gn:dem":201,
    "gn:feature_class":"P",
    "gn:feature_code":"PPL",
    "gn:name":"Qinlaozhuang",
    "gn:population":0,
    "gn:timezone":"Asia/Shanghai",
    "iso:country":"CN",
    "name:zho_x_preferred":[
        "\u79e6\u8001\u5e84"
    ],
    "wof:name":"Qinlaozhuang",
    "wof:placetype":"locality"
},
  "geometry": {"coordinates":[113.35554999999999,32.93172],"type":"Point"}
}