{
  "type": "Feature",
  "properties": {
    "gn:admin1_code":"1.0",
    "gn:asciiname":"Xiaqiaocun",
    "gn:country_code":"CN",
    "gn:dem":25,
    "gn:feature_class":"P",
    "gn:feature_code":"PPL",
    "gn:name":"Xiaqiaocun",
    "gn:population":0,
    "gn:timezone":"Asia/Shanghai",
    "iso:country":"CN",
    "name:zho_x_preferred":[
        "\u4e0b\u6865\u6751"
    ],
    "wof:name":"Xiaqiaocun",
    "wof:placetype":"locality"
},
  "geometry": {"coordinates":[117.13997999999999,32.91711],"type":"Point"}
}