{
  "type": "Feature",
  "properties": {
    "gn:admin1_code":"15",
    "gn:asciiname":"Quzi",
    "gn:country_code":"CN",
    "gn:dem":1158,
    "gn:feature_class":"P",
    "gn:feature_code":"PPLA4",
    "gn:name":"Quzi",
    "gn:population":0,
    "gn:timezone":"Asia/Shanghai",
    "iso:country":"CN",
    "name:und_x_variant":[
        "Tsyuytsz\u00f6chzhen",
        "Huan-hsien",
        "Ch\u2019u-tzu-chen",
        "Huan",
        "Ch\u2019\u00fc-tzu",
        "Quzi",
        "\u66f2\u5b50",
        "Quzi Zhen",
        "\u66f2\u5b50\u9547"
    ],
    "wof:name":"Quzi",
    "wof:placetype":"locality"
},
  "geometry": {"coordinates":[107.51203999999998,36.29323],"type":"Point"}
}