{
  "type": "Feature",
  "properties": {
    "gn:admin1_code":"12.0",
    "gn:asciiname":"Zhujiazui",
    "gn:country_code":"CN",
    "gn:dem":44,
    "gn:feature_class":"P",
    "gn:feature_code":"PPL",
    "gn:name":"Zhujiazui",
    "gn:population":0,
    "gn:timezone":"Asia/Shanghai",
    "iso:country":"CN",
    "name:zho_x_preferred":[
        "Zhujiazui"
    ],
    "name:zho_x_variant":[
        "\u6731\u5bb6\u5480"
    ],
    "wof:name":"Zhujiazui",
    "wof:placetype":"locality"
},
  "geometry": {"coordinates":[111.88003999999999,30.30708],"type":"Point"}
}