{
  "type": "Feature",
  "properties": {
    "gn:admin1_code":"16",
    "gn:asciiname":"Baizhuping",
    "gn:country_code":"CN",
    "gn:dem":421,
    "gn:feature_class":"P",
    "gn:feature_code":"PPL",
    "gn:name":"Baizhuping",
    "gn:population":0,
    "gn:timezone":"Asia/Shanghai",
    "iso:country":"CN",
    "name:zho_x_preferred":[
        "\u767d\u7af9\u576a"
    ],
    "wof:name":"Baizhuping",
    "wof:placetype":"locality"
},
  "geometry": {"coordinates":[111.187,25.7995],"type":"Point"}
}