{
  "type": "Feature",
  "properties": {
    "gn:admin1_code":"25.0",
    "gn:asciiname":"Ganggou",
    "gn:country_code":"CN",
    "gn:dem":158,
    "gn:feature_class":"P",
    "gn:feature_code":"PPL",
    "gn:name":"Ganggou",
    "gn:population":0,
    "gn:timezone":"Asia/Shanghai",
    "iso:country":"CN",
    "name:und_x_variant":[
        "Ganggou Zhen"
    ],
    "name:zho_x_preferred":[
        "\u6e2f\u6c9f\u9547"
    ],
    "name:zho_x_variant":[
        "\u6e2f\u6c9f"
    ],
    "wof:name":"Ganggou",
    "wof:placetype":"locality"
},
  "geometry": {"coordinates":[117.176,36.6381],"type":"Point"}
}