{
  "type": "Feature",
  "properties": {
    "gn:admin1_code":"5.0",
    "gn:asciiname":"Guandaogou",
    "gn:country_code":"CN",
    "gn:dem":169,
    "gn:feature_class":"P",
    "gn:feature_code":"PPL",
    "gn:name":"Guandaogou",
    "gn:population":0,
    "gn:timezone":"Asia/Shanghai",
    "iso:country":"CN",
    "name:und_x_variant":[
        "\u5b98\u9053\u6c9f"
    ],
    "wof:name":"Guandaogou",
    "wof:placetype":"locality"
},
  "geometry": {"coordinates":[131.00953999999999,42.96712],"type":"Point"}
}