{
  "type": "Feature",
  "properties": {
    "gn:admin1_code":"16.0",
    "gn:asciiname":"Gangdaodong",
    "gn:country_code":"CN",
    "gn:dem":528,
    "gn:feature_class":"P",
    "gn:feature_code":"PPL",
    "gn:name":"Gangdaodong",
    "gn:population":0,
    "gn:timezone":"Asia/Shanghai",
    "iso:country":"CN",
    "name:zho_x_preferred":[
        "\u521a\u5200\u5cd2"
    ],
    "wof:name":"Gangdaodong",
    "wof:placetype":"locality"
},
  "geometry": {"coordinates":[108.127,24.3473],"type":"Point"}
}