{
  "type": "Feature",
  "properties": {
    "gn:admin1_code":"08",
    "gn:asciiname":"Hou-fu-an-t'un",
    "gn:country_code":"CN",
    "gn:dem":168,
    "gn:feature_class":"P",
    "gn:feature_code":"PPL",
    "gn:name":"Hou-fu-an-t\u2019un",
    "gn:population":0,
    "gn:timezone":"Asia/Shanghai",
    "iso:country":"CN",
    "wof:name":"Hou-fu-an-t'un",
    "wof:placetype":"locality"
},
  "geometry": {"coordinates":[124.17694,47.98667],"type":"Point"}
}