{
  "type": "Feature",
  "properties": {
    "gn:admin1_code":"9",
    "gn:asciiname":"Zaoke",
    "gn:country_code":"CN",
    "gn:dem":47,
    "gn:feature_class":"P",
    "gn:feature_code":"PPL",
    "gn:name":"Zaoke",
    "gn:population":0,
    "gn:timezone":"Asia/Shanghai",
    "iso:country":"CN",
    "name:zho_x_preferred":[
        "\u67a3\u79d1"
    ],
    "wof:name":"Zaoke",
    "wof:placetype":"locality"
},
  "geometry": {"coordinates":[115.41779,36.04363],"type":"Point"}
}