{
  "type": "Feature",
  "properties": {
    "gn:admin1_code":"33.0",
    "gn:asciiname":"Songshuwan",
    "gn:country_code":"CN",
    "gn:dem":302,
    "gn:feature_class":"P",
    "gn:feature_code":"PPL",
    "gn:name":"Songshuwan",
    "gn:population":0,
    "gn:timezone":"Asia/Shanghai",
    "iso:country":"CN",
    "name:zho_x_preferred":[
        "\u677e\u6811\u6e7e"
    ],
    "wof:name":"Songshuwan",
    "wof:placetype":"locality"
},
  "geometry": {"coordinates":[107.8313,30.08635],"type":"Point"}
}