{
  "type": "Feature",
  "properties": {
    "gn:admin1_code":"02",
    "gn:asciiname":"Zhangshuxia",
    "gn:cc2":"CN",
    "gn:country_code":"CN",
    "gn:dem":58,
    "gn:feature_class":"P",
    "gn:feature_code":"PPL",
    "gn:name":"Zhangshuxia",
    "gn:population":0,
    "gn:timezone":"Asia/Shanghai",
    "iso:country":"CN",
    "name:und_x_variant":[
        "Chang-shu-hsia",
        "Zhangshuxia",
        "\u6a1f\u6811\u4e0b"
    ],
    "name:zho_x_preferred":[
        "\u6a1f\u6811\u4e0b"
    ],
    "wof:name":"Zhangshuxia",
    "wof:placetype":"locality"
},
  "geometry": {"coordinates":[121.29167,29.05],"type":"Point"}
}