{
  "type": "Feature",
  "properties": {
    "gn:admin1_code":"24.0",
    "gn:asciiname":"Houjiayuan",
    "gn:country_code":"CN",
    "gn:dem":753,
    "gn:feature_class":"P",
    "gn:feature_code":"PPL",
    "gn:name":"Houjiayuan",
    "gn:population":0,
    "gn:timezone":"Asia/Shanghai",
    "iso:country":"CN",
    "name:zho_x_preferred":[
        "\u4faf\u5bb6\u539f"
    ],
    "wof:name":"Houjiayuan",
    "wof:placetype":"locality"
},
  "geometry": {"coordinates":[110.48684,36.19195],"type":"Point"}
}