{
  "type": "Feature",
  "properties": {
    "gn:admin1_code":"19",
    "gn:asciiname":"Dapingfang",
    "gn:cc2":"CN",
    "gn:country_code":"CN",
    "gn:dem":209,
    "gn:feature_class":"P",
    "gn:feature_code":"PPL",
    "gn:name":"Dapingfang",
    "gn:population":0,
    "gn:timezone":"Asia/Shanghai",
    "iso:country":"CN",
    "name:und_x_variant":[
        "T\u2019ai-p\u2019ing-fang",
        "Ta-p\u2019ing-fang",
        "Taipingfan",
        "Dapingfang"
    ],
    "wof:name":"Dapingfang",
    "wof:placetype":"locality"
},
  "geometry": {"coordinates":[120.17528,41.42389],"type":"Point"}
}