{
  "type": "Feature",
  "properties": {
    "gn:admin1_code":"14.0",
    "gn:asciiname":"Guoxiongcun",
    "gn:country_code":"CN",
    "gn:dem":4219,
    "gn:feature_class":"P",
    "gn:feature_code":"PPL",
    "gn:name":"Guoxiongcun",
    "gn:population":0,
    "gn:timezone":"Asia/Urumqi",
    "iso:country":"CN",
    "name:zho_x_preferred":[
        "\u90ed\u96c4\u6751"
    ],
    "wof:name":"Guoxiongcun",
    "wof:placetype":"locality"
},
  "geometry": {"coordinates":[93.61745000000001,31.97729],"type":"Point"}
}