{
  "type": "Feature",
  "properties": {
    "gn:admin1_code":"11.0",
    "gn:asciiname":"Yuxing",
    "gn:country_code":"CN",
    "gn:dem":94,
    "gn:feature_class":"P",
    "gn:feature_code":"PPL",
    "gn:name":"Yuxing",
    "gn:population":0,
    "gn:timezone":"Asia/Shanghai",
    "iso:country":"CN",
    "name:zho_x_preferred":[
        "\u9c7c\u5f62"
    ],
    "wof:name":"Yuxing",
    "wof:placetype":"locality"
},
  "geometry": {"coordinates":[113.14122999999999,27.06676],"type":"Point"}
}