{
  "type": "Feature",
  "properties": {
    "gn:admin1_code":"15.0",
    "gn:asciiname":"Hongliuling",
    "gn:country_code":"CN",
    "gn:dem":1079,
    "gn:feature_class":"P",
    "gn:feature_code":"PPL",
    "gn:name":"Hongliuling",
    "gn:population":0,
    "gn:timezone":"Asia/Urumqi",
    "iso:country":"CN",
    "name:zho_x_preferred":[
        "\u7ea2\u67f3\u5cad"
    ],
    "wof:name":"Hongliuling",
    "wof:placetype":"locality"
},
  "geometry": {"coordinates":[95.04349999999999,40.5606],"type":"Point"}
}