{
  "type": "Feature",
  "properties": {
    "gn:admin1_code":"33.0",
    "gn:asciiname":"Tongmeng",
    "gn:country_code":"CN",
    "gn:dem":886,
    "gn:feature_class":"P",
    "gn:feature_code":"PPL",
    "gn:name":"Tongmeng",
    "gn:population":0,
    "gn:timezone":"Asia/Shanghai",
    "iso:country":"CN",
    "name:zho_x_preferred":[
        "\u540c\u76df"
    ],
    "wof:name":"Tongmeng",
    "wof:placetype":"locality"
},
  "geometry": {"coordinates":[107.82844,29.38066],"type":"Point"}
}