{
  "type": "Feature",
  "properties": {
    "gn:admin1_code":"7.0",
    "gn:asciiname":"Pingyu",
    "gn:country_code":"CN",
    "gn:dem":477,
    "gn:feature_class":"P",
    "gn:feature_code":"PPL",
    "gn:name":"Pingyu",
    "gn:population":0,
    "gn:timezone":"Asia/Shanghai",
    "iso:country":"CN",
    "name:zho_x_preferred":[
        "\u576a\u756c"
    ],
    "wof:name":"Pingyu",
    "wof:placetype":"locality"
},
  "geometry": {"coordinates":[118.11721,27.66961],"type":"Point"}
}