{
  "type": "Feature",
  "properties": {
    "gn:admin1_code":"29.0",
    "gn:asciiname":"Zhumi",
    "gn:country_code":"CN",
    "gn:dem":2236,
    "gn:feature_class":"P",
    "gn:feature_code":"PPL",
    "gn:name":"Zhumi",
    "gn:population":0,
    "gn:timezone":"Asia/Shanghai",
    "iso:country":"CN",
    "name:zho_x_preferred":[
        "\u4e3b\u7c73"
    ],
    "wof:name":"Zhumi",
    "wof:placetype":"locality"
},
  "geometry": {"coordinates":[99.37309999999999,26.916],"type":"Point"}
}