{
  "type": "Feature",
  "properties": {
    "gn:admin1_code":"4.0",
    "gn:asciiname":"Xiaxingzhuang",
    "gn:country_code":"CN",
    "gn:dem":1,
    "gn:feature_class":"P",
    "gn:feature_code":"PPL",
    "gn:name":"Xiaxingzhuang",
    "gn:population":0,
    "gn:timezone":"Asia/Shanghai",
    "iso:country":"CN",
    "name:zho_x_preferred":[
        "Xiaxingzhuang"
    ],
    "name:zho_x_variant":[
        "\u4e0b\u5174\u5e84"
    ],
    "wof:name":"Xiaxingzhuang",
    "wof:placetype":"locality"
},
  "geometry": {"coordinates":[119.29208,34.29395],"type":"Point"}
}