{
  "type": "Feature",
  "properties": {
    "gn:admin1_code":"19",
    "gn:asciiname":"Qingyang",
    "gn:country_code":"CN",
    "gn:dem":34,
    "gn:feature_class":"P",
    "gn:feature_code":"PPL",
    "gn:name":"Qingyang",
    "gn:population":0,
    "gn:timezone":"Asia/Shanghai",
    "iso:country":"CN",
    "name:ara_x_preferred":[
        "\u0643\u064a\u0646\u063a\u064a\u0627\u0646\u063a"
    ],
    "name:cdo_x_preferred":[
        "K\u00e9ng-i\u00f2ng"
    ],
    "name:ces_x_preferred":[
        "\u010cching-jang"
    ],
    "name:dan_x_preferred":[
        "Qingyang"
    ],
    "name:deu_x_preferred":[
        "Qingyang"
    ],
    "name:eus_x_preferred":[
        "Qingyang"
    ],
    "name:fas_x_preferred":[
        "\u06a9\u06cc\u0646\u06af\u06cc\u0627\u0646\u06af"
    ],
    "name:fin_x_preferred":[
        "Qingyang"
    ],
    "name:fra_x_preferred":[
        "Qingyang"
    ],
    "name:hye_x_preferred":[
        "\u0551\u056b\u0576\u0575\u0561\u0576"
    ],
    "name:ita_x_preferred":[
        "Qingyang"
    ],
    "name:jpn_x_preferred":[
        "\u6176\u967d\u5e02"
    ],
    "name:kik_x_preferred":[
        "Qingyang"
    ],
    "name:kor_x_preferred":[
        "\uce6d\uc591\uc2dc"
    ],
    "name:mlg_x_preferred":[
        "Qingyang"
    ],
    "name:nld_x_preferred":[
        "Qingyang"
    ],
    "name:nno_x_preferred":[
        "Qingyang"
    ],
    "name:nor_x_preferred":[
        "Qingyang"
    ],
    "name:pam_x_preferred":[
        "Qingyang"
    ],
    "name:pnb_x_preferred":[
        "\u0686\u0646\u06af\u06cc\u0627\u0646\u06af"
    ],
    "name:pol_x_preferred":[
        "Qingyang"
    ],
    "name:rus_x_preferred":[
        "\u0426\u0438\u043d\u044a\u044f\u043d"
    ],
    "name:spa_x_preferred":[
        "Qingyang"
    ],
    "name:swe_x_preferred":[
        "Qingyang"
    ],
    "name:tgl_x_preferred":[
        "Qingyang"
    ],
    "name:tur_x_preferred":[
        "Qingyang"
    ],
    "name:urd_x_preferred":[
        "\u0686\u0646\u06af\u06cc\u0627\u0646\u06af"
    ],
    "name:vie_x_preferred":[
        "Kh\u00e1nh D\u01b0\u01a1ng"
    ],
    "name:war_x_preferred":[
        "Qingyang"
    ],
    "name:wuu_x_preferred":[
        "\u5e86\u9633\u5e02"
    ],
    "name:zho_x_preferred":[
        "\u5e86\u9633\u5e02"
    ],
    "wof:name":"Qingyang",
    "wof:placetype":"locality"
},
  "geometry": {"coordinates":[123.27806,41.25222],"type":"Point"}
}