{
  "type": "Feature",
  "properties": {
    "gn:admin1_code":"1.0",
    "gn:asciiname":"Wangxinzhuangcun",
    "gn:country_code":"CN",
    "gn:dem":31,
    "gn:feature_class":"P",
    "gn:feature_code":"PPL",
    "gn:name":"Wangxinzhuangcun",
    "gn:population":0,
    "gn:timezone":"Asia/Shanghai",
    "iso:country":"CN",
    "name:zho_x_preferred":[
        "\u738b\u65b0\u5e84\u6751"
    ],
    "wof:name":"Wangxinzhuangcun",
    "wof:placetype":"locality"
},
  "geometry": {"coordinates":[116.24556,32.54446],"type":"Point"}
}