{
  "type": "Feature",
  "properties": {
    "gn:admin1_code":"2.0",
    "gn:asciiname":"Chiyuan",
    "gn:country_code":"CN",
    "gn:dem":157,
    "gn:feature_class":"P",
    "gn:feature_code":"PPL",
    "gn:name":"Chiyuan",
    "gn:population":0,
    "gn:timezone":"Asia/Shanghai",
    "iso:country":"CN",
    "name:und_x_variant":[
        "\u8d64\u6e90",
        "Chiyuan"
    ],
    "wof:name":"Chiyuan",
    "wof:placetype":"locality"
},
  "geometry": {"coordinates":[119.11313,29.39451],"type":"Point"}
}