{
  "type": "Feature",
  "properties": {
    "gn:admin1_code":"25",
    "gn:asciiname":"Danbei",
    "gn:country_code":"CN",
    "gn:dem":34,
    "gn:feature_class":"P",
    "gn:feature_code":"PPL",
    "gn:name":"Danbei",
    "gn:population":0,
    "gn:timezone":"Asia/Shanghai",
    "iso:country":"CN",
    "name:zho_x_preferred":[
        "\u65e6\u5317"
    ],
    "wof:name":"Danbei",
    "wof:placetype":"locality"
},
  "geometry": {"coordinates":[116.435,36.4681],"type":"Point"}
}