{
  "type": "Feature",
  "properties": {
    "gn:admin1_code":"29.0",
    "gn:asciiname":"Wusazhuang",
    "gn:country_code":"CN",
    "gn:dem":2033,
    "gn:feature_class":"P",
    "gn:feature_code":"PPL",
    "gn:name":"Wusazhuang",
    "gn:population":0,
    "gn:timezone":"Asia/Shanghai",
    "iso:country":"CN",
    "name:zho_x_preferred":[
        "\u4e4c\u6492\u5e84"
    ],
    "wof:name":"Wusazhuang",
    "wof:placetype":"locality"
},
  "geometry": {"coordinates":[102.95,25.128],"type":"Point"}
}