{
  "type": "Feature",
  "properties": {
    "gn:admin1_code":"1.0",
    "gn:asciiname":"Zhanghan",
    "gn:country_code":"CN",
    "gn:dem":15,
    "gn:feature_class":"P",
    "gn:feature_code":"PPL",
    "gn:name":"Zhanghan",
    "gn:population":0,
    "gn:timezone":"Asia/Shanghai",
    "iso:country":"CN",
    "name:und_x_variant":[
        "Ts\u2019ang-han-ch\u2019iao",
        "Chang-han-ch\u2019iao-t\u2019ou",
        "Zanghanqiao",
        "Zhanghan"
    ],
    "name:zho_x_preferred":[
        "\u85cf\u6c49"
    ],
    "wof:name":"Zhanghan",
    "wof:placetype":"locality"
},
  "geometry": {"coordinates":[118.54446000000002,31.55539000000001],"type":"Point"}
}