{
  "type": "Feature",
  "properties": {
    "gn:admin1_code":"9",
    "gn:asciiname":"Sunxiaolou",
    "gn:country_code":"CN",
    "gn:dem":52,
    "gn:feature_class":"P",
    "gn:feature_code":"PPL",
    "gn:name":"Sunxiaolou",
    "gn:population":0,
    "gn:timezone":"Asia/Shanghai",
    "iso:country":"CN",
    "name:zho_x_preferred":[
        "\u5b59\u5c0f\u697c"
    ],
    "wof:name":"Sunxiaolou",
    "wof:placetype":"locality"
},
  "geometry": {"coordinates":[115.735,34.4595],"type":"Point"}
}