{
  "type": "Feature",
  "properties": {
    "gn:admin1_code":"29.0",
    "gn:asciiname":"Ashuling",
    "gn:country_code":"CN",
    "gn:dem":1733,
    "gn:feature_class":"P",
    "gn:feature_code":"PPL",
    "gn:name":"Ashuling",
    "gn:population":0,
    "gn:timezone":"Asia/Shanghai",
    "iso:country":"CN",
    "name:zho_x_preferred":[
        "\u963f\u6811\u5cad"
    ],
    "wof:name":"Ashuling",
    "wof:placetype":"locality"
},
  "geometry": {"coordinates":[99.65170000000001,25.5769],"type":"Point"}
}