{
  "type": "Feature",
  "properties": {
    "gn:admin1_code":"22.0",
    "gn:asciiname":"Shuiquangoucun",
    "gn:country_code":"CN",
    "gn:dem":491,
    "gn:feature_class":"P",
    "gn:feature_code":"PPL",
    "gn:name":"Shuiquangoucun",
    "gn:population":0,
    "gn:timezone":"Asia/Shanghai",
    "iso:country":"CN",
    "name:zho_x_preferred":[
        "\u6c34\u6cc9\u6c9f\u6751"
    ],
    "wof:name":"Shuiquangoucun",
    "wof:placetype":"locality"
},
  "geometry": {"coordinates":[116.24539,40.41352],"type":"Point"}
}