{
  "type": "Feature",
  "properties": {
    "gn:admin1_code":"3.0",
    "gn:asciiname":"Quankou",
    "gn:country_code":"CN",
    "gn:dem":99,
    "gn:feature_class":"P",
    "gn:feature_code":"PPL",
    "gn:name":"Quankou",
    "gn:population":0,
    "gn:timezone":"Asia/Shanghai",
    "iso:country":"CN",
    "name:und_x_variant":[
        "\u6cc9\u53e3"
    ],
    "wof:name":"Quankou",
    "wof:placetype":"locality"
},
  "geometry": {"coordinates":[114.93616000000002,29.49566],"type":"Point"}
}