{
  "type": "Feature",
  "properties": {
    "gn:admin1_code":"26.0",
    "gn:asciiname":"Dianzicheng",
    "gn:country_code":"CN",
    "gn:dem":417,
    "gn:feature_class":"P",
    "gn:feature_code":"PPLA4",
    "gn:name":"Dianzicheng",
    "gn:population":0,
    "gn:timezone":"Asia/Shanghai",
    "iso:country":"CN",
    "name:und_x_variant":[
        "Dianzicheng Jieban",
        "Dianzicheng"
    ],
    "name:zho_x_preferred":[
        "\u7535\u5b50\u57ce"
    ],
    "name:zho_x_variant":[
        "\u7535\u5b50\u57ce\u8857\u529e"
    ],
    "wof:name":"Dianzicheng",
    "wof:placetype":"locality"
},
  "geometry": {"coordinates":[108.90412999999999,34.19172],"type":"Point"}
}