{
  "type": "Feature",
  "properties": {
    "gn:admin1_code":"24.0",
    "gn:asciiname":"Guojialicun",
    "gn:country_code":"CN",
    "gn:dem":977,
    "gn:feature_class":"P",
    "gn:feature_code":"PPL",
    "gn:name":"Guojialicun",
    "gn:population":0,
    "gn:timezone":"Asia/Shanghai",
    "iso:country":"CN",
    "name:zho_x_preferred":[
        "\u90ed\u5bb6\u91cc\u6751"
    ],
    "wof:name":"Guojialicun",
    "wof:placetype":"locality"
},
  "geometry": {"coordinates":[110.59573,37.95087],"type":"Point"}
}