{
  "type": "Feature",
  "properties": {
    "gn:admin1_code":"16.0",
    "gn:asciiname":"Neile",
    "gn:country_code":"CN",
    "gn:dem":477,
    "gn:feature_class":"P",
    "gn:feature_code":"PPL",
    "gn:name":"Neile",
    "gn:population":0,
    "gn:timezone":"Asia/Shanghai",
    "iso:country":"CN",
    "name:zho_x_preferred":[
        "\u5185\u4e50"
    ],
    "wof:name":"Neile",
    "wof:placetype":"locality"
},
  "geometry": {"coordinates":[107.383,24.6522],"type":"Point"}
}