{
  "type": "Feature",
  "properties": {
    "gn:admin1_code":"25.0",
    "gn:asciiname":"Zhongchijia",
    "gn:country_code":"CN",
    "gn:dem":49,
    "gn:feature_class":"P",
    "gn:feature_code":"PPL",
    "gn:name":"Zhongchijia",
    "gn:population":0,
    "gn:timezone":"Asia/Shanghai",
    "iso:country":"CN",
    "name:zho_x_preferred":[
        "\u4e2d\u8fdf\u5bb6"
    ],
    "wof:name":"Zhongchijia",
    "wof:placetype":"locality"
},
  "geometry": {"coordinates":[120.69887,37.6286],"type":"Point"}
}