{
  "type": "Feature",
  "properties": {
    "gn:admin1_code":"12.0",
    "gn:asciiname":"Dazhuchong",
    "gn:country_code":"CN",
    "gn:dem":181,
    "gn:feature_class":"P",
    "gn:feature_code":"PPL",
    "gn:name":"Dazhuchong",
    "gn:population":0,
    "gn:timezone":"Asia/Shanghai",
    "iso:country":"CN",
    "name:zho_x_preferred":[
        "\u5927\u7af9\u51b2"
    ],
    "wof:name":"Dazhuchong",
    "wof:placetype":"locality"
},
  "geometry": {"coordinates":[115.87302,30.42619],"type":"Point"}
}