{
  "type": "Feature",
  "properties": {
    "gn:admin1_code":"18.0",
    "gn:asciiname":"Huchangcun",
    "gn:country_code":"CN",
    "gn:dem":1115,
    "gn:feature_class":"P",
    "gn:feature_code":"PPL",
    "gn:name":"Huchangcun",
    "gn:population":0,
    "gn:timezone":"Asia/Shanghai",
    "iso:country":"CN",
    "name:zho_x_preferred":[
        "\u864e\u573a\u6751"
    ],
    "wof:name":"Huchangcun",
    "wof:placetype":"locality"
},
  "geometry": {"coordinates":[107.461,27.032],"type":"Point"}
}