{
  "type": "Feature",
  "properties": {
    "gn:admin1_code":"29.0",
    "gn:asciiname":"Aweicai",
    "gn:country_code":"CN",
    "gn:dem":1432,
    "gn:feature_class":"P",
    "gn:feature_code":"PPL",
    "gn:name":"Aweicai",
    "gn:population":0,
    "gn:timezone":"Asia/Shanghai",
    "iso:country":"CN",
    "name:zho_x_preferred":[
        "\u963f\u7ef4\u5f69"
    ],
    "wof:name":"Aweicai",
    "wof:placetype":"locality"
},
  "geometry": {"coordinates":[98.8704,26.0123],"type":"Point"}
}