{
  "type": "Feature",
  "properties": {
    "gn:admin1_code":"7.0",
    "gn:asciiname":"Dingxu",
    "gn:country_code":"CN",
    "gn:dem":11,
    "gn:feature_class":"P",
    "gn:feature_code":"PPL",
    "gn:name":"Dingxu",
    "gn:population":0,
    "gn:timezone":"Asia/Shanghai",
    "iso:country":"CN",
    "name:zho_x_preferred":[
        "\u9876\u8bb8"
    ],
    "wof:name":"Dingxu",
    "wof:placetype":"locality"
},
  "geometry": {"coordinates":[118.00707,24.63229],"type":"Point"}
}