{
  "type": "Feature",
  "properties": {
    "gn:admin1_code":"12.0",
    "gn:asciiname":"Zhugentang",
    "gn:country_code":"CN",
    "gn:dem":33,
    "gn:feature_class":"P",
    "gn:feature_code":"PPL",
    "gn:name":"Zhugentang",
    "gn:population":0,
    "gn:timezone":"Asia/Shanghai",
    "iso:country":"CN",
    "name:zho_x_preferred":[
        "Zhugentang"
    ],
    "name:zho_x_variant":[
        "\u7af9\u6839\u5858"
    ],
    "wof:name":"Zhugentang",
    "wof:placetype":"locality"
},
  "geometry": {"coordinates":[115.28819,30.45941],"type":"Point"}
}