{
  "type": "Feature",
  "properties": {
    "gn:admin1_code":"26",
    "gn:asciiname":"Jinjiahe",
    "gn:country_code":"CN",
    "gn:dem":881,
    "gn:feature_class":"P",
    "gn:feature_code":"PPLA4",
    "gn:name":"Jinjiahe",
    "gn:population":0,
    "gn:timezone":"Asia/Shanghai",
    "iso:country":"CN",
    "name:und_x_variant":[
        "Chin-chia-ho",
        "Jinjiahe",
        "\u91d1\u5bb6\u6cb3",
        "Jinjiahe Zhen",
        "\u91d1\u5bb6\u6cb3\u9547"
    ],
    "wof:name":"Jinjiahe",
    "wof:placetype":"locality"
},
  "geometry": {"coordinates":[105.96702999999999,33.34097],"type":"Point"}
}