{
  "type": "Feature",
  "properties": {
    "gn:admin1_code":"12.0",
    "gn:asciiname":"Cuijiazui",
    "gn:country_code":"CN",
    "gn:dem":124,
    "gn:feature_class":"P",
    "gn:feature_code":"PPL",
    "gn:name":"Cuijiazui",
    "gn:population":0,
    "gn:timezone":"Asia/Shanghai",
    "iso:country":"CN",
    "name:zho_x_preferred":[
        "Cuijiazui"
    ],
    "name:zho_x_variant":[
        "\u5d14\u5bb6\u5480"
    ],
    "wof:name":"Cuijiazui",
    "wof:placetype":"locality"
},
  "geometry": {"coordinates":[111.80616000000001,30.72847],"type":"Point"}
}