{
  "type": "Feature",
  "properties": {
    "gn:admin1_code":"16.0",
    "gn:asciiname":"Buniao",
    "gn:country_code":"CN",
    "gn:dem":524,
    "gn:feature_class":"P",
    "gn:feature_code":"PPL",
    "gn:name":"Buniao",
    "gn:population":0,
    "gn:timezone":"Asia/Shanghai",
    "iso:country":"CN",
    "name:zho_x_preferred":[
        "\u5e03\u9e1f"
    ],
    "wof:name":"Buniao",
    "wof:placetype":"locality"
},
  "geometry": {"coordinates":[106.78,22.9363],"type":"Point"}
}