{
  "type": "Feature",
  "properties": {
    "gn:admin1_code":"11.0",
    "gn:asciiname":"Dayuanzi",
    "gn:country_code":"CN",
    "gn:dem":159,
    "gn:feature_class":"P",
    "gn:feature_code":"PPL",
    "gn:name":"Dayuanzi",
    "gn:population":0,
    "gn:timezone":"Asia/Shanghai",
    "iso:country":"CN",
    "name:zho_x_preferred":[
        "\u5927\u9662\u5b50"
    ],
    "wof:name":"Dayuanzi",
    "wof:placetype":"locality"
},
  "geometry": {"coordinates":[111.32111,26.43222],"type":"Point"}
}