{
  "type": "Feature",
  "properties": {
    "gn:admin1_code":"11.0",
    "gn:asciiname":"Shiliushan",
    "gn:country_code":"CN",
    "gn:dem":721,
    "gn:feature_class":"P",
    "gn:feature_code":"PPL",
    "gn:name":"Shiliushan",
    "gn:population":0,
    "gn:timezone":"Asia/Shanghai",
    "iso:country":"CN",
    "name:zho_x_preferred":[
        "\u77f3\u5218\u5c71"
    ],
    "wof:name":"Shiliushan",
    "wof:placetype":"locality"
},
  "geometry": {"coordinates":[109.39209,26.5201],"type":"Point"}
}