{
  "type": "Feature",
  "properties": {
    "gn:admin1_code":"26.0",
    "gn:asciiname":"Kuaziyan",
    "gn:country_code":"CN",
    "gn:dem":1346,
    "gn:feature_class":"P",
    "gn:feature_code":"PPL",
    "gn:name":"Kuaziyan",
    "gn:population":0,
    "gn:timezone":"Asia/Shanghai",
    "iso:country":"CN",
    "name:und_x_variant":[
        "\u8de8\u5b50\u5ca9"
    ],
    "wof:name":"Kuaziyan",
    "wof:placetype":"locality"
},
  "geometry": {"coordinates":[105.96805000000001,33.61046],"type":"Point"}
}