{
  "type": "Feature",
  "properties": {
    "gn:admin1_code":"10",
    "gn:asciiname":"Huangfu",
    "gn:country_code":"CN",
    "gn:dem":19,
    "gn:feature_class":"P",
    "gn:feature_code":"PPL",
    "gn:name":"Huangfu",
    "gn:population":0,
    "gn:timezone":"Asia/Shanghai",
    "iso:country":"CN",
    "name:kor_x_preferred":[
        "\ud669\ubcf4"
    ],
    "name:und_x_variant":[
        "Huang-fu-ts\u2019un",
        "Huangfu"
    ],
    "name:vie_x_preferred":[
        "Ho\u00e0ng Ph\u1ee7"
    ],
    "name:zho_x_preferred":[
        "\u7687\u752b"
    ],
    "name:zho_x_variant":[
        "\u7687\u752b\u59d3"
    ],
    "wof:name":"Huangfu",
    "wof:placetype":"locality"
},
  "geometry": {"coordinates":[115.824,38.0807],"type":"Point"}
}