{
  "type": "Feature",
  "properties": {
    "gn:admin1_code":"6.0",
    "gn:asciiname":"Eqieneng",
    "gn:country_code":"CN",
    "gn:dem":4308,
    "gn:feature_class":"P",
    "gn:feature_code":"PPL",
    "gn:name":"Eqieneng",
    "gn:population":0,
    "gn:timezone":"Asia/Urumqi",
    "iso:country":"CN",
    "name:zho_x_preferred":[
        "\u4fc4\u5207\u80fd"
    ],
    "wof:name":"Eqieneng",
    "wof:placetype":"locality"
},
  "geometry": {"coordinates":[95.64567,32.19633],"type":"Point"}
}