{
  "type": "Feature",
  "properties": {
    "gn:admin1_code":"21.0",
    "gn:asciiname":"Quyang",
    "gn:country_code":"CN",
    "gn:dem":1093,
    "gn:feature_class":"P",
    "gn:feature_code":"PPL",
    "gn:name":"Quyang",
    "gn:population":0,
    "gn:timezone":"Asia/Shanghai",
    "iso:country":"CN",
    "name:zho_x_preferred":[
        "\u6e20\u7f8a"
    ],
    "wof:name":"Quyang",
    "wof:placetype":"locality"
},
  "geometry": {"coordinates":[106.746,39.0506],"type":"Point"}
}