{
  "type": "Feature",
  "properties": {
    "gn:admin1_code":"5.0",
    "gn:asciiname":"Tiaozihe",
    "gn:country_code":"CN",
    "gn:dem":162,
    "gn:feature_class":"P",
    "gn:feature_code":"PPL",
    "gn:name":"Tiaozihe",
    "gn:population":0,
    "gn:timezone":"Asia/Shanghai",
    "iso:country":"CN",
    "name:zho_x_preferred":[
        "\u6761\u5b50\u6cb3"
    ],
    "wof:name":"Tiaozihe",
    "wof:placetype":"locality"
},
  "geometry": {"coordinates":[124.3353,43.17512],"type":"Point"}
}