{
  "type": "Feature",
  "properties": {
    "gn:admin1_code":"9.0",
    "gn:asciiname":"Beibaopeng",
    "gn:country_code":"CN",
    "gn:dem":190,
    "gn:feature_class":"P",
    "gn:feature_code":"PPL",
    "gn:name":"Beibaopeng",
    "gn:population":0,
    "gn:timezone":"Asia/Shanghai",
    "iso:country":"CN",
    "name:zho_x_preferred":[
        "\u5317\u9c8d\u68da"
    ],
    "wof:name":"Beibaopeng",
    "wof:placetype":"locality"
},
  "geometry": {"coordinates":[113.64807999999999,32.75689000000001],"type":"Point"}
}