{
  "type": "Feature",
  "properties": {
    "gn:admin1_code":"32.0",
    "gn:asciiname":"Dabakou",
    "gn:country_code":"CN",
    "gn:dem":3326,
    "gn:feature_class":"P",
    "gn:feature_code":"PPL",
    "gn:name":"Dabakou",
    "gn:population":0,
    "gn:timezone":"Asia/Shanghai",
    "iso:country":"CN",
    "name:zho_x_preferred":[
        "\u5927\u575d\u53e3"
    ],
    "wof:name":"Dabakou",
    "wof:placetype":"locality"
},
  "geometry": {"coordinates":[101.47157,31.07374],"type":"Point"}
}