{
  "type": "Feature",
  "properties": {
    "gn:admin1_code":"19.0",
    "gn:asciiname":"Dafangshencun",
    "gn:country_code":"CN",
    "gn:dem":103,
    "gn:feature_class":"P",
    "gn:feature_code":"PPL",
    "gn:name":"Dafangshencun",
    "gn:population":0,
    "gn:timezone":"Asia/Shanghai",
    "iso:country":"CN",
    "name:zho_x_preferred":[
        "\u5927\u623f\u8eab\u6751"
    ],
    "wof:name":"Dafangshencun",
    "wof:placetype":"locality"
},
  "geometry": {"coordinates":[123.86426000000002,42.6775],"type":"Point"}
}