{
  "type": "Feature",
  "properties": {
    "gn:admin1_code":"11.0",
    "gn:asciiname":"Yueshan",
    "gn:country_code":"CN",
    "gn:dem":474,
    "gn:feature_class":"P",
    "gn:feature_code":"PPL",
    "gn:name":"Yueshan",
    "gn:population":0,
    "gn:timezone":"Asia/Shanghai",
    "iso:country":"CN",
    "name:zho_x_preferred":[
        "\u6708\u5c71"
    ],
    "wof:name":"Yueshan",
    "wof:placetype":"locality"
},
  "geometry": {"coordinates":[109.60984999999999,26.09538],"type":"Point"}
}