{
  "type": "Feature",
  "properties": {
    "gn:admin1_code":"20.0",
    "gn:asciiname":"Dongchang",
    "gn:country_code":"CN",
    "gn:dem":1589,
    "gn:feature_class":"P",
    "gn:feature_code":"PPL",
    "gn:name":"Dongchang",
    "gn:population":0,
    "gn:timezone":"Asia/Shanghai",
    "iso:country":"CN",
    "name:ceb_x_preferred":[
        "Dongchang"
    ],
    "name:deu_x_preferred":[
        "Dongchang"
    ],
    "name:und_x_variant":[
        "\u4e1c\u573a"
    ],
    "wof:name":"Dongchang",
    "wof:placetype":"locality"
},
  "geometry": {"coordinates":[110.00509,41.38314],"type":"Point"}
}