{
  "type": "Feature",
  "properties": {
    "gn:admin1_code":"29.0",
    "gn:asciiname":"Apiela Yicun",
    "gn:country_code":"CN",
    "gn:dem":2385,
    "gn:feature_class":"P",
    "gn:feature_code":"PPL",
    "gn:name":"Apiela Yicun",
    "gn:population":0,
    "gn:timezone":"Asia/Shanghai",
    "iso:country":"CN",
    "name:zho_x_preferred":[
        "\u963f\u82e4\u62c9\u8fe4\u6751"
    ],
    "wof:name":"Apiela Yicun",
    "wof:placetype":"locality"
},
  "geometry": {"coordinates":[101.111,25.607],"type":"Point"}
}