{
  "type": "Feature",
  "properties": {
    "gn:admin1_code":"32.0",
    "gn:asciiname":"Zeda",
    "gn:country_code":"CN",
    "gn:dem":3586,
    "gn:feature_class":"P",
    "gn:feature_code":"PPL",
    "gn:name":"Zeda",
    "gn:population":0,
    "gn:timezone":"Asia/Shanghai",
    "iso:country":"CN",
    "name:zho_x_preferred":[
        "\u5219\u8fbe"
    ],
    "wof:name":"Zeda",
    "wof:placetype":"locality"
},
  "geometry": {"coordinates":[99.31619999999999,31.5498],"type":"Point"}
}