{
  "type": "Feature",
  "properties": {
    "gn:admin1_code":"3.0",
    "gn:asciiname":"Zhuzhao'an",
    "gn:country_code":"CN",
    "gn:dem":352,
    "gn:feature_class":"P",
    "gn:feature_code":"PPL",
    "gn:name":"Zhuzhao\u2019an",
    "gn:population":0,
    "gn:timezone":"Asia/Shanghai",
    "iso:country":"CN",
    "name:und_x_variant":[
        "Zhuzhao\u2019an",
        "\u7af9\u5146\u5eb5"
    ],
    "wof:name":"Zhuzhao'an",
    "wof:placetype":"locality"
},
  "geometry": {"coordinates":[115.15653,26.36678],"type":"Point"}
}