{
  "type": "Feature",
  "properties": {
    "gn:admin1_code":"2.0",
    "gn:asciiname":"Chengtou",
    "gn:country_code":"CN",
    "gn:dem":6,
    "gn:feature_class":"P",
    "gn:feature_code":"PPL",
    "gn:name":"Chengtou",
    "gn:population":0,
    "gn:timezone":"Asia/Shanghai",
    "iso:country":"CN",
    "name:und_x_variant":[
        "\u57ce\u5934"
    ],
    "wof:name":"Chengtou",
    "wof:placetype":"locality"
},
  "geometry": {"coordinates":[120.23748999999999,30.54019000000001],"type":"Point"}
}