{
  "type": "Feature",
  "properties": {
    "gn:admin1_code":"08",
    "gn:asciiname":"Qixingpao",
    "gn:cc2":"CN",
    "gn:country_code":"CN",
    "gn:dem":95,
    "gn:feature_class":"P",
    "gn:feature_code":"PPL",
    "gn:name":"Qixingpao",
    "gn:population":0,
    "gn:timezone":"Asia/Shanghai",
    "iso:country":"CN",
    "name:und_x_variant":[
        "Ch\u2019i-hsing-p\u2019ao",
        "Qixingpao"
    ],
    "wof:name":"Qixingpao",
    "wof:placetype":"locality"
},
  "geometry": {"coordinates":[131.80806000000001,46.55667],"type":"Point"}
}