{
  "type": "Feature",
  "properties": {
    "gn:admin1_code":"14.0",
    "gn:asciiname":"Zhaya",
    "gn:country_code":"CN",
    "gn:dem":4638,
    "gn:feature_class":"P",
    "gn:feature_code":"PPL",
    "gn:name":"Zhaya",
    "gn:population":0,
    "gn:timezone":"Asia/Urumqi",
    "iso:country":"CN",
    "name:zho_x_preferred":[
        "\u624e\u5440"
    ],
    "wof:name":"Zhaya",
    "wof:placetype":"locality"
},
  "geometry": {"coordinates":[92.18061,31.62812000000001],"type":"Point"}
}