{
  "type": "Feature",
  "properties": {
    "gn:admin1_code":"7.0",
    "gn:asciiname":"Cuntoucun",
    "gn:country_code":"CN",
    "gn:dem":733,
    "gn:feature_class":"P",
    "gn:feature_code":"PPL",
    "gn:name":"Cuntoucun",
    "gn:population":0,
    "gn:timezone":"Asia/Shanghai",
    "iso:country":"CN",
    "name:zho_x_preferred":[
        "\u6751\u5934\u6751"
    ],
    "wof:name":"Cuntoucun",
    "wof:placetype":"locality"
},
  "geometry": {"coordinates":[119.54934,27.49827],"type":"Point"}
}