{
  "type": "Feature",
  "properties": {
    "gn:admin1_code":"18.0",
    "gn:asciiname":"Yi'ai",
    "gn:country_code":"CN",
    "gn:dem":560,
    "gn:feature_class":"P",
    "gn:feature_code":"PPL",
    "gn:name":"Yi\u2019ai",
    "gn:population":0,
    "gn:timezone":"Asia/Shanghai",
    "iso:country":"CN",
    "name:und_x_variant":[
        "Yi\u2019ai"
    ],
    "name:zho_x_preferred":[
        "\u5df2\u57c3"
    ],
    "wof:name":"Yi'ai",
    "wof:placetype":"locality"
},
  "geometry": {"coordinates":[109.24299999999999,25.9328],"type":"Point"}
}