{
  "type": "Feature",
  "properties": {
    "gn:admin1_code":"5.0",
    "gn:asciiname":"Zuojia Diantun",
    "gn:country_code":"CN",
    "gn:dem":143,
    "gn:feature_class":"P",
    "gn:feature_code":"PPL",
    "gn:name":"Zuojia Diantun",
    "gn:population":0,
    "gn:timezone":"Asia/Shanghai",
    "iso:country":"CN",
    "name:zho_x_preferred":[
        "\u5de6\u5bb6\u5e97\u5c6f"
    ],
    "wof:name":"Zuojia Diantun",
    "wof:placetype":"locality"
},
  "geometry": {"coordinates":[123.56305,45.07037],"type":"Point"}
}