{
  "type": "Feature",
  "properties": {
    "gn:admin1_code":"16.0",
    "gn:asciiname":"Weishetun",
    "gn:country_code":"CN",
    "gn:dem":542,
    "gn:feature_class":"P",
    "gn:feature_code":"PPL",
    "gn:name":"Weishetun",
    "gn:population":0,
    "gn:timezone":"Asia/Shanghai",
    "iso:country":"CN",
    "name:zho_x_preferred":[
        "\u6e2d\u793e\u5c6f"
    ],
    "wof:name":"Weishetun",
    "wof:placetype":"locality"
},
  "geometry": {"coordinates":[106.08199999999999,24.3601],"type":"Point"}
}