{
  "type": "Feature",
  "properties": {
    "gn:admin1_code":"19.0",
    "gn:asciiname":"Erdaogoucun",
    "gn:country_code":"CN",
    "gn:dem":246,
    "gn:feature_class":"P",
    "gn:feature_code":"PPL",
    "gn:name":"Erdaogoucun",
    "gn:population":0,
    "gn:timezone":"Asia/Shanghai",
    "iso:country":"CN",
    "name:und_x_variant":[
        "\u4e8c\u9053\u6c9f\u6751"
    ],
    "wof:name":"Erdaogoucun",
    "wof:placetype":"locality"
},
  "geometry": {"coordinates":[124.22998,41.74055],"type":"Point"}
}