{
  "type": "Feature",
  "properties": {
    "gn:admin1_code":"19.0",
    "gn:asciiname":"Tangzhangzicun",
    "gn:country_code":"CN",
    "gn:dem":486,
    "gn:feature_class":"P",
    "gn:feature_code":"PPL",
    "gn:name":"Tangzhangzicun",
    "gn:population":0,
    "gn:timezone":"Asia/Shanghai",
    "iso:country":"CN",
    "name:zho_x_preferred":[
        "\u6c64\u6756\u5b50\u6751"
    ],
    "wof:name":"Tangzhangzicun",
    "wof:placetype":"locality"
},
  "geometry": {"coordinates":[119.43300000000001,41.0632],"type":"Point"}
}