{
  "type": "Feature",
  "properties": {
    "gn:admin1_code":"11",
    "gn:asciiname":"Dadian",
    "gn:country_code":"CN",
    "gn:dem":370,
    "gn:feature_class":"P",
    "gn:feature_code":"PPL",
    "gn:name":"Dadian",
    "gn:population":0,
    "gn:timezone":"Asia/Shanghai",
    "iso:country":"CN",
    "wof:name":"Dadian",
    "wof:placetype":"locality"
},
  "geometry": {"coordinates":[110.73389,26.68306],"type":"Point"}
}