{
  "type": "Feature",
  "properties": {
    "gn:admin1_code":"3.0",
    "gn:asciiname":"Luomutang",
    "gn:country_code":"CN",
    "gn:dem":330,
    "gn:feature_class":"P",
    "gn:feature_code":"PPL",
    "gn:name":"Luomutang",
    "gn:population":0,
    "gn:timezone":"Asia/Shanghai",
    "iso:country":"CN",
    "name:und_x_variant":[
        "\u7f57\u6728\u5858"
    ],
    "wof:name":"Luomutang",
    "wof:placetype":"locality"
},
  "geometry": {"coordinates":[115.56717,26.58089],"type":"Point"}
}