{
  "type": "Feature",
  "properties": {
    "gn:admin1_code":"32.0",
    "gn:asciiname":"Songyu",
    "gn:country_code":"CN",
    "gn:dem":3215,
    "gn:feature_class":"P",
    "gn:feature_code":"PPL",
    "gn:name":"Songyu",
    "gn:population":0,
    "gn:timezone":"Asia/Shanghai",
    "iso:country":"CN",
    "name:zho_x_preferred":[
        "\u5b8b\u7389"
    ],
    "wof:name":"Songyu",
    "wof:placetype":"locality"
},
  "geometry": {"coordinates":[101.1016,29.36269],"type":"Point"}
}