{
  "type": "Feature",
  "properties": {
    "gn:admin1_code":"32.0",
    "gn:asciiname":"Lifangzui",
    "gn:country_code":"CN",
    "gn:dem":399,
    "gn:feature_class":"P",
    "gn:feature_code":"PPL",
    "gn:name":"Lifangzui",
    "gn:population":0,
    "gn:timezone":"Asia/Shanghai",
    "iso:country":"CN",
    "name:zho_x_preferred":[
        "\u674e\u65b9\u5480"
    ],
    "wof:name":"Lifangzui",
    "wof:placetype":"locality"
},
  "geometry": {"coordinates":[104.01106,29.66446],"type":"Point"}
}