{
  "type": "Feature",
  "properties": {
    "gn:admin1_code":"31.0",
    "gn:asciiname":"Xinzai",
    "gn:country_code":"CN",
    "gn:dem":272,
    "gn:feature_class":"P",
    "gn:feature_code":"PPL",
    "gn:name":"Xinzai",
    "gn:population":0,
    "gn:timezone":"Asia/Shanghai",
    "iso:country":"CN",
    "name:und_x_variant":[
        "\u65b0\u4ed4"
    ],
    "name:zho_x_preferred":[
        "\u65b0\u4ed4"
    ],
    "wof:name":"Xinzai",
    "wof:placetype":"locality"
},
  "geometry": {"coordinates":[109.92179,19.16867],"type":"Point"}
}