{
  "type": "Feature",
  "properties": {
    "gn:admin1_code":"3.0",
    "gn:asciiname":"Xiaoshuiku",
    "gn:country_code":"CN",
    "gn:dem":62,
    "gn:feature_class":"P",
    "gn:feature_code":"PPL",
    "gn:name":"Xiaoshuiku",
    "gn:population":0,
    "gn:timezone":"Asia/Shanghai",
    "iso:country":"CN",
    "name:und_x_variant":[
        "\u5c0f\u6c34\u7a9f"
    ],
    "wof:name":"Xiaoshuiku",
    "wof:placetype":"locality"
},
  "geometry": {"coordinates":[115.08958,28.15196],"type":"Point"}
}