{
  "type": "Feature",
  "properties": {
    "gn:admin1_code":"18",
    "gn:asciiname":"Lagu",
    "gn:country_code":"CN",
    "gn:dem":1164,
    "gn:feature_class":"P",
    "gn:feature_code":"PPL",
    "gn:name":"Lagu",
    "gn:population":0,
    "gn:timezone":"Asia/Shanghai",
    "iso:country":"CN",
    "name:rus_x_preferred":[
        "\u041b\u0430\u0433\u0443"
    ],
    "name:zho_x_preferred":[
        "\u62c9\u6545"
    ],
    "wof:name":"Lagu",
    "wof:placetype":"locality"
},
  "geometry": {"coordinates":[106.901,25.7587],"type":"Point"}
}