{
  "type": "Feature",
  "properties": {
    "gn:admin1_code":"24.0",
    "gn:asciiname":"Qianhongtuliang",
    "gn:country_code":"CN",
    "gn:dem":1259,
    "gn:feature_class":"P",
    "gn:feature_code":"PPL",
    "gn:name":"Qianhongtuliang",
    "gn:population":0,
    "gn:timezone":"Asia/Shanghai",
    "iso:country":"CN",
    "name:zho_x_preferred":[
        "\u524d\u7ea2\u571f\u6881"
    ],
    "wof:name":"Qianhongtuliang",
    "wof:placetype":"locality"
},
  "geometry": {"coordinates":[111.36323,36.30622],"type":"Point"}
}