{
  "type": "Feature",
  "properties": {
    "gn:admin1_code":"5.0",
    "gn:asciiname":"Jiuhaocun",
    "gn:country_code":"CN",
    "gn:dem":194,
    "gn:feature_class":"P",
    "gn:feature_code":"PPL",
    "gn:name":"Jiuhaocun",
    "gn:population":0,
    "gn:timezone":"Asia/Shanghai",
    "iso:country":"CN",
    "name:zho_x_preferred":[
        "\u4e5d\u53f7\u6751"
    ],
    "wof:name":"Jiuhaocun",
    "wof:placetype":"locality"
},
  "geometry": {"coordinates":[126.40018999999999,45.07931],"type":"Point"}
}