{
  "type": "Feature",
  "properties": {
    "gn:admin1_code":"2",
    "gn:asciiname":"Shantougang",
    "gn:country_code":"CN",
    "gn:dem":793,
    "gn:feature_class":"P",
    "gn:feature_code":"PPL",
    "gn:name":"Shantougang",
    "gn:population":0,
    "gn:timezone":"Asia/Shanghai",
    "iso:country":"CN",
    "name:zho_x_preferred":[
        "\u5c71\u5934\u5c97"
    ],
    "wof:name":"Shantougang",
    "wof:placetype":"locality"
},
  "geometry": {"coordinates":[118.94194,27.50722],"type":"Point"}
}