{
  "type": "Feature",
  "properties": {
    "gn:admin1_code":"32.0",
    "gn:asciiname":"Zuishang",
    "gn:country_code":"CN",
    "gn:dem":416,
    "gn:feature_class":"P",
    "gn:feature_code":"PPL",
    "gn:name":"Zuishang",
    "gn:population":0,
    "gn:timezone":"Asia/Shanghai",
    "iso:country":"CN",
    "name:zho_x_preferred":[
        "\u5480\u4e0a"
    ],
    "wof:name":"Zuishang",
    "wof:placetype":"locality"
},
  "geometry": {"coordinates":[104.85487999999999,28.85245],"type":"Point"}
}