{
  "type": "Feature",
  "properties": {
    "gn:admin1_code":"18",
    "gn:asciiname":"Longtang",
    "gn:country_code":"CN",
    "gn:dem":835,
    "gn:feature_class":"P",
    "gn:feature_code":"PPL",
    "gn:name":"Longtang",
    "gn:population":0,
    "gn:timezone":"Asia/Shanghai",
    "iso:country":"CN",
    "name:zho_x_preferred":[
        "\u9f99\u5858"
    ],
    "wof:name":"Longtang",
    "wof:placetype":"locality"
},
  "geometry": {"coordinates":[106.55500000000001,28.0433],"type":"Point"}
}