{
  "type": "Feature",
  "properties": {
    "gn:admin1_code":"10",
    "gn:asciiname":"Qiaomuliang",
    "gn:country_code":"CN",
    "gn:dem":315,
    "gn:feature_class":"P",
    "gn:feature_code":"PPL",
    "gn:name":"Qiaomuliang",
    "gn:population":0,
    "gn:timezone":"Asia/Shanghai",
    "iso:country":"CN",
    "name:zho_x_preferred":[
        "\u6865\u6728\u6881"
    ],
    "wof:name":"Qiaomuliang",
    "wof:placetype":"locality"
},
  "geometry": {"coordinates":[118.01802000000001,40.60342],"type":"Point"}
}