{
  "type": "Feature",
  "properties": {
    "gn:admin1_code":"12.0",
    "gn:asciiname":"Shangzhujiazui",
    "gn:country_code":"CN",
    "gn:dem":28,
    "gn:feature_class":"P",
    "gn:feature_code":"PPL",
    "gn:name":"Shangzhujiazui",
    "gn:population":0,
    "gn:timezone":"Asia/Shanghai",
    "iso:country":"CN",
    "name:zho_x_preferred":[
        "\u4e0a\u6731\u5bb6\u5480"
    ],
    "wof:name":"Shangzhujiazui",
    "wof:placetype":"locality"
},
  "geometry": {"coordinates":[113.02818000000001,30.69937],"type":"Point"}
}