{
  "type": "Feature",
  "properties": {
    "gn:admin1_code":"14.0",
    "gn:asciiname":"Gabxi",
    "gn:country_code":"CN",
    "gn:dem":4103,
    "gn:feature_class":"P",
    "gn:feature_code":"PPL",
    "gn:name":"Gabxi",
    "gn:population":0,
    "gn:timezone":"Asia/Urumqi",
    "iso:country":"CN",
    "name:bod_x_preferred":[
        "Gabxi"
    ],
    "name:zho_x_preferred":[
        "Gebuxi"
    ],
    "name:zho_x_variant":[
        "\u683c\u5e03\u897f",
        "Zijin Gongshe",
        "\u7d2b\u91d1\u516c\u793e"
    ],
    "wof:name":"Gabxi",
    "wof:placetype":"locality"
},
  "geometry": {"coordinates":[89.50299999999999,28.903],"type":"Point"}
}