{
  "type": "Feature",
  "properties": {
    "gn:admin1_code":"26.0",
    "gn:asciiname":"Yujianba",
    "gn:country_code":"CN",
    "gn:dem":713,
    "gn:feature_class":"P",
    "gn:feature_code":"PPL",
    "gn:name":"Yujianba",
    "gn:population":0,
    "gn:timezone":"Asia/Shanghai",
    "iso:country":"CN",
    "name:und_x_variant":[
        "\u9c7c\u526a\u575d"
    ],
    "wof:name":"Yujianba",
    "wof:placetype":"locality"
},
  "geometry": {"coordinates":[106.04004,33.45325],"type":"Point"}
}