{
  "type": "Feature",
  "properties": {
    "gn:admin1_code":"3.0",
    "gn:asciiname":"Nanyinping",
    "gn:country_code":"CN",
    "gn:dem":531,
    "gn:feature_class":"P",
    "gn:feature_code":"PPL",
    "gn:name":"Nanyinping",
    "gn:population":0,
    "gn:timezone":"Asia/Shanghai",
    "iso:country":"CN",
    "name:zho_x_preferred":[
        "\u5357\u9634\u576a"
    ],
    "wof:name":"Nanyinping",
    "wof:placetype":"locality"
},
  "geometry": {"coordinates":[114.996,29.4027],"type":"Point"}
}