{
  "type": "Feature",
  "properties": {
    "gn:admin1_code":"11.0",
    "gn:asciiname":"Lashuxia",
    "gn:country_code":"CN",
    "gn:dem":516,
    "gn:feature_class":"P",
    "gn:feature_code":"PPL",
    "gn:name":"Lashuxia",
    "gn:population":0,
    "gn:timezone":"Asia/Shanghai",
    "iso:country":"CN",
    "name:zho_x_preferred":[
        "\u814a\u6811\u4e0b"
    ],
    "wof:name":"Lashuxia",
    "wof:placetype":"locality"
},
  "geometry": {"coordinates":[113.77188,25.77097],"type":"Point"}
}