{
  "type": "Feature",
  "properties": {
    "gn:admin1_code":"01",
    "gn:asciiname":"Huaishudian",
    "gn:cc2":"CN",
    "gn:country_code":"CN",
    "gn:dem":59,
    "gn:feature_class":"P",
    "gn:feature_code":"PPL",
    "gn:name":"Huaishudian",
    "gn:population":0,
    "gn:timezone":"Asia/Shanghai",
    "iso:country":"CN",
    "name:und_x_variant":[
        "Huai-shu-tien",
        "Huaishudian"
    ],
    "wof:name":"Huaishudian",
    "wof:placetype":"locality"
},
  "geometry": {"coordinates":[117.49056000000002,32.02861],"type":"Point"}
}