{
  "type": "Feature",
  "properties": {
    "gn:admin1_code":"29",
    "gn:asciiname":"Anudai",
    "gn:country_code":"CN",
    "gn:dem":1969,
    "gn:feature_class":"P",
    "gn:feature_code":"PPL",
    "gn:name":"Anudai",
    "gn:population":0,
    "gn:timezone":"Asia/Shanghai",
    "iso:country":"CN",
    "name:zho_x_preferred":[
        "\u963f\u52aa\u4ee3"
    ],
    "wof:name":"Anudai",
    "wof:placetype":"locality"
},
  "geometry": {"coordinates":[101.90000000000001,23.9943],"type":"Point"}
}