{
  "type": "Feature",
  "properties": {
    "gn:admin1_code":"29.0",
    "gn:asciiname":"Xialuoliang",
    "gn:country_code":"CN",
    "gn:dem":1905,
    "gn:feature_class":"P",
    "gn:feature_code":"PPL",
    "gn:name":"Xialuoliang",
    "gn:population":0,
    "gn:timezone":"Asia/Shanghai",
    "iso:country":"CN",
    "name:zho_x_preferred":[
        "\u4e0b\u7f57\u826f"
    ],
    "wof:name":"Xialuoliang",
    "wof:placetype":"locality"
},
  "geometry": {"coordinates":[103.098,25.2351],"type":"Point"}
}