{
  "type": "Feature",
  "properties": {
    "gn:admin1_code":"24",
    "gn:asciiname":"Lingdong",
    "gn:country_code":"CN",
    "gn:dem":1392,
    "gn:feature_class":"P",
    "gn:feature_code":"PPL",
    "gn:name":"Lingdong",
    "gn:population":0,
    "gn:timezone":"Asia/Shanghai",
    "iso:country":"CN",
    "name:zho_x_preferred":[
        "\u5cad\u4e1c"
    ],
    "wof:name":"Lingdong",
    "wof:placetype":"locality"
},
  "geometry": {"coordinates":[113.54127,35.71827000000001],"type":"Point"}
}