{
  "type": "Feature",
  "properties": {
    "gn:admin1_code":"3.0",
    "gn:asciiname":"Fenggusi",
    "gn:country_code":"CN",
    "gn:dem":159,
    "gn:feature_class":"P",
    "gn:feature_code":"PPL",
    "gn:name":"Fenggusi",
    "gn:population":0,
    "gn:timezone":"Asia/Shanghai",
    "iso:country":"CN",
    "name:und_x_variant":[
        "\u5949\u8c37\u5bfa"
    ],
    "wof:name":"Fenggusi",
    "wof:placetype":"locality"
},
  "geometry": {"coordinates":[114.52825,27.2831],"type":"Point"}
}