{
  "type": "Feature",
  "properties": {
    "gn:admin1_code":"16.0",
    "gn:asciiname":"Linghu",
    "gn:country_code":"CN",
    "gn:dem":61,
    "gn:feature_class":"P",
    "gn:feature_code":"PPL",
    "gn:name":"Linghu",
    "gn:population":0,
    "gn:timezone":"Asia/Shanghai",
    "iso:country":"CN",
    "name:rus_x_preferred":[
        "\u041b\u0438\u043d\u0445\u0443"
    ],
    "name:vie_x_preferred":[
        "L\u1ec7nh H\u1ed3"
    ],
    "name:zho_x_preferred":[
        "\u5cad\u62a4"
    ],
    "name:zho_x_variant":[
        "\u4ee4\u72d0\u59d3"
    ],
    "wof:name":"Linghu",
    "wof:placetype":"locality"
},
  "geometry": {"coordinates":[109.745,22.8665],"type":"Point"}
}