{
  "type": "Feature",
  "properties": {
    "gn:admin1_code":"32.0",
    "gn:asciiname":"Aidi",
    "gn:country_code":"CN",
    "gn:dem":3615,
    "gn:feature_class":"P",
    "gn:feature_code":"PPL",
    "gn:name":"Aidi",
    "gn:population":0,
    "gn:timezone":"Asia/Shanghai",
    "iso:country":"CN",
    "name:ara_x_preferred":[
        "\u0622\u064a\u062f\u064a"
    ],
    "name:bul_x_preferred":[
        "\u0410\u0438\u0434\u0438"
    ],
    "name:ces_x_preferred":[
        "Aidi"
    ],
    "name:deu_x_preferred":[
        "A\u00efdi"
    ],
    "name:est_x_preferred":[
        "A\u00efdi"
    ],
    "name:fin_x_preferred":[
        "Aidi"
    ],
    "name:fra_x_preferred":[
        "A\u00efdi"
    ],
    "name:heb_x_preferred":[
        "\u05d0\u05d9\u05d3\u05d9"
    ],
    "name:hin_x_preferred":[
        "\u090f\u0921\u0940"
    ],
    "name:hun_x_preferred":[
        "Atlaszi hegyikutya"
    ],
    "name:ita_x_preferred":[
        "Cane dell'Atlas"
    ],
    "name:jpn_x_preferred":[
        "\u30a2\u30a4\u30c7\u30a3"
    ],
    "name:msa_x_preferred":[
        "Aidi"
    ],
    "name:nld_x_preferred":[
        "Aidi"
    ],
    "name:nor_x_preferred":[
        "Aidi"
    ],
    "name:pnb_x_preferred":[
        "\u0627\u06cc\u0688\u06cc"
    ],
    "name:pol_x_preferred":[
        "Aidi"
    ],
    "name:por_x_preferred":[
        "Aidi"
    ],
    "name:rus_x_preferred":[
        "\u0410\u0438\u0434\u0438"
    ],
    "name:slk_x_preferred":[
        "Aidi"
    ],
    "name:spa_x_preferred":[
        "A\u00efdi"
    ],
    "name:swe_x_preferred":[
        "Aidi"
    ],
    "name:tur_x_preferred":[
        "Aidi"
    ],
    "name:vie_x_preferred":[
        "Ch\u00f3 Aidi"
    ],
    "name:zho_x_preferred":[
        "\u57c3\u5730"
    ],
    "wof:name":"Aidi",
    "wof:placetype":"locality"
},
  "geometry": {"coordinates":[100.68300000000001,29.0335],"type":"Point"}
}