{
  "type": "Feature",
  "properties": {
    "gn:admin1_code":"32.0",
    "gn:asciiname":"Aidi",
    "gn:country_code":"CN",
    "gn:dem":3615,
    "gn:feature_class":"P",
    "gn:feature_code":"PPL",
    "gn:name":"Aidi",
    "gn:population":0,
    "gn:timezone":"Asia/Shanghai",
    "iso:country":"CN",
    "name:zho_x_preferred":[
        "\u57c3\u5730"
    ],
    "wof:name":"Aidi",
    "wof:placetype":"locality"
},
  "geometry": {"coordinates":[100.68300000000001,29.0335],"type":"Point"}
}