{
  "type": "Feature",
  "properties": {
    "gn:admin1_code":"3.0",
    "gn:asciiname":"Yunlin",
    "gn:country_code":"CN",
    "gn:dem":428,
    "gn:feature_class":"P",
    "gn:feature_code":"PPL",
    "gn:name":"Yunlin",
    "gn:population":0,
    "gn:timezone":"Asia/Shanghai",
    "iso:country":"CN",
    "name:fas_x_preferred":[
        "\u06cc\u0648\u0646\u0644\u06cc\u0646"
    ],
    "name:heb_x_preferred":[
        "\u05d9\u05d5\u05e0\u05dc\u05d9\u05df"
    ],
    "name:hun_x_preferred":[
        "Yunlin"
    ],
    "name:und_x_variant":[
        "\u4e91\u6797"
    ],
    "wof:name":"Yunlin",
    "wof:placetype":"locality"
},
  "geometry": {"coordinates":[114.59483,28.45768],"type":"Point"}
}