{
  "type": "Feature",
  "properties": {
    "gn:admin1_code":"3.0",
    "gn:asciiname":"Bianjiecun",
    "gn:country_code":"CN",
    "gn:dem":431,
    "gn:feature_class":"P",
    "gn:feature_code":"PPL",
    "gn:name":"Bianjiecun",
    "gn:population":0,
    "gn:timezone":"Asia/Shanghai",
    "iso:country":"CN",
    "name:und_x_variant":[
        "\u8fb9\u754c\u6751"
    ],
    "wof:name":"Bianjiecun",
    "wof:placetype":"locality"
},
  "geometry": {"coordinates":[116.24451999999999,26.67345],"type":"Point"}
}