{
  "type": "Feature",
  "properties": {
    "gn:admin1_code":"5.0",
    "gn:asciiname":"Xiaobanshigou",
    "gn:country_code":"CN",
    "gn:dem":521,
    "gn:feature_class":"P",
    "gn:feature_code":"PPL",
    "gn:name":"Xiaobanshigou",
    "gn:population":0,
    "gn:timezone":"Asia/Shanghai",
    "iso:country":"CN",
    "name:zho_x_preferred":[
        "\u5c0f\u677f\u77f3\u6c9f"
    ],
    "wof:name":"Xiaobanshigou",
    "wof:placetype":"locality"
},
  "geometry": {"coordinates":[126.43623999999998,41.97877],"type":"Point"}
}