{
  "type": "Feature",
  "properties": {
    "gn:admin1_code":"29",
    "gn:asciiname":"Bannei",
    "gn:country_code":"CN",
    "gn:dem":1542,
    "gn:feature_class":"P",
    "gn:feature_code":"PPL",
    "gn:name":"Bannei",
    "gn:population":0,
    "gn:timezone":"Asia/Shanghai",
    "iso:country":"CN",
    "name:zho_x_preferred":[
        "\u677f\u5185"
    ],
    "wof:name":"Bannei",
    "wof:placetype":"locality"
},
  "geometry": {"coordinates":[104.789,24.2106],"type":"Point"}
}