{
  "type": "Feature",
  "properties": {
    "gn:admin1_code":"9.0",
    "gn:asciiname":"Kaolinggang",
    "gn:country_code":"CN",
    "gn:dem":374,
    "gn:feature_class":"P",
    "gn:feature_code":"PPL",
    "gn:name":"Kaolinggang",
    "gn:population":0,
    "gn:timezone":"Asia/Shanghai",
    "iso:country":"CN",
    "name:zho_x_preferred":[
        "\u8003\u5cad\u5c97"
    ],
    "wof:name":"Kaolinggang",
    "wof:placetype":"locality"
},
  "geometry": {"coordinates":[115.21216,31.59973],"type":"Point"}
}