{
  "type": "Feature",
  "properties": {
    "gn:admin1_code":"8.0",
    "gn:asciiname":"Qianlijia",
    "gn:country_code":"CN",
    "gn:dem":212,
    "gn:feature_class":"P",
    "gn:feature_code":"PPL",
    "gn:name":"Qianlijia",
    "gn:population":0,
    "gn:timezone":"Asia/Shanghai",
    "iso:country":"CN",
    "name:zho_x_preferred":[
        "\u524d\u6817\u5bb6"
    ],
    "wof:name":"Qianlijia",
    "wof:placetype":"locality"
},
  "geometry": {"coordinates":[127.83271000000001,46.93568],"type":"Point"}
}