{
  "type": "Feature",
  "properties": {
    "gn:admin1_code":"7.0",
    "gn:asciiname":"Qinglishan",
    "gn:country_code":"CN",
    "gn:dem":654,
    "gn:feature_class":"P",
    "gn:feature_code":"PPL",
    "gn:name":"Qinglishan",
    "gn:population":0,
    "gn:timezone":"Asia/Shanghai",
    "iso:country":"CN",
    "name:und_x_variant":[
        "\u9752\u91cc\u5c71"
    ],
    "name:zho_x_preferred":[
        "\u9752\u91cc\u5c71"
    ],
    "wof:name":"Qinglishan",
    "wof:placetype":"locality"
},
  "geometry": {"coordinates":[117.59708000000001,26.08526],"type":"Point"}
}