{
  "type": "Feature",
  "properties": {
    "gn:admin1_code":"18",
    "gn:asciiname":"Yuetianhe",
    "gn:country_code":"CN",
    "gn:dem":554,
    "gn:feature_class":"P",
    "gn:feature_code":"PPL",
    "gn:name":"Yuetianhe",
    "gn:population":0,
    "gn:timezone":"Asia/Shanghai",
    "iso:country":"CN",
    "name:zho_x_preferred":[
        "\u8dc3\u7530\u6cb3"
    ],
    "wof:name":"Yuetianhe",
    "wof:placetype":"locality"
},
  "geometry": {"coordinates":[108.13200000000001,27.4437],"type":"Point"}
}