{
  "type": "Feature",
  "properties": {
    "gn:admin1_code":"23",
    "gn:asciiname":"Changzheng Nongchang",
    "gn:country_code":"CN",
    "gn:dem":2,
    "gn:feature_class":"P",
    "gn:feature_code":"PPLF",
    "gn:name":"Changzheng Nongchang",
    "gn:population":0,
    "gn:timezone":"Asia/Shanghai",
    "iso:country":"CN",
    "name:und_x_variant":[
        "Changzheng",
        "Changzheng Nongchang"
    ],
    "wof:name":"Changzheng Nongchang",
    "wof:placetype":"locality"
},
  "geometry": {"coordinates":[121.42,31.76028],"type":"Point"}
}