{
  "type": "Feature",
  "properties": {
    "gn:admin1_code":"32.0",
    "gn:asciiname":"Bajiaomiao",
    "gn:country_code":"CN",
    "gn:dem":428,
    "gn:feature_class":"P",
    "gn:feature_code":"PPL",
    "gn:name":"Bajiaomiao",
    "gn:population":0,
    "gn:timezone":"Asia/Shanghai",
    "iso:country":"CN",
    "name:zho_x_preferred":[
        "\u516b\u89d2\u5e99"
    ],
    "wof:name":"Bajiaomiao",
    "wof:placetype":"locality"
},
  "geometry": {"coordinates":[105.002,30.2022],"type":"Point"}
}