{
  "type": "Feature",
  "properties": {
    "gn:admin1_code":"29.0",
    "gn:asciiname":"Diantou",
    "gn:country_code":"CN",
    "gn:dem":2251,
    "gn:feature_class":"P",
    "gn:feature_code":"PPL",
    "gn:name":"Diantou",
    "gn:population":0,
    "gn:timezone":"Asia/Shanghai",
    "iso:country":"CN",
    "name:zho_x_preferred":[
        "\u7538\u5934"
    ],
    "wof:name":"Diantou",
    "wof:placetype":"locality"
},
  "geometry": {"coordinates":[99.9211,26.5732],"type":"Point"}
}