{
  "type": "Feature",
  "properties": {
    "gn:admin1_code":"14.0",
    "gn:asciiname":"Niyacun",
    "gn:country_code":"CN",
    "gn:dem":3716,
    "gn:feature_class":"P",
    "gn:feature_code":"PPL",
    "gn:name":"Niyacun",
    "gn:population":0,
    "gn:timezone":"Asia/Urumqi",
    "iso:country":"CN",
    "name:zho_x_preferred":[
        "\u5c3c\u4e9a\u6751"
    ],
    "wof:name":"Niyacun",
    "wof:placetype":"locality"
},
  "geometry": {"coordinates":[95.37015,31.1037],"type":"Point"}
}