{
  "type": "Feature",
  "properties": {
    "gn:admin1_code":"30.0",
    "gn:asciiname":"Fengma Yicun",
    "gn:country_code":"CN",
    "gn:dem":-3,
    "gn:feature_class":"P",
    "gn:feature_code":"PPL",
    "gn:name":"Fengma Yicun",
    "gn:population":0,
    "gn:timezone":"Asia/Shanghai",
    "iso:country":"CN",
    "name:zho_x_preferred":[
        "\u99ae\u99ac\u4e00\u6751"
    ],
    "wof:name":"Fengma Yicun",
    "wof:placetype":"locality"
},
  "geometry": {"coordinates":[113.47957,22.7216],"type":"Point"}
}