{
  "type": "Feature",
  "properties": {
    "gn:admin1_code":"26.0",
    "gn:asciiname":"Taowan",
    "gn:country_code":"CN",
    "gn:dem":997,
    "gn:feature_class":"P",
    "gn:feature_code":"PPL",
    "gn:name":"Taowan",
    "gn:population":0,
    "gn:timezone":"Asia/Shanghai",
    "iso:country":"CN",
    "name:zho_x_preferred":[
        "\u6843\u6e7e"
    ],
    "wof:name":"Taowan",
    "wof:placetype":"locality"
},
  "geometry": {"coordinates":[109.05992999999999,35.92997000000001],"type":"Point"}
}