{
  "type": "Feature",
  "properties": {
    "gn:admin1_code":"15.0",
    "gn:asciiname":"Goukou",
    "gn:country_code":"CN",
    "gn:dem":1985,
    "gn:feature_class":"P",
    "gn:feature_code":"PPL",
    "gn:name":"Goukou",
    "gn:population":0,
    "gn:timezone":"Asia/Shanghai",
    "iso:country":"CN",
    "name:zho_x_preferred":[
        "\u6c9f\u53e3"
    ],
    "wof:name":"Goukou",
    "wof:placetype":"locality"
},
  "geometry": {"coordinates":[103.901,37.1268],"type":"Point"}
}