{
  "type": "Feature",
  "properties": {
    "gn:admin1_code":"12.0",
    "gn:asciiname":"Chenjia Laowu",
    "gn:country_code":"CN",
    "gn:dem":342,
    "gn:feature_class":"P",
    "gn:feature_code":"PPL",
    "gn:name":"Chenjia Laowu",
    "gn:population":0,
    "gn:timezone":"Asia/Shanghai",
    "iso:country":"CN",
    "name:zho_x_preferred":[
        "\u9648\u5bb6\u8001\u5c4b"
    ],
    "wof:name":"Chenjia Laowu",
    "wof:placetype":"locality"
},
  "geometry": {"coordinates":[111.61456,31.71331],"type":"Point"}
}