{
  "type": "Feature",
  "properties": {
    "gn:admin1_code":"26.0",
    "gn:asciiname":"Qianjiapingcun",
    "gn:country_code":"CN",
    "gn:dem":748,
    "gn:feature_class":"P",
    "gn:feature_code":"PPL",
    "gn:name":"Qianjiapingcun",
    "gn:population":0,
    "gn:timezone":"Asia/Shanghai",
    "iso:country":"CN",
    "name:zho_x_preferred":[
        "\u5343\u5bb6\u576a\u6751"
    ],
    "wof:name":"Qianjiapingcun",
    "wof:placetype":"locality"
},
  "geometry": {"coordinates":[110.67768999999998,33.34492],"type":"Point"}
}