{
  "type": "Feature",
  "properties": {
    "gn:admin1_code":"19.0",
    "gn:asciiname":"Xiaomintun",
    "gn:country_code":"CN",
    "gn:dem":28,
    "gn:feature_class":"P",
    "gn:feature_code":"PPL",
    "gn:name":"Xiaomintun",
    "gn:population":0,
    "gn:timezone":"Asia/Shanghai",
    "iso:country":"CN",
    "name:und_x_variant":[
        "\u5c0f\u6c11\u5c6f"
    ],
    "name:zho_x_preferred":[
        "\u5c0f\u6c11\u5c6f"
    ],
    "wof:name":"Xiaomintun",
    "wof:placetype":"locality"
},
  "geometry": {"coordinates":[122.9415,41.83135],"type":"Point"}
}