{
  "type": "Feature",
  "properties": {
    "gn:admin1_code":"8.0",
    "gn:asciiname":"Daohuaxiang",
    "gn:country_code":"CN",
    "gn:dem":183,
    "gn:feature_class":"P",
    "gn:feature_code":"PPL",
    "gn:name":"Daohuaxiang",
    "gn:population":0,
    "gn:timezone":"Asia/Shanghai",
    "iso:country":"CN",
    "name:zho_x_preferred":[
        "\u7a3b\u82b1\u9999"
    ],
    "wof:name":"Daohuaxiang",
    "wof:placetype":"locality"
},
  "geometry": {"coordinates":[124.27939000000001,48.21139],"type":"Point"}
}