{
  "type": "Feature",
  "properties": {
    "gn:admin1_code":"25",
    "gn:asciiname":"Jingshanzhuang",
    "gn:country_code":"CN",
    "gn:dem":139,
    "gn:feature_class":"P",
    "gn:feature_code":"PPL",
    "gn:name":"Jingshanzhuang",
    "gn:population":0,
    "gn:timezone":"Asia/Shanghai",
    "iso:country":"CN",
    "name:zho_x_preferred":[
        "\u8346\u5c71\u5e84"
    ],
    "wof:name":"Jingshanzhuang",
    "wof:placetype":"locality"
},
  "geometry": {"coordinates":[117.075,36.6417],"type":"Point"}
}