{
  "type": "Feature",
  "properties": {
    "gn:admin1_code":"1.0",
    "gn:asciiname":"Wufengpo",
    "gn:country_code":"CN",
    "gn:dem":168,
    "gn:feature_class":"P",
    "gn:feature_code":"PPL",
    "gn:name":"Wufengpo",
    "gn:population":0,
    "gn:timezone":"Asia/Shanghai",
    "iso:country":"CN",
    "name:zho_x_preferred":[
        "\u4e94\u4e30\u5761"
    ],
    "wof:name":"Wufengpo",
    "wof:placetype":"locality"
},
  "geometry": {"coordinates":[118.75246,30.29547],"type":"Point"}
}