{
  "type": "Feature",
  "properties": {
    "gn:admin1_code":"32.0",
    "gn:asciiname":"Zongza",
    "gn:cc2":"CN",
    "gn:country_code":"CN",
    "gn:dem":3009,
    "gn:feature_class":"P",
    "gn:feature_code":"PPL",
    "gn:name":"Zongza",
    "gn:population":0,
    "gn:timezone":"Asia/Shanghai",
    "iso:country":"CN",
    "name:und_x_variant":[
        "Chung-tsan",
        "Zongza"
    ],
    "wof:name":"Zongza",
    "wof:placetype":"locality"
},
  "geometry": {"coordinates":[99.31667,29.33333],"type":"Point"}
}