{
  "type": "Feature",
  "properties": {
    "gn:admin1_code":"7.0",
    "gn:asciiname":"Xiushan",
    "gn:country_code":"CN",
    "gn:dem":29,
    "gn:feature_class":"P",
    "gn:feature_code":"PPL",
    "gn:name":"Xiushan",
    "gn:population":0,
    "gn:timezone":"Asia/Shanghai",
    "iso:country":"CN",
    "name:und_x_variant":[
        "\u79c0\u5c71",
        "\u79c0\u5c71\u6751"
    ],
    "name:zho_x_preferred":[
        "Xiushancun"
    ],
    "wof:name":"Xiushan",
    "wof:placetype":"locality"
},
  "geometry": {"coordinates":[119.31461000000002,26.13965],"type":"Point"}
}