{
  "type": "Feature",
  "properties": {
    "gn:admin1_code":"29.0",
    "gn:asciiname":"Shihailuo",
    "gn:country_code":"CN",
    "gn:dem":2224,
    "gn:feature_class":"P",
    "gn:feature_code":"PPL",
    "gn:name":"Shihailuo",
    "gn:population":0,
    "gn:timezone":"Asia/Shanghai",
    "iso:country":"CN",
    "name:zho_x_preferred":[
        "\u77f3\u6d77\u87ba"
    ],
    "wof:name":"Shihailuo",
    "wof:placetype":"locality"
},
  "geometry": {"coordinates":[103.80200000000001,27.7436],"type":"Point"}
}