{
  "type": "Feature",
  "properties": {
    "gn:admin1_code":"8.0",
    "gn:asciiname":"Caifucun",
    "gn:country_code":"CN",
    "gn:dem":195,
    "gn:feature_class":"P",
    "gn:feature_code":"PPL",
    "gn:name":"Caifucun",
    "gn:population":0,
    "gn:timezone":"Asia/Shanghai",
    "iso:country":"CN",
    "name:zho_x_preferred":[
        "\u8d22\u5bcc\u6751"
    ],
    "wof:name":"Caifucun",
    "wof:placetype":"locality"
},
  "geometry": {"coordinates":[127.29123,47.00575],"type":"Point"}
}