{
  "type": "Feature",
  "properties": {
    "gn:admin1_code":"12.0",
    "gn:asciiname":"Qixinping",
    "gn:country_code":"CN",
    "gn:dem":1282,
    "gn:feature_class":"P",
    "gn:feature_code":"PPL",
    "gn:name":"Qixinping",
    "gn:population":0,
    "gn:timezone":"Asia/Shanghai",
    "iso:country":"CN",
    "name:zho_x_preferred":[
        "\u9f50\u5fc3\u576a"
    ],
    "wof:name":"Qixinping",
    "wof:placetype":"locality"
},
  "geometry": {"coordinates":[109.12578999999999,30.23405],"type":"Point"}
}