{
  "type": "Feature",
  "properties": {
    "gn:admin1_code":"20",
    "gn:asciiname":"Shih-ta-fen",
    "gn:country_code":"CN",
    "gn:dem":535,
    "gn:feature_class":"P",
    "gn:feature_code":"PPL",
    "gn:name":"Shih-ta-fen",
    "gn:population":0,
    "gn:timezone":"Asia/Shanghai",
    "iso:country":"CN",
    "wof:name":"Shih-ta-fen",
    "wof:placetype":"locality"
},
  "geometry": {"coordinates":[119.25333000000001,42.0625],"type":"Point"}
}