{
  "type": "Feature",
  "properties": {
    "gn:admin1_code":"4.0",
    "gn:asciiname":"Xinding",
    "gn:country_code":"CN",
    "gn:dem":1,
    "gn:feature_class":"P",
    "gn:feature_code":"PPL",
    "gn:name":"Xinding",
    "gn:population":0,
    "gn:timezone":"Asia/Shanghai",
    "iso:country":"CN",
    "name:zho_x_preferred":[
        "Xinding"
    ],
    "name:zho_x_variant":[
        "\u65b0\u9876"
    ],
    "wof:name":"Xinding",
    "wof:placetype":"locality"
},
  "geometry": {"coordinates":[119.00206,34.64504],"type":"Point"}
}