{
  "type": "Feature",
  "properties": {
    "gn:admin1_code":"11.0",
    "gn:asciiname":"Wuxia",
    "gn:country_code":"CN",
    "gn:dem":212,
    "gn:feature_class":"P",
    "gn:feature_code":"PPL",
    "gn:name":"Wuxia",
    "gn:population":0,
    "gn:timezone":"Asia/Shanghai",
    "iso:country":"CN",
    "name:zho_x_preferred":[
        "\u5434\u4e0b"
    ],
    "wof:name":"Wuxia",
    "wof:placetype":"locality"
},
  "geometry": {"coordinates":[113.87694999999999,26.92315],"type":"Point"}
}