{
  "type": "Feature",
  "properties": {
    "gn:admin1_code":"33.0",
    "gn:asciiname":"Houba",
    "gn:country_code":"CN",
    "gn:dem":164,
    "gn:feature_class":"P",
    "gn:feature_code":"PPLA4",
    "gn:name":"Houba",
    "gn:population":0,
    "gn:timezone":"Asia/Shanghai",
    "iso:country":"CN",
    "name:zho_x_preferred":[
        "\u539a\u575d"
    ],
    "wof:name":"Houba",
    "wof:placetype":"locality"
},
  "geometry": {"coordinates":[108.50628,31.20509],"type":"Point"}
}