{
  "type": "Feature",
  "properties": {
    "gn:admin1_code":"15.0",
    "gn:asciiname":"Nianziping",
    "gn:country_code":"CN",
    "gn:dem":1300,
    "gn:feature_class":"P",
    "gn:feature_code":"PPL",
    "gn:name":"Nianziping",
    "gn:population":0,
    "gn:timezone":"Asia/Shanghai",
    "iso:country":"CN",
    "name:zho_x_preferred":[
        "\u78be\u5b50\u576a"
    ],
    "wof:name":"Nianziping",
    "wof:placetype":"locality"
},
  "geometry": {"coordinates":[106.53100000000001,34.4131],"type":"Point"}
}