{
  "type": "Feature",
  "properties": {
    "gn:admin1_code":"16.0",
    "gn:asciiname":"Shenchong",
    "gn:country_code":"CN",
    "gn:dem":153,
    "gn:feature_class":"P",
    "gn:feature_code":"PPL",
    "gn:name":"Shenchong",
    "gn:population":0,
    "gn:timezone":"Asia/Shanghai",
    "iso:country":"CN",
    "name:zho_x_preferred":[
        "\u6df1\u51b2"
    ],
    "wof:name":"Shenchong",
    "wof:placetype":"locality"
},
  "geometry": {"coordinates":[110.57599999999999,23.02],"type":"Point"}
}