{
  "type": "Feature",
  "properties": {
    "gn:admin1_code":"32.0",
    "gn:asciiname":"Chesuoba",
    "gn:country_code":"CN",
    "gn:dem":1381,
    "gn:feature_class":"P",
    "gn:feature_code":"PPL",
    "gn:name":"Chesuoba",
    "gn:population":0,
    "gn:timezone":"Asia/Shanghai",
    "iso:country":"CN",
    "name:zho_x_preferred":[
        "\u626f\u7d22\u575d"
    ],
    "wof:name":"Chesuoba",
    "wof:placetype":"locality"
},
  "geometry": {"coordinates":[102.205,29.7564],"type":"Point"}
}