{
  "type": "Feature",
  "properties": {
    "gn:admin1_code":"30",
    "gn:asciiname":"Qili",
    "gn:country_code":"CN",
    "gn:dem":29,
    "gn:feature_class":"P",
    "gn:feature_code":"PPL",
    "gn:name":"Qili",
    "gn:population":0,
    "gn:timezone":"Asia/Urumqi",
    "iso:country":"CN",
    "name:zho_x_preferred":[
        "\u4e03\u91cc"
    ],
    "wof:name":"Qili",
    "wof:placetype":"locality"
},
  "geometry": {"coordinates":[109.88663,20.53805],"type":"Point"}
}