{
  "type": "Feature",
  "properties": {
    "gn:admin1_code":"30.0",
    "gn:asciiname":"Jiaozhoucun",
    "gn:country_code":"CN",
    "gn:dem":176,
    "gn:feature_class":"P",
    "gn:feature_code":"PPL",
    "gn:name":"Jiaozhoucun",
    "gn:population":0,
    "gn:timezone":"Asia/Shanghai",
    "iso:country":"CN",
    "name:zho_x_preferred":[
        "\u8549\u5dde\u6751"
    ],
    "wof:name":"Jiaozhoucun",
    "wof:placetype":"locality"
},
  "geometry": {"coordinates":[115.86168000000001,23.84993],"type":"Point"}
}