{
  "type": "Feature",
  "properties": {
    "gn:admin1_code":"32.0",
    "gn:asciiname":"Jinxihe",
    "gn:country_code":"CN",
    "gn:dem":574,
    "gn:feature_class":"P",
    "gn:feature_code":"PPL",
    "gn:name":"Jinxihe",
    "gn:population":0,
    "gn:timezone":"Asia/Shanghai",
    "iso:country":"CN",
    "name:zho_x_preferred":[
        "\u91d1\u6eaa\u6cb3"
    ],
    "wof:name":"Jinxihe",
    "wof:placetype":"locality"
},
  "geometry": {"coordinates":[107.121,32.3415],"type":"Point"}
}