{
  "type": "Feature",
  "properties": {
    "gn:admin1_code":"7.0",
    "gn:asciiname":"Wenjiang",
    "gn:country_code":"CN",
    "gn:dem":885,
    "gn:feature_class":"P",
    "gn:feature_code":"PPL",
    "gn:name":"Wenjiang",
    "gn:population":0,
    "gn:timezone":"Asia/Shanghai",
    "iso:country":"CN",
    "name:und_x_variant":[
        "\u6c76\u6d46"
    ],
    "name:zho_x_preferred":[
        "\u6c76\u6d46"
    ],
    "wof:name":"Wenjiang",
    "wof:placetype":"locality"
},
  "geometry": {"coordinates":[118.08893999999999,26.71783],"type":"Point"}
}