{
  "type": "Feature",
  "properties": {
    "gn:admin1_code":"24.0",
    "gn:asciiname":"Jundicun",
    "gn:country_code":"CN",
    "gn:dem":1119,
    "gn:feature_class":"P",
    "gn:feature_code":"PPL",
    "gn:name":"Jundicun",
    "gn:population":0,
    "gn:timezone":"Asia/Shanghai",
    "iso:country":"CN",
    "name:zho_x_preferred":[
        "\u519b\u5730\u6751"
    ],
    "wof:name":"Jundicun",
    "wof:placetype":"locality"
},
  "geometry": {"coordinates":[110.88815,36.43579],"type":"Point"}
}