{
  "type": "Feature",
  "properties": {
    "gn:admin1_code":"14.0",
    "gn:asciiname":"Shalong Muchang",
    "gn:country_code":"CN",
    "gn:dem":4402,
    "gn:feature_class":"P",
    "gn:feature_code":"PPLF",
    "gn:name":"Shalong Muchang",
    "gn:population":0,
    "gn:timezone":"Asia/Urumqi",
    "iso:country":"CN",
    "name:zho_x_preferred":[
        "\u6c99\u9f99\u7267\u573a"
    ],
    "wof:name":"Shalong Muchang",
    "wof:placetype":"locality"
},
  "geometry": {"coordinates":[97.90013,29.87736],"type":"Point"}
}