{
  "type": "Feature",
  "properties": {
    "gn:admin1_code":"11.0",
    "gn:asciiname":"Fangyangwan",
    "gn:country_code":"CN",
    "gn:dem":83,
    "gn:feature_class":"P",
    "gn:feature_code":"PPL",
    "gn:name":"Fangyangwan",
    "gn:population":0,
    "gn:timezone":"Asia/Shanghai",
    "iso:country":"CN",
    "name:zho_x_preferred":[
        "\u653e\u7f8a\u6e7e"
    ],
    "wof:name":"Fangyangwan",
    "wof:placetype":"locality"
},
  "geometry": {"coordinates":[113.31299,29.07446],"type":"Point"}
}