{
  "type": "Feature",
  "properties": {
    "gn:admin1_code":"25",
    "gn:asciiname":"Qianchelanbo",
    "gn:country_code":"CN",
    "gn:dem":79,
    "gn:feature_class":"P",
    "gn:feature_code":"PPL",
    "gn:name":"Qianchelanbo",
    "gn:population":0,
    "gn:timezone":"Asia/Shanghai",
    "iso:country":"CN",
    "name:zho_x_preferred":[
        "\u524d\u8f66\u5170\u6cca"
    ],
    "wof:name":"Qianchelanbo",
    "wof:placetype":"locality"
},
  "geometry": {"coordinates":[120.502,36.9279],"type":"Point"}
}