{
  "type": "Feature",
  "properties": {
    "gn:admin1_code":"12.0",
    "gn:asciiname":"Zhangxiangtang",
    "gn:country_code":"CN",
    "gn:dem":49,
    "gn:feature_class":"P",
    "gn:feature_code":"PPL",
    "gn:name":"Zhangxiangtang",
    "gn:population":0,
    "gn:timezone":"Asia/Shanghai",
    "iso:country":"CN",
    "name:zho_x_preferred":[
        "\u5f20\u4eab\u5802"
    ],
    "wof:name":"Zhangxiangtang",
    "wof:placetype":"locality"
},
  "geometry": {"coordinates":[115.91254000000001,30.14336],"type":"Point"}
}