{
  "type": "Feature",
  "properties": {
    "gn:admin1_code":"5.0",
    "gn:asciiname":"Yaojingzi Erdui Caiyuanzi",
    "gn:country_code":"CN",
    "gn:dem":149,
    "gn:feature_class":"P",
    "gn:feature_code":"PPLF",
    "gn:name":"Yaojingzi Erdui Caiyuanzi",
    "gn:population":0,
    "gn:timezone":"Asia/Shanghai",
    "iso:country":"CN",
    "name:zho_x_preferred":[
        "\u8170\u4e95\u5b50\u4e8c\u961f\u83dc\u56ed\u5b50"
    ],
    "wof:name":"Yaojingzi Erdui Caiyuanzi",
    "wof:placetype":"locality"
},
  "geometry": {"coordinates":[123.64024000000001,44.56746],"type":"Point"}
}