{
  "type": "Feature",
  "properties": {
    "gn:admin1_code":"24",
    "gn:asciiname":"Diaokou",
    "gn:country_code":"CN",
    "gn:dem":1339,
    "gn:feature_class":"P",
    "gn:feature_code":"PPL",
    "gn:name":"Diaokou",
    "gn:population":0,
    "gn:timezone":"Asia/Shanghai",
    "iso:country":"CN",
    "name:und_x_variant":[
        "Tao-k\u2019ou",
        "Tiao-k\u2019ou",
        "Diaokou"
    ],
    "name:zho_x_preferred":[
        "\u5201\u53e3"
    ],
    "wof:name":"Diaokou",
    "wof:placetype":"locality"
},
  "geometry": {"coordinates":[111.12597,36.26841],"type":"Point"}
}