{
  "type": "Feature",
  "properties": {
    "gn:admin1_code":"20.0",
    "gn:asciiname":"Guzimiao",
    "gn:country_code":"CN",
    "gn:dem":614,
    "gn:feature_class":"P",
    "gn:feature_code":"PPL",
    "gn:name":"Guzimiao",
    "gn:population":0,
    "gn:timezone":"Asia/Shanghai",
    "iso:country":"CN",
    "name:zho_x_preferred":[
        "\u59d1\u5b50\u5e99"
    ],
    "wof:name":"Guzimiao",
    "wof:placetype":"locality"
},
  "geometry": {"coordinates":[120.72059,50.4192],"type":"Point"}
}