{
  "type": "Feature",
  "properties": {
    "gn:admin1_code":"30.0",
    "gn:asciiname":"Jilongbu",
    "gn:country_code":"CN",
    "gn:dem":125,
    "gn:feature_class":"P",
    "gn:feature_code":"PPL",
    "gn:name":"Jilongbu",
    "gn:population":0,
    "gn:timezone":"Asia/Shanghai",
    "iso:country":"CN",
    "name:zho_x_preferred":[
        "\u9e21\u7b3c\u5e03"
    ],
    "wof:name":"Jilongbu",
    "wof:placetype":"locality"
},
  "geometry": {"coordinates":[114.13612000000001,23.61117],"type":"Point"}
}