{
  "type": "Feature",
  "properties": {
    "gn:admin1_code":"5.0",
    "gn:asciiname":"Qianshihao",
    "gn:country_code":"CN",
    "gn:dem":194,
    "gn:feature_class":"P",
    "gn:feature_code":"PPL",
    "gn:name":"Qianshihao",
    "gn:population":0,
    "gn:timezone":"Asia/Shanghai",
    "iso:country":"CN",
    "name:zho_x_preferred":[
        "\u524d\u5341\u53f7"
    ],
    "wof:name":"Qianshihao",
    "wof:placetype":"locality"
},
  "geometry": {"coordinates":[126.42066,45.0406],"type":"Point"}
}