{
  "type": "Feature",
  "properties": {
    "gn:admin1_code":"4.0",
    "gn:asciiname":"Pu'an",
    "gn:country_code":"CN",
    "gn:dem":9,
    "gn:feature_class":"P",
    "gn:feature_code":"PPL",
    "gn:name":"Pu\u2019an",
    "gn:population":0,
    "gn:timezone":"Asia/Shanghai",
    "iso:country":"CN",
    "name:zho_x_preferred":[
        "Pu\u2019an"
    ],
    "name:zho_x_variant":[
        "\u666e\u5eb5"
    ],
    "wof:name":"Pu'an",
    "wof:placetype":"locality"
},
  "geometry": {"coordinates":[119.13132,34.26009000000001],"type":"Point"}
}