{
  "type": "Feature",
  "properties": {
    "gn:admin1_code":"16.0",
    "gn:asciiname":"Jishan",
    "gn:country_code":"CN",
    "gn:dem":657,
    "gn:feature_class":"P",
    "gn:feature_code":"PPL",
    "gn:name":"Jishan",
    "gn:population":0,
    "gn:timezone":"Asia/Shanghai",
    "iso:country":"CN",
    "name:deu_x_preferred":[
        "Jishan"
    ],
    "name:zho_x_preferred":[
        "\u79ef\u5584"
    ],
    "wof:name":"Jishan",
    "wof:placetype":"locality"
},
  "geometry": {"coordinates":[106.845,24.4406],"type":"Point"}
}