{
  "type": "Feature",
  "properties": {
    "gn:admin1_code":"8.0",
    "gn:asciiname":"Juhecun",
    "gn:country_code":"CN",
    "gn:dem":192,
    "gn:feature_class":"P",
    "gn:feature_code":"PPL",
    "gn:name":"Juhecun",
    "gn:population":0,
    "gn:timezone":"Asia/Shanghai",
    "iso:country":"CN",
    "name:zho_x_preferred":[
        "\u5de8\u548c\u6751"
    ],
    "wof:name":"Juhecun",
    "wof:placetype":"locality"
},
  "geometry": {"coordinates":[125.34054,47.89439],"type":"Point"}
}