{
  "type": "Feature",
  "properties": {
    "gn:admin1_code":"07",
    "gn:asciiname":"Chituzhai",
    "gn:country_code":"CN",
    "gn:dem":846,
    "gn:feature_class":"P",
    "gn:feature_code":"PPL",
    "gn:name":"Chituzhai",
    "gn:population":0,
    "gn:timezone":"Asia/Shanghai",
    "iso:country":"CN",
    "name:zho_x_preferred":[
        "\u8d64\u571f\u5be8"
    ],
    "wof:name":"Chituzhai",
    "wof:placetype":"locality"
},
  "geometry": {"coordinates":[118.12438,25.82138],"type":"Point"}
}