{
  "type": "Feature",
  "properties": {
    "gn:admin1_code":"30",
    "gn:asciiname":"Shancaoyin",
    "gn:country_code":"CN",
    "gn:dem":232,
    "gn:feature_class":"P",
    "gn:feature_code":"PPL",
    "gn:name":"Shancaoyin",
    "gn:population":0,
    "gn:timezone":"Asia/Shanghai",
    "iso:country":"CN",
    "name:zho_x_preferred":[
        "\u5c71\u8349\u57a0"
    ],
    "wof:name":"Shancaoyin",
    "wof:placetype":"locality"
},
  "geometry": {"coordinates":[116.48981999999999,23.77084],"type":"Point"}
}