{
  "type": "Feature",
  "properties": {
    "gn:admin1_code":"20",
    "gn:asciiname":"Yu-chia-wo-p'u",
    "gn:country_code":"CN",
    "gn:dem":729,
    "gn:feature_class":"P",
    "gn:feature_code":"PPL",
    "gn:name":"Y\u00fc-chia-wo-p\u2019u",
    "gn:population":0,
    "gn:timezone":"Asia/Shanghai",
    "iso:country":"CN",
    "wof:name":"Yu-chia-wo-p'u",
    "wof:placetype":"locality"
},
  "geometry": {"coordinates":[118.88194,42.85611],"type":"Point"}
}