{
  "type": "Feature",
  "properties": {
    "gn:admin1_code":"11",
    "gn:asciiname":"Ganzixi",
    "gn:country_code":"CN",
    "gn:dem":436,
    "gn:feature_class":"P",
    "gn:feature_code":"PPL",
    "gn:name":"Ganzixi",
    "gn:population":0,
    "gn:timezone":"Asia/Shanghai",
    "iso:country":"CN",
    "name:zho_x_preferred":[
        "\u6746\u5b50\u6eaa"
    ],
    "wof:name":"Ganzixi",
    "wof:placetype":"locality"
},
  "geometry": {"coordinates":[109.60133999999999,26.34153],"type":"Point"}
}