{
  "type": "Feature",
  "properties": {
    "gn:admin1_code":"16.0",
    "gn:asciiname":"Babao",
    "gn:country_code":"CN",
    "gn:dem":102,
    "gn:feature_class":"P",
    "gn:feature_code":"PPL",
    "gn:name":"Babao",
    "gn:population":0,
    "gn:timezone":"Asia/Shanghai",
    "iso:country":"CN",
    "name:deu_x_preferred":[
        "Babao"
    ],
    "name:zho_x_preferred":[
        "\u516b\u5b9d"
    ],
    "wof:name":"Babao",
    "wof:placetype":"locality"
},
  "geometry": {"coordinates":[109.02800000000001,23.2487],"type":"Point"}
}