{
  "type": "Feature",
  "properties": {
    "gn:admin1_code":"25",
    "gn:asciiname":"Lianziwang",
    "gn:country_code":"CN",
    "gn:dem":54,
    "gn:feature_class":"P",
    "gn:feature_code":"PPL",
    "gn:name":"Lianziwang",
    "gn:population":0,
    "gn:timezone":"Asia/Shanghai",
    "iso:country":"CN",
    "name:zho_x_preferred":[
        "\u83b2\u5b50\u6c6a"
    ],
    "wof:name":"Lianziwang",
    "wof:placetype":"locality"
},
  "geometry": {"coordinates":[118.096,34.9132],"type":"Point"}
}