{
  "type": "Feature",
  "properties": {
    "gn:admin1_code":"1.0",
    "gn:asciiname":"Chajiaduo",
    "gn:country_code":"CN",
    "gn:dem":7,
    "gn:feature_class":"P",
    "gn:feature_code":"PPL",
    "gn:name":"Chajiaduo",
    "gn:population":0,
    "gn:timezone":"Asia/Shanghai",
    "iso:country":"CN",
    "name:zho_x_preferred":[
        "\u67e5\u5bb6\u579b"
    ],
    "wof:name":"Chajiaduo",
    "wof:placetype":"locality"
},
  "geometry": {"coordinates":[118.50311000000001,31.3481],"type":"Point"}
}