{
  "type": "Feature",
  "properties": {
    "gn:admin1_code":"12.0",
    "gn:asciiname":"Fujiawan",
    "gn:country_code":"CN",
    "gn:dem":71,
    "gn:feature_class":"P",
    "gn:feature_code":"PPL",
    "gn:name":"Fujiawan",
    "gn:population":0,
    "gn:timezone":"Asia/Shanghai",
    "iso:country":"CN",
    "name:und_x_variant":[
        "\u5085\u5bb6\u5846"
    ],
    "wof:name":"Fujiawan",
    "wof:placetype":"locality"
},
  "geometry": {"coordinates":[115.23994999999999,30.55389000000001],"type":"Point"}
}