{
  "type": "Feature",
  "properties": {
    "gn:admin1_code":"8.0",
    "gn:asciiname":"Wangguilintun",
    "gn:country_code":"CN",
    "gn:dem":198,
    "gn:feature_class":"P",
    "gn:feature_code":"PPL",
    "gn:name":"Wangguilintun",
    "gn:population":0,
    "gn:timezone":"Asia/Shanghai",
    "iso:country":"CN",
    "name:zho_x_preferred":[
        "\u738b\u8d35\u6797\u5c6f"
    ],
    "wof:name":"Wangguilintun",
    "wof:placetype":"locality"
},
  "geometry": {"coordinates":[127.21648,47.31812],"type":"Point"}
}