{
  "type": "Feature",
  "properties": {
    "gn:admin1_code":"14",
    "gn:asciiname":"Karlung",
    "gn:country_code":"CN",
    "gn:dem":4480,
    "gn:feature_class":"P",
    "gn:feature_code":"PPL",
    "gn:name":"Karlung",
    "gn:population":0,
    "gn:timezone":"Asia/Urumqi",
    "iso:country":"CN",
    "name:bod_x_preferred":[
        "\u0f58\u0f41\u0f62\u0f0b\u0f63\u0f74\u0f44"
    ],
    "name:bod_x_variant":[
        "\u0f42\u0f51\u0f7c\u0f44\u0f0b\u0f51\u0f40\u0f62"
    ],
    "name:und_x_variant":[
        "Donggar",
        "Kalong"
    ],
    "name:zho_x_preferred":[
        "\u5494\u9f99"
    ],
    "name:zho_x_variant":[
        "\u5361\u9f99"
    ],
    "wof:name":"Karlung",
    "wof:placetype":"locality"
},
  "geometry": {"coordinates":[90.47154999999999,29.03614],"type":"Point"}
}