{
  "type": "Feature",
  "properties": {
    "gn:admin1_code":"19.0",
    "gn:asciiname":"Gaojiafangshen",
    "gn:country_code":"CN",
    "gn:dem":46,
    "gn:feature_class":"P",
    "gn:feature_code":"PPL",
    "gn:name":"Gaojiafangshen",
    "gn:population":0,
    "gn:timezone":"Asia/Shanghai",
    "iso:country":"CN",
    "name:zho_x_preferred":[
        "\u9ad8\u5bb6\u623f\u8eab"
    ],
    "wof:name":"Gaojiafangshen",
    "wof:placetype":"locality"
},
  "geometry": {"coordinates":[121.84671000000002,39.32068],"type":"Point"}
}