{
  "type": "Feature",
  "properties": {
    "gn:admin1_code":"14.0",
    "gn:asciiname":"Cangqucun",
    "gn:country_code":"CN",
    "gn:dem":4614,
    "gn:feature_class":"P",
    "gn:feature_code":"PPL",
    "gn:name":"Cangqucun",
    "gn:population":0,
    "gn:timezone":"Asia/Urumqi",
    "iso:country":"CN",
    "name:zho_x_preferred":[
        "\u85cf\u66f2\u6751"
    ],
    "wof:name":"Cangqucun",
    "wof:placetype":"locality"
},
  "geometry": {"coordinates":[86.825,33.1389],"type":"Point"}
}