{
  "type": "Feature",
  "properties": {
    "gn:admin1_code":"5.0",
    "gn:asciiname":"Yulincun",
    "gn:country_code":"CN",
    "gn:dem":165,
    "gn:feature_class":"P",
    "gn:feature_code":"PPL",
    "gn:name":"Yulincun",
    "gn:population":0,
    "gn:timezone":"Asia/Shanghai",
    "iso:country":"CN",
    "name:zho_x_preferred":[
        "\u6986\u6797\u6751"
    ],
    "wof:name":"Yulincun",
    "wof:placetype":"locality"
},
  "geometry": {"coordinates":[122.35809999999999,45.22273],"type":"Point"}
}