{
  "type": "Feature",
  "properties": {
    "gn:admin1_code":"32.0",
    "gn:asciiname":"Zhama",
    "gn:country_code":"CN",
    "gn:dem":3667,
    "gn:feature_class":"P",
    "gn:feature_code":"PPL",
    "gn:name":"Zhama",
    "gn:population":0,
    "gn:timezone":"Asia/Urumqi",
    "iso:country":"CN",
    "name:und_x_variant":[
        "\u624e\u739b"
    ],
    "wof:name":"Zhama",
    "wof:placetype":"locality"
},
  "geometry": {"coordinates":[98.40000000000001,31.79],"type":"Point"}
}