{
  "type": "Feature",
  "properties": {
    "gn:admin1_code":"29.0",
    "gn:asciiname":"Suhu",
    "gn:country_code":"CN",
    "gn:dem":1776,
    "gn:feature_class":"P",
    "gn:feature_code":"PPL",
    "gn:name":"Suhu",
    "gn:population":0,
    "gn:timezone":"Asia/Shanghai",
    "iso:country":"CN",
    "name:zho_x_preferred":[
        "\u82cf\u80e1"
    ],
    "wof:name":"Suhu",
    "wof:placetype":"locality"
},
  "geometry": {"coordinates":[100.526,21.8996],"type":"Point"}
}