{
  "type": "Feature",
  "properties": {
    "gn:admin1_code":"14.0",
    "gn:asciiname":"Cha'arucun",
    "gn:country_code":"CN",
    "gn:dem":2522,
    "gn:feature_class":"P",
    "gn:feature_code":"PPL",
    "gn:name":"Cha\u2019arucun",
    "gn:population":0,
    "gn:timezone":"Asia/Urumqi",
    "iso:country":"CN",
    "name:und_x_variant":[
        "Cha\u2019arucun"
    ],
    "name:zho_x_preferred":[
        "\u5bdf\u963f\u5982\u6751"
    ],
    "wof:name":"Cha'arucun",
    "wof:placetype":"locality"
},
  "geometry": {"coordinates":[97.94456,29.01659],"type":"Point"}
}