{
  "type": "Feature",
  "properties": {
    "gn:admin1_code":"11.0",
    "gn:asciiname":"Changleyuan",
    "gn:country_code":"CN",
    "gn:dem":28,
    "gn:feature_class":"P",
    "gn:feature_code":"PPL",
    "gn:name":"Changleyuan",
    "gn:population":0,
    "gn:timezone":"Asia/Shanghai",
    "iso:country":"CN",
    "name:zho_x_preferred":[
        "\u957f\u4e50\u57b8"
    ],
    "wof:name":"Changleyuan",
    "wof:placetype":"locality"
},
  "geometry": {"coordinates":[112.40777,29.1003],"type":"Point"}
}