{
  "type": "Feature",
  "properties": {
    "gn:admin1_code":"12",
    "gn:asciiname":"Jianyang",
    "gn:country_code":"CN",
    "gn:dem":45,
    "gn:feature_class":"P",
    "gn:feature_code":"PPL",
    "gn:name":"Jianyang",
    "gn:population":0,
    "gn:timezone":"Asia/Shanghai",
    "iso:country":"CN",
    "name:deu_x_preferred":[
        "Jianyang"
    ],
    "name:fra_x_preferred":[
        "Jianyang"
    ],
    "name:kor_x_preferred":[
        "\uc820\uc591\uc2dc"
    ],
    "name:nld_x_preferred":[
        "Jianyang"
    ],
    "name:nor_x_preferred":[
        "Jianyang"
    ],
    "name:rus_x_preferred":[
        "\u0426\u0437\u044f\u043d\u044c\u044f\u043d"
    ],
    "name:swe_x_preferred":[
        "Jianyang"
    ],
    "name:und_x_variant":[
        "Chien-yang-i",
        "Jianyangyi",
        "Jianyang",
        "\u5efa\u9633"
    ],
    "wof:name":"Jianyang",
    "wof:placetype":"locality"
},
  "geometry": {"coordinates":[112.19202,30.67426],"type":"Point"}
}