{
  "type": "Feature",
  "properties": {
    "gn:admin1_code":"24.0",
    "gn:asciiname":"Xiawu",
    "gn:country_code":"CN",
    "gn:dem":479,
    "gn:feature_class":"P",
    "gn:feature_code":"PPL",
    "gn:name":"Xiawu",
    "gn:population":0,
    "gn:timezone":"Asia/Shanghai",
    "iso:country":"CN",
    "name:und_x_variant":[
        "Hsia-wu",
        "Xiawu",
        "\u4e0b\u575e"
    ],
    "wof:name":"Xiawu",
    "wof:placetype":"locality"
},
  "geometry": {"coordinates":[111.49419,35.75764],"type":"Point"}
}