{
  "type": "Feature",
  "properties": {
    "gn:admin1_code":"14.0",
    "gn:asciiname":"Caijiakuo",
    "gn:country_code":"CN",
    "gn:dem":4314,
    "gn:feature_class":"P",
    "gn:feature_code":"PPL",
    "gn:name":"Caijiakuo",
    "gn:population":0,
    "gn:timezone":"Asia/Urumqi",
    "iso:country":"CN",
    "name:zho_x_preferred":[
        "\u624d\u5bb6\u9614"
    ],
    "wof:name":"Caijiakuo",
    "wof:placetype":"locality"
},
  "geometry": {"coordinates":[98.03291,32.40289],"type":"Point"}
}