{
  "type": "Feature",
  "properties": {
    "gn:admin1_code":"7",
    "gn:asciiname":"Keminglou",
    "gn:country_code":"CN",
    "gn:dem":20,
    "gn:feature_class":"P",
    "gn:feature_code":"PPL",
    "gn:name":"Keminglou",
    "gn:population":0,
    "gn:timezone":"Asia/Shanghai",
    "iso:country":"CN",
    "name:und_x_variant":[
        "K\u2019o-ming-lou",
        "Keminglou"
    ],
    "name:zho_x_preferred":[
        "\u514b\u660e\u697c"
    ],
    "wof:name":"Keminglou",
    "wof:placetype":"locality"
},
  "geometry": {"coordinates":[119.59204,25.81883],"type":"Point"}
}