{
  "type": "Feature",
  "properties": {
    "gn:admin1_code":"3.0",
    "gn:asciiname":"Wenfeng",
    "gn:country_code":"CN",
    "gn:dem":306,
    "gn:feature_class":"P",
    "gn:feature_code":"PPLA4",
    "gn:name":"Wenfeng",
    "gn:population":0,
    "gn:timezone":"Asia/Shanghai",
    "iso:country":"CN",
    "name:und_x_variant":[
        "Wenfeng Xiang"
    ],
    "name:zho_x_preferred":[
        "\u6587\u5cf0"
    ],
    "name:zho_x_variant":[
        "\u6587\u5cf0\u4e61"
    ],
    "wof:name":"Wenfeng",
    "wof:placetype":"locality"
},
  "geometry": {"coordinates":[115.63354,24.96471],"type":"Point"}
}