{
  "type": "Feature",
  "properties": {
    "gn:admin1_code":"29.0",
    "gn:asciiname":"Dacun",
    "gn:country_code":"CN",
    "gn:dem":1558,
    "gn:feature_class":"P",
    "gn:feature_code":"PPL",
    "gn:name":"Dacun",
    "gn:population":0,
    "gn:timezone":"Asia/Shanghai",
    "iso:country":"CN",
    "name:zho_x_preferred":[
        "\u5927\u6751"
    ],
    "wof:name":"Dacun",
    "wof:placetype":"locality"
},
  "geometry": {"coordinates":[101.60299999999999,26.0162],"type":"Point"}
}