{
  "type": "Feature",
  "properties": {
    "gn:admin1_code":"11.0",
    "gn:asciiname":"Xiahui",
    "gn:country_code":"CN",
    "gn:dem":349,
    "gn:feature_class":"P",
    "gn:feature_code":"PPL",
    "gn:name":"Xiahui",
    "gn:population":0,
    "gn:timezone":"Asia/Shanghai",
    "iso:country":"CN",
    "name:zho_x_preferred":[
        "\u4e0b\u8ff4"
    ],
    "name:zho_x_variant":[
        "\u4e0b\u56de"
    ],
    "wof:name":"Xiahui",
    "wof:placetype":"locality"
},
  "geometry": {"coordinates":[110.15442,29.31045],"type":"Point"}
}