{
  "type": "Feature",
  "properties": {
    "gn:admin1_code":"4.0",
    "gn:asciiname":"Houlizhuang",
    "gn:country_code":"CN",
    "gn:dem":22,
    "gn:feature_class":"P",
    "gn:feature_code":"PPL",
    "gn:name":"Houlizhuang",
    "gn:population":0,
    "gn:timezone":"Asia/Shanghai",
    "iso:country":"CN",
    "name:zho_x_preferred":[
        "\u540e\u674e\u5e84"
    ],
    "wof:name":"Houlizhuang",
    "wof:placetype":"locality"
},
  "geometry": {"coordinates":[118.73999999999999,33.0587],"type":"Point"}
}