{
  "type": "Feature",
  "properties": {
    "gn:admin1_code":"3.0",
    "gn:asciiname":"Shaoshuitang",
    "gn:country_code":"CN",
    "gn:dem":257,
    "gn:feature_class":"P",
    "gn:feature_code":"PPL",
    "gn:name":"Shaoshuitang",
    "gn:population":0,
    "gn:timezone":"Asia/Shanghai",
    "iso:country":"CN",
    "name:und_x_variant":[
        "\u70e7\u6c34\u5858"
    ],
    "wof:name":"Shaoshuitang",
    "wof:placetype":"locality"
},
  "geometry": {"coordinates":[116.96222,27.78212000000001],"type":"Point"}
}