{
  "type": "Feature",
  "properties": {
    "gn:admin1_code":"8.0",
    "gn:asciiname":"Chengxiangcun",
    "gn:country_code":"CN",
    "gn:dem":106,
    "gn:feature_class":"P",
    "gn:feature_code":"PPL",
    "gn:name":"Chengxiangcun",
    "gn:population":0,
    "gn:timezone":"Asia/Shanghai",
    "iso:country":"CN",
    "name:zho_x_preferred":[
        "\u57ce\u4e61\u6751"
    ],
    "wof:name":"Chengxiangcun",
    "wof:placetype":"locality"
},
  "geometry": {"coordinates":[128.7174,45.97323],"type":"Point"}
}