{
  "type": "Feature",
  "properties": {
    "gn:admin1_code":"9.0",
    "gn:asciiname":"Zhuxinqiao",
    "gn:country_code":"CN",
    "gn:dem":44,
    "gn:feature_class":"P",
    "gn:feature_code":"PPL",
    "gn:name":"Zhuxinqiao",
    "gn:population":0,
    "gn:timezone":"Asia/Shanghai",
    "iso:country":"CN",
    "name:zho_x_preferred":[
        "\u6731\u65b0\u6865"
    ],
    "wof:name":"Zhuxinqiao",
    "wof:placetype":"locality"
},
  "geometry": {"coordinates":[115.11645,33.52565],"type":"Point"}
}