{
  "type": "Feature",
  "properties": {
    "gn:admin1_code":"24.0",
    "gn:asciiname":"Yawa",
    "gn:country_code":"CN",
    "gn:dem":1063,
    "gn:feature_class":"P",
    "gn:feature_code":"PPL",
    "gn:name":"Yawa",
    "gn:population":0,
    "gn:timezone":"Asia/Shanghai",
    "iso:country":"CN",
    "name:ceb_x_preferred":[
        "Yawa"
    ],
    "name:deu_x_preferred":[
        "Yawa"
    ],
    "name:swe_x_preferred":[
        "Yawa"
    ],
    "name:zho_x_preferred":[
        "\u9e26\u6d3c"
    ],
    "wof:name":"Yawa",
    "wof:placetype":"locality"
},
  "geometry": {"coordinates":[113.57248,37.67902],"type":"Point"}
}