{
  "type": "Feature",
  "properties": {
    "gn:admin1_code":"31.0",
    "gn:asciiname":"Zhonglin",
    "gn:country_code":"CN",
    "gn:dem":48,
    "gn:feature_class":"P",
    "gn:feature_code":"PPL",
    "gn:name":"Zhonglin",
    "gn:population":0,
    "gn:timezone":"Asia/Shanghai",
    "iso:country":"CN",
    "name:zho_x_preferred":[
        "\u4e2d\u6797"
    ],
    "wof:name":"Zhonglin",
    "wof:placetype":"locality"
},
  "geometry": {"coordinates":[109.87322,19.73351],"type":"Point"}
}