{
  "type": "Feature",
  "properties": {
    "gn:admin1_code":"5.0",
    "gn:asciiname":"Luotuoshancun",
    "gn:country_code":"CN",
    "gn:dem":306,
    "gn:feature_class":"P",
    "gn:feature_code":"PPL",
    "gn:name":"Luotuoshancun",
    "gn:population":0,
    "gn:timezone":"Asia/Shanghai",
    "iso:country":"CN",
    "name:zho_x_preferred":[
        "\u9a86\u9a7c\u5c71\u6751"
    ],
    "wof:name":"Luotuoshancun",
    "wof:placetype":"locality"
},
  "geometry": {"coordinates":[129.53319999999999,43.64677],"type":"Point"}
}