{
  "type": "Feature",
  "properties": {
    "gn:admin1_code":"32.0",
    "gn:asciiname":"Gekong",
    "gn:country_code":"CN",
    "gn:dem":3821,
    "gn:feature_class":"P",
    "gn:feature_code":"PPL",
    "gn:name":"Gekong",
    "gn:population":0,
    "gn:timezone":"Asia/Shanghai",
    "iso:country":"CN",
    "name:zho_x_preferred":[
        "\u5404\u7a7a"
    ],
    "wof:name":"Gekong",
    "wof:placetype":"locality"
},
  "geometry": {"coordinates":[98.6841,31.8369],"type":"Point"}
}