{
  "type": "Feature",
  "properties": {
    "gn:admin1_code":"2.0",
    "gn:asciiname":"Fanshi",
    "gn:country_code":"CN",
    "gn:dem":10,
    "gn:feature_class":"P",
    "gn:feature_code":"PPL",
    "gn:name":"Fanshi",
    "gn:population":0,
    "gn:timezone":"Asia/Shanghai",
    "iso:country":"CN",
    "name:und_x_variant":[
        "\u6a0a\u5e02"
    ],
    "wof:name":"Fanshi",
    "wof:placetype":"locality"
},
  "geometry": {"coordinates":[119.94448,30.82716],"type":"Point"}
}