{
  "type": "Feature",
  "properties": {
    "gn:admin1_code":"14.0",
    "gn:asciiname":"Julongcun",
    "gn:country_code":"CN",
    "gn:dem":4879,
    "gn:feature_class":"P",
    "gn:feature_code":"PPL",
    "gn:name":"Julongcun",
    "gn:population":0,
    "gn:timezone":"Asia/Urumqi",
    "iso:country":"CN",
    "name:zho_x_preferred":[
        "\u5c45\u9686\u6751"
    ],
    "wof:name":"Julongcun",
    "wof:placetype":"locality"
},
  "geometry": {"coordinates":[92.92545,31.08835],"type":"Point"}
}