{
  "type": "Feature",
  "properties": {
    "gn:admin1_code":"4.0",
    "gn:asciiname":"Jiulongmiaodai",
    "gn:country_code":"CN",
    "gn:dem":5,
    "gn:feature_class":"P",
    "gn:feature_code":"PPL",
    "gn:name":"Jiulongmiaodai",
    "gn:population":0,
    "gn:timezone":"Asia/Shanghai",
    "iso:country":"CN",
    "name:und_x_variant":[
        "\u4e5d\u9f99\u5e99\u5788"
    ],
    "name:zho_x_preferred":[
        "\u4e5d\u9f99\u5e99\u5788"
    ],
    "wof:name":"Jiulongmiaodai",
    "wof:placetype":"locality"
},
  "geometry": {"coordinates":[120.02487000000001,32.19661],"type":"Point"}
}