{
  "type": "Feature",
  "properties": {
    "gn:admin1_code":"30.0",
    "gn:asciiname":"Gongwuling",
    "gn:country_code":"CN",
    "gn:dem":162,
    "gn:feature_class":"P",
    "gn:feature_code":"PPL",
    "gn:name":"Gongwuling",
    "gn:population":0,
    "gn:timezone":"Asia/Shanghai",
    "iso:country":"CN",
    "name:zho_x_preferred":[
        "\u529f\u6b66\u5cad"
    ],
    "wof:name":"Gongwuling",
    "wof:placetype":"locality"
},
  "geometry": {"coordinates":[114.20489999999999,23.54015],"type":"Point"}
}