{
  "type": "Feature",
  "properties": {
    "gn:admin1_code":"2.0",
    "gn:asciiname":"Jianqiao",
    "gn:country_code":"CN",
    "gn:dem":9,
    "gn:feature_class":"P",
    "gn:feature_code":"PPL",
    "gn:name":"Jianqiao",
    "gn:population":0,
    "gn:timezone":"Asia/Shanghai",
    "iso:country":"CN",
    "name:swe_x_preferred":[
        "Jianqiao"
    ],
    "name:zho_x_preferred":[
        "\u7b15\u6865"
    ],
    "wof:name":"Jianqiao",
    "wof:placetype":"locality"
},
  "geometry": {"coordinates":[120.39715,27.50115],"type":"Point"}
}