{
  "type": "Feature",
  "properties": {
    "gn:admin1_code":"30",
    "gn:asciiname":"Geshui",
    "gn:country_code":"CN",
    "gn:dem":103,
    "gn:feature_class":"P",
    "gn:feature_code":"PPL",
    "gn:name":"Geshui",
    "gn:population":0,
    "gn:timezone":"Asia/Shanghai",
    "iso:country":"CN",
    "name:zho_x_preferred":[
        "\u683c\u6c34"
    ],
    "wof:name":"Geshui",
    "wof:placetype":"locality"
},
  "geometry": {"coordinates":[112.03936000000002,22.42282],"type":"Point"}
}