{
  "type": "Feature",
  "properties": {
    "gn:admin1_code":"26.0",
    "gn:asciiname":"Zongguankou",
    "gn:country_code":"CN",
    "gn:dem":1223,
    "gn:feature_class":"P",
    "gn:feature_code":"PPL",
    "gn:name":"Zongguankou",
    "gn:population":0,
    "gn:timezone":"Asia/Shanghai",
    "iso:country":"CN",
    "name:zho_x_preferred":[
        "\u603b\u5173\u53e3"
    ],
    "wof:name":"Zongguankou",
    "wof:placetype":"locality"
},
  "geometry": {"coordinates":[109.23448,37.37443],"type":"Point"}
}