{
  "type": "Feature",
  "properties": {
    "gn:admin1_code":"26.0",
    "gn:asciiname":"Yangtianba",
    "gn:country_code":"CN",
    "gn:dem":1019,
    "gn:feature_class":"P",
    "gn:feature_code":"PPL",
    "gn:name":"Yangtianba",
    "gn:population":0,
    "gn:timezone":"Asia/Shanghai",
    "iso:country":"CN",
    "name:und_x_variant":[
        "\u79e7\u7530\u575d"
    ],
    "wof:name":"Yangtianba",
    "wof:placetype":"locality"
},
  "geometry": {"coordinates":[107.00528,33.58788],"type":"Point"}
}