{
  "type": "Feature",
  "properties": {
    "gn:admin1_code":"25.0",
    "gn:asciiname":"Erpenkou",
    "gn:country_code":"CN",
    "gn:dem":115,
    "gn:feature_class":"P",
    "gn:feature_code":"PPL",
    "gn:name":"Erpenkou",
    "gn:population":0,
    "gn:timezone":"Asia/Shanghai",
    "iso:country":"CN",
    "name:zho_x_preferred":[
        "\u4e8c\u76c6\u53e3"
    ],
    "wof:name":"Erpenkou",
    "wof:placetype":"locality"
},
  "geometry": {"coordinates":[120.1585,37.1748],"type":"Point"}
}