{
  "type": "Feature",
  "properties": {
    "gn:admin1_code":"23.0",
    "gn:asciiname":"Kangjianong",
    "gn:country_code":"CN",
    "gn:dem":3,
    "gn:feature_class":"P",
    "gn:feature_code":"PPL",
    "gn:name":"Kangjianong",
    "gn:population":0,
    "gn:timezone":"Asia/Shanghai",
    "iso:country":"CN",
    "name:zho_x_preferred":[
        "Kangjianong"
    ],
    "name:zho_x_variant":[
        "\u5eb7\u5bb6\u5f04"
    ],
    "wof:name":"Kangjianong",
    "wof:placetype":"locality"
},
  "geometry": {"coordinates":[121.25623,31.22794],"type":"Point"}
}