{
  "type": "Feature",
  "properties": {
    "gn:admin1_code":"11",
    "gn:asciiname":"Laoxingchang",
    "gn:country_code":"CN",
    "gn:dem":502,
    "gn:feature_class":"P",
    "gn:feature_code":"PPLA4",
    "gn:name":"Laoxingchang",
    "gn:population":0,
    "gn:timezone":"Asia/Shanghai",
    "iso:country":"CN",
    "name:und_x_variant":[
        "Laoxing",
        "Laoxing Xiang",
        "Laoxingchang"
    ],
    "name:zho_x_preferred":[
        "\u8001\u5174\u573a"
    ],
    "name:zho_x_variant":[
        "\u8001\u5174\u4e61"
    ],
    "wof:name":"Laoxingchang",
    "wof:placetype":"locality"
},
  "geometry": {"coordinates":[109.34311,29.15584],"type":"Point"}
}