{
  "type": "Feature",
  "properties": {
    "gn:admin1_code":"21.0",
    "gn:asciiname":"Modaoshi Wanzi",
    "gn:country_code":"CN",
    "gn:dem":1398,
    "gn:feature_class":"P",
    "gn:feature_code":"PPL",
    "gn:name":"Modaoshi Wanzi",
    "gn:population":0,
    "gn:timezone":"Asia/Shanghai",
    "iso:country":"CN",
    "name:zho_x_preferred":[
        "\u78e8\u5200\u77f3\u6e7e\u5b50"
    ],
    "wof:name":"Modaoshi Wanzi",
    "wof:placetype":"locality"
},
  "geometry": {"coordinates":[105.724,37.3621],"type":"Point"}
}