{
  "type": "Feature",
  "properties": {
    "gn:admin1_code":"32.0",
    "gn:asciiname":"Changdipian",
    "gn:country_code":"CN",
    "gn:dem":743,
    "gn:feature_class":"P",
    "gn:feature_code":"PPL",
    "gn:name":"Changdipian",
    "gn:population":0,
    "gn:timezone":"Asia/Shanghai",
    "iso:country":"CN",
    "name:zho_x_preferred":[
        "\u957f\u5730\u7247"
    ],
    "wof:name":"Changdipian",
    "wof:placetype":"locality"
},
  "geometry": {"coordinates":[104.926,28.3631],"type":"Point"}
}