{
  "type": "Feature",
  "properties": {
    "gn:admin1_code":"11",
    "gn:asciiname":"Niu'etang",
    "gn:country_code":"CN",
    "gn:dem":343,
    "gn:feature_class":"P",
    "gn:feature_code":"PPL",
    "gn:name":"Niu\u2019etang",
    "gn:population":0,
    "gn:timezone":"Asia/Shanghai",
    "iso:country":"CN",
    "name:und_x_variant":[
        "Niu\u2019etang"
    ],
    "name:zho_x_preferred":[
        "\u725b\u627c\u5858"
    ],
    "name:zho_x_variant":[
        "\u725b\u8f6d\u5858"
    ],
    "wof:name":"Niu'etang",
    "wof:placetype":"locality"
},
  "geometry": {"coordinates":[111.22159000000001,27.21613],"type":"Point"}
}