{
  "type": "Feature",
  "properties": {
    "gn:admin1_code":"15.0",
    "gn:asciiname":"Niqiannang",
    "gn:country_code":"CN",
    "gn:dem":2972,
    "gn:feature_class":"P",
    "gn:feature_code":"PPL",
    "gn:name":"Niqiannang",
    "gn:population":0,
    "gn:timezone":"Asia/Shanghai",
    "iso:country":"CN",
    "name:und_x_variant":[
        "\u5c3c\u6b20\u56ca"
    ],
    "wof:name":"Niqiannang",
    "wof:placetype":"locality"
},
  "geometry": {"coordinates":[102.95162000000001,34.76205],"type":"Point"}
}