{
  "type": "Feature",
  "properties": {
    "gn:admin1_code":"18.0",
    "gn:asciiname":"Dongwang",
    "gn:country_code":"CN",
    "gn:dem":937,
    "gn:feature_class":"P",
    "gn:feature_code":"PPL",
    "gn:name":"Dongwang",
    "gn:population":0,
    "gn:timezone":"Asia/Shanghai",
    "iso:country":"CN",
    "name:deu_x_preferred":[
        "Dongwang"
    ],
    "name:zho_x_preferred":[
        "\u8463\u738b"
    ],
    "wof:name":"Dongwang",
    "wof:placetype":"locality"
},
  "geometry": {"coordinates":[107.625,25.4612],"type":"Point"}
}