{
  "type": "Feature",
  "properties": {
    "gn:admin1_code":"15.0",
    "gn:asciiname":"Miaohao",
    "gn:country_code":"CN",
    "gn:dem":1553,
    "gn:feature_class":"P",
    "gn:feature_code":"PPL",
    "gn:name":"Miaohao",
    "gn:population":0,
    "gn:timezone":"Asia/Shanghai",
    "iso:country":"CN",
    "name:und_x_variant":[
        "\u5e99\u58d5"
    ],
    "wof:name":"Miaohao",
    "wof:placetype":"locality"
},
  "geometry": {"coordinates":[107.43235,36.81374],"type":"Point"}
}