{
  "type": "Feature",
  "properties": {
    "gn:admin1_code":"7.0",
    "gn:asciiname":"Fushi",
    "gn:country_code":"CN",
    "gn:dem":279,
    "gn:feature_class":"P",
    "gn:feature_code":"PPL",
    "gn:name":"Fushi",
    "gn:population":0,
    "gn:timezone":"Asia/Shanghai",
    "iso:country":"CN",
    "name:ceb_x_preferred":[
        "Fushi"
    ],
    "name:fra_x_preferred":[
        "Fushi"
    ],
    "name:nld_x_preferred":[
        "Fushi"
    ],
    "name:swe_x_preferred":[
        "Fushi"
    ],
    "name:zho_x_preferred":[
        "\u5bcc\u77f3"
    ],
    "wof:name":"Fushi",
    "wof:placetype":"locality"
},
  "geometry": {"coordinates":[117.93176,27.11706],"type":"Point"}
}