{
  "type": "Feature",
  "properties": {
    "gn:admin1_code":"21.0",
    "gn:asciiname":"Jinya",
    "gn:country_code":"CN",
    "gn:dem":1188,
    "gn:feature_class":"P",
    "gn:feature_code":"PPL",
    "gn:name":"Jinya",
    "gn:population":0,
    "gn:timezone":"Asia/Shanghai",
    "iso:country":"CN",
    "name:zho_x_preferred":[
        "\u9773\u5d16"
    ],
    "wof:name":"Jinya",
    "wof:placetype":"locality"
},
  "geometry": {"coordinates":[105.622,37.4856],"type":"Point"}
}