{
  "type": "Feature",
  "properties": {
    "gn:admin1_code":"29.0",
    "gn:asciiname":"Hedengcun",
    "gn:country_code":"CN",
    "gn:dem":1790,
    "gn:feature_class":"P",
    "gn:feature_code":"PPL",
    "gn:name":"Hedengcun",
    "gn:population":0,
    "gn:timezone":"Asia/Shanghai",
    "iso:country":"CN",
    "name:zho_x_preferred":[
        "\u79be\u767b\u6751"
    ],
    "wof:name":"Hedengcun",
    "wof:placetype":"locality"
},
  "geometry": {"coordinates":[103.051,24.9739],"type":"Point"}
}