{
  "type": "Feature",
  "properties": {
    "gn:admin1_code":"18",
    "gn:asciiname":"Sandanba",
    "gn:country_code":"CN",
    "gn:dem":1152,
    "gn:feature_class":"P",
    "gn:feature_code":"PPL",
    "gn:name":"Sandanba",
    "gn:population":0,
    "gn:timezone":"Asia/Shanghai",
    "iso:country":"CN",
    "name:zho_x_preferred":[
        "\u4e09\u62c5\u575d"
    ],
    "wof:name":"Sandanba",
    "wof:placetype":"locality"
},
  "geometry": {"coordinates":[107.98999999999999,28.4497],"type":"Point"}
}