{
  "type": "Feature",
  "properties": {
    "gn:admin1_code":"8.0",
    "gn:asciiname":"Jinxiangcun",
    "gn:country_code":"CN",
    "gn:dem":249,
    "gn:feature_class":"P",
    "gn:feature_code":"PPL",
    "gn:name":"Jinxiangcun",
    "gn:population":0,
    "gn:timezone":"Asia/Shanghai",
    "iso:country":"CN",
    "name:zho_x_preferred":[
        "\u91d1\u4e61\u6751"
    ],
    "wof:name":"Jinxiangcun",
    "wof:placetype":"locality"
},
  "geometry": {"coordinates":[131.28876,45.76368],"type":"Point"}
}