{
  "type": "Feature",
  "properties": {
    "gn:admin1_code":"25.0",
    "gn:asciiname":"Dazhuangzicun",
    "gn:country_code":"CN",
    "gn:dem":33,
    "gn:feature_class":"P",
    "gn:feature_code":"PPL",
    "gn:name":"Dazhuangzicun",
    "gn:population":0,
    "gn:timezone":"Asia/Shanghai",
    "iso:country":"CN",
    "name:zho_x_preferred":[
        "\u5927\u5e84\u5b50\u6751"
    ],
    "wof:name":"Dazhuangzicun",
    "wof:placetype":"locality"
},
  "geometry": {"coordinates":[119.75712,36.96957],"type":"Point"}
}