{
  "type": "Feature",
  "properties": {
    "gn:admin1_code":"18.0",
    "gn:asciiname":"Sige",
    "gn:country_code":"CN",
    "gn:dem":638,
    "gn:feature_class":"P",
    "gn:feature_code":"PPL",
    "gn:name":"Sige",
    "gn:population":0,
    "gn:timezone":"Asia/Shanghai",
    "iso:country":"CN",
    "name:ceb_x_preferred":[
        "Sige"
    ],
    "name:fra_x_preferred":[
        "Sige"
    ],
    "name:msa_x_preferred":[
        "Sige"
    ],
    "name:por_x_preferred":[
        "Sige"
    ],
    "name:slv_x_preferred":[
        "Sige"
    ],
    "name:srp_x_preferred":[
        "\u0421\u0438\u0433\u0435"
    ],
    "name:zho_x_preferred":[
        "\u56db\u683c"
    ],
    "wof:name":"Sige",
    "wof:placetype":"locality"
},
  "geometry": {"coordinates":[108.27800000000001,25.9624],"type":"Point"}
}