{
  "type": "Feature",
  "properties": {
    "gn:admin1_code":"30",
    "gn:asciiname":"Maxu",
    "gn:country_code":"CN",
    "gn:dem":21,
    "gn:feature_class":"P",
    "gn:feature_code":"PPLA4",
    "gn:name":"Maxu",
    "gn:population":0,
    "gn:timezone":"Asia/Shanghai",
    "iso:country":"CN",
    "name:und_x_variant":[
        "Mawei",
        "Maxu",
        "Mayu Zhen",
        "\u9a6c\u5729\u9547"
    ],
    "name:zho_x_preferred":[
        "\u9a6c\u5729"
    ],
    "wof:name":"Maxu",
    "wof:placetype":"locality"
},
  "geometry": {"coordinates":[111.83678,23.23974],"type":"Point"}
}