{
  "type": "Feature",
  "properties": {
    "gn:admin1_code":"18",
    "gn:asciiname":"Tuozhai",
    "gn:country_code":"CN",
    "gn:dem":763,
    "gn:feature_class":"P",
    "gn:feature_code":"PPL",
    "gn:name":"Tuozhai",
    "gn:population":0,
    "gn:timezone":"Asia/Shanghai",
    "iso:country":"CN",
    "name:zho_x_preferred":[
        "\u9640\u5be8"
    ],
    "wof:name":"Tuozhai",
    "wof:placetype":"locality"
},
  "geometry": {"coordinates":[108.34999999999999,27.8457],"type":"Point"}
}