{
  "type": "Feature",
  "properties": {
    "gn:admin1_code":"12.0",
    "gn:asciiname":"Niulanjie",
    "gn:country_code":"CN",
    "gn:dem":732,
    "gn:feature_class":"P",
    "gn:feature_code":"PPL",
    "gn:name":"Niulanjie",
    "gn:population":0,
    "gn:timezone":"Asia/Shanghai",
    "iso:country":"CN",
    "name:und_x_variant":[
        "Niulangai",
        "Niulanjie",
        "\u725b\u680f\u754c"
    ],
    "name:zho_x_preferred":[
        "\u725b\u5170\u76d6"
    ],
    "wof:name":"Niulanjie",
    "wof:placetype":"locality"
},
  "geometry": {"coordinates":[109.2833,29.82597],"type":"Point"}
}