{
  "type": "Feature",
  "properties": {
    "gn:admin1_code":"11.0",
    "gn:asciiname":"Xinwanli",
    "gn:country_code":"CN",
    "gn:dem":88,
    "gn:feature_class":"P",
    "gn:feature_code":"PPL",
    "gn:name":"Xinwanli",
    "gn:population":0,
    "gn:timezone":"Asia/Shanghai",
    "iso:country":"CN",
    "name:zho_x_preferred":[
        "\u65b0\u6e7e\u91cc"
    ],
    "wof:name":"Xinwanli",
    "wof:placetype":"locality"
},
  "geometry": {"coordinates":[112.90498999999998,26.45334],"type":"Point"}
}