{
  "type": "Feature",
  "properties": {
    "gn:admin1_code":"18",
    "gn:asciiname":"Leidazhai",
    "gn:country_code":"CN",
    "gn:dem":1527,
    "gn:feature_class":"P",
    "gn:feature_code":"PPL",
    "gn:name":"Leidazhai",
    "gn:population":0,
    "gn:timezone":"Asia/Shanghai",
    "iso:country":"CN",
    "name:zho_x_preferred":[
        "\u96f7\u6253\u5be8"
    ],
    "wof:name":"Leidazhai",
    "wof:placetype":"locality"
},
  "geometry": {"coordinates":[104.68899999999999,26.2063],"type":"Point"}
}