{
  "type": "Feature",
  "properties": {
    "gn:admin1_code":"16.0",
    "gn:asciiname":"Naxin",
    "gn:country_code":"CN",
    "gn:dem":171,
    "gn:feature_class":"P",
    "gn:feature_code":"PPL",
    "gn:name":"Naxin",
    "gn:population":0,
    "gn:timezone":"Asia/Shanghai",
    "iso:country":"CN",
    "name:zho_x_preferred":[
        "\u90a3\u65b0"
    ],
    "wof:name":"Naxin",
    "wof:placetype":"locality"
},
  "geometry": {"coordinates":[106.89400000000001,22.417],"type":"Point"}
}