{
  "type": "Feature",
  "properties": {
    "gn:admin1_code":"33.0",
    "gn:asciiname":"Baisheng",
    "gn:country_code":"CN",
    "gn:dem":378,
    "gn:feature_class":"P",
    "gn:feature_code":"PPLA4",
    "gn:name":"Baisheng",
    "gn:population":0,
    "gn:timezone":"Asia/Shanghai",
    "iso:country":"CN",
    "name:und_x_variant":[
        "Baisheng Zhen",
        "Baijiachang"
    ],
    "name:zho_x_preferred":[
        "\u767e\u80dc"
    ],
    "name:zho_x_variant":[
        "\u767e\u80dc\u9547",
        "\u767e\u5bb6\u573a"
    ],
    "wof:name":"Baisheng",
    "wof:placetype":"locality"
},
  "geometry": {"coordinates":[107.39261,29.81351],"type":"Point"}
}