{
  "type": "Feature",
  "properties": {
    "gn:admin1_code":"15.0",
    "gn:asciiname":"Diaogou",
    "gn:country_code":"CN",
    "gn:dem":1897,
    "gn:feature_class":"P",
    "gn:feature_code":"PPL",
    "gn:name":"Diaogou",
    "gn:population":0,
    "gn:timezone":"Asia/Shanghai",
    "iso:country":"CN",
    "name:zho_x_preferred":[
        "\u540a\u6c9f"
    ],
    "wof:name":"Diaogou",
    "wof:placetype":"locality"
},
  "geometry": {"coordinates":[105.23399999999999,34.4364],"type":"Point"}
}