{
  "type": "Feature",
  "properties": {
    "gn:admin1_code":"26.0",
    "gn:asciiname":"Huangtupo",
    "gn:country_code":"CN",
    "gn:dem":324,
    "gn:feature_class":"P",
    "gn:feature_code":"PPL",
    "gn:name":"Huangtupo",
    "gn:population":0,
    "gn:timezone":"Asia/Shanghai",
    "iso:country":"CN",
    "name:zho_x_preferred":[
        "\u9ec4\u571f\u5761"
    ],
    "wof:name":"Huangtupo",
    "wof:placetype":"locality"
},
  "geometry": {"coordinates":[110.95931000000002,33.29387],"type":"Point"}
}