{
  "type": "Feature",
  "properties": {
    "gn:admin1_code":"10",
    "gn:asciiname":"Shangdian",
    "gn:country_code":"CN",
    "gn:dem":1387,
    "gn:feature_class":"P",
    "gn:feature_code":"PPL",
    "gn:name":"Shangdian",
    "gn:population":0,
    "gn:timezone":"Asia/Shanghai",
    "iso:country":"CN",
    "name:zho_x_preferred":[
        "\u4e0a\u5e97"
    ],
    "wof:name":"Shangdian",
    "wof:placetype":"locality"
},
  "geometry": {"coordinates":[115.31137,41.69321],"type":"Point"}
}