{
  "type": "Feature",
  "properties": {
    "gn:admin1_code":"32.0",
    "gn:asciiname":"Wengjiagu",
    "gn:country_code":"CN",
    "gn:dem":1617,
    "gn:feature_class":"P",
    "gn:feature_code":"PPL",
    "gn:name":"Wengjiagu",
    "gn:population":0,
    "gn:timezone":"Asia/Shanghai",
    "iso:country":"CN",
    "name:zho_x_preferred":[
        "\u7fc1\u52a0\u59d1"
    ],
    "wof:name":"Wengjiagu",
    "wof:placetype":"locality"
},
  "geometry": {"coordinates":[103.19499999999999,28.9572],"type":"Point"}
}