{
  "type": "Feature",
  "properties": {
    "gn:admin1_code":"12.0",
    "gn:asciiname":"Xiaolongmugou",
    "gn:country_code":"CN",
    "gn:dem":1113,
    "gn:feature_class":"P",
    "gn:feature_code":"PPL",
    "gn:name":"Xiaolongmugou",
    "gn:population":0,
    "gn:timezone":"Asia/Shanghai",
    "iso:country":"CN",
    "name:zho_x_preferred":[
        "\u5c0f\u9f99\u6728\u6c9f"
    ],
    "wof:name":"Xiaolongmugou",
    "wof:placetype":"locality"
},
  "geometry": {"coordinates":[110.53239000000001,31.93499000000001],"type":"Point"}
}