{
  "type": "Feature",
  "properties": {
    "gn:admin1_code":"4.0",
    "gn:asciiname":"Taozha",
    "gn:country_code":"CN",
    "gn:dem":4,
    "gn:feature_class":"P",
    "gn:feature_code":"PPL",
    "gn:name":"Taozha",
    "gn:population":0,
    "gn:timezone":"Asia/Shanghai",
    "iso:country":"CN",
    "name:zho_x_preferred":[
        "Taozha"
    ],
    "name:zho_x_variant":[
        "\u5957\u95f8"
    ],
    "wof:name":"Taozha",
    "wof:placetype":"locality"
},
  "geometry": {"coordinates":[121.03942000000001,32.28326],"type":"Point"}
}