{
  "type": "Feature",
  "properties": {
    "gn:admin1_code":"29.0",
    "gn:asciiname":"Changdige",
    "gn:country_code":"CN",
    "gn:dem":2026,
    "gn:feature_class":"P",
    "gn:feature_code":"PPL",
    "gn:name":"Changdige",
    "gn:population":0,
    "gn:timezone":"Asia/Shanghai",
    "iso:country":"CN",
    "name:zho_x_preferred":[
        "\u957f\u5730\u683c"
    ],
    "wof:name":"Changdige",
    "wof:placetype":"locality"
},
  "geometry": {"coordinates":[103.24299999999999,25.5165],"type":"Point"}
}