{
  "type": "Feature",
  "properties": {
    "gn:admin1_code":"24",
    "gn:asciiname":"Sucun",
    "gn:country_code":"CN",
    "gn:dem":1002,
    "gn:feature_class":"P",
    "gn:feature_code":"PPL",
    "gn:name":"Sucun",
    "gn:population":0,
    "gn:timezone":"Asia/Shanghai",
    "iso:country":"CN",
    "name:und_x_variant":[
        "Su-ts\u2019un",
        "Sucun"
    ],
    "name:zho_x_preferred":[
        "\u82cf\u6751"
    ],
    "wof:name":"Sucun",
    "wof:placetype":"locality"
},
  "geometry": {"coordinates":[112.48396,38.06683],"type":"Point"}
}