{
  "type": "Feature",
  "properties": {
    "gn:admin1_code":"5.0",
    "gn:asciiname":"Matuncun",
    "gn:country_code":"CN",
    "gn:dem":216,
    "gn:feature_class":"P",
    "gn:feature_code":"PPL",
    "gn:name":"Matuncun",
    "gn:population":0,
    "gn:timezone":"Asia/Shanghai",
    "iso:country":"CN",
    "name:zho_x_preferred":[
        "\u9a6c\u5c6f\u6751"
    ],
    "wof:name":"Matuncun",
    "wof:placetype":"locality"
},
  "geometry": {"coordinates":[126.01900000000001,43.70265],"type":"Point"}
}