{
  "type": "Feature",
  "properties": {
    "gn:admin1_code":"30.0",
    "gn:asciiname":"Xiatian Laitang",
    "gn:country_code":"CN",
    "gn:dem":369,
    "gn:feature_class":"P",
    "gn:feature_code":"PPL",
    "gn:name":"Xiatian Laitang",
    "gn:population":0,
    "gn:timezone":"Asia/Shanghai",
    "iso:country":"CN",
    "name:zho_x_preferred":[
        "\u4e0b\u7530\u6765\u5858"
    ],
    "wof:name":"Xiatian Laitang",
    "wof:placetype":"locality"
},
  "geometry": {"coordinates":[114.58055,24.34425],"type":"Point"}
}