{
  "type": "Feature",
  "properties": {
    "gn:admin1_code":"30.0",
    "gn:asciiname":"Henglong",
    "gn:country_code":"CN",
    "gn:dem":306,
    "gn:feature_class":"P",
    "gn:feature_code":"PPL",
    "gn:name":"Henglong",
    "gn:population":0,
    "gn:timezone":"Asia/Shanghai",
    "iso:country":"CN",
    "name:zho_x_preferred":[
        "Henglong"
    ],
    "name:zho_x_variant":[
        "\u6a2a\u9f99"
    ],
    "wof:name":"Henglong",
    "wof:placetype":"locality"
},
  "geometry": {"coordinates":[114.29461999999999,24.76741],"type":"Point"}
}