{
  "type": "Feature",
  "properties": {
    "gn:admin1_code":"3.0",
    "gn:asciiname":"Hunanchun",
    "gn:country_code":"CN",
    "gn:dem":23,
    "gn:feature_class":"P",
    "gn:feature_code":"PPL",
    "gn:name":"Hunanchun",
    "gn:population":0,
    "gn:timezone":"Asia/Shanghai",
    "iso:country":"CN",
    "name:und_x_variant":[
        "\u80e1\u5357\u6625"
    ],
    "wof:name":"Hunanchun",
    "wof:placetype":"locality"
},
  "geometry": {"coordinates":[116.36315999999999,29.81165],"type":"Point"}
}