{
  "type": "Feature",
  "properties": {
    "gn:admin1_code":"10",
    "gn:asciiname":"San-ho-ts'un",
    "gn:country_code":"CN",
    "gn:dem":701,
    "gn:feature_class":"P",
    "gn:feature_code":"PPL",
    "gn:name":"San-ho-ts\u2019un",
    "gn:population":0,
    "gn:timezone":"Asia/Shanghai",
    "iso:country":"CN",
    "wof:name":"San-ho-ts'un",
    "wof:placetype":"locality"
},
  "geometry": {"coordinates":[117.55500000000001,40.38472],"type":"Point"}
}