{
  "type": "Feature",
  "properties": {
    "gn:admin1_code":"16.0",
    "gn:asciiname":"Tengbaochong",
    "gn:country_code":"CN",
    "gn:dem":379,
    "gn:feature_class":"P",
    "gn:feature_code":"PPL",
    "gn:name":"Tengbaochong",
    "gn:population":0,
    "gn:timezone":"Asia/Shanghai",
    "iso:country":"CN",
    "name:zho_x_preferred":[
        "\u85e4\u5b9d\u51b2"
    ],
    "wof:name":"Tengbaochong",
    "wof:placetype":"locality"
},
  "geometry": {"coordinates":[110.762,24.0051],"type":"Point"}
}