{
  "type": "Feature",
  "properties": {
    "gn:admin1_code":"32.0",
    "gn:asciiname":"Changtian",
    "gn:country_code":"CN",
    "gn:dem":1329,
    "gn:feature_class":"P",
    "gn:feature_code":"PPL",
    "gn:name":"Changtian",
    "gn:population":0,
    "gn:timezone":"Asia/Shanghai",
    "iso:country":"CN",
    "name:zho_x_preferred":[
        "\u957f\u7530"
    ],
    "wof:name":"Changtian",
    "wof:placetype":"locality"
},
  "geometry": {"coordinates":[101.518,26.5494],"type":"Point"}
}