{
  "type": "Feature",
  "properties": {
    "gn:admin1_code":"33.0",
    "gn:asciiname":"Huilongqiao",
    "gn:country_code":"CN",
    "gn:dem":531,
    "gn:feature_class":"P",
    "gn:feature_code":"PPL",
    "gn:name":"Huilongqiao",
    "gn:population":0,
    "gn:timezone":"Asia/Shanghai",
    "iso:country":"CN",
    "name:zho_x_preferred":[
        "\u4f1a\u9f99\u6865"
    ],
    "wof:name":"Huilongqiao",
    "wof:placetype":"locality"
},
  "geometry": {"coordinates":[105.75467999999999,29.34169],"type":"Point"}
}