{
  "type": "Feature",
  "properties": {
    "gn:admin1_code":"7",
    "gn:asciiname":"Xiaxincun",
    "gn:country_code":"CN",
    "gn:dem":21,
    "gn:feature_class":"P",
    "gn:feature_code":"PPL",
    "gn:name":"Xiaxincun",
    "gn:population":0,
    "gn:timezone":"Asia/Shanghai",
    "iso:country":"CN",
    "name:und_x_variant":[
        "Xiaguang"
    ],
    "name:zho_x_preferred":[
        "\u971e\u65b0\u6751"
    ],
    "name:zho_x_variant":[
        "\u971e\u5149"
    ],
    "wof:name":"Xiaxincun",
    "wof:placetype":"locality"
},
  "geometry": {"coordinates":[118.47778,24.92028],"type":"Point"}
}