{
  "type": "Feature",
  "properties": {
    "gn:admin1_code":"15.0",
    "gn:asciiname":"Xiongchi",
    "gn:country_code":"CN",
    "gn:dem":1367,
    "gn:feature_class":"P",
    "gn:feature_code":"PPLA4",
    "gn:name":"Xiongchi",
    "gn:population":0,
    "gn:timezone":"Asia/Shanghai",
    "iso:country":"CN",
    "name:und_x_variant":[
        "\u718a\u6c60"
    ],
    "wof:name":"Xiongchi",
    "wof:placetype":"locality"
},
  "geometry": {"coordinates":[105.33033,33.40575],"type":"Point"}
}