{
  "type": "Feature",
  "properties": {
    "gn:admin1_code":"32.0",
    "gn:asciiname":"Jimaodian",
    "gn:country_code":"CN",
    "gn:dem":2832,
    "gn:feature_class":"P",
    "gn:feature_code":"PPL",
    "gn:name":"Jimaodian",
    "gn:population":0,
    "gn:timezone":"Asia/Shanghai",
    "iso:country":"CN",
    "name:zho_x_preferred":[
        "\u9e21\u6bdb\u5e97"
    ],
    "wof:name":"Jimaodian",
    "wof:placetype":"locality"
},
  "geometry": {"coordinates":[101.544,28.2024],"type":"Point"}
}