{
  "type": "Feature",
  "properties": {
    "gn:admin1_code":"26.0",
    "gn:asciiname":"Yangtiao",
    "gn:country_code":"CN",
    "gn:dem":1408,
    "gn:feature_class":"P",
    "gn:feature_code":"PPL",
    "gn:name":"Yangtiao",
    "gn:population":0,
    "gn:timezone":"Asia/Shanghai",
    "iso:country":"CN",
    "name:zho_x_preferred":[
        "\u6768\u6761"
    ],
    "wof:name":"Yangtiao",
    "wof:placetype":"locality"
},
  "geometry": {"coordinates":[109.37514,37.09044],"type":"Point"}
}