{
  "type": "Feature",
  "properties": {
    "gn:admin1_code":"19.0",
    "gn:asciiname":"Guojiacun",
    "gn:country_code":"CN",
    "gn:dem":188,
    "gn:feature_class":"P",
    "gn:feature_code":"PPL",
    "gn:name":"Guojiacun",
    "gn:population":0,
    "gn:timezone":"Asia/Shanghai",
    "iso:country":"CN",
    "name:zho_x_preferred":[
        "\u90ed\u5bb6\u6751"
    ],
    "wof:name":"Guojiacun",
    "wof:placetype":"locality"
},
  "geometry": {"coordinates":[120.40089999999999,41.52829000000001],"type":"Point"}
}