{
  "type": "Feature",
  "properties": {
    "gn:admin1_code":"20",
    "gn:asciiname":"Gun Holoi",
    "gn:cc2":"CN",
    "gn:country_code":"CN",
    "gn:dem":134,
    "gn:feature_class":"P",
    "gn:feature_code":"PPL",
    "gn:name":"Gun Holoi",
    "gn:population":0,
    "gn:timezone":"Asia/Shanghai",
    "iso:country":"CN",
    "name:und_x_variant":[
        "Kung-ho-lai",
        "Gun Holoi"
    ],
    "wof:name":"Gun Holoi",
    "wof:placetype":"locality"
},
  "geometry": {"coordinates":[123.14278,42.89778],"type":"Point"}
}