{
  "type": "Feature",
  "properties": {
    "gn:admin1_code":"10",
    "gn:asciiname":"Shuishitang",
    "gn:country_code":"CN",
    "gn:dem":1653,
    "gn:feature_class":"P",
    "gn:feature_code":"PPL",
    "gn:name":"Shuishitang",
    "gn:population":0,
    "gn:timezone":"Asia/Shanghai",
    "iso:country":"CN",
    "wof:name":"Shuishitang",
    "wof:placetype":"locality"
},
  "geometry": {"coordinates":[115.11611000000001,39.9675],"type":"Point"}
}