{
  "type": "Feature",
  "properties": {
    "gn:admin1_code":"2.0",
    "gn:asciiname":"Shentanghou",
    "gn:country_code":"CN",
    "gn:dem":358,
    "gn:feature_class":"P",
    "gn:feature_code":"PPL",
    "gn:name":"Shentanghou",
    "gn:population":0,
    "gn:timezone":"Asia/Shanghai",
    "iso:country":"CN",
    "name:zho_x_preferred":[
        "\u6df1\u5858\u540e"
    ],
    "wof:name":"Shentanghou",
    "wof:placetype":"locality"
},
  "geometry": {"coordinates":[119.58056000000001,28.81509],"type":"Point"}
}