{
  "type": "Feature",
  "properties": {
    "gn:admin1_code":"3.0",
    "gn:asciiname":"Cailing",
    "gn:country_code":"CN",
    "gn:dem":40,
    "gn:feature_class":"P",
    "gn:feature_code":"PPLA4",
    "gn:name":"Cailing",
    "gn:population":0,
    "gn:timezone":"Asia/Shanghai",
    "iso:country":"CN",
    "name:und_x_variant":[
        "\u8521\u5cad",
        "Cailing Zhen",
        "\u8521\u5cad\u9547"
    ],
    "wof:name":"Cailing",
    "wof:placetype":"locality"
},
  "geometry": {"coordinates":[116.38109,29.49985],"type":"Point"}
}