{
  "type": "Feature",
  "properties": {
    "gn:admin1_code":"26.0",
    "gn:asciiname":"Nianyaowan",
    "gn:country_code":"CN",
    "gn:dem":1515,
    "gn:feature_class":"P",
    "gn:feature_code":"PPL",
    "gn:name":"Nianyaowan",
    "gn:population":0,
    "gn:timezone":"Asia/Shanghai",
    "iso:country":"CN",
    "name:und_x_variant":[
        "\u78be\u7a91\u6e7e"
    ],
    "wof:name":"Nianyaowan",
    "wof:placetype":"locality"
},
  "geometry": {"coordinates":[107.73213,36.94537],"type":"Point"}
}