{
  "type": "Feature",
  "properties": {
    "gn:admin1_code":"26.0",
    "gn:asciiname":"Maojia'ancun",
    "gn:country_code":"CN",
    "gn:dem":1080,
    "gn:feature_class":"P",
    "gn:feature_code":"PPL",
    "gn:name":"Maojia\u2019ancun",
    "gn:population":0,
    "gn:timezone":"Asia/Shanghai",
    "iso:country":"CN",
    "name:und_x_variant":[
        "Maojia\u2019ancun"
    ],
    "name:zho_x_preferred":[
        "\u6bdb\u5bb6\u5b89\u6751"
    ],
    "wof:name":"Maojia'ancun",
    "wof:placetype":"locality"
},
  "geometry": {"coordinates":[109.26013,36.20127],"type":"Point"}
}