{
  "type": "Feature",
  "properties": {
    "gn:admin1_code":"32.0",
    "gn:asciiname":"Luwamo",
    "gn:country_code":"CN",
    "gn:dem":2461,
    "gn:feature_class":"P",
    "gn:feature_code":"PPL",
    "gn:name":"Luwamo",
    "gn:population":0,
    "gn:timezone":"Asia/Shanghai",
    "iso:country":"CN",
    "name:zho_x_preferred":[
        "\u9c81\u74e6\u83ab"
    ],
    "wof:name":"Luwamo",
    "wof:placetype":"locality"
},
  "geometry": {"coordinates":[102.91598999999999,28.01236],"type":"Point"}
}