{
  "type": "Feature",
  "properties": {
    "gn:admin1_code":"30",
    "gn:asciiname":"Guanhu",
    "gn:country_code":"CN",
    "gn:dem":4,
    "gn:feature_class":"P",
    "gn:feature_code":"PPL",
    "gn:name":"Guanhu",
    "gn:population":0,
    "gn:timezone":"Asia/Urumqi",
    "iso:country":"CN",
    "name:zho_x_preferred":[
        "\u5b98\u6e56"
    ],
    "wof:name":"Guanhu",
    "wof:placetype":"locality"
},
  "geometry": {"coordinates":[110.31431000000001,21.41034],"type":"Point"}
}