{
  "type": "Feature",
  "properties": {
    "gn:admin1_code":"32.0",
    "gn:asciiname":"Lieyue",
    "gn:country_code":"CN",
    "gn:dem":3344,
    "gn:feature_class":"P",
    "gn:feature_code":"PPL",
    "gn:name":"Lieyue",
    "gn:population":0,
    "gn:timezone":"Asia/Shanghai",
    "iso:country":"CN",
    "name:zho_x_preferred":[
        "\u5217\u7ea6"
    ],
    "wof:name":"Lieyue",
    "wof:placetype":"locality"
},
  "geometry": {"coordinates":[101.199,30.9424],"type":"Point"}
}