{
  "type": "Feature",
  "properties": {
    "gn:admin1_code":"13",
    "gn:asciiname":"Yingkaner",
    "gn:country_code":"CN",
    "gn:dem":276,
    "gn:feature_class":"P",
    "gn:feature_code":"PPL",
    "gn:name":"Yingkaner",
    "gn:population":0,
    "gn:timezone":"Asia/Urumqi",
    "iso:country":"CN",
    "name:und_x_variant":[
        "\u82f1\u574e\u513f"
    ],
    "wof:name":"Yingkaner",
    "wof:placetype":"locality"
},
  "geometry": {"coordinates":[89.49216,43.01085],"type":"Point"}
}