{
  "type": "Feature",
  "properties": {
    "gn:admin1_code":"21.0",
    "gn:asciiname":"Aofen",
    "gn:country_code":"CN",
    "gn:dem":1212,
    "gn:feature_class":"P",
    "gn:feature_code":"PPL",
    "gn:name":"Aofen",
    "gn:population":0,
    "gn:timezone":"Asia/Shanghai",
    "iso:country":"CN",
    "name:zho_x_preferred":[
        "\u51f9\u575f"
    ],
    "wof:name":"Aofen",
    "wof:placetype":"locality"
},
  "geometry": {"coordinates":[105.96299999999999,38.4387],"type":"Point"}
}