{
  "type": "Feature",
  "properties": {
    "gn:admin1_code":"15",
    "gn:asciiname":"Lianghekou",
    "gn:country_code":"CN",
    "gn:dem":1237,
    "gn:feature_class":"P",
    "gn:feature_code":"PPL",
    "gn:name":"Lianghekou",
    "gn:population":0,
    "gn:timezone":"Asia/Shanghai",
    "iso:country":"CN",
    "name:und_x_variant":[
        "Lyankhekou",
        "Lianghekou"
    ],
    "name:zho_x_preferred":[
        "Liang-ho-k\u2019ou"
    ],
    "name:zho_x_variant":[
        "\u4e24\u6cb3\u53e3"
    ],
    "wof:name":"Lianghekou",
    "wof:placetype":"locality"
},
  "geometry": {"coordinates":[104.488,33.6904],"type":"Point"}
}