{
  "type": "Feature",
  "properties": {
    "gn:admin1_code":"15.0",
    "gn:asciiname":"Liujiagou",
    "gn:country_code":"CN",
    "gn:dem":1276,
    "gn:feature_class":"P",
    "gn:feature_code":"PPL",
    "gn:name":"Liujiagou",
    "gn:population":0,
    "gn:timezone":"Asia/Shanghai",
    "iso:country":"CN",
    "name:zho_x_preferred":[
        "\u67f3\u5bb6\u6c9f"
    ],
    "wof:name":"Liujiagou",
    "wof:placetype":"locality"
},
  "geometry": {"coordinates":[106.97199999999999,35.3412],"type":"Point"}
}