{
  "type": "Feature",
  "properties": {
    "gn:admin1_code":"11.0",
    "gn:asciiname":"Chengquanpu",
    "gn:country_code":"CN",
    "gn:dem":103,
    "gn:feature_class":"P",
    "gn:feature_code":"PPL",
    "gn:name":"Chengquanpu",
    "gn:population":0,
    "gn:timezone":"Asia/Shanghai",
    "iso:country":"CN",
    "name:zho_x_preferred":[
        "\u6f84\u6cc9\u94fa"
    ],
    "wof:name":"Chengquanpu",
    "wof:placetype":"locality"
},
  "geometry": {"coordinates":[113.42603,26.89316],"type":"Point"}
}