{
  "type": "Feature",
  "properties": {
    "gn:admin1_code":"1.0",
    "gn:asciiname":"Youfangchongcun",
    "gn:country_code":"CN",
    "gn:dem":116,
    "gn:feature_class":"P",
    "gn:feature_code":"PPL",
    "gn:name":"Youfangchongcun",
    "gn:population":0,
    "gn:timezone":"Asia/Shanghai",
    "iso:country":"CN",
    "name:zho_x_preferred":[
        "\u6cb9\u574a\u51b2\u6751"
    ],
    "wof:name":"Youfangchongcun",
    "wof:placetype":"locality"
},
  "geometry": {"coordinates":[116.58358,31.48604000000001],"type":"Point"}
}