{
  "type": "Feature",
  "properties": {
    "gn:admin1_code":"10",
    "gn:asciiname":"Liushixing",
    "gn:country_code":"CN",
    "gn:dem":1412,
    "gn:feature_class":"P",
    "gn:feature_code":"PPL",
    "gn:name":"Liushixing",
    "gn:population":0,
    "gn:timezone":"Asia/Shanghai",
    "iso:country":"CN",
    "name:zho_x_preferred":[
        "\u5218\u4e16\u5174"
    ],
    "wof:name":"Liushixing",
    "wof:placetype":"locality"
},
  "geometry": {"coordinates":[114.57595999999999,41.80741],"type":"Point"}
}