{
  "type": "Feature",
  "properties": {
    "gn:admin1_code":"4.0",
    "gn:asciiname":"Taozhuang",
    "gn:country_code":"CN",
    "gn:dem":4,
    "gn:feature_class":"P",
    "gn:feature_code":"PPLA4",
    "gn:name":"Taozhuang",
    "gn:population":0,
    "gn:timezone":"Asia/Shanghai",
    "iso:country":"CN",
    "name:mlg_x_preferred":[
        "Taozhuang"
    ],
    "name:und_x_variant":[
        "\u9676\u5e84",
        "Taozhuang Zhen",
        "\u9676\u5e84\u9547"
    ],
    "name:zho_x_preferred":[
        "\u9676\u5e84\u9547"
    ],
    "wof:name":"Taozhuang",
    "wof:placetype":"locality"
},
  "geometry": {"coordinates":[120.13889,32.86667],"type":"Point"}
}