{
  "type": "Feature",
  "properties": {
    "gn:admin1_code":"15.0",
    "gn:asciiname":"Maquantan",
    "gn:country_code":"CN",
    "gn:dem":1085,
    "gn:feature_class":"P",
    "gn:feature_code":"PPL",
    "gn:name":"Maquantan",
    "gn:population":0,
    "gn:timezone":"Asia/Urumqi",
    "iso:country":"CN",
    "name:zho_x_preferred":[
        "\u9a6c\u5708\u6ee9"
    ],
    "wof:name":"Maquantan",
    "wof:placetype":"locality"
},
  "geometry": {"coordinates":[94.68640000000001,40.3079],"type":"Point"}
}