{
  "type": "Feature",
  "properties": {
    "gn:admin1_code":"29.0",
    "gn:asciiname":"Manjiunan Laozhai",
    "gn:country_code":"CN",
    "gn:dem":962,
    "gn:feature_class":"P",
    "gn:feature_code":"PPL",
    "gn:name":"Manjiunan Laozhai",
    "gn:population":0,
    "gn:timezone":"Asia/Shanghai",
    "iso:country":"CN",
    "name:zho_x_preferred":[
        "\u66fc\u65e7\u56e1\u8001\u5be8"
    ],
    "wof:name":"Manjiunan Laozhai",
    "wof:placetype":"locality"
},
  "geometry": {"coordinates":[100.824,21.9193],"type":"Point"}
}