{
  "type": "Feature",
  "properties": {
    "gn:admin1_code":"3.0",
    "gn:asciiname":"Chengxia Liujia",
    "gn:country_code":"CN",
    "gn:dem":22,
    "gn:feature_class":"P",
    "gn:feature_code":"PPL",
    "gn:name":"Chengxia Liujia",
    "gn:population":0,
    "gn:timezone":"Asia/Shanghai",
    "iso:country":"CN",
    "name:und_x_variant":[
        "\u57ce\u4e0b\u5218\u5bb6"
    ],
    "wof:name":"Chengxia Liujia",
    "wof:placetype":"locality"
},
  "geometry": {"coordinates":[116.43547,29.72734],"type":"Point"}
}