{
  "type": "Feature",
  "properties": {
    "gn:admin1_code":"32.0",
    "gn:asciiname":"Kuzhugang",
    "gn:country_code":"CN",
    "gn:dem":544,
    "gn:feature_class":"P",
    "gn:feature_code":"PPL",
    "gn:name":"Kuzhugang",
    "gn:population":0,
    "gn:timezone":"Asia/Shanghai",
    "iso:country":"CN",
    "name:zho_x_preferred":[
        "\u82e6\u7af9\u5c97"
    ],
    "wof:name":"Kuzhugang",
    "wof:placetype":"locality"
},
  "geometry": {"coordinates":[103.34999999999999,29.9287],"type":"Point"}
}