{
  "type": "Feature",
  "properties": {
    "gn:admin1_code":"5.0",
    "gn:asciiname":"Xinjiacun",
    "gn:country_code":"CN",
    "gn:dem":141,
    "gn:feature_class":"P",
    "gn:feature_code":"PPL",
    "gn:name":"Xinjiacun",
    "gn:population":0,
    "gn:timezone":"Asia/Shanghai",
    "iso:country":"CN",
    "name:zho_x_preferred":[
        "\u8f9b\u5bb6\u6751"
    ],
    "wof:name":"Xinjiacun",
    "wof:placetype":"locality"
},
  "geometry": {"coordinates":[124.95542,45.13216],"type":"Point"}
}