{
  "type": "Feature",
  "properties": {
    "gn:admin1_code":"29.0",
    "gn:asciiname":"Zhabieshan Laozhai",
    "gn:country_code":"CN",
    "gn:dem":1321,
    "gn:feature_class":"P",
    "gn:feature_code":"PPL",
    "gn:name":"Zhabieshan Laozhai",
    "gn:population":0,
    "gn:timezone":"Asia/Shanghai",
    "iso:country":"CN",
    "name:zho_x_preferred":[
        "\u624e\u522b\u5c71\u8001\u5be8"
    ],
    "wof:name":"Zhabieshan Laozhai",
    "wof:placetype":"locality"
},
  "geometry": {"coordinates":[100.021,22.7591],"type":"Point"}
}