{
  "type": "Feature",
  "properties": {
    "gn:admin1_code":"12.0",
    "gn:asciiname":"Xiazitang",
    "gn:country_code":"CN",
    "gn:dem":55,
    "gn:feature_class":"P",
    "gn:feature_code":"PPL",
    "gn:name":"Xiazitang",
    "gn:population":0,
    "gn:timezone":"Asia/Shanghai",
    "iso:country":"CN",
    "name:zho_x_preferred":[
        "Xiazitang"
    ],
    "name:zho_x_variant":[
        "\u867e\u5b50\u5858"
    ],
    "wof:name":"Xiazitang",
    "wof:placetype":"locality"
},
  "geometry": {"coordinates":[115.12347,30.61689],"type":"Point"}
}