{
  "type": "Feature",
  "properties": {
    "gn:admin1_code":"18.0",
    "gn:asciiname":"Yangxing",
    "gn:country_code":"CN",
    "gn:dem":641,
    "gn:feature_class":"P",
    "gn:feature_code":"PPLA4",
    "gn:name":"Yangxing",
    "gn:population":0,
    "gn:timezone":"Asia/Shanghai",
    "iso:country":"CN",
    "name:und_x_variant":[
        "Yangxing Zhen"
    ],
    "name:zho_x_preferred":[
        "\u6768\u5174"
    ],
    "name:zho_x_variant":[
        "\u6768\u5174\u9547"
    ],
    "wof:name":"Yangxing",
    "wof:placetype":"locality"
},
  "geometry": {"coordinates":[107.38643,28.70972],"type":"Point"}
}