{
  "type": "Feature",
  "properties": {
    "gn:admin1_code":"26.0",
    "gn:asciiname":"Qinjia Geda",
    "gn:country_code":"CN",
    "gn:dem":1274,
    "gn:feature_class":"P",
    "gn:feature_code":"PPL",
    "gn:name":"Qinjia Geda",
    "gn:population":0,
    "gn:timezone":"Asia/Shanghai",
    "iso:country":"CN",
    "name:zho_x_preferred":[
        "\u79e6\u5bb6\u572a\u57af"
    ],
    "wof:name":"Qinjia Geda",
    "wof:placetype":"locality"
},
  "geometry": {"coordinates":[110.00700000000001,39.1125],"type":"Point"}
}