{
  "type": "Feature",
  "properties": {
    "gn:admin1_code":"32.0",
    "gn:asciiname":"Yuanjiaci",
    "gn:country_code":"CN",
    "gn:dem":586,
    "gn:feature_class":"P",
    "gn:feature_code":"PPL",
    "gn:name":"Yuanjiaci",
    "gn:population":0,
    "gn:timezone":"Asia/Shanghai",
    "iso:country":"CN",
    "name:zho_x_preferred":[
        "\u8881\u5bb6\u8bcd"
    ],
    "wof:name":"Yuanjiaci",
    "wof:placetype":"locality"
},
  "geometry": {"coordinates":[103.669,30.7572],"type":"Point"}
}