{
  "type": "Feature",
  "properties": {
    "gn:admin1_code":"4.0",
    "gn:asciiname":"Fushancun",
    "gn:country_code":"CN",
    "gn:dem":11,
    "gn:feature_class":"P",
    "gn:feature_code":"PPL",
    "gn:name":"Fushancun",
    "gn:population":0,
    "gn:timezone":"Asia/Shanghai",
    "iso:country":"CN",
    "name:zho_x_preferred":[
        "\u7f58\u5c71\u6751"
    ],
    "wof:name":"Fushancun",
    "wof:placetype":"locality"
},
  "geometry": {"coordinates":[119.3717,34.4303],"type":"Point"}
}