{
  "type": "Feature",
  "properties": {
    "gn:admin1_code":"15.0",
    "gn:asciiname":"Huzhangwan",
    "gn:country_code":"CN",
    "gn:dem":1457,
    "gn:feature_class":"P",
    "gn:feature_code":"PPL",
    "gn:name":"Huzhangwan",
    "gn:population":0,
    "gn:timezone":"Asia/Shanghai",
    "iso:country":"CN",
    "name:zho_x_preferred":[
        "\u80e1\u638c\u6e7e"
    ],
    "wof:name":"Huzhangwan",
    "wof:placetype":"locality"
},
  "geometry": {"coordinates":[108.283,35.7416],"type":"Point"}
}