{
  "type": "Feature",
  "properties": {
    "gn:admin1_code":"32.0",
    "gn:asciiname":"Liexicun",
    "gn:country_code":"CN",
    "gn:dem":3136,
    "gn:feature_class":"P",
    "gn:feature_code":"PPL",
    "gn:name":"Liexicun",
    "gn:population":0,
    "gn:timezone":"Asia/Shanghai",
    "iso:country":"CN",
    "name:zho_x_preferred":[
        "\u5217\u897f\u6751"
    ],
    "wof:name":"Liexicun",
    "wof:placetype":"locality"
},
  "geometry": {"coordinates":[98.39790000000001,32.0541],"type":"Point"}
}