{
  "type": "Feature",
  "properties": {
    "gn:admin1_code":"24.0",
    "gn:asciiname":"Songjiacun",
    "gn:country_code":"CN",
    "gn:dem":1282,
    "gn:feature_class":"P",
    "gn:feature_code":"PPL",
    "gn:name":"Songjiacun",
    "gn:population":0,
    "gn:timezone":"Asia/Shanghai",
    "iso:country":"CN",
    "name:zho_x_preferred":[
        "\u5b8b\u5bb6\u6751"
    ],
    "wof:name":"Songjiacun",
    "wof:placetype":"locality"
},
  "geometry": {"coordinates":[111.94452,38.40504],"type":"Point"}
}