{
  "type": "Feature",
  "properties": {
    "gn:admin1_code":"19.0",
    "gn:asciiname":"Boyinhua",
    "gn:country_code":"CN",
    "gn:dem":174,
    "gn:feature_class":"P",
    "gn:feature_code":"PPL",
    "gn:name":"Boyinhua",
    "gn:population":0,
    "gn:timezone":"Asia/Shanghai",
    "iso:country":"CN",
    "name:zho_x_preferred":[
        "\u535a\u97f3\u82b1"
    ],
    "wof:name":"Boyinhua",
    "wof:placetype":"locality"
},
  "geometry": {"coordinates":[122.782,42.6474],"type":"Point"}
}