{
  "type": "Feature",
  "properties": {
    "gn:admin1_code":"29",
    "gn:asciiname":"Xinfazhai",
    "gn:country_code":"CN",
    "gn:dem":1277,
    "gn:feature_class":"P",
    "gn:feature_code":"PPL",
    "gn:name":"Xinfazhai",
    "gn:population":0,
    "gn:timezone":"Asia/Shanghai",
    "iso:country":"CN",
    "name:zho_x_preferred":[
        "\u65b0\u53d1\u5be8"
    ],
    "wof:name":"Xinfazhai",
    "wof:placetype":"locality"
},
  "geometry": {"coordinates":[104.672,23.216],"type":"Point"}
}