{
  "type": "Feature",
  "properties": {
    "gn:admin1_code":"25",
    "gn:asciiname":"Xinjia Zhuangzi",
    "gn:country_code":"CN",
    "gn:dem":163,
    "gn:feature_class":"P",
    "gn:feature_code":"PPL",
    "gn:name":"Xinjia Zhuangzi",
    "gn:population":0,
    "gn:timezone":"Asia/Shanghai",
    "iso:country":"CN",
    "name:zho_x_preferred":[
        "\u65b0\u5bb6\u5e84\u5b50"
    ],
    "wof:name":"Xinjia Zhuangzi",
    "wof:placetype":"locality"
},
  "geometry": {"coordinates":[118.33,35.5452],"type":"Point"}
}