{
  "type": "Feature",
  "properties": {
    "gn:admin1_code":"8.0",
    "gn:asciiname":"Sanjiazicun",
    "gn:country_code":"CN",
    "gn:dem":130,
    "gn:feature_class":"P",
    "gn:feature_code":"PPL",
    "gn:name":"Sanjiazicun",
    "gn:population":0,
    "gn:timezone":"Asia/Shanghai",
    "iso:country":"CN",
    "name:zho_x_preferred":[
        "\u4e09\u5bb6\u5b50\u6751"
    ],
    "wof:name":"Sanjiazicun",
    "wof:placetype":"locality"
},
  "geometry": {"coordinates":[124.9628,45.55907],"type":"Point"}
}