{
  "type": "Feature",
  "properties": {
    "gn:admin1_code":"02",
    "gn:asciiname":"Congkeng",
    "gn:cc2":"CN",
    "gn:country_code":"CN",
    "gn:dem":126,
    "gn:feature_class":"P",
    "gn:feature_code":"PPL",
    "gn:name":"Congkeng",
    "gn:population":0,
    "gn:timezone":"Asia/Shanghai",
    "iso:country":"CN",
    "name:und_x_variant":[
        "Nien-k\u2019eng",
        "Congkeng"
    ],
    "wof:name":"Congkeng",
    "wof:placetype":"locality"
},
  "geometry": {"coordinates":[121.30944,28.81306],"type":"Point"}
}