{
  "type": "Feature",
  "properties": {
    "gn:admin1_code":"30.0",
    "gn:asciiname":"Jiaolongcun",
    "gn:country_code":"CN",
    "gn:dem":5,
    "gn:feature_class":"P",
    "gn:feature_code":"PPL",
    "gn:name":"Jiaolongcun",
    "gn:population":0,
    "gn:timezone":"Asia/Shanghai",
    "iso:country":"CN",
    "name:zho_x_preferred":[
        "\u86df\u9f99\u6751"
    ],
    "wof:name":"Jiaolongcun",
    "wof:placetype":"locality"
},
  "geometry": {"coordinates":[116.49889,23.4756],"type":"Point"}
}