{
  "type": "Feature",
  "properties": {
    "gn:admin1_code":"20.0",
    "gn:asciiname":"Niuyangwan",
    "gn:country_code":"CN",
    "gn:dem":1493,
    "gn:feature_class":"P",
    "gn:feature_code":"PPL",
    "gn:name":"Niuyangwan",
    "gn:population":0,
    "gn:timezone":"Asia/Shanghai",
    "iso:country":"CN",
    "name:und_x_variant":[
        "\u725b\u7f8a\u6e7e"
    ],
    "wof:name":"Niuyangwan",
    "wof:placetype":"locality"
},
  "geometry": {"coordinates":[109.97654,40.79746],"type":"Point"}
}