{
  "type": "Feature",
  "properties": {
    "gn:admin1_code":"32.0",
    "gn:asciiname":"Yangyi",
    "gn:country_code":"CN",
    "gn:dem":575,
    "gn:feature_class":"P",
    "gn:feature_code":"PPL",
    "gn:name":"Yangyi",
    "gn:population":0,
    "gn:timezone":"Asia/Shanghai",
    "iso:country":"CN",
    "name:zho_x_preferred":[
        "\u6768\u4e49"
    ],
    "wof:name":"Yangyi",
    "wof:placetype":"locality"
},
  "geometry": {"coordinates":[104.68899999999999,28.3484],"type":"Point"}
}