{
  "type": "Feature",
  "properties": {
    "gn:admin1_code":"14.0",
    "gn:asciiname":"Angzha",
    "gn:country_code":"CN",
    "gn:dem":3314,
    "gn:feature_class":"P",
    "gn:feature_code":"PPL",
    "gn:name":"Angzha",
    "gn:population":0,
    "gn:timezone":"Asia/Urumqi",
    "iso:country":"CN",
    "name:zho_x_preferred":[
        "\u6602\u624e"
    ],
    "wof:name":"Angzha",
    "wof:placetype":"locality"
},
  "geometry": {"coordinates":[98.15996,32.37473],"type":"Point"}
}