{
  "type": "Feature",
  "properties": {
    "gn:admin1_code":"14.0",
    "gn:asciiname":"Menbacun",
    "gn:country_code":"CN",
    "gn:dem":2856,
    "gn:feature_class":"P",
    "gn:feature_code":"PPL",
    "gn:name":"Menbacun",
    "gn:population":0,
    "gn:timezone":"Asia/Urumqi",
    "iso:country":"CN",
    "name:zho_x_preferred":[
        "\u95e8\u5df4\u6751"
    ],
    "wof:name":"Menbacun",
    "wof:placetype":"locality"
},
  "geometry": {"coordinates":[98.89944,29.03545],"type":"Point"}
}