{
  "type": "Feature",
  "properties": {
    "gn:admin1_code":"31.0",
    "gn:asciiname":"Yanglin",
    "gn:country_code":"CN",
    "gn:dem":425,
    "gn:feature_class":"P",
    "gn:feature_code":"PPL",
    "gn:name":"Yanglin",
    "gn:population":0,
    "gn:timezone":"Asia/Shanghai",
    "iso:country":"CN",
    "name:und_x_variant":[
        "Yalin",
        "Yanglin",
        "\u6d0b\u6797"
    ],
    "name:zho_x_preferred":[
        "\u96c5\u6797"
    ],
    "wof:name":"Yanglin",
    "wof:placetype":"locality"
},
  "geometry": {"coordinates":[109.21178,18.50234],"type":"Point"}
}