{
  "type": "Feature",
  "properties": {
    "gn:admin1_code":"24.0",
    "gn:asciiname":"Langou",
    "gn:country_code":"CN",
    "gn:dem":733,
    "gn:feature_class":"P",
    "gn:feature_code":"PPL",
    "gn:name":"Langou",
    "gn:population":0,
    "gn:timezone":"Asia/Shanghai",
    "iso:country":"CN",
    "name:zho_x_preferred":[
        "\u62e6\u6c9f"
    ],
    "wof:name":"Langou",
    "wof:placetype":"locality"
},
  "geometry": {"coordinates":[113.66328,38.21208],"type":"Point"}
}