{
  "type": "Feature",
  "properties": {
    "gn:admin1_code":"24",
    "gn:asciiname":"Taipingbu",
    "gn:country_code":"CN",
    "gn:dem":1052,
    "gn:feature_class":"P",
    "gn:feature_code":"PPL",
    "gn:name":"Taipingbu",
    "gn:population":0,
    "gn:timezone":"Asia/Shanghai",
    "iso:country":"CN",
    "name:und_x_variant":[
        "T\u2019ai-p\u2019ing-p\u2019u",
        "T\u2019ai-p\u2019ing-pao",
        "Taipingbu"
    ],
    "name:zho_x_preferred":[
        "\u592a\u5e73\u5821"
    ],
    "wof:name":"Taipingbu",
    "wof:placetype":"locality"
},
  "geometry": {"coordinates":[113.93495,40.42941],"type":"Point"}
}