{
  "type": "Feature",
  "properties": {
    "gn:admin1_code":"16.0",
    "gn:asciiname":"Yuanwai",
    "gn:country_code":"CN",
    "gn:dem":1121,
    "gn:feature_class":"P",
    "gn:feature_code":"PPL",
    "gn:name":"Yuanwai",
    "gn:population":0,
    "gn:timezone":"Asia/Shanghai",
    "iso:country":"CN",
    "name:zho_x_preferred":[
        "\u5143\u5916"
    ],
    "wof:name":"Yuanwai",
    "wof:placetype":"locality"
},
  "geometry": {"coordinates":[105.206,24.3853],"type":"Point"}
}