{
  "type": "Feature",
  "properties": {
    "gn:admin1_code":"8.0",
    "gn:asciiname":"Paoziyancun",
    "gn:country_code":"CN",
    "gn:dem":111,
    "gn:feature_class":"P",
    "gn:feature_code":"PPL",
    "gn:name":"Paoziyancun",
    "gn:population":0,
    "gn:timezone":"Asia/Shanghai",
    "iso:country":"CN",
    "name:zho_x_preferred":[
        "\u6ce1\u5b50\u6cbf\u6751"
    ],
    "wof:name":"Paoziyancun",
    "wof:placetype":"locality"
},
  "geometry": {"coordinates":[128.16238999999999,45.94351],"type":"Point"}
}