{
  "type": "Feature",
  "properties": {
    "gn:admin1_code":"16.0",
    "gn:asciiname":"Qianma",
    "gn:country_code":"CN",
    "gn:dem":305,
    "gn:feature_class":"P",
    "gn:feature_code":"PPL",
    "gn:name":"Qianma",
    "gn:population":0,
    "gn:timezone":"Asia/Shanghai",
    "iso:country":"CN",
    "name:zho_x_preferred":[
        "\u4e7e\u9a6c"
    ],
    "wof:name":"Qianma",
    "wof:placetype":"locality"
},
  "geometry": {"coordinates":[108.95099999999999,23.9589],"type":"Point"}
}