{
  "type": "Feature",
  "properties": {
    "gn:admin1_code":"24.0",
    "gn:asciiname":"Jiangedui",
    "gn:country_code":"CN",
    "gn:dem":858,
    "gn:feature_class":"P",
    "gn:feature_code":"PPL",
    "gn:name":"Jiangedui",
    "gn:population":0,
    "gn:timezone":"Asia/Shanghai",
    "iso:country":"CN",
    "name:zho_x_preferred":[
        "\u5c16\u572a\u5806"
    ],
    "wof:name":"Jiangedui",
    "wof:placetype":"locality"
},
  "geometry": {"coordinates":[112.52285000000001,35.76748],"type":"Point"}
}