{
  "type": "Feature",
  "properties": {
    "gn:admin1_code":"05",
    "gn:asciiname":"Dapingling",
    "gn:country_code":"CN",
    "gn:dem":446,
    "gn:feature_class":"P",
    "gn:feature_code":"PPL",
    "gn:name":"Dapingling",
    "gn:population":0,
    "gn:timezone":"Asia/Shanghai",
    "iso:country":"CN",
    "name:zho_x_preferred":[
        "\u5927\u5e73\u5cad"
    ],
    "wof:name":"Dapingling",
    "wof:placetype":"locality"
},
  "geometry": {"coordinates":[126.52155,43.33696],"type":"Point"}
}