{
  "type": "Feature",
  "properties": {
    "gn:admin1_code":"1.0",
    "gn:asciiname":"Guoghengcun",
    "gn:country_code":"CN",
    "gn:dem":31,
    "gn:feature_class":"P",
    "gn:feature_code":"PPL",
    "gn:name":"Guoghengcun",
    "gn:population":0,
    "gn:timezone":"Asia/Shanghai",
    "iso:country":"CN",
    "name:zho_x_preferred":[
        "\u56fd\u653f\u6751"
    ],
    "wof:name":"Guoghengcun",
    "wof:placetype":"locality"
},
  "geometry": {"coordinates":[116.59571,33.56006],"type":"Point"}
}