{
  "type": "Feature",
  "properties": {
    "gn:admin1_code":"32.0",
    "gn:asciiname":"Zuoshuitang",
    "gn:country_code":"CN",
    "gn:dem":1200,
    "gn:feature_class":"P",
    "gn:feature_code":"PPL",
    "gn:name":"Zuoshuitang",
    "gn:population":0,
    "gn:timezone":"Asia/Shanghai",
    "iso:country":"CN",
    "name:zho_x_preferred":[
        "\u5750\u6c34\u5858"
    ],
    "wof:name":"Zuoshuitang",
    "wof:placetype":"locality"
},
  "geometry": {"coordinates":[104.63200000000001,32.3574],"type":"Point"}
}