{
  "type": "Feature",
  "properties": {
    "gn:admin1_code":"13.0",
    "gn:asciiname":"Sadegaji",
    "gn:country_code":"CN",
    "gn:dem":921,
    "gn:feature_class":"P",
    "gn:feature_code":"PPL",
    "gn:name":"Sadegaji",
    "gn:population":0,
    "gn:timezone":"Asia/Urumqi",
    "iso:country":"CN",
    "name:zho_x_preferred":[
        "\u8428\u5fb7\u560e\u5409"
    ],
    "wof:name":"Sadegaji",
    "wof:placetype":"locality"
},
  "geometry": {"coordinates":[84.8141,40.89172],"type":"Point"}
}