{
  "type": "Feature",
  "properties": {
    "gn:admin1_code":"3.0",
    "gn:asciiname":"Zhuxiqiao",
    "gn:country_code":"CN",
    "gn:dem":44,
    "gn:feature_class":"P",
    "gn:feature_code":"PPL",
    "gn:name":"Zhuxiqiao",
    "gn:population":0,
    "gn:timezone":"Asia/Shanghai",
    "iso:country":"CN",
    "name:und_x_variant":[
        "\u7af9\u6eaa\u6865"
    ],
    "wof:name":"Zhuxiqiao",
    "wof:placetype":"locality"
},
  "geometry": {"coordinates":[115.50158999999999,28.46406],"type":"Point"}
}