{
  "type": "Feature",
  "properties": {
    "gn:admin1_code":"4.0",
    "gn:asciiname":"Banchengcun",
    "gn:country_code":"CN",
    "gn:dem":26,
    "gn:feature_class":"P",
    "gn:feature_code":"PPL",
    "gn:name":"Banchengcun",
    "gn:population":0,
    "gn:timezone":"Asia/Shanghai",
    "iso:country":"CN",
    "name:zho_x_preferred":[
        "\u534a\u57ce\u6751"
    ],
    "wof:name":"Banchengcun",
    "wof:placetype":"locality"
},
  "geometry": {"coordinates":[118.15912,34.31567],"type":"Point"}
}