{
  "type": "Feature",
  "properties": {
    "gn:admin1_code":"9.0",
    "gn:asciiname":"Lianjiesi",
    "gn:country_code":"CN",
    "gn:dem":597,
    "gn:feature_class":"P",
    "gn:feature_code":"PPL",
    "gn:name":"Lianjiesi",
    "gn:population":0,
    "gn:timezone":"Asia/Shanghai",
    "iso:country":"CN",
    "name:zho_x_preferred":[
        "\u8fde\u754c\u5bfa"
    ],
    "wof:name":"Lianjiesi",
    "wof:placetype":"locality"
},
  "geometry": {"coordinates":[113.72615999999999,32.1094],"type":"Point"}
}