{
  "type": "Feature",
  "properties": {
    "gn:admin1_code":"32.0",
    "gn:asciiname":"Bachuan",
    "gn:country_code":"CN",
    "gn:dem":2085,
    "gn:feature_class":"P",
    "gn:feature_code":"PPL",
    "gn:name":"Bachuan",
    "gn:population":0,
    "gn:timezone":"Asia/Shanghai",
    "iso:country":"CN",
    "name:zho_x_preferred":[
        "\u5df4\u5ddd"
    ],
    "wof:name":"Bachuan",
    "wof:placetype":"locality"
},
  "geometry": {"coordinates":[103.69428000000001,31.50735],"type":"Point"}
}