{
  "type": "Feature",
  "properties": {
    "gn:admin1_code":"14.0",
    "gn:asciiname":"Banong",
    "gn:country_code":"CN",
    "gn:dem":3362,
    "gn:feature_class":"P",
    "gn:feature_code":"PPL",
    "gn:name":"Banong",
    "gn:population":0,
    "gn:timezone":"Asia/Urumqi",
    "iso:country":"CN",
    "name:zho_x_preferred":[
        "\u516b\u5f04"
    ],
    "wof:name":"Banong",
    "wof:placetype":"locality"
},
  "geometry": {"coordinates":[96.05244,30.00827],"type":"Point"}
}