{
  "type": "Feature",
  "properties": {
    "gn:admin1_code":"32.0",
    "gn:asciiname":"Zhuanshan",
    "gn:country_code":"CN",
    "gn:dem":1535,
    "gn:feature_class":"P",
    "gn:feature_code":"PPL",
    "gn:name":"Zhuanshan",
    "gn:population":0,
    "gn:timezone":"Asia/Shanghai",
    "iso:country":"CN",
    "name:zho_x_preferred":[
        "\u8f6c\u5c71"
    ],
    "wof:name":"Zhuanshan",
    "wof:placetype":"locality"
},
  "geometry": {"coordinates":[102.15600000000001,27.9076],"type":"Point"}
}