{
  "type": "Feature",
  "properties": {
    "gn:admin1_code":"21.0",
    "gn:asciiname":"Xieluwa",
    "gn:country_code":"CN",
    "gn:dem":2014,
    "gn:feature_class":"P",
    "gn:feature_code":"PPL",
    "gn:name":"Xieluwa",
    "gn:population":0,
    "gn:timezone":"Asia/Shanghai",
    "iso:country":"CN",
    "name:zho_x_preferred":[
        "\u659c\u8def\u5c72"
    ],
    "wof:name":"Xieluwa",
    "wof:placetype":"locality"
},
  "geometry": {"coordinates":[105.833,36.0859],"type":"Point"}
}