{
  "type": "Feature",
  "properties": {
    "gn:admin1_code":"11.0",
    "gn:asciiname":"Debaowan",
    "gn:country_code":"CN",
    "gn:dem":28,
    "gn:feature_class":"P",
    "gn:feature_code":"PPL",
    "gn:name":"Debaowan",
    "gn:population":0,
    "gn:timezone":"Asia/Shanghai",
    "iso:country":"CN",
    "name:zho_x_preferred":[
        "\u5fb7\u5b9d\u6e7e"
    ],
    "wof:name":"Debaowan",
    "wof:placetype":"locality"
},
  "geometry": {"coordinates":[112.65755,28.54246],"type":"Point"}
}