{
  "type": "Feature",
  "properties": {
    "gn:admin1_code":"7.0",
    "gn:asciiname":"Sudi",
    "gn:country_code":"CN",
    "gn:dem":786,
    "gn:feature_class":"P",
    "gn:feature_code":"PPL",
    "gn:name":"Sudi",
    "gn:population":0,
    "gn:timezone":"Asia/Shanghai",
    "iso:country":"CN",
    "name:ceb_x_preferred":[
        "S\u016bdi"
    ],
    "name:deu_x_preferred":[
        "Sudi"
    ],
    "name:hin_x_preferred":[
        "\u0938\u0941\u0926\u0940"
    ],
    "name:kan_x_preferred":[
        "\u0cb8\u0cc2\u0ca1\u0cbf"
    ],
    "name:swe_x_preferred":[
        "S\u016bdi"
    ],
    "name:zho_x_preferred":[
        "\u82cf\u5730"
    ],
    "wof:name":"Sudi",
    "wof:placetype":"locality"
},
  "geometry": {"coordinates":[117.21021,25.75109],"type":"Point"}
}