{
  "type": "Feature",
  "properties": {
    "gn:admin1_code":"1.0",
    "gn:asciiname":"Shihuaita",
    "gn:country_code":"CN",
    "gn:dem":104,
    "gn:feature_class":"P",
    "gn:feature_code":"PPL",
    "gn:name":"Shihuaita",
    "gn:population":0,
    "gn:timezone":"Asia/Shanghai",
    "iso:country":"CN",
    "name:zho_x_preferred":[
        "Shihuaita"
    ],
    "name:zho_x_variant":[
        "\u77f3\u69d0\u5854"
    ],
    "wof:name":"Shihuaita",
    "wof:placetype":"locality"
},
  "geometry": {"coordinates":[119.07487,30.87265],"type":"Point"}
}