{
  "type": "Feature",
  "properties": {
    "gn:admin1_code":"02",
    "gn:asciiname":"Putaokengcun",
    "gn:country_code":"CN",
    "gn:dem":675,
    "gn:feature_class":"P",
    "gn:feature_code":"PPL",
    "gn:name":"Putaokengcun",
    "gn:population":0,
    "gn:timezone":"Asia/Shanghai",
    "iso:country":"CN",
    "name:und_x_variant":[
        "Putaokeng",
        "Putaokengcun"
    ],
    "name:zho_x_preferred":[
        "\u8461\u8404\u5751"
    ],
    "name:zho_x_variant":[
        "\u8461\u8404\u5751\u6751"
    ],
    "wof:name":"Putaokengcun",
    "wof:placetype":"locality"
},
  "geometry": {"coordinates":[120.91146999999999,28.51793],"type":"Point"}
}