{
  "type": "Feature",
  "properties": {
    "gn:admin1_code":"7.0",
    "gn:asciiname":"Wangshankou",
    "gn:country_code":"CN",
    "gn:dem":177,
    "gn:feature_class":"P",
    "gn:feature_code":"PPL",
    "gn:name":"Wangshankou",
    "gn:population":0,
    "gn:timezone":"Asia/Shanghai",
    "iso:country":"CN",
    "name:zho_x_preferred":[
        "\u738b\u5c71\u53e3"
    ],
    "wof:name":"Wangshankou",
    "wof:placetype":"locality"
},
  "geometry": {"coordinates":[118.73116,27.34352],"type":"Point"}
}