{
  "type": "Feature",
  "properties": {
    "gn:admin1_code":"24.0",
    "gn:asciiname":"Luotuancun",
    "gn:country_code":"CN",
    "gn:dem":1067,
    "gn:feature_class":"P",
    "gn:feature_code":"PPL",
    "gn:name":"Luotuancun",
    "gn:population":0,
    "gn:timezone":"Asia/Shanghai",
    "iso:country":"CN",
    "name:zho_x_preferred":[
        "\u7f57\u7583\u6751"
    ],
    "wof:name":"Luotuancun",
    "wof:placetype":"locality"
},
  "geometry": {"coordinates":[114.38141,39.85394],"type":"Point"}
}