{
  "type": "Feature",
  "properties": {
    "iso:country":"CN",
    "name:ara_x_preferred":[
        "\u0645\u0646\u062a\u0648\u0642\u0648"
    ],
    "name:cat_x_preferred":[
        "Mentougou"
    ],
    "name:ceb_x_preferred":[
        "Mentougou Qu"
    ],
    "name:ces_x_preferred":[
        "Men-tchou-kou"
    ],
    "name:cym_x_preferred":[
        "Ardal Mentougou"
    ],
    "name:deu_x_preferred":[
        "Mentougou"
    ],
    "name:eng_x_preferred":[
        "Mentougou District"
    ],
    "name:eus_x_preferred":[
        "Mentougou Barrutia"
    ],
    "name:fas_x_preferred":[
        "\u0645\u0646\u062a\u0648\u06af\u0648"
    ],
    "name:gan_x_preferred":[
        "\u95e8\u5934\u6c9f\u533a"
    ],
    "name:ind_x_preferred":[
        "Distrik Mentougou"
    ],
    "name:jpn_x_preferred":[
        "\u9580\u982d\u6e9d\u533a"
    ],
    "name:kor_x_preferred":[
        "\uba3c\ud130\uc6b0\uac70\uc6b0\uad6c"
    ],
    "name:mwl_x_preferred":[
        "Mentougou"
    ],
    "name:nan_x_preferred":[
        "B\u00fbn-th\u00e2u-kau-khu"
    ],
    "name:nld_x_preferred":[
        "Mentougou-district"
    ],
    "name:nob_x_preferred":[
        "Mentougou"
    ],
    "name:pol_x_preferred":[
        "Mentougou"
    ],
    "name:rus_x_preferred":[
        "\u041c\u044d\u043d\u044c\u0442\u043e\u0443\u0433\u043e\u0443"
    ],
    "name:spa_x_preferred":[
        "Mentougou"
    ],
    "name:srp_x_preferred":[
        "\u041c\u0435\u043d\u0442\u043e\u0443\u0433\u043e\u0443"
    ],
    "name:swe_x_preferred":[
        "Mentougou"
    ],
    "name:tur_x_preferred":[
        "Mentougou"
    ],
    "name:urd_x_preferred":[
        "\u0645\u06cc\u0646\u062a\u0624\u06af\u0624 \u0636\u0644\u0639"
    ],
    "name:wuu_x_preferred":[
        "\u95e8\u5934\u6c9f\u533a"
    ],
    "name:yue_x_preferred":[
        "\u9580\u982d\u6e9d\u5340"
    ],
    "name:zho_x_preferred":[
        "\u95e8\u5934\u6c9f\u533a"
    ],
    "qs:name":"\u95e8\u5934\u6c9f\u533a",
    "qs:name_adm0":"\u4e2d\u570b",
    "qs:name_adm1":"\u5317\u4eac\u76f4\u8f96\u5e02",
    "qs:photos":1,
    "qs:photos_1k":1,
    "qs:photos_9k":4,
    "qs:photos_9r":6,
    "qs:photos_all":846,
    "qs:photos_sr":1,
    "qs:placetype":"LocalAdmin",
    "qs:pop_sr":"0",
    "wd:wordcount":446,
    "wof:name":"\u95e8\u5934\u6c9f\u533a",
    "wof:placetype":"localadmin"
},
  "geometry": {"coordinates":[116.076049,39.93795],"type":"Point"}
}