{
  "type": "Feature",
  "properties": {
    "iso:country":"CN",
    "qs:name":"\u95e8\u5934\u6c9f\u533a",
    "qs:name_adm0":"\u4e2d\u570b",
    "qs:name_adm1":"\u5317\u4eac\u76f4\u8f96\u5e02",
    "qs:photos":1,
    "qs:photos_1k":1,
    "qs:photos_9k":4,
    "qs:photos_9r":6,
    "qs:photos_all":846,
    "qs:photos_sr":1,
    "qs:placetype":"LocalAdmin",
    "qs:pop_sr":"0",
    "wd:wordcount":446,
    "wof:name":"\u95e8\u5934\u6c9f\u533a",
    "wof:placetype":"localadmin"
},
  "geometry": {"coordinates":[116.076049,39.93795],"type":"Point"}
}