{
  "type": "Feature",
  "properties": {
    "gn:admin1_code":"15.0",
    "gn:asciiname":"Yayao",
    "gn:country_code":"CN",
    "gn:dem":2267,
    "gn:feature_class":"P",
    "gn:feature_code":"PPL",
    "gn:name":"Yayao",
    "gn:population":0,
    "gn:timezone":"Asia/Shanghai",
    "iso:country":"CN",
    "name:zho_x_preferred":[
        "\u538b\u8170"
    ],
    "wof:name":"Yayao",
    "wof:placetype":"locality"
},
  "geometry": {"coordinates":[101.651,38.3034],"type":"Point"}
}