{
  "type": "Feature",
  "properties": {
    "gn:admin1_code":"1.0",
    "gn:asciiname":"Dingyingcun",
    "gn:country_code":"CN",
    "gn:dem":27,
    "gn:feature_class":"P",
    "gn:feature_code":"PPL",
    "gn:name":"Dingyingcun",
    "gn:population":0,
    "gn:timezone":"Asia/Shanghai",
    "iso:country":"CN",
    "name:zho_x_preferred":[
        "\u4e01\u90e2\u6751"
    ],
    "wof:name":"Dingyingcun",
    "wof:placetype":"locality"
},
  "geometry": {"coordinates":[116.89632,32.67743],"type":"Point"}
}