{
  "type": "Feature",
  "properties": {
    "gn:admin1_code":"11.0",
    "gn:asciiname":"Weiziwan",
    "gn:country_code":"CN",
    "gn:dem":126,
    "gn:feature_class":"P",
    "gn:feature_code":"PPL",
    "gn:name":"Weiziwan",
    "gn:population":0,
    "gn:timezone":"Asia/Shanghai",
    "iso:country":"CN",
    "name:zho_x_preferred":[
        "\u6845\u5b50\u6e7e"
    ],
    "wof:name":"Weiziwan",
    "wof:placetype":"locality"
},
  "geometry": {"coordinates":[112.62815999999999,27.32845],"type":"Point"}
}