{
  "type": "Feature",
  "properties": {
    "gn:admin1_code":"32.0",
    "gn:asciiname":"Tianma",
    "gn:country_code":"CN",
    "gn:dem":541,
    "gn:feature_class":"P",
    "gn:feature_code":"PPL",
    "gn:name":"Tianma",
    "gn:population":0,
    "gn:timezone":"Asia/Shanghai",
    "iso:country":"CN",
    "name:deu_x_preferred":[
        "Tianma"
    ],
    "name:fra_x_preferred":[
        "Tianma"
    ],
    "name:por_x_preferred":[
        "Tianma"
    ],
    "name:zho_x_preferred":[
        "\u5929\u9ebb"
    ],
    "wof:name":"Tianma",
    "wof:placetype":"locality"
},
  "geometry": {"coordinates":[104.41500000000001,31.3114],"type":"Point"}
}