{
  "type": "Feature",
  "properties": {
    "gn:admin1_code":"19.0",
    "gn:asciiname":"Daganggang",
    "gn:country_code":"CN",
    "gn:dem":185,
    "gn:feature_class":"P",
    "gn:feature_code":"PPL",
    "gn:name":"Daganggang",
    "gn:population":0,
    "gn:timezone":"Asia/Shanghai",
    "iso:country":"CN",
    "name:zho_x_preferred":[
        "\u5927\u5c97\u5c97"
    ],
    "wof:name":"Daganggang",
    "wof:placetype":"locality"
},
  "geometry": {"coordinates":[121.83790999999999,42.08095],"type":"Point"}
}