{
  "type": "Feature",
  "properties": {
    "gn:country":"CN",
    "gn:fcode":"PPL",
    "gn:pop":74139,
    "iso:country":"CN",
    "name:rus_x_preferred":[
        "\u0421\u0438\u043d\u044c\u043c\u0438\u043d\u044c"
    ],
    "name:unk_x_variant":[
        "Sinmin"
    ],
    "qs:name":"Xinmin",
    "qs:photos_9r":0,
    "qs:photos_sr":0,
    "qs:pop_sr":"8",
    "wd:wordcount":224,
    "wof:name":"Xinmin",
    "wof:placetype":"locality",
    "wof:population":74139
},
  "geometry": {"coordinates":[122.82528000000001,41.99083],"type":"Point"}
}