{
  "type": "Feature",
  "properties": {
    "gn:admin1_code":"12.0",
    "gn:asciiname":"Zhangchao",
    "gn:country_code":"CN",
    "gn:dem":181,
    "gn:feature_class":"P",
    "gn:feature_code":"PPL",
    "gn:name":"Zhangchao",
    "gn:population":0,
    "gn:timezone":"Asia/Shanghai",
    "iso:country":"CN",
    "name:zho_x_preferred":[
        "Zhangchao"
    ],
    "name:zho_x_variant":[
        "\u5f20\u671d"
    ],
    "wof:name":"Zhangchao",
    "wof:placetype":"locality"
},
  "geometry": {"coordinates":[114.2864,29.42034],"type":"Point"}
}