{
  "type": "Feature",
  "properties": {
    "iso:country":"CN",
    "qs:name":"\u4fe1\u9633",
    "qs:name_adm0":"\u4e2d\u570b",
    "qs:name_adm1":"\u6cb3\u5357\u7701",
    "qs:photos":2,
    "qs:photos_1k":1,
    "qs:photos_9k":1,
    "qs:photos_9r":2,
    "qs:photos_all":46,
    "qs:photos_sr":1,
    "qs:placetype":"LocalAdmin",
    "qs:pop_sr":"0",
    "wof:name":"\u4fe1\u9633",
    "wof:placetype":"localadmin"
},
  "geometry": {"coordinates":[114.066667,32.122127],"type":"Point"}
}