{
  "type": "Feature",
  "properties": {
    "gn:admin1_code":"8.0",
    "gn:asciiname":"Jidi Fangzi",
    "gn:country_code":"CN",
    "gn:dem":143,
    "gn:feature_class":"P",
    "gn:feature_code":"PPL",
    "gn:name":"Jidi Fangzi",
    "gn:population":0,
    "gn:timezone":"Asia/Shanghai",
    "iso:country":"CN",
    "name:zho_x_preferred":[
        "\u7eaa\u5730\u623f\u5b50"
    ],
    "wof:name":"Jidi Fangzi",
    "wof:placetype":"locality"
},
  "geometry": {"coordinates":[123.75194999999999,47.02892],"type":"Point"}
}