{
  "type": "Feature",
  "properties": {
    "gn:admin1_code":"30",
    "gn:asciiname":"Shiling",
    "gn:country_code":"CN",
    "gn:dem":36,
    "gn:feature_class":"P",
    "gn:feature_code":"PPL",
    "gn:name":"Shiling",
    "gn:population":0,
    "gn:timezone":"Asia/Urumqi",
    "iso:country":"CN",
    "name:zho_x_preferred":[
        "\u77f3\u5cad"
    ],
    "wof:name":"Shiling",
    "wof:placetype":"locality"
},
  "geometry": {"coordinates":[110.44871999999999,21.8095],"type":"Point"}
}