{
  "type": "Feature",
  "properties": {
    "gn:admin1_code":"7.0",
    "gn:asciiname":"Zhixi",
    "gn:country_code":"CN",
    "gn:dem":23,
    "gn:feature_class":"P",
    "gn:feature_code":"PPL",
    "gn:name":"Zhixi",
    "gn:population":0,
    "gn:timezone":"Asia/Shanghai",
    "iso:country":"CN",
    "name:zho_x_preferred":[
        "\u96c9\u6eaa"
    ],
    "wof:name":"Zhixi",
    "wof:placetype":"locality"
},
  "geometry": {"coordinates":[120.12641000000001,26.98443],"type":"Point"}
}