{
  "type": "Feature",
  "properties": {
    "gn:admin1_code":"2",
    "gn:asciiname":"Huangwu",
    "gn:country_code":"CN",
    "gn:dem":90,
    "gn:feature_class":"P",
    "gn:feature_code":"PPLA4",
    "gn:name":"Huangwu",
    "gn:population":0,
    "gn:timezone":"Asia/Shanghai",
    "iso:country":"CN",
    "name:und_x_variant":[
        "Sanhe Zhen",
        "Sanhe",
        "Huangwu",
        "\u4e09\u5408\u9547"
    ],
    "name:zho_x_preferred":[
        "\u9ec4\u52a1"
    ],
    "name:zho_x_variant":[
        "\u4e09\u5408\u9547"
    ],
    "wof:name":"Huangwu",
    "wof:placetype":"locality"
},
  "geometry": {"coordinates":[121.1661,29.08454],"type":"Point"}
}