{
  "type": "Feature",
  "properties": {
    "gn:admin1_code":"5.0",
    "gn:asciiname":"Jinbaoshancun",
    "gn:country_code":"CN",
    "gn:dem":214,
    "gn:feature_class":"P",
    "gn:feature_code":"PPL",
    "gn:name":"Jinbaoshancun",
    "gn:population":0,
    "gn:timezone":"Asia/Shanghai",
    "iso:country":"CN",
    "name:zho_x_preferred":[
        "\u91d1\u5b9d\u5c71\u6751"
    ],
    "wof:name":"Jinbaoshancun",
    "wof:placetype":"locality"
},
  "geometry": {"coordinates":[124.51148000000001,44.41359],"type":"Point"}
}