{
  "type": "Feature",
  "properties": {
    "gn:admin1_code":"14.0",
    "gn:asciiname":"Yurugangcun",
    "gn:country_code":"CN",
    "gn:dem":3927,
    "gn:feature_class":"P",
    "gn:feature_code":"PPL",
    "gn:name":"Yurugangcun",
    "gn:population":0,
    "gn:timezone":"Asia/Urumqi",
    "iso:country":"CN",
    "name:zho_x_preferred":[
        "\u7389\u5982\u5c97\u6751"
    ],
    "wof:name":"Yurugangcun",
    "wof:placetype":"locality"
},
  "geometry": {"coordinates":[92.87542000000001,28.92768],"type":"Point"}
}