{
  "type": "Feature",
  "properties": {
    "gn:admin1_code":"26.0",
    "gn:asciiname":"Nianzikan",
    "gn:country_code":"CN",
    "gn:dem":686,
    "gn:feature_class":"P",
    "gn:feature_code":"PPL",
    "gn:name":"Nianzikan",
    "gn:population":0,
    "gn:timezone":"Asia/Shanghai",
    "iso:country":"CN",
    "name:und_x_variant":[
        "\u5e74\u5b50\u574e"
    ],
    "wof:name":"Nianzikan",
    "wof:placetype":"locality"
},
  "geometry": {"coordinates":[106.37275,33.0532],"type":"Point"}
}