{
  "type": "Feature",
  "properties": {
    "gn:admin1_code":"04",
    "gn:asciiname":"Jiulicun",
    "gn:country_code":"CN",
    "gn:dem":8,
    "gn:feature_class":"P",
    "gn:feature_code":"PPL",
    "gn:name":"Jiulicun",
    "gn:population":0,
    "gn:timezone":"Asia/Shanghai",
    "iso:country":"CN",
    "name:und_x_variant":[
        "Chiu-li",
        "Jiulizhen",
        "Chiu-li-p\u2019u",
        "Chiu-li-chen",
        "Jiuli",
        "Jiulicun"
    ],
    "name:zho_x_preferred":[
        "\u4e5d\u91cc"
    ],
    "name:zho_x_variant":[
        "\u4e5d\u91cc\u6751"
    ],
    "wof:name":"Jiulicun",
    "wof:placetype":"locality"
},
  "geometry": {"coordinates":[119.43908999999999,31.89209],"type":"Point"}
}