{
  "type": "Feature",
  "properties": {
    "gn:admin1_code":"23.0",
    "gn:asciiname":"Panjiabang",
    "gn:country_code":"CN",
    "gn:dem":5,
    "gn:feature_class":"P",
    "gn:feature_code":"PPL",
    "gn:name":"Panjiabang",
    "gn:population":0,
    "gn:timezone":"Asia/Shanghai",
    "iso:country":"CN",
    "name:und_x_variant":[
        "\u6f58\u5bb6\u6d5c"
    ],
    "wof:name":"Panjiabang",
    "wof:placetype":"locality"
},
  "geometry": {"coordinates":[121.32673,31.07522],"type":"Point"}
}