{
  "type": "Feature",
  "properties": {
    "gn:admin1_code":"33.0",
    "gn:asciiname":"Yingfeng",
    "gn:country_code":"CN",
    "gn:dem":753,
    "gn:feature_class":"P",
    "gn:feature_code":"PPL",
    "gn:name":"Yingfeng",
    "gn:population":0,
    "gn:timezone":"Asia/Shanghai",
    "iso:country":"CN",
    "name:zho_x_preferred":[
        "\u8fce\u98ce"
    ],
    "wof:name":"Yingfeng",
    "wof:placetype":"locality"
},
  "geometry": {"coordinates":[108.39906999999999,30.50398],"type":"Point"}
}