{
  "type": "Feature",
  "properties": {
    "gn:admin1_code":"32.0",
    "gn:asciiname":"Menghuo",
    "gn:country_code":"CN",
    "gn:dem":2569,
    "gn:feature_class":"P",
    "gn:feature_code":"PPL",
    "gn:name":"Menghuo",
    "gn:population":0,
    "gn:timezone":"Asia/Shanghai",
    "iso:country":"CN",
    "name:zho_x_preferred":[
        "\u5b5f\u83b7"
    ],
    "wof:name":"Menghuo",
    "wof:placetype":"locality"
},
  "geometry": {"coordinates":[102.34099999999999,28.9073],"type":"Point"}
}