{
  "type": "Feature",
  "properties": {
    "gn:admin1_code":"2.0",
    "gn:asciiname":"Zhang'ercun",
    "gn:country_code":"CN",
    "gn:dem":42,
    "gn:feature_class":"P",
    "gn:feature_code":"PPL",
    "gn:name":"Zhang\u2019ercun",
    "gn:population":0,
    "gn:timezone":"Asia/Shanghai",
    "iso:country":"CN",
    "name:und_x_variant":[
        "Zhang\u2019ercun"
    ],
    "name:zho_x_preferred":[
        "\u6a1f\u4e8c\u6751"
    ],
    "wof:name":"Zhang'ercun",
    "wof:placetype":"locality"
},
  "geometry": {"coordinates":[119.3524,29.21163],"type":"Point"}
}