{
  "type": "Feature",
  "properties": {
    "gn:admin1_code":"29.0",
    "gn:asciiname":"Heitutian",
    "gn:country_code":"CN",
    "gn:dem":1394,
    "gn:feature_class":"P",
    "gn:feature_code":"PPL",
    "gn:name":"Heitutian",
    "gn:population":0,
    "gn:timezone":"Asia/Shanghai",
    "iso:country":"CN",
    "name:zho_x_preferred":[
        "\u9ed1\u571f\u7530"
    ],
    "wof:name":"Heitutian",
    "wof:placetype":"locality"
},
  "geometry": {"coordinates":[98.9408,25.254],"type":"Point"}
}