{
  "type": "Feature",
  "properties": {
    "gn:admin1_code":"16",
    "gn:asciiname":"Dengjiawan",
    "gn:country_code":"CN",
    "gn:dem":935,
    "gn:feature_class":"P",
    "gn:feature_code":"PPL",
    "gn:name":"Dengjiawan",
    "gn:population":0,
    "gn:timezone":"Asia/Shanghai",
    "iso:country":"CN",
    "name:zho_x_preferred":[
        "\u9093\u5bb6\u6e7e"
    ],
    "wof:name":"Dengjiawan",
    "wof:placetype":"locality"
},
  "geometry": {"coordinates":[109.959,25.5411],"type":"Point"}
}