{
  "type": "Feature",
  "properties": {
    "gn:admin1_code":"32.0",
    "gn:asciiname":"Erlang",
    "gn:country_code":"CN",
    "gn:dem":629,
    "gn:feature_class":"P",
    "gn:feature_code":"PPL",
    "gn:name":"Erlang",
    "gn:population":0,
    "gn:timezone":"Asia/Shanghai",
    "iso:country":"CN",
    "name:zho_x_preferred":[
        "\u4e8c\u90ce"
    ],
    "wof:name":"Erlang",
    "wof:placetype":"locality"
},
  "geometry": {"coordinates":[106.685,31.2662],"type":"Point"}
}