{
  "type": "Feature",
  "properties": {
    "gn:admin1_code":"1.0",
    "gn:asciiname":"Gupeicun",
    "gn:country_code":"CN",
    "gn:dem":31,
    "gn:feature_class":"P",
    "gn:feature_code":"PPL",
    "gn:name":"Gupeicun",
    "gn:population":0,
    "gn:timezone":"Asia/Shanghai",
    "iso:country":"CN",
    "name:zho_x_preferred":[
        "\u53e4\u6c9b\u6751"
    ],
    "wof:name":"Gupeicun",
    "wof:placetype":"locality"
},
  "geometry": {"coordinates":[117.99823000000001,32.99225],"type":"Point"}
}