{
  "type": "Feature",
  "properties": {
    "gn:admin1_code":"29.0",
    "gn:asciiname":"Tudui Xiaozhai",
    "gn:country_code":"CN",
    "gn:dem":1597,
    "gn:feature_class":"P",
    "gn:feature_code":"PPL",
    "gn:name":"Tudui Xiaozhai",
    "gn:population":0,
    "gn:timezone":"Asia/Shanghai",
    "iso:country":"CN",
    "name:zho_x_preferred":[
        "\u571f\u5806\u5c0f\u5be8"
    ],
    "wof:name":"Tudui Xiaozhai",
    "wof:placetype":"locality"
},
  "geometry": {"coordinates":[101.82899999999999,23.3428],"type":"Point"}
}