{
  "type": "Feature",
  "properties": {
    "gn:admin1_code":"02",
    "gn:asciiname":"Jishan",
    "gn:cc2":"CN",
    "gn:country_code":"CN",
    "gn:dem":11,
    "gn:feature_class":"P",
    "gn:feature_code":"PPL",
    "gn:name":"Jishan",
    "gn:population":0,
    "gn:timezone":"Asia/Shanghai",
    "iso:country":"CN",
    "name:und_x_variant":[
        "Chi-shan-hsia-ts\u2019un",
        "Jishan",
        "\u7578\u5c71"
    ],
    "name:zho_x_preferred":[
        "\u7578\u5c71"
    ],
    "wof:name":"Jishan",
    "wof:placetype":"locality"
},
  "geometry": {"coordinates":[121.31083,29.6925],"type":"Point"}
}