{
  "type": "Feature",
  "properties": {
    "gn:admin1_code":"7.0",
    "gn:asciiname":"Xinsheng",
    "gn:country_code":"CN",
    "gn:dem":389,
    "gn:feature_class":"P",
    "gn:feature_code":"PPL",
    "gn:name":"Xinsheng",
    "gn:population":0,
    "gn:timezone":"Asia/Shanghai",
    "iso:country":"CN",
    "name:zho_x_preferred":[
        "\u65b0\u751f"
    ],
    "wof:name":"Xinsheng",
    "wof:placetype":"locality"
},
  "geometry": {"coordinates":[116.72657,25.28486],"type":"Point"}
}