{
  "type": "Feature",
  "properties": {
    "gn:admin1_code":"11.0",
    "gn:asciiname":"Xin'aisi",
    "gn:country_code":"CN",
    "gn:dem":144,
    "gn:feature_class":"P",
    "gn:feature_code":"PPL",
    "gn:name":"Xin\u2019aisi",
    "gn:population":0,
    "gn:timezone":"Asia/Shanghai",
    "iso:country":"CN",
    "name:und_x_variant":[
        "Xin\u2019aisi",
        "Xin\u2019aizi"
    ],
    "name:zho_x_preferred":[
        "\u65b0\u57c3\u5bfa"
    ],
    "wof:name":"Xin'aisi",
    "wof:placetype":"locality"
},
  "geometry": {"coordinates":[113.94668,28.85261],"type":"Point"}
}