{
  "type": "Feature",
  "properties": {
    "gn:admin1_code":"29",
    "gn:asciiname":"Paiting",
    "gn:country_code":"CN",
    "gn:dem":1167,
    "gn:feature_class":"P",
    "gn:feature_code":"PPL",
    "gn:name":"Paiting",
    "gn:population":0,
    "gn:timezone":"Asia/Shanghai",
    "iso:country":"CN",
    "name:zho_x_preferred":[
        "\u6d3e\u542c"
    ],
    "wof:name":"Paiting",
    "wof:placetype":"locality"
},
  "geometry": {"coordinates":[104.91500000000001,23.9974],"type":"Point"}
}