{
  "type": "Feature",
  "properties": {
    "gn:admin1_code":"29",
    "gn:asciiname":"Paiting",
    "gn:country_code":"CN",
    "gn:dem":1167,
    "gn:feature_class":"P",
    "gn:feature_code":"PPL",
    "gn:name":"Paiting",
    "gn:population":0,
    "gn:timezone":"Asia/Shanghai",
    "iso:country":"CN",
    "name:ast_x_preferred":[
        "Paiting"
    ],
    "name:kor_x_preferred":[
        "\ud30c\uc774\ud305"
    ],
    "name:spa_x_preferred":[
        "Paiting"
    ],
    "name:tha_x_preferred":[
        "\u0e44\u0e1f\u0e17\u0e4c\u0e15\u0e34\u0e49\u0e07!"
    ],
    "name:zho_x_preferred":[
        "\u6d3e\u542c"
    ],
    "wof:name":"Paiting",
    "wof:placetype":"locality"
},
  "geometry": {"coordinates":[104.91500000000001,23.9974],"type":"Point"}
}