{
  "type": "Feature",
  "properties": {
    "gn:admin1_code":"32.0",
    "gn:asciiname":"Xiangyangping",
    "gn:country_code":"CN",
    "gn:dem":1275,
    "gn:feature_class":"P",
    "gn:feature_code":"PPL",
    "gn:name":"Xiangyangping",
    "gn:population":0,
    "gn:timezone":"Asia/Shanghai",
    "iso:country":"CN",
    "name:zho_x_preferred":[
        "\u5411\u9633\u576a"
    ],
    "wof:name":"Xiangyangping",
    "wof:placetype":"locality"
},
  "geometry": {"coordinates":[105.83328,28.27207000000001],"type":"Point"}
}