{
  "type": "Feature",
  "properties": {
    "gn:admin1_code":"30.0",
    "gn:asciiname":"Zhugendu",
    "gn:country_code":"CN",
    "gn:dem":190,
    "gn:feature_class":"P",
    "gn:feature_code":"PPL",
    "gn:name":"Zhugendu",
    "gn:population":0,
    "gn:timezone":"Asia/Shanghai",
    "iso:country":"CN",
    "name:zho_x_preferred":[
        "\u7af9\u6839\u809a"
    ],
    "wof:name":"Zhugendu",
    "wof:placetype":"locality"
},
  "geometry": {"coordinates":[111.87177,23.71466],"type":"Point"}
}