{
  "type": "Feature",
  "properties": {
    "iso:country":"CN",
    "name:ceb_x_preferred":[
        "Pi Xian"
    ],
    "name:ces_x_preferred":[
        "Pchi"
    ],
    "name:cym_x_preferred":[
        "Ardal Pidu"
    ],
    "name:deu_x_preferred":[
        "Pi"
    ],
    "name:deu_x_variant":[
        "Pidu"
    ],
    "name:eng_x_preferred":[
        "Pidu District"
    ],
    "name:eus_x_preferred":[
        "Pi konderria"
    ],
    "name:fas_x_preferred":[
        "\u067e\u06cc \u06a9\u0627\u0646\u062a\u06cc"
    ],
    "name:fin_x_preferred":[
        "Pidu"
    ],
    "name:gan_x_preferred":[
        "\u90eb\u90fd\u533a"
    ],
    "name:hak_x_preferred":[
        "Ph\u00ee-yen"
    ],
    "name:ind_x_preferred":[
        "Distrik Pidu"
    ],
    "name:jpn_x_preferred":[
        "\u30d2\u770c"
    ],
    "name:jpn_x_variant":[
        "\u90eb\u90fd\u533a"
    ],
    "name:kor_x_preferred":[
        "\ud53c\ub450 \uad6c"
    ],
    "name:kor_x_variant":[
        "\ud53c\ub450\uad6c"
    ],
    "name:nan_x_preferred":[
        "P\u00ec-to\u0358-khu"
    ],
    "name:nld_x_preferred":[
        "Pi"
    ],
    "name:nld_x_variant":[
        "Pidu"
    ],
    "name:nob_x_preferred":[
        "Pi"
    ],
    "name:nob_x_variant":[
        "Pidu"
    ],
    "name:rus_x_preferred":[
        "\u041f\u0438\u0434\u0443"
    ],
    "name:spa_x_preferred":[
        "Pidu"
    ],
    "name:swe_x_preferred":[
        "Pi"
    ],
    "name:tur_x_preferred":[
        "Pidu"
    ],
    "name:vie_x_preferred":[
        "B\u00ec"
    ],
    "name:wuu_x_preferred":[
        "\u90eb\u90fd\u533a"
    ],
    "name:zho_x_preferred":[
        "\u90eb\u90fd\u533a"
    ],
    "qs:name":"\u90eb\u53bf",
    "qs:name_adm0":"\u4e2d\u570b",
    "qs:name_adm1":"\u56db\u5ddd\u7701",
    "qs:photos":16,
    "qs:photos_1k":3,
    "qs:photos_9k":1,
    "qs:photos_9r":3,
    "qs:photos_all":91,
    "qs:photos_sr":1,
    "qs:placetype":"LocalAdmin",
    "qs:pop_sr":"0",
    "wd:wordcount":284,
    "wof:name":"\u90eb\u53bf",
    "wof:placetype":"localadmin"
},
  "geometry": {"coordinates":[103.95418100000001,30.746709],"type":"Point"}
}