{
  "type": "Feature",
  "properties": {
    "iso:country":"CN",
    "qs:name":"\u90eb\u53bf",
    "qs:name_adm0":"\u4e2d\u570b",
    "qs:name_adm1":"\u56db\u5ddd\u7701",
    "qs:photos":16,
    "qs:photos_1k":3,
    "qs:photos_9k":1,
    "qs:photos_9r":3,
    "qs:photos_all":91,
    "qs:photos_sr":1,
    "qs:placetype":"LocalAdmin",
    "qs:pop_sr":"0",
    "wd:wordcount":284,
    "wof:name":"\u90eb\u53bf",
    "wof:placetype":"localadmin"
},
  "geometry": {"coordinates":[103.95418100000001,30.746709],"type":"Point"}
}