{
  "type": "Feature",
  "properties": {
    "gn:admin1_code":"24.0",
    "gn:asciiname":"Xiayingbucun",
    "gn:country_code":"CN",
    "gn:dem":1192,
    "gn:feature_class":"P",
    "gn:feature_code":"PPL",
    "gn:name":"Xiayingbucun",
    "gn:population":0,
    "gn:timezone":"Asia/Shanghai",
    "iso:country":"CN",
    "name:zho_x_preferred":[
        "\u4e0b\u8425\u5821\u6751"
    ],
    "wof:name":"Xiayingbucun",
    "wof:placetype":"locality"
},
  "geometry": {"coordinates":[114.22018,40.40896],"type":"Point"}
}