{
  "type": "Feature",
  "properties": {
    "gn:admin1_code":"2.0",
    "gn:asciiname":"Wukou",
    "gn:country_code":"CN",
    "gn:dem":204,
    "gn:feature_class":"P",
    "gn:feature_code":"PPL",
    "gn:name":"Wukou",
    "gn:population":0,
    "gn:timezone":"Asia/Shanghai",
    "iso:country":"CN",
    "name:zho_x_preferred":[
        "\u575e\u53e3"
    ],
    "wof:name":"Wukou",
    "wof:placetype":"locality"
},
  "geometry": {"coordinates":[118.85006,29.16172000000001],"type":"Point"}
}