{
  "type": "Feature",
  "properties": {
    "gn:admin1_code":"19.0",
    "gn:asciiname":"Xiaxianyucun",
    "gn:country_code":"CN",
    "gn:dem":208,
    "gn:feature_class":"P",
    "gn:feature_code":"PPL",
    "gn:name":"Xiaxianyucun",
    "gn:population":0,
    "gn:timezone":"Asia/Shanghai",
    "iso:country":"CN",
    "name:zho_x_preferred":[
        "\u4e0b\u4ed9\u5cea\u6751"
    ],
    "wof:name":"Xiaxianyucun",
    "wof:placetype":"locality"
},
  "geometry": {"coordinates":[122.8231,40.41933],"type":"Point"}
}