{
  "type": "Feature",
  "properties": {
    "gn:admin1_code":"24.0",
    "gn:asciiname":"Shachang",
    "gn:country_code":"CN",
    "gn:dem":1199,
    "gn:feature_class":"P",
    "gn:feature_code":"PPL",
    "gn:name":"Shachang",
    "gn:population":0,
    "gn:timezone":"Asia/Shanghai",
    "iso:country":"CN",
    "name:zho_x_preferred":[
        "\u6c99\u573a"
    ],
    "wof:name":"Shachang",
    "wof:placetype":"locality"
},
  "geometry": {"coordinates":[113.49039999999999,35.78878],"type":"Point"}
}