{
  "type": "Feature",
  "properties": {
    "gn:admin1_code":"4.0",
    "gn:asciiname":"Huanglongcun",
    "gn:country_code":"CN",
    "gn:dem":19,
    "gn:feature_class":"P",
    "gn:feature_code":"PPL",
    "gn:name":"Huanglongcun",
    "gn:population":0,
    "gn:timezone":"Asia/Shanghai",
    "iso:country":"CN",
    "name:zho_x_preferred":[
        "\u9ec4\u9f99\u6751"
    ],
    "wof:name":"Huanglongcun",
    "wof:placetype":"locality"
},
  "geometry": {"coordinates":[118.42632999999999,32.95227],"type":"Point"}
}