{
  "type": "Feature",
  "properties": {
    "gn:admin1_code":"26.0",
    "gn:asciiname":"Qiaoyugou",
    "gn:country_code":"CN",
    "gn:dem":1198,
    "gn:feature_class":"P",
    "gn:feature_code":"PPL",
    "gn:name":"Qiaoyugou",
    "gn:population":0,
    "gn:timezone":"Asia/Shanghai",
    "iso:country":"CN",
    "name:zho_x_preferred":[
        "\u6865\u6986\u6c9f"
    ],
    "wof:name":"Qiaoyugou",
    "wof:placetype":"locality"
},
  "geometry": {"coordinates":[109.98522,35.93049],"type":"Point"}
}