{
  "type": "Feature",
  "properties": {
    "gn:admin1_code":"24.0",
    "gn:asciiname":"Maozhuang",
    "gn:country_code":"CN",
    "gn:dem":551,
    "gn:feature_class":"P",
    "gn:feature_code":"PPL",
    "gn:name":"Maozhuang",
    "gn:population":0,
    "gn:timezone":"Asia/Shanghai",
    "iso:country":"CN",
    "name:zho_x_preferred":[
        "\u6bdb\u5e84"
    ],
    "wof:name":"Maozhuang",
    "wof:placetype":"locality"
},
  "geometry": {"coordinates":[111.15191000000002,34.86872],"type":"Point"}
}