{
  "type": "Feature",
  "properties": {
    "gn:admin1_code":"14.0",
    "gn:asciiname":"Cuoguocun",
    "gn:country_code":"CN",
    "gn:dem":4819,
    "gn:feature_class":"P",
    "gn:feature_code":"PPL",
    "gn:name":"Cuoguocun",
    "gn:population":0,
    "gn:timezone":"Asia/Urumqi",
    "iso:country":"CN",
    "name:zho_x_preferred":[
        "\u9519\u679c\u6751"
    ],
    "wof:name":"Cuoguocun",
    "wof:placetype":"locality"
},
  "geometry": {"coordinates":[92.65819,30.49615],"type":"Point"}
}