{
  "type": "Feature",
  "properties": {
    "gn:admin1_code":"12.0",
    "gn:asciiname":"Yuanziwan",
    "gn:country_code":"CN",
    "gn:dem":76,
    "gn:feature_class":"P",
    "gn:feature_code":"PPL",
    "gn:name":"Yuanziwan",
    "gn:population":0,
    "gn:timezone":"Asia/Shanghai",
    "iso:country":"CN",
    "name:zho_x_preferred":[
        "\u9662\u5b50\u6e7e"
    ],
    "wof:name":"Yuanziwan",
    "wof:placetype":"locality"
},
  "geometry": {"coordinates":[113.88003999999999,31.57001],"type":"Point"}
}