{
  "type": "Feature",
  "properties": {
    "gn:admin1_code":"26.0",
    "gn:asciiname":"Xichanggou",
    "gn:country_code":"CN",
    "gn:dem":1056,
    "gn:feature_class":"P",
    "gn:feature_code":"PPL",
    "gn:name":"Xichanggou",
    "gn:population":0,
    "gn:timezone":"Asia/Shanghai",
    "iso:country":"CN",
    "name:zho_x_preferred":[
        "\u897f\u957f\u6c9f"
    ],
    "wof:name":"Xichanggou",
    "wof:placetype":"locality"
},
  "geometry": {"coordinates":[109.91473999999999,33.43909],"type":"Point"}
}