{
  "type": "Feature",
  "properties": {
    "gn:admin1_code":"29.0",
    "gn:asciiname":"Gesa",
    "gn:country_code":"CN",
    "gn:dem":1547,
    "gn:feature_class":"P",
    "gn:feature_code":"PPL",
    "gn:name":"Gesa",
    "gn:population":0,
    "gn:timezone":"Asia/Shanghai",
    "iso:country":"CN",
    "name:zho_x_preferred":[
        "\u683c\u6d12"
    ],
    "wof:name":"Gesa",
    "wof:placetype":"locality"
},
  "geometry": {"coordinates":[104.286,23.0121],"type":"Point"}
}