{
  "type": "Feature",
  "properties": {
    "gn:admin1_code":"21.0",
    "gn:asciiname":"Shayaoxian",
    "gn:country_code":"CN",
    "gn:dem":1665,
    "gn:feature_class":"P",
    "gn:feature_code":"PPL",
    "gn:name":"Shayaoxian",
    "gn:population":0,
    "gn:timezone":"Asia/Shanghai",
    "iso:country":"CN",
    "name:zho_x_preferred":[
        "\u6c99\u5d3e\u5c98"
    ],
    "wof:name":"Shayaoxian",
    "wof:placetype":"locality"
},
  "geometry": {"coordinates":[107.28,37.1721],"type":"Point"}
}