{
  "type": "Feature",
  "properties": {
    "gn:admin1_code":"20.0",
    "gn:asciiname":"Baguashan",
    "gn:country_code":"CN",
    "gn:dem":220,
    "gn:feature_class":"P",
    "gn:feature_code":"PPL",
    "gn:name":"Baguashan",
    "gn:population":0,
    "gn:timezone":"Asia/Shanghai",
    "iso:country":"CN",
    "name:zho_x_preferred":[
        "\u516b\u5366\u5c71"
    ],
    "wof:name":"Baguashan",
    "wof:placetype":"locality"
},
  "geometry": {"coordinates":[123.89987000000001,48.33564000000001],"type":"Point"}
}