{
  "type": "Feature",
  "properties": {
    "gn:admin1_code":"30.0",
    "gn:asciiname":"Penwang",
    "gn:country_code":"CN",
    "gn:dem":80,
    "gn:feature_class":"P",
    "gn:feature_code":"PPL",
    "gn:name":"Penwang",
    "gn:population":0,
    "gn:timezone":"Asia/Shanghai",
    "iso:country":"CN",
    "name:zho_x_preferred":[
        "\u76c6\u738b"
    ],
    "wof:name":"Penwang",
    "wof:placetype":"locality"
},
  "geometry": {"coordinates":[111.65129,23.61393],"type":"Point"}
}