{
  "type": "Feature",
  "properties": {
    "gn:admin1_code":"26.0",
    "gn:asciiname":"Zuizishang",
    "gn:country_code":"CN",
    "gn:dem":1069,
    "gn:feature_class":"P",
    "gn:feature_code":"PPL",
    "gn:name":"Zuizishang",
    "gn:population":0,
    "gn:timezone":"Asia/Shanghai",
    "iso:country":"CN",
    "name:zho_x_preferred":[
        "\u5480\u5b50\u4e0a"
    ],
    "wof:name":"Zuizishang",
    "wof:placetype":"locality"
},
  "geometry": {"coordinates":[108.1367,32.6726],"type":"Point"}
}