{
  "type": "Feature",
  "properties": {
    "gn:admin1_code":"29.0",
    "gn:asciiname":"Luancaojie",
    "gn:country_code":"CN",
    "gn:dem":1209,
    "gn:feature_class":"P",
    "gn:feature_code":"PPL",
    "gn:name":"Luancaojie",
    "gn:population":0,
    "gn:timezone":"Asia/Shanghai",
    "iso:country":"CN",
    "name:zho_x_preferred":[
        "\u4e71\u8349\u8857"
    ],
    "wof:name":"Luancaojie",
    "wof:placetype":"locality"
},
  "geometry": {"coordinates":[103.145,26.1584],"type":"Point"}
}