{
  "type": "Feature",
  "properties": {
    "gn:admin1_code":"29",
    "gn:asciiname":"Lijing",
    "gn:country_code":"CN",
    "gn:dem":1876,
    "gn:feature_class":"P",
    "gn:feature_code":"PPL",
    "gn:name":"Lijing",
    "gn:population":0,
    "gn:timezone":"Asia/Shanghai",
    "iso:country":"CN",
    "name:zho_x_preferred":[
        "\u674e\u4e95"
    ],
    "wof:name":"Lijing",
    "wof:placetype":"locality"
},
  "geometry": {"coordinates":[102.58461,24.28043],"type":"Point"}
}