{
  "type": "Feature",
  "properties": {
    "gn:admin1_code":"5.0",
    "gn:asciiname":"Fuqiang",
    "gn:country_code":"CN",
    "gn:dem":312,
    "gn:feature_class":"P",
    "gn:feature_code":"PPL",
    "gn:name":"Fuqiang",
    "gn:population":0,
    "gn:timezone":"Asia/Shanghai",
    "iso:country":"CN",
    "name:und_x_variant":[
        "\u5bcc\u5f3a"
    ],
    "wof:name":"Fuqiang",
    "wof:placetype":"locality"
},
  "geometry": {"coordinates":[129.67465000000001,43.52036],"type":"Point"}
}