{
  "type": "Feature",
  "properties": {
    "gn:admin1_code":"10",
    "gn:asciiname":"Dazaolinzhuang",
    "gn:country_code":"CN",
    "gn:dem":15,
    "gn:feature_class":"P",
    "gn:feature_code":"PPL",
    "gn:name":"Dazaolinzhuang",
    "gn:population":0,
    "gn:timezone":"Asia/Shanghai",
    "iso:country":"CN",
    "name:zho_x_preferred":[
        "\u5927\u67a3\u6797\u5e84"
    ],
    "wof:name":"Dazaolinzhuang",
    "wof:placetype":"locality"
},
  "geometry": {"coordinates":[116.76964,39.49049],"type":"Point"}
}