{
  "type": "Feature",
  "properties": {
    "gn:admin1_code":"32.0",
    "gn:asciiname":"Xiasiji",
    "gn:country_code":"CN",
    "gn:dem":3205,
    "gn:feature_class":"P",
    "gn:feature_code":"PPL",
    "gn:name":"Xiasiji",
    "gn:population":0,
    "gn:timezone":"Asia/Shanghai",
    "iso:country":"CN",
    "name:zho_x_preferred":[
        "\u5477\u56db\u5b63"
    ],
    "wof:name":"Xiasiji",
    "wof:placetype":"locality"
},
  "geometry": {"coordinates":[100.714,31.4547],"type":"Point"}
}