{
  "type": "Feature",
  "properties": {
    "gn:admin1_code":"7",
    "gn:asciiname":"Zhongyangshe",
    "gn:country_code":"CN",
    "gn:dem":68,
    "gn:feature_class":"P",
    "gn:feature_code":"PPL",
    "gn:name":"Zhongyangshe",
    "gn:population":0,
    "gn:timezone":"Asia/Shanghai",
    "iso:country":"CN",
    "name:zho_x_preferred":[
        "\u4e2d\u592e\u793e"
    ],
    "wof:name":"Zhongyangshe",
    "wof:placetype":"locality"
},
  "geometry": {"coordinates":[117.77417,24.77861],"type":"Point"}
}