{
  "type": "Feature",
  "properties": {
    "gn:admin1_code":"26.0",
    "gn:asciiname":"Jiantoucun",
    "gn:country_code":"CN",
    "gn:dem":645,
    "gn:feature_class":"P",
    "gn:feature_code":"PPL",
    "gn:name":"Jiantoucun",
    "gn:population":0,
    "gn:timezone":"Asia/Shanghai",
    "iso:country":"CN",
    "name:zho_x_preferred":[
        "\u6da7\u5934\u6751"
    ],
    "wof:name":"Jiantoucun",
    "wof:placetype":"locality"
},
  "geometry": {"coordinates":[110.43053,35.95959000000001],"type":"Point"}
}