{
  "type": "Feature",
  "properties": {
    "gn:admin1_code":"31.0",
    "gn:asciiname":"Futibei",
    "gn:country_code":"CN",
    "gn:dem":9,
    "gn:feature_class":"P",
    "gn:feature_code":"PPL",
    "gn:name":"Futibei",
    "gn:population":0,
    "gn:timezone":"Asia/Shanghai",
    "iso:country":"CN",
    "name:zho_x_preferred":[
        "\u6276\u63d0\u5317"
    ],
    "wof:name":"Futibei",
    "wof:placetype":"locality"
},
  "geometry": {"coordinates":[109.62739000000001,19.99095],"type":"Point"}
}