{
  "type": "Feature",
  "properties": {
    "gn:admin1_code":"2.0",
    "gn:asciiname":"Wucheng",
    "gn:country_code":"CN",
    "gn:dem":7,
    "gn:feature_class":"P",
    "gn:feature_code":"PPL",
    "gn:name":"Wucheng",
    "gn:population":0,
    "gn:timezone":"Asia/Shanghai",
    "iso:country":"CN",
    "name:zho_x_preferred":[
        "\u5434\u57ce"
    ],
    "wof:name":"Wucheng",
    "wof:placetype":"locality"
},
  "geometry": {"coordinates":[119.89579000000001,31.10944000000001],"type":"Point"}
}