{
  "type": "Feature",
  "properties": {
    "gn:admin1_code":"16.0",
    "gn:asciiname":"Guihuo",
    "gn:country_code":"CN",
    "gn:dem":1093,
    "gn:feature_class":"P",
    "gn:feature_code":"PPL",
    "gn:name":"Guihuo",
    "gn:population":0,
    "gn:timezone":"Asia/Shanghai",
    "iso:country":"CN",
    "name:zho_x_preferred":[
        "\u89c4\u6216"
    ],
    "wof:name":"Guihuo",
    "wof:placetype":"locality"
},
  "geometry": {"coordinates":[105.73999999999999,23.1979],"type":"Point"}
}