{
  "type": "Feature",
  "properties": {
    "gn:admin1_code":"7.0",
    "gn:asciiname":"Guangkeng",
    "gn:country_code":"CN",
    "gn:dem":731,
    "gn:feature_class":"P",
    "gn:feature_code":"PPL",
    "gn:name":"Guangkeng",
    "gn:population":0,
    "gn:timezone":"Asia/Shanghai",
    "iso:country":"CN",
    "name:und_x_variant":[
        "\u5e7f\u5751",
        "Guangkeng"
    ],
    "wof:name":"Guangkeng",
    "wof:placetype":"locality"
},
  "geometry": {"coordinates":[119.10297,27.04552],"type":"Point"}
}