{
  "type": "Feature",
  "properties": {
    "gn:admin1_code":"4.0",
    "gn:asciiname":"Heye",
    "gn:country_code":"CN",
    "gn:dem":6,
    "gn:feature_class":"P",
    "gn:feature_code":"PPL",
    "gn:name":"Heye",
    "gn:population":0,
    "gn:timezone":"Asia/Shanghai",
    "iso:country":"CN",
    "name:ceb_x_preferred":[
        "Heye"
    ],
    "name:deu_x_preferred":[
        "Heye"
    ],
    "name:swe_x_preferred":[
        "Heye"
    ],
    "name:wln_x_preferred":[
        "Heye"
    ],
    "name:zho_x_preferred":[
        "\u6cb3\u91ce"
    ],
    "wof:name":"Heye",
    "wof:placetype":"locality"
},
  "geometry": {"coordinates":[120.02698999999998,32.61514],"type":"Point"}
}