{
  "type": "Feature",
  "properties": {
    "gn:admin1_code":"16.0",
    "gn:asciiname":"Duiwei",
    "gn:country_code":"CN",
    "gn:dem":191,
    "gn:feature_class":"P",
    "gn:feature_code":"PPL",
    "gn:name":"Duiwei",
    "gn:population":0,
    "gn:timezone":"Asia/Shanghai",
    "iso:country":"CN",
    "name:zho_x_preferred":[
        "\u5151\u97e6"
    ],
    "wof:name":"Duiwei",
    "wof:placetype":"locality"
},
  "geometry": {"coordinates":[108.13800000000001,23.6264],"type":"Point"}
}