{
  "type": "Feature",
  "properties": {
    "gn:admin1_code":"32.0",
    "gn:asciiname":"Hanniu",
    "gn:country_code":"CN",
    "gn:dem":2916,
    "gn:feature_class":"P",
    "gn:feature_code":"PPL",
    "gn:name":"Hanniu",
    "gn:population":0,
    "gn:timezone":"Asia/Shanghai",
    "iso:country":"CN",
    "name:zho_x_preferred":[
        "\u6c57\u725b"
    ],
    "wof:name":"Hanniu",
    "wof:placetype":"locality"
},
  "geometry": {"coordinates":[102.20954999999999,30.78632],"type":"Point"}
}