{
  "type": "Feature",
  "properties": {
    "gn:admin1_code":"15.0",
    "gn:asciiname":"Xuduogou",
    "gn:country_code":"CN",
    "gn:dem":1486,
    "gn:feature_class":"P",
    "gn:feature_code":"PPL",
    "gn:name":"Xuduogou",
    "gn:population":0,
    "gn:timezone":"Asia/Shanghai",
    "iso:country":"CN",
    "name:zho_x_preferred":[
        "\u8bb8\u591a\u6c9f"
    ],
    "wof:name":"Xuduogou",
    "wof:placetype":"locality"
},
  "geometry": {"coordinates":[106.806,35.1935],"type":"Point"}
}