{
  "type": "Feature",
  "properties": {
    "gn:admin1_code":"11.0",
    "gn:asciiname":"Qiluotang",
    "gn:country_code":"CN",
    "gn:dem":231,
    "gn:feature_class":"P",
    "gn:feature_code":"PPL",
    "gn:name":"Qiluotang",
    "gn:population":0,
    "gn:timezone":"Asia/Shanghai",
    "iso:country":"CN",
    "name:zho_x_preferred":[
        "\u9a91\u9a86\u5858"
    ],
    "wof:name":"Qiluotang",
    "wof:placetype":"locality"
},
  "geometry": {"coordinates":[112.99641,25.46872],"type":"Point"}
}