{
  "type": "Feature",
  "properties": {
    "gn:admin1_code":"6.0",
    "gn:asciiname":"Digan",
    "gn:country_code":"CN",
    "gn:dem":3112,
    "gn:feature_class":"P",
    "gn:feature_code":"PPL",
    "gn:name":"Digan",
    "gn:population":0,
    "gn:timezone":"Asia/Shanghai",
    "iso:country":"CN",
    "name:zho_x_preferred":[
        "\u5730\u5e72"
    ],
    "wof:name":"Digan",
    "wof:placetype":"locality"
},
  "geometry": {"coordinates":[100.51822,35.25040999999999],"type":"Point"}
}