{
  "type": "Feature",
  "properties": {
    "gn:admin1_code":"3.0",
    "gn:asciiname":"Shuyuan",
    "gn:country_code":"CN",
    "gn:dem":424,
    "gn:feature_class":"P",
    "gn:feature_code":"PPL",
    "gn:name":"Shuyuan",
    "gn:population":0,
    "gn:timezone":"Asia/Shanghai",
    "iso:country":"CN",
    "name:und_x_variant":[
        "\u7f72\u5143"
    ],
    "wof:name":"Shuyuan",
    "wof:placetype":"locality"
},
  "geometry": {"coordinates":[115.89277,26.90327000000001],"type":"Point"}
}