{
  "type": "Feature",
  "properties": {
    "gn:admin1_code":"3.0",
    "gn:asciiname":"Chejiadong",
    "gn:country_code":"CN",
    "gn:dem":342,
    "gn:feature_class":"P",
    "gn:feature_code":"PPL",
    "gn:name":"Chejiadong",
    "gn:population":0,
    "gn:timezone":"Asia/Shanghai",
    "iso:country":"CN",
    "name:und_x_variant":[
        "\u8f66\u5bb6\u6d1e"
    ],
    "wof:name":"Chejiadong",
    "wof:placetype":"locality"
},
  "geometry": {"coordinates":[114.3087,29.13656],"type":"Point"}
}