{
  "type": "Feature",
  "properties": {
    "gn:admin1_code":"12.0",
    "gn:asciiname":"Lanjing'an",
    "gn:country_code":"CN",
    "gn:dem":682,
    "gn:feature_class":"P",
    "gn:feature_code":"PPL",
    "gn:name":"Lanjing\u2019an",
    "gn:population":0,
    "gn:timezone":"Asia/Shanghai",
    "iso:country":"CN",
    "name:und_x_variant":[
        "Lanjing\u2019an"
    ],
    "name:zho_x_preferred":[
        "\u5170\u7ecf\u5eb5"
    ],
    "wof:name":"Lanjing'an",
    "wof:placetype":"locality"
},
  "geometry": {"coordinates":[110.99046,32.09607],"type":"Point"}
}