{
  "type": "Feature",
  "properties": {
    "gn:admin1_code":"3.0",
    "gn:asciiname":"Xingtang",
    "gn:country_code":"CN",
    "gn:dem":142,
    "gn:feature_class":"P",
    "gn:feature_code":"PPL",
    "gn:name":"Xingtang",
    "gn:population":0,
    "gn:timezone":"Asia/Shanghai",
    "iso:country":"CN",
    "name:und_x_variant":[
        "\u674f\u5858"
    ],
    "wof:name":"Xingtang",
    "wof:placetype":"locality"
},
  "geometry": {"coordinates":[114.18819999999999,28.05014000000001],"type":"Point"}
}