{
  "type": "Feature",
  "properties": {
    "gn:admin1_code":"32.0",
    "gn:asciiname":"Wujia Pingzi",
    "gn:country_code":"CN",
    "gn:dem":1530,
    "gn:feature_class":"P",
    "gn:feature_code":"PPL",
    "gn:name":"Wujia Pingzi",
    "gn:population":0,
    "gn:timezone":"Asia/Shanghai",
    "iso:country":"CN",
    "name:zho_x_preferred":[
        "\u5434\u5bb6\u576a\u5b50"
    ],
    "wof:name":"Wujia Pingzi",
    "wof:placetype":"locality"
},
  "geometry": {"coordinates":[101.741,26.7187],"type":"Point"}
}