{
  "type": "Feature",
  "properties": {
    "gn:admin1_code":"26.0",
    "gn:asciiname":"Fenghuangwan",
    "gn:country_code":"CN",
    "gn:dem":1585,
    "gn:feature_class":"P",
    "gn:feature_code":"PPL",
    "gn:name":"Fenghuangwan",
    "gn:population":0,
    "gn:timezone":"Asia/Shanghai",
    "iso:country":"CN",
    "name:zho_x_preferred":[
        "\u51e4\u51f0\u6e7e"
    ],
    "wof:name":"Fenghuangwan",
    "wof:placetype":"locality"
},
  "geometry": {"coordinates":[107.91943999999999,37.16523],"type":"Point"}
}