{
  "type": "Feature",
  "properties": {
    "gn:admin1_code":"19.0",
    "gn:asciiname":"Yuanjia Wobu",
    "gn:country_code":"CN",
    "gn:dem":98,
    "gn:feature_class":"P",
    "gn:feature_code":"PPL",
    "gn:name":"Yuanjia Wobu",
    "gn:population":0,
    "gn:timezone":"Asia/Shanghai",
    "iso:country":"CN",
    "name:und_x_variant":[
        "Yuanjiawobao",
        "Yuanjia Wobu"
    ],
    "name:zho_x_preferred":[
        "\u8881\u5bb6\u7a9d\u5821"
    ],
    "wof:name":"Yuanjia Wobu",
    "wof:placetype":"locality"
},
  "geometry": {"coordinates":[123.44643000000001,42.99303],"type":"Point"}
}