{
  "type": "Feature",
  "properties": {
    "gn:admin1_code":"9.0",
    "gn:asciiname":"Chigou",
    "gn:country_code":"CN",
    "gn:dem":301,
    "gn:feature_class":"P",
    "gn:feature_code":"PPL",
    "gn:name":"Chigou",
    "gn:population":0,
    "gn:timezone":"Asia/Shanghai",
    "iso:country":"CN",
    "name:zho_x_preferred":[
        "\u6c60\u6c9f"
    ],
    "wof:name":"Chigou",
    "wof:placetype":"locality"
},
  "geometry": {"coordinates":[113.20269,34.21387],"type":"Point"}
}