{
  "type": "Feature",
  "properties": {
    "gn:admin1_code":"19.0",
    "gn:asciiname":"Youyizhuang",
    "gn:country_code":"CN",
    "gn:dem":448,
    "gn:feature_class":"P",
    "gn:feature_code":"PPL",
    "gn:name":"Youyizhuang",
    "gn:population":0,
    "gn:timezone":"Asia/Shanghai",
    "iso:country":"CN",
    "name:zho_x_preferred":[
        "\u53cb\u8c0a\u5e84"
    ],
    "wof:name":"Youyizhuang",
    "wof:placetype":"locality"
},
  "geometry": {"coordinates":[119.446,40.9666],"type":"Point"}
}