{
  "type": "Feature",
  "properties": {
    "gn:admin1_code":"5.0",
    "gn:asciiname":"Chengbei",
    "gn:country_code":"CN",
    "gn:dem":280,
    "gn:feature_class":"P",
    "gn:feature_code":"PPL",
    "gn:name":"Chengbei",
    "gn:population":0,
    "gn:timezone":"Asia/Shanghai",
    "iso:country":"CN",
    "name:und_x_variant":[
        "\u57ce\u5317"
    ],
    "wof:name":"Chengbei",
    "wof:placetype":"locality"
},
  "geometry": {"coordinates":[129.30324999999999,42.7731],"type":"Point"}
}