{
  "type": "Feature",
  "properties": {
    "gn:admin1_code":"33.0",
    "gn:asciiname":"Yingxiong",
    "gn:country_code":"CN",
    "gn:dem":1109,
    "gn:feature_class":"P",
    "gn:feature_code":"PPL",
    "gn:name":"Yingxiong",
    "gn:population":0,
    "gn:timezone":"Asia/Shanghai",
    "iso:country":"CN",
    "name:zho_x_preferred":[
        "\u82f1\u96c4"
    ],
    "wof:name":"Yingxiong",
    "wof:placetype":"locality"
},
  "geometry": {"coordinates":[108.05953,29.49504],"type":"Point"}
}