{
  "type": "Feature",
  "properties": {
    "gn:admin1_code":"19",
    "gn:asciiname":"Guzhuyingzi",
    "gn:country_code":"CN",
    "gn:dem":286,
    "gn:feature_class":"P",
    "gn:feature_code":"PPLA4",
    "gn:name":"Guzhuyingzi",
    "gn:population":0,
    "gn:timezone":"Asia/Shanghai",
    "iso:country":"CN",
    "name:und_x_variant":[
        "Guzhuying",
        "Guzhuyingzi Xiang",
        "Guzhuyingzi"
    ],
    "name:zho_x_preferred":[
        "\u5b64\u7af9\u8425\u5b50"
    ],
    "name:zho_x_variant":[
        "\u5b64\u7af9\u8425\u5b50\u4e61"
    ],
    "wof:name":"Guzhuyingzi",
    "wof:placetype":"locality"
},
  "geometry": {"coordinates":[120.26719,40.93805],"type":"Point"}
}