{
  "type": "Feature",
  "properties": {
    "gn:admin1_code":"2.0",
    "gn:asciiname":"Xuekeng",
    "gn:country_code":"CN",
    "gn:dem":278,
    "gn:feature_class":"P",
    "gn:feature_code":"PPL",
    "gn:name":"Xuekeng",
    "gn:population":0,
    "gn:timezone":"Asia/Shanghai",
    "iso:country":"CN",
    "name:zho_x_preferred":[
        "\u96ea\u5751"
    ],
    "wof:name":"Xuekeng",
    "wof:placetype":"locality"
},
  "geometry": {"coordinates":[121.00321,29.05711],"type":"Point"}
}