{
  "type": "Feature",
  "properties": {
    "gn:admin1_code":"8.0",
    "gn:asciiname":"Cuolimucun",
    "gn:country_code":"CN",
    "gn:dem":144,
    "gn:feature_class":"P",
    "gn:feature_code":"PPL",
    "gn:name":"Cuolimucun",
    "gn:population":0,
    "gn:timezone":"Asia/Shanghai",
    "iso:country":"CN",
    "name:zho_x_preferred":[
        "\u64ae\u91cc\u6728\u6751"
    ],
    "wof:name":"Cuolimucun",
    "wof:placetype":"locality"
},
  "geometry": {"coordinates":[123.85617000000001,46.9556],"type":"Point"}
}