{
  "type": "Feature",
  "properties": {
    "gn:admin1_code":"11",
    "gn:asciiname":"Shegang",
    "gn:cc2":"CN",
    "gn:country_code":"CN",
    "gn:dem":98,
    "gn:feature_class":"P",
    "gn:feature_code":"PPL",
    "gn:name":"Shegang",
    "gn:population":0,
    "gn:timezone":"Asia/Shanghai",
    "iso:country":"CN",
    "name:und_x_variant":[
        "Sha-kang-shih",
        "Shegangshi",
        "Shegang"
    ],
    "wof:name":"Shegang",
    "wof:placetype":"locality"
},
  "geometry": {"coordinates":[113.55583,28.47139],"type":"Point"}
}