{
  "type": "Feature",
  "properties": {
    "gn:admin1_code":"29.0",
    "gn:asciiname":"Zongbi",
    "gn:country_code":"CN",
    "gn:dem":1991,
    "gn:feature_class":"P",
    "gn:feature_code":"PPL",
    "gn:name":"Zongbi",
    "gn:population":0,
    "gn:timezone":"Asia/Shanghai",
    "iso:country":"CN",
    "name:zho_x_preferred":[
        "\u603b\u5fc5"
    ],
    "wof:name":"Zongbi",
    "wof:placetype":"locality"
},
  "geometry": {"coordinates":[103.38500000000001,25.5184],"type":"Point"}
}