{
  "type": "Feature",
  "properties": {
    "gn:admin1_code":"29",
    "gn:asciiname":"Ediju",
    "gn:country_code":"CN",
    "gn:dem":1820,
    "gn:feature_class":"P",
    "gn:feature_code":"PPL",
    "gn:name":"Ediju",
    "gn:population":0,
    "gn:timezone":"Asia/Shanghai",
    "iso:country":"CN",
    "name:zho_x_preferred":[
        "\u5ce8\u5730\u82f4"
    ],
    "wof:name":"Ediju",
    "wof:placetype":"locality"
},
  "geometry": {"coordinates":[101.33199999999999,24.6529],"type":"Point"}
}