{
  "type": "Feature",
  "properties": {
    "gn:admin1_code":"8.0",
    "gn:asciiname":"Tianfutun",
    "gn:country_code":"CN",
    "gn:dem":207,
    "gn:feature_class":"P",
    "gn:feature_code":"PPL",
    "gn:name":"Tianfutun",
    "gn:population":0,
    "gn:timezone":"Asia/Shanghai",
    "iso:country":"CN",
    "name:zho_x_preferred":[
        "\u7530\u798f\u5c6f"
    ],
    "wof:name":"Tianfutun",
    "wof:placetype":"locality"
},
  "geometry": {"coordinates":[124.67033000000001,48.51451],"type":"Point"}
}