{
  "type": "Feature",
  "properties": {
    "gn:admin1_code":"6.0",
    "gn:asciiname":"Gashoupo",
    "gn:country_code":"CN",
    "gn:dem":3851,
    "gn:feature_class":"P",
    "gn:feature_code":"PPL",
    "gn:name":"Gashoupo",
    "gn:population":0,
    "gn:timezone":"Asia/Urumqi",
    "iso:country":"CN",
    "name:zho_x_preferred":[
        "\u5c15\u9996\u5761"
    ],
    "wof:name":"Gashoupo",
    "wof:placetype":"locality"
},
  "geometry": {"coordinates":[96.32136,32.41302],"type":"Point"}
}