{
  "type": "Feature",
  "properties": {
    "gn:admin1_code":"32.0",
    "gn:asciiname":"Xialang",
    "gn:country_code":"CN",
    "gn:dem":4297,
    "gn:feature_class":"P",
    "gn:feature_code":"PPL",
    "gn:name":"Xialang",
    "gn:population":0,
    "gn:timezone":"Asia/Shanghai",
    "iso:country":"CN",
    "name:zho_x_preferred":[
        "\u5477\u90ce"
    ],
    "wof:name":"Xialang",
    "wof:placetype":"locality"
},
  "geometry": {"coordinates":[101.238,31.4813],"type":"Point"}
}