{
  "type": "Feature",
  "properties": {
    "gn:admin1_code":"4.0",
    "gn:asciiname":"Suntaicun",
    "gn:country_code":"CN",
    "gn:dem":16,
    "gn:feature_class":"P",
    "gn:feature_code":"PPL",
    "gn:name":"Suntaicun",
    "gn:population":0,
    "gn:timezone":"Asia/Shanghai",
    "iso:country":"CN",
    "name:zho_x_preferred":[
        "\u5b59\u53f0\u6751"
    ],
    "wof:name":"Suntaicun",
    "wof:placetype":"locality"
},
  "geometry": {"coordinates":[118.24548,33.34027],"type":"Point"}
}