{
  "type": "Feature",
  "properties": {
    "gn:admin1_code":"32.0",
    "gn:asciiname":"Zhubi",
    "gn:country_code":"CN",
    "gn:dem":3159,
    "gn:feature_class":"P",
    "gn:feature_code":"PPL",
    "gn:name":"Zhubi",
    "gn:population":0,
    "gn:timezone":"Asia/Shanghai",
    "iso:country":"CN",
    "name:zho_x_preferred":[
        "\u7af9\u6bd4"
    ],
    "wof:name":"Zhubi",
    "wof:placetype":"locality"
},
  "geometry": {"coordinates":[101.2195,28.4872],"type":"Point"}
}