{
  "type": "Feature",
  "properties": {
    "gn:admin1_code":"02",
    "gn:asciiname":"Tian'aocun",
    "gn:country_code":"CN",
    "gn:dem":624,
    "gn:feature_class":"P",
    "gn:feature_code":"PPL",
    "gn:name":"Tian\u2019aocun",
    "gn:population":0,
    "gn:timezone":"Asia/Shanghai",
    "iso:country":"CN",
    "name:und_x_variant":[
        "T\u2019ien-ao",
        "Tian\u2019ao",
        "Tian\u2019aocun"
    ],
    "name:zho_x_preferred":[
        "\u7530\u5c99\u6751"
    ],
    "wof:name":"Tian'aocun",
    "wof:placetype":"locality"
},
  "geometry": {"coordinates":[120.89587,28.52117],"type":"Point"}
}