{
  "type": "Feature",
  "properties": {
    "gn:admin1_code":"3.0",
    "gn:asciiname":"Shitoujue",
    "gn:country_code":"CN",
    "gn:dem":82,
    "gn:feature_class":"P",
    "gn:feature_code":"PPL",
    "gn:name":"Shitoujue",
    "gn:population":0,
    "gn:timezone":"Asia/Shanghai",
    "iso:country":"CN",
    "name:zho_x_preferred":[
        "\u77f3\u5934\u5d1b"
    ],
    "wof:name":"Shitoujue",
    "wof:placetype":"locality"
},
  "geometry": {"coordinates":[117.779,29.2447],"type":"Point"}
}