{
  "type": "Feature",
  "properties": {
    "gn:admin1_code":"9.0",
    "gn:asciiname":"Zhulin",
    "gn:country_code":"CN",
    "gn:dem":124,
    "gn:feature_class":"P",
    "gn:feature_code":"PPL",
    "gn:name":"Zhulin",
    "gn:population":0,
    "gn:timezone":"Asia/Shanghai",
    "iso:country":"CN",
    "name:ceb_x_preferred":[
        "Zhulin"
    ],
    "name:swe_x_preferred":[
        "Zhulin"
    ],
    "name:zho_x_preferred":[
        "\u7af9\u6797"
    ],
    "wof:name":"Zhulin",
    "wof:placetype":"locality"
},
  "geometry": {"coordinates":[113.49079,32.93519000000001],"type":"Point"}
}