{
  "type": "Feature",
  "properties": {
    "gn:admin1_code":"29.0",
    "gn:asciiname":"Dajuan",
    "gn:country_code":"CN",
    "gn:dem":488,
    "gn:feature_class":"P",
    "gn:feature_code":"PPL",
    "gn:name":"Dajuan",
    "gn:population":0,
    "gn:timezone":"Asia/Shanghai",
    "iso:country":"CN",
    "name:zho_x_preferred":[
        "\u5927\u5377"
    ],
    "wof:name":"Dajuan",
    "wof:placetype":"locality"
},
  "geometry": {"coordinates":[103.45999999999999,28.1029],"type":"Point"}
}