{
  "type": "Feature",
  "properties": {
    "gn:admin1_code":"24.0",
    "gn:asciiname":"Xinjing",
    "gn:country_code":"CN",
    "gn:dem":1426,
    "gn:feature_class":"P",
    "gn:feature_code":"PPL",
    "gn:name":"Xinjing",
    "gn:population":0,
    "gn:timezone":"Asia/Shanghai",
    "iso:country":"CN",
    "name:deu_x_preferred":[
        "Xinjing"
    ],
    "name:zho_x_preferred":[
        "\u8f9b\u4e95"
    ],
    "wof:name":"Xinjing",
    "wof:placetype":"locality"
},
  "geometry": {"coordinates":[111.84086000000001,39.17328],"type":"Point"}
}