{
  "type": "Feature",
  "properties": {
    "gn:admin1_code":"7",
    "gn:asciiname":"Menkoushan",
    "gn:country_code":"CN",
    "gn:dem":50,
    "gn:feature_class":"P",
    "gn:feature_code":"PPL",
    "gn:name":"Menkoushan",
    "gn:population":0,
    "gn:timezone":"Asia/Shanghai",
    "iso:country":"CN",
    "name:zho_x_preferred":[
        "\u95e8\u53e3\u5c71"
    ],
    "wof:name":"Menkoushan",
    "wof:placetype":"locality"
},
  "geometry": {"coordinates":[117.93653999999999,24.24374],"type":"Point"}
}