{
  "type": "Feature",
  "properties": {
    "gn:admin1_code":"8.0",
    "gn:asciiname":"Rong'ancun",
    "gn:country_code":"CN",
    "gn:dem":161,
    "gn:feature_class":"P",
    "gn:feature_code":"PPL",
    "gn:name":"Rong\u2019ancun",
    "gn:population":0,
    "gn:timezone":"Asia/Shanghai",
    "iso:country":"CN",
    "name:und_x_variant":[
        "Rong\u2019ancun"
    ],
    "name:zho_x_preferred":[
        "\u8363\u5b89\u6751"
    ],
    "wof:name":"Rong'ancun",
    "wof:placetype":"locality"
},
  "geometry": {"coordinates":[130.33066000000002,46.14664000000001],"type":"Point"}
}