{
  "type": "Feature",
  "properties": {
    "gn:admin1_code":"18",
    "gn:asciiname":"Bikongshan",
    "gn:country_code":"CN",
    "gn:dem":1044,
    "gn:feature_class":"P",
    "gn:feature_code":"PPL",
    "gn:name":"Bikongshan",
    "gn:population":0,
    "gn:timezone":"Asia/Shanghai",
    "iso:country":"CN",
    "name:zho_x_preferred":[
        "\u9f3b\u5b54\u5c71"
    ],
    "wof:name":"Bikongshan",
    "wof:placetype":"locality"
},
  "geometry": {"coordinates":[107.07599999999999,28.6905],"type":"Point"}
}