{
  "type": "Feature",
  "properties": {
    "gn:admin1_code":"8.0",
    "gn:asciiname":"Houhamatang",
    "gn:country_code":"CN",
    "gn:dem":486,
    "gn:feature_class":"P",
    "gn:feature_code":"PPL",
    "gn:name":"Houhamatang",
    "gn:population":0,
    "gn:timezone":"Asia/Shanghai",
    "iso:country":"CN",
    "name:zho_x_preferred":[
        "\u540e\u86e4\u87c6\u5858"
    ],
    "wof:name":"Houhamatang",
    "wof:placetype":"locality"
},
  "geometry": {"coordinates":[129.30172999999999,44.69786],"type":"Point"}
}