{
  "type": "Feature",
  "properties": {
    "gn:admin1_code":"29",
    "gn:asciiname":"Shangxinzhai",
    "gn:country_code":"CN",
    "gn:dem":1255,
    "gn:feature_class":"P",
    "gn:feature_code":"PPL",
    "gn:name":"Shangxinzhai",
    "gn:population":0,
    "gn:timezone":"Asia/Shanghai",
    "iso:country":"CN",
    "name:zho_x_preferred":[
        "\u4e0a\u65b0\u5be8"
    ],
    "wof:name":"Shangxinzhai",
    "wof:placetype":"locality"
},
  "geometry": {"coordinates":[105.31,23.7533],"type":"Point"}
}