{
  "type": "Feature",
  "properties": {
    "gn:admin1_code":"7",
    "gn:asciiname":"Hengkenglong",
    "gn:country_code":"CN",
    "gn:dem":388,
    "gn:feature_class":"P",
    "gn:feature_code":"PPL",
    "gn:name":"Hengkenglong",
    "gn:population":0,
    "gn:timezone":"Asia/Shanghai",
    "iso:country":"CN",
    "name:und_x_variant":[
        "\u6a2a\u5751\u5784"
    ],
    "wof:name":"Hengkenglong",
    "wof:placetype":"locality"
},
  "geometry": {"coordinates":[118.88028,27.41694],"type":"Point"}
}