{
  "type": "Feature",
  "properties": {
    "gn:admin1_code":"29.0",
    "gn:asciiname":"Gegenshan",
    "gn:country_code":"CN",
    "gn:dem":2148,
    "gn:feature_class":"P",
    "gn:feature_code":"PPL",
    "gn:name":"Gegenshan",
    "gn:population":0,
    "gn:timezone":"Asia/Shanghai",
    "iso:country":"CN",
    "name:zho_x_preferred":[
        "\u845b\u6839\u5c71"
    ],
    "wof:name":"Gegenshan",
    "wof:placetype":"locality"
},
  "geometry": {"coordinates":[99.25020000000001,24.7899],"type":"Point"}
}