{
  "type": "Feature",
  "properties": {
    "gn:admin1_code":"19.0",
    "gn:asciiname":"Zhongyitun",
    "gn:country_code":"CN",
    "gn:dem":309,
    "gn:feature_class":"P",
    "gn:feature_code":"PPL",
    "gn:name":"Zhongyitun",
    "gn:population":0,
    "gn:timezone":"Asia/Shanghai",
    "iso:country":"CN",
    "name:und_x_variant":[
        "\u5fe0\u4e49\u5c6f"
    ],
    "name:zho_x_preferred":[
        "\u5fe0\u4e49\u5c6f"
    ],
    "wof:name":"Zhongyitun",
    "wof:placetype":"locality"
},
  "geometry": {"coordinates":[124.97611999999999,42.59506],"type":"Point"}
}