{
  "type": "Feature",
  "properties": {
    "gn:admin1_code":"10",
    "gn:asciiname":"Tangzhangzi",
    "gn:country_code":"CN",
    "gn:dem":508,
    "gn:feature_class":"P",
    "gn:feature_code":"PPL",
    "gn:name":"Tangzhangzi",
    "gn:population":0,
    "gn:timezone":"Asia/Shanghai",
    "iso:country":"CN",
    "name:zho_x_preferred":[
        "\u5510\u6756\u5b50"
    ],
    "wof:name":"Tangzhangzi",
    "wof:placetype":"locality"
},
  "geometry": {"coordinates":[118.93818,40.46681],"type":"Point"}
}