{
  "type": "Feature",
  "properties": {
    "gn:admin1_code":"12.0",
    "gn:asciiname":"Shangzhengjiawan",
    "gn:country_code":"CN",
    "gn:dem":1374,
    "gn:feature_class":"P",
    "gn:feature_code":"PPL",
    "gn:name":"Shangzhengjiawan",
    "gn:population":0,
    "gn:timezone":"Asia/Shanghai",
    "iso:country":"CN",
    "name:zho_x_preferred":[
        "\u4e0a\u90d1\u5bb6\u6e7e"
    ],
    "wof:name":"Shangzhengjiawan",
    "wof:placetype":"locality"
},
  "geometry": {"coordinates":[110.69508,30.31336],"type":"Point"}
}