{
  "type": "Feature",
  "properties": {
    "gn:admin1_code":"9.0",
    "gn:asciiname":"Huangmiaogou",
    "gn:country_code":"CN",
    "gn:dem":510,
    "gn:feature_class":"P",
    "gn:feature_code":"PPL",
    "gn:name":"Huangmiaogou",
    "gn:population":0,
    "gn:timezone":"Asia/Shanghai",
    "iso:country":"CN",
    "name:zho_x_preferred":[
        "\u9ec4\u5e99\u6c9f"
    ],
    "wof:name":"Huangmiaogou",
    "wof:placetype":"locality"
},
  "geometry": {"coordinates":[111.12317,33.23936],"type":"Point"}
}