{
  "type": "Feature",
  "properties": {
    "gn:admin1_code":"19.0",
    "gn:asciiname":"Shitoumiaozi",
    "gn:country_code":"CN",
    "gn:dem":72,
    "gn:feature_class":"P",
    "gn:feature_code":"PPL",
    "gn:name":"Shitoumiaozi",
    "gn:population":0,
    "gn:timezone":"Asia/Shanghai",
    "iso:country":"CN",
    "name:zho_x_preferred":[
        "\u77f3\u5934\u5e99\u5b50"
    ],
    "wof:name":"Shitoumiaozi",
    "wof:placetype":"locality"
},
  "geometry": {"coordinates":[121.43411999999999,41.62985],"type":"Point"}
}