{
  "type": "Feature",
  "properties": {
    "gn:admin1_code":"16",
    "gn:asciiname":"Dangshang",
    "gn:country_code":"CN",
    "gn:dem":149,
    "gn:feature_class":"P",
    "gn:feature_code":"PPL",
    "gn:name":"Dangshang",
    "gn:population":0,
    "gn:timezone":"Asia/Shanghai",
    "iso:country":"CN",
    "name:zho_x_preferred":[
        "\u5f53\u4e0a"
    ],
    "wof:name":"Dangshang",
    "wof:placetype":"locality"
},
  "geometry": {"coordinates":[110.027,24.9517],"type":"Point"}
}