{
  "type": "Feature",
  "properties": {
    "gn:admin1_code":"30.0",
    "gn:asciiname":"Da'nan",
    "gn:country_code":"CN",
    "gn:dem":6,
    "gn:feature_class":"P",
    "gn:feature_code":"PPL",
    "gn:name":"Da\u2019nan",
    "gn:population":0,
    "gn:timezone":"Asia/Shanghai",
    "iso:country":"CN",
    "name:und_x_variant":[
        "Da\u2019nan"
    ],
    "name:zho_x_preferred":[
        "\u5927\u6960"
    ],
    "wof:name":"Da'nan",
    "wof:placetype":"locality"
},
  "geometry": {"coordinates":[112.79094000000001,22.8658],"type":"Point"}
}