{
  "type": "Feature",
  "properties": {
    "gn:admin1_code":"29.0",
    "gn:asciiname":"Lelichong",
    "gn:country_code":"CN",
    "gn:dem":1965,
    "gn:feature_class":"P",
    "gn:feature_code":"PPL",
    "gn:name":"Lelichong",
    "gn:population":0,
    "gn:timezone":"Asia/Shanghai",
    "iso:country":"CN",
    "name:zho_x_preferred":[
        "\u4e50\u5229\u51b2"
    ],
    "wof:name":"Lelichong",
    "wof:placetype":"locality"
},
  "geometry": {"coordinates":[101.65000000000001,25.298],"type":"Point"}
}