{
  "type": "Feature",
  "properties": {
    "gn:admin1_code":"12.0",
    "gn:asciiname":"Dongzhaojianao",
    "gn:country_code":"CN",
    "gn:dem":29,
    "gn:feature_class":"P",
    "gn:feature_code":"PPL",
    "gn:name":"Dongzhaojianao",
    "gn:population":0,
    "gn:timezone":"Asia/Shanghai",
    "iso:country":"CN",
    "name:zho_x_preferred":[
        "\u4e1c\u8d75\u5bb6\u8111"
    ],
    "wof:name":"Dongzhaojianao",
    "wof:placetype":"locality"
},
  "geometry": {"coordinates":[112.80528,29.90448],"type":"Point"}
}