{
  "type": "Feature",
  "properties": {
    "gn:admin1_code":"30",
    "gn:asciiname":"Shaxi",
    "gn:country_code":"CN",
    "gn:dem":130,
    "gn:feature_class":"P",
    "gn:feature_code":"PPLA4",
    "gn:name":"Shaxi",
    "gn:population":0,
    "gn:timezone":"Asia/Shanghai",
    "iso:country":"CN",
    "name:und_x_variant":[
        "Sha-ch\u2019i",
        "Sha-ch\u2019i-hs\u00fc",
        "Sha-hsi",
        "Shaxi",
        "Shaxi Zhen",
        "\u6c99\u6eaa\u9547"
    ],
    "name:zho_x_preferred":[
        "\u6c99\u6eaa"
    ],
    "wof:name":"Shaxi",
    "wof:placetype":"locality"
},
  "geometry": {"coordinates":[113.67068,24.61694],"type":"Point"}
}