{
  "type": "Feature",
  "properties": {
    "gn:admin1_code":"14",
    "gn:asciiname":"Chuxi",
    "gn:country_code":"CN",
    "gn:dem":3717,
    "gn:feature_class":"P",
    "gn:feature_code":"PPL",
    "gn:name":"Chuxi",
    "gn:population":0,
    "gn:timezone":"Asia/Urumqi",
    "iso:country":"CN",
    "name:bod_x_preferred":[
        "\u0f42\u0fb2\u0f74\u0f0b\u0f56\u0f5e\u0f72"
    ],
    "wof:name":"Chuxi",
    "wof:placetype":"locality"
},
  "geometry": {"coordinates":[91.42805,29.69789],"type":"Point"}
}