{
  "type": "Feature",
  "properties": {
    "gn:admin1_code":"3.0",
    "gn:asciiname":"Tangtouxia",
    "gn:country_code":"CN",
    "gn:dem":186,
    "gn:feature_class":"P",
    "gn:feature_code":"PPL",
    "gn:name":"Tangtouxia",
    "gn:population":0,
    "gn:timezone":"Asia/Shanghai",
    "iso:country":"CN",
    "name:und_x_variant":[
        "\u5858\u5934\u4e0b"
    ],
    "wof:name":"Tangtouxia",
    "wof:placetype":"locality"
},
  "geometry": {"coordinates":[115.52006000000002,25.5974],"type":"Point"}
}