{
  "type": "Feature",
  "properties": {
    "gn:admin1_code":"2.0",
    "gn:asciiname":"Beigangyao",
    "gn:country_code":"CN",
    "gn:dem":90,
    "gn:feature_class":"P",
    "gn:feature_code":"PPL",
    "gn:name":"Beigangyao",
    "gn:population":0,
    "gn:timezone":"Asia/Shanghai",
    "iso:country":"CN",
    "name:zho_x_preferred":[
        "\u5317\u7f38\u7a91"
    ],
    "wof:name":"Beigangyao",
    "wof:placetype":"locality"
},
  "geometry": {"coordinates":[119.79980999999999,28.92328],"type":"Point"}
}