{
  "type": "Feature",
  "properties": {
    "gn:admin1_code":"11.0",
    "gn:asciiname":"Yanggunao",
    "gn:country_code":"CN",
    "gn:dem":747,
    "gn:feature_class":"P",
    "gn:feature_code":"PPL",
    "gn:name":"Yanggunao",
    "gn:population":0,
    "gn:timezone":"Asia/Shanghai",
    "iso:country":"CN",
    "name:zho_x_preferred":[
        "\u7f8a\u53e4\u8111"
    ],
    "wof:name":"Yanggunao",
    "wof:placetype":"locality"
},
  "geometry": {"coordinates":[111.08165,26.43066],"type":"Point"}
}