{
  "type": "Feature",
  "properties": {
    "gn:admin1_code":"11",
    "gn:asciiname":"Dengxintang",
    "gn:country_code":"CN",
    "gn:dem":214,
    "gn:feature_class":"P",
    "gn:feature_code":"PPL",
    "gn:name":"Dengxintang",
    "gn:population":0,
    "gn:timezone":"Asia/Shanghai",
    "iso:country":"CN",
    "name:zho_x_preferred":[
        "\u706f\u82af\u5858"
    ],
    "wof:name":"Dengxintang",
    "wof:placetype":"locality"
},
  "geometry": {"coordinates":[111.92901999999999,26.90551],"type":"Point"}
}