{
  "type": "Feature",
  "properties": {
    "gn:admin1_code":"3.0",
    "gn:asciiname":"Lukengcun",
    "gn:country_code":"CN",
    "gn:dem":272,
    "gn:feature_class":"P",
    "gn:feature_code":"PPL",
    "gn:name":"Lukengcun",
    "gn:population":0,
    "gn:timezone":"Asia/Shanghai",
    "iso:country":"CN",
    "name:und_x_variant":[
        "\u7089\u5751\u6751"
    ],
    "wof:name":"Lukengcun",
    "wof:placetype":"locality"
},
  "geometry": {"coordinates":[116.25568,26.0284],"type":"Point"}
}