{
  "type": "Feature",
  "properties": {
    "gn:admin1_code":"5.0",
    "gn:asciiname":"Daheishancun",
    "gn:country_code":"CN",
    "gn:dem":272,
    "gn:feature_class":"P",
    "gn:feature_code":"PPL",
    "gn:name":"Daheishancun",
    "gn:population":0,
    "gn:timezone":"Asia/Shanghai",
    "iso:country":"CN",
    "name:zho_x_preferred":[
        "\u5927\u9ed1\u5c71\u6751"
    ],
    "wof:name":"Daheishancun",
    "wof:placetype":"locality"
},
  "geometry": {"coordinates":[126.08695,43.2405],"type":"Point"}
}