{
  "type": "Feature",
  "properties": {
    "gn:admin1_code":"19.0",
    "gn:asciiname":"Xiwa",
    "gn:country_code":"CN",
    "gn:dem":368,
    "gn:feature_class":"P",
    "gn:feature_code":"PPL",
    "gn:name":"Xiwa",
    "gn:population":0,
    "gn:timezone":"Asia/Shanghai",
    "iso:country":"CN",
    "name:und_x_variant":[
        "\u897f\u6d3c"
    ],
    "name:zho_x_preferred":[
        "\u897f\u6d3c"
    ],
    "wof:name":"Xiwa",
    "wof:placetype":"locality"
},
  "geometry": {"coordinates":[120.52746,41.98842],"type":"Point"}
}