{
  "type": "Feature",
  "properties": {
    "gn:admin1_code":"2.0",
    "gn:asciiname":"Dashanjiao",
    "gn:country_code":"CN",
    "gn:dem":77,
    "gn:feature_class":"P",
    "gn:feature_code":"PPL",
    "gn:name":"Dashanjiao",
    "gn:population":0,
    "gn:timezone":"Asia/Shanghai",
    "iso:country":"CN",
    "name:und_x_variant":[
        "\u5927\u5c71\u811a"
    ],
    "wof:name":"Dashanjiao",
    "wof:placetype":"locality"
},
  "geometry": {"coordinates":[119.62285,30.19157],"type":"Point"}
}