{
  "type": "Feature",
  "properties": {
    "gn:admin1_code":"29",
    "gn:asciiname":"Mengweng",
    "gn:country_code":"CN",
    "gn:dem":1195,
    "gn:feature_class":"P",
    "gn:feature_code":"PPL",
    "gn:name":"Mengweng",
    "gn:population":0,
    "gn:timezone":"Asia/Shanghai",
    "iso:country":"CN",
    "name:und_x_variant":[
        "Ningkiang",
        "Pan-na-meng-wang",
        "Ning-chiang",
        "Ning-chiang-she-chih-ch\u00fc",
        "Mengwang",
        "Mengweng"
    ],
    "name:zho_x_preferred":[
        "\u52d0\u7fc1"
    ],
    "wof:name":"Mengweng",
    "wof:placetype":"locality"
},
  "geometry": {"coordinates":[100.41800000000001,22.0753],"type":"Point"}
}