{
  "type": "Feature",
  "properties": {
    "gn:admin1_code":"26.0",
    "gn:asciiname":"Tianliangou",
    "gn:country_code":"CN",
    "gn:dem":1322,
    "gn:feature_class":"P",
    "gn:feature_code":"PPL",
    "gn:name":"Tianliangou",
    "gn:population":0,
    "gn:timezone":"Asia/Shanghai",
    "iso:country":"CN",
    "name:zho_x_preferred":[
        "\u7530\u8fde\u6c9f"
    ],
    "wof:name":"Tianliangou",
    "wof:placetype":"locality"
},
  "geometry": {"coordinates":[108.64395,36.63356],"type":"Point"}
}