{
  "type": "Feature",
  "properties": {
    "gn:admin1_code":"16.0",
    "gn:asciiname":"Zaiwai",
    "gn:country_code":"CN",
    "gn:dem":378,
    "gn:feature_class":"P",
    "gn:feature_code":"PPL",
    "gn:name":"Zaiwai",
    "gn:population":0,
    "gn:timezone":"Asia/Shanghai",
    "iso:country":"CN",
    "name:zho_x_preferred":[
        "\u5728\u5916"
    ],
    "wof:name":"Zaiwai",
    "wof:placetype":"locality"
},
  "geometry": {"coordinates":[106.783,23.9521],"type":"Point"}
}