{
  "type": "Feature",
  "properties": {
    "gn:admin1_code":"4.0",
    "gn:asciiname":"Sanwacun",
    "gn:country_code":"CN",
    "gn:dem":0,
    "gn:feature_class":"P",
    "gn:feature_code":"PPL",
    "gn:name":"Sanwacun",
    "gn:population":0,
    "gn:timezone":"Asia/Shanghai",
    "iso:country":"CN",
    "name:zho_x_preferred":[
        "\u4e09\u6d3c\u6751"
    ],
    "wof:name":"Sanwacun",
    "wof:placetype":"locality"
},
  "geometry": {"coordinates":[120.12291999999999,34.01208],"type":"Point"}
}