{
  "type": "Feature",
  "properties": {
    "gn:admin1_code":"16.0",
    "gn:asciiname":"Dashanjiao",
    "gn:country_code":"CN",
    "gn:dem":321,
    "gn:feature_class":"P",
    "gn:feature_code":"PPL",
    "gn:name":"Dashanjiao",
    "gn:population":0,
    "gn:timezone":"Asia/Shanghai",
    "iso:country":"CN",
    "name:zho_x_preferred":[
        "\u5927\u5c71\u811a"
    ],
    "wof:name":"Dashanjiao",
    "wof:placetype":"locality"
},
  "geometry": {"coordinates":[108.90300000000001,24.8297],"type":"Point"}
}