{
  "type": "Feature",
  "properties": {
    "gn:admin1_code":"32.0",
    "gn:asciiname":"Renba",
    "gn:country_code":"CN",
    "gn:dem":3636,
    "gn:feature_class":"P",
    "gn:feature_code":"PPL",
    "gn:name":"Renba",
    "gn:population":0,
    "gn:timezone":"Asia/Shanghai",
    "iso:country":"CN",
    "name:zho_x_preferred":[
        "\u4ec1\u575d"
    ],
    "wof:name":"Renba",
    "wof:placetype":"locality"
},
  "geometry": {"coordinates":[100.27200000000001,30.4964],"type":"Point"}
}