{
  "type": "Feature",
  "properties": {
    "gn:admin1_code":"9",
    "gn:asciiname":"Dongdazhang",
    "gn:country_code":"CN",
    "gn:dem":58,
    "gn:feature_class":"P",
    "gn:feature_code":"PPL",
    "gn:name":"Dongdazhang",
    "gn:population":0,
    "gn:timezone":"Asia/Shanghai",
    "iso:country":"CN",
    "name:zho_x_preferred":[
        "\u4e1c\u5927\u5f20"
    ],
    "wof:name":"Dongdazhang",
    "wof:placetype":"locality"
},
  "geometry": {"coordinates":[115.16800000000001,35.64572000000001],"type":"Point"}
}