{
  "type": "Feature",
  "properties": {
    "gn:admin1_code":"7",
    "gn:asciiname":"Pengwei",
    "gn:country_code":"CN",
    "gn:dem":205,
    "gn:feature_class":"P",
    "gn:feature_code":"PPL",
    "gn:name":"Pengwei",
    "gn:population":0,
    "gn:timezone":"Asia/Shanghai",
    "iso:country":"CN",
    "name:und_x_variant":[
        "\u7bf7\u5c3e"
    ],
    "wof:name":"Pengwei",
    "wof:placetype":"locality"
},
  "geometry": {"coordinates":[118.57556,27.67583],"type":"Point"}
}