{
  "type": "Feature",
  "properties": {
    "gn:admin1_code":"26.0",
    "gn:asciiname":"Xinzhuangdian",
    "gn:country_code":"CN",
    "gn:dem":615,
    "gn:feature_class":"P",
    "gn:feature_code":"PPL",
    "gn:name":"Xinzhuangdian",
    "gn:population":0,
    "gn:timezone":"Asia/Shanghai",
    "iso:country":"CN",
    "name:zho_x_preferred":[
        "\u65b0\u5e84\u70b9"
    ],
    "wof:name":"Xinzhuangdian",
    "wof:placetype":"locality"
},
  "geometry": {"coordinates":[110.21429000000001,34.54124],"type":"Point"}
}