{
  "type": "Feature",
  "properties": {
    "gn:admin1_code":"11",
    "gn:asciiname":"Linglang",
    "gn:country_code":"CN",
    "gn:dem":616,
    "gn:feature_class":"P",
    "gn:feature_code":"PPL",
    "gn:name":"Linglang",
    "gn:population":0,
    "gn:timezone":"Asia/Shanghai",
    "iso:country":"CN",
    "wof:name":"Linglang",
    "wof:placetype":"locality"
},
  "geometry": {"coordinates":[109.15582999999999,27.24667],"type":"Point"}
}