{
  "type": "Feature",
  "properties": {
    "gn:admin1_code":"3",
    "gn:asciiname":"Shangwen",
    "gn:country_code":"CN",
    "gn:dem":386,
    "gn:feature_class":"P",
    "gn:feature_code":"PPL",
    "gn:name":"Shangwen",
    "gn:population":0,
    "gn:timezone":"Asia/Shanghai",
    "iso:country":"CN",
    "name:zho_x_preferred":[
        "\u4e0a\u6587"
    ],
    "wof:name":"Shangwen",
    "wof:placetype":"locality"
},
  "geometry": {"coordinates":[114.223,26.2358],"type":"Point"}
}