{
  "type": "Feature",
  "properties": {
    "gn:admin1_code":"4.0",
    "gn:asciiname":"Shunrong",
    "gn:country_code":"CN",
    "gn:dem":5,
    "gn:feature_class":"P",
    "gn:feature_code":"PPL",
    "gn:name":"Shunrong",
    "gn:population":0,
    "gn:timezone":"Asia/Shanghai",
    "iso:country":"CN",
    "name:und_x_variant":[
        "\u987a\u8363"
    ],
    "wof:name":"Shunrong",
    "wof:placetype":"locality"
},
  "geometry": {"coordinates":[121.24195,31.99149],"type":"Point"}
}