{
  "type": "Feature",
  "properties": {
    "gn:admin1_code":"29.0",
    "gn:asciiname":"Shaditou",
    "gn:country_code":"CN",
    "gn:dem":1151,
    "gn:feature_class":"P",
    "gn:feature_code":"PPL",
    "gn:name":"Shaditou",
    "gn:population":0,
    "gn:timezone":"Asia/Shanghai",
    "iso:country":"CN",
    "name:zho_x_preferred":[
        "\u6c99\u5730\u5934"
    ],
    "wof:name":"Shaditou",
    "wof:placetype":"locality"
},
  "geometry": {"coordinates":[105.21599999999999,27.7406],"type":"Point"}
}