{
  "type": "Feature",
  "properties": {
    "gn:admin1_code":"3.0",
    "gn:asciiname":"Zhuangtou",
    "gn:country_code":"CN",
    "gn:dem":53,
    "gn:feature_class":"P",
    "gn:feature_code":"PPL",
    "gn:name":"Zhuangtou",
    "gn:population":0,
    "gn:timezone":"Asia/Shanghai",
    "iso:country":"CN",
    "name:zho_x_preferred":[
        "\u5e84\u5934"
    ],
    "wof:name":"Zhuangtou",
    "wof:placetype":"locality"
},
  "geometry": {"coordinates":[115.129,28.1114],"type":"Point"}
}