{
  "type": "Feature",
  "properties": {
    "gn:admin1_code":"15.0",
    "gn:asciiname":"Xinyao",
    "gn:country_code":"CN",
    "gn:dem":1923,
    "gn:feature_class":"P",
    "gn:feature_code":"PPL",
    "gn:name":"Xinyao",
    "gn:population":0,
    "gn:timezone":"Asia/Shanghai",
    "iso:country":"CN",
    "name:und_x_variant":[
        "\u65b0\u7a91"
    ],
    "name:vie_x_preferred":[
        "T\u00e2n dao"
    ],
    "wof:name":"Xinyao",
    "wof:placetype":"locality"
},
  "geometry": {"coordinates":[105.0587,35.49934000000001],"type":"Point"}
}