{
  "type": "Feature",
  "properties": {
    "gn:admin1_code":"26.0",
    "gn:asciiname":"Tuduiliang",
    "gn:country_code":"CN",
    "gn:dem":1294,
    "gn:feature_class":"P",
    "gn:feature_code":"PPL",
    "gn:name":"Tuduiliang",
    "gn:population":0,
    "gn:timezone":"Asia/Shanghai",
    "iso:country":"CN",
    "name:zho_x_preferred":[
        "\u571f\u5806\u6881"
    ],
    "wof:name":"Tuduiliang",
    "wof:placetype":"locality"
},
  "geometry": {"coordinates":[109.10053000000001,37.83952],"type":"Point"}
}