{
  "type": "Feature",
  "properties": {
    "gn:admin1_code":"19.0",
    "gn:asciiname":"Jinjia Fenfang",
    "gn:country_code":"CN",
    "gn:dem":220,
    "gn:feature_class":"P",
    "gn:feature_code":"PPL",
    "gn:name":"Jinjia Fenfang",
    "gn:population":0,
    "gn:timezone":"Asia/Shanghai",
    "iso:country":"CN",
    "name:und_x_variant":[
        "\u91d1\u5bb6\u7c89\u623f"
    ],
    "wof:name":"Jinjia Fenfang",
    "wof:placetype":"locality"
},
  "geometry": {"coordinates":[122.72989,40.02118],"type":"Point"}
}