{
  "type": "Feature",
  "properties": {
    "gn:admin1_code":"30",
    "gn:asciiname":"Shengtang",
    "gn:country_code":"CN",
    "gn:dem":98,
    "gn:feature_class":"P",
    "gn:feature_code":"PPL",
    "gn:name":"Shengtang",
    "gn:population":0,
    "gn:timezone":"Asia/Shanghai",
    "iso:country":"CN",
    "name:und_x_variant":[
        "Kutang",
        "Shengtang"
    ],
    "name:zho_x_preferred":[
        "\u5723\u5802"
    ],
    "wof:name":"Shengtang",
    "wof:placetype":"locality"
},
  "geometry": {"coordinates":[116.15429,24.61986],"type":"Point"}
}