{
  "type": "Feature",
  "properties": {
    "gn:admin1_code":"5.0",
    "gn:asciiname":"Xinmin",
    "gn:country_code":"CN",
    "gn:dem":357,
    "gn:feature_class":"P",
    "gn:feature_code":"PPL",
    "gn:name":"Xinmin",
    "gn:population":0,
    "gn:timezone":"Asia/Shanghai",
    "iso:country":"CN",
    "name:ceb_x_preferred":[
        "Xinmin"
    ],
    "name:deu_x_preferred":[
        "Xinmin"
    ],
    "name:mlg_x_preferred":[
        "Xinmin"
    ],
    "name:und_x_variant":[
        "\u65b0\u6c11"
    ],
    "wof:name":"Xinmin",
    "wof:placetype":"locality"
},
  "geometry": {"coordinates":[125.59848,41.46735],"type":"Point"}
}