{
  "type": "Feature",
  "properties": {
    "gn:admin1_code":"22.0",
    "gn:asciiname":"Xiaoguanzhuang",
    "gn:country_code":"CN",
    "gn:dem":42,
    "gn:feature_class":"P",
    "gn:feature_code":"PPL",
    "gn:name":"Xiaoguanzhuang",
    "gn:population":0,
    "gn:timezone":"Asia/Shanghai",
    "iso:country":"CN",
    "name:zho_x_preferred":[
        "\u5c0f\u5b98\u5e84"
    ],
    "wof:name":"Xiaoguanzhuang",
    "wof:placetype":"locality"
},
  "geometry": {"coordinates":[116.60923,40.20125],"type":"Point"}
}