{
  "type": "Feature",
  "properties": {
    "gn:admin1_code":"5.0",
    "gn:asciiname":"Yangjia Yuanzi",
    "gn:country_code":"CN",
    "gn:dem":145,
    "gn:feature_class":"P",
    "gn:feature_code":"PPL",
    "gn:name":"Yangjia Yuanzi",
    "gn:population":0,
    "gn:timezone":"Asia/Shanghai",
    "iso:country":"CN",
    "name:zho_x_preferred":[
        "\u6768\u5bb6\u56ed\u5b50"
    ],
    "wof:name":"Yangjia Yuanzi",
    "wof:placetype":"locality"
},
  "geometry": {"coordinates":[123.02124000000001,44.93848],"type":"Point"}
}