{
  "type": "Feature",
  "properties": {
    "gn:admin1_code":"1.0",
    "gn:asciiname":"Ziliucun",
    "gn:country_code":"CN",
    "gn:dem":36,
    "gn:feature_class":"P",
    "gn:feature_code":"PPL",
    "gn:name":"Ziliucun",
    "gn:population":0,
    "gn:timezone":"Asia/Shanghai",
    "iso:country":"CN",
    "name:zho_x_preferred":[
        "\u8a3e\u5218\u6751"
    ],
    "wof:name":"Ziliucun",
    "wof:placetype":"locality"
},
  "geometry": {"coordinates":[115.88697000000001,33.64695],"type":"Point"}
}