{
  "type": "Feature",
  "properties": {
    "gn:admin1_code":"11.0",
    "gn:asciiname":"Fengtangchong",
    "gn:country_code":"CN",
    "gn:dem":293,
    "gn:feature_class":"P",
    "gn:feature_code":"PPL",
    "gn:name":"Fengtangchong",
    "gn:population":0,
    "gn:timezone":"Asia/Shanghai",
    "iso:country":"CN",
    "name:zho_x_preferred":[
        "\u98ce\u5858\u51b2"
    ],
    "wof:name":"Fengtangchong",
    "wof:placetype":"locality"
},
  "geometry": {"coordinates":[111.8682,27.20678],"type":"Point"}
}