{
  "type": "Feature",
  "properties": {
    "gn:admin1_code":"11.0",
    "gn:asciiname":"Dongdiguai",
    "gn:country_code":"CN",
    "gn:dem":28,
    "gn:feature_class":"P",
    "gn:feature_code":"PPL",
    "gn:name":"Dongdiguai",
    "gn:population":0,
    "gn:timezone":"Asia/Shanghai",
    "iso:country":"CN",
    "name:zho_x_preferred":[
        "\u4e1c\u5824\u62d0"
    ],
    "wof:name":"Dongdiguai",
    "wof:placetype":"locality"
},
  "geometry": {"coordinates":[112.44217999999999,29.10688],"type":"Point"}
}