{
  "type": "Feature",
  "properties": {
    "gn:admin1_code":"31.0",
    "gn:asciiname":"Xinxiang",
    "gn:country_code":"CN",
    "gn:dem":91,
    "gn:feature_class":"P",
    "gn:feature_code":"PPL",
    "gn:name":"Xinxiang",
    "gn:population":0,
    "gn:timezone":"Asia/Shanghai",
    "iso:country":"CN",
    "name:zho_x_preferred":[
        "Xinxiang"
    ],
    "name:zho_x_variant":[
        "\u65b0\u9999"
    ],
    "wof:name":"Xinxiang",
    "wof:placetype":"locality"
},
  "geometry": {"coordinates":[110.19456,19.92264],"type":"Point"}
}