{
  "type": "Feature",
  "properties": {
    "gn:admin1_code":"1.0",
    "gn:asciiname":"Yaojia Fancun",
    "gn:country_code":"CN",
    "gn:dem":348,
    "gn:feature_class":"P",
    "gn:feature_code":"PPL",
    "gn:name":"Yaojia Fancun",
    "gn:population":0,
    "gn:timezone":"Asia/Shanghai",
    "iso:country":"CN",
    "name:zho_x_preferred":[
        "\u59da\u5bb6\u7548\u6751"
    ],
    "wof:name":"Yaojia Fancun",
    "wof:placetype":"locality"
},
  "geometry": {"coordinates":[116.21724,31.31987],"type":"Point"}
}