{
  "type": "Feature",
  "properties": {
    "gn:admin1_code":"32.0",
    "gn:asciiname":"Lengjiaba",
    "gn:country_code":"CN",
    "gn:dem":603,
    "gn:feature_class":"P",
    "gn:feature_code":"PPL",
    "gn:name":"Lengjiaba",
    "gn:population":0,
    "gn:timezone":"Asia/Shanghai",
    "iso:country":"CN",
    "name:zho_x_preferred":[
        "\u51b7\u5bb6\u575d"
    ],
    "wof:name":"Lengjiaba",
    "wof:placetype":"locality"
},
  "geometry": {"coordinates":[105.114,32.0117],"type":"Point"}
}