{
  "type": "Feature",
  "properties": {
    "gn:admin1_code":"11.0",
    "gn:asciiname":"Dongxi",
    "gn:country_code":"CN",
    "gn:dem":351,
    "gn:feature_class":"P",
    "gn:feature_code":"PPL",
    "gn:name":"Dongxi",
    "gn:population":0,
    "gn:timezone":"Asia/Shanghai",
    "iso:country":"CN",
    "name:zho_x_preferred":[
        "Dongxi"
    ],
    "name:zho_x_variant":[
        "\u6d1e\u6eaa"
    ],
    "wof:name":"Dongxi",
    "wof:placetype":"locality"
},
  "geometry": {"coordinates":[111.00299,29.35765],"type":"Point"}
}