{
  "type": "Feature",
  "properties": {
    "gn:admin1_code":"1.0",
    "gn:asciiname":"Jiwucun",
    "gn:country_code":"CN",
    "gn:dem":49,
    "gn:feature_class":"P",
    "gn:feature_code":"PPL",
    "gn:name":"Jiwucun",
    "gn:population":0,
    "gn:timezone":"Asia/Shanghai",
    "iso:country":"CN",
    "name:zho_x_preferred":[
        "\u9e21\u545c\u6751"
    ],
    "wof:name":"Jiwucun",
    "wof:placetype":"locality"
},
  "geometry": {"coordinates":[117.80934000000001,32.11695],"type":"Point"}
}