{
  "type": "Feature",
  "properties": {
    "gn:admin1_code":"24.0",
    "gn:asciiname":"Sanquansi",
    "gn:country_code":"CN",
    "gn:dem":1935,
    "gn:feature_class":"P",
    "gn:feature_code":"PPL",
    "gn:name":"Sanquansi",
    "gn:population":0,
    "gn:timezone":"Asia/Shanghai",
    "iso:country":"CN",
    "name:zho_x_preferred":[
        "\u4e09\u6cc9\u5bfa"
    ],
    "wof:name":"Sanquansi",
    "wof:placetype":"locality"
},
  "geometry": {"coordinates":[113.58037,39.01704],"type":"Point"}
}