{
  "type": "Feature",
  "properties": {
    "gn:admin1_code":"02",
    "gn:asciiname":"Lai'aocun",
    "gn:country_code":"CN",
    "gn:dem":213,
    "gn:feature_class":"P",
    "gn:feature_code":"PPL",
    "gn:name":"Lai\u2019aocun",
    "gn:population":0,
    "gn:timezone":"Asia/Shanghai",
    "iso:country":"CN",
    "name:und_x_variant":[
        "Lai\u2019ao",
        "Lai\u2019aocun"
    ],
    "name:zho_x_preferred":[
        "\u8d56\u5c99"
    ],
    "name:zho_x_variant":[
        "\u8d56\u5c99\u6751"
    ],
    "wof:name":"Lai'aocun",
    "wof:placetype":"locality"
},
  "geometry": {"coordinates":[121.38269,28.9917],"type":"Point"}
}