{
  "type": "Feature",
  "properties": {
    "gn:admin1_code":"30.0",
    "gn:asciiname":"Xiaoyan",
    "gn:country_code":"CN",
    "gn:dem":380,
    "gn:feature_class":"P",
    "gn:feature_code":"PPL",
    "gn:name":"Xiaoyan",
    "gn:population":0,
    "gn:timezone":"Asia/Shanghai",
    "iso:country":"CN",
    "name:zho_x_preferred":[
        "Xiaoyan"
    ],
    "name:zho_x_variant":[
        "\u5c0f\u773c"
    ],
    "wof:name":"Xiaoyan",
    "wof:placetype":"locality"
},
  "geometry": {"coordinates":[111.98083,24.69889],"type":"Point"}
}