{
  "type": "Feature",
  "properties": {
    "gn:admin1_code":"7.0",
    "gn:asciiname":"Yangxing",
    "gn:country_code":"CN",
    "gn:dem":476,
    "gn:feature_class":"P",
    "gn:feature_code":"PPL",
    "gn:name":"Yangxing",
    "gn:population":0,
    "gn:timezone":"Asia/Shanghai",
    "iso:country":"CN",
    "name:und_x_variant":[
        "\u9633\u661f"
    ],
    "name:zho_x_preferred":[
        "\u9633\u661f"
    ],
    "wof:name":"Yangxing",
    "wof:placetype":"locality"
},
  "geometry": {"coordinates":[118.48353,26.18928],"type":"Point"}
}