{
  "type": "Feature",
  "properties": {
    "gn:admin1_code":"30",
    "gn:asciiname":"Dingdong",
    "gn:country_code":"CN",
    "gn:dem":951,
    "gn:feature_class":"P",
    "gn:feature_code":"PPL",
    "gn:name":"Dingdong",
    "gn:population":0,
    "gn:timezone":"Asia/Shanghai",
    "iso:country":"CN",
    "name:und_x_variant":[
        "\u4e01\u6d1e"
    ],
    "wof:name":"Dingdong",
    "wof:placetype":"locality"
},
  "geometry": {"coordinates":[113.95638999999998,25.21722],"type":"Point"}
}