{
  "type": "Feature",
  "properties": {
    "gn:admin1_code":"3.0",
    "gn:asciiname":"Luoyuantou",
    "gn:country_code":"CN",
    "gn:dem":329,
    "gn:feature_class":"P",
    "gn:feature_code":"PPL",
    "gn:name":"Luoyuantou",
    "gn:population":0,
    "gn:timezone":"Asia/Shanghai",
    "iso:country":"CN",
    "name:und_x_variant":[
        "\u7f57\u6e90\u5934"
    ],
    "wof:name":"Luoyuantou",
    "wof:placetype":"locality"
},
  "geometry": {"coordinates":[116.13621000000001,26.90061],"type":"Point"}
}