{
  "type": "Feature",
  "properties": {
    "gn:admin1_code":"30",
    "gn:asciiname":"Dong'an",
    "gn:country_code":"CN",
    "gn:dem":13,
    "gn:feature_class":"P",
    "gn:feature_code":"PPL",
    "gn:name":"Dong\u2019an",
    "gn:population":0,
    "gn:timezone":"Asia/Urumqi",
    "iso:country":"CN",
    "name:zho_x_preferred":[
        "\u4e1c\u5cb8"
    ],
    "name:zho_x_variant":[
        "Dong\u2019an"
    ],
    "wof:name":"Dong'an",
    "wof:placetype":"locality"
},
  "geometry": {"coordinates":[110.19304,21.07196],"type":"Point"}
}