{
  "type": "Feature",
  "properties": {
    "gn:admin1_code":"11.0",
    "gn:asciiname":"Hejiaping",
    "gn:country_code":"CN",
    "gn:dem":166,
    "gn:feature_class":"P",
    "gn:feature_code":"PPL",
    "gn:name":"Hejiaping",
    "gn:population":0,
    "gn:timezone":"Asia/Shanghai",
    "iso:country":"CN",
    "name:zho_x_preferred":[
        "\u4f55\u5bb6\u576a"
    ],
    "wof:name":"Hejiaping",
    "wof:placetype":"locality"
},
  "geometry": {"coordinates":[113.57877000000001,27.24102],"type":"Point"}
}