{
  "type": "Feature",
  "properties": {
    "gn:admin1_code":"3.0",
    "gn:asciiname":"Liyimen",
    "gn:country_code":"CN",
    "gn:dem":465,
    "gn:feature_class":"P",
    "gn:feature_code":"PPL",
    "gn:name":"Liyimen",
    "gn:population":0,
    "gn:timezone":"Asia/Shanghai",
    "iso:country":"CN",
    "name:und_x_variant":[
        "\u793c\u4e49\u95e8"
    ],
    "wof:name":"Liyimen",
    "wof:placetype":"locality"
},
  "geometry": {"coordinates":[115.40143999999999,25.21404],"type":"Point"}
}