{
  "type": "Feature",
  "properties": {
    "gn:admin1_code":"29",
    "gn:asciiname":"Tianbadong",
    "gn:country_code":"CN",
    "gn:dem":1537,
    "gn:feature_class":"P",
    "gn:feature_code":"PPL",
    "gn:name":"Tianbadong",
    "gn:population":0,
    "gn:timezone":"Asia/Shanghai",
    "iso:country":"CN",
    "name:zho_x_preferred":[
        "\u7530\u575d\u6d1e"
    ],
    "wof:name":"Tianbadong",
    "wof:placetype":"locality"
},
  "geometry": {"coordinates":[105.14,23.6528],"type":"Point"}
}