{
  "type": "Feature",
  "properties": {
    "gn:admin1_code":"20",
    "gn:asciiname":"Hao-lu-k'u-chung-yang-ch'ang",
    "gn:country_code":"CN",
    "gn:dem":1359,
    "gn:feature_class":"P",
    "gn:feature_code":"PPL",
    "gn:name":"Hao-lu-k\u2019u-chung-yang-ch\u2019ang",
    "gn:population":0,
    "gn:timezone":"Asia/Shanghai",
    "iso:country":"CN",
    "wof:name":"Hao-lu-k'u-chung-yang-ch'ang",
    "wof:placetype":"locality"
},
  "geometry": {"coordinates":[116.71138999999999,42.92889],"type":"Point"}
}