{
  "type": "Feature",
  "properties": {
    "gn:admin1_code":"31.0",
    "gn:asciiname":"Songtian",
    "gn:country_code":"CN",
    "gn:dem":107,
    "gn:feature_class":"P",
    "gn:feature_code":"PPL",
    "gn:name":"Songtian",
    "gn:population":0,
    "gn:timezone":"Asia/Shanghai",
    "iso:country":"CN",
    "name:zho_x_preferred":[
        "Songtian"
    ],
    "name:zho_x_variant":[
        "\u677e\u7530"
    ],
    "wof:name":"Songtian",
    "wof:placetype":"locality"
},
  "geometry": {"coordinates":[110.60738000000001,19.48898],"type":"Point"}
}