{
  "type": "Feature",
  "properties": {
    "gn:admin1_code":"14.0",
    "gn:asciiname":"Duinei",
    "gn:country_code":"CN",
    "gn:dem":3894,
    "gn:feature_class":"P",
    "gn:feature_code":"PPL",
    "gn:name":"Duinei",
    "gn:population":0,
    "gn:timezone":"Asia/Urumqi",
    "iso:country":"CN",
    "name:zho_x_preferred":[
        "\u5bf9\u5185"
    ],
    "wof:name":"Duinei",
    "wof:placetype":"locality"
},
  "geometry": {"coordinates":[97.06099,30.93631],"type":"Point"}
}