{
  "type": "Feature",
  "properties": {
    "gn:admin1_code":"14",
    "gn:asciiname":"Saicun",
    "gn:country_code":"CN",
    "gn:dem":4036,
    "gn:feature_class":"P",
    "gn:feature_code":"PPL",
    "gn:name":"Saicun",
    "gn:population":0,
    "gn:timezone":"Asia/Urumqi",
    "iso:country":"CN",
    "name:zho_x_preferred":[
        "\u816e\u6751"
    ],
    "wof:name":"Saicun",
    "wof:placetype":"locality"
},
  "geometry": {"coordinates":[89.43799999999997,29.4488],"type":"Point"}
}