{
  "type": "Feature",
  "properties": {
    "gn:admin1_code":"10",
    "gn:asciiname":"Julu",
    "gn:cc2":"CN",
    "gn:country_code":"CN",
    "gn:dem":31,
    "gn:feature_class":"P",
    "gn:feature_code":"PPL",
    "gn:name":"Julu",
    "gn:population":0,
    "gn:timezone":"Asia/Shanghai",
    "iso:country":"CN",
    "name:und_x_variant":[
        "K\u00fcluhsien",
        "Ch\u00fc-lu",
        "K\u00fclu",
        "Chu-lu-k\u2019o",
        "Ch\u00fc-lu-ch\u2019eng-kuan",
        "Ch\u00fc-lu-hsien",
        "Julu"
    ],
    "wof:name":"Julu",
    "wof:placetype":"locality"
},
  "geometry": {"coordinates":[115.02333,37.2075],"type":"Point"}
}