{
  "type": "Feature",
  "properties": {
    "gn:admin1_code":"29.0",
    "gn:asciiname":"Diximi",
    "gn:country_code":"CN",
    "gn:dem":2480,
    "gn:feature_class":"P",
    "gn:feature_code":"PPL",
    "gn:name":"Diximi",
    "gn:population":0,
    "gn:timezone":"Asia/Shanghai",
    "iso:country":"CN",
    "name:zho_x_preferred":[
        "\u5730\u897f\u5bc6"
    ],
    "wof:name":"Diximi",
    "wof:placetype":"locality"
},
  "geometry": {"coordinates":[99.4868,25.7321],"type":"Point"}
}