{
  "type": "Feature",
  "properties": {
    "gn:admin1_code":"25",
    "gn:asciiname":"Bianjia",
    "gn:country_code":"CN",
    "gn:dem":10,
    "gn:feature_class":"P",
    "gn:feature_code":"PPL",
    "gn:name":"Bianjia",
    "gn:population":0,
    "gn:timezone":"Asia/Shanghai",
    "iso:country":"CN",
    "name:zho_x_preferred":[
        "\u8fb9\u5bb6"
    ],
    "wof:name":"Bianjia",
    "wof:placetype":"locality"
},
  "geometry": {"coordinates":[118.16200000000001,37.4842],"type":"Point"}
}