{
  "type": "Feature",
  "properties": {
    "gn:admin1_code":"1.0",
    "gn:asciiname":"Wazikoucun",
    "gn:country_code":"CN",
    "gn:dem":39,
    "gn:feature_class":"P",
    "gn:feature_code":"PPL",
    "gn:name":"Wazikoucun",
    "gn:population":0,
    "gn:timezone":"Asia/Shanghai",
    "iso:country":"CN",
    "name:und_x_variant":[
        "Wa-tzu-k\u2019ou",
        "Wazikou",
        "Wazikoucun"
    ],
    "name:zho_x_preferred":[
        "\u74e6\u5b50\u53e3\u6751"
    ],
    "wof:name":"Wazikoucun",
    "wof:placetype":"locality"
},
  "geometry": {"coordinates":[116.81583000000001,34.095],"type":"Point"}
}