{
  "type": "Feature",
  "properties": {
    "gn:admin1_code":"24.0",
    "gn:asciiname":"Beilou",
    "gn:country_code":"CN",
    "gn:dem":1132,
    "gn:feature_class":"P",
    "gn:feature_code":"PPL",
    "gn:name":"Beilou",
    "gn:population":0,
    "gn:timezone":"Asia/Shanghai",
    "iso:country":"CN",
    "name:und_x_variant":[
        "\u5317\u697c"
    ],
    "wof:name":"Beilou",
    "wof:placetype":"locality"
},
  "geometry": {"coordinates":[113.42768999999998,39.52992],"type":"Point"}
}