{
  "type": "Feature",
  "properties": {
    "gn:admin1_code":"26",
    "gn:asciiname":"Po'ertou",
    "gn:country_code":"CN",
    "gn:dem":413,
    "gn:feature_class":"P",
    "gn:feature_code":"PPL",
    "gn:name":"Po\u2019ertou",
    "gn:population":0,
    "gn:timezone":"Asia/Shanghai",
    "iso:country":"CN",
    "name:und_x_variant":[
        "Po\u2019ertou",
        "\u5761\u8033\u5934"
    ],
    "name:zho_x_preferred":[
        "\u5761\u8033\u5934"
    ],
    "wof:name":"Po'ertou",
    "wof:placetype":"locality"
},
  "geometry": {"coordinates":[108.41139,34.24056],"type":"Point"}
}