{
  "type": "Feature",
  "properties": {
    "gn:admin1_code":"11.0",
    "gn:asciiname":"Dujiawan",
    "gn:country_code":"CN",
    "gn:dem":103,
    "gn:feature_class":"P",
    "gn:feature_code":"PPL",
    "gn:name":"Dujiawan",
    "gn:population":0,
    "gn:timezone":"Asia/Shanghai",
    "iso:country":"CN",
    "name:zho_x_preferred":[
        "Dujiawan"
    ],
    "name:zho_x_variant":[
        "\u675c\u5bb6\u6e7e"
    ],
    "wof:name":"Dujiawan",
    "wof:placetype":"locality"
},
  "geometry": {"coordinates":[111.54824000000001,29.18849],"type":"Point"}
}