{
  "type": "Feature",
  "properties": {
    "gn:admin1_code":"10",
    "gn:asciiname":"Dongsirang",
    "gn:country_code":"CN",
    "gn:dem":2020,
    "gn:feature_class":"P",
    "gn:feature_code":"PPL",
    "gn:name":"Dongsirang",
    "gn:population":0,
    "gn:timezone":"Asia/Shanghai",
    "iso:country":"CN",
    "wof:name":"Dongsirang",
    "wof:placetype":"locality"
},
  "geometry": {"coordinates":[114.76944,39.77861],"type":"Point"}
}