{
  "type": "Feature",
  "properties": {
    "gn:admin1_code":"25",
    "gn:asciiname":"Rentougu",
    "gn:country_code":"CN",
    "gn:dem":336,
    "gn:feature_class":"P",
    "gn:feature_code":"PPL",
    "gn:name":"Rentougu",
    "gn:population":0,
    "gn:timezone":"Asia/Shanghai",
    "iso:country":"CN",
    "name:zho_x_preferred":[
        "\u4eba\u5934\u5d2e"
    ],
    "wof:name":"Rentougu",
    "wof:placetype":"locality"
},
  "geometry": {"coordinates":[120.62862,36.24551],"type":"Point"}
}