{
  "type": "Feature",
  "properties": {
    "gn:admin1_code":"02",
    "gn:asciiname":"Shuangjietian",
    "gn:country_code":"CN",
    "gn:dem":471,
    "gn:feature_class":"P",
    "gn:feature_code":"PPL",
    "gn:name":"Shuangjietian",
    "gn:population":0,
    "gn:timezone":"Asia/Shanghai",
    "iso:country":"CN",
    "name:zho_x_preferred":[
        "\u53cc\u754c\u7530"
    ],
    "wof:name":"Shuangjietian",
    "wof:placetype":"locality"
},
  "geometry": {"coordinates":[120.44476,27.98067],"type":"Point"}
}