{
  "type": "Feature",
  "properties": {
    "gn:admin1_code":"3.0",
    "gn:asciiname":"Xiawushi",
    "gn:country_code":"CN",
    "gn:dem":29,
    "gn:feature_class":"P",
    "gn:feature_code":"PPL",
    "gn:name":"Xiawushi",
    "gn:population":0,
    "gn:timezone":"Asia/Shanghai",
    "iso:country":"CN",
    "name:und_x_variant":[
        "\u4e0b\u5c4b\u77f3"
    ],
    "wof:name":"Xiawushi",
    "wof:placetype":"locality"
},
  "geometry": {"coordinates":[116.49041,29.77699],"type":"Point"}
}