{
  "type": "Feature",
  "properties": {
    "gn:admin1_code":"30.0",
    "gn:asciiname":"Matizhai",
    "gn:country_code":"CN",
    "gn:dem":69,
    "gn:feature_class":"P",
    "gn:feature_code":"PPL",
    "gn:name":"Matizhai",
    "gn:population":0,
    "gn:timezone":"Asia/Shanghai",
    "iso:country":"CN",
    "name:zho_x_preferred":[
        "\u9a6c\u8e44\u5be8"
    ],
    "wof:name":"Matizhai",
    "wof:placetype":"locality"
},
  "geometry": {"coordinates":[113.15806000000001,24.33694],"type":"Point"}
}