{
  "type": "Feature",
  "properties": {
    "gn:admin1_code":"19.0",
    "gn:asciiname":"Shengshuitun",
    "gn:country_code":"CN",
    "gn:dem":79,
    "gn:feature_class":"P",
    "gn:feature_code":"PPL",
    "gn:name":"Shengshuitun",
    "gn:population":0,
    "gn:timezone":"Asia/Shanghai",
    "iso:country":"CN",
    "name:zho_x_preferred":[
        "\u80dc\u6c34\u5c6f"
    ],
    "wof:name":"Shengshuitun",
    "wof:placetype":"locality"
},
  "geometry": {"coordinates":[122.343,42.1556],"type":"Point"}
}