{
  "type": "Feature",
  "properties": {
    "gn:admin1_code":"29.0",
    "gn:asciiname":"Henibai",
    "gn:country_code":"CN",
    "gn:dem":596,
    "gn:feature_class":"P",
    "gn:feature_code":"PPL",
    "gn:name":"Henibai",
    "gn:population":0,
    "gn:timezone":"Asia/Shanghai",
    "iso:country":"CN",
    "name:zho_x_preferred":[
        "\u8d3a\u6ce5\u767d"
    ],
    "wof:name":"Henibai",
    "wof:placetype":"locality"
},
  "geometry": {"coordinates":[103.93000000000001,22.9372],"type":"Point"}
}