{
  "type": "Feature",
  "properties": {
    "gn:admin1_code":"16.0",
    "gn:asciiname":"Zhonglian",
    "gn:country_code":"CN",
    "gn:dem":166,
    "gn:feature_class":"P",
    "gn:feature_code":"PPL",
    "gn:name":"Zhonglian",
    "gn:population":0,
    "gn:timezone":"Asia/Shanghai",
    "iso:country":"CN",
    "name:zho_x_preferred":[
        "\u4f17\u8054"
    ],
    "wof:name":"Zhonglian",
    "wof:placetype":"locality"
},
  "geometry": {"coordinates":[108.40900000000001,24.4945],"type":"Point"}
}