{
  "type": "Feature",
  "properties": {
    "gn:admin1_code":"1.0",
    "gn:asciiname":"Lougecun",
    "gn:country_code":"CN",
    "gn:dem":26,
    "gn:feature_class":"P",
    "gn:feature_code":"PPL",
    "gn:name":"Lougecun",
    "gn:population":0,
    "gn:timezone":"Asia/Shanghai",
    "iso:country":"CN",
    "name:zho_x_preferred":[
        "\u697c\u9601\u6751"
    ],
    "wof:name":"Lougecun",
    "wof:placetype":"locality"
},
  "geometry": {"coordinates":[117.00400999999999,30.42816],"type":"Point"}
}