{
  "type": "Feature",
  "properties": {
    "gn:admin1_code":"9.0",
    "gn:asciiname":"Baisheyan",
    "gn:country_code":"CN",
    "gn:dem":73,
    "gn:feature_class":"P",
    "gn:feature_code":"PPL",
    "gn:name":"Baisheyan",
    "gn:population":0,
    "gn:timezone":"Asia/Shanghai",
    "iso:country":"CN",
    "name:zho_x_preferred":[
        "\u767d\u86c7\u5830"
    ],
    "wof:name":"Baisheyan",
    "wof:placetype":"locality"
},
  "geometry": {"coordinates":[115.52061,31.99151],"type":"Point"}
}