{
  "type": "Feature",
  "properties": {
    "gn:admin1_code":"14.0",
    "gn:asciiname":"Zhaxikangsar",
    "gn:country_code":"CN",
    "gn:dem":4159,
    "gn:feature_class":"P",
    "gn:feature_code":"PPL",
    "gn:name":"Zhaxikangsar",
    "gn:population":0,
    "gn:timezone":"Asia/Urumqi",
    "iso:country":"CN",
    "name:bod_x_preferred":[
        "Zhaxikangsar"
    ],
    "name:zho_x_preferred":[
        "Zhaxikangsha"
    ],
    "name:zho_x_variant":[
        "\u624e\u897f\u5eb7\u6c99",
        "Jialuo Gongshe",
        "\u52a0\u6d1b\u516c\u793e"
    ],
    "wof:name":"Zhaxikangsar",
    "wof:placetype":"locality"
},
  "geometry": {"coordinates":[92.303,28.403],"type":"Point"}
}