{
  "type": "Feature",
  "properties": {
    "gn:admin1_code":"14.0",
    "gn:asciiname":"Bugang",
    "gn:country_code":"CN",
    "gn:dem":4657,
    "gn:feature_class":"P",
    "gn:feature_code":"PPL",
    "gn:name":"Bugang",
    "gn:population":0,
    "gn:timezone":"Asia/Urumqi",
    "iso:country":"CN",
    "name:zho_x_preferred":[
        "\u5e03\u5c97"
    ],
    "wof:name":"Bugang",
    "wof:placetype":"locality"
},
  "geometry": {"coordinates":[87.2009,31.3342],"type":"Point"}
}