{
  "type": "Feature",
  "properties": {
    "gn:admin1_code":"19.0",
    "gn:asciiname":"Tumenzicun",
    "gn:country_code":"CN",
    "gn:dem":65,
    "gn:feature_class":"P",
    "gn:feature_code":"PPL",
    "gn:name":"Tumenzicun",
    "gn:population":0,
    "gn:timezone":"Asia/Shanghai",
    "iso:country":"CN",
    "name:zho_x_preferred":[
        "\u571f\u95e8\u5b50\u6751"
    ],
    "wof:name":"Tumenzicun",
    "wof:placetype":"locality"
},
  "geometry": {"coordinates":[121.92053,39.30227],"type":"Point"}
}