{
  "type": "Feature",
  "properties": {
    "gn:admin1_code":"19.0",
    "gn:asciiname":"Chudiancun",
    "gn:country_code":"CN",
    "gn:dem":49,
    "gn:feature_class":"P",
    "gn:feature_code":"PPL",
    "gn:name":"Chudiancun",
    "gn:population":0,
    "gn:timezone":"Asia/Shanghai",
    "iso:country":"CN",
    "name:zho_x_preferred":[
        "\u521d\u5e97\u6751"
    ],
    "wof:name":"Chudiancun",
    "wof:placetype":"locality"
},
  "geometry": {"coordinates":[122.37,39.65288],"type":"Point"}
}