{
  "type": "Feature",
  "properties": {
    "gn:admin1_code":"18.0",
    "gn:asciiname":"Lucheng",
    "gn:country_code":"CN",
    "gn:dem":1094,
    "gn:feature_class":"P",
    "gn:feature_code":"PPL",
    "gn:name":"Lucheng",
    "gn:population":0,
    "gn:timezone":"Asia/Shanghai",
    "iso:country":"CN",
    "name:ceb_x_preferred":[
        "Lucheng"
    ],
    "name:deu_x_preferred":[
        "Lucheng"
    ],
    "name:fra_x_preferred":[
        "Lucheng"
    ],
    "name:mlg_x_preferred":[
        "Lucheng"
    ],
    "name:nor_x_preferred":[
        "Lucheng"
    ],
    "name:rus_x_preferred":[
        "\u041b\u0443\u0447\u044d\u043d"
    ],
    "name:swe_x_preferred":[
        "Lucheng"
    ],
    "wof:name":"Lucheng",
    "wof:placetype":"locality"
},
  "geometry": {"coordinates":[106.65639,28.4675],"type":"Point"}
}