{
  "type": "Feature",
  "properties": {
    "gn:admin1_code":"19.0",
    "gn:asciiname":"Xujiatun",
    "gn:country_code":"CN",
    "gn:dem":96,
    "gn:feature_class":"P",
    "gn:feature_code":"PPL",
    "gn:name":"Xujiatun",
    "gn:population":0,
    "gn:timezone":"Asia/Shanghai",
    "iso:country":"CN",
    "name:und_x_variant":[
        "\u8bb8\u5bb6\u5c6f"
    ],
    "name:zho_x_preferred":[
        "\u8bb8\u5bb6\u5c6f"
    ],
    "wof:name":"Xujiatun",
    "wof:placetype":"locality"
},
  "geometry": {"coordinates":[122.58705,39.9643],"type":"Point"}
}