{
  "type": "Feature",
  "properties": {
    "gn:admin1_code":"3.0",
    "gn:asciiname":"Jingdong",
    "gn:country_code":"CN",
    "gn:dem":189,
    "gn:feature_class":"P",
    "gn:feature_code":"PPL",
    "gn:name":"Jingdong",
    "gn:population":0,
    "gn:timezone":"Asia/Shanghai",
    "iso:country":"CN",
    "name:und_x_variant":[
        "\u9756\u4e1c"
    ],
    "wof:name":"Jingdong",
    "wof:placetype":"locality"
},
  "geometry": {"coordinates":[115.51665,25.65102000000001],"type":"Point"}
}