{
  "type": "Feature",
  "properties": {
    "gn:admin1_code":"25",
    "gn:asciiname":"Fushansuo",
    "gn:country_code":"CN",
    "gn:dem":17,
    "gn:feature_class":"P",
    "gn:feature_code":"PPL",
    "gn:name":"Fushansuo",
    "gn:population":0,
    "gn:timezone":"Asia/Shanghai",
    "iso:country":"CN",
    "name:und_x_variant":[
        "Fu-shan-so",
        "Fushansuo"
    ],
    "name:zho_x_preferred":[
        "\u6d6e\u5c71\u6240"
    ],
    "wof:name":"Fushansuo",
    "wof:placetype":"locality"
},
  "geometry": {"coordinates":[120.37972000000001,36.07],"type":"Point"}
}