{
  "type": "Feature",
  "properties": {
    "gn:admin1_code":"23.0",
    "gn:asciiname":"Guanjian Erdui",
    "gn:country_code":"CN",
    "gn:dem":5,
    "gn:feature_class":"P",
    "gn:feature_code":"PPLF",
    "gn:name":"Guanjian Erdui",
    "gn:population":0,
    "gn:timezone":"Asia/Shanghai",
    "iso:country":"CN",
    "name:zho_x_preferred":[
        "Guanjian Erdui"
    ],
    "name:zho_x_variant":[
        "\u5b98\u5c16\u4e8c\u961f"
    ],
    "wof:name":"Guanjian Erdui",
    "wof:placetype":"locality"
},
  "geometry": {"coordinates":[121.46278,31.64585],"type":"Point"}
}