{
  "type": "Feature",
  "properties": {
    "gn:admin1_code":"30",
    "gn:asciiname":"Changjipo",
    "gn:country_code":"CN",
    "gn:dem":63,
    "gn:feature_class":"P",
    "gn:feature_code":"PPL",
    "gn:name":"Changjipo",
    "gn:population":0,
    "gn:timezone":"Asia/Urumqi",
    "iso:country":"CN",
    "name:zho_x_preferred":[
        "\u957f\u9e21\u5761"
    ],
    "wof:name":"Changjipo",
    "wof:placetype":"locality"
},
  "geometry": {"coordinates":[110.83790999999999,22.09913],"type":"Point"}
}