{
  "type": "Feature",
  "properties": {
    "gn:admin1_code":"30.0",
    "gn:asciiname":"Gaoshiyang",
    "gn:country_code":"CN",
    "gn:dem":440,
    "gn:feature_class":"P",
    "gn:feature_code":"PPL",
    "gn:name":"Gaoshiyang",
    "gn:population":0,
    "gn:timezone":"Asia/Shanghai",
    "iso:country":"CN",
    "name:zho_x_preferred":[
        "\u9ad8\u4ed5\u6d0b"
    ],
    "wof:name":"Gaoshiyang",
    "wof:placetype":"locality"
},
  "geometry": {"coordinates":[115.48862,23.3619],"type":"Point"}
}