{
  "type": "Feature",
  "properties": {
    "gn:admin1_code":"14.0",
    "gn:asciiname":"Lazhaxue",
    "gn:country_code":"CN",
    "gn:dem":4160,
    "gn:feature_class":"P",
    "gn:feature_code":"PPL",
    "gn:name":"Lazhaxue",
    "gn:population":0,
    "gn:timezone":"Asia/Urumqi",
    "iso:country":"CN",
    "name:zho_x_preferred":[
        "\u62c9\u624e\u8840"
    ],
    "wof:name":"Lazhaxue",
    "wof:placetype":"locality"
},
  "geometry": {"coordinates":[96.88432,31.70957000000001],"type":"Point"}
}