{
  "type": "Feature",
  "properties": {
    "gn:admin1_code":"8.0",
    "gn:asciiname":"Shengli Shidui",
    "gn:country_code":"CN",
    "gn:dem":259,
    "gn:feature_class":"P",
    "gn:feature_code":"PPLF",
    "gn:name":"Shengli Shidui",
    "gn:population":0,
    "gn:timezone":"Asia/Shanghai",
    "iso:country":"CN",
    "name:zho_x_preferred":[
        "\u80dc\u5229\u5341\u961f"
    ],
    "wof:name":"Shengli Shidui",
    "wof:placetype":"locality"
},
  "geometry": {"coordinates":[125.06453999999999,48.6746],"type":"Point"}
}