{
  "type": "Feature",
  "properties": {
    "gn:admin1_code":"2.0",
    "gn:asciiname":"Zhidubiao",
    "gn:country_code":"CN",
    "gn:dem":780,
    "gn:feature_class":"P",
    "gn:feature_code":"PPL",
    "gn:name":"Zhidubiao",
    "gn:population":0,
    "gn:timezone":"Asia/Shanghai",
    "iso:country":"CN",
    "name:zho_x_preferred":[
        "\u829d\u809a\u8868"
    ],
    "wof:name":"Zhidubiao",
    "wof:placetype":"locality"
},
  "geometry": {"coordinates":[119.43503,28.81502],"type":"Point"}
}