{
  "type": "Feature",
  "properties": {
    "gn:admin1_code":"6.0",
    "gn:asciiname":"Kanze",
    "gn:country_code":"CN",
    "gn:dem":2261,
    "gn:feature_class":"P",
    "gn:feature_code":"PPL",
    "gn:name":"Kanze",
    "gn:population":0,
    "gn:timezone":"Asia/Shanghai",
    "iso:country":"CN",
    "name:zho_x_preferred":[
        "\u574e\u5219"
    ],
    "wof:name":"Kanze",
    "wof:placetype":"locality"
},
  "geometry": {"coordinates":[101.71679,36.14039],"type":"Point"}
}