{
  "type": "Feature",
  "properties": {
    "gn:admin1_code":"2.0",
    "gn:asciiname":"Liu Dadui",
    "gn:country_code":"CN",
    "gn:dem":17,
    "gn:feature_class":"P",
    "gn:feature_code":"PPLF",
    "gn:name":"Liu Dadui",
    "gn:population":0,
    "gn:timezone":"Asia/Shanghai",
    "iso:country":"CN",
    "name:zho_x_preferred":[
        "\u516d\u5927\u961f"
    ],
    "wof:name":"Liu Dadui",
    "wof:placetype":"locality"
},
  "geometry": {"coordinates":[121.38173999999999,29.15519],"type":"Point"}
}