{
  "type": "Feature",
  "properties": {
    "gn:admin1_code":"26.0",
    "gn:asciiname":"Wujiayuan",
    "gn:country_code":"CN",
    "gn:dem":1200,
    "gn:feature_class":"P",
    "gn:feature_code":"PPL",
    "gn:name":"Wujiayuan",
    "gn:population":0,
    "gn:timezone":"Asia/Shanghai",
    "iso:country":"CN",
    "name:und_x_variant":[
        "\u6b66\u5bb6\u9662"
    ],
    "wof:name":"Wujiayuan",
    "wof:placetype":"locality"
},
  "geometry": {"coordinates":[106.24261,33.24107],"type":"Point"}
}