{
  "type": "Feature",
  "properties": {
    "gn:admin1_code":"26.0",
    "gn:asciiname":"Zhaojiamao",
    "gn:cc2":"CN",
    "gn:country_code":"CN",
    "gn:dem":1212,
    "gn:feature_class":"P",
    "gn:feature_code":"PPL",
    "gn:name":"Zhaojiamao",
    "gn:population":0,
    "gn:timezone":"Asia/Shanghai",
    "iso:country":"CN",
    "name:und_x_variant":[
        "Chao-chia-mao",
        "Zhaojiamao"
    ],
    "wof:name":"Zhaojiamao",
    "wof:placetype":"locality"
},
  "geometry": {"coordinates":[110.11667,38.48333],"type":"Point"}
}