{
  "type": "Feature",
  "properties": {
    "gn:admin1_code":"16.0",
    "gn:asciiname":"Longding",
    "gn:country_code":"CN",
    "gn:dem":171,
    "gn:feature_class":"P",
    "gn:feature_code":"PPL",
    "gn:name":"Longding",
    "gn:population":0,
    "gn:timezone":"Asia/Shanghai",
    "iso:country":"CN",
    "name:tgl_x_preferred":[
        "Longding"
    ],
    "name:urd_x_preferred":[
        "\u0644\u0648\u0646\u06af\u0688\u0646\u06af"
    ],
    "name:zho_x_preferred":[
        "\u9f99\u5b9a"
    ],
    "wof:name":"Longding",
    "wof:placetype":"locality"
},
  "geometry": {"coordinates":[110.523,24.1073],"type":"Point"}
}