{
  "type": "Feature",
  "properties": {
    "gn:admin1_code":"4.0",
    "gn:asciiname":"Baimao",
    "gn:country_code":"CN",
    "gn:dem":5,
    "gn:feature_class":"P",
    "gn:feature_code":"PPL",
    "gn:name":"Baimao",
    "gn:population":0,
    "gn:timezone":"Asia/Shanghai",
    "iso:country":"CN",
    "name:zho_x_preferred":[
        "\u767d\u8305"
    ],
    "wof:name":"Baimao",
    "wof:placetype":"locality"
},
  "geometry": {"coordinates":[120.06777,31.78673],"type":"Point"}
}