{
  "type": "Feature",
  "properties": {
    "gn:admin1_code":"32.0",
    "gn:asciiname":"Kele",
    "gn:country_code":"CN",
    "gn:dem":2721,
    "gn:feature_class":"P",
    "gn:feature_code":"PPL",
    "gn:name":"Kele",
    "gn:population":0,
    "gn:timezone":"Asia/Shanghai",
    "iso:country":"CN",
    "name:zho_x_preferred":[
        "\u514b\u52d2"
    ],
    "wof:name":"Kele",
    "wof:placetype":"locality"
},
  "geometry": {"coordinates":[102.786,28.3576],"type":"Point"}
}