{
  "type": "Feature",
  "properties": {
    "gn:admin1_code":"33.0",
    "gn:asciiname":"Shangheba",
    "gn:country_code":"CN",
    "gn:dem":770,
    "gn:feature_class":"P",
    "gn:feature_code":"PPL",
    "gn:name":"Shangheba",
    "gn:population":0,
    "gn:timezone":"Asia/Shanghai",
    "iso:country":"CN",
    "name:zho_x_preferred":[
        "\u4e0a\u6cb3\u575d"
    ],
    "wof:name":"Shangheba",
    "wof:placetype":"locality"
},
  "geometry": {"coordinates":[108.88028,28.25635],"type":"Point"}
}