{
  "type": "Feature",
  "properties": {
    "gn:admin1_code":"9.0",
    "gn:asciiname":"Beichenzhuangcun",
    "gn:country_code":"CN",
    "gn:dem":66,
    "gn:feature_class":"P",
    "gn:feature_code":"PPL",
    "gn:name":"Beichenzhuangcun",
    "gn:population":0,
    "gn:timezone":"Asia/Shanghai",
    "iso:country":"CN",
    "name:zho_x_preferred":[
        "\u5317\u9648\u5e84\u6751"
    ],
    "wof:name":"Beichenzhuangcun",
    "wof:placetype":"locality"
},
  "geometry": {"coordinates":[113.91974,33.92652],"type":"Point"}
}