{
  "type": "Feature",
  "properties": {
    "gn:country":"CN",
    "gn:fcode":"ADM3",
    "gn:population":0,
    "iso:country":"CN",
    "name:und_x_variant":[
        "Hsing-ning Hsien"
    ],
    "name:zho_x_preferred":[
        "\u5174\u5b81\u5e02"
    ],
    "name:zho_x_variant":[
        "\u5174\u5b81"
    ],
    "qs:name":"Xingning Shi",
    "qs:photos_9r":0,
    "qs:photos_sr":0,
    "qs:pop_sr":"0",
    "wof:name":"Xingning Shi",
    "wof:placetype":"localadmin",
    "wof:population":0
},
  "geometry": {"coordinates":[115.73904,24.26197],"type":"Point"}
}