{
  "type": "Feature",
  "properties": {
    "gn:admin1_code":"11",
    "gn:asciiname":"Changtang Yaozuxiang",
    "gn:country_code":"CN",
    "gn:dem":470,
    "gn:feature_class":"P",
    "gn:feature_code":"PPL",
    "gn:name":"Changtang Yaozuxiang",
    "gn:population":0,
    "gn:timezone":"Asia/Shanghai",
    "iso:country":"CN",
    "wof:name":"Changtang Yaozuxiang",
    "wof:placetype":"locality"
},
  "geometry": {"coordinates":[110.52443999999998,27.11444],"type":"Point"}
}