{
  "type": "Feature",
  "properties": {
    "gn:admin1_code":"26",
    "gn:asciiname":"Tongjiashan",
    "gn:country_code":"CN",
    "gn:dem":996,
    "gn:feature_class":"P",
    "gn:feature_code":"PPL",
    "gn:name":"Tongjiashan",
    "gn:population":0,
    "gn:timezone":"Asia/Shanghai",
    "iso:country":"CN",
    "name:und_x_variant":[
        "\u6850\u5bb6\u5c71"
    ],
    "name:zho_x_preferred":[
        "\u6850\u5bb6\u5c71"
    ],
    "wof:name":"Tongjiashan",
    "wof:placetype":"locality"
},
  "geometry": {"coordinates":[108.15611,34.73111],"type":"Point"}
}