{
  "type": "Feature",
  "properties": {
    "gn:admin1_code":"19.0",
    "gn:asciiname":"Jinchang",
    "gn:country_code":"CN",
    "gn:dem":163,
    "gn:feature_class":"P",
    "gn:feature_code":"PPL",
    "gn:name":"Jinchang",
    "gn:population":0,
    "gn:timezone":"Asia/Shanghai",
    "iso:country":"CN",
    "name:und_x_variant":[
        "\u91d1\u5382"
    ],
    "name:zho_x_preferred":[
        "\u91d1\u5382"
    ],
    "wof:name":"Jinchang",
    "wof:placetype":"locality"
},
  "geometry": {"coordinates":[123.19074000000001,40.91679],"type":"Point"}
}