{
  "type": "Feature",
  "properties": {
    "gn:admin1_code":"12.0",
    "gn:asciiname":"Luozhongsi",
    "gn:country_code":"CN",
    "gn:dem":858,
    "gn:feature_class":"P",
    "gn:feature_code":"PPL",
    "gn:name":"Luozhongsi",
    "gn:population":0,
    "gn:timezone":"Asia/Shanghai",
    "iso:country":"CN",
    "name:zho_x_preferred":[
        "\u843d\u949f\u5bfa"
    ],
    "wof:name":"Luozhongsi",
    "wof:placetype":"locality"
},
  "geometry": {"coordinates":[110.41204,31.13921],"type":"Point"}
}