{
  "type": "Feature",
  "properties": {
    "gn:admin1_code":"31.0",
    "gn:asciiname":"Nanqiu",
    "gn:country_code":"CN",
    "gn:dem":231,
    "gn:feature_class":"P",
    "gn:feature_code":"PPL",
    "gn:name":"Nanqiu",
    "gn:population":0,
    "gn:timezone":"Asia/Shanghai",
    "iso:country":"CN",
    "name:und_x_variant":[
        "\u5357\u4e18"
    ],
    "name:zho_x_preferred":[
        "\u5357\u4e18"
    ],
    "wof:name":"Nanqiu",
    "wof:placetype":"locality"
},
  "geometry": {"coordinates":[110.02267999999999,19.03394],"type":"Point"}
}