{
  "type": "Feature",
  "properties": {
    "gn:admin1_code":"24.0",
    "gn:asciiname":"Hongyangou",
    "gn:country_code":"CN",
    "gn:dem":1889,
    "gn:feature_class":"P",
    "gn:feature_code":"PPL",
    "gn:name":"Hongyangou",
    "gn:population":0,
    "gn:timezone":"Asia/Shanghai",
    "iso:country":"CN",
    "name:zho_x_preferred":[
        "\u7ea2\u773c\u6c9f"
    ],
    "wof:name":"Hongyangou",
    "wof:placetype":"locality"
},
  "geometry": {"coordinates":[111.70543000000001,38.68828],"type":"Point"}
}