{
  "type": "Feature",
  "properties": {
    "gn:admin1_code":"11.0",
    "gn:asciiname":"Zhengtouchong",
    "gn:country_code":"CN",
    "gn:dem":698,
    "gn:feature_class":"P",
    "gn:feature_code":"PPL",
    "gn:name":"Zhengtouchong",
    "gn:population":0,
    "gn:timezone":"Asia/Shanghai",
    "iso:country":"CN",
    "name:zho_x_preferred":[
        "\u6b63\u5934\u51b2"
    ],
    "wof:name":"Zhengtouchong",
    "wof:placetype":"locality"
},
  "geometry": {"coordinates":[109.84613,26.62318],"type":"Point"}
}