{
  "type": "Feature",
  "properties": {
    "gn:admin1_code":"24.0",
    "gn:asciiname":"Nianpinghui",
    "gn:country_code":"CN",
    "gn:dem":1007,
    "gn:feature_class":"P",
    "gn:feature_code":"PPL",
    "gn:name":"Nianpinghui",
    "gn:population":0,
    "gn:timezone":"Asia/Shanghai",
    "iso:country":"CN",
    "name:zho_x_preferred":[
        "\u78be\u576a\u4f1a"
    ],
    "wof:name":"Nianpinghui",
    "wof:placetype":"locality"
},
  "geometry": {"coordinates":[110.68982,38.22232],"type":"Point"}
}