{
  "type": "Feature",
  "properties": {
    "gn:admin1_code":"18",
    "gn:asciiname":"Ranjiaba",
    "gn:country_code":"CN",
    "gn:dem":658,
    "gn:feature_class":"P",
    "gn:feature_code":"PPL",
    "gn:name":"Ranjiaba",
    "gn:population":0,
    "gn:timezone":"Asia/Shanghai",
    "iso:country":"CN",
    "name:zho_x_preferred":[
        "\u5189\u5bb6\u575d"
    ],
    "wof:name":"Ranjiaba",
    "wof:placetype":"locality"
},
  "geometry": {"coordinates":[108.429,28.1001],"type":"Point"}
}