{
  "type": "Feature",
  "properties": {
    "gn:admin1_code":"9.0",
    "gn:asciiname":"Dongjiapo",
    "gn:country_code":"CN",
    "gn:dem":916,
    "gn:feature_class":"P",
    "gn:feature_code":"PPL",
    "gn:name":"Dongjiapo",
    "gn:population":0,
    "gn:timezone":"Asia/Shanghai",
    "iso:country":"CN",
    "name:zho_x_preferred":[
        "\u4e1c\u5bb6\u5761"
    ],
    "wof:name":"Dongjiapo",
    "wof:placetype":"locality"
},
  "geometry": {"coordinates":[111.15448000000001,34.57621],"type":"Point"}
}