{
  "type": "Feature",
  "properties": {
    "gn:admin1_code":"04",
    "gn:asciiname":"Miaotou",
    "gn:cc2":"CN",
    "gn:country_code":"CN",
    "gn:dem":9,
    "gn:feature_class":"P",
    "gn:feature_code":"PPL",
    "gn:name":"Miaotou",
    "gn:population":0,
    "gn:timezone":"Asia/Shanghai",
    "iso:country":"CN",
    "name:und_x_variant":[
        "Miao-t\u2019ou-chen",
        "Miaotou"
    ],
    "wof:name":"Miaotou",
    "wof:placetype":"locality"
},
  "geometry": {"coordinates":[118.69056,34.20639],"type":"Point"}
}