{
  "type": "Feature",
  "properties": {
    "gn:admin1_code":"30.0",
    "gn:asciiname":"Xiazhuangcun",
    "gn:country_code":"CN",
    "gn:dem":13,
    "gn:feature_class":"P",
    "gn:feature_code":"PPL",
    "gn:name":"Xiazhuangcun",
    "gn:population":0,
    "gn:timezone":"Asia/Shanghai",
    "iso:country":"CN",
    "name:zho_x_preferred":[
        "\u4e0b\u5e84\u6751"
    ],
    "wof:name":"Xiazhuangcun",
    "wof:placetype":"locality"
},
  "geometry": {"coordinates":[116.65676999999999,23.57833],"type":"Point"}
}