{
  "type": "Feature",
  "properties": {
    "gn:admin1_code":"9.0",
    "gn:asciiname":"Jingmeidian",
    "gn:country_code":"CN",
    "gn:dem":52,
    "gn:feature_class":"P",
    "gn:feature_code":"PPL",
    "gn:name":"Jingmeidian",
    "gn:population":0,
    "gn:timezone":"Asia/Shanghai",
    "iso:country":"CN",
    "name:zho_x_preferred":[
        "\u666f\u7f8e\u5e97"
    ],
    "wof:name":"Jingmeidian",
    "wof:placetype":"locality"
},
  "geometry": {"coordinates":[114.70092,32.19643],"type":"Point"}
}