{
  "type": "Feature",
  "properties": {
    "gn:admin1_code":"14",
    "gn:asciiname":"Kangma",
    "gn:country_code":"CN",
    "gn:dem":4189,
    "gn:feature_class":"P",
    "gn:feature_code":"PPL",
    "gn:name":"Kangma",
    "gn:population":0,
    "gn:timezone":"Asia/Urumqi",
    "iso:country":"CN",
    "name:zho_x_preferred":[
        "\u5eb7\u739b"
    ],
    "wof:name":"Kangma",
    "wof:placetype":"locality"
},
  "geometry": {"coordinates":[89.10720000000001,29.6017],"type":"Point"}
}