{
  "type": "Feature",
  "properties": {
    "gn:admin1_code":"14.0",
    "gn:asciiname":"Balongcun",
    "gn:country_code":"CN",
    "gn:dem":3609,
    "gn:feature_class":"P",
    "gn:feature_code":"PPL",
    "gn:name":"Balongcun",
    "gn:population":0,
    "gn:timezone":"Asia/Urumqi",
    "iso:country":"CN",
    "name:zho_x_preferred":[
        "\u5df4\u9f99\u6751"
    ],
    "wof:name":"Balongcun",
    "wof:placetype":"locality"
},
  "geometry": {"coordinates":[97.01078,31.27743],"type":"Point"}
}