{
  "type": "Feature",
  "properties": {
    "gn:admin1_code":"9.0",
    "gn:asciiname":"Zhonglecheng",
    "gn:country_code":"CN",
    "gn:dem":65,
    "gn:feature_class":"P",
    "gn:feature_code":"PPL",
    "gn:name":"Zhonglecheng",
    "gn:population":0,
    "gn:timezone":"Asia/Shanghai",
    "iso:country":"CN",
    "name:zho_x_preferred":[
        "\u4e2d\u4e86\u57ce"
    ],
    "wof:name":"Zhonglecheng",
    "wof:placetype":"locality"
},
  "geometry": {"coordinates":[114.76058999999999,34.69407],"type":"Point"}
}