{
  "type": "Feature",
  "properties": {
    "gn:admin1_code":"8.0",
    "gn:asciiname":"Du'ermenqin",
    "gn:country_code":"CN",
    "gn:dem":151,
    "gn:feature_class":"P",
    "gn:feature_code":"PPLA4",
    "gn:name":"Du\u2019ermenqin",
    "gn:population":0,
    "gn:timezone":"Asia/Shanghai",
    "iso:country":"CN",
    "name:und_x_variant":[
        "Du\u2019ermenqin",
        "Du\u2019ermenqin Dawo\u2019erzu Xiang"
    ],
    "name:zho_x_preferred":[
        "\u675c\u5c14\u95e8\u6c81"
    ],
    "name:zho_x_variant":[
        "\u675c\u5c14\u95e8\u6c81\u8fbe\u65a1\u5c14\u65cf\u4e61"
    ],
    "wof:name":"Du'ermenqin",
    "wof:placetype":"locality"
},
  "geometry": {"coordinates":[123.54165,47.13895],"type":"Point"}
}