{
  "type": "Feature",
  "properties": {
    "gn:admin1_code":"21.0",
    "gn:asciiname":"Jiefangshan",
    "gn:country_code":"CN",
    "gn:dem":1940,
    "gn:feature_class":"P",
    "gn:feature_code":"PPL",
    "gn:name":"Jiefangshan",
    "gn:population":0,
    "gn:timezone":"Asia/Shanghai",
    "iso:country":"CN",
    "name:zho_x_preferred":[
        "\u89e3\u653e\u5c71"
    ],
    "wof:name":"Jiefangshan",
    "wof:placetype":"locality"
},
  "geometry": {"coordinates":[106.252,35.8745],"type":"Point"}
}