{
  "type": "Feature",
  "properties": {
    "gn:admin1_code":"12.0",
    "gn:asciiname":"Xiaojing Qiao",
    "gn:country_code":"CN",
    "gn:dem":29,
    "gn:feature_class":"P",
    "gn:feature_code":"PPL",
    "gn:name":"Xiaojing Qiao",
    "gn:population":0,
    "gn:timezone":"Asia/Shanghai",
    "iso:country":"CN",
    "name:zho_x_preferred":[
        "\u5c0f\u8346\u6865"
    ],
    "wof:name":"Xiaojing Qiao",
    "wof:placetype":"locality"
},
  "geometry": {"coordinates":[112.54407999999999,30.34867],"type":"Point"}
}