{
  "type": "Feature",
  "properties": {
    "gn:admin1_code":"4.0",
    "gn:asciiname":"Wushan",
    "gn:country_code":"CN",
    "gn:dem":6,
    "gn:feature_class":"P",
    "gn:feature_code":"PPL",
    "gn:name":"Wushan",
    "gn:population":0,
    "gn:timezone":"Asia/Shanghai",
    "iso:country":"CN",
    "name:ceb_x_preferred":[
        "Wushan"
    ],
    "name:deu_x_preferred":[
        "Wushan"
    ],
    "name:fra_x_preferred":[
        "Wushan"
    ],
    "name:kor_x_preferred":[
        "\uc6b0\uc0b0\ud604"
    ],
    "name:nor_x_preferred":[
        "Wushan"
    ],
    "name:swe_x_preferred":[
        "Wushan"
    ],
    "name:zho_x_preferred":[
        "\u4e4c\u5c71"
    ],
    "wof:name":"Wushan",
    "wof:placetype":"locality"
},
  "geometry": {"coordinates":[118.57727,31.95987],"type":"Point"}
}