{
  "type": "Feature",
  "properties": {
    "gn:admin1_code":"2.0",
    "gn:asciiname":"Xuexiaosha",
    "gn:country_code":"CN",
    "gn:dem":12,
    "gn:feature_class":"P",
    "gn:feature_code":"PPL",
    "gn:name":"Xuexiaosha",
    "gn:population":0,
    "gn:timezone":"Asia/Shanghai",
    "iso:country":"CN",
    "name:und_x_variant":[
        "\u5b66\u6821\u6c99"
    ],
    "wof:name":"Xuexiaosha",
    "wof:placetype":"locality"
},
  "geometry": {"coordinates":[120.06264,30.06821],"type":"Point"}
}