{
  "type": "Feature",
  "properties": {
    "gn:admin1_code":"10",
    "gn:asciiname":"Guolongzhuang",
    "gn:country_code":"CN",
    "gn:dem":52,
    "gn:feature_class":"P",
    "gn:feature_code":"PPL",
    "gn:name":"Guolongzhuang",
    "gn:population":0,
    "gn:timezone":"Asia/Shanghai",
    "iso:country":"CN",
    "name:zho_x_preferred":[
        "\u90ed\u9f99\u5e84"
    ],
    "wof:name":"Guolongzhuang",
    "wof:placetype":"locality"
},
  "geometry": {"coordinates":[114.623,36.9484],"type":"Point"}
}