{
  "type": "Feature",
  "properties": {
    "gn:admin1_code":"02",
    "gn:asciiname":"Diaomen",
    "gn:cc2":"CN",
    "gn:country_code":"CN",
    "gn:dem":4,
    "gn:feature_class":"P",
    "gn:feature_code":"PPL",
    "gn:name":"Diaomen",
    "gn:population":0,
    "gn:timezone":"Asia/Shanghai",
    "iso:country":"CN",
    "name:und_x_variant":[
        "Tiao-men",
        "Diaomen",
        "\u9493\u95e8"
    ],
    "wof:name":"Diaomen",
    "wof:placetype":"locality"
},
  "geometry": {"coordinates":[122.22778,30.095],"type":"Point"}
}