{
  "type": "Feature",
  "properties": {
    "gn:admin1_code":"30.0",
    "gn:asciiname":"Niecun",
    "gn:country_code":"CN",
    "gn:dem":49,
    "gn:feature_class":"P",
    "gn:feature_code":"PPL",
    "gn:name":"Niecun",
    "gn:population":0,
    "gn:timezone":"Asia/Shanghai",
    "iso:country":"CN",
    "name:zho_x_preferred":[
        "\u8042\u6751"
    ],
    "wof:name":"Niecun",
    "wof:placetype":"locality"
},
  "geometry": {"coordinates":[112.15528999999999,22.14579],"type":"Point"}
}