{
  "type": "Feature",
  "properties": {
    "gn:admin1_code":"26.0",
    "gn:asciiname":"Yagouli",
    "gn:country_code":"CN",
    "gn:dem":1477,
    "gn:feature_class":"P",
    "gn:feature_code":"PPL",
    "gn:name":"Yagouli",
    "gn:population":0,
    "gn:timezone":"Asia/Shanghai",
    "iso:country":"CN",
    "name:zho_x_preferred":[
        "\u5d16\u6c9f\u91cc"
    ],
    "wof:name":"Yagouli",
    "wof:placetype":"locality"
},
  "geometry": {"coordinates":[106.72098,34.96044000000001],"type":"Point"}
}