{
  "type": "Feature",
  "properties": {
    "gn:admin1_code":"26.0",
    "gn:asciiname":"Liangmataicun",
    "gn:country_code":"CN",
    "gn:dem":1436,
    "gn:feature_class":"P",
    "gn:feature_code":"PPL",
    "gn:name":"Liangmataicun",
    "gn:population":0,
    "gn:timezone":"Asia/Shanghai",
    "iso:country":"CN",
    "name:zho_x_preferred":[
        "\u4eae\u9a6c\u53f0\u6751"
    ],
    "wof:name":"Liangmataicun",
    "wof:placetype":"locality"
},
  "geometry": {"coordinates":[107.67144,37.02289],"type":"Point"}
}