{
  "type": "Feature",
  "properties": {
    "gn:admin1_code":"30",
    "gn:asciiname":"Woshui",
    "gn:country_code":"CN",
    "gn:dem":373,
    "gn:feature_class":"P",
    "gn:feature_code":"PPLA4",
    "gn:name":"Woshui",
    "gn:population":0,
    "gn:timezone":"Asia/Shanghai",
    "iso:country":"CN",
    "name:und_x_variant":[
        "\u6da1\u6c34",
        "Woshui Zhen",
        "\u6da1\u6c34\u9547"
    ],
    "wof:name":"Woshui",
    "wof:placetype":"locality"
},
  "geometry": {"coordinates":[112.22556000000002,24.57167],"type":"Point"}
}