{
  "type": "Feature",
  "properties": {
    "iso:country":"CN",
    "name:bel_x_preferred":[
        "\u0413\u043e\u0440\u0430\u0434 \u042e\u0439\u0446\u044b"
    ],
    "name:ceb_x_preferred":[
        "Yuci Qu"
    ],
    "name:cym_x_preferred":[
        "Ardal Yuci"
    ],
    "name:deu_x_preferred":[
        "Yuci"
    ],
    "name:eng_x_preferred":[
        "Yuci District"
    ],
    "name:gan_x_preferred":[
        "\u6986\u6b21\u533a"
    ],
    "name:jpn_x_preferred":[
        "\u6961\u6b21\u533a"
    ],
    "name:kor_x_preferred":[
        "\uc704\uce20\uad6c"
    ],
    "name:nan_x_preferred":[
        "Ji\u00fb-chh\u00f9-khu"
    ],
    "name:nld_x_preferred":[
        "Yuci"
    ],
    "name:nob_x_preferred":[
        "Yuci"
    ],
    "name:rus_x_preferred":[
        "\u042e\u0439\u0446\u044b"
    ],
    "name:srp_x_preferred":[
        "\u0408\u0443\u0446\u0438"
    ],
    "name:swe_x_preferred":[
        "Yuci"
    ],
    "name:urd_x_preferred":[
        "\u06cc\u06a9\u06cc \u0636\u0644\u0639"
    ],
    "name:vie_x_preferred":[
        "Du Th\u1ee9"
    ],
    "name:wuu_x_preferred":[
        "\u6986\u6b21\u533a"
    ],
    "name:yue_x_preferred":[
        "\u6986\u6b21"
    ],
    "name:zho_x_preferred":[
        "\u6986\u6b21\u533a"
    ],
    "qs:name":"\u6986\u6b21\u533a",
    "qs:name_adm0":"\u4e2d\u570b",
    "qs:name_adm1":"\u5c71\u897f\u7701",
    "qs:photos":3,
    "qs:photos_1k":1,
    "qs:photos_9k":1,
    "qs:photos_9r":3,
    "qs:photos_all":79,
    "qs:photos_sr":1,
    "qs:placetype":"LocalAdmin",
    "qs:pop_sr":"0",
    "wd:wordcount":96,
    "wof:name":"\u6986\u6b21\u533a",
    "wof:placetype":"localadmin"
},
  "geometry": {"coordinates":[112.732601,37.67945],"type":"Point"}
}