{
  "type": "Feature",
  "properties": {
    "gn:admin1_code":"5.0",
    "gn:asciiname":"Yuanjiatun",
    "gn:country_code":"CN",
    "gn:dem":112,
    "gn:feature_class":"P",
    "gn:feature_code":"PPL",
    "gn:name":"Yuanjiatun",
    "gn:population":0,
    "gn:timezone":"Asia/Shanghai",
    "iso:country":"CN",
    "name:zho_x_preferred":[
        "\u82d1\u5bb6\u5c6f"
    ],
    "wof:name":"Yuanjiatun",
    "wof:placetype":"locality"
},
  "geometry": {"coordinates":[123.63396000000002,43.39612],"type":"Point"}
}