{
  "type": "Feature",
  "properties": {
    "gn:admin1_code":"32.0",
    "gn:asciiname":"Xiaogouwan",
    "gn:country_code":"CN",
    "gn:dem":377,
    "gn:feature_class":"P",
    "gn:feature_code":"PPL",
    "gn:name":"Xiaogouwan",
    "gn:population":0,
    "gn:timezone":"Asia/Shanghai",
    "iso:country":"CN",
    "name:zho_x_preferred":[
        "\u5c0f\u6c9f\u6e7e"
    ],
    "wof:name":"Xiaogouwan",
    "wof:placetype":"locality"
},
  "geometry": {"coordinates":[106.744,30.9277],"type":"Point"}
}