{
  "type": "Feature",
  "properties": {
    "gn:admin1_code":"25.0",
    "gn:asciiname":"Muzhuangcun",
    "gn:country_code":"CN",
    "gn:dem":40,
    "gn:feature_class":"P",
    "gn:feature_code":"PPL",
    "gn:name":"Muzhuangcun",
    "gn:population":0,
    "gn:timezone":"Asia/Shanghai",
    "iso:country":"CN",
    "name:zho_x_preferred":[
        "\u7a46\u5e84\u6751"
    ],
    "wof:name":"Muzhuangcun",
    "wof:placetype":"locality"
},
  "geometry": {"coordinates":[115.97557999999999,36.25729000000001],"type":"Point"}
}