{
  "type": "Feature",
  "properties": {
    "gn:admin1_code":"26.0",
    "gn:asciiname":"Dahetan",
    "gn:country_code":"CN",
    "gn:dem":1341,
    "gn:feature_class":"P",
    "gn:feature_code":"PPL",
    "gn:name":"Dahetan",
    "gn:population":0,
    "gn:timezone":"Asia/Shanghai",
    "iso:country":"CN",
    "name:und_x_variant":[
        "\u5927\u6cb3\u6ee9",
        "Dahetan"
    ],
    "wof:name":"Dahetan",
    "wof:placetype":"locality"
},
  "geometry": {"coordinates":[107.56761000000002,33.82549],"type":"Point"}
}