{
  "type": "Feature",
  "properties": {
    "gn:admin1_code":"21.0",
    "gn:asciiname":"Huasi Dadui Jiudui",
    "gn:country_code":"CN",
    "gn:dem":1134,
    "gn:feature_class":"P",
    "gn:feature_code":"PPLF",
    "gn:name":"Huasi Dadui Jiudui",
    "gn:population":0,
    "gn:timezone":"Asia/Shanghai",
    "iso:country":"CN",
    "name:zho_x_preferred":[
        "\u82b1\u5bfa\u5927\u961f\u4e5d\u961f"
    ],
    "wof:name":"Huasi Dadui Jiudui",
    "wof:placetype":"locality"
},
  "geometry": {"coordinates":[106.286,37.9169],"type":"Point"}
}