{
  "type": "Feature",
  "properties": {
    "gn:admin1_code":"2.0",
    "gn:asciiname":"Shantouli",
    "gn:country_code":"CN",
    "gn:dem":42,
    "gn:feature_class":"P",
    "gn:feature_code":"PPL",
    "gn:name":"Shantouli",
    "gn:population":0,
    "gn:timezone":"Asia/Shanghai",
    "iso:country":"CN",
    "name:zho_x_preferred":[
        "\u5c71\u5934\u91cc"
    ],
    "wof:name":"Shantouli",
    "wof:placetype":"locality"
},
  "geometry": {"coordinates":[120.9522,29.53772],"type":"Point"}
}