{
  "type": "Feature",
  "properties": {
    "gn:admin1_code":"19.0",
    "gn:asciiname":"Houbigou",
    "gn:country_code":"CN",
    "gn:dem":47,
    "gn:feature_class":"P",
    "gn:feature_code":"PPL",
    "gn:name":"Houbigou",
    "gn:population":0,
    "gn:timezone":"Asia/Shanghai",
    "iso:country":"CN",
    "name:und_x_variant":[
        "\u540e\u6bd5\u6c9f"
    ],
    "name:zho_x_preferred":[
        "\u540e\u6bd5\u6c9f"
    ],
    "wof:name":"Houbigou",
    "wof:placetype":"locality"
},
  "geometry": {"coordinates":[122.071,39.3757],"type":"Point"}
}