{
  "type": "Feature",
  "properties": {
    "gn:admin1_code":"4.0",
    "gn:asciiname":"Gengdongcun",
    "gn:country_code":"CN",
    "gn:dem":16,
    "gn:feature_class":"P",
    "gn:feature_code":"PPL",
    "gn:name":"Gengdongcun",
    "gn:population":0,
    "gn:timezone":"Asia/Shanghai",
    "iso:country":"CN",
    "name:zho_x_preferred":[
        "\u803f\u4e1c\u6751"
    ],
    "wof:name":"Gengdongcun",
    "wof:placetype":"locality"
},
  "geometry": {"coordinates":[118.48999999999999,33.6869],"type":"Point"}
}