{
  "type": "Feature",
  "properties": {
    "gn:admin1_code":"1.0",
    "gn:asciiname":"Xinyuancun",
    "gn:country_code":"CN",
    "gn:dem":127,
    "gn:feature_class":"P",
    "gn:feature_code":"PPL",
    "gn:name":"Xinyuancun",
    "gn:population":0,
    "gn:timezone":"Asia/Shanghai",
    "iso:country":"CN",
    "name:zho_x_preferred":[
        "\u65b0\u6e90\u6751"
    ],
    "wof:name":"Xinyuancun",
    "wof:placetype":"locality"
},
  "geometry": {"coordinates":[117.68591000000001,29.85028],"type":"Point"}
}