{
  "type": "Feature",
  "properties": {
    "gn:admin1_code":"15.0",
    "gn:asciiname":"Xuanjiawan",
    "gn:country_code":"CN",
    "gn:dem":1110,
    "gn:feature_class":"P",
    "gn:feature_code":"PPL",
    "gn:name":"Xuanjiawan",
    "gn:population":0,
    "gn:timezone":"Asia/Shanghai",
    "iso:country":"CN",
    "name:zho_x_preferred":[
        "\u65cb\u5bb6\u6e7e"
    ],
    "wof:name":"Xuanjiawan",
    "wof:placetype":"locality"
},
  "geometry": {"coordinates":[105.104,32.8102],"type":"Point"}
}