{
  "type": "Feature",
  "properties": {
    "gn:admin1_code":"15.0",
    "gn:asciiname":"Xingjiacha",
    "gn:country_code":"CN",
    "gn:dem":1938,
    "gn:feature_class":"P",
    "gn:feature_code":"PPL",
    "gn:name":"Xingjiacha",
    "gn:population":0,
    "gn:timezone":"Asia/Shanghai",
    "iso:country":"CN",
    "name:zho_x_preferred":[
        "\u5211\u5bb6\u5c94"
    ],
    "wof:name":"Xingjiacha",
    "wof:placetype":"locality"
},
  "geometry": {"coordinates":[104.748,35.1976],"type":"Point"}
}