{
  "type": "Feature",
  "properties": {
    "gn:admin1_code":"3.0",
    "gn:asciiname":"Lishushan",
    "gn:country_code":"CN",
    "gn:dem":57,
    "gn:feature_class":"P",
    "gn:feature_code":"PPL",
    "gn:name":"Lishushan",
    "gn:population":0,
    "gn:timezone":"Asia/Shanghai",
    "iso:country":"CN",
    "name:und_x_variant":[
        "\u6817\u6811\u5c71"
    ],
    "wof:name":"Lishushan",
    "wof:placetype":"locality"
},
  "geometry": {"coordinates":[116.94395,28.1271],"type":"Point"}
}