{
  "type": "Feature",
  "properties": {
    "gn:admin1_code":"18.0",
    "gn:asciiname":"Pingle",
    "gn:country_code":"CN",
    "gn:dem":969,
    "gn:feature_class":"P",
    "gn:feature_code":"PPLA4",
    "gn:name":"Pingle",
    "gn:population":0,
    "gn:timezone":"Asia/Shanghai",
    "iso:country":"CN",
    "name:und_x_variant":[
        "Pingle Xiang",
        "Dingjiabao"
    ],
    "name:zho_x_preferred":[
        "\u576a\u4e50"
    ],
    "name:zho_x_variant":[
        "\u576a\u4e50\u4e61",
        "\u4e01\u5bb6\u5821"
    ],
    "wof:name":"Pingle",
    "wof:placetype":"locality"
},
  "geometry": {"coordinates":[107.4618,28.21245],"type":"Point"}
}