{
  "type": "Feature",
  "properties": {
    "gn:admin1_code":"1.0",
    "gn:asciiname":"Zhongzhuangcun",
    "gn:country_code":"CN",
    "gn:dem":41,
    "gn:feature_class":"P",
    "gn:feature_code":"PPL",
    "gn:name":"Zhongzhuangcun",
    "gn:population":0,
    "gn:timezone":"Asia/Shanghai",
    "iso:country":"CN",
    "name:zho_x_preferred":[
        "\u949f\u5e84\u6751"
    ],
    "wof:name":"Zhongzhuangcun",
    "wof:placetype":"locality"
},
  "geometry": {"coordinates":[115.16462,32.91418],"type":"Point"}
}