{
  "type": "Feature",
  "properties": {
    "gn:admin1_code":"4.0",
    "gn:asciiname":"Wangjiadai",
    "gn:country_code":"CN",
    "gn:dem":3,
    "gn:feature_class":"P",
    "gn:feature_code":"PPL",
    "gn:name":"Wangjiadai",
    "gn:population":0,
    "gn:timezone":"Asia/Shanghai",
    "iso:country":"CN",
    "name:zho_x_preferred":[
        "\u6c6a\u5bb6\u57ed"
    ],
    "wof:name":"Wangjiadai",
    "wof:placetype":"locality"
},
  "geometry": {"coordinates":[119.80083,32.27118],"type":"Point"}
}