{
  "type": "Feature",
  "properties": {
    "gn:admin1_code":"4.0",
    "gn:asciiname":"Hongcheng",
    "gn:country_code":"CN",
    "gn:dem":10,
    "gn:feature_class":"P",
    "gn:feature_code":"PPL",
    "gn:name":"Hongcheng",
    "gn:population":0,
    "gn:timezone":"Asia/Shanghai",
    "iso:country":"CN",
    "name:zho_x_preferred":[
        "\u6d2a\u6210"
    ],
    "wof:name":"Hongcheng",
    "wof:placetype":"locality"
},
  "geometry": {"coordinates":[118.45999999999999,33.3237],"type":"Point"}
}