{
  "type": "Feature",
  "properties": {
    "gn:admin1_code":"20.0",
    "gn:asciiname":"Housan Daogou",
    "gn:country_code":"CN",
    "gn:dem":1962,
    "gn:feature_class":"P",
    "gn:feature_code":"PPL",
    "gn:name":"Housan Daogou",
    "gn:population":0,
    "gn:timezone":"Asia/Shanghai",
    "iso:country":"CN",
    "name:und_x_variant":[
        "\u540e\u4e09\u9053\u6c9f"
    ],
    "wof:name":"Housan Daogou",
    "wof:placetype":"locality"
},
  "geometry": {"coordinates":[110.55783999999998,41.11204],"type":"Point"}
}