{
  "type": "Feature",
  "properties": {
    "gn:admin1_code":"2",
    "gn:asciiname":"Wutongyang",
    "gn:country_code":"CN",
    "gn:dem":778,
    "gn:feature_class":"P",
    "gn:feature_code":"PPL",
    "gn:name":"Wutongyang",
    "gn:population":0,
    "gn:timezone":"Asia/Shanghai",
    "iso:country":"CN",
    "name:zho_x_preferred":[
        "\u68a7\u6850\u579f"
    ],
    "wof:name":"Wutongyang",
    "wof:placetype":"locality"
},
  "geometry": {"coordinates":[119.97360999999999,27.5325],"type":"Point"}
}