{
  "type": "Feature",
  "properties": {
    "gn:admin1_code":"15.0",
    "gn:asciiname":"Dayaoxian",
    "gn:country_code":"CN",
    "gn:dem":1497,
    "gn:feature_class":"P",
    "gn:feature_code":"PPL",
    "gn:name":"Dayaoxian",
    "gn:population":0,
    "gn:timezone":"Asia/Shanghai",
    "iso:country":"CN",
    "name:und_x_variant":[
        "\u5927\u5d3e\u5c98"
    ],
    "wof:name":"Dayaoxian",
    "wof:placetype":"locality"
},
  "geometry": {"coordinates":[107.94965999999999,36.47885],"type":"Point"}
}