{
  "type": "Feature",
  "properties": {
    "gn:admin1_code":"32.0",
    "gn:asciiname":"Jiazongduo",
    "gn:country_code":"CN",
    "gn:dem":3627,
    "gn:feature_class":"P",
    "gn:feature_code":"PPL",
    "gn:name":"Jiazongduo",
    "gn:population":0,
    "gn:timezone":"Asia/Shanghai",
    "iso:country":"CN",
    "name:zho_x_preferred":[
        "\u52a0\u5b97\u591a"
    ],
    "wof:name":"Jiazongduo",
    "wof:placetype":"locality"
},
  "geometry": {"coordinates":[100.79358999999999,31.79489],"type":"Point"}
}