{
  "type": "Feature",
  "properties": {
    "gn:admin1_code":"18.0",
    "gn:asciiname":"Kangzhongcun",
    "gn:country_code":"CN",
    "gn:dem":439,
    "gn:feature_class":"P",
    "gn:feature_code":"PPL",
    "gn:name":"Kangzhongcun",
    "gn:population":0,
    "gn:timezone":"Asia/Shanghai",
    "iso:country":"CN",
    "name:zho_x_preferred":[
        "\u5eb7\u4e2d\u6751"
    ],
    "wof:name":"Kangzhongcun",
    "wof:placetype":"locality"
},
  "geometry": {"coordinates":[108.839,26.5242],"type":"Point"}
}