{
  "type": "Feature",
  "properties": {
    "gn:admin1_code":"14.0",
    "gn:asciiname":"Duoge",
    "gn:country_code":"CN",
    "gn:dem":4276,
    "gn:feature_class":"P",
    "gn:feature_code":"PPL",
    "gn:name":"Duoge",
    "gn:population":0,
    "gn:timezone":"Asia/Urumqi",
    "iso:country":"CN",
    "name:zho_x_preferred":[
        "\u591a\u5404"
    ],
    "wof:name":"Duoge",
    "wof:placetype":"locality"
},
  "geometry": {"coordinates":[94.52665,29.94779],"type":"Point"}
}