{
  "type": "Feature",
  "properties": {
    "gn:admin1_code":"9.0",
    "gn:asciiname":"Dengjiachong",
    "gn:country_code":"CN",
    "gn:dem":150,
    "gn:feature_class":"P",
    "gn:feature_code":"PPL",
    "gn:name":"Dengjiachong",
    "gn:population":0,
    "gn:timezone":"Asia/Shanghai",
    "iso:country":"CN",
    "name:zho_x_preferred":[
        "\u9093\u5bb6\u51b2"
    ],
    "wof:name":"Dengjiachong",
    "wof:placetype":"locality"
},
  "geometry": {"coordinates":[114.01429,31.94611],"type":"Point"}
}