{
  "type": "Feature",
  "properties": {
    "gn:admin1_code":"18",
    "gn:asciiname":"Lingdang",
    "gn:country_code":"CN",
    "gn:dem":966,
    "gn:feature_class":"P",
    "gn:feature_code":"PPL",
    "gn:name":"Lingdang",
    "gn:population":0,
    "gn:timezone":"Asia/Shanghai",
    "iso:country":"CN",
    "name:zho_x_preferred":[
        "\u4ee4\u5f53"
    ],
    "wof:name":"Lingdang",
    "wof:placetype":"locality"
},
  "geometry": {"coordinates":[106.599,25.7243],"type":"Point"}
}