{
  "type": "Feature",
  "properties": {
    "gn:admin1_code":"14.0",
    "gn:asciiname":"Naiqiong",
    "gn:country_code":"CN",
    "gn:dem":4071,
    "gn:feature_class":"P",
    "gn:feature_code":"PPL",
    "gn:name":"Naiqiong",
    "gn:population":0,
    "gn:timezone":"Asia/Urumqi",
    "iso:country":"CN",
    "name:zho_x_preferred":[
        "\u4e43\u7a77"
    ],
    "wof:name":"Naiqiong",
    "wof:placetype":"locality"
},
  "geometry": {"coordinates":[91.45753999999999,30.11193],"type":"Point"}
}