{
  "type": "Feature",
  "properties": {
    "gn:admin1_code":"30",
    "gn:asciiname":"Yingnan",
    "gn:country_code":"CN",
    "gn:dem":3,
    "gn:feature_class":"P",
    "gn:feature_code":"PPL",
    "gn:name":"Yingnan",
    "gn:population":0,
    "gn:timezone":"Asia/Urumqi",
    "iso:country":"CN",
    "name:zho_x_preferred":[
        "\u82f1\u6960"
    ],
    "wof:name":"Yingnan",
    "wof:placetype":"locality"
},
  "geometry": {"coordinates":[109.9171,20.47923],"type":"Point"}
}