{
  "type": "Feature",
  "properties": {
    "gn:admin1_code":"8.0",
    "gn:asciiname":"Tieren Yicun",
    "gn:country_code":"CN",
    "gn:dem":149,
    "gn:feature_class":"P",
    "gn:feature_code":"PPL",
    "gn:name":"Tieren Yicun",
    "gn:population":0,
    "gn:timezone":"Asia/Shanghai",
    "iso:country":"CN",
    "name:zho_x_preferred":[
        "\u94c1\u4eba\u4e00\u6751"
    ],
    "wof:name":"Tieren Yicun",
    "wof:placetype":"locality"
},
  "geometry": {"coordinates":[124.96795,46.60394],"type":"Point"}
}