{
  "type": "Feature",
  "properties": {
    "gn:admin1_code":"2.0",
    "gn:asciiname":"Xibukengkou",
    "gn:country_code":"CN",
    "gn:dem":272,
    "gn:feature_class":"P",
    "gn:feature_code":"PPL",
    "gn:name":"Xibukengkou",
    "gn:population":0,
    "gn:timezone":"Asia/Shanghai",
    "iso:country":"CN",
    "name:zho_x_preferred":[
        "\u897f\u535c\u5751\u53e3"
    ],
    "wof:name":"Xibukengkou",
    "wof:placetype":"locality"
},
  "geometry": {"coordinates":[119.87295,28.67341],"type":"Point"}
}