{
  "type": "Feature",
  "properties": {
    "gn:admin1_code":"05",
    "gn:asciiname":"Hsi-nan-ch'a-kou-tzu",
    "gn:country_code":"CN",
    "gn:dem":600,
    "gn:feature_class":"P",
    "gn:feature_code":"PPL",
    "gn:name":"Hsi-nan-ch\u2019a-kou-tzu",
    "gn:population":0,
    "gn:timezone":"Asia/Shanghai",
    "iso:country":"CN",
    "wof:name":"Hsi-nan-ch'a-kou-tzu",
    "wof:placetype":"locality"
},
  "geometry": {"coordinates":[128.52667,42.93611],"type":"Point"}
}