{
  "type": "Feature",
  "properties": {
    "gn:admin1_code":"32.0",
    "gn:asciiname":"Qingning",
    "gn:country_code":"CN",
    "gn:dem":2197,
    "gn:feature_class":"P",
    "gn:feature_code":"PPL",
    "gn:name":"Qingning",
    "gn:population":0,
    "gn:timezone":"Asia/Shanghai",
    "iso:country":"CN",
    "name:zho_x_preferred":[
        "\u5e86\u5b81"
    ],
    "wof:name":"Qingning",
    "wof:placetype":"locality"
},
  "geometry": {"coordinates":[102.06014999999999,31.55425],"type":"Point"}
}