{
  "type": "Feature",
  "properties": {
    "gn:admin1_code":"6.0",
    "gn:asciiname":"Sequnlang",
    "gn:country_code":"CN",
    "gn:dem":4312,
    "gn:feature_class":"P",
    "gn:feature_code":"PPL",
    "gn:name":"Sequnlang",
    "gn:population":0,
    "gn:timezone":"Asia/Urumqi",
    "iso:country":"CN",
    "name:zho_x_preferred":[
        "\u8272\u7fa4\u90ce"
    ],
    "wof:name":"Sequnlang",
    "wof:placetype":"locality"
},
  "geometry": {"coordinates":[95.63630999999999,32.09299],"type":"Point"}
}