{
  "type": "Feature",
  "properties": {
    "gn:admin1_code":"29.0",
    "gn:asciiname":"Yitangde",
    "gn:country_code":"CN",
    "gn:dem":953,
    "gn:feature_class":"P",
    "gn:feature_code":"PPL",
    "gn:name":"Yitangde",
    "gn:population":0,
    "gn:timezone":"Asia/Shanghai",
    "iso:country":"CN",
    "name:zho_x_preferred":[
        "\u4ee5\u6c64\u5fb7"
    ],
    "wof:name":"Yitangde",
    "wof:placetype":"locality"
},
  "geometry": {"coordinates":[102.366,26.2618],"type":"Point"}
}