{
  "type": "Feature",
  "properties": {
    "gn:admin1_code":"5.0",
    "gn:asciiname":"Gaoligou",
    "gn:country_code":"CN",
    "gn:dem":150,
    "gn:feature_class":"P",
    "gn:feature_code":"PPL",
    "gn:name":"Gaoligou",
    "gn:population":0,
    "gn:timezone":"Asia/Shanghai",
    "iso:country":"CN",
    "name:und_x_variant":[
        "\u9ad8\u4e3d\u6c9f"
    ],
    "wof:name":"Gaoligou",
    "wof:placetype":"locality"
},
  "geometry": {"coordinates":[125.75711,40.93095],"type":"Point"}
}