{
  "type": "Feature",
  "properties": {
    "gn:admin1_code":"16.0",
    "gn:asciiname":"Jiashang",
    "gn:country_code":"CN",
    "gn:dem":612,
    "gn:feature_class":"P",
    "gn:feature_code":"PPL",
    "gn:name":"Jiashang",
    "gn:population":0,
    "gn:timezone":"Asia/Shanghai",
    "iso:country":"CN",
    "name:zho_x_preferred":[
        "\u52a0\u5c1a"
    ],
    "wof:name":"Jiashang",
    "wof:placetype":"locality"
},
  "geometry": {"coordinates":[108.48099999999999,24.0739],"type":"Point"}
}