{
  "type": "Feature",
  "properties": {
    "gn:admin1_code":"3.0",
    "gn:asciiname":"Diaozhongxing",
    "gn:country_code":"CN",
    "gn:dem":145,
    "gn:feature_class":"P",
    "gn:feature_code":"PPL",
    "gn:name":"Diaozhongxing",
    "gn:population":0,
    "gn:timezone":"Asia/Shanghai",
    "iso:country":"CN",
    "name:und_x_variant":[
        "\u540a\u949f\u5f62"
    ],
    "wof:name":"Diaozhongxing",
    "wof:placetype":"locality"
},
  "geometry": {"coordinates":[115.1807,26.72548],"type":"Point"}
}