{
  "type": "Feature",
  "properties": {
    "gn:admin1_code":"23.0",
    "gn:asciiname":"Wangjiazhai",
    "gn:country_code":"CN",
    "gn:dem":2,
    "gn:feature_class":"P",
    "gn:feature_code":"PPL",
    "gn:name":"Wangjiazhai",
    "gn:population":0,
    "gn:timezone":"Asia/Shanghai",
    "iso:country":"CN",
    "name:zho_x_preferred":[
        "Wangjiazhai"
    ],
    "name:zho_x_variant":[
        "\u738b\u5bb6\u5b85"
    ],
    "wof:name":"Wangjiazhai",
    "wof:placetype":"locality"
},
  "geometry": {"coordinates":[121.63218000000001,31.2277],"type":"Point"}
}