{
  "type": "Feature",
  "properties": {
    "gn:admin1_code":"2",
    "gn:asciiname":"Chisong",
    "gn:country_code":"CN",
    "gn:dem":82,
    "gn:feature_class":"P",
    "gn:feature_code":"PPL",
    "gn:name":"Chisong",
    "gn:population":0,
    "gn:timezone":"Asia/Shanghai",
    "iso:country":"CN",
    "name:und_x_variant":[
        "\u8d64\u677e"
    ],
    "wof:name":"Chisong",
    "wof:placetype":"locality"
},
  "geometry": {"coordinates":[119.98736,30.09672],"type":"Point"}
}