{
  "type": "Feature",
  "properties": {
    "gn:admin1_code":"20.0",
    "gn:asciiname":"Dawukulun",
    "gn:country_code":"CN",
    "gn:dem":1658,
    "gn:feature_class":"P",
    "gn:feature_code":"PPL",
    "gn:name":"Dawukulun",
    "gn:population":0,
    "gn:timezone":"Asia/Shanghai",
    "iso:country":"CN",
    "name:und_x_variant":[
        "\u5927\u4e4c\u5e93\u4f26"
    ],
    "wof:name":"Dawukulun",
    "wof:placetype":"locality"
},
  "geometry": {"coordinates":[111.63142000000001,41.24776],"type":"Point"}
}