{
  "type": "Feature",
  "properties": {
    "gn:admin1_code":"10.0",
    "gn:asciiname":"Chaojiazhuang",
    "gn:country_code":"CN",
    "gn:dem":57,
    "gn:feature_class":"P",
    "gn:feature_code":"PPL",
    "gn:name":"Chaojiazhuang",
    "gn:population":0,
    "gn:timezone":"Asia/Shanghai",
    "iso:country":"CN",
    "name:zho_x_preferred":[
        "\u6641\u5bb6\u5e84"
    ],
    "wof:name":"Chaojiazhuang",
    "wof:placetype":"locality"
},
  "geometry": {"coordinates":[118.33965000000001,39.89246],"type":"Point"}
}