{
  "type": "Feature",
  "properties": {
    "gn:admin1_code":"7.0",
    "gn:asciiname":"Louyuancun",
    "gn:country_code":"CN",
    "gn:dem":154,
    "gn:feature_class":"P",
    "gn:feature_code":"PPL",
    "gn:name":"Louyuancun",
    "gn:population":0,
    "gn:timezone":"Asia/Shanghai",
    "iso:country":"CN",
    "name:und_x_variant":[
        "\u697c\u6e90\u6751"
    ],
    "name:zho_x_preferred":[
        "\u697c\u6e90\u6751"
    ],
    "wof:name":"Louyuancun",
    "wof:placetype":"locality"
},
  "geometry": {"coordinates":[117.45593999999998,26.15083],"type":"Point"}
}