{
  "type": "Feature",
  "properties": {
    "gn:admin1_code":"26.0",
    "gn:asciiname":"Ajimancun",
    "gn:country_code":"CN",
    "gn:dem":1171,
    "gn:feature_class":"P",
    "gn:feature_code":"PPL",
    "gn:name":"Ajimancun",
    "gn:population":0,
    "gn:timezone":"Asia/Shanghai",
    "iso:country":"CN",
    "name:zho_x_preferred":[
        "\u963f\u9e21\u66fc\u6751"
    ],
    "wof:name":"Ajimancun",
    "wof:placetype":"locality"
},
  "geometry": {"coordinates":[110.29649000000001,38.88338],"type":"Point"}
}