{
  "type": "Feature",
  "properties": {
    "gn:admin1_code":"32",
    "gn:asciiname":"Baihe",
    "gn:country_code":"CN",
    "gn:dem":362,
    "gn:feature_class":"P",
    "gn:feature_code":"PPL",
    "gn:name":"Baihe",
    "gn:population":0,
    "gn:timezone":"Asia/Shanghai",
    "iso:country":"CN",
    "name:und_x_variant":[
        "Pai-ho",
        "Baihe Zhen",
        "Baihe"
    ],
    "name:zho_x_preferred":[
        "\u767d\u5408"
    ],
    "wof:name":"Baihe",
    "wof:placetype":"locality"
},
  "geometry": {"coordinates":[105.2889,29.68956],"type":"Point"}
}