{
  "type": "Feature",
  "properties": {
    "gn:admin1_code":"30.0",
    "gn:asciiname":"Gaoxiacun",
    "gn:country_code":"CN",
    "gn:dem":11,
    "gn:feature_class":"P",
    "gn:feature_code":"PPL",
    "gn:name":"Gaoxiacun",
    "gn:population":0,
    "gn:timezone":"Asia/Shanghai",
    "iso:country":"CN",
    "name:und_x_variant":[
        "Gaoxia"
    ],
    "name:zho_x_preferred":[
        "\u9ad8\u5ec8\u6751"
    ],
    "wof:name":"Gaoxiacun",
    "wof:placetype":"locality"
},
  "geometry": {"coordinates":[116.59711,23.62579],"type":"Point"}
}