{
  "type": "Feature",
  "properties": {
    "gn:admin1_code":"8.0",
    "gn:asciiname":"Daohezi",
    "gn:country_code":"CN",
    "gn:dem":314,
    "gn:feature_class":"P",
    "gn:feature_code":"PPL",
    "gn:name":"Daohezi",
    "gn:population":0,
    "gn:timezone":"Asia/Shanghai",
    "iso:country":"CN",
    "name:und_x_variant":[
        "\u9053\u6cb3\u5b50"
    ],
    "wof:name":"Daohezi",
    "wof:placetype":"locality"
},
  "geometry": {"coordinates":[127.08332,50.16573],"type":"Point"}
}