{
  "type": "Feature",
  "properties": {
    "gn:admin1_code":"14.0",
    "gn:asciiname":"Guodaka",
    "gn:country_code":"CN",
    "gn:dem":4489,
    "gn:feature_class":"P",
    "gn:feature_code":"PPL",
    "gn:name":"Guodaka",
    "gn:population":0,
    "gn:timezone":"Asia/Urumqi",
    "iso:country":"CN",
    "name:zho_x_preferred":[
        "\u90ed\u5927\u5361"
    ],
    "wof:name":"Guodaka",
    "wof:placetype":"locality"
},
  "geometry": {"coordinates":[98.70573,29.63151],"type":"Point"}
}