{
  "type": "Feature",
  "properties": {
    "gn:admin1_code":"11.0",
    "gn:asciiname":"Majiahe",
    "gn:country_code":"CN",
    "gn:dem":36,
    "gn:feature_class":"P",
    "gn:feature_code":"PPL",
    "gn:name":"Majiahe",
    "gn:population":0,
    "gn:timezone":"Asia/Shanghai",
    "iso:country":"CN",
    "name:zho_x_preferred":[
        "Majiahe"
    ],
    "name:zho_x_variant":[
        "\u9a6c\u5bb6\u6cb3"
    ],
    "wof:name":"Majiahe",
    "wof:placetype":"locality"
},
  "geometry": {"coordinates":[111.85272000000001,29.6635],"type":"Point"}
}