{
  "type": "Feature",
  "properties": {
    "gn:admin1_code":"14.0",
    "gn:asciiname":"Buhadi",
    "gn:country_code":"CN",
    "gn:dem":3518,
    "gn:feature_class":"P",
    "gn:feature_code":"PPL",
    "gn:name":"Buhadi",
    "gn:population":0,
    "gn:timezone":"Asia/Urumqi",
    "iso:country":"CN",
    "name:zho_x_preferred":[
        "\u5e03\u54c8\u5730"
    ],
    "wof:name":"Buhadi",
    "wof:placetype":"locality"
},
  "geometry": {"coordinates":[98.86074000000001,29.05549],"type":"Point"}
}