{
  "type": "Feature",
  "properties": {
    "gn:admin1_code":"01",
    "gn:asciiname":"Lide",
    "gn:cc2":"CN",
    "gn:country_code":"CN",
    "gn:dem":33,
    "gn:feature_class":"P",
    "gn:feature_code":"PPL",
    "gn:name":"Lide",
    "gn:population":0,
    "gn:timezone":"Asia/Shanghai",
    "iso:country":"CN",
    "name:und_x_variant":[
        "Li-te-ssu",
        "Lidesi",
        "Lide"
    ],
    "wof:name":"Lide",
    "wof:placetype":"locality"
},
  "geometry": {"coordinates":[115.88361,33.53722],"type":"Point"}
}