{
  "type": "Feature",
  "properties": {
    "gn:admin1_code":"29.0",
    "gn:asciiname":"Dasongdeng",
    "gn:country_code":"CN",
    "gn:dem":1739,
    "gn:feature_class":"P",
    "gn:feature_code":"PPL",
    "gn:name":"Dasongdeng",
    "gn:population":0,
    "gn:timezone":"Asia/Shanghai",
    "iso:country":"CN",
    "name:zho_x_preferred":[
        "\u5927\u677e\u767b"
    ],
    "wof:name":"Dasongdeng",
    "wof:placetype":"locality"
},
  "geometry": {"coordinates":[99.12649999999999,26.4222],"type":"Point"}
}