{
  "type": "Feature",
  "properties": {
    "gn:admin1_code":"30.0",
    "gn:asciiname":"Tongle",
    "gn:country_code":"CN",
    "gn:dem":104,
    "gn:feature_class":"P",
    "gn:feature_code":"PPL",
    "gn:name":"Tongle",
    "gn:population":0,
    "gn:timezone":"Asia/Shanghai",
    "iso:country":"CN",
    "name:zho_x_preferred":[
        "\u540c\u4e50"
    ],
    "wof:name":"Tongle",
    "wof:placetype":"locality"
},
  "geometry": {"coordinates":[113.63194,24.2525],"type":"Point"}
}