{
  "type": "Feature",
  "properties": {
    "gn:admin1_code":"02",
    "gn:asciiname":"Shizhu",
    "gn:country_code":"CN",
    "gn:dem":109,
    "gn:feature_class":"P",
    "gn:feature_code":"PPLA4",
    "gn:name":"Shizhu",
    "gn:population":0,
    "gn:timezone":"Asia/Shanghai",
    "iso:country":"CN",
    "name:und_x_variant":[
        "Shih-chu-chieh",
        "Shih-chu",
        "Shizhu",
        "Shizhu Zhen"
    ],
    "name:zho_x_preferred":[
        "\u77f3\u67f1"
    ],
    "name:zho_x_variant":[
        "\u77f3\u67f1\u9547"
    ],
    "wof:name":"Shizhu",
    "wof:placetype":"locality"
},
  "geometry": {"coordinates":[120.09596000000001,28.84567],"type":"Point"}
}