{
  "type": "Feature",
  "properties": {
    "gn:admin1_code":"8.0",
    "gn:asciiname":"Zhalanggecun",
    "gn:country_code":"CN",
    "gn:dem":145,
    "gn:feature_class":"P",
    "gn:feature_code":"PPL",
    "gn:name":"Zhalanggecun",
    "gn:population":0,
    "gn:timezone":"Asia/Shanghai",
    "iso:country":"CN",
    "name:zho_x_preferred":[
        "\u624e\u90ce\u683c\u6751"
    ],
    "wof:name":"Zhalanggecun",
    "wof:placetype":"locality"
},
  "geometry": {"coordinates":[123.96228000000001,46.89754],"type":"Point"}
}