{
  "type": "Feature",
  "properties": {
    "gn:admin1_code":"30.0",
    "gn:asciiname":"Pingdi",
    "gn:country_code":"CN",
    "gn:dem":265,
    "gn:feature_class":"P",
    "gn:feature_code":"PPL",
    "gn:name":"Pingdi",
    "gn:population":0,
    "gn:timezone":"Asia/Shanghai",
    "iso:country":"CN",
    "name:zho_x_preferred":[
        "Pingdi"
    ],
    "name:zho_x_variant":[
        "\u576a\u5e95"
    ],
    "wof:name":"Pingdi",
    "wof:placetype":"locality"
},
  "geometry": {"coordinates":[112.73721999999999,24.2375],"type":"Point"}
}