{
  "type": "Feature",
  "properties": {
    "gn:admin1_code":"15.0",
    "gn:asciiname":"Jiantai",
    "gn:country_code":"CN",
    "gn:dem":1412,
    "gn:feature_class":"P",
    "gn:feature_code":"PPL",
    "gn:name":"Jiantai",
    "gn:population":0,
    "gn:timezone":"Asia/Shanghai",
    "iso:country":"CN",
    "name:zho_x_preferred":[
        "\u7bad\u53f0"
    ],
    "wof:name":"Jiantai",
    "wof:placetype":"locality"
},
  "geometry": {"coordinates":[100.33199999999999,39.1723],"type":"Point"}
}