{
  "type": "Feature",
  "properties": {
    "gn:admin1_code":"16",
    "gn:asciiname":"Malu'an",
    "gn:country_code":"CN",
    "gn:dem":387,
    "gn:feature_class":"P",
    "gn:feature_code":"PPL",
    "gn:name":"Malu\u2019an",
    "gn:population":0,
    "gn:timezone":"Asia/Shanghai",
    "iso:country":"CN",
    "name:und_x_variant":[
        "Malu\u2019an"
    ],
    "name:zho_x_preferred":[
        "\u9a6c\u9a74\u978d"
    ],
    "wof:name":"Malu'an",
    "wof:placetype":"locality"
},
  "geometry": {"coordinates":[110.736,25.0864],"type":"Point"}
}