{
  "type": "Feature",
  "properties": {
    "gn:admin1_code":"31.0",
    "gn:asciiname":"Ruxue",
    "gn:country_code":"CN",
    "gn:dem":16,
    "gn:feature_class":"P",
    "gn:feature_code":"PPL",
    "gn:name":"Ruxue",
    "gn:population":0,
    "gn:timezone":"Asia/Shanghai",
    "iso:country":"CN",
    "name:zho_x_preferred":[
        "\u5165\u5b66"
    ],
    "wof:name":"Ruxue",
    "wof:placetype":"locality"
},
  "geometry": {"coordinates":[108.64633000000001,18.86923],"type":"Point"}
}