{
  "type": "Feature",
  "properties": {
    "gn:admin1_code":"16.0",
    "gn:asciiname":"Bili",
    "gn:country_code":"CN",
    "gn:dem":438,
    "gn:feature_class":"P",
    "gn:feature_code":"PPL",
    "gn:name":"Bili",
    "gn:population":0,
    "gn:timezone":"Asia/Shanghai",
    "iso:country":"CN",
    "name:bre_x_preferred":[
        "Bili"
    ],
    "name:ceb_x_preferred":[
        "Bili"
    ],
    "name:fra_x_preferred":[
        "Bili"
    ],
    "name:kat_x_preferred":[
        "\u10d1\u10d8\u10da\u10d8"
    ],
    "name:swe_x_preferred":[
        "Bili"
    ],
    "name:zho_x_preferred":[
        "\u5fc5\u529b"
    ],
    "wof:name":"Bili",
    "wof:placetype":"locality"
},
  "geometry": {"coordinates":[107.605,24.0979],"type":"Point"}
}