{
  "type": "Feature",
  "properties": {
    "gn:admin1_code":"12.0",
    "gn:asciiname":"Lianglukou",
    "gn:country_code":"CN",
    "gn:dem":219,
    "gn:feature_class":"P",
    "gn:feature_code":"PPL",
    "gn:name":"Lianglukou",
    "gn:population":0,
    "gn:timezone":"Asia/Shanghai",
    "iso:country":"CN",
    "name:zho_x_preferred":[
        "\u4e24\u8def\u53e3"
    ],
    "wof:name":"Lianglukou",
    "wof:placetype":"locality"
},
  "geometry": {"coordinates":[115.15129,31.56406],"type":"Point"}
}