{
  "type": "Feature",
  "properties": {
    "gn:admin1_code":"5.0",
    "gn:asciiname":"Renaojie",
    "gn:country_code":"CN",
    "gn:dem":323,
    "gn:feature_class":"P",
    "gn:feature_code":"PPL",
    "gn:name":"Renaojie",
    "gn:population":0,
    "gn:timezone":"Asia/Shanghai",
    "iso:country":"CN",
    "name:zho_x_preferred":[
        "\u70ed\u95f9\u8857"
    ],
    "wof:name":"Renaojie",
    "wof:placetype":"locality"
},
  "geometry": {"coordinates":[125.81476000000001,42.79447],"type":"Point"}
}