{
  "type": "Feature",
  "properties": {
    "gn:admin1_code":"02",
    "gn:asciiname":"Qijia Dashan",
    "gn:country_code":"CN",
    "gn:dem":154,
    "gn:feature_class":"P",
    "gn:feature_code":"PPL",
    "gn:name":"Qijia Dashan",
    "gn:population":0,
    "gn:timezone":"Asia/Shanghai",
    "iso:country":"CN",
    "name:und_x_variant":[
        "Chi-chia-ta-shan",
        "Qijia Dashan",
        "\u621a\u5bb6\u5927\u5c71"
    ],
    "wof:name":"Qijia Dashan",
    "wof:placetype":"locality"
},
  "geometry": {"coordinates":[121.28167000000001,30.07944],"type":"Point"}
}