{
  "type": "Feature",
  "properties": {
    "gn:admin1_code":"16",
    "gn:asciiname":"Pingjie",
    "gn:country_code":"CN",
    "gn:dem":445,
    "gn:feature_class":"P",
    "gn:feature_code":"PPL",
    "gn:name":"Pingjie",
    "gn:population":0,
    "gn:timezone":"Asia/Shanghai",
    "iso:country":"CN",
    "name:zho_x_preferred":[
        "\u5e73\u8857"
    ],
    "wof:name":"Pingjie",
    "wof:placetype":"locality"
},
  "geometry": {"coordinates":[110.76900000000001,25.9389],"type":"Point"}
}