{
  "type": "Feature",
  "properties": {
    "gn:admin1_code":"11.0",
    "gn:asciiname":"Yaojiaxi",
    "gn:country_code":"CN",
    "gn:dem":854,
    "gn:feature_class":"P",
    "gn:feature_code":"PPL",
    "gn:name":"Yaojiaxi",
    "gn:population":0,
    "gn:timezone":"Asia/Shanghai",
    "iso:country":"CN",
    "name:zho_x_preferred":[
        "Yaojiaxi"
    ],
    "name:zho_x_variant":[
        "\u59da\u5bb6\u6eaa"
    ],
    "wof:name":"Yaojiaxi",
    "wof:placetype":"locality"
},
  "geometry": {"coordinates":[110.35312999999999,28.89109],"type":"Point"}
}