{
  "type": "Feature",
  "properties": {
    "gn:admin1_code":"9",
    "gn:asciiname":"Wanglou",
    "gn:country_code":"CN",
    "gn:dem":44,
    "gn:feature_class":"P",
    "gn:feature_code":"PPL",
    "gn:name":"Wanglou",
    "gn:population":0,
    "gn:timezone":"Asia/Shanghai",
    "iso:country":"CN",
    "name:zho_x_preferred":[
        "\u738b\u697c"
    ],
    "wof:name":"Wanglou",
    "wof:placetype":"locality"
},
  "geometry": {"coordinates":[116.104,34.242],"type":"Point"}
}