{
  "type": "Feature",
  "properties": {
    "gn:admin1_code":"05",
    "gn:asciiname":"Yushugou",
    "gn:country_code":"CN",
    "gn:dem":323,
    "gn:feature_class":"P",
    "gn:feature_code":"PPLA4",
    "gn:name":"Yushugou",
    "gn:population":0,
    "gn:timezone":"Asia/Shanghai",
    "iso:country":"CN",
    "name:und_x_variant":[
        "Y\u00fc-shu-kou",
        "Yushugou",
        "Yushugou Xiang"
    ],
    "name:zho_x_preferred":[
        "\u6986\u6811\u6c9f"
    ],
    "name:zho_x_variant":[
        "\u6986\u6811\u6c9f\u4e61"
    ],
    "wof:name":"Yushugou",
    "wof:placetype":"locality"
},
  "geometry": {"coordinates":[127.53072,44.124],"type":"Point"}
}