{
  "type": "Feature",
  "properties": {
    "gn:admin1_code":"10",
    "gn:asciiname":"Beibu",
    "gn:country_code":"CN",
    "gn:dem":3,
    "gn:feature_class":"P",
    "gn:feature_code":"PPL",
    "gn:name":"Beibu",
    "gn:population":0,
    "gn:timezone":"Asia/Shanghai",
    "iso:country":"CN",
    "name:und_x_variant":[
        "Pei-pao",
        "Beipu",
        "Beibu"
    ],
    "name:zho_x_preferred":[
        "\u5317\u5821"
    ],
    "wof:name":"Beibu",
    "wof:placetype":"locality"
},
  "geometry": {"coordinates":[118.23333,39.11667],"type":"Point"}
}