{
  "type": "Feature",
  "properties": {
    "gn:admin1_code":"32.0",
    "gn:asciiname":"Xialakan",
    "gn:country_code":"CN",
    "gn:dem":3014,
    "gn:feature_class":"P",
    "gn:feature_code":"PPL",
    "gn:name":"Xialakan",
    "gn:population":0,
    "gn:timezone":"Asia/Shanghai",
    "iso:country":"CN",
    "name:zho_x_preferred":[
        "\u5477\u62c9\u574e"
    ],
    "wof:name":"Xialakan",
    "wof:placetype":"locality"
},
  "geometry": {"coordinates":[101.07599999999999,30.5332],"type":"Point"}
}