{
  "type": "Feature",
  "properties": {
    "gn:admin1_code":"30.0",
    "gn:asciiname":"Guoyuan",
    "gn:country_code":"CN",
    "gn:dem":36,
    "gn:feature_class":"P",
    "gn:feature_code":"PPL",
    "gn:name":"Guoyuan",
    "gn:population":0,
    "gn:timezone":"Asia/Shanghai",
    "iso:country":"CN",
    "name:zho_x_preferred":[
        "\u679c\u56ed"
    ],
    "wof:name":"Guoyuan",
    "wof:placetype":"locality"
},
  "geometry": {"coordinates":[114.07637,23.27054],"type":"Point"}
}