{
  "type": "Feature",
  "properties": {
    "gn:admin1_code":"18.0",
    "gn:asciiname":"Pingcha",
    "gn:country_code":"CN",
    "gn:dem":641,
    "gn:feature_class":"P",
    "gn:feature_code":"PPL",
    "gn:name":"Pingcha",
    "gn:population":0,
    "gn:timezone":"Asia/Shanghai",
    "iso:country":"CN",
    "name:zho_x_preferred":[
        "\u5e73\u8336"
    ],
    "name:zho_x_variant":[
        "\u5e73\u8336\u9547"
    ],
    "wof:name":"Pingcha",
    "wof:placetype":"locality"
},
  "geometry": {"coordinates":[109.316,25.7513],"type":"Point"}
}