{
  "type": "Feature",
  "properties": {
    "gn:admin1_code":"16.0",
    "gn:asciiname":"Youjiao",
    "gn:country_code":"CN",
    "gn:dem":810,
    "gn:feature_class":"P",
    "gn:feature_code":"PPL",
    "gn:name":"Youjiao",
    "gn:population":0,
    "gn:timezone":"Asia/Shanghai",
    "iso:country":"CN",
    "name:zho_x_preferred":[
        "\u7531\u89d2"
    ],
    "wof:name":"Youjiao",
    "wof:placetype":"locality"
},
  "geometry": {"coordinates":[107.08199999999999,25.5653],"type":"Point"}
}