{
  "type": "Feature",
  "properties": {
    "gn:admin1_code":"32.0",
    "gn:asciiname":"Mingguangsi",
    "gn:country_code":"CN",
    "gn:dem":960,
    "gn:feature_class":"P",
    "gn:feature_code":"PPL",
    "gn:name":"Mingguangsi",
    "gn:population":0,
    "gn:timezone":"Asia/Shanghai",
    "iso:country":"CN",
    "name:zho_x_preferred":[
        "\u660e\u5149\u5bfa"
    ],
    "wof:name":"Mingguangsi",
    "wof:placetype":"locality"
},
  "geometry": {"coordinates":[106.94587,30.47949],"type":"Point"}
}