{
  "type": "Feature",
  "properties": {
    "gn:admin1_code":"19.0",
    "gn:asciiname":"Nanta Xishan",
    "gn:country_code":"CN",
    "gn:dem":390,
    "gn:feature_class":"P",
    "gn:feature_code":"PPL",
    "gn:name":"Nanta Xishan",
    "gn:population":0,
    "gn:timezone":"Asia/Shanghai",
    "iso:country":"CN",
    "name:zho_x_preferred":[
        "\u5357\u5854\u897f\u5c71"
    ],
    "wof:name":"Nanta Xishan",
    "wof:placetype":"locality"
},
  "geometry": {"coordinates":[120.229,41.1821],"type":"Point"}
}