{
  "type": "Feature",
  "properties": {
    "gn:admin1_code":"32.0",
    "gn:asciiname":"Fengshi",
    "gn:country_code":"CN",
    "gn:dem":362,
    "gn:feature_class":"P",
    "gn:feature_code":"PPL",
    "gn:name":"Fengshi",
    "gn:population":0,
    "gn:timezone":"Asia/Shanghai",
    "iso:country":"CN",
    "name:zho_x_preferred":[
        "\u5cf0\u77f3"
    ],
    "wof:name":"Fengshi",
    "wof:placetype":"locality"
},
  "geometry": {"coordinates":[107.616,31.2841],"type":"Point"}
}