{
  "type": "Feature",
  "properties": {
    "gn:admin1_code":"30.0",
    "gn:asciiname":"Luxiajiao",
    "gn:country_code":"CN",
    "gn:dem":282,
    "gn:feature_class":"P",
    "gn:feature_code":"PPL",
    "gn:name":"Luxiajiao",
    "gn:population":0,
    "gn:timezone":"Asia/Shanghai",
    "iso:country":"CN",
    "name:zho_x_preferred":[
        "\u7089\u4e0b\u89d2"
    ],
    "wof:name":"Luxiajiao",
    "wof:placetype":"locality"
},
  "geometry": {"coordinates":[113.175,24.44833],"type":"Point"}
}