{
  "type": "Feature",
  "properties": {
    "gn:admin1_code":"30",
    "gn:asciiname":"Houpoliaocun",
    "gn:country_code":"CN",
    "gn:dem":69,
    "gn:feature_class":"P",
    "gn:feature_code":"PPL",
    "gn:name":"Houpoliaocun",
    "gn:population":0,
    "gn:timezone":"Asia/Urumqi",
    "iso:country":"CN",
    "name:zho_x_preferred":[
        "\u540e\u5761\u5bee\u6751"
    ],
    "wof:name":"Houpoliaocun",
    "wof:placetype":"locality"
},
  "geometry": {"coordinates":[110.09175999999999,20.35915],"type":"Point"}
}