{
  "type": "Feature",
  "properties": {
    "gn:admin1_code":"24.0",
    "gn:asciiname":"Zhangguangpo",
    "gn:country_code":"CN",
    "gn:dem":2298,
    "gn:feature_class":"P",
    "gn:feature_code":"PPL",
    "gn:name":"Zhangguangpo",
    "gn:population":0,
    "gn:timezone":"Asia/Shanghai",
    "iso:country":"CN",
    "name:und_x_variant":[
        "\u5f20\u5e7f\u5761"
    ],
    "name:zho_x_preferred":[
        "\u5f20\u5e7f\u5761"
    ],
    "wof:name":"Zhangguangpo",
    "wof:placetype":"locality"
},
  "geometry": {"coordinates":[112.02544,38.84634000000001],"type":"Point"}
}