{
  "type": "Feature",
  "properties": {
    "gn:admin1_code":"5.0",
    "gn:asciiname":"Jiguanshancun",
    "gn:country_code":"CN",
    "gn:dem":217,
    "gn:feature_class":"P",
    "gn:feature_code":"PPL",
    "gn:name":"Jiguanshancun",
    "gn:population":0,
    "gn:timezone":"Asia/Shanghai",
    "iso:country":"CN",
    "name:zho_x_preferred":[
        "\u9e21\u51a0\u5c71\u6751"
    ],
    "wof:name":"Jiguanshancun",
    "wof:placetype":"locality"
},
  "geometry": {"coordinates":[126.55665999999999,43.74687],"type":"Point"}
}