{
  "type": "Feature",
  "properties": {
    "gn:admin1_code":"15.0",
    "gn:asciiname":"Balisi",
    "gn:country_code":"CN",
    "gn:dem":2477,
    "gn:feature_class":"P",
    "gn:feature_code":"PPL",
    "gn:name":"Balisi",
    "gn:population":0,
    "gn:timezone":"Asia/Shanghai",
    "iso:country":"CN",
    "name:und_x_variant":[
        "\u516b\u91cc\u5bfa"
    ],
    "wof:name":"Balisi",
    "wof:placetype":"locality"
},
  "geometry": {"coordinates":[102.85286000000001,35.53426],"type":"Point"}
}