{
  "type": "Feature",
  "properties": {
    "gn:admin1_code":"32.0",
    "gn:asciiname":"Ranjiawan",
    "gn:country_code":"CN",
    "gn:dem":1125,
    "gn:feature_class":"P",
    "gn:feature_code":"PPL",
    "gn:name":"Ranjiawan",
    "gn:population":0,
    "gn:timezone":"Asia/Shanghai",
    "iso:country":"CN",
    "name:zho_x_preferred":[
        "\u5189\u5bb6\u6e7e"
    ],
    "wof:name":"Ranjiawan",
    "wof:placetype":"locality"
},
  "geometry": {"coordinates":[108.121,32.2043],"type":"Point"}
}