{
  "type": "Feature",
  "properties": {
    "gn:admin1_code":"12.0",
    "gn:asciiname":"Wawuwan",
    "gn:country_code":"CN",
    "gn:dem":206,
    "gn:feature_class":"P",
    "gn:feature_code":"PPL",
    "gn:name":"Wawuwan",
    "gn:population":0,
    "gn:timezone":"Asia/Shanghai",
    "iso:country":"CN",
    "name:zho_x_preferred":[
        "\u74e6\u5c4b\u5846"
    ],
    "wof:name":"Wawuwan",
    "wof:placetype":"locality"
},
  "geometry": {"coordinates":[113.59396,32.14268],"type":"Point"}
}