{
  "type": "Feature",
  "properties": {
    "gn:admin1_code":"5.0",
    "gn:asciiname":"Caijia Wobu",
    "gn:country_code":"CN",
    "gn:dem":166,
    "gn:feature_class":"P",
    "gn:feature_code":"PPL",
    "gn:name":"Caijia Wobu",
    "gn:population":0,
    "gn:timezone":"Asia/Shanghai",
    "iso:country":"CN",
    "name:zho_x_preferred":[
        "\u8521\u5bb6\u7a9d\u5821"
    ],
    "wof:name":"Caijia Wobu",
    "wof:placetype":"locality"
},
  "geometry": {"coordinates":[125.13785,45.117],"type":"Point"}
}