{
  "type": "Feature",
  "properties": {
    "gn:admin1_code":"18.0",
    "gn:asciiname":"Maogoutang",
    "gn:country_code":"CN",
    "gn:dem":1264,
    "gn:feature_class":"P",
    "gn:feature_code":"PPL",
    "gn:name":"Maogoutang",
    "gn:population":0,
    "gn:timezone":"Asia/Shanghai",
    "iso:country":"CN",
    "name:zho_x_preferred":[
        "\u6bdb\u72d7\u5858"
    ],
    "wof:name":"Maogoutang",
    "wof:placetype":"locality"
},
  "geometry": {"coordinates":[107.587,27.0156],"type":"Point"}
}