{
  "type": "Feature",
  "properties": {
    "gn:admin1_code":"1.0",
    "gn:asciiname":"Daiducun",
    "gn:country_code":"CN",
    "gn:dem":7,
    "gn:feature_class":"P",
    "gn:feature_code":"PPL",
    "gn:name":"Daiducun",
    "gn:population":0,
    "gn:timezone":"Asia/Shanghai",
    "iso:country":"CN",
    "name:zho_x_preferred":[
        "\u6234\u6e21\u6751"
    ],
    "wof:name":"Daiducun",
    "wof:placetype":"locality"
},
  "geometry": {"coordinates":[117.69450999999999,31.15983],"type":"Point"}
}