{
  "type": "Feature",
  "properties": {
    "gn:admin1_code":"4.0",
    "gn:asciiname":"Doubeicun",
    "gn:country_code":"CN",
    "gn:dem":16,
    "gn:feature_class":"P",
    "gn:feature_code":"PPL",
    "gn:name":"Doubeicun",
    "gn:population":0,
    "gn:timezone":"Asia/Shanghai",
    "iso:country":"CN",
    "name:zho_x_preferred":[
        "\u9661\u5317\u6751"
    ],
    "wof:name":"Doubeicun",
    "wof:placetype":"locality"
},
  "geometry": {"coordinates":[118.38952999999999,33.0531],"type":"Point"}
}