{
  "type": "Feature",
  "properties": {
    "gn:admin1_code":"12.0",
    "gn:asciiname":"Jiangyoupu",
    "gn:country_code":"CN",
    "gn:dem":58,
    "gn:feature_class":"P",
    "gn:feature_code":"PPL",
    "gn:name":"Jiangyoupu",
    "gn:population":0,
    "gn:timezone":"Asia/Shanghai",
    "iso:country":"CN",
    "name:zho_x_preferred":[
        "Jiangyoupu"
    ],
    "name:zho_x_variant":[
        "\u6c5f\u6cb9\u94fa"
    ],
    "wof:name":"Jiangyoupu",
    "wof:placetype":"locality"
},
  "geometry": {"coordinates":[115.32829,30.31029],"type":"Point"}
}