{
  "type": "Feature",
  "properties": {
    "gn:admin1_code":"16.0",
    "gn:asciiname":"Yutoutang",
    "gn:country_code":"CN",
    "gn:dem":38,
    "gn:feature_class":"P",
    "gn:feature_code":"PPL",
    "gn:name":"Yutoutang",
    "gn:population":0,
    "gn:timezone":"Asia/Shanghai",
    "iso:country":"CN",
    "name:zho_x_preferred":[
        "\u828b\u5934\u5858"
    ],
    "wof:name":"Yutoutang",
    "wof:placetype":"locality"
},
  "geometry": {"coordinates":[109.492,21.6457],"type":"Point"}
}