{
  "type": "Feature",
  "properties": {
    "gn:admin1_code":"3.0",
    "gn:asciiname":"Yuanping",
    "gn:country_code":"CN",
    "gn:dem":189,
    "gn:feature_class":"P",
    "gn:feature_code":"PPL",
    "gn:name":"Yuanping",
    "gn:population":0,
    "gn:timezone":"Asia/Shanghai",
    "iso:country":"CN",
    "name:und_x_variant":[
        "\u56ed\u576a"
    ],
    "wof:name":"Yuanping",
    "wof:placetype":"locality"
},
  "geometry": {"coordinates":[115.14935,28.74674000000001],"type":"Point"}
}