{
  "type": "Feature",
  "properties": {
    "gn:admin1_code":"05",
    "gn:asciiname":"T'ang-t'un",
    "gn:country_code":"CN",
    "gn:dem":311,
    "gn:feature_class":"P",
    "gn:feature_code":"PPL",
    "gn:name":"T\u2019ang-t\u2019un",
    "gn:population":0,
    "gn:timezone":"Asia/Shanghai",
    "iso:country":"CN",
    "wof:name":"T'ang-t'un",
    "wof:placetype":"locality"
},
  "geometry": {"coordinates":[126.12860999999999,42.62722],"type":"Point"}
}