{
  "type": "Feature",
  "properties": {
    "gn:admin1_code":"03",
    "gn:asciiname":"Guzhu",
    "gn:cc2":"CN",
    "gn:country_code":"CN",
    "gn:dem":597,
    "gn:feature_class":"P",
    "gn:feature_code":"PPL",
    "gn:name":"Guzhu",
    "gn:population":0,
    "gn:timezone":"Asia/Shanghai",
    "iso:country":"CN",
    "name:jpn_x_preferred":[
        "\u5b64\u7af9\u56fd"
    ],
    "name:kor_x_preferred":[
        "\uace0\uc8fd\uad6d"
    ],
    "name:und_x_variant":[
        "K\u2019u-chu-hs\u00fc",
        "Ku-chu",
        "Guzhu"
    ],
    "name:vie_x_preferred":[
        "C\u00f4 Tr\u00fac"
    ],
    "name:zho_x_preferred":[
        "\u5b64\u7af9\u56fd"
    ],
    "wof:name":"Guzhu",
    "wof:placetype":"locality"
},
  "geometry": {"coordinates":[116.15000000000001,26.91667],"type":"Point"}
}