{
  "type": "Feature",
  "properties": {
    "gn:admin1_code":"26.0",
    "gn:asciiname":"Huoshiwan",
    "gn:country_code":"CN",
    "gn:dem":1568,
    "gn:feature_class":"P",
    "gn:feature_code":"PPL",
    "gn:name":"Huoshiwan",
    "gn:population":0,
    "gn:timezone":"Asia/Shanghai",
    "iso:country":"CN",
    "name:und_x_variant":[
        "\u706b\u77f3\u6e7e"
    ],
    "wof:name":"Huoshiwan",
    "wof:placetype":"locality"
},
  "geometry": {"coordinates":[106.30606,32.74036],"type":"Point"}
}