{
  "type": "Feature",
  "properties": {
    "gn:admin1_code":"30",
    "gn:asciiname":"Yangtaoshan",
    "gn:country_code":"CN",
    "gn:dem":214,
    "gn:feature_class":"P",
    "gn:feature_code":"PPL",
    "gn:name":"Yangtaoshan",
    "gn:population":0,
    "gn:timezone":"Asia/Shanghai",
    "iso:country":"CN",
    "name:und_x_variant":[
        "\u6768\u6843\u5c71",
        "Yangtaoshan"
    ],
    "wof:name":"Yangtaoshan",
    "wof:placetype":"locality"
},
  "geometry": {"coordinates":[115.59674,24.10513],"type":"Point"}
}