{
  "type": "Feature",
  "properties": {
    "gn:admin1_code":"32.0",
    "gn:asciiname":"Xintangfang",
    "gn:country_code":"CN",
    "gn:dem":329,
    "gn:feature_class":"P",
    "gn:feature_code":"PPL",
    "gn:name":"Xintangfang",
    "gn:population":0,
    "gn:timezone":"Asia/Shanghai",
    "iso:country":"CN",
    "name:zho_x_preferred":[
        "\u65b0\u7cd6\u574a"
    ],
    "wof:name":"Xintangfang",
    "wof:placetype":"locality"
},
  "geometry": {"coordinates":[105.00779,29.57843],"type":"Point"}
}