{
  "type": "Feature",
  "properties": {
    "gn:admin1_code":"29.0",
    "gn:asciiname":"Long'ai",
    "gn:country_code":"CN",
    "gn:dem":1612,
    "gn:feature_class":"P",
    "gn:feature_code":"PPL",
    "gn:name":"Long\u2019ai",
    "gn:population":0,
    "gn:timezone":"Asia/Shanghai",
    "iso:country":"CN",
    "name:und_x_variant":[
        "Long\u2019ai"
    ],
    "name:zho_x_preferred":[
        "\u9f99\u827e"
    ],
    "wof:name":"Long'ai",
    "wof:placetype":"locality"
},
  "geometry": {"coordinates":[104.514,23.6218],"type":"Point"}
}