{
  "type": "Feature",
  "properties": {
    "gn:admin1_code":"13.0",
    "gn:asciiname":"Tashiqi Maili",
    "gn:country_code":"CN",
    "gn:dem":1329,
    "gn:feature_class":"P",
    "gn:feature_code":"PPL",
    "gn:name":"Tashiqi Maili",
    "gn:population":0,
    "gn:timezone":"Asia/Shanghai",
    "iso:country":"CN",
    "name:zho_x_preferred":[
        "\u5854\u4ec0\u5176\u4e70\u91cc"
    ],
    "wof:name":"Tashiqi Maili",
    "wof:placetype":"locality"
},
  "geometry": {"coordinates":[79.94995,37.17304],"type":"Point"}
}