{
  "type": "Feature",
  "properties": {
    "gn:admin1_code":"32.0",
    "gn:asciiname":"Yijue",
    "gn:country_code":"CN",
    "gn:dem":2242,
    "gn:feature_class":"P",
    "gn:feature_code":"PPL",
    "gn:name":"Yijue",
    "gn:population":0,
    "gn:timezone":"Asia/Shanghai",
    "iso:country":"CN",
    "name:zho_x_preferred":[
        "\u4f9d\u89c9"
    ],
    "wof:name":"Yijue",
    "wof:placetype":"locality"
},
  "geometry": {"coordinates":[103.053,28.2453],"type":"Point"}
}