{
  "type": "Feature",
  "properties": {
    "gn:admin1_code":"02",
    "gn:asciiname":"Kantoucun",
    "gn:country_code":"CN",
    "gn:dem":82,
    "gn:feature_class":"P",
    "gn:feature_code":"PPL",
    "gn:name":"Kantoucun",
    "gn:population":0,
    "gn:timezone":"Asia/Shanghai",
    "iso:country":"CN",
    "name:und_x_variant":[
        "Kantou",
        "Kantoucun"
    ],
    "name:zho_x_preferred":[
        "\u574e\u5934"
    ],
    "name:zho_x_variant":[
        "\u574e\u5934\u6751"
    ],
    "wof:name":"Kantoucun",
    "wof:placetype":"locality"
},
  "geometry": {"coordinates":[121.27271,29.06488],"type":"Point"}
}