{
  "type": "Feature",
  "properties": {
    "gn:admin1_code":"2.0",
    "gn:asciiname":"Shangzhang Jiabu",
    "gn:country_code":"CN",
    "gn:dem":47,
    "gn:feature_class":"P",
    "gn:feature_code":"PPL",
    "gn:name":"Shangzhang Jiabu",
    "gn:population":0,
    "gn:timezone":"Asia/Shanghai",
    "iso:country":"CN",
    "name:zho_x_preferred":[
        "\u4e0a\u5f20\u5bb6\u57e0"
    ],
    "wof:name":"Shangzhang Jiabu",
    "wof:placetype":"locality"
},
  "geometry": {"coordinates":[119.21302,29.07332],"type":"Point"}
}