{
  "type": "Feature",
  "properties": {
    "gn:admin1_code":"31.0",
    "gn:asciiname":"Shanrong Xiangcai Fadui",
    "gn:country_code":"CN",
    "gn:dem":245,
    "gn:feature_class":"P",
    "gn:feature_code":"PPLF",
    "gn:name":"Shanrong Xiangcai Fadui",
    "gn:population":0,
    "gn:timezone":"Asia/Shanghai",
    "iso:country":"CN",
    "name:und_x_variant":[
        "\u5c71\u8363\u4e61\u91c7\u4f10\u961f"
    ],
    "wof:name":"Shanrong Xiangcai Fadui",
    "wof:placetype":"locality"
},
  "geometry": {"coordinates":[109.06082000000001,18.77288],"type":"Point"}
}