{
  "type": "Feature",
  "properties": {
    "gn:admin1_code":"3",
    "gn:asciiname":"Jinjixu",
    "gn:country_code":"CN",
    "gn:dem":195,
    "gn:feature_class":"P",
    "gn:feature_code":"PPL",
    "gn:name":"Jinjixu",
    "gn:population":0,
    "gn:timezone":"Asia/Shanghai",
    "iso:country":"CN",
    "name:und_x_variant":[
        "\u91d1\u9e21\u5729"
    ],
    "wof:name":"Jinjixu",
    "wof:placetype":"locality"
},
  "geometry": {"coordinates":[115.21213,25.39997],"type":"Point"}
}