{
  "type": "Feature",
  "properties": {
    "gn:admin1_code":"10",
    "gn:asciiname":"Balisenggou",
    "gn:country_code":"CN",
    "gn:dem":954,
    "gn:feature_class":"P",
    "gn:feature_code":"PPL",
    "gn:name":"Balisenggou",
    "gn:population":0,
    "gn:timezone":"Asia/Shanghai",
    "iso:country":"CN",
    "name:zho_x_preferred":[
        "\u516b\u91cc\u50e7\u6c9f"
    ],
    "wof:name":"Balisenggou",
    "wof:placetype":"locality"
},
  "geometry": {"coordinates":[117.51134999999999,41.61547],"type":"Point"}
}