{
  "type": "Feature",
  "properties": {
    "gn:admin1_code":"26.0",
    "gn:asciiname":"Gaofengsi",
    "gn:country_code":"CN",
    "gn:dem":1416,
    "gn:feature_class":"P",
    "gn:feature_code":"PPL",
    "gn:name":"Gaofengsi",
    "gn:population":0,
    "gn:timezone":"Asia/Shanghai",
    "iso:country":"CN",
    "name:und_x_variant":[
        "\u9ad8\u4e30\u5bfa"
    ],
    "wof:name":"Gaofengsi",
    "wof:placetype":"locality"
},
  "geometry": {"coordinates":[107.51163,34.78041],"type":"Point"}
}