{
  "type": "Feature",
  "properties": {
    "gn:admin1_code":"31",
    "gn:asciiname":"Bangxi Nongchang Jiudui",
    "gn:country_code":"CN",
    "gn:dem":48,
    "gn:feature_class":"P",
    "gn:feature_code":"PPLF",
    "gn:name":"Bangxi Nongchang Jiudui",
    "gn:population":0,
    "gn:timezone":"Asia/Shanghai",
    "iso:country":"CN",
    "name:und_x_variant":[
        "\u90a6\u6eaa\u519c\u573a\u4e5d\u961f",
        "Bangxizhengu"
    ],
    "wof:name":"Bangxi Nongchang Jiudui",
    "wof:placetype":"locality"
},
  "geometry": {"coordinates":[109.07092,19.39943],"type":"Point"}
}