{
  "type": "Feature",
  "properties": {
    "gn:admin1_code":"7.0",
    "gn:asciiname":"Zhongyangli",
    "gn:country_code":"CN",
    "gn:dem":851,
    "gn:feature_class":"P",
    "gn:feature_code":"PPL",
    "gn:name":"Zhongyangli",
    "gn:population":0,
    "gn:timezone":"Asia/Shanghai",
    "iso:country":"CN",
    "name:zho_x_preferred":[
        "\u4e2d\u6d0b\u91cc"
    ],
    "wof:name":"Zhongyangli",
    "wof:placetype":"locality"
},
  "geometry": {"coordinates":[119.28633000000001,26.78446],"type":"Point"}
}