{
  "type": "Feature",
  "properties": {
    "gn:admin1_code":"26.0",
    "gn:asciiname":"Beipocun",
    "gn:country_code":"CN",
    "gn:dem":1088,
    "gn:feature_class":"P",
    "gn:feature_code":"PPL",
    "gn:name":"Beipocun",
    "gn:population":0,
    "gn:timezone":"Asia/Shanghai",
    "iso:country":"CN",
    "name:zho_x_preferred":[
        "\u80cc\u5761\u6751"
    ],
    "wof:name":"Beipocun",
    "wof:placetype":"locality"
},
  "geometry": {"coordinates":[109.22727999999999,36.17723],"type":"Point"}
}