{
  "type": "Feature",
  "properties": {
    "gn:admin1_code":"16.0",
    "gn:asciiname":"Gudu",
    "gn:country_code":"CN",
    "gn:dem":119,
    "gn:feature_class":"P",
    "gn:feature_code":"PPL",
    "gn:name":"Gudu",
    "gn:population":0,
    "gn:timezone":"Asia/Shanghai",
    "iso:country":"CN",
    "name:ceb_x_preferred":[
        "Gudu"
    ],
    "name:fra_x_preferred":[
        "Gudu"
    ],
    "name:glg_x_preferred":[
        "Gudu"
    ],
    "name:hau_x_preferred":[
        "Gudu"
    ],
    "name:ita_x_preferred":[
        "Gudu"
    ],
    "name:por_x_preferred":[
        "Gudu"
    ],
    "name:spa_x_preferred":[
        "Gudu"
    ],
    "name:zho_x_preferred":[
        "\u53e4\u90fd"
    ],
    "wof:name":"Gudu",
    "wof:placetype":"locality"
},
  "geometry": {"coordinates":[109.21899999999999,24.9567],"type":"Point"}
}