{
  "type": "Feature",
  "properties": {
    "gn:admin1_code":"19.0",
    "gn:asciiname":"Xuannucun",
    "gn:country_code":"CN",
    "gn:dem":74,
    "gn:feature_class":"P",
    "gn:feature_code":"PPL",
    "gn:name":"Xuann\u00fccun",
    "gn:population":0,
    "gn:timezone":"Asia/Shanghai",
    "iso:country":"CN",
    "name:und_x_variant":[
        "Xuann\u00fccun",
        "Xuann\u00fcwobao",
        "Xuann\u00fc Wobu"
    ],
    "name:zho_x_preferred":[
        "\u5ba3\u5973\u6751"
    ],
    "name:zho_x_variant":[
        "\u5ba3\u5973\u7a9d\u5821"
    ],
    "wof:name":"Xuannucun",
    "wof:placetype":"locality"
},
  "geometry": {"coordinates":[122.414,42.2525],"type":"Point"}
}