{
  "type": "Feature",
  "properties": {
    "gn:admin1_code":"4.0",
    "gn:asciiname":"Zhenghecun",
    "gn:country_code":"CN",
    "gn:dem":3,
    "gn:feature_class":"P",
    "gn:feature_code":"PPL",
    "gn:name":"Zhenghecun",
    "gn:population":0,
    "gn:timezone":"Asia/Shanghai",
    "iso:country":"CN",
    "name:zho_x_preferred":[
        "\u90d1\u6cb3\u6751"
    ],
    "wof:name":"Zhenghecun",
    "wof:placetype":"locality"
},
  "geometry": {"coordinates":[119.34808,33.17609],"type":"Point"}
}