{
  "type": "Feature",
  "properties": {
    "gn:admin1_code":"12.0",
    "gn:asciiname":"Gejiawan",
    "gn:country_code":"CN",
    "gn:dem":121,
    "gn:feature_class":"P",
    "gn:feature_code":"PPL",
    "gn:name":"Gejiawan",
    "gn:population":0,
    "gn:timezone":"Asia/Shanghai",
    "iso:country":"CN",
    "name:zho_x_preferred":[
        "Gejiawan"
    ],
    "name:zho_x_variant":[
        "\u845b\u5bb6\u6e7e"
    ],
    "wof:name":"Gejiawan",
    "wof:placetype":"locality"
},
  "geometry": {"coordinates":[114.70345,29.88292],"type":"Point"}
}