{
  "type": "Feature",
  "properties": {
    "gn:admin1_code":"1.0",
    "gn:asciiname":"Dazhuangcun",
    "gn:country_code":"CN",
    "gn:dem":66,
    "gn:feature_class":"P",
    "gn:feature_code":"PPL",
    "gn:name":"Dazhuangcun",
    "gn:population":0,
    "gn:timezone":"Asia/Shanghai",
    "iso:country":"CN",
    "name:zho_x_preferred":[
        "\u5927\u5e84\u6751"
    ],
    "wof:name":"Dazhuangcun",
    "wof:placetype":"locality"
},
  "geometry": {"coordinates":[117.64587,31.88269],"type":"Point"}
}