{
  "type": "Feature",
  "properties": {
    "gn:admin1_code":"11",
    "gn:asciiname":"Fujiazhou",
    "gn:country_code":"CN",
    "gn:dem":195,
    "gn:feature_class":"P",
    "gn:feature_code":"PPL",
    "gn:name":"Fujiazhou",
    "gn:population":0,
    "gn:timezone":"Asia/Shanghai",
    "iso:country":"CN",
    "name:zho_x_preferred":[
        "\u4ed8\u5bb6\u6d32"
    ],
    "wof:name":"Fujiazhou",
    "wof:placetype":"locality"
},
  "geometry": {"coordinates":[111.44257,27.64236],"type":"Point"}
}