{
  "type": "Feature",
  "properties": {
    "gn:admin1_code":"11.0",
    "gn:asciiname":"Wanzisun",
    "gn:country_code":"CN",
    "gn:dem":280,
    "gn:feature_class":"P",
    "gn:feature_code":"PPL",
    "gn:name":"Wanzisun",
    "gn:population":0,
    "gn:timezone":"Asia/Shanghai",
    "iso:country":"CN",
    "name:zho_x_preferred":[
        "Wanzisun"
    ],
    "name:zho_x_variant":[
        "\u7897\u5b50\u7b0b"
    ],
    "wof:name":"Wanzisun",
    "wof:placetype":"locality"
},
  "geometry": {"coordinates":[111.01382,29.06357],"type":"Point"}
}