{
  "type": "Feature",
  "properties": {
    "gn:admin1_code":"2.0",
    "gn:asciiname":"Longshan Matou",
    "gn:country_code":"CN",
    "gn:dem":3,
    "gn:feature_class":"P",
    "gn:feature_code":"PPL",
    "gn:name":"Longshan Matou",
    "gn:population":0,
    "gn:timezone":"Asia/Shanghai",
    "iso:country":"CN",
    "name:zho_x_preferred":[
        "\u9f99\u5c71\u9a6c\u5934"
    ],
    "wof:name":"Longshan Matou",
    "wof:placetype":"locality"
},
  "geometry": {"coordinates":[121.569,30.11047],"type":"Point"}
}