{
  "type": "Feature",
  "properties": {
    "gn:admin1_code":"11.0",
    "gn:asciiname":"Xintangchong",
    "gn:country_code":"CN",
    "gn:dem":47,
    "gn:feature_class":"P",
    "gn:feature_code":"PPL",
    "gn:name":"Xintangchong",
    "gn:population":0,
    "gn:timezone":"Asia/Shanghai",
    "iso:country":"CN",
    "name:zho_x_preferred":[
        "\u65b0\u5858\u51b2"
    ],
    "wof:name":"Xintangchong",
    "wof:placetype":"locality"
},
  "geometry": {"coordinates":[112.58808999999999,28.45913],"type":"Point"}
}