{
  "type": "Feature",
  "properties": {
    "gn:admin1_code":"5.0",
    "gn:asciiname":"Shangweizi",
    "gn:country_code":"CN",
    "gn:dem":394,
    "gn:feature_class":"P",
    "gn:feature_code":"PPL",
    "gn:name":"Shangweizi",
    "gn:population":0,
    "gn:timezone":"Asia/Shanghai",
    "iso:country":"CN",
    "name:zho_x_preferred":[
        "\u4e0a\u5d34\u5b50"
    ],
    "wof:name":"Shangweizi",
    "wof:placetype":"locality"
},
  "geometry": {"coordinates":[125.25593000000001,42.67908],"type":"Point"}
}