{
  "type": "Feature",
  "properties": {
    "gn:admin1_code":"5.0",
    "gn:asciiname":"Zhuangjiatun",
    "gn:country_code":"CN",
    "gn:dem":152,
    "gn:feature_class":"P",
    "gn:feature_code":"PPL",
    "gn:name":"Zhuangjiatun",
    "gn:population":0,
    "gn:timezone":"Asia/Shanghai",
    "iso:country":"CN",
    "name:zho_x_preferred":[
        "\u5e84\u5bb6\u5c6f"
    ],
    "wof:name":"Zhuangjiatun",
    "wof:placetype":"locality"
},
  "geometry": {"coordinates":[124.21805000000001,43.56577],"type":"Point"}
}