{
  "type": "Feature",
  "properties": {
    "gn:admin1_code":"26.0",
    "gn:asciiname":"Qiaojinggou",
    "gn:country_code":"CN",
    "gn:dem":1144,
    "gn:feature_class":"P",
    "gn:feature_code":"PPL",
    "gn:name":"Qiaojinggou",
    "gn:population":0,
    "gn:timezone":"Asia/Shanghai",
    "iso:country":"CN",
    "name:und_x_variant":[
        "\u6865\u4e95\u6c9f"
    ],
    "wof:name":"Qiaojinggou",
    "wof:placetype":"locality"
},
  "geometry": {"coordinates":[106.05802,33.52631],"type":"Point"}
}