{
  "type": "Feature",
  "properties": {
    "gn:admin1_code":"16.0",
    "gn:asciiname":"Zhengwancun",
    "gn:country_code":"CN",
    "gn:dem":312,
    "gn:feature_class":"P",
    "gn:feature_code":"PPL",
    "gn:name":"Zhengwancun",
    "gn:population":0,
    "gn:timezone":"Asia/Shanghai",
    "iso:country":"CN",
    "name:zho_x_preferred":[
        "\u6b63\u4e07\u6751"
    ],
    "wof:name":"Zhengwancun",
    "wof:placetype":"locality"
},
  "geometry": {"coordinates":[108.468,23.6425],"type":"Point"}
}