{
  "type": "Feature",
  "properties": {
    "gn:admin1_code":"21.0",
    "gn:asciiname":"Nanyanggou",
    "gn:country_code":"CN",
    "gn:dem":1651,
    "gn:feature_class":"P",
    "gn:feature_code":"PPL",
    "gn:name":"Nanyanggou",
    "gn:population":0,
    "gn:timezone":"Asia/Shanghai",
    "iso:country":"CN",
    "name:zho_x_preferred":[
        "\u5357\u9633\u6c9f"
    ],
    "wof:name":"Nanyanggou",
    "wof:placetype":"locality"
},
  "geometry": {"coordinates":[107.128,37.8137],"type":"Point"}
}