{
  "type": "Feature",
  "properties": {
    "gn:admin1_code":"12.0",
    "gn:asciiname":"Guanziyao",
    "gn:country_code":"CN",
    "gn:dem":48,
    "gn:feature_class":"P",
    "gn:feature_code":"PPL",
    "gn:name":"Guanziyao",
    "gn:population":0,
    "gn:timezone":"Asia/Shanghai",
    "iso:country":"CN",
    "name:zho_x_preferred":[
        "\u7f50\u5b50\u7a91"
    ],
    "wof:name":"Guanziyao",
    "wof:placetype":"locality"
},
  "geometry": {"coordinates":[114.42679,31.29284],"type":"Point"}
}