{
  "type": "Feature",
  "properties": {
    "gn:admin1_code":"19.0",
    "gn:asciiname":"Yushutuncun",
    "gn:country_code":"CN",
    "gn:dem":42,
    "gn:feature_class":"P",
    "gn:feature_code":"PPL",
    "gn:name":"Yushutuncun",
    "gn:population":0,
    "gn:timezone":"Asia/Shanghai",
    "iso:country":"CN",
    "name:zho_x_preferred":[
        "\u6986\u6811\u5c6f\u6751"
    ],
    "name:zho_x_variant":[
        "\u4e8e\u6811\u5c6f\u6751"
    ],
    "wof:name":"Yushutuncun",
    "wof:placetype":"locality"
},
  "geometry": {"coordinates":[121.447,41.417],"type":"Point"}
}