{
  "type": "Feature",
  "properties": {
    "gn:admin1_code":"8.0",
    "gn:asciiname":"Yongshengcun",
    "gn:country_code":"CN",
    "gn:dem":214,
    "gn:feature_class":"P",
    "gn:feature_code":"PPL",
    "gn:name":"Yongshengcun",
    "gn:population":0,
    "gn:timezone":"Asia/Shanghai",
    "iso:country":"CN",
    "name:zho_x_preferred":[
        "\u6c38\u80dc\u6751"
    ],
    "wof:name":"Yongshengcun",
    "wof:placetype":"locality"
},
  "geometry": {"coordinates":[126.60330999999999,47.74752],"type":"Point"}
}