{
  "type": "Feature",
  "properties": {
    "gn:admin1_code":"33.0",
    "gn:asciiname":"Maliu",
    "gn:country_code":"CN",
    "gn:dem":484,
    "gn:feature_class":"P",
    "gn:feature_code":"PPLA4",
    "gn:name":"Maliu",
    "gn:population":0,
    "gn:timezone":"Asia/Shanghai",
    "iso:country":"CN",
    "name:und_x_variant":[
        "Maliu Xiang"
    ],
    "name:zho_x_preferred":[
        "\u9ebb\u67f3"
    ],
    "name:zho_x_variant":[
        "\u9ebb\u67f3\u4e61"
    ],
    "wof:name":"Maliu",
    "wof:placetype":"locality"
},
  "geometry": {"coordinates":[108.24463,31.43421],"type":"Point"}
}