{
  "type": "Feature",
  "properties": {
    "gn:admin1_code":"20.0",
    "gn:asciiname":"Bayanhada Gacha",
    "gn:country_code":"CN",
    "gn:dem":589,
    "gn:feature_class":"P",
    "gn:feature_code":"PPL",
    "gn:name":"Bayanhada Gacha",
    "gn:population":0,
    "gn:timezone":"Asia/Shanghai",
    "iso:country":"CN",
    "name:zho_x_preferred":[
        "\u5df4\u5f66\u54c8\u8fbe\u560e\u67e5"
    ],
    "wof:name":"Bayanhada Gacha",
    "wof:placetype":"locality"
},
  "geometry": {"coordinates":[119.18337,49.20962],"type":"Point"}
}