{
  "type": "Feature",
  "properties": {
    "gn:admin1_code":"29",
    "gn:asciiname":"Mopanshan",
    "gn:country_code":"CN",
    "gn:dem":1847,
    "gn:feature_class":"P",
    "gn:feature_code":"PPL",
    "gn:name":"Mopanshan",
    "gn:population":0,
    "gn:timezone":"Asia/Shanghai",
    "iso:country":"CN",
    "name:zho_x_preferred":[
        "\u78e8\u76d8\u5c71"
    ],
    "wof:name":"Mopanshan",
    "wof:placetype":"locality"
},
  "geometry": {"coordinates":[102.836,24.5734],"type":"Point"}
}