{
  "type": "Feature",
  "properties": {
    "gn:admin1_code":"14.0",
    "gn:asciiname":"Yala",
    "gn:country_code":"CN",
    "gn:dem":3797,
    "gn:feature_class":"P",
    "gn:feature_code":"PPL",
    "gn:name":"Yala",
    "gn:population":0,
    "gn:timezone":"Asia/Urumqi",
    "iso:country":"CN",
    "name:zho_x_preferred":[
        "\u4e9a\u62c9"
    ],
    "wof:name":"Yala",
    "wof:placetype":"locality"
},
  "geometry": {"coordinates":[84.72969999999999,28.7013],"type":"Point"}
}