{
  "type": "Feature",
  "properties": {
    "gn:admin1_code":"4.0",
    "gn:asciiname":"Dahudiancun",
    "gn:country_code":"CN",
    "gn:dem":5,
    "gn:feature_class":"P",
    "gn:feature_code":"PPL",
    "gn:name":"Dahudiancun",
    "gn:population":0,
    "gn:timezone":"Asia/Shanghai",
    "iso:country":"CN",
    "name:und_x_variant":[
        "\u5927\u6e56\u7538\u6751"
    ],
    "name:zho_x_preferred":[
        "\u5927\u6e56\u7538\u6751"
    ],
    "wof:name":"Dahudiancun",
    "wof:placetype":"locality"
},
  "geometry": {"coordinates":[120.71008,31.64807],"type":"Point"}
}