{
  "type": "Feature",
  "properties": {
    "gn:admin1_code":"29.0",
    "gn:asciiname":"Xinsong",
    "gn:country_code":"CN",
    "gn:dem":2502,
    "gn:feature_class":"P",
    "gn:feature_code":"PPL",
    "gn:name":"Xinsong",
    "gn:population":0,
    "gn:timezone":"Asia/Shanghai",
    "iso:country":"CN",
    "name:zho_x_preferred":[
        "\u65b0\u677e"
    ],
    "wof:name":"Xinsong",
    "wof:placetype":"locality"
},
  "geometry": {"coordinates":[99.8192,26.1939],"type":"Point"}
}