{
  "type": "Feature",
  "properties": {
    "gn:admin1_code":"29.0",
    "gn:asciiname":"Jianpeng",
    "gn:country_code":"CN",
    "gn:dem":2275,
    "gn:feature_class":"P",
    "gn:feature_code":"PPL",
    "gn:name":"Jianpeng",
    "gn:population":0,
    "gn:timezone":"Asia/Shanghai",
    "iso:country":"CN",
    "name:zho_x_preferred":[
        "\u6da7\u68da"
    ],
    "wof:name":"Jianpeng",
    "wof:placetype":"locality"
},
  "geometry": {"coordinates":[99.52930000000001,25.8754],"type":"Point"}
}