{
  "type": "Feature",
  "properties": {
    "gn:admin1_code":"29",
    "gn:asciiname":"Daruicheng",
    "gn:country_code":"CN",
    "gn:dem":1471,
    "gn:feature_class":"P",
    "gn:feature_code":"PPL",
    "gn:name":"Daruicheng",
    "gn:population":0,
    "gn:timezone":"Asia/Shanghai",
    "iso:country":"CN",
    "name:zho_x_preferred":[
        "\u5927\u745e\u57ce"
    ],
    "wof:name":"Daruicheng",
    "wof:placetype":"locality"
},
  "geometry": {"coordinates":[102.496,23.6993],"type":"Point"}
}