{
  "type": "Feature",
  "properties": {
    "gn:admin1_code":"10",
    "gn:asciiname":"Jiuyangtun",
    "gn:country_code":"CN",
    "gn:dem":825,
    "gn:feature_class":"P",
    "gn:feature_code":"PPL",
    "gn:name":"Jiuyangtun",
    "gn:population":0,
    "gn:timezone":"Asia/Shanghai",
    "iso:country":"CN",
    "name:zho_x_preferred":[
        "\u65e7\u7f8a\u5c6f"
    ],
    "wof:name":"Jiuyangtun",
    "wof:placetype":"locality"
},
  "geometry": {"coordinates":[114.52607,40.74547000000001],"type":"Point"}
}