{
  "type": "Feature",
  "properties": {
    "gn:admin1_code":"32.0",
    "gn:asciiname":"Shichangwan",
    "gn:country_code":"CN",
    "gn:dem":430,
    "gn:feature_class":"P",
    "gn:feature_code":"PPL",
    "gn:name":"Shichangwan",
    "gn:population":0,
    "gn:timezone":"Asia/Shanghai",
    "iso:country":"CN",
    "name:zho_x_preferred":[
        "\u77f3\u573a\u6e7e"
    ],
    "wof:name":"Shichangwan",
    "wof:placetype":"locality"
},
  "geometry": {"coordinates":[103.91,29.9447],"type":"Point"}
}