{
  "type": "Feature",
  "properties": {
    "gn:admin1_code":"29.0",
    "gn:asciiname":"Dalibai",
    "gn:country_code":"CN",
    "gn:dem":1812,
    "gn:feature_class":"P",
    "gn:feature_code":"PPL",
    "gn:name":"Dalibai",
    "gn:population":0,
    "gn:timezone":"Asia/Shanghai",
    "iso:country":"CN",
    "name:zho_x_preferred":[
        "\u5927\u674e\u767e"
    ],
    "wof:name":"Dalibai",
    "wof:placetype":"locality"
},
  "geometry": {"coordinates":[102.325,25.0091],"type":"Point"}
}