{
  "type": "Feature",
  "properties": {
    "gn:admin1_code":"1.0",
    "gn:asciiname":"Lujicun",
    "gn:country_code":"CN",
    "gn:dem":37,
    "gn:feature_class":"P",
    "gn:feature_code":"PPL",
    "gn:name":"Lujicun",
    "gn:population":0,
    "gn:timezone":"Asia/Shanghai",
    "iso:country":"CN",
    "name:und_x_variant":[
        "Luji"
    ],
    "name:zho_x_preferred":[
        "\u9646\u96c6\u6751"
    ],
    "wof:name":"Lujicun",
    "wof:placetype":"locality"
},
  "geometry": {"coordinates":[115.38333,33.11667],"type":"Point"}
}