{
  "type": "Feature",
  "properties": {
    "gn:admin1_code":"18",
    "gn:asciiname":"Changbagou",
    "gn:country_code":"CN",
    "gn:dem":811,
    "gn:feature_class":"P",
    "gn:feature_code":"PPL",
    "gn:name":"Changbagou",
    "gn:population":0,
    "gn:timezone":"Asia/Shanghai",
    "iso:country":"CN",
    "name:zho_x_preferred":[
        "\u957f\u575d\u6c9f"
    ],
    "wof:name":"Changbagou",
    "wof:placetype":"locality"
},
  "geometry": {"coordinates":[108.40600000000001,27.1903],"type":"Point"}
}