{
  "type": "Feature",
  "properties": {
    "gn:admin1_code":"11",
    "gn:asciiname":"Mashi",
    "gn:cc2":"CN",
    "gn:country_code":"CN",
    "gn:dem":443,
    "gn:feature_class":"P",
    "gn:feature_code":"PPL",
    "gn:name":"Mashi",
    "gn:population":0,
    "gn:timezone":"Asia/Shanghai",
    "iso:country":"CN",
    "name:fra_x_preferred":[
        "Mashi"
    ],
    "name:hau_x_preferred":[
        "Mashi"
    ],
    "name:ita_x_preferred":[
        "Mashi"
    ],
    "name:spa_x_preferred":[
        "Mashi"
    ],
    "name:und_x_variant":[
        "Ma-shih",
        "Mashi"
    ],
    "wof:name":"Mashi",
    "wof:placetype":"locality"
},
  "geometry": {"coordinates":[112.02,24.91583],"type":"Point"}
}