{
  "type": "Feature",
  "properties": {
    "gn:admin1_code":"26.0",
    "gn:asciiname":"Yanjiashan",
    "gn:country_code":"CN",
    "gn:dem":1002,
    "gn:feature_class":"P",
    "gn:feature_code":"PPL",
    "gn:name":"Yanjiashan",
    "gn:population":0,
    "gn:timezone":"Asia/Shanghai",
    "iso:country":"CN",
    "name:und_x_variant":[
        "\u960e\u5bb6\u5c71",
        "Yanjiashan"
    ],
    "wof:name":"Yanjiashan",
    "wof:placetype":"locality"
},
  "geometry": {"coordinates":[107.78574999999999,33.34007],"type":"Point"}
}