{
  "type": "Feature",
  "properties": {
    "gn:admin1_code":"4.0",
    "gn:asciiname":"Zhangjiabian",
    "gn:country_code":"CN",
    "gn:dem":7,
    "gn:feature_class":"P",
    "gn:feature_code":"PPL",
    "gn:name":"Zhangjiabian",
    "gn:population":0,
    "gn:timezone":"Asia/Shanghai",
    "iso:country":"CN",
    "name:zho_x_preferred":[
        "\u7ae0\u5bb6\u8fb9"
    ],
    "wof:name":"Zhangjiabian",
    "wof:placetype":"locality"
},
  "geometry": {"coordinates":[119.21630999999999,31.33984],"type":"Point"}
}