{
  "type": "Feature",
  "properties": {
    "gn:admin1_code":"22",
    "gn:asciiname":"Dujiazhuang",
    "gn:country_code":"CN",
    "gn:dem":601,
    "gn:feature_class":"P",
    "gn:feature_code":"PPL",
    "gn:name":"Dujiazhuang",
    "gn:population":0,
    "gn:timezone":"Asia/Shanghai",
    "iso:country":"CN",
    "name:und_x_variant":[
        "Tu-chia-chuang",
        "Dujiazhuang"
    ],
    "name:zho_x_preferred":[
        "\u675c\u5bb6\u5e84"
    ],
    "wof:name":"Dujiazhuang",
    "wof:placetype":"locality"
},
  "geometry": {"coordinates":[115.53955999999999,39.92196],"type":"Point"}
}