{
  "type": "Feature",
  "properties": {
    "gn:admin1_code":"29.0",
    "gn:asciiname":"Shizhalong",
    "gn:country_code":"CN",
    "gn:dem":1728,
    "gn:feature_class":"P",
    "gn:feature_code":"PPL",
    "gn:name":"Shizhalong",
    "gn:population":0,
    "gn:timezone":"Asia/Shanghai",
    "iso:country":"CN",
    "name:zho_x_preferred":[
        "\u77f3\u6e23\u9f99"
    ],
    "wof:name":"Shizhalong",
    "wof:placetype":"locality"
},
  "geometry": {"coordinates":[102.821,23.4086],"type":"Point"}
}