{
  "type": "Feature",
  "properties": {
    "gn:admin1_code":"8.0",
    "gn:asciiname":"Henancun",
    "gn:country_code":"CN",
    "gn:dem":132,
    "gn:feature_class":"P",
    "gn:feature_code":"PPL",
    "gn:name":"Henancun",
    "gn:population":0,
    "gn:timezone":"Asia/Shanghai",
    "iso:country":"CN",
    "name:zho_x_preferred":[
        "\u6cb3\u5357\u6751"
    ],
    "wof:name":"Henancun",
    "wof:placetype":"locality"
},
  "geometry": {"coordinates":[124.19164000000001,45.84051],"type":"Point"}
}