{
  "type": "Feature",
  "properties": {
    "gn:admin1_code":"32.0",
    "gn:asciiname":"Wujiawan",
    "gn:country_code":"CN",
    "gn:dem":328,
    "gn:feature_class":"P",
    "gn:feature_code":"PPL",
    "gn:name":"Wujiawan",
    "gn:population":0,
    "gn:timezone":"Asia/Shanghai",
    "iso:country":"CN",
    "name:zho_x_preferred":[
        "\u4e94\u5bb6\u6e7e"
    ],
    "wof:name":"Wujiawan",
    "wof:placetype":"locality"
},
  "geometry": {"coordinates":[105.795,30.4759],"type":"Point"}
}