{
  "type": "Feature",
  "properties": {
    "iso:country":"CN",
    "name:eng_x_preferred":[
        "Yanziji"
    ],
    "name:zho_x_preferred":[
        "\u71d5\u5b50\u77f6"
    ],
    "qs:name":"\u71d5\u5b50\u77f6",
    "qs:name_adm0":"\u4e2d\u570b",
    "qs:name_adm1":"\u6c5f\u82cf\u7701",
    "qs:photos":66,
    "qs:photos_1k":13,
    "qs:photos_9k":1,
    "qs:photos_9r":2,
    "qs:photos_all":66,
    "qs:photos_sr":2,
    "qs:placetype":"Town",
    "qs:pop_sr":"0",
    "wof:name":"Yanziji",
    "wof:placetype":"locality"
},
  "geometry": {"coordinates":[118.78143300000001,32.125616],"type":"Point"}
}