{
  "type": "Feature",
  "properties": {
    "gn:admin1_code":"02",
    "gn:asciiname":"Suifengcun",
    "gn:country_code":"CN",
    "gn:dem":7,
    "gn:feature_class":"P",
    "gn:feature_code":"PPL",
    "gn:name":"Suifengcun",
    "gn:population":0,
    "gn:timezone":"Asia/Shanghai",
    "iso:country":"CN",
    "name:und_x_variant":[
        "Sui-feng-chen",
        "Suifeng",
        "Suifengcun"
    ],
    "name:zho_x_preferred":[
        "\u7a57\u4e30\u6751"
    ],
    "wof:name":"Suifengcun",
    "wof:placetype":"locality"
},
  "geometry": {"coordinates":[120.67431999999999,27.8623],"type":"Point"}
}