{
  "type": "Feature",
  "properties": {
    "gn:admin1_code":"33.0",
    "gn:asciiname":"Xiaodongyan",
    "gn:country_code":"CN",
    "gn:dem":838,
    "gn:feature_class":"P",
    "gn:feature_code":"PPL",
    "gn:name":"Xiaodongyan",
    "gn:population":0,
    "gn:timezone":"Asia/Shanghai",
    "iso:country":"CN",
    "name:zho_x_preferred":[
        "\u785d\u6d1e\u5ca9"
    ],
    "wof:name":"Xiaodongyan",
    "wof:placetype":"locality"
},
  "geometry": {"coordinates":[107.38800000000001,29.2519],"type":"Point"}
}