{
  "type": "Feature",
  "properties": {
    "gn:admin1_code":"09",
    "gn:asciiname":"Duanji",
    "gn:cc2":"CN",
    "gn:country_code":"CN",
    "gn:dem":86,
    "gn:feature_class":"P",
    "gn:feature_code":"PPL",
    "gn:name":"Duanji",
    "gn:population":0,
    "gn:timezone":"Asia/Shanghai",
    "iso:country":"CN",
    "name:und_x_variant":[
        "Tuan-chi",
        "Duanji"
    ],
    "wof:name":"Duanji",
    "wof:placetype":"locality"
},
  "geometry": {"coordinates":[115.67722000000001,31.89583],"type":"Point"}
}