{
  "type": "Feature",
  "properties": {
    "gn:admin1_code":"29.0",
    "gn:asciiname":"Sanjiaodi",
    "gn:country_code":"CN",
    "gn:dem":1462,
    "gn:feature_class":"P",
    "gn:feature_code":"PPL",
    "gn:name":"Sanjiaodi",
    "gn:population":0,
    "gn:timezone":"Asia/Shanghai",
    "iso:country":"CN",
    "name:zho_x_preferred":[
        "\u4e09\u89d2\u5730"
    ],
    "wof:name":"Sanjiaodi",
    "wof:placetype":"locality"
},
  "geometry": {"coordinates":[104.31699999999999,23.1626],"type":"Point"}
}