{
  "type": "Feature",
  "properties": {
    "gn:admin1_code":"2.0",
    "gn:asciiname":"Baiyutan",
    "gn:country_code":"CN",
    "gn:dem":13,
    "gn:feature_class":"P",
    "gn:feature_code":"PPL",
    "gn:name":"Baiyutan",
    "gn:population":0,
    "gn:timezone":"Asia/Shanghai",
    "iso:country":"CN",
    "name:und_x_variant":[
        "\u767d\u9c7c\u6f6d"
    ],
    "wof:name":"Baiyutan",
    "wof:placetype":"locality"
},
  "geometry": {"coordinates":[120.55481,30.04161],"type":"Point"}
}