{
  "type": "Feature",
  "properties": {
    "gn:admin1_code":"2.0",
    "gn:asciiname":"Zijinwu",
    "gn:country_code":"CN",
    "gn:dem":202,
    "gn:feature_class":"P",
    "gn:feature_code":"PPL",
    "gn:name":"Zijinwu",
    "gn:population":0,
    "gn:timezone":"Asia/Shanghai",
    "iso:country":"CN",
    "name:zho_x_preferred":[
        "\u7d2b\u91d1\u575e"
    ],
    "wof:name":"Zijinwu",
    "wof:placetype":"locality"
},
  "geometry": {"coordinates":[118.28367,29.05729],"type":"Point"}
}