{
  "type": "Feature",
  "properties": {
    "gn:admin1_code":"32.0",
    "gn:asciiname":"Zhouli",
    "gn:country_code":"CN",
    "gn:dem":386,
    "gn:feature_class":"P",
    "gn:feature_code":"PPL",
    "gn:name":"Zhouli",
    "gn:population":0,
    "gn:timezone":"Asia/Shanghai",
    "iso:country":"CN",
    "name:und_x_variant":[
        "Chou-li-ch\u2019ang",
        "Zhoulichang",
        "Zhouli"
    ],
    "name:zho_x_preferred":[
        "\u5468\u793c"
    ],
    "wof:name":"Zhouli",
    "wof:placetype":"locality"
},
  "geometry": {"coordinates":[105.13061999999999,29.89344],"type":"Point"}
}