{
  "type": "Feature",
  "properties": {
    "gn:admin1_code":"31.0",
    "gn:asciiname":"Xiayun",
    "gn:country_code":"CN",
    "gn:dem":41,
    "gn:feature_class":"P",
    "gn:feature_code":"PPL",
    "gn:name":"Xiayun",
    "gn:population":0,
    "gn:timezone":"Asia/Shanghai",
    "iso:country":"CN",
    "name:zho_x_preferred":[
        "Xiayun"
    ],
    "name:zho_x_variant":[
        "\u4e0b\u4e91"
    ],
    "wof:name":"Xiayun",
    "wof:placetype":"locality"
},
  "geometry": {"coordinates":[110.55292,19.81695],"type":"Point"}
}