{
  "type": "Feature",
  "properties": {
    "gn:admin1_code":"5.0",
    "gn:asciiname":"Xiaoliujiatun",
    "gn:country_code":"CN",
    "gn:dem":181,
    "gn:feature_class":"P",
    "gn:feature_code":"PPL",
    "gn:name":"Xiaoliujiatun",
    "gn:population":0,
    "gn:timezone":"Asia/Shanghai",
    "iso:country":"CN",
    "name:zho_x_preferred":[
        "\u5c0f\u5218\u5bb6\u5c6f"
    ],
    "wof:name":"Xiaoliujiatun",
    "wof:placetype":"locality"
},
  "geometry": {"coordinates":[124.43913999999999,43.84015],"type":"Point"}
}