{
  "type": "Feature",
  "properties": {
    "gn:admin1_code":"24",
    "gn:asciiname":"Shifohe",
    "gn:country_code":"CN",
    "gn:dem":1339,
    "gn:feature_class":"P",
    "gn:feature_code":"PPL",
    "gn:name":"Shifohe",
    "gn:population":0,
    "gn:timezone":"Asia/Shanghai",
    "iso:country":"CN",
    "name:und_x_variant":[
        "Shih-fo-ho",
        "Shifohe"
    ],
    "name:zho_x_preferred":[
        "\u77f3\u4f5b\u6cb3"
    ],
    "wof:name":"Shifohe",
    "wof:placetype":"locality"
},
  "geometry": {"coordinates":[111.43174999999999,38.95742],"type":"Point"}
}