{
  "type": "Feature",
  "properties": {
    "gn:admin1_code":"14.0",
    "gn:asciiname":"Mixiao",
    "gn:country_code":"CN",
    "gn:dem":4760,
    "gn:feature_class":"P",
    "gn:feature_code":"PPL",
    "gn:name":"Mixiao",
    "gn:population":0,
    "gn:timezone":"Asia/Urumqi",
    "iso:country":"CN",
    "name:zho_x_preferred":[
        "\u7c73\u524a"
    ],
    "wof:name":"Mixiao",
    "wof:placetype":"locality"
},
  "geometry": {"coordinates":[90.75613,31.0781],"type":"Point"}
}