{
  "type": "Feature",
  "properties": {
    "gn:admin1_code":"22.0",
    "gn:asciiname":"Maziyucun",
    "gn:country_code":"CN",
    "gn:dem":190,
    "gn:feature_class":"P",
    "gn:feature_code":"PPL",
    "gn:name":"Maziyucun",
    "gn:population":0,
    "gn:timezone":"Asia/Shanghai",
    "iso:country":"CN",
    "name:zho_x_preferred":[
        "\u9ebb\u5b50\u5cea\u6751"
    ],
    "wof:name":"Maziyucun",
    "wof:placetype":"locality"
},
  "geometry": {"coordinates":[117.09034,40.26115],"type":"Point"}
}