{
  "type": "Feature",
  "properties": {
    "gn:admin1_code":"25",
    "gn:asciiname":"Lujiahe",
    "gn:country_code":"CN",
    "gn:dem":26,
    "gn:feature_class":"P",
    "gn:feature_code":"PPL",
    "gn:name":"Lujiahe",
    "gn:population":0,
    "gn:timezone":"Asia/Shanghai",
    "iso:country":"CN",
    "name:zho_x_preferred":[
        "\u82a6\u5bb6\u6cb3"
    ],
    "wof:name":"Lujiahe",
    "wof:placetype":"locality"
},
  "geometry": {"coordinates":[116.34099999999999,37.4034],"type":"Point"}
}