{
  "type": "Feature",
  "properties": {
    "gn:admin1_code":"2.0",
    "gn:asciiname":"Xiejia",
    "gn:country_code":"CN",
    "gn:dem":446,
    "gn:feature_class":"P",
    "gn:feature_code":"PPL",
    "gn:name":"Xiejia",
    "gn:population":0,
    "gn:timezone":"Asia/Shanghai",
    "iso:country":"CN",
    "name:und_x_variant":[
        "\u8c22\u5bb6"
    ],
    "wof:name":"Xiejia",
    "wof:placetype":"locality"
},
  "geometry": {"coordinates":[118.93534,30.13775],"type":"Point"}
}