{
  "type": "Feature",
  "properties": {
    "gn:admin1_code":"30",
    "gn:asciiname":"Henggang",
    "gn:country_code":"CN",
    "gn:dem":74,
    "gn:feature_class":"P",
    "gn:feature_code":"PPLA4",
    "gn:name":"Henggang",
    "gn:population":0,
    "gn:timezone":"Asia/Shanghai",
    "iso:country":"CN",
    "name:und_x_variant":[
        "Wangkong",
        "Heng-kang",
        "Heng-kang-hs\u00fc",
        "Henggang Jiedao",
        "Henggang",
        "\u6a2a\u5c97\u8857\u9053"
    ],
    "name:zho_x_preferred":[
        "\u6a2a\u5c97"
    ],
    "wof:name":"Henggang",
    "wof:placetype":"locality"
},
  "geometry": {"coordinates":[114.19611999999999,22.6489],"type":"Point"}
}