{
  "type": "Feature",
  "properties": {
    "gn:admin1_code":"29.0",
    "gn:asciiname":"Buruoluo",
    "gn:country_code":"CN",
    "gn:dem":2297,
    "gn:feature_class":"P",
    "gn:feature_code":"PPL",
    "gn:name":"Buruoluo",
    "gn:population":0,
    "gn:timezone":"Asia/Shanghai",
    "iso:country":"CN",
    "name:zho_x_preferred":[
        "\u4e0d\u82e5\u843d"
    ],
    "wof:name":"Buruoluo",
    "wof:placetype":"locality"
},
  "geometry": {"coordinates":[100.375,27.6735],"type":"Point"}
}