{
  "type": "Feature",
  "properties": {
    "gn:admin1_code":"16.0",
    "gn:asciiname":"Gudeng",
    "gn:country_code":"CN",
    "gn:dem":249,
    "gn:feature_class":"P",
    "gn:feature_code":"PPL",
    "gn:name":"Gudeng",
    "gn:population":0,
    "gn:timezone":"Asia/Shanghai",
    "iso:country":"CN",
    "name:zho_x_preferred":[
        "\u53e4\u706f"
    ],
    "wof:name":"Gudeng",
    "wof:placetype":"locality"
},
  "geometry": {"coordinates":[110.107,24.3208],"type":"Point"}
}