{
  "type": "Feature",
  "properties": {
    "gn:admin1_code":"25.0",
    "gn:asciiname":"Dongnanya",
    "gn:cc2":"CN",
    "gn:country_code":"CN",
    "gn:dem":52,
    "gn:feature_class":"P",
    "gn:feature_code":"PPL",
    "gn:name":"Dongnanya",
    "gn:population":0,
    "gn:timezone":"Asia/Shanghai",
    "iso:country":"CN",
    "name:zho_x_preferred":[
        "\u4e1c\u5357\u5d16"
    ],
    "wof:name":"Dongnanya",
    "wof:placetype":"locality"
},
  "geometry": {"coordinates":[120.45077999999999,36.23273],"type":"Point"}
}