{
  "type": "Feature",
  "properties": {
    "gn:admin1_code":"19.0",
    "gn:asciiname":"Ping'anhecun",
    "gn:country_code":"CN",
    "gn:dem":1,
    "gn:feature_class":"P",
    "gn:feature_code":"PPL",
    "gn:name":"Ping\u2019anhecun",
    "gn:population":0,
    "gn:timezone":"Asia/Shanghai",
    "iso:country":"CN",
    "name:und_x_variant":[
        "Ping\u2019anhecun"
    ],
    "name:zho_x_preferred":[
        "\u5e73\u5b89\u6cb3\u6751"
    ],
    "wof:name":"Ping'anhecun",
    "wof:placetype":"locality"
},
  "geometry": {"coordinates":[122.032,40.7827],"type":"Point"}
}