{
  "type": "Feature",
  "properties": {
    "gn:admin1_code":"21.0",
    "gn:asciiname":"Fenwan",
    "gn:country_code":"CN",
    "gn:dem":1917,
    "gn:feature_class":"P",
    "gn:feature_code":"PPL",
    "gn:name":"Fenwan",
    "gn:population":0,
    "gn:timezone":"Asia/Shanghai",
    "iso:country":"CN",
    "name:zho_x_preferred":[
        "\u575f\u6e7e"
    ],
    "wof:name":"Fenwan",
    "wof:placetype":"locality"
},
  "geometry": {"coordinates":[105.81816000000001,35.87613],"type":"Point"}
}