{
  "type": "Feature",
  "properties": {
    "gn:admin1_code":"26",
    "gn:asciiname":"Fengmingcun",
    "gn:cc2":"CN",
    "gn:country_code":"CN",
    "gn:dem":542,
    "gn:feature_class":"P",
    "gn:feature_code":"PPL",
    "gn:name":"Fengmingcun",
    "gn:population":0,
    "gn:timezone":"Asia/Shanghai",
    "iso:country":"CN",
    "name:und_x_variant":[
        "Feng-ming-li",
        "Feng-ming-ts\u2019un",
        "Fengmingcun"
    ],
    "wof:name":"Fengmingcun",
    "wof:placetype":"locality"
},
  "geometry": {"coordinates":[107.42667,34.31167],"type":"Point"}
}