{
  "type": "Feature",
  "properties": {
    "gn:admin1_code":"18",
    "gn:asciiname":"Cheji",
    "gn:country_code":"CN",
    "gn:dem":2037,
    "gn:feature_class":"P",
    "gn:feature_code":"PPL",
    "gn:name":"Cheji",
    "gn:population":0,
    "gn:timezone":"Asia/Shanghai",
    "iso:country":"CN",
    "name:zho_x_preferred":[
        "\u626f\u5df1"
    ],
    "wof:name":"Cheji",
    "wof:placetype":"locality"
},
  "geometry": {"coordinates":[104.917,26.3457],"type":"Point"}
}