{
  "type": "Feature",
  "properties": {
    "gn:admin1_code":"12.0",
    "gn:asciiname":"Magang",
    "gn:country_code":"CN",
    "gn:dem":112,
    "gn:feature_class":"P",
    "gn:feature_code":"PPL",
    "gn:name":"Magang",
    "gn:population":0,
    "gn:timezone":"Asia/Shanghai",
    "iso:country":"CN",
    "name:ceb_x_preferred":[
        "Magang"
    ],
    "name:swe_x_preferred":[
        "Magang"
    ],
    "name:zho_x_preferred":[
        "\u9a6c\u5c97"
    ],
    "wof:name":"Magang",
    "wof:placetype":"locality"
},
  "geometry": {"coordinates":[112.60786,32.105],"type":"Point"}
}