{
  "type": "Feature",
  "properties": {
    "gn:admin1_code":"1.0",
    "gn:asciiname":"Shunchong",
    "gn:country_code":"CN",
    "gn:dem":62,
    "gn:feature_class":"P",
    "gn:feature_code":"PPL",
    "gn:name":"Shunchong",
    "gn:population":0,
    "gn:timezone":"Asia/Shanghai",
    "iso:country":"CN",
    "name:und_x_variant":[
        "\u987a\u51b2"
    ],
    "wof:name":"Shunchong",
    "wof:placetype":"locality"
},
  "geometry": {"coordinates":[118.06636,30.83002],"type":"Point"}
}