{
  "type": "Feature",
  "properties": {
    "gn:admin1_code":"29.0",
    "gn:asciiname":"Xiamaizhuang",
    "gn:country_code":"CN",
    "gn:dem":2148,
    "gn:feature_class":"P",
    "gn:feature_code":"PPL",
    "gn:name":"Xiamaizhuang",
    "gn:population":0,
    "gn:timezone":"Asia/Shanghai",
    "iso:country":"CN",
    "name:zho_x_preferred":[
        "\u4e0b\u9ea6\u5e84"
    ],
    "wof:name":"Xiamaizhuang",
    "wof:placetype":"locality"
},
  "geometry": {"coordinates":[99.0265,25.5495],"type":"Point"}
}