{
  "type": "Feature",
  "properties": {
    "gn:admin1_code":"26.0",
    "gn:asciiname":"Lujia Wacun",
    "gn:country_code":"CN",
    "gn:dem":986,
    "gn:feature_class":"P",
    "gn:feature_code":"PPL",
    "gn:name":"Lujia Wacun",
    "gn:population":0,
    "gn:timezone":"Asia/Shanghai",
    "iso:country":"CN",
    "name:zho_x_preferred":[
        "\u8def\u5bb6\u6d3c\u6751"
    ],
    "wof:name":"Lujia Wacun",
    "wof:placetype":"locality"
},
  "geometry": {"coordinates":[110.58499999999999,37.5088],"type":"Point"}
}