{
  "type": "Feature",
  "properties": {
    "gn:admin1_code":"9.0",
    "gn:asciiname":"Liushenzhuang",
    "gn:country_code":"CN",
    "gn:dem":85,
    "gn:feature_class":"P",
    "gn:feature_code":"PPL",
    "gn:name":"Liushenzhuang",
    "gn:population":0,
    "gn:timezone":"Asia/Shanghai",
    "iso:country":"CN",
    "name:zho_x_preferred":[
        "\u5218\u7533\u5e84"
    ],
    "wof:name":"Liushenzhuang",
    "wof:placetype":"locality"
},
  "geometry": {"coordinates":[113.9182,34.71859],"type":"Point"}
}