{
  "type": "Feature",
  "properties": {
    "gn:admin1_code":"5.0",
    "gn:asciiname":"Xiluanjia Tuozi",
    "gn:country_code":"CN",
    "gn:dem":204,
    "gn:feature_class":"P",
    "gn:feature_code":"PPL",
    "gn:name":"Xiluanjia Tuozi",
    "gn:population":0,
    "gn:timezone":"Asia/Shanghai",
    "iso:country":"CN",
    "name:zho_x_preferred":[
        "\u897f\u683e\u5bb6\u5768\u5b50"
    ],
    "wof:name":"Xiluanjia Tuozi",
    "wof:placetype":"locality"
},
  "geometry": {"coordinates":[124.0579,44.06953],"type":"Point"}
}