{
  "type": "Feature",
  "properties": {
    "gn:admin1_code":"9.0",
    "gn:asciiname":"Shiyaogou",
    "gn:country_code":"CN",
    "gn:dem":606,
    "gn:feature_class":"P",
    "gn:feature_code":"PPL",
    "gn:name":"Shiyaogou",
    "gn:population":0,
    "gn:timezone":"Asia/Shanghai",
    "iso:country":"CN",
    "name:und_x_variant":[
        "\u77f3\u7a91\u6c9f",
        "Shiyaogou"
    ],
    "wof:name":"Shiyaogou",
    "wof:placetype":"locality"
},
  "geometry": {"coordinates":[112.43398999999999,33.5856],"type":"Point"}
}