{
  "type": "Feature",
  "properties": {
    "gn:admin1_code":"15.0",
    "gn:asciiname":"Gongjian",
    "gn:country_code":"CN",
    "gn:dem":1770,
    "gn:feature_class":"P",
    "gn:feature_code":"PPL",
    "gn:name":"Gongjian",
    "gn:population":0,
    "gn:timezone":"Asia/Shanghai",
    "iso:country":"CN",
    "name:und_x_variant":[
        "\u8d21\u5c16"
    ],
    "name:zho_x_preferred":[
        "\u8d21\u5c16"
    ],
    "wof:name":"Gongjian",
    "wof:placetype":"locality"
},
  "geometry": {"coordinates":[103.90751,34.04248],"type":"Point"}
}