{
  "type": "Feature",
  "properties": {
    "gn:admin1_code":"1.0",
    "gn:asciiname":"Xintian",
    "gn:country_code":"CN",
    "gn:dem":94,
    "gn:feature_class":"P",
    "gn:feature_code":"PPLA4",
    "gn:name":"Xintian",
    "gn:population":0,
    "gn:timezone":"Asia/Shanghai",
    "iso:country":"CN",
    "name:ceb_x_preferred":[
        "Xintian"
    ],
    "name:deu_x_preferred":[
        "Xintian"
    ],
    "name:und_x_variant":[
        "Hsin-t\u2019ien-shan",
        "Xintianshan",
        "Xintian",
        "\u65b0\u7530",
        "Xintian Zhen",
        "\u65b0\u7530\u9547"
    ],
    "name:zho_x_preferred":[
        "\u65b0\u7530\u9109"
    ],
    "wof:name":"Xintian",
    "wof:placetype":"locality"
},
  "geometry": {"coordinates":[118.76947,30.75531],"type":"Point"}
}