{
  "type": "Feature",
  "properties": {
    "gn:admin1_code":"1.0",
    "gn:asciiname":"Changgangcun",
    "gn:country_code":"CN",
    "gn:dem":39,
    "gn:feature_class":"P",
    "gn:feature_code":"PPL",
    "gn:name":"Changgangcun",
    "gn:population":0,
    "gn:timezone":"Asia/Shanghai",
    "iso:country":"CN",
    "name:zho_x_preferred":[
        "\u957f\u5c97\u6751"
    ],
    "wof:name":"Changgangcun",
    "wof:placetype":"locality"
},
  "geometry": {"coordinates":[117.03588999999999,31.09631],"type":"Point"}
}