{
  "type": "Feature",
  "properties": {
    "gn:admin1_code":"24.0",
    "gn:asciiname":"Beizhangcun",
    "gn:country_code":"CN",
    "gn:dem":720,
    "gn:feature_class":"P",
    "gn:feature_code":"PPL",
    "gn:name":"Beizhangcun",
    "gn:population":0,
    "gn:timezone":"Asia/Shanghai",
    "iso:country":"CN",
    "name:und_x_variant":[
        "Beizhang"
    ],
    "name:zho_x_preferred":[
        "\u5317\u5f20\u6751"
    ],
    "name:zho_x_variant":[
        "\u5317\u5f20"
    ],
    "wof:name":"Beizhangcun",
    "wof:placetype":"locality"
},
  "geometry": {"coordinates":[111.23429,35.46107999999999],"type":"Point"}
}