{
  "type": "Feature",
  "properties": {
    "gn:admin1_code":"29.0",
    "gn:asciiname":"Yingshang",
    "gn:country_code":"CN",
    "gn:dem":2107,
    "gn:feature_class":"P",
    "gn:feature_code":"PPL",
    "gn:name":"Yingshang",
    "gn:population":0,
    "gn:timezone":"Asia/Shanghai",
    "iso:country":"CN",
    "name:zho_x_preferred":[
        "\u8425\u4e0a"
    ],
    "wof:name":"Yingshang",
    "wof:placetype":"locality"
},
  "geometry": {"coordinates":[103.724,27.6481],"type":"Point"}
}