{
  "type": "Feature",
  "properties": {
    "gn:admin1_code":"1.0",
    "gn:asciiname":"Gaochaocun",
    "gn:country_code":"CN",
    "gn:dem":83,
    "gn:feature_class":"P",
    "gn:feature_code":"PPL",
    "gn:name":"Gaochaocun",
    "gn:population":0,
    "gn:timezone":"Asia/Shanghai",
    "iso:country":"CN",
    "name:zho_x_preferred":[
        "\u9ad8\u6f6e\u6751"
    ],
    "wof:name":"Gaochaocun",
    "wof:placetype":"locality"
},
  "geometry": {"coordinates":[117.49267999999999,32.5639],"type":"Point"}
}