{
  "type": "Feature",
  "properties": {
    "gn:admin1_code":"22.0",
    "gn:asciiname":"Lishitaicun",
    "gn:country_code":"CN",
    "gn:dem":485,
    "gn:feature_class":"P",
    "gn:feature_code":"PPL",
    "gn:name":"Lishitaicun",
    "gn:population":0,
    "gn:timezone":"Asia/Shanghai",
    "iso:country":"CN",
    "name:zho_x_preferred":[
        "\u7acb\u77f3\u53f0\u6751"
    ],
    "wof:name":"Lishitaicun",
    "wof:placetype":"locality"
},
  "geometry": {"coordinates":[115.85249,40.05002],"type":"Point"}
}