{
  "type": "Feature",
  "properties": {
    "gn:admin1_code":"11.0",
    "gn:asciiname":"Muzitou",
    "gn:country_code":"CN",
    "gn:dem":516,
    "gn:feature_class":"P",
    "gn:feature_code":"PPL",
    "gn:name":"Muzitou",
    "gn:population":0,
    "gn:timezone":"Asia/Shanghai",
    "iso:country":"CN",
    "name:zho_x_preferred":[
        "Muzitou"
    ],
    "name:zho_x_variant":[
        "\u6728\u5b50\u5934"
    ],
    "wof:name":"Muzitou",
    "wof:placetype":"locality"
},
  "geometry": {"coordinates":[114.10366999999999,28.35459],"type":"Point"}
}