{
  "type": "Feature",
  "properties": {
    "gn:admin1_code":"22.0",
    "gn:asciiname":"Tianxianyucun",
    "gn:country_code":"CN",
    "gn:dem":207,
    "gn:feature_class":"P",
    "gn:feature_code":"PPL",
    "gn:name":"Tianxianyucun",
    "gn:population":0,
    "gn:timezone":"Asia/Shanghai",
    "iso:country":"CN",
    "name:zho_x_preferred":[
        "\u7530\u4ed9\u5cea\u6751"
    ],
    "wof:name":"Tianxianyucun",
    "wof:placetype":"locality"
},
  "geometry": {"coordinates":[116.53128999999998,40.42953],"type":"Point"}
}