{
  "type": "Feature",
  "properties": {
    "gn:admin1_code":"32.0",
    "gn:asciiname":"Qiujiawan",
    "gn:country_code":"CN",
    "gn:dem":402,
    "gn:feature_class":"P",
    "gn:feature_code":"PPL",
    "gn:name":"Qiujiawan",
    "gn:population":0,
    "gn:timezone":"Asia/Shanghai",
    "iso:country":"CN",
    "name:zho_x_preferred":[
        "\u90b1\u5bb6\u6e7e"
    ],
    "wof:name":"Qiujiawan",
    "wof:placetype":"locality"
},
  "geometry": {"coordinates":[104.599,29.9881],"type":"Point"}
}