{
  "type": "Feature",
  "properties": {
    "gn:admin1_code":"24.0",
    "gn:asciiname":"Baleng Shangcun",
    "gn:country_code":"CN",
    "gn:dem":949,
    "gn:feature_class":"P",
    "gn:feature_code":"PPL",
    "gn:name":"Baleng Shangcun",
    "gn:population":0,
    "gn:timezone":"Asia/Shanghai",
    "iso:country":"CN",
    "name:zho_x_preferred":[
        "\u6252\u580e\u4e0a\u6751"
    ],
    "wof:name":"Baleng Shangcun",
    "wof:placetype":"locality"
},
  "geometry": {"coordinates":[110.99176,38.39222],"type":"Point"}
}