{
  "type": "Feature",
  "properties": {
    "gn:admin1_code":"15.0",
    "gn:asciiname":"Xi Wopu",
    "gn:country_code":"CN",
    "gn:dem":1833,
    "gn:feature_class":"P",
    "gn:feature_code":"PPL",
    "gn:name":"Xi Wopu",
    "gn:population":0,
    "gn:timezone":"Asia/Shanghai",
    "iso:country":"CN",
    "name:zho_x_preferred":[
        "\u897f\u7a9d\u94fa"
    ],
    "wof:name":"Xi Wopu",
    "wof:placetype":"locality"
},
  "geometry": {"coordinates":[103.21599999999999,37.6013],"type":"Point"}
}