{
  "type": "Feature",
  "properties": {
    "gn:admin1_code":"10",
    "gn:asciiname":"Xiaobinlang Goumen",
    "gn:country_code":"CN",
    "gn:dem":895,
    "gn:feature_class":"P",
    "gn:feature_code":"PPL",
    "gn:name":"Xiaobinlang Goumen",
    "gn:population":0,
    "gn:timezone":"Asia/Shanghai",
    "iso:country":"CN",
    "name:zho_x_preferred":[
        "\u5c0f\u69df\u6994\u6c9f\u95e8"
    ],
    "wof:name":"Xiaobinlang Goumen",
    "wof:placetype":"locality"
},
  "geometry": {"coordinates":[118.24876999999999,41.52321],"type":"Point"}
}