{
  "type": "Feature",
  "properties": {
    "gn:admin1_code":"31",
    "gn:asciiname":"Zhongkun Nongchang Sanshisandui",
    "gn:country_code":"CN",
    "gn:dem":133,
    "gn:feature_class":"P",
    "gn:feature_code":"PPLF",
    "gn:name":"Zhongkun Nongchang Sanshisandui",
    "gn:population":0,
    "gn:timezone":"Asia/Shanghai",
    "iso:country":"CN",
    "name:und_x_variant":[
        "\u4e2d\u5764\u519c\u573a\u4e09\u5341\u4e09\u961f",
        "Fengshoudui"
    ],
    "wof:name":"Zhongkun Nongchang Sanshisandui",
    "wof:placetype":"locality"
},
  "geometry": {"coordinates":[109.8278,19.3494],"type":"Point"}
}