{
  "type": "Feature",
  "properties": {
    "gn:admin1_code":"9",
    "gn:asciiname":"Jinxin",
    "gn:country_code":"CN",
    "gn:dem":56,
    "gn:feature_class":"P",
    "gn:feature_code":"PPL",
    "gn:name":"Jinxin",
    "gn:population":0,
    "gn:timezone":"Asia/Shanghai",
    "iso:country":"CN",
    "name:zho_x_preferred":[
        "\u91d1\u8f9b"
    ],
    "wof:name":"Jinxin",
    "wof:placetype":"locality"
},
  "geometry": {"coordinates":[115.13082,35.4657],"type":"Point"}
}