{
  "type": "Feature",
  "properties": {
    "gn:admin1_code":"18",
    "gn:asciiname":"Gemu",
    "gn:country_code":"CN",
    "gn:dem":1750,
    "gn:feature_class":"P",
    "gn:feature_code":"PPL",
    "gn:name":"Gemu",
    "gn:population":0,
    "gn:timezone":"Asia/Shanghai",
    "iso:country":"CN",
    "name:zho_x_preferred":[
        "\u5404\u6728"
    ],
    "wof:name":"Gemu",
    "wof:placetype":"locality"
},
  "geometry": {"coordinates":[104.813,24.9333],"type":"Point"}
}