{
  "type": "Feature",
  "properties": {
    "gn:admin1_code":"9.0",
    "gn:asciiname":"Fuzhai",
    "gn:country_code":"CN",
    "gn:dem":219,
    "gn:feature_class":"P",
    "gn:feature_code":"PPL",
    "gn:name":"Fuzhai",
    "gn:population":0,
    "gn:timezone":"Asia/Shanghai",
    "iso:country":"CN",
    "name:und_x_variant":[
        "\u5085\u5be8",
        "Fuzhai"
    ],
    "wof:name":"Fuzhai",
    "wof:placetype":"locality"
},
  "geometry": {"coordinates":[112.02983999999999,33.17773],"type":"Point"}
}