{
  "type": "Feature",
  "properties": {
    "gn:admin1_code":"4.0",
    "gn:asciiname":"Lujiaobucun",
    "gn:country_code":"CN",
    "gn:dem":26,
    "gn:feature_class":"P",
    "gn:feature_code":"PPL",
    "gn:name":"Lujiaobucun",
    "gn:population":0,
    "gn:timezone":"Asia/Shanghai",
    "iso:country":"CN",
    "name:zho_x_preferred":[
        "\u9646\u89d2\u57e0\u6751"
    ],
    "wof:name":"Lujiaobucun",
    "wof:placetype":"locality"
},
  "geometry": {"coordinates":[117.74652,34.34967],"type":"Point"}
}