{
  "type": "Feature",
  "properties": {
    "gn:admin1_code":"29.0",
    "gn:asciiname":"Yujiagou",
    "gn:country_code":"CN",
    "gn:dem":706,
    "gn:feature_class":"P",
    "gn:feature_code":"PPL",
    "gn:name":"Yujiagou",
    "gn:population":0,
    "gn:timezone":"Asia/Shanghai",
    "iso:country":"CN",
    "name:zho_x_preferred":[
        "\u4f59\u5bb6\u6c9f"
    ],
    "wof:name":"Yujiagou",
    "wof:placetype":"locality"
},
  "geometry": {"coordinates":[103.908,28.5767],"type":"Point"}
}