{
  "type": "Feature",
  "properties": {
    "gn:admin1_code":"32",
    "gn:asciiname":"Qima",
    "gn:country_code":"CN",
    "gn:dem":712,
    "gn:feature_class":"P",
    "gn:feature_code":"PPL",
    "gn:name":"Qima",
    "gn:population":0,
    "gn:timezone":"Asia/Shanghai",
    "iso:country":"CN",
    "name:und_x_variant":[
        "Ch\u2019i-ma-ch\u2019ang",
        "Qimachang",
        "Qima"
    ],
    "name:zho_x_preferred":[
        "\u9a91\u9a6c"
    ],
    "wof:name":"Qima",
    "wof:placetype":"locality"
},
  "geometry": {"coordinates":[105.41698,32.58709],"type":"Point"}
}