{
  "type": "Feature",
  "properties": {
    "gn:admin1_code":"14.0",
    "gn:asciiname":"Nongzhi",
    "gn:country_code":"CN",
    "gn:dem":4551,
    "gn:feature_class":"P",
    "gn:feature_code":"PPL",
    "gn:name":"Nongzhi",
    "gn:population":0,
    "gn:timezone":"Asia/Urumqi",
    "iso:country":"CN",
    "name:zho_x_preferred":[
        "\u519c\u652f"
    ],
    "wof:name":"Nongzhi",
    "wof:placetype":"locality"
},
  "geometry": {"coordinates":[90.55155999999999,28.72893],"type":"Point"}
}