{
  "type": "Feature",
  "properties": {
    "gn:admin1_code":"3.0",
    "gn:asciiname":"Xinhuai",
    "gn:country_code":"CN",
    "gn:dem":202,
    "gn:feature_class":"P",
    "gn:feature_code":"PPL",
    "gn:name":"Xinhuai",
    "gn:population":0,
    "gn:timezone":"Asia/Shanghai",
    "iso:country":"CN",
    "name:und_x_variant":[
        "\u5fc3\u6000"
    ],
    "wof:name":"Xinhuai",
    "wof:placetype":"locality"
},
  "geometry": {"coordinates":[115.46771,25.42296],"type":"Point"}
}