{
  "type": "Feature",
  "properties": {
    "gn:admin1_code":"31",
    "gn:asciiname":"Hesheng",
    "gn:country_code":"CN",
    "gn:dem":156,
    "gn:feature_class":"P",
    "gn:feature_code":"PPL",
    "gn:name":"Hesheng",
    "gn:population":0,
    "gn:timezone":"Asia/Shanghai",
    "iso:country":"CN",
    "name:und_x_variant":[
        "Ho-sheng-shih",
        "Hesheng",
        "\u548c\u76db"
    ],
    "wof:name":"Hesheng",
    "wof:placetype":"locality"
},
  "geometry": {"coordinates":[109.36447,19.4167],"type":"Point"}
}