{
  "type": "Feature",
  "properties": {
    "gn:admin1_code":"15.0",
    "gn:asciiname":"Shanshuiliang",
    "gn:country_code":"CN",
    "gn:dem":1436,
    "gn:feature_class":"P",
    "gn:feature_code":"PPL",
    "gn:name":"Shanshuiliang",
    "gn:population":0,
    "gn:timezone":"Asia/Urumqi",
    "iso:country":"CN",
    "name:zho_x_preferred":[
        "\u5c71\u6c34\u6881"
    ],
    "wof:name":"Shanshuiliang",
    "wof:placetype":"locality"
},
  "geometry": {"coordinates":[96.8265,40.4385],"type":"Point"}
}