{
  "type": "Feature",
  "properties": {
    "gn:admin1_code":"26.0",
    "gn:asciiname":"Ganyucun",
    "gn:country_code":"CN",
    "gn:dem":537,
    "gn:feature_class":"P",
    "gn:feature_code":"PPL",
    "gn:name":"Ganyucun",
    "gn:population":0,
    "gn:timezone":"Asia/Shanghai",
    "iso:country":"CN",
    "name:zho_x_preferred":[
        "\u7518\u5cea\u6751"
    ],
    "wof:name":"Ganyucun",
    "wof:placetype":"locality"
},
  "geometry": {"coordinates":[109.1767,34.25055],"type":"Point"}
}