{
  "type": "Feature",
  "properties": {
    "gn:admin1_code":"29.0",
    "gn:asciiname":"Shayi",
    "gn:country_code":"CN",
    "gn:dem":3088,
    "gn:feature_class":"P",
    "gn:feature_code":"PPL",
    "gn:name":"Shayi",
    "gn:population":0,
    "gn:timezone":"Asia/Shanghai",
    "iso:country":"CN",
    "name:und_x_variant":[
        "\u970e\u8863"
    ],
    "wof:name":"Shayi",
    "wof:placetype":"locality"
},
  "geometry": {"coordinates":[102.98885,27.28604],"type":"Point"}
}