{
  "type": "Feature",
  "properties": {
    "gn:admin1_code":"15.0",
    "gn:asciiname":"Qingchi",
    "gn:country_code":"CN",
    "gn:dem":1493,
    "gn:feature_class":"P",
    "gn:feature_code":"PPL",
    "gn:name":"Qingchi",
    "gn:population":0,
    "gn:timezone":"Asia/Shanghai",
    "iso:country":"CN",
    "name:und_x_variant":[
        "\u6e05\u6c60"
    ],
    "wof:name":"Qingchi",
    "wof:placetype":"locality"
},
  "geometry": {"coordinates":[104.84981999999999,34.7415],"type":"Point"}
}