{
  "type": "Feature",
  "properties": {
    "gn:admin1_code":"26.0",
    "gn:asciiname":"Zhangjiayuan",
    "gn:country_code":"CN",
    "gn:dem":758,
    "gn:feature_class":"P",
    "gn:feature_code":"PPL",
    "gn:name":"Zhangjiayuan",
    "gn:population":0,
    "gn:timezone":"Asia/Shanghai",
    "iso:country":"CN",
    "name:und_x_variant":[
        "\u5f20\u5bb6\u9662"
    ],
    "wof:name":"Zhangjiayuan",
    "wof:placetype":"locality"
},
  "geometry": {"coordinates":[106.93926,32.81881],"type":"Point"}
}