{
  "type": "Feature",
  "properties": {
    "gn:admin1_code":"11.0",
    "gn:asciiname":"Hongjiachong",
    "gn:country_code":"CN",
    "gn:dem":789,
    "gn:feature_class":"P",
    "gn:feature_code":"PPL",
    "gn:name":"Hongjiachong",
    "gn:population":0,
    "gn:timezone":"Asia/Shanghai",
    "iso:country":"CN",
    "name:zho_x_preferred":[
        "\u7ea2\u5bb6\u51b2"
    ],
    "wof:name":"Hongjiachong",
    "wof:placetype":"locality"
},
  "geometry": {"coordinates":[111.14875000000001,26.61175],"type":"Point"}
}