{
  "type": "Feature",
  "properties": {
    "gn:admin1_code":"8.0",
    "gn:asciiname":"Liuchongxitun",
    "gn:country_code":"CN",
    "gn:dem":225,
    "gn:feature_class":"P",
    "gn:feature_code":"PPL",
    "gn:name":"Liuchongxitun",
    "gn:population":0,
    "gn:timezone":"Asia/Shanghai",
    "iso:country":"CN",
    "name:zho_x_preferred":[
        "\u5218\u5d07\u559c\u5c6f"
    ],
    "wof:name":"Liuchongxitun",
    "wof:placetype":"locality"
},
  "geometry": {"coordinates":[128.09059999999999,45.79249],"type":"Point"}
}