{
  "type": "Feature",
  "properties": {
    "gn:admin1_code":"15.0",
    "gn:asciiname":"Sanchaxiang",
    "gn:country_code":"CN",
    "gn:dem":2041,
    "gn:feature_class":"P",
    "gn:feature_code":"PPL",
    "gn:name":"Sanchaxiang",
    "gn:population":0,
    "gn:timezone":"Asia/Shanghai",
    "iso:country":"CN",
    "name:und_x_variant":[
        "\u4e09\u5c94\u4e61"
    ],
    "wof:name":"Sanchaxiang",
    "wof:placetype":"locality"
},
  "geometry": {"coordinates":[104.32938,34.87637],"type":"Point"}
}