{
  "type": "Feature",
  "properties": {
    "gn:admin1_code":"32.0",
    "gn:asciiname":"Wojia",
    "gn:country_code":"CN",
    "gn:dem":2014,
    "gn:feature_class":"P",
    "gn:feature_code":"PPL",
    "gn:name":"Wojia",
    "gn:population":0,
    "gn:timezone":"Asia/Shanghai",
    "iso:country":"CN",
    "name:zho_x_preferred":[
        "\u5367\u5bb6"
    ],
    "wof:name":"Wojia",
    "wof:placetype":"locality"
},
  "geometry": {"coordinates":[101.11799999999999,27.6557],"type":"Point"}
}