{
  "type": "Feature",
  "properties": {
    "gn:admin1_code":"20.0",
    "gn:asciiname":"Tuchengzi",
    "gn:country_code":"CN",
    "gn:dem":1844,
    "gn:feature_class":"P",
    "gn:feature_code":"PPL",
    "gn:name":"Tuchengzi",
    "gn:population":0,
    "gn:timezone":"Asia/Shanghai",
    "iso:country":"CN",
    "name:und_x_variant":[
        "\u571f\u57ce\u5b50"
    ],
    "wof:name":"Tuchengzi",
    "wof:placetype":"locality"
},
  "geometry": {"coordinates":[110.66323,41.15332],"type":"Point"}
}