{
  "type": "Feature",
  "properties": {
    "gn:admin1_code":"4.0",
    "gn:asciiname":"Qianbading",
    "gn:country_code":"CN",
    "gn:dem":11,
    "gn:feature_class":"P",
    "gn:feature_code":"PPL",
    "gn:name":"Qianbading",
    "gn:population":0,
    "gn:timezone":"Asia/Shanghai",
    "iso:country":"CN",
    "name:zho_x_preferred":[
        "Qianbading"
    ],
    "name:zho_x_variant":[
        "\u524d\u516b\u4e01"
    ],
    "wof:name":"Qianbading",
    "wof:placetype":"locality"
},
  "geometry": {"coordinates":[119.73978,34.0436],"type":"Point"}
}