{
  "type": "Feature",
  "properties": {
    "gn:admin1_code":"16.0",
    "gn:asciiname":"Nongdun",
    "gn:country_code":"CN",
    "gn:dem":546,
    "gn:feature_class":"P",
    "gn:feature_code":"PPL",
    "gn:name":"Nongdun",
    "gn:population":0,
    "gn:timezone":"Asia/Shanghai",
    "iso:country":"CN",
    "name:zho_x_preferred":[
        "\u5f04\u6c8c"
    ],
    "wof:name":"Nongdun",
    "wof:placetype":"locality"
},
  "geometry": {"coordinates":[108.154,24.2045],"type":"Point"}
}