{
  "type": "Feature",
  "properties": {
    "gn:admin1_code":"3.0",
    "gn:asciiname":"Niujiayuan",
    "gn:country_code":"CN",
    "gn:dem":61,
    "gn:feature_class":"P",
    "gn:feature_code":"PPL",
    "gn:name":"Niujiayuan",
    "gn:population":0,
    "gn:timezone":"Asia/Shanghai",
    "iso:country":"CN",
    "name:und_x_variant":[
        "\u725b\u5bb6\u6e90"
    ],
    "wof:name":"Niujiayuan",
    "wof:placetype":"locality"
},
  "geometry": {"coordinates":[116.66783999999998,27.75933],"type":"Point"}
}