{
  "type": "Feature",
  "properties": {
    "gn:admin1_code":"15.0",
    "gn:asciiname":"Chunshuping",
    "gn:country_code":"CN",
    "gn:dem":1738,
    "gn:feature_class":"P",
    "gn:feature_code":"PPL",
    "gn:name":"Chunshuping",
    "gn:population":0,
    "gn:timezone":"Asia/Shanghai",
    "iso:country":"CN",
    "name:zho_x_preferred":[
        "\u693f\u6811\u576a"
    ],
    "wof:name":"Chunshuping",
    "wof:placetype":"locality"
},
  "geometry": {"coordinates":[105.217,34.7811],"type":"Point"}
}