{
  "type": "Feature",
  "properties": {
    "gn:admin1_code":"29",
    "gn:asciiname":"Laomachang",
    "gn:country_code":"CN",
    "gn:dem":2103,
    "gn:feature_class":"P",
    "gn:feature_code":"PPL",
    "gn:name":"Laomachang",
    "gn:population":0,
    "gn:timezone":"Asia/Shanghai",
    "iso:country":"CN",
    "name:und_x_variant":[
        "\u8001\u9a6c\u573a"
    ],
    "wof:name":"Laomachang",
    "wof:placetype":"locality"
},
  "geometry": {"coordinates":[104.03976,25.58588],"type":"Point"}
}