{
  "type": "Feature",
  "properties": {
    "gn:admin1_code":"14.0",
    "gn:asciiname":"Gong'erlian",
    "gn:country_code":"CN",
    "gn:dem":2955,
    "gn:feature_class":"P",
    "gn:feature_code":"PPL",
    "gn:name":"Gong\u2019erlian",
    "gn:population":0,
    "gn:timezone":"Asia/Urumqi",
    "iso:country":"CN",
    "name:und_x_variant":[
        "Gong\u2019erlian"
    ],
    "name:zho_x_preferred":[
        "\u5de5\u4e8c\u8fde"
    ],
    "wof:name":"Gong'erlian",
    "wof:placetype":"locality"
},
  "geometry": {"coordinates":[94.48293,29.42056],"type":"Point"}
}