{
  "type": "Feature",
  "properties": {
    "gn:admin1_code":"15.0",
    "gn:asciiname":"Jiaojiawan",
    "gn:country_code":"CN",
    "gn:dem":1871,
    "gn:feature_class":"P",
    "gn:feature_code":"PPL",
    "gn:name":"Jiaojiawan",
    "gn:population":0,
    "gn:timezone":"Asia/Shanghai",
    "iso:country":"CN",
    "name:zho_x_preferred":[
        "\u7126\u5bb6\u6e7e"
    ],
    "wof:name":"Jiaojiawan",
    "wof:placetype":"locality"
},
  "geometry": {"coordinates":[104.751,35.1466],"type":"Point"}
}