{
  "type": "Feature",
  "properties": {
    "gn:admin1_code":"26",
    "gn:asciiname":"Majiaping",
    "gn:country_code":"CN",
    "gn:dem":959,
    "gn:feature_class":"P",
    "gn:feature_code":"PPL",
    "gn:name":"Majiaping",
    "gn:population":0,
    "gn:timezone":"Asia/Shanghai",
    "iso:country":"CN",
    "wof:name":"Majiaping",
    "wof:placetype":"locality"
},
  "geometry": {"coordinates":[110.56778,33.81833],"type":"Point"}
}