{
  "type": "Feature",
  "properties": {
    "gn:admin1_code":"11.0",
    "gn:asciiname":"Yuanjian",
    "gn:country_code":"CN",
    "gn:dem":160,
    "gn:feature_class":"P",
    "gn:feature_code":"PPL",
    "gn:name":"Yuanjian",
    "gn:population":0,
    "gn:timezone":"Asia/Shanghai",
    "iso:country":"CN",
    "name:zho_x_preferred":[
        "\u82ab\u67a7"
    ],
    "wof:name":"Yuanjian",
    "wof:placetype":"locality"
},
  "geometry": {"coordinates":[113.64678000000001,26.62238],"type":"Point"}
}