{
  "type": "Feature",
  "properties": {
    "gn:admin1_code":"5.0",
    "gn:asciiname":"Pipadong",
    "gn:country_code":"CN",
    "gn:dem":33,
    "gn:feature_class":"P",
    "gn:feature_code":"PPL",
    "gn:name":"Pipadong",
    "gn:population":0,
    "gn:timezone":"Asia/Shanghai",
    "iso:country":"CN",
    "name:und_x_variant":[
        "\u7435\u7436\u6d1e"
    ],
    "wof:name":"Pipadong",
    "wof:placetype":"locality"
},
  "geometry": {"coordinates":[130.37545,42.63491],"type":"Point"}
}