{
  "type": "Feature",
  "properties": {
    "gn:admin1_code":"29.0",
    "gn:asciiname":"Puchuzhai",
    "gn:country_code":"CN",
    "gn:dem":1692,
    "gn:feature_class":"P",
    "gn:feature_code":"PPL",
    "gn:name":"Puchuzhai",
    "gn:population":0,
    "gn:timezone":"Asia/Shanghai",
    "iso:country":"CN",
    "name:zho_x_preferred":[
        "\u666e\u695a\u5be8"
    ],
    "wof:name":"Puchuzhai",
    "wof:placetype":"locality"
},
  "geometry": {"coordinates":[98.4764,25.3549],"type":"Point"}
}