{
  "type": "Feature",
  "properties": {
    "gn:admin1_code":"2",
    "gn:asciiname":"Guangongtang",
    "gn:country_code":"CN",
    "gn:dem":658,
    "gn:feature_class":"P",
    "gn:feature_code":"PPL",
    "gn:name":"Guangongtang",
    "gn:population":0,
    "gn:timezone":"Asia/Shanghai",
    "iso:country":"CN",
    "name:zho_x_preferred":[
        "\u5173\u516c\u5802"
    ],
    "wof:name":"Guangongtang",
    "wof:placetype":"locality"
},
  "geometry": {"coordinates":[119.74972,27.67167],"type":"Point"}
}