{
  "type": "Feature",
  "properties": {
    "gn:admin1_code":"18.0",
    "gn:asciiname":"Hujiapo",
    "gn:country_code":"CN",
    "gn:dem":891,
    "gn:feature_class":"P",
    "gn:feature_code":"PPL",
    "gn:name":"Hujiapo",
    "gn:population":0,
    "gn:timezone":"Asia/Shanghai",
    "iso:country":"CN",
    "name:zho_x_preferred":[
        "\u80e1\u5bb6\u5761"
    ],
    "wof:name":"Hujiapo",
    "wof:placetype":"locality"
},
  "geometry": {"coordinates":[108.56,27.651],"type":"Point"}
}