{
  "type": "Feature",
  "properties": {
    "gn:admin1_code":"14.0",
    "gn:asciiname":"Zhongzi",
    "gn:country_code":"CN",
    "gn:dem":3956,
    "gn:feature_class":"P",
    "gn:feature_code":"PPLA4",
    "gn:name":"Zhongzi",
    "gn:population":0,
    "gn:timezone":"Asia/Urumqi",
    "iso:country":"CN",
    "name:bod_x_preferred":[
        "Zhongz\u00ea"
    ],
    "name:und_x_variant":[
        "Zhongzi Xiang"
    ],
    "name:zho_x_preferred":[
        "Zhongzi"
    ],
    "name:zho_x_variant":[
        "\u91cd\u5b5c",
        "\u91cd\u5b5c\u4e61"
    ],
    "wof:name":"Zhongzi",
    "wof:placetype":"locality"
},
  "geometry": {"coordinates":[89.46032,29.02268],"type":"Point"}
}