{
  "type": "Feature",
  "properties": {
    "gn:admin1_code":"4.0",
    "gn:asciiname":"Biandongcun",
    "gn:country_code":"CN",
    "gn:dem":15,
    "gn:feature_class":"P",
    "gn:feature_code":"PPL",
    "gn:name":"Biandongcun",
    "gn:population":0,
    "gn:timezone":"Asia/Shanghai",
    "iso:country":"CN",
    "name:zho_x_preferred":[
        "\u6c74\u4e1c\u6751"
    ],
    "wof:name":"Biandongcun",
    "wof:placetype":"locality"
},
  "geometry": {"coordinates":[118.27,33.3769],"type":"Point"}
}