{
  "type": "Feature",
  "properties": {
    "gn:admin1_code":"26",
    "gn:asciiname":"Bei'angu",
    "gn:country_code":"CN",
    "gn:dem":421,
    "gn:feature_class":"P",
    "gn:feature_code":"PPL",
    "gn:name":"Bei\u2019angu",
    "gn:population":0,
    "gn:timezone":"Asia/Shanghai",
    "iso:country":"CN",
    "name:und_x_variant":[
        "Bei\u2019angu"
    ],
    "name:zho_x_preferred":[
        "\u5317\u5b89\u8c37"
    ],
    "wof:name":"Bei'angu",
    "wof:placetype":"locality"
},
  "geometry": {"coordinates":[108.3775,34.2525],"type":"Point"}
}