{
  "type": "Feature",
  "properties": {
    "gn:admin1_code":"26.0",
    "gn:asciiname":"Quliubucun",
    "gn:country_code":"CN",
    "gn:dem":552,
    "gn:feature_class":"P",
    "gn:feature_code":"PPL",
    "gn:name":"Quliubucun",
    "gn:population":0,
    "gn:timezone":"Asia/Shanghai",
    "iso:country":"CN",
    "name:zho_x_preferred":[
        "\u5c48\u5218\u5821\u6751"
    ],
    "wof:name":"Quliubucun",
    "wof:placetype":"locality"
},
  "geometry": {"coordinates":[107.88539,34.17132],"type":"Point"}
}