{
  "type": "Feature",
  "properties": {
    "gn:admin1_code":"11",
    "gn:asciiname":"Baibi",
    "gn:country_code":"CN",
    "gn:dem":123,
    "gn:feature_class":"P",
    "gn:feature_code":"PPL",
    "gn:name":"Baibi",
    "gn:population":0,
    "gn:timezone":"Asia/Shanghai",
    "iso:country":"CN",
    "name:zho_x_preferred":[
        "\u767d\u78a7"
    ],
    "wof:name":"Baibi",
    "wof:placetype":"locality"
},
  "geometry": {"coordinates":[112.43164,27.44184000000001],"type":"Point"}
}