{
  "type": "Feature",
  "properties": {
    "gn:admin1_code":"8.0",
    "gn:asciiname":"Zhengyongcun",
    "gn:country_code":"CN",
    "gn:dem":160,
    "gn:feature_class":"P",
    "gn:feature_code":"PPL",
    "gn:name":"Zhengyongcun",
    "gn:population":0,
    "gn:timezone":"Asia/Shanghai",
    "iso:country":"CN",
    "name:zho_x_preferred":[
        "\u653f\u6c38\u6751"
    ],
    "wof:name":"Zhengyongcun",
    "wof:placetype":"locality"
},
  "geometry": {"coordinates":[126.43837000000001,45.29138],"type":"Point"}
}