{
  "type": "Feature",
  "properties": {
    "gn:admin1_code":"25",
    "gn:asciiname":"Nanxulou",
    "gn:country_code":"CN",
    "gn:dem":40,
    "gn:feature_class":"P",
    "gn:feature_code":"PPL",
    "gn:name":"Nanxulou",
    "gn:population":0,
    "gn:timezone":"Asia/Shanghai",
    "iso:country":"CN",
    "name:zho_x_preferred":[
        "\u5357\u5f90\u697c"
    ],
    "wof:name":"Nanxulou",
    "wof:placetype":"locality"
},
  "geometry": {"coordinates":[116.93300000000001,35.0588],"type":"Point"}
}