{
  "type": "Feature",
  "properties": {
    "gn:admin1_code":"18",
    "gn:asciiname":"Longdongshan",
    "gn:country_code":"CN",
    "gn:dem":2026,
    "gn:feature_class":"P",
    "gn:feature_code":"PPL",
    "gn:name":"Longdongshan",
    "gn:population":0,
    "gn:timezone":"Asia/Shanghai",
    "iso:country":"CN",
    "name:zho_x_preferred":[
        "\u9f99\u6d1e\u5c71"
    ],
    "wof:name":"Longdongshan",
    "wof:placetype":"locality"
},
  "geometry": {"coordinates":[104.741,27.1077],"type":"Point"}
}