{
  "type": "Feature",
  "properties": {
    "gn:admin1_code":"29.0",
    "gn:asciiname":"Laizidong",
    "gn:country_code":"CN",
    "gn:dem":2278,
    "gn:feature_class":"P",
    "gn:feature_code":"PPL",
    "gn:name":"Laizidong",
    "gn:population":0,
    "gn:timezone":"Asia/Shanghai",
    "iso:country":"CN",
    "name:zho_x_preferred":[
        "\u765e\u5b50\u6d1e"
    ],
    "wof:name":"Laizidong",
    "wof:placetype":"locality"
},
  "geometry": {"coordinates":[103.617,26.4336],"type":"Point"}
}