{
  "type": "Feature",
  "properties": {
    "gn:admin1_code":"15.0",
    "gn:asciiname":"Dashanli",
    "gn:country_code":"CN",
    "gn:dem":1522,
    "gn:feature_class":"P",
    "gn:feature_code":"PPL",
    "gn:name":"Dashanli",
    "gn:population":0,
    "gn:timezone":"Asia/Shanghai",
    "iso:country":"CN",
    "name:und_x_variant":[
        "\u5927\u5c71\u91cc"
    ],
    "wof:name":"Dashanli",
    "wof:placetype":"locality"
},
  "geometry": {"coordinates":[105.37837,32.99701],"type":"Point"}
}