{
  "type": "Feature",
  "properties": {
    "gn:admin1_code":"18",
    "gn:asciiname":"Zhuquanba",
    "gn:country_code":"CN",
    "gn:dem":776,
    "gn:feature_class":"P",
    "gn:feature_code":"PPL",
    "gn:name":"Zhuquanba",
    "gn:population":0,
    "gn:timezone":"Asia/Shanghai",
    "iso:country":"CN",
    "name:zho_x_preferred":[
        "\u732a\u5708\u575d"
    ],
    "wof:name":"Zhuquanba",
    "wof:placetype":"locality"
},
  "geometry": {"coordinates":[107.604,28.6706],"type":"Point"}
}