{
  "type": "Feature",
  "properties": {
    "gn:admin1_code":"29.0",
    "gn:asciiname":"Dagumen",
    "gn:country_code":"CN",
    "gn:dem":2226,
    "gn:feature_class":"P",
    "gn:feature_code":"PPL",
    "gn:name":"Dagumen",
    "gn:population":0,
    "gn:timezone":"Asia/Shanghai",
    "iso:country":"CN",
    "name:zho_x_preferred":[
        "\u6253\u53e4\u95e8"
    ],
    "wof:name":"Dagumen",
    "wof:placetype":"locality"
},
  "geometry": {"coordinates":[99.1557,26.2626],"type":"Point"}
}