{
  "type": "Feature",
  "properties": {
    "gn:admin1_code":"30.0",
    "gn:asciiname":"Tongmu'ao",
    "gn:country_code":"CN",
    "gn:dem":658,
    "gn:feature_class":"P",
    "gn:feature_code":"PPL",
    "gn:name":"Tongmu\u2019ao",
    "gn:population":0,
    "gn:timezone":"Asia/Shanghai",
    "iso:country":"CN",
    "name:und_x_variant":[
        "Tongmu\u2019ao"
    ],
    "name:zho_x_preferred":[
        "\u6850\u6728\u51f9"
    ],
    "wof:name":"Tongmu'ao",
    "wof:placetype":"locality"
},
  "geometry": {"coordinates":[113.39660000000001,24.49142],"type":"Point"}
}