{
  "type": "Feature",
  "properties": {
    "gn:admin1_code":"26",
    "gn:asciiname":"Taoqucun",
    "gn:country_code":"CN",
    "gn:dem":1039,
    "gn:feature_class":"P",
    "gn:feature_code":"PPL",
    "gn:name":"Taoqucun",
    "gn:population":0,
    "gn:timezone":"Asia/Shanghai",
    "iso:country":"CN",
    "name:und_x_variant":[
        "T\u2019ao-ch\u2019\u00fc",
        "Taoqu",
        "Taoqucun"
    ],
    "name:zho_x_preferred":[
        "\u6843\u66f2\u6751"
    ],
    "wof:name":"Taoqucun",
    "wof:placetype":"locality"
},
  "geometry": {"coordinates":[108.98775999999999,35.52887],"type":"Point"}
}