{
  "type": "Feature",
  "properties": {
    "gn:admin1_code":"15.0",
    "gn:asciiname":"Jiufangqu",
    "gn:country_code":"CN",
    "gn:dem":1750,
    "gn:feature_class":"P",
    "gn:feature_code":"PPL",
    "gn:name":"Jiufangqu",
    "gn:population":0,
    "gn:timezone":"Asia/Shanghai",
    "iso:country":"CN",
    "name:und_x_variant":[
        "\u9152\u623f\u6e20"
    ],
    "wof:name":"Jiufangqu",
    "wof:placetype":"locality"
},
  "geometry": {"coordinates":[106.75049,36.57055],"type":"Point"}
}