{
  "type": "Feature",
  "properties": {
    "gn:admin1_code":"5.0",
    "gn:asciiname":"Xiaosandaogou",
    "gn:country_code":"CN",
    "gn:dem":267,
    "gn:feature_class":"P",
    "gn:feature_code":"PPL",
    "gn:name":"Xiaosandaogou",
    "gn:population":0,
    "gn:timezone":"Asia/Shanghai",
    "iso:country":"CN",
    "name:zho_x_preferred":[
        "\u5c0f\u4e09\u9053\u6c9f"
    ],
    "wof:name":"Xiaosandaogou",
    "wof:placetype":"locality"
},
  "geometry": {"coordinates":[125.11691999999999,43.23009],"type":"Point"}
}