{
  "type": "Feature",
  "properties": {
    "gn:admin1_code":"14.0",
    "gn:asciiname":"Chagkug",
    "gn:country_code":"CN",
    "gn:dem":4445,
    "gn:feature_class":"P",
    "gn:feature_code":"PPL",
    "gn:name":"Chagkug",
    "gn:population":0,
    "gn:timezone":"Asia/Urumqi",
    "iso:country":"CN",
    "name:bod_x_preferred":[
        "Chagkug"
    ],
    "name:zho_x_preferred":[
        "Zhagui"
    ],
    "name:zho_x_variant":[
        "\u624e\u89c4",
        "Dongjiao Gongshe",
        "\u4e1c\u90ca\u516c\u793e"
    ],
    "wof:name":"Chagkug",
    "wof:placetype":"locality"
},
  "geometry": {"coordinates":[89.60799999999998,28.808],"type":"Point"}
}