{
  "type": "Feature",
  "properties": {
    "gn:admin1_code":"18",
    "gn:asciiname":"Xiaoyanguan",
    "gn:country_code":"CN",
    "gn:dem":489,
    "gn:feature_class":"P",
    "gn:feature_code":"PPL",
    "gn:name":"Xiaoyanguan",
    "gn:population":0,
    "gn:timezone":"Asia/Shanghai",
    "iso:country":"CN",
    "name:zho_x_preferred":[
        "\u5c0f\u5ca9\u5173"
    ],
    "wof:name":"Xiaoyanguan",
    "wof:placetype":"locality"
},
  "geometry": {"coordinates":[108.23699999999999,27.9325],"type":"Point"}
}