{
  "type": "Feature",
  "properties": {
    "gn:admin1_code":"26.0",
    "gn:asciiname":"Qingbaishi",
    "gn:country_code":"CN",
    "gn:dem":630,
    "gn:feature_class":"P",
    "gn:feature_code":"PPL",
    "gn:name":"Qingbaishi",
    "gn:population":0,
    "gn:timezone":"Asia/Shanghai",
    "iso:country":"CN",
    "name:und_x_variant":[
        "\u9752\u767d\u77f3"
    ],
    "wof:name":"Qingbaishi",
    "wof:placetype":"locality"
},
  "geometry": {"coordinates":[106.0827,33.24415],"type":"Point"}
}