{
  "type": "Feature",
  "properties": {
    "gn:admin1_code":"9",
    "gn:asciiname":"Dahulou",
    "gn:country_code":"CN",
    "gn:dem":49,
    "gn:feature_class":"P",
    "gn:feature_code":"PPL",
    "gn:name":"Dahulou",
    "gn:population":0,
    "gn:timezone":"Asia/Shanghai",
    "iso:country":"CN",
    "name:zho_x_preferred":[
        "\u5927\u80e1\u697c"
    ],
    "wof:name":"Dahulou",
    "wof:placetype":"locality"
},
  "geometry": {"coordinates":[115.58759000000001,35.90298],"type":"Point"}
}