{
  "type": "Feature",
  "properties": {
    "gn:admin1_code":"2.0",
    "gn:asciiname":"Yingchungang",
    "gn:country_code":"CN",
    "gn:dem":7,
    "gn:feature_class":"P",
    "gn:feature_code":"PPL",
    "gn:name":"Yingchungang",
    "gn:population":0,
    "gn:timezone":"Asia/Shanghai",
    "iso:country":"CN",
    "name:und_x_variant":[
        "\u8fce\u6625\u6e2f"
    ],
    "wof:name":"Yingchungang",
    "wof:placetype":"locality"
},
  "geometry": {"coordinates":[120.71613000000001,30.63706],"type":"Point"}
}