{
  "type": "Feature",
  "properties": {
    "gn:admin1_code":"5.0",
    "gn:asciiname":"Fuxing Nongchang Erdui",
    "gn:country_code":"CN",
    "gn:dem":605,
    "gn:feature_class":"P",
    "gn:feature_code":"PPLF",
    "gn:name":"Fuxing Nongchang Erdui",
    "gn:population":0,
    "gn:timezone":"Asia/Shanghai",
    "iso:country":"CN",
    "name:und_x_variant":[
        "\u590d\u5174\u519c\u573a\u4e8c\u961f"
    ],
    "wof:name":"Fuxing Nongchang Erdui",
    "wof:placetype":"locality"
},
  "geometry": {"coordinates":[130.42286999999999,43.42406],"type":"Point"}
}