{
  "type": "Feature",
  "properties": {
    "gn:admin1_code":"30",
    "gn:asciiname":"Dawangzhu",
    "gn:country_code":"CN",
    "gn:dem":292,
    "gn:feature_class":"P",
    "gn:feature_code":"PPL",
    "gn:name":"Dawangzhu",
    "gn:population":0,
    "gn:timezone":"Asia/Urumqi",
    "iso:country":"CN",
    "name:zho_x_preferred":[
        "\u5927\u65fa\u7af9"
    ],
    "wof:name":"Dawangzhu",
    "wof:placetype":"locality"
},
  "geometry": {"coordinates":[110.99142000000001,22.20282000000001],"type":"Point"}
}