{
  "type": "Feature",
  "properties": {
    "gn:admin1_code":"18.0",
    "gn:asciiname":"Tuanjie",
    "gn:country_code":"CN",
    "gn:dem":501,
    "gn:feature_class":"P",
    "gn:feature_code":"PPL",
    "gn:name":"Tuanjie",
    "gn:population":0,
    "gn:timezone":"Asia/Shanghai",
    "iso:country":"CN",
    "name:zho_x_preferred":[
        "\u56e2\u7ed3"
    ],
    "wof:name":"Tuanjie",
    "wof:placetype":"locality"
},
  "geometry": {"coordinates":[108.70099999999999,25.831],"type":"Point"}
}