{
  "type": "Feature",
  "properties": {
    "gn:admin1_code":"25",
    "gn:asciiname":"Beiwuli",
    "gn:country_code":"CN",
    "gn:dem":33,
    "gn:feature_class":"P",
    "gn:feature_code":"PPL",
    "gn:name":"Beiwuli",
    "gn:population":0,
    "gn:timezone":"Asia/Shanghai",
    "iso:country":"CN",
    "name:zho_x_preferred":[
        "\u5317\u4e94\u91cc"
    ],
    "wof:name":"Beiwuli",
    "wof:placetype":"locality"
},
  "geometry": {"coordinates":[116.142,36.5835],"type":"Point"}
}