{
  "type": "Feature",
  "properties": {
    "gn:admin1_code":"14.0",
    "gn:asciiname":"Shalangge",
    "gn:country_code":"CN",
    "gn:dem":4078,
    "gn:feature_class":"P",
    "gn:feature_code":"PPL",
    "gn:name":"Shalangge",
    "gn:population":0,
    "gn:timezone":"Asia/Urumqi",
    "iso:country":"CN",
    "name:zho_x_preferred":[
        "\u6c99\u90ce\u683c"
    ],
    "wof:name":"Shalangge",
    "wof:placetype":"locality"
},
  "geometry": {"coordinates":[97.54485,32.26691],"type":"Point"}
}