{
  "type": "Feature",
  "properties": {
    "gn:admin1_code":"11.0",
    "gn:asciiname":"Songxifu",
    "gn:country_code":"CN",
    "gn:dem":58,
    "gn:feature_class":"P",
    "gn:feature_code":"PPL",
    "gn:name":"Songxifu",
    "gn:population":0,
    "gn:timezone":"Asia/Shanghai",
    "iso:country":"CN",
    "name:zho_x_preferred":[
        "\u677e\u6eaa\u5085"
    ],
    "wof:name":"Songxifu",
    "wof:placetype":"locality"
},
  "geometry": {"coordinates":[113.34701,29.011],"type":"Point"}
}