{
  "type": "Feature",
  "properties": {
    "gn:admin1_code":"5.0",
    "gn:asciiname":"Xiqingzhen",
    "gn:country_code":"CN",
    "gn:dem":697,
    "gn:feature_class":"P",
    "gn:feature_code":"PPL",
    "gn:name":"Xiqingzhen",
    "gn:population":0,
    "gn:timezone":"Asia/Shanghai",
    "iso:country":"CN",
    "name:zho_x_preferred":[
        "\u897f\u6e05\u771f"
    ],
    "wof:name":"Xiqingzhen",
    "wof:placetype":"locality"
},
  "geometry": {"coordinates":[128.02795,43.40414000000001],"type":"Point"}
}