{
  "type": "Feature",
  "properties": {
    "gn:admin1_code":"24.0",
    "gn:asciiname":"Dishuiyacun",
    "gn:country_code":"CN",
    "gn:dem":1142,
    "gn:feature_class":"P",
    "gn:feature_code":"PPL",
    "gn:name":"Dishuiyacun",
    "gn:population":0,
    "gn:timezone":"Asia/Shanghai",
    "iso:country":"CN",
    "name:zho_x_preferred":[
        "\u6ef4\u6c34\u5d16\u6751"
    ],
    "wof:name":"Dishuiyacun",
    "wof:placetype":"locality"
},
  "geometry": {"coordinates":[114.2861,39.83299],"type":"Point"}
}