{
  "type": "Feature",
  "properties": {
    "gn:admin1_code":"25.0",
    "gn:asciiname":"Kongjiazhuangcun",
    "gn:country_code":"CN",
    "gn:dem":39,
    "gn:feature_class":"P",
    "gn:feature_code":"PPL",
    "gn:name":"Kongjiazhuangcun",
    "gn:population":0,
    "gn:timezone":"Asia/Shanghai",
    "iso:country":"CN",
    "name:zho_x_preferred":[
        "\u5b54\u5bb6\u5e84\u6751"
    ],
    "wof:name":"Kongjiazhuangcun",
    "wof:placetype":"locality"
},
  "geometry": {"coordinates":[122.36685,37.11223],"type":"Point"}
}