{
  "type": "Feature",
  "properties": {
    "gn:admin1_code":"25",
    "gn:asciiname":"Lijiashanzhuang",
    "gn:country_code":"CN",
    "gn:dem":276,
    "gn:feature_class":"P",
    "gn:feature_code":"PPL",
    "gn:name":"Lijiashanzhuang",
    "gn:population":0,
    "gn:timezone":"Asia/Shanghai",
    "iso:country":"CN",
    "name:zho_x_preferred":[
        "\u674e\u5bb6\u5c71\u5e84"
    ],
    "wof:name":"Lijiashanzhuang",
    "wof:placetype":"locality"
},
  "geometry": {"coordinates":[119.062,35.5929],"type":"Point"}
}