{
  "type": "Feature",
  "properties": {
    "gn:admin1_code":"25",
    "gn:asciiname":"Dongyujiatun",
    "gn:country_code":"CN",
    "gn:dem":72,
    "gn:feature_class":"P",
    "gn:feature_code":"PPL",
    "gn:name":"Dongyujiatun",
    "gn:population":0,
    "gn:timezone":"Asia/Shanghai",
    "iso:country":"CN",
    "name:zho_x_preferred":[
        "\u4e1c\u4e8e\u5bb6\u5c6f"
    ],
    "wof:name":"Dongyujiatun",
    "wof:placetype":"locality"
},
  "geometry": {"coordinates":[120.256,36.8906],"type":"Point"}
}