{
  "type": "Feature",
  "properties": {
    "gn:admin1_code":"15.0",
    "gn:asciiname":"Shibugou",
    "gn:country_code":"CN",
    "gn:dem":1664,
    "gn:feature_class":"P",
    "gn:feature_code":"PPL",
    "gn:name":"Shibugou",
    "gn:population":0,
    "gn:timezone":"Asia/Shanghai",
    "iso:country":"CN",
    "name:zho_x_preferred":[
        "\u77f3\u5e03\u6c9f"
    ],
    "wof:name":"Shibugou",
    "wof:placetype":"locality"
},
  "geometry": {"coordinates":[104.596,32.798],"type":"Point"}
}