{
  "type": "Feature",
  "properties": {
    "gn:admin1_code":"25",
    "gn:asciiname":"Cangqiu Yicun",
    "gn:country_code":"CN",
    "gn:dem":63,
    "gn:feature_class":"P",
    "gn:feature_code":"PPL",
    "gn:name":"Cangqiu Yicun",
    "gn:population":0,
    "gn:timezone":"Asia/Shanghai",
    "iso:country":"CN",
    "name:zho_x_preferred":[
        "\u82cd\u90b1\u4e00\u6751"
    ],
    "wof:name":"Cangqiu Yicun",
    "wof:placetype":"locality"
},
  "geometry": {"coordinates":[116.61799999999999,35.975],"type":"Point"}
}