{
  "type": "Feature",
  "properties": {
    "gn:admin1_code":"9.0",
    "gn:asciiname":"Jiancaoping",
    "gn:country_code":"CN",
    "gn:dem":1064,
    "gn:feature_class":"P",
    "gn:feature_code":"PPL",
    "gn:name":"Jiancaoping",
    "gn:population":0,
    "gn:timezone":"Asia/Shanghai",
    "iso:country":"CN",
    "name:zho_x_preferred":[
        "\u5c16\u8349\u576a"
    ],
    "wof:name":"Jiancaoping",
    "wof:placetype":"locality"
},
  "geometry": {"coordinates":[110.58341,34.25388],"type":"Point"}
}