{
  "type": "Feature",
  "properties": {
    "gn:admin1_code":"11",
    "gn:asciiname":"Longjia",
    "gn:country_code":"CN",
    "gn:dem":609,
    "gn:feature_class":"P",
    "gn:feature_code":"PPL",
    "gn:name":"Longjia",
    "gn:population":0,
    "gn:timezone":"Asia/Shanghai",
    "iso:country":"CN",
    "name:deu_x_preferred":[
        "Longjia"
    ],
    "name:und_x_variant":[
        "\u9f99\u5bb6"
    ],
    "wof:name":"Longjia",
    "wof:placetype":"locality"
},
  "geometry": {"coordinates":[111.77611,25.82194],"type":"Point"}
}