{
  "type": "Feature",
  "properties": {
    "gn:admin1_code":"30.0",
    "gn:asciiname":"Shangyan",
    "gn:country_code":"CN",
    "gn:dem":217,
    "gn:feature_class":"P",
    "gn:feature_code":"PPL",
    "gn:name":"Shangyan",
    "gn:population":0,
    "gn:timezone":"Asia/Shanghai",
    "iso:country":"CN",
    "name:zho_x_preferred":[
        "Shangyan"
    ],
    "name:zho_x_variant":[
        "\u4e0a\u989c"
    ],
    "wof:name":"Shangyan",
    "wof:placetype":"locality"
},
  "geometry": {"coordinates":[114.43838,24.29037000000001],"type":"Point"}
}