{
  "type": "Feature",
  "properties": {
    "gn:admin1_code":"12",
    "gn:asciiname":"Fankou",
    "gn:country_code":"CN",
    "gn:dem":25,
    "gn:feature_class":"P",
    "gn:feature_code":"PPLA4",
    "gn:name":"Fankou",
    "gn:population":0,
    "gn:timezone":"Asia/Shanghai",
    "iso:country":"CN",
    "name:und_x_variant":[
        "Fan-k\u2019ou-chieh",
        "Fankou",
        "\u6a0a\u53e3",
        "Fankou Jiedao",
        "\u6a0a\u53e3\u8857\u9053"
    ],
    "wof:name":"Fankou",
    "wof:placetype":"locality"
},
  "geometry": {"coordinates":[114.83333,30.41667],"type":"Point"}
}