{
  "type": "Feature",
  "properties": {
    "gn:admin1_code":"2",
    "gn:asciiname":"Dongwu",
    "gn:country_code":"CN",
    "gn:dem":267,
    "gn:feature_class":"P",
    "gn:feature_code":"PPLA4",
    "gn:name":"Dongwu",
    "gn:population":0,
    "gn:timezone":"Asia/Shanghai",
    "iso:country":"CN",
    "name:und_x_variant":[
        "Changpu"
    ],
    "name:zho_x_preferred":[
        "\u4e1c\u575e"
    ],
    "name:zho_x_variant":[
        "\u83d6\u84b2"
    ],
    "wof:name":"Dongwu",
    "wof:placetype":"locality"
},
  "geometry": {"coordinates":[118.54769,29.23439],"type":"Point"}
}