{
  "type": "Feature",
  "properties": {
    "gn:admin1_code":"7.0",
    "gn:asciiname":"Longxibang",
    "gn:country_code":"CN",
    "gn:dem":373,
    "gn:feature_class":"P",
    "gn:feature_code":"PPL",
    "gn:name":"Longxibang",
    "gn:population":0,
    "gn:timezone":"Asia/Shanghai",
    "iso:country":"CN",
    "name:zho_x_preferred":[
        "\u9f99\u6eaa\u90a6"
    ],
    "wof:name":"Longxibang",
    "wof:placetype":"locality"
},
  "geometry": {"coordinates":[116.96832999999999,25.04472],"type":"Point"}
}