{
  "type": "Feature",
  "properties": {
    "gn:admin1_code":"12.0",
    "gn:asciiname":"Wujialaozhuang",
    "gn:country_code":"CN",
    "gn:dem":126,
    "gn:feature_class":"P",
    "gn:feature_code":"PPL",
    "gn:name":"Wujialaozhuang",
    "gn:population":0,
    "gn:timezone":"Asia/Shanghai",
    "iso:country":"CN",
    "name:zho_x_preferred":[
        "\u5434\u5bb6\u8001\u5e84"
    ],
    "wof:name":"Wujialaozhuang",
    "wof:placetype":"locality"
},
  "geometry": {"coordinates":[111.58325000000001,32.38915],"type":"Point"}
}