{
  "type": "Feature",
  "properties": {
    "gn:admin1_code":"4.0",
    "gn:asciiname":"Yingshan",
    "gn:country_code":"CN",
    "gn:dem":62,
    "gn:feature_class":"P",
    "gn:feature_code":"PPL",
    "gn:name":"Yingshan",
    "gn:population":0,
    "gn:timezone":"Asia/Shanghai",
    "iso:country":"CN",
    "name:und_x_variant":[
        "\u82f1\u5c71"
    ],
    "wof:name":"Yingshan",
    "wof:placetype":"locality"
},
  "geometry": {"coordinates":[118.46556,34.66893],"type":"Point"}
}