{
  "type": "Feature",
  "properties": {
    "gn:admin1_code":"14.0",
    "gn:asciiname":"Sinyachagdog",
    "gn:country_code":"CN",
    "gn:dem":4533,
    "gn:feature_class":"P",
    "gn:feature_code":"PPL",
    "gn:name":"Sinyachagdog",
    "gn:population":0,
    "gn:timezone":"Asia/Urumqi",
    "iso:country":"CN",
    "name:bod_x_preferred":[
        "Sinyachagdog"
    ],
    "name:zho_x_preferred":[
        "Senyachaduo"
    ],
    "name:zho_x_variant":[
        "\u68ee\u4e9a\u67e5\u591a"
    ],
    "wof:name":"Sinyachagdog",
    "wof:placetype":"locality"
},
  "geometry": {"coordinates":[88.101,32.001],"type":"Point"}
}