{
  "type": "Feature",
  "properties": {
    "gn:admin1_code":"25",
    "gn:asciiname":"Shuangqing",
    "gn:country_code":"CN",
    "gn:dem":204,
    "gn:feature_class":"P",
    "gn:feature_code":"PPL",
    "gn:name":"Shuangqing",
    "gn:population":0,
    "gn:timezone":"Asia/Shanghai",
    "iso:country":"CN",
    "name:zho_x_preferred":[
        "\u53cc\u9752"
    ],
    "wof:name":"Shuangqing",
    "wof:placetype":"locality"
},
  "geometry": {"coordinates":[117.73,36.7062],"type":"Point"}
}