{
  "type": "Feature",
  "properties": {
    "gn:admin1_code":"15.0",
    "gn:asciiname":"Baiyazi",
    "gn:country_code":"CN",
    "gn:dem":2306,
    "gn:feature_class":"P",
    "gn:feature_code":"PPL",
    "gn:name":"Baiyazi",
    "gn:population":0,
    "gn:timezone":"Asia/Shanghai",
    "iso:country":"CN",
    "name:zho_x_preferred":[
        "\u767d\u5d16\u5b50"
    ],
    "wof:name":"Baiyazi",
    "wof:placetype":"locality"
},
  "geometry": {"coordinates":[103.413,36.7861],"type":"Point"}
}