{
  "type": "Feature",
  "properties": {
    "gn:admin1_code":"29.0",
    "gn:asciiname":"Shanglaowu",
    "gn:country_code":"CN",
    "gn:dem":1959,
    "gn:feature_class":"P",
    "gn:feature_code":"PPL",
    "gn:name":"Shanglaowu",
    "gn:population":0,
    "gn:timezone":"Asia/Shanghai",
    "iso:country":"CN",
    "name:und_x_variant":[
        "\u4e0a\u8001\u4e4c"
    ],
    "wof:name":"Shanglaowu",
    "wof:placetype":"locality"
},
  "geometry": {"coordinates":[102.57191,25.58302],"type":"Point"}
}