{
  "type": "Feature",
  "properties": {
    "gn:admin1_code":"9.0",
    "gn:asciiname":"Tangji",
    "gn:country_code":"CN",
    "gn:dem":61,
    "gn:feature_class":"P",
    "gn:feature_code":"PPL",
    "gn:name":"Tangji",
    "gn:population":0,
    "gn:timezone":"Asia/Shanghai",
    "iso:country":"CN",
    "name:zho_x_preferred":[
        "\u5510\u96c6"
    ],
    "wof:name":"Tangji",
    "wof:placetype":"locality"
},
  "geometry": {"coordinates":[115.59484,32.34023],"type":"Point"}
}