{
  "type": "Feature",
  "properties": {
    "gn:admin1_code":"29",
    "gn:asciiname":"Luoguochong",
    "gn:country_code":"CN",
    "gn:dem":1914,
    "gn:feature_class":"P",
    "gn:feature_code":"PPL",
    "gn:name":"Luoguochong",
    "gn:population":0,
    "gn:timezone":"Asia/Shanghai",
    "iso:country":"CN",
    "name:zho_x_preferred":[
        "\u7f57\u8fc7\u51b2"
    ],
    "wof:name":"Luoguochong",
    "wof:placetype":"locality"
},
  "geometry": {"coordinates":[101.961,23.4628],"type":"Point"}
}