{
  "type": "Feature",
  "properties": {
    "gn:admin1_code":"8.0",
    "gn:asciiname":"Fanrongcun",
    "gn:country_code":"CN",
    "gn:dem":140,
    "gn:feature_class":"P",
    "gn:feature_code":"PPL",
    "gn:name":"Fanrongcun",
    "gn:population":0,
    "gn:timezone":"Asia/Shanghai",
    "iso:country":"CN",
    "name:zho_x_preferred":[
        "\u7e41\u8363\u6751"
    ],
    "wof:name":"Fanrongcun",
    "wof:placetype":"locality"
},
  "geometry": {"coordinates":[125.75136999999999,45.40484],"type":"Point"}
}