{
  "type": "Feature",
  "properties": {
    "gn:admin1_code":"16.0",
    "gn:asciiname":"Qun'an",
    "gn:country_code":"CN",
    "gn:dem":142,
    "gn:feature_class":"P",
    "gn:feature_code":"PPL",
    "gn:name":"Qun\u2019an",
    "gn:population":0,
    "gn:timezone":"Asia/Shanghai",
    "iso:country":"CN",
    "name:und_x_variant":[
        "Qun\u2019an"
    ],
    "name:zho_x_preferred":[
        "\u7fa4\u5b89"
    ],
    "wof:name":"Qun'an",
    "wof:placetype":"locality"
},
  "geometry": {"coordinates":[109.14700000000001,23.5013],"type":"Point"}
}