{
  "type": "Feature",
  "properties": {
    "gn:admin1_code":"19.0",
    "gn:asciiname":"Huangdingzi",
    "gn:country_code":"CN",
    "gn:dem":226,
    "gn:feature_class":"P",
    "gn:feature_code":"PPL",
    "gn:name":"Huangdingzi",
    "gn:population":0,
    "gn:timezone":"Asia/Shanghai",
    "iso:country":"CN",
    "name:zho_x_preferred":[
        "\u8352\u9876\u5b50"
    ],
    "wof:name":"Huangdingzi",
    "wof:placetype":"locality"
},
  "geometry": {"coordinates":[124.22801,42.82957],"type":"Point"}
}