{
  "type": "Feature",
  "properties": {
    "gn:admin1_code":"1.0",
    "gn:asciiname":"Shaolian",
    "gn:country_code":"CN",
    "gn:dem":176,
    "gn:feature_class":"P",
    "gn:feature_code":"PPLA4",
    "gn:name":"Shaolian",
    "gn:population":0,
    "gn:timezone":"Asia/Shanghai",
    "iso:country":"CN",
    "name:und_x_variant":[
        "Shao-lien",
        "Shaolian",
        "Shaolian Xiang"
    ],
    "name:zho_x_preferred":[
        "\u7ecd\u6fc2"
    ],
    "wof:name":"Shaolian",
    "wof:placetype":"locality"
},
  "geometry": {"coordinates":[118.46274,29.70438],"type":"Point"}
}