{
  "type": "Feature",
  "properties": {
    "gn:admin1_code":"3.0",
    "gn:asciiname":"Fenglang",
    "gn:country_code":"CN",
    "gn:dem":163,
    "gn:feature_class":"P",
    "gn:feature_code":"PPL",
    "gn:name":"Fenglang",
    "gn:population":0,
    "gn:timezone":"Asia/Shanghai",
    "iso:country":"CN",
    "name:und_x_variant":[
        "\u98ce\u6d6a"
    ],
    "wof:name":"Fenglang",
    "wof:placetype":"locality"
},
  "geometry": {"coordinates":[114.51352,29.05412],"type":"Point"}
}