{
  "type": "Feature",
  "properties": {
    "gn:admin1_code":"10",
    "gn:asciiname":"Songmen",
    "gn:country_code":"CN",
    "gn:dem":21,
    "gn:feature_class":"P",
    "gn:feature_code":"PPL",
    "gn:name":"Songmen",
    "gn:population":0,
    "gn:timezone":"Asia/Shanghai",
    "iso:country":"CN",
    "name:und_x_variant":[
        "Sung-men",
        "Sung-men-chen",
        "Songmen"
    ],
    "name:zho_x_preferred":[
        "\u5b8b\u95e8"
    ],
    "wof:name":"Songmen",
    "wof:placetype":"locality"
},
  "geometry": {"coordinates":[116.11893000000001,37.73867],"type":"Point"}
}