{
  "type": "Feature",
  "properties": {
    "gn:admin1_code":"4.0",
    "gn:asciiname":"Tailiuxu",
    "gn:country_code":"CN",
    "gn:dem":3,
    "gn:feature_class":"P",
    "gn:feature_code":"PPLF",
    "gn:name":"Tailiuxu",
    "gn:population":0,
    "gn:timezone":"Asia/Shanghai",
    "iso:country":"CN",
    "name:zho_x_preferred":[
        "\u592a\u516d\u5729"
    ],
    "wof:name":"Tailiuxu",
    "wof:placetype":"locality"
},
  "geometry": {"coordinates":[120.09520000000001,32.00371],"type":"Point"}
}