{
  "type": "Feature",
  "properties": {
    "gn:admin1_code":"3.0",
    "gn:asciiname":"Guangshan Xunongchang",
    "gn:country_code":"CN",
    "gn:dem":51,
    "gn:feature_class":"P",
    "gn:feature_code":"PPLF",
    "gn:name":"Guangshan Xunongchang",
    "gn:population":0,
    "gn:timezone":"Asia/Shanghai",
    "iso:country":"CN",
    "name:und_x_variant":[
        "\u5e7f\u5c71\u755c\u7267\u573a"
    ],
    "wof:name":"Guangshan Xunongchang",
    "wof:placetype":"locality"
},
  "geometry": {"coordinates":[115.60088,29.00638],"type":"Point"}
}