{
  "type": "Feature",
  "properties": {
    "gn:admin1_code":"16.0",
    "gn:asciiname":"Danxian",
    "gn:country_code":"CN",
    "gn:dem":465,
    "gn:feature_class":"P",
    "gn:feature_code":"PPL",
    "gn:name":"Danxian",
    "gn:population":0,
    "gn:timezone":"Asia/Shanghai",
    "iso:country":"CN",
    "name:zho_x_preferred":[
        "\u4e39\u7ebf"
    ],
    "wof:name":"Danxian",
    "wof:placetype":"locality"
},
  "geometry": {"coordinates":[107.754,23.8322],"type":"Point"}
}