{
  "type": "Feature",
  "properties": {
    "gn:admin1_code":"12.0",
    "gn:asciiname":"Caojiayuan",
    "gn:country_code":"CN",
    "gn:dem":176,
    "gn:feature_class":"P",
    "gn:feature_code":"PPL",
    "gn:name":"Caojiayuan",
    "gn:population":0,
    "gn:timezone":"Asia/Shanghai",
    "iso:country":"CN",
    "name:zho_x_preferred":[
        "\u66f9\u5bb6\u9662"
    ],
    "wof:name":"Caojiayuan",
    "wof:placetype":"locality"
},
  "geometry": {"coordinates":[111.40175000000001,32.58326],"type":"Point"}
}