{
  "type": "Feature",
  "properties": {
    "gn:admin1_code":"30",
    "gn:asciiname":"Bainixu",
    "gn:country_code":"CN",
    "gn:dem":5,
    "gn:feature_class":"P",
    "gn:feature_code":"PPL",
    "gn:name":"Bainixu",
    "gn:population":0,
    "gn:timezone":"Asia/Shanghai",
    "iso:country":"CN",
    "name:und_x_variant":[
        "\u767d\u6ce5\u5729"
    ],
    "wof:name":"Bainixu",
    "wof:placetype":"locality"
},
  "geometry": {"coordinates":[113.01727,23.42472],"type":"Point"}
}