{
  "type": "Feature",
  "properties": {
    "gn:admin1_code":"11",
    "gn:asciiname":"Pipasuo",
    "gn:country_code":"CN",
    "gn:dem":398,
    "gn:feature_class":"P",
    "gn:feature_code":"PPL",
    "gn:name":"Pipasuo",
    "gn:population":0,
    "gn:timezone":"Asia/Shanghai",
    "iso:country":"CN",
    "name:zho_x_preferred":[
        "\u6787\u6777\u6240"
    ],
    "wof:name":"Pipasuo",
    "wof:placetype":"locality"
},
  "geometry": {"coordinates":[111.43895000000001,25.08106],"type":"Point"}
}