{
  "type": "Feature",
  "properties": {
    "gn:admin1_code":"1.0",
    "gn:asciiname":"Yangpingcun",
    "gn:country_code":"CN",
    "gn:dem":401,
    "gn:feature_class":"P",
    "gn:feature_code":"PPL",
    "gn:name":"Yangpingcun",
    "gn:population":0,
    "gn:timezone":"Asia/Shanghai",
    "iso:country":"CN",
    "name:zho_x_preferred":[
        "\u9633\u576a\u6751"
    ],
    "wof:name":"Yangpingcun",
    "wof:placetype":"locality"
},
  "geometry": {"coordinates":[116.00359,30.41379],"type":"Point"}
}