{
  "type": "Feature",
  "properties": {
    "gn:admin1_code":"5.0",
    "gn:asciiname":"Xiaohongqi Hedong",
    "gn:country_code":"CN",
    "gn:dem":89,
    "gn:feature_class":"P",
    "gn:feature_code":"PPL",
    "gn:name":"Xiaohongqi Hedong",
    "gn:population":0,
    "gn:timezone":"Asia/Shanghai",
    "iso:country":"CN",
    "name:und_x_variant":[
        "\u5c0f\u7ea2\u65d7\u6cb3\u4e1c"
    ],
    "wof:name":"Xiaohongqi Hedong",
    "wof:placetype":"locality"
},
  "geometry": {"coordinates":[130.60361,42.95741],"type":"Point"}
}