{
  "type": "Feature",
  "properties": {
    "gn:admin1_code":"18",
    "gn:asciiname":"Najian",
    "gn:country_code":"CN",
    "gn:dem":716,
    "gn:feature_class":"P",
    "gn:feature_code":"PPL",
    "gn:name":"Najian",
    "gn:population":0,
    "gn:timezone":"Asia/Shanghai",
    "iso:country":"CN",
    "name:zho_x_preferred":[
        "\u7eb3\u89c1"
    ],
    "wof:name":"Najian",
    "wof:placetype":"locality"
},
  "geometry": {"coordinates":[106.517,25.4323],"type":"Point"}
}