{
  "type": "Feature",
  "properties": {
    "gn:admin1_code":"3.0",
    "gn:asciiname":"Aozixia",
    "gn:country_code":"CN",
    "gn:dem":195,
    "gn:feature_class":"P",
    "gn:feature_code":"PPL",
    "gn:name":"Aozixia",
    "gn:population":0,
    "gn:timezone":"Asia/Shanghai",
    "iso:country":"CN",
    "name:und_x_variant":[
        "\u5773\u5b50\u4e0b"
    ],
    "wof:name":"Aozixia",
    "wof:placetype":"locality"
},
  "geometry": {"coordinates":[115.26269000000001,29.47855],"type":"Point"}
}