{
  "type": "Feature",
  "properties": {
    "gn:admin1_code":"32.0",
    "gn:asciiname":"Bamu Qiedeng",
    "gn:country_code":"CN",
    "gn:dem":4098,
    "gn:feature_class":"P",
    "gn:feature_code":"PPL",
    "gn:name":"Bamu Qiedeng",
    "gn:population":0,
    "gn:timezone":"Asia/Shanghai",
    "iso:country":"CN",
    "name:zho_x_preferred":[
        "\u62d4\u6bcd\u5207\u767b"
    ],
    "wof:name":"Bamu Qiedeng",
    "wof:placetype":"locality"
},
  "geometry": {"coordinates":[101.702,29.6359],"type":"Point"}
}