{
  "type": "Feature",
  "properties": {
    "gn:admin1_code":"29.0",
    "gn:asciiname":"Batou",
    "gn:country_code":"CN",
    "gn:dem":1885,
    "gn:feature_class":"P",
    "gn:feature_code":"PPL",
    "gn:name":"Batou",
    "gn:population":0,
    "gn:timezone":"Asia/Shanghai",
    "iso:country":"CN",
    "name:jpn_x_preferred":[
        "\u30d0\u30c8\u30fc"
    ],
    "name:spa_x_preferred":[
        "Batou"
    ],
    "name:zho_x_preferred":[
        "\u575d\u5934"
    ],
    "wof:name":"Batou",
    "wof:placetype":"locality"
},
  "geometry": {"coordinates":[98.71510000000001,24.4057],"type":"Point"}
}