{
  "type": "Feature",
  "properties": {
    "gn:admin1_code":"4.0",
    "gn:asciiname":"Hanqiao",
    "gn:country_code":"CN",
    "gn:dem":7,
    "gn:feature_class":"P",
    "gn:feature_code":"PPL",
    "gn:name":"Hanqiao",
    "gn:population":0,
    "gn:timezone":"Asia/Shanghai",
    "iso:country":"CN",
    "name:zho_x_preferred":[
        "Hanqiao"
    ],
    "name:zho_x_variant":[
        "\u97e9\u6865"
    ],
    "wof:name":"Hanqiao",
    "wof:placetype":"locality"
},
  "geometry": {"coordinates":[119.99612999999999,34.16103],"type":"Point"}
}