{
  "type": "Feature",
  "properties": {
    "gn:admin1_code":"2.0",
    "gn:asciiname":"Kenbu",
    "gn:country_code":"CN",
    "gn:dem":14,
    "gn:feature_class":"P",
    "gn:feature_code":"PPL",
    "gn:name":"Kenbu",
    "gn:population":0,
    "gn:timezone":"Asia/Shanghai",
    "iso:country":"CN",
    "name:zho_x_preferred":[
        "\u80af\u6b65"
    ],
    "wof:name":"Kenbu",
    "wof:placetype":"locality"
},
  "geometry": {"coordinates":[121.52715000000001,28.78345],"type":"Point"}
}