{
  "type": "Feature",
  "properties": {
    "gn:admin1_code":"32.0",
    "gn:asciiname":"Huoqiao",
    "gn:country_code":"CN",
    "gn:dem":281,
    "gn:feature_class":"P",
    "gn:feature_code":"PPL",
    "gn:name":"Huoqiao",
    "gn:population":0,
    "gn:timezone":"Asia/Shanghai",
    "iso:country":"CN",
    "name:zho_x_preferred":[
        "\u6d3b\u6865"
    ],
    "wof:name":"Huoqiao",
    "wof:placetype":"locality"
},
  "geometry": {"coordinates":[105.53400000000001,30.1106],"type":"Point"}
}