{
  "type": "Feature",
  "properties": {
    "gn:admin1_code":"5.0",
    "gn:asciiname":"Nongfengcun",
    "gn:country_code":"CN",
    "gn:dem":155,
    "gn:feature_class":"P",
    "gn:feature_code":"PPL",
    "gn:name":"Nongfengcun",
    "gn:population":0,
    "gn:timezone":"Asia/Shanghai",
    "iso:country":"CN",
    "name:zho_x_preferred":[
        "\u519c\u4e30\u6751"
    ],
    "wof:name":"Nongfengcun",
    "wof:placetype":"locality"
},
  "geometry": {"coordinates":[122.78749999999999,44.63809000000001],"type":"Point"}
}