{
  "type": "Feature",
  "properties": {
    "gn:admin1_code":"30",
    "gn:asciiname":"Lu'an",
    "gn:country_code":"CN",
    "gn:dem":18,
    "gn:feature_class":"P",
    "gn:feature_code":"PPL",
    "gn:name":"Lu\u2019an",
    "gn:population":0,
    "gn:timezone":"Asia/Shanghai",
    "iso:country":"CN",
    "name:zho_x_preferred":[
        "\u7984\u5cb8"
    ],
    "name:zho_x_variant":[
        "Lu\u2019an"
    ],
    "wof:name":"Lu'an",
    "wof:placetype":"locality"
},
  "geometry": {"coordinates":[112.30761,23.04721],"type":"Point"}
}