{
  "type": "Feature",
  "properties": {
    "gn:admin1_code":"22.0",
    "gn:asciiname":"Wanghuicun",
    "gn:country_code":"CN",
    "gn:dem":43,
    "gn:feature_class":"P",
    "gn:feature_code":"PPL",
    "gn:name":"Wanghuicun",
    "gn:population":0,
    "gn:timezone":"Asia/Shanghai",
    "iso:country":"CN",
    "name:zho_x_preferred":[
        "\u738b\u4f1a\u6751"
    ],
    "wof:name":"Wanghuicun",
    "wof:placetype":"locality"
},
  "geometry": {"coordinates":[116.91955,40.17512],"type":"Point"}
}