{
  "type": "Feature",
  "properties": {
    "gn:admin1_code":"15.0",
    "gn:asciiname":"Bojiwan",
    "gn:country_code":"CN",
    "gn:dem":1733,
    "gn:feature_class":"P",
    "gn:feature_code":"PPL",
    "gn:name":"Bojiwan",
    "gn:population":0,
    "gn:timezone":"Asia/Shanghai",
    "iso:country":"CN",
    "name:und_x_variant":[
        "\u7c38\u7b95\u6e7e"
    ],
    "wof:name":"Bojiwan",
    "wof:placetype":"locality"
},
  "geometry": {"coordinates":[106.66383,36.33046],"type":"Point"}
}