{
  "type": "Feature",
  "properties": {
    "gn:admin1_code":"5.0",
    "gn:asciiname":"Dongniucun",
    "gn:country_code":"CN",
    "gn:dem":215,
    "gn:feature_class":"P",
    "gn:feature_code":"PPL",
    "gn:name":"Dongniucun",
    "gn:population":0,
    "gn:timezone":"Asia/Shanghai",
    "iso:country":"CN",
    "name:zho_x_preferred":[
        "\u4e1c\u725b\u6751"
    ],
    "wof:name":"Dongniucun",
    "wof:placetype":"locality"
},
  "geometry": {"coordinates":[126.24381,44.82786],"type":"Point"}
}