{
  "type": "Feature",
  "properties": {
    "gn:admin1_code":"10.0",
    "gn:asciiname":"Cheyuanzhai",
    "gn:country_code":"CN",
    "gn:dem":81,
    "gn:feature_class":"P",
    "gn:feature_code":"PPL",
    "gn:name":"Cheyuanzhai",
    "gn:population":0,
    "gn:timezone":"Asia/Shanghai",
    "iso:country":"CN",
    "name:zho_x_preferred":[
        "\u8f66\u8f95\u5be8"
    ],
    "wof:name":"Cheyuanzhai",
    "wof:placetype":"locality"
},
  "geometry": {"coordinates":[118.56206,39.9851],"type":"Point"}
}