{
  "type": "Feature",
  "properties": {
    "gn:admin1_code":"14.0",
    "gn:asciiname":"Baburi",
    "gn:country_code":"CN",
    "gn:dem":4426,
    "gn:feature_class":"P",
    "gn:feature_code":"PPL",
    "gn:name":"Baburi",
    "gn:population":0,
    "gn:timezone":"Asia/Urumqi",
    "iso:country":"CN",
    "name:zho_x_preferred":[
        "\u516b\u5e03\u65e5"
    ],
    "wof:name":"Baburi",
    "wof:placetype":"locality"
},
  "geometry": {"coordinates":[94.2903,29.86153],"type":"Point"}
}