{
  "type": "Feature",
  "properties": {
    "gn:admin1_code":"13.0",
    "gn:asciiname":"Qarek",
    "gn:cc2":"CN",
    "gn:country_code":"CN",
    "gn:dem":1259,
    "gn:feature_class":"P",
    "gn:feature_code":"PPL",
    "gn:name":"Qarek",
    "gn:population":0,
    "gn:timezone":"Asia/Shanghai",
    "iso:country":"CN",
    "name:uig_x_preferred":[
        "Qar\u0259k"
    ],
    "name:uig_x_variant":[
        "Charek",
        "\u0686\u0627\u0631\u06d5\u0643",
        "\u0427\u0430\u0440\u04d9\u043a"
    ],
    "name:und_x_variant":[
        "Ch\u2019ia-je-k\u2019o",
        "Qarak",
        "Qarek"
    ],
    "wof:name":"Qarek",
    "wof:placetype":"locality"
},
  "geometry": {"coordinates":[76.99028,38.37222],"type":"Point"}
}