{
  "type": "Feature",
  "properties": {
    "gn:admin1_code":"03",
    "gn:asciiname":"Shishikou",
    "gn:country_code":"CN",
    "gn:dem":366,
    "gn:feature_class":"P",
    "gn:feature_code":"PPL",
    "gn:name":"Shishikou",
    "gn:population":0,
    "gn:timezone":"Asia/Shanghai",
    "iso:country":"CN",
    "name:und_x_variant":[
        "Shih-shih-k\u2019ou",
        "Shishikou"
    ],
    "name:zho_x_preferred":[
        "\u77f3\u72ee\u53e3"
    ],
    "wof:name":"Shishikou",
    "wof:placetype":"locality"
},
  "geometry": {"coordinates":[114.23399999999999,26.6751],"type":"Point"}
}