{
  "type": "Feature",
  "properties": {
    "gn:admin1_code":"14.0",
    "gn:asciiname":"Shaquancun",
    "gn:country_code":"CN",
    "gn:dem":4710,
    "gn:feature_class":"P",
    "gn:feature_code":"PPL",
    "gn:name":"Shaquancun",
    "gn:population":0,
    "gn:timezone":"Asia/Urumqi",
    "iso:country":"CN",
    "name:zho_x_preferred":[
        "\u838e\u6cc9\u6751"
    ],
    "wof:name":"Shaquancun",
    "wof:placetype":"locality"
},
  "geometry": {"coordinates":[89.79411,32.45212],"type":"Point"}
}