{
  "type": "Feature",
  "properties": {
    "gn:admin1_code":"29",
    "gn:asciiname":"Hengcun",
    "gn:country_code":"CN",
    "gn:dem":504,
    "gn:feature_class":"P",
    "gn:feature_code":"PPL",
    "gn:name":"Hengcun",
    "gn:population":0,
    "gn:timezone":"Asia/Shanghai",
    "iso:country":"CN",
    "name:zho_x_preferred":[
        "\u6052\u6751"
    ],
    "wof:name":"Hengcun",
    "wof:placetype":"locality"
},
  "geometry": {"coordinates":[106.04900000000001,23.5613],"type":"Point"}
}