{
  "type": "Feature",
  "properties": {
    "gn:admin1_code":"4.0",
    "gn:asciiname":"Lingwang",
    "gn:country_code":"CN",
    "gn:dem":14,
    "gn:feature_class":"P",
    "gn:feature_code":"PPL",
    "gn:name":"Lingwang",
    "gn:population":0,
    "gn:timezone":"Asia/Shanghai",
    "iso:country":"CN",
    "name:zho_x_preferred":[
        "\u51cc\u6c6a"
    ],
    "wof:name":"Lingwang",
    "wof:placetype":"locality"
},
  "geometry": {"coordinates":[118.25700000000001,33.6586],"type":"Point"}
}