{
  "type": "Feature",
  "properties": {
    "gn:admin1_code":"31.0",
    "gn:asciiname":"Fujiyuan",
    "gn:country_code":"CN",
    "gn:dem":55,
    "gn:feature_class":"P",
    "gn:feature_code":"PPL",
    "gn:name":"Fujiyuan",
    "gn:population":0,
    "gn:timezone":"Asia/Shanghai",
    "iso:country":"CN",
    "name:zho_x_preferred":[
        "\u798f\u57fa\u56ed"
    ],
    "wof:name":"Fujiyuan",
    "wof:placetype":"locality"
},
  "geometry": {"coordinates":[110.63916999999999,19.58773],"type":"Point"}
}