{
  "type": "Feature",
  "properties": {
    "gn:admin1_code":"25",
    "gn:asciiname":"Malangtou",
    "gn:country_code":"CN",
    "gn:dem":23,
    "gn:feature_class":"P",
    "gn:feature_code":"PPL",
    "gn:name":"Malangtou",
    "gn:population":0,
    "gn:timezone":"Asia/Shanghai",
    "iso:country":"CN",
    "name:zho_x_preferred":[
        "\u9a6c\u6d6a\u5934"
    ],
    "wof:name":"Malangtou",
    "wof:placetype":"locality"
},
  "geometry": {"coordinates":[117.075,37.0109],"type":"Point"}
}