{
  "type": "Feature",
  "properties": {
    "gn:admin1_code":"32.0",
    "gn:asciiname":"Dayandong",
    "gn:country_code":"CN",
    "gn:dem":1889,
    "gn:feature_class":"P",
    "gn:feature_code":"PPL",
    "gn:name":"Dayandong",
    "gn:population":0,
    "gn:timezone":"Asia/Shanghai",
    "iso:country":"CN",
    "name:zho_x_preferred":[
        "\u5927\u5ca9\u6d1e"
    ],
    "wof:name":"Dayandong",
    "wof:placetype":"locality"
},
  "geometry": {"coordinates":[103.31837,28.35823],"type":"Point"}
}