{
  "type": "Feature",
  "properties": {
    "gn:admin1_code":"25",
    "gn:asciiname":"Xietun",
    "gn:country_code":"CN",
    "gn:dem":21,
    "gn:feature_class":"P",
    "gn:feature_code":"PPL",
    "gn:name":"Xietun",
    "gn:population":0,
    "gn:timezone":"Asia/Shanghai",
    "iso:country":"CN",
    "name:zho_x_preferred":[
        "\u8c22\u5c6f"
    ],
    "wof:name":"Xietun",
    "wof:placetype":"locality"
},
  "geometry": {"coordinates":[116.657,37.4163],"type":"Point"}
}