{
  "type": "Feature",
  "properties": {
    "gn:admin1_code":"26.0",
    "gn:asciiname":"Miaowancun",
    "gn:country_code":"CN",
    "gn:dem":1237,
    "gn:feature_class":"P",
    "gn:feature_code":"PPL",
    "gn:name":"Miaowancun",
    "gn:population":0,
    "gn:timezone":"Asia/Shanghai",
    "iso:country":"CN",
    "name:zho_x_preferred":[
        "\u5e99\u6e7e\u6751"
    ],
    "wof:name":"Miaowancun",
    "wof:placetype":"locality"
},
  "geometry": {"coordinates":[109.34375,36.92588],"type":"Point"}
}