{
  "type": "Feature",
  "properties": {
    "gn:admin1_code":"20.0",
    "gn:asciiname":"Hesege Baole Duru",
    "gn:country_code":"CN",
    "gn:dem":567,
    "gn:feature_class":"P",
    "gn:feature_code":"PPL",
    "gn:name":"Hesege Baole Duru",
    "gn:population":0,
    "gn:timezone":"Asia/Shanghai",
    "iso:country":"CN",
    "name:zho_x_preferred":[
        "\u548c\u8272\u683c\u5305\u52d2\u90fd\u5982"
    ],
    "wof:name":"Hesege Baole Duru",
    "wof:placetype":"locality"
},
  "geometry": {"coordinates":[116.69777000000001,48.55934],"type":"Point"}
}