{
  "type": "Feature",
  "properties": {
    "gn:admin1_code":"30",
    "gn:asciiname":"Oujia",
    "gn:country_code":"CN",
    "gn:dem":9,
    "gn:feature_class":"P",
    "gn:feature_code":"PPL",
    "gn:name":"Oujia",
    "gn:population":0,
    "gn:timezone":"Asia/Urumqi",
    "iso:country":"CN",
    "name:zho_x_preferred":[
        "\u6b27\u5bb6"
    ],
    "wof:name":"Oujia",
    "wof:placetype":"locality"
},
  "geometry": {"coordinates":[110.02576999999999,21.49539],"type":"Point"}
}