{
  "type": "Feature",
  "properties": {
    "gn:admin1_code":"26.0",
    "gn:asciiname":"Taohuacun",
    "gn:country_code":"CN",
    "gn:dem":799,
    "gn:feature_class":"P",
    "gn:feature_code":"PPL",
    "gn:name":"Taohuacun",
    "gn:population":0,
    "gn:timezone":"Asia/Shanghai",
    "iso:country":"CN",
    "name:zho_x_preferred":[
        "\u6843\u82b1\u6751"
    ],
    "wof:name":"Taohuacun",
    "wof:placetype":"locality"
},
  "geometry": {"coordinates":[110.44508999999999,33.64906],"type":"Point"}
}