{
  "type": "Feature",
  "properties": {
    "gn:admin1_code":"22.0",
    "gn:asciiname":"Huangguayuancun",
    "gn:country_code":"CN",
    "gn:dem":58,
    "gn:feature_class":"P",
    "gn:feature_code":"PPL",
    "gn:name":"Huangguayuancun",
    "gn:population":0,
    "gn:timezone":"Asia/Shanghai",
    "iso:country":"CN",
    "name:zho_x_preferred":[
        "\u9ec4\u74dc\u56ed\u6751"
    ],
    "wof:name":"Huangguayuancun",
    "wof:placetype":"locality"
},
  "geometry": {"coordinates":[116.20471000000001,40.20134],"type":"Point"}
}