{
  "type": "Feature",
  "properties": {
    "gn:admin1_code":"32.0",
    "gn:asciiname":"Daofosi",
    "gn:country_code":"CN",
    "gn:dem":408,
    "gn:feature_class":"P",
    "gn:feature_code":"PPL",
    "gn:name":"Daofosi",
    "gn:population":0,
    "gn:timezone":"Asia/Shanghai",
    "iso:country":"CN",
    "name:zho_x_preferred":[
        "\u9053\u4f5b\u5bfa"
    ],
    "wof:name":"Daofosi",
    "wof:placetype":"locality"
},
  "geometry": {"coordinates":[104.33123999999999,30.07214],"type":"Point"}
}