{
  "type": "Feature",
  "properties": {
    "gn:admin1_code":"4.0",
    "gn:asciiname":"Tao'an",
    "gn:country_code":"CN",
    "gn:dem":212,
    "gn:feature_class":"P",
    "gn:feature_code":"PPL",
    "gn:name":"Tao\u2019an",
    "gn:population":0,
    "gn:timezone":"Asia/Shanghai",
    "iso:country":"CN",
    "name:zho_x_preferred":[
        "Tao\u2019an"
    ],
    "name:zho_x_variant":[
        "\u9676\u5eb5"
    ],
    "wof:name":"Tao'an",
    "wof:placetype":"locality"
},
  "geometry": {"coordinates":[119.44708,34.70323],"type":"Point"}
}