{
  "type": "Feature",
  "properties": {
    "gn:admin1_code":"9.0",
    "gn:asciiname":"Chenzhuangcun",
    "gn:country_code":"CN",
    "gn:dem":78,
    "gn:feature_class":"P",
    "gn:feature_code":"PPL",
    "gn:name":"Chenzhuangcun",
    "gn:population":0,
    "gn:timezone":"Asia/Shanghai",
    "iso:country":"CN",
    "name:und_x_variant":[
        "\u9648\u5e84\u6751"
    ],
    "name:zho_x_preferred":[
        "\u9648\u5e84\u6751"
    ],
    "wof:name":"Chenzhuangcun",
    "wof:placetype":"locality"
},
  "geometry": {"coordinates":[113.78909,33.08605],"type":"Point"}
}