{
  "type": "Feature",
  "properties": {
    "gn:admin1_code":"32.0",
    "gn:asciiname":"Maoyazi",
    "gn:country_code":"CN",
    "gn:dem":709,
    "gn:feature_class":"P",
    "gn:feature_code":"PPL",
    "gn:name":"Maoyazi",
    "gn:population":0,
    "gn:timezone":"Asia/Shanghai",
    "iso:country":"CN",
    "name:zho_x_preferred":[
        "\u8305\u57ad\u5b50"
    ],
    "wof:name":"Maoyazi",
    "wof:placetype":"locality"
},
  "geometry": {"coordinates":[105.462,32.7558],"type":"Point"}
}