{
  "type": "Feature",
  "properties": {
    "gn:admin1_code":"25.0",
    "gn:asciiname":"Datun",
    "gn:cc2":"CN",
    "gn:country_code":"CN",
    "gn:dem":82,
    "gn:feature_class":"P",
    "gn:feature_code":"PPL",
    "gn:name":"Datun",
    "gn:population":0,
    "gn:timezone":"Asia/Shanghai",
    "iso:country":"CN",
    "name:zho_x_preferred":[
        "\u5927\u5c6f"
    ],
    "wof:name":"Datun",
    "wof:placetype":"locality"
},
  "geometry": {"coordinates":[119.63461,36.03654],"type":"Point"}
}