{
  "type": "Feature",
  "properties": {
    "gn:admin1_code":"29.0",
    "gn:asciiname":"Mudile Xincun",
    "gn:country_code":"CN",
    "gn:dem":1882,
    "gn:feature_class":"P",
    "gn:feature_code":"PPL",
    "gn:name":"Mudile Xincun",
    "gn:population":0,
    "gn:timezone":"Asia/Shanghai",
    "iso:country":"CN",
    "name:zho_x_preferred":[
        "\u6bcd\u5e95\u4e50\u65b0\u6751"
    ],
    "wof:name":"Mudile Xincun",
    "wof:placetype":"locality"
},
  "geometry": {"coordinates":[100.285,24.8257],"type":"Point"}
}