{
  "type": "Feature",
  "properties": {
    "gn:admin1_code":"1.0",
    "gn:asciiname":"Jiaohucun",
    "gn:country_code":"CN",
    "gn:dem":70,
    "gn:feature_class":"P",
    "gn:feature_code":"PPL",
    "gn:name":"Jiaohucun",
    "gn:population":0,
    "gn:timezone":"Asia/Shanghai",
    "iso:country":"CN",
    "name:zho_x_preferred":[
        "\u7126\u6e56\u6751"
    ],
    "wof:name":"Jiaohucun",
    "wof:placetype":"locality"
},
  "geometry": {"coordinates":[117.00876,31.9853],"type":"Point"}
}