{
  "type": "Feature",
  "properties": {
    "gn:admin1_code":"7",
    "gn:asciiname":"Maobu Famuchang",
    "gn:country_code":"CN",
    "gn:dem":471,
    "gn:feature_class":"P",
    "gn:feature_code":"PPL",
    "gn:name":"Maobu Famuchang",
    "gn:population":0,
    "gn:timezone":"Asia/Shanghai",
    "iso:country":"CN",
    "wof:name":"Maobu Famuchang",
    "wof:placetype":"locality"
},
  "geometry": {"coordinates":[116.03,25.39417000000001],"type":"Point"}
}