{
  "type": "Feature",
  "properties": {
    "gn:admin1_code":"14.0",
    "gn:asciiname":"Luomei",
    "gn:country_code":"CN",
    "gn:dem":4034,
    "gn:feature_class":"P",
    "gn:feature_code":"PPL",
    "gn:name":"Luomei",
    "gn:population":0,
    "gn:timezone":"Asia/Urumqi",
    "iso:country":"CN",
    "name:zho_x_preferred":[
        "\u6d1b\u7f8e"
    ],
    "wof:name":"Luomei",
    "wof:placetype":"locality"
},
  "geometry": {"coordinates":[96.18103000000001,29.995],"type":"Point"}
}