{
  "type": "Feature",
  "properties": {
    "gn:admin1_code":"11.0",
    "gn:asciiname":"Zhoubatang",
    "gn:country_code":"CN",
    "gn:dem":102,
    "gn:feature_class":"P",
    "gn:feature_code":"PPL",
    "gn:name":"Zhoubatang",
    "gn:population":0,
    "gn:timezone":"Asia/Shanghai",
    "iso:country":"CN",
    "name:zho_x_preferred":[
        "\u5468\u5df4\u5858"
    ],
    "wof:name":"Zhoubatang",
    "wof:placetype":"locality"
},
  "geometry": {"coordinates":[113.23962,28.98992],"type":"Point"}
}