{
  "type": "Feature",
  "properties": {
    "gn:admin1_code":"26.0",
    "gn:asciiname":"Zhangjia Shancun",
    "gn:country_code":"CN",
    "gn:dem":1237,
    "gn:feature_class":"P",
    "gn:feature_code":"PPL",
    "gn:name":"Zhangjia Shancun",
    "gn:population":0,
    "gn:timezone":"Asia/Shanghai",
    "iso:country":"CN",
    "name:zho_x_preferred":[
        "\u5f20\u5bb6\u5c71\u6751"
    ],
    "wof:name":"Zhangjia Shancun",
    "wof:placetype":"locality"
},
  "geometry": {"coordinates":[110.116,38.1237],"type":"Point"}
}