{
  "type": "Feature",
  "properties": {
    "gn:admin1_code":"18.0",
    "gn:asciiname":"Dayoushi",
    "gn:country_code":"CN",
    "gn:dem":848,
    "gn:feature_class":"P",
    "gn:feature_code":"PPL",
    "gn:name":"Dayoushi",
    "gn:population":0,
    "gn:timezone":"Asia/Shanghai",
    "iso:country":"CN",
    "name:zho_x_preferred":[
        "\u6253\u6cb9\u8bd7"
    ],
    "wof:name":"Dayoushi",
    "wof:placetype":"locality"
},
  "geometry": {"coordinates":[108.706,28.3931],"type":"Point"}
}