{
  "type": "Feature",
  "properties": {
    "gn:admin1_code":"12.0",
    "gn:asciiname":"Yangguidian",
    "gn:country_code":"CN",
    "gn:dem":144,
    "gn:feature_class":"P",
    "gn:feature_code":"PPL",
    "gn:name":"Yangguidian",
    "gn:population":0,
    "gn:timezone":"Asia/Shanghai",
    "iso:country":"CN",
    "name:zho_x_preferred":[
        "\u6768\u8d35\u5e97"
    ],
    "wof:name":"Yangguidian",
    "wof:placetype":"locality"
},
  "geometry": {"coordinates":[110.98354999999999,30.80246],"type":"Point"}
}