{
  "type": "Feature",
  "properties": {
    "gn:admin1_code":"24",
    "gn:asciiname":"Qili",
    "gn:country_code":"CN",
    "gn:dem":910,
    "gn:feature_class":"P",
    "gn:feature_code":"PPL",
    "gn:name":"Qili",
    "gn:population":0,
    "gn:timezone":"Asia/Shanghai",
    "iso:country":"CN",
    "name:zho_x_preferred":[
        "\u5f03\u91cc"
    ],
    "wof:name":"Qili",
    "wof:placetype":"locality"
},
  "geometry": {"coordinates":[111.76939,35.83584000000001],"type":"Point"}
}