{
  "type": "Feature",
  "properties": {
    "gn:admin1_code":"4.0",
    "gn:asciiname":"Liuyunlingcun",
    "gn:country_code":"CN",
    "gn:dem":36,
    "gn:feature_class":"P",
    "gn:feature_code":"PPL",
    "gn:name":"Liuyunlingcun",
    "gn:population":0,
    "gn:timezone":"Asia/Shanghai",
    "iso:country":"CN",
    "name:zho_x_preferred":[
        "\u7559\u4e91\u5cad\u6751"
    ],
    "wof:name":"Liuyunlingcun",
    "wof:placetype":"locality"
},
  "geometry": {"coordinates":[119.41193,34.7041],"type":"Point"}
}