{
  "type": "Feature",
  "properties": {
    "gn:admin1_code":"18",
    "gn:asciiname":"Yisukuai",
    "gn:country_code":"CN",
    "gn:dem":1581,
    "gn:feature_class":"P",
    "gn:feature_code":"PPL",
    "gn:name":"Yisukuai",
    "gn:population":0,
    "gn:timezone":"Asia/Shanghai",
    "iso:country":"CN",
    "name:zho_x_preferred":[
        "\u4ee5\u82cf\u5757"
    ],
    "wof:name":"Yisukuai",
    "wof:placetype":"locality"
},
  "geometry": {"coordinates":[105.14100000000001,27.0531],"type":"Point"}
}