{
  "type": "Feature",
  "properties": {
    "gn:admin1_code":"20.0",
    "gn:asciiname":"Zhangkedi",
    "gn:country_code":"CN",
    "gn:dem":1487,
    "gn:feature_class":"P",
    "gn:feature_code":"PPL",
    "gn:name":"Zhangkedi",
    "gn:population":0,
    "gn:timezone":"Asia/Shanghai",
    "iso:country":"CN",
    "name:und_x_variant":[
        "\u5f20\u79d1\u5730"
    ],
    "wof:name":"Zhangkedi",
    "wof:placetype":"locality"
},
  "geometry": {"coordinates":[113.15989999999999,41.97391],"type":"Point"}
}