{
  "type": "Feature",
  "properties": {
    "gn:admin1_code":"12.0",
    "gn:asciiname":"Tianshansi",
    "gn:country_code":"CN",
    "gn:dem":573,
    "gn:feature_class":"P",
    "gn:feature_code":"PPL",
    "gn:name":"Tianshansi",
    "gn:population":0,
    "gn:timezone":"Asia/Shanghai",
    "iso:country":"CN",
    "name:zho_x_preferred":[
        "Tianshansi"
    ],
    "name:zho_x_variant":[
        "\u5929\u5c71\u5bfa"
    ],
    "wof:name":"Tianshansi",
    "wof:placetype":"locality"
},
  "geometry": {"coordinates":[111.23783,30.24692000000001],"type":"Point"}
}