{
  "type": "Feature",
  "properties": {
    "gn:admin1_code":"08",
    "gn:asciiname":"Baoquancun",
    "gn:country_code":"CN",
    "gn:dem":135,
    "gn:feature_class":"P",
    "gn:feature_code":"PPL",
    "gn:name":"Baoquancun",
    "gn:population":0,
    "gn:timezone":"Asia/Shanghai",
    "iso:country":"CN",
    "name:und_x_variant":[
        "Baoquan",
        "Baoquancun"
    ],
    "name:zho_x_preferred":[
        "\u5b9d\u6cc9"
    ],
    "name:zho_x_variant":[
        "\u5b9d\u6cc9\u6751"
    ],
    "wof:name":"Baoquancun",
    "wof:placetype":"locality"
},
  "geometry": {"coordinates":[129.52177,46.92344],"type":"Point"}
}