{
  "type": "Feature",
  "properties": {
    "gn:admin1_code":"15.0",
    "gn:asciiname":"Jiage",
    "gn:country_code":"CN",
    "gn:dem":3141,
    "gn:feature_class":"P",
    "gn:feature_code":"PPL",
    "gn:name":"Jiage",
    "gn:population":0,
    "gn:timezone":"Asia/Shanghai",
    "iso:country":"CN",
    "name:zho_x_preferred":[
        "\u52a0\u683c"
    ],
    "wof:name":"Jiage",
    "wof:placetype":"locality"
},
  "geometry": {"coordinates":[102.508,34.5858],"type":"Point"}
}