{
  "type": "Feature",
  "properties": {
    "gn:admin1_code":"29.0",
    "gn:asciiname":"Shangma Jiawo",
    "gn:country_code":"CN",
    "gn:dem":2158,
    "gn:feature_class":"P",
    "gn:feature_code":"PPL",
    "gn:name":"Shangma Jiawo",
    "gn:population":0,
    "gn:timezone":"Asia/Shanghai",
    "iso:country":"CN",
    "name:zho_x_preferred":[
        "\u4e0a\u9a6c\u5bb6\u7a9d"
    ],
    "wof:name":"Shangma Jiawo",
    "wof:placetype":"locality"
},
  "geometry": {"coordinates":[101.105,26.7614],"type":"Point"}
}