{
  "type": "Feature",
  "properties": {
    "gn:admin1_code":"29.0",
    "gn:asciiname":"Duimenshan",
    "gn:country_code":"CN",
    "gn:dem":1675,
    "gn:feature_class":"P",
    "gn:feature_code":"PPL",
    "gn:name":"Duimenshan",
    "gn:population":0,
    "gn:timezone":"Asia/Shanghai",
    "iso:country":"CN",
    "name:zho_x_preferred":[
        "\u5bf9\u95e8\u5c71"
    ],
    "wof:name":"Duimenshan",
    "wof:placetype":"locality"
},
  "geometry": {"coordinates":[99.9174,24.4193],"type":"Point"}
}