{
  "type": "Feature",
  "properties": {
    "gn:admin1_code":"26.0",
    "gn:asciiname":"Shinangou",
    "gn:country_code":"CN",
    "gn:dem":1162,
    "gn:feature_class":"P",
    "gn:feature_code":"PPL",
    "gn:name":"Shinangou",
    "gn:population":0,
    "gn:timezone":"Asia/Shanghai",
    "iso:country":"CN",
    "name:zho_x_preferred":[
        "\u77f3\u5357\u6c9f"
    ],
    "wof:name":"Shinangou",
    "wof:placetype":"locality"
},
  "geometry": {"coordinates":[108.67641,33.6693],"type":"Point"}
}