{
  "type": "Feature",
  "properties": {
    "gn:admin1_code":"8.0",
    "gn:asciiname":"Xiahua Liudui",
    "gn:country_code":"CN",
    "gn:dem":235,
    "gn:feature_class":"P",
    "gn:feature_code":"PPLF",
    "gn:name":"Xiahua Liudui",
    "gn:population":0,
    "gn:timezone":"Asia/Shanghai",
    "iso:country":"CN",
    "name:zho_x_preferred":[
        "\u4e0b\u6866\u516d\u961f"
    ],
    "wof:name":"Xiahua Liudui",
    "wof:placetype":"locality"
},
  "geometry": {"coordinates":[130.79061999999999,46.30299],"type":"Point"}
}