{
  "type": "Feature",
  "properties": {
    "gn:admin1_code":"16.0",
    "gn:asciiname":"Yunhe",
    "gn:country_code":"CN",
    "gn:dem":156,
    "gn:feature_class":"P",
    "gn:feature_code":"PPL",
    "gn:name":"Yunhe",
    "gn:population":0,
    "gn:timezone":"Asia/Shanghai",
    "iso:country":"CN",
    "name:ceb_x_preferred":[
        "Yunhe"
    ],
    "name:deu_x_preferred":[
        "Yunhe"
    ],
    "name:fra_x_preferred":[
        "Yunhe"
    ],
    "name:nor_x_preferred":[
        "Yunhe"
    ],
    "name:swe_x_preferred":[
        "Yunhe"
    ],
    "name:zho_x_preferred":[
        "\u4e91\u4f55"
    ],
    "wof:name":"Yunhe",
    "wof:placetype":"locality"
},
  "geometry": {"coordinates":[108.56699999999999,23.5265],"type":"Point"}
}