{
  "type": "Feature",
  "properties": {
    "gn:admin1_code":"2.0",
    "gn:asciiname":"Gengtang",
    "gn:country_code":"CN",
    "gn:dem":437,
    "gn:feature_class":"P",
    "gn:feature_code":"PPL",
    "gn:name":"Gengtang",
    "gn:population":0,
    "gn:timezone":"Asia/Shanghai",
    "iso:country":"CN",
    "name:zho_x_preferred":[
        "\u5e9a\u5802"
    ],
    "wof:name":"Gengtang",
    "wof:placetype":"locality"
},
  "geometry": {"coordinates":[120.38589,27.69175],"type":"Point"}
}