{
  "type": "Feature",
  "properties": {
    "gn:admin1_code":"16.0",
    "gn:asciiname":"Shanghaolong",
    "gn:country_code":"CN",
    "gn:dem":785,
    "gn:feature_class":"P",
    "gn:feature_code":"PPL",
    "gn:name":"Shanghaolong",
    "gn:population":0,
    "gn:timezone":"Asia/Shanghai",
    "iso:country":"CN",
    "name:zho_x_preferred":[
        "\u4e0a\u597d\u9f99"
    ],
    "wof:name":"Shanghaolong",
    "wof:placetype":"locality"
},
  "geometry": {"coordinates":[107.131,24.4423],"type":"Point"}
}