{
  "type": "Feature",
  "properties": {
    "gn:admin1_code":"25.0",
    "gn:asciiname":"Yuanxiacun",
    "gn:country_code":"CN",
    "gn:dem":25,
    "gn:feature_class":"P",
    "gn:feature_code":"PPL",
    "gn:name":"Yuanxiacun",
    "gn:population":0,
    "gn:timezone":"Asia/Shanghai",
    "iso:country":"CN",
    "name:zho_x_preferred":[
        "\u9662\u4e0b\u6751"
    ],
    "wof:name":"Yuanxiacun",
    "wof:placetype":"locality"
},
  "geometry": {"coordinates":[121.30646000000002,36.82283],"type":"Point"}
}