{
  "type": "Feature",
  "properties": {
    "gn:admin1_code":"24.0",
    "gn:asciiname":"Sizi",
    "gn:country_code":"CN",
    "gn:dem":1505,
    "gn:feature_class":"P",
    "gn:feature_code":"PPL",
    "gn:name":"Sizi",
    "gn:population":0,
    "gn:timezone":"Asia/Shanghai",
    "iso:country":"CN",
    "name:zho_x_preferred":[
        "\u5bfa\u5b50"
    ],
    "wof:name":"Sizi",
    "wof:placetype":"locality"
},
  "geometry": {"coordinates":[113.55866,39.18646],"type":"Point"}
}