{
  "type": "Feature",
  "properties": {
    "gn:admin1_code":"2.0",
    "gn:asciiname":"Huangcun",
    "gn:country_code":"CN",
    "gn:dem":394,
    "gn:feature_class":"P",
    "gn:feature_code":"PPL",
    "gn:name":"Huangcun",
    "gn:population":0,
    "gn:timezone":"Asia/Shanghai",
    "iso:country":"CN",
    "name:und_x_variant":[
        "Huang-k\u2019eng-ts\u2019un"
    ],
    "name:zho_x_preferred":[
        "\u9ec4\u6751"
    ],
    "wof:name":"Huangcun",
    "wof:placetype":"locality"
},
  "geometry": {"coordinates":[120.90665,28.12069],"type":"Point"}
}