{
  "type": "Feature",
  "properties": {
    "gn:admin1_code":"32.0",
    "gn:asciiname":"Jianleqiao",
    "gn:country_code":"CN",
    "gn:dem":388,
    "gn:feature_class":"P",
    "gn:feature_code":"PPL",
    "gn:name":"Jianleqiao",
    "gn:population":0,
    "gn:timezone":"Asia/Shanghai",
    "iso:country":"CN",
    "name:zho_x_preferred":[
        "\u7b80\u4e50\u6865"
    ],
    "wof:name":"Jianleqiao",
    "wof:placetype":"locality"
},
  "geometry": {"coordinates":[104.84099999999999,30.3053],"type":"Point"}
}