{
  "type": "Feature",
  "properties": {
    "gn:admin1_code":"28.0",
    "gn:asciiname":"Yuexiulu",
    "gn:country_code":"CN",
    "gn:dem":4,
    "gn:feature_class":"P",
    "gn:feature_code":"PPLA4",
    "gn:name":"Yuexiulu",
    "gn:population":0,
    "gn:timezone":"Asia/Shanghai",
    "iso:country":"CN",
    "name:und_x_variant":[
        "Yuexiulu Jiedao"
    ],
    "name:zho_x_preferred":[
        "\u8d8a\u79c0\u8def"
    ],
    "name:zho_x_variant":[
        "\u8d8a\u79c0\u8def\u8857\u9053"
    ],
    "wof:name":"Yuexiulu",
    "wof:placetype":"locality"
},
  "geometry": {"coordinates":[117.22331,39.09116],"type":"Point"}
}