{
  "type": "Feature",
  "properties": {
    "gn:admin1_code":"14.0",
    "gn:asciiname":"Zhaze",
    "gn:country_code":"CN",
    "gn:dem":4295,
    "gn:feature_class":"P",
    "gn:feature_code":"PPL",
    "gn:name":"Zhaze",
    "gn:population":0,
    "gn:timezone":"Asia/Urumqi",
    "iso:country":"CN",
    "name:zho_x_preferred":[
        "\u624e\u5219"
    ],
    "wof:name":"Zhaze",
    "wof:placetype":"locality"
},
  "geometry": {"coordinates":[92.25714000000001,29.03691],"type":"Point"}
}