{
  "type": "Feature",
  "properties": {
    "gn:admin1_code":"26.0",
    "gn:asciiname":"Yangsimiaocun",
    "gn:country_code":"CN",
    "gn:dem":1312,
    "gn:feature_class":"P",
    "gn:feature_code":"PPL",
    "gn:name":"Yangsimiaocun",
    "gn:population":0,
    "gn:timezone":"Asia/Shanghai",
    "iso:country":"CN",
    "name:zho_x_preferred":[
        "\u6768\u56db\u5e99\u6751"
    ],
    "wof:name":"Yangsimiaocun",
    "wof:placetype":"locality"
},
  "geometry": {"coordinates":[109.10278,33.8406],"type":"Point"}
}