{
  "type": "Feature",
  "properties": {
    "gn:admin1_code":"32.0",
    "gn:asciiname":"Dahua",
    "gn:country_code":"CN",
    "gn:dem":1152,
    "gn:feature_class":"P",
    "gn:feature_code":"PPL",
    "gn:name":"Dahua",
    "gn:population":0,
    "gn:timezone":"Asia/Shanghai",
    "iso:country":"CN",
    "name:zho_x_preferred":[
        "\u5927\u82b1"
    ],
    "wof:name":"Dahua",
    "wof:placetype":"locality"
},
  "geometry": {"coordinates":[105.627,32.564],"type":"Point"}
}