{
  "type": "Feature",
  "properties": {
    "gn:admin1_code":"2.0",
    "gn:asciiname":"Yangjiashan",
    "gn:country_code":"CN",
    "gn:dem":4,
    "gn:feature_class":"P",
    "gn:feature_code":"PPL",
    "gn:name":"Yangjiashan",
    "gn:population":0,
    "gn:timezone":"Asia/Shanghai",
    "iso:country":"CN",
    "name:und_x_variant":[
        "\u6768\u5bb6\u5c71"
    ],
    "name:zho_x_preferred":[
        "Yangjiashan"
    ],
    "wof:name":"Yangjiashan",
    "wof:placetype":"locality"
},
  "geometry": {"coordinates":[119.98408000000001,30.97424],"type":"Point"}
}