{
  "type": "Feature",
  "properties": {
    "gn:admin1_code":"30.0",
    "gn:asciiname":"Ousuyuan",
    "gn:country_code":"CN",
    "gn:dem":17,
    "gn:feature_class":"P",
    "gn:feature_code":"PPL",
    "gn:name":"Ousuyuan",
    "gn:population":0,
    "gn:timezone":"Asia/Shanghai",
    "iso:country":"CN",
    "name:zho_x_preferred":[
        "\u6b27\u82cf\u56ed"
    ],
    "wof:name":"Ousuyuan",
    "wof:placetype":"locality"
},
  "geometry": {"coordinates":[114.51770999999999,22.53189],"type":"Point"}
}