{
  "type": "Feature",
  "properties": {
    "gn:admin1_code":"4.0",
    "gn:asciiname":"Zhima",
    "gn:country_code":"CN",
    "gn:dem":10,
    "gn:feature_class":"P",
    "gn:feature_code":"PPL",
    "gn:name":"Zhima",
    "gn:population":0,
    "gn:timezone":"Asia/Shanghai",
    "iso:country":"CN",
    "name:zho_x_preferred":[
        "\u829d\u9ebb"
    ],
    "wof:name":"Zhima",
    "wof:placetype":"locality"
},
  "geometry": {"coordinates":[118.81100000000001,34.4575],"type":"Point"}
}