{
  "type": "Feature",
  "properties": {
    "gn:admin1_code":"32.0",
    "gn:asciiname":"Tianbaozhai",
    "gn:country_code":"CN",
    "gn:dem":323,
    "gn:feature_class":"P",
    "gn:feature_code":"PPL",
    "gn:name":"Tianbaozhai",
    "gn:population":0,
    "gn:timezone":"Asia/Shanghai",
    "iso:country":"CN",
    "name:zho_x_preferred":[
        "\u5929\u4fdd\u5be8"
    ],
    "wof:name":"Tianbaozhai",
    "wof:placetype":"locality"
},
  "geometry": {"coordinates":[105.18149,29.08349],"type":"Point"}
}