{
  "type": "Feature",
  "properties": {
    "gn:admin1_code":"7",
    "gn:asciiname":"Diyang",
    "gn:country_code":"CN",
    "gn:dem":692,
    "gn:feature_class":"P",
    "gn:feature_code":"PPL",
    "gn:name":"Diyang",
    "gn:population":0,
    "gn:timezone":"Asia/Shanghai",
    "iso:country":"CN",
    "name:und_x_variant":[
        "\u5730\u6d0b"
    ],
    "wof:name":"Diyang",
    "wof:placetype":"locality"
},
  "geometry": {"coordinates":[118.83333,27.30694],"type":"Point"}
}