{
  "type": "Feature",
  "properties": {
    "gn:admin1_code":"26.0",
    "gn:asciiname":"Yanggoulicun",
    "gn:country_code":"CN",
    "gn:dem":999,
    "gn:feature_class":"P",
    "gn:feature_code":"PPL",
    "gn:name":"Yanggoulicun",
    "gn:population":0,
    "gn:timezone":"Asia/Shanghai",
    "iso:country":"CN",
    "name:zho_x_preferred":[
        "\u9633\u6c9f\u91cc\u6751"
    ],
    "wof:name":"Yanggoulicun",
    "wof:placetype":"locality"
},
  "geometry": {"coordinates":[110.55432,37.29532],"type":"Point"}
}