{
  "type": "Feature",
  "properties": {
    "gn:admin1_code":"1.0",
    "gn:asciiname":"Pifangcun",
    "gn:country_code":"CN",
    "gn:dem":248,
    "gn:feature_class":"P",
    "gn:feature_code":"PPL",
    "gn:name":"Pifangcun",
    "gn:population":0,
    "gn:timezone":"Asia/Shanghai",
    "iso:country":"CN",
    "name:zho_x_preferred":[
        "\u76ae\u574a\u6751"
    ],
    "wof:name":"Pifangcun",
    "wof:placetype":"locality"
},
  "geometry": {"coordinates":[115.71248,31.66416],"type":"Point"}
}