{
  "type": "Feature",
  "properties": {
    "gn:admin1_code":"10.0",
    "gn:asciiname":"Bujiaying",
    "gn:country_code":"CN",
    "gn:dem":2,
    "gn:feature_class":"P",
    "gn:feature_code":"PPL",
    "gn:name":"Bujiaying",
    "gn:population":0,
    "gn:timezone":"Asia/Shanghai",
    "iso:country":"CN",
    "name:zho_x_preferred":[
        "\u535c\u5bb6\u8425"
    ],
    "wof:name":"Bujiaying",
    "wof:placetype":"locality"
},
  "geometry": {"coordinates":[119.28539000000001,39.73145],"type":"Point"}
}