{
  "type": "Feature",
  "properties": {
    "gn:admin1_code":"14",
    "gn:asciiname":"Sanba Ercun",
    "gn:country_code":"CN",
    "gn:dem":4539,
    "gn:feature_class":"P",
    "gn:feature_code":"PPL",
    "gn:name":"Sanba Ercun",
    "gn:population":0,
    "gn:timezone":"Asia/Urumqi",
    "iso:country":"CN",
    "name:zho_x_preferred":[
        "\u4e09\u516b\u4e8c\u6751"
    ],
    "wof:name":"Sanba Ercun",
    "wof:placetype":"locality"
},
  "geometry": {"coordinates":[88.9483,32.0103],"type":"Point"}
}