{
  "type": "Feature",
  "properties": {
    "gn:admin1_code":"12.0",
    "gn:asciiname":"Cehujie",
    "gn:country_code":"CN",
    "gn:dem":26,
    "gn:feature_class":"P",
    "gn:feature_code":"PPL",
    "gn:name":"Cehujie",
    "gn:population":0,
    "gn:timezone":"Asia/Shanghai",
    "iso:country":"CN",
    "name:zho_x_preferred":[
        "Cehujie"
    ],
    "name:zho_x_variant":[
        "\u7b56\u6e56\u8857"
    ],
    "wof:name":"Cehujie",
    "wof:placetype":"locality"
},
  "geometry": {"coordinates":[115.15251000000001,30.26296],"type":"Point"}
}