{
  "type": "Feature",
  "properties": {
    "gn:admin1_code":"19.0",
    "gn:asciiname":"Kuangdonggou",
    "gn:country_code":"CN",
    "gn:dem":128,
    "gn:feature_class":"P",
    "gn:feature_code":"PPL",
    "gn:name":"Kuangdonggou",
    "gn:population":0,
    "gn:timezone":"Asia/Shanghai",
    "iso:country":"CN",
    "name:zho_x_preferred":[
        "\u77ff\u6d1e\u6c9f"
    ],
    "wof:name":"Kuangdonggou",
    "wof:placetype":"locality"
},
  "geometry": {"coordinates":[123.297,41.0902],"type":"Point"}
}