{
  "type": "Feature",
  "properties": {
    "gn:admin1_code":"13.0",
    "gn:asciiname":"Yanqi",
    "gn:country_code":"CN",
    "gn:dem":1059,
    "gn:feature_class":"P",
    "gn:feature_code":"PPLA3",
    "gn:name":"Yanqi",
    "gn:population":0,
    "gn:timezone":"Asia/Urumqi",
    "iso:country":"CN",
    "name:bul_x_preferred":[
        "\u041a\u0430\u0440\u0430\u0448\u0430\u0440"
    ],
    "name:cat_x_preferred":[
        "Qaraixahr"
    ],
    "name:deu_x_preferred":[
        "Karashahr"
    ],
    "name:fas_x_preferred":[
        "\u0642\u0631\u0647\u200c\u0634\u0647\u0631"
    ],
    "name:fra_x_preferred":[
        "Karachahr"
    ],
    "name:hin_x_preferred":[
        "\u0915\u093e\u0930\u093e\u0936\u0939\u0930"
    ],
    "name:ind_x_preferred":[
        "Karasahr"
    ],
    "name:ita_x_preferred":[
        "Karasahr"
    ],
    "name:kor_x_preferred":[
        "\uce74\ub77c\uc0e4\ub974"
    ],
    "name:lit_x_preferred":[
        "Kara\u0161aras"
    ],
    "name:mon_x_preferred":[
        "\u041a\u0430\u0440\u0430\u0448\u0430\u0440"
    ],
    "name:pnb_x_preferred":[
        "\u06a9\u0627\u0631\u0627\u0634\u06c1\u0631"
    ],
    "name:por_x_preferred":[
        "Karasahr"
    ],
    "name:rus_x_preferred":[
        "\u041a\u0430\u0440\u0430\u0448\u0430\u0440"
    ],
    "name:tur_x_preferred":[
        "Kara\u015fehir"
    ],
    "name:uig_x_preferred":[
        "K\u0329arax\u0259h\u0328\u0259r"
    ],
    "name:uig_x_variant":[
        "Qarasheher",
        "\u0642\u0627\u0631\u0627\u0634\u06d5\u06be\u06d5\u0631",
        "\u049a\u0430\u0440\u0430\u0448\u04d9\u04bb\u04d9\u0440",
        "\u0642\u0627\u0631\u0627\u0634\u06d5\u06be\u06d5\u0631 \u0628\u0627\u0632\u0649\u0631\u0649"
    ],
    "name:ukr_x_preferred":[
        "\u041a\u0430\u0440\u0430\u0448\u0430\u0440"
    ],
    "name:und_x_variant":[
        "K\u2019o-la-sha-erh",
        "Yen-ch\u2019i-hui-tsu-tzu-chih-ch\u2019\u00fc",
        "Kara-schahr",
        "Yinki",
        "K\u2019a-la-sha-erh",
        "Yen-ch\u2019i-chen",
        "Khara Shar",
        "Yenki",
        "Ha-la-sha-erh",
        "Yen-ch\u2019i",
        "Kurashar\u2019",
        "Yan\u2019tsy",
        "Yen-ch\u2019i-hui-tsu-tzu-chih-hsien",
        "Karashar",
        "Yen-ch\u2019i-hsien",
        "Qara Shahr",
        "Yanqi",
        "\u7109\u8006",
        "Yanqi Zhen",
        "\u7109\u8006\u9547"
    ],
    "name:vie_x_preferred":[
        "Y\u00ean K\u1ef3"
    ],
    "wof:name":"Yanqi",
    "wof:placetype":"locality"
},
  "geometry": {"coordinates":[86.56631999999998,42.06204],"type":"Point"}
}