{
  "type": "Feature",
  "properties": {
    "gn:admin1_code":"13.0",
    "gn:asciiname":"Yanqi",
    "gn:country_code":"CN",
    "gn:dem":1059,
    "gn:feature_class":"P",
    "gn:feature_code":"PPLA3",
    "gn:name":"Yanqi",
    "gn:population":0,
    "gn:timezone":"Asia/Urumqi",
    "iso:country":"CN",
    "name:uig_x_preferred":[
        "K\u0329arax\u0259h\u0328\u0259r"
    ],
    "name:uig_x_variant":[
        "Qarasheher",
        "\u0642\u0627\u0631\u0627\u0634\u06d5\u06be\u06d5\u0631",
        "\u049a\u0430\u0440\u0430\u0448\u04d9\u04bb\u04d9\u0440"
    ],
    "name:und_x_variant":[
        "K\u2019o-la-sha-erh",
        "Yen-ch\u2019i-hui-tsu-tzu-chih-ch\u2019\u00fc",
        "Kara-schahr",
        "Yinki",
        "K\u2019a-la-sha-erh",
        "Yen-ch\u2019i-chen",
        "Khara Shar",
        "Yenki",
        "Ha-la-sha-erh",
        "Yen-ch\u2019i",
        "Kurashar\u2019",
        "Yan\u2019tsy",
        "Karashahr",
        "Yen-ch\u2019i-hui-tsu-tzu-chih-hsien",
        "Karashar",
        "Yen-ch\u2019i-hsien",
        "Karachahr",
        "Qara Shahr",
        "Yanqi",
        "\u7109\u8006",
        "Yanqi Zhen",
        "\u7109\u8006\u9547"
    ],
    "wof:name":"Yanqi",
    "wof:placetype":"locality"
},
  "geometry": {"coordinates":[86.56631999999998,42.06204],"type":"Point"}
}