{
  "type": "Feature",
  "properties": {
    "gn:admin1_code":"26.0",
    "gn:asciiname":"Shiyao Goucun",
    "gn:country_code":"CN",
    "gn:dem":1066,
    "gn:feature_class":"P",
    "gn:feature_code":"PPL",
    "gn:name":"Shiyao Goucun",
    "gn:population":0,
    "gn:timezone":"Asia/Shanghai",
    "iso:country":"CN",
    "name:zho_x_preferred":[
        "\u77f3\u78d8\u6c9f\u6751"
    ],
    "wof:name":"Shiyao Goucun",
    "wof:placetype":"locality"
},
  "geometry": {"coordinates":[110.613,38.5987],"type":"Point"}
}