{
  "type": "Feature",
  "properties": {
    "gn:admin1_code":"1.0",
    "gn:asciiname":"Songshuwancun",
    "gn:country_code":"CN",
    "gn:dem":385,
    "gn:feature_class":"P",
    "gn:feature_code":"PPL",
    "gn:name":"Songshuwancun",
    "gn:population":0,
    "gn:timezone":"Asia/Shanghai",
    "iso:country":"CN",
    "name:zho_x_preferred":[
        "\u677e\u6811\u6e7e\u6751"
    ],
    "wof:name":"Songshuwancun",
    "wof:placetype":"locality"
},
  "geometry": {"coordinates":[115.62725,31.27755],"type":"Point"}
}