{
  "type": "Feature",
  "properties": {
    "gn:admin1_code":"07",
    "gn:asciiname":"Yankeng",
    "gn:country_code":"CN",
    "gn:dem":641,
    "gn:feature_class":"P",
    "gn:feature_code":"PPL",
    "gn:name":"Yankeng",
    "gn:population":0,
    "gn:timezone":"Asia/Shanghai",
    "iso:country":"CN",
    "name:zho_x_preferred":[
        "\u781a\u5751"
    ],
    "wof:name":"Yankeng",
    "wof:placetype":"locality"
},
  "geometry": {"coordinates":[118.01432,25.58881],"type":"Point"}
}