{
  "type": "Feature",
  "properties": {
    "gn:admin1_code":"10.0",
    "gn:asciiname":"Dongzhouzhuang",
    "gn:country_code":"CN",
    "gn:dem":75,
    "gn:feature_class":"P",
    "gn:feature_code":"PPL",
    "gn:name":"Dongzhouzhuang",
    "gn:population":0,
    "gn:timezone":"Asia/Shanghai",
    "iso:country":"CN",
    "name:zho_x_preferred":[
        "\u4e1c\u5468\u5e84"
    ],
    "wof:name":"Dongzhouzhuang",
    "wof:placetype":"locality"
},
  "geometry": {"coordinates":[118.63253,39.9083],"type":"Point"}
}