{
  "type": "Feature",
  "properties": {
    "gn:admin1_code":"5.0",
    "gn:asciiname":"Erdaogou",
    "gn:country_code":"CN",
    "gn:dem":311,
    "gn:feature_class":"P",
    "gn:feature_code":"PPL",
    "gn:name":"Erdaogou",
    "gn:population":0,
    "gn:timezone":"Asia/Shanghai",
    "iso:country":"CN",
    "name:und_x_variant":[
        "\u4e8c\u9053\u6c9f"
    ],
    "wof:name":"Erdaogou",
    "wof:placetype":"locality"
},
  "geometry": {"coordinates":[125.64111,41.41889000000001],"type":"Point"}
}