{
  "type": "Feature",
  "properties": {
    "gn:country":"CN",
    "gn:fcode":"ADM3",
    "gn:pop":0,
    "iso:country":"CN",
    "name:unk_x_variant":[
        "Jung-ch\u2019eng Hsien"
    ],
    "name:zho_x_preferred":[
        "\u5bb9\u57ce\u53bf"
    ],
    "name:zho_x_variant":[
        "\u5bb9\u57ce"
    ],
    "qs:name":"Rongcheng Xian",
    "qs:photos_9r":0,
    "qs:photos_sr":0,
    "qs:pop_sr":"0",
    "wof:name":"Rongcheng Xian",
    "wof:placetype":"localadmin",
    "wof:population":0
},
  "geometry": {"coordinates":[115.86667,39.05],"type":"Point"}
}