{
  "type": "Feature",
  "properties": {
    "gn:admin1_code":"29.0",
    "gn:asciiname":"Geyi",
    "gn:country_code":"CN",
    "gn:dem":1728,
    "gn:feature_class":"P",
    "gn:feature_code":"PPL",
    "gn:name":"Geyi",
    "gn:population":0,
    "gn:timezone":"Asia/Shanghai",
    "iso:country":"CN",
    "name:kor_x_preferred":[
        "\uaca9\uc758\ubd88\uad50"
    ],
    "name:zho_x_preferred":[
        "\u9769\u5b9c"
    ],
    "wof:name":"Geyi",
    "wof:placetype":"locality"
},
  "geometry": {"coordinates":[104.152,24.988],"type":"Point"}
}