{
  "type": "Feature",
  "properties": {
    "gn:admin1_code":"14.0",
    "gn:asciiname":"Gaxue",
    "gn:country_code":"CN",
    "gn:dem":4637,
    "gn:feature_class":"P",
    "gn:feature_code":"PPL",
    "gn:name":"Gaxue",
    "gn:population":0,
    "gn:timezone":"Asia/Urumqi",
    "iso:country":"CN",
    "name:zho_x_preferred":[
        "\u560e\u5b66"
    ],
    "wof:name":"Gaxue",
    "wof:placetype":"locality"
},
  "geometry": {"coordinates":[96.86647000000001,29.95642],"type":"Point"}
}