{
  "type": "Feature",
  "properties": {
    "gn:admin1_code":"32.0",
    "gn:asciiname":"Shangma Yixi",
    "gn:country_code":"CN",
    "gn:dem":3633,
    "gn:feature_class":"P",
    "gn:feature_code":"PPL",
    "gn:name":"Shangma Yixi",
    "gn:population":0,
    "gn:timezone":"Asia/Shanghai",
    "iso:country":"CN",
    "name:zho_x_preferred":[
        "\u4e0a\u739b\u4f0a\u5e0c"
    ],
    "wof:name":"Shangma Yixi",
    "wof:placetype":"locality"
},
  "geometry": {"coordinates":[100.95999999999999,29.5132],"type":"Point"}
}