{
  "type": "Feature",
  "properties": {
    "gn:admin1_code":"14.0",
    "gn:asciiname":"Dalongcun",
    "gn:country_code":"CN",
    "gn:dem":4807,
    "gn:feature_class":"P",
    "gn:feature_code":"PPL",
    "gn:name":"Dalongcun",
    "gn:population":0,
    "gn:timezone":"Asia/Urumqi",
    "iso:country":"CN",
    "name:zho_x_preferred":[
        "\u8fbe\u9686\u6751"
    ],
    "wof:name":"Dalongcun",
    "wof:placetype":"locality"
},
  "geometry": {"coordinates":[89.62523,30.81557],"type":"Point"}
}