{
  "type": "Feature",
  "properties": {
    "gn:admin1_code":"29.0",
    "gn:asciiname":"Dianweiping",
    "gn:country_code":"CN",
    "gn:dem":2287,
    "gn:feature_class":"P",
    "gn:feature_code":"PPL",
    "gn:name":"Dianweiping",
    "gn:population":0,
    "gn:timezone":"Asia/Shanghai",
    "iso:country":"CN",
    "name:zho_x_preferred":[
        "\u7538\u5c3e\u576a"
    ],
    "wof:name":"Dianweiping",
    "wof:placetype":"locality"
},
  "geometry": {"coordinates":[99.95010000000001,26.6269],"type":"Point"}
}