{
  "type": "Feature",
  "properties": {
    "gn:admin1_code":"4.0",
    "gn:asciiname":"Miaoqian",
    "gn:country_code":"CN",
    "gn:dem":4,
    "gn:feature_class":"P",
    "gn:feature_code":"PPL",
    "gn:name":"Miaoqian",
    "gn:population":0,
    "gn:timezone":"Asia/Shanghai",
    "iso:country":"CN",
    "name:zho_x_preferred":[
        "\u5e99\u524d"
    ],
    "wof:name":"Miaoqian",
    "wof:placetype":"locality"
},
  "geometry": {"coordinates":[120.16021000000001,31.86442000000001],"type":"Point"}
}