{
  "type": "Feature",
  "properties": {
    "gn:admin1_code":"29",
    "gn:asciiname":"Shuidigong",
    "gn:country_code":"CN",
    "gn:dem":1730,
    "gn:feature_class":"P",
    "gn:feature_code":"PPL",
    "gn:name":"Shuidigong",
    "gn:population":0,
    "gn:timezone":"Asia/Shanghai",
    "iso:country":"CN",
    "name:zho_x_preferred":[
        "\u6c34\u5e95\u6c5e"
    ],
    "wof:name":"Shuidigong",
    "wof:placetype":"locality"
},
  "geometry": {"coordinates":[101.63500000000001,24.21],"type":"Point"}
}