{
  "type": "Feature",
  "properties": {
    "gn:admin1_code":"14.0",
    "gn:asciiname":"Ri'abaizhong",
    "gn:country_code":"CN",
    "gn:dem":3180,
    "gn:feature_class":"P",
    "gn:feature_code":"PPL",
    "gn:name":"Ri\u2019abaizhong",
    "gn:population":0,
    "gn:timezone":"Asia/Urumqi",
    "iso:country":"CN",
    "name:und_x_variant":[
        "Ri\u2019abaizhong"
    ],
    "name:zho_x_preferred":[
        "\u65e5\u963f\u767e\u4ef2"
    ],
    "wof:name":"Ri'abaizhong",
    "wof:placetype":"locality"
},
  "geometry": {"coordinates":[98.45099,31.78563],"type":"Point"}
}