{
  "type": "Feature",
  "properties": {
    "gn:admin1_code":"24.0",
    "gn:asciiname":"Caojiayucun",
    "gn:country_code":"CN",
    "gn:dem":893,
    "gn:feature_class":"P",
    "gn:feature_code":"PPL",
    "gn:name":"Caojiayucun",
    "gn:population":0,
    "gn:timezone":"Asia/Shanghai",
    "iso:country":"CN",
    "name:zho_x_preferred":[
        "\u66f9\u5bb6\u5cea\u6751"
    ],
    "wof:name":"Caojiayucun",
    "wof:placetype":"locality"
},
  "geometry": {"coordinates":[110.80502,37.17811],"type":"Point"}
}