{
  "type": "Feature",
  "properties": {
    "gn:admin1_code":"32.0",
    "gn:asciiname":"Mulan",
    "gn:country_code":"CN",
    "gn:dem":1947,
    "gn:feature_class":"P",
    "gn:feature_code":"PPL",
    "gn:name":"Mulan",
    "gn:population":0,
    "gn:timezone":"Asia/Shanghai",
    "iso:country":"CN",
    "name:zho_x_preferred":[
        "\u6728\u680f"
    ],
    "wof:name":"Mulan",
    "wof:placetype":"locality"
},
  "geometry": {"coordinates":[102.057,27.0505],"type":"Point"}
}