{
  "type": "Feature",
  "properties": {
    "gn:admin1_code":"8.0",
    "gn:asciiname":"Taihecun",
    "gn:country_code":"CN",
    "gn:dem":137,
    "gn:feature_class":"P",
    "gn:feature_code":"PPL",
    "gn:name":"Taihecun",
    "gn:population":0,
    "gn:timezone":"Asia/Shanghai",
    "iso:country":"CN",
    "name:zho_x_preferred":[
        "\u592a\u5408\u6751"
    ],
    "wof:name":"Taihecun",
    "wof:placetype":"locality"
},
  "geometry": {"coordinates":[130.74816999999999,46.78838],"type":"Point"}
}