{
  "type": "Feature",
  "properties": {
    "gn:admin1_code":"16.0",
    "gn:asciiname":"Taixing",
    "gn:country_code":"CN",
    "gn:dem":60,
    "gn:feature_class":"P",
    "gn:feature_code":"PPL",
    "gn:name":"Taixing",
    "gn:population":0,
    "gn:timezone":"Asia/Shanghai",
    "iso:country":"CN",
    "name:zho_x_preferred":[
        "\u6cf0\u5174"
    ],
    "wof:name":"Taixing",
    "wof:placetype":"locality"
},
  "geometry": {"coordinates":[109.72199999999999,24.1406],"type":"Point"}
}