{
  "type": "Feature",
  "properties": {
    "gn:admin1_code":"22.0",
    "gn:asciiname":"Chedaolingcun",
    "gn:country_code":"CN",
    "gn:dem":203,
    "gn:feature_class":"P",
    "gn:feature_code":"PPL",
    "gn:name":"Chedaolingcun",
    "gn:population":0,
    "gn:timezone":"Asia/Shanghai",
    "iso:country":"CN",
    "name:zho_x_preferred":[
        "\u8f66\u9053\u5cad\u6751"
    ],
    "wof:name":"Chedaolingcun",
    "wof:placetype":"locality"
},
  "geometry": {"coordinates":[117.01942,40.59975],"type":"Point"}
}