{
  "type": "Feature",
  "properties": {
    "gn:admin1_code":"25",
    "gn:asciiname":"Dongzhujiacun",
    "gn:country_code":"CN",
    "gn:dem":99,
    "gn:feature_class":"P",
    "gn:feature_code":"PPL",
    "gn:name":"Dongzhujiacun",
    "gn:population":0,
    "gn:timezone":"Asia/Shanghai",
    "iso:country":"CN",
    "name:zho_x_preferred":[
        "\u4e1c\u6731\u5bb6\u6751"
    ],
    "wof:name":"Dongzhujiacun",
    "wof:placetype":"locality"
},
  "geometry": {"coordinates":[117.11,35.7018],"type":"Point"}
}