{
  "type": "Feature",
  "properties": {
    "gn:admin1_code":"15.0",
    "gn:asciiname":"Yinli",
    "gn:country_code":"CN",
    "gn:dem":2355,
    "gn:feature_class":"P",
    "gn:feature_code":"PPL",
    "gn:name":"Yinli",
    "gn:population":0,
    "gn:timezone":"Asia/Shanghai",
    "iso:country":"CN",
    "name:zho_x_preferred":[
        "\u6bb7\u91cc"
    ],
    "wof:name":"Yinli",
    "wof:placetype":"locality"
},
  "geometry": {"coordinates":[103.63,35.1586],"type":"Point"}
}