{
  "type": "Feature",
  "properties": {
    "gn:admin1_code":"01",
    "gn:asciiname":"Datiancun",
    "gn:country_code":"CN",
    "gn:dem":33,
    "gn:feature_class":"P",
    "gn:feature_code":"PPL",
    "gn:name":"Datiancun",
    "gn:population":0,
    "gn:timezone":"Asia/Shanghai",
    "iso:country":"CN",
    "name:und_x_variant":[
        "T\u2019ien-chia-chi",
        "Huatuo",
        "Ta-t\u2019ien-chi",
        "Hua-t\u2019o",
        "Ta-t\u2019ien",
        "Ta-t\u2019ien-shih-chi",
        "Datian",
        "Datiancun"
    ],
    "name:zho_x_preferred":[
        "\u5927\u7530\u6751"
    ],
    "wof:name":"Datiancun",
    "wof:placetype":"locality"
},
  "geometry": {"coordinates":[115.62989,32.94194],"type":"Point"}
}