{
  "type": "Feature",
  "properties": {
    "gn:admin1_code":"3",
    "gn:asciiname":"Shangjiangjiadong",
    "gn:country_code":"CN",
    "gn:dem":447,
    "gn:feature_class":"P",
    "gn:feature_code":"PPL",
    "gn:name":"Shangjiangjiadong",
    "gn:population":0,
    "gn:timezone":"Asia/Shanghai",
    "iso:country":"CN",
    "name:zho_x_preferred":[
        "\u4e0a\u59dc\u5bb6\u6d1e"
    ],
    "wof:name":"Shangjiangjiadong",
    "wof:placetype":"locality"
},
  "geometry": {"coordinates":[114.383,25.7884],"type":"Point"}
}