{
  "type": "Feature",
  "properties": {
    "gn:admin1_code":"18",
    "gn:asciiname":"Pengjiazhai",
    "gn:country_code":"CN",
    "gn:dem":1918,
    "gn:feature_class":"P",
    "gn:feature_code":"PPL",
    "gn:name":"Pengjiazhai",
    "gn:population":0,
    "gn:timezone":"Asia/Shanghai",
    "iso:country":"CN",
    "name:zho_x_preferred":[
        "\u5f6d\u5bb6\u5be8"
    ],
    "wof:name":"Pengjiazhai",
    "wof:placetype":"locality"
},
  "geometry": {"coordinates":[105.32899999999999,27.0841],"type":"Point"}
}