{
  "type": "Feature",
  "properties": {
    "gn:admin1_code":"11.0",
    "gn:asciiname":"Qujiazhou",
    "gn:country_code":"CN",
    "gn:dem":36,
    "gn:feature_class":"P",
    "gn:feature_code":"PPL",
    "gn:name":"Qujiazhou",
    "gn:population":0,
    "gn:timezone":"Asia/Shanghai",
    "iso:country":"CN",
    "name:zho_x_preferred":[
        "\u77bf\u5bb6\u6d32"
    ],
    "wof:name":"Qujiazhou",
    "wof:placetype":"locality"
},
  "geometry": {"coordinates":[112.00373999999999,28.81597],"type":"Point"}
}