{
  "type": "Feature",
  "properties": {
    "gn:admin1_code":"11.0",
    "gn:asciiname":"Doujing Duanjia",
    "gn:country_code":"CN",
    "gn:dem":293,
    "gn:feature_class":"P",
    "gn:feature_code":"PPL",
    "gn:name":"Doujing Duanjia",
    "gn:population":0,
    "gn:timezone":"Asia/Shanghai",
    "iso:country":"CN",
    "name:zho_x_preferred":[
        "\u6597\u4e95\u6bb5\u5bb6"
    ],
    "wof:name":"Doujing Duanjia",
    "wof:placetype":"locality"
},
  "geometry": {"coordinates":[110.86478,27.10486],"type":"Point"}
}