{
  "type": "Feature",
  "properties": {
    "gn:admin1_code":"29.0",
    "gn:asciiname":"Xiashuicheng",
    "gn:country_code":"CN",
    "gn:dem":2299,
    "gn:feature_class":"P",
    "gn:feature_code":"PPL",
    "gn:name":"Xiashuicheng",
    "gn:population":0,
    "gn:timezone":"Asia/Shanghai",
    "iso:country":"CN",
    "name:zho_x_preferred":[
        "\u4e0b\u6c34\u57ce"
    ],
    "wof:name":"Xiashuicheng",
    "wof:placetype":"locality"
},
  "geometry": {"coordinates":[102.346,25.8263],"type":"Point"}
}