{
  "type": "Feature",
  "properties": {
    "gn:admin1_code":"18",
    "gn:asciiname":"Baideng",
    "gn:country_code":"CN",
    "gn:dem":1389,
    "gn:feature_class":"P",
    "gn:feature_code":"PPL",
    "gn:name":"Baideng",
    "gn:population":0,
    "gn:timezone":"Asia/Shanghai",
    "iso:country":"CN",
    "name:zho_x_preferred":[
        "\u6446\u7b49"
    ],
    "wof:name":"Baideng",
    "wof:placetype":"locality"
},
  "geometry": {"coordinates":[106.88800000000001,26.2949],"type":"Point"}
}