{
  "type": "Feature",
  "properties": {
    "gn:admin1_code":"19.0",
    "gn:asciiname":"Sanjia Wopu",
    "gn:country_code":"CN",
    "gn:dem":247,
    "gn:feature_class":"P",
    "gn:feature_code":"PPL",
    "gn:name":"Sanjia Wopu",
    "gn:population":0,
    "gn:timezone":"Asia/Shanghai",
    "iso:country":"CN",
    "name:zho_x_preferred":[
        "\u4e09\u5bb6\u7a9d\u94fa"
    ],
    "wof:name":"Sanjia Wopu",
    "wof:placetype":"locality"
},
  "geometry": {"coordinates":[121.06999999999999,41.8186],"type":"Point"}
}