{
  "type": "Feature",
  "properties": {
    "gn:admin1_code":"9",
    "gn:asciiname":"Hualou",
    "gn:country_code":"CN",
    "gn:dem":58,
    "gn:feature_class":"P",
    "gn:feature_code":"PPL",
    "gn:name":"Hualou",
    "gn:population":0,
    "gn:timezone":"Asia/Shanghai",
    "iso:country":"CN",
    "name:zho_x_preferred":[
        "\u6ed1\u697c"
    ],
    "name:zho_x_variant":[
        "\u5316\u697c\u9547"
    ],
    "wof:name":"Hualou",
    "wof:placetype":"locality"
},
  "geometry": {"coordinates":[115.059,34.3326],"type":"Point"}
}