{
  "type": "Feature",
  "properties": {
    "gn:admin1_code":"13.0",
    "gn:asciiname":"Kokterak",
    "gn:country_code":"CN",
    "gn:dem":1641,
    "gn:feature_class":"P",
    "gn:feature_code":"PPL",
    "gn:name":"Kokterak",
    "gn:population":0,
    "gn:timezone":"Asia/Shanghai",
    "iso:country":"CN",
    "name:uig_x_preferred":[
        "K\u0275k Ter\u0259k"
    ],
    "name:uig_x_variant":[
        "K\u00f6k T\u00e9rek",
        "\u0643\u06c6\u0643 \u062a\u06d0\u0631\u06d5\u0643",
        "\u041a\u04e9\u043a \u0422\u0435\u0440\u04d9\u043a"
    ],
    "wof:name":"Kokterak",
    "wof:placetype":"locality"
},
  "geometry": {"coordinates":[81.59194000000002,42.97972],"type":"Point"}
}