{
  "type": "Feature",
  "properties": {
    "gn:admin1_code":"32.0",
    "gn:asciiname":"Jinwangchang",
    "gn:country_code":"CN",
    "gn:dem":545,
    "gn:feature_class":"P",
    "gn:feature_code":"PPL",
    "gn:name":"Jinwangchang",
    "gn:population":0,
    "gn:timezone":"Asia/Shanghai",
    "iso:country":"CN",
    "name:zho_x_preferred":[
        "\u664b\u738b\u573a"
    ],
    "wof:name":"Jinwangchang",
    "wof:placetype":"locality"
},
  "geometry": {"coordinates":[103.62184999999999,30.18825],"type":"Point"}
}