{
  "type": "Feature",
  "properties": {
    "gn:admin1_code":"9.0",
    "gn:asciiname":"Wuminggou",
    "gn:country_code":"CN",
    "gn:dem":839,
    "gn:feature_class":"P",
    "gn:feature_code":"PPL",
    "gn:name":"Wuminggou",
    "gn:population":0,
    "gn:timezone":"Asia/Shanghai",
    "iso:country":"CN",
    "name:zho_x_preferred":[
        "\u68a7\u9e23\u6c9f"
    ],
    "wof:name":"Wuminggou",
    "wof:placetype":"locality"
},
  "geometry": {"coordinates":[111.08714000000001,33.82007],"type":"Point"}
}