{
  "type": "Feature",
  "properties": {
    "gn:admin1_code":"32.0",
    "gn:asciiname":"Hebashang",
    "gn:country_code":"CN",
    "gn:dem":704,
    "gn:feature_class":"P",
    "gn:feature_code":"PPL",
    "gn:name":"Hebashang",
    "gn:population":0,
    "gn:timezone":"Asia/Shanghai",
    "iso:country":"CN",
    "name:zho_x_preferred":[
        "\u6cb3\u575d\u4e0a"
    ],
    "wof:name":"Hebashang",
    "wof:placetype":"locality"
},
  "geometry": {"coordinates":[102.98257,29.94795],"type":"Point"}
}