{
  "type": "Feature",
  "properties": {
    "gn:admin1_code":"19.0",
    "gn:asciiname":"Dengjiajie",
    "gn:country_code":"CN",
    "gn:dem":67,
    "gn:feature_class":"P",
    "gn:feature_code":"PPL",
    "gn:name":"Dengjiajie",
    "gn:population":0,
    "gn:timezone":"Asia/Shanghai",
    "iso:country":"CN",
    "name:und_x_variant":[
        "\u9093\u5bb6\u8857"
    ],
    "name:zho_x_preferred":[
        "\u9093\u5bb6\u8857"
    ],
    "wof:name":"Dengjiajie",
    "wof:placetype":"locality"
},
  "geometry": {"coordinates":[123.78997,42.46188],"type":"Point"}
}