{
  "type": "Feature",
  "properties": {
    "gn:admin1_code":"19.0",
    "gn:asciiname":"Yushu Tuozicun",
    "gn:country_code":"CN",
    "gn:dem":6,
    "gn:feature_class":"P",
    "gn:feature_code":"PPL",
    "gn:name":"Yushu Tuozicun",
    "gn:population":0,
    "gn:timezone":"Asia/Shanghai",
    "iso:country":"CN",
    "name:zho_x_preferred":[
        "\u6986\u6811\u5768\u5b50\u6751"
    ],
    "wof:name":"Yushu Tuozicun",
    "wof:placetype":"locality"
},
  "geometry": {"coordinates":[122.39100000000001,41.1934],"type":"Point"}
}