{
  "type": "Feature",
  "properties": {
    "gn:admin1_code":"29",
    "gn:asciiname":"Houtangzi",
    "gn:country_code":"CN",
    "gn:dem":1317,
    "gn:feature_class":"P",
    "gn:feature_code":"PPL",
    "gn:name":"Houtangzi",
    "gn:population":0,
    "gn:timezone":"Asia/Shanghai",
    "iso:country":"CN",
    "name:zho_x_preferred":[
        "\u540e\u5858\u5b50"
    ],
    "wof:name":"Houtangzi",
    "wof:placetype":"locality"
},
  "geometry": {"coordinates":[105.15000000000001,23.9794],"type":"Point"}
}