{
  "type": "Feature",
  "properties": {
    "gn:admin1_code":"5.0",
    "gn:asciiname":"Yongfucun",
    "gn:country_code":"CN",
    "gn:dem":174,
    "gn:feature_class":"P",
    "gn:feature_code":"PPL",
    "gn:name":"Yongfucun",
    "gn:population":0,
    "gn:timezone":"Asia/Shanghai",
    "iso:country":"CN",
    "name:zho_x_preferred":[
        "\u6c38\u5bcc\u6751"
    ],
    "wof:name":"Yongfucun",
    "wof:placetype":"locality"
},
  "geometry": {"coordinates":[126.71187999999999,44.80889000000001],"type":"Point"}
}