{
  "type": "Feature",
  "properties": {
    "gn:admin1_code":"32.0",
    "gn:asciiname":"Ashamo",
    "gn:country_code":"CN",
    "gn:dem":1659,
    "gn:feature_class":"P",
    "gn:feature_code":"PPL",
    "gn:name":"Ashamo",
    "gn:population":0,
    "gn:timezone":"Asia/Shanghai",
    "iso:country":"CN",
    "name:zho_x_preferred":[
        "\u963f\u6c99\u83ab"
    ],
    "wof:name":"Ashamo",
    "wof:placetype":"locality"
},
  "geometry": {"coordinates":[102.846,28.8074],"type":"Point"}
}