{
  "type": "Feature",
  "properties": {
    "gn:admin1_code":"10.0",
    "gn:asciiname":"Xixinlizhuang",
    "gn:country_code":"CN",
    "gn:dem":3,
    "gn:feature_class":"P",
    "gn:feature_code":"PPL",
    "gn:name":"Xixinlizhuang",
    "gn:population":0,
    "gn:timezone":"Asia/Shanghai",
    "iso:country":"CN",
    "name:zho_x_preferred":[
        "\u897f\u65b0\u7acb\u5e84"
    ],
    "wof:name":"Xixinlizhuang",
    "wof:placetype":"locality"
},
  "geometry": {"coordinates":[119.18113999999998,39.53406],"type":"Point"}
}