{
  "type": "Feature",
  "properties": {
    "gn:admin1_code":"21.0",
    "gn:asciiname":"Niupigou",
    "gn:country_code":"CN",
    "gn:dem":1514,
    "gn:feature_class":"P",
    "gn:feature_code":"PPL",
    "gn:name":"Niupigou",
    "gn:population":0,
    "gn:timezone":"Asia/Shanghai",
    "iso:country":"CN",
    "name:zho_x_preferred":[
        "\u725b\u76ae\u6c9f"
    ],
    "wof:name":"Niupigou",
    "wof:placetype":"locality"
},
  "geometry": {"coordinates":[106.848,37.3046],"type":"Point"}
}