{
  "type": "Feature",
  "properties": {
    "gn:admin1_code":"32.0",
    "gn:asciiname":"Liangfengding",
    "gn:country_code":"CN",
    "gn:dem":552,
    "gn:feature_class":"P",
    "gn:feature_code":"PPL",
    "gn:name":"Liangfengding",
    "gn:population":0,
    "gn:timezone":"Asia/Shanghai",
    "iso:country":"CN",
    "name:zho_x_preferred":[
        "\u51c9\u98ce\u9876"
    ],
    "wof:name":"Liangfengding",
    "wof:placetype":"locality"
},
  "geometry": {"coordinates":[103.97927,29.82871],"type":"Point"}
}