{
  "type": "Feature",
  "properties": {
    "gn:admin1_code":"8.0",
    "gn:asciiname":"Futaitun",
    "gn:country_code":"CN",
    "gn:dem":333,
    "gn:feature_class":"P",
    "gn:feature_code":"PPL",
    "gn:name":"Futaitun",
    "gn:population":0,
    "gn:timezone":"Asia/Shanghai",
    "iso:country":"CN",
    "name:zho_x_preferred":[
        "\u798f\u592a\u5c6f"
    ],
    "wof:name":"Futaitun",
    "wof:placetype":"locality"
},
  "geometry": {"coordinates":[127.82201000000001,44.30894],"type":"Point"}
}