{
  "type": "Feature",
  "properties": {
    "gn:admin1_code":"33.0",
    "gn:asciiname":"Xinglong'ao",
    "gn:country_code":"CN",
    "gn:dem":565,
    "gn:feature_class":"P",
    "gn:feature_code":"PPL",
    "gn:name":"Xinglong\u2019ao",
    "gn:population":0,
    "gn:timezone":"Asia/Shanghai",
    "iso:country":"CN",
    "name:und_x_variant":[
        "Xinglong\u2019ao"
    ],
    "name:zho_x_preferred":[
        "\u5174\u9f99\u5773"
    ],
    "wof:name":"Xinglong'ao",
    "wof:placetype":"locality"
},
  "geometry": {"coordinates":[108.92794000000001,28.48276],"type":"Point"}
}