{
  "type": "Feature",
  "properties": {
    "gn:admin1_code":"8.0",
    "gn:asciiname":"Biaogancun",
    "gn:country_code":"CN",
    "gn:dem":152,
    "gn:feature_class":"P",
    "gn:feature_code":"PPL",
    "gn:name":"Biaogancun",
    "gn:population":0,
    "gn:timezone":"Asia/Shanghai",
    "iso:country":"CN",
    "name:zho_x_preferred":[
        "\u6807\u6746\u6751"
    ],
    "wof:name":"Biaogancun",
    "wof:placetype":"locality"
},
  "geometry": {"coordinates":[125.0403,46.6475],"type":"Point"}
}