{
  "type": "Feature",
  "properties": {
    "gn:admin1_code":"26.0",
    "gn:asciiname":"Jindongzi",
    "gn:country_code":"CN",
    "gn:dem":1597,
    "gn:feature_class":"P",
    "gn:feature_code":"PPL",
    "gn:name":"Jindongzi",
    "gn:population":0,
    "gn:timezone":"Asia/Shanghai",
    "iso:country":"CN",
    "name:und_x_variant":[
        "\u91d1\u6d1e\u5b50"
    ],
    "wof:name":"Jindongzi",
    "wof:placetype":"locality"
},
  "geometry": {"coordinates":[108.02003000000001,33.46453],"type":"Point"}
}