{
  "type": "Feature",
  "properties": {
    "gn:admin1_code":"24.0",
    "gn:asciiname":"Shenpo",
    "gn:country_code":"CN",
    "gn:dem":1125,
    "gn:feature_class":"P",
    "gn:feature_code":"PPL",
    "gn:name":"Shenpo",
    "gn:population":0,
    "gn:timezone":"Asia/Shanghai",
    "iso:country":"CN",
    "name:und_x_variant":[
        "\u795e\u5761"
    ],
    "wof:name":"Shenpo",
    "wof:placetype":"locality"
},
  "geometry": {"coordinates":[111.65801999999999,35.86945],"type":"Point"}
}