{
  "type": "Feature",
  "properties": {
    "gn:admin1_code":"03",
    "gn:asciiname":"Dongshanba",
    "gn:country_code":"CN",
    "gn:dem":216,
    "gn:feature_class":"P",
    "gn:feature_code":"PPLA4",
    "gn:name":"Dongshanba",
    "gn:population":0,
    "gn:timezone":"Asia/Shanghai",
    "iso:country":"CN",
    "name:und_x_variant":[
        "\u4e1c\u5c71\u575d",
        "Dongshanba Zhen",
        "\u4e1c\u5c71\u575d\u9547"
    ],
    "wof:name":"Dongshanba",
    "wof:placetype":"locality"
},
  "geometry": {"coordinates":[116.06046000000001,26.74057],"type":"Point"}
}