{
  "type": "Feature",
  "properties": {
    "gn:admin1_code":"7",
    "gn:asciiname":"Shandou",
    "gn:country_code":"CN",
    "gn:dem":30,
    "gn:feature_class":"P",
    "gn:feature_code":"PPL",
    "gn:name":"Shandou",
    "gn:population":0,
    "gn:timezone":"Asia/Shanghai",
    "iso:country":"CN",
    "name:und_x_variant":[
        "\u5c71\u515c",
        "Shandou"
    ],
    "wof:name":"Shandou",
    "wof:placetype":"locality"
},
  "geometry": {"coordinates":[118.60550000000001,24.74704],"type":"Point"}
}