{
  "type": "Feature",
  "properties": {
    "gn:admin1_code":"26.0",
    "gn:asciiname":"Zhongmajiahe",
    "gn:country_code":"CN",
    "gn:dem":1471,
    "gn:feature_class":"P",
    "gn:feature_code":"PPL",
    "gn:name":"Zhongmajiahe",
    "gn:population":0,
    "gn:timezone":"Asia/Shanghai",
    "iso:country":"CN",
    "name:zho_x_preferred":[
        "\u4e2d\u9ebb\u5bb6\u6cb3"
    ],
    "wof:name":"Zhongmajiahe",
    "wof:placetype":"locality"
},
  "geometry": {"coordinates":[108.90586999999999,36.74389],"type":"Point"}
}