{
  "type": "Feature",
  "properties": {
    "gn:admin1_code":"15.0",
    "gn:asciiname":"Zhangjiacha",
    "gn:country_code":"CN",
    "gn:dem":1714,
    "gn:feature_class":"P",
    "gn:feature_code":"PPL",
    "gn:name":"Zhangjiacha",
    "gn:population":0,
    "gn:timezone":"Asia/Shanghai",
    "iso:country":"CN",
    "name:zho_x_preferred":[
        "\u5f20\u5bb6\u5c94"
    ],
    "wof:name":"Zhangjiacha",
    "wof:placetype":"locality"
},
  "geometry": {"coordinates":[105.489,34.791],"type":"Point"}
}