{
  "type": "Feature",
  "properties": {
    "gn:admin1_code":"29.0",
    "gn:asciiname":"Kekanggang",
    "gn:country_code":"CN",
    "gn:dem":3346,
    "gn:feature_class":"P",
    "gn:feature_code":"PPL",
    "gn:name":"Kekanggang",
    "gn:population":0,
    "gn:timezone":"Asia/Shanghai",
    "iso:country":"CN",
    "name:zho_x_preferred":[
        "\u5777\u5eb7\u5188"
    ],
    "wof:name":"Kekanggang",
    "wof:placetype":"locality"
},
  "geometry": {"coordinates":[99.71040000000001,27.7595],"type":"Point"}
}