{
  "type": "Feature",
  "properties": {
    "gn:admin1_code":"32.0",
    "gn:asciiname":"Ka'ergu",
    "gn:country_code":"CN",
    "gn:dem":3222,
    "gn:feature_class":"P",
    "gn:feature_code":"PPL",
    "gn:name":"Ka\u2019ergu",
    "gn:population":0,
    "gn:timezone":"Asia/Shanghai",
    "iso:country":"CN",
    "name:und_x_variant":[
        "Ka\u2019ergu"
    ],
    "name:zho_x_preferred":[
        "\u5361\u5c14\u53e4"
    ],
    "wof:name":"Ka'ergu",
    "wof:placetype":"locality"
},
  "geometry": {"coordinates":[102.242,32.1798],"type":"Point"}
}