{
  "type": "Feature",
  "properties": {
    "gn:admin1_code":"30.0",
    "gn:asciiname":"Litouzui",
    "gn:country_code":"CN",
    "gn:dem":47,
    "gn:feature_class":"P",
    "gn:feature_code":"PPL",
    "gn:name":"Litouzui",
    "gn:population":0,
    "gn:timezone":"Asia/Shanghai",
    "iso:country":"CN",
    "name:zho_x_preferred":[
        "Litouzui"
    ],
    "name:zho_x_variant":[
        "\u7281\u5934\u5480"
    ],
    "wof:name":"Litouzui",
    "wof:placetype":"locality"
},
  "geometry": {"coordinates":[113.15472,23.85694],"type":"Point"}
}