{
  "type": "Feature",
  "properties": {
    "gn:admin1_code":"32.0",
    "gn:asciiname":"Wudu",
    "gn:country_code":"CN",
    "gn:dem":2669,
    "gn:feature_class":"P",
    "gn:feature_code":"PPL",
    "gn:name":"Wudu",
    "gn:population":0,
    "gn:timezone":"Asia/Shanghai",
    "iso:country":"CN",
    "name:zho_x_preferred":[
        "\u4e94\u90fd"
    ],
    "wof:name":"Wudu",
    "wof:placetype":"locality"
},
  "geometry": {"coordinates":[101.652,32.1936],"type":"Point"}
}