{
  "type": "Feature",
  "properties": {
    "gn:admin1_code":"32.0",
    "gn:asciiname":"Daxingzhai",
    "gn:country_code":"CN",
    "gn:dem":338,
    "gn:feature_class":"P",
    "gn:feature_code":"PPL",
    "gn:name":"Daxingzhai",
    "gn:population":0,
    "gn:timezone":"Asia/Shanghai",
    "iso:country":"CN",
    "name:zho_x_preferred":[
        "\u5927\u661f\u5be8"
    ],
    "wof:name":"Daxingzhai",
    "wof:placetype":"locality"
},
  "geometry": {"coordinates":[106.505,31.007],"type":"Point"}
}