{
  "type": "Feature",
  "properties": {
    "gn:admin1_code":"9.0",
    "gn:asciiname":"Lingshang",
    "gn:country_code":"CN",
    "gn:dem":269,
    "gn:feature_class":"P",
    "gn:feature_code":"PPL",
    "gn:name":"Lingshang",
    "gn:population":0,
    "gn:timezone":"Asia/Shanghai",
    "iso:country":"CN",
    "name:und_x_variant":[
        "\u5cad\u4e0a",
        "Lingshang"
    ],
    "wof:name":"Lingshang",
    "wof:placetype":"locality"
},
  "geometry": {"coordinates":[112.15729,33.17305],"type":"Point"}
}