{
  "type": "Feature",
  "properties": {
    "gn:admin1_code":"19.0",
    "gn:asciiname":"Xingshutuocun",
    "gn:country_code":"CN",
    "gn:dem":12,
    "gn:feature_class":"P",
    "gn:feature_code":"PPL",
    "gn:name":"Xingshutuocun",
    "gn:population":0,
    "gn:timezone":"Asia/Shanghai",
    "iso:country":"CN",
    "name:zho_x_preferred":[
        "\u674f\u6811\u5768\u6751"
    ],
    "wof:name":"Xingshutuocun",
    "wof:placetype":"locality"
},
  "geometry": {"coordinates":[122.81310999999999,41.30847],"type":"Point"}
}