{
  "type": "Feature",
  "properties": {
    "gn:admin1_code":"30.0",
    "gn:asciiname":"Chashanpai",
    "gn:country_code":"CN",
    "gn:dem":513,
    "gn:feature_class":"P",
    "gn:feature_code":"PPL",
    "gn:name":"Chashanpai",
    "gn:population":0,
    "gn:timezone":"Asia/Shanghai",
    "iso:country":"CN",
    "name:zho_x_preferred":[
        "Chashanpai"
    ],
    "name:zho_x_variant":[
        "\u8336\u5c71\u6392"
    ],
    "wof:name":"Chashanpai",
    "wof:placetype":"locality"
},
  "geometry": {"coordinates":[113.97278,25.395],"type":"Point"}
}