{
  "type": "Feature",
  "properties": {
    "gn:admin1_code":"7.0",
    "gn:asciiname":"Shuichao",
    "gn:country_code":"CN",
    "gn:dem":161,
    "gn:feature_class":"P",
    "gn:feature_code":"PPL",
    "gn:name":"Shuichao",
    "gn:population":0,
    "gn:timezone":"Asia/Shanghai",
    "iso:country":"CN",
    "name:zho_x_preferred":[
        "Shuichao"
    ],
    "name:zho_x_variant":[
        "\u6c34\u6f6e"
    ],
    "wof:name":"Shuichao",
    "wof:placetype":"locality"
},
  "geometry": {"coordinates":[118.73944,26.37667],"type":"Point"}
}