{
  "type": "Feature",
  "properties": {
    "gn:admin1_code":"14.0",
    "gn:asciiname":"Tongxin Muni",
    "gn:country_code":"CN",
    "gn:dem":3811,
    "gn:feature_class":"P",
    "gn:feature_code":"PPL",
    "gn:name":"Tongxin Muni",
    "gn:population":0,
    "gn:timezone":"Asia/Urumqi",
    "iso:country":"CN",
    "name:zho_x_preferred":[
        "\u901a\u5fc3\u6728\u5c3c"
    ],
    "wof:name":"Tongxin Muni",
    "wof:placetype":"locality"
},
  "geometry": {"coordinates":[95.46471,30.2502],"type":"Point"}
}