{
  "type": "Feature",
  "properties": {
    "gn:admin1_code":"31.0",
    "gn:asciiname":"Zhen Nongchang",
    "gn:country_code":"CN",
    "gn:dem":56,
    "gn:feature_class":"P",
    "gn:feature_code":"PPLF",
    "gn:name":"Zhen Nongchang",
    "gn:population":0,
    "gn:timezone":"Asia/Shanghai",
    "iso:country":"CN",
    "name:und_x_variant":[
        "\u9547\u519c\u573a"
    ],
    "wof:name":"Zhen Nongchang",
    "wof:placetype":"locality"
},
  "geometry": {"coordinates":[109.02509000000001,18.46785],"type":"Point"}
}