{
  "type": "Feature",
  "properties": {
    "gn:admin1_code":"9",
    "gn:asciiname":"Huangyao",
    "gn:country_code":"CN",
    "gn:dem":73,
    "gn:feature_class":"P",
    "gn:feature_code":"PPL",
    "gn:name":"Huangyao",
    "gn:population":0,
    "gn:timezone":"Asia/Shanghai",
    "iso:country":"CN",
    "name:fra_x_preferred":[
        "Huangyao"
    ],
    "name:zho_x_preferred":[
        "\u9ec4\u7a91"
    ],
    "name:zho_x_variant":[
        "\u9ec4\u59da\u9547"
    ],
    "wof:name":"Huangyao",
    "wof:placetype":"locality"
},
  "geometry": {"coordinates":[114.88800000000001,34.898],"type":"Point"}
}