{
  "type": "Feature",
  "properties": {
    "gn:admin1_code":"18",
    "gn:asciiname":"Maolibu",
    "gn:country_code":"CN",
    "gn:dem":854,
    "gn:feature_class":"P",
    "gn:feature_code":"PPL",
    "gn:name":"Maolibu",
    "gn:population":0,
    "gn:timezone":"Asia/Shanghai",
    "iso:country":"CN",
    "name:zho_x_preferred":[
        "\u6bdb\u6817\u5821"
    ],
    "wof:name":"Maolibu",
    "wof:placetype":"locality"
},
  "geometry": {"coordinates":[107.56399999999999,27.709],"type":"Point"}
}