{
  "type": "Feature",
  "properties": {
    "gn:admin1_code":"26.0",
    "gn:asciiname":"Guanshang",
    "gn:country_code":"CN",
    "gn:dem":1244,
    "gn:feature_class":"P",
    "gn:feature_code":"PPL",
    "gn:name":"Guanshang",
    "gn:population":0,
    "gn:timezone":"Asia/Shanghai",
    "iso:country":"CN",
    "name:zho_x_preferred":[
        "\u5173\u4e0a"
    ],
    "wof:name":"Guanshang",
    "wof:placetype":"locality"
},
  "geometry": {"coordinates":[109.97474,33.44472],"type":"Point"}
}