{
  "type": "Feature",
  "properties": {
    "gn:admin1_code":"33.0",
    "gn:asciiname":"Baihuatai",
    "gn:country_code":"CN",
    "gn:dem":1303,
    "gn:feature_class":"P",
    "gn:feature_code":"PPL",
    "gn:name":"Baihuatai",
    "gn:population":0,
    "gn:timezone":"Asia/Shanghai",
    "iso:country":"CN",
    "name:zho_x_preferred":[
        "\u767d\u82b1\u53f0"
    ],
    "wof:name":"Baihuatai",
    "wof:placetype":"locality"
},
  "geometry": {"coordinates":[106.95099999999999,28.8194],"type":"Point"}
}