{
  "type": "Feature",
  "properties": {
    "gn:admin1_code":"21.0",
    "gn:asciiname":"Dacha",
    "gn:country_code":"CN",
    "gn:dem":1808,
    "gn:feature_class":"P",
    "gn:feature_code":"PPL",
    "gn:name":"Dacha",
    "gn:population":0,
    "gn:timezone":"Asia/Shanghai",
    "iso:country":"CN",
    "name:und_x_variant":[
        "\u5927\u5c94"
    ],
    "name:zho_x_preferred":[
        "\u5927\u5c94"
    ],
    "wof:name":"Dacha",
    "wof:placetype":"locality"
},
  "geometry": {"coordinates":[106.44262999999999,36.24804],"type":"Point"}
}