{
  "type": "Feature",
  "properties": {
    "gn:country":"CN",
    "gn:fcode":"PPLA3",
    "gn:population":0,
    "iso:country":"CN",
    "name:und_x_variant":[
        "Shunde"
    ],
    "name:zho_x_preferred":[
        "\u987a\u5fb7"
    ],
    "qs_pg:aaroncc":"CN",
    "qs_pg:gn_country":"CN",
    "qs_pg:gn_fcode":"PPLA3",
    "qs_pg:gn_pop":0,
    "qs_pg:name":"\u987a\u5fb7\u533a",
    "qs_pg:name_adm0":"\u4e2d\u570b",
    "qs_pg:name_adm1":"\u5e7f\u4e1c\u7701",
    "qs_pg:photos":538,
    "qs_pg:photos_1k":109,
    "qs_pg:photos_9k":10,
    "qs_pg:photos_9r":9,
    "qs_pg:photos_all":2233,
    "qs_pg:photos_sr":7,
    "qs_pg:pop_sr":0,
    "qs_pg:qs_pg_placetype":"localadmin",
    "qs_pg:qs_pg_placetype_gp":"LocalAdmin",
    "qs_pg:woe_adm0":23424781,
    "woe:adm0_id":23424781,
    "woe:name_adm0":"\u4e2d\u570b",
    "woe:name_adm1":"\u5e7f\u4e1c\u7701",
    "woe:placetype":"LocalAdmin",
    "wof:name":"\u987a\u5fb7\u533a",
    "wof:placetype":"localadmin"
},
  "geometry": {"coordinates":[113.29208,22.80087],"type":"Point"}
}