{
  "type": "Feature",
  "properties": {
    "gn:admin1_code":"24.0",
    "gn:asciiname":"Sunjiayuan",
    "gn:country_code":"CN",
    "gn:dem":402,
    "gn:feature_class":"P",
    "gn:feature_code":"PPL",
    "gn:name":"Sunjiayuan",
    "gn:population":0,
    "gn:timezone":"Asia/Shanghai",
    "iso:country":"CN",
    "name:und_x_variant":[
        "\u5b59\u5bb6\u9662"
    ],
    "wof:name":"Sunjiayuan",
    "wof:placetype":"locality"
},
  "geometry": {"coordinates":[111.25848000000001,35.57547],"type":"Point"}
}