{
  "type": "Feature",
  "properties": {
    "gn:admin1_code":"15.0",
    "gn:asciiname":"Zhangma",
    "gn:country_code":"CN",
    "gn:dem":1621,
    "gn:feature_class":"P",
    "gn:feature_code":"PPL",
    "gn:name":"Zhangma",
    "gn:population":0,
    "gn:timezone":"Asia/Shanghai",
    "iso:country":"CN",
    "name:zho_x_preferred":[
        "\u5f20\u9ebb"
    ],
    "wof:name":"Zhangma",
    "wof:placetype":"locality"
},
  "geometry": {"coordinates":[105.90000000000001,34.9683],"type":"Point"}
}