{
  "type": "Feature",
  "properties": {
    "gn:admin1_code":"16.0",
    "gn:asciiname":"Shilong",
    "gn:country_code":"CN",
    "gn:dem":152,
    "gn:feature_class":"P",
    "gn:feature_code":"PPL",
    "gn:name":"Shilong",
    "gn:population":0,
    "gn:timezone":"Asia/Shanghai",
    "iso:country":"CN",
    "name:zho_x_preferred":[
        "\u77f3\u9f99"
    ],
    "wof:name":"Shilong",
    "wof:placetype":"locality"
},
  "geometry": {"coordinates":[109.592,24.6776],"type":"Point"}
}