{
  "type": "Feature",
  "properties": {
    "gn:admin1_code":"15.0",
    "gn:asciiname":"Biandiping",
    "gn:country_code":"CN",
    "gn:dem":1227,
    "gn:feature_class":"P",
    "gn:feature_code":"PPL",
    "gn:name":"Biandiping",
    "gn:population":0,
    "gn:timezone":"Asia/Shanghai",
    "iso:country":"CN",
    "name:und_x_variant":[
        "\u8fb9\u5730\u576a"
    ],
    "name:zho_x_preferred":[
        "\u8fb9\u5730\u576a"
    ],
    "wof:name":"Biandiping",
    "wof:placetype":"locality"
},
  "geometry": {"coordinates":[104.38448,33.06004],"type":"Point"}
}