{
  "type": "Feature",
  "properties": {
    "gn:admin1_code":"18",
    "gn:asciiname":"Xuelu Pingzi",
    "gn:country_code":"CN",
    "gn:dem":2375,
    "gn:feature_class":"P",
    "gn:feature_code":"PPL",
    "gn:name":"Xuelu Pingzi",
    "gn:population":0,
    "gn:timezone":"Asia/Shanghai",
    "iso:country":"CN",
    "name:zho_x_preferred":[
        "\u96ea\u8def\u576a\u5b50"
    ],
    "wof:name":"Xuelu Pingzi",
    "wof:placetype":"locality"
},
  "geometry": {"coordinates":[104.173,26.7425],"type":"Point"}
}