{
  "type": "Feature",
  "properties": {
    "gn:admin1_code":"7",
    "gn:asciiname":"Qianmian",
    "gn:country_code":"CN",
    "gn:dem":600,
    "gn:feature_class":"P",
    "gn:feature_code":"PPL",
    "gn:name":"Qianmian",
    "gn:population":0,
    "gn:timezone":"Asia/Shanghai",
    "iso:country":"CN",
    "name:zho_x_preferred":[
        "\u524d\u9762"
    ],
    "wof:name":"Qianmian",
    "wof:placetype":"locality"
},
  "geometry": {"coordinates":[118.80297,25.49729],"type":"Point"}
}