{
  "type": "Feature",
  "properties": {
    "gn:admin1_code":"32.0",
    "gn:asciiname":"Shuangqiaozi",
    "gn:country_code":"CN",
    "gn:dem":326,
    "gn:feature_class":"P",
    "gn:feature_code":"PPL",
    "gn:name":"Shuangqiaozi",
    "gn:population":0,
    "gn:timezone":"Asia/Shanghai",
    "iso:country":"CN",
    "name:zho_x_preferred":[
        "\u53cc\u6865\u5b50"
    ],
    "wof:name":"Shuangqiaozi",
    "wof:placetype":"locality"
},
  "geometry": {"coordinates":[106.35299999999999,31.0322],"type":"Point"}
}