{
  "type": "Feature",
  "properties": {
    "gn:admin1_code":"1.0",
    "gn:asciiname":"Jiawucun",
    "gn:country_code":"CN",
    "gn:dem":59,
    "gn:feature_class":"P",
    "gn:feature_code":"PPL",
    "gn:name":"Jiawucun",
    "gn:population":0,
    "gn:timezone":"Asia/Shanghai",
    "iso:country":"CN",
    "name:zho_x_preferred":[
        "\u9a7e\u96fe\u6751"
    ],
    "wof:name":"Jiawucun",
    "wof:placetype":"locality"
},
  "geometry": {"coordinates":[116.41516,30.65984000000001],"type":"Point"}
}