{
  "type": "Feature",
  "properties": {
    "gn:admin1_code":"30.0",
    "gn:asciiname":"Dingxincun",
    "gn:country_code":"CN",
    "gn:dem":364,
    "gn:feature_class":"P",
    "gn:feature_code":"PPL",
    "gn:name":"Dingxincun",
    "gn:population":0,
    "gn:timezone":"Asia/Shanghai",
    "iso:country":"CN",
    "name:zho_x_preferred":[
        "\u9876\u65b0\u6751"
    ],
    "wof:name":"Dingxincun",
    "wof:placetype":"locality"
},
  "geometry": {"coordinates":[116.69472,23.91491],"type":"Point"}
}