{
  "type": "Feature",
  "properties": {
    "gn:admin1_code":"12.0",
    "gn:asciiname":"Luduan",
    "gn:country_code":"CN",
    "gn:dem":16,
    "gn:feature_class":"P",
    "gn:feature_code":"PPL",
    "gn:name":"Luduan",
    "gn:population":0,
    "gn:timezone":"Asia/Shanghai",
    "iso:country":"CN",
    "name:ara_x_preferred":[
        "\u0644\u0648 \u062f\u0648\u0627\u0646"
    ],
    "name:rus_x_preferred":[
        "\u041b\u0443\u0434\u0443\u043d\u044c"
    ],
    "name:zho_x_preferred":[
        "\u82a6\u5845"
    ],
    "wof:name":"Luduan",
    "wof:placetype":"locality"
},
  "geometry": {"coordinates":[115.95475999999999,29.82623],"type":"Point"}
}