{
  "type": "Feature",
  "properties": {
    "gn:admin1_code":"02",
    "gn:asciiname":"Lin'aocun",
    "gn:country_code":"CN",
    "gn:dem":55,
    "gn:feature_class":"P",
    "gn:feature_code":"PPL",
    "gn:name":"Lin\u2019aocun",
    "gn:population":0,
    "gn:timezone":"Asia/Shanghai",
    "iso:country":"CN",
    "name:und_x_variant":[
        "Lin\u2019aocun"
    ],
    "name:zho_x_preferred":[
        "\u6797\u5c99"
    ],
    "name:zho_x_variant":[
        "Lin\u2019ao",
        "\u6797\u5c99\u6751"
    ],
    "wof:name":"Lin'aocun",
    "wof:placetype":"locality"
},
  "geometry": {"coordinates":[120.42657,28.03542],"type":"Point"}
}