{
  "type": "Feature",
  "properties": {
    "gn:admin1_code":"21.0",
    "gn:asciiname":"Tangjiachuan",
    "gn:country_code":"CN",
    "gn:dem":2046,
    "gn:feature_class":"P",
    "gn:feature_code":"PPL",
    "gn:name":"Tangjiachuan",
    "gn:population":0,
    "gn:timezone":"Asia/Shanghai",
    "iso:country":"CN",
    "name:zho_x_preferred":[
        "\u5510\u5bb6\u5ddd"
    ],
    "wof:name":"Tangjiachuan",
    "wof:placetype":"locality"
},
  "geometry": {"coordinates":[105.267,36.7143],"type":"Point"}
}