{
  "type": "Feature",
  "properties": {
    "gn:admin1_code":"21.0",
    "gn:asciiname":"Liujiajing",
    "gn:country_code":"CN",
    "gn:dem":1496,
    "gn:feature_class":"P",
    "gn:feature_code":"PPL",
    "gn:name":"Liujiajing",
    "gn:population":0,
    "gn:timezone":"Asia/Shanghai",
    "iso:country":"CN",
    "name:und_x_variant":[
        "\u5218\u5bb6\u4e95"
    ],
    "name:zho_x_preferred":[
        "\u5218\u5bb6\u4e95"
    ],
    "wof:name":"Liujiajing",
    "wof:placetype":"locality"
},
  "geometry": {"coordinates":[106.15812,36.38223],"type":"Point"}
}