{
  "type": "Feature",
  "properties": {
    "gn:admin1_code":"4.0",
    "gn:asciiname":"Chenjiamofang",
    "gn:country_code":"CN",
    "gn:dem":7,
    "gn:feature_class":"P",
    "gn:feature_code":"PPL",
    "gn:name":"Chenjiamofang",
    "gn:population":0,
    "gn:timezone":"Asia/Shanghai",
    "iso:country":"CN",
    "name:und_x_variant":[
        "\u9648\u5bb6\u78e8\u574a"
    ],
    "name:zho_x_preferred":[
        "\u9648\u5bb6\u78e8\u574a"
    ],
    "wof:name":"Chenjiamofang",
    "wof:placetype":"locality"
},
  "geometry": {"coordinates":[120.71491,31.72459000000001],"type":"Point"}
}