{
  "type": "Feature",
  "properties": {
    "gn:admin1_code":"14.0",
    "gn:asciiname":"Xiucai Muchang",
    "gn:country_code":"CN",
    "gn:dem":3350,
    "gn:feature_class":"P",
    "gn:feature_code":"PPLF",
    "gn:name":"Xiucai Muchang",
    "gn:population":0,
    "gn:timezone":"Asia/Urumqi",
    "iso:country":"CN",
    "name:zho_x_preferred":[
        "\u79c0\u5f69\u7267\u573a"
    ],
    "wof:name":"Xiucai Muchang",
    "wof:placetype":"locality"
},
  "geometry": {"coordinates":[94.38175,29.23654],"type":"Point"}
}