{
  "type": "Feature",
  "properties": {
    "gn:admin1_code":"20.0",
    "gn:asciiname":"Taolihan",
    "gn:country_code":"CN",
    "gn:dem":451,
    "gn:feature_class":"P",
    "gn:feature_code":"PPL",
    "gn:name":"Taolihan",
    "gn:population":0,
    "gn:timezone":"Asia/Shanghai",
    "iso:country":"CN",
    "name:zho_x_preferred":[
        "\u9676\u529b\u7f55"
    ],
    "wof:name":"Taolihan",
    "wof:placetype":"locality"
},
  "geometry": {"coordinates":[123.22302000000001,50.1024],"type":"Point"}
}