{
  "type": "Feature",
  "properties": {
    "gn:admin1_code":"1.0",
    "gn:asciiname":"Jiayingcun",
    "gn:country_code":"CN",
    "gn:dem":66,
    "gn:feature_class":"P",
    "gn:feature_code":"PPL",
    "gn:name":"Jiayingcun",
    "gn:population":0,
    "gn:timezone":"Asia/Shanghai",
    "iso:country":"CN",
    "name:zho_x_preferred":[
        "\u8d3e\u90e2\u6751"
    ],
    "wof:name":"Jiayingcun",
    "wof:placetype":"locality"
},
  "geometry": {"coordinates":[117.01243999999998,31.96227],"type":"Point"}
}