{
  "type": "Feature",
  "properties": {
    "gn:admin1_code":"1.0",
    "gn:asciiname":"Shiwancun",
    "gn:country_code":"CN",
    "gn:dem":18,
    "gn:feature_class":"P",
    "gn:feature_code":"PPL",
    "gn:name":"Shiwancun",
    "gn:population":0,
    "gn:timezone":"Asia/Shanghai",
    "iso:country":"CN",
    "name:zho_x_preferred":[
        "\u65bd\u6e7e\u6751"
    ],
    "wof:name":"Shiwancun",
    "wof:placetype":"locality"
},
  "geometry": {"coordinates":[117.61087999999999,30.94766],"type":"Point"}
}