{
  "type": "Feature",
  "properties": {
    "gn:admin1_code":"32.0",
    "gn:asciiname":"Shuimo",
    "gn:country_code":"CN",
    "gn:dem":1345,
    "gn:feature_class":"P",
    "gn:feature_code":"PPL",
    "gn:name":"Shuimo",
    "gn:population":0,
    "gn:timezone":"Asia/Shanghai",
    "iso:country":"CN",
    "name:zho_x_preferred":[
        "\u6c34\u78e8"
    ],
    "wof:name":"Shuimo",
    "wof:placetype":"locality"
},
  "geometry": {"coordinates":[106.57277000000001,32.44671],"type":"Point"}
}