{
  "type": "Feature",
  "properties": {
    "gn:admin1_code":"1.0",
    "gn:asciiname":"Chengxihu Nongchang",
    "gn:country_code":"CN",
    "gn:dem":18,
    "gn:feature_class":"P",
    "gn:feature_code":"PPLF",
    "gn:name":"Chengxihu Nongchang",
    "gn:population":0,
    "gn:timezone":"Asia/Shanghai",
    "iso:country":"CN",
    "wof:name":"Chengxihu Nongchang",
    "wof:placetype":"locality"
},
  "geometry": {"coordinates":[116.175,32.375],"type":"Point"}
}