{
  "type": "Feature",
  "properties": {
    "gn:admin1_code":"5.0",
    "gn:asciiname":"Yanjia Weizi",
    "gn:country_code":"CN",
    "gn:dem":220,
    "gn:feature_class":"P",
    "gn:feature_code":"PPL",
    "gn:name":"Yanjia Weizi",
    "gn:population":0,
    "gn:timezone":"Asia/Shanghai",
    "iso:country":"CN",
    "name:zho_x_preferred":[
        "\u960e\u5bb6\u56f4\u5b50"
    ],
    "wof:name":"Yanjia Weizi",
    "wof:placetype":"locality"
},
  "geometry": {"coordinates":[122.09439,45.68582],"type":"Point"}
}