{
  "type": "Feature",
  "properties": {
    "gn:admin1_code":"30.0",
    "gn:asciiname":"Gangmeicun",
    "gn:country_code":"CN",
    "gn:dem":10,
    "gn:feature_class":"P",
    "gn:feature_code":"PPL",
    "gn:name":"Gangmeicun",
    "gn:population":0,
    "gn:timezone":"Asia/Shanghai",
    "iso:country":"CN",
    "name:zho_x_preferred":[
        "\u6e2f\u7f8e\u6751"
    ],
    "wof:name":"Gangmeicun",
    "wof:placetype":"locality"
},
  "geometry": {"coordinates":[116.42109000000001,23.57254],"type":"Point"}
}