{
  "type": "Feature",
  "properties": {
    "gn:admin1_code":"5.0",
    "gn:asciiname":"Hebeitun",
    "gn:country_code":"CN",
    "gn:dem":313,
    "gn:feature_class":"P",
    "gn:feature_code":"PPL",
    "gn:name":"Hebeitun",
    "gn:population":0,
    "gn:timezone":"Asia/Shanghai",
    "iso:country":"CN",
    "name:zho_x_preferred":[
        "\u6cb3\u5317\u5c6f"
    ],
    "wof:name":"Hebeitun",
    "wof:placetype":"locality"
},
  "geometry": {"coordinates":[126.12858,43.1422],"type":"Point"}
}