{
  "type": "Feature",
  "properties": {
    "gn:admin1_code":"18",
    "gn:asciiname":"Zhoubie",
    "gn:country_code":"CN",
    "gn:dem":1236,
    "gn:feature_class":"P",
    "gn:feature_code":"PPL",
    "gn:name":"Zhoubie",
    "gn:population":0,
    "gn:timezone":"Asia/Shanghai",
    "iso:country":"CN",
    "name:zho_x_preferred":[
        "\u5468\u522b"
    ],
    "wof:name":"Zhoubie",
    "wof:placetype":"locality"
},
  "geometry": {"coordinates":[104.967,25.0969],"type":"Point"}
}