{
  "type": "Feature",
  "properties": {
    "gn:admin1_code":"4.0",
    "gn:asciiname":"Chengxiang",
    "gn:country_code":"CN",
    "gn:dem":14,
    "gn:feature_class":"P",
    "gn:feature_code":"PPL",
    "gn:name":"Chengxiang",
    "gn:population":0,
    "gn:timezone":"Asia/Shanghai",
    "iso:country":"CN",
    "name:ceb_x_preferred":[
        "Chengxiang"
    ],
    "name:deu_x_preferred":[
        "Chengxiang"
    ],
    "name:nor_x_preferred":[
        "Chengxiang"
    ],
    "wof:name":"Chengxiang",
    "wof:placetype":"locality"
},
  "geometry": {"coordinates":[118.65000000000001,33.68333],"type":"Point"}
}