{
  "type": "Feature",
  "properties": {
    "gn:admin1_code":"24",
    "gn:asciiname":"Aoshi",
    "gn:country_code":"CN",
    "gn:dem":891,
    "gn:feature_class":"P",
    "gn:feature_code":"PPLA4",
    "gn:name":"Aoshi",
    "gn:population":0,
    "gn:timezone":"Asia/Shanghai",
    "iso:country":"CN",
    "name:und_x_variant":[
        "Ao-shih-ts\u2019un",
        "Ao-shih",
        "Aoshi",
        "\u9ccc\u77f3",
        "Aoshi Xiang",
        "\u9ccc\u77f3\u4e61"
    ],
    "wof:name":"Aoshi",
    "wof:placetype":"locality"
},
  "geometry": {"coordinates":[113.96587,39.96675],"type":"Point"}
}