{
  "type": "Feature",
  "properties": {
    "gn:admin1_code":"29.0",
    "gn:asciiname":"Baomalong",
    "gn:country_code":"CN",
    "gn:dem":2249,
    "gn:feature_class":"P",
    "gn:feature_code":"PPL",
    "gn:name":"Baomalong",
    "gn:population":0,
    "gn:timezone":"Asia/Shanghai",
    "iso:country":"CN",
    "name:zho_x_preferred":[
        "\u4fdd\u9a6c\u9f99"
    ],
    "wof:name":"Baomalong",
    "wof:placetype":"locality"
},
  "geometry": {"coordinates":[100.861,25.0653],"type":"Point"}
}