{
  "type": "Feature",
  "properties": {
    "gn:admin1_code":"19.0",
    "gn:asciiname":"Yaolingzi",
    "gn:country_code":"CN",
    "gn:dem":164,
    "gn:feature_class":"P",
    "gn:feature_code":"PPL",
    "gn:name":"Yaolingzi",
    "gn:population":0,
    "gn:timezone":"Asia/Shanghai",
    "iso:country":"CN",
    "name:und_x_variant":[
        "\u8170\u5cad\u5b50"
    ],
    "wof:name":"Yaolingzi",
    "wof:placetype":"locality"
},
  "geometry": {"coordinates":[123.15516,40.18638],"type":"Point"}
}