{
  "type": "Feature",
  "properties": {
    "gn:admin1_code":"26.0",
    "gn:asciiname":"Shihuichangcun",
    "gn:country_code":"CN",
    "gn:dem":724,
    "gn:feature_class":"P",
    "gn:feature_code":"PPL",
    "gn:name":"Shihuichangcun",
    "gn:population":0,
    "gn:timezone":"Asia/Shanghai",
    "iso:country":"CN",
    "name:zho_x_preferred":[
        "\u62fe\u56de\u5382\u6751"
    ],
    "wof:name":"Shihuichangcun",
    "wof:placetype":"locality"
},
  "geometry": {"coordinates":[109.32424,34.02478],"type":"Point"}
}