{
  "type": "Feature",
  "properties": {
    "gn:admin1_code":"12.0",
    "gn:asciiname":"Zhangjiawan",
    "gn:country_code":"CN",
    "gn:dem":763,
    "gn:feature_class":"P",
    "gn:feature_code":"PPL",
    "gn:name":"Zhangjiawan",
    "gn:population":0,
    "gn:timezone":"Asia/Shanghai",
    "iso:country":"CN",
    "name:zho_x_preferred":[
        "Zhangjiawan"
    ],
    "name:zho_x_variant":[
        "\u5f20\u5bb6\u6e7e"
    ],
    "wof:name":"Zhangjiawan",
    "wof:placetype":"locality"
},
  "geometry": {"coordinates":[109.56146,29.89999000000001],"type":"Point"}
}