{
  "type": "Feature",
  "properties": {
    "gn:admin1_code":"32.0",
    "gn:asciiname":"Taipingnian",
    "gn:country_code":"CN",
    "gn:dem":600,
    "gn:feature_class":"P",
    "gn:feature_code":"PPL",
    "gn:name":"Taipingnian",
    "gn:population":0,
    "gn:timezone":"Asia/Shanghai",
    "iso:country":"CN",
    "name:zho_x_preferred":[
        "\u592a\u5e73\u57dd"
    ],
    "wof:name":"Taipingnian",
    "wof:placetype":"locality"
},
  "geometry": {"coordinates":[103.75802,30.83095],"type":"Point"}
}