{
  "type": "Feature",
  "properties": {
    "gn:admin1_code":"21.0",
    "gn:asciiname":"Zhenhe",
    "gn:country_code":"CN",
    "gn:dem":1115,
    "gn:feature_class":"P",
    "gn:feature_code":"PPL",
    "gn:name":"Zhenhe",
    "gn:population":0,
    "gn:timezone":"Asia/Shanghai",
    "iso:country":"CN",
    "name:zho_x_preferred":[
        "\u9547\u6cb3"
    ],
    "wof:name":"Zhenhe",
    "wof:placetype":"locality"
},
  "geometry": {"coordinates":[106.389,38.4494],"type":"Point"}
}