{
  "type": "Feature",
  "properties": {
    "gn:admin1_code":"32.0",
    "gn:asciiname":"Tangfangchong",
    "gn:country_code":"CN",
    "gn:dem":375,
    "gn:feature_class":"P",
    "gn:feature_code":"PPL",
    "gn:name":"Tangfangchong",
    "gn:population":0,
    "gn:timezone":"Asia/Shanghai",
    "iso:country":"CN",
    "name:zho_x_preferred":[
        "\u7cd6\u574a\u51b2"
    ],
    "wof:name":"Tangfangchong",
    "wof:placetype":"locality"
},
  "geometry": {"coordinates":[105.28700000000001,29.674],"type":"Point"}
}