{
  "type": "Feature",
  "properties": {
    "gn:admin1_code":"16.0",
    "gn:asciiname":"Xiajiaosha",
    "gn:country_code":"CN",
    "gn:dem":721,
    "gn:feature_class":"P",
    "gn:feature_code":"PPL",
    "gn:name":"Xiajiaosha",
    "gn:population":0,
    "gn:timezone":"Asia/Shanghai",
    "iso:country":"CN",
    "name:zho_x_preferred":[
        "\u4e0b\u4ea4\u6c99"
    ],
    "wof:name":"Xiajiaosha",
    "wof:placetype":"locality"
},
  "geometry": {"coordinates":[107.15900000000001,24.3624],"type":"Point"}
}