{
  "type": "Feature",
  "properties": {
    "gn:admin1_code":"3.0",
    "gn:asciiname":"Pengxi",
    "gn:country_code":"CN",
    "gn:dem":120,
    "gn:feature_class":"P",
    "gn:feature_code":"PPL",
    "gn:name":"Pengxi",
    "gn:population":0,
    "gn:timezone":"Asia/Shanghai",
    "iso:country":"CN",
    "name:und_x_variant":[
        "\u9e4f\u6eaa"
    ],
    "wof:name":"Pengxi",
    "wof:placetype":"locality"
},
  "geometry": {"coordinates":[115.50834999999999,27.46014000000001],"type":"Point"}
}