{
  "type": "Feature",
  "properties": {
    "gn:admin1_code":"26.0",
    "gn:asciiname":"Biliang",
    "gn:country_code":"CN",
    "gn:dem":1023,
    "gn:feature_class":"P",
    "gn:feature_code":"PPL",
    "gn:name":"Biliang",
    "gn:population":0,
    "gn:timezone":"Asia/Shanghai",
    "iso:country":"CN",
    "name:und_x_variant":[
        "\u9f3b\u6881"
    ],
    "wof:name":"Biliang",
    "wof:placetype":"locality"
},
  "geometry": {"coordinates":[107.01831,34.63132],"type":"Point"}
}