{
  "type": "Feature",
  "properties": {
    "gn:admin1_code":"3.0",
    "gn:asciiname":"Dajiangqiao",
    "gn:country_code":"CN",
    "gn:dem":255,
    "gn:feature_class":"P",
    "gn:feature_code":"PPL",
    "gn:name":"Dajiangqiao",
    "gn:population":0,
    "gn:timezone":"Asia/Shanghai",
    "iso:country":"CN",
    "name:und_x_variant":[
        "\u5927\u6c5f\u6865"
    ],
    "wof:name":"Dajiangqiao",
    "wof:placetype":"locality"
},
  "geometry": {"coordinates":[115.27160000000001,26.20266],"type":"Point"}
}