{
  "type": "Feature",
  "properties": {
    "gn:admin1_code":"12.0",
    "gn:asciiname":"Lanchizi",
    "gn:country_code":"CN",
    "gn:dem":1471,
    "gn:feature_class":"P",
    "gn:feature_code":"PPL",
    "gn:name":"Lanchizi",
    "gn:population":0,
    "gn:timezone":"Asia/Shanghai",
    "iso:country":"CN",
    "name:zho_x_preferred":[
        "\u70c2\u6c60\u5b50"
    ],
    "wof:name":"Lanchizi",
    "wof:placetype":"locality"
},
  "geometry": {"coordinates":[109.89779,30.72279],"type":"Point"}
}