{
  "type": "Feature",
  "properties": {
    "gn:admin1_code":"19.0",
    "gn:asciiname":"Liuxianggou",
    "gn:country_code":"CN",
    "gn:dem":491,
    "gn:feature_class":"P",
    "gn:feature_code":"PPL",
    "gn:name":"Liuxianggou",
    "gn:population":0,
    "gn:timezone":"Asia/Shanghai",
    "iso:country":"CN",
    "name:und_x_variant":[
        "\u5218\u9879\u6c9f"
    ],
    "wof:name":"Liuxianggou",
    "wof:placetype":"locality"
},
  "geometry": {"coordinates":[123.59820000000001,40.79758],"type":"Point"}
}