{
  "type": "Feature",
  "properties": {
    "gn:admin1_code":"02",
    "gn:asciiname":"Houchenlang'an",
    "gn:country_code":"CN",
    "gn:dem":6,
    "gn:feature_class":"P",
    "gn:feature_code":"PPL",
    "gn:name":"Houchenlang\u2019an",
    "gn:population":0,
    "gn:timezone":"Asia/Shanghai",
    "iso:country":"CN",
    "name:und_x_variant":[
        "Hou-ch\u2019en",
        "Houchenlang\u2019an"
    ],
    "wof:name":"Houchenlang'an",
    "wof:placetype":"locality"
},
  "geometry": {"coordinates":[121.58889000000001,29.78667],"type":"Point"}
}