{
  "type": "Feature",
  "properties": {
    "gn:admin1_code":"3.0",
    "gn:asciiname":"Ruozhukeng",
    "gn:country_code":"CN",
    "gn:dem":596,
    "gn:feature_class":"P",
    "gn:feature_code":"PPL",
    "gn:name":"Ruozhukeng",
    "gn:population":0,
    "gn:timezone":"Asia/Shanghai",
    "iso:country":"CN",
    "name:und_x_variant":[
        "\u7bac\u7af9\u5751"
    ],
    "wof:name":"Ruozhukeng",
    "wof:placetype":"locality"
},
  "geometry": {"coordinates":[115.59208999999998,25.16967],"type":"Point"}
}