{
  "type": "Feature",
  "properties": {
    "gn:admin1_code":"15.0",
    "gn:asciiname":"Luo'eryuan",
    "gn:country_code":"CN",
    "gn:dem":1463,
    "gn:feature_class":"P",
    "gn:feature_code":"PPL",
    "gn:name":"Luo\u2019eryuan",
    "gn:population":0,
    "gn:timezone":"Asia/Shanghai",
    "iso:country":"CN",
    "name:und_x_variant":[
        "Luo\u2019eryuan"
    ],
    "name:zho_x_preferred":[
        "\u7f57\u513f\u586c"
    ],
    "wof:name":"Luo'eryuan",
    "wof:placetype":"locality"
},
  "geometry": {"coordinates":[108.265,35.9408],"type":"Point"}
}