{
  "type": "Feature",
  "properties": {
    "gn:admin1_code":"4.0",
    "gn:asciiname":"Caochen",
    "gn:country_code":"CN",
    "gn:dem":4,
    "gn:feature_class":"P",
    "gn:feature_code":"PPL",
    "gn:name":"Caochen",
    "gn:population":0,
    "gn:timezone":"Asia/Shanghai",
    "iso:country":"CN",
    "name:zho_x_preferred":[
        "Caochen"
    ],
    "name:zho_x_variant":[
        "\u66f9\u9648"
    ],
    "wof:name":"Caochen",
    "wof:placetype":"locality"
},
  "geometry": {"coordinates":[121.52079999999999,31.86382],"type":"Point"}
}