{
  "type": "Feature",
  "properties": {
    "gn:admin1_code":"19.0",
    "gn:asciiname":"Shangyao",
    "gn:country_code":"CN",
    "gn:dem":284,
    "gn:feature_class":"P",
    "gn:feature_code":"PPL",
    "gn:name":"Shangyao",
    "gn:population":0,
    "gn:timezone":"Asia/Shanghai",
    "iso:country":"CN",
    "name:zho_x_preferred":[
        "\u4e0a\u7a91"
    ],
    "wof:name":"Shangyao",
    "wof:placetype":"locality"
},
  "geometry": {"coordinates":[120.351,41.32389000000001],"type":"Point"}
}