{
  "type": "Feature",
  "properties": {
    "gn:admin1_code":"19.0",
    "gn:asciiname":"Yaobeitai",
    "gn:country_code":"CN",
    "gn:dem":30,
    "gn:feature_class":"P",
    "gn:feature_code":"PPL",
    "gn:name":"Yaobeitai",
    "gn:population":0,
    "gn:timezone":"Asia/Shanghai",
    "iso:country":"CN",
    "name:und_x_variant":[
        "\u8170\u5317\u53f0"
    ],
    "name:zho_x_preferred":[
        "\u8170\u5317\u53f0"
    ],
    "wof:name":"Yaobeitai",
    "wof:placetype":"locality"
},
  "geometry": {"coordinates":[122.57348,41.90255],"type":"Point"}
}