{
  "type": "Feature",
  "properties": {
    "gn:admin1_code":"29.0",
    "gn:asciiname":"Zhaojia Yakou",
    "gn:country_code":"CN",
    "gn:dem":1908,
    "gn:feature_class":"P",
    "gn:feature_code":"PPL",
    "gn:name":"Zhaojia Yakou",
    "gn:population":0,
    "gn:timezone":"Asia/Shanghai",
    "iso:country":"CN",
    "name:zho_x_preferred":[
        "\u8d75\u5bb6\u57ad\u53e3"
    ],
    "wof:name":"Zhaojia Yakou",
    "wof:placetype":"locality"
},
  "geometry": {"coordinates":[103.676,27.4761],"type":"Point"}
}