{
  "type": "Feature",
  "properties": {
    "gn:admin1_code":"29.0",
    "gn:asciiname":"Beishanpo",
    "gn:country_code":"CN",
    "gn:dem":1458,
    "gn:feature_class":"P",
    "gn:feature_code":"PPL",
    "gn:name":"Beishanpo",
    "gn:population":0,
    "gn:timezone":"Asia/Shanghai",
    "iso:country":"CN",
    "name:zho_x_preferred":[
        "\u5317\u5c71\u5761"
    ],
    "wof:name":"Beishanpo",
    "wof:placetype":"locality"
},
  "geometry": {"coordinates":[100.55500000000001,25.8512],"type":"Point"}
}