{
  "type": "Feature",
  "properties": {
    "gn:admin1_code":"16.0",
    "gn:asciiname":"Laopanjie",
    "gn:country_code":"CN",
    "gn:dem":494,
    "gn:feature_class":"P",
    "gn:feature_code":"PPL",
    "gn:name":"Laopanjie",
    "gn:population":0,
    "gn:timezone":"Asia/Shanghai",
    "iso:country":"CN",
    "name:zho_x_preferred":[
        "\u8001\u6f58\u754c"
    ],
    "wof:name":"Laopanjie",
    "wof:placetype":"locality"
},
  "geometry": {"coordinates":[110.09699999999999,23.7557],"type":"Point"}
}