{
  "type": "Feature",
  "properties": {
    "gn:admin1_code":"29.0",
    "gn:asciiname":"Zhongyuanle",
    "gn:country_code":"CN",
    "gn:dem":2064,
    "gn:feature_class":"P",
    "gn:feature_code":"PPL",
    "gn:name":"Zhongyuanle",
    "gn:population":0,
    "gn:timezone":"Asia/Shanghai",
    "iso:country":"CN",
    "name:zho_x_preferred":[
        "\u4e2d\u5143\u4e50"
    ],
    "wof:name":"Zhongyuanle",
    "wof:placetype":"locality"
},
  "geometry": {"coordinates":[102.298,25.6744],"type":"Point"}
}