{
  "type": "Feature",
  "properties": {
    "gn:admin1_code":"15.0",
    "gn:asciiname":"Diqi",
    "gn:country_code":"CN",
    "gn:dem":2228,
    "gn:feature_class":"P",
    "gn:feature_code":"PPL",
    "gn:name":"Diqi",
    "gn:population":0,
    "gn:timezone":"Asia/Shanghai",
    "iso:country":"CN",
    "name:und_x_variant":[
        "\u5e95\u65d7"
    ],
    "wof:name":"Diqi",
    "wof:placetype":"locality"
},
  "geometry": {"coordinates":[103.84791,34.70078],"type":"Point"}
}