{
  "type": "Feature",
  "properties": {
    "gn:admin1_code":"3.0",
    "gn:asciiname":"Xiafajing",
    "gn:country_code":"CN",
    "gn:dem":91,
    "gn:feature_class":"P",
    "gn:feature_code":"PPL",
    "gn:name":"Xiafajing",
    "gn:population":0,
    "gn:timezone":"Asia/Shanghai",
    "iso:country":"CN",
    "name:und_x_variant":[
        "\u4e0b\u6cd5\u4eac"
    ],
    "wof:name":"Xiafajing",
    "wof:placetype":"locality"
},
  "geometry": {"coordinates":[117.33087999999999,29.67455],"type":"Point"}
}