{
  "type": "Feature",
  "properties": {
    "gn:admin1_code":"32.0",
    "gn:asciiname":"Luojia Wuji",
    "gn:country_code":"CN",
    "gn:dem":2101,
    "gn:feature_class":"P",
    "gn:feature_code":"PPL",
    "gn:name":"Luojia Wuji",
    "gn:population":0,
    "gn:timezone":"Asia/Shanghai",
    "iso:country":"CN",
    "name:zho_x_preferred":[
        "\u7f57\u5bb6\u5c4b\u57fa"
    ],
    "wof:name":"Luojia Wuji",
    "wof:placetype":"locality"
},
  "geometry": {"coordinates":[101.97,27.1319],"type":"Point"}
}