{
  "type": "Feature",
  "properties": {
    "gn:admin1_code":"4.0",
    "gn:asciiname":"Huayuancun",
    "gn:country_code":"CN",
    "gn:dem":39,
    "gn:feature_class":"P",
    "gn:feature_code":"PPL",
    "gn:name":"Huayuancun",
    "gn:population":0,
    "gn:timezone":"Asia/Shanghai",
    "iso:country":"CN",
    "name:zho_x_preferred":[
        "\u82b1\u56ed\u6751"
    ],
    "wof:name":"Huayuancun",
    "wof:placetype":"locality"
},
  "geometry": {"coordinates":[116.64612,34.81189000000001],"type":"Point"}
}