{
  "type": "Feature",
  "properties": {
    "gn:admin1_code":"1.0",
    "gn:asciiname":"Laowu Xiacun",
    "gn:country_code":"CN",
    "gn:dem":221,
    "gn:feature_class":"P",
    "gn:feature_code":"PPL",
    "gn:name":"Laowu Xiacun",
    "gn:population":0,
    "gn:timezone":"Asia/Shanghai",
    "iso:country":"CN",
    "name:zho_x_preferred":[
        "\u8001\u5c4b\u4e0b\u6751"
    ],
    "wof:name":"Laowu Xiacun",
    "wof:placetype":"locality"
},
  "geometry": {"coordinates":[117.03036000000002,29.69811],"type":"Point"}
}