{
  "type": "Feature",
  "properties": {
    "gn:admin1_code":"26.0",
    "gn:asciiname":"Duanjiahecun",
    "gn:country_code":"CN",
    "gn:dem":622,
    "gn:feature_class":"P",
    "gn:feature_code":"PPL",
    "gn:name":"Duanjiahecun",
    "gn:population":0,
    "gn:timezone":"Asia/Shanghai",
    "iso:country":"CN",
    "name:zho_x_preferred":[
        "\u6bb5\u5bb6\u6cb3\u6751"
    ],
    "wof:name":"Duanjiahecun",
    "wof:placetype":"locality"
},
  "geometry": {"coordinates":[110.00745000000001,35.23633],"type":"Point"}
}