{
  "type": "Feature",
  "properties": {
    "gn:admin1_code":"18",
    "gn:asciiname":"Gaotiankan",
    "gn:country_code":"CN",
    "gn:dem":927,
    "gn:feature_class":"P",
    "gn:feature_code":"PPL",
    "gn:name":"Gaotiankan",
    "gn:population":0,
    "gn:timezone":"Asia/Shanghai",
    "iso:country":"CN",
    "name:zho_x_preferred":[
        "\u9ad8\u7530\u574e"
    ],
    "wof:name":"Gaotiankan",
    "wof:placetype":"locality"
},
  "geometry": {"coordinates":[106.497,27.4758],"type":"Point"}
}