{
  "type": "Feature",
  "properties": {
    "gn:admin1_code":"18.0",
    "gn:asciiname":"Xiawengxi",
    "gn:country_code":"CN",
    "gn:dem":1144,
    "gn:feature_class":"P",
    "gn:feature_code":"PPL",
    "gn:name":"Xiawengxi",
    "gn:population":0,
    "gn:timezone":"Asia/Shanghai",
    "iso:country":"CN",
    "name:zho_x_preferred":[
        "\u4e0b\u7fc1\u6eaa"
    ],
    "wof:name":"Xiawengxi",
    "wof:placetype":"locality"
},
  "geometry": {"coordinates":[107.56,26.8957],"type":"Point"}
}