{
  "type": "Feature",
  "properties": {
    "gn:admin1_code":"5.0",
    "gn:asciiname":"Liangjingzi",
    "gn:country_code":"CN",
    "gn:dem":159,
    "gn:feature_class":"P",
    "gn:feature_code":"PPL",
    "gn:name":"Liangjingzi",
    "gn:population":0,
    "gn:timezone":"Asia/Shanghai",
    "iso:country":"CN",
    "name:zho_x_preferred":[
        "\u826f\u4e95\u5b50"
    ],
    "wof:name":"Liangjingzi",
    "wof:placetype":"locality"
},
  "geometry": {"coordinates":[122.49393999999999,44.42796],"type":"Point"}
}