{
  "type": "Feature",
  "properties": {
    "gn:admin1_code":"7",
    "gn:asciiname":"Jizaitou",
    "gn:country_code":"CN",
    "gn:dem":771,
    "gn:feature_class":"P",
    "gn:feature_code":"PPL",
    "gn:name":"Jizaitou",
    "gn:population":0,
    "gn:timezone":"Asia/Shanghai",
    "iso:country":"CN",
    "name:zho_x_preferred":[
        "\u6f08\u4ed4\u5934"
    ],
    "wof:name":"Jizaitou",
    "wof:placetype":"locality"
},
  "geometry": {"coordinates":[118.70417,25.89444],"type":"Point"}
}