{
  "type": "Feature",
  "properties": {
    "gn:admin1_code":"4.0",
    "gn:asciiname":"Wadong Yizu",
    "gn:country_code":"CN",
    "gn:dem":7,
    "gn:feature_class":"P",
    "gn:feature_code":"PPLF",
    "gn:name":"Wadong Yizu",
    "gn:population":0,
    "gn:timezone":"Asia/Shanghai",
    "iso:country":"CN",
    "name:zho_x_preferred":[
        "Wadong Yizu"
    ],
    "name:zho_x_variant":[
        "\u6d3c\u4e1c\u4e00\u7ec4"
    ],
    "wof:name":"Wadong Yizu",
    "wof:placetype":"locality"
},
  "geometry": {"coordinates":[120.94412,32.10604],"type":"Point"}
}