{
  "type": "Feature",
  "properties": {
    "gn:admin1_code":"32.0",
    "gn:asciiname":"Jiaoteng",
    "gn:country_code":"CN",
    "gn:dem":1823,
    "gn:feature_class":"P",
    "gn:feature_code":"PPL",
    "gn:name":"Jiaoteng",
    "gn:population":0,
    "gn:timezone":"Asia/Shanghai",
    "iso:country":"CN",
    "name:zho_x_preferred":[
        "\u7ede\u817e"
    ],
    "name:zho_x_variant":[
        "\u7ede\u6ed5"
    ],
    "wof:name":"Jiaoteng",
    "wof:placetype":"locality"
},
  "geometry": {"coordinates":[102.024,26.3782],"type":"Point"}
}