{
  "type": "Feature",
  "properties": {
    "gn:admin1_code":"14.0",
    "gn:asciiname":"Poinnyin",
    "gn:country_code":"CN",
    "gn:dem":4617,
    "gn:feature_class":"P",
    "gn:feature_code":"PPLF",
    "gn:name":"Poinnyin",
    "gn:population":0,
    "gn:timezone":"Asia/Urumqi",
    "iso:country":"CN",
    "name:bod_x_preferred":[
        "Poinnyin"
    ],
    "name:zho_x_preferred":[
        "Pengni"
    ],
    "name:zho_x_variant":[
        "\u5f6d\u5c3c",
        "Yangrepama",
        "\u592e\u60f9\u5e15\u739b"
    ],
    "wof:name":"Poinnyin",
    "wof:placetype":"locality"
},
  "geometry": {"coordinates":[92.706,32.206],"type":"Point"}
}