{
  "type": "Feature",
  "properties": {
    "gn:admin1_code":"9.0",
    "gn:asciiname":"Gaopeng",
    "gn:country_code":"CN",
    "gn:dem":35,
    "gn:feature_class":"P",
    "gn:feature_code":"PPL",
    "gn:name":"Gaopeng",
    "gn:population":0,
    "gn:timezone":"Asia/Shanghai",
    "iso:country":"CN",
    "name:zho_x_preferred":[
        "\u9ad8\u68da"
    ],
    "wof:name":"Gaopeng",
    "wof:placetype":"locality"
},
  "geometry": {"coordinates":[115.78313,32.25538],"type":"Point"}
}