{
  "type": "Feature",
  "properties": {
    "gn:admin1_code":"5.0",
    "gn:asciiname":"Dongshengfutun",
    "gn:country_code":"CN",
    "gn:dem":361,
    "gn:feature_class":"P",
    "gn:feature_code":"PPL",
    "gn:name":"Dongshengfutun",
    "gn:population":0,
    "gn:timezone":"Asia/Shanghai",
    "iso:country":"CN",
    "name:zho_x_preferred":[
        "\u4e1c\u751f\u798f\u5c6f"
    ],
    "wof:name":"Dongshengfutun",
    "wof:placetype":"locality"
},
  "geometry": {"coordinates":[125.904,43.09472],"type":"Point"}
}