{
  "type": "Feature",
  "properties": {
    "gn:admin1_code":"1.0",
    "gn:asciiname":"Zhaoquancun",
    "gn:country_code":"CN",
    "gn:dem":44,
    "gn:feature_class":"P",
    "gn:feature_code":"PPL",
    "gn:name":"Zhaoquancun",
    "gn:population":0,
    "gn:timezone":"Asia/Shanghai",
    "iso:country":"CN",
    "name:und_x_variant":[
        "Chao-ch\u2019\u00fcan",
        "Chao-ch\u2019\u00fcan-chai",
        "Zhaoquan",
        "Zhaoquancun"
    ],
    "name:zho_x_preferred":[
        "\u8d75\u5708\u6751"
    ],
    "wof:name":"Zhaoquancun",
    "wof:placetype":"locality"
},
  "geometry": {"coordinates":[116.64191,34.29688],"type":"Point"}
}