{
  "type": "Feature",
  "properties": {
    "gn:admin1_code":"6.0",
    "gn:asciiname":"Xiongxian",
    "gn:country_code":"CN",
    "gn:dem":3207,
    "gn:feature_class":"P",
    "gn:feature_code":"PPL",
    "gn:name":"Xiongxian",
    "gn:population":0,
    "gn:timezone":"Asia/Shanghai",
    "iso:country":"CN",
    "wof:name":"Xiongxian",
    "wof:placetype":"locality"
},
  "geometry": {"coordinates":[101.78333000000001,36.26667],"type":"Point"}
}