{
  "type": "Feature",
  "properties": {
    "gn:admin1_code":"2.0",
    "gn:asciiname":"Shita Ercun",
    "gn:country_code":"CN",
    "gn:dem":50,
    "gn:feature_class":"P",
    "gn:feature_code":"PPL",
    "gn:name":"Shita Ercun",
    "gn:population":0,
    "gn:timezone":"Asia/Shanghai",
    "iso:country":"CN",
    "name:zho_x_preferred":[
        "\u77f3\u5854\u4e8c\u6751"
    ],
    "wof:name":"Shita Ercun",
    "wof:placetype":"locality"
},
  "geometry": {"coordinates":[119.96692,29.25909],"type":"Point"}
}