{
  "type": "Feature",
  "properties": {
    "gn:admin1_code":"30.0",
    "gn:asciiname":"Benji",
    "gn:country_code":"CN",
    "gn:dem":59,
    "gn:feature_class":"P",
    "gn:feature_code":"PPL",
    "gn:name":"Benji",
    "gn:population":0,
    "gn:timezone":"Asia/Shanghai",
    "iso:country":"CN",
    "name:bul_x_preferred":[
        "\u0411\u0435\u043d\u0434\u0436\u0438"
    ],
    "name:fra_x_preferred":[
        "Benji"
    ],
    "name:hun_x_preferred":[
        "Bendzsi"
    ],
    "name:por_x_preferred":[
        "Benji"
    ],
    "name:zho_x_preferred":[
        "\u672c\u5409"
    ],
    "wof:name":"Benji",
    "wof:placetype":"locality"
},
  "geometry": {"coordinates":[112.06041,23.91662],"type":"Point"}
}