{
  "type": "Feature",
  "properties": {
    "gn:admin1_code":"19.0",
    "gn:asciiname":"Pandaogou",
    "gn:country_code":"CN",
    "gn:dem":108,
    "gn:feature_class":"P",
    "gn:feature_code":"PPL",
    "gn:name":"Pandaogou",
    "gn:population":0,
    "gn:timezone":"Asia/Shanghai",
    "iso:country":"CN",
    "name:zho_x_preferred":[
        "\u76d8\u9053\u6c9f"
    ],
    "wof:name":"Pandaogou",
    "wof:placetype":"locality"
},
  "geometry": {"coordinates":[120.81842,40.90449],"type":"Point"}
}