{
  "type": "Feature",
  "properties": {
    "iso:country":"CN",
    "qs:name":"\u8bf8\u66a8",
    "qs:name_adm0":"\u4e2d\u570b",
    "qs:name_adm1":"\u6d59\u6c5f\u7701",
    "qs:photos":509,
    "qs:photos_1k":103,
    "qs:photos_9k":2,
    "qs:photos_9r":5,
    "qs:photos_all":509,
    "qs:photos_sr":7,
    "qs:placetype":"Town",
    "qs:pop_sr":"0",
    "wof:name":"\u8bf8\u66a8",
    "wof:placetype":"locality"
},
  "geometry": {"coordinates":[120.238838,29.712208],"type":"Point"}
}