{
  "type": "Feature",
  "properties": {
    "gn:admin1_code":"1.0",
    "gn:asciiname":"Dongmenloucun",
    "gn:country_code":"CN",
    "gn:dem":42,
    "gn:feature_class":"P",
    "gn:feature_code":"PPL",
    "gn:name":"Dongmenloucun",
    "gn:population":0,
    "gn:timezone":"Asia/Shanghai",
    "iso:country":"CN",
    "name:zho_x_preferred":[
        "\u8463\u95e8\u697c\u6751"
    ],
    "wof:name":"Dongmenloucun",
    "wof:placetype":"locality"
},
  "geometry": {"coordinates":[115.73932000000001,34.01111],"type":"Point"}
}