{
  "type": "Feature",
  "properties": {
    "gn:admin1_code":"19.0",
    "gn:asciiname":"Mijia Wobu",
    "gn:country_code":"CN",
    "gn:dem":169,
    "gn:feature_class":"P",
    "gn:feature_code":"PPL",
    "gn:name":"Mijia Wobu",
    "gn:population":0,
    "gn:timezone":"Asia/Shanghai",
    "iso:country":"CN",
    "name:und_x_variant":[
        "Mijiawobao",
        "\u7c73\u5bb6\u7a9d\u5821",
        "Mijia Wobu"
    ],
    "name:zho_x_preferred":[
        "\u7c73\u5bb6\u7a9d\u5821"
    ],
    "wof:name":"Mijia Wobu",
    "wof:placetype":"locality"
},
  "geometry": {"coordinates":[121.75489,42.03741],"type":"Point"}
}