{
  "type": "Feature",
  "properties": {
    "gn:admin1_code":"11",
    "gn:asciiname":"Lijialing",
    "gn:country_code":"CN",
    "gn:dem":184,
    "gn:feature_class":"P",
    "gn:feature_code":"PPL",
    "gn:name":"Lijialing",
    "gn:population":0,
    "gn:timezone":"Asia/Shanghai",
    "iso:country":"CN",
    "name:und_x_variant":[
        "\u674e\u5bb6\u5cad",
        "Lijialing"
    ],
    "wof:name":"Lijialing",
    "wof:placetype":"locality"
},
  "geometry": {"coordinates":[111.71333,25.74583],"type":"Point"}
}