{
  "type": "Feature",
  "properties": {
    "gn:admin1_code":"19.0",
    "gn:asciiname":"Tianshuigoucun",
    "gn:country_code":"CN",
    "gn:dem":593,
    "gn:feature_class":"P",
    "gn:feature_code":"PPL",
    "gn:name":"Tianshuigoucun",
    "gn:population":0,
    "gn:timezone":"Asia/Shanghai",
    "iso:country":"CN",
    "name:zho_x_preferred":[
        "\u751c\u6c34\u6c9f\u6751"
    ],
    "wof:name":"Tianshuigoucun",
    "wof:placetype":"locality"
},
  "geometry": {"coordinates":[119.59092,41.28475],"type":"Point"}
}