{
  "type": "Feature",
  "properties": {
    "gn:admin1_code":"8.0",
    "gn:asciiname":"Fanshencun",
    "gn:country_code":"CN",
    "gn:dem":133,
    "gn:feature_class":"P",
    "gn:feature_code":"PPL",
    "gn:name":"Fanshencun",
    "gn:population":0,
    "gn:timezone":"Asia/Shanghai",
    "iso:country":"CN",
    "name:zho_x_preferred":[
        "\u7ffb\u8eab\u6751"
    ],
    "wof:name":"Fanshencun",
    "wof:placetype":"locality"
},
  "geometry": {"coordinates":[124.12241000000002,46.07306],"type":"Point"}
}