{
  "type": "Feature",
  "properties": {
    "gn:admin1_code":"22.0",
    "gn:asciiname":"Xiaotuncun",
    "gn:country_code":"CN",
    "gn:dem":26,
    "gn:feature_class":"P",
    "gn:feature_code":"PPL",
    "gn:name":"Xiaotuncun",
    "gn:population":0,
    "gn:timezone":"Asia/Shanghai",
    "iso:country":"CN",
    "name:zho_x_preferred":[
        "\u5c0f\u5c6f\u6751"
    ],
    "wof:name":"Xiaotuncun",
    "wof:placetype":"locality"
},
  "geometry": {"coordinates":[117.01255999999999,40.06312],"type":"Point"}
}