{
  "type": "Feature",
  "properties": {
    "gn:admin1_code":"4.0",
    "gn:asciiname":"Zhongjia Qiancun",
    "gn:country_code":"CN",
    "gn:dem":7,
    "gn:feature_class":"P",
    "gn:feature_code":"PPL",
    "gn:name":"Zhongjia Qiancun",
    "gn:population":0,
    "gn:timezone":"Asia/Shanghai",
    "iso:country":"CN",
    "name:zho_x_preferred":[
        "\u4e2d\u5bb6\u524d\u6751"
    ],
    "wof:name":"Zhongjia Qiancun",
    "wof:placetype":"locality"
},
  "geometry": {"coordinates":[119.8721,32.05041],"type":"Point"}
}