{
  "type": "Feature",
  "properties": {
    "gn:admin1_code":"8.0",
    "gn:asciiname":"Dayanjia Wopeng",
    "gn:country_code":"CN",
    "gn:dem":175,
    "gn:feature_class":"P",
    "gn:feature_code":"PPL",
    "gn:name":"Dayanjia Wopeng",
    "gn:population":0,
    "gn:timezone":"Asia/Shanghai",
    "iso:country":"CN",
    "name:zho_x_preferred":[
        "\u5927\u960e\u5bb6\u7a9d\u68da"
    ],
    "wof:name":"Dayanjia Wopeng",
    "wof:placetype":"locality"
},
  "geometry": {"coordinates":[126.94109,47.06681],"type":"Point"}
}