{
  "type": "Feature",
  "properties": {
    "gn:admin1_code":"11.0",
    "gn:asciiname":"Datangxu",
    "gn:country_code":"CN",
    "gn:dem":358,
    "gn:feature_class":"P",
    "gn:feature_code":"PPL",
    "gn:name":"Datangxu",
    "gn:population":0,
    "gn:timezone":"Asia/Shanghai",
    "iso:country":"CN",
    "name:zho_x_preferred":[
        "\u5927\u5858\u5729"
    ],
    "wof:name":"Datangxu",
    "wof:placetype":"locality"
},
  "geometry": {"coordinates":[112.57974,25.59264],"type":"Point"}
}