{
  "type": "Feature",
  "properties": {
    "gn:admin1_code":"29.0",
    "gn:asciiname":"Yanzipo",
    "gn:country_code":"CN",
    "gn:dem":1737,
    "gn:feature_class":"P",
    "gn:feature_code":"PPL",
    "gn:name":"Yanzipo",
    "gn:population":0,
    "gn:timezone":"Asia/Shanghai",
    "iso:country":"CN",
    "name:zho_x_preferred":[
        "\u5ca9\u5b50\u5761"
    ],
    "wof:name":"Yanzipo",
    "wof:placetype":"locality"
},
  "geometry": {"coordinates":[97.73399999999999,24.6284],"type":"Point"}
}