{
  "type": "Feature",
  "properties": {
    "gn:admin1_code":"1.0",
    "gn:asciiname":"Wuzhaicun",
    "gn:country_code":"CN",
    "gn:dem":30,
    "gn:feature_class":"P",
    "gn:feature_code":"PPL",
    "gn:name":"Wuzhaicun",
    "gn:population":0,
    "gn:timezone":"Asia/Shanghai",
    "iso:country":"CN",
    "name:zho_x_preferred":[
        "\u5434\u5be8\u6751"
    ],
    "wof:name":"Wuzhaicun",
    "wof:placetype":"locality"
},
  "geometry": {"coordinates":[116.42673000000001,33.49554000000001],"type":"Point"}
}