{
  "type": "Feature",
  "properties": {
    "gn:admin1_code":"30",
    "gn:asciiname":"Leidashi",
    "gn:country_code":"CN",
    "gn:dem":153,
    "gn:feature_class":"P",
    "gn:feature_code":"PPL",
    "gn:name":"Leidashi",
    "gn:population":0,
    "gn:timezone":"Asia/Shanghai",
    "iso:country":"CN",
    "name:und_x_variant":[
        "Leibeishi",
        "Leidashi"
    ],
    "name:zho_x_preferred":[
        "\u96f7\u6253\u77f3"
    ],
    "wof:name":"Leidashi",
    "wof:placetype":"locality"
},
  "geometry": {"coordinates":[115.75463000000001,23.28189],"type":"Point"}
}