{
  "type": "Feature",
  "properties": {
    "gn:admin1_code":"8.0",
    "gn:asciiname":"Huoxing Zhongzidui",
    "gn:country_code":"CN",
    "gn:dem":153,
    "gn:feature_class":"P",
    "gn:feature_code":"PPLF",
    "gn:name":"Huoxing Zhongzidui",
    "gn:population":0,
    "gn:timezone":"Asia/Shanghai",
    "iso:country":"CN",
    "name:zho_x_preferred":[
        "\u706b\u661f\u79cd\u5b50\u961f"
    ],
    "wof:name":"Huoxing Zhongzidui",
    "wof:placetype":"locality"
},
  "geometry": {"coordinates":[125.48589,46.34032],"type":"Point"}
}