{
  "type": "Feature",
  "properties": {
    "gn:admin1_code":"25",
    "gn:asciiname":"Yushui",
    "gn:country_code":"CN",
    "gn:dem":361,
    "gn:feature_class":"P",
    "gn:feature_code":"PPL",
    "gn:name":"Yushui",
    "gn:population":0,
    "gn:timezone":"Asia/Shanghai",
    "iso:country":"CN",
    "name:ceb_x_preferred":[
        "Yushui"
    ],
    "name:fra_x_preferred":[
        "Yushui"
    ],
    "name:zho_x_preferred":[
        "\u7389\u6c34"
    ],
    "wof:name":"Yushui",
    "wof:placetype":"locality"
},
  "geometry": {"coordinates":[117.16800000000001,36.4631],"type":"Point"}
}