{
  "type": "Feature",
  "properties": {
    "gn:admin1_code":"32.0",
    "gn:asciiname":"Masangping",
    "gn:country_code":"CN",
    "gn:dem":1457,
    "gn:feature_class":"P",
    "gn:feature_code":"PPL",
    "gn:name":"Masangping",
    "gn:population":0,
    "gn:timezone":"Asia/Shanghai",
    "iso:country":"CN",
    "name:zho_x_preferred":[
        "\u9a6c\u6851\u576a"
    ],
    "wof:name":"Masangping",
    "wof:placetype":"locality"
},
  "geometry": {"coordinates":[103.273,27.7194],"type":"Point"}
}