{
  "type": "Feature",
  "properties": {
    "gn:admin1_code":"16.0",
    "gn:asciiname":"Nabao",
    "gn:country_code":"CN",
    "gn:dem":135,
    "gn:feature_class":"P",
    "gn:feature_code":"PPL",
    "gn:name":"Nabao",
    "gn:population":0,
    "gn:timezone":"Asia/Shanghai",
    "iso:country":"CN",
    "name:ceb_x_preferred":[
        "Nabao"
    ],
    "name:swe_x_preferred":[
        "Nabao"
    ],
    "name:zho_x_preferred":[
        "\u90a3\u5305"
    ],
    "wof:name":"Nabao",
    "wof:placetype":"locality"
},
  "geometry": {"coordinates":[108.267,22.0765],"type":"Point"}
}