{
  "type": "Feature",
  "properties": {
    "gn:admin1_code":"02",
    "gn:asciiname":"Xi'ancun",
    "gn:country_code":"CN",
    "gn:dem":7,
    "gn:feature_class":"P",
    "gn:feature_code":"PPL",
    "gn:name":"Xi\u2019ancun",
    "gn:population":0,
    "gn:timezone":"Asia/Shanghai",
    "iso:country":"CN",
    "name:und_x_variant":[
        "\u897f\u5cb8",
        "Xi\u2019ancun"
    ],
    "name:zho_x_preferred":[
        "Xi\u2019an"
    ],
    "name:zho_x_variant":[
        "\u897f\u5cb8",
        "\u897f\u5cb8\u6751"
    ],
    "wof:name":"Xi'ancun",
    "wof:placetype":"locality"
},
  "geometry": {"coordinates":[121.5218,28.73597],"type":"Point"}
}