{
  "type": "Feature",
  "properties": {
    "gn:admin1_code":"10.0",
    "gn:asciiname":"Xixianzi",
    "gn:country_code":"CN",
    "gn:dem":962,
    "gn:feature_class":"P",
    "gn:feature_code":"PPL",
    "gn:name":"Xixianzi",
    "gn:population":0,
    "gn:timezone":"Asia/Shanghai",
    "iso:country":"CN",
    "name:zho_x_preferred":[
        "\u7ec6\u5f26\u5b50"
    ],
    "wof:name":"Xixianzi",
    "wof:placetype":"locality"
},
  "geometry": {"coordinates":[114.69823999999998,40.1798],"type":"Point"}
}