{
  "type": "Feature",
  "properties": {
    "gn:admin1_code":"9.0",
    "gn:asciiname":"Houtongshan",
    "gn:country_code":"CN",
    "gn:dem":64,
    "gn:feature_class":"P",
    "gn:feature_code":"PPL",
    "gn:name":"Houtongshan",
    "gn:population":0,
    "gn:timezone":"Asia/Shanghai",
    "iso:country":"CN",
    "name:zho_x_preferred":[
        "\u540e\u540c\u5c71"
    ],
    "wof:name":"Houtongshan",
    "wof:placetype":"locality"
},
  "geometry": {"coordinates":[114.37802000000001,35.6145],"type":"Point"}
}