{
  "type": "Feature",
  "properties": {
    "gn:admin1_code":"11",
    "gn:asciiname":"Zaoshuling",
    "gn:country_code":"CN",
    "gn:dem":96,
    "gn:feature_class":"P",
    "gn:feature_code":"PPL",
    "gn:name":"Zaoshuling",
    "gn:population":0,
    "gn:timezone":"Asia/Shanghai",
    "iso:country":"CN",
    "name:zho_x_preferred":[
        "\u67a3\u6811\u5cad"
    ],
    "wof:name":"Zaoshuling",
    "wof:placetype":"locality"
},
  "geometry": {"coordinates":[111.84448,26.61367000000001],"type":"Point"}
}