{
  "type": "Feature",
  "properties": {
    "gn:admin1_code":"24",
    "gn:asciiname":"Tanjia",
    "gn:country_code":"CN",
    "gn:dem":346,
    "gn:feature_class":"P",
    "gn:feature_code":"PPL",
    "gn:name":"Tanjia",
    "gn:population":0,
    "gn:timezone":"Asia/Shanghai",
    "iso:country":"CN",
    "name:und_x_variant":[
        "T\u2019an-chia",
        "T\u2019an-chia-ts\u2019un",
        "Tanjia"
    ],
    "name:zho_x_preferred":[
        "\u8c2d\u5bb6"
    ],
    "wof:name":"Tanjia",
    "wof:placetype":"locality"
},
  "geometry": {"coordinates":[111.90053,35.18031],"type":"Point"}
}