{
  "type": "Feature",
  "properties": {
    "gn:admin1_code":"5.0",
    "gn:asciiname":"Houtaipingshan",
    "gn:country_code":"CN",
    "gn:dem":134,
    "gn:feature_class":"P",
    "gn:feature_code":"PPL",
    "gn:name":"Houtaipingshan",
    "gn:population":0,
    "gn:timezone":"Asia/Shanghai",
    "iso:country":"CN",
    "name:zho_x_preferred":[
        "\u540e\u592a\u5e73\u5c71"
    ],
    "wof:name":"Houtaipingshan",
    "wof:placetype":"locality"
},
  "geometry": {"coordinates":[124.13484,45.44607],"type":"Point"}
}