{
  "type": "Feature",
  "properties": {
    "gn:admin1_code":"7.0",
    "gn:asciiname":"Shunxiyang",
    "gn:country_code":"CN",
    "gn:dem":182,
    "gn:feature_class":"P",
    "gn:feature_code":"PPL",
    "gn:name":"Shunxiyang",
    "gn:population":0,
    "gn:timezone":"Asia/Shanghai",
    "iso:country":"CN",
    "name:zho_x_preferred":[
        "\u987a\u6eaa\u6d0b"
    ],
    "wof:name":"Shunxiyang",
    "wof:placetype":"locality"
},
  "geometry": {"coordinates":[117.85242,26.42046],"type":"Point"}
}