{
  "type": "Feature",
  "properties": {
    "gn:admin1_code":"11.0",
    "gn:asciiname":"Nanhetou",
    "gn:country_code":"CN",
    "gn:dem":31,
    "gn:feature_class":"P",
    "gn:feature_code":"PPL",
    "gn:name":"Nanhetou",
    "gn:population":0,
    "gn:timezone":"Asia/Shanghai",
    "iso:country":"CN",
    "name:zho_x_preferred":[
        "\u5357\u6cb3\u5934"
    ],
    "wof:name":"Nanhetou",
    "wof:placetype":"locality"
},
  "geometry": {"coordinates":[112.56811,29.25867],"type":"Point"}
}