{
  "type": "Feature",
  "properties": {
    "gn:admin1_code":"9.0",
    "gn:asciiname":"Youli",
    "gn:country_code":"CN",
    "gn:dem":79,
    "gn:feature_class":"P",
    "gn:feature_code":"PPL",
    "gn:name":"Youli",
    "gn:population":0,
    "gn:timezone":"Asia/Shanghai",
    "iso:country":"CN",
    "name:zho_x_preferred":[
        "\u5c24\u91cc"
    ],
    "wof:name":"Youli",
    "wof:placetype":"locality"
},
  "geometry": {"coordinates":[113.87944,34.16172],"type":"Point"}
}