{
  "type": "Feature",
  "properties": {
    "gn:admin1_code":"16.0",
    "gn:asciiname":"Xiaoyaoshan",
    "gn:country_code":"CN",
    "gn:dem":1496,
    "gn:feature_class":"P",
    "gn:feature_code":"PPL",
    "gn:name":"Xiaoyaoshan",
    "gn:population":0,
    "gn:timezone":"Asia/Shanghai",
    "iso:country":"CN",
    "name:zho_x_preferred":[
        "\u5c0f\u7476\u5c71"
    ],
    "wof:name":"Xiaoyaoshan",
    "wof:placetype":"locality"
},
  "geometry": {"coordinates":[106.384,24.6237],"type":"Point"}
}