{
  "type": "Feature",
  "properties": {
    "gn:admin1_code":"15.0",
    "gn:asciiname":"Hejiatan",
    "gn:country_code":"CN",
    "gn:dem":1927,
    "gn:feature_class":"P",
    "gn:feature_code":"PPL",
    "gn:name":"Hejiatan",
    "gn:population":0,
    "gn:timezone":"Asia/Shanghai",
    "iso:country":"CN",
    "name:zho_x_preferred":[
        "\u4f55\u5bb6\u6ee9"
    ],
    "wof:name":"Hejiatan",
    "wof:placetype":"locality"
},
  "geometry": {"coordinates":[103.84,37.2009],"type":"Point"}
}