{
  "type": "Feature",
  "properties": {
    "gn:admin1_code":"4.0",
    "gn:asciiname":"Zhaoheya",
    "gn:country_code":"CN",
    "gn:dem":43,
    "gn:feature_class":"P",
    "gn:feature_code":"PPL",
    "gn:name":"Zhaoheya",
    "gn:population":0,
    "gn:timezone":"Asia/Shanghai",
    "iso:country":"CN",
    "name:zho_x_preferred":[
        "\u8d75\u6cb3\u6daf"
    ],
    "wof:name":"Zhaoheya",
    "wof:placetype":"locality"
},
  "geometry": {"coordinates":[116.63,34.6393],"type":"Point"}
}