{
  "type": "Feature",
  "properties": {
    "gn:admin1_code":"21.0",
    "gn:asciiname":"Bajiafang",
    "gn:country_code":"CN",
    "gn:dem":1133,
    "gn:feature_class":"P",
    "gn:feature_code":"PPL",
    "gn:name":"Bajiafang",
    "gn:population":0,
    "gn:timezone":"Asia/Shanghai",
    "iso:country":"CN",
    "name:zho_x_preferred":[
        "\u516b\u5bb6\u574a"
    ],
    "wof:name":"Bajiafang",
    "wof:placetype":"locality"
},
  "geometry": {"coordinates":[106.20099999999999,37.9744],"type":"Point"}
}