{
  "type": "Feature",
  "properties": {
    "gn:admin1_code":"26.0",
    "gn:asciiname":"Yulinqiaocun",
    "gn:country_code":"CN",
    "gn:dem":958,
    "gn:feature_class":"P",
    "gn:feature_code":"PPL",
    "gn:name":"Yulinqiaocun",
    "gn:population":0,
    "gn:timezone":"Asia/Shanghai",
    "iso:country":"CN",
    "name:zho_x_preferred":[
        "\u6986\u6797\u6865\u6751"
    ],
    "wof:name":"Yulinqiaocun",
    "wof:placetype":"locality"
},
  "geometry": {"coordinates":[109.38500000000001,36.0618],"type":"Point"}
}