{
  "type": "Feature",
  "properties": {
    "gn:admin1_code":"11.0",
    "gn:asciiname":"Shamuling",
    "gn:country_code":"CN",
    "gn:dem":320,
    "gn:feature_class":"P",
    "gn:feature_code":"PPL",
    "gn:name":"Shamuling",
    "gn:population":0,
    "gn:timezone":"Asia/Shanghai",
    "iso:country":"CN",
    "name:zho_x_preferred":[
        "\u6749\u6728\u5cad"
    ],
    "wof:name":"Shamuling",
    "wof:placetype":"locality"
},
  "geometry": {"coordinates":[113.47226000000001,26.2684],"type":"Point"}
}