{
  "type": "Feature",
  "properties": {
    "gn:admin1_code":"29",
    "gn:asciiname":"Dazhuangba",
    "gn:country_code":"CN",
    "gn:dem":1624,
    "gn:feature_class":"P",
    "gn:feature_code":"PPL",
    "gn:name":"Dazhuangba",
    "gn:population":0,
    "gn:timezone":"Asia/Shanghai",
    "iso:country":"CN",
    "name:zho_x_preferred":[
        "\u5927\u5e84\u575d"
    ],
    "wof:name":"Dazhuangba",
    "wof:placetype":"locality"
},
  "geometry": {"coordinates":[103.28838,24.06351],"type":"Point"}
}