{
  "type": "Feature",
  "properties": {
    "gn:admin1_code":"14.0",
    "gn:asciiname":"Queding",
    "gn:country_code":"CN",
    "gn:dem":4470,
    "gn:feature_class":"P",
    "gn:feature_code":"PPL",
    "gn:name":"Queding",
    "gn:population":0,
    "gn:timezone":"Asia/Shanghai",
    "iso:country":"CN",
    "name:und_x_variant":[
        "Qiao\u2019erdun",
        "Queding"
    ],
    "name:zho_x_preferred":[
        "\u4e54\u5c14\u58a9"
    ],
    "name:zho_x_variant":[
        "\u5374\u5b9a"
    ],
    "wof:name":"Queding",
    "wof:placetype":"locality"
},
  "geometry": {"coordinates":[79.89245,32.85799],"type":"Point"}
}