{
  "type": "Feature",
  "properties": {
    "gn:admin1_code":"9.0",
    "gn:asciiname":"Xitan",
    "gn:country_code":"CN",
    "gn:dem":134,
    "gn:feature_class":"P",
    "gn:feature_code":"PPL",
    "gn:name":"Xitan",
    "gn:population":0,
    "gn:timezone":"Asia/Shanghai",
    "iso:country":"CN",
    "name:zho_x_preferred":[
        "\u897f\u6ee9"
    ],
    "wof:name":"Xitan",
    "wof:placetype":"locality"
},
  "geometry": {"coordinates":[112.48771000000001,34.9103],"type":"Point"}
}