{
  "type": "Feature",
  "properties": {
    "gn:admin1_code":"26.0",
    "gn:asciiname":"Wanghuajiagoucun",
    "gn:country_code":"CN",
    "gn:dem":1027,
    "gn:feature_class":"P",
    "gn:feature_code":"PPL",
    "gn:name":"Wanghuajiagoucun",
    "gn:population":0,
    "gn:timezone":"Asia/Shanghai",
    "iso:country":"CN",
    "name:zho_x_preferred":[
        "\u738b\u5316\u5bb6\u6c9f\u6751"
    ],
    "wof:name":"Wanghuajiagoucun",
    "wof:placetype":"locality"
},
  "geometry": {"coordinates":[110.04474999999999,37.18168],"type":"Point"}
}