{
  "type": "Feature",
  "properties": {
    "gn:admin1_code":"19.0",
    "gn:asciiname":"Xiaoshenjinhua",
    "gn:country_code":"CN",
    "gn:dem":100,
    "gn:feature_class":"P",
    "gn:feature_code":"PPL",
    "gn:name":"Xiaoshenjinhua",
    "gn:population":0,
    "gn:timezone":"Asia/Shanghai",
    "iso:country":"CN",
    "name:zho_x_preferred":[
        "\u5c0f\u7533\u91d1\u82b1"
    ],
    "wof:name":"Xiaoshenjinhua",
    "wof:placetype":"locality"
},
  "geometry": {"coordinates":[122.238,42.3539],"type":"Point"}
}