{
  "type": "Feature",
  "properties": {
    "gn:admin1_code":"22.0",
    "gn:asciiname":"Wangyucun",
    "gn:country_code":"CN",
    "gn:dem":239,
    "gn:feature_class":"P",
    "gn:feature_code":"PPL",
    "gn:name":"Wangyucun",
    "gn:population":0,
    "gn:timezone":"Asia/Shanghai",
    "iso:country":"CN",
    "name:zho_x_preferred":[
        "\u738b\u5cea\u6751"
    ],
    "wof:name":"Wangyucun",
    "wof:placetype":"locality"
},
  "geometry": {"coordinates":[116.00802,40.15738],"type":"Point"}
}