{
  "type": "Feature",
  "properties": {
    "gn:admin1_code":"12.0",
    "gn:asciiname":"Caochitang",
    "gn:country_code":"CN",
    "gn:dem":1437,
    "gn:feature_class":"P",
    "gn:feature_code":"PPL",
    "gn:name":"Caochitang",
    "gn:population":0,
    "gn:timezone":"Asia/Shanghai",
    "iso:country":"CN",
    "name:zho_x_preferred":[
        "\u8349\u6c60\u5858"
    ],
    "wof:name":"Caochitang",
    "wof:placetype":"locality"
},
  "geometry": {"coordinates":[110.29761000000001,30.48486],"type":"Point"}
}