{
  "type": "Feature",
  "properties": {
    "gn:admin1_code":"22.0",
    "gn:asciiname":"Zhuanghugoumen",
    "gn:country_code":"CN",
    "gn:dem":332,
    "gn:feature_class":"P",
    "gn:feature_code":"PPL",
    "gn:name":"Zhuanghugoumen",
    "gn:population":0,
    "gn:timezone":"Asia/Shanghai",
    "iso:country":"CN",
    "name:zho_x_preferred":[
        "\u5e84\u6237\u6c9f\u95e8"
    ],
    "wof:name":"Zhuanghugoumen",
    "wof:placetype":"locality"
},
  "geometry": {"coordinates":[116.62067,40.73285],"type":"Point"}
}