{
  "type": "Feature",
  "properties": {
    "gn:admin1_code":"02",
    "gn:asciiname":"Hsu-p'an-ch'iao",
    "gn:country_code":"CN",
    "gn:dem":10,
    "gn:feature_class":"P",
    "gn:feature_code":"PPL",
    "gn:name":"Hs\u00fc-p\u2019an-ch\u2019iao",
    "gn:population":0,
    "gn:timezone":"Asia/Shanghai",
    "iso:country":"CN",
    "wof:name":"Hsu-p'an-ch'iao",
    "wof:placetype":"locality"
},
  "geometry": {"coordinates":[121.205,30.05278],"type":"Point"}
}