{
  "type": "Feature",
  "properties": {
    "gn:admin1_code":"22",
    "gn:asciiname":"Ciqu",
    "gn:country_code":"CN",
    "gn:dem":30,
    "gn:feature_class":"P",
    "gn:feature_code":"PPL",
    "gn:name":"Ciqu",
    "gn:population":0,
    "gn:timezone":"Asia/Shanghai",
    "iso:country":"CN",
    "name:zho_x_preferred":[
        "\u6b21\u6e20"
    ],
    "wof:name":"Ciqu",
    "wof:placetype":"locality"
},
  "geometry": {"coordinates":[116.58343000000001,39.80448],"type":"Point"}
}