{
  "type": "Feature",
  "properties": {
    "gn:admin1_code":"16",
    "gn:asciiname":"Muqiao",
    "gn:country_code":"CN",
    "gn:dem":121,
    "gn:feature_class":"P",
    "gn:feature_code":"PPL",
    "gn:name":"Muqiao",
    "gn:population":0,
    "gn:timezone":"Asia/Shanghai",
    "iso:country":"CN",
    "name:zho_x_preferred":[
        "\u6728\u6865"
    ],
    "wof:name":"Muqiao",
    "wof:placetype":"locality"
},
  "geometry": {"coordinates":[110.55800000000001,24.7292],"type":"Point"}
}