{
  "type": "Feature",
  "properties": {
    "gn:admin1_code":"26.0",
    "gn:asciiname":"Diaoyutaicun",
    "gn:country_code":"CN",
    "gn:dem":1499,
    "gn:feature_class":"P",
    "gn:feature_code":"PPL",
    "gn:name":"Diaoyutaicun",
    "gn:population":0,
    "gn:timezone":"Asia/Shanghai",
    "iso:country":"CN",
    "name:und_x_variant":[
        "\u9493\u9c7c\u53f0\u6751"
    ],
    "wof:name":"Diaoyutaicun",
    "wof:placetype":"locality"
},
  "geometry": {"coordinates":[107.78112,33.8439],"type":"Point"}
}