{
  "type": "Feature",
  "properties": {
    "gn:admin1_code":"3.0",
    "gn:asciiname":"Yang'ao",
    "gn:country_code":"CN",
    "gn:dem":122,
    "gn:feature_class":"P",
    "gn:feature_code":"PPL",
    "gn:name":"Yang\u2019ao",
    "gn:population":0,
    "gn:timezone":"Asia/Shanghai",
    "iso:country":"CN",
    "name:und_x_variant":[
        "Yang\u2019ao",
        "\u6d0b\u5773"
    ],
    "wof:name":"Yang'ao",
    "wof:placetype":"locality"
},
  "geometry": {"coordinates":[115.67775,27.38246],"type":"Point"}
}