{
  "type": "Feature",
  "properties": {
    "gn:admin1_code":"1.0",
    "gn:asciiname":"Wazhangcun",
    "gn:country_code":"CN",
    "gn:dem":24,
    "gn:feature_class":"P",
    "gn:feature_code":"PPL",
    "gn:name":"Wazhangcun",
    "gn:population":0,
    "gn:timezone":"Asia/Shanghai",
    "iso:country":"CN",
    "name:zho_x_preferred":[
        "\u6d3c\u5f20\u6751"
    ],
    "wof:name":"Wazhangcun",
    "wof:placetype":"locality"
},
  "geometry": {"coordinates":[117.38415000000001,32.87665],"type":"Point"}
}