{
  "type": "Feature",
  "properties": {
    "gn:admin1_code":"14.0",
    "gn:asciiname":"Gunzhubacun",
    "gn:country_code":"CN",
    "gn:dem":3353,
    "gn:feature_class":"P",
    "gn:feature_code":"PPL",
    "gn:name":"Gunzhubacun",
    "gn:population":0,
    "gn:timezone":"Asia/Urumqi",
    "iso:country":"CN",
    "name:zho_x_preferred":[
        "\u6eda\u4e3b\u5df4\u6751"
    ],
    "wof:name":"Gunzhubacun",
    "wof:placetype":"locality"
},
  "geometry": {"coordinates":[92.51179,29.14208],"type":"Point"}
}