{
  "type": "Feature",
  "properties": {
    "gn:admin1_code":"4.0",
    "gn:asciiname":"Miaodaokou",
    "gn:country_code":"CN",
    "gn:dem":39,
    "gn:feature_class":"P",
    "gn:feature_code":"PPL",
    "gn:name":"Miaodaokou",
    "gn:population":0,
    "gn:timezone":"Asia/Shanghai",
    "iso:country":"CN",
    "name:zho_x_preferred":[
        "\u5e99\u9053\u53e3"
    ],
    "wof:name":"Miaodaokou",
    "wof:placetype":"locality"
},
  "geometry": {"coordinates":[116.85599999999999,34.8615],"type":"Point"}
}