{
  "type": "Feature",
  "properties": {
    "gn:admin1_code":"9.0",
    "gn:asciiname":"Yanlinggou",
    "gn:country_code":"CN",
    "gn:dem":319,
    "gn:feature_class":"P",
    "gn:feature_code":"PPL",
    "gn:name":"Yanlinggou",
    "gn:population":0,
    "gn:timezone":"Asia/Shanghai",
    "iso:country":"CN",
    "name:zho_x_preferred":[
        "\u95eb\u5cad\u6c9f"
    ],
    "wof:name":"Yanlinggou",
    "wof:placetype":"locality"
},
  "geometry": {"coordinates":[114.12014000000001,35.75043],"type":"Point"}
}