{
  "type": "Feature",
  "properties": {
    "gn:admin1_code":"16.0",
    "gn:asciiname":"Luoxiuhe",
    "gn:country_code":"CN",
    "gn:dem":125,
    "gn:feature_class":"P",
    "gn:feature_code":"PPL",
    "gn:name":"Luoxiuhe",
    "gn:population":0,
    "gn:timezone":"Asia/Shanghai",
    "iso:country":"CN",
    "name:zho_x_preferred":[
        "\u7f57\u79c0\u6cb3"
    ],
    "wof:name":"Luoxiuhe",
    "wof:placetype":"locality"
},
  "geometry": {"coordinates":[109.834,24.0352],"type":"Point"}
}