{
  "type": "Feature",
  "properties": {
    "gn:admin1_code":"8.0",
    "gn:asciiname":"Chagedaicun",
    "gn:country_code":"CN",
    "gn:dem":128,
    "gn:feature_class":"P",
    "gn:feature_code":"PPL",
    "gn:name":"Chagedaicun",
    "gn:population":0,
    "gn:timezone":"Asia/Shanghai",
    "iso:country":"CN",
    "name:zho_x_preferred":[
        "\u5c94\u683c\u5cb1\u6751"
    ],
    "wof:name":"Chagedaicun",
    "wof:placetype":"locality"
},
  "geometry": {"coordinates":[124.38579,45.58049000000001],"type":"Point"}
}