{
  "type": "Feature",
  "properties": {
    "gn:admin1_code":"16.0",
    "gn:asciiname":"Jie'an",
    "gn:country_code":"CN",
    "gn:dem":441,
    "gn:feature_class":"P",
    "gn:feature_code":"PPL",
    "gn:name":"Jie\u2019an",
    "gn:population":0,
    "gn:timezone":"Asia/Shanghai",
    "iso:country":"CN",
    "name:und_x_variant":[
        "Jie\u2019an"
    ],
    "name:zho_x_preferred":[
        "\u7ed3\u5b89"
    ],
    "wof:name":"Jie'an",
    "wof:placetype":"locality"
},
  "geometry": {"coordinates":[107.255,23.2119],"type":"Point"}
}