{
  "type": "Feature",
  "properties": {
    "gn:admin1_code":"3.0",
    "gn:asciiname":"Jianpu",
    "gn:country_code":"CN",
    "gn:dem":37,
    "gn:feature_class":"P",
    "gn:feature_code":"PPL",
    "gn:name":"Jianpu",
    "gn:population":0,
    "gn:timezone":"Asia/Shanghai",
    "iso:country":"CN",
    "name:und_x_variant":[
        "\u6e10\u6d66"
    ],
    "wof:name":"Jianpu",
    "wof:placetype":"locality"
},
  "geometry": {"coordinates":[115.35533,27.68048],"type":"Point"}
}