{
  "type": "Feature",
  "properties": {
    "gn:admin1_code":"11",
    "gn:asciiname":"Gantangchong",
    "gn:country_code":"CN",
    "gn:dem":81,
    "gn:feature_class":"P",
    "gn:feature_code":"PPL",
    "gn:name":"Gantangchong",
    "gn:population":0,
    "gn:timezone":"Asia/Shanghai",
    "iso:country":"CN",
    "name:zho_x_preferred":[
        "\u7518\u68e0\u51b2"
    ],
    "wof:name":"Gantangchong",
    "wof:placetype":"locality"
},
  "geometry": {"coordinates":[112.26215000000001,26.55079000000001],"type":"Point"}
}