{
  "type": "Feature",
  "properties": {
    "gn:admin1_code":"32.0",
    "gn:asciiname":"Wubeisi",
    "gn:country_code":"CN",
    "gn:dem":509,
    "gn:feature_class":"P",
    "gn:feature_code":"PPL",
    "gn:name":"Wubeisi",
    "gn:population":0,
    "gn:timezone":"Asia/Shanghai",
    "iso:country":"CN",
    "name:zho_x_preferred":[
        "\u5434\u7891\u5bfa"
    ],
    "wof:name":"Wubeisi",
    "wof:placetype":"locality"
},
  "geometry": {"coordinates":[103.94799999999999,30.1123],"type":"Point"}
}