{
  "type": "Feature",
  "properties": {
    "gn:admin1_code":"16.0",
    "gn:asciiname":"Xiaoxiang",
    "gn:country_code":"CN",
    "gn:dem":125,
    "gn:feature_class":"P",
    "gn:feature_code":"PPL",
    "gn:name":"Xiaoxiang",
    "gn:population":0,
    "gn:timezone":"Asia/Shanghai",
    "iso:country":"CN",
    "name:swe_x_preferred":[
        "Xiaoxiang"
    ],
    "name:zho_x_preferred":[
        "\u5c0f\u5411"
    ],
    "wof:name":"Xiaoxiang",
    "wof:placetype":"locality"
},
  "geometry": {"coordinates":[109.526,22.6969],"type":"Point"}
}