{
  "type": "Feature",
  "properties": {
    "gn:admin1_code":"4.0",
    "gn:asciiname":"Zhaze",
    "gn:country_code":"CN",
    "gn:dem":5,
    "gn:feature_class":"P",
    "gn:feature_code":"PPL",
    "gn:name":"Zhaze",
    "gn:population":0,
    "gn:timezone":"Asia/Shanghai",
    "iso:country":"CN",
    "name:zho_x_preferred":[
        "\u6e23\u6cfd"
    ],
    "wof:name":"Zhaze",
    "wof:placetype":"locality"
},
  "geometry": {"coordinates":[119.81095999999999,32.37669],"type":"Point"}
}