{
  "type": "Feature",
  "properties": {
    "gn:admin1_code":"12.0",
    "gn:asciiname":"Jujiadun",
    "gn:country_code":"CN",
    "gn:dem":14,
    "gn:feature_class":"P",
    "gn:feature_code":"PPL",
    "gn:name":"Jujiadun",
    "gn:population":0,
    "gn:timezone":"Asia/Shanghai",
    "iso:country":"CN",
    "name:zho_x_preferred":[
        "\u741a\u5bb6\u58a9"
    ],
    "wof:name":"Jujiadun",
    "wof:placetype":"locality"
},
  "geometry": {"coordinates":[115.97495000000001,29.77567],"type":"Point"}
}