{
  "type": "Feature",
  "properties": {
    "gn:admin1_code":"22.0",
    "gn:asciiname":"Weishanzhuang",
    "gn:country_code":"CN",
    "gn:dem":33,
    "gn:feature_class":"P",
    "gn:feature_code":"PPLA4",
    "gn:name":"Weishanzhuang",
    "gn:population":0,
    "gn:timezone":"Asia/Shanghai",
    "iso:country":"CN",
    "name:und_x_variant":[
        "Wei-shan-chuang",
        "Weishanzhuang",
        "Weishanzhuang Zhen"
    ],
    "name:zho_x_preferred":[
        "\u9b4f\u5584\u5e84"
    ],
    "name:zho_x_variant":[
        "\u9b4f\u5584\u5e84\u9547"
    ],
    "wof:name":"Weishanzhuang",
    "wof:placetype":"locality"
},
  "geometry": {"coordinates":[116.41645,39.62961],"type":"Point"}
}