{
  "type": "Feature",
  "properties": {
    "gn:admin1_code":"18",
    "gn:asciiname":"Tongdaping",
    "gn:country_code":"CN",
    "gn:dem":1222,
    "gn:feature_class":"P",
    "gn:feature_code":"PPL",
    "gn:name":"Tongdaping",
    "gn:population":0,
    "gn:timezone":"Asia/Shanghai",
    "iso:country":"CN",
    "name:zho_x_preferred":[
        "\u901a\u5927\u576a"
    ],
    "wof:name":"Tongdaping",
    "wof:placetype":"locality"
},
  "geometry": {"coordinates":[106.47,27.9509],"type":"Point"}
}