{
  "type": "Feature",
  "properties": {
    "gn:admin1_code":"5.0",
    "gn:asciiname":"Shi'erhaocun",
    "gn:country_code":"CN",
    "gn:dem":160,
    "gn:feature_class":"P",
    "gn:feature_code":"PPL",
    "gn:name":"Shi\u2019erhaocun",
    "gn:population":0,
    "gn:timezone":"Asia/Shanghai",
    "iso:country":"CN",
    "name:und_x_variant":[
        "Shi\u2019erhaocun"
    ],
    "name:zho_x_preferred":[
        "\u5341\u4e8c\u53f7\u6751"
    ],
    "wof:name":"Shi'erhaocun",
    "wof:placetype":"locality"
},
  "geometry": {"coordinates":[123.63493,44.21535],"type":"Point"}
}