{
  "type": "Feature",
  "properties": {
    "gn:admin1_code":"09",
    "gn:asciiname":"Guolutan",
    "gn:cc2":"CN",
    "gn:country_code":"CN",
    "gn:dem":44,
    "gn:feature_class":"P",
    "gn:feature_code":"PPL",
    "gn:name":"Guolutan",
    "gn:population":0,
    "gn:timezone":"Asia/Shanghai",
    "iso:country":"CN",
    "name:und_x_variant":[
        "Kuo-lu-t\u2019an",
        "Guolutan"
    ],
    "wof:name":"Guolutan",
    "wof:placetype":"locality"
},
  "geometry": {"coordinates":[115.65000000000001,32.03333],"type":"Point"}
}