{
  "type": "Feature",
  "properties": {
    "gn:admin1_code":"4.0",
    "gn:asciiname":"Yanba Guanliqu Shenghuoqu",
    "gn:country_code":"CN",
    "gn:dem":4,
    "gn:feature_class":"P",
    "gn:feature_code":"PPLF",
    "gn:name":"Yanba Guanliqu Shenghuoqu",
    "gn:population":0,
    "gn:timezone":"Asia/Shanghai",
    "iso:country":"CN",
    "name:zho_x_preferred":[
        "\u76d0\u575d\u7ba1\u7406\u533a\u751f\u6d3b\u533a"
    ],
    "wof:name":"Yanba Guanliqu Shenghuoqu",
    "wof:placetype":"locality"
},
  "geometry": {"coordinates":[120.80328,32.93091],"type":"Point"}
}