{
  "type": "Feature",
  "properties": {
    "gn:admin1_code":"32.0",
    "gn:asciiname":"Mushiduo",
    "gn:country_code":"CN",
    "gn:dem":2594,
    "gn:feature_class":"P",
    "gn:feature_code":"PPL",
    "gn:name":"Mushiduo",
    "gn:population":0,
    "gn:timezone":"Asia/Shanghai",
    "iso:country":"CN",
    "name:zho_x_preferred":[
        "\u6728\u77f3\u591a"
    ],
    "wof:name":"Mushiduo",
    "wof:placetype":"locality"
},
  "geometry": {"coordinates":[103.31999999999999,31.9223],"type":"Point"}
}