{
  "type": "Feature",
  "properties": {
    "gn:admin1_code":"16.0",
    "gn:asciiname":"Chaochang",
    "gn:country_code":"CN",
    "gn:dem":111,
    "gn:feature_class":"P",
    "gn:feature_code":"PPL",
    "gn:name":"Chaochang",
    "gn:population":0,
    "gn:timezone":"Asia/Shanghai",
    "iso:country":"CN",
    "name:zho_x_preferred":[
        "\u8d85\u5e38"
    ],
    "wof:name":"Chaochang",
    "wof:placetype":"locality"
},
  "geometry": {"coordinates":[109.14400000000001,23.1836],"type":"Point"}
}