{
  "type": "Feature",
  "properties": {
    "gn:admin1_code":"30",
    "gn:asciiname":"Meiziwo",
    "gn:country_code":"CN",
    "gn:dem":720,
    "gn:feature_class":"P",
    "gn:feature_code":"PPL",
    "gn:name":"Meiziwo",
    "gn:population":0,
    "gn:timezone":"Asia/Shanghai",
    "iso:country":"CN",
    "name:und_x_variant":[
        "\u6885\u5b50\u7a9d"
    ],
    "wof:name":"Meiziwo",
    "wof:placetype":"locality"
},
  "geometry": {"coordinates":[114.19598000000001,24.79534],"type":"Point"}
}