{
  "type": "Feature",
  "properties": {
    "gn:admin1_code":"15.0",
    "gn:asciiname":"Zhonghe",
    "gn:country_code":"CN",
    "gn:dem":1869,
    "gn:feature_class":"P",
    "gn:feature_code":"PPL",
    "gn:name":"Zhonghe",
    "gn:population":0,
    "gn:timezone":"Asia/Shanghai",
    "iso:country":"CN",
    "name:ceb_x_preferred":[
        "Zhonghe"
    ],
    "name:deu_x_preferred":[
        "Zhonghe"
    ],
    "name:swe_x_preferred":[
        "Zhonghe"
    ],
    "name:und_x_variant":[
        "\u4e2d\u548c"
    ],
    "wof:name":"Zhonghe",
    "wof:placetype":"locality"
},
  "geometry": {"coordinates":[105.2744,35.15597],"type":"Point"}
}