{
  "type": "Feature",
  "properties": {
    "gn:admin1_code":"15.0",
    "gn:asciiname":"Siwan",
    "gn:country_code":"CN",
    "gn:dem":2207,
    "gn:feature_class":"P",
    "gn:feature_code":"PPL",
    "gn:name":"Siwan",
    "gn:population":0,
    "gn:timezone":"Asia/Shanghai",
    "iso:country":"CN",
    "name:und_x_variant":[
        "\u56db\u6e7e"
    ],
    "wof:name":"Siwan",
    "wof:placetype":"locality"
},
  "geometry": {"coordinates":[104.89988999999998,34.78217],"type":"Point"}
}