{
  "type": "Feature",
  "properties": {
    "gn:admin1_code":"18.0",
    "gn:asciiname":"Shangshoudong",
    "gn:country_code":"CN",
    "gn:dem":578,
    "gn:feature_class":"P",
    "gn:feature_code":"PPL",
    "gn:name":"Shangshoudong",
    "gn:population":0,
    "gn:timezone":"Asia/Shanghai",
    "iso:country":"CN",
    "name:zho_x_preferred":[
        "\u4e0a\u5bff\u6d1e"
    ],
    "wof:name":"Shangshoudong",
    "wof:placetype":"locality"
},
  "geometry": {"coordinates":[108.61199999999999,26.1327],"type":"Point"}
}