{
  "type": "Feature",
  "properties": {
    "gn:admin1_code":"24.0",
    "gn:asciiname":"Gujiapo",
    "gn:country_code":"CN",
    "gn:dem":993,
    "gn:feature_class":"P",
    "gn:feature_code":"PPL",
    "gn:name":"Gujiapo",
    "gn:population":0,
    "gn:timezone":"Asia/Shanghai",
    "iso:country":"CN",
    "name:und_x_variant":[
        "\u53e4\u5bb6\u5761"
    ],
    "name:zho_x_preferred":[
        "\u53e4\u5bb6\u5761"
    ],
    "wof:name":"Gujiapo",
    "wof:placetype":"locality"
},
  "geometry": {"coordinates":[113.38958999999998,39.84511],"type":"Point"}
}