{
  "type": "Feature",
  "properties": {
    "gn:admin1_code":"2.0",
    "gn:asciiname":"Bancheng",
    "gn:country_code":"CN",
    "gn:dem":426,
    "gn:feature_class":"P",
    "gn:feature_code":"PPL",
    "gn:name":"Bancheng",
    "gn:population":0,
    "gn:timezone":"Asia/Shanghai",
    "iso:country":"CN",
    "name:zho_x_preferred":[
        "\u534a\u7a0b"
    ],
    "wof:name":"Bancheng",
    "wof:placetype":"locality"
},
  "geometry": {"coordinates":[120.56813,29.66094],"type":"Point"}
}