{
  "type": "Feature",
  "properties": {
    "gn:admin1_code":"18",
    "gn:asciiname":"Mada Liangzi",
    "gn:country_code":"CN",
    "gn:dem":1612,
    "gn:feature_class":"P",
    "gn:feature_code":"PPL",
    "gn:name":"Mada Liangzi",
    "gn:population":0,
    "gn:timezone":"Asia/Shanghai",
    "iso:country":"CN",
    "name:zho_x_preferred":[
        "\u9a6c\u8fbe\u6881\u5b50"
    ],
    "wof:name":"Mada Liangzi",
    "wof:placetype":"locality"
},
  "geometry": {"coordinates":[104.723,26.1704],"type":"Point"}
}