{
  "type": "Feature",
  "properties": {
    "gn:admin1_code":"25.0",
    "gn:asciiname":"Lingxitou",
    "gn:country_code":"CN",
    "gn:dem":48,
    "gn:feature_class":"P",
    "gn:feature_code":"PPL",
    "gn:name":"Lingxitou",
    "gn:population":0,
    "gn:timezone":"Asia/Shanghai",
    "iso:country":"CN",
    "name:zho_x_preferred":[
        "\u5cad\u897f\u5934"
    ],
    "wof:name":"Lingxitou",
    "wof:placetype":"locality"
},
  "geometry": {"coordinates":[120.41833,36.8209],"type":"Point"}
}