{
  "type": "Feature",
  "properties": {
    "gn:admin1_code":"11",
    "gn:asciiname":"Yuantou",
    "gn:country_code":"CN",
    "gn:dem":488,
    "gn:feature_class":"P",
    "gn:feature_code":"PPL",
    "gn:name":"Yuantou",
    "gn:population":0,
    "gn:timezone":"Asia/Shanghai",
    "iso:country":"CN",
    "name:und_x_variant":[
        "\u6c85\u5934",
        "Yuantou"
    ],
    "wof:name":"Yuantou",
    "wof:placetype":"locality"
},
  "geometry": {"coordinates":[112.17333000000001,26.01722],"type":"Point"}
}