{
  "type": "Feature",
  "properties": {
    "gn:admin1_code":"1.0",
    "gn:asciiname":"Yongmao",
    "gn:country_code":"CN",
    "gn:dem":46,
    "gn:feature_class":"P",
    "gn:feature_code":"PPL",
    "gn:name":"Yongmao",
    "gn:population":0,
    "gn:timezone":"Asia/Shanghai",
    "iso:country":"CN",
    "name:zho_x_preferred":[
        "Yongmao"
    ],
    "name:zho_x_variant":[
        "\u6c38\u8302"
    ],
    "wof:name":"Yongmao",
    "wof:placetype":"locality"
},
  "geometry": {"coordinates":[119.53022,30.94485],"type":"Point"}
}