{
  "type": "Feature",
  "properties": {
    "gn:admin1_code":"2.0",
    "gn:asciiname":"Xiahongtou",
    "gn:country_code":"CN",
    "gn:dem":78,
    "gn:feature_class":"P",
    "gn:feature_code":"PPL",
    "gn:name":"Xiahongtou",
    "gn:population":0,
    "gn:timezone":"Asia/Shanghai",
    "iso:country":"CN",
    "name:zho_x_preferred":[
        "\u4e0b\u70d8\u5934"
    ],
    "wof:name":"Xiahongtou",
    "wof:placetype":"locality"
},
  "geometry": {"coordinates":[120.73639,28.27821],"type":"Point"}
}