{
  "type": "Feature",
  "properties": {
    "gn:admin1_code":"29.0",
    "gn:asciiname":"Tangfang",
    "gn:country_code":"CN",
    "gn:dem":1854,
    "gn:feature_class":"P",
    "gn:feature_code":"PPL",
    "gn:name":"Tangfang",
    "gn:population":0,
    "gn:timezone":"Asia/Shanghai",
    "iso:country":"CN",
    "name:zho_x_preferred":[
        "\u5858\u623f"
    ],
    "wof:name":"Tangfang",
    "wof:placetype":"locality"
},
  "geometry": {"coordinates":[104.122,27.4614],"type":"Point"}
}