{
  "type": "Feature",
  "properties": {
    "gn:admin1_code":"14.0",
    "gn:asciiname":"Jagsam",
    "gn:country_code":"CN",
    "gn:dem":3936,
    "gn:feature_class":"P",
    "gn:feature_code":"PPLF",
    "gn:name":"Jagsam",
    "gn:population":0,
    "gn:timezone":"Asia/Urumqi",
    "iso:country":"CN",
    "name:bod_x_preferred":[
        "Jagsam"
    ],
    "name:zho_x_preferred":[
        "Jiasang"
    ],
    "name:zho_x_variant":[
        "\u7532\u6851"
    ],
    "wof:name":"Jagsam",
    "wof:placetype":"locality"
},
  "geometry": {"coordinates":[96.30500000000001,31.705],"type":"Point"}
}