{
  "type": "Feature",
  "properties": {
    "gn:admin1_code":"4.0",
    "gn:asciiname":"Caoliang",
    "gn:country_code":"CN",
    "gn:dem":5,
    "gn:feature_class":"P",
    "gn:feature_code":"PPL",
    "gn:name":"Caoliang",
    "gn:population":0,
    "gn:timezone":"Asia/Shanghai",
    "iso:country":"CN",
    "name:zho_x_preferred":[
        "Caoliang"
    ],
    "name:zho_x_variant":[
        "\u6f15\u7cae"
    ],
    "wof:name":"Caoliang",
    "wof:placetype":"locality"
},
  "geometry": {"coordinates":[120.98265000000001,32.30713],"type":"Point"}
}