{
  "type": "Feature",
  "properties": {
    "gn:admin1_code":"10",
    "gn:asciiname":"Waqiangou",
    "gn:country_code":"CN",
    "gn:dem":1311,
    "gn:feature_class":"P",
    "gn:feature_code":"PPL",
    "gn:name":"Waqiangou",
    "gn:population":0,
    "gn:timezone":"Asia/Shanghai",
    "iso:country":"CN",
    "name:zho_x_preferred":[
        "\u6316\u94b1\u6c9f"
    ],
    "wof:name":"Waqiangou",
    "wof:placetype":"locality"
},
  "geometry": {"coordinates":[116.99575,42.08863],"type":"Point"}
}