{
  "type": "Feature",
  "properties": {
    "gn:admin1_code":"8.0",
    "gn:asciiname":"Gongzhengcun",
    "gn:country_code":"CN",
    "gn:dem":218,
    "gn:feature_class":"P",
    "gn:feature_code":"PPL",
    "gn:name":"Gongzhengcun",
    "gn:population":0,
    "gn:timezone":"Asia/Shanghai",
    "iso:country":"CN",
    "name:zho_x_preferred":[
        "\u516c\u653f\u6751"
    ],
    "wof:name":"Gongzhengcun",
    "wof:placetype":"locality"
},
  "geometry": {"coordinates":[126.00708,48.02068],"type":"Point"}
}