{
  "type": "Feature",
  "properties": {
    "gn:admin1_code":"1.0",
    "gn:asciiname":"Guhecun",
    "gn:country_code":"CN",
    "gn:dem":39,
    "gn:feature_class":"P",
    "gn:feature_code":"PPL",
    "gn:name":"Guhecun",
    "gn:population":0,
    "gn:timezone":"Asia/Shanghai",
    "iso:country":"CN",
    "name:zho_x_preferred":[
        "\u53e4\u6cb3\u6751"
    ],
    "wof:name":"Guhecun",
    "wof:placetype":"locality"
},
  "geometry": {"coordinates":[116.75228,31.45426],"type":"Point"}
}