{
  "type": "Feature",
  "properties": {
    "gn:admin1_code":"5.0",
    "gn:asciiname":"Sukemacun",
    "gn:country_code":"CN",
    "gn:dem":133,
    "gn:feature_class":"P",
    "gn:feature_code":"PPL",
    "gn:name":"Sukemacun",
    "gn:population":0,
    "gn:timezone":"Asia/Shanghai",
    "iso:country":"CN",
    "name:zho_x_preferred":[
        "\u82cf\u514b\u9a6c\u6751"
    ],
    "wof:name":"Sukemacun",
    "wof:placetype":"locality"
},
  "geometry": {"coordinates":[123.65109,45.88774],"type":"Point"}
}