{
  "type": "Feature",
  "properties": {
    "gn:admin1_code":"7",
    "gn:asciiname":"Gaomingkeng",
    "gn:country_code":"CN",
    "gn:dem":421,
    "gn:feature_class":"P",
    "gn:feature_code":"PPL",
    "gn:name":"Gaomingkeng",
    "gn:population":0,
    "gn:timezone":"Asia/Shanghai",
    "iso:country":"CN",
    "name:zho_x_preferred":[
        "\u9ad8\u660e\u5751"
    ],
    "wof:name":"Gaomingkeng",
    "wof:placetype":"locality"
},
  "geometry": {"coordinates":[117.38722,25.25806],"type":"Point"}
}