{
  "type": "Feature",
  "properties": {
    "gn:admin1_code":"18.0",
    "gn:asciiname":"Yuetuan",
    "gn:country_code":"CN",
    "gn:dem":712,
    "gn:feature_class":"P",
    "gn:feature_code":"PPL",
    "gn:name":"Yuetuan",
    "gn:population":0,
    "gn:timezone":"Asia/Shanghai",
    "iso:country":"CN",
    "name:zho_x_preferred":[
        "\u6708\u56e2"
    ],
    "wof:name":"Yuetuan",
    "wof:placetype":"locality"
},
  "geometry": {"coordinates":[109.191,26.2436],"type":"Point"}
}