{
  "type": "Feature",
  "properties": {
    "gn:admin1_code":"3.0",
    "gn:asciiname":"He'aoling",
    "gn:country_code":"CN",
    "gn:dem":292,
    "gn:feature_class":"P",
    "gn:feature_code":"PPL",
    "gn:name":"He\u2019aoling",
    "gn:population":0,
    "gn:timezone":"Asia/Shanghai",
    "iso:country":"CN",
    "name:und_x_variant":[
        "He\u2019aoling",
        "\u548c\u5773\u5cad"
    ],
    "wof:name":"He'aoling",
    "wof:placetype":"locality"
},
  "geometry": {"coordinates":[114.11459000000001,29.01459],"type":"Point"}
}