{
  "type": "Feature",
  "properties": {
    "gn:admin1_code":"3.0",
    "gn:asciiname":"Shixifan",
    "gn:country_code":"CN",
    "gn:dem":25,
    "gn:feature_class":"P",
    "gn:feature_code":"PPL",
    "gn:name":"Shixifan",
    "gn:population":0,
    "gn:timezone":"Asia/Shanghai",
    "iso:country":"CN",
    "name:und_x_variant":[
        "\u77f3\u6eaa\u7548"
    ],
    "wof:name":"Shixifan",
    "wof:placetype":"locality"
},
  "geometry": {"coordinates":[116.26106,28.53609],"type":"Point"}
}