{
  "type": "Feature",
  "properties": {
    "gn:admin1_code":"32.0",
    "gn:asciiname":"Jiarong",
    "gn:country_code":"CN",
    "gn:dem":3940,
    "gn:feature_class":"P",
    "gn:feature_code":"PPL",
    "gn:name":"Jiarong",
    "gn:population":0,
    "gn:timezone":"Asia/Shanghai",
    "iso:country":"CN",
    "name:zho_x_preferred":[
        "\u7532\u7ed2"
    ],
    "wof:name":"Jiarong",
    "wof:placetype":"locality"
},
  "geometry": {"coordinates":[99.6103,32.3591],"type":"Point"}
}