{
  "type": "Feature",
  "properties": {
    "gn:admin1_code":"16.0",
    "gn:asciiname":"Shanhuping",
    "gn:country_code":"CN",
    "gn:dem":591,
    "gn:feature_class":"P",
    "gn:feature_code":"PPL",
    "gn:name":"Shanhuping",
    "gn:population":0,
    "gn:timezone":"Asia/Shanghai",
    "iso:country":"CN",
    "name:zho_x_preferred":[
        "\u5c71\u80e1\u576a"
    ],
    "wof:name":"Shanhuping",
    "wof:placetype":"locality"
},
  "geometry": {"coordinates":[110.86499999999999,22.7026],"type":"Point"}
}