{
  "type": "Feature",
  "properties": {
    "gn:admin1_code":"1.0",
    "gn:asciiname":"Baimachang",
    "gn:country_code":"CN",
    "gn:dem":169,
    "gn:feature_class":"P",
    "gn:feature_code":"PPL",
    "gn:name":"Baimachang",
    "gn:population":0,
    "gn:timezone":"Asia/Shanghai",
    "iso:country":"CN",
    "name:und_x_variant":[
        "\u767d\u9a6c\u573a"
    ],
    "wof:name":"Baimachang",
    "wof:placetype":"locality"
},
  "geometry": {"coordinates":[119.611,31.07153],"type":"Point"}
}