{
  "type": "Feature",
  "properties": {
    "gn:admin1_code":"18",
    "gn:asciiname":"Lujiawan",
    "gn:country_code":"CN",
    "gn:dem":1245,
    "gn:feature_class":"P",
    "gn:feature_code":"PPL",
    "gn:name":"L\u00fcjiawan",
    "gn:population":0,
    "gn:timezone":"Asia/Shanghai",
    "iso:country":"CN",
    "name:und_x_variant":[
        "L\u00fcjiawan"
    ],
    "name:zho_x_preferred":[
        "\u5415\u5bb6\u6e7e"
    ],
    "wof:name":"Lujiawan",
    "wof:placetype":"locality"
},
  "geometry": {"coordinates":[107.65900000000001,28.2507],"type":"Point"}
}