{
  "type": "Feature",
  "properties": {
    "gn:admin1_code":"11",
    "gn:asciiname":"Liwanbei",
    "gn:country_code":"CN",
    "gn:dem":81,
    "gn:feature_class":"P",
    "gn:feature_code":"PPL",
    "gn:name":"Liwanbei",
    "gn:population":0,
    "gn:timezone":"Asia/Shanghai",
    "iso:country":"CN",
    "name:zho_x_preferred":[
        "\u674e\u6e7e\u80cc"
    ],
    "wof:name":"Liwanbei",
    "wof:placetype":"locality"
},
  "geometry": {"coordinates":[112.4087,26.47769000000001],"type":"Point"}
}