{
  "type": "Feature",
  "properties": {
    "gn:admin1_code":"8.0",
    "gn:asciiname":"Benbeicun",
    "gn:country_code":"CN",
    "gn:dem":66,
    "gn:feature_class":"P",
    "gn:feature_code":"PPL",
    "gn:name":"Benbeicun",
    "gn:population":0,
    "gn:timezone":"Asia/Shanghai",
    "iso:country":"CN",
    "name:zho_x_preferred":[
        "\u672c\u5317\u6751"
    ],
    "wof:name":"Benbeicun",
    "wof:placetype":"locality"
},
  "geometry": {"coordinates":[132.2329,46.53311],"type":"Point"}
}