{
  "type": "Feature",
  "properties": {
    "gn:admin1_code":"30",
    "gn:asciiname":"Nafu",
    "gn:country_code":"CN",
    "gn:dem":5,
    "gn:feature_class":"P",
    "gn:feature_code":"PPL",
    "gn:name":"Nafu",
    "gn:population":0,
    "gn:timezone":"Asia/Shanghai",
    "iso:country":"CN",
    "name:und_x_variant":[
        "Na-fu-hsu",
        "Nafu",
        "Nafu Zhen",
        "\u90a3\u6276\u9547"
    ],
    "name:zho_x_preferred":[
        "\u90a3\u6276"
    ],
    "wof:name":"Nafu",
    "wof:placetype":"locality"
},
  "geometry": {"coordinates":[112.39842,22.08694],"type":"Point"}
}