{
  "type": "Feature",
  "properties": {
    "gn:admin1_code":"29",
    "gn:asciiname":"Dahuotang",
    "gn:country_code":"CN",
    "gn:dem":1855,
    "gn:feature_class":"P",
    "gn:feature_code":"PPL",
    "gn:name":"Dahuotang",
    "gn:population":0,
    "gn:timezone":"Asia/Shanghai",
    "iso:country":"CN",
    "name:zho_x_preferred":[
        "\u5927\u706b\u5858"
    ],
    "wof:name":"Dahuotang",
    "wof:placetype":"locality"
},
  "geometry": {"coordinates":[101.551,24.4013],"type":"Point"}
}