{
  "type": "Feature",
  "properties": {
    "gn:admin1_code":"4.0",
    "gn:asciiname":"Dongdu Chaitang",
    "gn:country_code":"CN",
    "gn:dem":4,
    "gn:feature_class":"P",
    "gn:feature_code":"PPL",
    "gn:name":"Dongdu Chaitang",
    "gn:population":0,
    "gn:timezone":"Asia/Shanghai",
    "iso:country":"CN",
    "name:und_x_variant":[
        "\u4e1c\u675c\u67f4\u5858"
    ],
    "wof:name":"Dongdu Chaitang",
    "wof:placetype":"locality"
},
  "geometry": {"coordinates":[121.0549,31.51232000000001],"type":"Point"}
}