{
  "type": "Feature",
  "properties": {
    "gn:admin1_code":"10.0",
    "gn:asciiname":"Shicaogou",
    "gn:country_code":"CN",
    "gn:dem":343,
    "gn:feature_class":"P",
    "gn:feature_code":"PPL",
    "gn:name":"Shicaogou",
    "gn:population":0,
    "gn:timezone":"Asia/Shanghai",
    "iso:country":"CN",
    "name:und_x_variant":[
        "\u77f3\u69fd\u6c9f"
    ],
    "wof:name":"Shicaogou",
    "wof:placetype":"locality"
},
  "geometry": {"coordinates":[114.14837,38.9002],"type":"Point"}
}