{
  "type": "Feature",
  "properties": {
    "gn:admin1_code":"09",
    "gn:asciiname":"Mangchuan",
    "gn:country_code":"CN",
    "gn:dem":281,
    "gn:feature_class":"P",
    "gn:feature_code":"PPL",
    "gn:name":"Mangchuan",
    "gn:population":0,
    "gn:timezone":"Asia/Shanghai",
    "iso:country":"CN",
    "wof:name":"Mangchuan",
    "wof:placetype":"locality"
},
  "geometry": {"coordinates":[112.75972,34.05667],"type":"Point"}
}