{
  "type": "Feature",
  "properties": {
    "gn:admin1_code":"21.0",
    "gn:asciiname":"Hantao",
    "gn:country_code":"CN",
    "gn:dem":1799,
    "gn:feature_class":"P",
    "gn:feature_code":"PPL",
    "gn:name":"Hantao",
    "gn:population":0,
    "gn:timezone":"Asia/Shanghai",
    "iso:country":"CN",
    "name:zho_x_preferred":[
        "\u97e9\u5957"
    ],
    "wof:name":"Hantao",
    "wof:placetype":"locality"
},
  "geometry": {"coordinates":[105.396,36.8522],"type":"Point"}
}