{
  "type": "Feature",
  "properties": {
    "gn:admin1_code":"11.0",
    "gn:asciiname":"Xiaxingluo",
    "gn:country_code":"CN",
    "gn:dem":256,
    "gn:feature_class":"P",
    "gn:feature_code":"PPL",
    "gn:name":"Xiaxingluo",
    "gn:population":0,
    "gn:timezone":"Asia/Shanghai",
    "iso:country":"CN",
    "name:zho_x_preferred":[
        "\u4e0b\u661f\u7f57"
    ],
    "wof:name":"Xiaxingluo",
    "wof:placetype":"locality"
},
  "geometry": {"coordinates":[112.32258,25.60006],"type":"Point"}
}