{
  "type": "Feature",
  "properties": {
    "gn:admin1_code":"26",
    "gn:asciiname":"Dongchaliu",
    "gn:country_code":"CN",
    "gn:dem":544,
    "gn:feature_class":"P",
    "gn:feature_code":"PPL",
    "gn:name":"Dongchaliu",
    "gn:population":0,
    "gn:timezone":"Asia/Shanghai",
    "iso:country":"CN",
    "name:zho_x_preferred":[
        "\u4e1c\u63d2\u67f3"
    ],
    "wof:name":"Dongchaliu",
    "wof:placetype":"locality"
},
  "geometry": {"coordinates":[108.20228,34.34265],"type":"Point"}
}