{
  "type": "Feature",
  "properties": {
    "gn:admin1_code":"9.0",
    "gn:asciiname":"Guangou",
    "gn:country_code":"CN",
    "gn:dem":256,
    "gn:feature_class":"P",
    "gn:feature_code":"PPL",
    "gn:name":"Guangou",
    "gn:population":0,
    "gn:timezone":"Asia/Shanghai",
    "iso:country":"CN",
    "name:und_x_variant":[
        "\u5173\u6c9f",
        "Guangou"
    ],
    "wof:name":"Guangou",
    "wof:placetype":"locality"
},
  "geometry": {"coordinates":[112.77508,33.40701],"type":"Point"}
}