{
  "type": "Feature",
  "properties": {
    "gn:admin1_code":"32.0",
    "gn:asciiname":"Wanjia Dafangzi",
    "gn:country_code":"CN",
    "gn:dem":372,
    "gn:feature_class":"P",
    "gn:feature_code":"PPL",
    "gn:name":"Wanjia Dafangzi",
    "gn:population":0,
    "gn:timezone":"Asia/Shanghai",
    "iso:country":"CN",
    "name:zho_x_preferred":[
        "\u4e07\u5bb6\u5927\u623f\u5b50"
    ],
    "wof:name":"Wanjia Dafangzi",
    "wof:placetype":"locality"
},
  "geometry": {"coordinates":[105.28932,29.33685],"type":"Point"}
}