{
  "type": "Feature",
  "properties": {
    "gn:admin1_code":"9.0",
    "gn:asciiname":"Guolou",
    "gn:country_code":"CN",
    "gn:dem":131,
    "gn:feature_class":"P",
    "gn:feature_code":"PPL",
    "gn:name":"Guolou",
    "gn:population":0,
    "gn:timezone":"Asia/Shanghai",
    "iso:country":"CN",
    "name:und_x_variant":[
        "\u90ed\u697c",
        "Guolou"
    ],
    "wof:name":"Guolou",
    "wof:placetype":"locality"
},
  "geometry": {"coordinates":[112.99811,33.13535],"type":"Point"}
}