{
  "type": "Feature",
  "properties": {
    "gn:admin1_code":"19.0",
    "gn:asciiname":"Houbolihongwa",
    "gn:country_code":"CN",
    "gn:dem":227,
    "gn:feature_class":"P",
    "gn:feature_code":"PPL",
    "gn:name":"Houbolihongwa",
    "gn:population":0,
    "gn:timezone":"Asia/Shanghai",
    "iso:country":"CN",
    "name:zho_x_preferred":[
        "\u540e\u73bb\u529b\u6d2a\u6d3c"
    ],
    "name:zho_x_variant":[
        "\u540e\u73bb\u7483\u7ea2\u6d3c"
    ],
    "wof:name":"Houbolihongwa",
    "wof:placetype":"locality"
},
  "geometry": {"coordinates":[122.643,42.7705],"type":"Point"}
}