{
  "type": "Feature",
  "properties": {
    "gn:admin1_code":"32.0",
    "gn:asciiname":"Asechatuo",
    "gn:country_code":"CN",
    "gn:dem":3649,
    "gn:feature_class":"P",
    "gn:feature_code":"PPL",
    "gn:name":"Asechatuo",
    "gn:population":0,
    "gn:timezone":"Asia/Shanghai",
    "iso:country":"CN",
    "name:zho_x_preferred":[
        "\u963f\u8272\u8336\u6258"
    ],
    "wof:name":"Asechatuo",
    "wof:placetype":"locality"
},
  "geometry": {"coordinates":[100.91848,31.483],"type":"Point"}
}