{
  "type": "Feature",
  "properties": {
    "gn:admin1_code":"13.0",
    "gn:asciiname":"Tuozila",
    "gn:country_code":"CN",
    "gn:dem":2842,
    "gn:feature_class":"P",
    "gn:feature_code":"PPL",
    "gn:name":"Tuozila",
    "gn:population":0,
    "gn:timezone":"Asia/Shanghai",
    "iso:country":"CN",
    "name:zho_x_preferred":[
        "\u6258\u5b5c\u62c9"
    ],
    "wof:name":"Tuozila",
    "wof:placetype":"locality"
},
  "geometry": {"coordinates":[77.53946999999999,36.81533],"type":"Point"}
}