{
  "type": "Feature",
  "properties": {
    "gn:admin1_code":"15.0",
    "gn:asciiname":"Dawa",
    "gn:country_code":"CN",
    "gn:dem":1797,
    "gn:feature_class":"P",
    "gn:feature_code":"PPL",
    "gn:name":"Dawa",
    "gn:population":0,
    "gn:timezone":"Asia/Shanghai",
    "iso:country":"CN",
    "name:ceb_x_preferred":[
        "Dawa"
    ],
    "name:deu_x_preferred":[
        "Dawa"
    ],
    "name:fra_x_preferred":[
        "Dawa"
    ],
    "name:nor_x_preferred":[
        "Dawa"
    ],
    "name:por_x_preferred":[
        "Dawa"
    ],
    "name:swe_x_preferred":[
        "Dawa"
    ],
    "name:und_x_variant":[
        "\u5927\u6d3c"
    ],
    "wof:name":"Dawa",
    "wof:placetype":"locality"
},
  "geometry": {"coordinates":[106.54861,36.35745],"type":"Point"}
}