{
  "type": "Feature",
  "properties": {
    "gn:admin1_code":"1.0",
    "gn:asciiname":"Yaobu",
    "gn:country_code":"CN",
    "gn:dem":17,
    "gn:feature_class":"P",
    "gn:feature_code":"PPL",
    "gn:name":"Yaobu",
    "gn:population":0,
    "gn:timezone":"Asia/Shanghai",
    "iso:country":"CN",
    "name:und_x_variant":[
        "Yao-p\u2019u",
        "Yaobu"
    ],
    "name:zho_x_preferred":[
        "\u8170\u57e0"
    ],
    "wof:name":"Yaobu",
    "wof:placetype":"locality"
},
  "geometry": {"coordinates":[118.2259,31.73629],"type":"Point"}
}