{
  "type": "Feature",
  "properties": {
    "gn:admin1_code":"16.0",
    "gn:asciiname":"Daliantang",
    "gn:country_code":"CN",
    "gn:dem":191,
    "gn:feature_class":"P",
    "gn:feature_code":"PPL",
    "gn:name":"Daliantang",
    "gn:population":0,
    "gn:timezone":"Asia/Shanghai",
    "iso:country":"CN",
    "name:zho_x_preferred":[
        "\u5927\u83b2\u5858"
    ],
    "wof:name":"Daliantang",
    "wof:placetype":"locality"
},
  "geometry": {"coordinates":[111.364,24.7636],"type":"Point"}
}