{
  "type": "Feature",
  "properties": {
    "gn:admin1_code":"25",
    "gn:asciiname":"Gucheng",
    "gn:country_code":"CN",
    "gn:dem":143,
    "gn:feature_class":"P",
    "gn:feature_code":"PPL",
    "gn:name":"Gucheng",
    "gn:population":0,
    "gn:timezone":"Asia/Shanghai",
    "iso:country":"CN",
    "name:ceb_x_preferred":[
        "Gucheng"
    ],
    "name:deu_x_preferred":[
        "Gucheng"
    ],
    "name:est_x_preferred":[
        "Gucheng"
    ],
    "name:fra_x_preferred":[
        "Gucheng"
    ],
    "name:kor_x_preferred":[
        "\uad6c\uccad\ud604"
    ],
    "name:nor_x_preferred":[
        "Gucheng"
    ],
    "name:swe_x_preferred":[
        "Gucheng"
    ],
    "name:zho_x_preferred":[
        "\u56fa\u57ce"
    ],
    "wof:name":"Gucheng",
    "wof:placetype":"locality"
},
  "geometry": {"coordinates":[117.783,35.4745],"type":"Point"}
}