{
  "type": "Feature",
  "properties": {
    "gn:admin1_code":"8.0",
    "gn:asciiname":"Houchengcun",
    "gn:country_code":"CN",
    "gn:dem":121,
    "gn:feature_class":"P",
    "gn:feature_code":"PPL",
    "gn:name":"Houchengcun",
    "gn:population":0,
    "gn:timezone":"Asia/Shanghai",
    "iso:country":"CN",
    "name:zho_x_preferred":[
        "\u540e\u57ce\u6751"
    ],
    "wof:name":"Houchengcun",
    "wof:placetype":"locality"
},
  "geometry": {"coordinates":[126.4007,45.82794000000001],"type":"Point"}
}