{
  "type": "Feature",
  "properties": {
    "gn:admin1_code":"02",
    "gn:asciiname":"Niushi'an",
    "gn:country_code":"CN",
    "gn:dem":47,
    "gn:feature_class":"P",
    "gn:feature_code":"PPL",
    "gn:name":"Niushi\u2019an",
    "gn:population":0,
    "gn:timezone":"Asia/Shanghai",
    "iso:country":"CN",
    "name:zho_x_preferred":[
        "\u725b\u77f3\u5eb5"
    ],
    "name:zho_x_variant":[
        "Niushi\u2019an"
    ],
    "wof:name":"Niushi'an",
    "wof:placetype":"locality"
},
  "geometry": {"coordinates":[120.45293999999998,27.83385],"type":"Point"}
}