{
  "type": "Feature",
  "properties": {
    "gn:admin1_code":"16.0",
    "gn:asciiname":"Hengshui",
    "gn:country_code":"CN",
    "gn:dem":221,
    "gn:feature_class":"P",
    "gn:feature_code":"PPL",
    "gn:name":"Hengshui",
    "gn:population":0,
    "gn:timezone":"Asia/Shanghai",
    "iso:country":"CN",
    "name:zho_x_preferred":[
        "\u6a2a\u6c34"
    ],
    "wof:name":"Hengshui",
    "wof:placetype":"locality"
},
  "geometry": {"coordinates":[110.245,24.4335],"type":"Point"}
}