{
  "type": "Feature",
  "properties": {
    "gn:admin1_code":"32.0",
    "gn:asciiname":"Jungu",
    "gn:country_code":"CN",
    "gn:dem":2720,
    "gn:feature_class":"P",
    "gn:feature_code":"PPL",
    "gn:name":"Jungu",
    "gn:population":0,
    "gn:timezone":"Asia/Shanghai",
    "iso:country":"CN",
    "name:zho_x_preferred":[
        "\u5747\u53e4"
    ],
    "wof:name":"Jungu",
    "wof:placetype":"locality"
},
  "geometry": {"coordinates":[99.1905,28.5494],"type":"Point"}
}