{
  "type": "Feature",
  "properties": {
    "gn:admin1_code":"26",
    "gn:asciiname":"Heliu",
    "gn:country_code":"CN",
    "gn:dem":564,
    "gn:feature_class":"P",
    "gn:feature_code":"PPL",
    "gn:name":"Heliu",
    "gn:population":0,
    "gn:timezone":"Asia/Shanghai",
    "iso:country":"CN",
    "name:ceb_x_preferred":[
        "Heliu"
    ],
    "name:swe_x_preferred":[
        "Heliu"
    ],
    "name:zho_x_preferred":[
        "\u4f55\u5218"
    ],
    "wof:name":"Heliu",
    "wof:placetype":"locality"
},
  "geometry": {"coordinates":[109.44623,34.41154],"type":"Point"}
}