{
  "type": "Feature",
  "properties": {
    "gn:admin1_code":"29.0",
    "gn:asciiname":"Hudao",
    "gn:country_code":"CN",
    "gn:dem":1297,
    "gn:feature_class":"P",
    "gn:feature_code":"PPL",
    "gn:name":"Hudao",
    "gn:population":0,
    "gn:timezone":"Asia/Shanghai",
    "iso:country":"CN",
    "name:zho_x_preferred":[
        "\u6237\u5c9b"
    ],
    "wof:name":"Hudao",
    "wof:placetype":"locality"
},
  "geometry": {"coordinates":[97.81189999999999,24.3517],"type":"Point"}
}