{
  "type": "Feature",
  "properties": {
    "gn:admin1_code":"2.0",
    "gn:asciiname":"Xiaodoumen",
    "gn:country_code":"CN",
    "gn:dem":6,
    "gn:feature_class":"P",
    "gn:feature_code":"PPL",
    "gn:name":"Xiaodoumen",
    "gn:population":0,
    "gn:timezone":"Asia/Shanghai",
    "iso:country":"CN",
    "name:und_x_variant":[
        "Tou-men",
        "Xiaodoumen"
    ],
    "name:zho_x_preferred":[
        "\u5c0f\u9661\u95e8"
    ],
    "wof:name":"Xiaodoumen",
    "wof:placetype":"locality"
},
  "geometry": {"coordinates":[120.85287,27.94263],"type":"Point"}
}