{
  "type": "Feature",
  "properties": {
    "gn:admin1_code":"8.0",
    "gn:asciiname":"Dayantong",
    "gn:country_code":"CN",
    "gn:dem":185,
    "gn:feature_class":"P",
    "gn:feature_code":"PPL",
    "gn:name":"Dayantong",
    "gn:population":0,
    "gn:timezone":"Asia/Shanghai",
    "iso:country":"CN",
    "name:zho_x_preferred":[
        "\u5927\u70df\u7b52"
    ],
    "wof:name":"Dayantong",
    "wof:placetype":"locality"
},
  "geometry": {"coordinates":[127.51785,45.0309],"type":"Point"}
}