{
  "type": "Feature",
  "properties": {
    "gn:admin1_code":"8.0",
    "gn:asciiname":"Zhongshancun",
    "gn:country_code":"CN",
    "gn:dem":141,
    "gn:feature_class":"P",
    "gn:feature_code":"PPL",
    "gn:name":"Zhongshancun",
    "gn:population":0,
    "gn:timezone":"Asia/Shanghai",
    "iso:country":"CN",
    "name:zho_x_preferred":[
        "\u4ef2\u5c71\u6751"
    ],
    "wof:name":"Zhongshancun",
    "wof:placetype":"locality"
},
  "geometry": {"coordinates":[126.12881000000002,46.05166],"type":"Point"}
}