{
  "type": "Feature",
  "properties": {
    "gn:admin1_code":"26.0",
    "gn:asciiname":"Dongbashicun",
    "gn:country_code":"CN",
    "gn:dem":458,
    "gn:feature_class":"P",
    "gn:feature_code":"PPL",
    "gn:name":"Dongbashicun",
    "gn:population":0,
    "gn:timezone":"Asia/Shanghai",
    "iso:country":"CN",
    "name:zho_x_preferred":[
        "\u4e1c\u516b\u4ec0\u6751"
    ],
    "wof:name":"Dongbashicun",
    "wof:placetype":"locality"
},
  "geometry": {"coordinates":[108.5331,34.061],"type":"Point"}
}