{
  "type": "Feature",
  "properties": {
    "gn:admin1_code":"8.0",
    "gn:asciiname":"Yonglicun",
    "gn:country_code":"CN",
    "gn:dem":144,
    "gn:feature_class":"P",
    "gn:feature_code":"PPL",
    "gn:name":"Yonglicun",
    "gn:population":0,
    "gn:timezone":"Asia/Shanghai",
    "iso:country":"CN",
    "name:zho_x_preferred":[
        "\u6c38\u5229\u6751"
    ],
    "wof:name":"Yonglicun",
    "wof:placetype":"locality"
},
  "geometry": {"coordinates":[130.43191999999999,46.21522],"type":"Point"}
}