{
  "type": "Feature",
  "properties": {
    "gn:admin1_code":"26.0",
    "gn:asciiname":"Guanfengya",
    "gn:country_code":"CN",
    "gn:dem":995,
    "gn:feature_class":"P",
    "gn:feature_code":"PPL",
    "gn:name":"Guanfengya",
    "gn:population":0,
    "gn:timezone":"Asia/Shanghai",
    "iso:country":"CN",
    "name:zho_x_preferred":[
        "\u5173\u4e30\u57ad"
    ],
    "wof:name":"Guanfengya",
    "wof:placetype":"locality"
},
  "geometry": {"coordinates":[109.17775,32.34046],"type":"Point"}
}