{
  "type": "Feature",
  "properties": {
    "gn:admin1_code":"26.0",
    "gn:asciiname":"Yuejiazhuang",
    "gn:country_code":"CN",
    "gn:dem":862,
    "gn:feature_class":"P",
    "gn:feature_code":"PPL",
    "gn:name":"Yuejiazhuang",
    "gn:population":0,
    "gn:timezone":"Asia/Shanghai",
    "iso:country":"CN",
    "name:und_x_variant":[
        "\u5cb3\u5bb6\u5e84"
    ],
    "wof:name":"Yuejiazhuang",
    "wof:placetype":"locality"
},
  "geometry": {"coordinates":[107.09497,34.61799],"type":"Point"}
}