{
  "type": "Feature",
  "properties": {
    "gn:admin1_code":"4.0",
    "gn:asciiname":"Hemujian",
    "gn:country_code":"CN",
    "gn:dem":25,
    "gn:feature_class":"P",
    "gn:feature_code":"PPL",
    "gn:name":"Hemujian",
    "gn:population":0,
    "gn:timezone":"Asia/Shanghai",
    "iso:country":"CN",
    "name:zho_x_preferred":[
        "\u548c\u7766\u6da7"
    ],
    "wof:name":"Hemujian",
    "wof:placetype":"locality"
},
  "geometry": {"coordinates":[119.07523,31.3144],"type":"Point"}
}