{
  "type": "Feature",
  "properties": {
    "gn:admin1_code":"30",
    "gn:asciiname":"Lipozhai",
    "gn:country_code":"CN",
    "gn:dem":173,
    "gn:feature_class":"P",
    "gn:feature_code":"PPL",
    "gn:name":"Lipozhai",
    "gn:population":0,
    "gn:timezone":"Asia/Shanghai",
    "iso:country":"CN",
    "name:und_x_variant":[
        "\u91cc\u5761\u5be8",
        "Lipozhai"
    ],
    "name:zho_x_preferred":[
        "\u91cc\u5761\u5be8"
    ],
    "wof:name":"Lipozhai",
    "wof:placetype":"locality"
},
  "geometry": {"coordinates":[115.9135,24.10963],"type":"Point"}
}