{
  "type": "Feature",
  "properties": {
    "gn:admin1_code":"32.0",
    "gn:asciiname":"Laoguantan",
    "gn:country_code":"CN",
    "gn:dem":298,
    "gn:feature_class":"P",
    "gn:feature_code":"PPL",
    "gn:name":"Laoguantan",
    "gn:population":0,
    "gn:timezone":"Asia/Shanghai",
    "iso:country":"CN",
    "name:zho_x_preferred":[
        "\u8001\u89c2\u6ee9"
    ],
    "wof:name":"Laoguantan",
    "wof:placetype":"locality"
},
  "geometry": {"coordinates":[105.413,30.6199],"type":"Point"}
}