{
  "type": "Feature",
  "properties": {
    "gn:admin1_code":"29",
    "gn:asciiname":"Ganbatang",
    "gn:country_code":"CN",
    "gn:dem":2056,
    "gn:feature_class":"P",
    "gn:feature_code":"PPL",
    "gn:name":"Ganbatang",
    "gn:population":0,
    "gn:timezone":"Asia/Shanghai",
    "iso:country":"CN",
    "name:zho_x_preferred":[
        "\u5e72\u575d\u5858"
    ],
    "wof:name":"Ganbatang",
    "wof:placetype":"locality"
},
  "geometry": {"coordinates":[102.961,24.9305],"type":"Point"}
}