{
  "type": "Feature",
  "properties": {
    "gn:admin1_code":"18",
    "gn:asciiname":"Shayanjing",
    "gn:country_code":"CN",
    "gn:dem":966,
    "gn:feature_class":"P",
    "gn:feature_code":"PPL",
    "gn:name":"Shayanjing",
    "gn:population":0,
    "gn:timezone":"Asia/Shanghai",
    "iso:country":"CN",
    "name:zho_x_preferred":[
        "\u6c99\u773c\u4e95"
    ],
    "wof:name":"Shayanjing",
    "wof:placetype":"locality"
},
  "geometry": {"coordinates":[106.59699999999999,26.0246],"type":"Point"}
}