{
  "type": "Feature",
  "properties": {
    "gn:admin1_code":"9.0",
    "gn:asciiname":"Huanghou",
    "gn:country_code":"CN",
    "gn:dem":235,
    "gn:feature_class":"P",
    "gn:feature_code":"PPLA4",
    "gn:name":"Huanghou",
    "gn:population":0,
    "gn:timezone":"Asia/Shanghai",
    "iso:country":"CN",
    "name:und_x_variant":[
        "\u7687\u540e",
        "Huanghou"
    ],
    "wof:name":"Huanghou",
    "wof:placetype":"locality"
},
  "geometry": {"coordinates":[112.75697,33.48004],"type":"Point"}
}