{
  "type": "Feature",
  "properties": {
    "gn:admin1_code":"32.0",
    "gn:asciiname":"Zhoucitang",
    "gn:country_code":"CN",
    "gn:dem":555,
    "gn:feature_class":"P",
    "gn:feature_code":"PPL",
    "gn:name":"Zhoucitang",
    "gn:population":0,
    "gn:timezone":"Asia/Shanghai",
    "iso:country":"CN",
    "name:zho_x_preferred":[
        "\u5468\u7960\u5802"
    ],
    "wof:name":"Zhoucitang",
    "wof:placetype":"locality"
},
  "geometry": {"coordinates":[103.496,30.325],"type":"Point"}
}