{
  "type": "Feature",
  "properties": {
    "gn:admin1_code":"25",
    "gn:asciiname":"Shijiu",
    "gn:country_code":"CN",
    "gn:dem":18,
    "gn:feature_class":"P",
    "gn:feature_code":"PPL",
    "gn:name":"Shijiu",
    "gn:population":0,
    "gn:timezone":"Asia/Shanghai",
    "iso:country":"CN",
    "name:und_x_variant":[
        "Shijiusuo",
        "Shihkiuso",
        "Shih-chiu-so",
        "Shijiu"
    ],
    "name:zho_x_preferred":[
        "\u77f3\u81fc"
    ],
    "wof:name":"Shijiu",
    "wof:placetype":"locality"
},
  "geometry": {"coordinates":[119.54583,35.39028],"type":"Point"}
}