{
  "type": "Feature",
  "properties": {
    "gn:admin1_code":"19.0",
    "gn:asciiname":"Silama Wobu",
    "gn:country_code":"CN",
    "gn:dem":114,
    "gn:feature_class":"P",
    "gn:feature_code":"PPL",
    "gn:name":"Silama Wobu",
    "gn:population":0,
    "gn:timezone":"Asia/Shanghai",
    "iso:country":"CN",
    "name:und_x_variant":[
        "Silamawobao",
        "\u56db\u5587\u561b\u7a9d\u5821",
        "Silama Wobu"
    ],
    "name:zho_x_preferred":[
        "\u56db\u5587\u561b\u7a9d\u5821"
    ],
    "wof:name":"Silama Wobu",
    "wof:placetype":"locality"
},
  "geometry": {"coordinates":[122.79619,42.45404],"type":"Point"}
}