{
  "type": "Feature",
  "properties": {
    "gn:admin1_code":"16.0",
    "gn:asciiname":"Jiujie",
    "gn:country_code":"CN",
    "gn:dem":99,
    "gn:feature_class":"P",
    "gn:feature_code":"PPL",
    "gn:name":"Jiujie",
    "gn:population":0,
    "gn:timezone":"Asia/Shanghai",
    "iso:country":"CN",
    "name:zho_x_preferred":[
        "\u65e7\u8857"
    ],
    "wof:name":"Jiujie",
    "wof:placetype":"locality"
},
  "geometry": {"coordinates":[109.803,24.6113],"type":"Point"}
}