{
  "type": "Feature",
  "properties": {
    "gn:admin1_code":"2.0",
    "gn:asciiname":"Aoli",
    "gn:country_code":"CN",
    "gn:dem":335,
    "gn:feature_class":"P",
    "gn:feature_code":"PPL",
    "gn:name":"Aoli",
    "gn:population":0,
    "gn:timezone":"Asia/Shanghai",
    "iso:country":"CN",
    "name:zho_x_preferred":[
        "\u5c99\u91cc"
    ],
    "wof:name":"Aoli",
    "wof:placetype":"locality"
},
  "geometry": {"coordinates":[121.02992999999999,29.86989],"type":"Point"}
}