{
  "type": "Feature",
  "properties": {
    "gn:admin1_code":"24.0",
    "gn:asciiname":"Houhuyu",
    "gn:country_code":"CN",
    "gn:dem":1345,
    "gn:feature_class":"P",
    "gn:feature_code":"PPL",
    "gn:name":"Houhuyu",
    "gn:population":0,
    "gn:timezone":"Asia/Shanghai",
    "iso:country":"CN",
    "name:zho_x_preferred":[
        "\u540e\u864e\u5cea"
    ],
    "wof:name":"Houhuyu",
    "wof:placetype":"locality"
},
  "geometry": {"coordinates":[113.76946,37.26751],"type":"Point"}
}