{
  "type": "Feature",
  "properties": {
    "gn:admin1_code":"09",
    "gn:asciiname":"Shaoyuan",
    "gn:cc2":"CN",
    "gn:country_code":"CN",
    "gn:dem":577,
    "gn:feature_class":"P",
    "gn:feature_code":"PPL",
    "gn:name":"Shaoyuan",
    "gn:population":0,
    "gn:timezone":"Asia/Shanghai",
    "iso:country":"CN",
    "name:und_x_variant":[
        "Shao-y\u00fcan-chen",
        "Shaoyuan"
    ],
    "wof:name":"Shaoyuan",
    "wof:placetype":"locality"
},
  "geometry": {"coordinates":[112.12721999999999,35.16],"type":"Point"}
}