{
  "type": "Feature",
  "properties": {
    "gn:admin1_code":"4.0",
    "gn:asciiname":"Yanzhuocun",
    "gn:country_code":"CN",
    "gn:dem":10,
    "gn:feature_class":"P",
    "gn:feature_code":"PPL",
    "gn:name":"Yanzhuocun",
    "gn:population":0,
    "gn:timezone":"Asia/Shanghai",
    "iso:country":"CN",
    "name:zho_x_preferred":[
        "\u4e25\u5353\u6751"
    ],
    "wof:name":"Yanzhuocun",
    "wof:placetype":"locality"
},
  "geometry": {"coordinates":[119.07349000000001,33.52911],"type":"Point"}
}