{
  "type": "Feature",
  "properties": {
    "gn:admin1_code":"11",
    "gn:asciiname":"Dajing",
    "gn:country_code":"CN",
    "gn:dem":213,
    "gn:feature_class":"P",
    "gn:feature_code":"PPL",
    "gn:name":"Dajing",
    "gn:population":0,
    "gn:timezone":"Asia/Shanghai",
    "iso:country":"CN",
    "name:ceb_x_preferred":[
        "Dajing"
    ],
    "name:swe_x_preferred":[
        "Dajing"
    ],
    "wof:name":"Dajing",
    "wof:placetype":"locality"
},
  "geometry": {"coordinates":[111.48083,25.34611],"type":"Point"}
}