{
  "type": "Feature",
  "properties": {
    "gn:admin1_code":"33.0",
    "gn:asciiname":"Gushangou",
    "gn:country_code":"CN",
    "gn:dem":576,
    "gn:feature_class":"P",
    "gn:feature_code":"PPL",
    "gn:name":"Gushangou",
    "gn:population":0,
    "gn:timezone":"Asia/Shanghai",
    "iso:country":"CN",
    "name:zho_x_preferred":[
        "\u8c37\u5c71\u6c9f"
    ],
    "wof:name":"Gushangou",
    "wof:placetype":"locality"
},
  "geometry": {"coordinates":[106.73999999999999,28.7052],"type":"Point"}
}