{
  "type": "Feature",
  "properties": {
    "gn:admin1_code":"05",
    "gn:asciiname":"Xinlitun",
    "gn:cc2":"CN",
    "gn:country_code":"CN",
    "gn:dem":157,
    "gn:feature_class":"P",
    "gn:feature_code":"PPL",
    "gn:name":"Xinlitun",
    "gn:population":0,
    "gn:timezone":"Asia/Shanghai",
    "iso:country":"CN",
    "name:und_x_variant":[
        "Hsin-li-t\u2019un",
        "Sin\u2019litun\u2019",
        "Hsin-li-pao",
        "Xinlitun"
    ],
    "name:zho_x_preferred":[
        "\u65b0\u7acb\u5c6f\u9547"
    ],
    "wof:name":"Xinlitun",
    "wof:placetype":"locality"
},
  "geometry": {"coordinates":[122.43333,45.36667],"type":"Point"}
}