{
  "type": "Feature",
  "properties": {
    "gn:admin1_code":"04",
    "gn:asciiname":"Longhaizhen",
    "gn:cc2":"CN",
    "gn:country_code":"CN",
    "gn:dem":27,
    "gn:feature_class":"P",
    "gn:feature_code":"PPL",
    "gn:name":"Longhaizhen",
    "gn:population":0,
    "gn:timezone":"Asia/Shanghai",
    "iso:country":"CN",
    "name:und_x_variant":[
        "Lung-ch\u2019ih-chi",
        "Lung-hai-chen",
        "Longhaizhen"
    ],
    "wof:name":"Longhaizhen",
    "wof:placetype":"locality"
},
  "geometry": {"coordinates":[118.08333,34.36667],"type":"Point"}
}