{
  "type": "Feature",
  "properties": {
    "gn:admin1_code":"2",
    "gn:asciiname":"Fangcun",
    "gn:country_code":"CN",
    "gn:dem":888,
    "gn:feature_class":"P",
    "gn:feature_code":"PPL",
    "gn:name":"Fangcun",
    "gn:population":0,
    "gn:timezone":"Asia/Shanghai",
    "iso:country":"CN",
    "name:und_x_variant":[
        "\u82b3\u6751",
        "Fangcun"
    ],
    "wof:name":"Fangcun",
    "wof:placetype":"locality"
},
  "geometry": {"coordinates":[119.32643,27.50698],"type":"Point"}
}