{
  "type": "Feature",
  "properties": {
    "gn:admin1_code":"20.0",
    "gn:asciiname":"Diaobinggou",
    "gn:country_code":"CN",
    "gn:dem":1486,
    "gn:feature_class":"P",
    "gn:feature_code":"PPL",
    "gn:name":"Diaobinggou",
    "gn:population":0,
    "gn:timezone":"Asia/Shanghai",
    "iso:country":"CN",
    "name:und_x_variant":[
        "\u8c03\u5175\u6c9f"
    ],
    "wof:name":"Diaobinggou",
    "wof:placetype":"locality"
},
  "geometry": {"coordinates":[113.73519,41.15802],"type":"Point"}
}