{
  "type": "Feature",
  "properties": {
    "gn:admin1_code":"1.0",
    "gn:asciiname":"Wanxucun",
    "gn:country_code":"CN",
    "gn:dem":28,
    "gn:feature_class":"P",
    "gn:feature_code":"PPL",
    "gn:name":"Wanxucun",
    "gn:population":0,
    "gn:timezone":"Asia/Shanghai",
    "iso:country":"CN",
    "name:und_x_variant":[
        "Wanwei"
    ],
    "name:zho_x_preferred":[
        "\u4e07\u5729\u6751"
    ],
    "wof:name":"Wanxucun",
    "wof:placetype":"locality"
},
  "geometry": {"coordinates":[117.08333,33.27778],"type":"Point"}
}