{
  "type": "Feature",
  "properties": {
    "gn:admin1_code":"12.0",
    "gn:asciiname":"Mulongya",
    "gn:country_code":"CN",
    "gn:dem":1204,
    "gn:feature_class":"P",
    "gn:feature_code":"PPL",
    "gn:name":"Mulongya",
    "gn:population":0,
    "gn:timezone":"Asia/Shanghai",
    "iso:country":"CN",
    "name:zho_x_preferred":[
        "\u6728\u9f99\u57ad"
    ],
    "wof:name":"Mulongya",
    "wof:placetype":"locality"
},
  "geometry": {"coordinates":[110.42198,30.6451],"type":"Point"}
}