{
  "type": "Feature",
  "properties": {
    "gn:admin1_code":"26",
    "gn:asciiname":"Beizhu",
    "gn:country_code":"CN",
    "gn:dem":493,
    "gn:feature_class":"P",
    "gn:feature_code":"PPL",
    "gn:name":"Beizhu",
    "gn:population":0,
    "gn:timezone":"Asia/Shanghai",
    "iso:country":"CN",
    "name:und_x_variant":[
        "Beizhucun"
    ],
    "name:zho_x_preferred":[
        "\u5317\u6731"
    ],
    "wof:name":"Beizhu",
    "wof:placetype":"locality"
},
  "geometry": {"coordinates":[108.7075,34.45133],"type":"Point"}
}