{
  "type": "Feature",
  "properties": {
    "gn:admin1_code":"24.0",
    "gn:asciiname":"Yangpingshang",
    "gn:country_code":"CN",
    "gn:dem":1087,
    "gn:feature_class":"P",
    "gn:feature_code":"PPL",
    "gn:name":"Yangpingshang",
    "gn:population":0,
    "gn:timezone":"Asia/Shanghai",
    "iso:country":"CN",
    "name:zho_x_preferred":[
        "\u9633\u576a\u4e0a"
    ],
    "wof:name":"Yangpingshang",
    "wof:placetype":"locality"
},
  "geometry": {"coordinates":[110.76904,38.19083],"type":"Point"}
}