{
  "type": "Feature",
  "properties": {
    "gn:admin1_code":"25",
    "gn:asciiname":"Guliu",
    "gn:cc2":"CN",
    "gn:country_code":"CN",
    "gn:dem":33,
    "gn:feature_class":"P",
    "gn:feature_code":"PPL",
    "gn:name":"Guliu",
    "gn:population":0,
    "gn:timezone":"Asia/Shanghai",
    "iso:country":"CN",
    "name:und_x_variant":[
        "Guliu Zhen",
        "Guliu"
    ],
    "wof:name":"Guliu",
    "wof:placetype":"locality"
},
  "geometry": {"coordinates":[120.71417,36.93333],"type":"Point"}
}