{
  "type": "Feature",
  "properties": {
    "gn:admin1_code":"10.0",
    "gn:asciiname":"Zhijiazhuang",
    "gn:country_code":"CN",
    "gn:dem":1169,
    "gn:feature_class":"P",
    "gn:feature_code":"PPL",
    "gn:name":"Zhijiazhuang",
    "gn:population":0,
    "gn:timezone":"Asia/Shanghai",
    "iso:country":"CN",
    "name:zho_x_preferred":[
        "\u6cbb\u5bb6\u5e84"
    ],
    "wof:name":"Zhijiazhuang",
    "wof:placetype":"locality"
},
  "geometry": {"coordinates":[114.28815,40.6236],"type":"Point"}
}