{
  "type": "Feature",
  "properties": {
    "gn:admin1_code":"29.0",
    "gn:asciiname":"Ailuo Xinzhai",
    "gn:country_code":"CN",
    "gn:dem":1726,
    "gn:feature_class":"P",
    "gn:feature_code":"PPL",
    "gn:name":"Ailuo Xinzhai",
    "gn:population":0,
    "gn:timezone":"Asia/Shanghai",
    "iso:country":"CN",
    "name:zho_x_preferred":[
        "\u57c3\u502e\u65b0\u5be8"
    ],
    "wof:name":"Ailuo Xinzhai",
    "wof:placetype":"locality"
},
  "geometry": {"coordinates":[102.489,23.0273],"type":"Point"}
}