{
  "type": "Feature",
  "properties": {
    "gn:admin1_code":"29.0",
    "gn:asciiname":"Zhamunai",
    "gn:country_code":"CN",
    "gn:dem":1676,
    "gn:feature_class":"P",
    "gn:feature_code":"PPL",
    "gn:name":"Zhamunai",
    "gn:population":0,
    "gn:timezone":"Asia/Shanghai",
    "iso:country":"CN",
    "name:zho_x_preferred":[
        "\u624e\u6bcd\u4e43"
    ],
    "wof:name":"Zhamunai",
    "wof:placetype":"locality"
},
  "geometry": {"coordinates":[99.7694,22.9214],"type":"Point"}
}