{
  "type": "Feature",
  "properties": {
    "gn:admin1_code":"11.0",
    "gn:asciiname":"Aitangli",
    "gn:country_code":"CN",
    "gn:dem":262,
    "gn:feature_class":"P",
    "gn:feature_code":"PPL",
    "gn:name":"Aitangli",
    "gn:population":0,
    "gn:timezone":"Asia/Shanghai",
    "iso:country":"CN",
    "name:zho_x_preferred":[
        "\u827e\u5858\u91cc"
    ],
    "wof:name":"Aitangli",
    "wof:placetype":"locality"
},
  "geometry": {"coordinates":[112.69794,26.24396],"type":"Point"}
}