{
  "type": "Feature",
  "properties": {
    "gn:admin1_code":"19.0",
    "gn:asciiname":"Shizigoucun",
    "gn:country_code":"CN",
    "gn:dem":146,
    "gn:feature_class":"P",
    "gn:feature_code":"PPL",
    "gn:name":"Shizigoucun",
    "gn:population":0,
    "gn:timezone":"Asia/Shanghai",
    "iso:country":"CN",
    "name:zho_x_preferred":[
        "\u72ee\u5b50\u6c9f\u6751"
    ],
    "wof:name":"Shizigoucun",
    "wof:placetype":"locality"
},
  "geometry": {"coordinates":[124.22171000000002,42.68591],"type":"Point"}
}