{
  "type": "Feature",
  "properties": {
    "gn:admin1_code":"25",
    "gn:asciiname":"Weijiazhuang",
    "gn:country_code":"CN",
    "gn:dem":104,
    "gn:feature_class":"P",
    "gn:feature_code":"PPL",
    "gn:name":"Weijiazhuang",
    "gn:population":0,
    "gn:timezone":"Asia/Shanghai",
    "iso:country":"CN",
    "name:zho_x_preferred":[
        "\u97e6\u5bb6\u5e84"
    ],
    "wof:name":"Weijiazhuang",
    "wof:placetype":"locality"
},
  "geometry": {"coordinates":[117.05800000000001,35.7622],"type":"Point"}
}