{
  "type": "Feature",
  "properties": {
    "gn:admin1_code":"12.0",
    "gn:asciiname":"Nanhu",
    "gn:country_code":"CN",
    "gn:dem":19,
    "gn:feature_class":"P",
    "gn:feature_code":"PPL",
    "gn:name":"Nanhu",
    "gn:population":0,
    "gn:timezone":"Asia/Shanghai",
    "iso:country":"CN",
    "name:deu_x_preferred":[
        "Nanhu"
    ],
    "name:und_x_variant":[
        "\u5357\u6e56"
    ],
    "wof:name":"Nanhu",
    "wof:placetype":"locality"
},
  "geometry": {"coordinates":[114.64265,30.28156],"type":"Point"}
}