{
  "type": "Feature",
  "properties": {
    "gn:admin1_code":"8.0",
    "gn:asciiname":"Shahetaicun",
    "gn:country_code":"CN",
    "gn:dem":158,
    "gn:feature_class":"P",
    "gn:feature_code":"PPL",
    "gn:name":"Shahetaicun",
    "gn:population":0,
    "gn:timezone":"Asia/Shanghai",
    "iso:country":"CN",
    "name:zho_x_preferred":[
        "\u6c99\u6cb3\u53f0\u6751"
    ],
    "wof:name":"Shahetaicun",
    "wof:placetype":"locality"
},
  "geometry": {"coordinates":[123.3733,47.17775],"type":"Point"}
}