{
  "type": "Feature",
  "properties": {
    "gn:admin1_code":"19.0",
    "gn:asciiname":"Qinchaigou",
    "gn:country_code":"CN",
    "gn:dem":167,
    "gn:feature_class":"P",
    "gn:feature_code":"PPL",
    "gn:name":"Qinchaigou",
    "gn:population":0,
    "gn:timezone":"Asia/Shanghai",
    "iso:country":"CN",
    "name:und_x_variant":[
        "\u94a6\u5dee\u6c9f"
    ],
    "name:zho_x_preferred":[
        "\u94a6\u5dee\u6c9f"
    ],
    "wof:name":"Qinchaigou",
    "wof:placetype":"locality"
},
  "geometry": {"coordinates":[121.85445,41.81703],"type":"Point"}
}