{
  "type": "Feature",
  "properties": {
    "gn:admin1_code":"30.0",
    "gn:asciiname":"Zhuliao",
    "gn:country_code":"CN",
    "gn:dem":12,
    "gn:feature_class":"P",
    "gn:feature_code":"PPL",
    "gn:name":"Zhuliao",
    "gn:population":0,
    "gn:timezone":"Asia/Shanghai",
    "iso:country":"CN",
    "name:und_x_variant":[
        "Chu-liao",
        "Zhuliao"
    ],
    "name:zho_x_preferred":[
        "\u7af9\u6599"
    ],
    "wof:name":"Zhuliao",
    "wof:placetype":"locality"
},
  "geometry": {"coordinates":[113.34696,23.36481],"type":"Point"}
}