{
  "type": "Feature",
  "properties": {
    "gn:admin1_code":"2.0",
    "gn:asciiname":"Yuanmingsi",
    "gn:country_code":"CN",
    "gn:dem":367,
    "gn:feature_class":"P",
    "gn:feature_code":"PPL",
    "gn:name":"Yuanmingsi",
    "gn:population":0,
    "gn:timezone":"Asia/Shanghai",
    "iso:country":"CN",
    "name:zho_x_preferred":[
        "\u5143\u660e\u5bfa"
    ],
    "wof:name":"Yuanmingsi",
    "wof:placetype":"locality"
},
  "geometry": {"coordinates":[119.64578,28.88222],"type":"Point"}
}