{
  "type": "Feature",
  "properties": {
    "gn:admin1_code":"9",
    "gn:asciiname":"Cuilouji",
    "gn:country_code":"CN",
    "gn:dem":44,
    "gn:feature_class":"P",
    "gn:feature_code":"PPL",
    "gn:name":"Cuilouji",
    "gn:population":0,
    "gn:timezone":"Asia/Shanghai",
    "iso:country":"CN",
    "name:zho_x_preferred":[
        "\u5d14\u697c\u96c6"
    ],
    "wof:name":"Cuilouji",
    "wof:placetype":"locality"
},
  "geometry": {"coordinates":[116.321,34.2979],"type":"Point"}
}