{
  "type": "Feature",
  "properties": {
    "gn:admin1_code":"2.0",
    "gn:asciiname":"Xintang",
    "gn:country_code":"CN",
    "gn:dem":6,
    "gn:feature_class":"P",
    "gn:feature_code":"PPL",
    "gn:name":"Xintang",
    "gn:population":0,
    "gn:timezone":"Asia/Shanghai",
    "iso:country":"CN",
    "name:und_x_variant":[
        "Hsin-t\u2019ang",
        "Xintang",
        "\u65b0\u5858"
    ],
    "wof:name":"Xintang",
    "wof:placetype":"locality"
},
  "geometry": {"coordinates":[119.99106,31.02785],"type":"Point"}
}