{
  "type": "Feature",
  "properties": {
    "gn:admin1_code":"11.0",
    "gn:asciiname":"Huangshitang",
    "gn:country_code":"CN",
    "gn:dem":109,
    "gn:feature_class":"P",
    "gn:feature_code":"PPL",
    "gn:name":"Huangshitang",
    "gn:population":0,
    "gn:timezone":"Asia/Shanghai",
    "iso:country":"CN",
    "name:zho_x_preferred":[
        "\u9ec4\u4ec0\u5858"
    ],
    "wof:name":"Huangshitang",
    "wof:placetype":"locality"
},
  "geometry": {"coordinates":[112.72866,26.58037],"type":"Point"}
}