{
  "type": "Feature",
  "properties": {
    "gn:admin1_code":"14.0",
    "gn:asciiname":"Debacun",
    "gn:country_code":"CN",
    "gn:dem":3481,
    "gn:feature_class":"P",
    "gn:feature_code":"PPL",
    "gn:name":"Debacun",
    "gn:population":0,
    "gn:timezone":"Asia/Urumqi",
    "iso:country":"CN",
    "name:zho_x_preferred":[
        "\u5fb7\u575d\u6751"
    ],
    "wof:name":"Debacun",
    "wof:placetype":"locality"
},
  "geometry": {"coordinates":[98.12289,29.09749],"type":"Point"}
}