{
  "type": "Feature",
  "properties": {
    "gn:admin1_code":"32.0",
    "gn:asciiname":"Luowu",
    "gn:country_code":"CN",
    "gn:dem":1726,
    "gn:feature_class":"P",
    "gn:feature_code":"PPL",
    "gn:name":"Luowu",
    "gn:population":0,
    "gn:timezone":"Asia/Shanghai",
    "iso:country":"CN",
    "name:zho_x_preferred":[
        "\u6d1b\u4e4c"
    ],
    "wof:name":"Luowu",
    "wof:placetype":"locality"
},
  "geometry": {"coordinates":[102.517,27.398],"type":"Point"}
}