{
  "type": "Feature",
  "properties": {
    "gn:admin1_code":"32.0",
    "gn:asciiname":"Qianqiu",
    "gn:country_code":"CN",
    "gn:dem":597,
    "gn:feature_class":"P",
    "gn:feature_code":"PPL",
    "gn:name":"Qianqiu",
    "gn:population":0,
    "gn:timezone":"Asia/Shanghai",
    "iso:country":"CN",
    "name:zho_x_preferred":[
        "\u5343\u4e18"
    ],
    "wof:name":"Qianqiu",
    "wof:placetype":"locality"
},
  "geometry": {"coordinates":[107.126,31.7479],"type":"Point"}
}