{
  "type": "Feature",
  "properties": {
    "gn:admin1_code":"15.0",
    "gn:asciiname":"Donggouli",
    "gn:country_code":"CN",
    "gn:dem":2490,
    "gn:feature_class":"P",
    "gn:feature_code":"PPL",
    "gn:name":"Donggouli",
    "gn:population":0,
    "gn:timezone":"Asia/Shanghai",
    "iso:country":"CN",
    "name:und_x_variant":[
        "\u4e1c\u6c9f\u91cc"
    ],
    "wof:name":"Donggouli",
    "wof:placetype":"locality"
},
  "geometry": {"coordinates":[103.83068,34.50380999999999],"type":"Point"}
}