{
  "type": "Feature",
  "properties": {
    "gn:admin1_code":"11.0",
    "gn:asciiname":"Puzili",
    "gn:country_code":"CN",
    "gn:dem":218,
    "gn:feature_class":"P",
    "gn:feature_code":"PPL",
    "gn:name":"Puzili",
    "gn:population":0,
    "gn:timezone":"Asia/Shanghai",
    "iso:country":"CN",
    "name:zho_x_preferred":[
        "\u94fa\u5b50\u91cc"
    ],
    "wof:name":"Puzili",
    "wof:placetype":"locality"
},
  "geometry": {"coordinates":[113.42014,26.35125],"type":"Point"}
}