{
  "type": "Feature",
  "properties": {
    "gn:admin1_code":"16.0",
    "gn:asciiname":"Guzhan",
    "gn:country_code":"CN",
    "gn:dem":139,
    "gn:feature_class":"P",
    "gn:feature_code":"PPL",
    "gn:name":"Guzhan",
    "gn:population":0,
    "gn:timezone":"Asia/Shanghai",
    "iso:country":"CN",
    "name:zho_x_preferred":[
        "\u53e4\u76cf"
    ],
    "wof:name":"Guzhan",
    "wof:placetype":"locality"
},
  "geometry": {"coordinates":[109.98099999999999,24.5064],"type":"Point"}
}