{
  "type": "Feature",
  "properties": {
    "gn:admin1_code":"10.0",
    "gn:asciiname":"Shangsuzhuang",
    "gn:country_code":"CN",
    "gn:dem":998,
    "gn:feature_class":"P",
    "gn:feature_code":"PPL",
    "gn:name":"Shangsuzhuang",
    "gn:population":0,
    "gn:timezone":"Asia/Shanghai",
    "iso:country":"CN",
    "name:zho_x_preferred":[
        "\u4e0a\u82cf\u5e84"
    ],
    "wof:name":"Shangsuzhuang",
    "wof:placetype":"locality"
},
  "geometry": {"coordinates":[114.6528,39.77408],"type":"Point"}
}