{
  "type": "Feature",
  "properties": {
    "gn:admin1_code":"7.0",
    "gn:asciiname":"Shangyuan",
    "gn:country_code":"CN",
    "gn:dem":386,
    "gn:feature_class":"P",
    "gn:feature_code":"PPL",
    "gn:name":"Shangyuan",
    "gn:population":0,
    "gn:timezone":"Asia/Shanghai",
    "iso:country":"CN",
    "name:zho_x_preferred":[
        "\u4e0a\u6c85"
    ],
    "name:zho_x_variant":[
        "\u4e0a\u5143"
    ],
    "wof:name":"Shangyuan",
    "wof:placetype":"locality"
},
  "geometry": {"coordinates":[117.34572,27.49961],"type":"Point"}
}