{
  "type": "Feature",
  "properties": {
    "gn:admin1_code":"32.0",
    "gn:asciiname":"Shidiaolou",
    "gn:country_code":"CN",
    "gn:dem":2994,
    "gn:feature_class":"P",
    "gn:feature_code":"PPL",
    "gn:name":"Shidiaolou",
    "gn:population":0,
    "gn:timezone":"Asia/Shanghai",
    "iso:country":"CN",
    "name:zho_x_preferred":[
        "\u77f3\u7889\u697c"
    ],
    "wof:name":"Shidiaolou",
    "wof:placetype":"locality"
},
  "geometry": {"coordinates":[103.41847,32.02215],"type":"Point"}
}