{
  "type": "Feature",
  "properties": {
    "gn:admin1_code":"11.0",
    "gn:asciiname":"Longxihu",
    "gn:country_code":"CN",
    "gn:dem":73,
    "gn:feature_class":"P",
    "gn:feature_code":"PPL",
    "gn:name":"Longxihu",
    "gn:population":0,
    "gn:timezone":"Asia/Shanghai",
    "iso:country":"CN",
    "name:zho_x_preferred":[
        "\u9f99\u897f\u6e56"
    ],
    "wof:name":"Longxihu",
    "wof:placetype":"locality"
},
  "geometry": {"coordinates":[113.13124999999999,26.96571],"type":"Point"}
}