{
  "type": "Feature",
  "properties": {
    "gn:admin1_code":"13.0",
    "gn:asciiname":"Digar",
    "gn:country_code":"CN",
    "gn:dem":-21,
    "gn:feature_class":"P",
    "gn:feature_code":"PPL",
    "gn:name":"Digar",
    "gn:population":0,
    "gn:timezone":"Asia/Urumqi",
    "iso:country":"CN",
    "name:uig_x_preferred":[
        "Digar"
    ],
    "name:und_x_variant":[
        "Dikaner"
    ],
    "name:zho_x_preferred":[
        "\u8fea\u574e\u5c14"
    ],
    "wof:name":"Digar",
    "wof:placetype":"locality"
},
  "geometry": {"coordinates":[89.89191,42.57644000000001],"type":"Point"}
}