{
  "type": "Feature",
  "properties": {
    "gn:admin1_code":"3.0",
    "gn:asciiname":"Paizui Liujia",
    "gn:country_code":"CN",
    "gn:dem":28,
    "gn:feature_class":"P",
    "gn:feature_code":"PPL",
    "gn:name":"Paizui Liujia",
    "gn:population":0,
    "gn:timezone":"Asia/Shanghai",
    "iso:country":"CN",
    "name:und_x_variant":[
        "\u6392\u5480\u5218\u5bb6"
    ],
    "wof:name":"Paizui Liujia",
    "wof:placetype":"locality"
},
  "geometry": {"coordinates":[116.27313999999998,28.34319],"type":"Point"}
}