{
  "type": "Feature",
  "properties": {
    "gn:admin1_code":"19.0",
    "gn:asciiname":"Liuzhugou",
    "gn:country_code":"CN",
    "gn:dem":518,
    "gn:feature_class":"P",
    "gn:feature_code":"PPL",
    "gn:name":"Liuzhugou",
    "gn:population":0,
    "gn:timezone":"Asia/Shanghai",
    "iso:country":"CN",
    "name:zho_x_preferred":[
        "\u5218\u4f4f\u6c9f"
    ],
    "wof:name":"Liuzhugou",
    "wof:placetype":"locality"
},
  "geometry": {"coordinates":[119.38372,40.77011],"type":"Point"}
}