{
  "type": "Feature",
  "properties": {
    "gn:admin1_code":"10",
    "gn:asciiname":"Xiaomiaowa",
    "gn:country_code":"CN",
    "gn:dem":1398,
    "gn:feature_class":"P",
    "gn:feature_code":"PPL",
    "gn:name":"Xiaomiaowa",
    "gn:population":0,
    "gn:timezone":"Asia/Shanghai",
    "iso:country":"CN",
    "name:zho_x_preferred":[
        "\u5c0f\u5e99\u6d3c"
    ],
    "wof:name":"Xiaomiaowa",
    "wof:placetype":"locality"
},
  "geometry": {"coordinates":[114.8693,41.51159000000001],"type":"Point"}
}