{
  "type": "Feature",
  "properties": {
    "gn:admin1_code":"1.0",
    "gn:asciiname":"Yuqiaocun",
    "gn:country_code":"CN",
    "gn:dem":17,
    "gn:feature_class":"P",
    "gn:feature_code":"PPL",
    "gn:name":"Yuqiaocun",
    "gn:population":0,
    "gn:timezone":"Asia/Shanghai",
    "iso:country":"CN",
    "name:zho_x_preferred":[
        "\u4f59\u6865\u6751"
    ],
    "wof:name":"Yuqiaocun",
    "wof:placetype":"locality"
},
  "geometry": {"coordinates":[117.12848,30.5249],"type":"Point"}
}