{
  "type": "Feature",
  "properties": {
    "gn:admin1_code":"24.0",
    "gn:asciiname":"Shapingzecun",
    "gn:country_code":"CN",
    "gn:dem":625,
    "gn:feature_class":"P",
    "gn:feature_code":"PPL",
    "gn:name":"Shapingzecun",
    "gn:population":0,
    "gn:timezone":"Asia/Shanghai",
    "iso:country":"CN",
    "name:zho_x_preferred":[
        "\u6c99\u576a\u5219\u6751"
    ],
    "wof:name":"Shapingzecun",
    "wof:placetype":"locality"
},
  "geometry": {"coordinates":[110.68438999999999,37.29931],"type":"Point"}
}