{
  "type": "Feature",
  "properties": {
    "gn:admin1_code":"11.0",
    "gn:asciiname":"Chiziwan",
    "gn:country_code":"CN",
    "gn:dem":58,
    "gn:feature_class":"P",
    "gn:feature_code":"PPL",
    "gn:name":"Chiziwan",
    "gn:population":0,
    "gn:timezone":"Asia/Shanghai",
    "iso:country":"CN",
    "name:zho_x_preferred":[
        "\u6c60\u5b50\u6e7e"
    ],
    "wof:name":"Chiziwan",
    "wof:placetype":"locality"
},
  "geometry": {"coordinates":[112.82144,28.0193],"type":"Point"}
}