{
  "type": "Feature",
  "properties": {
    "gn:admin1_code":"4.0",
    "gn:asciiname":"Xiaozhuang",
    "gn:country_code":"CN",
    "gn:dem":3,
    "gn:feature_class":"P",
    "gn:feature_code":"PPL",
    "gn:name":"Xiaozhuang",
    "gn:population":0,
    "gn:timezone":"Asia/Shanghai",
    "iso:country":"CN",
    "name:ceb_x_preferred":[
        "Xiaozhuang"
    ],
    "name:zho_x_preferred":[
        "\u8096\u5e84"
    ],
    "wof:name":"Xiaozhuang",
    "wof:placetype":"locality"
},
  "geometry": {"coordinates":[120.12573999999999,32.75961],"type":"Point"}
}