{
  "type": "Feature",
  "properties": {
    "gn:admin1_code":"12",
    "gn:asciiname":"Hengdian",
    "gn:country_code":"CN",
    "gn:dem":51,
    "gn:feature_class":"P",
    "gn:feature_code":"PPLA4",
    "gn:name":"Hengdian",
    "gn:population":0,
    "gn:timezone":"Asia/Shanghai",
    "iso:country":"CN",
    "name:swe_x_preferred":[
        "Hengdian"
    ],
    "name:und_x_variant":[
        "Heng-tien",
        "\u6a2a\u5e97",
        "Hengdian Jiedao",
        "\u6a2a\u5e97\u8857\u9053"
    ],
    "wof:name":"Hengdian",
    "wof:placetype":"locality"
},
  "geometry": {"coordinates":[114.29172,30.80532],"type":"Point"}
}