{
  "type": "Feature",
  "properties": {
    "gn:admin1_code":"8.0",
    "gn:asciiname":"Tangguangfutun",
    "gn:country_code":"CN",
    "gn:dem":123,
    "gn:feature_class":"P",
    "gn:feature_code":"PPL",
    "gn:name":"Tangguangfutun",
    "gn:population":0,
    "gn:timezone":"Asia/Shanghai",
    "iso:country":"CN",
    "name:zho_x_preferred":[
        "\u5510\u5e7f\u5bcc\u5c6f"
    ],
    "wof:name":"Tangguangfutun",
    "wof:placetype":"locality"
},
  "geometry": {"coordinates":[126.26384,45.81496],"type":"Point"}
}