{
  "type": "Feature",
  "properties": {
    "gn:admin1_code":"3.0",
    "gn:asciiname":"Xinwushang",
    "gn:country_code":"CN",
    "gn:dem":152,
    "gn:feature_class":"P",
    "gn:feature_code":"PPL",
    "gn:name":"Xinwushang",
    "gn:population":0,
    "gn:timezone":"Asia/Shanghai",
    "iso:country":"CN",
    "name:und_x_variant":[
        "\u65b0\u5c4b\u4e0a"
    ],
    "wof:name":"Xinwushang",
    "wof:placetype":"locality"
},
  "geometry": {"coordinates":[115.57753999999998,26.87741],"type":"Point"}
}