{
  "type": "Feature",
  "properties": {
    "gn:admin1_code":"29.0",
    "gn:asciiname":"Xinsha",
    "gn:country_code":"CN",
    "gn:dem":1880,
    "gn:feature_class":"P",
    "gn:feature_code":"PPL",
    "gn:name":"Xinsha",
    "gn:population":0,
    "gn:timezone":"Asia/Shanghai",
    "iso:country":"CN",
    "name:zho_x_preferred":[
        "\u65b0\u6c99"
    ],
    "wof:name":"Xinsha",
    "wof:placetype":"locality"
},
  "geometry": {"coordinates":[102.873,25.4881],"type":"Point"}
}