{
  "type": "Feature",
  "properties": {
    "gn:admin1_code":"02",
    "gn:asciiname":"Songxia",
    "gn:country_code":"CN",
    "gn:dem":13,
    "gn:feature_class":"P",
    "gn:feature_code":"PPLA4",
    "gn:name":"Songxia",
    "gn:population":0,
    "gn:timezone":"Asia/Shanghai",
    "iso:country":"CN",
    "name:und_x_variant":[
        "Sung-hsia",
        "Sung-hsia-chen",
        "Songxia",
        "\u5d27\u53a6",
        "Songxia Zhen",
        "\u5d27\u53a6\u9547"
    ],
    "wof:name":"Songxia",
    "wof:placetype":"locality"
},
  "geometry": {"coordinates":[120.84125,30.09763],"type":"Point"}
}