{
  "type": "Feature",
  "properties": {
    "gn:admin1_code":"4.0",
    "gn:asciiname":"Zhinancun",
    "gn:country_code":"CN",
    "gn:dem":6,
    "gn:feature_class":"P",
    "gn:feature_code":"PPL",
    "gn:name":"Zhinancun",
    "gn:population":0,
    "gn:timezone":"Asia/Shanghai",
    "iso:country":"CN",
    "name:und_x_variant":[
        "\u5fd7\u5357\u6751"
    ],
    "wof:name":"Zhinancun",
    "wof:placetype":"locality"
},
  "geometry": {"coordinates":[121.06435999999999,31.95136],"type":"Point"}
}