{
  "type": "Feature",
  "properties": {
    "gn:admin1_code":"30.0",
    "gn:asciiname":"Lingxiacun",
    "gn:country_code":"CN",
    "gn:dem":394,
    "gn:feature_class":"P",
    "gn:feature_code":"PPL",
    "gn:name":"Lingxiacun",
    "gn:population":0,
    "gn:timezone":"Asia/Shanghai",
    "iso:country":"CN",
    "name:zho_x_preferred":[
        "\u5cad\u4e0b\u6751"
    ],
    "wof:name":"Lingxiacun",
    "wof:placetype":"locality"
},
  "geometry": {"coordinates":[115.83737000000001,23.38455],"type":"Point"}
}