{
  "type": "Feature",
  "properties": {
    "gn:admin1_code":"4.0",
    "gn:asciiname":"Jijiayuan",
    "gn:country_code":"CN",
    "gn:dem":7,
    "gn:feature_class":"P",
    "gn:feature_code":"PPL",
    "gn:name":"Jijiayuan",
    "gn:population":0,
    "gn:timezone":"Asia/Shanghai",
    "iso:country":"CN",
    "name:und_x_variant":[
        "\u5b63\u5bb6\u56ed"
    ],
    "wof:name":"Jijiayuan",
    "wof:placetype":"locality"
},
  "geometry": {"coordinates":[121.24871,32.40479000000001],"type":"Point"}
}