{
  "type": "Feature",
  "properties": {
    "gn:admin1_code":"24.0",
    "gn:asciiname":"Weifen",
    "gn:country_code":"CN",
    "gn:dem":1213,
    "gn:feature_class":"P",
    "gn:feature_code":"PPLA3",
    "gn:name":"Weifen",
    "gn:population":0,
    "gn:timezone":"Asia/Shanghai",
    "iso:country":"CN",
    "name:und_x_variant":[
        "Hinghsien",
        "Hsing-hsien",
        "Hsing",
        "Xingxian",
        "Weifen",
        "Xing Xian",
        "Weifen Zhen",
        "\u5174\u53bf",
        "\u851a\u6c7e\u9547"
    ],
    "name:zho_x_preferred":[
        "Sinsyan\u2019"
    ],
    "name:zho_x_variant":[
        "\u851a\u6c7e"
    ],
    "wof:name":"Weifen",
    "wof:placetype":"locality"
},
  "geometry": {"coordinates":[111.16664,38.48064],"type":"Point"}
}