{
  "type": "Feature",
  "properties": {
    "gn:admin1_code":"24.0",
    "gn:asciiname":"Sheke",
    "gn:country_code":"CN",
    "gn:dem":1919,
    "gn:feature_class":"P",
    "gn:feature_code":"PPL",
    "gn:name":"Sheke",
    "gn:population":0,
    "gn:timezone":"Asia/Shanghai",
    "iso:country":"CN",
    "name:zho_x_preferred":[
        "\u793e\u79d1"
    ],
    "wof:name":"Sheke",
    "wof:placetype":"locality"
},
  "geometry": {"coordinates":[112.02409,38.80427],"type":"Point"}
}