{
  "type": "Feature",
  "properties": {
    "gn:admin1_code":"14.0",
    "gn:asciiname":"Zhouqianma",
    "gn:country_code":"CN",
    "gn:dem":4391,
    "gn:feature_class":"P",
    "gn:feature_code":"PPL",
    "gn:name":"Zhouqianma",
    "gn:population":0,
    "gn:timezone":"Asia/Urumqi",
    "iso:country":"CN",
    "name:zho_x_preferred":[
        "\u5468\u524d\u9a6c"
    ],
    "wof:name":"Zhouqianma",
    "wof:placetype":"locality"
},
  "geometry": {"coordinates":[96.33582,31.05032000000001],"type":"Point"}
}