{
  "type": "Feature",
  "properties": {
    "gn:admin1_code":"5.0",
    "gn:asciiname":"Houpaoyan",
    "gn:country_code":"CN",
    "gn:dem":158,
    "gn:feature_class":"P",
    "gn:feature_code":"PPL",
    "gn:name":"Houpaoyan",
    "gn:population":0,
    "gn:timezone":"Asia/Shanghai",
    "iso:country":"CN",
    "name:zho_x_preferred":[
        "\u540e\u6ce1\u6cbf"
    ],
    "wof:name":"Houpaoyan",
    "wof:placetype":"locality"
},
  "geometry": {"coordinates":[122.57671999999999,44.70552],"type":"Point"}
}