{
  "type": "Feature",
  "properties": {
    "gn:admin1_code":"19.0",
    "gn:asciiname":"Xiaonuhu",
    "gn:country_code":"CN",
    "gn:dem":174,
    "gn:feature_class":"P",
    "gn:feature_code":"PPL",
    "gn:name":"Xiaonuhu",
    "gn:population":0,
    "gn:timezone":"Asia/Shanghai",
    "iso:country":"CN",
    "name:zho_x_preferred":[
        "\u5c0f\u6012\u864e"
    ],
    "wof:name":"Xiaonuhu",
    "wof:placetype":"locality"
},
  "geometry": {"coordinates":[121.97199999999999,42.3601],"type":"Point"}
}