{
  "type": "Feature",
  "properties": {
    "gn:admin1_code":"19.0",
    "gn:asciiname":"Gaolijing",
    "gn:country_code":"CN",
    "gn:dem":134,
    "gn:feature_class":"P",
    "gn:feature_code":"PPL",
    "gn:name":"Gaolijing",
    "gn:population":0,
    "gn:timezone":"Asia/Shanghai",
    "iso:country":"CN",
    "name:zho_x_preferred":[
        "\u9ad8\u4e3d\u4e95"
    ],
    "wof:name":"Gaolijing",
    "wof:placetype":"locality"
},
  "geometry": {"coordinates":[123.967,42.9048],"type":"Point"}
}