{
  "type": "Feature",
  "properties": {
    "gn:admin1_code":"11.0",
    "gn:asciiname":"Lianmeng",
    "gn:country_code":"CN",
    "gn:dem":530,
    "gn:feature_class":"P",
    "gn:feature_code":"PPL",
    "gn:name":"Lianmeng",
    "gn:population":0,
    "gn:timezone":"Asia/Shanghai",
    "iso:country":"CN",
    "name:zho_x_preferred":[
        "\u8054\u76df"
    ],
    "wof:name":"Lianmeng",
    "wof:placetype":"locality"
},
  "geometry": {"coordinates":[109.46523999999999,29.42182],"type":"Point"}
}