{
  "type": "Feature",
  "properties": {
    "gn:admin1_code":"25.0",
    "gn:asciiname":"Tanjiazhuang",
    "gn:country_code":"CN",
    "gn:dem":73,
    "gn:feature_class":"P",
    "gn:feature_code":"PPL",
    "gn:name":"Tanjiazhuang",
    "gn:population":0,
    "gn:timezone":"Asia/Shanghai",
    "iso:country":"CN",
    "name:zho_x_preferred":[
        "\u8c2d\u5bb6\u5e84"
    ],
    "wof:name":"Tanjiazhuang",
    "wof:placetype":"locality"
},
  "geometry": {"coordinates":[119.29837000000001,35.94382],"type":"Point"}
}