{
  "type": "Feature",
  "properties": {
    "gn:admin1_code":"3.0",
    "gn:asciiname":"Cangqian",
    "gn:country_code":"CN",
    "gn:dem":193,
    "gn:feature_class":"P",
    "gn:feature_code":"PPL",
    "gn:name":"Cangqian",
    "gn:population":0,
    "gn:timezone":"Asia/Shanghai",
    "iso:country":"CN",
    "name:und_x_variant":[
        "\u4ed3\u524d"
    ],
    "wof:name":"Cangqian",
    "wof:placetype":"locality"
},
  "geometry": {"coordinates":[115.51233000000001,26.76292],"type":"Point"}
}