{
  "type": "Feature",
  "properties": {
    "gn:admin1_code":"29.0",
    "gn:asciiname":"Hongbu Zhaizi",
    "gn:country_code":"CN",
    "gn:dem":2297,
    "gn:feature_class":"P",
    "gn:feature_code":"PPL",
    "gn:name":"Hongbu Zhaizi",
    "gn:population":0,
    "gn:timezone":"Asia/Shanghai",
    "iso:country":"CN",
    "name:und_x_variant":[
        "\u7ea2\u5e03\u5be8\u5b50"
    ],
    "wof:name":"Hongbu Zhaizi",
    "wof:placetype":"locality"
},
  "geometry": {"coordinates":[103.297,27.2307],"type":"Point"}
}