{
  "type": "Feature",
  "properties": {
    "gn:admin1_code":"26.0",
    "gn:asciiname":"Yongquansi",
    "gn:country_code":"CN",
    "gn:dem":711,
    "gn:feature_class":"P",
    "gn:feature_code":"PPL",
    "gn:name":"Yongquansi",
    "gn:population":0,
    "gn:timezone":"Asia/Shanghai",
    "iso:country":"CN",
    "name:zho_x_preferred":[
        "\u62e5\u6cc9\u5bfa"
    ],
    "wof:name":"Yongquansi",
    "wof:placetype":"locality"
},
  "geometry": {"coordinates":[109.05656,33.06967],"type":"Point"}
}