{
  "type": "Feature",
  "properties": {
    "gn:admin1_code":"4.0",
    "gn:asciiname":"Shuangloucun",
    "gn:country_code":"CN",
    "gn:dem":6,
    "gn:feature_class":"P",
    "gn:feature_code":"PPL",
    "gn:name":"Shuangloucun",
    "gn:population":0,
    "gn:timezone":"Asia/Shanghai",
    "iso:country":"CN",
    "name:zho_x_preferred":[
        "\u53cc\u5a04\u6751"
    ],
    "wof:name":"Shuangloucun",
    "wof:placetype":"locality"
},
  "geometry": {"coordinates":[120.60965,31.53238],"type":"Point"}
}