{
  "type": "Feature",
  "properties": {
    "gn:admin1_code":"32.0",
    "gn:asciiname":"Shi'echang",
    "gn:country_code":"CN",
    "gn:dem":333,
    "gn:feature_class":"P",
    "gn:feature_code":"PPL",
    "gn:name":"Shi\u2019echang",
    "gn:population":0,
    "gn:timezone":"Asia/Shanghai",
    "iso:country":"CN",
    "name:zho_x_preferred":[
        "\u77f3\u9e45\u573a"
    ],
    "name:zho_x_variant":[
        "Shi\u2019echang"
    ],
    "wof:name":"Shi'echang",
    "wof:placetype":"locality"
},
  "geometry": {"coordinates":[105.27901,29.26881],"type":"Point"}
}