{
  "type": "Feature",
  "properties": {
    "gn:admin1_code":"12.0",
    "gn:asciiname":"Xiangjiahe",
    "gn:cc2":"CN",
    "gn:country_code":"CN",
    "gn:dem":123,
    "gn:feature_class":"P",
    "gn:feature_code":"PPL",
    "gn:name":"Xiangjiahe",
    "gn:population":0,
    "gn:timezone":"Asia/Shanghai",
    "iso:country":"CN",
    "name:und_x_variant":[
        "Hsiang-chia-ho",
        "Xiangjiahe"
    ],
    "wof:name":"Xiangjiahe",
    "wof:placetype":"locality"
},
  "geometry": {"coordinates":[114.79722,31.47472],"type":"Point"}
}