{
  "type": "Feature",
  "properties": {
    "gn:admin1_code":"18.0",
    "gn:asciiname":"Xiaba",
    "gn:country_code":"CN",
    "gn:dem":864,
    "gn:feature_class":"P",
    "gn:feature_code":"PPL",
    "gn:name":"Xiaba",
    "gn:population":0,
    "gn:timezone":"Asia/Shanghai",
    "iso:country":"CN",
    "name:zho_x_preferred":[
        "\u4e0b\u575d"
    ],
    "wof:name":"Xiaba",
    "wof:placetype":"locality"
},
  "geometry": {"coordinates":[107.496,26.3714],"type":"Point"}
}