{
  "type": "Feature",
  "properties": {
    "gn:admin1_code":"16.0",
    "gn:asciiname":"Liunie",
    "gn:country_code":"CN",
    "gn:dem":521,
    "gn:feature_class":"P",
    "gn:feature_code":"PPL",
    "gn:name":"Liunie",
    "gn:population":0,
    "gn:timezone":"Asia/Shanghai",
    "iso:country":"CN",
    "name:zho_x_preferred":[
        "\u516d\u4e5c"
    ],
    "wof:name":"Liunie",
    "wof:placetype":"locality"
},
  "geometry": {"coordinates":[106.04300000000001,24.3996],"type":"Point"}
}