{
  "type": "Feature",
  "properties": {
    "gn:admin1_code":"30.0",
    "gn:asciiname":"Heshuikou",
    "gn:country_code":"CN",
    "gn:dem":34,
    "gn:feature_class":"P",
    "gn:feature_code":"PPL",
    "gn:name":"Heshuikou",
    "gn:population":0,
    "gn:timezone":"Asia/Shanghai",
    "iso:country":"CN",
    "name:zho_x_preferred":[
        "\u5408\u6c34\u53e3"
    ],
    "wof:name":"Heshuikou",
    "wof:placetype":"locality"
},
  "geometry": {"coordinates":[113.20305999999999,23.92056],"type":"Point"}
}