{
  "type": "Feature",
  "properties": {
    "gn:admin1_code":"2.0",
    "gn:asciiname":"Lannishan",
    "gn:country_code":"CN",
    "gn:dem":276,
    "gn:feature_class":"P",
    "gn:feature_code":"PPL",
    "gn:name":"Lannishan",
    "gn:population":0,
    "gn:timezone":"Asia/Shanghai",
    "iso:country":"CN",
    "name:zho_x_preferred":[
        "\u70c2\u6ce5\u5c71"
    ],
    "wof:name":"Lannishan",
    "wof:placetype":"locality"
},
  "geometry": {"coordinates":[118.91419999999999,29.22933],"type":"Point"}
}