{
  "type": "Feature",
  "properties": {
    "gn:admin1_code":"14.0",
    "gn:asciiname":"Qudengpeiwei",
    "gn:country_code":"CN",
    "gn:dem":4656,
    "gn:feature_class":"P",
    "gn:feature_code":"PPL",
    "gn:name":"Qudengpeiwei",
    "gn:population":0,
    "gn:timezone":"Asia/Urumqi",
    "iso:country":"CN",
    "name:zho_x_preferred":[
        "\u66f2\u767b\u57f9\u59d4"
    ],
    "wof:name":"Qudengpeiwei",
    "wof:placetype":"locality"
},
  "geometry": {"coordinates":[83.4213,29.6231],"type":"Point"}
}