{
  "type": "Feature",
  "properties": {
    "gn:admin1_code":"10.0",
    "gn:asciiname":"Shitizi",
    "gn:country_code":"CN",
    "gn:dem":43,
    "gn:feature_class":"P",
    "gn:feature_code":"PPL",
    "gn:name":"Shitizi",
    "gn:population":0,
    "gn:timezone":"Asia/Shanghai",
    "iso:country":"CN",
    "name:zho_x_preferred":[
        "\u77f3\u68af\u5b50"
    ],
    "wof:name":"Shitizi",
    "wof:placetype":"locality"
},
  "geometry": {"coordinates":[118.81599,39.86398],"type":"Point"}
}