{
  "type": "Feature",
  "properties": {
    "gn:admin1_code":"7.0",
    "gn:asciiname":"Liujiaotai",
    "gn:country_code":"CN",
    "gn:dem":441,
    "gn:feature_class":"P",
    "gn:feature_code":"PPL",
    "gn:name":"Liujiaotai",
    "gn:population":0,
    "gn:timezone":"Asia/Shanghai",
    "iso:country":"CN",
    "name:zho_x_preferred":[
        "\u516d\u89d2\u53f0"
    ],
    "wof:name":"Liujiaotai",
    "wof:placetype":"locality"
},
  "geometry": {"coordinates":[119.20945,26.97471],"type":"Point"}
}