{
  "type": "Feature",
  "properties": {
    "gn:admin1_code":"26.0",
    "gn:asciiname":"Xinmiaocun",
    "gn:country_code":"CN",
    "gn:dem":559,
    "gn:feature_class":"P",
    "gn:feature_code":"PPL",
    "gn:name":"Xinmiaocun",
    "gn:population":0,
    "gn:timezone":"Asia/Shanghai",
    "iso:country":"CN",
    "name:zho_x_preferred":[
        "\u65b0\u5e99\u6751"
    ],
    "wof:name":"Xinmiaocun",
    "wof:placetype":"locality"
},
  "geometry": {"coordinates":[111.00747,33.3731],"type":"Point"}
}