{
  "type": "Feature",
  "properties": {
    "gn:admin1_code":"9.0",
    "gn:asciiname":"Liuzhaozhuang",
    "gn:country_code":"CN",
    "gn:dem":163,
    "gn:feature_class":"P",
    "gn:feature_code":"PPL",
    "gn:name":"Liuzhaozhuang",
    "gn:population":0,
    "gn:timezone":"Asia/Shanghai",
    "iso:country":"CN",
    "name:zho_x_preferred":[
        "\u5218\u627e\u5e84"
    ],
    "wof:name":"Liuzhaozhuang",
    "wof:placetype":"locality"
},
  "geometry": {"coordinates":[112.69987,33.21944000000001],"type":"Point"}
}