{
  "type": "Feature",
  "properties": {
    "gn:admin1_code":"25.0",
    "gn:asciiname":"Chengzi",
    "gn:country_code":"CN",
    "gn:dem":122,
    "gn:feature_class":"P",
    "gn:feature_code":"PPL",
    "gn:name":"Chengzi",
    "gn:population":0,
    "gn:timezone":"Asia/Shanghai",
    "iso:country":"CN",
    "name:zho_x_preferred":[
        "\u57ce\u5b50"
    ],
    "wof:name":"Chengzi",
    "wof:placetype":"locality"
},
  "geometry": {"coordinates":[120.50454000000001,37.21946],"type":"Point"}
}