{
  "type": "Feature",
  "properties": {
    "gn:admin1_code":"19.0",
    "gn:asciiname":"Shanghuang Jiagou",
    "gn:country_code":"CN",
    "gn:dem":592,
    "gn:feature_class":"P",
    "gn:feature_code":"PPL",
    "gn:name":"Shanghuang Jiagou",
    "gn:population":0,
    "gn:timezone":"Asia/Shanghai",
    "iso:country":"CN",
    "name:und_x_variant":[
        "\u4e0a\u9ec4\u5bb6\u6c9f"
    ],
    "name:zho_x_preferred":[
        "\u4e0a\u9ec4\u5bb6\u6c9f"
    ],
    "wof:name":"Shanghuang Jiagou",
    "wof:placetype":"locality"
},
  "geometry": {"coordinates":[119.452,40.6108],"type":"Point"}
}