{
  "type": "Feature",
  "properties": {
    "gn:admin1_code":"11.0",
    "gn:asciiname":"Miaozuihe",
    "gn:country_code":"CN",
    "gn:dem":427,
    "gn:feature_class":"P",
    "gn:feature_code":"PPL",
    "gn:name":"Miaozuihe",
    "gn:population":0,
    "gn:timezone":"Asia/Shanghai",
    "iso:country":"CN",
    "name:zho_x_preferred":[
        "\u5e99\u5480\u6cb3"
    ],
    "wof:name":"Miaozuihe",
    "wof:placetype":"locality"
},
  "geometry": {"coordinates":[110.06356,29.6153],"type":"Point"}
}