{
  "type": "Feature",
  "properties": {
    "gn:admin1_code":"15",
    "gn:asciiname":"Qilian",
    "gn:country_code":"CN",
    "gn:dem":2266,
    "gn:feature_class":"P",
    "gn:feature_code":"PPL",
    "gn:name":"Qilian",
    "gn:population":0,
    "gn:timezone":"Asia/Shanghai",
    "iso:country":"CN",
    "name:und_x_variant":[
        "Ch\u2019i-lien",
        "Qilian"
    ],
    "name:zho_x_preferred":[
        "\u7941\u8054"
    ],
    "wof:name":"Qilian",
    "wof:placetype":"locality"
},
  "geometry": {"coordinates":[103.52800000000001,36.7604],"type":"Point"}
}