{
  "type": "Feature",
  "properties": {
    "gn:admin1_code":"10",
    "gn:asciiname":"Changshenggou",
    "gn:country_code":"CN",
    "gn:dem":1416,
    "gn:feature_class":"P",
    "gn:feature_code":"PPL",
    "gn:name":"Changshenggou",
    "gn:population":0,
    "gn:timezone":"Asia/Shanghai",
    "iso:country":"CN",
    "name:zho_x_preferred":[
        "\u5e38\u80dc\u6c9f"
    ],
    "wof:name":"Changshenggou",
    "wof:placetype":"locality"
},
  "geometry": {"coordinates":[113.91795,41.10844],"type":"Point"}
}