{
  "type": "Feature",
  "properties": {
    "gn:admin1_code":"19.0",
    "gn:asciiname":"Shansong Buzi",
    "gn:country_code":"CN",
    "gn:dem":346,
    "gn:feature_class":"P",
    "gn:feature_code":"PPL",
    "gn:name":"Shansong Buzi",
    "gn:population":0,
    "gn:timezone":"Asia/Shanghai",
    "iso:country":"CN",
    "name:und_x_variant":[
        "Shansongbaozi",
        "\u6749\u677e\u5821\u5b50",
        "Shansong Buzi"
    ],
    "name:zho_x_preferred":[
        "\u6749\u677e\u5821\u5b50"
    ],
    "wof:name":"Shansong Buzi",
    "wof:placetype":"locality"
},
  "geometry": {"coordinates":[125.06223,40.72676],"type":"Point"}
}