{
  "type": "Feature",
  "properties": {
    "gn:admin1_code":"11.0",
    "gn:asciiname":"Wanjiawan",
    "gn:country_code":"CN",
    "gn:dem":36,
    "gn:feature_class":"P",
    "gn:feature_code":"PPL",
    "gn:name":"Wanjiawan",
    "gn:population":0,
    "gn:timezone":"Asia/Shanghai",
    "iso:country":"CN",
    "name:zho_x_preferred":[
        "\u4e07\u5bb6\u6e7e"
    ],
    "wof:name":"Wanjiawan",
    "wof:placetype":"locality"
},
  "geometry": {"coordinates":[112.39604,29.48959],"type":"Point"}
}