{
  "type": "Feature",
  "properties": {
    "gn:admin1_code":"4.0",
    "gn:asciiname":"Xiaowu",
    "gn:country_code":"CN",
    "gn:dem":51,
    "gn:feature_class":"P",
    "gn:feature_code":"PPL",
    "gn:name":"Xiaowu",
    "gn:population":0,
    "gn:timezone":"Asia/Shanghai",
    "iso:country":"CN",
    "name:ceb_x_preferred":[
        "Xiaowu"
    ],
    "name:swe_x_preferred":[
        "Xiaowu"
    ],
    "name:zho_x_preferred":[
        "\u5c0f\u5434"
    ],
    "wof:name":"Xiaowu",
    "wof:placetype":"locality"
},
  "geometry": {"coordinates":[117.61499999999999,34.479],"type":"Point"}
}