{
  "type": "Feature",
  "properties": {
    "gn:admin1_code":"24.0",
    "gn:asciiname":"Jingyincun",
    "gn:country_code":"CN",
    "gn:dem":1257,
    "gn:feature_class":"P",
    "gn:feature_code":"PPL",
    "gn:name":"Jingyincun",
    "gn:population":0,
    "gn:timezone":"Asia/Shanghai",
    "iso:country":"CN",
    "name:zho_x_preferred":[
        "\u4e95\u5819\u6751"
    ],
    "wof:name":"Jingyincun",
    "wof:placetype":"locality"
},
  "geometry": {"coordinates":[113.18985000000001,38.04899],"type":"Point"}
}