{
  "type": "Feature",
  "properties": {
    "gn:admin1_code":"18",
    "gn:asciiname":"Chashangou",
    "gn:country_code":"CN",
    "gn:dem":1044,
    "gn:feature_class":"P",
    "gn:feature_code":"PPL",
    "gn:name":"Chashangou",
    "gn:population":0,
    "gn:timezone":"Asia/Shanghai",
    "iso:country":"CN",
    "name:zho_x_preferred":[
        "\u8336\u5c71\u6c9f"
    ],
    "wof:name":"Chashangou",
    "wof:placetype":"locality"
},
  "geometry": {"coordinates":[106.708,27.1141],"type":"Point"}
}