{
  "type": "Feature",
  "properties": {
    "gn:admin1_code":"09",
    "gn:asciiname":"Pengjiawan",
    "gn:cc2":"CN",
    "gn:country_code":"CN",
    "gn:dem":116,
    "gn:feature_class":"P",
    "gn:feature_code":"PPL",
    "gn:name":"Pengjiawan",
    "gn:population":0,
    "gn:timezone":"Asia/Shanghai",
    "iso:country":"CN",
    "name:und_x_variant":[
        "P\u2019eng-chia-wan",
        "Pengjiawan"
    ],
    "wof:name":"Pengjiawan",
    "wof:placetype":"locality"
},
  "geometry": {"coordinates":[114.07528000000001,32.24806],"type":"Point"}
}