{
  "type": "Feature",
  "properties": {
    "gn:admin1_code":"10",
    "gn:asciiname":"Laowanggou",
    "gn:country_code":"CN",
    "gn:dem":1214,
    "gn:feature_class":"P",
    "gn:feature_code":"PPL",
    "gn:name":"Laowanggou",
    "gn:population":0,
    "gn:timezone":"Asia/Shanghai",
    "iso:country":"CN",
    "name:zho_x_preferred":[
        "\u8001\u738b\u6c9f"
    ],
    "wof:name":"Laowanggou",
    "wof:placetype":"locality"
},
  "geometry": {"coordinates":[115.67628000000001,41.0095],"type":"Point"}
}