{
  "type": "Feature",
  "properties": {
    "gn:admin1_code":"30.0",
    "gn:asciiname":"Jianbei",
    "gn:country_code":"CN",
    "gn:dem":452,
    "gn:feature_class":"P",
    "gn:feature_code":"PPL",
    "gn:name":"Jianbei",
    "gn:population":0,
    "gn:timezone":"Asia/Shanghai",
    "iso:country":"CN",
    "name:zho_x_preferred":[
        "Jianbei"
    ],
    "name:zho_x_variant":[
        "\u5c16\u80cc"
    ],
    "wof:name":"Jianbei",
    "wof:placetype":"locality"
},
  "geometry": {"coordinates":[114.78917,24.44028],"type":"Point"}
}