{
  "type": "Feature",
  "properties": {
    "gn:admin1_code":"04",
    "gn:asciiname":"Licheng",
    "gn:country_code":"CN",
    "gn:dem":10,
    "gn:feature_class":"P",
    "gn:feature_code":"PPL",
    "gn:name":"Licheng",
    "gn:population":0,
    "gn:timezone":"Asia/Shanghai",
    "iso:country":"CN",
    "name:und_x_variant":[
        "Chin-hu",
        "Jinhu",
        "Lungkangchen",
        "Li-ch\u2019eng-chen",
        "Licheng"
    ],
    "name:zho_x_preferred":[
        "\u9ece\u57ce"
    ],
    "wof:name":"Licheng",
    "wof:placetype":"locality"
},
  "geometry": {"coordinates":[119.00769,33.01648],"type":"Point"}
}