{
  "type": "Feature",
  "properties": {
    "gn:admin1_code":"04",
    "gn:asciiname":"Licheng",
    "gn:country_code":"CN",
    "gn:dem":10,
    "gn:feature_class":"P",
    "gn:feature_code":"PPL",
    "gn:name":"Licheng",
    "gn:population":0,
    "gn:timezone":"Asia/Shanghai",
    "iso:country":"CN",
    "name:deu_x_preferred":[
        "Jinhu"
    ],
    "name:fas_x_preferred":[
        "\u0634\u0647\u0631\u0633\u062a\u0627\u0646 \u062c\u06cc\u0646\u0647\u0648"
    ],
    "name:jpn_x_preferred":[
        "\u91d1\u6e56\u770c"
    ],
    "name:kor_x_preferred":[
        "\uc9c4\ud6c4\ud604"
    ],
    "name:nor_x_preferred":[
        "Jinhu"
    ],
    "name:rus_x_preferred":[
        "\u0426\u0437\u0438\u043d\u044c\u0445\u0443"
    ],
    "name:swe_x_preferred":[
        "Jinhu"
    ],
    "name:und_x_variant":[
        "Chin-hu",
        "Lungkangchen",
        "Li-ch\u2019eng-chen",
        "Licheng"
    ],
    "name:urd_x_preferred":[
        "\u062c\u06cc\u0646\u06c1\u0648 \u06a9\u0627\u0624\u0646\u0679\u06cc"
    ],
    "name:vie_x_preferred":[
        "Kim H\u1ed3"
    ],
    "name:zho_x_preferred":[
        "\u9ece\u57ce"
    ],
    "name:zho_x_variant":[
        "\u91d1\u6e56\u53bf"
    ],
    "wof:name":"Licheng",
    "wof:placetype":"locality"
},
  "geometry": {"coordinates":[119.00769,33.01648],"type":"Point"}
}