{
  "type": "Feature",
  "properties": {
    "gn:admin1_code":"5.0",
    "gn:asciiname":"Erjia Wopeng",
    "gn:country_code":"CN",
    "gn:dem":254,
    "gn:feature_class":"P",
    "gn:feature_code":"PPL",
    "gn:name":"Erjia Wopeng",
    "gn:population":0,
    "gn:timezone":"Asia/Shanghai",
    "iso:country":"CN",
    "name:zho_x_preferred":[
        "\u4e8c\u5bb6\u7a9d\u68da"
    ],
    "wof:name":"Erjia Wopeng",
    "wof:placetype":"locality"
},
  "geometry": {"coordinates":[125.02097999999999,44.77248],"type":"Point"}
}