{
  "type": "Feature",
  "properties": {
    "gn:admin1_code":"26.0",
    "gn:asciiname":"Xiaohexicun",
    "gn:country_code":"CN",
    "gn:dem":709,
    "gn:feature_class":"P",
    "gn:feature_code":"PPL",
    "gn:name":"Xiaohexicun",
    "gn:population":0,
    "gn:timezone":"Asia/Shanghai",
    "iso:country":"CN",
    "name:zho_x_preferred":[
        "\u5c0f\u6cb3\u897f\u6751"
    ],
    "wof:name":"Xiaohexicun",
    "wof:placetype":"locality"
},
  "geometry": {"coordinates":[109.75870999999999,35.23222],"type":"Point"}
}