{
  "type": "Feature",
  "properties": {
    "gn:admin1_code":"32.0",
    "gn:asciiname":"Luoqian'ege",
    "gn:country_code":"CN",
    "gn:dem":3934,
    "gn:feature_class":"P",
    "gn:feature_code":"PPL",
    "gn:name":"Luoqian\u2019ege",
    "gn:population":0,
    "gn:timezone":"Asia/Shanghai",
    "iso:country":"CN",
    "name:zho_x_preferred":[
        "\u7f57\u6d45\u4fc4\u54e5"
    ],
    "name:zho_x_variant":[
        "Luoqian\u2019ege"
    ],
    "wof:name":"Luoqian'ege",
    "wof:placetype":"locality"
},
  "geometry": {"coordinates":[99.42529,32.25039],"type":"Point"}
}