{
  "type": "Feature",
  "properties": {
    "gn:admin1_code":"18.0",
    "gn:asciiname":"Gouping",
    "gn:country_code":"CN",
    "gn:dem":825,
    "gn:feature_class":"P",
    "gn:feature_code":"PPLA4",
    "gn:name":"Gouping",
    "gn:population":0,
    "gn:timezone":"Asia/Shanghai",
    "iso:country":"CN",
    "name:und_x_variant":[
        "Gouping Xiang"
    ],
    "name:zho_x_preferred":[
        "\u57a2\u576a"
    ],
    "name:zho_x_variant":[
        "\u57a2\u576a\u4e61"
    ],
    "wof:name":"Gouping",
    "wof:placetype":"locality"
},
  "geometry": {"coordinates":[108.14294,28.98771],"type":"Point"}
}