{
  "type": "Feature",
  "properties": {
    "gn:admin1_code":"5.0",
    "gn:asciiname":"Yonghecun",
    "gn:country_code":"CN",
    "gn:dem":175,
    "gn:feature_class":"P",
    "gn:feature_code":"PPL",
    "gn:name":"Yonghecun",
    "gn:population":0,
    "gn:timezone":"Asia/Shanghai",
    "iso:country":"CN",
    "name:zho_x_preferred":[
        "\u6c38\u548c\u6751"
    ],
    "wof:name":"Yonghecun",
    "wof:placetype":"locality"
},
  "geometry": {"coordinates":[126.76433,44.99501],"type":"Point"}
}