{
  "type": "Feature",
  "properties": {
    "gn:admin1_code":"25",
    "gn:asciiname":"Xiejiayu",
    "gn:country_code":"CN",
    "gn:dem":159,
    "gn:feature_class":"P",
    "gn:feature_code":"PPL",
    "gn:name":"Xiejiayu",
    "gn:population":0,
    "gn:timezone":"Asia/Shanghai",
    "iso:country":"CN",
    "name:zho_x_preferred":[
        "\u8c22\u5bb6\u5cea"
    ],
    "wof:name":"Xiejiayu",
    "wof:placetype":"locality"
},
  "geometry": {"coordinates":[118.283,35.5156],"type":"Point"}
}