{
  "type": "Feature",
  "properties": {
    "gn:admin1_code":"25.0",
    "gn:asciiname":"Liujiazhuangcun",
    "gn:country_code":"CN",
    "gn:dem":17,
    "gn:feature_class":"P",
    "gn:feature_code":"PPL",
    "gn:name":"Liujiazhuangcun",
    "gn:population":0,
    "gn:timezone":"Asia/Shanghai",
    "iso:country":"CN",
    "name:zho_x_preferred":[
        "\u516d\u7532\u5e84\u6751"
    ],
    "wof:name":"Liujiazhuangcun",
    "wof:placetype":"locality"
},
  "geometry": {"coordinates":[119.28945,35.25136],"type":"Point"}
}