{
  "type": "Feature",
  "properties": {
    "gn:admin1_code":"4.0",
    "gn:asciiname":"Lianchengcun",
    "gn:country_code":"CN",
    "gn:dem":3,
    "gn:feature_class":"P",
    "gn:feature_code":"PPL",
    "gn:name":"Lianchengcun",
    "gn:population":0,
    "gn:timezone":"Asia/Shanghai",
    "iso:country":"CN",
    "name:zho_x_preferred":[
        "\u8fde\u6210\u6751"
    ],
    "wof:name":"Lianchengcun",
    "wof:placetype":"locality"
},
  "geometry": {"coordinates":[119.46729000000001,34.34851],"type":"Point"}
}