{
  "type": "Feature",
  "properties": {
    "gn:admin1_code":"3.0",
    "gn:asciiname":"Shanghuangdong",
    "gn:country_code":"CN",
    "gn:dem":103,
    "gn:feature_class":"P",
    "gn:feature_code":"PPL",
    "gn:name":"Shanghuangdong",
    "gn:population":0,
    "gn:timezone":"Asia/Shanghai",
    "iso:country":"CN",
    "name:und_x_variant":[
        "\u4e0a\u9ec4\u6d1e"
    ],
    "wof:name":"Shanghuangdong",
    "wof:placetype":"locality"
},
  "geometry": {"coordinates":[114.58418,27.47314],"type":"Point"}
}