{
  "type": "Feature",
  "properties": {
    "gn:admin1_code":"16.0",
    "gn:asciiname":"Daomo",
    "gn:country_code":"CN",
    "gn:dem":119,
    "gn:feature_class":"P",
    "gn:feature_code":"PPL",
    "gn:name":"Daomo",
    "gn:population":0,
    "gn:timezone":"Asia/Shanghai",
    "iso:country":"CN",
    "name:zho_x_preferred":[
        "\u5200\u83ab"
    ],
    "wof:name":"Daomo",
    "wof:placetype":"locality"
},
  "geometry": {"coordinates":[108.69199999999999,23.4099],"type":"Point"}
}