{
  "type": "Feature",
  "properties": {
    "gn:admin1_code":"31",
    "gn:asciiname":"Nanda",
    "gn:country_code":"CN",
    "gn:dem":219,
    "gn:feature_class":"P",
    "gn:feature_code":"PPL",
    "gn:name":"Nanda",
    "gn:population":0,
    "gn:timezone":"Asia/Shanghai",
    "iso:country":"CN",
    "name:ceb_x_preferred":[
        "Nanda"
    ],
    "name:deu_x_preferred":[
        "Nanda"
    ],
    "name:por_x_preferred":[
        "Nanda"
    ],
    "name:rus_x_preferred":[
        "\u041d\u0430\u043d\u0434\u0430"
    ],
    "name:swe_x_preferred":[
        "Nanda"
    ],
    "name:und_x_variant":[
        "Nandacun",
        "\u5357\u8fbe\u6751",
        "Mugua",
        "\u6728\u74dc",
        "Nanda",
        "\u5357\u8fbe"
    ],
    "wof:name":"Nanda",
    "wof:placetype":"locality"
},
  "geometry": {"coordinates":[109.336,19.2516],"type":"Point"}
}