{
  "type": "Feature",
  "properties": {
    "gn:admin1_code":"3.0",
    "gn:asciiname":"Pailoupu",
    "gn:country_code":"CN",
    "gn:dem":60,
    "gn:feature_class":"P",
    "gn:feature_code":"PPL",
    "gn:name":"Pailoupu",
    "gn:population":0,
    "gn:timezone":"Asia/Shanghai",
    "iso:country":"CN",
    "name:und_x_variant":[
        "\u6392\u697c\u94fa"
    ],
    "wof:name":"Pailoupu",
    "wof:placetype":"locality"
},
  "geometry": {"coordinates":[116.41777999999999,28.0383],"type":"Point"}
}