{
  "type": "Feature",
  "properties": {
    "gn:admin1_code":"12.0",
    "gn:asciiname":"Lijiahe",
    "gn:country_code":"CN",
    "gn:dem":40,
    "gn:feature_class":"P",
    "gn:feature_code":"PPL",
    "gn:name":"Lijiahe",
    "gn:population":0,
    "gn:timezone":"Asia/Shanghai",
    "iso:country":"CN",
    "name:und_x_variant":[
        "\u6613\u5bb6\u4f55"
    ],
    "wof:name":"Lijiahe",
    "wof:placetype":"locality"
},
  "geometry": {"coordinates":[114.90770000000001,30.93608],"type":"Point"}
}