{
  "type": "Feature",
  "properties": {
    "gn:admin1_code":"7.0",
    "gn:asciiname":"Huguancun",
    "gn:country_code":"CN",
    "gn:dem":334,
    "gn:feature_class":"P",
    "gn:feature_code":"PPL",
    "gn:name":"Huguancun",
    "gn:population":0,
    "gn:timezone":"Asia/Shanghai",
    "iso:country":"CN",
    "name:zho_x_preferred":[
        "\u6e56\u7ba1\u6751"
    ],
    "wof:name":"Huguancun",
    "wof:placetype":"locality"
},
  "geometry": {"coordinates":[117.52558000000001,26.66964],"type":"Point"}
}