{
  "type": "Feature",
  "properties": {
    "gn:admin1_code":"19.0",
    "gn:asciiname":"Nantaizi",
    "gn:country_code":"CN",
    "gn:dem":289,
    "gn:feature_class":"P",
    "gn:feature_code":"PPL",
    "gn:name":"Nantaizi",
    "gn:population":0,
    "gn:timezone":"Asia/Shanghai",
    "iso:country":"CN",
    "name:zho_x_preferred":[
        "\u5357\u53f0\u5b50"
    ],
    "wof:name":"Nantaizi",
    "wof:placetype":"locality"
},
  "geometry": {"coordinates":[120.27979000000001,41.26146],"type":"Point"}
}