{
  "type": "Feature",
  "properties": {
    "gn:admin1_code":"15.0",
    "gn:asciiname":"Yujiaping",
    "gn:country_code":"CN",
    "gn:dem":2250,
    "gn:feature_class":"P",
    "gn:feature_code":"PPL",
    "gn:name":"Yujiaping",
    "gn:population":0,
    "gn:timezone":"Asia/Shanghai",
    "iso:country":"CN",
    "name:zho_x_preferred":[
        "\u4f59\u5bb6\u576a"
    ],
    "wof:name":"Yujiaping",
    "wof:placetype":"locality"
},
  "geometry": {"coordinates":[103.13800000000001,35.5941],"type":"Point"}
}