{
  "type": "Feature",
  "properties": {
    "gn:admin1_code":"11",
    "gn:asciiname":"Yudetang",
    "gn:country_code":"CN",
    "gn:dem":129,
    "gn:feature_class":"P",
    "gn:feature_code":"PPL",
    "gn:name":"Yudetang",
    "gn:population":0,
    "gn:timezone":"Asia/Shanghai",
    "iso:country":"CN",
    "name:zho_x_preferred":[
        "\u80b2\u5fb7\u5802"
    ],
    "wof:name":"Yudetang",
    "wof:placetype":"locality"
},
  "geometry": {"coordinates":[112.01039,27.44521],"type":"Point"}
}