{
  "type": "Feature",
  "properties": {
    "gn:admin1_code":"24.0",
    "gn:asciiname":"Yan'erwo",
    "gn:country_code":"CN",
    "gn:dem":1151,
    "gn:feature_class":"P",
    "gn:feature_code":"PPL",
    "gn:name":"Yan\u2019erwo",
    "gn:population":0,
    "gn:timezone":"Asia/Shanghai",
    "iso:country":"CN",
    "name:und_x_variant":[
        "Yan\u2019erwo",
        "\u71d5\u513f\u7a9d"
    ],
    "wof:name":"Yan'erwo",
    "wof:placetype":"locality"
},
  "geometry": {"coordinates":[111.67376000000002,35.85854000000001],"type":"Point"}
}