{
  "type": "Feature",
  "properties": {
    "gn:admin1_code":"26",
    "gn:asciiname":"Yanjiagou",
    "gn:country_code":"CN",
    "gn:dem":663,
    "gn:feature_class":"P",
    "gn:feature_code":"PPL",
    "gn:name":"Yanjiagou",
    "gn:population":0,
    "gn:timezone":"Asia/Shanghai",
    "iso:country":"CN",
    "name:und_x_variant":[
        "\u960e\u5bb6\u6c9f"
    ],
    "name:zho_x_preferred":[
        "\u960e\u5bb6\u6c9f"
    ],
    "wof:name":"Yanjiagou",
    "wof:placetype":"locality"
},
  "geometry": {"coordinates":[108.70111,34.72528],"type":"Point"}
}