{
  "type": "Feature",
  "properties": {
    "gn:admin1_code":"12.0",
    "gn:asciiname":"Dawangjiawan",
    "gn:country_code":"CN",
    "gn:dem":161,
    "gn:feature_class":"P",
    "gn:feature_code":"PPL",
    "gn:name":"Dawangjiawan",
    "gn:population":0,
    "gn:timezone":"Asia/Shanghai",
    "iso:country":"CN",
    "name:zho_x_preferred":[
        "\u5927\u738b\u5bb6\u5846"
    ],
    "wof:name":"Dawangjiawan",
    "wof:placetype":"locality"
},
  "geometry": {"coordinates":[112.94173000000001,32.05163],"type":"Point"}
}