{
  "type": "Feature",
  "properties": {
    "gn:admin1_code":"19.0",
    "gn:asciiname":"Tuangangzi",
    "gn:country_code":"CN",
    "gn:dem":98,
    "gn:feature_class":"P",
    "gn:feature_code":"PPL",
    "gn:name":"Tuangangzi",
    "gn:population":0,
    "gn:timezone":"Asia/Shanghai",
    "iso:country":"CN",
    "name:und_x_variant":[
        "\u56e2\u5c97\u5b50"
    ],
    "name:zho_x_preferred":[
        "\u56e2\u5c97\u5b50"
    ],
    "wof:name":"Tuangangzi",
    "wof:placetype":"locality"
},
  "geometry": {"coordinates":[123.46171,42.58042],"type":"Point"}
}