{
  "type": "Feature",
  "properties": {
    "gn:admin1_code":"5.0",
    "gn:asciiname":"Libingou",
    "gn:country_code":"CN",
    "gn:dem":946,
    "gn:feature_class":"P",
    "gn:feature_code":"PPL",
    "gn:name":"Libingou",
    "gn:population":0,
    "gn:timezone":"Asia/Shanghai",
    "iso:country":"CN",
    "name:und_x_variant":[
        "\u674e\u5bbe\u6c9f"
    ],
    "wof:name":"Libingou",
    "wof:placetype":"locality"
},
  "geometry": {"coordinates":[126.5444,41.75362],"type":"Point"}
}