{
  "type": "Feature",
  "properties": {
    "gn:admin1_code":"4.0",
    "gn:asciiname":"Chanshi",
    "gn:country_code":"CN",
    "gn:dem":9,
    "gn:feature_class":"P",
    "gn:feature_code":"PPL",
    "gn:name":"Chanshi",
    "gn:population":0,
    "gn:timezone":"Asia/Shanghai",
    "iso:country":"CN",
    "name:zho_x_preferred":[
        "\u7985\u5e08"
    ],
    "wof:name":"Chanshi",
    "wof:placetype":"locality"
},
  "geometry": {"coordinates":[120.28682000000001,32.151],"type":"Point"}
}