{
  "type": "Feature",
  "properties": {
    "gn:admin1_code":"10.0",
    "gn:asciiname":"Jiaolangou",
    "gn:country_code":"CN",
    "gn:dem":21,
    "gn:feature_class":"P",
    "gn:feature_code":"PPL",
    "gn:name":"Jiaolangou",
    "gn:population":0,
    "gn:timezone":"Asia/Shanghai",
    "iso:country":"CN",
    "name:zho_x_preferred":[
        "\u7126\u5170\u6c9f"
    ],
    "wof:name":"Jiaolangou",
    "wof:placetype":"locality"
},
  "geometry": {"coordinates":[115.92113000000001,39.1776],"type":"Point"}
}