{
  "type": "Feature",
  "properties": {
    "gn:admin1_code":"25",
    "gn:asciiname":"Shiheyu",
    "gn:country_code":"CN",
    "gn:dem":137,
    "gn:feature_class":"P",
    "gn:feature_code":"PPL",
    "gn:name":"Shiheyu",
    "gn:population":0,
    "gn:timezone":"Asia/Shanghai",
    "iso:country":"CN",
    "name:und_x_variant":[
        "\u77f3\u6cb3\u5cea"
    ],
    "name:zho_x_preferred":[
        "\u77f3\u6cb3\u5cea"
    ],
    "wof:name":"Shiheyu",
    "wof:placetype":"locality"
},
  "geometry": {"coordinates":[119.02119,35.29825],"type":"Point"}
}