{
  "type": "Feature",
  "properties": {
    "gn:admin1_code":"11",
    "gn:asciiname":"Gaojianchong",
    "gn:country_code":"CN",
    "gn:dem":211,
    "gn:feature_class":"P",
    "gn:feature_code":"PPL",
    "gn:name":"Gaojianchong",
    "gn:population":0,
    "gn:timezone":"Asia/Shanghai",
    "iso:country":"CN",
    "name:zho_x_preferred":[
        "\u9ad8\u67a7\u51b2"
    ],
    "wof:name":"Gaojianchong",
    "wof:placetype":"locality"
},
  "geometry": {"coordinates":[111.31726999999999,27.84837000000001],"type":"Point"}
}