{
  "type": "Feature",
  "properties": {
    "gn:admin1_code":"14.0",
    "gn:asciiname":"Zaniguo",
    "gn:country_code":"CN",
    "gn:dem":4645,
    "gn:feature_class":"P",
    "gn:feature_code":"PPL",
    "gn:name":"Zaniguo",
    "gn:population":0,
    "gn:timezone":"Asia/Urumqi",
    "iso:country":"CN",
    "name:zho_x_preferred":[
        "\u6742\u5c3c\u679c"
    ],
    "wof:name":"Zaniguo",
    "wof:placetype":"locality"
},
  "geometry": {"coordinates":[90.339,30.0486],"type":"Point"}
}