{
  "type": "Feature",
  "properties": {
    "gn:admin1_code":"03",
    "gn:asciiname":"Lianhu",
    "gn:country_code":"CN",
    "gn:dem":18,
    "gn:feature_class":"P",
    "gn:feature_code":"PPLA4",
    "gn:name":"Lianhu",
    "gn:population":0,
    "gn:timezone":"Asia/Shanghai",
    "iso:country":"CN",
    "name:und_x_variant":[
        "\u83b2\u6e56",
        "Lianhu Xiang",
        "\u83b2\u6e56\u4e61"
    ],
    "wof:name":"Lianhu",
    "wof:placetype":"locality"
},
  "geometry": {"coordinates":[116.54198999999998,28.99549],"type":"Point"}
}