{
  "type": "Feature",
  "properties": {
    "gn:admin1_code":"26.0",
    "gn:asciiname":"Zengjiahe",
    "gn:country_code":"CN",
    "gn:dem":807,
    "gn:feature_class":"P",
    "gn:feature_code":"PPLA4",
    "gn:name":"Zengjiahe",
    "gn:population":0,
    "gn:timezone":"Asia/Shanghai",
    "iso:country":"CN",
    "name:und_x_variant":[
        "\u66fe\u5bb6\u6cb3"
    ],
    "wof:name":"Zengjiahe",
    "wof:placetype":"locality"
},
  "geometry": {"coordinates":[106.12649999999999,33.12096],"type":"Point"}
}