{
  "type": "Feature",
  "properties": {
    "gn:admin1_code":"25",
    "gn:asciiname":"Wujia Guanzhuang",
    "gn:country_code":"CN",
    "gn:dem":86,
    "gn:feature_class":"P",
    "gn:feature_code":"PPL",
    "gn:name":"Wujia Guanzhuang",
    "gn:population":0,
    "gn:timezone":"Asia/Shanghai",
    "iso:country":"CN",
    "name:zho_x_preferred":[
        "\u5434\u5bb6\u5b98\u5e84"
    ],
    "wof:name":"Wujia Guanzhuang",
    "wof:placetype":"locality"
},
  "geometry": {"coordinates":[117.917,34.9135],"type":"Point"}
}