{
  "type": "Feature",
  "properties": {
    "gn:admin1_code":"18.0",
    "gn:asciiname":"Aoyang",
    "gn:country_code":"CN",
    "gn:dem":1051,
    "gn:feature_class":"P",
    "gn:feature_code":"PPL",
    "gn:name":"Aoyang",
    "gn:population":0,
    "gn:timezone":"Asia/Shanghai",
    "iso:country":"CN",
    "name:zho_x_preferred":[
        "\u5773\u7f8a"
    ],
    "wof:name":"Aoyang",
    "wof:placetype":"locality"
},
  "geometry": {"coordinates":[107.496,26.5424],"type":"Point"}
}