{
  "type": "Feature",
  "properties": {
    "gn:admin1_code":"11.0",
    "gn:asciiname":"Xiaoguangpu",
    "gn:country_code":"CN",
    "gn:dem":423,
    "gn:feature_class":"P",
    "gn:feature_code":"PPL",
    "gn:name":"Xiaoguangpu",
    "gn:population":0,
    "gn:timezone":"Asia/Shanghai",
    "iso:country":"CN",
    "name:zho_x_preferred":[
        "\u5c0f\u5e7f\u94fa"
    ],
    "wof:name":"Xiaoguangpu",
    "wof:placetype":"locality"
},
  "geometry": {"coordinates":[112.60713,25.14757],"type":"Point"}
}