{
  "type": "Feature",
  "properties": {
    "gn:admin1_code":"11.0",
    "gn:asciiname":"Laolujie",
    "gn:country_code":"CN",
    "gn:dem":327,
    "gn:feature_class":"P",
    "gn:feature_code":"PPL",
    "gn:name":"Laolujie",
    "gn:population":0,
    "gn:timezone":"Asia/Shanghai",
    "iso:country":"CN",
    "name:zho_x_preferred":[
        "\u8001\u8def\u754c"
    ],
    "wof:name":"Laolujie",
    "wof:placetype":"locality"
},
  "geometry": {"coordinates":[110.01837,26.73701],"type":"Point"}
}