{
  "type": "Feature",
  "properties": {
    "gn:admin1_code":"30",
    "gn:asciiname":"Chenshanliao",
    "gn:country_code":"CN",
    "gn:dem":115,
    "gn:feature_class":"P",
    "gn:feature_code":"PPL",
    "gn:name":"Chenshanliao",
    "gn:population":0,
    "gn:timezone":"Asia/Shanghai",
    "iso:country":"CN",
    "name:zho_x_preferred":[
        "\u9648\u5c71\u5bee"
    ],
    "wof:name":"Chenshanliao",
    "wof:placetype":"locality"
},
  "geometry": {"coordinates":[115.9953,24.07861],"type":"Point"}
}