{
  "type": "Feature",
  "properties": {
    "gn:admin1_code":"9.0",
    "gn:asciiname":"Malaozhuang",
    "gn:country_code":"CN",
    "gn:dem":39,
    "gn:feature_class":"P",
    "gn:feature_code":"PPL",
    "gn:name":"Malaozhuang",
    "gn:population":0,
    "gn:timezone":"Asia/Shanghai",
    "iso:country":"CN",
    "name:zho_x_preferred":[
        "\u9a6c\u8001\u5e84"
    ],
    "wof:name":"Malaozhuang",
    "wof:placetype":"locality"
},
  "geometry": {"coordinates":[115.15612,32.703],"type":"Point"}
}