{
  "type": "Feature",
  "properties": {
    "gn:admin1_code":"8.0",
    "gn:asciiname":"Daduchuan Liudui",
    "gn:country_code":"CN",
    "gn:dem":194,
    "gn:feature_class":"P",
    "gn:feature_code":"PPLF",
    "gn:name":"Daduchuan Liudui",
    "gn:population":0,
    "gn:timezone":"Asia/Shanghai",
    "iso:country":"CN",
    "name:zho_x_preferred":[
        "\u5927\u809a\u5ddd\u516d\u961f"
    ],
    "wof:name":"Daduchuan Liudui",
    "wof:placetype":"locality"
},
  "geometry": {"coordinates":[122.98519,47.19094000000001],"type":"Point"}
}