{
  "type": "Feature",
  "properties": {
    "gn:admin1_code":"19.0",
    "gn:asciiname":"Dagouli",
    "gn:country_code":"CN",
    "gn:dem":322,
    "gn:feature_class":"P",
    "gn:feature_code":"PPL",
    "gn:name":"Dagouli",
    "gn:population":0,
    "gn:timezone":"Asia/Shanghai",
    "iso:country":"CN",
    "name:und_x_variant":[
        "\u5927\u6c9f\u91cc"
    ],
    "wof:name":"Dagouli",
    "wof:placetype":"locality"
},
  "geometry": {"coordinates":[123.38656,40.67283],"type":"Point"}
}