{
  "type": "Feature",
  "properties": {
    "gn:admin1_code":"21.0",
    "gn:asciiname":"Chenjia Shuitang",
    "gn:country_code":"CN",
    "gn:dem":1452,
    "gn:feature_class":"P",
    "gn:feature_code":"PPL",
    "gn:name":"Chenjia Shuitang",
    "gn:population":0,
    "gn:timezone":"Asia/Shanghai",
    "iso:country":"CN",
    "name:zho_x_preferred":[
        "\u9648\u5bb6\u6c34\u6dcc"
    ],
    "wof:name":"Chenjia Shuitang",
    "wof:placetype":"locality"
},
  "geometry": {"coordinates":[106.749,37.4901],"type":"Point"}
}