{
  "type": "Feature",
  "properties": {
    "gn:admin1_code":"3.0",
    "gn:asciiname":"Laoyeping",
    "gn:country_code":"CN",
    "gn:dem":297,
    "gn:feature_class":"P",
    "gn:feature_code":"PPL",
    "gn:name":"Laoyeping",
    "gn:population":0,
    "gn:timezone":"Asia/Shanghai",
    "iso:country":"CN",
    "name:und_x_variant":[
        "\u8001\u7237\u576a"
    ],
    "wof:name":"Laoyeping",
    "wof:placetype":"locality"
},
  "geometry": {"coordinates":[116.90697,27.6579],"type":"Point"}
}