{
  "type": "Feature",
  "properties": {
    "gn:admin1_code":"15.0",
    "gn:asciiname":"Chuan'er",
    "gn:country_code":"CN",
    "gn:dem":1289,
    "gn:feature_class":"P",
    "gn:feature_code":"PPL",
    "gn:name":"Chuan\u2019er",
    "gn:population":0,
    "gn:timezone":"Asia/Shanghai",
    "iso:country":"CN",
    "name:und_x_variant":[
        "Chuan\u2019er"
    ],
    "name:zho_x_preferred":[
        "\u5ddd\u513f"
    ],
    "wof:name":"Chuan'er",
    "wof:placetype":"locality"
},
  "geometry": {"coordinates":[105.815,34.725],"type":"Point"}
}