{
  "type": "Feature",
  "properties": {
    "gn:admin1_code":"33.0",
    "gn:asciiname":"Ziyunsi",
    "gn:country_code":"CN",
    "gn:dem":959,
    "gn:feature_class":"P",
    "gn:feature_code":"PPL",
    "gn:name":"Ziyunsi",
    "gn:population":0,
    "gn:timezone":"Asia/Shanghai",
    "iso:country":"CN",
    "name:zho_x_preferred":[
        "\u7d2b\u4e91\u5bfa"
    ],
    "wof:name":"Ziyunsi",
    "wof:placetype":"locality"
},
  "geometry": {"coordinates":[108.01600000000001,30.00135],"type":"Point"}
}