{
  "type": "Feature",
  "properties": {
    "gn:admin1_code":"1.0",
    "gn:asciiname":"Huangliangoucun",
    "gn:country_code":"CN",
    "gn:dem":26,
    "gn:feature_class":"P",
    "gn:feature_code":"PPL",
    "gn:name":"Huangliangoucun",
    "gn:population":0,
    "gn:timezone":"Asia/Shanghai",
    "iso:country":"CN",
    "name:zho_x_preferred":[
        "\u9ec4\u8fde\u6c9f\u6751"
    ],
    "wof:name":"Huangliangoucun",
    "wof:placetype":"locality"
},
  "geometry": {"coordinates":[116.21482,32.51148],"type":"Point"}
}