{
  "type": "Feature",
  "properties": {
    "gn:admin1_code":"08",
    "gn:asciiname":"Datonggoucun",
    "gn:country_code":"CN",
    "gn:dem":279,
    "gn:feature_class":"P",
    "gn:feature_code":"PPL",
    "gn:name":"Datonggoucun",
    "gn:population":0,
    "gn:timezone":"Asia/Shanghai",
    "iso:country":"CN",
    "name:und_x_variant":[
        "Datonggou",
        "Datonggoucun"
    ],
    "name:zho_x_preferred":[
        "\u5927\u901a\u6c9f"
    ],
    "name:zho_x_variant":[
        "\u5927\u901a\u6c9f\u6751"
    ],
    "wof:name":"Datonggoucun",
    "wof:placetype":"locality"
},
  "geometry": {"coordinates":[130.68787,45.39523],"type":"Point"}
}