{
  "type": "Feature",
  "properties": {
    "gn:admin1_code":"25.0",
    "gn:asciiname":"Nangucun",
    "gn:country_code":"CN",
    "gn:dem":19,
    "gn:feature_class":"P",
    "gn:feature_code":"PPL",
    "gn:name":"Nangucun",
    "gn:population":0,
    "gn:timezone":"Asia/Shanghai",
    "iso:country":"CN",
    "name:zho_x_preferred":[
        "\u5357\u6cbd\u6751"
    ],
    "wof:name":"Nangucun",
    "wof:placetype":"locality"
},
  "geometry": {"coordinates":[122.41442000000001,37.12124],"type":"Point"}
}