{
  "type": "Feature",
  "properties": {
    "gn:admin1_code":"25",
    "gn:asciiname":"Dazhang Guanzhuang",
    "gn:country_code":"CN",
    "gn:dem":208,
    "gn:feature_class":"P",
    "gn:feature_code":"PPL",
    "gn:name":"Dazhang Guanzhuang",
    "gn:population":0,
    "gn:timezone":"Asia/Shanghai",
    "iso:country":"CN",
    "name:zho_x_preferred":[
        "\u5927\u5f20\u5b98\u5e84"
    ],
    "wof:name":"Dazhang Guanzhuang",
    "wof:placetype":"locality"
},
  "geometry": {"coordinates":[118.74299999999999,35.842],"type":"Point"}
}