{
  "type": "Feature",
  "properties": {
    "gn:admin1_code":"11",
    "gn:asciiname":"Youcaoqiao",
    "gn:country_code":"CN",
    "gn:dem":233,
    "gn:feature_class":"P",
    "gn:feature_code":"PPL",
    "gn:name":"Youcaoqiao",
    "gn:population":0,
    "gn:timezone":"Asia/Shanghai",
    "iso:country":"CN",
    "name:zho_x_preferred":[
        "\u6cb9\u8349\u6865"
    ],
    "wof:name":"Youcaoqiao",
    "wof:placetype":"locality"
},
  "geometry": {"coordinates":[111.28755,27.1635],"type":"Point"}
}