{
  "type": "Feature",
  "properties": {
    "gn:admin1_code":"12.0",
    "gn:asciiname":"Dabaitian",
    "gn:country_code":"CN",
    "gn:dem":987,
    "gn:feature_class":"P",
    "gn:feature_code":"PPL",
    "gn:name":"Dabaitian",
    "gn:population":0,
    "gn:timezone":"Asia/Shanghai",
    "iso:country":"CN",
    "name:zho_x_preferred":[
        "Dabaitian"
    ],
    "name:zho_x_variant":[
        "\u5927\u767d\u7530"
    ],
    "wof:name":"Dabaitian",
    "wof:placetype":"locality"
},
  "geometry": {"coordinates":[110.05757,29.87483],"type":"Point"}
}