{
  "type": "Feature",
  "properties": {
    "gn:admin1_code":"29.0",
    "gn:asciiname":"Niangwa",
    "gn:country_code":"CN",
    "gn:dem":2532,
    "gn:feature_class":"P",
    "gn:feature_code":"PPL",
    "gn:name":"Niangwa",
    "gn:population":0,
    "gn:timezone":"Asia/Shanghai",
    "iso:country":"CN",
    "name:zho_x_preferred":[
        "\u5a18\u54c7"
    ],
    "wof:name":"Niangwa",
    "wof:placetype":"locality"
},
  "geometry": {"coordinates":[98.8639,28.5609],"type":"Point"}
}