{
  "type": "Feature",
  "properties": {
    "gn:admin1_code":"30",
    "gn:asciiname":"Xianlai",
    "gn:country_code":"CN",
    "gn:dem":13,
    "gn:feature_class":"P",
    "gn:feature_code":"PPL",
    "gn:name":"Xianlai",
    "gn:population":0,
    "gn:timezone":"Asia/Urumqi",
    "iso:country":"CN",
    "name:zho_x_preferred":[
        "\u4ed9\u6765"
    ],
    "wof:name":"Xianlai",
    "wof:placetype":"locality"
},
  "geometry": {"coordinates":[110.09455,21.08266],"type":"Point"}
}