{
  "type": "Feature",
  "properties": {
    "gn:admin1_code":"9.0",
    "gn:asciiname":"Qincaigou",
    "gn:country_code":"CN",
    "gn:dem":234,
    "gn:feature_class":"P",
    "gn:feature_code":"PPL",
    "gn:name":"Qincaigou",
    "gn:population":0,
    "gn:timezone":"Asia/Shanghai",
    "iso:country":"CN",
    "name:zho_x_preferred":[
        "\u82b9\u83dc\u6c9f"
    ],
    "wof:name":"Qincaigou",
    "wof:placetype":"locality"
},
  "geometry": {"coordinates":[113.57028,32.72777],"type":"Point"}
}