{
  "type": "Feature",
  "properties": {
    "gn:admin1_code":"26.0",
    "gn:asciiname":"Wangjiacun",
    "gn:country_code":"CN",
    "gn:dem":1309,
    "gn:feature_class":"P",
    "gn:feature_code":"PPL",
    "gn:name":"Wangjiacun",
    "gn:population":0,
    "gn:timezone":"Asia/Shanghai",
    "iso:country":"CN",
    "name:zho_x_preferred":[
        "\u738b\u5bb6\u6751"
    ],
    "wof:name":"Wangjiacun",
    "wof:placetype":"locality"
},
  "geometry": {"coordinates":[109.98333999999998,39.16942],"type":"Point"}
}