{
  "type": "Feature",
  "properties": {
    "gn:admin1_code":"19.0",
    "gn:asciiname":"Huangdicun",
    "gn:country_code":"CN",
    "gn:dem":181,
    "gn:feature_class":"P",
    "gn:feature_code":"PPL",
    "gn:name":"Huangdicun",
    "gn:population":0,
    "gn:timezone":"Asia/Shanghai",
    "iso:country":"CN",
    "name:zho_x_preferred":[
        "\u8352\u5730\u6751"
    ],
    "wof:name":"Huangdicun",
    "wof:placetype":"locality"
},
  "geometry": {"coordinates":[120.53343999999998,41.68264],"type":"Point"}
}