{
  "type": "Feature",
  "properties": {
    "gn:admin1_code":"22.0",
    "gn:asciiname":"Caojia Hutongcun",
    "gn:country_code":"CN",
    "gn:dem":59,
    "gn:feature_class":"P",
    "gn:feature_code":"PPL",
    "gn:name":"Caojia Hutongcun",
    "gn:population":0,
    "gn:timezone":"Asia/Shanghai",
    "iso:country":"CN",
    "name:zho_x_preferred":[
        "\u66f9\u5bb6\u80e1\u540c\u6751"
    ],
    "wof:name":"Caojia Hutongcun",
    "wof:placetype":"locality"
},
  "geometry": {"coordinates":[117.20475,40.18636],"type":"Point"}
}