{
  "type": "Feature",
  "properties": {
    "gn:admin1_code":"29.0",
    "gn:asciiname":"Lusha Dacun",
    "gn:country_code":"CN",
    "gn:dem":1616,
    "gn:feature_class":"P",
    "gn:feature_code":"PPL",
    "gn:name":"Lusha Dacun",
    "gn:population":0,
    "gn:timezone":"Asia/Shanghai",
    "iso:country":"CN",
    "name:zho_x_preferred":[
        "\u7984\u53a6\u5927\u6751"
    ],
    "wof:name":"Lusha Dacun",
    "wof:placetype":"locality"
},
  "geometry": {"coordinates":[99.994,24.9562],"type":"Point"}
}