{
  "type": "Feature",
  "properties": {
    "gn:admin1_code":"32.0",
    "gn:asciiname":"Shaowuji",
    "gn:country_code":"CN",
    "gn:dem":411,
    "gn:feature_class":"P",
    "gn:feature_code":"PPL",
    "gn:name":"Shaowuji",
    "gn:population":0,
    "gn:timezone":"Asia/Shanghai",
    "iso:country":"CN",
    "name:zho_x_preferred":[
        "\u5c11\u5c4b\u57fa"
    ],
    "wof:name":"Shaowuji",
    "wof:placetype":"locality"
},
  "geometry": {"coordinates":[106.82576,30.0481],"type":"Point"}
}