{
  "type": "Feature",
  "properties": {
    "gn:admin1_code":"16.0",
    "gn:asciiname":"Sanhe",
    "gn:country_code":"CN",
    "gn:dem":97,
    "gn:feature_class":"P",
    "gn:feature_code":"PPL",
    "gn:name":"Sanhe",
    "gn:population":0,
    "gn:timezone":"Asia/Shanghai",
    "iso:country":"CN",
    "name:ceb_x_preferred":[
        "Sanhe"
    ],
    "name:deu_x_preferred":[
        "Sanhe"
    ],
    "name:nor_x_preferred":[
        "Sanhe"
    ],
    "name:zho_x_preferred":[
        "\u4e09\u5408"
    ],
    "wof:name":"Sanhe",
    "wof:placetype":"locality"
},
  "geometry": {"coordinates":[109.36199999999999,24.447],"type":"Point"}
}