{
  "type": "Feature",
  "properties": {
    "gn:admin1_code":"24",
    "gn:asciiname":"Jiajiatun",
    "gn:cc2":"CN",
    "gn:country_code":"CN",
    "gn:dem":1217,
    "gn:feature_class":"P",
    "gn:feature_code":"PPL",
    "gn:name":"Jiajiatun",
    "gn:population":0,
    "gn:timezone":"Asia/Shanghai",
    "iso:country":"CN",
    "name:und_x_variant":[
        "Chia-chia-t\u2019un",
        "Chih-chia-t\u2019un",
        "Jiajiatun"
    ],
    "wof:name":"Jiajiatun",
    "wof:placetype":"locality"
},
  "geometry": {"coordinates":[114.095,40.26139000000001],"type":"Point"}
}