{
  "type": "Feature",
  "properties": {
    "gn:admin1_code":"26",
    "gn:asciiname":"Shifosi",
    "gn:cc2":"CN",
    "gn:country_code":"CN",
    "gn:dem":1127,
    "gn:feature_class":"P",
    "gn:feature_code":"PPL",
    "gn:name":"Shifosi",
    "gn:population":0,
    "gn:timezone":"Asia/Shanghai",
    "iso:country":"CN",
    "name:und_x_variant":[
        "Shih-fo-ssu",
        "Shifosi"
    ],
    "wof:name":"Shifosi",
    "wof:placetype":"locality"
},
  "geometry": {"coordinates":[109.56167000000001,32.1775],"type":"Point"}
}