{
  "type": "Feature",
  "properties": {
    "gn:admin1_code":"3",
    "gn:asciiname":"Dongqiu",
    "gn:country_code":"CN",
    "gn:dem":57,
    "gn:feature_class":"P",
    "gn:feature_code":"PPL",
    "gn:name":"Dongqiu",
    "gn:population":0,
    "gn:timezone":"Asia/Shanghai",
    "iso:country":"CN",
    "name:zho_x_preferred":[
        "\u51bb\u4e18"
    ],
    "wof:name":"Dongqiu",
    "wof:placetype":"locality"
},
  "geometry": {"coordinates":[114.88968,26.99078],"type":"Point"}
}