{
  "type": "Feature",
  "properties": {
    "gn:admin1_code":"30.0",
    "gn:asciiname":"Qinglanjing",
    "gn:country_code":"CN",
    "gn:dem":172,
    "gn:feature_class":"P",
    "gn:feature_code":"PPL",
    "gn:name":"Qinglanjing",
    "gn:population":0,
    "gn:timezone":"Asia/Shanghai",
    "iso:country":"CN",
    "name:zho_x_preferred":[
        "\u9752\u84dd\u8ff3"
    ],
    "wof:name":"Qinglanjing",
    "wof:placetype":"locality"
},
  "geometry": {"coordinates":[111.86503999999999,22.72192],"type":"Point"}
}