{
  "type": "Feature",
  "properties": {
    "gn:admin1_code":"14",
    "gn:asciiname":"Wujiu",
    "gn:country_code":"CN",
    "gn:dem":4759,
    "gn:feature_class":"P",
    "gn:feature_code":"PPL",
    "gn:name":"Wujiu",
    "gn:population":0,
    "gn:timezone":"Asia/Urumqi",
    "iso:country":"CN",
    "name:zho_x_preferred":[
        "\u543e\u4e45"
    ],
    "wof:name":"Wujiu",
    "wof:placetype":"locality"
},
  "geometry": {"coordinates":[88.9796,28.5557],"type":"Point"}
}