{
  "type": "Feature",
  "properties": {
    "gn:admin1_code":"15.0",
    "gn:asciiname":"Huaixiacun",
    "gn:country_code":"CN",
    "gn:dem":1427,
    "gn:feature_class":"P",
    "gn:feature_code":"PPL",
    "gn:name":"Huaixiacun",
    "gn:population":0,
    "gn:timezone":"Asia/Shanghai",
    "iso:country":"CN",
    "name:zho_x_preferred":[
        "\u6000\u4e0b\u6751"
    ],
    "wof:name":"Huaixiacun",
    "wof:placetype":"locality"
},
  "geometry": {"coordinates":[98.575,39.8187],"type":"Point"}
}