{
  "type": "Feature",
  "properties": {
    "gn:admin1_code":"32.0",
    "gn:asciiname":"Banbanping",
    "gn:country_code":"CN",
    "gn:dem":2640,
    "gn:feature_class":"P",
    "gn:feature_code":"PPL",
    "gn:name":"Banbanping",
    "gn:population":0,
    "gn:timezone":"Asia/Shanghai",
    "iso:country":"CN",
    "name:zho_x_preferred":[
        "\u677f\u677f\u576a"
    ],
    "wof:name":"Banbanping",
    "wof:placetype":"locality"
},
  "geometry": {"coordinates":[101.357,27.9329],"type":"Point"}
}