{
  "type": "Feature",
  "properties": {
    "gn:admin1_code":"1.0",
    "gn:asciiname":"Laodiancun",
    "gn:country_code":"CN",
    "gn:dem":745,
    "gn:feature_class":"P",
    "gn:feature_code":"PPL",
    "gn:name":"Laodiancun",
    "gn:population":0,
    "gn:timezone":"Asia/Shanghai",
    "iso:country":"CN",
    "name:zho_x_preferred":[
        "\u8001\u5e97\u6751"
    ],
    "wof:name":"Laodiancun",
    "wof:placetype":"locality"
},
  "geometry": {"coordinates":[115.77824,31.21851],"type":"Point"}
}