{
  "type": "Feature",
  "properties": {
    "gn:admin1_code":"4.0",
    "gn:asciiname":"Xinya",
    "gn:country_code":"CN",
    "gn:dem":3,
    "gn:feature_class":"P",
    "gn:feature_code":"PPL",
    "gn:name":"Xinya",
    "gn:population":0,
    "gn:timezone":"Asia/Shanghai",
    "iso:country":"CN",
    "name:zho_x_preferred":[
        "Xinya"
    ],
    "name:zho_x_variant":[
        "\u65b0\u4e9a"
    ],
    "wof:name":"Xinya",
    "wof:placetype":"locality"
},
  "geometry": {"coordinates":[121.13777,31.63285],"type":"Point"}
}