{
  "type": "Feature",
  "properties": {
    "gn:admin1_code":"26.0",
    "gn:asciiname":"Nanzhengcun",
    "gn:country_code":"CN",
    "gn:dem":364,
    "gn:feature_class":"P",
    "gn:feature_code":"PPL",
    "gn:name":"Nanzhengcun",
    "gn:population":0,
    "gn:timezone":"Asia/Shanghai",
    "iso:country":"CN",
    "name:zho_x_preferred":[
        "\u5357\u90d1\u6751"
    ],
    "wof:name":"Nanzhengcun",
    "wof:placetype":"locality"
},
  "geometry": {"coordinates":[109.07514,34.43202],"type":"Point"}
}