{
  "type": "Feature",
  "properties": {
    "iso:country":"CN",
    "qs:name":"\u5e38\u5dde\u5e02",
    "qs:name_adm0":"\u4e2d\u570b",
    "qs:name_adm1":"\u6c5f\u82cf\u7701",
    "qs:photos":389,
    "qs:photos_1k":79,
    "qs:photos_9k":22,
    "qs:photos_9r":14,
    "qs:photos_all":4908,
    "qs:photos_sr":6,
    "qs:placetype":"LocalAdmin",
    "qs:pop_sr":"0",
    "wof:name":"\u5e38\u5dde\u5e02",
    "wof:placetype":"localadmin"
},
  "geometry": {"coordinates":[119.947219,31.773126],"type":"Point"}
}