{
  "type": "Feature",
  "properties": {
    "gn:admin1_code":"24.0",
    "gn:asciiname":"Houjingtoucun",
    "gn:country_code":"CN",
    "gn:dem":1066,
    "gn:feature_class":"P",
    "gn:feature_code":"PPL",
    "gn:name":"Houjingtoucun",
    "gn:population":0,
    "gn:timezone":"Asia/Shanghai",
    "iso:country":"CN",
    "name:zho_x_preferred":[
        "\u540e\u4e95\u5934\u6751"
    ],
    "wof:name":"Houjingtoucun",
    "wof:placetype":"locality"
},
  "geometry": {"coordinates":[110.90351,37.87124],"type":"Point"}
}