{
  "type": "Feature",
  "properties": {
    "gn:admin1_code":"9.0",
    "gn:asciiname":"Lixianqiao",
    "gn:country_code":"CN",
    "gn:dem":202,
    "gn:feature_class":"P",
    "gn:feature_code":"PPL",
    "gn:name":"Lixianqiao",
    "gn:population":0,
    "gn:timezone":"Asia/Shanghai",
    "iso:country":"CN",
    "name:zho_x_preferred":[
        "\u674e\u4ed9\u6865"
    ],
    "wof:name":"Lixianqiao",
    "wof:placetype":"locality"
},
  "geometry": {"coordinates":[113.25736000000001,33.07501],"type":"Point"}
}