{
  "type": "Feature",
  "properties": {
    "gn:admin1_code":"1.0",
    "gn:asciiname":"Yaoting",
    "gn:country_code":"CN",
    "gn:dem":255,
    "gn:feature_class":"P",
    "gn:feature_code":"PPL",
    "gn:name":"Yaoting",
    "gn:population":0,
    "gn:timezone":"Asia/Shanghai",
    "iso:country":"CN",
    "name:zho_x_preferred":[
        "\u7a91\u4ead"
    ],
    "wof:name":"Yaoting",
    "wof:placetype":"locality"
},
  "geometry": {"coordinates":[118.65654000000001,30.43932],"type":"Point"}
}