{
  "type": "Feature",
  "properties": {
    "gn:admin1_code":"32.0",
    "gn:asciiname":"Pengjia Dawan",
    "gn:country_code":"CN",
    "gn:dem":314,
    "gn:feature_class":"P",
    "gn:feature_code":"PPL",
    "gn:name":"Pengjia Dawan",
    "gn:population":0,
    "gn:timezone":"Asia/Shanghai",
    "iso:country":"CN",
    "name:zho_x_preferred":[
        "\u5f6d\u5bb6\u5927\u6e7e"
    ],
    "wof:name":"Pengjia Dawan",
    "wof:placetype":"locality"
},
  "geometry": {"coordinates":[106.29335,30.92418],"type":"Point"}
}