{
  "type": "Feature",
  "properties": {
    "gn:admin1_code":"10",
    "gn:asciiname":"Haocungou",
    "gn:country_code":"CN",
    "gn:dem":789,
    "gn:feature_class":"P",
    "gn:feature_code":"PPL",
    "gn:name":"Haocungou",
    "gn:population":0,
    "gn:timezone":"Asia/Shanghai",
    "iso:country":"CN",
    "name:zho_x_preferred":[
        "\u597d\u6751\u6c9f"
    ],
    "wof:name":"Haocungou",
    "wof:placetype":"locality"
},
  "geometry": {"coordinates":[117.43375,41.51961],"type":"Point"}
}