{
  "type": "Feature",
  "properties": {
    "gn:admin1_code":"01",
    "gn:asciiname":"Linhuaiguan",
    "gn:cc2":"CN",
    "gn:country_code":"CN",
    "gn:dem":15,
    "gn:feature_class":"P",
    "gn:feature_code":"PPL",
    "gn:name":"Linhuaiguan",
    "gn:population":0,
    "gn:timezone":"Asia/Shanghai",
    "iso:country":"CN",
    "name:und_x_variant":[
        "Lin-hoai-kuan",
        "Lin-huai-kuan",
        "Linhwaikwan",
        "Linhuaiguan"
    ],
    "wof:name":"Linhuaiguan",
    "wof:placetype":"locality"
},
  "geometry": {"coordinates":[117.62444000000001,32.90028],"type":"Point"}
}