{
  "type": "Feature",
  "properties": {
    "gn:admin1_code":"25.0",
    "gn:asciiname":"Xinan Zhaojia",
    "gn:country_code":"CN",
    "gn:dem":14,
    "gn:feature_class":"P",
    "gn:feature_code":"PPL",
    "gn:name":"Xinan Zhaojia",
    "gn:population":0,
    "gn:timezone":"Asia/Shanghai",
    "iso:country":"CN",
    "name:zho_x_preferred":[
        "\u897f\u5357\u8d75\u5bb6"
    ],
    "wof:name":"Xinan Zhaojia",
    "wof:placetype":"locality"
},
  "geometry": {"coordinates":[121.47020000000001,36.84714],"type":"Point"}
}