{
  "type": "Feature",
  "properties": {
    "gn:admin1_code":"3.0",
    "gn:asciiname":"Shibachen",
    "gn:country_code":"CN",
    "gn:dem":834,
    "gn:feature_class":"P",
    "gn:feature_code":"PPL",
    "gn:name":"Shibachen",
    "gn:population":0,
    "gn:timezone":"Asia/Shanghai",
    "iso:country":"CN",
    "name:und_x_variant":[
        "\u5341\u516b\u6987"
    ],
    "wof:name":"Shibachen",
    "wof:placetype":"locality"
},
  "geometry": {"coordinates":[114.69074999999999,29.38146],"type":"Point"}
}