{
  "type": "Feature",
  "properties": {
    "gn:admin1_code":"2.0",
    "gn:asciiname":"Lisiji",
    "gn:country_code":"CN",
    "gn:dem":3,
    "gn:feature_class":"P",
    "gn:feature_code":"PPL",
    "gn:name":"Lisiji",
    "gn:population":0,
    "gn:timezone":"Asia/Shanghai",
    "iso:country":"CN",
    "name:zho_x_preferred":[
        "\u91cc\u53f8\u57fa"
    ],
    "wof:name":"Lisiji",
    "wof:placetype":"locality"
},
  "geometry": {"coordinates":[122.16004,30.2904],"type":"Point"}
}