{
  "type": "Feature",
  "properties": {
    "gn:admin1_code":"15.0",
    "gn:asciiname":"Yanjia Yuanzi",
    "gn:country_code":"CN",
    "gn:dem":1181,
    "gn:feature_class":"P",
    "gn:feature_code":"PPL",
    "gn:name":"Yanjia Yuanzi",
    "gn:population":0,
    "gn:timezone":"Asia/Shanghai",
    "iso:country":"CN",
    "name:zho_x_preferred":[
        "\u960e\u5bb6\u56ed\u5b50"
    ],
    "wof:name":"Yanjia Yuanzi",
    "wof:placetype":"locality"
},
  "geometry": {"coordinates":[108.13,36.0657],"type":"Point"}
}