{
  "type": "Feature",
  "properties": {
    "gn:admin1_code":"11.0",
    "gn:asciiname":"Yue'erxi",
    "gn:country_code":"CN",
    "gn:dem":237,
    "gn:feature_class":"P",
    "gn:feature_code":"PPL",
    "gn:name":"Yue\u2019erxi",
    "gn:population":0,
    "gn:timezone":"Asia/Shanghai",
    "iso:country":"CN",
    "name:und_x_variant":[
        "Yue\u2019erxi"
    ],
    "name:zho_x_preferred":[
        "\u6708\u513f\u6eaa"
    ],
    "wof:name":"Yue'erxi",
    "wof:placetype":"locality"
},
  "geometry": {"coordinates":[110.49473999999999,28.52807],"type":"Point"}
}