{
  "type": "Feature",
  "properties": {
    "gn:admin1_code":"8.0",
    "gn:asciiname":"Miaoling Nancun",
    "gn:country_code":"CN",
    "gn:dem":182,
    "gn:feature_class":"P",
    "gn:feature_code":"PPL",
    "gn:name":"Miaoling Nancun",
    "gn:population":0,
    "gn:timezone":"Asia/Shanghai",
    "iso:country":"CN",
    "name:zho_x_preferred":[
        "\u5e99\u5cad\u5357\u6751"
    ],
    "wof:name":"Miaoling Nancun",
    "wof:placetype":"locality"
},
  "geometry": {"coordinates":[131.67526000000001,45.54579],"type":"Point"}
}