{
  "type": "Feature",
  "properties": {
    "gn:admin1_code":"3.0",
    "gn:asciiname":"Hangqiao",
    "gn:country_code":"CN",
    "gn:dem":69,
    "gn:feature_class":"P",
    "gn:feature_code":"PPL",
    "gn:name":"Hangqiao",
    "gn:population":0,
    "gn:timezone":"Asia/Shanghai",
    "iso:country":"CN",
    "name:und_x_variant":[
        "\u676d\u6865"
    ],
    "wof:name":"Hangqiao",
    "wof:placetype":"locality"
},
  "geometry": {"coordinates":[115.97636,29.46754],"type":"Point"}
}