{
  "type": "Feature",
  "properties": {
    "gn:admin1_code":"25.0",
    "gn:asciiname":"Xigucun",
    "gn:country_code":"CN",
    "gn:dem":389,
    "gn:feature_class":"P",
    "gn:feature_code":"PPL",
    "gn:name":"Xigucun",
    "gn:population":0,
    "gn:timezone":"Asia/Shanghai",
    "iso:country":"CN",
    "name:zho_x_preferred":[
        "\u897f\u80a1\u6751"
    ],
    "wof:name":"Xigucun",
    "wof:placetype":"locality"
},
  "geometry": {"coordinates":[118.33376,36.52336],"type":"Point"}
}