{
  "type": "Feature",
  "properties": {
    "gn:admin1_code":"19.0",
    "gn:asciiname":"Beitangcun",
    "gn:country_code":"CN",
    "gn:dem":91,
    "gn:feature_class":"P",
    "gn:feature_code":"PPL",
    "gn:name":"Beitangcun",
    "gn:population":0,
    "gn:timezone":"Asia/Shanghai",
    "iso:country":"CN",
    "name:zho_x_preferred":[
        "\u5317\u6c64\u6751"
    ],
    "wof:name":"Beitangcun",
    "wof:placetype":"locality"
},
  "geometry": {"coordinates":[124.083,40.6243],"type":"Point"}
}