{
  "type": "Feature",
  "properties": {
    "gn:admin1_code":"29.0",
    "gn:asciiname":"Duanjia",
    "gn:country_code":"CN",
    "gn:dem":1947,
    "gn:feature_class":"P",
    "gn:feature_code":"PPL",
    "gn:name":"Duanjia",
    "gn:population":0,
    "gn:timezone":"Asia/Shanghai",
    "iso:country":"CN",
    "name:zho_x_preferred":[
        "\u6bb5\u5bb6"
    ],
    "wof:name":"Duanjia",
    "wof:placetype":"locality"
},
  "geometry": {"coordinates":[101.262,25.8345],"type":"Point"}
}