{
  "type": "Feature",
  "properties": {
    "gn:admin1_code":"12.0",
    "gn:asciiname":"Zhangjia Daqiao",
    "gn:country_code":"CN",
    "gn:dem":56,
    "gn:feature_class":"P",
    "gn:feature_code":"PPL",
    "gn:name":"Zhangjia Daqiao",
    "gn:population":0,
    "gn:timezone":"Asia/Shanghai",
    "iso:country":"CN",
    "name:zho_x_preferred":[
        "\u5f20\u5bb6\u5927\u6865"
    ],
    "wof:name":"Zhangjia Daqiao",
    "wof:placetype":"locality"
},
  "geometry": {"coordinates":[112.67399,31.25154],"type":"Point"}
}