{
  "type": "Feature",
  "properties": {
    "gn:admin1_code":"29.0",
    "gn:asciiname":"Aqida",
    "gn:country_code":"CN",
    "gn:dem":2054,
    "gn:feature_class":"P",
    "gn:feature_code":"PPL",
    "gn:name":"Aqida",
    "gn:population":0,
    "gn:timezone":"Asia/Shanghai",
    "iso:country":"CN",
    "name:zho_x_preferred":[
        "\u554a\u5176\u6253"
    ],
    "wof:name":"Aqida",
    "wof:placetype":"locality"
},
  "geometry": {"coordinates":[98.7921,27.5923],"type":"Point"}
}