{
  "type": "Feature",
  "properties": {
    "gn:admin1_code":"18",
    "gn:asciiname":"Damiaozhai",
    "gn:country_code":"CN",
    "gn:dem":1863,
    "gn:feature_class":"P",
    "gn:feature_code":"PPL",
    "gn:name":"Damiaozhai",
    "gn:population":0,
    "gn:timezone":"Asia/Shanghai",
    "iso:country":"CN",
    "name:zho_x_preferred":[
        "\u5927\u82d7\u5be8"
    ],
    "wof:name":"Damiaozhai",
    "wof:placetype":"locality"
},
  "geometry": {"coordinates":[104.26900000000001,27.2437],"type":"Point"}
}