{
  "type": "Feature",
  "properties": {
    "gn:admin1_code":"03",
    "gn:asciiname":"Madang",
    "gn:country_code":"CN",
    "gn:dem":20,
    "gn:feature_class":"P",
    "gn:feature_code":"PPLA4",
    "gn:name":"Madang",
    "gn:population":0,
    "gn:timezone":"Asia/Shanghai",
    "iso:country":"CN",
    "name:eng_x_historical":[
        "Matung"
    ],
    "name:eng_x_preferred":[
        "Matung"
    ],
    "name:und_x_variant":[
        "Ma-tang",
        "Madang",
        "\u9a6c\u57b1",
        "Madang Zhen",
        "\u9a6c\u57b1\u9547"
    ],
    "wof:name":"Madang",
    "wof:placetype":"locality"
},
  "geometry": {"coordinates":[116.65443,29.99064000000001],"type":"Point"}
}