{
  "type": "Feature",
  "properties": {
    "gn:admin1_code":"18",
    "gn:asciiname":"Lishanping",
    "gn:country_code":"CN",
    "gn:dem":1422,
    "gn:feature_class":"P",
    "gn:feature_code":"PPL",
    "gn:name":"Lishanping",
    "gn:population":0,
    "gn:timezone":"Asia/Shanghai",
    "iso:country":"CN",
    "name:zho_x_preferred":[
        "\u68a8\u5c71\u576a"
    ],
    "wof:name":"Lishanping",
    "wof:placetype":"locality"
},
  "geometry": {"coordinates":[104.971,25.8817],"type":"Point"}
}