{
  "type": "Feature",
  "properties": {
    "gn:admin1_code":"5.0",
    "gn:asciiname":"Liangjia Gangzi",
    "gn:country_code":"CN",
    "gn:dem":208,
    "gn:feature_class":"P",
    "gn:feature_code":"PPL",
    "gn:name":"Liangjia Gangzi",
    "gn:population":0,
    "gn:timezone":"Asia/Shanghai",
    "iso:country":"CN",
    "name:zho_x_preferred":[
        "\u6881\u5bb6\u5c97\u5b50"
    ],
    "wof:name":"Liangjia Gangzi",
    "wof:placetype":"locality"
},
  "geometry": {"coordinates":[124.48074,43.94666],"type":"Point"}
}