{
  "type": "Feature",
  "properties": {
    "gn:admin1_code":"19.0",
    "gn:asciiname":"Lingqiancun",
    "gn:country_code":"CN",
    "gn:dem":381,
    "gn:feature_class":"P",
    "gn:feature_code":"PPL",
    "gn:name":"Lingqiancun",
    "gn:population":0,
    "gn:timezone":"Asia/Shanghai",
    "iso:country":"CN",
    "name:zho_x_preferred":[
        "\u5cad\u524d\u6751"
    ],
    "wof:name":"Lingqiancun",
    "wof:placetype":"locality"
},
  "geometry": {"coordinates":[125.041,41.7002],"type":"Point"}
}