{
  "type": "Feature",
  "properties": {
    "iso:country":"CN",
    "name:eng_x_preferred":[
        "Yansi"
    ],
    "name:zho_x_preferred":[
        "\u5ca9\u5bfa\u9547"
    ],
    "qs:name":"\u5ca9\u5bfa\u9547",
    "qs:name_adm0":"\u4e2d\u570b",
    "qs:name_adm1":"\u5b89\u5fbd\u7701",
    "qs:photos":196,
    "qs:photos_1k":40,
    "qs:photos_9k":1,
    "qs:photos_9r":4,
    "qs:photos_all":196,
    "qs:photos_sr":4,
    "qs:placetype":"Town",
    "qs:pop_sr":"0",
    "wof:name":"Yansi",
    "wof:placetype":"locality"
},
  "geometry": {"coordinates":[118.365325,29.771827],"type":"Point"}
}