{
  "type": "Feature",
  "properties": {
    "gn:admin1_code":"20.0",
    "gn:asciiname":"Nanboazi",
    "gn:country_code":"CN",
    "gn:dem":1320,
    "gn:feature_class":"P",
    "gn:feature_code":"PPL",
    "gn:name":"Nanboazi",
    "gn:population":0,
    "gn:timezone":"Asia/Shanghai",
    "iso:country":"CN",
    "name:und_x_variant":[
        "\u5357\u5821\u5b50"
    ],
    "wof:name":"Nanboazi",
    "wof:placetype":"locality"
},
  "geometry": {"coordinates":[111.72895,39.7811],"type":"Point"}
}