{
  "type": "Feature",
  "properties": {
    "gn:admin1_code":"16",
    "gn:asciiname":"Tianzhou",
    "gn:country_code":"CN",
    "gn:dem":119,
    "gn:feature_class":"P",
    "gn:feature_code":"PPLA3",
    "gn:name":"Tianzhou",
    "gn:population":0,
    "gn:timezone":"Asia/Shanghai",
    "iso:country":"CN",
    "name:kor_x_preferred":[
        "\ud188\uc800\uc6b0"
    ],
    "name:und_x_variant":[
        "Chiu-feng-i",
        "Feng-i",
        "Tienchow",
        "Tianyang",
        "Tianzhou"
    ],
    "name:zho_x_preferred":[
        "T\u2019ien-yang"
    ],
    "name:zho_x_variant":[
        "T\u2019ien-chou-hs\u00fc",
        "T\u2019ien-chou",
        "T\u2019ien-chou-chen",
        "\u7530\u5dde"
    ],
    "wof:name":"Tianzhou",
    "wof:placetype":"locality"
},
  "geometry": {"coordinates":[106.89718000000001,23.77861],"type":"Point"}
}