{
  "type": "Feature",
  "properties": {
    "gn:admin1_code":"30.0",
    "gn:asciiname":"Jingshuilong",
    "gn:country_code":"CN",
    "gn:dem":21,
    "gn:feature_class":"P",
    "gn:feature_code":"PPL",
    "gn:name":"Jingshuilong",
    "gn:population":0,
    "gn:timezone":"Asia/Shanghai",
    "iso:country":"CN",
    "name:zho_x_preferred":[
        "\u4e95\u6c34\u9f99"
    ],
    "wof:name":"Jingshuilong",
    "wof:placetype":"locality"
},
  "geometry": {"coordinates":[114.18651,22.95809],"type":"Point"}
}