{
  "type": "Feature",
  "properties": {
    "gn:admin1_code":"8.0",
    "gn:asciiname":"Fengjicun",
    "gn:country_code":"CN",
    "gn:dem":137,
    "gn:feature_class":"P",
    "gn:feature_code":"PPL",
    "gn:name":"Fengjicun",
    "gn:population":0,
    "gn:timezone":"Asia/Shanghai",
    "iso:country":"CN",
    "name:zho_x_preferred":[
        "\u4e30\u57fa\u6751"
    ],
    "wof:name":"Fengjicun",
    "wof:placetype":"locality"
},
  "geometry": {"coordinates":[130.45368999999999,46.06954],"type":"Point"}
}