{
  "type": "Feature",
  "properties": {
    "gn:admin1_code":"2.0",
    "gn:asciiname":"Hengyan",
    "gn:country_code":"CN",
    "gn:dem":497,
    "gn:feature_class":"P",
    "gn:feature_code":"PPL",
    "gn:name":"Hengyan",
    "gn:population":0,
    "gn:timezone":"Asia/Shanghai",
    "iso:country":"CN",
    "name:zho_x_preferred":[
        "\u6a2a\u6cbf"
    ],
    "wof:name":"Hengyan",
    "wof:placetype":"locality"
},
  "geometry": {"coordinates":[121.01094999999999,29.90138],"type":"Point"}
}