{
  "type": "Feature",
  "properties": {
    "gn:admin1_code":"26.0",
    "gn:asciiname":"Laowuli",
    "gn:country_code":"CN",
    "gn:dem":541,
    "gn:feature_class":"P",
    "gn:feature_code":"PPL",
    "gn:name":"Laowuli",
    "gn:population":0,
    "gn:timezone":"Asia/Shanghai",
    "iso:country":"CN",
    "name:und_x_variant":[
        "\u8001\u96fe\u91cc"
    ],
    "wof:name":"Laowuli",
    "wof:placetype":"locality"
},
  "geometry": {"coordinates":[106.92061,32.98322],"type":"Point"}
}