{
  "type": "Feature",
  "properties": {
    "gn:admin1_code":"1.0",
    "gn:asciiname":"Longtaicun",
    "gn:country_code":"CN",
    "gn:dem":8,
    "gn:feature_class":"P",
    "gn:feature_code":"PPL",
    "gn:name":"Longtaicun",
    "gn:population":0,
    "gn:timezone":"Asia/Shanghai",
    "iso:country":"CN",
    "name:zho_x_preferred":[
        "\u9f99\u53f0\u6751"
    ],
    "wof:name":"Longtaicun",
    "wof:placetype":"locality"
},
  "geometry": {"coordinates":[117.93845,31.57233],"type":"Point"}
}