{
  "type": "Feature",
  "properties": {
    "gn:admin1_code":"25",
    "gn:asciiname":"Jinlingdian",
    "gn:country_code":"CN",
    "gn:dem":137,
    "gn:feature_class":"P",
    "gn:feature_code":"PPL",
    "gn:name":"Jinlingdian",
    "gn:population":0,
    "gn:timezone":"Asia/Shanghai",
    "iso:country":"CN",
    "name:zho_x_preferred":[
        "\u91d1\u7fce\u5e97"
    ],
    "wof:name":"Jinlingdian",
    "wof:placetype":"locality"
},
  "geometry": {"coordinates":[119.087,35.7463],"type":"Point"}
}