{
  "type": "Feature",
  "properties": {
    "gn:admin1_code":"30.0",
    "gn:asciiname":"Gaoqiantou",
    "gn:country_code":"CN",
    "gn:dem":140,
    "gn:feature_class":"P",
    "gn:feature_code":"PPL",
    "gn:name":"Gaoqiantou",
    "gn:population":0,
    "gn:timezone":"Asia/Shanghai",
    "iso:country":"CN",
    "name:zho_x_preferred":[
        "Gaoqiantou"
    ],
    "name:zho_x_variant":[
        "\u9ad8\u4e7e\u5934"
    ],
    "wof:name":"Gaoqiantou",
    "wof:placetype":"locality"
},
  "geometry": {"coordinates":[114.74101,24.21334],"type":"Point"}
}