{
  "type": "Feature",
  "properties": {
    "gn:admin1_code":"19.0",
    "gn:asciiname":"Nianpangou",
    "gn:country_code":"CN",
    "gn:dem":262,
    "gn:feature_class":"P",
    "gn:feature_code":"PPL",
    "gn:name":"Nianpangou",
    "gn:population":0,
    "gn:timezone":"Asia/Shanghai",
    "iso:country":"CN",
    "name:und_x_variant":[
        "\u78be\u76d8\u6c9f"
    ],
    "wof:name":"Nianpangou",
    "wof:placetype":"locality"
},
  "geometry": {"coordinates":[122.75378000000001,40.3429],"type":"Point"}
}