{
  "type": "Feature",
  "properties": {
    "gn:admin1_code":"21.0",
    "gn:asciiname":"Hongguliang",
    "gn:country_code":"CN",
    "gn:dem":1605,
    "gn:feature_class":"P",
    "gn:feature_code":"PPL",
    "gn:name":"Hongguliang",
    "gn:population":0,
    "gn:timezone":"Asia/Shanghai",
    "iso:country":"CN",
    "name:zho_x_preferred":[
        "\u7ea2\u8c37\u6881"
    ],
    "wof:name":"Hongguliang",
    "wof:placetype":"locality"
},
  "geometry": {"coordinates":[105.408,37.3489],"type":"Point"}
}