{
  "type": "Feature",
  "properties": {
    "gn:admin1_code":"16.0",
    "gn:asciiname":"Dongdeng",
    "gn:country_code":"CN",
    "gn:dem":933,
    "gn:feature_class":"P",
    "gn:feature_code":"PPL",
    "gn:name":"Dongdeng",
    "gn:population":0,
    "gn:timezone":"Asia/Shanghai",
    "iso:country":"CN",
    "name:zho_x_preferred":[
        "\u6d1e\u7b49"
    ],
    "wof:name":"Dongdeng",
    "wof:placetype":"locality"
},
  "geometry": {"coordinates":[105.43600000000001,24.692],"type":"Point"}
}