{
  "type": "Feature",
  "properties": {
    "gn:admin1_code":"24.0",
    "gn:asciiname":"Pengtougou",
    "gn:country_code":"CN",
    "gn:dem":1718,
    "gn:feature_class":"P",
    "gn:feature_code":"PPL",
    "gn:name":"Pengtougou",
    "gn:population":0,
    "gn:timezone":"Asia/Shanghai",
    "iso:country":"CN",
    "name:und_x_variant":[
        "\u5f6d\u5934\u6c9f"
    ],
    "name:zho_x_preferred":[
        "\u5f6d\u5934\u6c9f"
    ],
    "wof:name":"Pengtougou",
    "wof:placetype":"locality"
},
  "geometry": {"coordinates":[113.78838,39.67117],"type":"Point"}
}