{
  "type": "Feature",
  "properties": {
    "gn:admin1_code":"1.0",
    "gn:asciiname":"Qinmacun",
    "gn:country_code":"CN",
    "gn:dem":9,
    "gn:feature_class":"P",
    "gn:feature_code":"PPL",
    "gn:name":"Qinmacun",
    "gn:population":0,
    "gn:timezone":"Asia/Shanghai",
    "iso:country":"CN",
    "name:zho_x_preferred":[
        "\u79e6\u9a6c\u6751"
    ],
    "wof:name":"Qinmacun",
    "wof:placetype":"locality"
},
  "geometry": {"coordinates":[117.73116,31.24458],"type":"Point"}
}