{
  "type": "Feature",
  "properties": {
    "gn:admin1_code":"7.0",
    "gn:asciiname":"Langshan",
    "gn:country_code":"CN",
    "gn:dem":8,
    "gn:feature_class":"P",
    "gn:feature_code":"PPL",
    "gn:name":"Langshan",
    "gn:population":0,
    "gn:timezone":"Asia/Shanghai",
    "iso:country":"CN",
    "name:ces_x_preferred":[
        "Lang-\u0161an"
    ],
    "name:zho_x_preferred":[
        "\u7405\u5c71"
    ],
    "wof:name":"Langshan",
    "wof:placetype":"locality"
},
  "geometry": {"coordinates":[118.72717,24.85479],"type":"Point"}
}