{
  "type": "Feature",
  "properties": {
    "gn:admin1_code":"7.0",
    "gn:asciiname":"Liangkecuo",
    "gn:country_code":"CN",
    "gn:dem":347,
    "gn:feature_class":"P",
    "gn:feature_code":"PPL",
    "gn:name":"Liangkecuo",
    "gn:population":0,
    "gn:timezone":"Asia/Shanghai",
    "iso:country":"CN",
    "name:zho_x_preferred":[
        "\u826f\u79d1\u539d"
    ],
    "wof:name":"Liangkecuo",
    "wof:placetype":"locality"
},
  "geometry": {"coordinates":[118.64476000000001,26.09726],"type":"Point"}
}