{
  "type": "Feature",
  "properties": {
    "gn:admin1_code":"7.0",
    "gn:asciiname":"Manli",
    "gn:country_code":"CN",
    "gn:dem":876,
    "gn:feature_class":"P",
    "gn:feature_code":"PPL",
    "gn:name":"Manli",
    "gn:population":0,
    "gn:timezone":"Asia/Shanghai",
    "iso:country":"CN",
    "name:zho_x_preferred":[
        "\u6ee1\u91cc"
    ],
    "wof:name":"Manli",
    "wof:placetype":"locality"
},
  "geometry": {"coordinates":[119.06228,27.01101],"type":"Point"}
}