{
  "type": "Feature",
  "properties": {
    "gn:admin1_code":"10.0",
    "gn:asciiname":"Dahuiluo",
    "gn:country_code":"CN",
    "gn:dem":8,
    "gn:feature_class":"P",
    "gn:feature_code":"PPL",
    "gn:name":"Dahuiluo",
    "gn:population":0,
    "gn:timezone":"Asia/Shanghai",
    "iso:country":"CN",
    "name:zho_x_preferred":[
        "\u5927\u4f1a\u7f57"
    ],
    "wof:name":"Dahuiluo",
    "wof:placetype":"locality"
},
  "geometry": {"coordinates":[116.509,38.6785],"type":"Point"}
}