{
  "type": "Feature",
  "properties": {
    "gn:admin1_code":"15.0",
    "gn:asciiname":"Niujiahe",
    "gn:country_code":"CN",
    "gn:dem":1652,
    "gn:feature_class":"P",
    "gn:feature_code":"PPL",
    "gn:name":"Niujiahe",
    "gn:population":0,
    "gn:timezone":"Asia/Shanghai",
    "iso:country":"CN",
    "name:zho_x_preferred":[
        "\u725b\u5bb6\u6cb3"
    ],
    "wof:name":"Niujiahe",
    "wof:placetype":"locality"
},
  "geometry": {"coordinates":[104.70399999999999,36.0352],"type":"Point"}
}