{
  "type": "Feature",
  "properties": {
    "gn:admin1_code":"03",
    "gn:asciiname":"Luoxi",
    "gn:country_code":"CN",
    "gn:dem":19,
    "gn:feature_class":"P",
    "gn:feature_code":"PPLA4",
    "gn:name":"Luoxi",
    "gn:population":0,
    "gn:timezone":"Asia/Shanghai",
    "iso:country":"CN",
    "name:und_x_variant":[
        "\u7f57\u6eaa",
        "Luoxi Zhen",
        "\u7f57\u6eaa\u9547"
    ],
    "wof:name":"Luoxi",
    "wof:placetype":"locality"
},
  "geometry": {"coordinates":[116.15073999999998,28.4149],"type":"Point"}
}