{
  "type": "Feature",
  "properties": {
    "gn:admin1_code":"18.0",
    "gn:asciiname":"Bailagou",
    "gn:country_code":"CN",
    "gn:dem":653,
    "gn:feature_class":"P",
    "gn:feature_code":"PPL",
    "gn:name":"Bailagou",
    "gn:population":0,
    "gn:timezone":"Asia/Shanghai",
    "iso:country":"CN",
    "name:zho_x_preferred":[
        "\u767d\u814a\u6c9f"
    ],
    "wof:name":"Bailagou",
    "wof:placetype":"locality"
},
  "geometry": {"coordinates":[108.494,27.3077],"type":"Point"}
}