{
  "type": "Feature",
  "properties": {
    "gn:admin1_code":"21.0",
    "gn:asciiname":"Horsefarm",
    "gn:country_code":"CN",
    "gn:dem":2051,
    "gn:feature_class":"P",
    "gn:feature_code":"PPL",
    "gn:name":"Horsefarm",
    "gn:population":0,
    "gn:timezone":"Asia/Shanghai",
    "iso:country":"CN",
    "name:zho_x_preferred":[
        "\u9a6c\u573a"
    ],
    "wof:name":"Horsefarm",
    "wof:placetype":"locality"
},
  "geometry": {"coordinates":[106.021,35.9322],"type":"Point"}
}