{
  "type": "Feature",
  "properties": {
    "gn:admin1_code":"24.0",
    "gn:asciiname":"Lijinzhang",
    "gn:country_code":"CN",
    "gn:dem":1023,
    "gn:feature_class":"P",
    "gn:feature_code":"PPL",
    "gn:name":"Lijinzhang",
    "gn:population":0,
    "gn:timezone":"Asia/Shanghai",
    "iso:country":"CN",
    "name:zho_x_preferred":[
        "\u91cc\u8fdb\u638c"
    ],
    "wof:name":"Lijinzhang",
    "wof:placetype":"locality"
},
  "geometry": {"coordinates":[113.22942999999999,35.59058],"type":"Point"}
}