{
  "type": "Feature",
  "properties": {
    "gn:admin1_code":"18",
    "gn:asciiname":"Maogouchong",
    "gn:country_code":"CN",
    "gn:dem":1142,
    "gn:feature_class":"P",
    "gn:feature_code":"PPL",
    "gn:name":"Maogouchong",
    "gn:population":0,
    "gn:timezone":"Asia/Shanghai",
    "iso:country":"CN",
    "name:zho_x_preferred":[
        "\u6bdb\u6c9f\u51b2"
    ],
    "wof:name":"Maogouchong",
    "wof:placetype":"locality"
},
  "geometry": {"coordinates":[106.723,27.0403],"type":"Point"}
}