{
  "type": "Feature",
  "properties": {
    "gn:admin1_code":"14.0",
    "gn:asciiname":"Dacha",
    "gn:country_code":"CN",
    "gn:dem":3506,
    "gn:feature_class":"P",
    "gn:feature_code":"PPL",
    "gn:name":"Dacha",
    "gn:population":0,
    "gn:timezone":"Asia/Urumqi",
    "iso:country":"CN",
    "name:zho_x_preferred":[
        "\u8fbe\u5bdf"
    ],
    "wof:name":"Dacha",
    "wof:placetype":"locality"
},
  "geometry": {"coordinates":[97.24129000000001,30.10965],"type":"Point"}
}