{
  "type": "Feature",
  "properties": {
    "gn:admin1_code":"33.0",
    "gn:asciiname":"Erpanliang",
    "gn:country_code":"CN",
    "gn:dem":1198,
    "gn:feature_class":"P",
    "gn:feature_code":"PPL",
    "gn:name":"Erpanliang",
    "gn:population":0,
    "gn:timezone":"Asia/Shanghai",
    "iso:country":"CN",
    "name:zho_x_preferred":[
        "\u8033\u76d8\u6881"
    ],
    "wof:name":"Erpanliang",
    "wof:placetype":"locality"
},
  "geometry": {"coordinates":[108.50216,32.10756],"type":"Point"}
}