{
  "type": "Feature",
  "properties": {
    "gn:admin1_code":"15",
    "gn:asciiname":"Xinhe",
    "gn:country_code":"CN",
    "gn:dem":1785,
    "gn:feature_class":"P",
    "gn:feature_code":"PPL",
    "gn:name":"Xinhe",
    "gn:population":0,
    "gn:timezone":"Asia/Shanghai",
    "iso:country":"CN",
    "name:ceb_x_preferred":[
        "Xinhe"
    ],
    "name:deu_x_preferred":[
        "Xinhe"
    ],
    "name:fra_x_preferred":[
        "Xinhe"
    ],
    "name:kor_x_preferred":[
        "\uc2e0\ud5c8\ud604"
    ],
    "wof:name":"Xinhe",
    "wof:placetype":"locality"
},
  "geometry": {"coordinates":[105.23667,36.86667],"type":"Point"}
}