{
  "type": "Feature",
  "properties": {
    "gn:admin1_code":"9.0",
    "gn:asciiname":"Nanfangzhuang",
    "gn:country_code":"CN",
    "gn:dem":116,
    "gn:feature_class":"P",
    "gn:feature_code":"PPL",
    "gn:name":"Nanfangzhuang",
    "gn:population":0,
    "gn:timezone":"Asia/Shanghai",
    "iso:country":"CN",
    "name:zho_x_preferred":[
        "\u5357\u623f\u5e84"
    ],
    "wof:name":"Nanfangzhuang",
    "wof:placetype":"locality"
},
  "geometry": {"coordinates":[113.35814999999999,33.37192],"type":"Point"}
}