{
  "type": "Feature",
  "properties": {
    "gn:admin1_code":"11",
    "gn:asciiname":"Huangjialingxiang",
    "gn:country_code":"CN",
    "gn:dem":342,
    "gn:feature_class":"P",
    "gn:feature_code":"PPL",
    "gn:name":"Huangjialingxiang",
    "gn:population":0,
    "gn:timezone":"Asia/Shanghai",
    "iso:country":"CN",
    "name:und_x_variant":[
        "Huangjialing",
        "Huangjialingxiang"
    ],
    "name:zho_x_preferred":[
        "\u9ec4\u7532\u5cad\u4e61"
    ],
    "wof:name":"Huangjialingxiang",
    "wof:placetype":"locality"
},
  "geometry": {"coordinates":[111.41611,25.20056],"type":"Point"}
}