{
  "type": "Feature",
  "properties": {
    "gn:admin1_code":"11.0",
    "gn:asciiname":"Cuojipo",
    "gn:country_code":"CN",
    "gn:dem":700,
    "gn:feature_class":"P",
    "gn:feature_code":"PPL",
    "gn:name":"Cuojipo",
    "gn:population":0,
    "gn:timezone":"Asia/Shanghai",
    "iso:country":"CN",
    "name:zho_x_preferred":[
        "\u64ae\u7b95\u5761"
    ],
    "wof:name":"Cuojipo",
    "wof:placetype":"locality"
},
  "geometry": {"coordinates":[109.58665999999999,29.30537],"type":"Point"}
}