{
  "type": "Feature",
  "properties": {
    "gn:admin1_code":"3.0",
    "gn:asciiname":"Louxia",
    "gn:country_code":"CN",
    "gn:dem":57,
    "gn:feature_class":"P",
    "gn:feature_code":"PPL",
    "gn:name":"Louxia",
    "gn:population":0,
    "gn:timezone":"Asia/Shanghai",
    "iso:country":"CN",
    "name:und_x_variant":[
        "\u5a04\u4e0b"
    ],
    "wof:name":"Louxia",
    "wof:placetype":"locality"
},
  "geometry": {"coordinates":[116.29531,27.75872],"type":"Point"}
}