{
  "type": "Feature",
  "properties": {
    "gn:admin1_code":"2.0",
    "gn:asciiname":"Dasukeng",
    "gn:country_code":"CN",
    "gn:dem":276,
    "gn:feature_class":"P",
    "gn:feature_code":"PPL",
    "gn:name":"Dasukeng",
    "gn:population":0,
    "gn:timezone":"Asia/Shanghai",
    "iso:country":"CN",
    "name:und_x_variant":[
        "\u5927\u82cf\u5751",
        "Dasukeng"
    ],
    "wof:name":"Dasukeng",
    "wof:placetype":"locality"
},
  "geometry": {"coordinates":[119.58877,27.94678],"type":"Point"}
}