{
  "type": "Feature",
  "properties": {
    "gn:admin1_code":"16.0",
    "gn:asciiname":"Lingrui",
    "gn:country_code":"CN",
    "gn:dem":73,
    "gn:feature_class":"P",
    "gn:feature_code":"PPL",
    "gn:name":"Lingrui",
    "gn:population":0,
    "gn:timezone":"Asia/Shanghai",
    "iso:country":"CN",
    "name:zho_x_preferred":[
        "\u5cad\u745e"
    ],
    "wof:name":"Lingrui",
    "wof:placetype":"locality"
},
  "geometry": {"coordinates":[110.56999999999999,23.3614],"type":"Point"}
}