{
  "type": "Feature",
  "properties": {
    "gn:admin1_code":"9.0",
    "gn:asciiname":"Nangaozhuang",
    "gn:country_code":"CN",
    "gn:dem":219,
    "gn:feature_class":"P",
    "gn:feature_code":"PPL",
    "gn:name":"Nangaozhuang",
    "gn:population":0,
    "gn:timezone":"Asia/Shanghai",
    "iso:country":"CN",
    "name:zho_x_preferred":[
        "\u5357\u9ad8\u5e84"
    ],
    "wof:name":"Nangaozhuang",
    "wof:placetype":"locality"
},
  "geometry": {"coordinates":[113.90692,32.89811],"type":"Point"}
}