{
  "type": "Feature",
  "properties": {
    "gn:admin1_code":"23.0",
    "gn:asciiname":"Nongzhan Sidui",
    "gn:country_code":"CN",
    "gn:dem":7,
    "gn:feature_class":"P",
    "gn:feature_code":"PPLF",
    "gn:name":"Nongzhan Sidui",
    "gn:population":0,
    "gn:timezone":"Asia/Shanghai",
    "iso:country":"CN",
    "name:und_x_variant":[
        "\u519c\u5c55\u56db\u961f"
    ],
    "wof:name":"Nongzhan Sidui",
    "wof:placetype":"locality"
},
  "geometry": {"coordinates":[121.69055,30.91172000000001],"type":"Point"}
}