{
  "type": "Feature",
  "properties": {
    "gn:admin1_code":"14.0",
    "gn:asciiname":"Samukasa",
    "gn:country_code":"CN",
    "gn:dem":4435,
    "gn:feature_class":"P",
    "gn:feature_code":"PPL",
    "gn:name":"Samukasa",
    "gn:population":0,
    "gn:timezone":"Asia/Urumqi",
    "iso:country":"CN",
    "name:zho_x_preferred":[
        "\u8428\u6bcd\u5361\u8428"
    ],
    "wof:name":"Samukasa",
    "wof:placetype":"locality"
},
  "geometry": {"coordinates":[92.33123999999999,31.47647000000001],"type":"Point"}
}