{
  "type": "Feature",
  "properties": {
    "gn:admin1_code":"02",
    "gn:asciiname":"Duanqiao",
    "gn:cc2":"CN",
    "gn:country_code":"CN",
    "gn:dem":37,
    "gn:feature_class":"P",
    "gn:feature_code":"PPL",
    "gn:name":"Duanqiao",
    "gn:population":0,
    "gn:timezone":"Asia/Shanghai",
    "iso:country":"CN",
    "name:und_x_variant":[
        "Tuan-ch\u2019iao",
        "Duanqiao"
    ],
    "wof:name":"Duanqiao",
    "wof:placetype":"locality"
},
  "geometry": {"coordinates":[120.80667,28.88667],"type":"Point"}
}