{
  "type": "Feature",
  "properties": {
    "gn:admin1_code":"10.0",
    "gn:asciiname":"Linggendi",
    "gn:country_code":"CN",
    "gn:dem":462,
    "gn:feature_class":"P",
    "gn:feature_code":"PPL",
    "gn:name":"Linggendi",
    "gn:population":0,
    "gn:timezone":"Asia/Shanghai",
    "iso:country":"CN",
    "name:und_x_variant":[
        "\u5cad\u6839\u5e95"
    ],
    "wof:name":"Linggendi",
    "wof:placetype":"locality"
},
  "geometry": {"coordinates":[114.00342000000001,38.53088],"type":"Point"}
}