{
  "type": "Feature",
  "properties": {
    "gn:admin1_code":"29.0",
    "gn:asciiname":"Malishu",
    "gn:country_code":"CN",
    "gn:dem":1101,
    "gn:feature_class":"P",
    "gn:feature_code":"PPL",
    "gn:name":"Malishu",
    "gn:population":0,
    "gn:timezone":"Asia/Shanghai",
    "iso:country":"CN",
    "name:zho_x_preferred":[
        "\u9ebb\u6817\u6811"
    ],
    "wof:name":"Malishu",
    "wof:placetype":"locality"
},
  "geometry": {"coordinates":[98.9268,23.8225],"type":"Point"}
}