{
  "type": "Feature",
  "properties": {
    "gn:admin1_code":"12.0",
    "gn:asciiname":"Luojiaya",
    "gn:country_code":"CN",
    "gn:dem":1250,
    "gn:feature_class":"P",
    "gn:feature_code":"PPL",
    "gn:name":"Luojiaya",
    "gn:population":0,
    "gn:timezone":"Asia/Shanghai",
    "iso:country":"CN",
    "name:zho_x_preferred":[
        "\u7f57\u5bb6\u57ad"
    ],
    "wof:name":"Luojiaya",
    "wof:placetype":"locality"
},
  "geometry": {"coordinates":[110.13919,31.54561],"type":"Point"}
}