{
  "type": "Feature",
  "properties": {
    "gn:admin1_code":"1.0",
    "gn:asciiname":"Yinggangcun",
    "gn:country_code":"CN",
    "gn:dem":39,
    "gn:feature_class":"P",
    "gn:feature_code":"PPL",
    "gn:name":"Yinggangcun",
    "gn:population":0,
    "gn:timezone":"Asia/Shanghai",
    "iso:country":"CN",
    "name:zho_x_preferred":[
        "\u8fce\u5c97\u6751"
    ],
    "wof:name":"Yinggangcun",
    "wof:placetype":"locality"
},
  "geometry": {"coordinates":[116.16701999999999,31.83467000000001],"type":"Point"}
}