{
  "type": "Feature",
  "properties": {
    "gn:admin1_code":"2.0",
    "gn:asciiname":"Zhuhu",
    "gn:country_code":"CN",
    "gn:dem":109,
    "gn:feature_class":"P",
    "gn:feature_code":"PPL",
    "gn:name":"Zhuhu",
    "gn:population":0,
    "gn:timezone":"Asia/Shanghai",
    "iso:country":"CN",
    "name:zho_x_preferred":[
        "\u6f74\u6e56"
    ],
    "wof:name":"Zhuhu",
    "wof:placetype":"locality"
},
  "geometry": {"coordinates":[120.02249,29.34762000000001],"type":"Point"}
}