{
  "type": "Feature",
  "properties": {
    "gn:admin1_code":"11.0",
    "gn:asciiname":"Shexiacun",
    "gn:country_code":"CN",
    "gn:dem":178,
    "gn:feature_class":"P",
    "gn:feature_code":"PPL",
    "gn:name":"Shexiacun",
    "gn:population":0,
    "gn:timezone":"Asia/Shanghai",
    "iso:country":"CN",
    "name:zho_x_preferred":[
        "\u793e\u4e0b\u6751"
    ],
    "wof:name":"Shexiacun",
    "wof:placetype":"locality"
},
  "geometry": {"coordinates":[112.48387,25.7601],"type":"Point"}
}