{
  "type": "Feature",
  "properties": {
    "gn:admin1_code":"8.0",
    "gn:asciiname":"Xinfu",
    "gn:country_code":"CN",
    "gn:dem":137,
    "gn:feature_class":"P",
    "gn:feature_code":"PPLA4",
    "gn:name":"Xinfu",
    "gn:population":0,
    "gn:timezone":"Asia/Shanghai",
    "iso:country":"CN",
    "name:ceb_x_preferred":[
        "Xinfu"
    ],
    "name:deu_x_preferred":[
        "Xinfu"
    ],
    "name:fra_x_preferred":[
        "Xinfu"
    ],
    "name:kor_x_preferred":[
        "\uc2e0\ud478\uad6c"
    ],
    "name:nor_x_preferred":[
        "Xinfu"
    ],
    "name:rus_x_preferred":[
        "\u0421\u0438\u043d\u044c\u0444\u0443"
    ],
    "name:swe_x_preferred":[
        "Xinfu"
    ],
    "name:und_x_variant":[
        "\u5e78\u798f",
        "Xinfu Xiang"
    ],
    "name:zho_x_preferred":[
        "\u5e78\u798f\u4e61"
    ],
    "wof:name":"Xinfu",
    "wof:placetype":"locality"
},
  "geometry": {"coordinates":[127.48997,50.23784000000001],"type":"Point"}
}