{
  "type": "Feature",
  "properties": {
    "gn:admin1_code":"24.0",
    "gn:asciiname":"Shangbaihou",
    "gn:country_code":"CN",
    "gn:dem":1276,
    "gn:feature_class":"P",
    "gn:feature_code":"PPL",
    "gn:name":"Shangbaihou",
    "gn:population":0,
    "gn:timezone":"Asia/Shanghai",
    "iso:country":"CN",
    "name:zho_x_preferred":[
        "\u4e0a\u767d\u5820"
    ],
    "wof:name":"Shangbaihou",
    "wof:placetype":"locality"
},
  "geometry": {"coordinates":[113.15658000000001,37.17429],"type":"Point"}
}