{
  "type": "Feature",
  "properties": {
    "gn:admin1_code":"15.0",
    "gn:asciiname":"Zhaojia Shagou",
    "gn:country_code":"CN",
    "gn:dem":1826,
    "gn:feature_class":"P",
    "gn:feature_code":"PPL",
    "gn:name":"Zhaojia Shagou",
    "gn:population":0,
    "gn:timezone":"Asia/Shanghai",
    "iso:country":"CN",
    "name:zho_x_preferred":[
        "\u8d75\u5bb6\u6c99\u6c9f"
    ],
    "wof:name":"Zhaojia Shagou",
    "wof:placetype":"locality"
},
  "geometry": {"coordinates":[102.327,38.0203],"type":"Point"}
}