{
  "type": "Feature",
  "properties": {
    "gn:admin1_code":"19.0",
    "gn:asciiname":"Sanyanjingcun",
    "gn:country_code":"CN",
    "gn:dem":83,
    "gn:feature_class":"P",
    "gn:feature_code":"PPL",
    "gn:name":"Sanyanjingcun",
    "gn:population":0,
    "gn:timezone":"Asia/Shanghai",
    "iso:country":"CN",
    "name:zho_x_preferred":[
        "\u4e09\u773c\u4e95\u6751"
    ],
    "wof:name":"Sanyanjingcun",
    "wof:placetype":"locality"
},
  "geometry": {"coordinates":[123.66795,42.74558],"type":"Point"}
}