{
  "type": "Feature",
  "properties": {
    "gn:admin1_code":"9.0",
    "gn:asciiname":"Hualiucun",
    "gn:country_code":"CN",
    "gn:dem":112,
    "gn:feature_class":"P",
    "gn:feature_code":"PPL",
    "gn:name":"Hualiucun",
    "gn:population":0,
    "gn:timezone":"Asia/Shanghai",
    "iso:country":"CN",
    "name:zho_x_preferred":[
        "\u82b1\u5218\u6751"
    ],
    "wof:name":"Hualiucun",
    "wof:placetype":"locality"
},
  "geometry": {"coordinates":[113.3553,33.99545999999999],"type":"Point"}
}