{
  "type": "Feature",
  "properties": {
    "gn:admin1_code":"26.0",
    "gn:asciiname":"Fanjiagou",
    "gn:country_code":"CN",
    "gn:dem":1126,
    "gn:feature_class":"P",
    "gn:feature_code":"PPL",
    "gn:name":"Fanjiagou",
    "gn:population":0,
    "gn:timezone":"Asia/Shanghai",
    "iso:country":"CN",
    "name:zho_x_preferred":[
        "\u8303\u5bb6\u6c9f"
    ],
    "wof:name":"Fanjiagou",
    "wof:placetype":"locality"
},
  "geometry": {"coordinates":[109.07675,38.01201],"type":"Point"}
}