{
  "type": "Feature",
  "properties": {
    "gn:admin1_code":"16.0",
    "gn:asciiname":"Shiwan",
    "gn:country_code":"CN",
    "gn:dem":294,
    "gn:feature_class":"P",
    "gn:feature_code":"PPL",
    "gn:name":"Shiwan",
    "gn:population":0,
    "gn:timezone":"Asia/Shanghai",
    "iso:country":"CN",
    "name:deu_x_preferred":[
        "Shiwan"
    ],
    "name:zho_x_preferred":[
        "\u77f3\u6e7e"
    ],
    "wof:name":"Shiwan",
    "wof:placetype":"locality"
},
  "geometry": {"coordinates":[107.328,24.0638],"type":"Point"}
}