{
  "type": "Feature",
  "properties": {
    "gn:admin1_code":"30.0",
    "gn:asciiname":"Yingzai",
    "gn:country_code":"CN",
    "gn:dem":22,
    "gn:feature_class":"P",
    "gn:feature_code":"PPLA4",
    "gn:name":"Yingzai",
    "gn:population":0,
    "gn:timezone":"Asia/Urumqi",
    "iso:country":"CN",
    "name:und_x_variant":[
        "Yingzai Zhen",
        "\u8425\u4ed4\u9547"
    ],
    "name:zho_x_preferred":[
        "\u8425\u4ed4"
    ],
    "wof:name":"Yingzai",
    "wof:placetype":"locality"
},
  "geometry": {"coordinates":[109.9252,21.49052],"type":"Point"}
}