{
  "type": "Feature",
  "properties": {
    "gn:admin1_code":"29.0",
    "gn:asciiname":"Machang",
    "gn:country_code":"CN",
    "gn:dem":1997,
    "gn:feature_class":"P",
    "gn:feature_code":"PPL",
    "gn:name":"Machang",
    "gn:population":0,
    "gn:timezone":"Asia/Shanghai",
    "iso:country":"CN",
    "name:ceb_x_preferred":[
        "Machang"
    ],
    "name:deu_x_preferred":[
        "Machang"
    ],
    "name:nld_x_preferred":[
        "Machang"
    ],
    "name:nor_x_preferred":[
        "Machang"
    ],
    "name:swe_x_preferred":[
        "Machang"
    ],
    "name:vie_x_preferred":[
        "Machang"
    ],
    "name:zho_x_preferred":[
        "\u9a6c\u5382"
    ],
    "name:zho_x_variant":[
        "\u9a6c\u5382\u9547"
    ],
    "wof:name":"Machang",
    "wof:placetype":"locality"
},
  "geometry": {"coordinates":[103.849,24.8253],"type":"Point"}
}