{
  "type": "Feature",
  "properties": {
    "gn:admin1_code":"29",
    "gn:asciiname":"T'ai-yang-chai",
    "gn:country_code":"CN",
    "gn:dem":1153,
    "gn:feature_class":"P",
    "gn:feature_code":"PPL",
    "gn:name":"T\u2019ai-yang-chai",
    "gn:population":0,
    "gn:timezone":"Asia/Shanghai",
    "iso:country":"CN",
    "wof:name":"T'ai-yang-chai",
    "wof:placetype":"locality"
},
  "geometry": {"coordinates":[103.98860999999999,22.77972],"type":"Point"}
}