{
  "type": "Feature",
  "properties": {
    "gn:admin1_code":"10",
    "gn:asciiname":"Yangshugou",
    "gn:country_code":"CN",
    "gn:dem":1619,
    "gn:feature_class":"P",
    "gn:feature_code":"PPL",
    "gn:name":"Yangshugou",
    "gn:population":0,
    "gn:timezone":"Asia/Shanghai",
    "iso:country":"CN",
    "name:zho_x_preferred":[
        "\u6768\u6811\u6c9f"
    ],
    "wof:name":"Yangshugou",
    "wof:placetype":"locality"
},
  "geometry": {"coordinates":[115.32102,41.15444],"type":"Point"}
}