{
  "type": "Feature",
  "properties": {
    "gn:admin1_code":"10",
    "gn:asciiname":"Weiyuantun",
    "gn:country_code":"CN",
    "gn:dem":16,
    "gn:feature_class":"P",
    "gn:feature_code":"PPL",
    "gn:name":"Weiyuantun",
    "gn:population":0,
    "gn:timezone":"Asia/Shanghai",
    "iso:country":"CN",
    "name:zho_x_preferred":[
        "\u82c7\u5143\u5c6f"
    ],
    "wof:name":"Weiyuantun",
    "wof:placetype":"locality"
},
  "geometry": {"coordinates":[115.63200000000001,38.7188],"type":"Point"}
}