{
  "type": "Feature",
  "properties": {
    "gn:admin1_code":"25",
    "gn:asciiname":"Lintun",
    "gn:country_code":"CN",
    "gn:dem":49,
    "gn:feature_class":"P",
    "gn:feature_code":"PPL",
    "gn:name":"Lintun",
    "gn:population":0,
    "gn:timezone":"Asia/Shanghai",
    "iso:country":"CN",
    "name:zho_x_preferred":[
        "\u853a\u5c6f"
    ],
    "wof:name":"Lintun",
    "wof:placetype":"locality"
},
  "geometry": {"coordinates":[115.762,35.7031],"type":"Point"}
}