{
  "type": "Feature",
  "properties": {
    "gn:admin1_code":"26.0",
    "gn:asciiname":"Qi'anzicun",
    "gn:country_code":"CN",
    "gn:dem":1274,
    "gn:feature_class":"P",
    "gn:feature_code":"PPL",
    "gn:name":"Qi\u2019anzicun",
    "gn:population":0,
    "gn:timezone":"Asia/Shanghai",
    "iso:country":"CN",
    "name:und_x_variant":[
        "Qi\u2019anzicun"
    ],
    "name:zho_x_preferred":[
        "\u4e03\u5b89\u5b50\u6751"
    ],
    "wof:name":"Qi'anzicun",
    "wof:placetype":"locality"
},
  "geometry": {"coordinates":[109.39209,33.89735],"type":"Point"}
}