{
  "type": "Feature",
  "properties": {
    "gn:admin1_code":"12.0",
    "gn:asciiname":"Zhaizishang",
    "gn:country_code":"CN",
    "gn:dem":1094,
    "gn:feature_class":"P",
    "gn:feature_code":"PPL",
    "gn:name":"Zhaizishang",
    "gn:population":0,
    "gn:timezone":"Asia/Shanghai",
    "iso:country":"CN",
    "name:zho_x_preferred":[
        "\u5be8\u5b50\u4e0a"
    ],
    "wof:name":"Zhaizishang",
    "wof:placetype":"locality"
},
  "geometry": {"coordinates":[109.15788000000001,29.75483],"type":"Point"}
}