{
  "type": "Feature",
  "properties": {
    "gn:admin1_code":"19.0",
    "gn:asciiname":"Shijiagoucun",
    "gn:country_code":"CN",
    "gn:dem":98,
    "gn:feature_class":"P",
    "gn:feature_code":"PPL",
    "gn:name":"Shijiagoucun",
    "gn:population":0,
    "gn:timezone":"Asia/Shanghai",
    "iso:country":"CN",
    "name:zho_x_preferred":[
        "\u77f3\u5bb6\u6c9f\u6751"
    ],
    "wof:name":"Shijiagoucun",
    "wof:placetype":"locality"
},
  "geometry": {"coordinates":[121.923,41.8237],"type":"Point"}
}