{
  "type": "Feature",
  "properties": {
    "gn:admin1_code":"16",
    "gn:asciiname":"Jinguidong",
    "gn:country_code":"CN",
    "gn:dem":315,
    "gn:feature_class":"P",
    "gn:feature_code":"PPL",
    "gn:name":"Jinguidong",
    "gn:population":0,
    "gn:timezone":"Asia/Shanghai",
    "iso:country":"CN",
    "name:zho_x_preferred":[
        "\u91d1\u9f9f\u6d1e"
    ],
    "wof:name":"Jinguidong",
    "wof:placetype":"locality"
},
  "geometry": {"coordinates":[110.477,24.8378],"type":"Point"}
}