{
  "type": "Feature",
  "properties": {
    "gn:admin1_code":"19.0",
    "gn:asciiname":"Maquanzigou",
    "gn:country_code":"CN",
    "gn:dem":220,
    "gn:feature_class":"P",
    "gn:feature_code":"PPL",
    "gn:name":"Maquanzigou",
    "gn:population":0,
    "gn:timezone":"Asia/Shanghai",
    "iso:country":"CN",
    "name:und_x_variant":[
        "\u9a6c\u5708\u5b50\u6c9f"
    ],
    "name:zho_x_preferred":[
        "\u9a6c\u5708\u5b50\u6c9f"
    ],
    "wof:name":"Maquanzigou",
    "wof:placetype":"locality"
},
  "geometry": {"coordinates":[124.52143,40.86788],"type":"Point"}
}