{
  "type": "Feature",
  "properties": {
    "gn:admin1_code":"26.0",
    "gn:asciiname":"Yuanjiashan",
    "gn:country_code":"CN",
    "gn:dem":1292,
    "gn:feature_class":"P",
    "gn:feature_code":"PPL",
    "gn:name":"Yuanjiashan",
    "gn:population":0,
    "gn:timezone":"Asia/Shanghai",
    "iso:country":"CN",
    "name:und_x_variant":[
        "\u8881\u5bb6\u5c71"
    ],
    "wof:name":"Yuanjiashan",
    "wof:placetype":"locality"
},
  "geometry": {"coordinates":[107.00161,33.75491],"type":"Point"}
}