{
  "type": "Feature",
  "properties": {
    "gn:admin1_code":"15.0",
    "gn:asciiname":"Majiayaoxian",
    "gn:country_code":"CN",
    "gn:dem":1531,
    "gn:feature_class":"P",
    "gn:feature_code":"PPL",
    "gn:name":"Majiayaoxian",
    "gn:population":0,
    "gn:timezone":"Asia/Shanghai",
    "iso:country":"CN",
    "name:und_x_variant":[
        "\u9a6c\u5bb6\u5d3e\u5c98"
    ],
    "wof:name":"Majiayaoxian",
    "wof:placetype":"locality"
},
  "geometry": {"coordinates":[106.88706000000001,36.85959],"type":"Point"}
}