{
  "type": "Feature",
  "properties": {
    "gn:admin1_code":"29.0",
    "gn:asciiname":"Shanghuapan",
    "gn:country_code":"CN",
    "gn:dem":2345,
    "gn:feature_class":"P",
    "gn:feature_code":"PPL",
    "gn:name":"Shanghuapan",
    "gn:population":0,
    "gn:timezone":"Asia/Shanghai",
    "iso:country":"CN",
    "name:zho_x_preferred":[
        "\u4e0a\u82b1\u76d8"
    ],
    "wof:name":"Shanghuapan",
    "wof:placetype":"locality"
},
  "geometry": {"coordinates":[100.113,25.512],"type":"Point"}
}