{
  "type": "Feature",
  "properties": {
    "gn:admin1_code":"14.0",
    "gn:asciiname":"Duogen",
    "gn:country_code":"CN",
    "gn:dem":4090,
    "gn:feature_class":"P",
    "gn:feature_code":"PPL",
    "gn:name":"Duogen",
    "gn:population":0,
    "gn:timezone":"Asia/Urumqi",
    "iso:country":"CN",
    "name:zho_x_preferred":[
        "\u591a\u6839"
    ],
    "wof:name":"Duogen",
    "wof:placetype":"locality"
},
  "geometry": {"coordinates":[96.15472,31.17782],"type":"Point"}
}