{
  "type": "Feature",
  "properties": {
    "iso:country":"CN",
    "qs:name":"\u8386\u7530\u5e02",
    "qs:name_adm0":"\u4e2d\u570b",
    "qs:name_adm1":"\u798f\u5efa\u7701",
    "qs:photos":2,
    "qs:photos_1k":1,
    "qs:photos_9k":2,
    "qs:photos_9r":5,
    "qs:photos_all":516,
    "qs:photos_sr":1,
    "qs:placetype":"LocalAdmin",
    "qs:pop_sr":"0",
    "wof:name":"\u8386\u7530\u5e02",
    "wof:placetype":"localadmin"
},
  "geometry": {"coordinates":[119.00339099999999,25.431924],"type":"Point"}
}