{
  "type": "Feature",
  "properties": {
    "gn:admin1_code":"1.0",
    "gn:asciiname":"Duloucun",
    "gn:country_code":"CN",
    "gn:dem":23,
    "gn:feature_class":"P",
    "gn:feature_code":"PPL",
    "gn:name":"Duloucun",
    "gn:population":0,
    "gn:timezone":"Asia/Shanghai",
    "iso:country":"CN",
    "name:zho_x_preferred":[
        "\u675c\u697c\u6751"
    ],
    "wof:name":"Duloucun",
    "wof:placetype":"locality"
},
  "geometry": {"coordinates":[116.46210000000001,32.50848],"type":"Point"}
}