{
  "type": "Feature",
  "properties": {
    "gn:admin1_code":"19.0",
    "gn:asciiname":"Caomaoshan Nangou",
    "gn:country_code":"CN",
    "gn:dem":771,
    "gn:feature_class":"P",
    "gn:feature_code":"PPL",
    "gn:name":"Caomaoshan Nangou",
    "gn:population":0,
    "gn:timezone":"Asia/Shanghai",
    "iso:country":"CN",
    "name:zho_x_preferred":[
        "\u8349\u5e3d\u5c71\u5357\u6c9f"
    ],
    "wof:name":"Caomaoshan Nangou",
    "wof:placetype":"locality"
},
  "geometry": {"coordinates":[119.76000000000001,41.7258],"type":"Point"}
}