{
  "type": "Feature",
  "properties": {
    "gn:admin1_code":"4.0",
    "gn:asciiname":"Beifengtouba",
    "gn:country_code":"CN",
    "gn:dem":7,
    "gn:feature_class":"P",
    "gn:feature_code":"PPL",
    "gn:name":"Beifengtouba",
    "gn:population":0,
    "gn:timezone":"Asia/Shanghai",
    "iso:country":"CN",
    "name:zho_x_preferred":[
        "\u5317\u98ce\u5934\u575d"
    ],
    "wof:name":"Beifengtouba",
    "wof:placetype":"locality"
},
  "geometry": {"coordinates":[120.29696,32.0097],"type":"Point"}
}