{
  "type": "Feature",
  "properties": {
    "gn:admin1_code":"10.0",
    "gn:asciiname":"Ximalian",
    "gn:country_code":"CN",
    "gn:dem":9,
    "gn:feature_class":"P",
    "gn:feature_code":"PPL",
    "gn:name":"Ximalian",
    "gn:population":0,
    "gn:timezone":"Asia/Shanghai",
    "iso:country":"CN",
    "name:zho_x_preferred":[
        "\u897f\u9a6c\u8fde"
    ],
    "wof:name":"Ximalian",
    "wof:placetype":"locality"
},
  "geometry": {"coordinates":[117.20999999999999,38.2378],"type":"Point"}
}