{
  "type": "Feature",
  "properties": {
    "gn:admin1_code":"12",
    "gn:asciiname":"Niejiawan",
    "gn:country_code":"CN",
    "gn:dem":134,
    "gn:feature_class":"P",
    "gn:feature_code":"PPL",
    "gn:name":"Niejiawan",
    "gn:population":0,
    "gn:timezone":"Asia/Shanghai",
    "iso:country":"CN",
    "wof:name":"Niejiawan",
    "wof:placetype":"locality"
},
  "geometry": {"coordinates":[111.39749999999999,30.3375],"type":"Point"}
}