{
  "type": "Feature",
  "properties": {
    "gn:admin1_code":"15.0",
    "gn:asciiname":"Langzangshan",
    "gn:country_code":"CN",
    "gn:dem":1781,
    "gn:feature_class":"P",
    "gn:feature_code":"PPL",
    "gn:name":"Langzangshan",
    "gn:population":0,
    "gn:timezone":"Asia/Shanghai",
    "iso:country":"CN",
    "name:und_x_variant":[
        "\u90ce\u85cf\u5c71"
    ],
    "name:zho_x_preferred":[
        "\u90ce\u85cf\u5c71"
    ],
    "wof:name":"Langzangshan",
    "wof:placetype":"locality"
},
  "geometry": {"coordinates":[104.46518,32.99679],"type":"Point"}
}