{
  "type": "Feature",
  "properties": {
    "gn:admin1_code":"11",
    "gn:asciiname":"Taohuajiang",
    "gn:country_code":"CN",
    "gn:dem":45,
    "gn:feature_class":"P",
    "gn:feature_code":"PPLA3",
    "gn:name":"Taohuajiang",
    "gn:population":0,
    "gn:timezone":"Asia/Shanghai",
    "iso:country":"CN",
    "name:und_x_variant":[
        "Taojiang",
        "Taohuajiang",
        "Taojiang Xian"
    ],
    "name:zho_x_preferred":[
        "T\u2019ao-chiang-chen"
    ],
    "name:zho_x_variant":[
        "T\u2019ao-hua-chiang",
        "T\u2019ao-chiang",
        "\u6843\u82b1\u6c5f",
        "\u6843\u6c5f\u53bf",
        "\u6843\u82b1\u6c5f\u9547"
    ],
    "wof:name":"Taohuajiang",
    "wof:placetype":"locality"
},
  "geometry": {"coordinates":[112.12528,28.52361],"type":"Point"}
}