{
  "type": "Feature",
  "properties": {
    "gn:admin1_code":"20.0",
    "gn:asciiname":"Dashuiping",
    "gn:country_code":"CN",
    "gn:dem":1148,
    "gn:feature_class":"P",
    "gn:feature_code":"PPL",
    "gn:name":"Dashuiping",
    "gn:population":0,
    "gn:timezone":"Asia/Shanghai",
    "iso:country":"CN",
    "name:und_x_variant":[
        "\u5927\u6c34\u576a"
    ],
    "wof:name":"Dashuiping",
    "wof:placetype":"locality"
},
  "geometry": {"coordinates":[111.45744000000001,40.14899000000001],"type":"Point"}
}