{
  "type": "Feature",
  "properties": {
    "gn:admin1_code":"8.0",
    "gn:asciiname":"Zhengqi",
    "gn:country_code":"CN",
    "gn:dem":197,
    "gn:feature_class":"P",
    "gn:feature_code":"PPL",
    "gn:name":"Zhengqi",
    "gn:population":0,
    "gn:timezone":"Asia/Shanghai",
    "iso:country":"CN",
    "name:zho_x_preferred":[
        "\u6b63\u68cb"
    ],
    "wof:name":"Zhengqi",
    "wof:placetype":"locality"
},
  "geometry": {"coordinates":[126.17874,52.54186],"type":"Point"}
}