{
  "type": "Feature",
  "properties": {
    "gn:admin1_code":"13.0",
    "gn:asciiname":"Bageqi",
    "gn:country_code":"CN",
    "gn:dem":1413,
    "gn:feature_class":"P",
    "gn:feature_code":"PPL",
    "gn:name":"Bageqi",
    "gn:population":0,
    "gn:timezone":"Asia/Urumqi",
    "iso:country":"CN",
    "name:zho_x_preferred":[
        "\u5df4\u683c\u5176"
    ],
    "wof:name":"Bageqi",
    "wof:placetype":"locality"
},
  "geometry": {"coordinates":[82.96325,37.12353],"type":"Point"}
}