{
  "type": "Feature",
  "properties": {
    "gn:admin1_code":"22.0",
    "gn:asciiname":"Datangshancun",
    "gn:country_code":"CN",
    "gn:dem":94,
    "gn:feature_class":"P",
    "gn:feature_code":"PPL",
    "gn:name":"Datangshancun",
    "gn:population":0,
    "gn:timezone":"Asia/Shanghai",
    "iso:country":"CN",
    "name:zho_x_preferred":[
        "\u5927\u6c64\u5c71\u6751"
    ],
    "wof:name":"Datangshancun",
    "wof:placetype":"locality"
},
  "geometry": {"coordinates":[116.363,40.17987],"type":"Point"}
}