{
  "type": "Feature",
  "properties": {
    "gn:admin1_code":"29.0",
    "gn:asciiname":"Tianbian",
    "gn:country_code":"CN",
    "gn:dem":1655,
    "gn:feature_class":"P",
    "gn:feature_code":"PPL",
    "gn:name":"Tianbian",
    "gn:population":0,
    "gn:timezone":"Asia/Shanghai",
    "iso:country":"CN",
    "name:zho_x_preferred":[
        "\u7530\u8fb9"
    ],
    "wof:name":"Tianbian",
    "wof:placetype":"locality"
},
  "geometry": {"coordinates":[103.64700000000001,26.8843],"type":"Point"}
}