{
  "type": "Feature",
  "properties": {
    "gn:admin1_code":"30.0",
    "gn:asciiname":"Laofangcun",
    "gn:country_code":"CN",
    "gn:dem":6,
    "gn:feature_class":"P",
    "gn:feature_code":"PPL",
    "gn:name":"Laofangcun",
    "gn:population":0,
    "gn:timezone":"Asia/Shanghai",
    "iso:country":"CN",
    "name:zho_x_preferred":[
        "\u8001\u65b9\u6751"
    ],
    "wof:name":"Laofangcun",
    "wof:placetype":"locality"
},
  "geometry": {"coordinates":[116.23211000000001,23.50012000000001],"type":"Point"}
}