{
  "type": "Feature",
  "properties": {
    "gn:admin1_code":"26.0",
    "gn:asciiname":"Malianhe",
    "gn:country_code":"CN",
    "gn:dem":1235,
    "gn:feature_class":"P",
    "gn:feature_code":"PPL",
    "gn:name":"Malianhe",
    "gn:population":0,
    "gn:timezone":"Asia/Shanghai",
    "iso:country":"CN",
    "name:zho_x_preferred":[
        "\u9a6c\u8fde\u6cb3"
    ],
    "wof:name":"Malianhe",
    "wof:placetype":"locality"
},
  "geometry": {"coordinates":[109.94902,39.06947],"type":"Point"}
}