{
  "type": "Feature",
  "properties": {
    "gn:admin1_code":"24.0",
    "gn:asciiname":"Dataicun",
    "gn:country_code":"CN",
    "gn:dem":395,
    "gn:feature_class":"P",
    "gn:feature_code":"PPL",
    "gn:name":"Dataicun",
    "gn:population":0,
    "gn:timezone":"Asia/Shanghai",
    "iso:country":"CN",
    "name:zho_x_preferred":[
        "\u5927\u53f0\u6751"
    ],
    "wof:name":"Dataicun",
    "wof:placetype":"locality"
},
  "geometry": {"coordinates":[111.19831000000001,35.17999],"type":"Point"}
}