{
  "type": "Feature",
  "properties": {
    "gn:admin1_code":"19.0",
    "gn:asciiname":"Dongyingzi",
    "gn:country_code":"CN",
    "gn:dem":261,
    "gn:feature_class":"P",
    "gn:feature_code":"PPL",
    "gn:name":"Dongyingzi",
    "gn:population":0,
    "gn:timezone":"Asia/Shanghai",
    "iso:country":"CN",
    "name:zho_x_preferred":[
        "\u4e1c\u8425\u5b50"
    ],
    "wof:name":"Dongyingzi",
    "wof:placetype":"locality"
},
  "geometry": {"coordinates":[119.923,41.2354],"type":"Point"}
}