{
  "type": "Feature",
  "properties": {
    "gn:admin1_code":"26.0",
    "gn:asciiname":"Liangmengjia Tacun",
    "gn:country_code":"CN",
    "gn:dem":1044,
    "gn:feature_class":"P",
    "gn:feature_code":"PPL",
    "gn:name":"Liangmengjia Tacun",
    "gn:population":0,
    "gn:timezone":"Asia/Shanghai",
    "iso:country":"CN",
    "name:zho_x_preferred":[
        "\u6881\u5b5f\u5bb6\u5854\u6751"
    ],
    "wof:name":"Liangmengjia Tacun",
    "wof:placetype":"locality"
},
  "geometry": {"coordinates":[110.633,38.4526],"type":"Point"}
}