{
  "type": "Feature",
  "properties": {
    "gn:admin1_code":"12.0",
    "gn:asciiname":"Caiziping",
    "gn:country_code":"CN",
    "gn:dem":75,
    "gn:feature_class":"P",
    "gn:feature_code":"PPL",
    "gn:name":"Caiziping",
    "gn:population":0,
    "gn:timezone":"Asia/Shanghai",
    "iso:country":"CN",
    "name:zho_x_preferred":[
        "Caiziping"
    ],
    "name:zho_x_variant":[
        "\u83dc\u5b50\u576a"
    ],
    "wof:name":"Caiziping",
    "wof:placetype":"locality"
},
  "geometry": {"coordinates":[111.60496999999999,30.53224],"type":"Point"}
}