{
  "type": "Feature",
  "properties": {
    "gn:admin1_code":"4.0",
    "gn:asciiname":"Dongtan",
    "gn:country_code":"CN",
    "gn:dem":-3,
    "gn:feature_class":"P",
    "gn:feature_code":"PPL",
    "gn:name":"Dongtan",
    "gn:population":0,
    "gn:timezone":"Asia/Shanghai",
    "iso:country":"CN",
    "name:deu_x_preferred":[
        "Dongtan"
    ],
    "name:zho_x_preferred":[
        "Dongtan"
    ],
    "name:zho_x_variant":[
        "\u8463\u6ee9"
    ],
    "wof:name":"Dongtan",
    "wof:placetype":"locality"
},
  "geometry": {"coordinates":[119.88630999999999,33.77268],"type":"Point"}
}