{
  "type": "Feature",
  "properties": {
    "gn:admin1_code":"3.0",
    "gn:asciiname":"Meifangyuan",
    "gn:country_code":"CN",
    "gn:dem":454,
    "gn:feature_class":"P",
    "gn:feature_code":"PPL",
    "gn:name":"Meifangyuan",
    "gn:population":0,
    "gn:timezone":"Asia/Shanghai",
    "iso:country":"CN",
    "name:und_x_variant":[
        "\u6885\u574a\u6e90"
    ],
    "wof:name":"Meifangyuan",
    "wof:placetype":"locality"
},
  "geometry": {"coordinates":[115.65774999999999,25.22787000000001],"type":"Point"}
}