{
  "type": "Feature",
  "properties": {
    "gn:admin1_code":"23.0",
    "gn:asciiname":"Dongqi",
    "gn:country_code":"CN",
    "gn:dem":4,
    "gn:feature_class":"P",
    "gn:feature_code":"PPL",
    "gn:name":"Dongqi",
    "gn:population":0,
    "gn:timezone":"Asia/Shanghai",
    "iso:country":"CN",
    "name:und_x_variant":[
        "\u4e1c\u6dc7"
    ],
    "wof:name":"Dongqi",
    "wof:placetype":"locality"
},
  "geometry": {"coordinates":[121.01309999999999,30.97901],"type":"Point"}
}