{
  "type": "Feature",
  "properties": {
    "gn:admin1_code":"7.0",
    "gn:asciiname":"Dajinglou",
    "gn:country_code":"CN",
    "gn:dem":281,
    "gn:feature_class":"P",
    "gn:feature_code":"PPL",
    "gn:name":"Dajinglou",
    "gn:population":0,
    "gn:timezone":"Asia/Shanghai",
    "iso:country":"CN",
    "name:zho_x_preferred":[
        "\u5927\u4eac\u697c"
    ],
    "wof:name":"Dajinglou",
    "wof:placetype":"locality"
},
  "geometry": {"coordinates":[120.05047999999999,26.66347],"type":"Point"}
}