{
  "type": "Feature",
  "properties": {
    "gn:admin1_code":"24.0",
    "gn:asciiname":"Xiashihui",
    "gn:country_code":"CN",
    "gn:dem":1422,
    "gn:feature_class":"P",
    "gn:feature_code":"PPL",
    "gn:name":"Xiashihui",
    "gn:population":0,
    "gn:timezone":"Asia/Shanghai",
    "iso:country":"CN",
    "name:und_x_variant":[
        "\u4e0b\u77f3\u4f1a"
    ],
    "name:zho_x_preferred":[
        "\u4e0b\u77f3\u4f1a"
    ],
    "wof:name":"Xiashihui",
    "wof:placetype":"locality"
},
  "geometry": {"coordinates":[111.93864000000001,39.20392],"type":"Point"}
}