{
  "type": "Feature",
  "properties": {
    "gn:admin1_code":"3",
    "gn:asciiname":"Fenglin",
    "gn:country_code":"CN",
    "gn:dem":46,
    "gn:feature_class":"P",
    "gn:feature_code":"PPL",
    "gn:name":"Fenglin",
    "gn:population":0,
    "gn:timezone":"Asia/Shanghai",
    "iso:country":"CN",
    "name:ceb_x_preferred":[
        "Fenglin"
    ],
    "name:deu_x_preferred":[
        "Fenglin"
    ],
    "name:swe_x_preferred":[
        "Fenglin"
    ],
    "name:und_x_variant":[
        "\u67ab\u6797"
    ],
    "wof:name":"Fenglin",
    "wof:placetype":"locality"
},
  "geometry": {"coordinates":[115.18444,28.11917],"type":"Point"}
}