{
  "type": "Feature",
  "properties": {
    "gn:admin1_code":"16.0",
    "gn:asciiname":"Shangrongsheng",
    "gn:country_code":"CN",
    "gn:dem":964,
    "gn:feature_class":"P",
    "gn:feature_code":"PPL",
    "gn:name":"Shangrongsheng",
    "gn:population":0,
    "gn:timezone":"Asia/Shanghai",
    "iso:country":"CN",
    "name:zho_x_preferred":[
        "\u4e0a\u8363\u5347"
    ],
    "wof:name":"Shangrongsheng",
    "wof:placetype":"locality"
},
  "geometry": {"coordinates":[107.117,24.9648],"type":"Point"}
}