{
  "type": "Feature",
  "properties": {
    "gn:admin1_code":"4.0",
    "gn:asciiname":"Tengzhuang",
    "gn:country_code":"CN",
    "gn:dem":2,
    "gn:feature_class":"P",
    "gn:feature_code":"PPL",
    "gn:name":"Tengzhuang",
    "gn:population":0,
    "gn:timezone":"Asia/Shanghai",
    "iso:country":"CN",
    "name:zho_x_preferred":[
        "\u6ed5\u5e84"
    ],
    "wof:name":"Tengzhuang",
    "wof:placetype":"locality"
},
  "geometry": {"coordinates":[118.919,34.3851],"type":"Point"}
}