{
  "type": "Feature",
  "properties": {
    "gn:admin1_code":"5.0",
    "gn:asciiname":"Daliangjia Wobu",
    "gn:country_code":"CN",
    "gn:dem":195,
    "gn:feature_class":"P",
    "gn:feature_code":"PPL",
    "gn:name":"Daliangjia Wobu",
    "gn:population":0,
    "gn:timezone":"Asia/Shanghai",
    "iso:country":"CN",
    "name:zho_x_preferred":[
        "\u5927\u6881\u5bb6\u7a9d\u5821"
    ],
    "wof:name":"Daliangjia Wobu",
    "wof:placetype":"locality"
},
  "geometry": {"coordinates":[125.68076000000001,44.49376],"type":"Point"}
}