{
  "type": "Feature",
  "properties": {
    "gn:admin1_code":"16",
    "gn:asciiname":"Liusha",
    "gn:country_code":"CN",
    "gn:dem":180,
    "gn:feature_class":"P",
    "gn:feature_code":"PPL",
    "gn:name":"Liusha",
    "gn:population":0,
    "gn:timezone":"Asia/Shanghai",
    "iso:country":"CN",
    "name:zho_x_preferred":[
        "\u6d41\u6c99"
    ],
    "wof:name":"Liusha",
    "wof:placetype":"locality"
},
  "geometry": {"coordinates":[110.455,24.5511],"type":"Point"}
}