{
  "type": "Feature",
  "properties": {
    "gn:admin1_code":"19.0",
    "gn:asciiname":"Kangtuncun",
    "gn:country_code":"CN",
    "gn:dem":15,
    "gn:feature_class":"P",
    "gn:feature_code":"PPL",
    "gn:name":"Kangtuncun",
    "gn:population":0,
    "gn:timezone":"Asia/Shanghai",
    "iso:country":"CN",
    "name:und_x_variant":[
        "Kangtun"
    ],
    "name:zho_x_preferred":[
        "\u5eb7\u5c6f\u6751"
    ],
    "wof:name":"Kangtuncun",
    "wof:placetype":"locality"
},
  "geometry": {"coordinates":[122.45699999999999,41.6761],"type":"Point"}
}