{
  "type": "Feature",
  "properties": {
    "gn:admin1_code":"9.0",
    "gn:asciiname":"Gouyu",
    "gn:country_code":"CN",
    "gn:dem":543,
    "gn:feature_class":"P",
    "gn:feature_code":"PPL",
    "gn:name":"Gouyu",
    "gn:population":0,
    "gn:timezone":"Asia/Shanghai",
    "iso:country":"CN",
    "name:zho_x_preferred":[
        "\u57a2\u5cea"
    ],
    "wof:name":"Gouyu",
    "wof:placetype":"locality"
},
  "geometry": {"coordinates":[111.70968000000001,33.97595],"type":"Point"}
}