{
  "type": "Feature",
  "properties": {
    "gn:admin1_code":"7.0",
    "gn:asciiname":"Yuantanguoxi",
    "gn:country_code":"CN",
    "gn:dem":98,
    "gn:feature_class":"P",
    "gn:feature_code":"PPL",
    "gn:name":"Yuantanguoxi",
    "gn:population":0,
    "gn:timezone":"Asia/Shanghai",
    "iso:country":"CN",
    "name:zho_x_preferred":[
        "\u5143\u6f6d\u8fc7\u6eaa"
    ],
    "wof:name":"Yuantanguoxi",
    "wof:placetype":"locality"
},
  "geometry": {"coordinates":[119.54201,27.29075],"type":"Point"}
}