{
  "type": "Feature",
  "properties": {
    "gn:admin1_code":"14.0",
    "gn:asciiname":"Choucun",
    "gn:country_code":"CN",
    "gn:dem":4544,
    "gn:feature_class":"P",
    "gn:feature_code":"PPL",
    "gn:name":"Choucun",
    "gn:population":0,
    "gn:timezone":"Asia/Urumqi",
    "iso:country":"CN",
    "name:zho_x_preferred":[
        "\u7ef8\u6751"
    ],
    "wof:name":"Choucun",
    "wof:placetype":"locality"
},
  "geometry": {"coordinates":[88.07040000000001,28.3423],"type":"Point"}
}