{
  "type": "Feature",
  "properties": {
    "gn:admin1_code":"11.0",
    "gn:asciiname":"Yingfutang",
    "gn:country_code":"CN",
    "gn:dem":52,
    "gn:feature_class":"P",
    "gn:feature_code":"PPL",
    "gn:name":"Yingfutang",
    "gn:population":0,
    "gn:timezone":"Asia/Shanghai",
    "iso:country":"CN",
    "name:zho_x_preferred":[
        "\u5e94\u798f\u5858"
    ],
    "wof:name":"Yingfutang",
    "wof:placetype":"locality"
},
  "geometry": {"coordinates":[112.63509999999999,27.79947],"type":"Point"}
}