{
  "type": "Feature",
  "properties": {
    "gn:admin1_code":"19.0",
    "gn:asciiname":"Huangdi",
    "gn:country_code":"CN",
    "gn:dem":38,
    "gn:feature_class":"P",
    "gn:feature_code":"PPL",
    "gn:name":"Huangdi",
    "gn:population":0,
    "gn:timezone":"Asia/Shanghai",
    "iso:country":"CN",
    "name:und_x_variant":[
        "\u8352\u5730"
    ],
    "name:zho_x_preferred":[
        "\u8352\u5730"
    ],
    "wof:name":"Huangdi",
    "wof:placetype":"locality"
},
  "geometry": {"coordinates":[123.142,42.1031],"type":"Point"}
}