{
  "type": "Feature",
  "properties": {
    "gn:admin1_code":"19.0",
    "gn:asciiname":"Shuiyucun",
    "gn:country_code":"CN",
    "gn:dem":118,
    "gn:feature_class":"P",
    "gn:feature_code":"PPL",
    "gn:name":"Shuiyucun",
    "gn:population":0,
    "gn:timezone":"Asia/Shanghai",
    "iso:country":"CN",
    "name:zho_x_preferred":[
        "\u6c34\u5cea\u6751"
    ],
    "wof:name":"Shuiyucun",
    "wof:placetype":"locality"
},
  "geometry": {"coordinates":[122.20905999999999,40.12625],"type":"Point"}
}