{
  "type": "Feature",
  "properties": {
    "gn:admin1_code":"29.0",
    "gn:asciiname":"Yezhigu",
    "gn:country_code":"CN",
    "gn:dem":2666,
    "gn:feature_class":"P",
    "gn:feature_code":"PPL",
    "gn:name":"Yezhigu",
    "gn:population":0,
    "gn:timezone":"Asia/Shanghai",
    "iso:country":"CN",
    "name:zho_x_preferred":[
        "\u53f6\u652f\u53e4"
    ],
    "wof:name":"Yezhigu",
    "wof:placetype":"locality"
},
  "geometry": {"coordinates":[99.64400000000001,27.2506],"type":"Point"}
}