{
  "type": "Feature",
  "properties": {
    "gn:admin1_code":"11.0",
    "gn:asciiname":"Mojiaqiao",
    "gn:country_code":"CN",
    "gn:dem":243,
    "gn:feature_class":"P",
    "gn:feature_code":"PPL",
    "gn:name":"Mojiaqiao",
    "gn:population":0,
    "gn:timezone":"Asia/Shanghai",
    "iso:country":"CN",
    "name:zho_x_preferred":[
        "Mojiaqiao"
    ],
    "name:zho_x_variant":[
        "\u83ab\u5bb6\u6865"
    ],
    "wof:name":"Mojiaqiao",
    "wof:placetype":"locality"
},
  "geometry": {"coordinates":[111.083,29.5883],"type":"Point"}
}