{
  "type": "Feature",
  "properties": {
    "gn:admin1_code":"15.0",
    "gn:asciiname":"Erfangshan",
    "gn:country_code":"CN",
    "gn:dem":1843,
    "gn:feature_class":"P",
    "gn:feature_code":"PPL",
    "gn:name":"Erfangshan",
    "gn:population":0,
    "gn:timezone":"Asia/Shanghai",
    "iso:country":"CN",
    "name:zho_x_preferred":[
        "\u4e8c\u623f\u5c71"
    ],
    "wof:name":"Erfangshan",
    "wof:placetype":"locality"
},
  "geometry": {"coordinates":[106.09699999999999,34.6329],"type":"Point"}
}