{
  "type": "Feature",
  "properties": {
    "gn:admin1_code":"16.0",
    "gn:asciiname":"Longwaicun",
    "gn:country_code":"CN",
    "gn:dem":799,
    "gn:feature_class":"P",
    "gn:feature_code":"PPL",
    "gn:name":"Longwaicun",
    "gn:population":0,
    "gn:timezone":"Asia/Shanghai",
    "iso:country":"CN",
    "name:zho_x_preferred":[
        "\u9f99\u5916\u6751"
    ],
    "wof:name":"Longwaicun",
    "wof:placetype":"locality"
},
  "geometry": {"coordinates":[106.358,23.7765],"type":"Point"}
}