{
  "type": "Feature",
  "properties": {
    "gn:admin1_code":"29",
    "gn:asciiname":"Xinfacun",
    "gn:country_code":"CN",
    "gn:dem":1197,
    "gn:feature_class":"P",
    "gn:feature_code":"PPL",
    "gn:name":"Xinfacun",
    "gn:population":0,
    "gn:timezone":"Asia/Shanghai",
    "iso:country":"CN",
    "name:zho_x_preferred":[
        "\u4fe1\u6cd5\u6751"
    ],
    "wof:name":"Xinfacun",
    "wof:placetype":"locality"
},
  "geometry": {"coordinates":[102.01187,24.36201],"type":"Point"}
}