{
  "type": "Feature",
  "properties": {
    "gn:admin1_code":"18",
    "gn:asciiname":"Wengtiaowan",
    "gn:country_code":"CN",
    "gn:dem":992,
    "gn:feature_class":"P",
    "gn:feature_code":"PPL",
    "gn:name":"Wengtiaowan",
    "gn:population":0,
    "gn:timezone":"Asia/Shanghai",
    "iso:country":"CN",
    "name:zho_x_preferred":[
        "\u7fc1\u82d5\u6e7e"
    ],
    "wof:name":"Wengtiaowan",
    "wof:placetype":"locality"
},
  "geometry": {"coordinates":[106.741,25.6612],"type":"Point"}
}