{
  "type": "Feature",
  "properties": {
    "gn:admin1_code":"26",
    "gn:asciiname":"Maotuanhulun",
    "gn:country_code":"CN",
    "gn:dem":1353,
    "gn:feature_class":"P",
    "gn:feature_code":"PPL",
    "gn:name":"Maotuanhulun",
    "gn:population":0,
    "gn:timezone":"Asia/Shanghai",
    "iso:country":"CN",
    "name:und_x_variant":[
        "Mao-t\u2019u-hu-lun",
        "Maotuanhulun"
    ],
    "name:zho_x_preferred":[
        "\u6bdb\u56e2\u56eb\u56f5"
    ],
    "wof:name":"Maotuanhulun",
    "wof:placetype":"locality"
},
  "geometry": {"coordinates":[108.5194,37.60837],"type":"Point"}
}