{
  "type": "Feature",
  "properties": {
    "gn:admin1_code":"5.0",
    "gn:asciiname":"Dong'an",
    "gn:country_code":"CN",
    "gn:dem":604,
    "gn:feature_class":"P",
    "gn:feature_code":"PPL",
    "gn:name":"Dong\u2019an",
    "gn:population":0,
    "gn:timezone":"Asia/Shanghai",
    "iso:country":"CN",
    "name:und_x_variant":[
        "Dong\u2019an",
        "\u4e1c\u5b89"
    ],
    "wof:name":"Dong'an",
    "wof:placetype":"locality"
},
  "geometry": {"coordinates":[128.19406000000001,42.88513],"type":"Point"}
}