{
  "type": "Feature",
  "properties": {
    "gn:admin1_code":"12.0",
    "gn:asciiname":"Pengjiagang",
    "gn:country_code":"CN",
    "gn:dem":66,
    "gn:feature_class":"P",
    "gn:feature_code":"PPL",
    "gn:name":"Pengjiagang",
    "gn:population":0,
    "gn:timezone":"Asia/Shanghai",
    "iso:country":"CN",
    "name:zho_x_preferred":[
        "Pengjiagang"
    ],
    "name:zho_x_variant":[
        "\u5f6d\u5bb6\u5c97"
    ],
    "wof:name":"Pengjiagang",
    "wof:placetype":"locality"
},
  "geometry": {"coordinates":[111.92789,30.79704000000001],"type":"Point"}
}