{
  "type": "Feature",
  "properties": {
    "gn:admin1_code":"26.0",
    "gn:asciiname":"Qiangzhuangcun",
    "gn:country_code":"CN",
    "gn:dem":1575,
    "gn:feature_class":"P",
    "gn:feature_code":"PPL",
    "gn:name":"Qiangzhuangcun",
    "gn:population":0,
    "gn:timezone":"Asia/Shanghai",
    "iso:country":"CN",
    "name:zho_x_preferred":[
        "\u5f3a\u5e84\u6751"
    ],
    "wof:name":"Qiangzhuangcun",
    "wof:placetype":"locality"
},
  "geometry": {"coordinates":[107.64667,37.44072],"type":"Point"}
}