{
  "type": "Feature",
  "properties": {
    "gn:admin1_code":"12.0",
    "gn:asciiname":"Lujia Taizi",
    "gn:country_code":"CN",
    "gn:dem":643,
    "gn:feature_class":"P",
    "gn:feature_code":"PPL",
    "gn:name":"L\u00fcjia Taizi",
    "gn:population":0,
    "gn:timezone":"Asia/Shanghai",
    "iso:country":"CN",
    "name:und_x_variant":[
        "L\u00fcjia Taizi"
    ],
    "name:zho_x_preferred":[
        "\u5415\u5bb6\u53f0\u5b50"
    ],
    "wof:name":"Lujia Taizi",
    "wof:placetype":"locality"
},
  "geometry": {"coordinates":[110.89085,33.05058],"type":"Point"}
}