{
  "type": "Feature",
  "properties": {
    "gn:admin1_code":"4.0",
    "gn:asciiname":"Xinhua",
    "gn:country_code":"CN",
    "gn:dem":1,
    "gn:feature_class":"P",
    "gn:feature_code":"PPL",
    "gn:name":"Xinhua",
    "gn:population":0,
    "gn:timezone":"Asia/Shanghai",
    "iso:country":"CN",
    "name:zho_x_preferred":[
        "Xinhua"
    ],
    "name:zho_x_variant":[
        "\u65b0\u534e"
    ],
    "wof:name":"Xinhua",
    "wof:placetype":"locality"
},
  "geometry": {"coordinates":[119.94889000000001,33.48573],"type":"Point"}
}