{
  "type": "Feature",
  "properties": {
    "gn:admin1_code":"32.0",
    "gn:asciiname":"Shenshan",
    "gn:country_code":"CN",
    "gn:dem":2758,
    "gn:feature_class":"P",
    "gn:feature_code":"PPL",
    "gn:name":"Shenshan",
    "gn:population":0,
    "gn:timezone":"Asia/Shanghai",
    "iso:country":"CN",
    "name:zho_x_preferred":[
        "\u795e\u5c71"
    ],
    "wof:name":"Shenshan",
    "wof:placetype":"locality"
},
  "geometry": {"coordinates":[102.02800000000001,31.9362],"type":"Point"}
}