{
  "type": "Feature",
  "properties": {
    "gn:admin1_code":"12.0",
    "gn:asciiname":"Sanyangwan",
    "gn:country_code":"CN",
    "gn:dem":22,
    "gn:feature_class":"P",
    "gn:feature_code":"PPL",
    "gn:name":"Sanyangwan",
    "gn:population":0,
    "gn:timezone":"Asia/Shanghai",
    "iso:country":"CN",
    "name:und_x_variant":[
        "\u4e09\u6768\u5846"
    ],
    "wof:name":"Sanyangwan",
    "wof:placetype":"locality"
},
  "geometry": {"coordinates":[114.68683,30.79172],"type":"Point"}
}