{
  "type": "Feature",
  "properties": {
    "gn:admin1_code":"12.0",
    "gn:asciiname":"Xinji",
    "gn:country_code":"CN",
    "gn:dem":130,
    "gn:feature_class":"P",
    "gn:feature_code":"PPL",
    "gn:name":"Xinji",
    "gn:population":0,
    "gn:timezone":"Asia/Shanghai",
    "iso:country":"CN",
    "name:und_x_variant":[
        "Hsin-chi",
        "Xinji",
        "\u65b0\u96c6"
    ],
    "wof:name":"Xinji",
    "wof:placetype":"locality"
},
  "geometry": {"coordinates":[112.10250000000001,31.56374000000001],"type":"Point"}
}