{
  "type": "Feature",
  "properties": {
    "gn:admin1_code":"32.0",
    "gn:asciiname":"Benzirong",
    "gn:country_code":"CN",
    "gn:dem":3134,
    "gn:feature_class":"P",
    "gn:feature_code":"PPL",
    "gn:name":"Benzirong",
    "gn:population":0,
    "gn:timezone":"Asia/Shanghai",
    "iso:country":"CN",
    "name:zho_x_preferred":[
        "\u672c\u5b5c\u7ed2"
    ],
    "wof:name":"Benzirong",
    "wof:placetype":"locality"
},
  "geometry": {"coordinates":[101.13500000000001,29.7629],"type":"Point"}
}