{
  "type": "Feature",
  "properties": {
    "gn:admin1_code":"1.0",
    "gn:asciiname":"Xiaoyingcun",
    "gn:country_code":"CN",
    "gn:dem":25,
    "gn:feature_class":"P",
    "gn:feature_code":"PPL",
    "gn:name":"Xiaoyingcun",
    "gn:population":0,
    "gn:timezone":"Asia/Shanghai",
    "iso:country":"CN",
    "name:zho_x_preferred":[
        "\u5c0f\u90e2\u6751"
    ],
    "wof:name":"Xiaoyingcun",
    "wof:placetype":"locality"
},
  "geometry": {"coordinates":[116.81988,32.72492],"type":"Point"}
}