{
  "type": "Feature",
  "properties": {
    "gn:admin1_code":"32.0",
    "gn:asciiname":"Daguaping",
    "gn:country_code":"CN",
    "gn:dem":1996,
    "gn:feature_class":"P",
    "gn:feature_code":"PPL",
    "gn:name":"Daguaping",
    "gn:population":0,
    "gn:timezone":"Asia/Shanghai",
    "iso:country":"CN",
    "name:zho_x_preferred":[
        "\u5927\u74dc\u576a"
    ],
    "wof:name":"Daguaping",
    "wof:placetype":"locality"
},
  "geometry": {"coordinates":[102.55500000000001,28.9026],"type":"Point"}
}