{
  "type": "Feature",
  "properties": {
    "gn:admin1_code":"32.0",
    "gn:asciiname":"Duanchong",
    "gn:country_code":"CN",
    "gn:dem":375,
    "gn:feature_class":"P",
    "gn:feature_code":"PPL",
    "gn:name":"Duanchong",
    "gn:population":0,
    "gn:timezone":"Asia/Shanghai",
    "iso:country":"CN",
    "name:zho_x_preferred":[
        "\u6bb5\u51b2"
    ],
    "wof:name":"Duanchong",
    "wof:placetype":"locality"
},
  "geometry": {"coordinates":[105.11,29.6784],"type":"Point"}
}