{
  "type": "Feature",
  "properties": {
    "gn:admin1_code":"25.0",
    "gn:asciiname":"Ma'ecun",
    "gn:country_code":"CN",
    "gn:dem":38,
    "gn:feature_class":"P",
    "gn:feature_code":"PPL",
    "gn:name":"Ma\u2019ecun",
    "gn:population":0,
    "gn:timezone":"Asia/Shanghai",
    "iso:country":"CN",
    "name:und_x_variant":[
        "Ma\u2019ecun"
    ],
    "name:zho_x_preferred":[
        "\u9a6c\u5a25\u6751"
    ],
    "wof:name":"Ma'ecun",
    "wof:placetype":"locality"
},
  "geometry": {"coordinates":[116.50163999999999,34.91326],"type":"Point"}
}