{
  "type": "Feature",
  "properties": {
    "gn:admin1_code":"29.0",
    "gn:asciiname":"Shangmuguazhai",
    "gn:country_code":"CN",
    "gn:dem":1837,
    "gn:feature_class":"P",
    "gn:feature_code":"PPL",
    "gn:name":"Shangmuguazhai",
    "gn:population":0,
    "gn:timezone":"Asia/Shanghai",
    "iso:country":"CN",
    "name:zho_x_preferred":[
        "\u4e0a\u6728\u74dc\u5be8"
    ],
    "wof:name":"Shangmuguazhai",
    "wof:placetype":"locality"
},
  "geometry": {"coordinates":[99.2585,24.0539],"type":"Point"}
}