{
  "type": "Feature",
  "properties": {
    "gn:admin1_code":"25.0",
    "gn:asciiname":"Wujiagoucun",
    "gn:country_code":"CN",
    "gn:dem":42,
    "gn:feature_class":"P",
    "gn:feature_code":"PPL",
    "gn:name":"Wujiagoucun",
    "gn:population":0,
    "gn:timezone":"Asia/Shanghai",
    "iso:country":"CN",
    "name:zho_x_preferred":[
        "\u5434\u5bb6\u6c9f\u6751"
    ],
    "wof:name":"Wujiagoucun",
    "wof:placetype":"locality"
},
  "geometry": {"coordinates":[121.58777000000001,36.94261],"type":"Point"}
}