{
  "type": "Feature",
  "properties": {
    "gn:admin1_code":"10.0",
    "gn:asciiname":"Jianshao",
    "gn:country_code":"CN",
    "gn:dem":381,
    "gn:feature_class":"P",
    "gn:feature_code":"PPL",
    "gn:name":"Jianshao",
    "gn:population":0,
    "gn:timezone":"Asia/Shanghai",
    "iso:country":"CN",
    "name:zho_x_preferred":[
        "\u5c16\u7a0d"
    ],
    "wof:name":"Jianshao",
    "wof:placetype":"locality"
},
  "geometry": {"coordinates":[114.69589999999999,39.00289],"type":"Point"}
}