{
  "type": "Feature",
  "properties": {
    "gn:admin1_code":"8.0",
    "gn:asciiname":"Debaocun",
    "gn:country_code":"CN",
    "gn:dem":263,
    "gn:feature_class":"P",
    "gn:feature_code":"PPL",
    "gn:name":"Debaocun",
    "gn:population":0,
    "gn:timezone":"Asia/Shanghai",
    "iso:country":"CN",
    "name:zho_x_preferred":[
        "\u5fb7\u5b9d\u6751"
    ],
    "wof:name":"Debaocun",
    "wof:placetype":"locality"
},
  "geometry": {"coordinates":[125.25313,48.55843],"type":"Point"}
}