{
  "type": "Feature",
  "properties": {
    "gn:admin1_code":"4.0",
    "gn:asciiname":"Touzao",
    "gn:country_code":"CN",
    "gn:dem":3,
    "gn:feature_class":"P",
    "gn:feature_code":"PPL",
    "gn:name":"Touzao",
    "gn:population":0,
    "gn:timezone":"Asia/Shanghai",
    "iso:country":"CN",
    "name:zho_x_preferred":[
        "\u5934\u7076"
    ],
    "name:zho_x_variant":[
        "\u5934\u7076\u9547"
    ],
    "wof:name":"Touzao",
    "wof:placetype":"locality"
},
  "geometry": {"coordinates":[120.1344,33.43789],"type":"Point"}
}