{
  "type": "Feature",
  "properties": {
    "gn:admin1_code":"14.0",
    "gn:asciiname":"Qiayiquguo",
    "gn:country_code":"CN",
    "gn:dem":4632,
    "gn:feature_class":"P",
    "gn:feature_code":"PPL",
    "gn:name":"Qiayiquguo",
    "gn:population":0,
    "gn:timezone":"Asia/Urumqi",
    "iso:country":"CN",
    "name:zho_x_preferred":[
        "\u6070\u4f9d\u66f2\u679c"
    ],
    "wof:name":"Qiayiquguo",
    "wof:placetype":"locality"
},
  "geometry": {"coordinates":[91.78527,30.32406],"type":"Point"}
}