{
  "type": "Feature",
  "properties": {
    "gn:admin1_code":"25",
    "gn:asciiname":"Xigaoping",
    "gn:country_code":"CN",
    "gn:dem":155,
    "gn:feature_class":"P",
    "gn:feature_code":"PPL",
    "gn:name":"Xigaoping",
    "gn:population":0,
    "gn:timezone":"Asia/Shanghai",
    "iso:country":"CN",
    "name:zho_x_preferred":[
        "\u897f\u9ad8\u5e73"
    ],
    "wof:name":"Xigaoping",
    "wof:placetype":"locality"
},
  "geometry": {"coordinates":[117.44499999999999,35.8859],"type":"Point"}
}