{
  "type": "Feature",
  "properties": {
    "gn:admin1_code":"15.0",
    "gn:asciiname":"Zhaojiayuan",
    "gn:country_code":"CN",
    "gn:dem":1639,
    "gn:feature_class":"P",
    "gn:feature_code":"PPL",
    "gn:name":"Zhaojiayuan",
    "gn:population":0,
    "gn:timezone":"Asia/Shanghai",
    "iso:country":"CN",
    "name:und_x_variant":[
        "\u8d75\u5bb6\u586c"
    ],
    "wof:name":"Zhaojiayuan",
    "wof:placetype":"locality"
},
  "geometry": {"coordinates":[106.99609,36.84896],"type":"Point"}
}