{
  "type": "Feature",
  "properties": {
    "gn:admin1_code":"29.0",
    "gn:asciiname":"Nalouzhai",
    "gn:country_code":"CN",
    "gn:dem":1312,
    "gn:feature_class":"P",
    "gn:feature_code":"PPL",
    "gn:name":"Nalouzhai",
    "gn:population":0,
    "gn:timezone":"Asia/Shanghai",
    "iso:country":"CN",
    "name:zho_x_preferred":[
        "\u7eb3\u697c\u5be8"
    ],
    "wof:name":"Nalouzhai",
    "wof:placetype":"locality"
},
  "geometry": {"coordinates":[103.009,23.6538],"type":"Point"}
}