{
  "type": "Feature",
  "properties": {
    "gn:admin1_code":"11.0",
    "gn:asciiname":"Tianpingshan",
    "gn:country_code":"CN",
    "gn:dem":855,
    "gn:feature_class":"P",
    "gn:feature_code":"PPL",
    "gn:name":"Tianpingshan",
    "gn:population":0,
    "gn:timezone":"Asia/Shanghai",
    "iso:country":"CN",
    "name:zho_x_preferred":[
        "\u7530\u576a\u5c71"
    ],
    "wof:name":"Tianpingshan",
    "wof:placetype":"locality"
},
  "geometry": {"coordinates":[113.82271,25.63282],"type":"Point"}
}