{
  "type": "Feature",
  "properties": {
    "gn:admin1_code":"30",
    "gn:asciiname":"Datetang",
    "gn:country_code":"CN",
    "gn:dem":29,
    "gn:feature_class":"P",
    "gn:feature_code":"PPL",
    "gn:name":"Datetang",
    "gn:population":0,
    "gn:timezone":"Asia/Urumqi",
    "iso:country":"CN",
    "name:und_x_variant":[
        "\u6253\u7279\u5858",
        "Datetang"
    ],
    "wof:name":"Datetang",
    "wof:placetype":"locality"
},
  "geometry": {"coordinates":[110.01324,21.38525],"type":"Point"}
}