{
  "type": "Feature",
  "properties": {
    "gn:admin1_code":"18.0",
    "gn:asciiname":"Songhe",
    "gn:country_code":"CN",
    "gn:dem":1747,
    "gn:feature_class":"P",
    "gn:feature_code":"PPL",
    "gn:name":"Songhe",
    "gn:population":0,
    "gn:timezone":"Asia/Shanghai",
    "iso:country":"CN",
    "wof:name":"Songhe",
    "wof:placetype":"locality"
},
  "geometry": {"coordinates":[104.61667,26.03333],"type":"Point"}
}