{
  "type": "Feature",
  "properties": {
    "gn:admin1_code":"07",
    "gn:asciiname":"Xiacuodi",
    "gn:country_code":"CN",
    "gn:dem":387,
    "gn:feature_class":"P",
    "gn:feature_code":"PPL",
    "gn:name":"Xiacuodi",
    "gn:population":0,
    "gn:timezone":"Asia/Shanghai",
    "iso:country":"CN",
    "name:zho_x_preferred":[
        "\u4e0b\u539d\u5730"
    ],
    "wof:name":"Xiacuodi",
    "wof:placetype":"locality"
},
  "geometry": {"coordinates":[117.84148,25.88522],"type":"Point"}
}