{
  "type": "Feature",
  "properties": {
    "gn:admin1_code":"32.0",
    "gn:asciiname":"Pujiawan",
    "gn:country_code":"CN",
    "gn:dem":493,
    "gn:feature_class":"P",
    "gn:feature_code":"PPL",
    "gn:name":"Pujiawan",
    "gn:population":0,
    "gn:timezone":"Asia/Shanghai",
    "iso:country":"CN",
    "name:zho_x_preferred":[
        "\u84b2\u5bb6\u6e7e"
    ],
    "wof:name":"Pujiawan",
    "wof:placetype":"locality"
},
  "geometry": {"coordinates":[104.82599999999999,31.3279],"type":"Point"}
}