{
  "type": "Feature",
  "properties": {
    "gn:admin1_code":"7.0",
    "gn:asciiname":"Cunli",
    "gn:country_code":"CN",
    "gn:dem":477,
    "gn:feature_class":"P",
    "gn:feature_code":"PPL",
    "gn:name":"Cunli",
    "gn:population":0,
    "gn:timezone":"Asia/Shanghai",
    "iso:country":"CN",
    "name:und_x_variant":[
        "\u6751\u91cc"
    ],
    "name:zho_x_preferred":[
        "\u6751\u91cc"
    ],
    "wof:name":"Cunli",
    "wof:placetype":"locality"
},
  "geometry": {"coordinates":[116.68998999999999,26.4351],"type":"Point"}
}