{
  "type": "Feature",
  "properties": {
    "gn:admin1_code":"26.0",
    "gn:asciiname":"Wanjiachengcun",
    "gn:country_code":"CN",
    "gn:dem":1319,
    "gn:feature_class":"P",
    "gn:feature_code":"PPL",
    "gn:name":"Wanjiachengcun",
    "gn:population":0,
    "gn:timezone":"Asia/Shanghai",
    "iso:country":"CN",
    "name:zho_x_preferred":[
        "\u4e07\u5bb6\u57ce\u6751"
    ],
    "wof:name":"Wanjiachengcun",
    "wof:placetype":"locality"
},
  "geometry": {"coordinates":[107.43163,34.85234000000001],"type":"Point"}
}