{
  "type": "Feature",
  "properties": {
    "gn:admin1_code":"26.0",
    "gn:asciiname":"Liuxingzhuang",
    "gn:country_code":"CN",
    "gn:dem":1637,
    "gn:feature_class":"P",
    "gn:feature_code":"PPL",
    "gn:name":"Liuxingzhuang",
    "gn:population":0,
    "gn:timezone":"Asia/Shanghai",
    "iso:country":"CN",
    "name:zho_x_preferred":[
        "\u5218\u5174\u5e84"
    ],
    "wof:name":"Liuxingzhuang",
    "wof:placetype":"locality"
},
  "geometry": {"coordinates":[108.62214,37.51122],"type":"Point"}
}