{
  "type": "Feature",
  "properties": {
    "gn:admin1_code":"18",
    "gn:asciiname":"Guorao",
    "gn:country_code":"CN",
    "gn:dem":930,
    "gn:feature_class":"P",
    "gn:feature_code":"PPL",
    "gn:name":"Guorao",
    "gn:population":0,
    "gn:timezone":"Asia/Shanghai",
    "iso:country":"CN",
    "name:zho_x_preferred":[
        "\u8fc7\u7ed5"
    ],
    "wof:name":"Guorao",
    "wof:placetype":"locality"
},
  "geometry": {"coordinates":[106.536,25.6266],"type":"Point"}
}