{
  "type": "Feature",
  "properties": {
    "gn:admin1_code":"25",
    "gn:asciiname":"Zhonghonglin",
    "gn:country_code":"CN",
    "gn:dem":62,
    "gn:feature_class":"P",
    "gn:feature_code":"PPL",
    "gn:name":"Zhonghonglin",
    "gn:population":0,
    "gn:timezone":"Asia/Shanghai",
    "iso:country":"CN",
    "name:zho_x_preferred":[
        "\u4e2d\u6d2a\u6797"
    ],
    "wof:name":"Zhonghonglin",
    "wof:placetype":"locality"
},
  "geometry": {"coordinates":[117.28400000000001,34.9293],"type":"Point"}
}