{
  "type": "Feature",
  "properties": {
    "gn:admin1_code":"3.0",
    "gn:asciiname":"Dunshang Qianjia",
    "gn:country_code":"CN",
    "gn:dem":72,
    "gn:feature_class":"P",
    "gn:feature_code":"PPL",
    "gn:name":"Dunshang Qianjia",
    "gn:population":0,
    "gn:timezone":"Asia/Shanghai",
    "iso:country":"CN",
    "name:und_x_variant":[
        "\u58a9\u4e0a\u94b1\u5bb6"
    ],
    "wof:name":"Dunshang Qianjia",
    "wof:placetype":"locality"
},
  "geometry": {"coordinates":[116.96852,28.10775],"type":"Point"}
}