{
  "type": "Feature",
  "properties": {
    "gn:admin1_code":"14.0",
    "gn:asciiname":"Tongdecun",
    "gn:country_code":"CN",
    "gn:dem":3732,
    "gn:feature_class":"P",
    "gn:feature_code":"PPL",
    "gn:name":"Tongdecun",
    "gn:population":0,
    "gn:timezone":"Asia/Urumqi",
    "iso:country":"CN",
    "name:zho_x_preferred":[
        "\u901a\u5fb7\u6751"
    ],
    "wof:name":"Tongdecun",
    "wof:placetype":"locality"
},
  "geometry": {"coordinates":[96.43247,30.17077],"type":"Point"}
}