{
  "type": "Feature",
  "properties": {
    "gn:admin1_code":"16",
    "gn:asciiname":"Dielu",
    "gn:country_code":"CN",
    "gn:dem":145,
    "gn:feature_class":"P",
    "gn:feature_code":"PPL",
    "gn:name":"Dielu",
    "gn:population":0,
    "gn:timezone":"Asia/Shanghai",
    "iso:country":"CN",
    "name:zho_x_preferred":[
        "\u53e0\u7984"
    ],
    "wof:name":"Dielu",
    "wof:placetype":"locality"
},
  "geometry": {"coordinates":[111.20999999999999,26.0539],"type":"Point"}
}