{
  "type": "Feature",
  "properties": {
    "gn:admin1_code":"29.0",
    "gn:asciiname":"Jigao Liangzi",
    "gn:country_code":"CN",
    "gn:dem":2050,
    "gn:feature_class":"P",
    "gn:feature_code":"PPL",
    "gn:name":"Jigao Liangzi",
    "gn:population":0,
    "gn:timezone":"Asia/Shanghai",
    "iso:country":"CN",
    "name:zho_x_preferred":[
        "\u9e21\u9ad8\u6881\u5b50"
    ],
    "wof:name":"Jigao Liangzi",
    "wof:placetype":"locality"
},
  "geometry": {"coordinates":[101.27,26.089],"type":"Point"}
}