{
  "type": "Feature",
  "properties": {
    "gn:admin1_code":"2.0",
    "gn:asciiname":"Guanqiao",
    "gn:country_code":"CN",
    "gn:dem":125,
    "gn:feature_class":"P",
    "gn:feature_code":"PPL",
    "gn:name":"Guanqiao",
    "gn:population":0,
    "gn:timezone":"Asia/Shanghai",
    "iso:country":"CN",
    "name:ceb_x_preferred":[
        "Guanqiao"
    ],
    "name:deu_x_preferred":[
        "Guanqiao"
    ],
    "name:swe_x_preferred":[
        "Guanqiao"
    ],
    "name:zho_x_preferred":[
        "\u5b98\u6865"
    ],
    "wof:name":"Guanqiao",
    "wof:placetype":"locality"
},
  "geometry": {"coordinates":[120.25933000000001,29.10837],"type":"Point"}
}