{
  "type": "Feature",
  "properties": {
    "gn:admin1_code":"14.0",
    "gn:asciiname":"Bajianpu",
    "gn:country_code":"CN",
    "gn:dem":4112,
    "gn:feature_class":"P",
    "gn:feature_code":"PPL",
    "gn:name":"Bajianpu",
    "gn:population":0,
    "gn:timezone":"Asia/Urumqi",
    "iso:country":"CN",
    "name:zho_x_preferred":[
        "\u5df4\u5c16\u666e"
    ],
    "wof:name":"Bajianpu",
    "wof:placetype":"locality"
},
  "geometry": {"coordinates":[95.05087,31.66162000000001],"type":"Point"}
}