{
  "type": "Feature",
  "properties": {
    "gn:admin1_code":"12.0",
    "gn:asciiname":"Ranfangzhuang",
    "gn:country_code":"CN",
    "gn:dem":213,
    "gn:feature_class":"P",
    "gn:feature_code":"PPL",
    "gn:name":"Ranfangzhuang",
    "gn:population":0,
    "gn:timezone":"Asia/Shanghai",
    "iso:country":"CN",
    "name:zho_x_preferred":[
        "\u67d3\u574a\u5e84"
    ],
    "wof:name":"Ranfangzhuang",
    "wof:placetype":"locality"
},
  "geometry": {"coordinates":[112.81319999999999,32.35013],"type":"Point"}
}