{
  "type": "Feature",
  "properties": {
    "gn:admin1_code":"10.0",
    "gn:asciiname":"Xisizhuang",
    "gn:country_code":"CN",
    "gn:dem":23,
    "gn:feature_class":"P",
    "gn:feature_code":"PPL",
    "gn:name":"Xisizhuang",
    "gn:population":0,
    "gn:timezone":"Asia/Shanghai",
    "iso:country":"CN",
    "name:zho_x_preferred":[
        "\u897f\u56db\u5e84"
    ],
    "wof:name":"Xisizhuang",
    "wof:placetype":"locality"
},
  "geometry": {"coordinates":[115.83195000000001,39.11808],"type":"Point"}
}