{
  "type": "Feature",
  "properties": {
    "gn:admin1_code":"12.0",
    "gn:asciiname":"Lumaowan",
    "gn:country_code":"CN",
    "gn:dem":658,
    "gn:feature_class":"P",
    "gn:feature_code":"PPL",
    "gn:name":"Lumaowan",
    "gn:population":0,
    "gn:timezone":"Asia/Shanghai",
    "iso:country":"CN",
    "name:zho_x_preferred":[
        "Lumaowan"
    ],
    "name:zho_x_variant":[
        "\u82a6\u8305\u6e7e"
    ],
    "wof:name":"Lumaowan",
    "wof:placetype":"locality"
},
  "geometry": {"coordinates":[109.64633000000001,29.81524000000001],"type":"Point"}
}