{
  "type": "Feature",
  "properties": {
    "gn:admin1_code":"29.0",
    "gn:asciiname":"Wude Laozhai",
    "gn:country_code":"CN",
    "gn:dem":2002,
    "gn:feature_class":"P",
    "gn:feature_code":"PPL",
    "gn:name":"Wude Laozhai",
    "gn:population":0,
    "gn:timezone":"Asia/Shanghai",
    "iso:country":"CN",
    "name:zho_x_preferred":[
        "\u65e0\u7684\u8001\u5be8"
    ],
    "wof:name":"Wude Laozhai",
    "wof:placetype":"locality"
},
  "geometry": {"coordinates":[99.9147,22.8827],"type":"Point"}
}