{
  "type": "Feature",
  "properties": {
    "gn:admin1_code":"32.0",
    "gn:asciiname":"Yonghong",
    "gn:country_code":"CN",
    "gn:dem":1199,
    "gn:feature_class":"P",
    "gn:feature_code":"PPL",
    "gn:name":"Yonghong",
    "gn:population":0,
    "gn:timezone":"Asia/Shanghai",
    "iso:country":"CN",
    "name:zho_x_preferred":[
        "\u6c38\u7ea2"
    ],
    "wof:name":"Yonghong",
    "wof:placetype":"locality"
},
  "geometry": {"coordinates":[102.244,27.1292],"type":"Point"}
}