{
  "type": "Feature",
  "properties": {
    "gn:admin1_code":"5.0",
    "gn:asciiname":"Dawajie",
    "gn:country_code":"CN",
    "gn:dem":195,
    "gn:feature_class":"P",
    "gn:feature_code":"PPL",
    "gn:name":"Dawajie",
    "gn:population":0,
    "gn:timezone":"Asia/Shanghai",
    "iso:country":"CN",
    "name:zho_x_preferred":[
        "\u5927\u6d3c\u8857"
    ],
    "wof:name":"Dawajie",
    "wof:placetype":"locality"
},
  "geometry": {"coordinates":[124.92616,43.85081],"type":"Point"}
}