{
  "type": "Feature",
  "properties": {
    "gn:admin1_code":"9.0",
    "gn:asciiname":"Xiyangjia",
    "gn:country_code":"CN",
    "gn:dem":367,
    "gn:feature_class":"P",
    "gn:feature_code":"PPL",
    "gn:name":"Xiyangjia",
    "gn:population":0,
    "gn:timezone":"Asia/Shanghai",
    "iso:country":"CN",
    "name:zho_x_preferred":[
        "\u897f\u6768\u5bb6"
    ],
    "wof:name":"Xiyangjia",
    "wof:placetype":"locality"
},
  "geometry": {"coordinates":[110.3652,34.56916],"type":"Point"}
}