{
  "type": "Feature",
  "properties": {
    "gn:admin1_code":"14.0",
    "gn:asciiname":"Daxue",
    "gn:country_code":"CN",
    "gn:dem":3544,
    "gn:feature_class":"P",
    "gn:feature_code":"PPL",
    "gn:name":"Daxue",
    "gn:population":0,
    "gn:timezone":"Asia/Urumqi",
    "iso:country":"CN",
    "name:deu_x_preferred":[
        "Daxue"
    ],
    "name:fra_x_preferred":[
        "Daxue"
    ],
    "name:swe_x_preferred":[
        "Daxue"
    ],
    "name:zho_x_preferred":[
        "\u8fbe\u96ea"
    ],
    "wof:name":"Daxue",
    "wof:placetype":"locality"
},
  "geometry": {"coordinates":[96.42281,30.48061],"type":"Point"}
}