{
  "type": "Feature",
  "properties": {
    "gn:admin1_code":"3.0",
    "gn:asciiname":"Shishan",
    "gn:country_code":"CN",
    "gn:dem":109,
    "gn:feature_class":"P",
    "gn:feature_code":"PPL",
    "gn:name":"Shishan",
    "gn:population":0,
    "gn:timezone":"Asia/Shanghai",
    "iso:country":"CN",
    "name:und_x_variant":[
        "\u65f6\u5c71"
    ],
    "wof:name":"Shishan",
    "wof:placetype":"locality"
},
  "geometry": {"coordinates":[115.48045,27.52089],"type":"Point"}
}