{
  "type": "Feature",
  "properties": {
    "gn:admin1_code":"5.0",
    "gn:asciiname":"Laoshili",
    "gn:country_code":"CN",
    "gn:dem":243,
    "gn:feature_class":"P",
    "gn:feature_code":"PPL",
    "gn:name":"Laoshili",
    "gn:population":0,
    "gn:timezone":"Asia/Shanghai",
    "iso:country":"CN",
    "name:zho_x_preferred":[
        "\u8001\u5b9e\u674e"
    ],
    "wof:name":"Laoshili",
    "wof:placetype":"locality"
},
  "geometry": {"coordinates":[126.08308,44.18021],"type":"Point"}
}