{
  "type": "Feature",
  "properties": {
    "gn:admin1_code":"24",
    "gn:asciiname":"Leishang",
    "gn:country_code":"CN",
    "gn:dem":968,
    "gn:feature_class":"P",
    "gn:feature_code":"PPL",
    "gn:name":"Leishang",
    "gn:population":0,
    "gn:timezone":"Asia/Shanghai",
    "iso:country":"CN",
    "name:und_x_variant":[
        "Lei-shang-ts\u2019un",
        "Leishang"
    ],
    "name:zho_x_preferred":[
        "\u78ca\u4e0a"
    ],
    "wof:name":"Leishang",
    "wof:placetype":"locality"
},
  "geometry": {"coordinates":[111.51788000000001,36.47246],"type":"Point"}
}