{
  "type": "Feature",
  "properties": {
    "gn:admin1_code":"25",
    "gn:asciiname":"Henangoutou",
    "gn:country_code":"CN",
    "gn:dem":115,
    "gn:feature_class":"P",
    "gn:feature_code":"PPL",
    "gn:name":"Henangoutou",
    "gn:population":0,
    "gn:timezone":"Asia/Shanghai",
    "iso:country":"CN",
    "name:zho_x_preferred":[
        "\u6cb3\u5357\u6c9f\u5934"
    ],
    "wof:name":"Henangoutou",
    "wof:placetype":"locality"
},
  "geometry": {"coordinates":[118.599,35.5771],"type":"Point"}
}