{
  "type": "Feature",
  "properties": {
    "gn:admin1_code":"7.0",
    "gn:asciiname":"Xiaoshuaikeng",
    "gn:country_code":"CN",
    "gn:dem":689,
    "gn:feature_class":"P",
    "gn:feature_code":"PPL",
    "gn:name":"Xiaoshuaikeng",
    "gn:population":0,
    "gn:timezone":"Asia/Shanghai",
    "iso:country":"CN",
    "name:zho_x_preferred":[
        "\u5c0f\u7529\u5751"
    ],
    "wof:name":"Xiaoshuaikeng",
    "wof:placetype":"locality"
},
  "geometry": {"coordinates":[118.35008999999999,25.98925],"type":"Point"}
}