{
  "type": "Feature",
  "properties": {
    "gn:admin1_code":"9.0",
    "gn:asciiname":"Xiapigang",
    "gn:country_code":"CN",
    "gn:dem":38,
    "gn:feature_class":"P",
    "gn:feature_code":"PPL",
    "gn:name":"Xiapigang",
    "gn:population":0,
    "gn:timezone":"Asia/Shanghai",
    "iso:country":"CN",
    "name:zho_x_preferred":[
        "\u4e0b\u4e15\u5c97"
    ],
    "wof:name":"Xiapigang",
    "wof:placetype":"locality"
},
  "geometry": {"coordinates":[115.04501999999999,32.72508],"type":"Point"}
}