{
  "type": "Feature",
  "properties": {
    "gn:admin1_code":"29.0",
    "gn:asciiname":"Nasu",
    "gn:country_code":"CN",
    "gn:dem":1482,
    "gn:feature_class":"P",
    "gn:feature_code":"PPL",
    "gn:name":"Nasu",
    "gn:population":0,
    "gn:timezone":"Asia/Shanghai",
    "iso:country":"CN",
    "name:zho_x_preferred":[
        "\u90a3\u82cf"
    ],
    "wof:name":"Nasu",
    "wof:placetype":"locality"
},
  "geometry": {"coordinates":[101.83499999999999,23.116],"type":"Point"}
}