{
  "type": "Feature",
  "properties": {
    "gn:admin1_code":"26.0",
    "gn:asciiname":"Yazhonggou",
    "gn:country_code":"CN",
    "gn:dem":857,
    "gn:feature_class":"P",
    "gn:feature_code":"PPL",
    "gn:name":"Yazhonggou",
    "gn:population":0,
    "gn:timezone":"Asia/Shanghai",
    "iso:country":"CN",
    "name:und_x_variant":[
        "\u538b\u91cd\u6c9f"
    ],
    "wof:name":"Yazhonggou",
    "wof:placetype":"locality"
},
  "geometry": {"coordinates":[105.90355,33.50032],"type":"Point"}
}