{
  "type": "Feature",
  "properties": {
    "gn:admin1_code":"24.0",
    "gn:asciiname":"Huangjiacun",
    "gn:country_code":"CN",
    "gn:dem":1298,
    "gn:feature_class":"P",
    "gn:feature_code":"PPL",
    "gn:name":"Huangjiacun",
    "gn:population":0,
    "gn:timezone":"Asia/Shanghai",
    "iso:country":"CN",
    "name:zho_x_preferred":[
        "\u9ec4\u5bb6\u6751"
    ],
    "wof:name":"Huangjiacun",
    "wof:placetype":"locality"
},
  "geometry": {"coordinates":[112.73802999999999,40.07578],"type":"Point"}
}