{
  "type": "Feature",
  "properties": {
    "gn:admin1_code":"30.0",
    "gn:asciiname":"Yangmeitang",
    "gn:country_code":"CN",
    "gn:dem":132,
    "gn:feature_class":"P",
    "gn:feature_code":"PPL",
    "gn:name":"Yangmeitang",
    "gn:population":0,
    "gn:timezone":"Asia/Shanghai",
    "iso:country":"CN",
    "name:zho_x_preferred":[
        "Yangmeitang"
    ],
    "name:zho_x_variant":[
        "\u6768\u6885\u5858"
    ],
    "wof:name":"Yangmeitang",
    "wof:placetype":"locality"
},
  "geometry": {"coordinates":[114.12314000000001,24.37293],"type":"Point"}
}