{
  "type": "Feature",
  "properties": {
    "gn:admin1_code":"7.0",
    "gn:asciiname":"Xiaolongli",
    "gn:country_code":"CN",
    "gn:dem":454,
    "gn:feature_class":"P",
    "gn:feature_code":"PPL",
    "gn:name":"Xiaolongli",
    "gn:population":0,
    "gn:timezone":"Asia/Shanghai",
    "iso:country":"CN",
    "name:zho_x_preferred":[
        "\u5c0f\u5784\u91cc"
    ],
    "wof:name":"Xiaolongli",
    "wof:placetype":"locality"
},
  "geometry": {"coordinates":[116.48359000000001,26.30364],"type":"Point"}
}