{
  "type": "Feature",
  "properties": {
    "gn:admin1_code":"9.0",
    "gn:asciiname":"Yuanji",
    "gn:country_code":"CN",
    "gn:dem":135,
    "gn:feature_class":"P",
    "gn:feature_code":"PPL",
    "gn:name":"Yuanji",
    "gn:population":0,
    "gn:timezone":"Asia/Shanghai",
    "iso:country":"CN",
    "name:zho_x_preferred":[
        "\u8881\u96c6"
    ],
    "wof:name":"Yuanji",
    "wof:placetype":"locality"
},
  "geometry": {"coordinates":[113.62345999999999,34.42145],"type":"Point"}
}