{
  "type": "Feature",
  "properties": {
    "gn:admin1_code":"29.0",
    "gn:asciiname":"Laomanpo",
    "gn:country_code":"CN",
    "gn:dem":1740,
    "gn:feature_class":"P",
    "gn:feature_code":"PPL",
    "gn:name":"Laomanpo",
    "gn:population":0,
    "gn:timezone":"Asia/Shanghai",
    "iso:country":"CN",
    "name:zho_x_preferred":[
        "\u8001\u6ee1\u5761"
    ],
    "wof:name":"Laomanpo",
    "wof:placetype":"locality"
},
  "geometry": {"coordinates":[98.79179999999999,24.1674],"type":"Point"}
}