{
  "type": "Feature",
  "properties": {
    "gn:admin1_code":"9",
    "gn:asciiname":"Qiansangyuan",
    "gn:country_code":"CN",
    "gn:dem":63,
    "gn:feature_class":"P",
    "gn:feature_code":"PPL",
    "gn:name":"Qiansangyuan",
    "gn:population":0,
    "gn:timezone":"Asia/Shanghai",
    "iso:country":"CN",
    "name:zho_x_preferred":[
        "\u524d\u6851\u56ed"
    ],
    "wof:name":"Qiansangyuan",
    "wof:placetype":"locality"
},
  "geometry": {"coordinates":[114.86799999999999,35.2799],"type":"Point"}
}