{
  "type": "Feature",
  "properties": {
    "gn:admin1_code":"19.0",
    "gn:asciiname":"Huanglatuocun",
    "gn:country_code":"CN",
    "gn:dem":17,
    "gn:feature_class":"P",
    "gn:feature_code":"PPL",
    "gn:name":"Huanglatuocun",
    "gn:population":0,
    "gn:timezone":"Asia/Shanghai",
    "iso:country":"CN",
    "name:zho_x_preferred":[
        "\u9ec4\u814a\u5768\u6751"
    ],
    "wof:name":"Huanglatuocun",
    "wof:placetype":"locality"
},
  "geometry": {"coordinates":[122.9624,41.49554000000001],"type":"Point"}
}