{
  "type": "Feature",
  "properties": {
    "gn:admin1_code":"11.0",
    "gn:asciiname":"Xiaogongxi",
    "gn:country_code":"CN",
    "gn:dem":272,
    "gn:feature_class":"P",
    "gn:feature_code":"PPL",
    "gn:name":"Xiaogongxi",
    "gn:population":0,
    "gn:timezone":"Asia/Shanghai",
    "iso:country":"CN",
    "name:zho_x_preferred":[
        "\u8096\u516c\u6eaa"
    ],
    "wof:name":"Xiaogongxi",
    "wof:placetype":"locality"
},
  "geometry": {"coordinates":[109.61751,27.40565],"type":"Point"}
}