{
  "type": "Feature",
  "properties": {
    "gn:admin1_code":"29.0",
    "gn:asciiname":"Laoloufang",
    "gn:country_code":"CN",
    "gn:dem":2524,
    "gn:feature_class":"P",
    "gn:feature_code":"PPL",
    "gn:name":"Laoloufang",
    "gn:population":0,
    "gn:timezone":"Asia/Shanghai",
    "iso:country":"CN",
    "name:zho_x_preferred":[
        "\u8001\u697c\u623f"
    ],
    "wof:name":"Laoloufang",
    "wof:placetype":"locality"
},
  "geometry": {"coordinates":[99.1185,27.5713],"type":"Point"}
}