{
  "type": "Feature",
  "properties": {
    "gn:admin1_code":"30",
    "gn:asciiname":"Caotangjiao",
    "gn:country_code":"CN",
    "gn:dem":18,
    "gn:feature_class":"P",
    "gn:feature_code":"PPL",
    "gn:name":"Caotangjiao",
    "gn:population":0,
    "gn:timezone":"Asia/Urumqi",
    "iso:country":"CN",
    "name:zho_x_preferred":[
        "\u8349\u5858\u89d2"
    ],
    "wof:name":"Caotangjiao",
    "wof:placetype":"locality"
},
  "geometry": {"coordinates":[110.05701999999999,21.54022],"type":"Point"}
}