{
  "type": "Feature",
  "properties": {
    "gn:admin1_code":"29.0",
    "gn:asciiname":"Yongrang",
    "gn:country_code":"CN",
    "gn:dem":1530,
    "gn:feature_class":"P",
    "gn:feature_code":"PPL",
    "gn:name":"Yongrang",
    "gn:population":0,
    "gn:timezone":"Asia/Shanghai",
    "iso:country":"CN",
    "name:zho_x_preferred":[
        "\u6c38\u8ba9"
    ],
    "wof:name":"Yongrang",
    "wof:placetype":"locality"
},
  "geometry": {"coordinates":[99.42959999999999,23.2491],"type":"Point"}
}