{
  "type": "Feature",
  "properties": {
    "gn:admin1_code":"16.0",
    "gn:asciiname":"Huibu",
    "gn:country_code":"CN",
    "gn:dem":640,
    "gn:feature_class":"P",
    "gn:feature_code":"PPL",
    "gn:name":"Huibu",
    "gn:population":0,
    "gn:timezone":"Asia/Shanghai",
    "iso:country":"CN",
    "name:zho_x_preferred":[
        "\u60e0\u5e03"
    ],
    "wof:name":"Huibu",
    "wof:placetype":"locality"
},
  "geometry": {"coordinates":[105.92700000000001,23.4825],"type":"Point"}
}