{
  "type": "Feature",
  "properties": {
    "gn:admin1_code":"26.0",
    "gn:asciiname":"Hanjiayuan",
    "gn:country_code":"CN",
    "gn:dem":1217,
    "gn:feature_class":"P",
    "gn:feature_code":"PPL",
    "gn:name":"Hanjiayuan",
    "gn:population":0,
    "gn:timezone":"Asia/Shanghai",
    "iso:country":"CN",
    "name:fas_x_preferred":[
        "\u0647\u0627\u0646\u062c\u06cc\u0627\u06cc\u0648\u0627\u0646"
    ],
    "name:zho_x_preferred":[
        "\u97e9\u5bb6\u586c"
    ],
    "name:zho_x_variant":[
        "\u97e9\u5bb6\u56ed\u9547"
    ],
    "wof:name":"Hanjiayuan",
    "wof:placetype":"locality"
},
  "geometry": {"coordinates":[109.51862,36.04633],"type":"Point"}
}