{
  "type": "Feature",
  "properties": {
    "gn:country":"CN",
    "gn:fcode":"PPLA3",
    "gn:pop":0,
    "iso:country":"CN",
    "name:unk_x_variant":[
        "Yang-ling-chen"
    ],
    "name:zho_x_preferred":[
        "\u6768\u9675"
    ],
    "qs:name":"Yangling",
    "qs:photos_9r":0,
    "qs:photos_sr":0,
    "qs:pop_sr":"0",
    "wd:wordcount":275,
    "wof:name":"Yangling",
    "wof:placetype":"locality",
    "wof:population":0
},
  "geometry": {"coordinates":[108.07890999999999,34.27173],"type":"Point"}
}