{
  "type": "Feature",
  "properties": {
    "gn:country":"CN",
    "gn:fcode":"PPLA3",
    "gn:population":0,
    "iso:country":"CN",
    "name:cym_x_preferred":[
        "Ardal Yangling"
    ],
    "name:deu_x_preferred":[
        "Yangling"
    ],
    "name:eng_x_preferred":[
        "Yangling District"
    ],
    "name:gan_x_preferred":[
        "\u6768\u9675\u533a"
    ],
    "name:heb_x_preferred":[
        "\u05d9\u05d0\u05e0\u05d2\u05dc\u05d9\u05e0\u05d2"
    ],
    "name:ind_x_preferred":[
        "Distrik Yangling"
    ],
    "name:jpn_x_preferred":[
        "\u694a\u9675\u533a"
    ],
    "name:kor_x_preferred":[
        "\uc591\ub9c1\uad6c"
    ],
    "name:nan_x_preferred":[
        "I\u00f4ng-l\u00eang-khu"
    ],
    "name:nld_x_preferred":[
        "Yangling"
    ],
    "name:nob_x_preferred":[
        "Yangling"
    ],
    "name:rus_x_preferred":[
        "\u042f\u043d\u043b\u0438\u043d"
    ],
    "name:swe_x_preferred":[
        "Yangling"
    ],
    "name:und_x_variant":[
        "Yang-ling-chen"
    ],
    "name:urd_x_preferred":[
        "\u06cc\u0646\u06af\u0644\u0646\u06af \u0636\u0644\u0639"
    ],
    "name:vie_x_preferred":[
        "D\u01b0\u01a1ng L\u0103ng"
    ],
    "name:wuu_x_preferred":[
        "\u6768\u9675\u533a"
    ],
    "name:yue_x_preferred":[
        "\u694a\u9675\u5340"
    ],
    "name:zho_x_preferred":[
        "\u6768\u9675"
    ],
    "name:zho_x_variant":[
        "\u6768\u9675\u533a"
    ],
    "qs:name":"Yangling",
    "qs:photos_9r":0,
    "qs:photos_sr":0,
    "qs:pop_sr":"0",
    "wd:wordcount":275,
    "wof:name":"Yangling",
    "wof:placetype":"locality",
    "wof:population":0
},
  "geometry": {"coordinates":[108.07890999999999,34.27173],"type":"Point"}
}