{
  "type": "Feature",
  "properties": {
    "gn:admin1_code":"8.0",
    "gn:asciiname":"Yanjun Disanlinchang",
    "gn:country_code":"CN",
    "gn:dem":135,
    "gn:feature_class":"P",
    "gn:feature_code":"PPLF",
    "gn:name":"Yanjun Disanlinchang",
    "gn:population":0,
    "gn:timezone":"Asia/Shanghai",
    "iso:country":"CN",
    "name:zho_x_preferred":[
        "\u5ef6\u519b\u7b2c\u4e09\u6797\u573a"
    ],
    "wof:name":"Yanjun Disanlinchang",
    "wof:placetype":"locality"
},
  "geometry": {"coordinates":[130.7972,47.82183],"type":"Point"}
}