{
  "type": "Feature",
  "properties": {
    "gn:admin1_code":"18",
    "gn:asciiname":"Leishipo",
    "gn:country_code":"CN",
    "gn:dem":1356,
    "gn:feature_class":"P",
    "gn:feature_code":"PPL",
    "gn:name":"Leishipo",
    "gn:population":0,
    "gn:timezone":"Asia/Shanghai",
    "iso:country":"CN",
    "name:zho_x_preferred":[
        "\u7d2f\u77f3\u5761"
    ],
    "wof:name":"Leishipo",
    "wof:placetype":"locality"
},
  "geometry": {"coordinates":[106.05200000000001,27.503],"type":"Point"}
}