{
  "type": "Feature",
  "properties": {
    "gn:admin1_code":"1.0",
    "gn:asciiname":"Nongfengcun",
    "gn:country_code":"CN",
    "gn:dem":21,
    "gn:feature_class":"P",
    "gn:feature_code":"PPLF",
    "gn:name":"Nongfengcun",
    "gn:population":0,
    "gn:timezone":"Asia/Shanghai",
    "iso:country":"CN",
    "name:zho_x_preferred":[
        "\u519c\u4e30\u6751"
    ],
    "wof:name":"Nongfengcun",
    "wof:placetype":"locality"
},
  "geometry": {"coordinates":[117.25202,30.77475],"type":"Point"}
}