{
  "type": "Feature",
  "properties": {
    "gn:admin1_code":"20.0",
    "gn:asciiname":"Houguoni",
    "gn:country_code":"CN",
    "gn:dem":209,
    "gn:feature_class":"P",
    "gn:feature_code":"PPL",
    "gn:name":"Houguoni",
    "gn:population":0,
    "gn:timezone":"Asia/Shanghai",
    "iso:country":"CN",
    "name:zho_x_preferred":[
        "\u540e\u90ed\u5c3c"
    ],
    "wof:name":"Houguoni",
    "wof:placetype":"locality"
},
  "geometry": {"coordinates":[124.60562,48.70537],"type":"Point"}
}