{
  "type": "Feature",
  "properties": {
    "gn:admin1_code":"25.0",
    "gn:asciiname":"Liqucun",
    "gn:country_code":"CN",
    "gn:dem":28,
    "gn:feature_class":"P",
    "gn:feature_code":"PPL",
    "gn:name":"Liqucun",
    "gn:population":0,
    "gn:timezone":"Asia/Shanghai",
    "iso:country":"CN",
    "name:zho_x_preferred":[
        "\u674e\u74a9\u6751"
    ],
    "wof:name":"Liqucun",
    "wof:placetype":"locality"
},
  "geometry": {"coordinates":[118.40633,36.9549],"type":"Point"}
}