{
  "type": "Feature",
  "properties": {
    "gn:admin1_code":"2",
    "gn:asciiname":"Julong",
    "gn:country_code":"CN",
    "gn:dem":294,
    "gn:feature_class":"P",
    "gn:feature_code":"PPL",
    "gn:name":"Julong",
    "gn:population":0,
    "gn:timezone":"Asia/Shanghai",
    "iso:country":"CN",
    "name:und_x_variant":[
        "\u5de8\u9f99"
    ],
    "wof:name":"Julong",
    "wof:placetype":"locality"
},
  "geometry": {"coordinates":[119.53342000000001,30.0276],"type":"Point"}
}