{
  "type": "Feature",
  "properties": {
    "gn:admin1_code":"33.0",
    "gn:asciiname":"Shazipo",
    "gn:country_code":"CN",
    "gn:dem":324,
    "gn:feature_class":"P",
    "gn:feature_code":"PPL",
    "gn:name":"Shazipo",
    "gn:population":0,
    "gn:timezone":"Asia/Shanghai",
    "iso:country":"CN",
    "name:zho_x_preferred":[
        "\u6c99\u5b50\u5761"
    ],
    "wof:name":"Shazipo",
    "wof:placetype":"locality"
},
  "geometry": {"coordinates":[105.96926999999999,29.30332000000001],"type":"Point"}
}