{
  "type": "Feature",
  "properties": {
    "gn:admin1_code":"18.0",
    "gn:asciiname":"Changshanhe",
    "gn:country_code":"CN",
    "gn:dem":1015,
    "gn:feature_class":"P",
    "gn:feature_code":"PPL",
    "gn:name":"Changshanhe",
    "gn:population":0,
    "gn:timezone":"Asia/Shanghai",
    "iso:country":"CN",
    "name:zho_x_preferred":[
        "\u957f\u5c71\u6cb3"
    ],
    "wof:name":"Changshanhe",
    "wof:placetype":"locality"
},
  "geometry": {"coordinates":[107.21599999999999,26.155],"type":"Point"}
}