{
  "type": "Feature",
  "properties": {
    "gn:admin1_code":"1.0",
    "gn:asciiname":"Changzhoucun",
    "gn:country_code":"CN",
    "gn:dem":17,
    "gn:feature_class":"P",
    "gn:feature_code":"PPL",
    "gn:name":"Changzhoucun",
    "gn:population":0,
    "gn:timezone":"Asia/Shanghai",
    "iso:country":"CN",
    "name:zho_x_preferred":[
        "\u5e38\u5dde\u6751"
    ],
    "wof:name":"Changzhoucun",
    "wof:placetype":"locality"
},
  "geometry": {"coordinates":[117.82015,30.72446],"type":"Point"}
}