{
  "type": "Feature",
  "properties": {
    "gn:admin1_code":"22.0",
    "gn:asciiname":"Qianjiaojiawucun",
    "gn:country_code":"CN",
    "gn:dem":92,
    "gn:feature_class":"P",
    "gn:feature_code":"PPL",
    "gn:name":"Qianjiaojiawucun",
    "gn:population":0,
    "gn:timezone":"Asia/Shanghai",
    "iso:country":"CN",
    "name:zho_x_preferred":[
        "\u524d\u7126\u5bb6\u575e\u6751"
    ],
    "wof:name":"Qianjiaojiawucun",
    "wof:placetype":"locality"
},
  "geometry": {"coordinates":[116.92974,40.38075],"type":"Point"}
}