{
  "type": "Feature",
  "properties": {
    "gn:admin1_code":"9.0",
    "gn:asciiname":"Xiaoluozhuang",
    "gn:country_code":"CN",
    "gn:dem":53,
    "gn:feature_class":"P",
    "gn:feature_code":"PPL",
    "gn:name":"Xiaoluozhuang",
    "gn:population":0,
    "gn:timezone":"Asia/Shanghai",
    "iso:country":"CN",
    "name:zho_x_preferred":[
        "\u5c0f\u7f57\u5e84"
    ],
    "wof:name":"Xiaoluozhuang",
    "wof:placetype":"locality"
},
  "geometry": {"coordinates":[114.50178,33.03562],"type":"Point"}
}