{
  "type": "Feature",
  "properties": {
    "gn:admin1_code":"4.0",
    "gn:asciiname":"Haimenxu",
    "gn:country_code":"CN",
    "gn:dem":5,
    "gn:feature_class":"P",
    "gn:feature_code":"PPL",
    "gn:name":"Haimenxu",
    "gn:population":0,
    "gn:timezone":"Asia/Shanghai",
    "iso:country":"CN",
    "name:zho_x_preferred":[
        "\u6d77\u95e8\u5729"
    ],
    "wof:name":"Haimenxu",
    "wof:placetype":"locality"
},
  "geometry": {"coordinates":[120.30491000000001,32.12327],"type":"Point"}
}