{
  "type": "Feature",
  "properties": {
    "gn:admin1_code":"8.0",
    "gn:asciiname":"Shuanghecun",
    "gn:country_code":"CN",
    "gn:dem":283,
    "gn:feature_class":"P",
    "gn:feature_code":"PPL",
    "gn:name":"Shuanghecun",
    "gn:population":0,
    "gn:timezone":"Asia/Shanghai",
    "iso:country":"CN",
    "name:zho_x_preferred":[
        "\u53cc\u5408\u6751"
    ],
    "wof:name":"Shuanghecun",
    "wof:placetype":"locality"
},
  "geometry": {"coordinates":[126.23786,48.0459],"type":"Point"}
}