{
  "type": "Feature",
  "properties": {
    "gn:admin1_code":"18.0",
    "gn:asciiname":"Hongyan",
    "gn:country_code":"CN",
    "gn:dem":1097,
    "gn:feature_class":"P",
    "gn:feature_code":"PPL",
    "gn:name":"Hongyan",
    "gn:population":0,
    "gn:timezone":"Asia/Shanghai",
    "iso:country":"CN",
    "name:ceb_x_preferred":[
        "Hongyan"
    ],
    "name:deu_x_preferred":[
        "Hongyan"
    ],
    "name:ita_x_preferred":[
        "Hongyan"
    ],
    "name:swe_x_preferred":[
        "Hongyan"
    ],
    "name:zho_x_preferred":[
        "\u7ea2\u5ca9"
    ],
    "wof:name":"Hongyan",
    "wof:placetype":"locality"
},
  "geometry": {"coordinates":[107.25700000000001,26.5104],"type":"Point"}
}