{
  "type": "Feature",
  "properties": {
    "gn:admin1_code":"9",
    "gn:asciiname":"Xililou",
    "gn:country_code":"CN",
    "gn:dem":51,
    "gn:feature_class":"P",
    "gn:feature_code":"PPL",
    "gn:name":"Xililou",
    "gn:population":0,
    "gn:timezone":"Asia/Shanghai",
    "iso:country":"CN",
    "name:zho_x_preferred":[
        "\u897f\u674e\u697c"
    ],
    "wof:name":"Xililou",
    "wof:placetype":"locality"
},
  "geometry": {"coordinates":[114.92400000000001,33.923],"type":"Point"}
}