{
  "type": "Feature",
  "properties": {
    "gn:country":"CN",
    "gn:fcode":"ADM3",
    "gn:population":0,
    "iso:country":"CN",
    "name:und_x_variant":[
        "Ch\u2019uan-sha Hsien"
    ],
    "name:zho_x_preferred":[
        "\u6d66\u4e1c"
    ],
    "name:zho_x_variant":[
        "\u6d66\u4e1c\u65b0\u533a"
    ],
    "qs:name":"Pudong Xinqu",
    "qs:photos_9r":0,
    "qs:photos_sr":0,
    "qs:pop_sr":"0",
    "wof:name":"Pudong Xinqu",
    "wof:placetype":"localadmin",
    "wof:population":0
},
  "geometry": {"coordinates":[121.64131,31.2246],"type":"Point"}
}