{
  "type": "Feature",
  "properties": {
    "gn:admin1_code":"4.0",
    "gn:asciiname":"Houjiaqiao",
    "gn:country_code":"CN",
    "gn:dem":4,
    "gn:feature_class":"P",
    "gn:feature_code":"PPL",
    "gn:name":"Houjiaqiao",
    "gn:population":0,
    "gn:timezone":"Asia/Shanghai",
    "iso:country":"CN",
    "name:zho_x_preferred":[
        "\u4faf\u5bb6\u6865"
    ],
    "wof:name":"Houjiaqiao",
    "wof:placetype":"locality"
},
  "geometry": {"coordinates":[119.63291,32.21809],"type":"Point"}
}