{
  "type": "Feature",
  "properties": {
    "gn:admin1_code":"29.0",
    "gn:asciiname":"Taizishang",
    "gn:country_code":"CN",
    "gn:dem":2196,
    "gn:feature_class":"P",
    "gn:feature_code":"PPL",
    "gn:name":"Taizishang",
    "gn:population":0,
    "gn:timezone":"Asia/Shanghai",
    "iso:country":"CN",
    "name:zho_x_preferred":[
        "\u53f0\u5b50\u4e0a"
    ],
    "wof:name":"Taizishang",
    "wof:placetype":"locality"
},
  "geometry": {"coordinates":[103.36199999999999,26.5763],"type":"Point"}
}