{
  "type": "Feature",
  "properties": {
    "gn:admin1_code":"29.0",
    "gn:asciiname":"Nimuchong",
    "gn:country_code":"CN",
    "gn:dem":2405,
    "gn:feature_class":"P",
    "gn:feature_code":"PPL",
    "gn:name":"Nimuchong",
    "gn:population":0,
    "gn:timezone":"Asia/Shanghai",
    "iso:country":"CN",
    "name:zho_x_preferred":[
        "\u5c3c\u6728\u51b2"
    ],
    "wof:name":"Nimuchong",
    "wof:placetype":"locality"
},
  "geometry": {"coordinates":[99.2593,27.9316],"type":"Point"}
}