{
  "type": "Feature",
  "properties": {
    "gn:admin1_code":"10.0",
    "gn:asciiname":"Liumingzhuang",
    "gn:country_code":"CN",
    "gn:dem":18,
    "gn:feature_class":"P",
    "gn:feature_code":"PPL",
    "gn:name":"Liumingzhuang",
    "gn:population":0,
    "gn:timezone":"Asia/Shanghai",
    "iso:country":"CN",
    "name:zho_x_preferred":[
        "\u5218\u94ed\u5e84"
    ],
    "wof:name":"Liumingzhuang",
    "wof:placetype":"locality"
},
  "geometry": {"coordinates":[115.65000000000001,38.6201],"type":"Point"}
}