{
  "type": "Feature",
  "properties": {
    "gn:admin1_code":"10",
    "gn:asciiname":"Gouli",
    "gn:country_code":"CN",
    "gn:dem":1242,
    "gn:feature_class":"P",
    "gn:feature_code":"PPL",
    "gn:name":"Gouli",
    "gn:population":0,
    "gn:timezone":"Asia/Shanghai",
    "iso:country":"CN",
    "name:zho_x_preferred":[
        "\u6c9f\u91cc"
    ],
    "wof:name":"Gouli",
    "wof:placetype":"locality"
},
  "geometry": {"coordinates":[118.5286,41.34992],"type":"Point"}
}