{
  "type": "Feature",
  "properties": {
    "gn:admin1_code":"26",
    "gn:asciiname":"Dongzhang",
    "gn:country_code":"CN",
    "gn:dem":387,
    "gn:feature_class":"P",
    "gn:feature_code":"PPL",
    "gn:name":"Dongzhang",
    "gn:population":0,
    "gn:timezone":"Asia/Shanghai",
    "iso:country":"CN",
    "name:und_x_variant":[
        "Dongzhangcun"
    ],
    "wof:name":"Dongzhang",
    "wof:placetype":"locality"
},
  "geometry": {"coordinates":[108.87806,34.50278],"type":"Point"}
}