{
  "type": "Feature",
  "properties": {
    "gn:admin1_code":"16",
    "gn:asciiname":"Niukoutian",
    "gn:country_code":"CN",
    "gn:dem":259,
    "gn:feature_class":"P",
    "gn:feature_code":"PPL",
    "gn:name":"Niukoutian",
    "gn:population":0,
    "gn:timezone":"Asia/Shanghai",
    "iso:country":"CN",
    "name:zho_x_preferred":[
        "\u725b\u53e3\u7530"
    ],
    "wof:name":"Niukoutian",
    "wof:placetype":"locality"
},
  "geometry": {"coordinates":[110.72799999999999,25.5672],"type":"Point"}
}