{
  "type": "Feature",
  "properties": {
    "gn:admin1_code":"33.0",
    "gn:asciiname":"Tiechangba",
    "gn:country_code":"CN",
    "gn:dem":628,
    "gn:feature_class":"P",
    "gn:feature_code":"PPL",
    "gn:name":"Tiechangba",
    "gn:population":0,
    "gn:timezone":"Asia/Shanghai",
    "iso:country":"CN",
    "name:zho_x_preferred":[
        "\u94c1\u5382\u575d"
    ],
    "wof:name":"Tiechangba",
    "wof:placetype":"locality"
},
  "geometry": {"coordinates":[107.88628,29.93276],"type":"Point"}
}