{
  "type": "Feature",
  "properties": {
    "gn:admin1_code":"32.0",
    "gn:asciiname":"Cihang",
    "gn:country_code":"CN",
    "gn:dem":418,
    "gn:feature_class":"P",
    "gn:feature_code":"PPL",
    "gn:name":"Cihang",
    "gn:population":0,
    "gn:timezone":"Asia/Shanghai",
    "iso:country":"CN",
    "name:zho_x_preferred":[
        "\u6148\u822a"
    ],
    "wof:name":"Cihang",
    "wof:placetype":"locality"
},
  "geometry": {"coordinates":[104.12617,29.7482],"type":"Point"}
}