{
  "type": "Feature",
  "properties": {
    "gn:admin1_code":"12.0",
    "gn:asciiname":"Qianjiapu",
    "gn:country_code":"CN",
    "gn:dem":23,
    "gn:feature_class":"P",
    "gn:feature_code":"PPL",
    "gn:name":"Qianjiapu",
    "gn:population":0,
    "gn:timezone":"Asia/Shanghai",
    "iso:country":"CN",
    "name:zho_x_preferred":[
        "Qianjiapu"
    ],
    "name:zho_x_variant":[
        "\u94b1\u5bb6\u94fa"
    ],
    "wof:name":"Qianjiapu",
    "wof:placetype":"locality"
},
  "geometry": {"coordinates":[115.10296,30.24805],"type":"Point"}
}