{
  "type": "Feature",
  "properties": {
    "gn:admin1_code":"15.0",
    "gn:asciiname":"Qiagao",
    "gn:country_code":"CN",
    "gn:dem":2319,
    "gn:feature_class":"P",
    "gn:feature_code":"PPL",
    "gn:name":"Qiagao",
    "gn:population":0,
    "gn:timezone":"Asia/Shanghai",
    "iso:country":"CN",
    "name:und_x_variant":[
        "\u6070\u544a"
    ],
    "wof:name":"Qiagao",
    "wof:placetype":"locality"
},
  "geometry": {"coordinates":[103.30992000000001,34.01808],"type":"Point"}
}