{
  "type": "Feature",
  "properties": {
    "gn:admin1_code":"7.0",
    "gn:asciiname":"Liping",
    "gn:country_code":"CN",
    "gn:dem":798,
    "gn:feature_class":"P",
    "gn:feature_code":"PPL",
    "gn:name":"Liping",
    "gn:population":0,
    "gn:timezone":"Asia/Shanghai",
    "iso:country":"CN",
    "name:zho_x_preferred":[
        "Liping"
    ],
    "name:zho_x_variant":[
        "\u68a8\u576a"
    ],
    "wof:name":"Liping",
    "wof:placetype":"locality"
},
  "geometry": {"coordinates":[118.6575,26.67444],"type":"Point"}
}