{
  "type": "Feature",
  "properties": {
    "gn:admin1_code":"8.0",
    "gn:asciiname":"Miaoling",
    "gn:country_code":"CN",
    "gn:dem":285,
    "gn:feature_class":"P",
    "gn:feature_code":"PPL",
    "gn:name":"Miaoling",
    "gn:population":0,
    "gn:timezone":"Asia/Shanghai",
    "iso:country":"CN",
    "name:zho_x_preferred":[
        "\u5e99\u5cad"
    ],
    "wof:name":"Miaoling",
    "wof:placetype":"locality"
},
  "geometry": {"coordinates":[128.35289,45.03829],"type":"Point"}
}