{
  "type": "Feature",
  "properties": {
    "gn:admin1_code":"6.0",
    "gn:asciiname":"Shangzhao Jiagou",
    "gn:country_code":"CN",
    "gn:dem":2763,
    "gn:feature_class":"P",
    "gn:feature_code":"PPL",
    "gn:name":"Shangzhao Jiagou",
    "gn:population":0,
    "gn:timezone":"Asia/Shanghai",
    "iso:country":"CN",
    "name:zho_x_preferred":[
        "\u4e0a\u8d75\u5bb6\u6c9f"
    ],
    "wof:name":"Shangzhao Jiagou",
    "wof:placetype":"locality"
},
  "geometry": {"coordinates":[101.53513,36.00199999999999],"type":"Point"}
}