{
  "type": "Feature",
  "properties": {
    "gn:admin1_code":"18",
    "gn:asciiname":"Yeqi",
    "gn:country_code":"CN",
    "gn:dem":2015,
    "gn:feature_class":"P",
    "gn:feature_code":"PPL",
    "gn:name":"Yeqi",
    "gn:population":0,
    "gn:timezone":"Asia/Shanghai",
    "iso:country":"CN",
    "name:zho_x_preferred":[
        "\u91ce\u671f"
    ],
    "wof:name":"Yeqi",
    "wof:placetype":"locality"
},
  "geometry": {"coordinates":[104.014,27.2689],"type":"Point"}
}