{
  "type": "Feature",
  "properties": {
    "gn:admin1_code":"15.0",
    "gn:asciiname":"Yangcaogou",
    "gn:country_code":"CN",
    "gn:dem":1776,
    "gn:feature_class":"P",
    "gn:feature_code":"PPL",
    "gn:name":"Yangcaogou",
    "gn:population":0,
    "gn:timezone":"Asia/Shanghai",
    "iso:country":"CN",
    "name:zho_x_preferred":[
        "\u6768\u8349\u6c9f"
    ],
    "wof:name":"Yangcaogou",
    "wof:placetype":"locality"
},
  "geometry": {"coordinates":[105.604,34.3842],"type":"Point"}
}