{
  "type": "Feature",
  "properties": {
    "gn:admin1_code":"29",
    "gn:asciiname":"Tuguoqingmafeng",
    "gn:country_code":"CN",
    "gn:dem":2060,
    "gn:feature_class":"P",
    "gn:feature_code":"PPL",
    "gn:name":"Tuguoqingmafeng",
    "gn:population":0,
    "gn:timezone":"Asia/Shanghai",
    "iso:country":"CN",
    "name:zho_x_preferred":[
        "\u571f\u9505\u7b90\u9ebb\u75af"
    ],
    "wof:name":"Tuguoqingmafeng",
    "wof:placetype":"locality"
},
  "geometry": {"coordinates":[101.56999999999999,25.1882],"type":"Point"}
}