{
  "type": "Feature",
  "properties": {
    "gn:admin1_code":"21.0",
    "gn:asciiname":"Xiayingzi",
    "gn:country_code":"CN",
    "gn:dem":1091,
    "gn:feature_class":"P",
    "gn:feature_code":"PPL",
    "gn:name":"Xiayingzi",
    "gn:population":0,
    "gn:timezone":"Asia/Shanghai",
    "iso:country":"CN",
    "name:und_x_variant":[
        "Xiayingzi Xiang"
    ],
    "name:zho_x_preferred":[
        "\u4e0b\u8425\u5b50"
    ],
    "name:zho_x_variant":[
        "\u4e0b\u8425\u5b50\u4e61"
    ],
    "wof:name":"Xiayingzi",
    "wof:placetype":"locality"
},
  "geometry": {"coordinates":[106.69889999999999,39.14088],"type":"Point"}
}