{
  "type": "Feature",
  "properties": {
    "gn:admin1_code":"29.0",
    "gn:asciiname":"Taozicun",
    "gn:country_code":"CN",
    "gn:dem":698,
    "gn:feature_class":"P",
    "gn:feature_code":"PPL",
    "gn:name":"Taozicun",
    "gn:population":0,
    "gn:timezone":"Asia/Shanghai",
    "iso:country":"CN",
    "name:zho_x_preferred":[
        "\u6843\u5b50\u6751"
    ],
    "wof:name":"Taozicun",
    "wof:placetype":"locality"
},
  "geometry": {"coordinates":[104.248,28.0439],"type":"Point"}
}