{
  "type": "Feature",
  "properties": {
    "gn:admin1_code":"23.0",
    "gn:asciiname":"Nanzhuzhai",
    "gn:country_code":"CN",
    "gn:dem":5,
    "gn:feature_class":"P",
    "gn:feature_code":"PPL",
    "gn:name":"Nanzhuzhai",
    "gn:population":0,
    "gn:timezone":"Asia/Shanghai",
    "iso:country":"CN",
    "name:zho_x_preferred":[
        "Nanzhuzhai"
    ],
    "name:zho_x_variant":[
        "\u5357\u6731\u5b85"
    ],
    "wof:name":"Nanzhuzhai",
    "wof:placetype":"locality"
},
  "geometry": {"coordinates":[121.3368,31.395],"type":"Point"}
}