{
  "type": "Feature",
  "properties": {
    "gn:admin1_code":"16.0",
    "gn:asciiname":"Qin'an",
    "gn:country_code":"CN",
    "gn:dem":182,
    "gn:feature_class":"P",
    "gn:feature_code":"PPL",
    "gn:name":"Qin\u2019an",
    "gn:population":0,
    "gn:timezone":"Asia/Shanghai",
    "iso:country":"CN",
    "name:und_x_variant":[
        "Qin\u2019an"
    ],
    "name:zho_x_preferred":[
        "\u94a6\u5b89"
    ],
    "wof:name":"Qin'an",
    "wof:placetype":"locality"
},
  "geometry": {"coordinates":[107.881,22.1391],"type":"Point"}
}