{
  "type": "Feature",
  "properties": {
    "gn:admin1_code":"32.0",
    "gn:asciiname":"Tiangutang",
    "gn:country_code":"CN",
    "gn:dem":647,
    "gn:feature_class":"P",
    "gn:feature_code":"PPL",
    "gn:name":"Tiangutang",
    "gn:population":0,
    "gn:timezone":"Asia/Shanghai",
    "iso:country":"CN",
    "name:zho_x_preferred":[
        "\u5929\u9f13\u5802"
    ],
    "wof:name":"Tiangutang",
    "wof:placetype":"locality"
},
  "geometry": {"coordinates":[107.485,31.7937],"type":"Point"}
}