{
  "type": "Feature",
  "properties": {
    "gn:admin1_code":"7.0",
    "gn:asciiname":"Liucuo",
    "gn:country_code":"CN",
    "gn:dem":10,
    "gn:feature_class":"P",
    "gn:feature_code":"PPL",
    "gn:name":"Liucuo",
    "gn:population":0,
    "gn:timezone":"Asia/Shanghai",
    "iso:country":"CN",
    "name:zho_x_preferred":[
        "\u67f3\u539d"
    ],
    "wof:name":"Liucuo",
    "wof:placetype":"locality"
},
  "geometry": {"coordinates":[119.28655999999999,25.58498],"type":"Point"}
}