{
  "type": "Feature",
  "properties": {
    "gn:admin1_code":"1.0",
    "gn:asciiname":"Weilaozhuangcun",
    "gn:country_code":"CN",
    "gn:dem":42,
    "gn:feature_class":"P",
    "gn:feature_code":"PPL",
    "gn:name":"Weilaozhuangcun",
    "gn:population":0,
    "gn:timezone":"Asia/Shanghai",
    "iso:country":"CN",
    "name:zho_x_preferred":[
        "\u97e6\u8001\u5e84\u6751"
    ],
    "wof:name":"Weilaozhuangcun",
    "wof:placetype":"locality"
},
  "geometry": {"coordinates":[115.13054,32.91787],"type":"Point"}
}