{
  "type": "Feature",
  "properties": {
    "gn:admin1_code":"26.0",
    "gn:asciiname":"Muzhu'ao",
    "gn:country_code":"CN",
    "gn:dem":818,
    "gn:feature_class":"P",
    "gn:feature_code":"PPL",
    "gn:name":"Muzhu\u2019ao",
    "gn:population":0,
    "gn:timezone":"Asia/Shanghai",
    "iso:country":"CN",
    "name:und_x_variant":[
        "Muzhu\u2019ao"
    ],
    "name:zho_x_preferred":[
        "\u6bcd\u732a\u51f9"
    ],
    "wof:name":"Muzhu'ao",
    "wof:placetype":"locality"
},
  "geometry": {"coordinates":[109.85396,32.81697],"type":"Point"}
}