{
  "type": "Feature",
  "properties": {
    "gn:admin1_code":"30.0",
    "gn:asciiname":"Siliuyuan",
    "gn:country_code":"CN",
    "gn:dem":42,
    "gn:feature_class":"P",
    "gn:feature_code":"PPL",
    "gn:name":"Siliuyuan",
    "gn:population":0,
    "gn:timezone":"Asia/Shanghai",
    "iso:country":"CN",
    "name:zho_x_preferred":[
        "\u601d\u7559\u8fdc"
    ],
    "wof:name":"Siliuyuan",
    "wof:placetype":"locality"
},
  "geometry": {"coordinates":[111.5624,23.62848],"type":"Point"}
}