{
  "type": "Feature",
  "properties": {
    "gn:admin1_code":"26.0",
    "gn:asciiname":"Qiao'ergoucun",
    "gn:country_code":"CN",
    "gn:dem":1218,
    "gn:feature_class":"P",
    "gn:feature_code":"PPL",
    "gn:name":"Qiao\u2019ergoucun",
    "gn:population":0,
    "gn:timezone":"Asia/Shanghai",
    "iso:country":"CN",
    "name:und_x_variant":[
        "Qiao\u2019ergoucun"
    ],
    "name:zho_x_preferred":[
        "\u4e54\u513f\u6c9f\u6751"
    ],
    "wof:name":"Qiao'ergoucun",
    "wof:placetype":"locality"
},
  "geometry": {"coordinates":[108.48706,35.17488],"type":"Point"}
}