{
  "type": "Feature",
  "properties": {
    "gn:admin1_code":"32.0",
    "gn:asciiname":"Tianbatou",
    "gn:country_code":"CN",
    "gn:dem":827,
    "gn:feature_class":"P",
    "gn:feature_code":"PPL",
    "gn:name":"Tianbatou",
    "gn:population":0,
    "gn:timezone":"Asia/Shanghai",
    "iso:country":"CN",
    "name:zho_x_preferred":[
        "\u7530\u575d\u5934"
    ],
    "wof:name":"Tianbatou",
    "wof:placetype":"locality"
},
  "geometry": {"coordinates":[103.35435,30.05528],"type":"Point"}
}