{
  "type": "Feature",
  "properties": {
    "gn:admin1_code":"26.0",
    "gn:asciiname":"Miaogoukou",
    "gn:country_code":"CN",
    "gn:dem":1013,
    "gn:feature_class":"P",
    "gn:feature_code":"PPL",
    "gn:name":"Miaogoukou",
    "gn:population":0,
    "gn:timezone":"Asia/Shanghai",
    "iso:country":"CN",
    "name:zho_x_preferred":[
        "\u5e99\u6c9f\u53e3"
    ],
    "wof:name":"Miaogoukou",
    "wof:placetype":"locality"
},
  "geometry": {"coordinates":[109.42538999999999,33.42654],"type":"Point"}
}