{
  "type": "Feature",
  "properties": {
    "gn:admin1_code":"32.0",
    "gn:asciiname":"Zimushi",
    "gn:country_code":"CN",
    "gn:dem":2072,
    "gn:feature_class":"P",
    "gn:feature_code":"PPL",
    "gn:name":"Zimushi",
    "gn:population":0,
    "gn:timezone":"Asia/Shanghai",
    "iso:country":"CN",
    "name:zho_x_preferred":[
        "\u5b50\u6728\u53f2"
    ],
    "wof:name":"Zimushi",
    "wof:placetype":"locality"
},
  "geometry": {"coordinates":[102.994,27.5489],"type":"Point"}
}