{
  "type": "Feature",
  "properties": {
    "gn:admin1_code":"18",
    "gn:asciiname":"Majuntun",
    "gn:country_code":"CN",
    "gn:dem":1431,
    "gn:feature_class":"P",
    "gn:feature_code":"PPL",
    "gn:name":"Majuntun",
    "gn:population":0,
    "gn:timezone":"Asia/Shanghai",
    "iso:country":"CN",
    "name:zho_x_preferred":[
        "\u9a6c\u519b\u5c6f"
    ],
    "wof:name":"Majuntun",
    "wof:placetype":"locality"
},
  "geometry": {"coordinates":[105.989,26.3017],"type":"Point"}
}