{
  "type": "Feature",
  "properties": {
    "gn:admin1_code":"12.0",
    "gn:asciiname":"Xiongjiazhawu",
    "gn:country_code":"CN",
    "gn:dem":280,
    "gn:feature_class":"P",
    "gn:feature_code":"PPL",
    "gn:name":"Xiongjiazhawu",
    "gn:population":0,
    "gn:timezone":"Asia/Shanghai",
    "iso:country":"CN",
    "name:zho_x_preferred":[
        "\u718a\u5bb6\u69a8\u5c4b"
    ],
    "wof:name":"Xiongjiazhawu",
    "wof:placetype":"locality"
},
  "geometry": {"coordinates":[111.95529999999999,31.28923],"type":"Point"}
}