{
  "type": "Feature",
  "properties": {
    "gn:admin1_code":"26.0",
    "gn:asciiname":"Zhoujia Yancun",
    "gn:country_code":"CN",
    "gn:dem":1006,
    "gn:feature_class":"P",
    "gn:feature_code":"PPL",
    "gn:name":"Zhoujia Yancun",
    "gn:population":0,
    "gn:timezone":"Asia/Shanghai",
    "iso:country":"CN",
    "name:zho_x_preferred":[
        "\u5468\u5bb6\u5895\u6751"
    ],
    "wof:name":"Zhoujia Yancun",
    "wof:placetype":"locality"
},
  "geometry": {"coordinates":[110.04600000000001,37.9654],"type":"Point"}
}