{
  "type": "Feature",
  "properties": {
    "gn:admin1_code":"1.0",
    "gn:asciiname":"Tianchongcun",
    "gn:country_code":"CN",
    "gn:dem":19,
    "gn:feature_class":"P",
    "gn:feature_code":"PPL",
    "gn:name":"Tianchongcun",
    "gn:population":0,
    "gn:timezone":"Asia/Shanghai",
    "iso:country":"CN",
    "name:zho_x_preferred":[
        "\u5929\u5d07\u6751"
    ],
    "wof:name":"Tianchongcun",
    "wof:placetype":"locality"
},
  "geometry": {"coordinates":[116.60086,30.48566],"type":"Point"}
}