{
  "type": "Feature",
  "properties": {
    "gn:admin1_code":"8.0",
    "gn:asciiname":"Dahuashu",
    "gn:country_code":"CN",
    "gn:dem":58,
    "gn:feature_class":"P",
    "gn:feature_code":"PPL",
    "gn:name":"Dahuashu",
    "gn:population":0,
    "gn:timezone":"Asia/Shanghai",
    "iso:country":"CN",
    "name:zho_x_preferred":[
        "\u5927\u6866\u6811"
    ],
    "wof:name":"Dahuashu",
    "wof:placetype":"locality"
},
  "geometry": {"coordinates":[132.27991,47.48603],"type":"Point"}
}