{
  "type": "Feature",
  "properties": {
    "gn:admin1_code":"9.0",
    "gn:asciiname":"Jiahe",
    "gn:country_code":"CN",
    "gn:dem":209,
    "gn:feature_class":"P",
    "gn:feature_code":"PPL",
    "gn:name":"Jiahe",
    "gn:population":0,
    "gn:timezone":"Asia/Shanghai",
    "iso:country":"CN",
    "name:zho_x_preferred":[
        "\u5939\u6cb3"
    ],
    "wof:name":"Jiahe",
    "wof:placetype":"locality"
},
  "geometry": {"coordinates":[112.40227,34.37458],"type":"Point"}
}