{
  "type": "Feature",
  "properties": {
    "gn:admin1_code":"15.0",
    "gn:asciiname":"Ridangyitang",
    "gn:country_code":"CN",
    "gn:dem":3558,
    "gn:feature_class":"P",
    "gn:feature_code":"PPL",
    "gn:name":"Ridangyitang",
    "gn:population":0,
    "gn:timezone":"Asia/Shanghai",
    "iso:country":"CN",
    "name:und_x_variant":[
        "\u65e5\u5f53\u4f0a\u5858"
    ],
    "wof:name":"Ridangyitang",
    "wof:placetype":"locality"
},
  "geometry": {"coordinates":[103.17688,35.04897],"type":"Point"}
}