{
  "type": "Feature",
  "properties": {
    "gn:admin1_code":"2.0",
    "gn:asciiname":"Santiaobu",
    "gn:country_code":"CN",
    "gn:dem":1006,
    "gn:feature_class":"P",
    "gn:feature_code":"PPL",
    "gn:name":"Santiaobu",
    "gn:population":0,
    "gn:timezone":"Asia/Shanghai",
    "iso:country":"CN",
    "name:zho_x_preferred":[
        "\u4e09\u6761\u6b65"
    ],
    "wof:name":"Santiaobu",
    "wof:placetype":"locality"
},
  "geometry": {"coordinates":[120.10209,27.96487],"type":"Point"}
}