{
  "type": "Feature",
  "properties": {
    "gn:admin1_code":"1.0",
    "gn:asciiname":"Yueyatangcun",
    "gn:country_code":"CN",
    "gn:dem":43,
    "gn:feature_class":"P",
    "gn:feature_code":"PPL",
    "gn:name":"Yueyatangcun",
    "gn:population":0,
    "gn:timezone":"Asia/Shanghai",
    "iso:country":"CN",
    "name:zho_x_preferred":[
        "\u6708\u7259\u5858\u6751"
    ],
    "wof:name":"Yueyatangcun",
    "wof:placetype":"locality"
},
  "geometry": {"coordinates":[116.64328999999999,31.48756],"type":"Point"}
}