{
  "type": "Feature",
  "properties": {
    "gn:admin1_code":"3.0",
    "gn:asciiname":"Yaoxia",
    "gn:country_code":"CN",
    "gn:dem":66,
    "gn:feature_class":"P",
    "gn:feature_code":"PPL",
    "gn:name":"Yaoxia",
    "gn:population":0,
    "gn:timezone":"Asia/Shanghai",
    "iso:country":"CN",
    "name:und_x_variant":[
        "\u7476\u4e0b"
    ],
    "wof:name":"Yaoxia",
    "wof:placetype":"locality"
},
  "geometry": {"coordinates":[115.02585000000001,28.09634],"type":"Point"}
}