{
  "type": "Feature",
  "properties": {
    "gn:admin1_code":"29.0",
    "gn:asciiname":"Pipo",
    "gn:country_code":"CN",
    "gn:dem":2028,
    "gn:feature_class":"P",
    "gn:feature_code":"PPL",
    "gn:name":"Pipo",
    "gn:population":0,
    "gn:timezone":"Asia/Shanghai",
    "iso:country":"CN",
    "name:deu_x_preferred":[
        "Pipo"
    ],
    "name:epo_x_preferred":[
        "Pipo"
    ],
    "name:fra_x_preferred":[
        "Pipo"
    ],
    "name:pol_x_preferred":[
        "Pipo"
    ],
    "name:por_x_preferred":[
        "Pipo"
    ],
    "name:spa_x_preferred":[
        "Pipo"
    ],
    "name:zho_x_preferred":[
        "\u8f9f\u5761"
    ],
    "wof:name":"Pipo",
    "wof:placetype":"locality"
},
  "geometry": {"coordinates":[101.012,24.4803],"type":"Point"}
}