{
  "type": "Feature",
  "properties": {
    "gn:admin1_code":"16.0",
    "gn:asciiname":"Lishanwei",
    "gn:country_code":"CN",
    "gn:dem":177,
    "gn:feature_class":"P",
    "gn:feature_code":"PPL",
    "gn:name":"Lishanwei",
    "gn:population":0,
    "gn:timezone":"Asia/Shanghai",
    "iso:country":"CN",
    "name:zho_x_preferred":[
        "\u4e3d\u5c71\u5c3e"
    ],
    "wof:name":"Lishanwei",
    "wof:placetype":"locality"
},
  "geometry": {"coordinates":[111.09399999999999,23.4989],"type":"Point"}
}