{
  "type": "Feature",
  "properties": {
    "gn:admin1_code":"24.0",
    "gn:asciiname":"Gaozhuang",
    "gn:country_code":"CN",
    "gn:dem":1041,
    "gn:feature_class":"P",
    "gn:feature_code":"PPL",
    "gn:name":"Gaozhuang",
    "gn:population":0,
    "gn:timezone":"Asia/Shanghai",
    "iso:country":"CN",
    "name:und_x_variant":[
        "\u9ad8\u5e84"
    ],
    "wof:name":"Gaozhuang",
    "wof:placetype":"locality"
},
  "geometry": {"coordinates":[112.70805,39.28974],"type":"Point"}
}