{
  "type": "Feature",
  "properties": {
    "gn:admin1_code":"20.0",
    "gn:asciiname":"Yanyazi",
    "gn:country_code":"CN",
    "gn:dem":1518,
    "gn:feature_class":"P",
    "gn:feature_code":"PPL",
    "gn:name":"Yanyazi",
    "gn:population":0,
    "gn:timezone":"Asia/Shanghai",
    "iso:country":"CN",
    "name:und_x_variant":[
        "\u9633\u5d16\u5b50"
    ],
    "wof:name":"Yanyazi",
    "wof:placetype":"locality"
},
  "geometry": {"coordinates":[111.75594,39.68386],"type":"Point"}
}