{
  "type": "Feature",
  "properties": {
    "gn:admin1_code":"12.0",
    "gn:asciiname":"Shangniejiawan",
    "gn:country_code":"CN",
    "gn:dem":31,
    "gn:feature_class":"P",
    "gn:feature_code":"PPL",
    "gn:name":"Shangniejiawan",
    "gn:population":0,
    "gn:timezone":"Asia/Shanghai",
    "iso:country":"CN",
    "name:zho_x_preferred":[
        "\u4e0a\u8042\u5bb6\u6e7e"
    ],
    "wof:name":"Shangniejiawan",
    "wof:placetype":"locality"
},
  "geometry": {"coordinates":[112.90234,30.01812],"type":"Point"}
}