{
  "type": "Feature",
  "properties": {
    "gn:admin1_code":"29.0",
    "gn:asciiname":"Baicaiwang",
    "gn:country_code":"CN",
    "gn:dem":1674,
    "gn:feature_class":"P",
    "gn:feature_code":"PPL",
    "gn:name":"Baicaiwang",
    "gn:population":0,
    "gn:timezone":"Asia/Shanghai",
    "iso:country":"CN",
    "name:zho_x_preferred":[
        "\u767e\u83dc\u65fa"
    ],
    "wof:name":"Baicaiwang",
    "wof:placetype":"locality"
},
  "geometry": {"coordinates":[98.69159999999999,27.854],"type":"Point"}
}