{
  "type": "Feature",
  "properties": {
    "gn:admin1_code":"16",
    "gn:asciiname":"Nanhualing",
    "gn:country_code":"CN",
    "gn:dem":242,
    "gn:feature_class":"P",
    "gn:feature_code":"PPL",
    "gn:name":"Nanhualing",
    "gn:population":0,
    "gn:timezone":"Asia/Shanghai",
    "iso:country":"CN",
    "name:zho_x_preferred":[
        "\u5357\u82b1\u5cad"
    ],
    "wof:name":"Nanhualing",
    "wof:placetype":"locality"
},
  "geometry": {"coordinates":[110.64700000000001,25.6624],"type":"Point"}
}