{
  "type": "Feature",
  "properties": {
    "gn:admin1_code":"07",
    "gn:asciiname":"Hushan",
    "gn:country_code":"CN",
    "gn:dem":544,
    "gn:feature_class":"P",
    "gn:feature_code":"PPLA4",
    "gn:name":"Hushan",
    "gn:population":0,
    "gn:timezone":"Asia/Shanghai",
    "iso:country":"CN",
    "name:und_x_variant":[
        "Sanlaizhou",
        "San-lai-chou",
        "Hushan",
        "Hushan Xiang"
    ],
    "name:zho_x_preferred":[
        "\u6e56\u5c71"
    ],
    "name:zho_x_variant":[
        "\u4e09\u6765\u5dde",
        "\u6e56\u5c71\u4e61"
    ],
    "wof:name":"Hushan",
    "wof:placetype":"locality"
},
  "geometry": {"coordinates":[116.87357,24.47026],"type":"Point"}
}