{
  "type": "Feature",
  "properties": {
    "gn:admin1_code":"31",
    "gn:asciiname":"Duoge",
    "gn:country_code":"CN",
    "gn:dem":9,
    "gn:feature_class":"P",
    "gn:feature_code":"PPL",
    "gn:name":"Duoge",
    "gn:population":0,
    "gn:timezone":"Asia/Shanghai",
    "iso:country":"CN",
    "name:und_x_variant":[
        "\u591a\u683c"
    ],
    "wof:name":"Duoge",
    "wof:placetype":"locality"
},
  "geometry": {"coordinates":[110.542,19.0582],"type":"Point"}
}