{
  "type": "Feature",
  "properties": {
    "gn:admin1_code":"3.0",
    "gn:asciiname":"Xingfucun",
    "gn:country_code":"CN",
    "gn:dem":52,
    "gn:feature_class":"P",
    "gn:feature_code":"PPL",
    "gn:name":"Xingfucun",
    "gn:population":0,
    "gn:timezone":"Asia/Shanghai",
    "iso:country":"CN",
    "name:und_x_variant":[
        "\u5e78\u798f\u6751"
    ],
    "wof:name":"Xingfucun",
    "wof:placetype":"locality"
},
  "geometry": {"coordinates":[115.69929999999999,28.69298],"type":"Point"}
}