{
  "type": "Feature",
  "properties": {
    "gn:admin1_code":"10",
    "gn:asciiname":"Houdasong",
    "gn:country_code":"CN",
    "gn:dem":39,
    "gn:feature_class":"P",
    "gn:feature_code":"PPL",
    "gn:name":"Houdasong",
    "gn:population":0,
    "gn:timezone":"Asia/Shanghai",
    "iso:country":"CN",
    "name:zho_x_preferred":[
        "\u540e\u5927\u5b8b"
    ],
    "wof:name":"Houdasong",
    "wof:placetype":"locality"
},
  "geometry": {"coordinates":[114.71599999999999,37.1107],"type":"Point"}
}