{
  "type": "Feature",
  "properties": {
    "gn:admin1_code":"18",
    "gn:asciiname":"Lingyang",
    "gn:country_code":"CN",
    "gn:dem":766,
    "gn:feature_class":"P",
    "gn:feature_code":"PPL",
    "gn:name":"Lingyang",
    "gn:population":0,
    "gn:timezone":"Asia/Shanghai",
    "iso:country":"CN",
    "name:deu_x_preferred":[
        "Lingyang"
    ],
    "wof:name":"Lingyang",
    "wof:placetype":"locality"
},
  "geometry": {"coordinates":[106.91667,25.46667],"type":"Point"}
}