{
  "type": "Feature",
  "properties": {
    "gn:admin1_code":"8.0",
    "gn:asciiname":"Nanyangcun",
    "gn:country_code":"CN",
    "gn:dem":281,
    "gn:feature_class":"P",
    "gn:feature_code":"PPL",
    "gn:name":"Nanyangcun",
    "gn:population":0,
    "gn:timezone":"Asia/Shanghai",
    "iso:country":"CN",
    "name:zho_x_preferred":[
        "\u5357\u9633\u6751"
    ],
    "wof:name":"Nanyangcun",
    "wof:placetype":"locality"
},
  "geometry": {"coordinates":[129.04102,44.16824],"type":"Point"}
}