{
  "type": "Feature",
  "properties": {
    "gn:admin1_code":"18.0",
    "gn:asciiname":"Shuizouping",
    "gn:country_code":"CN",
    "gn:dem":595,
    "gn:feature_class":"P",
    "gn:feature_code":"PPL",
    "gn:name":"Shuizouping",
    "gn:population":0,
    "gn:timezone":"Asia/Shanghai",
    "iso:country":"CN",
    "name:zho_x_preferred":[
        "\u6c34\u8d70\u576a"
    ],
    "wof:name":"Shuizouping",
    "wof:placetype":"locality"
},
  "geometry": {"coordinates":[109.259,27.9532],"type":"Point"}
}