{
  "type": "Feature",
  "properties": {
    "gn:admin1_code":"9.0",
    "gn:asciiname":"Dongyue",
    "gn:country_code":"CN",
    "gn:dem":48,
    "gn:feature_class":"P",
    "gn:feature_code":"PPL",
    "gn:name":"Dongyue",
    "gn:population":0,
    "gn:timezone":"Asia/Shanghai",
    "iso:country":"CN",
    "name:ceb_x_preferred":[
        "Dongyue"
    ],
    "name:swe_x_preferred":[
        "Dongyue"
    ],
    "name:zho_x_preferred":[
        "\u4e1c\u5cb3"
    ],
    "wof:name":"Dongyue",
    "wof:placetype":"locality"
},
  "geometry": {"coordinates":[115.83629999999999,31.96244],"type":"Point"}
}