{
  "type": "Feature",
  "properties": {
    "gn:admin1_code":"4.0",
    "gn:asciiname":"Longtian Wuzu",
    "gn:country_code":"CN",
    "gn:dem":5,
    "gn:feature_class":"P",
    "gn:feature_code":"PPLF",
    "gn:name":"Longtian Wuzu",
    "gn:population":0,
    "gn:timezone":"Asia/Shanghai",
    "iso:country":"CN",
    "name:und_x_variant":[
        "\u9f99\u7530\u4e94\u7ec4"
    ],
    "name:zho_x_preferred":[
        "\u9f99\u7530\u4e94\u7ec4"
    ],
    "wof:name":"Longtian Wuzu",
    "wof:placetype":"locality"
},
  "geometry": {"coordinates":[120.98614999999999,31.91064],"type":"Point"}
}