{
  "type": "Feature",
  "properties": {
    "gn:admin1_code":"24.0",
    "gn:asciiname":"Xialangjian",
    "gn:country_code":"CN",
    "gn:dem":1117,
    "gn:feature_class":"P",
    "gn:feature_code":"PPL",
    "gn:name":"Xialangjian",
    "gn:population":0,
    "gn:timezone":"Asia/Shanghai",
    "iso:country":"CN",
    "name:und_x_variant":[
        "\u4e0b\u6d6a\u6da7"
    ],
    "name:zho_x_preferred":[
        "\u4e0b\u6d6a\u6da7"
    ],
    "wof:name":"Xialangjian",
    "wof:placetype":"locality"
},
  "geometry": {"coordinates":[113.61686,39.29766],"type":"Point"}
}