{
  "type": "Feature",
  "properties": {
    "gn:admin1_code":"29.0",
    "gn:asciiname":"Zhedu",
    "gn:country_code":"CN",
    "gn:dem":1505,
    "gn:feature_class":"P",
    "gn:feature_code":"PPL",
    "gn:name":"Zhedu",
    "gn:population":0,
    "gn:timezone":"Asia/Shanghai",
    "iso:country":"CN",
    "name:zho_x_preferred":[
        "\u6d59\u90fd"
    ],
    "wof:name":"Zhedu",
    "wof:placetype":"locality"
},
  "geometry": {"coordinates":[104.517,24.9729],"type":"Point"}
}