{
  "type": "Feature",
  "properties": {
    "gn:admin1_code":"2.0",
    "gn:asciiname":"Xiaodongyuan",
    "gn:country_code":"CN",
    "gn:dem":757,
    "gn:feature_class":"P",
    "gn:feature_code":"PPL",
    "gn:name":"Xiaodongyuan",
    "gn:population":0,
    "gn:timezone":"Asia/Shanghai",
    "iso:country":"CN",
    "name:zho_x_preferred":[
        "\u5c0f\u6d1e\u6e90"
    ],
    "wof:name":"Xiaodongyuan",
    "wof:placetype":"locality"
},
  "geometry": {"coordinates":[118.90979,28.47032],"type":"Point"}
}