{
  "type": "Feature",
  "properties": {
    "gn:admin1_code":"32.0",
    "gn:asciiname":"Buzhongcun",
    "gn:country_code":"CN",
    "gn:dem":2904,
    "gn:feature_class":"P",
    "gn:feature_code":"PPL",
    "gn:name":"Buzhongcun",
    "gn:population":0,
    "gn:timezone":"Asia/Shanghai",
    "iso:country":"CN",
    "name:zho_x_preferred":[
        "\u5e03\u4e2d\u6751"
    ],
    "wof:name":"Buzhongcun",
    "wof:placetype":"locality"
},
  "geometry": {"coordinates":[99.1602,28.7612],"type":"Point"}
}