{
  "type": "Feature",
  "properties": {
    "gn:admin1_code":"19.0",
    "gn:asciiname":"Shanzui",
    "gn:country_code":"CN",
    "gn:dem":80,
    "gn:feature_class":"P",
    "gn:feature_code":"PPL",
    "gn:name":"Shanzui",
    "gn:population":0,
    "gn:timezone":"Asia/Shanghai",
    "iso:country":"CN",
    "name:und_x_variant":[
        "\u5c71\u5634"
    ],
    "wof:name":"Shanzui",
    "wof:placetype":"locality"
},
  "geometry": {"coordinates":[122.25261999999999,40.09641],"type":"Point"}
}