{
  "type": "Feature",
  "properties": {
    "gn:admin1_code":"09",
    "gn:asciiname":"Dachai",
    "gn:country_code":"CN",
    "gn:dem":60,
    "gn:feature_class":"P",
    "gn:feature_code":"PPL",
    "gn:name":"Dachai",
    "gn:population":0,
    "gn:timezone":"Asia/Shanghai",
    "iso:country":"CN",
    "name:und_x_variant":[
        "Ta-chai-ts\u2019un",
        "Dachai"
    ],
    "name:zho_x_preferred":[
        "\u5927\u67f4"
    ],
    "wof:name":"Dachai",
    "wof:placetype":"locality"
},
  "geometry": {"coordinates":[114.82170000000001,35.77605],"type":"Point"}
}