{
  "type": "Feature",
  "properties": {
    "gn:admin1_code":"13",
    "gn:asciiname":"Aletunqi",
    "gn:country_code":"CN",
    "gn:dem":1252,
    "gn:feature_class":"P",
    "gn:feature_code":"PPL",
    "gn:name":"Aletunqi",
    "gn:population":0,
    "gn:timezone":"Asia/Shanghai",
    "iso:country":"CN",
    "name:und_x_variant":[
        "\u963f\u52d2\u541e\u5176"
    ],
    "wof:name":"Aletunqi",
    "wof:placetype":"locality"
},
  "geometry": {"coordinates":[77.35578000000002,38.22548],"type":"Point"}
}