{
  "type": "Feature",
  "properties": {
    "gn:admin1_code":"33.0",
    "gn:asciiname":"Jiayuan",
    "gn:country_code":"CN",
    "gn:dem":956,
    "gn:feature_class":"P",
    "gn:feature_code":"PPL",
    "gn:name":"Jiayuan",
    "gn:population":0,
    "gn:timezone":"Asia/Shanghai",
    "iso:country":"CN",
    "name:zho_x_preferred":[
        "\u5bb6\u56ed"
    ],
    "wof:name":"Jiayuan",
    "wof:placetype":"locality"
},
  "geometry": {"coordinates":[108.81041999999999,31.86234],"type":"Point"}
}