{
  "type": "Feature",
  "properties": {
    "gn:admin1_code":"29.0",
    "gn:asciiname":"Ludeke",
    "gn:country_code":"CN",
    "gn:dem":1572,
    "gn:feature_class":"P",
    "gn:feature_code":"PPL",
    "gn:name":"Ludeke",
    "gn:population":0,
    "gn:timezone":"Asia/Shanghai",
    "iso:country":"CN",
    "name:zho_x_preferred":[
        "\u9c81\u5f97\u514b"
    ],
    "wof:name":"Ludeke",
    "wof:placetype":"locality"
},
  "geometry": {"coordinates":[104.004,23.4624],"type":"Point"}
}