{
  "type": "Feature",
  "properties": {
    "gn:admin1_code":"19.0",
    "gn:asciiname":"Zhaogujiazi",
    "gn:country_code":"CN",
    "gn:dem":84,
    "gn:feature_class":"P",
    "gn:feature_code":"PPL",
    "gn:name":"Zhaogujiazi",
    "gn:population":0,
    "gn:timezone":"Asia/Shanghai",
    "iso:country":"CN",
    "name:zho_x_preferred":[
        "\u8d75\u5b64\u5bb6\u5b50"
    ],
    "wof:name":"Zhaogujiazi",
    "wof:placetype":"locality"
},
  "geometry": {"coordinates":[120.00842,40.21111],"type":"Point"}
}