{
  "type": "Feature",
  "properties": {
    "gn:admin1_code":"10",
    "gn:asciiname":"Wangchang",
    "gn:country_code":"CN",
    "gn:dem":252,
    "gn:feature_class":"P",
    "gn:feature_code":"PPL",
    "gn:name":"Wangchang",
    "gn:population":0,
    "gn:timezone":"Asia/Shanghai",
    "iso:country":"CN",
    "name:und_x_variant":[
        "Wang-chiang",
        "Wangchang"
    ],
    "name:zho_x_preferred":[
        "\u738b\u5382"
    ],
    "wof:name":"Wangchang",
    "wof:placetype":"locality"
},
  "geometry": {"coordinates":[118.71593,40.41612],"type":"Point"}
}