{
  "type": "Feature",
  "properties": {
    "gn:admin1_code":"10",
    "gn:asciiname":"Guoguantun",
    "gn:country_code":"CN",
    "gn:dem":21,
    "gn:feature_class":"P",
    "gn:feature_code":"PPL",
    "gn:name":"Guoguantun",
    "gn:population":0,
    "gn:timezone":"Asia/Shanghai",
    "iso:country":"CN",
    "name:zho_x_preferred":[
        "\u90ed\u5b98\u5c6f"
    ],
    "wof:name":"Guoguantun",
    "wof:placetype":"locality"
},
  "geometry": {"coordinates":[117.99487000000001,39.80881],"type":"Point"}
}