{
  "type": "Feature",
  "properties": {
    "gn:admin1_code":"3.0",
    "gn:asciiname":"Meishan",
    "gn:country_code":"CN",
    "gn:dem":37,
    "gn:feature_class":"P",
    "gn:feature_code":"PPL",
    "gn:name":"Meishan",
    "gn:population":0,
    "gn:timezone":"Asia/Shanghai",
    "iso:country":"CN",
    "name:ara_x_preferred":[
        "\u0645\u064a\u0634\u0627\u0646"
    ],
    "name:cdo_x_preferred":[
        "M\u00ec-s\u0103ng"
    ],
    "name:ceb_x_preferred":[
        "Meishan Shi"
    ],
    "name:ces_x_preferred":[
        "Mej-\u0161an"
    ],
    "name:dan_x_preferred":[
        "Meishan"
    ],
    "name:deu_x_preferred":[
        "Meishan"
    ],
    "name:eus_x_preferred":[
        "Meishan"
    ],
    "name:fas_x_preferred":[
        "\u0645\u0627\u06cc\u0634\u0627\u0646"
    ],
    "name:fin_x_preferred":[
        "Meishan"
    ],
    "name:fra_x_preferred":[
        "Meishan"
    ],
    "name:ita_x_preferred":[
        "Meishan"
    ],
    "name:jpn_x_preferred":[
        "\u7709\u5c71\u5e02"
    ],
    "name:kik_x_preferred":[
        "Meishan"
    ],
    "name:kor_x_preferred":[
        "\uba54\uc774\uc0b0\uc2dc"
    ],
    "name:nld_x_preferred":[
        "Meishan"
    ],
    "name:nno_x_preferred":[
        "Meishan"
    ],
    "name:nor_x_preferred":[
        "Meishan"
    ],
    "name:pol_x_preferred":[
        "Meishan"
    ],
    "name:rus_x_preferred":[
        "\u041c\u044d\u0439\u0448\u0430\u043d\u044c"
    ],
    "name:spa_x_preferred":[
        "Meish\u00e1n"
    ],
    "name:swe_x_preferred":[
        "Meishan"
    ],
    "name:tur_x_preferred":[
        "Meishan"
    ],
    "name:und_x_variant":[
        "\u7709\u5c71"
    ],
    "name:urd_x_preferred":[
        "\u0645\u06cc\u0626\u0634\u0627\u0646"
    ],
    "name:vie_x_preferred":[
        "Mi S\u01a1n"
    ],
    "name:zho_x_preferred":[
        "\u7709\u5c71\u5e02"
    ],
    "wof:name":"Meishan",
    "wof:placetype":"locality"
},
  "geometry": {"coordinates":[115.50714000000001,28.72896],"type":"Point"}
}