{
  "type": "Feature",
  "properties": {
    "gn:admin1_code":"3.0",
    "gn:asciiname":"Meishan",
    "gn:country_code":"CN",
    "gn:dem":37,
    "gn:feature_class":"P",
    "gn:feature_code":"PPL",
    "gn:name":"Meishan",
    "gn:population":0,
    "gn:timezone":"Asia/Shanghai",
    "iso:country":"CN",
    "name:und_x_variant":[
        "\u7709\u5c71"
    ],
    "wof:name":"Meishan",
    "wof:placetype":"locality"
},
  "geometry": {"coordinates":[115.50714000000001,28.72896],"type":"Point"}
}