{
  "type": "Feature",
  "properties": {
    "gn:admin1_code":"12.0",
    "gn:asciiname":"Xiangjiadaping",
    "gn:country_code":"CN",
    "gn:dem":1475,
    "gn:feature_class":"P",
    "gn:feature_code":"PPL",
    "gn:name":"Xiangjiadaping",
    "gn:population":0,
    "gn:timezone":"Asia/Shanghai",
    "iso:country":"CN",
    "name:zho_x_preferred":[
        "\u5411\u5bb6\u5927\u576a"
    ],
    "wof:name":"Xiangjiadaping",
    "wof:placetype":"locality"
},
  "geometry": {"coordinates":[110.96941,31.35822000000001],"type":"Point"}
}