{
  "type": "Feature",
  "properties": {
    "gn:admin1_code":"25",
    "gn:asciiname":"Donghexiyingcun",
    "gn:country_code":"CN",
    "gn:dem":4,
    "gn:feature_class":"P",
    "gn:feature_code":"PPL",
    "gn:name":"Donghexiyingcun",
    "gn:population":0,
    "gn:timezone":"Asia/Shanghai",
    "iso:country":"CN",
    "name:und_x_variant":[
        "Hexiying"
    ],
    "name:zho_x_preferred":[
        "\u4e1c\u6cb3\u897f\u8425\u6751"
    ],
    "wof:name":"Donghexiyingcun",
    "wof:placetype":"locality"
},
  "geometry": {"coordinates":[117.72917,37.74639000000001],"type":"Point"}
}