{
  "type": "Feature",
  "properties": {
    "gn:admin1_code":"26.0",
    "gn:asciiname":"Sidicun",
    "gn:country_code":"CN",
    "gn:dem":457,
    "gn:feature_class":"P",
    "gn:feature_code":"PPL",
    "gn:name":"Sidicun",
    "gn:population":0,
    "gn:timezone":"Asia/Shanghai",
    "iso:country":"CN",
    "name:zho_x_preferred":[
        "\u5bfa\u5e95\u6751"
    ],
    "wof:name":"Sidicun",
    "wof:placetype":"locality"
},
  "geometry": {"coordinates":[110.34475,34.51336],"type":"Point"}
}