{
  "type": "Feature",
  "properties": {
    "gn:admin1_code":"32",
    "gn:asciiname":"Gaotizi",
    "gn:country_code":"CN",
    "gn:dem":329,
    "gn:feature_class":"P",
    "gn:feature_code":"PPL",
    "gn:name":"Gaotizi",
    "gn:population":0,
    "gn:timezone":"Asia/Shanghai",
    "iso:country":"CN",
    "name:zho_x_preferred":[
        "\u9ad8\u68af\u5b50"
    ],
    "wof:name":"Gaotizi",
    "wof:placetype":"locality"
},
  "geometry": {"coordinates":[106.39642000000001,30.32996],"type":"Point"}
}