{
  "type": "Feature",
  "properties": {
    "gn:admin1_code":"12.0",
    "gn:asciiname":"Lijia Dawan",
    "gn:country_code":"CN",
    "gn:dem":57,
    "gn:feature_class":"P",
    "gn:feature_code":"PPL",
    "gn:name":"Lijia Dawan",
    "gn:population":0,
    "gn:timezone":"Asia/Shanghai",
    "iso:country":"CN",
    "name:zho_x_preferred":[
        "\u674e\u5bb6\u5927\u6e7e"
    ],
    "wof:name":"Lijia Dawan",
    "wof:placetype":"locality"
},
  "geometry": {"coordinates":[112.65067999999999,31.04278],"type":"Point"}
}