{
  "type": "Feature",
  "properties": {
    "gn:admin1_code":"21.0",
    "gn:asciiname":"Liwazi",
    "gn:country_code":"CN",
    "gn:dem":1719,
    "gn:feature_class":"P",
    "gn:feature_code":"PPL",
    "gn:name":"Liwazi",
    "gn:population":0,
    "gn:timezone":"Asia/Shanghai",
    "iso:country":"CN",
    "name:zho_x_preferred":[
        "\u674e\u6d3c\u5b50"
    ],
    "wof:name":"Liwazi",
    "wof:placetype":"locality"
},
  "geometry": {"coordinates":[106.24742999999999,36.88211],"type":"Point"}
}