{
  "type": "Feature",
  "properties": {
    "gn:admin1_code":"12.0",
    "gn:asciiname":"Tangxia",
    "gn:country_code":"CN",
    "gn:dem":91,
    "gn:feature_class":"P",
    "gn:feature_code":"PPL",
    "gn:name":"Tangxia",
    "gn:population":0,
    "gn:timezone":"Asia/Shanghai",
    "iso:country":"CN",
    "name:zho_x_preferred":[
        "Tangxia"
    ],
    "name:zho_x_variant":[
        "\u5858\u4e0b"
    ],
    "wof:name":"Tangxia",
    "wof:placetype":"locality"
},
  "geometry": {"coordinates":[114.73053,29.87085],"type":"Point"}
}