{
  "type": "Feature",
  "properties": {
    "gn:admin1_code":"30.0",
    "gn:asciiname":"Shizhuanwu",
    "gn:country_code":"CN",
    "gn:dem":428,
    "gn:feature_class":"P",
    "gn:feature_code":"PPL",
    "gn:name":"Shizhuanwu",
    "gn:population":0,
    "gn:timezone":"Asia/Shanghai",
    "iso:country":"CN",
    "name:und_x_variant":[
        "\u77f3\u7816\u5c4b"
    ],
    "name:zho_x_preferred":[
        "\u77f3\u7816\u5c4b"
    ],
    "wof:name":"Shizhuanwu",
    "wof:placetype":"locality"
},
  "geometry": {"coordinates":[115.37392,23.78702],"type":"Point"}
}