{
  "type": "Feature",
  "properties": {
    "gn:admin1_code":"7",
    "gn:asciiname":"Yuyao",
    "gn:country_code":"CN",
    "gn:dem":13,
    "gn:feature_class":"P",
    "gn:feature_code":"PPL",
    "gn:name":"Yuyao",
    "gn:population":0,
    "gn:timezone":"Asia/Shanghai",
    "iso:country":"CN",
    "name:ceb_x_preferred":[
        "Yuyao"
    ],
    "name:deu_x_preferred":[
        "Yuyao"
    ],
    "name:fas_x_preferred":[
        "\u06cc\u0648\u06cc\u0627\u0626\u0648"
    ],
    "name:fra_x_preferred":[
        "Yuyao"
    ],
    "name:hak_x_preferred":[
        "Y\u00ec-y\u00e0u-s\u1e73"
    ],
    "name:ita_x_preferred":[
        "Yuyao"
    ],
    "name:jpn_x_preferred":[
        "\u4f59\u59da\u5e02"
    ],
    "name:kik_x_preferred":[
        "Yuyao"
    ],
    "name:kor_x_preferred":[
        "\uc704\uc57c\uc624\uc2dc"
    ],
    "name:mlg_x_preferred":[
        "Yuyao"
    ],
    "name:nld_x_preferred":[
        "Yuyao"
    ],
    "name:nno_x_preferred":[
        "Yuyao"
    ],
    "name:nor_x_preferred":[
        "Yuyao"
    ],
    "name:rus_x_preferred":[
        "\u042e\u0439\u044f\u043e"
    ],
    "name:spa_x_preferred":[
        "Yuyao"
    ],
    "name:swe_x_preferred":[
        "Yuyao"
    ],
    "name:tgl_x_preferred":[
        "Yuyao"
    ],
    "name:urd_x_preferred":[
        "\u06cc\u0648\u06cc\u0648"
    ],
    "name:vie_x_preferred":[
        "D\u01b0 Di\u00eau"
    ],
    "name:war_x_preferred":[
        "Yuyao"
    ],
    "name:wuu_x_preferred":[
        "\u4f59\u59da\u5e02"
    ],
    "name:zho_x_preferred":[
        "\u4f59\u59da\u5e02"
    ],
    "wof:name":"Yuyao",
    "wof:placetype":"locality"
},
  "geometry": {"coordinates":[119.73972000000001,25.60389],"type":"Point"}
}