{
  "type": "Feature",
  "properties": {
    "gn:admin1_code":"26.0",
    "gn:asciiname":"Hezishang",
    "gn:country_code":"CN",
    "gn:dem":1346,
    "gn:feature_class":"P",
    "gn:feature_code":"PPL",
    "gn:name":"Hezishang",
    "gn:population":0,
    "gn:timezone":"Asia/Shanghai",
    "iso:country":"CN",
    "name:zho_x_preferred":[
        "\u5408\u5b50\u4e0a"
    ],
    "wof:name":"Hezishang",
    "wof:placetype":"locality"
},
  "geometry": {"coordinates":[108.53839000000001,33.95389],"type":"Point"}
}