{
  "type": "Feature",
  "properties": {
    "gn:admin1_code":"1.0",
    "gn:asciiname":"Chengzicun",
    "gn:country_code":"CN",
    "gn:dem":30,
    "gn:feature_class":"P",
    "gn:feature_code":"PPL",
    "gn:name":"Chengzicun",
    "gn:population":0,
    "gn:timezone":"Asia/Shanghai",
    "iso:country":"CN",
    "name:zho_x_preferred":[
        "\u57ce\u5b5c\u6751"
    ],
    "wof:name":"Chengzicun",
    "wof:placetype":"locality"
},
  "geometry": {"coordinates":[117.15752999999999,33.88723],"type":"Point"}
}