{
  "type": "Feature",
  "properties": {
    "gn:admin1_code":"7.0",
    "gn:asciiname":"Taiwei",
    "gn:country_code":"CN",
    "gn:dem":178,
    "gn:feature_class":"P",
    "gn:feature_code":"PPL",
    "gn:name":"Taiwei",
    "gn:population":0,
    "gn:timezone":"Asia/Shanghai",
    "iso:country":"CN",
    "name:zho_x_preferred":[
        "\u53f0\u5c3e"
    ],
    "wof:name":"Taiwei",
    "wof:placetype":"locality"
},
  "geometry": {"coordinates":[118.34529999999999,27.21215],"type":"Point"}
}