{
  "type": "Feature",
  "properties": {
    "gn:admin1_code":"32.0",
    "gn:asciiname":"Yide'amo",
    "gn:country_code":"CN",
    "gn:dem":2454,
    "gn:feature_class":"P",
    "gn:feature_code":"PPL",
    "gn:name":"Yide\u2019amo",
    "gn:population":0,
    "gn:timezone":"Asia/Shanghai",
    "iso:country":"CN",
    "name:und_x_variant":[
        "Yide\u2019amo"
    ],
    "name:zho_x_preferred":[
        "\u8863\u5fb7\u963f\u83ab"
    ],
    "wof:name":"Yide'amo",
    "wof:placetype":"locality"
},
  "geometry": {"coordinates":[103.149,28.6127],"type":"Point"}
}