{
  "type": "Feature",
  "properties": {
    "gn:admin1_code":"19.0",
    "gn:asciiname":"Shentanggou",
    "gn:country_code":"CN",
    "gn:dem":295,
    "gn:feature_class":"P",
    "gn:feature_code":"PPL",
    "gn:name":"Shentanggou",
    "gn:population":0,
    "gn:timezone":"Asia/Shanghai",
    "iso:country":"CN",
    "name:und_x_variant":[
        "\u6c88\u5858\u6c9f"
    ],
    "name:zho_x_preferred":[
        "\u6c88\u5858\u6c9f"
    ],
    "wof:name":"Shentanggou",
    "wof:placetype":"locality"
},
  "geometry": {"coordinates":[123.962,42.0191],"type":"Point"}
}