{
  "type": "Feature",
  "properties": {
    "gn:admin1_code":"3.0",
    "gn:asciiname":"Songjiafan",
    "gn:country_code":"CN",
    "gn:dem":94,
    "gn:feature_class":"P",
    "gn:feature_code":"PPL",
    "gn:name":"Songjiafan",
    "gn:population":0,
    "gn:timezone":"Asia/Shanghai",
    "iso:country":"CN",
    "name:und_x_variant":[
        "\u5b8b\u5bb6\u7548"
    ],
    "wof:name":"Songjiafan",
    "wof:placetype":"locality"
},
  "geometry": {"coordinates":[115.29589,27.11265],"type":"Point"}
}