{
  "type": "Feature",
  "properties": {
    "gn:admin1_code":"19.0",
    "gn:asciiname":"Kaoshantun",
    "gn:country_code":"CN",
    "gn:dem":59,
    "gn:feature_class":"P",
    "gn:feature_code":"PPL",
    "gn:name":"Kaoshantun",
    "gn:population":0,
    "gn:timezone":"Asia/Shanghai",
    "iso:country":"CN",
    "name:und_x_variant":[
        "\u9760\u5c71\u5c6f"
    ],
    "name:zho_x_preferred":[
        "\u9760\u5c71\u5c6f"
    ],
    "wof:name":"Kaoshantun",
    "wof:placetype":"locality"
},
  "geometry": {"coordinates":[122.98712999999999,42.24476],"type":"Point"}
}