{
  "type": "Feature",
  "properties": {
    "gn:admin1_code":"29.0",
    "gn:asciiname":"Qingshuigou Dongcun",
    "gn:country_code":"CN",
    "gn:dem":2432,
    "gn:feature_class":"P",
    "gn:feature_code":"PPL",
    "gn:name":"Qingshuigou Dongcun",
    "gn:population":0,
    "gn:timezone":"Asia/Shanghai",
    "iso:country":"CN",
    "name:zho_x_preferred":[
        "\u6e05\u6c34\u6c9f\u4e1c\u6751"
    ],
    "wof:name":"Qingshuigou Dongcun",
    "wof:placetype":"locality"
},
  "geometry": {"coordinates":[100.343,25.4144],"type":"Point"}
}