{
  "type": "Feature",
  "properties": {
    "gn:admin1_code":"18",
    "gn:asciiname":"Mojian",
    "gn:country_code":"CN",
    "gn:dem":863,
    "gn:feature_class":"P",
    "gn:feature_code":"PPL",
    "gn:name":"Mojian",
    "gn:population":0,
    "gn:timezone":"Asia/Shanghai",
    "iso:country":"CN",
    "name:zho_x_preferred":[
        "\u62b9\u5c16"
    ],
    "wof:name":"Mojian",
    "wof:placetype":"locality"
},
  "geometry": {"coordinates":[106.92400000000001,25.5928],"type":"Point"}
}