{
  "type": "Feature",
  "properties": {
    "gn:admin1_code":"26.0",
    "gn:asciiname":"Wenhecun",
    "gn:country_code":"CN",
    "gn:dem":1017,
    "gn:feature_class":"P",
    "gn:feature_code":"PPL",
    "gn:name":"Wenhecun",
    "gn:population":0,
    "gn:timezone":"Asia/Shanghai",
    "iso:country":"CN",
    "name:zho_x_preferred":[
        "\u6e29\u6cb3\u6751"
    ],
    "wof:name":"Wenhecun",
    "wof:placetype":"locality"
},
  "geometry": {"coordinates":[106.80076,34.92081],"type":"Point"}
}