{
  "type": "Feature",
  "properties": {
    "gn:admin1_code":"14.0",
    "gn:asciiname":"Wangda",
    "gn:country_code":"CN",
    "gn:dem":3806,
    "gn:feature_class":"P",
    "gn:feature_code":"PPLA3",
    "gn:name":"Wangda",
    "gn:population":0,
    "gn:timezone":"Asia/Urumqi",
    "iso:country":"CN",
    "name:bod_x_preferred":[
        "Wangda"
    ],
    "name:bod_x_variant":[
        "Wangda Zhen"
    ],
    "name:msa_x_preferred":[
        "Wangda"
    ],
    "name:und_x_variant":[
        "Tso-kung",
        "Wang-ta",
        "Zogang",
        "Wangda"
    ],
    "name:zho_x_preferred":[
        "\u6c6a\u8fbe"
    ],
    "name:zho_x_variant":[
        "Zuogong Xian",
        "\u5de6\u8d21\u53bf",
        "\u65fa\u8fbe",
        "\u65fa\u8fbe\u9547"
    ],
    "wof:name":"Wangda",
    "wof:placetype":"locality"
},
  "geometry": {"coordinates":[97.83736,29.67445],"type":"Point"}
}