{
  "type": "Feature",
  "properties": {
    "gn:admin1_code":"21.0",
    "gn:asciiname":"Zuandongzi",
    "gn:country_code":"CN",
    "gn:dem":1781,
    "gn:feature_class":"P",
    "gn:feature_code":"PPL",
    "gn:name":"Zuandongzi",
    "gn:population":0,
    "gn:timezone":"Asia/Shanghai",
    "iso:country":"CN",
    "name:zho_x_preferred":[
        "\u94bb\u6d1e\u5b50"
    ],
    "wof:name":"Zuandongzi",
    "wof:placetype":"locality"
},
  "geometry": {"coordinates":[104.99299999999999,37.2026],"type":"Point"}
}