{
  "type": "Feature",
  "properties": {
    "gn:admin1_code":"05",
    "gn:asciiname":"Anshi",
    "gn:cc2":"CN",
    "gn:country_code":"CN",
    "gn:dem":293,
    "gn:feature_class":"P",
    "gn:feature_code":"PPL",
    "gn:name":"Anshi",
    "gn:population":0,
    "gn:timezone":"Asia/Shanghai",
    "iso:country":"CN",
    "name:und_x_variant":[
        "An-shih",
        "Anshi"
    ],
    "wof:name":"Anshi",
    "wof:placetype":"locality"
},
  "geometry": {"coordinates":[125.31639,43.00111],"type":"Point"}
}