{
  "type": "Feature",
  "properties": {
    "gn:admin1_code":"32.0",
    "gn:asciiname":"Huangheshi",
    "gn:country_code":"CN",
    "gn:dem":382,
    "gn:feature_class":"P",
    "gn:feature_code":"PPL",
    "gn:name":"Huangheshi",
    "gn:population":0,
    "gn:timezone":"Asia/Shanghai",
    "iso:country":"CN",
    "name:zho_x_preferred":[
        "\u9ec4\u9e64\u77f3"
    ],
    "wof:name":"Huangheshi",
    "wof:placetype":"locality"
},
  "geometry": {"coordinates":[103.879,29.3043],"type":"Point"}
}