{
  "type": "Feature",
  "properties": {
    "gn:admin1_code":"26.0",
    "gn:asciiname":"Tangpocun",
    "gn:country_code":"CN",
    "gn:dem":593,
    "gn:feature_class":"P",
    "gn:feature_code":"PPL",
    "gn:name":"Tangpocun",
    "gn:population":0,
    "gn:timezone":"Asia/Shanghai",
    "iso:country":"CN",
    "name:zho_x_preferred":[
        "\u5510\u5761\u6751"
    ],
    "wof:name":"Tangpocun",
    "wof:placetype":"locality"
},
  "geometry": {"coordinates":[109.25935,32.85063],"type":"Point"}
}