{
  "type": "Feature",
  "properties": {
    "gn:admin1_code":"21.0",
    "gn:asciiname":"Shangduancha",
    "gn:country_code":"CN",
    "gn:dem":1950,
    "gn:feature_class":"P",
    "gn:feature_code":"PPL",
    "gn:name":"Shangduancha",
    "gn:population":0,
    "gn:timezone":"Asia/Shanghai",
    "iso:country":"CN",
    "name:und_x_variant":[
        "\u4e0a\u77ed\u5c94"
    ],
    "name:zho_x_preferred":[
        "\u4e0a\u77ed\u5c94"
    ],
    "wof:name":"Shangduancha",
    "wof:placetype":"locality"
},
  "geometry": {"coordinates":[105.93724,35.56361],"type":"Point"}
}