{
  "type": "Feature",
  "properties": {
    "gn:admin1_code":"7.0",
    "gn:asciiname":"Tiancuoku",
    "gn:country_code":"CN",
    "gn:dem":19,
    "gn:feature_class":"P",
    "gn:feature_code":"PPL",
    "gn:name":"Tiancuoku",
    "gn:population":0,
    "gn:timezone":"Asia/Shanghai",
    "iso:country":"CN",
    "name:zho_x_preferred":[
        "\u7530\u539d\u7a9f"
    ],
    "wof:name":"Tiancuoku",
    "wof:placetype":"locality"
},
  "geometry": {"coordinates":[117.99444,24.49244],"type":"Point"}
}