{
  "type": "Feature",
  "properties": {
    "gn:admin1_code":"15.0",
    "gn:asciiname":"Lanjiacha",
    "gn:country_code":"CN",
    "gn:dem":1480,
    "gn:feature_class":"P",
    "gn:feature_code":"PPL",
    "gn:name":"Lanjiacha",
    "gn:population":0,
    "gn:timezone":"Asia/Shanghai",
    "iso:country":"CN",
    "name:zho_x_preferred":[
        "\u5170\u5bb6\u5c94"
    ],
    "wof:name":"Lanjiacha",
    "wof:placetype":"locality"
},
  "geometry": {"coordinates":[107.12,35.7645],"type":"Point"}
}