{
  "type": "Feature",
  "properties": {
    "gn:admin1_code":"22",
    "gn:asciiname":"Lugouqiao",
    "gn:country_code":"CN",
    "gn:dem":54,
    "gn:feature_class":"P",
    "gn:feature_code":"PPLA4",
    "gn:name":"Lugouqiao",
    "gn:population":0,
    "gn:timezone":"Asia/Shanghai",
    "iso:country":"CN",
    "name:deu_x_preferred":[
        "Wanping-Festung"
    ],
    "name:nor_x_preferred":[
        "Wanpingfortet"
    ],
    "name:pol_x_preferred":[
        "Twierdza Wanping"
    ],
    "name:rus_x_preferred":[
        "\u0412\u0430\u043d\u044c\u043f\u0438\u043d"
    ],
    "name:swe_x_preferred":[
        "Wanping"
    ],
    "name:ukr_x_preferred":[
        "\u0412\u0430\u043d\u044c\u043f\u0456\u043d"
    ],
    "name:und_x_variant":[
        "Van\u2019pin",
        "Lu-kou-ch\u2019iao",
        "Wan-p\u2019ing-hsien",
        "Wanping",
        "Lugouqiao",
        "Lugouqiao Jiedao"
    ],
    "name:zho_x_preferred":[
        "\u5362\u6c9f\u6865"
    ],
    "name:zho_x_variant":[
        "\u5362\u6c9f\u6865\u8857\u9053",
        "\u5b9b\u5e73\u57ce"
    ],
    "wof:name":"Lugouqiao",
    "wof:placetype":"locality"
},
  "geometry": {"coordinates":[116.27745,39.8688],"type":"Point"}
}