{
  "type": "Feature",
  "properties": {
    "gn:admin1_code":"19.0",
    "gn:asciiname":"Shimengoucun",
    "gn:country_code":"CN",
    "gn:dem":622,
    "gn:feature_class":"P",
    "gn:feature_code":"PPL",
    "gn:name":"Shimengoucun",
    "gn:population":0,
    "gn:timezone":"Asia/Shanghai",
    "iso:country":"CN",
    "name:zho_x_preferred":[
        "\u77f3\u95e8\u6c9f\u6751"
    ],
    "wof:name":"Shimengoucun",
    "wof:placetype":"locality"
},
  "geometry": {"coordinates":[119.64100000000001,40.4965],"type":"Point"}
}