{
  "type": "Feature",
  "properties": {
    "gn:admin1_code":"30.0",
    "gn:asciiname":"Chiniling",
    "gn:country_code":"CN",
    "gn:dem":244,
    "gn:feature_class":"P",
    "gn:feature_code":"PPL",
    "gn:name":"Chiniling",
    "gn:population":0,
    "gn:timezone":"Asia/Shanghai",
    "iso:country":"CN",
    "name:zho_x_preferred":[
        "\u8d64\u6ce5\u5cad"
    ],
    "wof:name":"Chiniling",
    "wof:placetype":"locality"
},
  "geometry": {"coordinates":[114.92563,23.19739],"type":"Point"}
}