{
  "type": "Feature",
  "properties": {
    "gn:admin1_code":"21.0",
    "gn:asciiname":"Ji'erwan",
    "gn:country_code":"CN",
    "gn:dem":1681,
    "gn:feature_class":"P",
    "gn:feature_code":"PPL",
    "gn:name":"Ji\u2019erwan",
    "gn:population":0,
    "gn:timezone":"Asia/Shanghai",
    "iso:country":"CN",
    "name:und_x_variant":[
        "Ji\u2019erwan"
    ],
    "name:zho_x_preferred":[
        "\u9e21\u513f\u6e7e"
    ],
    "wof:name":"Ji'erwan",
    "wof:placetype":"locality"
},
  "geometry": {"coordinates":[105.744,36.6165],"type":"Point"}
}