{
  "type": "Feature",
  "properties": {
    "gn:admin1_code":"16.0",
    "gn:asciiname":"Touliang",
    "gn:country_code":"CN",
    "gn:dem":170,
    "gn:feature_class":"P",
    "gn:feature_code":"PPL",
    "gn:name":"Touliang",
    "gn:population":0,
    "gn:timezone":"Asia/Shanghai",
    "iso:country":"CN",
    "name:zho_x_preferred":[
        "\u5934\u4eae"
    ],
    "wof:name":"Touliang",
    "wof:placetype":"locality"
},
  "geometry": {"coordinates":[108.03700000000001,23.8215],"type":"Point"}
}