{
  "type": "Feature",
  "properties": {
    "gn:admin1_code":"14",
    "gn:asciiname":"Kangjian",
    "gn:country_code":"CN",
    "gn:dem":4018,
    "gn:feature_class":"P",
    "gn:feature_code":"PPL",
    "gn:name":"Kangjian",
    "gn:population":0,
    "gn:timezone":"Asia/Urumqi",
    "iso:country":"CN",
    "name:zho_x_preferred":[
        "\u5eb7\u575a"
    ],
    "wof:name":"Kangjian",
    "wof:placetype":"locality"
},
  "geometry": {"coordinates":[88.5891,29.1705],"type":"Point"}
}