{
  "type": "Feature",
  "properties": {
    "gn:admin1_code":"7.0",
    "gn:asciiname":"Wangjiazhou",
    "gn:country_code":"CN",
    "gn:dem":340,
    "gn:feature_class":"P",
    "gn:feature_code":"PPL",
    "gn:name":"Wangjiazhou",
    "gn:population":0,
    "gn:timezone":"Asia/Shanghai",
    "iso:country":"CN",
    "name:zho_x_preferred":[
        "\u738b\u5bb6\u6d32"
    ],
    "wof:name":"Wangjiazhou",
    "wof:placetype":"locality"
},
  "geometry": {"coordinates":[117.46639999999999,27.74546],"type":"Point"}
}