{
  "type": "Feature",
  "properties": {
    "gn:admin1_code":"29.0",
    "gn:asciiname":"Landuifang",
    "gn:country_code":"CN",
    "gn:dem":1070,
    "gn:feature_class":"P",
    "gn:feature_code":"PPL",
    "gn:name":"Landuifang",
    "gn:population":0,
    "gn:timezone":"Asia/Shanghai",
    "iso:country":"CN",
    "name:zho_x_preferred":[
        "\u61d2\u7893\u623f"
    ],
    "wof:name":"Landuifang",
    "wof:placetype":"locality"
},
  "geometry": {"coordinates":[101.315,22.7835],"type":"Point"}
}