{
  "type": "Feature",
  "properties": {
    "gn:admin1_code":"10.0",
    "gn:asciiname":"Madaqu",
    "gn:country_code":"CN",
    "gn:dem":862,
    "gn:feature_class":"P",
    "gn:feature_code":"PPL",
    "gn:name":"Madaqu",
    "gn:population":0,
    "gn:timezone":"Asia/Shanghai",
    "iso:country":"CN",
    "name:zho_x_preferred":[
        "\u9a6c\u8fbe\u6e20"
    ],
    "wof:name":"Madaqu",
    "wof:placetype":"locality"
},
  "geometry": {"coordinates":[115.03046000000001,39.34276],"type":"Point"}
}