{
  "type": "Feature",
  "properties": {
    "gn:admin1_code":"29.0",
    "gn:asciiname":"Diesha",
    "gn:country_code":"CN",
    "gn:dem":817,
    "gn:feature_class":"P",
    "gn:feature_code":"PPL",
    "gn:name":"Diesha",
    "gn:population":0,
    "gn:timezone":"Asia/Shanghai",
    "iso:country":"CN",
    "name:zho_x_preferred":[
        "\u8dcc\u6c99"
    ],
    "wof:name":"Diesha",
    "wof:placetype":"locality"
},
  "geometry": {"coordinates":[98.19880000000001,24.2307],"type":"Point"}
}