{
  "type": "Feature",
  "properties": {
    "gn:admin1_code":"32.0",
    "gn:asciiname":"Niutouzhai",
    "gn:country_code":"CN",
    "gn:dem":567,
    "gn:feature_class":"P",
    "gn:feature_code":"PPL",
    "gn:name":"Niutouzhai",
    "gn:population":0,
    "gn:timezone":"Asia/Shanghai",
    "iso:country":"CN",
    "name:zho_x_preferred":[
        "\u725b\u5934\u5be8"
    ],
    "wof:name":"Niutouzhai",
    "wof:placetype":"locality"
},
  "geometry": {"coordinates":[104.46899999999999,29.5293],"type":"Point"}
}