{
  "type": "Feature",
  "properties": {
    "gn:admin1_code":"1.0",
    "gn:asciiname":"Xiwushi",
    "gn:country_code":"CN",
    "gn:dem":205,
    "gn:feature_class":"P",
    "gn:feature_code":"PPL",
    "gn:name":"Xiwushi",
    "gn:population":0,
    "gn:timezone":"Asia/Shanghai",
    "iso:country":"CN",
    "name:zho_x_preferred":[
        "\u897f\u575e\u77f3"
    ],
    "wof:name":"Xiwushi",
    "wof:placetype":"locality"
},
  "geometry": {"coordinates":[118.29378,29.93824],"type":"Point"}
}