{
  "type": "Feature",
  "properties": {
    "gn:admin1_code":"9",
    "gn:asciiname":"Hengling",
    "gn:country_code":"CN",
    "gn:dem":881,
    "gn:feature_class":"P",
    "gn:feature_code":"PPL",
    "gn:name":"Hengling",
    "gn:population":0,
    "gn:timezone":"Asia/Shanghai",
    "iso:country":"CN",
    "wof:name":"Hengling",
    "wof:placetype":"locality"
},
  "geometry": {"coordinates":[111.2375,33.75139],"type":"Point"}
}