{
  "type": "Feature",
  "properties": {
    "gn:admin1_code":"12",
    "gn:asciiname":"Donggong",
    "gn:country_code":"CN",
    "gn:dem":180,
    "gn:feature_class":"P",
    "gn:feature_code":"PPLA4",
    "gn:name":"Donggong",
    "gn:population":0,
    "gn:timezone":"Asia/Shanghai",
    "iso:country":"CN",
    "name:und_x_variant":[
        "Tung-kung",
        "Donggong",
        "Donggong Zhen"
    ],
    "name:zho_x_preferred":[
        "\u4e1c\u5de9"
    ],
    "name:zho_x_variant":[
        "\u4e1c\u5de9\u9547"
    ],
    "wof:name":"Donggong",
    "wof:placetype":"locality"
},
  "geometry": {"coordinates":[111.83147,31.3258],"type":"Point"}
}