{
  "type": "Feature",
  "properties": {
    "gn:admin1_code":"10.0",
    "gn:asciiname":"Jiuxinzhuang",
    "gn:country_code":"CN",
    "gn:dem":1152,
    "gn:feature_class":"P",
    "gn:feature_code":"PPL",
    "gn:name":"Jiuxinzhuang",
    "gn:population":0,
    "gn:timezone":"Asia/Shanghai",
    "iso:country":"CN",
    "name:zho_x_preferred":[
        "\u4e5d\u8f9b\u5e84"
    ],
    "wof:name":"Jiuxinzhuang",
    "wof:placetype":"locality"
},
  "geometry": {"coordinates":[114.78417,39.84342],"type":"Point"}
}