{
  "type": "Feature",
  "properties": {
    "gn:admin1_code":"7.0",
    "gn:asciiname":"Chidun",
    "gn:country_code":"CN",
    "gn:dem":336,
    "gn:feature_class":"P",
    "gn:feature_code":"PPL",
    "gn:name":"Chidun",
    "gn:population":0,
    "gn:timezone":"Asia/Shanghai",
    "iso:country":"CN",
    "name:zho_x_preferred":[
        "\u6c60\u58a9"
    ],
    "wof:name":"Chidun",
    "wof:placetype":"locality"
},
  "geometry": {"coordinates":[117.89324000000001,26.95859],"type":"Point"}
}