{
  "type": "Feature",
  "properties": {
    "gn:admin1_code":"10.0",
    "gn:asciiname":"Nanlupo",
    "gn:country_code":"CN",
    "gn:dem":45,
    "gn:feature_class":"P",
    "gn:feature_code":"PPL",
    "gn:name":"Nanlupo",
    "gn:population":0,
    "gn:timezone":"Asia/Shanghai",
    "iso:country":"CN",
    "name:zho_x_preferred":[
        "\u5357\u9c81\u5761"
    ],
    "wof:name":"Nanlupo",
    "wof:placetype":"locality"
},
  "geometry": {"coordinates":[115.86994,39.52748],"type":"Point"}
}