{
  "type": "Feature",
  "properties": {
    "gn:admin1_code":"22.0",
    "gn:asciiname":"Dongshui Nanzhuang",
    "gn:country_code":"CN",
    "gn:dem":38,
    "gn:feature_class":"P",
    "gn:feature_code":"PPL",
    "gn:name":"Dongshui Nanzhuang",
    "gn:population":0,
    "gn:timezone":"Asia/Shanghai",
    "iso:country":"CN",
    "name:zho_x_preferred":[
        "\u4e1c\u6c34\u5357\u5e84"
    ],
    "wof:name":"Dongshui Nanzhuang",
    "wof:placetype":"locality"
},
  "geometry": {"coordinates":[116.50726,39.90251],"type":"Point"}
}