{
  "type": "Feature",
  "properties": {
    "gn:admin1_code":"29.0",
    "gn:asciiname":"Siyonggong",
    "gn:country_code":"CN",
    "gn:dem":2529,
    "gn:feature_class":"P",
    "gn:feature_code":"PPL",
    "gn:name":"Siyonggong",
    "gn:population":0,
    "gn:timezone":"Asia/Shanghai",
    "iso:country":"CN",
    "name:zho_x_preferred":[
        "\u65af\u6c38\u8d21"
    ],
    "wof:name":"Siyonggong",
    "wof:placetype":"locality"
},
  "geometry": {"coordinates":[98.8449,28.281],"type":"Point"}
}