{
  "type": "Feature",
  "properties": {
    "gn:admin1_code":"15.0",
    "gn:asciiname":"Huaishuzhuang",
    "gn:country_code":"CN",
    "gn:dem":1497,
    "gn:feature_class":"P",
    "gn:feature_code":"PPL",
    "gn:name":"Huaishuzhuang",
    "gn:population":0,
    "gn:timezone":"Asia/Shanghai",
    "iso:country":"CN",
    "name:und_x_variant":[
        "\u69d0\u6811\u5e84"
    ],
    "wof:name":"Huaishuzhuang",
    "wof:placetype":"locality"
},
  "geometry": {"coordinates":[107.33414999999999,36.18468],"type":"Point"}
}