{
  "type": "Feature",
  "properties": {
    "gn:admin1_code":"15.0",
    "gn:asciiname":"Canka",
    "gn:country_code":"CN",
    "gn:dem":2042,
    "gn:feature_class":"P",
    "gn:feature_code":"PPL",
    "gn:name":"Canka",
    "gn:population":0,
    "gn:timezone":"Asia/Shanghai",
    "iso:country":"CN",
    "name:und_x_variant":[
        "\u707f\u5361"
    ],
    "name:zho_x_preferred":[
        "\u707f\u5361"
    ],
    "wof:name":"Canka",
    "wof:placetype":"locality"
},
  "geometry": {"coordinates":[103.88118,34.05731],"type":"Point"}
}