{
  "type": "Feature",
  "properties": {
    "gn:admin1_code":"3.0",
    "gn:asciiname":"Maikeng",
    "gn:country_code":"CN",
    "gn:dem":164,
    "gn:feature_class":"P",
    "gn:feature_code":"PPL",
    "gn:name":"Maikeng",
    "gn:population":0,
    "gn:timezone":"Asia/Shanghai",
    "iso:country":"CN",
    "name:und_x_variant":[
        "\u9ea6\u5751"
    ],
    "wof:name":"Maikeng",
    "wof:placetype":"locality"
},
  "geometry": {"coordinates":[115.62300999999999,27.51788],"type":"Point"}
}