{
  "type": "Feature",
  "properties": {
    "gn:admin1_code":"10.0",
    "gn:asciiname":"Jiaochangzhuang",
    "gn:country_code":"CN",
    "gn:dem":76,
    "gn:feature_class":"P",
    "gn:feature_code":"PPL",
    "gn:name":"Jiaochangzhuang",
    "gn:population":0,
    "gn:timezone":"Asia/Shanghai",
    "iso:country":"CN",
    "name:und_x_variant":[
        "\u6559\u573a\u5e84"
    ],
    "wof:name":"Jiaochangzhuang",
    "wof:placetype":"locality"
},
  "geometry": {"coordinates":[114.56865000000001,38.17681],"type":"Point"}
}