{
  "type": "Feature",
  "properties": {
    "gn:admin1_code":"26.0",
    "gn:asciiname":"Mapizigouzhang",
    "gn:country_code":"CN",
    "gn:dem":1329,
    "gn:feature_class":"P",
    "gn:feature_code":"PPL",
    "gn:name":"Mapizigouzhang",
    "gn:population":0,
    "gn:timezone":"Asia/Shanghai",
    "iso:country":"CN",
    "name:zho_x_preferred":[
        "\u9a6c\u76ae\u5b50\u6c9f\u638c"
    ],
    "wof:name":"Mapizigouzhang",
    "wof:placetype":"locality"
},
  "geometry": {"coordinates":[109.12278000000001,36.15259],"type":"Point"}
}