{
  "type": "Feature",
  "properties": {
    "gn:admin1_code":"29.0",
    "gn:asciiname":"Shishancun",
    "gn:country_code":"CN",
    "gn:dem":2110,
    "gn:feature_class":"P",
    "gn:feature_code":"PPL",
    "gn:name":"Shishancun",
    "gn:population":0,
    "gn:timezone":"Asia/Shanghai",
    "iso:country":"CN",
    "name:zho_x_preferred":[
        "\u72ee\u5c71\u6751"
    ],
    "wof:name":"Shishancun",
    "wof:placetype":"locality"
},
  "geometry": {"coordinates":[102.36799999999999,25.5248],"type":"Point"}
}