{
  "type": "Feature",
  "properties": {
    "gn:admin1_code":"21.0",
    "gn:asciiname":"Lanjiawozi",
    "gn:country_code":"CN",
    "gn:dem":1541,
    "gn:feature_class":"P",
    "gn:feature_code":"PPL",
    "gn:name":"Lanjiawozi",
    "gn:population":0,
    "gn:timezone":"Asia/Shanghai",
    "iso:country":"CN",
    "name:und_x_variant":[
        "\u5170\u5bb6\u7a9d\u5b50"
    ],
    "name:zho_x_preferred":[
        "\u5170\u5bb6\u7a9d\u5b50"
    ],
    "wof:name":"Lanjiawozi",
    "wof:placetype":"locality"
},
  "geometry": {"coordinates":[106.12645999999999,36.29638],"type":"Point"}
}