{
  "type": "Feature",
  "properties": {
    "gn:admin1_code":"9",
    "gn:asciiname":"Sulijia",
    "gn:country_code":"CN",
    "gn:dem":35,
    "gn:feature_class":"P",
    "gn:feature_code":"PPL",
    "gn:name":"Sulijia",
    "gn:population":0,
    "gn:timezone":"Asia/Shanghai",
    "iso:country":"CN",
    "name:zho_x_preferred":[
        "\u82cf\u674e\u5bb6"
    ],
    "wof:name":"Sulijia",
    "wof:placetype":"locality"
},
  "geometry": {"coordinates":[116.16800000000001,33.7722],"type":"Point"}
}