{
  "type": "Feature",
  "properties": {
    "gn:admin1_code":"1.0",
    "gn:asciiname":"Zhengzhuangcun",
    "gn:country_code":"CN",
    "gn:dem":20,
    "gn:feature_class":"P",
    "gn:feature_code":"PPL",
    "gn:name":"Zhengzhuangcun",
    "gn:population":0,
    "gn:timezone":"Asia/Shanghai",
    "iso:country":"CN",
    "name:zho_x_preferred":[
        "\u90d1\u5e84\u6751"
    ],
    "wof:name":"Zhengzhuangcun",
    "wof:placetype":"locality"
},
  "geometry": {"coordinates":[117.90962,33.26709],"type":"Point"}
}