{
  "type": "Feature",
  "properties": {
    "gn:admin1_code":"14.0",
    "gn:asciiname":"Benza",
    "gn:country_code":"CN",
    "gn:dem":4510,
    "gn:feature_class":"P",
    "gn:feature_code":"PPL",
    "gn:name":"Benza",
    "gn:population":0,
    "gn:timezone":"Asia/Urumqi",
    "iso:country":"CN",
    "name:zho_x_preferred":[
        "\u672c\u6742"
    ],
    "wof:name":"Benza",
    "wof:placetype":"locality"
},
  "geometry": {"coordinates":[91.77203,28.33455],"type":"Point"}
}