{
  "type": "Feature",
  "properties": {
    "gn:admin1_code":"4.0",
    "gn:asciiname":"Beihuangyin",
    "gn:country_code":"CN",
    "gn:dem":3,
    "gn:feature_class":"P",
    "gn:feature_code":"PPL",
    "gn:name":"Beihuangyin",
    "gn:population":0,
    "gn:timezone":"Asia/Shanghai",
    "iso:country":"CN",
    "name:zho_x_preferred":[
        "Beihuangyin"
    ],
    "name:zho_x_variant":[
        "\u5317\u9ec4\u5c39"
    ],
    "wof:name":"Beihuangyin",
    "wof:placetype":"locality"
},
  "geometry": {"coordinates":[119.76719,33.2684],"type":"Point"}
}