{
  "type": "Feature",
  "properties": {
    "gn:admin1_code":"19.0",
    "gn:asciiname":"Haitanggou",
    "gn:country_code":"CN",
    "gn:dem":713,
    "gn:feature_class":"P",
    "gn:feature_code":"PPL",
    "gn:name":"Haitanggou",
    "gn:population":0,
    "gn:timezone":"Asia/Shanghai",
    "iso:country":"CN",
    "name:zho_x_preferred":[
        "\u6d77\u68e0\u6c9f"
    ],
    "wof:name":"Haitanggou",
    "wof:placetype":"locality"
},
  "geometry": {"coordinates":[119.64167999999999,41.69882],"type":"Point"}
}