{
  "type": "Feature",
  "properties": {
    "gn:admin1_code":"25",
    "gn:asciiname":"Shalingzi",
    "gn:country_code":"CN",
    "gn:dem":177,
    "gn:feature_class":"P",
    "gn:feature_code":"PPL",
    "gn:name":"Shalingzi",
    "gn:population":0,
    "gn:timezone":"Asia/Shanghai",
    "iso:country":"CN",
    "name:zho_x_preferred":[
        "\u6c99\u5cad\u5b50"
    ],
    "wof:name":"Shalingzi",
    "wof:placetype":"locality"
},
  "geometry": {"coordinates":[118.729,35.9394],"type":"Point"}
}