{
  "type": "Feature",
  "properties": {
    "gn:admin1_code":"03",
    "gn:asciiname":"Gongfang",
    "gn:country_code":"CN",
    "gn:dem":96,
    "gn:feature_class":"P",
    "gn:feature_code":"PPLA4",
    "gn:name":"Gongfang",
    "gn:population":0,
    "gn:timezone":"Asia/Shanghai",
    "iso:country":"CN",
    "name:und_x_variant":[
        "Kung-fang",
        "Kung-fang-hs\u00fc",
        "Gongfang",
        "\u9f9a\u574a",
        "Gongfang Zhen",
        "\u9f9a\u574a\u9547"
    ],
    "wof:name":"Gongfang",
    "wof:placetype":"locality"
},
  "geometry": {"coordinates":[115.75342999999999,27.5923],"type":"Point"}
}