{
  "type": "Feature",
  "properties": {
    "gn:admin1_code":"8.0",
    "gn:asciiname":"Halawusucun",
    "gn:country_code":"CN",
    "gn:dem":147,
    "gn:feature_class":"P",
    "gn:feature_code":"PPL",
    "gn:name":"Halawusucun",
    "gn:population":0,
    "gn:timezone":"Asia/Shanghai",
    "iso:country":"CN",
    "name:zho_x_preferred":[
        "\u54c8\u62c9\u4e4c\u82cf\u6751"
    ],
    "wof:name":"Halawusucun",
    "wof:placetype":"locality"
},
  "geometry": {"coordinates":[124.18053999999999,47.24344],"type":"Point"}
}