{
  "type": "Feature",
  "properties": {
    "gn:admin1_code":"26.0",
    "gn:asciiname":"Goupingcun",
    "gn:country_code":"CN",
    "gn:dem":676,
    "gn:feature_class":"P",
    "gn:feature_code":"PPL",
    "gn:name":"Goupingcun",
    "gn:population":0,
    "gn:timezone":"Asia/Shanghai",
    "iso:country":"CN",
    "name:zho_x_preferred":[
        "\u6784\u576a\u6751"
    ],
    "wof:name":"Goupingcun",
    "wof:placetype":"locality"
},
  "geometry": {"coordinates":[108.91781,32.22764],"type":"Point"}
}