{
  "type": "Feature",
  "properties": {
    "gn:admin1_code":"12.0",
    "gn:asciiname":"Yulukou",
    "gn:country_code":"CN",
    "gn:dem":36,
    "gn:feature_class":"P",
    "gn:feature_code":"PPL",
    "gn:name":"Yulukou",
    "gn:population":0,
    "gn:timezone":"Asia/Shanghai",
    "iso:country":"CN",
    "name:zho_x_preferred":[
        "\u5fa1\u8def\u53e3"
    ],
    "wof:name":"Yulukou",
    "wof:placetype":"locality"
},
  "geometry": {"coordinates":[112.19192,30.32928],"type":"Point"}
}