{
  "type": "Feature",
  "properties": {
    "gn:admin1_code":"2.0",
    "gn:asciiname":"Chengcun",
    "gn:country_code":"CN",
    "gn:dem":197,
    "gn:feature_class":"P",
    "gn:feature_code":"PPL",
    "gn:name":"Chengcun",
    "gn:population":0,
    "gn:timezone":"Asia/Shanghai",
    "iso:country":"CN",
    "name:zho_x_preferred":[
        "\u7a0b\u6751"
    ],
    "wof:name":"Chengcun",
    "wof:placetype":"locality"
},
  "geometry": {"coordinates":[121.08441999999999,29.7842],"type":"Point"}
}