{
  "type": "Feature",
  "properties": {
    "gn:admin1_code":"29.0",
    "gn:asciiname":"Dajiana",
    "gn:country_code":"CN",
    "gn:dem":2345,
    "gn:feature_class":"P",
    "gn:feature_code":"PPL",
    "gn:name":"Dajiana",
    "gn:population":0,
    "gn:timezone":"Asia/Shanghai",
    "iso:country":"CN",
    "name:zho_x_preferred":[
        "\u5927\u621b\u90a3"
    ],
    "wof:name":"Dajiana",
    "wof:placetype":"locality"
},
  "geometry": {"coordinates":[104.114,25.492],"type":"Point"}
}