{
  "type": "Feature",
  "properties": {
    "gn:admin1_code":"16.0",
    "gn:asciiname":"Damaogong",
    "gn:country_code":"CN",
    "gn:dem":1,
    "gn:feature_class":"P",
    "gn:feature_code":"PPL",
    "gn:name":"Damaogong",
    "gn:population":0,
    "gn:timezone":"Asia/Shanghai",
    "iso:country":"CN",
    "name:zho_x_preferred":[
        "\u5927\u5e3d\u516c"
    ],
    "wof:name":"Damaogong",
    "wof:placetype":"locality"
},
  "geometry": {"coordinates":[108.092,21.5539],"type":"Point"}
}