{
  "type": "Feature",
  "properties": {
    "gn:admin1_code":"32.0",
    "gn:asciiname":"Shanghuanshan",
    "gn:country_code":"CN",
    "gn:dem":1816,
    "gn:feature_class":"P",
    "gn:feature_code":"PPL",
    "gn:name":"Shanghuanshan",
    "gn:population":0,
    "gn:timezone":"Asia/Shanghai",
    "iso:country":"CN",
    "name:zho_x_preferred":[
        "\u4e0a\u73af\u5c71"
    ],
    "wof:name":"Shanghuanshan",
    "wof:placetype":"locality"
},
  "geometry": {"coordinates":[102.61781000000001,29.02963],"type":"Point"}
}