{
  "type": "Feature",
  "properties": {
    "gn:admin1_code":"1.0",
    "gn:asciiname":"Li'ancun",
    "gn:country_code":"CN",
    "gn:dem":507,
    "gn:feature_class":"P",
    "gn:feature_code":"PPL",
    "gn:name":"Li\u2019ancun",
    "gn:population":0,
    "gn:timezone":"Asia/Shanghai",
    "iso:country":"CN",
    "name:und_x_variant":[
        "Li\u2019ancun"
    ],
    "name:zho_x_preferred":[
        "\u674e\u5b89\u6751"
    ],
    "wof:name":"Li'ancun",
    "wof:placetype":"locality"
},
  "geometry": {"coordinates":[115.94262999999999,30.48656],"type":"Point"}
}