{
  "type": "Feature",
  "properties": {
    "gn:admin1_code":"30.0",
    "gn:asciiname":"Ducai",
    "gn:country_code":"CN",
    "gn:dem":306,
    "gn:feature_class":"P",
    "gn:feature_code":"PPL",
    "gn:name":"Ducai",
    "gn:population":0,
    "gn:timezone":"Asia/Shanghai",
    "iso:country":"CN",
    "name:zho_x_preferred":[
        "Ducai"
    ],
    "name:zho_x_variant":[
        "\u675c\u83dc"
    ],
    "wof:name":"Ducai",
    "wof:placetype":"locality"
},
  "geometry": {"coordinates":[112.78667,24.74083],"type":"Point"}
}