{
  "type": "Feature",
  "properties": {
    "gn:admin1_code":"4.0",
    "gn:asciiname":"Henan",
    "gn:country_code":"CN",
    "gn:dem":4,
    "gn:feature_class":"P",
    "gn:feature_code":"PPL",
    "gn:name":"Henan",
    "gn:population":0,
    "gn:timezone":"Asia/Shanghai",
    "iso:country":"CN",
    "name:zho_x_preferred":[
        "Henan"
    ],
    "name:zho_x_variant":[
        "\u6cb3\u5357"
    ],
    "wof:name":"Henan",
    "wof:placetype":"locality"
},
  "geometry": {"coordinates":[119.44843,33.66331],"type":"Point"}
}