{
  "type": "Feature",
  "properties": {
    "gn:admin1_code":"3.0",
    "gn:asciiname":"Xiaoqiaozhen",
    "gn:country_code":"CN",
    "gn:dem":37,
    "gn:feature_class":"P",
    "gn:feature_code":"PPL",
    "gn:name":"Xiaoqiaozhen",
    "gn:population":0,
    "gn:timezone":"Asia/Shanghai",
    "iso:country":"CN",
    "name:und_x_variant":[
        "\u5b5d\u6865\u9547"
    ],
    "wof:name":"Xiaoqiaozhen",
    "wof:placetype":"locality"
},
  "geometry": {"coordinates":[116.36306999999999,28.01238],"type":"Point"}
}