{
  "type": "Feature",
  "properties": {
    "gn:admin1_code":"8.0",
    "gn:asciiname":"Beidashan",
    "gn:country_code":"CN",
    "gn:dem":168,
    "gn:feature_class":"P",
    "gn:feature_code":"PPL",
    "gn:name":"Beidashan",
    "gn:population":0,
    "gn:timezone":"Asia/Shanghai",
    "iso:country":"CN",
    "name:zho_x_preferred":[
        "\u5317\u5927\u5c71"
    ],
    "wof:name":"Beidashan",
    "wof:placetype":"locality"
},
  "geometry": {"coordinates":[125.59451,45.70333],"type":"Point"}
}