{
  "type": "Feature",
  "properties": {
    "gn:admin1_code":"29.0",
    "gn:asciiname":"Laosuzhai",
    "gn:country_code":"CN",
    "gn:dem":1411,
    "gn:feature_class":"P",
    "gn:feature_code":"PPL",
    "gn:name":"Laosuzhai",
    "gn:population":0,
    "gn:timezone":"Asia/Shanghai",
    "iso:country":"CN",
    "name:zho_x_preferred":[
        "\u8001\u82cf\u5be8"
    ],
    "wof:name":"Laosuzhai",
    "wof:placetype":"locality"
},
  "geometry": {"coordinates":[101.697,23.09],"type":"Point"}
}