{
  "type": "Feature",
  "properties": {
    "gn:admin1_code":"1.0",
    "gn:asciiname":"Landu",
    "gn:country_code":"CN",
    "gn:dem":156,
    "gn:feature_class":"P",
    "gn:feature_code":"PPL",
    "gn:name":"Landu",
    "gn:population":0,
    "gn:timezone":"Asia/Shanghai",
    "iso:country":"CN",
    "name:und_x_variant":[
        "Lan-tu",
        "Landu"
    ],
    "name:zho_x_preferred":[
        "\u5170\u6e21"
    ],
    "wof:name":"Landu",
    "wof:placetype":"locality"
},
  "geometry": {"coordinates":[118.10917000000001,29.79196],"type":"Point"}
}