{
  "type": "Feature",
  "properties": {
    "gn:admin1_code":"9.0",
    "gn:asciiname":"Conglou",
    "gn:country_code":"CN",
    "gn:dem":58,
    "gn:feature_class":"P",
    "gn:feature_code":"PPL",
    "gn:name":"Conglou",
    "gn:population":0,
    "gn:timezone":"Asia/Shanghai",
    "iso:country":"CN",
    "name:zho_x_preferred":[
        "\u4ece\u697c"
    ],
    "wof:name":"Conglou",
    "wof:placetype":"locality"
},
  "geometry": {"coordinates":[114.48536,32.71779],"type":"Point"}
}