{
  "type": "Feature",
  "properties": {
    "gn:admin1_code":"32.0",
    "gn:asciiname":"Shuiya",
    "gn:country_code":"CN",
    "gn:dem":650,
    "gn:feature_class":"P",
    "gn:feature_code":"PPL",
    "gn:name":"Shuiya",
    "gn:population":0,
    "gn:timezone":"Asia/Shanghai",
    "iso:country":"CN",
    "name:zho_x_preferred":[
        "\u6c34\u57ad"
    ],
    "wof:name":"Shuiya",
    "wof:placetype":"locality"
},
  "geometry": {"coordinates":[106.351,31.8982],"type":"Point"}
}