{
  "type": "Feature",
  "properties": {
    "gn:admin1_code":"11.0",
    "gn:asciiname":"Qiaojia Wuchang",
    "gn:country_code":"CN",
    "gn:dem":47,
    "gn:feature_class":"P",
    "gn:feature_code":"PPL",
    "gn:name":"Qiaojia Wuchang",
    "gn:population":0,
    "gn:timezone":"Asia/Shanghai",
    "iso:country":"CN",
    "name:zho_x_preferred":[
        "Qiaojia Wuchang"
    ],
    "name:zho_x_variant":[
        "\u4e54\u5bb6\u5c4b\u573a"
    ],
    "wof:name":"Qiaojia Wuchang",
    "wof:placetype":"locality"
},
  "geometry": {"coordinates":[111.60668,29.6482],"type":"Point"}
}