{
  "type": "Feature",
  "properties": {
    "gn:admin1_code":"32.0",
    "gn:asciiname":"Xiajia Woshan",
    "gn:country_code":"CN",
    "gn:dem":1738,
    "gn:feature_class":"P",
    "gn:feature_code":"PPL",
    "gn:name":"Xiajia Woshan",
    "gn:population":0,
    "gn:timezone":"Asia/Shanghai",
    "iso:country":"CN",
    "name:zho_x_preferred":[
        "\u590f\u5bb6\u7a9d\u5c71"
    ],
    "wof:name":"Xiajia Woshan",
    "wof:placetype":"locality"
},
  "geometry": {"coordinates":[101.764,26.7378],"type":"Point"}
}