{
  "type": "Feature",
  "properties": {
    "gn:admin1_code":"10.0",
    "gn:asciiname":"Shangpabeishi",
    "gn:country_code":"CN",
    "gn:dem":791,
    "gn:feature_class":"P",
    "gn:feature_code":"PPL",
    "gn:name":"Shangpabeishi",
    "gn:population":0,
    "gn:timezone":"Asia/Shanghai",
    "iso:country":"CN",
    "name:und_x_variant":[
        "\u4e0a\u722c\u80cc\u77f3"
    ],
    "wof:name":"Shangpabeishi",
    "wof:placetype":"locality"
},
  "geometry": {"coordinates":[114.02406999999999,38.82223],"type":"Point"}
}