{
  "type": "Feature",
  "properties": {
    "gn:admin1_code":"14.0",
    "gn:asciiname":"Abulie",
    "gn:country_code":"CN",
    "gn:dem":4596,
    "gn:feature_class":"P",
    "gn:feature_code":"PPL",
    "gn:name":"Abulie",
    "gn:population":0,
    "gn:timezone":"Asia/Urumqi",
    "iso:country":"CN",
    "name:zho_x_preferred":[
        "\u963f\u5e03\u5217"
    ],
    "wof:name":"Abulie",
    "wof:placetype":"locality"
},
  "geometry": {"coordinates":[86.6151,29.4366],"type":"Point"}
}