{
  "type": "Feature",
  "properties": {
    "gn:admin1_code":"29.0",
    "gn:asciiname":"Shuitoushang",
    "gn:country_code":"CN",
    "gn:dem":1880,
    "gn:feature_class":"P",
    "gn:feature_code":"PPL",
    "gn:name":"Shuitoushang",
    "gn:population":0,
    "gn:timezone":"Asia/Shanghai",
    "iso:country":"CN",
    "name:zho_x_preferred":[
        "\u6c34\u5934\u4e0a"
    ],
    "wof:name":"Shuitoushang",
    "wof:placetype":"locality"
},
  "geometry": {"coordinates":[104.645,26.3754],"type":"Point"}
}