{
  "type": "Feature",
  "properties": {
    "gn:admin1_code":"1.0",
    "gn:asciiname":"Dongguancun",
    "gn:country_code":"CN",
    "gn:dem":153,
    "gn:feature_class":"P",
    "gn:feature_code":"PPL",
    "gn:name":"Dongguancun",
    "gn:population":0,
    "gn:timezone":"Asia/Shanghai",
    "iso:country":"CN",
    "name:und_x_variant":[
        "Dongguan"
    ],
    "name:zho_x_preferred":[
        "\u4e1c\u5173\u6751"
    ],
    "name:zho_x_variant":[
        "\u4e1c\u5173"
    ],
    "wof:name":"Dongguancun",
    "wof:placetype":"locality"
},
  "geometry": {"coordinates":[118.2945,29.75993],"type":"Point"}
}