{
  "type": "Feature",
  "properties": {
    "gn:admin1_code":"16.0",
    "gn:asciiname":"Gaohua",
    "gn:country_code":"CN",
    "gn:dem":613,
    "gn:feature_class":"P",
    "gn:feature_code":"PPL",
    "gn:name":"Gaohua",
    "gn:population":0,
    "gn:timezone":"Asia/Shanghai",
    "iso:country":"CN",
    "name:zho_x_preferred":[
        "\u544a\u82b1"
    ],
    "wof:name":"Gaohua",
    "wof:placetype":"locality"
},
  "geometry": {"coordinates":[107.631,24.2884],"type":"Point"}
}