{
  "type": "Feature",
  "properties": {
    "gn:admin1_code":"11.0",
    "gn:asciiname":"Liangqiao",
    "gn:country_code":"CN",
    "gn:dem":759,
    "gn:feature_class":"P",
    "gn:feature_code":"PPL",
    "gn:name":"Liangqiao",
    "gn:population":0,
    "gn:timezone":"Asia/Shanghai",
    "iso:country":"CN",
    "name:zho_x_preferred":[
        "\u6881\u6865"
    ],
    "wof:name":"Liangqiao",
    "wof:placetype":"locality"
},
  "geometry": {"coordinates":[113.95283999999999,26.40553],"type":"Point"}
}