{
  "type": "Feature",
  "properties": {
    "gn:admin1_code":"11.0",
    "gn:asciiname":"Anxia",
    "gn:country_code":"CN",
    "gn:dem":284,
    "gn:feature_class":"P",
    "gn:feature_code":"PPL",
    "gn:name":"Anxia",
    "gn:population":0,
    "gn:timezone":"Asia/Shanghai",
    "iso:country":"CN",
    "name:zho_x_preferred":[
        "Anxia"
    ],
    "name:zho_x_variant":[
        "\u5eb5\u4e0b"
    ],
    "wof:name":"Anxia",
    "wof:placetype":"locality"
},
  "geometry": {"coordinates":[114.05476000000002,28.2072],"type":"Point"}
}