{
  "type": "Feature",
  "properties": {
    "gn:admin1_code":"19.0",
    "gn:asciiname":"Xiaowu Daogou",
    "gn:country_code":"CN",
    "gn:dem":280,
    "gn:feature_class":"P",
    "gn:feature_code":"PPL",
    "gn:name":"Xiaowu Daogou",
    "gn:population":0,
    "gn:timezone":"Asia/Shanghai",
    "iso:country":"CN",
    "name:und_x_variant":[
        "\u5c0f\u4e94\u9053\u6c9f"
    ],
    "wof:name":"Xiaowu Daogou",
    "wof:placetype":"locality"
},
  "geometry": {"coordinates":[122.75008,40.33663],"type":"Point"}
}