{
  "type": "Feature",
  "properties": {
    "gn:admin1_code":"32.0",
    "gn:asciiname":"Mingyuexia",
    "gn:country_code":"CN",
    "gn:dem":788,
    "gn:feature_class":"P",
    "gn:feature_code":"PPL",
    "gn:name":"Mingyuexia",
    "gn:population":0,
    "gn:timezone":"Asia/Shanghai",
    "iso:country":"CN",
    "name:zho_x_preferred":[
        "\u660e\u6708\u5ce1"
    ],
    "wof:name":"Mingyuexia",
    "wof:placetype":"locality"
},
  "geometry": {"coordinates":[105.84,32.6282],"type":"Point"}
}