{
  "type": "Feature",
  "properties": {
    "gn:admin1_code":"26.0",
    "gn:asciiname":"Beihenao",
    "gn:country_code":"CN",
    "gn:dem":1694,
    "gn:feature_class":"P",
    "gn:feature_code":"PPL",
    "gn:name":"Beihenao",
    "gn:population":0,
    "gn:timezone":"Asia/Shanghai",
    "iso:country":"CN",
    "name:zho_x_preferred":[
        "\u5317\u6cb3\u8111"
    ],
    "wof:name":"Beihenao",
    "wof:placetype":"locality"
},
  "geometry": {"coordinates":[109.15680999999999,33.86023],"type":"Point"}
}