{
  "type": "Feature",
  "properties": {
    "gn:admin1_code":"9",
    "gn:asciiname":"Zhulou",
    "gn:country_code":"CN",
    "gn:dem":89,
    "gn:feature_class":"P",
    "gn:feature_code":"PPL",
    "gn:name":"Zhulou",
    "gn:population":0,
    "gn:timezone":"Asia/Shanghai",
    "iso:country":"CN",
    "wof:name":"Zhulou",
    "wof:placetype":"locality"
},
  "geometry": {"coordinates":[113.67583,35.04],"type":"Point"}
}