{
  "type": "Feature",
  "properties": {
    "gn:admin1_code":"11.0",
    "gn:asciiname":"Xinshao",
    "gn:country_code":"CN",
    "gn:dem":623,
    "gn:feature_class":"P",
    "gn:feature_code":"PPL",
    "gn:name":"Xinshao",
    "gn:population":0,
    "gn:timezone":"Asia/Shanghai",
    "iso:country":"CN",
    "name:zho_x_preferred":[
        "\u65b0\u54e8"
    ],
    "wof:name":"Xinshao",
    "wof:placetype":"locality"
},
  "geometry": {"coordinates":[110.24637,26.93724000000001],"type":"Point"}
}