{
  "type": "Feature",
  "properties": {
    "gn:admin1_code":"24",
    "gn:asciiname":"Mahuangtou",
    "gn:country_code":"CN",
    "gn:dem":1416,
    "gn:feature_class":"P",
    "gn:feature_code":"PPL",
    "gn:name":"Mahuangtou",
    "gn:population":0,
    "gn:timezone":"Asia/Shanghai",
    "iso:country":"CN",
    "name:und_x_variant":[
        "\u9ebb\u9ec4\u5934"
    ],
    "wof:name":"Mahuangtou",
    "wof:placetype":"locality"
},
  "geometry": {"coordinates":[112.68783999999999,39.92307],"type":"Point"}
}