{
  "type": "Feature",
  "properties": {
    "gn:admin1_code":"25",
    "gn:asciiname":"Songlaozhi Xicun",
    "gn:country_code":"CN",
    "gn:dem":42,
    "gn:feature_class":"P",
    "gn:feature_code":"PPL",
    "gn:name":"Songlaozhi Xicun",
    "gn:population":0,
    "gn:timezone":"Asia/Shanghai",
    "iso:country":"CN",
    "name:zho_x_preferred":[
        "\u5b8b\u6d9d\u679d\u897f\u6751"
    ],
    "wof:name":"Songlaozhi Xicun",
    "wof:placetype":"locality"
},
  "geometry": {"coordinates":[118.70999999999999,34.7024],"type":"Point"}
}