{
  "type": "Feature",
  "properties": {
    "gn:admin1_code":"33.0",
    "gn:asciiname":"Niujiaowan",
    "gn:country_code":"CN",
    "gn:dem":874,
    "gn:feature_class":"P",
    "gn:feature_code":"PPL",
    "gn:name":"Niujiaowan",
    "gn:population":0,
    "gn:timezone":"Asia/Shanghai",
    "iso:country":"CN",
    "name:zho_x_preferred":[
        "\u725b\u89d2\u6e7e"
    ],
    "wof:name":"Niujiaowan",
    "wof:placetype":"locality"
},
  "geometry": {"coordinates":[109.5321,30.90073],"type":"Point"}
}