{
  "type": "Feature",
  "properties": {
    "gn:admin1_code":"20.0",
    "gn:asciiname":"Ewenke Minzu Sumu",
    "gn:country_code":"CN",
    "gn:dem":660,
    "gn:feature_class":"P",
    "gn:feature_code":"PPL",
    "gn:name":"Ewenke Minzu Sumu",
    "gn:population":0,
    "gn:timezone":"Asia/Shanghai",
    "iso:country":"CN",
    "name:ceb_x_preferred":[
        "Ewenki"
    ],
    "name:rus_x_preferred":[
        "\u042d\u0432\u0435\u043d\u043a\u0438\u0439\u0441\u043a\u0438\u0439 \u043d\u0430\u0446\u0438\u043e\u043d\u0430\u043b\u044c\u043d\u044b\u0439 \u0441\u043e\u043c\u043e\u043d"
    ],
    "name:swe_x_preferred":[
        "Ewenki"
    ],
    "name:zho_x_preferred":[
        "\u9102\u6e29\u514b\u6c11\u65cf\u82cf\u6728"
    ],
    "wof:name":"Ewenke Minzu Sumu",
    "wof:placetype":"locality"
},
  "geometry": {"coordinates":[120.08199,49.7902],"type":"Point"}
}