{
  "type": "Feature",
  "properties": {
    "gn:admin1_code":"9",
    "gn:asciiname":"Dashizhuang",
    "gn:country_code":"CN",
    "gn:dem":51,
    "gn:feature_class":"P",
    "gn:feature_code":"PPL",
    "gn:name":"Dashizhuang",
    "gn:population":0,
    "gn:timezone":"Asia/Shanghai",
    "iso:country":"CN",
    "name:zho_x_preferred":[
        "\u5927\u53f2\u5e84"
    ],
    "wof:name":"Dashizhuang",
    "wof:placetype":"locality"
},
  "geometry": {"coordinates":[115.14400000000001,34.0053],"type":"Point"}
}