{
  "type": "Feature",
  "properties": {
    "gn:admin1_code":"29.0",
    "gn:asciiname":"Zashipeng",
    "gn:country_code":"CN",
    "gn:dem":2075,
    "gn:feature_class":"P",
    "gn:feature_code":"PPL",
    "gn:name":"Zashipeng",
    "gn:population":0,
    "gn:timezone":"Asia/Shanghai",
    "iso:country":"CN",
    "name:zho_x_preferred":[
        "\u6742\u77f3\u68da"
    ],
    "wof:name":"Zashipeng",
    "wof:placetype":"locality"
},
  "geometry": {"coordinates":[100.337,25.8361],"type":"Point"}
}