{
  "type": "Feature",
  "properties": {
    "gn:admin1_code":"24.0",
    "gn:asciiname":"Maxingzhuang",
    "gn:country_code":"CN",
    "gn:dem":1520,
    "gn:feature_class":"P",
    "gn:feature_code":"PPL",
    "gn:name":"Maxingzhuang",
    "gn:population":0,
    "gn:timezone":"Asia/Shanghai",
    "iso:country":"CN",
    "name:zho_x_preferred":[
        "\u9a6c\u5174\u5e84"
    ],
    "wof:name":"Maxingzhuang",
    "wof:placetype":"locality"
},
  "geometry": {"coordinates":[111.60169999999999,38.90938],"type":"Point"}
}