{
  "type": "Feature",
  "properties": {
    "gn:admin1_code":"15.0",
    "gn:asciiname":"Zhuangzhuang",
    "gn:country_code":"CN",
    "gn:dem":2665,
    "gn:feature_class":"P",
    "gn:feature_code":"PPL",
    "gn:name":"Zhuangzhuang",
    "gn:population":0,
    "gn:timezone":"Asia/Shanghai",
    "iso:country":"CN",
    "name:zho_x_preferred":[
        "\u5e84\u5e84"
    ],
    "wof:name":"Zhuangzhuang",
    "wof:placetype":"locality"
},
  "geometry": {"coordinates":[102.964,37.1165],"type":"Point"}
}