{
  "type": "Feature",
  "properties": {
    "gn:admin1_code":"15.0",
    "gn:asciiname":"Shimenxian",
    "gn:country_code":"CN",
    "gn:dem":2736,
    "gn:feature_class":"P",
    "gn:feature_code":"PPL",
    "gn:name":"Shimenxian",
    "gn:population":0,
    "gn:timezone":"Asia/Shanghai",
    "iso:country":"CN",
    "name:zho_x_preferred":[
        "\u77f3\u95e8\u5c98"
    ],
    "wof:name":"Shimenxian",
    "wof:placetype":"locality"
},
  "geometry": {"coordinates":[103.01900000000001,36.9399],"type":"Point"}
}