{
  "type": "Feature",
  "properties": {
    "gn:admin1_code":"24.0",
    "gn:asciiname":"Cangfeng",
    "gn:country_code":"CN",
    "gn:dem":558,
    "gn:feature_class":"P",
    "gn:feature_code":"PPL",
    "gn:name":"Cangfeng",
    "gn:population":0,
    "gn:timezone":"Asia/Shanghai",
    "iso:country":"CN",
    "name:zho_x_preferred":[
        "\u4ed3\u4e30"
    ],
    "wof:name":"Cangfeng",
    "wof:placetype":"locality"
},
  "geometry": {"coordinates":[111.66428999999999,35.60341],"type":"Point"}
}