{
  "type": "Feature",
  "properties": {
    "gn:admin1_code":"14",
    "gn:asciiname":"Guqiong",
    "gn:country_code":"CN",
    "gn:dem":4643,
    "gn:feature_class":"P",
    "gn:feature_code":"PPL",
    "gn:name":"Guqiong",
    "gn:population":0,
    "gn:timezone":"Asia/Urumqi",
    "iso:country":"CN",
    "name:zho_x_preferred":[
        "\u53e4\u7a77"
    ],
    "wof:name":"Guqiong",
    "wof:placetype":"locality"
},
  "geometry": {"coordinates":[88.48909999999999,29.7495],"type":"Point"}
}