{
  "type": "Feature",
  "properties": {
    "gn:admin1_code":"26.0",
    "gn:asciiname":"Huangjiamiao",
    "gn:country_code":"CN",
    "gn:dem":506,
    "gn:feature_class":"P",
    "gn:feature_code":"PPL",
    "gn:name":"Huangjiamiao",
    "gn:population":0,
    "gn:timezone":"Asia/Shanghai",
    "iso:country":"CN",
    "name:und_x_variant":[
        "Huangjiapo",
        "\u9ec4\u5bb6\u5761",
        "Huangjiamiao"
    ],
    "name:zho_x_preferred":[
        "\u9ec4\u5bb6\u5e99"
    ],
    "wof:name":"Huangjiamiao",
    "wof:placetype":"locality"
},
  "geometry": {"coordinates":[107.07803,33.05398],"type":"Point"}
}