{
  "type": "Feature",
  "properties": {
    "gn:admin1_code":"20.0",
    "gn:asciiname":"Lingquan",
    "gn:country_code":"CN",
    "gn:dem":569,
    "gn:feature_class":"P",
    "gn:feature_code":"PPL",
    "gn:name":"Lingquan",
    "gn:population":0,
    "gn:timezone":"Asia/Shanghai",
    "iso:country":"CN",
    "name:und_x_variant":[
        "\u7075\u6cc9"
    ],
    "wof:name":"Lingquan",
    "wof:placetype":"locality"
},
  "geometry": {"coordinates":[117.67700000000001,49.4052],"type":"Point"}
}