{
  "type": "Feature",
  "properties": {
    "gn:admin1_code":"25.0",
    "gn:asciiname":"Shansunjiacun",
    "gn:country_code":"CN",
    "gn:dem":105,
    "gn:feature_class":"P",
    "gn:feature_code":"PPL",
    "gn:name":"Shansunjiacun",
    "gn:population":0,
    "gn:timezone":"Asia/Shanghai",
    "iso:country":"CN",
    "name:zho_x_preferred":[
        "\u5c71\u5b59\u5bb6\u6751"
    ],
    "wof:name":"Shansunjiacun",
    "wof:placetype":"locality"
},
  "geometry": {"coordinates":[119.9499,37.12884],"type":"Point"}
}