{
  "type": "Feature",
  "properties": {
    "gn:admin1_code":"3.0",
    "gn:asciiname":"Chikoucun",
    "gn:country_code":"CN",
    "gn:dem":25,
    "gn:feature_class":"P",
    "gn:feature_code":"PPL",
    "gn:name":"Chikoucun",
    "gn:population":0,
    "gn:timezone":"Asia/Shanghai",
    "iso:country":"CN",
    "name:und_x_variant":[
        "\u7fc5\u53e3\u6751"
    ],
    "wof:name":"Chikoucun",
    "wof:placetype":"locality"
},
  "geometry": {"coordinates":[116.55226,28.61599],"type":"Point"}
}