{
  "type": "Feature",
  "properties": {
    "gn:admin1_code":"30.0",
    "gn:asciiname":"Anjingzi",
    "gn:country_code":"CN",
    "gn:dem":97,
    "gn:feature_class":"P",
    "gn:feature_code":"PPL",
    "gn:name":"Anjingzi",
    "gn:population":0,
    "gn:timezone":"Asia/Shanghai",
    "iso:country":"CN",
    "name:zho_x_preferred":[
        "\u6697\u5f84\u5b50"
    ],
    "wof:name":"Anjingzi",
    "wof:placetype":"locality"
},
  "geometry": {"coordinates":[115.06612,23.48169],"type":"Point"}
}