{
  "type": "Feature",
  "properties": {
    "gn:admin1_code":"14.0",
    "gn:asciiname":"Gongba",
    "gn:country_code":"CN",
    "gn:dem":3346,
    "gn:feature_class":"P",
    "gn:feature_code":"PPL",
    "gn:name":"Gongba",
    "gn:population":0,
    "gn:timezone":"Asia/Urumqi",
    "iso:country":"CN",
    "name:zho_x_preferred":[
        "\u5171\u5df4"
    ],
    "wof:name":"Gongba",
    "wof:placetype":"locality"
},
  "geometry": {"coordinates":[93.55492,29.89791],"type":"Point"}
}