{
  "type": "Feature",
  "properties": {
    "gn:admin1_code":"15.0",
    "gn:asciiname":"Gaojia Wopu",
    "gn:country_code":"CN",
    "gn:dem":2434,
    "gn:feature_class":"P",
    "gn:feature_code":"PPL",
    "gn:name":"Gaojia Wopu",
    "gn:population":0,
    "gn:timezone":"Asia/Shanghai",
    "iso:country":"CN",
    "name:zho_x_preferred":[
        "\u9ad8\u5bb6\u7a9d\u94fa"
    ],
    "wof:name":"Gaojia Wopu",
    "wof:placetype":"locality"
},
  "geometry": {"coordinates":[103.43600000000001,35.2764],"type":"Point"}
}