{
  "type": "Feature",
  "properties": {
    "gn:admin1_code":"32.0",
    "gn:asciiname":"Bamagongba",
    "gn:country_code":"CN",
    "gn:dem":2560,
    "gn:feature_class":"P",
    "gn:feature_code":"PPL",
    "gn:name":"Bamagongba",
    "gn:population":0,
    "gn:timezone":"Asia/Shanghai",
    "iso:country":"CN",
    "name:zho_x_preferred":[
        "\u516b\u739b\u8d21\u5df4"
    ],
    "wof:name":"Bamagongba",
    "wof:placetype":"locality"
},
  "geometry": {"coordinates":[103.04900000000001,34.1317],"type":"Point"}
}