{
  "type": "Feature",
  "properties": {
    "gn:admin1_code":"4.0",
    "gn:asciiname":"Anlincun",
    "gn:country_code":"CN",
    "gn:dem":2,
    "gn:feature_class":"P",
    "gn:feature_code":"PPL",
    "gn:name":"Anlincun",
    "gn:population":0,
    "gn:timezone":"Asia/Shanghai",
    "iso:country":"CN",
    "name:zho_x_preferred":[
        "\u5b89\u6dcb\u6751"
    ],
    "wof:name":"Anlincun",
    "wof:placetype":"locality"
},
  "geometry": {"coordinates":[119.35509999999999,34.20129],"type":"Point"}
}