{
  "type": "Feature",
  "properties": {
    "gn:admin1_code":"10.0",
    "gn:asciiname":"Nanhuangtou",
    "gn:country_code":"CN",
    "gn:dem":948,
    "gn:feature_class":"P",
    "gn:feature_code":"PPL",
    "gn:name":"Nanhuangtou",
    "gn:population":0,
    "gn:timezone":"Asia/Shanghai",
    "iso:country":"CN",
    "name:zho_x_preferred":[
        "\u5357\u9ec4\u5934"
    ],
    "wof:name":"Nanhuangtou",
    "wof:placetype":"locality"
},
  "geometry": {"coordinates":[115.04259,40.28079],"type":"Point"}
}