{
  "type": "Feature",
  "properties": {
    "gn:admin1_code":"12.0",
    "gn:asciiname":"Dengjiapu",
    "gn:country_code":"CN",
    "gn:dem":36,
    "gn:feature_class":"P",
    "gn:feature_code":"PPL",
    "gn:name":"Dengjiapu",
    "gn:population":0,
    "gn:timezone":"Asia/Shanghai",
    "iso:country":"CN",
    "name:zho_x_preferred":[
        "Dengjiapu"
    ],
    "name:zho_x_variant":[
        "\u9093\u5bb6\u94fa"
    ],
    "wof:name":"Dengjiapu",
    "wof:placetype":"locality"
},
  "geometry": {"coordinates":[111.99106,29.9819],"type":"Point"}
}