{
  "type": "Feature",
  "properties": {
    "gn:admin1_code":"11.0",
    "gn:asciiname":"Huangsili",
    "gn:country_code":"CN",
    "gn:dem":52,
    "gn:feature_class":"P",
    "gn:feature_code":"PPL",
    "gn:name":"Huangsili",
    "gn:population":0,
    "gn:timezone":"Asia/Shanghai",
    "iso:country":"CN",
    "name:zho_x_preferred":[
        "\u9ec4\u6cd7\u91cc"
    ],
    "wof:name":"Huangsili",
    "wof:placetype":"locality"
},
  "geometry": {"coordinates":[111.94511,28.60269000000001],"type":"Point"}
}