{
  "type": "Feature",
  "properties": {
    "gn:admin1_code":"32.0",
    "gn:asciiname":"Wenwu",
    "gn:country_code":"CN",
    "gn:dem":388,
    "gn:feature_class":"P",
    "gn:feature_code":"PPL",
    "gn:name":"Wenwu",
    "gn:population":0,
    "gn:timezone":"Asia/Shanghai",
    "iso:country":"CN",
    "name:zho_x_preferred":[
        "\u6587\u6b66"
    ],
    "wof:name":"Wenwu",
    "wof:placetype":"locality"
},
  "geometry": {"coordinates":[106.43000000000001,31.2318],"type":"Point"}
}