{
  "type": "Feature",
  "properties": {
    "gn:admin1_code":"12.0",
    "gn:asciiname":"Laowuwan",
    "gn:country_code":"CN",
    "gn:dem":165,
    "gn:feature_class":"P",
    "gn:feature_code":"PPL",
    "gn:name":"Laowuwan",
    "gn:population":0,
    "gn:timezone":"Asia/Shanghai",
    "iso:country":"CN",
    "name:zho_x_preferred":[
        "\u8001\u5c4b\u5846"
    ],
    "wof:name":"Laowuwan",
    "wof:placetype":"locality"
},
  "geometry": {"coordinates":[115.70253,30.94904],"type":"Point"}
}