{
  "type": "Feature",
  "properties": {
    "gn:admin1_code":"32.0",
    "gn:asciiname":"Dasunjiaying",
    "gn:country_code":"CN",
    "gn:dem":541,
    "gn:feature_class":"P",
    "gn:feature_code":"PPL",
    "gn:name":"Dasunjiaying",
    "gn:population":0,
    "gn:timezone":"Asia/Shanghai",
    "iso:country":"CN",
    "name:zho_x_preferred":[
        "\u5927\u5b59\u5bb6\u8425"
    ],
    "wof:name":"Dasunjiaying",
    "wof:placetype":"locality"
},
  "geometry": {"coordinates":[105.712,31.9026],"type":"Point"}
}