{
  "type": "Feature",
  "properties": {
    "gn:admin1_code":"30.0",
    "gn:asciiname":"Shangping Shacun",
    "gn:country_code":"CN",
    "gn:dem":77,
    "gn:feature_class":"P",
    "gn:feature_code":"PPL",
    "gn:name":"Shangping Shacun",
    "gn:population":0,
    "gn:timezone":"Asia/Shanghai",
    "iso:country":"CN",
    "name:zho_x_preferred":[
        "\u4e0a\u576a\u6c99\u6751"
    ],
    "wof:name":"Shangping Shacun",
    "wof:placetype":"locality"
},
  "geometry": {"coordinates":[116.58453,24.52602000000001],"type":"Point"}
}