{
  "type": "Feature",
  "properties": {
    "gn:admin1_code":"8.0",
    "gn:asciiname":"Fangmamuying",
    "gn:country_code":"CN",
    "gn:dem":444,
    "gn:feature_class":"P",
    "gn:feature_code":"PPL",
    "gn:name":"Fangmamuying",
    "gn:population":0,
    "gn:timezone":"Asia/Shanghai",
    "iso:country":"CN",
    "name:zho_x_preferred":[
        "\u653e\u9a6c\u7267\u8425"
    ],
    "wof:name":"Fangmamuying",
    "wof:placetype":"locality"
},
  "geometry": {"coordinates":[131.20491999999999,46.39082],"type":"Point"}
}