{
  "type": "Feature",
  "properties": {
    "gn:admin1_code":"1.0",
    "gn:asciiname":"Sanhuzhongcun",
    "gn:country_code":"CN",
    "gn:dem":62,
    "gn:feature_class":"P",
    "gn:feature_code":"PPL",
    "gn:name":"Sanhuzhongcun",
    "gn:population":0,
    "gn:timezone":"Asia/Shanghai",
    "iso:country":"CN",
    "name:zho_x_preferred":[
        "\u4e09\u6237\u949f\u6751"
    ],
    "wof:name":"Sanhuzhongcun",
    "wof:placetype":"locality"
},
  "geometry": {"coordinates":[117.67847,32.19917],"type":"Point"}
}