{
  "type": "Feature",
  "properties": {
    "gn:admin1_code":"2.0",
    "gn:asciiname":"Wushiqiao",
    "gn:country_code":"CN",
    "gn:dem":8,
    "gn:feature_class":"P",
    "gn:feature_code":"PPL",
    "gn:name":"Wushiqiao",
    "gn:population":0,
    "gn:timezone":"Asia/Shanghai",
    "iso:country":"CN",
    "name:und_x_variant":[
        "\u5deb\u5e08\u6865"
    ],
    "wof:name":"Wushiqiao",
    "wof:placetype":"locality"
},
  "geometry": {"coordinates":[120.64688999999998,30.49704],"type":"Point"}
}