{
  "type": "Feature",
  "properties": {
    "gn:admin1_code":"32.0",
    "gn:asciiname":"Shiyanzi",
    "gn:country_code":"CN",
    "gn:dem":295,
    "gn:feature_class":"P",
    "gn:feature_code":"PPL",
    "gn:name":"Shiyanzi",
    "gn:population":0,
    "gn:timezone":"Asia/Shanghai",
    "iso:country":"CN",
    "name:zho_x_preferred":[
        "\u77f3\u71d5\u5b50"
    ],
    "wof:name":"Shiyanzi",
    "wof:placetype":"locality"
},
  "geometry": {"coordinates":[105.32317999999999,29.2652],"type":"Point"}
}