{
  "type": "Feature",
  "properties": {
    "gn:admin1_code":"1.0",
    "gn:asciiname":"Houliuqiaocun",
    "gn:country_code":"CN",
    "gn:dem":40,
    "gn:feature_class":"P",
    "gn:feature_code":"PPL",
    "gn:name":"Houliuqiaocun",
    "gn:population":0,
    "gn:timezone":"Asia/Shanghai",
    "iso:country":"CN",
    "name:zho_x_preferred":[
        "\u540e\u5218\u6865\u6751"
    ],
    "wof:name":"Houliuqiaocun",
    "wof:placetype":"locality"
},
  "geometry": {"coordinates":[115.35863999999999,33.40674],"type":"Point"}
}