{
  "type": "Feature",
  "properties": {
    "gn:admin1_code":"19.0",
    "gn:asciiname":"Kuangdonggoucun",
    "gn:country_code":"CN",
    "gn:dem":224,
    "gn:feature_class":"P",
    "gn:feature_code":"PPL",
    "gn:name":"Kuangdonggoucun",
    "gn:population":0,
    "gn:timezone":"Asia/Shanghai",
    "iso:country":"CN",
    "name:und_x_variant":[
        "\u77ff\u6d1e\u6c9f\u6751"
    ],
    "wof:name":"Kuangdonggoucun",
    "wof:placetype":"locality"
},
  "geometry": {"coordinates":[122.70814,40.18105],"type":"Point"}
}