{
  "type": "Feature",
  "properties": {
    "gn:admin1_code":"31.0",
    "gn:asciiname":"Jiazao",
    "gn:country_code":"CN",
    "gn:dem":19,
    "gn:feature_class":"P",
    "gn:feature_code":"PPL",
    "gn:name":"Jiazao",
    "gn:population":0,
    "gn:timezone":"Asia/Shanghai",
    "iso:country":"CN",
    "name:zho_x_preferred":[
        "\u52a0\u9020"
    ],
    "wof:name":"Jiazao",
    "wof:placetype":"locality"
},
  "geometry": {"coordinates":[110.39067,19.06826],"type":"Point"}
}