{
  "type": "Feature",
  "properties": {
    "gn:admin1_code":"19.0",
    "gn:asciiname":"Dijiagoucun",
    "gn:country_code":"CN",
    "gn:dem":115,
    "gn:feature_class":"P",
    "gn:feature_code":"PPL",
    "gn:name":"Dijiagoucun",
    "gn:population":0,
    "gn:timezone":"Asia/Shanghai",
    "iso:country":"CN",
    "name:zho_x_preferred":[
        "\u7fdf\u5bb6\u6c9f\u6751"
    ],
    "wof:name":"Dijiagoucun",
    "wof:placetype":"locality"
},
  "geometry": {"coordinates":[121.907,41.8232],"type":"Point"}
}