{
  "type": "Feature",
  "properties": {
    "gn:admin1_code":"19.0",
    "gn:asciiname":"Xiaowangjiagou",
    "gn:country_code":"CN",
    "gn:dem":28,
    "gn:feature_class":"P",
    "gn:feature_code":"PPL",
    "gn:name":"Xiaowangjiagou",
    "gn:population":0,
    "gn:timezone":"Asia/Shanghai",
    "iso:country":"CN",
    "name:zho_x_preferred":[
        "\u5c0f\u738b\u5bb6\u6c9f"
    ],
    "wof:name":"Xiaowangjiagou",
    "wof:placetype":"locality"
},
  "geometry": {"coordinates":[122.94199999999999,39.6958],"type":"Point"}
}