{
  "type": "Feature",
  "properties": {
    "gn:admin1_code":"15.0",
    "gn:asciiname":"Zhouyaoxian",
    "gn:country_code":"CN",
    "gn:dem":1486,
    "gn:feature_class":"P",
    "gn:feature_code":"PPL",
    "gn:name":"Zhouyaoxian",
    "gn:population":0,
    "gn:timezone":"Asia/Shanghai",
    "iso:country":"CN",
    "name:und_x_variant":[
        "\u5468\u5d3e\u5c98"
    ],
    "wof:name":"Zhouyaoxian",
    "wof:placetype":"locality"
},
  "geometry": {"coordinates":[107.7306,36.64871],"type":"Point"}
}