{
  "type": "Feature",
  "properties": {
    "gn:admin1_code":"32.0",
    "gn:asciiname":"Ga'erma",
    "gn:country_code":"CN",
    "gn:dem":3440,
    "gn:feature_class":"P",
    "gn:feature_code":"PPL",
    "gn:name":"Ga\u2019erma",
    "gn:population":0,
    "gn:timezone":"Asia/Shanghai",
    "iso:country":"CN",
    "name:zho_x_preferred":[
        "\u560e\u5c14\u739b"
    ],
    "name:zho_x_variant":[
        "Ga\u2019erma"
    ],
    "wof:name":"Ga'erma",
    "wof:placetype":"locality"
},
  "geometry": {"coordinates":[102.48358,33.39301],"type":"Point"}
}