{
  "type": "Feature",
  "properties": {
    "gn:admin1_code":"30.0",
    "gn:asciiname":"Anhoucun",
    "gn:country_code":"CN",
    "gn:dem":16,
    "gn:feature_class":"P",
    "gn:feature_code":"PPL",
    "gn:name":"Anhoucun",
    "gn:population":0,
    "gn:timezone":"Asia/Shanghai",
    "iso:country":"CN",
    "name:und_x_variant":[
        "Anhou"
    ],
    "name:zho_x_preferred":[
        "\u5eb5\u540e\u6751"
    ],
    "name:zho_x_variant":[
        "\u5eb5\u540e"
    ],
    "wof:name":"Anhoucun",
    "wof:placetype":"locality"
},
  "geometry": {"coordinates":[116.41459999999999,23.6081],"type":"Point"}
}