{
  "type": "Feature",
  "properties": {
    "gn:admin1_code":"5.0",
    "gn:asciiname":"Qianwangjia",
    "gn:country_code":"CN",
    "gn:dem":133,
    "gn:feature_class":"P",
    "gn:feature_code":"PPL",
    "gn:name":"Qianwangjia",
    "gn:population":0,
    "gn:timezone":"Asia/Shanghai",
    "iso:country":"CN",
    "name:zho_x_preferred":[
        "\u524d\u738b\u5bb6"
    ],
    "wof:name":"Qianwangjia",
    "wof:placetype":"locality"
},
  "geometry": {"coordinates":[123.77858000000001,45.35274],"type":"Point"}
}