{
  "type": "Feature",
  "properties": {
    "gn:admin1_code":"11.0",
    "gn:asciiname":"Linguchang",
    "gn:country_code":"CN",
    "gn:dem":152,
    "gn:feature_class":"P",
    "gn:feature_code":"PPL",
    "gn:name":"Linguchang",
    "gn:population":0,
    "gn:timezone":"Asia/Shanghai",
    "iso:country":"CN",
    "name:zho_x_preferred":[
        "\u6797\u53e4\u573a"
    ],
    "wof:name":"Linguchang",
    "wof:placetype":"locality"
},
  "geometry": {"coordinates":[112.19429,27.1761],"type":"Point"}
}