{
  "type": "Feature",
  "properties": {
    "gn:admin1_code":"2.0",
    "gn:asciiname":"Shandi",
    "gn:country_code":"CN",
    "gn:dem":35,
    "gn:feature_class":"P",
    "gn:feature_code":"PPL",
    "gn:name":"Shandi",
    "gn:population":0,
    "gn:timezone":"Asia/Shanghai",
    "iso:country":"CN",
    "name:ceb_x_preferred":[
        "Shandi"
    ],
    "name:por_x_preferred":[
        "Shandi"
    ],
    "name:zho_x_preferred":[
        "\u5c71\u5e95"
    ],
    "wof:name":"Shandi",
    "wof:placetype":"locality"
},
  "geometry": {"coordinates":[121.67027,29.59919],"type":"Point"}
}