{
  "type": "Feature",
  "properties": {
    "gn:admin1_code":"29.0",
    "gn:asciiname":"Mazha Xinzhai",
    "gn:country_code":"CN",
    "gn:dem":1603,
    "gn:feature_class":"P",
    "gn:feature_code":"PPL",
    "gn:name":"Mazha Xinzhai",
    "gn:population":0,
    "gn:timezone":"Asia/Shanghai",
    "iso:country":"CN",
    "name:zho_x_preferred":[
        "\u5988\u6e23\u65b0\u5be8"
    ],
    "wof:name":"Mazha Xinzhai",
    "wof:placetype":"locality"
},
  "geometry": {"coordinates":[102.685,23.1996],"type":"Point"}
}