{
  "type": "Feature",
  "properties": {
    "gn:admin1_code":"2",
    "gn:asciiname":"Chimushan",
    "gn:country_code":"CN",
    "gn:dem":873,
    "gn:feature_class":"P",
    "gn:feature_code":"PPL",
    "gn:name":"Chimushan",
    "gn:population":0,
    "gn:timezone":"Asia/Shanghai",
    "iso:country":"CN",
    "name:zho_x_preferred":[
        "\u6555\u6728\u5c71"
    ],
    "wof:name":"Chimushan",
    "wof:placetype":"locality"
},
  "geometry": {"coordinates":[119.65443999999999,27.93194],"type":"Point"}
}