{
  "type": "Feature",
  "properties": {
    "gn:admin1_code":"8.0",
    "gn:asciiname":"Kaoshancun",
    "gn:country_code":"CN",
    "gn:dem":133,
    "gn:feature_class":"P",
    "gn:feature_code":"PPL",
    "gn:name":"Kaoshancun",
    "gn:population":0,
    "gn:timezone":"Asia/Shanghai",
    "iso:country":"CN",
    "name:zho_x_preferred":[
        "\u9760\u5c71\u6751"
    ],
    "wof:name":"Kaoshancun",
    "wof:placetype":"locality"
},
  "geometry": {"coordinates":[128.48599999999999,49.53106],"type":"Point"}
}