{
  "type": "Feature",
  "properties": {
    "gn:admin1_code":"16",
    "gn:asciiname":"Tingliang",
    "gn:cc2":"CN",
    "gn:country_code":"CN",
    "gn:dem":131,
    "gn:feature_class":"P",
    "gn:feature_code":"PPL",
    "gn:name":"Tingliang",
    "gn:population":0,
    "gn:timezone":"Asia/Shanghai",
    "iso:country":"CN",
    "name:und_x_variant":[
        "T\u2019ing-liang-hs\u00fc",
        "Tingliang"
    ],
    "wof:name":"Tingliang",
    "wof:placetype":"locality"
},
  "geometry": {"coordinates":[108.59999999999999,23.36667000000001],"type":"Point"}
}