{
  "type": "Feature",
  "properties": {
    "gn:admin1_code":"9",
    "gn:asciiname":"Yangjiaji",
    "gn:country_code":"CN",
    "gn:dem":163,
    "gn:feature_class":"P",
    "gn:feature_code":"PPLA4",
    "gn:name":"Yangjiaji",
    "gn:population":0,
    "gn:timezone":"Asia/Shanghai",
    "iso:country":"CN",
    "name:zho_x_preferred":[
        "\u6768\u5bb6\u96c6"
    ],
    "wof:name":"Yangjiaji",
    "wof:placetype":"locality"
},
  "geometry": {"coordinates":[113.33844999999999,32.82948],"type":"Point"}
}