{
  "type": "Feature",
  "properties": {
    "gn:admin1_code":"26",
    "gn:asciiname":"Laocheng",
    "gn:country_code":"CN",
    "gn:dem":515,
    "gn:feature_class":"P",
    "gn:feature_code":"PPL",
    "gn:name":"Laocheng",
    "gn:population":0,
    "gn:timezone":"Asia/Shanghai",
    "iso:country":"CN",
    "name:und_x_variant":[
        "Dongweijia",
        "Laocheng"
    ],
    "name:zho_x_preferred":[
        "\u8001\u57ce"
    ],
    "wof:name":"Laocheng",
    "wof:placetype":"locality"
},
  "geometry": {"coordinates":[109.40003,34.9552],"type":"Point"}
}