{
  "type": "Feature",
  "properties": {
    "gn:admin1_code":"7",
    "gn:asciiname":"Jizhao",
    "gn:country_code":"CN",
    "gn:dem":26,
    "gn:feature_class":"P",
    "gn:feature_code":"PPL",
    "gn:name":"Jizhao",
    "gn:population":0,
    "gn:timezone":"Asia/Shanghai",
    "iso:country":"CN",
    "name:zho_x_preferred":[
        "\u5409\u5146"
    ],
    "wof:name":"Jizhao",
    "wof:placetype":"locality"
},
  "geometry": {"coordinates":[119.5836,25.67609],"type":"Point"}
}