{
  "type": "Feature",
  "properties": {
    "gn:admin1_code":"7",
    "gn:asciiname":"Daizai",
    "gn:country_code":"CN",
    "gn:dem":9,
    "gn:feature_class":"P",
    "gn:feature_code":"PPL",
    "gn:name":"Daizai",
    "gn:population":0,
    "gn:timezone":"Asia/Shanghai",
    "iso:country":"CN",
    "name:zho_x_preferred":[
        "\u5cb1\u4ed4"
    ],
    "wof:name":"Daizai",
    "wof:placetype":"locality"
},
  "geometry": {"coordinates":[117.60057,23.77018],"type":"Point"}
}