{
  "type": "Feature",
  "properties": {
    "gn:admin1_code":"19.0",
    "gn:asciiname":"Nangangzicun",
    "gn:country_code":"CN",
    "gn:dem":5,
    "gn:feature_class":"P",
    "gn:feature_code":"PPL",
    "gn:name":"Nangangzicun",
    "gn:population":0,
    "gn:timezone":"Asia/Shanghai",
    "iso:country":"CN",
    "name:zho_x_preferred":[
        "\u5357\u5c97\u5b50\u6751"
    ],
    "wof:name":"Nangangzicun",
    "wof:placetype":"locality"
},
  "geometry": {"coordinates":[121.98999999999999,40.9966],"type":"Point"}
}