{
  "type": "Feature",
  "properties": {
    "gn:admin1_code":"05",
    "gn:asciiname":"Wanbao",
    "gn:country_code":"CN",
    "gn:dem":188,
    "gn:feature_class":"P",
    "gn:feature_code":"PPL",
    "gn:name":"Wanbao",
    "gn:population":0,
    "gn:timezone":"Asia/Shanghai",
    "iso:country":"CN",
    "name:und_x_variant":[
        "Wan-pao-shan",
        "Wan-pao",
        "Wanbao"
    ],
    "wof:name":"Wanbao",
    "wof:placetype":"locality"
},
  "geometry": {"coordinates":[125.33333,44.15],"type":"Point"}
}