{
  "type": "Feature",
  "properties": {
    "gn:admin1_code":"24.0",
    "gn:asciiname":"Lengquan",
    "gn:country_code":"CN",
    "gn:dem":504,
    "gn:feature_class":"P",
    "gn:feature_code":"PPL",
    "gn:name":"Lengquan",
    "gn:population":0,
    "gn:timezone":"Asia/Shanghai",
    "iso:country":"CN",
    "name:und_x_variant":[
        "\u51b7\u6cc9"
    ],
    "wof:name":"Lengquan",
    "wof:placetype":"locality"
},
  "geometry": {"coordinates":[111.29380999999999,35.36827],"type":"Point"}
}