{
  "type": "Feature",
  "properties": {
    "gn:admin1_code":"1.0",
    "gn:asciiname":"Jiuliancun",
    "gn:country_code":"CN",
    "gn:dem":10,
    "gn:feature_class":"P",
    "gn:feature_code":"PPL",
    "gn:name":"Jiuliancun",
    "gn:population":0,
    "gn:timezone":"Asia/Shanghai",
    "iso:country":"CN",
    "name:zho_x_preferred":[
        "\u4e5d\u8054\u6751"
    ],
    "wof:name":"Jiuliancun",
    "wof:placetype":"locality"
},
  "geometry": {"coordinates":[118.12148999999999,31.59032],"type":"Point"}
}