{
  "type": "Feature",
  "properties": {
    "gn:admin1_code":"15.0",
    "gn:asciiname":"Youtai Wazui",
    "gn:country_code":"CN",
    "gn:dem":1230,
    "gn:feature_class":"P",
    "gn:feature_code":"PPL",
    "gn:name":"Youtai Wazui",
    "gn:population":0,
    "gn:timezone":"Asia/Shanghai",
    "iso:country":"CN",
    "name:zho_x_preferred":[
        "\u53cb\u53f0\u6d3c\u5480"
    ],
    "wof:name":"Youtai Wazui",
    "wof:placetype":"locality"
},
  "geometry": {"coordinates":[107.30800000000001,35.6453],"type":"Point"}
}