{
  "type": "Feature",
  "properties": {
    "gn:admin1_code":"4.0",
    "gn:asciiname":"Lujiazui",
    "gn:country_code":"CN",
    "gn:dem":9,
    "gn:feature_class":"P",
    "gn:feature_code":"PPL",
    "gn:name":"Lujiazui",
    "gn:population":0,
    "gn:timezone":"Asia/Shanghai",
    "iso:country":"CN",
    "name:eus_x_preferred":[
        "Lujiazui"
    ],
    "name:fra_x_preferred":[
        "Lujiazui"
    ],
    "name:kor_x_preferred":[
        "\ub8e8\uc790\ucb48\uc774"
    ],
    "name:nor_x_preferred":[
        "Lujiazui"
    ],
    "name:spa_x_preferred":[
        "Lujiazui"
    ],
    "name:wuu_x_preferred":[
        "\u9646\u5bb6\u5634\u91d1\u878d\u8d38\u6613\u533a"
    ],
    "name:zho_x_preferred":[
        "\u9646\u5bb6\u5480"
    ],
    "name:zho_x_variant":[
        "\u9646\u5bb6\u5634\u91d1\u878d\u8d38\u6613\u533a"
    ],
    "wof:name":"Lujiazui",
    "wof:placetype":"locality"
},
  "geometry": {"coordinates":[119.42652,32.54311],"type":"Point"}
}