{
  "type": "Feature",
  "properties": {
    "gn:admin1_code":"15.0",
    "gn:asciiname":"Qiganzui",
    "gn:country_code":"CN",
    "gn:dem":1603,
    "gn:feature_class":"P",
    "gn:feature_code":"PPL",
    "gn:name":"Qiganzui",
    "gn:population":0,
    "gn:timezone":"Asia/Shanghai",
    "iso:country":"CN",
    "name:zho_x_preferred":[
        "\u65d7\u6746\u5480"
    ],
    "wof:name":"Qiganzui",
    "wof:placetype":"locality"
},
  "geometry": {"coordinates":[106.816,35.3273],"type":"Point"}
}