{
  "type": "Feature",
  "properties": {
    "gn:admin1_code":"22",
    "gn:asciiname":"Fengheying",
    "gn:country_code":"CN",
    "gn:dem":19,
    "gn:feature_class":"P",
    "gn:feature_code":"PPL",
    "gn:name":"Fengheying",
    "gn:population":0,
    "gn:timezone":"Asia/Shanghai",
    "iso:country":"CN",
    "name:und_x_variant":[
        "Feng-ho-ying",
        "Fengheying"
    ],
    "name:zho_x_preferred":[
        "\u51e4\u6cb3\u8425"
    ],
    "wof:name":"Fengheying",
    "wof:placetype":"locality"
},
  "geometry": {"coordinates":[116.68814,39.61313],"type":"Point"}
}