{
  "type": "Feature",
  "properties": {
    "gn:admin1_code":"3.0",
    "gn:asciiname":"Junlingcun",
    "gn:country_code":"CN",
    "gn:dem":74,
    "gn:feature_class":"P",
    "gn:feature_code":"PPL",
    "gn:name":"Junlingcun",
    "gn:population":0,
    "gn:timezone":"Asia/Shanghai",
    "iso:country":"CN",
    "name:und_x_variant":[
        "\u519b\u5cad\u6751"
    ],
    "wof:name":"Junlingcun",
    "wof:placetype":"locality"
},
  "geometry": {"coordinates":[116.49003,28.28409000000001],"type":"Point"}
}