{
  "type": "Feature",
  "properties": {
    "gn:admin1_code":"24",
    "gn:asciiname":"Songjiazhuang",
    "gn:country_code":"CN",
    "gn:dem":1043,
    "gn:feature_class":"P",
    "gn:feature_code":"PPL",
    "gn:name":"Songjiazhuang",
    "gn:population":0,
    "gn:timezone":"Asia/Shanghai",
    "iso:country":"CN",
    "name:und_x_variant":[
        "Sung-chia-chuang",
        "Chu-chia-chuang",
        "Songjiazhuang",
        "\u5b8b\u5bb6\u5e84"
    ],
    "wof:name":"Songjiazhuang",
    "wof:placetype":"locality"
},
  "geometry": {"coordinates":[113.02171,39.78302],"type":"Point"}
}