{
  "type": "Feature",
  "properties": {
    "gn:admin1_code":"30.0",
    "gn:asciiname":"Lincuoliaocun",
    "gn:country_code":"CN",
    "gn:dem":14,
    "gn:feature_class":"P",
    "gn:feature_code":"PPL",
    "gn:name":"Lincuoliaocun",
    "gn:population":0,
    "gn:timezone":"Asia/Shanghai",
    "iso:country":"CN",
    "name:zho_x_preferred":[
        "\u6797\u539d\u5bee\u6751"
    ],
    "wof:name":"Lincuoliaocun",
    "wof:placetype":"locality"
},
  "geometry": {"coordinates":[116.2567,23.31927],"type":"Point"}
}