{
  "type": "Feature",
  "properties": {
    "gn:admin1_code":"29.0",
    "gn:asciiname":"Houjiazhai",
    "gn:country_code":"CN",
    "gn:dem":1963,
    "gn:feature_class":"P",
    "gn:feature_code":"PPL",
    "gn:name":"Houjiazhai",
    "gn:population":0,
    "gn:timezone":"Asia/Shanghai",
    "iso:country":"CN",
    "name:zho_x_preferred":[
        "\u4faf\u5bb6\u5be8"
    ],
    "wof:name":"Houjiazhai",
    "wof:placetype":"locality"
},
  "geometry": {"coordinates":[98.94880000000001,24.4823],"type":"Point"}
}