{
  "type": "Feature",
  "properties": {
    "gn:admin1_code":"10",
    "gn:asciiname":"Beidian",
    "gn:country_code":"CN",
    "gn:dem":436,
    "gn:feature_class":"P",
    "gn:feature_code":"PPL",
    "gn:name":"Beidian",
    "gn:population":0,
    "gn:timezone":"Asia/Shanghai",
    "iso:country":"CN",
    "name:zho_x_preferred":[
        "\u5317\u5e97"
    ],
    "wof:name":"Beidian",
    "wof:placetype":"locality"
},
  "geometry": {"coordinates":[117.81816000000001,40.49307],"type":"Point"}
}