{
  "type": "Feature",
  "properties": {
    "gn:admin1_code":"19.0",
    "gn:asciiname":"Wenjia Buzi",
    "gn:country_code":"CN",
    "gn:dem":93,
    "gn:feature_class":"P",
    "gn:feature_code":"PPL",
    "gn:name":"Wenjia Buzi",
    "gn:population":0,
    "gn:timezone":"Asia/Shanghai",
    "iso:country":"CN",
    "name:und_x_variant":[
        "Wenjiabaozi",
        "\u6e29\u5bb6\u5821\u5b50",
        "Wenjia Puzi",
        "Wenjia Buzi"
    ],
    "name:zho_x_preferred":[
        "\u6e29\u5bb6\u5821\u5b50"
    ],
    "wof:name":"Wenjia Buzi",
    "wof:placetype":"locality"
},
  "geometry": {"coordinates":[123.57193999999998,40.38275],"type":"Point"}
}