{
  "type": "Feature",
  "properties": {
    "gn:admin1_code":"11.0",
    "gn:asciiname":"Hanfeng'ao",
    "gn:country_code":"CN",
    "gn:dem":361,
    "gn:feature_class":"P",
    "gn:feature_code":"PPL",
    "gn:name":"Hanfeng\u2019ao",
    "gn:population":0,
    "gn:timezone":"Asia/Shanghai",
    "iso:country":"CN",
    "name:und_x_variant":[
        "Hanfeng\u2019ao"
    ],
    "name:zho_x_preferred":[
        "\u5bd2\u98ce\u5773"
    ],
    "wof:name":"Hanfeng'ao",
    "wof:placetype":"locality"
},
  "geometry": {"coordinates":[109.86084,28.26691],"type":"Point"}
}