{
  "type": "Feature",
  "properties": {
    "gn:admin1_code":"19.0",
    "gn:asciiname":"Shihuiyaozi Gouli",
    "gn:country_code":"CN",
    "gn:dem":219,
    "gn:feature_class":"P",
    "gn:feature_code":"PPL",
    "gn:name":"Shihuiyaozi Gouli",
    "gn:population":0,
    "gn:timezone":"Asia/Shanghai",
    "iso:country":"CN",
    "name:zho_x_preferred":[
        "\u77f3\u7070\u7a91\u5b50\u6c9f\u91cc"
    ],
    "wof:name":"Shihuiyaozi Gouli",
    "wof:placetype":"locality"
},
  "geometry": {"coordinates":[120.176,40.8202],"type":"Point"}
}