{
  "type": "Feature",
  "properties": {
    "gn:admin1_code":"3",
    "gn:asciiname":"Zhushanli",
    "gn:country_code":"CN",
    "gn:dem":823,
    "gn:feature_class":"P",
    "gn:feature_code":"PPL",
    "gn:name":"Zhushanli",
    "gn:population":0,
    "gn:timezone":"Asia/Shanghai",
    "iso:country":"CN",
    "name:zho_x_preferred":[
        "\u7af9\u5c71\u91cc"
    ],
    "wof:name":"Zhushanli",
    "wof:placetype":"locality"
},
  "geometry": {"coordinates":[114.102,26.2445],"type":"Point"}
}