{
  "type": "Feature",
  "properties": {
    "gn:admin1_code":"14",
    "gn:asciiname":"Loma",
    "gn:country_code":"CN",
    "gn:dem":4194,
    "gn:feature_class":"P",
    "gn:feature_code":"PPL",
    "gn:name":"Loma",
    "gn:population":0,
    "gn:timezone":"Asia/Urumqi",
    "iso:country":"CN",
    "name:bod_x_preferred":[
        "\u0f63\u0f7c\u0f0b\u0f58"
    ],
    "name:ceb_x_preferred":[
        "Loma"
    ],
    "name:deu_x_preferred":[
        "Loma"
    ],
    "name:fra_x_preferred":[
        "Loma"
    ],
    "name:ita_x_preferred":[
        "Loma"
    ],
    "name:nld_x_preferred":[
        "Loma"
    ],
    "name:pol_x_preferred":[
        "Loma"
    ],
    "name:pus_x_preferred":[
        "\u0644\u0648\u0645\u0647"
    ],
    "name:spa_x_preferred":[
        "Loma"
    ],
    "name:srp_x_preferred":[
        "\u041b\u043e\u043c\u0430"
    ],
    "name:swe_x_preferred":[
        "Loma"
    ],
    "name:ukr_x_preferred":[
        "\u041b\u043e\u043c\u0430"
    ],
    "name:vol_x_preferred":[
        "Loma"
    ],
    "wof:name":"Loma",
    "wof:placetype":"locality"
},
  "geometry": {"coordinates":[92.02063,29.70923],"type":"Point"}
}