{
  "type": "Feature",
  "properties": {
    "gn:admin1_code":"8.0",
    "gn:asciiname":"Xishagang",
    "gn:country_code":"CN",
    "gn:dem":52,
    "gn:feature_class":"P",
    "gn:feature_code":"PPL",
    "gn:name":"Xishagang",
    "gn:population":0,
    "gn:timezone":"Asia/Shanghai",
    "iso:country":"CN",
    "name:zho_x_preferred":[
        "\u897f\u6c99\u5c97"
    ],
    "wof:name":"Xishagang",
    "wof:placetype":"locality"
},
  "geometry": {"coordinates":[133.34793999999999,47.2776],"type":"Point"}
}