{
  "type": "Feature",
  "properties": {
    "gn:admin1_code":"13.0",
    "gn:asciiname":"Tatilike",
    "gn:country_code":"CN",
    "gn:dem":898,
    "gn:feature_class":"P",
    "gn:feature_code":"PPL",
    "gn:name":"Tatilike",
    "gn:population":0,
    "gn:timezone":"Asia/Urumqi",
    "iso:country":"CN",
    "name:zho_x_preferred":[
        "\u5854\u63d0\u91cc\u514b"
    ],
    "wof:name":"Tatilike",
    "wof:placetype":"locality"
},
  "geometry": {"coordinates":[85.74764,41.09561],"type":"Point"}
}