{
  "type": "Feature",
  "properties": {
    "gn:admin1_code":"4.0",
    "gn:asciiname":"Beiyangzhuang",
    "gn:country_code":"CN",
    "gn:dem":32,
    "gn:feature_class":"P",
    "gn:feature_code":"PPL",
    "gn:name":"Beiyangzhuang",
    "gn:population":0,
    "gn:timezone":"Asia/Shanghai",
    "iso:country":"CN",
    "name:zho_x_preferred":[
        "\u5317\u6768\u5e84"
    ],
    "wof:name":"Beiyangzhuang",
    "wof:placetype":"locality"
},
  "geometry": {"coordinates":[117.82899999999999,34.5167],"type":"Point"}
}