{
  "type": "Feature",
  "properties": {
    "gn:admin1_code":"24.0",
    "gn:asciiname":"Suotuocun",
    "gn:country_code":"CN",
    "gn:dem":1032,
    "gn:feature_class":"P",
    "gn:feature_code":"PPL",
    "gn:name":"Suotuocun",
    "gn:population":0,
    "gn:timezone":"Asia/Shanghai",
    "iso:country":"CN",
    "name:zho_x_preferred":[
        "\u7d22\u9a7c\u6751"
    ],
    "wof:name":"Suotuocun",
    "wof:placetype":"locality"
},
  "geometry": {"coordinates":[110.71203,36.81401],"type":"Point"}
}