{
  "type": "Feature",
  "properties": {
    "gn:admin1_code":"26.0",
    "gn:asciiname":"Tangjiasi",
    "gn:country_code":"CN",
    "gn:dem":1235,
    "gn:feature_class":"P",
    "gn:feature_code":"PPL",
    "gn:name":"Tangjiasi",
    "gn:population":0,
    "gn:timezone":"Asia/Shanghai",
    "iso:country":"CN",
    "name:zho_x_preferred":[
        "\u5510\u5bb6\u5bfa"
    ],
    "wof:name":"Tangjiasi",
    "wof:placetype":"locality"
},
  "geometry": {"coordinates":[109.64524,36.02354000000001],"type":"Point"}
}