{
  "type": "Feature",
  "properties": {
    "gn:admin1_code":"11",
    "gn:asciiname":"Gumuxi",
    "gn:country_code":"CN",
    "gn:dem":321,
    "gn:feature_class":"P",
    "gn:feature_code":"PPL",
    "gn:name":"Gumuxi",
    "gn:population":0,
    "gn:timezone":"Asia/Shanghai",
    "iso:country":"CN",
    "name:zho_x_preferred":[
        "\u8c37\u6bcd\u6eaa"
    ],
    "wof:name":"Gumuxi",
    "wof:placetype":"locality"
},
  "geometry": {"coordinates":[111.41297,25.22956],"type":"Point"}
}