{
  "type": "Feature",
  "properties": {
    "gn:admin1_code":"11.0",
    "gn:asciiname":"Maotangwan",
    "gn:country_code":"CN",
    "gn:dem":154,
    "gn:feature_class":"P",
    "gn:feature_code":"PPL",
    "gn:name":"Maotangwan",
    "gn:population":0,
    "gn:timezone":"Asia/Shanghai",
    "iso:country":"CN",
    "name:zho_x_preferred":[
        "\u8305\u5858\u6e7e"
    ],
    "wof:name":"Maotangwan",
    "wof:placetype":"locality"
},
  "geometry": {"coordinates":[111.73607,27.7667],"type":"Point"}
}