{
  "type": "Feature",
  "properties": {
    "gn:admin1_code":"5.0",
    "gn:asciiname":"Dongjinkeng",
    "gn:country_code":"CN",
    "gn:dem":666,
    "gn:feature_class":"P",
    "gn:feature_code":"PPL",
    "gn:name":"Dongjinkeng",
    "gn:population":0,
    "gn:timezone":"Asia/Shanghai",
    "iso:country":"CN",
    "name:zho_x_preferred":[
        "\u4e1c\u91d1\u5751"
    ],
    "wof:name":"Dongjinkeng",
    "wof:placetype":"locality"
},
  "geometry": {"coordinates":[126.48078,41.91107],"type":"Point"}
}