{
  "type": "Feature",
  "properties": {
    "gn:admin1_code":"14.0",
    "gn:asciiname":"Wengdagangcun",
    "gn:country_code":"CN",
    "gn:dem":3493,
    "gn:feature_class":"P",
    "gn:feature_code":"PPL",
    "gn:name":"Wengdagangcun",
    "gn:population":0,
    "gn:timezone":"Asia/Urumqi",
    "iso:country":"CN",
    "name:zho_x_preferred":[
        "\u7fc1\u8fbe\u5c97\u6751"
    ],
    "wof:name":"Wengdagangcun",
    "wof:placetype":"locality"
},
  "geometry": {"coordinates":[97.0916,31.68687000000001],"type":"Point"}
}