{
  "type": "Feature",
  "properties": {
    "gn:admin1_code":"15.0",
    "gn:asciiname":"Qijiazhuang",
    "gn:country_code":"CN",
    "gn:dem":2324,
    "gn:feature_class":"P",
    "gn:feature_code":"PPL",
    "gn:name":"Qijiazhuang",
    "gn:population":0,
    "gn:timezone":"Asia/Shanghai",
    "iso:country":"CN",
    "name:und_x_variant":[
        "\u9f50\u5bb6\u5e84"
    ],
    "wof:name":"Qijiazhuang",
    "wof:placetype":"locality"
},
  "geometry": {"coordinates":[103.98135000000001,34.42693],"type":"Point"}
}