{
  "type": "Feature",
  "properties": {
    "gn:admin1_code":"14.0",
    "gn:asciiname":"Lianqiukacun",
    "gn:country_code":"CN",
    "gn:dem":4577,
    "gn:feature_class":"P",
    "gn:feature_code":"PPL",
    "gn:name":"Lianqiukacun",
    "gn:population":0,
    "gn:timezone":"Asia/Urumqi",
    "iso:country":"CN",
    "name:zho_x_preferred":[
        "\u8054\u79cb\u5494\u6751"
    ],
    "wof:name":"Lianqiukacun",
    "wof:placetype":"locality"
},
  "geometry": {"coordinates":[91.41463,31.54465],"type":"Point"}
}