{
  "type": "Feature",
  "properties": {
    "gn:admin1_code":"19.0",
    "gn:asciiname":"Qianxinqiucun",
    "gn:country_code":"CN",
    "gn:dem":111,
    "gn:feature_class":"P",
    "gn:feature_code":"PPL",
    "gn:name":"Qianxinqiucun",
    "gn:population":0,
    "gn:timezone":"Asia/Shanghai",
    "iso:country":"CN",
    "name:zho_x_preferred":[
        "\u524d\u65b0\u79cb\u6751"
    ],
    "wof:name":"Qianxinqiucun",
    "wof:placetype":"locality"
},
  "geometry": {"coordinates":[122.843,42.4902],"type":"Point"}
}