{
  "type": "Feature",
  "properties": {
    "gn:country":"CN",
    "gn:fcode":"ADM3",
    "gn:pop":0,
    "iso:country":"CN",
    "name:unk_x_variant":[
        "Tu-y\u00fcn Shih"
    ],
    "name:zho_x_preferred":[
        "\u90fd\u5300\u5e02"
    ],
    "name:zho_x_variant":[
        "\u90fd\u5300"
    ],
    "qs:name":"Duyun Shi",
    "qs:photos_9r":0,
    "qs:photos_sr":0,
    "qs:pop_sr":"0",
    "wof:name":"Duyun Shi",
    "wof:placetype":"localadmin",
    "wof:population":0
},
  "geometry": {"coordinates":[107.44955,26.19008],"type":"Point"}
}