{
  "type": "Feature",
  "properties": {
    "gn:admin1_code":"12.0",
    "gn:asciiname":"Dawolong",
    "gn:country_code":"CN",
    "gn:dem":726,
    "gn:feature_class":"P",
    "gn:feature_code":"PPL",
    "gn:name":"Dawolong",
    "gn:population":0,
    "gn:timezone":"Asia/Shanghai",
    "iso:country":"CN",
    "name:zho_x_preferred":[
        "\u5927\u5367\u9f99"
    ],
    "wof:name":"Dawolong",
    "wof:placetype":"locality"
},
  "geometry": {"coordinates":[109.70753000000001,30.0804],"type":"Point"}
}