{
  "type": "Feature",
  "properties": {
    "gn:admin1_code":"31",
    "gn:asciiname":"Mumian",
    "gn:country_code":"CN",
    "gn:dem":190,
    "gn:feature_class":"P",
    "gn:feature_code":"PPL",
    "gn:name":"Mumian",
    "gn:population":0,
    "gn:timezone":"Asia/Shanghai",
    "iso:country":"CN",
    "name:und_x_variant":[
        "\u6728\u68c9"
    ],
    "wof:name":"Mumian",
    "wof:placetype":"locality"
},
  "geometry": {"coordinates":[109.16800000000001,18.6419],"type":"Point"}
}