{
  "type": "Feature",
  "properties": {
    "gn:admin1_code":"33.0",
    "gn:asciiname":"Dafo",
    "gn:country_code":"CN",
    "gn:dem":653,
    "gn:feature_class":"P",
    "gn:feature_code":"PPL",
    "gn:name":"Dafo",
    "gn:population":0,
    "gn:timezone":"Asia/Shanghai",
    "iso:country":"CN",
    "name:zho_x_preferred":[
        "\u5927\u4f5b"
    ],
    "wof:name":"Dafo",
    "wof:placetype":"locality"
},
  "geometry": {"coordinates":[106.66,29.2418],"type":"Point"}
}