{
  "type": "Feature",
  "properties": {
    "gn:admin1_code":"14.0",
    "gn:asciiname":"Aluocun",
    "gn:country_code":"CN",
    "gn:dem":3984,
    "gn:feature_class":"P",
    "gn:feature_code":"PPL",
    "gn:name":"Aluocun",
    "gn:population":0,
    "gn:timezone":"Asia/Urumqi",
    "iso:country":"CN",
    "name:zho_x_preferred":[
        "\u963f\u6d1b\u6751"
    ],
    "wof:name":"Aluocun",
    "wof:placetype":"locality"
},
  "geometry": {"coordinates":[98.49496000000001,30.61722],"type":"Point"}
}