{
  "type": "Feature",
  "properties": {
    "gn:admin1_code":"3.0",
    "gn:asciiname":"Qulaicun",
    "gn:country_code":"CN",
    "gn:dem":301,
    "gn:feature_class":"P",
    "gn:feature_code":"PPL",
    "gn:name":"Qulaicun",
    "gn:population":0,
    "gn:timezone":"Asia/Shanghai",
    "iso:country":"CN",
    "name:und_x_variant":[
        "\u66f2\u8d56\u6751"
    ],
    "wof:name":"Qulaicun",
    "wof:placetype":"locality"
},
  "geometry": {"coordinates":[116.06001999999999,26.30597],"type":"Point"}
}