{
  "type": "Feature",
  "properties": {
    "gn:admin1_code":"33.0",
    "gn:asciiname":"Tucheng",
    "gn:country_code":"CN",
    "gn:dem":1014,
    "gn:feature_class":"P",
    "gn:feature_code":"PPL",
    "gn:name":"Tucheng",
    "gn:population":0,
    "gn:timezone":"Asia/Shanghai",
    "iso:country":"CN",
    "name:zho_x_preferred":[
        "\u571f\u57ce"
    ],
    "wof:name":"Tucheng",
    "wof:placetype":"locality"
},
  "geometry": {"coordinates":[108.29516,30.9103],"type":"Point"}
}