{
  "type": "Feature",
  "properties": {
    "gn:admin1_code":"12.0",
    "gn:asciiname":"Hujiabao",
    "gn:country_code":"CN",
    "gn:dem":683,
    "gn:feature_class":"P",
    "gn:feature_code":"PPL",
    "gn:name":"Hujiabao",
    "gn:population":0,
    "gn:timezone":"Asia/Shanghai",
    "iso:country":"CN",
    "name:zho_x_preferred":[
        "\u80e1\u5bb6\u5305"
    ],
    "wof:name":"Hujiabao",
    "wof:placetype":"locality"
},
  "geometry": {"coordinates":[111.11415,31.93414000000001],"type":"Point"}
}