{
  "type": "Feature",
  "properties": {
    "gn:admin1_code":"24.0",
    "gn:asciiname":"Guandaoyao",
    "gn:country_code":"CN",
    "gn:dem":1112,
    "gn:feature_class":"P",
    "gn:feature_code":"PPL",
    "gn:name":"Guandaoyao",
    "gn:population":0,
    "gn:timezone":"Asia/Shanghai",
    "iso:country":"CN",
    "name:zho_x_preferred":[
        "\u5b98\u9053\u7a91"
    ],
    "wof:name":"Guandaoyao",
    "wof:placetype":"locality"
},
  "geometry": {"coordinates":[111.35272999999999,36.24735],"type":"Point"}
}