{
  "type": "Feature",
  "properties": {
    "gn:admin1_code":"22.0",
    "gn:asciiname":"Saoziying",
    "gn:country_code":"CN",
    "gn:dem":52,
    "gn:feature_class":"P",
    "gn:feature_code":"PPL",
    "gn:name":"Saoziying",
    "gn:population":0,
    "gn:timezone":"Asia/Shanghai",
    "iso:country":"CN",
    "name:zho_x_preferred":[
        "\u9a9a\u5b50\u8425"
    ],
    "wof:name":"Saoziying",
    "wof:placetype":"locality"
},
  "geometry": {"coordinates":[116.27819,40.00743],"type":"Point"}
}