{
  "type": "Feature",
  "properties": {
    "gn:admin1_code":"32.0",
    "gn:asciiname":"Yuanjia Pingshang",
    "gn:country_code":"CN",
    "gn:dem":1384,
    "gn:feature_class":"P",
    "gn:feature_code":"PPL",
    "gn:name":"Yuanjia Pingshang",
    "gn:population":0,
    "gn:timezone":"Asia/Shanghai",
    "iso:country":"CN",
    "name:zho_x_preferred":[
        "\u8881\u5bb6\u576a\u4e0a"
    ],
    "wof:name":"Yuanjia Pingshang",
    "wof:placetype":"locality"
},
  "geometry": {"coordinates":[105.10684999999999,32.567],"type":"Point"}
}