{
  "type": "Feature",
  "properties": {
    "gn:admin1_code":"19.0",
    "gn:asciiname":"Bajiacun",
    "gn:country_code":"CN",
    "gn:dem":512,
    "gn:feature_class":"P",
    "gn:feature_code":"PPL",
    "gn:name":"Bajiacun",
    "gn:population":0,
    "gn:timezone":"Asia/Shanghai",
    "iso:country":"CN",
    "name:zho_x_preferred":[
        "\u516b\u5bb6\u6751"
    ],
    "wof:name":"Bajiacun",
    "wof:placetype":"locality"
},
  "geometry": {"coordinates":[119.0124,41.02459],"type":"Point"}
}