{
  "type": "Feature",
  "properties": {
    "gn:admin1_code":"30",
    "gn:asciiname":"Shibi",
    "gn:country_code":"CN",
    "gn:dem":60,
    "gn:feature_class":"P",
    "gn:feature_code":"PPL",
    "gn:name":"Shibi",
    "gn:population":0,
    "gn:timezone":"Asia/Shanghai",
    "iso:country":"CN",
    "name:ceb_x_preferred":[
        "Shibi"
    ],
    "name:deu_x_preferred":[
        "Shibi"
    ],
    "name:swe_x_preferred":[
        "Shibi"
    ],
    "name:zho_x_preferred":[
        "\u77f3\u58c1"
    ],
    "wof:name":"Shibi",
    "wof:placetype":"locality"
},
  "geometry": {"coordinates":[116.39891,23.40967],"type":"Point"}
}