{
  "type": "Feature",
  "properties": {
    "gn:admin1_code":"19.0",
    "gn:asciiname":"Shahegouli",
    "gn:country_code":"CN",
    "gn:dem":307,
    "gn:feature_class":"P",
    "gn:feature_code":"PPL",
    "gn:name":"Shahegouli",
    "gn:population":0,
    "gn:timezone":"Asia/Shanghai",
    "iso:country":"CN",
    "name:und_x_variant":[
        "\u6c99\u6cb3\u6c9f\u91cc"
    ],
    "wof:name":"Shahegouli",
    "wof:placetype":"locality"
},
  "geometry": {"coordinates":[123.57764,40.67065],"type":"Point"}
}