{
  "type": "Feature",
  "properties": {
    "gn:admin1_code":"4.0",
    "gn:asciiname":"Guiliu",
    "gn:country_code":"CN",
    "gn:dem":5,
    "gn:feature_class":"P",
    "gn:feature_code":"PPL",
    "gn:name":"Guiliu",
    "gn:population":0,
    "gn:timezone":"Asia/Shanghai",
    "iso:country":"CN",
    "name:zho_x_preferred":[
        "Guiliu"
    ],
    "name:zho_x_variant":[
        "\u6842\u5218"
    ],
    "wof:name":"Guiliu",
    "wof:placetype":"locality"
},
  "geometry": {"coordinates":[120.22942999999999,34.24714],"type":"Point"}
}