{
  "type": "Feature",
  "properties": {
    "gn:admin1_code":"29.0",
    "gn:asciiname":"Bingding",
    "gn:country_code":"CN",
    "gn:dem":2556,
    "gn:feature_class":"P",
    "gn:feature_code":"PPL",
    "gn:name":"Bingding",
    "gn:population":0,
    "gn:timezone":"Asia/Shanghai",
    "iso:country":"CN",
    "name:zho_x_preferred":[
        "\u5175\u4e01"
    ],
    "wof:name":"Bingding",
    "wof:placetype":"locality"
},
  "geometry": {"coordinates":[99.2107,27.3931],"type":"Point"}
}