{
  "type": "Feature",
  "properties": {
    "gn:admin1_code":"32.0",
    "gn:asciiname":"Liyuzhai",
    "gn:country_code":"CN",
    "gn:dem":2478,
    "gn:feature_class":"P",
    "gn:feature_code":"PPL",
    "gn:name":"Liyuzhai",
    "gn:population":0,
    "gn:timezone":"Asia/Shanghai",
    "iso:country":"CN",
    "name:zho_x_preferred":[
        "\u9ca4\u9c7c\u5be8"
    ],
    "wof:name":"Liyuzhai",
    "wof:placetype":"locality"
},
  "geometry": {"coordinates":[103.78400000000001,31.8364],"type":"Point"}
}