{
  "type": "Feature",
  "properties": {
    "gn:admin1_code":"03",
    "gn:asciiname":"Chijiang",
    "gn:cc2":"CN",
    "gn:country_code":"CN",
    "gn:dem":144,
    "gn:feature_class":"P",
    "gn:feature_code":"PPL",
    "gn:name":"Chijiang",
    "gn:population":0,
    "gn:timezone":"Asia/Shanghai",
    "iso:country":"CN",
    "name:und_x_variant":[
        "Ch\u2019ih-chiang",
        "Chijiang"
    ],
    "wof:name":"Chijiang",
    "wof:placetype":"locality"
},
  "geometry": {"coordinates":[114.55,25.48333],"type":"Point"}
}