{
  "type": "Feature",
  "properties": {
    "gn:admin1_code":"18",
    "gn:asciiname":"Tuanfeng",
    "gn:country_code":"CN",
    "gn:dem":1019,
    "gn:feature_class":"P",
    "gn:feature_code":"PPL",
    "gn:name":"Tuanfeng",
    "gn:population":0,
    "gn:timezone":"Asia/Shanghai",
    "iso:country":"CN",
    "name:zho_x_preferred":[
        "\u56e2\u4e30"
    ],
    "wof:name":"Tuanfeng",
    "wof:placetype":"locality"
},
  "geometry": {"coordinates":[106.14700000000001,25.7813],"type":"Point"}
}