{
  "type": "Feature",
  "properties": {
    "gn:admin1_code":"12.0",
    "gn:asciiname":"Dongguijiapu",
    "gn:country_code":"CN",
    "gn:dem":33,
    "gn:feature_class":"P",
    "gn:feature_code":"PPL",
    "gn:name":"Dongguijiapu",
    "gn:population":0,
    "gn:timezone":"Asia/Shanghai",
    "iso:country":"CN",
    "name:zho_x_preferred":[
        "\u4e1c\u6842\u5bb6\u94fa"
    ],
    "wof:name":"Dongguijiapu",
    "wof:placetype":"locality"
},
  "geometry": {"coordinates":[112.59977000000001,29.6687],"type":"Point"}
}