{
  "type": "Feature",
  "properties": {
    "gn:admin1_code":"15.0",
    "gn:asciiname":"Xia'anmen",
    "gn:country_code":"CN",
    "gn:dem":1955,
    "gn:feature_class":"P",
    "gn:feature_code":"PPL",
    "gn:name":"Xia\u2019anmen",
    "gn:population":0,
    "gn:timezone":"Asia/Shanghai",
    "iso:country":"CN",
    "name:und_x_variant":[
        "Xia\u2019anmen"
    ],
    "name:zho_x_preferred":[
        "\u4e0b\u5b89\u95e8"
    ],
    "wof:name":"Xia'anmen",
    "wof:placetype":"locality"
},
  "geometry": {"coordinates":[101.892,38.3306],"type":"Point"}
}