{
  "type": "Feature",
  "properties": {
    "gn:admin1_code":"16",
    "gn:asciiname":"Duimenhe",
    "gn:country_code":"CN",
    "gn:dem":771,
    "gn:feature_class":"P",
    "gn:feature_code":"PPL",
    "gn:name":"Duimenhe",
    "gn:population":0,
    "gn:timezone":"Asia/Shanghai",
    "iso:country":"CN",
    "name:zho_x_preferred":[
        "\u5bf9\u95e8\u6cb3"
    ],
    "wof:name":"Duimenhe",
    "wof:placetype":"locality"
},
  "geometry": {"coordinates":[109.98099999999999,26.1641],"type":"Point"}
}