{
  "type": "Feature",
  "properties": {
    "gn:admin1_code":"32.0",
    "gn:asciiname":"Jindingshan",
    "gn:country_code":"CN",
    "gn:dem":324,
    "gn:feature_class":"P",
    "gn:feature_code":"PPL",
    "gn:name":"Jindingshan",
    "gn:population":0,
    "gn:timezone":"Asia/Shanghai",
    "iso:country":"CN",
    "name:zho_x_preferred":[
        "\u91d1\u9f0e\u5c71"
    ],
    "wof:name":"Jindingshan",
    "wof:placetype":"locality"
},
  "geometry": {"coordinates":[106.65300000000001,30.3522],"type":"Point"}
}