{
  "type": "Feature",
  "properties": {
    "gn:admin1_code":"02",
    "gn:asciiname":"Gaokantoucun",
    "gn:country_code":"CN",
    "gn:dem":53,
    "gn:feature_class":"P",
    "gn:feature_code":"PPL",
    "gn:name":"Gaokantoucun",
    "gn:population":0,
    "gn:timezone":"Asia/Shanghai",
    "iso:country":"CN",
    "name:und_x_variant":[
        "Gaokantou",
        "Gaokantoucun"
    ],
    "name:zho_x_preferred":[
        "\u9ad8\u574e\u5934"
    ],
    "name:zho_x_variant":[
        "\u9ad8\u574e\u5934\u6751"
    ],
    "wof:name":"Gaokantoucun",
    "wof:placetype":"locality"
},
  "geometry": {"coordinates":[121.91827000000001,29.11793],"type":"Point"}
}