{
  "type": "Feature",
  "properties": {
    "gn:admin1_code":"5.0",
    "gn:asciiname":"Wudao Hezi",
    "gn:country_code":"CN",
    "gn:dem":471,
    "gn:feature_class":"P",
    "gn:feature_code":"PPL",
    "gn:name":"Wudao Hezi",
    "gn:population":0,
    "gn:timezone":"Asia/Shanghai",
    "iso:country":"CN",
    "name:zho_x_preferred":[
        "\u4e94\u9053\u6cb3\u5b50"
    ],
    "wof:name":"Wudao Hezi",
    "wof:placetype":"locality"
},
  "geometry": {"coordinates":[127.75293000000001,44.03918],"type":"Point"}
}