{
  "type": "Feature",
  "properties": {
    "gn:admin1_code":"11.0",
    "gn:asciiname":"Shangdaheshan",
    "gn:country_code":"CN",
    "gn:dem":80,
    "gn:feature_class":"P",
    "gn:feature_code":"PPL",
    "gn:name":"Shangdaheshan",
    "gn:population":0,
    "gn:timezone":"Asia/Shanghai",
    "iso:country":"CN",
    "name:zho_x_preferred":[
        "\u4e0a\u5927\u79be\u5c71"
    ],
    "wof:name":"Shangdaheshan",
    "wof:placetype":"locality"
},
  "geometry": {"coordinates":[112.86248999999999,27.02005],"type":"Point"}
}