{
  "type": "Feature",
  "properties": {
    "iso:country":"CN",
    "name:eng_x_preferred":[
        "Changping"
    ],
    "name:zho_x_preferred":[
        "\u5e38\u5e73\u9547"
    ],
    "qs:name":"\u5e38\u5e73\u9547",
    "qs:name_adm0":"\u4e2d\u570b",
    "qs:name_adm1":"\u5e7f\u4e1c\u7701",
    "qs:photos":95,
    "qs:photos_1k":19,
    "qs:photos_9k":1,
    "qs:photos_9r":3,
    "qs:photos_all":95,
    "qs:photos_sr":3,
    "qs:placetype":"Town",
    "qs:pop_sr":"0",
    "wof:name":"Changping",
    "wof:placetype":"locality"
},
  "geometry": {"coordinates":[113.99774499999999,22.972177],"type":"Point"}
}