{
  "type": "Feature",
  "properties": {
    "iso:country":"CN",
    "name:ara_x_preferred":[
        "\u062a\u0634\u0627\u0646\u063a\u0628\u064a\u0646\u063a"
    ],
    "name:ben_x_preferred":[
        "\u099a\u09cd\u09af\u09be\u0982\u09aa\u09bf\u0982"
    ],
    "name:deu_x_preferred":[
        "Changping"
    ],
    "name:ell_x_preferred":[
        "\u03a4\u03c3\u03b1\u03bd\u03b3\u03ba\u03c0\u03af\u03bd\u03b3\u03ba"
    ],
    "name:eng_x_preferred":[
        "Changping"
    ],
    "name:fas_x_preferred":[
        "\u0686\u0627\u0646\u06af \u067e\u06cc\u0646\u06af"
    ],
    "name:fra_x_preferred":[
        "Changping"
    ],
    "name:heb_x_preferred":[
        "\u05e6'\u05e0\u05d2\u05e4\u05d9\u05e0\u05d2"
    ],
    "name:hin_x_preferred":[
        "\u091a\u0948\u0902\u0917\u092a\u093f\u0902\u0917"
    ],
    "name:hun_x_preferred":[
        "Changping"
    ],
    "name:ind_x_preferred":[
        "Changping"
    ],
    "name:ita_x_preferred":[
        "Changping"
    ],
    "name:jpn_x_preferred":[
        "\u5e38\u5e73\u9547"
    ],
    "name:kor_x_preferred":[
        "\ucc3d\ud551"
    ],
    "name:nld_x_preferred":[
        "Changping"
    ],
    "name:pol_x_preferred":[
        "Changping"
    ],
    "name:por_x_preferred":[
        "Changping"
    ],
    "name:rus_x_preferred":[
        "\u0427\u0430\u043d\u043f\u0438\u043d"
    ],
    "name:spa_x_preferred":[
        "Changping"
    ],
    "name:swe_x_preferred":[
        "Changping"
    ],
    "name:tur_x_preferred":[
        "Changping"
    ],
    "name:ukr_x_preferred":[
        "\u0427\u0430\u043d\u043f\u0456\u043d"
    ],
    "name:urd_x_preferred":[
        "\u0686\u06cc\u0646\u06af\u067e\u0646\u06af"
    ],
    "name:vie_x_preferred":[
        "X\u01b0\u01a1ng B\u00ecnh"
    ],
    "name:zho_cn_x_preferred":[
        "\u5e38\u5e73\u9547"
    ],
    "name:zho_tw_x_preferred":[
        "\u5e38\u5e73"
    ],
    "name:zho_x_preferred":[
        "\u5e38\u5e73\u9547"
    ],
    "qs:name":"\u5e38\u5e73\u9547",
    "qs:name_adm0":"\u4e2d\u570b",
    "qs:name_adm1":"\u5e7f\u4e1c\u7701",
    "qs:photos":95,
    "qs:photos_1k":19,
    "qs:photos_9k":1,
    "qs:photos_9r":3,
    "qs:photos_all":95,
    "qs:photos_sr":3,
    "qs:placetype":"Town",
    "qs:pop_sr":"0",
    "wof:name":"Changping",
    "wof:placetype":"locality"
},
  "geometry": {"coordinates":[113.99774499999999,22.972177],"type":"Point"}
}