{
  "type": "Feature",
  "properties": {
    "gn:admin1_code":"8.0",
    "gn:asciiname":"Erdaogangzi",
    "gn:country_code":"CN",
    "gn:dem":123,
    "gn:feature_class":"P",
    "gn:feature_code":"PPL",
    "gn:name":"Erdaogangzi",
    "gn:population":0,
    "gn:timezone":"Asia/Shanghai",
    "iso:country":"CN",
    "name:zho_x_preferred":[
        "\u4e8c\u9053\u5c97\u5b50"
    ],
    "wof:name":"Erdaogangzi",
    "wof:placetype":"locality"
},
  "geometry": {"coordinates":[125.71402,45.47479000000001],"type":"Point"}
}