{
  "type": "Feature",
  "properties": {
    "gn:admin1_code":"10.0",
    "gn:asciiname":"Liuchengzi",
    "gn:country_code":"CN",
    "gn:dem":248,
    "gn:feature_class":"P",
    "gn:feature_code":"PPL",
    "gn:name":"Liuchengzi",
    "gn:population":0,
    "gn:timezone":"Asia/Shanghai",
    "iso:country":"CN",
    "name:zho_x_preferred":[
        "\u5218\u57ce\u5b50"
    ],
    "wof:name":"Liuchengzi",
    "wof:placetype":"locality"
},
  "geometry": {"coordinates":[119.72335,40.18279],"type":"Point"}
}