{
  "type": "Feature",
  "properties": {
    "gn:admin1_code":"1.0",
    "gn:asciiname":"Shanguan",
    "gn:country_code":"CN",
    "gn:dem":68,
    "gn:feature_class":"P",
    "gn:feature_code":"PPL",
    "gn:name":"Shanguan",
    "gn:population":0,
    "gn:timezone":"Asia/Shanghai",
    "iso:country":"CN",
    "name:zho_x_preferred":[
        "Shanguan"
    ],
    "name:zho_x_variant":[
        "\u5c71\u5173"
    ],
    "wof:name":"Shanguan",
    "wof:placetype":"locality"
},
  "geometry": {"coordinates":[119.37766000000001,30.89764000000001],"type":"Point"}
}