{
  "type": "Feature",
  "properties": {
    "gn:admin1_code":"26.0",
    "gn:asciiname":"Bailonggou",
    "gn:country_code":"CN",
    "gn:dem":532,
    "gn:feature_class":"P",
    "gn:feature_code":"PPL",
    "gn:name":"Bailonggou",
    "gn:population":0,
    "gn:timezone":"Asia/Shanghai",
    "iso:country":"CN",
    "name:zho_x_preferred":[
        "\u767d\u9f99\u6c9f"
    ],
    "wof:name":"Bailonggou",
    "wof:placetype":"locality"
},
  "geometry": {"coordinates":[108.4875,34.0475],"type":"Point"}
}