{
  "type": "Feature",
  "properties": {
    "gn:admin1_code":"9.0",
    "gn:asciiname":"Loudidian",
    "gn:country_code":"CN",
    "gn:dem":43,
    "gn:feature_class":"P",
    "gn:feature_code":"PPL",
    "gn:name":"Loudidian",
    "gn:population":0,
    "gn:timezone":"Asia/Shanghai",
    "iso:country":"CN",
    "name:zho_x_preferred":[
        "\u5a04\u5824\u5e97"
    ],
    "wof:name":"Loudidian",
    "wof:placetype":"locality"
},
  "geometry": {"coordinates":[114.83263999999998,33.27775],"type":"Point"}
}