{
  "type": "Feature",
  "properties": {
    "gn:admin1_code":"19.0",
    "gn:asciiname":"Jinjia Kouzi",
    "gn:country_code":"CN",
    "gn:dem":69,
    "gn:feature_class":"P",
    "gn:feature_code":"PPL",
    "gn:name":"Jinjia Kouzi",
    "gn:population":0,
    "gn:timezone":"Asia/Shanghai",
    "iso:country":"CN",
    "name:zho_x_preferred":[
        "\u91d1\u5bb6\u53e3\u5b50"
    ],
    "wof:name":"Jinjia Kouzi",
    "wof:placetype":"locality"
},
  "geometry": {"coordinates":[122.68979,40.76654],"type":"Point"}
}