{
  "type": "Feature",
  "properties": {
    "gn:admin1_code":"8.0",
    "gn:asciiname":"Guangmingcun",
    "gn:country_code":"CN",
    "gn:dem":162,
    "gn:feature_class":"P",
    "gn:feature_code":"PPL",
    "gn:name":"Guangmingcun",
    "gn:population":0,
    "gn:timezone":"Asia/Shanghai",
    "iso:country":"CN",
    "name:zho_x_preferred":[
        "\u5149\u660e\u6751"
    ],
    "wof:name":"Guangmingcun",
    "wof:placetype":"locality"
},
  "geometry": {"coordinates":[126.76415,45.69834],"type":"Point"}
}