{
  "type": "Feature",
  "properties": {
    "gn:admin1_code":"9.0",
    "gn:asciiname":"Litan",
    "gn:country_code":"CN",
    "gn:dem":58,
    "gn:feature_class":"P",
    "gn:feature_code":"PPL",
    "gn:name":"Litan",
    "gn:population":0,
    "gn:timezone":"Asia/Shanghai",
    "iso:country":"CN",
    "name:zho_x_preferred":[
        "\u9ca4\u6ee9"
    ],
    "wof:name":"Litan",
    "wof:placetype":"locality"
},
  "geometry": {"coordinates":[114.49191999999999,33.9355],"type":"Point"}
}