{
  "type": "Feature",
  "properties": {
    "gn:admin1_code":"4.0",
    "gn:asciiname":"Dongzengcun",
    "gn:country_code":"CN",
    "gn:dem":2,
    "gn:feature_class":"P",
    "gn:feature_code":"PPL",
    "gn:name":"Dongzengcun",
    "gn:population":0,
    "gn:timezone":"Asia/Shanghai",
    "iso:country":"CN",
    "name:zho_x_preferred":[
        "\u4e1c\u7f7e\u6751"
    ],
    "wof:name":"Dongzengcun",
    "wof:placetype":"locality"
},
  "geometry": {"coordinates":[120.07373,34.29572],"type":"Point"}
}