{
  "type": "Feature",
  "properties": {
    "gn:admin1_code":"25.0",
    "gn:asciiname":"Erzhang",
    "gn:country_code":"CN",
    "gn:dem":20,
    "gn:feature_class":"P",
    "gn:feature_code":"PPL",
    "gn:name":"Erzhang",
    "gn:population":0,
    "gn:timezone":"Asia/Shanghai",
    "iso:country":"CN",
    "name:zho_x_preferred":[
        "\u4e8c\u7ae0"
    ],
    "wof:name":"Erzhang",
    "wof:placetype":"locality"
},
  "geometry": {"coordinates":[122.31834000000001,37.05624],"type":"Point"}
}