{
  "type": "Feature",
  "properties": {
    "gn:admin1_code":"7",
    "gn:asciiname":"Haotan",
    "gn:country_code":"CN",
    "gn:dem":182,
    "gn:feature_class":"P",
    "gn:feature_code":"PPL",
    "gn:name":"Haotan",
    "gn:population":0,
    "gn:timezone":"Asia/Shanghai",
    "iso:country":"CN",
    "name:und_x_variant":[
        "\u8814\u6f6d"
    ],
    "name:zho_x_preferred":[
        "\u8814\u6f6d"
    ],
    "wof:name":"Haotan",
    "wof:placetype":"locality"
},
  "geometry": {"coordinates":[117.39361,23.91361],"type":"Point"}
}