{
  "type": "Feature",
  "properties": {
    "gn:admin1_code":"9.0",
    "gn:asciiname":"Wangmeng Linzhuang",
    "gn:country_code":"CN",
    "gn:dem":43,
    "gn:feature_class":"P",
    "gn:feature_code":"PPL",
    "gn:name":"Wangmeng Linzhuang",
    "gn:population":0,
    "gn:timezone":"Asia/Shanghai",
    "iso:country":"CN",
    "name:zho_x_preferred":[
        "\u738b\u5b5f\u6797\u5e84"
    ],
    "wof:name":"Wangmeng Linzhuang",
    "wof:placetype":"locality"
},
  "geometry": {"coordinates":[115.00524,33.28618],"type":"Point"}
}