{
  "type": "Feature",
  "properties": {
    "gn:admin1_code":"3",
    "gn:asciiname":"Huyang",
    "gn:country_code":"CN",
    "gn:dem":277,
    "gn:feature_class":"P",
    "gn:feature_code":"PPL",
    "gn:name":"Huyang",
    "gn:population":0,
    "gn:timezone":"Asia/Shanghai",
    "iso:country":"CN",
    "name:und_x_variant":[
        "\u6e56\u6d0b"
    ],
    "wof:name":"Huyang",
    "wof:placetype":"locality"
},
  "geometry": {"coordinates":[116.23659000000001,25.99684],"type":"Point"}
}