{
  "type": "Feature",
  "properties": {
    "gn:admin1_code":"1.0",
    "gn:asciiname":"Songjingcun",
    "gn:country_code":"CN",
    "gn:dem":28,
    "gn:feature_class":"P",
    "gn:feature_code":"PPL",
    "gn:name":"Songjingcun",
    "gn:population":0,
    "gn:timezone":"Asia/Shanghai",
    "iso:country":"CN",
    "name:und_x_variant":[
        "Songjing"
    ],
    "name:zho_x_preferred":[
        "\u5b8b\u4e95\u6751"
    ],
    "wof:name":"Songjingcun",
    "wof:placetype":"locality"
},
  "geometry": {"coordinates":[116.29068999999998,32.85581],"type":"Point"}
}