{
  "type": "Feature",
  "properties": {
    "gn:admin1_code":"9.0",
    "gn:asciiname":"Shangmigang",
    "gn:country_code":"CN",
    "gn:dem":130,
    "gn:feature_class":"P",
    "gn:feature_code":"PPL",
    "gn:name":"Shangmigang",
    "gn:population":0,
    "gn:timezone":"Asia/Shanghai",
    "iso:country":"CN",
    "name:zho_x_preferred":[
        "\u4e0a\u7c73\u5c97"
    ],
    "wof:name":"Shangmigang",
    "wof:placetype":"locality"
},
  "geometry": {"coordinates":[112.10463,32.80649],"type":"Point"}
}