{
  "type": "Feature",
  "properties": {
    "gn:admin1_code":"30.0",
    "gn:asciiname":"Bulicun",
    "gn:country_code":"CN",
    "gn:dem":66,
    "gn:feature_class":"P",
    "gn:feature_code":"PPL",
    "gn:name":"Bulicun",
    "gn:population":0,
    "gn:timezone":"Asia/Shanghai",
    "iso:country":"CN",
    "name:zho_x_preferred":[
        "\u5e03\u91cc\u6751"
    ],
    "wof:name":"Bulicun",
    "wof:placetype":"locality"
},
  "geometry": {"coordinates":[116.31038999999998,24.41538],"type":"Point"}
}