{
  "type": "Feature",
  "properties": {
    "gn:admin1_code":"5.0",
    "gn:asciiname":"Lanxiang Wobu",
    "gn:country_code":"CN",
    "gn:dem":126,
    "gn:feature_class":"P",
    "gn:feature_code":"PPL",
    "gn:name":"Lanxiang Wobu",
    "gn:population":0,
    "gn:timezone":"Asia/Shanghai",
    "iso:country":"CN",
    "name:zho_x_preferred":[
        "\u5170\u9999\u7a9d\u5821"
    ],
    "wof:name":"Lanxiang Wobu",
    "wof:placetype":"locality"
},
  "geometry": {"coordinates":[125.55383999999999,45.41538],"type":"Point"}
}