{
  "type": "Feature",
  "properties": {
    "gn:admin1_code":"26",
    "gn:asciiname":"Tiewang",
    "gn:country_code":"CN",
    "gn:dem":920,
    "gn:feature_class":"P",
    "gn:feature_code":"PPL",
    "gn:name":"Tiewang",
    "gn:population":0,
    "gn:timezone":"Asia/Shanghai",
    "iso:country":"CN",
    "name:und_x_variant":[
        "\u94c1\u738b"
    ],
    "name:zho_x_preferred":[
        "\u94c1\u738b"
    ],
    "wof:name":"Tiewang",
    "wof:placetype":"locality"
},
  "geometry": {"coordinates":[108.13131,34.62255],"type":"Point"}
}