{
  "type": "Feature",
  "properties": {
    "gn:admin1_code":"10",
    "gn:asciiname":"Wenjiatai",
    "gn:country_code":"CN",
    "gn:dem":634,
    "gn:feature_class":"P",
    "gn:feature_code":"PPL",
    "gn:name":"Wenjiatai",
    "gn:population":0,
    "gn:timezone":"Asia/Shanghai",
    "iso:country":"CN",
    "name:zho_x_preferred":[
        "\u6e29\u5bb6\u53f0"
    ],
    "wof:name":"Wenjiatai",
    "wof:placetype":"locality"
},
  "geometry": {"coordinates":[117.70771999999999,40.81302],"type":"Point"}
}