{
  "type": "Feature",
  "properties": {
    "gn:admin1_code":"4.0",
    "gn:asciiname":"Bianjiaxu",
    "gn:country_code":"CN",
    "gn:dem":7,
    "gn:feature_class":"P",
    "gn:feature_code":"PPL",
    "gn:name":"Bianjiaxu",
    "gn:population":0,
    "gn:timezone":"Asia/Shanghai",
    "iso:country":"CN",
    "name:zho_x_preferred":[
        "\u535e\u5bb6\u5729"
    ],
    "wof:name":"Bianjiaxu",
    "wof:placetype":"locality"
},
  "geometry": {"coordinates":[120.04855999999999,32.01704],"type":"Point"}
}