{
  "type": "Feature",
  "properties": {
    "gn:admin1_code":"29.0",
    "gn:asciiname":"Gucheng",
    "gn:country_code":"CN",
    "gn:dem":1601,
    "gn:feature_class":"P",
    "gn:feature_code":"PPL",
    "gn:name":"Gucheng",
    "gn:population":0,
    "gn:timezone":"Asia/Shanghai",
    "iso:country":"CN",
    "name:zho_x_preferred":[
        "\u53e4\u57ce"
    ],
    "wof:name":"Gucheng",
    "wof:placetype":"locality"
},
  "geometry": {"coordinates":[103.116,25.8458],"type":"Point"}
}