{
  "type": "Feature",
  "properties": {
    "gn:admin1_code":"30",
    "gn:asciiname":"Jiang'andong",
    "gn:country_code":"CN",
    "gn:dem":46,
    "gn:feature_class":"P",
    "gn:feature_code":"PPL",
    "gn:name":"Jiang\u2019andong",
    "gn:population":0,
    "gn:timezone":"Asia/Urumqi",
    "iso:country":"CN",
    "name:zho_x_preferred":[
        "\u6c5f\u5cb8\u578c"
    ],
    "name:zho_x_variant":[
        "Jiang\u2019andong"
    ],
    "wof:name":"Jiang'andong",
    "wof:placetype":"locality"
},
  "geometry": {"coordinates":[110.07949000000001,21.79014],"type":"Point"}
}