{
  "type": "Feature",
  "properties": {
    "gn:admin1_code":"10.0",
    "gn:asciiname":"Fengjiagou",
    "gn:country_code":"CN",
    "gn:dem":274,
    "gn:feature_class":"P",
    "gn:feature_code":"PPL",
    "gn:name":"Fengjiagou",
    "gn:population":0,
    "gn:timezone":"Asia/Shanghai",
    "iso:country":"CN",
    "name:und_x_variant":[
        "\u51af\u5bb6\u6c9f"
    ],
    "wof:name":"Fengjiagou",
    "wof:placetype":"locality"
},
  "geometry": {"coordinates":[114.33046000000002,38.7517],"type":"Point"}
}