{
  "type": "Feature",
  "properties": {
    "gn:admin1_code":"9.0",
    "gn:asciiname":"Huangbaiyan",
    "gn:country_code":"CN",
    "gn:dem":46,
    "gn:feature_class":"P",
    "gn:feature_code":"PPL",
    "gn:name":"Huangbaiyan",
    "gn:population":0,
    "gn:timezone":"Asia/Shanghai",
    "iso:country":"CN",
    "name:zho_x_preferred":[
        "\u9ec4\u67cf\u5830"
    ],
    "wof:name":"Huangbaiyan",
    "wof:placetype":"locality"
},
  "geometry": {"coordinates":[115.71823999999999,32.01588],"type":"Point"}
}