{
  "type": "Feature",
  "properties": {
    "gn:admin1_code":"16.0",
    "gn:asciiname":"Shuanglingzui",
    "gn:country_code":"CN",
    "gn:dem":150,
    "gn:feature_class":"P",
    "gn:feature_code":"PPL",
    "gn:name":"Shuanglingzui",
    "gn:population":0,
    "gn:timezone":"Asia/Shanghai",
    "iso:country":"CN",
    "name:zho_x_preferred":[
        "\u53cc\u5cad\u5480"
    ],
    "wof:name":"Shuanglingzui",
    "wof:placetype":"locality"
},
  "geometry": {"coordinates":[110.31699999999999,23.0595],"type":"Point"}
}