{
  "type": "Feature",
  "properties": {
    "gn:admin1_code":"29.0",
    "gn:asciiname":"Cigou",
    "gn:country_code":"CN",
    "gn:dem":2165,
    "gn:feature_class":"P",
    "gn:feature_code":"PPL",
    "gn:name":"Cigou",
    "gn:population":0,
    "gn:timezone":"Asia/Shanghai",
    "iso:country":"CN",
    "name:zho_x_preferred":[
        "\u8328\u6c9f"
    ],
    "wof:name":"Cigou",
    "wof:placetype":"locality"
},
  "geometry": {"coordinates":[102.574,25.077],"type":"Point"}
}