{
  "type": "Feature",
  "properties": {
    "gn:admin1_code":"30.0",
    "gn:asciiname":"Heducun",
    "gn:country_code":"CN",
    "gn:dem":199,
    "gn:feature_class":"P",
    "gn:feature_code":"PPL",
    "gn:name":"Heducun",
    "gn:population":0,
    "gn:timezone":"Asia/Shanghai",
    "iso:country":"CN",
    "name:zho_x_preferred":[
        "Heducun"
    ],
    "name:zho_x_variant":[
        "\u6cb3\u6e21\u6751"
    ],
    "wof:name":"Heducun",
    "wof:placetype":"locality"
},
  "geometry": {"coordinates":[114.16397000000001,24.85083],"type":"Point"}
}