{
  "type": "Feature",
  "properties": {
    "gn:admin1_code":"31.0",
    "gn:asciiname":"Jinzhong",
    "gn:country_code":"CN",
    "gn:dem":35,
    "gn:feature_class":"P",
    "gn:feature_code":"PPL",
    "gn:name":"Jinzhong",
    "gn:population":0,
    "gn:timezone":"Asia/Shanghai",
    "iso:country":"CN",
    "name:ara_x_preferred":[
        "\u062c\u064a\u0646\u062a\u0634\u0648\u0646\u063a"
    ],
    "name:bre_x_preferred":[
        "Jinzhong"
    ],
    "name:cdo_x_preferred":[
        "C\u00e9ng-d\u1e73\u0306ng"
    ],
    "name:ceb_x_preferred":[
        "Jinzhong Shi"
    ],
    "name:ces_x_preferred":[
        "\u0164in-\u010dung"
    ],
    "name:dan_x_preferred":[
        "Jinzhong"
    ],
    "name:deu_x_preferred":[
        "Jinzhong"
    ],
    "name:eus_x_preferred":[
        "Jinzhong"
    ],
    "name:fas_x_preferred":[
        "\u062c\u06cc\u0646\u062c\u0648\u0646\u06af"
    ],
    "name:fin_x_preferred":[
        "Jinzhong"
    ],
    "name:fra_x_preferred":[
        "Jinzhong"
    ],
    "name:ita_x_preferred":[
        "Jinzhong"
    ],
    "name:jpn_x_preferred":[
        "\u664b\u4e2d\u5e02"
    ],
    "name:kik_x_preferred":[
        "Jinzhong"
    ],
    "name:kor_x_preferred":[
        "\uc9c4\uc911\uc2dc"
    ],
    "name:mlg_x_preferred":[
        "Jinzhong"
    ],
    "name:nld_x_preferred":[
        "Jinzhong"
    ],
    "name:nno_x_preferred":[
        "Jinzhong"
    ],
    "name:nor_x_preferred":[
        "Jinzhong"
    ],
    "name:pol_x_preferred":[
        "Jinzhong"
    ],
    "name:rus_x_preferred":[
        "\u0426\u0437\u0438\u043d\u044c\u0447\u0436\u0443\u043d"
    ],
    "name:spa_x_preferred":[
        "Jinzhong"
    ],
    "name:swe_x_preferred":[
        "Jinzhong"
    ],
    "name:tur_x_preferred":[
        "Jinzhong"
    ],
    "name:und_x_variant":[
        "\u8fdb\u5fe0"
    ],
    "name:urd_x_preferred":[
        "\u062c\u0646\u0698\u0648\u0646\u06af"
    ],
    "name:vie_x_preferred":[
        "T\u1ea5n Trung"
    ],
    "name:war_x_preferred":[
        "Jinzhong"
    ],
    "name:wuu_x_preferred":[
        "\u664b\u4e2d\u5e02"
    ],
    "name:zho_x_preferred":[
        "\u664b\u4e2d\u5e02"
    ],
    "wof:name":"Jinzhong",
    "wof:placetype":"locality"
},
  "geometry": {"coordinates":[109.9619,18.55225],"type":"Point"}
}