{
  "type": "Feature",
  "properties": {
    "gn:admin1_code":"31.0",
    "gn:asciiname":"Jinzhong",
    "gn:country_code":"CN",
    "gn:dem":35,
    "gn:feature_class":"P",
    "gn:feature_code":"PPL",
    "gn:name":"Jinzhong",
    "gn:population":0,
    "gn:timezone":"Asia/Shanghai",
    "iso:country":"CN",
    "name:und_x_variant":[
        "\u8fdb\u5fe0"
    ],
    "wof:name":"Jinzhong",
    "wof:placetype":"locality"
},
  "geometry": {"coordinates":[109.9619,18.55225],"type":"Point"}
}