{
  "type": "Feature",
  "properties": {
    "gn:admin1_code":"29.0",
    "gn:asciiname":"Beiyinzhai",
    "gn:country_code":"CN",
    "gn:dem":1759,
    "gn:feature_class":"P",
    "gn:feature_code":"PPL",
    "gn:name":"Beiyinzhai",
    "gn:population":0,
    "gn:timezone":"Asia/Shanghai",
    "iso:country":"CN",
    "name:zho_x_preferred":[
        "\u80cc\u9634\u5be8"
    ],
    "wof:name":"Beiyinzhai",
    "wof:placetype":"locality"
},
  "geometry": {"coordinates":[99.509,24.6305],"type":"Point"}
}