{
  "type": "Feature",
  "properties": {
    "gn:admin1_code":"24.0",
    "gn:asciiname":"Xinanzhuang",
    "gn:country_code":"CN",
    "gn:dem":834,
    "gn:feature_class":"P",
    "gn:feature_code":"PPL",
    "gn:name":"Xinanzhuang",
    "gn:population":0,
    "gn:timezone":"Asia/Shanghai",
    "iso:country":"CN",
    "name:zho_x_preferred":[
        "\u897f\u5357\u5e84"
    ],
    "wof:name":"Xinanzhuang",
    "wof:placetype":"locality"
},
  "geometry": {"coordinates":[112.94655,35.77828],"type":"Point"}
}