{
  "type": "Feature",
  "properties": {
    "gn:admin1_code":"1.0",
    "gn:asciiname":"Yaoyingcun",
    "gn:country_code":"CN",
    "gn:dem":37,
    "gn:feature_class":"P",
    "gn:feature_code":"PPL",
    "gn:name":"Yaoyingcun",
    "gn:population":0,
    "gn:timezone":"Asia/Shanghai",
    "iso:country":"CN",
    "name:zho_x_preferred":[
        "\u59da\u90e2\u6751"
    ],
    "wof:name":"Yaoyingcun",
    "wof:placetype":"locality"
},
  "geometry": {"coordinates":[117.21408,32.7488],"type":"Point"}
}