{
  "type": "Feature",
  "properties": {
    "gn:admin1_code":"04",
    "gn:asciiname":"Hongjiazhuang",
    "gn:cc2":"CN",
    "gn:country_code":"CN",
    "gn:dem":5,
    "gn:feature_class":"P",
    "gn:feature_code":"PPL",
    "gn:name":"Hongjiazhuang",
    "gn:population":0,
    "gn:timezone":"Asia/Shanghai",
    "iso:country":"CN",
    "name:und_x_variant":[
        "Hung-chia-chuang",
        "Hongjiazhuang"
    ],
    "wof:name":"Hongjiazhuang",
    "wof:placetype":"locality"
},
  "geometry": {"coordinates":[120.64556,32.24667],"type":"Point"}
}