{
  "type": "Feature",
  "properties": {
    "gn:admin1_code":"15.0",
    "gn:asciiname":"Sunjiahe",
    "gn:country_code":"CN",
    "gn:dem":1018,
    "gn:feature_class":"P",
    "gn:feature_code":"PPL",
    "gn:name":"Sunjiahe",
    "gn:population":0,
    "gn:timezone":"Asia/Shanghai",
    "iso:country":"CN",
    "name:und_x_variant":[
        "\u5b59\u5bb6\u6cb3"
    ],
    "wof:name":"Sunjiahe",
    "wof:placetype":"locality"
},
  "geometry": {"coordinates":[106.26958,33.66054],"type":"Point"}
}