{
  "type": "Feature",
  "properties": {
    "gn:admin1_code":"26.0",
    "gn:asciiname":"Liansanhaize",
    "gn:country_code":"CN",
    "gn:dem":1195,
    "gn:feature_class":"P",
    "gn:feature_code":"PPL",
    "gn:name":"Liansanhaize",
    "gn:population":0,
    "gn:timezone":"Asia/Shanghai",
    "iso:country":"CN",
    "name:zho_x_preferred":[
        "\u8fde\u4e09\u6d77\u5219"
    ],
    "wof:name":"Liansanhaize",
    "wof:placetype":"locality"
},
  "geometry": {"coordinates":[109.52655,38.26373],"type":"Point"}
}