{
  "type": "Feature",
  "properties": {
    "gn:admin1_code":"5.0",
    "gn:asciiname":"Duzijing",
    "gn:country_code":"CN",
    "gn:dem":147,
    "gn:feature_class":"P",
    "gn:feature_code":"PPL",
    "gn:name":"Duzijing",
    "gn:population":0,
    "gn:timezone":"Asia/Shanghai",
    "iso:country":"CN",
    "name:zho_x_preferred":[
        "\u7b03\u5b57\u4e95"
    ],
    "wof:name":"Duzijing",
    "wof:placetype":"locality"
},
  "geometry": {"coordinates":[123.95863,44.84244],"type":"Point"}
}