{
  "type": "Feature",
  "properties": {
    "gn:admin1_code":"11.0",
    "gn:asciiname":"Zhuya",
    "gn:country_code":"CN",
    "gn:dem":238,
    "gn:feature_class":"P",
    "gn:feature_code":"PPL",
    "gn:name":"Zhuya",
    "gn:population":0,
    "gn:timezone":"Asia/Shanghai",
    "iso:country":"CN",
    "name:zho_x_preferred":[
        "\u7af9\u57ad"
    ],
    "wof:name":"Zhuya",
    "wof:placetype":"locality"
},
  "geometry": {"coordinates":[110.51839,28.75205],"type":"Point"}
}