{
  "type": "Feature",
  "properties": {
    "gn:admin1_code":"32.0",
    "gn:asciiname":"Waibajiazhai",
    "gn:country_code":"CN",
    "gn:dem":3187,
    "gn:feature_class":"P",
    "gn:feature_code":"PPL",
    "gn:name":"Waibajiazhai",
    "gn:population":0,
    "gn:timezone":"Asia/Shanghai",
    "iso:country":"CN",
    "name:zho_x_preferred":[
        "\u5916\u516b\u5bb6\u5be8"
    ],
    "wof:name":"Waibajiazhai",
    "wof:placetype":"locality"
},
  "geometry": {"coordinates":[102.349,31.0426],"type":"Point"}
}