{
  "type": "Feature",
  "properties": {
    "gn:admin1_code":"24",
    "gn:asciiname":"Houdayu",
    "gn:cc2":"CN",
    "gn:country_code":"CN",
    "gn:dem":1068,
    "gn:feature_class":"P",
    "gn:feature_code":"PPL",
    "gn:name":"Houdayu",
    "gn:population":0,
    "gn:timezone":"Asia/Shanghai",
    "iso:country":"CN",
    "name:und_x_variant":[
        "Ta-y\u00fc-ts\u2019un",
        "Hou-ta-y\u00fc",
        "Houdayu"
    ],
    "wof:name":"Houdayu",
    "wof:placetype":"locality"
},
  "geometry": {"coordinates":[111.08,37.84694],"type":"Point"}
}