{
  "type": "Feature",
  "properties": {
    "gn:admin1_code":"16.0",
    "gn:asciiname":"Xiabingli",
    "gn:country_code":"CN",
    "gn:dem":626,
    "gn:feature_class":"P",
    "gn:feature_code":"PPL",
    "gn:name":"Xiabingli",
    "gn:population":0,
    "gn:timezone":"Asia/Shanghai",
    "iso:country":"CN",
    "name:zho_x_preferred":[
        "\u4e0b\u5e76\u91cc"
    ],
    "wof:name":"Xiabingli",
    "wof:placetype":"locality"
},
  "geometry": {"coordinates":[107.239,25.179],"type":"Point"}
}