{
  "type": "Feature",
  "properties": {
    "gn:admin1_code":"23.0",
    "gn:asciiname":"Bijian",
    "gn:country_code":"CN",
    "gn:dem":5,
    "gn:feature_class":"P",
    "gn:feature_code":"PPL",
    "gn:name":"Bijian",
    "gn:population":0,
    "gn:timezone":"Asia/Shanghai",
    "iso:country":"CN",
    "name:und_x_variant":[
        "\u859c\u95f4"
    ],
    "wof:name":"Bijian",
    "wof:placetype":"locality"
},
  "geometry": {"coordinates":[121.03140999999999,31.09904],"type":"Point"}
}