{
  "type": "Feature",
  "properties": {
    "gn:admin1_code":"3.0",
    "gn:asciiname":"Wuliaoji",
    "gn:country_code":"CN",
    "gn:dem":295,
    "gn:feature_class":"P",
    "gn:feature_code":"PPL",
    "gn:name":"Wuliaoji",
    "gn:population":0,
    "gn:timezone":"Asia/Shanghai",
    "iso:country":"CN",
    "name:und_x_variant":[
        "\u4e4c\u5ed6\u5c8c"
    ],
    "wof:name":"Wuliaoji",
    "wof:placetype":"locality"
},
  "geometry": {"coordinates":[115.31452,25.31252000000001],"type":"Point"}
}