{
  "type": "Feature",
  "properties": {
    "gn:admin1_code":"15.0",
    "gn:asciiname":"Youjiashan",
    "gn:country_code":"CN",
    "gn:dem":1650,
    "gn:feature_class":"P",
    "gn:feature_code":"PPL",
    "gn:name":"Youjiashan",
    "gn:population":0,
    "gn:timezone":"Asia/Shanghai",
    "iso:country":"CN",
    "name:zho_x_preferred":[
        "\u6e38\u5bb6\u5c71"
    ],
    "wof:name":"Youjiashan",
    "wof:placetype":"locality"
},
  "geometry": {"coordinates":[107.078,37.0059],"type":"Point"}
}