{
  "type": "Feature",
  "properties": {
    "gn:admin1_code":"26.0",
    "gn:asciiname":"Pangliucun",
    "gn:country_code":"CN",
    "gn:dem":585,
    "gn:feature_class":"P",
    "gn:feature_code":"PPL",
    "gn:name":"Pangliucun",
    "gn:population":0,
    "gn:timezone":"Asia/Shanghai",
    "iso:country":"CN",
    "name:zho_x_preferred":[
        "\u5e9e\u7559\u6751"
    ],
    "wof:name":"Pangliucun",
    "wof:placetype":"locality"
},
  "geometry": {"coordinates":[109.04192999999999,34.10588],"type":"Point"}
}