{
  "type": "Feature",
  "properties": {
    "gn:admin1_code":"12.0",
    "gn:asciiname":"Niutousi",
    "gn:country_code":"CN",
    "gn:dem":37,
    "gn:feature_class":"P",
    "gn:feature_code":"PPL",
    "gn:name":"Niutousi",
    "gn:population":0,
    "gn:timezone":"Asia/Shanghai",
    "iso:country":"CN",
    "name:zho_x_preferred":[
        "Niutousi"
    ],
    "name:zho_x_variant":[
        "\u725b\u5934\u5bfa"
    ],
    "wof:name":"Niutousi",
    "wof:placetype":"locality"
},
  "geometry": {"coordinates":[111.99209,30.04334],"type":"Point"}
}