{
  "type": "Feature",
  "properties": {
    "gn:admin1_code":"16.0",
    "gn:asciiname":"Chongkun",
    "gn:country_code":"CN",
    "gn:dem":118,
    "gn:feature_class":"P",
    "gn:feature_code":"PPL",
    "gn:name":"Chongkun",
    "gn:population":0,
    "gn:timezone":"Asia/Shanghai",
    "iso:country":"CN",
    "name:zho_x_preferred":[
        "\u51b2\u56f0"
    ],
    "wof:name":"Chongkun",
    "wof:placetype":"locality"
},
  "geometry": {"coordinates":[108.00700000000001,21.6513],"type":"Point"}
}