{
  "type": "Feature",
  "properties": {
    "gn:admin1_code":"5.0",
    "gn:asciiname":"Yaowujiu",
    "gn:country_code":"CN",
    "gn:dem":151,
    "gn:feature_class":"P",
    "gn:feature_code":"PPL",
    "gn:name":"Yaowujiu",
    "gn:population":0,
    "gn:timezone":"Asia/Shanghai",
    "iso:country":"CN",
    "name:zho_x_preferred":[
        "\u8170\u4e94\u4e5d"
    ],
    "wof:name":"Yaowujiu",
    "wof:placetype":"locality"
},
  "geometry": {"coordinates":[122.80413,44.73741],"type":"Point"}
}