{
  "type": "Feature",
  "properties": {
    "gn:admin1_code":"5",
    "gn:asciiname":"Xiaodonggoutun",
    "gn:country_code":"CN",
    "gn:dem":535,
    "gn:feature_class":"P",
    "gn:feature_code":"PPL",
    "gn:name":"Xiaodonggoutun",
    "gn:population":0,
    "gn:timezone":"Asia/Shanghai",
    "iso:country":"CN",
    "name:zho_x_preferred":[
        "\u5c0f\u4e1c\u6c9f\u5c6f"
    ],
    "wof:name":"Xiaodonggoutun",
    "wof:placetype":"locality"
},
  "geometry": {"coordinates":[127.791,43.5892],"type":"Point"}
}