{
  "type": "Feature",
  "properties": {
    "gn:admin1_code":"19.0",
    "gn:asciiname":"Xinnongcun",
    "gn:country_code":"CN",
    "gn:dem":41,
    "gn:feature_class":"P",
    "gn:feature_code":"PPL",
    "gn:name":"Xinnongcun",
    "gn:population":0,
    "gn:timezone":"Asia/Shanghai",
    "iso:country":"CN",
    "name:und_x_variant":[
        "\u65b0\u519c\u6751"
    ],
    "name:zho_x_preferred":[
        "\u65b0\u519c\u6751"
    ],
    "wof:name":"Xinnongcun",
    "wof:placetype":"locality"
},
  "geometry": {"coordinates":[122.343,41.9837],"type":"Point"}
}