{
  "type": "Feature",
  "properties": {
    "gn:admin1_code":"30",
    "gn:asciiname":"Baigong",
    "gn:country_code":"CN",
    "gn:dem":28,
    "gn:feature_class":"P",
    "gn:feature_code":"PPL",
    "gn:name":"Baigong",
    "gn:population":0,
    "gn:timezone":"Asia/Shanghai",
    "iso:country":"CN",
    "name:zho_x_preferred":[
        "\u4f2f\u516c"
    ],
    "wof:name":"Baigong",
    "wof:placetype":"locality"
},
  "geometry": {"coordinates":[114.55472,23.43528],"type":"Point"}
}