{
  "type": "Feature",
  "properties": {
    "gn:admin1_code":"7.0",
    "gn:asciiname":"Cunwei",
    "gn:country_code":"CN",
    "gn:dem":133,
    "gn:feature_class":"P",
    "gn:feature_code":"PPL",
    "gn:name":"Cunwei",
    "gn:population":0,
    "gn:timezone":"Asia/Shanghai",
    "iso:country":"CN",
    "name:zho_x_preferred":[
        "\u6751\u5c3e"
    ],
    "wof:name":"Cunwei",
    "wof:placetype":"locality"
},
  "geometry": {"coordinates":[118.40954000000001,26.3479],"type":"Point"}
}