{
  "type": "Feature",
  "properties": {
    "gn:admin1_code":"29",
    "gn:asciiname":"Xiandu",
    "gn:country_code":"CN",
    "gn:dem":1441,
    "gn:feature_class":"P",
    "gn:feature_code":"PPL",
    "gn:name":"Xiandu",
    "gn:population":0,
    "gn:timezone":"Asia/Shanghai",
    "iso:country":"CN",
    "name:zho_x_preferred":[
        "\u4ed9\u90fd"
    ],
    "wof:name":"Xiandu",
    "wof:placetype":"locality"
},
  "geometry": {"coordinates":[104.967,24.1424],"type":"Point"}
}