{
  "type": "Feature",
  "properties": {
    "gn:admin1_code":"11",
    "gn:asciiname":"Xinpu",
    "gn:country_code":"CN",
    "gn:dem":292,
    "gn:feature_class":"P",
    "gn:feature_code":"PPL",
    "gn:name":"Xinpu",
    "gn:population":0,
    "gn:timezone":"Asia/Shanghai",
    "iso:country":"CN",
    "name:ceb_x_preferred":[
        "Xinpu"
    ],
    "name:deu_x_preferred":[
        "Xinpu"
    ],
    "name:fra_x_preferred":[
        "Xinpu"
    ],
    "name:swe_x_preferred":[
        "Xinpu"
    ],
    "name:zho_x_preferred":[
        "\u65b0\u94fa"
    ],
    "wof:name":"Xinpu",
    "wof:placetype":"locality"
},
  "geometry": {"coordinates":[111.66507,27.64493],"type":"Point"}
}