{
  "type": "Feature",
  "properties": {
    "gn:admin1_code":"30.0",
    "gn:asciiname":"Lujing",
    "gn:country_code":"CN",
    "gn:dem":22,
    "gn:feature_class":"P",
    "gn:feature_code":"PPL",
    "gn:name":"Lujing",
    "gn:population":0,
    "gn:timezone":"Asia/Shanghai",
    "iso:country":"CN",
    "name:zho_x_preferred":[
        "\u9e7f\u4e95"
    ],
    "wof:name":"Lujing",
    "wof:placetype":"locality"
},
  "geometry": {"coordinates":[112.27540999999999,22.07800000000001],"type":"Point"}
}