{
  "type": "Feature",
  "properties": {
    "gn:admin1_code":"12.0",
    "gn:asciiname":"Shenglidui",
    "gn:country_code":"CN",
    "gn:dem":23,
    "gn:feature_class":"P",
    "gn:feature_code":"PPLF",
    "gn:name":"Shenglidui",
    "gn:population":0,
    "gn:timezone":"Asia/Shanghai",
    "iso:country":"CN",
    "name:und_x_variant":[
        "\u80dc\u5229\u961f"
    ],
    "name:zho_x_preferred":[
        "Shenglidui"
    ],
    "wof:name":"Shenglidui",
    "wof:placetype":"locality"
},
  "geometry": {"coordinates":[114.09568,30.61237],"type":"Point"}
}