{
  "type": "Feature",
  "properties": {
    "gn:admin1_code":"2.0",
    "gn:asciiname":"Shendaobang",
    "gn:country_code":"CN",
    "gn:dem":8,
    "gn:feature_class":"P",
    "gn:feature_code":"PPL",
    "gn:name":"Shendaobang",
    "gn:population":0,
    "gn:timezone":"Asia/Shanghai",
    "iso:country":"CN",
    "name:und_x_variant":[
        "\u6c88\u9053\u6d5c"
    ],
    "wof:name":"Shendaobang",
    "wof:placetype":"locality"
},
  "geometry": {"coordinates":[120.87372000000001,30.95347000000001],"type":"Point"}
}