{
  "type": "Feature",
  "properties": {
    "gn:admin1_code":"16.0",
    "gn:asciiname":"Guangjihua",
    "gn:country_code":"CN",
    "gn:dem":77,
    "gn:feature_class":"P",
    "gn:feature_code":"PPL",
    "gn:name":"Guangjihua",
    "gn:population":0,
    "gn:timezone":"Asia/Shanghai",
    "iso:country":"CN",
    "name:zho_x_preferred":[
        "\u5e7f\u6d4e\u5316"
    ],
    "wof:name":"Guangjihua",
    "wof:placetype":"locality"
},
  "geometry": {"coordinates":[110.35899999999999,23.2173],"type":"Point"}
}