{
  "type": "Feature",
  "properties": {
    "gn:admin1_code":"33.0",
    "gn:asciiname":"Huping",
    "gn:country_code":"CN",
    "gn:dem":583,
    "gn:feature_class":"P",
    "gn:feature_code":"PPL",
    "gn:name":"Huping",
    "gn:population":0,
    "gn:timezone":"Asia/Shanghai",
    "iso:country":"CN",
    "name:zho_x_preferred":[
        "\u80e1\u576a"
    ],
    "wof:name":"Huping",
    "wof:placetype":"locality"
},
  "geometry": {"coordinates":[108.35809,29.67172],"type":"Point"}
}