{
  "type": "Feature",
  "properties": {
    "gn:admin1_code":"15.0",
    "gn:asciiname":"Kayang",
    "gn:country_code":"CN",
    "gn:dem":3228,
    "gn:feature_class":"P",
    "gn:feature_code":"PPL",
    "gn:name":"Kayang",
    "gn:population":0,
    "gn:timezone":"Asia/Shanghai",
    "iso:country":"CN",
    "name:und_x_variant":[
        "\u5361\u7f8a"
    ],
    "wof:name":"Kayang",
    "wof:placetype":"locality"
},
  "geometry": {"coordinates":[103.16703,34.83995],"type":"Point"}
}