{
  "type": "Feature",
  "properties": {
    "gn:admin1_code":"10",
    "gn:asciiname":"Erdao Wopu",
    "gn:country_code":"CN",
    "gn:dem":456,
    "gn:feature_class":"P",
    "gn:feature_code":"PPL",
    "gn:name":"Erdao Wopu",
    "gn:population":0,
    "gn:timezone":"Asia/Shanghai",
    "iso:country":"CN",
    "name:zho_x_preferred":[
        "\u4e8c\u9053\u7a9d\u94fa"
    ],
    "wof:name":"Erdao Wopu",
    "wof:placetype":"locality"
},
  "geometry": {"coordinates":[118.02131,41.03657000000001],"type":"Point"}
}