{
  "type": "Feature",
  "properties": {
    "gn:admin1_code":"8.0",
    "gn:asciiname":"Youjiagang",
    "gn:country_code":"CN",
    "gn:dem":121,
    "gn:feature_class":"P",
    "gn:feature_code":"PPL",
    "gn:name":"Youjiagang",
    "gn:population":0,
    "gn:timezone":"Asia/Shanghai",
    "iso:country":"CN",
    "name:zho_x_preferred":[
        "\u5c24\u5bb6\u5c97"
    ],
    "wof:name":"Youjiagang",
    "wof:placetype":"locality"
},
  "geometry": {"coordinates":[128.12755000000001,45.98704],"type":"Point"}
}