{
  "type": "Feature",
  "properties": {
    "gn:admin1_code":"07",
    "gn:asciiname":"Shangji",
    "gn:country_code":"CN",
    "gn:dem":749,
    "gn:feature_class":"P",
    "gn:feature_code":"PPL",
    "gn:name":"Shangji",
    "gn:population":0,
    "gn:timezone":"Asia/Shanghai",
    "iso:country":"CN",
    "name:zho_x_preferred":[
        "\u4e0a\u6f08"
    ],
    "wof:name":"Shangji",
    "wof:placetype":"locality"
},
  "geometry": {"coordinates":[118.05958,25.63499],"type":"Point"}
}