{
  "type": "Feature",
  "properties": {
    "gn:admin1_code":"6.0",
    "gn:asciiname":"Yangchang",
    "gn:country_code":"CN",
    "gn:dem":3931,
    "gn:feature_class":"P",
    "gn:feature_code":"PPL",
    "gn:name":"Yangchang",
    "gn:population":0,
    "gn:timezone":"Asia/Shanghai",
    "iso:country":"CN",
    "wof:name":"Yangchang",
    "wof:placetype":"locality"
},
  "geometry": {"coordinates":[100.36667,34.41667],"type":"Point"}
}