{
  "type": "Feature",
  "properties": {
    "gn:admin1_code":"15.0",
    "gn:asciiname":"Zhaojiatai",
    "gn:country_code":"CN",
    "gn:dem":2052,
    "gn:feature_class":"P",
    "gn:feature_code":"PPL",
    "gn:name":"Zhaojiatai",
    "gn:population":0,
    "gn:timezone":"Asia/Shanghai",
    "iso:country":"CN",
    "name:zho_x_preferred":[
        "\u8d75\u5bb6\u53f0"
    ],
    "wof:name":"Zhaojiatai",
    "wof:placetype":"locality"
},
  "geometry": {"coordinates":[103.072,35.5087],"type":"Point"}
}