{
  "type": "Feature",
  "properties": {
    "gn:admin1_code":"12.0",
    "gn:asciiname":"Shangping",
    "gn:country_code":"CN",
    "gn:dem":348,
    "gn:feature_class":"P",
    "gn:feature_code":"PPL",
    "gn:name":"Shangping",
    "gn:population":0,
    "gn:timezone":"Asia/Shanghai",
    "iso:country":"CN",
    "name:zho_x_preferred":[
        "Shangping"
    ],
    "name:zho_x_variant":[
        "\u4e0a\u576a"
    ],
    "wof:name":"Shangping",
    "wof:placetype":"locality"
},
  "geometry": {"coordinates":[111.25754000000001,30.05907],"type":"Point"}
}