{
  "type": "Feature",
  "properties": {
    "gn:admin1_code":"26.0",
    "gn:asciiname":"Linjiazhuang",
    "gn:country_code":"CN",
    "gn:dem":762,
    "gn:feature_class":"P",
    "gn:feature_code":"PPL",
    "gn:name":"Linjiazhuang",
    "gn:population":0,
    "gn:timezone":"Asia/Shanghai",
    "iso:country":"CN",
    "name:und_x_variant":[
        "\u6797\u5bb6\u5e84"
    ],
    "wof:name":"Linjiazhuang",
    "wof:placetype":"locality"
},
  "geometry": {"coordinates":[107.03964999999999,34.41642],"type":"Point"}
}