{
  "type": "Feature",
  "properties": {
    "gn:admin1_code":"30",
    "gn:asciiname":"Fengtiankeng",
    "gn:country_code":"CN",
    "gn:dem":245,
    "gn:feature_class":"P",
    "gn:feature_code":"PPL",
    "gn:name":"Fengtiankeng",
    "gn:population":0,
    "gn:timezone":"Asia/Shanghai",
    "iso:country":"CN",
    "name:zho_x_preferred":[
        "\u4e30\u7530\u5751"
    ],
    "wof:name":"Fengtiankeng",
    "wof:placetype":"locality"
},
  "geometry": {"coordinates":[115.9145,23.32836],"type":"Point"}
}