{
  "type": "Feature",
  "properties": {
    "gn:admin1_code":"30.0",
    "gn:asciiname":"Shantiancun",
    "gn:country_code":"CN",
    "gn:dem":258,
    "gn:feature_class":"P",
    "gn:feature_code":"PPL",
    "gn:name":"Shantiancun",
    "gn:population":0,
    "gn:timezone":"Asia/Shanghai",
    "iso:country":"CN",
    "name:zho_x_preferred":[
        "\u73ca\u7530\u6751"
    ],
    "wof:name":"Shantiancun",
    "wof:placetype":"locality"
},
  "geometry": {"coordinates":[115.94798,24.16289],"type":"Point"}
}