{
  "type": "Feature",
  "properties": {
    "gn:admin1_code":"14.0",
    "gn:asciiname":"Badengcun",
    "gn:country_code":"CN",
    "gn:dem":1456,
    "gn:feature_class":"P",
    "gn:feature_code":"PPL",
    "gn:name":"Badengcun",
    "gn:population":0,
    "gn:timezone":"Asia/Urumqi",
    "iso:country":"CN",
    "name:zho_x_preferred":[
        "\u5df4\u767b\u6751"
    ],
    "wof:name":"Badengcun",
    "wof:placetype":"locality"
},
  "geometry": {"coordinates":[95.15709,29.26637],"type":"Point"}
}