{
  "type": "Feature",
  "properties": {
    "gn:admin1_code":"10",
    "gn:asciiname":"Liugezhuang",
    "gn:country_code":"CN",
    "gn:dem":35,
    "gn:feature_class":"P",
    "gn:feature_code":"PPL",
    "gn:name":"Liugezhuang",
    "gn:population":0,
    "gn:timezone":"Asia/Shanghai",
    "iso:country":"CN",
    "name:zho_x_preferred":[
        "\u5218\u5404\u5e84"
    ],
    "wof:name":"Liugezhuang",
    "wof:placetype":"locality"
},
  "geometry": {"coordinates":[117.81851,40.00254],"type":"Point"}
}