{
  "type": "Feature",
  "properties": {
    "gn:admin1_code":"14",
    "gn:asciiname":"Karbo",
    "gn:country_code":"CN",
    "gn:dem":3948,
    "gn:feature_class":"P",
    "gn:feature_code":"PPL",
    "gn:name":"Karbo",
    "gn:population":0,
    "gn:timezone":"Asia/Urumqi",
    "iso:country":"CN",
    "name:bod_x_preferred":[
        "\u0f58\u0f41\u0f62\u0f0b\u0f54\u0f7c"
    ],
    "wof:name":"Karbo",
    "wof:placetype":"locality"
},
  "geometry": {"coordinates":[92.76949999999999,28.65135],"type":"Point"}
}