{
  "type": "Feature",
  "properties": {
    "gn:admin1_code":"15.0",
    "gn:asciiname":"Zonggongba",
    "gn:country_code":"CN",
    "gn:dem":1928,
    "gn:feature_class":"P",
    "gn:feature_code":"PPL",
    "gn:name":"Zonggongba",
    "gn:population":0,
    "gn:timezone":"Asia/Shanghai",
    "iso:country":"CN",
    "name:und_x_variant":[
        "\u603b\u62f1\u575d"
    ],
    "name:zho_x_preferred":[
        "\u603b\u62f1\u575d"
    ],
    "wof:name":"Zonggongba",
    "wof:placetype":"locality"
},
  "geometry": {"coordinates":[104.56350999999999,33.36324],"type":"Point"}
}