{
  "type": "Feature",
  "properties": {
    "gn:admin1_code":"26.0",
    "gn:asciiname":"Jiepaishi",
    "gn:country_code":"CN",
    "gn:dem":863,
    "gn:feature_class":"P",
    "gn:feature_code":"PPL",
    "gn:name":"Jiepaishi",
    "gn:population":0,
    "gn:timezone":"Asia/Shanghai",
    "iso:country":"CN",
    "name:zho_x_preferred":[
        "\u754c\u724c\u77f3"
    ],
    "wof:name":"Jiepaishi",
    "wof:placetype":"locality"
},
  "geometry": {"coordinates":[110.06878,33.52512],"type":"Point"}
}