{
  "type": "Feature",
  "properties": {
    "gn:admin1_code":"32.0",
    "gn:asciiname":"Wenzeluo",
    "gn:country_code":"CN",
    "gn:dem":1831,
    "gn:feature_class":"P",
    "gn:feature_code":"PPL",
    "gn:name":"Wenzeluo",
    "gn:population":0,
    "gn:timezone":"Asia/Shanghai",
    "iso:country":"CN",
    "name:zho_x_preferred":[
        "\u6587\u5219\u6d1b"
    ],
    "wof:name":"Wenzeluo",
    "wof:placetype":"locality"
},
  "geometry": {"coordinates":[102.73,28.8203],"type":"Point"}
}