{
  "type": "Feature",
  "properties": {
    "gn:admin1_code":"3.0",
    "gn:asciiname":"Jinshimian",
    "gn:country_code":"CN",
    "gn:dem":353,
    "gn:feature_class":"P",
    "gn:feature_code":"PPL",
    "gn:name":"Jinshimian",
    "gn:population":0,
    "gn:timezone":"Asia/Shanghai",
    "iso:country":"CN",
    "name:und_x_variant":[
        "\u91d1\u72ee\u9762"
    ],
    "wof:name":"Jinshimian",
    "wof:placetype":"locality"
},
  "geometry": {"coordinates":[114.03643999999998,27.48949],"type":"Point"}
}