{
  "type": "Feature",
  "properties": {
    "gn:admin1_code":"1.0",
    "gn:asciiname":"Lumiaocun",
    "gn:country_code":"CN",
    "gn:dem":27,
    "gn:feature_class":"P",
    "gn:feature_code":"PPL",
    "gn:name":"Lumiaocun",
    "gn:population":0,
    "gn:timezone":"Asia/Shanghai",
    "iso:country":"CN",
    "name:zho_x_preferred":[
        "\u8def\u5e99\u6751"
    ],
    "wof:name":"Lumiaocun",
    "wof:placetype":"locality"
},
  "geometry": {"coordinates":[117.09220999999999,33.31629],"type":"Point"}
}