{
  "type": "Feature",
  "properties": {
    "gn:admin1_code":"9.0",
    "gn:asciiname":"Panguanzhuang",
    "gn:country_code":"CN",
    "gn:dem":83,
    "gn:feature_class":"P",
    "gn:feature_code":"PPL",
    "gn:name":"Panguanzhuang",
    "gn:population":0,
    "gn:timezone":"Asia/Shanghai",
    "iso:country":"CN",
    "name:zho_x_preferred":[
        "\u5224\u5b98\u5e84"
    ],
    "wof:name":"Panguanzhuang",
    "wof:placetype":"locality"
},
  "geometry": {"coordinates":[112.36388999999998,32.3797],"type":"Point"}
}