{
  "type": "Feature",
  "properties": {
    "gn:admin1_code":"18",
    "gn:asciiname":"Panlongwan",
    "gn:country_code":"CN",
    "gn:dem":1501,
    "gn:feature_class":"P",
    "gn:feature_code":"PPL",
    "gn:name":"Panlongwan",
    "gn:population":0,
    "gn:timezone":"Asia/Shanghai",
    "iso:country":"CN",
    "name:zho_x_preferred":[
        "\u87e0\u9f99\u6e7e"
    ],
    "wof:name":"Panlongwan",
    "wof:placetype":"locality"
},
  "geometry": {"coordinates":[104.944,25.5956],"type":"Point"}
}