{
  "type": "Feature",
  "properties": {
    "gn:admin1_code":"21.0",
    "gn:asciiname":"Baoziwan",
    "gn:country_code":"CN",
    "gn:dem":1946,
    "gn:feature_class":"P",
    "gn:feature_code":"PPL",
    "gn:name":"Baoziwan",
    "gn:population":0,
    "gn:timezone":"Asia/Shanghai",
    "iso:country":"CN",
    "name:zho_x_preferred":[
        "\u5821\u5b50\u6e7e"
    ],
    "wof:name":"Baoziwan",
    "wof:placetype":"locality"
},
  "geometry": {"coordinates":[105.82601,35.84533],"type":"Point"}
}