{
  "type": "Feature",
  "properties": {
    "gn:admin1_code":"15.0",
    "gn:asciiname":"Bei'ercha",
    "gn:country_code":"CN",
    "gn:dem":1543,
    "gn:feature_class":"P",
    "gn:feature_code":"PPL",
    "gn:name":"Bei\u2019ercha",
    "gn:population":0,
    "gn:timezone":"Asia/Shanghai",
    "iso:country":"CN",
    "name:und_x_variant":[
        "Bei\u2019ercha",
        "\u5317\u513f\u5c94"
    ],
    "wof:name":"Bei'ercha",
    "wof:placetype":"locality"
},
  "geometry": {"coordinates":[107.27445,36.17246],"type":"Point"}
}