{
  "type": "Feature",
  "properties": {
    "gn:admin1_code":"2",
    "gn:asciiname":"Jiangjiawan",
    "gn:country_code":"CN",
    "gn:dem":273,
    "gn:feature_class":"P",
    "gn:feature_code":"PPL",
    "gn:name":"Jiangjiawan",
    "gn:population":0,
    "gn:timezone":"Asia/Shanghai",
    "iso:country":"CN",
    "name:zho_x_preferred":[
        "\u848b\u5bb6\u6e7e"
    ],
    "wof:name":"Jiangjiawan",
    "wof:placetype":"locality"
},
  "geometry": {"coordinates":[120.67610999999999,29.38639],"type":"Point"}
}