{
  "type": "Feature",
  "properties": {
    "gn:admin1_code":"23.0",
    "gn:asciiname":"Qianggu Jiazhai",
    "gn:country_code":"CN",
    "gn:dem":5,
    "gn:feature_class":"P",
    "gn:feature_code":"PPL",
    "gn:name":"Qianggu Jiazhai",
    "gn:population":0,
    "gn:timezone":"Asia/Shanghai",
    "iso:country":"CN",
    "name:zho_x_preferred":[
        "Qianggu Jiazhai"
    ],
    "name:zho_x_variant":[
        "\u5f3a\u987e\u5bb6\u5b85"
    ],
    "wof:name":"Qianggu Jiazhai",
    "wof:placetype":"locality"
},
  "geometry": {"coordinates":[121.65663000000001,31.26788],"type":"Point"}
}