{
  "type": "Feature",
  "properties": {
    "gn:admin1_code":"19.0",
    "gn:asciiname":"Beidi",
    "gn:country_code":"CN",
    "gn:dem":302,
    "gn:feature_class":"P",
    "gn:feature_code":"PPL",
    "gn:name":"Beidi",
    "gn:population":0,
    "gn:timezone":"Asia/Shanghai",
    "iso:country":"CN",
    "name:bul_x_preferred":[
        "\u0411\u0435\u0439\u0434\u0438"
    ],
    "name:ind_x_preferred":[
        "Beidi"
    ],
    "name:nld_x_preferred":[
        "Noordelijke Di"
    ],
    "name:rus_x_preferred":[
        "\u0421\u0435\u0432\u0435\u0440\u043d\u044b\u0435 \u0432\u0430\u0440\u0432\u0430\u0440\u044b"
    ],
    "name:spa_x_preferred":[
        "Beidi"
    ],
    "name:swe_x_preferred":[
        "Beidi"
    ],
    "name:ukr_x_preferred":[
        "\u041f\u0456\u0432\u043d\u0456\u0447\u043d\u0456 \u0432\u0430\u0440\u0432\u0430\u0440\u0438"
    ],
    "name:und_x_variant":[
        "\u5317\u5730"
    ],
    "name:vie_x_preferred":[
        "B\u1eafc \u0110\u1ecbch"
    ],
    "name:zho_x_preferred":[
        "\u5317\u5730"
    ],
    "wof:name":"Beidi",
    "wof:placetype":"locality"
},
  "geometry": {"coordinates":[121.1853,41.80715],"type":"Point"}
}