{
  "type": "Feature",
  "properties": {
    "gn:admin1_code":"19.0",
    "gn:asciiname":"Qincaigou",
    "gn:country_code":"CN",
    "gn:dem":30,
    "gn:feature_class":"P",
    "gn:feature_code":"PPL",
    "gn:name":"Qincaigou",
    "gn:population":0,
    "gn:timezone":"Asia/Shanghai",
    "iso:country":"CN",
    "name:und_x_variant":[
        "\u82b9\u83dc\u6c9f"
    ],
    "name:zho_x_preferred":[
        "\u82b9\u83dc\u6c9f"
    ],
    "wof:name":"Qincaigou",
    "wof:placetype":"locality"
},
  "geometry": {"coordinates":[120.62017,40.62724],"type":"Point"}
}