{
  "type": "Feature",
  "properties": {
    "gn:admin1_code":"12.0",
    "gn:asciiname":"Daliujia",
    "gn:country_code":"CN",
    "gn:dem":37,
    "gn:feature_class":"P",
    "gn:feature_code":"PPL",
    "gn:name":"Daliujia",
    "gn:population":0,
    "gn:timezone":"Asia/Shanghai",
    "iso:country":"CN",
    "name:zho_x_preferred":[
        "\u5927\u5218\u5bb6"
    ],
    "wof:name":"Daliujia",
    "wof:placetype":"locality"
},
  "geometry": {"coordinates":[114.65498999999998,31.00864],"type":"Point"}
}