{
  "type": "Feature",
  "properties": {
    "gn:admin1_code":"11.0",
    "gn:asciiname":"Yihao",
    "gn:country_code":"CN",
    "gn:dem":29,
    "gn:feature_class":"P",
    "gn:feature_code":"PPL",
    "gn:name":"Yihao",
    "gn:population":0,
    "gn:timezone":"Asia/Shanghai",
    "iso:country":"CN",
    "name:zho_x_preferred":[
        "\u4e00\u53f7"
    ],
    "wof:name":"Yihao",
    "wof:placetype":"locality"
},
  "geometry": {"coordinates":[112.88272000000001,29.5342],"type":"Point"}
}