{
  "type": "Feature",
  "properties": {
    "gn:admin1_code":"09",
    "gn:asciiname":"Nangou",
    "gn:country_code":"CN",
    "gn:dem":1026,
    "gn:feature_class":"P",
    "gn:feature_code":"PPL",
    "gn:name":"Nangou",
    "gn:population":0,
    "gn:timezone":"Asia/Shanghai",
    "iso:country":"CN",
    "wof:name":"Nangou",
    "wof:placetype":"locality"
},
  "geometry": {"coordinates":[110.98333,34.36667],"type":"Point"}
}