{
  "type": "Feature",
  "properties": {
    "gn:admin1_code":"1.0",
    "gn:asciiname":"Yihucun",
    "gn:country_code":"CN",
    "gn:dem":11,
    "gn:feature_class":"P",
    "gn:feature_code":"PPL",
    "gn:name":"Yihucun",
    "gn:population":0,
    "gn:timezone":"Asia/Shanghai",
    "iso:country":"CN",
    "name:zho_x_preferred":[
        "\u6c82\u6e56\u6751"
    ],
    "wof:name":"Yihucun",
    "wof:placetype":"locality"
},
  "geometry": {"coordinates":[119.03668,32.79272],"type":"Point"}
}