{
  "type": "Feature",
  "properties": {
    "gn:admin1_code":"33.0",
    "gn:asciiname":"Shaojikou",
    "gn:country_code":"CN",
    "gn:dem":599,
    "gn:feature_class":"P",
    "gn:feature_code":"PPL",
    "gn:name":"Shaojikou",
    "gn:population":0,
    "gn:timezone":"Asia/Shanghai",
    "iso:country":"CN",
    "name:zho_x_preferred":[
        "\u7b72\u7b95\u53e3"
    ],
    "wof:name":"Shaojikou",
    "wof:placetype":"locality"
},
  "geometry": {"coordinates":[106.833,28.8437],"type":"Point"}
}