{
  "type": "Feature",
  "properties": {
    "gn:admin1_code":"24",
    "gn:asciiname":"Housuo",
    "gn:country_code":"CN",
    "gn:dem":1037,
    "gn:feature_class":"P",
    "gn:feature_code":"PPLA4",
    "gn:name":"Housuo",
    "gn:population":0,
    "gn:timezone":"Asia/Shanghai",
    "iso:country":"CN",
    "name:und_x_variant":[
        "Hou-so-ts\u2019un",
        "Hou-so",
        "Housuo",
        "\u540e\u6240",
        "Housuo Xiang",
        "\u540e\u6240\u4e61"
    ],
    "wof:name":"Housuo",
    "wof:placetype":"locality"
},
  "geometry": {"coordinates":[112.84389,39.31083],"type":"Point"}
}