{
  "type": "Feature",
  "properties": {
    "gn:admin1_code":"3.0",
    "gn:asciiname":"Huangqinyuan",
    "gn:country_code":"CN",
    "gn:dem":90,
    "gn:feature_class":"P",
    "gn:feature_code":"PPL",
    "gn:name":"Huangqinyuan",
    "gn:population":0,
    "gn:timezone":"Asia/Shanghai",
    "iso:country":"CN",
    "name:und_x_variant":[
        "\u9ec4\u82b9\u56ed"
    ],
    "wof:name":"Huangqinyuan",
    "wof:placetype":"locality"
},
  "geometry": {"coordinates":[114.99589,27.65939],"type":"Point"}
}