{
  "type": "Feature",
  "properties": {
    "gn:admin1_code":"4.0",
    "gn:asciiname":"Jiufengcun",
    "gn:country_code":"CN",
    "gn:dem":0,
    "gn:feature_class":"P",
    "gn:feature_code":"PPL",
    "gn:name":"Jiufengcun",
    "gn:population":0,
    "gn:timezone":"Asia/Shanghai",
    "iso:country":"CN",
    "name:zho_x_preferred":[
        "\u4e45\u4e30\u6751"
    ],
    "wof:name":"Jiufengcun",
    "wof:placetype":"locality"
},
  "geometry": {"coordinates":[120.43810999999999,33.44391],"type":"Point"}
}