{
  "type": "Feature",
  "properties": {
    "gn:admin1_code":"9.0",
    "gn:asciiname":"Jingzhuang",
    "gn:country_code":"CN",
    "gn:dem":154,
    "gn:feature_class":"P",
    "gn:feature_code":"PPL",
    "gn:name":"Jingzhuang",
    "gn:population":0,
    "gn:timezone":"Asia/Shanghai",
    "iso:country":"CN",
    "name:zho_x_preferred":[
        "\u4e95\u5e84"
    ],
    "name:zho_x_variant":[
        "\u4e95\u5e84\u9547"
    ],
    "wof:name":"Jingzhuang",
    "wof:placetype":"locality"
},
  "geometry": {"coordinates":[113.40061,32.39032],"type":"Point"}
}