{
  "type": "Feature",
  "properties": {
    "gn:admin1_code":"4.0",
    "gn:asciiname":"Zhenzhongcun",
    "gn:country_code":"CN",
    "gn:dem":5,
    "gn:feature_class":"P",
    "gn:feature_code":"PPL",
    "gn:name":"Zhenzhongcun",
    "gn:population":0,
    "gn:timezone":"Asia/Shanghai",
    "iso:country":"CN",
    "name:zho_x_preferred":[
        "\u9547\u4e2d\u6751"
    ],
    "wof:name":"Zhenzhongcun",
    "wof:placetype":"locality"
},
  "geometry": {"coordinates":[119.33386000000002,34.09233],"type":"Point"}
}