{
  "type": "Feature",
  "properties": {
    "gn:admin1_code":"15.0",
    "gn:asciiname":"Niujiazui",
    "gn:country_code":"CN",
    "gn:dem":1270,
    "gn:feature_class":"P",
    "gn:feature_code":"PPL",
    "gn:name":"Niujiazui",
    "gn:population":0,
    "gn:timezone":"Asia/Shanghai",
    "iso:country":"CN",
    "name:zho_x_preferred":[
        "\u725b\u5bb6\u5480"
    ],
    "wof:name":"Niujiazui",
    "wof:placetype":"locality"
},
  "geometry": {"coordinates":[107.48999999999999,35.2489],"type":"Point"}
}