{
  "type": "Feature",
  "properties": {
    "gn:admin1_code":"29.0",
    "gn:asciiname":"Qiujiawan",
    "gn:country_code":"CN",
    "gn:dem":1066,
    "gn:feature_class":"P",
    "gn:feature_code":"PPL",
    "gn:name":"Qiujiawan",
    "gn:population":0,
    "gn:timezone":"Asia/Shanghai",
    "iso:country":"CN",
    "name:zho_x_preferred":[
        "\u4e18\u5bb6\u6e7e"
    ],
    "wof:name":"Qiujiawan",
    "wof:placetype":"locality"
},
  "geometry": {"coordinates":[104.13800000000001,28.1808],"type":"Point"}
}