{
  "type": "Feature",
  "properties": {
    "gn:admin1_code":"4.0",
    "gn:asciiname":"Qianyao",
    "gn:country_code":"CN",
    "gn:dem":2,
    "gn:feature_class":"P",
    "gn:feature_code":"PPL",
    "gn:name":"Qianyao",
    "gn:population":0,
    "gn:timezone":"Asia/Shanghai",
    "iso:country":"CN",
    "name:zho_x_preferred":[
        "Qianyao"
    ],
    "name:zho_x_variant":[
        "\u524d\u8170"
    ],
    "wof:name":"Qianyao",
    "wof:placetype":"locality"
},
  "geometry": {"coordinates":[119.47423000000001,34.4417],"type":"Point"}
}