{
  "type": "Feature",
  "properties": {
    "gn:admin1_code":"7.0",
    "gn:asciiname":"Pudou",
    "gn:country_code":"CN",
    "gn:dem":9,
    "gn:feature_class":"P",
    "gn:feature_code":"PPL",
    "gn:name":"Pudou",
    "gn:population":0,
    "gn:timezone":"Asia/Shanghai",
    "iso:country":"CN",
    "name:zho_x_preferred":[
        "\u57d4\u515c"
    ],
    "wof:name":"Pudou",
    "wof:placetype":"locality"
},
  "geometry": {"coordinates":[118.67230000000001,24.99358],"type":"Point"}
}