{
  "type": "Feature",
  "properties": {
    "gn:admin1_code":"16.0",
    "gn:asciiname":"Panchao",
    "gn:country_code":"CN",
    "gn:dem":240,
    "gn:feature_class":"P",
    "gn:feature_code":"PPL",
    "gn:name":"Panchao",
    "gn:population":0,
    "gn:timezone":"Asia/Shanghai",
    "iso:country":"CN",
    "name:zho_x_preferred":[
        "\u76d8\u671d"
    ],
    "wof:name":"Panchao",
    "wof:placetype":"locality"
},
  "geometry": {"coordinates":[107.304,24.1684],"type":"Point"}
}