{
  "type": "Feature",
  "properties": {
    "gn:admin1_code":"12.0",
    "gn:asciiname":"Fengshuling",
    "gn:country_code":"CN",
    "gn:dem":29,
    "gn:feature_class":"P",
    "gn:feature_code":"PPL",
    "gn:name":"Fengshuling",
    "gn:population":0,
    "gn:timezone":"Asia/Shanghai",
    "iso:country":"CN",
    "name:zho_x_preferred":[
        "Fengshuling"
    ],
    "name:zho_x_variant":[
        "\u67ab\u6811\u5cad"
    ],
    "wof:name":"Fengshuling",
    "wof:placetype":"locality"
},
  "geometry": {"coordinates":[115.37788,30.06727],"type":"Point"}
}