{
  "type": "Feature",
  "properties": {
    "gn:admin1_code":"29.0",
    "gn:asciiname":"Aqumian Jiucun",
    "gn:country_code":"CN",
    "gn:dem":1976,
    "gn:feature_class":"P",
    "gn:feature_code":"PPL",
    "gn:name":"Aqumian Jiucun",
    "gn:population":0,
    "gn:timezone":"Asia/Shanghai",
    "iso:country":"CN",
    "name:zho_x_preferred":[
        "\u963f\u53bb\u9762\u65e7\u6751"
    ],
    "wof:name":"Aqumian Jiucun",
    "wof:placetype":"locality"
},
  "geometry": {"coordinates":[100.31,24.9922],"type":"Point"}
}