{
  "type": "Feature",
  "properties": {
    "gn:admin1_code":"9.0",
    "gn:asciiname":"Hanzhuang",
    "gn:country_code":"CN",
    "gn:dem":78,
    "gn:feature_class":"P",
    "gn:feature_code":"PPL",
    "gn:name":"Hanzhuang",
    "gn:population":0,
    "gn:timezone":"Asia/Shanghai",
    "iso:country":"CN",
    "name:zho_x_preferred":[
        "\u97e9\u5e84"
    ],
    "wof:name":"Hanzhuang",
    "wof:placetype":"locality"
},
  "geometry": {"coordinates":[114.22141000000001,32.53593],"type":"Point"}
}