{
  "type": "Feature",
  "properties": {
    "gn:admin1_code":"7.0",
    "gn:asciiname":"Fuxi",
    "gn:country_code":"CN",
    "gn:dem":94,
    "gn:feature_class":"P",
    "gn:feature_code":"PPL",
    "gn:name":"Fuxi",
    "gn:population":0,
    "gn:timezone":"Asia/Shanghai",
    "iso:country":"CN",
    "name:bul_x_preferred":[
        "\u0424\u0443 \u0421\u0438"
    ],
    "name:cat_x_preferred":[
        "Fu Xi"
    ],
    "name:ces_x_preferred":[
        "Fu-si"
    ],
    "name:deu_x_preferred":[
        "Fu Xi"
    ],
    "name:epo_x_preferred":[
        "Fu Xi"
    ],
    "name:est_x_preferred":[
        "Fu Xi"
    ],
    "name:fas_x_preferred":[
        "\u0641\u0648 \u0647\u0633\u06cc"
    ],
    "name:fra_x_preferred":[
        "Fuxi"
    ],
    "name:hak_x_preferred":[
        "Phu\u030dk-h\u00ee"
    ],
    "name:heb_x_preferred":[
        "\u05e4\u05d5 \u05e9\u05d9"
    ],
    "name:hrv_x_preferred":[
        "Fu Xi"
    ],
    "name:hun_x_preferred":[
        "Fu-hszi"
    ],
    "name:ind_x_preferred":[
        "F\u00fax\u012b"
    ],
    "name:ita_x_preferred":[
        "Fu Xi"
    ],
    "name:kat_x_preferred":[
        "\u10e4\u10e3\u10e1\u10d8"
    ],
    "name:lit_x_preferred":[
        "Fu\u0161i"
    ],
    "name:msa_x_preferred":[
        "Fu Xi"
    ],
    "name:nld_x_preferred":[
        "Fuxi"
    ],
    "name:nor_x_preferred":[
        "Fuxi"
    ],
    "name:pol_x_preferred":[
        "Fuxi"
    ],
    "name:por_x_preferred":[
        "Fu Xi"
    ],
    "name:rus_x_preferred":[
        "\u0424\u0443 \u0421\u0438"
    ],
    "name:slk_x_preferred":[
        "Fu si"
    ],
    "name:spa_x_preferred":[
        "Fuxi"
    ],
    "name:swe_x_preferred":[
        "Fuxi"
    ],
    "name:tha_x_preferred":[
        "\u0e1d\u0e39\u0e0b\u0e35"
    ],
    "name:tur_x_preferred":[
        "Fu Xi"
    ],
    "name:ukr_x_preferred":[
        "\u0424\u0443-\u0441\u0456"
    ],
    "name:vie_x_preferred":[
        "Ph\u1ee5c Hy"
    ],
    "name:zho_x_preferred":[
        "\u6d6e\u6eaa"
    ],
    "wof:name":"Fuxi",
    "wof:placetype":"locality"
},
  "geometry": {"coordinates":[119.75695,26.75193],"type":"Point"}
}