{
  "type": "Feature",
  "properties": {
    "gn:admin1_code":"14.0",
    "gn:asciiname":"Xarling",
    "gn:country_code":"CN",
    "gn:dem":5134,
    "gn:feature_class":"P",
    "gn:feature_code":"PPLF",
    "gn:name":"Xarling",
    "gn:population":0,
    "gn:timezone":"Asia/Urumqi",
    "iso:country":"CN",
    "name:bod_x_preferred":[
        "Xarling"
    ],
    "name:zho_x_preferred":[
        "Xialin"
    ],
    "name:zho_x_variant":[
        "\u4e0b\u6797",
        "Tangkeqie",
        "\u6dcc\u5ba2\u5207"
    ],
    "wof:name":"Xarling",
    "wof:placetype":"locality"
},
  "geometry": {"coordinates":[91.70099999999999,30.101],"type":"Point"}
}