{
  "type": "Feature",
  "properties": {
    "gn:admin1_code":"15.0",
    "gn:asciiname":"Dagongcha",
    "gn:cc2":"CN",
    "gn:country_code":"CN",
    "gn:dem":2772,
    "gn:feature_class":"P",
    "gn:feature_code":"PPL",
    "gn:name":"Dagongcha",
    "gn:population":0,
    "gn:timezone":"Asia/Urumqi",
    "iso:country":"CN",
    "name:und_x_variant":[
        "Ta-kung-ch\u2019a",
        "Dagongcha"
    ],
    "wof:name":"Dagongcha",
    "wof:placetype":"locality"
},
  "geometry": {"coordinates":[96.06667,39.66667],"type":"Point"}
}