{
  "type": "Feature",
  "properties": {
    "gn:admin1_code":"1.0",
    "gn:asciiname":"Xiashicun",
    "gn:country_code":"CN",
    "gn:dem":19,
    "gn:feature_class":"P",
    "gn:feature_code":"PPL",
    "gn:name":"Xiashicun",
    "gn:population":0,
    "gn:timezone":"Asia/Shanghai",
    "iso:country":"CN",
    "name:zho_x_preferred":[
        "\u7856\u77f3\u6751"
    ],
    "wof:name":"Xiashicun",
    "wof:placetype":"locality"
},
  "geometry": {"coordinates":[117.90862,33.07328],"type":"Point"}
}