{
  "type": "Feature",
  "properties": {
    "gn:admin1_code":"32",
    "gn:asciiname":"Luxi",
    "gn:country_code":"CN",
    "gn:dem":435,
    "gn:feature_class":"P",
    "gn:feature_code":"PPL",
    "gn:name":"Luxi",
    "gn:population":0,
    "gn:timezone":"Asia/Shanghai",
    "iso:country":"CN",
    "name:ceb_x_preferred":[
        "Luxi"
    ],
    "name:deu_x_preferred":[
        "Luxi"
    ],
    "name:fra_x_preferred":[
        "Luxi"
    ],
    "name:kor_x_preferred":[
        "\ub8e8\uc2dc\ud604"
    ],
    "name:nor_x_preferred":[
        "Luxi"
    ],
    "name:swe_x_preferred":[
        "Luxi"
    ],
    "name:und_x_variant":[
        "Lu-hsi",
        "Khulutsi",
        "Hu-lu-ch\u2019i",
        "Hu-lu",
        "Luxi"
    ],
    "name:zho_x_preferred":[
        "\u82a6\u6eaa"
    ],
    "wof:name":"Luxi",
    "wof:placetype":"locality"
},
  "geometry": {"coordinates":[104.8869,31.27018],"type":"Point"}
}