{
  "type": "Feature",
  "properties": {
    "gn:admin1_code":"14",
    "gn:asciiname":"Debuju",
    "gn:country_code":"CN",
    "gn:dem":4487,
    "gn:feature_class":"P",
    "gn:feature_code":"PPL",
    "gn:name":"Debuju",
    "gn:population":0,
    "gn:timezone":"Asia/Urumqi",
    "iso:country":"CN",
    "name:zho_x_preferred":[
        "\u5fb7\u5e03\u5177"
    ],
    "wof:name":"Debuju",
    "wof:placetype":"locality"
},
  "geometry": {"coordinates":[88.5301,29.8108],"type":"Point"}
}