{
  "type": "Feature",
  "properties": {
    "gn:admin1_code":"30",
    "gn:asciiname":"Qi'ao",
    "gn:country_code":"CN",
    "gn:dem":8,
    "gn:feature_class":"P",
    "gn:feature_code":"PPL",
    "gn:name":"Qi\u2019ao",
    "gn:population":0,
    "gn:timezone":"Asia/Shanghai",
    "iso:country":"CN",
    "name:und_x_variant":[
        "Ch\u2019i-ao"
    ],
    "name:zho_x_preferred":[
        "\u6dc7\u6fb3"
    ],
    "name:zho_x_variant":[
        "Qi\u2019ao"
    ],
    "wof:name":"Qi'ao",
    "wof:placetype":"locality"
},
  "geometry": {"coordinates":[113.64188,22.413],"type":"Point"}
}