{
  "type": "Feature",
  "properties": {
    "gn:admin1_code":"6.0",
    "gn:asciiname":"Ri'a Shaoda",
    "gn:country_code":"CN",
    "gn:dem":4170,
    "gn:feature_class":"P",
    "gn:feature_code":"PPL",
    "gn:name":"Ri\u2019a Shaoda",
    "gn:population":0,
    "gn:timezone":"Asia/Urumqi",
    "iso:country":"CN",
    "name:und_x_variant":[
        "Ri\u2019a Shaoda"
    ],
    "name:zho_x_preferred":[
        "\u65e5\u554a\u7ecd\u6253"
    ],
    "wof:name":"Ri'a Shaoda",
    "wof:placetype":"locality"
},
  "geometry": {"coordinates":[95.76268,32.21135],"type":"Point"}
}