{
  "type": "Feature",
  "properties": {
    "gn:admin1_code":"29.0",
    "gn:asciiname":"Hecaodi",
    "gn:country_code":"CN",
    "gn:dem":1827,
    "gn:feature_class":"P",
    "gn:feature_code":"PPL",
    "gn:name":"Hecaodi",
    "gn:population":0,
    "gn:timezone":"Asia/Shanghai",
    "iso:country":"CN",
    "name:zho_x_preferred":[
        "\u79be\u8349\u5730"
    ],
    "wof:name":"Hecaodi",
    "wof:placetype":"locality"
},
  "geometry": {"coordinates":[103.88500000000001,23.4587],"type":"Point"}
}