{
  "type": "Feature",
  "properties": {
    "gn:admin1_code":"18",
    "gn:asciiname":"Langong",
    "gn:country_code":"CN",
    "gn:dem":880,
    "gn:feature_class":"P",
    "gn:feature_code":"PPL",
    "gn:name":"Langong",
    "gn:population":0,
    "gn:timezone":"Asia/Shanghai",
    "iso:country":"CN",
    "name:zho_x_preferred":[
        "\u6ee5\u529f"
    ],
    "wof:name":"Langong",
    "wof:placetype":"locality"
},
  "geometry": {"coordinates":[106.57599999999999,25.7022],"type":"Point"}
}