{
  "type": "Feature",
  "properties": {
    "gn:admin1_code":"6.0",
    "gn:asciiname":"Gongba",
    "gn:country_code":"CN",
    "gn:dem":2330,
    "gn:feature_class":"P",
    "gn:feature_code":"PPL",
    "gn:name":"Gongba",
    "gn:population":0,
    "gn:timezone":"Asia/Shanghai",
    "iso:country":"CN",
    "name:zho_x_preferred":[
        "\u8d21\u5df4"
    ],
    "wof:name":"Gongba",
    "wof:placetype":"locality"
},
  "geometry": {"coordinates":[101.46317000000001,36.00111],"type":"Point"}
}