{
  "type": "Feature",
  "properties": {
    "gn:admin1_code":"11.0",
    "gn:asciiname":"Zimuping",
    "gn:country_code":"CN",
    "gn:dem":1209,
    "gn:feature_class":"P",
    "gn:feature_code":"PPL",
    "gn:name":"Zimuping",
    "gn:population":0,
    "gn:timezone":"Asia/Shanghai",
    "iso:country":"CN",
    "name:zho_x_preferred":[
        "\u5b50\u6728\u576a"
    ],
    "wof:name":"Zimuping",
    "wof:placetype":"locality"
},
  "geometry": {"coordinates":[113.79177,26.10311],"type":"Point"}
}