{
  "type": "Feature",
  "properties": {
    "gn:admin1_code":"29.0",
    "gn:asciiname":"Maowu",
    "gn:country_code":"CN",
    "gn:dem":1666,
    "gn:feature_class":"P",
    "gn:feature_code":"PPL",
    "gn:name":"Maowu",
    "gn:population":0,
    "gn:timezone":"Asia/Shanghai",
    "iso:country":"CN",
    "name:zho_x_preferred":[
        "\u8302\u609f"
    ],
    "wof:name":"Maowu",
    "wof:placetype":"locality"
},
  "geometry": {"coordinates":[99.2179,23.9421],"type":"Point"}
}