{
  "type": "Feature",
  "properties": {
    "gn:admin1_code":"8.0",
    "gn:asciiname":"Xiaomiaozi",
    "gn:country_code":"CN",
    "gn:dem":137,
    "gn:feature_class":"P",
    "gn:feature_code":"PPL",
    "gn:name":"Xiaomiaozi",
    "gn:population":0,
    "gn:timezone":"Asia/Shanghai",
    "iso:country":"CN",
    "name:zho_x_preferred":[
        "\u5c0f\u5e99\u5b50"
    ],
    "wof:name":"Xiaomiaozi",
    "wof:placetype":"locality"
},
  "geometry": {"coordinates":[123.71975999999999,46.48382],"type":"Point"}
}