{
  "type": "Feature",
  "properties": {
    "gn:admin1_code":"19.0",
    "gn:asciiname":"Xiaopaoziyan",
    "gn:country_code":"CN",
    "gn:dem":15,
    "gn:feature_class":"P",
    "gn:feature_code":"PPL",
    "gn:name":"Xiaopaoziyan",
    "gn:population":0,
    "gn:timezone":"Asia/Shanghai",
    "iso:country":"CN",
    "name:und_x_variant":[
        "\u5c0f\u6ce1\u5b50\u6cbf"
    ],
    "name:zho_x_preferred":[
        "\u5c0f\u6ce1\u5b50\u6cbf"
    ],
    "wof:name":"Xiaopaoziyan",
    "wof:placetype":"locality"
},
  "geometry": {"coordinates":[123.61621,40.09694],"type":"Point"}
}