{
  "type": "Feature",
  "properties": {
    "gn:admin1_code":"3",
    "gn:asciiname":"Guixing",
    "gn:country_code":"CN",
    "gn:dem":197,
    "gn:feature_class":"P",
    "gn:feature_code":"PPL",
    "gn:name":"Guixing",
    "gn:population":0,
    "gn:timezone":"Asia/Shanghai",
    "iso:country":"CN",
    "name:zho_x_preferred":[
        "\u8d35\u5174"
    ],
    "wof:name":"Guixing",
    "wof:placetype":"locality"
},
  "geometry": {"coordinates":[114.98099999999999,25.2362],"type":"Point"}
}