{
  "type": "Feature",
  "properties": {
    "gn:country":"CN",
    "gn:fcode":"PPL",
    "gn:pop":120965,
    "iso:country":"CN",
    "name:unk_x_variant":[
        "A-pa-ha-na-erh-tso-i-ch\u2019i"
    ],
    "ne:ADM0CAP":0.0,
    "ne:ADM0NAME":"China",
    "ne:ADM0_A3":"CHN",
    "ne:ADM1NAME":"Nei Mongol",
    "ne:ADMIN1_COD":20,
    "ne:CAPALT":0,
    "ne:CHANGED":1,
    "ne:CHECKME":0,
    "ne:COMPARE":0,
    "ne:DIFFASCII":0,
    "ne:DIFFNOTE":"Changed scale rank.",
    "ne:ELEVATION":0.0,
    "ne:FEATURECLA":"Populated place",
    "ne:FEATURE_CL":"P",
    "ne:FEATURE_CO":"PPL",
    "ne:GEONAMEID":2033824,
    "ne:GEONAMESNO":"GeoNames spatial join with similar names only.",
    "ne:GN_ASCII":"Xilin Hot",
    "ne:GN_POP":120965,
    "ne:GTOPO30":994.0,
    "ne:ISO_A2":"CN",
    "ne:LABELRANK":1,
    "ne:LATITUDE":43.944332,
    "ne:LONGITUDE":116.044327,
    "ne:LS_MATCH":1,
    "ne:LS_NAME":"Xilinhot",
    "ne:MAX_AREAKM":27.0,
    "ne:MAX_AREAMI":10.0,
    "ne:MAX_BBXMAX":116.125,
    "ne:MAX_BBXMIN":116.05,
    "ne:MAX_BBYMAX":43.975,
    "ne:MAX_BBYMIN":43.916667,
    "ne:MAX_NATSCA":20.0,
    "ne:MAX_PERKM":27.0,
    "ne:MAX_PERMI":17.0,
    "ne:MAX_POP10":111348,
    "ne:MAX_POP20":111348,
    "ne:MAX_POP300":0,
    "ne:MAX_POP310":0,
    "ne:MAX_POP50":0,
    "ne:MEAN_BBXC":116.087306,
    "ne:MEAN_BBYC":43.946996,
    "ne:MEGACITY":0,
    "ne:MIN_AREAKM":27.0,
    "ne:MIN_AREAMI":10.0,
    "ne:MIN_BBXMAX":116.125,
    "ne:MIN_BBXMIN":116.05,
    "ne:MIN_BBYMAX":43.975,
    "ne:MIN_BBYMIN":43.916667,
    "ne:MIN_PERKM":27.0,
    "ne:MIN_PERMI":17.0,
    "ne:NAME":"Xilinhot",
    "ne:NAMEASCII":"Xilinhot",
    "ne:NAMEDIFF":0,
    "ne:NATSCALE":30,
    "ne:POP1950":0,
    "ne:POP1955":0,
    "ne:POP1960":0,
    "ne:POP1965":0,
    "ne:POP1970":0,
    "ne:POP1975":0,
    "ne:POP1980":0,
    "ne:POP1985":0,
    "ne:POP1990":0,
    "ne:POP1995":0,
    "ne:POP2000":0,
    "ne:POP2005":0,
    "ne:POP2010":0,
    "ne:POP2015":0,
    "ne:POP2020":0,
    "ne:POP2025":0,
    "ne:POP2050":0,
    "ne:POP_MAX":120965,
    "ne:POP_MIN":111348,
    "ne:POP_OTHER":0,
    "ne:RANK_MAX":9,
    "ne:RANK_MIN":9,
    "ne:SCALERANK":6,
    "ne:SOV0NAME":"China",
    "ne:SOV_A3":"CHN",
    "ne:TIMEZONE":"Asia/Harbin",
    "ne:UN_FID":0,
    "ne:UN_LAT":0.0,
    "ne:UN_LONG":0.0,
    "ne:WORLDCITY":0,
    "qs:name":"Xilin Hot",
    "qs:photos_9r":0,
    "qs:photos_sr":0,
    "qs:pop_sr":"9",
    "wd:wordcount":686,
    "wof:name":"Xilin Hot",
    "wof:placetype":"locality",
    "wof:population":120965
},
  "geometry": {"coordinates":[116.03333000000001,43.96667],"type":"Point"}
}