{
  "type": "Feature",
  "properties": {
    "gn:admin1_code":"15.0",
    "gn:asciiname":"Ganjiazhuang",
    "gn:country_code":"CN",
    "gn:dem":1436,
    "gn:feature_class":"P",
    "gn:feature_code":"PPL",
    "gn:name":"Ganjiazhuang",
    "gn:population":0,
    "gn:timezone":"Asia/Urumqi",
    "iso:country":"CN",
    "name:zho_x_preferred":[
        "\u7518\u5bb6\u5e84"
    ],
    "wof:name":"Ganjiazhuang",
    "wof:placetype":"locality"
},
  "geometry": {"coordinates":[96.8382,40.4362],"type":"Point"}
}