{
  "type": "Feature",
  "properties": {
    "gn:admin1_code":"32.0",
    "gn:asciiname":"Tancunba",
    "gn:country_code":"CN",
    "gn:dem":505,
    "gn:feature_class":"P",
    "gn:feature_code":"PPL",
    "gn:name":"Tancunba",
    "gn:population":0,
    "gn:timezone":"Asia/Shanghai",
    "iso:country":"CN",
    "name:zho_x_preferred":[
        "\u8c2d\u6751\u575d"
    ],
    "wof:name":"Tancunba",
    "wof:placetype":"locality"
},
  "geometry": {"coordinates":[104.542,28.2212],"type":"Point"}
}