{
  "type": "Feature",
  "properties": {
    "gn:admin1_code":"11.0",
    "gn:asciiname":"Datangchong",
    "gn:country_code":"CN",
    "gn:dem":173,
    "gn:feature_class":"P",
    "gn:feature_code":"PPL",
    "gn:name":"Datangchong",
    "gn:population":0,
    "gn:timezone":"Asia/Shanghai",
    "iso:country":"CN",
    "name:zho_x_preferred":[
        "\u5927\u5858\u51b2"
    ],
    "wof:name":"Datangchong",
    "wof:placetype":"locality"
},
  "geometry": {"coordinates":[113.63267999999999,27.1913],"type":"Point"}
}