{
  "type": "Feature",
  "properties": {
    "gn:admin1_code":"4.0",
    "gn:asciiname":"Zhangqianhu",
    "gn:country_code":"CN",
    "gn:dem":44,
    "gn:feature_class":"P",
    "gn:feature_code":"PPL",
    "gn:name":"Zhangqianhu",
    "gn:population":0,
    "gn:timezone":"Asia/Shanghai",
    "iso:country":"CN",
    "name:zho_x_preferred":[
        "\u5f20\u5343\u6237"
    ],
    "wof:name":"Zhangqianhu",
    "wof:placetype":"locality"
},
  "geometry": {"coordinates":[119.06979,31.43609],"type":"Point"}
}