{
  "type": "Feature",
  "properties": {
    "gn:admin1_code":"18",
    "gn:asciiname":"Xiangcunping",
    "gn:country_code":"CN",
    "gn:dem":1905,
    "gn:feature_class":"P",
    "gn:feature_code":"PPL",
    "gn:name":"Xiangcunping",
    "gn:population":0,
    "gn:timezone":"Asia/Shanghai",
    "iso:country":"CN",
    "name:zho_x_preferred":[
        "\u9999\u6751\u576a"
    ],
    "wof:name":"Xiangcunping",
    "wof:placetype":"locality"
},
  "geometry": {"coordinates":[105.13800000000001,27.2463],"type":"Point"}
}