{
  "type": "Feature",
  "properties": {
    "gn:admin1_code":"9.0",
    "gn:asciiname":"Huoshishancun",
    "gn:country_code":"CN",
    "gn:dem":145,
    "gn:feature_class":"P",
    "gn:feature_code":"PPL",
    "gn:name":"Huoshishancun",
    "gn:population":0,
    "gn:timezone":"Asia/Shanghai",
    "iso:country":"CN",
    "name:zho_x_preferred":[
        "\u706b\u77f3\u5c71\u6751"
    ],
    "wof:name":"Huoshishancun",
    "wof:placetype":"locality"
},
  "geometry": {"coordinates":[113.7128,33.08916],"type":"Point"}
}