{
  "type": "Feature",
  "properties": {
    "gn:admin1_code":"2.0",
    "gn:asciiname":"Aizu",
    "gn:country_code":"CN",
    "gn:dem":737,
    "gn:feature_class":"P",
    "gn:feature_code":"PPL",
    "gn:name":"Aizu",
    "gn:population":0,
    "gn:timezone":"Asia/Shanghai",
    "iso:country":"CN",
    "name:cat_x_preferred":[
        "Aizu"
    ],
    "name:fas_x_preferred":[
        "\u0622\u06cc\u0632\u0648"
    ],
    "name:fra_x_preferred":[
        "Aizu"
    ],
    "name:ind_x_preferred":[
        "Aizu"
    ],
    "name:ita_x_preferred":[
        "Aizu"
    ],
    "name:kor_x_preferred":[
        "\uc544\uc774\uc988"
    ],
    "name:por_x_preferred":[
        "Aizu"
    ],
    "name:rus_x_preferred":[
        "\u0410\u0439\u0434\u0437\u0443"
    ],
    "name:spa_x_preferred":[
        "Aizu"
    ],
    "name:srp_x_preferred":[
        "\u0410\u0438\u0437\u0443"
    ],
    "name:ukr_x_preferred":[
        "\u0410\u0439\u0434\u0437\u0443"
    ],
    "name:zho_x_preferred":[
        "\u5867\u5d2a"
    ],
    "wof:name":"Aizu",
    "wof:placetype":"locality"
},
  "geometry": {"coordinates":[120.90671,28.3309],"type":"Point"}
}