{
  "type": "Feature",
  "properties": {
    "gn:admin1_code":"2.0",
    "gn:asciiname":"Aizu",
    "gn:country_code":"CN",
    "gn:dem":737,
    "gn:feature_class":"P",
    "gn:feature_code":"PPL",
    "gn:name":"Aizu",
    "gn:population":0,
    "gn:timezone":"Asia/Shanghai",
    "iso:country":"CN",
    "name:zho_x_preferred":[
        "\u5867\u5d2a"
    ],
    "wof:name":"Aizu",
    "wof:placetype":"locality"
},
  "geometry": {"coordinates":[120.90671,28.3309],"type":"Point"}
}