{
  "type": "Feature",
  "properties": {
    "gn:admin1_code":"26.0",
    "gn:asciiname":"Donggou",
    "gn:country_code":"CN",
    "gn:dem":1346,
    "gn:feature_class":"P",
    "gn:feature_code":"PPL",
    "gn:name":"Donggou",
    "gn:population":0,
    "gn:timezone":"Asia/Shanghai",
    "iso:country":"CN",
    "name:und_x_variant":[
        "\u4e1c\u6c9f"
    ],
    "wof:name":"Donggou",
    "wof:placetype":"locality"
},
  "geometry": {"coordinates":[107.83504000000001,34.83727],"type":"Point"}
}