{
  "type": "Feature",
  "properties": {
    "gn:admin1_code":"1.0",
    "gn:asciiname":"Sanqiaocun",
    "gn:country_code":"CN",
    "gn:dem":28,
    "gn:feature_class":"P",
    "gn:feature_code":"PPL",
    "gn:name":"Sanqiaocun",
    "gn:population":0,
    "gn:timezone":"Asia/Shanghai",
    "iso:country":"CN",
    "name:zho_x_preferred":[
        "\u4e09\u6865\u6751"
    ],
    "wof:name":"Sanqiaocun",
    "wof:placetype":"locality"
},
  "geometry": {"coordinates":[116.15002,32.55958],"type":"Point"}
}