{
  "type": "Feature",
  "properties": {
    "gn:admin1_code":"7.0",
    "gn:asciiname":"Qianyangban",
    "gn:country_code":"CN",
    "gn:dem":1091,
    "gn:feature_class":"P",
    "gn:feature_code":"PPL",
    "gn:name":"Qianyangban",
    "gn:population":0,
    "gn:timezone":"Asia/Shanghai",
    "iso:country":"CN",
    "name:zho_x_preferred":[
        "Qianyangban"
    ],
    "name:zho_x_variant":[
        "\u524d\u6d0b\u5742"
    ],
    "wof:name":"Qianyangban",
    "wof:placetype":"locality"
},
  "geometry": {"coordinates":[118.96167,26.76333],"type":"Point"}
}