{
  "type": "Feature",
  "properties": {
    "gn:admin1_code":"16.0",
    "gn:asciiname":"Foma",
    "gn:country_code":"CN",
    "gn:dem":364,
    "gn:feature_class":"P",
    "gn:feature_code":"PPL",
    "gn:name":"Foma",
    "gn:population":0,
    "gn:timezone":"Asia/Shanghai",
    "iso:country":"CN",
    "name:deu_x_preferred":[
        "Foma"
    ],
    "name:fra_x_preferred":[
        "Foma"
    ],
    "name:jpn_x_preferred":[
        "\u30d5\u30a9\u30fc\u30de"
    ],
    "name:rus_x_preferred":[
        "\u0424\u043e\u043c\u0430"
    ],
    "name:tur_x_preferred":[
        "FOMA"
    ],
    "name:ukr_x_preferred":[
        "\u0424\u043e\u043c\u0430"
    ],
    "name:zho_x_preferred":[
        "\u4f5b\u5988"
    ],
    "wof:name":"Foma",
    "wof:placetype":"locality"
},
  "geometry": {"coordinates":[111.813,24.4949],"type":"Point"}
}