{
  "type": "Feature",
  "properties": {
    "gn:admin1_code":"29.0",
    "gn:asciiname":"Pangxiezhai",
    "gn:country_code":"CN",
    "gn:dem":1414,
    "gn:feature_class":"P",
    "gn:feature_code":"PPL",
    "gn:name":"Pangxiezhai",
    "gn:population":0,
    "gn:timezone":"Asia/Shanghai",
    "iso:country":"CN",
    "name:zho_x_preferred":[
        "\u8783\u87f9\u5be8"
    ],
    "wof:name":"Pangxiezhai",
    "wof:placetype":"locality"
},
  "geometry": {"coordinates":[101.697,21.5703],"type":"Point"}
}