{
  "type": "Feature",
  "properties": {
    "gn:admin1_code":"8.0",
    "gn:asciiname":"Ping'an",
    "gn:country_code":"CN",
    "gn:dem":79,
    "gn:feature_class":"P",
    "gn:feature_code":"PPLA4",
    "gn:name":"Ping\u2019an",
    "gn:population":0,
    "gn:timezone":"Asia/Shanghai",
    "iso:country":"CN",
    "name:ceb_x_preferred":[
        "Ping'an"
    ],
    "name:deu_x_preferred":[
        "Ping\u2019an"
    ],
    "name:fra_x_preferred":[
        "Pingan"
    ],
    "name:nld_x_preferred":[
        "Ping An"
    ],
    "name:und_x_variant":[
        "Ping\u2019an Xiang"
    ],
    "name:zho_x_preferred":[
        "\u5e73\u5b89"
    ],
    "name:zho_x_variant":[
        "\u5e73\u5b89\u4e61"
    ],
    "wof:name":"Ping'an",
    "wof:placetype":"locality"
},
  "geometry": {"coordinates":[130.31921,46.877],"type":"Point"}
}