{
  "type": "Feature",
  "properties": {
    "gn:admin1_code":"5.0",
    "gn:asciiname":"Xinfangzi",
    "gn:country_code":"CN",
    "gn:dem":248,
    "gn:feature_class":"P",
    "gn:feature_code":"PPL",
    "gn:name":"Xinfangzi",
    "gn:population":0,
    "gn:timezone":"Asia/Shanghai",
    "iso:country":"CN",
    "name:zho_x_preferred":[
        "\u65b0\u623f\u5b50"
    ],
    "wof:name":"Xinfangzi",
    "wof:placetype":"locality"
},
  "geometry": {"coordinates":[124.42818,43.0003],"type":"Point"}
}