{
  "type": "Feature",
  "properties": {
    "gn:admin1_code":"9",
    "gn:asciiname":"Zaiqiao",
    "gn:country_code":"CN",
    "gn:dem":38,
    "gn:feature_class":"P",
    "gn:feature_code":"PPL",
    "gn:name":"Zaiqiao",
    "gn:population":0,
    "gn:timezone":"Asia/Shanghai",
    "iso:country":"CN",
    "name:zho_x_preferred":[
        "\u5bb0\u6865"
    ],
    "wof:name":"Zaiqiao",
    "wof:placetype":"locality"
},
  "geometry": {"coordinates":[116.06399999999999,33.8624],"type":"Point"}
}