{
  "type": "Feature",
  "properties": {
    "gn:admin1_code":"19.0",
    "gn:asciiname":"Huishanzi",
    "gn:country_code":"CN",
    "gn:dem":81,
    "gn:feature_class":"P",
    "gn:feature_code":"PPL",
    "gn:name":"Huishanzi",
    "gn:population":0,
    "gn:timezone":"Asia/Shanghai",
    "iso:country":"CN",
    "name:zho_x_preferred":[
        "\u7070\u5c71\u5b50"
    ],
    "wof:name":"Huishanzi",
    "wof:placetype":"locality"
},
  "geometry": {"coordinates":[121.31971,41.44254],"type":"Point"}
}