{
  "type": "Feature",
  "properties": {
    "gn:admin1_code":"8.0",
    "gn:asciiname":"Xibeigoucun",
    "gn:country_code":"CN",
    "gn:dem":100,
    "gn:feature_class":"P",
    "gn:feature_code":"PPL",
    "gn:name":"Xibeigoucun",
    "gn:population":0,
    "gn:timezone":"Asia/Shanghai",
    "iso:country":"CN",
    "name:zho_x_preferred":[
        "\u897f\u5317\u6c9f\u6751"
    ],
    "wof:name":"Xibeigoucun",
    "wof:placetype":"locality"
},
  "geometry": {"coordinates":[132.19791000000001,45.4258],"type":"Point"}
}