{
  "type": "Feature",
  "properties": {
    "gn:admin1_code":"26.0",
    "gn:asciiname":"Huanggelengcun",
    "gn:country_code":"CN",
    "gn:dem":1312,
    "gn:feature_class":"P",
    "gn:feature_code":"PPL",
    "gn:name":"Huanggelengcun",
    "gn:population":0,
    "gn:timezone":"Asia/Shanghai",
    "iso:country":"CN",
    "name:zho_x_preferred":[
        "\u9ec4\u572a\u5844\u6751"
    ],
    "wof:name":"Huanggelengcun",
    "wof:placetype":"locality"
},
  "geometry": {"coordinates":[109.41976,37.77425],"type":"Point"}
}