{
  "type": "Feature",
  "properties": {
    "gn:admin1_code":"31",
    "gn:asciiname":"Ruben",
    "gn:country_code":"CN",
    "gn:dem":105,
    "gn:feature_class":"P",
    "gn:feature_code":"PPL",
    "gn:name":"Ruben",
    "gn:population":0,
    "gn:timezone":"Asia/Shanghai",
    "iso:country":"CN",
    "name:und_x_variant":[
        "\u5112\u672c",
        "Dunmu"
    ],
    "wof:name":"Ruben",
    "wof:placetype":"locality"
},
  "geometry": {"coordinates":[110.2525,19.86611],"type":"Point"}
}