{
  "type": "Feature",
  "properties": {
    "gn:admin1_code":"15.0",
    "gn:asciiname":"Yaxia",
    "gn:country_code":"CN",
    "gn:dem":2010,
    "gn:feature_class":"P",
    "gn:feature_code":"PPL",
    "gn:name":"Yaxia",
    "gn:population":0,
    "gn:timezone":"Asia/Shanghai",
    "iso:country":"CN",
    "name:und_x_variant":[
        "\u7259\u4e0b"
    ],
    "wof:name":"Yaxia",
    "wof:placetype":"locality"
},
  "geometry": {"coordinates":[104.39551,34.67698],"type":"Point"}
}