{
  "type": "Feature",
  "properties": {
    "gn:admin1_code":"10",
    "gn:asciiname":"Heilinzi",
    "gn:country_code":"CN",
    "gn:dem":994,
    "gn:feature_class":"P",
    "gn:feature_code":"PPL",
    "gn:name":"Heilinzi",
    "gn:population":0,
    "gn:timezone":"Asia/Shanghai",
    "iso:country":"CN",
    "name:zho_x_preferred":[
        "\u9ed1\u6797\u5b50"
    ],
    "wof:name":"Heilinzi",
    "wof:placetype":"locality"
},
  "geometry": {"coordinates":[116.99169999999999,41.88255],"type":"Point"}
}