{
  "type": "Feature",
  "properties": {
    "gn:admin1_code":"19.0",
    "gn:asciiname":"Jianshanzi",
    "gn:country_code":"CN",
    "gn:dem":240,
    "gn:feature_class":"P",
    "gn:feature_code":"PPL",
    "gn:name":"Jianshanzi",
    "gn:population":0,
    "gn:timezone":"Asia/Shanghai",
    "iso:country":"CN",
    "name:und_x_variant":[
        "\u5c16\u5c71\u5b50"
    ],
    "wof:name":"Jianshanzi",
    "wof:placetype":"locality"
},
  "geometry": {"coordinates":[123.06626,40.38187],"type":"Point"}
}