{
  "type": "Feature",
  "properties": {
    "gn:admin1_code":"29.0",
    "gn:asciiname":"Dahe",
    "gn:country_code":"CN",
    "gn:dem":1080,
    "gn:feature_class":"P",
    "gn:feature_code":"PPL",
    "gn:name":"Dahe",
    "gn:population":0,
    "gn:timezone":"Asia/Shanghai",
    "iso:country":"CN",
    "name:ceb_x_preferred":[
        "Dahe"
    ],
    "name:deu_x_preferred":[
        "Dahe"
    ],
    "name:swe_x_preferred":[
        "Dahe"
    ],
    "name:und_x_variant":[
        "\u5927\u6cb3"
    ],
    "wof:name":"Dahe",
    "wof:placetype":"locality"
},
  "geometry": {"coordinates":[105.09793999999999,27.7807],"type":"Point"}
}