{
  "type": "Feature",
  "properties": {
    "gn:admin1_code":"10.0",
    "gn:asciiname":"Bailinzhuang",
    "gn:country_code":"CN",
    "gn:dem":82,
    "gn:feature_class":"P",
    "gn:feature_code":"PPL",
    "gn:name":"Bailinzhuang",
    "gn:population":0,
    "gn:timezone":"Asia/Shanghai",
    "iso:country":"CN",
    "name:und_x_variant":[
        "\u67cf\u6797\u5e84"
    ],
    "wof:name":"Bailinzhuang",
    "wof:placetype":"locality"
},
  "geometry": {"coordinates":[114.47978000000001,38.07417],"type":"Point"}
}