{
  "type": "Feature",
  "properties": {
    "gn:admin1_code":"11",
    "gn:asciiname":"Dongbianling",
    "gn:country_code":"CN",
    "gn:dem":436,
    "gn:feature_class":"P",
    "gn:feature_code":"PPL",
    "gn:name":"Dongbianling",
    "gn:population":0,
    "gn:timezone":"Asia/Shanghai",
    "iso:country":"CN",
    "name:zho_x_preferred":[
        "\u4e1c\u8fb9\u5cad"
    ],
    "wof:name":"Dongbianling",
    "wof:placetype":"locality"
},
  "geometry": {"coordinates":[111.75771,26.13641],"type":"Point"}
}