{
  "type": "Feature",
  "properties": {
    "gn:admin1_code":"8.0",
    "gn:asciiname":"Fenglincun",
    "gn:country_code":"CN",
    "gn:dem":83,
    "gn:feature_class":"P",
    "gn:feature_code":"PPL",
    "gn:name":"Fenglincun",
    "gn:population":0,
    "gn:timezone":"Asia/Shanghai",
    "iso:country":"CN",
    "name:zho_x_preferred":[
        "\u51e4\u6797\u6751"
    ],
    "wof:name":"Fenglincun",
    "wof:placetype":"locality"
},
  "geometry": {"coordinates":[131.86041,46.61054],"type":"Point"}
}