{
  "type": "Feature",
  "properties": {
    "gn:admin1_code":"32",
    "gn:asciiname":"Fenshui",
    "gn:country_code":"CN",
    "gn:dem":1263,
    "gn:feature_class":"P",
    "gn:feature_code":"PPL",
    "gn:name":"Fenshui",
    "gn:population":0,
    "gn:timezone":"Asia/Shanghai",
    "iso:country":"CN",
    "name:und_x_variant":[
        "Fenshuijie",
        "Fenshui"
    ],
    "name:zho_x_preferred":[
        "\u5206\u6c34"
    ],
    "wof:name":"Fenshui",
    "wof:placetype":"locality"
},
  "geometry": {"coordinates":[105.26966000000002,27.87227],"type":"Point"}
}