{
  "type": "Feature",
  "properties": {
    "gn:admin1_code":"8.0",
    "gn:asciiname":"Changzhicun",
    "gn:country_code":"CN",
    "gn:dem":226,
    "gn:feature_class":"P",
    "gn:feature_code":"PPL",
    "gn:name":"Changzhicun",
    "gn:population":0,
    "gn:timezone":"Asia/Shanghai",
    "iso:country":"CN",
    "name:zho_x_preferred":[
        "\u957f\u5fd7\u6751"
    ],
    "wof:name":"Changzhicun",
    "wof:placetype":"locality"
},
  "geometry": {"coordinates":[126.96176,47.5144],"type":"Point"}
}