{
  "type": "Feature",
  "properties": {
    "gn:admin1_code":"8.0",
    "gn:asciiname":"Kaolincun",
    "gn:country_code":"CN",
    "gn:dem":308,
    "gn:feature_class":"P",
    "gn:feature_code":"PPL",
    "gn:name":"Kaolincun",
    "gn:population":0,
    "gn:timezone":"Asia/Shanghai",
    "iso:country":"CN",
    "name:zho_x_preferred":[
        "\u9760\u6797\u6751"
    ],
    "wof:name":"Kaolincun",
    "wof:placetype":"locality"
},
  "geometry": {"coordinates":[129.45871,44.60132],"type":"Point"}
}