{
  "type": "Feature",
  "properties": {
    "gn:admin1_code":"3.0",
    "gn:asciiname":"Dingzhai",
    "gn:country_code":"CN",
    "gn:dem":145,
    "gn:feature_class":"P",
    "gn:feature_code":"PPL",
    "gn:name":"Dingzhai",
    "gn:population":0,
    "gn:timezone":"Asia/Shanghai",
    "iso:country":"CN",
    "name:zho_x_preferred":[
        "\u4e01\u5b85"
    ],
    "name:zho_x_variant":[
        "\u4e01\u5be8\u6751"
    ],
    "wof:name":"Dingzhai",
    "wof:placetype":"locality"
},
  "geometry": {"coordinates":[117.91595,28.58225],"type":"Point"}
}