{
  "type": "Feature",
  "properties": {
    "gn:admin1_code":"12.0",
    "gn:asciiname":"Sanchaxi",
    "gn:country_code":"CN",
    "gn:dem":1283,
    "gn:feature_class":"P",
    "gn:feature_code":"PPL",
    "gn:name":"Sanchaxi",
    "gn:population":0,
    "gn:timezone":"Asia/Shanghai",
    "iso:country":"CN",
    "name:zho_x_preferred":[
        "\u4e09\u5c94\u6eaa"
    ],
    "wof:name":"Sanchaxi",
    "wof:placetype":"locality"
},
  "geometry": {"coordinates":[109.99748,30.53566],"type":"Point"}
}