{
  "type": "Feature",
  "properties": {
    "gn:admin1_code":"16.0",
    "gn:asciiname":"Dunmin",
    "gn:country_code":"CN",
    "gn:dem":22,
    "gn:feature_class":"P",
    "gn:feature_code":"PPL",
    "gn:name":"Dunmin",
    "gn:population":0,
    "gn:timezone":"Asia/Shanghai",
    "iso:country":"CN",
    "name:zho_x_preferred":[
        "\u6566\u6c11"
    ],
    "wof:name":"Dunmin",
    "wof:placetype":"locality"
},
  "geometry": {"coordinates":[108.42100000000001,22.1548],"type":"Point"}
}