{
  "type": "Feature",
  "properties": {
    "gn:admin1_code":"32.0",
    "gn:asciiname":"Xiaohaizi",
    "gn:country_code":"CN",
    "gn:dem":2719,
    "gn:feature_class":"P",
    "gn:feature_code":"PPL",
    "gn:name":"Xiaohaizi",
    "gn:population":0,
    "gn:timezone":"Asia/Shanghai",
    "iso:country":"CN",
    "name:zho_x_preferred":[
        "\u5c0f\u6d77\u5b50"
    ],
    "wof:name":"Xiaohaizi",
    "wof:placetype":"locality"
},
  "geometry": {"coordinates":[102.803,26.5138],"type":"Point"}
}