{
  "type": "Feature",
  "properties": {
    "gn:admin1_code":"12.0",
    "gn:asciiname":"Shangzhenya",
    "gn:country_code":"CN",
    "gn:dem":760,
    "gn:feature_class":"P",
    "gn:feature_code":"PPL",
    "gn:name":"Shangzhenya",
    "gn:population":0,
    "gn:timezone":"Asia/Shanghai",
    "iso:country":"CN",
    "name:zho_x_preferred":[
        "\u4e0a\u9635\u57ad"
    ],
    "wof:name":"Shangzhenya",
    "wof:placetype":"locality"
},
  "geometry": {"coordinates":[111.13426,31.15808],"type":"Point"}
}