{
  "type": "Feature",
  "properties": {
    "gn:admin1_code":"30",
    "gn:asciiname":"Puzhuping",
    "gn:country_code":"CN",
    "gn:dem":247,
    "gn:feature_class":"P",
    "gn:feature_code":"PPL",
    "gn:name":"Puzhuping",
    "gn:population":0,
    "gn:timezone":"Asia/Shanghai",
    "iso:country":"CN",
    "name:zho_x_preferred":[
        "\u84b2\u7af9\u576a"
    ],
    "wof:name":"Puzhuping",
    "wof:placetype":"locality"
},
  "geometry": {"coordinates":[111.67261999999999,22.33887],"type":"Point"}
}