{
  "type": "Feature",
  "properties": {
    "gn:admin1_code":"02",
    "gn:asciiname":"Zhangcicun",
    "gn:country_code":"CN",
    "gn:dem":7,
    "gn:feature_class":"P",
    "gn:feature_code":"PPL",
    "gn:name":"Zhangcicun",
    "gn:population":0,
    "gn:timezone":"Asia/Shanghai",
    "iso:country":"CN",
    "name:und_x_variant":[
        "Chang-ch\u2019ih-ts\u2019un",
        "Zhangci",
        "\u6da8\u6b21",
        "Zhangcicun",
        "\u6da8\u6b21\u6751"
    ],
    "wof:name":"Zhangcicun",
    "wof:placetype":"locality"
},
  "geometry": {"coordinates":[121.99109,30.0929],"type":"Point"}
}