{
  "type": "Feature",
  "properties": {
    "gn:admin1_code":"15.0",
    "gn:asciiname":"Sanxing",
    "gn:country_code":"CN",
    "gn:dem":1340,
    "gn:feature_class":"P",
    "gn:feature_code":"PPL",
    "gn:name":"Sanxing",
    "gn:population":0,
    "gn:timezone":"Asia/Shanghai",
    "iso:country":"CN",
    "name:zho_x_preferred":[
        "\u4e09\u661f"
    ],
    "wof:name":"Sanxing",
    "wof:placetype":"locality"
},
  "geometry": {"coordinates":[107.413,35.304],"type":"Point"}
}