{
  "type": "Feature",
  "properties": {
    "gn:admin1_code":"18",
    "gn:asciiname":"Heishitou",
    "gn:cc2":"CN",
    "gn:country_code":"CN",
    "gn:dem":2334,
    "gn:feature_class":"P",
    "gn:feature_code":"PPL",
    "gn:name":"Heishitou",
    "gn:population":0,
    "gn:timezone":"Asia/Shanghai",
    "iso:country":"CN",
    "name:und_x_variant":[
        "Hei-shih-t\u2019ou",
        "Heishitou"
    ],
    "wof:name":"Heishitou",
    "wof:placetype":"locality"
},
  "geometry": {"coordinates":[104.01667,26.73333],"type":"Point"}
}