{
  "type": "Feature",
  "properties": {
    "gn:admin1_code":"30",
    "gn:asciiname":"Fenglintang",
    "gn:country_code":"CN",
    "gn:dem":106,
    "gn:feature_class":"P",
    "gn:feature_code":"PPL",
    "gn:name":"Fenglintang",
    "gn:population":0,
    "gn:timezone":"Asia/Shanghai",
    "iso:country":"CN",
    "name:zho_x_preferred":[
        "\u67ab\u6797\u5858"
    ],
    "wof:name":"Fenglintang",
    "wof:placetype":"locality"
},
  "geometry": {"coordinates":[115.74172,23.97019],"type":"Point"}
}