{
  "type": "Feature",
  "properties": {
    "gn:admin1_code":"21.0",
    "gn:asciiname":"Shishangou",
    "gn:country_code":"CN",
    "gn:dem":1526,
    "gn:feature_class":"P",
    "gn:feature_code":"PPL",
    "gn:name":"Shishangou",
    "gn:population":0,
    "gn:timezone":"Asia/Shanghai",
    "iso:country":"CN",
    "name:zho_x_preferred":[
        "\u77f3\u5c71\u6c9f"
    ],
    "wof:name":"Shishangou",
    "wof:placetype":"locality"
},
  "geometry": {"coordinates":[107.241,37.5156],"type":"Point"}
}