{
  "type": "Feature",
  "properties": {
    "gn:admin1_code":"19.0",
    "gn:asciiname":"Zhusantaizi",
    "gn:country_code":"CN",
    "gn:dem":21,
    "gn:feature_class":"P",
    "gn:feature_code":"PPL",
    "gn:name":"Zhusantaizi",
    "gn:population":0,
    "gn:timezone":"Asia/Shanghai",
    "iso:country":"CN",
    "name:zho_x_preferred":[
        "\u6731\u4e09\u53f0\u5b50"
    ],
    "wof:name":"Zhusantaizi",
    "wof:placetype":"locality"
},
  "geometry": {"coordinates":[122.633,41.8041],"type":"Point"}
}