{
  "type": "Feature",
  "properties": {
    "gn:admin1_code":"30.0",
    "gn:asciiname":"Longhu",
    "gn:country_code":"CN",
    "gn:dem":8,
    "gn:feature_class":"P",
    "gn:feature_code":"PPL",
    "gn:name":"Longhu",
    "gn:population":0,
    "gn:timezone":"Asia/Shanghai",
    "iso:country":"CN",
    "name:ceb_x_preferred":[
        "Longhu"
    ],
    "name:deu_x_preferred":[
        "Longhu"
    ],
    "name:zho_x_preferred":[
        "\u9f99\u62a4"
    ],
    "wof:name":"Longhu",
    "wof:placetype":"locality"
},
  "geometry": {"coordinates":[112.53973000000001,22.28791],"type":"Point"}
}