{
  "type": "Feature",
  "properties": {
    "gn:admin1_code":"8.0",
    "gn:asciiname":"Gongrong",
    "gn:country_code":"CN",
    "gn:dem":222,
    "gn:feature_class":"P",
    "gn:feature_code":"PPLA4",
    "gn:name":"Gongrong",
    "gn:population":0,
    "gn:timezone":"Asia/Shanghai",
    "iso:country":"CN",
    "name:und_x_variant":[
        "Gongrong Xiang"
    ],
    "name:zho_x_preferred":[
        "\u5171\u8363"
    ],
    "name:zho_x_variant":[
        "\u5171\u8363\u4e61"
    ],
    "wof:name":"Gongrong",
    "wof:placetype":"locality"
},
  "geometry": {"coordinates":[126.85192000000001,47.16517],"type":"Point"}
}