{
  "type": "Feature",
  "properties": {
    "gn:admin1_code":"29.0",
    "gn:asciiname":"Laopushan",
    "gn:country_code":"CN",
    "gn:dem":1537,
    "gn:feature_class":"P",
    "gn:feature_code":"PPL",
    "gn:name":"Laopushan",
    "gn:population":0,
    "gn:timezone":"Asia/Shanghai",
    "iso:country":"CN",
    "name:zho_x_preferred":[
        "\u8001\u666e\u5c71"
    ],
    "wof:name":"Laopushan",
    "wof:placetype":"locality"
},
  "geometry": {"coordinates":[101.017,22.9008],"type":"Point"}
}