{
  "type": "Feature",
  "properties": {
    "gn:admin1_code":"18.0",
    "gn:asciiname":"Shangdeya",
    "gn:country_code":"CN",
    "gn:dem":864,
    "gn:feature_class":"P",
    "gn:feature_code":"PPL",
    "gn:name":"Shangdeya",
    "gn:population":0,
    "gn:timezone":"Asia/Shanghai",
    "iso:country":"CN",
    "name:zho_x_preferred":[
        "\u4e0a\u7684\u9e2d"
    ],
    "wof:name":"Shangdeya",
    "wof:placetype":"locality"
},
  "geometry": {"coordinates":[107.845,25.7139],"type":"Point"}
}