{
  "type": "Feature",
  "properties": {
    "gn:admin1_code":"3",
    "gn:asciiname":"Mazuyan",
    "gn:country_code":"CN",
    "gn:dem":123,
    "gn:feature_class":"P",
    "gn:feature_code":"PPL",
    "gn:name":"Mazuyan",
    "gn:population":0,
    "gn:timezone":"Asia/Shanghai",
    "iso:country":"CN",
    "name:zho_x_preferred":[
        "\u9a6c\u7956\u5ca9"
    ],
    "wof:name":"Mazuyan",
    "wof:placetype":"locality"
},
  "geometry": {"coordinates":[114.95735999999999,25.87436],"type":"Point"}
}