{
  "type": "Feature",
  "properties": {
    "gn:admin1_code":"07",
    "gn:asciiname":"Daquankeng",
    "gn:country_code":"CN",
    "gn:dem":481,
    "gn:feature_class":"P",
    "gn:feature_code":"PPL",
    "gn:name":"Daquankeng",
    "gn:population":0,
    "gn:timezone":"Asia/Shanghai",
    "iso:country":"CN",
    "name:zho_x_preferred":[
        "\u5927\u6cc9\u5751"
    ],
    "wof:name":"Daquankeng",
    "wof:placetype":"locality"
},
  "geometry": {"coordinates":[117.26054999999999,26.00167],"type":"Point"}
}