{
  "type": "Feature",
  "properties": {
    "gn:admin1_code":"30",
    "gn:asciiname":"Datangtou",
    "gn:country_code":"CN",
    "gn:dem":64,
    "gn:feature_class":"P",
    "gn:feature_code":"PPL",
    "gn:name":"Datangtou",
    "gn:population":0,
    "gn:timezone":"Asia/Urumqi",
    "iso:country":"CN",
    "name:zho_x_preferred":[
        "\u5927\u5858\u5934"
    ],
    "wof:name":"Datangtou",
    "wof:placetype":"locality"
},
  "geometry": {"coordinates":[110.11387000000001,21.73852],"type":"Point"}
}