{
  "type": "Feature",
  "properties": {
    "gn:admin1_code":"16.0",
    "gn:asciiname":"Longtoushi",
    "gn:country_code":"CN",
    "gn:dem":21,
    "gn:feature_class":"P",
    "gn:feature_code":"PPL",
    "gn:name":"Longtoushi",
    "gn:population":0,
    "gn:timezone":"Asia/Shanghai",
    "iso:country":"CN",
    "name:zho_x_preferred":[
        "\u9f99\u5934\u77f3"
    ],
    "wof:name":"Longtoushi",
    "wof:placetype":"locality"
},
  "geometry": {"coordinates":[108.273,21.8149],"type":"Point"}
}