{
  "type": "Feature",
  "properties": {
    "gn:admin1_code":"9.0",
    "gn:asciiname":"Xincai",
    "gn:country_code":"CN",
    "gn:dem":41,
    "gn:feature_class":"P",
    "gn:feature_code":"PPLA3",
    "gn:name":"Xincai",
    "gn:population":0,
    "gn:timezone":"Asia/Shanghai",
    "iso:country":"CN",
    "name:und_x_variant":[
        "Ching-fu",
        "Hsin-ts\u2019ai-hsien",
        "Sintsai-hsien",
        "Hsin-ts\u2019ai",
        "Xincai",
        "Gul\u00fc"
    ],
    "name:zho_x_preferred":[
        "\u53e4\u5415"
    ],
    "wof:name":"Xincai",
    "wof:placetype":"locality"
},
  "geometry": {"coordinates":[114.97611000000001,32.74389],"type":"Point"}
}