{
  "type": "Feature",
  "properties": {
    "gn:admin1_code":"15.0",
    "gn:asciiname":"Anjiashan",
    "gn:country_code":"CN",
    "gn:dem":1396,
    "gn:feature_class":"P",
    "gn:feature_code":"PPL",
    "gn:name":"Anjiashan",
    "gn:population":0,
    "gn:timezone":"Asia/Shanghai",
    "iso:country":"CN",
    "name:zho_x_preferred":[
        "\u5b89\u5bb6\u5c71"
    ],
    "wof:name":"Anjiashan",
    "wof:placetype":"locality"
},
  "geometry": {"coordinates":[105.09148,32.98003],"type":"Point"}
}