{
  "type": "Feature",
  "properties": {
    "gn:admin1_code":"7.0",
    "gn:asciiname":"Songlinxia",
    "gn:country_code":"CN",
    "gn:dem":363,
    "gn:feature_class":"P",
    "gn:feature_code":"PPL",
    "gn:name":"Songlinxia",
    "gn:population":0,
    "gn:timezone":"Asia/Shanghai",
    "iso:country":"CN",
    "name:zho_x_preferred":[
        "\u677e\u6797\u4e0b"
    ],
    "wof:name":"Songlinxia",
    "wof:placetype":"locality"
},
  "geometry": {"coordinates":[117.47578,27.80758],"type":"Point"}
}