{
  "type": "Feature",
  "properties": {
    "gn:admin1_code":"18.0",
    "gn:asciiname":"Bajiaowan",
    "gn:country_code":"CN",
    "gn:dem":492,
    "gn:feature_class":"P",
    "gn:feature_code":"PPL",
    "gn:name":"Bajiaowan",
    "gn:population":0,
    "gn:timezone":"Asia/Shanghai",
    "iso:country":"CN",
    "name:zho_x_preferred":[
        "\u82ad\u8549\u6e7e"
    ],
    "wof:name":"Bajiaowan",
    "wof:placetype":"locality"
},
  "geometry": {"coordinates":[108.70699999999999,27.1489],"type":"Point"}
}