{
  "type": "Feature",
  "properties": {
    "gn:admin1_code":"29.0",
    "gn:asciiname":"Yingtaoshu",
    "gn:country_code":"CN",
    "gn:dem":1474,
    "gn:feature_class":"P",
    "gn:feature_code":"PPL",
    "gn:name":"Yingtaoshu",
    "gn:population":0,
    "gn:timezone":"Asia/Shanghai",
    "iso:country":"CN",
    "name:zho_x_preferred":[
        "\u6a31\u6843\u6811"
    ],
    "wof:name":"Yingtaoshu",
    "wof:placetype":"locality"
},
  "geometry": {"coordinates":[103.968,27.6308],"type":"Point"}
}