{
  "type": "Feature",
  "properties": {
    "gn:admin1_code":"4.0",
    "gn:asciiname":"Zhahecun",
    "gn:country_code":"CN",
    "gn:dem":5,
    "gn:feature_class":"P",
    "gn:feature_code":"PPL",
    "gn:name":"Zhahecun",
    "gn:population":0,
    "gn:timezone":"Asia/Shanghai",
    "iso:country":"CN",
    "name:zho_x_preferred":[
        "\u95f8\u6cb3\u6751"
    ],
    "wof:name":"Zhahecun",
    "wof:placetype":"locality"
},
  "geometry": {"coordinates":[119.45690999999999,32.69269],"type":"Point"}
}