{
  "type": "Feature",
  "properties": {
    "gn:admin1_code":"29",
    "gn:asciiname":"Yangliuhe",
    "gn:country_code":"CN",
    "gn:dem":2049,
    "gn:feature_class":"P",
    "gn:feature_code":"PPL",
    "gn:name":"Yangliuhe",
    "gn:population":0,
    "gn:timezone":"Asia/Shanghai",
    "iso:country":"CN",
    "name:zho_x_preferred":[
        "\u6768\u67f3\u6cb3"
    ],
    "wof:name":"Yangliuhe",
    "wof:placetype":"locality"
},
  "geometry": {"coordinates":[102.33071,24.44771],"type":"Point"}
}