{
  "type": "Feature",
  "properties": {
    "gn:admin1_code":"26.0",
    "gn:asciiname":"Lujiayuancun",
    "gn:country_code":"CN",
    "gn:dem":1479,
    "gn:feature_class":"P",
    "gn:feature_code":"PPL",
    "gn:name":"Lujiayuancun",
    "gn:population":0,
    "gn:timezone":"Asia/Shanghai",
    "iso:country":"CN",
    "name:zho_x_preferred":[
        "\u9c81\u5bb6\u586c\u6751"
    ],
    "wof:name":"Lujiayuancun",
    "wof:placetype":"locality"
},
  "geometry": {"coordinates":[109.74843,35.70309],"type":"Point"}
}