{
  "type": "Feature",
  "properties": {
    "gn:admin1_code":"14",
    "gn:asciiname":"Tajie",
    "gn:country_code":"CN",
    "gn:dem":4057,
    "gn:feature_class":"P",
    "gn:feature_code":"PPL",
    "gn:name":"Tajie",
    "gn:population":0,
    "gn:timezone":"Asia/Urumqi",
    "iso:country":"CN",
    "name:zho_x_preferred":[
        "\u5854\u6770"
    ],
    "wof:name":"Tajie",
    "wof:placetype":"locality"
},
  "geometry": {"coordinates":[89.8952,29.1404],"type":"Point"}
}