{
  "type": "Feature",
  "properties": {
    "gn:admin1_code":"3.0",
    "gn:asciiname":"Xuejiashan",
    "gn:country_code":"CN",
    "gn:dem":54,
    "gn:feature_class":"P",
    "gn:feature_code":"PPL",
    "gn:name":"Xuejiashan",
    "gn:population":0,
    "gn:timezone":"Asia/Shanghai",
    "iso:country":"CN",
    "name:und_x_variant":[
        "\u859b\u5bb6\u5c71"
    ],
    "wof:name":"Xuejiashan",
    "wof:placetype":"locality"
},
  "geometry": {"coordinates":[116.48256000000001,29.3879],"type":"Point"}
}