{
  "type": "Feature",
  "properties": {
    "gn:admin1_code":"2.0",
    "gn:asciiname":"Xianzhiling",
    "gn:country_code":"CN",
    "gn:dem":379,
    "gn:feature_class":"P",
    "gn:feature_code":"PPL",
    "gn:name":"Xianzhiling",
    "gn:population":0,
    "gn:timezone":"Asia/Shanghai",
    "iso:country":"CN",
    "name:zho_x_preferred":[
        "\u4ed9\u829d\u5cad"
    ],
    "name:zho_x_variant":[
        "\u4ed9\u829d\u9675"
    ],
    "wof:name":"Xianzhiling",
    "wof:placetype":"locality"
},
  "geometry": {"coordinates":[120.42061,29.41297],"type":"Point"}
}