{
  "type": "Feature",
  "properties": {
    "gn:admin1_code":"19.0",
    "gn:asciiname":"Laomanzicun",
    "gn:country_code":"CN",
    "gn:dem":351,
    "gn:feature_class":"P",
    "gn:feature_code":"PPL",
    "gn:name":"Laomanzicun",
    "gn:population":0,
    "gn:timezone":"Asia/Shanghai",
    "iso:country":"CN",
    "name:zho_x_preferred":[
        "\u8001\u6f2b\u5b50\u6751"
    ],
    "wof:name":"Laomanzicun",
    "wof:placetype":"locality"
},
  "geometry": {"coordinates":[125.05446999999999,41.15169],"type":"Point"}
}