{
  "type": "Feature",
  "properties": {
    "gn:admin1_code":"7",
    "gn:asciiname":"Humei",
    "gn:country_code":"CN",
    "gn:dem":20,
    "gn:feature_class":"P",
    "gn:feature_code":"PPL",
    "gn:name":"Humei",
    "gn:population":0,
    "gn:timezone":"Asia/Shanghai",
    "iso:country":"CN",
    "name:zho_x_preferred":[
        "\u6e56\u7f8e"
    ],
    "wof:name":"Humei",
    "wof:placetype":"locality"
},
  "geometry": {"coordinates":[119.50445999999999,25.73371],"type":"Point"}
}