{
  "type": "Feature",
  "properties": {
    "gn:admin1_code":"3.0",
    "gn:asciiname":"Meijiapai",
    "gn:country_code":"CN",
    "gn:dem":146,
    "gn:feature_class":"P",
    "gn:feature_code":"PPL",
    "gn:name":"Meijiapai",
    "gn:population":0,
    "gn:timezone":"Asia/Shanghai",
    "iso:country":"CN",
    "name:und_x_variant":[
        "\u6885\u5bb6\u6392"
    ],
    "wof:name":"Meijiapai",
    "wof:placetype":"locality"
},
  "geometry": {"coordinates":[116.86453,27.84606],"type":"Point"}
}