{
  "type": "Feature",
  "properties": {
    "gn:admin1_code":"2.0",
    "gn:asciiname":"Yangkengtang",
    "gn:country_code":"CN",
    "gn:dem":294,
    "gn:feature_class":"P",
    "gn:feature_code":"PPL",
    "gn:name":"Yangkengtang",
    "gn:population":0,
    "gn:timezone":"Asia/Shanghai",
    "iso:country":"CN",
    "name:zho_x_preferred":[
        "\u9633\u5751\u5858"
    ],
    "wof:name":"Yangkengtang",
    "wof:placetype":"locality"
},
  "geometry": {"coordinates":[119.65749,28.69858],"type":"Point"}
}