{
  "type": "Feature",
  "properties": {
    "gn:admin1_code":"5.0",
    "gn:asciiname":"Longmumiao",
    "gn:country_code":"CN",
    "gn:dem":190,
    "gn:feature_class":"P",
    "gn:feature_code":"PPL",
    "gn:name":"Longmumiao",
    "gn:population":0,
    "gn:timezone":"Asia/Shanghai",
    "iso:country":"CN",
    "name:zho_x_preferred":[
        "\u9f99\u6bcd\u5e99"
    ],
    "wof:name":"Longmumiao",
    "wof:placetype":"locality"
},
  "geometry": {"coordinates":[125.63602,44.47121],"type":"Point"}
}