{
  "type": "Feature",
  "properties": {
    "gn:admin1_code":"01",
    "gn:asciiname":"Foziling",
    "gn:cc2":"CN",
    "gn:country_code":"CN",
    "gn:dem":97,
    "gn:feature_class":"P",
    "gn:feature_code":"PPL",
    "gn:name":"Foziling",
    "gn:population":0,
    "gn:timezone":"Asia/Shanghai",
    "iso:country":"CN",
    "name:und_x_variant":[
        "Futseling",
        "Fo-tzu-ling",
        "Fu-tzu-ling",
        "Foziling"
    ],
    "wof:name":"Foziling",
    "wof:placetype":"locality"
},
  "geometry": {"coordinates":[116.25221999999999,31.36167],"type":"Point"}
}