{
  "type": "Feature",
  "properties": {
    "gn:admin1_code":"19.0",
    "gn:asciiname":"Sanfangshencun",
    "gn:country_code":"CN",
    "gn:dem":79,
    "gn:feature_class":"P",
    "gn:feature_code":"PPL",
    "gn:name":"Sanfangshencun",
    "gn:population":0,
    "gn:timezone":"Asia/Shanghai",
    "iso:country":"CN",
    "name:zho_x_preferred":[
        "\u4e09\u623f\u8eab\u6751"
    ],
    "wof:name":"Sanfangshencun",
    "wof:placetype":"locality"
},
  "geometry": {"coordinates":[121.81999999999999,39.1435],"type":"Point"}
}