{
  "type": "Feature",
  "properties": {
    "gn:admin1_code":"26.0",
    "gn:asciiname":"Hanjiamao",
    "gn:country_code":"CN",
    "gn:dem":1154,
    "gn:feature_class":"P",
    "gn:feature_code":"PPL",
    "gn:name":"Hanjiamao",
    "gn:population":0,
    "gn:timezone":"Asia/Shanghai",
    "iso:country":"CN",
    "name:zho_x_preferred":[
        "\u97e9\u5bb6\u5cc1"
    ],
    "wof:name":"Hanjiamao",
    "wof:placetype":"locality"
},
  "geometry": {"coordinates":[109.06545,37.86026],"type":"Point"}
}