{
  "type": "Feature",
  "properties": {
    "gn:admin1_code":"33.0",
    "gn:asciiname":"Gaojiaba",
    "gn:country_code":"CN",
    "gn:dem":707,
    "gn:feature_class":"P",
    "gn:feature_code":"PPL",
    "gn:name":"Gaojiaba",
    "gn:population":0,
    "gn:timezone":"Asia/Shanghai",
    "iso:country":"CN",
    "name:zho_x_preferred":[
        "\u9ad8\u5bb6\u575d"
    ],
    "wof:name":"Gaojiaba",
    "wof:placetype":"locality"
},
  "geometry": {"coordinates":[108.76946,28.78002],"type":"Point"}
}