{
  "type": "Feature",
  "properties": {
    "gn:admin1_code":"33.0",
    "gn:asciiname":"Hongzhu",
    "gn:country_code":"CN",
    "gn:dem":390,
    "gn:feature_class":"P",
    "gn:feature_code":"PPL",
    "gn:name":"Hongzhu",
    "gn:population":0,
    "gn:timezone":"Asia/Shanghai",
    "iso:country":"CN",
    "name:zho_x_preferred":[
        "\u7ea2\u7af9"
    ],
    "wof:name":"Hongzhu",
    "wof:placetype":"locality"
},
  "geometry": {"coordinates":[106.78758000000001,29.92216],"type":"Point"}
}