{
  "type": "Feature",
  "properties": {
    "gn:admin1_code":"32.0",
    "gn:asciiname":"Shihegou",
    "gn:country_code":"CN",
    "gn:dem":449,
    "gn:feature_class":"P",
    "gn:feature_code":"PPL",
    "gn:name":"Shihegou",
    "gn:population":0,
    "gn:timezone":"Asia/Shanghai",
    "iso:country":"CN",
    "name:zho_x_preferred":[
        "\u77f3\u6cb3\u6c9f"
    ],
    "wof:name":"Shihegou",
    "wof:placetype":"locality"
},
  "geometry": {"coordinates":[104.43899999999999,30.55456],"type":"Point"}
}