{
  "type": "Feature",
  "properties": {
    "gn:admin1_code":"16.0",
    "gn:asciiname":"Lamen",
    "gn:country_code":"CN",
    "gn:dem":442,
    "gn:feature_class":"P",
    "gn:feature_code":"PPL",
    "gn:name":"Lamen",
    "gn:population":0,
    "gn:timezone":"Asia/Shanghai",
    "iso:country":"CN",
    "name:ceb_x_preferred":[
        "Lamen"
    ],
    "name:swe_x_preferred":[
        "Lamen"
    ],
    "name:zho_x_preferred":[
        "\u62c9\u95f7"
    ],
    "wof:name":"Lamen",
    "wof:placetype":"locality"
},
  "geometry": {"coordinates":[108.346,23.8374],"type":"Point"}
}