{
  "type": "Feature",
  "properties": {
    "gn:admin1_code":"26.0",
    "gn:asciiname":"Yaozigou",
    "gn:country_code":"CN",
    "gn:dem":1349,
    "gn:feature_class":"P",
    "gn:feature_code":"PPL",
    "gn:name":"Yaozigou",
    "gn:population":0,
    "gn:timezone":"Asia/Shanghai",
    "iso:country":"CN",
    "name:zho_x_preferred":[
        "\u7a91\u5b50\u6c9f"
    ],
    "wof:name":"Yaozigou",
    "wof:placetype":"locality"
},
  "geometry": {"coordinates":[109.33101000000001,37.02077],"type":"Point"}
}