{
  "type": "Feature",
  "properties": {
    "gn:admin1_code":"6.0",
    "gn:asciiname":"Kasha",
    "gn:country_code":"CN",
    "gn:dem":3712,
    "gn:feature_class":"P",
    "gn:feature_code":"PPL",
    "gn:name":"Kasha",
    "gn:population":0,
    "gn:timezone":"Asia/Urumqi",
    "iso:country":"CN",
    "name:zho_x_preferred":[
        "\u5361\u6c99"
    ],
    "wof:name":"Kasha",
    "wof:placetype":"locality"
},
  "geometry": {"coordinates":[97.37125,32.73051],"type":"Point"}
}