{
  "type": "Feature",
  "properties": {
    "gn:admin1_code":"6.0",
    "gn:asciiname":"Kasha",
    "gn:country_code":"CN",
    "gn:dem":3712,
    "gn:feature_class":"P",
    "gn:feature_code":"PPL",
    "gn:name":"Kasha",
    "gn:population":0,
    "gn:timezone":"Asia/Urumqi",
    "iso:country":"CN",
    "name:ara_x_preferred":[
        "\u0643\u0634\u0643\u0627\u0629"
    ],
    "name:aze_x_preferred":[
        "Qaraba\u015faq s\u0131y\u0131\u011f\u0131"
    ],
    "name:chv_x_preferred":[
        "\u041f\u0103\u0442\u0103"
    ],
    "name:deu_x_preferred":[
        "Gretschnewaja Kascha"
    ],
    "name:epo_x_preferred":[
        "Fagopira grio"
    ],
    "name:est_x_preferred":[
        "Tatrapuder"
    ],
    "name:fas_x_preferred":[
        "\u06a9\u0627\u0634\u0627"
    ],
    "name:fra_x_preferred":[
        "Kacha"
    ],
    "name:heb_x_preferred":[
        "\u05e7\u05d0\u05e9\u05d4"
    ],
    "name:hun_x_preferred":[
        "K\u00e1sa"
    ],
    "name:hye_x_preferred":[
        "\u0540\u0576\u0564\u056f\u0561\u0581\u0578\u0580\u0565\u0576\u056b \u0577\u056b\u056c\u0561"
    ],
    "name:ita_x_preferred":[
        "Ka\u0161a"
    ],
    "name:jpn_x_preferred":[
        "\u30ab\u30fc\u30b7\u30e3"
    ],
    "name:kat_x_preferred":[
        "\u10e4\u10d0\u10e4\u10d0"
    ],
    "name:lit_x_preferred":[
        "Griki\u0173 ko\u0161\u0117"
    ],
    "name:nld_x_preferred":[
        "Kasja"
    ],
    "name:pol_x_preferred":[
        "Kasza gryczana"
    ],
    "name:por_x_preferred":[
        "Kasha"
    ],
    "name:rus_x_preferred":[
        "\u0413\u0440\u0435\u0447\u043d\u0435\u0432\u0430\u044f \u043a\u0430\u0448\u0430"
    ],
    "name:sah_x_preferred":[
        "\u0413\u0440\u0435\u0447\u043d\u0435\u0432\u0430\u0439 \u0445\u0430\u0430\u04bb\u044b"
    ],
    "name:spa_x_preferred":[
        "Kasha"
    ],
    "name:szl_x_preferred":[
        "Poga\u0144ske krupy"
    ],
    "name:tur_x_preferred":[
        "D\u00fc\u011f\u00fcrc\u00fck \u00e7orbas\u0131"
    ],
    "name:ukr_x_preferred":[
        "\u0413\u0440\u0435\u0447\u0430\u043d\u0430 \u043a\u0430\u0448\u0430"
    ],
    "name:zho_x_preferred":[
        "\u5361\u6c99"
    ],
    "wof:name":"Kasha",
    "wof:placetype":"locality"
},
  "geometry": {"coordinates":[97.37125,32.73051],"type":"Point"}
}