{
  "type": "Feature",
  "properties": {
    "gn:admin1_code":"11",
    "gn:asciiname":"Liaoyelong",
    "gn:country_code":"CN",
    "gn:dem":348,
    "gn:feature_class":"P",
    "gn:feature_code":"PPL",
    "gn:name":"Liaoyelong",
    "gn:population":0,
    "gn:timezone":"Asia/Shanghai",
    "iso:country":"CN",
    "wof:name":"Liaoyelong",
    "wof:placetype":"locality"
},
  "geometry": {"coordinates":[113.58222000000001,27.08667],"type":"Point"}
}