{
  "type": "Feature",
  "properties": {
    "gn:admin1_code":"30",
    "gn:asciiname":"Bailian",
    "gn:country_code":"CN",
    "gn:dem":22,
    "gn:feature_class":"P",
    "gn:feature_code":"PPL",
    "gn:name":"Bailian",
    "gn:population":0,
    "gn:timezone":"Asia/Shanghai",
    "iso:country":"CN",
    "name:zho_x_preferred":[
        "\u767d\u83b2"
    ],
    "wof:name":"Bailian",
    "wof:placetype":"locality"
},
  "geometry": {"coordinates":[116.49415999999999,23.86179],"type":"Point"}
}