{
  "type": "Feature",
  "properties": {
    "gn:admin1_code":"13",
    "gn:asciiname":"Hongshan",
    "gn:country_code":"CN",
    "gn:dem":1076,
    "gn:feature_class":"P",
    "gn:feature_code":"PPL",
    "gn:name":"Hongshan",
    "gn:population":0,
    "gn:timezone":"Asia/Urumqi",
    "iso:country":"CN",
    "name:zho_x_preferred":[
        "\u7ea2\u5c71"
    ],
    "wof:name":"Hongshan",
    "wof:placetype":"locality"
},
  "geometry": {"coordinates":[91.62242000000001,43.37736],"type":"Point"}
}