{
  "type": "Feature",
  "properties": {
    "gn:admin1_code":"9.0",
    "gn:asciiname":"Qianlecheng",
    "gn:country_code":"CN",
    "gn:dem":65,
    "gn:feature_class":"P",
    "gn:feature_code":"PPL",
    "gn:name":"Qianlecheng",
    "gn:population":0,
    "gn:timezone":"Asia/Shanghai",
    "iso:country":"CN",
    "name:zho_x_preferred":[
        "\u524d\u4e86\u57ce"
    ],
    "wof:name":"Qianlecheng",
    "wof:placetype":"locality"
},
  "geometry": {"coordinates":[114.761,34.68795],"type":"Point"}
}