{
  "type": "Feature",
  "properties": {
    "gn:admin1_code":"7.0",
    "gn:asciiname":"Genggulai",
    "gn:country_code":"CN",
    "gn:dem":207,
    "gn:feature_class":"P",
    "gn:feature_code":"PPL",
    "gn:name":"Genggulai",
    "gn:population":0,
    "gn:timezone":"Asia/Shanghai",
    "iso:country":"CN",
    "name:und_x_variant":[
        "\u66f4\u9f13\u6fd1"
    ],
    "name:zho_x_preferred":[
        "\u66f4\u9f13\u6fd1"
    ],
    "wof:name":"Genggulai",
    "wof:placetype":"locality"
},
  "geometry": {"coordinates":[118.13509999999999,26.02116],"type":"Point"}
}