{
  "type": "Feature",
  "properties": {
    "gn:admin1_code":"30.0",
    "gn:asciiname":"Fozailingjiao",
    "gn:country_code":"CN",
    "gn:dem":217,
    "gn:feature_class":"P",
    "gn:feature_code":"PPL",
    "gn:name":"Fozailingjiao",
    "gn:population":0,
    "gn:timezone":"Asia/Shanghai",
    "iso:country":"CN",
    "name:zho_x_preferred":[
        "\u4f5b\u4ed4\u5cad\u811a"
    ],
    "wof:name":"Fozailingjiao",
    "wof:placetype":"locality"
},
  "geometry": {"coordinates":[112.47682,23.79601],"type":"Point"}
}