{
  "type": "Feature",
  "properties": {
    "gn:admin1_code":"32.0",
    "gn:asciiname":"Donghekou",
    "gn:country_code":"CN",
    "gn:dem":681,
    "gn:feature_class":"P",
    "gn:feature_code":"PPL",
    "gn:name":"Donghekou",
    "gn:population":0,
    "gn:timezone":"Asia/Shanghai",
    "iso:country":"CN",
    "name:zho_x_preferred":[
        "\u4e1c\u6cb3\u53e3"
    ],
    "wof:name":"Donghekou",
    "wof:placetype":"locality"
},
  "geometry": {"coordinates":[105.121,32.4122],"type":"Point"}
}