{
  "type": "Feature",
  "properties": {
    "gn:admin1_code":"18",
    "gn:asciiname":"Tiejiangzhai",
    "gn:country_code":"CN",
    "gn:dem":1962,
    "gn:feature_class":"P",
    "gn:feature_code":"PPL",
    "gn:name":"Tiejiangzhai",
    "gn:population":0,
    "gn:timezone":"Asia/Shanghai",
    "iso:country":"CN",
    "name:zho_x_preferred":[
        "\u94c1\u5320\u5be8"
    ],
    "wof:name":"Tiejiangzhai",
    "wof:placetype":"locality"
},
  "geometry": {"coordinates":[104.426,27.3804],"type":"Point"}
}