{
  "type": "Feature",
  "properties": {
    "gn:admin1_code":"12.0",
    "gn:asciiname":"Hejiawan",
    "gn:country_code":"CN",
    "gn:dem":30,
    "gn:feature_class":"P",
    "gn:feature_code":"PPL",
    "gn:name":"Hejiawan",
    "gn:population":0,
    "gn:timezone":"Asia/Shanghai",
    "iso:country":"CN",
    "name:und_x_variant":[
        "\u4f55\u5bb6\u5846"
    ],
    "wof:name":"Hejiawan",
    "wof:placetype":"locality"
},
  "geometry": {"coordinates":[114.59667,30.66997000000001],"type":"Point"}
}