{
  "type": "Feature",
  "properties": {
    "gn:admin1_code":"18",
    "gn:asciiname":"Hankongba",
    "gn:country_code":"CN",
    "gn:dem":1115,
    "gn:feature_class":"P",
    "gn:feature_code":"PPL",
    "gn:name":"Hankongba",
    "gn:population":0,
    "gn:timezone":"Asia/Shanghai",
    "iso:country":"CN",
    "name:zho_x_preferred":[
        "\u97e9\u7a7a\u575d"
    ],
    "wof:name":"Hankongba",
    "wof:placetype":"locality"
},
  "geometry": {"coordinates":[107.104,28.4257],"type":"Point"}
}