{
  "type": "Feature",
  "properties": {
    "gn:admin1_code":"29.0",
    "gn:asciiname":"Erla",
    "gn:country_code":"CN",
    "gn:dem":1354,
    "gn:feature_class":"P",
    "gn:feature_code":"PPL",
    "gn:name":"Erla",
    "gn:population":0,
    "gn:timezone":"Asia/Shanghai",
    "iso:country":"CN",
    "name:ara_x_preferred":[
        "\u0625\u0631\u0644\u0627"
    ],
    "name:arg_x_preferred":[
        "Erla"
    ],
    "name:ast_x_preferred":[
        "Erla"
    ],
    "name:azb_x_preferred":[
        "\u0627\u0631\u0644\u0627"
    ],
    "name:cat_x_preferred":[
        "Erla"
    ],
    "name:ceb_x_preferred":[
        "Erla"
    ],
    "name:eus_x_preferred":[
        "Erla"
    ],
    "name:fas_x_preferred":[
        "\u0627\u0631\u0644\u0627"
    ],
    "name:fra_x_preferred":[
        "Erla"
    ],
    "name:hak_x_preferred":[
        "Erla"
    ],
    "name:hun_x_preferred":[
        "Erla"
    ],
    "name:hye_x_preferred":[
        "\u0537\u0580\u056c\u0561"
    ],
    "name:ita_x_preferred":[
        "Erla"
    ],
    "name:msa_x_preferred":[
        "Erla"
    ],
    "name:oci_x_preferred":[
        "Erla"
    ],
    "name:pol_x_preferred":[
        "Erla"
    ],
    "name:por_x_preferred":[
        "Erla"
    ],
    "name:rus_x_preferred":[
        "\u042d\u0440\u043b\u0430"
    ],
    "name:spa_x_preferred":[
        "Erla"
    ],
    "name:swe_x_preferred":[
        "Erla"
    ],
    "name:ukr_x_preferred":[
        "\u0415\u0440\u043b\u0430"
    ],
    "name:uzb_x_preferred":[
        "Erla"
    ],
    "name:vie_x_preferred":[
        "Erla"
    ],
    "name:war_x_preferred":[
        "Erla"
    ],
    "name:zho_x_preferred":[
        "\u4e8c\u814a"
    ],
    "name:zho_x_variant":[
        "\u57c3\u5c14\u62c9"
    ],
    "wof:name":"Erla",
    "wof:placetype":"locality"
},
  "geometry": {"coordinates":[102.051,22.807],"type":"Point"}
}