{
  "type": "Feature",
  "properties": {
    "gn:admin1_code":"32.0",
    "gn:asciiname":"Nuozhami",
    "gn:country_code":"CN",
    "gn:dem":1013,
    "gn:feature_class":"P",
    "gn:feature_code":"PPL",
    "gn:name":"Nuozhami",
    "gn:population":0,
    "gn:timezone":"Asia/Shanghai",
    "iso:country":"CN",
    "name:zho_x_preferred":[
        "\u7cef\u6e23\u5bc6"
    ],
    "wof:name":"Nuozhami",
    "wof:placetype":"locality"
},
  "geometry": {"coordinates":[101.904,26.1889],"type":"Point"}
}