{
  "type": "Feature",
  "properties": {
    "gn:admin1_code":"11.0",
    "gn:asciiname":"Lingzuitou",
    "gn:country_code":"CN",
    "gn:dem":545,
    "gn:feature_class":"P",
    "gn:feature_code":"PPL",
    "gn:name":"Lingzuitou",
    "gn:population":0,
    "gn:timezone":"Asia/Shanghai",
    "iso:country":"CN",
    "name:zho_x_preferred":[
        "\u5cad\u5634\u5934"
    ],
    "wof:name":"Lingzuitou",
    "wof:placetype":"locality"
},
  "geometry": {"coordinates":[109.83259,26.54842],"type":"Point"}
}