{
  "type": "Feature",
  "properties": {
    "gn:admin1_code":"14.0",
    "gn:asciiname":"Langjin",
    "gn:country_code":"CN",
    "gn:dem":4261,
    "gn:feature_class":"P",
    "gn:feature_code":"PPL",
    "gn:name":"Langjin",
    "gn:population":0,
    "gn:timezone":"Asia/Urumqi",
    "iso:country":"CN",
    "name:zho_x_preferred":[
        "\u6717\u91d1"
    ],
    "wof:name":"Langjin",
    "wof:placetype":"locality"
},
  "geometry": {"coordinates":[87.8536,28.6699],"type":"Point"}
}