{
  "type": "Feature",
  "properties": {
    "gn:country":"CN",
    "gn:fcode":"ADM3",
    "gn:population":0,
    "iso:country":"CN",
    "name:und_x_variant":[
        "Ju-y\u00fcan Yao Autonomous Hsien"
    ],
    "name:zho_x_preferred":[
        "\u4e73\u6e90\u7476\u65cf\u81ea\u6cbb\u53bf"
    ],
    "name:zho_x_variant":[
        "\u4e73\u6e90"
    ],
    "qs:name":"Ruyuan Yaozu Zizhixian",
    "qs:photos_9r":0,
    "qs:photos_sr":0,
    "qs:pop_sr":"0",
    "wof:name":"Ruyuan Yaozu Zizhixian",
    "wof:placetype":"localadmin",
    "wof:population":0
},
  "geometry": {"coordinates":[113.18837000000001,24.87853],"type":"Point"}
}