{
  "type": "Feature",
  "properties": {
    "gn:admin1_code":"3.0",
    "gn:asciiname":"Weidu",
    "gn:country_code":"CN",
    "gn:dem":29,
    "gn:feature_class":"P",
    "gn:feature_code":"PPL",
    "gn:name":"Weidu",
    "gn:population":0,
    "gn:timezone":"Asia/Shanghai",
    "iso:country":"CN",
    "name:zho_x_preferred":[
        "\u56f4\u6e21"
    ],
    "wof:name":"Weidu",
    "wof:placetype":"locality"
},
  "geometry": {"coordinates":[117.16800000000001,28.8774],"type":"Point"}
}