{
  "type": "Feature",
  "properties": {
    "gn:admin1_code":"12.0",
    "gn:asciiname":"Sunjiadian",
    "gn:country_code":"CN",
    "gn:dem":34,
    "gn:feature_class":"P",
    "gn:feature_code":"PPL",
    "gn:name":"Sunjiadian",
    "gn:population":0,
    "gn:timezone":"Asia/Shanghai",
    "iso:country":"CN",
    "name:und_x_variant":[
        "\u5b59\u5bb6\u5e97"
    ],
    "wof:name":"Sunjiadian",
    "wof:placetype":"locality"
},
  "geometry": {"coordinates":[114.41974999999999,30.31285],"type":"Point"}
}