{
  "type": "Feature",
  "properties": {
    "gn:admin1_code":"32.0",
    "gn:asciiname":"Mengzizui",
    "gn:country_code":"CN",
    "gn:dem":376,
    "gn:feature_class":"P",
    "gn:feature_code":"PPL",
    "gn:name":"Mengzizui",
    "gn:population":0,
    "gn:timezone":"Asia/Shanghai",
    "iso:country":"CN",
    "name:zho_x_preferred":[
        "\u6aac\u5b50\u5480"
    ],
    "wof:name":"Mengzizui",
    "wof:placetype":"locality"
},
  "geometry": {"coordinates":[105.935,31.4295],"type":"Point"}
}