{
  "type": "Feature",
  "properties": {
    "gn:admin1_code":"9",
    "gn:asciiname":"Banpo",
    "gn:country_code":"CN",
    "gn:dem":392,
    "gn:feature_class":"P",
    "gn:feature_code":"PPL",
    "gn:name":"Banpo",
    "gn:population":0,
    "gn:timezone":"Asia/Shanghai",
    "iso:country":"CN",
    "wof:name":"Banpo",
    "wof:placetype":"locality"
},
  "geometry": {"coordinates":[112.70166999999999,34.37139000000001],"type":"Point"}
}