{
  "type": "Feature",
  "properties": {
    "gn:admin1_code":"18",
    "gn:asciiname":"Dajiaoba",
    "gn:country_code":"CN",
    "gn:dem":1319,
    "gn:feature_class":"P",
    "gn:feature_code":"PPL",
    "gn:name":"Dajiaoba",
    "gn:population":0,
    "gn:timezone":"Asia/Shanghai",
    "iso:country":"CN",
    "name:zho_x_preferred":[
        "\u6253\u811a\u575d"
    ],
    "wof:name":"Dajiaoba",
    "wof:placetype":"locality"
},
  "geometry": {"coordinates":[107.036,28.3988],"type":"Point"}
}