{
  "type": "Feature",
  "properties": {
    "gn:admin1_code":"19.0",
    "gn:asciiname":"Nanzhangkou",
    "gn:country_code":"CN",
    "gn:dem":4,
    "gn:feature_class":"P",
    "gn:feature_code":"PPL",
    "gn:name":"Nanzhangkou",
    "gn:population":0,
    "gn:timezone":"Asia/Shanghai",
    "iso:country":"CN",
    "name:und_x_variant":[
        "\u5357\u6756\u53e3"
    ],
    "name:zho_x_preferred":[
        "\u5357\u6756\u53e3"
    ],
    "wof:name":"Nanzhangkou",
    "wof:placetype":"locality"
},
  "geometry": {"coordinates":[122.40763,41.14054],"type":"Point"}
}