{
  "type": "Feature",
  "properties": {
    "gn:admin1_code":"30.0",
    "gn:asciiname":"Chishuitang",
    "gn:country_code":"CN",
    "gn:dem":13,
    "gn:feature_class":"P",
    "gn:feature_code":"PPL",
    "gn:name":"Chishuitang",
    "gn:population":0,
    "gn:timezone":"Asia/Shanghai",
    "iso:country":"CN",
    "name:zho_x_preferred":[
        "\u8d64\u6c34\u5858"
    ],
    "wof:name":"Chishuitang",
    "wof:placetype":"locality"
},
  "geometry": {"coordinates":[112.62989,22.93943],"type":"Point"}
}