{
  "type": "Feature",
  "properties": {
    "gn:admin1_code":"4.0",
    "gn:asciiname":"Shijiazhuang",
    "gn:country_code":"CN",
    "gn:dem":3,
    "gn:feature_class":"P",
    "gn:feature_code":"PPL",
    "gn:name":"Shijiazhuang",
    "gn:population":0,
    "gn:timezone":"Asia/Shanghai",
    "iso:country":"CN",
    "name:und_x_variant":[
        "\u77f3\u5bb6\u5e84"
    ],
    "wof:name":"Shijiazhuang",
    "wof:placetype":"locality"
},
  "geometry": {"coordinates":[120.94719000000001,32.31196],"type":"Point"}
}