{
  "type": "Feature",
  "properties": {
    "gn:admin1_code":"29.0",
    "gn:asciiname":"Damoqing",
    "gn:country_code":"CN",
    "gn:dem":1855,
    "gn:feature_class":"P",
    "gn:feature_code":"PPL",
    "gn:name":"Damoqing",
    "gn:population":0,
    "gn:timezone":"Asia/Shanghai",
    "iso:country":"CN",
    "name:zho_x_preferred":[
        "\u6253\u78e8\u7b90"
    ],
    "wof:name":"Damoqing",
    "wof:placetype":"locality"
},
  "geometry": {"coordinates":[99.62009999999999,25.2797],"type":"Point"}
}