{
  "type": "Feature",
  "properties": {
    "gn:admin1_code":"32.0",
    "gn:asciiname":"Jianding",
    "gn:country_code":"CN",
    "gn:dem":2987,
    "gn:feature_class":"P",
    "gn:feature_code":"PPL",
    "gn:name":"Jianding",
    "gn:population":0,
    "gn:timezone":"Asia/Shanghai",
    "iso:country":"CN",
    "name:zho_x_preferred":[
        "\u575a\u9876"
    ],
    "wof:name":"Jianding",
    "wof:placetype":"locality"
},
  "geometry": {"coordinates":[99.3249,29.3315],"type":"Point"}
}