{
  "type": "Feature",
  "properties": {
    "gn:admin1_code":"24.0",
    "gn:asciiname":"Zhoujiayaocun",
    "gn:country_code":"CN",
    "gn:dem":500,
    "gn:feature_class":"P",
    "gn:feature_code":"PPL",
    "gn:name":"Zhoujiayaocun",
    "gn:population":0,
    "gn:timezone":"Asia/Shanghai",
    "iso:country":"CN",
    "name:zho_x_preferred":[
        "\u5468\u5bb6\u7a91\u6751"
    ],
    "wof:name":"Zhoujiayaocun",
    "wof:placetype":"locality"
},
  "geometry": {"coordinates":[110.5603,35.13527],"type":"Point"}
}