{
  "type": "Feature",
  "properties": {
    "gn:admin1_code":"18",
    "gn:asciiname":"Xiaoguzeng",
    "gn:country_code":"CN",
    "gn:dem":1015,
    "gn:feature_class":"P",
    "gn:feature_code":"PPL",
    "gn:name":"Xiaoguzeng",
    "gn:population":0,
    "gn:timezone":"Asia/Shanghai",
    "iso:country":"CN",
    "name:zho_x_preferred":[
        "\u5c0f\u8c37\u589e"
    ],
    "wof:name":"Xiaoguzeng",
    "wof:placetype":"locality"
},
  "geometry": {"coordinates":[106.492,26.0289],"type":"Point"}
}