{
  "type": "Feature",
  "properties": {
    "gn:admin1_code":"11",
    "gn:asciiname":"Sanhe",
    "gn:country_code":"CN",
    "gn:dem":543,
    "gn:feature_class":"P",
    "gn:feature_code":"PPL",
    "gn:name":"Sanhe",
    "gn:population":0,
    "gn:timezone":"Asia/Shanghai",
    "iso:country":"CN",
    "name:ceb_x_preferred":[
        "Sanhe"
    ],
    "name:deu_x_preferred":[
        "Sanhe"
    ],
    "name:nor_x_preferred":[
        "Sanhe"
    ],
    "wof:name":"Sanhe",
    "wof:placetype":"locality"
},
  "geometry": {"coordinates":[112.53917,25.49778],"type":"Point"}
}