{
  "type": "Feature",
  "properties": {
    "gn:admin1_code":"1.0",
    "gn:asciiname":"Yulucun",
    "gn:country_code":"CN",
    "gn:dem":35,
    "gn:feature_class":"P",
    "gn:feature_code":"PPL",
    "gn:name":"Yulucun",
    "gn:population":0,
    "gn:timezone":"Asia/Shanghai",
    "iso:country":"CN",
    "name:zho_x_preferred":[
        "\u4e8e\u9646\u6751"
    ],
    "wof:name":"Yulucun",
    "wof:placetype":"locality"
},
  "geometry": {"coordinates":[117.26345000000001,32.72781],"type":"Point"}
}