{
  "type": "Feature",
  "properties": {
    "gn:admin1_code":"24",
    "gn:asciiname":"Shu'erliang",
    "gn:country_code":"CN",
    "gn:dem":1145,
    "gn:feature_class":"P",
    "gn:feature_code":"PPL",
    "gn:name":"Shu\u2019erliang",
    "gn:population":0,
    "gn:timezone":"Asia/Shanghai",
    "iso:country":"CN",
    "name:und_x_variant":[
        "Shu-erh-liang",
        "Shu\u2019erliang"
    ],
    "name:zho_x_preferred":[
        "\u6811\u513f\u6881"
    ],
    "wof:name":"Shu'erliang",
    "wof:placetype":"locality"
},
  "geometry": {"coordinates":[111.34547999999999,39.3674],"type":"Point"}
}