{
  "type": "Feature",
  "properties": {
    "gn:admin1_code":"8.0",
    "gn:asciiname":"Maqingyun",
    "gn:country_code":"CN",
    "gn:dem":155,
    "gn:feature_class":"P",
    "gn:feature_code":"PPL",
    "gn:name":"Maqingyun",
    "gn:population":0,
    "gn:timezone":"Asia/Shanghai",
    "iso:country":"CN",
    "name:zho_x_preferred":[
        "\u9a6c\u6e05\u4e91"
    ],
    "wof:name":"Maqingyun",
    "wof:placetype":"locality"
},
  "geometry": {"coordinates":[125.07071000000001,47.12902],"type":"Point"}
}