{
  "type": "Feature",
  "properties": {
    "gn:admin1_code":"01",
    "gn:asciiname":"Menkoutang",
    "gn:cc2":"CN",
    "gn:country_code":"CN",
    "gn:dem":29,
    "gn:feature_class":"P",
    "gn:feature_code":"PPL",
    "gn:name":"Menkoutang",
    "gn:population":0,
    "gn:timezone":"Asia/Shanghai",
    "iso:country":"CN",
    "name:und_x_variant":[
        "Qiucun",
        "Ch\u2019iu-ts\u2019un",
        "Menkoutang"
    ],
    "wof:name":"Menkoutang",
    "wof:placetype":"locality"
},
  "geometry": {"coordinates":[119.43333,31.01667],"type":"Point"}
}