{
  "type": "Feature",
  "properties": {
    "gn:admin1_code":"4.0",
    "gn:asciiname":"Tanjiazhuang",
    "gn:country_code":"CN",
    "gn:dem":6,
    "gn:feature_class":"P",
    "gn:feature_code":"PPL",
    "gn:name":"Tanjiazhuang",
    "gn:population":0,
    "gn:timezone":"Asia/Shanghai",
    "iso:country":"CN",
    "name:zho_x_preferred":[
        "\u8c08\u5bb6\u5e84"
    ],
    "wof:name":"Tanjiazhuang",
    "wof:placetype":"locality"
},
  "geometry": {"coordinates":[119.498,32.5453],"type":"Point"}
}