{
  "type": "Feature",
  "properties": {
    "gn:admin1_code":"11.0",
    "gn:asciiname":"Madu",
    "gn:country_code":"CN",
    "gn:dem":175,
    "gn:feature_class":"P",
    "gn:feature_code":"PPL",
    "gn:name":"Madu",
    "gn:population":0,
    "gn:timezone":"Asia/Shanghai",
    "iso:country":"CN",
    "name:deu_x_preferred":[
        "Madu"
    ],
    "name:lit_x_preferred":[
        "Madu"
    ],
    "name:slv_x_preferred":[
        "Madu"
    ],
    "name:zho_x_preferred":[
        "\u9a6c\u6e21"
    ],
    "wof:name":"Madu",
    "wof:placetype":"locality"
},
  "geometry": {"coordinates":[113.81524,27.0079],"type":"Point"}
}