{
  "type": "Feature",
  "properties": {
    "gn:admin1_code":"4.0",
    "gn:asciiname":"Bizhuang",
    "gn:country_code":"CN",
    "gn:dem":2,
    "gn:feature_class":"P",
    "gn:feature_code":"PPL",
    "gn:name":"Bizhuang",
    "gn:population":0,
    "gn:timezone":"Asia/Shanghai",
    "iso:country":"CN",
    "name:zho_x_preferred":[
        "\u58c1\u5e84"
    ],
    "wof:name":"Bizhuang",
    "wof:placetype":"locality"
},
  "geometry": {"coordinates":[119.98081999999999,33.44787],"type":"Point"}
}