{
  "type": "Feature",
  "properties": {
    "gn:admin1_code":"18",
    "gn:asciiname":"Taishang",
    "gn:country_code":"CN",
    "gn:dem":902,
    "gn:feature_class":"P",
    "gn:feature_code":"PPL",
    "gn:name":"Taishang",
    "gn:population":0,
    "gn:timezone":"Asia/Shanghai",
    "iso:country":"CN",
    "name:zho_x_preferred":[
        "\u53f0\u4e0a"
    ],
    "name:zho_x_variant":[
        "\u53f0\u7063\u5546\u4eba"
    ],
    "wof:name":"Taishang",
    "wof:placetype":"locality"
},
  "geometry": {"coordinates":[106.801,27.5747],"type":"Point"}
}