{
  "type": "Feature",
  "properties": {
    "gn:admin1_code":"15.0",
    "gn:asciiname":"Muchangshan",
    "gn:country_code":"CN",
    "gn:dem":1478,
    "gn:feature_class":"P",
    "gn:feature_code":"PPL",
    "gn:name":"Muchangshan",
    "gn:population":0,
    "gn:timezone":"Asia/Shanghai",
    "iso:country":"CN",
    "name:und_x_variant":[
        "\u6728\u5382\u5c71"
    ],
    "wof:name":"Muchangshan",
    "wof:placetype":"locality"
},
  "geometry": {"coordinates":[107.50727999999999,36.15769],"type":"Point"}
}