{
  "type": "Feature",
  "properties": {
    "gn:admin1_code":"12.0",
    "gn:asciiname":"Sijiafan",
    "gn:country_code":"CN",
    "gn:dem":483,
    "gn:feature_class":"P",
    "gn:feature_code":"PPL",
    "gn:name":"Sijiafan",
    "gn:population":0,
    "gn:timezone":"Asia/Shanghai",
    "iso:country":"CN",
    "name:zho_x_preferred":[
        "\u53f8\u5bb6\u7548"
    ],
    "wof:name":"Sijiafan",
    "wof:placetype":"locality"
},
  "geometry": {"coordinates":[111.33087999999999,31.13489],"type":"Point"}
}