{
  "type": "Feature",
  "properties": {
    "gn:admin1_code":"19.0",
    "gn:asciiname":"Shangsankeshu",
    "gn:country_code":"CN",
    "gn:dem":154,
    "gn:feature_class":"P",
    "gn:feature_code":"PPL",
    "gn:name":"Shangsankeshu",
    "gn:population":0,
    "gn:timezone":"Asia/Shanghai",
    "iso:country":"CN",
    "name:zho_x_preferred":[
        "\u4e0a\u4e09\u68f5\u6811"
    ],
    "wof:name":"Shangsankeshu",
    "wof:placetype":"locality"
},
  "geometry": {"coordinates":[122.989,42.7171],"type":"Point"}
}