{
  "type": "Feature",
  "properties": {
    "gn:admin1_code":"26.0",
    "gn:asciiname":"Zhangjiahecun",
    "gn:country_code":"CN",
    "gn:dem":1054,
    "gn:feature_class":"P",
    "gn:feature_code":"PPL",
    "gn:name":"Zhangjiahecun",
    "gn:population":0,
    "gn:timezone":"Asia/Shanghai",
    "iso:country":"CN",
    "name:zho_x_preferred":[
        "\u5f20\u5bb6\u6cb3\u6751"
    ],
    "wof:name":"Zhangjiahecun",
    "wof:placetype":"locality"
},
  "geometry": {"coordinates":[109.54940000000001,36.5852],"type":"Point"}
}