{
  "type": "Feature",
  "properties": {
    "gn:admin1_code":"05",
    "gn:asciiname":"Yima",
    "gn:country_code":"CN",
    "gn:dem":346,
    "gn:feature_class":"P",
    "gn:feature_code":"PPL",
    "gn:name":"Yima",
    "gn:population":0,
    "gn:timezone":"Asia/Shanghai",
    "iso:country":"CN",
    "name:ceb_x_preferred":[
        "Yima"
    ],
    "name:deu_x_preferred":[
        "Yima"
    ],
    "name:fra_x_preferred":[
        "Yima"
    ],
    "wof:name":"Yima",
    "wof:placetype":"locality"
},
  "geometry": {"coordinates":[126.25,43.13333],"type":"Point"}
}