{
  "type": "Feature",
  "properties": {
    "gn:admin1_code":"19.0",
    "gn:asciiname":"Dazhonggutun",
    "gn:country_code":"CN",
    "gn:dem":8,
    "gn:feature_class":"P",
    "gn:feature_code":"PPL",
    "gn:name":"Dazhonggutun",
    "gn:population":0,
    "gn:timezone":"Asia/Shanghai",
    "iso:country":"CN",
    "name:zho_x_preferred":[
        "\u5927\u949f\u9f13\u5c6f"
    ],
    "wof:name":"Dazhonggutun",
    "wof:placetype":"locality"
},
  "geometry": {"coordinates":[120.35353000000001,40.27112],"type":"Point"}
}