{
  "type": "Feature",
  "properties": {
    "gn:admin1_code":"8.0",
    "gn:asciiname":"Donggou",
    "gn:country_code":"CN",
    "gn:dem":315,
    "gn:feature_class":"P",
    "gn:feature_code":"PPL",
    "gn:name":"Donggou",
    "gn:population":0,
    "gn:timezone":"Asia/Shanghai",
    "iso:country":"CN",
    "name:zho_x_preferred":[
        "\u4e1c\u6c9f"
    ],
    "wof:name":"Donggou",
    "wof:placetype":"locality"
},
  "geometry": {"coordinates":[129.38246999999998,45.12302],"type":"Point"}
}