{
  "type": "Feature",
  "properties": {
    "gn:admin1_code":"4.0",
    "gn:asciiname":"Fengchetou",
    "gn:country_code":"CN",
    "gn:dem":4,
    "gn:feature_class":"P",
    "gn:feature_code":"PPL",
    "gn:name":"Fengchetou",
    "gn:population":0,
    "gn:timezone":"Asia/Shanghai",
    "iso:country":"CN",
    "name:und_x_variant":[
        "\u98ce\u8f66\u5934"
    ],
    "name:zho_x_preferred":[
        "\u98ce\u8f66\u5934"
    ],
    "wof:name":"Fengchetou",
    "wof:placetype":"locality"
},
  "geometry": {"coordinates":[120.85055,32.08952],"type":"Point"}
}