{
  "type": "Feature",
  "properties": {
    "gn:admin1_code":"9.0",
    "gn:asciiname":"Shangniuzhuang",
    "gn:country_code":"CN",
    "gn:dem":113,
    "gn:feature_class":"P",
    "gn:feature_code":"PPL",
    "gn:name":"Shangniuzhuang",
    "gn:population":0,
    "gn:timezone":"Asia/Shanghai",
    "iso:country":"CN",
    "name:zho_x_preferred":[
        "\u4e0a\u725b\u5e84"
    ],
    "wof:name":"Shangniuzhuang",
    "wof:placetype":"locality"
},
  "geometry": {"coordinates":[113.83718,32.44394],"type":"Point"}
}