{
  "type": "Feature",
  "properties": {
    "gn:admin1_code":"4.0",
    "gn:asciiname":"Dongjiao",
    "gn:country_code":"CN",
    "gn:dem":5,
    "gn:feature_class":"P",
    "gn:feature_code":"PPLA4",
    "gn:name":"Dongjiao",
    "gn:population":0,
    "gn:timezone":"Asia/Shanghai",
    "iso:country":"CN",
    "name:ceb_x_preferred":[
        "Dongjiao"
    ],
    "name:swe_x_preferred":[
        "Dongjiao"
    ],
    "name:und_x_variant":[
        "\u4e1c\u90ca"
    ],
    "wof:name":"Dongjiao",
    "wof:placetype":"locality"
},
  "geometry": {"coordinates":[119.93375,32.50302],"type":"Point"}
}