{
  "type": "Feature",
  "properties": {
    "gn:admin1_code":"11.0",
    "gn:asciiname":"Sitangwan",
    "gn:country_code":"CN",
    "gn:dem":182,
    "gn:feature_class":"P",
    "gn:feature_code":"PPL",
    "gn:name":"Sitangwan",
    "gn:population":0,
    "gn:timezone":"Asia/Shanghai",
    "iso:country":"CN",
    "name:zho_x_preferred":[
        "\u4e1d\u5858\u6e7e"
    ],
    "wof:name":"Sitangwan",
    "wof:placetype":"locality"
},
  "geometry": {"coordinates":[111.71963999999998,26.93941],"type":"Point"}
}