{
  "type": "Feature",
  "properties": {
    "gn:admin1_code":"11",
    "gn:asciiname":"Guidong Chengguanzhen",
    "gn:country_code":"CN",
    "gn:dem":826,
    "gn:feature_class":"P",
    "gn:feature_code":"PPLA3",
    "gn:name":"Guidong Chengguanzhen",
    "gn:population":0,
    "gn:timezone":"Asia/Shanghai",
    "iso:country":"CN",
    "name:und_x_variant":[
        "Kweitung",
        "Kuei-tung-hsien",
        "Kweitung-hsien",
        "Kuei-tung",
        "Guidong",
        "Guidong Chengguanzhen",
        "Guidong Xian"
    ],
    "name:zho_x_preferred":[
        "\u6842\u4e1c\u57ce\u5173\u9547"
    ],
    "name:zho_x_variant":[
        "\u6842\u4e1c\u53bf"
    ],
    "wof:name":"Guidong Chengguanzhen",
    "wof:placetype":"locality"
},
  "geometry": {"coordinates":[113.94062,26.07903],"type":"Point"}
}