{
  "type": "Feature",
  "properties": {
    "gn:admin1_code":"10",
    "gn:asciiname":"Changshengzhuang",
    "gn:country_code":"CN",
    "gn:dem":633,
    "gn:feature_class":"P",
    "gn:feature_code":"PPL",
    "gn:name":"Changshengzhuang",
    "gn:population":0,
    "gn:timezone":"Asia/Shanghai",
    "iso:country":"CN",
    "name:zho_x_preferred":[
        "\u5e38\u80dc\u5e84"
    ],
    "wof:name":"Changshengzhuang",
    "wof:placetype":"locality"
},
  "geometry": {"coordinates":[116.11333999999999,40.68231],"type":"Point"}
}