{
  "type": "Feature",
  "properties": {
    "gn:admin1_code":"26.0",
    "gn:asciiname":"Daxihecun",
    "gn:country_code":"CN",
    "gn:dem":1173,
    "gn:feature_class":"P",
    "gn:feature_code":"PPL",
    "gn:name":"Daxihecun",
    "gn:population":0,
    "gn:timezone":"Asia/Shanghai",
    "iso:country":"CN",
    "name:zho_x_preferred":[
        "\u5927\u897f\u6cb3\u6751"
    ],
    "wof:name":"Daxihecun",
    "wof:placetype":"locality"
},
  "geometry": {"coordinates":[107.11382,32.69861],"type":"Point"}
}