{
  "type": "Feature",
  "properties": {
    "gn:admin1_code":"12.0",
    "gn:asciiname":"Xingjiahe",
    "gn:country_code":"CN",
    "gn:dem":114,
    "gn:feature_class":"P",
    "gn:feature_code":"PPL",
    "gn:name":"Xingjiahe",
    "gn:population":0,
    "gn:timezone":"Asia/Shanghai",
    "iso:country":"CN",
    "name:zho_x_preferred":[
        "\u90a2\u5bb6\u6cb3"
    ],
    "wof:name":"Xingjiahe",
    "wof:placetype":"locality"
},
  "geometry": {"coordinates":[112.76673999999998,31.4943],"type":"Point"}
}