{
  "type": "Feature",
  "properties": {
    "gn:admin1_code":"29",
    "gn:asciiname":"Waita",
    "gn:country_code":"CN",
    "gn:dem":901,
    "gn:feature_class":"P",
    "gn:feature_code":"PPL",
    "gn:name":"Waita",
    "gn:population":0,
    "gn:timezone":"Asia/Shanghai",
    "iso:country":"CN",
    "name:zho_x_preferred":[
        "\u6b6a\u4ed6"
    ],
    "wof:name":"Waita",
    "wof:placetype":"locality"
},
  "geometry": {"coordinates":[104.77200000000001,24.4178],"type":"Point"}
}