{
  "type": "Feature",
  "properties": {
    "gn:admin1_code":"9.0",
    "gn:asciiname":"Chenjiazhuang",
    "gn:country_code":"CN",
    "gn:dem":577,
    "gn:feature_class":"P",
    "gn:feature_code":"PPL",
    "gn:name":"Chenjiazhuang",
    "gn:population":0,
    "gn:timezone":"Asia/Shanghai",
    "iso:country":"CN",
    "name:und_x_variant":[
        "\u9648\u5bb6\u5e84",
        "Chenjiazhuang"
    ],
    "wof:name":"Chenjiazhuang",
    "wof:placetype":"locality"
},
  "geometry": {"coordinates":[112.07637,33.24918],"type":"Point"}
}