{
  "type": "Feature",
  "properties": {
    "gn:admin1_code":"18.0",
    "gn:asciiname":"Dalongjing",
    "gn:country_code":"CN",
    "gn:dem":1321,
    "gn:feature_class":"P",
    "gn:feature_code":"PPL",
    "gn:name":"Dalongjing",
    "gn:population":0,
    "gn:timezone":"Asia/Shanghai",
    "iso:country":"CN",
    "name:zho_x_preferred":[
        "\u5927\u9f99\u4e95"
    ],
    "wof:name":"Dalongjing",
    "wof:placetype":"locality"
},
  "geometry": {"coordinates":[107.414,27.0465],"type":"Point"}
}