{
  "type": "Feature",
  "properties": {
    "gn:admin1_code":"14.0",
    "gn:asciiname":"Ledian",
    "gn:country_code":"CN",
    "gn:dem":5254,
    "gn:feature_class":"P",
    "gn:feature_code":"PPL",
    "gn:name":"Ledian",
    "gn:population":0,
    "gn:timezone":"Asia/Urumqi",
    "iso:country":"CN",
    "name:bod_x_preferred":[
        "Lhaid\u00eang"
    ],
    "name:und_x_variant":[
        "Gapu Gongshe"
    ],
    "name:zho_x_preferred":[
        "\u52d2\u5178"
    ],
    "name:zho_x_variant":[
        "\u560e\u666e\u516c\u793e"
    ],
    "wof:name":"Ledian",
    "wof:placetype":"locality"
},
  "geometry": {"coordinates":[89.101,28.701],"type":"Point"}
}