{
  "type": "Feature",
  "properties": {
    "gn:admin1_code":"26.0",
    "gn:asciiname":"Panzhuangcun",
    "gn:country_code":"CN",
    "gn:dem":413,
    "gn:feature_class":"P",
    "gn:feature_code":"PPL",
    "gn:name":"Panzhuangcun",
    "gn:population":0,
    "gn:timezone":"Asia/Shanghai",
    "iso:country":"CN",
    "name:zho_x_preferred":[
        "\u6f58\u5e84\u6751"
    ],
    "wof:name":"Panzhuangcun",
    "wof:placetype":"locality"
},
  "geometry": {"coordinates":[110.51878000000001,35.55251],"type":"Point"}
}