{
  "type": "Feature",
  "properties": {
    "gn:admin1_code":"12.0",
    "gn:asciiname":"Lengshuiyuan",
    "gn:country_code":"CN",
    "gn:dem":133,
    "gn:feature_class":"P",
    "gn:feature_code":"PPL",
    "gn:name":"Lengshuiyuan",
    "gn:population":0,
    "gn:timezone":"Asia/Shanghai",
    "iso:country":"CN",
    "name:zho_x_preferred":[
        "\u51b7\u6c34\u6c85"
    ],
    "wof:name":"Lengshuiyuan",
    "wof:placetype":"locality"
},
  "geometry": {"coordinates":[113.89675,29.24091],"type":"Point"}
}