{
  "type": "Feature",
  "properties": {
    "gn:admin1_code":"3.0",
    "gn:asciiname":"Xinzhou",
    "gn:country_code":"CN",
    "gn:dem":14,
    "gn:feature_class":"P",
    "gn:feature_code":"PPL",
    "gn:name":"Xinzhou",
    "gn:population":0,
    "gn:timezone":"Asia/Shanghai",
    "iso:country":"CN",
    "name:ara_x_preferred":[
        "\u0634\u064a\u0646\u062a\u0634\u0648"
    ],
    "name:bel_x_preferred":[
        "\u0421\u0456\u043d\u044c\u0434\u0436\u043e\u045e"
    ],
    "name:cdo_x_preferred":[
        "H\u1e73\u0306ng-ci\u016d"
    ],
    "name:ceb_x_preferred":[
        "Xinzhou"
    ],
    "name:ces_x_preferred":[
        "Sin-\u010dou"
    ],
    "name:dan_x_preferred":[
        "Xinzhou"
    ],
    "name:deu_x_preferred":[
        "Xinzhou"
    ],
    "name:eus_x_preferred":[
        "Xinzhou"
    ],
    "name:fas_x_preferred":[
        "\u0634\u06cc\u0646\u062c\u0648"
    ],
    "name:fin_x_preferred":[
        "Xinzhou"
    ],
    "name:fra_x_preferred":[
        "Xinzhou"
    ],
    "name:ita_x_preferred":[
        "Xinzhou"
    ],
    "name:jpn_x_preferred":[
        "\u5ffb\u5dde\u5e02"
    ],
    "name:kik_x_preferred":[
        "Xinzhou"
    ],
    "name:kor_x_preferred":[
        "\uc2e0\uc800\uc6b0\uc2dc"
    ],
    "name:mlg_x_preferred":[
        "Xinzhou"
    ],
    "name:nld_x_preferred":[
        "Xinzhou"
    ],
    "name:nno_x_preferred":[
        "Xinzhou"
    ],
    "name:nor_x_preferred":[
        "Xinzhou"
    ],
    "name:pol_x_preferred":[
        "Xinzhou"
    ],
    "name:rus_x_preferred":[
        "\u0421\u0438\u043d\u044c\u0447\u0436\u043e\u0443"
    ],
    "name:spa_x_preferred":[
        "Xinzh\u00f3u"
    ],
    "name:swe_x_preferred":[
        "Xinzhou"
    ],
    "name:tur_x_preferred":[
        "Xinzhou"
    ],
    "name:ukr_x_preferred":[
        "\u0421\u0456\u043d\u044c\u0447\u0436\u043e\u0443"
    ],
    "name:und_x_variant":[
        "\u65b0\u6d32"
    ],
    "name:urd_x_preferred":[
        "\u0634\u0646\u0698\u0648\u0648"
    ],
    "name:vie_x_preferred":[
        "H\u00e3n Ch\u00e2u"
    ],
    "name:war_x_preferred":[
        "Xinzhou"
    ],
    "name:wuu_x_preferred":[
        "\u5ffb\u5dde\u5e02"
    ],
    "name:zho_x_preferred":[
        "\u5ffb\u5dde\u5e02"
    ],
    "wof:name":"Xinzhou",
    "wof:placetype":"locality"
},
  "geometry": {"coordinates":[116.02108,29.0458],"type":"Point"}
}