{
  "type": "Feature",
  "properties": {
    "gn:admin1_code":"29.0",
    "gn:asciiname":"Shaba",
    "gn:country_code":"CN",
    "gn:dem":1878,
    "gn:feature_class":"P",
    "gn:feature_code":"PPL",
    "gn:name":"Shaba",
    "gn:population":0,
    "gn:timezone":"Asia/Shanghai",
    "iso:country":"CN",
    "name:bar_x_preferred":[
        "Shaba"
    ],
    "name:ceb_x_preferred":[
        "Shaba"
    ],
    "name:deu_x_preferred":[
        "Shaba"
    ],
    "name:ita_x_preferred":[
        "Shaba"
    ],
    "name:swe_x_preferred":[
        "Shaba"
    ],
    "name:zho_x_preferred":[
        "\u6c99\u575d"
    ],
    "wof:name":"Shaba",
    "wof:placetype":"locality"
},
  "geometry": {"coordinates":[99.23439999999999,25.6354],"type":"Point"}
}