{
  "type": "Feature",
  "properties": {
    "gn:admin1_code":"14.0",
    "gn:asciiname":"Duojitangcun",
    "gn:country_code":"CN",
    "gn:dem":4151,
    "gn:feature_class":"P",
    "gn:feature_code":"PPL",
    "gn:name":"Duojitangcun",
    "gn:population":0,
    "gn:timezone":"Asia/Urumqi",
    "iso:country":"CN",
    "name:zho_x_preferred":[
        "\u591a\u5409\u5858\u6751"
    ],
    "wof:name":"Duojitangcun",
    "wof:placetype":"locality"
},
  "geometry": {"coordinates":[93.4738,32.09773],"type":"Point"}
}