{
  "type": "Feature",
  "properties": {
    "gn:admin1_code":"4.0",
    "gn:asciiname":"Congliucun",
    "gn:country_code":"CN",
    "gn:dem":4,
    "gn:feature_class":"P",
    "gn:feature_code":"PPL",
    "gn:name":"Congliucun",
    "gn:population":0,
    "gn:timezone":"Asia/Shanghai",
    "iso:country":"CN",
    "name:zho_x_preferred":[
        "\u4ece\u516d\u6751"
    ],
    "wof:name":"Congliucun",
    "wof:placetype":"locality"
},
  "geometry": {"coordinates":[120.03918,32.90022],"type":"Point"}
}