{
  "type": "Feature",
  "properties": {
    "gn:admin1_code":"16.0",
    "gn:asciiname":"Lulin",
    "gn:country_code":"CN",
    "gn:dem":572,
    "gn:feature_class":"P",
    "gn:feature_code":"PPL",
    "gn:name":"Lulin",
    "gn:population":0,
    "gn:timezone":"Asia/Shanghai",
    "iso:country":"CN",
    "name:deu_x_preferred":[
        "L\u00fclin"
    ],
    "name:jpn_x_preferred":[
        "\u7dd1\u6797\u8ecd"
    ],
    "name:kor_x_preferred":[
        "\ub179\ub9bc\uad70"
    ],
    "name:wuu_x_preferred":[
        "\u7eff\u6797\u519b"
    ],
    "name:zho_x_preferred":[
        "\u6e0c\u541d"
    ],
    "name:zho_x_variant":[
        "\u7eff\u6797\u519b"
    ],
    "wof:name":"Lulin",
    "wof:placetype":"locality"
},
  "geometry": {"coordinates":[106.84399999999999,23.3839],"type":"Point"}
}