{
  "type": "Feature",
  "properties": {
    "gn:admin1_code":"16",
    "gn:asciiname":"Jiangjunshan",
    "gn:country_code":"CN",
    "gn:dem":463,
    "gn:feature_class":"P",
    "gn:feature_code":"PPL",
    "gn:name":"Jiangjunshan",
    "gn:population":0,
    "gn:timezone":"Asia/Shanghai",
    "iso:country":"CN",
    "name:zho_x_preferred":[
        "\u5c06\u519b\u5c71"
    ],
    "wof:name":"Jiangjunshan",
    "wof:placetype":"locality"
},
  "geometry": {"coordinates":[110.944,26.0764],"type":"Point"}
}