{
  "type": "Feature",
  "properties": {
    "gn:admin1_code":"32.0",
    "gn:asciiname":"Chongdaipu",
    "gn:country_code":"CN",
    "gn:dem":367,
    "gn:feature_class":"P",
    "gn:feature_code":"PPL",
    "gn:name":"Chongdaipu",
    "gn:population":0,
    "gn:timezone":"Asia/Shanghai",
    "iso:country":"CN",
    "name:zho_x_preferred":[
        "\u91cd\u5e26\u94fa"
    ],
    "wof:name":"Chongdaipu",
    "wof:placetype":"locality"
},
  "geometry": {"coordinates":[104.82435,29.88521],"type":"Point"}
}