{
  "type": "Feature",
  "properties": {
    "gn:admin1_code":"22.0",
    "gn:asciiname":"Yaoqiaoyucun",
    "gn:country_code":"CN",
    "gn:dem":431,
    "gn:feature_class":"P",
    "gn:feature_code":"PPL",
    "gn:name":"Yaoqiaoyucun",
    "gn:population":0,
    "gn:timezone":"Asia/Shanghai",
    "iso:country":"CN",
    "name:zho_x_preferred":[
        "\u9065\u6865\u5cea\u6751"
    ],
    "wof:name":"Yaoqiaoyucun",
    "wof:placetype":"locality"
},
  "geometry": {"coordinates":[117.37406,40.63372],"type":"Point"}
}