{
  "type": "Feature",
  "properties": {
    "gn:admin1_code":"15.0",
    "gn:asciiname":"Sanhuanggou",
    "gn:country_code":"CN",
    "gn:dem":1517,
    "gn:feature_class":"P",
    "gn:feature_code":"PPL",
    "gn:name":"Sanhuanggou",
    "gn:population":0,
    "gn:timezone":"Asia/Shanghai",
    "iso:country":"CN",
    "name:und_x_variant":[
        "\u4e09\u7687\u6c9f"
    ],
    "wof:name":"Sanhuanggou",
    "wof:placetype":"locality"
},
  "geometry": {"coordinates":[105.75678000000001,34.03094],"type":"Point"}
}