{
  "type": "Feature",
  "properties": {
    "gn:admin1_code":"2",
    "gn:asciiname":"Jinsanjiao",
    "gn:country_code":"CN",
    "gn:dem":9,
    "gn:feature_class":"P",
    "gn:feature_code":"PPLA4",
    "gn:name":"Jinsanjiao",
    "gn:population":0,
    "gn:timezone":"Asia/Shanghai",
    "iso:country":"CN",
    "name:und_x_variant":[
        "Fuquan Zhen",
        "Fuquan",
        "Jinsanjiao"
    ],
    "name:zho_x_preferred":[
        "\u798f\u5168\u9547"
    ],
    "name:zho_x_variant":[
        "\u91d1\u4e09\u89d2"
    ],
    "wof:name":"Jinsanjiao",
    "wof:placetype":"locality"
},
  "geometry": {"coordinates":[120.52715999999999,29.98938],"type":"Point"}
}