{
  "type": "Feature",
  "properties": {
    "gn:admin1_code":"4.0",
    "gn:asciiname":"Qigancun",
    "gn:country_code":"CN",
    "gn:dem":23,
    "gn:feature_class":"P",
    "gn:feature_code":"PPL",
    "gn:name":"Qigancun",
    "gn:population":0,
    "gn:timezone":"Asia/Shanghai",
    "iso:country":"CN",
    "name:zho_x_preferred":[
        "\u68cb\u6746\u6751"
    ],
    "wof:name":"Qigancun",
    "wof:placetype":"locality"
},
  "geometry": {"coordinates":[118.11829,33.77368],"type":"Point"}
}