{
  "type": "Feature",
  "properties": {
    "gn:admin1_code":"29.0",
    "gn:asciiname":"Dalong",
    "gn:country_code":"CN",
    "gn:dem":1309,
    "gn:feature_class":"P",
    "gn:feature_code":"PPL",
    "gn:name":"Dalong",
    "gn:population":0,
    "gn:timezone":"Asia/Shanghai",
    "iso:country":"CN",
    "name:zho_x_preferred":[
        "\u6253\u62e2"
    ],
    "wof:name":"Dalong",
    "wof:placetype":"locality"
},
  "geometry": {"coordinates":[99.0943,23.8037],"type":"Point"}
}