{
  "type": "Feature",
  "properties": {
    "gn:admin1_code":"30.0",
    "gn:asciiname":"Yanlingshan",
    "gn:country_code":"CN",
    "gn:dem":543,
    "gn:feature_class":"P",
    "gn:feature_code":"PPL",
    "gn:name":"Yanlingshan",
    "gn:population":0,
    "gn:timezone":"Asia/Shanghai",
    "iso:country":"CN",
    "name:zho_x_preferred":[
        "\u4e25\u5cad\u5c71"
    ],
    "wof:name":"Yanlingshan",
    "wof:placetype":"locality"
},
  "geometry": {"coordinates":[112.03937000000001,23.77969],"type":"Point"}
}