{
  "type": "Feature",
  "properties": {
    "gn:admin1_code":"3.0",
    "gn:asciiname":"Zhujiabei",
    "gn:country_code":"CN",
    "gn:dem":160,
    "gn:feature_class":"P",
    "gn:feature_code":"PPL",
    "gn:name":"Zhujiabei",
    "gn:population":0,
    "gn:timezone":"Asia/Shanghai",
    "iso:country":"CN",
    "name:und_x_variant":[
        "\u7af9\u5bb6\u9642"
    ],
    "wof:name":"Zhujiabei",
    "wof:placetype":"locality"
},
  "geometry": {"coordinates":[116.25223,26.81153],"type":"Point"}
}