{
  "type": "Feature",
  "properties": {
    "gn:admin1_code":"32.0",
    "gn:asciiname":"Sila'erdi",
    "gn:country_code":"CN",
    "gn:dem":3208,
    "gn:feature_class":"P",
    "gn:feature_code":"PPL",
    "gn:name":"Sila\u2019erdi",
    "gn:population":0,
    "gn:timezone":"Asia/Shanghai",
    "iso:country":"CN",
    "name:und_x_variant":[
        "Sila\u2019erdi"
    ],
    "name:zho_x_preferred":[
        "\u65af\u62c9\u5c14\u5e95"
    ],
    "wof:name":"Sila'erdi",
    "wof:placetype":"locality"
},
  "geometry": {"coordinates":[101.89700000000001,32.251],"type":"Point"}
}