{
  "type": "Feature",
  "properties": {
    "gn:admin1_code":"8.0",
    "gn:asciiname":"Chenglicun",
    "gn:country_code":"CN",
    "gn:dem":161,
    "gn:feature_class":"P",
    "gn:feature_code":"PPL",
    "gn:name":"Chenglicun",
    "gn:population":0,
    "gn:timezone":"Asia/Shanghai",
    "iso:country":"CN",
    "name:zho_x_preferred":[
        "\u8bda\u5229\u6751"
    ],
    "wof:name":"Chenglicun",
    "wof:placetype":"locality"
},
  "geometry": {"coordinates":[126.32098999999999,45.28841],"type":"Point"}
}