{
  "type": "Feature",
  "properties": {
    "gn:admin1_code":"32.0",
    "gn:asciiname":"Zhadu",
    "gn:country_code":"CN",
    "gn:dem":2559,
    "gn:feature_class":"P",
    "gn:feature_code":"PPL",
    "gn:name":"Zhadu",
    "gn:population":0,
    "gn:timezone":"Asia/Shanghai",
    "iso:country":"CN",
    "name:zho_x_preferred":[
        "\u624e\u90fd"
    ],
    "wof:name":"Zhadu",
    "wof:placetype":"locality"
},
  "geometry": {"coordinates":[102.35599999999999,28.0583],"type":"Point"}
}