{
  "type": "Feature",
  "properties": {
    "gn:admin1_code":"16",
    "gn:asciiname":"Shanggongjia",
    "gn:country_code":"CN",
    "gn:dem":432,
    "gn:feature_class":"P",
    "gn:feature_code":"PPL",
    "gn:name":"Shanggongjia",
    "gn:population":0,
    "gn:timezone":"Asia/Shanghai",
    "iso:country":"CN",
    "name:zho_x_preferred":[
        "\u4e0a\u9f9a\u5bb6"
    ],
    "wof:name":"Shanggongjia",
    "wof:placetype":"locality"
},
  "geometry": {"coordinates":[109.735,25.8112],"type":"Point"}
}