{
  "type": "Feature",
  "properties": {
    "gn:admin1_code":"12.0",
    "gn:asciiname":"Huanglongling",
    "gn:country_code":"CN",
    "gn:dem":25,
    "gn:feature_class":"P",
    "gn:feature_code":"PPL",
    "gn:name":"Huanglongling",
    "gn:population":0,
    "gn:timezone":"Asia/Shanghai",
    "iso:country":"CN",
    "name:zho_x_preferred":[
        "\u9ec4\u9f99\u5cad"
    ],
    "wof:name":"Huanglongling",
    "wof:placetype":"locality"
},
  "geometry": {"coordinates":[113.11673999999999,29.67745],"type":"Point"}
}