{
  "type": "Feature",
  "properties": {
    "gn:admin1_code":"1.0",
    "gn:asciiname":"Huangbaishan",
    "gn:country_code":"CN",
    "gn:dem":534,
    "gn:feature_class":"P",
    "gn:feature_code":"PPL",
    "gn:name":"Huangbaishan",
    "gn:population":0,
    "gn:timezone":"Asia/Shanghai",
    "iso:country":"CN",
    "name:zho_x_preferred":[
        "\u9ec4\u67cf\u5c71"
    ],
    "wof:name":"Huangbaishan",
    "wof:placetype":"locality"
},
  "geometry": {"coordinates":[118.35223000000001,30.10124],"type":"Point"}
}