{
  "type": "Feature",
  "properties": {
    "gn:admin1_code":"11",
    "gn:asciiname":"Jiqing",
    "gn:cc2":"CN",
    "gn:country_code":"CN",
    "gn:dem":472,
    "gn:feature_class":"P",
    "gn:feature_code":"PPL",
    "gn:name":"Jiqing",
    "gn:population":0,
    "gn:timezone":"Asia/Shanghai",
    "iso:country":"CN",
    "name:und_x_variant":[
        "Chi-ch\u2019ing",
        "Jijiaoyan",
        "Jiqing"
    ],
    "wof:name":"Jiqing",
    "wof:placetype":"locality"
},
  "geometry": {"coordinates":[111.42889,27.955],"type":"Point"}
}