{
  "type": "Feature",
  "properties": {
    "gn:admin1_code":"29.0",
    "gn:asciiname":"Xixi",
    "gn:country_code":"CN",
    "gn:dem":2333,
    "gn:feature_class":"P",
    "gn:feature_code":"PPL",
    "gn:name":"Xixi",
    "gn:population":0,
    "gn:timezone":"Asia/Shanghai",
    "iso:country":"CN",
    "name:ceb_x_preferred":[
        "Xixi"
    ],
    "name:deu_x_preferred":[
        "Xixi"
    ],
    "name:swe_x_preferred":[
        "Xixi"
    ],
    "name:zho_x_preferred":[
        "\u7ec6\u5e2d"
    ],
    "wof:name":"Xixi",
    "wof:placetype":"locality"
},
  "geometry": {"coordinates":[99.5806,25.6358],"type":"Point"}
}