{
  "type": "Feature",
  "properties": {
    "gn:admin1_code":"4.0",
    "gn:asciiname":"Sidangcun",
    "gn:country_code":"CN",
    "gn:dem":6,
    "gn:feature_class":"P",
    "gn:feature_code":"PPL",
    "gn:name":"Sidangcun",
    "gn:population":0,
    "gn:timezone":"Asia/Shanghai",
    "iso:country":"CN",
    "name:und_x_variant":[
        "\u6cd7\u8361\u6751"
    ],
    "name:zho_x_preferred":[
        "\u6cd7\u8361\u6751"
    ],
    "wof:name":"Sidangcun",
    "wof:placetype":"locality"
},
  "geometry": {"coordinates":[120.62485,31.48122],"type":"Point"}
}