{
  "type": "Feature",
  "properties": {
    "gn:admin1_code":"19.0",
    "gn:asciiname":"Gongjia Gouli",
    "gn:country_code":"CN",
    "gn:dem":243,
    "gn:feature_class":"P",
    "gn:feature_code":"PPL",
    "gn:name":"Gongjia Gouli",
    "gn:population":0,
    "gn:timezone":"Asia/Shanghai",
    "iso:country":"CN",
    "name:zho_x_preferred":[
        "\u5f13\u5bb6\u6c9f\u91cc"
    ],
    "wof:name":"Gongjia Gouli",
    "wof:placetype":"locality"
},
  "geometry": {"coordinates":[119.881,40.7109],"type":"Point"}
}