{
  "type": "Feature",
  "properties": {
    "gn:admin1_code":"12.0",
    "gn:asciiname":"Luozhi Liucun",
    "gn:country_code":"CN",
    "gn:dem":137,
    "gn:feature_class":"P",
    "gn:feature_code":"PPL",
    "gn:name":"Luozhi Liucun",
    "gn:population":0,
    "gn:timezone":"Asia/Shanghai",
    "iso:country":"CN",
    "name:zho_x_preferred":[
        "\u7f57\u5fd7\u516d\u6751"
    ],
    "wof:name":"Luozhi Liucun",
    "wof:placetype":"locality"
},
  "geometry": {"coordinates":[115.07953999999999,30.00302000000001],"type":"Point"}
}