{
  "type": "Feature",
  "properties": {
    "gn:admin1_code":"32.0",
    "gn:asciiname":"Huilong",
    "gn:country_code":"CN",
    "gn:dem":489,
    "gn:feature_class":"P",
    "gn:feature_code":"PPL",
    "gn:name":"Huilong",
    "gn:population":0,
    "gn:timezone":"Asia/Shanghai",
    "iso:country":"CN",
    "name:ceb_x_preferred":[
        "Huilong"
    ],
    "name:deu_x_preferred":[
        "Huilong"
    ],
    "name:swe_x_preferred":[
        "Huilong"
    ],
    "name:zho_x_preferred":[
        "\u56de\u9f99"
    ],
    "wof:name":"Huilong",
    "wof:placetype":"locality"
},
  "geometry": {"coordinates":[103.611,30.4627],"type":"Point"}
}