{
  "type": "Feature",
  "properties": {
    "gn:admin1_code":"10",
    "gn:asciiname":"Datucheng",
    "gn:country_code":"CN",
    "gn:dem":1336,
    "gn:feature_class":"P",
    "gn:feature_code":"PPL",
    "gn:name":"Datucheng",
    "gn:population":0,
    "gn:timezone":"Asia/Shanghai",
    "iso:country":"CN",
    "name:zho_x_preferred":[
        "\u5927\u571f\u57ce"
    ],
    "wof:name":"Datucheng",
    "wof:placetype":"locality"
},
  "geometry": {"coordinates":[114.42307,41.28568],"type":"Point"}
}