{
  "type": "Feature",
  "properties": {
    "gn:admin1_code":"5.0",
    "gn:asciiname":"Sidaopaocun",
    "gn:country_code":"CN",
    "gn:dem":19,
    "gn:feature_class":"P",
    "gn:feature_code":"PPL",
    "gn:name":"Sidaopaocun",
    "gn:population":0,
    "gn:timezone":"Asia/Shanghai",
    "iso:country":"CN",
    "name:und_x_variant":[
        "\u56db\u9053\u6ce1\u6751"
    ],
    "wof:name":"Sidaopaocun",
    "wof:placetype":"locality"
},
  "geometry": {"coordinates":[130.53481000000002,42.65122],"type":"Point"}
}