{
  "type": "Feature",
  "properties": {
    "gn:admin1_code":"16.0",
    "gn:asciiname":"Huangxuan",
    "gn:country_code":"CN",
    "gn:dem":159,
    "gn:feature_class":"P",
    "gn:feature_code":"PPL",
    "gn:name":"Huangxuan",
    "gn:population":0,
    "gn:timezone":"Asia/Shanghai",
    "iso:country":"CN",
    "name:zho_x_preferred":[
        "\u9ec4\u5ba3"
    ],
    "wof:name":"Huangxuan",
    "wof:placetype":"locality"
},
  "geometry": {"coordinates":[108.69799999999999,23.0389],"type":"Point"}
}