{
  "type": "Feature",
  "properties": {
    "gn:admin1_code":"2.0",
    "gn:asciiname":"Shanshangfang",
    "gn:country_code":"CN",
    "gn:dem":51,
    "gn:feature_class":"P",
    "gn:feature_code":"PPL",
    "gn:name":"Shanshangfang",
    "gn:population":0,
    "gn:timezone":"Asia/Shanghai",
    "iso:country":"CN",
    "name:und_x_variant":[
        "\u5c71\u4e0a\u65b9"
    ],
    "wof:name":"Shanshangfang",
    "wof:placetype":"locality"
},
  "geometry": {"coordinates":[119.89461,30.43453],"type":"Point"}
}