{
  "type": "Feature",
  "properties": {
    "gn:admin1_code":"11.0",
    "gn:asciiname":"Huahaitang",
    "gn:country_code":"CN",
    "gn:dem":74,
    "gn:feature_class":"P",
    "gn:feature_code":"PPL",
    "gn:name":"Huahaitang",
    "gn:population":0,
    "gn:timezone":"Asia/Shanghai",
    "iso:country":"CN",
    "name:zho_x_preferred":[
        "\u82b1\u6d77\u5858"
    ],
    "wof:name":"Huahaitang",
    "wof:placetype":"locality"
},
  "geometry": {"coordinates":[112.76097,28.19767],"type":"Point"}
}