{
  "type": "Feature",
  "properties": {
    "gn:admin1_code":"19.0",
    "gn:asciiname":"Panlong Nangou",
    "gn:country_code":"CN",
    "gn:dem":198,
    "gn:feature_class":"P",
    "gn:feature_code":"PPL",
    "gn:name":"Panlong Nangou",
    "gn:population":0,
    "gn:timezone":"Asia/Shanghai",
    "iso:country":"CN",
    "name:zho_x_preferred":[
        "\u76d8\u9f99\u5357\u6c9f"
    ],
    "wof:name":"Panlong Nangou",
    "wof:placetype":"locality"
},
  "geometry": {"coordinates":[119.88,40.3135],"type":"Point"}
}