{
  "type": "Feature",
  "properties": {
    "gn:admin1_code":"1.0",
    "gn:asciiname":"Yanyangcun",
    "gn:country_code":"CN",
    "gn:dem":22,
    "gn:feature_class":"P",
    "gn:feature_code":"PPL",
    "gn:name":"Yanyangcun",
    "gn:population":0,
    "gn:timezone":"Asia/Shanghai",
    "iso:country":"CN",
    "name:zho_x_preferred":[
        "\u8273\u9633\u6751"
    ],
    "wof:name":"Yanyangcun",
    "wof:placetype":"locality"
},
  "geometry": {"coordinates":[117.57689999999999,33.4743],"type":"Point"}
}