{
  "type": "Feature",
  "properties": {
    "gn:admin1_code":"32.0",
    "gn:asciiname":"Xuzi",
    "gn:country_code":"CN",
    "gn:dem":2243,
    "gn:feature_class":"P",
    "gn:feature_code":"PPL",
    "gn:name":"Xuzi",
    "gn:population":0,
    "gn:timezone":"Asia/Shanghai",
    "iso:country":"CN",
    "name:zho_x_preferred":[
        "\u8bb8\u5b50"
    ],
    "wof:name":"Xuzi",
    "wof:placetype":"locality"
},
  "geometry": {"coordinates":[102.041,28.3587],"type":"Point"}
}