{
  "type": "Feature",
  "properties": {
    "gn:admin1_code":"31",
    "gn:asciiname":"Fulong",
    "gn:country_code":"CN",
    "gn:dem":262,
    "gn:feature_class":"P",
    "gn:feature_code":"PPLA4",
    "gn:name":"Fulong",
    "gn:population":0,
    "gn:timezone":"Asia/Shanghai",
    "iso:country":"CN",
    "name:und_x_variant":[
        "\u961c\u9f99",
        "Fulong Xiang",
        "\u961c\u9f99\u4e61"
    ],
    "wof:name":"Fulong",
    "wof:placetype":"locality"
},
  "geometry": {"coordinates":[109.45534000000001,19.32387],"type":"Point"}
}