{
  "type": "Feature",
  "properties": {
    "gn:admin1_code":"4.0",
    "gn:asciiname":"Hejiadai",
    "gn:country_code":"CN",
    "gn:dem":2,
    "gn:feature_class":"P",
    "gn:feature_code":"PPL",
    "gn:name":"Hejiadai",
    "gn:population":0,
    "gn:timezone":"Asia/Shanghai",
    "iso:country":"CN",
    "name:zho_x_preferred":[
        "\u4f55\u5bb6\u5788"
    ],
    "wof:name":"Hejiadai",
    "wof:placetype":"locality"
},
  "geometry": {"coordinates":[120.28830000000001,32.09235],"type":"Point"}
}