{
  "type": "Feature",
  "properties": {
    "gn:admin1_code":"26.0",
    "gn:asciiname":"Jizhai",
    "gn:country_code":"CN",
    "gn:dem":529,
    "gn:feature_class":"P",
    "gn:feature_code":"PPL",
    "gn:name":"Jizhai",
    "gn:population":0,
    "gn:timezone":"Asia/Shanghai",
    "iso:country":"CN",
    "name:und_x_variant":[
        "\u7eaa\u5be8"
    ],
    "wof:name":"Jizhai",
    "wof:placetype":"locality"
},
  "geometry": {"coordinates":[106.86233,33.16271],"type":"Point"}
}