{
  "type": "Feature",
  "properties": {
    "gn:admin1_code":"5.0",
    "gn:asciiname":"Qianxiang Yuefang",
    "gn:country_code":"CN",
    "gn:dem":195,
    "gn:feature_class":"P",
    "gn:feature_code":"PPL",
    "gn:name":"Qianxiang Yuefang",
    "gn:population":0,
    "gn:timezone":"Asia/Shanghai",
    "iso:country":"CN",
    "name:zho_x_preferred":[
        "\u524d\u4e61\u7ea6\u623f"
    ],
    "wof:name":"Qianxiang Yuefang",
    "wof:placetype":"locality"
},
  "geometry": {"coordinates":[124.79313,44.14123],"type":"Point"}
}