{
  "type": "Feature",
  "properties": {
    "gn:admin1_code":"30.0",
    "gn:asciiname":"Fozidong",
    "gn:country_code":"CN",
    "gn:dem":193,
    "gn:feature_class":"P",
    "gn:feature_code":"PPL",
    "gn:name":"Fozidong",
    "gn:population":0,
    "gn:timezone":"Asia/Shanghai",
    "iso:country":"CN",
    "name:zho_x_preferred":[
        "\u4f5b\u5b50\u578c"
    ],
    "wof:name":"Fozidong",
    "wof:placetype":"locality"
},
  "geometry": {"coordinates":[111.35091,22.67723],"type":"Point"}
}