{
  "type": "Feature",
  "properties": {
    "gn:admin1_code":"16.0",
    "gn:asciiname":"Baibu",
    "gn:country_code":"CN",
    "gn:dem":832,
    "gn:feature_class":"P",
    "gn:feature_code":"PPL",
    "gn:name":"Baibu",
    "gn:population":0,
    "gn:timezone":"Asia/Shanghai",
    "iso:country":"CN",
    "name:zho_x_preferred":[
        "\u767e\u5e03"
    ],
    "wof:name":"Baibu",
    "wof:placetype":"locality"
},
  "geometry": {"coordinates":[106.19199999999999,23.0611],"type":"Point"}
}