{
  "type": "Feature",
  "properties": {
    "gn:admin1_code":"19.0",
    "gn:asciiname":"Leijiagou",
    "gn:country_code":"CN",
    "gn:dem":32,
    "gn:feature_class":"P",
    "gn:feature_code":"PPL",
    "gn:name":"Leijiagou",
    "gn:population":0,
    "gn:timezone":"Asia/Shanghai",
    "iso:country":"CN",
    "name:und_x_variant":[
        "\u96f7\u5bb6\u6c9f"
    ],
    "name:zho_x_preferred":[
        "\u96f7\u5bb6\u6c9f"
    ],
    "wof:name":"Leijiagou",
    "wof:placetype":"locality"
},
  "geometry": {"coordinates":[121.197,41.0359],"type":"Point"}
}