{
  "type": "Feature",
  "properties": {
    "gn:admin1_code":"7.0",
    "gn:asciiname":"Shanchakeng",
    "gn:country_code":"CN",
    "gn:dem":738,
    "gn:feature_class":"P",
    "gn:feature_code":"PPL",
    "gn:name":"Shanchakeng",
    "gn:population":0,
    "gn:timezone":"Asia/Shanghai",
    "iso:country":"CN",
    "name:zho_x_preferred":[
        "\u5c71\u8336\u5751"
    ],
    "wof:name":"Shanchakeng",
    "wof:placetype":"locality"
},
  "geometry": {"coordinates":[117.58946,26.42086],"type":"Point"}
}