{
  "type": "Feature",
  "properties": {
    "gn:admin1_code":"29.0",
    "gn:asciiname":"Jieman",
    "gn:country_code":"CN",
    "gn:dem":838,
    "gn:feature_class":"P",
    "gn:feature_code":"PPL",
    "gn:name":"Jieman",
    "gn:population":0,
    "gn:timezone":"Asia/Shanghai",
    "iso:country":"CN",
    "name:zho_x_preferred":[
        "\u59d0\u6ee1"
    ],
    "wof:name":"Jieman",
    "wof:placetype":"locality"
},
  "geometry": {"coordinates":[97.9842,24.7038],"type":"Point"}
}