{
  "type": "Feature",
  "properties": {
    "gn:admin1_code":"29",
    "gn:asciiname":"Tachong",
    "gn:country_code":"CN",
    "gn:dem":2024,
    "gn:feature_class":"P",
    "gn:feature_code":"PPL",
    "gn:name":"Tachong",
    "gn:population":0,
    "gn:timezone":"Asia/Shanghai",
    "iso:country":"CN",
    "name:zho_x_preferred":[
        "\u5854\u51b2"
    ],
    "wof:name":"Tachong",
    "wof:placetype":"locality"
},
  "geometry": {"coordinates":[102.111,24.3196],"type":"Point"}
}