{
  "type": "Feature",
  "properties": {
    "gn:admin1_code":"12.0",
    "gn:asciiname":"Hongqi Dadui",
    "gn:country_code":"CN",
    "gn:dem":50,
    "gn:feature_class":"P",
    "gn:feature_code":"PPLF",
    "gn:name":"Hongqi Dadui",
    "gn:population":0,
    "gn:timezone":"Asia/Shanghai",
    "iso:country":"CN",
    "name:zho_x_preferred":[
        "Hongqi Dadui"
    ],
    "name:zho_x_variant":[
        "\u7ea2\u65d7\u5927\u961f"
    ],
    "wof:name":"Hongqi Dadui",
    "wof:placetype":"locality"
},
  "geometry": {"coordinates":[114.01895,29.82439],"type":"Point"}
}