{
  "type": "Feature",
  "properties": {
    "gn:admin1_code":"12.0",
    "gn:asciiname":"Zhujialing",
    "gn:country_code":"CN",
    "gn:dem":41,
    "gn:feature_class":"P",
    "gn:feature_code":"PPL",
    "gn:name":"Zhujialing",
    "gn:population":0,
    "gn:timezone":"Asia/Shanghai",
    "iso:country":"CN",
    "name:zho_x_preferred":[
        "Zhujialing"
    ],
    "name:zho_x_variant":[
        "\u6731\u5bb6\u5cad"
    ],
    "wof:name":"Zhujialing",
    "wof:placetype":"locality"
},
  "geometry": {"coordinates":[112.05757,30.39586],"type":"Point"}
}