{
  "type": "Feature",
  "properties": {
    "gn:admin1_code":"4.0",
    "gn:asciiname":"Majiaba",
    "gn:country_code":"CN",
    "gn:dem":5,
    "gn:feature_class":"P",
    "gn:feature_code":"PPL",
    "gn:name":"Majiaba",
    "gn:population":0,
    "gn:timezone":"Asia/Shanghai",
    "iso:country":"CN",
    "name:und_x_variant":[
        "\u9a6c\u5bb6\u575d"
    ],
    "wof:name":"Majiaba",
    "wof:placetype":"locality"
},
  "geometry": {"coordinates":[120.9636,32.19727],"type":"Point"}
}