{
  "type": "Feature",
  "properties": {
    "gn:admin1_code":"16.0",
    "gn:asciiname":"Dahan",
    "gn:country_code":"CN",
    "gn:dem":804,
    "gn:feature_class":"P",
    "gn:feature_code":"PPL",
    "gn:name":"Dahan",
    "gn:population":0,
    "gn:timezone":"Asia/Shanghai",
    "iso:country":"CN",
    "name:ceb_x_preferred":[
        "Dahan"
    ],
    "name:deu_x_preferred":[
        "Dahan"
    ],
    "name:fra_x_preferred":[
        "Dahan"
    ],
    "name:heb_x_preferred":[
        "\u05d3\u05d4\u05d0\u05df"
    ],
    "name:swe_x_preferred":[
        "Dahan"
    ],
    "name:ukr_x_preferred":[
        "\u0414\u0430\u0430\u043d"
    ],
    "name:zho_x_preferred":[
        "\u5927\u6c57"
    ],
    "wof:name":"Dahan",
    "wof:placetype":"locality"
},
  "geometry": {"coordinates":[106.047,23.4437],"type":"Point"}
}