{
  "type": "Feature",
  "properties": {
    "gn:admin1_code":"10",
    "gn:asciiname":"Hanliuguan",
    "gn:country_code":"CN",
    "gn:dem":19,
    "gn:feature_class":"P",
    "gn:feature_code":"PPL",
    "gn:name":"Hanliuguan",
    "gn:population":0,
    "gn:timezone":"Asia/Shanghai",
    "iso:country":"CN",
    "name:zho_x_preferred":[
        "\u97e9\u7559\u8d2f"
    ],
    "wof:name":"Hanliuguan",
    "wof:placetype":"locality"
},
  "geometry": {"coordinates":[115.818,37.9485],"type":"Point"}
}