{
  "type": "Feature",
  "properties": {
    "gn:admin1_code":"7",
    "gn:asciiname":"Dakouyao",
    "gn:country_code":"CN",
    "gn:dem":235,
    "gn:feature_class":"P",
    "gn:feature_code":"PPL",
    "gn:name":"Dakouyao",
    "gn:population":0,
    "gn:timezone":"Asia/Shanghai",
    "iso:country":"CN",
    "name:und_x_variant":[
        "\u5927\u53e3\u7a91"
    ],
    "wof:name":"Dakouyao",
    "wof:placetype":"locality"
},
  "geometry": {"coordinates":[118.54277999999999,27.78694],"type":"Point"}
}