{
  "type": "Feature",
  "properties": {
    "gn:admin1_code":"29",
    "gn:asciiname":"Xianjiacun",
    "gn:country_code":"CN",
    "gn:dem":1786,
    "gn:feature_class":"P",
    "gn:feature_code":"PPL",
    "gn:name":"Xianjiacun",
    "gn:population":0,
    "gn:timezone":"Asia/Shanghai",
    "iso:country":"CN",
    "name:zho_x_preferred":[
        "\u53bf\u5bb6\u6751"
    ],
    "wof:name":"Xianjiacun",
    "wof:placetype":"locality"
},
  "geometry": {"coordinates":[102.27833,24.42882],"type":"Point"}
}