{
  "type": "Feature",
  "properties": {
    "gn:admin1_code":"26",
    "gn:asciiname":"Tianjiacha",
    "gn:cc2":"CN",
    "gn:country_code":"CN",
    "gn:dem":999,
    "gn:feature_class":"P",
    "gn:feature_code":"PPL",
    "gn:name":"Tianjiacha",
    "gn:population":0,
    "gn:timezone":"Asia/Shanghai",
    "iso:country":"CN",
    "name:und_x_variant":[
        "T\u2019ien-chia-ch\u2019a",
        "Tianjiacha"
    ],
    "wof:name":"Tianjiacha",
    "wof:placetype":"locality"
},
  "geometry": {"coordinates":[110.53333000000001,37.51667],"type":"Point"}
}