{
  "type": "Feature",
  "properties": {
    "gn:admin1_code":"4.0",
    "gn:asciiname":"Qiangao",
    "gn:country_code":"CN",
    "gn:dem":3,
    "gn:feature_class":"P",
    "gn:feature_code":"PPL",
    "gn:name":"Qiangao",
    "gn:population":0,
    "gn:timezone":"Asia/Shanghai",
    "iso:country":"CN",
    "name:zho_x_preferred":[
        "Qiangao"
    ],
    "name:zho_x_variant":[
        "\u524d\u9ad8"
    ],
    "wof:name":"Qiangao",
    "wof:placetype":"locality"
},
  "geometry": {"coordinates":[119.08176,34.12683],"type":"Point"}
}