{
  "type": "Feature",
  "properties": {
    "gn:admin1_code":"24.0",
    "gn:asciiname":"Luomianzui",
    "gn:country_code":"CN",
    "gn:dem":810,
    "gn:feature_class":"P",
    "gn:feature_code":"PPL",
    "gn:name":"Luomianzui",
    "gn:population":0,
    "gn:timezone":"Asia/Shanghai",
    "iso:country":"CN",
    "name:zho_x_preferred":[
        "\u7f57\u9762\u5480"
    ],
    "wof:name":"Luomianzui",
    "wof:placetype":"locality"
},
  "geometry": {"coordinates":[113.69183,38.04472],"type":"Point"}
}