{
  "type": "Feature",
  "properties": {
    "gn:admin1_code":"23.0",
    "gn:asciiname":"Huangjiazhai",
    "gn:country_code":"CN",
    "gn:dem":7,
    "gn:feature_class":"P",
    "gn:feature_code":"PPL",
    "gn:name":"Huangjiazhai",
    "gn:population":0,
    "gn:timezone":"Asia/Shanghai",
    "iso:country":"CN",
    "name:deu_x_preferred":[
        "Huangjiazhai"
    ],
    "name:eng_x_preferred":[
        "Huangjiazhai"
    ],
    "name:fra_x_preferred":[
        "Huangjiazhai"
    ],
    "name:zho_x_preferred":[
        "Huangjiazhai"
    ],
    "name:zho_x_variant":[
        "\u9ec4\u5bb6\u5b85"
    ],
    "wof:name":"Huangjiazhai",
    "wof:placetype":"locality"
},
  "geometry": {"coordinates":[121.56816000000001,31.20788],"type":"Point"}
}