{
  "type": "Feature",
  "properties": {
    "gn:admin1_code":"21.0",
    "gn:asciiname":"Tuochang",
    "gn:country_code":"CN",
    "gn:dem":1463,
    "gn:feature_class":"P",
    "gn:feature_code":"PPL",
    "gn:name":"Tuochang",
    "gn:population":0,
    "gn:timezone":"Asia/Shanghai",
    "iso:country":"CN",
    "name:zho_x_preferred":[
        "\u8131\u573a"
    ],
    "wof:name":"Tuochang",
    "wof:placetype":"locality"
},
  "geometry": {"coordinates":[105.848,36.7854],"type":"Point"}
}