{
  "type": "Feature",
  "properties": {
    "gn:admin1_code":"15.0",
    "gn:asciiname":"Shejiawan",
    "gn:country_code":"CN",
    "gn:dem":1733,
    "gn:feature_class":"P",
    "gn:feature_code":"PPL",
    "gn:name":"Shejiawan",
    "gn:population":0,
    "gn:timezone":"Asia/Shanghai",
    "iso:country":"CN",
    "name:und_x_variant":[
        "\u820d\u5bb6\u6e7e"
    ],
    "name:zho_x_preferred":[
        "\u820d\u5bb6\u6e7e"
    ],
    "wof:name":"Shejiawan",
    "wof:placetype":"locality"
},
  "geometry": {"coordinates":[105.05673,33.13997],"type":"Point"}
}