{
  "type": "Feature",
  "properties": {
    "gn:admin1_code":"8.0",
    "gn:asciiname":"Bao'ancun",
    "gn:country_code":"CN",
    "gn:dem":97,
    "gn:feature_class":"P",
    "gn:feature_code":"PPL",
    "gn:name":"Bao\u2019ancun",
    "gn:population":0,
    "gn:timezone":"Asia/Shanghai",
    "iso:country":"CN",
    "name:und_x_variant":[
        "Bao\u2019ancun"
    ],
    "name:zho_x_preferred":[
        "\u4fdd\u5b89\u6751"
    ],
    "wof:name":"Bao'ancun",
    "wof:placetype":"locality"
},
  "geometry": {"coordinates":[129.77083000000002,46.62962],"type":"Point"}
}