{
  "type": "Feature",
  "properties": {
    "gn:admin1_code":"9.0",
    "gn:asciiname":"Kongshandong",
    "gn:country_code":"CN",
    "gn:dem":455,
    "gn:feature_class":"P",
    "gn:feature_code":"PPL",
    "gn:name":"Kongshandong",
    "gn:population":0,
    "gn:timezone":"Asia/Shanghai",
    "iso:country":"CN",
    "name:zho_x_preferred":[
        "\u7a7a\u5c71\u6d1e"
    ],
    "wof:name":"Kongshandong",
    "wof:placetype":"locality"
},
  "geometry": {"coordinates":[113.08231000000001,34.16692],"type":"Point"}
}