{
  "type": "Feature",
  "properties": {
    "gn:admin1_code":"4.0",
    "gn:asciiname":"Wangjiadang",
    "gn:country_code":"CN",
    "gn:dem":22,
    "gn:feature_class":"P",
    "gn:feature_code":"PPL",
    "gn:name":"Wangjiadang",
    "gn:population":0,
    "gn:timezone":"Asia/Shanghai",
    "iso:country":"CN",
    "name:zho_x_preferred":[
        "\u738b\u5939\u8361"
    ],
    "wof:name":"Wangjiadang",
    "wof:placetype":"locality"
},
  "geometry": {"coordinates":[118.672,32.9842],"type":"Point"}
}