{
  "type": "Feature",
  "properties": {
    "gn:admin1_code":"8.0",
    "gn:asciiname":"Min'ancun",
    "gn:country_code":"CN",
    "gn:dem":304,
    "gn:feature_class":"P",
    "gn:feature_code":"PPL",
    "gn:name":"Min\u2019ancun",
    "gn:population":0,
    "gn:timezone":"Asia/Shanghai",
    "iso:country":"CN",
    "name:und_x_variant":[
        "Min\u2019ancun"
    ],
    "name:zho_x_preferred":[
        "\u6c11\u5b89\u6751"
    ],
    "wof:name":"Min'ancun",
    "wof:placetype":"locality"
},
  "geometry": {"coordinates":[126.42036,47.74399],"type":"Point"}
}