{
  "type": "Feature",
  "properties": {
    "gn:admin1_code":"8.0",
    "gn:asciiname":"Guofu",
    "gn:country_code":"CN",
    "gn:dem":154,
    "gn:feature_class":"P",
    "gn:feature_code":"PPL",
    "gn:name":"Guofu",
    "gn:population":0,
    "gn:timezone":"Asia/Shanghai",
    "iso:country":"CN",
    "name:zho_x_preferred":[
        "\u56fd\u5bcc"
    ],
    "wof:name":"Guofu",
    "wof:placetype":"locality"
},
  "geometry": {"coordinates":[124.94555,47.17856],"type":"Point"}
}