{
  "type": "Feature",
  "properties": {
    "gn:admin1_code":"10",
    "gn:asciiname":"Xiwei",
    "gn:country_code":"CN",
    "gn:dem":61,
    "gn:feature_class":"P",
    "gn:feature_code":"PPL",
    "gn:name":"Xiwei",
    "gn:population":0,
    "gn:timezone":"Asia/Shanghai",
    "iso:country":"CN",
    "name:ceb_x_preferred":[
        "Xiwei"
    ],
    "name:swe_x_preferred":[
        "Xiwei"
    ],
    "name:zho_x_preferred":[
        "\u897f\u9b4f"
    ],
    "wof:name":"Xiwei",
    "wof:placetype":"locality"
},
  "geometry": {"coordinates":[115.065,38.8155],"type":"Point"}
}