{
  "type": "Feature",
  "properties": {
    "gn:admin1_code":"29.0",
    "gn:asciiname":"Yangmian",
    "gn:country_code":"CN",
    "gn:dem":1617,
    "gn:feature_class":"P",
    "gn:feature_code":"PPL",
    "gn:name":"Yangmian",
    "gn:population":0,
    "gn:timezone":"Asia/Shanghai",
    "iso:country":"CN",
    "name:zho_x_preferred":[
        "\u592e\u7f05"
    ],
    "wof:name":"Yangmian",
    "wof:placetype":"locality"
},
  "geometry": {"coordinates":[99.43340000000001,23.2023],"type":"Point"}
}