{
  "type": "Feature",
  "properties": {
    "gn:admin1_code":"16.0",
    "gn:asciiname":"He'an",
    "gn:country_code":"CN",
    "gn:dem":268,
    "gn:feature_class":"P",
    "gn:feature_code":"PPL",
    "gn:name":"He\u2019an",
    "gn:population":0,
    "gn:timezone":"Asia/Shanghai",
    "iso:country":"CN",
    "name:und_x_variant":[
        "He\u2019an"
    ],
    "name:zho_x_preferred":[
        "\u548c\u5b89"
    ],
    "wof:name":"He'an",
    "wof:placetype":"locality"
},
  "geometry": {"coordinates":[110.43600000000001,23.9869],"type":"Point"}
}