{
  "type": "Feature",
  "properties": {
    "gn:admin1_code":"29.0",
    "gn:asciiname":"Xiaotangde",
    "gn:country_code":"CN",
    "gn:dem":2032,
    "gn:feature_class":"P",
    "gn:feature_code":"PPL",
    "gn:name":"Xiaotangde",
    "gn:population":0,
    "gn:timezone":"Asia/Shanghai",
    "iso:country":"CN",
    "name:zho_x_preferred":[
        "\u5c0f\u6c64\u5fb7"
    ],
    "wof:name":"Xiaotangde",
    "wof:placetype":"locality"
},
  "geometry": {"coordinates":[102.646,25.8452],"type":"Point"}
}