{
  "type": "Feature",
  "properties": {
    "gn:admin1_code":"26.0",
    "gn:asciiname":"Tailiucun",
    "gn:country_code":"CN",
    "gn:dem":953,
    "gn:feature_class":"P",
    "gn:feature_code":"PPL",
    "gn:name":"Tailiucun",
    "gn:population":0,
    "gn:timezone":"Asia/Shanghai",
    "iso:country":"CN",
    "name:zho_x_preferred":[
        "\u592a\u7559\u6751"
    ],
    "wof:name":"Tailiucun",
    "wof:placetype":"locality"
},
  "geometry": {"coordinates":[110.32743000000001,36.31171],"type":"Point"}
}