{
  "type": "Feature",
  "properties": {
    "gn:admin1_code":"10",
    "gn:asciiname":"Hetu",
    "gn:country_code":"CN",
    "gn:dem":35,
    "gn:feature_class":"P",
    "gn:feature_code":"PPL",
    "gn:name":"Hetu",
    "gn:population":0,
    "gn:timezone":"Asia/Shanghai",
    "iso:country":"CN",
    "name:deu_x_preferred":[
        "Hetu"
    ],
    "name:fin_x_preferred":[
        "Hetu"
    ],
    "name:zho_x_preferred":[
        "\u6cb3\u56fe"
    ],
    "wof:name":"Hetu",
    "wof:placetype":"locality"
},
  "geometry": {"coordinates":[115.30200000000001,38.752],"type":"Point"}
}