{
  "type": "Feature",
  "properties": {
    "gn:admin1_code":"20.0",
    "gn:asciiname":"Laoxuexiaotun",
    "gn:country_code":"CN",
    "gn:dem":309,
    "gn:feature_class":"P",
    "gn:feature_code":"PPL",
    "gn:name":"Laoxuexiaotun",
    "gn:population":0,
    "gn:timezone":"Asia/Shanghai",
    "iso:country":"CN",
    "name:zho_x_preferred":[
        "\u8001\u5b66\u6821\u5c6f"
    ],
    "wof:name":"Laoxuexiaotun",
    "wof:placetype":"locality"
},
  "geometry": {"coordinates":[122.74463,47.91197],"type":"Point"}
}