{
  "type": "Feature",
  "properties": {
    "gn:admin1_code":"32.0",
    "gn:asciiname":"Qianggengzi",
    "gn:country_code":"CN",
    "gn:dem":838,
    "gn:feature_class":"P",
    "gn:feature_code":"PPL",
    "gn:name":"Qianggengzi",
    "gn:population":0,
    "gn:timezone":"Asia/Shanghai",
    "iso:country":"CN",
    "name:zho_x_preferred":[
        "\u5f3a\u57c2\u5b50"
    ],
    "wof:name":"Qianggengzi",
    "wof:placetype":"locality"
},
  "geometry": {"coordinates":[103.38500000000001,30.0393],"type":"Point"}
}