{
  "type": "Feature",
  "properties": {
    "gn:admin1_code":"26.0",
    "gn:asciiname":"Getaliang",
    "gn:country_code":"CN",
    "gn:dem":937,
    "gn:feature_class":"P",
    "gn:feature_code":"PPL",
    "gn:name":"Getaliang",
    "gn:population":0,
    "gn:timezone":"Asia/Shanghai",
    "iso:country":"CN",
    "name:zho_x_preferred":[
        "\u572a\u5854\u6881"
    ],
    "wof:name":"Getaliang",
    "wof:placetype":"locality"
},
  "geometry": {"coordinates":[109.03416,34.90279],"type":"Point"}
}