{
  "type": "Feature",
  "properties": {
    "gn:admin1_code":"12.0",
    "gn:asciiname":"Tangshan",
    "gn:country_code":"CN",
    "gn:dem":500,
    "gn:feature_class":"P",
    "gn:feature_code":"PPL",
    "gn:name":"Tangshan",
    "gn:population":0,
    "gn:timezone":"Asia/Shanghai",
    "iso:country":"CN",
    "name:zho_x_preferred":[
        "\u5510\u5c71"
    ],
    "wof:name":"Tangshan",
    "wof:placetype":"locality"
},
  "geometry": {"coordinates":[115.74500999999999,30.55126],"type":"Point"}
}