{
  "type": "Feature",
  "properties": {
    "gn:admin1_code":"18.0",
    "gn:asciiname":"Jiunancun",
    "gn:country_code":"CN",
    "gn:dem":698,
    "gn:feature_class":"P",
    "gn:feature_code":"PPL",
    "gn:name":"Jiunancun",
    "gn:population":0,
    "gn:timezone":"Asia/Shanghai",
    "iso:country":"CN",
    "name:und_x_variant":[
        "Jiunan"
    ],
    "name:zho_x_preferred":[
        "\u4e5d\u5357\u6751"
    ],
    "wof:name":"Jiunancun",
    "wof:placetype":"locality"
},
  "geometry": {"coordinates":[109.345,26.4982],"type":"Point"}
}