{
  "type": "Feature",
  "properties": {
    "gn:admin1_code":"3.0",
    "gn:asciiname":"Luzhu",
    "gn:country_code":"CN",
    "gn:dem":81,
    "gn:feature_class":"P",
    "gn:feature_code":"PPL",
    "gn:name":"L\u00fczhu",
    "gn:population":0,
    "gn:timezone":"Asia/Shanghai",
    "iso:country":"CN",
    "name:und_x_variant":[
        "L\u00fczhu",
        "\u7eff\u7af9"
    ],
    "wof:name":"Luzhu",
    "wof:placetype":"locality"
},
  "geometry": {"coordinates":[115.02237,26.75304],"type":"Point"}
}