{
  "type": "Feature",
  "properties": {
    "gn:admin1_code":"5.0",
    "gn:asciiname":"Funan Linchang",
    "gn:country_code":"CN",
    "gn:dem":860,
    "gn:feature_class":"P",
    "gn:feature_code":"PPLF",
    "gn:name":"Funan Linchang",
    "gn:population":0,
    "gn:timezone":"Asia/Shanghai",
    "iso:country":"CN",
    "name:und_x_variant":[
        "\u629a\u5357\u6797\u573a"
    ],
    "wof:name":"Funan Linchang",
    "wof:placetype":"locality"
},
  "geometry": {"coordinates":[127.53482,42.08591],"type":"Point"}
}