{
  "type": "Feature",
  "properties": {
    "gn:admin1_code":"9.0",
    "gn:asciiname":"Hangjiagou",
    "gn:country_code":"CN",
    "gn:dem":291,
    "gn:feature_class":"P",
    "gn:feature_code":"PPL",
    "gn:name":"Hangjiagou",
    "gn:population":0,
    "gn:timezone":"Asia/Shanghai",
    "iso:country":"CN",
    "name:zho_x_preferred":[
        "\u676d\u5bb6\u6c9f"
    ],
    "wof:name":"Hangjiagou",
    "wof:placetype":"locality"
},
  "geometry": {"coordinates":[112.74473999999999,33.34577],"type":"Point"}
}