{
  "type": "Feature",
  "properties": {
    "gn:admin1_code":"32.0",
    "gn:asciiname":"Qinjiaping",
    "gn:country_code":"CN",
    "gn:dem":802,
    "gn:feature_class":"P",
    "gn:feature_code":"PPL",
    "gn:name":"Qinjiaping",
    "gn:population":0,
    "gn:timezone":"Asia/Shanghai",
    "iso:country":"CN",
    "name:zho_x_preferred":[
        "\u82b9\u5bb6\u576a"
    ],
    "wof:name":"Qinjiaping",
    "wof:placetype":"locality"
},
  "geometry": {"coordinates":[106.66464999999999,32.05348],"type":"Point"}
}