{
  "type": "Feature",
  "properties": {
    "gn:admin1_code":"30",
    "gn:asciiname":"Dazhai",
    "gn:country_code":"CN",
    "gn:dem":87,
    "gn:feature_class":"P",
    "gn:feature_code":"PPL",
    "gn:name":"Dazhai",
    "gn:population":0,
    "gn:timezone":"Asia/Urumqi",
    "iso:country":"CN",
    "name:zho_x_preferred":[
        "\u5927\u5be8"
    ],
    "wof:name":"Dazhai",
    "wof:placetype":"locality"
},
  "geometry": {"coordinates":[110.74800999999999,22.17315],"type":"Point"}
}