{
  "type": "Feature",
  "properties": {
    "gn:admin1_code":"16.0",
    "gn:asciiname":"Dong'ou",
    "gn:country_code":"CN",
    "gn:dem":630,
    "gn:feature_class":"P",
    "gn:feature_code":"PPL",
    "gn:name":"Dong\u2019ou",
    "gn:population":0,
    "gn:timezone":"Asia/Shanghai",
    "iso:country":"CN",
    "name:cdo_x_preferred":[
        "D\u0115\u0324ng-\u0115u-gu\u00f3k"
    ],
    "name:und_x_variant":[
        "Dong\u2019ou"
    ],
    "name:vie_x_preferred":[
        "\u0110\u00f4ng \u00c2u"
    ],
    "name:wuu_x_preferred":[
        "\u4e1c\u74ef\u56fd"
    ],
    "name:zho_x_preferred":[
        "\u6d1e\u6b27"
    ],
    "name:zho_x_variant":[
        "\u4e1c\u74ef\u56fd"
    ],
    "wof:name":"Dong'ou",
    "wof:placetype":"locality"
},
  "geometry": {"coordinates":[108.379,25.3959],"type":"Point"}
}