{
  "type": "Feature",
  "properties": {
    "gn:admin1_code":"2.0",
    "gn:asciiname":"Zhenwu Shanxia",
    "gn:country_code":"CN",
    "gn:dem":122,
    "gn:feature_class":"P",
    "gn:feature_code":"PPL",
    "gn:name":"Zhenwu Shanxia",
    "gn:population":0,
    "gn:timezone":"Asia/Shanghai",
    "iso:country":"CN",
    "name:zho_x_preferred":[
        "\u771f\u6b66\u5c71\u4e0b"
    ],
    "wof:name":"Zhenwu Shanxia",
    "wof:placetype":"locality"
},
  "geometry": {"coordinates":[119.07626,29.16306],"type":"Point"}
}