{
  "type": "Feature",
  "properties": {
    "gn:admin1_code":"29.0",
    "gn:asciiname":"Xiawanbi",
    "gn:country_code":"CN",
    "gn:dem":1118,
    "gn:feature_class":"P",
    "gn:feature_code":"PPL",
    "gn:name":"Xiawanbi",
    "gn:population":0,
    "gn:timezone":"Asia/Shanghai",
    "iso:country":"CN",
    "name:zho_x_preferred":[
        "\u4e0b\u6e7e\u78a7"
    ],
    "wof:name":"Xiawanbi",
    "wof:placetype":"locality"
},
  "geometry": {"coordinates":[101.194,26.3624],"type":"Point"}
}