{
  "type": "Feature",
  "properties": {
    "gn:admin1_code":"18.0",
    "gn:asciiname":"Duimenzhai",
    "gn:country_code":"CN",
    "gn:dem":720,
    "gn:feature_class":"P",
    "gn:feature_code":"PPL",
    "gn:name":"Duimenzhai",
    "gn:population":0,
    "gn:timezone":"Asia/Shanghai",
    "iso:country":"CN",
    "name:zho_x_preferred":[
        "\u5bf9\u95e8\u5be8"
    ],
    "wof:name":"Duimenzhai",
    "wof:placetype":"locality"
},
  "geometry": {"coordinates":[108.82299999999999,27.5825],"type":"Point"}
}