{
  "type": "Feature",
  "properties": {
    "gn:admin1_code":"33.0",
    "gn:asciiname":"Luping",
    "gn:country_code":"CN",
    "gn:dem":1014,
    "gn:feature_class":"P",
    "gn:feature_code":"PPL",
    "gn:name":"L\u00fcping",
    "gn:population":0,
    "gn:timezone":"Asia/Shanghai",
    "iso:country":"CN",
    "name:und_x_variant":[
        "L\u00fcping"
    ],
    "name:zho_x_preferred":[
        "\u7eff\u576a"
    ],
    "wof:name":"Luping",
    "wof:placetype":"locality"
},
  "geometry": {"coordinates":[109.06269,31.42345],"type":"Point"}
}