{
  "type": "Feature",
  "properties": {
    "gn:admin1_code":"31.0",
    "gn:asciiname":"Wushipo",
    "gn:country_code":"CN",
    "gn:dem":107,
    "gn:feature_class":"P",
    "gn:feature_code":"PPL",
    "gn:name":"Wushipo",
    "gn:population":0,
    "gn:timezone":"Asia/Shanghai",
    "iso:country":"CN",
    "name:zho_x_preferred":[
        "\u4e4c\u77f3\u5761"
    ],
    "wof:name":"Wushipo",
    "wof:placetype":"locality"
},
  "geometry": {"coordinates":[110.0977,19.17459],"type":"Point"}
}