{
  "type": "Feature",
  "properties": {
    "gn:admin1_code":"24.0",
    "gn:asciiname":"Duanling",
    "gn:country_code":"CN",
    "gn:dem":962,
    "gn:feature_class":"P",
    "gn:feature_code":"PPL",
    "gn:name":"Duanling",
    "gn:population":0,
    "gn:timezone":"Asia/Shanghai",
    "iso:country":"CN",
    "name:und_x_variant":[
        "\u77ed\u5cad"
    ],
    "wof:name":"Duanling",
    "wof:placetype":"locality"
},
  "geometry": {"coordinates":[111.51755,35.39352],"type":"Point"}
}