{
  "type": "Feature",
  "properties": {
    "gn:admin1_code":"16.0",
    "gn:asciiname":"Jiali",
    "gn:country_code":"CN",
    "gn:dem":542,
    "gn:feature_class":"P",
    "gn:feature_code":"PPL",
    "gn:name":"Jiali",
    "gn:population":0,
    "gn:timezone":"Asia/Shanghai",
    "iso:country":"CN",
    "name:fra_x_preferred":[
        "Jiali"
    ],
    "name:zho_x_preferred":[
        "\u52a0\u91cc"
    ],
    "wof:name":"Jiali",
    "wof:placetype":"locality"
},
  "geometry": {"coordinates":[106.748,24.7712],"type":"Point"}
}