{
  "type": "Feature",
  "properties": {
    "gn:admin1_code":"32.0",
    "gn:asciiname":"Ridang",
    "gn:country_code":"CN",
    "gn:dem":2840,
    "gn:feature_class":"P",
    "gn:feature_code":"PPL",
    "gn:name":"Ridang",
    "gn:population":0,
    "gn:timezone":"Asia/Shanghai",
    "iso:country":"CN",
    "name:zho_x_preferred":[
        "\u65e5\u5f53"
    ],
    "wof:name":"Ridang",
    "wof:placetype":"locality"
},
  "geometry": {"coordinates":[99.40649999999999,28.9243],"type":"Point"}
}