{
  "type": "Feature",
  "properties": {
    "gn:admin1_code":"26.0",
    "gn:asciiname":"Shicuncun",
    "gn:country_code":"CN",
    "gn:dem":981,
    "gn:feature_class":"P",
    "gn:feature_code":"PPL",
    "gn:name":"Shicuncun",
    "gn:population":0,
    "gn:timezone":"Asia/Shanghai",
    "iso:country":"CN",
    "name:zho_x_preferred":[
        "\u77f3\u6751\u6751"
    ],
    "wof:name":"Shicuncun",
    "wof:placetype":"locality"
},
  "geometry": {"coordinates":[107.98582,34.63478],"type":"Point"}
}