{
  "type": "Feature",
  "properties": {
    "gn:admin1_code":"1.0",
    "gn:asciiname":"Erdaoyancun",
    "gn:country_code":"CN",
    "gn:dem":48,
    "gn:feature_class":"P",
    "gn:feature_code":"PPL",
    "gn:name":"Erdaoyancun",
    "gn:population":0,
    "gn:timezone":"Asia/Shanghai",
    "iso:country":"CN",
    "name:zho_x_preferred":[
        "\u4e8c\u9053\u5830\u6751"
    ],
    "wof:name":"Erdaoyancun",
    "wof:placetype":"locality"
},
  "geometry": {"coordinates":[115.97351,32.36188],"type":"Point"}
}