{
  "type": "Feature",
  "properties": {
    "gn:admin1_code":"3.0",
    "gn:asciiname":"Huangniding",
    "gn:country_code":"CN",
    "gn:dem":781,
    "gn:feature_class":"P",
    "gn:feature_code":"PPL",
    "gn:name":"Huangniding",
    "gn:population":0,
    "gn:timezone":"Asia/Shanghai",
    "iso:country":"CN",
    "name:zho_x_preferred":[
        "\u9ec4\u6ce5\u9876"
    ],
    "wof:name":"Huangniding",
    "wof:placetype":"locality"
},
  "geometry": {"coordinates":[117.76331999999999,28.79305],"type":"Point"}
}