{
  "type": "Feature",
  "properties": {
    "gn:admin1_code":"10.0",
    "gn:asciiname":"Xiyaotou",
    "gn:country_code":"CN",
    "gn:dem":855,
    "gn:feature_class":"P",
    "gn:feature_code":"PPL",
    "gn:name":"Xiyaotou",
    "gn:population":0,
    "gn:timezone":"Asia/Shanghai",
    "iso:country":"CN",
    "name:zho_x_preferred":[
        "\u897f\u7a91\u5934"
    ],
    "wof:name":"Xiyaotou",
    "wof:placetype":"locality"
},
  "geometry": {"coordinates":[114.56206,40.19642],"type":"Point"}
}