{
  "type": "Feature",
  "properties": {
    "gn:admin1_code":"29.0",
    "gn:asciiname":"Taoshuwan",
    "gn:country_code":"CN",
    "gn:dem":1961,
    "gn:feature_class":"P",
    "gn:feature_code":"PPL",
    "gn:name":"Taoshuwan",
    "gn:population":0,
    "gn:timezone":"Asia/Shanghai",
    "iso:country":"CN",
    "name:zho_x_preferred":[
        "\u6843\u6811\u5f2f"
    ],
    "wof:name":"Taoshuwan",
    "wof:placetype":"locality"
},
  "geometry": {"coordinates":[103.54600000000001,25.7518],"type":"Point"}
}