{
  "type": "Feature",
  "properties": {
    "gn:admin1_code":"11.0",
    "gn:asciiname":"Dongtangwan",
    "gn:country_code":"CN",
    "gn:dem":68,
    "gn:feature_class":"P",
    "gn:feature_code":"PPL",
    "gn:name":"Dongtangwan",
    "gn:population":0,
    "gn:timezone":"Asia/Shanghai",
    "iso:country":"CN",
    "name:zho_x_preferred":[
        "\u4e1c\u5858\u6e7e"
    ],
    "wof:name":"Dongtangwan",
    "wof:placetype":"locality"
},
  "geometry": {"coordinates":[112.95307,27.51085],"type":"Point"}
}