{
  "type": "Feature",
  "properties": {
    "gn:admin1_code":"25.0",
    "gn:asciiname":"Donghonghe",
    "gn:cc2":"CN",
    "gn:country_code":"CN",
    "gn:dem":59,
    "gn:feature_class":"P",
    "gn:feature_code":"PPL",
    "gn:name":"Donghonghe",
    "gn:population":0,
    "gn:timezone":"Asia/Shanghai",
    "iso:country":"CN",
    "name:zho_x_preferred":[
        "\u4e1c\u6d2a\u6cb3"
    ],
    "wof:name":"Donghonghe",
    "wof:placetype":"locality"
},
  "geometry": {"coordinates":[119.28243000000001,35.54873],"type":"Point"}
}