{
  "type": "Feature",
  "properties": {
    "gn:admin1_code":"19.0",
    "gn:asciiname":"Donggaolifang",
    "gn:country_code":"CN",
    "gn:dem":5,
    "gn:feature_class":"P",
    "gn:feature_code":"PPL",
    "gn:name":"Donggaolifang",
    "gn:population":0,
    "gn:timezone":"Asia/Shanghai",
    "iso:country":"CN",
    "name:zho_x_preferred":[
        "\u4e1c\u9ad8\u529b\u623f"
    ],
    "wof:name":"Donggaolifang",
    "wof:placetype":"locality"
},
  "geometry": {"coordinates":[122.59416,41.04861],"type":"Point"}
}