{
  "type": "Feature",
  "properties": {
    "gn:admin1_code":"18.0",
    "gn:asciiname":"Ganyao",
    "gn:country_code":"CN",
    "gn:dem":824,
    "gn:feature_class":"P",
    "gn:feature_code":"PPL",
    "gn:name":"Ganyao",
    "gn:population":0,
    "gn:timezone":"Asia/Shanghai",
    "iso:country":"CN",
    "name:zho_x_preferred":[
        "\u5e72\u5c27"
    ],
    "wof:name":"Ganyao",
    "wof:placetype":"locality"
},
  "geometry": {"coordinates":[107.69499999999999,25.5698],"type":"Point"}
}