{
  "type": "Feature",
  "properties": {
    "gn:admin1_code":"32.0",
    "gn:asciiname":"Xujia Dagou",
    "gn:country_code":"CN",
    "gn:dem":2060,
    "gn:feature_class":"P",
    "gn:feature_code":"PPL",
    "gn:name":"Xujia Dagou",
    "gn:population":0,
    "gn:timezone":"Asia/Shanghai",
    "iso:country":"CN",
    "name:zho_x_preferred":[
        "\u5f90\u5bb6\u5927\u6c9f"
    ],
    "wof:name":"Xujia Dagou",
    "wof:placetype":"locality"
},
  "geometry": {"coordinates":[102.47199999999999,26.6412],"type":"Point"}
}