{
  "type": "Feature",
  "properties": {
    "gn:admin1_code":"4.0",
    "gn:asciiname":"Guaqieduo",
    "gn:country_code":"CN",
    "gn:dem":2,
    "gn:feature_class":"P",
    "gn:feature_code":"PPL",
    "gn:name":"Guaqieduo",
    "gn:population":0,
    "gn:timezone":"Asia/Shanghai",
    "iso:country":"CN",
    "name:zho_x_preferred":[
        "\u74dc\u8304\u579b"
    ],
    "wof:name":"Guaqieduo",
    "wof:placetype":"locality"
},
  "geometry": {"coordinates":[120.33965999999999,32.73113],"type":"Point"}
}