{
  "type": "Feature",
  "properties": {
    "gn:admin1_code":"26.0",
    "gn:asciiname":"Xiankou",
    "gn:cc2":"CN",
    "gn:country_code":"CN",
    "gn:dem":1220,
    "gn:feature_class":"P",
    "gn:feature_code":"PPL",
    "gn:name":"Xiankou",
    "gn:population":0,
    "gn:timezone":"Asia/Shanghai",
    "iso:country":"CN",
    "name:und_x_variant":[
        "Hsien-k\u2019ou",
        "Xiankou"
    ],
    "wof:name":"Xiankou",
    "wof:placetype":"locality"
},
  "geometry": {"coordinates":[109.12,35.22389000000001],"type":"Point"}
}