{
  "type": "Feature",
  "properties": {
    "gn:admin1_code":"10",
    "gn:asciiname":"Zhaozhuangzi",
    "gn:country_code":"CN",
    "gn:dem":12,
    "gn:feature_class":"P",
    "gn:feature_code":"PPL",
    "gn:name":"Zhaozhuangzi",
    "gn:population":0,
    "gn:timezone":"Asia/Shanghai",
    "iso:country":"CN",
    "name:zho_x_preferred":[
        "\u8d75\u5e84\u5b50"
    ],
    "wof:name":"Zhaozhuangzi",
    "wof:placetype":"locality"
},
  "geometry": {"coordinates":[116.032,38.9211],"type":"Point"}
}