{
  "type": "Feature",
  "properties": {
    "gn:admin1_code":"26.0",
    "gn:asciiname":"Huoshenpo",
    "gn:country_code":"CN",
    "gn:dem":772,
    "gn:feature_class":"P",
    "gn:feature_code":"PPL",
    "gn:name":"Huoshenpo",
    "gn:population":0,
    "gn:timezone":"Asia/Shanghai",
    "iso:country":"CN",
    "name:und_x_variant":[
        "\u706b\u795e\u5761"
    ],
    "wof:name":"Huoshenpo",
    "wof:placetype":"locality"
},
  "geometry": {"coordinates":[107.11956000000001,32.98832],"type":"Point"}
}