{
  "type": "Feature",
  "properties": {
    "gn:admin1_code":"14.0",
    "gn:asciiname":"Pijiu",
    "gn:country_code":"CN",
    "gn:dem":4754,
    "gn:feature_class":"P",
    "gn:feature_code":"PPL",
    "gn:name":"Pijiu",
    "gn:population":0,
    "gn:timezone":"Asia/Urumqi",
    "iso:country":"CN",
    "name:zho_x_preferred":[
        "\u76ae\u4e45"
    ],
    "wof:name":"Pijiu",
    "wof:placetype":"locality"
},
  "geometry": {"coordinates":[87.1755,28.8184],"type":"Point"}
}