{
  "type": "Feature",
  "properties": {
    "gn:admin1_code":"30.0",
    "gn:asciiname":"Zhongxin",
    "gn:country_code":"CN",
    "gn:dem":137,
    "gn:feature_class":"P",
    "gn:feature_code":"PPLA4",
    "gn:name":"Zhongxin",
    "gn:population":0,
    "gn:timezone":"Asia/Shanghai",
    "iso:country":"CN",
    "name:und_x_variant":[
        "Chung-hsin",
        "Lien-p\u2019ing",
        "Chung-hsin-hs\u00fc",
        "Chungsun",
        "Chung-hsin-chen",
        "Zhongxin",
        "\u5fe0\u4fe1",
        "Zhongxin Zhen",
        "\u5fe0\u4fe1\u9547"
    ],
    "wof:name":"Zhongxin",
    "wof:placetype":"locality"
},
  "geometry": {"coordinates":[114.73333,24.21667],"type":"Point"}
}