{
  "type": "Feature",
  "properties": {
    "gn:admin1_code":"21.0",
    "gn:asciiname":"Xiaojiazhang",
    "gn:country_code":"CN",
    "gn:dem":1891,
    "gn:feature_class":"P",
    "gn:feature_code":"PPL",
    "gn:name":"Xiaojiazhang",
    "gn:population":0,
    "gn:timezone":"Asia/Shanghai",
    "iso:country":"CN",
    "name:und_x_variant":[
        "\u785d\u5bb6\u7ae0"
    ],
    "name:zho_x_preferred":[
        "\u785d\u5bb6\u7ae0"
    ],
    "wof:name":"Xiaojiazhang",
    "wof:placetype":"locality"
},
  "geometry": {"coordinates":[105.44467,35.89754],"type":"Point"}
}