{
  "type": "Feature",
  "properties": {
    "gn:admin1_code":"29.0",
    "gn:asciiname":"Dasanjia",
    "gn:country_code":"CN",
    "gn:dem":2429,
    "gn:feature_class":"P",
    "gn:feature_code":"PPL",
    "gn:name":"Dasanjia",
    "gn:population":0,
    "gn:timezone":"Asia/Shanghai",
    "iso:country":"CN",
    "name:zho_x_preferred":[
        "\u5927\u4e09\u5bb6"
    ],
    "wof:name":"Dasanjia",
    "wof:placetype":"locality"
},
  "geometry": {"coordinates":[100.29000000000001,25.4218],"type":"Point"}
}