{
  "type": "Feature",
  "properties": {
    "gn:admin1_code":"19.0",
    "gn:asciiname":"Fumintun",
    "gn:country_code":"CN",
    "gn:dem":127,
    "gn:feature_class":"P",
    "gn:feature_code":"PPL",
    "gn:name":"Fumintun",
    "gn:population":0,
    "gn:timezone":"Asia/Shanghai",
    "iso:country":"CN",
    "name:zho_x_preferred":[
        "\u8f85\u6c11\u5c6f"
    ],
    "wof:name":"Fumintun",
    "wof:placetype":"locality"
},
  "geometry": {"coordinates":[123.92468,42.13032000000001],"type":"Point"}
}