{
  "type": "Feature",
  "properties": {
    "gn:admin1_code":"30.0",
    "gn:asciiname":"Houzixue",
    "gn:country_code":"CN",
    "gn:dem":630,
    "gn:feature_class":"P",
    "gn:feature_code":"PPL",
    "gn:name":"Houzixue",
    "gn:population":0,
    "gn:timezone":"Asia/Shanghai",
    "iso:country":"CN",
    "name:zho_x_preferred":[
        "\u7334\u5b50\u7a74"
    ],
    "wof:name":"Houzixue",
    "wof:placetype":"locality"
},
  "geometry": {"coordinates":[115.44201,23.25819],"type":"Point"}
}