{
  "type": "Feature",
  "properties": {
    "gn:admin1_code":"11.0",
    "gn:asciiname":"Laowanli",
    "gn:country_code":"CN",
    "gn:dem":433,
    "gn:feature_class":"P",
    "gn:feature_code":"PPL",
    "gn:name":"Laowanli",
    "gn:population":0,
    "gn:timezone":"Asia/Shanghai",
    "iso:country":"CN",
    "name:zho_x_preferred":[
        "\u8001\u6e7e\u91cc"
    ],
    "wof:name":"Laowanli",
    "wof:placetype":"locality"
},
  "geometry": {"coordinates":[113.50736999999999,26.21168],"type":"Point"}
}