{
  "type": "Feature",
  "properties": {
    "gn:admin1_code":"20.0",
    "gn:asciiname":"Sishihao",
    "gn:country_code":"CN",
    "gn:dem":1417,
    "gn:feature_class":"P",
    "gn:feature_code":"PPL",
    "gn:name":"Sishihao",
    "gn:population":0,
    "gn:timezone":"Asia/Shanghai",
    "iso:country":"CN",
    "name:und_x_variant":[
        "\u56db\u5341\u53f7"
    ],
    "wof:name":"Sishihao",
    "wof:placetype":"locality"
},
  "geometry": {"coordinates":[113.53263,40.75747],"type":"Point"}
}