{
  "type": "Feature",
  "properties": {
    "gn:admin1_code":"01",
    "gn:asciiname":"Shangtushi",
    "gn:cc2":"CN",
    "gn:country_code":"CN",
    "gn:dem":290,
    "gn:feature_class":"P",
    "gn:feature_code":"PPL",
    "gn:name":"Shangtushi",
    "gn:population":0,
    "gn:timezone":"Asia/Shanghai",
    "iso:country":"CN",
    "name:und_x_variant":[
        "Shang-t\u2019u-shih",
        "Shangtushi"
    ],
    "wof:name":"Shangtushi",
    "wof:placetype":"locality"
},
  "geometry": {"coordinates":[115.98333,31.13333],"type":"Point"}
}