{
  "type": "Feature",
  "properties": {
    "gn:admin1_code":"29.0",
    "gn:asciiname":"Xiaojia",
    "gn:country_code":"CN",
    "gn:dem":991,
    "gn:feature_class":"P",
    "gn:feature_code":"PPL",
    "gn:name":"Xiaojia",
    "gn:population":0,
    "gn:timezone":"Asia/Shanghai",
    "iso:country":"CN",
    "name:zho_x_preferred":[
        "\u8096\u5bb6"
    ],
    "wof:name":"Xiaojia",
    "wof:placetype":"locality"
},
  "geometry": {"coordinates":[101.27200000000001,24.0008],"type":"Point"}
}