{
  "type": "Feature",
  "properties": {
    "gn:admin1_code":"07",
    "gn:asciiname":"Kengyuantou",
    "gn:country_code":"CN",
    "gn:dem":950,
    "gn:feature_class":"P",
    "gn:feature_code":"PPL",
    "gn:name":"Kengyuantou",
    "gn:population":0,
    "gn:timezone":"Asia/Shanghai",
    "iso:country":"CN",
    "name:zho_x_preferred":[
        "\u5751\u6e90\u5934"
    ],
    "wof:name":"Kengyuantou",
    "wof:placetype":"locality"
},
  "geometry": {"coordinates":[117.35083,25.75361],"type":"Point"}
}