{
  "type": "Feature",
  "properties": {
    "gn:admin1_code":"24.0",
    "gn:asciiname":"Beijiajiayao",
    "gn:country_code":"CN",
    "gn:dem":1201,
    "gn:feature_class":"P",
    "gn:feature_code":"PPL",
    "gn:name":"Beijiajiayao",
    "gn:population":0,
    "gn:timezone":"Asia/Shanghai",
    "iso:country":"CN",
    "name:und_x_variant":[
        "\u5317\u8d3e\u5bb6\u7a91"
    ],
    "wof:name":"Beijiajiayao",
    "wof:placetype":"locality"
},
  "geometry": {"coordinates":[112.75644,39.55295],"type":"Point"}
}