{
  "type": "Feature",
  "properties": {
    "gn:admin1_code":"15.0",
    "gn:asciiname":"Bailinsi",
    "gn:country_code":"CN",
    "gn:dem":1028,
    "gn:feature_class":"P",
    "gn:feature_code":"PPL",
    "gn:name":"Bailinsi",
    "gn:population":0,
    "gn:timezone":"Asia/Shanghai",
    "iso:country":"CN",
    "name:und_x_variant":[
        "\u67cf\u6797\u5bfa"
    ],
    "wof:name":"Bailinsi",
    "wof:placetype":"locality"
},
  "geometry": {"coordinates":[105.13677,33.29871],"type":"Point"}
}