{
  "type": "Feature",
  "properties": {
    "gn:admin1_code":"25",
    "gn:asciiname":"Xicaoying",
    "gn:country_code":"CN",
    "gn:dem":49,
    "gn:feature_class":"P",
    "gn:feature_code":"PPL",
    "gn:name":"Xicaoying",
    "gn:population":0,
    "gn:timezone":"Asia/Shanghai",
    "iso:country":"CN",
    "name:zho_x_preferred":[
        "\u897f\u66f9\u8425"
    ],
    "wof:name":"Xicaoying",
    "wof:placetype":"locality"
},
  "geometry": {"coordinates":[115.639,35.9444],"type":"Point"}
}