{
  "type": "Feature",
  "properties": {
    "gn:admin1_code":"10.0",
    "gn:asciiname":"Chuaijiagou",
    "gn:country_code":"CN",
    "gn:dem":28,
    "gn:feature_class":"P",
    "gn:feature_code":"PPL",
    "gn:name":"Chuaijiagou",
    "gn:population":0,
    "gn:timezone":"Asia/Shanghai",
    "iso:country":"CN",
    "name:zho_x_preferred":[
        "\u63e3\u5bb6\u6c9f"
    ],
    "wof:name":"Chuaijiagou",
    "wof:placetype":"locality"
},
  "geometry": {"coordinates":[119.71536999999999,40.01332],"type":"Point"}
}