{
  "type": "Feature",
  "properties": {
    "gn:admin1_code":"32.0",
    "gn:asciiname":"Zhenjiawan",
    "gn:country_code":"CN",
    "gn:dem":689,
    "gn:feature_class":"P",
    "gn:feature_code":"PPL",
    "gn:name":"Zhenjiawan",
    "gn:population":0,
    "gn:timezone":"Asia/Shanghai",
    "iso:country":"CN",
    "name:zho_x_preferred":[
        "\u9547\u5bb6\u6e7e"
    ],
    "wof:name":"Zhenjiawan",
    "wof:placetype":"locality"
},
  "geometry": {"coordinates":[107.3343,30.7679],"type":"Point"}
}