{
  "type": "Feature",
  "properties": {
    "gn:admin1_code":"05",
    "gn:asciiname":"Zhurduohe",
    "gn:cc2":"CN",
    "gn:country_code":"CN",
    "gn:dem":428,
    "gn:feature_class":"P",
    "gn:feature_code":"PPL",
    "gn:name":"Zhurduohe",
    "gn:population":0,
    "gn:timezone":"Asia/Shanghai",
    "iso:country":"CN",
    "name:und_x_variant":[
        "Chu-erh-to-ho",
        "Zhurduohe"
    ],
    "wof:name":"Zhurduohe",
    "wof:placetype":"locality"
},
  "geometry": {"coordinates":[128.03556,43.80389],"type":"Point"}
}