{
  "type": "Feature",
  "properties": {
    "gn:admin1_code":"02",
    "gn:asciiname":"Zhoujiacun",
    "gn:country_code":"CN",
    "gn:dem":1,
    "gn:feature_class":"P",
    "gn:feature_code":"PPL",
    "gn:name":"Zhoujiacun",
    "gn:population":0,
    "gn:timezone":"Asia/Shanghai",
    "iso:country":"CN",
    "name:und_x_variant":[
        "Chou-chia-tung-men",
        "Zhoujia",
        "Zhoujiacun"
    ],
    "name:zho_x_preferred":[
        "\u5468\u5bb6\u6751"
    ],
    "wof:name":"Zhoujiacun",
    "wof:placetype":"locality"
},
  "geometry": {"coordinates":[121.45605,29.6613],"type":"Point"}
}