{
  "type": "Feature",
  "properties": {
    "gn:admin1_code":"29.0",
    "gn:asciiname":"Juedi",
    "gn:country_code":"CN",
    "gn:dem":2572,
    "gn:feature_class":"P",
    "gn:feature_code":"PPL",
    "gn:name":"Juedi",
    "gn:population":0,
    "gn:timezone":"Asia/Shanghai",
    "iso:country":"CN",
    "name:zho_x_preferred":[
        "\u8568\u5730"
    ],
    "wof:name":"Juedi",
    "wof:placetype":"locality"
},
  "geometry": {"coordinates":[99.3027,25.9151],"type":"Point"}
}