{
  "type": "Feature",
  "properties": {
    "gn:admin1_code":"33.0",
    "gn:asciiname":"Kongzimiao",
    "gn:country_code":"CN",
    "gn:dem":915,
    "gn:feature_class":"P",
    "gn:feature_code":"PPL",
    "gn:name":"Kongzimiao",
    "gn:population":0,
    "gn:timezone":"Asia/Shanghai",
    "iso:country":"CN",
    "name:zho_x_preferred":[
        "\u5b54\u5b50\u5e99"
    ],
    "wof:name":"Kongzimiao",
    "wof:placetype":"locality"
},
  "geometry": {"coordinates":[106.25454000000001,28.88914],"type":"Point"}
}