{
  "type": "Feature",
  "properties": {
    "gn:admin1_code":"5.0",
    "gn:asciiname":"Helaowobu",
    "gn:country_code":"CN",
    "gn:dem":150,
    "gn:feature_class":"P",
    "gn:feature_code":"PPL",
    "gn:name":"Helaowobu",
    "gn:population":0,
    "gn:timezone":"Asia/Shanghai",
    "iso:country":"CN",
    "name:zho_x_preferred":[
        "\u8d3a\u8001\u7a9d\u5821"
    ],
    "wof:name":"Helaowobu",
    "wof:placetype":"locality"
},
  "geometry": {"coordinates":[124.27576000000001,43.30903],"type":"Point"}
}