{
  "type": "Feature",
  "properties": {
    "gn:admin1_code":"18",
    "gn:asciiname":"Huadikan",
    "gn:country_code":"CN",
    "gn:dem":1220,
    "gn:feature_class":"P",
    "gn:feature_code":"PPL",
    "gn:name":"Huadikan",
    "gn:population":0,
    "gn:timezone":"Asia/Shanghai",
    "iso:country":"CN",
    "name:zho_x_preferred":[
        "\u82b1\u5730\u574e"
    ],
    "wof:name":"Huadikan",
    "wof:placetype":"locality"
},
  "geometry": {"coordinates":[106.27500000000001,27.1387],"type":"Point"}
}