{
  "type": "Feature",
  "properties": {
    "gn:admin1_code":"15.0",
    "gn:asciiname":"Xiadalin",
    "gn:country_code":"CN",
    "gn:dem":1412,
    "gn:feature_class":"P",
    "gn:feature_code":"PPL",
    "gn:name":"Xiadalin",
    "gn:population":0,
    "gn:timezone":"Asia/Shanghai",
    "iso:country":"CN",
    "name:zho_x_preferred":[
        "\u4e0b\u5927\u6797"
    ],
    "wof:name":"Xiadalin",
    "wof:placetype":"locality"
},
  "geometry": {"coordinates":[104.383,36.8575],"type":"Point"}
}