{
  "type": "Feature",
  "properties": {
    "gn:admin1_code":"18",
    "gn:asciiname":"Gezuo",
    "gn:country_code":"CN",
    "gn:dem":1451,
    "gn:feature_class":"P",
    "gn:feature_code":"PPL",
    "gn:name":"Gezuo",
    "gn:population":0,
    "gn:timezone":"Asia/Shanghai",
    "iso:country":"CN",
    "name:zho_x_preferred":[
        "\u6208\u5ea7"
    ],
    "wof:name":"Gezuo",
    "wof:placetype":"locality"
},
  "geometry": {"coordinates":[105.093,27.16800000000001],"type":"Point"}
}