{
  "type": "Feature",
  "properties": {
    "gn:admin1_code":"1.0",
    "gn:asciiname":"Yingshancun",
    "gn:country_code":"CN",
    "gn:dem":69,
    "gn:feature_class":"P",
    "gn:feature_code":"PPL",
    "gn:name":"Yingshancun",
    "gn:population":0,
    "gn:timezone":"Asia/Shanghai",
    "iso:country":"CN",
    "name:zho_x_preferred":[
        "\u83b9\u5c71\u6751"
    ],
    "wof:name":"Yingshancun",
    "wof:placetype":"locality"
},
  "geometry": {"coordinates":[119.31128,31.0033],"type":"Point"}
}