{
  "type": "Feature",
  "properties": {
    "gn:admin1_code":"18.0",
    "gn:asciiname":"Xiaozhaiyin",
    "gn:country_code":"CN",
    "gn:dem":688,
    "gn:feature_class":"P",
    "gn:feature_code":"PPL",
    "gn:name":"Xiaozhaiyin",
    "gn:population":0,
    "gn:timezone":"Asia/Shanghai",
    "iso:country":"CN",
    "name:zho_x_preferred":[
        "\u5c0f\u5be8\u5bc5"
    ],
    "wof:name":"Xiaozhaiyin",
    "wof:placetype":"locality"
},
  "geometry": {"coordinates":[109.178,28.3451],"type":"Point"}
}