{
  "type": "Feature",
  "properties": {
    "gn:admin1_code":"14.0",
    "gn:asciiname":"Bazhimaru",
    "gn:country_code":"CN",
    "gn:dem":4314,
    "gn:feature_class":"P",
    "gn:feature_code":"PPL",
    "gn:name":"Bazhimaru",
    "gn:population":0,
    "gn:timezone":"Asia/Urumqi",
    "iso:country":"CN",
    "name:zho_x_preferred":[
        "\u5df4\u76f4\u9a6c\u5982"
    ],
    "wof:name":"Bazhimaru",
    "wof:placetype":"locality"
},
  "geometry": {"coordinates":[93.84542,31.80848],"type":"Point"}
}