{
  "type": "Feature",
  "properties": {
    "gn:admin1_code":"3.0",
    "gn:asciiname":"Bankeng Laowu",
    "gn:country_code":"CN",
    "gn:dem":430,
    "gn:feature_class":"P",
    "gn:feature_code":"PPL",
    "gn:name":"Bankeng Laowu",
    "gn:population":0,
    "gn:timezone":"Asia/Shanghai",
    "iso:country":"CN",
    "name:zho_x_preferred":[
        "\u677f\u5751\u8001\u5c4b"
    ],
    "wof:name":"Bankeng Laowu",
    "wof:placetype":"locality"
},
  "geometry": {"coordinates":[114.196,29.0737],"type":"Point"}
}