{
  "type": "Feature",
  "properties": {
    "gn:admin1_code":"19.0",
    "gn:asciiname":"Dakanzi",
    "gn:country_code":"CN",
    "gn:dem":448,
    "gn:feature_class":"P",
    "gn:feature_code":"PPL",
    "gn:name":"Dakanzi",
    "gn:population":0,
    "gn:timezone":"Asia/Shanghai",
    "iso:country":"CN",
    "name:zho_x_preferred":[
        "\u5927\u574e\u5b50"
    ],
    "wof:name":"Dakanzi",
    "wof:placetype":"locality"
},
  "geometry": {"coordinates":[124.93968999999998,41.36383],"type":"Point"}
}