{
  "type": "Feature",
  "properties": {
    "gn:admin1_code":"29.0",
    "gn:asciiname":"Huanglianhe",
    "gn:country_code":"CN",
    "gn:dem":1700,
    "gn:feature_class":"P",
    "gn:feature_code":"PPL",
    "gn:name":"Huanglianhe",
    "gn:population":0,
    "gn:timezone":"Asia/Shanghai",
    "iso:country":"CN",
    "name:zho_x_preferred":[
        "\u9ec4\u8fde\u6cb3"
    ],
    "wof:name":"Huanglianhe",
    "wof:placetype":"locality"
},
  "geometry": {"coordinates":[97.6782,24.748],"type":"Point"}
}