{
  "type": "Feature",
  "properties": {
    "gn:admin1_code":"14.0",
    "gn:asciiname":"Zhamuduo",
    "gn:country_code":"CN",
    "gn:dem":4020,
    "gn:feature_class":"P",
    "gn:feature_code":"PPL",
    "gn:name":"Zhamuduo",
    "gn:population":0,
    "gn:timezone":"Asia/Urumqi",
    "iso:country":"CN",
    "name:zho_x_preferred":[
        "\u624e\u6728\u591a"
    ],
    "wof:name":"Zhamuduo",
    "wof:placetype":"locality"
},
  "geometry": {"coordinates":[91.57977,29.93161],"type":"Point"}
}