{
  "type": "Feature",
  "properties": {
    "gn:admin1_code":"33.0",
    "gn:asciiname":"Tianwan",
    "gn:country_code":"CN",
    "gn:dem":810,
    "gn:feature_class":"P",
    "gn:feature_code":"PPL",
    "gn:name":"Tianwan",
    "gn:population":0,
    "gn:timezone":"Asia/Shanghai",
    "iso:country":"CN",
    "name:zho_x_preferred":[
        "\u7530\u5f2f"
    ],
    "wof:name":"Tianwan",
    "wof:placetype":"locality"
},
  "geometry": {"coordinates":[108.03006999999999,30.73259],"type":"Point"}
}