{
  "type": "Feature",
  "properties": {
    "gn:admin1_code":"26.0",
    "gn:asciiname":"Youfangwa",
    "gn:country_code":"CN",
    "gn:dem":1362,
    "gn:feature_class":"P",
    "gn:feature_code":"PPL",
    "gn:name":"Youfangwa",
    "gn:population":0,
    "gn:timezone":"Asia/Shanghai",
    "iso:country":"CN",
    "name:zho_x_preferred":[
        "\u6cb9\u623f\u6d3c"
    ],
    "wof:name":"Youfangwa",
    "wof:placetype":"locality"
},
  "geometry": {"coordinates":[108.18716000000001,37.62447],"type":"Point"}
}