{
  "type": "Feature",
  "properties": {
    "gn:admin1_code":"16.0",
    "gn:asciiname":"Hanyongpo",
    "gn:country_code":"CN",
    "gn:dem":75,
    "gn:feature_class":"P",
    "gn:feature_code":"PPL",
    "gn:name":"Hanyongpo",
    "gn:population":0,
    "gn:timezone":"Asia/Shanghai",
    "iso:country":"CN",
    "name:zho_x_preferred":[
        "\u65f1\u57c7\u5761"
    ],
    "wof:name":"Hanyongpo",
    "wof:placetype":"locality"
},
  "geometry": {"coordinates":[109.45399999999999,22.1948],"type":"Point"}
}