{
  "type": "Feature",
  "properties": {
    "gn:admin1_code":"7.0",
    "gn:asciiname":"Zhaokeng",
    "gn:country_code":"CN",
    "gn:dem":852,
    "gn:feature_class":"P",
    "gn:feature_code":"PPL",
    "gn:name":"Zhaokeng",
    "gn:population":0,
    "gn:timezone":"Asia/Shanghai",
    "iso:country":"CN",
    "name:zho_x_preferred":[
        "\u62db\u5751"
    ],
    "wof:name":"Zhaokeng",
    "wof:placetype":"locality"
},
  "geometry": {"coordinates":[117.794,25.01315],"type":"Point"}
}