{
  "type": "Feature",
  "properties": {
    "gn:admin1_code":"26",
    "gn:asciiname":"Diewucun",
    "gn:country_code":"CN",
    "gn:dem":356,
    "gn:feature_class":"P",
    "gn:feature_code":"PPL",
    "gn:name":"Diewucun",
    "gn:population":0,
    "gn:timezone":"Asia/Shanghai",
    "iso:country":"CN",
    "name:zho_x_preferred":[
        "\u789f\u5434\u6751"
    ],
    "name:zho_x_variant":[
        "\u7252\u5434\u6751"
    ],
    "wof:name":"Diewucun",
    "wof:placetype":"locality"
},
  "geometry": {"coordinates":[109.50906000000001,34.69936],"type":"Point"}
}