{
  "type": "Feature",
  "properties": {
    "gn:admin1_code":"32.0",
    "gn:asciiname":"Lengshuiya",
    "gn:country_code":"CN",
    "gn:dem":386,
    "gn:feature_class":"P",
    "gn:feature_code":"PPL",
    "gn:name":"Lengshuiya",
    "gn:population":0,
    "gn:timezone":"Asia/Shanghai",
    "iso:country":"CN",
    "name:zho_x_preferred":[
        "\u51b7\u6c34\u57ad"
    ],
    "wof:name":"Lengshuiya",
    "wof:placetype":"locality"
},
  "geometry": {"coordinates":[105.16057000000001,28.35157],"type":"Point"}
}