{
  "type": "Feature",
  "properties": {
    "gn:admin1_code":"1.0",
    "gn:asciiname":"Zhangcunwancun",
    "gn:country_code":"CN",
    "gn:dem":111,
    "gn:feature_class":"P",
    "gn:feature_code":"PPL",
    "gn:name":"Zhangcunwancun",
    "gn:population":0,
    "gn:timezone":"Asia/Shanghai",
    "iso:country":"CN",
    "name:zho_x_preferred":[
        "\u6f33\u6751\u6e7e\u6751"
    ],
    "wof:name":"Zhangcunwancun",
    "wof:placetype":"locality"
},
  "geometry": {"coordinates":[118.54765999999999,29.80447],"type":"Point"}
}