{
  "type": "Feature",
  "properties": {
    "gn:admin1_code":"4.0",
    "gn:asciiname":"Caozhuangcun",
    "gn:country_code":"CN",
    "gn:dem":26,
    "gn:feature_class":"P",
    "gn:feature_code":"PPL",
    "gn:name":"Caozhuangcun",
    "gn:population":0,
    "gn:timezone":"Asia/Shanghai",
    "iso:country":"CN",
    "name:zho_x_preferred":[
        "\u66f9\u5e84\u6751"
    ],
    "wof:name":"Caozhuangcun",
    "wof:placetype":"locality"
},
  "geometry": {"coordinates":[118.0545,33.92249],"type":"Point"}
}