{
  "type": "Feature",
  "properties": {
    "gn:admin1_code":"30.0",
    "gn:asciiname":"Guheshi",
    "gn:country_code":"CN",
    "gn:dem":23,
    "gn:feature_class":"P",
    "gn:feature_code":"PPL",
    "gn:name":"Guheshi",
    "gn:population":0,
    "gn:timezone":"Asia/Shanghai",
    "iso:country":"CN",
    "name:zho_x_preferred":[
        "\u53e4\u5408\u77f3"
    ],
    "wof:name":"Guheshi",
    "wof:placetype":"locality"
},
  "geometry": {"coordinates":[112.9409,22.1118],"type":"Point"}
}