{
  "type": "Feature",
  "properties": {
    "gn:admin1_code":"29.0",
    "gn:asciiname":"Muguaqinggou",
    "gn:country_code":"CN",
    "gn:dem":1784,
    "gn:feature_class":"P",
    "gn:feature_code":"PPL",
    "gn:name":"Muguaqinggou",
    "gn:population":0,
    "gn:timezone":"Asia/Shanghai",
    "iso:country":"CN",
    "name:zho_x_preferred":[
        "\u6728\u74dc\u7b90\u6c9f"
    ],
    "wof:name":"Muguaqinggou",
    "wof:placetype":"locality"
},
  "geometry": {"coordinates":[99.2805,25.5854],"type":"Point"}
}