{
  "type": "Feature",
  "properties": {
    "gn:admin1_code":"29.0",
    "gn:asciiname":"Aciluo",
    "gn:country_code":"CN",
    "gn:dem":1937,
    "gn:feature_class":"P",
    "gn:feature_code":"PPL",
    "gn:name":"Aciluo",
    "gn:population":0,
    "gn:timezone":"Asia/Shanghai",
    "iso:country":"CN",
    "name:zho_x_preferred":[
        "\u963f\u6b21\u7f57"
    ],
    "wof:name":"Aciluo",
    "wof:placetype":"locality"
},
  "geometry": {"coordinates":[100.55800000000001,27.3603],"type":"Point"}
}