{
  "type": "Feature",
  "properties": {
    "gn:admin1_code":"9.0",
    "gn:asciiname":"Yuzang",
    "gn:country_code":"CN",
    "gn:dem":514,
    "gn:feature_class":"P",
    "gn:feature_code":"PPL",
    "gn:name":"Yuzang",
    "gn:population":0,
    "gn:timezone":"Asia/Shanghai",
    "iso:country":"CN",
    "name:und_x_variant":[
        "\u7389\u846c",
        "Yuzang"
    ],
    "wof:name":"Yuzang",
    "wof:placetype":"locality"
},
  "geometry": {"coordinates":[112.01931,33.51102],"type":"Point"}
}