{
  "type": "Feature",
  "properties": {
    "gn:admin1_code":"10",
    "gn:asciiname":"Batagou",
    "gn:country_code":"CN",
    "gn:dem":1564,
    "gn:feature_class":"P",
    "gn:feature_code":"PPL",
    "gn:name":"Batagou",
    "gn:population":0,
    "gn:timezone":"Asia/Shanghai",
    "iso:country":"CN",
    "name:zho_x_preferred":[
        "\u516b\u5854\u6c9f"
    ],
    "wof:name":"Batagou",
    "wof:placetype":"locality"
},
  "geometry": {"coordinates":[115.47745,41.30489],"type":"Point"}
}