{
  "type": "Feature",
  "properties": {
    "gn:admin1_code":"32.0",
    "gn:asciiname":"Tongziyuan",
    "gn:country_code":"CN",
    "gn:dem":807,
    "gn:feature_class":"P",
    "gn:feature_code":"PPL",
    "gn:name":"Tongziyuan",
    "gn:population":0,
    "gn:timezone":"Asia/Shanghai",
    "iso:country":"CN",
    "name:zho_x_preferred":[
        "\u94dc\u5b50\u9662"
    ],
    "wof:name":"Tongziyuan",
    "wof:placetype":"locality"
},
  "geometry": {"coordinates":[108.08812,31.58638],"type":"Point"}
}