{
  "type": "Feature",
  "properties": {
    "gn:admin1_code":"12.0",
    "gn:asciiname":"Xiadiyuan",
    "gn:country_code":"CN",
    "gn:dem":88,
    "gn:feature_class":"P",
    "gn:feature_code":"PPL",
    "gn:name":"Xiadiyuan",
    "gn:population":0,
    "gn:timezone":"Asia/Shanghai",
    "iso:country":"CN",
    "name:zho_x_preferred":[
        "Xiadiyuan"
    ],
    "name:zho_x_variant":[
        "\u4e0b\u5730\u6e90"
    ],
    "wof:name":"Xiadiyuan",
    "wof:placetype":"locality"
},
  "geometry": {"coordinates":[115.06294,29.59059],"type":"Point"}
}