{
  "type": "Feature",
  "properties": {
    "gn:admin1_code":"29.0",
    "gn:asciiname":"Salang",
    "gn:country_code":"CN",
    "gn:dem":839,
    "gn:feature_class":"P",
    "gn:feature_code":"PPL",
    "gn:name":"Salang",
    "gn:population":0,
    "gn:timezone":"Asia/Shanghai",
    "iso:country":"CN",
    "name:cat_x_preferred":[
        "Salang"
    ],
    "name:ceb_x_preferred":[
        "Salang"
    ],
    "name:new_x_preferred":[
        "\u0938\u0932\u093e\u0919"
    ],
    "name:swe_x_preferred":[
        "Salang"
    ],
    "name:zho_x_preferred":[
        "\u6492\u6994"
    ],
    "wof:name":"Salang",
    "wof:placetype":"locality"
},
  "geometry": {"coordinates":[100.095,23.4012],"type":"Point"}
}