{
  "type": "Feature",
  "properties": {
    "gn:admin1_code":"26.0",
    "gn:asciiname":"Hanjiayuan",
    "gn:country_code":"CN",
    "gn:dem":794,
    "gn:feature_class":"P",
    "gn:feature_code":"PPL",
    "gn:name":"Hanjiayuan",
    "gn:population":0,
    "gn:timezone":"Asia/Shanghai",
    "iso:country":"CN",
    "name:zho_x_preferred":[
        "\u97e9\u5bb6\u9662"
    ],
    "wof:name":"Hanjiayuan",
    "wof:placetype":"locality"
},
  "geometry": {"coordinates":[109.93275,32.63145],"type":"Point"}
}