{
  "type": "Feature",
  "properties": {
    "gn:admin1_code":"12",
    "gn:asciiname":"Lanhepu",
    "gn:cc2":"CN",
    "gn:country_code":"CN",
    "gn:dem":248,
    "gn:feature_class":"P",
    "gn:feature_code":"PPL",
    "gn:name":"Lanhepu",
    "gn:population":0,
    "gn:timezone":"Asia/Shanghai",
    "iso:country":"CN",
    "name:und_x_variant":[
        "Lan-ho-p\u2019u",
        "Lanhepu"
    ],
    "wof:name":"Lanhepu",
    "wof:placetype":"locality"
},
  "geometry": {"coordinates":[109.77583,32.89056],"type":"Point"}
}