{
  "type": "Feature",
  "properties": {
    "gn:admin1_code":"10.0",
    "gn:asciiname":"Zhennei",
    "gn:cc2":"CN",
    "gn:country_code":"CN",
    "gn:dem":44,
    "gn:feature_class":"P",
    "gn:feature_code":"PPL",
    "gn:name":"Zhennei",
    "gn:population":0,
    "gn:timezone":"Asia/Shanghai",
    "iso:country":"CN",
    "name:und_x_variant":[
        "Chen-nei",
        "Dongzhen",
        "Zhennei"
    ],
    "wof:name":"Zhennei",
    "wof:placetype":"locality"
},
  "geometry": {"coordinates":[114.65000000000001,37.45],"type":"Point"}
}