{
  "type": "Feature",
  "properties": {
    "gn:admin1_code":"30.0",
    "gn:asciiname":"Tangtou",
    "gn:country_code":"CN",
    "gn:dem":74,
    "gn:feature_class":"P",
    "gn:feature_code":"PPL",
    "gn:name":"Tangtou",
    "gn:population":0,
    "gn:timezone":"Asia/Shanghai",
    "iso:country":"CN",
    "name:zho_x_preferred":[
        "Tangtou"
    ],
    "name:zho_x_variant":[
        "\u5858\u5934"
    ],
    "wof:name":"Tangtou",
    "wof:placetype":"locality"
},
  "geometry": {"coordinates":[113.44513000000001,24.93659],"type":"Point"}
}