{
  "type": "Feature",
  "properties": {
    "gn:admin1_code":"14.0",
    "gn:asciiname":"Goggyi",
    "gn:country_code":"CN",
    "gn:dem":3868,
    "gn:feature_class":"P",
    "gn:feature_code":"PPL",
    "gn:name":"Goggyi",
    "gn:population":0,
    "gn:timezone":"Asia/Urumqi",
    "iso:country":"CN",
    "name:bod_x_preferred":[
        "Goggyi"
    ],
    "name:zho_x_preferred":[
        "Guoji"
    ],
    "name:zho_x_variant":[
        "\u679c\u9645"
    ],
    "wof:name":"Goggyi",
    "wof:placetype":"locality"
},
  "geometry": {"coordinates":[91.10299999999999,29.903],"type":"Point"}
}