{
  "type": "Feature",
  "properties": {
    "gn:admin1_code":"14",
    "gn:asciiname":"Qinglu",
    "gn:country_code":"CN",
    "gn:dem":3571,
    "gn:feature_class":"P",
    "gn:feature_code":"PPL",
    "gn:name":"Qinglu",
    "gn:population":0,
    "gn:timezone":"Asia/Urumqi",
    "iso:country":"CN",
    "name:bod_x_preferred":[
        "\u0f56\u0fb1\u0f72\u0f44\u0f0b\u0f40\u0fb3\u0f74"
    ],
    "name:und_x_variant":[
        "Jinlu"
    ],
    "name:zho_x_preferred":[
        "\u91d1\u9c81"
    ],
    "wof:name":"Qinglu",
    "wof:placetype":"locality"
},
  "geometry": {"coordinates":[91.61584999999999,29.2548],"type":"Point"}
}