{
  "type": "Feature",
  "properties": {
    "gn:admin1_code":"14.0",
    "gn:asciiname":"Pala",
    "gn:country_code":"CN",
    "gn:dem":4924,
    "gn:feature_class":"P",
    "gn:feature_code":"PPL",
    "gn:name":"Pala",
    "gn:population":0,
    "gn:timezone":"Asia/Urumqi",
    "iso:country":"CN",
    "name:zho_x_preferred":[
        "\u5e15\u62c9"
    ],
    "wof:name":"Pala",
    "wof:placetype":"locality"
},
  "geometry": {"coordinates":[87.9161,29.9476],"type":"Point"}
}