{
  "type": "Feature",
  "properties": {
    "gn:admin1_code":"3.0",
    "gn:asciiname":"Xutangcun",
    "gn:country_code":"CN",
    "gn:dem":329,
    "gn:feature_class":"P",
    "gn:feature_code":"PPL",
    "gn:name":"Xutangcun",
    "gn:population":0,
    "gn:timezone":"Asia/Shanghai",
    "iso:country":"CN",
    "name:und_x_variant":[
        "\u5729\u5858\u6751"
    ],
    "wof:name":"Xutangcun",
    "wof:placetype":"locality"
},
  "geometry": {"coordinates":[115.9511,26.61466],"type":"Point"}
}