{
  "type": "Feature",
  "properties": {
    "gn:admin1_code":"32.0",
    "gn:asciiname":"Shujiahe",
    "gn:country_code":"CN",
    "gn:dem":461,
    "gn:feature_class":"P",
    "gn:feature_code":"PPL",
    "gn:name":"Shujiahe",
    "gn:population":0,
    "gn:timezone":"Asia/Shanghai",
    "iso:country":"CN",
    "name:zho_x_preferred":[
        "\u8212\u5bb6\u6cb3"
    ],
    "wof:name":"Shujiahe",
    "wof:placetype":"locality"
},
  "geometry": {"coordinates":[105.164,30.8099],"type":"Point"}
}