{
  "type": "Feature",
  "properties": {
    "gn:admin1_code":"22.0",
    "gn:asciiname":"Taotiaogoucun",
    "gn:country_code":"CN",
    "gn:dem":543,
    "gn:feature_class":"P",
    "gn:feature_code":"PPL",
    "gn:name":"Taotiaogoucun",
    "gn:population":0,
    "gn:timezone":"Asia/Shanghai",
    "iso:country":"CN",
    "name:zho_x_preferred":[
        "\u6843\u6761\u6c9f\u6751"
    ],
    "wof:name":"Taotiaogoucun",
    "wof:placetype":"locality"
},
  "geometry": {"coordinates":[116.53306000000001,40.63606],"type":"Point"}
}