{
  "type": "Feature",
  "properties": {
    "gn:admin1_code":"19.0",
    "gn:asciiname":"Daziying",
    "gn:country_code":"CN",
    "gn:dem":17,
    "gn:feature_class":"P",
    "gn:feature_code":"PPL",
    "gn:name":"Daziying",
    "gn:population":0,
    "gn:timezone":"Asia/Shanghai",
    "iso:country":"CN",
    "name:zho_x_preferred":[
        "\u8fbe\u5b50\u8425"
    ],
    "wof:name":"Daziying",
    "wof:placetype":"locality"
},
  "geometry": {"coordinates":[121.75700000000001,39.7242],"type":"Point"}
}