{
  "type": "Feature",
  "properties": {
    "gn:admin1_code":"3.0",
    "gn:asciiname":"Biantan Fenchang",
    "gn:country_code":"CN",
    "gn:dem":15,
    "gn:feature_class":"P",
    "gn:feature_code":"PPL",
    "gn:name":"Biantan Fenchang",
    "gn:population":0,
    "gn:timezone":"Asia/Shanghai",
    "iso:country":"CN",
    "name:und_x_variant":[
        "\u8fb9\u575b\u5206\u573a"
    ],
    "wof:name":"Biantan Fenchang",
    "wof:placetype":"locality"
},
  "geometry": {"coordinates":[116.22611999999999,28.78638],"type":"Point"}
}