{
  "type": "Feature",
  "properties": {
    "gn:admin1_code":"30.0",
    "gn:asciiname":"Yangdigang",
    "gn:country_code":"CN",
    "gn:dem":396,
    "gn:feature_class":"P",
    "gn:feature_code":"PPL",
    "gn:name":"Yangdigang",
    "gn:population":0,
    "gn:timezone":"Asia/Urumqi",
    "iso:country":"CN",
    "name:zho_x_preferred":[
        "\u79e7\u5730\u5c97"
    ],
    "wof:name":"Yangdigang",
    "wof:placetype":"locality"
},
  "geometry": {"coordinates":[111.18389000000001,22.58603],"type":"Point"}
}