{
  "type": "Feature",
  "properties": {
    "gn:admin1_code":"32.0",
    "gn:asciiname":"Yueguang",
    "gn:country_code":"CN",
    "gn:dem":778,
    "gn:feature_class":"P",
    "gn:feature_code":"PPL",
    "gn:name":"Yueguang",
    "gn:population":0,
    "gn:timezone":"Asia/Shanghai",
    "iso:country":"CN",
    "name:zho_x_preferred":[
        "\u6708\u5149"
    ],
    "wof:name":"Yueguang",
    "wof:placetype":"locality"
},
  "geometry": {"coordinates":[103.004,30.2403],"type":"Point"}
}