{
  "type": "Feature",
  "properties": {
    "gn:admin1_code":"3.0",
    "gn:asciiname":"Yanggongcun",
    "gn:country_code":"CN",
    "gn:dem":142,
    "gn:feature_class":"P",
    "gn:feature_code":"PPL",
    "gn:name":"Yanggongcun",
    "gn:population":0,
    "gn:timezone":"Asia/Shanghai",
    "iso:country":"CN",
    "name:und_x_variant":[
        "\u6768\u516c\u6751"
    ],
    "wof:name":"Yanggongcun",
    "wof:placetype":"locality"
},
  "geometry": {"coordinates":[115.62611,26.08497],"type":"Point"}
}