{
  "type": "Feature",
  "properties": {
    "gn:admin1_code":"11",
    "gn:asciiname":"Shuangqiaoping",
    "gn:country_code":"CN",
    "gn:dem":53,
    "gn:feature_class":"P",
    "gn:feature_code":"PPLA4",
    "gn:name":"Shuangqiaoping",
    "gn:population":0,
    "gn:timezone":"Asia/Shanghai",
    "iso:country":"CN",
    "name:und_x_variant":[
        "\u53cc\u6865\u576a",
        "Shuangqiaoping Zhen",
        "\u53cc\u6865\u576a\u9547"
    ],
    "wof:name":"Shuangqiaoping",
    "wof:placetype":"locality"
},
  "geometry": {"coordinates":[111.77283,29.2662],"type":"Point"}
}