{
  "type": "Feature",
  "properties": {
    "gn:admin1_code":"11",
    "gn:asciiname":"Huanglongtou",
    "gn:country_code":"CN",
    "gn:dem":234,
    "gn:feature_class":"P",
    "gn:feature_code":"PPL",
    "gn:name":"Huanglongtou",
    "gn:population":0,
    "gn:timezone":"Asia/Shanghai",
    "iso:country":"CN",
    "name:und_x_variant":[
        "\u9ec4\u9f99\u5934",
        "Huanglongtou"
    ],
    "wof:name":"Huanglongtou",
    "wof:placetype":"locality"
},
  "geometry": {"coordinates":[111.98583000000001,25.63056],"type":"Point"}
}