{
  "type": "Feature",
  "properties": {
    "gn:admin1_code":"2.0",
    "gn:asciiname":"Waipokeng",
    "gn:country_code":"CN",
    "gn:dem":413,
    "gn:feature_class":"P",
    "gn:feature_code":"PPL",
    "gn:name":"Waipokeng",
    "gn:population":0,
    "gn:timezone":"Asia/Shanghai",
    "iso:country":"CN",
    "name:zho_x_preferred":[
        "\u5916\u5a46\u5751"
    ],
    "wof:name":"Waipokeng",
    "wof:placetype":"locality"
},
  "geometry": {"coordinates":[120.71429999999999,29.32939],"type":"Point"}
}