{
  "type": "Feature",
  "properties": {
    "gn:admin1_code":"30.0",
    "gn:asciiname":"Huaqingcun",
    "gn:country_code":"CN",
    "gn:dem":12,
    "gn:feature_class":"P",
    "gn:feature_code":"PPL",
    "gn:name":"Huaqingcun",
    "gn:population":0,
    "gn:timezone":"Asia/Shanghai",
    "iso:country":"CN",
    "name:zho_x_preferred":[
        "\u534e\u6e05\u6751"
    ],
    "wof:name":"Huaqingcun",
    "wof:placetype":"locality"
},
  "geometry": {"coordinates":[116.53973000000001,23.08374],"type":"Point"}
}