{
  "type": "Feature",
  "properties": {
    "gn:admin1_code":"10",
    "gn:asciiname":"Binggou",
    "gn:country_code":"CN",
    "gn:dem":257,
    "gn:feature_class":"P",
    "gn:feature_code":"PPL",
    "gn:name":"Binggou",
    "gn:population":0,
    "gn:timezone":"Asia/Shanghai",
    "iso:country":"CN",
    "name:zho_x_preferred":[
        "\u51b0\u6c9f"
    ],
    "wof:name":"Binggou",
    "wof:placetype":"locality"
},
  "geometry": {"coordinates":[118.21465000000001,40.64449000000001],"type":"Point"}
}