{
  "type": "Feature",
  "properties": {
    "gn:admin1_code":"2.0",
    "gn:asciiname":"Yang'ao",
    "gn:country_code":"CN",
    "gn:dem":181,
    "gn:feature_class":"P",
    "gn:feature_code":"PPL",
    "gn:name":"Yang\u2019ao",
    "gn:population":0,
    "gn:timezone":"Asia/Shanghai",
    "iso:country":"CN",
    "name:und_x_variant":[
        "Yang\u2019ao"
    ],
    "name:zho_x_preferred":[
        "\u6d0b\u5c99"
    ],
    "wof:name":"Yang'ao",
    "wof:placetype":"locality"
},
  "geometry": {"coordinates":[120.04537000000001,28.64046],"type":"Point"}
}