{
  "type": "Feature",
  "properties": {
    "gn:admin1_code":"32.0",
    "gn:asciiname":"Galuo",
    "gn:country_code":"CN",
    "gn:dem":2614,
    "gn:feature_class":"P",
    "gn:feature_code":"PPL",
    "gn:name":"Galuo",
    "gn:population":0,
    "gn:timezone":"Asia/Shanghai",
    "iso:country":"CN",
    "name:zho_x_preferred":[
        "\u560e\u6d1b"
    ],
    "wof:name":"Galuo",
    "wof:placetype":"locality"
},
  "geometry": {"coordinates":[101.75801,27.61407],"type":"Point"}
}