{
  "type": "Feature",
  "properties": {
    "gn:admin1_code":"11.0",
    "gn:asciiname":"Caishanchong",
    "gn:country_code":"CN",
    "gn:dem":282,
    "gn:feature_class":"P",
    "gn:feature_code":"PPL",
    "gn:name":"Caishanchong",
    "gn:population":0,
    "gn:timezone":"Asia/Shanghai",
    "iso:country":"CN",
    "name:zho_x_preferred":[
        "\u83dc\u5c71\u51b2"
    ],
    "wof:name":"Caishanchong",
    "wof:placetype":"locality"
},
  "geometry": {"coordinates":[111.81616,27.19419000000001],"type":"Point"}
}