{
  "type": "Feature",
  "properties": {
    "gn:admin1_code":"10",
    "gn:asciiname":"Xishui Yuwai",
    "gn:country_code":"CN",
    "gn:dem":172,
    "gn:feature_class":"P",
    "gn:feature_code":"PPL",
    "gn:name":"Xishui Yuwai",
    "gn:population":0,
    "gn:timezone":"Asia/Shanghai",
    "iso:country":"CN",
    "name:zho_x_preferred":[
        "\u897f\u6c34\u5cea\u5916"
    ],
    "wof:name":"Xishui Yuwai",
    "wof:placetype":"locality"
},
  "geometry": {"coordinates":[118.29592,40.31692],"type":"Point"}
}