{
  "type": "Feature",
  "properties": {
    "gn:admin1_code":"7",
    "gn:asciiname":"Changlingpu",
    "gn:country_code":"CN",
    "gn:dem":95,
    "gn:feature_class":"P",
    "gn:feature_code":"PPL",
    "gn:name":"Changlingpu",
    "gn:population":0,
    "gn:timezone":"Asia/Shanghai",
    "iso:country":"CN",
    "name:zho_x_preferred":[
        "\u957f\u5cad\u57d4"
    ],
    "wof:name":"Changlingpu",
    "wof:placetype":"locality"
},
  "geometry": {"coordinates":[117.59739999999999,24.66455],"type":"Point"}
}