{
  "type": "Feature",
  "properties": {
    "gn:admin1_code":"3.0",
    "gn:asciiname":"Xihuling",
    "gn:country_code":"CN",
    "gn:dem":68,
    "gn:feature_class":"P",
    "gn:feature_code":"PPL",
    "gn:name":"Xihuling",
    "gn:population":0,
    "gn:timezone":"Asia/Shanghai",
    "iso:country":"CN",
    "name:und_x_variant":[
        "\u897f\u6e56\u5cad"
    ],
    "wof:name":"Xihuling",
    "wof:placetype":"locality"
},
  "geometry": {"coordinates":[116.44792,29.70917],"type":"Point"}
}