{
  "type": "Feature",
  "properties": {
    "gn:admin1_code":"32.0",
    "gn:asciiname":"Kaxu",
    "gn:country_code":"CN",
    "gn:dem":3676,
    "gn:feature_class":"P",
    "gn:feature_code":"PPL",
    "gn:name":"Kaxu",
    "gn:population":0,
    "gn:timezone":"Asia/Shanghai",
    "iso:country":"CN",
    "name:zho_x_preferred":[
        "\u5361\u987b"
    ],
    "wof:name":"Kaxu",
    "wof:placetype":"locality"
},
  "geometry": {"coordinates":[98.68259999999999,31.6982],"type":"Point"}
}