{
  "type": "Feature",
  "properties": {
    "gn:admin1_code":"18",
    "gn:asciiname":"Hegoubian",
    "gn:country_code":"CN",
    "gn:dem":1422,
    "gn:feature_class":"P",
    "gn:feature_code":"PPL",
    "gn:name":"Hegoubian",
    "gn:population":0,
    "gn:timezone":"Asia/Shanghai",
    "iso:country":"CN",
    "name:zho_x_preferred":[
        "\u6cb3\u6c9f\u8fb9"
    ],
    "wof:name":"Hegoubian",
    "wof:placetype":"locality"
},
  "geometry": {"coordinates":[105.15600000000001,25.2085],"type":"Point"}
}