{
  "type": "Feature",
  "properties": {
    "gn:admin1_code":"30",
    "gn:asciiname":"Feng'an",
    "gn:country_code":"CN",
    "gn:dem":500,
    "gn:feature_class":"P",
    "gn:feature_code":"PPL",
    "gn:name":"Feng\u2019an",
    "gn:population":0,
    "gn:timezone":"Asia/Shanghai",
    "iso:country":"CN",
    "name:zho_x_preferred":[
        "\u4e30\u5b89"
    ],
    "name:zho_x_variant":[
        "Feng\u2019an"
    ],
    "wof:name":"Feng'an",
    "wof:placetype":"locality"
},
  "geometry": {"coordinates":[111.36273,22.22089],"type":"Point"}
}