{
  "type": "Feature",
  "properties": {
    "gn:admin1_code":"01",
    "gn:asciiname":"Tiantang",
    "gn:country_code":"CN",
    "gn:dem":376,
    "gn:feature_class":"P",
    "gn:feature_code":"PPLA3",
    "gn:name":"Tiantang",
    "gn:population":0,
    "gn:timezone":"Asia/Shanghai",
    "iso:country":"CN",
    "name:und_x_variant":[
        "Yaqian",
        "Yuexi",
        "Tiantang",
        "Yuexi Xian"
    ],
    "name:zho_x_preferred":[
        "Ya-ch\u2019ien-chen"
    ],
    "name:zho_x_variant":[
        "Ya-ch\u2019ien",
        "\u5929\u5802",
        "Y\u00fceh-hsi",
        "\u5cb3\u897f\u53bf"
    ],
    "wof:name":"Tiantang",
    "wof:placetype":"locality"
},
  "geometry": {"coordinates":[116.34999999999999,30.85],"type":"Point"}
}