{
  "type": "Feature",
  "properties": {
    "gn:admin1_code":"32.0",
    "gn:asciiname":"Chayuangou",
    "gn:country_code":"CN",
    "gn:dem":1904,
    "gn:feature_class":"P",
    "gn:feature_code":"PPL",
    "gn:name":"Chayuangou",
    "gn:population":0,
    "gn:timezone":"Asia/Shanghai",
    "iso:country":"CN",
    "name:zho_x_preferred":[
        "\u8336\u56ed\u6c9f"
    ],
    "wof:name":"Chayuangou",
    "wof:placetype":"locality"
},
  "geometry": {"coordinates":[102.14238,29.48002],"type":"Point"}
}