{
  "type": "Feature",
  "properties": {
    "gn:admin1_code":"25",
    "gn:asciiname":"Daomenwang",
    "gn:country_code":"CN",
    "gn:dem":11,
    "gn:feature_class":"P",
    "gn:feature_code":"PPL",
    "gn:name":"Daomenwang",
    "gn:population":0,
    "gn:timezone":"Asia/Shanghai",
    "iso:country":"CN",
    "name:zho_x_preferred":[
        "\u9053\u95e8\u738b"
    ],
    "wof:name":"Daomenwang",
    "wof:placetype":"locality"
},
  "geometry": {"coordinates":[117.642,37.5503],"type":"Point"}
}