{
  "type": "Feature",
  "properties": {
    "gn:admin1_code":"19.0",
    "gn:asciiname":"Weijiatang",
    "gn:country_code":"CN",
    "gn:dem":3,
    "gn:feature_class":"P",
    "gn:feature_code":"PPL",
    "gn:name":"Weijiatang",
    "gn:population":0,
    "gn:timezone":"Asia/Shanghai",
    "iso:country":"CN",
    "name:und_x_variant":[
        "\u9b4f\u5bb6\u5858"
    ],
    "wof:name":"Weijiatang",
    "wof:placetype":"locality"
},
  "geometry": {"coordinates":[122.22743,40.80902],"type":"Point"}
}