{
  "type": "Feature",
  "properties": {
    "gn:admin1_code":"13.0",
    "gn:asciiname":"Kailaiyimake",
    "gn:country_code":"CN",
    "gn:dem":1219,
    "gn:feature_class":"P",
    "gn:feature_code":"PPL",
    "gn:name":"Kailaiyimake",
    "gn:population":0,
    "gn:timezone":"Asia/Shanghai",
    "iso:country":"CN",
    "name:zho_x_preferred":[
        "\u5f00\u6765\u4f9d\u9a6c\u514b"
    ],
    "wof:name":"Kailaiyimake",
    "wof:placetype":"locality"
},
  "geometry": {"coordinates":[76.63231999999998,39.30788],"type":"Point"}
}