{
  "type": "Feature",
  "properties": {
    "gn:admin1_code":"19",
    "gn:asciiname":"Ta-chia-ying-tzu",
    "gn:country_code":"CN",
    "gn:dem":471,
    "gn:feature_class":"P",
    "gn:feature_code":"PPL",
    "gn:name":"Ta-chia-ying-tzu",
    "gn:population":0,
    "gn:timezone":"Asia/Shanghai",
    "iso:country":"CN",
    "wof:name":"Ta-chia-ying-tzu",
    "wof:placetype":"locality"
},
  "geometry": {"coordinates":[119.35639,42.29028],"type":"Point"}
}