{
  "type": "Feature",
  "properties": {
    "gn:admin1_code":"22.0",
    "gn:asciiname":"Nanxiangyucun",
    "gn:country_code":"CN",
    "gn:dem":253,
    "gn:feature_class":"P",
    "gn:feature_code":"PPL",
    "gn:name":"Nanxiangyucun",
    "gn:population":0,
    "gn:timezone":"Asia/Shanghai",
    "iso:country":"CN",
    "name:zho_x_preferred":[
        "\u5357\u9999\u5cea\u6751"
    ],
    "wof:name":"Nanxiangyucun",
    "wof:placetype":"locality"
},
  "geometry": {"coordinates":[117.04298,40.61631],"type":"Point"}
}