{
  "type": "Feature",
  "properties": {
    "gn:admin1_code":"3.0",
    "gn:asciiname":"Youya",
    "gn:country_code":"CN",
    "gn:dem":74,
    "gn:feature_class":"P",
    "gn:feature_code":"PPL",
    "gn:name":"Youya",
    "gn:population":0,
    "gn:timezone":"Asia/Shanghai",
    "iso:country":"CN",
    "name:und_x_variant":[
        "\u6e38\u4e9a"
    ],
    "wof:name":"Youya",
    "wof:placetype":"locality"
},
  "geometry": {"coordinates":[114.95893,27.03863],"type":"Point"}
}