{
  "type": "Feature",
  "properties": {
    "gn:admin1_code":"32.0",
    "gn:asciiname":"Dujue",
    "gn:country_code":"CN",
    "gn:dem":2697,
    "gn:feature_class":"P",
    "gn:feature_code":"PPL",
    "gn:name":"Dujue",
    "gn:population":0,
    "gn:timezone":"Asia/Shanghai",
    "iso:country":"CN",
    "name:zho_x_preferred":[
        "\u5835\u89c9"
    ],
    "wof:name":"Dujue",
    "wof:placetype":"locality"
},
  "geometry": {"coordinates":[103.10599999999999,27.9711],"type":"Point"}
}