{
  "type": "Feature",
  "properties": {
    "gn:admin1_code":"26.0",
    "gn:asciiname":"Shangqiaocun",
    "gn:country_code":"CN",
    "gn:dem":1155,
    "gn:feature_class":"P",
    "gn:feature_code":"PPL",
    "gn:name":"Shangqiaocun",
    "gn:population":0,
    "gn:timezone":"Asia/Shanghai",
    "iso:country":"CN",
    "name:zho_x_preferred":[
        "\u4e0a\u6865\u6751"
    ],
    "wof:name":"Shangqiaocun",
    "wof:placetype":"locality"
},
  "geometry": {"coordinates":[109.42615000000001,36.49683],"type":"Point"}
}