{
  "type": "Feature",
  "properties": {
    "gn:admin1_code":"12",
    "gn:asciiname":"Shuiyuesi",
    "gn:country_code":"CN",
    "gn:dem":857,
    "gn:feature_class":"P",
    "gn:feature_code":"PPLA4",
    "gn:name":"Shuiyuesi",
    "gn:population":0,
    "gn:timezone":"Asia/Shanghai",
    "iso:country":"CN",
    "name:und_x_variant":[
        "Shui-y\u00fceh-ssu",
        "Shuiyuesi",
        "Shuiyuesi Zhen"
    ],
    "name:zho_x_preferred":[
        "\u6c34\u6708\u5bfa"
    ],
    "name:zho_x_variant":[
        "\u6c34\u6708\u5bfa\u9547"
    ],
    "wof:name":"Shuiyuesi",
    "wof:placetype":"locality"
},
  "geometry": {"coordinates":[111.01406,31.23853],"type":"Point"}
}