{
  "type": "Feature",
  "properties": {
    "gn:admin1_code":"26.0",
    "gn:asciiname":"Liutaicun",
    "gn:country_code":"CN",
    "gn:dem":1684,
    "gn:feature_class":"P",
    "gn:feature_code":"PPL",
    "gn:name":"Liutaicun",
    "gn:population":0,
    "gn:timezone":"Asia/Shanghai",
    "iso:country":"CN",
    "name:zho_x_preferred":[
        "\u5218\u53f0\u6751"
    ],
    "wof:name":"Liutaicun",
    "wof:placetype":"locality"
},
  "geometry": {"coordinates":[107.55188,37.33287],"type":"Point"}
}