{
  "type": "Feature",
  "properties": {
    "gn:admin1_code":"14.0",
    "gn:asciiname":"Xiatianduo",
    "gn:country_code":"CN",
    "gn:dem":4464,
    "gn:feature_class":"P",
    "gn:feature_code":"PPL",
    "gn:name":"Xiatianduo",
    "gn:population":0,
    "gn:timezone":"Asia/Urumqi",
    "iso:country":"CN",
    "name:zho_x_preferred":[
        "\u4e0b\u6dfb\u591a"
    ],
    "wof:name":"Xiatianduo",
    "wof:placetype":"locality"
},
  "geometry": {"coordinates":[93.92982000000001,31.43121],"type":"Point"}
}