{
  "type": "Feature",
  "properties": {
    "gn:admin1_code":"4.0",
    "gn:asciiname":"Taoyuan",
    "gn:country_code":"CN",
    "gn:dem":5,
    "gn:feature_class":"P",
    "gn:feature_code":"PPLA4",
    "gn:name":"Taoyuan",
    "gn:population":0,
    "gn:timezone":"Asia/Shanghai",
    "iso:country":"CN",
    "name:und_x_variant":[
        "\u6843\u6e90",
        "Taoyuan Zhen",
        "\u6843\u6e90\u9547"
    ],
    "wof:name":"Taoyuan",
    "wof:placetype":"locality"
},
  "geometry": {"coordinates":[120.4948,30.81847],"type":"Point"}
}