{
  "type": "Feature",
  "properties": {
    "gn:admin1_code":"29",
    "gn:asciiname":"Chenwanzhuang",
    "gn:country_code":"CN",
    "gn:dem":1377,
    "gn:feature_class":"P",
    "gn:feature_code":"PPL",
    "gn:name":"Chenwanzhuang",
    "gn:population":0,
    "gn:timezone":"Asia/Shanghai",
    "iso:country":"CN",
    "name:zho_x_preferred":[
        "\u9648\u4e07\u5e84"
    ],
    "wof:name":"Chenwanzhuang",
    "wof:placetype":"locality"
},
  "geometry": {"coordinates":[101.98999999999999,24.8817],"type":"Point"}
}