{
  "type": "Feature",
  "properties": {
    "gn:admin1_code":"29.0",
    "gn:asciiname":"Shaojiaying",
    "gn:country_code":"CN",
    "gn:dem":1757,
    "gn:feature_class":"P",
    "gn:feature_code":"PPL",
    "gn:name":"Shaojiaying",
    "gn:population":0,
    "gn:timezone":"Asia/Shanghai",
    "iso:country":"CN",
    "name:zho_x_preferred":[
        "\u90b5\u5bb6\u8425"
    ],
    "wof:name":"Shaojiaying",
    "wof:placetype":"locality"
},
  "geometry": {"coordinates":[98.54089999999999,25.1168],"type":"Point"}
}