{
  "type": "Feature",
  "properties": {
    "gn:admin1_code":"10",
    "gn:asciiname":"Wangjiayingzi",
    "gn:country_code":"CN",
    "gn:dem":777,
    "gn:feature_class":"P",
    "gn:feature_code":"PPL",
    "gn:name":"Wangjiayingzi",
    "gn:population":0,
    "gn:timezone":"Asia/Shanghai",
    "iso:country":"CN",
    "name:zho_x_preferred":[
        "\u738b\u5bb6\u8425\u5b50"
    ],
    "wof:name":"Wangjiayingzi",
    "wof:placetype":"locality"
},
  "geometry": {"coordinates":[118.57849,41.12906],"type":"Point"}
}