{
  "type": "Feature",
  "properties": {
    "gn:admin1_code":"29.0",
    "gn:asciiname":"Xiaolian",
    "gn:country_code":"CN",
    "gn:dem":2198,
    "gn:feature_class":"P",
    "gn:feature_code":"PPL",
    "gn:name":"Xiaolian",
    "gn:population":0,
    "gn:timezone":"Asia/Shanghai",
    "iso:country":"CN",
    "name:fra_x_preferred":[
        "Xiaolian"
    ],
    "name:zho_x_preferred":[
        "\u5b5d\u5ec9"
    ],
    "wof:name":"Xiaolian",
    "wof:placetype":"locality"
},
  "geometry": {"coordinates":[100.194,26.5096],"type":"Point"}
}