{
  "type": "Feature",
  "properties": {
    "gn:admin1_code":"16.0",
    "gn:asciiname":"Sixiantian",
    "gn:country_code":"CN",
    "gn:dem":561,
    "gn:feature_class":"P",
    "gn:feature_code":"PPL",
    "gn:name":"Sixiantian",
    "gn:population":0,
    "gn:timezone":"Asia/Shanghai",
    "iso:country":"CN",
    "name:zho_x_preferred":[
        "\u4e1d\u7ebf\u7530"
    ],
    "wof:name":"Sixiantian",
    "wof:placetype":"locality"
},
  "geometry": {"coordinates":[111.008,24.7298],"type":"Point"}
}