{
  "type": "Feature",
  "properties": {
    "gn:admin1_code":"4.0",
    "gn:asciiname":"Xingang",
    "gn:country_code":"CN",
    "gn:dem":5,
    "gn:feature_class":"P",
    "gn:feature_code":"PPLA4",
    "gn:name":"Xingang",
    "gn:population":0,
    "gn:timezone":"Asia/Shanghai",
    "iso:country":"CN",
    "name:und_x_variant":[
        "\u65b0\u6e2f",
        "Xingang Zhen",
        "\u65b0\u6e2f\u9547"
    ],
    "wof:name":"Xingang",
    "wof:placetype":"locality"
},
  "geometry": {"coordinates":[120.92010999999999,31.72511],"type":"Point"}
}