{
  "type": "Feature",
  "properties": {
    "gn:admin1_code":"4.0",
    "gn:asciiname":"Puzi Xinxu",
    "gn:country_code":"CN",
    "gn:dem":0,
    "gn:feature_class":"P",
    "gn:feature_code":"PPL",
    "gn:name":"Puzi Xinxu",
    "gn:population":0,
    "gn:timezone":"Asia/Shanghai",
    "iso:country":"CN",
    "name:zho_x_preferred":[
        "\u666e\u5b50\u65b0\u5729"
    ],
    "wof:name":"Puzi Xinxu",
    "wof:placetype":"locality"
},
  "geometry": {"coordinates":[120.31292000000001,31.985],"type":"Point"}
}