{
  "type": "Feature",
  "properties": {
    "gn:admin1_code":"2.0",
    "gn:asciiname":"Baozhu",
    "gn:country_code":"CN",
    "gn:dem":105,
    "gn:feature_class":"P",
    "gn:feature_code":"PPL",
    "gn:name":"Baozhu",
    "gn:population":0,
    "gn:timezone":"Asia/Shanghai",
    "iso:country":"CN",
    "name:zho_x_preferred":[
        "\u82de\u7af9"
    ],
    "wof:name":"Baozhu",
    "wof:placetype":"locality"
},
  "geometry": {"coordinates":[120.21402999999999,29.09412],"type":"Point"}
}