{
  "type": "Feature",
  "properties": {
    "gn:admin1_code":"3",
    "gn:asciiname":"Sanjiangkou",
    "gn:country_code":"CN",
    "gn:dem":125,
    "gn:feature_class":"P",
    "gn:feature_code":"PPL",
    "gn:name":"Sanjiangkou",
    "gn:population":0,
    "gn:timezone":"Asia/Shanghai",
    "iso:country":"CN",
    "name:und_x_variant":[
        "\u4e09\u6c5f\u53e3"
    ],
    "wof:name":"Sanjiangkou",
    "wof:placetype":"locality"
},
  "geometry": {"coordinates":[116.96386,27.96208],"type":"Point"}
}