{
  "type": "Feature",
  "properties": {
    "gn:admin1_code":"16",
    "gn:asciiname":"Gaoze",
    "gn:country_code":"CN",
    "gn:dem":235,
    "gn:feature_class":"P",
    "gn:feature_code":"PPL",
    "gn:name":"Gaoze",
    "gn:population":0,
    "gn:timezone":"Asia/Shanghai",
    "iso:country":"CN",
    "name:zho_x_preferred":[
        "\u9ad8\u6cfd"
    ],
    "wof:name":"Gaoze",
    "wof:placetype":"locality"
},
  "geometry": {"coordinates":[110.699,25.5287],"type":"Point"}
}