{
  "type": "Feature",
  "properties": {
    "gn:admin1_code":"2.0",
    "gn:asciiname":"Jinpu",
    "gn:country_code":"CN",
    "gn:dem":793,
    "gn:feature_class":"P",
    "gn:feature_code":"PPL",
    "gn:name":"Jinpu",
    "gn:population":0,
    "gn:timezone":"Asia/Shanghai",
    "iso:country":"CN",
    "name:zho_x_preferred":[
        "\u91d1\u94fa"
    ],
    "wof:name":"Jinpu",
    "wof:placetype":"locality"
},
  "geometry": {"coordinates":[119.06453,28.29682],"type":"Point"}
}