{
  "type": "Feature",
  "properties": {
    "gn:admin1_code":"5.0",
    "gn:asciiname":"Shiyangcun",
    "gn:country_code":"CN",
    "gn:dem":220,
    "gn:feature_class":"P",
    "gn:feature_code":"PPL",
    "gn:name":"Shiyangcun",
    "gn:population":0,
    "gn:timezone":"Asia/Shanghai",
    "iso:country":"CN",
    "name:zho_x_preferred":[
        "\u77f3\u7f8a\u6751"
    ],
    "wof:name":"Shiyangcun",
    "wof:placetype":"locality"
},
  "geometry": {"coordinates":[126.19301000000002,44.47217],"type":"Point"}
}