{
  "type": "Feature",
  "properties": {
    "gn:admin1_code":"8.0",
    "gn:asciiname":"Pushilutun",
    "gn:country_code":"CN",
    "gn:dem":278,
    "gn:feature_class":"P",
    "gn:feature_code":"PPL",
    "gn:name":"Pushilutun",
    "gn:population":0,
    "gn:timezone":"Asia/Shanghai",
    "iso:country":"CN",
    "name:zho_x_preferred":[
        "\u6d66\u4e16\u7984\u5c6f"
    ],
    "wof:name":"Pushilutun",
    "wof:placetype":"locality"
},
  "geometry": {"coordinates":[126.33892,47.73556],"type":"Point"}
}