{
  "type": "Feature",
  "properties": {
    "gn:admin1_code":"26.0",
    "gn:asciiname":"Liangquancun",
    "gn:country_code":"CN",
    "gn:dem":1099,
    "gn:feature_class":"P",
    "gn:feature_code":"PPL",
    "gn:name":"Liangquancun",
    "gn:population":0,
    "gn:timezone":"Asia/Shanghai",
    "iso:country":"CN",
    "name:zho_x_preferred":[
        "\u51c9\u6cc9\u6751"
    ],
    "wof:name":"Liangquancun",
    "wof:placetype":"locality"
},
  "geometry": {"coordinates":[109.36669999999999,35.23801],"type":"Point"}
}