{
  "type": "Feature",
  "properties": {
    "gn:admin1_code":"1.0",
    "gn:asciiname":"Gangkouwan",
    "gn:country_code":"CN",
    "gn:dem":81,
    "gn:feature_class":"P",
    "gn:feature_code":"PPL",
    "gn:name":"Gangkouwan",
    "gn:population":0,
    "gn:timezone":"Asia/Shanghai",
    "iso:country":"CN",
    "name:und_x_variant":[
        "\u6e2f\u53e3\u6e7e"
    ],
    "wof:name":"Gangkouwan",
    "wof:placetype":"locality"
},
  "geometry": {"coordinates":[118.87689,30.59645],"type":"Point"}
}