{
  "type": "Feature",
  "properties": {
    "gn:admin1_code":"29.0",
    "gn:asciiname":"Laoniqing",
    "gn:country_code":"CN",
    "gn:dem":2270,
    "gn:feature_class":"P",
    "gn:feature_code":"PPL",
    "gn:name":"Laoniqing",
    "gn:population":0,
    "gn:timezone":"Asia/Shanghai",
    "iso:country":"CN",
    "name:zho_x_preferred":[
        "\u8001\u6ce5\u7b90"
    ],
    "wof:name":"Laoniqing",
    "wof:placetype":"locality"
},
  "geometry": {"coordinates":[101.46299999999999,25.6888],"type":"Point"}
}