{
  "type": "Feature",
  "properties": {
    "gn:admin1_code":"9.0",
    "gn:asciiname":"Fulizhuang",
    "gn:country_code":"CN",
    "gn:dem":68,
    "gn:feature_class":"P",
    "gn:feature_code":"PPL",
    "gn:name":"Fulizhuang",
    "gn:population":0,
    "gn:timezone":"Asia/Shanghai",
    "iso:country":"CN",
    "name:zho_x_preferred":[
        "\u4ed8\u91cc\u5e84"
    ],
    "wof:name":"Fulizhuang",
    "wof:placetype":"locality"
},
  "geometry": {"coordinates":[114.63905,34.6497],"type":"Point"}
}