{
  "type": "Feature",
  "properties": {
    "gn:admin1_code":"4.0",
    "gn:asciiname":"Zhengchangcun",
    "gn:country_code":"CN",
    "gn:dem":5,
    "gn:feature_class":"P",
    "gn:feature_code":"PPL",
    "gn:name":"Zhengchangcun",
    "gn:population":0,
    "gn:timezone":"Asia/Shanghai",
    "iso:country":"CN",
    "name:und_x_variant":[
        "Chen-ch\u2019ang-chen",
        "Cheng-ch\u2019ang",
        "Chen-ch\u2019ang",
        "Chen-hou-chen",
        "Zhengchang",
        "\u6b63\u573a",
        "Zhengchangcun"
    ],
    "name:zho_x_preferred":[
        "\u6b63\u573a\u6751"
    ],
    "wof:name":"Zhengchangcun",
    "wof:placetype":"locality"
},
  "geometry": {"coordinates":[121.02289,32.0437],"type":"Point"}
}