{
  "type": "Feature",
  "properties": {
    "gn:admin1_code":"18.0",
    "gn:asciiname":"Kaji",
    "gn:country_code":"CN",
    "gn:dem":600,
    "gn:feature_class":"P",
    "gn:feature_code":"PPL",
    "gn:name":"Kaji",
    "gn:population":0,
    "gn:timezone":"Asia/Shanghai",
    "iso:country":"CN",
    "name:ceb_x_preferred":[
        "Kaji"
    ],
    "name:deu_x_preferred":[
        "Kaji"
    ],
    "name:rus_x_preferred":[
        "\u041a\u0430\u0434\u0437\u0438"
    ],
    "name:swe_x_preferred":[
        "Kaji"
    ],
    "name:zho_x_preferred":[
        "\u5361\u8bb0"
    ],
    "wof:name":"Kaji",
    "wof:placetype":"locality"
},
  "geometry": {"coordinates":[108.012,25.2467],"type":"Point"}
}