{
  "type": "Feature",
  "properties": {
    "gn:admin1_code":"02",
    "gn:asciiname":"Shanwai",
    "gn:country_code":"CN",
    "gn:dem":124,
    "gn:feature_class":"P",
    "gn:feature_code":"PPL",
    "gn:name":"Shanwai",
    "gn:population":0,
    "gn:timezone":"Asia/Shanghai",
    "iso:country":"CN",
    "name:zho_x_preferred":[
        "\u5c71\u5916"
    ],
    "wof:name":"Shanwai",
    "wof:placetype":"locality"
},
  "geometry": {"coordinates":[121.21344999999999,28.05723],"type":"Point"}
}