{
  "type": "Feature",
  "properties": {
    "gn:admin1_code":"15.0",
    "gn:asciiname":"Shuangying",
    "gn:country_code":"CN",
    "gn:dem":2215,
    "gn:feature_class":"P",
    "gn:feature_code":"PPL",
    "gn:name":"Shuangying",
    "gn:population":0,
    "gn:timezone":"Asia/Shanghai",
    "iso:country":"CN",
    "name:zho_x_preferred":[
        "\u53cc\u8425"
    ],
    "wof:name":"Shuangying",
    "wof:placetype":"locality"
},
  "geometry": {"coordinates":[100.67,38.5067],"type":"Point"}
}