{
  "type": "Feature",
  "properties": {
    "gn:admin1_code":"16.0",
    "gn:asciiname":"Zhiguang",
    "gn:country_code":"CN",
    "gn:dem":114,
    "gn:feature_class":"P",
    "gn:feature_code":"PPL",
    "gn:name":"Zhiguang",
    "gn:population":0,
    "gn:timezone":"Asia/Shanghai",
    "iso:country":"CN",
    "name:zho_x_preferred":[
        "\u5fd7\u5e7f"
    ],
    "wof:name":"Zhiguang",
    "wof:placetype":"locality"
},
  "geometry": {"coordinates":[109.163,23.2433],"type":"Point"}
}