{
  "type": "Feature",
  "properties": {
    "gn:admin1_code":"18",
    "gn:asciiname":"Yakoushang",
    "gn:country_code":"CN",
    "gn:dem":1084,
    "gn:feature_class":"P",
    "gn:feature_code":"PPL",
    "gn:name":"Yakoushang",
    "gn:population":0,
    "gn:timezone":"Asia/Shanghai",
    "iso:country":"CN",
    "name:zho_x_preferred":[
        "\u5d16\u53e3\u4e0a"
    ],
    "wof:name":"Yakoushang",
    "wof:placetype":"locality"
},
  "geometry": {"coordinates":[104.98699999999999,24.948],"type":"Point"}
}