{
  "type": "Feature",
  "properties": {
    "gn:admin1_code":"26",
    "gn:asciiname":"Shuiducun",
    "gn:country_code":"CN",
    "gn:dem":502,
    "gn:feature_class":"P",
    "gn:feature_code":"PPL",
    "gn:name":"Shuiducun",
    "gn:population":0,
    "gn:timezone":"Asia/Shanghai",
    "iso:country":"CN",
    "name:zho_x_preferred":[
        "\u6c34\u6e21\u6751"
    ],
    "wof:name":"Shuiducun",
    "wof:placetype":"locality"
},
  "geometry": {"coordinates":[109.37354000000001,34.93763],"type":"Point"}
}