{
  "type": "Feature",
  "properties": {
    "gn:admin1_code":"32.0",
    "gn:asciiname":"Jueba",
    "gn:country_code":"CN",
    "gn:dem":1916,
    "gn:feature_class":"P",
    "gn:feature_code":"PPL",
    "gn:name":"Jueba",
    "gn:population":0,
    "gn:timezone":"Asia/Shanghai",
    "iso:country":"CN",
    "name:zho_x_preferred":[
        "\u89c9\u5df4"
    ],
    "wof:name":"Jueba",
    "wof:placetype":"locality"
},
  "geometry": {"coordinates":[102.482,28.483],"type":"Point"}
}