{
  "type": "Feature",
  "properties": {
    "gn:admin1_code":"29.0",
    "gn:asciiname":"Mengdui",
    "gn:country_code":"CN",
    "gn:dem":2196,
    "gn:feature_class":"P",
    "gn:feature_code":"PPL",
    "gn:name":"Mengdui",
    "gn:population":0,
    "gn:timezone":"Asia/Shanghai",
    "iso:country":"CN",
    "name:zho_x_preferred":[
        "\u52d0\u5806"
    ],
    "wof:name":"Mengdui",
    "wof:placetype":"locality"
},
  "geometry": {"coordinates":[98.7636,24.2566],"type":"Point"}
}