{
  "type": "Feature",
  "properties": {
    "gn:admin1_code":"19",
    "gn:asciiname":"Daba",
    "gn:cc2":"CN",
    "gn:country_code":"CN",
    "gn:dem":112,
    "gn:feature_class":"P",
    "gn:feature_code":"PPL",
    "gn:name":"Daba",
    "gn:population":0,
    "gn:timezone":"Asia/Shanghai",
    "iso:country":"CN",
    "name:ceb_x_preferred":[
        "Daba"
    ],
    "name:fra_x_preferred":[
        "Daba"
    ],
    "name:kat_x_preferred":[
        "\u10d3\u10d0\u10d1\u10d0"
    ],
    "name:rus_x_preferred":[
        "\u0414\u0430\u0431\u0430"
    ],
    "name:swe_x_preferred":[
        "Daba"
    ],
    "name:und_x_variant":[
        "Ta-pa",
        "Daba"
    ],
    "wof:name":"Daba",
    "wof:placetype":"locality"
},
  "geometry": {"coordinates":[121.99556,42.0975],"type":"Point"}
}