{
  "type": "Feature",
  "properties": {
    "gn:admin1_code":"4.0",
    "gn:asciiname":"Maogang",
    "gn:country_code":"CN",
    "gn:dem":-1,
    "gn:feature_class":"P",
    "gn:feature_code":"PPL",
    "gn:name":"Maogang",
    "gn:population":0,
    "gn:timezone":"Asia/Shanghai",
    "iso:country":"CN",
    "name:zho_x_preferred":[
        "Maogang"
    ],
    "name:zho_x_variant":[
        "\u5192\u6e2f"
    ],
    "wof:name":"Maogang",
    "wof:placetype":"locality"
},
  "geometry": {"coordinates":[119.86328,33.77753],"type":"Point"}
}