{
  "type": "Feature",
  "properties": {
    "gn:admin1_code":"5.0",
    "gn:asciiname":"Nangangzi",
    "gn:country_code":"CN",
    "gn:dem":335,
    "gn:feature_class":"P",
    "gn:feature_code":"PPL",
    "gn:name":"Nangangzi",
    "gn:population":0,
    "gn:timezone":"Asia/Shanghai",
    "iso:country":"CN",
    "name:zho_x_preferred":[
        "\u5357\u5c97\u5b50"
    ],
    "wof:name":"Nangangzi",
    "wof:placetype":"locality"
},
  "geometry": {"coordinates":[125.60137,42.45039000000001],"type":"Point"}
}