{
  "type": "Feature",
  "properties": {
    "gn:admin1_code":"10",
    "gn:asciiname":"Sunjialiang",
    "gn:country_code":"CN",
    "gn:dem":1356,
    "gn:feature_class":"P",
    "gn:feature_code":"PPL",
    "gn:name":"Sunjialiang",
    "gn:population":0,
    "gn:timezone":"Asia/Shanghai",
    "iso:country":"CN",
    "name:zho_x_preferred":[
        "\u5b59\u5bb6\u6881"
    ],
    "wof:name":"Sunjialiang",
    "wof:placetype":"locality"
},
  "geometry": {"coordinates":[114.36798,41.6185],"type":"Point"}
}