{
  "type": "Feature",
  "properties": {
    "gn:admin1_code":"32.0",
    "gn:asciiname":"Geta",
    "gn:country_code":"CN",
    "gn:dem":3828,
    "gn:feature_class":"P",
    "gn:feature_code":"PPL",
    "gn:name":"Geta",
    "gn:population":0,
    "gn:timezone":"Asia/Shanghai",
    "iso:country":"CN",
    "name:zho_x_preferred":[
        "\u5404\u5854"
    ],
    "wof:name":"Geta",
    "wof:placetype":"locality"
},
  "geometry": {"coordinates":[101.45699999999999,29.246],"type":"Point"}
}