{
  "type": "Feature",
  "properties": {
    "gn:admin1_code":"14.0",
    "gn:asciiname":"Cuorelongcun",
    "gn:country_code":"CN",
    "gn:dem":4679,
    "gn:feature_class":"P",
    "gn:feature_code":"PPL",
    "gn:name":"Cuorelongcun",
    "gn:population":0,
    "gn:timezone":"Asia/Urumqi",
    "iso:country":"CN",
    "name:zho_x_preferred":[
        "\u63aa\u70ed\u9686\u6751"
    ],
    "wof:name":"Cuorelongcun",
    "wof:placetype":"locality"
},
  "geometry": {"coordinates":[91.70259,32.00738],"type":"Point"}
}