{
  "type": "Feature",
  "properties": {
    "gn:admin1_code":"18",
    "gn:asciiname":"Fangjiawan",
    "gn:country_code":"CN",
    "gn:dem":1141,
    "gn:feature_class":"P",
    "gn:feature_code":"PPL",
    "gn:name":"Fangjiawan",
    "gn:population":0,
    "gn:timezone":"Asia/Shanghai",
    "iso:country":"CN",
    "name:zho_x_preferred":[
        "\u65b9\u5bb6\u6e7e"
    ],
    "wof:name":"Fangjiawan",
    "wof:placetype":"locality"
},
  "geometry": {"coordinates":[107.071,28.0754],"type":"Point"}
}