{
  "type": "Feature",
  "properties": {
    "gn:admin1_code":"8.0",
    "gn:asciiname":"Yumincun",
    "gn:country_code":"CN",
    "gn:dem":122,
    "gn:feature_class":"P",
    "gn:feature_code":"PPL",
    "gn:name":"Yumincun",
    "gn:population":0,
    "gn:timezone":"Asia/Shanghai",
    "iso:country":"CN",
    "name:zho_x_preferred":[
        "\u88d5\u6c11\u6751"
    ],
    "wof:name":"Yumincun",
    "wof:placetype":"locality"
},
  "geometry": {"coordinates":[128.69475,45.70073],"type":"Point"}
}