{
  "type": "Feature",
  "properties": {
    "gn:admin1_code":"3.0",
    "gn:asciiname":"Yangshutu",
    "gn:country_code":"CN",
    "gn:dem":172,
    "gn:feature_class":"P",
    "gn:feature_code":"PPL",
    "gn:name":"Yangshutu",
    "gn:population":0,
    "gn:timezone":"Asia/Shanghai",
    "iso:country":"CN",
    "name:zho_x_preferred":[
        "\u6768\u6811\u51f8"
    ],
    "wof:name":"Yangshutu",
    "wof:placetype":"locality"
},
  "geometry": {"coordinates":[118.32102999999999,28.31895],"type":"Point"}
}