{
  "type": "Feature",
  "properties": {
    "gn:admin1_code":"2.0",
    "gn:asciiname":"Dalingshan",
    "gn:country_code":"CN",
    "gn:dem":339,
    "gn:feature_class":"P",
    "gn:feature_code":"PPL",
    "gn:name":"Dalingshan",
    "gn:population":0,
    "gn:timezone":"Asia/Shanghai",
    "iso:country":"CN",
    "name:fas_x_preferred":[
        "\u062f\u0627\u0644\u06cc\u0646\u06af\u0634\u0627\u0646"
    ],
    "name:sco_x_preferred":[
        "Dalingshan"
    ],
    "name:swe_x_preferred":[
        "Dalingshan"
    ],
    "name:zho_x_preferred":[
        "\u5927\u5cad\u5c71"
    ],
    "name:zho_x_variant":[
        "\u5927\u5cad\u5c71\u9547"
    ],
    "wof:name":"Dalingshan",
    "wof:placetype":"locality"
},
  "geometry": {"coordinates":[121.12138,28.90129],"type":"Point"}
}