{
  "type": "Feature",
  "properties": {
    "gn:admin1_code":"11",
    "gn:asciiname":"Shajiang",
    "gn:cc2":"CN",
    "gn:country_code":"CN",
    "gn:dem":217,
    "gn:feature_class":"P",
    "gn:feature_code":"PPL",
    "gn:name":"Shajiang",
    "gn:population":0,
    "gn:timezone":"Asia/Shanghai",
    "iso:country":"CN",
    "name:und_x_variant":[
        "Sha-chiang-shih",
        "Sha-chiang",
        "Shajiang"
    ],
    "wof:name":"Shajiang",
    "wof:placetype":"locality"
},
  "geometry": {"coordinates":[111.16667,27.86667000000001],"type":"Point"}
}