{
  "type": "Feature",
  "properties": {
    "gn:admin1_code":"2.0",
    "gn:asciiname":"Dengxia",
    "gn:country_code":"CN",
    "gn:dem":365,
    "gn:feature_class":"P",
    "gn:feature_code":"PPL",
    "gn:name":"Dengxia",
    "gn:population":0,
    "gn:timezone":"Asia/Shanghai",
    "iso:country":"CN",
    "name:zho_x_preferred":[
        "\u767b\u53a6"
    ],
    "name:zho_x_variant":[
        "\u767b\u590f"
    ],
    "wof:name":"Dengxia",
    "wof:placetype":"locality"
},
  "geometry": {"coordinates":[120.51058999999999,29.39814],"type":"Point"}
}