{
  "type": "Feature",
  "properties": {
    "gn:admin1_code":"21.0",
    "gn:asciiname":"Liubu",
    "gn:country_code":"CN",
    "gn:dem":2173,
    "gn:feature_class":"P",
    "gn:feature_code":"PPL",
    "gn:name":"Liubu",
    "gn:population":0,
    "gn:timezone":"Asia/Shanghai",
    "iso:country":"CN",
    "name:zho_x_preferred":[
        "\u5218\u5821"
    ],
    "wof:name":"Liubu",
    "wof:placetype":"locality"
},
  "geometry": {"coordinates":[106.13,35.8058],"type":"Point"}
}