{
  "type": "Feature",
  "properties": {
    "gn:admin1_code":"26.0",
    "gn:asciiname":"Yangchun",
    "gn:country_code":"CN",
    "gn:dem":527,
    "gn:feature_class":"P",
    "gn:feature_code":"PPLA4",
    "gn:name":"Yangchun",
    "gn:population":0,
    "gn:timezone":"Asia/Shanghai",
    "iso:country":"CN",
    "name:und_x_variant":[
        "\u9633\u6625",
        "Yangchun Zhen",
        "\u9633\u6625\u9547"
    ],
    "wof:name":"Yangchun",
    "wof:placetype":"locality"
},
  "geometry": {"coordinates":[106.90148000000001,33.03324],"type":"Point"}
}