{
  "type": "Feature",
  "properties": {
    "gn:admin1_code":"8.0",
    "gn:asciiname":"Shenglisicun",
    "gn:country_code":"CN",
    "gn:dem":155,
    "gn:feature_class":"P",
    "gn:feature_code":"PPL",
    "gn:name":"Shenglisicun",
    "gn:population":0,
    "gn:timezone":"Asia/Shanghai",
    "iso:country":"CN",
    "name:zho_x_preferred":[
        "\u80dc\u5229\u56db\u6751"
    ],
    "wof:name":"Shenglisicun",
    "wof:placetype":"locality"
},
  "geometry": {"coordinates":[126.75731,46.56332],"type":"Point"}
}