{
  "type": "Feature",
  "properties": {
    "gn:admin1_code":"5.0",
    "gn:asciiname":"Fuyangcun",
    "gn:country_code":"CN",
    "gn:dem":580,
    "gn:feature_class":"P",
    "gn:feature_code":"PPL",
    "gn:name":"Fuyangcun",
    "gn:population":0,
    "gn:timezone":"Asia/Shanghai",
    "iso:country":"CN",
    "name:zho_x_preferred":[
        "\u5bcc\u9633\u6751"
    ],
    "wof:name":"Fuyangcun",
    "wof:placetype":"locality"
},
  "geometry": {"coordinates":[126.73273,42.43199],"type":"Point"}
}