{
  "type": "Feature",
  "properties": {
    "gn:admin1_code":"11.0",
    "gn:asciiname":"Laosaxi",
    "gn:country_code":"CN",
    "gn:dem":255,
    "gn:feature_class":"P",
    "gn:feature_code":"PPL",
    "gn:name":"Laosaxi",
    "gn:population":0,
    "gn:timezone":"Asia/Shanghai",
    "iso:country":"CN",
    "name:zho_x_preferred":[
        "\u8001\u6d12\u6eaa"
    ],
    "wof:name":"Laosaxi",
    "wof:placetype":"locality"
},
  "geometry": {"coordinates":[110.26442,27.42937],"type":"Point"}
}