{
  "type": "Feature",
  "properties": {
    "gn:admin1_code":"18",
    "gn:asciiname":"Shanggonggu",
    "gn:country_code":"CN",
    "gn:dem":1281,
    "gn:feature_class":"P",
    "gn:feature_code":"PPL",
    "gn:name":"Shanggonggu",
    "gn:population":0,
    "gn:timezone":"Asia/Shanghai",
    "iso:country":"CN",
    "name:zho_x_preferred":[
        "\u4e0a\u5de9\u56fa"
    ],
    "wof:name":"Shanggonggu",
    "wof:placetype":"locality"
},
  "geometry": {"coordinates":[106.821,26.4049],"type":"Point"}
}