{
  "type": "Feature",
  "properties": {
    "gn:admin1_code":"14.0",
    "gn:asciiname":"Dongnicun",
    "gn:country_code":"CN",
    "gn:dem":3981,
    "gn:feature_class":"P",
    "gn:feature_code":"PPL",
    "gn:name":"Dongnicun",
    "gn:population":0,
    "gn:timezone":"Asia/Urumqi",
    "iso:country":"CN",
    "name:zho_x_preferred":[
        "\u4e1c\u5c3c\u6751"
    ],
    "wof:name":"Dongnicun",
    "wof:placetype":"locality"
},
  "geometry": {"coordinates":[96.22445999999999,30.49001],"type":"Point"}
}