{
  "type": "Feature",
  "properties": {
    "gn:admin1_code":"7.0",
    "gn:asciiname":"Longhuiqiao",
    "gn:country_code":"CN",
    "gn:dem":157,
    "gn:feature_class":"P",
    "gn:feature_code":"PPL",
    "gn:name":"Longhuiqiao",
    "gn:population":0,
    "gn:timezone":"Asia/Shanghai",
    "iso:country":"CN",
    "name:zho_x_preferred":[
        "\u9f99\u4f1a\u6865"
    ],
    "wof:name":"Longhuiqiao",
    "wof:placetype":"locality"
},
  "geometry": {"coordinates":[118.08192,24.28447],"type":"Point"}
}