{
  "type": "Feature",
  "properties": {
    "gn:admin1_code":"18",
    "gn:asciiname":"Wafangzhai",
    "gn:country_code":"CN",
    "gn:dem":1264,
    "gn:feature_class":"P",
    "gn:feature_code":"PPL",
    "gn:name":"Wafangzhai",
    "gn:population":0,
    "gn:timezone":"Asia/Shanghai",
    "iso:country":"CN",
    "name:zho_x_preferred":[
        "\u74e6\u623f\u5be8"
    ],
    "wof:name":"Wafangzhai",
    "wof:placetype":"locality"
},
  "geometry": {"coordinates":[106.52200000000001,27.064],"type":"Point"}
}