{
  "type": "Feature",
  "properties": {
    "gn:admin1_code":"1.0",
    "gn:asciiname":"Wantangcun",
    "gn:country_code":"CN",
    "gn:dem":75,
    "gn:feature_class":"P",
    "gn:feature_code":"PPL",
    "gn:name":"Wantangcun",
    "gn:population":0,
    "gn:timezone":"Asia/Shanghai",
    "iso:country":"CN",
    "name:zho_x_preferred":[
        "\u6e7e\u5858\u6751"
    ],
    "wof:name":"Wantangcun",
    "wof:placetype":"locality"
},
  "geometry": {"coordinates":[116.81451,31.2829],"type":"Point"}
}