{
  "type": "Feature",
  "properties": {
    "gn:admin1_code":"2.0",
    "gn:asciiname":"Baijia",
    "gn:country_code":"CN",
    "gn:dem":5,
    "gn:feature_class":"P",
    "gn:feature_code":"PPL",
    "gn:name":"Baijia",
    "gn:population":0,
    "gn:timezone":"Asia/Shanghai",
    "iso:country":"CN",
    "name:und_x_variant":[
        "\u67cf\u5bb6"
    ],
    "name:zho_x_preferred":[
        "Baijia"
    ],
    "wof:name":"Baijia",
    "wof:placetype":"locality"
},
  "geometry": {"coordinates":[119.81025,30.98794],"type":"Point"}
}