{
  "type": "Feature",
  "properties": {
    "gn:admin1_code":"18.0",
    "gn:asciiname":"Fanglongtang",
    "gn:country_code":"CN",
    "gn:dem":766,
    "gn:feature_class":"P",
    "gn:feature_code":"PPL",
    "gn:name":"Fanglongtang",
    "gn:population":0,
    "gn:timezone":"Asia/Shanghai",
    "iso:country":"CN",
    "name:zho_x_preferred":[
        "\u65b9\u9647\u5858"
    ],
    "wof:name":"Fanglongtang",
    "wof:placetype":"locality"
},
  "geometry": {"coordinates":[108.367,26.6947],"type":"Point"}
}