{
  "type": "Feature",
  "properties": {
    "gn:admin1_code":"1.0",
    "gn:asciiname":"Hongmiao",
    "gn:country_code":"CN",
    "gn:dem":14,
    "gn:feature_class":"P",
    "gn:feature_code":"PPL",
    "gn:name":"Hongmiao",
    "gn:population":0,
    "gn:timezone":"Asia/Shanghai",
    "iso:country":"CN",
    "name:zho_x_preferred":[
        "\u6d2a\u5e99"
    ],
    "wof:name":"Hongmiao",
    "wof:placetype":"locality"
},
  "geometry": {"coordinates":[119.04608,32.70399],"type":"Point"}
}