{
  "type": "Feature",
  "properties": {
    "gn:admin1_code":"10",
    "gn:asciiname":"Daqinghe",
    "gn:country_code":"CN",
    "gn:dem":1,
    "gn:feature_class":"P",
    "gn:feature_code":"PPL",
    "gn:name":"Daqinghe",
    "gn:population":0,
    "gn:timezone":"Asia/Shanghai",
    "iso:country":"CN",
    "name:und_x_variant":[
        "Ta-ch\u2019ing-ho",
        "Daqinghe"
    ],
    "name:zho_x_preferred":[
        "\u5927\u6e05\u6cb3"
    ],
    "wof:name":"Daqinghe",
    "wof:placetype":"locality"
},
  "geometry": {"coordinates":[118.85948,39.19837],"type":"Point"}
}