{
  "type": "Feature",
  "properties": {
    "gn:admin1_code":"15.0",
    "gn:asciiname":"Liangjiasanhao",
    "gn:country_code":"CN",
    "gn:dem":1431,
    "gn:feature_class":"P",
    "gn:feature_code":"PPL",
    "gn:name":"Liangjiasanhao",
    "gn:population":0,
    "gn:timezone":"Asia/Shanghai",
    "iso:country":"CN",
    "name:zho_x_preferred":[
        "\u6881\u5bb6\u4e09\u53f7"
    ],
    "wof:name":"Liangjiasanhao",
    "wof:placetype":"locality"
},
  "geometry": {"coordinates":[100.15300000000001,39.1865],"type":"Point"}
}