{
  "type": "Feature",
  "properties": {
    "gn:admin1_code":"4.0",
    "gn:asciiname":"Taifeng",
    "gn:country_code":"CN",
    "gn:dem":2,
    "gn:feature_class":"P",
    "gn:feature_code":"PPL",
    "gn:name":"Taifeng",
    "gn:population":0,
    "gn:timezone":"Asia/Shanghai",
    "iso:country":"CN",
    "name:und_x_variant":[
        "\u6cf0\u4e30"
    ],
    "wof:name":"Taifeng",
    "wof:placetype":"locality"
},
  "geometry": {"coordinates":[120.47960999999999,33.18251],"type":"Point"}
}