{
  "type": "Feature",
  "properties": {
    "gn:admin1_code":"9.0",
    "gn:asciiname":"Xiyuanlou",
    "gn:country_code":"CN",
    "gn:dem":109,
    "gn:feature_class":"P",
    "gn:feature_code":"PPL",
    "gn:name":"Xiyuanlou",
    "gn:population":0,
    "gn:timezone":"Asia/Shanghai",
    "iso:country":"CN",
    "name:zho_x_preferred":[
        "\u897f\u8881\u697c"
    ],
    "wof:name":"Xiyuanlou",
    "wof:placetype":"locality"
},
  "geometry": {"coordinates":[112.91321000000001,32.8113],"type":"Point"}
}