{
  "type": "Feature",
  "properties": {
    "gn:admin1_code":"19.0",
    "gn:asciiname":"Daganhecun",
    "gn:country_code":"CN",
    "gn:dem":276,
    "gn:feature_class":"P",
    "gn:feature_code":"PPL",
    "gn:name":"Daganhecun",
    "gn:population":0,
    "gn:timezone":"Asia/Shanghai",
    "iso:country":"CN",
    "name:zho_x_preferred":[
        "\u5927\u7518\u6cb3\u6751"
    ],
    "wof:name":"Daganhecun",
    "wof:placetype":"locality"
},
  "geometry": {"coordinates":[124.916,42.3428],"type":"Point"}
}