{
  "type": "Feature",
  "properties": {
    "gn:admin1_code":"26.0",
    "gn:asciiname":"Anxinzhuangcun",
    "gn:country_code":"CN",
    "gn:dem":1597,
    "gn:feature_class":"P",
    "gn:feature_code":"PPL",
    "gn:name":"Anxinzhuangcun",
    "gn:population":0,
    "gn:timezone":"Asia/Shanghai",
    "iso:country":"CN",
    "name:zho_x_preferred":[
        "\u5b89\u65b0\u5e84\u6751"
    ],
    "wof:name":"Anxinzhuangcun",
    "wof:placetype":"locality"
},
  "geometry": {"coordinates":[108.53279000000001,36.9364],"type":"Point"}
}