{
  "type": "Feature",
  "properties": {
    "gn:admin1_code":"15.0",
    "gn:asciiname":"Louzidi",
    "gn:country_code":"CN",
    "gn:dem":1155,
    "gn:feature_class":"P",
    "gn:feature_code":"PPL",
    "gn:name":"Louzidi",
    "gn:population":0,
    "gn:timezone":"Asia/Shanghai",
    "iso:country":"CN",
    "name:zho_x_preferred":[
        "\u697c\u5b50\u5e95"
    ],
    "wof:name":"Louzidi",
    "wof:placetype":"locality"
},
  "geometry": {"coordinates":[107.86199999999999,35.7433],"type":"Point"}
}