{
  "type": "Feature",
  "properties": {
    "gn:admin1_code":"16.0",
    "gn:asciiname":"Jinlonghe",
    "gn:country_code":"CN",
    "gn:dem":922,
    "gn:feature_class":"P",
    "gn:feature_code":"PPL",
    "gn:name":"Jinlonghe",
    "gn:population":0,
    "gn:timezone":"Asia/Shanghai",
    "iso:country":"CN",
    "name:zho_x_preferred":[
        "\u91d1\u9f99\u6cb3"
    ],
    "wof:name":"Jinlonghe",
    "wof:placetype":"locality"
},
  "geometry": {"coordinates":[110.211,24.3024],"type":"Point"}
}