{
  "type": "Feature",
  "properties": {
    "gn:admin1_code":"29.0",
    "gn:asciiname":"Paiba",
    "gn:country_code":"CN",
    "gn:dem":1813,
    "gn:feature_class":"P",
    "gn:feature_code":"PPL",
    "gn:name":"Paiba",
    "gn:population":0,
    "gn:timezone":"Asia/Shanghai",
    "iso:country":"CN",
    "name:zho_x_preferred":[
        "\u6392\u53ed"
    ],
    "wof:name":"Paiba",
    "wof:placetype":"locality"
},
  "geometry": {"coordinates":[98.919,26.3317],"type":"Point"}
}