{
  "type": "Feature",
  "properties": {
    "gn:admin1_code":"11.0",
    "gn:asciiname":"Heijianang",
    "gn:country_code":"CN",
    "gn:dem":618,
    "gn:feature_class":"P",
    "gn:feature_code":"PPL",
    "gn:name":"Heijianang",
    "gn:population":0,
    "gn:timezone":"Asia/Shanghai",
    "iso:country":"CN",
    "name:zho_x_preferred":[
        "\u9ed1\u5bb6\u4e6a"
    ],
    "wof:name":"Heijianang",
    "wof:placetype":"locality"
},
  "geometry": {"coordinates":[110.35715,29.51362],"type":"Point"}
}