{
  "type": "Feature",
  "properties": {
    "gn:admin1_code":"24",
    "gn:asciiname":"Gudatun",
    "gn:cc2":"CN",
    "gn:country_code":"CN",
    "gn:dem":1323,
    "gn:feature_class":"P",
    "gn:feature_code":"PPL",
    "gn:name":"Gudatun",
    "gn:population":0,
    "gn:timezone":"Asia/Shanghai",
    "iso:country":"CN",
    "name:und_x_variant":[
        "Ku-ta-t\u2019un",
        "Gudatun"
    ],
    "wof:name":"Gudatun",
    "wof:placetype":"locality"
},
  "geometry": {"coordinates":[114.22972,40.31944],"type":"Point"}
}