{
  "type": "Feature",
  "properties": {
    "gn:admin1_code":"8.0",
    "gn:asciiname":"Dongchunshengtangzi",
    "gn:country_code":"CN",
    "gn:dem":345,
    "gn:feature_class":"P",
    "gn:feature_code":"PPL",
    "gn:name":"Dongchunshengtangzi",
    "gn:population":0,
    "gn:timezone":"Asia/Shanghai",
    "iso:country":"CN",
    "name:zho_x_preferred":[
        "\u8463\u6625\u751f\u8d9f\u5b50"
    ],
    "wof:name":"Dongchunshengtangzi",
    "wof:placetype":"locality"
},
  "geometry": {"coordinates":[129.8656,48.57208],"type":"Point"}
}