{
  "type": "Feature",
  "properties": {
    "gn:admin1_code":"1.0",
    "gn:asciiname":"Yijizhancun",
    "gn:country_code":"CN",
    "gn:dem":63,
    "gn:feature_class":"P",
    "gn:feature_code":"PPL",
    "gn:name":"Yijizhancun",
    "gn:population":0,
    "gn:timezone":"Asia/Shanghai",
    "iso:country":"CN",
    "name:zho_x_preferred":[
        "\u4e00\u7ea7\u7ad9\u6751"
    ],
    "wof:name":"Yijizhancun",
    "wof:placetype":"locality"
},
  "geometry": {"coordinates":[116.46352,31.68762000000001],"type":"Point"}
}