{
  "type": "Feature",
  "properties": {
    "gn:admin1_code":"15.0",
    "gn:asciiname":"Tangnaihe Gongma",
    "gn:country_code":"CN",
    "gn:dem":2975,
    "gn:feature_class":"P",
    "gn:feature_code":"PPL",
    "gn:name":"Tangnaihe Gongma",
    "gn:population":0,
    "gn:timezone":"Asia/Shanghai",
    "iso:country":"CN",
    "name:und_x_variant":[
        "\u5858\u4e43\u5408\u8d21\u739b"
    ],
    "wof:name":"Tangnaihe Gongma",
    "wof:placetype":"locality"
},
  "geometry": {"coordinates":[102.488,35.18],"type":"Point"}
}