{
  "type": "Feature",
  "properties": {
    "gn:admin1_code":"11.0",
    "gn:asciiname":"Chayuan",
    "gn:country_code":"CN",
    "gn:dem":779,
    "gn:feature_class":"P",
    "gn:feature_code":"PPL",
    "gn:name":"Chayuan",
    "gn:population":0,
    "gn:timezone":"Asia/Shanghai",
    "iso:country":"CN",
    "name:zho_x_preferred":[
        "\u8336\u56ed"
    ],
    "wof:name":"Chayuan",
    "wof:placetype":"locality"
},
  "geometry": {"coordinates":[110.22362,29.56216],"type":"Point"}
}