{
  "type": "Feature",
  "properties": {
    "gn:admin1_code":"11",
    "gn:asciiname":"Meishuiqiao",
    "gn:country_code":"CN",
    "gn:dem":122,
    "gn:feature_class":"P",
    "gn:feature_code":"PPL",
    "gn:name":"Meishuiqiao",
    "gn:population":0,
    "gn:timezone":"Asia/Shanghai",
    "iso:country":"CN",
    "name:zho_x_preferred":[
        "\u6e44\u6c34\u6865"
    ],
    "wof:name":"Meishuiqiao",
    "wof:placetype":"locality"
},
  "geometry": {"coordinates":[112.13527999999999,27.36829],"type":"Point"}
}