{
  "type": "Feature",
  "properties": {
    "gn:admin1_code":"26.0",
    "gn:asciiname":"Zhoujia Goucun",
    "gn:country_code":"CN",
    "gn:dem":1009,
    "gn:feature_class":"P",
    "gn:feature_code":"PPL",
    "gn:name":"Zhoujia Goucun",
    "gn:population":0,
    "gn:timezone":"Asia/Shanghai",
    "iso:country":"CN",
    "name:zho_x_preferred":[
        "\u5468\u5bb6\u6c9f\u6751"
    ],
    "wof:name":"Zhoujia Goucun",
    "wof:placetype":"locality"
},
  "geometry": {"coordinates":[110.324,37.6904],"type":"Point"}
}