{
  "type": "Feature",
  "properties": {
    "gn:admin1_code":"32.0",
    "gn:asciiname":"Jiucengzhai",
    "gn:country_code":"CN",
    "gn:dem":668,
    "gn:feature_class":"P",
    "gn:feature_code":"PPL",
    "gn:name":"Jiucengzhai",
    "gn:population":0,
    "gn:timezone":"Asia/Shanghai",
    "iso:country":"CN",
    "name:zho_x_preferred":[
        "\u4e5d\u5c42\u5be8"
    ],
    "wof:name":"Jiucengzhai",
    "wof:placetype":"locality"
},
  "geometry": {"coordinates":[107.01600000000001,31.25800000000001],"type":"Point"}
}