{
  "type": "Feature",
  "properties": {
    "gn:admin1_code":"15.0",
    "gn:asciiname":"Jiadi Kuhe",
    "gn:country_code":"CN",
    "gn:dem":3068,
    "gn:feature_class":"P",
    "gn:feature_code":"PPL",
    "gn:name":"Jiadi Kuhe",
    "gn:population":0,
    "gn:timezone":"Asia/Shanghai",
    "iso:country":"CN",
    "name:zho_x_preferred":[
        "\u52a0\u5730\u5e93\u5408"
    ],
    "wof:name":"Jiadi Kuhe",
    "wof:placetype":"locality"
},
  "geometry": {"coordinates":[102.82899999999999,34.8709],"type":"Point"}
}