{
  "type": "Feature",
  "properties": {
    "gn:admin1_code":"18.0",
    "gn:asciiname":"Yantaitai",
    "gn:country_code":"CN",
    "gn:dem":785,
    "gn:feature_class":"P",
    "gn:feature_code":"PPL",
    "gn:name":"Yantaitai",
    "gn:population":0,
    "gn:timezone":"Asia/Shanghai",
    "iso:country":"CN",
    "name:zho_x_preferred":[
        "\u5ca9\u53f0\u53f0"
    ],
    "wof:name":"Yantaitai",
    "wof:placetype":"locality"
},
  "geometry": {"coordinates":[108.32299999999999,26.97300000000001],"type":"Point"}
}