{
  "type": "Feature",
  "properties": {
    "gn:admin1_code":"25",
    "gn:asciiname":"Taoyangsi",
    "gn:country_code":"CN",
    "gn:dem":37,
    "gn:feature_class":"P",
    "gn:feature_code":"PPL",
    "gn:name":"Taoyangsi",
    "gn:population":0,
    "gn:timezone":"Asia/Shanghai",
    "iso:country":"CN",
    "name:zho_x_preferred":[
        "\u9676\u9633\u5bfa"
    ],
    "wof:name":"Taoyangsi",
    "wof:placetype":"locality"
},
  "geometry": {"coordinates":[117.042,34.8703],"type":"Point"}
}