{
  "type": "Feature",
  "properties": {
    "gn:admin1_code":"32.0",
    "gn:asciiname":"Zhongpingmiao",
    "gn:country_code":"CN",
    "gn:dem":927,
    "gn:feature_class":"P",
    "gn:feature_code":"PPL",
    "gn:name":"Zhongpingmiao",
    "gn:population":0,
    "gn:timezone":"Asia/Shanghai",
    "iso:country":"CN",
    "name:zho_x_preferred":[
        "\u949f\u576a\u5e99"
    ],
    "wof:name":"Zhongpingmiao",
    "wof:placetype":"locality"
},
  "geometry": {"coordinates":[102.74773999999999,30.03688],"type":"Point"}
}