{
  "type": "Feature",
  "properties": {
    "gn:admin1_code":"24",
    "gn:asciiname":"Huangwei",
    "gn:country_code":"CN",
    "gn:dem":1014,
    "gn:feature_class":"P",
    "gn:feature_code":"PPL",
    "gn:name":"Huangwei",
    "gn:population":0,
    "gn:timezone":"Asia/Shanghai",
    "iso:country":"CN",
    "name:und_x_variant":[
        "Huang-wei-ts\u2019un",
        "Huangwei",
        "\u9ec4\u5dcd"
    ],
    "wof:name":"Huangwei",
    "wof:placetype":"locality"
},
  "geometry": {"coordinates":[112.89845,39.548],"type":"Point"}
}