{
  "type": "Feature",
  "properties": {
    "gn:admin1_code":"10",
    "gn:asciiname":"Guyushu",
    "gn:country_code":"CN",
    "gn:dem":1112,
    "gn:feature_class":"P",
    "gn:feature_code":"PPL",
    "gn:name":"Guyushu",
    "gn:population":0,
    "gn:timezone":"Asia/Shanghai",
    "iso:country":"CN",
    "name:zho_x_preferred":[
        "\u5b64\u6986\u6811"
    ],
    "wof:name":"Guyushu",
    "wof:placetype":"locality"
},
  "geometry": {"coordinates":[116.91392999999999,41.87379],"type":"Point"}
}