{
  "type": "Feature",
  "properties": {
    "gn:admin1_code":"08",
    "gn:asciiname":"Lao-ch'en-chia",
    "gn:country_code":"CN",
    "gn:dem":140,
    "gn:feature_class":"P",
    "gn:feature_code":"PPL",
    "gn:name":"Lao-ch\u2019en-chia",
    "gn:population":0,
    "gn:timezone":"Asia/Shanghai",
    "iso:country":"CN",
    "wof:name":"Lao-ch'en-chia",
    "wof:placetype":"locality"
},
  "geometry": {"coordinates":[124.22056000000001,47.01194],"type":"Point"}
}