{
  "type": "Feature",
  "properties": {
    "gn:admin1_code":"10",
    "gn:asciiname":"Leizhuang",
    "gn:cc2":"CN",
    "gn:country_code":"CN",
    "gn:dem":43,
    "gn:feature_class":"P",
    "gn:feature_code":"PPL",
    "gn:name":"Leizhuang",
    "gn:population":0,
    "gn:timezone":"Asia/Shanghai",
    "iso:country":"CN",
    "name:und_x_variant":[
        "Leichwang",
        "Lei-chuang",
        "Leizhuang"
    ],
    "wof:name":"Leizhuang",
    "wof:placetype":"locality"
},
  "geometry": {"coordinates":[118.56667,39.73333],"type":"Point"}
}