{
  "type": "Feature",
  "properties": {
    "gn:admin1_code":"2.0",
    "gn:asciiname":"Xikoucun",
    "gn:country_code":"CN",
    "gn:dem":211,
    "gn:feature_class":"P",
    "gn:feature_code":"PPL",
    "gn:name":"Xikoucun",
    "gn:population":0,
    "gn:timezone":"Asia/Shanghai",
    "iso:country":"CN",
    "name:und_x_variant":[
        "Ch\u2019i-k\u2019ou",
        "Xikou",
        "Xikoucun"
    ],
    "name:zho_x_preferred":[
        "\u6eaa\u53e3"
    ],
    "name:zho_x_variant":[
        "\u6eaa\u53e3\u6751"
    ],
    "wof:name":"Xikoucun",
    "wof:placetype":"locality"
},
  "geometry": {"coordinates":[120.47161,28.64852],"type":"Point"}
}