{
  "type": "Feature",
  "properties": {
    "gn:admin1_code":"33.0",
    "gn:asciiname":"Xiniu",
    "gn:country_code":"CN",
    "gn:dem":334,
    "gn:feature_class":"P",
    "gn:feature_code":"PPL",
    "gn:name":"Xiniu",
    "gn:population":0,
    "gn:timezone":"Asia/Shanghai",
    "iso:country":"CN",
    "name:zho_x_preferred":[
        "\u7280\u725b"
    ],
    "wof:name":"Xiniu",
    "wof:placetype":"locality"
},
  "geometry": {"coordinates":[108.04855999999999,30.21908],"type":"Point"}
}