{
  "type": "Feature",
  "properties": {
    "gn:admin1_code":"25",
    "gn:asciiname":"Dongwuzhuang",
    "gn:country_code":"CN",
    "gn:dem":60,
    "gn:feature_class":"P",
    "gn:feature_code":"PPL",
    "gn:name":"Dongwuzhuang",
    "gn:population":0,
    "gn:timezone":"Asia/Shanghai",
    "iso:country":"CN",
    "name:zho_x_preferred":[
        "\u4e1c\u5434\u5e84"
    ],
    "wof:name":"Dongwuzhuang",
    "wof:placetype":"locality"
},
  "geometry": {"coordinates":[115.11,35.2802],"type":"Point"}
}