{
  "type": "Feature",
  "properties": {
    "gn:admin1_code":"11",
    "gn:asciiname":"Lingguan",
    "gn:cc2":"CN",
    "gn:country_code":"CN",
    "gn:dem":146,
    "gn:feature_class":"P",
    "gn:feature_code":"PPL",
    "gn:name":"Lingguan",
    "gn:population":0,
    "gn:timezone":"Asia/Shanghai",
    "iso:country":"CN",
    "name:und_x_variant":[
        "Lingguandian",
        "Lingguan"
    ],
    "wof:name":"Lingguan",
    "wof:placetype":"locality"
},
  "geometry": {"coordinates":[111.95667,26.71889],"type":"Point"}
}