{
  "type": "Feature",
  "properties": {
    "gn:admin1_code":"8.0",
    "gn:asciiname":"Wushantun",
    "gn:country_code":"CN",
    "gn:dem":122,
    "gn:feature_class":"P",
    "gn:feature_code":"PPL",
    "gn:name":"Wushantun",
    "gn:population":0,
    "gn:timezone":"Asia/Shanghai",
    "iso:country":"CN",
    "name:zho_x_preferred":[
        "\u5434\u5c71\u5c6f"
    ],
    "wof:name":"Wushantun",
    "wof:placetype":"locality"
},
  "geometry": {"coordinates":[125.79452999999999,45.61298],"type":"Point"}
}