{
  "type": "Feature",
  "properties": {
    "gn:admin1_code":"10",
    "gn:asciiname":"Shizigou",
    "gn:country_code":"CN",
    "gn:dem":1058,
    "gn:feature_class":"P",
    "gn:feature_code":"PPL",
    "gn:name":"Shizigou",
    "gn:population":0,
    "gn:timezone":"Asia/Shanghai",
    "iso:country":"CN",
    "name:zho_x_preferred":[
        "\u72ee\u5b50\u6c9f"
    ],
    "wof:name":"Shizigou",
    "wof:placetype":"locality"
},
  "geometry": {"coordinates":[114.26857,40.86889],"type":"Point"}
}