{
  "type": "Feature",
  "properties": {
    "gn:admin1_code":"15.0",
    "gn:asciiname":"Fuyesi",
    "gn:country_code":"CN",
    "gn:dem":1776,
    "gn:feature_class":"P",
    "gn:feature_code":"PPL",
    "gn:name":"Fuyesi",
    "gn:population":0,
    "gn:timezone":"Asia/Shanghai",
    "iso:country":"CN",
    "name:zho_x_preferred":[
        "\u5bcc\u4e1a\u5bfa"
    ],
    "wof:name":"Fuyesi",
    "wof:placetype":"locality"
},
  "geometry": {"coordinates":[103.628,35.7506],"type":"Point"}
}