{
  "type": "Feature",
  "properties": {
    "gn:admin1_code":"25.0",
    "gn:asciiname":"Dongmajiatuan",
    "gn:country_code":"CN",
    "gn:dem":26,
    "gn:feature_class":"P",
    "gn:feature_code":"PPL",
    "gn:name":"Dongmajiatuan",
    "gn:population":0,
    "gn:timezone":"Asia/Shanghai",
    "iso:country":"CN",
    "name:zho_x_preferred":[
        "\u4e1c\u9a6c\u5bb6\u7583"
    ],
    "wof:name":"Dongmajiatuan",
    "wof:placetype":"locality"
},
  "geometry": {"coordinates":[119.84905999999999,36.77367],"type":"Point"}
}