{
  "type": "Feature",
  "properties": {
    "gn:admin1_code":"29.0",
    "gn:asciiname":"Axule",
    "gn:country_code":"CN",
    "gn:dem":1306,
    "gn:feature_class":"P",
    "gn:feature_code":"PPL",
    "gn:name":"Axule",
    "gn:population":0,
    "gn:timezone":"Asia/Shanghai",
    "iso:country":"CN",
    "name:zho_x_preferred":[
        "\u963f\u987b\u4e50"
    ],
    "wof:name":"Axule",
    "wof:placetype":"locality"
},
  "geometry": {"coordinates":[100.343,24.7995],"type":"Point"}
}