{
  "type": "Feature",
  "properties": {
    "gn:admin1_code":"8.0",
    "gn:asciiname":"Guanjiagou",
    "gn:country_code":"CN",
    "gn:dem":133,
    "gn:feature_class":"P",
    "gn:feature_code":"PPL",
    "gn:name":"Guanjiagou",
    "gn:population":0,
    "gn:timezone":"Asia/Shanghai",
    "iso:country":"CN",
    "name:zho_x_preferred":[
        "\u7ba1\u5bb6\u6c9f"
    ],
    "wof:name":"Guanjiagou",
    "wof:placetype":"locality"
},
  "geometry": {"coordinates":[127.17137,46.08373],"type":"Point"}
}