{
  "type": "Feature",
  "properties": {
    "gn:admin1_code":"33",
    "gn:asciiname":"Sanqu",
    "gn:country_code":"CN",
    "gn:dem":383,
    "gn:feature_class":"P",
    "gn:feature_code":"PPLA4",
    "gn:name":"Sanqu",
    "gn:population":0,
    "gn:timezone":"Asia/Shanghai",
    "iso:country":"CN",
    "name:und_x_variant":[
        "San-ch\u2019\u00fc-chen",
        "Sanqu Zhen",
        "Sanqu",
        "Wangjiaba"
    ],
    "name:zho_x_preferred":[
        "\u4e09\u9a71"
    ],
    "name:zho_x_variant":[
        "\u4e09\u9a71\u9547",
        "\u6c6a\u5bb6\u575d"
    ],
    "wof:name":"Sanqu",
    "wof:placetype":"locality"
},
  "geometry": {"coordinates":[105.62161,29.64157],"type":"Point"}
}