{
  "type": "Feature",
  "properties": {
    "gn:admin1_code":"32.0",
    "gn:asciiname":"Luogoupu",
    "gn:country_code":"CN",
    "gn:dem":2051,
    "gn:feature_class":"P",
    "gn:feature_code":"PPL",
    "gn:name":"Luogoupu",
    "gn:population":0,
    "gn:timezone":"Asia/Shanghai",
    "iso:country":"CN",
    "name:zho_x_preferred":[
        "\u7f57\u6c9f\u94fa"
    ],
    "wof:name":"Luogoupu",
    "wof:placetype":"locality"
},
  "geometry": {"coordinates":[102.273,27.7437],"type":"Point"}
}