{
  "type": "Feature",
  "properties": {
    "gn:admin1_code":"26",
    "gn:asciiname":"Huojiatai",
    "gn:cc2":"CN",
    "gn:country_code":"CN",
    "gn:dem":692,
    "gn:feature_class":"P",
    "gn:feature_code":"PPL",
    "gn:name":"Huojiatai",
    "gn:population":0,
    "gn:timezone":"Asia/Shanghai",
    "iso:country":"CN",
    "name:und_x_variant":[
        "Ho-chia-t\u2019ai",
        "Huo-t\u2019ai",
        "Huo-chia-t\u2019ai",
        "Huojiatai"
    ],
    "wof:name":"Huojiatai",
    "wof:placetype":"locality"
},
  "geometry": {"coordinates":[109.44222000000001,33.48972],"type":"Point"}
}