{
  "type": "Feature",
  "properties": {
    "gn:admin1_code":"7.0",
    "gn:asciiname":"Wuyang",
    "gn:country_code":"CN",
    "gn:dem":808,
    "gn:feature_class":"P",
    "gn:feature_code":"PPL",
    "gn:name":"Wuyang",
    "gn:population":0,
    "gn:timezone":"Asia/Shanghai",
    "iso:country":"CN",
    "name:ceb_x_preferred":[
        "Wuyang"
    ],
    "name:deu_x_preferred":[
        "Wuyang"
    ],
    "name:nor_x_preferred":[
        "Wuyang"
    ],
    "name:zho_x_preferred":[
        "\u6b66\u6d0b"
    ],
    "wof:name":"Wuyang",
    "wof:placetype":"locality"
},
  "geometry": {"coordinates":[118.54986,26.21215],"type":"Point"}
}