{
  "type": "Feature",
  "properties": {
    "gn:admin1_code":"2.0",
    "gn:asciiname":"Fengruo",
    "gn:country_code":"CN",
    "gn:dem":156,
    "gn:feature_class":"P",
    "gn:feature_code":"PPL",
    "gn:name":"Fengruo",
    "gn:population":0,
    "gn:timezone":"Asia/Shanghai",
    "iso:country":"CN",
    "name:zho_x_preferred":[
        "\u5cf0\u7bac"
    ],
    "wof:name":"Fengruo",
    "wof:placetype":"locality"
},
  "geometry": {"coordinates":[120.13976,28.84703],"type":"Point"}
}