{
  "type": "Feature",
  "properties": {
    "gn:admin1_code":"33.0",
    "gn:asciiname":"Shangmuping",
    "gn:country_code":"CN",
    "gn:dem":1169,
    "gn:feature_class":"P",
    "gn:feature_code":"PPL",
    "gn:name":"Shangmuping",
    "gn:population":0,
    "gn:timezone":"Asia/Shanghai",
    "iso:country":"CN",
    "name:zho_x_preferred":[
        "\u4e0a\u6728\u576a"
    ],
    "wof:name":"Shangmuping",
    "wof:placetype":"locality"
},
  "geometry": {"coordinates":[107.96701000000002,29.63799],"type":"Point"}
}