{
  "type": "Feature",
  "properties": {
    "gn:admin1_code":"31.0",
    "gn:asciiname":"Disancun",
    "gn:country_code":"CN",
    "gn:dem":21,
    "gn:feature_class":"P",
    "gn:feature_code":"PPL",
    "gn:name":"Disancun",
    "gn:population":0,
    "gn:timezone":"Asia/Shanghai",
    "iso:country":"CN",
    "name:und_x_variant":[
        "Disantou"
    ],
    "name:zho_x_preferred":[
        "\u7b2c\u4e09\u6751"
    ],
    "name:zho_x_variant":[
        "\u7b2c\u4e09\u5934"
    ],
    "wof:name":"Disancun",
    "wof:placetype":"locality"
},
  "geometry": {"coordinates":[109.84,18.393],"type":"Point"}
}