{
  "type": "Feature",
  "properties": {
    "gn:admin1_code":"32.0",
    "gn:asciiname":"Duilongxiang",
    "gn:country_code":"CN",
    "gn:dem":508,
    "gn:feature_class":"P",
    "gn:feature_code":"PPL",
    "gn:name":"Duilongxiang",
    "gn:population":0,
    "gn:timezone":"Asia/Shanghai",
    "iso:country":"CN",
    "name:zho_x_preferred":[
        "\u5151\u9f99\u4e61"
    ],
    "wof:name":"Duilongxiang",
    "wof:placetype":"locality"
},
  "geometry": {"coordinates":[104.09099999999999,29.9181],"type":"Point"}
}