{
  "type": "Feature",
  "properties": {
    "gn:admin1_code":"3.0",
    "gn:asciiname":"Laikeng",
    "gn:country_code":"CN",
    "gn:dem":61,
    "gn:feature_class":"P",
    "gn:feature_code":"PPL",
    "gn:name":"Laikeng",
    "gn:population":0,
    "gn:timezone":"Asia/Shanghai",
    "iso:country":"CN",
    "name:und_x_variant":[
        "\u8d56\u5751"
    ],
    "wof:name":"Laikeng",
    "wof:placetype":"locality"
},
  "geometry": {"coordinates":[115.78362,27.96375],"type":"Point"}
}