{
  "type": "Feature",
  "properties": {
    "gn:admin1_code":"29.0",
    "gn:asciiname":"Wawujie",
    "gn:country_code":"CN",
    "gn:dem":1793,
    "gn:feature_class":"P",
    "gn:feature_code":"PPL",
    "gn:name":"Wawujie",
    "gn:population":0,
    "gn:timezone":"Asia/Shanghai",
    "iso:country":"CN",
    "name:zho_x_preferred":[
        "\u74e6\u5c4b\u8857"
    ],
    "wof:name":"Wawujie",
    "wof:placetype":"locality"
},
  "geometry": {"coordinates":[100.11499999999999,24.8149],"type":"Point"}
}