{
  "type": "Feature",
  "properties": {
    "gn:admin1_code":"4.0",
    "gn:asciiname":"Houxiaoyuan",
    "gn:country_code":"CN",
    "gn:dem":10,
    "gn:feature_class":"P",
    "gn:feature_code":"PPL",
    "gn:name":"Houxiaoyuan",
    "gn:population":0,
    "gn:timezone":"Asia/Shanghai",
    "iso:country":"CN",
    "name:zho_x_preferred":[
        "\u540e\u5c0f\u56ed"
    ],
    "wof:name":"Houxiaoyuan",
    "wof:placetype":"locality"
},
  "geometry": {"coordinates":[118.752,33.7194],"type":"Point"}
}