{
  "type": "Feature",
  "properties": {
    "gn:admin1_code":"26.0",
    "gn:asciiname":"Donggouzhangcun",
    "gn:country_code":"CN",
    "gn:dem":1069,
    "gn:feature_class":"P",
    "gn:feature_code":"PPL",
    "gn:name":"Donggouzhangcun",
    "gn:population":0,
    "gn:timezone":"Asia/Shanghai",
    "iso:country":"CN",
    "name:zho_x_preferred":[
        "\u4e1c\u6c9f\u638c\u6751"
    ],
    "wof:name":"Donggouzhangcun",
    "wof:placetype":"locality"
},
  "geometry": {"coordinates":[109.95686000000001,37.09401],"type":"Point"}
}