{
  "type": "Feature",
  "properties": {
    "gn:admin1_code":"4.0",
    "gn:asciiname":"Caixiaolou",
    "gn:country_code":"CN",
    "gn:dem":41,
    "gn:feature_class":"P",
    "gn:feature_code":"PPL",
    "gn:name":"Caixiaolou",
    "gn:population":0,
    "gn:timezone":"Asia/Shanghai",
    "iso:country":"CN",
    "name:zho_x_preferred":[
        "\u8521\u5c0f\u697c"
    ],
    "wof:name":"Caixiaolou",
    "wof:placetype":"locality"
},
  "geometry": {"coordinates":[116.822,34.7738],"type":"Point"}
}