{
  "type": "Feature",
  "properties": {
    "gn:admin1_code":"12.0",
    "gn:asciiname":"Yejiaba",
    "gn:country_code":"CN",
    "gn:dem":29,
    "gn:feature_class":"P",
    "gn:feature_code":"PPL",
    "gn:name":"Yejiaba",
    "gn:population":0,
    "gn:timezone":"Asia/Shanghai",
    "iso:country":"CN",
    "name:und_x_variant":[
        "\u53f6\u5bb6\u575d"
    ],
    "wof:name":"Yejiaba",
    "wof:placetype":"locality"
},
  "geometry": {"coordinates":[114.97664,30.10419000000001],"type":"Point"}
}