{
  "type": "Feature",
  "properties": {
    "gn:admin1_code":"4.0",
    "gn:asciiname":"Jianghecun",
    "gn:country_code":"CN",
    "gn:dem":3,
    "gn:feature_class":"P",
    "gn:feature_code":"PPL",
    "gn:name":"Jianghecun",
    "gn:population":0,
    "gn:timezone":"Asia/Shanghai",
    "iso:country":"CN",
    "name:zho_x_preferred":[
        "\u59dc\u4f55\u6751"
    ],
    "wof:name":"Jianghecun",
    "wof:placetype":"locality"
},
  "geometry": {"coordinates":[120.08771000000002,32.74988],"type":"Point"}
}