{
  "type": "Feature",
  "properties": {
    "gn:admin1_code":"1.0",
    "gn:asciiname":"Shanxicun",
    "gn:country_code":"CN",
    "gn:dem":46,
    "gn:feature_class":"P",
    "gn:feature_code":"PPL",
    "gn:name":"Shanxicun",
    "gn:population":0,
    "gn:timezone":"Asia/Shanghai",
    "iso:country":"CN",
    "name:zho_x_preferred":[
        "\u5c71\u897f\u6751"
    ],
    "wof:name":"Shanxicun",
    "wof:placetype":"locality"
},
  "geometry": {"coordinates":[117.07268999999999,31.91324],"type":"Point"}
}