{
  "type": "Feature",
  "properties": {
    "gn:admin1_code":"1.0",
    "gn:asciiname":"Yinzhaicun",
    "gn:country_code":"CN",
    "gn:dem":30,
    "gn:feature_class":"P",
    "gn:feature_code":"PPL",
    "gn:name":"Yinzhaicun",
    "gn:population":0,
    "gn:timezone":"Asia/Shanghai",
    "iso:country":"CN",
    "name:zho_x_preferred":[
        "\u5c39\u5be8\u6751"
    ],
    "wof:name":"Yinzhaicun",
    "wof:placetype":"locality"
},
  "geometry": {"coordinates":[115.95028000000001,32.68894],"type":"Point"}
}