{
  "type": "Feature",
  "properties": {
    "gn:admin1_code":"10",
    "gn:asciiname":"Gaoyang",
    "gn:cc2":"CN",
    "gn:country_code":"CN",
    "gn:dem":11,
    "gn:feature_class":"P",
    "gn:feature_code":"PPL",
    "gn:name":"Gaoyang",
    "gn:population":0,
    "gn:timezone":"Asia/Shanghai",
    "iso:country":"CN",
    "name:und_x_variant":[
        "Kao-yang-hsien",
        "Gaoyan",
        "Kao-yang",
        "Kao-yang-ch\u2019eng-kuan",
        "Gaoyang"
    ],
    "name:zho_x_preferred":[
        "\u9526\u534e\u8857\u9053"
    ],
    "wof:name":"Gaoyang",
    "wof:placetype":"locality"
},
  "geometry": {"coordinates":[115.77556,38.67944],"type":"Point"}
}