{
  "type": "Feature",
  "properties": {
    "gn:admin1_code":"10.0",
    "gn:asciiname":"Yujian",
    "gn:country_code":"CN",
    "gn:dem":1059,
    "gn:feature_class":"P",
    "gn:feature_code":"PPL",
    "gn:name":"Yujian",
    "gn:population":0,
    "gn:timezone":"Asia/Shanghai",
    "iso:country":"CN",
    "name:zho_x_preferred":[
        "\u6986\u6da7"
    ],
    "wof:name":"Yujian",
    "wof:placetype":"locality"
},
  "geometry": {"coordinates":[114.78588000000001,40.09791],"type":"Point"}
}