{
  "type": "Feature",
  "properties": {
    "gn:admin1_code":"15.0",
    "gn:asciiname":"Xiujiacha",
    "gn:country_code":"CN",
    "gn:dem":1750,
    "gn:feature_class":"P",
    "gn:feature_code":"PPL",
    "gn:name":"Xiujiacha",
    "gn:population":0,
    "gn:timezone":"Asia/Shanghai",
    "iso:country":"CN",
    "name:und_x_variant":[
        "\u4fee\u5bb6\u5c94"
    ],
    "wof:name":"Xiujiacha",
    "wof:placetype":"locality"
},
  "geometry": {"coordinates":[105.045,35.9229],"type":"Point"}
}