{
  "type": "Feature",
  "properties": {
    "gn:admin1_code":"11.0",
    "gn:asciiname":"Zhulongquan",
    "gn:country_code":"CN",
    "gn:dem":551,
    "gn:feature_class":"P",
    "gn:feature_code":"PPL",
    "gn:name":"Zhulongquan",
    "gn:population":0,
    "gn:timezone":"Asia/Shanghai",
    "iso:country":"CN",
    "name:zho_x_preferred":[
        "\u4f4f\u9f99\u6cc9"
    ],
    "wof:name":"Zhulongquan",
    "wof:placetype":"locality"
},
  "geometry": {"coordinates":[113.81196,27.261],"type":"Point"}
}