{
  "type": "Feature",
  "properties": {
    "gn:admin1_code":"24.0",
    "gn:asciiname":"Bandi",
    "gn:country_code":"CN",
    "gn:dem":738,
    "gn:feature_class":"P",
    "gn:feature_code":"PPL",
    "gn:name":"Bandi",
    "gn:population":0,
    "gn:timezone":"Asia/Shanghai",
    "iso:country":"CN",
    "name:ceb_x_preferred":[
        "Bandi"
    ],
    "name:deu_x_preferred":[
        "Bandi"
    ],
    "name:fra_x_preferred":[
        "Bandi"
    ],
    "name:ita_x_preferred":[
        "Bandi"
    ],
    "name:slv_x_preferred":[
        "Bandi"
    ],
    "name:swe_x_preferred":[
        "Bandi"
    ],
    "name:vie_x_preferred":[
        "Bandi"
    ],
    "name:zho_x_preferred":[
        "\u5742\u5e95"
    ],
    "wof:name":"Bandi",
    "wof:placetype":"locality"
},
  "geometry": {"coordinates":[111.60012999999999,36.56967],"type":"Point"}
}