{
  "type": "Feature",
  "properties": {
    "gn:admin1_code":"16.0",
    "gn:asciiname":"Nale",
    "gn:country_code":"CN",
    "gn:dem":652,
    "gn:feature_class":"P",
    "gn:feature_code":"PPL",
    "gn:name":"Nale",
    "gn:population":0,
    "gn:timezone":"Asia/Shanghai",
    "iso:country":"CN",
    "name:zho_x_preferred":[
        "\u90a3\u4e50"
    ],
    "wof:name":"Nale",
    "wof:placetype":"locality"
},
  "geometry": {"coordinates":[106.986,24.5946],"type":"Point"}
}