{
  "type": "Feature",
  "properties": {
    "gn:admin1_code":"26.0",
    "gn:asciiname":"Liujiawancun",
    "gn:country_code":"CN",
    "gn:dem":755,
    "gn:feature_class":"P",
    "gn:feature_code":"PPL",
    "gn:name":"Liujiawancun",
    "gn:population":0,
    "gn:timezone":"Asia/Shanghai",
    "iso:country":"CN",
    "name:zho_x_preferred":[
        "\u5218\u5bb6\u6e7e\u6751"
    ],
    "wof:name":"Liujiawancun",
    "wof:placetype":"locality"
},
  "geometry": {"coordinates":[110.20180999999999,36.85941],"type":"Point"}
}