{
  "type": "Feature",
  "properties": {
    "gn:admin1_code":"30",
    "gn:asciiname":"Dayang",
    "gn:country_code":"CN",
    "gn:dem":3,
    "gn:feature_class":"P",
    "gn:feature_code":"PPL",
    "gn:name":"Dayang",
    "gn:population":0,
    "gn:timezone":"Asia/Shanghai",
    "iso:country":"CN",
    "name:ceb_x_preferred":[
        "Dayang"
    ],
    "name:msa_x_preferred":[
        "Dayang"
    ],
    "name:swe_x_preferred":[
        "Dayang"
    ],
    "name:und_x_variant":[
        "Ta-yang",
        "Dayang",
        "\u5927\u6d0b"
    ],
    "name:zho_x_preferred":[
        "\u5927\u6d0b"
    ],
    "wof:name":"Dayang",
    "wof:placetype":"locality"
},
  "geometry": {"coordinates":[112.74775,21.93558],"type":"Point"}
}