{
  "type": "Feature",
  "properties": {
    "gn:admin1_code":"2.0",
    "gn:asciiname":"Zhujiabang",
    "gn:country_code":"CN",
    "gn:dem":5,
    "gn:feature_class":"P",
    "gn:feature_code":"PPL",
    "gn:name":"Zhujiabang",
    "gn:population":0,
    "gn:timezone":"Asia/Shanghai",
    "iso:country":"CN",
    "name:und_x_variant":[
        "\u7af9\u5bb6\u6d5c"
    ],
    "wof:name":"Zhujiabang",
    "wof:placetype":"locality"
},
  "geometry": {"coordinates":[120.87356,30.8927],"type":"Point"}
}