{
  "type": "Feature",
  "properties": {
    "gn:admin1_code":"19.0",
    "gn:asciiname":"Hudiegou",
    "gn:country_code":"CN",
    "gn:dem":208,
    "gn:feature_class":"P",
    "gn:feature_code":"PPL",
    "gn:name":"Hudiegou",
    "gn:population":0,
    "gn:timezone":"Asia/Shanghai",
    "iso:country":"CN",
    "name:und_x_variant":[
        "\u8774\u8776\u6c9f"
    ],
    "name:zho_x_preferred":[
        "\u8774\u8776\u6c9f"
    ],
    "wof:name":"Hudiegou",
    "wof:placetype":"locality"
},
  "geometry": {"coordinates":[120.77556,41.62503],"type":"Point"}
}