{
  "type": "Feature",
  "properties": {
    "gn:admin1_code":"14.0",
    "gn:asciiname":"Sanggyu",
    "gn:country_code":"CN",
    "gn:dem":3546,
    "gn:feature_class":"P",
    "gn:feature_code":"PPL",
    "gn:name":"Sanggyu",
    "gn:population":0,
    "gn:timezone":"Asia/Urumqi",
    "iso:country":"CN",
    "name:bod_x_preferred":[
        "Sanggyu"
    ],
    "name:zho_x_preferred":[
        "Sangjiu"
    ],
    "name:zho_x_variant":[
        "\u6851\u4e45"
    ],
    "wof:name":"Sanggyu",
    "wof:placetype":"locality"
},
  "geometry": {"coordinates":[97.50752,28.77519],"type":"Point"}
}