{
  "type": "Feature",
  "properties": {
    "gn:admin1_code":"2.0",
    "gn:asciiname":"Lishan",
    "gn:country_code":"CN",
    "gn:dem":13,
    "gn:feature_class":"P",
    "gn:feature_code":"PPLA4",
    "gn:name":"Lishan",
    "gn:population":0,
    "gn:timezone":"Asia/Shanghai",
    "iso:country":"CN",
    "name:ceb_x_preferred":[
        "Lishan"
    ],
    "name:deu_x_preferred":[
        "Lishan"
    ],
    "name:nor_x_preferred":[
        "Lishan"
    ],
    "name:und_x_variant":[
        "\u91cc\u5c71",
        "Lishan Zhen",
        "\u91cc\u5c71\u9547"
    ],
    "wof:name":"Lishan",
    "wof:placetype":"locality"
},
  "geometry": {"coordinates":[120.06206,30.05033],"type":"Point"}
}