{
  "type": "Feature",
  "properties": {
    "gn:admin1_code":"15.0",
    "gn:asciiname":"Lucaogou",
    "gn:country_code":"CN",
    "gn:dem":1944,
    "gn:feature_class":"P",
    "gn:feature_code":"PPL",
    "gn:name":"Lucaogou",
    "gn:population":0,
    "gn:timezone":"Asia/Shanghai",
    "iso:country":"CN",
    "name:und_x_variant":[
        "\u82a6\u8349\u6c9f"
    ],
    "wof:name":"Lucaogou",
    "wof:placetype":"locality"
},
  "geometry": {"coordinates":[106.52248,36.65056],"type":"Point"}
}