{
  "type": "Feature",
  "properties": {
    "gn:admin1_code":"14",
    "gn:asciiname":"Wuri",
    "gn:country_code":"CN",
    "gn:dem":4165,
    "gn:feature_class":"P",
    "gn:feature_code":"PPL",
    "gn:name":"Wuri",
    "gn:population":0,
    "gn:timezone":"Asia/Urumqi",
    "iso:country":"CN",
    "name:ceb_x_preferred":[
        "Wuri"
    ],
    "name:deu_x_preferred":[
        "Wuri"
    ],
    "name:swe_x_preferred":[
        "Wuri"
    ],
    "name:zho_x_preferred":[
        "\u6b66\u65e5"
    ],
    "wof:name":"Wuri",
    "wof:placetype":"locality"
},
  "geometry": {"coordinates":[89.1288,28.8714],"type":"Point"}
}