{
  "type": "Feature",
  "properties": {
    "gn:admin1_code":"7",
    "gn:asciiname":"Dinggang",
    "gn:cc2":"CN",
    "gn:country_code":"CN",
    "gn:dem":17,
    "gn:feature_class":"P",
    "gn:feature_code":"PPL",
    "gn:name":"Dinggang",
    "gn:population":0,
    "gn:timezone":"Asia/Shanghai",
    "iso:country":"CN",
    "name:und_x_variant":[
        "Ting-chiang",
        "Dinggang"
    ],
    "wof:name":"Dinggang",
    "wof:placetype":"locality"
},
  "geometry": {"coordinates":[119.29472,25.30639],"type":"Point"}
}