{
  "type": "Feature",
  "properties": {
    "gn:admin1_code":"9.0",
    "gn:asciiname":"Zhaozhongpu",
    "gn:country_code":"CN",
    "gn:dem":117,
    "gn:feature_class":"P",
    "gn:feature_code":"PPL",
    "gn:name":"Zhaozhongpu",
    "gn:population":0,
    "gn:timezone":"Asia/Shanghai",
    "iso:country":"CN",
    "name:zho_x_preferred":[
        "\u8d75\u4e2d\u94fa"
    ],
    "wof:name":"Zhaozhongpu",
    "wof:placetype":"locality"
},
  "geometry": {"coordinates":[112.76721999999999,32.76306],"type":"Point"}
}