{
  "type": "Feature",
  "properties": {
    "gn:admin1_code":"29.0",
    "gn:asciiname":"Xiaotuanshan",
    "gn:country_code":"CN",
    "gn:dem":1172,
    "gn:feature_class":"P",
    "gn:feature_code":"PPL",
    "gn:name":"Xiaotuanshan",
    "gn:population":0,
    "gn:timezone":"Asia/Shanghai",
    "iso:country":"CN",
    "name:zho_x_preferred":[
        "\u5c0f\u56e2\u5c71"
    ],
    "wof:name":"Xiaotuanshan",
    "wof:placetype":"locality"
},
  "geometry": {"coordinates":[100.93300000000001,24.2826],"type":"Point"}
}