{
  "type": "Feature",
  "properties": {
    "gn:admin1_code":"26.0",
    "gn:asciiname":"Yaoxian",
    "gn:country_code":"CN",
    "gn:dem":1082,
    "gn:feature_class":"P",
    "gn:feature_code":"PPL",
    "gn:name":"Yaoxian",
    "gn:population":0,
    "gn:timezone":"Asia/Shanghai",
    "iso:country":"CN",
    "name:zho_x_preferred":[
        "\u5d3e\u5c98"
    ],
    "wof:name":"Yaoxian",
    "wof:placetype":"locality"
},
  "geometry": {"coordinates":[108.82393999999999,35.06741],"type":"Point"}
}