{
  "type": "Feature",
  "properties": {
    "gn:admin1_code":"19.0",
    "gn:asciiname":"Hapengyingzicun",
    "gn:country_code":"CN",
    "gn:dem":190,
    "gn:feature_class":"P",
    "gn:feature_code":"PPL",
    "gn:name":"Hapengyingzicun",
    "gn:population":0,
    "gn:timezone":"Asia/Shanghai",
    "iso:country":"CN",
    "name:zho_x_preferred":[
        "\u54c8\u670b\u8425\u5b50\u6751"
    ],
    "wof:name":"Hapengyingzicun",
    "wof:placetype":"locality"
},
  "geometry": {"coordinates":[121.676,42.0871],"type":"Point"}
}