{
  "type": "Feature",
  "properties": {
    "gn:admin1_code":"30",
    "gn:asciiname":"Dunzai",
    "gn:country_code":"CN",
    "gn:dem":35,
    "gn:feature_class":"P",
    "gn:feature_code":"PPL",
    "gn:name":"Dunzai",
    "gn:population":0,
    "gn:timezone":"Asia/Urumqi",
    "iso:country":"CN",
    "name:zho_x_preferred":[
        "\u58a9\u4ed4"
    ],
    "wof:name":"Dunzai",
    "wof:placetype":"locality"
},
  "geometry": {"coordinates":[110.28169,21.65136],"type":"Point"}
}