{
  "type": "Feature",
  "properties": {
    "gn:admin1_code":"33.0",
    "gn:asciiname":"Meichi",
    "gn:country_code":"CN",
    "gn:dem":343,
    "gn:feature_class":"P",
    "gn:feature_code":"PPL",
    "gn:name":"Meichi",
    "gn:population":0,
    "gn:timezone":"Asia/Shanghai",
    "iso:country":"CN",
    "name:zho_x_preferred":[
        "\u6885\u6c60"
    ],
    "wof:name":"Meichi",
    "wof:placetype":"locality"
},
  "geometry": {"coordinates":[108.45237,31.05592],"type":"Point"}
}