{
  "type": "Feature",
  "properties": {
    "gn:admin1_code":"15.0",
    "gn:asciiname":"Yangdazhuang",
    "gn:country_code":"CN",
    "gn:dem":1652,
    "gn:feature_class":"P",
    "gn:feature_code":"PPL",
    "gn:name":"Yangdazhuang",
    "gn:population":0,
    "gn:timezone":"Asia/Shanghai",
    "iso:country":"CN",
    "name:zho_x_preferred":[
        "\u6768\u5927\u5e84"
    ],
    "wof:name":"Yangdazhuang",
    "wof:placetype":"locality"
},
  "geometry": {"coordinates":[106.53400000000001,35.3151],"type":"Point"}
}