{
  "type": "Feature",
  "properties": {
    "gn:admin1_code":"2.0",
    "gn:asciiname":"Tali",
    "gn:country_code":"CN",
    "gn:dem":6,
    "gn:feature_class":"P",
    "gn:feature_code":"PPL",
    "gn:name":"Tali",
    "gn:population":0,
    "gn:timezone":"Asia/Shanghai",
    "iso:country":"CN",
    "name:ceb_x_preferred":[
        "Tali"
    ],
    "name:deu_x_preferred":[
        "Tali"
    ],
    "name:fin_x_preferred":[
        "Tali"
    ],
    "name:fra_x_preferred":[
        "Tali"
    ],
    "name:heb_x_preferred":[
        "\u05d8\u05dc\u05d9"
    ],
    "name:nld_x_preferred":[
        "Tali"
    ],
    "name:ron_x_preferred":[
        "Tali"
    ],
    "name:rus_x_preferred":[
        "\u0422\u0430\u043b\u0438"
    ],
    "name:swe_x_preferred":[
        "Tali"
    ],
    "name:zho_x_preferred":[
        "\u5854\u91cc"
    ],
    "wof:name":"Tali",
    "wof:placetype":"locality"
},
  "geometry": {"coordinates":[120.45416000000002,27.52284],"type":"Point"}
}