{
  "type": "Feature",
  "properties": {
    "gn:admin1_code":"32",
    "gn:asciiname":"Legsang",
    "gn:country_code":"CN",
    "gn:dem":3575,
    "gn:feature_class":"P",
    "gn:feature_code":"PPL",
    "gn:name":"L\u00eagsang",
    "gn:population":0,
    "gn:timezone":"Asia/Shanghai",
    "iso:country":"CN",
    "wof:name":"Legsang",
    "wof:placetype":"locality"
},
  "geometry": {"coordinates":[101.84999999999999,28.93333],"type":"Point"}
}