{
  "type": "Feature",
  "properties": {
    "gn:admin1_code":"12.0",
    "gn:asciiname":"Leijiayuan",
    "gn:country_code":"CN",
    "gn:dem":371,
    "gn:feature_class":"P",
    "gn:feature_code":"PPL",
    "gn:name":"Leijiayuan",
    "gn:population":0,
    "gn:timezone":"Asia/Shanghai",
    "iso:country":"CN",
    "name:zho_x_preferred":[
        "\u96f7\u5bb6\u9662"
    ],
    "wof:name":"Leijiayuan",
    "wof:placetype":"locality"
},
  "geometry": {"coordinates":[111.01585,32.7799],"type":"Point"}
}