{
  "type": "Feature",
  "properties": {
    "gn:admin1_code":"18",
    "gn:asciiname":"Luowozhai",
    "gn:country_code":"CN",
    "gn:dem":1419,
    "gn:feature_class":"P",
    "gn:feature_code":"PPL",
    "gn:name":"Luowozhai",
    "gn:population":0,
    "gn:timezone":"Asia/Shanghai",
    "iso:country":"CN",
    "name:zho_x_preferred":[
        "\u843d\u7a9d\u5be8"
    ],
    "wof:name":"Luowozhai",
    "wof:placetype":"locality"
},
  "geometry": {"coordinates":[105.16500000000001,27.1049],"type":"Point"}
}