{
  "type": "Feature",
  "properties": {
    "gn:admin1_code":"10.0",
    "gn:asciiname":"Hanji",
    "gn:country_code":"CN",
    "gn:dem":13,
    "gn:feature_class":"P",
    "gn:feature_code":"PPL",
    "gn:name":"Hanji",
    "gn:population":0,
    "gn:timezone":"Asia/Shanghai",
    "iso:country":"CN",
    "name:ceb_x_preferred":[
        "Hanji"
    ],
    "name:swe_x_preferred":[
        "Hanji"
    ],
    "name:zho_x_preferred":[
        "\u97e9\u96c6"
    ],
    "wof:name":"Hanji",
    "wof:placetype":"locality"
},
  "geometry": {"coordinates":[116.44,38.1009],"type":"Point"}
}