{
  "type": "Feature",
  "properties": {
    "gn:admin1_code":"5.0",
    "gn:asciiname":"Chaifucun",
    "gn:country_code":"CN",
    "gn:dem":205,
    "gn:feature_class":"P",
    "gn:feature_code":"PPL",
    "gn:name":"Chaifucun",
    "gn:population":0,
    "gn:timezone":"Asia/Shanghai",
    "iso:country":"CN",
    "name:zho_x_preferred":[
        "\u67f4\u798f\u6751"
    ],
    "wof:name":"Chaifucun",
    "wof:placetype":"locality"
},
  "geometry": {"coordinates":[126.06932,44.35649],"type":"Point"}
}