{
  "type": "Feature",
  "properties": {
    "gn:admin1_code":"02",
    "gn:asciiname":"Shaojia",
    "gn:country_code":"CN",
    "gn:dem":4,
    "gn:feature_class":"P",
    "gn:feature_code":"PPL",
    "gn:name":"Shaojia",
    "gn:population":0,
    "gn:timezone":"Asia/Shanghai",
    "iso:country":"CN",
    "name:und_x_variant":[
        "Shaojiaqiao",
        "\u90b5\u5bb6\u6865",
        "Shaojia"
    ],
    "name:zho_x_preferred":[
        "\u90b5\u5bb6"
    ],
    "wof:name":"Shaojia",
    "wof:placetype":"locality"
},
  "geometry": {"coordinates":[121.0171,30.73721],"type":"Point"}
}