{
  "type": "Feature",
  "properties": {
    "gn:admin1_code":"14.0",
    "gn:asciiname":"Paggarama",
    "gn:country_code":"CN",
    "gn:dem":4923,
    "gn:feature_class":"P",
    "gn:feature_code":"PPL",
    "gn:name":"Paggarama",
    "gn:population":0,
    "gn:timezone":"Asia/Urumqi",
    "iso:country":"CN",
    "name:bod_x_preferred":[
        "Paggarama"
    ],
    "name:zho_x_preferred":[
        "Pagarema"
    ],
    "name:zho_x_variant":[
        "\u5e15\u560e\u60f9\u739b",
        "Zhasa Gongshe",
        "\u624e\u8428\u516c\u793e"
    ],
    "wof:name":"Paggarama",
    "wof:placetype":"locality"
},
  "geometry": {"coordinates":[91.301,32.801],"type":"Point"}
}