{
  "type": "Feature",
  "properties": {
    "gn:admin1_code":"32",
    "gn:asciiname":"Amu",
    "gn:country_code":"CN",
    "gn:dem":3477,
    "gn:feature_class":"P",
    "gn:feature_code":"PPL",
    "gn:name":"Amu",
    "gn:population":0,
    "gn:timezone":"Asia/Shanghai",
    "iso:country":"CN",
    "name:und_x_variant":[
        "Amoikog",
        "Amu"
    ],
    "name:zho_x_preferred":[
        "\u963f\u6728"
    ],
    "wof:name":"Amu",
    "wof:placetype":"locality"
},
  "geometry": {"coordinates":[102.62942,32.91739],"type":"Point"}
}