{
  "type": "Feature",
  "properties": {
    "gn:admin1_code":"10",
    "gn:asciiname":"Ershisanqing",
    "gn:country_code":"CN",
    "gn:dem":1440,
    "gn:feature_class":"P",
    "gn:feature_code":"PPL",
    "gn:name":"Ershisanqing",
    "gn:population":0,
    "gn:timezone":"Asia/Shanghai",
    "iso:country":"CN",
    "name:zho_x_preferred":[
        "\u4e8c\u5341\u4e09\u9877"
    ],
    "wof:name":"Ershisanqing",
    "wof:placetype":"locality"
},
  "geometry": {"coordinates":[114.67097,41.79117],"type":"Point"}
}