{
  "type": "Feature",
  "properties": {
    "gn:admin1_code":"2.0",
    "gn:asciiname":"Xuantengshan",
    "gn:country_code":"CN",
    "gn:dem":579,
    "gn:feature_class":"P",
    "gn:feature_code":"PPL",
    "gn:name":"Xuantengshan",
    "gn:population":0,
    "gn:timezone":"Asia/Shanghai",
    "iso:country":"CN",
    "name:zho_x_preferred":[
        "\u60ac\u85e4\u5c71"
    ],
    "wof:name":"Xuantengshan",
    "wof:placetype":"locality"
},
  "geometry": {"coordinates":[120.2099,28.68701],"type":"Point"}
}