{
  "type": "Feature",
  "properties": {
    "gn:admin1_code":"4.0",
    "gn:asciiname":"Dongqi",
    "gn:country_code":"CN",
    "gn:dem":1,
    "gn:feature_class":"P",
    "gn:feature_code":"PPL",
    "gn:name":"Dongqi",
    "gn:population":0,
    "gn:timezone":"Asia/Shanghai",
    "iso:country":"CN",
    "name:und_x_variant":[
        "\u4e1c\u7941"
    ],
    "name:zho_x_preferred":[
        "\u4e1c\u7941"
    ],
    "wof:name":"Dongqi",
    "wof:placetype":"locality"
},
  "geometry": {"coordinates":[120.14196,33.06134],"type":"Point"}
}