{
  "type": "Feature",
  "properties": {
    "gn:admin1_code":"33.0",
    "gn:asciiname":"Xiongjiayan",
    "gn:country_code":"CN",
    "gn:dem":635,
    "gn:feature_class":"P",
    "gn:feature_code":"PPL",
    "gn:name":"Xiongjiayan",
    "gn:population":0,
    "gn:timezone":"Asia/Shanghai",
    "iso:country":"CN",
    "name:zho_x_preferred":[
        "\u718a\u5bb6\u5ca9"
    ],
    "wof:name":"Xiongjiayan",
    "wof:placetype":"locality"
},
  "geometry": {"coordinates":[107.80501,30.11648],"type":"Point"}
}