{
  "type": "Feature",
  "properties": {
    "gn:admin1_code":"25",
    "gn:asciiname":"Shiguzhuang",
    "gn:country_code":"CN",
    "gn:dem":169,
    "gn:feature_class":"P",
    "gn:feature_code":"PPL",
    "gn:name":"Shiguzhuang",
    "gn:population":0,
    "gn:timezone":"Asia/Shanghai",
    "iso:country":"CN",
    "name:zho_x_preferred":[
        "\u77f3\u5d2e\u5e84"
    ],
    "wof:name":"Shiguzhuang",
    "wof:placetype":"locality"
},
  "geometry": {"coordinates":[117.607,35.4775],"type":"Point"}
}