{
  "type": "Feature",
  "properties": {
    "gn:admin1_code":"32.0",
    "gn:asciiname":"Yuri",
    "gn:country_code":"CN",
    "gn:dem":2699,
    "gn:feature_class":"P",
    "gn:feature_code":"PPL",
    "gn:name":"Yuri",
    "gn:population":0,
    "gn:timezone":"Asia/Shanghai",
    "iso:country":"CN",
    "name:zho_x_preferred":[
        "\u9c7c\u65e5"
    ],
    "wof:name":"Yuri",
    "wof:placetype":"locality"
},
  "geometry": {"coordinates":[101.986,30.7021],"type":"Point"}
}