{
  "type": "Feature",
  "properties": {
    "gn:admin1_code":"16.0",
    "gn:asciiname":"Longtaicao",
    "gn:country_code":"CN",
    "gn:dem":977,
    "gn:feature_class":"P",
    "gn:feature_code":"PPL",
    "gn:name":"Longtaicao",
    "gn:population":0,
    "gn:timezone":"Asia/Shanghai",
    "iso:country":"CN",
    "name:zho_x_preferred":[
        "\u9647\u53f0\u69fd"
    ],
    "wof:name":"Longtaicao",
    "wof:placetype":"locality"
},
  "geometry": {"coordinates":[106.325,24.8546],"type":"Point"}
}