{
  "type": "Feature",
  "properties": {
    "gn:admin1_code":"14.0",
    "gn:asciiname":"Chongdun'ogka",
    "gn:country_code":"CN",
    "gn:dem":4622,
    "gn:feature_class":"P",
    "gn:feature_code":"PPL",
    "gn:name":"Chongd\u00fcn\u2019ogka",
    "gn:population":0,
    "gn:timezone":"Asia/Urumqi",
    "iso:country":"CN",
    "name:bod_x_preferred":[
        "Chongd\u00fcn\u2019ogka"
    ],
    "name:zho_x_preferred":[
        "Zhongdui\u2019ega"
    ],
    "name:zho_x_variant":[
        "\u4ef2\u5806\u4fc4\u560e",
        "Zhongdui Gongshe",
        "\u4ef2\u5806\u516c\u793e"
    ],
    "wof:name":"Chongdun'ogka",
    "wof:placetype":"locality"
},
  "geometry": {"coordinates":[91.60599999999999,28.906],"type":"Point"}
}