{
  "type": "Feature",
  "properties": {
    "gn:admin1_code":"32.0",
    "gn:asciiname":"Wajinggou",
    "gn:country_code":"CN",
    "gn:dem":1973,
    "gn:feature_class":"P",
    "gn:feature_code":"PPL",
    "gn:name":"Wajinggou",
    "gn:population":0,
    "gn:timezone":"Asia/Shanghai",
    "iso:country":"CN",
    "name:zho_x_preferred":[
        "\u74e6\u4e95\u6c9f"
    ],
    "wof:name":"Wajinggou",
    "wof:placetype":"locality"
},
  "geometry": {"coordinates":[103.30500000000001,27.778],"type":"Point"}
}