{
  "type": "Feature",
  "properties": {
    "gn:admin1_code":"03",
    "gn:asciiname":"Caoxi",
    "gn:country_code":"CN",
    "gn:dem":174,
    "gn:feature_class":"P",
    "gn:feature_code":"PPLA4",
    "gn:name":"Caoxi",
    "gn:population":0,
    "gn:timezone":"Asia/Shanghai",
    "iso:country":"CN",
    "name:und_x_variant":[
        "Ts\u2019ao-hsi",
        "Caoxi Zhen",
        "Caoxi"
    ],
    "name:zho_x_preferred":[
        "\u66f9\u6eaa"
    ],
    "wof:name":"Caoxi",
    "wof:placetype":"locality"
},
  "geometry": {"coordinates":[117.34417000000001,28.70242],"type":"Point"}
}