{
  "type": "Feature",
  "properties": {
    "gn:admin1_code":"8.0",
    "gn:asciiname":"Yangshidi",
    "gn:country_code":"CN",
    "gn:dem":132,
    "gn:feature_class":"P",
    "gn:feature_code":"PPL",
    "gn:name":"Yangshidi",
    "gn:population":0,
    "gn:timezone":"Asia/Shanghai",
    "iso:country":"CN",
    "name:zho_x_preferred":[
        "\u7f8a\u5e02\u5730"
    ],
    "wof:name":"Yangshidi",
    "wof:placetype":"locality"
},
  "geometry": {"coordinates":[124.69765,45.47284000000001],"type":"Point"}
}