{
  "type": "Feature",
  "properties": {
    "gn:admin1_code":"29.0",
    "gn:asciiname":"Xiapujia",
    "gn:country_code":"CN",
    "gn:dem":2365,
    "gn:feature_class":"P",
    "gn:feature_code":"PPL",
    "gn:name":"Xiapujia",
    "gn:population":0,
    "gn:timezone":"Asia/Shanghai",
    "iso:country":"CN",
    "name:zho_x_preferred":[
        "\u4e0b\u94fa\u621b"
    ],
    "wof:name":"Xiapujia",
    "wof:placetype":"locality"
},
  "geometry": {"coordinates":[103.01900000000001,25.7468],"type":"Point"}
}