{
  "type": "Feature",
  "properties": {
    "gn:admin1_code":"9.0",
    "gn:asciiname":"Fengshan",
    "gn:country_code":"CN",
    "gn:dem":178,
    "gn:feature_class":"P",
    "gn:feature_code":"PPL",
    "gn:name":"Fengshan",
    "gn:population":0,
    "gn:timezone":"Asia/Shanghai",
    "iso:country":"CN",
    "name:ceb_x_preferred":[
        "Fengshan"
    ],
    "name:deu_x_preferred":[
        "Fengshan"
    ],
    "name:fra_x_preferred":[
        "Fengshan"
    ],
    "name:nor_x_preferred":[
        "Fengshan"
    ],
    "name:swe_x_preferred":[
        "Fengshan"
    ],
    "name:und_x_variant":[
        "\u4e30\u5c71",
        "Fengshan"
    ],
    "name:vie_x_preferred":[
        "Ph\u01b0\u1ee3ng S\u01a1n"
    ],
    "wof:name":"Fengshan",
    "wof:placetype":"locality"
},
  "geometry": {"coordinates":[112.85980000000001,33.22743],"type":"Point"}
}