{
  "type": "Feature",
  "properties": {
    "gn:admin1_code":"12",
    "gn:asciiname":"Jingjiazhuang",
    "gn:cc2":"CN",
    "gn:country_code":"CN",
    "gn:dem":1016,
    "gn:feature_class":"P",
    "gn:feature_code":"PPL",
    "gn:name":"Jingjiazhuang",
    "gn:population":0,
    "gn:timezone":"Asia/Shanghai",
    "iso:country":"CN",
    "name:und_x_variant":[
        "Ching-chia-chuang",
        "Jingjiazhuang"
    ],
    "wof:name":"Jingjiazhuang",
    "wof:placetype":"locality"
},
  "geometry": {"coordinates":[109.93333,32.96667],"type":"Point"}
}