{
  "type": "Feature",
  "properties": {
    "gn:admin1_code":"30",
    "gn:asciiname":"Xiagaoling",
    "gn:country_code":"CN",
    "gn:dem":144,
    "gn:feature_class":"P",
    "gn:feature_code":"PPL",
    "gn:name":"Xiagaoling",
    "gn:population":0,
    "gn:timezone":"Asia/Shanghai",
    "iso:country":"CN",
    "name:und_x_variant":[
        "Shanggaoling",
        "Xiagaoling"
    ],
    "name:zho_x_preferred":[
        "\u4e0b\u544a\u5cad"
    ],
    "wof:name":"Xiagaoling",
    "wof:placetype":"locality"
},
  "geometry": {"coordinates":[115.58092000000001,23.60462],"type":"Point"}
}