{
  "type": "Feature",
  "properties": {
    "gn:admin1_code":"5.0",
    "gn:asciiname":"Bagedaicun",
    "gn:country_code":"CN",
    "gn:dem":144,
    "gn:feature_class":"P",
    "gn:feature_code":"PPL",
    "gn:name":"Bagedaicun",
    "gn:population":0,
    "gn:timezone":"Asia/Shanghai",
    "iso:country":"CN",
    "name:zho_x_preferred":[
        "\u516b\u5404\u6b79\u6751"
    ],
    "wof:name":"Bagedaicun",
    "wof:placetype":"locality"
},
  "geometry": {"coordinates":[123.23390999999999,45.66351],"type":"Point"}
}