{
  "type": "Feature",
  "properties": {
    "gn:admin1_code":"29.0",
    "gn:asciiname":"Xinbaozhai",
    "gn:country_code":"CN",
    "gn:dem":1503,
    "gn:feature_class":"P",
    "gn:feature_code":"PPL",
    "gn:name":"Xinbaozhai",
    "gn:population":0,
    "gn:timezone":"Asia/Shanghai",
    "iso:country":"CN",
    "name:zho_x_preferred":[
        "\u65b0\u4fdd\u5be8"
    ],
    "wof:name":"Xinbaozhai",
    "wof:placetype":"locality"
},
  "geometry": {"coordinates":[104.307,22.9365],"type":"Point"}
}