{
  "type": "Feature",
  "properties": {
    "gn:admin1_code":"18",
    "gn:asciiname":"Canggeng",
    "gn:cc2":"CN",
    "gn:country_code":"CN",
    "gn:dem":1223,
    "gn:feature_class":"P",
    "gn:feature_code":"PPL",
    "gn:name":"Canggeng",
    "gn:population":0,
    "gn:timezone":"Asia/Shanghai",
    "iso:country":"CN",
    "name:und_x_variant":[
        "Ts\u2019ang-keng",
        "Canggeng"
    ],
    "wof:name":"Canggeng",
    "wof:placetype":"locality"
},
  "geometry": {"coordinates":[104.73333,24.75],"type":"Point"}
}