{
  "type": "Feature",
  "properties": {
    "gn:admin1_code":"12.0",
    "gn:asciiname":"Shibeiwu",
    "gn:country_code":"CN",
    "gn:dem":114,
    "gn:feature_class":"P",
    "gn:feature_code":"PPL",
    "gn:name":"Shibeiwu",
    "gn:population":0,
    "gn:timezone":"Asia/Shanghai",
    "iso:country":"CN",
    "name:zho_x_preferred":[
        "Shibeiwu"
    ],
    "name:zho_x_variant":[
        "\u77f3\u80cc\u5434"
    ],
    "wof:name":"Shibeiwu",
    "wof:placetype":"locality"
},
  "geometry": {"coordinates":[114.38527000000001,29.55184],"type":"Point"}
}