{
  "type": "Feature",
  "properties": {
    "gn:admin1_code":"19.0",
    "gn:asciiname":"Wolongfang",
    "gn:country_code":"CN",
    "gn:dem":38,
    "gn:feature_class":"P",
    "gn:feature_code":"PPL",
    "gn:name":"Wolongfang",
    "gn:population":0,
    "gn:timezone":"Asia/Shanghai",
    "iso:country":"CN",
    "name:zho_x_preferred":[
        "\u5367\u9f99\u623f"
    ],
    "wof:name":"Wolongfang",
    "wof:placetype":"locality"
},
  "geometry": {"coordinates":[121.58499999999999,39.8362],"type":"Point"}
}