{
  "type": "Feature",
  "properties": {
    "gn:admin1_code":"21",
    "gn:asciiname":"Gaoshawo",
    "gn:cc2":"CN",
    "gn:country_code":"CN",
    "gn:dem":1435,
    "gn:feature_class":"P",
    "gn:feature_code":"PPL",
    "gn:name":"Gaoshawo",
    "gn:population":0,
    "gn:timezone":"Asia/Shanghai",
    "iso:country":"CN",
    "name:und_x_variant":[
        "Kao-sha-wo",
        "Gaoshawo"
    ],
    "wof:name":"Gaoshawo",
    "wof:placetype":"locality"
},
  "geometry": {"coordinates":[107.03333000000001,38.01667],"type":"Point"}
}