{
  "type": "Feature",
  "properties": {
    "gn:admin1_code":"29",
    "gn:asciiname":"Mosuo",
    "gn:country_code":"CN",
    "gn:dem":723,
    "gn:feature_class":"P",
    "gn:feature_code":"PPL",
    "gn:name":"Mosuo",
    "gn:population":0,
    "gn:timezone":"Asia/Shanghai",
    "iso:country":"CN",
    "name:azb_x_preferred":[
        "\u0645\u0648\u0633\u0648\u0648\u200c\u0644\u0627\u0631"
    ],
    "name:aze_x_preferred":[
        "Mosuolar"
    ],
    "name:cat_x_preferred":[
        "Mosuo"
    ],
    "name:dan_x_preferred":[
        "Mosuo"
    ],
    "name:deu_x_preferred":[
        "Mosuo"
    ],
    "name:fas_x_preferred":[
        "\u0642\u0648\u0645 \u0645\u0648\u0633\u0648"
    ],
    "name:fra_x_preferred":[
        "Moso"
    ],
    "name:glg_x_preferred":[
        "Pobo mosuo"
    ],
    "name:heb_x_preferred":[
        "\u05de\u05d5\u05e1\u05d5\u05d0\u05d5"
    ],
    "name:ita_x_preferred":[
        "Mosuo"
    ],
    "name:kor_x_preferred":[
        "\ubaa8\uc480\uc871"
    ],
    "name:mal_x_preferred":[
        "\u0d2e\u0d4b\u0d38\u0d4b \u0d1c\u0d28\u0d19\u0d4d\u0d19\u0d7e"
    ],
    "name:pol_x_preferred":[
        "Mosuo"
    ],
    "name:por_x_preferred":[
        "Mosuo"
    ],
    "name:rus_x_preferred":[
        "\u041c\u043e\u0441\u043e"
    ],
    "name:spa_x_preferred":[
        "Mosuo"
    ],
    "name:tat_x_preferred":[
        "\u041c\u043e\u0441\u043e \u0445\u0430\u043b\u043a\u044b"
    ],
    "name:tur_x_preferred":[
        "Mosuolar"
    ],
    "name:ukr_x_preferred":[
        "\u041c\u043e\u0441\u0443\u043e"
    ],
    "name:vie_x_preferred":[
        "Ng\u01b0\u1eddi Mosuo"
    ],
    "name:zho_x_preferred":[
        "\u6a21\u7d22"
    ],
    "name:zho_x_variant":[
        "\u6469\u68ad\u4eba"
    ],
    "wof:name":"Mosuo",
    "wof:placetype":"locality"
},
  "geometry": {"coordinates":[104.917,23.2986],"type":"Point"}
}