{
  "type": "Feature",
  "properties": {
    "gn:admin1_code":"29",
    "gn:asciiname":"Mosuo",
    "gn:country_code":"CN",
    "gn:dem":723,
    "gn:feature_class":"P",
    "gn:feature_code":"PPL",
    "gn:name":"Mosuo",
    "gn:population":0,
    "gn:timezone":"Asia/Shanghai",
    "iso:country":"CN",
    "name:zho_x_preferred":[
        "\u6a21\u7d22"
    ],
    "wof:name":"Mosuo",
    "wof:placetype":"locality"
},
  "geometry": {"coordinates":[104.917,23.2986],"type":"Point"}
}