{
  "type": "Feature",
  "properties": {
    "gn:admin1_code":"30",
    "gn:asciiname":"Xiaoliang",
    "gn:country_code":"CN",
    "gn:dem":16,
    "gn:feature_class":"P",
    "gn:feature_code":"PPLA4",
    "gn:name":"Xiaoliang",
    "gn:population":0,
    "gn:timezone":"Asia/Urumqi",
    "iso:country":"CN",
    "name:und_x_variant":[
        "Xiaoliang Zhen",
        "\u5c0f\u826f\u9547"
    ],
    "name:zho_x_preferred":[
        "\u5c0f\u826f"
    ],
    "wof:name":"Xiaoliang",
    "wof:placetype":"locality"
},
  "geometry": {"coordinates":[110.89064999999999,21.4931],"type":"Point"}
}