{
  "type": "Feature",
  "properties": {
    "gn:admin1_code":"16.0",
    "gn:asciiname":"Xuantun",
    "gn:country_code":"CN",
    "gn:dem":668,
    "gn:feature_class":"P",
    "gn:feature_code":"PPL",
    "gn:name":"Xuantun",
    "gn:population":0,
    "gn:timezone":"Asia/Shanghai",
    "iso:country":"CN",
    "name:zho_x_preferred":[
        "\u7384\u5c6f"
    ],
    "wof:name":"Xuantun",
    "wof:placetype":"locality"
},
  "geometry": {"coordinates":[106.89,23.0259],"type":"Point"}
}