{
  "type": "Feature",
  "properties": {
    "gn:admin1_code":"1.0",
    "gn:asciiname":"Kengkou",
    "gn:country_code":"CN",
    "gn:dem":107,
    "gn:feature_class":"P",
    "gn:feature_code":"PPL",
    "gn:name":"Kengkou",
    "gn:population":0,
    "gn:timezone":"Asia/Shanghai",
    "iso:country":"CN",
    "name:und_x_variant":[
        "Hs\u00fceh-k\u2019eng-k\u2019ou",
        "Hsieh-k\u2019eng",
        "Hsieh-k\u2019eng-k\u2019ou",
        "Hsieh-k\u2019ou-an",
        "Xuekengkou"
    ],
    "name:zho_x_preferred":[
        "\u5751\u53e3"
    ],
    "wof:name":"Kengkou",
    "wof:placetype":"locality"
},
  "geometry": {"coordinates":[118.52551,29.81459000000001],"type":"Point"}
}