{
  "type": "Feature",
  "properties": {
    "gn:admin1_code":"11",
    "gn:asciiname":"Caijia Yuanzi",
    "gn:country_code":"CN",
    "gn:dem":130,
    "gn:feature_class":"P",
    "gn:feature_code":"PPL",
    "gn:name":"Caijia Yuanzi",
    "gn:population":0,
    "gn:timezone":"Asia/Shanghai",
    "iso:country":"CN",
    "name:zho_x_preferred":[
        "\u8521\u5bb6\u9662\u5b50"
    ],
    "wof:name":"Caijia Yuanzi",
    "wof:placetype":"locality"
},
  "geometry": {"coordinates":[111.49612999999999,26.59926],"type":"Point"}
}