{
  "type": "Feature",
  "properties": {
    "gn:admin1_code":"25.0",
    "gn:asciiname":"Caijiagou",
    "gn:cc2":"CN",
    "gn:country_code":"CN",
    "gn:dem":43,
    "gn:feature_class":"P",
    "gn:feature_code":"PPL",
    "gn:name":"Caijiagou",
    "gn:population":0,
    "gn:timezone":"Asia/Shanghai",
    "iso:country":"CN",
    "name:zho_x_preferred":[
        "\u8521\u5bb6\u6c9f"
    ],
    "wof:name":"Caijiagou",
    "wof:placetype":"locality"
},
  "geometry": {"coordinates":[119.92341999999999,36.17181],"type":"Point"}
}