{
  "type": "Feature",
  "properties": {
    "gn:admin1_code":"11.0",
    "gn:asciiname":"Loutiping",
    "gn:country_code":"CN",
    "gn:dem":385,
    "gn:feature_class":"P",
    "gn:feature_code":"PPL",
    "gn:name":"Loutiping",
    "gn:population":0,
    "gn:timezone":"Asia/Shanghai",
    "iso:country":"CN",
    "name:zho_x_preferred":[
        "\u697c\u68af\u576a"
    ],
    "wof:name":"Loutiping",
    "wof:placetype":"locality"
},
  "geometry": {"coordinates":[109.45687,26.67136],"type":"Point"}
}