{
  "type": "Feature",
  "properties": {
    "gn:admin1_code":"19.0",
    "gn:asciiname":"Xiawengjiagou",
    "gn:country_code":"CN",
    "gn:dem":204,
    "gn:feature_class":"P",
    "gn:feature_code":"PPL",
    "gn:name":"Xiawengjiagou",
    "gn:population":0,
    "gn:timezone":"Asia/Shanghai",
    "iso:country":"CN",
    "name:und_x_variant":[
        "\u4e0b\u7fc1\u5bb6\u6c9f"
    ],
    "name:zho_x_preferred":[
        "\u4e0b\u7fc1\u5bb6\u6c9f"
    ],
    "wof:name":"Xiawengjiagou",
    "wof:placetype":"locality"
},
  "geometry": {"coordinates":[123.52731,41.09062],"type":"Point"}
}