{
  "type": "Feature",
  "properties": {
    "gn:admin1_code":"32.0",
    "gn:asciiname":"Huping",
    "gn:country_code":"CN",
    "gn:dem":414,
    "gn:feature_class":"P",
    "gn:feature_code":"PPL",
    "gn:name":"Huping",
    "gn:population":0,
    "gn:timezone":"Asia/Shanghai",
    "iso:country":"CN",
    "name:zho_x_preferred":[
        "\u864e\u576a"
    ],
    "wof:name":"Huping",
    "wof:placetype":"locality"
},
  "geometry": {"coordinates":[106.774,31.3173],"type":"Point"}
}