{
  "type": "Feature",
  "properties": {
    "gn:admin1_code":"10",
    "gn:asciiname":"Weiwuzhuang",
    "gn:country_code":"CN",
    "gn:dem":148,
    "gn:feature_class":"P",
    "gn:feature_code":"PPL",
    "gn:name":"Weiwuzhuang",
    "gn:population":0,
    "gn:timezone":"Asia/Shanghai",
    "iso:country":"CN",
    "name:zho_x_preferred":[
        "\u97e6\u6b66\u5e84"
    ],
    "wof:name":"Weiwuzhuang",
    "wof:placetype":"locality"
},
  "geometry": {"coordinates":[114.227,36.3692],"type":"Point"}
}