{
  "type": "Feature",
  "properties": {
    "gn:admin1_code":"19.0",
    "gn:asciiname":"Jingoucun",
    "gn:country_code":"CN",
    "gn:dem":161,
    "gn:feature_class":"P",
    "gn:feature_code":"PPL",
    "gn:name":"Jingoucun",
    "gn:population":0,
    "gn:timezone":"Asia/Shanghai",
    "iso:country":"CN",
    "name:zho_x_preferred":[
        "\u91d1\u6c9f\u6751"
    ],
    "wof:name":"Jingoucun",
    "wof:placetype":"locality"
},
  "geometry": {"coordinates":[120.54425000000001,41.63276],"type":"Point"}
}