{
  "type": "Feature",
  "properties": {
    "gn:admin1_code":"9",
    "gn:asciiname":"Wangshilan",
    "gn:country_code":"CN",
    "gn:dem":41,
    "gn:feature_class":"P",
    "gn:feature_code":"PPL",
    "gn:name":"Wangshilan",
    "gn:population":0,
    "gn:timezone":"Asia/Shanghai",
    "iso:country":"CN",
    "name:zho_x_preferred":[
        "\u738b\u77f3\u680f"
    ],
    "wof:name":"Wangshilan",
    "wof:placetype":"locality"
},
  "geometry": {"coordinates":[116.02200000000001,33.9744],"type":"Point"}
}