{
  "type": "Feature",
  "properties": {
    "gn:admin1_code":"29",
    "gn:asciiname":"Guangwo Shangzhai",
    "gn:country_code":"CN",
    "gn:dem":1096,
    "gn:feature_class":"P",
    "gn:feature_code":"PPL",
    "gn:name":"Guangwo Shangzhai",
    "gn:population":0,
    "gn:timezone":"Asia/Shanghai",
    "iso:country":"CN",
    "name:zho_x_preferred":[
        "\u5e7f\u7a9d\u4e0a\u5be8"
    ],
    "wof:name":"Guangwo Shangzhai",
    "wof:placetype":"locality"
},
  "geometry": {"coordinates":[104.80800000000001,23.2632],"type":"Point"}
}