{
  "type": "Feature",
  "properties": {
    "gn:admin1_code":"24",
    "gn:asciiname":"Shisi",
    "gn:cc2":"CN",
    "gn:country_code":"CN",
    "gn:dem":1008,
    "gn:feature_class":"P",
    "gn:feature_code":"PPL",
    "gn:name":"Shisi",
    "gn:population":0,
    "gn:timezone":"Asia/Shanghai",
    "iso:country":"CN",
    "name:und_x_variant":[
        "Chung-shih-ssu",
        "Shih-ssu",
        "Shisi"
    ],
    "wof:name":"Shisi",
    "wof:placetype":"locality"
},
  "geometry": {"coordinates":[112.67028000000001,38.93444],"type":"Point"}
}