{
  "type": "Feature",
  "properties": {
    "gn:admin1_code":"12.0",
    "gn:asciiname":"Miaoxiawan",
    "gn:country_code":"CN",
    "gn:dem":57,
    "gn:feature_class":"P",
    "gn:feature_code":"PPL",
    "gn:name":"Miaoxiawan",
    "gn:population":0,
    "gn:timezone":"Asia/Shanghai",
    "iso:country":"CN",
    "name:und_x_variant":[
        "\u5e99\u4e0b\u5846"
    ],
    "wof:name":"Miaoxiawan",
    "wof:placetype":"locality"
},
  "geometry": {"coordinates":[115.18244,30.67765],"type":"Point"}
}