{
  "type": "Feature",
  "properties": {
    "gn:admin1_code":"26.0",
    "gn:asciiname":"Quanjiagoucun",
    "gn:country_code":"CN",
    "gn:dem":501,
    "gn:feature_class":"P",
    "gn:feature_code":"PPL",
    "gn:name":"Quanjiagoucun",
    "gn:population":0,
    "gn:timezone":"Asia/Shanghai",
    "iso:country":"CN",
    "name:und_x_variant":[
        "\u5168\u5bb6\u6c9f\u6751"
    ],
    "wof:name":"Quanjiagoucun",
    "wof:placetype":"locality"
},
  "geometry": {"coordinates":[107.49836000000001,33.23892],"type":"Point"}
}