{
  "type": "Feature",
  "properties": {
    "gn:admin1_code":"32.0",
    "gn:asciiname":"Lujiawan",
    "gn:country_code":"CN",
    "gn:dem":416,
    "gn:feature_class":"P",
    "gn:feature_code":"PPL",
    "gn:name":"Lujiawan",
    "gn:population":0,
    "gn:timezone":"Asia/Shanghai",
    "iso:country":"CN",
    "name:zho_x_preferred":[
        "\u9c81\u5bb6\u6e7e"
    ],
    "wof:name":"Lujiawan",
    "wof:placetype":"locality"
},
  "geometry": {"coordinates":[104.953,30.7564],"type":"Point"}
}