{
  "type": "Feature",
  "properties": {
    "gn:admin1_code":"02",
    "gn:asciiname":"Baifen",
    "gn:cc2":"CN",
    "gn:country_code":"CN",
    "gn:dem":94,
    "gn:feature_class":"P",
    "gn:feature_code":"PPL",
    "gn:name":"Baifen",
    "gn:population":0,
    "gn:timezone":"Asia/Shanghai",
    "iso:country":"CN",
    "name:und_x_variant":[
        "Pai-fen",
        "Baifen"
    ],
    "name:zho_x_preferred":[
        "\u767d\u575f"
    ],
    "wof:name":"Baifen",
    "wof:placetype":"locality"
},
  "geometry": {"coordinates":[120.48472,27.47639],"type":"Point"}
}