{
  "type": "Feature",
  "properties": {
    "gn:admin1_code":"14.0",
    "gn:asciiname":"Yuruo",
    "gn:country_code":"CN",
    "gn:dem":4462,
    "gn:feature_class":"P",
    "gn:feature_code":"PPL",
    "gn:name":"Yuruo",
    "gn:population":0,
    "gn:timezone":"Asia/Urumqi",
    "iso:country":"CN",
    "name:zho_x_preferred":[
        "\u9c7c\u82e5"
    ],
    "wof:name":"Yuruo",
    "wof:placetype":"locality"
},
  "geometry": {"coordinates":[90.70923999999999,28.15119],"type":"Point"}
}