{
  "type": "Feature",
  "properties": {
    "gn:admin1_code":"32.0",
    "gn:asciiname":"Yijia",
    "gn:country_code":"CN",
    "gn:dem":618,
    "gn:feature_class":"P",
    "gn:feature_code":"PPL",
    "gn:name":"Yijia",
    "gn:population":0,
    "gn:timezone":"Asia/Shanghai",
    "iso:country":"CN",
    "name:zho_x_preferred":[
        "\u6613\u5bb6"
    ],
    "wof:name":"Yijia",
    "wof:placetype":"locality"
},
  "geometry": {"coordinates":[104.60599999999999,28.0842],"type":"Point"}
}