{
  "type": "Feature",
  "properties": {
    "gn:admin1_code":"7",
    "gn:asciiname":"Banwei",
    "gn:country_code":"CN",
    "gn:dem":6,
    "gn:feature_class":"P",
    "gn:feature_code":"PPL",
    "gn:name":"Banwei",
    "gn:population":0,
    "gn:timezone":"Asia/Shanghai",
    "iso:country":"CN",
    "name:und_x_variant":[
        "Pan-wei",
        "Banwei"
    ],
    "name:zho_x_preferred":[
        "\u5742\u5c3e"
    ],
    "wof:name":"Banwei",
    "wof:placetype":"locality"
},
  "geometry": {"coordinates":[119.09659000000001,25.25618],"type":"Point"}
}