{
  "type": "Feature",
  "properties": {
    "gn:admin1_code":"4.0",
    "gn:asciiname":"Fengcuncun",
    "gn:country_code":"CN",
    "gn:dem":4,
    "gn:feature_class":"P",
    "gn:feature_code":"PPL",
    "gn:name":"Fengcuncun",
    "gn:population":0,
    "gn:timezone":"Asia/Shanghai",
    "iso:country":"CN",
    "name:zho_x_preferred":[
        "\u51e4\u5b58\u6751"
    ],
    "wof:name":"Fengcuncun",
    "wof:placetype":"locality"
},
  "geometry": {"coordinates":[120.2735,33.0329],"type":"Point"}
}