{
  "type": "Feature",
  "properties": {
    "gn:admin1_code":"16.0",
    "gn:asciiname":"Dazhengya",
    "gn:country_code":"CN",
    "gn:dem":999,
    "gn:feature_class":"P",
    "gn:feature_code":"PPL",
    "gn:name":"Dazhengya",
    "gn:population":0,
    "gn:timezone":"Asia/Shanghai",
    "iso:country":"CN",
    "name:zho_x_preferred":[
        "\u5927\u6b63\u82bd"
    ],
    "wof:name":"Dazhengya",
    "wof:placetype":"locality"
},
  "geometry": {"coordinates":[111.661,24.7573],"type":"Point"}
}