{
  "type": "Feature",
  "properties": {
    "gn:admin1_code":"7.0",
    "gn:asciiname":"Pinggaozhuang",
    "gn:country_code":"CN",
    "gn:dem":855,
    "gn:feature_class":"P",
    "gn:feature_code":"PPL",
    "gn:name":"Pinggaozhuang",
    "gn:population":0,
    "gn:timezone":"Asia/Shanghai",
    "iso:country":"CN",
    "name:zho_x_preferred":[
        "\u5e73\u9ad8\u5e84"
    ],
    "wof:name":"Pinggaozhuang",
    "wof:placetype":"locality"
},
  "geometry": {"coordinates":[116.87542999999999,25.0891],"type":"Point"}
}