{
  "type": "Feature",
  "properties": {
    "gn:admin1_code":"19.0",
    "gn:asciiname":"Linjiagoucun",
    "gn:country_code":"CN",
    "gn:dem":240,
    "gn:feature_class":"P",
    "gn:feature_code":"PPL",
    "gn:name":"Linjiagoucun",
    "gn:population":0,
    "gn:timezone":"Asia/Shanghai",
    "iso:country":"CN",
    "name:zho_x_preferred":[
        "\u6797\u5bb6\u6c9f\u6751"
    ],
    "wof:name":"Linjiagoucun",
    "wof:placetype":"locality"
},
  "geometry": {"coordinates":[120.25601,41.47144],"type":"Point"}
}