{
  "type": "Feature",
  "properties": {
    "gn:admin1_code":"13",
    "gn:asciiname":"Bositan",
    "gn:country_code":"CN",
    "gn:dem":1046,
    "gn:feature_class":"P",
    "gn:feature_code":"PPL",
    "gn:name":"Bositan",
    "gn:population":0,
    "gn:timezone":"Asia/Shanghai",
    "iso:country":"CN",
    "name:und_x_variant":[
        "\u535a\u65af\u5766"
    ],
    "wof:name":"Bositan",
    "wof:placetype":"locality"
},
  "geometry": {"coordinates":[80.24409,40.19692],"type":"Point"}
}