{
  "type": "Feature",
  "properties": {
    "gn:admin1_code":"19.0",
    "gn:asciiname":"Xishantun",
    "gn:country_code":"CN",
    "gn:dem":126,
    "gn:feature_class":"P",
    "gn:feature_code":"PPL",
    "gn:name":"Xishantun",
    "gn:population":0,
    "gn:timezone":"Asia/Shanghai",
    "iso:country":"CN",
    "name:zho_x_preferred":[
        "\u897f\u5c71\u5c6f"
    ],
    "wof:name":"Xishantun",
    "wof:placetype":"locality"
},
  "geometry": {"coordinates":[124.05911999999999,42.75833],"type":"Point"}
}