{
  "type": "Feature",
  "properties": {
    "gn:admin1_code":"12.0",
    "gn:asciiname":"Xiaozengjiawan",
    "gn:country_code":"CN",
    "gn:dem":277,
    "gn:feature_class":"P",
    "gn:feature_code":"PPL",
    "gn:name":"Xiaozengjiawan",
    "gn:population":0,
    "gn:timezone":"Asia/Shanghai",
    "iso:country":"CN",
    "name:zho_x_preferred":[
        "\u5c0f\u66fe\u5bb6\u6e7e"
    ],
    "wof:name":"Xiaozengjiawan",
    "wof:placetype":"locality"
},
  "geometry": {"coordinates":[111.73976999999999,31.32313],"type":"Point"}
}