{
  "type": "Feature",
  "properties": {
    "gn:admin1_code":"25",
    "gn:asciiname":"Cao Zhuangzi",
    "gn:country_code":"CN",
    "gn:dem":56,
    "gn:feature_class":"P",
    "gn:feature_code":"PPL",
    "gn:name":"Cao Zhuangzi",
    "gn:population":0,
    "gn:timezone":"Asia/Shanghai",
    "iso:country":"CN",
    "name:zho_x_preferred":[
        "\u66f9\u5e84\u5b50"
    ],
    "wof:name":"Cao Zhuangzi",
    "wof:placetype":"locality"
},
  "geometry": {"coordinates":[118.563,34.8776],"type":"Point"}
}