{
  "type": "Feature",
  "properties": {
    "gn:admin1_code":"15.0",
    "gn:asciiname":"Guandian",
    "gn:country_code":"CN",
    "gn:dem":1115,
    "gn:feature_class":"P",
    "gn:feature_code":"PPL",
    "gn:name":"Guandian",
    "gn:population":0,
    "gn:timezone":"Asia/Shanghai",
    "iso:country":"CN",
    "name:und_x_variant":[
        "\u5b98\u5e97"
    ],
    "wof:name":"Guandian",
    "wof:placetype":"locality"
},
  "geometry": {"coordinates":[105.68877999999999,33.89294],"type":"Point"}
}