{
  "type": "Feature",
  "properties": {
    "gn:admin1_code":"30.0",
    "gn:admin2_code":"1809857",
    "gn:asciiname":"Luohantang",
    "gn:country_code":"CN",
    "gn:dem":16,
    "gn:feature_class":"P",
    "gn:feature_code":"PPL",
    "gn:name":"Luohantang",
    "gn:population":0,
    "gn:timezone":"Asia/Shanghai",
    "iso:country":"CN",
    "name:und_x_variant":[
        "\u7f57\u6c49\u5858"
    ],
    "name:zho_x_preferred":[
        "\u7f57\u6c49\u5858"
    ],
    "wof:name":"Luohantang",
    "wof:placetype":"locality"
},
  "geometry": {"coordinates":[113.32295000000001,23.38206],"type":"Point"}
}