{
  "type": "Feature",
  "properties": {
    "gn:admin1_code":"3.0",
    "gn:asciiname":"Fujialing",
    "gn:country_code":"CN",
    "gn:dem":759,
    "gn:feature_class":"P",
    "gn:feature_code":"PPL",
    "gn:name":"Fujialing",
    "gn:population":0,
    "gn:timezone":"Asia/Shanghai",
    "iso:country":"CN",
    "name:und_x_variant":[
        "\u5085\u5bb6\u5cad"
    ],
    "wof:name":"Fujialing",
    "wof:placetype":"locality"
},
  "geometry": {"coordinates":[114.27143,29.23176],"type":"Point"}
}