{
  "type": "Feature",
  "properties": {
    "gn:admin1_code":"7.0",
    "gn:asciiname":"Chengkeng",
    "gn:country_code":"CN",
    "gn:dem":340,
    "gn:feature_class":"P",
    "gn:feature_code":"PPL",
    "gn:name":"Chengkeng",
    "gn:population":0,
    "gn:timezone":"Asia/Shanghai",
    "iso:country":"CN",
    "name:zho_x_preferred":[
        "\u7a0b\u5751"
    ],
    "wof:name":"Chengkeng",
    "wof:placetype":"locality"
},
  "geometry": {"coordinates":[118.71263999999999,27.65487000000001],"type":"Point"}
}