{
  "type": "Feature",
  "properties": {
    "gn:admin1_code":"18",
    "gn:asciiname":"Shuijingwan",
    "gn:country_code":"CN",
    "gn:dem":1097,
    "gn:feature_class":"P",
    "gn:feature_code":"PPL",
    "gn:name":"Shuijingwan",
    "gn:population":0,
    "gn:timezone":"Asia/Shanghai",
    "iso:country":"CN",
    "name:zho_x_preferred":[
        "\u6c34\u4e95\u6e7e"
    ],
    "wof:name":"Shuijingwan",
    "wof:placetype":"locality"
},
  "geometry": {"coordinates":[106.872,28.1391],"type":"Point"}
}