{
  "type": "Feature",
  "properties": {
    "gn:admin1_code":"02",
    "gn:asciiname":"Lizhu",
    "gn:country_code":"CN",
    "gn:dem":10,
    "gn:feature_class":"P",
    "gn:feature_code":"PPLA4",
    "gn:name":"Lizhu",
    "gn:population":0,
    "gn:timezone":"Asia/Shanghai",
    "iso:country":"CN",
    "name:und_x_variant":[
        "Li-chu-shih",
        "Li-chu",
        "Lizhu",
        "Lizhu Zhen",
        "\u6f13\u6e1a\u9547"
    ],
    "name:zho_x_preferred":[
        "\u6f13\u6e1a"
    ],
    "wof:name":"Lizhu",
    "wof:placetype":"locality"
},
  "geometry": {"coordinates":[120.46666999999999,29.95528],"type":"Point"}
}