{
  "type": "Feature",
  "properties": {
    "gn:admin1_code":"15.0",
    "gn:asciiname":"Caodixia",
    "gn:country_code":"CN",
    "gn:dem":2544,
    "gn:feature_class":"P",
    "gn:feature_code":"PPL",
    "gn:name":"Caodixia",
    "gn:population":0,
    "gn:timezone":"Asia/Shanghai",
    "iso:country":"CN",
    "name:und_x_variant":[
        "\u8349\u5730\u4e0b"
    ],
    "wof:name":"Caodixia",
    "wof:placetype":"locality"
},
  "geometry": {"coordinates":[104.4156,34.63543],"type":"Point"}
}