{
  "type": "Feature",
  "properties": {
    "gn:admin1_code":"1.0",
    "gn:asciiname":"Huangjicun",
    "gn:country_code":"CN",
    "gn:dem":42,
    "gn:feature_class":"P",
    "gn:feature_code":"PPL",
    "gn:name":"Huangjicun",
    "gn:population":0,
    "gn:timezone":"Asia/Shanghai",
    "iso:country":"CN",
    "name:zho_x_preferred":[
        "\u9ec4\u96c6\u6751"
    ],
    "wof:name":"Huangjicun",
    "wof:placetype":"locality"
},
  "geometry": {"coordinates":[117.99151999999999,31.9751],"type":"Point"}
}