{
  "type": "Feature",
  "properties": {
    "gn:admin1_code":"32.0",
    "gn:asciiname":"Zecu",
    "gn:country_code":"CN",
    "gn:dem":2137,
    "gn:feature_class":"P",
    "gn:feature_code":"PPL",
    "gn:name":"Zecu",
    "gn:population":0,
    "gn:timezone":"Asia/Shanghai",
    "iso:country":"CN",
    "name:zho_x_preferred":[
        "\u5219\u7c97"
    ],
    "wof:name":"Zecu",
    "wof:placetype":"locality"
},
  "geometry": {"coordinates":[102.85193,27.32147],"type":"Point"}
}