{
  "type": "Feature",
  "properties": {
    "gn:admin1_code":"16.0",
    "gn:asciiname":"Yaodong",
    "gn:country_code":"CN",
    "gn:dem":726,
    "gn:feature_class":"P",
    "gn:feature_code":"PPL",
    "gn:name":"Yaodong",
    "gn:population":0,
    "gn:timezone":"Asia/Shanghai",
    "iso:country":"CN",
    "name:zho_x_preferred":[
        "\u7476\u6d1e"
    ],
    "wof:name":"Yaodong",
    "wof:placetype":"locality"
},
  "geometry": {"coordinates":[107.748,24.4261],"type":"Point"}
}