{
  "type": "Feature",
  "properties": {
    "gn:admin1_code":"11",
    "gn:asciiname":"Dongshi",
    "gn:cc2":"CN",
    "gn:country_code":"CN",
    "gn:dem":305,
    "gn:feature_class":"P",
    "gn:feature_code":"PPL",
    "gn:name":"Dongshi",
    "gn:population":0,
    "gn:timezone":"Asia/Shanghai",
    "iso:country":"CN",
    "name:deu_x_preferred":[
        "Dongshi"
    ],
    "name:kor_x_preferred":[
        "\ub465\uc2a4 \ud5a5"
    ],
    "name:und_x_variant":[
        "Tung-shih",
        "Dongshi"
    ],
    "wof:name":"Dongshi",
    "wof:placetype":"locality"
},
  "geometry": {"coordinates":[111.43277999999999,28.24972],"type":"Point"}
}