{
  "type": "Feature",
  "properties": {
    "gn:admin1_code":"1.0",
    "gn:asciiname":"Lijiachongcun",
    "gn:country_code":"CN",
    "gn:dem":79,
    "gn:feature_class":"P",
    "gn:feature_code":"PPL",
    "gn:name":"Lijiachongcun",
    "gn:population":0,
    "gn:timezone":"Asia/Shanghai",
    "iso:country":"CN",
    "name:zho_x_preferred":[
        "\u674e\u5bb6\u51b2\u6751"
    ],
    "wof:name":"Lijiachongcun",
    "wof:placetype":"locality"
},
  "geometry": {"coordinates":[116.29495,31.44986],"type":"Point"}
}