{
  "type": "Feature",
  "properties": {
    "gn:admin1_code":"16",
    "gn:asciiname":"Guayushan",
    "gn:country_code":"CN",
    "gn:dem":421,
    "gn:feature_class":"P",
    "gn:feature_code":"PPL",
    "gn:name":"Guayushan",
    "gn:population":0,
    "gn:timezone":"Asia/Shanghai",
    "iso:country":"CN",
    "name:zho_x_preferred":[
        "\u6302\u9c7c\u5c71"
    ],
    "wof:name":"Guayushan",
    "wof:placetype":"locality"
},
  "geometry": {"coordinates":[111.203,25.9331],"type":"Point"}
}