{
  "type": "Feature",
  "properties": {
    "gn:admin1_code":"8.0",
    "gn:asciiname":"Baishengcun",
    "gn:country_code":"CN",
    "gn:dem":167,
    "gn:feature_class":"P",
    "gn:feature_code":"PPL",
    "gn:name":"Baishengcun",
    "gn:population":0,
    "gn:timezone":"Asia/Shanghai",
    "iso:country":"CN",
    "name:zho_x_preferred":[
        "\u767e\u5347\u6751"
    ],
    "wof:name":"Baishengcun",
    "wof:placetype":"locality"
},
  "geometry": {"coordinates":[126.44812,47.36802],"type":"Point"}
}