{
  "type": "Feature",
  "properties": {
    "gn:admin1_code":"9",
    "gn:asciiname":"Mengquan",
    "gn:country_code":"CN",
    "gn:dem":315,
    "gn:feature_class":"P",
    "gn:feature_code":"PPL",
    "gn:name":"Mengquan",
    "gn:population":0,
    "gn:timezone":"Asia/Shanghai",
    "iso:country":"CN",
    "name:zho_x_preferred":[
        "\u5b5f\u6cc9"
    ],
    "wof:name":"Mengquan",
    "wof:placetype":"locality"
},
  "geometry": {"coordinates":[113.32459,35.35966],"type":"Point"}
}