{
  "type": "Feature",
  "properties": {
    "gn:admin1_code":"33.0",
    "gn:asciiname":"Ruancun",
    "gn:country_code":"CN",
    "gn:dem":1101,
    "gn:feature_class":"P",
    "gn:feature_code":"PPL",
    "gn:name":"Ruancun",
    "gn:population":0,
    "gn:timezone":"Asia/Shanghai",
    "iso:country":"CN",
    "name:zho_x_preferred":[
        "\u962e\u6751"
    ],
    "wof:name":"Ruancun",
    "wof:placetype":"locality"
},
  "geometry": {"coordinates":[110.04155,31.31571],"type":"Point"}
}