{
  "type": "Feature",
  "properties": {
    "gn:admin1_code":"11.0",
    "gn:asciiname":"Laowupo",
    "gn:country_code":"CN",
    "gn:dem":346,
    "gn:feature_class":"P",
    "gn:feature_code":"PPL",
    "gn:name":"Laowupo",
    "gn:population":0,
    "gn:timezone":"Asia/Shanghai",
    "iso:country":"CN",
    "name:zho_x_preferred":[
        "\u8001\u5c4b\u5761"
    ],
    "wof:name":"Laowupo",
    "wof:placetype":"locality"
},
  "geometry": {"coordinates":[109.61302999999999,27.26993],"type":"Point"}
}