{
  "type": "Feature",
  "properties": {
    "gn:admin1_code":"1.0",
    "gn:asciiname":"Gaozhencun",
    "gn:country_code":"CN",
    "gn:dem":72,
    "gn:feature_class":"P",
    "gn:feature_code":"PPL",
    "gn:name":"Gaozhencun",
    "gn:population":0,
    "gn:timezone":"Asia/Shanghai",
    "iso:country":"CN",
    "name:und_x_variant":[
        "Gaozhen"
    ],
    "name:zho_x_preferred":[
        "\u9ad8\u9547\u6751"
    ],
    "wof:name":"Gaozhencun",
    "wof:placetype":"locality"
},
  "geometry": {"coordinates":[115.94873,32.04449],"type":"Point"}
}