{
  "type": "Feature",
  "properties": {
    "gn:admin1_code":"4.0",
    "gn:asciiname":"Shisan Xudai",
    "gn:country_code":"CN",
    "gn:dem":4,
    "gn:feature_class":"P",
    "gn:feature_code":"PPL",
    "gn:name":"Shisan Xudai",
    "gn:population":0,
    "gn:timezone":"Asia/Shanghai",
    "iso:country":"CN",
    "name:zho_x_preferred":[
        "\u5e02\u4e09\u5729\u5788"
    ],
    "wof:name":"Shisan Xudai",
    "wof:placetype":"locality"
},
  "geometry": {"coordinates":[120.42534999999999,32.10876],"type":"Point"}
}