{
  "type": "Feature",
  "properties": {
    "gn:admin1_code":"18",
    "gn:asciiname":"Rangcun",
    "gn:country_code":"CN",
    "gn:dem":320,
    "gn:feature_class":"P",
    "gn:feature_code":"PPL",
    "gn:name":"Rangcun",
    "gn:population":0,
    "gn:timezone":"Asia/Shanghai",
    "iso:country":"CN",
    "name:zho_x_preferred":[
        "\u8ba9\u6751"
    ],
    "wof:name":"Rangcun",
    "wof:placetype":"locality"
},
  "geometry": {"coordinates":[106.759,25.2022],"type":"Point"}
}