{
  "type": "Feature",
  "properties": {
    "gn:admin1_code":"32.0",
    "gn:asciiname":"Shuicaozi",
    "gn:country_code":"CN",
    "gn:dem":1390,
    "gn:feature_class":"P",
    "gn:feature_code":"PPL",
    "gn:name":"Shuicaozi",
    "gn:population":0,
    "gn:timezone":"Asia/Shanghai",
    "iso:country":"CN",
    "name:zho_x_preferred":[
        "\u6c34\u69fd\u5b50"
    ],
    "wof:name":"Shuicaozi",
    "wof:placetype":"locality"
},
  "geometry": {"coordinates":[103.00700000000001,26.6331],"type":"Point"}
}