{
  "type": "Feature",
  "properties": {
    "gn:admin1_code":"14.0",
    "gn:asciiname":"Xogsum",
    "gn:country_code":"CN",
    "gn:dem":3426,
    "gn:feature_class":"P",
    "gn:feature_code":"PPLF",
    "gn:name":"Xogsum",
    "gn:population":0,
    "gn:timezone":"Asia/Urumqi",
    "iso:country":"CN",
    "name:bod_x_preferred":[
        "Xogsum"
    ],
    "name:zho_x_preferred":[
        "Xuesong"
    ],
    "name:zho_x_variant":[
        "\u5b66\u677e"
    ],
    "wof:name":"Xogsum",
    "wof:placetype":"locality"
},
  "geometry": {"coordinates":[97.601,30.501],"type":"Point"}
}