{
  "type": "Feature",
  "properties": {
    "gn:admin1_code":"3.0",
    "gn:asciiname":"Huaguoyuan",
    "gn:country_code":"CN",
    "gn:dem":17,
    "gn:feature_class":"P",
    "gn:feature_code":"PPL",
    "gn:name":"Huaguoyuan",
    "gn:population":0,
    "gn:timezone":"Asia/Shanghai",
    "iso:country":"CN",
    "name:und_x_variant":[
        "\u82b1\u679c\u56ed"
    ],
    "wof:name":"Huaguoyuan",
    "wof:placetype":"locality"
},
  "geometry": {"coordinates":[116.7684,29.26973],"type":"Point"}
}