{
  "type": "Feature",
  "properties": {
    "gn:admin1_code":"1.0",
    "gn:asciiname":"Zhaopoloucun",
    "gn:country_code":"CN",
    "gn:dem":40,
    "gn:feature_class":"P",
    "gn:feature_code":"PPL",
    "gn:name":"Zhaopoloucun",
    "gn:population":0,
    "gn:timezone":"Asia/Shanghai",
    "iso:country":"CN",
    "name:zho_x_preferred":[
        "\u8d75\u7834\u697c\u6751"
    ],
    "wof:name":"Zhaopoloucun",
    "wof:placetype":"locality"
},
  "geometry": {"coordinates":[116.53100999999999,34.1217],"type":"Point"}
}