{
  "type": "Feature",
  "properties": {
    "gn:admin1_code":"11",
    "gn:asciiname":"Shangjiangxu",
    "gn:country_code":"CN",
    "gn:dem":233,
    "gn:feature_class":"P",
    "gn:feature_code":"PPLA4",
    "gn:name":"Shangjiangxu",
    "gn:population":0,
    "gn:timezone":"Asia/Shanghai",
    "iso:country":"CN",
    "name:und_x_variant":[
        "Shangjiangxu Zhen",
        "\u4e0a\u6c5f\u5729\u9547",
        "Shangjiangxu"
    ],
    "name:zho_x_preferred":[
        "\u4e0a\u6c5f\u5729"
    ],
    "wof:name":"Shangjiangxu",
    "wof:placetype":"locality"
},
  "geometry": {"coordinates":[111.42694,25.35583],"type":"Point"}
}