{
  "type": "Feature",
  "properties": {
    "gn:admin1_code":"30.0",
    "gn:asciiname":"Danyuankengwei",
    "gn:country_code":"CN",
    "gn:dem":193,
    "gn:feature_class":"P",
    "gn:feature_code":"PPL",
    "gn:name":"Danyuankengwei",
    "gn:population":0,
    "gn:timezone":"Asia/Shanghai",
    "iso:country":"CN",
    "name:zho_x_preferred":[
        "\u4e39\u6e90\u5751\u5c3e"
    ],
    "wof:name":"Danyuankengwei",
    "wof:placetype":"locality"
},
  "geometry": {"coordinates":[112.1841,23.63923],"type":"Point"}
}