{
  "type": "Feature",
  "properties": {
    "gn:admin1_code":"26.0",
    "gn:asciiname":"Daiwuchacun",
    "gn:country_code":"CN",
    "gn:dem":972,
    "gn:feature_class":"P",
    "gn:feature_code":"PPL",
    "gn:name":"Daiwuchacun",
    "gn:population":0,
    "gn:timezone":"Asia/Shanghai",
    "iso:country":"CN",
    "name:zho_x_preferred":[
        "\u5cb1\u6b66\u5c94\u6751"
    ],
    "wof:name":"Daiwuchacun",
    "wof:placetype":"locality"
},
  "geometry": {"coordinates":[110.3373,37.53541],"type":"Point"}
}