{
  "type": "Feature",
  "properties": {
    "gn:admin1_code":"9.0",
    "gn:asciiname":"Baiya",
    "gn:country_code":"CN",
    "gn:dem":503,
    "gn:feature_class":"P",
    "gn:feature_code":"PPL",
    "gn:name":"Baiya",
    "gn:population":0,
    "gn:timezone":"Asia/Shanghai",
    "iso:country":"CN",
    "name:zho_x_preferred":[
        "\u767d\u5d16"
    ],
    "wof:name":"Baiya",
    "wof:placetype":"locality"
},
  "geometry": {"coordinates":[111.53801,33.36537],"type":"Point"}
}