{
  "type": "Feature",
  "properties": {
    "gn:admin1_code":"32.0",
    "gn:asciiname":"Bandao",
    "gn:country_code":"CN",
    "gn:dem":4071,
    "gn:feature_class":"P",
    "gn:feature_code":"PPL",
    "gn:name":"Bandao",
    "gn:population":0,
    "gn:timezone":"Asia/Shanghai",
    "iso:country":"CN",
    "name:zho_x_preferred":[
        "\u534a\u5200"
    ],
    "wof:name":"Bandao",
    "wof:placetype":"locality"
},
  "geometry": {"coordinates":[100.172,28.7543],"type":"Point"}
}