{
  "type": "Feature",
  "properties": {
    "gn:admin1_code":"4.0",
    "gn:asciiname":"Handaloucun",
    "gn:country_code":"CN",
    "gn:dem":39,
    "gn:feature_class":"P",
    "gn:feature_code":"PPL",
    "gn:name":"Handaloucun",
    "gn:population":0,
    "gn:timezone":"Asia/Shanghai",
    "iso:country":"CN",
    "name:zho_x_preferred":[
        "\u97e9\u5927\u697c\u6751"
    ],
    "wof:name":"Handaloucun",
    "wof:placetype":"locality"
},
  "geometry": {"coordinates":[116.95367,34.5097],"type":"Point"}
}