{
  "type": "Feature",
  "properties": {
    "gn:admin1_code":"19",
    "gn:asciiname":"Lianshanguan",
    "gn:cc2":"CN",
    "gn:country_code":"CN",
    "gn:dem":291,
    "gn:feature_class":"P",
    "gn:feature_code":"PPL",
    "gn:name":"Lianshanguan",
    "gn:population":0,
    "gn:timezone":"Asia/Shanghai",
    "iso:country":"CN",
    "name:und_x_variant":[
        "Lien-shan-kuan",
        "Lianshanguan"
    ],
    "wof:name":"Lianshanguan",
    "wof:placetype":"locality"
},
  "geometry": {"coordinates":[123.72861,40.98222],"type":"Point"}
}