{
  "type": "Feature",
  "properties": {
    "gn:admin1_code":"25.0",
    "gn:asciiname":"Dashijia",
    "gn:country_code":"CN",
    "gn:dem":100,
    "gn:feature_class":"P",
    "gn:feature_code":"PPL",
    "gn:name":"Dashijia",
    "gn:population":0,
    "gn:timezone":"Asia/Shanghai",
    "iso:country":"CN",
    "name:zho_x_preferred":[
        "\u5927\u53f2\u5bb6"
    ],
    "wof:name":"Dashijia",
    "wof:placetype":"locality"
},
  "geometry": {"coordinates":[120.72044,37.72886],"type":"Point"}
}