{
  "type": "Feature",
  "properties": {
    "gn:admin1_code":"30.0",
    "gn:asciiname":"Dalianwei",
    "gn:country_code":"CN",
    "gn:dem":-2,
    "gn:feature_class":"P",
    "gn:feature_code":"PPL",
    "gn:name":"Dalianwei",
    "gn:population":0,
    "gn:timezone":"Asia/Shanghai",
    "iso:country":"CN",
    "name:zho_x_preferred":[
        "\u5927\u8fde\u56f4"
    ],
    "wof:name":"Dalianwei",
    "wof:placetype":"locality"
},
  "geometry": {"coordinates":[113.45247000000001,22.23394],"type":"Point"}
}