{
  "type": "Feature",
  "properties": {
    "gn:admin1_code":"07",
    "gn:asciiname":"Shicheng",
    "gn:country_code":"CN",
    "gn:dem":14,
    "gn:feature_class":"P",
    "gn:feature_code":"PPL",
    "gn:name":"Shicheng",
    "gn:population":0,
    "gn:timezone":"Asia/Shanghai",
    "iso:country":"CN",
    "name:und_x_variant":[
        "Shih-ch\u2019eng",
        "Hsiang-cheng",
        "Shicheng"
    ],
    "name:zho_x_preferred":[
        "\u77f3\u57ce"
    ],
    "wof:name":"Shicheng",
    "wof:placetype":"locality"
},
  "geometry": {"coordinates":[119.36337,25.26202],"type":"Point"}
}