{
  "type": "Feature",
  "properties": {
    "gn:admin1_code":"26.0",
    "gn:asciiname":"Erfanggou",
    "gn:country_code":"CN",
    "gn:dem":1010,
    "gn:feature_class":"P",
    "gn:feature_code":"PPL",
    "gn:name":"Erfanggou",
    "gn:population":0,
    "gn:timezone":"Asia/Shanghai",
    "iso:country":"CN",
    "name:und_x_variant":[
        "\u4e8c\u623f\u6c9f"
    ],
    "wof:name":"Erfanggou",
    "wof:placetype":"locality"
},
  "geometry": {"coordinates":[105.87396,33.46693],"type":"Point"}
}