{
  "type": "Feature",
  "properties": {
    "gn:admin1_code":"5.0",
    "gn:asciiname":"Yaolugutun",
    "gn:country_code":"CN",
    "gn:dem":193,
    "gn:feature_class":"P",
    "gn:feature_code":"PPL",
    "gn:name":"Yaolugutun",
    "gn:population":0,
    "gn:timezone":"Asia/Shanghai",
    "iso:country":"CN",
    "name:zho_x_preferred":[
        "\u8170\u5362\u53e4\u5c6f"
    ],
    "wof:name":"Yaolugutun",
    "wof:placetype":"locality"
},
  "geometry": {"coordinates":[126.71912,44.58166],"type":"Point"}
}