{
  "type": "Feature",
  "properties": {
    "gn:admin1_code":"01",
    "gn:asciiname":"Jiegoucun",
    "gn:country_code":"CN",
    "gn:dem":27,
    "gn:feature_class":"P",
    "gn:feature_code":"PPL",
    "gn:name":"Jiegoucun",
    "gn:population":0,
    "gn:timezone":"Asia/Shanghai",
    "iso:country":"CN",
    "name:und_x_variant":[
        "Chieh-kou-chi",
        "Chieh-kou",
        "Jiegou",
        "Jiegoucun"
    ],
    "name:zho_x_preferred":[
        "\u754c\u6c9f\u6751"
    ],
    "wof:name":"Jiegoucun",
    "wof:placetype":"locality"
},
  "geometry": {"coordinates":[117.46912,33.5553],"type":"Point"}
}