{
  "type": "Feature",
  "properties": {
    "gn:admin1_code":"12.0",
    "gn:asciiname":"Hejiahuang",
    "gn:country_code":"CN",
    "gn:dem":1598,
    "gn:feature_class":"P",
    "gn:feature_code":"PPL",
    "gn:name":"Hejiahuang",
    "gn:population":0,
    "gn:timezone":"Asia/Shanghai",
    "iso:country":"CN",
    "name:zho_x_preferred":[
        "\u4f55\u5bb6\u8352"
    ],
    "wof:name":"Hejiahuang",
    "wof:placetype":"locality"
},
  "geometry": {"coordinates":[110.73045999999999,30.55866],"type":"Point"}
}