{
  "type": "Feature",
  "properties": {
    "gn:admin1_code":"4.0",
    "gn:asciiname":"Xuwancun",
    "gn:country_code":"CN",
    "gn:dem":36,
    "gn:feature_class":"P",
    "gn:feature_code":"PPL",
    "gn:name":"Xuwancun",
    "gn:population":0,
    "gn:timezone":"Asia/Shanghai",
    "iso:country":"CN",
    "name:zho_x_preferred":[
        "\u80e5\u6e7e\u6751"
    ],
    "wof:name":"Xuwancun",
    "wof:placetype":"locality"
},
  "geometry": {"coordinates":[117.63549999999999,34.06073],"type":"Point"}
}