{
  "type": "Feature",
  "properties": {
    "gn:admin1_code":"14.0",
    "gn:asciiname":"Maiba",
    "gn:country_code":"CN",
    "gn:dem":4684,
    "gn:feature_class":"P",
    "gn:feature_code":"PPLA4",
    "gn:name":"Maiba",
    "gn:population":0,
    "gn:timezone":"Asia/Urumqi",
    "iso:country":"CN",
    "name:bod_x_preferred":[
        "Maiba"
    ],
    "name:und_x_variant":[
        "Maiba Xiang"
    ],
    "name:zho_x_preferred":[
        "\u4e70\u5df4"
    ],
    "name:zho_x_variant":[
        "Nizhi",
        "\u5c3c\u652f",
        "\u4e70\u5df4\u4e61"
    ],
    "wof:name":"Maiba",
    "wof:placetype":"locality"
},
  "geometry": {"coordinates":[89.09659000000001,31.00921],"type":"Point"}
}