{
  "type": "Feature",
  "properties": {
    "gn:admin1_code":"9.0",
    "gn:asciiname":"Xiangshuitan",
    "gn:country_code":"CN",
    "gn:dem":145,
    "gn:feature_class":"P",
    "gn:feature_code":"PPL",
    "gn:name":"Xiangshuitan",
    "gn:population":0,
    "gn:timezone":"Asia/Shanghai",
    "iso:country":"CN",
    "name:zho_x_preferred":[
        "\u54cd\u6c34\u6f6d"
    ],
    "wof:name":"Xiangshuitan",
    "wof:placetype":"locality"
},
  "geometry": {"coordinates":[113.60186000000002,32.91285],"type":"Point"}
}