{
  "type": "Feature",
  "properties": {
    "gn:admin1_code":"26.0",
    "gn:asciiname":"Heilongtan",
    "gn:country_code":"CN",
    "gn:dem":1242,
    "gn:feature_class":"P",
    "gn:feature_code":"PPL",
    "gn:name":"Heilongtan",
    "gn:population":0,
    "gn:timezone":"Asia/Shanghai",
    "iso:country":"CN",
    "name:und_x_variant":[
        "\u9ed1\u9f99\u5858"
    ],
    "wof:name":"Heilongtan",
    "wof:placetype":"locality"
},
  "geometry": {"coordinates":[106.78955000000001,32.75125999999999],"type":"Point"}
}