{
  "type": "Feature",
  "properties": {
    "gn:admin1_code":"1.0",
    "gn:asciiname":"Shenchongcun",
    "gn:country_code":"CN",
    "gn:dem":105,
    "gn:feature_class":"P",
    "gn:feature_code":"PPL",
    "gn:name":"Shenchongcun",
    "gn:population":0,
    "gn:timezone":"Asia/Shanghai",
    "iso:country":"CN",
    "name:zho_x_preferred":[
        "\u6df1\u51b2\u6751"
    ],
    "wof:name":"Shenchongcun",
    "wof:placetype":"locality"
},
  "geometry": {"coordinates":[116.89382999999999,31.28648],"type":"Point"}
}