{
  "type": "Feature",
  "properties": {
    "gn:admin1_code":"18",
    "gn:asciiname":"Hejia Wuji",
    "gn:country_code":"CN",
    "gn:dem":1139,
    "gn:feature_class":"P",
    "gn:feature_code":"PPL",
    "gn:name":"Hejia Wuji",
    "gn:population":0,
    "gn:timezone":"Asia/Shanghai",
    "iso:country":"CN",
    "name:zho_x_preferred":[
        "\u4f55\u5bb6\u5c4b\u57fa"
    ],
    "wof:name":"Hejia Wuji",
    "wof:placetype":"locality"
},
  "geometry": {"coordinates":[107.458,27.8922],"type":"Point"}
}