{
  "type": "Feature",
  "properties": {
    "gn:admin1_code":"10.0",
    "gn:asciiname":"Yihezhuang",
    "gn:country_code":"CN",
    "gn:dem":25,
    "gn:feature_class":"P",
    "gn:feature_code":"PPL",
    "gn:name":"Yihezhuang",
    "gn:population":0,
    "gn:timezone":"Asia/Shanghai",
    "iso:country":"CN",
    "name:zho_x_preferred":[
        "\u4e49\u5408\u5e84"
    ],
    "wof:name":"Yihezhuang",
    "wof:placetype":"locality"
},
  "geometry": {"coordinates":[115.58463999999999,39.04661],"type":"Point"}
}