{
  "type": "Feature",
  "properties": {
    "gn:admin1_code":"1.0",
    "gn:asciiname":"Longweizhang",
    "gn:country_code":"CN",
    "gn:dem":18,
    "gn:feature_class":"P",
    "gn:feature_code":"PPL",
    "gn:name":"Longweizhang",
    "gn:population":0,
    "gn:timezone":"Asia/Shanghai",
    "iso:country":"CN",
    "name:zho_x_preferred":[
        "\u9f99\u5c3e\u5f20"
    ],
    "wof:name":"Longweizhang",
    "wof:placetype":"locality"
},
  "geometry": {"coordinates":[118.55801,31.1138],"type":"Point"}
}