{
  "type": "Feature",
  "properties": {
    "gn:admin1_code":"15.0",
    "gn:asciiname":"Jing'erji",
    "gn:country_code":"CN",
    "gn:dem":2119,
    "gn:feature_class":"P",
    "gn:feature_code":"PPL",
    "gn:name":"Jing\u2019erji",
    "gn:population":0,
    "gn:timezone":"Asia/Shanghai",
    "iso:country":"CN",
    "name:und_x_variant":[
        "Jing\u2019erji"
    ],
    "name:zho_x_preferred":[
        "\u4e95\u513f\u96c6"
    ],
    "wof:name":"Jing'erji",
    "wof:placetype":"locality"
},
  "geometry": {"coordinates":[104.806,35.3292],"type":"Point"}
}