{
  "type": "Feature",
  "properties": {
    "gn:admin1_code":"15.0",
    "gn:asciiname":"Yangtai",
    "gn:country_code":"CN",
    "gn:dem":1371,
    "gn:feature_class":"P",
    "gn:feature_code":"PPL",
    "gn:name":"Yangtai",
    "gn:population":0,
    "gn:timezone":"Asia/Shanghai",
    "iso:country":"CN",
    "name:zho_x_preferred":[
        "\u9633\u53f0"
    ],
    "wof:name":"Yangtai",
    "wof:placetype":"locality"
},
  "geometry": {"coordinates":[108.122,36.2604],"type":"Point"}
}