{
  "type": "Feature",
  "properties": {
    "gn:admin1_code":"4.0",
    "gn:asciiname":"Hechengxu",
    "gn:country_code":"CN",
    "gn:dem":1,
    "gn:feature_class":"P",
    "gn:feature_code":"PPL",
    "gn:name":"Hechengxu",
    "gn:population":0,
    "gn:timezone":"Asia/Shanghai",
    "iso:country":"CN",
    "name:zho_x_preferred":[
        "\u548c\u6210\u5729"
    ],
    "wof:name":"Hechengxu",
    "wof:placetype":"locality"
},
  "geometry": {"coordinates":[119.79637,32.14074],"type":"Point"}
}