{
  "type": "Feature",
  "properties": {
    "gn:admin1_code":"28",
    "gn:asciiname":"Ts'ang-shan-chuang",
    "gn:country_code":"CN",
    "gn:dem":25,
    "gn:feature_class":"P",
    "gn:feature_code":"PPL",
    "gn:name":"Ts\u2019ang-shan-chuang",
    "gn:population":0,
    "gn:timezone":"Asia/Shanghai",
    "iso:country":"CN",
    "wof:name":"Ts'ang-shan-chuang",
    "wof:placetype":"locality"
},
  "geometry": {"coordinates":[117.73,40.02472],"type":"Point"}
}