{
  "type": "Feature",
  "properties": {
    "gn:admin1_code":"18",
    "gn:asciiname":"Meitanyao",
    "gn:country_code":"CN",
    "gn:dem":1718,
    "gn:feature_class":"P",
    "gn:feature_code":"PPL",
    "gn:name":"Meitanyao",
    "gn:population":0,
    "gn:timezone":"Asia/Shanghai",
    "iso:country":"CN",
    "name:zho_x_preferred":[
        "\u7164\u70ad\u7a91"
    ],
    "wof:name":"Meitanyao",
    "wof:placetype":"locality"
},
  "geometry": {"coordinates":[104.468,25.5011],"type":"Point"}
}