{
  "type": "Feature",
  "properties": {
    "gn:admin1_code":"18",
    "gn:asciiname":"Zhongzigou",
    "gn:country_code":"CN",
    "gn:dem":1152,
    "gn:feature_class":"P",
    "gn:feature_code":"PPL",
    "gn:name":"Zhongzigou",
    "gn:population":0,
    "gn:timezone":"Asia/Shanghai",
    "iso:country":"CN",
    "name:zho_x_preferred":[
        "\u4e2d\u5b50\u6c9f"
    ],
    "wof:name":"Zhongzigou",
    "wof:placetype":"locality"
},
  "geometry": {"coordinates":[106.977,27.7428],"type":"Point"}
}