{
  "type": "Feature",
  "properties": {
    "gn:admin1_code":"10",
    "gn:asciiname":"Daguo",
    "gn:country_code":"CN",
    "gn:dem":91,
    "gn:feature_class":"P",
    "gn:feature_code":"PPLA4",
    "gn:name":"Daguo",
    "gn:population":0,
    "gn:timezone":"Asia/Shanghai",
    "iso:country":"CN",
    "name:fas_x_preferred":[
        "\u062f\u0627\u06af\u0626\u0648"
    ],
    "name:und_x_variant":[
        "\u5927\u90ed",
        "Daguo Zhen",
        "\u5927\u90ed\u9547"
    ],
    "name:zho_x_preferred":[
        "\u5927\u90ed\u8857\u9053"
    ],
    "wof:name":"Daguo",
    "wof:placetype":"locality"
},
  "geometry": {"coordinates":[114.41030000000001,38.07388],"type":"Point"}
}