{
  "type": "Feature",
  "properties": {
    "gn:admin1_code":"18.0",
    "gn:asciiname":"Laojunzhai",
    "gn:country_code":"CN",
    "gn:dem":812,
    "gn:feature_class":"P",
    "gn:feature_code":"PPL",
    "gn:name":"Laojunzhai",
    "gn:population":0,
    "gn:timezone":"Asia/Shanghai",
    "iso:country":"CN",
    "name:zho_x_preferred":[
        "\u8001\u541b\u5be8"
    ],
    "wof:name":"Laojunzhai",
    "wof:placetype":"locality"
},
  "geometry": {"coordinates":[107.83799999999999,26.6894],"type":"Point"}
}