{
  "type": "Feature",
  "properties": {
    "gn:admin1_code":"14.0",
    "gn:asciiname":"Sharongke",
    "gn:country_code":"CN",
    "gn:dem":3703,
    "gn:feature_class":"P",
    "gn:feature_code":"PPL",
    "gn:name":"Sharongke",
    "gn:population":0,
    "gn:timezone":"Asia/Urumqi",
    "iso:country":"CN",
    "name:zho_x_preferred":[
        "\u6c99\u5bb9\u53ef"
    ],
    "wof:name":"Sharongke",
    "wof:placetype":"locality"
},
  "geometry": {"coordinates":[97.38558,32.07644000000001],"type":"Point"}
}