{
  "type": "Feature",
  "properties": {
    "gn:admin1_code":"32.0",
    "gn:asciiname":"Shangmudui",
    "gn:country_code":"CN",
    "gn:dem":1710,
    "gn:feature_class":"P",
    "gn:feature_code":"PPL",
    "gn:name":"Shangmudui",
    "gn:population":0,
    "gn:timezone":"Asia/Shanghai",
    "iso:country":"CN",
    "name:zho_x_preferred":[
        "\u4e0a\u6728\u5806"
    ],
    "wof:name":"Shangmudui",
    "wof:placetype":"locality"
},
  "geometry": {"coordinates":[102.07068,29.38252],"type":"Point"}
}