{
  "type": "Feature",
  "properties": {
    "gn:admin1_code":"14.0",
    "gn:asciiname":"Dianjiao",
    "gn:country_code":"CN",
    "gn:dem":4240,
    "gn:feature_class":"P",
    "gn:feature_code":"PPL",
    "gn:name":"Dianjiao",
    "gn:population":0,
    "gn:timezone":"Asia/Shanghai",
    "iso:country":"CN",
    "name:bod_x_preferred":[
        "D\u00eamqog"
    ],
    "name:ceb_x_preferred":[
        "Dianjiao"
    ],
    "name:deu_x_preferred":[
        "D\u00eamqog"
    ],
    "name:fas_x_preferred":[
        "\u062f\u0645\u06a9\u0648\u06af"
    ],
    "name:swe_x_preferred":[
        "Dianjiao"
    ],
    "name:und_x_variant":[
        "Tien-chiao"
    ],
    "name:zho_x_preferred":[
        "Dianjiao"
    ],
    "name:zho_x_variant":[
        "\u5178\u89d2",
        "Diemuchuoke",
        "\u789f\u7a46\u7ef0\u514b",
        "\u5178\u89d2\u6751"
    ],
    "wof:name":"Dianjiao",
    "wof:placetype":"locality"
},
  "geometry": {"coordinates":[79.46389000000001,32.69444],"type":"Point"}
}