{
  "type": "Feature",
  "properties": {
    "gn:admin1_code":"5.0",
    "gn:asciiname":"Gunmalingcun",
    "gn:country_code":"CN",
    "gn:dem":391,
    "gn:feature_class":"P",
    "gn:feature_code":"PPL",
    "gn:name":"Gunmalingcun",
    "gn:population":0,
    "gn:timezone":"Asia/Shanghai",
    "iso:country":"CN",
    "name:zho_x_preferred":[
        "\u6eda\u9a6c\u5cad\u6751"
    ],
    "wof:name":"Gunmalingcun",
    "wof:placetype":"locality"
},
  "geometry": {"coordinates":[126.36818,43.11565],"type":"Point"}
}