{
  "type": "Feature",
  "properties": {
    "gn:admin1_code":"3.0",
    "gn:asciiname":"Jianxi",
    "gn:country_code":"CN",
    "gn:dem":60,
    "gn:feature_class":"P",
    "gn:feature_code":"PPL",
    "gn:name":"Jianxi",
    "gn:population":0,
    "gn:timezone":"Asia/Shanghai",
    "iso:country":"CN",
    "name:und_x_variant":[
        "\u67a7\u6eaa"
    ],
    "wof:name":"Jianxi",
    "wof:placetype":"locality"
},
  "geometry": {"coordinates":[115.46926999999999,28.31056],"type":"Point"}
}