{
  "type": "Feature",
  "properties": {
    "gn:admin1_code":"25",
    "gn:asciiname":"Dashi Jiapo",
    "gn:country_code":"CN",
    "gn:dem":15,
    "gn:feature_class":"P",
    "gn:feature_code":"PPL",
    "gn:name":"Dashi Jiapo",
    "gn:population":0,
    "gn:timezone":"Asia/Shanghai",
    "iso:country":"CN",
    "name:zho_x_preferred":[
        "\u5927\u77f3\u5bb6\u6cca"
    ],
    "wof:name":"Dashi Jiapo",
    "wof:placetype":"locality"
},
  "geometry": {"coordinates":[122.63252,37.39478],"type":"Point"}
}