{
  "type": "Feature",
  "properties": {
    "gn:admin1_code":"18",
    "gn:asciiname":"Xiaoyunpo",
    "gn:country_code":"CN",
    "gn:dem":1078,
    "gn:feature_class":"P",
    "gn:feature_code":"PPL",
    "gn:name":"Xiaoyunpo",
    "gn:population":0,
    "gn:timezone":"Asia/Shanghai",
    "iso:country":"CN",
    "name:zho_x_preferred":[
        "\u5c0f\u4e91\u5761"
    ],
    "wof:name":"Xiaoyunpo",
    "wof:placetype":"locality"
},
  "geometry": {"coordinates":[106.777,26.5683],"type":"Point"}
}