{
  "type": "Feature",
  "properties": {
    "gn:admin1_code":"15.0",
    "gn:asciiname":"Fenlukou",
    "gn:country_code":"CN",
    "gn:dem":1748,
    "gn:feature_class":"P",
    "gn:feature_code":"PPL",
    "gn:name":"Fenlukou",
    "gn:population":0,
    "gn:timezone":"Asia/Shanghai",
    "iso:country":"CN",
    "name:zho_x_preferred":[
        "\u5206\u8def\u53e3"
    ],
    "wof:name":"Fenlukou",
    "wof:placetype":"locality"
},
  "geometry": {"coordinates":[103.226,36.0716],"type":"Point"}
}