{
  "type": "Feature",
  "properties": {
    "gn:admin1_code":"32.0",
    "gn:asciiname":"Jiuquan",
    "gn:country_code":"CN",
    "gn:dem":857,
    "gn:feature_class":"P",
    "gn:feature_code":"PPL",
    "gn:name":"Jiuquan",
    "gn:population":0,
    "gn:timezone":"Asia/Shanghai",
    "iso:country":"CN",
    "name:ara_x_preferred":[
        "\u062c\u064a\u0648\u063a\u0648\u0627\u0646"
    ],
    "name:cat_x_preferred":[
        "Jiuquan"
    ],
    "name:cdo_x_preferred":[
        "Ci\u016b-ci\u00f2ng"
    ],
    "name:ceb_x_preferred":[
        "Jiuquan"
    ],
    "name:ces_x_preferred":[
        "\u0164iou-\u010dch\u00fcan"
    ],
    "name:dan_x_preferred":[
        "Jiuquan"
    ],
    "name:deu_x_preferred":[
        "Jiuquan"
    ],
    "name:est_x_preferred":[
        "Jiuquan"
    ],
    "name:eus_x_preferred":[
        "Jiuquan"
    ],
    "name:fas_x_preferred":[
        "\u062c\u06cc\u0648\u0686\u0648\u0627\u0646"
    ],
    "name:fin_x_preferred":[
        "Jiuquan"
    ],
    "name:fra_x_preferred":[
        "Jiuquan"
    ],
    "name:ita_x_preferred":[
        "Jiuquan"
    ],
    "name:jpn_x_preferred":[
        "\u9152\u6cc9\u5e02"
    ],
    "name:kik_x_preferred":[
        "Jiuquan"
    ],
    "name:kor_x_preferred":[
        "\uc8fc\ucde8\uc548\uc2dc"
    ],
    "name:mlg_x_preferred":[
        "Jiuquan"
    ],
    "name:mon_x_preferred":[
        "\u0416\u044e\u0447\u0443\u0430\u043d\u044c"
    ],
    "name:nld_x_preferred":[
        "Jiuquan"
    ],
    "name:nno_x_preferred":[
        "Jiuquan"
    ],
    "name:nor_x_preferred":[
        "Jiuquan"
    ],
    "name:pam_x_preferred":[
        "Jiuquan"
    ],
    "name:pnb_x_preferred":[
        "\u062c\u06cc\u0648\u0686\u0648\u0622\u0646"
    ],
    "name:pol_x_preferred":[
        "Jiuquan"
    ],
    "name:por_x_preferred":[
        "Jiuquan"
    ],
    "name:rus_x_preferred":[
        "\u0426\u0437\u044e\u0446\u044e\u0430\u043d\u044c"
    ],
    "name:sco_x_preferred":[
        "Jiuquan"
    ],
    "name:spa_x_preferred":[
        "Jiuquan"
    ],
    "name:swe_x_preferred":[
        "Jiuquan"
    ],
    "name:tgl_x_preferred":[
        "Jiuquan"
    ],
    "name:tur_x_preferred":[
        "Jiuquan"
    ],
    "name:urd_x_preferred":[
        "\u062c\u06cc\u0648\u0686\u0648\u0627\u0646"
    ],
    "name:vie_x_preferred":[
        "T\u1eedu Tuy\u1ec1n"
    ],
    "name:war_x_preferred":[
        "Jiuquan"
    ],
    "name:wuu_x_preferred":[
        "\u9152\u6cc9\u5e02"
    ],
    "name:zho_x_preferred":[
        "\u4e5d\u6cc9"
    ],
    "name:zho_x_variant":[
        "\u9152\u6cc9\u5e02"
    ],
    "wof:name":"Jiuquan",
    "wof:placetype":"locality"
},
  "geometry": {"coordinates":[106.717,31.9956],"type":"Point"}
}