{
  "type": "Feature",
  "properties": {
    "gn:admin1_code":"29.0",
    "gn:asciiname":"Xinjiucun",
    "gn:country_code":"CN",
    "gn:dem":2278,
    "gn:feature_class":"P",
    "gn:feature_code":"PPL",
    "gn:name":"Xinjiucun",
    "gn:population":0,
    "gn:timezone":"Asia/Shanghai",
    "iso:country":"CN",
    "name:zho_x_preferred":[
        "\u65b0\u4e5d\u6751"
    ],
    "wof:name":"Xinjiucun",
    "wof:placetype":"locality"
},
  "geometry": {"coordinates":[100.044,25.4156],"type":"Point"}
}