{
  "type": "Feature",
  "properties": {
    "gn:admin1_code":"31.0",
    "gn:asciiname":"Chuntao",
    "gn:country_code":"CN",
    "gn:dem":8,
    "gn:feature_class":"P",
    "gn:feature_code":"PPL",
    "gn:name":"Chuntao",
    "gn:population":0,
    "gn:timezone":"Asia/Shanghai",
    "iso:country":"CN",
    "name:zho_x_preferred":[
        "Chuntao"
    ],
    "name:zho_x_variant":[
        "\u6625\u6843"
    ],
    "wof:name":"Chuntao",
    "wof:placetype":"locality"
},
  "geometry": {"coordinates":[110.96711000000001,19.63163],"type":"Point"}
}