{
  "type": "Feature",
  "properties": {
    "gn:admin1_code":"10.0",
    "gn:asciiname":"Xipaosha",
    "gn:country_code":"CN",
    "gn:dem":757,
    "gn:feature_class":"P",
    "gn:feature_code":"PPL",
    "gn:name":"Xipaosha",
    "gn:population":0,
    "gn:timezone":"Asia/Shanghai",
    "iso:country":"CN",
    "name:zho_x_preferred":[
        "\u897f\u6ce1\u6c99"
    ],
    "wof:name":"Xipaosha",
    "wof:placetype":"locality"
},
  "geometry": {"coordinates":[115.11716,40.66848],"type":"Point"}
}