{
  "type": "Feature",
  "properties": {
    "gn:admin1_code":"7.0",
    "gn:asciiname":"Xiaogaodi",
    "gn:country_code":"CN",
    "gn:dem":611,
    "gn:feature_class":"P",
    "gn:feature_code":"PPL",
    "gn:name":"Xiaogaodi",
    "gn:population":0,
    "gn:timezone":"Asia/Shanghai",
    "iso:country":"CN",
    "name:zho_x_preferred":[
        "\u5c0f\u9ad8\u5730"
    ],
    "wof:name":"Xiaogaodi",
    "wof:placetype":"locality"
},
  "geometry": {"coordinates":[116.89431999999999,26.30389000000001],"type":"Point"}
}