{
  "type": "Feature",
  "properties": {
    "gn:admin1_code":"9.0",
    "gn:asciiname":"Qingshan Houcun",
    "gn:country_code":"CN",
    "gn:dem":625,
    "gn:feature_class":"P",
    "gn:feature_code":"PPL",
    "gn:name":"Qingshan Houcun",
    "gn:population":0,
    "gn:timezone":"Asia/Shanghai",
    "iso:country":"CN",
    "name:zho_x_preferred":[
        "\u9752\u5c71\u540e\u6751"
    ],
    "wof:name":"Qingshan Houcun",
    "wof:placetype":"locality"
},
  "geometry": {"coordinates":[112.94387999999999,34.25235],"type":"Point"}
}