{
  "type": "Feature",
  "properties": {
    "gn:admin1_code":"5.0",
    "gn:asciiname":"Yujia Buzi",
    "gn:country_code":"CN",
    "gn:dem":428,
    "gn:feature_class":"P",
    "gn:feature_code":"PPL",
    "gn:name":"Yujia Buzi",
    "gn:population":0,
    "gn:timezone":"Asia/Shanghai",
    "iso:country":"CN",
    "name:und_x_variant":[
        "Yujiabaozi",
        "\u4e8e\u5bb6\u5821\u5b50",
        "Yujia Buzi"
    ],
    "wof:name":"Yujia Buzi",
    "wof:placetype":"locality"
},
  "geometry": {"coordinates":[125.51981000000001,41.52152],"type":"Point"}
}