{
  "type": "Feature",
  "properties": {
    "gn:admin1_code":"29.0",
    "gn:asciiname":"Miaopingzi",
    "gn:country_code":"CN",
    "gn:dem":2086,
    "gn:feature_class":"P",
    "gn:feature_code":"PPL",
    "gn:name":"Miaopingzi",
    "gn:population":0,
    "gn:timezone":"Asia/Shanghai",
    "iso:country":"CN",
    "name:zho_x_preferred":[
        "\u5e99\u576a\u5b50"
    ],
    "wof:name":"Miaopingzi",
    "wof:placetype":"locality"
},
  "geometry": {"coordinates":[103.696,27.6676],"type":"Point"}
}