{
  "type": "Feature",
  "properties": {
    "gn:admin1_code":"25",
    "gn:asciiname":"Liuditou",
    "gn:country_code":"CN",
    "gn:dem":65,
    "gn:feature_class":"P",
    "gn:feature_code":"PPL",
    "gn:name":"Liuditou",
    "gn:population":0,
    "gn:timezone":"Asia/Shanghai",
    "iso:country":"CN",
    "name:zho_x_preferred":[
        "\u5218\u5824\u5934"
    ],
    "wof:name":"Liuditou",
    "wof:placetype":"locality"
},
  "geometry": {"coordinates":[115.511,34.6794],"type":"Point"}
}