{
  "type": "Feature",
  "properties": {
    "gn:admin1_code":"32",
    "gn:asciiname":"Lewu",
    "gn:country_code":"CN",
    "gn:dem":1818,
    "gn:feature_class":"P",
    "gn:feature_code":"PPL",
    "gn:name":"Lewu",
    "gn:population":0,
    "gn:timezone":"Asia/Shanghai",
    "iso:country":"CN",
    "name:zho_x_preferred":[
        "\u52d2\u4e4c"
    ],
    "wof:name":"Lewu",
    "wof:placetype":"locality"
},
  "geometry": {"coordinates":[103.04246000000001,28.84591],"type":"Point"}
}