{
  "type": "Feature",
  "properties": {
    "gn:admin1_code":"22",
    "gn:asciiname":"Dashuiyu",
    "gn:country_code":"CN",
    "gn:dem":107,
    "gn:feature_class":"P",
    "gn:feature_code":"PPL",
    "gn:name":"Dashuiyu",
    "gn:population":0,
    "gn:timezone":"Asia/Shanghai",
    "iso:country":"CN",
    "name:und_x_variant":[
        "Ta-shui-y\u00fc",
        "Dashuiyu"
    ],
    "name:zho_x_preferred":[
        "\u5927\u6c34\u5cea"
    ],
    "wof:name":"Dashuiyu",
    "wof:placetype":"locality"
},
  "geometry": {"coordinates":[116.69453,40.44523],"type":"Point"}
}