{
  "type": "Feature",
  "properties": {
    "gn:admin1_code":"26.0",
    "gn:asciiname":"Zhangwanzi",
    "gn:country_code":"CN",
    "gn:dem":1444,
    "gn:feature_class":"P",
    "gn:feature_code":"PPL",
    "gn:name":"Zhangwanzi",
    "gn:population":0,
    "gn:timezone":"Asia/Shanghai",
    "iso:country":"CN",
    "name:und_x_variant":[
        "\u5f20\u6e7e\u5b50"
    ],
    "wof:name":"Zhangwanzi",
    "wof:placetype":"locality"
},
  "geometry": {"coordinates":[107.8815,36.9674],"type":"Point"}
}