{
  "type": "Feature",
  "properties": {
    "gn:admin1_code":"10",
    "gn:asciiname":"Guantao",
    "gn:country_code":"CN",
    "gn:dem":43,
    "gn:feature_class":"P",
    "gn:feature_code":"PPLA3",
    "gn:name":"Guantao",
    "gn:population":0,
    "gn:timezone":"Asia/Shanghai",
    "iso:country":"CN",
    "name:und_x_variant":[
        "Nan-kuan-t\u2019ao",
        "Kuan-t\u2019ao",
        "Nanguantao",
        "Guantao"
    ],
    "name:zho_x_preferred":[
        "\u9986\u9676"
    ],
    "wof:name":"Guantao",
    "wof:placetype":"locality"
},
  "geometry": {"coordinates":[115.28292999999999,36.54099],"type":"Point"}
}