{
  "type": "Feature",
  "properties": {
    "gn:admin1_code":"32.0",
    "gn:asciiname":"Dongqing",
    "gn:country_code":"CN",
    "gn:dem":3938,
    "gn:feature_class":"P",
    "gn:feature_code":"PPL",
    "gn:name":"Dongqing",
    "gn:population":0,
    "gn:timezone":"Asia/Shanghai",
    "iso:country":"CN",
    "name:zho_x_preferred":[
        "\u4e1c\u9752"
    ],
    "wof:name":"Dongqing",
    "wof:placetype":"locality"
},
  "geometry": {"coordinates":[100.392,32.1302],"type":"Point"}
}