{
  "type": "Feature",
  "properties": {
    "gn:admin1_code":"6.0",
    "gn:asciiname":"Yazigai",
    "gn:country_code":"CN",
    "gn:dem":2051,
    "gn:feature_class":"P",
    "gn:feature_code":"PPL",
    "gn:name":"Yazigai",
    "gn:population":0,
    "gn:timezone":"Asia/Shanghai",
    "iso:country":"CN",
    "name:und_x_variant":[
        "\u7259\u5b50\u76d6"
    ],
    "wof:name":"Yazigai",
    "wof:placetype":"locality"
},
  "geometry": {"coordinates":[102.05362,35.90091],"type":"Point"}
}