{
  "type": "Feature",
  "properties": {
    "gn:admin1_code":"26",
    "gn:asciiname":"Qianpo",
    "gn:country_code":"CN",
    "gn:dem":806,
    "gn:feature_class":"P",
    "gn:feature_code":"PPL",
    "gn:name":"Qianpo",
    "gn:population":0,
    "gn:timezone":"Asia/Shanghai",
    "iso:country":"CN",
    "name:und_x_variant":[
        "\u524d\u5761"
    ],
    "name:zho_x_preferred":[
        "\u524d\u5761"
    ],
    "wof:name":"Qianpo",
    "wof:placetype":"locality"
},
  "geometry": {"coordinates":[108.08972,34.52028],"type":"Point"}
}