{
  "type": "Feature",
  "properties": {
    "gn:admin1_code":"16.0",
    "gn:asciiname":"Baigong",
    "gn:country_code":"CN",
    "gn:dem":314,
    "gn:feature_class":"P",
    "gn:feature_code":"PPL",
    "gn:name":"Baigong",
    "gn:population":0,
    "gn:timezone":"Asia/Shanghai",
    "iso:country":"CN",
    "name:zho_x_preferred":[
        "\u767e\u4f9b"
    ],
    "wof:name":"Baigong",
    "wof:placetype":"locality"
},
  "geometry": {"coordinates":[107.554,24.0059],"type":"Point"}
}