{
  "type": "Feature",
  "properties": {
    "gn:admin1_code":"16.0",
    "gn:asciiname":"Longmaidong",
    "gn:country_code":"CN",
    "gn:dem":123,
    "gn:feature_class":"P",
    "gn:feature_code":"PPL",
    "gn:name":"Longmaidong",
    "gn:population":0,
    "gn:timezone":"Asia/Shanghai",
    "iso:country":"CN",
    "name:zho_x_preferred":[
        "\u9f99\u8109\u578c"
    ],
    "wof:name":"Longmaidong",
    "wof:placetype":"locality"
},
  "geometry": {"coordinates":[109.961,21.9953],"type":"Point"}
}