{
  "type": "Feature",
  "properties": {
    "gn:admin1_code":"10",
    "gn:asciiname":"Dadongguzhuang",
    "gn:country_code":"CN",
    "gn:dem":28,
    "gn:feature_class":"P",
    "gn:feature_code":"PPL",
    "gn:name":"Dadongguzhuang",
    "gn:population":0,
    "gn:timezone":"Asia/Shanghai",
    "iso:country":"CN",
    "name:zho_x_preferred":[
        "\u5927\u8463\u6545\u5e84"
    ],
    "wof:name":"Dadongguzhuang",
    "wof:placetype":"locality"
},
  "geometry": {"coordinates":[115.92100000000001,37.5088],"type":"Point"}
}