{
  "type": "Feature",
  "properties": {
    "gn:admin1_code":"14.0",
    "gn:asciiname":"Bianba",
    "gn:country_code":"CN",
    "gn:dem":3826,
    "gn:feature_class":"P",
    "gn:feature_code":"PPL",
    "gn:name":"Bianba",
    "gn:population":0,
    "gn:timezone":"Asia/Urumqi",
    "iso:country":"CN",
    "name:zho_x_preferred":[
        "\u8fb9\u575d"
    ],
    "wof:name":"Bianba",
    "wof:placetype":"locality"
},
  "geometry": {"coordinates":[98.37761,30.68469],"type":"Point"}
}