{
  "type": "Feature",
  "properties": {
    "gn:admin1_code":"9.0",
    "gn:asciiname":"Chenxiangcun",
    "gn:country_code":"CN",
    "gn:dem":78,
    "gn:feature_class":"P",
    "gn:feature_code":"PPL",
    "gn:name":"Chenxiangcun",
    "gn:population":0,
    "gn:timezone":"Asia/Shanghai",
    "iso:country":"CN",
    "name:zho_x_preferred":[
        "\u9648\u4e61\u6751"
    ],
    "wof:name":"Chenxiangcun",
    "wof:placetype":"locality"
},
  "geometry": {"coordinates":[114.99678,31.81977],"type":"Point"}
}