{
  "type": "Feature",
  "properties": {
    "gn:admin1_code":"11.0",
    "gn:asciiname":"Zhongyouzha",
    "gn:country_code":"CN",
    "gn:dem":373,
    "gn:feature_class":"P",
    "gn:feature_code":"PPL",
    "gn:name":"Zhongyouzha",
    "gn:population":0,
    "gn:timezone":"Asia/Shanghai",
    "iso:country":"CN",
    "name:zho_x_preferred":[
        "\u4e2d\u6cb9\u69a8"
    ],
    "wof:name":"Zhongyouzha",
    "wof:placetype":"locality"
},
  "geometry": {"coordinates":[113.43085000000001,25.84019],"type":"Point"}
}