{
  "type": "Feature",
  "properties": {
    "gn:admin1_code":"15.0",
    "gn:asciiname":"Yaogouping",
    "gn:country_code":"CN",
    "gn:dem":2045,
    "gn:feature_class":"P",
    "gn:feature_code":"PPL",
    "gn:name":"Yaogouping",
    "gn:population":0,
    "gn:timezone":"Asia/Shanghai",
    "iso:country":"CN",
    "name:zho_x_preferred":[
        "\u7a91\u6c9f\u576a"
    ],
    "wof:name":"Yaogouping",
    "wof:placetype":"locality"
},
  "geometry": {"coordinates":[104.568,35.7447],"type":"Point"}
}