{
  "type": "Feature",
  "properties": {
    "gn:admin1_code":"32.0",
    "gn:asciiname":"Caogou",
    "gn:country_code":"CN",
    "gn:dem":854,
    "gn:feature_class":"P",
    "gn:feature_code":"PPL",
    "gn:name":"Caogou",
    "gn:population":0,
    "gn:timezone":"Asia/Shanghai",
    "iso:country":"CN",
    "name:zho_x_preferred":[
        "\u66f9\u6c9f"
    ],
    "wof:name":"Caogou",
    "wof:placetype":"locality"
},
  "geometry": {"coordinates":[103.32899999999999,29.7349],"type":"Point"}
}