{
  "type": "Feature",
  "properties": {
    "gn:admin1_code":"20.0",
    "gn:asciiname":"Houbingtu",
    "gn:country_code":"CN",
    "gn:dem":1834,
    "gn:feature_class":"P",
    "gn:feature_code":"PPL",
    "gn:name":"Houbingtu",
    "gn:population":0,
    "gn:timezone":"Asia/Shanghai",
    "iso:country":"CN",
    "name:und_x_variant":[
        "\u540e\u5175\u56fe"
    ],
    "wof:name":"Houbingtu",
    "wof:placetype":"locality"
},
  "geometry": {"coordinates":[112.8394,41.24775],"type":"Point"}
}