{
  "type": "Feature",
  "properties": {
    "gn:admin1_code":"9.0",
    "gn:asciiname":"Shangyao",
    "gn:country_code":"CN",
    "gn:dem":493,
    "gn:feature_class":"P",
    "gn:feature_code":"PPL",
    "gn:name":"Shangyao",
    "gn:population":0,
    "gn:timezone":"Asia/Shanghai",
    "iso:country":"CN",
    "name:und_x_variant":[
        "\u4e0a\u7a91",
        "Shangyao"
    ],
    "wof:name":"Shangyao",
    "wof:placetype":"locality"
},
  "geometry": {"coordinates":[112.18866,33.60590999999999],"type":"Point"}
}