{
  "type": "Feature",
  "properties": {
    "gn:admin1_code":"16.0",
    "gn:asciiname":"Dengyin",
    "gn:country_code":"CN",
    "gn:dem":946,
    "gn:feature_class":"P",
    "gn:feature_code":"PPL",
    "gn:name":"Dengyin",
    "gn:population":0,
    "gn:timezone":"Asia/Shanghai",
    "iso:country":"CN",
    "name:zho_x_preferred":[
        "\u767b\u94f6"
    ],
    "wof:name":"Dengyin",
    "wof:placetype":"locality"
},
  "geometry": {"coordinates":[106.52800000000001,23.476],"type":"Point"}
}