{
  "type": "Feature",
  "properties": {
    "gn:admin1_code":"29",
    "gn:asciiname":"Xiaoweilin",
    "gn:country_code":"CN",
    "gn:dem":920,
    "gn:feature_class":"P",
    "gn:feature_code":"PPL",
    "gn:name":"Xiaoweilin",
    "gn:population":0,
    "gn:timezone":"Asia/Shanghai",
    "iso:country":"CN",
    "name:zho_x_preferred":[
        "\u5c0f\u672a\u6797"
    ],
    "wof:name":"Xiaoweilin",
    "wof:placetype":"locality"
},
  "geometry": {"coordinates":[104.512,24.3815],"type":"Point"}
}