{
  "type": "Feature",
  "properties": {
    "gn:admin1_code":"32.0",
    "gn:asciiname":"Luojiu",
    "gn:country_code":"CN",
    "gn:dem":2392,
    "gn:feature_class":"P",
    "gn:feature_code":"PPL",
    "gn:name":"Luojiu",
    "gn:population":0,
    "gn:timezone":"Asia/Shanghai",
    "iso:country":"CN",
    "name:zho_x_preferred":[
        "\u6d1b\u4e45"
    ],
    "wof:name":"Luojiu",
    "wof:placetype":"locality"
},
  "geometry": {"coordinates":[102.65600000000001,27.3025],"type":"Point"}
}