{
  "type": "Feature",
  "properties": {
    "gn:admin1_code":"30.0",
    "gn:asciiname":"Lilinzui",
    "gn:country_code":"CN",
    "gn:dem":161,
    "gn:feature_class":"P",
    "gn:feature_code":"PPL",
    "gn:name":"Lilinzui",
    "gn:population":0,
    "gn:timezone":"Asia/Shanghai",
    "iso:country":"CN",
    "name:zho_x_preferred":[
        "\u5229\u6797\u5480"
    ],
    "wof:name":"Lilinzui",
    "wof:placetype":"locality"
},
  "geometry": {"coordinates":[111.56113000000001,23.43577],"type":"Point"}
}