{
  "type": "Feature",
  "properties": {
    "gn:admin1_code":"32.0",
    "gn:asciiname":"Renkexi",
    "gn:country_code":"CN",
    "gn:dem":3301,
    "gn:feature_class":"P",
    "gn:feature_code":"PPL",
    "gn:name":"Renkexi",
    "gn:population":0,
    "gn:timezone":"Asia/Urumqi",
    "iso:country":"CN",
    "name:zho_x_preferred":[
        "\u4ec1\u67ef\u5e0c"
    ],
    "wof:name":"Renkexi",
    "wof:placetype":"locality"
},
  "geometry": {"coordinates":[98.11,32.398],"type":"Point"}
}