{
  "type": "Feature",
  "properties": {
    "gn:admin1_code":"8.0",
    "gn:asciiname":"Yilidi",
    "gn:country_code":"CN",
    "gn:dem":488,
    "gn:feature_class":"P",
    "gn:feature_code":"PPL",
    "gn:name":"Yilidi",
    "gn:population":0,
    "gn:timezone":"Asia/Shanghai",
    "iso:country":"CN",
    "name:zho_x_preferred":[
        "\u4e00\u91cc\u5730"
    ],
    "wof:name":"Yilidi",
    "wof:placetype":"locality"
},
  "geometry": {"coordinates":[128.74355,44.79764],"type":"Point"}
}