{
  "type": "Feature",
  "properties": {
    "gn:admin1_code":"8.0",
    "gn:asciiname":"Yiyangcun",
    "gn:country_code":"CN",
    "gn:dem":266,
    "gn:feature_class":"P",
    "gn:feature_code":"PPL",
    "gn:name":"Yiyangcun",
    "gn:population":0,
    "gn:timezone":"Asia/Shanghai",
    "iso:country":"CN",
    "name:zho_x_preferred":[
        "\u76ca\u9633\u6751"
    ],
    "wof:name":"Yiyangcun",
    "wof:placetype":"locality"
},
  "geometry": {"coordinates":[127.51608,45.59202],"type":"Point"}
}