{
  "type": "Feature",
  "properties": {
    "gn:admin1_code":"18",
    "gn:asciiname":"Xiaolin'ao",
    "gn:country_code":"CN",
    "gn:dem":898,
    "gn:feature_class":"P",
    "gn:feature_code":"PPL",
    "gn:name":"Xiaolin\u2019ao",
    "gn:population":0,
    "gn:timezone":"Asia/Shanghai",
    "iso:country":"CN",
    "name:und_x_variant":[
        "Xiaolin\u2019ao"
    ],
    "name:zho_x_preferred":[
        "\u5c0f\u6797\u5773"
    ],
    "wof:name":"Xiaolin'ao",
    "wof:placetype":"locality"
},
  "geometry": {"coordinates":[106.694,27.4154],"type":"Point"}
}