{
  "type": "Feature",
  "properties": {
    "gn:admin1_code":"24.0",
    "gn:asciiname":"Zhijin",
    "gn:country_code":"CN",
    "gn:dem":1193,
    "gn:feature_class":"P",
    "gn:feature_code":"PPL",
    "gn:name":"Zhijin",
    "gn:population":0,
    "gn:timezone":"Asia/Shanghai",
    "iso:country":"CN",
    "name:zho_x_preferred":[
        "\u652f\u8fdb"
    ],
    "wof:name":"Zhijin",
    "wof:placetype":"locality"
},
  "geometry": {"coordinates":[111.30022,36.80841],"type":"Point"}
}