{
  "type": "Feature",
  "properties": {
    "gn:admin1_code":"26.0",
    "gn:asciiname":"Yushu Geta",
    "gn:country_code":"CN",
    "gn:dem":1235,
    "gn:feature_class":"P",
    "gn:feature_code":"PPL",
    "gn:name":"Yushu Geta",
    "gn:population":0,
    "gn:timezone":"Asia/Shanghai",
    "iso:country":"CN",
    "name:zho_x_preferred":[
        "\u6986\u6811\u572a\u5854"
    ],
    "wof:name":"Yushu Geta",
    "wof:placetype":"locality"
},
  "geometry": {"coordinates":[109.53700000000001,37.8598],"type":"Point"}
}