{
  "type": "Feature",
  "properties": {
    "gn:admin1_code":"9",
    "gn:asciiname":"Xizhangbao",
    "gn:country_code":"CN",
    "gn:dem":57,
    "gn:feature_class":"P",
    "gn:feature_code":"PPL",
    "gn:name":"Xizhangbao",
    "gn:population":0,
    "gn:timezone":"Asia/Shanghai",
    "iso:country":"CN",
    "name:zho_x_preferred":[
        "\u897f\u4ed7\u4fdd"
    ],
    "wof:name":"Xizhangbao",
    "wof:placetype":"locality"
},
  "geometry": {"coordinates":[114.895,35.8824],"type":"Point"}
}