{
  "type": "Feature",
  "properties": {
    "gn:admin1_code":"9.0",
    "gn:asciiname":"Yuchigou",
    "gn:country_code":"CN",
    "gn:dem":217,
    "gn:feature_class":"P",
    "gn:feature_code":"PPL",
    "gn:name":"Yuchigou",
    "gn:population":0,
    "gn:timezone":"Asia/Shanghai",
    "iso:country":"CN",
    "name:zho_x_preferred":[
        "\u9c7c\u6c60\u6c9f"
    ],
    "wof:name":"Yuchigou",
    "wof:placetype":"locality"
},
  "geometry": {"coordinates":[111.49299999999999,33.18335],"type":"Point"}
}