{
  "type": "Feature",
  "properties": {
    "gn:admin1_code":"11.0",
    "gn:asciiname":"Yanlingshan",
    "gn:country_code":"CN",
    "gn:dem":153,
    "gn:feature_class":"P",
    "gn:feature_code":"PPL",
    "gn:name":"Yanlingshan",
    "gn:population":0,
    "gn:timezone":"Asia/Shanghai",
    "iso:country":"CN",
    "name:zho_x_preferred":[
        "\u5ca9\u5cad\u5c71"
    ],
    "wof:name":"Yanlingshan",
    "wof:placetype":"locality"
},
  "geometry": {"coordinates":[110.33929000000001,28.3543],"type":"Point"}
}