{
  "type": "Feature",
  "properties": {
    "gn:admin1_code":"32.0",
    "gn:asciiname":"Gangshanghu",
    "gn:country_code":"CN",
    "gn:dem":1542,
    "gn:feature_class":"P",
    "gn:feature_code":"PPL",
    "gn:name":"Gangshanghu",
    "gn:population":0,
    "gn:timezone":"Asia/Shanghai",
    "iso:country":"CN",
    "name:zho_x_preferred":[
        "\u5c97\u4e0a\u6237"
    ],
    "wof:name":"Gangshanghu",
    "wof:placetype":"locality"
},
  "geometry": {"coordinates":[103.14273,30.55086],"type":"Point"}
}