{
  "type": "Feature",
  "properties": {
    "gn:admin1_code":"20.0",
    "gn:asciiname":"Ergernhe",
    "gn:country_code":"CN",
    "gn:dem":399,
    "gn:feature_class":"P",
    "gn:feature_code":"PPL",
    "gn:name":"Ergernhe",
    "gn:population":0,
    "gn:timezone":"Asia/Shanghai",
    "iso:country":"CN",
    "name:zho_x_preferred":[
        "\u4e8c\u6839\u6cb3"
    ],
    "wof:name":"Ergernhe",
    "wof:placetype":"locality"
},
  "geometry": {"coordinates":[123.90619,49.57856],"type":"Point"}
}