{
  "type": "Feature",
  "properties": {
    "gn:admin1_code":"20.0",
    "gn:asciiname":"Fengzhengou",
    "gn:country_code":"CN",
    "gn:dem":1577,
    "gn:feature_class":"P",
    "gn:feature_code":"PPL",
    "gn:name":"Fengzhengou",
    "gn:population":0,
    "gn:timezone":"Asia/Shanghai",
    "iso:country":"CN",
    "name:und_x_variant":[
        "\u98ce\u6b63\u6c9f"
    ],
    "wof:name":"Fengzhengou",
    "wof:placetype":"locality"
},
  "geometry": {"coordinates":[109.83427,41.09452],"type":"Point"}
}