{
  "type": "Feature",
  "properties": {
    "gn:admin1_code":"29.0",
    "gn:asciiname":"Datianbao",
    "gn:country_code":"CN",
    "gn:dem":1377,
    "gn:feature_class":"P",
    "gn:feature_code":"PPL",
    "gn:name":"Datianbao",
    "gn:population":0,
    "gn:timezone":"Asia/Shanghai",
    "iso:country":"CN",
    "name:zho_x_preferred":[
        "\u5927\u7530\u5305"
    ],
    "wof:name":"Datianbao",
    "wof:placetype":"locality"
},
  "geometry": {"coordinates":[104.744,27.6942],"type":"Point"}
}