{
  "type": "Feature",
  "properties": {
    "gn:admin1_code":"19.0",
    "gn:asciiname":"Xitaizi",
    "gn:country_code":"CN",
    "gn:dem":136,
    "gn:feature_class":"P",
    "gn:feature_code":"PPL",
    "gn:name":"Xitaizi",
    "gn:population":0,
    "gn:timezone":"Asia/Shanghai",
    "iso:country":"CN",
    "name:zho_x_preferred":[
        "\u897f\u53f0\u5b50"
    ],
    "wof:name":"Xitaizi",
    "wof:placetype":"locality"
},
  "geometry": {"coordinates":[125.59399999999999,40.7833],"type":"Point"}
}