{
  "type": "Feature",
  "properties": {
    "gn:admin1_code":"15.0",
    "gn:asciiname":"Yuangong",
    "gn:country_code":"CN",
    "gn:dem":1871,
    "gn:feature_class":"P",
    "gn:feature_code":"PPL",
    "gn:name":"Yuangong",
    "gn:population":0,
    "gn:timezone":"Asia/Shanghai",
    "iso:country":"CN",
    "name:und_x_variant":[
        "\u8fdc\u5de9"
    ],
    "name:zho_x_preferred":[
        "\u8fdc\u5de9"
    ],
    "wof:name":"Yuangong",
    "wof:placetype":"locality"
},
  "geometry": {"coordinates":[104.65136,33.65475],"type":"Point"}
}