{
  "type": "Feature",
  "properties": {
    "gn:admin1_code":"29.0",
    "gn:asciiname":"Jiucheng",
    "gn:country_code":"CN",
    "gn:dem":1691,
    "gn:feature_class":"P",
    "gn:feature_code":"PPL",
    "gn:name":"Jiucheng",
    "gn:population":0,
    "gn:timezone":"Asia/Shanghai",
    "iso:country":"CN",
    "name:deu_x_preferred":[
        "Jiucheng"
    ],
    "name:zho_x_preferred":[
        "\u65e7\u57ce"
    ],
    "wof:name":"Jiucheng",
    "wof:placetype":"locality"
},
  "geometry": {"coordinates":[102.491,25.2326],"type":"Point"}
}