{
  "type": "Feature",
  "properties": {
    "gn:admin1_code":"05",
    "gn:asciiname":"Ganq Ger",
    "gn:country_code":"CN",
    "gn:dem":134,
    "gn:feature_class":"P",
    "gn:feature_code":"PPLA4",
    "gn:name":"Ganq Ger",
    "gn:population":0,
    "gn:timezone":"Asia/Shanghai",
    "iso:country":"CN",
    "name:und_x_variant":[
        "Ka-shih-ken",
        "Ganq Ger",
        "Gashigen",
        "Gashigen Xiang"
    ],
    "name:zho_x_preferred":[
        "\u560e\u4ec0\u6839"
    ],
    "name:zho_x_variant":[
        "\u560e\u4ec0\u6839\u4e61"
    ],
    "wof:name":"Ganq Ger",
    "wof:placetype":"locality"
},
  "geometry": {"coordinates":[123.66698999999998,46.21326],"type":"Point"}
}