{
  "type": "Feature",
  "properties": {
    "gn:admin1_code":"12.0",
    "gn:asciiname":"Wubangou",
    "gn:country_code":"CN",
    "gn:dem":1323,
    "gn:feature_class":"P",
    "gn:feature_code":"PPL",
    "gn:name":"Wubangou",
    "gn:population":0,
    "gn:timezone":"Asia/Shanghai",
    "iso:country":"CN",
    "name:zho_x_preferred":[
        "\u68a7\u677f\u6c9f"
    ],
    "wof:name":"Wubangou",
    "wof:placetype":"locality"
},
  "geometry": {"coordinates":[110.25736999999999,31.85615],"type":"Point"}
}