{
  "type": "Feature",
  "properties": {
    "gn:admin1_code":"7.0",
    "gn:asciiname":"Dongjingcun",
    "gn:country_code":"CN",
    "gn:dem":566,
    "gn:feature_class":"P",
    "gn:feature_code":"PPL",
    "gn:name":"Dongjingcun",
    "gn:population":0,
    "gn:timezone":"Asia/Shanghai",
    "iso:country":"CN",
    "name:zho_x_preferred":[
        "\u4e1c\u666f\u6751"
    ],
    "wof:name":"Dongjingcun",
    "wof:placetype":"locality"
},
  "geometry": {"coordinates":[117.72561,26.09633],"type":"Point"}
}