{
  "type": "Feature",
  "properties": {
    "gn:admin1_code":"11.0",
    "gn:asciiname":"Dabazi",
    "gn:country_code":"CN",
    "gn:dem":615,
    "gn:feature_class":"P",
    "gn:feature_code":"PPL",
    "gn:name":"Dabazi",
    "gn:population":0,
    "gn:timezone":"Asia/Shanghai",
    "iso:country":"CN",
    "name:zho_x_preferred":[
        "\u5927\u575d\u5b50"
    ],
    "wof:name":"Dabazi",
    "wof:placetype":"locality"
},
  "geometry": {"coordinates":[109.31456,26.29854000000001],"type":"Point"}
}