{
  "type": "Feature",
  "properties": {
    "gn:admin1_code":"15.0",
    "gn:asciiname":"Qiangfengou",
    "gn:country_code":"CN",
    "gn:dem":1938,
    "gn:feature_class":"P",
    "gn:feature_code":"PPL",
    "gn:name":"Qiangfengou",
    "gn:population":0,
    "gn:timezone":"Asia/Shanghai",
    "iso:country":"CN",
    "name:zho_x_preferred":[
        "\u7f8c\u575f\u6c9f"
    ],
    "wof:name":"Qiangfengou",
    "wof:placetype":"locality"
},
  "geometry": {"coordinates":[103.773,36.5439],"type":"Point"}
}