{
  "type": "Feature",
  "properties": {
    "gn:admin1_code":"29.0",
    "gn:asciiname":"Gaojia Wafang",
    "gn:country_code":"CN",
    "gn:dem":880,
    "gn:feature_class":"P",
    "gn:feature_code":"PPL",
    "gn:name":"Gaojia Wafang",
    "gn:population":0,
    "gn:timezone":"Asia/Shanghai",
    "iso:country":"CN",
    "name:zho_x_preferred":[
        "\u9ad8\u5bb6\u74e6\u623f"
    ],
    "wof:name":"Gaojia Wafang",
    "wof:placetype":"locality"
},
  "geometry": {"coordinates":[104.188,28.4791],"type":"Point"}
}