{
  "type": "Feature",
  "properties": {
    "gn:admin1_code":"32.0",
    "gn:asciiname":"Tuguansi",
    "gn:country_code":"CN",
    "gn:dem":1161,
    "gn:feature_class":"P",
    "gn:feature_code":"PPL",
    "gn:name":"Tuguansi",
    "gn:population":0,
    "gn:timezone":"Asia/Shanghai",
    "iso:country":"CN",
    "name:zho_x_preferred":[
        "\u571f\u5b98\u53f8"
    ],
    "wof:name":"Tuguansi",
    "wof:placetype":"locality"
},
  "geometry": {"coordinates":[104.503,27.8912],"type":"Point"}
}