{
  "type": "Feature",
  "properties": {
    "gn:admin1_code":"11.0",
    "gn:asciiname":"Misha",
    "gn:country_code":"CN",
    "gn:dem":250,
    "gn:feature_class":"P",
    "gn:feature_code":"PPL",
    "gn:name":"Misha",
    "gn:population":0,
    "gn:timezone":"Asia/Shanghai",
    "iso:country":"CN",
    "name:bel_x_preferred":[
        "\u0410\u043b\u0456\u043c\u043f\u0456\u0439\u0441\u043a\u0456 \u041c\u0456\u0448\u043a\u0430"
    ],
    "name:bul_x_preferred":[
        "\u041c\u0438\u0448\u0430"
    ],
    "name:cat_x_preferred":[
        "Misha"
    ],
    "name:ces_x_preferred":[
        "M\u00ed\u0161a"
    ],
    "name:deu_x_preferred":[
        "Mischa"
    ],
    "name:ell_x_preferred":[
        "\u039c\u03af\u03c3\u03b1"
    ],
    "name:eus_x_preferred":[
        "Misha"
    ],
    "name:fin_x_preferred":[
        "Miska-karhu"
    ],
    "name:fra_x_preferred":[
        "Misha"
    ],
    "name:heb_x_preferred":[
        "\u05de\u05d9\u05e9\u05d4"
    ],
    "name:hye_x_preferred":[
        "\u0555\u056c\u056b\u0574\u057a\u056b\u0561\u056f\u0561\u0576 \u0561\u0580\u057b\u0578\u0582\u056f"
    ],
    "name:kor_x_preferred":[
        "\ubbf8\uc0e4"
    ],
    "name:nld_x_preferred":[
        "Misha"
    ],
    "name:pol_x_preferred":[
        "Misza"
    ],
    "name:por_x_preferred":[
        "Misha"
    ],
    "name:rus_x_preferred":[
        "\u041e\u043b\u0438\u043c\u043f\u0438\u0439\u0441\u043a\u0438\u0439 \u041c\u0438\u0448\u043a\u0430"
    ],
    "name:sah_x_preferred":[
        "\u041c\u0438\u0448\u0430"
    ],
    "name:spa_x_preferred":[
        "Misha"
    ],
    "name:swe_x_preferred":[
        "Misja"
    ],
    "name:tha_x_preferred":[
        "\u0e21\u0e35\u0e0a\u0e32"
    ],
    "name:tur_x_preferred":[
        "Mi\u015fa"
    ],
    "name:ukr_x_preferred":[
        "\u041e\u043b\u0456\u043c\u043f\u0456\u0439\u0441\u044c\u043a\u0438\u0439 \u041c\u0456\u0448\u043a\u0430"
    ],
    "name:zho_x_preferred":[
        "\u7c73\u6c99"
    ],
    "name:zho_x_variant":[
        "\u7c73\u6c99\u718a"
    ],
    "wof:name":"Misha",
    "wof:placetype":"locality"
},
  "geometry": {"coordinates":[109.46826,27.71448],"type":"Point"}
}