{
  "type": "Feature",
  "properties": {
    "gn:admin1_code":"20.0",
    "gn:asciiname":"Dajiucaigou",
    "gn:country_code":"CN",
    "gn:dem":256,
    "gn:feature_class":"P",
    "gn:feature_code":"PPL",
    "gn:name":"Dajiucaigou",
    "gn:population":0,
    "gn:timezone":"Asia/Shanghai",
    "iso:country":"CN",
    "name:zho_x_preferred":[
        "\u5927\u97ed\u83dc\u6c9f"
    ],
    "wof:name":"Dajiucaigou",
    "wof:placetype":"locality"
},
  "geometry": {"coordinates":[125.21083,49.71987],"type":"Point"}
}