{
  "type": "Feature",
  "properties": {
    "gn:admin1_code":"26.0",
    "gn:asciiname":"Chenjiawancun",
    "gn:country_code":"CN",
    "gn:dem":650,
    "gn:feature_class":"P",
    "gn:feature_code":"PPL",
    "gn:name":"Chenjiawancun",
    "gn:population":0,
    "gn:timezone":"Asia/Shanghai",
    "iso:country":"CN",
    "name:zho_x_preferred":[
        "\u9648\u5bb6\u6e7e\u6751"
    ],
    "wof:name":"Chenjiawancun",
    "wof:placetype":"locality"
},
  "geometry": {"coordinates":[109.83606,33.51953],"type":"Point"}
}