{
  "type": "Feature",
  "properties": {
    "gn:admin1_code":"15.0",
    "gn:asciiname":"Beiguoyuan",
    "gn:country_code":"CN",
    "gn:dem":1578,
    "gn:feature_class":"P",
    "gn:feature_code":"PPL",
    "gn:name":"Beiguoyuan",
    "gn:population":0,
    "gn:timezone":"Asia/Shanghai",
    "iso:country":"CN",
    "name:und_x_variant":[
        "\u5317\u90ed\u586c"
    ],
    "wof:name":"Beiguoyuan",
    "wof:placetype":"locality"
},
  "geometry": {"coordinates":[107.29694000000001,36.64064000000001],"type":"Point"}
}