{
  "type": "Feature",
  "properties": {
    "gn:admin1_code":"11.0",
    "gn:asciiname":"Sunjiawan",
    "gn:country_code":"CN",
    "gn:dem":32,
    "gn:feature_class":"P",
    "gn:feature_code":"PPL",
    "gn:name":"Sunjiawan",
    "gn:population":0,
    "gn:timezone":"Asia/Shanghai",
    "iso:country":"CN",
    "name:zho_x_preferred":[
        "Sunjiawan"
    ],
    "name:zho_x_variant":[
        "\u5b59\u5bb6\u6e7e"
    ],
    "wof:name":"Sunjiawan",
    "wof:placetype":"locality"
},
  "geometry": {"coordinates":[111.79711,28.98808],"type":"Point"}
}