{
  "type": "Feature",
  "properties": {
    "gn:admin1_code":"2.0",
    "gn:asciiname":"Wailinshan",
    "gn:country_code":"CN",
    "gn:dem":171,
    "gn:feature_class":"P",
    "gn:feature_code":"PPL",
    "gn:name":"Wailinshan",
    "gn:population":0,
    "gn:timezone":"Asia/Shanghai",
    "iso:country":"CN",
    "name:zho_x_preferred":[
        "\u5916\u6797\u5c71"
    ],
    "wof:name":"Wailinshan",
    "wof:placetype":"locality"
},
  "geometry": {"coordinates":[119.50582,29.71648],"type":"Point"}
}