{
  "type": "Feature",
  "properties": {
    "gn:admin1_code":"3.0",
    "gn:asciiname":"Zhangshili",
    "gn:country_code":"CN",
    "gn:dem":75,
    "gn:feature_class":"P",
    "gn:feature_code":"PPL",
    "gn:name":"Zhangshili",
    "gn:population":0,
    "gn:timezone":"Asia/Shanghai",
    "iso:country":"CN",
    "name:und_x_variant":[
        "\u4e08\u77f3\u91cc"
    ],
    "wof:name":"Zhangshili",
    "wof:placetype":"locality"
},
  "geometry": {"coordinates":[115.20941000000001,28.74721],"type":"Point"}
}