{
  "type": "Feature",
  "properties": {
    "gn:admin1_code":"10.0",
    "gn:asciiname":"Huanggezhuang",
    "gn:country_code":"CN",
    "gn:dem":32,
    "gn:feature_class":"P",
    "gn:feature_code":"PPL",
    "gn:name":"Huanggezhuang",
    "gn:population":0,
    "gn:timezone":"Asia/Shanghai",
    "iso:country":"CN",
    "name:zho_x_preferred":[
        "\u9ec4\u5404\u5e84"
    ],
    "wof:name":"Huanggezhuang",
    "wof:placetype":"locality"
},
  "geometry": {"coordinates":[116.00848000000001,39.3785],"type":"Point"}
}