{
  "type": "Feature",
  "properties": {
    "gn:admin1_code":"4.0",
    "gn:asciiname":"Tongchengcun",
    "gn:country_code":"CN",
    "gn:dem":2,
    "gn:feature_class":"P",
    "gn:feature_code":"PPL",
    "gn:name":"Tongchengcun",
    "gn:population":0,
    "gn:timezone":"Asia/Shanghai",
    "iso:country":"CN",
    "name:zho_x_preferred":[
        "\u901a\u57ce\u6751"
    ],
    "wof:name":"Tongchengcun",
    "wof:placetype":"locality"
},
  "geometry": {"coordinates":[120.29730000000001,32.79852],"type":"Point"}
}