{
  "type": "Feature",
  "properties": {
    "gn:admin1_code":"32.0",
    "gn:asciiname":"Gaotiaodeng",
    "gn:country_code":"CN",
    "gn:dem":462,
    "gn:feature_class":"P",
    "gn:feature_code":"PPL",
    "gn:name":"Gaotiaodeng",
    "gn:population":0,
    "gn:timezone":"Asia/Shanghai",
    "iso:country":"CN",
    "name:zho_x_preferred":[
        "\u9ad8\u8df3\u767b"
    ],
    "wof:name":"Gaotiaodeng",
    "wof:placetype":"locality"
},
  "geometry": {"coordinates":[104.246,29.5554],"type":"Point"}
}