{
  "type": "Feature",
  "properties": {
    "gn:admin1_code":"9.0",
    "gn:asciiname":"Beiyecun",
    "gn:country_code":"CN",
    "gn:dem":273,
    "gn:feature_class":"P",
    "gn:feature_code":"PPL",
    "gn:name":"Beiyecun",
    "gn:population":0,
    "gn:timezone":"Asia/Shanghai",
    "iso:country":"CN",
    "name:zho_x_preferred":[
        "\u5317\u51b6\u6751"
    ],
    "wof:name":"Beiyecun",
    "wof:placetype":"locality"
},
  "geometry": {"coordinates":[112.13732,34.86769],"type":"Point"}
}