{
  "type": "Feature",
  "properties": {
    "gn:admin1_code":"1.0",
    "gn:asciiname":"Hongzhangcun",
    "gn:country_code":"CN",
    "gn:dem":66,
    "gn:feature_class":"P",
    "gn:feature_code":"PPL",
    "gn:name":"Hongzhangcun",
    "gn:population":0,
    "gn:timezone":"Asia/Shanghai",
    "iso:country":"CN",
    "name:zho_x_preferred":[
        "\u7ea2\u5f20\u6751"
    ],
    "wof:name":"Hongzhangcun",
    "wof:placetype":"locality"
},
  "geometry": {"coordinates":[117.79703000000001,32.19686],"type":"Point"}
}