{
  "type": "Feature",
  "properties": {
    "gn:admin1_code":"32.0",
    "gn:asciiname":"Chengjiao",
    "gn:country_code":"CN",
    "gn:dem":2888,
    "gn:feature_class":"P",
    "gn:feature_code":"PPL",
    "gn:name":"Chengjiao",
    "gn:population":0,
    "gn:timezone":"Asia/Shanghai",
    "iso:country":"CN",
    "name:ceb_x_preferred":[
        "Chengjiao"
    ],
    "name:deu_x_preferred":[
        "Chengjiao"
    ],
    "name:swe_x_preferred":[
        "Chengjiao"
    ],
    "name:zho_x_preferred":[
        "\u57ce\u90ca"
    ],
    "wof:name":"Chengjiao",
    "wof:placetype":"locality"
},
  "geometry": {"coordinates":[99.8005,28.9313],"type":"Point"}
}