{
  "type": "Feature",
  "properties": {
    "gn:admin1_code":"13.0",
    "gn:asciiname":"Karanggazi",
    "gn:country_code":"CN",
    "gn:dem":3122,
    "gn:feature_class":"P",
    "gn:feature_code":"PPL",
    "gn:name":"Karanggazi",
    "gn:population":0,
    "gn:timezone":"Asia/Shanghai",
    "iso:country":"CN",
    "name:zho_x_preferred":[
        "\u5580\u8ba9\u5c15\u5b5c"
    ],
    "wof:name":"Karanggazi",
    "wof:placetype":"locality"
},
  "geometry": {"coordinates":[78.68196,36.74873],"type":"Point"}
}