{
  "type": "Feature",
  "properties": {
    "gn:admin1_code":"19.0",
    "gn:asciiname":"Sitaizi",
    "gn:country_code":"CN",
    "gn:dem":43,
    "gn:feature_class":"P",
    "gn:feature_code":"PPL",
    "gn:name":"Sitaizi",
    "gn:population":0,
    "gn:timezone":"Asia/Shanghai",
    "iso:country":"CN",
    "name:zho_x_preferred":[
        "\u56db\u53f0\u5b50"
    ],
    "wof:name":"Sitaizi",
    "wof:placetype":"locality"
},
  "geometry": {"coordinates":[123.26000000000001,42.05544],"type":"Point"}
}