{
  "type": "Feature",
  "properties": {
    "gn:admin1_code":"16.0",
    "gn:asciiname":"Dingbiao",
    "gn:country_code":"CN",
    "gn:dem":131,
    "gn:feature_class":"P",
    "gn:feature_code":"PPL",
    "gn:name":"Dingbiao",
    "gn:population":0,
    "gn:timezone":"Asia/Shanghai",
    "iso:country":"CN",
    "name:zho_x_preferred":[
        "\u5b9a\u6807"
    ],
    "wof:name":"Dingbiao",
    "wof:placetype":"locality"
},
  "geometry": {"coordinates":[108.14100000000001,23.2223],"type":"Point"}
}