{
  "type": "Feature",
  "properties": {
    "gn:admin1_code":"18",
    "gn:asciiname":"Qianxincun",
    "gn:country_code":"CN",
    "gn:dem":892,
    "gn:feature_class":"P",
    "gn:feature_code":"PPL",
    "gn:name":"Qianxincun",
    "gn:population":0,
    "gn:timezone":"Asia/Shanghai",
    "iso:country":"CN",
    "name:zho_x_preferred":[
        "\u9ed4\u65b0\u6751"
    ],
    "wof:name":"Qianxincun",
    "wof:placetype":"locality"
},
  "geometry": {"coordinates":[106.456,28.4853],"type":"Point"}
}