{
  "type": "Feature",
  "properties": {
    "gn:admin1_code":"7",
    "gn:asciiname":"Shuyang",
    "gn:country_code":"CN",
    "gn:dem":240,
    "gn:feature_class":"P",
    "gn:feature_code":"PPL",
    "gn:name":"Shuyang",
    "gn:population":0,
    "gn:timezone":"Asia/Shanghai",
    "iso:country":"CN",
    "name:und_x_variant":[
        "\u67a2\u6d0b",
        "Shuyang"
    ],
    "wof:name":"Shuyang",
    "wof:placetype":"locality"
},
  "geometry": {"coordinates":[119.67703,27.16427],"type":"Point"}
}