{
  "type": "Feature",
  "properties": {
    "gn:admin1_code":"19.0",
    "gn:asciiname":"Yutuozicun",
    "gn:country_code":"CN",
    "gn:dem":12,
    "gn:feature_class":"P",
    "gn:feature_code":"PPL",
    "gn:name":"Yutuozicun",
    "gn:population":0,
    "gn:timezone":"Asia/Shanghai",
    "iso:country":"CN",
    "name:zho_x_preferred":[
        "\u6986\u5768\u5b50\u6751"
    ],
    "wof:name":"Yutuozicun",
    "wof:placetype":"locality"
},
  "geometry": {"coordinates":[122.38,41.5239],"type":"Point"}
}