{
  "type": "Feature",
  "properties": {
    "gn:admin1_code":"2.0",
    "gn:asciiname":"Sanshantou",
    "gn:country_code":"CN",
    "gn:dem":18,
    "gn:feature_class":"P",
    "gn:feature_code":"PPL",
    "gn:name":"Sanshantou",
    "gn:population":0,
    "gn:timezone":"Asia/Shanghai",
    "iso:country":"CN",
    "name:zho_x_preferred":[
        "\u4e09\u5c71\u5934"
    ],
    "wof:name":"Sanshantou",
    "wof:placetype":"locality"
},
  "geometry": {"coordinates":[120.59404000000001,27.83686],"type":"Point"}
}