{
  "type": "Feature",
  "properties": {
    "gn:admin1_code":"8.0",
    "gn:asciiname":"Xinzhengcun",
    "gn:country_code":"CN",
    "gn:dem":81,
    "gn:feature_class":"P",
    "gn:feature_code":"PPL",
    "gn:name":"Xinzhengcun",
    "gn:population":0,
    "gn:timezone":"Asia/Shanghai",
    "iso:country":"CN",
    "name:zho_x_preferred":[
        "\u65b0\u5f81\u6751"
    ],
    "wof:name":"Xinzhengcun",
    "wof:placetype":"locality"
},
  "geometry": {"coordinates":[130.27728000000002,46.96288],"type":"Point"}
}