{
  "type": "Feature",
  "properties": {
    "gn:admin1_code":"19.0",
    "gn:asciiname":"Chengzi",
    "gn:country_code":"CN",
    "gn:dem":127,
    "gn:feature_class":"P",
    "gn:feature_code":"PPL",
    "gn:name":"Chengzi",
    "gn:population":0,
    "gn:timezone":"Asia/Shanghai",
    "iso:country":"CN",
    "name:und_x_variant":[
        "\u57ce\u5b50"
    ],
    "name:zho_x_preferred":[
        "\u57ce\u5b50"
    ],
    "wof:name":"Chengzi",
    "wof:placetype":"locality"
},
  "geometry": {"coordinates":[123.47987999999999,42.4212],"type":"Point"}
}