{
  "type": "Feature",
  "properties": {
    "gn:admin1_code":"2.0",
    "gn:asciiname":"Zhufeng",
    "gn:country_code":"CN",
    "gn:dem":448,
    "gn:feature_class":"P",
    "gn:feature_code":"PPL",
    "gn:name":"Zhufeng",
    "gn:population":0,
    "gn:timezone":"Asia/Shanghai",
    "iso:country":"CN",
    "name:zho_x_preferred":[
        "\u67f1\u5cf0"
    ],
    "wof:name":"Zhufeng",
    "wof:placetype":"locality"
},
  "geometry": {"coordinates":[120.77070999999999,29.02386],"type":"Point"}
}