{
  "type": "Feature",
  "properties": {
    "gn:admin1_code":"11.0",
    "gn:asciiname":"Qiaotai",
    "gn:country_code":"CN",
    "gn:dem":481,
    "gn:feature_class":"P",
    "gn:feature_code":"PPL",
    "gn:name":"Qiaotai",
    "gn:population":0,
    "gn:timezone":"Asia/Shanghai",
    "iso:country":"CN",
    "name:zho_x_preferred":[
        "\u6865\u592a"
    ],
    "wof:name":"Qiaotai",
    "wof:placetype":"locality"
},
  "geometry": {"coordinates":[109.97302999999999,26.5551],"type":"Point"}
}