{
  "type": "Feature",
  "properties": {
    "gn:admin1_code":"1.0",
    "gn:asciiname":"Zaolincun",
    "gn:country_code":"CN",
    "gn:dem":26,
    "gn:feature_class":"P",
    "gn:feature_code":"PPL",
    "gn:name":"Zaolincun",
    "gn:population":0,
    "gn:timezone":"Asia/Shanghai",
    "iso:country":"CN",
    "name:zho_x_preferred":[
        "\u67a3\u6797\u6751"
    ],
    "wof:name":"Zaolincun",
    "wof:placetype":"locality"
},
  "geometry": {"coordinates":[116.8125,31.50989],"type":"Point"}
}