{
  "type": "Feature",
  "properties": {
    "gn:admin1_code":"29.0",
    "gn:asciiname":"Baojia Xiaozhai",
    "gn:country_code":"CN",
    "gn:dem":1756,
    "gn:feature_class":"P",
    "gn:feature_code":"PPL",
    "gn:name":"Baojia Xiaozhai",
    "gn:population":0,
    "gn:timezone":"Asia/Shanghai",
    "iso:country":"CN",
    "name:zho_x_preferred":[
        "\u5b9d\u5bb6\u5c0f\u5be8"
    ],
    "wof:name":"Baojia Xiaozhai",
    "wof:placetype":"locality"
},
  "geometry": {"coordinates":[98.7345,24.6794],"type":"Point"}
}