{
  "type": "Feature",
  "properties": {
    "gn:admin1_code":"32.0",
    "gn:asciiname":"Siji",
    "gn:country_code":"CN",
    "gn:dem":1232,
    "gn:feature_class":"P",
    "gn:feature_code":"PPL",
    "gn:name":"Siji",
    "gn:population":0,
    "gn:timezone":"Asia/Shanghai",
    "iso:country":"CN",
    "name:zho_x_preferred":[
        "\u56db\u5b63"
    ],
    "wof:name":"Siji",
    "wof:placetype":"locality"
},
  "geometry": {"coordinates":[105.48699999999999,28.25],"type":"Point"}
}