{
  "type": "Feature",
  "properties": {
    "gn:admin1_code":"24.0",
    "gn:asciiname":"Xiao'antan",
    "gn:country_code":"CN",
    "gn:dem":1038,
    "gn:feature_class":"P",
    "gn:feature_code":"PPL",
    "gn:name":"Xiao\u2019antan",
    "gn:population":0,
    "gn:timezone":"Asia/Shanghai",
    "iso:country":"CN",
    "name:und_x_variant":[
        "Xiao\u2019antan"
    ],
    "name:zho_x_preferred":[
        "\u5c0f\u5b89\u6ee9"
    ],
    "wof:name":"Xiao'antan",
    "wof:placetype":"locality"
},
  "geometry": {"coordinates":[113.71212,40.30322],"type":"Point"}
}