{
  "type": "Feature",
  "properties": {
    "gn:admin1_code":"18.0",
    "gn:asciiname":"Xiaodongjiao",
    "gn:country_code":"CN",
    "gn:dem":679,
    "gn:feature_class":"P",
    "gn:feature_code":"PPL",
    "gn:name":"Xiaodongjiao",
    "gn:population":0,
    "gn:timezone":"Asia/Shanghai",
    "iso:country":"CN",
    "name:zho_x_preferred":[
        "\u5c0f\u6d1e\u811a"
    ],
    "wof:name":"Xiaodongjiao",
    "wof:placetype":"locality"
},
  "geometry": {"coordinates":[108.86,26.7736],"type":"Point"}
}