{
  "type": "Feature",
  "properties": {
    "gn:admin1_code":"12.0",
    "gn:asciiname":"Mibei",
    "gn:country_code":"CN",
    "gn:dem":23,
    "gn:feature_class":"P",
    "gn:feature_code":"PPL",
    "gn:name":"Mibei",
    "gn:population":0,
    "gn:timezone":"Asia/Shanghai",
    "iso:country":"CN",
    "name:zho_x_preferred":[
        "\u7cdc\u5317"
    ],
    "wof:name":"Mibei",
    "wof:placetype":"locality"
},
  "geometry": {"coordinates":[113.55182000000001,30.64247],"type":"Point"}
}