{
  "type": "Feature",
  "properties": {
    "gn:admin1_code":"05",
    "gn:asciiname":"Yangmu Dingzi",
    "gn:country_code":"CN",
    "gn:dem":459,
    "gn:feature_class":"P",
    "gn:feature_code":"PPL",
    "gn:name":"Yangmu Dingzi",
    "gn:population":0,
    "gn:timezone":"Asia/Shanghai",
    "iso:country":"CN",
    "name:und_x_variant":[
        "Yangmudingzi"
    ],
    "name:zho_x_preferred":[
        "\u6768\u6728\u9876\u5b50"
    ],
    "wof:name":"Yangmu Dingzi",
    "wof:placetype":"locality"
},
  "geometry": {"coordinates":[126.26765,43.20891],"type":"Point"}
}