{
  "type": "Feature",
  "properties": {
    "gn:admin1_code":"2.0",
    "gn:asciiname":"Meifeng",
    "gn:country_code":"CN",
    "gn:dem":664,
    "gn:feature_class":"P",
    "gn:feature_code":"PPL",
    "gn:name":"Meifeng",
    "gn:population":0,
    "gn:timezone":"Asia/Shanghai",
    "iso:country":"CN",
    "name:und_x_variant":[
        "\u6885\u67ab",
        "Meifeng"
    ],
    "wof:name":"Meifeng",
    "wof:placetype":"locality"
},
  "geometry": {"coordinates":[119.58049,27.86452],"type":"Point"}
}