{
  "type": "Feature",
  "properties": {
    "gn:admin1_code":"26.0",
    "gn:asciiname":"Caojiafang",
    "gn:country_code":"CN",
    "gn:dem":1218,
    "gn:feature_class":"P",
    "gn:feature_code":"PPL",
    "gn:name":"Caojiafang",
    "gn:population":0,
    "gn:timezone":"Asia/Shanghai",
    "iso:country":"CN",
    "name:zho_x_preferred":[
        "\u66f9\u5bb6\u623f"
    ],
    "wof:name":"Caojiafang",
    "wof:placetype":"locality"
},
  "geometry": {"coordinates":[109.18446000000002,38.30489],"type":"Point"}
}