{
  "type": "Feature",
  "properties": {
    "gn:admin1_code":"9.0",
    "gn:asciiname":"Zhouweizi",
    "gn:country_code":"CN",
    "gn:dem":50,
    "gn:feature_class":"P",
    "gn:feature_code":"PPL",
    "gn:name":"Zhouweizi",
    "gn:population":0,
    "gn:timezone":"Asia/Shanghai",
    "iso:country":"CN",
    "name:zho_x_preferred":[
        "\u5468\u56f4\u5b5c"
    ],
    "wof:name":"Zhouweizi",
    "wof:placetype":"locality"
},
  "geometry": {"coordinates":[114.62739999999999,32.41194],"type":"Point"}
}