{
  "type": "Feature",
  "properties": {
    "gn:admin1_code":"29.0",
    "gn:asciiname":"Tuojing",
    "gn:country_code":"CN",
    "gn:dem":1692,
    "gn:feature_class":"P",
    "gn:feature_code":"PPL",
    "gn:name":"Tuojing",
    "gn:population":0,
    "gn:timezone":"Asia/Shanghai",
    "iso:country":"CN",
    "name:und_x_variant":[
        "\u62d6\u4e95"
    ],
    "wof:name":"Tuojing",
    "wof:placetype":"locality"
},
  "geometry": {"coordinates":[102.71373,25.91009],"type":"Point"}
}