{
  "type": "Feature",
  "properties": {
    "gn:admin1_code":"9.0",
    "gn:asciiname":"Xianpo",
    "gn:country_code":"CN",
    "gn:dem":860,
    "gn:feature_class":"P",
    "gn:feature_code":"PPL",
    "gn:name":"Xianpo",
    "gn:population":0,
    "gn:timezone":"Asia/Shanghai",
    "iso:country":"CN",
    "name:zho_x_preferred":[
        "\u73b0\u5761"
    ],
    "wof:name":"Xianpo",
    "wof:placetype":"locality"
},
  "geometry": {"coordinates":[110.72991,34.31156],"type":"Point"}
}