{
  "type": "Feature",
  "properties": {
    "gn:admin1_code":"26.0",
    "gn:asciiname":"Dongwang",
    "gn:country_code":"CN",
    "gn:dem":725,
    "gn:feature_class":"P",
    "gn:feature_code":"PPL",
    "gn:name":"Dongwang",
    "gn:population":0,
    "gn:timezone":"Asia/Shanghai",
    "iso:country":"CN",
    "name:deu_x_preferred":[
        "Dongwang"
    ],
    "name:und_x_variant":[
        "\u4e1c\u738b"
    ],
    "wof:name":"Dongwang",
    "wof:placetype":"locality"
},
  "geometry": {"coordinates":[107.41433000000001,34.39728],"type":"Point"}
}