{
  "type": "Feature",
  "properties": {
    "gn:admin1_code":"7.0",
    "gn:asciiname":"Kengkou Famuchang",
    "gn:country_code":"CN",
    "gn:dem":319,
    "gn:feature_class":"P",
    "gn:feature_code":"PPLF",
    "gn:name":"Kengkou Famuchang",
    "gn:population":0,
    "gn:timezone":"Asia/Shanghai",
    "iso:country":"CN",
    "name:zho_x_preferred":[
        "\u5751\u53e3\u4f10\u6728\u573a"
    ],
    "wof:name":"Kengkou Famuchang",
    "wof:placetype":"locality"
},
  "geometry": {"coordinates":[118.62430999999999,27.61907],"type":"Point"}
}