{
  "type": "Feature",
  "properties": {
    "gn:admin1_code":"9.0",
    "gn:asciiname":"Tieli",
    "gn:country_code":"CN",
    "gn:dem":128,
    "gn:feature_class":"P",
    "gn:feature_code":"PPL",
    "gn:name":"Tieli",
    "gn:population":0,
    "gn:timezone":"Asia/Shanghai",
    "iso:country":"CN",
    "name:ara_x_preferred":[
        "\u062a\u064a\u0644\u064a"
    ],
    "name:bxr_x_preferred":[
        "\u0422\u0435\u043b\u0438"
    ],
    "name:ceb_x_preferred":[
        "Tieli"
    ],
    "name:deu_x_preferred":[
        "Tieli"
    ],
    "name:fra_x_preferred":[
        "Tieli"
    ],
    "name:ita_x_preferred":[
        "Tieli"
    ],
    "name:jpn_x_preferred":[
        "\u9244\u529b\u5e02"
    ],
    "name:kik_x_preferred":[
        "Tieli"
    ],
    "name:kor_x_preferred":[
        "\ud184\ub9ac\uc2dc"
    ],
    "name:mlg_x_preferred":[
        "Tieli"
    ],
    "name:nor_x_preferred":[
        "Tieli"
    ],
    "name:pam_x_preferred":[
        "Tieli"
    ],
    "name:rus_x_preferred":[
        "\u0422\u0435\u043b\u0438"
    ],
    "name:swe_x_preferred":[
        "Tieli"
    ],
    "name:urd_x_preferred":[
        "\u062a\u06cc\u0626\u0644\u06cc"
    ],
    "name:vie_x_preferred":[
        "Thi\u1ebft L\u1ef1c"
    ],
    "name:war_x_preferred":[
        "Tieli"
    ],
    "name:zho_x_preferred":[
        "\u94c1\u674e"
    ],
    "name:zho_x_variant":[
        "\u94c1\u529b\u5e02"
    ],
    "wof:name":"Tieli",
    "wof:placetype":"locality"
},
  "geometry": {"coordinates":[113.84868,34.45012],"type":"Point"}
}