{
  "type": "Feature",
  "properties": {
    "gn:admin1_code":"18",
    "gn:asciiname":"Suozhu",
    "gn:country_code":"CN",
    "gn:dem":1358,
    "gn:feature_class":"P",
    "gn:feature_code":"PPL",
    "gn:name":"Suozhu",
    "gn:population":0,
    "gn:timezone":"Asia/Shanghai",
    "iso:country":"CN",
    "name:zho_x_preferred":[
        "\u68ad\u7af9"
    ],
    "wof:name":"Suozhu",
    "wof:placetype":"locality"
},
  "geometry": {"coordinates":[105.306,25.6335],"type":"Point"}
}