{
  "type": "Feature",
  "properties": {
    "gn:admin1_code":"26.0",
    "gn:asciiname":"Maijiagou",
    "gn:country_code":"CN",
    "gn:dem":730,
    "gn:feature_class":"P",
    "gn:feature_code":"PPL",
    "gn:name":"Maijiagou",
    "gn:population":0,
    "gn:timezone":"Asia/Shanghai",
    "iso:country":"CN",
    "name:zho_x_preferred":[
        "\u9ea6\u5bb6\u6c9f"
    ],
    "wof:name":"Maijiagou",
    "wof:placetype":"locality"
},
  "geometry": {"coordinates":[107.42771999999999,32.88808],"type":"Point"}
}