{
  "type": "Feature",
  "properties": {
    "gn:admin1_code":"24",
    "gn:asciiname":"Mishan",
    "gn:cc2":"CN",
    "gn:country_code":"CN",
    "gn:dem":842,
    "gn:feature_class":"P",
    "gn:feature_code":"PPL",
    "gn:name":"Mishan",
    "gn:population":0,
    "gn:timezone":"Asia/Shanghai",
    "iso:country":"CN",
    "name:deu_x_preferred":[
        "Mishan"
    ],
    "name:fra_x_preferred":[
        "Mishan"
    ],
    "name:ita_x_preferred":[
        "Mishan"
    ],
    "name:jpn_x_preferred":[
        "\u5bc6\u5c71\u5e02"
    ],
    "name:kik_x_preferred":[
        "Mishan"
    ],
    "name:kor_x_preferred":[
        "\ubbf8\uc0b0\uc2dc"
    ],
    "name:mlg_x_preferred":[
        "Mishan"
    ],
    "name:nor_x_preferred":[
        "Mishan"
    ],
    "name:pam_x_preferred":[
        "Mishan"
    ],
    "name:rus_x_preferred":[
        "\u041c\u0438\u0448\u0430\u043d\u044c"
    ],
    "name:swe_x_preferred":[
        "Mishan"
    ],
    "name:und_x_variant":[
        "Mi-shan-chen",
        "Mishan"
    ],
    "name:urd_x_preferred":[
        "\u0645\u06cc\u0634\u0627\u0646"
    ],
    "name:vie_x_preferred":[
        "M\u1eadt S\u01a1n"
    ],
    "name:war_x_preferred":[
        "Mishan"
    ],
    "name:zho_x_preferred":[
        "\u5bc6\u5c71\u5e02"
    ],
    "wof:name":"Mishan",
    "wof:placetype":"locality"
},
  "geometry": {"coordinates":[112.97333,35.76417],"type":"Point"}
}