{
  "type": "Feature",
  "properties": {
    "gn:admin1_code":"24",
    "gn:asciiname":"Mishan",
    "gn:cc2":"CN",
    "gn:country_code":"CN",
    "gn:dem":842,
    "gn:feature_class":"P",
    "gn:feature_code":"PPL",
    "gn:name":"Mishan",
    "gn:population":0,
    "gn:timezone":"Asia/Shanghai",
    "iso:country":"CN",
    "name:ara_x_preferred":[
        "\u0645\u064a\u0634\u0627\u0646"
    ],
    "name:deu_x_preferred":[
        "Mishan"
    ],
    "name:ell_x_preferred":[
        "\u039c\u03b9\u03c3\u03ac\u03bd"
    ],
    "name:fas_x_preferred":[
        "\u0645\u06cc\u0634\u0627\u0646"
    ],
    "name:fra_x_preferred":[
        "Mishan"
    ],
    "name:heb_x_preferred":[
        "\u05de\u05d9\u05e9\u05d0\u05df"
    ],
    "name:hin_x_preferred":[
        "\u092e\u093f\u0936\u093e\u0928"
    ],
    "name:hun_x_preferred":[
        "Mishan"
    ],
    "name:ind_x_preferred":[
        "Mishan"
    ],
    "name:ita_x_preferred":[
        "Mishan"
    ],
    "name:jpn_x_preferred":[
        "\u5bc6\u5c71\u5e02"
    ],
    "name:kik_x_preferred":[
        "Mishan"
    ],
    "name:kor_x_preferred":[
        "\ubbf8\uc0b0\uc2dc"
    ],
    "name:mlg_x_preferred":[
        "Mishan"
    ],
    "name:nor_x_preferred":[
        "Mishan"
    ],
    "name:pam_x_preferred":[
        "Mishan"
    ],
    "name:pol_x_preferred":[
        "Mishan"
    ],
    "name:por_x_preferred":[
        "Mishan"
    ],
    "name:rus_x_preferred":[
        "\u041c\u0438\u0448\u0430\u043d\u044c"
    ],
    "name:spa_x_preferred":[
        "Mishan"
    ],
    "name:swe_x_preferred":[
        "Mishan"
    ],
    "name:ukr_x_preferred":[
        "\u041c\u0456\u0448\u0430\u043d\u044c"
    ],
    "name:und_x_variant":[
        "Mi-shan-chen"
    ],
    "name:urd_x_preferred":[
        "\u0645\u06cc\u0634\u0627\u0646"
    ],
    "name:vie_x_preferred":[
        "M\u1eadt S\u01a1n"
    ],
    "name:war_x_preferred":[
        "Mishan"
    ],
    "name:zho_x_preferred":[
        "\u5bc6\u5c71\u5e02"
    ],
    "wof:name":"Mishan",
    "wof:placetype":"locality"
},
  "geometry": {"coordinates":[112.97333,35.76417],"type":"Point"}
}