{
  "type": "Feature",
  "properties": {
    "gn:admin1_code":"24",
    "gn:asciiname":"Mishan",
    "gn:cc2":"CN",
    "gn:country_code":"CN",
    "gn:dem":842,
    "gn:feature_class":"P",
    "gn:feature_code":"PPL",
    "gn:name":"Mishan",
    "gn:population":0,
    "gn:timezone":"Asia/Shanghai",
    "iso:country":"CN",
    "name:und_x_variant":[
        "Mi-shan-chen",
        "Mishan"
    ],
    "wof:name":"Mishan",
    "wof:placetype":"locality"
},
  "geometry": {"coordinates":[112.97333,35.76417],"type":"Point"}
}