{
  "type": "Feature",
  "properties": {
    "gn:admin1_code":"30.0",
    "gn:asciiname":"Gaozhen",
    "gn:country_code":"CN",
    "gn:dem":235,
    "gn:feature_class":"P",
    "gn:feature_code":"PPL",
    "gn:name":"Gaozhen",
    "gn:population":0,
    "gn:timezone":"Asia/Shanghai",
    "iso:country":"CN",
    "name:und_x_variant":[
        "\u9ad8\u5733"
    ],
    "name:zho_x_preferred":[
        "\u9ad8\u5733"
    ],
    "wof:name":"Gaozhen",
    "wof:placetype":"locality"
},
  "geometry": {"coordinates":[115.20271,23.47105],"type":"Point"}
}