{
  "type": "Feature",
  "properties": {
    "gn:admin1_code":"10",
    "gn:asciiname":"Sunmuying",
    "gn:country_code":"CN",
    "gn:dem":1406,
    "gn:feature_class":"P",
    "gn:feature_code":"PPL",
    "gn:name":"Sunmuying",
    "gn:population":0,
    "gn:timezone":"Asia/Shanghai",
    "iso:country":"CN",
    "name:zho_x_preferred":[
        "\u5b59\u7267\u8425"
    ],
    "wof:name":"Sunmuying",
    "wof:placetype":"locality"
},
  "geometry": {"coordinates":[114.91143,41.89474000000001],"type":"Point"}
}