{
  "type": "Feature",
  "properties": {
    "gn:admin1_code":"15.0",
    "gn:asciiname":"Datan",
    "gn:country_code":"CN",
    "gn:dem":2066,
    "gn:feature_class":"P",
    "gn:feature_code":"PPL",
    "gn:name":"Datan",
    "gn:population":0,
    "gn:timezone":"Asia/Shanghai",
    "iso:country":"CN",
    "name:zho_x_preferred":[
        "\u5927\u6ee9"
    ],
    "wof:name":"Datan",
    "wof:placetype":"locality"
},
  "geometry": {"coordinates":[103.65300000000001,35.3574],"type":"Point"}
}