{
  "type": "Feature",
  "properties": {
    "gn:admin1_code":"20.0",
    "gn:asciiname":"Huangyu Shuta",
    "gn:country_code":"CN",
    "gn:dem":1105,
    "gn:feature_class":"P",
    "gn:feature_code":"PPL",
    "gn:name":"Huangyu Shuta",
    "gn:population":0,
    "gn:timezone":"Asia/Shanghai",
    "iso:country":"CN",
    "name:und_x_variant":[
        "\u9ec4\u6986\u6811\u5854"
    ],
    "wof:name":"Huangyu Shuta",
    "wof:placetype":"locality"
},
  "geometry": {"coordinates":[111.41853999999999,39.83751],"type":"Point"}
}