{
  "type": "Feature",
  "properties": {
    "gn:admin1_code":"32.0",
    "gn:asciiname":"Samanipuka",
    "gn:country_code":"CN",
    "gn:dem":1738,
    "gn:feature_class":"P",
    "gn:feature_code":"PPL",
    "gn:name":"Samanipuka",
    "gn:population":0,
    "gn:timezone":"Asia/Shanghai",
    "iso:country":"CN",
    "name:zho_x_preferred":[
        "\u6492\u9a6c\u62df\u666e\u5580"
    ],
    "wof:name":"Samanipuka",
    "wof:placetype":"locality"
},
  "geometry": {"coordinates":[103.07599999999999,28.8919],"type":"Point"}
}