{
  "type": "Feature",
  "properties": {
    "gn:admin1_code":"11.0",
    "gn:asciiname":"Tielupo",
    "gn:country_code":"CN",
    "gn:dem":151,
    "gn:feature_class":"P",
    "gn:feature_code":"PPL",
    "gn:name":"Tielupo",
    "gn:population":0,
    "gn:timezone":"Asia/Shanghai",
    "iso:country":"CN",
    "name:zho_x_preferred":[
        "\u94c1\u8def\u5761"
    ],
    "wof:name":"Tielupo",
    "wof:placetype":"locality"
},
  "geometry": {"coordinates":[110.38916,28.43567],"type":"Point"}
}