{
  "type": "Feature",
  "properties": {
    "gn:admin1_code":"23.0",
    "gn:asciiname":"Yejiaqiao",
    "gn:country_code":"CN",
    "gn:dem":5,
    "gn:feature_class":"P",
    "gn:feature_code":"PPL",
    "gn:name":"Yejiaqiao",
    "gn:population":0,
    "gn:timezone":"Asia/Shanghai",
    "iso:country":"CN",
    "name:zho_x_preferred":[
        "Yejiaqiao"
    ],
    "name:zho_x_variant":[
        "\u53f6\u5bb6\u6865"
    ],
    "wof:name":"Yejiaqiao",
    "wof:placetype":"locality"
},
  "geometry": {"coordinates":[121.21414,31.30169],"type":"Point"}
}