{
  "type": "Feature",
  "properties": {
    "gn:admin1_code":"8.0",
    "gn:asciiname":"Beihecun",
    "gn:country_code":"CN",
    "gn:dem":135,
    "gn:feature_class":"P",
    "gn:feature_code":"PPL",
    "gn:name":"Beihecun",
    "gn:population":0,
    "gn:timezone":"Asia/Shanghai",
    "iso:country":"CN",
    "name:zho_x_preferred":[
        "\u5317\u6cb3\u6751"
    ],
    "wof:name":"Beihecun",
    "wof:placetype":"locality"
},
  "geometry": {"coordinates":[126.45032999999999,46.50495],"type":"Point"}
}