{
  "type": "Feature",
  "properties": {
    "gn:admin1_code":"29.0",
    "gn:asciiname":"Daganzhuang",
    "gn:country_code":"CN",
    "gn:dem":1710,
    "gn:feature_class":"P",
    "gn:feature_code":"PPL",
    "gn:name":"Daganzhuang",
    "gn:population":0,
    "gn:timezone":"Asia/Shanghai",
    "iso:country":"CN",
    "name:zho_x_preferred":[
        "\u5927\u7518\u5e84"
    ],
    "wof:name":"Daganzhuang",
    "wof:placetype":"locality"
},
  "geometry": {"coordinates":[100.27200000000001,25.2636],"type":"Point"}
}