{
  "type": "Feature",
  "properties": {
    "gn:admin1_code":"29.0",
    "gn:asciiname":"Lantangzhai",
    "gn:country_code":"CN",
    "gn:dem":1188,
    "gn:feature_class":"P",
    "gn:feature_code":"PPL",
    "gn:name":"Lantangzhai",
    "gn:population":0,
    "gn:timezone":"Asia/Shanghai",
    "iso:country":"CN",
    "name:zho_x_preferred":[
        "\u70c2\u6c64\u5be8"
    ],
    "wof:name":"Lantangzhai",
    "wof:placetype":"locality"
},
  "geometry": {"coordinates":[101.771,22.8257],"type":"Point"}
}