{
  "type": "Feature",
  "properties": {
    "gn:admin1_code":"10.0",
    "gn:asciiname":"Gezhuangzi",
    "gn:country_code":"CN",
    "gn:dem":231,
    "gn:feature_class":"P",
    "gn:feature_code":"PPL",
    "gn:name":"Gezhuangzi",
    "gn:population":0,
    "gn:timezone":"Asia/Shanghai",
    "iso:country":"CN",
    "name:zho_x_preferred":[
        "\u845b\u5e84\u5b50"
    ],
    "wof:name":"Gezhuangzi",
    "wof:placetype":"locality"
},
  "geometry": {"coordinates":[115.0729,39.00347],"type":"Point"}
}