{
  "type": "Feature",
  "properties": {
    "gn:admin1_code":"15.0",
    "gn:asciiname":"Silengkan",
    "gn:country_code":"CN",
    "gn:dem":1906,
    "gn:feature_class":"P",
    "gn:feature_code":"PPL",
    "gn:name":"Silengkan",
    "gn:population":0,
    "gn:timezone":"Asia/Shanghai",
    "iso:country":"CN",
    "name:und_x_variant":[
        "\u5bfa\u5844\u574e"
    ],
    "wof:name":"Silengkan",
    "wof:placetype":"locality"
},
  "geometry": {"coordinates":[105.10192000000001,33.40796],"type":"Point"}
}