{
  "type": "Feature",
  "properties": {
    "gn:admin1_code":"12",
    "gn:asciiname":"Cikou",
    "gn:country_code":"CN",
    "gn:dem":91,
    "gn:feature_class":"P",
    "gn:feature_code":"PPLA4",
    "gn:name":"Cikou",
    "gn:population":0,
    "gn:timezone":"Asia/Shanghai",
    "iso:country":"CN",
    "name:und_x_variant":[
        "Tz\u2019u-k\u2019ou",
        "Cikou",
        "\u6148\u53e3",
        "Cikou Xiang",
        "\u6148\u53e3\u4e61"
    ],
    "wof:name":"Cikou",
    "wof:placetype":"locality"
},
  "geometry": {"coordinates":[114.79476,29.68896],"type":"Point"}
}