{
  "type": "Feature",
  "properties": {
    "gn:admin1_code":"29.0",
    "gn:asciiname":"Nieyi",
    "gn:country_code":"CN",
    "gn:dem":1978,
    "gn:feature_class":"P",
    "gn:feature_code":"PPL",
    "gn:name":"Nieyi",
    "gn:population":0,
    "gn:timezone":"Asia/Shanghai",
    "iso:country":"CN",
    "name:zho_x_preferred":[
        "\u634f\u6021"
    ],
    "wof:name":"Nieyi",
    "wof:placetype":"locality"
},
  "geometry": {"coordinates":[104.11799999999999,25.1935],"type":"Point"}
}