{
  "type": "Feature",
  "properties": {
    "gn:admin1_code":"3.0",
    "gn:asciiname":"Wangjiashan",
    "gn:country_code":"CN",
    "gn:dem":69,
    "gn:feature_class":"P",
    "gn:feature_code":"PPL",
    "gn:name":"Wangjiashan",
    "gn:population":0,
    "gn:timezone":"Asia/Shanghai",
    "iso:country":"CN",
    "name:und_x_variant":[
        "\u6c6a\u5bb6\u5c71"
    ],
    "wof:name":"Wangjiashan",
    "wof:placetype":"locality"
},
  "geometry": {"coordinates":[114.99764,27.00194],"type":"Point"}
}