{
  "type": "Feature",
  "properties": {
    "gn:admin1_code":"11.0",
    "gn:asciiname":"Shangbaiyangping",
    "gn:country_code":"CN",
    "gn:dem":559,
    "gn:feature_class":"P",
    "gn:feature_code":"PPL",
    "gn:name":"Shangbaiyangping",
    "gn:population":0,
    "gn:timezone":"Asia/Shanghai",
    "iso:country":"CN",
    "name:zho_x_preferred":[
        "\u4e0a\u767d\u6d0b\u576a"
    ],
    "wof:name":"Shangbaiyangping",
    "wof:placetype":"locality"
},
  "geometry": {"coordinates":[110.68895999999999,26.53957],"type":"Point"}
}