{
  "type": "Feature",
  "properties": {
    "gn:admin1_code":"10.0",
    "gn:asciiname":"Lianggezhuang",
    "gn:country_code":"CN",
    "gn:dem":12,
    "gn:feature_class":"P",
    "gn:feature_code":"PPL",
    "gn:name":"Lianggezhuang",
    "gn:population":0,
    "gn:timezone":"Asia/Shanghai",
    "iso:country":"CN",
    "name:zho_x_preferred":[
        "\u6881\u5404\u5e84"
    ],
    "wof:name":"Lianggezhuang",
    "wof:placetype":"locality"
},
  "geometry": {"coordinates":[116.35299999999999,38.3941],"type":"Point"}
}