{
  "type": "Feature",
  "properties": {
    "gn:admin1_code":"29.0",
    "gn:asciiname":"Lengshan",
    "gn:country_code":"CN",
    "gn:dem":2565,
    "gn:feature_class":"P",
    "gn:feature_code":"PPL",
    "gn:name":"Lengshan",
    "gn:population":0,
    "gn:timezone":"Asia/Shanghai",
    "iso:country":"CN",
    "name:zho_x_preferred":[
        "\u51b7\u5c71"
    ],
    "wof:name":"Lengshan",
    "wof:placetype":"locality"
},
  "geometry": {"coordinates":[99.28279999999999,26.3169],"type":"Point"}
}