{
  "type": "Feature",
  "properties": {
    "gn:admin1_code":"7",
    "gn:asciiname":"Nanpu",
    "gn:country_code":"CN",
    "gn:dem":20,
    "gn:feature_class":"P",
    "gn:feature_code":"PPL",
    "gn:name":"Nanpu",
    "gn:population":0,
    "gn:timezone":"Asia/Shanghai",
    "iso:country":"CN",
    "name:zho_x_preferred":[
        "\u5357\u57d4"
    ],
    "wof:name":"Nanpu",
    "wof:placetype":"locality"
},
  "geometry": {"coordinates":[118.89991000000001,25.19767],"type":"Point"}
}