{
  "type": "Feature",
  "properties": {
    "gn:admin1_code":"1.0",
    "gn:asciiname":"Qifengcun",
    "gn:country_code":"CN",
    "gn:dem":626,
    "gn:feature_class":"P",
    "gn:feature_code":"PPL",
    "gn:name":"Qifengcun",
    "gn:population":0,
    "gn:timezone":"Asia/Shanghai",
    "iso:country":"CN",
    "name:zho_x_preferred":[
        "\u5947\u5cf0\u6751"
    ],
    "wof:name":"Qifengcun",
    "wof:placetype":"locality"
},
  "geometry": {"coordinates":[117.43847,30.08795],"type":"Point"}
}