{
  "type": "Feature",
  "properties": {
    "gn:admin1_code":"24.0",
    "gn:asciiname":"Mafulang",
    "gn:country_code":"CN",
    "gn:dem":1104,
    "gn:feature_class":"P",
    "gn:feature_code":"PPL",
    "gn:name":"Mafulang",
    "gn:population":0,
    "gn:timezone":"Asia/Shanghai",
    "iso:country":"CN",
    "name:zho_x_preferred":[
        "\u9a6c\u798f\u90ce"
    ],
    "wof:name":"Mafulang",
    "wof:placetype":"locality"
},
  "geometry": {"coordinates":[111.0471,38.40732],"type":"Point"}
}