{
  "type": "Feature",
  "properties": {
    "gn:admin1_code":"09",
    "gn:asciiname":"Zhaobu",
    "gn:cc2":"CN",
    "gn:country_code":"CN",
    "gn:dem":105,
    "gn:feature_class":"P",
    "gn:feature_code":"PPL",
    "gn:name":"Zhaobu",
    "gn:population":0,
    "gn:timezone":"Asia/Shanghai",
    "iso:country":"CN",
    "name:und_x_variant":[
        "Tung-sung",
        "Zhaobu"
    ],
    "wof:name":"Zhaobu",
    "wof:placetype":"locality"
},
  "geometry": {"coordinates":[113.17972,34.95222],"type":"Point"}
}