{
  "type": "Feature",
  "properties": {
    "gn:admin1_code":"19.0",
    "gn:asciiname":"Shadigou",
    "gn:country_code":"CN",
    "gn:dem":123,
    "gn:feature_class":"P",
    "gn:feature_code":"PPL",
    "gn:name":"Shadigou",
    "gn:population":0,
    "gn:timezone":"Asia/Shanghai",
    "iso:country":"CN",
    "name:zho_x_preferred":[
        "\u6c99\u5730\u6c9f"
    ],
    "wof:name":"Shadigou",
    "wof:placetype":"locality"
},
  "geometry": {"coordinates":[123.71299999999999,41.7043],"type":"Point"}
}