{
  "type": "Feature",
  "properties": {
    "gn:admin1_code":"14.0",
    "gn:asciiname":"Langnaicun",
    "gn:country_code":"CN",
    "gn:dem":3086,
    "gn:feature_class":"P",
    "gn:feature_code":"PPL",
    "gn:name":"Langnaicun",
    "gn:population":0,
    "gn:timezone":"Asia/Urumqi",
    "iso:country":"CN",
    "name:zho_x_preferred":[
        "\u6717\u4e43\u6751"
    ],
    "wof:name":"Langnaicun",
    "wof:placetype":"locality"
},
  "geometry": {"coordinates":[94.64108,29.51135],"type":"Point"}
}