{
  "type": "Feature",
  "properties": {
    "gn:admin1_code":"7.0",
    "gn:asciiname":"Houchang",
    "gn:country_code":"CN",
    "gn:dem":882,
    "gn:feature_class":"P",
    "gn:feature_code":"PPL",
    "gn:name":"Houchang",
    "gn:population":0,
    "gn:timezone":"Asia/Shanghai",
    "iso:country":"CN",
    "name:und_x_variant":[
        "\u540e\u573a"
    ],
    "name:zho_x_preferred":[
        "\u540e\u573a"
    ],
    "wof:name":"Houchang",
    "wof:placetype":"locality"
},
  "geometry": {"coordinates":[118.49499,26.02847],"type":"Point"}
}