{
  "type": "Feature",
  "properties": {
    "gn:admin1_code":"30.0",
    "gn:asciiname":"Liangwu",
    "gn:country_code":"CN",
    "gn:dem":225,
    "gn:feature_class":"P",
    "gn:feature_code":"PPL",
    "gn:name":"Liangwu",
    "gn:population":0,
    "gn:timezone":"Asia/Shanghai",
    "iso:country":"CN",
    "name:zho_x_preferred":[
        "\u6881\u5c4b"
    ],
    "wof:name":"Liangwu",
    "wof:placetype":"locality"
},
  "geometry": {"coordinates":[112.20191,24.07997],"type":"Point"}
}