{
  "type": "Feature",
  "properties": {
    "gn:admin1_code":"8.0",
    "gn:asciiname":"Ershisan Gongli",
    "gn:country_code":"CN",
    "gn:dem":371,
    "gn:feature_class":"P",
    "gn:feature_code":"PPL",
    "gn:name":"Ershisan Gongli",
    "gn:population":0,
    "gn:timezone":"Asia/Shanghai",
    "iso:country":"CN",
    "name:zho_x_preferred":[
        "\u4e8c\u5341\u4e09\u516c\u91cc"
    ],
    "wof:name":"Ershisan Gongli",
    "wof:placetype":"locality"
},
  "geometry": {"coordinates":[129.01728,47.22887],"type":"Point"}
}