{
  "type": "Feature",
  "properties": {
    "gn:admin1_code":"24.0",
    "gn:asciiname":"Dachangjiahui",
    "gn:country_code":"CN",
    "gn:dem":1083,
    "gn:feature_class":"P",
    "gn:feature_code":"PPL",
    "gn:name":"Dachangjiahui",
    "gn:population":0,
    "gn:timezone":"Asia/Shanghai",
    "iso:country":"CN",
    "name:zho_x_preferred":[
        "\u5927\u5e38\u5bb6\u4f1a"
    ],
    "wof:name":"Dachangjiahui",
    "wof:placetype":"locality"
},
  "geometry": {"coordinates":[113.03375,37.08821],"type":"Point"}
}