{
  "type": "Feature",
  "properties": {
    "gn:admin1_code":"30",
    "gn:asciiname":"Dachecun",
    "gn:country_code":"CN",
    "gn:dem":75,
    "gn:feature_class":"P",
    "gn:feature_code":"PPL",
    "gn:name":"Dachecun",
    "gn:population":0,
    "gn:timezone":"Asia/Urumqi",
    "iso:country":"CN",
    "name:zho_x_preferred":[
        "\u5927\u8f66\u6751"
    ],
    "wof:name":"Dachecun",
    "wof:placetype":"locality"
},
  "geometry": {"coordinates":[110.49029,22.08261],"type":"Point"}
}