{
  "type": "Feature",
  "properties": {
    "gn:admin1_code":"11",
    "gn:asciiname":"Liujiawei",
    "gn:country_code":"CN",
    "gn:dem":343,
    "gn:feature_class":"P",
    "gn:feature_code":"PPL",
    "gn:name":"Liujiawei",
    "gn:population":0,
    "gn:timezone":"Asia/Shanghai",
    "iso:country":"CN",
    "name:und_x_variant":[
        "\u7559\u4f73\u4f4d",
        "Liujiawei"
    ],
    "wof:name":"Liujiawei",
    "wof:placetype":"locality"
},
  "geometry": {"coordinates":[112.23056,25.62111],"type":"Point"}
}