{
  "type": "Feature",
  "properties": {
    "gn:admin1_code":"18",
    "gn:asciiname":"Sanchongyan",
    "gn:cc2":"CN",
    "gn:country_code":"CN",
    "gn:dem":1292,
    "gn:feature_class":"P",
    "gn:feature_code":"PPL",
    "gn:name":"Sanchongyan",
    "gn:population":0,
    "gn:timezone":"Asia/Shanghai",
    "iso:country":"CN",
    "name:und_x_variant":[
        "San-ch\u2019ung-yen",
        "Sanchongyan"
    ],
    "wof:name":"Sanchongyan",
    "wof:placetype":"locality"
},
  "geometry": {"coordinates":[106.16667,27.28333],"type":"Point"}
}