{
  "type": "Feature",
  "properties": {
    "gn:admin1_code":"16.0",
    "gn:asciiname":"Naqi",
    "gn:country_code":"CN",
    "gn:dem":113,
    "gn:feature_class":"P",
    "gn:feature_code":"PPL",
    "gn:name":"Naqi",
    "gn:population":0,
    "gn:timezone":"Asia/Shanghai",
    "iso:country":"CN",
    "name:zho_x_preferred":[
        "\u90a3\u9f50"
    ],
    "wof:name":"Naqi",
    "wof:placetype":"locality"
},
  "geometry": {"coordinates":[108.42400000000001,22.59800000000001],"type":"Point"}
}