{
  "type": "Feature",
  "properties": {
    "gn:admin1_code":"9",
    "gn:asciiname":"Dongbaiqiu",
    "gn:country_code":"CN",
    "gn:dem":58,
    "gn:feature_class":"P",
    "gn:feature_code":"PPL",
    "gn:name":"Dongbaiqiu",
    "gn:population":0,
    "gn:timezone":"Asia/Shanghai",
    "iso:country":"CN",
    "name:zho_x_preferred":[
        "\u4e1c\u767d\u4e18"
    ],
    "wof:name":"Dongbaiqiu",
    "wof:placetype":"locality"
},
  "geometry": {"coordinates":[115.104,35.4834],"type":"Point"}
}