{
  "type": "Feature",
  "properties": {
    "gn:admin1_code":"2.0",
    "gn:asciiname":"Huangshui",
    "gn:country_code":"CN",
    "gn:dem":975,
    "gn:feature_class":"P",
    "gn:feature_code":"PPL",
    "gn:name":"Huangshui",
    "gn:population":0,
    "gn:timezone":"Asia/Shanghai",
    "iso:country":"CN",
    "name:zho_x_preferred":[
        "\u9ec4\u6c34"
    ],
    "wof:name":"Huangshui",
    "wof:placetype":"locality"
},
  "geometry": {"coordinates":[119.2932,27.7622],"type":"Point"}
}