{
  "type": "Feature",
  "properties": {
    "gn:admin1_code":"26.0",
    "gn:asciiname":"Changlinzhen",
    "gn:country_code":"CN",
    "gn:dem":524,
    "gn:feature_class":"P",
    "gn:feature_code":"PPL",
    "gn:name":"Changlinzhen",
    "gn:population":0,
    "gn:timezone":"Asia/Shanghai",
    "iso:country":"CN",
    "name:und_x_variant":[
        "\u957f\u6797\u9547"
    ],
    "wof:name":"Changlinzhen",
    "wof:placetype":"locality"
},
  "geometry": {"coordinates":[106.91245000000001,33.14147],"type":"Point"}
}