{
  "type": "Feature",
  "properties": {
    "gn:admin1_code":"1.0",
    "gn:asciiname":"Bailoucun",
    "gn:country_code":"CN",
    "gn:dem":72,
    "gn:feature_class":"P",
    "gn:feature_code":"PPL",
    "gn:name":"Bailoucun",
    "gn:population":0,
    "gn:timezone":"Asia/Shanghai",
    "iso:country":"CN",
    "name:zho_x_preferred":[
        "\u767d\u697c\u6751"
    ],
    "wof:name":"Bailoucun",
    "wof:placetype":"locality"
},
  "geometry": {"coordinates":[115.97132999999999,31.9656],"type":"Point"}
}