{
  "type": "Feature",
  "properties": {
    "gn:admin1_code":"29.0",
    "gn:asciiname":"Xiaowangbi",
    "gn:country_code":"CN",
    "gn:dem":1160,
    "gn:feature_class":"P",
    "gn:feature_code":"PPL",
    "gn:name":"Xiaowangbi",
    "gn:population":0,
    "gn:timezone":"Asia/Shanghai",
    "iso:country":"CN",
    "name:zho_x_preferred":[
        "\u5c0f\u738b\u5f3c"
    ],
    "wof:name":"Xiaowangbi",
    "wof:placetype":"locality"
},
  "geometry": {"coordinates":[103.367,24.0109],"type":"Point"}
}