{
  "type": "Feature",
  "properties": {
    "gn:admin1_code":"16.0",
    "gn:asciiname":"Aishan",
    "gn:country_code":"CN",
    "gn:dem":256,
    "gn:feature_class":"P",
    "gn:feature_code":"PPL",
    "gn:name":"Aishan",
    "gn:population":0,
    "gn:timezone":"Asia/Shanghai",
    "iso:country":"CN",
    "name:zho_x_preferred":[
        "\u77ee\u5c71"
    ],
    "wof:name":"Aishan",
    "wof:placetype":"locality"
},
  "geometry": {"coordinates":[109.65000000000001,24.9358],"type":"Point"}
}