{
  "type": "Feature",
  "properties": {
    "gn:admin1_code":"32.0",
    "gn:asciiname":"Donggong",
    "gn:country_code":"CN",
    "gn:dem":2927,
    "gn:feature_class":"P",
    "gn:feature_code":"PPL",
    "gn:name":"Donggong",
    "gn:population":0,
    "gn:timezone":"Asia/Shanghai",
    "iso:country":"CN",
    "name:zho_x_preferred":[
        "\u4e1c\u5bab"
    ],
    "wof:name":"Donggong",
    "wof:placetype":"locality"
},
  "geometry": {"coordinates":[99.8035,28.9734],"type":"Point"}
}