{
  "type": "Feature",
  "properties": {
    "gn:admin1_code":"19.0",
    "gn:asciiname":"Xiaozhaojiagou",
    "gn:country_code":"CN",
    "gn:dem":456,
    "gn:feature_class":"P",
    "gn:feature_code":"PPL",
    "gn:name":"Xiaozhaojiagou",
    "gn:population":0,
    "gn:timezone":"Asia/Shanghai",
    "iso:country":"CN",
    "name:zho_x_preferred":[
        "\u5c0f\u8d75\u5bb6\u6c9f"
    ],
    "wof:name":"Xiaozhaojiagou",
    "wof:placetype":"locality"
},
  "geometry": {"coordinates":[119.44611999999999,40.94479000000001],"type":"Point"}
}