{
  "type": "Feature",
  "properties": {
    "gn:admin1_code":"11.0",
    "gn:asciiname":"Songshansi",
    "gn:country_code":"CN",
    "gn:dem":80,
    "gn:feature_class":"P",
    "gn:feature_code":"PPL",
    "gn:name":"Songshansi",
    "gn:population":0,
    "gn:timezone":"Asia/Shanghai",
    "iso:country":"CN",
    "name:zho_x_preferred":[
        "\u5d69\u5c71\u5bfa"
    ],
    "wof:name":"Songshansi",
    "wof:placetype":"locality"
},
  "geometry": {"coordinates":[113.13695,27.9875],"type":"Point"}
}