{
  "type": "Feature",
  "properties": {
    "gn:admin1_code":"32.0",
    "gn:asciiname":"Zitongguan",
    "gn:country_code":"CN",
    "gn:dem":588,
    "gn:feature_class":"P",
    "gn:feature_code":"PPL",
    "gn:name":"Zitongguan",
    "gn:population":0,
    "gn:timezone":"Asia/Shanghai",
    "iso:country":"CN",
    "name:zho_x_preferred":[
        "\u6893\u6f7c\u7f50"
    ],
    "wof:name":"Zitongguan",
    "wof:placetype":"locality"
},
  "geometry": {"coordinates":[103.23551,29.69871],"type":"Point"}
}