{
  "type": "Feature",
  "properties": {
    "gn:admin1_code":"15.0",
    "gn:asciiname":"Bange Yangquan",
    "gn:country_code":"CN",
    "gn:dem":2153,
    "gn:feature_class":"P",
    "gn:feature_code":"PPLF",
    "gn:name":"Bange Yangquan",
    "gn:population":0,
    "gn:timezone":"Asia/Shanghai",
    "iso:country":"CN",
    "name:zho_x_preferred":[
        "\u534a\u4e2a\u7f8a\u5708"
    ],
    "wof:name":"Bange Yangquan",
    "wof:placetype":"locality"
},
  "geometry": {"coordinates":[101.197,38.8159],"type":"Point"}
}