{
  "type": "Feature",
  "properties": {
    "gn:admin1_code":"19.0",
    "gn:asciiname":"Yinzhangzi",
    "gn:country_code":"CN",
    "gn:dem":374,
    "gn:feature_class":"P",
    "gn:feature_code":"PPL",
    "gn:name":"Yinzhangzi",
    "gn:population":0,
    "gn:timezone":"Asia/Shanghai",
    "iso:country":"CN",
    "name:zho_x_preferred":[
        "\u5c39\u6756\u5b50"
    ],
    "wof:name":"Yinzhangzi",
    "wof:placetype":"locality"
},
  "geometry": {"coordinates":[119.532,41.0666],"type":"Point"}
}