{
  "type": "Feature",
  "properties": {
    "gn:admin1_code":"08",
    "gn:asciiname":"Dahudian",
    "gn:country_code":"CN",
    "gn:dem":153,
    "gn:feature_class":"P",
    "gn:feature_code":"PPLA4",
    "gn:name":"Dahudian",
    "gn:population":0,
    "gn:timezone":"Asia/Shanghai",
    "iso:country":"CN",
    "name:und_x_variant":[
        "Dahudian Zhen"
    ],
    "name:zho_x_preferred":[
        "\u8fbe\u547c\u5e97"
    ],
    "name:zho_x_variant":[
        "\u8fbe\u547c\u5e97\u9547"
    ],
    "wof:name":"Dahudian",
    "wof:placetype":"locality"
},
  "geometry": {"coordinates":[123.81009,47.52932],"type":"Point"}
}