{
  "type": "Feature",
  "properties": {
    "gn:admin1_code":"11.0",
    "gn:asciiname":"Loutixia",
    "gn:country_code":"CN",
    "gn:dem":230,
    "gn:feature_class":"P",
    "gn:feature_code":"PPL",
    "gn:name":"Loutixia",
    "gn:population":0,
    "gn:timezone":"Asia/Shanghai",
    "iso:country":"CN",
    "name:zho_x_preferred":[
        "\u697c\u68af\u4e0b"
    ],
    "wof:name":"Loutixia",
    "wof:placetype":"locality"
},
  "geometry": {"coordinates":[113.17412,26.50817],"type":"Point"}
}