{
  "type": "Feature",
  "properties": {
    "gn:admin1_code":"11.0",
    "gn:asciiname":"Ganxiyu",
    "gn:country_code":"CN",
    "gn:dem":487,
    "gn:feature_class":"P",
    "gn:feature_code":"PPL",
    "gn:name":"Ganxiyu",
    "gn:population":0,
    "gn:timezone":"Asia/Shanghai",
    "iso:country":"CN",
    "name:zho_x_preferred":[
        "\u7518\u6eaa\u5cea"
    ],
    "wof:name":"Ganxiyu",
    "wof:placetype":"locality"
},
  "geometry": {"coordinates":[110.37639,29.31021],"type":"Point"}
}