{
  "type": "Feature",
  "properties": {
    "gn:admin1_code":"2.0",
    "gn:asciiname":"Shekou",
    "gn:country_code":"CN",
    "gn:dem":728,
    "gn:feature_class":"P",
    "gn:feature_code":"PPL",
    "gn:name":"Shekou",
    "gn:population":0,
    "gn:timezone":"Asia/Shanghai",
    "iso:country":"CN",
    "name:fra_x_preferred":[
        "Shekou"
    ],
    "name:nor_x_preferred":[
        "Shekou"
    ],
    "name:swe_x_preferred":[
        "Shekou"
    ],
    "name:zho_x_preferred":[
        "\u793e\u53e3"
    ],
    "name:zho_x_variant":[
        "\u86c7\u53e3\u5de5\u4e1a\u533a"
    ],
    "wof:name":"Shekou",
    "wof:placetype":"locality"
},
  "geometry": {"coordinates":[118.81386000000001,27.98562],"type":"Point"}
}