{
  "type": "Feature",
  "properties": {
    "gn:admin1_code":"7.0",
    "gn:asciiname":"Meifeng",
    "gn:country_code":"CN",
    "gn:dem":164,
    "gn:feature_class":"P",
    "gn:feature_code":"PPL",
    "gn:name":"Meifeng",
    "gn:population":0,
    "gn:timezone":"Asia/Shanghai",
    "iso:country":"CN",
    "name:zho_x_preferred":[
        "\u6885\u5cf0"
    ],
    "wof:name":"Meifeng",
    "wof:placetype":"locality"
},
  "geometry": {"coordinates":[118.47893999999999,26.28624000000001],"type":"Point"}
}