{
  "type": "Feature",
  "properties": {
    "gn:admin1_code":"15",
    "gn:asciiname":"Maima",
    "gn:country_code":"CN",
    "gn:dem":3495,
    "gn:feature_class":"P",
    "gn:feature_code":"PPLA4",
    "gn:name":"Maima",
    "gn:population":0,
    "gn:timezone":"Asia/Shanghai",
    "iso:country":"CN",
    "name:est_x_preferred":[
        "Maima"
    ],
    "name:hye_x_preferred":[
        "\u0544\u0561\u056b\u0574\u0561"
    ],
    "name:mon_x_preferred":[
        "Maima"
    ],
    "name:pol_x_preferred":[
        "Maima"
    ],
    "name:spa_x_preferred":[
        "Maima"
    ],
    "name:und_x_variant":[
        "Manrima",
        "Manrima Xiang"
    ],
    "name:vol_x_preferred":[
        "Maima"
    ],
    "name:zho_x_preferred":[
        "\u66fc\u65e5\u739b"
    ],
    "name:zho_x_variant":[
        "\u66fc\u65e5\u739b\u4e61"
    ],
    "wof:name":"Maima",
    "wof:placetype":"locality"
},
  "geometry": {"coordinates":[102.06874999999999,33.64086],"type":"Point"}
}