{
  "type": "Feature",
  "properties": {
    "gn:admin1_code":"04",
    "gn:asciiname":"Luxiang",
    "gn:country_code":"CN",
    "gn:dem":6,
    "gn:feature_class":"P",
    "gn:feature_code":"PPL",
    "gn:name":"Luxiang",
    "gn:population":0,
    "gn:timezone":"Asia/Shanghai",
    "iso:country":"CN",
    "name:und_x_variant":[
        "Lu-hsiang",
        "Luxiang"
    ],
    "name:zho_x_preferred":[
        "\u9646\u5df7"
    ],
    "wof:name":"Luxiang",
    "wof:placetype":"locality"
},
  "geometry": {"coordinates":[120.75208000000001,31.53009],"type":"Point"}
}