{
  "type": "Feature",
  "properties": {
    "gn:admin1_code":"32",
    "gn:asciiname":"Molo",
    "gn:country_code":"CN",
    "gn:dem":3344,
    "gn:feature_class":"P",
    "gn:feature_code":"PPL",
    "gn:name":"Molo",
    "gn:population":0,
    "gn:timezone":"Asia/Shanghai",
    "iso:country":"CN",
    "wof:name":"Molo",
    "wof:placetype":"locality"
},
  "geometry": {"coordinates":[101.98333,30.83333],"type":"Point"}
}