{
  "type": "Feature",
  "properties": {
    "gn:admin1_code":"32.0",
    "gn:asciiname":"Fuguiwan",
    "gn:country_code":"CN",
    "gn:dem":373,
    "gn:feature_class":"P",
    "gn:feature_code":"PPL",
    "gn:name":"Fuguiwan",
    "gn:population":0,
    "gn:timezone":"Asia/Shanghai",
    "iso:country":"CN",
    "name:zho_x_preferred":[
        "\u5bcc\u8d35\u6e7e"
    ],
    "wof:name":"Fuguiwan",
    "wof:placetype":"locality"
},
  "geometry": {"coordinates":[104.726,29.992],"type":"Point"}
}