{
  "type": "Feature",
  "properties": {
    "gn:admin1_code":"10",
    "gn:asciiname":"Mihong Yingzi",
    "gn:country_code":"CN",
    "gn:dem":1395,
    "gn:feature_class":"P",
    "gn:feature_code":"PPL",
    "gn:name":"Mihong Yingzi",
    "gn:population":0,
    "gn:timezone":"Asia/Shanghai",
    "iso:country":"CN",
    "name:zho_x_preferred":[
        "\u7c73\u6d2a\u8425\u5b50"
    ],
    "wof:name":"Mihong Yingzi",
    "wof:placetype":"locality"
},
  "geometry": {"coordinates":[115.3858,41.61053],"type":"Point"}
}