{
  "type": "Feature",
  "properties": {
    "gn:admin1_code":"18.0",
    "gn:asciiname":"Tianbajiao",
    "gn:country_code":"CN",
    "gn:dem":429,
    "gn:feature_class":"P",
    "gn:feature_code":"PPL",
    "gn:name":"Tianbajiao",
    "gn:population":0,
    "gn:timezone":"Asia/Shanghai",
    "iso:country":"CN",
    "name:zho_x_preferred":[
        "\u7530\u575d\u811a"
    ],
    "wof:name":"Tianbajiao",
    "wof:placetype":"locality"
},
  "geometry": {"coordinates":[109.247,26.4033],"type":"Point"}
}