{
  "type": "Feature",
  "properties": {
    "gn:admin1_code":"24",
    "gn:asciiname":"Jiehekou",
    "gn:cc2":"CN",
    "gn:country_code":"CN",
    "gn:dem":1294,
    "gn:feature_class":"P",
    "gn:feature_code":"PPL",
    "gn:name":"Jiehekou",
    "gn:population":0,
    "gn:timezone":"Asia/Shanghai",
    "iso:country":"CN",
    "name:und_x_variant":[
        "Chieh-ho-k\u2019ou",
        "Jiehekou"
    ],
    "wof:name":"Jiehekou",
    "wof:placetype":"locality"
},
  "geometry": {"coordinates":[111.38916999999999,38.52111],"type":"Point"}
}