{
  "type": "Feature",
  "properties": {
    "gn:admin1_code":"19.0",
    "gn:asciiname":"Dongtaizicun",
    "gn:country_code":"CN",
    "gn:dem":271,
    "gn:feature_class":"P",
    "gn:feature_code":"PPL",
    "gn:name":"Dongtaizicun",
    "gn:population":0,
    "gn:timezone":"Asia/Shanghai",
    "iso:country":"CN",
    "name:zho_x_preferred":[
        "\u4e1c\u53f0\u5b50\u6751"
    ],
    "wof:name":"Dongtaizicun",
    "wof:placetype":"locality"
},
  "geometry": {"coordinates":[119.86566000000001,41.17661],"type":"Point"}
}