{
  "type": "Feature",
  "properties": {
    "gn:admin1_code":"30",
    "gn:asciiname":"Tanhe",
    "gn:country_code":"CN",
    "gn:dem":21,
    "gn:feature_class":"P",
    "gn:feature_code":"PPL",
    "gn:name":"Tanhe",
    "gn:population":0,
    "gn:timezone":"Asia/Urumqi",
    "iso:country":"CN",
    "name:zho_x_preferred":[
        "\u6f6d\u6cb3"
    ],
    "wof:name":"Tanhe",
    "wof:placetype":"locality"
},
  "geometry": {"coordinates":[110.32598,21.36282000000001],"type":"Point"}
}