{
  "type": "Feature",
  "properties": {
    "gn:admin1_code":"9.0",
    "gn:asciiname":"Xiazhaochong",
    "gn:country_code":"CN",
    "gn:dem":103,
    "gn:feature_class":"P",
    "gn:feature_code":"PPL",
    "gn:name":"Xiazhaochong",
    "gn:population":0,
    "gn:timezone":"Asia/Shanghai",
    "iso:country":"CN",
    "name:zho_x_preferred":[
        "\u4e0b\u8d75\u51b2"
    ],
    "wof:name":"Xiazhaochong",
    "wof:placetype":"locality"
},
  "geometry": {"coordinates":[115.14539000000001,31.73825],"type":"Point"}
}