{
  "type": "Feature",
  "properties": {
    "gn:admin1_code":"26.0",
    "gn:asciiname":"Xiwangzhuangcun",
    "gn:country_code":"CN",
    "gn:dem":1100,
    "gn:feature_class":"P",
    "gn:feature_code":"PPL",
    "gn:name":"Xiwangzhuangcun",
    "gn:population":0,
    "gn:timezone":"Asia/Shanghai",
    "iso:country":"CN",
    "name:zho_x_preferred":[
        "\u897f\u738b\u5e84\u6751"
    ],
    "wof:name":"Xiwangzhuangcun",
    "wof:placetype":"locality"
},
  "geometry": {"coordinates":[108.38443999999998,34.71631],"type":"Point"}
}