{
  "type": "Feature",
  "properties": {
    "gn:admin1_code":"19.0",
    "gn:asciiname":"Aijia Donggou",
    "gn:country_code":"CN",
    "gn:dem":116,
    "gn:feature_class":"P",
    "gn:feature_code":"PPL",
    "gn:name":"Aijia Donggou",
    "gn:population":0,
    "gn:timezone":"Asia/Shanghai",
    "iso:country":"CN",
    "name:und_x_variant":[
        "\u827e\u5bb6\u4e1c\u6c9f"
    ],
    "wof:name":"Aijia Donggou",
    "wof:placetype":"locality"
},
  "geometry": {"coordinates":[123.9235,40.35932],"type":"Point"}
}