{
  "type": "Feature",
  "properties": {
    "gn:admin1_code":"16.0",
    "gn:asciiname":"Zhu'e",
    "gn:country_code":"CN",
    "gn:dem":93,
    "gn:feature_class":"P",
    "gn:feature_code":"PPL",
    "gn:name":"Zhu\u2019e",
    "gn:population":0,
    "gn:timezone":"Asia/Shanghai",
    "iso:country":"CN",
    "name:ceb_x_preferred":[
        "Zhu'a"
    ],
    "name:swe_x_preferred":[
        "Zhu'a"
    ],
    "name:und_x_variant":[
        "Zhu\u2019e"
    ],
    "name:zho_x_preferred":[
        "\u7af9\u9e45"
    ],
    "name:zho_x_variant":[
        "\u795d\u963f\u9547"
    ],
    "wof:name":"Zhu'e",
    "wof:placetype":"locality"
},
  "geometry": {"coordinates":[109.371,24.2821],"type":"Point"}
}