{
  "type": "Feature",
  "properties": {
    "gn:admin1_code":"4.0",
    "gn:asciiname":"Yuxiang",
    "gn:country_code":"CN",
    "gn:dem":7,
    "gn:feature_class":"P",
    "gn:feature_code":"PPL",
    "gn:name":"Yuxiang",
    "gn:population":0,
    "gn:timezone":"Asia/Shanghai",
    "iso:country":"CN",
    "name:fra_x_preferred":[
        "Yuxiang"
    ],
    "name:gle_x_preferred":[
        "Yuxiang"
    ],
    "name:ind_x_preferred":[
        "Yuxiang"
    ],
    "name:ita_x_preferred":[
        "Yuxiang"
    ],
    "name:msa_x_preferred":[
        "Yuxiang"
    ],
    "name:nor_x_preferred":[
        "Yuxiang"
    ],
    "name:por_x_preferred":[
        "Yuxiang"
    ],
    "name:sah_x_preferred":[
        "\u042e\u0439\u0441\u044f\u043d\u044c"
    ],
    "name:spa_x_preferred":[
        "Yuxiang"
    ],
    "name:swe_x_preferred":[
        "Yuxiang"
    ],
    "wof:name":"Yuxiang",
    "wof:placetype":"locality"
},
  "geometry": {"coordinates":[120.07946,31.71543],"type":"Point"}
}