{
  "type": "Feature",
  "properties": {
    "gn:admin1_code":"26.0",
    "gn:asciiname":"Gaojiapingcun",
    "gn:country_code":"CN",
    "gn:dem":1072,
    "gn:feature_class":"P",
    "gn:feature_code":"PPL",
    "gn:name":"Gaojiapingcun",
    "gn:population":0,
    "gn:timezone":"Asia/Shanghai",
    "iso:country":"CN",
    "name:zho_x_preferred":[
        "\u9ad8\u5bb6\u576a\u6751"
    ],
    "wof:name":"Gaojiapingcun",
    "wof:placetype":"locality"
},
  "geometry": {"coordinates":[109.84066,36.84311],"type":"Point"}
}