{
  "type": "Feature",
  "properties": {
    "gn:admin1_code":"30.0",
    "gn:asciiname":"Mudongkeng",
    "gn:country_code":"CN",
    "gn:dem":200,
    "gn:feature_class":"P",
    "gn:feature_code":"PPL",
    "gn:name":"Mudongkeng",
    "gn:population":0,
    "gn:timezone":"Asia/Shanghai",
    "iso:country":"CN",
    "name:zho_x_preferred":[
        "\u6728\u578c\u5751"
    ],
    "wof:name":"Mudongkeng",
    "wof:placetype":"locality"
},
  "geometry": {"coordinates":[111.88851,22.57876],"type":"Point"}
}