{
  "type": "Feature",
  "properties": {
    "gn:admin1_code":"18",
    "gn:asciiname":"Hetaozhai",
    "gn:country_code":"CN",
    "gn:dem":1794,
    "gn:feature_class":"P",
    "gn:feature_code":"PPL",
    "gn:name":"Hetaozhai",
    "gn:population":0,
    "gn:timezone":"Asia/Shanghai",
    "iso:country":"CN",
    "name:zho_x_preferred":[
        "\u6838\u6843\u5be8"
    ],
    "wof:name":"Hetaozhai",
    "wof:placetype":"locality"
},
  "geometry": {"coordinates":[105.425,26.5917],"type":"Point"}
}