{
  "type": "Feature",
  "properties": {
    "gn:admin1_code":"12.0",
    "gn:asciiname":"Yaohetai",
    "gn:country_code":"CN",
    "gn:dem":28,
    "gn:feature_class":"P",
    "gn:feature_code":"PPL",
    "gn:name":"Yaohetai",
    "gn:population":0,
    "gn:timezone":"Asia/Shanghai",
    "iso:country":"CN",
    "name:zho_x_preferred":[
        "\u7a91\u6cb3\u53f0"
    ],
    "wof:name":"Yaohetai",
    "wof:placetype":"locality"
},
  "geometry": {"coordinates":[113.51627000000001,30.64825],"type":"Point"}
}