{
  "type": "Feature",
  "properties": {
    "gn:admin1_code":"29.0",
    "gn:asciiname":"Xialianhuachi",
    "gn:country_code":"CN",
    "gn:dem":1722,
    "gn:feature_class":"P",
    "gn:feature_code":"PPL",
    "gn:name":"Xialianhuachi",
    "gn:population":0,
    "gn:timezone":"Asia/Shanghai",
    "iso:country":"CN",
    "name:zho_x_preferred":[
        "\u4e0b\u83b2\u82b1\u6c60"
    ],
    "wof:name":"Xialianhuachi",
    "wof:placetype":"locality"
},
  "geometry": {"coordinates":[101.151,25.8023],"type":"Point"}
}