{
  "type": "Feature",
  "properties": {
    "gn:admin1_code":"19.0",
    "gn:asciiname":"Libuzi",
    "gn:country_code":"CN",
    "gn:dem":206,
    "gn:feature_class":"P",
    "gn:feature_code":"PPL",
    "gn:name":"Libuzi",
    "gn:population":0,
    "gn:timezone":"Asia/Shanghai",
    "iso:country":"CN",
    "name:und_x_variant":[
        "Lipuzi",
        "\u674e\u5821\u5b50",
        "Libuzi"
    ],
    "wof:name":"Libuzi",
    "wof:placetype":"locality"
},
  "geometry": {"coordinates":[122.47474,40.24925],"type":"Point"}
}