{
  "type": "Feature",
  "properties": {
    "gn:admin1_code":"16",
    "gn:asciiname":"Xiagaozhai",
    "gn:country_code":"CN",
    "gn:dem":156,
    "gn:feature_class":"P",
    "gn:feature_code":"PPL",
    "gn:name":"Xiagaozhai",
    "gn:population":0,
    "gn:timezone":"Asia/Shanghai",
    "iso:country":"CN",
    "name:zho_x_preferred":[
        "\u4e0b\u9ad8\u5be8"
    ],
    "wof:name":"Xiagaozhai",
    "wof:placetype":"locality"
},
  "geometry": {"coordinates":[110.032,25.1823],"type":"Point"}
}