{
  "type": "Feature",
  "properties": {
    "gn:admin1_code":"9",
    "gn:asciiname":"Luguai",
    "gn:country_code":"CN",
    "gn:dem":67,
    "gn:feature_class":"P",
    "gn:feature_code":"PPL",
    "gn:name":"L\u00fcguai",
    "gn:population":0,
    "gn:timezone":"Asia/Shanghai",
    "iso:country":"CN",
    "name:und_x_variant":[
        "L\u00fcguai"
    ],
    "name:zho_x_preferred":[
        "\u5415\u62d0"
    ],
    "wof:name":"Luguai",
    "wof:placetype":"locality"
},
  "geometry": {"coordinates":[114.95,34.771],"type":"Point"}
}