{
  "type": "Feature",
  "properties": {
    "gn:admin1_code":"19.0",
    "gn:asciiname":"Wangjiadian",
    "gn:country_code":"CN",
    "gn:dem":11,
    "gn:feature_class":"P",
    "gn:feature_code":"PPL",
    "gn:name":"Wangjiadian",
    "gn:population":0,
    "gn:timezone":"Asia/Shanghai",
    "iso:country":"CN",
    "name:und_x_variant":[
        "\u738b\u5bb6\u5e97"
    ],
    "name:zho_x_preferred":[
        "\u738b\u5bb6\u5e97"
    ],
    "wof:name":"Wangjiadian",
    "wof:placetype":"locality"
},
  "geometry": {"coordinates":[123.56215,39.93013],"type":"Point"}
}