{
  "type": "Feature",
  "properties": {
    "gn:admin1_code":"26.0",
    "gn:asciiname":"Fenggoukou",
    "gn:country_code":"CN",
    "gn:dem":1453,
    "gn:feature_class":"P",
    "gn:feature_code":"PPL",
    "gn:name":"Fenggoukou",
    "gn:population":0,
    "gn:timezone":"Asia/Shanghai",
    "iso:country":"CN",
    "name:zho_x_preferred":[
        "\u51e4\u6c9f\u53e3"
    ],
    "wof:name":"Fenggoukou",
    "wof:placetype":"locality"
},
  "geometry": {"coordinates":[109.34551,33.90085],"type":"Point"}
}