{
  "type": "Feature",
  "properties": {
    "gn:admin1_code":"24.0",
    "gn:asciiname":"Dongzhuangwo",
    "gn:country_code":"CN",
    "gn:dem":1377,
    "gn:feature_class":"P",
    "gn:feature_code":"PPL",
    "gn:name":"Dongzhuangwo",
    "gn:population":0,
    "gn:timezone":"Asia/Shanghai",
    "iso:country":"CN",
    "name:zho_x_preferred":[
        "\u4e1c\u5e84\u7a9d"
    ],
    "wof:name":"Dongzhuangwo",
    "wof:placetype":"locality"
},
  "geometry": {"coordinates":[111.77739,39.15143],"type":"Point"}
}