{
  "type": "Feature",
  "properties": {
    "gn:admin1_code":"30.0",
    "gn:asciiname":"Qihai",
    "gn:country_code":"CN",
    "gn:dem":6,
    "gn:feature_class":"P",
    "gn:feature_code":"PPL",
    "gn:name":"Qihai",
    "gn:population":0,
    "gn:timezone":"Asia/Shanghai",
    "iso:country":"CN",
    "name:zho_x_preferred":[
        "\u5c90\u6d77"
    ],
    "wof:name":"Qihai",
    "wof:placetype":"locality"
},
  "geometry": {"coordinates":[112.64207,21.88445],"type":"Point"}
}