{
  "type": "Feature",
  "properties": {
    "gn:admin1_code":"30.0",
    "gn:asciiname":"Changfeng Shangcun",
    "gn:country_code":"CN",
    "gn:dem":11,
    "gn:feature_class":"P",
    "gn:feature_code":"PPL",
    "gn:name":"Changfeng Shangcun",
    "gn:population":0,
    "gn:timezone":"Asia/Urumqi",
    "iso:country":"CN",
    "name:zho_x_preferred":[
        "\u660c\u4ff8\u4e0a\u6751"
    ],
    "wof:name":"Changfeng Shangcun",
    "wof:placetype":"locality"
},
  "geometry": {"coordinates":[109.96065,20.34603],"type":"Point"}
}