{
  "type": "Feature",
  "properties": {
    "gn:admin1_code":"11",
    "gn:asciiname":"Dongping",
    "gn:country_code":"CN",
    "gn:dem":135,
    "gn:feature_class":"P",
    "gn:feature_code":"PPLA3",
    "gn:name":"Dongping",
    "gn:population":0,
    "gn:timezone":"Asia/Shanghai",
    "iso:country":"CN",
    "name:und_x_variant":[
        "An-hua-hsien",
        "Anhua",
        "Dongping",
        "Anhua Xian"
    ],
    "name:zho_x_preferred":[
        "Tung-p\u2019ing"
    ],
    "name:zho_x_variant":[
        "Tung-p\u2019ing-chen",
        "\u5b89\u5316\u53bf"
    ],
    "wof:name":"Dongping",
    "wof:placetype":"locality"
},
  "geometry": {"coordinates":[111.20586000000002,28.38017],"type":"Point"}
}