{
  "type": "Feature",
  "properties": {
    "gn:admin1_code":"5.0",
    "gn:asciiname":"Dapingfang",
    "gn:country_code":"CN",
    "gn:dem":225,
    "gn:feature_class":"P",
    "gn:feature_code":"PPL",
    "gn:name":"Dapingfang",
    "gn:population":0,
    "gn:timezone":"Asia/Shanghai",
    "iso:country":"CN",
    "name:zho_x_preferred":[
        "\u5927\u5e73\u623f"
    ],
    "wof:name":"Dapingfang",
    "wof:placetype":"locality"
},
  "geometry": {"coordinates":[124.62548,44.49449],"type":"Point"}
}