{
  "type": "Feature",
  "properties": {
    "gn:admin1_code":"15.0",
    "gn:asciiname":"Shengli Yidui",
    "gn:country_code":"CN",
    "gn:dem":1682,
    "gn:feature_class":"P",
    "gn:feature_code":"PPLF",
    "gn:name":"Shengli Yidui",
    "gn:population":0,
    "gn:timezone":"Asia/Shanghai",
    "iso:country":"CN",
    "name:zho_x_preferred":[
        "\u80dc\u5229\u4e00\u961f"
    ],
    "wof:name":"Shengli Yidui",
    "wof:placetype":"locality"
},
  "geometry": {"coordinates":[98.17610000000001,39.854],"type":"Point"}
}