{
  "type": "Feature",
  "properties": {
    "gn:admin1_code":"2.0",
    "gn:asciiname":"Feijia",
    "gn:country_code":"CN",
    "gn:dem":373,
    "gn:feature_class":"P",
    "gn:feature_code":"PPL",
    "gn:name":"Feijia",
    "gn:population":0,
    "gn:timezone":"Asia/Shanghai",
    "iso:country":"CN",
    "name:zho_x_preferred":[
        "\u8d39\u5bb6"
    ],
    "wof:name":"Feijia",
    "wof:placetype":"locality"
},
  "geometry": {"coordinates":[119.90022999999999,29.7648],"type":"Point"}
}