{
  "type": "Feature",
  "properties": {
    "gn:admin1_code":"12.0",
    "gn:asciiname":"Manguniu",
    "gn:country_code":"CN",
    "gn:dem":978,
    "gn:feature_class":"P",
    "gn:feature_code":"PPL",
    "gn:name":"Manguniu",
    "gn:population":0,
    "gn:timezone":"Asia/Shanghai",
    "iso:country":"CN",
    "name:zho_x_preferred":[
        "Manguniu"
    ],
    "name:zho_x_variant":[
        "\u6162\u726f\u725b"
    ],
    "wof:name":"Manguniu",
    "wof:placetype":"locality"
},
  "geometry": {"coordinates":[109.4701,29.80825],"type":"Point"}
}