{
  "type": "Feature",
  "properties": {
    "gn:admin1_code":"11.0",
    "gn:asciiname":"Nantianlong",
    "gn:country_code":"CN",
    "gn:dem":83,
    "gn:feature_class":"P",
    "gn:feature_code":"PPL",
    "gn:name":"Nantianlong",
    "gn:population":0,
    "gn:timezone":"Asia/Shanghai",
    "iso:country":"CN",
    "name:zho_x_preferred":[
        "\u5357\u7530\u5785"
    ],
    "wof:name":"Nantianlong",
    "wof:placetype":"locality"
},
  "geometry": {"coordinates":[113.28807,27.08125],"type":"Point"}
}