{
  "type": "Feature",
  "properties": {
    "gn:admin1_code":"11",
    "gn:asciiname":"Shuidong",
    "gn:cc2":"CN",
    "gn:country_code":"CN",
    "gn:dem":295,
    "gn:feature_class":"P",
    "gn:feature_code":"PPL",
    "gn:name":"Shuidong",
    "gn:population":0,
    "gn:timezone":"Asia/Shanghai",
    "iso:country":"CN",
    "name:und_x_variant":[
        "Shuidongqiao",
        "Shuidong"
    ],
    "wof:name":"Shuidong",
    "wof:placetype":"locality"
},
  "geometry": {"coordinates":[110.74583,27.15333],"type":"Point"}
}