{
  "type": "Feature",
  "properties": {
    "gn:admin1_code":"10",
    "gn:asciiname":"Xihuang Tukan",
    "gn:country_code":"CN",
    "gn:dem":394,
    "gn:feature_class":"P",
    "gn:feature_code":"PPL",
    "gn:name":"Xihuang Tukan",
    "gn:population":0,
    "gn:timezone":"Asia/Shanghai",
    "iso:country":"CN",
    "name:zho_x_preferred":[
        "\u897f\u9ec4\u571f\u574e"
    ],
    "wof:name":"Xihuang Tukan",
    "wof:placetype":"locality"
},
  "geometry": {"coordinates":[117.95285,41.11554],"type":"Point"}
}