{
  "type": "Feature",
  "properties": {
    "gn:admin1_code":"30.0",
    "gn:asciiname":"Dazhangping",
    "gn:country_code":"CN",
    "gn:dem":811,
    "gn:feature_class":"P",
    "gn:feature_code":"PPL",
    "gn:name":"Dazhangping",
    "gn:population":0,
    "gn:timezone":"Asia/Shanghai",
    "iso:country":"CN",
    "name:zho_x_preferred":[
        "Dazhangping"
    ],
    "name:zho_x_variant":[
        "\u5927\u638c\u576a"
    ],
    "wof:name":"Dazhangping",
    "wof:placetype":"locality"
},
  "geometry": {"coordinates":[112.15528,24.63861],"type":"Point"}
}