{
  "type": "Feature",
  "properties": {
    "gn:admin1_code":"5.0",
    "gn:asciiname":"Xiwulan Tuozi",
    "gn:country_code":"CN",
    "gn:dem":146,
    "gn:feature_class":"P",
    "gn:feature_code":"PPL",
    "gn:name":"Xiwulan Tuozi",
    "gn:population":0,
    "gn:timezone":"Asia/Shanghai",
    "iso:country":"CN",
    "name:zho_x_preferred":[
        "\u897f\u4e4c\u5170\u5768\u5b50"
    ],
    "wof:name":"Xiwulan Tuozi",
    "wof:placetype":"locality"
},
  "geometry": {"coordinates":[123.58772,43.98891],"type":"Point"}
}