{
  "type": "Feature",
  "properties": {
    "gn:admin1_code":"11.0",
    "gn:asciiname":"Xiongjiadun",
    "gn:country_code":"CN",
    "gn:dem":545,
    "gn:feature_class":"P",
    "gn:feature_code":"PPL",
    "gn:name":"Xiongjiadun",
    "gn:population":0,
    "gn:timezone":"Asia/Shanghai",
    "iso:country":"CN",
    "name:zho_x_preferred":[
        "Xiongjiadun"
    ],
    "name:zho_x_variant":[
        "\u718a\u5bb6\u58a9"
    ],
    "wof:name":"Xiongjiadun",
    "wof:placetype":"locality"
},
  "geometry": {"coordinates":[111.07655,29.98663],"type":"Point"}
}