{
  "type": "Feature",
  "properties": {
    "gn:admin1_code":"25.0",
    "gn:asciiname":"Xiaoyangquan",
    "gn:country_code":"CN",
    "gn:dem":35,
    "gn:feature_class":"P",
    "gn:feature_code":"PPL",
    "gn:name":"Xiaoyangquan",
    "gn:population":0,
    "gn:timezone":"Asia/Shanghai",
    "iso:country":"CN",
    "name:zho_x_preferred":[
        "\u5c0f\u7f8a\u5708"
    ],
    "wof:name":"Xiaoyangquan",
    "wof:placetype":"locality"
},
  "geometry": {"coordinates":[119.31046000000001,35.24592],"type":"Point"}
}