{
  "type": "Feature",
  "properties": {
    "gn:admin1_code":"13",
    "gn:asciiname":"Kuangshan",
    "gn:country_code":"CN",
    "gn:dem":753,
    "gn:feature_class":"P",
    "gn:feature_code":"PPL",
    "gn:name":"Kuangshan",
    "gn:population":0,
    "gn:timezone":"Asia/Urumqi",
    "iso:country":"CN",
    "name:zho_x_preferred":[
        "\u77ff\u5c71"
    ],
    "wof:name":"Kuangshan",
    "wof:placetype":"locality"
},
  "geometry": {"coordinates":[87.72842,43.90841],"type":"Point"}
}