{
  "type": "Feature",
  "properties": {
    "gn:admin1_code":"12.0",
    "gn:asciiname":"Wanjialing",
    "gn:country_code":"CN",
    "gn:dem":1552,
    "gn:feature_class":"P",
    "gn:feature_code":"PPL",
    "gn:name":"Wanjialing",
    "gn:population":0,
    "gn:timezone":"Asia/Shanghai",
    "iso:country":"CN",
    "name:zho_x_preferred":[
        "\u4e07\u5bb6\u9675"
    ],
    "name:zho_x_variant":[
        "\u4e07\u5bb6\u5cad"
    ],
    "wof:name":"Wanjialing",
    "wof:placetype":"locality"
},
  "geometry": {"coordinates":[110.90718,31.33812],"type":"Point"}
}