{
  "type": "Feature",
  "properties": {
    "gn:admin1_code":"18",
    "gn:asciiname":"Yiqi",
    "gn:country_code":"CN",
    "gn:dem":1344,
    "gn:feature_class":"P",
    "gn:feature_code":"PPL",
    "gn:name":"Yiqi",
    "gn:population":0,
    "gn:timezone":"Asia/Shanghai",
    "iso:country":"CN",
    "name:zho_x_preferred":[
        "\u8fe4\u8d77"
    ],
    "wof:name":"Yiqi",
    "wof:placetype":"locality"
},
  "geometry": {"coordinates":[105.381,26.8481],"type":"Point"}
}