{
  "type": "Feature",
  "properties": {
    "gn:admin1_code":"29.0",
    "gn:asciiname":"Xiaoshishan Xiazhai",
    "gn:country_code":"CN",
    "gn:dem":1479,
    "gn:feature_class":"P",
    "gn:feature_code":"PPL",
    "gn:name":"Xiaoshishan Xiazhai",
    "gn:population":0,
    "gn:timezone":"Asia/Shanghai",
    "iso:country":"CN",
    "name:zho_x_preferred":[
        "\u5c0f\u77f3\u5c71\u4e0b\u5be8"
    ],
    "wof:name":"Xiaoshishan Xiazhai",
    "wof:placetype":"locality"
},
  "geometry": {"coordinates":[104.08199999999999,23.4143],"type":"Point"}
}