{
  "type": "Feature",
  "properties": {
    "gn:admin1_code":"14.0",
    "gn:asciiname":"Rongkong",
    "gn:country_code":"CN",
    "gn:dem":4198,
    "gn:feature_class":"P",
    "gn:feature_code":"PPL",
    "gn:name":"Rongkong",
    "gn:population":0,
    "gn:timezone":"Asia/Urumqi",
    "iso:country":"CN",
    "name:zho_x_preferred":[
        "\u8363\u5b54"
    ],
    "wof:name":"Rongkong",
    "wof:placetype":"locality"
},
  "geometry": {"coordinates":[87.75530000000001,28.4262],"type":"Point"}
}