{
  "type": "Feature",
  "properties": {
    "gn:admin1_code":"02",
    "gn:asciiname":"Shuitou",
    "gn:country_code":"CN",
    "gn:dem":15,
    "gn:feature_class":"P",
    "gn:feature_code":"PPL",
    "gn:name":"Shuitou",
    "gn:population":0,
    "gn:timezone":"Asia/Shanghai",
    "iso:country":"CN",
    "name:zho_x_preferred":[
        "Shui-t\u2019ou-chieh"
    ],
    "name:zho_x_variant":[
        "Shui-t\u2019ou",
        "\u6c34\u5934\u9547"
    ],
    "wof:name":"Shuitou",
    "wof:placetype":"locality"
},
  "geometry": {"coordinates":[120.3211,27.63421],"type":"Point"}
}