{
  "type": "Feature",
  "properties": {
    "gn:admin1_code":"31",
    "gn:asciiname":"Xinmin Nongchang",
    "gn:country_code":"CN",
    "gn:dem":17,
    "gn:feature_class":"P",
    "gn:feature_code":"PPLF",
    "gn:name":"Xinmin Nongchang",
    "gn:population":0,
    "gn:timezone":"Asia/Shanghai",
    "iso:country":"CN",
    "wof:name":"Xinmin Nongchang",
    "wof:placetype":"locality"
},
  "geometry": {"coordinates":[110.39528,19.9225],"type":"Point"}
}