{
  "type": "Feature",
  "properties": {
    "gn:admin1_code":"8.0",
    "gn:asciiname":"Xiaojubaocun",
    "gn:country_code":"CN",
    "gn:dem":226,
    "gn:feature_class":"P",
    "gn:feature_code":"PPL",
    "gn:name":"Xiaojubaocun",
    "gn:population":0,
    "gn:timezone":"Asia/Shanghai",
    "iso:country":"CN",
    "name:zho_x_preferred":[
        "\u5c0f\u805a\u5b9d\u6751"
    ],
    "wof:name":"Xiaojubaocun",
    "wof:placetype":"locality"
},
  "geometry": {"coordinates":[122.92883999999999,47.31565],"type":"Point"}
}