{
  "type": "Feature",
  "properties": {
    "gn:admin1_code":"15.0",
    "gn:asciiname":"Huaishuping",
    "gn:country_code":"CN",
    "gn:dem":1227,
    "gn:feature_class":"P",
    "gn:feature_code":"PPL",
    "gn:name":"Huaishuping",
    "gn:population":0,
    "gn:timezone":"Asia/Shanghai",
    "iso:country":"CN",
    "name:zho_x_preferred":[
        "\u69d0\u6811\u576a"
    ],
    "wof:name":"Huaishuping",
    "wof:placetype":"locality"
},
  "geometry": {"coordinates":[106.185,34.1279],"type":"Point"}
}