{
  "type": "Feature",
  "properties": {
    "gn:admin1_code":"15.0",
    "gn:asciiname":"Changcha",
    "gn:country_code":"CN",
    "gn:dem":1766,
    "gn:feature_class":"P",
    "gn:feature_code":"PPL",
    "gn:name":"Changcha",
    "gn:population":0,
    "gn:timezone":"Asia/Shanghai",
    "iso:country":"CN",
    "name:und_x_variant":[
        "\u957f\u5c94"
    ],
    "wof:name":"Changcha",
    "wof:placetype":"locality"
},
  "geometry": {"coordinates":[105.70697,35.33449],"type":"Point"}
}