{
  "type": "Feature",
  "properties": {
    "gn:admin1_code":"12.0",
    "gn:asciiname":"Linjiazui",
    "gn:country_code":"CN",
    "gn:dem":40,
    "gn:feature_class":"P",
    "gn:feature_code":"PPL",
    "gn:name":"Linjiazui",
    "gn:population":0,
    "gn:timezone":"Asia/Shanghai",
    "iso:country":"CN",
    "name:zho_x_preferred":[
        "Linjiazui"
    ],
    "name:zho_x_variant":[
        "\u6797\u5bb6\u5480"
    ],
    "wof:name":"Linjiazui",
    "wof:placetype":"locality"
},
  "geometry": {"coordinates":[115.09023999999999,30.50446],"type":"Point"}
}