{
  "type": "Feature",
  "properties": {
    "gn:admin1_code":"7.0",
    "gn:asciiname":"Xiayansu",
    "gn:country_code":"CN",
    "gn:dem":678,
    "gn:feature_class":"P",
    "gn:feature_code":"PPL",
    "gn:name":"Xiayansu",
    "gn:population":0,
    "gn:timezone":"Asia/Shanghai",
    "iso:country":"CN",
    "name:zho_x_preferred":[
        "\u4e0b\u71d5\u5bbf"
    ],
    "wof:name":"Xiayansu",
    "wof:placetype":"locality"
},
  "geometry": {"coordinates":[119.06974,26.03458],"type":"Point"}
}