{
  "type": "Feature",
  "properties": {
    "gn:admin1_code":"32.0",
    "gn:asciiname":"Wazi",
    "gn:country_code":"CN",
    "gn:dem":2721,
    "gn:feature_class":"P",
    "gn:feature_code":"PPL",
    "gn:name":"Wazi",
    "gn:population":0,
    "gn:timezone":"Asia/Shanghai",
    "iso:country":"CN",
    "name:zho_x_preferred":[
        "\u74e6\u5b50"
    ],
    "wof:name":"Wazi",
    "wof:placetype":"locality"
},
  "geometry": {"coordinates":[103.35599999999999,27.8586],"type":"Point"}
}