{
  "type": "Feature",
  "properties": {
    "gn:admin1_code":"21",
    "gn:asciiname":"Majiatang",
    "gn:country_code":"CN",
    "gn:dem":1471,
    "gn:feature_class":"P",
    "gn:feature_code":"PPL",
    "gn:name":"Majiatang",
    "gn:population":0,
    "gn:timezone":"Asia/Shanghai",
    "iso:country":"CN",
    "wof:name":"Majiatang",
    "wof:placetype":"locality"
},
  "geometry": {"coordinates":[105.65472,36.94389],"type":"Point"}
}