{
  "type": "Feature",
  "properties": {
    "gn:admin1_code":"19.0",
    "gn:asciiname":"Zhaodian",
    "gn:country_code":"CN",
    "gn:dem":38,
    "gn:feature_class":"P",
    "gn:feature_code":"PPL",
    "gn:name":"Zhaodian",
    "gn:population":0,
    "gn:timezone":"Asia/Shanghai",
    "iso:country":"CN",
    "name:und_x_variant":[
        "\u8d75\u5e97"
    ],
    "name:zho_x_preferred":[
        "\u8d75\u5e97"
    ],
    "wof:name":"Zhaodian",
    "wof:placetype":"locality"
},
  "geometry": {"coordinates":[121.82901,39.77315],"type":"Point"}
}