{
  "type": "Feature",
  "properties": {
    "gn:admin1_code":"6.0",
    "gn:asciiname":"Liushiyi Daoban",
    "gn:country_code":"CN",
    "gn:dem":4449,
    "gn:feature_class":"P",
    "gn:feature_code":"PPL",
    "gn:name":"Liushiyi Daoban",
    "gn:population":0,
    "gn:timezone":"Asia/Urumqi",
    "iso:country":"CN",
    "name:und_x_variant":[
        "\u516d\u5341\u4e00\u9053\u73ed"
    ],
    "wof:name":"Liushiyi Daoban",
    "wof:placetype":"locality"
},
  "geometry": {"coordinates":[94.12287999999999,35.7222],"type":"Point"}
}