{
  "type": "Feature",
  "properties": {
    "gn:admin1_code":"32.0",
    "gn:asciiname":"Zhifosi",
    "gn:country_code":"CN",
    "gn:dem":347,
    "gn:feature_class":"P",
    "gn:feature_code":"PPL",
    "gn:name":"Zhifosi",
    "gn:population":0,
    "gn:timezone":"Asia/Shanghai",
    "iso:country":"CN",
    "name:zho_x_preferred":[
        "\u77e5\u4f5b\u5bfa"
    ],
    "wof:name":"Zhifosi",
    "wof:placetype":"locality"
},
  "geometry": {"coordinates":[105.41701,30.84781],"type":"Point"}
}