{
  "type": "Feature",
  "properties": {
    "gn:admin1_code":"4.0",
    "gn:asciiname":"Tangqiaocun",
    "gn:country_code":"CN",
    "gn:dem":9,
    "gn:feature_class":"P",
    "gn:feature_code":"PPL",
    "gn:name":"Tangqiaocun",
    "gn:population":0,
    "gn:timezone":"Asia/Shanghai",
    "iso:country":"CN",
    "name:und_x_variant":[
        "Tangqiao",
        "Tangqiaocun"
    ],
    "name:zho_x_preferred":[
        "\u6c64\u6865"
    ],
    "name:zho_x_variant":[
        "\u6c64\u6865\u6751"
    ],
    "wof:name":"Tangqiaocun",
    "wof:placetype":"locality"
},
  "geometry": {"coordinates":[119.20367,31.39947],"type":"Point"}
}