{
  "type": "Feature",
  "properties": {
    "gn:admin1_code":"4.0",
    "gn:asciiname":"Gengzhuangcun",
    "gn:country_code":"CN",
    "gn:dem":29,
    "gn:feature_class":"P",
    "gn:feature_code":"PPL",
    "gn:name":"Gengzhuangcun",
    "gn:population":0,
    "gn:timezone":"Asia/Shanghai",
    "iso:country":"CN",
    "name:zho_x_preferred":[
        "\u803f\u5e84\u6751"
    ],
    "wof:name":"Gengzhuangcun",
    "wof:placetype":"locality"
},
  "geometry": {"coordinates":[117.86011000000001,34.56708],"type":"Point"}
}