{
  "type": "Feature",
  "properties": {
    "gn:admin1_code":"24.0",
    "gn:asciiname":"Shangshenyu",
    "gn:country_code":"CN",
    "gn:dem":1151,
    "gn:feature_class":"P",
    "gn:feature_code":"PPL",
    "gn:name":"Shangshenyu",
    "gn:population":0,
    "gn:timezone":"Asia/Shanghai",
    "iso:country":"CN",
    "name:zho_x_preferred":[
        "\u4e0a\u795e\u5cea"
    ],
    "wof:name":"Shangshenyu",
    "wof:placetype":"locality"
},
  "geometry": {"coordinates":[113.86960000000001,40.14831],"type":"Point"}
}