{
  "type": "Feature",
  "properties": {
    "gn:admin1_code":"9.0",
    "gn:asciiname":"Kuixing",
    "gn:country_code":"CN",
    "gn:dem":371,
    "gn:feature_class":"P",
    "gn:feature_code":"PPL",
    "gn:name":"Kuixing",
    "gn:population":0,
    "gn:timezone":"Asia/Shanghai",
    "iso:country":"CN",
    "name:zho_x_preferred":[
        "\u9b41\u5174"
    ],
    "wof:name":"Kuixing",
    "wof:placetype":"locality"
},
  "geometry": {"coordinates":[111.09854,33.3344],"type":"Point"}
}