{
  "type": "Feature",
  "properties": {
    "gn:admin1_code":"11.0",
    "gn:asciiname":"Lutangchong",
    "gn:country_code":"CN",
    "gn:dem":123,
    "gn:feature_class":"P",
    "gn:feature_code":"PPL",
    "gn:name":"Lutangchong",
    "gn:population":0,
    "gn:timezone":"Asia/Shanghai",
    "iso:country":"CN",
    "name:zho_x_preferred":[
        "\u6cf8\u5858\u51b2"
    ],
    "wof:name":"Lutangchong",
    "wof:placetype":"locality"
},
  "geometry": {"coordinates":[111.81838999999999,26.32711],"type":"Point"}
}