{
  "type": "Feature",
  "properties": {
    "gn:admin1_code":"4.0",
    "gn:asciiname":"Xiaobei Wuzu",
    "gn:country_code":"CN",
    "gn:dem":4,
    "gn:feature_class":"P",
    "gn:feature_code":"PPLF",
    "gn:name":"Xiaobei Wuzu",
    "gn:population":0,
    "gn:timezone":"Asia/Shanghai",
    "iso:country":"CN",
    "name:zho_x_preferred":[
        "\u6821\u5317\u4e94\u7ec4"
    ],
    "wof:name":"Xiaobei Wuzu",
    "wof:placetype":"locality"
},
  "geometry": {"coordinates":[120.90625,32.0239],"type":"Point"}
}