{
  "type": "Feature",
  "properties": {
    "gn:admin1_code":"8.0",
    "gn:asciiname":"Sundafang",
    "gn:country_code":"CN",
    "gn:dem":255,
    "gn:feature_class":"P",
    "gn:feature_code":"PPL",
    "gn:name":"Sundafang",
    "gn:population":0,
    "gn:timezone":"Asia/Shanghai",
    "iso:country":"CN",
    "name:zho_x_preferred":[
        "\u5b59\u5927\u623f"
    ],
    "wof:name":"Sundafang",
    "wof:placetype":"locality"
},
  "geometry": {"coordinates":[125.05251,48.57467000000001],"type":"Point"}
}