{
  "type": "Feature",
  "properties": {
    "gn:admin1_code":"9",
    "gn:asciiname":"Cuiliangzhuang",
    "gn:country_code":"CN",
    "gn:dem":55,
    "gn:feature_class":"P",
    "gn:feature_code":"PPL",
    "gn:name":"Cuiliangzhuang",
    "gn:population":0,
    "gn:timezone":"Asia/Shanghai",
    "iso:country":"CN",
    "name:zho_x_preferred":[
        "\u5d14\u6881\u5e84"
    ],
    "wof:name":"Cuiliangzhuang",
    "wof:placetype":"locality"
},
  "geometry": {"coordinates":[114.994,35.6317],"type":"Point"}
}