{
  "type": "Feature",
  "properties": {
    "gn:admin1_code":"20.0",
    "gn:asciiname":"Shen'erdeng",
    "gn:country_code":"CN",
    "gn:dem":1695,
    "gn:feature_class":"P",
    "gn:feature_code":"PPL",
    "gn:name":"Shen\u2019erdeng",
    "gn:population":0,
    "gn:timezone":"Asia/Shanghai",
    "iso:country":"CN",
    "name:und_x_variant":[
        "Shen\u2019erdeng",
        "\u4ec0\u5c14\u767b"
    ],
    "wof:name":"Shen'erdeng",
    "wof:placetype":"locality"
},
  "geometry": {"coordinates":[111.49078,41.05292],"type":"Point"}
}