{
  "type": "Feature",
  "properties": {
    "gn:admin1_code":"8.0",
    "gn:asciiname":"Shi'erhao",
    "gn:country_code":"CN",
    "gn:dem":150,
    "gn:feature_class":"P",
    "gn:feature_code":"PPL",
    "gn:name":"Shi\u2019erhao",
    "gn:population":0,
    "gn:timezone":"Asia/Shanghai",
    "iso:country":"CN",
    "name:und_x_variant":[
        "Shi\u2019erhao"
    ],
    "name:zho_x_preferred":[
        "\u5341\u4e8c\u53f7"
    ],
    "wof:name":"Shi'erhao",
    "wof:placetype":"locality"
},
  "geometry": {"coordinates":[124.75841,47.01578],"type":"Point"}
}