{
  "type": "Feature",
  "properties": {
    "gn:admin1_code":"20.0",
    "gn:asciiname":"Yixi",
    "gn:country_code":"CN",
    "gn:dem":764,
    "gn:feature_class":"P",
    "gn:feature_code":"PPL",
    "gn:name":"Yixi",
    "gn:population":0,
    "gn:timezone":"Asia/Shanghai",
    "iso:country":"CN",
    "name:zho_x_preferred":[
        "\u4f0a\u897f"
    ],
    "wof:name":"Yixi",
    "wof:placetype":"locality"
},
  "geometry": {"coordinates":[121.54492,50.63227],"type":"Point"}
}