{
  "type": "Feature",
  "properties": {
    "gn:admin1_code":"19.0",
    "gn:asciiname":"Tianjiaying",
    "gn:country_code":"CN",
    "gn:dem":705,
    "gn:feature_class":"P",
    "gn:feature_code":"PPL",
    "gn:name":"Tianjiaying",
    "gn:population":0,
    "gn:timezone":"Asia/Shanghai",
    "iso:country":"CN",
    "name:zho_x_preferred":[
        "\u7530\u5bb6\u8425"
    ],
    "wof:name":"Tianjiaying",
    "wof:placetype":"locality"
},
  "geometry": {"coordinates":[119.54083,41.96265],"type":"Point"}
}