{
  "type": "Feature",
  "properties": {
    "gn:admin1_code":"12.0",
    "gn:asciiname":"Huangbaituo",
    "gn:country_code":"CN",
    "gn:dem":1689,
    "gn:feature_class":"P",
    "gn:feature_code":"PPL",
    "gn:name":"Huangbaituo",
    "gn:population":0,
    "gn:timezone":"Asia/Shanghai",
    "iso:country":"CN",
    "name:zho_x_preferred":[
        "\u9ec4\u67cf\u5768"
    ],
    "wof:name":"Huangbaituo",
    "wof:placetype":"locality"
},
  "geometry": {"coordinates":[109.88800000000001,30.06899],"type":"Point"}
}