{
  "type": "Feature",
  "properties": {
    "gn:admin1_code":"12.0",
    "gn:asciiname":"Wuluoxi",
    "gn:country_code":"CN",
    "gn:dem":32,
    "gn:feature_class":"P",
    "gn:feature_code":"PPL",
    "gn:name":"Wuluoxi",
    "gn:population":0,
    "gn:timezone":"Asia/Shanghai",
    "iso:country":"CN",
    "name:zho_x_preferred":[
        "\u5434\u843d\u6eaa"
    ],
    "wof:name":"Wuluoxi",
    "wof:placetype":"locality"
},
  "geometry": {"coordinates":[112.51178,29.62863],"type":"Point"}
}