{
  "type": "Feature",
  "properties": {
    "gn:admin1_code":"11.0",
    "gn:asciiname":"Baxianchong",
    "gn:country_code":"CN",
    "gn:dem":330,
    "gn:feature_class":"P",
    "gn:feature_code":"PPL",
    "gn:name":"Baxianchong",
    "gn:population":0,
    "gn:timezone":"Asia/Shanghai",
    "iso:country":"CN",
    "name:zho_x_preferred":[
        "\u516b\u4ed9\u51b2"
    ],
    "wof:name":"Baxianchong",
    "wof:placetype":"locality"
},
  "geometry": {"coordinates":[113.78631,28.05296],"type":"Point"}
}