{
  "type": "Feature",
  "properties": {
    "gn:admin1_code":"9.0",
    "gn:asciiname":"Qincun",
    "gn:country_code":"CN",
    "gn:dem":434,
    "gn:feature_class":"P",
    "gn:feature_code":"PPL",
    "gn:name":"Qincun",
    "gn:population":0,
    "gn:timezone":"Asia/Shanghai",
    "iso:country":"CN",
    "name:zho_x_preferred":[
        "\u79e6\u6751"
    ],
    "wof:name":"Qincun",
    "wof:placetype":"locality"
},
  "geometry": {"coordinates":[110.76687,34.52872],"type":"Point"}
}