{
  "type": "Feature",
  "properties": {
    "gn:admin1_code":"30.0",
    "gn:asciiname":"Kanxiacun",
    "gn:country_code":"CN",
    "gn:dem":43,
    "gn:feature_class":"P",
    "gn:feature_code":"PPL",
    "gn:name":"Kanxiacun",
    "gn:population":0,
    "gn:timezone":"Asia/Urumqi",
    "iso:country":"CN",
    "name:zho_x_preferred":[
        "\u574e\u4e0b\u6751"
    ],
    "wof:name":"Kanxiacun",
    "wof:placetype":"locality"
},
  "geometry": {"coordinates":[110.42046999999999,20.49691],"type":"Point"}
}