{
  "type": "Feature",
  "properties": {
    "gn:admin1_code":"5.0",
    "gn:asciiname":"Xizhangjia Wazi",
    "gn:country_code":"CN",
    "gn:dem":215,
    "gn:feature_class":"P",
    "gn:feature_code":"PPL",
    "gn:name":"Xizhangjia Wazi",
    "gn:population":0,
    "gn:timezone":"Asia/Shanghai",
    "iso:country":"CN",
    "name:zho_x_preferred":[
        "\u897f\u5f20\u5bb6\u6d3c\u5b50"
    ],
    "wof:name":"Xizhangjia Wazi",
    "wof:placetype":"locality"
},
  "geometry": {"coordinates":[124.98497999999999,43.69825],"type":"Point"}
}