{
  "type": "Feature",
  "properties": {
    "gn:admin1_code":"9.0",
    "gn:asciiname":"Jiangpo",
    "gn:country_code":"CN",
    "gn:dem":179,
    "gn:feature_class":"P",
    "gn:feature_code":"PPL",
    "gn:name":"Jiangpo",
    "gn:population":0,
    "gn:timezone":"Asia/Shanghai",
    "iso:country":"CN",
    "name:und_x_variant":[
        "\u848b\u5761",
        "Jiangpo"
    ],
    "wof:name":"Jiangpo",
    "wof:placetype":"locality"
},
  "geometry": {"coordinates":[112.19683000000001,33.01446],"type":"Point"}
}