{
  "type": "Feature",
  "properties": {
    "gn:admin1_code":"29.0",
    "gn:asciiname":"Machangyan",
    "gn:country_code":"CN",
    "gn:dem":2002,
    "gn:feature_class":"P",
    "gn:feature_code":"PPL",
    "gn:name":"Machangyan",
    "gn:population":0,
    "gn:timezone":"Asia/Shanghai",
    "iso:country":"CN",
    "name:zho_x_preferred":[
        "\u9a6c\u5382\u5ca9"
    ],
    "wof:name":"Machangyan",
    "wof:placetype":"locality"
},
  "geometry": {"coordinates":[103.40000000000001,25.9074],"type":"Point"}
}