{
  "type": "Feature",
  "properties": {
    "gn:admin1_code":"23.0",
    "gn:asciiname":"Guanwangmiao",
    "gn:country_code":"CN",
    "gn:dem":8,
    "gn:feature_class":"P",
    "gn:feature_code":"PPL",
    "gn:name":"Guanwangmiao",
    "gn:population":0,
    "gn:timezone":"Asia/Shanghai",
    "iso:country":"CN",
    "name:und_x_variant":[
        "\u5173\u738b\u5e99"
    ],
    "wof:name":"Guanwangmiao",
    "wof:placetype":"locality"
},
  "geometry": {"coordinates":[120.98681000000001,31.09688],"type":"Point"}
}