{
  "type": "Feature",
  "properties": {
    "gn:admin1_code":"8.0",
    "gn:asciiname":"Aipingcun",
    "gn:country_code":"CN",
    "gn:dem":175,
    "gn:feature_class":"P",
    "gn:feature_code":"PPL",
    "gn:name":"Aipingcun",
    "gn:population":0,
    "gn:timezone":"Asia/Shanghai",
    "iso:country":"CN",
    "name:zho_x_preferred":[
        "\u7231\u5e73\u6751"
    ],
    "wof:name":"Aipingcun",
    "wof:placetype":"locality"
},
  "geometry": {"coordinates":[126.57281999999999,47.53432],"type":"Point"}
}