{
  "type": "Feature",
  "properties": {
    "gn:admin1_code":"29.0",
    "gn:asciiname":"Aduhe",
    "gn:country_code":"CN",
    "gn:dem":2326,
    "gn:feature_class":"P",
    "gn:feature_code":"PPL",
    "gn:name":"Aduhe",
    "gn:population":0,
    "gn:timezone":"Asia/Shanghai",
    "iso:country":"CN",
    "name:zho_x_preferred":[
        "\u963f\u5ea6\u6cb3"
    ],
    "wof:name":"Aduhe",
    "wof:placetype":"locality"
},
  "geometry": {"coordinates":[99.26090000000001,26.7153],"type":"Point"}
}