{
  "type": "Feature",
  "properties": {
    "gn:admin1_code":"3.0",
    "gn:asciiname":"Shangfengxiang Meishan Linchang",
    "gn:country_code":"CN",
    "gn:dem":512,
    "gn:feature_class":"P",
    "gn:feature_code":"PPLF",
    "gn:name":"Shangfengxiang Meishan Linchang",
    "gn:population":0,
    "gn:timezone":"Asia/Shanghai",
    "iso:country":"CN",
    "name:und_x_variant":[
        "\u4e0a\u5949\u4e61\u6885\u5c71\u6797\u573a"
    ],
    "wof:name":"Shangfengxiang Meishan Linchang",
    "wof:placetype":"locality"
},
  "geometry": {"coordinates":[114.64506000000002,28.76086],"type":"Point"}
}