{
  "type": "Feature",
  "properties": {
    "gn:admin1_code":"26.0",
    "gn:asciiname":"Hujiaying",
    "gn:country_code":"CN",
    "gn:dem":505,
    "gn:feature_class":"P",
    "gn:feature_code":"PPLA4",
    "gn:name":"Hujiaying",
    "gn:population":0,
    "gn:timezone":"Asia/Shanghai",
    "iso:country":"CN",
    "name:und_x_variant":[
        "\u80e1\u5bb6\u8425"
    ],
    "wof:name":"Hujiaying",
    "wof:placetype":"locality"
},
  "geometry": {"coordinates":[107.02406999999999,33.02391],"type":"Point"}
}