{
  "type": "Feature",
  "properties": {
    "gn:admin1_code":"2.0",
    "gn:asciiname":"Yangjiayuan",
    "gn:country_code":"CN",
    "gn:dem":447,
    "gn:feature_class":"P",
    "gn:feature_code":"PPL",
    "gn:name":"Yangjiayuan",
    "gn:population":0,
    "gn:timezone":"Asia/Shanghai",
    "iso:country":"CN",
    "name:zho_x_preferred":[
        "\u6768\u5bb6\u56ed"
    ],
    "wof:name":"Yangjiayuan",
    "wof:placetype":"locality"
},
  "geometry": {"coordinates":[118.51646,29.08395],"type":"Point"}
}