{
  "type": "Feature",
  "properties": {
    "gn:admin1_code":"1.0",
    "gn:asciiname":"Chezuocun",
    "gn:country_code":"CN",
    "gn:dem":73,
    "gn:feature_class":"P",
    "gn:feature_code":"PPL",
    "gn:name":"Chezuocun",
    "gn:population":0,
    "gn:timezone":"Asia/Shanghai",
    "iso:country":"CN",
    "name:zho_x_preferred":[
        "\u8f66\u5de6\u6751"
    ],
    "wof:name":"Chezuocun",
    "wof:placetype":"locality"
},
  "geometry": {"coordinates":[117.04922999999999,32.02668],"type":"Point"}
}