{
  "type": "Feature",
  "properties": {
    "gn:admin1_code":"20",
    "gn:asciiname":"Chang-ku-t'ai",
    "gn:country_code":"CN",
    "gn:dem":633,
    "gn:feature_class":"P",
    "gn:feature_code":"PPL",
    "gn:name":"Chang-ku-t\u2019ai",
    "gn:population":0,
    "gn:timezone":"Asia/Shanghai",
    "iso:country":"CN",
    "wof:name":"Chang-ku-t'ai",
    "wof:placetype":"locality"
},
  "geometry": {"coordinates":[119.22278,42.76833],"type":"Point"}
}