{
  "type": "Feature",
  "properties": {
    "gn:admin1_code":"9",
    "gn:asciiname":"Wanghongdian",
    "gn:country_code":"CN",
    "gn:dem":51,
    "gn:feature_class":"P",
    "gn:feature_code":"PPL",
    "gn:name":"Wanghongdian",
    "gn:population":0,
    "gn:timezone":"Asia/Shanghai",
    "iso:country":"CN",
    "name:zho_x_preferred":[
        "\u738b\u6d2a\u5e97"
    ],
    "wof:name":"Wanghongdian",
    "wof:placetype":"locality"
},
  "geometry": {"coordinates":[115.18755,36.14273],"type":"Point"}
}