{
  "type": "Feature",
  "properties": {
    "gn:admin1_code":"33",
    "gn:asciiname":"Baizi",
    "gn:country_code":"CN",
    "gn:dem":263,
    "gn:feature_class":"P",
    "gn:feature_code":"PPLA4",
    "gn:name":"Baizi",
    "gn:population":0,
    "gn:timezone":"Asia/Shanghai",
    "iso:country":"CN",
    "name:und_x_variant":[
        "Pai-tzu",
        "Baizi",
        "Baizi Zhen"
    ],
    "name:zho_x_preferred":[
        "\u767d\u6893"
    ],
    "name:zho_x_variant":[
        "\u767d\u6893\u9547"
    ],
    "wof:name":"Baizi",
    "wof:placetype":"locality"
},
  "geometry": {"coordinates":[105.71297,30.09403],"type":"Point"}
}