{
  "type": "Feature",
  "properties": {
    "gn:admin1_code":"15.0",
    "gn:asciiname":"Shagouzhuang",
    "gn:country_code":"CN",
    "gn:dem":2292,
    "gn:feature_class":"P",
    "gn:feature_code":"PPL",
    "gn:name":"Shagouzhuang",
    "gn:population":0,
    "gn:timezone":"Asia/Shanghai",
    "iso:country":"CN",
    "name:zho_x_preferred":[
        "\u6c99\u6c9f\u5e84"
    ],
    "wof:name":"Shagouzhuang",
    "wof:placetype":"locality"
},
  "geometry": {"coordinates":[101.636,38.2237],"type":"Point"}
}