{
  "type": "Feature",
  "properties": {
    "gn:admin1_code":"2.0",
    "gn:asciiname":"Dashanwei",
    "gn:country_code":"CN",
    "gn:dem":268,
    "gn:feature_class":"P",
    "gn:feature_code":"PPL",
    "gn:name":"Dashanwei",
    "gn:population":0,
    "gn:timezone":"Asia/Shanghai",
    "iso:country":"CN",
    "name:zho_x_preferred":[
        "\u5927\u5c71\u5c3e"
    ],
    "wof:name":"Dashanwei",
    "wof:placetype":"locality"
},
  "geometry": {"coordinates":[118.52323,29.05539000000001],"type":"Point"}
}