{
  "type": "Feature",
  "properties": {
    "gn:admin1_code":"8.0",
    "gn:asciiname":"Zhangjiayoufang",
    "gn:country_code":"CN",
    "gn:dem":196,
    "gn:feature_class":"P",
    "gn:feature_code":"PPL",
    "gn:name":"Zhangjiayoufang",
    "gn:population":0,
    "gn:timezone":"Asia/Shanghai",
    "iso:country":"CN",
    "name:zho_x_preferred":[
        "\u5f20\u5bb6\u6cb9\u623f"
    ],
    "wof:name":"Zhangjiayoufang",
    "wof:placetype":"locality"
},
  "geometry": {"coordinates":[123.06167000000001,46.81038],"type":"Point"}
}