{
  "type": "Feature",
  "properties": {
    "gn:admin1_code":"18.0",
    "gn:asciiname":"Datiechong",
    "gn:country_code":"CN",
    "gn:dem":1211,
    "gn:feature_class":"P",
    "gn:feature_code":"PPL",
    "gn:name":"Datiechong",
    "gn:population":0,
    "gn:timezone":"Asia/Shanghai",
    "iso:country":"CN",
    "name:zho_x_preferred":[
        "\u6253\u94c1\u51b2"
    ],
    "wof:name":"Datiechong",
    "wof:placetype":"locality"
},
  "geometry": {"coordinates":[107.41800000000001,26.8273],"type":"Point"}
}