{
  "type": "Feature",
  "properties": {
    "gn:admin1_code":"15.0",
    "gn:asciiname":"Yudachuan",
    "gn:country_code":"CN",
    "gn:dem":1797,
    "gn:feature_class":"P",
    "gn:feature_code":"PPL",
    "gn:name":"Yudachuan",
    "gn:population":0,
    "gn:timezone":"Asia/Shanghai",
    "iso:country":"CN",
    "name:zho_x_preferred":[
        "\u4e8e\u5927\u5ddd"
    ],
    "wof:name":"Yudachuan",
    "wof:placetype":"locality"
},
  "geometry": {"coordinates":[104.78,36.9621],"type":"Point"}
}