{
  "type": "Feature",
  "properties": {
    "gn:admin1_code":"25",
    "gn:asciiname":"Taizhuang",
    "gn:country_code":"CN",
    "gn:dem":109,
    "gn:feature_class":"P",
    "gn:feature_code":"PPL",
    "gn:name":"Taizhuang",
    "gn:population":0,
    "gn:timezone":"Asia/Shanghai",
    "iso:country":"CN",
    "name:zho_x_preferred":[
        "\u53f0\u5e84"
    ],
    "wof:name":"Taizhuang",
    "wof:placetype":"locality"
},
  "geometry": {"coordinates":[117.869,34.9854],"type":"Point"}
}