{
  "type": "Feature",
  "properties": {
    "gn:admin1_code":"26.0",
    "gn:asciiname":"Xihekou",
    "gn:cc2":"CN",
    "gn:country_code":"CN",
    "gn:dem":1234,
    "gn:feature_class":"P",
    "gn:feature_code":"PPL",
    "gn:name":"Xihekou",
    "gn:population":0,
    "gn:timezone":"Asia/Shanghai",
    "iso:country":"CN",
    "name:und_x_variant":[
        "Hsi-ho-k\u2019ou",
        "Xihe",
        "Xihekou"
    ],
    "wof:name":"Xihekou",
    "wof:placetype":"locality"
},
  "geometry": {"coordinates":[107.12833000000001,32.69333],"type":"Point"}
}