{
  "type": "Feature",
  "properties": {
    "gn:admin1_code":"32.0",
    "gn:asciiname":"Shengdeng",
    "gn:country_code":"CN",
    "gn:dem":499,
    "gn:feature_class":"P",
    "gn:feature_code":"PPL",
    "gn:name":"Shengdeng",
    "gn:population":0,
    "gn:timezone":"Asia/Shanghai",
    "iso:country":"CN",
    "name:zho_x_preferred":[
        "\u5723\u706f"
    ],
    "wof:name":"Shengdeng",
    "wof:placetype":"locality"
},
  "geometry": {"coordinates":[104.12824000000001,30.68366],"type":"Point"}
}