{
  "type": "Feature",
  "properties": {
    "gn:admin1_code":"30",
    "gn:asciiname":"Yinkengzai",
    "gn:country_code":"CN",
    "gn:dem":272,
    "gn:feature_class":"P",
    "gn:feature_code":"PPL",
    "gn:name":"Yinkengzai",
    "gn:population":0,
    "gn:timezone":"Asia/Shanghai",
    "iso:country":"CN",
    "name:zho_x_preferred":[
        "\u94f6\u5751\u4ed4"
    ],
    "wof:name":"Yinkengzai",
    "wof:placetype":"locality"
},
  "geometry": {"coordinates":[111.54322000000001,22.28698],"type":"Point"}
}