{
  "type": "Feature",
  "properties": {
    "gn:admin1_code":"3.0",
    "gn:asciiname":"Beihukou",
    "gn:country_code":"CN",
    "gn:dem":16,
    "gn:feature_class":"P",
    "gn:feature_code":"PPL",
    "gn:name":"Beihukou",
    "gn:population":0,
    "gn:timezone":"Asia/Shanghai",
    "iso:country":"CN",
    "name:und_x_variant":[
        "\u5317\u6e56\u53e3"
    ],
    "wof:name":"Beihukou",
    "wof:placetype":"locality"
},
  "geometry": {"coordinates":[116.20265000000001,28.71207],"type":"Point"}
}