{
  "type": "Feature",
  "properties": {
    "gn:admin1_code":"7.0",
    "gn:asciiname":"Yuefengcun",
    "gn:country_code":"CN",
    "gn:dem":17,
    "gn:feature_class":"P",
    "gn:feature_code":"PPL",
    "gn:name":"Yuefengcun",
    "gn:population":0,
    "gn:timezone":"Asia/Shanghai",
    "iso:country":"CN",
    "name:und_x_variant":[
        "\u5cb3\u5cf0\u6751"
    ],
    "name:zho_x_preferred":[
        "Yuefengcun"
    ],
    "wof:name":"Yuefengcun",
    "wof:placetype":"locality"
},
  "geometry": {"coordinates":[119.32599999999999,26.09052],"type":"Point"}
}