{
  "type": "Feature",
  "properties": {
    "gn:admin1_code":"32.0",
    "gn:asciiname":"Huixian",
    "gn:country_code":"CN",
    "gn:dem":473,
    "gn:feature_class":"P",
    "gn:feature_code":"PPL",
    "gn:name":"Huixian",
    "gn:population":0,
    "gn:timezone":"Asia/Shanghai",
    "iso:country":"CN",
    "name:deu_x_preferred":[
        "Huixian"
    ],
    "name:fra_x_preferred":[
        "Huixian"
    ],
    "name:hak_x_preferred":[
        "F\u00ee-yen"
    ],
    "name:ita_x_preferred":[
        "Huixian"
    ],
    "name:jpn_x_preferred":[
        "\u8f1d\u770c\u5e02"
    ],
    "name:kik_x_preferred":[
        "Huixian"
    ],
    "name:kor_x_preferred":[
        "\ud6c4\uc774\uc174\uc2dc"
    ],
    "name:mlg_x_preferred":[
        "Huixian"
    ],
    "name:nld_x_preferred":[
        "Huixian"
    ],
    "name:nor_x_preferred":[
        "Huixian"
    ],
    "name:pam_x_preferred":[
        "Huixian"
    ],
    "name:pol_x_preferred":[
        "Huixian"
    ],
    "name:rus_x_preferred":[
        "\u0425\u0443\u044d\u0439\u0441\u044f\u043d\u044c"
    ],
    "name:swe_x_preferred":[
        "Huixian"
    ],
    "name:vie_x_preferred":[
        "Huy Huy\u1ec7n"
    ],
    "name:war_x_preferred":[
        "Huixian"
    ],
    "name:zho_x_preferred":[
        "\u4f1a\u8d24"
    ],
    "name:zho_x_variant":[
        "\u8f89\u53bf\u5e02"
    ],
    "wof:name":"Huixian",
    "wof:placetype":"locality"
},
  "geometry": {"coordinates":[105.55500000000001,28.4949],"type":"Point"}
}