{
  "type": "Feature",
  "properties": {
    "gn:admin1_code":"5.0",
    "gn:asciiname":"Fenglincun",
    "gn:country_code":"CN",
    "gn:dem":236,
    "gn:feature_class":"P",
    "gn:feature_code":"PPL",
    "gn:name":"Fenglincun",
    "gn:population":0,
    "gn:timezone":"Asia/Shanghai",
    "iso:country":"CN",
    "name:und_x_variant":[
        "\u51e4\u6797\u6751"
    ],
    "wof:name":"Fenglincun",
    "wof:placetype":"locality"
},
  "geometry": {"coordinates":[129.42042000000001,42.84846],"type":"Point"}
}