{
  "type": "Feature",
  "properties": {
    "gn:admin1_code":"03",
    "gn:asciiname":"Hongjiang",
    "gn:country_code":"CN",
    "gn:dem":237,
    "gn:feature_class":"P",
    "gn:feature_code":"PPLA4",
    "gn:name":"Hongjiang",
    "gn:population":0,
    "gn:timezone":"Asia/Shanghai",
    "iso:country":"CN",
    "name:ceb_x_preferred":[
        "Hongjiang"
    ],
    "name:deu_x_preferred":[
        "Hongjiang"
    ],
    "name:fra_x_preferred":[
        "Hongjiang"
    ],
    "name:ita_x_preferred":[
        "Hongjiang"
    ],
    "name:jpn_x_preferred":[
        "\u6d2a\u6c5f\u5e02"
    ],
    "name:kik_x_preferred":[
        "Hongjiang"
    ],
    "name:kor_x_preferred":[
        "\ud6d9\uc7a5\uc2dc"
    ],
    "name:mlg_x_preferred":[
        "Hongjiang"
    ],
    "name:nld_x_preferred":[
        "Hongjiang"
    ],
    "name:nor_x_preferred":[
        "Hongjiang"
    ],
    "name:pam_x_preferred":[
        "Hongjiang"
    ],
    "name:swe_x_preferred":[
        "Hongjiang"
    ],
    "name:und_x_variant":[
        "Hung-chiang",
        "Hongjiang",
        "\u6d2a\u6c5f",
        "Hongjiang Xiang",
        "\u6d2a\u6c5f\u4e61"
    ],
    "name:vie_x_preferred":[
        "H\u1ed3ng Giang"
    ],
    "name:zho_x_preferred":[
        "\u6d2a\u6c5f\u5e02"
    ],
    "wof:name":"Hongjiang",
    "wof:placetype":"locality"
},
  "geometry": {"coordinates":[114.39292,27.62027],"type":"Point"}
}