{
  "type": "Feature",
  "properties": {
    "gn:admin1_code":"18",
    "gn:asciiname":"Xiaodong",
    "gn:country_code":"CN",
    "gn:dem":1751,
    "gn:feature_class":"P",
    "gn:feature_code":"PPL",
    "gn:name":"Xiaodong",
    "gn:population":0,
    "gn:timezone":"Asia/Shanghai",
    "iso:country":"CN",
    "name:zho_x_preferred":[
        "\u5c0f\u6d1e"
    ],
    "wof:name":"Xiaodong",
    "wof:placetype":"locality"
},
  "geometry": {"coordinates":[105.712,27.422],"type":"Point"}
}