{
  "type": "Feature",
  "properties": {
    "gn:admin1_code":"9",
    "gn:asciiname":"Donggangtou",
    "gn:country_code":"CN",
    "gn:dem":73,
    "gn:feature_class":"P",
    "gn:feature_code":"PPL",
    "gn:name":"Donggangtou",
    "gn:population":0,
    "gn:timezone":"Asia/Shanghai",
    "iso:country":"CN",
    "name:zho_x_preferred":[
        "\u4e1c\u5c97\u5934"
    ],
    "wof:name":"Donggangtou",
    "wof:placetype":"locality"
},
  "geometry": {"coordinates":[114.877,34.8128],"type":"Point"}
}