{
  "type": "Feature",
  "properties": {
    "gn:admin1_code":"24.0",
    "gn:asciiname":"Jiazhaocun",
    "gn:country_code":"CN",
    "gn:dem":758,
    "gn:feature_class":"P",
    "gn:feature_code":"PPL",
    "gn:name":"Jiazhaocun",
    "gn:population":0,
    "gn:timezone":"Asia/Shanghai",
    "iso:country":"CN",
    "name:zho_x_preferred":[
        "\u8d3e\u5146\u6751"
    ],
    "wof:name":"Jiazhaocun",
    "wof:placetype":"locality"
},
  "geometry": {"coordinates":[112.26539,37.57204],"type":"Point"}
}