{
  "type": "Feature",
  "properties": {
    "gn:admin1_code":"16",
    "gn:asciiname":"Longshui",
    "gn:cc2":"CN",
    "gn:country_code":"CN",
    "gn:dem":183,
    "gn:feature_class":"P",
    "gn:feature_code":"PPL",
    "gn:name":"Longshui",
    "gn:population":0,
    "gn:timezone":"Asia/Shanghai",
    "iso:country":"CN",
    "name:und_x_variant":[
        "Lung-shui",
        "Longshui"
    ],
    "wof:name":"Longshui",
    "wof:placetype":"locality"
},
  "geometry": {"coordinates":[110.99417,26.04056],"type":"Point"}
}