{
  "type": "Feature",
  "properties": {
    "gn:admin1_code":"15.0",
    "gn:asciiname":"Shijiaying",
    "gn:country_code":"CN",
    "gn:dem":2379,
    "gn:feature_class":"P",
    "gn:feature_code":"PPL",
    "gn:name":"Shijiaying",
    "gn:population":0,
    "gn:timezone":"Asia/Shanghai",
    "iso:country":"CN",
    "name:zho_x_preferred":[
        "\u77f3\u5bb6\u8425"
    ],
    "wof:name":"Shijiaying",
    "wof:placetype":"locality"
},
  "geometry": {"coordinates":[104.005,35.14],"type":"Point"}
}