{
  "type": "Feature",
  "properties": {
    "gn:admin1_code":"26.0",
    "gn:asciiname":"Dongwangjia Guacun",
    "gn:country_code":"CN",
    "gn:dem":954,
    "gn:feature_class":"P",
    "gn:feature_code":"PPL",
    "gn:name":"Dongwangjia Guacun",
    "gn:population":0,
    "gn:timezone":"Asia/Shanghai",
    "iso:country":"CN",
    "name:zho_x_preferred":[
        "\u4e1c\u738b\u5bb6\u576c\u6751"
    ],
    "wof:name":"Dongwangjia Guacun",
    "wof:placetype":"locality"
},
  "geometry": {"coordinates":[110.526,37.2339],"type":"Point"}
}