{
  "type": "Feature",
  "properties": {
    "gn:admin1_code":"14.0",
    "gn:asciiname":"Yingda",
    "gn:country_code":"CN",
    "gn:dem":5005,
    "gn:feature_class":"P",
    "gn:feature_code":"PPL",
    "gn:name":"Yingda",
    "gn:population":0,
    "gn:timezone":"Asia/Urumqi",
    "iso:country":"CN",
    "name:bod_x_preferred":[
        "Y\u00eanda"
    ],
    "name:zho_x_preferred":[
        "Yingda"
    ],
    "name:zho_x_variant":[
        "\u82f1\u8fbe",
        "Yiba Gongshe",
        "\u4f9d\u5df4\u516c\u793e"
    ],
    "wof:name":"Yingda",
    "wof:placetype":"locality"
},
  "geometry": {"coordinates":[94.301,31.601],"type":"Point"}
}