{
  "type": "Feature",
  "properties": {
    "gn:admin1_code":"32.0",
    "gn:asciiname":"Huangjuewan",
    "gn:country_code":"CN",
    "gn:dem":472,
    "gn:feature_class":"P",
    "gn:feature_code":"PPL",
    "gn:name":"Huangjuewan",
    "gn:population":0,
    "gn:timezone":"Asia/Shanghai",
    "iso:country":"CN",
    "name:zho_x_preferred":[
        "\u9ec4\u6877\u5f2f"
    ],
    "wof:name":"Huangjuewan",
    "wof:placetype":"locality"
},
  "geometry": {"coordinates":[104.98,28.3976],"type":"Point"}
}