{
  "type": "Feature",
  "properties": {
    "gn:admin1_code":"19",
    "gn:asciiname":"Pien-shih-ha-ta",
    "gn:country_code":"CN",
    "gn:dem":382,
    "gn:feature_class":"P",
    "gn:feature_code":"PPL",
    "gn:name":"Pien-shih-ha-ta",
    "gn:population":0,
    "gn:timezone":"Asia/Shanghai",
    "iso:country":"CN",
    "wof:name":"Pien-shih-ha-ta",
    "wof:placetype":"locality"
},
  "geometry": {"coordinates":[125.37721999999999,41.41056],"type":"Point"}
}