{
  "type": "Feature",
  "properties": {
    "gn:admin1_code":"4.0",
    "gn:asciiname":"Xiaoxingzhuang",
    "gn:country_code":"CN",
    "gn:dem":4,
    "gn:feature_class":"P",
    "gn:feature_code":"PPL",
    "gn:name":"Xiaoxingzhuang",
    "gn:population":0,
    "gn:timezone":"Asia/Shanghai",
    "iso:country":"CN",
    "name:zho_x_preferred":[
        "Xiaoxingzhuang"
    ],
    "name:zho_x_variant":[
        "\u5c0f\u661f\u5e84"
    ],
    "wof:name":"Xiaoxingzhuang",
    "wof:placetype":"locality"
},
  "geometry": {"coordinates":[119.90581,34.0751],"type":"Point"}
}