{
  "type": "Feature",
  "properties": {
    "gn:admin1_code":"12.0",
    "gn:asciiname":"Manlihai",
    "gn:country_code":"CN",
    "gn:dem":112,
    "gn:feature_class":"P",
    "gn:feature_code":"PPL",
    "gn:name":"Manlihai",
    "gn:population":0,
    "gn:timezone":"Asia/Shanghai",
    "iso:country":"CN",
    "name:zho_x_preferred":[
        "\u86ee\u529b\u6d77"
    ],
    "wof:name":"Manlihai",
    "wof:placetype":"locality"
},
  "geometry": {"coordinates":[112.53751,31.7453],"type":"Point"}
}