{
  "type": "Feature",
  "properties": {
    "gn:admin1_code":"15.0",
    "gn:asciiname":"Tajiayuan",
    "gn:country_code":"CN",
    "gn:dem":2060,
    "gn:feature_class":"P",
    "gn:feature_code":"PPL",
    "gn:name":"Tajiayuan",
    "gn:population":0,
    "gn:timezone":"Asia/Shanghai",
    "iso:country":"CN",
    "name:zho_x_preferred":[
        "\u4ed6\u5bb6\u586c"
    ],
    "wof:name":"Tajiayuan",
    "wof:placetype":"locality"
},
  "geometry": {"coordinates":[103.321,35.8649],"type":"Point"}
}