{
  "type": "Feature",
  "properties": {
    "gn:admin1_code":"25",
    "gn:asciiname":"Luantun",
    "gn:country_code":"CN",
    "gn:dem":41,
    "gn:feature_class":"P",
    "gn:feature_code":"PPL",
    "gn:name":"Luantun",
    "gn:population":0,
    "gn:timezone":"Asia/Shanghai",
    "iso:country":"CN",
    "name:zho_x_preferred":[
        "\u683e\u5c6f"
    ],
    "wof:name":"Luantun",
    "wof:placetype":"locality"
},
  "geometry": {"coordinates":[115.64986,36.10603],"type":"Point"}
}