{
  "type": "Feature",
  "properties": {
    "gn:admin1_code":"30",
    "gn:asciiname":"Tanbeihu",
    "gn:country_code":"CN",
    "gn:dem":17,
    "gn:feature_class":"P",
    "gn:feature_code":"PPL",
    "gn:name":"Tanbeihu",
    "gn:population":0,
    "gn:timezone":"Asia/Urumqi",
    "iso:country":"CN",
    "name:und_x_variant":[
        "T\u2019an-pei-hu",
        "\u6f6d\u5317\u6e56",
        "Tanbeihu"
    ],
    "wof:name":"Tanbeihu",
    "wof:placetype":"locality"
},
  "geometry": {"coordinates":[110.62588,20.93233],"type":"Point"}
}