{
  "type": "Feature",
  "properties": {
    "gn:admin1_code":"31.0",
    "gn:asciiname":"Xianfengdui",
    "gn:country_code":"CN",
    "gn:dem":178,
    "gn:feature_class":"P",
    "gn:feature_code":"PPL",
    "gn:name":"Xianfengdui",
    "gn:population":0,
    "gn:timezone":"Asia/Shanghai",
    "iso:country":"CN",
    "name:zho_x_preferred":[
        "\u5148\u950b\u961f"
    ],
    "wof:name":"Xianfengdui",
    "wof:placetype":"locality"
},
  "geometry": {"coordinates":[110.18640000000001,19.04151],"type":"Point"}
}