{
  "type": "Feature",
  "properties": {
    "gn:admin1_code":"15.0",
    "gn:asciiname":"Wangjiachuan",
    "gn:country_code":"CN",
    "gn:dem":1676,
    "gn:feature_class":"P",
    "gn:feature_code":"PPL",
    "gn:name":"Wangjiachuan",
    "gn:population":0,
    "gn:timezone":"Asia/Shanghai",
    "iso:country":"CN",
    "name:zho_x_preferred":[
        "\u6c6a\u5bb6\u5ddd"
    ],
    "wof:name":"Wangjiachuan",
    "wof:placetype":"locality"
},
  "geometry": {"coordinates":[104.411,36.6931],"type":"Point"}
}