{
  "type": "Feature",
  "properties": {
    "gn:admin1_code":"18",
    "gn:asciiname":"Pinglu",
    "gn:country_code":"CN",
    "gn:dem":633,
    "gn:feature_class":"P",
    "gn:feature_code":"PPL",
    "gn:name":"Pinglu",
    "gn:population":0,
    "gn:timezone":"Asia/Shanghai",
    "iso:country":"CN",
    "name:deu_x_preferred":[
        "Pinglu"
    ],
    "name:swe_x_preferred":[
        "Pinglu"
    ],
    "name:zho_x_preferred":[
        "\u576a\u8def"
    ],
    "wof:name":"Pinglu",
    "wof:placetype":"locality"
},
  "geometry": {"coordinates":[105.77500000000001,25.3228],"type":"Point"}
}