{
  "type": "Feature",
  "properties": {
    "gn:admin1_code":"11.0",
    "gn:asciiname":"Wanqiaozi",
    "gn:country_code":"CN",
    "gn:dem":42,
    "gn:feature_class":"P",
    "gn:feature_code":"PPL",
    "gn:name":"Wanqiaozi",
    "gn:population":0,
    "gn:timezone":"Asia/Shanghai",
    "iso:country":"CN",
    "name:zho_x_preferred":[
        "\u6e7e\u6865\u5b50"
    ],
    "wof:name":"Wanqiaozi",
    "wof:placetype":"locality"
},
  "geometry": {"coordinates":[112.92089,27.91613],"type":"Point"}
}