{
  "type": "Feature",
  "properties": {
    "gn:admin1_code":"29.0",
    "gn:asciiname":"Sila",
    "gn:country_code":"CN",
    "gn:dem":1591,
    "gn:feature_class":"P",
    "gn:feature_code":"PPL",
    "gn:name":"Sila",
    "gn:population":0,
    "gn:timezone":"Asia/Shanghai",
    "iso:country":"CN",
    "name:bul_x_preferred":[
        "\u0421\u0438\u043b\u0430"
    ],
    "name:cat_x_preferred":[
        "Sila"
    ],
    "name:ceb_x_preferred":[
        "Sila"
    ],
    "name:dan_x_preferred":[
        "Sila"
    ],
    "name:deu_x_preferred":[
        "Sila"
    ],
    "name:fra_x_preferred":[
        "Sila"
    ],
    "name:hrv_x_preferred":[
        "Sila"
    ],
    "name:ita_x_preferred":[
        "Sila"
    ],
    "name:nld_x_preferred":[
        "Sila"
    ],
    "name:pol_x_preferred":[
        "Sila"
    ],
    "name:por_x_preferred":[
        "Sila"
    ],
    "name:rus_x_preferred":[
        "\u0421\u0438\u043b\u0430"
    ],
    "name:slk_x_preferred":[
        "Sila"
    ],
    "name:slv_x_preferred":[
        "Sila"
    ],
    "name:spa_x_preferred":[
        "Sila"
    ],
    "name:srp_x_preferred":[
        "Sila"
    ],
    "name:swe_x_preferred":[
        "Sila"
    ],
    "name:ukr_x_preferred":[
        "\u0421\u0438\u043b\u0430"
    ],
    "name:zho_x_preferred":[
        "\u601d\u814a"
    ],
    "wof:name":"Sila",
    "wof:placetype":"locality"
},
  "geometry": {"coordinates":[99.03700000000001,24.7405],"type":"Point"}
}