{
  "type": "Feature",
  "properties": {
    "gn:admin1_code":"9.0",
    "gn:asciiname":"Taoyuan",
    "gn:country_code":"CN",
    "gn:dem":149,
    "gn:feature_class":"P",
    "gn:feature_code":"PPL",
    "gn:name":"Taoyuan",
    "gn:population":0,
    "gn:timezone":"Asia/Shanghai",
    "iso:country":"CN",
    "name:ben_x_preferred":[
        "\u09a4\u09be\u09df\u09cb\u0987\u0989\u09df\u09be\u09a8"
    ],
    "name:ceb_x_preferred":[
        "Taoyuan"
    ],
    "name:deu_x_preferred":[
        "Taoyuan"
    ],
    "name:ell_x_preferred":[
        "\u03a4\u03b1\u03bf\u03b3\u03bf\u03c5\u03ac\u03bd"
    ],
    "name:fas_x_preferred":[
        "\u062a\u0648\u0626\u0627\u06cc\u0648\u0622\u0646"
    ],
    "name:fra_x_preferred":[
        "Taoyuan"
    ],
    "name:heb_x_preferred":[
        "\u05d8\u05d0\u05d5\u05d9\u05d5\u05d0\u05df"
    ],
    "name:hin_x_preferred":[
        "\u0924\u093e\u0913\u092f\u0941\u0906\u0928"
    ],
    "name:hun_x_preferred":[
        "Taoyuan"
    ],
    "name:ind_x_preferred":[
        "Taoyuan"
    ],
    "name:kor_x_preferred":[
        "\ud0c0\uc624\uc704\uc548"
    ],
    "name:lit_x_preferred":[
        "Taojuanas"
    ],
    "name:nld_x_preferred":[
        "Taoyuan"
    ],
    "name:nor_x_preferred":[
        "Taoyuan"
    ],
    "name:por_x_preferred":[
        "Taoyuan"
    ],
    "name:tur_x_preferred":[
        "Taoyuan"
    ],
    "name:vie_x_preferred":[
        "\u0110\u00e0o Vi\u00ean"
    ],
    "name:zho_x_preferred":[
        "\u6843\u56ed"
    ],
    "name:zho_x_variant":[
        "\u6843\u5712"
    ],
    "wof:name":"Taoyuan",
    "wof:placetype":"locality"
},
  "geometry": {"coordinates":[112.81189000000001,33.16029],"type":"Point"}
}