{
  "type": "Feature",
  "properties": {
    "gn:admin1_code":"29.0",
    "gn:asciiname":"Shangmiao",
    "gn:country_code":"CN",
    "gn:dem":1550,
    "gn:feature_class":"P",
    "gn:feature_code":"PPL",
    "gn:name":"Shangmiao",
    "gn:population":0,
    "gn:timezone":"Asia/Shanghai",
    "iso:country":"CN",
    "name:zho_x_preferred":[
        "\u4e0a\u5e99"
    ],
    "wof:name":"Shangmiao",
    "wof:placetype":"locality"
},
  "geometry": {"coordinates":[99.4015,24.9745],"type":"Point"}
}