{
  "type": "Feature",
  "properties": {
    "gn:admin1_code":"8.0",
    "gn:asciiname":"Tianjinzi",
    "gn:country_code":"CN",
    "gn:dem":152,
    "gn:feature_class":"P",
    "gn:feature_code":"PPL",
    "gn:name":"Tianjinzi",
    "gn:population":0,
    "gn:timezone":"Asia/Shanghai",
    "iso:country":"CN",
    "name:zho_x_preferred":[
        "\u5929\u6d25\u5b57"
    ],
    "wof:name":"Tianjinzi",
    "wof:placetype":"locality"
},
  "geometry": {"coordinates":[123.04143000000001,46.47421],"type":"Point"}
}