{
  "type": "Feature",
  "properties": {
    "gn:admin1_code":"26.0",
    "gn:asciiname":"Lingtouziyuan",
    "gn:country_code":"CN",
    "gn:dem":1157,
    "gn:feature_class":"P",
    "gn:feature_code":"PPL",
    "gn:name":"Lingtouziyuan",
    "gn:population":0,
    "gn:timezone":"Asia/Shanghai",
    "iso:country":"CN",
    "name:zho_x_preferred":[
        "\u5cad\u5934\u5b50\u586c"
    ],
    "wof:name":"Lingtouziyuan",
    "wof:placetype":"locality"
},
  "geometry": {"coordinates":[109.94774,36.71024],"type":"Point"}
}