{
  "type": "Feature",
  "properties": {
    "gn:admin1_code":"32.0",
    "gn:asciiname":"Nanmu",
    "gn:country_code":"CN",
    "gn:dem":782,
    "gn:feature_class":"P",
    "gn:feature_code":"PPL",
    "gn:name":"Nanmu",
    "gn:population":0,
    "gn:timezone":"Asia/Shanghai",
    "iso:country":"CN",
    "name:und_x_variant":[
        "\u6960\u6728"
    ],
    "wof:name":"Nanmu",
    "wof:placetype":"locality"
},
  "geometry": {"coordinates":[106.65593,32.39342],"type":"Point"}
}