{
  "type": "Feature",
  "properties": {
    "gn:admin1_code":"2.0",
    "gn:asciiname":"Xinwo",
    "gn:country_code":"CN",
    "gn:dem":302,
    "gn:feature_class":"P",
    "gn:feature_code":"PPLA4",
    "gn:name":"Xinwo",
    "gn:population":0,
    "gn:timezone":"Asia/Shanghai",
    "iso:country":"CN",
    "name:und_x_variant":[
        "Hsin-wo",
        "Xinwo",
        "Xinwo Zhen"
    ],
    "name:zho_x_preferred":[
        "\u65b0\u6e25"
    ],
    "name:zho_x_variant":[
        "\u65b0\u6e25\u9547"
    ],
    "wof:name":"Xinwo",
    "wof:placetype":"locality"
},
  "geometry": {"coordinates":[120.37412,28.9484],"type":"Point"}
}