{
  "type": "Feature",
  "properties": {
    "gn:admin1_code":"26",
    "gn:asciiname":"Haizetan",
    "gn:cc2":"CN",
    "gn:country_code":"CN",
    "gn:dem":1325,
    "gn:feature_class":"P",
    "gn:feature_code":"PPL",
    "gn:name":"Haizetan",
    "gn:population":0,
    "gn:timezone":"Asia/Shanghai",
    "iso:country":"CN",
    "name:und_x_variant":[
        "Hai-tse-t\u2019an",
        "Haizetan"
    ],
    "wof:name":"Haizetan",
    "wof:placetype":"locality"
},
  "geometry": {"coordinates":[108.88333,37.75],"type":"Point"}
}