{
  "type": "Feature",
  "properties": {
    "gn:admin1_code":"18",
    "gn:asciiname":"Baijiazhai",
    "gn:country_code":"CN",
    "gn:dem":1249,
    "gn:feature_class":"P",
    "gn:feature_code":"PPL",
    "gn:name":"Baijiazhai",
    "gn:population":0,
    "gn:timezone":"Asia/Shanghai",
    "iso:country":"CN",
    "name:zho_x_preferred":[
        "\u767d\u5bb6\u5be8"
    ],
    "wof:name":"Baijiazhai",
    "wof:placetype":"locality"
},
  "geometry": {"coordinates":[106.33199999999999,27.1469],"type":"Point"}
}