{
  "type": "Feature",
  "properties": {
    "gn:admin1_code":"13.0",
    "gn:asciiname":"Agaqi Kelangan",
    "gn:country_code":"CN",
    "gn:dem":2089,
    "gn:feature_class":"P",
    "gn:feature_code":"PPL",
    "gn:name":"Agaqi Kelangan",
    "gn:population":0,
    "gn:timezone":"Asia/Shanghai",
    "iso:country":"CN",
    "name:zho_x_preferred":[
        "\u963f\u5c15\u5176\u514b\u5170\u5e72"
    ],
    "wof:name":"Agaqi Kelangan",
    "wof:placetype":"locality"
},
  "geometry": {"coordinates":[80.84756,36.40717],"type":"Point"}
}