{
  "type": "Feature",
  "properties": {
    "gn:admin1_code":"9.0",
    "gn:asciiname":"Qingshipo",
    "gn:country_code":"CN",
    "gn:dem":271,
    "gn:feature_class":"P",
    "gn:feature_code":"PPL",
    "gn:name":"Qingshipo",
    "gn:population":0,
    "gn:timezone":"Asia/Shanghai",
    "iso:country":"CN",
    "name:und_x_variant":[
        "\u9752\u77f3\u5761",
        "Qingshipo"
    ],
    "wof:name":"Qingshipo",
    "wof:placetype":"locality"
},
  "geometry": {"coordinates":[112.88572000000001,33.38608],"type":"Point"}
}