{
  "type": "Feature",
  "properties": {
    "gn:admin1_code":"14.0",
    "gn:asciiname":"Oma",
    "gn:country_code":"CN",
    "gn:dem":4447,
    "gn:feature_class":"P",
    "gn:feature_code":"PPLF",
    "gn:name":"Oma",
    "gn:population":0,
    "gn:timezone":"Asia/Urumqi",
    "iso:country":"CN",
    "name:bod_x_preferred":[
        "Oma"
    ],
    "name:zho_x_preferred":[
        "Wuma"
    ],
    "name:zho_x_variant":[
        "\u7269\u739b",
        "Chaguo",
        "\u8336\u679c"
    ],
    "wof:name":"Oma",
    "wof:placetype":"locality"
},
  "geometry": {"coordinates":[83.23350000000001,32.42658],"type":"Point"}
}