{
  "type": "Feature",
  "properties": {
    "gn:admin1_code":"32.0",
    "gn:asciiname":"Shangqiliqiao",
    "gn:country_code":"CN",
    "gn:dem":315,
    "gn:feature_class":"P",
    "gn:feature_code":"PPL",
    "gn:name":"Shangqiliqiao",
    "gn:population":0,
    "gn:timezone":"Asia/Shanghai",
    "iso:country":"CN",
    "name:zho_x_preferred":[
        "\u4e0a\u4e03\u91cc\u6865"
    ],
    "wof:name":"Shangqiliqiao",
    "wof:placetype":"locality"
},
  "geometry": {"coordinates":[105.52466,30.50656],"type":"Point"}
}