{
  "type": "Feature",
  "properties": {
    "gn:admin1_code":"18.0",
    "gn:asciiname":"Zhanjia",
    "gn:country_code":"CN",
    "gn:dem":516,
    "gn:feature_class":"P",
    "gn:feature_code":"PPL",
    "gn:name":"Zhanjia",
    "gn:population":0,
    "gn:timezone":"Asia/Shanghai",
    "iso:country":"CN",
    "name:zho_x_preferred":[
        "\u5c55\u67b6"
    ],
    "wof:name":"Zhanjia",
    "wof:placetype":"locality"
},
  "geometry": {"coordinates":[108.48699999999999,26.7445],"type":"Point"}
}