{
  "type": "Feature",
  "properties": {
    "gn:admin1_code":"2",
    "gn:asciiname":"Fangjun",
    "gn:country_code":"CN",
    "gn:dem":108,
    "gn:feature_class":"P",
    "gn:feature_code":"PPLA4",
    "gn:name":"Fangjun",
    "gn:population":0,
    "gn:timezone":"Asia/Shanghai",
    "iso:country":"CN",
    "name:und_x_variant":[
        "Fangjun Zhen",
        "\u9632\u519b\u9547"
    ],
    "name:zho_x_preferred":[
        "\u9632\u519b"
    ],
    "name:zho_x_variant":[
        "\u9632\u519b\u9547"
    ],
    "wof:name":"Fangjun",
    "wof:placetype":"locality"
},
  "geometry": {"coordinates":[120.245,29.07139],"type":"Point"}
}