{
  "type": "Feature",
  "properties": {
    "gn:admin1_code":"32.0",
    "gn:asciiname":"Maopingshang",
    "gn:country_code":"CN",
    "gn:dem":1108,
    "gn:feature_class":"P",
    "gn:feature_code":"PPL",
    "gn:name":"Maopingshang",
    "gn:population":0,
    "gn:timezone":"Asia/Shanghai",
    "iso:country":"CN",
    "name:zho_x_preferred":[
        "\u8305\u576a\u4e0a"
    ],
    "wof:name":"Maopingshang",
    "wof:placetype":"locality"
},
  "geometry": {"coordinates":[104.696,32.0362],"type":"Point"}
}