{
  "type": "Feature",
  "properties": {
    "gn:admin1_code":"24",
    "gn:asciiname":"Jijiatacun",
    "gn:country_code":"CN",
    "gn:dem":891,
    "gn:feature_class":"P",
    "gn:feature_code":"PPL",
    "gn:name":"Jijiatacun",
    "gn:population":0,
    "gn:timezone":"Asia/Shanghai",
    "iso:country":"CN",
    "name:und_x_variant":[
        "Chi-chia-t\u2019a",
        "Jijiata",
        "Jijiatacun"
    ],
    "name:zho_x_preferred":[
        "\u5409\u5bb6\u5854\u6751"
    ],
    "wof:name":"Jijiatacun",
    "wof:placetype":"locality"
},
  "geometry": {"coordinates":[110.86225,37.53481],"type":"Point"}
}