{
  "type": "Feature",
  "properties": {
    "gn:admin1_code":"19.0",
    "gn:asciiname":"Erqi Yingzicun",
    "gn:country_code":"CN",
    "gn:dem":151,
    "gn:feature_class":"P",
    "gn:feature_code":"PPL",
    "gn:name":"Erqi Yingzicun",
    "gn:population":0,
    "gn:timezone":"Asia/Shanghai",
    "iso:country":"CN",
    "name:und_x_variant":[
        "Erqiyingzicun",
        "Erqi Yingzicun"
    ],
    "name:zho_x_preferred":[
        "\u4e8c\u5176\u8425\u5b50\u6751"
    ],
    "wof:name":"Erqi Yingzicun",
    "wof:placetype":"locality"
},
  "geometry": {"coordinates":[120.48904,41.60504],"type":"Point"}
}