{
  "type": "Feature",
  "properties": {
    "gn:admin1_code":"16.0",
    "gn:asciiname":"Dongya",
    "gn:country_code":"CN",
    "gn:dem":264,
    "gn:feature_class":"P",
    "gn:feature_code":"PPL",
    "gn:name":"Dongya",
    "gn:population":0,
    "gn:timezone":"Asia/Shanghai",
    "iso:country":"CN",
    "name:zho_x_preferred":[
        "\u6d1e\u9e26"
    ],
    "wof:name":"Dongya",
    "wof:placetype":"locality"
},
  "geometry": {"coordinates":[106.45699999999999,23.9901],"type":"Point"}
}