{
  "type": "Feature",
  "properties": {
    "gn:admin1_code":"30.0",
    "gn:asciiname":"Genzhudong",
    "gn:country_code":"CN",
    "gn:dem":78,
    "gn:feature_class":"P",
    "gn:feature_code":"PPL",
    "gn:name":"Genzhudong",
    "gn:population":0,
    "gn:timezone":"Asia/Shanghai",
    "iso:country":"CN",
    "name:zho_x_preferred":[
        "\u6839\u7af9\u578c"
    ],
    "wof:name":"Genzhudong",
    "wof:placetype":"locality"
},
  "geometry": {"coordinates":[111.94342,22.13844],"type":"Point"}
}