{
  "type": "Feature",
  "properties": {
    "gn:admin1_code":"16.0",
    "gn:asciiname":"Kumachong",
    "gn:country_code":"CN",
    "gn:dem":225,
    "gn:feature_class":"P",
    "gn:feature_code":"PPL",
    "gn:name":"Kumachong",
    "gn:population":0,
    "gn:timezone":"Asia/Shanghai",
    "iso:country":"CN",
    "name:zho_x_preferred":[
        "\u82e6\u9ebb\u51b2"
    ],
    "wof:name":"Kumachong",
    "wof:placetype":"locality"
},
  "geometry": {"coordinates":[109.56,25.2527],"type":"Point"}
}