{
  "type": "Feature",
  "properties": {
    "gn:admin1_code":"26.0",
    "gn:asciiname":"Koujiacun",
    "gn:country_code":"CN",
    "gn:dem":465,
    "gn:feature_class":"P",
    "gn:feature_code":"PPL",
    "gn:name":"Koujiacun",
    "gn:population":0,
    "gn:timezone":"Asia/Shanghai",
    "iso:country":"CN",
    "name:zho_x_preferred":[
        "\u5bc7\u5bb6\u6751"
    ],
    "wof:name":"Koujiacun",
    "wof:placetype":"locality"
},
  "geometry": {"coordinates":[109.1323,34.23775999999999],"type":"Point"}
}