{
  "type": "Feature",
  "properties": {
    "gn:admin1_code":"11.0",
    "gn:asciiname":"Baotaiyuan",
    "gn:country_code":"CN",
    "gn:dem":34,
    "gn:feature_class":"P",
    "gn:feature_code":"PPL",
    "gn:name":"Baotaiyuan",
    "gn:population":0,
    "gn:timezone":"Asia/Shanghai",
    "iso:country":"CN",
    "name:zho_x_preferred":[
        "\u4fdd\u592a\u57b8"
    ],
    "wof:name":"Baotaiyuan",
    "wof:placetype":"locality"
},
  "geometry": {"coordinates":[112.21411000000001,29.43279],"type":"Point"}
}