{
  "type": "Feature",
  "properties": {
    "gn:admin1_code":"33.0",
    "gn:asciiname":"Tiancang",
    "gn:country_code":"CN",
    "gn:dem":1207,
    "gn:feature_class":"P",
    "gn:feature_code":"PPL",
    "gn:name":"Tiancang",
    "gn:population":0,
    "gn:timezone":"Asia/Shanghai",
    "iso:country":"CN",
    "name:zho_x_preferred":[
        "\u5929\u4ed3"
    ],
    "wof:name":"Tiancang",
    "wof:placetype":"locality"
},
  "geometry": {"coordinates":[108.88245999999999,29.07474],"type":"Point"}
}