{
  "type": "Feature",
  "properties": {
    "gn:admin1_code":"16.0",
    "gn:asciiname":"Tingsha",
    "gn:country_code":"CN",
    "gn:dem":141,
    "gn:feature_class":"P",
    "gn:feature_code":"PPL",
    "gn:name":"Tingsha",
    "gn:population":0,
    "gn:timezone":"Asia/Shanghai",
    "iso:country":"CN",
    "name:ces_x_preferred":[
        "Ting\u0161a"
    ],
    "name:deu_x_preferred":[
        "Tingsha"
    ],
    "name:nld_x_preferred":[
        "Tingsha"
    ],
    "name:zho_x_preferred":[
        "\u4ead\u6c99"
    ],
    "wof:name":"Tingsha",
    "wof:placetype":"locality"
},
  "geometry": {"coordinates":[107.133,22.3555],"type":"Point"}
}