{
  "type": "Feature",
  "properties": {
    "gn:admin1_code":"30",
    "gn:asciiname":"Daxincun",
    "gn:country_code":"CN",
    "gn:dem":192,
    "gn:feature_class":"P",
    "gn:feature_code":"PPL",
    "gn:name":"Daxincun",
    "gn:population":0,
    "gn:timezone":"Asia/Shanghai",
    "iso:country":"CN",
    "name:und_x_variant":[
        "\u9ec4\u6d1e"
    ],
    "name:zho_x_preferred":[
        "Huangdong"
    ],
    "name:zho_x_variant":[
        "\u5927\u65b0\u6751"
    ],
    "wof:name":"Daxincun",
    "wof:placetype":"locality"
},
  "geometry": {"coordinates":[115.52248,24.00509],"type":"Point"}
}