{
  "type": "Feature",
  "properties": {
    "gn:admin1_code":"2.0",
    "gn:asciiname":"Luzhai",
    "gn:country_code":"CN",
    "gn:dem":164,
    "gn:feature_class":"P",
    "gn:feature_code":"PPL",
    "gn:name":"Luzhai",
    "gn:population":0,
    "gn:timezone":"Asia/Shanghai",
    "iso:country":"CN",
    "name:und_x_variant":[
        "\u5362\u5b85"
    ],
    "wof:name":"Luzhai",
    "wof:placetype":"locality"
},
  "geometry": {"coordinates":[119.09730999999999,30.16865],"type":"Point"}
}