{
  "type": "Feature",
  "properties": {
    "gn:admin1_code":"24.0",
    "gn:asciiname":"Louzitiao",
    "gn:country_code":"CN",
    "gn:dem":1633,
    "gn:feature_class":"P",
    "gn:feature_code":"PPL",
    "gn:name":"Louzitiao",
    "gn:population":0,
    "gn:timezone":"Asia/Shanghai",
    "iso:country":"CN",
    "name:zho_x_preferred":[
        "\u5a04\u5b50\u6761"
    ],
    "wof:name":"Louzitiao",
    "wof:placetype":"locality"
},
  "geometry": {"coordinates":[112.06652,38.13697],"type":"Point"}
}