{
  "type": "Feature",
  "properties": {
    "gn:admin1_code":"15.0",
    "gn:asciiname":"Yuanyang Zhen",
    "gn:country_code":"CN",
    "gn:dem":1555,
    "gn:feature_class":"P",
    "gn:feature_code":"PPLA4",
    "gn:name":"Yuanyang Zhen",
    "gn:population":0,
    "gn:timezone":"Asia/Shanghai",
    "iso:country":"CN",
    "name:und_x_variant":[
        "\u9e33\u9e2f\u9547"
    ],
    "wof:name":"Yuanyang Zhen",
    "wof:placetype":"locality"
},
  "geometry": {"coordinates":[104.77531,34.78768],"type":"Point"}
}