{
  "type": "Feature",
  "properties": {
    "gn:admin1_code":"26.0",
    "gn:asciiname":"Shangxinzhuang",
    "gn:country_code":"CN",
    "gn:dem":1302,
    "gn:feature_class":"P",
    "gn:feature_code":"PPL",
    "gn:name":"Shangxinzhuang",
    "gn:population":0,
    "gn:timezone":"Asia/Shanghai",
    "iso:country":"CN",
    "name:zho_x_preferred":[
        "\u4e0a\u65b0\u5e84"
    ],
    "wof:name":"Shangxinzhuang",
    "wof:placetype":"locality"
},
  "geometry": {"coordinates":[109.04656,37.15993],"type":"Point"}
}