{
  "type": "Feature",
  "properties": {
    "gn:admin1_code":"11.0",
    "gn:asciiname":"Longjiali",
    "gn:country_code":"CN",
    "gn:dem":152,
    "gn:feature_class":"P",
    "gn:feature_code":"PPL",
    "gn:name":"Longjiali",
    "gn:population":0,
    "gn:timezone":"Asia/Shanghai",
    "iso:country":"CN",
    "name:zho_x_preferred":[
        "\u9f99\u7532\u91cc"
    ],
    "wof:name":"Longjiali",
    "wof:placetype":"locality"
},
  "geometry": {"coordinates":[113.60668,26.56589],"type":"Point"}
}