{
  "type": "Feature",
  "properties": {
    "gn:admin1_code":"10.0",
    "gn:asciiname":"Longquansi",
    "gn:country_code":"CN",
    "gn:dem":896,
    "gn:feature_class":"P",
    "gn:feature_code":"PPL",
    "gn:name":"Longquansi",
    "gn:population":0,
    "gn:timezone":"Asia/Shanghai",
    "iso:country":"CN",
    "name:zho_x_preferred":[
        "\u9f99\u6cc9\u5bfa"
    ],
    "wof:name":"Longquansi",
    "wof:placetype":"locality"
},
  "geometry": {"coordinates":[114.56923,40.63202],"type":"Point"}
}