{
  "type": "Feature",
  "properties": {
    "gn:admin1_code":"32.0",
    "gn:asciiname":"Fujia Yuanzi",
    "gn:country_code":"CN",
    "gn:dem":2313,
    "gn:feature_class":"P",
    "gn:feature_code":"PPL",
    "gn:name":"Fujia Yuanzi",
    "gn:population":0,
    "gn:timezone":"Asia/Shanghai",
    "iso:country":"CN",
    "name:zho_x_preferred":[
        "\u7b26\u5bb6\u9662\u5b50"
    ],
    "wof:name":"Fujia Yuanzi",
    "wof:placetype":"locality"
},
  "geometry": {"coordinates":[102.241,27.9848],"type":"Point"}
}