{
  "type": "Feature",
  "properties": {
    "gn:admin1_code":"15.0",
    "gn:asciiname":"Majiasi",
    "gn:country_code":"CN",
    "gn:dem":2130,
    "gn:feature_class":"P",
    "gn:feature_code":"PPL",
    "gn:name":"Majiasi",
    "gn:population":0,
    "gn:timezone":"Asia/Shanghai",
    "iso:country":"CN",
    "name:zho_x_preferred":[
        "\u9ebb\u5bb6\u5bfa"
    ],
    "wof:name":"Majiasi",
    "wof:placetype":"locality"
},
  "geometry": {"coordinates":[104.032,35.8826],"type":"Point"}
}