{
  "type": "Feature",
  "properties": {
    "gn:admin1_code":"25",
    "gn:asciiname":"Longyizhuang",
    "gn:country_code":"CN",
    "gn:dem":57,
    "gn:feature_class":"P",
    "gn:feature_code":"PPL",
    "gn:name":"Longyizhuang",
    "gn:population":0,
    "gn:timezone":"Asia/Shanghai",
    "iso:country":"CN",
    "name:zho_x_preferred":[
        "\u9f99\u6c82\u5e84"
    ],
    "wof:name":"Longyizhuang",
    "wof:placetype":"locality"
},
  "geometry": {"coordinates":[118.048,34.8789],"type":"Point"}
}