{
  "type": "Feature",
  "properties": {
    "gn:admin1_code":"07",
    "gn:asciiname":"Huangkeng",
    "gn:country_code":"CN",
    "gn:dem":347,
    "gn:feature_class":"P",
    "gn:feature_code":"PPL",
    "gn:name":"Huangkeng",
    "gn:population":0,
    "gn:timezone":"Asia/Shanghai",
    "iso:country":"CN",
    "name:zho_x_preferred":[
        "\u9ec4\u5751"
    ],
    "name:zho_x_variant":[
        "\u9ec4\u5751\u9547"
    ],
    "wof:name":"Huangkeng",
    "wof:placetype":"locality"
},
  "geometry": {"coordinates":[117.65035,27.57643],"type":"Point"}
}