{
  "type": "Feature",
  "properties": {
    "gn:admin1_code":"29.0",
    "gn:asciiname":"Denglong",
    "gn:country_code":"CN",
    "gn:dem":1419,
    "gn:feature_class":"P",
    "gn:feature_code":"PPL",
    "gn:name":"Denglong",
    "gn:population":0,
    "gn:timezone":"Asia/Shanghai",
    "iso:country":"CN",
    "name:jpn_x_preferred":[
        "\u30b3\u30a6"
    ],
    "name:kor_x_preferred":[
        "\uc870\ucc9c\ud6c4"
    ],
    "name:zho_x_preferred":[
        "\u706f\u9f99"
    ],
    "wof:name":"Denglong",
    "wof:placetype":"locality"
},
  "geometry": {"coordinates":[102.358,22.8414],"type":"Point"}
}