{
  "type": "Feature",
  "properties": {
    "gn:admin1_code":"20.0",
    "gn:asciiname":"Lin Sandui",
    "gn:country_code":"CN",
    "gn:dem":912,
    "gn:feature_class":"P",
    "gn:feature_code":"PPLF",
    "gn:name":"Lin Sandui",
    "gn:population":0,
    "gn:timezone":"Asia/Shanghai",
    "iso:country":"CN",
    "name:zho_x_preferred":[
        "\u6797\u4e09\u961f"
    ],
    "wof:name":"Lin Sandui",
    "wof:placetype":"locality"
},
  "geometry": {"coordinates":[121.94506,50.35622],"type":"Point"}
}