{
  "type": "Feature",
  "properties": {
    "gn:admin1_code":"3.0",
    "gn:asciiname":"Tianpufan",
    "gn:country_code":"CN",
    "gn:dem":26,
    "gn:feature_class":"P",
    "gn:feature_code":"PPL",
    "gn:name":"Tianpufan",
    "gn:population":0,
    "gn:timezone":"Asia/Shanghai",
    "iso:country":"CN",
    "name:und_x_variant":[
        "\u7530\u94fa\u7548"
    ],
    "wof:name":"Tianpufan",
    "wof:placetype":"locality"
},
  "geometry": {"coordinates":[116.73222,29.48549],"type":"Point"}
}