{
  "type": "Feature",
  "properties": {
    "gn:admin1_code":"29.0",
    "gn:asciiname":"Jiuchangping",
    "gn:country_code":"CN",
    "gn:dem":1642,
    "gn:feature_class":"P",
    "gn:feature_code":"PPL",
    "gn:name":"Jiuchangping",
    "gn:population":0,
    "gn:timezone":"Asia/Shanghai",
    "iso:country":"CN",
    "name:zho_x_preferred":[
        "\u65e7\u957f\u576a"
    ],
    "wof:name":"Jiuchangping",
    "wof:placetype":"locality"
},
  "geometry": {"coordinates":[101.282,26.7287],"type":"Point"}
}