{
  "type": "Feature",
  "properties": {
    "gn:admin1_code":"10.0",
    "gn:asciiname":"Gujinzhuang",
    "gn:country_code":"CN",
    "gn:dem":20,
    "gn:feature_class":"P",
    "gn:feature_code":"PPL",
    "gn:name":"Gujinzhuang",
    "gn:population":0,
    "gn:timezone":"Asia/Shanghai",
    "iso:country":"CN",
    "name:zho_x_preferred":[
        "\u53e4\u4eca\u5e84"
    ],
    "wof:name":"Gujinzhuang",
    "wof:placetype":"locality"
},
  "geometry": {"coordinates":[116.023,38.1786],"type":"Point"}
}