{
  "type": "Feature",
  "properties": {
    "gn:admin1_code":"20.0",
    "gn:asciiname":"Songshuliang",
    "gn:country_code":"CN",
    "gn:dem":1496,
    "gn:feature_class":"P",
    "gn:feature_code":"PPL",
    "gn:name":"Songshuliang",
    "gn:population":0,
    "gn:timezone":"Asia/Shanghai",
    "iso:country":"CN",
    "name:und_x_variant":[
        "\u677e\u6811\u6881"
    ],
    "wof:name":"Songshuliang",
    "wof:placetype":"locality"
},
  "geometry": {"coordinates":[111.66446999999999,39.85566],"type":"Point"}
}