{
  "type": "Feature",
  "properties": {
    "gn:admin1_code":"9.0",
    "gn:asciiname":"Aozigou",
    "gn:country_code":"CN",
    "gn:dem":822,
    "gn:feature_class":"P",
    "gn:feature_code":"PPL",
    "gn:name":"Aozigou",
    "gn:population":0,
    "gn:timezone":"Asia/Shanghai",
    "iso:country":"CN",
    "name:zho_x_preferred":[
        "\u93ca\u5b50\u6c9f"
    ],
    "wof:name":"Aozigou",
    "wof:placetype":"locality"
},
  "geometry": {"coordinates":[111.90373999999998,33.80163],"type":"Point"}
}