{
  "type": "Feature",
  "properties": {
    "gn:admin1_code":"2.0",
    "gn:asciiname":"Yuyan",
    "gn:country_code":"CN",
    "gn:dem":497,
    "gn:feature_class":"P",
    "gn:feature_code":"PPL",
    "gn:name":"Yuyan",
    "gn:population":0,
    "gn:timezone":"Asia/Shanghai",
    "iso:country":"CN",
    "name:fra_x_preferred":[
        "Yuyan"
    ],
    "name:jpn_x_preferred":[
        "\u611b\u65b0\u899a\u7f85\u6bd3\u5d52"
    ],
    "name:kor_x_preferred":[
        "\uc544\uc774\uc2e0\uae30\uc624\ub85c \uc720\uc580"
    ],
    "name:tha_x_preferred":[
        "\u0e22\u0e27\u0e35\u0e48\u0e40\u0e2b\u0e22\u0e35\u0e22\u0e19"
    ],
    "name:zho_x_preferred":[
        "\u7389\u5ca9"
    ],
    "wof:name":"Yuyan",
    "wof:placetype":"locality"
},
  "geometry": {"coordinates":[119.26366000000002,28.37373],"type":"Point"}
}