{
  "type": "Feature",
  "properties": {
    "gn:admin1_code":"32.0",
    "gn:asciiname":"Moluolada",
    "gn:country_code":"CN",
    "gn:dem":2332,
    "gn:feature_class":"P",
    "gn:feature_code":"PPL",
    "gn:name":"Moluolada",
    "gn:population":0,
    "gn:timezone":"Asia/Shanghai",
    "iso:country":"CN",
    "name:zho_x_preferred":[
        "\u6478\u6d1b\u62c9\u8fbe"
    ],
    "wof:name":"Moluolada",
    "wof:placetype":"locality"
},
  "geometry": {"coordinates":[102.208,28.7679],"type":"Point"}
}