{
  "type": "Feature",
  "properties": {
    "gn:admin1_code":"2.0",
    "gn:asciiname":"Jianjiazhuang",
    "gn:country_code":"CN",
    "gn:dem":135,
    "gn:feature_class":"P",
    "gn:feature_code":"PPL",
    "gn:name":"Jianjiazhuang",
    "gn:population":0,
    "gn:timezone":"Asia/Shanghai",
    "iso:country":"CN",
    "name:zho_x_preferred":[
        "\u5c16\u5bb6\u5e84"
    ],
    "wof:name":"Jianjiazhuang",
    "wof:placetype":"locality"
},
  "geometry": {"coordinates":[120.86673999999999,29.54668],"type":"Point"}
}