{
  "type": "Feature",
  "properties": {
    "gn:admin1_code":"7",
    "gn:asciiname":"Xiaoling Linchang",
    "gn:country_code":"CN",
    "gn:dem":370,
    "gn:feature_class":"P",
    "gn:feature_code":"PPLF",
    "gn:name":"Xiaoling Linchang",
    "gn:population":0,
    "gn:timezone":"Asia/Shanghai",
    "iso:country":"CN",
    "name:und_x_variant":[
        "Xiaoling",
        "\u5c0f\u5cad\u6797\u573a",
        "Xiaoling Linchang"
    ],
    "wof:name":"Xiaoling Linchang",
    "wof:placetype":"locality"
},
  "geometry": {"coordinates":[118.66639000000001,27.29333],"type":"Point"}
}