{
  "type": "Feature",
  "properties": {
    "gn:admin1_code":"12.0",
    "gn:asciiname":"Raojiawan",
    "gn:country_code":"CN",
    "gn:dem":26,
    "gn:feature_class":"P",
    "gn:feature_code":"PPL",
    "gn:name":"Raojiawan",
    "gn:population":0,
    "gn:timezone":"Asia/Shanghai",
    "iso:country":"CN",
    "name:zho_x_preferred":[
        "\u9976\u5bb6\u6e7e"
    ],
    "wof:name":"Raojiawan",
    "wof:placetype":"locality"
},
  "geometry": {"coordinates":[113.40022999999999,30.02358],"type":"Point"}
}