{
  "type": "Feature",
  "properties": {
    "gn:admin1_code":"2.0",
    "gn:asciiname":"Huangmaoshan",
    "gn:country_code":"CN",
    "gn:dem":284,
    "gn:feature_class":"P",
    "gn:feature_code":"PPL",
    "gn:name":"Huangmaoshan",
    "gn:population":0,
    "gn:timezone":"Asia/Shanghai",
    "iso:country":"CN",
    "name:zho_x_preferred":[
        "\u9ec4\u8305\u5c71"
    ],
    "wof:name":"Huangmaoshan",
    "wof:placetype":"locality"
},
  "geometry": {"coordinates":[120.22364,28.76583],"type":"Point"}
}