{
  "type": "Feature",
  "properties": {
    "gn:admin1_code":"20.0",
    "gn:asciiname":"Xiaohaozi",
    "gn:country_code":"CN",
    "gn:dem":1626,
    "gn:feature_class":"P",
    "gn:feature_code":"PPL",
    "gn:name":"Xiaohaozi",
    "gn:population":0,
    "gn:timezone":"Asia/Shanghai",
    "iso:country":"CN",
    "name:und_x_variant":[
        "\u5c0f\u53f7\u5b50"
    ],
    "wof:name":"Xiaohaozi",
    "wof:placetype":"locality"
},
  "geometry": {"coordinates":[110.39833,41.29243],"type":"Point"}
}