{
  "type": "Feature",
  "properties": {
    "gn:admin1_code":"5.0",
    "gn:asciiname":"Tunjicun",
    "gn:country_code":"CN",
    "gn:dem":372,
    "gn:feature_class":"P",
    "gn:feature_code":"PPL",
    "gn:name":"Tunjicun",
    "gn:population":0,
    "gn:timezone":"Asia/Shanghai",
    "iso:country":"CN",
    "name:zho_x_preferred":[
        "\u5c6f\u57fa\u6751"
    ],
    "wof:name":"Tunjicun",
    "wof:placetype":"locality"
},
  "geometry": {"coordinates":[125.61192,42.76395],"type":"Point"}
}