{
  "type": "Feature",
  "properties": {
    "gn:admin1_code":"15.0",
    "gn:asciiname":"Micaogou",
    "gn:country_code":"CN",
    "gn:dem":1663,
    "gn:feature_class":"P",
    "gn:feature_code":"PPL",
    "gn:name":"Micaogou",
    "gn:population":0,
    "gn:timezone":"Asia/Shanghai",
    "iso:country":"CN",
    "name:zho_x_preferred":[
        "\u871c\u69fd\u6c9f"
    ],
    "wof:name":"Micaogou",
    "wof:placetype":"locality"
},
  "geometry": {"coordinates":[106.232,34.299],"type":"Point"}
}