{
  "type": "Feature",
  "properties": {
    "gn:admin1_code":"10.0",
    "gn:asciiname":"Dagouleng",
    "gn:country_code":"CN",
    "gn:dem":989,
    "gn:feature_class":"P",
    "gn:feature_code":"PPL",
    "gn:name":"Dagouleng",
    "gn:population":0,
    "gn:timezone":"Asia/Shanghai",
    "iso:country":"CN",
    "name:zho_x_preferred":[
        "\u5927\u6c9f\u5844"
    ],
    "wof:name":"Dagouleng",
    "wof:placetype":"locality"
},
  "geometry": {"coordinates":[114.58857,40.14557],"type":"Point"}
}