{
  "type": "Feature",
  "properties": {
    "gn:admin1_code":"21.0",
    "gn:asciiname":"Gouxi",
    "gn:country_code":"CN",
    "gn:dem":1763,
    "gn:feature_class":"P",
    "gn:feature_code":"PPL",
    "gn:name":"Gouxi",
    "gn:population":0,
    "gn:timezone":"Asia/Shanghai",
    "iso:country":"CN",
    "name:und_x_variant":[
        "\u6c9f\u897f"
    ],
    "wof:name":"Gouxi",
    "wof:placetype":"locality"
},
  "geometry": {"coordinates":[106.59341000000001,36.85455],"type":"Point"}
}