{
  "type": "Feature",
  "properties": {
    "gn:admin1_code":"12.0",
    "gn:asciiname":"Houwangjialou",
    "gn:country_code":"CN",
    "gn:dem":132,
    "gn:feature_class":"P",
    "gn:feature_code":"PPL",
    "gn:name":"Houwangjialou",
    "gn:population":0,
    "gn:timezone":"Asia/Shanghai",
    "iso:country":"CN",
    "name:zho_x_preferred":[
        "\u540e\u738b\u5bb6\u697c"
    ],
    "wof:name":"Houwangjialou",
    "wof:placetype":"locality"
},
  "geometry": {"coordinates":[113.27907,31.06671],"type":"Point"}
}