{
  "type": "Feature",
  "properties": {
    "gn:admin1_code":"24.0",
    "gn:asciiname":"Qiaojiawan",
    "gn:country_code":"CN",
    "gn:dem":1400,
    "gn:feature_class":"P",
    "gn:feature_code":"PPL",
    "gn:name":"Qiaojiawan",
    "gn:population":0,
    "gn:timezone":"Asia/Shanghai",
    "iso:country":"CN",
    "name:zho_x_preferred":[
        "\u4e54\u5bb6\u6e7e"
    ],
    "wof:name":"Qiaojiawan",
    "wof:placetype":"locality"
},
  "geometry": {"coordinates":[111.60760999999999,38.68477],"type":"Point"}
}