{
  "type": "Feature",
  "properties": {
    "gn:admin1_code":"18.0",
    "gn:asciiname":"Jinwohu",
    "gn:country_code":"CN",
    "gn:dem":625,
    "gn:feature_class":"P",
    "gn:feature_code":"PPL",
    "gn:name":"Jinwohu",
    "gn:population":0,
    "gn:timezone":"Asia/Shanghai",
    "iso:country":"CN",
    "name:zho_x_preferred":[
        "\u9526\u5367\u864e"
    ],
    "wof:name":"Jinwohu",
    "wof:placetype":"locality"
},
  "geometry": {"coordinates":[108.967,26.1059],"type":"Point"}
}