{
  "type": "Feature",
  "properties": {
    "gn:admin1_code":"02",
    "gn:asciiname":"Shangshancun",
    "gn:country_code":"CN",
    "gn:dem":11,
    "gn:feature_class":"P",
    "gn:feature_code":"PPL",
    "gn:name":"Shangshancun",
    "gn:population":0,
    "gn:timezone":"Asia/Shanghai",
    "iso:country":"CN",
    "name:und_x_variant":[
        "Shangshan"
    ],
    "name:zho_x_preferred":[
        "\u4e0a\u5c71\u6751"
    ],
    "wof:name":"Shangshancun",
    "wof:placetype":"locality"
},
  "geometry": {"coordinates":[121.26600999999999,29.67786],"type":"Point"}
}