{
  "type": "Feature",
  "properties": {
    "gn:admin1_code":"3.0",
    "gn:asciiname":"Shenjiatian",
    "gn:country_code":"CN",
    "gn:dem":256,
    "gn:feature_class":"P",
    "gn:feature_code":"PPL",
    "gn:name":"Shenjiatian",
    "gn:population":0,
    "gn:timezone":"Asia/Shanghai",
    "iso:country":"CN",
    "name:und_x_variant":[
        "\u6c88\u5bb6\u7530"
    ],
    "wof:name":"Shenjiatian",
    "wof:placetype":"locality"
},
  "geometry": {"coordinates":[114.61793,28.40442],"type":"Point"}
}