{
  "type": "Feature",
  "properties": {
    "gn:admin1_code":"32.0",
    "gn:asciiname":"Dasi",
    "gn:country_code":"CN",
    "gn:dem":2059,
    "gn:feature_class":"P",
    "gn:feature_code":"PPL",
    "gn:name":"Dasi",
    "gn:population":0,
    "gn:timezone":"Asia/Shanghai",
    "iso:country":"CN",
    "name:cat_x_preferred":[
        "Dasi"
    ],
    "name:ceb_x_preferred":[
        "Dasi"
    ],
    "name:deu_x_preferred":[
        "Dasi"
    ],
    "name:fra_x_preferred":[
        "Dasi"
    ],
    "name:swe_x_preferred":[
        "Dasi"
    ],
    "name:zho_x_preferred":[
        "\u5927\u5bfa"
    ],
    "wof:name":"Dasi",
    "wof:placetype":"locality"
},
  "geometry": {"coordinates":[103.59,31.5232],"type":"Point"}
}