{
  "type": "Feature",
  "properties": {
    "gn:admin1_code":"26.0",
    "gn:asciiname":"Caohuicun",
    "gn:country_code":"CN",
    "gn:dem":676,
    "gn:feature_class":"P",
    "gn:feature_code":"PPL",
    "gn:name":"Caohuicun",
    "gn:population":0,
    "gn:timezone":"Asia/Shanghai",
    "iso:country":"CN",
    "name:und_x_variant":[
        "Huijiacun",
        "Huijia"
    ],
    "name:zho_x_preferred":[
        "\u66f9\u60e0\u6751"
    ],
    "name:zho_x_variant":[
        "\u60e0\u5bb6"
    ],
    "wof:name":"Caohuicun",
    "wof:placetype":"locality"
},
  "geometry": {"coordinates":[108.85651,34.77029],"type":"Point"}
}