{
  "type": "Feature",
  "properties": {
    "gn:admin1_code":"6.0",
    "gn:asciiname":"Bayin",
    "gn:country_code":"CN",
    "gn:dem":3148,
    "gn:feature_class":"P",
    "gn:feature_code":"PPL",
    "gn:name":"Bayin",
    "gn:population":0,
    "gn:timezone":"Asia/Urumqi",
    "iso:country":"CN",
    "name:fas_x_preferred":[
        "\u0628\u0627\u06cc\u06cc\u0646"
    ],
    "name:zho_x_preferred":[
        "\u5df4\u97f3"
    ],
    "name:zho_x_variant":[
        "\u5df4\u97f3\u989d\u65e5\u4e50"
    ],
    "wof:name":"Bayin",
    "wof:placetype":"locality"
},
  "geometry": {"coordinates":[99.03721,36.84502],"type":"Point"}
}