{
  "type": "Feature",
  "properties": {
    "gn:admin1_code":"11.0",
    "gn:asciiname":"Tianmudu",
    "gn:country_code":"CN",
    "gn:dem":518,
    "gn:feature_class":"P",
    "gn:feature_code":"PPL",
    "gn:name":"Tianmudu",
    "gn:population":0,
    "gn:timezone":"Asia/Shanghai",
    "iso:country":"CN",
    "name:zho_x_preferred":[
        "\u7530\u4ea9\u90fd"
    ],
    "wof:name":"Tianmudu",
    "wof:placetype":"locality"
},
  "geometry": {"coordinates":[110.40685000000001,27.54776],"type":"Point"}
}