{
  "type": "Feature",
  "properties": {
    "gn:admin1_code":"18",
    "gn:asciiname":"Qingshenqiao",
    "gn:country_code":"CN",
    "gn:dem":811,
    "gn:feature_class":"P",
    "gn:feature_code":"PPL",
    "gn:name":"Qingshenqiao",
    "gn:population":0,
    "gn:timezone":"Asia/Shanghai",
    "iso:country":"CN",
    "name:zho_x_preferred":[
        "\u6e05\u795e\u6865"
    ],
    "wof:name":"Qingshenqiao",
    "wof:placetype":"locality"
},
  "geometry": {"coordinates":[107.081,27.7319],"type":"Point"}
}