{
  "type": "Feature",
  "properties": {
    "gn:admin1_code":"25.0",
    "gn:asciiname":"Yaokou",
    "gn:country_code":"CN",
    "gn:dem":76,
    "gn:feature_class":"P",
    "gn:feature_code":"PPL",
    "gn:name":"Yaokou",
    "gn:population":0,
    "gn:timezone":"Asia/Shanghai",
    "iso:country":"CN",
    "name:zho_x_preferred":[
        "\u7a91\u53e3"
    ],
    "wof:name":"Yaokou",
    "wof:placetype":"locality"
},
  "geometry": {"coordinates":[121.66683,37.35083],"type":"Point"}
}