{
  "type": "Feature",
  "properties": {
    "gn:admin1_code":"19",
    "gn:asciiname":"Jiefang",
    "gn:country_code":"CN",
    "gn:dem":37,
    "gn:feature_class":"P",
    "gn:feature_code":"PPL",
    "gn:name":"Jiefang",
    "gn:population":0,
    "gn:timezone":"Asia/Shanghai",
    "iso:country":"CN",
    "name:ceb_x_preferred":[
        "Jiefang"
    ],
    "name:deu_x_preferred":[
        "Jiefang"
    ],
    "wof:name":"Jiefang",
    "wof:placetype":"locality"
},
  "geometry": {"coordinates":[123.20778,41.995],"type":"Point"}
}