{
  "type": "Feature",
  "properties": {
    "gn:admin1_code":"32.0",
    "gn:asciiname":"Shicang",
    "gn:country_code":"CN",
    "gn:dem":728,
    "gn:feature_class":"P",
    "gn:feature_code":"PPL",
    "gn:name":"Shicang",
    "gn:population":0,
    "gn:timezone":"Asia/Shanghai",
    "iso:country":"CN",
    "name:zho_x_preferred":[
        "\u77f3\u4ed3"
    ],
    "wof:name":"Shicang",
    "wof:placetype":"locality"
},
  "geometry": {"coordinates":[107.36,31.5961],"type":"Point"}
}