{
  "type": "Feature",
  "properties": {
    "gn:admin1_code":"16.0",
    "gn:asciiname":"Baigongxia",
    "gn:country_code":"CN",
    "gn:dem":42,
    "gn:feature_class":"P",
    "gn:feature_code":"PPL",
    "gn:name":"Baigongxia",
    "gn:population":0,
    "gn:timezone":"Asia/Shanghai",
    "iso:country":"CN",
    "name:zho_x_preferred":[
        "\u4f70\u516c\u4e0b"
    ],
    "wof:name":"Baigongxia",
    "wof:placetype":"locality"
},
  "geometry": {"coordinates":[109.586,21.9319],"type":"Point"}
}