{
  "type": "Feature",
  "properties": {
    "gn:admin1_code":"21.0",
    "gn:asciiname":"Beitan",
    "gn:country_code":"CN",
    "gn:dem":1240,
    "gn:feature_class":"P",
    "gn:feature_code":"PPL",
    "gn:name":"Beitan",
    "gn:population":0,
    "gn:timezone":"Asia/Shanghai",
    "iso:country":"CN",
    "name:zho_x_preferred":[
        "\u5317\u6ee9"
    ],
    "wof:name":"Beitan",
    "wof:placetype":"locality"
},
  "geometry": {"coordinates":[105.574,37.423],"type":"Point"}
}