{
  "type": "Feature",
  "properties": {
    "gn:admin1_code":"32.0",
    "gn:asciiname":"Qingyun",
    "gn:country_code":"CN",
    "gn:dem":459,
    "gn:feature_class":"P",
    "gn:feature_code":"PPL",
    "gn:name":"Qingyun",
    "gn:population":0,
    "gn:timezone":"Asia/Shanghai",
    "iso:country":"CN",
    "name:zho_x_preferred":[
        "\u9752\u4e91"
    ],
    "wof:name":"Qingyun",
    "wof:placetype":"locality"
},
  "geometry": {"coordinates":[104.71299999999999,30.7517],"type":"Point"}
}