{
  "type": "Feature",
  "properties": {
    "gn:admin1_code":"02",
    "gn:asciiname":"Shanshi",
    "gn:country_code":"CN",
    "gn:dem":5,
    "gn:feature_class":"P",
    "gn:feature_code":"PPL",
    "gn:name":"Shanshi",
    "gn:population":0,
    "gn:timezone":"Asia/Shanghai",
    "iso:country":"CN",
    "name:und_x_variant":[
        "Shan-shih-t\u2019ang",
        "\u5c71\u5e02",
        "Shanshi"
    ],
    "wof:name":"Shanshi",
    "wof:placetype":"locality"
},
  "geometry": {"coordinates":[121.29113,28.50777],"type":"Point"}
}