{
  "type": "Feature",
  "properties": {
    "gn:admin1_code":"19.0",
    "gn:asciiname":"Bataizi",
    "gn:country_code":"CN",
    "gn:dem":11,
    "gn:feature_class":"P",
    "gn:feature_code":"PPL",
    "gn:name":"Bataizi",
    "gn:population":0,
    "gn:timezone":"Asia/Shanghai",
    "iso:country":"CN",
    "name:und_x_variant":[
        "\u516b\u53f0\u5b50"
    ],
    "name:zho_x_preferred":[
        "\u516b\u53f0\u5b50"
    ],
    "wof:name":"Bataizi",
    "wof:placetype":"locality"
},
  "geometry": {"coordinates":[122.19409,41.52934000000001],"type":"Point"}
}