{
  "type": "Feature",
  "properties": {
    "gn:admin1_code":"30",
    "gn:asciiname":"Qikuaizai",
    "gn:country_code":"CN",
    "gn:dem":22,
    "gn:feature_class":"P",
    "gn:feature_code":"PPL",
    "gn:name":"Qikuaizai",
    "gn:population":0,
    "gn:timezone":"Asia/Urumqi",
    "iso:country":"CN",
    "name:zho_x_preferred":[
        "\u4e03\u5757\u4ed4"
    ],
    "wof:name":"Qikuaizai",
    "wof:placetype":"locality"
},
  "geometry": {"coordinates":[110.04187,21.51135],"type":"Point"}
}