{
  "type": "Feature",
  "properties": {
    "gn:admin1_code":"11.0",
    "gn:asciiname":"Dengjiawan",
    "gn:country_code":"CN",
    "gn:dem":108,
    "gn:feature_class":"P",
    "gn:feature_code":"PPL",
    "gn:name":"Dengjiawan",
    "gn:population":0,
    "gn:timezone":"Asia/Shanghai",
    "iso:country":"CN",
    "name:zho_x_preferred":[
        "Dengjiawan"
    ],
    "name:zho_x_variant":[
        "\u9093\u5bb6\u6e7e"
    ],
    "wof:name":"Dengjiawan",
    "wof:placetype":"locality"
},
  "geometry": {"coordinates":[111.48611,29.75666],"type":"Point"}
}