{
  "type": "Feature",
  "properties": {
    "gn:admin1_code":"10",
    "gn:asciiname":"Ershilipu",
    "gn:country_code":"CN",
    "gn:dem":72,
    "gn:feature_class":"P",
    "gn:feature_code":"PPLA4",
    "gn:name":"Ershilipu",
    "gn:population":0,
    "gn:timezone":"Asia/Shanghai",
    "iso:country":"CN",
    "name:und_x_variant":[
        "Erh-shih-li-p\u2019u",
        "Ershilipu",
        "\u4e8c\u5341\u91cc\u94fa",
        "Ershilipu Zhen",
        "\u4e8c\u5341\u91cc\u94fa\u9547"
    ],
    "wof:name":"Ershilipu",
    "wof:placetype":"locality"
},
  "geometry": {"coordinates":[114.57416000000001,38.03295],"type":"Point"}
}