{
  "type": "Feature",
  "properties": {
    "gn:admin1_code":"30",
    "gn:asciiname":"Lugang",
    "gn:country_code":"CN",
    "gn:dem":4,
    "gn:feature_class":"P",
    "gn:feature_code":"PPLA4",
    "gn:name":"Lugang",
    "gn:population":0,
    "gn:timezone":"Asia/Shanghai",
    "iso:country":"CN",
    "name:ceb_x_preferred":[
        "Lugang"
    ],
    "name:swe_x_preferred":[
        "Lugang"
    ],
    "name:und_x_variant":[
        "Lugang Zhen",
        "\u80ea\u5c97\u9547"
    ],
    "name:zho_x_preferred":[
        "\u80ea\u5c97"
    ],
    "wof:name":"Lugang",
    "wof:placetype":"locality"
},
  "geometry": {"coordinates":[116.4598,23.22464],"type":"Point"}
}