{
  "type": "Feature",
  "properties": {
    "gn:admin1_code":"32.0",
    "gn:asciiname":"Guihuajing",
    "gn:country_code":"CN",
    "gn:dem":327,
    "gn:feature_class":"P",
    "gn:feature_code":"PPL",
    "gn:name":"Guihuajing",
    "gn:population":0,
    "gn:timezone":"Asia/Shanghai",
    "iso:country":"CN",
    "name:zho_x_preferred":[
        "\u6842\u82b1\u4e95"
    ],
    "wof:name":"Guihuajing",
    "wof:placetype":"locality"
},
  "geometry": {"coordinates":[106.36199999999999,30.8496],"type":"Point"}
}