{
  "type": "Feature",
  "properties": {
    "gn:admin1_code":"12.0",
    "gn:asciiname":"Hailuobao",
    "gn:country_code":"CN",
    "gn:dem":1160,
    "gn:feature_class":"P",
    "gn:feature_code":"PPL",
    "gn:name":"Hailuobao",
    "gn:population":0,
    "gn:timezone":"Asia/Shanghai",
    "iso:country":"CN",
    "name:zho_x_preferred":[
        "\u6d77\u87ba\u5305"
    ],
    "wof:name":"Hailuobao",
    "wof:placetype":"locality"
},
  "geometry": {"coordinates":[110.88066999999999,30.73664],"type":"Point"}
}