{
  "type": "Feature",
  "properties": {
    "gn:admin1_code":"24",
    "gn:asciiname":"Jiuguan",
    "gn:country_code":"CN",
    "gn:dem":677,
    "gn:feature_class":"P",
    "gn:feature_code":"PPL",
    "gn:name":"Jiuguan",
    "gn:population":0,
    "gn:timezone":"Asia/Shanghai",
    "iso:country":"CN",
    "name:und_x_variant":[
        "Chiu-kuan-chen",
        "Chiu-kuan",
        "Jiuguan"
    ],
    "name:zho_x_preferred":[
        "\u65e7\u5173"
    ],
    "wof:name":"Jiuguan",
    "wof:placetype":"locality"
},
  "geometry": {"coordinates":[113.91231999999999,37.91714],"type":"Point"}
}