{
  "type": "Feature",
  "properties": {
    "gn:admin1_code":"12",
    "gn:asciiname":"Anjiacha",
    "gn:country_code":"CN",
    "gn:dem":39,
    "gn:feature_class":"P",
    "gn:feature_code":"PPL",
    "gn:name":"Anjiacha",
    "gn:population":0,
    "gn:timezone":"Asia/Shanghai",
    "iso:country":"CN",
    "name:und_x_variant":[
        "\u5b89\u5bb6\u5c94"
    ],
    "wof:name":"Anjiacha",
    "wof:placetype":"locality"
},
  "geometry": {"coordinates":[112.18698999999999,30.40438],"type":"Point"}
}