{
  "type": "Feature",
  "properties": {
    "gn:admin1_code":"12.0",
    "gn:asciiname":"Zhashu'ao",
    "gn:country_code":"CN",
    "gn:dem":250,
    "gn:feature_class":"P",
    "gn:feature_code":"PPL",
    "gn:name":"Zhashu\u2019ao",
    "gn:population":0,
    "gn:timezone":"Asia/Shanghai",
    "iso:country":"CN",
    "name:und_x_variant":[
        "Zhashu\u2019ao"
    ],
    "name:zho_x_preferred":[
        "\u55b3\u6811\u5773"
    ],
    "wof:name":"Zhashu'ao",
    "wof:placetype":"locality"
},
  "geometry": {"coordinates":[114.98734,30.81092],"type":"Point"}
}