{
  "type": "Feature",
  "properties": {
    "gn:admin1_code":"29.0",
    "gn:asciiname":"Bainitang",
    "gn:country_code":"CN",
    "gn:dem":2113,
    "gn:feature_class":"P",
    "gn:feature_code":"PPL",
    "gn:name":"Bainitang",
    "gn:population":0,
    "gn:timezone":"Asia/Shanghai",
    "iso:country":"CN",
    "name:zho_x_preferred":[
        "\u767d\u6ce5\u5858"
    ],
    "wof:name":"Bainitang",
    "wof:placetype":"locality"
},
  "geometry": {"coordinates":[102.62,25.4604],"type":"Point"}
}