{
  "type": "Feature",
  "properties": {
    "gn:admin1_code":"9",
    "gn:asciiname":"Chuzhuangxi",
    "gn:country_code":"CN",
    "gn:dem":69,
    "gn:feature_class":"P",
    "gn:feature_code":"PPL",
    "gn:name":"Chuzhuangxi",
    "gn:population":0,
    "gn:timezone":"Asia/Shanghai",
    "iso:country":"CN",
    "name:zho_x_preferred":[
        "\u695a\u5e84\u897f"
    ],
    "wof:name":"Chuzhuangxi",
    "wof:placetype":"locality"
},
  "geometry": {"coordinates":[115.17100000000001,34.7576],"type":"Point"}
}