{
  "type": "Feature",
  "properties": {
    "gn:admin1_code":"1.0",
    "gn:asciiname":"Jianxicun",
    "gn:country_code":"CN",
    "gn:dem":15,
    "gn:feature_class":"P",
    "gn:feature_code":"PPL",
    "gn:name":"Jianxicun",
    "gn:population":0,
    "gn:timezone":"Asia/Shanghai",
    "iso:country":"CN",
    "name:zho_x_preferred":[
        "\u6da7\u6eaa\u6751"
    ],
    "wof:name":"Jianxicun",
    "wof:placetype":"locality"
},
  "geometry": {"coordinates":[118.2475,32.82568],"type":"Point"}
}