{
  "type": "Feature",
  "properties": {
    "gn:admin1_code":"32.0",
    "gn:asciiname":"Talu",
    "gn:country_code":"CN",
    "gn:dem":1642,
    "gn:feature_class":"P",
    "gn:feature_code":"PPL",
    "gn:name":"Talu",
    "gn:population":0,
    "gn:timezone":"Asia/Shanghai",
    "iso:country":"CN",
    "name:zho_x_preferred":[
        "\u584c\u8f98"
    ],
    "wof:name":"Talu",
    "wof:placetype":"locality"
},
  "geometry": {"coordinates":[101.86584999999999,26.1567],"type":"Point"}
}