{
  "type": "Feature",
  "properties": {
    "gn:admin1_code":"12.0",
    "gn:asciiname":"Guojialaowan",
    "gn:country_code":"CN",
    "gn:dem":1382,
    "gn:feature_class":"P",
    "gn:feature_code":"PPL",
    "gn:name":"Guojialaowan",
    "gn:population":0,
    "gn:timezone":"Asia/Shanghai",
    "iso:country":"CN",
    "name:zho_x_preferred":[
        "\u90ed\u5bb6\u8001\u6e7e"
    ],
    "wof:name":"Guojialaowan",
    "wof:placetype":"locality"
},
  "geometry": {"coordinates":[111.11109999999999,31.32053],"type":"Point"}
}