{
  "type": "Feature",
  "properties": {
    "gn:admin1_code":"30",
    "gn:asciiname":"Chengbei",
    "gn:country_code":"CN",
    "gn:dem":67,
    "gn:feature_class":"P",
    "gn:feature_code":"PPLA4",
    "gn:name":"Chengbei",
    "gn:population":0,
    "gn:timezone":"Asia/Urumqi",
    "iso:country":"CN",
    "name:und_x_variant":[
        "Chengbei Xiang",
        "Chengbei"
    ],
    "name:zho_x_preferred":[
        "\u57ce\u5317\u4e61"
    ],
    "name:zho_x_variant":[
        "\u57ce\u5317"
    ],
    "wof:name":"Chengbei",
    "wof:placetype":"locality"
},
  "geometry": {"coordinates":[110.17822,20.32463],"type":"Point"}
}