{
  "type": "Feature",
  "properties": {
    "gn:admin1_code":"26.0",
    "gn:asciiname":"Youfangping",
    "gn:country_code":"CN",
    "gn:dem":1448,
    "gn:feature_class":"P",
    "gn:feature_code":"PPL",
    "gn:name":"Youfangping",
    "gn:population":0,
    "gn:timezone":"Asia/Shanghai",
    "iso:country":"CN",
    "name:zho_x_preferred":[
        "\u6cb9\u623f\u576a"
    ],
    "wof:name":"Youfangping",
    "wof:placetype":"locality"
},
  "geometry": {"coordinates":[108.18635999999999,33.91858],"type":"Point"}
}