{
  "type": "Feature",
  "properties": {
    "gn:admin1_code":"25",
    "gn:asciiname":"Wangshantou",
    "gn:country_code":"CN",
    "gn:dem":76,
    "gn:feature_class":"P",
    "gn:feature_code":"PPL",
    "gn:name":"Wangshantou",
    "gn:population":0,
    "gn:timezone":"Asia/Shanghai",
    "iso:country":"CN",
    "name:zho_x_preferred":[
        "\u738b\u5c71\u5934"
    ],
    "wof:name":"Wangshantou",
    "wof:placetype":"locality"
},
  "geometry": {"coordinates":[118.661,34.9636],"type":"Point"}
}