{
  "type": "Feature",
  "properties": {
    "gn:admin1_code":"15.0",
    "gn:asciiname":"Renjiaping",
    "gn:country_code":"CN",
    "gn:dem":2181,
    "gn:feature_class":"P",
    "gn:feature_code":"PPL",
    "gn:name":"Renjiaping",
    "gn:population":0,
    "gn:timezone":"Asia/Shanghai",
    "iso:country":"CN",
    "name:zho_x_preferred":[
        "\u4ec1\u5bb6\u576a"
    ],
    "wof:name":"Renjiaping",
    "wof:placetype":"locality"
},
  "geometry": {"coordinates":[104.09099999999999,35.2429],"type":"Point"}
}