{
  "type": "Feature",
  "properties": {
    "gn:admin1_code":"08",
    "gn:asciiname":"Shiyizhan",
    "gn:cc2":"CN",
    "gn:country_code":"CN",
    "gn:dem":362,
    "gn:feature_class":"P",
    "gn:feature_code":"PPL",
    "gn:name":"Shiyizhan",
    "gn:population":0,
    "gn:timezone":"Asia/Shanghai",
    "iso:country":"CN",
    "name:eng_x_preferred":[
        "Shiyizhan"
    ],
    "name:rus_x_preferred":[
        "\u0428\u0438\u0438\u0447\u0436\u0430\u043d\u044c"
    ],
    "name:und_x_variant":[
        "Alukhe",
        "Shih-i-chan",
        "Ka-lu-ho",
        "Shiichzhan",
        "Ka-lu-ho-chan"
    ],
    "wof:name":"Shiyizhan",
    "wof:placetype":"locality"
},
  "geometry": {"coordinates":[125.98333,51.11667],"type":"Point"}
}