{
  "type": "Feature",
  "properties": {
    "gn:admin1_code":"25.0",
    "gn:asciiname":"Dongsicun",
    "gn:country_code":"CN",
    "gn:dem":20,
    "gn:feature_class":"P",
    "gn:feature_code":"PPL",
    "gn:name":"Dongsicun",
    "gn:population":0,
    "gn:timezone":"Asia/Shanghai",
    "iso:country":"CN",
    "name:zho_x_preferred":[
        "\u4e1c\u5bfa\u6751"
    ],
    "wof:name":"Dongsicun",
    "wof:placetype":"locality"
},
  "geometry": {"coordinates":[119.69386000000002,35.72692],"type":"Point"}
}