{
  "type": "Feature",
  "properties": {
    "gn:admin1_code":"9.0",
    "gn:asciiname":"Wenxiangcun",
    "gn:country_code":"CN",
    "gn:dem":404,
    "gn:feature_class":"P",
    "gn:feature_code":"PPL",
    "gn:name":"Wenxiangcun",
    "gn:population":0,
    "gn:timezone":"Asia/Shanghai",
    "iso:country":"CN",
    "name:und_x_variant":[
        "Wensiang",
        "Wen-hsiang",
        "Wenxiangcun"
    ],
    "name:zho_x_preferred":[
        "\u960c\u4e61\u6751"
    ],
    "wof:name":"Wenxiangcun",
    "wof:placetype":"locality"
},
  "geometry": {"coordinates":[110.62632000000001,34.57191],"type":"Point"}
}