{
  "type": "Feature",
  "properties": {
    "gn:admin1_code":"3.0",
    "gn:asciiname":"Shengli",
    "gn:country_code":"CN",
    "gn:dem":257,
    "gn:feature_class":"P",
    "gn:feature_code":"PPL",
    "gn:name":"Shengli",
    "gn:population":0,
    "gn:timezone":"Asia/Shanghai",
    "iso:country":"CN",
    "name:und_x_variant":[
        "\u80dc\u5229"
    ],
    "wof:name":"Shengli",
    "wof:placetype":"locality"
},
  "geometry": {"coordinates":[115.53366,29.8161],"type":"Point"}
}