{
  "type": "Feature",
  "properties": {
    "gn:admin1_code":"29.0",
    "gn:asciiname":"Huobalishu",
    "gn:country_code":"CN",
    "gn:dem":2305,
    "gn:feature_class":"P",
    "gn:feature_code":"PPL",
    "gn:name":"Huobalishu",
    "gn:population":0,
    "gn:timezone":"Asia/Shanghai",
    "iso:country":"CN",
    "name:zho_x_preferred":[
        "\u706b\u628a\u68a8\u6811"
    ],
    "wof:name":"Huobalishu",
    "wof:placetype":"locality"
},
  "geometry": {"coordinates":[101.14700000000001,25.2996],"type":"Point"}
}