{
  "type": "Feature",
  "properties": {
    "gn:admin1_code":"4.0",
    "gn:asciiname":"Liubangcun",
    "gn:country_code":"CN",
    "gn:dem":37,
    "gn:feature_class":"P",
    "gn:feature_code":"PPL",
    "gn:name":"Liubangcun",
    "gn:population":0,
    "gn:timezone":"Asia/Shanghai",
    "iso:country":"CN",
    "name:zho_x_preferred":[
        "\u5218\u90a6\u6751"
    ],
    "wof:name":"Liubangcun",
    "wof:placetype":"locality"
},
  "geometry": {"coordinates":[116.79492,34.82648],"type":"Point"}
}