{
  "type": "Feature",
  "properties": {
    "gn:admin1_code":"15.0",
    "gn:asciiname":"Lijiadun",
    "gn:country_code":"CN",
    "gn:dem":1196,
    "gn:feature_class":"P",
    "gn:feature_code":"PPL",
    "gn:name":"Lijiadun",
    "gn:population":0,
    "gn:timezone":"Asia/Urumqi",
    "iso:country":"CN",
    "name:zho_x_preferred":[
        "\u674e\u5bb6\u58a9"
    ],
    "wof:name":"Lijiadun",
    "wof:placetype":"locality"
},
  "geometry": {"coordinates":[94.5565,40.0688],"type":"Point"}
}