{
  "type": "Feature",
  "properties": {
    "gn:admin1_code":"3.0",
    "gn:asciiname":"Shagao",
    "gn:country_code":"CN",
    "gn:dem":366,
    "gn:feature_class":"P",
    "gn:feature_code":"PPL",
    "gn:name":"Shagao",
    "gn:population":0,
    "gn:timezone":"Asia/Shanghai",
    "iso:country":"CN",
    "name:und_x_variant":[
        "\u6c99\u544a"
    ],
    "wof:name":"Shagao",
    "wof:placetype":"locality"
},
  "geometry": {"coordinates":[115.98802999999999,25.60406],"type":"Point"}
}