{
  "type": "Feature",
  "properties": {
    "gn:admin1_code":"30.0",
    "gn:asciiname":"Longdong",
    "gn:country_code":"CN",
    "gn:dem":105,
    "gn:feature_class":"P",
    "gn:feature_code":"PPL",
    "gn:name":"Longdong",
    "gn:population":0,
    "gn:timezone":"Asia/Shanghai",
    "iso:country":"CN",
    "name:ceb_x_preferred":[
        "Longdong"
    ],
    "name:swe_x_preferred":[
        "Longdong"
    ],
    "name:zho_x_preferred":[
        "\u9f99\u6d1e"
    ],
    "wof:name":"Longdong",
    "wof:placetype":"locality"
},
  "geometry": {"coordinates":[112.25454999999999,23.36761],"type":"Point"}
}