{
  "type": "Feature",
  "properties": {
    "gn:admin1_code":"18",
    "gn:asciiname":"Xiaochagou",
    "gn:country_code":"CN",
    "gn:dem":1683,
    "gn:feature_class":"P",
    "gn:feature_code":"PPL",
    "gn:name":"Xiaochagou",
    "gn:population":0,
    "gn:timezone":"Asia/Shanghai",
    "iso:country":"CN",
    "name:zho_x_preferred":[
        "\u5c0f\u5c94\u6c9f"
    ],
    "wof:name":"Xiaochagou",
    "wof:placetype":"locality"
},
  "geometry": {"coordinates":[104.96599999999999,25.7799],"type":"Point"}
}