{
  "type": "Feature",
  "properties": {
    "gn:admin1_code":"11.0",
    "gn:asciiname":"Nangangzhou",
    "gn:country_code":"CN",
    "gn:dem":55,
    "gn:feature_class":"P",
    "gn:feature_code":"PPL",
    "gn:name":"Nangangzhou",
    "gn:population":0,
    "gn:timezone":"Asia/Shanghai",
    "iso:country":"CN",
    "name:zho_x_preferred":[
        "\u5357\u5c97\u6d32"
    ],
    "wof:name":"Nangangzhou",
    "wof:placetype":"locality"
},
  "geometry": {"coordinates":[112.00744,28.57668],"type":"Point"}
}