{
  "type": "Feature",
  "properties": {
    "gn:admin1_code":"10",
    "gn:asciiname":"Polizhuang",
    "gn:country_code":"CN",
    "gn:dem":29,
    "gn:feature_class":"P",
    "gn:feature_code":"PPL",
    "gn:name":"Polizhuang",
    "gn:population":0,
    "gn:timezone":"Asia/Shanghai",
    "iso:country":"CN",
    "name:zho_x_preferred":[
        "\u6cca\u91cc\u5e84"
    ],
    "wof:name":"Polizhuang",
    "wof:placetype":"locality"
},
  "geometry": {"coordinates":[114.964,37.5026],"type":"Point"}
}