{
  "type": "Feature",
  "properties": {
    "gn:admin1_code":"2.0",
    "gn:asciiname":"Pomu",
    "gn:country_code":"CN",
    "gn:dem":167,
    "gn:feature_class":"P",
    "gn:feature_code":"PPL",
    "gn:name":"Pomu",
    "gn:population":0,
    "gn:timezone":"Asia/Shanghai",
    "iso:country":"CN",
    "name:zho_x_preferred":[
        "\u5a46\u59c6"
    ],
    "wof:name":"Pomu",
    "wof:placetype":"locality"
},
  "geometry": {"coordinates":[120.16352000000001,29.47921],"type":"Point"}
}