{
  "type": "Feature",
  "properties": {
    "gn:admin1_code":"11.0",
    "gn:asciiname":"Sibeihou",
    "gn:country_code":"CN",
    "gn:dem":346,
    "gn:feature_class":"P",
    "gn:feature_code":"PPL",
    "gn:name":"Sibeihou",
    "gn:population":0,
    "gn:timezone":"Asia/Shanghai",
    "iso:country":"CN",
    "name:zho_x_preferred":[
        "\u5bfa\u80cc\u540e"
    ],
    "wof:name":"Sibeihou",
    "wof:placetype":"locality"
},
  "geometry": {"coordinates":[110.96544,26.97253],"type":"Point"}
}