{
  "type": "Feature",
  "properties": {
    "gn:admin1_code":"1.0",
    "gn:asciiname":"Shichongwan",
    "gn:country_code":"CN",
    "gn:dem":80,
    "gn:feature_class":"P",
    "gn:feature_code":"PPL",
    "gn:name":"Shichongwan",
    "gn:population":0,
    "gn:timezone":"Asia/Shanghai",
    "iso:country":"CN",
    "name:und_x_variant":[
        "\u77f3\u5d07\u6e7e"
    ],
    "wof:name":"Shichongwan",
    "wof:placetype":"locality"
},
  "geometry": {"coordinates":[118.95097,30.53495],"type":"Point"}
}