{
  "type": "Feature",
  "properties": {
    "gn:admin1_code":"18.0",
    "gn:asciiname":"Mianhuashan",
    "gn:country_code":"CN",
    "gn:dem":856,
    "gn:feature_class":"P",
    "gn:feature_code":"PPL",
    "gn:name":"Mianhuashan",
    "gn:population":0,
    "gn:timezone":"Asia/Shanghai",
    "iso:country":"CN",
    "name:zho_x_preferred":[
        "\u68c9\u82b1\u5c71"
    ],
    "wof:name":"Mianhuashan",
    "wof:placetype":"locality"
},
  "geometry": {"coordinates":[107.65000000000001,26.6756],"type":"Point"}
}