{
  "type": "Feature",
  "properties": {
    "gn:admin1_code":"29.0",
    "gn:asciiname":"Wanda",
    "gn:country_code":"CN",
    "gn:dem":965,
    "gn:feature_class":"P",
    "gn:feature_code":"PPL",
    "gn:name":"Wanda",
    "gn:population":0,
    "gn:timezone":"Asia/Shanghai",
    "iso:country":"CN",
    "name:bre_x_preferred":[
        "Wanda"
    ],
    "name:deu_x_preferred":[
        "Wanda"
    ],
    "name:ita_x_preferred":[
        "Wanda"
    ],
    "name:jpn_x_preferred":[
        "\u30f4\u30a1\u30f3\u30c0"
    ],
    "name:nld_x_preferred":[
        "Wanda"
    ],
    "name:nor_x_preferred":[
        "Wanda"
    ],
    "name:pol_x_preferred":[
        "Wanda"
    ],
    "name:rus_x_preferred":[
        "\u0412\u0430\u043d\u0434\u0430"
    ],
    "name:srp_x_preferred":[
        "\u0412\u0430\u043d\u0434\u0430"
    ],
    "name:zho_x_preferred":[
        "\u73a9\u8fbe"
    ],
    "wof:name":"Wanda",
    "wof:placetype":"locality"
},
  "geometry": {"coordinates":[99.64879999999999,22.1632],"type":"Point"}
}