{
  "type": "Feature",
  "properties": {
    "gn:admin1_code":"19.0",
    "gn:asciiname":"Jiangjia Buzi",
    "gn:country_code":"CN",
    "gn:dem":3,
    "gn:feature_class":"P",
    "gn:feature_code":"PPL",
    "gn:name":"Jiangjia Buzi",
    "gn:population":0,
    "gn:timezone":"Asia/Shanghai",
    "iso:country":"CN",
    "name:und_x_variant":[
        "Jiangjia Puzi",
        "\u848b\u5bb6\u5821\u5b50",
        "Jiangjia Buzi"
    ],
    "wof:name":"Jiangjia Buzi",
    "wof:placetype":"locality"
},
  "geometry": {"coordinates":[122.44907000000001,40.75459],"type":"Point"}
}