{
  "type": "Feature",
  "properties": {
    "gn:admin1_code":"26.0",
    "gn:asciiname":"Erlangba",
    "gn:country_code":"CN",
    "gn:dem":1018,
    "gn:feature_class":"P",
    "gn:feature_code":"PPL",
    "gn:name":"Erlangba",
    "gn:population":0,
    "gn:timezone":"Asia/Shanghai",
    "iso:country":"CN",
    "name:und_x_variant":[
        "\u4e8c\u90ce\u575d",
        "Erlangbaxiang",
        "\u4e8c\u90ce\u575d\u4e61"
    ],
    "wof:name":"Erlangba",
    "wof:placetype":"locality"
},
  "geometry": {"coordinates":[106.38957000000001,32.81483],"type":"Point"}
}