{
  "type": "Feature",
  "properties": {
    "gn:admin1_code":"26.0",
    "gn:asciiname":"Wangjia Nanshan",
    "gn:country_code":"CN",
    "gn:dem":1475,
    "gn:feature_class":"P",
    "gn:feature_code":"PPL",
    "gn:name":"Wangjia Nanshan",
    "gn:population":0,
    "gn:timezone":"Asia/Shanghai",
    "iso:country":"CN",
    "name:und_x_variant":[
        "\u738b\u5bb6\u5357\u5c71"
    ],
    "wof:name":"Wangjia Nanshan",
    "wof:placetype":"locality"
},
  "geometry": {"coordinates":[107.14069000000001,33.99139],"type":"Point"}
}