{
  "type": "Feature",
  "properties": {
    "gn:admin1_code":"1.0",
    "gn:asciiname":"Baliyangcun",
    "gn:country_code":"CN",
    "gn:dem":22,
    "gn:feature_class":"P",
    "gn:feature_code":"PPL",
    "gn:name":"Baliyangcun",
    "gn:population":0,
    "gn:timezone":"Asia/Shanghai",
    "iso:country":"CN",
    "name:zho_x_preferred":[
        "\u516b\u91cc\u6768\u6751"
    ],
    "wof:name":"Baliyangcun",
    "wof:placetype":"locality"
},
  "geometry": {"coordinates":[117.23838000000001,32.59654],"type":"Point"}
}