{
  "type": "Feature",
  "properties": {
    "gn:admin1_code":"21.0",
    "gn:asciiname":"Gaoying",
    "gn:country_code":"CN",
    "gn:dem":1223,
    "gn:feature_class":"P",
    "gn:feature_code":"PPL",
    "gn:name":"Gaoying",
    "gn:population":0,
    "gn:timezone":"Asia/Shanghai",
    "iso:country":"CN",
    "name:zho_x_preferred":[
        "\u9ad8\u8425"
    ],
    "wof:name":"Gaoying",
    "wof:placetype":"locality"
},
  "geometry": {"coordinates":[105.246,37.5253],"type":"Point"}
}