{
  "type": "Feature",
  "properties": {
    "gn:admin1_code":"2.0",
    "gn:asciiname":"Shuiduihou",
    "gn:country_code":"CN",
    "gn:dem":179,
    "gn:feature_class":"P",
    "gn:feature_code":"PPL",
    "gn:name":"Shuiduihou",
    "gn:population":0,
    "gn:timezone":"Asia/Shanghai",
    "iso:country":"CN",
    "name:zho_x_preferred":[
        "\u6c34\u7893\u540e"
    ],
    "wof:name":"Shuiduihou",
    "wof:placetype":"locality"
},
  "geometry": {"coordinates":[119.79571,28.79734],"type":"Point"}
}