{
  "type": "Feature",
  "properties": {
    "gn:admin1_code":"1.0",
    "gn:asciiname":"Mengshaocun",
    "gn:country_code":"CN",
    "gn:dem":30,
    "gn:feature_class":"P",
    "gn:feature_code":"PPL",
    "gn:name":"Mengshaocun",
    "gn:population":0,
    "gn:timezone":"Asia/Shanghai",
    "iso:country":"CN",
    "name:zho_x_preferred":[
        "\u5b5f\u90b5\u6751"
    ],
    "wof:name":"Mengshaocun",
    "wof:placetype":"locality"
},
  "geometry": {"coordinates":[117.62933999999998,33.96707],"type":"Point"}
}