{
  "type": "Feature",
  "properties": {
    "gn:admin1_code":"3",
    "gn:asciiname":"Shukeng",
    "gn:country_code":"CN",
    "gn:dem":210,
    "gn:feature_class":"P",
    "gn:feature_code":"PPL",
    "gn:name":"Shukeng",
    "gn:population":0,
    "gn:timezone":"Asia/Shanghai",
    "iso:country":"CN",
    "name:zho_x_preferred":[
        "\u85af\u5751"
    ],
    "wof:name":"Shukeng",
    "wof:placetype":"locality"
},
  "geometry": {"coordinates":[114.66177,25.9364],"type":"Point"}
}