{
  "type": "Feature",
  "properties": {
    "gn:admin1_code":"15.0",
    "gn:asciiname":"Lijia Shapozi",
    "gn:country_code":"CN",
    "gn:dem":1997,
    "gn:feature_class":"P",
    "gn:feature_code":"PPL",
    "gn:name":"Lijia Shapozi",
    "gn:population":0,
    "gn:timezone":"Asia/Shanghai",
    "iso:country":"CN",
    "name:zho_x_preferred":[
        "\u674e\u5bb6\u6c99\u5761\u5b50"
    ],
    "wof:name":"Lijia Shapozi",
    "wof:placetype":"locality"
},
  "geometry": {"coordinates":[102.033,38.2138],"type":"Point"}
}