{
  "type": "Feature",
  "properties": {
    "gn:admin1_code":"25.0",
    "gn:asciiname":"Qijiagoucun",
    "gn:country_code":"CN",
    "gn:dem":156,
    "gn:feature_class":"P",
    "gn:feature_code":"PPL",
    "gn:name":"Qijiagoucun",
    "gn:population":0,
    "gn:timezone":"Asia/Shanghai",
    "iso:country":"CN",
    "name:zho_x_preferred":[
        "\u9f50\u5bb6\u6c9f\u6751"
    ],
    "wof:name":"Qijiagoucun",
    "wof:placetype":"locality"
},
  "geometry": {"coordinates":[120.99659,37.55325],"type":"Point"}
}