{
  "type": "Feature",
  "properties": {
    "gn:admin1_code":"25",
    "gn:asciiname":"Lunali",
    "gn:country_code":"CN",
    "gn:dem":46,
    "gn:feature_class":"P",
    "gn:feature_code":"PPL",
    "gn:name":"Lunali",
    "gn:population":0,
    "gn:timezone":"Asia/Shanghai",
    "iso:country":"CN",
    "name:zho_x_preferred":[
        "\u8def\u90a3\u91cc"
    ],
    "wof:name":"Lunali",
    "wof:placetype":"locality"
},
  "geometry": {"coordinates":[116.01600000000001,35.9563],"type":"Point"}
}