{
  "type": "Feature",
  "properties": {
    "gn:admin1_code":"30.0",
    "gn:asciiname":"Huadongcun",
    "gn:country_code":"CN",
    "gn:dem":158,
    "gn:feature_class":"P",
    "gn:feature_code":"PPL",
    "gn:name":"Huadongcun",
    "gn:population":0,
    "gn:timezone":"Asia/Shanghai",
    "iso:country":"CN",
    "name:zho_x_preferred":[
        "\u534e\u4e1c\u6751"
    ],
    "wof:name":"Huadongcun",
    "wof:placetype":"locality"
},
  "geometry": {"coordinates":[116.27804999999999,24.09421],"type":"Point"}
}