{
  "type": "Feature",
  "properties": {
    "gn:admin1_code":"12.0",
    "gn:asciiname":"Huangjiutang Renjia",
    "gn:country_code":"CN",
    "gn:dem":57,
    "gn:feature_class":"P",
    "gn:feature_code":"PPL",
    "gn:name":"Huangjiutang Renjia",
    "gn:population":0,
    "gn:timezone":"Asia/Shanghai",
    "iso:country":"CN",
    "name:zho_x_preferred":[
        "\u9ec4\u4e5d\u5802\u4efb\u5bb6"
    ],
    "wof:name":"Huangjiutang Renjia",
    "wof:placetype":"locality"
},
  "geometry": {"coordinates":[113.87469,29.77313],"type":"Point"}
}