{
  "type": "Feature",
  "properties": {
    "gn:admin1_code":"6.0",
    "gn:asciiname":"Qierongtong",
    "gn:country_code":"CN",
    "gn:dem":4036,
    "gn:feature_class":"P",
    "gn:feature_code":"PPL",
    "gn:name":"Qierongtong",
    "gn:population":0,
    "gn:timezone":"Asia/Urumqi",
    "iso:country":"CN",
    "name:zho_x_preferred":[
        "\u4e14\u8363\u901a"
    ],
    "wof:name":"Qierongtong",
    "wof:placetype":"locality"
},
  "geometry": {"coordinates":[96.75387000000001,32.34817],"type":"Point"}
}