{
  "type": "Feature",
  "properties": {
    "gn:admin1_code":"4.0",
    "gn:asciiname":"Baotancun",
    "gn:country_code":"CN",
    "gn:dem":26,
    "gn:feature_class":"P",
    "gn:feature_code":"PPL",
    "gn:name":"Baotancun",
    "gn:population":0,
    "gn:timezone":"Asia/Shanghai",
    "iso:country":"CN",
    "name:zho_x_preferred":[
        "\u9c8d\u6ee9\u6751"
    ],
    "wof:name":"Baotancun",
    "wof:placetype":"locality"
},
  "geometry": {"coordinates":[117.85912999999999,34.00207],"type":"Point"}
}