{
  "type": "Feature",
  "properties": {
    "gn:admin1_code":"31",
    "gn:asciiname":"Zhongrui Nongchang",
    "gn:country_code":"CN",
    "gn:dem":67,
    "gn:feature_class":"P",
    "gn:feature_code":"PPLF",
    "gn:name":"Zhongrui Nongchang",
    "gn:population":0,
    "gn:timezone":"Asia/Shanghai",
    "iso:country":"CN",
    "wof:name":"Zhongrui Nongchang",
    "wof:placetype":"locality"
},
  "geometry": {"coordinates":[110.30528,19.24722],"type":"Point"}
}