{
  "type": "Feature",
  "properties": {
    "gn:admin1_code":"2.0",
    "gn:asciiname":"Yingtou",
    "gn:country_code":"CN",
    "gn:dem":470,
    "gn:feature_class":"P",
    "gn:feature_code":"PPL",
    "gn:name":"Yingtou",
    "gn:population":0,
    "gn:timezone":"Asia/Shanghai",
    "iso:country":"CN",
    "name:zho_x_preferred":[
        "\u8425\u5934"
    ],
    "wof:name":"Yingtou",
    "wof:placetype":"locality"
},
  "geometry": {"coordinates":[118.85816,28.55569],"type":"Point"}
}