{
  "type": "Feature",
  "properties": {
    "gn:admin1_code":"04",
    "gn:asciiname":"Gaomiao",
    "gn:country_code":"CN",
    "gn:dem":50,
    "gn:feature_class":"P",
    "gn:feature_code":"PPL",
    "gn:name":"Gaomiao",
    "gn:population":0,
    "gn:timezone":"Asia/Shanghai",
    "iso:country":"CN",
    "name:und_x_variant":[
        "Kao-miao",
        "Hsi-kao-miao",
        "Gaomiao"
    ],
    "name:zho_x_preferred":[
        "\u9ad8\u5e99"
    ],
    "wof:name":"Gaomiao",
    "wof:placetype":"locality"
},
  "geometry": {"coordinates":[118.51312,32.86432],"type":"Point"}
}