{
  "type": "Feature",
  "properties": {
    "gn:admin1_code":"1.0",
    "gn:asciiname":"Zhongxinzhuangcun",
    "gn:country_code":"CN",
    "gn:dem":39,
    "gn:feature_class":"P",
    "gn:feature_code":"PPL",
    "gn:name":"Zhongxinzhuangcun",
    "gn:population":0,
    "gn:timezone":"Asia/Shanghai",
    "iso:country":"CN",
    "name:zho_x_preferred":[
        "\u5fe0\u5fc3\u5e84\u6751"
    ],
    "wof:name":"Zhongxinzhuangcun",
    "wof:placetype":"locality"
},
  "geometry": {"coordinates":[115.68633,33.56517],"type":"Point"}
}