{
  "type": "Feature",
  "properties": {
    "gn:admin1_code":"2.0",
    "gn:asciiname":"Chunjian",
    "gn:country_code":"CN",
    "gn:dem":49,
    "gn:feature_class":"P",
    "gn:feature_code":"PPLA4",
    "gn:name":"Chunjian",
    "gn:population":0,
    "gn:timezone":"Asia/Shanghai",
    "iso:country":"CN",
    "name:und_x_variant":[
        "\u6625\u5efa",
        "Chunjian Xiang",
        "\u6625\u5efa\u4e61"
    ],
    "wof:name":"Chunjian",
    "wof:placetype":"locality"
},
  "geometry": {"coordinates":[119.82653000000001,30.07639],"type":"Point"}
}