{
  "type": "Feature",
  "properties": {
    "gn:admin1_code":"32.0",
    "gn:asciiname":"Menkanshi",
    "gn:country_code":"CN",
    "gn:dem":1230,
    "gn:feature_class":"P",
    "gn:feature_code":"PPL",
    "gn:name":"Menkanshi",
    "gn:population":0,
    "gn:timezone":"Asia/Shanghai",
    "iso:country":"CN",
    "name:zho_x_preferred":[
        "\u95e8\u574e\u77f3"
    ],
    "wof:name":"Menkanshi",
    "wof:placetype":"locality"
},
  "geometry": {"coordinates":[104.78442,32.41402],"type":"Point"}
}