{
  "type": "Feature",
  "properties": {
    "gn:admin1_code":"30.0",
    "gn:asciiname":"Tieluochang",
    "gn:country_code":"CN",
    "gn:dem":374,
    "gn:feature_class":"P",
    "gn:feature_code":"PPL",
    "gn:name":"Tieluochang",
    "gn:population":0,
    "gn:timezone":"Asia/Shanghai",
    "iso:country":"CN",
    "name:zho_x_preferred":[
        "Tieluochang"
    ],
    "name:zho_x_variant":[
        "\u94c1\u7f57\u573a"
    ],
    "wof:name":"Tieluochang",
    "wof:placetype":"locality"
},
  "geometry": {"coordinates":[114.43179000000001,24.3295],"type":"Point"}
}