{
  "type": "Feature",
  "properties": {
    "gn:admin1_code":"25.0",
    "gn:asciiname":"Duotuancun",
    "gn:country_code":"CN",
    "gn:dem":125,
    "gn:feature_class":"P",
    "gn:feature_code":"PPL",
    "gn:name":"Duotuancun",
    "gn:population":0,
    "gn:timezone":"Asia/Shanghai",
    "iso:country":"CN",
    "name:zho_x_preferred":[
        "\u94ce\u7583\u6751"
    ],
    "wof:name":"Duotuancun",
    "wof:placetype":"locality"
},
  "geometry": {"coordinates":[121.32829,37.21424],"type":"Point"}
}