{
  "type": "Feature",
  "properties": {
    "gn:admin1_code":"18",
    "gn:asciiname":"Wangjiawan",
    "gn:country_code":"CN",
    "gn:dem":1205,
    "gn:feature_class":"P",
    "gn:feature_code":"PPL",
    "gn:name":"Wangjiawan",
    "gn:population":0,
    "gn:timezone":"Asia/Shanghai",
    "iso:country":"CN",
    "name:zho_x_preferred":[
        "\u738b\u5bb6\u6e7e"
    ],
    "wof:name":"Wangjiawan",
    "wof:placetype":"locality"
},
  "geometry": {"coordinates":[106.92700000000001,25.7212],"type":"Point"}
}