{
  "type": "Feature",
  "properties": {
    "gn:admin1_code":"24",
    "gn:asciiname":"Quyu",
    "gn:country_code":"CN",
    "gn:dem":858,
    "gn:feature_class":"P",
    "gn:feature_code":"PPL",
    "gn:name":"Quyu",
    "gn:population":0,
    "gn:timezone":"Asia/Shanghai",
    "iso:country":"CN",
    "name:und_x_variant":[
        "Ch\u2019\u00fc-y\u00fc-ts\u2019un",
        "Ch\u2019\u00fc-y\u00fc",
        "Quyu"
    ],
    "name:zho_x_preferred":[
        "\u66f2\u5cea"
    ],
    "wof:name":"Quyu",
    "wof:placetype":"locality"
},
  "geometry": {"coordinates":[111.22991,39.27208],"type":"Point"}
}