{
  "type": "Feature",
  "properties": {
    "gn:admin1_code":"26.0",
    "gn:asciiname":"Dongchousang",
    "gn:country_code":"CN",
    "gn:dem":887,
    "gn:feature_class":"P",
    "gn:feature_code":"PPL",
    "gn:name":"Dongchousang",
    "gn:population":0,
    "gn:timezone":"Asia/Shanghai",
    "iso:country":"CN",
    "name:zho_x_preferred":[
        "\u4e1c\u7a20\u6851"
    ],
    "wof:name":"Dongchousang",
    "wof:placetype":"locality"
},
  "geometry": {"coordinates":[108.88882,34.95383],"type":"Point"}
}