{
  "type": "Feature",
  "properties": {
    "gn:admin1_code":"10",
    "gn:asciiname":"Chagou",
    "gn:country_code":"CN",
    "gn:dem":658,
    "gn:feature_class":"P",
    "gn:feature_code":"PPL",
    "gn:name":"Chagou",
    "gn:population":0,
    "gn:timezone":"Asia/Shanghai",
    "iso:country":"CN",
    "name:zho_x_preferred":[
        "\u5c94\u6c9f"
    ],
    "wof:name":"Chagou",
    "wof:placetype":"locality"
},
  "geometry": {"coordinates":[118.65600999999999,40.51132],"type":"Point"}
}