{
  "type": "Feature",
  "properties": {
    "gn:admin1_code":"32.0",
    "gn:asciiname":"Zhiping",
    "gn:country_code":"CN",
    "gn:dem":359,
    "gn:feature_class":"P",
    "gn:feature_code":"PPL",
    "gn:name":"Zhiping",
    "gn:population":0,
    "gn:timezone":"Asia/Shanghai",
    "iso:country":"CN",
    "name:zho_x_preferred":[
        "\u667a\u5e73"
    ],
    "wof:name":"Zhiping",
    "wof:placetype":"locality"
},
  "geometry": {"coordinates":[105.12,30.5867],"type":"Point"}
}