{
  "type": "Feature",
  "properties": {
    "gn:admin1_code":"11",
    "gn:asciiname":"Neijiacun",
    "gn:country_code":"CN",
    "gn:dem":281,
    "gn:feature_class":"P",
    "gn:feature_code":"PPL",
    "gn:name":"Neijiacun",
    "gn:population":0,
    "gn:timezone":"Asia/Shanghai",
    "iso:country":"CN",
    "wof:name":"Neijiacun",
    "wof:placetype":"locality"
},
  "geometry": {"coordinates":[110.08556000000002,27.66861],"type":"Point"}
}