{
  "type": "Feature",
  "properties": {
    "gn:admin1_code":"1.0",
    "gn:asciiname":"Dasunzhuangcun",
    "gn:country_code":"CN",
    "gn:dem":41,
    "gn:feature_class":"P",
    "gn:feature_code":"PPL",
    "gn:name":"Dasunzhuangcun",
    "gn:population":0,
    "gn:timezone":"Asia/Shanghai",
    "iso:country":"CN",
    "name:und_x_variant":[
        "Dasunzhuang"
    ],
    "name:zho_x_preferred":[
        "\u5927\u5b59\u5e84\u6751"
    ],
    "wof:name":"Dasunzhuangcun",
    "wof:placetype":"locality"
},
  "geometry": {"coordinates":[116.75162,34.22161],"type":"Point"}
}