{
  "type": "Feature",
  "properties": {
    "gn:admin1_code":"29",
    "gn:asciiname":"Sanzhuanwan",
    "gn:country_code":"CN",
    "gn:dem":2119,
    "gn:feature_class":"P",
    "gn:feature_code":"PPL",
    "gn:name":"Sanzhuanwan",
    "gn:population":0,
    "gn:timezone":"Asia/Shanghai",
    "iso:country":"CN",
    "name:zho_x_preferred":[
        "\u4e09\u8f6c\u5f2f"
    ],
    "wof:name":"Sanzhuanwan",
    "wof:placetype":"locality"
},
  "geometry": {"coordinates":[102.94168000000001,24.84302000000001],"type":"Point"}
}