{
  "type": "Feature",
  "properties": {
    "gn:admin1_code":"15.0",
    "gn:asciiname":"Huasheng",
    "gn:country_code":"CN",
    "gn:dem":1554,
    "gn:feature_class":"P",
    "gn:feature_code":"PPL",
    "gn:name":"Huasheng",
    "gn:population":0,
    "gn:timezone":"Asia/Shanghai",
    "iso:country":"CN",
    "name:zho_x_preferred":[
        "\u82b1\u76db"
    ],
    "wof:name":"Huasheng",
    "wof:placetype":"locality"
},
  "geometry": {"coordinates":[102.736,37.8682],"type":"Point"}
}