{
  "type": "Feature",
  "properties": {
    "gn:admin1_code":"4.0",
    "gn:asciiname":"Nanguan",
    "gn:country_code":"CN",
    "gn:dem":3,
    "gn:feature_class":"P",
    "gn:feature_code":"PPL",
    "gn:name":"Nanguan",
    "gn:population":0,
    "gn:timezone":"Asia/Shanghai",
    "iso:country":"CN",
    "name:ceb_x_preferred":[
        "Nanguan"
    ],
    "name:deu_x_preferred":[
        "Nanguan"
    ],
    "name:fra_x_preferred":[
        "Nanguan"
    ],
    "name:zho_x_preferred":[
        "Nanguan"
    ],
    "name:zho_x_variant":[
        "\u5357\u5b98"
    ],
    "wof:name":"Nanguan",
    "wof:placetype":"locality"
},
  "geometry": {"coordinates":[119.87629,33.19427],"type":"Point"}
}