{
  "type": "Feature",
  "properties": {
    "gn:admin1_code":"7",
    "gn:asciiname":"Xiayuan",
    "gn:country_code":"CN",
    "gn:dem":1019,
    "gn:feature_class":"P",
    "gn:feature_code":"PPL",
    "gn:name":"Xiayuan",
    "gn:population":0,
    "gn:timezone":"Asia/Shanghai",
    "iso:country":"CN",
    "name:und_x_variant":[
        "\u4e0b\u56ed"
    ],
    "wof:name":"Xiayuan",
    "wof:placetype":"locality"
},
  "geometry": {"coordinates":[119.06194000000001,27.2825],"type":"Point"}
}