{
  "type": "Feature",
  "properties": {
    "gn:admin1_code":"22.0",
    "gn:asciiname":"Huangyingcun",
    "gn:country_code":"CN",
    "gn:dem":728,
    "gn:feature_class":"P",
    "gn:feature_code":"PPL",
    "gn:name":"Huangyingcun",
    "gn:population":0,
    "gn:timezone":"Asia/Shanghai",
    "iso:country":"CN",
    "name:zho_x_preferred":[
        "\u9ec4\u8425\u6751"
    ],
    "wof:name":"Huangyingcun",
    "wof:placetype":"locality"
},
  "geometry": {"coordinates":[116.5829,40.96471],"type":"Point"}
}