{
  "type": "Feature",
  "properties": {
    "gn:admin1_code":"26",
    "gn:asciiname":"Jianlicun",
    "gn:country_code":"CN",
    "gn:dem":409,
    "gn:feature_class":"P",
    "gn:feature_code":"PPL",
    "gn:name":"Jianlicun",
    "gn:population":0,
    "gn:timezone":"Asia/Shanghai",
    "iso:country":"CN",
    "name:und_x_variant":[
        "Jianli",
        "Jianlicun"
    ],
    "name:zho_x_preferred":[
        "\u5efa\u7acb"
    ],
    "name:zho_x_variant":[
        "\u5efa\u7acb\u6751"
    ],
    "wof:name":"Jianlicun",
    "wof:placetype":"locality"
},
  "geometry": {"coordinates":[108.85720000000001,34.53993],"type":"Point"}
}