{
  "type": "Feature",
  "properties": {
    "gn:admin1_code":"3.0",
    "gn:asciiname":"Yanshangcun",
    "gn:country_code":"CN",
    "gn:dem":25,
    "gn:feature_class":"P",
    "gn:feature_code":"PPL",
    "gn:name":"Yanshangcun",
    "gn:population":0,
    "gn:timezone":"Asia/Shanghai",
    "iso:country":"CN",
    "name:und_x_variant":[
        "\u5ca9\u4e0a\u6751"
    ],
    "wof:name":"Yanshangcun",
    "wof:placetype":"locality"
},
  "geometry": {"coordinates":[115.92912,28.22431],"type":"Point"}
}