{
  "type": "Feature",
  "properties": {
    "gn:admin1_code":"25",
    "gn:asciiname":"Yangshoujia",
    "gn:country_code":"CN",
    "gn:dem":18,
    "gn:feature_class":"P",
    "gn:feature_code":"PPL",
    "gn:name":"Yangshoujia",
    "gn:population":0,
    "gn:timezone":"Asia/Shanghai",
    "iso:country":"CN",
    "name:zho_x_preferred":[
        "\u6768\u5bff\u5bb6"
    ],
    "wof:name":"Yangshoujia",
    "wof:placetype":"locality"
},
  "geometry": {"coordinates":[116.952,37.1901],"type":"Point"}
}