{
  "type": "Feature",
  "properties": {
    "gn:admin1_code":"29.0",
    "gn:asciiname":"Lasilong",
    "gn:country_code":"CN",
    "gn:dem":1743,
    "gn:feature_class":"P",
    "gn:feature_code":"PPL",
    "gn:name":"Lasilong",
    "gn:population":0,
    "gn:timezone":"Asia/Shanghai",
    "iso:country":"CN",
    "name:zho_x_preferred":[
        "\u62c9\u65af\u9647"
    ],
    "wof:name":"Lasilong",
    "wof:placetype":"locality"
},
  "geometry": {"coordinates":[99.54949999999999,22.8166],"type":"Point"}
}