{
  "type": "Feature",
  "properties": {
    "gn:admin1_code":"9.0",
    "gn:asciiname":"Luanshipa",
    "gn:country_code":"CN",
    "gn:dem":363,
    "gn:feature_class":"P",
    "gn:feature_code":"PPL",
    "gn:name":"Luanshipa",
    "gn:population":0,
    "gn:timezone":"Asia/Shanghai",
    "iso:country":"CN",
    "name:zho_x_preferred":[
        "\u4e71\u77f3\u722c"
    ],
    "wof:name":"Luanshipa",
    "wof:placetype":"locality"
},
  "geometry": {"coordinates":[113.88943999999999,31.99458],"type":"Point"}
}