{
  "type": "Feature",
  "properties": {
    "gn:admin1_code":"8.0",
    "gn:asciiname":"Qujia Weizi",
    "gn:country_code":"CN",
    "gn:dem":172,
    "gn:feature_class":"P",
    "gn:feature_code":"PPL",
    "gn:name":"Qujia Weizi",
    "gn:population":0,
    "gn:timezone":"Asia/Shanghai",
    "iso:country":"CN",
    "name:zho_x_preferred":[
        "\u66f2\u5bb6\u56f4\u5b50"
    ],
    "wof:name":"Qujia Weizi",
    "wof:placetype":"locality"
},
  "geometry": {"coordinates":[125.53298999999998,46.22248],"type":"Point"}
}