{
  "type": "Feature",
  "properties": {
    "iso:country":"CN",
    "qs:name":"\u592a\u8c37",
    "qs:name_adm0":"\u4e2d\u570b",
    "qs:name_adm1":"\u5c71\u897f\u7701",
    "qs:photos":69,
    "qs:photos_1k":14,
    "qs:photos_9k":1,
    "qs:photos_9r":2,
    "qs:photos_all":69,
    "qs:photos_sr":2,
    "qs:placetype":"Town",
    "qs:pop_sr":"0",
    "wof:name":"\u592a\u8c37",
    "wof:placetype":"locality"
},
  "geometry": {"coordinates":[112.545833,37.422662],"type":"Point"}
}