{
  "type": "Feature",
  "properties": {
    "gn:admin1_code":"8.0",
    "gn:asciiname":"Yabazigou",
    "gn:country_code":"CN",
    "gn:dem":261,
    "gn:feature_class":"P",
    "gn:feature_code":"PPL",
    "gn:name":"Yabazigou",
    "gn:population":0,
    "gn:timezone":"Asia/Shanghai",
    "iso:country":"CN",
    "name:und_x_variant":[
        "\u54d1\u5df4\u5b50\u6c9f"
    ],
    "wof:name":"Yabazigou",
    "wof:placetype":"locality"
},
  "geometry": {"coordinates":[130.91704999999999,43.89722],"type":"Point"}
}