{
  "type": "Feature",
  "properties": {
    "gn:admin1_code":"04",
    "gn:asciiname":"Geqiao",
    "gn:country_code":"CN",
    "gn:dem":6,
    "gn:feature_class":"P",
    "gn:feature_code":"PPL",
    "gn:name":"Geqiao",
    "gn:population":0,
    "gn:timezone":"Asia/Shanghai",
    "iso:country":"CN",
    "name:und_x_variant":[
        "Ko-chia-ch\u2019iao",
        "Geqiao"
    ],
    "name:zho_x_preferred":[
        "\u845b\u6865"
    ],
    "wof:name":"Geqiao",
    "wof:placetype":"locality"
},
  "geometry": {"coordinates":[118.83599,32.25314],"type":"Point"}
}