{
  "type": "Feature",
  "properties": {
    "gn:admin1_code":"18",
    "gn:asciiname":"Zhaochiba",
    "gn:country_code":"CN",
    "gn:dem":730,
    "gn:feature_class":"P",
    "gn:feature_code":"PPL",
    "gn:name":"Zhaochiba",
    "gn:population":0,
    "gn:timezone":"Asia/Shanghai",
    "iso:country":"CN",
    "name:zho_x_preferred":[
        "\u8d75\u6c60\u575d"
    ],
    "wof:name":"Zhaochiba",
    "wof:placetype":"locality"
},
  "geometry": {"coordinates":[107.88200000000001,28.3831],"type":"Point"}
}