{
  "type": "Feature",
  "properties": {
    "gn:admin1_code":"24.0",
    "gn:asciiname":"Louzituancun",
    "gn:country_code":"CN",
    "gn:dem":1207,
    "gn:feature_class":"P",
    "gn:feature_code":"PPL",
    "gn:name":"Louzituancun",
    "gn:population":0,
    "gn:timezone":"Asia/Shanghai",
    "iso:country":"CN",
    "name:zho_x_preferred":[
        "\u697c\u5b50\u7583\u6751"
    ],
    "wof:name":"Louzituancun",
    "wof:placetype":"locality"
},
  "geometry": {"coordinates":[114.13336,40.27357],"type":"Point"}
}