{
  "type": "Feature",
  "properties": {
    "gn:admin1_code":"16",
    "gn:asciiname":"Tian'etang",
    "gn:country_code":"CN",
    "gn:dem":382,
    "gn:feature_class":"P",
    "gn:feature_code":"PPL",
    "gn:name":"Tian\u2019etang",
    "gn:population":0,
    "gn:timezone":"Asia/Shanghai",
    "iso:country":"CN",
    "name:und_x_variant":[
        "Tian\u2019etang"
    ],
    "name:zho_x_preferred":[
        "\u5929\u9e45\u5802"
    ],
    "wof:name":"Tian'etang",
    "wof:placetype":"locality"
},
  "geometry": {"coordinates":[110.498,24.4764],"type":"Point"}
}