{
  "type": "Feature",
  "properties": {
    "gn:admin1_code":"10",
    "gn:asciiname":"Yangshugou",
    "gn:country_code":"CN",
    "gn:dem":558,
    "gn:feature_class":"P",
    "gn:feature_code":"PPL",
    "gn:name":"Yangshugou",
    "gn:population":0,
    "gn:timezone":"Asia/Shanghai",
    "iso:country":"CN",
    "name:und_x_variant":[
        "Yang-shu-kou",
        "Yangshugou"
    ],
    "name:zho_x_preferred":[
        "\u6768\u6811\u6c9f"
    ],
    "wof:name":"Yangshugou",
    "wof:placetype":"locality"
},
  "geometry": {"coordinates":[118.70149000000001,40.54192000000001],"type":"Point"}
}