{
  "type": "Feature",
  "properties": {
    "gn:admin1_code":"11.0",
    "gn:asciiname":"Jianxin Nongchang Liudadui",
    "gn:country_code":"CN",
    "gn:dem":31,
    "gn:feature_class":"P",
    "gn:feature_code":"PPLF",
    "gn:name":"Jianxin Nongchang Liudadui",
    "gn:population":0,
    "gn:timezone":"Asia/Shanghai",
    "iso:country":"CN",
    "name:zho_x_preferred":[
        "\u5efa\u65b0\u519c\u573a\u516d\u5927\u961f"
    ],
    "wof:name":"Jianxin Nongchang Liudadui",
    "wof:placetype":"locality"
},
  "geometry": {"coordinates":[112.87584,29.49576],"type":"Point"}
}