{
  "type": "Feature",
  "properties": {
    "gn:admin1_code":"7",
    "gn:asciiname":"Lucuo",
    "gn:country_code":"CN",
    "gn:dem":17,
    "gn:feature_class":"P",
    "gn:feature_code":"PPL",
    "gn:name":"Lucuo",
    "gn:population":0,
    "gn:timezone":"Asia/Shanghai",
    "iso:country":"CN",
    "name:zho_x_preferred":[
        "\u7089\u539d"
    ],
    "wof:name":"Lucuo",
    "wof:placetype":"locality"
},
  "geometry": {"coordinates":[119.32316000000002,25.24346],"type":"Point"}
}