{
  "type": "Feature",
  "properties": {
    "gn:admin1_code":"15.0",
    "gn:asciiname":"Liujiashan",
    "gn:country_code":"CN",
    "gn:dem":1424,
    "gn:feature_class":"P",
    "gn:feature_code":"PPL",
    "gn:name":"Liujiashan",
    "gn:population":0,
    "gn:timezone":"Asia/Shanghai",
    "iso:country":"CN",
    "name:und_x_variant":[
        "\u5218\u5bb6\u5c71"
    ],
    "wof:name":"Liujiashan",
    "wof:placetype":"locality"
},
  "geometry": {"coordinates":[105.5389,33.37212],"type":"Point"}
}