{
  "type": "Feature",
  "properties": {
    "gn:admin1_code":"4.0",
    "gn:asciiname":"Fankou",
    "gn:country_code":"CN",
    "gn:dem":2,
    "gn:feature_class":"P",
    "gn:feature_code":"PPL",
    "gn:name":"Fankou",
    "gn:population":0,
    "gn:timezone":"Asia/Shanghai",
    "iso:country":"CN",
    "name:zho_x_preferred":[
        "Fankou"
    ],
    "name:zho_x_variant":[
        "\u8303\u53e3"
    ],
    "wof:name":"Fankou",
    "wof:placetype":"locality"
},
  "geometry": {"coordinates":[119.13075000000001,34.74887],"type":"Point"}
}