{
  "type": "Feature",
  "properties": {
    "gn:admin1_code":"11",
    "gn:asciiname":"Maopingling",
    "gn:country_code":"CN",
    "gn:dem":780,
    "gn:feature_class":"P",
    "gn:feature_code":"PPL",
    "gn:name":"Maopingling",
    "gn:population":0,
    "gn:timezone":"Asia/Shanghai",
    "iso:country":"CN",
    "name:und_x_variant":[
        "\u6bdb\u576a\u5cad",
        "Maopingling"
    ],
    "wof:name":"Maopingling",
    "wof:placetype":"locality"
},
  "geometry": {"coordinates":[111.42139,25.82306],"type":"Point"}
}