{
  "type": "Feature",
  "properties": {
    "gn:admin1_code":"9.0",
    "gn:asciiname":"Dawanggou",
    "gn:country_code":"CN",
    "gn:dem":176,
    "gn:feature_class":"P",
    "gn:feature_code":"PPL",
    "gn:name":"Dawanggou",
    "gn:population":0,
    "gn:timezone":"Asia/Shanghai",
    "iso:country":"CN",
    "name:zho_x_preferred":[
        "\u5927\u738b\u6c9f"
    ],
    "wof:name":"Dawanggou",
    "wof:placetype":"locality"
},
  "geometry": {"coordinates":[112.46243,33.14557],"type":"Point"}
}