{
  "type": "Feature",
  "properties": {
    "gn:admin1_code":"32.0",
    "gn:asciiname":"Wangjiazui",
    "gn:country_code":"CN",
    "gn:dem":750,
    "gn:feature_class":"P",
    "gn:feature_code":"PPL",
    "gn:name":"Wangjiazui",
    "gn:population":0,
    "gn:timezone":"Asia/Shanghai",
    "iso:country":"CN",
    "name:zho_x_preferred":[
        "\u738b\u5bb6\u5480"
    ],
    "wof:name":"Wangjiazui",
    "wof:placetype":"locality"
},
  "geometry": {"coordinates":[105.795,32.1808],"type":"Point"}
}