{
  "type": "Feature",
  "properties": {
    "gn:admin1_code":"18",
    "gn:asciiname":"Lengfengkou",
    "gn:country_code":"CN",
    "gn:dem":1611,
    "gn:feature_class":"P",
    "gn:feature_code":"PPL",
    "gn:name":"Lengfengkou",
    "gn:population":0,
    "gn:timezone":"Asia/Shanghai",
    "iso:country":"CN",
    "name:zho_x_preferred":[
        "\u51b7\u98ce\u53e3"
    ],
    "wof:name":"Lengfengkou",
    "wof:placetype":"locality"
},
  "geometry": {"coordinates":[104.965,25.6001],"type":"Point"}
}