{
  "type": "Feature",
  "properties": {
    "gn:admin1_code":"14",
    "gn:asciiname":"Niangguolie",
    "gn:country_code":"CN",
    "gn:dem":4787,
    "gn:feature_class":"P",
    "gn:feature_code":"PPL",
    "gn:name":"Niangguolie",
    "gn:population":0,
    "gn:timezone":"Asia/Urumqi",
    "iso:country":"CN",
    "name:zho_x_preferred":[
        "\u5a18\u679c\u5217"
    ],
    "wof:name":"Niangguolie",
    "wof:placetype":"locality"
},
  "geometry": {"coordinates":[89.9855,29.2397],"type":"Point"}
}