{
  "type": "Feature",
  "properties": {
    "gn:admin1_code":"32.0",
    "gn:asciiname":"Aqicun",
    "gn:country_code":"CN",
    "gn:dem":1636,
    "gn:feature_class":"P",
    "gn:feature_code":"PPL",
    "gn:name":"Aqicun",
    "gn:population":0,
    "gn:timezone":"Asia/Shanghai",
    "iso:country":"CN",
    "name:zho_x_preferred":[
        "\u963f\u4e03\u6751"
    ],
    "wof:name":"Aqicun",
    "wof:placetype":"locality"
},
  "geometry": {"coordinates":[102.14076,27.62025],"type":"Point"}
}