{
  "type": "Feature",
  "properties": {
    "gn:admin1_code":"32.0",
    "gn:asciiname":"Nanjingchang",
    "gn:country_code":"CN",
    "gn:dem":263,
    "gn:feature_class":"P",
    "gn:feature_code":"PPL",
    "gn:name":"Nanjingchang",
    "gn:population":0,
    "gn:timezone":"Asia/Shanghai",
    "iso:country":"CN",
    "name:zho_x_preferred":[
        "\u5357\u4e95\u573a"
    ],
    "wof:name":"Nanjingchang",
    "wof:placetype":"locality"
},
  "geometry": {"coordinates":[105.20771000000001,28.82372],"type":"Point"}
}