{
  "type": "Feature",
  "properties": {
    "gn:admin1_code":"05",
    "gn:asciiname":"Dafangshen",
    "gn:cc2":"CN",
    "gn:country_code":"CN",
    "gn:dem":211,
    "gn:feature_class":"P",
    "gn:feature_code":"PPL",
    "gn:name":"Dafangshen",
    "gn:population":0,
    "gn:timezone":"Asia/Shanghai",
    "iso:country":"CN",
    "name:und_x_variant":[
        "Te-hui-hsien",
        "Te-hui",
        "Tehhwei",
        "Ta-fang-shen",
        "Dafangshen"
    ],
    "wof:name":"Dafangshen",
    "wof:placetype":"locality"
},
  "geometry": {"coordinates":[125.91667,44.58333],"type":"Point"}
}