{
  "type": "Feature",
  "properties": {
    "gn:admin1_code":"16",
    "gn:asciiname":"Gongzhengjie",
    "gn:cc2":"CN",
    "gn:country_code":"CN",
    "gn:dem":316,
    "gn:feature_class":"P",
    "gn:feature_code":"PPL",
    "gn:name":"Gongzhengjie",
    "gn:population":0,
    "gn:timezone":"Asia/Shanghai",
    "iso:country":"CN",
    "name:und_x_variant":[
        "Kung-cheng-chieh",
        "Kung-cheng",
        "Kung-cheng-hs\u00fc",
        "Gongzhengjie"
    ],
    "wof:name":"Gongzhengjie",
    "wof:placetype":"locality"
},
  "geometry": {"coordinates":[110.05,25.55],"type":"Point"}
}