{
  "type": "Feature",
  "properties": {
    "gn:admin1_code":"19.0",
    "gn:asciiname":"Huahonggou",
    "gn:country_code":"CN",
    "gn:dem":188,
    "gn:feature_class":"P",
    "gn:feature_code":"PPL",
    "gn:name":"Huahonggou",
    "gn:population":0,
    "gn:timezone":"Asia/Shanghai",
    "iso:country":"CN",
    "name:zho_x_preferred":[
        "\u82b1\u7ea2\u6c9f"
    ],
    "wof:name":"Huahonggou",
    "wof:placetype":"locality"
},
  "geometry": {"coordinates":[123.935,42.1132],"type":"Point"}
}