{
  "type": "Feature",
  "properties": {
    "gn:admin1_code":"15.0",
    "gn:asciiname":"Zhangdujiagou",
    "gn:country_code":"CN",
    "gn:dem":1864,
    "gn:feature_class":"P",
    "gn:feature_code":"PPL",
    "gn:name":"Zhangdujiagou",
    "gn:population":0,
    "gn:timezone":"Asia/Shanghai",
    "iso:country":"CN",
    "name:und_x_variant":[
        "\u5f20\u675c\u5bb6\u6c9f"
    ],
    "wof:name":"Zhangdujiagou",
    "wof:placetype":"locality"
},
  "geometry": {"coordinates":[105.94353999999998,35.44788],"type":"Point"}
}