{
  "type": "Feature",
  "properties": {
    "gn:admin1_code":"11.0",
    "gn:asciiname":"Jiangjiachong",
    "gn:country_code":"CN",
    "gn:dem":277,
    "gn:feature_class":"P",
    "gn:feature_code":"PPL",
    "gn:name":"Jiangjiachong",
    "gn:population":0,
    "gn:timezone":"Asia/Shanghai",
    "iso:country":"CN",
    "name:zho_x_preferred":[
        "\u848b\u5bb6\u51b2"
    ],
    "wof:name":"Jiangjiachong",
    "wof:placetype":"locality"
},
  "geometry": {"coordinates":[111.96738000000001,28.05782],"type":"Point"}
}