{
  "type": "Feature",
  "properties": {
    "gn:admin1_code":"32.0",
    "gn:asciiname":"Tagu",
    "gn:country_code":"CN",
    "gn:dem":561,
    "gn:feature_class":"P",
    "gn:feature_code":"PPL",
    "gn:name":"Tagu",
    "gn:population":0,
    "gn:timezone":"Asia/Shanghai",
    "iso:country":"CN",
    "name:mya_x_preferred":[
        "\u1010\u1014\u103a\u1001\u1030\u1038\u101c"
    ],
    "name:zho_x_preferred":[
        "\u631e\u8c37"
    ],
    "wof:name":"Tagu",
    "wof:placetype":"locality"
},
  "geometry": {"coordinates":[103.434,30.3508],"type":"Point"}
}