{
  "type": "Feature",
  "properties": {
    "gn:admin1_code":"18",
    "gn:asciiname":"Hundunping",
    "gn:country_code":"CN",
    "gn:dem":939,
    "gn:feature_class":"P",
    "gn:feature_code":"PPL",
    "gn:name":"Hundunping",
    "gn:population":0,
    "gn:timezone":"Asia/Shanghai",
    "iso:country":"CN",
    "name:zho_x_preferred":[
        "\u6df7\u6c8c\u576a"
    ],
    "wof:name":"Hundunping",
    "wof:placetype":"locality"
},
  "geometry": {"coordinates":[105.78100000000001,28.3507],"type":"Point"}
}