{
  "type": "Feature",
  "properties": {
    "gn:admin1_code":"19.0",
    "gn:asciiname":"Duanmugou",
    "gn:country_code":"CN",
    "gn:dem":429,
    "gn:feature_class":"P",
    "gn:feature_code":"PPL",
    "gn:name":"Duanmugou",
    "gn:population":0,
    "gn:timezone":"Asia/Shanghai",
    "iso:country":"CN",
    "name:und_x_variant":[
        "\u6934\u6728\u6c9f"
    ],
    "wof:name":"Duanmugou",
    "wof:placetype":"locality"
},
  "geometry": {"coordinates":[122.9109,40.1617],"type":"Point"}
}