{
  "type": "Feature",
  "properties": {
    "gn:admin1_code":"14.0",
    "gn:asciiname":"Gamulongma",
    "gn:country_code":"CN",
    "gn:dem":4466,
    "gn:feature_class":"P",
    "gn:feature_code":"PPL",
    "gn:name":"Gamulongma",
    "gn:population":0,
    "gn:timezone":"Asia/Urumqi",
    "iso:country":"CN",
    "name:zho_x_preferred":[
        "\u560e\u6728\u9f99\u739b"
    ],
    "wof:name":"Gamulongma",
    "wof:placetype":"locality"
},
  "geometry": {"coordinates":[92.37116,29.91847000000001],"type":"Point"}
}