{
  "type": "Feature",
  "properties": {
    "gn:admin1_code":"8.0",
    "gn:asciiname":"Yongqingcun",
    "gn:country_code":"CN",
    "gn:dem":135,
    "gn:feature_class":"P",
    "gn:feature_code":"PPL",
    "gn:name":"Yongqingcun",
    "gn:population":0,
    "gn:timezone":"Asia/Shanghai",
    "iso:country":"CN",
    "name:zho_x_preferred":[
        "\u6c38\u9752\u6751"
    ],
    "wof:name":"Yongqingcun",
    "wof:placetype":"locality"
},
  "geometry": {"coordinates":[131.69669999999999,45.36299],"type":"Point"}
}