{
  "type": "Feature",
  "properties": {
    "gn:admin1_code":"08",
    "gn:asciiname":"Tuchengzi",
    "gn:country_code":"CN",
    "gn:dem":117,
    "gn:feature_class":"P",
    "gn:feature_code":"PPL",
    "gn:name":"Tuchengzi",
    "gn:population":0,
    "gn:timezone":"Asia/Shanghai",
    "iso:country":"CN",
    "name:zho_x_preferred":[
        "\u571f\u57ce\u5b50"
    ],
    "wof:name":"Tuchengzi",
    "wof:placetype":"locality"
},
  "geometry": {"coordinates":[129.54908999999998,46.0362],"type":"Point"}
}