{
  "type": "Feature",
  "properties": {
    "gn:admin1_code":"5.0",
    "gn:asciiname":"Housihetun",
    "gn:country_code":"CN",
    "gn:dem":170,
    "gn:feature_class":"P",
    "gn:feature_code":"PPL",
    "gn:name":"Housihetun",
    "gn:population":0,
    "gn:timezone":"Asia/Shanghai",
    "iso:country":"CN",
    "name:zho_x_preferred":[
        "\u540e\u56db\u5408\u5c6f"
    ],
    "wof:name":"Housihetun",
    "wof:placetype":"locality"
},
  "geometry": {"coordinates":[126.67309,44.87229],"type":"Point"}
}