{
  "type": "Feature",
  "properties": {
    "gn:admin1_code":"30.0",
    "gn:asciiname":"Meishui",
    "gn:country_code":"CN",
    "gn:dem":213,
    "gn:feature_class":"P",
    "gn:feature_code":"PPL",
    "gn:name":"Meishui",
    "gn:population":0,
    "gn:timezone":"Asia/Shanghai",
    "iso:country":"CN",
    "name:zho_x_preferred":[
        "Meishui"
    ],
    "name:zho_x_variant":[
        "\u6885\u6c34"
    ],
    "wof:name":"Meishui",
    "wof:placetype":"locality"
},
  "geometry": {"coordinates":[112.14722,24.9975],"type":"Point"}
}