{
  "type": "Feature",
  "properties": {
    "gn:admin1_code":"12.0",
    "gn:asciiname":"Jingyang",
    "gn:country_code":"CN",
    "gn:dem":380,
    "gn:feature_class":"P",
    "gn:feature_code":"PPLA4",
    "gn:name":"Jingyang",
    "gn:population":0,
    "gn:timezone":"Asia/Shanghai",
    "iso:country":"CN",
    "name:ceb_x_preferred":[
        "Jingyang"
    ],
    "name:deu_x_preferred":[
        "Jingyang"
    ],
    "name:fra_x_preferred":[
        "Jingyang"
    ],
    "name:nor_x_preferred":[
        "Jingyang"
    ],
    "name:swe_x_preferred":[
        "Jingyang"
    ],
    "name:und_x_variant":[
        "Jingyang Zhen"
    ],
    "name:zho_x_preferred":[
        "\u666f\u9633"
    ],
    "name:zho_x_variant":[
        "\u666f\u9633\u9547"
    ],
    "wof:name":"Jingyang",
    "wof:placetype":"locality"
},
  "geometry": {"coordinates":[110.00274,30.36822],"type":"Point"}
}