{
  "type": "Feature",
  "properties": {
    "gn:admin1_code":"29.0",
    "gn:asciiname":"Meizishu",
    "gn:country_code":"CN",
    "gn:dem":2072,
    "gn:feature_class":"P",
    "gn:feature_code":"PPL",
    "gn:name":"Meizishu",
    "gn:population":0,
    "gn:timezone":"Asia/Shanghai",
    "iso:country":"CN",
    "name:zho_x_preferred":[
        "\u6885\u5b50\u6811"
    ],
    "wof:name":"Meizishu",
    "wof:placetype":"locality"
},
  "geometry": {"coordinates":[99.56180000000001,24.9435],"type":"Point"}
}