{
  "type": "Feature",
  "properties": {
    "gn:admin1_code":"5.0",
    "gn:asciiname":"Changfucun",
    "gn:country_code":"CN",
    "gn:dem":158,
    "gn:feature_class":"P",
    "gn:feature_code":"PPL",
    "gn:name":"Changfucun",
    "gn:population":0,
    "gn:timezone":"Asia/Shanghai",
    "iso:country":"CN",
    "name:zho_x_preferred":[
        "\u957f\u798f\u6751"
    ],
    "wof:name":"Changfucun",
    "wof:placetype":"locality"
},
  "geometry": {"coordinates":[126.89991000000001,45.12246],"type":"Point"}
}