{
  "type": "Feature",
  "properties": {
    "gn:admin1_code":"15.0",
    "gn:asciiname":"Axia Linchang",
    "gn:country_code":"CN",
    "gn:dem":1969,
    "gn:feature_class":"P",
    "gn:feature_code":"PPLF",
    "gn:name":"Axia Linchang",
    "gn:population":0,
    "gn:timezone":"Asia/Shanghai",
    "iso:country":"CN",
    "name:und_x_variant":[
        "\u963f\u590f\u6797\u573a"
    ],
    "wof:name":"Axia Linchang",
    "wof:placetype":"locality"
},
  "geometry": {"coordinates":[103.71897,33.94812],"type":"Point"}
}