{
  "type": "Feature",
  "properties": {
    "gn:admin1_code":"19.0",
    "gn:asciiname":"Magangou",
    "gn:country_code":"CN",
    "gn:dem":262,
    "gn:feature_class":"P",
    "gn:feature_code":"PPL",
    "gn:name":"Magangou",
    "gn:population":0,
    "gn:timezone":"Asia/Shanghai",
    "iso:country":"CN",
    "name:zho_x_preferred":[
        "\u9a6c\u5e72\u6c9f"
    ],
    "wof:name":"Magangou",
    "wof:placetype":"locality"
},
  "geometry": {"coordinates":[121.1093,41.76622],"type":"Point"}
}