{
  "type": "Feature",
  "properties": {
    "gn:admin1_code":"19.0",
    "gn:asciiname":"Daminquan",
    "gn:country_code":"CN",
    "gn:dem":36,
    "gn:feature_class":"P",
    "gn:feature_code":"PPL",
    "gn:name":"Daminquan",
    "gn:population":0,
    "gn:timezone":"Asia/Shanghai",
    "iso:country":"CN",
    "name:zho_x_preferred":[
        "\u5927\u6c11\u5708"
    ],
    "wof:name":"Daminquan",
    "wof:placetype":"locality"
},
  "geometry": {"coordinates":[122.34699999999999,41.9394],"type":"Point"}
}