{
  "type": "Feature",
  "properties": {
    "gn:admin1_code":"32.0",
    "gn:asciiname":"Diluo",
    "gn:country_code":"CN",
    "gn:dem":1695,
    "gn:feature_class":"P",
    "gn:feature_code":"PPL",
    "gn:name":"Diluo",
    "gn:population":0,
    "gn:timezone":"Asia/Shanghai",
    "iso:country":"CN",
    "name:zho_x_preferred":[
        "\u5730\u6d1b"
    ],
    "wof:name":"Diluo",
    "wof:placetype":"locality"
},
  "geometry": {"coordinates":[103.03360000000001,27.69303],"type":"Point"}
}