{
  "type": "Feature",
  "properties": {
    "gn:admin1_code":"2.0",
    "gn:asciiname":"Yangtangshan",
    "gn:country_code":"CN",
    "gn:dem":216,
    "gn:feature_class":"P",
    "gn:feature_code":"PPL",
    "gn:name":"Yangtangshan",
    "gn:population":0,
    "gn:timezone":"Asia/Shanghai",
    "iso:country":"CN",
    "name:zho_x_preferred":[
        "\u7f8a\u5858\u5c71"
    ],
    "wof:name":"Yangtangshan",
    "wof:placetype":"locality"
},
  "geometry": {"coordinates":[120.4585,29.30522],"type":"Point"}
}