{
  "type": "Feature",
  "properties": {
    "gn:admin1_code":"19.0",
    "gn:asciiname":"Pingdao",
    "gn:country_code":"CN",
    "gn:dem":9,
    "gn:feature_class":"P",
    "gn:feature_code":"PPL",
    "gn:name":"Pingdao",
    "gn:population":0,
    "gn:timezone":"Asia/Shanghai",
    "iso:country":"CN",
    "name:und_x_variant":[
        "\u5e73\u5c9b"
    ],
    "name:zho_x_preferred":[
        "\u5e73\u5c9b"
    ],
    "wof:name":"Pingdao",
    "wof:placetype":"locality"
},
  "geometry": {"coordinates":[121.464,39.4126],"type":"Point"}
}