{
  "type": "Feature",
  "properties": {
    "gn:admin1_code":"15.0",
    "gn:asciiname":"Liubuzi",
    "gn:country_code":"CN",
    "gn:dem":1314,
    "gn:feature_class":"P",
    "gn:feature_code":"PPL",
    "gn:name":"Liubuzi",
    "gn:population":0,
    "gn:timezone":"Asia/Shanghai",
    "iso:country":"CN",
    "name:und_x_variant":[
        "\u5218\u5821\u5b50"
    ],
    "wof:name":"Liubuzi",
    "wof:placetype":"locality"
},
  "geometry": {"coordinates":[107.80356,36.61763],"type":"Point"}
}