{
  "type": "Feature",
  "properties": {
    "gn:admin1_code":"9.0",
    "gn:asciiname":"Xiweizhuang",
    "gn:country_code":"CN",
    "gn:dem":167,
    "gn:feature_class":"P",
    "gn:feature_code":"PPL",
    "gn:name":"Xiweizhuang",
    "gn:population":0,
    "gn:timezone":"Asia/Shanghai",
    "iso:country":"CN",
    "name:zho_x_preferred":[
        "\u897f\u9b4f\u5e84"
    ],
    "wof:name":"Xiweizhuang",
    "wof:placetype":"locality"
},
  "geometry": {"coordinates":[113.3143,34.24175],"type":"Point"}
}