{
  "type": "Feature",
  "properties": {
    "gn:admin1_code":"18",
    "gn:asciiname":"Yanlao",
    "gn:country_code":"CN",
    "gn:dem":1048,
    "gn:feature_class":"P",
    "gn:feature_code":"PPL",
    "gn:name":"Yanlao",
    "gn:population":0,
    "gn:timezone":"Asia/Shanghai",
    "iso:country":"CN",
    "name:zho_x_preferred":[
        "\u5ca9\u8001"
    ],
    "wof:name":"Yanlao",
    "wof:placetype":"locality"
},
  "geometry": {"coordinates":[105.714,24.936],"type":"Point"}
}