{
  "type": "Feature",
  "properties": {
    "gn:admin1_code":"4.0",
    "gn:asciiname":"Fangxu",
    "gn:country_code":"CN",
    "gn:dem":8,
    "gn:feature_class":"P",
    "gn:feature_code":"PPL",
    "gn:name":"Fangxu",
    "gn:population":0,
    "gn:timezone":"Asia/Shanghai",
    "iso:country":"CN",
    "name:zho_x_preferred":[
        "Fangxu"
    ],
    "name:zho_x_variant":[
        "\u623f\u5729"
    ],
    "wof:name":"Fangxu",
    "wof:placetype":"locality"
},
  "geometry": {"coordinates":[119.89339,34.14343],"type":"Point"}
}