{
  "type": "Feature",
  "properties": {
    "gn:admin1_code":"26.0",
    "gn:asciiname":"Gaomiaocun",
    "gn:country_code":"CN",
    "gn:dem":369,
    "gn:feature_class":"P",
    "gn:feature_code":"PPL",
    "gn:name":"Gaomiaocun",
    "gn:population":0,
    "gn:timezone":"Asia/Shanghai",
    "iso:country":"CN",
    "name:zho_x_preferred":[
        "\u9ad8\u5e99\u6751"
    ],
    "wof:name":"Gaomiaocun",
    "wof:placetype":"locality"
},
  "geometry": {"coordinates":[109.19776,34.53427],"type":"Point"}
}