{
  "type": "Feature",
  "properties": {
    "gn:admin1_code":"18",
    "gn:asciiname":"Tangchiba",
    "gn:country_code":"CN",
    "gn:dem":767,
    "gn:feature_class":"P",
    "gn:feature_code":"PPL",
    "gn:name":"Tangchiba",
    "gn:population":0,
    "gn:timezone":"Asia/Shanghai",
    "iso:country":"CN",
    "name:zho_x_preferred":[
        "\u5858\u6c60\u575d"
    ],
    "wof:name":"Tangchiba",
    "wof:placetype":"locality"
},
  "geometry": {"coordinates":[107.98399999999999,28.6601],"type":"Point"}
}