{
  "type": "Feature",
  "properties": {
    "gn:admin1_code":"11.0",
    "gn:asciiname":"Baizhulin",
    "gn:country_code":"CN",
    "gn:dem":210,
    "gn:feature_class":"P",
    "gn:feature_code":"PPL",
    "gn:name":"Baizhulin",
    "gn:population":0,
    "gn:timezone":"Asia/Shanghai",
    "iso:country":"CN",
    "name:zho_x_preferred":[
        "\u767d\u7af9\u6797"
    ],
    "wof:name":"Baizhulin",
    "wof:placetype":"locality"
},
  "geometry": {"coordinates":[109.70099999999999,27.80464000000001],"type":"Point"}
}