{
  "type": "Feature",
  "properties": {
    "gn:admin1_code":"32.0",
    "gn:asciiname":"Datiankan",
    "gn:country_code":"CN",
    "gn:dem":455,
    "gn:feature_class":"P",
    "gn:feature_code":"PPL",
    "gn:name":"Datiankan",
    "gn:population":0,
    "gn:timezone":"Asia/Shanghai",
    "iso:country":"CN",
    "name:zho_x_preferred":[
        "\u5927\u7530\u574e"
    ],
    "wof:name":"Datiankan",
    "wof:placetype":"locality"
},
  "geometry": {"coordinates":[105.52448,28.6621],"type":"Point"}
}