{
  "type": "Feature",
  "properties": {
    "gn:admin1_code":"21.0",
    "gn:asciiname":"Sanbula",
    "gn:country_code":"CN",
    "gn:dem":1538,
    "gn:feature_class":"P",
    "gn:feature_code":"PPL",
    "gn:name":"Sanbula",
    "gn:population":0,
    "gn:timezone":"Asia/Shanghai",
    "iso:country":"CN",
    "name:zho_x_preferred":[
        "\u4e09\u4e0d\u62c9"
    ],
    "wof:name":"Sanbula",
    "wof:placetype":"locality"
},
  "geometry": {"coordinates":[105.571,37.0502],"type":"Point"}
}