{
  "type": "Feature",
  "properties": {
    "gn:admin1_code":"26.0",
    "gn:asciiname":"Wanglonggou",
    "gn:country_code":"CN",
    "gn:dem":1178,
    "gn:feature_class":"P",
    "gn:feature_code":"PPL",
    "gn:name":"Wanglonggou",
    "gn:population":0,
    "gn:timezone":"Asia/Shanghai",
    "iso:country":"CN",
    "name:zho_x_preferred":[
        "\u738b\u9f99\u6c9f"
    ],
    "wof:name":"Wanglonggou",
    "wof:placetype":"locality"
},
  "geometry": {"coordinates":[110.59137,38.92026],"type":"Point"}
}