{
  "type": "Feature",
  "properties": {
    "gn:admin1_code":"15.0",
    "gn:asciiname":"Sancang",
    "gn:country_code":"CN",
    "gn:dem":1537,
    "gn:feature_class":"P",
    "gn:feature_code":"PPLA4",
    "gn:name":"Sancang",
    "gn:population":0,
    "gn:timezone":"Asia/Shanghai",
    "iso:country":"CN",
    "name:und_x_variant":[
        "\u4e09\u4ed3"
    ],
    "wof:name":"Sancang",
    "wof:placetype":"locality"
},
  "geometry": {"coordinates":[105.11507,33.01378],"type":"Point"}
}