{
  "type": "Feature",
  "properties": {
    "gn:admin1_code":"29.0",
    "gn:asciiname":"Pingzi",
    "gn:country_code":"CN",
    "gn:dem":1920,
    "gn:feature_class":"P",
    "gn:feature_code":"PPL",
    "gn:name":"Pingzi",
    "gn:population":0,
    "gn:timezone":"Asia/Shanghai",
    "iso:country":"CN",
    "name:und_x_variant":[
        "\u576a\u5b50"
    ],
    "wof:name":"Pingzi",
    "wof:placetype":"locality"
},
  "geometry": {"coordinates":[102.96212,27.35572],"type":"Point"}
}