{
  "type": "Feature",
  "properties": {
    "gn:admin1_code":"26.0",
    "gn:asciiname":"Hongyan",
    "gn:country_code":"CN",
    "gn:dem":581,
    "gn:feature_class":"P",
    "gn:feature_code":"PPL",
    "gn:name":"Hongyan",
    "gn:population":0,
    "gn:timezone":"Asia/Shanghai",
    "iso:country":"CN",
    "name:und_x_variant":[
        "Hongyanxia"
    ],
    "name:zho_x_preferred":[
        "\u7ea2\u5ca9"
    ],
    "wof:name":"Hongyan",
    "wof:placetype":"locality"
},
  "geometry": {"coordinates":[109.73128,32.90817],"type":"Point"}
}