{
  "type": "Feature",
  "properties": {
    "gn:admin1_code":"29.0",
    "gn:asciiname":"Xijiwuji",
    "gn:country_code":"CN",
    "gn:dem":2544,
    "gn:feature_class":"P",
    "gn:feature_code":"PPL",
    "gn:name":"Xijiwuji",
    "gn:population":0,
    "gn:timezone":"Asia/Shanghai",
    "iso:country":"CN",
    "name:zho_x_preferred":[
        "\u7ec6\u57fa\u543e\u57fa"
    ],
    "wof:name":"Xijiwuji",
    "wof:placetype":"locality"
},
  "geometry": {"coordinates":[101.08499999999999,26.128],"type":"Point"}
}