{
  "type": "Feature",
  "properties": {
    "gn:admin1_code":"11",
    "gn:asciiname":"Xinsheng",
    "gn:country_code":"CN",
    "gn:dem":1052,
    "gn:feature_class":"P",
    "gn:feature_code":"PPL",
    "gn:name":"Xinsheng",
    "gn:population":0,
    "gn:timezone":"Asia/Shanghai",
    "iso:country":"CN",
    "wof:name":"Xinsheng",
    "wof:placetype":"locality"
},
  "geometry": {"coordinates":[110.60805999999999,27.44528],"type":"Point"}
}