{
  "type": "Feature",
  "properties": {
    "gn:admin1_code":"15.0",
    "gn:asciiname":"Dahebian",
    "gn:country_code":"CN",
    "gn:dem":2445,
    "gn:feature_class":"P",
    "gn:feature_code":"PPL",
    "gn:name":"Dahebian",
    "gn:population":0,
    "gn:timezone":"Asia/Shanghai",
    "iso:country":"CN",
    "name:und_x_variant":[
        "\u5927\u6cb3\u8fb9"
    ],
    "wof:name":"Dahebian",
    "wof:placetype":"locality"
},
  "geometry": {"coordinates":[104.68207,34.14971],"type":"Point"}
}