{
  "type": "Feature",
  "properties": {
    "gn:admin1_code":"9",
    "gn:asciiname":"Junze",
    "gn:country_code":"CN",
    "gn:dem":53,
    "gn:feature_class":"P",
    "gn:feature_code":"PPL",
    "gn:name":"Junze",
    "gn:population":0,
    "gn:timezone":"Asia/Shanghai",
    "iso:country":"CN",
    "name:zho_x_preferred":[
        "\u541b\u6cfd"
    ],
    "wof:name":"Junze",
    "wof:placetype":"locality"
},
  "geometry": {"coordinates":[115.14084,36.10819],"type":"Point"}
}