{
  "type": "Feature",
  "properties": {
    "gn:admin1_code":"11.0",
    "gn:asciiname":"Liuxianjiao",
    "gn:country_code":"CN",
    "gn:dem":32,
    "gn:feature_class":"P",
    "gn:feature_code":"PPL",
    "gn:name":"Liuxianjiao",
    "gn:population":0,
    "gn:timezone":"Asia/Shanghai",
    "iso:country":"CN",
    "name:zho_x_preferred":[
        "\u7559\u4ed9\u7a96"
    ],
    "wof:name":"Liuxianjiao",
    "wof:placetype":"locality"
},
  "geometry": {"coordinates":[112.44046000000002,29.47233],"type":"Point"}
}