{
  "type": "Feature",
  "properties": {
    "gn:admin1_code":"13",
    "gn:asciiname":"Aremaili",
    "gn:country_code":"CN",
    "gn:dem":1308,
    "gn:feature_class":"P",
    "gn:feature_code":"PPL",
    "gn:name":"Aremaili",
    "gn:population":0,
    "gn:timezone":"Asia/Shanghai",
    "iso:country":"CN",
    "name:und_x_variant":[
        "\u963f\u70ed\u4e70\u91cc"
    ],
    "wof:name":"Aremaili",
    "wof:placetype":"locality"
},
  "geometry": {"coordinates":[75.91535,39.45083],"type":"Point"}
}