{
  "type": "Feature",
  "properties": {
    "gn:admin1_code":"7.0",
    "gn:asciiname":"Yufang",
    "gn:country_code":"CN",
    "gn:dem":468,
    "gn:feature_class":"P",
    "gn:feature_code":"PPL",
    "gn:name":"Yufang",
    "gn:population":0,
    "gn:timezone":"Asia/Shanghai",
    "iso:country":"CN",
    "name:und_x_variant":[
        "\u4fde\u574a"
    ],
    "name:zho_x_preferred":[
        "\u4fde\u574a"
    ],
    "wof:name":"Yufang",
    "wof:placetype":"locality"
},
  "geometry": {"coordinates":[116.68853,26.04883],"type":"Point"}
}