{
  "type": "Feature",
  "properties": {
    "gn:admin1_code":"11.0",
    "gn:asciiname":"Liangtoutang",
    "gn:country_code":"CN",
    "gn:dem":259,
    "gn:feature_class":"P",
    "gn:feature_code":"PPL",
    "gn:name":"Liangtoutang",
    "gn:population":0,
    "gn:timezone":"Asia/Shanghai",
    "iso:country":"CN",
    "name:zho_x_preferred":[
        "\u4e24\u5934\u5858"
    ],
    "wof:name":"Liangtoutang",
    "wof:placetype":"locality"
},
  "geometry": {"coordinates":[111.63215,27.15676],"type":"Point"}
}