{
  "type": "Feature",
  "properties": {
    "gn:admin1_code":"1.0",
    "gn:asciiname":"Fuchongcun",
    "gn:country_code":"CN",
    "gn:dem":158,
    "gn:feature_class":"P",
    "gn:feature_code":"PPL",
    "gn:name":"Fuchongcun",
    "gn:population":0,
    "gn:timezone":"Asia/Shanghai",
    "iso:country":"CN",
    "name:zho_x_preferred":[
        "\u5085\u51b2\u6751"
    ],
    "wof:name":"Fuchongcun",
    "wof:placetype":"locality"
},
  "geometry": {"coordinates":[116.98882999999999,31.26732],"type":"Point"}
}