{
  "type": "Feature",
  "properties": {
    "gn:admin1_code":"19.0",
    "gn:asciiname":"Pingshimencun",
    "gn:country_code":"CN",
    "gn:dem":134,
    "gn:feature_class":"P",
    "gn:feature_code":"PPL",
    "gn:name":"Pingshimencun",
    "gn:population":0,
    "gn:timezone":"Asia/Shanghai",
    "iso:country":"CN",
    "name:zho_x_preferred":[
        "\u5e73\u77f3\u95e8\u6751"
    ],
    "wof:name":"Pingshimencun",
    "wof:placetype":"locality"
},
  "geometry": {"coordinates":[124.133,42.2811],"type":"Point"}
}