{
  "type": "Feature",
  "properties": {
    "gn:admin1_code":"12.0",
    "gn:asciiname":"Sanchaxi",
    "gn:country_code":"CN",
    "gn:dem":775,
    "gn:feature_class":"P",
    "gn:feature_code":"PPL",
    "gn:name":"Sanchaxi",
    "gn:population":0,
    "gn:timezone":"Asia/Shanghai",
    "iso:country":"CN",
    "name:zho_x_preferred":[
        "Sanchaxi"
    ],
    "name:zho_x_variant":[
        "\u4e09\u53c9\u6eaa"
    ],
    "wof:name":"Sanchaxi",
    "wof:placetype":"locality"
},
  "geometry": {"coordinates":[110.07907,29.8575],"type":"Point"}
}