{
  "type": "Feature",
  "properties": {
    "gn:admin1_code":"32.0",
    "gn:asciiname":"Xiahuangtian",
    "gn:country_code":"CN",
    "gn:dem":1225,
    "gn:feature_class":"P",
    "gn:feature_code":"PPL",
    "gn:name":"Xiahuangtian",
    "gn:population":0,
    "gn:timezone":"Asia/Shanghai",
    "iso:country":"CN",
    "name:zho_x_preferred":[
        "\u4e0b\u8352\u7530"
    ],
    "wof:name":"Xiahuangtian",
    "wof:placetype":"locality"
},
  "geometry": {"coordinates":[101.871,27.1955],"type":"Point"}
}