{
  "type": "Feature",
  "properties": {
    "gn:admin1_code":"31",
    "gn:asciiname":"Xinzhu",
    "gn:country_code":"CN",
    "gn:dem":39,
    "gn:feature_class":"P",
    "gn:feature_code":"PPLA4",
    "gn:name":"Xinzhu",
    "gn:population":0,
    "gn:timezone":"Asia/Shanghai",
    "iso:country":"CN",
    "name:und_x_variant":[
        "\u65b0\u7af9",
        "Xinzhu Zhen",
        "\u65b0\u7af9\u9547"
    ],
    "wof:name":"Xinzhu",
    "wof:placetype":"locality"
},
  "geometry": {"coordinates":[110.20650000000001,19.62158],"type":"Point"}
}