{
  "type": "Feature",
  "properties": {
    "gn:admin1_code":"5.0",
    "gn:asciiname":"Zuoshugou",
    "gn:country_code":"CN",
    "gn:dem":486,
    "gn:feature_class":"P",
    "gn:feature_code":"PPL",
    "gn:name":"Zuoshugou",
    "gn:population":0,
    "gn:timezone":"Asia/Shanghai",
    "iso:country":"CN",
    "name:und_x_variant":[
        "\u67de\u6811\u6c9f"
    ],
    "wof:name":"Zuoshugou",
    "wof:placetype":"locality"
},
  "geometry": {"coordinates":[125.72441999999999,41.25204],"type":"Point"}
}