{
  "type": "Feature",
  "properties": {
    "gn:admin1_code":"12.0",
    "gn:asciiname":"Qingshan Dadui",
    "gn:country_code":"CN",
    "gn:dem":193,
    "gn:feature_class":"P",
    "gn:feature_code":"PPLF",
    "gn:name":"Qingshan Dadui",
    "gn:population":0,
    "gn:timezone":"Asia/Shanghai",
    "iso:country":"CN",
    "name:zho_x_preferred":[
        "Qingshan Dadui"
    ],
    "name:zho_x_variant":[
        "\u9752\u5c71\u5927\u961f"
    ],
    "wof:name":"Qingshan Dadui",
    "wof:placetype":"locality"
},
  "geometry": {"coordinates":[115.00473999999998,29.95852],"type":"Point"}
}