{
  "type": "Feature",
  "properties": {
    "gn:admin1_code":"8.0",
    "gn:asciiname":"Gongsi Xicun",
    "gn:country_code":"CN",
    "gn:dem":221,
    "gn:feature_class":"P",
    "gn:feature_code":"PPL",
    "gn:name":"Gongsi Xicun",
    "gn:population":0,
    "gn:timezone":"Asia/Shanghai",
    "iso:country":"CN",
    "name:zho_x_preferred":[
        "\u606d\u56db\u897f\u6751"
    ],
    "wof:name":"Gongsi Xicun",
    "wof:placetype":"locality"
},
  "geometry": {"coordinates":[126.86400999999999,47.00584],"type":"Point"}
}