{
  "type": "Feature",
  "properties": {
    "gn:admin1_code":"20.0",
    "gn:asciiname":"Shisanhao",
    "gn:country_code":"CN",
    "gn:dem":1051,
    "gn:feature_class":"P",
    "gn:feature_code":"PPL",
    "gn:name":"Shisanhao",
    "gn:population":0,
    "gn:timezone":"Asia/Shanghai",
    "iso:country":"CN",
    "name:zho_x_preferred":[
        "\u5341\u4e09\u53f7"
    ],
    "wof:name":"Shisanhao",
    "wof:placetype":"locality"
},
  "geometry": {"coordinates":[100.26588,41.13769],"type":"Point"}
}