{
  "type": "Feature",
  "properties": {
    "gn:admin1_code":"9",
    "gn:asciiname":"Changlou",
    "gn:country_code":"CN",
    "gn:dem":61,
    "gn:feature_class":"P",
    "gn:feature_code":"PPL",
    "gn:name":"Changlou",
    "gn:population":0,
    "gn:timezone":"Asia/Shanghai",
    "iso:country":"CN",
    "name:zho_x_preferred":[
        "\u5e38\u697c"
    ],
    "wof:name":"Changlou",
    "wof:placetype":"locality"
},
  "geometry": {"coordinates":[115.37667,35.58387000000001],"type":"Point"}
}