{
  "type": "Feature",
  "properties": {
    "gn:admin1_code":"7.0",
    "gn:asciiname":"Hengpai",
    "gn:country_code":"CN",
    "gn:dem":714,
    "gn:feature_class":"P",
    "gn:feature_code":"PPL",
    "gn:name":"Hengpai",
    "gn:population":0,
    "gn:timezone":"Asia/Shanghai",
    "iso:country":"CN",
    "name:zho_x_preferred":[
        "\u6a2a\u6392"
    ],
    "wof:name":"Hengpai",
    "wof:placetype":"locality"
},
  "geometry": {"coordinates":[117.20971000000002,27.21276],"type":"Point"}
}