{
  "type": "Feature",
  "properties": {
    "gn:admin1_code":"8.0",
    "gn:asciiname":"Shengchan",
    "gn:country_code":"CN",
    "gn:dem":139,
    "gn:feature_class":"P",
    "gn:feature_code":"PPL",
    "gn:name":"Shengchan",
    "gn:population":0,
    "gn:timezone":"Asia/Shanghai",
    "iso:country":"CN",
    "name:zho_x_preferred":[
        "\u751f\u4ea7"
    ],
    "wof:name":"Shengchan",
    "wof:placetype":"locality"
},
  "geometry": {"coordinates":[127.59747,45.92442],"type":"Point"}
}