{
  "type": "Feature",
  "properties": {
    "gn:admin1_code":"25",
    "gn:asciiname":"Chaiwanglou",
    "gn:country_code":"CN",
    "gn:dem":44,
    "gn:feature_class":"P",
    "gn:feature_code":"PPL",
    "gn:name":"Chaiwanglou",
    "gn:population":0,
    "gn:timezone":"Asia/Shanghai",
    "iso:country":"CN",
    "name:zho_x_preferred":[
        "\u67f4\u738b\u697c"
    ],
    "wof:name":"Chaiwanglou",
    "wof:placetype":"locality"
},
  "geometry": {"coordinates":[116.20399999999999,34.6792],"type":"Point"}
}