{
  "type": "Feature",
  "properties": {
    "gn:admin1_code":"25.0",
    "gn:asciiname":"Zhanjiacun",
    "gn:country_code":"CN",
    "gn:dem":38,
    "gn:feature_class":"P",
    "gn:feature_code":"PPL",
    "gn:name":"Zhanjiacun",
    "gn:population":0,
    "gn:timezone":"Asia/Shanghai",
    "iso:country":"CN",
    "name:zho_x_preferred":[
        "\u6218\u5bb6\u6751"
    ],
    "wof:name":"Zhanjiacun",
    "wof:placetype":"locality"
},
  "geometry": {"coordinates":[119.81946000000001,37.01624],"type":"Point"}
}