{
  "type": "Feature",
  "properties": {
    "gn:admin1_code":"2.0",
    "gn:asciiname":"Yima",
    "gn:country_code":"CN",
    "gn:dem":8,
    "gn:feature_class":"P",
    "gn:feature_code":"PPL",
    "gn:name":"Yima",
    "gn:population":0,
    "gn:timezone":"Asia/Shanghai",
    "iso:country":"CN",
    "name:ceb_x_preferred":[
        "Yima"
    ],
    "name:deu_x_preferred":[
        "Yima"
    ],
    "name:fra_x_preferred":[
        "Yima"
    ],
    "name:und_x_variant":[
        "\u4e49\u9a6c"
    ],
    "wof:name":"Yima",
    "wof:placetype":"locality"
},
  "geometry": {"coordinates":[120.3223,30.55064],"type":"Point"}
}