{
  "type": "Feature",
  "properties": {
    "gn:admin1_code":"26.0",
    "gn:asciiname":"Shangyangzhuangcun",
    "gn:country_code":"CN",
    "gn:dem":1192,
    "gn:feature_class":"P",
    "gn:feature_code":"PPL",
    "gn:name":"Shangyangzhuangcun",
    "gn:population":0,
    "gn:timezone":"Asia/Shanghai",
    "iso:country":"CN",
    "name:zho_x_preferred":[
        "\u4e0a\u9633\u5e84\u6751"
    ],
    "wof:name":"Shangyangzhuangcun",
    "wof:placetype":"locality"
},
  "geometry": {"coordinates":[110.78377999999999,38.98759],"type":"Point"}
}