{
  "type": "Feature",
  "properties": {
    "gn:admin1_code":"13",
    "gn:asciiname":"Fengshousanchang Shuiying Zhan",
    "gn:country_code":"CN",
    "gn:dem":1040,
    "gn:feature_class":"P",
    "gn:feature_code":"PPL",
    "gn:name":"Fengshousanchang Shuiying Zhan",
    "gn:population":0,
    "gn:timezone":"Asia/Shanghai",
    "iso:country":"CN",
    "name:und_x_variant":[
        "\u4e30\u6536\u4e09\u573a\u6c34\u8425\u7ad9"
    ],
    "wof:name":"Fengshousanchang Shuiying Zhan",
    "wof:placetype":"locality"
},
  "geometry": {"coordinates":[80.20562,40.51663],"type":"Point"}
}