{
  "type": "Feature",
  "properties": {
    "gn:admin1_code":"26.0",
    "gn:asciiname":"Changjia Yuanzecun",
    "gn:country_code":"CN",
    "gn:dem":1016,
    "gn:feature_class":"P",
    "gn:feature_code":"PPL",
    "gn:name":"Changjia Yuanzecun",
    "gn:population":0,
    "gn:timezone":"Asia/Shanghai",
    "iso:country":"CN",
    "name:zho_x_preferred":[
        "\u5e38\u5bb6\u56ed\u5219\u6751"
    ],
    "wof:name":"Changjia Yuanzecun",
    "wof:placetype":"locality"
},
  "geometry": {"coordinates":[109.895,37.7503],"type":"Point"}
}