{
  "type": "Feature",
  "properties": {
    "gn:admin1_code":"2",
    "gn:asciiname":"Wangshantou",
    "gn:country_code":"CN",
    "gn:dem":903,
    "gn:feature_class":"P",
    "gn:feature_code":"PPL",
    "gn:name":"Wangshantou",
    "gn:population":0,
    "gn:timezone":"Asia/Shanghai",
    "iso:country":"CN",
    "name:und_x_variant":[
        "\u738b\u5c71\u5934",
        "Wangshantou"
    ],
    "wof:name":"Wangshantou",
    "wof:placetype":"locality"
},
  "geometry": {"coordinates":[119.39082999999999,27.95306],"type":"Point"}
}