{
  "type": "Feature",
  "properties": {
    "gn:admin1_code":"7",
    "gn:asciiname":"Kuiju",
    "gn:country_code":"CN",
    "gn:dem":11,
    "gn:feature_class":"P",
    "gn:feature_code":"PPL",
    "gn:name":"Kuiju",
    "gn:population":0,
    "gn:timezone":"Asia/Shanghai",
    "iso:country":"CN",
    "name:zho_x_preferred":[
        "\u594e\u805a"
    ],
    "wof:name":"Kuiju",
    "wof:placetype":"locality"
},
  "geometry": {"coordinates":[119.65488999999999,26.87528],"type":"Point"}
}