{
  "type": "Feature",
  "properties": {
    "gn:admin1_code":"07",
    "gn:asciiname":"Zhongjia",
    "gn:country_code":"CN",
    "gn:dem":591,
    "gn:feature_class":"P",
    "gn:feature_code":"PPL",
    "gn:name":"Zhongjia",
    "gn:population":0,
    "gn:timezone":"Asia/Shanghai",
    "iso:country":"CN",
    "name:zho_x_preferred":[
        "\u4e2d\u7532"
    ],
    "wof:name":"Zhongjia",
    "wof:placetype":"locality"
},
  "geometry": {"coordinates":[117.13512,25.04884],"type":"Point"}
}