{
  "type": "Feature",
  "properties": {
    "gn:admin1_code":"26.0",
    "gn:asciiname":"Guancaigou",
    "gn:country_code":"CN",
    "gn:dem":1206,
    "gn:feature_class":"P",
    "gn:feature_code":"PPL",
    "gn:name":"Guancaigou",
    "gn:population":0,
    "gn:timezone":"Asia/Shanghai",
    "iso:country":"CN",
    "name:und_x_variant":[
        "\u68fa\u6750\u6c9f"
    ],
    "wof:name":"Guancaigou",
    "wof:placetype":"locality"
},
  "geometry": {"coordinates":[108.00660999999999,34.06154],"type":"Point"}
}