{
  "type": "Feature",
  "properties": {
    "gn:admin1_code":"30.0",
    "gn:asciiname":"Xiatangliao",
    "gn:country_code":"CN",
    "gn:dem":33,
    "gn:feature_class":"P",
    "gn:feature_code":"PPL",
    "gn:name":"Xiatangliao",
    "gn:population":0,
    "gn:timezone":"Asia/Shanghai",
    "iso:country":"CN",
    "name:zho_x_preferred":[
        "\u4e0b\u7cd6\u5bee"
    ],
    "wof:name":"Xiatangliao",
    "wof:placetype":"locality"
},
  "geometry": {"coordinates":[113.37860999999999,24.12028],"type":"Point"}
}