{
  "type": "Feature",
  "properties": {
    "gn:admin1_code":"19.0",
    "gn:asciiname":"Yuwazi",
    "gn:country_code":"CN",
    "gn:dem":395,
    "gn:feature_class":"P",
    "gn:feature_code":"PPL",
    "gn:name":"Yuwazi",
    "gn:population":0,
    "gn:timezone":"Asia/Shanghai",
    "iso:country":"CN",
    "name:zho_x_preferred":[
        "\u4e8e\u6d3c\u5b50"
    ],
    "wof:name":"Yuwazi",
    "wof:placetype":"locality"
},
  "geometry": {"coordinates":[119.661,40.8173],"type":"Point"}
}