{
  "type": "Feature",
  "properties": {
    "gn:admin1_code":"30.0",
    "gn:asciiname":"Sanfucun",
    "gn:country_code":"CN",
    "gn:dem":6,
    "gn:feature_class":"P",
    "gn:feature_code":"PPL",
    "gn:name":"Sanfucun",
    "gn:population":0,
    "gn:timezone":"Asia/Shanghai",
    "iso:country":"CN",
    "name:zho_x_preferred":[
        "\u4e09\u798f\u6751"
    ],
    "wof:name":"Sanfucun",
    "wof:placetype":"locality"
},
  "geometry": {"coordinates":[116.21156000000001,23.51962],"type":"Point"}
}