{
  "type": "Feature",
  "properties": {
    "gn:admin1_code":"16.0",
    "gn:asciiname":"Yinan",
    "gn:country_code":"CN",
    "gn:dem":212,
    "gn:feature_class":"P",
    "gn:feature_code":"PPL",
    "gn:name":"Yinan",
    "gn:population":0,
    "gn:timezone":"Asia/Shanghai",
    "iso:country":"CN",
    "name:ceb_x_preferred":[
        "Yinan"
    ],
    "name:zho_x_preferred":[
        "\u5b9c\u7537"
    ],
    "wof:name":"Yinan",
    "wof:placetype":"locality"
},
  "geometry": {"coordinates":[108.90000000000001,24.3832],"type":"Point"}
}