{
  "type": "Feature",
  "properties": {
    "gn:admin1_code":"16.0",
    "gn:asciiname":"Nanen",
    "gn:country_code":"CN",
    "gn:dem":412,
    "gn:feature_class":"P",
    "gn:feature_code":"PPL",
    "gn:name":"Nanen",
    "gn:population":0,
    "gn:timezone":"Asia/Shanghai",
    "iso:country":"CN",
    "name:zho_x_preferred":[
        "\u90a3\u5ae9"
    ],
    "wof:name":"Nanen",
    "wof:placetype":"locality"
},
  "geometry": {"coordinates":[106.309,24.0025],"type":"Point"}
}