{
  "type": "Feature",
  "properties": {
    "gn:admin1_code":"30",
    "gn:asciiname":"Sanbao",
    "gn:country_code":"CN",
    "gn:dem":340,
    "gn:feature_class":"P",
    "gn:feature_code":"PPL",
    "gn:name":"Sanbao",
    "gn:population":0,
    "gn:timezone":"Asia/Urumqi",
    "iso:country":"CN",
    "name:ceb_x_preferred":[
        "Sanbao"
    ],
    "name:deu_x_preferred":[
        "Sanbao"
    ],
    "name:swe_x_preferred":[
        "Sanbao"
    ],
    "name:zho_x_preferred":[
        "\u4e09\u5305"
    ],
    "wof:name":"Sanbao",
    "wof:placetype":"locality"
},
  "geometry": {"coordinates":[111.25870999999999,22.06008],"type":"Point"}
}