{
  "type": "Feature",
  "properties": {
    "gn:admin1_code":"2.0",
    "gn:asciiname":"Xuekou",
    "gn:country_code":"CN",
    "gn:dem":107,
    "gn:feature_class":"P",
    "gn:feature_code":"PPL",
    "gn:name":"Xuekou",
    "gn:population":0,
    "gn:timezone":"Asia/Shanghai",
    "iso:country":"CN",
    "name:zho_x_preferred":[
        "Hs\u00fceh-k\u2019ou"
    ],
    "name:zho_x_variant":[
        "\u5cc3\u53e3",
        "Jia\u2019antang",
        "\u7532\u5cb8\u5802"
    ],
    "wof:name":"Xuekou",
    "wof:placetype":"locality"
},
  "geometry": {"coordinates":[120.14395,27.75582],"type":"Point"}
}