{
  "type": "Feature",
  "properties": {
    "gn:admin1_code":"12.0",
    "gn:asciiname":"Ketangtai",
    "gn:country_code":"CN",
    "gn:dem":30,
    "gn:feature_class":"P",
    "gn:feature_code":"PPL",
    "gn:name":"Ketangtai",
    "gn:population":0,
    "gn:timezone":"Asia/Shanghai",
    "iso:country":"CN",
    "name:und_x_variant":[
        "\u67ef\u94f4\u592a"
    ],
    "wof:name":"Ketangtai",
    "wof:placetype":"locality"
},
  "geometry": {"coordinates":[114.93153,30.08483],"type":"Point"}
}