{
  "type": "Feature",
  "properties": {
    "gn:admin1_code":"24.0",
    "gn:asciiname":"Dongsizhuang",
    "gn:country_code":"CN",
    "gn:dem":982,
    "gn:feature_class":"P",
    "gn:feature_code":"PPL",
    "gn:name":"Dongsizhuang",
    "gn:population":0,
    "gn:timezone":"Asia/Shanghai",
    "iso:country":"CN",
    "name:und_x_variant":[
        "\u4e1c\u5bfa\u5e84"
    ],
    "wof:name":"Dongsizhuang",
    "wof:placetype":"locality"
},
  "geometry": {"coordinates":[113.26754,39.74967],"type":"Point"}
}