{
  "type": "Feature",
  "properties": {
    "gn:admin1_code":"21",
    "gn:asciiname":"Changle",
    "gn:cc2":"CN",
    "gn:country_code":"CN",
    "gn:dem":1231,
    "gn:feature_class":"P",
    "gn:feature_code":"PPL",
    "gn:name":"Changle",
    "gn:population":0,
    "gn:timezone":"Asia/Shanghai",
    "iso:country":"CN",
    "name:und_x_variant":[
        "Changlepu",
        "Changle"
    ],
    "wof:name":"Changle",
    "wof:placetype":"locality"
},
  "geometry": {"coordinates":[105.11306,37.46472],"type":"Point"}
}