{
  "type": "Feature",
  "properties": {
    "gn:admin1_code":"12.0",
    "gn:asciiname":"Gongjiadawan",
    "gn:country_code":"CN",
    "gn:dem":28,
    "gn:feature_class":"P",
    "gn:feature_code":"PPL",
    "gn:name":"Gongjiadawan",
    "gn:population":0,
    "gn:timezone":"Asia/Shanghai",
    "iso:country":"CN",
    "name:zho_x_preferred":[
        "\u9f9a\u5bb6\u5927\u6e7e"
    ],
    "wof:name":"Gongjiadawan",
    "wof:placetype":"locality"
},
  "geometry": {"coordinates":[113.22589000000001,30.52946],"type":"Point"}
}