{
  "type": "Feature",
  "properties": {
    "gn:admin1_code":"07",
    "gn:asciiname":"Pinghai",
    "gn:country_code":"CN",
    "gn:dem":27,
    "gn:feature_class":"P",
    "gn:feature_code":"PPLA4",
    "gn:name":"Pinghai",
    "gn:population":0,
    "gn:timezone":"Asia/Shanghai",
    "iso:country":"CN",
    "name:und_x_variant":[
        "Pinghai Zhen"
    ],
    "name:zho_x_preferred":[
        "\u5e73\u6d77"
    ],
    "name:zho_x_variant":[
        "\u5e73\u6d77\u9547"
    ],
    "wof:name":"Pinghai",
    "wof:placetype":"locality"
},
  "geometry": {"coordinates":[119.26851000000001,25.18538],"type":"Point"}
}