{
  "type": "Feature",
  "properties": {
    "gn:admin1_code":"19.0",
    "gn:asciiname":"Jiangjia Shanzui",
    "gn:country_code":"CN",
    "gn:dem":48,
    "gn:feature_class":"P",
    "gn:feature_code":"PPL",
    "gn:name":"Jiangjia Shanzui",
    "gn:population":0,
    "gn:timezone":"Asia/Shanghai",
    "iso:country":"CN",
    "name:und_x_variant":[
        "\u59dc\u5bb6\u5c71\u5480"
    ],
    "name:zho_x_preferred":[
        "\u59dc\u5bb6\u5c71\u5480"
    ],
    "wof:name":"Jiangjia Shanzui",
    "wof:placetype":"locality"
},
  "geometry": {"coordinates":[122.13558999999999,39.52569],"type":"Point"}
}