{
  "type": "Feature",
  "properties": {
    "gn:admin1_code":"14.0",
    "gn:asciiname":"Nongri",
    "gn:country_code":"CN",
    "gn:dem":2722,
    "gn:feature_class":"P",
    "gn:feature_code":"PPL",
    "gn:name":"Nongri",
    "gn:population":0,
    "gn:timezone":"Asia/Urumqi",
    "iso:country":"CN",
    "name:zho_x_preferred":[
        "\u519c\u65e5"
    ],
    "wof:name":"Nongri",
    "wof:placetype":"locality"
},
  "geometry": {"coordinates":[98.63406999999999,28.98627],"type":"Point"}
}