{
  "type": "Feature",
  "properties": {
    "gn:admin1_code":"3.0",
    "gn:asciiname":"Jiangcun",
    "gn:country_code":"CN",
    "gn:dem":106,
    "gn:feature_class":"P",
    "gn:feature_code":"PPL",
    "gn:name":"Jiangcun",
    "gn:population":0,
    "gn:timezone":"Asia/Shanghai",
    "iso:country":"CN",
    "name:und_x_variant":[
        "\u6c5f\u6751"
    ],
    "wof:name":"Jiangcun",
    "wof:placetype":"locality"
},
  "geometry": {"coordinates":[117.71098000000001,29.19945],"type":"Point"}
}