{
  "type": "Feature",
  "properties": {
    "gn:admin1_code":"24.0",
    "gn:asciiname":"Sujiayan",
    "gn:country_code":"CN",
    "gn:dem":1265,
    "gn:feature_class":"P",
    "gn:feature_code":"PPL",
    "gn:name":"Sujiayan",
    "gn:population":0,
    "gn:timezone":"Asia/Shanghai",
    "iso:country":"CN",
    "name:zho_x_preferred":[
        "\u82cf\u5bb6\u6cbf"
    ],
    "wof:name":"Sujiayan",
    "wof:placetype":"locality"
},
  "geometry": {"coordinates":[111.45238999999999,37.12189],"type":"Point"}
}