{
  "type": "Feature",
  "properties": {
    "gn:admin1_code":"25",
    "gn:asciiname":"Baojia",
    "gn:country_code":"CN",
    "gn:dem":12,
    "gn:feature_class":"P",
    "gn:feature_code":"PPL",
    "gn:name":"Baojia",
    "gn:population":0,
    "gn:timezone":"Asia/Shanghai",
    "iso:country":"CN",
    "name:zho_x_preferred":[
        "\u9c8d\u5bb6"
    ],
    "wof:name":"Baojia",
    "wof:placetype":"locality"
},
  "geometry": {"coordinates":[118.589,36.9878],"type":"Point"}
}