{
  "type": "Feature",
  "properties": {
    "gn:admin1_code":"26.0",
    "gn:asciiname":"Donglizhuangcun",
    "gn:country_code":"CN",
    "gn:dem":436,
    "gn:feature_class":"P",
    "gn:feature_code":"PPL",
    "gn:name":"Donglizhuangcun",
    "gn:population":0,
    "gn:timezone":"Asia/Shanghai",
    "iso:country":"CN",
    "name:zho_x_preferred":[
        "\u4e1c\u674e\u5e84\u6751"
    ],
    "wof:name":"Donglizhuangcun",
    "wof:placetype":"locality"
},
  "geometry": {"coordinates":[108.87694999999999,34.66542],"type":"Point"}
}