{
  "type": "Feature",
  "properties": {
    "gn:admin1_code":"03",
    "gn:asciiname":"Sanmiaoqian",
    "gn:country_code":"CN",
    "gn:dem":15,
    "gn:feature_class":"P",
    "gn:feature_code":"PPLA4",
    "gn:name":"Sanmiaoqian",
    "gn:population":0,
    "gn:timezone":"Asia/Shanghai",
    "iso:country":"CN",
    "name:und_x_variant":[
        "San-miao-ch\u2019ien",
        "Sanmiaoqian",
        "\u4e09\u5e99\u524d",
        "Sanmiaoqiao",
        "Sanmiaoqian Xiang",
        "\u4e09\u5e99\u524d\u4e61"
    ],
    "wof:name":"Sanmiaoqian",
    "wof:placetype":"locality"
},
  "geometry": {"coordinates":[116.76732,28.9703],"type":"Point"}
}