{
  "type": "Feature",
  "properties": {
    "gn:admin1_code":"16.0",
    "gn:asciiname":"Baozhang",
    "gn:country_code":"CN",
    "gn:dem":140,
    "gn:feature_class":"P",
    "gn:feature_code":"PPL",
    "gn:name":"Baozhang",
    "gn:population":0,
    "gn:timezone":"Asia/Shanghai",
    "iso:country":"CN",
    "name:zho_x_preferred":[
        "\u82de\u5f20"
    ],
    "wof:name":"Baozhang",
    "wof:placetype":"locality"
},
  "geometry": {"coordinates":[108.379,23.2577],"type":"Point"}
}