{
  "type": "Feature",
  "properties": {
    "gn:admin1_code":"19.0",
    "gn:asciiname":"Youjianggou",
    "gn:country_code":"CN",
    "gn:dem":486,
    "gn:feature_class":"P",
    "gn:feature_code":"PPL",
    "gn:name":"Youjianggou",
    "gn:population":0,
    "gn:timezone":"Asia/Shanghai",
    "iso:country":"CN",
    "name:und_x_variant":[
        "\u6cb9\u5320\u6c9f"
    ],
    "wof:name":"Youjianggou",
    "wof:placetype":"locality"
},
  "geometry": {"coordinates":[124.53408,41.61248],"type":"Point"}
}