{
  "type": "Feature",
  "properties": {
    "gn:admin1_code":"02",
    "gn:asciiname":"Tianyuan",
    "gn:country_code":"CN",
    "gn:dem":8,
    "gn:feature_class":"P",
    "gn:feature_code":"PPLA4",
    "gn:name":"Tianyuan",
    "gn:population":0,
    "gn:timezone":"Asia/Shanghai",
    "iso:country":"CN",
    "name:deu_x_preferred":[
        "Tianyuan"
    ],
    "name:fra_x_preferred":[
        "Tianyuan"
    ],
    "name:und_x_variant":[
        "T\u2019ien-y\u00fcan-shih",
        "Tianyuan",
        "\u5929\u5143",
        "Tianyuan Zhen",
        "\u5929\u5143\u9547"
    ],
    "wof:name":"Tianyuan",
    "wof:placetype":"locality"
},
  "geometry": {"coordinates":[121.18155,30.1997],"type":"Point"}
}