{
  "type": "Feature",
  "properties": {
    "gn:admin1_code":"18.0",
    "gn:asciiname":"Peile",
    "gn:country_code":"CN",
    "gn:dem":619,
    "gn:feature_class":"P",
    "gn:feature_code":"PPL",
    "gn:name":"Peile",
    "gn:population":0,
    "gn:timezone":"Asia/Shanghai",
    "iso:country":"CN",
    "name:zho_x_preferred":[
        "\u57f9\u4e86"
    ],
    "wof:name":"Peile",
    "wof:placetype":"locality"
},
  "geometry": {"coordinates":[108.905,26.5724],"type":"Point"}
}