{
  "type": "Feature",
  "properties": {
    "gn:admin1_code":"19.0",
    "gn:asciiname":"Erdaoling",
    "gn:country_code":"CN",
    "gn:dem":263,
    "gn:feature_class":"P",
    "gn:feature_code":"PPL",
    "gn:name":"Erdaoling",
    "gn:population":0,
    "gn:timezone":"Asia/Shanghai",
    "iso:country":"CN",
    "name:zho_x_preferred":[
        "\u4e8c\u9053\u5cad"
    ],
    "wof:name":"Erdaoling",
    "wof:placetype":"locality"
},
  "geometry": {"coordinates":[123.73099999999999,41.1548],"type":"Point"}
}