{
  "type": "Feature",
  "properties": {
    "gn:admin1_code":"15.0",
    "gn:asciiname":"Yinmashui",
    "gn:country_code":"CN",
    "gn:dem":1680,
    "gn:feature_class":"P",
    "gn:feature_code":"PPL",
    "gn:name":"Yinmashui",
    "gn:population":0,
    "gn:timezone":"Asia/Shanghai",
    "iso:country":"CN",
    "name:zho_x_preferred":[
        "\u996e\u9a6c\u6c34"
    ],
    "wof:name":"Yinmashui",
    "wof:placetype":"locality"
},
  "geometry": {"coordinates":[104.44499999999999,36.7061],"type":"Point"}
}