{
  "type": "Feature",
  "properties": {
    "gn:admin1_code":"26.0",
    "gn:asciiname":"Shaojiashan",
    "gn:country_code":"CN",
    "gn:dem":1196,
    "gn:feature_class":"P",
    "gn:feature_code":"PPL",
    "gn:name":"Shaojiashan",
    "gn:population":0,
    "gn:timezone":"Asia/Shanghai",
    "iso:country":"CN",
    "name:und_x_variant":[
        "\u90b5\u5bb6\u5c71"
    ],
    "wof:name":"Shaojiashan",
    "wof:placetype":"locality"
},
  "geometry": {"coordinates":[105.87486,33.28052],"type":"Point"}
}