{
  "type": "Feature",
  "properties": {
    "gn:admin1_code":"10.0",
    "gn:asciiname":"Caitanzi",
    "gn:country_code":"CN",
    "gn:dem":60,
    "gn:feature_class":"P",
    "gn:feature_code":"PPL",
    "gn:name":"Caitanzi",
    "gn:population":0,
    "gn:timezone":"Asia/Shanghai",
    "iso:country":"CN",
    "name:zho_x_preferred":[
        "\u8521\u6ee9\u5b50"
    ],
    "wof:name":"Caitanzi",
    "wof:placetype":"locality"
},
  "geometry": {"coordinates":[118.64221000000001,40.04251],"type":"Point"}
}