{
  "type": "Feature",
  "properties": {
    "gn:admin1_code":"09",
    "gn:asciiname":"Shayugou",
    "gn:cc2":"CN",
    "gn:country_code":"CN",
    "gn:dem":141,
    "gn:feature_class":"P",
    "gn:feature_code":"PPL",
    "gn:name":"Shayugou",
    "gn:population":0,
    "gn:timezone":"Asia/Shanghai",
    "iso:country":"CN",
    "name:und_x_variant":[
        "Sha-y\u00fc-kou",
        "Shayugou"
    ],
    "wof:name":"Shayugou",
    "wof:placetype":"locality"
},
  "geometry": {"coordinates":[113.11861,34.81778],"type":"Point"}
}