{
  "type": "Feature",
  "properties": {
    "gn:admin1_code":"02",
    "gn:asciiname":"Zhongyan",
    "gn:country_code":"CN",
    "gn:dem":8,
    "gn:feature_class":"P",
    "gn:feature_code":"PPL",
    "gn:name":"Zhongyan",
    "gn:population":0,
    "gn:timezone":"Asia/Shanghai",
    "iso:country":"CN",
    "name:und_x_variant":[
        "Chung-hui-t\u2019ou",
        "Zhongyantou",
        "Zhongyan"
    ],
    "name:zho_x_preferred":[
        "\u949f\u5830"
    ],
    "wof:name":"Zhongyan",
    "wof:placetype":"locality"
},
  "geometry": {"coordinates":[120.54169,30.0033],"type":"Point"}
}