{
  "type": "Feature",
  "properties": {
    "gn:admin1_code":"19.0",
    "gn:asciiname":"Xiajialoucun",
    "gn:country_code":"CN",
    "gn:dem":71,
    "gn:feature_class":"P",
    "gn:feature_code":"PPL",
    "gn:name":"Xiajialoucun",
    "gn:population":0,
    "gn:timezone":"Asia/Shanghai",
    "iso:country":"CN",
    "name:zho_x_preferred":[
        "\u590f\u5bb6\u697c\u6751"
    ],
    "wof:name":"Xiajialoucun",
    "wof:placetype":"locality"
},
  "geometry": {"coordinates":[123.649,42.4178],"type":"Point"}
}