{
  "type": "Feature",
  "properties": {
    "gn:admin1_code":"4.0",
    "gn:asciiname":"Xiangyangli",
    "gn:country_code":"CN",
    "gn:dem":8,
    "gn:feature_class":"P",
    "gn:feature_code":"PPL",
    "gn:name":"Xiangyangli",
    "gn:population":0,
    "gn:timezone":"Asia/Shanghai",
    "iso:country":"CN",
    "name:und_x_variant":[
        "\u5411\u9633\u91cc"
    ],
    "name:zho_x_preferred":[
        "\u5411\u9633\u91cc"
    ],
    "wof:name":"Xiangyangli",
    "wof:placetype":"locality"
},
  "geometry": {"coordinates":[120.50711,31.49601],"type":"Point"}
}