{
  "type": "Feature",
  "properties": {
    "gn:admin1_code":"25",
    "gn:asciiname":"Xiliangzhuang",
    "gn:country_code":"CN",
    "gn:dem":43,
    "gn:feature_class":"P",
    "gn:feature_code":"PPL",
    "gn:name":"Xiliangzhuang",
    "gn:population":0,
    "gn:timezone":"Asia/Shanghai",
    "iso:country":"CN",
    "name:zho_x_preferred":[
        "\u897f\u6881\u5e84"
    ],
    "wof:name":"Xiliangzhuang",
    "wof:placetype":"locality"
},
  "geometry": {"coordinates":[115.61499999999999,36.0586],"type":"Point"}
}