{
  "type": "Feature",
  "properties": {
    "gn:admin1_code":"29.0",
    "gn:asciiname":"Chashuling",
    "gn:country_code":"CN",
    "gn:dem":1289,
    "gn:feature_class":"P",
    "gn:feature_code":"PPL",
    "gn:name":"Chashuling",
    "gn:population":0,
    "gn:timezone":"Asia/Shanghai",
    "iso:country":"CN",
    "name:zho_x_preferred":[
        "\u8336\u6811\u5cad"
    ],
    "wof:name":"Chashuling",
    "wof:placetype":"locality"
},
  "geometry": {"coordinates":[102.01000000000001,22.6103],"type":"Point"}
}