{
  "type": "Feature",
  "properties": {
    "gn:admin1_code":"19.0",
    "gn:asciiname":"Shimengouli",
    "gn:country_code":"CN",
    "gn:dem":144,
    "gn:feature_class":"P",
    "gn:feature_code":"PPL",
    "gn:name":"Shimengouli",
    "gn:population":0,
    "gn:timezone":"Asia/Shanghai",
    "iso:country":"CN",
    "name:zho_x_preferred":[
        "\u77f3\u95e8\u6c9f\u91cc"
    ],
    "wof:name":"Shimengouli",
    "wof:placetype":"locality"
},
  "geometry": {"coordinates":[124.848,40.5106],"type":"Point"}
}