{
  "type": "Feature",
  "properties": {
    "gn:admin1_code":"5.0",
    "gn:asciiname":"Zilidadui",
    "gn:country_code":"CN",
    "gn:dem":162,
    "gn:feature_class":"P",
    "gn:feature_code":"PPLF",
    "gn:name":"Zilidadui",
    "gn:population":0,
    "gn:timezone":"Asia/Shanghai",
    "iso:country":"CN",
    "name:zho_x_preferred":[
        "\u81ea\u529b\u5927\u961f"
    ],
    "wof:name":"Zilidadui",
    "wof:placetype":"locality"
},
  "geometry": {"coordinates":[122.41674,44.42173],"type":"Point"}
}