{
  "type": "Feature",
  "properties": {
    "gn:admin1_code":"32.0",
    "gn:asciiname":"Puzi",
    "gn:country_code":"CN",
    "gn:dem":686,
    "gn:feature_class":"P",
    "gn:feature_code":"PPL",
    "gn:name":"Puzi",
    "gn:population":0,
    "gn:timezone":"Asia/Shanghai",
    "iso:country":"CN",
    "name:deu_x_preferred":[
        "Puzi"
    ],
    "name:fas_x_preferred":[
        "\u067e\u0648\u0632\u06cc"
    ],
    "name:hak_x_preferred":[
        "Ph\u00fa-ch\u1e73\u0301-s\u1e73"
    ],
    "name:jpn_x_preferred":[
        "\u6734\u5b50\u5e02"
    ],
    "name:kor_x_preferred":[
        "\ud478\ucbd4\uc2dc"
    ],
    "name:lit_x_preferred":[
        "Pudzi"
    ],
    "name:pol_x_preferred":[
        "Pozi"
    ],
    "name:rus_x_preferred":[
        "\u041f\u0443\u0446\u0437\u044b"
    ],
    "name:spa_x_preferred":[
        "Puzi"
    ],
    "name:und_x_variant":[
        "\u666e\u5b50"
    ],
    "name:vie_x_preferred":[
        "Ph\u00e1c T\u1eed"
    ],
    "name:zho_x_preferred":[
        "\u6734\u5b50\u5e02"
    ],
    "wof:name":"Puzi",
    "wof:placetype":"locality"
},
  "geometry": {"coordinates":[106.01152999999999,32.28665],"type":"Point"}
}