{
  "type": "Feature",
  "properties": {
    "gn:admin1_code":"29.0",
    "gn:asciiname":"Xincunjie",
    "gn:country_code":"CN",
    "gn:dem":1719,
    "gn:feature_class":"P",
    "gn:feature_code":"PPL",
    "gn:name":"Xincunjie",
    "gn:population":0,
    "gn:timezone":"Asia/Shanghai",
    "iso:country":"CN",
    "name:zho_x_preferred":[
        "\u65b0\u6751\u8857"
    ],
    "wof:name":"Xincunjie",
    "wof:placetype":"locality"
},
  "geometry": {"coordinates":[100.392,24.6342],"type":"Point"}
}