{
  "type": "Feature",
  "properties": {
    "gn:admin1_code":"12.0",
    "gn:asciiname":"Baijia Gouzi",
    "gn:country_code":"CN",
    "gn:dem":30,
    "gn:feature_class":"P",
    "gn:feature_code":"PPL",
    "gn:name":"Baijia Gouzi",
    "gn:population":0,
    "gn:timezone":"Asia/Shanghai",
    "iso:country":"CN",
    "name:zho_x_preferred":[
        "\u767d\u5bb6\u6c9f\u5b50"
    ],
    "wof:name":"Baijia Gouzi",
    "wof:placetype":"locality"
},
  "geometry": {"coordinates":[113.05114,29.57542],"type":"Point"}
}