{
  "type": "Feature",
  "properties": {
    "gn:admin1_code":"25.0",
    "gn:asciiname":"Qijiayingcun",
    "gn:country_code":"CN",
    "gn:dem":28,
    "gn:feature_class":"P",
    "gn:feature_code":"PPL",
    "gn:name":"Qijiayingcun",
    "gn:population":0,
    "gn:timezone":"Asia/Shanghai",
    "iso:country":"CN",
    "name:zho_x_preferred":[
        "\u7da6\u5bb6\u8425\u6751"
    ],
    "wof:name":"Qijiayingcun",
    "wof:placetype":"locality"
},
  "geometry": {"coordinates":[119.98414,36.68946],"type":"Point"}
}