{
  "type": "Feature",
  "properties": {
    "gn:admin1_code":"8.0",
    "gn:asciiname":"Miaojiatun",
    "gn:country_code":"CN",
    "gn:dem":156,
    "gn:feature_class":"P",
    "gn:feature_code":"PPL",
    "gn:name":"Miaojiatun",
    "gn:population":0,
    "gn:timezone":"Asia/Shanghai",
    "iso:country":"CN",
    "name:zho_x_preferred":[
        "\u82d7\u5bb6\u5c6f"
    ],
    "wof:name":"Miaojiatun",
    "wof:placetype":"locality"
},
  "geometry": {"coordinates":[125.34238999999999,46.36961],"type":"Point"}
}