{
  "type": "Feature",
  "properties": {
    "gn:admin1_code":"5.0",
    "gn:asciiname":"Yangmuqiaozi",
    "gn:country_code":"CN",
    "gn:dem":601,
    "gn:feature_class":"P",
    "gn:feature_code":"PPL",
    "gn:name":"Yangmuqiaozi",
    "gn:population":0,
    "gn:timezone":"Asia/Shanghai",
    "iso:country":"CN",
    "name:und_x_variant":[
        "\u6768\u6728\u6865\u5b50"
    ],
    "wof:name":"Yangmuqiaozi",
    "wof:placetype":"locality"
},
  "geometry": {"coordinates":[125.47023,41.67176],"type":"Point"}
}