{
  "type": "Feature",
  "properties": {
    "gn:admin1_code":"10",
    "gn:asciiname":"Xiqiao",
    "gn:country_code":"CN",
    "gn:dem":31,
    "gn:feature_class":"P",
    "gn:feature_code":"PPL",
    "gn:name":"Xiqiao",
    "gn:population":0,
    "gn:timezone":"Asia/Shanghai",
    "iso:country":"CN",
    "name:ceb_x_preferred":[
        "Xiqiao"
    ],
    "name:swe_x_preferred":[
        "Xiqiao"
    ],
    "name:zho_x_preferred":[
        "\u897f\u4e54"
    ],
    "wof:name":"Xiqiao",
    "wof:placetype":"locality"
},
  "geometry": {"coordinates":[115.63200000000001,37.2677],"type":"Point"}
}