{
  "type": "Feature",
  "properties": {
    "gn:admin1_code":"08",
    "gn:asciiname":"Quanxiaocun",
    "gn:country_code":"CN",
    "gn:dem":214,
    "gn:feature_class":"P",
    "gn:feature_code":"PPL",
    "gn:name":"Quanxiaocun",
    "gn:population":0,
    "gn:timezone":"Asia/Shanghai",
    "iso:country":"CN",
    "name:und_x_variant":[
        "Ch\u2019\u00fcan-hsiao",
        "Quanxiao",
        "Quanxiaotun",
        "Quanxiaocun"
    ],
    "name:zho_x_preferred":[
        "\u5168\u5b5d\u6751"
    ],
    "wof:name":"Quanxiaocun",
    "wof:placetype":"locality"
},
  "geometry": {"coordinates":[127.52591,45.65288],"type":"Point"}
}