{
  "type": "Feature",
  "properties": {
    "gn:admin1_code":"19.0",
    "gn:asciiname":"Kongjia Wobu",
    "gn:country_code":"CN",
    "gn:dem":114,
    "gn:feature_class":"P",
    "gn:feature_code":"PPL",
    "gn:name":"Kongjia Wobu",
    "gn:population":0,
    "gn:timezone":"Asia/Shanghai",
    "iso:country":"CN",
    "name:und_x_variant":[
        "Kongjiawobao",
        "Kongjia Wobu"
    ],
    "name:zho_x_preferred":[
        "\u5b54\u5bb6\u7a9d\u5821"
    ],
    "wof:name":"Kongjia Wobu",
    "wof:placetype":"locality"
},
  "geometry": {"coordinates":[123.40000000000001,43.0092],"type":"Point"}
}