{
  "type": "Feature",
  "properties": {
    "gn:admin1_code":"26.0",
    "gn:asciiname":"Mu'ermao",
    "gn:country_code":"CN",
    "gn:dem":1146,
    "gn:feature_class":"P",
    "gn:feature_code":"PPL",
    "gn:name":"Mu\u2019ermao",
    "gn:population":0,
    "gn:timezone":"Asia/Shanghai",
    "iso:country":"CN",
    "name:und_x_variant":[
        "Mu\u2019ermao"
    ],
    "name:zho_x_preferred":[
        "\u6728\u8033\u5cc1"
    ],
    "wof:name":"Mu'ermao",
    "wof:placetype":"locality"
},
  "geometry": {"coordinates":[109.21214999999999,37.85785],"type":"Point"}
}