{
  "type": "Feature",
  "properties": {
    "gn:admin1_code":"1.0",
    "gn:asciiname":"Wangxi",
    "gn:country_code":"CN",
    "gn:dem":45,
    "gn:feature_class":"P",
    "gn:feature_code":"PPLA4",
    "gn:name":"Wangxi",
    "gn:population":0,
    "gn:timezone":"Asia/Shanghai",
    "iso:country":"CN",
    "name:und_x_variant":[
        "Ta-wang-ts\u2019un",
        "Dawangcun",
        "Wangxi",
        "\u6c6a\u6eaa",
        "Wangxi Zhen",
        "\u6c6a\u6eaa\u9547"
    ],
    "wof:name":"Wangxi",
    "wof:placetype":"locality"
},
  "geometry": {"coordinates":[118.97282,30.68673],"type":"Point"}
}