{
  "type": "Feature",
  "properties": {
    "gn:admin1_code":"1.0",
    "gn:asciiname":"Panzhuangcun",
    "gn:country_code":"CN",
    "gn:dem":31,
    "gn:feature_class":"P",
    "gn:feature_code":"PPL",
    "gn:name":"Panzhuangcun",
    "gn:population":0,
    "gn:timezone":"Asia/Shanghai",
    "iso:country":"CN",
    "name:und_x_variant":[
        "Panzhuang"
    ],
    "name:zho_x_preferred":[
        "\u6f58\u5e84\u6751"
    ],
    "wof:name":"Panzhuangcun",
    "wof:placetype":"locality"
},
  "geometry": {"coordinates":[117.27636,32.51991],"type":"Point"}
}