{
  "type": "Feature",
  "properties": {
    "gn:country":"CN",
    "gn:fcode":"ADM3",
    "gn:pop":0,
    "iso:country":"CN",
    "name:unk_x_variant":[
        "Ch\u2019ing-t\u2019ien Hsien"
    ],
    "name:zho_x_preferred":[
        "\u9752\u7530\u53bf"
    ],
    "name:zho_x_variant":[
        "\u9752\u7530"
    ],
    "qs:name":"Qingtian Xian",
    "qs:photos_9r":0,
    "qs:photos_sr":0,
    "qs:pop_sr":"0",
    "wof:name":"Qingtian Xian",
    "wof:placetype":"localadmin",
    "wof:population":0
},
  "geometry": {"coordinates":[120.13481,28.20533],"type":"Point"}
}