{
  "type": "Feature",
  "properties": {
    "gn:admin1_code":"8.0",
    "gn:asciiname":"Houshabaozi",
    "gn:country_code":"CN",
    "gn:dem":197,
    "gn:feature_class":"P",
    "gn:feature_code":"PPL",
    "gn:name":"Houshabaozi",
    "gn:population":0,
    "gn:timezone":"Asia/Shanghai",
    "iso:country":"CN",
    "name:zho_x_preferred":[
        "\u540e\u6c99\u5305\u5b50"
    ],
    "wof:name":"Houshabaozi",
    "wof:placetype":"locality"
},
  "geometry": {"coordinates":[127.29846000000001,44.72409],"type":"Point"}
}