{
  "type": "Feature",
  "properties": {
    "gn:admin1_code":"24.0",
    "gn:asciiname":"Xiniancun",
    "gn:country_code":"CN",
    "gn:dem":465,
    "gn:feature_class":"P",
    "gn:feature_code":"PPL",
    "gn:name":"Xiniancun",
    "gn:population":0,
    "gn:timezone":"Asia/Shanghai",
    "iso:country":"CN",
    "name:zho_x_preferred":[
        "\u897f\u57dd\u6751"
    ],
    "wof:name":"Xiniancun",
    "wof:placetype":"locality"
},
  "geometry": {"coordinates":[110.84195,35.52734],"type":"Point"}
}