{
  "type": "Feature",
  "properties": {
    "gn:admin1_code":"16.0",
    "gn:asciiname":"Bangaocun",
    "gn:country_code":"CN",
    "gn:dem":223,
    "gn:feature_class":"P",
    "gn:feature_code":"PPL",
    "gn:name":"Bangaocun",
    "gn:population":0,
    "gn:timezone":"Asia/Shanghai",
    "iso:country":"CN",
    "name:zho_x_preferred":[
        "\u677f\u9ad8\u6751"
    ],
    "wof:name":"Bangaocun",
    "wof:placetype":"locality"
},
  "geometry": {"coordinates":[108.377,24.4617],"type":"Point"}
}