{
  "type": "Feature",
  "properties": {
    "gn:admin1_code":"25",
    "gn:asciiname":"Tulou",
    "gn:country_code":"CN",
    "gn:dem":45,
    "gn:feature_class":"P",
    "gn:feature_code":"PPL",
    "gn:name":"Tulou",
    "gn:population":0,
    "gn:timezone":"Asia/Shanghai",
    "iso:country":"CN",
    "wof:name":"Tulou",
    "wof:placetype":"locality"
},
  "geometry": {"coordinates":[116.13083,34.78778],"type":"Point"}
}