{
  "type": "Feature",
  "properties": {
    "gn:admin1_code":"16.0",
    "gn:asciiname":"Lakuang",
    "gn:country_code":"CN",
    "gn:dem":882,
    "gn:feature_class":"P",
    "gn:feature_code":"PPL",
    "gn:name":"Lakuang",
    "gn:population":0,
    "gn:timezone":"Asia/Shanghai",
    "iso:country":"CN",
    "name:zho_x_preferred":[
        "\u62c9\u72c2"
    ],
    "wof:name":"Lakuang",
    "wof:placetype":"locality"
},
  "geometry": {"coordinates":[107.04000000000001,25.2637],"type":"Point"}
}