{
  "type": "Feature",
  "properties": {
    "gn:admin1_code":"11.0",
    "gn:asciiname":"Duiheting",
    "gn:country_code":"CN",
    "gn:dem":54,
    "gn:feature_class":"P",
    "gn:feature_code":"PPL",
    "gn:name":"Duiheting",
    "gn:population":0,
    "gn:timezone":"Asia/Shanghai",
    "iso:country":"CN",
    "name:zho_x_preferred":[
        "\u5bf9\u6cb3\u753a"
    ],
    "wof:name":"Duiheting",
    "wof:placetype":"locality"
},
  "geometry": {"coordinates":[112.55121,26.9278],"type":"Point"}
}