{
  "type": "Feature",
  "properties": {
    "gn:admin1_code":"18.0",
    "gn:asciiname":"Lulang",
    "gn:country_code":"CN",
    "gn:dem":1094,
    "gn:feature_class":"P",
    "gn:feature_code":"PPL",
    "gn:name":"Lulang",
    "gn:population":0,
    "gn:timezone":"Asia/Shanghai",
    "iso:country":"CN",
    "name:ceb_x_preferred":[
        "Lulang"
    ],
    "name:fra_x_preferred":[
        "Lulang"
    ],
    "name:mai_x_preferred":[
        "\u0932\u0941\u0932\u093e\u0919"
    ],
    "name:msa_x_preferred":[
        "Lulang"
    ],
    "name:nep_x_preferred":[
        "\u0932\u0941\u0932\u093e\u0919"
    ],
    "name:new_x_preferred":[
        "\u0932\u0941\u0932\u093e\u0919"
    ],
    "name:pol_x_preferred":[
        "Lulang"
    ],
    "name:zho_x_preferred":[
        "\u9c81\u90ce"
    ],
    "wof:name":"Lulang",
    "wof:placetype":"locality"
},
  "geometry": {"coordinates":[107.087,26.9158],"type":"Point"}
}