{
  "type": "Feature",
  "properties": {
    "gn:admin1_code":"14.0",
    "gn:asciiname":"Zuocuo",
    "gn:country_code":"CN",
    "gn:dem":4216,
    "gn:feature_class":"P",
    "gn:feature_code":"PPL",
    "gn:name":"Zuocuo",
    "gn:population":0,
    "gn:timezone":"Asia/Urumqi",
    "iso:country":"CN",
    "name:zho_x_preferred":[
        "\u5de6\u63aa"
    ],
    "wof:name":"Zuocuo",
    "wof:placetype":"locality"
},
  "geometry": {"coordinates":[87.3514,28.5833],"type":"Point"}
}