{
  "type": "Feature",
  "properties": {
    "gn:admin1_code":"25.0",
    "gn:asciiname":"Dawangjiacun",
    "gn:country_code":"CN",
    "gn:dem":44,
    "gn:feature_class":"P",
    "gn:feature_code":"PPL",
    "gn:name":"Dawangjiacun",
    "gn:population":0,
    "gn:timezone":"Asia/Shanghai",
    "iso:country":"CN",
    "name:zho_x_preferred":[
        "\u5927\u738b\u5bb6\u6751"
    ],
    "wof:name":"Dawangjiacun",
    "wof:placetype":"locality"
},
  "geometry": {"coordinates":[119.82478,36.88955],"type":"Point"}
}