{
  "type": "Feature",
  "properties": {
    "gn:admin1_code":"4.0",
    "gn:asciiname":"Ximeiyuan",
    "gn:country_code":"CN",
    "gn:dem":6,
    "gn:feature_class":"P",
    "gn:feature_code":"PPL",
    "gn:name":"Ximeiyuan",
    "gn:population":0,
    "gn:timezone":"Asia/Shanghai",
    "iso:country":"CN",
    "name:zho_x_preferred":[
        "\u897f\u6885\u56ed"
    ],
    "wof:name":"Ximeiyuan",
    "wof:placetype":"locality"
},
  "geometry": {"coordinates":[120.12358,31.51408],"type":"Point"}
}