{
  "type": "Feature",
  "properties": {
    "gn:admin1_code":"19.0",
    "gn:asciiname":"Fanjialiang",
    "gn:country_code":"CN",
    "gn:dem":358,
    "gn:feature_class":"P",
    "gn:feature_code":"PPL",
    "gn:name":"Fanjialiang",
    "gn:population":0,
    "gn:timezone":"Asia/Shanghai",
    "iso:country":"CN",
    "name:und_x_variant":[
        "\u8303\u5bb6\u6881"
    ],
    "name:zho_x_preferred":[
        "\u8303\u5bb6\u6881"
    ],
    "wof:name":"Fanjialiang",
    "wof:placetype":"locality"
},
  "geometry": {"coordinates":[120.46308999999999,41.71228],"type":"Point"}
}