{
  "type": "Feature",
  "properties": {
    "gn:admin1_code":"04",
    "gn:asciiname":"Dashicun",
    "gn:country_code":"CN",
    "gn:dem":7,
    "gn:feature_class":"P",
    "gn:feature_code":"PPL",
    "gn:name":"Dashicun",
    "gn:population":0,
    "gn:timezone":"Asia/Shanghai",
    "iso:country":"CN",
    "name:und_x_variant":[
        "Dashi",
        "\u5927\u5e02",
        "Dashicun"
    ],
    "name:zho_x_preferred":[
        "\u5927\u5e02\u6751"
    ],
    "wof:name":"Dashicun",
    "wof:placetype":"locality"
},
  "geometry": {"coordinates":[120.94823999999998,31.23397000000001],"type":"Point"}
}