{
  "type": "Feature",
  "properties": {
    "gn:admin1_code":"30.0",
    "gn:asciiname":"Wandong",
    "gn:country_code":"CN",
    "gn:dem":204,
    "gn:feature_class":"P",
    "gn:feature_code":"PPL",
    "gn:name":"Wandong",
    "gn:population":0,
    "gn:timezone":"Asia/Shanghai",
    "iso:country":"CN",
    "name:wuu_x_preferred":[
        "\u5558\u540c"
    ],
    "name:zho_x_preferred":[
        "\u4e07\u578c"
    ],
    "wof:name":"Wandong",
    "wof:placetype":"locality"
},
  "geometry": {"coordinates":[112.12739999999999,22.16149],"type":"Point"}
}