{
  "type": "Feature",
  "properties": {
    "gn:admin1_code":"1.0",
    "gn:asciiname":"Fufeng",
    "gn:country_code":"CN",
    "gn:dem":99,
    "gn:feature_class":"P",
    "gn:feature_code":"PPL",
    "gn:name":"Fufeng",
    "gn:population":0,
    "gn:timezone":"Asia/Shanghai",
    "iso:country":"CN",
    "name:zho_x_preferred":[
        "\u5bcc\u4e30"
    ],
    "wof:name":"Fufeng",
    "wof:placetype":"locality"
},
  "geometry": {"coordinates":[117.02058,29.75772000000001],"type":"Point"}
}