{
  "type": "Feature",
  "properties": {
    "gn:admin1_code":"29.0",
    "gn:asciiname":"Manbengtang",
    "gn:country_code":"CN",
    "gn:dem":1002,
    "gn:feature_class":"P",
    "gn:feature_code":"PPL",
    "gn:name":"Manbengtang",
    "gn:population":0,
    "gn:timezone":"Asia/Shanghai",
    "iso:country":"CN",
    "name:zho_x_preferred":[
        "\u66fc\u868c\u5858"
    ],
    "wof:name":"Manbengtang",
    "wof:placetype":"locality"
},
  "geometry": {"coordinates":[100.93600000000001,22.146],"type":"Point"}
}