{
  "type": "Feature",
  "properties": {
    "gn:admin1_code":"32.0",
    "gn:asciiname":"Chuluo",
    "gn:country_code":"CN",
    "gn:dem":3386,
    "gn:feature_class":"P",
    "gn:feature_code":"PPL",
    "gn:name":"Chuluo",
    "gn:population":0,
    "gn:timezone":"Asia/Shanghai",
    "iso:country":"CN",
    "name:zho_x_preferred":[
        "\u695a\u6d1b"
    ],
    "wof:name":"Chuluo",
    "wof:placetype":"locality"
},
  "geometry": {"coordinates":[100.063,31.5997],"type":"Point"}
}