{
  "type": "Feature",
  "properties": {
    "gn:admin1_code":"29",
    "gn:asciiname":"Aicun",
    "gn:country_code":"CN",
    "gn:dem":1400,
    "gn:feature_class":"P",
    "gn:feature_code":"PPL",
    "gn:name":"Aicun",
    "gn:population":0,
    "gn:timezone":"Asia/Shanghai",
    "iso:country":"CN",
    "name:zho_x_preferred":[
        "\u6328\u6751"
    ],
    "wof:name":"Aicun",
    "wof:placetype":"locality"
},
  "geometry": {"coordinates":[103.5087,24.10661],"type":"Point"}
}