{
  "type": "Feature",
  "properties": {
    "gn:admin1_code":"16.0",
    "gn:asciiname":"Shanghen",
    "gn:country_code":"CN",
    "gn:dem":258,
    "gn:feature_class":"P",
    "gn:feature_code":"PPL",
    "gn:name":"Shanghen",
    "gn:population":0,
    "gn:timezone":"Asia/Shanghai",
    "iso:country":"CN",
    "name:zho_x_preferred":[
        "\u4e0a\u5f88"
    ],
    "wof:name":"Shanghen",
    "wof:placetype":"locality"
},
  "geometry": {"coordinates":[108.21599999999999,25.0744],"type":"Point"}
}