{
  "type": "Feature",
  "properties": {
    "gn:admin1_code":"32.0",
    "gn:asciiname":"Fuchangba",
    "gn:country_code":"CN",
    "gn:dem":657,
    "gn:feature_class":"P",
    "gn:feature_code":"PPL",
    "gn:name":"Fuchangba",
    "gn:population":0,
    "gn:timezone":"Asia/Shanghai",
    "iso:country":"CN",
    "name:zho_x_preferred":[
        "\u798f\u957f\u575d"
    ],
    "wof:name":"Fuchangba",
    "wof:placetype":"locality"
},
  "geometry": {"coordinates":[104.92871,31.98958],"type":"Point"}
}