{
  "type": "Feature",
  "properties": {
    "gn:admin1_code":"9.0",
    "gn:asciiname":"Dalishu Zhangzhuang",
    "gn:country_code":"CN",
    "gn:dem":126,
    "gn:feature_class":"P",
    "gn:feature_code":"PPL",
    "gn:name":"Dalishu Zhangzhuang",
    "gn:population":0,
    "gn:timezone":"Asia/Shanghai",
    "iso:country":"CN",
    "name:zho_x_preferred":[
        "\u5927\u68a8\u6811\u5f20\u5e84"
    ],
    "wof:name":"Dalishu Zhangzhuang",
    "wof:placetype":"locality"
},
  "geometry": {"coordinates":[111.96906,32.49186],"type":"Point"}
}