{
  "type": "Feature",
  "properties": {
    "gn:admin1_code":"26.0",
    "gn:asciiname":"Dongzui",
    "gn:country_code":"CN",
    "gn:dem":972,
    "gn:feature_class":"P",
    "gn:feature_code":"PPL",
    "gn:name":"Dongzui",
    "gn:population":0,
    "gn:timezone":"Asia/Shanghai",
    "iso:country":"CN",
    "name:zho_x_preferred":[
        "\u4e1c\u5480"
    ],
    "wof:name":"Dongzui",
    "wof:placetype":"locality"
},
  "geometry": {"coordinates":[109.47826000000001,34.27252],"type":"Point"}
}