{
  "type": "Feature",
  "properties": {
    "gn:admin1_code":"16.0",
    "gn:asciiname":"Tunzhe",
    "gn:country_code":"CN",
    "gn:dem":370,
    "gn:feature_class":"P",
    "gn:feature_code":"PPL",
    "gn:name":"Tunzhe",
    "gn:population":0,
    "gn:timezone":"Asia/Shanghai",
    "iso:country":"CN",
    "name:zho_x_preferred":[
        "\u541e\u8fd9"
    ],
    "wof:name":"Tunzhe",
    "wof:placetype":"locality"
},
  "geometry": {"coordinates":[107.336,23.1356],"type":"Point"}
}