{
  "type": "Feature",
  "properties": {
    "gn:admin1_code":"13",
    "gn:asciiname":"Tianshan",
    "gn:country_code":"CN",
    "gn:dem":1508,
    "gn:feature_class":"P",
    "gn:feature_code":"PPL",
    "gn:name":"Tianshan",
    "gn:population":0,
    "gn:timezone":"Asia/Urumqi",
    "iso:country":"CN",
    "name:zho_x_preferred":[
        "\u5929\u5c71"
    ],
    "wof:name":"Tianshan",
    "wof:placetype":"locality"
},
  "geometry": {"coordinates":[87.09575,43.55391],"type":"Point"}
}