{
  "type": "Feature",
  "properties": {
    "gn:admin1_code":"30",
    "gn:asciiname":"Lecheng",
    "gn:country_code":"CN",
    "gn:dem":63,
    "gn:feature_class":"P",
    "gn:feature_code":"PPLA4",
    "gn:name":"Lecheng",
    "gn:population":0,
    "gn:timezone":"Asia/Shanghai",
    "iso:country":"CN",
    "name:swe_x_preferred":[
        "Lecheng"
    ],
    "name:und_x_variant":[
        "Lecheng Zhen",
        "\u4e50\u57ce\u9547"
    ],
    "wof:name":"Lecheng",
    "wof:placetype":"locality"
},
  "geometry": {"coordinates":[112.33244999999999,23.35351],"type":"Point"}
}