{
  "type": "Feature",
  "properties": {
    "gn:admin1_code":"26",
    "gn:asciiname":"Toudaohe",
    "gn:country_code":"CN",
    "gn:dem":1108,
    "gn:feature_class":"P",
    "gn:feature_code":"PPL",
    "gn:name":"Toudaohe",
    "gn:population":0,
    "gn:timezone":"Asia/Shanghai",
    "iso:country":"CN",
    "name:und_x_variant":[
        "T\u2019ou-tao-ho",
        "T\u2019ou-tao-ho-tzu",
        "Toudaohezi"
    ],
    "wof:name":"Toudaohe",
    "wof:placetype":"locality"
},
  "geometry": {"coordinates":[109.73583000000001,38.35139],"type":"Point"}
}