{
  "type": "Feature",
  "properties": {
    "gn:admin1_code":"4.0",
    "gn:asciiname":"Shuaixu",
    "gn:country_code":"CN",
    "gn:dem":6,
    "gn:feature_class":"P",
    "gn:feature_code":"PPL",
    "gn:name":"Shuaixu",
    "gn:population":0,
    "gn:timezone":"Asia/Shanghai",
    "iso:country":"CN",
    "name:zho_x_preferred":[
        "\u5e05\u5729"
    ],
    "wof:name":"Shuaixu",
    "wof:placetype":"locality"
},
  "geometry": {"coordinates":[119.89521000000001,32.38518],"type":"Point"}
}