{
  "type": "Feature",
  "properties": {
    "gn:admin1_code":"32.0",
    "gn:asciiname":"Zhuanzhuandi",
    "gn:country_code":"CN",
    "gn:dem":918,
    "gn:feature_class":"P",
    "gn:feature_code":"PPL",
    "gn:name":"Zhuanzhuandi",
    "gn:population":0,
    "gn:timezone":"Asia/Shanghai",
    "iso:country":"CN",
    "name:zho_x_preferred":[
        "\u8f6c\u8f6c\u5730"
    ],
    "wof:name":"Zhuanzhuandi",
    "wof:placetype":"locality"
},
  "geometry": {"coordinates":[103.318,30.0545],"type":"Point"}
}