{
  "type": "Feature",
  "properties": {
    "gn:admin1_code":"1.0",
    "gn:asciiname":"Putangcun",
    "gn:country_code":"CN",
    "gn:dem":34,
    "gn:feature_class":"P",
    "gn:feature_code":"PPL",
    "gn:name":"Putangcun",
    "gn:population":0,
    "gn:timezone":"Asia/Shanghai",
    "iso:country":"CN",
    "name:zho_x_preferred":[
        "\u84b2\u5858\u6751"
    ],
    "wof:name":"Putangcun",
    "wof:placetype":"locality"
},
  "geometry": {"coordinates":[117.09277,31.81895],"type":"Point"}
}