{
  "type": "Feature",
  "properties": {
    "gn:admin1_code":"26.0",
    "gn:asciiname":"Baipocun",
    "gn:country_code":"CN",
    "gn:dem":1010,
    "gn:feature_class":"P",
    "gn:feature_code":"PPL",
    "gn:name":"Baipocun",
    "gn:population":0,
    "gn:timezone":"Asia/Shanghai",
    "iso:country":"CN",
    "name:zho_x_preferred":[
        "\u767d\u5761\u6751"
    ],
    "wof:name":"Baipocun",
    "wof:placetype":"locality"
},
  "geometry": {"coordinates":[109.64239000000001,36.73953],"type":"Point"}
}