{
  "type": "Feature",
  "properties": {
    "gn:admin1_code":"1.0",
    "gn:asciiname":"Caoliucun",
    "gn:country_code":"CN",
    "gn:dem":20,
    "gn:feature_class":"P",
    "gn:feature_code":"PPL",
    "gn:name":"Caoliucun",
    "gn:population":0,
    "gn:timezone":"Asia/Shanghai",
    "iso:country":"CN",
    "name:zho_x_preferred":[
        "\u66f9\u5218\u6751"
    ],
    "wof:name":"Caoliucun",
    "wof:placetype":"locality"
},
  "geometry": {"coordinates":[117.51809,33.02294000000001],"type":"Point"}
}