{
  "type": "Feature",
  "properties": {
    "gn:admin1_code":"32.0",
    "gn:asciiname":"Bawang Shuikazi",
    "gn:country_code":"CN",
    "gn:dem":2141,
    "gn:feature_class":"P",
    "gn:feature_code":"PPL",
    "gn:name":"Bawang Shuikazi",
    "gn:population":0,
    "gn:timezone":"Asia/Shanghai",
    "iso:country":"CN",
    "name:zho_x_preferred":[
        "\u5df4\u65fa\u6c34\u5361\u5b50"
    ],
    "wof:name":"Bawang Shuikazi",
    "wof:placetype":"locality"
},
  "geometry": {"coordinates":[101.86499999999999,31.0248],"type":"Point"}
}