{
  "type": "Feature",
  "properties": {
    "gn:admin1_code":"8.0",
    "gn:asciiname":"Shiyanchangcun",
    "gn:country_code":"CN",
    "gn:dem":89,
    "gn:feature_class":"P",
    "gn:feature_code":"PPL",
    "gn:name":"Shiyanchangcun",
    "gn:population":0,
    "gn:timezone":"Asia/Shanghai",
    "iso:country":"CN",
    "name:zho_x_preferred":[
        "\u5b9e\u9a8c\u573a\u6751"
    ],
    "wof:name":"Shiyanchangcun",
    "wof:placetype":"locality"
},
  "geometry": {"coordinates":[132.29995,46.33831],"type":"Point"}
}