{
  "type": "Feature",
  "properties": {
    "gn:admin1_code":"24.0",
    "gn:asciiname":"Zhangsongcun",
    "gn:country_code":"CN",
    "gn:dem":390,
    "gn:feature_class":"P",
    "gn:feature_code":"PPL",
    "gn:name":"Zhangsongcun",
    "gn:population":0,
    "gn:timezone":"Asia/Shanghai",
    "iso:country":"CN",
    "name:zho_x_preferred":[
        "\u5f20\u5d69\u6751"
    ],
    "wof:name":"Zhangsongcun",
    "wof:placetype":"locality"
},
  "geometry": {"coordinates":[110.84952,35.05956],"type":"Point"}
}