{
  "type": "Feature",
  "properties": {
    "gn:admin1_code":"30.0",
    "gn:asciiname":"Gaoshifu",
    "gn:country_code":"CN",
    "gn:dem":209,
    "gn:feature_class":"P",
    "gn:feature_code":"PPL",
    "gn:name":"Gaoshifu",
    "gn:population":0,
    "gn:timezone":"Asia/Shanghai",
    "iso:country":"CN",
    "name:zho_x_preferred":[
        "Gaoshifu"
    ],
    "name:zho_x_variant":[
        "\u9ad8\u4e16\u5e9c"
    ],
    "wof:name":"Gaoshifu",
    "wof:placetype":"locality"
},
  "geometry": {"coordinates":[114.10107000000001,24.5485],"type":"Point"}
}