{
  "type": "Feature",
  "properties": {
    "gn:admin1_code":"29",
    "gn:asciiname":"Zhagangchejian",
    "gn:country_code":"CN",
    "gn:dem":1745,
    "gn:feature_class":"P",
    "gn:feature_code":"PPL",
    "gn:name":"Zhagangchejian",
    "gn:population":0,
    "gn:timezone":"Asia/Shanghai",
    "iso:country":"CN",
    "name:zho_x_preferred":[
        "\u624e\u94a2\u8f66\u95f4"
    ],
    "wof:name":"Zhagangchejian",
    "wof:placetype":"locality"
},
  "geometry": {"coordinates":[102.553,24.4669],"type":"Point"}
}