{
  "type": "Feature",
  "properties": {
    "gn:admin1_code":"15.0",
    "gn:asciiname":"Guandiwan",
    "gn:country_code":"CN",
    "gn:dem":2222,
    "gn:feature_class":"P",
    "gn:feature_code":"PPL",
    "gn:name":"Guandiwan",
    "gn:population":0,
    "gn:timezone":"Asia/Shanghai",
    "iso:country":"CN",
    "name:zho_x_preferred":[
        "\u5173\u5730\u6e7e"
    ],
    "wof:name":"Guandiwan",
    "wof:placetype":"locality"
},
  "geometry": {"coordinates":[104.54358000000001,32.96234],"type":"Point"}
}