{
  "type": "Feature",
  "properties": {
    "gn:admin1_code":"2.0",
    "gn:asciiname":"Heshangyan",
    "gn:country_code":"CN",
    "gn:dem":9,
    "gn:feature_class":"P",
    "gn:feature_code":"PPL",
    "gn:name":"Heshangyan",
    "gn:population":0,
    "gn:timezone":"Asia/Shanghai",
    "iso:country":"CN",
    "name:zho_x_preferred":[
        "\u548c\u5c1a\u5ca9"
    ],
    "wof:name":"Heshangyan",
    "wof:placetype":"locality"
},
  "geometry": {"coordinates":[122.40837999999999,29.94416],"type":"Point"}
}