{
  "type": "Feature",
  "properties": {
    "gn:admin1_code":"5.0",
    "gn:asciiname":"Liumuqiaocun",
    "gn:country_code":"CN",
    "gn:dem":442,
    "gn:feature_class":"P",
    "gn:feature_code":"PPL",
    "gn:name":"Liumuqiaocun",
    "gn:population":0,
    "gn:timezone":"Asia/Shanghai",
    "iso:country":"CN",
    "name:zho_x_preferred":[
        "\u67f3\u6728\u6865\u6751"
    ],
    "wof:name":"Liumuqiaocun",
    "wof:placetype":"locality"
},
  "geometry": {"coordinates":[128.43133,43.53081],"type":"Point"}
}