{
  "type": "Feature",
  "properties": {
    "gn:admin1_code":"29",
    "gn:asciiname":"Hongtupo",
    "gn:country_code":"CN",
    "gn:dem":1728,
    "gn:feature_class":"P",
    "gn:feature_code":"PPL",
    "gn:name":"Hongtupo",
    "gn:population":0,
    "gn:timezone":"Asia/Shanghai",
    "iso:country":"CN",
    "name:zho_x_preferred":[
        "\u7ea2\u571f\u5761"
    ],
    "wof:name":"Hongtupo",
    "wof:placetype":"locality"
},
  "geometry": {"coordinates":[102.08499999999999,23.4154],"type":"Point"}
}