{
  "type": "Feature",
  "properties": {
    "gn:admin1_code":"33.0",
    "gn:asciiname":"Tiangong",
    "gn:country_code":"CN",
    "gn:dem":493,
    "gn:feature_class":"P",
    "gn:feature_code":"PPL",
    "gn:name":"Tiangong",
    "gn:population":0,
    "gn:timezone":"Asia/Shanghai",
    "iso:country":"CN",
    "name:zho_x_preferred":[
        "\u5929\u5bab"
    ],
    "wof:name":"Tiangong",
    "wof:placetype":"locality"
},
  "geometry": {"coordinates":[105.78081,29.79633],"type":"Point"}
}