{
  "type": "Feature",
  "properties": {
    "gn:admin1_code":"21.0",
    "gn:asciiname":"Huaigou",
    "gn:country_code":"CN",
    "gn:dem":1522,
    "gn:feature_class":"P",
    "gn:feature_code":"PPL",
    "gn:name":"Huaigou",
    "gn:population":0,
    "gn:timezone":"Asia/Shanghai",
    "iso:country":"CN",
    "name:zho_x_preferred":[
        "\u69d0\u6c9f"
    ],
    "wof:name":"Huaigou",
    "wof:placetype":"locality"
},
  "geometry": {"coordinates":[106.602,35.8887],"type":"Point"}
}