{
  "type": "Feature",
  "properties": {
    "gn:admin1_code":"24",
    "gn:asciiname":"Polubu",
    "gn:country_code":"CN",
    "gn:dem":1231,
    "gn:feature_class":"P",
    "gn:feature_code":"PPL",
    "gn:name":"Polubu",
    "gn:population":0,
    "gn:timezone":"Asia/Shanghai",
    "iso:country":"CN",
    "name:und_x_variant":[
        "Polu",
        "P\u2019o-lu-pao",
        "Polubu Xiang",
        "P\u2019o-lu-p\u2019u",
        "Polubu"
    ],
    "name:zho_x_preferred":[
        "\u7834\u9c81\u5821"
    ],
    "wof:name":"Polubu",
    "wof:placetype":"locality"
},
  "geometry": {"coordinates":[112.96259000000001,40.22047],"type":"Point"}
}