{
  "type": "Feature",
  "properties": {
    "gn:admin1_code":"14.0",
    "gn:asciiname":"Guobuka",
    "gn:country_code":"CN",
    "gn:dem":3854,
    "gn:feature_class":"P",
    "gn:feature_code":"PPL",
    "gn:name":"Guobuka",
    "gn:population":0,
    "gn:timezone":"Asia/Urumqi",
    "iso:country":"CN",
    "name:zho_x_preferred":[
        "\u679c\u5e03\u5361"
    ],
    "wof:name":"Guobuka",
    "wof:placetype":"locality"
},
  "geometry": {"coordinates":[97.21044000000001,31.1396],"type":"Point"}
}