{
  "type": "Feature",
  "properties": {
    "gn:admin1_code":"31",
    "gn:asciiname":"Quanmei",
    "gn:country_code":"CN",
    "gn:dem":26,
    "gn:feature_class":"P",
    "gn:feature_code":"PPL",
    "gn:name":"Quanmei",
    "gn:population":0,
    "gn:timezone":"Asia/Shanghai",
    "iso:country":"CN",
    "name:und_x_variant":[
        "\u5168\u7f8e"
    ],
    "wof:name":"Quanmei",
    "wof:placetype":"locality"
},
  "geometry": {"coordinates":[110.95699999999999,19.6982],"type":"Point"}
}