{
  "type": "Feature",
  "properties": {
    "gn:admin1_code":"25.0",
    "gn:asciiname":"Xinfazhuangcun",
    "gn:country_code":"CN",
    "gn:dem":38,
    "gn:feature_class":"P",
    "gn:feature_code":"PPL",
    "gn:name":"Xinfazhuangcun",
    "gn:population":0,
    "gn:timezone":"Asia/Shanghai",
    "iso:country":"CN",
    "name:zho_x_preferred":[
        "\u65b0\u53d1\u5e84\u6751"
    ],
    "wof:name":"Xinfazhuangcun",
    "wof:placetype":"locality"
},
  "geometry": {"coordinates":[121.93563,37.22117],"type":"Point"}
}