{
  "type": "Feature",
  "properties": {
    "gn:admin1_code":"3.0",
    "gn:asciiname":"Qingguan",
    "gn:country_code":"CN",
    "gn:dem":80,
    "gn:feature_class":"P",
    "gn:feature_code":"PPL",
    "gn:name":"Qingguan",
    "gn:population":0,
    "gn:timezone":"Asia/Shanghai",
    "iso:country":"CN",
    "name:und_x_variant":[
        "\u9752\u89c2"
    ],
    "wof:name":"Qingguan",
    "wof:placetype":"locality"
},
  "geometry": {"coordinates":[114.78167000000001,27.48772],"type":"Point"}
}