{
  "type": "Feature",
  "properties": {
    "gn:admin1_code":"19.0",
    "gn:asciiname":"Liugudaocun",
    "gn:country_code":"CN",
    "gn:dem":147,
    "gn:feature_class":"P",
    "gn:feature_code":"PPL",
    "gn:name":"Liugudaocun",
    "gn:population":0,
    "gn:timezone":"Asia/Shanghai",
    "iso:country":"CN",
    "name:zho_x_preferred":[
        "\u516d\u80a1\u9053\u6751"
    ],
    "wof:name":"Liugudaocun",
    "wof:placetype":"locality"
},
  "geometry": {"coordinates":[122.254,42.6177],"type":"Point"}
}