{
  "type": "Feature",
  "properties": {
    "gn:admin1_code":"05",
    "gn:asciiname":"Taipingchuan",
    "gn:cc2":"CN",
    "gn:country_code":"CN",
    "gn:dem":404,
    "gn:feature_class":"P",
    "gn:feature_code":"PPL",
    "gn:name":"Taipingchuan",
    "gn:population":0,
    "gn:timezone":"Asia/Shanghai",
    "iso:country":"CN",
    "name:und_x_variant":[
        "Ta-p\u2019ing-ch\u2019uan",
        "Taipingchuan"
    ],
    "wof:name":"Taipingchuan",
    "wof:placetype":"locality"
},
  "geometry": {"coordinates":[127.28917,42.62694000000001],"type":"Point"}
}