{
  "type": "Feature",
  "properties": {
    "gn:admin1_code":"8.0",
    "gn:asciiname":"Yangmuzuizicun",
    "gn:country_code":"CN",
    "gn:dem":98,
    "gn:feature_class":"P",
    "gn:feature_code":"PPL",
    "gn:name":"Yangmuzuizicun",
    "gn:population":0,
    "gn:timezone":"Asia/Shanghai",
    "iso:country":"CN",
    "name:zho_x_preferred":[
        "\u6768\u6728\u5480\u5b50\u6751"
    ],
    "wof:name":"Yangmuzuizicun",
    "wof:placetype":"locality"
},
  "geometry": {"coordinates":[132.29658999999998,45.46837],"type":"Point"}
}