{
  "type": "Feature",
  "properties": {
    "gn:admin1_code":"18",
    "gn:asciiname":"Wotian",
    "gn:country_code":"CN",
    "gn:dem":1190,
    "gn:feature_class":"P",
    "gn:feature_code":"PPL",
    "gn:name":"Wotian",
    "gn:population":0,
    "gn:timezone":"Asia/Shanghai",
    "iso:country":"CN",
    "name:zho_x_preferred":[
        "\u6c83\u7530"
    ],
    "wof:name":"Wotian",
    "wof:placetype":"locality"
},
  "geometry": {"coordinates":[105.78,25.9466],"type":"Point"}
}