{
  "type": "Feature",
  "properties": {
    "gn:admin1_code":"25",
    "gn:asciiname":"Saosikuang",
    "gn:country_code":"CN",
    "gn:dem":139,
    "gn:feature_class":"P",
    "gn:feature_code":"PPL",
    "gn:name":"Saosikuang",
    "gn:population":0,
    "gn:timezone":"Asia/Shanghai",
    "iso:country":"CN",
    "name:zho_x_preferred":[
        "\u7f2b\u4e1d\u593c"
    ],
    "wof:name":"Saosikuang",
    "wof:placetype":"locality"
},
  "geometry": {"coordinates":[121.31399999999999,37.1703],"type":"Point"}
}