{
  "type": "Feature",
  "properties": {
    "gn:admin1_code":"15.0",
    "gn:asciiname":"Dashumao",
    "gn:country_code":"CN",
    "gn:dem":1486,
    "gn:feature_class":"P",
    "gn:feature_code":"PPL",
    "gn:name":"Dashumao",
    "gn:population":0,
    "gn:timezone":"Asia/Shanghai",
    "iso:country":"CN",
    "name:und_x_variant":[
        "\u5927\u6811\u5cc1"
    ],
    "wof:name":"Dashumao",
    "wof:placetype":"locality"
},
  "geometry": {"coordinates":[107.32735,36.76053],"type":"Point"}
}