{
  "type": "Feature",
  "properties": {
    "gn:admin1_code":"18.0",
    "gn:asciiname":"Baige",
    "gn:country_code":"CN",
    "gn:dem":934,
    "gn:feature_class":"P",
    "gn:feature_code":"PPL",
    "gn:name":"Baige",
    "gn:population":0,
    "gn:timezone":"Asia/Shanghai",
    "iso:country":"CN",
    "name:zho_x_preferred":[
        "\u6446\u683c"
    ],
    "wof:name":"Baige",
    "wof:placetype":"locality"
},
  "geometry": {"coordinates":[108.414,25.551],"type":"Point"}
}