{
  "type": "Feature",
  "properties": {
    "gn:admin1_code":"29.0",
    "gn:asciiname":"Shuanglawa",
    "gn:country_code":"CN",
    "gn:dem":1757,
    "gn:feature_class":"P",
    "gn:feature_code":"PPL",
    "gn:name":"Shuanglawa",
    "gn:population":0,
    "gn:timezone":"Asia/Shanghai",
    "iso:country":"CN",
    "name:zho_x_preferred":[
        "\u53cc\u62c9\u5a03"
    ],
    "wof:name":"Shuanglawa",
    "wof:placetype":"locality"
},
  "geometry": {"coordinates":[98.6276,27.7704],"type":"Point"}
}