{
  "type": "Feature",
  "properties": {
    "gn:admin1_code":"9.0",
    "gn:asciiname":"Pucheng",
    "gn:country_code":"CN",
    "gn:dem":83,
    "gn:feature_class":"P",
    "gn:feature_code":"PPL",
    "gn:name":"Pucheng",
    "gn:population":0,
    "gn:timezone":"Asia/Shanghai",
    "iso:country":"CN",
    "name:ceb_x_preferred":[
        "Pucheng"
    ],
    "name:deu_x_preferred":[
        "Pucheng"
    ],
    "name:fra_x_preferred":[
        "Pucheng"
    ],
    "name:kor_x_preferred":[
        "\ud478\uccad\ud604"
    ],
    "name:mlg_x_preferred":[
        "Pucheng"
    ],
    "name:nor_x_preferred":[
        "Pucheng"
    ],
    "name:rus_x_preferred":[
        "\u041f\u0443\u0447\u044d\u043d"
    ],
    "name:swe_x_preferred":[
        "Pucheng"
    ],
    "name:zho_x_preferred":[
        "\u84b2\u57ce"
    ],
    "wof:name":"Pucheng",
    "wof:placetype":"locality"
},
  "geometry": {"coordinates":[113.43391,33.72555999999999],"type":"Point"}
}