{
  "type": "Feature",
  "properties": {
    "gn:admin1_code":"15.0",
    "gn:asciiname":"Toufen",
    "gn:country_code":"CN",
    "gn:dem":1180,
    "gn:feature_class":"P",
    "gn:feature_code":"PPL",
    "gn:name":"Toufen",
    "gn:population":0,
    "gn:timezone":"Asia/Shanghai",
    "iso:country":"CN",
    "name:zho_x_preferred":[
        "\u5934\u5206"
    ],
    "wof:name":"Toufen",
    "wof:placetype":"locality"
},
  "geometry": {"coordinates":[99.52589999999999,40.2939],"type":"Point"}
}