{
  "type": "Feature",
  "properties": {
    "gn:admin1_code":"15.0",
    "gn:asciiname":"Toufen",
    "gn:country_code":"CN",
    "gn:dem":1180,
    "gn:feature_class":"P",
    "gn:feature_code":"PPL",
    "gn:name":"Toufen",
    "gn:population":0,
    "gn:timezone":"Asia/Shanghai",
    "iso:country":"CN",
    "name:deu_x_preferred":[
        "Toufen"
    ],
    "name:fas_x_preferred":[
        "\u062a\u0648\u0641\u0646"
    ],
    "name:fra_x_preferred":[
        "Toufen"
    ],
    "name:hak_x_preferred":[
        "Th\u00e8u-fun-s\u1e73"
    ],
    "name:ita_x_preferred":[
        "Toufen"
    ],
    "name:jpn_x_preferred":[
        "\u982d\u30d5\u30f3\u5e02"
    ],
    "name:kor_x_preferred":[
        "\ud130\uc6b0\ud380\uc2dc"
    ],
    "name:pol_x_preferred":[
        "Toufen"
    ],
    "name:rus_x_preferred":[
        "\u0422\u043e\u0443\u0444\u044d\u043d\u044c"
    ],
    "name:szl_x_preferred":[
        "Toufen"
    ],
    "name:vie_x_preferred":[
        "\u0110\u1ea7u Ph\u1ea7n"
    ],
    "name:zho_x_preferred":[
        "\u5934\u5206"
    ],
    "name:zho_x_variant":[
        "\u982d\u4efd\u5e02"
    ],
    "wof:name":"Toufen",
    "wof:placetype":"locality"
},
  "geometry": {"coordinates":[99.52589999999999,40.2939],"type":"Point"}
}