{
  "type": "Feature",
  "properties": {
    "gn:admin1_code":"24.0",
    "gn:asciiname":"Zhongzhuanggou",
    "gn:country_code":"CN",
    "gn:dem":1481,
    "gn:feature_class":"P",
    "gn:feature_code":"PPL",
    "gn:name":"Zhongzhuanggou",
    "gn:population":0,
    "gn:timezone":"Asia/Shanghai",
    "iso:country":"CN",
    "name:zho_x_preferred":[
        "\u4e2d\u5e84\u6c9f"
    ],
    "wof:name":"Zhongzhuanggou",
    "wof:placetype":"locality"
},
  "geometry": {"coordinates":[111.32826,37.84223],"type":"Point"}
}