{
  "type": "Feature",
  "properties": {
    "gn:admin1_code":"26",
    "gn:asciiname":"Donghou",
    "gn:country_code":"CN",
    "gn:dem":413,
    "gn:feature_class":"P",
    "gn:feature_code":"PPL",
    "gn:name":"Donghou",
    "gn:population":0,
    "gn:timezone":"Asia/Shanghai",
    "iso:country":"CN",
    "name:und_x_variant":[
        "\u4e1c\u4faf"
    ],
    "wof:name":"Donghou",
    "wof:placetype":"locality"
},
  "geometry": {"coordinates":[109.11944,34.27111],"type":"Point"}
}