{
  "type": "Feature",
  "properties": {
    "gn:admin1_code":"25",
    "gn:asciiname":"Wayuxi",
    "gn:country_code":"CN",
    "gn:dem":148,
    "gn:feature_class":"P",
    "gn:feature_code":"PPL",
    "gn:name":"Wayuxi",
    "gn:population":0,
    "gn:timezone":"Asia/Shanghai",
    "iso:country":"CN",
    "name:zho_x_preferred":[
        "\u74e6\u5cea\u897f"
    ],
    "wof:name":"Wayuxi",
    "wof:placetype":"locality"
},
  "geometry": {"coordinates":[117.267,35.2801],"type":"Point"}
}