{
  "type": "Feature",
  "properties": {
    "gn:admin1_code":"29.0",
    "gn:asciiname":"Yongning",
    "gn:country_code":"CN",
    "gn:dem":1530,
    "gn:feature_class":"P",
    "gn:feature_code":"PPL",
    "gn:name":"Yongning",
    "gn:population":0,
    "gn:timezone":"Asia/Shanghai",
    "iso:country":"CN",
    "name:ceb_x_preferred":[
        "Yongning"
    ],
    "name:deu_x_preferred":[
        "Yongning"
    ],
    "name:fra_x_preferred":[
        "Yongning"
    ],
    "name:mlg_x_preferred":[
        "Yongning"
    ],
    "name:nor_x_preferred":[
        "Yongning"
    ],
    "name:pol_x_preferred":[
        "Yongning"
    ],
    "name:rus_x_preferred":[
        "\u042e\u043d\u043d\u0438\u043d"
    ],
    "name:swe_x_preferred":[
        "Yongning"
    ],
    "name:zho_x_preferred":[
        "\u6c38\u5b81"
    ],
    "wof:name":"Yongning",
    "wof:placetype":"locality"
},
  "geometry": {"coordinates":[103.69199999999999,24.3723],"type":"Point"}
}