{
  "type": "Feature",
  "properties": {
    "gn:admin1_code":"1.0",
    "gn:asciiname":"Jiukeshucun",
    "gn:country_code":"CN",
    "gn:dem":50,
    "gn:feature_class":"P",
    "gn:feature_code":"PPL",
    "gn:name":"Jiukeshucun",
    "gn:population":0,
    "gn:timezone":"Asia/Shanghai",
    "iso:country":"CN",
    "name:zho_x_preferred":[
        "\u4e5d\u68f5\u6811\u6751"
    ],
    "wof:name":"Jiukeshucun",
    "wof:placetype":"locality"
},
  "geometry": {"coordinates":[116.15749,31.82681],"type":"Point"}
}