{
  "type": "Feature",
  "properties": {
    "gn:admin1_code":"30.0",
    "gn:asciiname":"Anweicun",
    "gn:country_code":"CN",
    "gn:dem":102,
    "gn:feature_class":"P",
    "gn:feature_code":"PPL",
    "gn:name":"Anweicun",
    "gn:population":0,
    "gn:timezone":"Asia/Shanghai",
    "iso:country":"CN",
    "name:zho_x_preferred":[
        "\u5b89\u5c3e\u6751"
    ],
    "wof:name":"Anweicun",
    "wof:placetype":"locality"
},
  "geometry": {"coordinates":[116.04071999999999,24.08991],"type":"Point"}
}