{
  "type": "Feature",
  "properties": {
    "gn:admin1_code":"16.0",
    "gn:asciiname":"Pinjie",
    "gn:country_code":"CN",
    "gn:dem":870,
    "gn:feature_class":"P",
    "gn:feature_code":"PPL",
    "gn:name":"Pinjie",
    "gn:population":0,
    "gn:timezone":"Asia/Shanghai",
    "iso:country":"CN",
    "name:zho_x_preferred":[
        "\u54c1\u754c"
    ],
    "wof:name":"Pinjie",
    "wof:placetype":"locality"
},
  "geometry": {"coordinates":[107.414,25.1381],"type":"Point"}
}