{
  "type": "Feature",
  "properties": {
    "gn:admin1_code":"32.0",
    "gn:asciiname":"Longzhuanian",
    "gn:country_code":"CN",
    "gn:dem":495,
    "gn:feature_class":"P",
    "gn:feature_code":"PPL",
    "gn:name":"Longzhuanian",
    "gn:population":0,
    "gn:timezone":"Asia/Shanghai",
    "iso:country":"CN",
    "name:zho_x_preferred":[
        "\u9f99\u722a\u57dd"
    ],
    "wof:name":"Longzhuanian",
    "wof:placetype":"locality"
},
  "geometry": {"coordinates":[104.199,31.0378],"type":"Point"}
}