{
  "type": "Feature",
  "properties": {
    "gn:admin1_code":"8.0",
    "gn:asciiname":"Zhuangjiagou",
    "gn:country_code":"CN",
    "gn:dem":167,
    "gn:feature_class":"P",
    "gn:feature_code":"PPL",
    "gn:name":"Zhuangjiagou",
    "gn:population":0,
    "gn:timezone":"Asia/Shanghai",
    "iso:country":"CN",
    "name:zho_x_preferred":[
        "\u5e84\u5bb6\u6c9f"
    ],
    "wof:name":"Zhuangjiagou",
    "wof:placetype":"locality"
},
  "geometry": {"coordinates":[127.06482,46.73909],"type":"Point"}
}