{
  "type": "Feature",
  "properties": {
    "gn:admin1_code":"29.0",
    "gn:asciiname":"Yangliuping",
    "gn:country_code":"CN",
    "gn:dem":3132,
    "gn:feature_class":"P",
    "gn:feature_code":"PPL",
    "gn:name":"Yangliuping",
    "gn:population":0,
    "gn:timezone":"Asia/Shanghai",
    "iso:country":"CN",
    "name:zho_x_preferred":[
        "\u6768\u67f3\u576a"
    ],
    "wof:name":"Yangliuping",
    "wof:placetype":"locality"
},
  "geometry": {"coordinates":[99.44589999999999,26.6945],"type":"Point"}
}