{
  "type": "Feature",
  "properties": {
    "gn:admin1_code":"21.0",
    "gn:asciiname":"Weituan",
    "gn:country_code":"CN",
    "gn:dem":1125,
    "gn:feature_class":"P",
    "gn:feature_code":"PPL",
    "gn:name":"Weituan",
    "gn:population":0,
    "gn:timezone":"Asia/Shanghai",
    "iso:country":"CN",
    "name:zho_x_preferred":[
        "\u4f4d\u56e2"
    ],
    "wof:name":"Weituan",
    "wof:placetype":"locality"
},
  "geometry": {"coordinates":[106.142,38.2051],"type":"Point"}
}