{
  "type": "Feature",
  "properties": {
    "gn:admin1_code":"07",
    "gn:asciiname":"Neibanshan",
    "gn:country_code":"CN",
    "gn:dem":883,
    "gn:feature_class":"P",
    "gn:feature_code":"PPL",
    "gn:name":"Neibanshan",
    "gn:population":0,
    "gn:timezone":"Asia/Shanghai",
    "iso:country":"CN",
    "name:zho_x_preferred":[
        "\u5185\u534a\u5c71"
    ],
    "wof:name":"Neibanshan",
    "wof:placetype":"locality"
},
  "geometry": {"coordinates":[117.91128,25.62916],"type":"Point"}
}