{
  "type": "Feature",
  "properties": {
    "gn:admin1_code":"20.0",
    "gn:asciiname":"Liushihao",
    "gn:country_code":"CN",
    "gn:dem":1466,
    "gn:feature_class":"P",
    "gn:feature_code":"PPL",
    "gn:name":"Liushihao",
    "gn:population":0,
    "gn:timezone":"Asia/Shanghai",
    "iso:country":"CN",
    "name:und_x_variant":[
        "\u516d\u5341\u53f7"
    ],
    "wof:name":"Liushihao",
    "wof:placetype":"locality"
},
  "geometry": {"coordinates":[113.5099,40.74981],"type":"Point"}
}