{
  "type": "Feature",
  "properties": {
    "gn:admin1_code":"29",
    "gn:asciiname":"Yaoheli",
    "gn:country_code":"CN",
    "gn:dem":1883,
    "gn:feature_class":"P",
    "gn:feature_code":"PPL",
    "gn:name":"Yaoheli",
    "gn:population":0,
    "gn:timezone":"Asia/Shanghai",
    "iso:country":"CN",
    "name:und_x_variant":[
        "Meheli",
        "Yaoheli"
    ],
    "name:zho_x_preferred":[
        "\u4e48\u6cb3\u529b"
    ],
    "wof:name":"Yaoheli",
    "wof:placetype":"locality"
},
  "geometry": {"coordinates":[101.538,24.9394],"type":"Point"}
}