{
  "type": "Feature",
  "properties": {
    "gn:admin1_code":"18.0",
    "gn:asciiname":"Mifeng",
    "gn:country_code":"CN",
    "gn:dem":2293,
    "gn:feature_class":"P",
    "gn:feature_code":"PPL",
    "gn:name":"Mifeng",
    "gn:population":0,
    "gn:timezone":"Asia/Shanghai",
    "iso:country":"CN",
    "name:zho_x_preferred":[
        "\u871c\u8702"
    ],
    "wof:name":"Mifeng",
    "wof:placetype":"locality"
},
  "geometry": {"coordinates":[103.983,26.6936],"type":"Point"}
}