{
  "type": "Feature",
  "properties": {
    "gn:admin1_code":"20",
    "gn:asciiname":"Wu-chia-tzu",
    "gn:country_code":"CN",
    "gn:dem":853,
    "gn:feature_class":"P",
    "gn:feature_code":"PPL",
    "gn:name":"Wu-chia-tzu",
    "gn:population":0,
    "gn:timezone":"Asia/Shanghai",
    "iso:country":"CN",
    "wof:name":"Wu-chia-tzu",
    "wof:placetype":"locality"
},
  "geometry": {"coordinates":[118.78417,42.54111],"type":"Point"}
}