{
  "type": "Feature",
  "properties": {
    "gn:admin1_code":"11.0",
    "gn:asciiname":"Xiaolitang",
    "gn:country_code":"CN",
    "gn:dem":76,
    "gn:feature_class":"P",
    "gn:feature_code":"PPL",
    "gn:name":"Xiaolitang",
    "gn:population":0,
    "gn:timezone":"Asia/Shanghai",
    "iso:country":"CN",
    "name:zho_x_preferred":[
        "\u5c0f\u91cc\u5858"
    ],
    "wof:name":"Xiaolitang",
    "wof:placetype":"locality"
},
  "geometry": {"coordinates":[113.20162999999999,27.62698],"type":"Point"}
}