{
  "type": "Feature",
  "properties": {
    "gn:admin1_code":"16.0",
    "gn:asciiname":"Wentoutang",
    "gn:country_code":"CN",
    "gn:dem":184,
    "gn:feature_class":"P",
    "gn:feature_code":"PPL",
    "gn:name":"Wentoutang",
    "gn:population":0,
    "gn:timezone":"Asia/Shanghai",
    "iso:country":"CN",
    "name:zho_x_preferred":[
        "\u6587\u5934\u5858"
    ],
    "wof:name":"Wentoutang",
    "wof:placetype":"locality"
},
  "geometry": {"coordinates":[109.682,22.188],"type":"Point"}
}