{
  "type": "Feature",
  "properties": {
    "gn:admin1_code":"12.0",
    "gn:asciiname":"Fengshupu",
    "gn:country_code":"CN",
    "gn:dem":181,
    "gn:feature_class":"P",
    "gn:feature_code":"PPL",
    "gn:name":"Fengshupu",
    "gn:population":0,
    "gn:timezone":"Asia/Shanghai",
    "iso:country":"CN",
    "name:zho_x_preferred":[
        "\u67ab\u6811\u94fa"
    ],
    "wof:name":"Fengshupu",
    "wof:placetype":"locality"
},
  "geometry": {"coordinates":[115.63996000000002,31.03604],"type":"Point"}
}