{
  "type": "Feature",
  "properties": {
    "gn:admin1_code":"19.0",
    "gn:asciiname":"Tujingshan",
    "gn:country_code":"CN",
    "gn:dem":83,
    "gn:feature_class":"P",
    "gn:feature_code":"PPL",
    "gn:name":"Tujingshan",
    "gn:population":0,
    "gn:timezone":"Asia/Shanghai",
    "iso:country":"CN",
    "name:zho_x_preferred":[
        "\u571f\u4e95\u5c71"
    ],
    "wof:name":"Tujingshan",
    "wof:placetype":"locality"
},
  "geometry": {"coordinates":[123.45399999999999,42.6588],"type":"Point"}
}