{
  "type": "Feature",
  "properties": {
    "gn:admin1_code":"1.0",
    "gn:asciiname":"Sanhe Minzucun",
    "gn:country_code":"CN",
    "gn:dem":29,
    "gn:feature_class":"P",
    "gn:feature_code":"PPL",
    "gn:name":"Sanhe Minzucun",
    "gn:population":0,
    "gn:timezone":"Asia/Shanghai",
    "iso:country":"CN",
    "name:zho_x_preferred":[
        "\u4e09\u548c\u6c11\u65cf\u6751"
    ],
    "wof:name":"Sanhe Minzucun",
    "wof:placetype":"locality"
},
  "geometry": {"coordinates":[115.75951999999999,32.71173],"type":"Point"}
}