{
  "type": "Feature",
  "properties": {
    "gn:admin1_code":"30.0",
    "gn:asciiname":"Meishuchong",
    "gn:country_code":"CN",
    "gn:dem":730,
    "gn:feature_class":"P",
    "gn:feature_code":"PPL",
    "gn:name":"Meishuchong",
    "gn:population":0,
    "gn:timezone":"Asia/Shanghai",
    "iso:country":"CN",
    "name:zho_x_preferred":[
        "Meishuchong"
    ],
    "name:zho_x_variant":[
        "\u6885\u6811\u51b2"
    ],
    "wof:name":"Meishuchong",
    "wof:placetype":"locality"
},
  "geometry": {"coordinates":[112.42972,25.1325],"type":"Point"}
}