{
  "type": "Feature",
  "properties": {
    "gn:admin1_code":"7",
    "gn:asciiname":"Xibian",
    "gn:country_code":"CN",
    "gn:dem":315,
    "gn:feature_class":"P",
    "gn:feature_code":"PPL",
    "gn:name":"Xibian",
    "gn:population":0,
    "gn:timezone":"Asia/Shanghai",
    "iso:country":"CN",
    "name:und_x_variant":[
        "\u897f\u8fb9"
    ],
    "wof:name":"Xibian",
    "wof:placetype":"locality"
},
  "geometry": {"coordinates":[118.77500000000001,27.765],"type":"Point"}
}