{
  "type": "Feature",
  "properties": {
    "gn:admin1_code":"11.0",
    "gn:asciiname":"Gaoshengling",
    "gn:country_code":"CN",
    "gn:dem":198,
    "gn:feature_class":"P",
    "gn:feature_code":"PPL",
    "gn:name":"Gaoshengling",
    "gn:population":0,
    "gn:timezone":"Asia/Shanghai",
    "iso:country":"CN",
    "name:und_x_variant":[
        "Gaoshengwan"
    ],
    "name:zho_x_preferred":[
        "\u9ad8\u5347\u5cad"
    ],
    "wof:name":"Gaoshengling",
    "wof:placetype":"locality"
},
  "geometry": {"coordinates":[113.84021,28.10388],"type":"Point"}
}