{
  "type": "Feature",
  "properties": {
    "gn:admin1_code":"14.0",
    "gn:asciiname":"Lamacun",
    "gn:country_code":"CN",
    "gn:dem":4104,
    "gn:feature_class":"P",
    "gn:feature_code":"PPL",
    "gn:name":"Lamacun",
    "gn:population":0,
    "gn:timezone":"Asia/Urumqi",
    "iso:country":"CN",
    "name:zho_x_preferred":[
        "\u62c9\u739b\u6751"
    ],
    "wof:name":"Lamacun",
    "wof:placetype":"locality"
},
  "geometry": {"coordinates":[98.10232000000001,30.93886],"type":"Point"}
}