{
  "type": "Feature",
  "properties": {
    "gn:admin1_code":"4.0",
    "gn:asciiname":"Lijia",
    "gn:country_code":"CN",
    "gn:dem":8,
    "gn:feature_class":"P",
    "gn:feature_code":"PPL",
    "gn:name":"Lijia",
    "gn:population":0,
    "gn:timezone":"Asia/Shanghai",
    "iso:country":"CN",
    "name:deu_x_preferred":[
        "Lijia"
    ],
    "name:zho_x_preferred":[
        "\u674e\u5bb6"
    ],
    "wof:name":"Lijia",
    "wof:placetype":"locality"
},
  "geometry": {"coordinates":[119.75194999999999,32.06818],"type":"Point"}
}