{
  "type": "Feature",
  "properties": {
    "gn:admin1_code":"3.0",
    "gn:asciiname":"Niudong Xiongjia",
    "gn:country_code":"CN",
    "gn:dem":56,
    "gn:feature_class":"P",
    "gn:feature_code":"PPL",
    "gn:name":"Niudong Xiongjia",
    "gn:population":0,
    "gn:timezone":"Asia/Shanghai",
    "iso:country":"CN",
    "name:zho_x_preferred":[
        "\u725b\u6d1e\u718a\u5bb6"
    ],
    "wof:name":"Niudong Xiongjia",
    "wof:placetype":"locality"
},
  "geometry": {"coordinates":[115.376,28.8041],"type":"Point"}
}