{
  "type": "Feature",
  "properties": {
    "gn:admin1_code":"26.0",
    "gn:asciiname":"Yuhuanggecun",
    "gn:country_code":"CN",
    "gn:dem":683,
    "gn:feature_class":"P",
    "gn:feature_code":"PPL",
    "gn:name":"Yuhuanggecun",
    "gn:population":0,
    "gn:timezone":"Asia/Shanghai",
    "iso:country":"CN",
    "name:zho_x_preferred":[
        "\u7389\u7687\u9601\u6751"
    ],
    "wof:name":"Yuhuanggecun",
    "wof:placetype":"locality"
},
  "geometry": {"coordinates":[108.89816999999999,34.87424],"type":"Point"}
}