{
  "type": "Feature",
  "properties": {
    "iso:country":"CN",
    "qs:name":"\u4e50\u6e05\u5e02",
    "qs:name_adm0":"\u4e2d\u570b",
    "qs:name_adm1":"\u6d59\u6c5f\u7701",
    "qs:photos":128,
    "qs:photos_1k":26,
    "qs:photos_9k":1,
    "qs:photos_9r":4,
    "qs:photos_all":286,
    "qs:photos_sr":3,
    "qs:placetype":"LocalAdmin",
    "qs:pop_sr":"0",
    "wof:name":"\u4e50\u6e05\u5e02",
    "wof:placetype":"localadmin"
},
  "geometry": {"coordinates":[120.9567845,28.134971],"type":"Point"}
}