{
  "type": "Feature",
  "properties": {
    "gn:admin1_code":"26.0",
    "gn:asciiname":"Qixincun",
    "gn:country_code":"CN",
    "gn:dem":1531,
    "gn:feature_class":"P",
    "gn:feature_code":"PPL",
    "gn:name":"Qixincun",
    "gn:population":0,
    "gn:timezone":"Asia/Shanghai",
    "iso:country":"CN",
    "name:und_x_variant":[
        "\u9f50\u5fc3\u6751"
    ],
    "wof:name":"Qixincun",
    "wof:placetype":"locality"
},
  "geometry": {"coordinates":[107.04006,34.06644],"type":"Point"}
}