{
  "type": "Feature",
  "properties": {
    "gn:admin1_code":"3.0",
    "gn:asciiname":"Dahefan",
    "gn:country_code":"CN",
    "gn:dem":28,
    "gn:feature_class":"P",
    "gn:feature_code":"PPL",
    "gn:name":"Dahefan",
    "gn:population":0,
    "gn:timezone":"Asia/Shanghai",
    "iso:country":"CN",
    "name:und_x_variant":[
        "\u5927\u4f55\u7548"
    ],
    "wof:name":"Dahefan",
    "wof:placetype":"locality"
},
  "geometry": {"coordinates":[115.6538,29.38068],"type":"Point"}
}