{
  "type": "Feature",
  "properties": {
    "gn:admin1_code":"2.0",
    "gn:asciiname":"Liyi",
    "gn:country_code":"CN",
    "gn:dem":84,
    "gn:feature_class":"P",
    "gn:feature_code":"PPL",
    "gn:name":"Liyi",
    "gn:population":0,
    "gn:timezone":"Asia/Shanghai",
    "iso:country":"CN",
    "name:zho_x_preferred":[
        "\u674e\u4e00"
    ],
    "wof:name":"Liyi",
    "wof:placetype":"locality"
},
  "geometry": {"coordinates":[119.97318,28.87258],"type":"Point"}
}