{
  "type": "Feature",
  "properties": {
    "gn:admin1_code":"19.0",
    "gn:asciiname":"Hailiban",
    "gn:country_code":"CN",
    "gn:dem":303,
    "gn:feature_class":"P",
    "gn:feature_code":"PPL",
    "gn:name":"Hailiban",
    "gn:population":0,
    "gn:timezone":"Asia/Shanghai",
    "iso:country":"CN",
    "name:und_x_variant":[
        "\u6d77\u529b\u677f"
    ],
    "name:zho_x_preferred":[
        "\u6d77\u529b\u677f"
    ],
    "wof:name":"Hailiban",
    "wof:placetype":"locality"
},
  "geometry": {"coordinates":[121.59271,42.34244],"type":"Point"}
}