{
  "type": "Feature",
  "properties": {
    "gn:admin1_code":"11.0",
    "gn:asciiname":"Cenzhong",
    "gn:country_code":"CN",
    "gn:dem":620,
    "gn:feature_class":"P",
    "gn:feature_code":"PPL",
    "gn:name":"Cenzhong",
    "gn:population":0,
    "gn:timezone":"Asia/Shanghai",
    "iso:country":"CN",
    "name:zho_x_preferred":[
        "\u5c91\u4e2d"
    ],
    "wof:name":"Cenzhong",
    "wof:placetype":"locality"
},
  "geometry": {"coordinates":[109.04768,27.10988],"type":"Point"}
}