{
  "type": "Feature",
  "properties": {
    "gn:admin1_code":"11.0",
    "gn:asciiname":"Yuantan",
    "gn:country_code":"CN",
    "gn:dem":129,
    "gn:feature_class":"P",
    "gn:feature_code":"PPL",
    "gn:name":"Yuantan",
    "gn:population":0,
    "gn:timezone":"Asia/Shanghai",
    "iso:country":"CN",
    "name:zho_x_preferred":[
        "\u6e0a\u6f6d"
    ],
    "wof:name":"Yuantan",
    "wof:placetype":"locality"
},
  "geometry": {"coordinates":[113.42828,26.61801],"type":"Point"}
}