{
  "type": "Feature",
  "properties": {
    "gn:admin1_code":"18",
    "gn:asciiname":"Houwucun",
    "gn:country_code":"CN",
    "gn:dem":1245,
    "gn:feature_class":"P",
    "gn:feature_code":"PPL",
    "gn:name":"Houwucun",
    "gn:population":0,
    "gn:timezone":"Asia/Shanghai",
    "iso:country":"CN",
    "name:zho_x_preferred":[
        "\u540e\u4e94\u6751"
    ],
    "wof:name":"Houwucun",
    "wof:placetype":"locality"
},
  "geometry": {"coordinates":[106.429,26.5062],"type":"Point"}
}