{
  "type": "Feature",
  "properties": {
    "gn:admin1_code":"4.0",
    "gn:asciiname":"Huangchengdun",
    "gn:country_code":"CN",
    "gn:dem":6,
    "gn:feature_class":"P",
    "gn:feature_code":"PPL",
    "gn:name":"Huangchengdun",
    "gn:population":0,
    "gn:timezone":"Asia/Shanghai",
    "iso:country":"CN",
    "name:zho_x_preferred":[
        "\u9ec4\u57ce\u58a9"
    ],
    "wof:name":"Huangchengdun",
    "wof:placetype":"locality"
},
  "geometry": {"coordinates":[119.91665,31.93874000000001],"type":"Point"}
}