{
  "type": "Feature",
  "properties": {
    "gn:admin1_code":"32.0",
    "gn:asciiname":"Mo'ershan",
    "gn:country_code":"CN",
    "gn:dem":470,
    "gn:feature_class":"P",
    "gn:feature_code":"PPL",
    "gn:name":"Mo\u2019ershan",
    "gn:population":0,
    "gn:timezone":"Asia/Shanghai",
    "iso:country":"CN",
    "name:und_x_variant":[
        "Mo\u2019ershan"
    ],
    "name:zho_x_preferred":[
        "\u78e8\u513f\u5c71"
    ],
    "wof:name":"Mo'ershan",
    "wof:placetype":"locality"
},
  "geometry": {"coordinates":[103.943,29.955],"type":"Point"}
}