{
  "type": "Feature",
  "properties": {
    "gn:admin1_code":"29.0",
    "gn:asciiname":"Daxuanwan",
    "gn:country_code":"CN",
    "gn:dem":1628,
    "gn:feature_class":"P",
    "gn:feature_code":"PPL",
    "gn:name":"Daxuanwan",
    "gn:population":0,
    "gn:timezone":"Asia/Shanghai",
    "iso:country":"CN",
    "name:zho_x_preferred":[
        "\u5927\u65cb\u6e7e"
    ],
    "wof:name":"Daxuanwan",
    "wof:placetype":"locality"
},
  "geometry": {"coordinates":[104.367,26.2216],"type":"Point"}
}