{
  "type": "Feature",
  "properties": {
    "gn:admin1_code":"19",
    "gn:asciiname":"Yangshufang",
    "gn:country_code":"CN",
    "gn:dem":206,
    "gn:feature_class":"P",
    "gn:feature_code":"PPLA4",
    "gn:name":"Yangshufang",
    "gn:population":0,
    "gn:timezone":"Asia/Shanghai",
    "iso:country":"CN",
    "name:und_x_variant":[
        "\u6768\u6811\u623f",
        "Xiaoshipeng Xiang",
        "\u5c0f\u77f3\u68da\u4e61"
    ],
    "wof:name":"Yangshufang",
    "wof:placetype":"locality"
},
  "geometry": {"coordinates":[122.43281,40.24254000000001],"type":"Point"}
}