{
  "type": "Feature",
  "properties": {
    "gn:admin1_code":"15.0",
    "gn:asciiname":"Chuandi",
    "gn:country_code":"CN",
    "gn:dem":1570,
    "gn:feature_class":"P",
    "gn:feature_code":"PPL",
    "gn:name":"Chuandi",
    "gn:population":0,
    "gn:timezone":"Asia/Shanghai",
    "iso:country":"CN",
    "name:zho_x_preferred":[
        "\u5ddd\u5730"
    ],
    "wof:name":"Chuandi",
    "wof:placetype":"locality"
},
  "geometry": {"coordinates":[105.449,34.2992],"type":"Point"}
}