{
  "type": "Feature",
  "properties": {
    "gn:admin1_code":"20",
    "gn:asciiname":"Badai",
    "gn:country_code":"CN",
    "gn:dem":158,
    "gn:feature_class":"P",
    "gn:feature_code":"PPLA4",
    "gn:name":"Badai",
    "gn:population":0,
    "gn:timezone":"Asia/Shanghai",
    "iso:country":"CN",
    "name:und_x_variant":[
        "Badai Xiang"
    ],
    "name:zho_x_preferred":[
        "\u5df4\u5cb1"
    ],
    "name:zho_x_variant":[
        "\u5df4\u5cb1\u4e61"
    ],
    "wof:name":"Badai",
    "wof:placetype":"locality"
},
  "geometry": {"coordinates":[123.16576999999999,46.64468],"type":"Point"}
}