{
  "type": "Feature",
  "properties": {
    "gn:admin1_code":"25",
    "gn:asciiname":"Liangshan Yicun",
    "gn:country_code":"CN",
    "gn:dem":146,
    "gn:feature_class":"P",
    "gn:feature_code":"PPL",
    "gn:name":"Liangshan Yicun",
    "gn:population":0,
    "gn:timezone":"Asia/Shanghai",
    "iso:country":"CN",
    "name:und_x_variant":[
        "\u7cae\u5c71\u4e00\u6751"
    ],
    "wof:name":"Liangshan Yicun",
    "wof:placetype":"locality"
},
  "geometry": {"coordinates":[119.05194,35.38973],"type":"Point"}
}