{
  "type": "Feature",
  "properties": {
    "gn:admin1_code":"19.0",
    "gn:asciiname":"Houdatun",
    "gn:country_code":"CN",
    "gn:dem":74,
    "gn:feature_class":"P",
    "gn:feature_code":"PPL",
    "gn:name":"Houdatun",
    "gn:population":0,
    "gn:timezone":"Asia/Shanghai",
    "iso:country":"CN",
    "name:zho_x_preferred":[
        "\u540e\u5927\u5c6f"
    ],
    "wof:name":"Houdatun",
    "wof:placetype":"locality"
},
  "geometry": {"coordinates":[123.099,42.4824],"type":"Point"}
}