{
  "type": "Feature",
  "properties": {
    "gn:admin1_code":"32.0",
    "gn:asciiname":"Shama",
    "gn:country_code":"CN",
    "gn:dem":4338,
    "gn:feature_class":"P",
    "gn:feature_code":"PPL",
    "gn:name":"Shama",
    "gn:population":0,
    "gn:timezone":"Asia/Shanghai",
    "iso:country":"CN",
    "name:ara_x_preferred":[
        "\u0634\u0627\u0645\u0629"
    ],
    "name:ben_x_preferred":[
        "\u09b6\u09be\u09ae\u09be"
    ],
    "name:ceb_x_preferred":[
        "Shama"
    ],
    "name:deu_x_preferred":[
        "Shama"
    ],
    "name:ell_x_preferred":[
        "\u03a3\u03ac\u03bc\u03b1"
    ],
    "name:fas_x_preferred":[
        "\u0634\u0627\u0645\u0627"
    ],
    "name:fra_x_preferred":[
        "Shama"
    ],
    "name:heb_x_preferred":[
        "\u05e9\u05d0\u05de\u05d4"
    ],
    "name:hin_x_preferred":[
        "\u0936\u092e\u093e"
    ],
    "name:hun_x_preferred":[
        "Shama"
    ],
    "name:ind_x_preferred":[
        "Shama"
    ],
    "name:ita_x_preferred":[
        "Shama"
    ],
    "name:jpn_x_preferred":[
        "\u30b7\u30e3\u30de\u5ddd"
    ],
    "name:kor_x_preferred":[
        "\uc0e4\ub9c8"
    ],
    "name:nld_x_preferred":[
        "Shama"
    ],
    "name:pol_x_preferred":[
        "Shama"
    ],
    "name:por_x_preferred":[
        "Shama"
    ],
    "name:spa_x_preferred":[
        "Shama"
    ],
    "name:swe_x_preferred":[
        "Shama"
    ],
    "name:tur_x_preferred":[
        "Shama"
    ],
    "name:ukr_x_preferred":[
        "\u0428\u0430\u043c\u0430"
    ],
    "name:urd_x_preferred":[
        "\u0634\u0627\u0645\u0627"
    ],
    "name:vie_x_preferred":[
        "S\u00f4ng Shama"
    ],
    "name:zho_cn_x_preferred":[
        "\u838e\u739b\u6cb3"
    ],
    "name:zho_tw_x_preferred":[
        "\u6c99\u746a\u6cb3"
    ],
    "name:zho_x_preferred":[
        "\u6c99\u9a6c"
    ],
    "wof:name":"Shama",
    "wof:placetype":"locality"
},
  "geometry": {"coordinates":[98.01730000000001,32.9391],"type":"Point"}
}