{
  "type": "Feature",
  "properties": {
    "gn:admin1_code":"18.0",
    "gn:asciiname":"Longbatang",
    "gn:country_code":"CN",
    "gn:dem":472,
    "gn:feature_class":"P",
    "gn:feature_code":"PPL",
    "gn:name":"Longbatang",
    "gn:population":0,
    "gn:timezone":"Asia/Shanghai",
    "iso:country":"CN",
    "name:zho_x_preferred":[
        "\u9f99\u6252\u5858"
    ],
    "wof:name":"Longbatang",
    "wof:placetype":"locality"
},
  "geometry": {"coordinates":[108.53100000000001,27.1023],"type":"Point"}
}