{
  "type": "Feature",
  "properties": {
    "gn:admin1_code":"29.0",
    "gn:asciiname":"Bijia",
    "gn:country_code":"CN",
    "gn:dem":2272,
    "gn:feature_class":"P",
    "gn:feature_code":"PPL",
    "gn:name":"Bijia",
    "gn:population":0,
    "gn:timezone":"Asia/Shanghai",
    "iso:country":"CN",
    "name:zho_x_preferred":[
        "\u95ed\u5bb6"
    ],
    "wof:name":"Bijia",
    "wof:placetype":"locality"
},
  "geometry": {"coordinates":[100.304,25.411],"type":"Point"}
}