{
  "type": "Feature",
  "properties": {
    "gn:admin1_code":"11.0",
    "gn:asciiname":"Zongyuanchong",
    "gn:country_code":"CN",
    "gn:dem":75,
    "gn:feature_class":"P",
    "gn:feature_code":"PPL",
    "gn:name":"Zongyuanchong",
    "gn:population":0,
    "gn:timezone":"Asia/Shanghai",
    "iso:country":"CN",
    "name:zho_x_preferred":[
        "\u679e\u5143\u51b2"
    ],
    "wof:name":"Zongyuanchong",
    "wof:placetype":"locality"
},
  "geometry": {"coordinates":[113.31202999999999,28.10222000000001],"type":"Point"}
}