{
  "type": "Feature",
  "properties": {
    "gn:admin1_code":"15.0",
    "gn:asciiname":"Mazhan",
    "gn:country_code":"CN",
    "gn:dem":1161,
    "gn:feature_class":"P",
    "gn:feature_code":"PPL",
    "gn:name":"Mazhan",
    "gn:population":0,
    "gn:timezone":"Asia/Shanghai",
    "iso:country":"CN",
    "name:zho_x_preferred":[
        "\u9a6c\u7ad9"
    ],
    "wof:name":"Mazhan",
    "wof:placetype":"locality"
},
  "geometry": {"coordinates":[107.13500000000001,35.1845],"type":"Point"}
}