{
  "type": "Feature",
  "properties": {
    "gn:admin1_code":"7.0",
    "gn:asciiname":"Qiaotouxi",
    "gn:country_code":"CN",
    "gn:dem":521,
    "gn:feature_class":"P",
    "gn:feature_code":"PPL",
    "gn:name":"Qiaotouxi",
    "gn:population":0,
    "gn:timezone":"Asia/Shanghai",
    "iso:country":"CN",
    "name:zho_x_preferred":[
        "\u6865\u5934\u6eaa"
    ],
    "wof:name":"Qiaotouxi",
    "wof:placetype":"locality"
},
  "geometry": {"coordinates":[117.50645,27.53292],"type":"Point"}
}