{
  "type": "Feature",
  "properties": {
    "gn:admin1_code":"18",
    "gn:asciiname":"Ronglai",
    "gn:country_code":"CN",
    "gn:dem":1357,
    "gn:feature_class":"P",
    "gn:feature_code":"PPL",
    "gn:name":"Ronglai",
    "gn:population":0,
    "gn:timezone":"Asia/Shanghai",
    "iso:country":"CN",
    "name:zho_x_preferred":[
        "\u5197\u8d56"
    ],
    "wof:name":"Ronglai",
    "wof:placetype":"locality"
},
  "geometry": {"coordinates":[106.36199999999999,25.984],"type":"Point"}
}