{
  "type": "Feature",
  "properties": {
    "gn:admin1_code":"02",
    "gn:asciiname":"Shangdiqian",
    "gn:country_code":"CN",
    "gn:dem":41,
    "gn:feature_class":"P",
    "gn:feature_code":"PPL",
    "gn:name":"Shangdiqian",
    "gn:population":0,
    "gn:timezone":"Asia/Shanghai",
    "iso:country":"CN",
    "name:zho_x_preferred":[
        "\u4e0a\u5730\u524d"
    ],
    "wof:name":"Shangdiqian",
    "wof:placetype":"locality"
},
  "geometry": {"coordinates":[121.72018,29.59383],"type":"Point"}
}