{
  "type": "Feature",
  "properties": {
    "gn:admin1_code":"16",
    "gn:asciiname":"Yuankou",
    "gn:country_code":"CN",
    "gn:dem":193,
    "gn:feature_class":"P",
    "gn:feature_code":"PPL",
    "gn:name":"Yuankou",
    "gn:population":0,
    "gn:timezone":"Asia/Shanghai",
    "iso:country":"CN",
    "name:zho_x_preferred":[
        "\u6e90\u53e3"
    ],
    "wof:name":"Yuankou",
    "wof:placetype":"locality"
},
  "geometry": {"coordinates":[111.15900000000001,26.0903],"type":"Point"}
}