{
  "type": "Feature",
  "properties": {
    "gn:admin1_code":"3.0",
    "gn:asciiname":"Yangsi",
    "gn:country_code":"CN",
    "gn:dem":37,
    "gn:feature_class":"P",
    "gn:feature_code":"PPL",
    "gn:name":"Yangsi",
    "gn:population":0,
    "gn:timezone":"Asia/Shanghai",
    "iso:country":"CN",
    "name:und_x_variant":[
        "\u6768\u6cd7"
    ],
    "wof:name":"Yangsi",
    "wof:placetype":"locality"
},
  "geometry": {"coordinates":[116.5013,28.13039],"type":"Point"}
}