{
  "type": "Feature",
  "properties": {
    "gn:admin1_code":"24",
    "gn:asciiname":"Qianya",
    "gn:cc2":"CN",
    "gn:country_code":"CN",
    "gn:dem":685,
    "gn:feature_class":"P",
    "gn:feature_code":"PPL",
    "gn:name":"Qianya",
    "gn:population":0,
    "gn:timezone":"Asia/Shanghai",
    "iso:country":"CN",
    "name:und_x_variant":[
        "Ch\u2019ien-yai",
        "Ch\u2019ien-ya",
        "Qianya"
    ],
    "wof:name":"Qianya",
    "wof:placetype":"locality"
},
  "geometry": {"coordinates":[110.60472,37.40028],"type":"Point"}
}