{
  "type": "Feature",
  "properties": {
    "gn:admin1_code":"16.0",
    "gn:asciiname":"Dongchong",
    "gn:country_code":"CN",
    "gn:dem":215,
    "gn:feature_class":"P",
    "gn:feature_code":"PPL",
    "gn:name":"Dongchong",
    "gn:population":0,
    "gn:timezone":"Asia/Shanghai",
    "iso:country":"CN",
    "name:zho_x_preferred":[
        "\u5cbd\u51b2"
    ],
    "wof:name":"Dongchong",
    "wof:placetype":"locality"
},
  "geometry": {"coordinates":[107.803,22.0533],"type":"Point"}
}