{
  "type": "Feature",
  "properties": {
    "gn:admin1_code":"31.0",
    "gn:asciiname":"Lizhitian",
    "gn:country_code":"CN",
    "gn:dem":74,
    "gn:feature_class":"P",
    "gn:feature_code":"PPL",
    "gn:name":"Lizhitian",
    "gn:population":0,
    "gn:timezone":"Asia/Shanghai",
    "iso:country":"CN",
    "name:zho_x_preferred":[
        "\u8354\u679d\u7530"
    ],
    "wof:name":"Lizhitian",
    "wof:placetype":"locality"
},
  "geometry": {"coordinates":[110.16871999999999,19.1461],"type":"Point"}
}