{
  "type": "Feature",
  "properties": {
    "gn:admin1_code":"18.0",
    "gn:asciiname":"Chonggen",
    "gn:country_code":"CN",
    "gn:dem":795,
    "gn:feature_class":"P",
    "gn:feature_code":"PPL",
    "gn:name":"Chonggen",
    "gn:population":0,
    "gn:timezone":"Asia/Shanghai",
    "iso:country":"CN",
    "name:zho_x_preferred":[
        "\u51b2\u6839"
    ],
    "wof:name":"Chonggen",
    "wof:placetype":"locality"
},
  "geometry": {"coordinates":[109.111,27.0671],"type":"Point"}
}