{
  "type": "Feature",
  "properties": {
    "gn:admin1_code":"16.0",
    "gn:asciiname":"Dahuanghoucun",
    "gn:country_code":"CN",
    "gn:dem":111,
    "gn:feature_class":"P",
    "gn:feature_code":"PPL",
    "gn:name":"Dahuanghoucun",
    "gn:population":0,
    "gn:timezone":"Asia/Shanghai",
    "iso:country":"CN",
    "name:zho_x_preferred":[
        "\u5927\u7687\u540e\u6751"
    ],
    "wof:name":"Dahuanghoucun",
    "wof:placetype":"locality"
},
  "geometry": {"coordinates":[108.239,23.1348],"type":"Point"}
}