{
  "type": "Feature",
  "properties": {
    "gn:admin1_code":"24",
    "gn:asciiname":"Jindian",
    "gn:cc2":"CN",
    "gn:country_code":"CN",
    "gn:dem":431,
    "gn:feature_class":"P",
    "gn:feature_code":"PPL",
    "gn:name":"Jindian",
    "gn:population":0,
    "gn:timezone":"Asia/Shanghai",
    "iso:country":"CN",
    "name:und_x_variant":[
        "Chin-tien-chen",
        "Chin-tien",
        "Jindian"
    ],
    "wof:name":"Jindian",
    "wof:placetype":"locality"
},
  "geometry": {"coordinates":[111.41667,36.05],"type":"Point"}
}