{
  "type": "Feature",
  "properties": {
    "gn:admin1_code":"9.0",
    "gn:asciiname":"Shijiahe",
    "gn:country_code":"CN",
    "gn:dem":101,
    "gn:feature_class":"P",
    "gn:feature_code":"PPL",
    "gn:name":"Shijiahe",
    "gn:population":0,
    "gn:timezone":"Asia/Shanghai",
    "iso:country":"CN",
    "name:zho_x_preferred":[
        "\u5e08\u5bb6\u6cb3"
    ],
    "wof:name":"Shijiahe",
    "wof:placetype":"locality"
},
  "geometry": {"coordinates":[113.55578,34.86404],"type":"Point"}
}