{
  "type": "Feature",
  "properties": {
    "gn:admin1_code":"12.0",
    "gn:asciiname":"Panshuihe",
    "gn:country_code":"CN",
    "gn:dem":1053,
    "gn:feature_class":"P",
    "gn:feature_code":"PPL",
    "gn:name":"Panshuihe",
    "gn:population":0,
    "gn:timezone":"Asia/Shanghai",
    "iso:country":"CN",
    "name:zho_x_preferred":[
        "\u76d8\u6c34\u6cb3"
    ],
    "wof:name":"Panshuihe",
    "wof:placetype":"locality"
},
  "geometry": {"coordinates":[110.61418999999999,31.75096],"type":"Point"}
}