{
  "type": "Feature",
  "properties": {
    "gn:admin1_code":"15.0",
    "gn:asciiname":"Sidian",
    "gn:country_code":"CN",
    "gn:dem":2176,
    "gn:feature_class":"P",
    "gn:feature_code":"PPL",
    "gn:name":"Sidian",
    "gn:population":0,
    "gn:timezone":"Asia/Shanghai",
    "iso:country":"CN",
    "name:und_x_variant":[
        "\u56db\u5e97"
    ],
    "wof:name":"Sidian",
    "wof:placetype":"locality"
},
  "geometry": {"coordinates":[104.39536,34.93412],"type":"Point"}
}