{
  "type": "Feature",
  "properties": {
    "gn:admin1_code":"16",
    "gn:asciiname":"Shangxiangxi",
    "gn:country_code":"CN",
    "gn:dem":480,
    "gn:feature_class":"P",
    "gn:feature_code":"PPL",
    "gn:name":"Shangxiangxi",
    "gn:population":0,
    "gn:timezone":"Asia/Shanghai",
    "iso:country":"CN",
    "name:zho_x_preferred":[
        "\u4e0a\u5411\u6eaa"
    ],
    "wof:name":"Shangxiangxi",
    "wof:placetype":"locality"
},
  "geometry": {"coordinates":[110.65900000000001,26.0078],"type":"Point"}
}