{
  "type": "Feature",
  "properties": {
    "gn:admin1_code":"24.0",
    "gn:asciiname":"Luoquangou",
    "gn:country_code":"CN",
    "gn:dem":1578,
    "gn:feature_class":"P",
    "gn:feature_code":"PPL",
    "gn:name":"Luoquangou",
    "gn:population":0,
    "gn:timezone":"Asia/Shanghai",
    "iso:country":"CN",
    "name:zho_x_preferred":[
        "\u7f57\u5168\u6c9f"
    ],
    "wof:name":"Luoquangou",
    "wof:placetype":"locality"
},
  "geometry": {"coordinates":[113.72557999999999,38.97362],"type":"Point"}
}