{
  "type": "Feature",
  "properties": {
    "gn:admin1_code":"29.0",
    "gn:asciiname":"Riduhuoshi",
    "gn:country_code":"CN",
    "gn:dem":3257,
    "gn:feature_class":"P",
    "gn:feature_code":"PPL",
    "gn:name":"Riduhuoshi",
    "gn:population":0,
    "gn:timezone":"Asia/Shanghai",
    "iso:country":"CN",
    "name:zho_x_preferred":[
        "\u65e5\u90fd\u706b\u77f3"
    ],
    "wof:name":"Riduhuoshi",
    "wof:placetype":"locality"
},
  "geometry": {"coordinates":[101.035,27.1505],"type":"Point"}
}