{
  "type": "Feature",
  "properties": {
    "gn:admin1_code":"29.0",
    "gn:asciiname":"Jinchangba",
    "gn:country_code":"CN",
    "gn:dem":1829,
    "gn:feature_class":"P",
    "gn:feature_code":"PPL",
    "gn:name":"Jinchangba",
    "gn:population":0,
    "gn:timezone":"Asia/Shanghai",
    "iso:country":"CN",
    "name:zho_x_preferred":[
        "\u91d1\u573a\u575d"
    ],
    "wof:name":"Jinchangba",
    "wof:placetype":"locality"
},
  "geometry": {"coordinates":[98.9821,23.9691],"type":"Point"}
}