{
  "type": "Feature",
  "properties": {
    "gn:admin1_code":"7.0",
    "gn:asciiname":"Keshan",
    "gn:country_code":"CN",
    "gn:dem":440,
    "gn:feature_class":"P",
    "gn:feature_code":"PPL",
    "gn:name":"Keshan",
    "gn:population":0,
    "gn:timezone":"Asia/Shanghai",
    "iso:country":"CN",
    "name:deu_x_preferred":[
        "Keshan"
    ],
    "name:zho_x_preferred":[
        "\u53ef\u5c71"
    ],
    "wof:name":"Keshan",
    "wof:placetype":"locality"
},
  "geometry": {"coordinates":[119.04688,25.68935],"type":"Point"}
}