{
  "type": "Feature",
  "properties": {
    "gn:admin1_code":"7.0",
    "gn:asciiname":"Keshan",
    "gn:country_code":"CN",
    "gn:dem":440,
    "gn:feature_class":"P",
    "gn:feature_code":"PPL",
    "gn:name":"Keshan",
    "gn:population":0,
    "gn:timezone":"Asia/Shanghai",
    "iso:country":"CN",
    "name:ara_x_preferred":[
        "\u0643\u064a\u0634\u0627\u0646"
    ],
    "name:ben_x_preferred":[
        "\u0995\u09c7\u09b6\u09be\u09a8"
    ],
    "name:deu_x_preferred":[
        "Keshan"
    ],
    "name:ell_x_preferred":[
        "\u039a\u03ad\u03c3\u03b1\u03bd"
    ],
    "name:eng_x_preferred":[
        "Keshan"
    ],
    "name:fas_x_preferred":[
        "\u06a9\u0634\u0627\u0646"
    ],
    "name:fra_x_preferred":[
        "Keshan"
    ],
    "name:heb_x_preferred":[
        "\u05e7\u05e9\u05d0\u05df"
    ],
    "name:hin_x_preferred":[
        "\u0915\u0947\u0936\u093e\u0928"
    ],
    "name:hun_x_preferred":[
        "Keshan"
    ],
    "name:ind_x_preferred":[
        "Keshan"
    ],
    "name:ita_x_preferred":[
        "Keshan"
    ],
    "name:kor_x_preferred":[
        "\ucf00\uc0b0"
    ],
    "name:nld_x_preferred":[
        "Keshan"
    ],
    "name:pol_x_preferred":[
        "Keshan"
    ],
    "name:por_x_preferred":[
        "Keshan"
    ],
    "name:rus_x_preferred":[
        "\u041a\u044d\u0448\u0430\u043d\u044c"
    ],
    "name:spa_x_preferred":[
        "Keshan"
    ],
    "name:swe_x_preferred":[
        "Keshan"
    ],
    "name:tur_x_preferred":[
        "Keshan"
    ],
    "name:ukr_x_preferred":[
        "\u041a\u0435\u0448\u0430\u043d\u044c"
    ],
    "name:urd_x_preferred":[
        "\u06a9\u06cc\u0634\u0627\u0646"
    ],
    "name:vie_x_preferred":[
        "Kh\u1eafc S\u01a1n"
    ],
    "name:zho_x_preferred":[
        "\u53ef\u5c71"
    ],
    "wof:name":"Keshan",
    "wof:placetype":"locality"
},
  "geometry": {"coordinates":[119.04688,25.68935],"type":"Point"}
}