{
  "type": "Feature",
  "properties": {
    "gn:admin1_code":"30.0",
    "gn:asciiname":"Huangguokeng",
    "gn:country_code":"CN",
    "gn:dem":256,
    "gn:feature_class":"P",
    "gn:feature_code":"PPL",
    "gn:name":"Huangguokeng",
    "gn:population":0,
    "gn:timezone":"Asia/Shanghai",
    "iso:country":"CN",
    "name:zho_x_preferred":[
        "\u9ec4\u679c\u5751"
    ],
    "wof:name":"Huangguokeng",
    "wof:placetype":"locality"
},
  "geometry": {"coordinates":[115.00171,23.70499],"type":"Point"}
}