{
  "type": "Feature",
  "properties": {
    "gn:admin1_code":"26.0",
    "gn:asciiname":"Lujiacun",
    "gn:country_code":"CN",
    "gn:dem":490,
    "gn:feature_class":"P",
    "gn:feature_code":"PPL",
    "gn:name":"L\u00fcjiacun",
    "gn:population":0,
    "gn:timezone":"Asia/Shanghai",
    "iso:country":"CN",
    "name:und_x_variant":[
        "L\u00fcjiacun",
        "\u5415\u5bb6\u6751"
    ],
    "wof:name":"Lujiacun",
    "wof:placetype":"locality"
},
  "geometry": {"coordinates":[107.28749999999999,33.20338],"type":"Point"}
}