{
  "type": "Feature",
  "properties": {
    "gn:admin1_code":"7.0",
    "gn:asciiname":"Waicun",
    "gn:country_code":"CN",
    "gn:dem":685,
    "gn:feature_class":"P",
    "gn:feature_code":"PPL",
    "gn:name":"Waicun",
    "gn:population":0,
    "gn:timezone":"Asia/Shanghai",
    "iso:country":"CN",
    "name:und_x_variant":[
        "\u5916\u6751"
    ],
    "name:zho_x_preferred":[
        "\u5916\u6751"
    ],
    "wof:name":"Waicun",
    "wof:placetype":"locality"
},
  "geometry": {"coordinates":[116.53346999999999,26.68761],"type":"Point"}
}