{
  "type": "Feature",
  "properties": {
    "gn:admin1_code":"5.0",
    "gn:asciiname":"Beifuxingcun",
    "gn:country_code":"CN",
    "gn:dem":365,
    "gn:feature_class":"P",
    "gn:feature_code":"PPL",
    "gn:name":"Beifuxingcun",
    "gn:population":0,
    "gn:timezone":"Asia/Shanghai",
    "iso:country":"CN",
    "name:zho_x_preferred":[
        "\u5317\u798f\u5174\u6751"
    ],
    "wof:name":"Beifuxingcun",
    "wof:placetype":"locality"
},
  "geometry": {"coordinates":[125.43852,42.62463],"type":"Point"}
}