{
  "type": "Feature",
  "properties": {
    "gn:admin1_code":"5.0",
    "gn:asciiname":"Yilongcun",
    "gn:country_code":"CN",
    "gn:dem":347,
    "gn:feature_class":"P",
    "gn:feature_code":"PPL",
    "gn:name":"Yilongcun",
    "gn:population":0,
    "gn:timezone":"Asia/Shanghai",
    "iso:country":"CN",
    "name:zho_x_preferred":[
        "\u4e49\u9686\u6751"
    ],
    "wof:name":"Yilongcun",
    "wof:placetype":"locality"
},
  "geometry": {"coordinates":[126.14337,42.56151],"type":"Point"}
}