{
  "type": "Feature",
  "properties": {
    "gn:admin1_code":"02",
    "gn:asciiname":"Xiamaqian",
    "gn:country_code":"CN",
    "gn:dem":11,
    "gn:feature_class":"P",
    "gn:feature_code":"PPL",
    "gn:name":"Xiamaqian",
    "gn:population":0,
    "gn:timezone":"Asia/Shanghai",
    "iso:country":"CN",
    "name:zho_x_preferred":[
        "\u4e0b\u9a6c\u524d"
    ],
    "wof:name":"Xiamaqian",
    "wof:placetype":"locality"
},
  "geometry": {"coordinates":[120.32644000000001,27.7789],"type":"Point"}
}