{
  "type": "Feature",
  "properties": {
    "gn:admin1_code":"12.0",
    "gn:asciiname":"Shuanggou",
    "gn:country_code":"CN",
    "gn:dem":23,
    "gn:feature_class":"P",
    "gn:feature_code":"PPL",
    "gn:name":"Shuanggou",
    "gn:population":0,
    "gn:timezone":"Asia/Shanghai",
    "iso:country":"CN",
    "name:zho_x_preferred":[
        "Shuanggou"
    ],
    "name:zho_x_variant":[
        "\u53cc\u6c9f"
    ],
    "wof:name":"Shuanggou",
    "wof:placetype":"locality"
},
  "geometry": {"coordinates":[115.29543,30.1341],"type":"Point"}
}