{
  "type": "Feature",
  "properties": {
    "gn:admin1_code":"18",
    "gn:asciiname":"Jiaopao Xiaozhai",
    "gn:country_code":"CN",
    "gn:dem":502,
    "gn:feature_class":"P",
    "gn:feature_code":"PPL",
    "gn:name":"Jiaopao Xiaozhai",
    "gn:population":0,
    "gn:timezone":"Asia/Shanghai",
    "iso:country":"CN",
    "name:zho_x_preferred":[
        "\u768e\u888d\u5c0f\u5be8"
    ],
    "wof:name":"Jiaopao Xiaozhai",
    "wof:placetype":"locality"
},
  "geometry": {"coordinates":[105.801,25.4462],"type":"Point"}
}