{
  "type": "Feature",
  "properties": {
    "gn:admin1_code":"26.0",
    "gn:asciiname":"Liangzhao",
    "gn:country_code":"CN",
    "gn:dem":782,
    "gn:feature_class":"P",
    "gn:feature_code":"PPL",
    "gn:name":"Liangzhao",
    "gn:population":0,
    "gn:timezone":"Asia/Shanghai",
    "iso:country":"CN",
    "name:und_x_variant":[
        "\u6881\u8d75"
    ],
    "wof:name":"Liangzhao",
    "wof:placetype":"locality"
},
  "geometry": {"coordinates":[107.98411000000002,34.52954],"type":"Point"}
}