{
  "type": "Feature",
  "properties": {
    "gn:admin1_code":"5.0",
    "gn:asciiname":"Housishiqicun",
    "gn:country_code":"CN",
    "gn:dem":146,
    "gn:feature_class":"P",
    "gn:feature_code":"PPL",
    "gn:name":"Housishiqicun",
    "gn:population":0,
    "gn:timezone":"Asia/Shanghai",
    "iso:country":"CN",
    "name:zho_x_preferred":[
        "\u540e\u56db\u5341\u4e03\u6751"
    ],
    "wof:name":"Housishiqicun",
    "wof:placetype":"locality"
},
  "geometry": {"coordinates":[123.40996,44.43142],"type":"Point"}
}