{
  "type": "Feature",
  "properties": {
    "gn:admin1_code":"19.0",
    "gn:asciiname":"Guoyuancun",
    "gn:country_code":"CN",
    "gn:dem":38,
    "gn:feature_class":"P",
    "gn:feature_code":"PPL",
    "gn:name":"Guoyuancun",
    "gn:population":0,
    "gn:timezone":"Asia/Shanghai",
    "iso:country":"CN",
    "name:zho_x_preferred":[
        "\u679c\u56ed\u6751"
    ],
    "wof:name":"Guoyuancun",
    "wof:placetype":"locality"
},
  "geometry": {"coordinates":[121.789,41.5233],"type":"Point"}
}