{
  "type": "Feature",
  "properties": {
    "gn:admin1_code":"12.0",
    "gn:asciiname":"Lanni Chongchen",
    "gn:country_code":"CN",
    "gn:dem":60,
    "gn:feature_class":"P",
    "gn:feature_code":"PPL",
    "gn:name":"Lanni Chongchen",
    "gn:population":0,
    "gn:timezone":"Asia/Shanghai",
    "iso:country":"CN",
    "name:zho_x_preferred":[
        "\u6ee5\u6ce5\u51b2\u9648"
    ],
    "wof:name":"Lanni Chongchen",
    "wof:placetype":"locality"
},
  "geometry": {"coordinates":[113.86733,31.20962],"type":"Point"}
}