{
  "type": "Feature",
  "properties": {
    "gn:admin1_code":"3.0",
    "gn:asciiname":"Xishanling",
    "gn:country_code":"CN",
    "gn:dem":144,
    "gn:feature_class":"P",
    "gn:feature_code":"PPL",
    "gn:name":"Xishanling",
    "gn:population":0,
    "gn:timezone":"Asia/Shanghai",
    "iso:country":"CN",
    "name:und_x_variant":[
        "\u897f\u5c71\u5cad"
    ],
    "wof:name":"Xishanling",
    "wof:placetype":"locality"
},
  "geometry": {"coordinates":[114.86754000000001,27.65447],"type":"Point"}
}