{
  "type": "Feature",
  "properties": {
    "gn:admin1_code":"16.0",
    "gn:asciiname":"Lalidong",
    "gn:country_code":"CN",
    "gn:dem":257,
    "gn:feature_class":"P",
    "gn:feature_code":"PPL",
    "gn:name":"Lalidong",
    "gn:population":0,
    "gn:timezone":"Asia/Shanghai",
    "iso:country":"CN",
    "name:zho_x_preferred":[
        "\u62c9\u529b\u5cd2"
    ],
    "wof:name":"Lalidong",
    "wof:placetype":"locality"
},
  "geometry": {"coordinates":[108.11799999999999,24.4339],"type":"Point"}
}