{
  "type": "Feature",
  "properties": {
    "gn:admin1_code":"19.0",
    "gn:asciiname":"Dasonglinggou",
    "gn:country_code":"CN",
    "gn:dem":29,
    "gn:feature_class":"P",
    "gn:feature_code":"PPL",
    "gn:name":"Dasonglinggou",
    "gn:population":0,
    "gn:timezone":"Asia/Shanghai",
    "iso:country":"CN",
    "name:zho_x_preferred":[
        "\u5927\u677e\u5cad\u6c9f"
    ],
    "wof:name":"Dasonglinggou",
    "wof:placetype":"locality"
},
  "geometry": {"coordinates":[119.98917,40.13121],"type":"Point"}
}