{
  "type": "Feature",
  "properties": {
    "gn:admin1_code":"24.0",
    "gn:asciiname":"Xiaheiyu",
    "gn:country_code":"CN",
    "gn:dem":1505,
    "gn:feature_class":"P",
    "gn:feature_code":"PPL",
    "gn:name":"Xiaheiyu",
    "gn:population":0,
    "gn:timezone":"Asia/Shanghai",
    "iso:country":"CN",
    "name:und_x_variant":[
        "\u4e0b\u9ed1\u5cea"
    ],
    "wof:name":"Xiaheiyu",
    "wof:placetype":"locality"
},
  "geometry": {"coordinates":[113.39124,39.44398],"type":"Point"}
}