{
  "type": "Feature",
  "properties": {
    "gn:admin1_code":"32.0",
    "gn:asciiname":"Wenjiang",
    "gn:country_code":"CN",
    "gn:dem":522,
    "gn:feature_class":"P",
    "gn:feature_code":"PPL",
    "gn:name":"Wenjiang",
    "gn:population":0,
    "gn:timezone":"Asia/Shanghai",
    "iso:country":"CN",
    "name:und_x_variant":[
        "Gaoxian",
        "Kao",
        "Kao-hsien",
        "Wenjiang"
    ],
    "name:zho_x_preferred":[
        "\u6587\u6c5f"
    ],
    "wof:name":"Wenjiang",
    "wof:placetype":"locality"
},
  "geometry": {"coordinates":[104.56339,28.38812],"type":"Point"}
}