{
  "type": "Feature",
  "properties": {
    "gn:admin1_code":"29.0",
    "gn:asciiname":"Mangfei",
    "gn:country_code":"CN",
    "gn:dem":983,
    "gn:feature_class":"P",
    "gn:feature_code":"PPL",
    "gn:name":"Mangfei",
    "gn:population":0,
    "gn:timezone":"Asia/Shanghai",
    "iso:country":"CN",
    "name:zho_x_preferred":[
        "\u8292\u8d39"
    ],
    "wof:name":"Mangfei",
    "wof:placetype":"locality"
},
  "geometry": {"coordinates":[100.861,23.2776],"type":"Point"}
}