{
  "type": "Feature",
  "properties": {
    "gn:admin1_code":"9",
    "gn:asciiname":"Tianzhuang",
    "gn:country_code":"CN",
    "gn:dem":58,
    "gn:feature_class":"P",
    "gn:feature_code":"PPL",
    "gn:name":"Tianzhuang",
    "gn:population":0,
    "gn:timezone":"Asia/Shanghai",
    "iso:country":"CN",
    "name:zho_x_preferred":[
        "\u7530\u5e84"
    ],
    "wof:name":"Tianzhuang",
    "wof:placetype":"locality"
},
  "geometry": {"coordinates":[115.01600000000001,34.4661],"type":"Point"}
}