{
  "type": "Feature",
  "properties": {
    "gn:admin1_code":"29",
    "gn:asciiname":"Pingshang",
    "gn:country_code":"CN",
    "gn:dem":1554,
    "gn:feature_class":"P",
    "gn:feature_code":"PPL",
    "gn:name":"Pingshang",
    "gn:population":0,
    "gn:timezone":"Asia/Shanghai",
    "iso:country":"CN",
    "name:zho_x_preferred":[
        "\u576a\u4e0a"
    ],
    "wof:name":"Pingshang",
    "wof:placetype":"locality"
},
  "geometry": {"coordinates":[105.01300000000001,23.4297],"type":"Point"}
}