{
  "type": "Feature",
  "properties": {
    "gn:admin1_code":"29.0",
    "gn:asciiname":"Liwaicun",
    "gn:country_code":"CN",
    "gn:dem":1596,
    "gn:feature_class":"P",
    "gn:feature_code":"PPL",
    "gn:name":"Liwaicun",
    "gn:population":0,
    "gn:timezone":"Asia/Shanghai",
    "iso:country":"CN",
    "name:zho_x_preferred":[
        "\u5229\u5916\u6751"
    ],
    "wof:name":"Liwaicun",
    "wof:placetype":"locality"
},
  "geometry": {"coordinates":[103.22,27.2314],"type":"Point"}
}