{
  "type": "Feature",
  "properties": {
    "gn:admin1_code":"7.0",
    "gn:asciiname":"Damengzai",
    "gn:country_code":"CN",
    "gn:dem":837,
    "gn:feature_class":"P",
    "gn:feature_code":"PPL",
    "gn:name":"Damengzai",
    "gn:population":0,
    "gn:timezone":"Asia/Shanghai",
    "iso:country":"CN",
    "name:zho_x_preferred":[
        "\u5927\u5b5f\u4ed4"
    ],
    "wof:name":"Damengzai",
    "wof:placetype":"locality"
},
  "geometry": {"coordinates":[117.79934,26.31584],"type":"Point"}
}