{
  "type": "Feature",
  "properties": {
    "gn:admin1_code":"3.0",
    "gn:asciiname":"Cunyuan",
    "gn:country_code":"CN",
    "gn:dem":445,
    "gn:feature_class":"P",
    "gn:feature_code":"PPL",
    "gn:name":"Cunyuan",
    "gn:population":0,
    "gn:timezone":"Asia/Shanghai",
    "iso:country":"CN",
    "name:zho_x_preferred":[
        "\u6751\u6c85"
    ],
    "wof:name":"Cunyuan",
    "wof:placetype":"locality"
},
  "geometry": {"coordinates":[117.06234000000001,27.43852],"type":"Point"}
}