{
  "type": "Feature",
  "properties": {
    "gn:admin1_code":"18.0",
    "gn:asciiname":"Potouyang",
    "gn:country_code":"CN",
    "gn:dem":351,
    "gn:feature_class":"P",
    "gn:feature_code":"PPL",
    "gn:name":"Potouyang",
    "gn:population":0,
    "gn:timezone":"Asia/Shanghai",
    "iso:country":"CN",
    "name:zho_x_preferred":[
        "\u5761\u5934\u9633"
    ],
    "wof:name":"Potouyang",
    "wof:placetype":"locality"
},
  "geometry": {"coordinates":[109.44499999999999,27.1014],"type":"Point"}
}