{
  "type": "Feature",
  "properties": {
    "gn:admin1_code":"29",
    "gn:asciiname":"Xiayiwei",
    "gn:country_code":"CN",
    "gn:dem":1704,
    "gn:feature_class":"P",
    "gn:feature_code":"PPL",
    "gn:name":"Xiayiwei",
    "gn:population":0,
    "gn:timezone":"Asia/Shanghai",
    "iso:country":"CN",
    "name:zho_x_preferred":[
        "\u4e0b\u77e3\u7ef4"
    ],
    "wof:name":"Xiayiwei",
    "wof:placetype":"locality"
},
  "geometry": {"coordinates":[103.184,24.3314],"type":"Point"}
}