{
  "type": "Feature",
  "properties": {
    "gn:admin1_code":"23.0",
    "gn:asciiname":"Zhangjiazhai",
    "gn:country_code":"CN",
    "gn:dem":6,
    "gn:feature_class":"P",
    "gn:feature_code":"PPL",
    "gn:name":"Zhangjiazhai",
    "gn:population":0,
    "gn:timezone":"Asia/Shanghai",
    "iso:country":"CN",
    "name:zho_x_preferred":[
        "Zhangjiazhai"
    ],
    "name:zho_x_variant":[
        "\u5f20\u5bb6\u5b85"
    ],
    "wof:name":"Zhangjiazhai",
    "wof:placetype":"locality"
},
  "geometry": {"coordinates":[121.34507000000001,31.05156],"type":"Point"}
}