{
  "type": "Feature",
  "properties": {
    "gn:admin1_code":"13",
    "gn:asciiname":"Suoguluke",
    "gn:country_code":"CN",
    "gn:dem":1319,
    "gn:feature_class":"P",
    "gn:feature_code":"PPL",
    "gn:name":"Suoguluke",
    "gn:population":0,
    "gn:timezone":"Asia/Shanghai",
    "iso:country":"CN",
    "name:und_x_variant":[
        "\u7d22\u53e4\u9c81\u514b"
    ],
    "wof:name":"Suoguluke",
    "wof:placetype":"locality"
},
  "geometry": {"coordinates":[75.88628,39.45118],"type":"Point"}
}