{
  "type": "Feature",
  "properties": {
    "gn:admin1_code":"32.0",
    "gn:asciiname":"Dahuoshan",
    "gn:country_code":"CN",
    "gn:dem":2449,
    "gn:feature_class":"P",
    "gn:feature_code":"PPL",
    "gn:name":"Dahuoshan",
    "gn:population":0,
    "gn:timezone":"Asia/Shanghai",
    "iso:country":"CN",
    "name:zho_x_preferred":[
        "\u5927\u706b\u5c71"
    ],
    "wof:name":"Dahuoshan",
    "wof:placetype":"locality"
},
  "geometry": {"coordinates":[101.673,26.8257],"type":"Point"}
}