{
  "type": "Feature",
  "properties": {
    "gn:admin1_code":"13.0",
    "gn:asciiname":"Sansituanchang",
    "gn:country_code":"CN",
    "gn:dem":847,
    "gn:feature_class":"P",
    "gn:feature_code":"PPLF",
    "gn:name":"Sansituanchang",
    "gn:population":0,
    "gn:timezone":"Asia/Urumqi",
    "iso:country":"CN",
    "name:zho_x_preferred":[
        "\u4e09\u56db\u56e2\u573a"
    ],
    "wof:name":"Sansituanchang",
    "wof:placetype":"locality"
},
  "geometry": {"coordinates":[87.74600000000002,40.60289],"type":"Point"}
}