{
  "type": "Feature",
  "properties": {
    "gn:admin1_code":"15.0",
    "gn:asciiname":"Xiaoshimen",
    "gn:country_code":"CN",
    "gn:dem":2063,
    "gn:feature_class":"P",
    "gn:feature_code":"PPL",
    "gn:name":"Xiaoshimen",
    "gn:population":0,
    "gn:timezone":"Asia/Shanghai",
    "iso:country":"CN",
    "name:und_x_variant":[
        "\u5c0f\u77f3\u95e8"
    ],
    "wof:name":"Xiaoshimen",
    "wof:placetype":"locality"
},
  "geometry": {"coordinates":[104.37002,34.66056],"type":"Point"}
}