{
  "type": "Feature",
  "properties": {
    "gn:admin1_code":"8.0",
    "gn:asciiname":"Songbei",
    "gn:country_code":"CN",
    "gn:dem":269,
    "gn:feature_class":"P",
    "gn:feature_code":"PPL",
    "gn:name":"Songbei",
    "gn:population":0,
    "gn:timezone":"Asia/Shanghai",
    "iso:country":"CN",
    "name:zho_x_preferred":[
        "\u677e\u5317"
    ],
    "wof:name":"Songbei",
    "wof:placetype":"locality"
},
  "geometry": {"coordinates":[128.75117,47.78504],"type":"Point"}
}