{
  "type": "Feature",
  "properties": {
    "gn:admin1_code":"29",
    "gn:asciiname":"Xuedamozu",
    "gn:country_code":"CN",
    "gn:dem":1574,
    "gn:feature_class":"P",
    "gn:feature_code":"PPL",
    "gn:name":"Xuedamozu",
    "gn:population":0,
    "gn:timezone":"Asia/Shanghai",
    "iso:country":"CN",
    "name:zho_x_preferred":[
        "\u96ea\u6253\u83ab\u7956"
    ],
    "wof:name":"Xuedamozu",
    "wof:placetype":"locality"
},
  "geometry": {"coordinates":[101.756,24.1464],"type":"Point"}
}