{
  "type": "Feature",
  "properties": {
    "gn:admin1_code":"9.0",
    "gn:asciiname":"Nanduangou",
    "gn:country_code":"CN",
    "gn:dem":464,
    "gn:feature_class":"P",
    "gn:feature_code":"PPL",
    "gn:name":"Nanduangou",
    "gn:population":0,
    "gn:timezone":"Asia/Shanghai",
    "iso:country":"CN",
    "name:zho_x_preferred":[
        "\u5357\u77ed\u6c9f"
    ],
    "wof:name":"Nanduangou",
    "wof:placetype":"locality"
},
  "geometry": {"coordinates":[113.75978000000001,36.18676],"type":"Point"}
}