{
  "type": "Feature",
  "properties": {
    "gn:admin1_code":"32.0",
    "gn:asciiname":"Deyu",
    "gn:country_code":"CN",
    "gn:dem":2152,
    "gn:feature_class":"P",
    "gn:feature_code":"PPL",
    "gn:name":"Deyu",
    "gn:population":0,
    "gn:timezone":"Asia/Shanghai",
    "iso:country":"CN",
    "name:zho_x_preferred":[
        "\u5fb7\u80b2"
    ],
    "wof:name":"Deyu",
    "wof:placetype":"locality"
},
  "geometry": {"coordinates":[102.419,27.5891],"type":"Point"}
}