{
  "type": "Feature",
  "properties": {
    "gn:admin1_code":"29.0",
    "gn:asciiname":"Kelaowai",
    "gn:country_code":"CN",
    "gn:dem":1799,
    "gn:feature_class":"P",
    "gn:feature_code":"PPL",
    "gn:name":"Kelaowai",
    "gn:population":0,
    "gn:timezone":"Asia/Shanghai",
    "iso:country":"CN",
    "name:zho_x_preferred":[
        "\u514b\u8001\u5916"
    ],
    "wof:name":"Kelaowai",
    "wof:placetype":"locality"
},
  "geometry": {"coordinates":[100.325,24.5333],"type":"Point"}
}