{
  "type": "Feature",
  "properties": {
    "gn:admin1_code":"24.0",
    "gn:asciiname":"Kuanping",
    "gn:country_code":"CN",
    "gn:dem":1494,
    "gn:feature_class":"P",
    "gn:feature_code":"PPL",
    "gn:name":"Kuanping",
    "gn:population":0,
    "gn:timezone":"Asia/Shanghai",
    "iso:country":"CN",
    "name:zho_x_preferred":[
        "\u5bbd\u576a"
    ],
    "wof:name":"Kuanping",
    "wof:placetype":"locality"
},
  "geometry": {"coordinates":[111.65536000000002,37.96896],"type":"Point"}
}