{
  "type": "Feature",
  "properties": {
    "gn:admin1_code":"6.0",
    "gn:asciiname":"Dongriwa",
    "gn:country_code":"CN",
    "gn:dem":3670,
    "gn:feature_class":"P",
    "gn:feature_code":"PPL",
    "gn:name":"Dongriwa",
    "gn:population":0,
    "gn:timezone":"Asia/Urumqi",
    "iso:country":"CN",
    "name:zho_x_preferred":[
        "\u4e1c\u65e5\u54c7"
    ],
    "wof:name":"Dongriwa",
    "wof:placetype":"locality"
},
  "geometry": {"coordinates":[96.51561,32.13468],"type":"Point"}
}