{
  "type": "Feature",
  "properties": {
    "gn:admin1_code":"3",
    "gn:asciiname":"Sili",
    "gn:country_code":"CN",
    "gn:dem":158,
    "gn:feature_class":"P",
    "gn:feature_code":"PPL",
    "gn:name":"Sili",
    "gn:population":0,
    "gn:timezone":"Asia/Shanghai",
    "iso:country":"CN",
    "name:cat_x_preferred":[
        "Sili"
    ],
    "name:ceb_x_preferred":[
        "Sili"
    ],
    "name:swe_x_preferred":[
        "Sili"
    ],
    "name:zho_x_preferred":[
        "\u5bfa\u91cc"
    ],
    "wof:name":"Sili",
    "wof:placetype":"locality"
},
  "geometry": {"coordinates":[114.57999,25.71778],"type":"Point"}
}