{
  "type": "Feature",
  "properties": {
    "gn:admin1_code":"18.0",
    "gn:asciiname":"Shiyang",
    "gn:country_code":"CN",
    "gn:dem":924,
    "gn:feature_class":"P",
    "gn:feature_code":"PPL",
    "gn:name":"Shiyang",
    "gn:population":0,
    "gn:timezone":"Asia/Shanghai",
    "iso:country":"CN",
    "wof:name":"Shiyang",
    "wof:placetype":"locality"
},
  "geometry": {"coordinates":[107.33083000000001,28.06583],"type":"Point"}
}