{
  "type": "Feature",
  "properties": {
    "gn:admin1_code":"14.0",
    "gn:asciiname":"Bangzhongcun",
    "gn:country_code":"CN",
    "gn:dem":2938,
    "gn:feature_class":"P",
    "gn:feature_code":"PPL",
    "gn:name":"Bangzhongcun",
    "gn:population":0,
    "gn:timezone":"Asia/Urumqi",
    "iso:country":"CN",
    "name:zho_x_preferred":[
        "\u5e2e\u4e2d\u6751"
    ],
    "wof:name":"Bangzhongcun",
    "wof:placetype":"locality"
},
  "geometry": {"coordinates":[94.32640000000001,29.29452],"type":"Point"}
}