{
  "type": "Feature",
  "properties": {
    "gn:admin1_code":"2.0",
    "gn:asciiname":"Xiaolin",
    "gn:country_code":"CN",
    "gn:dem":6,
    "gn:feature_class":"P",
    "gn:feature_code":"PPL",
    "gn:name":"Xiaolin",
    "gn:population":0,
    "gn:timezone":"Asia/Shanghai",
    "iso:country":"CN",
    "name:kor_x_preferred":[
        "\uc0e4\uc624\ub9b0"
    ],
    "name:und_x_variant":[
        "\u5c0f\u6797"
    ],
    "wof:name":"Xiaolin",
    "wof:placetype":"locality"
},
  "geometry": {"coordinates":[120.26264999999999,30.4383],"type":"Point"}
}