{
  "type": "Feature",
  "properties": {
    "gn:admin1_code":"25",
    "gn:asciiname":"Dazhaojia",
    "gn:country_code":"CN",
    "gn:dem":8,
    "gn:feature_class":"P",
    "gn:feature_code":"PPL",
    "gn:name":"Dazhaojia",
    "gn:population":0,
    "gn:timezone":"Asia/Shanghai",
    "iso:country":"CN",
    "name:zho_x_preferred":[
        "\u5927\u8d75\u5bb6"
    ],
    "wof:name":"Dazhaojia",
    "wof:placetype":"locality"
},
  "geometry": {"coordinates":[117.63800000000001,37.9722],"type":"Point"}
}