{
  "type": "Feature",
  "properties": {
    "gn:admin1_code":"24.0",
    "gn:asciiname":"Sishimu",
    "gn:country_code":"CN",
    "gn:dem":1617,
    "gn:feature_class":"P",
    "gn:feature_code":"PPL",
    "gn:name":"Sishimu",
    "gn:population":0,
    "gn:timezone":"Asia/Shanghai",
    "iso:country":"CN",
    "name:zho_x_preferred":[
        "\u56db\u5341\u4ea9"
    ],
    "wof:name":"Sishimu",
    "wof:placetype":"locality"
},
  "geometry": {"coordinates":[112.40324,38.94412],"type":"Point"}
}