{
  "type": "Feature",
  "properties": {
    "gn:admin1_code":"32.0",
    "gn:asciiname":"Xinmiaozi",
    "gn:country_code":"CN",
    "gn:dem":694,
    "gn:feature_class":"P",
    "gn:feature_code":"PPL",
    "gn:name":"Xinmiaozi",
    "gn:population":0,
    "gn:timezone":"Asia/Shanghai",
    "iso:country":"CN",
    "name:zho_x_preferred":[
        "\u65b0\u5e99\u5b50"
    ],
    "wof:name":"Xinmiaozi",
    "wof:placetype":"locality"
},
  "geometry": {"coordinates":[107.36499999999999,31.9671],"type":"Point"}
}