{
  "type": "Feature",
  "properties": {
    "gn:admin1_code":"4.0",
    "gn:asciiname":"Qiujiatan",
    "gn:country_code":"CN",
    "gn:dem":9,
    "gn:feature_class":"P",
    "gn:feature_code":"PPL",
    "gn:name":"Qiujiatan",
    "gn:population":0,
    "gn:timezone":"Asia/Shanghai",
    "iso:country":"CN",
    "name:zho_x_preferred":[
        "Qiujiatan"
    ],
    "name:zho_x_variant":[
        "\u90b1\u5bb6\u6ee9"
    ],
    "wof:name":"Qiujiatan",
    "wof:placetype":"locality"
},
  "geometry": {"coordinates":[120.40291999999999,30.91349],"type":"Point"}
}