{
  "type": "Feature",
  "properties": {
    "gn:admin1_code":"18",
    "gn:asciiname":"Luozhai",
    "gn:country_code":"CN",
    "gn:dem":913,
    "gn:feature_class":"P",
    "gn:feature_code":"PPL",
    "gn:name":"Luozhai",
    "gn:population":0,
    "gn:timezone":"Asia/Shanghai",
    "iso:country":"CN",
    "name:zho_x_preferred":[
        "\u7f57\u5be8"
    ],
    "wof:name":"Luozhai",
    "wof:placetype":"locality"
},
  "geometry": {"coordinates":[105.056,26.0909],"type":"Point"}
}