{
  "type": "Feature",
  "properties": {
    "gn:admin1_code":"26.0",
    "gn:asciiname":"Qianzitiao",
    "gn:country_code":"CN",
    "gn:dem":1466,
    "gn:feature_class":"P",
    "gn:feature_code":"PPL",
    "gn:name":"Qianzitiao",
    "gn:population":0,
    "gn:timezone":"Asia/Shanghai",
    "iso:country":"CN",
    "name:zho_x_preferred":[
        "\u7b7e\u5b50\u6761"
    ],
    "wof:name":"Qianzitiao",
    "wof:placetype":"locality"
},
  "geometry": {"coordinates":[109.02106000000001,36.30014],"type":"Point"}
}