{
  "type": "Feature",
  "properties": {
    "gn:admin1_code":"13.0",
    "gn:asciiname":"Kizilawat",
    "gn:cc2":"CN",
    "gn:country_code":"CN",
    "gn:dem":1190,
    "gn:feature_class":"P",
    "gn:feature_code":"PPL",
    "gn:name":"Kizilawat",
    "gn:population":0,
    "gn:timezone":"Asia/Shanghai",
    "iso:country":"CN",
    "name:uig_x_preferred":[
        "K\u0329izil Awat"
    ],
    "name:uig_x_variant":[
        "Qizil Awat",
        "\u0642\u0649\u0632\u0649\u0644 \u0626\u0627\u06cb\u0627\u062a",
        "\u049a\u044b\u0437\u0438\u043b \u0410\u0432\u0430\u0442"
    ],
    "name:und_x_variant":[
        "Hei-tzu-a-wa-t\u2019i",
        "Kizilawat"
    ],
    "wof:name":"Kizilawat",
    "wof:placetype":"locality"
},
  "geometry": {"coordinates":[77.59999999999999,38.65],"type":"Point"}
}