{
  "type": "Feature",
  "properties": {
    "gn:admin1_code":"32.0",
    "gn:asciiname":"Yuexing",
    "gn:country_code":"CN",
    "gn:dem":422,
    "gn:feature_class":"P",
    "gn:feature_code":"PPL",
    "gn:name":"Yuexing",
    "gn:population":0,
    "gn:timezone":"Asia/Shanghai",
    "iso:country":"CN",
    "name:zho_x_preferred":[
        "\u60a6\u5174"
    ],
    "wof:name":"Yuexing",
    "wof:placetype":"locality"
},
  "geometry": {"coordinates":[103.81361,30.11786],"type":"Point"}
}