{
  "type": "Feature",
  "properties": {
    "gn:admin1_code":"20.0",
    "gn:asciiname":"Erhao",
    "gn:country_code":"CN",
    "gn:dem":1453,
    "gn:feature_class":"P",
    "gn:feature_code":"PPL",
    "gn:name":"Erhao",
    "gn:population":0,
    "gn:timezone":"Asia/Shanghai",
    "iso:country":"CN",
    "name:und_x_variant":[
        "\u4e8c\u53f7"
    ],
    "wof:name":"Erhao",
    "wof:placetype":"locality"
},
  "geometry": {"coordinates":[113.66517,41.29255],"type":"Point"}
}