{
  "type": "Feature",
  "properties": {
    "gn:admin1_code":"24.0",
    "gn:asciiname":"Houzhuangwo",
    "gn:country_code":"CN",
    "gn:dem":1569,
    "gn:feature_class":"P",
    "gn:feature_code":"PPL",
    "gn:name":"Houzhuangwo",
    "gn:population":0,
    "gn:timezone":"Asia/Shanghai",
    "iso:country":"CN",
    "name:zho_x_preferred":[
        "\u540e\u5e84\u7a9d"
    ],
    "wof:name":"Houzhuangwo",
    "wof:placetype":"locality"
},
  "geometry": {"coordinates":[111.9286,39.24149],"type":"Point"}
}