{
  "type": "Feature",
  "properties": {
    "gn:admin1_code":"18.0",
    "gn:asciiname":"Kaizhai",
    "gn:country_code":"CN",
    "gn:dem":477,
    "gn:feature_class":"P",
    "gn:feature_code":"PPL",
    "gn:name":"Kaizhai",
    "gn:population":0,
    "gn:timezone":"Asia/Shanghai",
    "iso:country":"CN",
    "name:zho_x_preferred":[
        "\u51ef\u5be8"
    ],
    "wof:name":"Kaizhai",
    "wof:placetype":"locality"
},
  "geometry": {"coordinates":[108.926,26.8282],"type":"Point"}
}