{
  "type": "Feature",
  "properties": {
    "gn:admin1_code":"26.0",
    "gn:asciiname":"Erdaogou",
    "gn:country_code":"CN",
    "gn:dem":1711,
    "gn:feature_class":"P",
    "gn:feature_code":"PPL",
    "gn:name":"Erdaogou",
    "gn:population":0,
    "gn:timezone":"Asia/Shanghai",
    "iso:country":"CN",
    "name:zho_x_preferred":[
        "\u4e8c\u9053\u6c9f"
    ],
    "wof:name":"Erdaogou",
    "wof:placetype":"locality"
},
  "geometry": {"coordinates":[108.57138,37.47467],"type":"Point"}
}