{
  "type": "Feature",
  "properties": {
    "gn:admin1_code":"7",
    "gn:asciiname":"Yuanli",
    "gn:country_code":"CN",
    "gn:dem":578,
    "gn:feature_class":"P",
    "gn:feature_code":"PPL",
    "gn:name":"Yuanli",
    "gn:population":0,
    "gn:timezone":"Asia/Shanghai",
    "iso:country":"CN",
    "name:fra_x_preferred":[
        "Yuanli"
    ],
    "name:hak_x_preferred":[
        "Yen-l\u00ee-ch\u1e73\u0301n"
    ],
    "name:ita_x_preferred":[
        "Yuanli"
    ],
    "name:jpn_x_preferred":[
        "\u82d1\u88e1\u93ae"
    ],
    "name:kor_x_preferred":[
        "\uc704\uc548\ub9ac\uc9c4"
    ],
    "name:vie_x_preferred":[
        "Uy\u1ec3n L\u00fd"
    ],
    "name:zho_x_preferred":[
        "\u9662\u91cc"
    ],
    "name:zho_x_variant":[
        "\u82d1\u88e1\u93ae"
    ],
    "wof:name":"Yuanli",
    "wof:placetype":"locality"
},
  "geometry": {"coordinates":[118.80104,25.66496],"type":"Point"}
}