{
  "type": "Feature",
  "properties": {
    "gn:admin1_code":"29.0",
    "gn:asciiname":"Mianhuadi",
    "gn:country_code":"CN",
    "gn:dem":649,
    "gn:feature_class":"P",
    "gn:feature_code":"PPL",
    "gn:name":"Mianhuadi",
    "gn:population":0,
    "gn:timezone":"Asia/Shanghai",
    "iso:country":"CN",
    "name:zho_x_preferred":[
        "\u68c9\u82b1\u5730"
    ],
    "wof:name":"Mianhuadi",
    "wof:placetype":"locality"
},
  "geometry": {"coordinates":[103.404,22.8973],"type":"Point"}
}