{
  "type": "Feature",
  "properties": {
    "gn:admin1_code":"20",
    "gn:asciiname":"Gurin Ondor",
    "gn:cc2":"CN",
    "gn:country_code":"CN",
    "gn:dem":143,
    "gn:feature_class":"P",
    "gn:feature_code":"PPL",
    "gn:name":"Gurin Ondor",
    "gn:population":0,
    "gn:timezone":"Asia/Shanghai",
    "iso:country":"CN",
    "name:und_x_variant":[
        "Gureondoru",
        "Gurin Ondor"
    ],
    "wof:name":"Gurin Ondor",
    "wof:placetype":"locality"
},
  "geometry": {"coordinates":[123.02722,43.86417],"type":"Point"}
}