{
  "type": "Feature",
  "properties": {
    "gn:admin1_code":"26.0",
    "gn:asciiname":"Lianhuataicun",
    "gn:country_code":"CN",
    "gn:dem":539,
    "gn:feature_class":"P",
    "gn:feature_code":"PPL",
    "gn:name":"Lianhuataicun",
    "gn:population":0,
    "gn:timezone":"Asia/Shanghai",
    "iso:country":"CN",
    "name:zho_x_preferred":[
        "\u83b2\u82b1\u53f0\u6751"
    ],
    "wof:name":"Lianhuataicun",
    "wof:placetype":"locality"
},
  "geometry": {"coordinates":[109.14906999999999,32.34663],"type":"Point"}
}