{
  "type": "Feature",
  "properties": {
    "gn:admin1_code":"20.0",
    "gn:asciiname":"Sailin Hudong",
    "gn:country_code":"CN",
    "gn:dem":1855,
    "gn:feature_class":"P",
    "gn:feature_code":"PPL",
    "gn:name":"Sailin Hudong",
    "gn:population":0,
    "gn:timezone":"Asia/Shanghai",
    "iso:country":"CN",
    "name:und_x_variant":[
        "\u816e\u6797\u5ffd\u6d1e"
    ],
    "wof:name":"Sailin Hudong",
    "wof:placetype":"locality"
},
  "geometry": {"coordinates":[110.60365,41.14937000000001],"type":"Point"}
}