{
  "type": "Feature",
  "properties": {
    "gn:admin1_code":"5.0",
    "gn:asciiname":"Nanniuxin Dingzi",
    "gn:country_code":"CN",
    "gn:dem":306,
    "gn:feature_class":"P",
    "gn:feature_code":"PPL",
    "gn:name":"Nanniuxin Dingzi",
    "gn:population":0,
    "gn:timezone":"Asia/Shanghai",
    "iso:country":"CN",
    "name:zho_x_preferred":[
        "\u5357\u725b\u5fc3\u9876\u5b50"
    ],
    "wof:name":"Nanniuxin Dingzi",
    "wof:placetype":"locality"
},
  "geometry": {"coordinates":[126.13996000000002,42.85874],"type":"Point"}
}