{
  "type": "Feature",
  "properties": {
    "gn:admin1_code":"8.0",
    "gn:asciiname":"Jixing",
    "gn:country_code":"CN",
    "gn:dem":150,
    "gn:feature_class":"P",
    "gn:feature_code":"PPLA4",
    "gn:name":"Jixing",
    "gn:population":0,
    "gn:timezone":"Asia/Shanghai",
    "iso:country":"CN",
    "name:und_x_variant":[
        "Jixing Xiang"
    ],
    "name:zho_x_preferred":[
        "\u5409\u5174"
    ],
    "name:zho_x_variant":[
        "\u5409\u5174\u4e61"
    ],
    "wof:name":"Jixing",
    "wof:placetype":"locality"
},
  "geometry": {"coordinates":[130.42911999999998,45.99383],"type":"Point"}
}