{
  "type": "Feature",
  "properties": {
    "gn:admin1_code":"18",
    "gn:asciiname":"Wengbu Liucun",
    "gn:country_code":"CN",
    "gn:dem":806,
    "gn:feature_class":"P",
    "gn:feature_code":"PPL",
    "gn:name":"Wengbu Liucun",
    "gn:population":0,
    "gn:timezone":"Asia/Shanghai",
    "iso:country":"CN",
    "name:zho_x_preferred":[
        "\u7fc1\u4e0d\u516d\u6751"
    ],
    "wof:name":"Wengbu Liucun",
    "wof:placetype":"locality"
},
  "geometry": {"coordinates":[106.72499999999999,25.5783],"type":"Point"}
}