{
  "type": "Feature",
  "properties": {
    "gn:admin1_code":"03",
    "gn:asciiname":"Guancangwei",
    "gn:country_code":"CN",
    "gn:dem":246,
    "gn:feature_class":"P",
    "gn:feature_code":"PPL",
    "gn:name":"Guancangwei",
    "gn:population":0,
    "gn:timezone":"Asia/Shanghai",
    "iso:country":"CN",
    "name:und_x_variant":[
        "\u5b98\u4ed3\u5729"
    ],
    "wof:name":"Guancangwei",
    "wof:placetype":"locality"
},
  "geometry": {"coordinates":[115.93635,26.00713],"type":"Point"}
}