{
  "type": "Feature",
  "properties": {
    "gn:admin1_code":"26.0",
    "gn:asciiname":"Hualinyuan",
    "gn:country_code":"CN",
    "gn:dem":1473,
    "gn:feature_class":"P",
    "gn:feature_code":"PPL",
    "gn:name":"Hualinyuan",
    "gn:population":0,
    "gn:timezone":"Asia/Shanghai",
    "iso:country":"CN",
    "name:zho_x_preferred":[
        "\u5316\u6797\u56ed"
    ],
    "wof:name":"Hualinyuan",
    "wof:placetype":"locality"
},
  "geometry": {"coordinates":[106.48175999999999,34.65107],"type":"Point"}
}