{
  "type": "Feature",
  "properties": {
    "gn:admin1_code":"29",
    "gn:asciiname":"Lidi",
    "gn:country_code":"CN",
    "gn:dem":1330,
    "gn:feature_class":"P",
    "gn:feature_code":"PPL",
    "gn:name":"Lidi",
    "gn:population":0,
    "gn:timezone":"Asia/Shanghai",
    "iso:country":"CN",
    "name:zho_x_preferred":[
        "\u7406\u5730"
    ],
    "wof:name":"Lidi",
    "wof:placetype":"locality"
},
  "geometry": {"coordinates":[105.51900000000001,23.5312],"type":"Point"}
}