{
  "type": "Feature",
  "properties": {
    "gn:admin1_code":"16.0",
    "gn:asciiname":"Huangmaotian",
    "gn:country_code":"CN",
    "gn:dem":42,
    "gn:feature_class":"P",
    "gn:feature_code":"PPL",
    "gn:name":"Huangmaotian",
    "gn:population":0,
    "gn:timezone":"Asia/Shanghai",
    "iso:country":"CN",
    "name:zho_x_preferred":[
        "\u9ec4\u8305\u7530"
    ],
    "wof:name":"Huangmaotian",
    "wof:placetype":"locality"
},
  "geometry": {"coordinates":[108.96899999999999,22.1258],"type":"Point"}
}