{
  "type": "Feature",
  "properties": {
    "gn:admin1_code":"15.0",
    "gn:asciiname":"Huoshaocheng",
    "gn:country_code":"CN",
    "gn:dem":2664,
    "gn:feature_class":"P",
    "gn:feature_code":"PPL",
    "gn:name":"Huoshaocheng",
    "gn:population":0,
    "gn:timezone":"Asia/Shanghai",
    "iso:country":"CN",
    "name:zho_x_preferred":[
        "\u706b\u70e7\u57ce"
    ],
    "wof:name":"Huoshaocheng",
    "wof:placetype":"locality"
},
  "geometry": {"coordinates":[102.996,37.057],"type":"Point"}
}