{
  "type": "Feature",
  "properties": {
    "gn:admin1_code":"30.0",
    "gn:asciiname":"Dapuliaocun",
    "gn:country_code":"CN",
    "gn:dem":28,
    "gn:feature_class":"P",
    "gn:feature_code":"PPL",
    "gn:name":"Dapuliaocun",
    "gn:population":0,
    "gn:timezone":"Asia/Shanghai",
    "iso:country":"CN",
    "name:zho_x_preferred":[
        "\u5927\u57d4\u5bee\u6751"
    ],
    "wof:name":"Dapuliaocun",
    "wof:placetype":"locality"
},
  "geometry": {"coordinates":[116.26295,23.35884],"type":"Point"}
}