{
  "type": "Feature",
  "properties": {
    "gn:admin1_code":"16.0",
    "gn:asciiname":"Gaoliang",
    "gn:country_code":"CN",
    "gn:dem":1070,
    "gn:feature_class":"P",
    "gn:feature_code":"PPL",
    "gn:name":"Gaoliang",
    "gn:population":0,
    "gn:timezone":"Asia/Shanghai",
    "iso:country":"CN",
    "name:zho_x_preferred":[
        "\u9ad8\u826f"
    ],
    "wof:name":"Gaoliang",
    "wof:placetype":"locality"
},
  "geometry": {"coordinates":[104.785,24.5056],"type":"Point"}
}