{
  "type": "Feature",
  "properties": {
    "gn:admin1_code":"9",
    "gn:asciiname":"Fengtikou",
    "gn:country_code":"CN",
    "gn:dem":51,
    "gn:feature_class":"P",
    "gn:feature_code":"PPL",
    "gn:name":"Fengtikou",
    "gn:population":0,
    "gn:timezone":"Asia/Shanghai",
    "iso:country":"CN",
    "name:zho_x_preferred":[
        "\u51af\u63d0\u53e3"
    ],
    "wof:name":"Fengtikou",
    "wof:placetype":"locality"
},
  "geometry": {"coordinates":[115.42794000000001,35.71517],"type":"Point"}
}