{
  "type": "Feature",
  "properties": {
    "gn:admin1_code":"9.0",
    "gn:asciiname":"Jinghekou",
    "gn:country_code":"CN",
    "gn:dem":484,
    "gn:feature_class":"P",
    "gn:feature_code":"PPL",
    "gn:name":"Jinghekou",
    "gn:population":0,
    "gn:timezone":"Asia/Shanghai",
    "iso:country":"CN",
    "name:und_x_variant":[
        "\u4e95\u6cb3\u53e3",
        "Jinghekou"
    ],
    "wof:name":"Jinghekou",
    "wof:placetype":"locality"
},
  "geometry": {"coordinates":[112.53394,33.92772],"type":"Point"}
}