{
  "type": "Feature",
  "properties": {
    "gn:admin1_code":"9",
    "gn:asciiname":"Xitiegang",
    "gn:country_code":"CN",
    "gn:dem":64,
    "gn:feature_class":"P",
    "gn:feature_code":"PPL",
    "gn:name":"Xitiegang",
    "gn:population":0,
    "gn:timezone":"Asia/Shanghai",
    "iso:country":"CN",
    "name:zho_x_preferred":[
        "\u897f\u94c1\u5c97"
    ],
    "wof:name":"Xitiegang",
    "wof:placetype":"locality"
},
  "geometry": {"coordinates":[114.807,34.6659],"type":"Point"}
}