{
  "type": "Feature",
  "properties": {
    "gn:admin1_code":"32.0",
    "gn:asciiname":"Bangjuntian",
    "gn:country_code":"CN",
    "gn:dem":353,
    "gn:feature_class":"P",
    "gn:feature_code":"PPL",
    "gn:name":"Bangjuntian",
    "gn:population":0,
    "gn:timezone":"Asia/Shanghai",
    "iso:country":"CN",
    "name:zho_x_preferred":[
        "\u5e2e\u541b\u7530"
    ],
    "wof:name":"Bangjuntian",
    "wof:placetype":"locality"
},
  "geometry": {"coordinates":[105.506,28.8043],"type":"Point"}
}