{
  "type": "Feature",
  "properties": {
    "gn:admin1_code":"18",
    "gn:asciiname":"Tongsun",
    "gn:country_code":"CN",
    "gn:dem":1351,
    "gn:feature_class":"P",
    "gn:feature_code":"PPL",
    "gn:name":"Tongsun",
    "gn:population":0,
    "gn:timezone":"Asia/Shanghai",
    "iso:country":"CN",
    "name:zho_x_preferred":[
        "\u7b52\u7b0b"
    ],
    "wof:name":"Tongsun",
    "wof:placetype":"locality"
},
  "geometry": {"coordinates":[106.384,26.0069],"type":"Point"}
}