{
  "type": "Feature",
  "properties": {
    "gn:admin1_code":"19.0",
    "gn:asciiname":"Gangouzi",
    "gn:country_code":"CN",
    "gn:dem":488,
    "gn:feature_class":"P",
    "gn:feature_code":"PPL",
    "gn:name":"Gangouzi",
    "gn:population":0,
    "gn:timezone":"Asia/Shanghai",
    "iso:country":"CN",
    "name:zho_x_preferred":[
        "\u5e72\u6c9f\u5b50"
    ],
    "wof:name":"Gangouzi",
    "wof:placetype":"locality"
},
  "geometry": {"coordinates":[119.03413,40.97415],"type":"Point"}
}