{
  "type": "Feature",
  "properties": {
    "gn:admin1_code":"26.0",
    "gn:asciiname":"Chunshuwan",
    "gn:country_code":"CN",
    "gn:dem":705,
    "gn:feature_class":"P",
    "gn:feature_code":"PPL",
    "gn:name":"Chunshuwan",
    "gn:population":0,
    "gn:timezone":"Asia/Shanghai",
    "iso:country":"CN",
    "name:zho_x_preferred":[
        "\u693f\u6811\u6e7e"
    ],
    "wof:name":"Chunshuwan",
    "wof:placetype":"locality"
},
  "geometry": {"coordinates":[108.16953999999998,33.20455],"type":"Point"}
}