{
  "type": "Feature",
  "properties": {
    "gn:admin1_code":"19",
    "gn:asciiname":"Loufang",
    "gn:cc2":"CN",
    "gn:country_code":"CN",
    "gn:dem":53,
    "gn:feature_class":"P",
    "gn:feature_code":"PPL",
    "gn:name":"Loufang",
    "gn:population":0,
    "gn:timezone":"Asia/Shanghai",
    "iso:country":"CN",
    "name:und_x_variant":[
        "Daloufang",
        "Loufang Xiang",
        "Loufang"
    ],
    "wof:name":"Loufang",
    "wof:placetype":"locality"
},
  "geometry": {"coordinates":[124.39417,40.2175],"type":"Point"}
}