{
  "type": "Feature",
  "properties": {
    "gn:admin1_code":"26.0",
    "gn:asciiname":"Dongyuexiang",
    "gn:country_code":"CN",
    "gn:dem":1002,
    "gn:feature_class":"P",
    "gn:feature_code":"PPL",
    "gn:name":"Dongyuexiang",
    "gn:population":0,
    "gn:timezone":"Asia/Shanghai",
    "iso:country":"CN",
    "name:zho_x_preferred":[
        "\u4e1c\u5cb3\u4e61"
    ],
    "wof:name":"Dongyuexiang",
    "wof:placetype":"locality"
},
  "geometry": {"coordinates":[109.35742,34.33521],"type":"Point"}
}