{
  "type": "Feature",
  "properties": {
    "gn:admin1_code":"32",
    "gn:asciiname":"Enyang",
    "gn:country_code":"CN",
    "gn:dem":367,
    "gn:feature_class":"P",
    "gn:feature_code":"PPL",
    "gn:name":"Enyang",
    "gn:population":0,
    "gn:timezone":"Asia/Shanghai",
    "iso:country":"CN",
    "name:und_x_variant":[
        "En-yang-ho",
        "Enyangzhen",
        "Enyang"
    ],
    "name:zho_x_preferred":[
        "En\u2019yankhe"
    ],
    "name:zho_x_variant":[
        "\u6069\u9633"
    ],
    "wof:name":"Enyang",
    "wof:placetype":"locality"
},
  "geometry": {"coordinates":[106.62707,31.79397],"type":"Point"}
}