{
  "type": "Feature",
  "properties": {
    "gn:admin1_code":"32",
    "gn:asciiname":"Enyang",
    "gn:country_code":"CN",
    "gn:dem":367,
    "gn:feature_class":"P",
    "gn:feature_code":"PPL",
    "gn:name":"Enyang",
    "gn:population":0,
    "gn:timezone":"Asia/Shanghai",
    "iso:country":"CN",
    "name:deu_x_preferred":[
        "Enyang"
    ],
    "name:ell_x_preferred":[
        "\u0395\u03c0\u03b1\u03c1\u03c7\u03af\u03b1 \u0395\u03bd\u03b3\u03b9\u03ac\u03bd\u03b3\u03ba"
    ],
    "name:jpn_x_preferred":[
        "\u6069\u967d\u533a"
    ],
    "name:kor_x_preferred":[
        "\uc5b8\uc591\uad6c"
    ],
    "name:rus_x_preferred":[
        "\u042d\u043d\u044c\u044f\u043d"
    ],
    "name:swe_x_preferred":[
        "Enyang"
    ],
    "name:und_x_variant":[
        "En-yang-ho",
        "Enyangzhen"
    ],
    "name:urd_x_preferred":[
        "\u0639\u0646\u06cc\u0627\u0646\u06af \u0636\u0644\u0639"
    ],
    "name:vie_x_preferred":[
        "\u00c2n D\u01b0\u01a1ng"
    ],
    "name:zho_x_preferred":[
        "En\u2019yankhe"
    ],
    "name:zho_x_variant":[
        "\u6069\u9633",
        "\u6069\u9633\u533a"
    ],
    "wof:name":"Enyang",
    "wof:placetype":"locality"
},
  "geometry": {"coordinates":[106.62707,31.79397],"type":"Point"}
}