{
  "type": "Feature",
  "properties": {
    "gn:admin1_code":"25",
    "gn:asciiname":"Shenjiawan",
    "gn:country_code":"CN",
    "gn:dem":24,
    "gn:feature_class":"P",
    "gn:feature_code":"PPL",
    "gn:name":"Shenjiawan",
    "gn:population":0,
    "gn:timezone":"Asia/Shanghai",
    "iso:country":"CN",
    "name:zho_x_preferred":[
        "\u7533\u5bb6\u6e7e"
    ],
    "wof:name":"Shenjiawan",
    "wof:placetype":"locality"
},
  "geometry": {"coordinates":[116.59099999999999,37.4567],"type":"Point"}
}