{
  "type": "Feature",
  "properties": {
    "gn:admin1_code":"8.0",
    "gn:asciiname":"Yakeqiao",
    "gn:country_code":"CN",
    "gn:dem":74,
    "gn:feature_class":"P",
    "gn:feature_code":"PPL",
    "gn:name":"Yakeqiao",
    "gn:population":0,
    "gn:timezone":"Asia/Shanghai",
    "iso:country":"CN",
    "name:zho_x_preferred":[
        "\u7259\u514b\u6865"
    ],
    "wof:name":"Yakeqiao",
    "wof:placetype":"locality"
},
  "geometry": {"coordinates":[133.33309,46.84965],"type":"Point"}
}