{
  "type": "Feature",
  "properties": {
    "gn:admin1_code":"2.0",
    "gn:asciiname":"Bichuan Sancun",
    "gn:country_code":"CN",
    "gn:dem":148,
    "gn:feature_class":"P",
    "gn:feature_code":"PPL",
    "gn:name":"Bichuan Sancun",
    "gn:population":0,
    "gn:timezone":"Asia/Shanghai",
    "iso:country":"CN",
    "name:zho_x_preferred":[
        "\u78a7\u5ddd\u4e09\u6751"
    ],
    "wof:name":"Bichuan Sancun",
    "wof:placetype":"locality"
},
  "geometry": {"coordinates":[120.09107,28.7355],"type":"Point"}
}