{
  "type": "Feature",
  "properties": {
    "gn:admin1_code":"29.0",
    "gn:asciiname":"Kuxianping",
    "gn:country_code":"CN",
    "gn:dem":2306,
    "gn:feature_class":"P",
    "gn:feature_code":"PPL",
    "gn:name":"Kuxianping",
    "gn:population":0,
    "gn:timezone":"Asia/Shanghai",
    "iso:country":"CN",
    "name:zho_x_preferred":[
        "\u82e6\u4ed9\u576a"
    ],
    "wof:name":"Kuxianping",
    "wof:placetype":"locality"
},
  "geometry": {"coordinates":[100.55200000000001,27.3389],"type":"Point"}
}