{
  "type": "Feature",
  "properties": {
    "gn:admin1_code":"30.0",
    "gn:asciiname":"Aiguo",
    "gn:country_code":"CN",
    "gn:dem":7,
    "gn:feature_class":"P",
    "gn:feature_code":"PPL",
    "gn:name":"Aiguo",
    "gn:population":0,
    "gn:timezone":"Asia/Shanghai",
    "iso:country":"CN",
    "name:zho_x_preferred":[
        "\u611b\u570b"
    ],
    "wof:name":"Aiguo",
    "wof:placetype":"locality"
},
  "geometry": {"coordinates":[112.95677999999999,22.94612],"type":"Point"}
}