{
  "type": "Feature",
  "properties": {
    "gn:admin1_code":"20",
    "gn:asciiname":"Chao-pu-ying-tzu",
    "gn:country_code":"CN",
    "gn:dem":450,
    "gn:feature_class":"P",
    "gn:feature_code":"PPL",
    "gn:name":"Chao-pu-ying-tzu",
    "gn:population":0,
    "gn:timezone":"Asia/Shanghai",
    "iso:country":"CN",
    "wof:name":"Chao-pu-ying-tzu",
    "wof:placetype":"locality"
},
  "geometry": {"coordinates":[119.51611,42.42778],"type":"Point"}
}