{
  "type": "Feature",
  "properties": {
    "gn:admin1_code":"30",
    "gn:asciiname":"Longwei",
    "gn:country_code":"CN",
    "gn:dem":23,
    "gn:feature_class":"P",
    "gn:feature_code":"PPLA4",
    "gn:name":"Longwei",
    "gn:population":0,
    "gn:timezone":"Asia/Shanghai",
    "iso:country":"CN",
    "name:und_x_variant":[
        "\u9f99\u5c3e",
        "Longwei Zhen",
        "\u9f99\u5c3e\u9547"
    ],
    "wof:name":"Longwei",
    "wof:placetype":"locality"
},
  "geometry": {"coordinates":[116.14733,23.57554],"type":"Point"}
}