{
  "type": "Feature",
  "properties": {
    "gn:admin1_code":"10",
    "gn:asciiname":"Habiga",
    "gn:country_code":"CN",
    "gn:dem":1403,
    "gn:feature_class":"P",
    "gn:feature_code":"PPL",
    "gn:name":"Habiga",
    "gn:population":0,
    "gn:timezone":"Asia/Shanghai",
    "iso:country":"CN",
    "wof:name":"Habiga",
    "wof:placetype":"locality"
},
  "geometry": {"coordinates":[114.78055999999999,41.55139000000001],"type":"Point"}
}