{
  "type": "Feature",
  "properties": {
    "gn:admin1_code":"8.0",
    "gn:asciiname":"Hepingcun",
    "gn:country_code":"CN",
    "gn:dem":127,
    "gn:feature_class":"P",
    "gn:feature_code":"PPL",
    "gn:name":"Hepingcun",
    "gn:population":0,
    "gn:timezone":"Asia/Shanghai",
    "iso:country":"CN",
    "name:zho_x_preferred":[
        "\u548c\u5e73\u6751"
    ],
    "wof:name":"Hepingcun",
    "wof:placetype":"locality"
},
  "geometry": {"coordinates":[126.33476,45.66126],"type":"Point"}
}