{
  "type": "Feature",
  "properties": {
    "gn:admin1_code":"19.0",
    "gn:asciiname":"Tuanjiedui",
    "gn:country_code":"CN",
    "gn:dem":2,
    "gn:feature_class":"P",
    "gn:feature_code":"PPLF",
    "gn:name":"Tuanjiedui",
    "gn:population":0,
    "gn:timezone":"Asia/Shanghai",
    "iso:country":"CN",
    "name:zho_x_preferred":[
        "\u56e2\u7ed3\u961f"
    ],
    "wof:name":"Tuanjiedui",
    "wof:placetype":"locality"
},
  "geometry": {"coordinates":[121.73099999999999,41.2814],"type":"Point"}
}