{
  "type": "Feature",
  "properties": {
    "gn:admin1_code":"14.0",
    "gn:asciiname":"Xoiba",
    "gn:country_code":"CN",
    "gn:dem":4893,
    "gn:feature_class":"P",
    "gn:feature_code":"PPL",
    "gn:name":"Xoiba",
    "gn:population":0,
    "gn:timezone":"Asia/Urumqi",
    "iso:country":"CN",
    "name:bod_x_preferred":[
        "Xoiba"
    ],
    "name:zho_x_preferred":[
        "Xueba"
    ],
    "name:zho_x_variant":[
        "\u96ea\u5df4"
    ],
    "wof:name":"Xoiba",
    "wof:placetype":"locality"
},
  "geometry": {"coordinates":[94.602,30.902],"type":"Point"}
}