{
  "type": "Feature",
  "properties": {
    "gn:admin1_code":"18",
    "gn:asciiname":"Donggen",
    "gn:country_code":"CN",
    "gn:dem":974,
    "gn:feature_class":"P",
    "gn:feature_code":"PPL",
    "gn:name":"Donggen",
    "gn:population":0,
    "gn:timezone":"Asia/Shanghai",
    "iso:country":"CN",
    "name:zho_x_preferred":[
        "\u8463\u6839"
    ],
    "wof:name":"Donggen",
    "wof:placetype":"locality"
},
  "geometry": {"coordinates":[106.63500000000001,25.7071],"type":"Point"}
}