{
  "type": "Feature",
  "properties": {
    "gn:admin1_code":"32.0",
    "gn:asciiname":"Yuanzuishang",
    "gn:country_code":"CN",
    "gn:dem":975,
    "gn:feature_class":"P",
    "gn:feature_code":"PPL",
    "gn:name":"Yuanzuishang",
    "gn:population":0,
    "gn:timezone":"Asia/Shanghai",
    "iso:country":"CN",
    "name:zho_x_preferred":[
        "\u56ed\u5480\u4e0a"
    ],
    "wof:name":"Yuanzuishang",
    "wof:placetype":"locality"
},
  "geometry": {"coordinates":[105.31664000000001,32.5562],"type":"Point"}
}