{
  "type": "Feature",
  "properties": {
    "gn:admin1_code":"3.0",
    "gn:asciiname":"Quanjiaqiao",
    "gn:country_code":"CN",
    "gn:dem":81,
    "gn:feature_class":"P",
    "gn:feature_code":"PPL",
    "gn:name":"Quanjiaqiao",
    "gn:population":0,
    "gn:timezone":"Asia/Shanghai",
    "iso:country":"CN",
    "name:und_x_variant":[
        "\u6cc9\u5bb6\u6865"
    ],
    "wof:name":"Quanjiaqiao",
    "wof:placetype":"locality"
},
  "geometry": {"coordinates":[115.31348,29.2251],"type":"Point"}
}