{
  "type": "Feature",
  "properties": {
    "gn:admin1_code":"9.0",
    "gn:asciiname":"Hongcunsi",
    "gn:country_code":"CN",
    "gn:dem":102,
    "gn:feature_class":"P",
    "gn:feature_code":"PPL",
    "gn:name":"Hongcunsi",
    "gn:population":0,
    "gn:timezone":"Asia/Shanghai",
    "iso:country":"CN",
    "name:zho_x_preferred":[
        "\u6d2a\u6751\u5bfa"
    ],
    "wof:name":"Hongcunsi",
    "wof:placetype":"locality"
},
  "geometry": {"coordinates":[113.58613,34.01223],"type":"Point"}
}