{
  "type": "Feature",
  "properties": {
    "gn:admin1_code":"16",
    "gn:asciiname":"Tuokan",
    "gn:country_code":"CN",
    "gn:dem":440,
    "gn:feature_class":"P",
    "gn:feature_code":"PPL",
    "gn:name":"Tuokan",
    "gn:population":0,
    "gn:timezone":"Asia/Shanghai",
    "iso:country":"CN",
    "wof:name":"Tuokan",
    "wof:placetype":"locality"
},
  "geometry": {"coordinates":[107.25,23.16667],"type":"Point"}
}