{
  "type": "Feature",
  "properties": {
    "gn:admin1_code":"05",
    "gn:asciiname":"Longquan",
    "gn:country_code":"CN",
    "gn:dem":598,
    "gn:feature_class":"P",
    "gn:feature_code":"PPL",
    "gn:name":"Longquan",
    "gn:population":0,
    "gn:timezone":"Asia/Shanghai",
    "iso:country":"CN",
    "wof:name":"Longquan",
    "wof:placetype":"locality"
},
  "geometry": {"coordinates":[126.6125,42.43167],"type":"Point"}
}