{
  "type": "Feature",
  "properties": {
    "gn:admin1_code":"5.0",
    "gn:asciiname":"Dongchaoyanggou",
    "gn:country_code":"CN",
    "gn:dem":192,
    "gn:feature_class":"P",
    "gn:feature_code":"PPL",
    "gn:name":"Dongchaoyanggou",
    "gn:population":0,
    "gn:timezone":"Asia/Shanghai",
    "iso:country":"CN",
    "name:zho_x_preferred":[
        "\u4e1c\u671d\u9633\u6c9f"
    ],
    "wof:name":"Dongchaoyanggou",
    "wof:placetype":"locality"
},
  "geometry": {"coordinates":[126.92457,44.91754],"type":"Point"}
}