{
  "type": "Feature",
  "properties": {
    "gn:admin1_code":"24",
    "gn:asciiname":"Dananping",
    "gn:country_code":"CN",
    "gn:dem":1348,
    "gn:feature_class":"P",
    "gn:feature_code":"PPL",
    "gn:name":"Dananping",
    "gn:population":0,
    "gn:timezone":"Asia/Shanghai",
    "iso:country":"CN",
    "name:und_x_variant":[
        "Ta-nan-p\u2019ing",
        "Dananping"
    ],
    "name:zho_x_preferred":[
        "\u5927\u5357\u576a"
    ],
    "wof:name":"Dananping",
    "wof:placetype":"locality"
},
  "geometry": {"coordinates":[112.27118,37.96449000000001],"type":"Point"}
}