{
  "type": "Feature",
  "properties": {
    "gn:admin1_code":"4.0",
    "gn:asciiname":"Fengchencun",
    "gn:country_code":"CN",
    "gn:dem":5,
    "gn:feature_class":"P",
    "gn:feature_code":"PPL",
    "gn:name":"Fengchencun",
    "gn:population":0,
    "gn:timezone":"Asia/Shanghai",
    "iso:country":"CN",
    "name:zho_x_preferred":[
        "\u51af\u9648\u6751"
    ],
    "wof:name":"Fengchencun",
    "wof:placetype":"locality"
},
  "geometry": {"coordinates":[119.47948999999998,33.74329],"type":"Point"}
}