{
  "type": "Feature",
  "properties": {
    "gn:admin1_code":"3",
    "gn:asciiname":"Tangfu",
    "gn:country_code":"CN",
    "gn:dem":625,
    "gn:feature_class":"P",
    "gn:feature_code":"PPL",
    "gn:name":"Tangfu",
    "gn:population":0,
    "gn:timezone":"Asia/Shanghai",
    "iso:country":"CN",
    "name:zho_x_preferred":[
        "\u5510\u752b"
    ],
    "wof:name":"Tangfu",
    "wof:placetype":"locality"
},
  "geometry": {"coordinates":[114.182,25.4606],"type":"Point"}
}