{
  "type": "Feature",
  "properties": {
    "gn:admin1_code":"4.0",
    "gn:asciiname":"Xieniancun",
    "gn:country_code":"CN",
    "gn:dem":10,
    "gn:feature_class":"P",
    "gn:feature_code":"PPL",
    "gn:name":"Xieniancun",
    "gn:population":0,
    "gn:timezone":"Asia/Shanghai",
    "iso:country":"CN",
    "name:zho_x_preferred":[
        "\u8c22\u78be\u6751"
    ],
    "wof:name":"Xieniancun",
    "wof:placetype":"locality"
},
  "geometry": {"coordinates":[119.0437,33.51093],"type":"Point"}
}