{
  "type": "Feature",
  "properties": {
    "gn:admin1_code":"5.0",
    "gn:asciiname":"Chalin Tiaozicun",
    "gn:country_code":"CN",
    "gn:dem":156,
    "gn:feature_class":"P",
    "gn:feature_code":"PPL",
    "gn:name":"Chalin Tiaozicun",
    "gn:population":0,
    "gn:timezone":"Asia/Shanghai",
    "iso:country":"CN",
    "name:zho_x_preferred":[
        "\u8336\u6797\u6761\u5b50\u6751"
    ],
    "wof:name":"Chalin Tiaozicun",
    "wof:placetype":"locality"
},
  "geometry": {"coordinates":[125.77638,44.52692],"type":"Point"}
}