{
  "type": "Feature",
  "properties": {
    "gn:admin1_code":"29.0",
    "gn:asciiname":"Housuoying",
    "gn:country_code":"CN",
    "gn:dem":1649,
    "gn:feature_class":"P",
    "gn:feature_code":"PPL",
    "gn:name":"Housuoying",
    "gn:population":0,
    "gn:timezone":"Asia/Shanghai",
    "iso:country":"CN",
    "name:zho_x_preferred":[
        "\u540e\u6240\u8425"
    ],
    "wof:name":"Housuoying",
    "wof:placetype":"locality"
},
  "geometry": {"coordinates":[98.56440000000001,25.0779],"type":"Point"}
}