{
  "type": "Feature",
  "properties": {
    "gn:admin1_code":"25",
    "gn:asciiname":"Xixue",
    "gn:country_code":"CN",
    "gn:dem":7,
    "gn:feature_class":"P",
    "gn:feature_code":"PPL",
    "gn:name":"Xixue",
    "gn:population":0,
    "gn:timezone":"Asia/Shanghai",
    "iso:country":"CN",
    "name:zho_x_preferred":[
        "\u897f\u859b"
    ],
    "wof:name":"Xixue",
    "wof:placetype":"locality"
},
  "geometry": {"coordinates":[118.401,37.2128],"type":"Point"}
}