{
  "type": "Feature",
  "properties": {
    "gn:admin1_code":"19.0",
    "gn:asciiname":"Qijia Wobu",
    "gn:country_code":"CN",
    "gn:dem":93,
    "gn:feature_class":"P",
    "gn:feature_code":"PPL",
    "gn:name":"Qijia Wobu",
    "gn:population":0,
    "gn:timezone":"Asia/Shanghai",
    "iso:country":"CN",
    "name:und_x_variant":[
        "Qijiawobao",
        "Qijia Wobu"
    ],
    "name:zho_x_preferred":[
        "\u621a\u5bb6\u7a9d\u5821"
    ],
    "wof:name":"Qijia Wobu",
    "wof:placetype":"locality"
},
  "geometry": {"coordinates":[123.16136000000002,42.70813],"type":"Point"}
}