{
  "type": "Feature",
  "properties": {
    "gn:admin1_code":"7.0",
    "gn:asciiname":"Waizeng",
    "gn:country_code":"CN",
    "gn:dem":22,
    "gn:feature_class":"P",
    "gn:feature_code":"PPL",
    "gn:name":"Waizeng",
    "gn:population":0,
    "gn:timezone":"Asia/Shanghai",
    "iso:country":"CN",
    "name:zho_x_preferred":[
        "\u5916\u66fe"
    ],
    "wof:name":"Waizeng",
    "wof:placetype":"locality"
},
  "geometry": {"coordinates":[118.43831000000002,24.74219],"type":"Point"}
}