{
  "type": "Feature",
  "properties": {
    "gn:admin1_code":"07",
    "gn:asciiname":"Nanyan",
    "gn:country_code":"CN",
    "gn:dem":396,
    "gn:feature_class":"P",
    "gn:feature_code":"PPL",
    "gn:name":"Nanyan",
    "gn:population":0,
    "gn:timezone":"Asia/Shanghai",
    "iso:country":"CN",
    "name:rus_x_preferred":[
        "\u041d\u0430\u043d\u044c\u044f\u043d"
    ],
    "name:und_x_variant":[
        "Nan-yen",
        "Nanyan",
        "\u5357\u5ca9"
    ],
    "wof:name":"Nanyan",
    "wof:placetype":"locality"
},
  "geometry": {"coordinates":[116.22727,25.75762000000001],"type":"Point"}
}