{
  "type": "Feature",
  "properties": {
    "gn:admin1_code":"12.0",
    "gn:asciiname":"Zongkou",
    "gn:cc2":"CN",
    "gn:country_code":"CN",
    "gn:dem":31,
    "gn:feature_class":"P",
    "gn:feature_code":"PPL",
    "gn:name":"Zongkou",
    "gn:population":0,
    "gn:timezone":"Asia/Shanghai",
    "iso:country":"CN",
    "name:und_x_variant":[
        "Tsung-k\u2019ou",
        "Zongkou"
    ],
    "wof:name":"Zongkou",
    "wof:placetype":"locality"
},
  "geometry": {"coordinates":[112.90000000000001,30.23333],"type":"Point"}
}