{
  "type": "Feature",
  "properties": {
    "gn:admin1_code":"32.0",
    "gn:asciiname":"Dongwan",
    "gn:country_code":"CN",
    "gn:dem":276,
    "gn:feature_class":"P",
    "gn:feature_code":"PPL",
    "gn:name":"Dongwan",
    "gn:population":0,
    "gn:timezone":"Asia/Shanghai",
    "iso:country":"CN",
    "name:deu_x_preferred":[
        "Dongwan"
    ],
    "name:zho_x_preferred":[
        "\u8463\u6e7e"
    ],
    "wof:name":"Dongwan",
    "wof:placetype":"locality"
},
  "geometry": {"coordinates":[105.77415999999999,28.8903],"type":"Point"}
}