{
  "type": "Feature",
  "properties": {
    "gn:admin1_code":"18",
    "gn:asciiname":"Shengjia Yuanzi",
    "gn:country_code":"CN",
    "gn:dem":2352,
    "gn:feature_class":"P",
    "gn:feature_code":"PPL",
    "gn:name":"Shengjia Yuanzi",
    "gn:population":0,
    "gn:timezone":"Asia/Shanghai",
    "iso:country":"CN",
    "name:zho_x_preferred":[
        "\u76db\u5bb6\u9662\u5b50"
    ],
    "wof:name":"Shengjia Yuanzi",
    "wof:placetype":"locality"
},
  "geometry": {"coordinates":[103.892,27.3187],"type":"Point"}
}