{
  "type": "Feature",
  "properties": {
    "gn:admin1_code":"15.0",
    "gn:asciiname":"Chuangjiacha",
    "gn:country_code":"CN",
    "gn:dem":2069,
    "gn:feature_class":"P",
    "gn:feature_code":"PPL",
    "gn:name":"Chuangjiacha",
    "gn:population":0,
    "gn:timezone":"Asia/Shanghai",
    "iso:country":"CN",
    "name:zho_x_preferred":[
        "\u95ef\u5bb6\u5c94"
    ],
    "wof:name":"Chuangjiacha",
    "wof:placetype":"locality"
},
  "geometry": {"coordinates":[104.81100000000001,35.4761],"type":"Point"}
}