{
  "type": "Feature",
  "properties": {
    "gn:admin1_code":"29.0",
    "gn:asciiname":"Tiaojiwan",
    "gn:country_code":"CN",
    "gn:dem":2032,
    "gn:feature_class":"P",
    "gn:feature_code":"PPL",
    "gn:name":"Tiaojiwan",
    "gn:population":0,
    "gn:timezone":"Asia/Shanghai",
    "iso:country":"CN",
    "name:zho_x_preferred":[
        "\u7b24\u7b95\u6e7e"
    ],
    "wof:name":"Tiaojiwan",
    "wof:placetype":"locality"
},
  "geometry": {"coordinates":[100.459,26.8414],"type":"Point"}
}