{
  "type": "Feature",
  "properties": {
    "gn:admin1_code":"32.0",
    "gn:asciiname":"Tekoujiagu",
    "gn:country_code":"CN",
    "gn:dem":2983,
    "gn:feature_class":"P",
    "gn:feature_code":"PPL",
    "gn:name":"Tekoujiagu",
    "gn:population":0,
    "gn:timezone":"Asia/Shanghai",
    "iso:country":"CN",
    "name:zho_x_preferred":[
        "\u7279\u53e3\u7532\u8c37"
    ],
    "wof:name":"Tekoujiagu",
    "wof:placetype":"locality"
},
  "geometry": {"coordinates":[103.05201,27.89092],"type":"Point"}
}