{
  "type": "Feature",
  "properties": {
    "gn:country":"CN",
    "gn:fcode":"PPL",
    "gn:population":2430,
    "iso:country":"CN",
    "name:und_x_variant":[
        "T\u2019eng-t\u2019ou"
    ],
    "name:zho_x_preferred":[
        "\u9876\u5934"
    ],
    "qs:name":"Dingtou",
    "qs:photos_9r":0,
    "qs:photos_sr":0,
    "qs:pop_sr":"4",
    "wof:name":"Dingtou",
    "wof:placetype":"locality",
    "wof:population":2430
},
  "geometry": {"coordinates":[119.66056,26.84583],"type":"Point"}
}