{
  "type": "Feature",
  "properties": {
    "gn:admin1_code":"31.0",
    "gn:asciiname":"Longtangtian",
    "gn:country_code":"CN",
    "gn:dem":133,
    "gn:feature_class":"P",
    "gn:feature_code":"PPL",
    "gn:name":"Longtangtian",
    "gn:population":0,
    "gn:timezone":"Asia/Shanghai",
    "iso:country":"CN",
    "name:zho_x_preferred":[
        "\u9f99\u5858\u7530"
    ],
    "wof:name":"Longtangtian",
    "wof:placetype":"locality"
},
  "geometry": {"coordinates":[110.50857000000001,19.49012],"type":"Point"}
}