{
  "type": "Feature",
  "properties": {
    "gn:admin1_code":"11.0",
    "gn:asciiname":"Yujiawan",
    "gn:country_code":"CN",
    "gn:dem":130,
    "gn:feature_class":"P",
    "gn:feature_code":"PPL",
    "gn:name":"Yujiawan",
    "gn:population":0,
    "gn:timezone":"Asia/Shanghai",
    "iso:country":"CN",
    "name:zho_x_preferred":[
        "\u4fde\u5bb6\u5f2f"
    ],
    "wof:name":"Yujiawan",
    "wof:placetype":"locality"
},
  "geometry": {"coordinates":[111.23363999999999,28.84844],"type":"Point"}
}