{
  "type": "Feature",
  "properties": {
    "gn:admin1_code":"16.0",
    "gn:asciiname":"Shiliting",
    "gn:country_code":"CN",
    "gn:dem":100,
    "gn:feature_class":"P",
    "gn:feature_code":"PPL",
    "gn:name":"Shiliting",
    "gn:population":0,
    "gn:timezone":"Asia/Shanghai",
    "iso:country":"CN",
    "name:zho_x_preferred":[
        "\u5341\u91cc\u4ead"
    ],
    "wof:name":"Shiliting",
    "wof:placetype":"locality"
},
  "geometry": {"coordinates":[109.779,24.4864],"type":"Point"}
}