{
  "type": "Feature",
  "properties": {
    "gn:admin1_code":"12.0",
    "gn:asciiname":"Ganbodian",
    "gn:country_code":"CN",
    "gn:dem":32,
    "gn:feature_class":"P",
    "gn:feature_code":"PPL",
    "gn:name":"Ganbodian",
    "gn:population":0,
    "gn:timezone":"Asia/Shanghai",
    "iso:country":"CN",
    "name:und_x_variant":[
        "\u5e72\u6ce2\u5e97"
    ],
    "wof:name":"Ganbodian",
    "wof:placetype":"locality"
},
  "geometry": {"coordinates":[114.32178,30.79538],"type":"Point"}
}