{
  "type": "Feature",
  "properties": {
    "gn:admin1_code":"3.0",
    "gn:asciiname":"Xiaxiancun",
    "gn:country_code":"CN",
    "gn:dem":30,
    "gn:feature_class":"P",
    "gn:feature_code":"PPL",
    "gn:name":"Xiaxiancun",
    "gn:population":0,
    "gn:timezone":"Asia/Shanghai",
    "iso:country":"CN",
    "name:und_x_variant":[
        "\u4e0b\u5f26\u6751"
    ],
    "wof:name":"Xiaxiancun",
    "wof:placetype":"locality"
},
  "geometry": {"coordinates":[115.40586999999999,28.43163],"type":"Point"}
}