{
  "type": "Feature",
  "properties": {
    "gn:admin1_code":"30.0",
    "gn:asciiname":"Gaobeicun",
    "gn:country_code":"CN",
    "gn:dem":103,
    "gn:feature_class":"P",
    "gn:feature_code":"PPL",
    "gn:name":"Gaobeicun",
    "gn:population":0,
    "gn:timezone":"Asia/Shanghai",
    "iso:country":"CN",
    "name:zho_x_preferred":[
        "\u9ad8\u9642\u6751"
    ],
    "wof:name":"Gaobeicun",
    "wof:placetype":"locality"
},
  "geometry": {"coordinates":[116.16636,24.69399],"type":"Point"}
}