{
  "type": "Feature",
  "properties": {
    "gn:admin1_code":"11.0",
    "gn:asciiname":"Shizhuwan",
    "gn:country_code":"CN",
    "gn:dem":355,
    "gn:feature_class":"P",
    "gn:feature_code":"PPL",
    "gn:name":"Shizhuwan",
    "gn:population":0,
    "gn:timezone":"Asia/Shanghai",
    "iso:country":"CN",
    "name:zho_x_preferred":[
        "\u89c6\u7af9\u6e7e"
    ],
    "wof:name":"Shizhuwan",
    "wof:placetype":"locality"
},
  "geometry": {"coordinates":[111.42991000000001,28.59435],"type":"Point"}
}