{
  "type": "Feature",
  "properties": {
    "gn:admin1_code":"32.0",
    "gn:asciiname":"Xuangangshan",
    "gn:country_code":"CN",
    "gn:dem":401,
    "gn:feature_class":"P",
    "gn:feature_code":"PPL",
    "gn:name":"Xuangangshan",
    "gn:population":0,
    "gn:timezone":"Asia/Shanghai",
    "iso:country":"CN",
    "name:zho_x_preferred":[
        "\u60ac\u5c97\u5c71"
    ],
    "wof:name":"Xuangangshan",
    "wof:placetype":"locality"
},
  "geometry": {"coordinates":[105.11471,30.82958],"type":"Point"}
}