{
  "type": "Feature",
  "properties": {
    "gn:admin1_code":"32.0",
    "gn:asciiname":"Liushuiyan",
    "gn:country_code":"CN",
    "gn:dem":290,
    "gn:feature_class":"P",
    "gn:feature_code":"PPL",
    "gn:name":"Liushuiyan",
    "gn:population":0,
    "gn:timezone":"Asia/Shanghai",
    "iso:country":"CN",
    "name:zho_x_preferred":[
        "\u6d41\u6c34\u5ca9"
    ],
    "wof:name":"Liushuiyan",
    "wof:placetype":"locality"
},
  "geometry": {"coordinates":[105.64422,28.84725],"type":"Point"}
}