{
  "type": "Feature",
  "properties": {
    "gn:admin1_code":"12.0",
    "gn:asciiname":"Hongmiao",
    "gn:country_code":"CN",
    "gn:dem":345,
    "gn:feature_class":"P",
    "gn:feature_code":"PPL",
    "gn:name":"Hongmiao",
    "gn:population":0,
    "gn:timezone":"Asia/Shanghai",
    "iso:country":"CN",
    "name:zho_x_preferred":[
        "\u7ea2\u5e99"
    ],
    "wof:name":"Hongmiao",
    "wof:placetype":"locality"
},
  "geometry": {"coordinates":[110.95723,32.05987],"type":"Point"}
}