{
  "type": "Feature",
  "properties": {
    "gn:admin1_code":"9.0",
    "gn:asciiname":"Laojunmiao",
    "gn:country_code":"CN",
    "gn:dem":46,
    "gn:feature_class":"P",
    "gn:feature_code":"PPL",
    "gn:name":"Laojunmiao",
    "gn:population":0,
    "gn:timezone":"Asia/Shanghai",
    "iso:country":"CN",
    "name:zho_x_preferred":[
        "\u8001\u541b\u5e99"
    ],
    "wof:name":"Laojunmiao",
    "wof:placetype":"locality"
},
  "geometry": {"coordinates":[114.89058,33.38411],"type":"Point"}
}