{
  "type": "Feature",
  "properties": {
    "gn:admin1_code":"32.0",
    "gn:asciiname":"Sangeshi",
    "gn:country_code":"CN",
    "gn:dem":1484,
    "gn:feature_class":"P",
    "gn:feature_code":"PPL",
    "gn:name":"Sangeshi",
    "gn:population":0,
    "gn:timezone":"Asia/Shanghai",
    "iso:country":"CN",
    "name:zho_x_preferred":[
        "\u4e09\u4e2a\u77f3"
    ],
    "wof:name":"Sangeshi",
    "wof:placetype":"locality"
},
  "geometry": {"coordinates":[103.14449,29.55296],"type":"Point"}
}