{
  "type": "Feature",
  "properties": {
    "gn:admin1_code":"8.0",
    "gn:asciiname":"Shi'erdaogang",
    "gn:country_code":"CN",
    "gn:dem":220,
    "gn:feature_class":"P",
    "gn:feature_code":"PPL",
    "gn:name":"Shi\u2019erdaogang",
    "gn:population":0,
    "gn:timezone":"Asia/Shanghai",
    "iso:country":"CN",
    "name:und_x_variant":[
        "Shi\u2019erdaogang"
    ],
    "name:zho_x_preferred":[
        "\u5341\u4e8c\u9053\u5c97"
    ],
    "wof:name":"Shi'erdaogang",
    "wof:placetype":"locality"
},
  "geometry": {"coordinates":[127.76206000000001,47.17274000000001],"type":"Point"}
}