{
  "type": "Feature",
  "properties": {
    "gn:admin1_code":"26.0",
    "gn:asciiname":"Liujiadayuan",
    "gn:country_code":"CN",
    "gn:dem":718,
    "gn:feature_class":"P",
    "gn:feature_code":"PPL",
    "gn:name":"Liujiadayuan",
    "gn:population":0,
    "gn:timezone":"Asia/Shanghai",
    "iso:country":"CN",
    "name:zho_x_preferred":[
        "\u5218\u5bb6\u5927\u9662"
    ],
    "wof:name":"Liujiadayuan",
    "wof:placetype":"locality"
},
  "geometry": {"coordinates":[110.01027999999999,32.78355],"type":"Point"}
}