{
  "type": "Feature",
  "properties": {
    "gn:admin1_code":"10.0",
    "gn:asciiname":"Gaoyaozhuang",
    "gn:country_code":"CN",
    "gn:dem":11,
    "gn:feature_class":"P",
    "gn:feature_code":"PPL",
    "gn:name":"Gaoyaozhuang",
    "gn:population":0,
    "gn:timezone":"Asia/Shanghai",
    "iso:country":"CN",
    "name:zho_x_preferred":[
        "\u9ad8\u59da\u5e84"
    ],
    "wof:name":"Gaoyaozhuang",
    "wof:placetype":"locality"
},
  "geometry": {"coordinates":[117.151,38.0237],"type":"Point"}
}