{
  "type": "Feature",
  "properties": {
    "gn:admin1_code":"9.0",
    "gn:asciiname":"Tuyangou",
    "gn:country_code":"CN",
    "gn:dem":260,
    "gn:feature_class":"P",
    "gn:feature_code":"PPL",
    "gn:name":"Tuyangou",
    "gn:population":0,
    "gn:timezone":"Asia/Shanghai",
    "iso:country":"CN",
    "name:zho_x_preferred":[
        "\u571f\u5935\u6c9f"
    ],
    "wof:name":"Tuyangou",
    "wof:placetype":"locality"
},
  "geometry": {"coordinates":[113.21541000000001,34.22802],"type":"Point"}
}