{
  "type": "Feature",
  "properties": {
    "gn:admin1_code":"3.0",
    "gn:asciiname":"Zhangshucun",
    "gn:country_code":"CN",
    "gn:dem":48,
    "gn:feature_class":"P",
    "gn:feature_code":"PPL",
    "gn:name":"Zhangshucun",
    "gn:population":0,
    "gn:timezone":"Asia/Shanghai",
    "iso:country":"CN",
    "name:und_x_variant":[
        "\u6a1f\u6811\u6751"
    ],
    "wof:name":"Zhangshucun",
    "wof:placetype":"locality"
},
  "geometry": {"coordinates":[115.57485,28.88227],"type":"Point"}
}