{
  "type": "Feature",
  "properties": {
    "gn:admin1_code":"30",
    "gn:asciiname":"Banxi",
    "gn:country_code":"CN",
    "gn:dem":212,
    "gn:feature_class":"P",
    "gn:feature_code":"PPL",
    "gn:name":"Banxi",
    "gn:population":0,
    "gn:timezone":"Asia/Shanghai",
    "iso:country":"CN",
    "name:und_x_variant":[
        "\u534a\u6eaa"
    ],
    "wof:name":"Banxi",
    "wof:placetype":"locality"
},
  "geometry": {"coordinates":[114.21288,24.57428],"type":"Point"}
}