{
  "type": "Feature",
  "properties": {
    "gn:admin1_code":"4.0",
    "gn:asciiname":"Lishixu",
    "gn:country_code":"CN",
    "gn:dem":4,
    "gn:feature_class":"P",
    "gn:feature_code":"PPL",
    "gn:name":"Lishixu",
    "gn:population":0,
    "gn:timezone":"Asia/Shanghai",
    "iso:country":"CN",
    "name:zho_x_preferred":[
        "\u793c\u58eb\u5729"
    ],
    "wof:name":"Lishixu",
    "wof:placetype":"locality"
},
  "geometry": {"coordinates":[120.10657999999999,32.01459000000001],"type":"Point"}
}