{
  "type": "Feature",
  "properties": {
    "gn:admin1_code":"4.0",
    "gn:asciiname":"Huayang",
    "gn:country_code":"CN",
    "gn:dem":24,
    "gn:feature_class":"P",
    "gn:feature_code":"PPLA3",
    "gn:name":"Huayang",
    "gn:population":0,
    "gn:timezone":"Asia/Shanghai",
    "iso:country":"CN",
    "name:deu_x_preferred":[
        "Huayang"
    ],
    "name:und_x_variant":[
        "Huayang Zhen",
        "Jurong Shi"
    ],
    "name:zho_x_preferred":[
        "\u534e\u9633"
    ],
    "name:zho_x_variant":[
        "\u534e\u9633\u9547",
        "\u53e5\u5bb9\u5e02"
    ],
    "wof:name":"Huayang",
    "wof:placetype":"locality"
},
  "geometry": {"coordinates":[119.16284,31.95165],"type":"Point"}
}