{
  "type": "Feature",
  "properties": {
    "gn:admin1_code":"5.0",
    "gn:asciiname":"Sanlicun",
    "gn:country_code":"CN",
    "gn:dem":303,
    "gn:feature_class":"P",
    "gn:feature_code":"PPL",
    "gn:name":"Sanlicun",
    "gn:population":0,
    "gn:timezone":"Asia/Shanghai",
    "iso:country":"CN",
    "name:zho_x_preferred":[
        "\u4e09\u91cc\u6751"
    ],
    "wof:name":"Sanlicun",
    "wof:placetype":"locality"
},
  "geometry": {"coordinates":[125.96472,42.67629],"type":"Point"}
}