{
  "type": "Feature",
  "properties": {
    "gn:admin1_code":"24.0",
    "gn:asciiname":"Xielinbei",
    "gn:country_code":"CN",
    "gn:dem":1653,
    "gn:feature_class":"P",
    "gn:feature_code":"PPL",
    "gn:name":"Xielinbei",
    "gn:population":0,
    "gn:timezone":"Asia/Shanghai",
    "iso:country":"CN",
    "name:zho_x_preferred":[
        "\u659c\u6797\u80cc"
    ],
    "wof:name":"Xielinbei",
    "wof:placetype":"locality"
},
  "geometry": {"coordinates":[111.46142999999999,38.61144],"type":"Point"}
}