{
  "type": "Feature",
  "properties": {
    "gn:admin1_code":"30.0",
    "gn:asciiname":"Beixincun",
    "gn:country_code":"CN",
    "gn:dem":16,
    "gn:feature_class":"P",
    "gn:feature_code":"PPL",
    "gn:name":"Beixincun",
    "gn:population":0,
    "gn:timezone":"Asia/Shanghai",
    "iso:country":"CN",
    "name:zho_x_preferred":[
        "\u9642\u65b0\u6751"
    ],
    "wof:name":"Beixincun",
    "wof:placetype":"locality"
},
  "geometry": {"coordinates":[116.21187999999999,23.27146],"type":"Point"}
}