{
  "type": "Feature",
  "properties": {
    "gn:admin1_code":"13",
    "gn:asciiname":"Ercengtaizi",
    "gn:country_code":"CN",
    "gn:dem":1333,
    "gn:feature_class":"P",
    "gn:feature_code":"PPL",
    "gn:name":"Ercengtaizi",
    "gn:population":0,
    "gn:timezone":"Asia/Urumqi",
    "iso:country":"CN",
    "name:zho_x_preferred":[
        "\u4e8c\u5c42\u53f0\u5b50"
    ],
    "wof:name":"Ercengtaizi",
    "wof:placetype":"locality"
},
  "geometry": {"coordinates":[88.48491,43.39328],"type":"Point"}
}