{
  "type": "Feature",
  "properties": {
    "gn:admin1_code":"12.0",
    "gn:asciiname":"Shayuanzi",
    "gn:country_code":"CN",
    "gn:dem":767,
    "gn:feature_class":"P",
    "gn:feature_code":"PPL",
    "gn:name":"Shayuanzi",
    "gn:population":0,
    "gn:timezone":"Asia/Shanghai",
    "iso:country":"CN",
    "name:zho_x_preferred":[
        "\u6c99\u56ed\u5b50"
    ],
    "wof:name":"Shayuanzi",
    "wof:placetype":"locality"
},
  "geometry": {"coordinates":[109.00695,29.88653],"type":"Point"}
}