{
  "type": "Feature",
  "properties": {
    "gn:admin1_code":"11.0",
    "gn:asciiname":"Qingkou'ao",
    "gn:country_code":"CN",
    "gn:dem":1046,
    "gn:feature_class":"P",
    "gn:feature_code":"PPL",
    "gn:name":"Qingkou\u2019ao",
    "gn:population":0,
    "gn:timezone":"Asia/Shanghai",
    "iso:country":"CN",
    "name:zho_x_preferred":[
        "\u5e86\u53e3\u5773"
    ],
    "name:zho_x_variant":[
        "Qingkou\u2019ao"
    ],
    "wof:name":"Qingkou'ao",
    "wof:placetype":"locality"
},
  "geometry": {"coordinates":[109.48957,29.36515],"type":"Point"}
}