{
  "type": "Feature",
  "properties": {
    "gn:admin1_code":"26.0",
    "gn:asciiname":"Qianwujia Goucun",
    "gn:country_code":"CN",
    "gn:dem":969,
    "gn:feature_class":"P",
    "gn:feature_code":"PPL",
    "gn:name":"Qianwujia Goucun",
    "gn:population":0,
    "gn:timezone":"Asia/Shanghai",
    "iso:country":"CN",
    "name:zho_x_preferred":[
        "\u524d\u5434\u5bb6\u6c9f\u6751"
    ],
    "wof:name":"Qianwujia Goucun",
    "wof:placetype":"locality"
},
  "geometry": {"coordinates":[109.845,37.61],"type":"Point"}
}