{
  "type": "Feature",
  "properties": {
    "gn:admin1_code":"32.0",
    "gn:asciiname":"Linzi",
    "gn:country_code":"CN",
    "gn:dem":2243,
    "gn:feature_class":"P",
    "gn:feature_code":"PPL",
    "gn:name":"Linzi",
    "gn:population":0,
    "gn:timezone":"Asia/Shanghai",
    "iso:country":"CN",
    "name:ceb_x_preferred":[
        "Linzi"
    ],
    "name:swe_x_preferred":[
        "Linzi"
    ],
    "name:zho_x_preferred":[
        "\u6797\u5b50"
    ],
    "wof:name":"Linzi",
    "wof:placetype":"locality"
},
  "geometry": {"coordinates":[102.63800000000001,29.1897],"type":"Point"}
}