{
  "type": "Feature",
  "properties": {
    "gn:admin1_code":"19.0",
    "gn:asciiname":"Xiaoweitun",
    "gn:country_code":"CN",
    "gn:dem":204,
    "gn:feature_class":"P",
    "gn:feature_code":"PPL",
    "gn:name":"Xiaoweitun",
    "gn:population":0,
    "gn:timezone":"Asia/Shanghai",
    "iso:country":"CN",
    "name:und_x_variant":[
        "\u5c0f\u9b4f\u5c6f"
    ],
    "name:zho_x_preferred":[
        "\u5c0f\u9b4f\u5c6f"
    ],
    "wof:name":"Xiaoweitun",
    "wof:placetype":"locality"
},
  "geometry": {"coordinates":[123.09533,40.40905],"type":"Point"}
}