{
  "type": "Feature",
  "properties": {
    "gn:admin1_code":"29.0",
    "gn:asciiname":"Luti",
    "gn:country_code":"CN",
    "gn:dem":1343,
    "gn:feature_class":"P",
    "gn:feature_code":"PPL",
    "gn:name":"Luti",
    "gn:population":0,
    "gn:timezone":"Asia/Shanghai",
    "iso:country":"CN",
    "name:zho_x_preferred":[
        "\u8def\u68af"
    ],
    "wof:name":"Luti",
    "wof:placetype":"locality"
},
  "geometry": {"coordinates":[104.07599999999999,23.4952],"type":"Point"}
}