{
  "type": "Feature",
  "properties": {
    "gn:admin1_code":"10",
    "gn:asciiname":"Zhouzhangzi",
    "gn:country_code":"CN",
    "gn:dem":651,
    "gn:feature_class":"P",
    "gn:feature_code":"PPL",
    "gn:name":"Zhouzhangzi",
    "gn:population":0,
    "gn:timezone":"Asia/Shanghai",
    "iso:country":"CN",
    "name:zho_x_preferred":[
        "\u5468\u6756\u5b50"
    ],
    "wof:name":"Zhouzhangzi",
    "wof:placetype":"locality"
},
  "geometry": {"coordinates":[118.76647,40.76801],"type":"Point"}
}