{
  "type": "Feature",
  "properties": {
    "gn:admin1_code":"8.0",
    "gn:asciiname":"Zhaojiagoutun",
    "gn:country_code":"CN",
    "gn:dem":223,
    "gn:feature_class":"P",
    "gn:feature_code":"PPL",
    "gn:name":"Zhaojiagoutun",
    "gn:population":0,
    "gn:timezone":"Asia/Shanghai",
    "iso:country":"CN",
    "name:zho_x_preferred":[
        "\u8d75\u5bb6\u6c9f\u5c6f"
    ],
    "wof:name":"Zhaojiagoutun",
    "wof:placetype":"locality"
},
  "geometry": {"coordinates":[124.98954999999999,48.15685],"type":"Point"}
}