{
  "type": "Feature",
  "properties": {
    "gn:admin1_code":"23.0",
    "gn:asciiname":"Wuyao",
    "gn:country_code":"CN",
    "gn:dem":6,
    "gn:feature_class":"P",
    "gn:feature_code":"PPL",
    "gn:name":"Wuyao",
    "gn:population":0,
    "gn:timezone":"Asia/Shanghai",
    "iso:country":"CN",
    "name:zho_x_preferred":[
        "Wuyao"
    ],
    "name:zho_x_variant":[
        "\u4e94\u6ee7"
    ],
    "wof:name":"Wuyao",
    "wof:placetype":"locality"
},
  "geometry": {"coordinates":[121.67139,31.53849],"type":"Point"}
}