{
  "type": "Feature",
  "properties": {
    "gn:admin1_code":"02",
    "gn:asciiname":"Haidian Rongjia",
    "gn:country_code":"CN",
    "gn:dem":6,
    "gn:feature_class":"P",
    "gn:feature_code":"PPL",
    "gn:name":"Haidian Rongjia",
    "gn:population":0,
    "gn:timezone":"Asia/Shanghai",
    "iso:country":"CN",
    "name:und_x_variant":[
        "Jung-chia",
        "Haidian Rongjia"
    ],
    "name:zho_x_preferred":[
        "\u6d77\u7538\u620e\u5bb6"
    ],
    "wof:name":"Haidian Rongjia",
    "wof:placetype":"locality"
},
  "geometry": {"coordinates":[121.4875,30.09944],"type":"Point"}
}