{
  "type": "Feature",
  "properties": {
    "gn:admin1_code":"8.0",
    "gn:asciiname":"Langhuacun",
    "gn:country_code":"CN",
    "gn:dem":278,
    "gn:feature_class":"P",
    "gn:feature_code":"PPL",
    "gn:name":"Langhuacun",
    "gn:population":0,
    "gn:timezone":"Asia/Shanghai",
    "iso:country":"CN",
    "name:zho_x_preferred":[
        "\u6d6a\u82b1\u6751"
    ],
    "wof:name":"Langhuacun",
    "wof:placetype":"locality"
},
  "geometry": {"coordinates":[130.21375,45.24119],"type":"Point"}
}