{
  "type": "Feature",
  "properties": {
    "gn:admin1_code":"8.0",
    "gn:asciiname":"Qianshanwantun",
    "gn:country_code":"CN",
    "gn:dem":247,
    "gn:feature_class":"P",
    "gn:feature_code":"PPL",
    "gn:name":"Qianshanwantun",
    "gn:population":0,
    "gn:timezone":"Asia/Shanghai",
    "iso:country":"CN",
    "name:zho_x_preferred":[
        "\u524d\u5c71\u6e7e\u5c6f"
    ],
    "wof:name":"Qianshanwantun",
    "wof:placetype":"locality"
},
  "geometry": {"coordinates":[127.10912999999999,47.47814],"type":"Point"}
}