{
  "type": "Feature",
  "properties": {
    "gn:admin1_code":"14.0",
    "gn:asciiname":"Qiongguo",
    "gn:country_code":"CN",
    "gn:dem":4013,
    "gn:feature_class":"P",
    "gn:feature_code":"PPL",
    "gn:name":"Qiongguo",
    "gn:population":0,
    "gn:timezone":"Asia/Urumqi",
    "iso:country":"CN",
    "name:zho_x_preferred":[
        "\u7a77\u90ed"
    ],
    "wof:name":"Qiongguo",
    "wof:placetype":"locality"
},
  "geometry": {"coordinates":[96.35448,30.38272000000001],"type":"Point"}
}