{
  "type": "Feature",
  "properties": {
    "gn:admin1_code":"7.0",
    "gn:asciiname":"Shantouding",
    "gn:country_code":"CN",
    "gn:dem":985,
    "gn:feature_class":"P",
    "gn:feature_code":"PPL",
    "gn:name":"Shantouding",
    "gn:population":0,
    "gn:timezone":"Asia/Shanghai",
    "iso:country":"CN",
    "name:zho_x_preferred":[
        "Shantouding"
    ],
    "name:zho_x_variant":[
        "\u5c71\u5934\u9876"
    ],
    "wof:name":"Shantouding",
    "wof:placetype":"locality"
},
  "geometry": {"coordinates":[118.87333,26.80333],"type":"Point"}
}