{
  "type": "Feature",
  "properties": {
    "gn:admin1_code":"32.0",
    "gn:asciiname":"Baigang",
    "gn:country_code":"CN",
    "gn:dem":3636,
    "gn:feature_class":"P",
    "gn:feature_code":"PPL",
    "gn:name":"Baigang",
    "gn:population":0,
    "gn:timezone":"Asia/Shanghai",
    "iso:country":"CN",
    "name:zho_x_preferred":[
        "\u62dc\u5188"
    ],
    "wof:name":"Baigang",
    "wof:placetype":"locality"
},
  "geometry": {"coordinates":[99.4744,29.2002],"type":"Point"}
}