{
  "type": "Feature",
  "properties": {
    "gn:admin1_code":"02",
    "gn:asciiname":"Liu-li-pan-ch'iao",
    "gn:country_code":"CN",
    "gn:dem":6,
    "gn:feature_class":"P",
    "gn:feature_code":"PPL",
    "gn:name":"Liu-li-pan-ch\u2019iao",
    "gn:population":0,
    "gn:timezone":"Asia/Shanghai",
    "iso:country":"CN",
    "wof:name":"Liu-li-pan-ch'iao",
    "wof:placetype":"locality"
},
  "geometry": {"coordinates":[121.00221999999999,30.63389],"type":"Point"}
}