{
  "type": "Feature",
  "properties": {
    "gn:admin1_code":"1.0",
    "gn:asciiname":"Dasonglin",
    "gn:country_code":"CN",
    "gn:dem":55,
    "gn:feature_class":"P",
    "gn:feature_code":"PPL",
    "gn:name":"Dasonglin",
    "gn:population":0,
    "gn:timezone":"Asia/Shanghai",
    "iso:country":"CN",
    "name:zho_x_preferred":[
        "Dasonglin"
    ],
    "name:zho_x_variant":[
        "\u5927\u677e\u6797"
    ],
    "wof:name":"Dasonglin",
    "wof:placetype":"locality"
},
  "geometry": {"coordinates":[119.52509999999999,30.91197],"type":"Point"}
}