{
  "type": "Feature",
  "properties": {
    "gn:admin1_code":"21.0",
    "gn:asciiname":"Sandaocha",
    "gn:country_code":"CN",
    "gn:dem":1887,
    "gn:feature_class":"P",
    "gn:feature_code":"PPL",
    "gn:name":"Sandaocha",
    "gn:population":0,
    "gn:timezone":"Asia/Shanghai",
    "iso:country":"CN",
    "name:und_x_variant":[
        "\u4e09\u9053\u5c94"
    ],
    "name:zho_x_preferred":[
        "\u4e09\u9053\u5c94"
    ],
    "wof:name":"Sandaocha",
    "wof:placetype":"locality"
},
  "geometry": {"coordinates":[106.33744,36.08901],"type":"Point"}
}