{
  "type": "Feature",
  "properties": {
    "gn:admin1_code":"4.0",
    "gn:asciiname":"Xusheng",
    "gn:country_code":"CN",
    "gn:dem":3,
    "gn:feature_class":"P",
    "gn:feature_code":"PPL",
    "gn:name":"Xusheng",
    "gn:population":0,
    "gn:timezone":"Asia/Shanghai",
    "iso:country":"CN",
    "name:und_x_variant":[
        "\u65ed\u5347"
    ],
    "wof:name":"Xusheng",
    "wof:placetype":"locality"
},
  "geometry": {"coordinates":[121.3571,32.00494],"type":"Point"}
}