{
  "type": "Feature",
  "properties": {
    "gn:admin1_code":"25.0",
    "gn:asciiname":"Daxishaocun",
    "gn:country_code":"CN",
    "gn:dem":66,
    "gn:feature_class":"P",
    "gn:feature_code":"PPL",
    "gn:name":"Daxishaocun",
    "gn:population":0,
    "gn:timezone":"Asia/Shanghai",
    "iso:country":"CN",
    "name:und_x_variant":[
        "Shiyazi"
    ],
    "name:zho_x_preferred":[
        "\u5927\u897f\u90b5\u6751"
    ],
    "name:zho_x_variant":[
        "\u77f3\u5d16\u5b50"
    ],
    "wof:name":"Daxishaocun",
    "wof:placetype":"locality"
},
  "geometry": {"coordinates":[119.37163,36.45884],"type":"Point"}
}