{
  "type": "Feature",
  "properties": {
    "gn:admin1_code":"10",
    "gn:asciiname":"Leting",
    "gn:cc2":"CN",
    "gn:country_code":"CN",
    "gn:dem":11,
    "gn:feature_class":"P",
    "gn:feature_code":"PPL",
    "gn:name":"Leting",
    "gn:population":0,
    "gn:timezone":"Asia/Shanghai",
    "iso:country":"CN",
    "name:deu_x_preferred":[
        "Laoting"
    ],
    "name:fas_x_preferred":[
        "\u0634\u0647\u0631\u0633\u062a\u0627\u0646 \u0644\u0627\u0648\u062a\u06cc\u0646\u06af"
    ],
    "name:jpn_x_preferred":[
        "\u697d\u4ead\u770c"
    ],
    "name:kor_x_preferred":[
        "\ub7ec\ub529\ud604"
    ],
    "name:nor_x_preferred":[
        "Leting"
    ],
    "name:rus_x_preferred":[
        "\u041b\u0430\u043e\u0442\u0438\u043d"
    ],
    "name:swe_x_preferred":[
        "Laoting"
    ],
    "name:und_x_variant":[
        "Lo-t\u2019ing-hsien",
        "Lao-t\u2019ing",
        "Lo-t\u2019ing",
        "Lo-t\u2019ing-ch\u2019eng-kuan"
    ],
    "name:urd_x_preferred":[
        "\u0644\u0627\u0648\u0679\u06cc\u0646\u06af \u06a9\u0627\u0624\u0646\u0679\u06cc"
    ],
    "name:vie_x_preferred":[
        "L\u1ea1c \u0110\u00ecnh"
    ],
    "name:zho_x_preferred":[
        "\u4e50\u4ead\u53bf"
    ],
    "wof:name":"Leting",
    "wof:placetype":"locality"
},
  "geometry": {"coordinates":[118.93333,39.43333],"type":"Point"}
}