{
  "type": "Feature",
  "properties": {
    "gn:admin1_code":"10",
    "gn:asciiname":"Leting",
    "gn:cc2":"CN",
    "gn:country_code":"CN",
    "gn:dem":11,
    "gn:feature_class":"P",
    "gn:feature_code":"PPL",
    "gn:name":"Leting",
    "gn:population":0,
    "gn:timezone":"Asia/Shanghai",
    "iso:country":"CN",
    "name:und_x_variant":[
        "Lo-t\u2019ing-hsien",
        "Lao-t\u2019ing",
        "Lo-t\u2019ing",
        "Lo-t\u2019ing-ch\u2019eng-kuan",
        "Leting"
    ],
    "wof:name":"Leting",
    "wof:placetype":"locality"
},
  "geometry": {"coordinates":[118.93333,39.43333],"type":"Point"}
}