{
  "type": "Feature",
  "properties": {
    "gn:admin1_code":"32.0",
    "gn:asciiname":"Luogu",
    "gn:country_code":"CN",
    "gn:dem":2896,
    "gn:feature_class":"P",
    "gn:feature_code":"PPL",
    "gn:name":"Luogu",
    "gn:population":0,
    "gn:timezone":"Asia/Shanghai",
    "iso:country":"CN",
    "name:zho_x_preferred":[
        "\u6d1b\u53e4"
    ],
    "wof:name":"Luogu",
    "wof:placetype":"locality"
},
  "geometry": {"coordinates":[102.505,27.8168],"type":"Point"}
}