{
  "type": "Feature",
  "properties": {
    "gn:admin1_code":"21.0",
    "gn:asciiname":"Taiping Sidui",
    "gn:country_code":"CN",
    "gn:dem":1189,
    "gn:feature_class":"P",
    "gn:feature_code":"PPLF",
    "gn:name":"Taiping Sidui",
    "gn:population":0,
    "gn:timezone":"Asia/Shanghai",
    "iso:country":"CN",
    "name:zho_x_preferred":[
        "\u592a\u5e73\u56db\u961f"
    ],
    "wof:name":"Taiping Sidui",
    "wof:placetype":"locality"
},
  "geometry": {"coordinates":[105.687,37.5495],"type":"Point"}
}