{
  "type": "Feature",
  "properties": {
    "gn:admin1_code":"9.0",
    "gn:asciiname":"Laohulongzhuang",
    "gn:country_code":"CN",
    "gn:dem":594,
    "gn:feature_class":"P",
    "gn:feature_code":"PPL",
    "gn:name":"Laohulongzhuang",
    "gn:population":0,
    "gn:timezone":"Asia/Shanghai",
    "iso:country":"CN",
    "name:zho_x_preferred":[
        "\u8001\u864e\u7b3c\u5e84"
    ],
    "wof:name":"Laohulongzhuang",
    "wof:placetype":"locality"
},
  "geometry": {"coordinates":[112.51328999999998,33.94879],"type":"Point"}
}