{
  "type": "Feature",
  "properties": {
    "gn:admin1_code":"3",
    "gn:asciiname":"Waling",
    "gn:country_code":"CN",
    "gn:dem":151,
    "gn:feature_class":"P",
    "gn:feature_code":"PPL",
    "gn:name":"Waling",
    "gn:population":0,
    "gn:timezone":"Asia/Shanghai",
    "iso:country":"CN",
    "name:deu_x_preferred":[
        "Waling"
    ],
    "name:hin_x_preferred":[
        "\u0935\u093e\u0932\u093f\u0919 \u0928\u0917\u0930\u092a\u093e\u0932\u093f\u0915\u093e"
    ],
    "name:mai_x_preferred":[
        "\u0935\u093e\u0932\u093f\u0919 \u0928\u0917\u0930\u092a\u093e\u0932\u093f\u0915\u093e"
    ],
    "name:msa_x_preferred":[
        "Waling"
    ],
    "name:nep_x_preferred":[
        "\u0935\u093e\u0932\u093f\u0919 \u0928\u0917\u0930\u092a\u093e\u0932\u093f\u0915\u093e"
    ],
    "name:new_x_preferred":[
        "\u0935\u093e\u0932\u093f\u0919 \u0928\u0917\u0930\u092a\u093e\u0932\u093f\u0915\u093e"
    ],
    "name:pol_x_preferred":[
        "Waling"
    ],
    "name:urd_x_preferred":[
        "\u0648\u0627\u0644\u0646\u06af"
    ],
    "name:zho_x_preferred":[
        "\u74e6\u5cad"
    ],
    "name:zho_x_variant":[
        "\u6c83\u6797\u683c"
    ],
    "wof:name":"Waling",
    "wof:placetype":"locality"
},
  "geometry": {"coordinates":[114.68473,25.63031],"type":"Point"}
}