{
  "type": "Feature",
  "properties": {
    "gn:admin1_code":"5.0",
    "gn:asciiname":"Lizhu Wobu",
    "gn:country_code":"CN",
    "gn:dem":195,
    "gn:feature_class":"P",
    "gn:feature_code":"PPL",
    "gn:name":"Lizhu Wobu",
    "gn:population":0,
    "gn:timezone":"Asia/Shanghai",
    "iso:country":"CN",
    "name:zho_x_preferred":[
        "\u674e\u73e0\u7a9d\u5821"
    ],
    "wof:name":"Lizhu Wobu",
    "wof:placetype":"locality"
},
  "geometry": {"coordinates":[125.77137,45.09967],"type":"Point"}
}