{
  "type": "Feature",
  "properties": {
    "gn:admin1_code":"12.0",
    "gn:asciiname":"Yaohe",
    "gn:country_code":"CN",
    "gn:dem":24,
    "gn:feature_class":"P",
    "gn:feature_code":"PPL",
    "gn:name":"Yaohe",
    "gn:population":0,
    "gn:timezone":"Asia/Shanghai",
    "iso:country":"CN",
    "name:zho_x_preferred":[
        "\u59da\u6cb3"
    ],
    "wof:name":"Yaohe",
    "wof:placetype":"locality"
},
  "geometry": {"coordinates":[113.50306,30.06693],"type":"Point"}
}