{
  "type": "Feature",
  "properties": {
    "gn:admin1_code":"1.0",
    "gn:asciiname":"Dakuangwei Nongchang",
    "gn:country_code":"CN",
    "gn:dem":10,
    "gn:feature_class":"P",
    "gn:feature_code":"PPLF",
    "gn:name":"Dakuangwei Nongchang",
    "gn:population":0,
    "gn:timezone":"Asia/Shanghai",
    "iso:country":"CN",
    "wof:name":"Dakuangwei Nongchang",
    "wof:placetype":"locality"
},
  "geometry": {"coordinates":[119.09008,32.74346],"type":"Point"}
}