{
  "type": "Feature",
  "properties": {
    "gn:admin1_code":"18",
    "gn:asciiname":"Dongkoushao",
    "gn:country_code":"CN",
    "gn:dem":1350,
    "gn:feature_class":"P",
    "gn:feature_code":"PPL",
    "gn:name":"Dongkoushao",
    "gn:population":0,
    "gn:timezone":"Asia/Shanghai",
    "iso:country":"CN",
    "name:zho_x_preferred":[
        "\u6d1e\u53e3\u54e8"
    ],
    "wof:name":"Dongkoushao",
    "wof:placetype":"locality"
},
  "geometry": {"coordinates":[106.441,26.1973],"type":"Point"}
}