{
  "type": "Feature",
  "properties": {
    "gn:admin1_code":"19.0",
    "gn:asciiname":"Wanbaocun",
    "gn:country_code":"CN",
    "gn:dem":12,
    "gn:feature_class":"P",
    "gn:feature_code":"PPL",
    "gn:name":"Wanbaocun",
    "gn:population":0,
    "gn:timezone":"Asia/Shanghai",
    "iso:country":"CN",
    "name:zho_x_preferred":[
        "\u4e07\u5b9d\u6751"
    ],
    "wof:name":"Wanbaocun",
    "wof:placetype":"locality"
},
  "geometry": {"coordinates":[124.18471,40.05624],"type":"Point"}
}