{
  "type": "Feature",
  "properties": {
    "gn:admin1_code":"6.0",
    "gn:asciiname":"Eyi",
    "gn:country_code":"CN",
    "gn:dem":2774,
    "gn:feature_class":"P",
    "gn:feature_code":"PPL",
    "gn:name":"Eyi",
    "gn:population":0,
    "gn:timezone":"Asia/Shanghai",
    "iso:country":"CN",
    "name:und_x_variant":[
        "\u9e45\u4f9d"
    ],
    "wof:name":"Eyi",
    "wof:placetype":"locality"
},
  "geometry": {"coordinates":[102.36951000000001,35.98013],"type":"Point"}
}