{
  "type": "Feature",
  "properties": {
    "gn:admin1_code":"33.0",
    "gn:asciiname":"Qingji",
    "gn:country_code":"CN",
    "gn:dem":647,
    "gn:feature_class":"P",
    "gn:feature_code":"PPL",
    "gn:name":"Qingji",
    "gn:population":0,
    "gn:timezone":"Asia/Shanghai",
    "iso:country":"CN",
    "name:vie_x_preferred":[
        "Kh\u00e1nh K\u1ef5"
    ],
    "name:zho_x_preferred":[
        "\u6e05\u5409"
    ],
    "wof:name":"Qingji",
    "wof:placetype":"locality"
},
  "geometry": {"coordinates":[108.05279,30.85333],"type":"Point"}
}