{
  "type": "Feature",
  "properties": {
    "gn:admin1_code":"25.0",
    "gn:asciiname":"Xijujiacun",
    "gn:country_code":"CN",
    "gn:dem":89,
    "gn:feature_class":"P",
    "gn:feature_code":"PPL",
    "gn:name":"Xijujiacun",
    "gn:population":0,
    "gn:timezone":"Asia/Shanghai",
    "iso:country":"CN",
    "name:zho_x_preferred":[
        "\u897f\u5de8\u5bb6\u6751"
    ],
    "wof:name":"Xijujiacun",
    "wof:placetype":"locality"
},
  "geometry": {"coordinates":[120.41238,37.10525],"type":"Point"}
}