{
  "type": "Feature",
  "properties": {
    "gn:admin1_code":"30.0",
    "gn:asciiname":"Quyuan",
    "gn:country_code":"CN",
    "gn:dem":37,
    "gn:feature_class":"P",
    "gn:feature_code":"PPL",
    "gn:name":"Quyuan",
    "gn:population":0,
    "gn:timezone":"Asia/Shanghai",
    "iso:country":"CN",
    "name:zho_x_preferred":[
        "\u66f2\u6e90"
    ],
    "wof:name":"Quyuan",
    "wof:placetype":"locality"
},
  "geometry": {"coordinates":[112.30278,23.26321],"type":"Point"}
}