{
  "type": "Feature",
  "properties": {
    "gn:admin1_code":"26",
    "gn:asciiname":"Caiyuan",
    "gn:country_code":"CN",
    "gn:dem":575,
    "gn:feature_class":"P",
    "gn:feature_code":"PPL",
    "gn:name":"Caiyuan",
    "gn:population":0,
    "gn:timezone":"Asia/Shanghai",
    "iso:country":"CN",
    "name:und_x_variant":[
        "Caiyuancun"
    ],
    "name:zho_x_preferred":[
        "\u83dc\u56ed"
    ],
    "wof:name":"Caiyuan",
    "wof:placetype":"locality"
},
  "geometry": {"coordinates":[108.47806,34.57694],"type":"Point"}
}