{
  "type": "Feature",
  "properties": {
    "gn:admin1_code":"29.0",
    "gn:asciiname":"Bansa",
    "gn:country_code":"CN",
    "gn:dem":1306,
    "gn:feature_class":"P",
    "gn:feature_code":"PPL",
    "gn:name":"Bansa",
    "gn:population":0,
    "gn:timezone":"Asia/Shanghai",
    "iso:country":"CN",
    "name:zho_x_preferred":[
        "\u73ed\u6d12"
    ],
    "wof:name":"Bansa",
    "wof:placetype":"locality"
},
  "geometry": {"coordinates":[100.25,23.2065],"type":"Point"}
}