{
  "type": "Feature",
  "properties": {
    "gn:admin1_code":"30.0",
    "gn:asciiname":"Yongliangwei",
    "gn:country_code":"CN",
    "gn:dem":21,
    "gn:feature_class":"P",
    "gn:feature_code":"PPL",
    "gn:name":"Yongliangwei",
    "gn:population":0,
    "gn:timezone":"Asia/Shanghai",
    "iso:country":"CN",
    "name:zho_x_preferred":[
        "\u6c38\u826f\u56f4"
    ],
    "wof:name":"Yongliangwei",
    "wof:placetype":"locality"
},
  "geometry": {"coordinates":[114.47333,23.31183],"type":"Point"}
}