{
  "type": "Feature",
  "properties": {
    "gn:admin1_code":"30.0",
    "gn:asciiname":"Chengtouchong",
    "gn:country_code":"CN",
    "gn:dem":128,
    "gn:feature_class":"P",
    "gn:feature_code":"PPL",
    "gn:name":"Chengtouchong",
    "gn:population":0,
    "gn:timezone":"Asia/Shanghai",
    "iso:country":"CN",
    "name:zho_x_preferred":[
        "Chengtouchong"
    ],
    "name:zho_x_variant":[
        "\u6210\u5934\u51b2"
    ],
    "wof:name":"Chengtouchong",
    "wof:placetype":"locality"
},
  "geometry": {"coordinates":[112.37083,24.57889],"type":"Point"}
}