{
  "type": "Feature",
  "properties": {
    "gn:admin1_code":"2.0",
    "gn:asciiname":"Goukunong",
    "gn:country_code":"CN",
    "gn:dem":15,
    "gn:feature_class":"P",
    "gn:feature_code":"PPL",
    "gn:name":"Goukunong",
    "gn:population":0,
    "gn:timezone":"Asia/Shanghai",
    "iso:country":"CN",
    "name:und_x_variant":[
        "\u6784\u67af\u5f04"
    ],
    "wof:name":"Goukunong",
    "wof:placetype":"locality"
},
  "geometry": {"coordinates":[120.19983999999999,30.30625],"type":"Point"}
}