{
  "type": "Feature",
  "properties": {
    "gn:admin1_code":"30.0",
    "gn:asciiname":"Gaoluxia",
    "gn:country_code":"CN",
    "gn:dem":317,
    "gn:feature_class":"P",
    "gn:feature_code":"PPL",
    "gn:name":"Gaoluxia",
    "gn:population":0,
    "gn:timezone":"Asia/Shanghai",
    "iso:country":"CN",
    "name:zho_x_preferred":[
        "Gaoluxia"
    ],
    "name:zho_x_variant":[
        "\u9ad8\u8def\u4e0b"
    ],
    "wof:name":"Gaoluxia",
    "wof:placetype":"locality"
},
  "geometry": {"coordinates":[115.31444,24.29167],"type":"Point"}
}