{
  "type": "Feature",
  "properties": {
    "gn:admin1_code":"16.0",
    "gn:asciiname":"Caicheng",
    "gn:country_code":"CN",
    "gn:dem":222,
    "gn:feature_class":"P",
    "gn:feature_code":"PPL",
    "gn:name":"Caicheng",
    "gn:population":0,
    "gn:timezone":"Asia/Shanghai",
    "iso:country":"CN",
    "name:zho_x_preferred":[
        "\u5f69\u627f"
    ],
    "wof:name":"Caicheng",
    "wof:placetype":"locality"
},
  "geometry": {"coordinates":[111.58499999999999,24.0662],"type":"Point"}
}