{
  "type": "Feature",
  "properties": {
    "gn:admin1_code":"26.0",
    "gn:asciiname":"Yaomuyuan",
    "gn:country_code":"CN",
    "gn:dem":704,
    "gn:feature_class":"P",
    "gn:feature_code":"PPL",
    "gn:name":"Yaomuyuan",
    "gn:population":0,
    "gn:timezone":"Asia/Shanghai",
    "iso:country":"CN",
    "name:und_x_variant":[
        "Yao-shui-y\u00fcan",
        "Yaomuyuan",
        "\u836f\u6728\u9662"
    ],
    "wof:name":"Yaomuyuan",
    "wof:placetype":"locality"
},
  "geometry": {"coordinates":[105.97732999999999,33.43569],"type":"Point"}
}