{
  "type": "Feature",
  "properties": {
    "gn:admin1_code":"5.0",
    "gn:asciiname":"Qianzhouzijing",
    "gn:country_code":"CN",
    "gn:dem":135,
    "gn:feature_class":"P",
    "gn:feature_code":"PPL",
    "gn:name":"Qianzhouzijing",
    "gn:population":0,
    "gn:timezone":"Asia/Shanghai",
    "iso:country":"CN",
    "name:zho_x_preferred":[
        "\u524d\u5b99\u5b57\u4e95"
    ],
    "wof:name":"Qianzhouzijing",
    "wof:placetype":"locality"
},
  "geometry": {"coordinates":[124.12202000000001,45.20578],"type":"Point"}
}