{
  "type": "Feature",
  "properties": {
    "gn:admin1_code":"16",
    "gn:asciiname":"Cewai",
    "gn:cc2":"CN",
    "gn:country_code":"CN",
    "gn:dem":358,
    "gn:feature_class":"P",
    "gn:feature_code":"PPL",
    "gn:name":"Cewai",
    "gn:population":0,
    "gn:timezone":"Asia/Shanghai",
    "iso:country":"CN",
    "name:und_x_variant":[
        "Ts\u2019e-wai",
        "Cewai"
    ],
    "wof:name":"Cewai",
    "wof:placetype":"locality"
},
  "geometry": {"coordinates":[106.16916999999999,23.7725],"type":"Point"}
}