{
  "type": "Feature",
  "properties": {
    "gn:admin1_code":"9.0",
    "gn:asciiname":"Beiling",
    "gn:country_code":"CN",
    "gn:dem":666,
    "gn:feature_class":"P",
    "gn:feature_code":"PPL",
    "gn:name":"Beiling",
    "gn:population":0,
    "gn:timezone":"Asia/Shanghai",
    "iso:country":"CN",
    "name:und_x_variant":[
        "\u5317\u5cad",
        "Beiling"
    ],
    "wof:name":"Beiling",
    "wof:placetype":"locality"
},
  "geometry": {"coordinates":[112.17296,33.95151],"type":"Point"}
}