{
  "type": "Feature",
  "properties": {
    "gn:admin1_code":"32.0",
    "gn:asciiname":"Bomo",
    "gn:country_code":"CN",
    "gn:dem":2261,
    "gn:feature_class":"P",
    "gn:feature_code":"PPL",
    "gn:name":"Bomo",
    "gn:population":0,
    "gn:timezone":"Asia/Shanghai",
    "iso:country":"CN",
    "name:zho_x_preferred":[
        "\u6ce2\u83ab"
    ],
    "wof:name":"Bomo",
    "wof:placetype":"locality"
},
  "geometry": {"coordinates":[102.483,28.4482],"type":"Point"}
}