{
  "type": "Feature",
  "properties": {
    "gn:admin1_code":"4.0",
    "gn:asciiname":"Wangjiawei",
    "gn:country_code":"CN",
    "gn:dem":3,
    "gn:feature_class":"P",
    "gn:feature_code":"PPL",
    "gn:name":"Wangjiawei",
    "gn:population":0,
    "gn:timezone":"Asia/Shanghai",
    "iso:country":"CN",
    "name:zho_x_preferred":[
        "Wangjiawei"
    ],
    "name:zho_x_variant":[
        "\u738b\u5bb6\u5729"
    ],
    "wof:name":"Wangjiawei",
    "wof:placetype":"locality"
},
  "geometry": {"coordinates":[120.54080999999999,30.99163],"type":"Point"}
}