{
  "type": "Feature",
  "properties": {
    "gn:admin1_code":"30.0",
    "gn:asciiname":"Shixitang",
    "gn:country_code":"CN",
    "gn:dem":206,
    "gn:feature_class":"P",
    "gn:feature_code":"PPL",
    "gn:name":"Shixitang",
    "gn:population":0,
    "gn:timezone":"Asia/Shanghai",
    "iso:country":"CN",
    "name:zho_x_preferred":[
        "\u77f3\u6eaa\u5858"
    ],
    "wof:name":"Shixitang",
    "wof:placetype":"locality"
},
  "geometry": {"coordinates":[114.605,25.29022],"type":"Point"}
}