{
  "type": "Feature",
  "properties": {
    "gn:admin1_code":"20.0",
    "gn:asciiname":"Xinzhuangwo",
    "gn:country_code":"CN",
    "gn:dem":1678,
    "gn:feature_class":"P",
    "gn:feature_code":"PPL",
    "gn:name":"Xinzhuangwo",
    "gn:population":0,
    "gn:timezone":"Asia/Shanghai",
    "iso:country":"CN",
    "name:und_x_variant":[
        "\u65b0\u5e84\u7a9d"
    ],
    "wof:name":"Xinzhuangwo",
    "wof:placetype":"locality"
},
  "geometry": {"coordinates":[111.94762,39.72708],"type":"Point"}
}