{
  "type": "Feature",
  "properties": {
    "gn:admin1_code":"30.0",
    "gn:asciiname":"Weizheng",
    "gn:country_code":"CN",
    "gn:dem":47,
    "gn:feature_class":"P",
    "gn:feature_code":"PPLA4",
    "gn:name":"Weizheng",
    "gn:population":0,
    "gn:timezone":"Asia/Shanghai",
    "iso:country":"CN",
    "name:und_x_variant":[
        "Wei-cheng",
        "Weizheng",
        "Weizheng Zhen",
        "\u5a01\u6574\u9547"
    ],
    "name:zho_x_preferred":[
        "\u5a01\u6574"
    ],
    "wof:name":"Weizheng",
    "wof:placetype":"locality"
},
  "geometry": {"coordinates":[112.73136,23.65075],"type":"Point"}
}