{
  "type": "Feature",
  "properties": {
    "gn:admin1_code":"32.0",
    "gn:asciiname":"Quanjiagou",
    "gn:country_code":"CN",
    "gn:dem":851,
    "gn:feature_class":"P",
    "gn:feature_code":"PPL",
    "gn:name":"Quanjiagou",
    "gn:population":0,
    "gn:timezone":"Asia/Shanghai",
    "iso:country":"CN",
    "name:zho_x_preferred":[
        "\u6cc9\u5bb6\u6c9f"
    ],
    "wof:name":"Quanjiagou",
    "wof:placetype":"locality"
},
  "geometry": {"coordinates":[105.93809,32.72312],"type":"Point"}
}