{
  "type": "Feature",
  "properties": {
    "gn:admin1_code":"26.0",
    "gn:asciiname":"Wugongtai",
    "gn:country_code":"CN",
    "gn:dem":1563,
    "gn:feature_class":"P",
    "gn:feature_code":"PPL",
    "gn:name":"Wugongtai",
    "gn:population":0,
    "gn:timezone":"Asia/Shanghai",
    "iso:country":"CN",
    "name:zho_x_preferred":[
        "\u8708\u86a3\u53f0"
    ],
    "wof:name":"Wugongtai",
    "wof:placetype":"locality"
},
  "geometry": {"coordinates":[109.89228,34.34177],"type":"Point"}
}