{
  "type": "Feature",
  "properties": {
    "gn:admin1_code":"29.0",
    "gn:asciiname":"Shangdawa",
    "gn:country_code":"CN",
    "gn:dem":1620,
    "gn:feature_class":"P",
    "gn:feature_code":"PPL",
    "gn:name":"Shangdawa",
    "gn:population":0,
    "gn:timezone":"Asia/Shanghai",
    "iso:country":"CN",
    "name:zho_x_preferred":[
        "\u4e0a\u6253\u74e6"
    ],
    "wof:name":"Shangdawa",
    "wof:placetype":"locality"
},
  "geometry": {"coordinates":[99.5269,24.3998],"type":"Point"}
}