{
  "type": "Feature",
  "properties": {
    "gn:admin1_code":"29.0",
    "gn:asciiname":"Nipuluo",
    "gn:country_code":"CN",
    "gn:dem":2266,
    "gn:feature_class":"P",
    "gn:feature_code":"PPL",
    "gn:name":"Nipuluo",
    "gn:population":0,
    "gn:timezone":"Asia/Shanghai",
    "iso:country":"CN",
    "name:zho_x_preferred":[
        "\u5c3c\u666e\u6d1b"
    ],
    "wof:name":"Nipuluo",
    "wof:placetype":"locality"
},
  "geometry": {"coordinates":[98.98099999999999,26.1887],"type":"Point"}
}