{
  "type": "Feature",
  "properties": {
    "gn:admin1_code":"32.0",
    "gn:asciiname":"Zhoujia Buzi",
    "gn:country_code":"CN",
    "gn:dem":1923,
    "gn:feature_class":"P",
    "gn:feature_code":"PPL",
    "gn:name":"Zhoujia Buzi",
    "gn:population":0,
    "gn:timezone":"Asia/Shanghai",
    "iso:country":"CN",
    "name:zho_x_preferred":[
        "\u5468\u5bb6\u5821\u5b50"
    ],
    "wof:name":"Zhoujia Buzi",
    "wof:placetype":"locality"
},
  "geometry": {"coordinates":[102.2159,28.56842],"type":"Point"}
}