{
  "type": "Feature",
  "properties": {
    "gn:admin1_code":"15.0",
    "gn:asciiname":"Sunxinzhuang",
    "gn:country_code":"CN",
    "gn:dem":1896,
    "gn:feature_class":"P",
    "gn:feature_code":"PPL",
    "gn:name":"Sunxinzhuang",
    "gn:population":0,
    "gn:timezone":"Asia/Shanghai",
    "iso:country":"CN",
    "name:zho_x_preferred":[
        "\u5b59\u65b0\u5e84"
    ],
    "wof:name":"Sunxinzhuang",
    "wof:placetype":"locality"
},
  "geometry": {"coordinates":[102.167,38.1792],"type":"Point"}
}