{
  "type": "Feature",
  "properties": {
    "gn:admin1_code":"26",
    "gn:asciiname":"Maowanggou",
    "gn:country_code":"CN",
    "gn:dem":426,
    "gn:feature_class":"P",
    "gn:feature_code":"PPL",
    "gn:name":"Maowanggou",
    "gn:population":0,
    "gn:timezone":"Asia/Shanghai",
    "iso:country":"CN",
    "name:zho_x_preferred":[
        "\u6bdb\u738b\u6c9f"
    ],
    "wof:name":"Maowanggou",
    "wof:placetype":"locality"
},
  "geometry": {"coordinates":[108.82871000000002,34.41403],"type":"Point"}
}