{
  "type": "Feature",
  "properties": {
    "gn:admin1_code":"19.0",
    "gn:asciiname":"Shuitaling",
    "gn:country_code":"CN",
    "gn:dem":142,
    "gn:feature_class":"P",
    "gn:feature_code":"PPL",
    "gn:name":"Shuitaling",
    "gn:population":0,
    "gn:timezone":"Asia/Shanghai",
    "iso:country":"CN",
    "name:zho_x_preferred":[
        "\u6c34\u736d\u5cad"
    ],
    "wof:name":"Shuitaling",
    "wof:placetype":"locality"
},
  "geometry": {"coordinates":[123.42847,40.60152],"type":"Point"}
}