{
  "type": "Feature",
  "properties": {
    "gn:admin1_code":"15.0",
    "gn:asciiname":"Sumucheng",
    "gn:country_code":"CN",
    "gn:dem":2825,
    "gn:feature_class":"P",
    "gn:feature_code":"PPL",
    "gn:name":"Sumucheng",
    "gn:population":0,
    "gn:timezone":"Asia/Shanghai",
    "iso:country":"CN",
    "name:und_x_variant":[
        "\u82cf\u6728\u57ce"
    ],
    "wof:name":"Sumucheng",
    "wof:placetype":"locality"
},
  "geometry": {"coordinates":[103.74071000000001,34.71958],"type":"Point"}
}