{
  "type": "Feature",
  "properties": {
    "gn:admin1_code":"14.0",
    "gn:asciiname":"Xialacun",
    "gn:country_code":"CN",
    "gn:dem":3843,
    "gn:feature_class":"P",
    "gn:feature_code":"PPL",
    "gn:name":"Xialacun",
    "gn:population":0,
    "gn:timezone":"Asia/Urumqi",
    "iso:country":"CN",
    "name:zho_x_preferred":[
        "\u590f\u62c9\u6751"
    ],
    "wof:name":"Xialacun",
    "wof:placetype":"locality"
},
  "geometry": {"coordinates":[95.68947,31.35915],"type":"Point"}
}