{
  "type": "Feature",
  "properties": {
    "gn:admin1_code":"4.0",
    "gn:asciiname":"Boli",
    "gn:country_code":"CN",
    "gn:dem":0,
    "gn:feature_class":"P",
    "gn:feature_code":"PPL",
    "gn:name":"Boli",
    "gn:population":0,
    "gn:timezone":"Asia/Shanghai",
    "iso:country":"CN",
    "name:bar_x_preferred":[
        "Boli"
    ],
    "name:ceb_x_preferred":[
        "Boli"
    ],
    "name:deu_x_preferred":[
        "Boli"
    ],
    "name:fin_x_preferred":[
        "Boli"
    ],
    "name:fra_x_preferred":[
        "Boli"
    ],
    "name:rus_x_preferred":[
        "\u0411\u043e\u043b\u0438"
    ],
    "name:spa_x_preferred":[
        "Boli"
    ],
    "name:srp_x_preferred":[
        "\u0411\u043e\u043b\u0438"
    ],
    "name:swe_x_preferred":[
        "Boli"
    ],
    "name:ukr_x_preferred":[
        "\u0411\u043e\u043b\u0456"
    ],
    "wof:name":"Boli",
    "wof:placetype":"locality"
},
  "geometry": {"coordinates":[119.45,33.51667],"type":"Point"}
}