{
  "type": "Feature",
  "properties": {
    "gn:admin1_code":"07",
    "gn:asciiname":"Yongshui",
    "gn:country_code":"CN",
    "gn:dem":725,
    "gn:feature_class":"P",
    "gn:feature_code":"PPL",
    "gn:name":"Yongshui",
    "gn:population":0,
    "gn:timezone":"Asia/Shanghai",
    "iso:country":"CN",
    "name:zho_x_preferred":[
        "\u6c38\u6c34"
    ],
    "wof:name":"Yongshui",
    "wof:placetype":"locality"
},
  "geometry": {"coordinates":[118.08722,25.49917],"type":"Point"}
}