{
  "type": "Feature",
  "properties": {
    "gn:admin1_code":"32.0",
    "gn:asciiname":"Laoxia'erhu",
    "gn:country_code":"CN",
    "gn:dem":2521,
    "gn:feature_class":"P",
    "gn:feature_code":"PPL",
    "gn:name":"Laoxia\u2019erhu",
    "gn:population":0,
    "gn:timezone":"Asia/Shanghai",
    "iso:country":"CN",
    "name:und_x_variant":[
        "Laoxia\u2019erhu"
    ],
    "name:zho_x_preferred":[
        "\u8001\u5477\u513f\u864e"
    ],
    "wof:name":"Laoxia'erhu",
    "wof:placetype":"locality"
},
  "geometry": {"coordinates":[102.529,28.1187],"type":"Point"}
}