{
  "type": "Feature",
  "properties": {
    "gn:admin1_code":"21.0",
    "gn:asciiname":"Dingnan Qidui",
    "gn:country_code":"CN",
    "gn:dem":1102,
    "gn:feature_class":"P",
    "gn:feature_code":"PPLF",
    "gn:name":"Dingnan Qidui",
    "gn:population":0,
    "gn:timezone":"Asia/Shanghai",
    "iso:country":"CN",
    "name:zho_x_preferred":[
        "\u4e01\u5357\u4e03\u961f"
    ],
    "wof:name":"Dingnan Qidui",
    "wof:placetype":"locality"
},
  "geometry": {"coordinates":[106.386,38.6689],"type":"Point"}
}