{
  "type": "Feature",
  "properties": {
    "gn:admin1_code":"18",
    "gn:asciiname":"Zhuyuantai",
    "gn:country_code":"CN",
    "gn:dem":1032,
    "gn:feature_class":"P",
    "gn:feature_code":"PPL",
    "gn:name":"Zhuyuantai",
    "gn:population":0,
    "gn:timezone":"Asia/Shanghai",
    "iso:country":"CN",
    "name:zho_x_preferred":[
        "\u7af9\u56ed\u53f0"
    ],
    "wof:name":"Zhuyuantai",
    "wof:placetype":"locality"
},
  "geometry": {"coordinates":[107.327,27.8403],"type":"Point"}
}