{
  "type": "Feature",
  "properties": {
    "gn:admin1_code":"5.0",
    "gn:asciiname":"Zhoujia Tuozi",
    "gn:country_code":"CN",
    "gn:dem":228,
    "gn:feature_class":"P",
    "gn:feature_code":"PPL",
    "gn:name":"Zhoujia Tuozi",
    "gn:population":0,
    "gn:timezone":"Asia/Shanghai",
    "iso:country":"CN",
    "name:zho_x_preferred":[
        "\u5468\u5bb6\u5768\u5b50"
    ],
    "wof:name":"Zhoujia Tuozi",
    "wof:placetype":"locality"
},
  "geometry": {"coordinates":[124.99063,44.67777],"type":"Point"}
}