{
  "type": "Feature",
  "properties": {
    "gn:admin1_code":"8.0",
    "gn:asciiname":"Deshengtun",
    "gn:country_code":"CN",
    "gn:dem":130,
    "gn:feature_class":"P",
    "gn:feature_code":"PPL",
    "gn:name":"Deshengtun",
    "gn:population":0,
    "gn:timezone":"Asia/Shanghai",
    "iso:country":"CN",
    "name:zho_x_preferred":[
        "\u5f97\u80dc\u5c6f"
    ],
    "wof:name":"Deshengtun",
    "wof:placetype":"locality"
},
  "geometry": {"coordinates":[124.43678,45.66238],"type":"Point"}
}