{
  "type": "Feature",
  "properties": {
    "gn:admin1_code":"12.0",
    "gn:asciiname":"Bailuowan",
    "gn:country_code":"CN",
    "gn:dem":21,
    "gn:feature_class":"P",
    "gn:feature_code":"PPL",
    "gn:name":"Bailuowan",
    "gn:population":0,
    "gn:timezone":"Asia/Shanghai",
    "iso:country":"CN",
    "name:und_x_variant":[
        "\u767e\u7f57\u6e7e"
    ],
    "wof:name":"Bailuowan",
    "wof:placetype":"locality"
},
  "geometry": {"coordinates":[114.72019,30.43591],"type":"Point"}
}