{
  "type": "Feature",
  "properties": {
    "gn:admin1_code":"29.0",
    "gn:asciiname":"Dushuijing",
    "gn:country_code":"CN",
    "gn:dem":1868,
    "gn:feature_class":"P",
    "gn:feature_code":"PPL",
    "gn:name":"Dushuijing",
    "gn:population":0,
    "gn:timezone":"Asia/Shanghai",
    "iso:country":"CN",
    "name:zho_x_preferred":[
        "\u72ec\u6c34\u4e95"
    ],
    "wof:name":"Dushuijing",
    "wof:placetype":"locality"
},
  "geometry": {"coordinates":[99.4015,24.006],"type":"Point"}
}