{
  "type": "Feature",
  "properties": {
    "gn:admin1_code":"5.0",
    "gn:asciiname":"Huapi",
    "gn:country_code":"CN",
    "gn:dem":353,
    "gn:feature_class":"P",
    "gn:feature_code":"PPL",
    "gn:name":"Huapi",
    "gn:population":0,
    "gn:timezone":"Asia/Shanghai",
    "iso:country":"CN",
    "name:und_x_variant":[
        "\u6866\u76ae"
    ],
    "wof:name":"Huapi",
    "wof:placetype":"locality"
},
  "geometry": {"coordinates":[126.52798,41.50758],"type":"Point"}
}