{
  "type": "Feature",
  "properties": {
    "gn:admin1_code":"4.0",
    "gn:asciiname":"Xiadai",
    "gn:country_code":"CN",
    "gn:dem":1,
    "gn:feature_class":"P",
    "gn:feature_code":"PPL",
    "gn:name":"Xiadai",
    "gn:population":0,
    "gn:timezone":"Asia/Shanghai",
    "iso:country":"CN",
    "name:zho_x_preferred":[
        "\u590f\u5cb1"
    ],
    "wof:name":"Xiadai",
    "wof:placetype":"locality"
},
  "geometry": {"coordinates":[120.38,32.2957],"type":"Point"}
}