{
  "type": "Feature",
  "properties": {
    "gn:admin1_code":"32.0",
    "gn:asciiname":"Baishasi",
    "gn:country_code":"CN",
    "gn:dem":503,
    "gn:feature_class":"P",
    "gn:feature_code":"PPL",
    "gn:name":"Baishasi",
    "gn:population":0,
    "gn:timezone":"Asia/Shanghai",
    "iso:country":"CN",
    "name:zho_x_preferred":[
        "\u767d\u6c99\u5bfa"
    ],
    "wof:name":"Baishasi",
    "wof:placetype":"locality"
},
  "geometry": {"coordinates":[104.846,31.6027],"type":"Point"}
}