{
  "type": "Feature",
  "properties": {
    "gn:admin1_code":"19.0",
    "gn:asciiname":"Mengguyingzi",
    "gn:country_code":"CN",
    "gn:dem":342,
    "gn:feature_class":"P",
    "gn:feature_code":"PPL",
    "gn:name":"Mengguyingzi",
    "gn:population":0,
    "gn:timezone":"Asia/Shanghai",
    "iso:country":"CN",
    "name:zho_x_preferred":[
        "\u8499\u53e4\u8425\u5b50"
    ],
    "wof:name":"Mengguyingzi",
    "wof:placetype":"locality"
},
  "geometry": {"coordinates":[119.077,40.7796],"type":"Point"}
}