{
  "type": "Feature",
  "properties": {
    "gn:admin1_code":"9.0",
    "gn:asciiname":"Limaiyao",
    "gn:country_code":"CN",
    "gn:dem":495,
    "gn:feature_class":"P",
    "gn:feature_code":"PPL",
    "gn:name":"Limaiyao",
    "gn:population":0,
    "gn:timezone":"Asia/Shanghai",
    "iso:country":"CN",
    "name:zho_x_preferred":[
        "\u91cc\u9ea6\u7a91"
    ],
    "wof:name":"Limaiyao",
    "wof:placetype":"locality"
},
  "geometry": {"coordinates":[113.69663,35.79324000000001],"type":"Point"}
}