{
  "type": "Feature",
  "properties": {
    "gn:admin1_code":"25",
    "gn:asciiname":"Suchengwang",
    "gn:country_code":"CN",
    "gn:dem":70,
    "gn:feature_class":"P",
    "gn:feature_code":"PPL",
    "gn:name":"Suchengwang",
    "gn:population":0,
    "gn:timezone":"Asia/Shanghai",
    "iso:country":"CN",
    "name:zho_x_preferred":[
        "\u82cf\u5448\u65fa"
    ],
    "wof:name":"Suchengwang",
    "wof:placetype":"locality"
},
  "geometry": {"coordinates":[118.554,35.1776],"type":"Point"}
}