{
  "type": "Feature",
  "properties": {
    "gn:admin1_code":"16.0",
    "gn:asciiname":"Fadang",
    "gn:country_code":"CN",
    "gn:dem":627,
    "gn:feature_class":"P",
    "gn:feature_code":"PPL",
    "gn:name":"Fadang",
    "gn:population":0,
    "gn:timezone":"Asia/Shanghai",
    "iso:country":"CN",
    "name:zho_x_preferred":[
        "\u53d1\u6321"
    ],
    "wof:name":"Fadang",
    "wof:placetype":"locality"
},
  "geometry": {"coordinates":[105.535,24.2996],"type":"Point"}
}