{
  "type": "Feature",
  "properties": {
    "gn:admin1_code":"29",
    "gn:asciiname":"Toudian",
    "gn:country_code":"CN",
    "gn:dem":2052,
    "gn:feature_class":"P",
    "gn:feature_code":"PPL",
    "gn:name":"Toudian",
    "gn:population":0,
    "gn:timezone":"Asia/Shanghai",
    "iso:country":"CN",
    "name:zho_x_preferred":[
        "\u5934\u7538"
    ],
    "wof:name":"Toudian",
    "wof:placetype":"locality"
},
  "geometry": {"coordinates":[102.92591,24.95841],"type":"Point"}
}