{
  "type": "Feature",
  "properties": {
    "gn:admin1_code":"8.0",
    "gn:asciiname":"Hanbodai",
    "gn:country_code":"CN",
    "gn:dem":154,
    "gn:feature_class":"P",
    "gn:feature_code":"PPL",
    "gn:name":"Hanbodai",
    "gn:population":0,
    "gn:timezone":"Asia/Shanghai",
    "iso:country":"CN",
    "name:zho_x_preferred":[
        "\u7f55\u4f2f\u5cb1"
    ],
    "wof:name":"Hanbodai",
    "wof:placetype":"locality"
},
  "geometry": {"coordinates":[123.54933,47.0951],"type":"Point"}
}