{
  "type": "Feature",
  "properties": {
    "gn:admin1_code":"19.0",
    "gn:asciiname":"Machengye",
    "gn:country_code":"CN",
    "gn:dem":80,
    "gn:feature_class":"P",
    "gn:feature_code":"PPL",
    "gn:name":"Machengye",
    "gn:population":0,
    "gn:timezone":"Asia/Shanghai",
    "iso:country":"CN",
    "name:zho_x_preferred":[
        "\u9a6c\u6210\u4e1a"
    ],
    "wof:name":"Machengye",
    "wof:placetype":"locality"
},
  "geometry": {"coordinates":[120.87421000000001,40.98526],"type":"Point"}
}