{
  "type": "Feature",
  "properties": {
    "gn:admin1_code":"3.0",
    "gn:asciiname":"Qirenshi",
    "gn:country_code":"CN",
    "gn:dem":733,
    "gn:feature_class":"P",
    "gn:feature_code":"PPL",
    "gn:name":"Qirenshi",
    "gn:population":0,
    "gn:timezone":"Asia/Shanghai",
    "iso:country":"CN",
    "name:zho_x_preferred":[
        "\u4f01\u4eba\u77f3"
    ],
    "wof:name":"Qirenshi",
    "wof:placetype":"locality"
},
  "geometry": {"coordinates":[115.754,24.6502],"type":"Point"}
}