{
  "type": "Feature",
  "properties": {
    "gn:admin1_code":"11.0",
    "gn:asciiname":"Ma'achong",
    "gn:country_code":"CN",
    "gn:dem":136,
    "gn:feature_class":"P",
    "gn:feature_code":"PPL",
    "gn:name":"Ma\u2019achong",
    "gn:population":0,
    "gn:timezone":"Asia/Shanghai",
    "iso:country":"CN",
    "name:und_x_variant":[
        "Ma\u2019achong"
    ],
    "name:zho_x_preferred":[
        "\u9a6c\u963f\u51b2"
    ],
    "wof:name":"Ma'achong",
    "wof:placetype":"locality"
},
  "geometry": {"coordinates":[112.38343999999999,28.45802],"type":"Point"}
}