{
  "type": "Feature",
  "properties": {
    "gn:admin1_code":"10",
    "gn:asciiname":"Lijia Wopu",
    "gn:country_code":"CN",
    "gn:dem":969,
    "gn:feature_class":"P",
    "gn:feature_code":"PPL",
    "gn:name":"Lijia Wopu",
    "gn:population":0,
    "gn:timezone":"Asia/Shanghai",
    "iso:country":"CN",
    "name:zho_x_preferred":[
        "\u674e\u5bb6\u7a9d\u94fa"
    ],
    "wof:name":"Lijia Wopu",
    "wof:placetype":"locality"
},
  "geometry": {"coordinates":[116.95186,41.52997],"type":"Point"}
}