{
  "type": "Feature",
  "properties": {
    "gn:admin1_code":"10",
    "gn:asciiname":"Hailiutu",
    "gn:country_code":"CN",
    "gn:dem":1338,
    "gn:feature_class":"P",
    "gn:feature_code":"PPL",
    "gn:name":"Hailiutu",
    "gn:population":0,
    "gn:timezone":"Asia/Shanghai",
    "iso:country":"CN",
    "name:zho_x_preferred":[
        "\u6d77\u6d41\u56fe"
    ],
    "wof:name":"Hailiutu",
    "wof:placetype":"locality"
},
  "geometry": {"coordinates":[115.20493,41.08895],"type":"Point"}
}