{
  "type": "Feature",
  "properties": {
    "gn:admin1_code":"18",
    "gn:asciiname":"Aotian",
    "gn:country_code":"CN",
    "gn:dem":770,
    "gn:feature_class":"P",
    "gn:feature_code":"PPL",
    "gn:name":"Aotian",
    "gn:population":0,
    "gn:timezone":"Asia/Shanghai",
    "iso:country":"CN",
    "name:zho_x_preferred":[
        "\u5773\u7530"
    ],
    "wof:name":"Aotian",
    "wof:placetype":"locality"
},
  "geometry": {"coordinates":[107.831,27.5606],"type":"Point"}
}