{
  "type": "Feature",
  "properties": {
    "gn:admin1_code":"14.0",
    "gn:asciiname":"Guoyu",
    "gn:country_code":"CN",
    "gn:dem":3905,
    "gn:feature_class":"P",
    "gn:feature_code":"PPL",
    "gn:name":"Guoyu",
    "gn:population":0,
    "gn:timezone":"Asia/Urumqi",
    "iso:country":"CN",
    "name:deu_x_preferred":[
        "Guoyu"
    ],
    "name:fra_x_preferred":[
        "Guoyu"
    ],
    "name:slk_x_preferred":[
        "Kuo-j\u00fc"
    ],
    "name:zho_x_preferred":[
        "\u90ed\u7389"
    ],
    "wof:name":"Guoyu",
    "wof:placetype":"locality"
},
  "geometry": {"coordinates":[98.44145,31.20411],"type":"Point"}
}