{
  "type": "Feature",
  "properties": {
    "gn:admin1_code":"14.0",
    "gn:asciiname":"Waidoi",
    "gn:country_code":"CN",
    "gn:dem":4866,
    "gn:feature_class":"P",
    "gn:feature_code":"PPLF",
    "gn:name":"Waidoi",
    "gn:population":0,
    "gn:timezone":"Asia/Urumqi",
    "iso:country":"CN",
    "name:bod_x_preferred":[
        "Waidoi"
    ],
    "name:zho_x_preferred":[
        "Wadui"
    ],
    "name:zho_x_variant":[
        "\u74e6\u5806",
        "Layu",
        "\u62c9\u7389"
    ],
    "wof:name":"Waidoi",
    "wof:placetype":"locality"
},
  "geometry": {"coordinates":[97.40300000000001,29.603],"type":"Point"}
}