{
  "type": "Feature",
  "properties": {
    "gn:admin1_code":"5.0",
    "gn:asciiname":"Gaojia Wopeng",
    "gn:country_code":"CN",
    "gn:dem":170,
    "gn:feature_class":"P",
    "gn:feature_code":"PPL",
    "gn:name":"Gaojia Wopeng",
    "gn:population":0,
    "gn:timezone":"Asia/Shanghai",
    "iso:country":"CN",
    "name:zho_x_preferred":[
        "\u9ad8\u5bb6\u7a9d\u68da"
    ],
    "wof:name":"Gaojia Wopeng",
    "wof:placetype":"locality"
},
  "geometry": {"coordinates":[126.42419,44.36219000000001],"type":"Point"}
}