{
  "type": "Feature",
  "properties": {
    "gn:admin1_code":"18.0",
    "gn:asciiname":"Bidong",
    "gn:country_code":"CN",
    "gn:dem":540,
    "gn:feature_class":"P",
    "gn:feature_code":"PPL",
    "gn:name":"Bidong",
    "gn:population":0,
    "gn:timezone":"Asia/Shanghai",
    "iso:country":"CN",
    "name:zho_x_preferred":[
        "\u4ffe\u6d1e"
    ],
    "wof:name":"Bidong",
    "wof:placetype":"locality"
},
  "geometry": {"coordinates":[108.47799999999999,26.0111],"type":"Point"}
}