{
  "type": "Feature",
  "properties": {
    "gn:admin1_code":"2.0",
    "gn:asciiname":"Xili",
    "gn:country_code":"CN",
    "gn:dem":201,
    "gn:feature_class":"P",
    "gn:feature_code":"PPL",
    "gn:name":"Xili",
    "gn:population":0,
    "gn:timezone":"Asia/Shanghai",
    "iso:country":"CN",
    "name:und_x_variant":[
        "\u6eaa\u91cc"
    ],
    "wof:name":"Xili",
    "wof:placetype":"locality"
},
  "geometry": {"coordinates":[119.60868000000001,30.32988],"type":"Point"}
}