{
  "type": "Feature",
  "properties": {
    "gn:admin1_code":"30.0",
    "gn:asciiname":"Siwangpingcun",
    "gn:country_code":"CN",
    "gn:dem":556,
    "gn:feature_class":"P",
    "gn:feature_code":"PPL",
    "gn:name":"Siwangpingcun",
    "gn:population":0,
    "gn:timezone":"Asia/Shanghai",
    "iso:country":"CN",
    "name:und_x_variant":[
        "Siwangping"
    ],
    "name:zho_x_preferred":[
        "\u56db\u671b\u576a\u6751"
    ],
    "name:zho_x_variant":[
        "\u56db\u671b\u576a"
    ],
    "wof:name":"Siwangpingcun",
    "wof:placetype":"locality"
},
  "geometry": {"coordinates":[116.5633,23.89868],"type":"Point"}
}