{
  "type": "Feature",
  "properties": {
    "gn:admin1_code":"29.0",
    "gn:asciiname":"Sandaohe",
    "gn:country_code":"CN",
    "gn:dem":2156,
    "gn:feature_class":"P",
    "gn:feature_code":"PPL",
    "gn:name":"Sandaohe",
    "gn:population":0,
    "gn:timezone":"Asia/Shanghai",
    "iso:country":"CN",
    "name:und_x_variant":[
        "\u4e09\u9053\u6cb3"
    ],
    "wof:name":"Sandaohe",
    "wof:placetype":"locality"
},
  "geometry": {"coordinates":[102.50618,25.93458],"type":"Point"}
}