{
  "type": "Feature",
  "properties": {
    "gn:admin1_code":"4.0",
    "gn:asciiname":"Liujiashe",
    "gn:country_code":"CN",
    "gn:dem":-1,
    "gn:feature_class":"P",
    "gn:feature_code":"PPL",
    "gn:name":"Liujiashe",
    "gn:population":0,
    "gn:timezone":"Asia/Shanghai",
    "iso:country":"CN",
    "name:zho_x_preferred":[
        "Liujiashe"
    ],
    "name:zho_x_variant":[
        "\u5218\u5bb6\u820d"
    ],
    "wof:name":"Liujiashe",
    "wof:placetype":"locality"
},
  "geometry": {"coordinates":[119.83448,33.52417],"type":"Point"}
}