{
  "type": "Feature",
  "properties": {
    "gn:admin1_code":"19.0",
    "gn:asciiname":"Nanchang",
    "gn:country_code":"CN",
    "gn:dem":233,
    "gn:feature_class":"P",
    "gn:feature_code":"PPL",
    "gn:name":"Nanchang",
    "gn:population":0,
    "gn:timezone":"Asia/Shanghai",
    "iso:country":"CN",
    "name:und_x_variant":[
        "\u5357\u573a"
    ],
    "name:zho_x_preferred":[
        "\u5357\u573a"
    ],
    "wof:name":"Nanchang",
    "wof:placetype":"locality"
},
  "geometry": {"coordinates":[122.56100000000001,42.7329],"type":"Point"}
}