{
  "type": "Feature",
  "properties": {
    "gn:admin1_code":"29.0",
    "gn:asciiname":"Yubo",
    "gn:country_code":"CN",
    "gn:dem":1346,
    "gn:feature_class":"P",
    "gn:feature_code":"PPL",
    "gn:name":"Yubo",
    "gn:population":0,
    "gn:timezone":"Asia/Shanghai",
    "iso:country":"CN",
    "name:zho_x_preferred":[
        "\u96e8\u6ce2"
    ],
    "wof:name":"Yubo",
    "wof:placetype":"locality"
},
  "geometry": {"coordinates":[104.34,23.012],"type":"Point"}
}