{
  "type": "Feature",
  "properties": {
    "gn:admin1_code":"15.0",
    "gn:asciiname":"Youfangzhuang",
    "gn:country_code":"CN",
    "gn:dem":1730,
    "gn:feature_class":"P",
    "gn:feature_code":"PPL",
    "gn:name":"Youfangzhuang",
    "gn:population":0,
    "gn:timezone":"Asia/Shanghai",
    "iso:country":"CN",
    "name:und_x_variant":[
        "\u6cb9\u623f\u5e84"
    ],
    "wof:name":"Youfangzhuang",
    "wof:placetype":"locality"
},
  "geometry": {"coordinates":[106.69036,36.28962],"type":"Point"}
}