{
  "type": "Feature",
  "properties": {
    "gn:admin1_code":"30",
    "gn:asciiname":"Gaoshan",
    "gn:country_code":"CN",
    "gn:dem":21,
    "gn:feature_class":"P",
    "gn:feature_code":"PPLA4",
    "gn:name":"Gaoshan",
    "gn:population":0,
    "gn:timezone":"Asia/Urumqi",
    "iso:country":"CN",
    "name:und_x_variant":[
        "Gaoshan Zhen",
        "\u9ad8\u5c71\u9547"
    ],
    "name:zho_x_preferred":[
        "\u9ad8\u5c71"
    ],
    "wof:name":"Gaoshan",
    "wof:placetype":"locality"
},
  "geometry": {"coordinates":[110.89829,21.6544],"type":"Point"}
}