{
  "type": "Feature",
  "properties": {
    "gn:admin1_code":"5.0",
    "gn:asciiname":"Hexingcun",
    "gn:country_code":"CN",
    "gn:dem":422,
    "gn:feature_class":"P",
    "gn:feature_code":"PPL",
    "gn:name":"Hexingcun",
    "gn:population":0,
    "gn:timezone":"Asia/Shanghai",
    "iso:country":"CN",
    "name:zho_x_preferred":[
        "\u6cb3\u5174\u6751"
    ],
    "wof:name":"Hexingcun",
    "wof:placetype":"locality"
},
  "geometry": {"coordinates":[125.28856,42.5683],"type":"Point"}
}