{
  "type": "Feature",
  "properties": {
    "gn:admin1_code":"8.0",
    "gn:asciiname":"Lumincun",
    "gn:country_code":"CN",
    "gn:dem":209,
    "gn:feature_class":"P",
    "gn:feature_code":"PPL",
    "gn:name":"Lumincun",
    "gn:population":0,
    "gn:timezone":"Asia/Shanghai",
    "iso:country":"CN",
    "name:zho_x_preferred":[
        "\u9c81\u6c11\u6751"
    ],
    "wof:name":"Lumincun",
    "wof:placetype":"locality"
},
  "geometry": {"coordinates":[125.04349999999999,48.41922],"type":"Point"}
}