{
  "type": "Feature",
  "properties": {
    "gn:admin1_code":"10",
    "gn:asciiname":"Xiangshan",
    "gn:country_code":"CN",
    "gn:dem":185,
    "gn:feature_class":"P",
    "gn:feature_code":"PPL",
    "gn:name":"Xiangshan",
    "gn:population":0,
    "gn:timezone":"Asia/Shanghai",
    "iso:country":"CN",
    "name:ceb_x_preferred":[
        "Xiangshan"
    ],
    "name:deu_x_preferred":[
        "Xiangshan"
    ],
    "name:eus_x_preferred":[
        "Xiangshan"
    ],
    "name:fra_x_preferred":[
        "Xiangshan"
    ],
    "name:kor_x_preferred":[
        "\uc0f9\uc0b0\uad6c"
    ],
    "name:nor_x_preferred":[
        "Xiangshan"
    ],
    "name:pol_x_preferred":[
        "Xiangshan"
    ],
    "name:swe_x_preferred":[
        "Xiangshan"
    ],
    "name:zho_x_preferred":[
        "\u9999\u5c71"
    ],
    "wof:name":"Xiangshan",
    "wof:placetype":"locality"
},
  "geometry": {"coordinates":[114.253,36.5193],"type":"Point"}
}