{
  "type": "Feature",
  "properties": {
    "gn:admin1_code":"19.0",
    "gn:asciiname":"Shaolinzi",
    "gn:country_code":"CN",
    "gn:dem":33,
    "gn:feature_class":"P",
    "gn:feature_code":"PPL",
    "gn:name":"Shaolinzi",
    "gn:population":0,
    "gn:timezone":"Asia/Shanghai",
    "iso:country":"CN",
    "name:zho_x_preferred":[
        "\u90b5\u6797\u5b50"
    ],
    "wof:name":"Shaolinzi",
    "wof:placetype":"locality"
},
  "geometry": {"coordinates":[123.27433000000001,41.60289],"type":"Point"}
}