{
  "type": "Feature",
  "properties": {
    "gn:admin1_code":"14.0",
    "gn:asciiname":"Tongqiong",
    "gn:country_code":"CN",
    "gn:dem":4023,
    "gn:feature_class":"P",
    "gn:feature_code":"PPL",
    "gn:name":"Tongqiong",
    "gn:population":0,
    "gn:timezone":"Asia/Urumqi",
    "iso:country":"CN",
    "name:zho_x_preferred":[
        "\u901a\u7a77"
    ],
    "wof:name":"Tongqiong",
    "wof:placetype":"locality"
},
  "geometry": {"coordinates":[96.19042,29.83409],"type":"Point"}
}