{
  "type": "Feature",
  "properties": {
    "gn:admin1_code":"24.0",
    "gn:asciiname":"Nanpocun",
    "gn:country_code":"CN",
    "gn:dem":821,
    "gn:feature_class":"P",
    "gn:feature_code":"PPL",
    "gn:name":"Nanpocun",
    "gn:population":0,
    "gn:timezone":"Asia/Shanghai",
    "iso:country":"CN",
    "name:zho_x_preferred":[
        "\u5357\u5761\u6751"
    ],
    "wof:name":"Nanpocun",
    "wof:placetype":"locality"
},
  "geometry": {"coordinates":[110.73327999999999,37.38582],"type":"Point"}
}