{
  "type": "Feature",
  "properties": {
    "gn:admin1_code":"26.0",
    "gn:asciiname":"Gaoqiaojie",
    "gn:country_code":"CN",
    "gn:dem":1070,
    "gn:feature_class":"P",
    "gn:feature_code":"PPL",
    "gn:name":"Gaoqiaojie",
    "gn:population":0,
    "gn:timezone":"Asia/Shanghai",
    "iso:country":"CN",
    "name:zho_x_preferred":[
        "\u9ad8\u6865\u8857"
    ],
    "wof:name":"Gaoqiaojie",
    "wof:placetype":"locality"
},
  "geometry": {"coordinates":[108.54196,33.71739],"type":"Point"}
}