{
  "type": "Feature",
  "properties": {
    "gn:country":"CN",
    "gn:fcode":"PPL",
    "gn:pop":138704,
    "iso:country":"CN",
    "name:unk_x_variant":[
        "Hsin-ch\u2019eng"
    ],
    "ne:ADM0CAP":0.0,
    "ne:ADM0NAME":"China",
    "ne:ADM0_A3":"CHN",
    "ne:ADM1NAME":"Jilin",
    "ne:ADMIN1_COD":5,
    "ne:CAPALT":0,
    "ne:CHANGED":0,
    "ne:CHECKME":0,
    "ne:COMPARE":0,
    "ne:DIFFASCII":0,
    "ne:ELEVATION":0.0,
    "ne:FEATURECLA":"Populated place",
    "ne:FEATURE_CL":"P",
    "ne:FEATURE_CO":"PPL",
    "ne:GEONAMEID":2037335,
    "ne:GEONAMESNO":"Geonames ascii name + lat.d + long.d matching.",
    "ne:GN_ASCII":"Fuyu",
    "ne:GN_POP":138704,
    "ne:GTOPO30":141.0,
    "ne:ISO_A2":"CN",
    "ne:LABELRANK":1,
    "ne:LATITUDE":45.18038,
    "ne:LONGITUDE":124.820019,
    "ne:LS_MATCH":1,
    "ne:LS_NAME":"Fuyu",
    "ne:MAX_AREAKM":113.0,
    "ne:MAX_AREAMI":44.0,
    "ne:MAX_BBXMAX":124.9,
    "ne:MAX_BBXMIN":124.733333,
    "ne:MAX_BBYMAX":45.266667,
    "ne:MAX_BBYMIN":45.066667,
    "ne:MAX_NATSCA":20.0,
    "ne:MAX_PERKM":122.0,
    "ne:MAX_PERMI":76.0,
    "ne:MAX_POP10":356905,
    "ne:MAX_POP20":356905,
    "ne:MAX_POP300":0,
    "ne:MAX_POP310":0,
    "ne:MAX_POP50":0,
    "ne:MEAN_BBXC":124.82119,
    "ne:MEAN_BBYC":45.170655,
    "ne:MEGACITY":0,
    "ne:MIN_AREAKM":113.0,
    "ne:MIN_AREAMI":44.0,
    "ne:MIN_BBXMAX":124.9,
    "ne:MIN_BBXMIN":124.733333,
    "ne:MIN_BBYMAX":45.266667,
    "ne:MIN_BBYMIN":45.066667,
    "ne:MIN_PERKM":122.0,
    "ne:MIN_PERMI":76.0,
    "ne:NAME":"Fuyu",
    "ne:NAMEASCII":"Fuyu",
    "ne:NAMEDIFF":0,
    "ne:NATSCALE":20,
    "ne:POP1950":0,
    "ne:POP1955":0,
    "ne:POP1960":0,
    "ne:POP1965":0,
    "ne:POP1970":0,
    "ne:POP1975":0,
    "ne:POP1980":0,
    "ne:POP1985":0,
    "ne:POP1990":0,
    "ne:POP1995":0,
    "ne:POP2000":0,
    "ne:POP2005":0,
    "ne:POP2010":0,
    "ne:POP2015":0,
    "ne:POP2020":0,
    "ne:POP2025":0,
    "ne:POP2050":0,
    "ne:POP_MAX":356905,
    "ne:POP_MIN":138704,
    "ne:POP_OTHER":345980,
    "ne:RANK_MAX":10,
    "ne:RANK_MIN":9,
    "ne:SCALERANK":7,
    "ne:SOV0NAME":"China",
    "ne:SOV_A3":"CHN",
    "ne:TIMEZONE":"Asia/Harbin",
    "ne:UN_FID":0,
    "ne:UN_LAT":0.0,
    "ne:UN_LONG":0.0,
    "ne:WORLDCITY":0,
    "qs:name":"\u6276\u4f59\u5e02",
    "qs:name_adm0":"\u4e2d\u570b",
    "qs:name_adm1":"\u5409\u6797\u7701",
    "qs:photos_9k":1,
    "qs:photos_9r":1,
    "qs:photos_all":1,
    "qs:photos_sr":0,
    "qs:placetype":"Town",
    "qs:pop_sr":"10",
    "wof:name":"\u6276\u4f59\u5e02",
    "wof:placetype":"locality",
    "wof:population":138704
},
  "geometry": {"coordinates":[124.81667,45.18333],"type":"Point"}
}