{
  "type": "Feature",
  "properties": {
    "gn:admin1_code":"10.0",
    "gn:asciiname":"Chenliubo",
    "gn:country_code":"CN",
    "gn:dem":11,
    "gn:feature_class":"P",
    "gn:feature_code":"PPL",
    "gn:name":"Chenliubo",
    "gn:population":0,
    "gn:timezone":"Asia/Shanghai",
    "iso:country":"CN",
    "name:zho_x_preferred":[
        "\u9648\u516d\u62e8"
    ],
    "wof:name":"Chenliubo",
    "wof:placetype":"locality"
},
  "geometry": {"coordinates":[116.85899999999999,38.131],"type":"Point"}
}