{
  "type": "Feature",
  "properties": {
    "gn:admin1_code":"7",
    "gn:asciiname":"Youchuang",
    "gn:country_code":"CN",
    "gn:dem":723,
    "gn:feature_class":"P",
    "gn:feature_code":"PPL",
    "gn:name":"Youchuang",
    "gn:population":0,
    "gn:timezone":"Asia/Shanghai",
    "iso:country":"CN",
    "wof:name":"Youchuang",
    "wof:placetype":"locality"
},
  "geometry": {"coordinates":[117.98472,25.76139],"type":"Point"}
}