{
  "type": "Feature",
  "properties": {
    "gn:admin1_code":"30.0",
    "gn:asciiname":"Limukeng",
    "gn:country_code":"CN",
    "gn:dem":133,
    "gn:feature_class":"P",
    "gn:feature_code":"PPL",
    "gn:name":"Limukeng",
    "gn:population":0,
    "gn:timezone":"Asia/Shanghai",
    "iso:country":"CN",
    "name:zho_x_preferred":[
        "Limukeng"
    ],
    "name:zho_x_variant":[
        "\u68a8\u6728\u5751"
    ],
    "wof:name":"Limukeng",
    "wof:placetype":"locality"
},
  "geometry": {"coordinates":[114.70892000000001,24.09932],"type":"Point"}
}