{
  "type": "Feature",
  "properties": {
    "gn:admin1_code":"16.0",
    "gn:asciiname":"Xialiubai",
    "gn:country_code":"CN",
    "gn:dem":173,
    "gn:feature_class":"P",
    "gn:feature_code":"PPL",
    "gn:name":"Xialiubai",
    "gn:population":0,
    "gn:timezone":"Asia/Shanghai",
    "iso:country":"CN",
    "name:zho_x_preferred":[
        "\u4e0b\u516d\u767d"
    ],
    "wof:name":"Xialiubai",
    "wof:placetype":"locality"
},
  "geometry": {"coordinates":[108.08,23.687],"type":"Point"}
}