{
  "type": "Feature",
  "properties": {
    "gn:admin1_code":"26.0",
    "gn:asciiname":"Houzhengjia Goucun",
    "gn:country_code":"CN",
    "gn:dem":1037,
    "gn:feature_class":"P",
    "gn:feature_code":"PPL",
    "gn:name":"Houzhengjia Goucun",
    "gn:population":0,
    "gn:timezone":"Asia/Shanghai",
    "iso:country":"CN",
    "name:zho_x_preferred":[
        "\u540e\u90d1\u5bb6\u6c9f\u6751"
    ],
    "wof:name":"Houzhengjia Goucun",
    "wof:placetype":"locality"
},
  "geometry": {"coordinates":[110.28,38.2829],"type":"Point"}
}