{
  "type": "Feature",
  "properties": {
    "gn:admin1_code":"30.0",
    "gn:asciiname":"Dahedong",
    "gn:country_code":"CN",
    "gn:dem":558,
    "gn:feature_class":"P",
    "gn:feature_code":"PPL",
    "gn:name":"Dahedong",
    "gn:population":0,
    "gn:timezone":"Asia/Shanghai",
    "iso:country":"CN",
    "name:zho_x_preferred":[
        "Dahedong"
    ],
    "name:zho_x_variant":[
        "\u5927\u79be\u578c"
    ],
    "wof:name":"Dahedong",
    "wof:placetype":"locality"
},
  "geometry": {"coordinates":[112.74056000000002,24.83028],"type":"Point"}
}