{
  "type": "Feature",
  "properties": {
    "gn:admin1_code":"15.0",
    "gn:asciiname":"Magaozhuang",
    "gn:country_code":"CN",
    "gn:dem":1266,
    "gn:feature_class":"P",
    "gn:feature_code":"PPL",
    "gn:name":"Magaozhuang",
    "gn:population":0,
    "gn:timezone":"Asia/Shanghai",
    "iso:country":"CN",
    "name:und_x_variant":[
        "\u9a6c\u9ad8\u5e84"
    ],
    "wof:name":"Magaozhuang",
    "wof:placetype":"locality"
},
  "geometry": {"coordinates":[107.75291,36.55634000000001],"type":"Point"}
}