{
  "type": "Feature",
  "properties": {
    "gn:admin1_code":"19.0",
    "gn:asciiname":"Hongqigoucun",
    "gn:country_code":"CN",
    "gn:dem":42,
    "gn:feature_class":"P",
    "gn:feature_code":"PPL",
    "gn:name":"Hongqigoucun",
    "gn:population":0,
    "gn:timezone":"Asia/Shanghai",
    "iso:country":"CN",
    "name:zho_x_preferred":[
        "\u7ea2\u65d7\u6c9f\u6751"
    ],
    "wof:name":"Hongqigoucun",
    "wof:placetype":"locality"
},
  "geometry": {"coordinates":[121.848,41.5855],"type":"Point"}
}