{
  "type": "Feature",
  "properties": {
    "gn:admin1_code":"28.0",
    "gn:asciiname":"Zhongtang",
    "gn:country_code":"CN",
    "gn:dem":6,
    "gn:feature_class":"P",
    "gn:feature_code":"PPL",
    "gn:name":"Zhongtang",
    "gn:population":0,
    "gn:timezone":"Asia/Shanghai",
    "iso:country":"CN",
    "name:sco_x_preferred":[
        "Zhongtang"
    ],
    "name:und_x_variant":[
        "Chung-t\u2019ang",
        "Zhongtang"
    ],
    "wof:name":"Zhongtang",
    "wof:placetype":"locality"
},
  "geometry": {"coordinates":[117.33113,38.83987],"type":"Point"}
}