{
  "type": "Feature",
  "properties": {
    "gn:admin1_code":"26.0",
    "gn:asciiname":"Heiling",
    "gn:country_code":"CN",
    "gn:dem":965,
    "gn:feature_class":"P",
    "gn:feature_code":"PPL",
    "gn:name":"Heiling",
    "gn:population":0,
    "gn:timezone":"Asia/Shanghai",
    "iso:country":"CN",
    "name:zho_x_preferred":[
        "\u9ed1\u5cad"
    ],
    "wof:name":"Heiling",
    "wof:placetype":"locality"
},
  "geometry": {"coordinates":[106.93323999999998,34.33971],"type":"Point"}
}