{
  "type": "Feature",
  "properties": {
    "gn:country":"CN",
    "gn:fcode":"PPLA4",
    "gn:pop":5407,
    "iso:country":"CN",
    "name:ceb_x_preferred":[
        "Beichen Qu"
    ],
    "name:cym_x_preferred":[
        "Ardal Beichen"
    ],
    "name:deu_x_preferred":[
        "Beichen"
    ],
    "name:eng_x_preferred":[
        "Beichen District"
    ],
    "name:eus_x_preferred":[
        "Beichen Barrutia"
    ],
    "name:gan_x_preferred":[
        "\u5317\u8fb0\u533a"
    ],
    "name:jpn_x_preferred":[
        "\u5317\u8fb0\u533a"
    ],
    "name:kor_x_preferred":[
        "\ubca0\uc774\ucc9c\uad6c"
    ],
    "name:nan_x_preferred":[
        "Pak-s\u00een-khu"
    ],
    "name:nld_x_preferred":[
        "Beichen District"
    ],
    "name:nob_x_preferred":[
        "Beichen"
    ],
    "name:rus_x_preferred":[
        "\u0411\u044d\u0439\u0447\u044d\u043d\u044c"
    ],
    "name:swe_x_preferred":[
        "Beichen"
    ],
    "name:unk_x_variant":[
        "Hai-ti-t\u2019ou"
    ],
    "name:urd_x_preferred":[
        "\u0628\u0626\u06cc\u0686\u06cc\u0646 \u0636\u0644\u0639"
    ],
    "name:vie_x_preferred":[
        "B\u1eafc Th\u1ea7n"
    ],
    "name:wuu_x_preferred":[
        "\u5317\u8fb0\u533a"
    ],
    "name:zho_x_preferred":[
        "\u897f\u5824\u5934"
    ],
    "name:zho_x_variant":[
        "\u897f\u5824\u5934\u9547",
        "\u5317\u8fb0\u533a"
    ],
    "qs:name":"Xiditou",
    "qs:photos_9r":0,
    "qs:photos_sr":0,
    "qs:pop_sr":"5",
    "wd:wordcount":282,
    "wof:name":"Xiditou",
    "wof:placetype":"locality",
    "wof:population":5407
},
  "geometry": {"coordinates":[117.34814,39.25375],"type":"Point"}
}