{
  "type": "Feature",
  "properties": {
    "gn:admin1_code":"32.0",
    "gn:asciiname":"Muzilaiwo",
    "gn:country_code":"CN",
    "gn:dem":2471,
    "gn:feature_class":"P",
    "gn:feature_code":"PPL",
    "gn:name":"Muzilaiwo",
    "gn:population":0,
    "gn:timezone":"Asia/Shanghai",
    "iso:country":"CN",
    "name:zho_x_preferred":[
        "\u6bcd\u5b50\u6765\u7a9d"
    ],
    "wof:name":"Muzilaiwo",
    "wof:placetype":"locality"
},
  "geometry": {"coordinates":[102.974,28.1807],"type":"Point"}
}