{
  "type": "Feature",
  "properties": {
    "gn:admin1_code":"19.0",
    "gn:asciiname":"Maoyingzicun",
    "gn:country_code":"CN",
    "gn:dem":16,
    "gn:feature_class":"P",
    "gn:feature_code":"PPL",
    "gn:name":"Maoyingzicun",
    "gn:population":0,
    "gn:timezone":"Asia/Shanghai",
    "iso:country":"CN",
    "name:zho_x_preferred":[
        "\u6bdb\u83b9\u5b50\u6751"
    ],
    "name:zho_x_variant":[
        "\u6bdb\u8314\u5b50\u6751"
    ],
    "wof:name":"Maoyingzicun",
    "wof:placetype":"locality"
},
  "geometry": {"coordinates":[121.66383,39.06767],"type":"Point"}
}