{
  "type": "Feature",
  "properties": {
    "gn:admin1_code":"9.0",
    "gn:asciiname":"Xiaolingwang",
    "gn:country_code":"CN",
    "gn:dem":190,
    "gn:feature_class":"P",
    "gn:feature_code":"PPL",
    "gn:name":"Xiaolingwang",
    "gn:population":0,
    "gn:timezone":"Asia/Shanghai",
    "iso:country":"CN",
    "name:und_x_variant":[
        "\u5c0f\u5cad\u738b",
        "Xiaolingwang"
    ],
    "wof:name":"Xiaolingwang",
    "wof:placetype":"locality"
},
  "geometry": {"coordinates":[112.94331,33.92538],"type":"Point"}
}