{
  "type": "Feature",
  "properties": {
    "gn:admin1_code":"6.0",
    "gn:asciiname":"Xiuma",
    "gn:country_code":"CN",
    "gn:dem":3240,
    "gn:feature_class":"P",
    "gn:feature_code":"PPLA4",
    "gn:name":"Xiuma",
    "gn:population":0,
    "gn:timezone":"Asia/Shanghai",
    "iso:country":"CN",
    "name:und_x_variant":[
        "Jiangqun",
        "\u6c5f\u7fa4",
        "Xiuma Xiang",
        "\u79c0\u9ebb\u4e61",
        "Xiuma"
    ],
    "name:zho_x_preferred":[
        "\u79c0\u9ebb"
    ],
    "wof:name":"Xiuma",
    "wof:placetype":"locality"
},
  "geometry": {"coordinates":[100.33283,35.05538],"type":"Point"}
}