{
  "type": "Feature",
  "properties": {
    "gn:admin1_code":"29.0",
    "gn:asciiname":"Xiamalutang",
    "gn:country_code":"CN",
    "gn:dem":1952,
    "gn:feature_class":"P",
    "gn:feature_code":"PPL",
    "gn:name":"Xiamalutang",
    "gn:population":0,
    "gn:timezone":"Asia/Shanghai",
    "iso:country":"CN",
    "name:zho_x_preferred":[
        "\u4e0b\u9a6c\u9e7f\u5858"
    ],
    "wof:name":"Xiamalutang",
    "wof:placetype":"locality"
},
  "geometry": {"coordinates":[101.541,26.2768],"type":"Point"}
}