{
  "type": "Feature",
  "properties": {
    "gn:admin1_code":"15.0",
    "gn:asciiname":"Gaoqiao",
    "gn:country_code":"CN",
    "gn:dem":1273,
    "gn:feature_class":"P",
    "gn:feature_code":"PPL",
    "gn:name":"Gaoqiao",
    "gn:population":0,
    "gn:timezone":"Asia/Shanghai",
    "iso:country":"CN",
    "name:zho_x_preferred":[
        "\u9ad8\u6865"
    ],
    "wof:name":"Gaoqiao",
    "wof:placetype":"locality"
},
  "geometry": {"coordinates":[105.327,34.7514],"type":"Point"}
}