{
  "type": "Feature",
  "properties": {
    "gn:admin1_code":"7",
    "gn:asciiname":"Matoucuo",
    "gn:country_code":"CN",
    "gn:dem":57,
    "gn:feature_class":"P",
    "gn:feature_code":"PPL",
    "gn:name":"Matoucuo",
    "gn:population":0,
    "gn:timezone":"Asia/Shanghai",
    "iso:country":"CN",
    "name:zho_x_preferred":[
        "\u9a6c\u5934\u539d"
    ],
    "wof:name":"Matoucuo",
    "wof:placetype":"locality"
},
  "geometry": {"coordinates":[119.00385,25.91122],"type":"Point"}
}