{
  "type": "Feature",
  "properties": {
    "gn:admin1_code":"9",
    "gn:asciiname":"Houduzhuang",
    "gn:country_code":"CN",
    "gn:dem":42,
    "gn:feature_class":"P",
    "gn:feature_code":"PPL",
    "gn:name":"Houduzhuang",
    "gn:population":0,
    "gn:timezone":"Asia/Shanghai",
    "iso:country":"CN",
    "name:zho_x_preferred":[
        "\u540e\u675c\u5e84"
    ],
    "wof:name":"Houduzhuang",
    "wof:placetype":"locality"
},
  "geometry": {"coordinates":[115.352,33.7487],"type":"Point"}
}