{
  "type": "Feature",
  "properties": {
    "gn:admin1_code":"15.0",
    "gn:asciiname":"Gaoyaoxian",
    "gn:country_code":"CN",
    "gn:dem":1458,
    "gn:feature_class":"P",
    "gn:feature_code":"PPL",
    "gn:name":"Gaoyaoxian",
    "gn:population":0,
    "gn:timezone":"Asia/Shanghai",
    "iso:country":"CN",
    "name:und_x_variant":[
        "\u9ad8\u5d3e\u5c98"
    ],
    "wof:name":"Gaoyaoxian",
    "wof:placetype":"locality"
},
  "geometry": {"coordinates":[107.30288,36.10263],"type":"Point"}
}