{
  "type": "Feature",
  "properties": {
    "gn:admin1_code":"4.0",
    "gn:asciiname":"Dongshisanxu",
    "gn:country_code":"CN",
    "gn:dem":6,
    "gn:feature_class":"P",
    "gn:feature_code":"PPLF",
    "gn:name":"Dongshisanxu",
    "gn:population":0,
    "gn:timezone":"Asia/Shanghai",
    "iso:country":"CN",
    "name:zho_x_preferred":[
        "\u4e1c\u5341\u4e09\u5729"
    ],
    "wof:name":"Dongshisanxu",
    "wof:placetype":"locality"
},
  "geometry": {"coordinates":[120.39738,32.10938],"type":"Point"}
}