{
  "type": "Feature",
  "properties": {
    "gn:admin1_code":"16.0",
    "gn:asciiname":"Shenping",
    "gn:country_code":"CN",
    "gn:dem":13,
    "gn:feature_class":"P",
    "gn:feature_code":"PPL",
    "gn:name":"Shenping",
    "gn:population":0,
    "gn:timezone":"Asia/Shanghai",
    "iso:country":"CN",
    "name:zho_x_preferred":[
        "\u6df1\u576a"
    ],
    "wof:name":"Shenping",
    "wof:placetype":"locality"
},
  "geometry": {"coordinates":[108.642,21.7928],"type":"Point"}
}