{
  "type": "Feature",
  "properties": {
    "gn:admin1_code":"4.0",
    "gn:asciiname":"Jiaomucun",
    "gn:country_code":"CN",
    "gn:dem":3,
    "gn:feature_class":"P",
    "gn:feature_code":"PPL",
    "gn:name":"Jiaomucun",
    "gn:population":0,
    "gn:timezone":"Asia/Shanghai",
    "iso:country":"CN",
    "name:zho_x_preferred":[
        "\u4ea4\u7766\u6751"
    ],
    "wof:name":"Jiaomucun",
    "wof:placetype":"locality"
},
  "geometry": {"coordinates":[119.69153,33.46008],"type":"Point"}
}