{
  "type": "Feature",
  "properties": {
    "gn:admin1_code":"2.0",
    "gn:asciiname":"Guanqingfan",
    "gn:country_code":"CN",
    "gn:dem":70,
    "gn:feature_class":"P",
    "gn:feature_code":"PPL",
    "gn:name":"Guanqingfan",
    "gn:population":0,
    "gn:timezone":"Asia/Shanghai",
    "iso:country":"CN",
    "name:zho_x_preferred":[
        "\u5b98\u6e05\u7548"
    ],
    "wof:name":"Guanqingfan",
    "wof:placetype":"locality"
},
  "geometry": {"coordinates":[120.01009999999999,29.29753],"type":"Point"}
}