{
  "type": "Feature",
  "properties": {
    "gn:admin1_code":"26",
    "gn:asciiname":"Tangguanzhai",
    "gn:country_code":"CN",
    "gn:dem":413,
    "gn:feature_class":"P",
    "gn:feature_code":"PPL",
    "gn:name":"Tangguanzhai",
    "gn:population":0,
    "gn:timezone":"Asia/Shanghai",
    "iso:country":"CN",
    "name:und_x_variant":[
        "\u6c64\u5b98\u5be8"
    ],
    "name:zho_x_preferred":[
        "\u6c64\u5b98\u5be8"
    ],
    "wof:name":"Tangguanzhai",
    "wof:placetype":"locality"
},
  "geometry": {"coordinates":[108.96639,34.57639],"type":"Point"}
}