{
  "type": "Feature",
  "properties": {
    "gn:admin1_code":"30",
    "gn:asciiname":"Wangcun",
    "gn:country_code":"CN",
    "gn:dem":93,
    "gn:feature_class":"P",
    "gn:feature_code":"PPL",
    "gn:name":"Wangcun",
    "gn:population":0,
    "gn:timezone":"Asia/Urumqi",
    "iso:country":"CN",
    "name:deu_x_preferred":[
        "Wangcun"
    ],
    "name:zho_x_preferred":[
        "\u65fa\u6751"
    ],
    "wof:name":"Wangcun",
    "wof:placetype":"locality"
},
  "geometry": {"coordinates":[110.78382999999999,22.13753],"type":"Point"}
}