{
  "type": "Feature",
  "properties": {
    "gn:admin1_code":"20.0",
    "gn:asciiname":"Hexinggong",
    "gn:country_code":"CN",
    "gn:dem":1457,
    "gn:feature_class":"P",
    "gn:feature_code":"PPL",
    "gn:name":"Hexinggong",
    "gn:population":0,
    "gn:timezone":"Asia/Shanghai",
    "iso:country":"CN",
    "name:und_x_variant":[
        "\u5408\u5174\u516c"
    ],
    "wof:name":"Hexinggong",
    "wof:placetype":"locality"
},
  "geometry": {"coordinates":[113.4363,41.29171],"type":"Point"}
}