{
  "type": "Feature",
  "properties": {
    "gn:admin1_code":"26",
    "gn:asciiname":"Huangshapu",
    "gn:country_code":"CN",
    "gn:dem":685,
    "gn:feature_class":"P",
    "gn:feature_code":"PPL",
    "gn:name":"Huangshapu",
    "gn:population":0,
    "gn:timezone":"Asia/Shanghai",
    "iso:country":"CN",
    "wof:name":"Huangshapu",
    "wof:placetype":"locality"
},
  "geometry": {"coordinates":[107.4025,33.06610999999999],"type":"Point"}
}