{
  "type": "Feature",
  "properties": {
    "gn:admin1_code":"15.0",
    "gn:asciiname":"Macaogou",
    "gn:country_code":"CN",
    "gn:dem":1209,
    "gn:feature_class":"P",
    "gn:feature_code":"PPL",
    "gn:name":"Macaogou",
    "gn:population":0,
    "gn:timezone":"Asia/Shanghai",
    "iso:country":"CN",
    "name:und_x_variant":[
        "\u9a6c\u69fd\u6c9f"
    ],
    "wof:name":"Macaogou",
    "wof:placetype":"locality"
},
  "geometry": {"coordinates":[105.63942,33.57761],"type":"Point"}
}