{
  "type": "Feature",
  "properties": {
    "gn:admin1_code":"32.0",
    "gn:asciiname":"Wenfengzhai",
    "gn:country_code":"CN",
    "gn:dem":377,
    "gn:feature_class":"P",
    "gn:feature_code":"PPL",
    "gn:name":"Wenfengzhai",
    "gn:population":0,
    "gn:timezone":"Asia/Shanghai",
    "iso:country":"CN",
    "name:zho_x_preferred":[
        "\u6587\u5cf0\u5be8"
    ],
    "wof:name":"Wenfengzhai",
    "wof:placetype":"locality"
},
  "geometry": {"coordinates":[107.063,30.5701],"type":"Point"}
}