{
  "type": "Feature",
  "properties": {
    "gn:admin1_code":"16.0",
    "gn:asciiname":"Weiling",
    "gn:country_code":"CN",
    "gn:dem":1286,
    "gn:feature_class":"P",
    "gn:feature_code":"PPL",
    "gn:name":"Weiling",
    "gn:population":0,
    "gn:timezone":"Asia/Shanghai",
    "iso:country":"CN",
    "name:zho_x_preferred":[
        "\u4f1f\u5cad"
    ],
    "wof:name":"Weiling",
    "wof:placetype":"locality"
},
  "geometry": {"coordinates":[105.538,24.6387],"type":"Point"}
}