{
  "type": "Feature",
  "properties": {
    "gn:admin1_code":"18.0",
    "gn:asciiname":"Jiugui",
    "gn:country_code":"CN",
    "gn:dem":1431,
    "gn:feature_class":"P",
    "gn:feature_code":"PPL",
    "gn:name":"Jiugui",
    "gn:population":0,
    "gn:timezone":"Asia/Shanghai",
    "iso:country":"CN",
    "name:zho_x_preferred":[
        "\u4e5d\u5f52"
    ],
    "wof:name":"Jiugui",
    "wof:placetype":"locality"
},
  "geometry": {"coordinates":[104.815,26.1961],"type":"Point"}
}