{
  "type": "Feature",
  "properties": {
    "gn:admin1_code":"18",
    "gn:asciiname":"Suona",
    "gn:country_code":"CN",
    "gn:dem":1060,
    "gn:feature_class":"P",
    "gn:feature_code":"PPL",
    "gn:name":"Suona",
    "gn:population":0,
    "gn:timezone":"Asia/Shanghai",
    "iso:country":"CN",
    "name:bod_x_preferred":[
        "\u0f62\u0f92\u0fb1\u0f0b\u0f42\u0fb3\u0f72\u0f44\u0f0b\u0f0d"
    ],
    "name:cat_x_preferred":[
        "Suona"
    ],
    "name:cdo_x_preferred":[
        "D\u012d-d\u0103"
    ],
    "name:deu_x_preferred":[
        "Suona"
    ],
    "name:epo_x_preferred":[
        "Suona"
    ],
    "name:fra_x_preferred":[
        "Suona"
    ],
    "name:ita_x_preferred":[
        "Suona"
    ],
    "name:jpn_x_preferred":[
        "\u30c1\u30e3\u30eb\u30e1\u30e9"
    ],
    "name:nor_x_preferred":[
        "Suona"
    ],
    "name:que_x_preferred":[
        "Suona"
    ],
    "name:rus_x_preferred":[
        "\u0421\u043e\u043d\u0430"
    ],
    "name:spa_x_preferred":[
        "Suona"
    ],
    "name:swe_x_preferred":[
        "Suona"
    ],
    "name:ukr_x_preferred":[
        "\u0421\u043e\u043d\u0430"
    ],
    "name:zho_x_preferred":[
        "\u6240\u7eb3"
    ],
    "wof:name":"Suona",
    "wof:placetype":"locality"
},
  "geometry": {"coordinates":[106.611,25.8465],"type":"Point"}
}