{
  "type": "Feature",
  "properties": {
    "gn:admin1_code":"3.0",
    "gn:asciiname":"Zhujiazhuang",
    "gn:country_code":"CN",
    "gn:dem":115,
    "gn:feature_class":"P",
    "gn:feature_code":"PPL",
    "gn:name":"Zhujiazhuang",
    "gn:population":0,
    "gn:timezone":"Asia/Shanghai",
    "iso:country":"CN",
    "name:und_x_variant":[
        "\u795d\u5bb6\u5e84"
    ],
    "wof:name":"Zhujiazhuang",
    "wof:placetype":"locality"
},
  "geometry": {"coordinates":[116.42927,27.14781],"type":"Point"}
}