{
  "type": "Feature",
  "properties": {
    "gn:admin1_code":"12.0",
    "gn:asciiname":"Jiangkouba",
    "gn:country_code":"CN",
    "gn:dem":486,
    "gn:feature_class":"P",
    "gn:feature_code":"PPL",
    "gn:name":"Jiangkouba",
    "gn:population":0,
    "gn:timezone":"Asia/Shanghai",
    "iso:country":"CN",
    "name:zho_x_preferred":[
        "\u6c5f\u53e3\u575d"
    ],
    "wof:name":"Jiangkouba",
    "wof:placetype":"locality"
},
  "geometry": {"coordinates":[109.36172999999999,29.43931],"type":"Point"}
}