{
  "type": "Feature",
  "properties": {
    "gn:admin1_code":"04",
    "gn:asciiname":"Antou",
    "gn:country_code":"CN",
    "gn:dem":5,
    "gn:feature_class":"P",
    "gn:feature_code":"PPLA4",
    "gn:name":"Antou",
    "gn:population":0,
    "gn:timezone":"Asia/Shanghai",
    "iso:country":"CN",
    "name:und_x_variant":[
        "An-t\u2019ou-chen",
        "Antou",
        "\u5cb8\u5934",
        "Antouzhen",
        "Wanghao",
        "Antou Zhen",
        "\u5cb8\u5934\u9547",
        "\u738b\u6d69",
        "Wanghao Zhen",
        "\u738b\u6d69\u9547"
    ],
    "wof:name":"Antou",
    "wof:placetype":"locality"
},
  "geometry": {"coordinates":[121.31686000000001,32.06139],"type":"Point"}
}