{
  "type": "Feature",
  "properties": {
    "gn:admin1_code":"32.0",
    "gn:asciiname":"Paotai",
    "gn:country_code":"CN",
    "gn:dem":884,
    "gn:feature_class":"P",
    "gn:feature_code":"PPL",
    "gn:name":"Paotai",
    "gn:population":0,
    "gn:timezone":"Asia/Shanghai",
    "iso:country":"CN",
    "name:zho_x_preferred":[
        "\u70ae\u53f0"
    ],
    "wof:name":"Paotai",
    "wof:placetype":"locality"
},
  "geometry": {"coordinates":[108.072,31.6518],"type":"Point"}
}