{
  "type": "Feature",
  "properties": {
    "gn:admin1_code":"2.0",
    "gn:asciiname":"Miaojia",
    "gn:country_code":"CN",
    "gn:dem":129,
    "gn:feature_class":"P",
    "gn:feature_code":"PPL",
    "gn:name":"Miaojia",
    "gn:population":0,
    "gn:timezone":"Asia/Shanghai",
    "iso:country":"CN",
    "name:zho_x_preferred":[
        "\u7f2a\u5bb6"
    ],
    "wof:name":"Miaojia",
    "wof:placetype":"locality"
},
  "geometry": {"coordinates":[118.99554000000001,29.66868],"type":"Point"}
}