{
  "type": "Feature",
  "properties": {
    "gn:admin1_code":"32.0",
    "gn:asciiname":"Juemo",
    "gn:country_code":"CN",
    "gn:dem":2637,
    "gn:feature_class":"P",
    "gn:feature_code":"PPL",
    "gn:name":"Juemo",
    "gn:population":0,
    "gn:timezone":"Asia/Shanghai",
    "iso:country":"CN",
    "name:zho_x_preferred":[
        "\u89c9\u83ab"
    ],
    "wof:name":"Juemo",
    "wof:placetype":"locality"
},
  "geometry": {"coordinates":[102.69,28.1129],"type":"Point"}
}