{
  "type": "Feature",
  "properties": {
    "gn:admin1_code":"9",
    "gn:asciiname":"Xishaoguo",
    "gn:country_code":"CN",
    "gn:dem":49,
    "gn:feature_class":"P",
    "gn:feature_code":"PPL",
    "gn:name":"Xishaoguo",
    "gn:population":0,
    "gn:timezone":"Asia/Shanghai",
    "iso:country":"CN",
    "name:zho_x_preferred":[
        "\u897f\u90b5\u90ed"
    ],
    "wof:name":"Xishaoguo",
    "wof:placetype":"locality"
},
  "geometry": {"coordinates":[115.25084,36.13735],"type":"Point"}
}