{
  "type": "Feature",
  "properties": {
    "gn:admin1_code":"14.0",
    "gn:asciiname":"Zhongdaka",
    "gn:country_code":"CN",
    "gn:dem":4409,
    "gn:feature_class":"P",
    "gn:feature_code":"PPL",
    "gn:name":"Zhongdaka",
    "gn:population":0,
    "gn:timezone":"Asia/Urumqi",
    "iso:country":"CN",
    "name:zho_x_preferred":[
        "\u4ef2\u8fbe\u5361"
    ],
    "wof:name":"Zhongdaka",
    "wof:placetype":"locality"
},
  "geometry": {"coordinates":[94.21228000000001,31.51421],"type":"Point"}
}