{
  "type": "Feature",
  "properties": {
    "gn:admin1_code":"25.0",
    "gn:asciiname":"Dalanjiazhuangcun",
    "gn:country_code":"CN",
    "gn:dem":19,
    "gn:feature_class":"P",
    "gn:feature_code":"PPL",
    "gn:name":"Dalanjiazhuangcun",
    "gn:population":0,
    "gn:timezone":"Asia/Shanghai",
    "iso:country":"CN",
    "name:zho_x_preferred":[
        "\u5927\u84dd\u5bb6\u5e84\u6751"
    ],
    "wof:name":"Dalanjiazhuangcun",
    "wof:placetype":"locality"
},
  "geometry": {"coordinates":[120.25194999999999,36.55098],"type":"Point"}
}