{
  "type": "Feature",
  "properties": {
    "gn:admin1_code":"11.0",
    "gn:asciiname":"Lujiazhai",
    "gn:country_code":"CN",
    "gn:dem":321,
    "gn:feature_class":"P",
    "gn:feature_code":"PPL",
    "gn:name":"Lujiazhai",
    "gn:population":0,
    "gn:timezone":"Asia/Shanghai",
    "iso:country":"CN",
    "name:zho_x_preferred":[
        "\u9646\u5bb6\u5be8"
    ],
    "wof:name":"Lujiazhai",
    "wof:placetype":"locality"
},
  "geometry": {"coordinates":[109.27585000000001,28.53079],"type":"Point"}
}