{
  "type": "Feature",
  "properties": {
    "gn:admin1_code":"18",
    "gn:asciiname":"Baogulang",
    "gn:country_code":"CN",
    "gn:dem":1662,
    "gn:feature_class":"P",
    "gn:feature_code":"PPL",
    "gn:name":"Baogulang",
    "gn:population":0,
    "gn:timezone":"Asia/Shanghai",
    "iso:country":"CN",
    "name:zho_x_preferred":[
        "\u82de\u8c37\u6d6a"
    ],
    "wof:name":"Baogulang",
    "wof:placetype":"locality"
},
  "geometry": {"coordinates":[104.63500000000001,24.8457],"type":"Point"}
}