{
  "type": "Feature",
  "properties": {
    "gn:admin1_code":"18.0",
    "gn:asciiname":"Jingtaizhai",
    "gn:country_code":"CN",
    "gn:dem":1010,
    "gn:feature_class":"P",
    "gn:feature_code":"PPL",
    "gn:name":"Jingtaizhai",
    "gn:population":0,
    "gn:timezone":"Asia/Shanghai",
    "iso:country":"CN",
    "name:zho_x_preferred":[
        "\u4e95\u53f0\u5be8"
    ],
    "wof:name":"Jingtaizhai",
    "wof:placetype":"locality"
},
  "geometry": {"coordinates":[107.393,26.6986],"type":"Point"}
}