{
  "type": "Feature",
  "properties": {
    "gn:admin1_code":"14.0",
    "gn:asciiname":"Bapucun",
    "gn:country_code":"CN",
    "gn:dem":3972,
    "gn:feature_class":"P",
    "gn:feature_code":"PPL",
    "gn:name":"Bapucun",
    "gn:population":0,
    "gn:timezone":"Asia/Urumqi",
    "iso:country":"CN",
    "name:zho_x_preferred":[
        "\u5df4\u666e\u6751"
    ],
    "wof:name":"Bapucun",
    "wof:placetype":"locality"
},
  "geometry": {"coordinates":[98.24544,31.07791],"type":"Point"}
}