{
  "type": "Feature",
  "properties": {
    "gn:admin1_code":"14.0",
    "gn:asciiname":"Xilang",
    "gn:country_code":"CN",
    "gn:dem":3862,
    "gn:feature_class":"P",
    "gn:feature_code":"PPL",
    "gn:name":"Xilang",
    "gn:population":0,
    "gn:timezone":"Asia/Urumqi",
    "iso:country":"CN",
    "name:zho_x_preferred":[
        "\u5e2d\u6d6a"
    ],
    "wof:name":"Xilang",
    "wof:placetype":"locality"
},
  "geometry": {"coordinates":[91.16826,29.37662000000001],"type":"Point"}
}