{
  "type": "Feature",
  "properties": {
    "gn:admin1_code":"32.0",
    "gn:asciiname":"Guoziping",
    "gn:country_code":"CN",
    "gn:dem":1103,
    "gn:feature_class":"P",
    "gn:feature_code":"PPL",
    "gn:name":"Guoziping",
    "gn:population":0,
    "gn:timezone":"Asia/Shanghai",
    "iso:country":"CN",
    "name:zho_x_preferred":[
        "\u679c\u5b50\u576a"
    ],
    "wof:name":"Guoziping",
    "wof:placetype":"locality"
},
  "geometry": {"coordinates":[103.904,28.8175],"type":"Point"}
}