{
  "type": "Feature",
  "properties": {
    "gn:admin1_code":"24.0",
    "gn:asciiname":"Shangbaise",
    "gn:country_code":"CN",
    "gn:dem":1294,
    "gn:feature_class":"P",
    "gn:feature_code":"PPL",
    "gn:name":"Shangbaise",
    "gn:population":0,
    "gn:timezone":"Asia/Shanghai",
    "iso:country":"CN",
    "name:zho_x_preferred":[
        "\u4e0a\u67cf\u8272"
    ],
    "wof:name":"Shangbaise",
    "wof:placetype":"locality"
},
  "geometry": {"coordinates":[112.39337999999999,38.46549],"type":"Point"}
}