{
  "type": "Feature",
  "properties": {
    "gn:admin1_code":"16.0",
    "gn:asciiname":"Jiaokan",
    "gn:country_code":"CN",
    "gn:dem":384,
    "gn:feature_class":"P",
    "gn:feature_code":"PPL",
    "gn:name":"Jiaokan",
    "gn:population":0,
    "gn:timezone":"Asia/Shanghai",
    "iso:country":"CN",
    "name:zho_x_preferred":[
        "\u53eb\u582a"
    ],
    "wof:name":"Jiaokan",
    "wof:placetype":"locality"
},
  "geometry": {"coordinates":[107.39400000000001,22.0361],"type":"Point"}
}