{
  "type": "Feature",
  "properties": {
    "gn:admin1_code":"25.0",
    "gn:asciiname":"Wuxuntun",
    "gn:country_code":"CN",
    "gn:dem":36,
    "gn:feature_class":"P",
    "gn:feature_code":"PPL",
    "gn:name":"Wuxuntun",
    "gn:population":0,
    "gn:timezone":"Asia/Shanghai",
    "iso:country":"CN",
    "name:zho_x_preferred":[
        "\u6b66\u5dfd\u5c6f"
    ],
    "wof:name":"Wuxuntun",
    "wof:placetype":"locality"
},
  "geometry": {"coordinates":[119.52751000000001,36.45485],"type":"Point"}
}