{
  "type": "Feature",
  "properties": {
    "gn:admin1_code":"15.0",
    "gn:asciiname":"Tangjiazhuang",
    "gn:country_code":"CN",
    "gn:dem":2324,
    "gn:feature_class":"P",
    "gn:feature_code":"PPL",
    "gn:name":"Tangjiazhuang",
    "gn:population":0,
    "gn:timezone":"Asia/Shanghai",
    "iso:country":"CN",
    "name:zho_x_preferred":[
        "\u6c64\u5bb6\u5e84"
    ],
    "wof:name":"Tangjiazhuang",
    "wof:placetype":"locality"
},
  "geometry": {"coordinates":[100.837,38.4243],"type":"Point"}
}