{
  "type": "Feature",
  "properties": {
    "gn:admin1_code":"19.0",
    "gn:asciiname":"Xiwangtun",
    "gn:country_code":"CN",
    "gn:dem":50,
    "gn:feature_class":"P",
    "gn:feature_code":"PPL",
    "gn:name":"Xiwangtun",
    "gn:population":0,
    "gn:timezone":"Asia/Shanghai",
    "iso:country":"CN",
    "name:zho_x_preferred":[
        "\u897f\u738b\u5c6f"
    ],
    "wof:name":"Xiwangtun",
    "wof:placetype":"locality"
},
  "geometry": {"coordinates":[121.788,41.5642],"type":"Point"}
}