{
  "type": "Feature",
  "properties": {
    "gn:admin1_code":"29.0",
    "gn:asciiname":"Lazangu",
    "gn:country_code":"CN",
    "gn:dem":2010,
    "gn:feature_class":"P",
    "gn:feature_code":"PPL",
    "gn:name":"Lazangu",
    "gn:population":0,
    "gn:timezone":"Asia/Shanghai",
    "iso:country":"CN",
    "name:zho_x_preferred":[
        "\u62c9\u54b1\u53e4"
    ],
    "wof:name":"Lazangu",
    "wof:placetype":"locality"
},
  "geometry": {"coordinates":[100.056,27.1687],"type":"Point"}
}