{
  "type": "Feature",
  "properties": {
    "gn:admin1_code":"7",
    "gn:asciiname":"Wangshanli",
    "gn:country_code":"CN",
    "gn:dem":1164,
    "gn:feature_class":"P",
    "gn:feature_code":"PPL",
    "gn:name":"Wangshanli",
    "gn:population":0,
    "gn:timezone":"Asia/Shanghai",
    "iso:country":"CN",
    "name:zho_x_preferred":[
        "\u738b\u5c71\u91cc"
    ],
    "wof:name":"Wangshanli",
    "wof:placetype":"locality"
},
  "geometry": {"coordinates":[119.12194,27.21278],"type":"Point"}
}