{
  "type": "Feature",
  "properties": {
    "gn:admin1_code":"11",
    "gn:asciiname":"Shouyanzhen",
    "gn:country_code":"CN",
    "gn:dem":202,
    "gn:feature_class":"P",
    "gn:feature_code":"PPL",
    "gn:name":"Shouyanzhen",
    "gn:population":0,
    "gn:timezone":"Asia/Shanghai",
    "iso:country":"CN",
    "name:und_x_variant":[
        "Shou-yen-hs\u00fc",
        "Shouyanxu",
        "Shouyan",
        "Shouyanzhen"
    ],
    "name:zho_x_preferred":[
        "\u5bff\u96c1\u9547"
    ],
    "wof:name":"Shouyanzhen",
    "wof:placetype":"locality"
},
  "geometry": {"coordinates":[111.49556,25.57972],"type":"Point"}
}