{
  "type": "Feature",
  "properties": {
    "gn:admin1_code":"19.0",
    "gn:asciiname":"Lutuncun",
    "gn:country_code":"CN",
    "gn:dem":52,
    "gn:feature_class":"P",
    "gn:feature_code":"PPL",
    "gn:name":"Lutuncun",
    "gn:population":0,
    "gn:timezone":"Asia/Shanghai",
    "iso:country":"CN",
    "name:zho_x_preferred":[
        "\u8def\u5c6f\u6751"
    ],
    "wof:name":"Lutuncun",
    "wof:placetype":"locality"
},
  "geometry": {"coordinates":[121.742,41.54600000000001],"type":"Point"}
}