{
  "type": "Feature",
  "properties": {
    "gn:admin1_code":"25",
    "gn:asciiname":"Dongzhu",
    "gn:country_code":"CN",
    "gn:dem":21,
    "gn:feature_class":"P",
    "gn:feature_code":"PPL",
    "gn:name":"Dongzhu",
    "gn:population":0,
    "gn:timezone":"Asia/Shanghai",
    "iso:country":"CN",
    "name:zho_x_preferred":[
        "\u4e1c\u795d"
    ],
    "name:zho_x_variant":[
        "\u4e1c\u6e1a\u8857\u9053"
    ],
    "wof:name":"Dongzhu",
    "wof:placetype":"locality"
},
  "geometry": {"coordinates":[116.77200000000001,37.2596],"type":"Point"}
}