{
  "type": "Feature",
  "properties": {
    "gn:admin1_code":"30",
    "gn:asciiname":"Jinjingshan",
    "gn:country_code":"CN",
    "gn:dem":31,
    "gn:feature_class":"P",
    "gn:feature_code":"PPL",
    "gn:name":"Jinjingshan",
    "gn:population":0,
    "gn:timezone":"Asia/Shanghai",
    "iso:country":"CN",
    "name:und_x_variant":[
        "Jinggen",
        "Jinjingshan"
    ],
    "name:zho_x_preferred":[
        "\u91d1\u955c\u5c71"
    ],
    "wof:name":"Jinjingshan",
    "wof:placetype":"locality"
},
  "geometry": {"coordinates":[112.99204,22.636],"type":"Point"}
}