{
  "type": "Feature",
  "properties": {
    "gn:admin1_code":"24.0",
    "gn:asciiname":"Zhangmazhuang",
    "gn:country_code":"CN",
    "gn:dem":1174,
    "gn:feature_class":"P",
    "gn:feature_code":"PPL",
    "gn:name":"Zhangmazhuang",
    "gn:population":0,
    "gn:timezone":"Asia/Shanghai",
    "iso:country":"CN",
    "name:zho_x_preferred":[
        "\u5f20\u9a6c\u5e84"
    ],
    "wof:name":"Zhangmazhuang",
    "wof:placetype":"locality"
},
  "geometry": {"coordinates":[111.18442,36.1709],"type":"Point"}
}