{
  "type": "Feature",
  "properties": {
    "gn:admin1_code":"18",
    "gn:asciiname":"Suijizhai",
    "gn:country_code":"CN",
    "gn:dem":1371,
    "gn:feature_class":"P",
    "gn:feature_code":"PPL",
    "gn:name":"Suijizhai",
    "gn:population":0,
    "gn:timezone":"Asia/Shanghai",
    "iso:country":"CN",
    "name:zho_x_preferred":[
        "\u968b\u7b95\u5be8"
    ],
    "wof:name":"Suijizhai",
    "wof:placetype":"locality"
},
  "geometry": {"coordinates":[105.52200000000001,25.609],"type":"Point"}
}