{
  "type": "Feature",
  "properties": {
    "gn:admin1_code":"29.0",
    "gn:asciiname":"Yinchanggoucun",
    "gn:country_code":"CN",
    "gn:dem":1481,
    "gn:feature_class":"P",
    "gn:feature_code":"PPL",
    "gn:name":"Yinchanggoucun",
    "gn:population":0,
    "gn:timezone":"Asia/Shanghai",
    "iso:country":"CN",
    "name:zho_x_preferred":[
        "\u94f6\u5382\u6c9f\u6751"
    ],
    "wof:name":"Yinchanggoucun",
    "wof:placetype":"locality"
},
  "geometry": {"coordinates":[105.126,27.4369],"type":"Point"}
}