{
  "type": "Feature",
  "properties": {
    "gn:admin1_code":"24",
    "gn:asciiname":"Nanjia",
    "gn:country_code":"CN",
    "gn:dem":1209,
    "gn:feature_class":"P",
    "gn:feature_code":"PPL",
    "gn:name":"Nanjia",
    "gn:population":0,
    "gn:timezone":"Asia/Shanghai",
    "iso:country":"CN",
    "wof:name":"Nanjia",
    "wof:placetype":"locality"
},
  "geometry": {"coordinates":[112.15028,35.96389],"type":"Point"}
}