{
  "type": "Feature",
  "properties": {
    "gn:admin1_code":"16.0",
    "gn:asciiname":"Long'ang",
    "gn:country_code":"CN",
    "gn:dem":351,
    "gn:feature_class":"P",
    "gn:feature_code":"PPL",
    "gn:name":"Long\u2019ang",
    "gn:population":0,
    "gn:timezone":"Asia/Shanghai",
    "iso:country":"CN",
    "name:und_x_variant":[
        "Long\u2019ang"
    ],
    "name:zho_x_preferred":[
        "\u9f99\u76ce"
    ],
    "wof:name":"Long'ang",
    "wof:placetype":"locality"
},
  "geometry": {"coordinates":[107.304,23.3258],"type":"Point"}
}