{
  "type": "Feature",
  "properties": {
    "gn:admin1_code":"32.0",
    "gn:asciiname":"Jifumiao",
    "gn:country_code":"CN",
    "gn:dem":286,
    "gn:feature_class":"P",
    "gn:feature_code":"PPL",
    "gn:name":"Jifumiao",
    "gn:population":0,
    "gn:timezone":"Asia/Shanghai",
    "iso:country":"CN",
    "name:zho_x_preferred":[
        "\u5409\u798f\u5e99"
    ],
    "wof:name":"Jifumiao",
    "wof:placetype":"locality"
},
  "geometry": {"coordinates":[105.68921,30.45619000000001],"type":"Point"}
}