{
  "type": "Feature",
  "properties": {
    "gn:admin1_code":"14.0",
    "gn:asciiname":"Namugunba",
    "gn:country_code":"CN",
    "gn:dem":4008,
    "gn:feature_class":"P",
    "gn:feature_code":"PPL",
    "gn:name":"Namugunba",
    "gn:population":0,
    "gn:timezone":"Asia/Urumqi",
    "iso:country":"CN",
    "name:zho_x_preferred":[
        "\u90a3\u6728\u68cd\u5df4"
    ],
    "wof:name":"Namugunba",
    "wof:placetype":"locality"
},
  "geometry": {"coordinates":[91.07653999999999,29.97103],"type":"Point"}
}