{
  "type": "Feature",
  "properties": {
    "gn:admin1_code":"24.0",
    "gn:asciiname":"Xianjiashan",
    "gn:country_code":"CN",
    "gn:dem":1493,
    "gn:feature_class":"P",
    "gn:feature_code":"PPL",
    "gn:name":"Xianjiashan",
    "gn:population":0,
    "gn:timezone":"Asia/Shanghai",
    "iso:country":"CN",
    "name:zho_x_preferred":[
        "\u8d24\u5bb6\u5c71"
    ],
    "wof:name":"Xianjiashan",
    "wof:placetype":"locality"
},
  "geometry": {"coordinates":[111.30972,37.23879],"type":"Point"}
}