{
  "type": "Feature",
  "properties": {
    "gn:admin1_code":"31.0",
    "gn:asciiname":"Xianxiao",
    "gn:country_code":"CN",
    "gn:dem":54,
    "gn:feature_class":"P",
    "gn:feature_code":"PPL",
    "gn:name":"Xianxiao",
    "gn:population":0,
    "gn:timezone":"Asia/Shanghai",
    "iso:country":"CN",
    "name:zho_x_preferred":[
        "\u8d24\u5b5d"
    ],
    "wof:name":"Xianxiao",
    "wof:placetype":"locality"
},
  "geometry": {"coordinates":[110.66556,19.59815],"type":"Point"}
}