{
  "type": "Feature",
  "properties": {
    "gn:admin1_code":"19.0",
    "gn:asciiname":"Mayingzi",
    "gn:country_code":"CN",
    "gn:dem":298,
    "gn:feature_class":"P",
    "gn:feature_code":"PPL",
    "gn:name":"Mayingzi",
    "gn:population":0,
    "gn:timezone":"Asia/Shanghai",
    "iso:country":"CN",
    "name:zho_x_preferred":[
        "\u9a6c\u8425\u5b50"
    ],
    "wof:name":"Mayingzi",
    "wof:placetype":"locality"
},
  "geometry": {"coordinates":[120.0869,41.5073],"type":"Point"}
}