{
  "type": "Feature",
  "properties": {
    "gn:admin1_code":"32.0",
    "gn:asciiname":"Hujia Wuji",
    "gn:country_code":"CN",
    "gn:dem":914,
    "gn:feature_class":"P",
    "gn:feature_code":"PPL",
    "gn:name":"Hujia Wuji",
    "gn:population":0,
    "gn:timezone":"Asia/Shanghai",
    "iso:country":"CN",
    "name:zho_x_preferred":[
        "\u80e1\u5bb6\u5c4b\u57fa"
    ],
    "wof:name":"Hujia Wuji",
    "wof:placetype":"locality"
},
  "geometry": {"coordinates":[103.714,28.6394],"type":"Point"}
}