{
  "type": "Feature",
  "properties": {
    "gn:admin1_code":"3.0",
    "gn:asciiname":"Jingyuancun",
    "gn:country_code":"CN",
    "gn:dem":214,
    "gn:feature_class":"P",
    "gn:feature_code":"PPL",
    "gn:name":"Jingyuancun",
    "gn:population":0,
    "gn:timezone":"Asia/Shanghai",
    "iso:country":"CN",
    "name:und_x_variant":[
        "\u955c\u6e90\u6751"
    ],
    "wof:name":"Jingyuancun",
    "wof:placetype":"locality"
},
  "geometry": {"coordinates":[115.68474000000001,26.71191],"type":"Point"}
}