{
  "type": "Feature",
  "properties": {
    "gn:admin1_code":"21.0",
    "gn:asciiname":"Caizichuan",
    "gn:country_code":"CN",
    "gn:dem":2349,
    "gn:feature_class":"P",
    "gn:feature_code":"PPL",
    "gn:name":"Caizichuan",
    "gn:population":0,
    "gn:timezone":"Asia/Shanghai",
    "iso:country":"CN",
    "name:zho_x_preferred":[
        "\u83dc\u5b50\u5ddd"
    ],
    "wof:name":"Caizichuan",
    "wof:placetype":"locality"
},
  "geometry": {"coordinates":[106.179,35.5247],"type":"Point"}
}