{
  "type": "Feature",
  "properties": {
    "gn:admin1_code":"15.0",
    "gn:asciiname":"Liyaowan",
    "gn:country_code":"CN",
    "gn:dem":1328,
    "gn:feature_class":"P",
    "gn:feature_code":"PPL",
    "gn:name":"Liyaowan",
    "gn:population":0,
    "gn:timezone":"Asia/Shanghai",
    "iso:country":"CN",
    "name:und_x_variant":[
        "\u674e\u7a91\u6e7e"
    ],
    "wof:name":"Liyaowan",
    "wof:placetype":"locality"
},
  "geometry": {"coordinates":[107.14994,36.60921],"type":"Point"}
}