{
  "type": "Feature",
  "properties": {
    "gn:admin1_code":"20.0",
    "gn:asciiname":"Sanhe Machang Xidi Yingzi",
    "gn:country_code":"CN",
    "gn:dem":633,
    "gn:feature_class":"P",
    "gn:feature_code":"PPL",
    "gn:name":"Sanhe Machang Xidi Yingzi",
    "gn:population":0,
    "gn:timezone":"Asia/Shanghai",
    "iso:country":"CN",
    "name:zho_x_preferred":[
        "\u4e09\u6cb3\u9a6c\u573a\u897f\u5730\u8425\u5b50"
    ],
    "wof:name":"Sanhe Machang Xidi Yingzi",
    "wof:placetype":"locality"
},
  "geometry": {"coordinates":[119.65326,50.26004],"type":"Point"}
}