{
  "type": "Feature",
  "properties": {
    "gn:admin1_code":"1.0",
    "gn:asciiname":"Chenliu",
    "gn:country_code":"CN",
    "gn:dem":11,
    "gn:feature_class":"P",
    "gn:feature_code":"PPL",
    "gn:name":"Chenliu",
    "gn:population":0,
    "gn:timezone":"Asia/Shanghai",
    "iso:country":"CN",
    "name:fas_x_preferred":[
        "\u0686\u0646\u0644\u06cc\u0648"
    ],
    "name:fra_x_preferred":[
        "Chenliu"
    ],
    "name:zho_x_preferred":[
        "\u9648\u5218"
    ],
    "name:zho_x_variant":[
        "\u9648\u7559\u9547"
    ],
    "wof:name":"Chenliu",
    "wof:placetype":"locality"
},
  "geometry": {"coordinates":[118.30901,31.59241],"type":"Point"}
}