{
  "type": "Feature",
  "properties": {
    "gn:admin1_code":"26.0",
    "gn:asciiname":"Kangjia Dawu",
    "gn:country_code":"CN",
    "gn:dem":929,
    "gn:feature_class":"P",
    "gn:feature_code":"PPL",
    "gn:name":"Kangjia Dawu",
    "gn:population":0,
    "gn:timezone":"Asia/Shanghai",
    "iso:country":"CN",
    "name:zho_x_preferred":[
        "\u5eb7\u5bb6\u5927\u5c4b"
    ],
    "wof:name":"Kangjia Dawu",
    "wof:placetype":"locality"
},
  "geometry": {"coordinates":[109.55495000000001,31.98529000000001],"type":"Point"}
}