{
  "type": "Feature",
  "properties": {
    "gn:admin1_code":"2.0",
    "gn:asciiname":"Yanmenxia",
    "gn:country_code":"CN",
    "gn:dem":417,
    "gn:feature_class":"P",
    "gn:feature_code":"PPL",
    "gn:name":"Yanmenxia",
    "gn:population":0,
    "gn:timezone":"Asia/Shanghai",
    "iso:country":"CN",
    "name:zho_x_preferred":[
        "\u5ca9\u95e8\u4e0b"
    ],
    "wof:name":"Yanmenxia",
    "wof:placetype":"locality"
},
  "geometry": {"coordinates":[120.64555,28.5471],"type":"Point"}
}