{
  "type": "Feature",
  "properties": {
    "gn:admin1_code":"5.0",
    "gn:asciiname":"Xinnongcun",
    "gn:country_code":"CN",
    "gn:dem":224,
    "gn:feature_class":"P",
    "gn:feature_code":"PPLF",
    "gn:name":"Xinnongcun",
    "gn:population":0,
    "gn:timezone":"Asia/Shanghai",
    "iso:country":"CN",
    "name:zho_x_preferred":[
        "\u65b0\u519c\u6751"
    ],
    "wof:name":"Xinnongcun",
    "wof:placetype":"locality"
},
  "geometry": {"coordinates":[125.50324000000001,43.95012],"type":"Point"}
}