{
  "type": "Feature",
  "properties": {
    "gn:admin1_code":"15.0",
    "gn:asciiname":"Changliu",
    "gn:country_code":"CN",
    "gn:dem":1792,
    "gn:feature_class":"P",
    "gn:feature_code":"PPL",
    "gn:name":"Changliu",
    "gn:population":0,
    "gn:timezone":"Asia/Shanghai",
    "iso:country":"CN",
    "name:fas_x_preferred":[
        "\u0686\u0627\u0646\u06af\u0644\u06cc\u0648"
    ],
    "name:zho_x_preferred":[
        "\u957f\u6d41"
    ],
    "name:zho_x_variant":[
        "\u957f\u6d41\u9547"
    ],
    "wof:name":"Changliu",
    "wof:placetype":"locality"
},
  "geometry": {"coordinates":[102.70999999999999,37.7042],"type":"Point"}
}