{
  "type": "Feature",
  "properties": {
    "gn:admin1_code":"32.0",
    "gn:asciiname":"Guangli",
    "gn:country_code":"CN",
    "gn:dem":353,
    "gn:feature_class":"P",
    "gn:feature_code":"PPL",
    "gn:name":"Guangli",
    "gn:population":0,
    "gn:timezone":"Asia/Shanghai",
    "iso:country":"CN",
    "name:zho_x_preferred":[
        "\u5e7f\u5229"
    ],
    "wof:name":"Guangli",
    "wof:placetype":"locality"
},
  "geometry": {"coordinates":[105.24160000000001,30.80318],"type":"Point"}
}