{
  "type": "Feature",
  "properties": {
    "gn:admin1_code":"16.0",
    "gn:asciiname":"Guochao",
    "gn:country_code":"CN",
    "gn:dem":1105,
    "gn:feature_class":"P",
    "gn:feature_code":"PPL",
    "gn:name":"Guochao",
    "gn:population":0,
    "gn:timezone":"Asia/Shanghai",
    "iso:country":"CN",
    "name:zho_x_preferred":[
        "\u679c\u671d"
    ],
    "wof:name":"Guochao",
    "wof:placetype":"locality"
},
  "geometry": {"coordinates":[106.51900000000001,24.3217],"type":"Point"}
}