{
  "type": "Feature",
  "properties": {
    "gn:admin1_code":"14",
    "gn:asciiname":"Jidibama",
    "gn:country_code":"CN",
    "gn:dem":4853,
    "gn:feature_class":"P",
    "gn:feature_code":"PPL",
    "gn:name":"Jidibama",
    "gn:population":0,
    "gn:timezone":"Asia/Urumqi",
    "iso:country":"CN",
    "name:zho_x_preferred":[
        "\u5409\u5730\u5df4\u739b"
    ],
    "wof:name":"Jidibama",
    "wof:placetype":"locality"
},
  "geometry": {"coordinates":[88.5791,30.2928],"type":"Point"}
}