{
  "type": "Feature",
  "properties": {
    "gn:admin1_code":"26.0",
    "gn:asciiname":"Podicun",
    "gn:country_code":"CN",
    "gn:dem":1041,
    "gn:feature_class":"P",
    "gn:feature_code":"PPL",
    "gn:name":"Podicun",
    "gn:population":0,
    "gn:timezone":"Asia/Shanghai",
    "iso:country":"CN",
    "name:zho_x_preferred":[
        "\u5761\u5e95\u6751"
    ],
    "wof:name":"Podicun",
    "wof:placetype":"locality"
},
  "geometry": {"coordinates":[109.37629,36.2352],"type":"Point"}
}