{
  "type": "Feature",
  "properties": {
    "gn:admin1_code":"1.0",
    "gn:asciiname":"Sangbeicun",
    "gn:country_code":"CN",
    "gn:dem":65,
    "gn:feature_class":"P",
    "gn:feature_code":"PPL",
    "gn:name":"Sangbeicun",
    "gn:population":0,
    "gn:timezone":"Asia/Shanghai",
    "iso:country":"CN",
    "name:zho_x_preferred":[
        "\u6851\u5317\u6751"
    ],
    "wof:name":"Sangbeicun",
    "wof:placetype":"locality"
},
  "geometry": {"coordinates":[117.80616999999999,32.53624],"type":"Point"}
}