{
  "type": "Feature",
  "properties": {
    "gn:admin1_code":"25.0",
    "gn:asciiname":"Daleishicun",
    "gn:country_code":"CN",
    "gn:dem":132,
    "gn:feature_class":"P",
    "gn:feature_code":"PPL",
    "gn:name":"Daleishicun",
    "gn:population":0,
    "gn:timezone":"Asia/Shanghai",
    "iso:country":"CN",
    "name:zho_x_preferred":[
        "\u5927\u78ca\u77f3\u6751"
    ],
    "wof:name":"Daleishicun",
    "wof:placetype":"locality"
},
  "geometry": {"coordinates":[121.09977000000001,36.84174],"type":"Point"}
}