{
  "type": "Feature",
  "properties": {
    "gn:admin1_code":"11.0",
    "gn:asciiname":"Laocaixi",
    "gn:country_code":"CN",
    "gn:dem":244,
    "gn:feature_class":"P",
    "gn:feature_code":"PPL",
    "gn:name":"Laocaixi",
    "gn:population":0,
    "gn:timezone":"Asia/Shanghai",
    "iso:country":"CN",
    "name:zho_x_preferred":[
        "\u8001\u624d\u6eaa"
    ],
    "wof:name":"Laocaixi",
    "wof:placetype":"locality"
},
  "geometry": {"coordinates":[109.76425999999999,27.68556],"type":"Point"}
}