{
  "type": "Feature",
  "properties": {
    "gn:admin1_code":"26.0",
    "gn:asciiname":"Fengxiangping",
    "gn:country_code":"CN",
    "gn:dem":769,
    "gn:feature_class":"P",
    "gn:feature_code":"PPL",
    "gn:name":"Fengxiangping",
    "gn:population":0,
    "gn:timezone":"Asia/Shanghai",
    "iso:country":"CN",
    "name:zho_x_preferred":[
        "\u5c01\u9999\u576a"
    ],
    "wof:name":"Fengxiangping",
    "wof:placetype":"locality"
},
  "geometry": {"coordinates":[109.89117,32.61724],"type":"Point"}
}