{
  "type": "Feature",
  "properties": {
    "gn:admin1_code":"20.0",
    "gn:asciiname":"Nuomenhan Buride",
    "gn:country_code":"CN",
    "gn:dem":731,
    "gn:feature_class":"P",
    "gn:feature_code":"PPL",
    "gn:name":"Nuomenhan Buride",
    "gn:population":0,
    "gn:timezone":"Asia/Shanghai",
    "iso:country":"CN",
    "name:zho_x_preferred":[
        "\u8bfa\u95e8\u7f55\u5e03\u65e5\u5fb7"
    ],
    "wof:name":"Nuomenhan Buride",
    "wof:placetype":"locality"
},
  "geometry": {"coordinates":[118.82538999999998,47.85001],"type":"Point"}
}