{
  "type": "Feature",
  "properties": {
    "gn:admin1_code":"30",
    "gn:asciiname":"Masi",
    "gn:country_code":"CN",
    "gn:dem":4,
    "gn:feature_class":"P",
    "gn:feature_code":"PPL",
    "gn:name":"Masi",
    "gn:population":0,
    "gn:timezone":"Asia/Shanghai",
    "iso:country":"CN",
    "name:ceb_x_preferred":[
        "Masi"
    ],
    "name:deu_x_preferred":[
        "Masi"
    ],
    "name:fra_x_preferred":[
        "Masi"
    ],
    "name:ita_x_preferred":[
        "Masi"
    ],
    "name:nld_x_preferred":[
        "Masi"
    ],
    "name:pol_x_preferred":[
        "Masi"
    ],
    "name:spa_x_preferred":[
        "Masi"
    ],
    "name:srp_x_preferred":[
        "Mazi"
    ],
    "name:swe_x_preferred":[
        "Masi"
    ],
    "name:und_x_variant":[
        "Ma-ssu",
        "Masi",
        "\u9a6c\u5636"
    ],
    "wof:name":"Masi",
    "wof:placetype":"locality"
},
  "geometry": {"coordinates":[114.03676000000002,23.10765],"type":"Point"}
}