{
  "type": "Feature",
  "properties": {
    "gn:admin1_code":"19.0",
    "gn:asciiname":"Liangzhongchang",
    "gn:country_code":"CN",
    "gn:dem":87,
    "gn:feature_class":"P",
    "gn:feature_code":"PPL",
    "gn:name":"Liangzhongchang",
    "gn:population":0,
    "gn:timezone":"Asia/Shanghai",
    "iso:country":"CN",
    "name:zho_x_preferred":[
        "\u826f\u79cd\u573a"
    ],
    "wof:name":"Liangzhongchang",
    "wof:placetype":"locality"
},
  "geometry": {"coordinates":[123.999,42.5365],"type":"Point"}
}