{
  "type": "Feature",
  "properties": {
    "gn:admin1_code":"16.0",
    "gn:asciiname":"Neilu",
    "gn:country_code":"CN",
    "gn:dem":339,
    "gn:feature_class":"P",
    "gn:feature_code":"PPL",
    "gn:name":"Neilu",
    "gn:population":0,
    "gn:timezone":"Asia/Shanghai",
    "iso:country":"CN",
    "name:zho_x_preferred":[
        "\u5185\u7089"
    ],
    "wof:name":"Neilu",
    "wof:placetype":"locality"
},
  "geometry": {"coordinates":[108.206,23.7828],"type":"Point"}
}