{
  "type": "Feature",
  "properties": {
    "gn:admin1_code":"4.0",
    "gn:asciiname":"Chengjiao",
    "gn:country_code":"CN",
    "gn:dem":9,
    "gn:feature_class":"P",
    "gn:feature_code":"PPL",
    "gn:name":"Chengjiao",
    "gn:population":0,
    "gn:timezone":"Asia/Shanghai",
    "iso:country":"CN",
    "name:zho_x_preferred":[
        "Chengjiao"
    ],
    "name:zho_x_variant":[
        "\u57ce\u90ca"
    ],
    "wof:name":"Chengjiao",
    "wof:placetype":"locality"
},
  "geometry": {"coordinates":[119.13073,33.53583],"type":"Point"}
}