{
  "type": "Feature",
  "properties": {
    "gn:admin1_code":"18.0",
    "gn:asciiname":"Miaotianchong",
    "gn:country_code":"CN",
    "gn:dem":509,
    "gn:feature_class":"P",
    "gn:feature_code":"PPL",
    "gn:name":"Miaotianchong",
    "gn:population":0,
    "gn:timezone":"Asia/Shanghai",
    "iso:country":"CN",
    "name:zho_x_preferred":[
        "\u82d7\u7530\u51b2"
    ],
    "wof:name":"Miaotianchong",
    "wof:placetype":"locality"
},
  "geometry": {"coordinates":[109.35599999999999,27.0667],"type":"Point"}
}