{
  "type": "Feature",
  "properties": {
    "gn:admin1_code":"26.0",
    "gn:asciiname":"Anjiawancun",
    "gn:country_code":"CN",
    "gn:dem":1063,
    "gn:feature_class":"P",
    "gn:feature_code":"PPL",
    "gn:name":"Anjiawancun",
    "gn:population":0,
    "gn:timezone":"Asia/Shanghai",
    "iso:country":"CN",
    "name:zho_x_preferred":[
        "\u5b89\u5bb6\u6e7e\u6751"
    ],
    "wof:name":"Anjiawancun",
    "wof:placetype":"locality"
},
  "geometry": {"coordinates":[107.21619,32.53761],"type":"Point"}
}