{
  "type": "Feature",
  "properties": {
    "gn:admin1_code":"11.0",
    "gn:asciiname":"Huangmu'ao",
    "gn:country_code":"CN",
    "gn:dem":791,
    "gn:feature_class":"P",
    "gn:feature_code":"PPL",
    "gn:name":"Huangmu\u2019ao",
    "gn:population":0,
    "gn:timezone":"Asia/Shanghai",
    "iso:country":"CN",
    "name:und_x_variant":[
        "Huangmu\u2019ao"
    ],
    "name:zho_x_preferred":[
        "\u9ec4\u6728\u5773"
    ],
    "wof:name":"Huangmu'ao",
    "wof:placetype":"locality"
},
  "geometry": {"coordinates":[112.39960000000001,25.19051],"type":"Point"}
}