{
  "type": "Feature",
  "properties": {
    "gn:admin1_code":"10.0",
    "gn:asciiname":"Jianhuabu",
    "gn:country_code":"CN",
    "gn:dem":907,
    "gn:feature_class":"P",
    "gn:feature_code":"PPL",
    "gn:name":"Jianhuabu",
    "gn:population":0,
    "gn:timezone":"Asia/Shanghai",
    "iso:country":"CN",
    "name:zho_x_preferred":[
        "\u62e3\u82b1\u5821"
    ],
    "wof:name":"Jianhuabu",
    "wof:placetype":"locality"
},
  "geometry": {"coordinates":[114.06825000000001,40.05894],"type":"Point"}
}