{
  "type": "Feature",
  "properties": {
    "gn:admin1_code":"18",
    "gn:asciiname":"Fawo",
    "gn:country_code":"CN",
    "gn:dem":2097,
    "gn:feature_class":"P",
    "gn:feature_code":"PPL",
    "gn:name":"Fawo",
    "gn:population":0,
    "gn:timezone":"Asia/Shanghai",
    "iso:country":"CN",
    "name:zho_x_preferred":[
        "\u53d1\u7a9d"
    ],
    "wof:name":"Fawo",
    "wof:placetype":"locality"
},
  "geometry": {"coordinates":[104.42400000000001,26.8184],"type":"Point"}
}