{
  "type": "Feature",
  "properties": {
    "gn:admin1_code":"24.0",
    "gn:asciiname":"Pingdichuan",
    "gn:country_code":"CN",
    "gn:dem":1456,
    "gn:feature_class":"P",
    "gn:feature_code":"PPL",
    "gn:name":"Pingdichuan",
    "gn:population":0,
    "gn:timezone":"Asia/Shanghai",
    "iso:country":"CN",
    "name:zho_x_preferred":[
        "\u576a\u5730\u5ddd"
    ],
    "wof:name":"Pingdichuan",
    "wof:placetype":"locality"
},
  "geometry": {"coordinates":[113.72582,37.33662],"type":"Point"}
}