{
  "type": "Feature",
  "properties": {
    "gn:admin1_code":"14.0",
    "gn:asciiname":"Ganam",
    "gn:country_code":"CN",
    "gn:dem":2812,
    "gn:feature_class":"P",
    "gn:feature_code":"PPL",
    "gn:name":"Ganam",
    "gn:population":0,
    "gn:timezone":"Asia/Urumqi",
    "iso:country":"CN",
    "name:bod_x_preferred":[
        "Ganam"
    ],
    "name:zho_x_preferred":[
        "Galang"
    ],
    "name:zho_x_variant":[
        "\u560e\u90ce",
        "Kada Gongshe",
        "\u5361\u8fbe\u516c\u793e"
    ],
    "wof:name":"Ganam",
    "wof:placetype":"locality"
},
  "geometry": {"coordinates":[95.62089,29.91917],"type":"Point"}
}