{
  "type": "Feature",
  "properties": {
    "gn:admin1_code":"32.0",
    "gn:asciiname":"Hamucuo",
    "gn:country_code":"CN",
    "gn:dem":3182,
    "gn:feature_class":"P",
    "gn:feature_code":"PPL",
    "gn:name":"Hamucuo",
    "gn:population":0,
    "gn:timezone":"Asia/Shanghai",
    "iso:country":"CN",
    "name:zho_x_preferred":[
        "\u54c8\u6728\u9519"
    ],
    "wof:name":"Hamucuo",
    "wof:placetype":"locality"
},
  "geometry": {"coordinates":[101.521,32.6279],"type":"Point"}
}