{
  "type": "Feature",
  "properties": {
    "gn:admin1_code":"5.0",
    "gn:asciiname":"Daweitanggou",
    "gn:country_code":"CN",
    "gn:dem":411,
    "gn:feature_class":"P",
    "gn:feature_code":"PPL",
    "gn:name":"Daweitanggou",
    "gn:population":0,
    "gn:timezone":"Asia/Shanghai",
    "iso:country":"CN",
    "name:und_x_variant":[
        "\u5927\u82c7\u5858\u6c9f"
    ],
    "wof:name":"Daweitanggou",
    "wof:placetype":"locality"
},
  "geometry": {"coordinates":[125.73515999999999,41.59136],"type":"Point"}
}