{
  "type": "Feature",
  "properties": {
    "gn:admin1_code":"16.0",
    "gn:asciiname":"Donglang",
    "gn:country_code":"CN",
    "gn:dem":173,
    "gn:feature_class":"P",
    "gn:feature_code":"PPL",
    "gn:name":"Donglang",
    "gn:population":0,
    "gn:timezone":"Asia/Shanghai",
    "iso:country":"CN",
    "name:zho_x_preferred":[
        "\u5cbd\u6d6a"
    ],
    "wof:name":"Donglang",
    "wof:placetype":"locality"
},
  "geometry": {"coordinates":[107.29000000000001,22.0104],"type":"Point"}
}