{
  "type": "Feature",
  "properties": {
    "gn:admin1_code":"20.0",
    "gn:asciiname":"Houwulan Hada",
    "gn:country_code":"CN",
    "gn:dem":1707,
    "gn:feature_class":"P",
    "gn:feature_code":"PPL",
    "gn:name":"Houwulan Hada",
    "gn:population":0,
    "gn:timezone":"Asia/Shanghai",
    "iso:country":"CN",
    "name:und_x_variant":[
        "\u540e\u4e4c\u5170\u54c8\u8fbe"
    ],
    "wof:name":"Houwulan Hada",
    "wof:placetype":"locality"
},
  "geometry": {"coordinates":[111.06178,40.90566],"type":"Point"}
}