{
  "type": "Feature",
  "properties": {
    "gn:admin1_code":"16.0",
    "gn:asciiname":"Podou",
    "gn:country_code":"CN",
    "gn:dem":1134,
    "gn:feature_class":"P",
    "gn:feature_code":"PPL",
    "gn:name":"Podou",
    "gn:population":0,
    "gn:timezone":"Asia/Shanghai",
    "iso:country":"CN",
    "name:zho_x_preferred":[
        "\u5761\u6597"
    ],
    "wof:name":"Podou",
    "wof:placetype":"locality"
},
  "geometry": {"coordinates":[105.449,24.6196],"type":"Point"}
}