{
  "type": "Feature",
  "properties": {
    "gn:admin1_code":"32.0",
    "gn:asciiname":"Guanyan",
    "gn:country_code":"CN",
    "gn:dem":463,
    "gn:feature_class":"P",
    "gn:feature_code":"PPL",
    "gn:name":"Guanyan",
    "gn:population":0,
    "gn:timezone":"Asia/Shanghai",
    "iso:country":"CN",
    "name:zho_x_preferred":[
        "\u5173\u5830"
    ],
    "wof:name":"Guanyan",
    "wof:placetype":"locality"
},
  "geometry": {"coordinates":[104.104,30.3187],"type":"Point"}
}