{
  "type": "Feature",
  "properties": {
    "gn:admin1_code":"2.0",
    "gn:asciiname":"Caotamiao",
    "gn:country_code":"CN",
    "gn:dem":5,
    "gn:feature_class":"P",
    "gn:feature_code":"PPL",
    "gn:name":"Caotamiao",
    "gn:population":0,
    "gn:timezone":"Asia/Shanghai",
    "iso:country":"CN",
    "name:und_x_variant":[
        "\u8349\u5854\u5e99"
    ],
    "wof:name":"Caotamiao",
    "wof:placetype":"locality"
},
  "geometry": {"coordinates":[121.22389,30.73212],"type":"Point"}
}