{
  "type": "Feature",
  "properties": {
    "gn:admin1_code":"3",
    "gn:asciiname":"Shanggushi",
    "gn:country_code":"CN",
    "gn:dem":1088,
    "gn:feature_class":"P",
    "gn:feature_code":"PPL",
    "gn:name":"Shanggushi",
    "gn:population":0,
    "gn:timezone":"Asia/Shanghai",
    "iso:country":"CN",
    "name:zho_x_preferred":[
        "\u4e0a\u9f13\u77f3"
    ],
    "wof:name":"Shanggushi",
    "wof:placetype":"locality"
},
  "geometry": {"coordinates":[114.093,25.8944],"type":"Point"}
}