{
  "type": "Feature",
  "properties": {
    "gn:admin1_code":"29",
    "gn:asciiname":"Luojiayi",
    "gn:country_code":"CN",
    "gn:dem":1575,
    "gn:feature_class":"P",
    "gn:feature_code":"PPL",
    "gn:name":"Luojiayi",
    "gn:population":0,
    "gn:timezone":"Asia/Shanghai",
    "iso:country":"CN",
    "name:zho_x_preferred":[
        "\u502e\u5bb6\u9091"
    ],
    "wof:name":"Luojiayi",
    "wof:placetype":"locality"
},
  "geometry": {"coordinates":[104.18300000000001,23.5445],"type":"Point"}
}