{
  "type": "Feature",
  "properties": {
    "gn:admin1_code":"30",
    "gn:asciiname":"Xiutianwei",
    "gn:country_code":"CN",
    "gn:dem":233,
    "gn:feature_class":"P",
    "gn:feature_code":"PPL",
    "gn:name":"Xiutianwei",
    "gn:population":0,
    "gn:timezone":"Asia/Shanghai",
    "iso:country":"CN",
    "name:zho_x_preferred":[
        "\u79c0\u7530\u5c3e"
    ],
    "wof:name":"Xiutianwei",
    "wof:placetype":"locality"
},
  "geometry": {"coordinates":[115.90449,24.37794],"type":"Point"}
}