{
  "type": "Feature",
  "properties": {
    "gn:admin1_code":"24.0",
    "gn:asciiname":"Fengzecun",
    "gn:country_code":"CN",
    "gn:dem":758,
    "gn:feature_class":"P",
    "gn:feature_code":"PPL",
    "gn:name":"Fengzecun",
    "gn:population":0,
    "gn:timezone":"Asia/Shanghai",
    "iso:country":"CN",
    "name:zho_x_preferred":[
        "\u4e30\u6cfd\u6751"
    ],
    "wof:name":"Fengzecun",
    "wof:placetype":"locality"
},
  "geometry": {"coordinates":[112.32474000000001,37.38302],"type":"Point"}
}