{
  "type": "Feature",
  "properties": {
    "gn:admin1_code":"09",
    "gn:asciiname":"Baitan",
    "gn:cc2":"CN",
    "gn:country_code":"CN",
    "gn:dem":62,
    "gn:feature_class":"P",
    "gn:feature_code":"PPL",
    "gn:name":"Baitan",
    "gn:population":0,
    "gn:timezone":"Asia/Shanghai",
    "iso:country":"CN",
    "name:und_x_variant":[
        "Pai-t\u2019an",
        "Baitan"
    ],
    "wof:name":"Baitan",
    "wof:placetype":"locality"
},
  "geometry": {"coordinates":[114.34999999999999,34.25],"type":"Point"}
}