{
  "type": "Feature",
  "properties": {
    "gn:admin1_code":"20.0",
    "gn:asciiname":"Qirumutai",
    "gn:country_code":"CN",
    "gn:dem":253,
    "gn:feature_class":"P",
    "gn:feature_code":"PPL",
    "gn:name":"Qirumutai",
    "gn:population":0,
    "gn:timezone":"Asia/Shanghai",
    "iso:country":"CN",
    "name:zho_x_preferred":[
        "\u5947\u5982\u6728\u53f0"
    ],
    "wof:name":"Qirumutai",
    "wof:placetype":"locality"
},
  "geometry": {"coordinates":[124.79038,49.43233],"type":"Point"}
}