{
  "type": "Feature",
  "properties": {
    "gn:admin1_code":"10.0",
    "gn:asciiname":"Lujiaxiu",
    "gn:country_code":"CN",
    "gn:dem":6,
    "gn:feature_class":"P",
    "gn:feature_code":"PPL",
    "gn:name":"Lujiaxiu",
    "gn:population":0,
    "gn:timezone":"Asia/Shanghai",
    "iso:country":"CN",
    "name:zho_x_preferred":[
        "\u82a6\u7532\u5cab"
    ],
    "wof:name":"Lujiaxiu",
    "wof:placetype":"locality"
},
  "geometry": {"coordinates":[117.67161000000002,39.70368],"type":"Point"}
}