{
  "type": "Feature",
  "properties": {
    "gn:admin1_code":"5.0",
    "gn:asciiname":"Niuxin",
    "gn:country_code":"CN",
    "gn:dem":617,
    "gn:feature_class":"P",
    "gn:feature_code":"PPL",
    "gn:name":"Niuxin",
    "gn:population":0,
    "gn:timezone":"Asia/Shanghai",
    "iso:country":"CN",
    "name:und_x_variant":[
        "\u725b\u5fc3",
        "Niuxincun",
        "\u725b\u5fc3\u6751"
    ],
    "wof:name":"Niuxin",
    "wof:placetype":"locality"
},
  "geometry": {"coordinates":[129.02529999999999,42.43194],"type":"Point"}
}