{
  "type": "Feature",
  "properties": {
    "gn:admin1_code":"30.0",
    "gn:asciiname":"Hekou Linchang Dajian Gongqu",
    "gn:country_code":"CN",
    "gn:dem":206,
    "gn:feature_class":"P",
    "gn:feature_code":"PPLF",
    "gn:name":"Hekou Linchang Dajian Gongqu",
    "gn:population":0,
    "gn:timezone":"Asia/Shanghai",
    "iso:country":"CN",
    "name:und_x_variant":[
        "\u6cb3\u53e3\u6797\u573a\u5927\u67a7\u5de5\u533a"
    ],
    "wof:name":"Hekou Linchang Dajian Gongqu",
    "wof:placetype":"locality"
},
  "geometry": {"coordinates":[114.09846,24.74221],"type":"Point"}
}