{
  "type": "Feature",
  "properties": {
    "gn:admin1_code":"16.0",
    "gn:asciiname":"Zhilang",
    "gn:cc2":"CN",
    "gn:country_code":"CN",
    "gn:dem":222,
    "gn:feature_class":"P",
    "gn:feature_code":"PPL",
    "gn:name":"Zhilang",
    "gn:population":0,
    "gn:timezone":"Asia/Shanghai",
    "iso:country":"CN",
    "name:und_x_variant":[
        "Chih-lang",
        "Zhilang"
    ],
    "wof:name":"Zhilang",
    "wof:placetype":"locality"
},
  "geometry": {"coordinates":[107.09999999999999,21.86667000000001],"type":"Point"}
}