{
  "type": "Feature",
  "properties": {
    "gn:admin1_code":"29.0",
    "gn:asciiname":"Wanzi",
    "gn:country_code":"CN",
    "gn:dem":2249,
    "gn:feature_class":"P",
    "gn:feature_code":"PPL",
    "gn:name":"Wanzi",
    "gn:population":0,
    "gn:timezone":"Asia/Shanghai",
    "iso:country":"CN",
    "name:zho_x_preferred":[
        "\u5f2f\u5b50"
    ],
    "wof:name":"Wanzi",
    "wof:placetype":"locality"
},
  "geometry": {"coordinates":[103.04000000000001,26.2602],"type":"Point"}
}