{
  "type": "Feature",
  "properties": {
    "gn:admin1_code":"7.0",
    "gn:asciiname":"Xi'an",
    "gn:country_code":"CN",
    "gn:dem":132,
    "gn:feature_class":"P",
    "gn:feature_code":"PPL",
    "gn:name":"Xi\u2019an",
    "gn:population":0,
    "gn:timezone":"Asia/Shanghai",
    "iso:country":"CN",
    "name:und_x_variant":[
        "Xi\u2019an"
    ],
    "name:zho_x_preferred":[
        "\u897f\u5b89"
    ],
    "wof:name":"Xi'an",
    "wof:placetype":"locality"
},
  "geometry": {"coordinates":[118.26429,25.34141],"type":"Point"}
}