{
  "type": "Feature",
  "properties": {
    "gn:admin1_code":"8.0",
    "gn:asciiname":"Niuweiba Gangzi",
    "gn:country_code":"CN",
    "gn:dem":146,
    "gn:feature_class":"P",
    "gn:feature_code":"PPL",
    "gn:name":"Niuweiba Gangzi",
    "gn:population":0,
    "gn:timezone":"Asia/Shanghai",
    "iso:country":"CN",
    "name:zho_x_preferred":[
        "\u725b\u5c3e\u5df4\u5c97\u5b50"
    ],
    "wof:name":"Niuweiba Gangzi",
    "wof:placetype":"locality"
},
  "geometry": {"coordinates":[124.44316000000001,47.21207],"type":"Point"}
}