{
  "type": "Feature",
  "properties": {
    "gn:admin1_code":"16.0",
    "gn:asciiname":"Longya",
    "gn:country_code":"CN",
    "gn:dem":105,
    "gn:feature_class":"P",
    "gn:feature_code":"PPL",
    "gn:name":"Longya",
    "gn:population":0,
    "gn:timezone":"Asia/Shanghai",
    "iso:country":"CN",
    "name:zho_x_preferred":[
        "\u9f99\u96c5"
    ],
    "wof:name":"Longya",
    "wof:placetype":"locality"
},
  "geometry": {"coordinates":[111.61499999999999,24.4353],"type":"Point"}
}