{
  "type": "Feature",
  "properties": {
    "gn:admin1_code":"25",
    "gn:asciiname":"Caiyuanliu",
    "gn:country_code":"CN",
    "gn:dem":11,
    "gn:feature_class":"P",
    "gn:feature_code":"PPL",
    "gn:name":"Caiyuanliu",
    "gn:population":0,
    "gn:timezone":"Asia/Shanghai",
    "iso:country":"CN",
    "name:zho_x_preferred":[
        "\u83dc\u56ed\u5218"
    ],
    "wof:name":"Caiyuanliu",
    "wof:placetype":"locality"
},
  "geometry": {"coordinates":[117.714,37.5379],"type":"Point"}
}