{
  "type": "Feature",
  "properties": {
    "gn:admin1_code":"10",
    "gn:asciiname":"Moding",
    "gn:country_code":"CN",
    "gn:dem":64,
    "gn:feature_class":"P",
    "gn:feature_code":"PPL",
    "gn:name":"Moding",
    "gn:population":0,
    "gn:timezone":"Asia/Shanghai",
    "iso:country":"CN",
    "name:zho_x_preferred":[
        "\u62b9\u753a"
    ],
    "wof:name":"Moding",
    "wof:placetype":"locality"
},
  "geometry": {"coordinates":[114.75700000000001,36.328],"type":"Point"}
}