{
  "type": "Feature",
  "properties": {
    "gn:admin1_code":"5.0",
    "gn:asciiname":"Zhangjiajiecun",
    "gn:country_code":"CN",
    "gn:dem":190,
    "gn:feature_class":"P",
    "gn:feature_code":"PPL",
    "gn:name":"Zhangjiajiecun",
    "gn:population":0,
    "gn:timezone":"Asia/Shanghai",
    "iso:country":"CN",
    "name:zho_x_preferred":[
        "\u5f20\u5bb6\u8857\u6751"
    ],
    "wof:name":"Zhangjiajiecun",
    "wof:placetype":"locality"
},
  "geometry": {"coordinates":[124.37076,43.43333],"type":"Point"}
}