{
  "type": "Feature",
  "properties": {
    "gn:admin1_code":"12.0",
    "gn:asciiname":"Tieluling",
    "gn:country_code":"CN",
    "gn:dem":158,
    "gn:feature_class":"P",
    "gn:feature_code":"PPL",
    "gn:name":"Tieluling",
    "gn:population":0,
    "gn:timezone":"Asia/Shanghai",
    "iso:country":"CN",
    "name:zho_x_preferred":[
        "Tieluling"
    ],
    "name:zho_x_variant":[
        "\u94c1\u7089\u5cad"
    ],
    "wof:name":"Tieluling",
    "wof:placetype":"locality"
},
  "geometry": {"coordinates":[114.11874,29.4608],"type":"Point"}
}