{
  "type": "Feature",
  "properties": {
    "gn:admin1_code":"20.0",
    "gn:asciiname":"Xudi Yingzi",
    "gn:country_code":"CN",
    "gn:dem":318,
    "gn:feature_class":"P",
    "gn:feature_code":"PPL",
    "gn:name":"Xudi Yingzi",
    "gn:population":0,
    "gn:timezone":"Asia/Shanghai",
    "iso:country":"CN",
    "name:zho_x_preferred":[
        "\u5f90\u5730\u8425\u5b50"
    ],
    "wof:name":"Xudi Yingzi",
    "wof:placetype":"locality"
},
  "geometry": {"coordinates":[122.78933000000001,47.97098],"type":"Point"}
}