{
  "type": "Feature",
  "properties": {
    "gn:admin1_code":"32.0",
    "gn:asciiname":"Guangdongwan",
    "gn:country_code":"CN",
    "gn:dem":387,
    "gn:feature_class":"P",
    "gn:feature_code":"PPL",
    "gn:name":"Guangdongwan",
    "gn:population":0,
    "gn:timezone":"Asia/Shanghai",
    "iso:country":"CN",
    "name:zho_x_preferred":[
        "\u5e7f\u4e1c\u6e7e"
    ],
    "wof:name":"Guangdongwan",
    "wof:placetype":"locality"
},
  "geometry": {"coordinates":[104.761,30.2889],"type":"Point"}
}