{
  "type": "Feature",
  "properties": {
    "gn:admin1_code":"11.0",
    "gn:asciiname":"Wunipu",
    "gn:country_code":"CN",
    "gn:dem":121,
    "gn:feature_class":"P",
    "gn:feature_code":"PPL",
    "gn:name":"Wunipu",
    "gn:population":0,
    "gn:timezone":"Asia/Shanghai",
    "iso:country":"CN",
    "name:zho_x_preferred":[
        "\u4e4c\u6ce5\u94fa"
    ],
    "wof:name":"Wunipu",
    "wof:placetype":"locality"
},
  "geometry": {"coordinates":[113.07389000000001,26.052],"type":"Point"}
}