{
  "type": "Feature",
  "properties": {
    "gn:admin1_code":"32.0",
    "gn:asciiname":"Baojiachong",
    "gn:country_code":"CN",
    "gn:dem":455,
    "gn:feature_class":"P",
    "gn:feature_code":"PPL",
    "gn:name":"Baojiachong",
    "gn:population":0,
    "gn:timezone":"Asia/Shanghai",
    "iso:country":"CN",
    "name:zho_x_preferred":[
        "\u5305\u5bb6\u51b2"
    ],
    "wof:name":"Baojiachong",
    "wof:placetype":"locality"
},
  "geometry": {"coordinates":[104.828,29.6578],"type":"Point"}
}