{
  "type": "Feature",
  "properties": {
    "gn:admin1_code":"4.0",
    "gn:asciiname":"Sunjiashe",
    "gn:country_code":"CN",
    "gn:dem":0,
    "gn:feature_class":"P",
    "gn:feature_code":"PPL",
    "gn:name":"Sunjiashe",
    "gn:population":0,
    "gn:timezone":"Asia/Shanghai",
    "iso:country":"CN",
    "name:zho_x_preferred":[
        "Sunjiashe"
    ],
    "name:zho_x_variant":[
        "\u5b59\u5bb6\u820d"
    ],
    "wof:name":"Sunjiashe",
    "wof:placetype":"locality"
},
  "geometry": {"coordinates":[119.99772,33.26669],"type":"Point"}
}