{
  "type": "Feature",
  "properties": {
    "gn:admin1_code":"21.0",
    "gn:asciiname":"Hongquan",
    "gn:country_code":"CN",
    "gn:dem":1659,
    "gn:feature_class":"P",
    "gn:feature_code":"PPL",
    "gn:name":"Hongquan",
    "gn:population":0,
    "gn:timezone":"Asia/Shanghai",
    "iso:country":"CN",
    "name:zho_x_preferred":[
        "\u7ea2\u5708"
    ],
    "wof:name":"Hongquan",
    "wof:placetype":"locality"
},
  "geometry": {"coordinates":[105.831,36.7312],"type":"Point"}
}