{
  "type": "Feature",
  "properties": {
    "gn:admin1_code":"24.0",
    "gn:asciiname":"Nanyinggoucun",
    "gn:country_code":"CN",
    "gn:dem":1107,
    "gn:feature_class":"P",
    "gn:feature_code":"PPL",
    "gn:name":"Nanyinggoucun",
    "gn:population":0,
    "gn:timezone":"Asia/Shanghai",
    "iso:country":"CN",
    "name:zho_x_preferred":[
        "\u5357\u8425\u6c9f\u6751"
    ],
    "wof:name":"Nanyinggoucun",
    "wof:placetype":"locality"
},
  "geometry": {"coordinates":[114.15505,40.46328],"type":"Point"}
}