{
  "type": "Feature",
  "properties": {
    "gn:admin1_code":"4.0",
    "gn:asciiname":"Xuebeicun",
    "gn:country_code":"CN",
    "gn:dem":5,
    "gn:feature_class":"P",
    "gn:feature_code":"PPL",
    "gn:name":"Xuebeicun",
    "gn:population":0,
    "gn:timezone":"Asia/Shanghai",
    "iso:country":"CN",
    "name:zho_x_preferred":[
        "\u859b\u5317\u6751"
    ],
    "wof:name":"Xuebeicun",
    "wof:placetype":"locality"
},
  "geometry": {"coordinates":[119.55468999999999,32.9707],"type":"Point"}
}