{
  "type": "Feature",
  "properties": {
    "gn:admin1_code":"9.0",
    "gn:asciiname":"Gongjiazhuang",
    "gn:country_code":"CN",
    "gn:dem":177,
    "gn:feature_class":"P",
    "gn:feature_code":"PPL",
    "gn:name":"Gongjiazhuang",
    "gn:population":0,
    "gn:timezone":"Asia/Shanghai",
    "iso:country":"CN",
    "name:zho_x_preferred":[
        "\u5f13\u5bb6\u5e84"
    ],
    "wof:name":"Gongjiazhuang",
    "wof:placetype":"locality"
},
  "geometry": {"coordinates":[114.06869,35.84151],"type":"Point"}
}