{
  "type": "Feature",
  "properties": {
    "gn:admin1_code":"11",
    "gn:asciiname":"Xiongjia",
    "gn:country_code":"CN",
    "gn:dem":179,
    "gn:feature_class":"P",
    "gn:feature_code":"PPL",
    "gn:name":"Xiongjia",
    "gn:population":0,
    "gn:timezone":"Asia/Shanghai",
    "iso:country":"CN",
    "name:und_x_variant":[
        "\u718a\u5bb6",
        "Xiongjia"
    ],
    "wof:name":"Xiongjia",
    "wof:placetype":"locality"
},
  "geometry": {"coordinates":[111.71083,25.5625],"type":"Point"}
}