{
  "type": "Feature",
  "properties": {
    "gn:admin1_code":"12.0",
    "gn:asciiname":"Baijiawan",
    "gn:country_code":"CN",
    "gn:dem":1129,
    "gn:feature_class":"P",
    "gn:feature_code":"PPL",
    "gn:name":"Baijiawan",
    "gn:population":0,
    "gn:timezone":"Asia/Shanghai",
    "iso:country":"CN",
    "name:zho_x_preferred":[
        "\u767e\u5bb6\u6e7e"
    ],
    "wof:name":"Baijiawan",
    "wof:placetype":"locality"
},
  "geometry": {"coordinates":[110.23957,30.40749000000001],"type":"Point"}
}