{
  "type": "Feature",
  "properties": {
    "gn:admin1_code":"10.0",
    "gn:asciiname":"Jingtuo",
    "gn:country_code":"CN",
    "gn:dem":13,
    "gn:feature_class":"P",
    "gn:feature_code":"PPL",
    "gn:name":"Jingtuo",
    "gn:population":0,
    "gn:timezone":"Asia/Shanghai",
    "iso:country":"CN",
    "name:zho_x_preferred":[
        "\u4e95\u5768"
    ],
    "wof:name":"Jingtuo",
    "wof:placetype":"locality"
},
  "geometry": {"coordinates":[118.89588000000001,39.45657],"type":"Point"}
}