{
  "type": "Feature",
  "properties": {
    "gn:admin1_code":"11.0",
    "gn:asciiname":"Tangguanpu",
    "gn:country_code":"CN",
    "gn:dem":905,
    "gn:feature_class":"P",
    "gn:feature_code":"PPL",
    "gn:name":"Tangguanpu",
    "gn:population":0,
    "gn:timezone":"Asia/Shanghai",
    "iso:country":"CN",
    "name:zho_x_preferred":[
        "\u5858\u5b98\u94fa"
    ],
    "wof:name":"Tangguanpu",
    "wof:placetype":"locality"
},
  "geometry": {"coordinates":[112.50454000000001,25.45015],"type":"Point"}
}