{
  "type": "Feature",
  "properties": {
    "gn:admin1_code":"9.0",
    "gn:asciiname":"Xiamiaodi",
    "gn:country_code":"CN",
    "gn:dem":462,
    "gn:feature_class":"P",
    "gn:feature_code":"PPL",
    "gn:name":"Xiamiaodi",
    "gn:population":0,
    "gn:timezone":"Asia/Shanghai",
    "iso:country":"CN",
    "name:zho_x_preferred":[
        "\u4e0b\u5e99\u5730"
    ],
    "wof:name":"Xiamiaodi",
    "wof:placetype":"locality"
},
  "geometry": {"coordinates":[110.69846,34.54843],"type":"Point"}
}