{
  "type": "Feature",
  "properties": {
    "gn:admin1_code":"14.0",
    "gn:asciiname":"Xiaomojiu",
    "gn:country_code":"CN",
    "gn:dem":3758,
    "gn:feature_class":"P",
    "gn:feature_code":"PPL",
    "gn:name":"Xiaomojiu",
    "gn:population":0,
    "gn:timezone":"Asia/Urumqi",
    "iso:country":"CN",
    "name:zho_x_preferred":[
        "\u5c0f\u78e8\u4e5d"
    ],
    "wof:name":"Xiaomojiu",
    "wof:placetype":"locality"
},
  "geometry": {"coordinates":[98.68801000000001,31.11668],"type":"Point"}
}