{
  "type": "Feature",
  "properties": {
    "gn:admin1_code":"9.0",
    "gn:asciiname":"Jiulonggang",
    "gn:country_code":"CN",
    "gn:dem":47,
    "gn:feature_class":"P",
    "gn:feature_code":"PPL",
    "gn:name":"Jiulonggang",
    "gn:population":0,
    "gn:timezone":"Asia/Shanghai",
    "iso:country":"CN",
    "name:zho_x_preferred":[
        "\u4e5d\u9f99\u5c97"
    ],
    "wof:name":"Jiulonggang",
    "wof:placetype":"locality"
},
  "geometry": {"coordinates":[115.86721,32.11617],"type":"Point"}
}