{
  "type": "Feature",
  "properties": {
    "gn:admin1_code":"30",
    "gn:asciiname":"Lantian",
    "gn:country_code":"CN",
    "gn:dem":170,
    "gn:feature_class":"P",
    "gn:feature_code":"PPLA4",
    "gn:name":"Lantian",
    "gn:population":0,
    "gn:timezone":"Asia/Shanghai",
    "iso:country":"CN",
    "name:und_x_variant":[
        "Lan-t\u2019ien",
        "Futian Yaozuxiang",
        "Lantian Yaozuxiang",
        "Lantian",
        "Lantianyaozuxiang",
        "\u84dd\u7530\u7476\u65cf\u4e61"
    ],
    "name:zho_x_preferred":[
        "\u84dd\u7530"
    ],
    "wof:name":"Lantian",
    "wof:placetype":"locality"
},
  "geometry": {"coordinates":[114.22678000000001,23.86287],"type":"Point"}
}