{
  "type": "Feature",
  "properties": {
    "gn:admin1_code":"20",
    "gn:asciiname":"Shangjibaogou",
    "gn:cc2":"CN",
    "gn:country_code":"CN",
    "gn:dem":559,
    "gn:feature_class":"P",
    "gn:feature_code":"PPL",
    "gn:name":"Shangjibaogou",
    "gn:population":0,
    "gn:timezone":"Asia/Shanghai",
    "iso:country":"CN",
    "name:und_x_variant":[
        "Chi-pao-kou",
        "Shangjibaogou"
    ],
    "wof:name":"Shangjibaogou",
    "wof:placetype":"locality"
},
  "geometry": {"coordinates":[120.00833,51.22389],"type":"Point"}
}