{
  "type": "Feature",
  "properties": {
    "gn:admin1_code":"2.0",
    "gn:asciiname":"Dongshandi",
    "gn:country_code":"CN",
    "gn:dem":241,
    "gn:feature_class":"P",
    "gn:feature_code":"PPLA4",
    "gn:name":"Dongshandi",
    "gn:population":0,
    "gn:timezone":"Asia/Shanghai",
    "iso:country":"CN",
    "name:und_x_variant":[
        "Furong",
        "Dongshandi"
    ],
    "name:zho_x_preferred":[
        "\u4e1c\u5c71\u5e95"
    ],
    "name:zho_x_variant":[
        "\u8299\u84c9"
    ],
    "wof:name":"Dongshandi",
    "wof:placetype":"locality"
},
  "geometry": {"coordinates":[118.64857000000001,29.12471],"type":"Point"}
}