{
  "type": "Feature",
  "properties": {
    "gn:admin1_code":"30",
    "gn:asciiname":"Douxi",
    "gn:country_code":"CN",
    "gn:dem":287,
    "gn:feature_class":"P",
    "gn:feature_code":"PPL",
    "gn:name":"Douxi",
    "gn:population":0,
    "gn:timezone":"Asia/Shanghai",
    "iso:country":"CN",
    "name:zho_x_preferred":[
        "\u6597\u6eaa"
    ],
    "wof:name":"Douxi",
    "wof:placetype":"locality"
},
  "geometry": {"coordinates":[116.06628000000001,23.99104],"type":"Point"}
}