{
  "type": "Feature",
  "properties": {
    "gn:admin1_code":"30.0",
    "gn:asciiname":"Songling",
    "gn:country_code":"CN",
    "gn:dem":109,
    "gn:feature_class":"P",
    "gn:feature_code":"PPL",
    "gn:name":"Songling",
    "gn:population":0,
    "gn:timezone":"Asia/Shanghai",
    "iso:country":"CN",
    "name:zho_x_preferred":[
        "\u677e\u5cad"
    ],
    "wof:name":"Songling",
    "wof:placetype":"locality"
},
  "geometry": {"coordinates":[113.9456,23.2938],"type":"Point"}
}