{
  "type": "Feature",
  "properties": {
    "gn:admin1_code":"13.0",
    "gn:asciiname":"Langan Airike",
    "gn:country_code":"CN",
    "gn:dem":1313,
    "gn:feature_class":"P",
    "gn:feature_code":"PPL",
    "gn:name":"Langan Airike",
    "gn:population":0,
    "gn:timezone":"Asia/Shanghai",
    "iso:country":"CN",
    "name:und_x_variant":[
        "\u5170\u5e72\u827e\u65e5\u514b"
    ],
    "wof:name":"Langan Airike",
    "wof:placetype":"locality"
},
  "geometry": {"coordinates":[76.48801,38.65871],"type":"Point"}
}