{
  "type": "Feature",
  "properties": {
    "gn:admin1_code":"32.0",
    "gn:asciiname":"Malianhuan",
    "gn:country_code":"CN",
    "gn:dem":3411,
    "gn:feature_class":"P",
    "gn:feature_code":"PPL",
    "gn:name":"Malianhuan",
    "gn:population":0,
    "gn:timezone":"Asia/Shanghai",
    "iso:country":"CN",
    "name:zho_x_preferred":[
        "\u9ebb\u8138\u7f13"
    ],
    "wof:name":"Malianhuan",
    "wof:placetype":"locality"
},
  "geometry": {"coordinates":[100.557,28.014],"type":"Point"}
}