{
  "type": "Feature",
  "properties": {
    "gn:admin1_code":"5.0",
    "gn:asciiname":"Lianhecun",
    "gn:country_code":"CN",
    "gn:dem":286,
    "gn:feature_class":"P",
    "gn:feature_code":"PPL",
    "gn:name":"Lianhecun",
    "gn:population":0,
    "gn:timezone":"Asia/Shanghai",
    "iso:country":"CN",
    "name:und_x_variant":[
        "Lianhe",
        "\u8054\u5408",
        "Lianhecun"
    ],
    "name:zho_x_preferred":[
        "\u8054\u5408\u6751"
    ],
    "wof:name":"Lianhecun",
    "wof:placetype":"locality"
},
  "geometry": {"coordinates":[126.93277999999999,43.00448],"type":"Point"}
}