{
  "type": "Feature",
  "properties": {
    "gn:admin1_code":"7.0",
    "gn:asciiname":"Fuyuancun",
    "gn:country_code":"CN",
    "gn:dem":172,
    "gn:feature_class":"P",
    "gn:feature_code":"PPL",
    "gn:name":"Fuyuancun",
    "gn:population":0,
    "gn:timezone":"Asia/Shanghai",
    "iso:country":"CN",
    "name:und_x_variant":[
        "\u5bcc\u6e90\u6751"
    ],
    "name:zho_x_preferred":[
        "\u5bcc\u6e90\u6751"
    ],
    "wof:name":"Fuyuancun",
    "wof:placetype":"locality"
},
  "geometry": {"coordinates":[117.41199,26.17835],"type":"Point"}
}