{
  "type": "Feature",
  "properties": {
    "gn:admin1_code":"15.0",
    "gn:asciiname":"Shulehe",
    "gn:cc2":"CN",
    "gn:country_code":"CN",
    "gn:dem":1425,
    "gn:feature_class":"P",
    "gn:feature_code":"PPL",
    "gn:name":"Shulehe",
    "gn:population":0,
    "gn:timezone":"Asia/Urumqi",
    "iso:country":"CN",
    "name:und_x_variant":[
        "Shu-le-ho",
        "Shulehe"
    ],
    "wof:name":"Shulehe",
    "wof:placetype":"locality"
},
  "geometry": {"coordinates":[96.78333000000001,40.45],"type":"Point"}
}