{
  "type": "Feature",
  "properties": {
    "gn:admin1_code":"2.0",
    "gn:asciiname":"Yuankeng",
    "gn:country_code":"CN",
    "gn:dem":797,
    "gn:feature_class":"P",
    "gn:feature_code":"PPL",
    "gn:name":"Yuankeng",
    "gn:population":0,
    "gn:timezone":"Asia/Shanghai",
    "iso:country":"CN",
    "name:zho_x_preferred":[
        "\u6c85\u5751"
    ],
    "wof:name":"Yuankeng",
    "wof:placetype":"locality"
},
  "geometry": {"coordinates":[119.336,28.36656],"type":"Point"}
}