{
  "type": "Feature",
  "properties": {
    "gn:admin1_code":"12.0",
    "gn:asciiname":"Xiongjia Dawan",
    "gn:country_code":"CN",
    "gn:dem":23,
    "gn:feature_class":"P",
    "gn:feature_code":"PPL",
    "gn:name":"Xiongjia Dawan",
    "gn:population":0,
    "gn:timezone":"Asia/Shanghai",
    "iso:country":"CN",
    "name:und_x_variant":[
        "\u718a\u5bb6\u5927\u5846"
    ],
    "wof:name":"Xiongjia Dawan",
    "wof:placetype":"locality"
},
  "geometry": {"coordinates":[114.42901999999999,30.80182000000001],"type":"Point"}
}