{
  "type": "Feature",
  "properties": {
    "gn:country":"CN",
    "gn:fcode":"PPL",
    "gn:population":523,
    "iso:country":"CN",
    "name:und_x_variant":[
        "Yangliu"
    ],
    "name:zho_x_preferred":[
        "\u6768\u67f3\u6c9f"
    ],
    "qs:name":"Yangliugou",
    "qs:photos_9r":0,
    "qs:photos_sr":0,
    "qs:pop_sr":"2",
    "wof:name":"Yangliugou",
    "wof:placetype":"locality",
    "wof:population":523
},
  "geometry": {"coordinates":[108.79528000000001,27.45722],"type":"Point"}
}