{
  "type": "Feature",
  "properties": {
    "gn:admin1_code":"3.0",
    "gn:asciiname":"Wumeizhou",
    "gn:country_code":"CN",
    "gn:dem":91,
    "gn:feature_class":"P",
    "gn:feature_code":"PPL",
    "gn:name":"Wumeizhou",
    "gn:population":0,
    "gn:timezone":"Asia/Shanghai",
    "iso:country":"CN",
    "name:und_x_variant":[
        "\u4e94\u6885\u6d32"
    ],
    "wof:name":"Wumeizhou",
    "wof:placetype":"locality"
},
  "geometry": {"coordinates":[114.8544,27.37664],"type":"Point"}
}