{
  "type": "Feature",
  "properties": {
    "gn:admin1_code":"2.0",
    "gn:asciiname":"Bailingxia",
    "gn:country_code":"CN",
    "gn:dem":2,
    "gn:feature_class":"P",
    "gn:feature_code":"PPL",
    "gn:name":"Bailingxia",
    "gn:population":0,
    "gn:timezone":"Asia/Shanghai",
    "iso:country":"CN",
    "name:zho_x_preferred":[
        "\u767d\u5cad\u4e0b"
    ],
    "wof:name":"Bailingxia",
    "wof:placetype":"locality"
},
  "geometry": {"coordinates":[121.7928,29.92487],"type":"Point"}
}