{
  "type": "Feature",
  "properties": {
    "gn:admin1_code":"7.0",
    "gn:asciiname":"Nanbian",
    "gn:country_code":"CN",
    "gn:dem":7,
    "gn:feature_class":"P",
    "gn:feature_code":"PPL",
    "gn:name":"Nanbian",
    "gn:population":0,
    "gn:timezone":"Asia/Shanghai",
    "iso:country":"CN",
    "name:zho_x_preferred":[
        "\u5357\u8fb9"
    ],
    "wof:name":"Nanbian",
    "wof:placetype":"locality"
},
  "geometry": {"coordinates":[117.87385999999999,24.36804],"type":"Point"}
}