{
  "type": "Feature",
  "properties": {
    "gn:admin1_code":"3.0",
    "gn:asciiname":"Longhui",
    "gn:country_code":"CN",
    "gn:dem":659,
    "gn:feature_class":"P",
    "gn:feature_code":"PPL",
    "gn:name":"Longhui",
    "gn:population":0,
    "gn:timezone":"Asia/Shanghai",
    "iso:country":"CN",
    "name:und_x_variant":[
        "\u9f99\u56de"
    ],
    "wof:name":"Longhui",
    "wof:placetype":"locality"
},
  "geometry": {"coordinates":[114.30885000000001,27.51641],"type":"Point"}
}