{
  "type": "Feature",
  "properties": {
    "gn:admin1_code":"9.0",
    "gn:asciiname":"Yanzhuang",
    "gn:country_code":"CN",
    "gn:dem":127,
    "gn:feature_class":"P",
    "gn:feature_code":"PPL",
    "gn:name":"Yanzhuang",
    "gn:population":0,
    "gn:timezone":"Asia/Shanghai",
    "iso:country":"CN",
    "name:ceb_x_preferred":[
        "Yanzhuang"
    ],
    "name:swe_x_preferred":[
        "Yanzhuang"
    ],
    "name:und_x_variant":[
        "\u960e\u5e84",
        "Yanzhuang"
    ],
    "wof:name":"Yanzhuang",
    "wof:placetype":"locality"
},
  "geometry": {"coordinates":[112.79810999999999,33.03965],"type":"Point"}
}