{
  "type": "Feature",
  "properties": {
    "gn:admin1_code":"29.0",
    "gn:asciiname":"Datian",
    "gn:country_code":"CN",
    "gn:dem":1919,
    "gn:feature_class":"P",
    "gn:feature_code":"PPL",
    "gn:name":"Datian",
    "gn:population":0,
    "gn:timezone":"Asia/Shanghai",
    "iso:country":"CN",
    "name:zho_x_preferred":[
        "\u5927\u7530"
    ],
    "wof:name":"Datian",
    "wof:placetype":"locality"
},
  "geometry": {"coordinates":[98.9665,24.8941],"type":"Point"}
}