{
  "type": "Feature",
  "properties": {
    "gn:admin1_code":"32.0",
    "gn:asciiname":"Tiantaisi",
    "gn:country_code":"CN",
    "gn:dem":382,
    "gn:feature_class":"P",
    "gn:feature_code":"PPL",
    "gn:name":"Tiantaisi",
    "gn:population":0,
    "gn:timezone":"Asia/Shanghai",
    "iso:country":"CN",
    "name:zho_x_preferred":[
        "\u5929\u53f0\u5bfa"
    ],
    "wof:name":"Tiantaisi",
    "wof:placetype":"locality"
},
  "geometry": {"coordinates":[105.2954,30.02582],"type":"Point"}
}