{
  "type": "Feature",
  "properties": {
    "gn:admin1_code":"10",
    "gn:asciiname":"Donglituan",
    "gn:country_code":"CN",
    "gn:dem":40,
    "gn:feature_class":"P",
    "gn:feature_code":"PPL",
    "gn:name":"Donglituan",
    "gn:population":0,
    "gn:timezone":"Asia/Shanghai",
    "iso:country":"CN",
    "name:zho_x_preferred":[
        "\u4e1c\u91cc\u7583"
    ],
    "wof:name":"Donglituan",
    "wof:placetype":"locality"
},
  "geometry": {"coordinates":[115.00491,36.92907],"type":"Point"}
}