{
  "type": "Feature",
  "properties": {
    "gn:country":"CN",
    "gn:fcode":"ADM3",
    "gn:pop":0,
    "iso:country":"CN",
    "name:uig_x_preferred":[
        "Toksun Xian"
    ],
    "name:uig_x_variant":[
        "Toksun"
    ],
    "name:unk_x_variant":[
        "T\u2019o-k\u2019o-hs\u00fcn Hsien"
    ],
    "qs:name":"Toksun Xian",
    "qs:photos_9r":0,
    "qs:photos_sr":0,
    "qs:pop_sr":"0",
    "wof:name":"Toksun Xian",
    "wof:placetype":"localadmin",
    "wof:population":0
},
  "geometry": {"coordinates":[88.63333,42.78333],"type":"Point"}
}