{
  "type": "Feature",
  "properties": {
    "gn:admin1_code":"29.0",
    "gn:asciiname":"Chenjuka",
    "gn:country_code":"CN",
    "gn:dem":2314,
    "gn:feature_class":"P",
    "gn:feature_code":"PPL",
    "gn:name":"Chenjuka",
    "gn:population":0,
    "gn:timezone":"Asia/Shanghai",
    "iso:country":"CN",
    "name:zho_x_preferred":[
        "\u9648\u5c45\u5361"
    ],
    "wof:name":"Chenjuka",
    "wof:placetype":"locality"
},
  "geometry": {"coordinates":[103.297,26.5929],"type":"Point"}
}