{
  "type": "Feature",
  "properties": {
    "gn:admin1_code":"19.0",
    "gn:asciiname":"Cimeihuagou",
    "gn:country_code":"CN",
    "gn:dem":266,
    "gn:feature_class":"P",
    "gn:feature_code":"PPL",
    "gn:name":"Cimeihuagou",
    "gn:population":0,
    "gn:timezone":"Asia/Shanghai",
    "iso:country":"CN",
    "name:zho_x_preferred":[
        "\u523a\u6885\u82b1\u6c9f"
    ],
    "wof:name":"Cimeihuagou",
    "wof:placetype":"locality"
},
  "geometry": {"coordinates":[120.34399999999999,40.8805],"type":"Point"}
}