{
  "type": "Feature",
  "properties": {
    "gn:admin1_code":"4.0",
    "gn:asciiname":"Hexing",
    "gn:country_code":"CN",
    "gn:dem":7,
    "gn:feature_class":"P",
    "gn:feature_code":"PPL",
    "gn:name":"Hexing",
    "gn:population":0,
    "gn:timezone":"Asia/Shanghai",
    "iso:country":"CN",
    "name:zho_x_preferred":[
        "\u5408\u5174"
    ],
    "wof:name":"Hexing",
    "wof:placetype":"locality"
},
  "geometry": {"coordinates":[120.77975000000001,32.28682],"type":"Point"}
}