{
  "type": "Feature",
  "properties": {
    "gn:admin1_code":"9.0",
    "gn:asciiname":"Daohuan",
    "gn:country_code":"CN",
    "gn:dem":367,
    "gn:feature_class":"P",
    "gn:feature_code":"PPL",
    "gn:name":"Daohuan",
    "gn:population":0,
    "gn:timezone":"Asia/Shanghai",
    "iso:country":"CN",
    "name:zho_x_preferred":[
        "\u5200\u73af"
    ],
    "wof:name":"Daohuan",
    "wof:placetype":"locality"
},
  "geometry": {"coordinates":[111.70543000000001,34.54297],"type":"Point"}
}