{
  "type": "Feature",
  "properties": {
    "gn:admin1_code":"29.0",
    "gn:asciiname":"Tinghu",
    "gn:country_code":"CN",
    "gn:dem":1512,
    "gn:feature_class":"P",
    "gn:feature_code":"PPL",
    "gn:name":"Tinghu",
    "gn:population":0,
    "gn:timezone":"Asia/Shanghai",
    "iso:country":"CN",
    "name:zho_x_preferred":[
        "\u542c\u6e56"
    ],
    "wof:name":"Tinghu",
    "wof:placetype":"locality"
},
  "geometry": {"coordinates":[104.396,23.664],"type":"Point"}
}