{
  "type": "Feature",
  "properties": {
    "gn:admin1_code":"1.0",
    "gn:asciiname":"Huaqiaocun",
    "gn:country_code":"CN",
    "gn:dem":29,
    "gn:feature_class":"P",
    "gn:feature_code":"PPL",
    "gn:name":"Huaqiaocun",
    "gn:population":0,
    "gn:timezone":"Asia/Shanghai",
    "iso:country":"CN",
    "name:zho_x_preferred":[
        "\u5316\u6865\u6751"
    ],
    "wof:name":"Huaqiaocun",
    "wof:placetype":"locality"
},
  "geometry": {"coordinates":[116.10420000000001,32.69708],"type":"Point"}
}