{
  "type": "Feature",
  "properties": {
    "gn:admin1_code":"15.0",
    "gn:asciiname":"Dujiazhuang",
    "gn:country_code":"CN",
    "gn:dem":1358,
    "gn:feature_class":"P",
    "gn:feature_code":"PPL",
    "gn:name":"Dujiazhuang",
    "gn:population":0,
    "gn:timezone":"Asia/Shanghai",
    "iso:country":"CN",
    "name:und_x_variant":[
        "\u675c\u5bb6\u5e84"
    ],
    "wof:name":"Dujiazhuang",
    "wof:placetype":"locality"
},
  "geometry": {"coordinates":[107.63348999999999,36.24486],"type":"Point"}
}