{
  "type": "Feature",
  "properties": {
    "gn:admin1_code":"11.0",
    "gn:asciiname":"Gushao",
    "gn:country_code":"CN",
    "gn:dem":587,
    "gn:feature_class":"P",
    "gn:feature_code":"PPL",
    "gn:name":"Gushao",
    "gn:population":0,
    "gn:timezone":"Asia/Shanghai",
    "iso:country":"CN",
    "name:zho_x_preferred":[
        "\u8c37\u54e8"
    ],
    "wof:name":"Gushao",
    "wof:placetype":"locality"
},
  "geometry": {"coordinates":[109.32080000000001,28.40481],"type":"Point"}
}