{
  "type": "Feature",
  "properties": {
    "gn:admin1_code":"19.0",
    "gn:asciiname":"Ximiaocun",
    "gn:country_code":"CN",
    "gn:dem":9,
    "gn:feature_class":"P",
    "gn:feature_code":"PPL",
    "gn:name":"Ximiaocun",
    "gn:population":0,
    "gn:timezone":"Asia/Shanghai",
    "iso:country":"CN",
    "name:zho_x_preferred":[
        "\u897f\u5e99\u6751"
    ],
    "wof:name":"Ximiaocun",
    "wof:placetype":"locality"
},
  "geometry": {"coordinates":[122.55200000000001,40.7817],"type":"Point"}
}