{
  "type": "Feature",
  "properties": {
    "gn:admin1_code":"10",
    "gn:asciiname":"Zhengjialiang",
    "gn:country_code":"CN",
    "gn:dem":960,
    "gn:feature_class":"P",
    "gn:feature_code":"PPL",
    "gn:name":"Zhengjialiang",
    "gn:population":0,
    "gn:timezone":"Asia/Shanghai",
    "iso:country":"CN",
    "name:zho_x_preferred":[
        "\u90d1\u5bb6\u6881"
    ],
    "wof:name":"Zhengjialiang",
    "wof:placetype":"locality"
},
  "geometry": {"coordinates":[115.72512999999999,40.69091],"type":"Point"}
}