{
  "type": "Feature",
  "properties": {
    "gn:admin1_code":"2.0",
    "gn:asciiname":"Sunjiabu",
    "gn:country_code":"CN",
    "gn:dem":79,
    "gn:feature_class":"P",
    "gn:feature_code":"PPL",
    "gn:name":"Sunjiabu",
    "gn:population":0,
    "gn:timezone":"Asia/Shanghai",
    "iso:country":"CN",
    "name:zho_x_preferred":[
        "\u5b59\u5bb6\u57e0"
    ],
    "wof:name":"Sunjiabu",
    "wof:placetype":"locality"
},
  "geometry": {"coordinates":[120.09653,29.22188],"type":"Point"}
}