{
  "type": "Feature",
  "properties": {
    "gn:admin1_code":"18",
    "gn:asciiname":"Huaihuachi",
    "gn:country_code":"CN",
    "gn:dem":1321,
    "gn:feature_class":"P",
    "gn:feature_code":"PPL",
    "gn:name":"Huaihuachi",
    "gn:population":0,
    "gn:timezone":"Asia/Shanghai",
    "iso:country":"CN",
    "name:zho_x_preferred":[
        "\u69d0\u82b1\u6c60"
    ],
    "wof:name":"Huaihuachi",
    "wof:placetype":"locality"
},
  "geometry": {"coordinates":[107.58,28.5395],"type":"Point"}
}