{
  "type": "Feature",
  "properties": {
    "gn:admin1_code":"25",
    "gn:asciiname":"Fuzishan",
    "gn:country_code":"CN",
    "gn:dem":222,
    "gn:feature_class":"P",
    "gn:feature_code":"PPL",
    "gn:name":"Fuzishan",
    "gn:population":0,
    "gn:timezone":"Asia/Shanghai",
    "iso:country":"CN",
    "name:zho_x_preferred":[
        "\u592b\u5b50\u5c71"
    ],
    "wof:name":"Fuzishan",
    "wof:placetype":"locality"
},
  "geometry": {"coordinates":[117.523,35.3773],"type":"Point"}
}