{
  "type": "Feature",
  "properties": {
    "gn:admin1_code":"04",
    "gn:asciiname":"Miaoquan",
    "gn:cc2":"CN",
    "gn:country_code":"CN",
    "gn:dem":5,
    "gn:feature_class":"P",
    "gn:feature_code":"PPL",
    "gn:name":"Miaoquan",
    "gn:population":0,
    "gn:timezone":"Asia/Shanghai",
    "iso:country":"CN",
    "name:und_x_variant":[
        "Miao-ch\u2019ien-chen",
        "Miaoquan"
    ],
    "wof:name":"Miaoquan",
    "wof:placetype":"locality"
},
  "geometry": {"coordinates":[120.81583000000001,31.66667],"type":"Point"}
}