{
  "type": "Feature",
  "properties": {
    "gn:admin1_code":"29.0",
    "gn:asciiname":"Shangzhuangfang",
    "gn:country_code":"CN",
    "gn:dem":1705,
    "gn:feature_class":"P",
    "gn:feature_code":"PPL",
    "gn:name":"Shangzhuangfang",
    "gn:population":0,
    "gn:timezone":"Asia/Shanghai",
    "iso:country":"CN",
    "name:zho_x_preferred":[
        "\u4e0a\u5e84\u623f"
    ],
    "wof:name":"Shangzhuangfang",
    "wof:placetype":"locality"
},
  "geometry": {"coordinates":[99.6439,25.2528],"type":"Point"}
}