{
  "type": "Feature",
  "properties": {
    "gn:admin1_code":"18.0",
    "gn:asciiname":"Daping",
    "gn:country_code":"CN",
    "gn:dem":431,
    "gn:feature_class":"P",
    "gn:feature_code":"PPL",
    "gn:name":"Daping",
    "gn:population":0,
    "gn:timezone":"Asia/Shanghai",
    "iso:country":"CN",
    "name:zho_x_preferred":[
        "\u5927\u576a"
    ],
    "wof:name":"Daping",
    "wof:placetype":"locality"
},
  "geometry": {"coordinates":[109.50700000000001,26.9697],"type":"Point"}
}