{
  "type": "Feature",
  "properties": {
    "gn:admin1_code":"29.0",
    "gn:asciiname":"Suozuodi",
    "gn:country_code":"CN",
    "gn:dem":2039,
    "gn:feature_class":"P",
    "gn:feature_code":"PPL",
    "gn:name":"Suozuodi",
    "gn:population":0,
    "gn:timezone":"Asia/Shanghai",
    "iso:country":"CN",
    "name:zho_x_preferred":[
        "\u6240\u4f5c\u5e95"
    ],
    "wof:name":"Suozuodi",
    "wof:placetype":"locality"
},
  "geometry": {"coordinates":[103.961,23.3861],"type":"Point"}
}