{
  "type": "Feature",
  "properties": {
    "gn:admin1_code":"29.0",
    "gn:asciiname":"Wangguotong",
    "gn:country_code":"CN",
    "gn:dem":3875,
    "gn:feature_class":"P",
    "gn:feature_code":"PPL",
    "gn:name":"Wangguotong",
    "gn:population":0,
    "gn:timezone":"Asia/Shanghai",
    "iso:country":"CN",
    "name:zho_x_preferred":[
        "\u738b\u679c\u901a"
    ],
    "wof:name":"Wangguotong",
    "wof:placetype":"locality"
},
  "geometry": {"coordinates":[99.8228,28.561],"type":"Point"}
}