{
  "type": "Feature",
  "properties": {
    "gn:admin1_code":"32.0",
    "gn:asciiname":"Hou'ershi",
    "gn:country_code":"CN",
    "gn:dem":279,
    "gn:feature_class":"P",
    "gn:feature_code":"PPL",
    "gn:name":"Hou\u2019ershi",
    "gn:population":0,
    "gn:timezone":"Asia/Shanghai",
    "iso:country":"CN",
    "name:zho_x_preferred":[
        "\u7334\u513f\u77f3"
    ],
    "name:zho_x_variant":[
        "Hou\u2019ershi"
    ],
    "wof:name":"Hou'ershi",
    "wof:placetype":"locality"
},
  "geometry": {"coordinates":[105.56863,30.14861],"type":"Point"}
}