{
  "type": "Feature",
  "properties": {
    "gn:admin1_code":"15.0",
    "gn:asciiname":"Xiabaiya",
    "gn:country_code":"CN",
    "gn:dem":2226,
    "gn:feature_class":"P",
    "gn:feature_code":"PPL",
    "gn:name":"Xiabaiya",
    "gn:population":0,
    "gn:timezone":"Asia/Shanghai",
    "iso:country":"CN",
    "name:zho_x_preferred":[
        "\u4e0b\u767d\u5d16"
    ],
    "wof:name":"Xiabaiya",
    "wof:placetype":"locality"
},
  "geometry": {"coordinates":[103.78,35.8296],"type":"Point"}
}