{
  "type": "Feature",
  "properties": {
    "gn:admin1_code":"29.0",
    "gn:asciiname":"Xiaotianchong",
    "gn:country_code":"CN",
    "gn:dem":2048,
    "gn:feature_class":"P",
    "gn:feature_code":"PPL",
    "gn:name":"Xiaotianchong",
    "gn:population":0,
    "gn:timezone":"Asia/Shanghai",
    "iso:country":"CN",
    "name:zho_x_preferred":[
        "\u5c0f\u7530\u51b2"
    ],
    "wof:name":"Xiaotianchong",
    "wof:placetype":"locality"
},
  "geometry": {"coordinates":[103.59,25.4608],"type":"Point"}
}