{
  "type": "Feature",
  "properties": {
    "gn:admin1_code":"18",
    "gn:asciiname":"Shanglongkong",
    "gn:country_code":"CN",
    "gn:dem":970,
    "gn:feature_class":"P",
    "gn:feature_code":"PPL",
    "gn:name":"Shanglongkong",
    "gn:population":0,
    "gn:timezone":"Asia/Shanghai",
    "iso:country":"CN",
    "name:zho_x_preferred":[
        "\u4e0a\u9f99\u5b54"
    ],
    "wof:name":"Shanglongkong",
    "wof:placetype":"locality"
},
  "geometry": {"coordinates":[107.51300000000001,28.1228],"type":"Point"}
}