{
  "type": "Feature",
  "properties": {
    "gn:admin1_code":"3.0",
    "gn:asciiname":"Lailong",
    "gn:country_code":"CN",
    "gn:dem":276,
    "gn:feature_class":"P",
    "gn:feature_code":"PPL",
    "gn:name":"Lailong",
    "gn:population":0,
    "gn:timezone":"Asia/Shanghai",
    "iso:country":"CN",
    "name:und_x_variant":[
        "\u6765\u9f99"
    ],
    "wof:name":"Lailong",
    "wof:placetype":"locality"
},
  "geometry": {"coordinates":[114.50767999999999,24.70544],"type":"Point"}
}