{
  "type": "Feature",
  "properties": {
    "gn:admin1_code":"7",
    "gn:asciiname":"Yuankeng",
    "gn:country_code":"CN",
    "gn:dem":361,
    "gn:feature_class":"P",
    "gn:feature_code":"PPL",
    "gn:name":"Yuankeng",
    "gn:population":0,
    "gn:timezone":"Asia/Shanghai",
    "iso:country":"CN",
    "name:und_x_variant":[
        "\u5143\u5751"
    ],
    "wof:name":"Yuankeng",
    "wof:placetype":"locality"
},
  "geometry": {"coordinates":[116.47284999999999,25.54808],"type":"Point"}
}