{
  "type": "Feature",
  "properties": {
    "gn:admin1_code":"6.0",
    "gn:asciiname":"Tuole",
    "gn:cc2":"CN",
    "gn:country_code":"CN",
    "gn:dem":3358,
    "gn:feature_class":"P",
    "gn:feature_code":"PPL",
    "gn:name":"Tuole",
    "gn:population":0,
    "gn:timezone":"Asia/Shanghai",
    "iso:country":"CN",
    "name:und_x_variant":[
        "Tulai",
        "T\u2019o-lai",
        "T\u2019o-le",
        "Tuole"
    ],
    "wof:name":"Tuole",
    "wof:placetype":"locality"
},
  "geometry": {"coordinates":[98.40582999999999,38.81222],"type":"Point"}
}