{
  "type": "Feature",
  "properties": {
    "gn:admin1_code":"11",
    "gn:asciiname":"Xinzhaiping",
    "gn:country_code":"CN",
    "gn:dem":430,
    "gn:feature_class":"P",
    "gn:feature_code":"PPLA4",
    "gn:name":"Xinzhaiping",
    "gn:population":0,
    "gn:timezone":"Asia/Shanghai",
    "iso:country":"CN",
    "name:und_x_variant":[
        "Xinzhai Xiang",
        "Xinzhaiping"
    ],
    "name:zho_x_preferred":[
        "\u65b0\u5be8\u576a"
    ],
    "name:zho_x_variant":[
        "\u65b0\u5be8\u4e61"
    ],
    "wof:name":"Xinzhaiping",
    "wof:placetype":"locality"
},
  "geometry": {"coordinates":[109.8918,29.1343],"type":"Point"}
}