{
  "type": "Feature",
  "properties": {
    "gn:admin1_code":"5.0",
    "gn:asciiname":"Dagangzi",
    "gn:country_code":"CN",
    "gn:dem":210,
    "gn:feature_class":"P",
    "gn:feature_code":"PPL",
    "gn:name":"Dagangzi",
    "gn:population":0,
    "gn:timezone":"Asia/Shanghai",
    "iso:country":"CN",
    "name:zho_x_preferred":[
        "\u5927\u5c97\u5b50"
    ],
    "wof:name":"Dagangzi",
    "wof:placetype":"locality"
},
  "geometry": {"coordinates":[124.87057,43.76271],"type":"Point"}
}