{
  "type": "Feature",
  "properties": {
    "gn:admin1_code":"25.0",
    "gn:asciiname":"Diwentou",
    "gn:country_code":"CN",
    "gn:dem":48,
    "gn:feature_class":"P",
    "gn:feature_code":"PPL",
    "gn:name":"Diwentou",
    "gn:population":0,
    "gn:timezone":"Asia/Shanghai",
    "iso:country":"CN",
    "name:zho_x_preferred":[
        "\u5730\u6587\u5934"
    ],
    "wof:name":"Diwentou",
    "wof:placetype":"locality"
},
  "geometry": {"coordinates":[121.94669,37.33189],"type":"Point"}
}