{
  "type": "Feature",
  "properties": {
    "gn:admin1_code":"7.0",
    "gn:asciiname":"Yanxiacun",
    "gn:country_code":"CN",
    "gn:dem":270,
    "gn:feature_class":"P",
    "gn:feature_code":"PPL",
    "gn:name":"Yanxiacun",
    "gn:population":0,
    "gn:timezone":"Asia/Shanghai",
    "iso:country":"CN",
    "name:zho_x_preferred":[
        "\u5ca9\u4e0b\u6751"
    ],
    "wof:name":"Yanxiacun",
    "wof:placetype":"locality"
},
  "geometry": {"coordinates":[118.87618999999999,27.63381],"type":"Point"}
}