{
  "type": "Feature",
  "properties": {
    "gn:admin1_code":"29.0",
    "gn:asciiname":"Lamoshi",
    "gn:country_code":"CN",
    "gn:dem":2891,
    "gn:feature_class":"P",
    "gn:feature_code":"PPL",
    "gn:name":"Lamoshi",
    "gn:population":0,
    "gn:timezone":"Asia/Shanghai",
    "iso:country":"CN",
    "name:zho_x_preferred":[
        "\u814a\u83ab\u53f2"
    ],
    "wof:name":"Lamoshi",
    "wof:placetype":"locality"
},
  "geometry": {"coordinates":[100.587,26.959],"type":"Point"}
}