{
  "type": "Feature",
  "properties": {
    "gn:admin1_code":"33.0",
    "gn:asciiname":"Zhenxi",
    "gn:country_code":"CN",
    "gn:dem":1159,
    "gn:feature_class":"P",
    "gn:feature_code":"PPL",
    "gn:name":"Zhenxi",
    "gn:population":0,
    "gn:timezone":"Asia/Shanghai",
    "iso:country":"CN",
    "name:zho_x_preferred":[
        "\u9547\u6eaa"
    ],
    "wof:name":"Zhenxi",
    "wof:placetype":"locality"
},
  "geometry": {"coordinates":[109.16057000000001,31.52132000000001],"type":"Point"}
}