{
  "type": "Feature",
  "properties": {
    "gn:admin1_code":"19.0",
    "gn:asciiname":"Yaodudi",
    "gn:country_code":"CN",
    "gn:dem":515,
    "gn:feature_class":"P",
    "gn:feature_code":"PPL",
    "gn:name":"Yaodudi",
    "gn:population":0,
    "gn:timezone":"Asia/Shanghai",
    "iso:country":"CN",
    "name:zho_x_preferred":[
        "\u5c27\u90fd\u5730"
    ],
    "wof:name":"Yaodudi",
    "wof:placetype":"locality"
},
  "geometry": {"coordinates":[119.34035,41.87881],"type":"Point"}
}