{
  "type": "Feature",
  "properties": {
    "gn:admin1_code":"29.0",
    "gn:asciiname":"Manyaone",
    "gn:country_code":"CN",
    "gn:dem":1209,
    "gn:feature_class":"P",
    "gn:feature_code":"PPL",
    "gn:name":"Manyaone",
    "gn:population":0,
    "gn:timezone":"Asia/Shanghai",
    "iso:country":"CN",
    "name:und_x_variant":[
        "Manmene",
        "Manyaone"
    ],
    "name:zho_x_preferred":[
        "\u66fc\u4e48\u8bb7"
    ],
    "wof:name":"Manyaone",
    "wof:placetype":"locality"
},
  "geometry": {"coordinates":[100.205,21.9757],"type":"Point"}
}