{
  "type": "Feature",
  "properties": {
    "gn:admin1_code":"1.0",
    "gn:asciiname":"Xiangudian",
    "gn:country_code":"CN",
    "gn:dem":331,
    "gn:feature_class":"P",
    "gn:feature_code":"PPL",
    "gn:name":"Xiangudian",
    "gn:population":0,
    "gn:timezone":"Asia/Shanghai",
    "iso:country":"CN",
    "name:zho_x_preferred":[
        "\u4ed9\u59d1\u6bbf"
    ],
    "wof:name":"Xiangudian",
    "wof:placetype":"locality"
},
  "geometry": {"coordinates":[116.99469999999999,29.82613],"type":"Point"}
}