{
  "type": "Feature",
  "properties": {
    "gn:admin1_code":"3.0",
    "gn:asciiname":"Shexiacun",
    "gn:country_code":"CN",
    "gn:dem":264,
    "gn:feature_class":"P",
    "gn:feature_code":"PPL",
    "gn:name":"Shexiacun",
    "gn:population":0,
    "gn:timezone":"Asia/Shanghai",
    "iso:country":"CN",
    "name:zho_x_preferred":[
        "\u5962\u4e0b\u6751"
    ],
    "wof:name":"Shexiacun",
    "wof:placetype":"locality"
},
  "geometry": {"coordinates":[113.94199999999999,27.2654],"type":"Point"}
}