{
  "type": "Feature",
  "properties": {
    "gn:admin1_code":"16.0",
    "gn:asciiname":"Tuojiang",
    "gn:country_code":"CN",
    "gn:dem":86,
    "gn:feature_class":"P",
    "gn:feature_code":"PPL",
    "gn:name":"Tuojiang",
    "gn:population":0,
    "gn:timezone":"Asia/Shanghai",
    "iso:country":"CN",
    "name:zho_x_preferred":[
        "\u6cb1\u6c5f"
    ],
    "wof:name":"Tuojiang",
    "wof:placetype":"locality"
},
  "geometry": {"coordinates":[108.74299999999999,22.8855],"type":"Point"}
}