{
  "type": "Feature",
  "properties": {
    "gn:admin1_code":"9.0",
    "gn:asciiname":"Liujiazhuang",
    "gn:country_code":"CN",
    "gn:dem":364,
    "gn:feature_class":"P",
    "gn:feature_code":"PPL",
    "gn:name":"Liujiazhuang",
    "gn:population":0,
    "gn:timezone":"Asia/Shanghai",
    "iso:country":"CN",
    "name:und_x_variant":[
        "\u5218\u5bb6\u5e84",
        "Liujiazhuang"
    ],
    "wof:name":"Liujiazhuang",
    "wof:placetype":"locality"
},
  "geometry": {"coordinates":[112.13433000000001,33.20298],"type":"Point"}
}