{
  "type": "Feature",
  "properties": {
    "gn:admin1_code":"22.0",
    "gn:asciiname":"Huangtuliangcun",
    "gn:country_code":"CN",
    "gn:dem":706,
    "gn:feature_class":"P",
    "gn:feature_code":"PPL",
    "gn:name":"Huangtuliangcun",
    "gn:population":0,
    "gn:timezone":"Asia/Shanghai",
    "iso:country":"CN",
    "name:zho_x_preferred":[
        "\u9ec4\u571f\u6881\u6751"
    ],
    "wof:name":"Huangtuliangcun",
    "wof:placetype":"locality"
},
  "geometry": {"coordinates":[116.03907,40.36811],"type":"Point"}
}