{
  "type": "Feature",
  "properties": {
    "gn:admin1_code":"16",
    "gn:asciiname":"Gancun",
    "gn:country_code":"CN",
    "gn:dem":248,
    "gn:feature_class":"P",
    "gn:feature_code":"PPL",
    "gn:name":"Gancun",
    "gn:population":0,
    "gn:timezone":"Asia/Shanghai",
    "iso:country":"CN",
    "name:zho_x_preferred":[
        "\u7518\u6751"
    ],
    "wof:name":"Gancun",
    "wof:placetype":"locality"
},
  "geometry": {"coordinates":[110.735,24.5967],"type":"Point"}
}