{
  "type": "Feature",
  "properties": {
    "gn:admin1_code":"1.0",
    "gn:asciiname":"Zhudacun",
    "gn:country_code":"CN",
    "gn:dem":30,
    "gn:feature_class":"P",
    "gn:feature_code":"PPL",
    "gn:name":"Zhudacun",
    "gn:population":0,
    "gn:timezone":"Asia/Shanghai",
    "iso:country":"CN",
    "name:zho_x_preferred":[
        "\u6731\u5927\u6751"
    ],
    "wof:name":"Zhudacun",
    "wof:placetype":"locality"
},
  "geometry": {"coordinates":[115.87838000000001,32.77422],"type":"Point"}
}