{
  "type": "Feature",
  "properties": {
    "gn:admin1_code":"1.0",
    "gn:asciiname":"Fengsicun",
    "gn:country_code":"CN",
    "gn:dem":25,
    "gn:feature_class":"P",
    "gn:feature_code":"PPL",
    "gn:name":"Fengsicun",
    "gn:population":0,
    "gn:timezone":"Asia/Shanghai",
    "iso:country":"CN",
    "name:zho_x_preferred":[
        "\u5c01\u5bfa\u6751"
    ],
    "wof:name":"Fengsicun",
    "wof:placetype":"locality"
},
  "geometry": {"coordinates":[117.31480999999999,33.45093],"type":"Point"}
}