{
  "type": "Feature",
  "properties": {
    "gn:admin1_code":"26.0",
    "gn:asciiname":"Renjiacun",
    "gn:country_code":"CN",
    "gn:dem":812,
    "gn:feature_class":"P",
    "gn:feature_code":"PPL",
    "gn:name":"Renjiacun",
    "gn:population":0,
    "gn:timezone":"Asia/Shanghai",
    "iso:country":"CN",
    "name:zho_x_preferred":[
        "\u4efb\u5bb6\u6751"
    ],
    "wof:name":"Renjiacun",
    "wof:placetype":"locality"
},
  "geometry": {"coordinates":[110.04606,33.76345999999999],"type":"Point"}
}