{
  "type": "Feature",
  "properties": {
    "gn:admin1_code":"11",
    "gn:asciiname":"Baoshantang",
    "gn:country_code":"CN",
    "gn:dem":220,
    "gn:feature_class":"P",
    "gn:feature_code":"PPL",
    "gn:name":"Baoshantang",
    "gn:population":0,
    "gn:timezone":"Asia/Shanghai",
    "iso:country":"CN",
    "name:zho_x_preferred":[
        "\u5b9d\u5584\u5802"
    ],
    "wof:name":"Baoshantang",
    "wof:placetype":"locality"
},
  "geometry": {"coordinates":[111.8967,27.52564000000001],"type":"Point"}
}