{
  "type": "Feature",
  "properties": {
    "gn:admin1_code":"11.0",
    "gn:asciiname":"Liaojiayuan",
    "gn:country_code":"CN",
    "gn:dem":642,
    "gn:feature_class":"P",
    "gn:feature_code":"PPL",
    "gn:name":"Liaojiayuan",
    "gn:population":0,
    "gn:timezone":"Asia/Shanghai",
    "iso:country":"CN",
    "name:zho_x_preferred":[
        "\u5ed6\u5bb6\u9662"
    ],
    "wof:name":"Liaojiayuan",
    "wof:placetype":"locality"
},
  "geometry": {"coordinates":[110.057,29.39129],"type":"Point"}
}