{
  "type": "Feature",
  "properties": {
    "gn:admin1_code":"30.0",
    "gn:asciiname":"Shangliuxue",
    "gn:country_code":"CN",
    "gn:dem":626,
    "gn:feature_class":"P",
    "gn:feature_code":"PPL",
    "gn:name":"Shangliuxue",
    "gn:population":0,
    "gn:timezone":"Asia/Shanghai",
    "iso:country":"CN",
    "name:zho_x_preferred":[
        "Shangliuxue"
    ],
    "name:zho_x_variant":[
        "\u4e0a\u516d\u96ea"
    ],
    "wof:name":"Shangliuxue",
    "wof:placetype":"locality"
},
  "geometry": {"coordinates":[112.20417,24.24056],"type":"Point"}
}