{
  "type": "Feature",
  "properties": {
    "gn:admin1_code":"3",
    "gn:asciiname":"Xinweishang",
    "gn:country_code":"CN",
    "gn:dem":162,
    "gn:feature_class":"P",
    "gn:feature_code":"PPL",
    "gn:name":"Xinweishang",
    "gn:population":0,
    "gn:timezone":"Asia/Shanghai",
    "iso:country":"CN",
    "name:zho_x_preferred":[
        "\u65b0\u56f4\u4e0a"
    ],
    "wof:name":"Xinweishang",
    "wof:placetype":"locality"
},
  "geometry": {"coordinates":[114.941,25.3485],"type":"Point"}
}