{
  "type": "Feature",
  "properties": {
    "gn:admin1_code":"25.0",
    "gn:asciiname":"Zoujiachuang",
    "gn:country_code":"CN",
    "gn:dem":24,
    "gn:feature_class":"P",
    "gn:feature_code":"PPL",
    "gn:name":"Zoujiachuang",
    "gn:population":0,
    "gn:timezone":"Asia/Shanghai",
    "iso:country":"CN",
    "name:zho_x_preferred":[
        "\u90b9\u5bb6\u5e8a"
    ],
    "wof:name":"Zoujiachuang",
    "wof:placetype":"locality"
},
  "geometry": {"coordinates":[122.07116000000001,37.07878],"type":"Point"}
}