{
  "type": "Feature",
  "properties": {
    "gn:admin1_code":"7.0",
    "gn:asciiname":"Guanxicun",
    "gn:country_code":"CN",
    "gn:dem":59,
    "gn:feature_class":"P",
    "gn:feature_code":"PPL",
    "gn:name":"Guanxicun",
    "gn:population":0,
    "gn:timezone":"Asia/Shanghai",
    "iso:country":"CN",
    "name:zho_x_preferred":[
        "\u5173\u897f\u6751"
    ],
    "wof:name":"Guanxicun",
    "wof:placetype":"locality"
},
  "geometry": {"coordinates":[119.16623,26.19594],"type":"Point"}
}