{
  "type": "Feature",
  "properties": {
    "gn:admin1_code":"16",
    "gn:asciiname":"Jiangyou",
    "gn:country_code":"CN",
    "gn:dem":119,
    "gn:feature_class":"P",
    "gn:feature_code":"PPL",
    "gn:name":"Jiangyou",
    "gn:population":0,
    "gn:timezone":"Asia/Shanghai",
    "iso:country":"CN",
    "name:zho_x_preferred":[
        "\u6c5f\u53f3"
    ],
    "wof:name":"Jiangyou",
    "wof:placetype":"locality"
},
  "geometry": {"coordinates":[110.645,24.6828],"type":"Point"}
}