{
  "type": "Feature",
  "properties": {
    "gn:admin1_code":"8.0",
    "gn:asciiname":"Xumuchangcun",
    "gn:country_code":"CN",
    "gn:dem":136,
    "gn:feature_class":"P",
    "gn:feature_code":"PPLF",
    "gn:name":"Xumuchangcun",
    "gn:population":0,
    "gn:timezone":"Asia/Shanghai",
    "iso:country":"CN",
    "name:zho_x_preferred":[
        "\u755c\u7267\u573a\u6751"
    ],
    "wof:name":"Xumuchangcun",
    "wof:placetype":"locality"
},
  "geometry": {"coordinates":[132.12386999999998,46.34042],"type":"Point"}
}