{
  "type": "Feature",
  "properties": {
    "gn:admin1_code":"15.0",
    "gn:asciiname":"Huangnigang",
    "gn:country_code":"CN",
    "gn:dem":2452,
    "gn:feature_class":"P",
    "gn:feature_code":"PPL",
    "gn:name":"Huangnigang",
    "gn:population":0,
    "gn:timezone":"Asia/Shanghai",
    "iso:country":"CN",
    "name:zho_x_preferred":[
        "\u9ec4\u6ce5\u5c97"
    ],
    "wof:name":"Huangnigang",
    "wof:placetype":"locality"
},
  "geometry": {"coordinates":[102.99299999999999,37.361],"type":"Point"}
}