{
  "type": "Feature",
  "properties": {
    "gn:admin1_code":"26.0",
    "gn:asciiname":"Tongqiancun",
    "gn:country_code":"CN",
    "gn:dem":1133,
    "gn:feature_class":"P",
    "gn:feature_code":"PPL",
    "gn:name":"Tongqiancun",
    "gn:population":0,
    "gn:timezone":"Asia/Shanghai",
    "iso:country":"CN",
    "name:zho_x_preferred":[
        "\u94dc\u94b1\u6751"
    ],
    "wof:name":"Tongqiancun",
    "wof:placetype":"locality"
},
  "geometry": {"coordinates":[108.67621,33.1397],"type":"Point"}
}