{
  "type": "Feature",
  "properties": {
    "gn:admin1_code":"32.0",
    "gn:asciiname":"Wenzhouping",
    "gn:country_code":"CN",
    "gn:dem":717,
    "gn:feature_class":"P",
    "gn:feature_code":"PPL",
    "gn:name":"Wenzhouping",
    "gn:population":0,
    "gn:timezone":"Asia/Shanghai",
    "iso:country":"CN",
    "name:zho_x_preferred":[
        "\u95ee\u5dde\u576a"
    ],
    "wof:name":"Wenzhouping",
    "wof:placetype":"locality"
},
  "geometry": {"coordinates":[107.62048,31.5666],"type":"Point"}
}