{
  "type": "Feature",
  "properties": {
    "gn:admin1_code":"14.0",
    "gn:asciiname":"Maiduicun",
    "gn:country_code":"CN",
    "gn:dem":3685,
    "gn:feature_class":"P",
    "gn:feature_code":"PPL",
    "gn:name":"Maiduicun",
    "gn:population":0,
    "gn:timezone":"Asia/Urumqi",
    "iso:country":"CN",
    "name:zho_x_preferred":[
        "\u9ea6\u5806\u6751"
    ],
    "wof:name":"Maiduicun",
    "wof:placetype":"locality"
},
  "geometry": {"coordinates":[97.83327,30.50788],"type":"Point"}
}