{
  "type": "Feature",
  "properties": {
    "gn:admin1_code":"16.0",
    "gn:asciiname":"Zhongjian",
    "gn:country_code":"CN",
    "gn:dem":142,
    "gn:feature_class":"P",
    "gn:feature_code":"PPL",
    "gn:name":"Zhongjian",
    "gn:population":0,
    "gn:timezone":"Asia/Shanghai",
    "iso:country":"CN",
    "name:zho_x_preferred":[
        "\u4e2d\u95f4"
    ],
    "wof:name":"Zhongjian",
    "wof:placetype":"locality"
},
  "geometry": {"coordinates":[108.303,23.3402],"type":"Point"}
}