{
  "type": "Feature",
  "properties": {
    "gn:admin1_code":"28.0",
    "gn:asciiname":"Xinfangzi",
    "gn:cc2":"CN",
    "gn:country_code":"CN",
    "gn:dem":5,
    "gn:feature_class":"P",
    "gn:feature_code":"PPL",
    "gn:name":"Xinfangzi",
    "gn:population":0,
    "gn:timezone":"Asia/Shanghai",
    "iso:country":"CN",
    "name:und_x_variant":[
        "Hsinfangtze",
        "Hsin-fang-tzu",
        "Xinfangzi"
    ],
    "wof:name":"Xinfangzi",
    "wof:placetype":"locality"
},
  "geometry": {"coordinates":[117.11667,38.81667],"type":"Point"}
}