{
  "type": "Feature",
  "properties": {
    "gn:admin1_code":"8.0",
    "gn:asciiname":"Wangqingtuozi",
    "gn:country_code":"CN",
    "gn:dem":123,
    "gn:feature_class":"P",
    "gn:feature_code":"PPL",
    "gn:name":"Wangqingtuozi",
    "gn:population":0,
    "gn:timezone":"Asia/Shanghai",
    "iso:country":"CN",
    "name:zho_x_preferred":[
        "\u671b\u9752\u5768\u5b50"
    ],
    "wof:name":"Wangqingtuozi",
    "wof:placetype":"locality"
},
  "geometry": {"coordinates":[125.06974,45.44682],"type":"Point"}
}