{
  "type": "Feature",
  "properties": {
    "gn:admin1_code":"26.0",
    "gn:asciiname":"Luyuancun",
    "gn:country_code":"CN",
    "gn:dem":963,
    "gn:feature_class":"P",
    "gn:feature_code":"PPL",
    "gn:name":"Luyuancun",
    "gn:population":0,
    "gn:timezone":"Asia/Shanghai",
    "iso:country":"CN",
    "name:zho_x_preferred":[
        "\u9e7f\u586c\u6751"
    ],
    "wof:name":"Luyuancun",
    "wof:placetype":"locality"
},
  "geometry": {"coordinates":[110.50329000000001,37.1617],"type":"Point"}
}