{
  "type": "Feature",
  "properties": {
    "gn:admin1_code":"16",
    "gn:asciiname":"Xiaojieling",
    "gn:country_code":"CN",
    "gn:dem":242,
    "gn:feature_class":"P",
    "gn:feature_code":"PPL",
    "gn:name":"Xiaojieling",
    "gn:population":0,
    "gn:timezone":"Asia/Shanghai",
    "iso:country":"CN",
    "name:zho_x_preferred":[
        "\u5c0f\u754c\u5cad"
    ],
    "wof:name":"Xiaojieling",
    "wof:placetype":"locality"
},
  "geometry": {"coordinates":[110.518,25.2888],"type":"Point"}
}