{
  "type": "Feature",
  "properties": {
    "gn:admin1_code":"29.0",
    "gn:asciiname":"Sanshao",
    "gn:country_code":"CN",
    "gn:dem":2266,
    "gn:feature_class":"P",
    "gn:feature_code":"PPL",
    "gn:name":"Sanshao",
    "gn:population":0,
    "gn:timezone":"Asia/Shanghai",
    "iso:country":"CN",
    "name:und_x_variant":[
        "\u4e09\u54e8"
    ],
    "wof:name":"Sanshao",
    "wof:placetype":"locality"
},
  "geometry": {"coordinates":[102.6939,25.68376],"type":"Point"}
}