{
  "type": "Feature",
  "properties": {
    "gn:admin1_code":"13",
    "gn:asciiname":"Yasidun",
    "gn:country_code":"CN",
    "gn:dem":1428,
    "gn:feature_class":"P",
    "gn:feature_code":"PPL",
    "gn:name":"Yasidun",
    "gn:population":0,
    "gn:timezone":"Asia/Shanghai",
    "iso:country":"CN",
    "name:und_x_variant":[
        "\u4e9a\u65af\u58a9"
    ],
    "wof:name":"Yasidun",
    "wof:placetype":"locality"
},
  "geometry": {"coordinates":[76.95256999999999,38.01229],"type":"Point"}
}