{
  "type": "Feature",
  "properties": {
    "gn:admin1_code":"16",
    "gn:asciiname":"Nailing",
    "gn:country_code":"CN",
    "gn:dem":317,
    "gn:feature_class":"P",
    "gn:feature_code":"PPL",
    "gn:name":"Nailing",
    "gn:population":0,
    "gn:timezone":"Asia/Shanghai",
    "iso:country":"CN",
    "name:zho_x_preferred":[
        "\u5948\u5cad"
    ],
    "wof:name":"Nailing",
    "wof:placetype":"locality"
},
  "geometry": {"coordinates":[110.23699999999999,25.6023],"type":"Point"}
}