{
  "type": "Feature",
  "properties": {
    "gn:admin1_code":"26.0",
    "gn:asciiname":"Yuzitan",
    "gn:country_code":"CN",
    "gn:dem":1273,
    "gn:feature_class":"P",
    "gn:feature_code":"PPL",
    "gn:name":"Yuzitan",
    "gn:population":0,
    "gn:timezone":"Asia/Shanghai",
    "iso:country":"CN",
    "name:zho_x_preferred":[
        "\u828b\u5b50\u6ee9"
    ],
    "wof:name":"Yuzitan",
    "wof:placetype":"locality"
},
  "geometry": {"coordinates":[109.19767,36.70643],"type":"Point"}
}