{
  "type": "Feature",
  "properties": {
    "gn:admin1_code":"10.0",
    "gn:asciiname":"Mijia'an",
    "gn:country_code":"CN",
    "gn:dem":145,
    "gn:feature_class":"P",
    "gn:feature_code":"PPL",
    "gn:name":"Mijia\u2019an",
    "gn:population":0,
    "gn:timezone":"Asia/Shanghai",
    "iso:country":"CN",
    "name:und_x_variant":[
        "Mijia\u2019an",
        "\u79d8\u5bb6\u5cb8"
    ],
    "wof:name":"Mijia'an",
    "wof:placetype":"locality"
},
  "geometry": {"coordinates":[114.10393999999999,38.3365],"type":"Point"}
}