{
  "type": "Feature",
  "properties": {
    "gn:admin1_code":"29.0",
    "gn:asciiname":"Shiqiaohe",
    "gn:country_code":"CN",
    "gn:dem":2421,
    "gn:feature_class":"P",
    "gn:feature_code":"PPL",
    "gn:name":"Shiqiaohe",
    "gn:population":0,
    "gn:timezone":"Asia/Shanghai",
    "iso:country":"CN",
    "name:zho_x_preferred":[
        "\u77f3\u6865\u6cb3"
    ],
    "wof:name":"Shiqiaohe",
    "wof:placetype":"locality"
},
  "geometry": {"coordinates":[100.996,25.2912],"type":"Point"}
}