{
  "type": "Feature",
  "properties": {
    "gn:admin1_code":"8.0",
    "gn:asciiname":"Gaoshengcun",
    "gn:country_code":"CN",
    "gn:dem":219,
    "gn:feature_class":"P",
    "gn:feature_code":"PPL",
    "gn:name":"Gaoshengcun",
    "gn:population":0,
    "gn:timezone":"Asia/Shanghai",
    "iso:country":"CN",
    "name:zho_x_preferred":[
        "\u9ad8\u5347\u6751"
    ],
    "wof:name":"Gaoshengcun",
    "wof:placetype":"locality"
},
  "geometry": {"coordinates":[124.76528999999999,48.08489],"type":"Point"}
}