{
  "type": "Feature",
  "properties": {
    "gn:admin1_code":"26",
    "gn:asciiname":"Zhenxing",
    "gn:country_code":"CN",
    "gn:dem":388,
    "gn:feature_class":"P",
    "gn:feature_code":"PPLA4",
    "gn:name":"Zhenxing",
    "gn:population":0,
    "gn:timezone":"Asia/Shanghai",
    "iso:country":"CN",
    "name:zho_x_preferred":[
        "\u632f\u5174"
    ],
    "wof:name":"Zhenxing",
    "wof:placetype":"locality"
},
  "geometry": {"coordinates":[109.19284,34.66853],"type":"Point"}
}