{
  "type": "Feature",
  "properties": {
    "gn:admin1_code":"26.0",
    "gn:asciiname":"Xujiaya",
    "gn:country_code":"CN",
    "gn:dem":1500,
    "gn:feature_class":"P",
    "gn:feature_code":"PPL",
    "gn:name":"Xujiaya",
    "gn:population":0,
    "gn:timezone":"Asia/Shanghai",
    "iso:country":"CN",
    "name:und_x_variant":[
        "\u80e5\u5bb6\u57ad"
    ],
    "wof:name":"Xujiaya",
    "wof:placetype":"locality"
},
  "geometry": {"coordinates":[106.41852,32.70532],"type":"Point"}
}