{
  "type": "Feature",
  "properties": {
    "gn:admin1_code":"16",
    "gn:asciiname":"Liangfeng",
    "gn:country_code":"CN",
    "gn:dem":151,
    "gn:feature_class":"P",
    "gn:feature_code":"PPL",
    "gn:name":"Liangfeng",
    "gn:population":0,
    "gn:timezone":"Asia/Shanghai",
    "iso:country":"CN",
    "name:und_x_variant":[
        "Liangfungh\u00fc",
        "Liang-feng-hs\u00fc",
        "Lin-kuei",
        "Liangfeng"
    ],
    "name:zho_x_preferred":[
        "\u826f\u4e30"
    ],
    "wof:name":"Liangfeng",
    "wof:placetype":"locality"
},
  "geometry": {"coordinates":[110.294,25.1007],"type":"Point"}
}