{
  "type": "Feature",
  "properties": {
    "gn:admin1_code":"12.0",
    "gn:asciiname":"Fengshuqiao",
    "gn:country_code":"CN",
    "gn:dem":68,
    "gn:feature_class":"P",
    "gn:feature_code":"PPL",
    "gn:name":"Fengshuqiao",
    "gn:population":0,
    "gn:timezone":"Asia/Shanghai",
    "iso:country":"CN",
    "name:zho_x_preferred":[
        "\u67ab\u6811\u6865"
    ],
    "wof:name":"Fengshuqiao",
    "wof:placetype":"locality"
},
  "geometry": {"coordinates":[115.58089,30.35477],"type":"Point"}
}