{
  "type": "Feature",
  "properties": {
    "gn:admin1_code":"32.0",
    "gn:asciiname":"Yuxigou",
    "gn:country_code":"CN",
    "gn:dem":424,
    "gn:feature_class":"P",
    "gn:feature_code":"PPL",
    "gn:name":"Yuxigou",
    "gn:population":0,
    "gn:timezone":"Asia/Shanghai",
    "iso:country":"CN",
    "name:zho_x_preferred":[
        "\u9c7c\u6eaa\u6c9f"
    ],
    "wof:name":"Yuxigou",
    "wof:placetype":"locality"
},
  "geometry": {"coordinates":[106.291,31.6722],"type":"Point"}
}