{
  "type": "Feature",
  "properties": {
    "gn:admin1_code":"3.0",
    "gn:asciiname":"Tongkengzhang",
    "gn:country_code":"CN",
    "gn:dem":493,
    "gn:feature_class":"P",
    "gn:feature_code":"PPL",
    "gn:name":"Tongkengzhang",
    "gn:population":0,
    "gn:timezone":"Asia/Shanghai",
    "iso:country":"CN",
    "name:und_x_variant":[
        "\u94dc\u5751\u5d82"
    ],
    "wof:name":"Tongkengzhang",
    "wof:placetype":"locality"
},
  "geometry": {"coordinates":[115.69658,25.02721],"type":"Point"}
}