{
  "type": "Feature",
  "properties": {
    "gn:admin1_code":"15.0",
    "gn:asciiname":"Qujiazhuang",
    "gn:country_code":"CN",
    "gn:dem":2217,
    "gn:feature_class":"P",
    "gn:feature_code":"PPL",
    "gn:name":"Qujiazhuang",
    "gn:population":0,
    "gn:timezone":"Asia/Shanghai",
    "iso:country":"CN",
    "name:zho_x_preferred":[
        "\u5c48\u5bb6\u5e84"
    ],
    "wof:name":"Qujiazhuang",
    "wof:placetype":"locality"
},
  "geometry": {"coordinates":[105.23099999999999,36.4968],"type":"Point"}
}