{
  "type": "Feature",
  "properties": {
    "gn:admin1_code":"3.0",
    "gn:asciiname":"Hongqiaocun",
    "gn:country_code":"CN",
    "gn:dem":41,
    "gn:feature_class":"P",
    "gn:feature_code":"PPL",
    "gn:name":"Hongqiaocun",
    "gn:population":0,
    "gn:timezone":"Asia/Shanghai",
    "iso:country":"CN",
    "name:und_x_variant":[
        "\u7ea2\u6865\u6751"
    ],
    "wof:name":"Hongqiaocun",
    "wof:placetype":"locality"
},
  "geometry": {"coordinates":[115.60154,28.57955],"type":"Point"}
}