{
  "type": "Feature",
  "properties": {
    "gn:admin1_code":"30",
    "gn:asciiname":"Huayuan",
    "gn:country_code":"CN",
    "gn:dem":659,
    "gn:feature_class":"P",
    "gn:feature_code":"PPL",
    "gn:name":"Huayuan",
    "gn:population":0,
    "gn:timezone":"Asia/Shanghai",
    "iso:country":"CN",
    "name:ceb_x_preferred":[
        "Huayuan"
    ],
    "name:deu_x_preferred":[
        "Huayuan"
    ],
    "name:kor_x_preferred":[
        "\ud654\uc704\uc548"
    ],
    "wof:name":"Huayuan",
    "wof:placetype":"locality"
},
  "geometry": {"coordinates":[116.69528,23.87528],"type":"Point"}
}