{
  "type": "Feature",
  "properties": {
    "gn:admin1_code":"1.0",
    "gn:asciiname":"Shiguancun",
    "gn:country_code":"CN",
    "gn:dem":28,
    "gn:feature_class":"P",
    "gn:feature_code":"PPL",
    "gn:name":"Shiguancun",
    "gn:population":0,
    "gn:timezone":"Asia/Shanghai",
    "iso:country":"CN",
    "name:zho_x_preferred":[
        "\u65bd\u5b98\u6751"
    ],
    "wof:name":"Shiguancun",
    "wof:placetype":"locality"
},
  "geometry": {"coordinates":[118.58551,32.46509],"type":"Point"}
}