{
  "type": "Feature",
  "properties": {
    "gn:admin1_code":"3.0",
    "gn:asciiname":"Mamianxia",
    "gn:country_code":"CN",
    "gn:dem":191,
    "gn:feature_class":"P",
    "gn:feature_code":"PPL",
    "gn:name":"Mamianxia",
    "gn:population":0,
    "gn:timezone":"Asia/Shanghai",
    "iso:country":"CN",
    "name:zho_x_preferred":[
        "\u9a6c\u9762\u4e0b"
    ],
    "wof:name":"Mamianxia",
    "wof:placetype":"locality"
},
  "geometry": {"coordinates":[115.066,26.3425],"type":"Point"}
}