{
  "type": "Feature",
  "properties": {
    "gn:admin1_code":"32.0",
    "gn:asciiname":"Gaochenggan",
    "gn:country_code":"CN",
    "gn:dem":463,
    "gn:feature_class":"P",
    "gn:feature_code":"PPL",
    "gn:name":"Gaochenggan",
    "gn:population":0,
    "gn:timezone":"Asia/Shanghai",
    "iso:country":"CN",
    "name:zho_x_preferred":[
        "\u9ad8\u6491\u7aff"
    ],
    "wof:name":"Gaochenggan",
    "wof:placetype":"locality"
},
  "geometry": {"coordinates":[104.346,30.9397],"type":"Point"}
}