{
  "type": "Feature",
  "properties": {
    "gn:admin1_code":"21.0",
    "gn:asciiname":"Zhangyuan",
    "gn:country_code":"CN",
    "gn:dem":2008,
    "gn:feature_class":"P",
    "gn:feature_code":"PPL",
    "gn:name":"Zhangyuan",
    "gn:population":0,
    "gn:timezone":"Asia/Shanghai",
    "iso:country":"CN",
    "name:zho_x_preferred":[
        "\u5f20\u5143"
    ],
    "wof:name":"Zhangyuan",
    "wof:placetype":"locality"
},
  "geometry": {"coordinates":[105.715,36.2247],"type":"Point"}
}