{
  "type": "Feature",
  "properties": {
    "gn:admin1_code":"7",
    "gn:asciiname":"Beishan",
    "gn:country_code":"CN",
    "gn:dem":18,
    "gn:feature_class":"P",
    "gn:feature_code":"PPL",
    "gn:name":"Beishan",
    "gn:population":0,
    "gn:timezone":"Asia/Shanghai",
    "iso:country":"CN",
    "name:zho_x_preferred":[
        "\u5317\u5c71"
    ],
    "wof:name":"Beishan",
    "wof:placetype":"locality"
},
  "geometry": {"coordinates":[119.23148999999999,25.28203],"type":"Point"}
}