{
  "type": "Feature",
  "properties": {
    "gn:admin1_code":"23.0",
    "gn:asciiname":"Dengzhen",
    "gn:country_code":"CN",
    "gn:dem":6,
    "gn:feature_class":"P",
    "gn:feature_code":"PPL",
    "gn:name":"Dengzhen",
    "gn:population":0,
    "gn:timezone":"Asia/Shanghai",
    "iso:country":"CN",
    "name:zho_x_preferred":[
        "Dengzhen"
    ],
    "name:zho_x_variant":[
        "\u9093\u9547"
    ],
    "wof:name":"Dengzhen",
    "wof:placetype":"locality"
},
  "geometry": {"coordinates":[121.75366,31.14435],"type":"Point"}
}