{
  "type": "Feature",
  "properties": {
    "gn:admin1_code":"32.0",
    "gn:asciiname":"Cangtian",
    "gn:country_code":"CN",
    "gn:dem":1533,
    "gn:feature_class":"P",
    "gn:feature_code":"PPL",
    "gn:name":"Cangtian",
    "gn:population":0,
    "gn:timezone":"Asia/Shanghai",
    "iso:country":"CN",
    "name:zho_x_preferred":[
        "\u4ed3\u7530"
    ],
    "wof:name":"Cangtian",
    "wof:placetype":"locality"
},
  "geometry": {"coordinates":[102.35426,27.07438],"type":"Point"}
}