{
  "type": "Feature",
  "properties": {
    "gn:admin1_code":"29.0",
    "gn:asciiname":"Jinyueliang",
    "gn:country_code":"CN",
    "gn:dem":2416,
    "gn:feature_class":"P",
    "gn:feature_code":"PPL",
    "gn:name":"Jinyueliang",
    "gn:population":0,
    "gn:timezone":"Asia/Shanghai",
    "iso:country":"CN",
    "name:zho_x_preferred":[
        "\u91d1\u6708\u4eae"
    ],
    "wof:name":"Jinyueliang",
    "wof:placetype":"locality"
},
  "geometry": {"coordinates":[99.10760000000001,25.7687],"type":"Point"}
}