{
  "type": "Feature",
  "properties": {
    "gn:admin1_code":"25",
    "gn:asciiname":"Luxi",
    "gn:country_code":"CN",
    "gn:dem":162,
    "gn:feature_class":"P",
    "gn:feature_code":"PPL",
    "gn:name":"Luxi",
    "gn:population":0,
    "gn:timezone":"Asia/Shanghai",
    "iso:country":"CN",
    "name:ceb_x_preferred":[
        "Luxi"
    ],
    "name:deu_x_preferred":[
        "Luxi"
    ],
    "name:fra_x_preferred":[
        "Luxi"
    ],
    "name:kor_x_preferred":[
        "\ub8e8\uc2dc\ud604"
    ],
    "name:nor_x_preferred":[
        "Luxi"
    ],
    "name:swe_x_preferred":[
        "Luxi"
    ],
    "name:zho_x_preferred":[
        "\u9c81\u897f"
    ],
    "wof:name":"Luxi",
    "wof:placetype":"locality"
},
  "geometry": {"coordinates":[117.508,36.2047],"type":"Point"}
}