{
  "type": "Feature",
  "properties": {
    "gn:admin1_code":"29.0",
    "gn:asciiname":"Longjie Xiazhai",
    "gn:country_code":"CN",
    "gn:dem":1514,
    "gn:feature_class":"P",
    "gn:feature_code":"PPL",
    "gn:name":"Longjie Xiazhai",
    "gn:population":0,
    "gn:timezone":"Asia/Shanghai",
    "iso:country":"CN",
    "name:zho_x_preferred":[
        "\u9f99\u7ed3\u4e0b\u5be8"
    ],
    "wof:name":"Longjie Xiazhai",
    "wof:placetype":"locality"
},
  "geometry": {"coordinates":[104.453,24.0899],"type":"Point"}
}