{
  "type": "Feature",
  "properties": {
    "gn:admin1_code":"1.0",
    "gn:asciiname":"Yangjiloucun",
    "gn:country_code":"CN",
    "gn:dem":31,
    "gn:feature_class":"P",
    "gn:feature_code":"PPL",
    "gn:name":"Yangjiloucun",
    "gn:population":0,
    "gn:timezone":"Asia/Shanghai",
    "iso:country":"CN",
    "name:zho_x_preferred":[
        "\u6768\u5b63\u697c\u6751"
    ],
    "wof:name":"Yangjiloucun",
    "wof:placetype":"locality"
},
  "geometry": {"coordinates":[117.00776,33.74558],"type":"Point"}
}