{
  "type": "Feature",
  "properties": {
    "gn:admin1_code":"18.0",
    "gn:asciiname":"Lanhualing",
    "gn:country_code":"CN",
    "gn:dem":678,
    "gn:feature_class":"P",
    "gn:feature_code":"PPL",
    "gn:name":"Lanhualing",
    "gn:population":0,
    "gn:timezone":"Asia/Shanghai",
    "iso:country":"CN",
    "name:zho_x_preferred":[
        "\u5170\u82b1\u5cad"
    ],
    "wof:name":"Lanhualing",
    "wof:placetype":"locality"
},
  "geometry": {"coordinates":[108.53100000000001,26.1373],"type":"Point"}
}