{
  "type": "Feature",
  "properties": {
    "gn:admin1_code":"2",
    "gn:asciiname":"Shangdian",
    "gn:country_code":"CN",
    "gn:dem":196,
    "gn:feature_class":"P",
    "gn:feature_code":"PPL",
    "gn:name":"Shangdian",
    "gn:population":0,
    "gn:timezone":"Asia/Shanghai",
    "iso:country":"CN",
    "name:und_x_variant":[
        "\u4e0a\u5e97"
    ],
    "wof:name":"Shangdian",
    "wof:placetype":"locality"
},
  "geometry": {"coordinates":[119.81610999999999,29.78306],"type":"Point"}
}