{
  "type": "Feature",
  "properties": {
    "gn:admin1_code":"12.0",
    "gn:asciiname":"Huanglingxiang",
    "gn:country_code":"CN",
    "gn:dem":25,
    "gn:feature_class":"P",
    "gn:feature_code":"PPL",
    "gn:name":"Huanglingxiang",
    "gn:population":0,
    "gn:timezone":"Asia/Shanghai",
    "iso:country":"CN",
    "name:und_x_variant":[
        "\u9ec4\u9675\u5df7"
    ],
    "wof:name":"Huanglingxiang",
    "wof:placetype":"locality"
},
  "geometry": {"coordinates":[114.04517,30.3334],"type":"Point"}
}