{
  "type": "Feature",
  "properties": {
    "gn:admin1_code":"13",
    "gn:asciiname":"Batuan Jiulian",
    "gn:country_code":"CN",
    "gn:dem":1025,
    "gn:feature_class":"P",
    "gn:feature_code":"PPL",
    "gn:name":"Batuan Jiulian",
    "gn:population":0,
    "gn:timezone":"Asia/Shanghai",
    "iso:country":"CN",
    "name:und_x_variant":[
        "\u516b\u56e2\u4e5d\u8fde"
    ],
    "wof:name":"Batuan Jiulian",
    "wof:placetype":"locality"
},
  "geometry": {"coordinates":[80.84054,40.52787],"type":"Point"}
}