{
  "type": "Feature",
  "properties": {
    "gn:admin1_code":"14.0",
    "gn:asciiname":"Weiqing",
    "gn:country_code":"CN",
    "gn:dem":4229,
    "gn:feature_class":"P",
    "gn:feature_code":"PPL",
    "gn:name":"Weiqing",
    "gn:population":0,
    "gn:timezone":"Asia/Urumqi",
    "iso:country":"CN",
    "name:bod_x_preferred":[
        "Oiq\u00ean"
    ],
    "name:zho_x_preferred":[
        "Weiqing"
    ],
    "name:zho_x_variant":[
        "\u7ef4\u6e05",
        "Chawutang Gongshe",
        "\u67e5\u543e\u5858\u516c\u793e"
    ],
    "wof:name":"Weiqing",
    "wof:placetype":"locality"
},
  "geometry": {"coordinates":[98.001,31.901],"type":"Point"}
}