{
  "type": "Feature",
  "properties": {
    "gn:admin1_code":"4.0",
    "gn:asciiname":"Daguanzhuang",
    "gn:country_code":"CN",
    "gn:dem":5,
    "gn:feature_class":"P",
    "gn:feature_code":"PPL",
    "gn:name":"Daguanzhuang",
    "gn:population":0,
    "gn:timezone":"Asia/Shanghai",
    "iso:country":"CN",
    "name:und_x_variant":[
        "\u5927\u5b98\u5e84"
    ],
    "name:zho_x_preferred":[
        "\u5927\u5b98\u5e84"
    ],
    "wof:name":"Daguanzhuang",
    "wof:placetype":"locality"
},
  "geometry": {"coordinates":[120.65294,31.26514],"type":"Point"}
}