{
  "type": "Feature",
  "properties": {
    "gn:country":"CN",
    "gn:fcode":"PPL",
    "gn:pop":2279,
    "iso:country":"CN",
    "name:unk_x_variant":[
        "Ta-tun-ch\u2019iu"
    ],
    "qs:name":"Dadunqiu",
    "qs:photos_9r":0,
    "qs:photos_sr":0,
    "qs:pop_sr":"4",
    "wof:name":"Dadunqiu",
    "wof:placetype":"locality",
    "wof:population":2279
},
  "geometry": {"coordinates":[117.03306000000001,39.40611],"type":"Point"}
}