{
  "type": "Feature",
  "properties": {
    "gn:admin1_code":"2.0",
    "gn:asciiname":"Dahengling",
    "gn:country_code":"CN",
    "gn:dem":882,
    "gn:feature_class":"P",
    "gn:feature_code":"PPL",
    "gn:name":"Dahengling",
    "gn:population":0,
    "gn:timezone":"Asia/Shanghai",
    "iso:country":"CN",
    "name:zho_x_preferred":[
        "\u5927\u6a2a\u5cad"
    ],
    "wof:name":"Dahengling",
    "wof:placetype":"locality"
},
  "geometry": {"coordinates":[119.29263,27.55977],"type":"Point"}
}