{
  "type": "Feature",
  "properties": {
    "gn:admin1_code":"15.0",
    "gn:asciiname":"Jingpo'er",
    "gn:country_code":"CN",
    "gn:dem":2060,
    "gn:feature_class":"P",
    "gn:feature_code":"PPL",
    "gn:name":"Jingpo\u2019er",
    "gn:population":0,
    "gn:timezone":"Asia/Shanghai",
    "iso:country":"CN",
    "name:und_x_variant":[
        "Jingpo\u2019er"
    ],
    "name:zho_x_preferred":[
        "\u666f\u5761\u513f"
    ],
    "wof:name":"Jingpo'er",
    "wof:placetype":"locality"
},
  "geometry": {"coordinates":[105.247,34.6583],"type":"Point"}
}