{
  "type": "Feature",
  "properties": {
    "gn:admin1_code":"29.0",
    "gn:asciiname":"Pingda",
    "gn:country_code":"CN",
    "gn:dem":1591,
    "gn:feature_class":"P",
    "gn:feature_code":"PPL",
    "gn:name":"Pingda",
    "gn:population":0,
    "gn:timezone":"Asia/Shanghai",
    "iso:country":"CN",
    "wof:name":"Pingda",
    "wof:placetype":"locality"
},
  "geometry": {"coordinates":[98.93333,24.31667],"type":"Point"}
}