{
  "type": "Feature",
  "properties": {
    "gn:admin1_code":"25",
    "gn:asciiname":"Qianhuangtuyan",
    "gn:country_code":"CN",
    "gn:dem":64,
    "gn:feature_class":"P",
    "gn:feature_code":"PPL",
    "gn:name":"Qianhuangtuyan",
    "gn:population":0,
    "gn:timezone":"Asia/Shanghai",
    "iso:country":"CN",
    "name:zho_x_preferred":[
        "\u524d\u9ec4\u571f\u5830"
    ],
    "wof:name":"Qianhuangtuyan",
    "wof:placetype":"locality"
},
  "geometry": {"coordinates":[118.22,34.9715],"type":"Point"}
}