{
  "type": "Feature",
  "properties": {
    "gn:admin1_code":"18.0",
    "gn:asciiname":"Liaojianwan",
    "gn:country_code":"CN",
    "gn:dem":684,
    "gn:feature_class":"P",
    "gn:feature_code":"PPL",
    "gn:name":"Liaojianwan",
    "gn:population":0,
    "gn:timezone":"Asia/Shanghai",
    "iso:country":"CN",
    "name:zho_x_preferred":[
        "\u8fbd\u89c1\u6e7e"
    ],
    "wof:name":"Liaojianwan",
    "wof:placetype":"locality"
},
  "geometry": {"coordinates":[108.992,27.8841],"type":"Point"}
}