{
  "type": "Feature",
  "properties": {
    "gn:admin1_code":"29.0",
    "gn:asciiname":"Wubai",
    "gn:country_code":"CN",
    "gn:dem":1917,
    "gn:feature_class":"P",
    "gn:feature_code":"PPL",
    "gn:name":"Wubai",
    "gn:population":0,
    "gn:timezone":"Asia/Shanghai",
    "iso:country":"CN",
    "name:zho_x_preferred":[
        "\u575e\u767d"
    ],
    "wof:name":"Wubai",
    "wof:placetype":"locality"
},
  "geometry": {"coordinates":[104.032,24.9485],"type":"Point"}
}