{
  "type": "Feature",
  "properties": {
    "gn:admin1_code":"16",
    "gn:asciiname":"Shatang",
    "gn:cc2":"CN",
    "gn:country_code":"CN",
    "gn:dem":76,
    "gn:feature_class":"P",
    "gn:feature_code":"PPL",
    "gn:name":"Shatang",
    "gn:population":0,
    "gn:timezone":"Asia/Shanghai",
    "iso:country":"CN",
    "name:und_x_variant":[
        "Sha-t\u2019ang-hs\u00fc",
        "Shatang"
    ],
    "wof:name":"Shatang",
    "wof:placetype":"locality"
},
  "geometry": {"coordinates":[109.86333,22.92278],"type":"Point"}
}