{
  "type": "Feature",
  "properties": {
    "gn:admin1_code":"32.0",
    "gn:asciiname":"Sanfengzui",
    "gn:country_code":"CN",
    "gn:dem":350,
    "gn:feature_class":"P",
    "gn:feature_code":"PPL",
    "gn:name":"Sanfengzui",
    "gn:population":0,
    "gn:timezone":"Asia/Shanghai",
    "iso:country":"CN",
    "name:zho_x_preferred":[
        "\u4e09\u51e4\u5480"
    ],
    "wof:name":"Sanfengzui",
    "wof:placetype":"locality"
},
  "geometry": {"coordinates":[105.17162999999999,30.62353],"type":"Point"}
}