{
  "type": "Feature",
  "properties": {
    "gn:admin1_code":"14.0",
    "gn:asciiname":"Kangzuobugang",
    "gn:country_code":"CN",
    "gn:dem":4483,
    "gn:feature_class":"P",
    "gn:feature_code":"PPL",
    "gn:name":"Kangzuobugang",
    "gn:population":0,
    "gn:timezone":"Asia/Urumqi",
    "iso:country":"CN",
    "name:zho_x_preferred":[
        "\u5eb7\u4f5c\u5e03\u5c97"
    ],
    "wof:name":"Kangzuobugang",
    "wof:placetype":"locality"
},
  "geometry": {"coordinates":[90.36454999999999,29.82864],"type":"Point"}
}