{
  "type": "Feature",
  "properties": {
    "gn:admin1_code":"11",
    "gn:asciiname":"Baisha",
    "gn:cc2":"CN",
    "gn:country_code":"CN",
    "gn:dem":94,
    "gn:feature_class":"P",
    "gn:feature_code":"PPL",
    "gn:name":"Baisha",
    "gn:population":0,
    "gn:timezone":"Asia/Shanghai",
    "iso:country":"CN",
    "name:ceb_x_preferred":[
        "Baisha"
    ],
    "name:deu_x_preferred":[
        "Baisha"
    ],
    "name:fra_x_preferred":[
        "Baisha"
    ],
    "name:nld_x_preferred":[
        "Baisha"
    ],
    "name:und_x_variant":[
        "Pai-sha",
        "Pai-sha-hs\u00fc"
    ],
    "wof:name":"Baisha",
    "wof:placetype":"locality"
},
  "geometry": {"coordinates":[112.675,26.15611],"type":"Point"}
}