{
  "type": "Feature",
  "properties": {
    "gn:admin1_code":"11.0",
    "gn:asciiname":"Hengchongzi",
    "gn:country_code":"CN",
    "gn:dem":74,
    "gn:feature_class":"P",
    "gn:feature_code":"PPL",
    "gn:name":"Hengchongzi",
    "gn:population":0,
    "gn:timezone":"Asia/Shanghai",
    "iso:country":"CN",
    "name:zho_x_preferred":[
        "\u6a2a\u51b2\u5b50"
    ],
    "wof:name":"Hengchongzi",
    "wof:placetype":"locality"
},
  "geometry": {"coordinates":[112.62474,28.06828],"type":"Point"}
}