{
  "type": "Feature",
  "properties": {
    "gn:admin1_code":"2.0",
    "gn:asciiname":"Dongwushan",
    "gn:country_code":"CN",
    "gn:dem":180,
    "gn:feature_class":"P",
    "gn:feature_code":"PPL",
    "gn:name":"Dongwushan",
    "gn:population":0,
    "gn:timezone":"Asia/Shanghai",
    "iso:country":"CN",
    "name:und_x_variant":[
        "\u4e1c\u575e\u5c71"
    ],
    "name:zho_x_preferred":[
        "Dongwushan"
    ],
    "wof:name":"Dongwushan",
    "wof:placetype":"locality"
},
  "geometry": {"coordinates":[119.99838,30.17255],"type":"Point"}
}