{
  "type": "Feature",
  "properties": {
    "gn:admin1_code":"5.0",
    "gn:asciiname":"Yaoqihaocun",
    "gn:country_code":"CN",
    "gn:dem":176,
    "gn:feature_class":"P",
    "gn:feature_code":"PPL",
    "gn:name":"Yaoqihaocun",
    "gn:population":0,
    "gn:timezone":"Asia/Shanghai",
    "iso:country":"CN",
    "name:zho_x_preferred":[
        "\u8170\u4e03\u53f7\u6751"
    ],
    "wof:name":"Yaoqihaocun",
    "wof:placetype":"locality"
},
  "geometry": {"coordinates":[126.12588999999998,45.00686],"type":"Point"}
}