{
  "type": "Feature",
  "properties": {
    "gn:admin1_code":"02",
    "gn:asciiname":"Huangyang",
    "gn:country_code":"CN",
    "gn:dem":404,
    "gn:feature_class":"P",
    "gn:feature_code":"PPLA4",
    "gn:name":"Huangyang",
    "gn:population":0,
    "gn:timezone":"Asia/Shanghai",
    "iso:country":"CN",
    "name:und_x_variant":[
        "Shipingchuan",
        "Huangyang",
        "Huangyang Xiang"
    ],
    "name:zho_x_preferred":[
        "\u9ec4\u579f"
    ],
    "name:zho_x_variant":[
        "\u9ec4\u579f\u4e61",
        "\u77f3\u5e73\u5ddd"
    ],
    "wof:name":"Huangyang",
    "wof:placetype":"locality"
},
  "geometry": {"coordinates":[120.35147000000001,28.2963],"type":"Point"}
}