{
  "type": "Feature",
  "properties": {
    "gn:admin1_code":"32",
    "gn:asciiname":"Daxinghuizu",
    "gn:country_code":"CN",
    "gn:dem":391,
    "gn:feature_class":"P",
    "gn:feature_code":"PPL",
    "gn:name":"Daxinghuizu",
    "gn:population":0,
    "gn:timezone":"Asia/Shanghai",
    "iso:country":"CN",
    "name:und_x_variant":[
        "Daxingchang",
        "Daxinghuizu"
    ],
    "name:zho_x_preferred":[
        "\u5927\u5174\u56de\u65cf"
    ],
    "wof:name":"Daxinghuizu",
    "wof:placetype":"locality"
},
  "geometry": {"coordinates":[105.42362,31.2656],"type":"Point"}
}