{
  "type": "Feature",
  "properties": {
    "gn:admin1_code":"32.0",
    "gn:asciiname":"Tuwuji",
    "gn:country_code":"CN",
    "gn:dem":447,
    "gn:feature_class":"P",
    "gn:feature_code":"PPL",
    "gn:name":"Tuwuji",
    "gn:population":0,
    "gn:timezone":"Asia/Shanghai",
    "iso:country":"CN",
    "name:zho_x_preferred":[
        "\u571f\u5c4b\u57fa"
    ],
    "wof:name":"Tuwuji",
    "wof:placetype":"locality"
},
  "geometry": {"coordinates":[104.215,29.2473],"type":"Point"}
}