{
  "type": "Feature",
  "properties": {
    "gn:admin1_code":"12.0",
    "gn:asciiname":"Dayanban",
    "gn:country_code":"CN",
    "gn:dem":557,
    "gn:feature_class":"P",
    "gn:feature_code":"PPL",
    "gn:name":"Dayanban",
    "gn:population":0,
    "gn:timezone":"Asia/Shanghai",
    "iso:country":"CN",
    "name:zho_x_preferred":[
        "Dayanban"
    ],
    "name:zho_x_variant":[
        "\u5927\u5ca9\u677f"
    ],
    "wof:name":"Dayanban",
    "wof:placetype":"locality"
},
  "geometry": {"coordinates":[109.31077000000001,29.50102],"type":"Point"}
}