{
  "type": "Feature",
  "properties": {
    "gn:admin1_code":"25",
    "gn:asciiname":"Fujia Wuzi",
    "gn:country_code":"CN",
    "gn:dem":5,
    "gn:feature_class":"P",
    "gn:feature_code":"PPL",
    "gn:name":"Fujia Wuzi",
    "gn:population":0,
    "gn:timezone":"Asia/Shanghai",
    "iso:country":"CN",
    "name:zho_x_preferred":[
        "\u5085\u5bb6\u5c4b\u5b50"
    ],
    "wof:name":"Fujia Wuzi",
    "wof:placetype":"locality"
},
  "geometry": {"coordinates":[117.795,38.0504],"type":"Point"}
}