{
  "type": "Feature",
  "properties": {
    "gn:admin1_code":"15.0",
    "gn:asciiname":"Niutiwan",
    "gn:country_code":"CN",
    "gn:dem":2194,
    "gn:feature_class":"P",
    "gn:feature_code":"PPL",
    "gn:name":"Niutiwan",
    "gn:population":0,
    "gn:timezone":"Asia/Shanghai",
    "iso:country":"CN",
    "name:zho_x_preferred":[
        "\u725b\u8e44\u6e7e"
    ],
    "wof:name":"Niutiwan",
    "wof:placetype":"locality"
},
  "geometry": {"coordinates":[104.59699999999999,35.0902],"type":"Point"}
}