{
  "type": "Feature",
  "properties": {
    "gn:admin1_code":"4.0",
    "gn:asciiname":"Zhouzhuangzhaicun",
    "gn:country_code":"CN",
    "gn:dem":47,
    "gn:feature_class":"P",
    "gn:feature_code":"PPL",
    "gn:name":"Zhouzhuangzhaicun",
    "gn:population":0,
    "gn:timezone":"Asia/Shanghai",
    "iso:country":"CN",
    "name:zho_x_preferred":[
        "\u5468\u5e84\u5be8\u6751"
    ],
    "wof:name":"Zhouzhuangzhaicun",
    "wof:placetype":"locality"
},
  "geometry": {"coordinates":[116.43170000000001,34.67908],"type":"Point"}
}