{
  "type": "Feature",
  "properties": {
    "gn:admin1_code":"25.0",
    "gn:asciiname":"Yukou Dongcun",
    "gn:country_code":"CN",
    "gn:dem":144,
    "gn:feature_class":"P",
    "gn:feature_code":"PPL",
    "gn:name":"Yukou Dongcun",
    "gn:population":0,
    "gn:timezone":"Asia/Shanghai",
    "iso:country":"CN",
    "name:und_x_variant":[
        "Yukou"
    ],
    "name:zho_x_preferred":[
        "\u5cea\u53e3\u4e1c\u6751"
    ],
    "wof:name":"Yukou Dongcun",
    "wof:placetype":"locality"
},
  "geometry": {"coordinates":[116.98333,35.76667],"type":"Point"}
}