{
  "type": "Feature",
  "properties": {
    "gn:admin1_code":"26.0",
    "gn:asciiname":"Matizhangcun",
    "gn:country_code":"CN",
    "gn:dem":1671,
    "gn:feature_class":"P",
    "gn:feature_code":"PPL",
    "gn:name":"Matizhangcun",
    "gn:population":0,
    "gn:timezone":"Asia/Shanghai",
    "iso:country":"CN",
    "name:zho_x_preferred":[
        "\u9a6c\u8e44\u638c\u6751"
    ],
    "wof:name":"Matizhangcun",
    "wof:placetype":"locality"
},
  "geometry": {"coordinates":[109.92999,35.7557],"type":"Point"}
}