{
  "type": "Feature",
  "properties": {
    "gn:admin1_code":"5.0",
    "gn:asciiname":"Zhanglaocun",
    "gn:country_code":"CN",
    "gn:dem":175,
    "gn:feature_class":"P",
    "gn:feature_code":"PPL",
    "gn:name":"Zhanglaocun",
    "gn:population":0,
    "gn:timezone":"Asia/Shanghai",
    "iso:country":"CN",
    "name:zho_x_preferred":[
        "\u5f20\u8001\u6751"
    ],
    "wof:name":"Zhanglaocun",
    "wof:placetype":"locality"
},
  "geometry": {"coordinates":[126.52641,44.11366],"type":"Point"}
}