{
  "type": "Feature",
  "properties": {
    "gn:admin1_code":"08",
    "gn:asciiname":"Qianshao Linchang",
    "gn:country_code":"CN",
    "gn:dem":506,
    "gn:feature_class":"P",
    "gn:feature_code":"PPLF",
    "gn:name":"Qianshao Linchang",
    "gn:population":0,
    "gn:timezone":"Asia/Shanghai",
    "iso:country":"CN",
    "wof:name":"Qianshao Linchang",
    "wof:placetype":"locality"
},
  "geometry": {"coordinates":[122.35167,53.05416999999999],"type":"Point"}
}