{
  "type": "Feature",
  "properties": {
    "gn:admin1_code":"4.0",
    "gn:asciiname":"Gexin",
    "gn:country_code":"CN",
    "gn:dem":5,
    "gn:feature_class":"P",
    "gn:feature_code":"PPL",
    "gn:name":"Gexin",
    "gn:population":0,
    "gn:timezone":"Asia/Shanghai",
    "iso:country":"CN",
    "name:zho_x_preferred":[
        "\u9769\u65b0"
    ],
    "wof:name":"Gexin",
    "wof:placetype":"locality"
},
  "geometry": {"coordinates":[120.19788,32.25964],"type":"Point"}
}