{
  "type": "Feature",
  "properties": {
    "gn:admin1_code":"11.0",
    "gn:asciiname":"Yangquewan",
    "gn:country_code":"CN",
    "gn:dem":31,
    "gn:feature_class":"P",
    "gn:feature_code":"PPL",
    "gn:name":"Yangquewan",
    "gn:population":0,
    "gn:timezone":"Asia/Shanghai",
    "iso:country":"CN",
    "name:zho_x_preferred":[
        "\u6768\u96c0\u6e7e"
    ],
    "wof:name":"Yangquewan",
    "wof:placetype":"locality"
},
  "geometry": {"coordinates":[112.67162999999999,28.49451],"type":"Point"}
}