{
  "type": "Feature",
  "properties": {
    "gn:admin1_code":"19.0",
    "gn:asciiname":"Xiabaili Yingzi",
    "gn:country_code":"CN",
    "gn:dem":231,
    "gn:feature_class":"P",
    "gn:feature_code":"PPL",
    "gn:name":"Xiabaili Yingzi",
    "gn:population":0,
    "gn:timezone":"Asia/Shanghai",
    "iso:country":"CN",
    "name:zho_x_preferred":[
        "\u4e0b\u767d\u91cc\u8425\u5b50"
    ],
    "wof:name":"Xiabaili Yingzi",
    "wof:placetype":"locality"
},
  "geometry": {"coordinates":[121.12379,41.89089],"type":"Point"}
}