{
  "type": "Feature",
  "properties": {
    "gn:admin1_code":"2.0",
    "gn:asciiname":"Yingjiawu",
    "gn:country_code":"CN",
    "gn:dem":144,
    "gn:feature_class":"P",
    "gn:feature_code":"PPL",
    "gn:name":"Yingjiawu",
    "gn:population":0,
    "gn:timezone":"Asia/Shanghai",
    "iso:country":"CN",
    "name:zho_x_preferred":[
        "\u5e94\u5bb6\u575e"
    ],
    "wof:name":"Yingjiawu",
    "wof:placetype":"locality"
},
  "geometry": {"coordinates":[120.03939,29.96895],"type":"Point"}
}