{
  "type": "Feature",
  "properties": {
    "gn:admin1_code":"32.0",
    "gn:asciiname":"Fanrong",
    "gn:country_code":"CN",
    "gn:dem":801,
    "gn:feature_class":"P",
    "gn:feature_code":"PPL",
    "gn:name":"Fanrong",
    "gn:population":0,
    "gn:timezone":"Asia/Shanghai",
    "iso:country":"CN",
    "name:zho_x_preferred":[
        "\u7e41\u8363"
    ],
    "wof:name":"Fanrong",
    "wof:placetype":"locality"
},
  "geometry": {"coordinates":[105.371,32.0965],"type":"Point"}
}