{
  "type": "Feature",
  "properties": {
    "gn:admin1_code":"3.0",
    "gn:asciiname":"Diaolingxia",
    "gn:country_code":"CN",
    "gn:dem":181,
    "gn:feature_class":"P",
    "gn:feature_code":"PPL",
    "gn:name":"Diaolingxia",
    "gn:population":0,
    "gn:timezone":"Asia/Shanghai",
    "iso:country":"CN",
    "name:und_x_variant":[
        "\u540a\u5cad\u4e0b"
    ],
    "wof:name":"Diaolingxia",
    "wof:placetype":"locality"
},
  "geometry": {"coordinates":[115.33986000000002,26.41728],"type":"Point"}
}