{
  "type": "Feature",
  "properties": {
    "gn:admin1_code":"11.0",
    "gn:asciiname":"Xinguang",
    "gn:country_code":"CN",
    "gn:dem":583,
    "gn:feature_class":"P",
    "gn:feature_code":"PPL",
    "gn:name":"Xinguang",
    "gn:population":0,
    "gn:timezone":"Asia/Shanghai",
    "iso:country":"CN",
    "name:zho_x_preferred":[
        "\u65b0\u5149"
    ],
    "wof:name":"Xinguang",
    "wof:placetype":"locality"
},
  "geometry": {"coordinates":[109.48224999999999,28.03399000000001],"type":"Point"}
}