{
  "type": "Feature",
  "properties": {
    "gn:admin1_code":"16.0",
    "gn:asciiname":"Wangtiantang",
    "gn:country_code":"CN",
    "gn:dem":105,
    "gn:feature_class":"P",
    "gn:feature_code":"PPL",
    "gn:name":"Wangtiantang",
    "gn:population":0,
    "gn:timezone":"Asia/Shanghai",
    "iso:country":"CN",
    "name:zho_x_preferred":[
        "\u671b\u5929\u5858"
    ],
    "wof:name":"Wangtiantang",
    "wof:placetype":"locality"
},
  "geometry": {"coordinates":[110.343,22.6819],"type":"Point"}
}