{
  "type": "Feature",
  "properties": {
    "gn:admin1_code":"32.0",
    "gn:asciiname":"Waguluo",
    "gn:country_code":"CN",
    "gn:dem":1507,
    "gn:feature_class":"P",
    "gn:feature_code":"PPL",
    "gn:name":"Waguluo",
    "gn:population":0,
    "gn:timezone":"Asia/Shanghai",
    "iso:country":"CN",
    "name:zho_x_preferred":[
        "\u5a03\u59d1\u6d1b"
    ],
    "wof:name":"Waguluo",
    "wof:placetype":"locality"
},
  "geometry": {"coordinates":[102.80800000000001,29.2199],"type":"Point"}
}