{
  "type": "Feature",
  "properties": {
    "gn:admin1_code":"32.0",
    "gn:asciiname":"Yiwu",
    "gn:country_code":"CN",
    "gn:dem":2160,
    "gn:feature_class":"P",
    "gn:feature_code":"PPL",
    "gn:name":"Yiwu",
    "gn:population":0,
    "gn:timezone":"Asia/Shanghai",
    "iso:country":"CN",
    "name:zho_x_preferred":[
        "\u4f9d\u4f0d"
    ],
    "wof:name":"Yiwu",
    "wof:placetype":"locality"
},
  "geometry": {"coordinates":[103.24299999999999,27.8139],"type":"Point"}
}