{
  "type": "Feature",
  "properties": {
    "gn:admin1_code":"1.0",
    "gn:asciiname":"Yaowan",
    "gn:country_code":"CN",
    "gn:dem":122,
    "gn:feature_class":"P",
    "gn:feature_code":"PPL",
    "gn:name":"Yaowan",
    "gn:population":0,
    "gn:timezone":"Asia/Shanghai",
    "iso:country":"CN",
    "name:und_x_variant":[
        "\u7a91\u6e7e"
    ],
    "name:zho_x_preferred":[
        "Yaowan"
    ],
    "wof:name":"Yaowan",
    "wof:placetype":"locality"
},
  "geometry": {"coordinates":[119.02545000000001,30.58512],"type":"Point"}
}