{
  "type": "Feature",
  "properties": {
    "gn:admin1_code":"31.0",
    "gn:asciiname":"Fupo",
    "gn:country_code":"CN",
    "gn:dem":56,
    "gn:feature_class":"P",
    "gn:feature_code":"PPL",
    "gn:name":"Fupo",
    "gn:population":0,
    "gn:timezone":"Asia/Shanghai",
    "iso:country":"CN",
    "name:zho_x_preferred":[
        "Fupo"
    ],
    "name:zho_x_variant":[
        "\u798f\u5761"
    ],
    "wof:name":"Fupo",
    "wof:placetype":"locality"
},
  "geometry": {"coordinates":[110.53864,19.75441],"type":"Point"}
}