{
  "type": "Feature",
  "properties": {
    "gn:admin1_code":"19.0",
    "gn:asciiname":"Huangxiandong",
    "gn:country_code":"CN",
    "gn:dem":242,
    "gn:feature_class":"P",
    "gn:feature_code":"PPL",
    "gn:name":"Huangxiandong",
    "gn:population":0,
    "gn:timezone":"Asia/Shanghai",
    "iso:country":"CN",
    "name:und_x_variant":[
        "\u9ec4\u4ed9\u6d1e"
    ],
    "wof:name":"Huangxiandong",
    "wof:placetype":"locality"
},
  "geometry": {"coordinates":[122.28100000000001,40.0045],"type":"Point"}
}