{
  "type": "Feature",
  "properties": {
    "gn:admin1_code":"19.0",
    "gn:asciiname":"Xiasanjia",
    "gn:country_code":"CN",
    "gn:dem":364,
    "gn:feature_class":"P",
    "gn:feature_code":"PPL",
    "gn:name":"Xiasanjia",
    "gn:population":0,
    "gn:timezone":"Asia/Shanghai",
    "iso:country":"CN",
    "name:zho_x_preferred":[
        "\u4e0b\u4e09\u5bb6"
    ],
    "wof:name":"Xiasanjia",
    "wof:placetype":"locality"
},
  "geometry": {"coordinates":[119.81699999999999,41.39149000000001],"type":"Point"}
}