{
  "type": "Feature",
  "properties": {
    "gn:admin1_code":"3.0",
    "gn:asciiname":"Bajiao",
    "gn:country_code":"CN",
    "gn:dem":243,
    "gn:feature_class":"P",
    "gn:feature_code":"PPL",
    "gn:name":"Bajiao",
    "gn:population":0,
    "gn:timezone":"Asia/Shanghai",
    "iso:country":"CN",
    "name:und_x_variant":[
        "\u82ad\u8549"
    ],
    "wof:name":"Bajiao",
    "wof:placetype":"locality"
},
  "geometry": {"coordinates":[114.92824,29.05153],"type":"Point"}
}