{
  "type": "Feature",
  "properties": {
    "gn:admin1_code":"10",
    "gn:asciiname":"Baozhugoumen",
    "gn:country_code":"CN",
    "gn:dem":352,
    "gn:feature_class":"P",
    "gn:feature_code":"PPL",
    "gn:name":"Baozhugoumen",
    "gn:population":0,
    "gn:timezone":"Asia/Shanghai",
    "iso:country":"CN",
    "name:zho_x_preferred":[
        "\u7206\u7af9\u6c9f\u95e8"
    ],
    "wof:name":"Baozhugoumen",
    "wof:placetype":"locality"
},
  "geometry": {"coordinates":[118.02630000000001,40.77767],"type":"Point"}
}