{
  "type": "Feature",
  "properties": {
    "gn:admin1_code":"21.0",
    "gn:asciiname":"Zhoutacun",
    "gn:country_code":"CN",
    "gn:dem":1187,
    "gn:feature_class":"P",
    "gn:feature_code":"PPL",
    "gn:name":"Zhoutacun",
    "gn:population":0,
    "gn:timezone":"Asia/Shanghai",
    "iso:country":"CN",
    "name:zho_x_preferred":[
        "\u821f\u5854\u6751"
    ],
    "wof:name":"Zhoutacun",
    "wof:placetype":"locality"
},
  "geometry": {"coordinates":[105.63500000000001,37.4827],"type":"Point"}
}