{
  "type": "Feature",
  "properties": {
    "gn:admin1_code":"02",
    "gn:asciiname":"Huzhuangcun",
    "gn:country_code":"CN",
    "gn:dem":331,
    "gn:feature_class":"P",
    "gn:feature_code":"PPL",
    "gn:name":"Huzhuangcun",
    "gn:population":0,
    "gn:timezone":"Asia/Shanghai",
    "iso:country":"CN",
    "name:und_x_variant":[
        "Hu-chuang",
        "Huzhuang",
        "Huzhuangcun"
    ],
    "name:zho_x_preferred":[
        "\u80e1\u5e84"
    ],
    "name:zho_x_variant":[
        "\u80e1\u5e84\u6751"
    ],
    "wof:name":"Huzhuangcun",
    "wof:placetype":"locality"
},
  "geometry": {"coordinates":[120.36013,28.87251],"type":"Point"}
}