{
  "type": "Feature",
  "properties": {
    "gn:admin1_code":"3.0",
    "gn:asciiname":"Ma'ancun",
    "gn:country_code":"CN",
    "gn:dem":74,
    "gn:feature_class":"P",
    "gn:feature_code":"PPL",
    "gn:name":"Ma\u2019ancun",
    "gn:population":0,
    "gn:timezone":"Asia/Shanghai",
    "iso:country":"CN",
    "name:und_x_variant":[
        "Ma\u2019ancun",
        "Ma\u2019anbei"
    ],
    "name:zho_x_preferred":[
        "\u9a6c\u978d\u6751"
    ],
    "name:zho_x_variant":[
        "\u9a6c\u978d\u7891"
    ],
    "wof:name":"Ma'ancun",
    "wof:placetype":"locality"
},
  "geometry": {"coordinates":[117.477,28.4975],"type":"Point"}
}