{
  "type": "Feature",
  "properties": {
    "gn:admin1_code":"22.0",
    "gn:asciiname":"Nianzi Nangou",
    "gn:country_code":"CN",
    "gn:dem":622,
    "gn:feature_class":"P",
    "gn:feature_code":"PPL",
    "gn:name":"Nianzi Nangou",
    "gn:population":0,
    "gn:timezone":"Asia/Shanghai",
    "iso:country":"CN",
    "name:zho_x_preferred":[
        "\u78be\u5b50\u5357\u6c9f"
    ],
    "wof:name":"Nianzi Nangou",
    "wof:placetype":"locality"
},
  "geometry": {"coordinates":[116.50338000000001,40.80613],"type":"Point"}
}