{
  "type": "Feature",
  "properties": {
    "gn:admin1_code":"26.0",
    "gn:asciiname":"Doujiabucun",
    "gn:country_code":"CN",
    "gn:dem":498,
    "gn:feature_class":"P",
    "gn:feature_code":"PPL",
    "gn:name":"Doujiabucun",
    "gn:population":0,
    "gn:timezone":"Asia/Shanghai",
    "iso:country":"CN",
    "name:zho_x_preferred":[
        "\u8c46\u5bb6\u5821\u6751"
    ],
    "wof:name":"Doujiabucun",
    "wof:placetype":"locality"
},
  "geometry": {"coordinates":[107.95064000000001,34.17326],"type":"Point"}
}