{
  "type": "Feature",
  "properties": {
    "gn:admin1_code":"7.0",
    "gn:asciiname":"Changsha",
    "gn:country_code":"CN",
    "gn:dem":11,
    "gn:feature_class":"P",
    "gn:feature_code":"PPL",
    "gn:name":"Changsha",
    "gn:population":0,
    "gn:timezone":"Asia/Shanghai",
    "iso:country":"CN",
    "name:zho_x_preferred":[
        "\u957f\u6c99"
    ],
    "wof:name":"Changsha",
    "wof:placetype":"locality"
},
  "geometry": {"coordinates":[119.62130999999999,26.19522000000001],"type":"Point"}
}