{
  "type": "Feature",
  "properties": {
    "gn:admin1_code":"31.0",
    "gn:asciiname":"Lijia",
    "gn:country_code":"CN",
    "gn:dem":273,
    "gn:feature_class":"P",
    "gn:feature_code":"PPL",
    "gn:name":"Lijia",
    "gn:population":0,
    "gn:timezone":"Asia/Shanghai",
    "iso:country":"CN",
    "name:deu_x_preferred":[
        "Lijia"
    ],
    "name:und_x_variant":[
        "\u91cc\u4f73"
    ],
    "name:zho_x_preferred":[
        "\u91cc\u4f73"
    ],
    "wof:name":"Lijia",
    "wof:placetype":"locality"
},
  "geometry": {"coordinates":[109.8819,19.156],"type":"Point"}
}