{
  "type": "Feature",
  "properties": {
    "gn:admin1_code":"8.0",
    "gn:asciiname":"Chuangangcun",
    "gn:country_code":"CN",
    "gn:dem":166,
    "gn:feature_class":"P",
    "gn:feature_code":"PPL",
    "gn:name":"Chuangangcun",
    "gn:population":0,
    "gn:timezone":"Asia/Shanghai",
    "iso:country":"CN",
    "name:zho_x_preferred":[
        "\u5ddd\u5c97\u6751"
    ],
    "wof:name":"Chuangangcun",
    "wof:placetype":"locality"
},
  "geometry": {"coordinates":[125.97743,46.56813],"type":"Point"}
}