{
  "type": "Feature",
  "properties": {
    "gn:admin1_code":"31.0",
    "gn:asciiname":"Zhiwei",
    "gn:country_code":"CN",
    "gn:dem":164,
    "gn:feature_class":"P",
    "gn:feature_code":"PPL",
    "gn:name":"Zhiwei",
    "gn:population":0,
    "gn:timezone":"Asia/Shanghai",
    "iso:country":"CN",
    "name:zho_x_preferred":[
        "\u53ea\u5fae"
    ],
    "wof:name":"Zhiwei",
    "wof:placetype":"locality"
},
  "geometry": {"coordinates":[109.07733,18.75754],"type":"Point"}
}