{
  "type": "Feature",
  "properties": {
    "gn:admin1_code":"18",
    "gn:asciiname":"Yezhiluo",
    "gn:country_code":"CN",
    "gn:dem":2143,
    "gn:feature_class":"P",
    "gn:feature_code":"PPL",
    "gn:name":"Yezhiluo",
    "gn:population":0,
    "gn:timezone":"Asia/Shanghai",
    "iso:country":"CN",
    "name:zho_x_preferred":[
        "\u91ce\u4e4b\u843d"
    ],
    "wof:name":"Yezhiluo",
    "wof:placetype":"locality"
},
  "geometry": {"coordinates":[103.88,27.2308],"type":"Point"}
}