{
  "type": "Feature",
  "properties": {
    "gn:admin1_code":"9.0",
    "gn:asciiname":"Gunziling",
    "gn:country_code":"CN",
    "gn:dem":523,
    "gn:feature_class":"P",
    "gn:feature_code":"PPL",
    "gn:name":"Gunziling",
    "gn:population":0,
    "gn:timezone":"Asia/Shanghai",
    "iso:country":"CN",
    "name:und_x_variant":[
        "\u6eda\u5b50\u5cad",
        "Gunziling"
    ],
    "wof:name":"Gunziling",
    "wof:placetype":"locality"
},
  "geometry": {"coordinates":[112.17428999999998,33.50293],"type":"Point"}
}