{
  "type": "Feature",
  "properties": {
    "gn:admin1_code":"26.0",
    "gn:asciiname":"Jiangtaisi",
    "gn:country_code":"CN",
    "gn:dem":651,
    "gn:feature_class":"P",
    "gn:feature_code":"PPL",
    "gn:name":"Jiangtaisi",
    "gn:population":0,
    "gn:timezone":"Asia/Shanghai",
    "iso:country":"CN",
    "name:und_x_variant":[
        "\u5c06\u53f0\u5bfa"
    ],
    "wof:name":"Jiangtaisi",
    "wof:placetype":"locality"
},
  "geometry": {"coordinates":[106.58101000000001,33.19609000000001],"type":"Point"}
}