{
  "type": "Feature",
  "properties": {
    "gn:admin1_code":"4.0",
    "gn:asciiname":"Majiashan",
    "gn:country_code":"CN",
    "gn:dem":7,
    "gn:feature_class":"P",
    "gn:feature_code":"PPL",
    "gn:name":"Majiashan",
    "gn:population":0,
    "gn:timezone":"Asia/Shanghai",
    "iso:country":"CN",
    "name:zho_x_preferred":[
        "\u9a6c\u5bb6\u5c71"
    ],
    "wof:name":"Majiashan",
    "wof:placetype":"locality"
},
  "geometry": {"coordinates":[119.49548,32.17432],"type":"Point"}
}