{
  "type": "Feature",
  "properties": {
    "gn:admin1_code":"1.0",
    "gn:asciiname":"Hulaocun",
    "gn:country_code":"CN",
    "gn:dem":41,
    "gn:feature_class":"P",
    "gn:feature_code":"PPL",
    "gn:name":"Hulaocun",
    "gn:population":0,
    "gn:timezone":"Asia/Shanghai",
    "iso:country":"CN",
    "name:und_x_variant":[
        "Hulaozhuang"
    ],
    "name:zho_x_preferred":[
        "\u80e1\u8001\u6751"
    ],
    "wof:name":"Hulaocun",
    "wof:placetype":"locality"
},
  "geometry": {"coordinates":[115.56667,33.575],"type":"Point"}
}