{
  "type": "Feature",
  "properties": {
    "gn:admin1_code":"12.0",
    "gn:asciiname":"Guojialiangzi",
    "gn:country_code":"CN",
    "gn:dem":655,
    "gn:feature_class":"P",
    "gn:feature_code":"PPL",
    "gn:name":"Guojialiangzi",
    "gn:population":0,
    "gn:timezone":"Asia/Shanghai",
    "iso:country":"CN",
    "name:zho_x_preferred":[
        "\u90ed\u5bb6\u6881\u5b50"
    ],
    "wof:name":"Guojialiangzi",
    "wof:placetype":"locality"
},
  "geometry": {"coordinates":[109.99057999999999,32.13927],"type":"Point"}
}