{
  "type": "Feature",
  "properties": {
    "gn:admin1_code":"11.0",
    "gn:asciiname":"Zanzhazhula",
    "gn:country_code":"CN",
    "gn:dem":333,
    "gn:feature_class":"P",
    "gn:feature_code":"PPL",
    "gn:name":"Zanzhazhula",
    "gn:population":0,
    "gn:timezone":"Asia/Shanghai",
    "iso:country":"CN",
    "name:zho_x_preferred":[
        "\u54b1\u69a8\u4e3b\u62c9"
    ],
    "wof:name":"Zanzhazhula",
    "wof:placetype":"locality"
},
  "geometry": {"coordinates":[109.50479,29.01696],"type":"Point"}
}