{
  "type": "Feature",
  "properties": {
    "gn:admin1_code":"25.0",
    "gn:asciiname":"Zhangzhao",
    "gn:country_code":"CN",
    "gn:dem":76,
    "gn:feature_class":"P",
    "gn:feature_code":"PPL",
    "gn:name":"Zhangzhao",
    "gn:population":0,
    "gn:timezone":"Asia/Shanghai",
    "iso:country":"CN",
    "name:zho_x_preferred":[
        "\u5f20\u8d75"
    ],
    "wof:name":"Zhangzhao",
    "wof:placetype":"locality"
},
  "geometry": {"coordinates":[120.71831,37.79775],"type":"Point"}
}