{
  "type": "Feature",
  "properties": {
    "gn:admin1_code":"12.0",
    "gn:asciiname":"Chihukou",
    "gn:country_code":"CN",
    "gn:dem":26,
    "gn:feature_class":"P",
    "gn:feature_code":"PPL",
    "gn:name":"Chihukou",
    "gn:population":0,
    "gn:timezone":"Asia/Shanghai",
    "iso:country":"CN",
    "name:zho_x_preferred":[
        "\u5c3a\u6e56\u53e3"
    ],
    "wof:name":"Chihukou",
    "wof:placetype":"locality"
},
  "geometry": {"coordinates":[113.18283999999998,29.63669],"type":"Point"}
}