{
  "type": "Feature",
  "properties": {
    "gn:admin1_code":"21.0",
    "gn:asciiname":"Zhangjia Xinbuzi",
    "gn:country_code":"CN",
    "gn:dem":1819,
    "gn:feature_class":"P",
    "gn:feature_code":"PPL",
    "gn:name":"Zhangjia Xinbuzi",
    "gn:population":0,
    "gn:timezone":"Asia/Shanghai",
    "iso:country":"CN",
    "name:zho_x_preferred":[
        "\u5f20\u5bb6\u65b0\u5821\u5b50"
    ],
    "wof:name":"Zhangjia Xinbuzi",
    "wof:placetype":"locality"
},
  "geometry": {"coordinates":[105.51922999999999,35.81708],"type":"Point"}
}