{
  "type": "Feature",
  "properties": {
    "gn:admin1_code":"26.0",
    "gn:asciiname":"Bajiaping",
    "gn:country_code":"CN",
    "gn:dem":1614,
    "gn:feature_class":"P",
    "gn:feature_code":"PPL",
    "gn:name":"Bajiaping",
    "gn:population":0,
    "gn:timezone":"Asia/Shanghai",
    "iso:country":"CN",
    "name:und_x_variant":[
        "\u516b\u5bb6\u576a"
    ],
    "wof:name":"Bajiaping",
    "wof:placetype":"locality"
},
  "geometry": {"coordinates":[106.97042,34.0725],"type":"Point"}
}