{
  "type": "Feature",
  "properties": {
    "gn:admin1_code":"3.0",
    "gn:asciiname":"Shanglouxia",
    "gn:country_code":"CN",
    "gn:dem":281,
    "gn:feature_class":"P",
    "gn:feature_code":"PPL",
    "gn:name":"Shanglouxia",
    "gn:population":0,
    "gn:timezone":"Asia/Shanghai",
    "iso:country":"CN",
    "name:und_x_variant":[
        "\u4e0a\u697c\u4e0b"
    ],
    "wof:name":"Shanglouxia",
    "wof:placetype":"locality"
},
  "geometry": {"coordinates":[115.33176,29.12647],"type":"Point"}
}