{
  "type": "Feature",
  "properties": {
    "gn:admin1_code":"8.0",
    "gn:asciiname":"Changlicun",
    "gn:country_code":"CN",
    "gn:dem":181,
    "gn:feature_class":"P",
    "gn:feature_code":"PPL",
    "gn:name":"Changlicun",
    "gn:population":0,
    "gn:timezone":"Asia/Shanghai",
    "iso:country":"CN",
    "name:zho_x_preferred":[
        "\u957f\u5229\u6751"
    ],
    "wof:name":"Changlicun",
    "wof:placetype":"locality"
},
  "geometry": {"coordinates":[125.61481999999999,46.75341],"type":"Point"}
}