{
  "type": "Feature",
  "properties": {
    "gn:admin1_code":"13",
    "gn:asciiname":"Yasidun Linchang",
    "gn:country_code":"CN",
    "gn:dem":1412,
    "gn:feature_class":"P",
    "gn:feature_code":"PPLF",
    "gn:name":"Yasidun Linchang",
    "gn:population":0,
    "gn:timezone":"Asia/Shanghai",
    "iso:country":"CN",
    "name:und_x_variant":[
        "\u4e9a\u65af\u58a9\u6797\u573a"
    ],
    "wof:name":"Yasidun Linchang",
    "wof:placetype":"locality"
},
  "geometry": {"coordinates":[76.95933000000002,38.02632],"type":"Point"}
}