{
  "type": "Feature",
  "properties": {
    "gn:admin1_code":"12.0",
    "gn:asciiname":"Xiangtangwan",
    "gn:country_code":"CN",
    "gn:dem":27,
    "gn:feature_class":"P",
    "gn:feature_code":"PPL",
    "gn:name":"Xiangtangwan",
    "gn:population":0,
    "gn:timezone":"Asia/Shanghai",
    "iso:country":"CN",
    "name:und_x_variant":[
        "\u5411\u5858\u5846"
    ],
    "wof:name":"Xiangtangwan",
    "wof:placetype":"locality"
},
  "geometry": {"coordinates":[114.08105999999999,30.3596],"type":"Point"}
}