{
  "type": "Feature",
  "properties": {
    "gn:admin1_code":"29.0",
    "gn:asciiname":"Tengjiacun",
    "gn:country_code":"CN",
    "gn:dem":1718,
    "gn:feature_class":"P",
    "gn:feature_code":"PPL",
    "gn:name":"Tengjiacun",
    "gn:population":0,
    "gn:timezone":"Asia/Shanghai",
    "iso:country":"CN",
    "name:zho_x_preferred":[
        "\u6ed5\u5bb6\u6751"
    ],
    "wof:name":"Tengjiacun",
    "wof:placetype":"locality"
},
  "geometry": {"coordinates":[104.461,26.2104],"type":"Point"}
}