{
  "type": "Feature",
  "properties": {
    "gn:admin1_code":"29.0",
    "gn:asciiname":"Laoyuzhai",
    "gn:country_code":"CN",
    "gn:dem":1352,
    "gn:feature_class":"P",
    "gn:feature_code":"PPL",
    "gn:name":"Laoyuzhai",
    "gn:population":0,
    "gn:timezone":"Asia/Shanghai",
    "iso:country":"CN",
    "name:zho_x_preferred":[
        "\u8001\u4f59\u5be8"
    ],
    "wof:name":"Laoyuzhai",
    "wof:placetype":"locality"
},
  "geometry": {"coordinates":[101.10899999999999,22.756],"type":"Point"}
}