{
  "type": "Feature",
  "properties": {
    "gn:admin1_code":"10",
    "gn:asciiname":"Beibimeng",
    "gn:cc2":"CN",
    "gn:country_code":"CN",
    "gn:dem":6,
    "gn:feature_class":"P",
    "gn:feature_code":"PPL",
    "gn:name":"Beibimeng",
    "gn:population":0,
    "gn:timezone":"Asia/Shanghai",
    "iso:country":"CN",
    "name:und_x_variant":[
        "Pi-meng-chen",
        "Pei-pi-meng",
        "Beibimeng"
    ],
    "wof:name":"Beibimeng",
    "wof:placetype":"locality"
},
  "geometry": {"coordinates":[117.16667,38.25],"type":"Point"}
}