{
  "type": "Feature",
  "properties": {
    "gn:admin1_code":"3.0",
    "gn:asciiname":"Fenghuangzhou",
    "gn:country_code":"CN",
    "gn:dem":213,
    "gn:feature_class":"P",
    "gn:feature_code":"PPL",
    "gn:name":"Fenghuangzhou",
    "gn:population":0,
    "gn:timezone":"Asia/Shanghai",
    "iso:country":"CN",
    "name:und_x_variant":[
        "\u51e4\u51f0\u6d32"
    ],
    "wof:name":"Fenghuangzhou",
    "wof:placetype":"locality"
},
  "geometry": {"coordinates":[114.37157999999999,28.35119000000001],"type":"Point"}
}