{
  "type": "Feature",
  "properties": {
    "gn:admin1_code":"30",
    "gn:asciiname":"Lanshan",
    "gn:country_code":"CN",
    "gn:dem":49,
    "gn:feature_class":"P",
    "gn:feature_code":"PPL",
    "gn:name":"Lanshan",
    "gn:population":0,
    "gn:timezone":"Asia/Urumqi",
    "iso:country":"CN",
    "name:zho_x_preferred":[
        "\u5170\u5c71"
    ],
    "wof:name":"Lanshan",
    "wof:placetype":"locality"
},
  "geometry": {"coordinates":[110.37478,21.83621],"type":"Point"}
}