{
  "type": "Feature",
  "properties": {
    "gn:admin1_code":"30",
    "gn:asciiname":"Lanshan",
    "gn:country_code":"CN",
    "gn:dem":49,
    "gn:feature_class":"P",
    "gn:feature_code":"PPL",
    "gn:name":"Lanshan",
    "gn:population":0,
    "gn:timezone":"Asia/Urumqi",
    "iso:country":"CN",
    "name:ceb_x_preferred":[
        "Lanshan"
    ],
    "name:deu_x_preferred":[
        "Lanshan"
    ],
    "name:fra_x_preferred":[
        "Lanshan"
    ],
    "name:nor_x_preferred":[
        "Lanshan"
    ],
    "name:rus_x_preferred":[
        "\u041b\u0430\u043d\u044c\u0448\u0430\u043d\u044c"
    ],
    "name:swe_x_preferred":[
        "Lanshan"
    ],
    "name:zho_x_preferred":[
        "\u5170\u5c71"
    ],
    "wof:name":"Lanshan",
    "wof:placetype":"locality"
},
  "geometry": {"coordinates":[110.37478,21.83621],"type":"Point"}
}