{
  "type": "Feature",
  "properties": {
    "gn:admin1_code":"9",
    "gn:asciiname":"Shifulou",
    "gn:country_code":"CN",
    "gn:dem":48,
    "gn:feature_class":"P",
    "gn:feature_code":"PPL",
    "gn:name":"Shifulou",
    "gn:population":0,
    "gn:timezone":"Asia/Shanghai",
    "iso:country":"CN",
    "name:zho_x_preferred":[
        "\u5341\u4ed8\u697c"
    ],
    "wof:name":"Shifulou",
    "wof:placetype":"locality"
},
  "geometry": {"coordinates":[115.56100000000001,34.1387],"type":"Point"}
}