{
  "type": "Feature",
  "properties": {
    "gn:admin1_code":"11.0",
    "gn:asciiname":"Eryashang",
    "gn:country_code":"CN",
    "gn:dem":572,
    "gn:feature_class":"P",
    "gn:feature_code":"PPL",
    "gn:name":"Eryashang",
    "gn:population":0,
    "gn:timezone":"Asia/Shanghai",
    "iso:country":"CN",
    "name:zho_x_preferred":[
        "\u4e8c\u57ad\u4e0a"
    ],
    "wof:name":"Eryashang",
    "wof:placetype":"locality"
},
  "geometry": {"coordinates":[109.66818000000001,29.34575],"type":"Point"}
}