{
  "type": "Feature",
  "properties": {
    "gn:admin1_code":"11",
    "gn:asciiname":"Chengkang",
    "gn:country_code":"CN",
    "gn:dem":1262,
    "gn:feature_class":"P",
    "gn:feature_code":"PPL",
    "gn:name":"Chengkang",
    "gn:population":0,
    "gn:timezone":"Asia/Shanghai",
    "iso:country":"CN",
    "wof:name":"Chengkang",
    "wof:placetype":"locality"
},
  "geometry": {"coordinates":[113.61194,25.88444],"type":"Point"}
}