{
  "type": "Feature",
  "properties": {
    "gn:admin1_code":"24.0",
    "gn:asciiname":"Lianzhuang",
    "gn:country_code":"CN",
    "gn:dem":1333,
    "gn:feature_class":"P",
    "gn:feature_code":"PPL",
    "gn:name":"Lianzhuang",
    "gn:population":0,
    "gn:timezone":"Asia/Shanghai",
    "iso:country":"CN",
    "name:zho_x_preferred":[
        "\u8fde\u5e84"
    ],
    "wof:name":"Lianzhuang",
    "wof:placetype":"locality"
},
  "geometry": {"coordinates":[113.15624,37.09226],"type":"Point"}
}