{
  "type": "Feature",
  "properties": {
    "gn:admin1_code":"32.0",
    "gn:asciiname":"Boluo",
    "gn:country_code":"CN",
    "gn:dem":2824,
    "gn:feature_class":"P",
    "gn:feature_code":"PPL",
    "gn:name":"Boluo",
    "gn:population":0,
    "gn:timezone":"Asia/Shanghai",
    "iso:country":"CN",
    "name:zho_x_preferred":[
        "\u6ce2\u6d1b"
    ],
    "wof:name":"Boluo",
    "wof:placetype":"locality"
},
  "geometry": {"coordinates":[102.74133999999999,28.28944000000001],"type":"Point"}
}