{
  "type": "Feature",
  "properties": {
    "gn:admin1_code":"32.0",
    "gn:asciiname":"Weiganba",
    "gn:country_code":"CN",
    "gn:dem":528,
    "gn:feature_class":"P",
    "gn:feature_code":"PPL",
    "gn:name":"Weiganba",
    "gn:population":0,
    "gn:timezone":"Asia/Shanghai",
    "iso:country":"CN",
    "name:zho_x_preferred":[
        "\u6845\u6746\u575d"
    ],
    "wof:name":"Weiganba",
    "wof:placetype":"locality"
},
  "geometry": {"coordinates":[104.26300000000001,29.6418],"type":"Point"}
}