{
  "type": "Feature",
  "properties": {
    "gn:admin1_code":"31.0",
    "gn:asciiname":"Shihao",
    "gn:country_code":"CN",
    "gn:dem":97,
    "gn:feature_class":"P",
    "gn:feature_code":"PPL",
    "gn:name":"Shihao",
    "gn:population":0,
    "gn:timezone":"Asia/Shanghai",
    "iso:country":"CN",
    "name:und_x_variant":[
        "\u4ec0\u597d"
    ],
    "wof:name":"Shihao",
    "wof:placetype":"locality"
},
  "geometry": {"coordinates":[109.64894,18.66847000000001],"type":"Point"}
}