{
  "type": "Feature",
  "properties": {
    "gn:admin1_code":"33.0",
    "gn:asciiname":"Fujia Laofangzi",
    "gn:country_code":"CN",
    "gn:dem":1508,
    "gn:feature_class":"P",
    "gn:feature_code":"PPL",
    "gn:name":"Fujia Laofangzi",
    "gn:population":0,
    "gn:timezone":"Asia/Shanghai",
    "iso:country":"CN",
    "name:zho_x_preferred":[
        "\u4ed8\u5bb6\u8001\u623f\u5b50"
    ],
    "wof:name":"Fujia Laofangzi",
    "wof:placetype":"locality"
},
  "geometry": {"coordinates":[108.50941,32.15506],"type":"Point"}
}