{
  "type": "Feature",
  "properties": {
    "gn:admin1_code":"11",
    "gn:asciiname":"Lashujiao",
    "gn:country_code":"CN",
    "gn:dem":468,
    "gn:feature_class":"P",
    "gn:feature_code":"PPL",
    "gn:name":"Lashujiao",
    "gn:population":0,
    "gn:timezone":"Asia/Shanghai",
    "iso:country":"CN",
    "name:und_x_variant":[
        "\u814a\u6811\u811a",
        "Lashujiao"
    ],
    "wof:name":"Lashujiao",
    "wof:placetype":"locality"
},
  "geometry": {"coordinates":[111.95528,25.44972000000001],"type":"Point"}
}