{
  "type": "Feature",
  "properties": {
    "gn:admin1_code":"18",
    "gn:asciiname":"Zhanggouwan",
    "gn:country_code":"CN",
    "gn:dem":1055,
    "gn:feature_class":"P",
    "gn:feature_code":"PPL",
    "gn:name":"Zhanggouwan",
    "gn:population":0,
    "gn:timezone":"Asia/Shanghai",
    "iso:country":"CN",
    "name:zho_x_preferred":[
        "\u5f20\u6c9f\u6e7e"
    ],
    "wof:name":"Zhanggouwan",
    "wof:placetype":"locality"
},
  "geometry": {"coordinates":[106.78100000000001,27.6249],"type":"Point"}
}