{
  "type": "Feature",
  "properties": {
    "gn:admin1_code":"2.0",
    "gn:asciiname":"Changbang",
    "gn:country_code":"CN",
    "gn:dem":4,
    "gn:feature_class":"P",
    "gn:feature_code":"PPL",
    "gn:name":"Changbang",
    "gn:population":0,
    "gn:timezone":"Asia/Shanghai",
    "iso:country":"CN",
    "name:und_x_variant":[
        "\u957f\u6d5c"
    ],
    "wof:name":"Changbang",
    "wof:placetype":"locality"
},
  "geometry": {"coordinates":[120.91280999999999,30.92562],"type":"Point"}
}