{
  "type": "Feature",
  "properties": {
    "gn:admin1_code":"08",
    "gn:asciiname":"Xigangzi",
    "gn:country_code":"CN",
    "gn:dem":157,
    "gn:feature_class":"P",
    "gn:feature_code":"PPLA4",
    "gn:name":"Xigangzi",
    "gn:population":0,
    "gn:timezone":"Asia/Shanghai",
    "iso:country":"CN",
    "name:eng_x_preferred":[
        "Xigangzi"
    ],
    "name:rus_x_preferred":[
        "\u0421\u0438\u0433\u0430\u043d\u0446\u0437\u044b"
    ],
    "name:und_x_variant":[
        "Hsi-kang-tzu",
        "Xigangzi Zhen"
    ],
    "name:zho_x_preferred":[
        "\u897f\u5c97\u5b50"
    ],
    "name:zho_x_variant":[
        "\u897f\u5c97\u5b50\u9547"
    ],
    "wof:name":"Xigangzi",
    "wof:placetype":"locality"
},
  "geometry": {"coordinates":[127.33874,49.8966],"type":"Point"}
}