{
  "type": "Feature",
  "properties": {
    "gn:admin1_code":"20",
    "gn:asciiname":"Shanghulin",
    "gn:country_code":"CN",
    "gn:dem":624,
    "gn:feature_class":"P",
    "gn:feature_code":"PPL",
    "gn:name":"Shanghulin",
    "gn:population":0,
    "gn:timezone":"Asia/Shanghai",
    "iso:country":"CN",
    "name:eng_x_preferred":[
        "Shanghulin"
    ],
    "name:rus_x_preferred":[
        "\u0428\u0430\u043d\u043b\u0443\u043b\u0438\u043d\u044c"
    ],
    "name:zho_x_preferred":[
        "\u4e0a\u62a4\u6797"
    ],
    "wof:name":"Shanghulin",
    "wof:placetype":"locality"
},
  "geometry": {"coordinates":[120.25409000000001,50.67591],"type":"Point"}
}