{
  "type": "Feature",
  "properties": {
    "gn:admin1_code":"12.0",
    "gn:asciiname":"Daxuechang",
    "gn:country_code":"CN",
    "gn:dem":884,
    "gn:feature_class":"P",
    "gn:feature_code":"PPL",
    "gn:name":"Daxuechang",
    "gn:population":0,
    "gn:timezone":"Asia/Shanghai",
    "iso:country":"CN",
    "name:zho_x_preferred":[
        "Daxuechang"
    ],
    "name:zho_x_variant":[
        "\u5927\u96ea\u573a"
    ],
    "wof:name":"Daxuechang",
    "wof:placetype":"locality"
},
  "geometry": {"coordinates":[109.64255,29.75959000000001],"type":"Point"}
}