{
  "type": "Feature",
  "properties": {
    "gn:admin1_code":"33.0",
    "gn:asciiname":"Shuibiaoxi",
    "gn:country_code":"CN",
    "gn:dem":506,
    "gn:feature_class":"P",
    "gn:feature_code":"PPL",
    "gn:name":"Shuibiaoxi",
    "gn:population":0,
    "gn:timezone":"Asia/Shanghai",
    "iso:country":"CN",
    "name:zho_x_preferred":[
        "\u6c34\u6807\u6eaa"
    ],
    "wof:name":"Shuibiaoxi",
    "wof:placetype":"locality"
},
  "geometry": {"coordinates":[108.89515,28.58273],"type":"Point"}
}