{
  "type": "Feature",
  "properties": {
    "gn:admin1_code":"10.0",
    "gn:asciiname":"Aoyukou",
    "gn:country_code":"CN",
    "gn:dem":1111,
    "gn:feature_class":"P",
    "gn:feature_code":"PPL",
    "gn:name":"Aoyukou",
    "gn:population":0,
    "gn:timezone":"Asia/Shanghai",
    "iso:country":"CN",
    "name:zho_x_preferred":[
        "\u9ccc\u9c7c\u53e3"
    ],
    "wof:name":"Aoyukou",
    "wof:placetype":"locality"
},
  "geometry": {"coordinates":[114.39802,40.19096],"type":"Point"}
}