{
  "type": "Feature",
  "properties": {
    "gn:admin1_code":"16.0",
    "gn:asciiname":"Pingsancun",
    "gn:country_code":"CN",
    "gn:dem":403,
    "gn:feature_class":"P",
    "gn:feature_code":"PPL",
    "gn:name":"Pingsancun",
    "gn:population":0,
    "gn:timezone":"Asia/Shanghai",
    "iso:country":"CN",
    "name:zho_x_preferred":[
        "\u5e73\u4e09\u6751"
    ],
    "wof:name":"Pingsancun",
    "wof:placetype":"locality"
},
  "geometry": {"coordinates":[106.515,23.8002],"type":"Point"}
}