{
  "type": "Feature",
  "properties": {
    "gn:admin1_code":"4.0",
    "gn:asciiname":"Fanzhuangcun",
    "gn:country_code":"CN",
    "gn:dem":40,
    "gn:feature_class":"P",
    "gn:feature_code":"PPL",
    "gn:name":"Fanzhuangcun",
    "gn:population":0,
    "gn:timezone":"Asia/Shanghai",
    "iso:country":"CN",
    "name:zho_x_preferred":[
        "\u8303\u5e84\u6751"
    ],
    "wof:name":"Fanzhuangcun",
    "wof:placetype":"locality"
},
  "geometry": {"coordinates":[116.63769000000001,34.71173],"type":"Point"}
}