{
  "type": "Feature",
  "properties": {
    "gn:admin1_code":"14.0",
    "gn:asciiname":"Gula",
    "gn:country_code":"CN",
    "gn:dem":4004,
    "gn:feature_class":"P",
    "gn:feature_code":"PPL",
    "gn:name":"Gula",
    "gn:population":0,
    "gn:timezone":"Asia/Urumqi",
    "iso:country":"CN",
    "name:ara_x_preferred":[
        "\u063a\u0648\u0644\u0627"
    ],
    "name:ceb_x_preferred":[
        "Gula"
    ],
    "name:deu_x_preferred":[
        "Gula"
    ],
    "name:fra_x_preferred":[
        "Gula"
    ],
    "name:ita_x_preferred":[
        "Gula"
    ],
    "name:pol_x_preferred":[
        "Gula"
    ],
    "name:por_x_preferred":[
        "Gula"
    ],
    "name:slk_x_preferred":[
        "Gula"
    ],
    "name:swe_x_preferred":[
        "Gula"
    ],
    "name:zho_x_preferred":[
        "\u53e4\u62c9"
    ],
    "wof:name":"Gula",
    "wof:placetype":"locality"
},
  "geometry": {"coordinates":[95.72384,30.84004],"type":"Point"}
}