{
  "type": "Feature",
  "properties": {
    "gn:admin1_code":"9.0",
    "gn:asciiname":"Liangjia",
    "gn:country_code":"CN",
    "gn:dem":212,
    "gn:feature_class":"P",
    "gn:feature_code":"PPL",
    "gn:name":"Liangjia",
    "gn:population":0,
    "gn:timezone":"Asia/Shanghai",
    "iso:country":"CN",
    "name:zho_x_preferred":[
        "\u6881\u5bb6"
    ],
    "name:zho_x_variant":[
        "\u6881\u5bb6\u9547"
    ],
    "wof:name":"Liangjia",
    "wof:placetype":"locality"
},
  "geometry": {"coordinates":[113.25727999999999,33.8094],"type":"Point"}
}