{
  "type": "Feature",
  "properties": {
    "gn:admin1_code":"07",
    "gn:asciiname":"Changbianxi",
    "gn:country_code":"CN",
    "gn:dem":189,
    "gn:feature_class":"P",
    "gn:feature_code":"PPL",
    "gn:name":"Changbianxi",
    "gn:population":0,
    "gn:timezone":"Asia/Shanghai",
    "iso:country":"CN",
    "name:zho_x_preferred":[
        "\u957f\u8fb9\u6eaa"
    ],
    "wof:name":"Changbianxi",
    "wof:placetype":"locality"
},
  "geometry": {"coordinates":[118.24393999999999,25.28342],"type":"Point"}
}