{
  "type": "Feature",
  "properties": {
    "gn:admin1_code":"14.0",
    "gn:asciiname":"Shuoma",
    "gn:country_code":"CN",
    "gn:dem":3629,
    "gn:feature_class":"P",
    "gn:feature_code":"PPL",
    "gn:name":"Shuoma",
    "gn:population":0,
    "gn:timezone":"Asia/Urumqi",
    "iso:country":"CN",
    "name:zho_x_preferred":[
        "\u8bf4\u5988"
    ],
    "wof:name":"Shuoma",
    "wof:placetype":"locality"
},
  "geometry": {"coordinates":[95.50689,30.87798],"type":"Point"}
}