{
  "type": "Feature",
  "properties": {
    "gn:admin1_code":"12.0",
    "gn:asciiname":"Weirixin",
    "gn:country_code":"CN",
    "gn:dem":69,
    "gn:feature_class":"P",
    "gn:feature_code":"PPL",
    "gn:name":"Weirixin",
    "gn:population":0,
    "gn:timezone":"Asia/Shanghai",
    "iso:country":"CN",
    "name:zho_x_preferred":[
        "Weirixin"
    ],
    "name:zho_x_variant":[
        "\u536b\u65e5\u65b0"
    ],
    "wof:name":"Weirixin",
    "wof:placetype":"locality"
},
  "geometry": {"coordinates":[114.9242,29.89175],"type":"Point"}
}