{
  "type": "Feature",
  "properties": {
    "gn:admin1_code":"11.0",
    "gn:asciiname":"Shazi'ao",
    "gn:country_code":"CN",
    "gn:dem":466,
    "gn:feature_class":"P",
    "gn:feature_code":"PPL",
    "gn:name":"Shazi\u2019ao",
    "gn:population":0,
    "gn:timezone":"Asia/Shanghai",
    "iso:country":"CN",
    "name:zho_x_preferred":[
        "\u6c99\u5b50\u5773"
    ],
    "name:zho_x_variant":[
        "Shazi\u2019ao"
    ],
    "wof:name":"Shazi'ao",
    "wof:placetype":"locality"
},
  "geometry": {"coordinates":[109.93998000000001,29.15429],"type":"Point"}
}