{
  "type": "Feature",
  "properties": {
    "gn:admin1_code":"16.0",
    "gn:asciiname":"Nengshou",
    "gn:country_code":"CN",
    "gn:dem":577,
    "gn:feature_class":"P",
    "gn:feature_code":"PPL",
    "gn:name":"Nengshou",
    "gn:population":0,
    "gn:timezone":"Asia/Shanghai",
    "iso:country":"CN",
    "name:zho_x_preferred":[
        "\u80fd\u9996"
    ],
    "wof:name":"Nengshou",
    "wof:placetype":"locality"
},
  "geometry": {"coordinates":[106.488,22.9873],"type":"Point"}
}