{
  "type": "Feature",
  "properties": {
    "gn:admin1_code":"7.0",
    "gn:asciiname":"Panfu",
    "gn:country_code":"CN",
    "gn:dem":244,
    "gn:feature_class":"P",
    "gn:feature_code":"PPL",
    "gn:name":"Panfu",
    "gn:population":0,
    "gn:timezone":"Asia/Shanghai",
    "iso:country":"CN",
    "name:ara_x_preferred":[
        "\u0628\u0627\u0646\u0641\u0648"
    ],
    "name:deu_x_preferred":[
        "Panfu"
    ],
    "name:fin_x_preferred":[
        "Panfu"
    ],
    "name:fra_x_preferred":[
        "Panfu"
    ],
    "name:pol_x_preferred":[
        "Panfu"
    ],
    "name:swe_x_preferred":[
        "Panfu"
    ],
    "name:tur_x_preferred":[
        "Panfu"
    ],
    "name:zho_x_preferred":[
        "\u76d8\u5bcc"
    ],
    "wof:name":"Panfu",
    "wof:placetype":"locality"
},
  "geometry": {"coordinates":[118.77104,25.70151],"type":"Point"}
}