{
  "type": "Feature",
  "properties": {
    "gn:admin1_code":"25",
    "gn:asciiname":"Hetaoli",
    "gn:country_code":"CN",
    "gn:dem":14,
    "gn:feature_class":"P",
    "gn:feature_code":"PPL",
    "gn:name":"Hetaoli",
    "gn:population":0,
    "gn:timezone":"Asia/Shanghai",
    "iso:country":"CN",
    "name:zho_x_preferred":[
        "\u6cb3\u5957\u674e"
    ],
    "wof:name":"Hetaoli",
    "wof:placetype":"locality"
},
  "geometry": {"coordinates":[118.20999999999999,37.4076],"type":"Point"}
}