{
  "type": "Feature",
  "properties": {
    "gn:admin1_code":"18",
    "gn:asciiname":"Laohuangtian",
    "gn:country_code":"CN",
    "gn:dem":345,
    "gn:feature_class":"P",
    "gn:feature_code":"PPL",
    "gn:name":"Laohuangtian",
    "gn:population":0,
    "gn:timezone":"Asia/Shanghai",
    "iso:country":"CN",
    "name:zho_x_preferred":[
        "\u8001\u9ec4\u7530"
    ],
    "wof:name":"Laohuangtian",
    "wof:placetype":"locality"
},
  "geometry": {"coordinates":[109.485,26.8168],"type":"Point"}
}