{
  "type": "Feature",
  "properties": {
    "gn:admin1_code":"3",
    "gn:asciiname":"Xinjiayuan",
    "gn:country_code":"CN",
    "gn:dem":114,
    "gn:feature_class":"P",
    "gn:feature_code":"PPL",
    "gn:name":"Xinjiayuan",
    "gn:population":0,
    "gn:timezone":"Asia/Shanghai",
    "iso:country":"CN",
    "name:und_x_variant":[
        "\u65b0\u5bb6\u6e90"
    ],
    "wof:name":"Xinjiayuan",
    "wof:placetype":"locality"
},
  "geometry": {"coordinates":[117.20473,29.66142],"type":"Point"}
}