{
  "type": "Feature",
  "properties": {
    "gn:admin1_code":"3.0",
    "gn:asciiname":"Lanbei",
    "gn:country_code":"CN",
    "gn:dem":214,
    "gn:feature_class":"P",
    "gn:feature_code":"PPL",
    "gn:name":"Lanbei",
    "gn:population":0,
    "gn:timezone":"Asia/Shanghai",
    "iso:country":"CN",
    "name:und_x_variant":[
        "\u84dd\u8d1d"
    ],
    "wof:name":"Lanbei",
    "wof:placetype":"locality"
},
  "geometry": {"coordinates":[115.11228,25.46094],"type":"Point"}
}