{
  "type": "Feature",
  "properties": {
    "gn:admin1_code":"19.0",
    "gn:asciiname":"Lazishancun",
    "gn:country_code":"CN",
    "gn:dem":205,
    "gn:feature_class":"P",
    "gn:feature_code":"PPL",
    "gn:name":"Lazishancun",
    "gn:population":0,
    "gn:timezone":"Asia/Shanghai",
    "iso:country":"CN",
    "name:zho_x_preferred":[
        "\u782c\u5b50\u5c71\u6751"
    ],
    "wof:name":"Lazishancun",
    "wof:placetype":"locality"
},
  "geometry": {"coordinates":[121.304,41.7414],"type":"Point"}
}