{
  "type": "Feature",
  "properties": {
    "gn:admin1_code":"7.0",
    "gn:asciiname":"Gaomen",
    "gn:country_code":"CN",
    "gn:dem":188,
    "gn:feature_class":"P",
    "gn:feature_code":"PPL",
    "gn:name":"Gaomen",
    "gn:population":0,
    "gn:timezone":"Asia/Shanghai",
    "iso:country":"CN",
    "name:und_x_variant":[
        "\u9ad8\u95e8"
    ],
    "name:zho_x_preferred":[
        "\u9ad8\u95e8"
    ],
    "wof:name":"Gaomen",
    "wof:placetype":"locality"
},
  "geometry": {"coordinates":[118.43289,26.9003],"type":"Point"}
}