{
  "type": "Feature",
  "properties": {
    "gn:admin1_code":"18",
    "gn:asciiname":"Xiewanzi",
    "gn:country_code":"CN",
    "gn:dem":931,
    "gn:feature_class":"P",
    "gn:feature_code":"PPL",
    "gn:name":"Xiewanzi",
    "gn:population":0,
    "gn:timezone":"Asia/Shanghai",
    "iso:country":"CN",
    "name:zho_x_preferred":[
        "\u8c22\u6e7e\u5b50"
    ],
    "wof:name":"Xiewanzi",
    "wof:placetype":"locality"
},
  "geometry": {"coordinates":[105.94499999999999,27.6642],"type":"Point"}
}