{
  "type": "Feature",
  "properties": {
    "gn:admin1_code":"29.0",
    "gn:asciiname":"Hewai",
    "gn:country_code":"CN",
    "gn:dem":1978,
    "gn:feature_class":"P",
    "gn:feature_code":"PPL",
    "gn:name":"Hewai",
    "gn:population":0,
    "gn:timezone":"Asia/Shanghai",
    "iso:country":"CN",
    "name:zho_x_preferred":[
        "\u6cb3\u5916"
    ],
    "wof:name":"Hewai",
    "wof:placetype":"locality"
},
  "geometry": {"coordinates":[99.0993,25.6253],"type":"Point"}
}