{
  "type": "Feature",
  "properties": {
    "gn:admin1_code":"5.0",
    "gn:asciiname":"Dongyangshugou",
    "gn:country_code":"CN",
    "gn:dem":193,
    "gn:feature_class":"P",
    "gn:feature_code":"PPL",
    "gn:name":"Dongyangshugou",
    "gn:population":0,
    "gn:timezone":"Asia/Shanghai",
    "iso:country":"CN",
    "name:zho_x_preferred":[
        "\u4e1c\u6768\u6811\u6c9f"
    ],
    "wof:name":"Dongyangshugou",
    "wof:placetype":"locality"
},
  "geometry": {"coordinates":[126.43228000000001,44.86287],"type":"Point"}
}