{
  "type": "Feature",
  "properties": {
    "gn:admin1_code":"32.0",
    "gn:asciiname":"Hanluping",
    "gn:country_code":"CN",
    "gn:dem":1122,
    "gn:feature_class":"P",
    "gn:feature_code":"PPL",
    "gn:name":"Hanluping",
    "gn:population":0,
    "gn:timezone":"Asia/Shanghai",
    "iso:country":"CN",
    "name:zho_x_preferred":[
        "\u65f1\u7089\u576a"
    ],
    "wof:name":"Hanluping",
    "wof:placetype":"locality"
},
  "geometry": {"coordinates":[105.176,32.2865],"type":"Point"}
}