{
  "type": "Feature",
  "properties": {
    "gn:admin1_code":"14.0",
    "gn:asciiname":"Gongzhi",
    "gn:country_code":"CN",
    "gn:dem":5009,
    "gn:feature_class":"P",
    "gn:feature_code":"PPL",
    "gn:name":"Gongzhi",
    "gn:population":0,
    "gn:timezone":"Asia/Urumqi",
    "iso:country":"CN",
    "name:bod_x_preferred":[
        "Gomzh\u00ea"
    ],
    "name:zho_x_preferred":[
        "Gongzhi"
    ],
    "name:zho_x_variant":[
        "\u8d21\u667a"
    ],
    "wof:name":"Gongzhi",
    "wof:placetype":"locality"
},
  "geometry": {"coordinates":[88.001,28.801],"type":"Point"}
}