{
  "type": "Feature",
  "properties": {
    "gn:admin1_code":"29.0",
    "gn:asciiname":"Xiaopingcun",
    "gn:country_code":"CN",
    "gn:dem":1522,
    "gn:feature_class":"P",
    "gn:feature_code":"PPL",
    "gn:name":"Xiaopingcun",
    "gn:population":0,
    "gn:timezone":"Asia/Shanghai",
    "iso:country":"CN",
    "name:zho_x_preferred":[
        "\u5c0f\u5e73\u6751"
    ],
    "wof:name":"Xiaopingcun",
    "wof:placetype":"locality"
},
  "geometry": {"coordinates":[100.601,25.7897],"type":"Point"}
}