{
  "type": "Feature",
  "properties": {
    "gn:admin1_code":"29",
    "gn:asciiname":"Xuying",
    "gn:country_code":"CN",
    "gn:dem":1964,
    "gn:feature_class":"P",
    "gn:feature_code":"PPL",
    "gn:name":"Xuying",
    "gn:population":0,
    "gn:timezone":"Asia/Shanghai",
    "iso:country":"CN",
    "name:zho_x_preferred":[
        "\u5f90\u8425"
    ],
    "wof:name":"Xuying",
    "wof:placetype":"locality"
},
  "geometry": {"coordinates":[102.67694,24.0907],"type":"Point"}
}