{
  "type": "Feature",
  "properties": {
    "gn:admin1_code":"30.0",
    "gn:asciiname":"Gucangnei",
    "gn:country_code":"CN",
    "gn:dem":60,
    "gn:feature_class":"P",
    "gn:feature_code":"PPL",
    "gn:name":"Gucangnei",
    "gn:population":0,
    "gn:timezone":"Asia/Urumqi",
    "iso:country":"CN",
    "name:zho_x_preferred":[
        "\u8c37\u4ed3\u5185"
    ],
    "wof:name":"Gucangnei",
    "wof:placetype":"locality"
},
  "geometry": {"coordinates":[109.95283000000001,20.60455],"type":"Point"}
}