{
  "type": "Feature",
  "properties": {
    "gn:admin1_code":"14",
    "gn:asciiname":"Xiabo",
    "gn:country_code":"CN",
    "gn:dem":4728,
    "gn:feature_class":"P",
    "gn:feature_code":"PPL",
    "gn:name":"Xiabo",
    "gn:population":0,
    "gn:timezone":"Asia/Urumqi",
    "iso:country":"CN",
    "name:zho_x_preferred":[
        "\u867e\u6ce2"
    ],
    "wof:name":"Xiabo",
    "wof:placetype":"locality"
},
  "geometry": {"coordinates":[89.336,29.9382],"type":"Point"}
}