{
  "type": "Feature",
  "properties": {
    "gn:admin1_code":"14.0",
    "gn:asciiname":"Kaduicun",
    "gn:country_code":"CN",
    "gn:dem":3982,
    "gn:feature_class":"P",
    "gn:feature_code":"PPL",
    "gn:name":"Kaduicun",
    "gn:population":0,
    "gn:timezone":"Asia/Urumqi",
    "iso:country":"CN",
    "name:zho_x_preferred":[
        "\u5361\u5806\u6751"
    ],
    "wof:name":"Kaduicun",
    "wof:placetype":"locality"
},
  "geometry": {"coordinates":[96.85075999999999,30.08997],"type":"Point"}
}