{
  "type": "Feature",
  "properties": {
    "gn:admin1_code":"32.0",
    "gn:asciiname":"Luorong'ede",
    "gn:country_code":"CN",
    "gn:dem":3350,
    "gn:feature_class":"P",
    "gn:feature_code":"PPL",
    "gn:name":"Luorong\u2019ede",
    "gn:population":0,
    "gn:timezone":"Asia/Shanghai",
    "iso:country":"CN",
    "name:und_x_variant":[
        "Luorong\u2019ede"
    ],
    "name:zho_x_preferred":[
        "\u6d1b\u7ed2\u989d\u5fb7"
    ],
    "wof:name":"Luorong'ede",
    "wof:placetype":"locality"
},
  "geometry": {"coordinates":[101.026,29.7715],"type":"Point"}
}