{
  "type": "Feature",
  "properties": {
    "gn:admin1_code":"2.0",
    "gn:asciiname":"Yougekou",
    "gn:country_code":"CN",
    "gn:dem":80,
    "gn:feature_class":"P",
    "gn:feature_code":"PPL",
    "gn:name":"Yougekou",
    "gn:population":0,
    "gn:timezone":"Asia/Shanghai",
    "iso:country":"CN",
    "name:zho_x_preferred":[
        "\u7337\u9601\u53e3"
    ],
    "wof:name":"Yougekou",
    "wof:placetype":"locality"
},
  "geometry": {"coordinates":[120.11060999999999,29.35895],"type":"Point"}
}