{
  "type": "Feature",
  "properties": {
    "gn:admin1_code":"8.0",
    "gn:asciiname":"Daishancun",
    "gn:country_code":"CN",
    "gn:dem":180,
    "gn:feature_class":"P",
    "gn:feature_code":"PPL",
    "gn:name":"Daishancun",
    "gn:population":0,
    "gn:timezone":"Asia/Shanghai",
    "iso:country":"CN",
    "name:zho_x_preferred":[
        "\u5cb1\u5c71\u6751"
    ],
    "wof:name":"Daishancun",
    "wof:placetype":"locality"
},
  "geometry": {"coordinates":[130.12676999999999,46.01533],"type":"Point"}
}