{
  "type": "Feature",
  "properties": {
    "gn:admin1_code":"25",
    "gn:asciiname":"Guxian",
    "gn:country_code":"CN",
    "gn:dem":98,
    "gn:feature_class":"P",
    "gn:feature_code":"PPL",
    "gn:name":"Guxian",
    "gn:population":0,
    "gn:timezone":"Asia/Shanghai",
    "iso:country":"CN",
    "name:zho_x_preferred":[
        "\u6545\u53bf"
    ],
    "wof:name":"Guxian",
    "wof:placetype":"locality"
},
  "geometry": {"coordinates":[117.26900000000001,35.6919],"type":"Point"}
}