{
  "type": "Feature",
  "properties": {
    "gn:admin1_code":"16.0",
    "gn:asciiname":"Pingguang",
    "gn:country_code":"CN",
    "gn:dem":480,
    "gn:feature_class":"P",
    "gn:feature_code":"PPL",
    "gn:name":"Pingguang",
    "gn:population":0,
    "gn:timezone":"Asia/Shanghai",
    "iso:country":"CN",
    "name:zho_x_preferred":[
        "\u5e73\u5149"
    ],
    "wof:name":"Pingguang",
    "wof:placetype":"locality"
},
  "geometry": {"coordinates":[108.033,24.9977],"type":"Point"}
}