{
  "type": "Feature",
  "properties": {
    "gn:admin1_code":"30",
    "gn:asciiname":"Haipo",
    "gn:country_code":"CN",
    "gn:dem":4,
    "gn:feature_class":"P",
    "gn:feature_code":"PPL",
    "gn:name":"Haipo",
    "gn:population":0,
    "gn:timezone":"Asia/Urumqi",
    "iso:country":"CN",
    "name:zho_x_preferred":[
        "\u6d77\u5761"
    ],
    "wof:name":"Haipo",
    "wof:placetype":"locality"
},
  "geometry": {"coordinates":[111.42026,21.57155],"type":"Point"}
}