{
  "type": "Feature",
  "properties": {
    "gn:admin1_code":"10",
    "gn:asciiname":"Beimaqian",
    "gn:country_code":"CN",
    "gn:dem":28,
    "gn:feature_class":"P",
    "gn:feature_code":"PPL",
    "gn:name":"Beimaqian",
    "gn:population":0,
    "gn:timezone":"Asia/Shanghai",
    "iso:country":"CN",
    "name:zho_x_preferred":[
        "\u5317\u9a6c\u524d"
    ],
    "wof:name":"Beimaqian",
    "wof:placetype":"locality"
},
  "geometry": {"coordinates":[115.788,37.3469],"type":"Point"}
}