{
  "type": "Feature",
  "properties": {
    "gn:admin1_code":"5.0",
    "gn:asciiname":"Xiaoduanshugou",
    "gn:country_code":"CN",
    "gn:dem":232,
    "gn:feature_class":"P",
    "gn:feature_code":"PPL",
    "gn:name":"Xiaoduanshugou",
    "gn:population":0,
    "gn:timezone":"Asia/Shanghai",
    "iso:country":"CN",
    "name:zho_x_preferred":[
        "\u5c0f\u6934\u6811\u6c9f"
    ],
    "wof:name":"Xiaoduanshugou",
    "wof:placetype":"locality"
},
  "geometry": {"coordinates":[124.83207,43.35815],"type":"Point"}
}