{
  "type": "Feature",
  "properties": {
    "gn:admin1_code":"15.0",
    "gn:asciiname":"Weicha",
    "gn:country_code":"CN",
    "gn:dem":1798,
    "gn:feature_class":"P",
    "gn:feature_code":"PPL",
    "gn:name":"Weicha",
    "gn:population":0,
    "gn:timezone":"Asia/Shanghai",
    "iso:country":"CN",
    "name:und_x_variant":[
        "\u9b4f\u5c94"
    ],
    "wof:name":"Weicha",
    "wof:placetype":"locality"
},
  "geometry": {"coordinates":[105.62058,35.62878],"type":"Point"}
}