{
  "type": "Feature",
  "properties": {
    "gn:admin1_code":"30",
    "gn:asciiname":"Shanxia",
    "gn:country_code":"CN",
    "gn:dem":136,
    "gn:feature_class":"P",
    "gn:feature_code":"PPL",
    "gn:name":"Shanxia",
    "gn:population":0,
    "gn:timezone":"Asia/Shanghai",
    "iso:country":"CN",
    "name:und_x_variant":[
        "\u5c71\u4e0b"
    ],
    "wof:name":"Shanxia",
    "wof:placetype":"locality"
},
  "geometry": {"coordinates":[115.22338000000001,23.90294],"type":"Point"}
}