{
  "type": "Feature",
  "properties": {
    "gn:admin1_code":"3.0",
    "gn:asciiname":"Yaole Chenjia",
    "gn:country_code":"CN",
    "gn:dem":52,
    "gn:feature_class":"P",
    "gn:feature_code":"PPL",
    "gn:name":"Yaole Chenjia",
    "gn:population":0,
    "gn:timezone":"Asia/Shanghai",
    "iso:country":"CN",
    "name:zho_x_preferred":[
        "\u7a91\u4ec2\u9648\u5bb6"
    ],
    "wof:name":"Yaole Chenjia",
    "wof:placetype":"locality"
},
  "geometry": {"coordinates":[117.25808000000001,28.23326],"type":"Point"}
}