{
  "type": "Feature",
  "properties": {
    "gn:admin1_code":"32.0",
    "gn:asciiname":"Kasa",
    "gn:country_code":"CN",
    "gn:dem":2683,
    "gn:feature_class":"P",
    "gn:feature_code":"PPL",
    "gn:name":"Kasa",
    "gn:population":0,
    "gn:timezone":"Asia/Shanghai",
    "iso:country":"CN",
    "name:zho_x_preferred":[
        "\u5361\u6492"
    ],
    "wof:name":"Kasa",
    "wof:placetype":"locality"
},
  "geometry": {"coordinates":[102.11104,31.24878],"type":"Point"}
}