{
  "type": "Feature",
  "properties": {
    "gn:admin1_code":"33.0",
    "gn:asciiname":"Zhangjiayakou",
    "gn:country_code":"CN",
    "gn:dem":1304,
    "gn:feature_class":"P",
    "gn:feature_code":"PPL",
    "gn:name":"Zhangjiayakou",
    "gn:population":0,
    "gn:timezone":"Asia/Shanghai",
    "iso:country":"CN",
    "name:zho_x_preferred":[
        "\u5f20\u5bb6\u57ad\u53e3"
    ],
    "wof:name":"Zhangjiayakou",
    "wof:placetype":"locality"
},
  "geometry": {"coordinates":[107.98944,29.28941],"type":"Point"}
}