{
  "type": "Feature",
  "properties": {
    "gn:admin1_code":"16.0",
    "gn:asciiname":"Zhangguwei",
    "gn:country_code":"CN",
    "gn:dem":434,
    "gn:feature_class":"P",
    "gn:feature_code":"PPL",
    "gn:name":"Zhangguwei",
    "gn:population":0,
    "gn:timezone":"Asia/Shanghai",
    "iso:country":"CN",
    "name:zho_x_preferred":[
        "\u6a1f\u59d1\u5c3e"
    ],
    "wof:name":"Zhangguwei",
    "wof:placetype":"locality"
},
  "geometry": {"coordinates":[111.349,23.9372],"type":"Point"}
}