{
  "type": "Feature",
  "properties": {
    "gn:admin1_code":"16",
    "gn:asciiname":"Quanzhou",
    "gn:country_code":"CN",
    "gn:dem":152,
    "gn:feature_class":"P",
    "gn:feature_code":"PPLA3",
    "gn:name":"Quanzhou",
    "gn:population":0,
    "gn:timezone":"Asia/Shanghai",
    "iso:country":"CN",
    "name:afr_x_preferred":[
        "Quanzhou"
    ],
    "name:als_x_preferred":[
        "Quanzhou"
    ],
    "name:ara_x_preferred":[
        "\u062a\u0634\u0648\u0627\u0646\u062a\u0634\u0648"
    ],
    "name:cat_x_preferred":[
        "Quanzhou"
    ],
    "name:cdo_x_preferred":[
        "Ci\u00f2ng-ci\u016d"
    ],
    "name:ceb_x_preferred":[
        "Quanzhou"
    ],
    "name:ces_x_preferred":[
        "\u010cch\u00fcan-\u010dou"
    ],
    "name:dan_x_preferred":[
        "Quanzhou"
    ],
    "name:deu_x_preferred":[
        "Quanzhou"
    ],
    "name:epo_x_preferred":[
        "\u0108juan\u011do\u016d"
    ],
    "name:eus_x_preferred":[
        "Quanzhou"
    ],
    "name:fas_x_preferred":[
        "\u06a9\u0648\u0627\u0646\u0698\u0648"
    ],
    "name:fin_x_preferred":[
        "Quanzhou"
    ],
    "name:fra_x_preferred":[
        "Quanzhou"
    ],
    "name:hak_x_preferred":[
        "Chhi\u00e8n-ch\u00fb-s\u1e73"
    ],
    "name:ind_x_preferred":[
        "Quanzhou"
    ],
    "name:ita_x_preferred":[
        "Quanzhou"
    ],
    "name:jpn_x_preferred":[
        "\u6cc9\u5dde\u5e02"
    ],
    "name:kik_x_preferred":[
        "Quanzhou"
    ],
    "name:kor_x_preferred":[
        "\ucde8\uc548\uc800\uc6b0\uc2dc"
    ],
    "name:lat_x_preferred":[
        "Quanzhou"
    ],
    "name:lit_x_preferred":[
        "\u010ciuand\u017eou"
    ],
    "name:mlg_x_preferred":[
        "Quanzhou"
    ],
    "name:nld_x_preferred":[
        "Quanzhou"
    ],
    "name:nno_x_preferred":[
        "Quanzhou"
    ],
    "name:nor_x_preferred":[
        "Quanzhou"
    ],
    "name:pam_x_preferred":[
        "Quanzhou"
    ],
    "name:pnb_x_preferred":[
        "\u0686\u0648\u0626\u0646\u0698\u0648"
    ],
    "name:pol_x_preferred":[
        "Quanzhou"
    ],
    "name:por_x_preferred":[
        "Quanzhou"
    ],
    "name:ron_x_preferred":[
        "Quanzhou"
    ],
    "name:rus_x_preferred":[
        "\u0426\u044e\u0430\u043d\u044c\u0447\u0436\u043e\u0443"
    ],
    "name:sco_x_preferred":[
        "Quanzhou"
    ],
    "name:spa_x_preferred":[
        "Quanzhou"
    ],
    "name:swe_x_preferred":[
        "Quanzhou"
    ],
    "name:tgl_x_preferred":[
        "Quanzhou"
    ],
    "name:tha_x_preferred":[
        "\u0e40\u0e09\u0e27\u0e35\u0e22\u0e19\u0e42\u0e08\u0e27"
    ],
    "name:tur_x_preferred":[
        "Quanzhou"
    ],
    "name:uig_x_preferred":[
        "Ch\u00fcenju shehiri"
    ],
    "name:ukr_x_preferred":[
        "\u0426\u044e\u0430\u043d\u044c\u0447\u0436\u043e\u0443"
    ],
    "name:und_x_variant":[
        "Chuanchow"
    ],
    "name:urd_x_preferred":[
        "\u0686\u0648\u0627\u0646\u0698\u0648"
    ],
    "name:vie_x_preferred":[
        "Tuy\u1ec1n Ch\u00e2u"
    ],
    "name:war_x_preferred":[
        "Quanzhou"
    ],
    "name:zho_x_preferred":[
        "Ch\u2019\u00fcan"
    ],
    "name:zho_x_variant":[
        "Ch\u2019\u00fcan-chou",
        "Ch\u2019\u00fcan-hsien-ch\u2019eng",
        "Ch\u2019\u00fcan-chou-chen",
        "Ch\u2019\u00fcan-hsien",
        "\u5168\u5dde",
        "\u6cc9\u5dde\u5e02"
    ],
    "wof:name":"Quanzhou",
    "wof:placetype":"locality"
},
  "geometry": {"coordinates":[111.03639,25.94459],"type":"Point"}
}