{
  "type": "Feature",
  "properties": {
    "gn:admin1_code":"16",
    "gn:asciiname":"Quanzhou",
    "gn:country_code":"CN",
    "gn:dem":152,
    "gn:feature_class":"P",
    "gn:feature_code":"PPLA3",
    "gn:name":"Quanzhou",
    "gn:population":0,
    "gn:timezone":"Asia/Shanghai",
    "iso:country":"CN",
    "name:und_x_variant":[
        "Chuanchow",
        "Quanzhou"
    ],
    "name:zho_x_preferred":[
        "Ch\u2019\u00fcan"
    ],
    "name:zho_x_variant":[
        "Ch\u2019\u00fcan-chou",
        "Ch\u2019\u00fcan-hsien-ch\u2019eng",
        "Ch\u2019\u00fcan-chou-chen",
        "Ch\u2019\u00fcan-hsien",
        "\u5168\u5dde"
    ],
    "wof:name":"Quanzhou",
    "wof:placetype":"locality"
},
  "geometry": {"coordinates":[111.03639,25.94459],"type":"Point"}
}