{
  "type": "Feature",
  "properties": {
    "gn:admin1_code":"33.0",
    "gn:asciiname":"Qingping",
    "gn:country_code":"CN",
    "gn:dem":1445,
    "gn:feature_class":"P",
    "gn:feature_code":"PPL",
    "gn:name":"Qingping",
    "gn:population":0,
    "gn:timezone":"Asia/Shanghai",
    "iso:country":"CN",
    "name:deu_x_preferred":[
        "Qingping"
    ],
    "name:zho_x_preferred":[
        "\u9752\u576a"
    ],
    "wof:name":"Qingping",
    "wof:placetype":"locality"
},
  "geometry": {"coordinates":[108.52637,30.14608],"type":"Point"}
}