{
  "type": "Feature",
  "properties": {
    "gn:admin1_code":"11.0",
    "gn:asciiname":"Zumo",
    "gn:country_code":"CN",
    "gn:dem":628,
    "gn:feature_class":"P",
    "gn:feature_code":"PPL",
    "gn:name":"Zumo",
    "gn:population":0,
    "gn:timezone":"Asia/Shanghai",
    "iso:country":"CN",
    "name:zho_x_preferred":[
        "\u7956\u78e8"
    ],
    "wof:name":"Zumo",
    "wof:placetype":"locality"
},
  "geometry": {"coordinates":[109.18241999999999,27.289],"type":"Point"}
}