{
  "type": "Feature",
  "properties": {
    "gn:admin1_code":"20.0",
    "gn:asciiname":"Heli",
    "gn:country_code":"CN",
    "gn:dem":295,
    "gn:feature_class":"P",
    "gn:feature_code":"PPL",
    "gn:name":"Heli",
    "gn:population":0,
    "gn:timezone":"Asia/Shanghai",
    "iso:country":"CN",
    "name:cat_x_preferred":[
        "Heli"
    ],
    "name:deu_x_preferred":[
        "Heli"
    ],
    "name:fin_x_preferred":[
        "Heli"
    ],
    "name:nld_x_preferred":[
        "Heli"
    ],
    "name:zho_x_preferred":[
        "\u5408\u529b"
    ],
    "wof:name":"Heli",
    "wof:placetype":"locality"
},
  "geometry": {"coordinates":[124.39234999999999,49.56983],"type":"Point"}
}