{
  "type": "Feature",
  "properties": {
    "gn:admin1_code":"24.0",
    "gn:asciiname":"Beimazhuang",
    "gn:country_code":"CN",
    "gn:dem":1003,
    "gn:feature_class":"P",
    "gn:feature_code":"PPL",
    "gn:name":"Beimazhuang",
    "gn:population":0,
    "gn:timezone":"Asia/Shanghai",
    "iso:country":"CN",
    "name:und_x_variant":[
        "\u5317\u9a6c\u5e84"
    ],
    "name:zho_x_preferred":[
        "\u5317\u9a6c\u5e84"
    ],
    "wof:name":"Beimazhuang",
    "wof:placetype":"locality"
},
  "geometry": {"coordinates":[113.27866000000002,39.5948],"type":"Point"}
}