{
  "type": "Feature",
  "properties": {
    "gn:admin1_code":"33.0",
    "gn:asciiname":"Jinyan",
    "gn:country_code":"CN",
    "gn:dem":1188,
    "gn:feature_class":"P",
    "gn:feature_code":"PPL",
    "gn:name":"Jinyan",
    "gn:population":0,
    "gn:timezone":"Asia/Shanghai",
    "iso:country":"CN",
    "name:zho_x_preferred":[
        "\u91d1\u71d5"
    ],
    "wof:name":"Jinyan",
    "wof:placetype":"locality"
},
  "geometry": {"coordinates":[109.07658000000001,31.81572],"type":"Point"}
}