{
  "type": "Feature",
  "properties": {
    "gn:admin1_code":"32.0",
    "gn:asciiname":"Shizi",
    "gn:country_code":"CN",
    "gn:dem":655,
    "gn:feature_class":"P",
    "gn:feature_code":"PPL",
    "gn:name":"Shizi",
    "gn:population":0,
    "gn:timezone":"Asia/Shanghai",
    "iso:country":"CN",
    "name:zho_x_preferred":[
        "\u77f3\u5b50"
    ],
    "wof:name":"Shizi",
    "wof:placetype":"locality"
},
  "geometry": {"coordinates":[103.492,30.744],"type":"Point"}
}