{
  "type": "Feature",
  "properties": {
    "gn:admin1_code":"16",
    "gn:asciiname":"Longtou",
    "gn:cc2":"CN",
    "gn:country_code":"CN",
    "gn:dem":97,
    "gn:feature_class":"P",
    "gn:feature_code":"PPL",
    "gn:name":"Longtou",
    "gn:population":0,
    "gn:timezone":"Asia/Shanghai",
    "iso:country":"CN",
    "name:und_x_variant":[
        "Lung-t\u2019ou",
        "Lung-t\u2019ou-hs\u00fc",
        "Longtou"
    ],
    "wof:name":"Longtou",
    "wof:placetype":"locality"
},
  "geometry": {"coordinates":[109.16833,24.75806],"type":"Point"}
}