{
  "type": "Feature",
  "properties": {
    "gn:admin1_code":"10",
    "gn:asciiname":"Wangshenggui",
    "gn:country_code":"CN",
    "gn:dem":1452,
    "gn:feature_class":"P",
    "gn:feature_code":"PPL",
    "gn:name":"Wangshenggui",
    "gn:population":0,
    "gn:timezone":"Asia/Shanghai",
    "iso:country":"CN",
    "name:zho_x_preferred":[
        "\u738b\u751f\u8d35"
    ],
    "wof:name":"Wangshenggui",
    "wof:placetype":"locality"
},
  "geometry": {"coordinates":[114.89959,41.95322],"type":"Point"}
}