{
  "type": "Feature",
  "properties": {
    "gn:admin1_code":"1.0",
    "gn:asciiname":"Weicun",
    "gn:country_code":"CN",
    "gn:dem":9,
    "gn:feature_class":"P",
    "gn:feature_code":"PPL",
    "gn:name":"Weicun",
    "gn:population":0,
    "gn:timezone":"Asia/Shanghai",
    "iso:country":"CN",
    "name:zho_x_preferred":[
        "\u9b4f\u6751"
    ],
    "wof:name":"Weicun",
    "wof:placetype":"locality"
},
  "geometry": {"coordinates":[118.81891,31.13153],"type":"Point"}
}