{
  "type": "Feature",
  "properties": {
    "gn:admin1_code":"04",
    "gn:asciiname":"Qingshengcun",
    "gn:country_code":"CN",
    "gn:dem":3,
    "gn:feature_class":"P",
    "gn:feature_code":"PPL",
    "gn:name":"Qingshengcun",
    "gn:population":0,
    "gn:timezone":"Asia/Shanghai",
    "iso:country":"CN",
    "name:und_x_variant":[
        "Qingsheng",
        "\u5e86\u751f",
        "Qingshengcun"
    ],
    "name:zho_x_preferred":[
        "\u5e86\u751f\u6751"
    ],
    "wof:name":"Qingshengcun",
    "wof:placetype":"locality"
},
  "geometry": {"coordinates":[120.62488,33.11353],"type":"Point"}
}