{
  "type": "Feature",
  "properties": {
    "gn:admin1_code":"19.0",
    "gn:asciiname":"Chenjiacun",
    "gn:country_code":"CN",
    "gn:dem":248,
    "gn:feature_class":"P",
    "gn:feature_code":"PPL",
    "gn:name":"Chenjiacun",
    "gn:population":0,
    "gn:timezone":"Asia/Shanghai",
    "iso:country":"CN",
    "name:und_x_variant":[
        "Chenjiabaozi",
        "Chenjia Buzi"
    ],
    "name:zho_x_preferred":[
        "\u9648\u5bb6\u6751"
    ],
    "name:zho_x_variant":[
        "\u9648\u5bb6\u5821\u5b50"
    ],
    "wof:name":"Chenjiacun",
    "wof:placetype":"locality"
},
  "geometry": {"coordinates":[123.62638,41.06457],"type":"Point"}
}