{
  "type": "Feature",
  "properties": {
    "gn:admin1_code":"12.0",
    "gn:asciiname":"Xiaomacaogou",
    "gn:country_code":"CN",
    "gn:dem":645,
    "gn:feature_class":"P",
    "gn:feature_code":"PPL",
    "gn:name":"Xiaomacaogou",
    "gn:population":0,
    "gn:timezone":"Asia/Shanghai",
    "iso:country":"CN",
    "name:zho_x_preferred":[
        "\u5c0f\u9a6c\u8349\u6c9f"
    ],
    "wof:name":"Xiaomacaogou",
    "wof:placetype":"locality"
},
  "geometry": {"coordinates":[111.31852000000001,31.98798],"type":"Point"}
}