{
  "type": "Feature",
  "properties": {
    "gn:admin1_code":"1.0",
    "gn:asciiname":"Nongkecun",
    "gn:country_code":"CN",
    "gn:dem":22,
    "gn:feature_class":"P",
    "gn:feature_code":"PPLF",
    "gn:name":"Nongkecun",
    "gn:population":0,
    "gn:timezone":"Asia/Shanghai",
    "iso:country":"CN",
    "name:zho_x_preferred":[
        "\u519c\u79d1\u6751"
    ],
    "wof:name":"Nongkecun",
    "wof:placetype":"locality"
},
  "geometry": {"coordinates":[117.95654999999999,31.91777],"type":"Point"}
}