{
  "type": "Feature",
  "properties": {
    "gn:admin1_code":"5.0",
    "gn:asciiname":"Baojintaicun",
    "gn:country_code":"CN",
    "gn:dem":137,
    "gn:feature_class":"P",
    "gn:feature_code":"PPL",
    "gn:name":"Baojintaicun",
    "gn:population":0,
    "gn:timezone":"Asia/Shanghai",
    "iso:country":"CN",
    "name:zho_x_preferred":[
        "\u5305\u91d1\u53f0\u6751"
    ],
    "wof:name":"Baojintaicun",
    "wof:placetype":"locality"
},
  "geometry": {"coordinates":[123.41791000000001,45.77063],"type":"Point"}
}