{
  "type": "Feature",
  "properties": {
    "gn:admin1_code":"32.0",
    "gn:asciiname":"Zengda",
    "gn:country_code":"CN",
    "gn:dem":2074,
    "gn:feature_class":"P",
    "gn:feature_code":"PPL",
    "gn:name":"Zengda",
    "gn:population":0,
    "gn:timezone":"Asia/Shanghai",
    "iso:country":"CN",
    "name:zho_x_preferred":[
        "\u66fe\u8fbe"
    ],
    "wof:name":"Zengda",
    "wof:placetype":"locality"
},
  "geometry": {"coordinates":[102.01058999999999,31.20254000000001],"type":"Point"}
}