{
  "type": "Feature",
  "properties": {
    "gn:admin1_code":"24.0",
    "gn:asciiname":"Xigoucun",
    "gn:country_code":"CN",
    "gn:dem":1095,
    "gn:feature_class":"P",
    "gn:feature_code":"PPL",
    "gn:name":"Xigoucun",
    "gn:population":0,
    "gn:timezone":"Asia/Shanghai",
    "iso:country":"CN",
    "name:und_x_variant":[
        "\u897f\u6c9f\u6751"
    ],
    "name:zho_x_preferred":[
        "\u897f\u6c9f\u6751"
    ],
    "wof:name":"Xigoucun",
    "wof:placetype":"locality"
},
  "geometry": {"coordinates":[114.02976,39.37782],"type":"Point"}
}