{
  "type": "Feature",
  "properties": {
    "gn:admin1_code":"16",
    "gn:asciiname":"Tiechang",
    "gn:country_code":"CN",
    "gn:dem":220,
    "gn:feature_class":"P",
    "gn:feature_code":"PPL",
    "gn:name":"Tiechang",
    "gn:population":0,
    "gn:timezone":"Asia/Shanghai",
    "iso:country":"CN",
    "name:ceb_x_preferred":[
        "Tiechang"
    ],
    "name:deu_x_preferred":[
        "Tiechang"
    ],
    "name:swe_x_preferred":[
        "Tiechang"
    ],
    "name:zho_x_preferred":[
        "\u94c1\u5382"
    ],
    "wof:name":"Tiechang",
    "wof:placetype":"locality"
},
  "geometry": {"coordinates":[110.279,24.6606],"type":"Point"}
}