{
  "type": "Feature",
  "properties": {
    "gn:admin1_code":"15.0",
    "gn:asciiname":"Yingke",
    "gn:country_code":"CN",
    "gn:dem":1318,
    "gn:feature_class":"P",
    "gn:feature_code":"PPL",
    "gn:name":"Yingke",
    "gn:population":0,
    "gn:timezone":"Asia/Shanghai",
    "iso:country":"CN",
    "name:zho_x_preferred":[
        "\u76c8\u79d1"
    ],
    "wof:name":"Yingke",
    "wof:placetype":"locality"
},
  "geometry": {"coordinates":[103.63200000000001,38.9343],"type":"Point"}
}