{
  "type": "Feature",
  "properties": {
    "gn:admin1_code":"24.0",
    "gn:asciiname":"Zhangcun",
    "gn:country_code":"CN",
    "gn:dem":885,
    "gn:feature_class":"P",
    "gn:feature_code":"PPL",
    "gn:name":"Zhangcun",
    "gn:population":0,
    "gn:timezone":"Asia/Shanghai",
    "iso:country":"CN",
    "name:zho_x_preferred":[
        "\u5f20\u6751"
    ],
    "wof:name":"Zhangcun",
    "wof:placetype":"locality"
},
  "geometry": {"coordinates":[112.74596,35.44317],"type":"Point"}
}