{
  "type": "Feature",
  "properties": {
    "gn:admin1_code":"04",
    "gn:asciiname":"Mudian",
    "gn:country_code":"CN",
    "gn:dem":50,
    "gn:feature_class":"P",
    "gn:feature_code":"PPLA4",
    "gn:name":"Mudian",
    "gn:population":0,
    "gn:timezone":"Asia/Shanghai",
    "iso:country":"CN",
    "name:und_x_variant":[
        "Mu-tien",
        "Mudian",
        "Mudian Xiang"
    ],
    "name:zho_x_preferred":[
        "\u7a46\u5e97"
    ],
    "name:zho_x_variant":[
        "\u7a46\u5e97\u4e61"
    ],
    "wof:name":"Mudian",
    "wof:placetype":"locality"
},
  "geometry": {"coordinates":[118.60754,32.91839],"type":"Point"}
}