{
  "type": "Feature",
  "properties": {
    "gn:admin1_code":"8.0",
    "gn:asciiname":"Qinyuan",
    "gn:country_code":"CN",
    "gn:dem":256,
    "gn:feature_class":"P",
    "gn:feature_code":"PPL",
    "gn:name":"Qinyuan",
    "gn:population":0,
    "gn:timezone":"Asia/Shanghai",
    "iso:country":"CN",
    "name:zho_x_preferred":[
        "\u6c81\u6e90"
    ],
    "wof:name":"Qinyuan",
    "wof:placetype":"locality"
},
  "geometry": {"coordinates":[133.42642000000001,46.51209],"type":"Point"}
}