{
  "type": "Feature",
  "properties": {
    "gn:admin1_code":"5.0",
    "gn:asciiname":"Dongmingliuta",
    "gn:country_code":"CN",
    "gn:dem":579,
    "gn:feature_class":"P",
    "gn:feature_code":"PPL",
    "gn:name":"Dongmingliuta",
    "gn:population":0,
    "gn:timezone":"Asia/Shanghai",
    "iso:country":"CN",
    "name:und_x_variant":[
        "\u4e1c\u660e\u516d\u4ed6"
    ],
    "wof:name":"Dongmingliuta",
    "wof:placetype":"locality"
},
  "geometry": {"coordinates":[126.27446,41.56688],"type":"Point"}
}