{
  "type": "Feature",
  "properties": {
    "gn:admin1_code":"32",
    "gn:asciiname":"Qujiang",
    "gn:country_code":"CN",
    "gn:dem":284,
    "gn:feature_class":"P",
    "gn:feature_code":"PPLA3",
    "gn:name":"Qujiang",
    "gn:population":0,
    "gn:timezone":"Asia/Shanghai",
    "iso:country":"CN",
    "name:und_x_variant":[
        "Tsyuysyan\u2019",
        "Ch\u2019\u00fc",
        "Quxian",
        "Ch\u2019\u00fc-hsien",
        "Qujiang"
    ],
    "name:zho_x_preferred":[
        "\u6e20\u6c5f"
    ],
    "wof:name":"Qujiang",
    "wof:placetype":"locality"
},
  "geometry": {"coordinates":[106.96785,30.84206],"type":"Point"}
}