{
  "type": "Feature",
  "properties": {
    "gn:admin1_code":"20.0",
    "gn:asciiname":"Tabu Hudong",
    "gn:country_code":"CN",
    "gn:dem":1666,
    "gn:feature_class":"P",
    "gn:feature_code":"PPL",
    "gn:name":"Tabu Hudong",
    "gn:population":0,
    "gn:timezone":"Asia/Shanghai",
    "iso:country":"CN",
    "name:und_x_variant":[
        "\u5854\u5e03\u5ffd\u6d1e"
    ],
    "wof:name":"Tabu Hudong",
    "wof:placetype":"locality"
},
  "geometry": {"coordinates":[112.43668999999998,41.48053],"type":"Point"}
}