{
  "type": "Feature",
  "properties": {
    "gn:admin1_code":"3.0",
    "gn:asciiname":"Chongtoulong",
    "gn:country_code":"CN",
    "gn:dem":100,
    "gn:feature_class":"P",
    "gn:feature_code":"PPL",
    "gn:name":"Chongtoulong",
    "gn:population":0,
    "gn:timezone":"Asia/Shanghai",
    "iso:country":"CN",
    "name:und_x_variant":[
        "\u51b2\u5934\u5785"
    ],
    "wof:name":"Chongtoulong",
    "wof:placetype":"locality"
},
  "geometry": {"coordinates":[115.21057,29.34088],"type":"Point"}
}