{
  "type": "Feature",
  "properties": {
    "gn:admin1_code":"30.0",
    "gn:asciiname":"Shuangkengshui",
    "gn:country_code":"CN",
    "gn:dem":65,
    "gn:feature_class":"P",
    "gn:feature_code":"PPL",
    "gn:name":"Shuangkengshui",
    "gn:population":0,
    "gn:timezone":"Asia/Shanghai",
    "iso:country":"CN",
    "name:zho_x_preferred":[
        "\u53cc\u5751\u6c34"
    ],
    "wof:name":"Shuangkengshui",
    "wof:placetype":"locality"
},
  "geometry": {"coordinates":[114.05410999999999,23.45316],"type":"Point"}
}