{
  "type": "Feature",
  "properties": {
    "gn:admin1_code":"09",
    "gn:asciiname":"Jiasong",
    "gn:cc2":"CN",
    "gn:country_code":"CN",
    "gn:dem":157,
    "gn:feature_class":"P",
    "gn:feature_code":"PPL",
    "gn:name":"Jiasong",
    "gn:population":0,
    "gn:timezone":"Asia/Shanghai",
    "iso:country":"CN",
    "name:und_x_variant":[
        "Chia-sung",
        "Chia-sung-chen",
        "Jiasong"
    ],
    "wof:name":"Jiasong",
    "wof:placetype":"locality"
},
  "geometry": {"coordinates":[112.06694,32.94333],"type":"Point"}
}