{
  "type": "Feature",
  "properties": {
    "gn:admin1_code":"29.0",
    "gn:asciiname":"Yangjia Wuji",
    "gn:country_code":"CN",
    "gn:dem":3029,
    "gn:feature_class":"P",
    "gn:feature_code":"PPL",
    "gn:name":"Yangjia Wuji",
    "gn:population":0,
    "gn:timezone":"Asia/Shanghai",
    "iso:country":"CN",
    "name:zho_x_preferred":[
        "\u6768\u5bb6\u5c4b\u57fa"
    ],
    "wof:name":"Yangjia Wuji",
    "wof:placetype":"locality"
},
  "geometry": {"coordinates":[100.977,27.3081],"type":"Point"}
}