{
  "type": "Feature",
  "properties": {
    "gn:admin1_code":"10.0",
    "gn:asciiname":"Dongbalizhuang",
    "gn:country_code":"CN",
    "gn:dem":16,
    "gn:feature_class":"P",
    "gn:feature_code":"PPL",
    "gn:name":"Dongbalizhuang",
    "gn:population":0,
    "gn:timezone":"Asia/Shanghai",
    "iso:country":"CN",
    "name:zho_x_preferred":[
        "\u4e1c\u516b\u91cc\u5e84"
    ],
    "wof:name":"Dongbalizhuang",
    "wof:placetype":"locality"
},
  "geometry": {"coordinates":[116.50454000000001,39.35382],"type":"Point"}
}