{
  "type": "Feature",
  "properties": {
    "gn:admin1_code":"2.0",
    "gn:asciiname":"Dakan",
    "gn:country_code":"CN",
    "gn:dem":221,
    "gn:feature_class":"P",
    "gn:feature_code":"PPL",
    "gn:name":"Dakan",
    "gn:population":0,
    "gn:timezone":"Asia/Shanghai",
    "iso:country":"CN",
    "name:und_x_variant":[
        "\u5927\u574e",
        "Dakan"
    ],
    "wof:name":"Dakan",
    "wof:placetype":"locality"
},
  "geometry": {"coordinates":[119.90208,29.63027],"type":"Point"}
}