{
  "type": "Feature",
  "properties": {
    "gn:admin1_code":"7.0",
    "gn:asciiname":"Zhuchouling",
    "gn:country_code":"CN",
    "gn:dem":958,
    "gn:feature_class":"P",
    "gn:feature_code":"PPL",
    "gn:name":"Zhuchouling",
    "gn:population":0,
    "gn:timezone":"Asia/Shanghai",
    "iso:country":"CN",
    "name:zho_x_preferred":[
        "\u73e0\u7a20\u5cad"
    ],
    "wof:name":"Zhuchouling",
    "wof:placetype":"locality"
},
  "geometry": {"coordinates":[117.57234,27.93725],"type":"Point"}
}