{
  "type": "Feature",
  "properties": {
    "gn:admin1_code":"11.0",
    "gn:asciiname":"Tuma'ao",
    "gn:country_code":"CN",
    "gn:dem":103,
    "gn:feature_class":"P",
    "gn:feature_code":"PPL",
    "gn:name":"Tuma\u2019ao",
    "gn:population":0,
    "gn:timezone":"Asia/Shanghai",
    "iso:country":"CN",
    "name:und_x_variant":[
        "Tuma\u2019ao"
    ],
    "name:zho_x_preferred":[
        "\u571f\u9a6c\u5773"
    ],
    "wof:name":"Tuma'ao",
    "wof:placetype":"locality"
},
  "geometry": {"coordinates":[113.2816,29.38295],"type":"Point"}
}