{
  "type": "Feature",
  "properties": {
    "gn:admin1_code":"29.0",
    "gn:asciiname":"Zongqichang",
    "gn:country_code":"CN",
    "gn:dem":1724,
    "gn:feature_class":"P",
    "gn:feature_code":"PPL",
    "gn:name":"Zongqichang",
    "gn:population":0,
    "gn:timezone":"Asia/Shanghai",
    "iso:country":"CN",
    "name:zho_x_preferred":[
        "\u5b97\u65d7\u5382"
    ],
    "wof:name":"Zongqichang",
    "wof:placetype":"locality"
},
  "geometry": {"coordinates":[100.271,25.2973],"type":"Point"}
}