{
  "type": "Feature",
  "properties": {
    "gn:admin1_code":"4.0",
    "gn:asciiname":"Liushijing",
    "gn:country_code":"CN",
    "gn:dem":3,
    "gn:feature_class":"P",
    "gn:feature_code":"PPL",
    "gn:name":"Liushijing",
    "gn:population":0,
    "gn:timezone":"Asia/Shanghai",
    "iso:country":"CN",
    "name:und_x_variant":[
        "\u516d\u65f6\u6cfe"
    ],
    "wof:name":"Liushijing",
    "wof:placetype":"locality"
},
  "geometry": {"coordinates":[121.08528,31.35502],"type":"Point"}
}