{
  "type": "Feature",
  "properties": {
    "gn:admin1_code":"24.0",
    "gn:asciiname":"Yuantashan",
    "gn:country_code":"CN",
    "gn:dem":1107,
    "gn:feature_class":"P",
    "gn:feature_code":"PPL",
    "gn:name":"Yuantashan",
    "gn:population":0,
    "gn:timezone":"Asia/Shanghai",
    "iso:country":"CN",
    "name:zho_x_preferred":[
        "\u8881\u5854\u5c71"
    ],
    "wof:name":"Yuantashan",
    "wof:placetype":"locality"
},
  "geometry": {"coordinates":[110.83723999999999,35.81303],"type":"Point"}
}