{
  "type": "Feature",
  "properties": {
    "gn:admin1_code":"4.0",
    "gn:asciiname":"Jiangwancun",
    "gn:country_code":"CN",
    "gn:dem":1,
    "gn:feature_class":"P",
    "gn:feature_code":"PPL",
    "gn:name":"Jiangwancun",
    "gn:population":0,
    "gn:timezone":"Asia/Shanghai",
    "iso:country":"CN",
    "name:und_x_variant":[
        "\u6c5f\u6e7e\u6751"
    ],
    "name:zho_x_preferred":[
        "\u6c5f\u6e7e\u6751"
    ],
    "wof:name":"Jiangwancun",
    "wof:placetype":"locality"
},
  "geometry": {"coordinates":[120.74811,31.23273],"type":"Point"}
}