{
  "type": "Feature",
  "properties": {
    "gn:admin1_code":"7",
    "gn:asciiname":"Zhucaotan",
    "gn:country_code":"CN",
    "gn:dem":358,
    "gn:feature_class":"P",
    "gn:feature_code":"PPL",
    "gn:name":"Zhucaotan",
    "gn:population":0,
    "gn:timezone":"Asia/Shanghai",
    "iso:country":"CN",
    "name:zho_x_preferred":[
        "\u732a\u69fd\u6f6d"
    ],
    "wof:name":"Zhucaotan",
    "wof:placetype":"locality"
},
  "geometry": {"coordinates":[117.02075000000001,24.21272],"type":"Point"}
}