{
  "type": "Feature",
  "properties": {
    "gn:admin1_code":"4.0",
    "gn:asciiname":"Yuweiqiao",
    "gn:country_code":"CN",
    "gn:dem":1,
    "gn:feature_class":"P",
    "gn:feature_code":"PPL",
    "gn:name":"Yuweiqiao",
    "gn:population":0,
    "gn:timezone":"Asia/Shanghai",
    "iso:country":"CN",
    "name:zho_x_preferred":[
        "Yuweiqiao"
    ],
    "name:zho_x_variant":[
        "\u9c7c\u5c3e\u6865"
    ],
    "wof:name":"Yuweiqiao",
    "wof:placetype":"locality"
},
  "geometry": {"coordinates":[119.38733999999999,33.2933],"type":"Point"}
}