{
  "type": "Feature",
  "properties": {
    "gn:admin1_code":"29.0",
    "gn:asciiname":"Zhamozhai",
    "gn:country_code":"CN",
    "gn:dem":1662,
    "gn:feature_class":"P",
    "gn:feature_code":"PPL",
    "gn:name":"Zhamozhai",
    "gn:population":0,
    "gn:timezone":"Asia/Shanghai",
    "iso:country":"CN",
    "name:zho_x_preferred":[
        "\u624e\u83ab\u5be8"
    ],
    "wof:name":"Zhamozhai",
    "wof:placetype":"locality"
},
  "geometry": {"coordinates":[100.056,22.9238],"type":"Point"}
}