{
  "type": "Feature",
  "properties": {
    "gn:admin1_code":"11.0",
    "gn:asciiname":"Yuanjiagang",
    "gn:country_code":"CN",
    "gn:dem":34,
    "gn:feature_class":"P",
    "gn:feature_code":"PPL",
    "gn:name":"Yuanjiagang",
    "gn:population":0,
    "gn:timezone":"Asia/Shanghai",
    "iso:country":"CN",
    "name:zho_x_preferred":[
        "Yuanjiagang"
    ],
    "name:zho_x_variant":[
        "\u8881\u5bb6\u6e2f"
    ],
    "wof:name":"Yuanjiagang",
    "wof:placetype":"locality"
},
  "geometry": {"coordinates":[111.85996000000002,29.73802],"type":"Point"}
}