{
  "type": "Feature",
  "properties": {
    "gn:admin1_code":"25.0",
    "gn:asciiname":"Maojiabu",
    "gn:country_code":"CN",
    "gn:dem":17,
    "gn:feature_class":"P",
    "gn:feature_code":"PPL",
    "gn:name":"Maojiabu",
    "gn:population":0,
    "gn:timezone":"Asia/Shanghai",
    "iso:country":"CN",
    "name:zho_x_preferred":[
        "\u6bdb\u5bb6\u57e0"
    ],
    "wof:name":"Maojiabu",
    "wof:placetype":"locality"
},
  "geometry": {"coordinates":[119.24836000000001,36.78585],"type":"Point"}
}