{
  "type": "Feature",
  "properties": {
    "gn:admin1_code":"4.0",
    "gn:asciiname":"Wuhu",
    "gn:country_code":"CN",
    "gn:dem":5,
    "gn:feature_class":"P",
    "gn:feature_code":"PPL",
    "gn:name":"Wuhu",
    "gn:population":0,
    "gn:timezone":"Asia/Shanghai",
    "iso:country":"CN",
    "name:afr_x_preferred":[
        "Wuhu"
    ],
    "name:ara_x_preferred":[
        "\u0648\u0648\u0647\u0648"
    ],
    "name:bul_x_preferred":[
        "\u0423\u0445\u0443"
    ],
    "name:cdo_x_preferred":[
        "\u00d9-h\u00f9"
    ],
    "name:ceb_x_preferred":[
        "Wuhu Shi"
    ],
    "name:ces_x_preferred":[
        "Wu-chu"
    ],
    "name:cym_x_preferred":[
        "Wuhu"
    ],
    "name:dan_x_preferred":[
        "Wuhu"
    ],
    "name:deu_x_preferred":[
        "Wuhu"
    ],
    "name:epo_x_preferred":[
        "Vu\u0125u"
    ],
    "name:eus_x_preferred":[
        "Wuhu"
    ],
    "name:fas_x_preferred":[
        "\u0648\u0627\u0647\u0627"
    ],
    "name:fin_x_preferred":[
        "Wuhu"
    ],
    "name:fra_x_preferred":[
        "Wuhu"
    ],
    "name:heb_x_preferred":[
        "\u05d5\u05d5\u05d4\u05d5"
    ],
    "name:hye_x_preferred":[
        "\u054e\u0578\u0582\u0570\u0578\u0582"
    ],
    "name:ita_x_preferred":[
        "Wuhu"
    ],
    "name:jpn_x_preferred":[
        "\u856a\u6e56\u5e02"
    ],
    "name:kik_x_preferred":[
        "Wuhu"
    ],
    "name:kor_x_preferred":[
        "\uc6b0\ud6c4\uc2dc"
    ],
    "name:lit_x_preferred":[
        "Uhu"
    ],
    "name:mal_x_preferred":[
        "\u0d35\u0d41\u0d39\u0d41"
    ],
    "name:mlg_x_preferred":[
        "Wuhu"
    ],
    "name:mwl_x_preferred":[
        "Wuhu"
    ],
    "name:nld_x_preferred":[
        "Wuhu"
    ],
    "name:nno_x_preferred":[
        "Wuhu"
    ],
    "name:nor_x_preferred":[
        "Wuhu"
    ],
    "name:pam_x_preferred":[
        "Wuhu"
    ],
    "name:pnb_x_preferred":[
        "\u0648\u0648\u06c1\u0648"
    ],
    "name:pol_x_preferred":[
        "Wuhu"
    ],
    "name:por_x_preferred":[
        "Wuhu"
    ],
    "name:rus_x_preferred":[
        "\u0423\u0445\u0443"
    ],
    "name:spa_x_preferred":[
        "Wuhu"
    ],
    "name:srp_x_preferred":[
        "\u0412\u0443\u0445\u0443"
    ],
    "name:swe_x_preferred":[
        "Wuhu"
    ],
    "name:tam_x_preferred":[
        "\u0b89\u0b95\u0bc1"
    ],
    "name:tgl_x_preferred":[
        "Wuhu"
    ],
    "name:tur_x_preferred":[
        "Wuhu"
    ],
    "name:urd_x_preferred":[
        "\u0648\u0648\u06c1\u0648"
    ],
    "name:vie_x_preferred":[
        "Vu H\u1ed3"
    ],
    "name:war_x_preferred":[
        "Wuhu"
    ],
    "name:wuu_x_preferred":[
        "\u829c\u6e56\u5e02"
    ],
    "name:zho_x_preferred":[
        "\u4e94\u864e"
    ],
    "name:zho_x_variant":[
        "\u829c\u6e56\u5e02"
    ],
    "wof:name":"Wuhu",
    "wof:placetype":"locality"
},
  "geometry": {"coordinates":[120.78473,32.54959],"type":"Point"}
}