{
  "type": "Feature",
  "properties": {
    "gn:admin1_code":"29.0",
    "gn:asciiname":"Xiaseguande",
    "gn:country_code":"CN",
    "gn:dem":1861,
    "gn:feature_class":"P",
    "gn:feature_code":"PPL",
    "gn:name":"Xiaseguande",
    "gn:population":0,
    "gn:timezone":"Asia/Shanghai",
    "iso:country":"CN",
    "name:zho_x_preferred":[
        "\u4e0b\u8272\u5b98\u5f97"
    ],
    "wof:name":"Xiaseguande",
    "wof:placetype":"locality"
},
  "geometry": {"coordinates":[103.801,26.5015],"type":"Point"}
}