{
  "type": "Feature",
  "properties": {
    "gn:admin1_code":"26",
    "gn:asciiname":"Dangjiawan",
    "gn:cc2":"CN",
    "gn:country_code":"CN",
    "gn:dem":980,
    "gn:feature_class":"P",
    "gn:feature_code":"PPL",
    "gn:name":"Dangjiawan",
    "gn:population":0,
    "gn:timezone":"Asia/Shanghai",
    "iso:country":"CN",
    "name:und_x_variant":[
        "Tang-chia-wan",
        "Dangjiawan"
    ],
    "wof:name":"Dangjiawan",
    "wof:placetype":"locality"
},
  "geometry": {"coordinates":[109.02249999999999,35.9725],"type":"Point"}
}