{
  "type": "Feature",
  "properties": {
    "gn:admin1_code":"10.0",
    "gn:asciiname":"Gaojialiang",
    "gn:country_code":"CN",
    "gn:dem":914,
    "gn:feature_class":"P",
    "gn:feature_code":"PPL",
    "gn:name":"Gaojialiang",
    "gn:population":0,
    "gn:timezone":"Asia/Shanghai",
    "iso:country":"CN",
    "name:zho_x_preferred":[
        "\u90dc\u5bb6\u6881"
    ],
    "wof:name":"Gaojialiang",
    "wof:placetype":"locality"
},
  "geometry": {"coordinates":[115.50217000000001,40.19287],"type":"Point"}
}