{
  "type": "Feature",
  "properties": {
    "gn:admin1_code":"12.0",
    "gn:asciiname":"Laocha",
    "gn:country_code":"CN",
    "gn:dem":564,
    "gn:feature_class":"P",
    "gn:feature_code":"PPL",
    "gn:name":"Laocha",
    "gn:population":0,
    "gn:timezone":"Asia/Shanghai",
    "iso:country":"CN",
    "name:zho_x_preferred":[
        "Laocha"
    ],
    "name:zho_x_variant":[
        "\u8001\u8336"
    ],
    "wof:name":"Laocha",
    "wof:placetype":"locality"
},
  "geometry": {"coordinates":[109.39915000000001,29.58219],"type":"Point"}
}