{
  "type": "Feature",
  "properties": {
    "gn:admin1_code":"9.0",
    "gn:asciiname":"Donglihe",
    "gn:country_code":"CN",
    "gn:dem":155,
    "gn:feature_class":"P",
    "gn:feature_code":"PPL",
    "gn:name":"Donglihe",
    "gn:population":0,
    "gn:timezone":"Asia/Shanghai",
    "iso:country":"CN",
    "name:zho_x_preferred":[
        "\u4e1c\u674e\u6cb3"
    ],
    "wof:name":"Donglihe",
    "wof:placetype":"locality"
},
  "geometry": {"coordinates":[111.78527,32.60346],"type":"Point"}
}