{
  "type": "Feature",
  "properties": {
    "gn:admin1_code":"25",
    "gn:asciiname":"Yuepengcun",
    "gn:country_code":"CN",
    "gn:dem":324,
    "gn:feature_class":"P",
    "gn:feature_code":"PPL",
    "gn:name":"Yuepengcun",
    "gn:population":0,
    "gn:timezone":"Asia/Shanghai",
    "iso:country":"CN",
    "name:zho_x_preferred":[
        "\u8d8a\u68da\u6751"
    ],
    "wof:name":"Yuepengcun",
    "wof:placetype":"locality"
},
  "geometry": {"coordinates":[117.426,35.2708],"type":"Point"}
}