{
  "type": "Feature",
  "properties": {
    "gn:admin1_code":"8.0",
    "gn:asciiname":"Xiqiangcun",
    "gn:country_code":"CN",
    "gn:dem":157,
    "gn:feature_class":"P",
    "gn:feature_code":"PPL",
    "gn:name":"Xiqiangcun",
    "gn:population":0,
    "gn:timezone":"Asia/Shanghai",
    "iso:country":"CN",
    "name:zho_x_preferred":[
        "\u5e0c\u5f3a\u6751"
    ],
    "wof:name":"Xiqiangcun",
    "wof:placetype":"locality"
},
  "geometry": {"coordinates":[126.04424,45.28794],"type":"Point"}
}