{
  "type": "Feature",
  "properties": {
    "gn:admin1_code":"3.0",
    "gn:asciiname":"Jingtouwu",
    "gn:country_code":"CN",
    "gn:dem":569,
    "gn:feature_class":"P",
    "gn:feature_code":"PPL",
    "gn:name":"Jingtouwu",
    "gn:population":0,
    "gn:timezone":"Asia/Shanghai",
    "iso:country":"CN",
    "name:und_x_variant":[
        "\u4e95\u5934\u575e"
    ],
    "wof:name":"Jingtouwu",
    "wof:placetype":"locality"
},
  "geometry": {"coordinates":[115.60892,26.36517000000001],"type":"Point"}
}