{
  "type": "Feature",
  "properties": {
    "gn:admin1_code":"32.0",
    "gn:asciiname":"Heluoba",
    "gn:country_code":"CN",
    "gn:dem":735,
    "gn:feature_class":"P",
    "gn:feature_code":"PPL",
    "gn:name":"Heluoba",
    "gn:population":0,
    "gn:timezone":"Asia/Shanghai",
    "iso:country":"CN",
    "name:zho_x_preferred":[
        "\u4f55\u7f57\u575d"
    ],
    "wof:name":"Heluoba",
    "wof:placetype":"locality"
},
  "geometry": {"coordinates":[105.15597,32.17816],"type":"Point"}
}