{
  "type": "Feature",
  "properties": {
    "gn:admin1_code":"19.0",
    "gn:asciiname":"Hengjietun",
    "gn:country_code":"CN",
    "gn:dem":189,
    "gn:feature_class":"P",
    "gn:feature_code":"PPL",
    "gn:name":"Hengjietun",
    "gn:population":0,
    "gn:timezone":"Asia/Shanghai",
    "iso:country":"CN",
    "name:zho_x_preferred":[
        "\u6a2a\u8857\u5c6f"
    ],
    "wof:name":"Hengjietun",
    "wof:placetype":"locality"
},
  "geometry": {"coordinates":[124.61154000000001,42.76602000000001],"type":"Point"}
}