{
  "type": "Feature",
  "properties": {
    "gn:admin1_code":"24",
    "gn:asciiname":"Fengnaizhuang",
    "gn:cc2":"CN",
    "gn:country_code":"CN",
    "gn:dem":1472,
    "gn:feature_class":"P",
    "gn:feature_code":"PPL",
    "gn:name":"Fengnaizhuang",
    "gn:population":0,
    "gn:timezone":"Asia/Shanghai",
    "iso:country":"CN",
    "name:und_x_variant":[
        "Feng-nai-chuang",
        "Fengnaizhuang"
    ],
    "wof:name":"Fengnaizhuang",
    "wof:placetype":"locality"
},
  "geometry": {"coordinates":[114.40000000000001,40.31667],"type":"Point"}
}