{
  "type": "Feature",
  "properties": {
    "gn:admin1_code":"21.0",
    "gn:asciiname":"Xiwa",
    "gn:country_code":"CN",
    "gn:dem":1726,
    "gn:feature_class":"P",
    "gn:feature_code":"PPL",
    "gn:name":"Xiwa",
    "gn:population":0,
    "gn:timezone":"Asia/Shanghai",
    "iso:country":"CN",
    "name:zho_x_preferred":[
        "\u897f\u6d3c"
    ],
    "wof:name":"Xiwa",
    "wof:placetype":"locality"
},
  "geometry": {"coordinates":[105.98999999999999,36.6557],"type":"Point"}
}