{
  "type": "Feature",
  "properties": {
    "gn:admin1_code":"30.0",
    "gn:asciiname":"Xiyuanxin",
    "gn:country_code":"CN",
    "gn:dem":13,
    "gn:feature_class":"P",
    "gn:feature_code":"PPL",
    "gn:name":"Xiyuanxin",
    "gn:population":0,
    "gn:timezone":"Asia/Shanghai",
    "iso:country":"CN",
    "name:zho_x_preferred":[
        "\u897f\u5712\u65b0"
    ],
    "wof:name":"Xiyuanxin",
    "wof:placetype":"locality"
},
  "geometry": {"coordinates":[113.02139,22.52372],"type":"Point"}
}