{
  "type": "Feature",
  "properties": {
    "gn:admin1_code":"29.0",
    "gn:asciiname":"Da'aba",
    "gn:country_code":"CN",
    "gn:dem":1405,
    "gn:feature_class":"P",
    "gn:feature_code":"PPL",
    "gn:name":"Da\u2019aba",
    "gn:population":0,
    "gn:timezone":"Asia/Shanghai",
    "iso:country":"CN",
    "name:und_x_variant":[
        "Da\u2019aba"
    ],
    "name:zho_x_preferred":[
        "\u5927\u963f\u5df4"
    ],
    "wof:name":"Da'aba",
    "wof:placetype":"locality"
},
  "geometry": {"coordinates":[102.00700000000001,22.8985],"type":"Point"}
}