{
  "type": "Feature",
  "properties": {
    "gn:admin1_code":"15.0",
    "gn:asciiname":"Huangyangtou",
    "gn:country_code":"CN",
    "gn:dem":1621,
    "gn:feature_class":"P",
    "gn:feature_code":"PPL",
    "gn:name":"Huangyangtou",
    "gn:population":0,
    "gn:timezone":"Asia/Shanghai",
    "iso:country":"CN",
    "name:zho_x_preferred":[
        "\u9ec4\u7f8a\u5934"
    ],
    "wof:name":"Huangyangtou",
    "wof:placetype":"locality"
},
  "geometry": {"coordinates":[103.589,36.1824],"type":"Point"}
}