{
  "type": "Feature",
  "properties": {
    "gn:admin1_code":"24.0",
    "gn:asciiname":"Sha'aoli",
    "gn:country_code":"CN",
    "gn:dem":1378,
    "gn:feature_class":"P",
    "gn:feature_code":"PPL",
    "gn:name":"Sha\u2019aoli",
    "gn:population":0,
    "gn:timezone":"Asia/Shanghai",
    "iso:country":"CN",
    "name:und_x_variant":[
        "Sha\u2019aoli"
    ],
    "name:zho_x_preferred":[
        "\u6c99\u51f9\u91cc"
    ],
    "wof:name":"Sha'aoli",
    "wof:placetype":"locality"
},
  "geometry": {"coordinates":[111.38861,36.46093],"type":"Point"}
}