{
  "type": "Feature",
  "properties": {
    "gn:admin1_code":"15.0",
    "gn:asciiname":"Shangchi",
    "gn:country_code":"CN",
    "gn:dem":1593,
    "gn:feature_class":"P",
    "gn:feature_code":"PPL",
    "gn:name":"Shangchi",
    "gn:population":0,
    "gn:timezone":"Asia/Shanghai",
    "iso:country":"CN",
    "name:zho_x_preferred":[
        "\u4e0a\u6c60"
    ],
    "wof:name":"Shangchi",
    "wof:placetype":"locality"
},
  "geometry": {"coordinates":[105.563,34.681],"type":"Point"}
}