{
  "type": "Feature",
  "properties": {
    "gn:admin1_code":"3.0",
    "gn:asciiname":"Chengjiang",
    "gn:country_code":"CN",
    "gn:dem":344,
    "gn:feature_class":"P",
    "gn:feature_code":"PPL",
    "gn:name":"Chengjiang",
    "gn:population":0,
    "gn:timezone":"Asia/Shanghai",
    "iso:country":"CN",
    "name:und_x_variant":[
        "\u6f84\u6c5f"
    ],
    "wof:name":"Chengjiang",
    "wof:placetype":"locality"
},
  "geometry": {"coordinates":[114.53821000000001,24.6901],"type":"Point"}
}