{
  "type": "Feature",
  "properties": {
    "gn:admin1_code":"14.0",
    "gn:asciiname":"Lamugangku",
    "gn:country_code":"CN",
    "gn:dem":4657,
    "gn:feature_class":"P",
    "gn:feature_code":"PPL",
    "gn:name":"Lamugangku",
    "gn:population":0,
    "gn:timezone":"Asia/Urumqi",
    "iso:country":"CN",
    "name:zho_x_preferred":[
        "\u62c9\u6bcd\u5c97\u54ed"
    ],
    "wof:name":"Lamugangku",
    "wof:placetype":"locality"
},
  "geometry": {"coordinates":[90.25779,29.97469],"type":"Point"}
}