{
  "type": "Feature",
  "properties": {
    "gn:admin1_code":"24.0",
    "gn:asciiname":"Fanzhai",
    "gn:country_code":"CN",
    "gn:dem":1054,
    "gn:feature_class":"P",
    "gn:feature_code":"PPL",
    "gn:name":"Fanzhai",
    "gn:population":0,
    "gn:timezone":"Asia/Shanghai",
    "iso:country":"CN",
    "name:zho_x_preferred":[
        "\u8303\u5be8"
    ],
    "wof:name":"Fanzhai",
    "wof:placetype":"locality"
},
  "geometry": {"coordinates":[112.11216,36.12895],"type":"Point"}
}