{
  "type": "Feature",
  "properties": {
    "gn:admin1_code":"24.0",
    "gn:asciiname":"Beishangzhuangcun",
    "gn:country_code":"CN",
    "gn:dem":1392,
    "gn:feature_class":"P",
    "gn:feature_code":"PPL",
    "gn:name":"Beishangzhuangcun",
    "gn:population":0,
    "gn:timezone":"Asia/Shanghai",
    "iso:country":"CN",
    "name:zho_x_preferred":[
        "\u5317\u4e0a\u5e84\u6751"
    ],
    "wof:name":"Beishangzhuangcun",
    "wof:placetype":"locality"
},
  "geometry": {"coordinates":[114.37269000000001,39.60578],"type":"Point"}
}