{
  "type": "Feature",
  "properties": {
    "gn:admin1_code":"25.0",
    "gn:asciiname":"Muyucun",
    "gn:country_code":"CN",
    "gn:dem":33,
    "gn:feature_class":"P",
    "gn:feature_code":"PPL",
    "gn:name":"Muyucun",
    "gn:population":0,
    "gn:timezone":"Asia/Shanghai",
    "iso:country":"CN",
    "name:zho_x_preferred":[
        "\u6c90\u6d74\u6751"
    ],
    "wof:name":"Muyucun",
    "wof:placetype":"locality"
},
  "geometry": {"coordinates":[121.35032,37.33281],"type":"Point"}
}