{
  "type": "Feature",
  "properties": {
    "gn:admin1_code":"11.0",
    "gn:asciiname":"Pubanxi",
    "gn:country_code":"CN",
    "gn:dem":533,
    "gn:feature_class":"P",
    "gn:feature_code":"PPL",
    "gn:name":"Pubanxi",
    "gn:population":0,
    "gn:timezone":"Asia/Shanghai",
    "iso:country":"CN",
    "name:zho_x_preferred":[
        "\u84b2\u677f\u6eaa"
    ],
    "wof:name":"Pubanxi",
    "wof:placetype":"locality"
},
  "geometry": {"coordinates":[110.65384,27.33119000000001],"type":"Point"}
}