{
  "type": "Feature",
  "properties": {
    "gn:admin1_code":"11.0",
    "gn:asciiname":"Helong",
    "gn:country_code":"CN",
    "gn:dem":279,
    "gn:feature_class":"P",
    "gn:feature_code":"PPL",
    "gn:name":"Helong",
    "gn:population":0,
    "gn:timezone":"Asia/Shanghai",
    "iso:country":"CN",
    "name:ara_x_preferred":[
        "\u0647\u0644\u0648\u0646\u063a"
    ],
    "name:ceb_x_preferred":[
        "Helong"
    ],
    "name:deu_x_preferred":[
        "Helong"
    ],
    "name:fra_x_preferred":[
        "Helong"
    ],
    "name:ita_x_preferred":[
        "Helong"
    ],
    "name:jpn_x_preferred":[
        "\u548c\u7adc\u5e02"
    ],
    "name:kik_x_preferred":[
        "Helong"
    ],
    "name:kor_x_preferred":[
        "\ud5c8\ub8fd\uc2dc"
    ],
    "name:mlg_x_preferred":[
        "Helong"
    ],
    "name:nld_x_preferred":[
        "Helong"
    ],
    "name:nor_x_preferred":[
        "Helong"
    ],
    "name:pol_x_preferred":[
        "Helong"
    ],
    "name:rus_x_preferred":[
        "\u0425\u044d\u043b\u0443\u043d"
    ],
    "name:swe_x_preferred":[
        "Helong"
    ],
    "name:urd_x_preferred":[
        "\u06c1\u06cc\u0644\u0648\u0646\u06af"
    ],
    "name:vie_x_preferred":[
        "H\u00f2a Long"
    ],
    "name:zho_x_preferred":[
        "\u5408\u9f99"
    ],
    "name:zho_x_variant":[
        "\u548c\u9f99\u5e02"
    ],
    "wof:name":"Helong",
    "wof:placetype":"locality"
},
  "geometry": {"coordinates":[111.00028,27.14674],"type":"Point"}
}