{
  "type": "Feature",
  "properties": {
    "gn:admin1_code":"11.0",
    "gn:asciiname":"Jianjiayu",
    "gn:country_code":"CN",
    "gn:dem":247,
    "gn:feature_class":"P",
    "gn:feature_code":"PPL",
    "gn:name":"Jianjiayu",
    "gn:population":0,
    "gn:timezone":"Asia/Shanghai",
    "iso:country":"CN",
    "name:zho_x_preferred":[
        "Jianjiayu"
    ],
    "name:zho_x_variant":[
        "\u7b80\u5bb6\u5cea"
    ],
    "wof:name":"Jianjiayu",
    "wof:placetype":"locality"
},
  "geometry": {"coordinates":[110.87528,28.9784],"type":"Point"}
}