{
  "type": "Feature",
  "properties": {
    "gn:admin1_code":"3.0",
    "gn:asciiname":"Caijiayuan",
    "gn:country_code":"CN",
    "gn:dem":29,
    "gn:feature_class":"P",
    "gn:feature_code":"PPL",
    "gn:name":"Caijiayuan",
    "gn:population":0,
    "gn:timezone":"Asia/Shanghai",
    "iso:country":"CN",
    "name:zho_x_preferred":[
        "\u8d22\u5bb6\u6e90"
    ],
    "wof:name":"Caijiayuan",
    "wof:placetype":"locality"
},
  "geometry": {"coordinates":[117.01264,28.90494],"type":"Point"}
}