{
  "type": "Feature",
  "properties": {
    "gn:admin1_code":"24.0",
    "gn:asciiname":"Quanzipo",
    "gn:country_code":"CN",
    "gn:dem":1614,
    "gn:feature_class":"P",
    "gn:feature_code":"PPL",
    "gn:name":"Quanzipo",
    "gn:population":0,
    "gn:timezone":"Asia/Shanghai",
    "iso:country":"CN",
    "name:und_x_variant":[
        "\u6cc9\u5b50\u5761"
    ],
    "wof:name":"Quanzipo",
    "wof:placetype":"locality"
},
  "geometry": {"coordinates":[112.05755000000001,39.80231],"type":"Point"}
}