{
  "type": "Feature",
  "properties": {
    "gn:admin1_code":"07",
    "gn:asciiname":"Shangbian Lingkeng",
    "gn:country_code":"CN",
    "gn:dem":682,
    "gn:feature_class":"P",
    "gn:feature_code":"PPL",
    "gn:name":"Shangbian Lingkeng",
    "gn:population":0,
    "gn:timezone":"Asia/Shanghai",
    "iso:country":"CN",
    "name:zho_x_preferred":[
        "\u4e0a\u6241\u5cad\u5751"
    ],
    "wof:name":"Shangbian Lingkeng",
    "wof:placetype":"locality"
},
  "geometry": {"coordinates":[117.13977,25.41219],"type":"Point"}
}