{
  "type": "Feature",
  "properties": {
    "gn:admin1_code":"4.0",
    "gn:asciiname":"Hangfang",
    "gn:country_code":"CN",
    "gn:dem":0,
    "gn:feature_class":"P",
    "gn:feature_code":"PPL",
    "gn:name":"Hangfang",
    "gn:population":0,
    "gn:timezone":"Asia/Shanghai",
    "iso:country":"CN",
    "name:zho_x_preferred":[
        "Hangfang"
    ],
    "name:zho_x_variant":[
        "\u676d\u623f"
    ],
    "wof:name":"Hangfang",
    "wof:placetype":"locality"
},
  "geometry": {"coordinates":[120.11409999999999,34.14894],"type":"Point"}
}