{
  "type": "Feature",
  "properties": {
    "gn:admin1_code":"19.0",
    "gn:asciiname":"Wangjiakanzi",
    "gn:country_code":"CN",
    "gn:dem":11,
    "gn:feature_class":"P",
    "gn:feature_code":"PPL",
    "gn:name":"Wangjiakanzi",
    "gn:population":0,
    "gn:timezone":"Asia/Shanghai",
    "iso:country":"CN",
    "name:und_x_variant":[
        "\u738b\u5bb6\u574e\u5b50"
    ],
    "name:zho_x_preferred":[
        "\u738b\u5bb6\u574e\u5b50"
    ],
    "wof:name":"Wangjiakanzi",
    "wof:placetype":"locality"
},
  "geometry": {"coordinates":[121.57599999999999,39.6478],"type":"Point"}
}