{
  "type": "Feature",
  "properties": {
    "gn:admin1_code":"16.0",
    "gn:asciiname":"Nongfa",
    "gn:country_code":"CN",
    "gn:dem":427,
    "gn:feature_class":"P",
    "gn:feature_code":"PPL",
    "gn:name":"Nongfa",
    "gn:population":0,
    "gn:timezone":"Asia/Shanghai",
    "iso:country":"CN",
    "name:zho_x_preferred":[
        "\u5f04\u53d1"
    ],
    "wof:name":"Nongfa",
    "wof:placetype":"locality"
},
  "geometry": {"coordinates":[107.28700000000001,24.2247],"type":"Point"}
}