{
  "type": "Feature",
  "properties": {
    "gn:admin1_code":"29",
    "gn:asciiname":"Reshuitang",
    "gn:country_code":"CN",
    "gn:dem":1203,
    "gn:feature_class":"P",
    "gn:feature_code":"PPL",
    "gn:name":"Reshuitang",
    "gn:population":0,
    "gn:timezone":"Asia/Shanghai",
    "iso:country":"CN",
    "name:zho_x_preferred":[
        "\u70ed\u6c34\u5858"
    ],
    "wof:name":"Reshuitang",
    "wof:placetype":"locality"
},
  "geometry": {"coordinates":[103.14053,24.16764],"type":"Point"}
}