{
  "type": "Feature",
  "properties": {
    "gn:admin1_code":"16.0",
    "gn:asciiname":"Jiuling",
    "gn:country_code":"CN",
    "gn:dem":1047,
    "gn:feature_class":"P",
    "gn:feature_code":"PPL",
    "gn:name":"Jiuling",
    "gn:population":0,
    "gn:timezone":"Asia/Shanghai",
    "iso:country":"CN",
    "name:zho_x_preferred":[
        "\u4e5d\u5cad"
    ],
    "wof:name":"Jiuling",
    "wof:placetype":"locality"
},
  "geometry": {"coordinates":[106.55800000000001,24.6969],"type":"Point"}
}