{
  "type": "Feature",
  "properties": {
    "gn:admin1_code":"29.0",
    "gn:asciiname":"Cangshang",
    "gn:country_code":"CN",
    "gn:dem":1645,
    "gn:feature_class":"P",
    "gn:feature_code":"PPL",
    "gn:name":"Cangshang",
    "gn:population":0,
    "gn:timezone":"Asia/Shanghai",
    "iso:country":"CN",
    "name:zho_x_preferred":[
        "\u4ed3\u4e0a"
    ],
    "wof:name":"Cangshang",
    "wof:placetype":"locality"
},
  "geometry": {"coordinates":[104.001,27.4491],"type":"Point"}
}