{
  "type": "Feature",
  "properties": {
    "gn:admin1_code":"11.0",
    "gn:asciiname":"Waguchong",
    "gn:country_code":"CN",
    "gn:dem":489,
    "gn:feature_class":"P",
    "gn:feature_code":"PPL",
    "gn:name":"Waguchong",
    "gn:population":0,
    "gn:timezone":"Asia/Shanghai",
    "iso:country":"CN",
    "name:zho_x_preferred":[
        "\u6316\u53e4\u51b2"
    ],
    "wof:name":"Waguchong",
    "wof:placetype":"locality"
},
  "geometry": {"coordinates":[109.50832,27.21973],"type":"Point"}
}