{
  "type": "Feature",
  "properties": {
    "gn:admin1_code":"32.0",
    "gn:asciiname":"Yideng'amen",
    "gn:country_code":"CN",
    "gn:dem":1709,
    "gn:feature_class":"P",
    "gn:feature_code":"PPL",
    "gn:name":"Yideng\u2019amen",
    "gn:population":0,
    "gn:timezone":"Asia/Shanghai",
    "iso:country":"CN",
    "name:und_x_variant":[
        "Yideng\u2019amen"
    ],
    "name:zho_x_preferred":[
        "\u4f9d\u767b\u963f\u95e8"
    ],
    "wof:name":"Yideng'amen",
    "wof:placetype":"locality"
},
  "geometry": {"coordinates":[103.39100000000001,28.1309],"type":"Point"}
}