{
  "type": "Feature",
  "properties": {
    "gn:admin1_code":"1.0",
    "gn:asciiname":"Zhaogangcun",
    "gn:country_code":"CN",
    "gn:dem":26,
    "gn:feature_class":"P",
    "gn:feature_code":"PPL",
    "gn:name":"Zhaogangcun",
    "gn:population":0,
    "gn:timezone":"Asia/Shanghai",
    "iso:country":"CN",
    "name:zho_x_preferred":[
        "\u8d75\u5c97\u6751"
    ],
    "wof:name":"Zhaogangcun",
    "wof:placetype":"locality"
},
  "geometry": {"coordinates":[117.55268999999998,31.86356],"type":"Point"}
}