{
  "type": "Feature",
  "properties": {
    "gn:admin1_code":"24",
    "gn:asciiname":"Dongguo",
    "gn:cc2":"CN",
    "gn:country_code":"CN",
    "gn:dem":340,
    "gn:feature_class":"P",
    "gn:feature_code":"PPL",
    "gn:name":"Dongguo",
    "gn:population":0,
    "gn:timezone":"Asia/Shanghai",
    "iso:country":"CN",
    "name:und_x_variant":[
        "Tung-kuo",
        "Tung-kuo-chen",
        "Dongguo"
    ],
    "wof:name":"Dongguo",
    "wof:placetype":"locality"
},
  "geometry": {"coordinates":[111.12,35.02833],"type":"Point"}
}