{
  "type": "Feature",
  "properties": {
    "gn:admin1_code":"3.0",
    "gn:asciiname":"Tangbeicun",
    "gn:country_code":"CN",
    "gn:dem":487,
    "gn:feature_class":"P",
    "gn:feature_code":"PPL",
    "gn:name":"Tangbeicun",
    "gn:population":0,
    "gn:timezone":"Asia/Shanghai",
    "iso:country":"CN",
    "name:und_x_variant":[
        "\u5858\u80cc\u6751"
    ],
    "wof:name":"Tangbeicun",
    "wof:placetype":"locality"
},
  "geometry": {"coordinates":[115.92608,26.52734],"type":"Point"}
}