{
  "type": "Feature",
  "properties": {
    "gn:admin1_code":"8.0",
    "gn:asciiname":"Zhaoxingwutun",
    "gn:country_code":"CN",
    "gn:dem":193,
    "gn:feature_class":"P",
    "gn:feature_code":"PPL",
    "gn:name":"Zhaoxingwutun",
    "gn:population":0,
    "gn:timezone":"Asia/Shanghai",
    "iso:country":"CN",
    "name:zho_x_preferred":[
        "\u8d75\u5174\u6b66\u5c6f"
    ],
    "wof:name":"Zhaoxingwutun",
    "wof:placetype":"locality"
},
  "geometry": {"coordinates":[126.05625000000001,46.69377],"type":"Point"}
}