{
  "type": "Feature",
  "properties": {
    "gn:admin1_code":"29.0",
    "gn:asciiname":"Guangdong",
    "gn:country_code":"CN",
    "gn:dem":981,
    "gn:feature_class":"P",
    "gn:feature_code":"PPL",
    "gn:name":"Guangdong",
    "gn:population":0,
    "gn:timezone":"Asia/Shanghai",
    "iso:country":"CN",
    "name:zho_x_preferred":[
        "\u5e7f\u6d1e"
    ],
    "wof:name":"Guangdong",
    "wof:placetype":"locality"
},
  "geometry": {"coordinates":[97.94880000000001,24.3239],"type":"Point"}
}