{
  "type": "Feature",
  "properties": {
    "gn:admin1_code":"12.0",
    "gn:asciiname":"Leizhou",
    "gn:country_code":"CN",
    "gn:dem":38,
    "gn:feature_class":"P",
    "gn:feature_code":"PPL",
    "gn:name":"Leizhou",
    "gn:population":0,
    "gn:timezone":"Asia/Shanghai",
    "iso:country":"CN",
    "name:ara_x_preferred":[
        "\u0644\u064a\u0632\u0648"
    ],
    "name:deu_x_preferred":[
        "Leizhou"
    ],
    "name:fas_x_preferred":[
        "\u0644\u06cc\u0698\u0648"
    ],
    "name:fra_x_preferred":[
        "Leizhou"
    ],
    "name:hak_x_preferred":[
        "L\u00f9i-ch\u00fb-s\u1e73"
    ],
    "name:ita_x_preferred":[
        "Leizhou"
    ],
    "name:jpn_x_preferred":[
        "\u96f7\u5dde\u5e02"
    ],
    "name:kik_x_preferred":[
        "Leizhou"
    ],
    "name:kor_x_preferred":[
        "\ub808\uc774\uc800\uc6b0\uc2dc"
    ],
    "name:mwl_x_preferred":[
        "Leizhou"
    ],
    "name:nor_x_preferred":[
        "Leizhou"
    ],
    "name:pam_x_preferred":[
        "Leizhou"
    ],
    "name:pnb_x_preferred":[
        "\u0644\u06cc\u0626\u06cc\u0698\u0648\u0624"
    ],
    "name:pol_x_preferred":[
        "Leizhou"
    ],
    "name:swe_x_preferred":[
        "Leizhou"
    ],
    "name:urd_x_preferred":[
        "\u0644\u0627\u0626\u0698\u0648\u0648"
    ],
    "name:vie_x_preferred":[
        "L\u00f4i Ch\u00e2u"
    ],
    "name:zho_x_preferred":[
        "\u96f7\u6d32"
    ],
    "name:zho_x_variant":[
        "\u96f7\u5dde\u5e02"
    ],
    "wof:name":"Leizhou",
    "wof:placetype":"locality"
},
  "geometry": {"coordinates":[112.21321,30.19498],"type":"Point"}
}