{
  "type": "Feature",
  "properties": {
    "gn:admin1_code":"29.0",
    "gn:asciiname":"Edemi",
    "gn:country_code":"CN",
    "gn:dem":1883,
    "gn:feature_class":"P",
    "gn:feature_code":"PPL",
    "gn:name":"Edemi",
    "gn:population":0,
    "gn:timezone":"Asia/Shanghai",
    "iso:country":"CN",
    "name:zho_x_preferred":[
        "\u4fc4\u7684\u7c73"
    ],
    "wof:name":"Edemi",
    "wof:placetype":"locality"
},
  "geometry": {"coordinates":[100.402,27.7942],"type":"Point"}
}