{
  "type": "Feature",
  "properties": {
    "gn:admin1_code":"29",
    "gn:asciiname":"Miebu",
    "gn:country_code":"CN",
    "gn:dem":2069,
    "gn:feature_class":"P",
    "gn:feature_code":"PPL",
    "gn:name":"Miebu",
    "gn:population":0,
    "gn:timezone":"Asia/Shanghai",
    "iso:country":"CN",
    "name:zho_x_preferred":[
        "\u54a9\u54fa"
    ],
    "wof:name":"Miebu",
    "wof:placetype":"locality"
},
  "geometry": {"coordinates":[102.496,23.8522],"type":"Point"}
}