{
  "type": "Feature",
  "properties": {
    "gn:admin1_code":"26.0",
    "gn:asciiname":"Guangxingzhaicun",
    "gn:country_code":"CN",
    "gn:dem":702,
    "gn:feature_class":"P",
    "gn:feature_code":"PPL",
    "gn:name":"Guangxingzhaicun",
    "gn:population":0,
    "gn:timezone":"Asia/Shanghai",
    "iso:country":"CN",
    "name:zho_x_preferred":[
        "\u5e7f\u5174\u5be8\u6751"
    ],
    "wof:name":"Guangxingzhaicun",
    "wof:placetype":"locality"
},
  "geometry": {"coordinates":[109.13026000000001,32.46086],"type":"Point"}
}