{
  "type": "Feature",
  "properties": {
    "gn:admin1_code":"18",
    "gn:asciiname":"Guanyinshan",
    "gn:country_code":"CN",
    "gn:dem":1325,
    "gn:feature_class":"P",
    "gn:feature_code":"PPL",
    "gn:name":"Guanyinshan",
    "gn:population":0,
    "gn:timezone":"Asia/Shanghai",
    "iso:country":"CN",
    "name:zho_x_preferred":[
        "\u89c2\u97f3\u5c71"
    ],
    "wof:name":"Guanyinshan",
    "wof:placetype":"locality"
},
  "geometry": {"coordinates":[104.977,25.2474],"type":"Point"}
}