{
  "type": "Feature",
  "properties": {
    "gn:admin1_code":"29.0",
    "gn:asciiname":"Chalujie",
    "gn:country_code":"CN",
    "gn:dem":1709,
    "gn:feature_class":"P",
    "gn:feature_code":"PPL",
    "gn:name":"Chalujie",
    "gn:population":0,
    "gn:timezone":"Asia/Shanghai",
    "iso:country":"CN",
    "name:zho_x_preferred":[
        "\u5c94\u8def\u8857"
    ],
    "wof:name":"Chalujie",
    "wof:placetype":"locality"
},
  "geometry": {"coordinates":[99.70740000000001,24.5583],"type":"Point"}
}