{
  "type": "Feature",
  "properties": {
    "gn:admin1_code":"19.0",
    "gn:asciiname":"Xiaozhaizi",
    "gn:country_code":"CN",
    "gn:dem":149,
    "gn:feature_class":"P",
    "gn:feature_code":"PPL",
    "gn:name":"Xiaozhaizi",
    "gn:population":0,
    "gn:timezone":"Asia/Shanghai",
    "iso:country":"CN",
    "name:zho_x_preferred":[
        "\u5c0f\u5be8\u5b50"
    ],
    "wof:name":"Xiaozhaizi",
    "wof:placetype":"locality"
},
  "geometry": {"coordinates":[124.33546,42.23295],"type":"Point"}
}