{
  "type": "Feature",
  "properties": {
    "gn:admin1_code":"14.0",
    "gn:asciiname":"Wuma",
    "gn:country_code":"CN",
    "gn:dem":4737,
    "gn:feature_class":"P",
    "gn:feature_code":"PPL",
    "gn:name":"Wuma",
    "gn:population":0,
    "gn:timezone":"Asia/Shanghai",
    "iso:country":"CN",
    "name:und_x_variant":[
        "Wo\u2019erze",
        "Wuma"
    ],
    "name:zho_x_preferred":[
        "\u6c83\u513f\u6cfd"
    ],
    "name:zho_x_variant":[
        "\u5434\u739b"
    ],
    "wof:name":"Wuma",
    "wof:placetype":"locality"
},
  "geometry": {"coordinates":[81.36790000000001,30.7989],"type":"Point"}
}