{
  "type": "Feature",
  "properties": {
    "gn:admin1_code":"13.0",
    "gn:asciiname":"Yushugou",
    "gn:country_code":"CN",
    "gn:dem":1794,
    "gn:feature_class":"P",
    "gn:feature_code":"PPL",
    "gn:name":"Yushugou",
    "gn:population":0,
    "gn:timezone":"Asia/Urumqi",
    "iso:country":"CN",
    "name:zho_x_preferred":[
        "\u6986\u6811\u6c9f"
    ],
    "wof:name":"Yushugou",
    "wof:placetype":"locality"
},
  "geometry": {"coordinates":[93.94813000000001,43.07523],"type":"Point"}
}