{
  "type": "Feature",
  "properties": {
    "gn:admin1_code":"32.0",
    "gn:asciiname":"Dengjiashan",
    "gn:country_code":"CN",
    "gn:dem":3286,
    "gn:feature_class":"P",
    "gn:feature_code":"PPL",
    "gn:name":"Dengjiashan",
    "gn:population":0,
    "gn:timezone":"Asia/Shanghai",
    "iso:country":"CN",
    "name:zho_x_preferred":[
        "\u9093\u5bb6\u5c71"
    ],
    "wof:name":"Dengjiashan",
    "wof:placetype":"locality"
},
  "geometry": {"coordinates":[102.389,31.0376],"type":"Point"}
}