{
  "type": "Feature",
  "properties": {
    "gn:admin1_code":"29",
    "gn:asciiname":"Jiayiji",
    "gn:country_code":"CN",
    "gn:dem":1868,
    "gn:feature_class":"P",
    "gn:feature_code":"PPL",
    "gn:name":"Jiayiji",
    "gn:population":0,
    "gn:timezone":"Asia/Shanghai",
    "iso:country":"CN",
    "name:zho_x_preferred":[
        "\u7532\u4e59\u5df1"
    ],
    "wof:name":"Jiayiji",
    "wof:placetype":"locality"
},
  "geometry": {"coordinates":[102.56100000000001,23.5088],"type":"Point"}
}