{
  "type": "Feature",
  "properties": {
    "gn:admin1_code":"5.0",
    "gn:asciiname":"Banmiaozi",
    "gn:country_code":"CN",
    "gn:dem":373,
    "gn:feature_class":"P",
    "gn:feature_code":"PPL",
    "gn:name":"Banmiaozi",
    "gn:population":0,
    "gn:timezone":"Asia/Shanghai",
    "iso:country":"CN",
    "name:und_x_variant":[
        "Pan-miao"
    ],
    "name:zho_x_preferred":[
        "\u677f\u5e99\u5b50"
    ],
    "wof:name":"Banmiaozi",
    "wof:placetype":"locality"
},
  "geometry": {"coordinates":[125.40816,42.57682],"type":"Point"}
}