{
  "type": "Feature",
  "properties": {
    "gn:admin1_code":"32.0",
    "gn:asciiname":"Longwangba",
    "gn:country_code":"CN",
    "gn:dem":671,
    "gn:feature_class":"P",
    "gn:feature_code":"PPL",
    "gn:name":"Longwangba",
    "gn:population":0,
    "gn:timezone":"Asia/Shanghai",
    "iso:country":"CN",
    "name:zho_x_preferred":[
        "\u9f99\u738b\u575d"
    ],
    "wof:name":"Longwangba",
    "wof:placetype":"locality"
},
  "geometry": {"coordinates":[104.49329,29.56308],"type":"Point"}
}