{
  "type": "Feature",
  "properties": {
    "gn:admin1_code":"19.0",
    "gn:asciiname":"Sanmenliu",
    "gn:country_code":"CN",
    "gn:dem":34,
    "gn:feature_class":"P",
    "gn:feature_code":"PPL",
    "gn:name":"Sanmenliu",
    "gn:population":0,
    "gn:timezone":"Asia/Shanghai",
    "iso:country":"CN",
    "name:zho_x_preferred":[
        "\u4e09\u95e8\u5218"
    ],
    "wof:name":"Sanmenliu",
    "wof:placetype":"locality"
},
  "geometry": {"coordinates":[122.816,39.7812],"type":"Point"}
}