{
  "type": "Feature",
  "properties": {
    "gn:admin1_code":"10",
    "gn:asciiname":"Hanjialin",
    "gn:country_code":"CN",
    "gn:dem":19,
    "gn:feature_class":"P",
    "gn:feature_code":"PPL",
    "gn:name":"Hanjialin",
    "gn:population":0,
    "gn:timezone":"Asia/Shanghai",
    "iso:country":"CN",
    "name:zho_x_preferred":[
        "\u97e9\u5bb6\u6797"
    ],
    "wof:name":"Hanjialin",
    "wof:placetype":"locality"
},
  "geometry": {"coordinates":[117.81626,39.867],"type":"Point"}
}