{
  "type": "Feature",
  "properties": {
    "gn:admin1_code":"32",
    "gn:asciiname":"Chongyang",
    "gn:country_code":"CN",
    "gn:dem":535,
    "gn:feature_class":"P",
    "gn:feature_code":"PPLS",
    "gn:name":"Chongyang",
    "gn:population":0,
    "gn:timezone":"Asia/Shanghai",
    "iso:country":"CN",
    "name:und_x_variant":[
        "Ch\u2019ung-ch\u2019ing",
        "Ts\u2019ung-ch\u2019ing",
        "Ch\u2019ung-Tsin",
        "Ch\u2019ung-ch\u2019ing-hsien",
        "Chungking-hsien",
        "Chongyang"
    ],
    "name:zho_x_preferred":[
        "\u5d07\u9633"
    ],
    "wof:name":"Chongyang",
    "wof:placetype":"locality"
},
  "geometry": {"coordinates":[103.67565999999999,30.62939],"type":"Point"}
}