{
  "type": "Feature",
  "properties": {
    "gn:admin1_code":"30",
    "gn:asciiname":"Wenzhai",
    "gn:country_code":"CN",
    "gn:dem":23,
    "gn:feature_class":"P",
    "gn:feature_code":"PPL",
    "gn:name":"Wenzhai",
    "gn:population":0,
    "gn:timezone":"Asia/Urumqi",
    "iso:country":"CN",
    "name:und_x_variant":[
        "Wen-chai",
        "Wenzhai",
        "\u6587\u5b85",
        "Wenzhaicun",
        "\u6587\u5b85\u6751"
    ],
    "wof:name":"Wenzhai",
    "wof:placetype":"locality"
},
  "geometry": {"coordinates":[110.05823999999998,21.06214],"type":"Point"}
}