{
  "type": "Feature",
  "properties": {
    "gn:admin1_code":"4.0",
    "gn:asciiname":"Gucun",
    "gn:country_code":"CN",
    "gn:dem":14,
    "gn:feature_class":"P",
    "gn:feature_code":"PPL",
    "gn:name":"Gucun",
    "gn:population":0,
    "gn:timezone":"Asia/Shanghai",
    "iso:country":"CN",
    "name:zho_x_preferred":[
        "Gucun"
    ],
    "name:zho_x_variant":[
        "\u53e4\u6751"
    ],
    "wof:name":"Gucun",
    "wof:placetype":"locality"
},
  "geometry": {"coordinates":[119.05522000000001,34.94119],"type":"Point"}
}