{
  "type": "Feature",
  "properties": {
    "gn:admin1_code":"29",
    "gn:asciiname":"Nagun",
    "gn:country_code":"CN",
    "gn:dem":1453,
    "gn:feature_class":"P",
    "gn:feature_code":"PPL",
    "gn:name":"Nagun",
    "gn:population":0,
    "gn:timezone":"Asia/Shanghai",
    "iso:country":"CN",
    "name:zho_x_preferred":[
        "\u90a3\u6eda"
    ],
    "wof:name":"Nagun",
    "wof:placetype":"locality"
},
  "geometry": {"coordinates":[105.47799999999999,23.5176],"type":"Point"}
}