{
  "type": "Feature",
  "properties": {
    "gn:admin1_code":"20.0",
    "gn:asciiname":"Beishatan",
    "gn:country_code":"CN",
    "gn:dem":1182,
    "gn:feature_class":"P",
    "gn:feature_code":"PPL",
    "gn:name":"Beishatan",
    "gn:population":0,
    "gn:timezone":"Asia/Shanghai",
    "iso:country":"CN",
    "name:und_x_variant":[
        "\u5317\u6c99\u6ee9"
    ],
    "wof:name":"Beishatan",
    "wof:placetype":"locality"
},
  "geometry": {"coordinates":[114.03301,40.68136],"type":"Point"}
}