{
  "type": "Feature",
  "properties": {
    "gn:admin1_code":"4.0",
    "gn:asciiname":"Zhugangcun",
    "gn:country_code":"CN",
    "gn:dem":0,
    "gn:feature_class":"P",
    "gn:feature_code":"PPL",
    "gn:name":"Zhugangcun",
    "gn:population":0,
    "gn:timezone":"Asia/Shanghai",
    "iso:country":"CN",
    "name:zho_x_preferred":[
        "\u6731\u6e2f\u6751"
    ],
    "wof:name":"Zhugangcun",
    "wof:placetype":"locality"
},
  "geometry": {"coordinates":[119.91748,33.4129],"type":"Point"}
}