{
  "type": "Feature",
  "properties": {
    "gn:admin1_code":"13",
    "gn:asciiname":"Yiyilian",
    "gn:country_code":"CN",
    "gn:dem":1041,
    "gn:feature_class":"P",
    "gn:feature_code":"PPL",
    "gn:name":"Yiyilian",
    "gn:population":0,
    "gn:timezone":"Asia/Shanghai",
    "iso:country":"CN",
    "name:und_x_variant":[
        "\u4e00\u4e00\u8fde"
    ],
    "wof:name":"Yiyilian",
    "wof:placetype":"locality"
},
  "geometry": {"coordinates":[80.38008000000001,40.33426],"type":"Point"}
}