{
  "type": "Feature",
  "properties": {
    "gn:admin1_code":"16.0",
    "gn:asciiname":"Guchi",
    "gn:country_code":"CN",
    "gn:dem":147,
    "gn:feature_class":"P",
    "gn:feature_code":"PPL",
    "gn:name":"Guchi",
    "gn:population":0,
    "gn:timezone":"Asia/Shanghai",
    "iso:country":"CN",
    "name:zho_x_preferred":[
        "\u53e4\u6c60"
    ],
    "wof:name":"Guchi",
    "wof:placetype":"locality"
},
  "geometry": {"coordinates":[110.917,23.8217],"type":"Point"}
}