{
  "type": "Feature",
  "properties": {
    "gn:admin1_code":"4.0",
    "gn:asciiname":"Zhuyuancun",
    "gn:country_code":"CN",
    "gn:dem":30,
    "gn:feature_class":"P",
    "gn:feature_code":"PPL",
    "gn:name":"Zhuyuancun",
    "gn:population":0,
    "gn:timezone":"Asia/Shanghai",
    "iso:country":"CN",
    "name:und_x_variant":[
        "Zhuyuan"
    ],
    "name:zho_x_preferred":[
        "\u7af9\u56ed\u6751"
    ],
    "wof:name":"Zhuyuancun",
    "wof:placetype":"locality"
},
  "geometry": {"coordinates":[118.06592000000001,34.42151],"type":"Point"}
}