{
  "type": "Feature",
  "properties": {
    "gn:admin1_code":"33.0",
    "gn:asciiname":"Xuanlongmiao",
    "gn:country_code":"CN",
    "gn:dem":614,
    "gn:feature_class":"P",
    "gn:feature_code":"PPL",
    "gn:name":"Xuanlongmiao",
    "gn:population":0,
    "gn:timezone":"Asia/Shanghai",
    "iso:country":"CN",
    "name:zho_x_preferred":[
        "\u7384\u9f99\u5e99"
    ],
    "wof:name":"Xuanlongmiao",
    "wof:placetype":"locality"
},
  "geometry": {"coordinates":[106.545,28.9309],"type":"Point"}
}