{
  "type": "Feature",
  "properties": {
    "gn:admin1_code":"16.0",
    "gn:asciiname":"Zhenxincun",
    "gn:country_code":"CN",
    "gn:dem":145,
    "gn:feature_class":"P",
    "gn:feature_code":"PPL",
    "gn:name":"Zhenxincun",
    "gn:population":0,
    "gn:timezone":"Asia/Shanghai",
    "iso:country":"CN",
    "name:zho_x_preferred":[
        "\u632f\u65b0\u6751"
    ],
    "wof:name":"Zhenxincun",
    "wof:placetype":"locality"
},
  "geometry": {"coordinates":[110.733,22.5734],"type":"Point"}
}