{
  "type": "Feature",
  "properties": {
    "gn:admin1_code":"12.0",
    "gn:asciiname":"Hutangwang",
    "gn:country_code":"CN",
    "gn:dem":103,
    "gn:feature_class":"P",
    "gn:feature_code":"PPL",
    "gn:name":"Hutangwang",
    "gn:population":0,
    "gn:timezone":"Asia/Shanghai",
    "iso:country":"CN",
    "name:zho_x_preferred":[
        "Hutangwang"
    ],
    "name:zho_x_variant":[
        "\u80e1\u5858\u738b"
    ],
    "wof:name":"Hutangwang",
    "wof:placetype":"locality"
},
  "geometry": {"coordinates":[114.84068000000001,29.7486],"type":"Point"}
}