{
  "type": "Feature",
  "properties": {
    "gn:admin1_code":"31",
    "gn:asciiname":"Guangxincun",
    "gn:country_code":"CN",
    "gn:dem":145,
    "gn:feature_class":"P",
    "gn:feature_code":"PPL",
    "gn:name":"Guangxincun",
    "gn:population":0,
    "gn:timezone":"Asia/Shanghai",
    "iso:country":"CN",
    "name:und_x_variant":[
        "Naguang"
    ],
    "name:zho_x_preferred":[
        "\u5149\u65b0\u6751"
    ],
    "wof:name":"Guangxincun",
    "wof:placetype":"locality"
},
  "geometry": {"coordinates":[109.27806,19.3006],"type":"Point"}
}