{
  "type": "Feature",
  "properties": {
    "gn:admin1_code":"12.0",
    "gn:asciiname":"Qiaotouba",
    "gn:country_code":"CN",
    "gn:dem":612,
    "gn:feature_class":"P",
    "gn:feature_code":"PPL",
    "gn:name":"Qiaotouba",
    "gn:population":0,
    "gn:timezone":"Asia/Shanghai",
    "iso:country":"CN",
    "name:zho_x_preferred":[
        "\u6865\u5934\u575d"
    ],
    "wof:name":"Qiaotouba",
    "wof:placetype":"locality"
},
  "geometry": {"coordinates":[109.64766000000002,30.42783],"type":"Point"}
}