{
  "type": "Feature",
  "properties": {
    "gn:admin1_code":"12.0",
    "gn:asciiname":"Shaziling",
    "gn:country_code":"CN",
    "gn:dem":756,
    "gn:feature_class":"P",
    "gn:feature_code":"PPL",
    "gn:name":"Shaziling",
    "gn:population":0,
    "gn:timezone":"Asia/Shanghai",
    "iso:country":"CN",
    "name:zho_x_preferred":[
        "Shaziling"
    ],
    "name:zho_x_variant":[
        "\u6c99\u5b50\u5cad"
    ],
    "wof:name":"Shaziling",
    "wof:placetype":"locality"
},
  "geometry": {"coordinates":[111.37081000000001,30.97321],"type":"Point"}
}