{
  "type": "Feature",
  "properties": {
    "gn:admin1_code":"18.0",
    "gn:asciiname":"Jiabu",
    "gn:country_code":"CN",
    "gn:dem":1363,
    "gn:feature_class":"P",
    "gn:feature_code":"PPL",
    "gn:name":"Jiabu",
    "gn:population":0,
    "gn:timezone":"Asia/Shanghai",
    "iso:country":"CN",
    "name:zho_x_preferred":[
        "\u67b6\u5e03"
    ],
    "wof:name":"Jiabu",
    "wof:placetype":"locality"
},
  "geometry": {"coordinates":[106.06100000000001,26.441],"type":"Point"}
}