{
  "type": "Feature",
  "properties": {
    "gn:admin1_code":"4.0",
    "gn:asciiname":"Sichahe",
    "gn:country_code":"CN",
    "gn:dem":4,
    "gn:feature_class":"P",
    "gn:feature_code":"PPL",
    "gn:name":"Sichahe",
    "gn:population":0,
    "gn:timezone":"Asia/Shanghai",
    "iso:country":"CN",
    "name:und_x_variant":[
        "\u56db\u5c94\u6cb3"
    ],
    "name:zho_x_preferred":[
        "\u56db\u5c94\u6cb3"
    ],
    "wof:name":"Sichahe",
    "wof:placetype":"locality"
},
  "geometry": {"coordinates":[120.26328999999998,32.06716],"type":"Point"}
}