{
  "type": "Feature",
  "properties": {
    "gn:admin1_code":"07",
    "gn:asciiname":"Guiling",
    "gn:country_code":"CN",
    "gn:dem":127,
    "gn:feature_class":"P",
    "gn:feature_code":"PPL",
    "gn:name":"Guiling",
    "gn:population":0,
    "gn:timezone":"Asia/Shanghai",
    "iso:country":"CN",
    "name:zho_x_preferred":[
        "\u9f9f\u5cad"
    ],
    "wof:name":"Guiling",
    "wof:placetype":"locality"
},
  "geometry": {"coordinates":[120.35038,27.33882],"type":"Point"}
}