{
  "type": "Feature",
  "properties": {
    "gn:admin1_code":"32.0",
    "gn:asciiname":"Yangfanggou",
    "gn:country_code":"CN",
    "gn:dem":3045,
    "gn:feature_class":"P",
    "gn:feature_code":"PPL",
    "gn:name":"Yangfanggou",
    "gn:population":0,
    "gn:timezone":"Asia/Shanghai",
    "iso:country":"CN",
    "name:zho_x_preferred":[
        "\u7f8a\u623f\u6c9f"
    ],
    "wof:name":"Yangfanggou",
    "wof:placetype":"locality"
},
  "geometry": {"coordinates":[101.63800000000001,28.1072],"type":"Point"}
}