{
  "type": "Feature",
  "properties": {
    "gn:country":"CN",
    "gn:fcode":"PPLA4",
    "gn:population":0,
    "iso:country":"CN",
    "name:ara_x_preferred":[
        "\u062a\u0648\u0646\u063a\u0644\u064a"
    ],
    "name:deu_x_preferred":[
        "Tongli"
    ],
    "name:eng_x_preferred":[
        "Tongli"
    ],
    "name:fra_x_preferred":[
        "Tongli"
    ],
    "name:gan_x_preferred":[
        "\u540c\u91cc\u9547"
    ],
    "name:hun_x_preferred":[
        "Tungli"
    ],
    "name:jpn_x_preferred":[
        "\u540c\u91cc\u93ae"
    ],
    "name:kor_x_preferred":[
        "\ud241\ub9ac \uc9c4"
    ],
    "name:nob_x_preferred":[
        "Tongli"
    ],
    "name:swe_x_preferred":[
        "Tongli"
    ],
    "name:tha_x_preferred":[
        "\u0e16\u0e07\u0e2b\u0e25\u0e35\u0e48"
    ],
    "name:und_x_variant":[
        "T\u2019ung-li-chen"
    ],
    "name:vie_x_preferred":[
        "\u0110\u1ed3ng L\u00fd"
    ],
    "name:wuu_x_preferred":[
        "\u540c\u91cc\u9547"
    ],
    "name:zho_x_preferred":[
        "\u540c\u91cc\u9547"
    ],
    "qs:name":"Tongli",
    "qs:photos_9r":0,
    "qs:photos_sr":0,
    "qs:pop_sr":"0",
    "wd:wordcount":374,
    "wof:name":"Tongli",
    "wof:placetype":"locality",
    "wof:population":0
},
  "geometry": {"coordinates":[120.71177,31.16097],"type":"Point"}
}