{
  "type": "Feature",
  "properties": {
    "gn:admin1_code":"7.0",
    "gn:asciiname":"Jialongli",
    "gn:country_code":"CN",
    "gn:dem":175,
    "gn:feature_class":"P",
    "gn:feature_code":"PPL",
    "gn:name":"Jialongli",
    "gn:population":0,
    "gn:timezone":"Asia/Shanghai",
    "iso:country":"CN",
    "name:zho_x_preferred":[
        "\u5bb6\u5784\u91cc"
    ],
    "wof:name":"Jialongli",
    "wof:placetype":"locality"
},
  "geometry": {"coordinates":[119.45753999999999,26.42783],"type":"Point"}
}