{
  "type": "Feature",
  "properties": {
    "gn:admin1_code":"8.0",
    "gn:asciiname":"Kanjiatun",
    "gn:country_code":"CN",
    "gn:dem":187,
    "gn:feature_class":"P",
    "gn:feature_code":"PPL",
    "gn:name":"Kanjiatun",
    "gn:population":0,
    "gn:timezone":"Asia/Shanghai",
    "iso:country":"CN",
    "name:zho_x_preferred":[
        "\u961a\u5bb6\u5c6f"
    ],
    "wof:name":"Kanjiatun",
    "wof:placetype":"locality"
},
  "geometry": {"coordinates":[126.55423,47.3259],"type":"Point"}
}