{
  "type": "Feature",
  "properties": {
    "gn:admin1_code":"29.0",
    "gn:asciiname":"Huagang",
    "gn:country_code":"CN",
    "gn:dem":2821,
    "gn:feature_class":"P",
    "gn:feature_code":"PPL",
    "gn:name":"Huagang",
    "gn:population":0,
    "gn:timezone":"Asia/Shanghai",
    "iso:country":"CN",
    "name:zho_x_preferred":[
        "\u534e\u5c97"
    ],
    "wof:name":"Huagang",
    "wof:placetype":"locality"
},
  "geometry": {"coordinates":[100.926,27.4253],"type":"Point"}
}