{
  "type": "Feature",
  "properties": {
    "gn:admin1_code":"25.0",
    "gn:asciiname":"Maguocun",
    "gn:country_code":"CN",
    "gn:dem":3,
    "gn:feature_class":"P",
    "gn:feature_code":"PPL",
    "gn:name":"Maguocun",
    "gn:population":0,
    "gn:timezone":"Asia/Shanghai",
    "iso:country":"CN",
    "name:zho_x_preferred":[
        "\u9ebb\u90ed\u6751"
    ],
    "wof:name":"Maguocun",
    "wof:placetype":"locality"
},
  "geometry": {"coordinates":[118.23224999999999,37.94985],"type":"Point"}
}