{
  "type": "Feature",
  "properties": {
    "gn:admin1_code":"26.0",
    "gn:asciiname":"Xinyaoke",
    "gn:country_code":"CN",
    "gn:dem":1197,
    "gn:feature_class":"P",
    "gn:feature_code":"PPL",
    "gn:name":"Xinyaoke",
    "gn:population":0,
    "gn:timezone":"Asia/Shanghai",
    "iso:country":"CN",
    "name:zho_x_preferred":[
        "\u65b0\u7a91\u79d1"
    ],
    "wof:name":"Xinyaoke",
    "wof:placetype":"locality"
},
  "geometry": {"coordinates":[109.80758,36.28805],"type":"Point"}
}