{
  "type": "Feature",
  "properties": {
    "gn:admin1_code":"32.0",
    "gn:asciiname":"Shuangxi'ao",
    "gn:country_code":"CN",
    "gn:dem":1325,
    "gn:feature_class":"P",
    "gn:feature_code":"PPL",
    "gn:name":"Shuangxi\u2019ao",
    "gn:population":0,
    "gn:timezone":"Asia/Shanghai",
    "iso:country":"CN",
    "name:zho_x_preferred":[
        "\u53cc\u559c\u5773"
    ],
    "name:zho_x_variant":[
        "Shuangxi\u2019ao"
    ],
    "wof:name":"Shuangxi'ao",
    "wof:placetype":"locality"
},
  "geometry": {"coordinates":[103.62318999999999,28.68588],"type":"Point"}
}