{
  "type": "Feature",
  "properties": {
    "gn:admin1_code":"1.0",
    "gn:asciiname":"Huigangcun",
    "gn:country_code":"CN",
    "gn:dem":20,
    "gn:feature_class":"P",
    "gn:feature_code":"PPL",
    "gn:name":"Huigangcun",
    "gn:population":0,
    "gn:timezone":"Asia/Shanghai",
    "iso:country":"CN",
    "name:zho_x_preferred":[
        "\u60e0\u5c97\u6751"
    ],
    "wof:name":"Huigangcun",
    "wof:placetype":"locality"
},
  "geometry": {"coordinates":[117.0467,33.03339],"type":"Point"}
}