{
  "type": "Feature",
  "properties": {
    "gn:admin1_code":"11.0",
    "gn:asciiname":"Gulouchong",
    "gn:country_code":"CN",
    "gn:dem":50,
    "gn:feature_class":"P",
    "gn:feature_code":"PPL",
    "gn:name":"Gulouchong",
    "gn:population":0,
    "gn:timezone":"Asia/Shanghai",
    "iso:country":"CN",
    "name:zho_x_preferred":[
        "\u53e4\u697c\u51b2"
    ],
    "wof:name":"Gulouchong",
    "wof:placetype":"locality"
},
  "geometry": {"coordinates":[113.01833999999999,28.0065],"type":"Point"}
}