{
  "type": "Feature",
  "properties": {
    "gn:admin1_code":"29.0",
    "gn:asciiname":"Heinigou",
    "gn:country_code":"CN",
    "gn:dem":2208,
    "gn:feature_class":"P",
    "gn:feature_code":"PPL",
    "gn:name":"Heinigou",
    "gn:population":0,
    "gn:timezone":"Asia/Shanghai",
    "iso:country":"CN",
    "name:zho_x_preferred":[
        "\u9ed1\u6ce5\u6c9f"
    ],
    "wof:name":"Heinigou",
    "wof:placetype":"locality"
},
  "geometry": {"coordinates":[103.184,25.4384],"type":"Point"}
}