{
  "type": "Feature",
  "properties": {
    "gn:admin1_code":"14.0",
    "gn:asciiname":"Duoren",
    "gn:country_code":"CN",
    "gn:dem":4472,
    "gn:feature_class":"P",
    "gn:feature_code":"PPL",
    "gn:name":"Duoren",
    "gn:population":0,
    "gn:timezone":"Asia/Shanghai",
    "iso:country":"CN",
    "name:zho_x_preferred":[
        "\u591a\u4ec1"
    ],
    "wof:name":"Duoren",
    "wof:placetype":"locality"
},
  "geometry": {"coordinates":[81.3655,32.8623],"type":"Point"}
}