{
  "type": "Feature",
  "properties": {
    "gn:admin1_code":"32.0",
    "gn:asciiname":"Caodongzi",
    "gn:country_code":"CN",
    "gn:dem":633,
    "gn:feature_class":"P",
    "gn:feature_code":"PPL",
    "gn:name":"Caodongzi",
    "gn:population":0,
    "gn:timezone":"Asia/Shanghai",
    "iso:country":"CN",
    "name:zho_x_preferred":[
        "\u8349\u6d1e\u5b50"
    ],
    "wof:name":"Caodongzi",
    "wof:placetype":"locality"
},
  "geometry": {"coordinates":[104.545,31.7427],"type":"Point"}
}