{
  "type": "Feature",
  "properties": {
    "gn:admin1_code":"3.0",
    "gn:asciiname":"Luoshicun",
    "gn:country_code":"CN",
    "gn:dem":285,
    "gn:feature_class":"P",
    "gn:feature_code":"PPL",
    "gn:name":"Luoshicun",
    "gn:population":0,
    "gn:timezone":"Asia/Shanghai",
    "iso:country":"CN",
    "name:und_x_variant":[
        "\u7f57\u77f3\u6751"
    ],
    "wof:name":"Luoshicun",
    "wof:placetype":"locality"
},
  "geometry": {"coordinates":[115.65823,28.77947],"type":"Point"}
}