{
  "type": "Feature",
  "properties": {
    "gn:admin1_code":"18",
    "gn:asciiname":"Bianzao",
    "gn:country_code":"CN",
    "gn:dem":1142,
    "gn:feature_class":"P",
    "gn:feature_code":"PPL",
    "gn:name":"Bianzao",
    "gn:population":0,
    "gn:timezone":"Asia/Shanghai",
    "iso:country":"CN",
    "name:zho_x_preferred":[
        "\u6241\u7cdf"
    ],
    "wof:name":"Bianzao",
    "wof:placetype":"locality"
},
  "geometry": {"coordinates":[105.194,26.1386],"type":"Point"}
}