{
  "type": "Feature",
  "properties": {
    "gn:admin1_code":"30.0",
    "gn:asciiname":"Xinyan",
    "gn:country_code":"CN",
    "gn:dem":157,
    "gn:feature_class":"P",
    "gn:feature_code":"PPL",
    "gn:name":"Xinyan",
    "gn:population":0,
    "gn:timezone":"Asia/Shanghai",
    "iso:country":"CN",
    "name:zho_x_preferred":[
        "Xinyan"
    ],
    "name:zho_x_variant":[
        "\u65b0\u5ca9"
    ],
    "wof:name":"Xinyan",
    "wof:placetype":"locality"
},
  "geometry": {"coordinates":[112.28667,24.74444],"type":"Point"}
}