{
  "type": "Feature",
  "properties": {
    "gn:admin1_code":"29.0",
    "gn:asciiname":"Lanniqing",
    "gn:country_code":"CN",
    "gn:dem":2299,
    "gn:feature_class":"P",
    "gn:feature_code":"PPL",
    "gn:name":"Lanniqing",
    "gn:population":0,
    "gn:timezone":"Asia/Shanghai",
    "iso:country":"CN",
    "name:zho_x_preferred":[
        "\u70c2\u6ce5\u7b90"
    ],
    "wof:name":"Lanniqing",
    "wof:placetype":"locality"
},
  "geometry": {"coordinates":[102.93300000000001,27.3299],"type":"Point"}
}