{
  "type": "Feature",
  "properties": {
    "gn:admin1_code":"25.0",
    "gn:asciiname":"Xujialushui",
    "gn:cc2":"CN",
    "gn:country_code":"CN",
    "gn:dem":65,
    "gn:feature_class":"P",
    "gn:feature_code":"PPL",
    "gn:name":"Xujialushui",
    "gn:population":0,
    "gn:timezone":"Asia/Shanghai",
    "iso:country":"CN",
    "name:zho_x_preferred":[
        "\u5f90\u5bb6\u82a6\u6c34"
    ],
    "wof:name":"Xujialushui",
    "wof:placetype":"locality"
},
  "geometry": {"coordinates":[119.50287,36.04252],"type":"Point"}
}