{
  "type": "Feature",
  "properties": {
    "gn:admin1_code":"30",
    "gn:asciiname":"Nansuozai",
    "gn:country_code":"CN",
    "gn:dem":24,
    "gn:feature_class":"P",
    "gn:feature_code":"PPL",
    "gn:name":"Nansuozai",
    "gn:population":0,
    "gn:timezone":"Asia/Urumqi",
    "iso:country":"CN",
    "name:zho_x_preferred":[
        "\u90a3\u68ad\u4ed4"
    ],
    "wof:name":"Nansuozai",
    "wof:placetype":"locality"
},
  "geometry": {"coordinates":[109.89686,21.18554],"type":"Point"}
}