{
  "type": "Feature",
  "properties": {
    "gn:admin1_code":"8.0",
    "gn:asciiname":"Dongxingtun",
    "gn:country_code":"CN",
    "gn:dem":205,
    "gn:feature_class":"P",
    "gn:feature_code":"PPL",
    "gn:name":"Dongxingtun",
    "gn:population":0,
    "gn:timezone":"Asia/Shanghai",
    "iso:country":"CN",
    "name:zho_x_preferred":[
        "\u4e1c\u5174\u5c6f"
    ],
    "wof:name":"Dongxingtun",
    "wof:placetype":"locality"
},
  "geometry": {"coordinates":[124.8141,48.05942],"type":"Point"}
}