{
  "type": "Feature",
  "properties": {
    "gn:admin1_code":"10.0",
    "gn:asciiname":"Taojiaxiaozhuang",
    "gn:country_code":"CN",
    "gn:dem":1435,
    "gn:feature_class":"P",
    "gn:feature_code":"PPL",
    "gn:name":"Taojiaxiaozhuang",
    "gn:population":0,
    "gn:timezone":"Asia/Shanghai",
    "iso:country":"CN",
    "name:zho_x_preferred":[
        "\u9676\u5bb6\u5c0f\u5e84"
    ],
    "wof:name":"Taojiaxiaozhuang",
    "wof:placetype":"locality"
},
  "geometry": {"coordinates":[114.77797,39.6763],"type":"Point"}
}