{
  "type": "Feature",
  "properties": {
    "gn:admin1_code":"14.0",
    "gn:asciiname":"Xiamadang",
    "gn:country_code":"CN",
    "gn:dem":4028,
    "gn:feature_class":"P",
    "gn:feature_code":"PPL",
    "gn:name":"Xiamadang",
    "gn:population":0,
    "gn:timezone":"Asia/Urumqi",
    "iso:country":"CN",
    "name:zho_x_preferred":[
        "\u4e0b\u9a6c\u5f53"
    ],
    "wof:name":"Xiamadang",
    "wof:placetype":"locality"
},
  "geometry": {"coordinates":[92.22556,28.4338],"type":"Point"}
}