{
  "type": "Feature",
  "properties": {
    "gn:admin1_code":"4.0",
    "gn:asciiname":"Tuanwa",
    "gn:country_code":"CN",
    "gn:dem":7,
    "gn:feature_class":"P",
    "gn:feature_code":"PPL",
    "gn:name":"Tuanwa",
    "gn:population":0,
    "gn:timezone":"Asia/Shanghai",
    "iso:country":"CN",
    "name:und_x_variant":[
        "\u56e2\u6d3c"
    ],
    "name:zho_x_preferred":[
        "\u56e2\u6d3c"
    ],
    "wof:name":"Tuanwa",
    "wof:placetype":"locality"
},
  "geometry": {"coordinates":[120.37390000000001,32.18201],"type":"Point"}
}