{
  "type": "Feature",
  "properties": {
    "gn:admin1_code":"7.0",
    "gn:asciiname":"Jiukengnei",
    "gn:country_code":"CN",
    "gn:dem":31,
    "gn:feature_class":"P",
    "gn:feature_code":"PPL",
    "gn:name":"Jiukengnei",
    "gn:population":0,
    "gn:timezone":"Asia/Shanghai",
    "iso:country":"CN",
    "name:zho_x_preferred":[
        "\u65e7\u5751\u5185"
    ],
    "wof:name":"Jiukengnei",
    "wof:placetype":"locality"
},
  "geometry": {"coordinates":[117.40727,23.72958],"type":"Point"}
}