{
  "type": "Feature",
  "properties": {
    "gn:admin1_code":"26.0",
    "gn:asciiname":"Xuyangguan",
    "gn:country_code":"CN",
    "gn:dem":1274,
    "gn:feature_class":"P",
    "gn:feature_code":"PPL",
    "gn:name":"Xuyangguan",
    "gn:population":0,
    "gn:timezone":"Asia/Shanghai",
    "iso:country":"CN",
    "name:zho_x_preferred":[
        "\u5f90\u517b\u5173"
    ],
    "wof:name":"Xuyangguan",
    "wof:placetype":"locality"
},
  "geometry": {"coordinates":[109.3956,37.51546],"type":"Point"}
}