{
  "type": "Feature",
  "properties": {
    "gn:admin1_code":"32.0",
    "gn:asciiname":"Chunyangdian",
    "gn:country_code":"CN",
    "gn:dem":934,
    "gn:feature_class":"P",
    "gn:feature_code":"PPL",
    "gn:name":"Chunyangdian",
    "gn:population":0,
    "gn:timezone":"Asia/Shanghai",
    "iso:country":"CN",
    "name:zho_x_preferred":[
        "\u7eaf\u9633\u6bbf"
    ],
    "wof:name":"Chunyangdian",
    "wof:placetype":"locality"
},
  "geometry": {"coordinates":[103.419,29.5687],"type":"Point"}
}