{
  "type": "Feature",
  "properties": {
    "gn:admin1_code":"2.0",
    "gn:asciiname":"Gongyuan",
    "gn:country_code":"CN",
    "gn:dem":83,
    "gn:feature_class":"P",
    "gn:feature_code":"PPL",
    "gn:name":"Gongyuan",
    "gn:population":0,
    "gn:timezone":"Asia/Shanghai",
    "iso:country":"CN",
    "name:und_x_variant":[
        "Kung-y\u00fcan-ts\u2019un",
        "Gongyuan"
    ],
    "name:zho_x_preferred":[
        "\u9f9a\u539f"
    ],
    "wof:name":"Gongyuan",
    "wof:placetype":"locality"
},
  "geometry": {"coordinates":[121.37631,29.52071],"type":"Point"}
}