{
  "type": "Feature",
  "properties": {
    "gn:admin1_code":"32.0",
    "gn:asciiname":"Dahong",
    "gn:country_code":"CN",
    "gn:dem":432,
    "gn:feature_class":"P",
    "gn:feature_code":"PPL",
    "gn:name":"Dahong",
    "gn:population":0,
    "gn:timezone":"Asia/Shanghai",
    "iso:country":"CN",
    "name:zho_x_preferred":[
        "\u5927\u7ea2"
    ],
    "wof:name":"Dahong",
    "wof:placetype":"locality"
},
  "geometry": {"coordinates":[105.414,29.9307],"type":"Point"}
}