{
  "type": "Feature",
  "properties": {
    "gn:admin1_code":"3.0",
    "gn:asciiname":"Yuankouhuang",
    "gn:country_code":"CN",
    "gn:dem":68,
    "gn:feature_class":"P",
    "gn:feature_code":"PPL",
    "gn:name":"Yuankouhuang",
    "gn:population":0,
    "gn:timezone":"Asia/Shanghai",
    "iso:country":"CN",
    "name:und_x_variant":[
        "\u6c85\u53e3\u9ec4"
    ],
    "wof:name":"Yuankouhuang",
    "wof:placetype":"locality"
},
  "geometry": {"coordinates":[115.44750000000001,29.44527],"type":"Point"}
}