{
  "type": "Feature",
  "properties": {
    "gn:admin1_code":"19.0",
    "gn:asciiname":"Qingcaogou",
    "gn:country_code":"CN",
    "gn:dem":178,
    "gn:feature_class":"P",
    "gn:feature_code":"PPL",
    "gn:name":"Qingcaogou",
    "gn:population":0,
    "gn:timezone":"Asia/Shanghai",
    "iso:country":"CN",
    "name:und_x_variant":[
        "\u9752\u8349\u6c9f"
    ],
    "wof:name":"Qingcaogou",
    "wof:placetype":"locality"
},
  "geometry": {"coordinates":[122.99451999999999,40.91886],"type":"Point"}
}