{
  "type": "Feature",
  "properties": {
    "gn:admin1_code":"7.0",
    "gn:asciiname":"Xiangya",
    "gn:country_code":"CN",
    "gn:dem":29,
    "gn:feature_class":"P",
    "gn:feature_code":"PPL",
    "gn:name":"Xiangya",
    "gn:population":0,
    "gn:timezone":"Asia/Shanghai",
    "iso:country":"CN",
    "name:zho_x_preferred":[
        "\u8c61\u7259"
    ],
    "wof:name":"Xiangya",
    "wof:placetype":"locality"
},
  "geometry": {"coordinates":[117.47024999999999,24.15728],"type":"Point"}
}