{
  "type": "Feature",
  "properties": {
    "gn:admin1_code":"26.0",
    "gn:asciiname":"Wuquanlei",
    "gn:country_code":"CN",
    "gn:dem":1180,
    "gn:feature_class":"P",
    "gn:feature_code":"PPL",
    "gn:name":"Wuquanlei",
    "gn:population":0,
    "gn:timezone":"Asia/Shanghai",
    "iso:country":"CN",
    "name:zho_x_preferred":[
        "\u4e94\u6cc9\u78ca"
    ],
    "wof:name":"Wuquanlei",
    "wof:placetype":"locality"
},
  "geometry": {"coordinates":[110.27226,35.76900999999999],"type":"Point"}
}