{
  "type": "Feature",
  "properties": {
    "gn:admin1_code":"15.0",
    "gn:asciiname":"Lizitan",
    "gn:country_code":"CN",
    "gn:dem":2667,
    "gn:feature_class":"P",
    "gn:feature_code":"PPL",
    "gn:name":"Lizitan",
    "gn:population":0,
    "gn:timezone":"Asia/Shanghai",
    "iso:country":"CN",
    "name:und_x_variant":[
        "\u7acb\u5b50\u6ee9"
    ],
    "wof:name":"Lizitan",
    "wof:placetype":"locality"
},
  "geometry": {"coordinates":[103.238,34.64061],"type":"Point"}
}