{
  "type": "Feature",
  "properties": {
    "gn:admin1_code":"11",
    "gn:asciiname":"Wangjiawan",
    "gn:country_code":"CN",
    "gn:dem":81,
    "gn:feature_class":"P",
    "gn:feature_code":"PPL",
    "gn:name":"Wangjiawan",
    "gn:population":0,
    "gn:timezone":"Asia/Shanghai",
    "iso:country":"CN",
    "name:deu_x_preferred":[
        "Wangjiawan"
    ],
    "wof:name":"Wangjiawan",
    "wof:placetype":"locality"
},
  "geometry": {"coordinates":[111.515,28.6925],"type":"Point"}
}