{
  "type": "Feature",
  "properties": {
    "gn:admin1_code":"2",
    "gn:asciiname":"Yinzishan",
    "gn:country_code":"CN",
    "gn:dem":157,
    "gn:feature_class":"P",
    "gn:feature_code":"PPL",
    "gn:name":"Yinzishan",
    "gn:population":0,
    "gn:timezone":"Asia/Shanghai",
    "iso:country":"CN",
    "name:und_x_variant":[
        "\u94f6\u5b50\u5c71"
    ],
    "wof:name":"Yinzishan",
    "wof:placetype":"locality"
},
  "geometry": {"coordinates":[119.84523,30.5094],"type":"Point"}
}