{
  "type": "Feature",
  "properties": {
    "gn:admin1_code":"11.0",
    "gn:asciiname":"Xiangguling",
    "gn:country_code":"CN",
    "gn:dem":981,
    "gn:feature_class":"P",
    "gn:feature_code":"PPL",
    "gn:name":"Xiangguling",
    "gn:population":0,
    "gn:timezone":"Asia/Shanghai",
    "iso:country":"CN",
    "name:zho_x_preferred":[
        "\u54cd\u9f13\u5cad"
    ],
    "wof:name":"Xiangguling",
    "wof:placetype":"locality"
},
  "geometry": {"coordinates":[110.85445,27.30498],"type":"Point"}
}