{
  "type": "Feature",
  "properties": {
    "gn:admin1_code":"30.0",
    "gn:asciiname":"Datongcun",
    "gn:country_code":"CN",
    "gn:dem":315,
    "gn:feature_class":"P",
    "gn:feature_code":"PPL",
    "gn:name":"Datongcun",
    "gn:population":0,
    "gn:timezone":"Asia/Shanghai",
    "iso:country":"CN",
    "name:zho_x_preferred":[
        "\u5927\u540c\u6751"
    ],
    "wof:name":"Datongcun",
    "wof:placetype":"locality"
},
  "geometry": {"coordinates":[115.79827,24.73201],"type":"Point"}
}