{
  "type": "Feature",
  "properties": {
    "gn:admin1_code":"26.0",
    "gn:asciiname":"Yaojiawan",
    "gn:country_code":"CN",
    "gn:dem":1000,
    "gn:feature_class":"P",
    "gn:feature_code":"PPL",
    "gn:name":"Yaojiawan",
    "gn:population":0,
    "gn:timezone":"Asia/Shanghai",
    "iso:country":"CN",
    "name:zho_x_preferred":[
        "\u836f\u5bb6\u6e7e"
    ],
    "wof:name":"Yaojiawan",
    "wof:placetype":"locality"
},
  "geometry": {"coordinates":[110.06721,33.54674],"type":"Point"}
}