{
  "type": "Feature",
  "properties": {
    "gn:admin1_code":"2.0",
    "gn:asciiname":"Huweiwu",
    "gn:country_code":"CN",
    "gn:dem":186,
    "gn:feature_class":"P",
    "gn:feature_code":"PPL",
    "gn:name":"Huweiwu",
    "gn:population":0,
    "gn:timezone":"Asia/Shanghai",
    "iso:country":"CN",
    "name:und_x_variant":[
        "\u864e\u5c3e\u575e"
    ],
    "wof:name":"Huweiwu",
    "wof:placetype":"locality"
},
  "geometry": {"coordinates":[119.83891,30.15343],"type":"Point"}
}