{
  "type": "Feature",
  "properties": {
    "gn:admin1_code":"4.0",
    "gn:asciiname":"Chaonanlicun",
    "gn:country_code":"CN",
    "gn:dem":6,
    "gn:feature_class":"P",
    "gn:feature_code":"PPL",
    "gn:name":"Chaonanlicun",
    "gn:population":0,
    "gn:timezone":"Asia/Shanghai",
    "iso:country":"CN",
    "name:zho_x_preferred":[
        "\u671d\u5357\u674e\u6751"
    ],
    "wof:name":"Chaonanlicun",
    "wof:placetype":"locality"
},
  "geometry": {"coordinates":[119.74502,32.00394],"type":"Point"}
}