{
  "type": "Feature",
  "properties": {
    "gn:admin1_code":"24",
    "gn:asciiname":"Beizhouzhuang",
    "gn:country_code":"CN",
    "gn:dem":1050,
    "gn:feature_class":"P",
    "gn:feature_code":"PPLA4",
    "gn:name":"Beizhouzhuang",
    "gn:population":0,
    "gn:timezone":"Asia/Shanghai",
    "iso:country":"CN",
    "name:und_x_variant":[
        "Pei-chou-chuang",
        "Beizhouzhuang",
        "\u5317\u5468\u5e84",
        "Beizhouzhuang Zhen",
        "\u5317\u5468\u5e84\u9547"
    ],
    "wof:name":"Beizhouzhuang",
    "wof:placetype":"locality"
},
  "geometry": {"coordinates":[112.82284,39.59804000000001],"type":"Point"}
}