{
  "type": "Feature",
  "properties": {
    "gn:admin1_code":"10",
    "gn:asciiname":"Beishuiquan",
    "gn:country_code":"CN",
    "gn:dem":720,
    "gn:feature_class":"P",
    "gn:feature_code":"PPL",
    "gn:name":"Beishuiquan",
    "gn:population":0,
    "gn:timezone":"Asia/Shanghai",
    "iso:country":"CN",
    "name:zho_x_preferred":[
        "\u5317\u6c34\u6cc9"
    ],
    "wof:name":"Beishuiquan",
    "wof:placetype":"locality"
},
  "geometry": {"coordinates":[118.66919,41.08521],"type":"Point"}
}