{
  "type": "Feature",
  "properties": {
    "gn:admin1_code":"16",
    "gn:asciiname":"Ande",
    "gn:cc2":"CN",
    "gn:country_code":"CN",
    "gn:dem":869,
    "gn:feature_class":"P",
    "gn:feature_code":"PPL",
    "gn:name":"Ande",
    "gn:population":0,
    "gn:timezone":"Asia/Shanghai",
    "iso:country":"CN",
    "name:und_x_variant":[
        "An-te-hs\u00fc",
        "An-te",
        "Ande"
    ],
    "wof:name":"Ande",
    "wof:placetype":"locality"
},
  "geometry": {"coordinates":[106.01416999999999,23.26],"type":"Point"}
}