{
  "type": "Feature",
  "properties": {
    "gn:admin1_code":"26",
    "gn:asciiname":"Shangcun",
    "gn:country_code":"CN",
    "gn:dem":412,
    "gn:feature_class":"P",
    "gn:feature_code":"PPLA4",
    "gn:name":"Shangcun",
    "gn:population":0,
    "gn:timezone":"Asia/Shanghai",
    "iso:country":"CN",
    "name:und_x_variant":[
        "Shangcun Zhen",
        "Shangcun"
    ],
    "name:zho_x_preferred":[
        "\u5c1a\u6751"
    ],
    "name:zho_x_variant":[
        "\u5c1a\u6751\u9547"
    ],
    "wof:name":"Shangcun",
    "wof:placetype":"locality"
},
  "geometry": {"coordinates":[108.46872999999999,34.15516],"type":"Point"}
}