{
  "type": "Feature",
  "properties": {
    "gn:admin1_code":"25.0",
    "gn:asciiname":"Sanwangjia",
    "gn:country_code":"CN",
    "gn:dem":156,
    "gn:feature_class":"P",
    "gn:feature_code":"PPL",
    "gn:name":"Sanwangjia",
    "gn:population":0,
    "gn:timezone":"Asia/Shanghai",
    "iso:country":"CN",
    "name:zho_x_preferred":[
        "\u4e09\u738b\u5bb6"
    ],
    "wof:name":"Sanwangjia",
    "wof:placetype":"locality"
},
  "geometry": {"coordinates":[121.16727,36.94106],"type":"Point"}
}