{
  "type": "Feature",
  "properties": {
    "gn:admin1_code":"15.0",
    "gn:asciiname":"Zhouqu Chengguanzhen",
    "gn:country_code":"CN",
    "gn:dem":1326,
    "gn:feature_class":"P",
    "gn:feature_code":"PPLA3",
    "gn:name":"Zhouqu Chengguanzhen",
    "gn:population":0,
    "gn:timezone":"Asia/Shanghai",
    "iso:country":"CN",
    "name:und_x_variant":[
        "Lung-tieh",
        "Si-ku",
        "Hsi-ku",
        "Hsi-ku-hsien",
        "Zhouqu Chengguanzhen",
        "\u821f\u66f2\u57ce\u5173\u9547",
        "Zhugqu",
        "Zhouqu",
        "Zhouqu Xian",
        "\u821f\u66f2",
        "\u821f\u66f2\u53bf"
    ],
    "name:zho_x_preferred":[
        "Chou-ch\u2019\u00fc"
    ],
    "name:zho_x_variant":[
        "Chou-ch\u2019\u00fc-hsien",
        "Hsi-ku-hsien-ch\u2019eng",
        "\u821f\u66f2\u57ce\u5173\u9547",
        "\u821f\u66f2",
        "\u821f\u66f2\u53bf"
    ],
    "wof:name":"Zhouqu Chengguanzhen",
    "wof:placetype":"locality"
},
  "geometry": {"coordinates":[104.36278,33.78417],"type":"Point"}
}