{
  "type": "Feature",
  "properties": {
    "gn:admin1_code":"19.0",
    "gn:asciiname":"Caozigou",
    "gn:country_code":"CN",
    "gn:dem":113,
    "gn:feature_class":"P",
    "gn:feature_code":"PPL",
    "gn:name":"Caozigou",
    "gn:population":0,
    "gn:timezone":"Asia/Shanghai",
    "iso:country":"CN",
    "name:zho_x_preferred":[
        "\u66f9\u5b50\u6c9f"
    ],
    "wof:name":"Caozigou",
    "wof:placetype":"locality"
},
  "geometry": {"coordinates":[123.42516000000001,40.3895],"type":"Point"}
}