{
  "type": "Feature",
  "properties": {
    "gn:admin1_code":"18.0",
    "gn:asciiname":"Dapingpo",
    "gn:country_code":"CN",
    "gn:dem":575,
    "gn:feature_class":"P",
    "gn:feature_code":"PPL",
    "gn:name":"Dapingpo",
    "gn:population":0,
    "gn:timezone":"Asia/Shanghai",
    "iso:country":"CN",
    "name:zho_x_preferred":[
        "\u5927\u576a\u5761"
    ],
    "wof:name":"Dapingpo",
    "wof:placetype":"locality"
},
  "geometry": {"coordinates":[109.09699999999999,27.7603],"type":"Point"}
}