{
  "type": "Feature",
  "properties": {
    "gn:admin1_code":"15.0",
    "gn:asciiname":"Xiashantou",
    "gn:country_code":"CN",
    "gn:dem":2335,
    "gn:feature_class":"P",
    "gn:feature_code":"PPL",
    "gn:name":"Xiashantou",
    "gn:population":0,
    "gn:timezone":"Asia/Shanghai",
    "iso:country":"CN",
    "name:zho_x_preferred":[
        "\u4e0b\u5c71\u5934"
    ],
    "wof:name":"Xiashantou",
    "wof:placetype":"locality"
},
  "geometry": {"coordinates":[103.158,36.0486],"type":"Point"}
}