{
  "type": "Feature",
  "properties": {
    "gn:admin1_code":"16.0",
    "gn:asciiname":"Longling Shangzhai",
    "gn:country_code":"CN",
    "gn:dem":542,
    "gn:feature_class":"P",
    "gn:feature_code":"PPL",
    "gn:name":"Longling Shangzhai",
    "gn:population":0,
    "gn:timezone":"Asia/Shanghai",
    "iso:country":"CN",
    "name:zho_x_preferred":[
        "\u9f99\u4ee4\u4e0a\u5be8"
    ],
    "wof:name":"Longling Shangzhai",
    "wof:placetype":"locality"
},
  "geometry": {"coordinates":[109.26000000000001,25.6114],"type":"Point"}
}