{
  "type": "Feature",
  "properties": {
    "gn:admin1_code":"14.0",
    "gn:asciiname":"Baidingcun",
    "gn:country_code":"CN",
    "gn:dem":3845,
    "gn:feature_class":"P",
    "gn:feature_code":"PPL",
    "gn:name":"Baidingcun",
    "gn:population":0,
    "gn:timezone":"Asia/Urumqi",
    "iso:country":"CN",
    "name:zho_x_preferred":[
        "\u767d\u5b9a\u6751"
    ],
    "wof:name":"Baidingcun",
    "wof:placetype":"locality"
},
  "geometry": {"coordinates":[91.23774,29.95544000000001],"type":"Point"}
}