{
  "type": "Feature",
  "properties": {
    "gn:admin1_code":"29.0",
    "gn:asciiname":"Xuelin",
    "gn:cc2":"CN",
    "gn:country_code":"CN",
    "gn:dem":1748,
    "gn:feature_class":"P",
    "gn:feature_code":"PPL",
    "gn:name":"Xuelin",
    "gn:population":0,
    "gn:timezone":"Asia/Shanghai",
    "iso:country":"CN",
    "name:und_x_variant":[
        "Hs\u00fceh-lin",
        "Salin",
        "Xuelin"
    ],
    "wof:name":"Xuelin",
    "wof:placetype":"locality"
},
  "geometry": {"coordinates":[99.55,23.05],"type":"Point"}
}