{
  "type": "Feature",
  "properties": {
    "gn:admin1_code":"30",
    "gn:asciiname":"Lingjie",
    "gn:country_code":"CN",
    "gn:dem":42,
    "gn:feature_class":"P",
    "gn:feature_code":"PPL",
    "gn:name":"Lingjie",
    "gn:population":0,
    "gn:timezone":"Asia/Urumqi",
    "iso:country":"CN",
    "name:und_x_variant":[
        "Shang-ling-chieh",
        "Lingjie"
    ],
    "name:zho_x_preferred":[
        "\u7075\u754c"
    ],
    "wof:name":"Lingjie",
    "wof:placetype":"locality"
},
  "geometry": {"coordinates":[109.87223,20.85965],"type":"Point"}
}