{
  "type": "Feature",
  "properties": {
    "gn:admin1_code":"21.0",
    "gn:asciiname":"Xuezhuang",
    "gn:country_code":"CN",
    "gn:dem":1652,
    "gn:feature_class":"P",
    "gn:feature_code":"PPL",
    "gn:name":"Xuezhuang",
    "gn:population":0,
    "gn:timezone":"Asia/Shanghai",
    "iso:country":"CN",
    "name:und_x_variant":[
        "\u859b\u5e84"
    ],
    "name:zho_x_preferred":[
        "\u859b\u5e84"
    ],
    "wof:name":"Xuezhuang",
    "wof:placetype":"locality"
},
  "geometry": {"coordinates":[106.28206000000002,36.08896],"type":"Point"}
}