{
  "type": "Feature",
  "properties": {
    "gn:admin1_code":"15.0",
    "gn:asciiname":"Pingwan",
    "gn:country_code":"CN",
    "gn:dem":1372,
    "gn:feature_class":"P",
    "gn:feature_code":"PPL",
    "gn:name":"Pingwan",
    "gn:population":0,
    "gn:timezone":"Asia/Shanghai",
    "iso:country":"CN",
    "name:zho_x_preferred":[
        "\u5e73\u6e7e"
    ],
    "wof:name":"Pingwan",
    "wof:placetype":"locality"
},
  "geometry": {"coordinates":[107.012,35.3421],"type":"Point"}
}