{
  "type": "Feature",
  "properties": {
    "gn:admin1_code":"8.0",
    "gn:asciiname":"Quanyangoucun",
    "gn:country_code":"CN",
    "gn:dem":289,
    "gn:feature_class":"P",
    "gn:feature_code":"PPL",
    "gn:name":"Quanyangoucun",
    "gn:population":0,
    "gn:timezone":"Asia/Shanghai",
    "iso:country":"CN",
    "name:zho_x_preferred":[
        "\u6cc9\u773c\u6c9f\u6751"
    ],
    "wof:name":"Quanyangoucun",
    "wof:placetype":"locality"
},
  "geometry": {"coordinates":[129.20195000000001,44.17374],"type":"Point"}
}