{
  "type": "Feature",
  "properties": {
    "gn:admin1_code":"16",
    "gn:asciiname":"Dalijin",
    "gn:country_code":"CN",
    "gn:dem":1015,
    "gn:feature_class":"P",
    "gn:feature_code":"PPL",
    "gn:name":"Dalijin",
    "gn:population":0,
    "gn:timezone":"Asia/Shanghai",
    "iso:country":"CN",
    "name:zho_x_preferred":[
        "\u5927\u91cc\u6d78"
    ],
    "wof:name":"Dalijin",
    "wof:placetype":"locality"
},
  "geometry": {"coordinates":[110.93899999999999,25.5798],"type":"Point"}
}