{
  "type": "Feature",
  "properties": {
    "gn:admin1_code":"21.0",
    "gn:asciiname":"Baishagou",
    "gn:country_code":"CN",
    "gn:dem":1571,
    "gn:feature_class":"P",
    "gn:feature_code":"PPL",
    "gn:name":"Baishagou",
    "gn:population":0,
    "gn:timezone":"Asia/Shanghai",
    "iso:country":"CN",
    "name:und_x_variant":[
        "\u767d\u7802\u6c9f"
    ],
    "name:zho_x_preferred":[
        "\u767d\u7802\u6c9f"
    ],
    "wof:name":"Baishagou",
    "wof:placetype":"locality"
},
  "geometry": {"coordinates":[106.15725999999999,36.25457],"type":"Point"}
}