{
  "type": "Feature",
  "properties": {
    "gn:admin1_code":"9",
    "gn:asciiname":"Guojidao",
    "gn:country_code":"CN",
    "gn:dem":52,
    "gn:feature_class":"P",
    "gn:feature_code":"PPL",
    "gn:name":"Guojidao",
    "gn:population":0,
    "gn:timezone":"Asia/Shanghai",
    "iso:country":"CN",
    "name:zho_x_preferred":[
        "\u90ed\u5409\u9053"
    ],
    "wof:name":"Guojidao",
    "wof:placetype":"locality"
},
  "geometry": {"coordinates":[115.17064999999999,36.02864],"type":"Point"}
}