{
  "type": "Feature",
  "properties": {
    "gn:admin1_code":"33.0",
    "gn:asciiname":"Xiongfang",
    "gn:country_code":"CN",
    "gn:dem":783,
    "gn:feature_class":"P",
    "gn:feature_code":"PPL",
    "gn:name":"Xiongfang",
    "gn:population":0,
    "gn:timezone":"Asia/Shanghai",
    "iso:country":"CN",
    "name:zho_x_preferred":[
        "\u96c4\u82b3"
    ],
    "wof:name":"Xiongfang",
    "wof:placetype":"locality"
},
  "geometry": {"coordinates":[106.702,29.1264],"type":"Point"}
}