{
  "type": "Feature",
  "properties": {
    "gn:admin1_code":"18",
    "gn:asciiname":"Youyao",
    "gn:country_code":"CN",
    "gn:dem":774,
    "gn:feature_class":"P",
    "gn:feature_code":"PPL",
    "gn:name":"Youyao",
    "gn:population":0,
    "gn:timezone":"Asia/Shanghai",
    "iso:country":"CN",
    "name:und_x_variant":[
        "Youme",
        "Youyao"
    ],
    "name:zho_x_preferred":[
        "\u7531\u4e48"
    ],
    "wof:name":"Youyao",
    "wof:placetype":"locality"
},
  "geometry": {"coordinates":[105.944,25.2417],"type":"Point"}
}