{
  "type": "Feature",
  "properties": {
    "gn:admin1_code":"2.0",
    "gn:asciiname":"Wanzhukou",
    "gn:country_code":"CN",
    "gn:dem":122,
    "gn:feature_class":"P",
    "gn:feature_code":"PPL",
    "gn:name":"Wanzhukou",
    "gn:population":0,
    "gn:timezone":"Asia/Shanghai",
    "iso:country":"CN",
    "name:zho_x_preferred":[
        "\u4e07\u7af9\u53e3"
    ],
    "wof:name":"Wanzhukou",
    "wof:placetype":"locality"
},
  "geometry": {"coordinates":[120.52212,28.72594],"type":"Point"}
}