{
  "type": "Feature",
  "properties": {
    "gn:admin1_code":"5.0",
    "gn:asciiname":"Xingshugoucun",
    "gn:country_code":"CN",
    "gn:dem":192,
    "gn:feature_class":"P",
    "gn:feature_code":"PPL",
    "gn:name":"Xingshugoucun",
    "gn:population":0,
    "gn:timezone":"Asia/Shanghai",
    "iso:country":"CN",
    "name:zho_x_preferred":[
        "\u674f\u6811\u6c9f\u6751"
    ],
    "wof:name":"Xingshugoucun",
    "wof:placetype":"locality"
},
  "geometry": {"coordinates":[125.85063999999998,45.09554],"type":"Point"}
}