{
  "type": "Feature",
  "properties": {
    "gn:admin1_code":"29.0",
    "gn:asciiname":"Boluotang",
    "gn:country_code":"CN",
    "gn:dem":1562,
    "gn:feature_class":"P",
    "gn:feature_code":"PPL",
    "gn:name":"Boluotang",
    "gn:population":0,
    "gn:timezone":"Asia/Shanghai",
    "iso:country":"CN",
    "name:zho_x_preferred":[
        "\u6ce2\u841d\u5858"
    ],
    "wof:name":"Boluotang",
    "wof:placetype":"locality"
},
  "geometry": {"coordinates":[104.232,23.7064],"type":"Point"}
}