{
  "type": "Feature",
  "properties": {
    "gn:admin1_code":"29.0",
    "gn:asciiname":"Dongji",
    "gn:country_code":"CN",
    "gn:dem":1892,
    "gn:feature_class":"P",
    "gn:feature_code":"PPL",
    "gn:name":"Dongji",
    "gn:population":0,
    "gn:timezone":"Asia/Shanghai",
    "iso:country":"CN",
    "name:zho_x_preferred":[
        "\u4e1c\u7ed9"
    ],
    "wof:name":"Dongji",
    "wof:placetype":"locality"
},
  "geometry": {"coordinates":[98.3103,28.0186],"type":"Point"}
}