{
  "type": "Feature",
  "properties": {
    "gn:admin1_code":"5.0",
    "gn:asciiname":"Shuanglongcun",
    "gn:country_code":"CN",
    "gn:dem":148,
    "gn:feature_class":"P",
    "gn:feature_code":"PPL",
    "gn:name":"Shuanglongcun",
    "gn:population":0,
    "gn:timezone":"Asia/Shanghai",
    "iso:country":"CN",
    "name:zho_x_preferred":[
        "\u53cc\u9f99\u6751"
    ],
    "wof:name":"Shuanglongcun",
    "wof:placetype":"locality"
},
  "geometry": {"coordinates":[124.17950999999999,43.53721],"type":"Point"}
}