{
  "type": "Feature",
  "properties": {
    "gn:admin1_code":"23.0",
    "gn:asciiname":"Taojiatang",
    "gn:country_code":"CN",
    "gn:dem":4,
    "gn:feature_class":"P",
    "gn:feature_code":"PPL",
    "gn:name":"Taojiatang",
    "gn:population":0,
    "gn:timezone":"Asia/Shanghai",
    "iso:country":"CN",
    "name:zho_x_preferred":[
        "Taojiatang"
    ],
    "name:zho_x_variant":[
        "\u9676\u5bb6\u5858"
    ],
    "wof:name":"Taojiatang",
    "wof:placetype":"locality"
},
  "geometry": {"coordinates":[121.30588,31.14149],"type":"Point"}
}