{
  "type": "Feature",
  "properties": {
    "gn:admin1_code":"32.0",
    "gn:asciiname":"Yaka",
    "gn:country_code":"CN",
    "gn:dem":3560,
    "gn:feature_class":"P",
    "gn:feature_code":"PPL",
    "gn:name":"Yaka",
    "gn:population":0,
    "gn:timezone":"Asia/Shanghai",
    "iso:country":"CN",
    "name:zho_x_preferred":[
        "\u4e9a\u5580"
    ],
    "wof:name":"Yaka",
    "wof:placetype":"locality"
},
  "geometry": {"coordinates":[101.68249,31.89498],"type":"Point"}
}