{
  "type": "Feature",
  "properties": {
    "gn:admin1_code":"12.0",
    "gn:asciiname":"Ehuangdong",
    "gn:country_code":"CN",
    "gn:dem":252,
    "gn:feature_class":"P",
    "gn:feature_code":"PPL",
    "gn:name":"Ehuangdong",
    "gn:population":0,
    "gn:timezone":"Asia/Shanghai",
    "iso:country":"CN",
    "name:zho_x_preferred":[
        "\u5a25\u7687\u6d1e"
    ],
    "wof:name":"Ehuangdong",
    "wof:placetype":"locality"
},
  "geometry": {"coordinates":[112.75708,31.65093],"type":"Point"}
}