{
  "type": "Feature",
  "properties": {
    "gn:admin1_code":"26.0",
    "gn:asciiname":"Luoxing",
    "gn:country_code":"CN",
    "gn:dem":652,
    "gn:feature_class":"P",
    "gn:feature_code":"PPL",
    "gn:name":"Luoxing",
    "gn:population":0,
    "gn:timezone":"Asia/Shanghai",
    "iso:country":"CN",
    "name:und_x_variant":[
        "\u843d\u661f"
    ],
    "wof:name":"Luoxing",
    "wof:placetype":"locality"
},
  "geometry": {"coordinates":[107.64122999999999,34.20238],"type":"Point"}
}