{
  "type": "Feature",
  "properties": {
    "gn:admin1_code":"16.0",
    "gn:asciiname":"Nachao",
    "gn:country_code":"CN",
    "gn:dem":465,
    "gn:feature_class":"P",
    "gn:feature_code":"PPL",
    "gn:name":"Nachao",
    "gn:population":0,
    "gn:timezone":"Asia/Shanghai",
    "iso:country":"CN",
    "name:zho_x_preferred":[
        "\u90a3\u671d"
    ],
    "wof:name":"Nachao",
    "wof:placetype":"locality"
},
  "geometry": {"coordinates":[107.21299999999999,24.7365],"type":"Point"}
}