{
  "type": "Feature",
  "properties": {
    "gn:admin1_code":"12.0",
    "gn:asciiname":"Zhaohe",
    "gn:country_code":"CN",
    "gn:dem":52,
    "gn:feature_class":"P",
    "gn:feature_code":"PPL",
    "gn:name":"Zhaohe",
    "gn:population":0,
    "gn:timezone":"Asia/Shanghai",
    "iso:country":"CN",
    "name:zho_x_preferred":[
        "\u8d75\u6cb3"
    ],
    "wof:name":"Zhaohe",
    "wof:placetype":"locality"
},
  "geometry": {"coordinates":[112.3845,31.43031],"type":"Point"}
}