{
  "type": "Feature",
  "properties": {
    "gn:admin1_code":"8.0",
    "gn:asciiname":"Miaolingtun",
    "gn:country_code":"CN",
    "gn:dem":199,
    "gn:feature_class":"P",
    "gn:feature_code":"PPL",
    "gn:name":"Miaolingtun",
    "gn:population":0,
    "gn:timezone":"Asia/Shanghai",
    "iso:country":"CN",
    "name:zho_x_preferred":[
        "\u5e99\u5cad\u5c6f"
    ],
    "wof:name":"Miaolingtun",
    "wof:placetype":"locality"
},
  "geometry": {"coordinates":[127.54792999999999,45.76839],"type":"Point"}
}