{
  "type": "Feature",
  "properties": {
    "gn:admin1_code":"14.0",
    "gn:asciiname":"Ngarzhag",
    "gn:country_code":"CN",
    "gn:dem":4482,
    "gn:feature_class":"P",
    "gn:feature_code":"PPL",
    "gn:name":"Ngarzhag",
    "gn:population":0,
    "gn:timezone":"Asia/Urumqi",
    "iso:country":"CN",
    "name:bod_x_preferred":[
        "\u0f58\u0f44\u0f62\u0f0b\u0f56\u0fb2\u0f42"
    ],
    "name:msa_x_preferred":[
        "Ngarzhag"
    ],
    "name:und_x_variant":[
        "Azha"
    ],
    "name:zho_x_preferred":[
        "\u963f\u624e"
    ],
    "wof:name":"Ngarzhag",
    "wof:placetype":"locality"
},
  "geometry": {"coordinates":[90.60545,28.97406],"type":"Point"}
}