{
  "type": "Feature",
  "properties": {
    "gn:admin1_code":"18",
    "gn:asciiname":"Songkefen",
    "gn:country_code":"CN",
    "gn:dem":642,
    "gn:feature_class":"P",
    "gn:feature_code":"PPL",
    "gn:name":"Songkefen",
    "gn:population":0,
    "gn:timezone":"Asia/Shanghai",
    "iso:country":"CN",
    "name:zho_x_preferred":[
        "\u9001\u5ba2\u4efd"
    ],
    "wof:name":"Songkefen",
    "wof:placetype":"locality"
},
  "geometry": {"coordinates":[106.79000000000001,28.4204],"type":"Point"}
}