{
  "type": "Feature",
  "properties": {
    "gn:admin1_code":"15.0",
    "gn:asciiname":"Xiaowan Nongchang",
    "gn:country_code":"CN",
    "gn:dem":1233,
    "gn:feature_class":"P",
    "gn:feature_code":"PPLF",
    "gn:name":"Xiaowan Nongchang",
    "gn:population":0,
    "gn:timezone":"Asia/Urumqi",
    "iso:country":"CN",
    "name:zho_x_preferred":[
        "\u5c0f\u5b9b\u519c\u573a"
    ],
    "wof:name":"Xiaowan Nongchang",
    "wof:placetype":"locality"
},
  "geometry": {"coordinates":[96.05155999999999,40.53729000000001],"type":"Point"}
}