{
  "type": "Feature",
  "properties": {
    "gn:admin1_code":"25",
    "gn:asciiname":"Yuquanzhuang",
    "gn:country_code":"CN",
    "gn:dem":121,
    "gn:feature_class":"P",
    "gn:feature_code":"PPL",
    "gn:name":"Yuquanzhuang",
    "gn:population":0,
    "gn:timezone":"Asia/Shanghai",
    "iso:country":"CN",
    "name:zho_x_preferred":[
        "\u7389\u6cc9\u5e84"
    ],
    "wof:name":"Yuquanzhuang",
    "wof:placetype":"locality"
},
  "geometry": {"coordinates":[118.09099999999999,35.1519],"type":"Point"}
}