{
  "type": "Feature",
  "properties": {
    "gn:admin1_code":"12.0",
    "gn:asciiname":"Xiaojiagou",
    "gn:country_code":"CN",
    "gn:dem":168,
    "gn:feature_class":"P",
    "gn:feature_code":"PPL",
    "gn:name":"Xiaojiagou",
    "gn:population":0,
    "gn:timezone":"Asia/Shanghai",
    "iso:country":"CN",
    "name:zho_x_preferred":[
        "Xiaojiagou"
    ],
    "name:zho_x_variant":[
        "\u8096\u5bb6\u6c9f"
    ],
    "wof:name":"Xiaojiagou",
    "wof:placetype":"locality"
},
  "geometry": {"coordinates":[111.79103000000001,30.93907],"type":"Point"}
}