{
  "type": "Feature",
  "properties": {
    "gn:admin1_code":"25.0",
    "gn:asciiname":"Dagutou",
    "gn:country_code":"CN",
    "gn:dem":48,
    "gn:feature_class":"P",
    "gn:feature_code":"PPL",
    "gn:name":"Dagutou",
    "gn:population":0,
    "gn:timezone":"Asia/Shanghai",
    "iso:country":"CN",
    "name:zho_x_preferred":[
        "\u5927\u5d2e\u5934"
    ],
    "wof:name":"Dagutou",
    "wof:placetype":"locality"
},
  "geometry": {"coordinates":[121.37223,37.09077],"type":"Point"}
}