{
  "type": "Feature",
  "properties": {
    "gn:admin1_code":"25",
    "gn:asciiname":"Changmazhuang",
    "gn:country_code":"CN",
    "gn:dem":246,
    "gn:feature_class":"P",
    "gn:feature_code":"PPL",
    "gn:name":"Changmazhuang",
    "gn:population":0,
    "gn:timezone":"Asia/Shanghai",
    "iso:country":"CN",
    "name:zho_x_preferred":[
        "\u5e38\u9a6c\u5e84"
    ],
    "wof:name":"Changmazhuang",
    "wof:placetype":"locality"
},
  "geometry": {"coordinates":[117.79600000000001,35.6766],"type":"Point"}
}