{
  "type": "Feature",
  "properties": {
    "gn:admin1_code":"11.0",
    "gn:asciiname":"Yangmei Lijia",
    "gn:country_code":"CN",
    "gn:dem":114,
    "gn:feature_class":"P",
    "gn:feature_code":"PPL",
    "gn:name":"Yangmei Lijia",
    "gn:population":0,
    "gn:timezone":"Asia/Shanghai",
    "iso:country":"CN",
    "name:zho_x_preferred":[
        "\u6768\u6885\u674e\u5bb6"
    ],
    "wof:name":"Yangmei Lijia",
    "wof:placetype":"locality"
},
  "geometry": {"coordinates":[112.19258000000001,26.64699],"type":"Point"}
}