{
  "type": "Feature",
  "properties": {
    "gn:admin1_code":"2.0",
    "gn:asciiname":"Loujiawu",
    "gn:country_code":"CN",
    "gn:dem":397,
    "gn:feature_class":"P",
    "gn:feature_code":"PPL",
    "gn:name":"Loujiawu",
    "gn:population":0,
    "gn:timezone":"Asia/Shanghai",
    "iso:country":"CN",
    "name:zho_x_preferred":[
        "\u5a04\u5bb6\u575e"
    ],
    "wof:name":"Loujiawu",
    "wof:placetype":"locality"
},
  "geometry": {"coordinates":[121.09730999999999,29.51629],"type":"Point"}
}