{
  "type": "Feature",
  "properties": {
    "gn:admin1_code":"4.0",
    "gn:asciiname":"Qianshizhuang",
    "gn:country_code":"CN",
    "gn:dem":7,
    "gn:feature_class":"P",
    "gn:feature_code":"PPL",
    "gn:name":"Qianshizhuang",
    "gn:population":0,
    "gn:timezone":"Asia/Shanghai",
    "iso:country":"CN",
    "name:zho_x_preferred":[
        "\u524d\u67ff\u5e84"
    ],
    "wof:name":"Qianshizhuang",
    "wof:placetype":"locality"
},
  "geometry": {"coordinates":[119.69580000000001,31.515],"type":"Point"}
}