{
  "type": "Feature",
  "properties": {
    "gn:admin1_code":"7",
    "gn:asciiname":"Dafengshan Nongchang",
    "gn:country_code":"CN",
    "gn:dem":302,
    "gn:feature_class":"P",
    "gn:feature_code":"PPLF",
    "gn:name":"Dafengshan Nongchang",
    "gn:population":0,
    "gn:timezone":"Asia/Shanghai",
    "iso:country":"CN",
    "name:und_x_variant":[
        "\u5927\u4e30\u5c71\u519c\u573a"
    ],
    "wof:name":"Dafengshan Nongchang",
    "wof:placetype":"locality"
},
  "geometry": {"coordinates":[116.84325,25.99221],"type":"Point"}
}