{
  "type": "Feature",
  "properties": {
    "gn:admin1_code":"30",
    "gn:asciiname":"Huangbei",
    "gn:country_code":"CN",
    "gn:dem":180,
    "gn:feature_class":"P",
    "gn:feature_code":"PPLA4",
    "gn:name":"Huangbei",
    "gn:population":0,
    "gn:timezone":"Asia/Shanghai",
    "iso:country":"CN",
    "name:und_x_variant":[
        "Wongpo",
        "Huang-pei",
        "Huangbei Zhen",
        "Huangbei",
        "Huangpi Zhen",
        "\u9ec4\u9642\u9547"
    ],
    "name:zho_x_preferred":[
        "Huang-p\u2019o"
    ],
    "name:zho_x_variant":[
        "\u9ec4\u9642",
        "Huang-pei-hs\u00fc"
    ],
    "wof:name":"Huangbei",
    "wof:placetype":"locality"
},
  "geometry": {"coordinates":[115.73814,24.41147],"type":"Point"}
}