{
  "type": "Feature",
  "properties": {
    "gn:admin1_code":"2.0",
    "gn:asciiname":"Lichetou",
    "gn:country_code":"CN",
    "gn:dem":603,
    "gn:feature_class":"P",
    "gn:feature_code":"PPL",
    "gn:name":"Lichetou",
    "gn:population":0,
    "gn:timezone":"Asia/Shanghai",
    "iso:country":"CN",
    "name:zho_x_preferred":[
        "\u91cc\u8f66\u5934"
    ],
    "wof:name":"Lichetou",
    "wof:placetype":"locality"
},
  "geometry": {"coordinates":[121.24366999999999,29.43384],"type":"Point"}
}