{
  "type": "Feature",
  "properties": {
    "gn:admin1_code":"19.0",
    "gn:asciiname":"Qianzhantuncun",
    "gn:country_code":"CN",
    "gn:dem":68,
    "gn:feature_class":"P",
    "gn:feature_code":"PPL",
    "gn:name":"Qianzhantuncun",
    "gn:population":0,
    "gn:timezone":"Asia/Shanghai",
    "iso:country":"CN",
    "name:zho_x_preferred":[
        "\u524d\u5360\u5c6f\u6751"
    ],
    "wof:name":"Qianzhantuncun",
    "wof:placetype":"locality"
},
  "geometry": {"coordinates":[123.51000000000001,41.9228],"type":"Point"}
}