{
  "type": "Feature",
  "properties": {
    "gn:admin1_code":"26.0",
    "gn:asciiname":"Yan'erba",
    "gn:country_code":"CN",
    "gn:dem":606,
    "gn:feature_class":"P",
    "gn:feature_code":"PPL",
    "gn:name":"Yan\u2019erba",
    "gn:population":0,
    "gn:timezone":"Asia/Shanghai",
    "iso:country":"CN",
    "name:und_x_variant":[
        "Yan\u2019erba",
        "\u5ca9\u513f\u575d"
    ],
    "wof:name":"Yan'erba",
    "wof:placetype":"locality"
},
  "geometry": {"coordinates":[107.05368,32.93733],"type":"Point"}
}