{
  "type": "Feature",
  "properties": {
    "gn:admin1_code":"26.0",
    "gn:asciiname":"Huwo Beizuishang",
    "gn:country_code":"CN",
    "gn:dem":1351,
    "gn:feature_class":"P",
    "gn:feature_code":"PPL",
    "gn:name":"Huwo Beizuishang",
    "gn:population":0,
    "gn:timezone":"Asia/Shanghai",
    "iso:country":"CN",
    "name:zho_x_preferred":[
        "\u864e\u7a9d\u5317\u5480\u4e0a"
    ],
    "wof:name":"Huwo Beizuishang",
    "wof:placetype":"locality"
},
  "geometry": {"coordinates":[108.11641000000002,33.90243],"type":"Point"}
}