{
  "type": "Feature",
  "properties": {
    "gn:admin1_code":"19.0",
    "gn:asciiname":"Wenjiagou",
    "gn:country_code":"CN",
    "gn:dem":184,
    "gn:feature_class":"P",
    "gn:feature_code":"PPL",
    "gn:name":"Wenjiagou",
    "gn:population":0,
    "gn:timezone":"Asia/Shanghai",
    "iso:country":"CN",
    "name:und_x_variant":[
        "\u6e29\u5bb6\u6c9f"
    ],
    "wof:name":"Wenjiagou",
    "wof:placetype":"locality"
},
  "geometry": {"coordinates":[122.60396,40.11221],"type":"Point"}
}