{
  "type": "Feature",
  "properties": {
    "gn:admin1_code":"4.0",
    "gn:asciiname":"Xiaocao",
    "gn:country_code":"CN",
    "gn:dem":4,
    "gn:feature_class":"P",
    "gn:feature_code":"PPL",
    "gn:name":"Xiaocao",
    "gn:population":0,
    "gn:timezone":"Asia/Shanghai",
    "iso:country":"CN",
    "name:zho_x_preferred":[
        "Xiaocao"
    ],
    "name:zho_x_variant":[
        "\u5c0f\u66f9"
    ],
    "wof:name":"Xiaocao",
    "wof:placetype":"locality"
},
  "geometry": {"coordinates":[119.59578,33.74413],"type":"Point"}
}