{
  "type": "Feature",
  "properties": {
    "gn:admin1_code":"19.0",
    "gn:asciiname":"Sujia Buzi",
    "gn:country_code":"CN",
    "gn:dem":460,
    "gn:feature_class":"P",
    "gn:feature_code":"PPL",
    "gn:name":"Sujia Buzi",
    "gn:population":0,
    "gn:timezone":"Asia/Shanghai",
    "iso:country":"CN",
    "name:und_x_variant":[
        "Sujiabaozi",
        "Sujia Buzi"
    ],
    "name:zho_x_preferred":[
        "\u82cf\u5bb6\u5821\u5b50"
    ],
    "wof:name":"Sujia Buzi",
    "wof:placetype":"locality"
},
  "geometry": {"coordinates":[123.61468000000001,40.80738],"type":"Point"}
}