{
  "type": "Feature",
  "properties": {
    "gn:admin1_code":"19.0",
    "gn:asciiname":"Diaojiagou",
    "gn:country_code":"CN",
    "gn:dem":34,
    "gn:feature_class":"P",
    "gn:feature_code":"PPL",
    "gn:name":"Diaojiagou",
    "gn:population":0,
    "gn:timezone":"Asia/Shanghai",
    "iso:country":"CN",
    "name:zho_x_preferred":[
        "\u5201\u5bb6\u6c9f"
    ],
    "wof:name":"Diaojiagou",
    "wof:placetype":"locality"
},
  "geometry": {"coordinates":[123.205,39.9156],"type":"Point"}
}