{
  "type": "Feature",
  "properties": {
    "gn:admin1_code":"21.0",
    "gn:asciiname":"Laoquanwan",
    "gn:country_code":"CN",
    "gn:dem":1377,
    "gn:feature_class":"P",
    "gn:feature_code":"PPL",
    "gn:name":"Laoquanwan",
    "gn:population":0,
    "gn:timezone":"Asia/Shanghai",
    "iso:country":"CN",
    "name:zho_x_preferred":[
        "\u8001\u5708\u6e7e"
    ],
    "wof:name":"Laoquanwan",
    "wof:placetype":"locality"
},
  "geometry": {"coordinates":[106.742,37.9708],"type":"Point"}
}