{
  "type": "Feature",
  "properties": {
    "gn:admin1_code":"8.0",
    "gn:asciiname":"Songyuancun",
    "gn:country_code":"CN",
    "gn:dem":121,
    "gn:feature_class":"P",
    "gn:feature_code":"PPL",
    "gn:name":"Songyuancun",
    "gn:population":0,
    "gn:timezone":"Asia/Shanghai",
    "iso:country":"CN",
    "name:zho_x_preferred":[
        "\u677e\u6e90\u6751"
    ],
    "wof:name":"Songyuancun",
    "wof:placetype":"locality"
},
  "geometry": {"coordinates":[126.63495,45.91725],"type":"Point"}
}