{
  "type": "Feature",
  "properties": {
    "gn:admin1_code":"15.0",
    "gn:asciiname":"Xianmaqu",
    "gn:country_code":"CN",
    "gn:dem":1319,
    "gn:feature_class":"P",
    "gn:feature_code":"PPL",
    "gn:name":"Xianmaqu",
    "gn:population":0,
    "gn:timezone":"Asia/Shanghai",
    "iso:country":"CN",
    "name:und_x_variant":[
        "\u82cb\u9ebb\u6e20"
    ],
    "wof:name":"Xianmaqu",
    "wof:placetype":"locality"
},
  "geometry": {"coordinates":[107.2153,36.3002],"type":"Point"}
}