{
  "type": "Feature",
  "properties": {
    "gn:admin1_code":"4.0",
    "gn:asciiname":"Xiaomawang",
    "gn:country_code":"CN",
    "gn:dem":21,
    "gn:feature_class":"P",
    "gn:feature_code":"PPL",
    "gn:name":"Xiaomawang",
    "gn:population":0,
    "gn:timezone":"Asia/Shanghai",
    "iso:country":"CN",
    "name:zho_x_preferred":[
        "\u5c0f\u9ebb\u6c6a"
    ],
    "wof:name":"Xiaomawang",
    "wof:placetype":"locality"
},
  "geometry": {"coordinates":[118.72199999999999,34.581],"type":"Point"}
}