{
  "type": "Feature",
  "properties": {
    "iso:country":"CN",
    "name:bod_x_preferred":[
        "\u0f50\u0f74\u0f44\u0f0b\u0f62\u0f7a\u0f53\u0f0b"
    ],
    "name:ceb_x_preferred":[
        "Tongren Xian"
    ],
    "name:deu_x_preferred":[
        "Tongren"
    ],
    "name:eng_x_preferred":[
        "Tongren County"
    ],
    "name:fas_x_preferred":[
        "\u0634\u0647\u0631\u0633\u062a\u0627\u0646 \u062a\u0648\u0646\u06af\u0631\u0646"
    ],
    "name:gan_x_preferred":[
        "\u540c\u4ec1\u53bf"
    ],
    "name:jpn_x_preferred":[
        "\u540c\u4ec1\u770c"
    ],
    "name:kor_x_preferred":[
        "\ud241\ub7f0\ud604"
    ],
    "name:nan_x_preferred":[
        "T\u00f4ng-j\u00een-ko\u0101n"
    ],
    "name:nld_x_preferred":[
        "Tongren"
    ],
    "name:nob_x_preferred":[
        "Tongren"
    ],
    "name:rus_x_preferred":[
        "\u0422\u0443\u043d\u0436\u044d\u043d\u044c"
    ],
    "name:swe_x_preferred":[
        "Tongren"
    ],
    "name:urd_x_preferred":[
        "\u062a\u0648\u0646\u06af\u0631\u06cc\u0646 \u06a9\u0627\u0624\u0646\u0679\u06cc"
    ],
    "name:vie_x_preferred":[
        "\u0110\u1ed3ng Nh\u00e2n"
    ],
    "name:wuu_x_preferred":[
        "\u540c\u4ec1\u53bf"
    ],
    "name:zho_x_preferred":[
        "\u540c\u4ec1\u53bf"
    ],
    "qs:name":"\u540c\u4ec1\u53bf",
    "qs:name_adm0":"\u4e2d\u570b",
    "qs:name_adm1":"\u9752\u6d77\u7701",
    "qs:photos":44,
    "qs:photos_1k":9,
    "qs:photos_9k":3,
    "qs:photos_9r":5,
    "qs:photos_all":662,
    "qs:photos_sr":2,
    "qs:placetype":"LocalAdmin",
    "qs:pop_sr":"0",
    "wd:wordcount":431,
    "wof:name":"\u540c\u4ec1\u53bf",
    "wof:placetype":"localadmin"
},
  "geometry": {"coordinates":[102.009773,35.507242],"type":"Point"}
}