{
  "type": "Feature",
  "properties": {
    "iso:country":"CN",
    "qs:name":"\u540c\u4ec1\u53bf",
    "qs:name_adm0":"\u4e2d\u570b",
    "qs:name_adm1":"\u9752\u6d77\u7701",
    "qs:photos":44,
    "qs:photos_1k":9,
    "qs:photos_9k":3,
    "qs:photos_9r":5,
    "qs:photos_all":662,
    "qs:photos_sr":2,
    "qs:placetype":"LocalAdmin",
    "qs:pop_sr":"0",
    "wd:wordcount":431,
    "wof:name":"\u540c\u4ec1\u53bf",
    "wof:placetype":"localadmin"
},
  "geometry": {"coordinates":[102.009773,35.507242],"type":"Point"}
}