{
  "type": "Feature",
  "properties": {
    "gn:admin1_code":"11.0",
    "gn:asciiname":"Guantouling",
    "gn:country_code":"CN",
    "gn:dem":115,
    "gn:feature_class":"P",
    "gn:feature_code":"PPL",
    "gn:name":"Guantouling",
    "gn:population":0,
    "gn:timezone":"Asia/Shanghai",
    "iso:country":"CN",
    "name:zho_x_preferred":[
        "\u5173\u5934\u5cad"
    ],
    "wof:name":"Guantouling",
    "wof:placetype":"locality"
},
  "geometry": {"coordinates":[112.90355,26.8194],"type":"Point"}
}