{
  "type": "Feature",
  "properties": {
    "gn:admin1_code":"10",
    "gn:asciiname":"Dawangzhuang",
    "gn:cc2":"CN",
    "gn:country_code":"CN",
    "gn:dem":7,
    "gn:feature_class":"P",
    "gn:feature_code":"PPL",
    "gn:name":"Dawangzhuang",
    "gn:population":0,
    "gn:timezone":"Asia/Shanghai",
    "iso:country":"CN",
    "name:und_x_variant":[
        "Ta-wang-chuang",
        "Dawangzhuang"
    ],
    "wof:name":"Dawangzhuang",
    "wof:placetype":"locality"
},
  "geometry": {"coordinates":[115.92972,38.98556],"type":"Point"}
}