{
  "type": "Feature",
  "properties": {
    "gn:admin1_code":"5.0",
    "gn:asciiname":"Changfacun",
    "gn:country_code":"CN",
    "gn:dem":207,
    "gn:feature_class":"P",
    "gn:feature_code":"PPL",
    "gn:name":"Changfacun",
    "gn:population":0,
    "gn:timezone":"Asia/Shanghai",
    "iso:country":"CN",
    "name:zho_x_preferred":[
        "\u957f\u53d1\u6751"
    ],
    "wof:name":"Changfacun",
    "wof:placetype":"locality"
},
  "geometry": {"coordinates":[126.35896,44.9914],"type":"Point"}
}