{
  "type": "Feature",
  "properties": {
    "gn:admin1_code":"3.0",
    "gn:asciiname":"Shantian Hongjia",
    "gn:country_code":"CN",
    "gn:dem":62,
    "gn:feature_class":"P",
    "gn:feature_code":"PPL",
    "gn:name":"Shantian Hongjia",
    "gn:population":0,
    "gn:timezone":"Asia/Shanghai",
    "iso:country":"CN",
    "name:zho_x_preferred":[
        "\u5c71\u7530\u6d2a\u5bb6"
    ],
    "wof:name":"Shantian Hongjia",
    "wof:placetype":"locality"
},
  "geometry": {"coordinates":[117.02285000000001,28.77899],"type":"Point"}
}