{
  "type": "Feature",
  "properties": {
    "gn:admin1_code":"19.0",
    "gn:asciiname":"Taigoucun",
    "gn:country_code":"CN",
    "gn:dem":64,
    "gn:feature_class":"P",
    "gn:feature_code":"PPL",
    "gn:name":"Taigoucun",
    "gn:population":0,
    "gn:timezone":"Asia/Shanghai",
    "iso:country":"CN",
    "name:zho_x_preferred":[
        "\u53f0\u6c9f\u6751"
    ],
    "wof:name":"Taigoucun",
    "wof:placetype":"locality"
},
  "geometry": {"coordinates":[124.86001,40.49662],"type":"Point"}
}