{
  "type": "Feature",
  "properties": {
    "gn:admin1_code":"18.0",
    "gn:asciiname":"Yinyangtun",
    "gn:country_code":"CN",
    "gn:dem":1119,
    "gn:feature_class":"P",
    "gn:feature_code":"PPL",
    "gn:name":"Yinyangtun",
    "gn:population":0,
    "gn:timezone":"Asia/Shanghai",
    "iso:country":"CN",
    "name:zho_x_preferred":[
        "\u9634\u9633\u5c6f"
    ],
    "wof:name":"Yinyangtun",
    "wof:placetype":"locality"
},
  "geometry": {"coordinates":[108.00700000000001,26.8727],"type":"Point"}
}