{
  "type": "Feature",
  "properties": {
    "gn:admin1_code":"10.0",
    "gn:asciiname":"Shageda",
    "gn:country_code":"CN",
    "gn:dem":615,
    "gn:feature_class":"P",
    "gn:feature_code":"PPL",
    "gn:name":"Shageda",
    "gn:population":0,
    "gn:timezone":"Asia/Shanghai",
    "iso:country":"CN",
    "name:zho_x_preferred":[
        "\u6c99\u572a\u57af"
    ],
    "wof:name":"Shageda",
    "wof:placetype":"locality"
},
  "geometry": {"coordinates":[114.98594,40.61969000000001],"type":"Point"}
}