{
  "type": "Feature",
  "properties": {
    "gn:admin1_code":"5.0",
    "gn:asciiname":"Suojiatun",
    "gn:country_code":"CN",
    "gn:dem":261,
    "gn:feature_class":"P",
    "gn:feature_code":"PPL",
    "gn:name":"Suojiatun",
    "gn:population":0,
    "gn:timezone":"Asia/Shanghai",
    "iso:country":"CN",
    "name:zho_x_preferred":[
        "\u7d22\u5bb6\u5c6f"
    ],
    "wof:name":"Suojiatun",
    "wof:placetype":"locality"
},
  "geometry": {"coordinates":[126.18644,43.72545],"type":"Point"}
}