{
  "type": "Feature",
  "properties": {
    "gn:admin1_code":"26",
    "gn:asciiname":"Shipojie",
    "gn:cc2":"CN",
    "gn:country_code":"CN",
    "gn:dem":974,
    "gn:feature_class":"P",
    "gn:feature_code":"PPL",
    "gn:name":"Shipojie",
    "gn:population":0,
    "gn:timezone":"Asia/Shanghai",
    "iso:country":"CN",
    "name:und_x_variant":[
        "Shekiapu",
        "Shitszyabochzhen",
        "Shipo",
        "Shih-chia-p\u2019o-chen",
        "Shih-p\u2019o",
        "Shipojie"
    ],
    "wof:name":"Shipojie",
    "wof:placetype":"locality"
},
  "geometry": {"coordinates":[110.29528000000001,34.1975],"type":"Point"}
}