{
  "type": "Feature",
  "properties": {
    "gn:admin1_code":"26.0",
    "gn:asciiname":"Liujia Guacun",
    "gn:country_code":"CN",
    "gn:dem":889,
    "gn:feature_class":"P",
    "gn:feature_code":"PPL",
    "gn:name":"Liujia Guacun",
    "gn:population":0,
    "gn:timezone":"Asia/Shanghai",
    "iso:country":"CN",
    "name:zho_x_preferred":[
        "\u5218\u5bb6\u576c\u6751"
    ],
    "wof:name":"Liujia Guacun",
    "wof:placetype":"locality"
},
  "geometry": {"coordinates":[110.44199999999999,37.159],"type":"Point"}
}