{
  "type": "Feature",
  "properties": {
    "gn:admin1_code":"29.0",
    "gn:asciiname":"Bianlanba",
    "gn:country_code":"CN",
    "gn:dem":1204,
    "gn:feature_class":"P",
    "gn:feature_code":"PPL",
    "gn:name":"Bianlanba",
    "gn:population":0,
    "gn:timezone":"Asia/Shanghai",
    "iso:country":"CN",
    "name:zho_x_preferred":[
        "\u6241\u6984\u575d"
    ],
    "wof:name":"Bianlanba",
    "wof:placetype":"locality"
},
  "geometry": {"coordinates":[99.6271,23.841],"type":"Point"}
}