{
  "type": "Feature",
  "properties": {
    "gn:admin1_code":"24.0",
    "gn:asciiname":"Xituanbu",
    "gn:country_code":"CN",
    "gn:dem":1014,
    "gn:feature_class":"P",
    "gn:feature_code":"PPL",
    "gn:name":"Xituanbu",
    "gn:population":0,
    "gn:timezone":"Asia/Shanghai",
    "iso:country":"CN",
    "name:und_x_variant":[
        "T\u2019uan-pao-ts\u2019un",
        "Hsi-t\u2019uan-pao",
        "Xituanbu",
        "\u897f\u56e2\u5821"
    ],
    "wof:name":"Xituanbu",
    "wof:placetype":"locality"
},
  "geometry": {"coordinates":[113.86002000000001,39.93554],"type":"Point"}
}