{
  "type": "Feature",
  "properties": {
    "gn:admin1_code":"19.0",
    "gn:asciiname":"Delong Chaoxiancun",
    "gn:country_code":"CN",
    "gn:dem":179,
    "gn:feature_class":"P",
    "gn:feature_code":"PPL",
    "gn:name":"Delong Chaoxiancun",
    "gn:population":0,
    "gn:timezone":"Asia/Shanghai",
    "iso:country":"CN",
    "name:zho_x_preferred":[
        "\u5fb7\u9686\u671d\u9c9c\u6751"
    ],
    "wof:name":"Delong Chaoxiancun",
    "wof:placetype":"locality"
},
  "geometry": {"coordinates":[124.566,42.5993],"type":"Point"}
}