{
  "type": "Feature",
  "properties": {
    "gn:admin1_code":"29",
    "gn:asciiname":"Anha",
    "gn:country_code":"CN",
    "gn:dem":868,
    "gn:feature_class":"P",
    "gn:feature_code":"PPL",
    "gn:name":"Anha",
    "gn:population":0,
    "gn:timezone":"Asia/Shanghai",
    "iso:country":"CN",
    "name:ceb_x_preferred":[
        "Anha"
    ],
    "name:kaz_x_preferred":[
        "\u0412\u0438\u043b\u0430-\u041d\u043e\u0432\u0430-\u0434\u0435-\u0410\u043d\u044c\u044f"
    ],
    "name:msa_x_preferred":[
        "Anha"
    ],
    "name:por_x_preferred":[
        "Anha"
    ],
    "name:rus_x_preferred":[
        "\u0412\u0438\u043b\u0430-\u041d\u043e\u0432\u0430-\u0434\u0435-\u0410\u043d\u044c\u044f"
    ],
    "name:spa_x_preferred":[
        "Anha"
    ],
    "name:tur_x_preferred":[
        "Anha"
    ],
    "name:zho_x_preferred":[
        "\u5b89\u54c8"
    ],
    "wof:name":"Anha",
    "wof:placetype":"locality"
},
  "geometry": {"coordinates":[105.902,23.7271],"type":"Point"}
}