{
  "type": "Feature",
  "properties": {
    "gn:admin1_code":"32.0",
    "gn:asciiname":"Dagaozhuping",
    "gn:country_code":"CN",
    "gn:dem":1053,
    "gn:feature_class":"P",
    "gn:feature_code":"PPL",
    "gn:name":"Dagaozhuping",
    "gn:population":0,
    "gn:timezone":"Asia/Shanghai",
    "iso:country":"CN",
    "name:zho_x_preferred":[
        "\u5927\u9ad8\u7af9\u576a"
    ],
    "wof:name":"Dagaozhuping",
    "wof:placetype":"locality"
},
  "geometry": {"coordinates":[105.03,28.1066],"type":"Point"}
}