{
  "type": "Feature",
  "properties": {
    "gn:admin1_code":"10",
    "gn:asciiname":"Ruyi Linzi",
    "gn:country_code":"CN",
    "gn:dem":1489,
    "gn:feature_class":"P",
    "gn:feature_code":"PPL",
    "gn:name":"Ruyi Linzi",
    "gn:population":0,
    "gn:timezone":"Asia/Shanghai",
    "iso:country":"CN",
    "name:zho_x_preferred":[
        "\u5982\u610f\u6797\u5b50"
    ],
    "wof:name":"Ruyi Linzi",
    "wof:placetype":"locality"
},
  "geometry": {"coordinates":[117.22166,42.19417],"type":"Point"}
}