{
  "type": "Feature",
  "properties": {
    "gn:admin1_code":"33.0",
    "gn:asciiname":"Sanquan",
    "gn:country_code":"CN",
    "gn:dem":593,
    "gn:feature_class":"P",
    "gn:feature_code":"PPLA4",
    "gn:name":"Sanquan",
    "gn:population":0,
    "gn:timezone":"Asia/Shanghai",
    "iso:country":"CN",
    "name:und_x_variant":[
        "Sanquan Zhen"
    ],
    "name:zho_x_preferred":[
        "\u4e09\u6cc9"
    ],
    "name:zho_x_variant":[
        "\u4e09\u6cc9\u9547"
    ],
    "wof:name":"Sanquan",
    "wof:placetype":"locality"
},
  "geometry": {"coordinates":[107.20375,29.13233],"type":"Point"}
}