{
  "type": "Feature",
  "properties": {
    "gn:admin1_code":"18.0",
    "gn:asciiname":"Fengxiangxi",
    "gn:country_code":"CN",
    "gn:dem":755,
    "gn:feature_class":"P",
    "gn:feature_code":"PPLA4",
    "gn:name":"Fengxiangxi",
    "gn:population":0,
    "gn:timezone":"Asia/Shanghai",
    "iso:country":"CN",
    "name:und_x_variant":[
        "Fengxiangxi Zhen"
    ],
    "name:zho_x_preferred":[
        "\u67ab\u9999\u6eaa"
    ],
    "name:zho_x_variant":[
        "\u67ab\u9999\u6eaa\u9547"
    ],
    "wof:name":"Fengxiangxi",
    "wof:placetype":"locality"
},
  "geometry": {"coordinates":[108.3241,28.12767],"type":"Point"}
}