{
  "type": "Feature",
  "properties": {
    "gn:admin1_code":"02",
    "gn:asciiname":"Zhizhong",
    "gn:country_code":"CN",
    "gn:dem":20,
    "gn:feature_class":"P",
    "gn:feature_code":"PPL",
    "gn:name":"Zhizhong",
    "gn:population":0,
    "gn:timezone":"Asia/Shanghai",
    "iso:country":"CN",
    "name:und_x_variant":[
        "\u5cd9\u4e2d"
    ],
    "wof:name":"Zhizhong",
    "wof:placetype":"locality"
},
  "geometry": {"coordinates":[122.08056000000001,30.20917],"type":"Point"}
}