{
  "type": "Feature",
  "properties": {
    "gn:admin1_code":"11.0",
    "gn:asciiname":"Yanzhutang",
    "gn:country_code":"CN",
    "gn:dem":54,
    "gn:feature_class":"P",
    "gn:feature_code":"PPL",
    "gn:name":"Yanzhutang",
    "gn:population":0,
    "gn:timezone":"Asia/Shanghai",
    "iso:country":"CN",
    "name:zho_x_preferred":[
        "\u70df\u7af9\u5858"
    ],
    "wof:name":"Yanzhutang",
    "wof:placetype":"locality"
},
  "geometry": {"coordinates":[113.10748,27.39274],"type":"Point"}
}