{
  "type": "Feature",
  "properties": {
    "gn:admin1_code":"32.0",
    "gn:asciiname":"Sinide",
    "gn:country_code":"CN",
    "gn:dem":1887,
    "gn:feature_class":"P",
    "gn:feature_code":"PPL",
    "gn:name":"Sinide",
    "gn:population":0,
    "gn:timezone":"Asia/Shanghai",
    "iso:country":"CN",
    "name:zho_x_preferred":[
        "\u65af\u5c3c\u5fb7"
    ],
    "wof:name":"Sinide",
    "wof:placetype":"locality"
},
  "geometry": {"coordinates":[103.31614999999999,27.70474],"type":"Point"}
}