{
  "type": "Feature",
  "properties": {
    "gn:admin1_code":"32.0",
    "gn:asciiname":"Chazi'amu",
    "gn:country_code":"CN",
    "gn:dem":2768,
    "gn:feature_class":"P",
    "gn:feature_code":"PPL",
    "gn:name":"Chazi\u2019amu",
    "gn:population":0,
    "gn:timezone":"Asia/Shanghai",
    "iso:country":"CN",
    "name:und_x_variant":[
        "Chazi\u2019amu"
    ],
    "name:zho_x_preferred":[
        "\u5c94\u5b50\u963f\u6bcd"
    ],
    "wof:name":"Chazi'amu",
    "wof:placetype":"locality"
},
  "geometry": {"coordinates":[102.374,28.2077],"type":"Point"}
}