{
  "type": "Feature",
  "properties": {
    "gn:admin1_code":"12.0",
    "gn:asciiname":"Jiyangguan",
    "gn:country_code":"CN",
    "gn:dem":784,
    "gn:feature_class":"P",
    "gn:feature_code":"PPL",
    "gn:name":"Jiyangguan",
    "gn:population":0,
    "gn:timezone":"Asia/Shanghai",
    "iso:country":"CN",
    "name:zho_x_preferred":[
        "\u5409\u9633\u5173"
    ],
    "wof:name":"Jiyangguan",
    "wof:placetype":"locality"
},
  "geometry": {"coordinates":[110.09505,32.53044000000001],"type":"Point"}
}