{
  "type": "Feature",
  "properties": {
    "gn:admin1_code":"07",
    "gn:asciiname":"Kengneicun",
    "gn:country_code":"CN",
    "gn:dem":411,
    "gn:feature_class":"P",
    "gn:feature_code":"PPL",
    "gn:name":"Kengneicun",
    "gn:population":0,
    "gn:timezone":"Asia/Shanghai",
    "iso:country":"CN",
    "name:zho_x_preferred":[
        "\u5751\u5185\u6751"
    ],
    "wof:name":"Kengneicun",
    "wof:placetype":"locality"
},
  "geometry": {"coordinates":[116.92225000000001,24.41211],"type":"Point"}
}