{
  "type": "Feature",
  "properties": {
    "gn:admin1_code":"25",
    "gn:asciiname":"Gushanpozi",
    "gn:country_code":"CN",
    "gn:dem":92,
    "gn:feature_class":"P",
    "gn:feature_code":"PPL",
    "gn:name":"Gushanpozi",
    "gn:population":0,
    "gn:timezone":"Asia/Shanghai",
    "iso:country":"CN",
    "name:zho_x_preferred":[
        "\u5d2e\u5c71\u5761\u5b50"
    ],
    "wof:name":"Gushanpozi",
    "wof:placetype":"locality"
},
  "geometry": {"coordinates":[120.13800000000001,37.1879],"type":"Point"}
}