{
  "type": "Feature",
  "properties": {
    "gn:admin1_code":"24.0",
    "gn:asciiname":"Lichakou",
    "gn:country_code":"CN",
    "gn:dem":1584,
    "gn:feature_class":"P",
    "gn:feature_code":"PPL",
    "gn:name":"Lichakou",
    "gn:population":0,
    "gn:timezone":"Asia/Shanghai",
    "iso:country":"CN",
    "name:zho_x_preferred":[
        "\u91cc\u5c94\u53e3"
    ],
    "wof:name":"Lichakou",
    "wof:placetype":"locality"
},
  "geometry": {"coordinates":[112.36891,38.79418],"type":"Point"}
}