{
  "type": "Feature",
  "properties": {
    "gn:admin1_code":"18",
    "gn:asciiname":"Waxiluo",
    "gn:country_code":"CN",
    "gn:dem":2325,
    "gn:feature_class":"P",
    "gn:feature_code":"PPL",
    "gn:name":"Waxiluo",
    "gn:population":0,
    "gn:timezone":"Asia/Shanghai",
    "iso:country":"CN",
    "name:zho_x_preferred":[
        "\u54c7\u5e0c\u502e"
    ],
    "wof:name":"Waxiluo",
    "wof:placetype":"locality"
},
  "geometry": {"coordinates":[104.577,26.7364],"type":"Point"}
}