{
  "type": "Feature",
  "properties": {
    "gn:admin1_code":"9",
    "gn:asciiname":"Wangxin",
    "gn:country_code":"CN",
    "gn:dem":60,
    "gn:feature_class":"P",
    "gn:feature_code":"PPL",
    "gn:name":"Wangxin",
    "gn:population":0,
    "gn:timezone":"Asia/Shanghai",
    "iso:country":"CN",
    "name:zho_x_preferred":[
        "\u738b\u65b0"
    ],
    "wof:name":"Wangxin",
    "wof:placetype":"locality"
},
  "geometry": {"coordinates":[115.00127000000001,35.3742],"type":"Point"}
}