{
  "type": "Feature",
  "properties": {
    "gn:admin1_code":"1.0",
    "gn:asciiname":"Lujiacun",
    "gn:country_code":"CN",
    "gn:dem":38,
    "gn:feature_class":"P",
    "gn:feature_code":"PPL",
    "gn:name":"Lujiacun",
    "gn:population":0,
    "gn:timezone":"Asia/Shanghai",
    "iso:country":"CN",
    "name:zho_x_preferred":[
        "\u9646\u5bb6\u6751"
    ],
    "wof:name":"Lujiacun",
    "wof:placetype":"locality"
},
  "geometry": {"coordinates":[116.86402,34.32249],"type":"Point"}
}