{
  "type": "Feature",
  "properties": {
    "gn:admin1_code":"5.0",
    "gn:asciiname":"Dayangshu Beigang",
    "gn:country_code":"CN",
    "gn:dem":689,
    "gn:feature_class":"P",
    "gn:feature_code":"PPL",
    "gn:name":"Dayangshu Beigang",
    "gn:population":0,
    "gn:timezone":"Asia/Shanghai",
    "iso:country":"CN",
    "name:und_x_variant":[
        "\u5927\u6768\u6811\u5317\u5c97"
    ],
    "wof:name":"Dayangshu Beigang",
    "wof:placetype":"locality"
},
  "geometry": {"coordinates":[127.23313,41.61666],"type":"Point"}
}