{
  "type": "Feature",
  "properties": {
    "gn:admin1_code":"18",
    "gn:asciiname":"Bamunei",
    "gn:country_code":"CN",
    "gn:dem":575,
    "gn:feature_class":"P",
    "gn:feature_code":"PPL",
    "gn:name":"Bamunei",
    "gn:population":0,
    "gn:timezone":"Asia/Shanghai",
    "iso:country":"CN",
    "name:zho_x_preferred":[
        "\u575d\u6728\u5185"
    ],
    "wof:name":"Bamunei",
    "wof:placetype":"locality"
},
  "geometry": {"coordinates":[108.23099999999999,28.8833],"type":"Point"}
}