{
  "type": "Feature",
  "properties": {
    "gn:admin1_code":"15.0",
    "gn:asciiname":"Miaoquyuan",
    "gn:country_code":"CN",
    "gn:dem":1627,
    "gn:feature_class":"P",
    "gn:feature_code":"PPL",
    "gn:name":"Miaoquyuan",
    "gn:population":0,
    "gn:timezone":"Asia/Shanghai",
    "iso:country":"CN",
    "name:und_x_variant":[
        "\u5e99\u6e20\u9662"
    ],
    "wof:name":"Miaoquyuan",
    "wof:placetype":"locality"
},
  "geometry": {"coordinates":[106.80671,36.50429000000001],"type":"Point"}
}