{
  "type": "Feature",
  "properties": {
    "gn:admin1_code":"25",
    "gn:asciiname":"Houzhujiazhuang",
    "gn:country_code":"CN",
    "gn:dem":74,
    "gn:feature_class":"P",
    "gn:feature_code":"PPL",
    "gn:name":"Houzhujiazhuang",
    "gn:population":0,
    "gn:timezone":"Asia/Shanghai",
    "iso:country":"CN",
    "name:zho_x_preferred":[
        "\u540e\u6731\u5bb6\u5e84"
    ],
    "wof:name":"Houzhujiazhuang",
    "wof:placetype":"locality"
},
  "geometry": {"coordinates":[119.194,36.2071],"type":"Point"}
}