{
  "type": "Feature",
  "properties": {
    "gn:admin1_code":"25.0",
    "gn:asciiname":"Luantuncun",
    "gn:country_code":"CN",
    "gn:dem":41,
    "gn:feature_class":"P",
    "gn:feature_code":"PPL",
    "gn:name":"Luantuncun",
    "gn:population":0,
    "gn:timezone":"Asia/Shanghai",
    "iso:country":"CN",
    "name:zho_x_preferred":[
        "\u683e\u5c6f\u6751"
    ],
    "wof:name":"Luantuncun",
    "wof:placetype":"locality"
},
  "geometry": {"coordinates":[115.64628,36.10482],"type":"Point"}
}