{
  "type": "Feature",
  "properties": {
    "gn:admin1_code":"15",
    "gn:asciiname":"Lixin",
    "gn:country_code":"CN",
    "gn:dem":1562,
    "gn:feature_class":"P",
    "gn:feature_code":"PPL",
    "gn:name":"Lixin",
    "gn:population":0,
    "gn:timezone":"Asia/Shanghai",
    "iso:country":"CN",
    "name:ceb_x_preferred":[
        "Lixin"
    ],
    "name:deu_x_preferred":[
        "Lixin"
    ],
    "wof:name":"Lixin",
    "wof:placetype":"locality"
},
  "geometry": {"coordinates":[105.08056000000001,34.91222],"type":"Point"}
}