{
  "type": "Feature",
  "properties": {
    "gn:admin1_code":"32.0",
    "gn:asciiname":"Baimatan",
    "gn:country_code":"CN",
    "gn:dem":449,
    "gn:feature_class":"P",
    "gn:feature_code":"PPL",
    "gn:name":"Baimatan",
    "gn:population":0,
    "gn:timezone":"Asia/Shanghai",
    "iso:country":"CN",
    "name:zho_x_preferred":[
        "\u767d\u9a6c\u6ee9"
    ],
    "wof:name":"Baimatan",
    "wof:placetype":"locality"
},
  "geometry": {"coordinates":[103.96835,30.39537],"type":"Point"}
}