{
  "type": "Feature",
  "properties": {
    "gn:admin1_code":"15.0",
    "gn:asciiname":"Shaogou",
    "gn:country_code":"CN",
    "gn:dem":1934,
    "gn:feature_class":"P",
    "gn:feature_code":"PPL",
    "gn:name":"Shaogou",
    "gn:population":0,
    "gn:timezone":"Asia/Shanghai",
    "iso:country":"CN",
    "name:zho_x_preferred":[
        "\u7a0d\u6c9f"
    ],
    "wof:name":"Shaogou",
    "wof:placetype":"locality"
},
  "geometry": {"coordinates":[105.32899999999999,36.3197],"type":"Point"}
}