{
  "type": "Feature",
  "properties": {
    "gn:admin1_code":"12",
    "gn:asciiname":"Guandukou",
    "gn:country_code":"CN",
    "gn:dem":117,
    "gn:feature_class":"P",
    "gn:feature_code":"PPLA4",
    "gn:name":"Guandukou",
    "gn:population":0,
    "gn:timezone":"Asia/Shanghai",
    "iso:country":"CN",
    "name:und_x_variant":[
        "Kuan-tu-k\u2019ou",
        "Guandukou",
        "Guandukou Zhen"
    ],
    "name:zho_x_preferred":[
        "\u5b98\u6e21\u53e3"
    ],
    "name:zho_x_variant":[
        "\u5b98\u6e21\u53e3\u9547"
    ],
    "wof:name":"Guandukou",
    "wof:placetype":"locality"
},
  "geometry": {"coordinates":[110.30901,31.03921],"type":"Point"}
}