{
  "type": "Feature",
  "properties": {
    "gn:admin1_code":"15.0",
    "gn:asciiname":"Fenping",
    "gn:country_code":"CN",
    "gn:dem":976,
    "gn:feature_class":"P",
    "gn:feature_code":"PPL",
    "gn:name":"Fenping",
    "gn:population":0,
    "gn:timezone":"Asia/Shanghai",
    "iso:country":"CN",
    "name:und_x_variant":[
        "\u575f\u576a"
    ],
    "wof:name":"Fenping",
    "wof:placetype":"locality"
},
  "geometry": {"coordinates":[105.77785,33.22955],"type":"Point"}
}