{
  "type": "Feature",
  "properties": {
    "gn:admin1_code":"20.0",
    "gn:asciiname":"Guanghechang",
    "gn:country_code":"CN",
    "gn:dem":1668,
    "gn:feature_class":"P",
    "gn:feature_code":"PPL",
    "gn:name":"Guanghechang",
    "gn:population":0,
    "gn:timezone":"Asia/Shanghai",
    "iso:country":"CN",
    "name:und_x_variant":[
        "\u5e7f\u548c\u660c"
    ],
    "wof:name":"Guanghechang",
    "wof:placetype":"locality"
},
  "geometry": {"coordinates":[111.52516,41.23131],"type":"Point"}
}