{
  "type": "Feature",
  "properties": {
    "gn:admin1_code":"16.0",
    "gn:asciiname":"Funancun",
    "gn:country_code":"CN",
    "gn:dem":61,
    "gn:feature_class":"P",
    "gn:feature_code":"PPL",
    "gn:name":"Funancun",
    "gn:population":0,
    "gn:timezone":"Asia/Shanghai",
    "iso:country":"CN",
    "name:zho_x_preferred":[
        "\u6276\u5357\u6751"
    ],
    "wof:name":"Funancun",
    "wof:placetype":"locality"
},
  "geometry": {"coordinates":[110.90900000000001,23.0725],"type":"Point"}
}