{
  "type": "Feature",
  "properties": {
    "gn:admin1_code":"11.0",
    "gn:asciiname":"Jiangmi",
    "gn:country_code":"CN",
    "gn:dem":695,
    "gn:feature_class":"P",
    "gn:feature_code":"PPL",
    "gn:name":"Jiangmi",
    "gn:population":0,
    "gn:timezone":"Asia/Shanghai",
    "iso:country":"CN",
    "name:zho_x_preferred":[
        "\u6c5f\u7c73"
    ],
    "wof:name":"Jiangmi",
    "wof:placetype":"locality"
},
  "geometry": {"coordinates":[109.30592,27.21033],"type":"Point"}
}