{
  "type": "Feature",
  "properties": {
    "gn:admin1_code":"10",
    "gn:asciiname":"Chaye Goumen",
    "gn:country_code":"CN",
    "gn:dem":540,
    "gn:feature_class":"P",
    "gn:feature_code":"PPL",
    "gn:name":"Chaye Goumen",
    "gn:population":0,
    "gn:timezone":"Asia/Shanghai",
    "iso:country":"CN",
    "name:zho_x_preferred":[
        "\u8336\u53f6\u6c9f\u95e8"
    ],
    "wof:name":"Chaye Goumen",
    "wof:placetype":"locality"
},
  "geometry": {"coordinates":[117.74927,41.08487],"type":"Point"}
}