{
  "type": "Feature",
  "properties": {
    "gn:admin1_code":"1.0",
    "gn:asciiname":"Danzhuangcun",
    "gn:country_code":"CN",
    "gn:dem":24,
    "gn:feature_class":"P",
    "gn:feature_code":"PPL",
    "gn:name":"Danzhuangcun",
    "gn:population":0,
    "gn:timezone":"Asia/Shanghai",
    "iso:country":"CN",
    "name:zho_x_preferred":[
        "\u5355\u5e84\u6751"
    ],
    "wof:name":"Danzhuangcun",
    "wof:placetype":"locality"
},
  "geometry": {"coordinates":[117.41358,33.34423],"type":"Point"}
}