{
  "type": "Feature",
  "properties": {
    "gn:admin1_code":"02",
    "gn:asciiname":"Bei'ao",
    "gn:country_code":"CN",
    "gn:dem":18,
    "gn:feature_class":"P",
    "gn:feature_code":"PPL",
    "gn:name":"Bei\u2019ao",
    "gn:population":0,
    "gn:timezone":"Asia/Shanghai",
    "iso:country":"CN",
    "name:und_x_variant":[
        "Pei-ch\u2019ang-sha",
        "Bei\u2019ao"
    ],
    "wof:name":"Bei'ao",
    "wof:placetype":"locality"
},
  "geometry": {"coordinates":[121.91556,30.04306],"type":"Point"}
}