{
  "type": "Feature",
  "properties": {
    "gn:admin1_code":"5.0",
    "gn:asciiname":"Miaodong",
    "gn:country_code":"CN",
    "gn:dem":435,
    "gn:feature_class":"P",
    "gn:feature_code":"PPL",
    "gn:name":"Miaodong",
    "gn:population":0,
    "gn:timezone":"Asia/Shanghai",
    "iso:country":"CN",
    "name:und_x_variant":[
        "\u5e99\u4e1c"
    ],
    "wof:name":"Miaodong",
    "wof:placetype":"locality"
},
  "geometry": {"coordinates":[125.81632999999999,41.78715],"type":"Point"}
}