{
  "type": "Feature",
  "properties": {
    "gn:admin1_code":"15.0",
    "gn:asciiname":"Nacha",
    "gn:country_code":"CN",
    "gn:dem":1979,
    "gn:feature_class":"P",
    "gn:feature_code":"PPL",
    "gn:name":"Nacha",
    "gn:population":0,
    "gn:timezone":"Asia/Shanghai",
    "iso:country":"CN",
    "name:ceb_x_preferred":[
        "Nacha"
    ],
    "name:swe_x_preferred":[
        "Nacha"
    ],
    "name:und_x_variant":[
        "\u90a3\u5c94"
    ],
    "wof:name":"Nacha",
    "wof:placetype":"locality"
},
  "geometry": {"coordinates":[105.47381,35.55367000000001],"type":"Point"}
}