{
  "type": "Feature",
  "properties": {
    "gn:admin1_code":"06",
    "gn:asciiname":"Bayan",
    "gn:country_code":"CN",
    "gn:dem":2797,
    "gn:feature_class":"P",
    "gn:feature_code":"PPLA4",
    "gn:name":"Bayan",
    "gn:population":0,
    "gn:timezone":"Asia/Shanghai",
    "iso:country":"CN",
    "name:und_x_variant":[
        "Pa-yen",
        "Bayan",
        "Bayan Xiang"
    ],
    "name:zho_x_preferred":[
        "\u5df4\u71d5"
    ],
    "name:zho_x_variant":[
        "\u5df4\u71d5\u4e61"
    ],
    "wof:name":"Bayan",
    "wof:placetype":"locality"
},
  "geometry": {"coordinates":[101.13194,36.76611],"type":"Point"}
}