{
  "type": "Feature",
  "properties": {
    "gn:admin1_code":"06",
    "gn:asciiname":"Bayan",
    "gn:country_code":"CN",
    "gn:dem":2797,
    "gn:feature_class":"P",
    "gn:feature_code":"PPLA4",
    "gn:name":"Bayan",
    "gn:population":0,
    "gn:timezone":"Asia/Shanghai",
    "iso:country":"CN",
    "name:ara_x_preferred":[
        "\u0627\u0644\u0628\u064a\u0627\u0646"
    ],
    "name:aze_x_preferred":[
        "Bayan"
    ],
    "name:cat_x_preferred":[
        "Bayan"
    ],
    "name:ceb_x_preferred":[
        "Bayan"
    ],
    "name:deu_x_preferred":[
        "Bayan"
    ],
    "name:fra_x_preferred":[
        "Bayan"
    ],
    "name:glg_x_preferred":[
        "Baian"
    ],
    "name:ind_x_preferred":[
        "Bayan"
    ],
    "name:ita_x_preferred":[
        "Bayan"
    ],
    "name:jpn_x_preferred":[
        "\u30d0\u30e4\u30f3"
    ],
    "name:kat_x_preferred":[
        "\u10d1\u10d0\u10d8\u10d0\u10dc\u10d8"
    ],
    "name:kaz_x_preferred":[
        "\u0411\u0430\u044f\u043d"
    ],
    "name:mlg_x_preferred":[
        "Bayan"
    ],
    "name:nld_x_preferred":[
        "Bayan"
    ],
    "name:nor_x_preferred":[
        "Bayan"
    ],
    "name:rus_x_preferred":[
        "\u0411\u0430\u044f\u043d"
    ],
    "name:swe_x_preferred":[
        "Bayan"
    ],
    "name:tgl_x_preferred":[
        "Bayan"
    ],
    "name:tur_x_preferred":[
        "Bayan"
    ],
    "name:ukr_x_preferred":[
        "\u0411\u0430\u044f\u043d"
    ],
    "name:und_x_variant":[
        "Pa-yen",
        "Bayan",
        "Bayan Xiang"
    ],
    "name:zho_x_preferred":[
        "\u5df4\u71d5"
    ],
    "name:zho_x_variant":[
        "\u5df4\u71d5\u4e61"
    ],
    "wof:name":"Bayan",
    "wof:placetype":"locality"
},
  "geometry": {"coordinates":[101.13194,36.76611],"type":"Point"}
}