{
  "type": "Feature",
  "properties": {
    "gn:admin1_code":"02",
    "gn:asciiname":"Hai'ao",
    "gn:country_code":"CN",
    "gn:dem":6,
    "gn:feature_class":"P",
    "gn:feature_code":"PPL",
    "gn:name":"Hai\u2019ao",
    "gn:population":0,
    "gn:timezone":"Asia/Shanghai",
    "iso:country":"CN",
    "name:und_x_variant":[
        "Ta-han-ao",
        "Hai\u2019ao",
        "\u6d77\u5c99"
    ],
    "wof:name":"Hai'ao",
    "wof:placetype":"locality"
},
  "geometry": {"coordinates":[122.18222,30.19167],"type":"Point"}
}