{
  "type": "Feature",
  "properties": {
    "gn:admin1_code":"8.0",
    "gn:asciiname":"Xiyaotun",
    "gn:country_code":"CN",
    "gn:dem":260,
    "gn:feature_class":"P",
    "gn:feature_code":"PPL",
    "gn:name":"Xiyaotun",
    "gn:population":0,
    "gn:timezone":"Asia/Shanghai",
    "iso:country":"CN",
    "name:zho_x_preferred":[
        "\u897f\u7a91\u5c6f"
    ],
    "wof:name":"Xiyaotun",
    "wof:placetype":"locality"
},
  "geometry": {"coordinates":[128.26533999999998,46.93638],"type":"Point"}
}