{
  "type": "Feature",
  "properties": {
    "gn:admin1_code":"14.0",
    "gn:asciiname":"Pucun",
    "gn:country_code":"CN",
    "gn:dem":4357,
    "gn:feature_class":"P",
    "gn:feature_code":"PPL",
    "gn:name":"Pucun",
    "gn:population":0,
    "gn:timezone":"Asia/Urumqi",
    "iso:country":"CN",
    "name:zho_x_preferred":[
        "\u666e\u6751"
    ],
    "wof:name":"Pucun",
    "wof:placetype":"locality"
},
  "geometry": {"coordinates":[87.6502,28.9283],"type":"Point"}
}