{
  "type": "Feature",
  "properties": {
    "gn:admin1_code":"4.0",
    "gn:asciiname":"Gudai",
    "gn:country_code":"CN",
    "gn:dem":3,
    "gn:feature_class":"P",
    "gn:feature_code":"PPL",
    "gn:name":"Gudai",
    "gn:population":0,
    "gn:timezone":"Asia/Shanghai",
    "iso:country":"CN",
    "name:zho_x_preferred":[
        "\u987e\u5cb1"
    ],
    "wof:name":"Gudai",
    "wof:placetype":"locality"
},
  "geometry": {"coordinates":[120.69838,32.27144000000001],"type":"Point"}
}