{
  "type": "Feature",
  "properties": {
    "gn:admin1_code":"20.0",
    "gn:asciiname":"Bayin Naobao",
    "gn:country_code":"CN",
    "gn:dem":1365,
    "gn:feature_class":"P",
    "gn:feature_code":"PPL",
    "gn:name":"Bayin Naobao",
    "gn:population":0,
    "gn:timezone":"Asia/Shanghai",
    "iso:country":"CN",
    "name:und_x_variant":[
        "\u5df4\u97f3\u8111\u5305"
    ],
    "wof:name":"Bayin Naobao",
    "wof:placetype":"locality"
},
  "geometry": {"coordinates":[112.81038999999998,41.77684],"type":"Point"}
}