{
  "type": "Feature",
  "properties": {
    "gn:admin1_code":"2.0",
    "gn:asciiname":"Liangtingdi",
    "gn:country_code":"CN",
    "gn:dem":500,
    "gn:feature_class":"P",
    "gn:feature_code":"PPL",
    "gn:name":"Liangtingdi",
    "gn:population":0,
    "gn:timezone":"Asia/Shanghai",
    "iso:country":"CN",
    "name:zho_x_preferred":[
        "\u51c9\u4ead\u5e95"
    ],
    "wof:name":"Liangtingdi",
    "wof:placetype":"locality"
},
  "geometry": {"coordinates":[118.87702,29.26046],"type":"Point"}
}