{
  "type": "Feature",
  "properties": {
    "gn:admin1_code":"25.0",
    "gn:asciiname":"Wangshuangloucun",
    "gn:country_code":"CN",
    "gn:dem":52,
    "gn:feature_class":"P",
    "gn:feature_code":"PPL",
    "gn:name":"Wangshuangloucun",
    "gn:population":0,
    "gn:timezone":"Asia/Shanghai",
    "iso:country":"CN",
    "name:zho_x_preferred":[
        "\u738b\u53cc\u697c\u6751"
    ],
    "wof:name":"Wangshuangloucun",
    "wof:placetype":"locality"
},
  "geometry": {"coordinates":[115.71287,35.03589],"type":"Point"}
}