{
  "type": "Feature",
  "properties": {
    "gn:admin1_code":"26.0",
    "gn:asciiname":"Zhangziping",
    "gn:country_code":"CN",
    "gn:dem":1455,
    "gn:feature_class":"P",
    "gn:feature_code":"PPL",
    "gn:name":"Zhangziping",
    "gn:population":0,
    "gn:timezone":"Asia/Shanghai",
    "iso:country":"CN",
    "name:zho_x_preferred":[
        "\u5f20\u5b50\u576a"
    ],
    "wof:name":"Zhangziping",
    "wof:placetype":"locality"
},
  "geometry": {"coordinates":[108.97016000000001,33.59229000000001],"type":"Point"}
}