{
  "type": "Feature",
  "properties": {
    "gn:admin1_code":"24.0",
    "gn:asciiname":"Qingcaogou",
    "gn:country_code":"CN",
    "gn:dem":1236,
    "gn:feature_class":"P",
    "gn:feature_code":"PPL",
    "gn:name":"Qingcaogou",
    "gn:population":0,
    "gn:timezone":"Asia/Shanghai",
    "iso:country":"CN",
    "name:zho_x_preferred":[
        "\u9752\u8349\u6c9f"
    ],
    "wof:name":"Qingcaogou",
    "wof:placetype":"locality"
},
  "geometry": {"coordinates":[111.18844,38.84873],"type":"Point"}
}