{
  "type": "Feature",
  "properties": {
    "gn:admin1_code":"1.0",
    "gn:asciiname":"Shenzhaicun",
    "gn:country_code":"CN",
    "gn:dem":29,
    "gn:feature_class":"P",
    "gn:feature_code":"PPL",
    "gn:name":"Shenzhaicun",
    "gn:population":0,
    "gn:timezone":"Asia/Shanghai",
    "iso:country":"CN",
    "name:zho_x_preferred":[
        "\u7533\u5be8\u6751"
    ],
    "wof:name":"Shenzhaicun",
    "wof:placetype":"locality"
},
  "geometry": {"coordinates":[117.61656000000001,33.88112],"type":"Point"}
}