{
  "type": "Feature",
  "properties": {
    "gn:admin1_code":"26.0",
    "gn:asciiname":"Hejia Yuancun",
    "gn:country_code":"CN",
    "gn:dem":1189,
    "gn:feature_class":"P",
    "gn:feature_code":"PPL",
    "gn:name":"Hejia Yuancun",
    "gn:population":0,
    "gn:timezone":"Asia/Shanghai",
    "iso:country":"CN",
    "name:zho_x_preferred":[
        "\u8d3a\u5bb6\u5143\u6751"
    ],
    "wof:name":"Hejia Yuancun",
    "wof:placetype":"locality"
},
  "geometry": {"coordinates":[110.14400000000001,38.075],"type":"Point"}
}