{
  "type": "Feature",
  "properties": {
    "gn:admin1_code":"32.0",
    "gn:asciiname":"Laowu",
    "gn:country_code":"CN",
    "gn:dem":590,
    "gn:feature_class":"P",
    "gn:feature_code":"PPL",
    "gn:name":"Laowu",
    "gn:population":0,
    "gn:timezone":"Asia/Shanghai",
    "iso:country":"CN",
    "name:und_x_variant":[
        "\u8001\u5c4b"
    ],
    "wof:name":"Laowu",
    "wof:placetype":"locality"
},
  "geometry": {"coordinates":[106.29469,32.1694],"type":"Point"}
}