{
  "type": "Feature",
  "properties": {
    "gn:admin1_code":"29.0",
    "gn:asciiname":"Fenggou",
    "gn:country_code":"CN",
    "gn:dem":2316,
    "gn:feature_class":"P",
    "gn:feature_code":"PPL",
    "gn:name":"Fenggou",
    "gn:population":0,
    "gn:timezone":"Asia/Shanghai",
    "iso:country":"CN",
    "name:und_x_variant":[
        "\u5c01\u6c9f"
    ],
    "wof:name":"Fenggou",
    "wof:placetype":"locality"
},
  "geometry": {"coordinates":[102.38754,26.11344],"type":"Point"}
}