{
  "type": "Feature",
  "properties": {
    "gn:admin1_code":"16.0",
    "gn:asciiname":"Guozhe",
    "gn:country_code":"CN",
    "gn:dem":582,
    "gn:feature_class":"P",
    "gn:feature_code":"PPL",
    "gn:name":"Guozhe",
    "gn:population":0,
    "gn:timezone":"Asia/Shanghai",
    "iso:country":"CN",
    "name:zho_x_preferred":[
        "\u679c\u8fd9"
    ],
    "wof:name":"Guozhe",
    "wof:placetype":"locality"
},
  "geometry": {"coordinates":[106.94199999999999,24.2931],"type":"Point"}
}