{
  "type": "Feature",
  "properties": {
    "gn:admin1_code":"10",
    "gn:asciiname":"Pianqiaozi",
    "gn:country_code":"CN",
    "gn:dem":622,
    "gn:feature_class":"P",
    "gn:feature_code":"PPL",
    "gn:name":"Pianqiaozi",
    "gn:population":0,
    "gn:timezone":"Asia/Shanghai",
    "iso:country":"CN",
    "name:zho_x_preferred":[
        "\u504f\u6865\u5b50"
    ],
    "wof:name":"Pianqiaozi",
    "wof:placetype":"locality"
},
  "geometry": {"coordinates":[117.35621,41.32404],"type":"Point"}
}