{
  "type": "Feature",
  "properties": {
    "gn:admin1_code":"12.0",
    "gn:asciiname":"Dujiawan",
    "gn:country_code":"CN",
    "gn:dem":30,
    "gn:feature_class":"P",
    "gn:feature_code":"PPL",
    "gn:name":"Dujiawan",
    "gn:population":0,
    "gn:timezone":"Asia/Shanghai",
    "iso:country":"CN",
    "name:und_x_variant":[
        "\u675c\u5bb6\u5846"
    ],
    "name:zho_x_preferred":[
        "\u675c\u5bb6\u6e7e"
    ],
    "wof:name":"Dujiawan",
    "wof:placetype":"locality"
},
  "geometry": {"coordinates":[114.87611,30.49166],"type":"Point"}
}