{
  "type": "Feature",
  "properties": {
    "gn:admin1_code":"31.0",
    "gn:asciiname":"Tuiding",
    "gn:country_code":"CN",
    "gn:dem":138,
    "gn:feature_class":"P",
    "gn:feature_code":"PPL",
    "gn:name":"Tuiding",
    "gn:population":0,
    "gn:timezone":"Asia/Shanghai",
    "iso:country":"CN",
    "name:zho_x_preferred":[
        "\u63a8\u9876"
    ],
    "wof:name":"Tuiding",
    "wof:placetype":"locality"
},
  "geometry": {"coordinates":[109.29510000000001,19.46955],"type":"Point"}
}