{
  "type": "Feature",
  "properties": {
    "gn:admin1_code":"26.0",
    "gn:asciiname":"Shuimoba",
    "gn:country_code":"CN",
    "gn:dem":1210,
    "gn:feature_class":"P",
    "gn:feature_code":"PPL",
    "gn:name":"Shuimoba",
    "gn:population":0,
    "gn:timezone":"Asia/Shanghai",
    "iso:country":"CN",
    "name:und_x_variant":[
        "\u6c34\u78e8\u575d"
    ],
    "wof:name":"Shuimoba",
    "wof:placetype":"locality"
},
  "geometry": {"coordinates":[106.30577,33.24067],"type":"Point"}
}