{
  "type": "Feature",
  "properties": {
    "gn:admin1_code":"19.0",
    "gn:asciiname":"Huangtuling Gouli",
    "gn:country_code":"CN",
    "gn:dem":101,
    "gn:feature_class":"P",
    "gn:feature_code":"PPL",
    "gn:name":"Huangtuling Gouli",
    "gn:population":0,
    "gn:timezone":"Asia/Shanghai",
    "iso:country":"CN",
    "name:und_x_variant":[
        "\u9ec4\u571f\u5cad\u6c9f\u91cc"
    ],
    "wof:name":"Huangtuling Gouli",
    "wof:placetype":"locality"
},
  "geometry": {"coordinates":[122.59005999999999,40.49916],"type":"Point"}
}