{
  "type": "Feature",
  "properties": {
    "gn:admin1_code":"16.0",
    "gn:asciiname":"Longdian",
    "gn:country_code":"CN",
    "gn:dem":501,
    "gn:feature_class":"P",
    "gn:feature_code":"PPL",
    "gn:name":"Longdian",
    "gn:population":0,
    "gn:timezone":"Asia/Shanghai",
    "iso:country":"CN",
    "name:zho_x_preferred":[
        "\u9647\u70b9"
    ],
    "wof:name":"Longdian",
    "wof:placetype":"locality"
},
  "geometry": {"coordinates":[107.39400000000001,23.1714],"type":"Point"}
}