{
  "type": "Feature",
  "properties": {
    "gn:admin1_code":"29.0",
    "gn:asciiname":"Lishu",
    "gn:country_code":"CN",
    "gn:dem":1918,
    "gn:feature_class":"P",
    "gn:feature_code":"PPL",
    "gn:name":"Lishu",
    "gn:population":0,
    "gn:timezone":"Asia/Shanghai",
    "iso:country":"CN",
    "name:ceb_x_preferred":[
        "Lishu"
    ],
    "name:deu_x_preferred":[
        "Lishu"
    ],
    "name:fra_x_preferred":[
        "Lishu"
    ],
    "name:mlg_x_preferred":[
        "Lishu"
    ],
    "name:nor_x_preferred":[
        "Lishu"
    ],
    "name:pol_x_preferred":[
        "Lishu"
    ],
    "name:rus_x_preferred":[
        "\u041b\u0438\u0448\u0443"
    ],
    "name:swe_x_preferred":[
        "Lishu"
    ],
    "name:zho_x_preferred":[
        "\u6817\u6811"
    ],
    "wof:name":"Lishu",
    "wof:placetype":"locality"
},
  "geometry": {"coordinates":[103.913,24.5907],"type":"Point"}
}