{
  "type": "Feature",
  "properties": {
    "gn:admin1_code":"11.0",
    "gn:asciiname":"Niushiping",
    "gn:country_code":"CN",
    "gn:dem":1213,
    "gn:feature_class":"P",
    "gn:feature_code":"PPL",
    "gn:name":"Niushiping",
    "gn:population":0,
    "gn:timezone":"Asia/Shanghai",
    "iso:country":"CN",
    "name:zho_x_preferred":[
        "\u725b\u5c4e\u576a"
    ],
    "wof:name":"Niushiping",
    "wof:placetype":"locality"
},
  "geometry": {"coordinates":[113.89896,26.11987],"type":"Point"}
}