{
  "type": "Feature",
  "properties": {
    "gn:admin1_code":"26.0",
    "gn:asciiname":"Qianxiaogouzecun",
    "gn:country_code":"CN",
    "gn:dem":969,
    "gn:feature_class":"P",
    "gn:feature_code":"PPL",
    "gn:name":"Qianxiaogouzecun",
    "gn:population":0,
    "gn:timezone":"Asia/Shanghai",
    "iso:country":"CN",
    "name:zho_x_preferred":[
        "\u524d\u5c0f\u6c9f\u5219\u6751"
    ],
    "wof:name":"Qianxiaogouzecun",
    "wof:placetype":"locality"
},
  "geometry": {"coordinates":[110.02795999999999,37.38394],"type":"Point"}
}