{
  "type": "Feature",
  "properties": {
    "gn:admin1_code":"7",
    "gn:asciiname":"Xiqi",
    "gn:country_code":"CN",
    "gn:dem":20,
    "gn:feature_class":"P",
    "gn:feature_code":"PPL",
    "gn:name":"Xiqi",
    "gn:population":0,
    "gn:timezone":"Asia/Shanghai",
    "iso:country":"CN",
    "name:kor_x_preferred":[
        "\ud574\uc81c"
    ],
    "wof:name":"Xiqi",
    "wof:placetype":"locality"
},
  "geometry": {"coordinates":[117.34361,23.60083],"type":"Point"}
}