{
  "type": "Feature",
  "properties": {
    "gn:admin1_code":"29.0",
    "gn:asciiname":"Zhongpai",
    "gn:country_code":"CN",
    "gn:dem":2401,
    "gn:feature_class":"P",
    "gn:feature_code":"PPL",
    "gn:name":"Zhongpai",
    "gn:population":0,
    "gn:timezone":"Asia/Shanghai",
    "iso:country":"CN",
    "wof:name":"Zhongpai",
    "wof:placetype":"locality"
},
  "geometry": {"coordinates":[99.23333,26.88333],"type":"Point"}
}