{
  "type": "Feature",
  "properties": {
    "gn:admin1_code":"19.0",
    "gn:asciiname":"Houwangtun",
    "gn:country_code":"CN",
    "gn:dem":20,
    "gn:feature_class":"P",
    "gn:feature_code":"PPL",
    "gn:name":"Houwangtun",
    "gn:population":0,
    "gn:timezone":"Asia/Shanghai",
    "iso:country":"CN",
    "name:und_x_variant":[
        "\u540e\u738b\u5c6f"
    ],
    "name:zho_x_preferred":[
        "\u540e\u738b\u5c6f"
    ],
    "wof:name":"Houwangtun",
    "wof:placetype":"locality"
},
  "geometry": {"coordinates":[120.52603999999999,40.47659],"type":"Point"}
}