{
  "type": "Feature",
  "properties": {
    "gn:admin1_code":"8.0",
    "gn:asciiname":"Lifucun",
    "gn:country_code":"CN",
    "gn:dem":72,
    "gn:feature_class":"P",
    "gn:feature_code":"PPL",
    "gn:name":"Lifucun",
    "gn:population":0,
    "gn:timezone":"Asia/Shanghai",
    "iso:country":"CN",
    "name:zho_x_preferred":[
        "\u68a8\u5bcc\u6751"
    ],
    "wof:name":"Lifucun",
    "wof:placetype":"locality"
},
  "geometry": {"coordinates":[131.11006,46.99245],"type":"Point"}
}