{
  "type": "Feature",
  "properties": {
    "gn:admin1_code":"32.0",
    "gn:asciiname":"Wang'anhe",
    "gn:country_code":"CN",
    "gn:dem":417,
    "gn:feature_class":"P",
    "gn:feature_code":"PPL",
    "gn:name":"Wang\u2019anhe",
    "gn:population":0,
    "gn:timezone":"Asia/Shanghai",
    "iso:country":"CN",
    "name:zho_x_preferred":[
        "\u738b\u5b89\u6cb3"
    ],
    "name:zho_x_variant":[
        "Wang\u2019anhe"
    ],
    "wof:name":"Wang'anhe",
    "wof:placetype":"locality"
},
  "geometry": {"coordinates":[104.95358,30.05967],"type":"Point"}
}