{
  "type": "Feature",
  "properties": {
    "gn:admin1_code":"14.0",
    "gn:asciiname":"Danubu",
    "gn:country_code":"CN",
    "gn:dem":3141,
    "gn:feature_class":"P",
    "gn:feature_code":"PPL",
    "gn:name":"Danubu",
    "gn:population":0,
    "gn:timezone":"Asia/Urumqi",
    "iso:country":"CN",
    "name:zho_x_preferred":[
        "\u8fbe\u5974\u5e03"
    ],
    "wof:name":"Danubu",
    "wof:placetype":"locality"
},
  "geometry": {"coordinates":[97.40029,30.71634],"type":"Point"}
}