{
  "type": "Feature",
  "properties": {
    "gn:admin1_code":"14",
    "gn:asciiname":"Nadui",
    "gn:country_code":"CN",
    "gn:dem":4399,
    "gn:feature_class":"P",
    "gn:feature_code":"PPL",
    "gn:name":"Nadui",
    "gn:population":0,
    "gn:timezone":"Asia/Urumqi",
    "iso:country":"CN",
    "name:zho_x_preferred":[
        "\u90a3\u5806"
    ],
    "wof:name":"Nadui",
    "wof:placetype":"locality"
},
  "geometry": {"coordinates":[89.93040000000001,28.6865],"type":"Point"}
}