{
  "type": "Feature",
  "properties": {
    "gn:admin1_code":"03",
    "gn:asciiname":"Tangang",
    "gn:cc2":"CN",
    "gn:country_code":"CN",
    "gn:dem":22,
    "gn:feature_class":"P",
    "gn:feature_code":"PPL",
    "gn:name":"Tangang",
    "gn:population":0,
    "gn:timezone":"Asia/Shanghai",
    "iso:country":"CN",
    "name:und_x_variant":[
        "T\u2019an-kang",
        "Tangang"
    ],
    "wof:name":"Tangang",
    "wof:placetype":"locality"
},
  "geometry": {"coordinates":[115.88333,28.31667],"type":"Point"}
}