{
  "type": "Feature",
  "properties": {
    "gn:admin1_code":"29.0",
    "gn:asciiname":"Muhaitang",
    "gn:country_code":"CN",
    "gn:dem":1421,
    "gn:feature_class":"P",
    "gn:feature_code":"PPL",
    "gn:name":"Muhaitang",
    "gn:population":0,
    "gn:timezone":"Asia/Shanghai",
    "iso:country":"CN",
    "name:zho_x_preferred":[
        "\u6728\u6d77\u5858"
    ],
    "wof:name":"Muhaitang",
    "wof:placetype":"locality"
},
  "geometry": {"coordinates":[104.575,27.8259],"type":"Point"}
}