{
  "type": "Feature",
  "properties": {
    "gn:admin1_code":"18",
    "gn:asciiname":"Longquanwan",
    "gn:country_code":"CN",
    "gn:dem":865,
    "gn:feature_class":"P",
    "gn:feature_code":"PPL",
    "gn:name":"Longquanwan",
    "gn:population":0,
    "gn:timezone":"Asia/Shanghai",
    "iso:country":"CN",
    "name:zho_x_preferred":[
        "\u9f99\u6cc9\u6e7e"
    ],
    "wof:name":"Longquanwan",
    "wof:placetype":"locality"
},
  "geometry": {"coordinates":[107.80500000000001,28.0666],"type":"Point"}
}