{
  "type": "Feature",
  "properties": {
    "gn:admin1_code":"25",
    "gn:asciiname":"Beibaqing",
    "gn:country_code":"CN",
    "gn:dem":3,
    "gn:feature_class":"P",
    "gn:feature_code":"PPL",
    "gn:name":"Beibaqing",
    "gn:population":0,
    "gn:timezone":"Asia/Shanghai",
    "iso:country":"CN",
    "name:zho_x_preferred":[
        "\u5317\u516b\u503e"
    ],
    "wof:name":"Beibaqing",
    "wof:placetype":"locality"
},
  "geometry": {"coordinates":[118.366,38.0018],"type":"Point"}
}