{
  "type": "Feature",
  "properties": {
    "gn:admin1_code":"30",
    "gn:asciiname":"Guishan",
    "gn:country_code":"CN",
    "gn:dem":755,
    "gn:feature_class":"P",
    "gn:feature_code":"PPL",
    "gn:name":"Guishan",
    "gn:population":0,
    "gn:timezone":"Asia/Shanghai",
    "iso:country":"CN",
    "name:deu_x_preferred":[
        "Guishan"
    ],
    "name:kor_x_preferred":[
        "\uad6c\uc774\uc0b0"
    ],
    "name:zho_x_preferred":[
        "\u5f52\u5584"
    ],
    "wof:name":"Guishan",
    "wof:placetype":"locality"
},
  "geometry": {"coordinates":[115.88985,23.57663],"type":"Point"}
}