{
  "type": "Feature",
  "properties": {
    "gn:admin1_code":"3.0",
    "gn:asciiname":"Louzishang",
    "gn:country_code":"CN",
    "gn:dem":754,
    "gn:feature_class":"P",
    "gn:feature_code":"PPL",
    "gn:name":"Louzishang",
    "gn:population":0,
    "gn:timezone":"Asia/Shanghai",
    "iso:country":"CN",
    "name:und_x_variant":[
        "\u697c\u5b50\u4e0a"
    ],
    "wof:name":"Louzishang",
    "wof:placetype":"locality"
},
  "geometry": {"coordinates":[116.50087000000001,26.56489],"type":"Point"}
}