{
  "type": "Feature",
  "properties": {
    "gn:admin1_code":"20.0",
    "gn:asciiname":"Dahuhuadai",
    "gn:country_code":"CN",
    "gn:dem":1931,
    "gn:feature_class":"P",
    "gn:feature_code":"PPL",
    "gn:name":"Dahuhuadai",
    "gn:population":0,
    "gn:timezone":"Asia/Shanghai",
    "iso:country":"CN",
    "name:und_x_variant":[
        "\u5927\u864e\u82b1\u5cb1"
    ],
    "wof:name":"Dahuhuadai",
    "wof:placetype":"locality"
},
  "geometry": {"coordinates":[110.74975000000001,41.13128],"type":"Point"}
}