{
  "type": "Feature",
  "properties": {
    "gn:admin1_code":"24.0",
    "gn:asciiname":"Dingxing",
    "gn:country_code":"CN",
    "gn:dem":508,
    "gn:feature_class":"P",
    "gn:feature_code":"PPL",
    "gn:name":"Dingxing",
    "gn:population":0,
    "gn:timezone":"Asia/Shanghai",
    "iso:country":"CN",
    "name:und_x_variant":[
        "\u5b9a\u5174"
    ],
    "wof:name":"Dingxing",
    "wof:placetype":"locality"
},
  "geometry": {"coordinates":[111.27093000000001,35.79012],"type":"Point"}
}