{
  "type": "Feature",
  "properties": {
    "gn:admin1_code":"1.0",
    "gn:asciiname":"Wangloucun",
    "gn:country_code":"CN",
    "gn:dem":33,
    "gn:feature_class":"P",
    "gn:feature_code":"PPL",
    "gn:name":"Wangloucun",
    "gn:population":0,
    "gn:timezone":"Asia/Shanghai",
    "iso:country":"CN",
    "name:und_x_variant":[
        "Wang-chia-lou",
        "Wanglou",
        "Wangloucun"
    ],
    "name:zho_x_preferred":[
        "\u738b\u697c\u6751"
    ],
    "wof:name":"Wangloucun",
    "wof:placetype":"locality"
},
  "geometry": {"coordinates":[115.81471999999999,33.44583],"type":"Point"}
}