{
  "type": "Feature",
  "properties": {
    "gn:admin1_code":"31.0",
    "gn:asciiname":"Jinfeng",
    "gn:country_code":"CN",
    "gn:dem":12,
    "gn:feature_class":"P",
    "gn:feature_code":"PPL",
    "gn:name":"Jinfeng",
    "gn:population":0,
    "gn:timezone":"Asia/Shanghai",
    "iso:country":"CN",
    "name:ceb_x_preferred":[
        "Jinfeng"
    ],
    "name:zho_x_preferred":[
        "\u9526\u4e30"
    ],
    "wof:name":"Jinfeng",
    "wof:placetype":"locality"
},
  "geometry": {"coordinates":[110.45041999999999,19.96758],"type":"Point"}
}