{
  "type": "Feature",
  "properties": {
    "gn:admin1_code":"4.0",
    "gn:asciiname":"Zhaoxuzhuang",
    "gn:country_code":"CN",
    "gn:dem":5,
    "gn:feature_class":"P",
    "gn:feature_code":"PPL",
    "gn:name":"Zhaoxuzhuang",
    "gn:population":0,
    "gn:timezone":"Asia/Shanghai",
    "iso:country":"CN",
    "name:zho_x_preferred":[
        "Zhaoxuzhuang"
    ],
    "name:zho_x_variant":[
        "\u8d75\u5f90\u5e84"
    ],
    "wof:name":"Zhaoxuzhuang",
    "wof:placetype":"locality"
},
  "geometry": {"coordinates":[121.30606,32.36581],"type":"Point"}
}