{
  "type": "Feature",
  "properties": {
    "gn:admin1_code":"14.0",
    "gn:asciiname":"Yayiwa",
    "gn:country_code":"CN",
    "gn:dem":3966,
    "gn:feature_class":"P",
    "gn:feature_code":"PPL",
    "gn:name":"Yayiwa",
    "gn:population":0,
    "gn:timezone":"Asia/Urumqi",
    "iso:country":"CN",
    "name:zho_x_preferred":[
        "\u7259\u4e49\u74e6"
    ],
    "wof:name":"Yayiwa",
    "wof:placetype":"locality"
},
  "geometry": {"coordinates":[97.99449,30.47284],"type":"Point"}
}