{
  "type": "Feature",
  "properties": {
    "gn:admin1_code":"8.0",
    "gn:asciiname":"Panlongshan",
    "gn:country_code":"CN",
    "gn:dem":447,
    "gn:feature_class":"P",
    "gn:feature_code":"PPL",
    "gn:name":"Panlongshan",
    "gn:population":0,
    "gn:timezone":"Asia/Shanghai",
    "iso:country":"CN",
    "name:zho_x_preferred":[
        "\u76d8\u9f99\u5c71"
    ],
    "wof:name":"Panlongshan",
    "wof:placetype":"locality"
},
  "geometry": {"coordinates":[125.69129,50.14895],"type":"Point"}
}