{
  "type": "Feature",
  "properties": {
    "gn:admin1_code":"4.0",
    "gn:asciiname":"Daxiang Jiedao",
    "gn:country_code":"CN",
    "gn:dem":31,
    "gn:feature_class":"P",
    "gn:feature_code":"PPL",
    "gn:name":"Daxiang Jiedao",
    "gn:population":0,
    "gn:timezone":"Asia/Shanghai",
    "iso:country":"CN",
    "name:zho_x_preferred":[
        "\u5927\u5df7\u8857\u9053"
    ],
    "wof:name":"Daxiang Jiedao",
    "wof:placetype":"locality"
},
  "geometry": {"coordinates":[119.24829,32.57391],"type":"Point"}
}