{
  "type": "Feature",
  "properties": {
    "gn:admin1_code":"10",
    "gn:asciiname":"Sigoutai",
    "gn:country_code":"CN",
    "gn:dem":810,
    "gn:feature_class":"P",
    "gn:feature_code":"PPL",
    "gn:name":"Sigoutai",
    "gn:population":0,
    "gn:timezone":"Asia/Shanghai",
    "iso:country":"CN",
    "name:zho_x_preferred":[
        "\u56db\u6c9f\u53f0"
    ],
    "wof:name":"Sigoutai",
    "wof:placetype":"locality"
},
  "geometry": {"coordinates":[117.89176999999999,41.41629],"type":"Point"}
}