{
  "type": "Feature",
  "properties": {
    "gn:admin1_code":"26.0",
    "gn:asciiname":"Youfangjie",
    "gn:cc2":"CN",
    "gn:country_code":"CN",
    "gn:dem":1148,
    "gn:feature_class":"P",
    "gn:feature_code":"PPL",
    "gn:name":"Youfangjie",
    "gn:population":0,
    "gn:timezone":"Asia/Shanghai",
    "iso:country":"CN",
    "name:und_x_variant":[
        "Yu-fang-chieh",
        "Youfangjie"
    ],
    "wof:name":"Youfangjie",
    "wof:placetype":"locality"
},
  "geometry": {"coordinates":[109.98333,33.65],"type":"Point"}
}