{
  "type": "Feature",
  "properties": {
    "gn:admin1_code":"26.0",
    "gn:asciiname":"Shijingzi",
    "gn:country_code":"CN",
    "gn:dem":1324,
    "gn:feature_class":"P",
    "gn:feature_code":"PPL",
    "gn:name":"Shijingzi",
    "gn:population":0,
    "gn:timezone":"Asia/Shanghai",
    "iso:country":"CN",
    "name:zho_x_preferred":[
        "\u77f3\u4e95\u5b50"
    ],
    "wof:name":"Shijingzi",
    "wof:placetype":"locality"
},
  "geometry": {"coordinates":[107.49688,37.70891],"type":"Point"}
}