{
  "type": "Feature",
  "properties": {
    "gn:admin1_code":"19.0",
    "gn:asciiname":"Gunianggou",
    "gn:country_code":"CN",
    "gn:dem":44,
    "gn:feature_class":"P",
    "gn:feature_code":"PPL",
    "gn:name":"Gunianggou",
    "gn:population":0,
    "gn:timezone":"Asia/Shanghai",
    "iso:country":"CN",
    "name:zho_x_preferred":[
        "\u59d1\u5a18\u6c9f"
    ],
    "wof:name":"Gunianggou",
    "wof:placetype":"locality"
},
  "geometry": {"coordinates":[124.60657999999999,40.32181],"type":"Point"}
}