{
  "type": "Feature",
  "properties": {
    "gn:admin1_code":"14.0",
    "gn:asciiname":"Guobuquguo",
    "gn:country_code":"CN",
    "gn:dem":4900,
    "gn:feature_class":"P",
    "gn:feature_code":"PPL",
    "gn:name":"Guobuquguo",
    "gn:population":0,
    "gn:timezone":"Asia/Urumqi",
    "iso:country":"CN",
    "name:zho_x_preferred":[
        "\u679c\u5e03\u66f2\u679c"
    ],
    "wof:name":"Guobuquguo",
    "wof:placetype":"locality"
},
  "geometry": {"coordinates":[87.3047,30.6775],"type":"Point"}
}