{
  "type": "Feature",
  "properties": {
    "gn:admin1_code":"21.0",
    "gn:asciiname":"Miao'ercha",
    "gn:country_code":"CN",
    "gn:dem":2074,
    "gn:feature_class":"P",
    "gn:feature_code":"PPL",
    "gn:name":"Miao\u2019ercha",
    "gn:population":0,
    "gn:timezone":"Asia/Shanghai",
    "iso:country":"CN",
    "name:und_x_variant":[
        "Miao\u2019ercha"
    ],
    "name:zho_x_preferred":[
        "\u5e99\u513f\u5c94"
    ],
    "wof:name":"Miao'ercha",
    "wof:placetype":"locality"
},
  "geometry": {"coordinates":[105.58799999999999,36.0214],"type":"Point"}
}