{
  "type": "Feature",
  "properties": {
    "gn:admin1_code":"13",
    "gn:asciiname":"Xia'ercaikai",
    "gn:country_code":"CN",
    "gn:dem":1892,
    "gn:feature_class":"P",
    "gn:feature_code":"PPL",
    "gn:name":"Xia\u2019ercaikai",
    "gn:population":0,
    "gn:timezone":"Asia/Urumqi",
    "iso:country":"CN",
    "name:und_x_variant":[
        "Xia\u2019ercaikai",
        "\u590f\u5c14\u624d\u5f00"
    ],
    "wof:name":"Xia'ercaikai",
    "wof:placetype":"locality"
},
  "geometry": {"coordinates":[86.34477,42.81178],"type":"Point"}
}