{
  "type": "Feature",
  "properties": {
    "gn:admin1_code":"14.0",
    "gn:asciiname":"Ba'antongcun",
    "gn:country_code":"CN",
    "gn:dem":1716,
    "gn:feature_class":"P",
    "gn:feature_code":"PPL",
    "gn:name":"Ba\u2019antongcun",
    "gn:population":0,
    "gn:timezone":"Asia/Urumqi",
    "iso:country":"CN",
    "name:und_x_variant":[
        "Ba\u2019antongcun"
    ],
    "name:zho_x_preferred":[
        "\u5df4\u5b89\u901a\u6751"
    ],
    "wof:name":"Ba'antongcun",
    "wof:placetype":"locality"
},
  "geometry": {"coordinates":[96.99845000000001,28.51771],"type":"Point"}
}