{
  "type": "Feature",
  "properties": {
    "gn:admin1_code":"12.0",
    "gn:asciiname":"Dashuikeng",
    "gn:country_code":"CN",
    "gn:dem":1434,
    "gn:feature_class":"P",
    "gn:feature_code":"PPL",
    "gn:name":"Dashuikeng",
    "gn:population":0,
    "gn:timezone":"Asia/Shanghai",
    "iso:country":"CN",
    "name:zho_x_preferred":[
        "\u5927\u6c34\u5751"
    ],
    "wof:name":"Dashuikeng",
    "wof:placetype":"locality"
},
  "geometry": {"coordinates":[111.40093,31.65693],"type":"Point"}
}