{
  "type": "Feature",
  "properties": {
    "gn:admin1_code":"29.0",
    "gn:asciiname":"Shangsimeng",
    "gn:country_code":"CN",
    "gn:dem":2523,
    "gn:feature_class":"P",
    "gn:feature_code":"PPL",
    "gn:name":"Shangsimeng",
    "gn:population":0,
    "gn:timezone":"Asia/Shanghai",
    "iso:country":"CN",
    "name:zho_x_preferred":[
        "\u4e0a\u53f8\u5b5f"
    ],
    "wof:name":"Shangsimeng",
    "wof:placetype":"locality"
},
  "geometry": {"coordinates":[99.5577,25.851],"type":"Point"}
}