{
  "type": "Feature",
  "properties": {
    "gn:admin1_code":"4.0",
    "gn:asciiname":"Wugang",
    "gn:country_code":"CN",
    "gn:dem":4,
    "gn:feature_class":"P",
    "gn:feature_code":"PPL",
    "gn:name":"Wugang",
    "gn:population":0,
    "gn:timezone":"Asia/Shanghai",
    "iso:country":"CN",
    "name:ceb_x_preferred":[
        "Wugang"
    ],
    "name:deu_x_preferred":[
        "Wugang"
    ],
    "name:fra_x_preferred":[
        "Wugang"
    ],
    "name:nor_x_preferred":[
        "Wugang"
    ],
    "name:rus_x_preferred":[
        "\u0423\u0433\u0430\u043d"
    ],
    "name:swe_x_preferred":[
        "Wugang"
    ],
    "name:zho_x_preferred":[
        "\u4e4c\u6e2f"
    ],
    "wof:name":"Wugang",
    "wof:placetype":"locality"
},
  "geometry": {"coordinates":[120.196,33.1937],"type":"Point"}
}