{
  "type": "Feature",
  "properties": {
    "gn:admin1_code":"16",
    "gn:asciiname":"Luobubei",
    "gn:country_code":"CN",
    "gn:dem":167,
    "gn:feature_class":"P",
    "gn:feature_code":"PPL",
    "gn:name":"Luobubei",
    "gn:population":0,
    "gn:timezone":"Asia/Shanghai",
    "iso:country":"CN",
    "name:zho_x_preferred":[
        "\u841d\u535c\u9642"
    ],
    "wof:name":"Luobubei",
    "wof:placetype":"locality"
},
  "geometry": {"coordinates":[110.06100000000001,25.0073],"type":"Point"}
}