{
  "type": "Feature",
  "properties": {
    "gn:admin1_code":"30",
    "gn:asciiname":"Shilingxicun",
    "gn:country_code":"CN",
    "gn:dem":87,
    "gn:feature_class":"P",
    "gn:feature_code":"PPL",
    "gn:name":"Shilingxicun",
    "gn:population":0,
    "gn:timezone":"Asia/Urumqi",
    "iso:country":"CN",
    "name:zho_x_preferred":[
        "\u77f3\u7075\u6eaa\u6751"
    ],
    "wof:name":"Shilingxicun",
    "wof:placetype":"locality"
},
  "geometry": {"coordinates":[110.32358000000001,20.40667],"type":"Point"}
}