{
  "type": "Feature",
  "properties": {
    "gn:admin1_code":"15.0",
    "gn:asciiname":"Qi'erguoda",
    "gn:country_code":"CN",
    "gn:dem":2762,
    "gn:feature_class":"P",
    "gn:feature_code":"PPL",
    "gn:name":"Qi\u2019erguoda",
    "gn:population":0,
    "gn:timezone":"Asia/Shanghai",
    "iso:country":"CN",
    "name:und_x_variant":[
        "Qi\u2019erguoda",
        "\u5176\u5c14\u679c\u8fbe"
    ],
    "wof:name":"Qi'erguoda",
    "wof:placetype":"locality"
},
  "geometry": {"coordinates":[103.80928,33.99705],"type":"Point"}
}