{
  "type": "Feature",
  "properties": {
    "gn:admin1_code":"20.0",
    "gn:asciiname":"Houlong",
    "gn:country_code":"CN",
    "gn:dem":226,
    "gn:feature_class":"P",
    "gn:feature_code":"PPL",
    "gn:name":"Houlong",
    "gn:population":0,
    "gn:timezone":"Asia/Shanghai",
    "iso:country":"CN",
    "name:fra_x_preferred":[
        "Houlong"
    ],
    "name:hak_x_preferred":[
        "Heu-li\u00f9ng-ch\u1e73\u0301n"
    ],
    "name:ita_x_preferred":[
        "Houlong"
    ],
    "name:jpn_x_preferred":[
        "\u5f8c\u9f8d\u93ae"
    ],
    "name:kor_x_preferred":[
        "\ud5c8\uc6b0\ub8fd\uc9c4"
    ],
    "name:vie_x_preferred":[
        "H\u1eadu Long"
    ],
    "name:zho_x_preferred":[
        "\u540e\u9f99"
    ],
    "name:zho_x_variant":[
        "\u5f8c\u9f8d\u93ae"
    ],
    "wof:name":"Houlong",
    "wof:placetype":"locality"
},
  "geometry": {"coordinates":[123.61593000000001,48.12107],"type":"Point"}
}