{
  "type": "Feature",
  "properties": {
    "gn:admin1_code":"18",
    "gn:asciiname":"Xiaomabuzhai",
    "gn:country_code":"CN",
    "gn:dem":1203,
    "gn:feature_class":"P",
    "gn:feature_code":"PPL",
    "gn:name":"Xiaomabuzhai",
    "gn:population":0,
    "gn:timezone":"Asia/Shanghai",
    "iso:country":"CN",
    "name:zho_x_preferred":[
        "\u5c0f\u9ebb\u5e03\u5be8"
    ],
    "wof:name":"Xiaomabuzhai",
    "wof:placetype":"locality"
},
  "geometry": {"coordinates":[106.16200000000001,27.1465],"type":"Point"}
}