{
  "type": "Feature",
  "properties": {
    "gn:admin1_code":"5.0",
    "gn:asciiname":"Ertaizi",
    "gn:country_code":"CN",
    "gn:dem":183,
    "gn:feature_class":"P",
    "gn:feature_code":"PPL",
    "gn:name":"Ertaizi",
    "gn:population":0,
    "gn:timezone":"Asia/Shanghai",
    "iso:country":"CN",
    "name:zho_x_preferred":[
        "\u4e8c\u53f0\u5b50"
    ],
    "wof:name":"Ertaizi",
    "wof:placetype":"locality"
},
  "geometry": {"coordinates":[126.40823,44.00139],"type":"Point"}
}