{
  "type": "Feature",
  "properties": {
    "gn:admin1_code":"21.0",
    "gn:asciiname":"Luqu",
    "gn:country_code":"CN",
    "gn:dem":1095,
    "gn:feature_class":"P",
    "gn:feature_code":"PPL",
    "gn:name":"Luqu",
    "gn:population":0,
    "gn:timezone":"Asia/Shanghai",
    "iso:country":"CN",
    "name:zho_x_preferred":[
        "\u9646\u6e20"
    ],
    "wof:name":"Luqu",
    "wof:placetype":"locality"
},
  "geometry": {"coordinates":[106.72499999999999,39.0334],"type":"Point"}
}