{
  "type": "Feature",
  "properties": {
    "gn:admin1_code":"4.0",
    "gn:asciiname":"Tian'ecun",
    "gn:country_code":"CN",
    "gn:dem":4,
    "gn:feature_class":"P",
    "gn:feature_code":"PPL",
    "gn:name":"Tian\u2019ecun",
    "gn:population":0,
    "gn:timezone":"Asia/Shanghai",
    "iso:country":"CN",
    "name:und_x_variant":[
        "Tian\u2019ecun"
    ],
    "name:zho_x_preferred":[
        "\u5929\u9e45\u6751"
    ],
    "wof:name":"Tian'ecun",
    "wof:placetype":"locality"
},
  "geometry": {"coordinates":[120.53052,32.8075],"type":"Point"}
}