{
  "type": "Feature",
  "properties": {
    "gn:admin1_code":"32.0",
    "gn:asciiname":"Wengsongping",
    "gn:country_code":"CN",
    "gn:dem":967,
    "gn:feature_class":"P",
    "gn:feature_code":"PPL",
    "gn:name":"Wengsongping",
    "gn:population":0,
    "gn:timezone":"Asia/Shanghai",
    "iso:country":"CN",
    "name:zho_x_preferred":[
        "\u7fc1\u677e\u576a"
    ],
    "wof:name":"Wengsongping",
    "wof:placetype":"locality"
},
  "geometry": {"coordinates":[108.08852,31.70154],"type":"Point"}
}