{
  "type": "Feature",
  "properties": {
    "gn:admin1_code":"9.0",
    "gn:asciiname":"Yangji",
    "gn:cc2":"CN",
    "gn:country_code":"CN",
    "gn:dem":48,
    "gn:feature_class":"P",
    "gn:feature_code":"PPL",
    "gn:name":"Yangji",
    "gn:population":0,
    "gn:timezone":"Asia/Shanghai",
    "iso:country":"CN",
    "name:und_x_variant":[
        "Yang-chi",
        "Yangji"
    ],
    "wof:name":"Yangji",
    "wof:placetype":"locality"
},
  "geometry": {"coordinates":[115.49111000000001,35.74055999999999],"type":"Point"}
}