{
  "type": "Feature",
  "properties": {
    "gn:admin1_code":"12.0",
    "gn:asciiname":"Leibajia",
    "gn:country_code":"CN",
    "gn:dem":37,
    "gn:feature_class":"P",
    "gn:feature_code":"PPL",
    "gn:name":"Leibajia",
    "gn:population":0,
    "gn:timezone":"Asia/Shanghai",
    "iso:country":"CN",
    "name:zho_x_preferred":[
        "\u96f7\u516b\u5bb6"
    ],
    "wof:name":"Leibajia",
    "wof:placetype":"locality"
},
  "geometry": {"coordinates":[113.04828999999999,30.75919],"type":"Point"}
}