{
  "type": "Feature",
  "properties": {
    "gn:admin1_code":"18",
    "gn:asciiname":"Chujialaobao",
    "gn:country_code":"CN",
    "gn:dem":1763,
    "gn:feature_class":"P",
    "gn:feature_code":"PPL",
    "gn:name":"Chujialaobao",
    "gn:population":0,
    "gn:timezone":"Asia/Shanghai",
    "iso:country":"CN",
    "name:zho_x_preferred":[
        "\u50a8\u5bb6\u8001\u5305"
    ],
    "wof:name":"Chujialaobao",
    "wof:placetype":"locality"
},
  "geometry": {"coordinates":[104.65300000000001,25.8191],"type":"Point"}
}