{
  "type": "Feature",
  "properties": {
    "gn:admin1_code":"24.0",
    "gn:asciiname":"Xingwangyuan",
    "gn:country_code":"CN",
    "gn:dem":1070,
    "gn:feature_class":"P",
    "gn:feature_code":"PPL",
    "gn:name":"Xingwangyuan",
    "gn:population":0,
    "gn:timezone":"Asia/Shanghai",
    "iso:country":"CN",
    "name:zho_x_preferred":[
        "\u5174\u65fa\u539f"
    ],
    "wof:name":"Xingwangyuan",
    "wof:placetype":"locality"
},
  "geometry": {"coordinates":[111.56108999999999,36.90713],"type":"Point"}
}