{
  "type": "Feature",
  "properties": {
    "gn:admin1_code":"24.0",
    "gn:asciiname":"Quanzizui",
    "gn:country_code":"CN",
    "gn:dem":1388,
    "gn:feature_class":"P",
    "gn:feature_code":"PPL",
    "gn:name":"Quanzizui",
    "gn:population":0,
    "gn:timezone":"Asia/Shanghai",
    "iso:country":"CN",
    "name:zho_x_preferred":[
        "\u6cc9\u5b50\u5480"
    ],
    "wof:name":"Quanzizui",
    "wof:placetype":"locality"
},
  "geometry": {"coordinates":[112.26769,39.22807],"type":"Point"}
}