{
  "type": "Feature",
  "properties": {
    "gn:admin1_code":"33.0",
    "gn:asciiname":"Lengfengcao",
    "gn:country_code":"CN",
    "gn:dem":1767,
    "gn:feature_class":"P",
    "gn:feature_code":"PPL",
    "gn:name":"Lengfengcao",
    "gn:population":0,
    "gn:timezone":"Asia/Shanghai",
    "iso:country":"CN",
    "name:zho_x_preferred":[
        "\u51b7\u98ce\u69fd"
    ],
    "wof:name":"Lengfengcao",
    "wof:placetype":"locality"
},
  "geometry": {"coordinates":[109.07884,31.53721],"type":"Point"}
}