{
  "type": "Feature",
  "properties": {
    "gn:admin1_code":"18.0",
    "gn:asciiname":"Dangge",
    "gn:country_code":"CN",
    "gn:dem":698,
    "gn:feature_class":"P",
    "gn:feature_code":"PPL",
    "gn:name":"Dangge",
    "gn:population":0,
    "gn:timezone":"Asia/Shanghai",
    "iso:country":"CN",
    "name:zho_x_preferred":[
        "\u515a\u6208"
    ],
    "wof:name":"Dangge",
    "wof:placetype":"locality"
},
  "geometry": {"coordinates":[108.245,26.1376],"type":"Point"}
}