{
  "type": "Feature",
  "properties": {
    "gn:admin1_code":"31.0",
    "gn:asciiname":"Shengshan",
    "gn:country_code":"CN",
    "gn:dem":133,
    "gn:feature_class":"P",
    "gn:feature_code":"PPL",
    "gn:name":"Shengshan",
    "gn:population":0,
    "gn:timezone":"Asia/Shanghai",
    "iso:country":"CN",
    "name:zho_x_preferred":[
        "\u5723\u5c71"
    ],
    "wof:name":"Shengshan",
    "wof:placetype":"locality"
},
  "geometry": {"coordinates":[109.40741,19.48209],"type":"Point"}
}