{
  "type": "Feature",
  "properties": {
    "gn:admin1_code":"29.0",
    "gn:asciiname":"Liuhe",
    "gn:country_code":"CN",
    "gn:dem":1954,
    "gn:feature_class":"P",
    "gn:feature_code":"PPL",
    "gn:name":"Liuhe",
    "gn:population":0,
    "gn:timezone":"Asia/Shanghai",
    "iso:country":"CN",
    "name:ara_x_preferred":[
        "\u064a\u0648\u062e\u064a\u0647"
    ],
    "name:ben_x_preferred":[
        "\u09b2\u09bf\u0989\u09b9\u09c7"
    ],
    "name:ceb_x_preferred":[
        "Liuhe"
    ],
    "name:deu_x_preferred":[
        "Liuhe"
    ],
    "name:ell_x_preferred":[
        "\u039b\u03b9\u03bf\u03cd\u03c7\u03b5"
    ],
    "name:fas_x_preferred":[
        "\u0644\u06cc\u0648\u0647\u0647"
    ],
    "name:fra_x_preferred":[
        "Liuhe"
    ],
    "name:heb_x_preferred":[
        "\u05dc\u05d9\u05d0\u05d5\u05d7\u05d4"
    ],
    "name:hin_x_preferred":[
        "\u0932\u094d\u092f\u0942\u0939\u0947"
    ],
    "name:hun_x_preferred":[
        "Liuhe"
    ],
    "name:ind_x_preferred":[
        "Liuhe"
    ],
    "name:ita_x_preferred":[
        "Liuhe"
    ],
    "name:kor_x_preferred":[
        "\ub958\ud5c8"
    ],
    "name:nld_x_preferred":[
        "Liuhe"
    ],
    "name:pol_x_preferred":[
        "Liuhe"
    ],
    "name:por_x_preferred":[
        "Liuhe"
    ],
    "name:rus_x_preferred":[
        "\u041b\u044e\u0445\u044d"
    ],
    "name:spa_x_preferred":[
        "Liuhe"
    ],
    "name:swe_x_preferred":[
        "Liuhe"
    ],
    "name:tur_x_preferred":[
        "Liuhe"
    ],
    "name:ukr_x_preferred":[
        "\u041b\u044e\u0445\u0435"
    ],
    "name:und_x_variant":[
        "\u516d\u5408"
    ],
    "name:urd_x_preferred":[
        "\u0644\u06cc\u0648\u06c1\u06cc"
    ],
    "name:vie_x_preferred":[
        "Li\u1ec5u H\u00e0"
    ],
    "wof:name":"Liuhe",
    "wof:placetype":"locality"
},
  "geometry": {"coordinates":[103.4434,26.58309],"type":"Point"}
}