{
  "type": "Feature",
  "properties": {
    "gn:admin1_code":"16.0",
    "gn:asciiname":"Zhangmuping",
    "gn:country_code":"CN",
    "gn:dem":195,
    "gn:feature_class":"P",
    "gn:feature_code":"PPL",
    "gn:name":"Zhangmuping",
    "gn:population":0,
    "gn:timezone":"Asia/Shanghai",
    "iso:country":"CN",
    "name:zho_x_preferred":[
        "\u6a1f\u6728\u576a"
    ],
    "wof:name":"Zhangmuping",
    "wof:placetype":"locality"
},
  "geometry": {"coordinates":[108.58799999999999,23.1837],"type":"Point"}
}