{
  "type": "Feature",
  "properties": {
    "gn:admin1_code":"14.0",
    "gn:asciiname":"Qangdoi",
    "gn:country_code":"CN",
    "gn:dem":4121,
    "gn:feature_class":"P",
    "gn:feature_code":"PPLF",
    "gn:name":"Qangdoi",
    "gn:population":0,
    "gn:timezone":"Asia/Urumqi",
    "iso:country":"CN",
    "name:bod_x_preferred":[
        "Qangdoi"
    ],
    "name:msa_x_preferred":[
        "Qangdoi"
    ],
    "name:zho_x_preferred":[
        "Qiangdui"
    ],
    "name:zho_x_variant":[
        "\u5f3a\u5806",
        "Xiaqi",
        "\u590f\u5951"
    ],
    "wof:name":"Qangdoi",
    "wof:placetype":"locality"
},
  "geometry": {"coordinates":[89.303,29.003],"type":"Point"}
}