{
  "type": "Feature",
  "properties": {
    "gn:admin1_code":"21.0",
    "gn:asciiname":"Liguoyuan",
    "gn:country_code":"CN",
    "gn:dem":1463,
    "gn:feature_class":"P",
    "gn:feature_code":"PPL",
    "gn:name":"Liguoyuan",
    "gn:population":0,
    "gn:timezone":"Asia/Shanghai",
    "iso:country":"CN",
    "name:und_x_variant":[
        "\u674e\u679c\u56ed"
    ],
    "name:zho_x_preferred":[
        "\u674e\u679c\u56ed"
    ],
    "wof:name":"Liguoyuan",
    "wof:placetype":"locality"
},
  "geometry": {"coordinates":[106.00873,36.77335],"type":"Point"}
}