{
  "type": "Feature",
  "properties": {
    "gn:admin1_code":"2.0",
    "gn:asciiname":"Laitianwu",
    "gn:country_code":"CN",
    "gn:dem":508,
    "gn:feature_class":"P",
    "gn:feature_code":"PPL",
    "gn:name":"Laitianwu",
    "gn:population":0,
    "gn:timezone":"Asia/Shanghai",
    "iso:country":"CN",
    "name:und_x_variant":[
        "\u8d56\u7530\u575e",
        "Laitianwu"
    ],
    "wof:name":"Laitianwu",
    "wof:placetype":"locality"
},
  "geometry": {"coordinates":[119.47014,29.78251],"type":"Point"}
}