{
  "type": "Feature",
  "properties": {
    "gn:admin1_code":"4.0",
    "gn:asciiname":"Xinjicun",
    "gn:country_code":"CN",
    "gn:dem":44,
    "gn:feature_class":"P",
    "gn:feature_code":"PPL",
    "gn:name":"Xinjicun",
    "gn:population":0,
    "gn:timezone":"Asia/Shanghai",
    "iso:country":"CN",
    "name:und_x_variant":[
        "Hsin-chi",
        "Xinji",
        "Xinjicun"
    ],
    "name:zho_x_preferred":[
        "\u65b0\u96c6"
    ],
    "name:zho_x_variant":[
        "\u65b0\u96c6\u6751"
    ],
    "wof:name":"Xinjicun",
    "wof:placetype":"locality"
},
  "geometry": {"coordinates":[116.74072,34.5647],"type":"Point"}
}