{
  "type": "Feature",
  "properties": {
    "gn:admin1_code":"5.0",
    "gn:asciiname":"Chuantiaozi",
    "gn:country_code":"CN",
    "gn:dem":197,
    "gn:feature_class":"P",
    "gn:feature_code":"PPL",
    "gn:name":"Chuantiaozi",
    "gn:population":0,
    "gn:timezone":"Asia/Shanghai",
    "iso:country":"CN",
    "name:zho_x_preferred":[
        "\u5ddd\u6761\u5b50"
    ],
    "wof:name":"Chuantiaozi",
    "wof:placetype":"locality"
},
  "geometry": {"coordinates":[126.22271000000001,44.01559],"type":"Point"}
}