{
  "type": "Feature",
  "properties": {
    "gn:admin1_code":"7.0",
    "gn:asciiname":"Nanhua",
    "gn:country_code":"CN",
    "gn:dem":662,
    "gn:feature_class":"P",
    "gn:feature_code":"PPL",
    "gn:name":"Nanhua",
    "gn:population":0,
    "gn:timezone":"Asia/Shanghai",
    "iso:country":"CN",
    "name:zho_x_preferred":[
        "\u5357\u534e"
    ],
    "wof:name":"Nanhua",
    "wof:placetype":"locality"
},
  "geometry": {"coordinates":[117.93377,26.15401],"type":"Point"}
}