{
  "type": "Feature",
  "properties": {
    "gn:admin1_code":"16.0",
    "gn:asciiname":"Weise",
    "gn:country_code":"CN",
    "gn:dem":594,
    "gn:feature_class":"P",
    "gn:feature_code":"PPL",
    "gn:name":"Weise",
    "gn:population":0,
    "gn:timezone":"Asia/Shanghai",
    "iso:country":"CN",
    "name:zho_x_preferred":[
        "\u4f1f\u8272"
    ],
    "wof:name":"Weise",
    "wof:placetype":"locality"
},
  "geometry": {"coordinates":[108.41500000000001,25.419],"type":"Point"}
}