{
  "type": "Feature",
  "properties": {
    "gn:admin1_code":"12",
    "gn:asciiname":"Baiyang",
    "gn:country_code":"CN",
    "gn:dem":49,
    "gn:feature_class":"P",
    "gn:feature_code":"PPLA4",
    "gn:name":"Baiyang",
    "gn:population":0,
    "gn:timezone":"Asia/Shanghai",
    "iso:country":"CN",
    "name:ceb_x_preferred":[
        "Baiyang"
    ],
    "name:deu_x_preferred":[
        "Baiyang"
    ],
    "name:swe_x_preferred":[
        "Baiyang"
    ],
    "name:und_x_variant":[
        "Pai-yang",
        "Baiyang",
        "\u767d\u6d0b",
        "Baiyang Zhen",
        "\u767d\u6d0b\u9547",
        "Pih-Yang"
    ],
    "wof:name":"Baiyang",
    "wof:placetype":"locality"
},
  "geometry": {"coordinates":[111.50874,30.42277],"type":"Point"}
}