{
  "type": "Feature",
  "properties": {
    "gn:admin1_code":"25",
    "gn:asciiname":"Taiping",
    "gn:cc2":"CN",
    "gn:country_code":"CN",
    "gn:dem":7,
    "gn:feature_class":"P",
    "gn:feature_code":"PPL",
    "gn:name":"Taiping",
    "gn:population":0,
    "gn:timezone":"Asia/Shanghai",
    "iso:country":"CN",
    "name:ceb_x_preferred":[
        "Taiping"
    ],
    "name:deu_x_preferred":[
        "Taiping"
    ],
    "name:fra_x_preferred":[
        "Taiping"
    ],
    "name:ind_x_preferred":[
        "Taiping"
    ],
    "name:msa_x_preferred":[
        "Taiping"
    ],
    "name:nld_x_preferred":[
        "Taiping"
    ],
    "name:rus_x_preferred":[
        "\u0422\u0430\u0439\u043f\u0438\u043d"
    ],
    "name:swe_x_preferred":[
        "Taiping"
    ],
    "name:und_x_variant":[
        "T\u2019ai-p\u2019ing-chen",
        "Taipingzhen",
        "Taiping"
    ],
    "wof:name":"Taiping",
    "wof:placetype":"locality"
},
  "geometry": {"coordinates":[118.31667,37.93333],"type":"Point"}
}