{
  "type": "Feature",
  "properties": {
    "gn:admin1_code":"1.0",
    "gn:asciiname":"Shuangbancun",
    "gn:country_code":"CN",
    "gn:dem":27,
    "gn:feature_class":"P",
    "gn:feature_code":"PPL",
    "gn:name":"Shuangbancun",
    "gn:population":0,
    "gn:timezone":"Asia/Shanghai",
    "iso:country":"CN",
    "name:zho_x_preferred":[
        "\u53cc\u677f\u6751"
    ],
    "wof:name":"Shuangbancun",
    "wof:placetype":"locality"
},
  "geometry": {"coordinates":[118.61351999999999,31.73187],"type":"Point"}
}