{
  "type": "Feature",
  "properties": {
    "gn:admin1_code":"18",
    "gn:asciiname":"Shangleizhuang",
    "gn:country_code":"CN",
    "gn:dem":1405,
    "gn:feature_class":"P",
    "gn:feature_code":"PPL",
    "gn:name":"Shangleizhuang",
    "gn:population":0,
    "gn:timezone":"Asia/Shanghai",
    "iso:country":"CN",
    "name:zho_x_preferred":[
        "\u4e0a\u96f7\u5e84"
    ],
    "wof:name":"Shangleizhuang",
    "wof:placetype":"locality"
},
  "geometry": {"coordinates":[105.556,25.0959],"type":"Point"}
}