{
  "type": "Feature",
  "properties": {
    "gn:admin1_code":"24",
    "gn:asciiname":"Hougong",
    "gn:country_code":"CN",
    "gn:dem":589,
    "gn:feature_class":"P",
    "gn:feature_code":"PPLA4",
    "gn:name":"Hougong",
    "gn:population":0,
    "gn:timezone":"Asia/Shanghai",
    "iso:country":"CN",
    "name:und_x_variant":[
        "Hou-kung",
        "Hougong",
        "\u540e\u5bab",
        "Hougong Xiang",
        "\u540e\u5bab\u4e61"
    ],
    "wof:name":"Hougong",
    "wof:placetype":"locality"
},
  "geometry": {"coordinates":[111.39832,35.35778],"type":"Point"}
}