{
  "type": "Feature",
  "properties": {
    "gn:admin1_code":"32.0",
    "gn:asciiname":"Luoruogunba",
    "gn:country_code":"CN",
    "gn:dem":3773,
    "gn:feature_class":"P",
    "gn:feature_code":"PPL",
    "gn:name":"Luoruogunba",
    "gn:population":0,
    "gn:timezone":"Asia/Shanghai",
    "iso:country":"CN",
    "name:zho_x_preferred":[
        "\u6d1b\u82e5\u68cd\u5df4"
    ],
    "wof:name":"Luoruogunba",
    "wof:placetype":"locality"
},
  "geometry": {"coordinates":[100.471,32.0735],"type":"Point"}
}