{
  "type": "Feature",
  "properties": {
    "gn:admin1_code":"10.0",
    "gn:asciiname":"Xizhaohe",
    "gn:country_code":"CN",
    "gn:dem":10,
    "gn:feature_class":"P",
    "gn:feature_code":"PPL",
    "gn:name":"Xizhaohe",
    "gn:population":0,
    "gn:timezone":"Asia/Shanghai",
    "iso:country":"CN",
    "name:zho_x_preferred":[
        "\u897f\u8d75\u6cb3"
    ],
    "wof:name":"Xizhaohe",
    "wof:placetype":"locality"
},
  "geometry": {"coordinates":[117.129,38.1796],"type":"Point"}
}