{
  "type": "Feature",
  "properties": {
    "gn:admin1_code":"12.0",
    "gn:asciiname":"Wudouqiu",
    "gn:country_code":"CN",
    "gn:dem":23,
    "gn:feature_class":"P",
    "gn:feature_code":"PPL",
    "gn:name":"Wudouqiu",
    "gn:population":0,
    "gn:timezone":"Asia/Shanghai",
    "iso:country":"CN",
    "name:zho_x_preferred":[
        "\u4e94\u6597\u4e18"
    ],
    "wof:name":"Wudouqiu",
    "wof:placetype":"locality"
},
  "geometry": {"coordinates":[114.77929,30.45574],"type":"Point"}
}