{
  "type": "Feature",
  "properties": {
    "gn:admin1_code":"11.0",
    "gn:asciiname":"Niujiaotang",
    "gn:country_code":"CN",
    "gn:dem":1001,
    "gn:feature_class":"P",
    "gn:feature_code":"PPL",
    "gn:name":"Niujiaotang",
    "gn:population":0,
    "gn:timezone":"Asia/Shanghai",
    "iso:country":"CN",
    "name:zho_x_preferred":[
        "\u725b\u89d2\u5858"
    ],
    "wof:name":"Niujiaotang",
    "wof:placetype":"locality"
},
  "geometry": {"coordinates":[110.09836,28.86097],"type":"Point"}
}