{
  "type": "Feature",
  "properties": {
    "gn:admin1_code":"16.0",
    "gn:asciiname":"Mawangdong",
    "gn:country_code":"CN",
    "gn:dem":211,
    "gn:feature_class":"P",
    "gn:feature_code":"PPL",
    "gn:name":"Mawangdong",
    "gn:population":0,
    "gn:timezone":"Asia/Shanghai",
    "iso:country":"CN",
    "name:zho_x_preferred":[
        "\u9a6c\u738b\u578c"
    ],
    "wof:name":"Mawangdong",
    "wof:placetype":"locality"
},
  "geometry": {"coordinates":[111.04000000000001,22.9261],"type":"Point"}
}