{
  "type": "Feature",
  "properties": {
    "gn:admin1_code":"8.0",
    "gn:asciiname":"Changshengdi Yingzi",
    "gn:country_code":"CN",
    "gn:dem":473,
    "gn:feature_class":"P",
    "gn:feature_code":"PPLF",
    "gn:name":"Changshengdi Yingzi",
    "gn:population":0,
    "gn:timezone":"Asia/Shanghai",
    "iso:country":"CN",
    "name:und_x_variant":[
        "\u957f\u80dc\u5730\u8425\u5b50"
    ],
    "wof:name":"Changshengdi Yingzi",
    "wof:placetype":"locality"
},
  "geometry": {"coordinates":[126.52728,49.894],"type":"Point"}
}