{
  "type": "Feature",
  "properties": {
    "gn:admin1_code":"32.0",
    "gn:asciiname":"Qidaogou",
    "gn:country_code":"CN",
    "gn:dem":458,
    "gn:feature_class":"P",
    "gn:feature_code":"PPL",
    "gn:name":"Qidaogou",
    "gn:population":0,
    "gn:timezone":"Asia/Shanghai",
    "iso:country":"CN",
    "name:zho_x_preferred":[
        "\u4e03\u9053\u6c9f"
    ],
    "wof:name":"Qidaogou",
    "wof:placetype":"locality"
},
  "geometry": {"coordinates":[104.408,30.9366],"type":"Point"}
}