{
  "type": "Feature",
  "properties": {
    "gn:admin1_code":"20.0",
    "gn:asciiname":"Chijiayao",
    "gn:country_code":"CN",
    "gn:dem":1308,
    "gn:feature_class":"P",
    "gn:feature_code":"PPL",
    "gn:name":"Chijiayao",
    "gn:population":0,
    "gn:timezone":"Asia/Shanghai",
    "iso:country":"CN",
    "name:und_x_variant":[
        "\u6c60\u5bb6\u7a91"
    ],
    "wof:name":"Chijiayao",
    "wof:placetype":"locality"
},
  "geometry": {"coordinates":[111.69448,39.79508],"type":"Point"}
}