{
  "type": "Feature",
  "properties": {
    "gn:admin1_code":"32.0",
    "gn:asciiname":"Dingyang",
    "gn:country_code":"CN",
    "gn:dem":3564,
    "gn:feature_class":"P",
    "gn:feature_code":"PPL",
    "gn:name":"Dingyang",
    "gn:population":0,
    "gn:timezone":"Asia/Shanghai",
    "iso:country":"CN",
    "name:zho_x_preferred":[
        "\u4e01\u592e"
    ],
    "wof:name":"Dingyang",
    "wof:placetype":"locality"
},
  "geometry": {"coordinates":[101.03932,28.7898],"type":"Point"}
}