{
  "type": "Feature",
  "properties": {
    "gn:admin1_code":"21",
    "gn:asciiname":"Baijigou",
    "gn:country_code":"CN",
    "gn:dem":1847,
    "gn:feature_class":"P",
    "gn:feature_code":"PPL",
    "gn:name":"Baijigou",
    "gn:population":0,
    "gn:timezone":"Asia/Shanghai",
    "iso:country":"CN",
    "name:zho_x_preferred":[
        "\u767d\u82a8\u6c9f"
    ],
    "wof:name":"Baijigou",
    "wof:placetype":"locality"
},
  "geometry": {"coordinates":[106.142,39.1217],"type":"Point"}
}