{
  "type": "Feature",
  "properties": {
    "gn:admin1_code":"14.0",
    "gn:asciiname":"Guina",
    "gn:country_code":"CN",
    "gn:dem":4758,
    "gn:feature_class":"P",
    "gn:feature_code":"PPL",
    "gn:name":"Guina",
    "gn:population":0,
    "gn:timezone":"Asia/Urumqi",
    "iso:country":"CN",
    "name:zho_x_preferred":[
        "\u5f52\u90a3"
    ],
    "wof:name":"Guina",
    "wof:placetype":"locality"
},
  "geometry": {"coordinates":[91.44226999999999,32.21685],"type":"Point"}
}