{
  "type": "Feature",
  "properties": {
    "gn:admin1_code":"29.0",
    "gn:asciiname":"Guanlei",
    "gn:country_code":"CN",
    "gn:dem":533,
    "gn:feature_class":"P",
    "gn:feature_code":"PPL",
    "gn:name":"Guanlei",
    "gn:population":0,
    "gn:timezone":"Asia/Yangon",
    "iso:country":"CN",
    "name:zho_x_preferred":[
        "\u5173\u7d2f"
    ],
    "wof:name":"Guanlei",
    "wof:placetype":"locality"
},
  "geometry": {"coordinates":[101.12,21.6925],"type":"Point"}
}