{
  "type": "Feature",
  "properties": {
    "gn:admin1_code":"15.0",
    "gn:asciiname":"Kuanchuan",
    "gn:country_code":"CN",
    "gn:dem":2283,
    "gn:feature_class":"P",
    "gn:feature_code":"PPL",
    "gn:name":"Kuanchuan",
    "gn:population":0,
    "gn:timezone":"Asia/Shanghai",
    "iso:country":"CN",
    "name:zho_x_preferred":[
        "\u5bbd\u5ddd"
    ],
    "wof:name":"Kuanchuan",
    "wof:placetype":"locality"
},
  "geometry": {"coordinates":[104.187,35.3377],"type":"Point"}
}