{
  "type": "Feature",
  "properties": {
    "gn:admin1_code":"2.0",
    "gn:asciiname":"Xuokengkou",
    "gn:country_code":"CN",
    "gn:dem":641,
    "gn:feature_class":"P",
    "gn:feature_code":"PPL",
    "gn:name":"Xuokengkou",
    "gn:population":0,
    "gn:timezone":"Asia/Shanghai",
    "iso:country":"CN",
    "name:zho_x_preferred":[
        "\u5de6\u5751\u53e3"
    ],
    "wof:name":"Xuokengkou",
    "wof:placetype":"locality"
},
  "geometry": {"coordinates":[118.69944,28.46052],"type":"Point"}
}