{
  "type": "Feature",
  "properties": {
    "gn:admin1_code":"16.0",
    "gn:asciiname":"Bafang",
    "gn:country_code":"CN",
    "gn:dem":493,
    "gn:feature_class":"P",
    "gn:feature_code":"PPL",
    "gn:name":"Bafang",
    "gn:population":0,
    "gn:timezone":"Asia/Shanghai",
    "iso:country":"CN",
    "name:ceb_x_preferred":[
        "Bafang"
    ],
    "name:ces_x_preferred":[
        "Bafang"
    ],
    "name:deu_x_preferred":[
        "Bafang"
    ],
    "name:fra_x_preferred":[
        "Bafang"
    ],
    "name:heb_x_preferred":[
        "\u05d1\u05e4\u05e0\u05d2"
    ],
    "name:ita_x_preferred":[
        "Bafang"
    ],
    "name:msa_x_preferred":[
        "Bafang"
    ],
    "name:pol_x_preferred":[
        "Bafang"
    ],
    "name:por_x_preferred":[
        "Bafang"
    ],
    "name:ron_x_preferred":[
        "Bafang"
    ],
    "name:spa_x_preferred":[
        "Bafang"
    ],
    "name:swe_x_preferred":[
        "Bafang"
    ],
    "name:zho_x_preferred":[
        "\u5c9c\u9632"
    ],
    "wof:name":"Bafang",
    "wof:placetype":"locality"
},
  "geometry": {"coordinates":[107.29300000000001,24.4663],"type":"Point"}
}