{
  "type": "Feature",
  "properties": {
    "gn:admin1_code":"16.0",
    "gn:asciiname":"Bafang",
    "gn:country_code":"CN",
    "gn:dem":493,
    "gn:feature_class":"P",
    "gn:feature_code":"PPL",
    "gn:name":"Bafang",
    "gn:population":0,
    "gn:timezone":"Asia/Shanghai",
    "iso:country":"CN",
    "name:ben_x_preferred":[
        "\u09ac\u09be\u09ab\u09be\u0982\u0997"
    ],
    "name:ceb_x_preferred":[
        "Bafang"
    ],
    "name:ces_x_preferred":[
        "Bafang"
    ],
    "name:deu_x_preferred":[
        "Bafang"
    ],
    "name:ell_x_preferred":[
        "\u039c\u03c0\u03b1\u03c6\u03ac\u03bd\u03b3\u03ba"
    ],
    "name:fas_x_preferred":[
        "\u0628\u0627\u0641\u0627\u0646\u06af"
    ],
    "name:fra_x_preferred":[
        "Bafang"
    ],
    "name:heb_x_preferred":[
        "\u05d1\u05e4\u05e0\u05d2"
    ],
    "name:hin_x_preferred":[
        "\u092c\u092b\u093e\u0902\u0917"
    ],
    "name:hun_x_preferred":[
        "Bafang"
    ],
    "name:ind_x_preferred":[
        "Bafang"
    ],
    "name:ita_x_preferred":[
        "Bafang"
    ],
    "name:jpn_x_preferred":[
        "\u30d0\u30d5\u30a1\u30f3"
    ],
    "name:kor_x_preferred":[
        "\ubc14\ud321"
    ],
    "name:msa_x_preferred":[
        "Bafang"
    ],
    "name:pol_x_preferred":[
        "Bafang"
    ],
    "name:por_x_preferred":[
        "Bafang"
    ],
    "name:ron_x_preferred":[
        "Bafang"
    ],
    "name:rus_x_preferred":[
        "\u0411\u0430\u0444\u0430\u043d"
    ],
    "name:spa_x_preferred":[
        "Bafang"
    ],
    "name:swe_x_preferred":[
        "Bafang"
    ],
    "name:tur_x_preferred":[
        "Bafang"
    ],
    "name:ukr_x_preferred":[
        "\u0411\u0430\u0444\u0430\u043d\u0433"
    ],
    "name:urd_x_preferred":[
        "\u0628\u0627\u0641\u0627\u0646\u06af"
    ],
    "name:vie_x_preferred":[
        "Bafang"
    ],
    "name:zho_x_preferred":[
        "\u5c9c\u9632"
    ],
    "wof:name":"Bafang",
    "wof:placetype":"locality"
},
  "geometry": {"coordinates":[107.29300000000001,24.4663],"type":"Point"}
}