{
  "type": "Feature",
  "properties": {
    "gn:admin1_code":"1.0",
    "gn:asciiname":"Nongchangcun",
    "gn:country_code":"CN",
    "gn:dem":65,
    "gn:feature_class":"P",
    "gn:feature_code":"PPLF",
    "gn:name":"Nongchangcun",
    "gn:population":0,
    "gn:timezone":"Asia/Shanghai",
    "iso:country":"CN",
    "name:zho_x_preferred":[
        "\u519c\u573a\u6751"
    ],
    "wof:name":"Nongchangcun",
    "wof:placetype":"locality"
},
  "geometry": {"coordinates":[115.92442,31.74734],"type":"Point"}
}