{
  "type": "Feature",
  "properties": {
    "gn:admin1_code":"10",
    "gn:asciiname":"Weijiahui",
    "gn:country_code":"CN",
    "gn:dem":164,
    "gn:feature_class":"P",
    "gn:feature_code":"PPL",
    "gn:name":"Weijiahui",
    "gn:population":0,
    "gn:timezone":"Asia/Shanghai",
    "iso:country":"CN",
    "name:zho_x_preferred":[
        "\u9b4f\u5bb6\u8f89"
    ],
    "wof:name":"Weijiahui",
    "wof:placetype":"locality"
},
  "geometry": {"coordinates":[114.36199999999999,37.3934],"type":"Point"}
}