{
  "type": "Feature",
  "properties": {
    "gn:admin1_code":"23.0",
    "gn:asciiname":"Qingongtang",
    "gn:country_code":"CN",
    "gn:dem":4,
    "gn:feature_class":"P",
    "gn:feature_code":"PPL",
    "gn:name":"Qingongtang",
    "gn:population":0,
    "gn:timezone":"Asia/Shanghai",
    "iso:country":"CN",
    "name:und_x_variant":[
        "\u94a6\u516c\u5858"
    ],
    "wof:name":"Qingongtang",
    "wof:placetype":"locality"
},
  "geometry": {"coordinates":[121.66750999999999,31.31257],"type":"Point"}
}