{
  "type": "Feature",
  "properties": {
    "gn:admin1_code":"8.0",
    "gn:asciiname":"Jinshengtun",
    "gn:country_code":"CN",
    "gn:dem":195,
    "gn:feature_class":"P",
    "gn:feature_code":"PPL",
    "gn:name":"Jinshengtun",
    "gn:population":0,
    "gn:timezone":"Asia/Shanghai",
    "iso:country":"CN",
    "name:zho_x_preferred":[
        "\u91d1\u80dc\u5c6f"
    ],
    "wof:name":"Jinshengtun",
    "wof:placetype":"locality"
},
  "geometry": {"coordinates":[128.47116,45.47005],"type":"Point"}
}