{
  "type": "Feature",
  "properties": {
    "gn:admin1_code":"19.0",
    "gn:asciiname":"Shangwangjiadian",
    "gn:country_code":"CN",
    "gn:dem":252,
    "gn:feature_class":"P",
    "gn:feature_code":"PPL",
    "gn:name":"Shangwangjiadian",
    "gn:population":0,
    "gn:timezone":"Asia/Shanghai",
    "iso:country":"CN",
    "name:zho_x_preferred":[
        "\u4e0a\u738b\u5bb6\u5e97"
    ],
    "wof:name":"Shangwangjiadian",
    "wof:placetype":"locality"
},
  "geometry": {"coordinates":[123.10455,40.68813],"type":"Point"}
}