{
  "type": "Feature",
  "properties": {
    "gn:admin1_code":"9.0",
    "gn:asciiname":"Wangzhifang",
    "gn:country_code":"CN",
    "gn:dem":72,
    "gn:feature_class":"P",
    "gn:feature_code":"PPL",
    "gn:name":"Wangzhifang",
    "gn:population":0,
    "gn:timezone":"Asia/Shanghai",
    "iso:country":"CN",
    "name:zho_x_preferred":[
        "\u738b\u7eb8\u7eba"
    ],
    "wof:name":"Wangzhifang",
    "wof:placetype":"locality"
},
  "geometry": {"coordinates":[114.36508000000001,35.18734],"type":"Point"}
}