{
  "type": "Feature",
  "properties": {
    "gn:admin1_code":"11.0",
    "gn:asciiname":"Tianjiaping",
    "gn:country_code":"CN",
    "gn:dem":65,
    "gn:feature_class":"P",
    "gn:feature_code":"PPL",
    "gn:name":"Tianjiaping",
    "gn:population":0,
    "gn:timezone":"Asia/Shanghai",
    "iso:country":"CN",
    "name:zho_x_preferred":[
        "Tianjiaping"
    ],
    "name:zho_x_variant":[
        "\u7530\u5bb6\u576a"
    ],
    "wof:name":"Tianjiaping",
    "wof:placetype":"locality"
},
  "geometry": {"coordinates":[111.65281,29.20089],"type":"Point"}
}