{
  "type": "Feature",
  "properties": {
    "gn:admin1_code":"29.0",
    "gn:asciiname":"Nanmuping",
    "gn:country_code":"CN",
    "gn:dem":1286,
    "gn:feature_class":"P",
    "gn:feature_code":"PPL",
    "gn:name":"Nanmuping",
    "gn:population":0,
    "gn:timezone":"Asia/Shanghai",
    "iso:country":"CN",
    "name:zho_x_preferred":[
        "\u6960\u6728\u576a"
    ],
    "wof:name":"Nanmuping",
    "wof:placetype":"locality"
},
  "geometry": {"coordinates":[104.535,27.7307],"type":"Point"}
}