{
  "type": "Feature",
  "properties": {
    "gn:admin1_code":"19",
    "gn:admin2_code":"2033369.0",
    "gn:admin3_code":"6599874.0",
    "gn:asciiname":"Lanqi",
    "gn:country_code":"CN",
    "gn:dem":3,
    "gn:feature_class":"P",
    "gn:feature_code":"PPL",
    "gn:name":"Lanqi",
    "gn:population":0,
    "gn:timezone":"Asia/Shanghai",
    "iso:country":"CN",
    "name:eng_x_preferred":[
        "Lanqi"
    ],
    "name:zho_x_preferred":[
        "\u5170\u65d7"
    ],
    "wof:name":"Lanqi",
    "wof:placetype":"locality"
},
  "geometry": {"coordinates":[122.31844,40.54457],"type":"Point"}
}