{
  "type": "Feature",
  "properties": {
    "gn:admin1_code":"33.0",
    "gn:asciiname":"Shiyun",
    "gn:country_code":"CN",
    "gn:dem":562,
    "gn:feature_class":"P",
    "gn:feature_code":"PPL",
    "gn:name":"Shiyun",
    "gn:population":0,
    "gn:timezone":"Asia/Shanghai",
    "iso:country":"CN",
    "name:zho_x_preferred":[
        "\u77f3\u4e91"
    ],
    "wof:name":"Shiyun",
    "wof:placetype":"locality"
},
  "geometry": {"coordinates":[108.74348999999999,30.9752],"type":"Point"}
}