{
  "type": "Feature",
  "properties": {
    "gn:admin1_code":"33.0",
    "gn:asciiname":"Huanpo",
    "gn:country_code":"CN",
    "gn:dem":867,
    "gn:feature_class":"P",
    "gn:feature_code":"PPL",
    "gn:name":"Huanpo",
    "gn:population":0,
    "gn:timezone":"Asia/Shanghai",
    "iso:country":"CN",
    "name:zho_x_preferred":[
        "\u73af\u5761"
    ],
    "wof:name":"Huanpo",
    "wof:placetype":"locality"
},
  "geometry": {"coordinates":[108.22217000000001,29.26588],"type":"Point"}
}