{
  "type": "Feature",
  "properties": {
    "gn:admin1_code":"11.0",
    "gn:asciiname":"Heyewan",
    "gn:country_code":"CN",
    "gn:dem":851,
    "gn:feature_class":"P",
    "gn:feature_code":"PPL",
    "gn:name":"Heyewan",
    "gn:population":0,
    "gn:timezone":"Asia/Shanghai",
    "iso:country":"CN",
    "name:zho_x_preferred":[
        "\u6cb3\u53f6\u6e7e"
    ],
    "wof:name":"Heyewan",
    "wof:placetype":"locality"
},
  "geometry": {"coordinates":[110.61618,29.3395],"type":"Point"}
}