{
  "type": "Feature",
  "properties": {
    "gn:admin1_code":"2.0",
    "gn:asciiname":"Ruopingkeng",
    "gn:country_code":"CN",
    "gn:dem":610,
    "gn:feature_class":"P",
    "gn:feature_code":"PPL",
    "gn:name":"Ruopingkeng",
    "gn:population":0,
    "gn:timezone":"Asia/Shanghai",
    "iso:country":"CN",
    "name:zho_x_preferred":[
        "\u7bac\u576a\u5751"
    ],
    "wof:name":"Ruopingkeng",
    "wof:placetype":"locality"
},
  "geometry": {"coordinates":[118.809,28.34152000000001],"type":"Point"}
}