{
  "type": "Feature",
  "properties": {
    "gn:admin1_code":"9.0",
    "gn:asciiname":"Zhanggou",
    "gn:country_code":"CN",
    "gn:dem":1000,
    "gn:feature_class":"P",
    "gn:feature_code":"PPL",
    "gn:name":"Zhanggou",
    "gn:population":0,
    "gn:timezone":"Asia/Shanghai",
    "iso:country":"CN",
    "name:zho_x_preferred":[
        "\u5f20\u6c9f"
    ],
    "wof:name":"Zhanggou",
    "wof:placetype":"locality"
},
  "geometry": {"coordinates":[113.60002,35.62972],"type":"Point"}
}