{
  "type": "Feature",
  "properties": {
    "gn:admin1_code":"4.0",
    "gn:asciiname":"Dingshe",
    "gn:country_code":"CN",
    "gn:dem":0,
    "gn:feature_class":"P",
    "gn:feature_code":"PPL",
    "gn:name":"Dingshe",
    "gn:population":0,
    "gn:timezone":"Asia/Shanghai",
    "iso:country":"CN",
    "name:zho_x_preferred":[
        "Dingshe"
    ],
    "name:zho_x_variant":[
        "\u4e01\u820d"
    ],
    "wof:name":"Dingshe",
    "wof:placetype":"locality"
},
  "geometry": {"coordinates":[119.81415,33.63129],"type":"Point"}
}