{
  "type": "Feature",
  "properties": {
    "gn:admin1_code":"15.0",
    "gn:asciiname":"Shuipingyuan",
    "gn:country_code":"CN",
    "gn:dem":1442,
    "gn:feature_class":"P",
    "gn:feature_code":"PPL",
    "gn:name":"Shuipingyuan",
    "gn:population":0,
    "gn:timezone":"Asia/Shanghai",
    "iso:country":"CN",
    "name:zho_x_preferred":[
        "\u6c34\u5e73\u586c"
    ],
    "wof:name":"Shuipingyuan",
    "wof:placetype":"locality"
},
  "geometry": {"coordinates":[108.02800000000001,36.2772],"type":"Point"}
}