{
  "type": "Feature",
  "properties": {
    "gn:admin1_code":"29",
    "gn:asciiname":"Baoan",
    "gn:country_code":"CN",
    "gn:dem":1626,
    "gn:feature_class":"P",
    "gn:feature_code":"PPL",
    "gn:name":"Baoan",
    "gn:population":0,
    "gn:timezone":"Asia/Shanghai",
    "iso:country":"CN",
    "name:zho_x_preferred":[
        "\u4fdd\u5b89"
    ],
    "wof:name":"Baoan",
    "wof:placetype":"locality"
},
  "geometry": {"coordinates":[102.26378,24.46133],"type":"Point"}
}