{
  "type": "Feature",
  "properties": {
    "gn:admin1_code":"12.0",
    "gn:asciiname":"Xinleyuan",
    "gn:country_code":"CN",
    "gn:dem":28,
    "gn:feature_class":"P",
    "gn:feature_code":"PPL",
    "gn:name":"Xinleyuan",
    "gn:population":0,
    "gn:timezone":"Asia/Shanghai",
    "iso:country":"CN",
    "name:zho_x_preferred":[
        "\u65b0\u4e50\u57b8"
    ],
    "wof:name":"Xinleyuan",
    "wof:placetype":"locality"
},
  "geometry": {"coordinates":[113.85809,30.68354],"type":"Point"}
}