{
  "type": "Feature",
  "properties": {
    "gn:admin1_code":"3",
    "gn:asciiname":"Shaxi",
    "gn:country_code":"CN",
    "gn:dem":552,
    "gn:feature_class":"P",
    "gn:feature_code":"PPL",
    "gn:name":"Shaxi",
    "gn:population":0,
    "gn:timezone":"Asia/Shanghai",
    "iso:country":"CN",
    "name:ceb_x_preferred":[
        "Shaxi"
    ],
    "name:deu_x_preferred":[
        "Shaxi"
    ],
    "name:fra_x_preferred":[
        "Shaxi"
    ],
    "name:swe_x_preferred":[
        "Shaxi"
    ],
    "name:zho_x_preferred":[
        "\u6c99\u6eaa"
    ],
    "wof:name":"Shaxi",
    "wof:placetype":"locality"
},
  "geometry": {"coordinates":[114.146,25.5565],"type":"Point"}
}