{
  "type": "Feature",
  "properties": {
    "gn:admin1_code":"32.0",
    "gn:asciiname":"Tongtou",
    "gn:country_code":"CN",
    "gn:dem":696,
    "gn:feature_class":"P",
    "gn:feature_code":"PPL",
    "gn:name":"Tongtou",
    "gn:population":0,
    "gn:timezone":"Asia/Shanghai",
    "iso:country":"CN",
    "name:zho_x_preferred":[
        "\u94dc\u5934"
    ],
    "wof:name":"Tongtou",
    "wof:placetype":"locality"
},
  "geometry": {"coordinates":[102.88500000000001,30.1513],"type":"Point"}
}