{
  "type": "Feature",
  "properties": {
    "gn:admin1_code":"25",
    "gn:asciiname":"Fangzi",
    "gn:cc2":"CN",
    "gn:country_code":"CN",
    "gn:dem":70,
    "gn:feature_class":"P",
    "gn:feature_code":"PPL",
    "gn:name":"Fangzi",
    "gn:population":0,
    "gn:timezone":"Asia/Shanghai",
    "iso:country":"CN",
    "name:und_x_variant":[
        "Fang-tzu",
        "Fangtze",
        "Fangzi"
    ],
    "wof:name":"Fangzi",
    "wof:placetype":"locality"
},
  "geometry": {"coordinates":[119.15416999999999,36.59528],"type":"Point"}
}