{
  "type": "Feature",
  "properties": {
    "gn:admin1_code":"19.0",
    "gn:asciiname":"Dongkutui",
    "gn:country_code":"CN",
    "gn:dem":153,
    "gn:feature_class":"P",
    "gn:feature_code":"PPL",
    "gn:name":"Dongkutui",
    "gn:population":0,
    "gn:timezone":"Asia/Shanghai",
    "iso:country":"CN",
    "name:und_x_variant":[
        "\u4e1c\u88e4\u817f"
    ],
    "name:zho_x_preferred":[
        "\u4e1c\u88e4\u817f"
    ],
    "wof:name":"Dongkutui",
    "wof:placetype":"locality"
},
  "geometry": {"coordinates":[125.16416,40.6823],"type":"Point"}
}