{
  "type": "Feature",
  "properties": {
    "gn:admin1_code":"5.0",
    "gn:asciiname":"Yangmugoucun",
    "gn:country_code":"CN",
    "gn:dem":252,
    "gn:feature_class":"P",
    "gn:feature_code":"PPL",
    "gn:name":"Yangmugoucun",
    "gn:population":0,
    "gn:timezone":"Asia/Shanghai",
    "iso:country":"CN",
    "name:zho_x_preferred":[
        "\u6768\u6728\u6c9f\u6751"
    ],
    "wof:name":"Yangmugoucun",
    "wof:placetype":"locality"
},
  "geometry": {"coordinates":[126.88777,43.65719],"type":"Point"}
}