{
  "type": "Feature",
  "properties": {
    "gn:admin1_code":"16.0",
    "gn:asciiname":"Ruanyun",
    "gn:country_code":"CN",
    "gn:dem":108,
    "gn:feature_class":"P",
    "gn:feature_code":"PPL",
    "gn:name":"Ruanyun",
    "gn:population":0,
    "gn:timezone":"Asia/Shanghai",
    "iso:country":"CN",
    "name:zho_x_preferred":[
        "\u962e\u4e91"
    ],
    "wof:name":"Ruanyun",
    "wof:placetype":"locality"
},
  "geometry": {"coordinates":[108.854,23.4933],"type":"Point"}
}