{
  "type": "Feature",
  "properties": {
    "gn:admin1_code":"10",
    "gn:asciiname":"Dongshanwan",
    "gn:country_code":"CN",
    "gn:dem":1499,
    "gn:feature_class":"P",
    "gn:feature_code":"PPL",
    "gn:name":"Dongshanwan",
    "gn:population":0,
    "gn:timezone":"Asia/Shanghai",
    "iso:country":"CN",
    "name:und_x_variant":[
        "Tung-shan-wan"
    ],
    "name:zho_x_preferred":[
        "\u4e1c\u5c71\u6e7e"
    ],
    "wof:name":"Dongshanwan",
    "wof:placetype":"locality"
},
  "geometry": {"coordinates":[116.00360999999999,41.55583],"type":"Point"}
}