{
  "type": "Feature",
  "properties": {
    "gn:admin1_code":"26.0",
    "gn:asciiname":"Mujiatacun",
    "gn:country_code":"CN",
    "gn:dem":1360,
    "gn:feature_class":"P",
    "gn:feature_code":"PPL",
    "gn:name":"Mujiatacun",
    "gn:population":0,
    "gn:timezone":"Asia/Shanghai",
    "iso:country":"CN",
    "name:zho_x_preferred":[
        "\u7a46\u5bb6\u584c\u6751"
    ],
    "wof:name":"Mujiatacun",
    "wof:placetype":"locality"
},
  "geometry": {"coordinates":[109.40291000000001,37.06124000000001],"type":"Point"}
}