{
  "type": "Feature",
  "properties": {
    "gn:admin1_code":"18.0",
    "gn:asciiname":"Shuitang",
    "gn:country_code":"CN",
    "gn:dem":836,
    "gn:feature_class":"P",
    "gn:feature_code":"PPL",
    "gn:name":"Shuitang",
    "gn:population":0,
    "gn:timezone":"Asia/Shanghai",
    "iso:country":"CN",
    "name:zho_x_preferred":[
        "\u6c34\u5858"
    ],
    "wof:name":"Shuitang",
    "wof:placetype":"locality"
},
  "geometry": {"coordinates":[107.952,27.6761],"type":"Point"}
}