{
  "type": "Feature",
  "properties": {
    "gn:admin1_code":"9.0",
    "gn:asciiname":"Changqing",
    "gn:country_code":"CN",
    "gn:dem":809,
    "gn:feature_class":"P",
    "gn:feature_code":"PPL",
    "gn:name":"Changqing",
    "gn:population":0,
    "gn:timezone":"Asia/Shanghai",
    "iso:country":"CN",
    "name:deu_x_preferred":[
        "Changqing"
    ],
    "name:zho_x_preferred":[
        "\u957f\u9752"
    ],
    "wof:name":"Changqing",
    "wof:placetype":"locality"
},
  "geometry": {"coordinates":[110.72843,34.01249],"type":"Point"}
}