{
  "type": "Feature",
  "properties": {
    "gn:admin1_code":"19.0",
    "gn:asciiname":"Fujialou",
    "gn:country_code":"CN",
    "gn:dem":241,
    "gn:feature_class":"P",
    "gn:feature_code":"PPL",
    "gn:name":"Fujialou",
    "gn:population":0,
    "gn:timezone":"Asia/Shanghai",
    "iso:country":"CN",
    "name:zho_x_preferred":[
        "\u5bcc\u5bb6\u697c"
    ],
    "wof:name":"Fujialou",
    "wof:placetype":"locality"
},
  "geometry": {"coordinates":[124.28767000000001,41.41883],"type":"Point"}
}