{
  "type": "Feature",
  "properties": {
    "gn:admin1_code":"29.0",
    "gn:asciiname":"Leiche",
    "gn:country_code":"CN",
    "gn:dem":1525,
    "gn:feature_class":"P",
    "gn:feature_code":"PPL",
    "gn:name":"Leiche",
    "gn:population":0,
    "gn:timezone":"Asia/Shanghai",
    "iso:country":"CN",
    "name:zho_x_preferred":[
        "\u96f7\u8f66"
    ],
    "wof:name":"Leiche",
    "wof:placetype":"locality"
},
  "geometry": {"coordinates":[100.595,25.9787],"type":"Point"}
}