{
  "type": "Feature",
  "properties": {
    "gn:admin1_code":"12.0",
    "gn:asciiname":"Laofanggou",
    "gn:country_code":"CN",
    "gn:dem":252,
    "gn:feature_class":"P",
    "gn:feature_code":"PPL",
    "gn:name":"Laofanggou",
    "gn:population":0,
    "gn:timezone":"Asia/Shanghai",
    "iso:country":"CN",
    "name:zho_x_preferred":[
        "\u8001\u623f\u6c9f"
    ],
    "wof:name":"Laofanggou",
    "wof:placetype":"locality"
},
  "geometry": {"coordinates":[111.39185999999999,32.6579],"type":"Point"}
}