{
  "type": "Feature",
  "properties": {
    "gn:admin1_code":"16.0",
    "gn:asciiname":"Muyang",
    "gn:country_code":"CN",
    "gn:dem":497,
    "gn:feature_class":"P",
    "gn:feature_code":"PPL",
    "gn:name":"Muyang",
    "gn:population":0,
    "gn:timezone":"Asia/Shanghai",
    "iso:country":"CN",
    "name:deu_x_preferred":[
        "Muyang"
    ],
    "name:zho_x_preferred":[
        "\u5893\u6d0b"
    ],
    "wof:name":"Muyang",
    "wof:placetype":"locality"
},
  "geometry": {"coordinates":[107.739,23.867],"type":"Point"}
}