{
  "type": "Feature",
  "properties": {
    "gn:admin1_code":"24.0",
    "gn:asciiname":"Xiameizhicun",
    "gn:country_code":"CN",
    "gn:dem":972,
    "gn:feature_class":"P",
    "gn:feature_code":"PPL",
    "gn:name":"Xiameizhicun",
    "gn:population":0,
    "gn:timezone":"Asia/Shanghai",
    "iso:country":"CN",
    "name:zho_x_preferred":[
        "\u4e0b\u7709\u829d\u6751"
    ],
    "wof:name":"Xiameizhicun",
    "wof:placetype":"locality"
},
  "geometry": {"coordinates":[110.92253999999998,37.32616],"type":"Point"}
}