{
  "type": "Feature",
  "properties": {
    "gn:admin1_code":"16",
    "gn:asciiname":"Jiebeitian",
    "gn:country_code":"CN",
    "gn:dem":567,
    "gn:feature_class":"P",
    "gn:feature_code":"PPL",
    "gn:name":"Jiebeitian",
    "gn:population":0,
    "gn:timezone":"Asia/Shanghai",
    "iso:country":"CN",
    "name:zho_x_preferred":[
        "\u754c\u80cc\u7530"
    ],
    "wof:name":"Jiebeitian",
    "wof:placetype":"locality"
},
  "geometry": {"coordinates":[110.746,25.3715],"type":"Point"}
}