{
  "type": "Feature",
  "properties": {
    "gn:admin1_code":"30.0",
    "gn:asciiname":"Jingxiacun",
    "gn:country_code":"CN",
    "gn:dem":192,
    "gn:feature_class":"P",
    "gn:feature_code":"PPL",
    "gn:name":"Jingxiacun",
    "gn:population":0,
    "gn:timezone":"Asia/Shanghai",
    "iso:country":"CN",
    "name:zho_x_preferred":[
        "\u5f84\u4e0b\u6751"
    ],
    "wof:name":"Jingxiacun",
    "wof:placetype":"locality"
},
  "geometry": {"coordinates":[115.96961,23.90127],"type":"Point"}
}