{
  "type": "Feature",
  "properties": {
    "gn:admin1_code":"32.0",
    "gn:asciiname":"Huangtianwan",
    "gn:country_code":"CN",
    "gn:dem":424,
    "gn:feature_class":"P",
    "gn:feature_code":"PPL",
    "gn:name":"Huangtianwan",
    "gn:population":0,
    "gn:timezone":"Asia/Shanghai",
    "iso:country":"CN",
    "name:zho_x_preferred":[
        "\u9ec4\u6dfb\u6e7e"
    ],
    "wof:name":"Huangtianwan",
    "wof:placetype":"locality"
},
  "geometry": {"coordinates":[104.53218,30.06558],"type":"Point"}
}