{
  "type": "Feature",
  "properties": {
    "gn:admin1_code":"29.0",
    "gn:asciiname":"Gaojiaying",
    "gn:country_code":"CN",
    "gn:dem":1840,
    "gn:feature_class":"P",
    "gn:feature_code":"PPL",
    "gn:name":"Gaojiaying",
    "gn:population":0,
    "gn:timezone":"Asia/Shanghai",
    "iso:country":"CN",
    "name:zho_x_preferred":[
        "\u9ad8\u5bb6\u8425"
    ],
    "wof:name":"Gaojiaying",
    "wof:placetype":"locality"
},
  "geometry": {"coordinates":[103.76900000000001,27.6049],"type":"Point"}
}