{
  "type": "Feature",
  "properties": {
    "gn:admin1_code":"15.0",
    "gn:asciiname":"Xiazhongzhai",
    "gn:country_code":"CN",
    "gn:dem":2209,
    "gn:feature_class":"P",
    "gn:feature_code":"PPL",
    "gn:name":"Xiazhongzhai",
    "gn:population":0,
    "gn:timezone":"Asia/Shanghai",
    "iso:country":"CN",
    "name:und_x_variant":[
        "\u4e0b\u4e2d\u5be8"
    ],
    "wof:name":"Xiazhongzhai",
    "wof:placetype":"locality"
},
  "geometry": {"coordinates":[103.87641000000001,34.68725],"type":"Point"}
}