{
  "type": "Feature",
  "properties": {
    "gn:admin1_code":"4.0",
    "gn:asciiname":"Wanqiao",
    "gn:country_code":"CN",
    "gn:dem":5,
    "gn:feature_class":"P",
    "gn:feature_code":"PPL",
    "gn:name":"Wanqiao",
    "gn:population":0,
    "gn:timezone":"Asia/Shanghai",
    "iso:country":"CN",
    "name:zho_x_preferred":[
        "\u4e07\u6865"
    ],
    "wof:name":"Wanqiao",
    "wof:placetype":"locality"
},
  "geometry": {"coordinates":[120.587,32.3206],"type":"Point"}
}