{
  "type": "Feature",
  "properties": {
    "gn:admin1_code":"29",
    "gn:asciiname":"Mugen",
    "gn:country_code":"CN",
    "gn:dem":1449,
    "gn:feature_class":"P",
    "gn:feature_code":"PPL",
    "gn:name":"Mugen",
    "gn:population":0,
    "gn:timezone":"Asia/Shanghai",
    "iso:country":"CN",
    "name:ceb_x_preferred":[
        "Mugen"
    ],
    "name:fra_x_preferred":[
        "Mugen"
    ],
    "name:jpn_x_preferred":[
        "Mugen"
    ],
    "name:rus_x_preferred":[
        "Mugen"
    ],
    "name:spa_x_preferred":[
        "Mugen"
    ],
    "name:swe_x_preferred":[
        "Mugen"
    ],
    "name:zho_x_preferred":[
        "\u6728\u6839"
    ],
    "wof:name":"Mugen",
    "wof:placetype":"locality"
},
  "geometry": {"coordinates":[105.44199999999999,23.5649],"type":"Point"}
}