{
  "type": "Feature",
  "properties": {
    "gn:admin1_code":"12.0",
    "gn:asciiname":"Chenjiataizi",
    "gn:country_code":"CN",
    "gn:dem":90,
    "gn:feature_class":"P",
    "gn:feature_code":"PPL",
    "gn:name":"Chenjiataizi",
    "gn:population":0,
    "gn:timezone":"Asia/Shanghai",
    "iso:country":"CN",
    "name:zho_x_preferred":[
        "\u9648\u5bb6\u53f0\u5b50"
    ],
    "wof:name":"Chenjiataizi",
    "wof:placetype":"locality"
},
  "geometry": {"coordinates":[112.08369999999999,31.52599],"type":"Point"}
}