{
  "type": "Feature",
  "properties": {
    "gn:admin1_code":"32.0",
    "gn:asciiname":"Laoxiangping",
    "gn:country_code":"CN",
    "gn:dem":502,
    "gn:feature_class":"P",
    "gn:feature_code":"PPL",
    "gn:name":"Laoxiangping",
    "gn:population":0,
    "gn:timezone":"Asia/Shanghai",
    "iso:country":"CN",
    "name:zho_x_preferred":[
        "\u8001\u53a2\u576a"
    ],
    "wof:name":"Laoxiangping",
    "wof:placetype":"locality"
},
  "geometry": {"coordinates":[106.66459,31.89186],"type":"Point"}
}