{
  "type": "Feature",
  "properties": {
    "gn:admin1_code":"14.0",
    "gn:asciiname":"Mazha",
    "gn:country_code":"CN",
    "gn:dem":3982,
    "gn:feature_class":"P",
    "gn:feature_code":"PPL",
    "gn:name":"Mazha",
    "gn:population":0,
    "gn:timezone":"Asia/Urumqi",
    "iso:country":"CN",
    "name:mal_x_preferred":[
        "\u0d2e\u0d34"
    ],
    "name:zho_x_preferred":[
        "\u739b\u624e"
    ],
    "wof:name":"Mazha",
    "wof:placetype":"locality"
},
  "geometry": {"coordinates":[91.56139,30.08353],"type":"Point"}
}