{
  "type": "Feature",
  "properties": {
    "gn:admin1_code":"4.0",
    "gn:asciiname":"Yupogang",
    "gn:country_code":"CN",
    "gn:dem":4,
    "gn:feature_class":"P",
    "gn:feature_code":"PPL",
    "gn:name":"Yupogang",
    "gn:population":0,
    "gn:timezone":"Asia/Shanghai",
    "iso:country":"CN",
    "name:zho_x_preferred":[
        "\u9c7c\u5a46\u6e2f"
    ],
    "wof:name":"Yupogang",
    "wof:placetype":"locality"
},
  "geometry": {"coordinates":[120.26038,32.02753],"type":"Point"}
}