{
  "type": "Feature",
  "properties": {
    "gn:admin1_code":"32.0",
    "gn:asciiname":"Dapingzi",
    "gn:country_code":"CN",
    "gn:dem":2134,
    "gn:feature_class":"P",
    "gn:feature_code":"PPL",
    "gn:name":"Dapingzi",
    "gn:population":0,
    "gn:timezone":"Asia/Shanghai",
    "iso:country":"CN",
    "name:zho_x_preferred":[
        "\u5927\u576a\u5b50"
    ],
    "wof:name":"Dapingzi",
    "wof:placetype":"locality"
},
  "geometry": {"coordinates":[101.36887,26.8932],"type":"Point"}
}