{
  "type": "Feature",
  "properties": {
    "gn:admin1_code":"7.0",
    "gn:asciiname":"Bao'en",
    "gn:country_code":"CN",
    "gn:dem":132,
    "gn:feature_class":"P",
    "gn:feature_code":"PPL",
    "gn:name":"Bao\u2019en",
    "gn:population":0,
    "gn:timezone":"Asia/Shanghai",
    "iso:country":"CN",
    "name:zho_x_preferred":[
        "Bao\u2019en"
    ],
    "name:zho_x_variant":[
        "\u62a5\u6069"
    ],
    "wof:name":"Bao'en",
    "wof:placetype":"locality"
},
  "geometry": {"coordinates":[118.30662,26.98056],"type":"Point"}
}