{
  "type": "Feature",
  "properties": {
    "gn:admin1_code":"19.0",
    "gn:asciiname":"Juzhangzicun",
    "gn:country_code":"CN",
    "gn:dem":327,
    "gn:feature_class":"P",
    "gn:feature_code":"PPL",
    "gn:name":"Juzhangzicun",
    "gn:population":0,
    "gn:timezone":"Asia/Shanghai",
    "iso:country":"CN",
    "name:zho_x_preferred":[
        "\u97a0\u6756\u5b50\u6751"
    ],
    "wof:name":"Juzhangzicun",
    "wof:placetype":"locality"
},
  "geometry": {"coordinates":[120.24599000000001,41.65419],"type":"Point"}
}