{
  "type": "Feature",
  "properties": {
    "gn:admin1_code":"4.0",
    "gn:asciiname":"Pangxiawa",
    "gn:country_code":"CN",
    "gn:dem":33,
    "gn:feature_class":"P",
    "gn:feature_code":"PPL",
    "gn:name":"Pangxiawa",
    "gn:population":0,
    "gn:timezone":"Asia/Shanghai",
    "iso:country":"CN",
    "name:zho_x_preferred":[
        "\u5e9e\u590f\u6d3c"
    ],
    "wof:name":"Pangxiawa",
    "wof:placetype":"locality"
},
  "geometry": {"coordinates":[117.313,34.377],"type":"Point"}
}