{
  "type": "Feature",
  "properties": {
    "gn:admin1_code":"7.0",
    "gn:asciiname":"Caolongqi",
    "gn:country_code":"CN",
    "gn:dem":839,
    "gn:feature_class":"P",
    "gn:feature_code":"PPL",
    "gn:name":"Caolongqi",
    "gn:population":0,
    "gn:timezone":"Asia/Shanghai",
    "iso:country":"CN",
    "name:zho_x_preferred":[
        "\u8349\u5784\u5d0e"
    ],
    "wof:name":"Caolongqi",
    "wof:placetype":"locality"
},
  "geometry": {"coordinates":[117.74370999999999,25.54997],"type":"Point"}
}