{
  "type": "Feature",
  "properties": {
    "gn:admin1_code":"19.0",
    "gn:asciiname":"Xinglonggou",
    "gn:country_code":"CN",
    "gn:dem":683,
    "gn:feature_class":"P",
    "gn:feature_code":"PPL",
    "gn:name":"Xinglonggou",
    "gn:population":0,
    "gn:timezone":"Asia/Shanghai",
    "iso:country":"CN",
    "name:zho_x_preferred":[
        "\u5174\u9686\u6c9f"
    ],
    "name:zho_x_variant":[
        "\u5174\u9686\u6c9f\u9057\u5740"
    ],
    "wof:name":"Xinglonggou",
    "wof:placetype":"locality"
},
  "geometry": {"coordinates":[119.64700000000001,41.6785],"type":"Point"}
}