{
  "type": "Feature",
  "properties": {
    "gn:admin1_code":"3.0",
    "gn:asciiname":"Hailuowu",
    "gn:country_code":"CN",
    "gn:dem":456,
    "gn:feature_class":"P",
    "gn:feature_code":"PPL",
    "gn:name":"Hailuowu",
    "gn:population":0,
    "gn:timezone":"Asia/Shanghai",
    "iso:country":"CN",
    "name:zho_x_preferred":[
        "\u6d77\u87ba\u575e"
    ],
    "wof:name":"Hailuowu",
    "wof:placetype":"locality"
},
  "geometry": {"coordinates":[117.55500000000001,29.5897],"type":"Point"}
}