{
  "type": "Feature",
  "properties": {
    "gn:admin1_code":"30",
    "gn:asciiname":"Shiguhe",
    "gn:country_code":"CN",
    "gn:dem":26,
    "gn:feature_class":"P",
    "gn:feature_code":"PPL",
    "gn:name":"Shiguhe",
    "gn:population":0,
    "gn:timezone":"Asia/Urumqi",
    "iso:country":"CN",
    "name:zho_x_preferred":[
        "\u77f3\u53e4\u6cb3"
    ],
    "wof:name":"Shiguhe",
    "wof:placetype":"locality"
},
  "geometry": {"coordinates":[109.94837,21.50257],"type":"Point"}
}