{
  "type": "Feature",
  "properties": {
    "gn:admin1_code":"29.0",
    "gn:asciiname":"Jiuwuji",
    "gn:country_code":"CN",
    "gn:dem":2210,
    "gn:feature_class":"P",
    "gn:feature_code":"PPL",
    "gn:name":"Jiuwuji",
    "gn:population":0,
    "gn:timezone":"Asia/Shanghai",
    "iso:country":"CN",
    "name:zho_x_preferred":[
        "\u65e7\u5c4b\u57fa"
    ],
    "wof:name":"Jiuwuji",
    "wof:placetype":"locality"
},
  "geometry": {"coordinates":[100.512,26.4277],"type":"Point"}
}