{
  "type": "Feature",
  "properties": {
    "gn:admin1_code":"26.0",
    "gn:asciiname":"Dujiatai",
    "gn:country_code":"CN",
    "gn:dem":952,
    "gn:feature_class":"P",
    "gn:feature_code":"PPL",
    "gn:name":"Dujiatai",
    "gn:population":0,
    "gn:timezone":"Asia/Shanghai",
    "iso:country":"CN",
    "name:und_x_variant":[
        "\u675c\u5bb6\u53f0"
    ],
    "wof:name":"Dujiatai",
    "wof:placetype":"locality"
},
  "geometry": {"coordinates":[108.08692000000001,33.45865999999999],"type":"Point"}
}