{
  "type": "Feature",
  "properties": {
    "gn:admin1_code":"32.0",
    "gn:asciiname":"Zhuanmalu",
    "gn:country_code":"CN",
    "gn:dem":1198,
    "gn:feature_class":"P",
    "gn:feature_code":"PPL",
    "gn:name":"Zhuanmalu",
    "gn:population":0,
    "gn:timezone":"Asia/Shanghai",
    "iso:country":"CN",
    "name:zho_x_preferred":[
        "\u8f6c\u9a6c\u8def"
    ],
    "wof:name":"Zhuanmalu",
    "wof:placetype":"locality"
},
  "geometry": {"coordinates":[106.169,27.8372],"type":"Point"}
}