{
  "type": "Feature",
  "properties": {
    "gn:admin1_code":"24.0",
    "gn:asciiname":"Tiezhuang",
    "gn:country_code":"CN",
    "gn:dem":1003,
    "gn:feature_class":"P",
    "gn:feature_code":"PPL",
    "gn:name":"Tiezhuang",
    "gn:population":0,
    "gn:timezone":"Asia/Shanghai",
    "iso:country":"CN",
    "name:und_x_variant":[
        "\u5e16\u5e84"
    ],
    "name:zho_x_preferred":[
        "\u5e16\u5e84"
    ],
    "wof:name":"Tiezhuang",
    "wof:placetype":"locality"
},
  "geometry": {"coordinates":[113.01572,39.58266],"type":"Point"}
}