{
  "type": "Feature",
  "properties": {
    "gn:admin1_code":"26.0",
    "gn:asciiname":"Aiquanhe",
    "gn:country_code":"CN",
    "gn:dem":1071,
    "gn:feature_class":"P",
    "gn:feature_code":"PPL",
    "gn:name":"Aiquanhe",
    "gn:population":0,
    "gn:timezone":"Asia/Shanghai",
    "iso:country":"CN",
    "name:zho_x_preferred":[
        "\u66a7\u6cc9\u6cb3"
    ],
    "wof:name":"Aiquanhe",
    "wof:placetype":"locality"
},
  "geometry": {"coordinates":[109.17400000000001,35.9866],"type":"Point"}
}