{
  "type": "Feature",
  "properties": {
    "gn:admin1_code":"13",
    "gn:asciiname":"Kaiputai Erhana",
    "gn:country_code":"CN",
    "gn:dem":1261,
    "gn:feature_class":"P",
    "gn:feature_code":"PPL",
    "gn:name":"Kaiputai Erhana",
    "gn:population":0,
    "gn:timezone":"Asia/Shanghai",
    "iso:country":"CN",
    "name:und_x_variant":[
        "\u5f00\u666e\u53f0\u5c14\u54c8\u7eb3"
    ],
    "wof:name":"Kaiputai Erhana",
    "wof:placetype":"locality"
},
  "geometry": {"coordinates":[76.21795999999998,39.58916],"type":"Point"}
}