{
  "type": "Feature",
  "properties": {
    "gn:admin1_code":"3.0",
    "gn:asciiname":"Daokeng",
    "gn:country_code":"CN",
    "gn:dem":316,
    "gn:feature_class":"P",
    "gn:feature_code":"PPL",
    "gn:name":"Daokeng",
    "gn:population":0,
    "gn:timezone":"Asia/Shanghai",
    "iso:country":"CN",
    "name:zho_x_preferred":[
        "\u5200\u5751"
    ],
    "wof:name":"Daokeng",
    "wof:placetype":"locality"
},
  "geometry": {"coordinates":[115.28700000000001,25.4946],"type":"Point"}
}