{
  "type": "Feature",
  "properties": {
    "gn:admin1_code":"32.0",
    "gn:asciiname":"Dayuhuangmiao",
    "gn:country_code":"CN",
    "gn:dem":537,
    "gn:feature_class":"P",
    "gn:feature_code":"PPL",
    "gn:name":"Dayuhuangmiao",
    "gn:population":0,
    "gn:timezone":"Asia/Shanghai",
    "iso:country":"CN",
    "name:zho_x_preferred":[
        "\u5927\u7389\u7687\u5e99"
    ],
    "wof:name":"Dayuhuangmiao",
    "wof:placetype":"locality"
},
  "geometry": {"coordinates":[106.56618,30.97774],"type":"Point"}
}