{
  "type": "Feature",
  "properties": {
    "gn:admin1_code":"2",
    "gn:asciiname":"Bajiaoting",
    "gn:country_code":"CN",
    "gn:dem":92,
    "gn:feature_class":"P",
    "gn:feature_code":"PPL",
    "gn:name":"Bajiaoting",
    "gn:population":0,
    "gn:timezone":"Asia/Shanghai",
    "iso:country":"CN",
    "name:und_x_variant":[
        "\u516b\u89d2\u4ead"
    ],
    "wof:name":"Bajiaoting",
    "wof:placetype":"locality"
},
  "geometry": {"coordinates":[119.90694000000001,30.23278],"type":"Point"}
}