{
  "type": "Feature",
  "properties": {
    "gn:admin1_code":"32.0",
    "gn:asciiname":"Changpingzi",
    "gn:country_code":"CN",
    "gn:dem":1402,
    "gn:feature_class":"P",
    "gn:feature_code":"PPL",
    "gn:name":"Changpingzi",
    "gn:population":0,
    "gn:timezone":"Asia/Shanghai",
    "iso:country":"CN",
    "name:zho_x_preferred":[
        "\u957f\u576a\u5b50"
    ],
    "wof:name":"Changpingzi",
    "wof:placetype":"locality"
},
  "geometry": {"coordinates":[101.96299999999999,27.4683],"type":"Point"}
}