{
  "type": "Feature",
  "properties": {
    "gn:admin1_code":"5.0",
    "gn:asciiname":"Huaijiagou",
    "gn:country_code":"CN",
    "gn:dem":179,
    "gn:feature_class":"P",
    "gn:feature_code":"PPL",
    "gn:name":"Huaijiagou",
    "gn:population":0,
    "gn:timezone":"Asia/Shanghai",
    "iso:country":"CN",
    "name:zho_x_preferred":[
        "\u6000\u5bb6\u6c9f"
    ],
    "wof:name":"Huaijiagou",
    "wof:placetype":"locality"
},
  "geometry": {"coordinates":[126.71321,45.1187],"type":"Point"}
}