{
  "type": "Feature",
  "properties": {
    "gn:admin1_code":"11.0",
    "gn:asciiname":"Zhilan",
    "gn:country_code":"CN",
    "gn:dem":415,
    "gn:feature_class":"P",
    "gn:feature_code":"PPL",
    "gn:name":"Zhilan",
    "gn:population":0,
    "gn:timezone":"Asia/Shanghai",
    "iso:country":"CN",
    "name:zho_x_preferred":[
        "Zhilan"
    ],
    "name:zho_x_variant":[
        "\u829d\u5170"
    ],
    "wof:name":"Zhilan",
    "wof:placetype":"locality"
},
  "geometry": {"coordinates":[109.94199,29.19809],"type":"Point"}
}