{
  "type": "Feature",
  "properties": {
    "gn:admin1_code":"19.0",
    "gn:asciiname":"Chaijia Wopu",
    "gn:country_code":"CN",
    "gn:dem":20,
    "gn:feature_class":"P",
    "gn:feature_code":"PPL",
    "gn:name":"Chaijia Wopu",
    "gn:population":0,
    "gn:timezone":"Asia/Shanghai",
    "iso:country":"CN",
    "name:zho_x_preferred":[
        "\u67f4\u5bb6\u7a9d\u94fa"
    ],
    "wof:name":"Chaijia Wopu",
    "wof:placetype":"locality"
},
  "geometry": {"coordinates":[122.499,41.713],"type":"Point"}
}