{
  "type": "Feature",
  "properties": {
    "gn:admin1_code":"8.0",
    "gn:asciiname":"Fazhancun",
    "gn:country_code":"CN",
    "gn:dem":224,
    "gn:feature_class":"P",
    "gn:feature_code":"PPL",
    "gn:name":"Fazhancun",
    "gn:population":0,
    "gn:timezone":"Asia/Shanghai",
    "iso:country":"CN",
    "name:zho_x_preferred":[
        "\u53d1\u5c55\u6751"
    ],
    "wof:name":"Fazhancun",
    "wof:placetype":"locality"
},
  "geometry": {"coordinates":[125.92399,47.01229],"type":"Point"}
}