{
  "type": "Feature",
  "properties": {
    "gn:admin1_code":"3.0",
    "gn:asciiname":"Dongxiang",
    "gn:country_code":"CN",
    "gn:dem":389,
    "gn:feature_class":"P",
    "gn:feature_code":"PPL",
    "gn:name":"Dongxiang",
    "gn:population":0,
    "gn:timezone":"Asia/Shanghai",
    "iso:country":"CN",
    "name:deu_x_preferred":[
        "Dongxiang"
    ],
    "name:fra_x_preferred":[
        "Dongxiang"
    ],
    "name:nor_x_preferred":[
        "Dongxiang"
    ],
    "name:pol_x_preferred":[
        "Dongxiang"
    ],
    "name:und_x_variant":[
        "\u4e1c\u4e61"
    ],
    "name:vie_x_preferred":[
        "\u0110\u00f4ng H\u01b0\u01a1ng"
    ],
    "wof:name":"Dongxiang",
    "wof:placetype":"locality"
},
  "geometry": {"coordinates":[115.87796000000002,25.59583],"type":"Point"}
}