{
  "type": "Feature",
  "properties": {
    "gn:admin1_code":"12",
    "gn:asciiname":"Jianchi",
    "gn:country_code":"CN",
    "gn:dem":220,
    "gn:feature_class":"P",
    "gn:feature_code":"PPLA4",
    "gn:name":"Jianchi",
    "gn:population":0,
    "gn:timezone":"Asia/Shanghai",
    "iso:country":"CN",
    "name:und_x_variant":[
        "Jianchi Xiang"
    ],
    "name:zho_x_preferred":[
        "\u6da7\u6c60"
    ],
    "name:zho_x_variant":[
        "\u6da7\u6c60\u4e61"
    ],
    "wof:name":"Jianchi",
    "wof:placetype":"locality"
},
  "geometry": {"coordinates":[110.33113,32.87011],"type":"Point"}
}