{
  "type": "Feature",
  "properties": {
    "gn:admin1_code":"30.0",
    "gn:asciiname":"Guhucun",
    "gn:country_code":"CN",
    "gn:dem":16,
    "gn:feature_class":"P",
    "gn:feature_code":"PPL",
    "gn:name":"Guhucun",
    "gn:population":0,
    "gn:timezone":"Asia/Shanghai",
    "iso:country":"CN",
    "name:zho_x_preferred":[
        "\u53e4\u6e56\u6751"
    ],
    "wof:name":"Guhucun",
    "wof:placetype":"locality"
},
  "geometry": {"coordinates":[116.44262000000001,23.60336],"type":"Point"}
}