{
  "type": "Feature",
  "properties": {
    "gn:admin1_code":"2.0",
    "gn:asciiname":"Wuyuandu",
    "gn:country_code":"CN",
    "gn:dem":9,
    "gn:feature_class":"P",
    "gn:feature_code":"PPL",
    "gn:name":"Wuyuandu",
    "gn:population":0,
    "gn:timezone":"Asia/Shanghai",
    "iso:country":"CN",
    "name:und_x_variant":[
        "\u5348\u6e90\u6e21"
    ],
    "wof:name":"Wuyuandu",
    "wof:placetype":"locality"
},
  "geometry": {"coordinates":[119.88812,30.8738],"type":"Point"}
}