{
  "type": "Feature",
  "properties": {
    "gn:admin1_code":"24.0",
    "gn:asciiname":"Dongyingcun",
    "gn:country_code":"CN",
    "gn:dem":804,
    "gn:feature_class":"P",
    "gn:feature_code":"PPL",
    "gn:name":"Dongyingcun",
    "gn:population":0,
    "gn:timezone":"Asia/Shanghai",
    "iso:country":"CN",
    "name:zho_x_preferred":[
        "\u4e1c\u8425\u6751"
    ],
    "wof:name":"Dongyingcun",
    "wof:placetype":"locality"
},
  "geometry": {"coordinates":[112.76011,38.7389],"type":"Point"}
}