{
  "type": "Feature",
  "properties": {
    "gn:admin1_code":"20.0",
    "gn:asciiname":"Zhuoshanmaidian",
    "gn:country_code":"CN",
    "gn:dem":674,
    "gn:feature_class":"P",
    "gn:feature_code":"PPL",
    "gn:name":"Zhuoshanmaidian",
    "gn:population":0,
    "gn:timezone":"Asia/Shanghai",
    "iso:country":"CN",
    "name:zho_x_preferred":[
        "\u5353\u5c71\u9ea6\u70b9"
    ],
    "wof:name":"Zhuoshanmaidian",
    "wof:placetype":"locality"
},
  "geometry": {"coordinates":[121.01613,49.4285],"type":"Point"}
}