{
  "type": "Feature",
  "properties": {
    "gn:admin1_code":"1.0",
    "gn:asciiname":"Nanshuicun",
    "gn:country_code":"CN",
    "gn:dem":440,
    "gn:feature_class":"P",
    "gn:feature_code":"PPL",
    "gn:name":"Nanshuicun",
    "gn:population":0,
    "gn:timezone":"Asia/Shanghai",
    "iso:country":"CN",
    "name:zho_x_preferred":[
        "\u5357\u6c34\u6751"
    ],
    "wof:name":"Nanshuicun",
    "wof:placetype":"locality"
},
  "geometry": {"coordinates":[115.88169000000001,31.6176],"type":"Point"}
}