{
  "type": "Feature",
  "properties": {
    "gn:admin1_code":"32.0",
    "gn:asciiname":"Lancaogou",
    "gn:country_code":"CN",
    "gn:dem":894,
    "gn:feature_class":"P",
    "gn:feature_code":"PPL",
    "gn:name":"Lancaogou",
    "gn:population":0,
    "gn:timezone":"Asia/Shanghai",
    "iso:country":"CN",
    "name:zho_x_preferred":[
        "\u5170\u8349\u6c9f"
    ],
    "wof:name":"Lancaogou",
    "wof:placetype":"locality"
},
  "geometry": {"coordinates":[107.85063,30.80618],"type":"Point"}
}