{
  "type": "Feature",
  "properties": {
    "gn:admin1_code":"19.0",
    "gn:asciiname":"Jianshecun",
    "gn:country_code":"CN",
    "gn:dem":86,
    "gn:feature_class":"P",
    "gn:feature_code":"PPL",
    "gn:name":"Jianshecun",
    "gn:population":0,
    "gn:timezone":"Asia/Shanghai",
    "iso:country":"CN",
    "name:zho_x_preferred":[
        "\u5efa\u8bbe\u6751"
    ],
    "wof:name":"Jianshecun",
    "wof:placetype":"locality"
},
  "geometry": {"coordinates":[123.84878,42.63864],"type":"Point"}
}