{
  "type": "Feature",
  "properties": {
    "gn:admin1_code":"9.0",
    "gn:asciiname":"Lilaocun",
    "gn:country_code":"CN",
    "gn:dem":51,
    "gn:feature_class":"P",
    "gn:feature_code":"PPL",
    "gn:name":"Lilaocun",
    "gn:population":0,
    "gn:timezone":"Asia/Shanghai",
    "iso:country":"CN",
    "name:zho_x_preferred":[
        "\u674e\u8001\u6751"
    ],
    "wof:name":"Lilaocun",
    "wof:placetype":"locality"
},
  "geometry": {"coordinates":[114.68198999999998,33.56889],"type":"Point"}
}