{
  "type": "Feature",
  "properties": {
    "gn:admin1_code":"31",
    "gn:asciiname":"Shadi",
    "gn:country_code":"CN",
    "gn:dem":12,
    "gn:feature_class":"P",
    "gn:feature_code":"PPL",
    "gn:name":"Shadi",
    "gn:population":0,
    "gn:timezone":"Asia/Shanghai",
    "iso:country":"CN",
    "name:und_x_variant":[
        "Sha-ti",
        "Shadi",
        "\u6c99\u5730"
    ],
    "wof:name":"Shadi",
    "wof:placetype":"locality"
},
  "geometry": {"coordinates":[108.759,19.3722],"type":"Point"}
}