{
  "type": "Feature",
  "properties": {
    "gn:admin1_code":"29",
    "gn:asciiname":"Yezu",
    "gn:country_code":"CN",
    "gn:dem":1625,
    "gn:feature_class":"P",
    "gn:feature_code":"PPL",
    "gn:name":"Yezu",
    "gn:population":0,
    "gn:timezone":"Asia/Shanghai",
    "iso:country":"CN",
    "name:zho_x_preferred":[
        "\u4e1a\u79df"
    ],
    "wof:name":"Yezu",
    "wof:placetype":"locality"
},
  "geometry": {"coordinates":[102.663,23.5256],"type":"Point"}
}