{
  "type": "Feature",
  "properties": {
    "gn:admin1_code":"32.0",
    "gn:asciiname":"Dawuji",
    "gn:country_code":"CN",
    "gn:dem":543,
    "gn:feature_class":"P",
    "gn:feature_code":"PPL",
    "gn:name":"Dawuji",
    "gn:population":0,
    "gn:timezone":"Asia/Shanghai",
    "iso:country":"CN",
    "name:zho_x_preferred":[
        "\u5927\u5c4b\u57fa"
    ],
    "wof:name":"Dawuji",
    "wof:placetype":"locality"
},
  "geometry": {"coordinates":[105.441,28.5041],"type":"Point"}
}