{
  "type": "Feature",
  "properties": {
    "gn:admin1_code":"2.0",
    "gn:asciiname":"Huacheng",
    "gn:country_code":"CN",
    "gn:dem":180,
    "gn:feature_class":"P",
    "gn:feature_code":"PPL",
    "gn:name":"Huacheng",
    "gn:population":0,
    "gn:timezone":"Asia/Shanghai",
    "iso:country":"CN",
    "name:fas_x_preferred":[
        "\u0647\u0648\u0627\u0686\u0646\u06af"
    ],
    "name:und_x_variant":[
        "\u5316\u57ce"
    ],
    "name:zho_x_preferred":[
        "Huacheng"
    ],
    "name:zho_x_variant":[
        "\u534e\u57ce\u9547"
    ],
    "wof:name":"Huacheng",
    "wof:placetype":"locality"
},
  "geometry": {"coordinates":[119.80956,30.38988],"type":"Point"}
}