{
  "type": "Feature",
  "properties": {
    "gn:admin1_code":"11.0",
    "gn:asciiname":"Shanbianshang",
    "gn:country_code":"CN",
    "gn:dem":597,
    "gn:feature_class":"P",
    "gn:feature_code":"PPL",
    "gn:name":"Shanbianshang",
    "gn:population":0,
    "gn:timezone":"Asia/Shanghai",
    "iso:country":"CN",
    "name:zho_x_preferred":[
        "\u5c71\u8fb9\u4e0a"
    ],
    "wof:name":"Shanbianshang",
    "wof:placetype":"locality"
},
  "geometry": {"coordinates":[110.59737,27.48552],"type":"Point"}
}