{
  "type": "Feature",
  "properties": {
    "gn:admin1_code":"14",
    "gn:asciiname":"Log",
    "gn:country_code":"CN",
    "gn:dem":3997,
    "gn:feature_class":"P",
    "gn:feature_code":"PPL",
    "gn:name":"Log",
    "gn:population":0,
    "gn:timezone":"Asia/Urumqi",
    "iso:country":"CN",
    "name:bod_x_preferred":[
        "\u0f40\u0fb3\u0f7c\u0f42"
    ],
    "wof:name":"Log",
    "wof:placetype":"locality"
},
  "geometry": {"coordinates":[92.12783,28.97526],"type":"Point"}
}