{
  "type": "Feature",
  "properties": {
    "gn:admin1_code":"14",
    "gn:asciiname":"Log",
    "gn:country_code":"CN",
    "gn:dem":3997,
    "gn:feature_class":"P",
    "gn:feature_code":"PPL",
    "gn:name":"Log",
    "gn:population":0,
    "gn:timezone":"Asia/Urumqi",
    "iso:country":"CN",
    "name:ara_x_preferred":[
        "\u0633\u062c\u0644"
    ],
    "name:bod_x_preferred":[
        "\u0f40\u0fb3\u0f7c\u0f42"
    ],
    "name:bos_x_preferred":[
        "Log"
    ],
    "name:ceb_x_preferred":[
        "Log"
    ],
    "name:deu_x_preferred":[
        "Log"
    ],
    "name:fas_x_preferred":[
        "Log"
    ],
    "name:fra_x_preferred":[
        "Log"
    ],
    "name:heb_x_preferred":[
        "\u05dc\u05d5\u05d2"
    ],
    "name:hrv_x_preferred":[
        "Log"
    ],
    "name:kor_x_preferred":[
        "\ub85c\uadf8"
    ],
    "name:nld_x_preferred":[
        "Log"
    ],
    "name:nno_x_preferred":[
        "Log"
    ],
    "name:pol_x_preferred":[
        "Log"
    ],
    "name:por_x_preferred":[
        "Log"
    ],
    "name:rus_x_preferred":[
        "Log"
    ],
    "name:slv_x_preferred":[
        "Log"
    ],
    "name:spa_x_preferred":[
        "Log"
    ],
    "name:swe_x_preferred":[
        "Log"
    ],
    "name:ukr_x_preferred":[
        "Log"
    ],
    "name:urd_x_preferred":[
        "\u0646\u0648\u0634\u062a\u06c1"
    ],
    "name:zho_x_preferred":[
        "Log"
    ],
    "wof:name":"Log",
    "wof:placetype":"locality"
},
  "geometry": {"coordinates":[92.12783,28.97526],"type":"Point"}
}