{
  "type": "Feature",
  "properties": {
    "gn:admin1_code":"26",
    "gn:asciiname":"Gongshencun",
    "gn:country_code":"CN",
    "gn:dem":521,
    "gn:feature_class":"P",
    "gn:feature_code":"PPL",
    "gn:name":"Gongshencun",
    "gn:population":0,
    "gn:timezone":"Asia/Shanghai",
    "iso:country":"CN",
    "name:und_x_variant":[
        "Gongshen",
        "Gongshencun"
    ],
    "name:zho_x_preferred":[
        "\u529f\u795e"
    ],
    "name:zho_x_variant":[
        "\u529f\u795e\u6751"
    ],
    "wof:name":"Gongshencun",
    "wof:placetype":"locality"
},
  "geometry": {"coordinates":[108.48438,34.40298],"type":"Point"}
}