{
  "type": "Feature",
  "properties": {
    "gn:admin1_code":"11.0",
    "gn:asciiname":"Jiangtou",
    "gn:country_code":"CN",
    "gn:dem":502,
    "gn:feature_class":"P",
    "gn:feature_code":"PPL",
    "gn:name":"Jiangtou",
    "gn:population":0,
    "gn:timezone":"Asia/Shanghai",
    "iso:country":"CN",
    "name:zho_x_preferred":[
        "\u6c5f\u5934"
    ],
    "wof:name":"Jiangtou",
    "wof:placetype":"locality"
},
  "geometry": {"coordinates":[109.84208999999998,26.09888],"type":"Point"}
}