{
  "type": "Feature",
  "properties": {
    "gn:admin1_code":"3",
    "gn:asciiname":"Taihu",
    "gn:country_code":"CN",
    "gn:dem":224,
    "gn:feature_class":"P",
    "gn:feature_code":"PPL",
    "gn:name":"Taihu",
    "gn:population":0,
    "gn:timezone":"Asia/Shanghai",
    "iso:country":"CN",
    "name:zho_x_preferred":[
        "\u592a\u6e56"
    ],
    "wof:name":"Taihu",
    "wof:placetype":"locality"
},
  "geometry": {"coordinates":[114.32599999999999,26.7021],"type":"Point"}
}