{
  "type": "Feature",
  "properties": {
    "gn:admin1_code":"14.0",
    "gn:asciiname":"Dangpian",
    "gn:country_code":"CN",
    "gn:dem":4005,
    "gn:feature_class":"P",
    "gn:feature_code":"PPL",
    "gn:name":"Dangpian",
    "gn:population":0,
    "gn:timezone":"Asia/Urumqi",
    "iso:country":"CN",
    "name:zho_x_preferred":[
        "\u5f53\u7247"
    ],
    "wof:name":"Dangpian",
    "wof:placetype":"locality"
},
  "geometry": {"coordinates":[94.77132,30.95573],"type":"Point"}
}