{
  "type": "Feature",
  "properties": {
    "gn:admin1_code":"16.0",
    "gn:asciiname":"Tingshe",
    "gn:country_code":"CN",
    "gn:dem":51,
    "gn:feature_class":"P",
    "gn:feature_code":"PPL",
    "gn:name":"Tingshe",
    "gn:population":0,
    "gn:timezone":"Asia/Shanghai",
    "iso:country":"CN",
    "name:zho_x_preferred":[
        "\u505c\u793e"
    ],
    "wof:name":"Tingshe",
    "wof:placetype":"locality"
},
  "geometry": {"coordinates":[109.453,23.0481],"type":"Point"}
}