{
  "type": "Feature",
  "properties": {
    "gn:admin1_code":"12.0",
    "gn:asciiname":"Gou'ertan",
    "gn:country_code":"CN",
    "gn:dem":441,
    "gn:feature_class":"P",
    "gn:feature_code":"PPL",
    "gn:name":"Gou\u2019ertan",
    "gn:population":0,
    "gn:timezone":"Asia/Shanghai",
    "iso:country":"CN",
    "name:und_x_variant":[
        "Gou\u2019ertan"
    ],
    "name:zho_x_preferred":[
        "\u6c9f\u4e8c\u6ee9"
    ],
    "wof:name":"Gou'ertan",
    "wof:placetype":"locality"
},
  "geometry": {"coordinates":[110.77395,31.40995],"type":"Point"}
}