{
  "type": "Feature",
  "properties": {
    "gn:admin1_code":"10",
    "gn:asciiname":"Yihecheng",
    "gn:country_code":"CN",
    "gn:dem":1437,
    "gn:feature_class":"P",
    "gn:feature_code":"PPL",
    "gn:name":"Yihecheng",
    "gn:population":0,
    "gn:timezone":"Asia/Shanghai",
    "iso:country":"CN",
    "name:zho_x_preferred":[
        "\u4e49\u5408\u6210"
    ],
    "wof:name":"Yihecheng",
    "wof:placetype":"locality"
},
  "geometry": {"coordinates":[115.71946,41.56981],"type":"Point"}
}