{
  "type": "Feature",
  "properties": {
    "gn:admin1_code":"19.0",
    "gn:asciiname":"Hengluzicun",
    "gn:country_code":"CN",
    "gn:dem":35,
    "gn:feature_class":"P",
    "gn:feature_code":"PPL",
    "gn:name":"Hengluzicun",
    "gn:population":0,
    "gn:timezone":"Asia/Shanghai",
    "iso:country":"CN",
    "name:zho_x_preferred":[
        "\u6a2a\u8def\u5b50\u6751"
    ],
    "wof:name":"Hengluzicun",
    "wof:placetype":"locality"
},
  "geometry": {"coordinates":[123.143,42.0142],"type":"Point"}
}