{
  "type": "Feature",
  "properties": {
    "gn:admin1_code":"11.0",
    "gn:asciiname":"Xixia",
    "gn:country_code":"CN",
    "gn:dem":837,
    "gn:feature_class":"P",
    "gn:feature_code":"PPL",
    "gn:name":"Xixia",
    "gn:population":0,
    "gn:timezone":"Asia/Shanghai",
    "iso:country":"CN",
    "name:zho_x_preferred":[
        "\u6eaa\u4e0b"
    ],
    "wof:name":"Xixia",
    "wof:placetype":"locality"
},
  "geometry": {"coordinates":[113.79443999999999,25.86521],"type":"Point"}
}