{
  "type": "Feature",
  "properties": {
    "gn:admin1_code":"12.0",
    "gn:asciiname":"Lianjiagang",
    "gn:country_code":"CN",
    "gn:dem":48,
    "gn:feature_class":"P",
    "gn:feature_code":"PPL",
    "gn:name":"Lianjiagang",
    "gn:population":0,
    "gn:timezone":"Asia/Shanghai",
    "iso:country":"CN",
    "name:und_x_variant":[
        "\u8fde\u5bb6\u5c97"
    ],
    "wof:name":"Lianjiagang",
    "wof:placetype":"locality"
},
  "geometry": {"coordinates":[114.24638,30.85956],"type":"Point"}
}