{
  "type": "Feature",
  "properties": {
    "gn:admin1_code":"11.0",
    "gn:asciiname":"Gaoqiaowan",
    "gn:country_code":"CN",
    "gn:dem":63,
    "gn:feature_class":"P",
    "gn:feature_code":"PPL",
    "gn:name":"Gaoqiaowan",
    "gn:population":0,
    "gn:timezone":"Asia/Shanghai",
    "iso:country":"CN",
    "name:zho_x_preferred":[
        "\u9ad8\u6865\u6e7e"
    ],
    "wof:name":"Gaoqiaowan",
    "wof:placetype":"locality"
},
  "geometry": {"coordinates":[113.30401999999999,27.97443],"type":"Point"}
}