{
  "type": "Feature",
  "properties": {
    "gn:admin1_code":"10",
    "gn:asciiname":"Nanshanwan",
    "gn:country_code":"CN",
    "gn:dem":681,
    "gn:feature_class":"P",
    "gn:feature_code":"PPL",
    "gn:name":"Nanshanwan",
    "gn:population":0,
    "gn:timezone":"Asia/Shanghai",
    "iso:country":"CN",
    "name:zho_x_preferred":[
        "\u5357\u5c71\u6e7e"
    ],
    "wof:name":"Nanshanwan",
    "wof:placetype":"locality"
},
  "geometry": {"coordinates":[116.65628,41.19175],"type":"Point"}
}