{
  "type": "Feature",
  "properties": {
    "gn:admin1_code":"14.0",
    "gn:asciiname":"Buyu",
    "gn:country_code":"CN",
    "gn:dem":3724,
    "gn:feature_class":"P",
    "gn:feature_code":"PPL",
    "gn:name":"Buyu",
    "gn:population":0,
    "gn:timezone":"Asia/Urumqi",
    "iso:country":"CN",
    "name:bod_x_preferred":[
        "Boy\u00fc"
    ],
    "name:zho_x_preferred":[
        "Buyu"
    ],
    "name:zho_x_variant":[
        "\u5e03\u7389"
    ],
    "wof:name":"Buyu",
    "wof:placetype":"locality"
},
  "geometry": {"coordinates":[97.18647,29.15429],"type":"Point"}
}