{
  "type": "Feature",
  "properties": {
    "gn:admin1_code":"11.0",
    "gn:asciiname":"Wantouwu",
    "gn:country_code":"CN",
    "gn:dem":97,
    "gn:feature_class":"P",
    "gn:feature_code":"PPL",
    "gn:name":"Wantouwu",
    "gn:population":0,
    "gn:timezone":"Asia/Shanghai",
    "iso:country":"CN",
    "name:zho_x_preferred":[
        "\u6e7e\u5934\u5c4b"
    ],
    "wof:name":"Wantouwu",
    "wof:placetype":"locality"
},
  "geometry": {"coordinates":[113.43414,29.01956],"type":"Point"}
}