{
  "type": "Feature",
  "properties": {
    "gn:admin1_code":"32.0",
    "gn:asciiname":"Jiangjiajie",
    "gn:country_code":"CN",
    "gn:dem":331,
    "gn:feature_class":"P",
    "gn:feature_code":"PPL",
    "gn:name":"Jiangjiajie",
    "gn:population":0,
    "gn:timezone":"Asia/Shanghai",
    "iso:country":"CN",
    "name:zho_x_preferred":[
        "\u848b\u5bb6\u8857"
    ],
    "wof:name":"Jiangjiajie",
    "wof:placetype":"locality"
},
  "geometry": {"coordinates":[105.27324,29.54058],"type":"Point"}
}