{
  "type": "Feature",
  "properties": {
    "gn:admin1_code":"11.0",
    "gn:asciiname":"Xinwu'ao",
    "gn:country_code":"CN",
    "gn:dem":291,
    "gn:feature_class":"P",
    "gn:feature_code":"PPL",
    "gn:name":"Xinwu\u2019ao",
    "gn:population":0,
    "gn:timezone":"Asia/Shanghai",
    "iso:country":"CN",
    "name:und_x_variant":[
        "Xinwu\u2019ao"
    ],
    "name:zho_x_preferred":[
        "\u65b0\u5c4b\u5773"
    ],
    "wof:name":"Xinwu'ao",
    "wof:placetype":"locality"
},
  "geometry": {"coordinates":[111.77585999999999,27.04134],"type":"Point"}
}