{
  "type": "Feature",
  "properties": {
    "gn:admin1_code":"11",
    "gn:asciiname":"Anshun",
    "gn:country_code":"CN",
    "gn:dem":820,
    "gn:feature_class":"P",
    "gn:feature_code":"PPL",
    "gn:name":"Anshun",
    "gn:population":0,
    "gn:timezone":"Asia/Shanghai",
    "iso:country":"CN",
    "name:ara_x_preferred":[
        "\u0623\u0646\u0634\u0648\u0646"
    ],
    "name:cdo_x_preferred":[
        "\u0102ng-s\u00f4ng"
    ],
    "name:ceb_x_preferred":[
        "Anshun"
    ],
    "name:ces_x_preferred":[
        "An-\u0161un"
    ],
    "name:cym_x_preferred":[
        "Anshun"
    ],
    "name:dan_x_preferred":[
        "Anshun"
    ],
    "name:deu_x_preferred":[
        "Anshun"
    ],
    "name:eus_x_preferred":[
        "Anshun"
    ],
    "name:fas_x_preferred":[
        "\u0627\u0646\u0634\u0648\u0646"
    ],
    "name:fin_x_preferred":[
        "Anshun"
    ],
    "name:fra_x_preferred":[
        "Anshun"
    ],
    "name:heb_x_preferred":[
        "\u05d0\u05e0\u05e9\u05d5\u05df"
    ],
    "name:hun_x_preferred":[
        "Anshun"
    ],
    "name:ita_x_preferred":[
        "Anshun"
    ],
    "name:jpn_x_preferred":[
        "\u5b89\u9806\u5e02"
    ],
    "name:kik_x_preferred":[
        "Anshun"
    ],
    "name:kor_x_preferred":[
        "\uc548\uc21c\uc2dc"
    ],
    "name:lit_x_preferred":[
        "An\u0161unas"
    ],
    "name:mlg_x_preferred":[
        "Anshun"
    ],
    "name:nld_x_preferred":[
        "Anshun"
    ],
    "name:nno_x_preferred":[
        "Anshun"
    ],
    "name:nor_x_preferred":[
        "Anshun"
    ],
    "name:pam_x_preferred":[
        "Anshun"
    ],
    "name:pnb_x_preferred":[
        "\u0627\u0646\u0634\u0648\u0646"
    ],
    "name:pol_x_preferred":[
        "Anshun"
    ],
    "name:por_x_preferred":[
        "Anshun"
    ],
    "name:rus_x_preferred":[
        "\u0410\u043d\u044c\u0448\u0443\u043d\u044c"
    ],
    "name:spa_x_preferred":[
        "Anshun"
    ],
    "name:srp_x_preferred":[
        "\u0410\u043d\u0448\u0443\u043d"
    ],
    "name:swe_x_preferred":[
        "Anshun"
    ],
    "name:tur_x_preferred":[
        "Anshun"
    ],
    "name:ukr_x_preferred":[
        "\u0410\u043d\u044c\u0448\u0443\u043d\u044c"
    ],
    "name:urd_x_preferred":[
        "\u0627\u0646\u0634\u0648\u0646"
    ],
    "name:vie_x_preferred":[
        "An Thu\u1eadn"
    ],
    "name:war_x_preferred":[
        "Anshun"
    ],
    "name:zho_x_preferred":[
        "\u5b89\u987a\u5e02"
    ],
    "wof:name":"Anshun",
    "wof:placetype":"locality"
},
  "geometry": {"coordinates":[110.16333,27.04028],"type":"Point"}
}