{
  "type": "Feature",
  "properties": {
    "gn:admin1_code":"3.0",
    "gn:asciiname":"Bei'an",
    "gn:country_code":"CN",
    "gn:dem":71,
    "gn:feature_class":"P",
    "gn:feature_code":"PPL",
    "gn:name":"Bei\u2019an",
    "gn:population":0,
    "gn:timezone":"Asia/Shanghai",
    "iso:country":"CN",
    "name:und_x_variant":[
        "Bei\u2019an",
        "\u5317\u5cb8"
    ],
    "wof:name":"Bei'an",
    "wof:placetype":"locality"
},
  "geometry": {"coordinates":[114.6651,28.28212000000001],"type":"Point"}
}