{
  "type": "Feature",
  "properties": {
    "gn:admin1_code":"8.0",
    "gn:asciiname":"Baixitun",
    "gn:country_code":"CN",
    "gn:dem":182,
    "gn:feature_class":"P",
    "gn:feature_code":"PPL",
    "gn:name":"Baixitun",
    "gn:population":0,
    "gn:timezone":"Asia/Shanghai",
    "iso:country":"CN",
    "name:zho_x_preferred":[
        "\u767d\u559c\u5c6f"
    ],
    "wof:name":"Baixitun",
    "wof:placetype":"locality"
},
  "geometry": {"coordinates":[125.53738,46.12503],"type":"Point"}
}