{
  "type": "Feature",
  "properties": {
    "gn:admin1_code":"3.0",
    "gn:asciiname":"Dakengtou",
    "gn:country_code":"CN",
    "gn:dem":441,
    "gn:feature_class":"P",
    "gn:feature_code":"PPL",
    "gn:name":"Dakengtou",
    "gn:population":0,
    "gn:timezone":"Asia/Shanghai",
    "iso:country":"CN",
    "name:und_x_variant":[
        "\u5927\u5751\u5934"
    ],
    "wof:name":"Dakengtou",
    "wof:placetype":"locality"
},
  "geometry": {"coordinates":[115.7443,25.69229],"type":"Point"}
}