{
  "type": "Feature",
  "properties": {
    "gn:admin1_code":"16.0",
    "gn:asciiname":"Moushan",
    "gn:country_code":"CN",
    "gn:dem":627,
    "gn:feature_class":"P",
    "gn:feature_code":"PPL",
    "gn:name":"Moushan",
    "gn:population":0,
    "gn:timezone":"Asia/Shanghai",
    "iso:country":"CN",
    "name:zho_x_preferred":[
        "\u8c0b\u5c71"
    ],
    "wof:name":"Moushan",
    "wof:placetype":"locality"
},
  "geometry": {"coordinates":[108.53,25.0526],"type":"Point"}
}