{
  "type": "Feature",
  "properties": {
    "gn:admin1_code":"15.0",
    "gn:asciiname":"Weijiaping",
    "gn:country_code":"CN",
    "gn:dem":1971,
    "gn:feature_class":"P",
    "gn:feature_code":"PPL",
    "gn:name":"Weijiaping",
    "gn:population":0,
    "gn:timezone":"Asia/Shanghai",
    "iso:country":"CN",
    "name:zho_x_preferred":[
        "\u9b4f\u5bb6\u576a"
    ],
    "wof:name":"Weijiaping",
    "wof:placetype":"locality"
},
  "geometry": {"coordinates":[103.093,35.6991],"type":"Point"}
}