{
  "type": "Feature",
  "properties": {
    "gn:admin1_code":"29.0",
    "gn:asciiname":"Achao",
    "gn:country_code":"CN",
    "gn:dem":2064,
    "gn:feature_class":"P",
    "gn:feature_code":"PPL",
    "gn:name":"Achao",
    "gn:population":0,
    "gn:timezone":"Asia/Shanghai",
    "iso:country":"CN",
    "name:fas_x_preferred":[
        "\u0627\u0686\u0627\u0626\u0648"
    ],
    "name:spa_x_preferred":[
        "Achao"
    ],
    "name:zho_x_preferred":[
        "\u963f\u671d"
    ],
    "wof:name":"Achao",
    "wof:placetype":"locality"
},
  "geometry": {"coordinates":[103.751,24.3645],"type":"Point"}
}