{
  "type": "Feature",
  "properties": {
    "gn:admin1_code":"15.0",
    "gn:asciiname":"Haozhang",
    "gn:country_code":"CN",
    "gn:dem":1576,
    "gn:feature_class":"P",
    "gn:feature_code":"PPL",
    "gn:name":"Haozhang",
    "gn:population":0,
    "gn:timezone":"Asia/Shanghai",
    "iso:country":"CN",
    "name:und_x_variant":[
        "\u90dd\u638c"
    ],
    "wof:name":"Haozhang",
    "wof:placetype":"locality"
},
  "geometry": {"coordinates":[106.94492,36.98221],"type":"Point"}
}