{
  "type": "Feature",
  "properties": {
    "gn:admin1_code":"26.0",
    "gn:asciiname":"Huyancun",
    "gn:country_code":"CN",
    "gn:dem":886,
    "gn:feature_class":"P",
    "gn:feature_code":"PPL",
    "gn:name":"Huyancun",
    "gn:population":0,
    "gn:timezone":"Asia/Shanghai",
    "iso:country":"CN",
    "name:zho_x_preferred":[
        "\u547c\u5ef6\u6751"
    ],
    "wof:name":"Huyancun",
    "wof:placetype":"locality"
},
  "geometry": {"coordinates":[110.43008,36.53565],"type":"Point"}
}