{
  "type": "Feature",
  "properties": {
    "gn:admin1_code":"26.0",
    "gn:asciiname":"Zhoujiazhaicun",
    "gn:country_code":"CN",
    "gn:dem":404,
    "gn:feature_class":"P",
    "gn:feature_code":"PPL",
    "gn:name":"Zhoujiazhaicun",
    "gn:population":0,
    "gn:timezone":"Asia/Shanghai",
    "iso:country":"CN",
    "name:zho_x_preferred":[
        "\u5468\u5bb6\u5be8\u6751"
    ],
    "wof:name":"Zhoujiazhaicun",
    "wof:placetype":"locality"
},
  "geometry": {"coordinates":[108.81949,34.21945],"type":"Point"}
}