{
  "type": "Feature",
  "properties": {
    "gn:admin1_code":"32.0",
    "gn:asciiname":"Shuwan",
    "gn:country_code":"CN",
    "gn:dem":362,
    "gn:feature_class":"P",
    "gn:feature_code":"PPL",
    "gn:name":"Shuwan",
    "gn:population":0,
    "gn:timezone":"Asia/Shanghai",
    "iso:country":"CN",
    "name:zho_x_preferred":[
        "\u4e66\u6e7e"
    ],
    "wof:name":"Shuwan",
    "wof:placetype":"locality"
},
  "geometry": {"coordinates":[106.935,31.0569],"type":"Point"}
}