{
  "type": "Feature",
  "properties": {
    "gn:admin1_code":"7",
    "gn:asciiname":"Qiantang",
    "gn:country_code":"CN",
    "gn:dem":28,
    "gn:feature_class":"P",
    "gn:feature_code":"PPL",
    "gn:name":"Qiantang",
    "gn:population":0,
    "gn:timezone":"Asia/Shanghai",
    "iso:country":"CN",
    "name:und_x_variant":[
        "Ch\u2019ien-t\u2019ang",
        "Qiantang"
    ],
    "name:zho_x_preferred":[
        "\u524d\u5858"
    ],
    "wof:name":"Qiantang",
    "wof:placetype":"locality"
},
  "geometry": {"coordinates":[119.49421,25.86845],"type":"Point"}
}