{
  "type": "Feature",
  "properties": {
    "gn:admin1_code":"14.0",
    "gn:asciiname":"Zhamujia",
    "gn:country_code":"CN",
    "gn:dem":4548,
    "gn:feature_class":"P",
    "gn:feature_code":"PPL",
    "gn:name":"Zhamujia",
    "gn:population":0,
    "gn:timezone":"Asia/Urumqi",
    "iso:country":"CN",
    "name:zho_x_preferred":[
        "\u624e\u6728\u5bb6"
    ],
    "wof:name":"Zhamujia",
    "wof:placetype":"locality"
},
  "geometry": {"coordinates":[87.7608,28.9029],"type":"Point"}
}