{
  "type": "Feature",
  "properties": {
    "gn:admin1_code":"30.0",
    "gn:asciiname":"Shuikou'ao",
    "gn:country_code":"CN",
    "gn:dem":378,
    "gn:feature_class":"P",
    "gn:feature_code":"PPL",
    "gn:name":"Shuikou\u2019ao",
    "gn:population":0,
    "gn:timezone":"Asia/Urumqi",
    "iso:country":"CN",
    "name:zho_x_preferred":[
        "\u6c34\u53e3\u51f9"
    ],
    "name:zho_x_variant":[
        "Shuikou\u2019ao"
    ],
    "wof:name":"Shuikou'ao",
    "wof:placetype":"locality"
},
  "geometry": {"coordinates":[111.41611,22.40555],"type":"Point"}
}