{
  "type": "Feature",
  "properties": {
    "gn:admin1_code":"4.0",
    "gn:asciiname":"Sanwang",
    "gn:country_code":"CN",
    "gn:dem":3,
    "gn:feature_class":"P",
    "gn:feature_code":"PPL",
    "gn:name":"Sanwang",
    "gn:population":0,
    "gn:timezone":"Asia/Shanghai",
    "iso:country":"CN",
    "name:zho_x_preferred":[
        "Sanwang"
    ],
    "name:zho_x_variant":[
        "\u4e09\u65fa"
    ],
    "wof:name":"Sanwang",
    "wof:placetype":"locality"
},
  "geometry": {"coordinates":[119.94681,33.35334],"type":"Point"}
}