{
  "type": "Feature",
  "properties": {
    "gn:admin1_code":"32.0",
    "gn:asciiname":"Qingbaoguan",
    "gn:country_code":"CN",
    "gn:dem":656,
    "gn:feature_class":"P",
    "gn:feature_code":"PPL",
    "gn:name":"Qingbaoguan",
    "gn:population":0,
    "gn:timezone":"Asia/Shanghai",
    "iso:country":"CN",
    "name:zho_x_preferred":[
        "\u6e05\u4fdd\u89c2"
    ],
    "name:zho_x_variant":[
        "\u9752\u5b9d\u89c2"
    ],
    "wof:name":"Qingbaoguan",
    "wof:placetype":"locality"
},
  "geometry": {"coordinates":[106.76300000000001,32.1825],"type":"Point"}
}