{
  "type": "Feature",
  "properties": {
    "gn:admin1_code":"30.0",
    "gn:asciiname":"Louxia",
    "gn:country_code":"CN",
    "gn:dem":106,
    "gn:feature_class":"P",
    "gn:feature_code":"PPL",
    "gn:name":"Louxia",
    "gn:population":0,
    "gn:timezone":"Asia/Shanghai",
    "iso:country":"CN",
    "name:zho_x_preferred":[
        "Louxia"
    ],
    "name:zho_x_variant":[
        "\u697c\u4e0b"
    ],
    "wof:name":"Louxia",
    "wof:placetype":"locality"
},
  "geometry": {"coordinates":[113.45305999999999,25.1225],"type":"Point"}
}