{
  "type": "Feature",
  "properties": {
    "gn:admin1_code":"20",
    "gn:asciiname":"Shi'erzhan Linchang",
    "gn:country_code":"CN",
    "gn:dem":375,
    "gn:feature_class":"P",
    "gn:feature_code":"PPLF",
    "gn:name":"Shi\u2019erzhan Linchang",
    "gn:population":0,
    "gn:timezone":"Asia/Shanghai",
    "iso:country":"CN",
    "name:zho_x_preferred":[
        "Shi\u2019erzhan Linchang"
    ],
    "wof:name":"Shi'erzhan Linchang",
    "wof:placetype":"locality"
},
  "geometry": {"coordinates":[125.74028,51.23472],"type":"Point"}
}