{
  "type": "Feature",
  "properties": {
    "gn:admin1_code":"7.0",
    "gn:asciiname":"Fengcuocun",
    "gn:country_code":"CN",
    "gn:dem":572,
    "gn:feature_class":"P",
    "gn:feature_code":"PPL",
    "gn:name":"Fengcuocun",
    "gn:population":0,
    "gn:timezone":"Asia/Shanghai",
    "iso:country":"CN",
    "name:und_x_variant":[
        "\u51af\u539d\u6751"
    ],
    "name:zho_x_preferred":[
        "\u51af\u539d\u6751"
    ],
    "wof:name":"Fengcuocun",
    "wof:placetype":"locality"
},
  "geometry": {"coordinates":[117.17869,26.26287],"type":"Point"}
}