{
  "type": "Feature",
  "properties": {
    "gn:admin1_code":"3",
    "gn:asciiname":"Matoushang",
    "gn:country_code":"CN",
    "gn:dem":137,
    "gn:feature_class":"P",
    "gn:feature_code":"PPL",
    "gn:name":"Matoushang",
    "gn:population":0,
    "gn:timezone":"Asia/Shanghai",
    "iso:country":"CN",
    "name:zho_x_preferred":[
        "\u7801\u5934\u4e0a"
    ],
    "wof:name":"Matoushang",
    "wof:placetype":"locality"
},
  "geometry": {"coordinates":[114.166,26.9672],"type":"Point"}
}