{
  "type": "Feature",
  "properties": {
    "gn:admin1_code":"16.0",
    "gn:asciiname":"Haochong",
    "gn:country_code":"CN",
    "gn:dem":130,
    "gn:feature_class":"P",
    "gn:feature_code":"PPL",
    "gn:name":"Haochong",
    "gn:population":0,
    "gn:timezone":"Asia/Shanghai",
    "iso:country":"CN",
    "name:zho_x_preferred":[
        "\u597d\u51b2"
    ],
    "wof:name":"Haochong",
    "wof:placetype":"locality"
},
  "geometry": {"coordinates":[110.60299999999999,22.6877],"type":"Point"}
}