{
  "type": "Feature",
  "properties": {
    "gn:admin1_code":"1.0",
    "gn:asciiname":"Xishagengcun",
    "gn:country_code":"CN",
    "gn:dem":118,
    "gn:feature_class":"P",
    "gn:feature_code":"PPL",
    "gn:name":"Xishagengcun",
    "gn:population":0,
    "gn:timezone":"Asia/Shanghai",
    "iso:country":"CN",
    "name:zho_x_preferred":[
        "\u897f\u6c99\u57c2\u6751"
    ],
    "wof:name":"Xishagengcun",
    "wof:placetype":"locality"
},
  "geometry": {"coordinates":[116.84253,31.22528],"type":"Point"}
}