{
  "type": "Feature",
  "properties": {
    "gn:admin1_code":"3.0",
    "gn:asciiname":"Shaojiwo",
    "gn:country_code":"CN",
    "gn:dem":268,
    "gn:feature_class":"P",
    "gn:feature_code":"PPL",
    "gn:name":"Shaojiwo",
    "gn:population":0,
    "gn:timezone":"Asia/Shanghai",
    "iso:country":"CN",
    "name:und_x_variant":[
        "\u7b72\u7b95\u7a9d"
    ],
    "wof:name":"Shaojiwo",
    "wof:placetype":"locality"
},
  "geometry": {"coordinates":[115.7191,26.43748],"type":"Point"}
}