{
  "type": "Feature",
  "properties": {
    "gn:admin1_code":"33.0",
    "gn:asciiname":"Li'er",
    "gn:country_code":"CN",
    "gn:dem":1142,
    "gn:feature_class":"P",
    "gn:feature_code":"PPL",
    "gn:name":"Li\u2019er",
    "gn:population":0,
    "gn:timezone":"Asia/Shanghai",
    "iso:country":"CN",
    "name:und_x_variant":[
        "Li\u2019er"
    ],
    "name:zho_x_preferred":[
        "\u68a8\u8033"
    ],
    "wof:name":"Li'er",
    "wof:placetype":"locality"
},
  "geometry": {"coordinates":[108.94798,29.18494],"type":"Point"}
}