{
  "type": "Feature",
  "properties": {
    "gn:admin1_code":"19.0",
    "gn:asciiname":"Huanggou",
    "gn:country_code":"CN",
    "gn:dem":373,
    "gn:feature_class":"P",
    "gn:feature_code":"PPL",
    "gn:name":"Huanggou",
    "gn:population":0,
    "gn:timezone":"Asia/Shanghai",
    "iso:country":"CN",
    "name:zho_x_preferred":[
        "\u8352\u6c9f"
    ],
    "wof:name":"Huanggou",
    "wof:placetype":"locality"
},
  "geometry": {"coordinates":[124.06977999999999,41.18887],"type":"Point"}
}