{
  "type": "Feature",
  "properties": {
    "gn:admin1_code":"9.0",
    "gn:asciiname":"Niuwangcha",
    "gn:country_code":"CN",
    "gn:dem":1236,
    "gn:feature_class":"P",
    "gn:feature_code":"PPL",
    "gn:name":"Niuwangcha",
    "gn:population":0,
    "gn:timezone":"Asia/Shanghai",
    "iso:country":"CN",
    "name:zho_x_preferred":[
        "\u725b\u65fa\u5c94"
    ],
    "wof:name":"Niuwangcha",
    "wof:placetype":"locality"
},
  "geometry": {"coordinates":[110.71727,34.17775],"type":"Point"}
}