{
  "type": "Feature",
  "properties": {
    "gn:admin1_code":"32.0",
    "gn:asciiname":"Chahualin",
    "gn:country_code":"CN",
    "gn:dem":2821,
    "gn:feature_class":"P",
    "gn:feature_code":"PPL",
    "gn:name":"Chahualin",
    "gn:population":0,
    "gn:timezone":"Asia/Shanghai",
    "iso:country":"CN",
    "name:zho_x_preferred":[
        "\u8336\u82b1\u6797"
    ],
    "wof:name":"Chahualin",
    "wof:placetype":"locality"
},
  "geometry": {"coordinates":[101.136,29.1305],"type":"Point"}
}