{
  "type": "Feature",
  "properties": {
    "gn:admin1_code":"30.0",
    "gn:asciiname":"Zengpeng",
    "gn:country_code":"CN",
    "gn:dem":-2,
    "gn:feature_class":"P",
    "gn:feature_code":"PPL",
    "gn:name":"Zengpeng",
    "gn:population":0,
    "gn:timezone":"Asia/Shanghai",
    "iso:country":"CN",
    "name:zho_x_preferred":[
        "\u7e52\u68da"
    ],
    "wof:name":"Zengpeng",
    "wof:placetype":"locality"
},
  "geometry": {"coordinates":[112.99424,22.44426],"type":"Point"}
}