{
  "type": "Feature",
  "properties": {
    "gn:admin1_code":"24.0",
    "gn:asciiname":"Nankoucun",
    "gn:country_code":"CN",
    "gn:dem":1135,
    "gn:feature_class":"P",
    "gn:feature_code":"PPL",
    "gn:name":"Nankoucun",
    "gn:population":0,
    "gn:timezone":"Asia/Shanghai",
    "iso:country":"CN",
    "name:und_x_variant":[
        "\u5357\u53e3\u6751"
    ],
    "name:zho_x_preferred":[
        "\u5357\u53e3\u6751"
    ],
    "wof:name":"Nankoucun",
    "wof:placetype":"locality"
},
  "geometry": {"coordinates":[112.88491999999999,39.13152],"type":"Point"}
}