{
  "type": "Feature",
  "properties": {
    "gn:admin1_code":"13.0",
    "gn:asciiname":"Kuruke Yilaike",
    "gn:country_code":"CN",
    "gn:dem":3257,
    "gn:feature_class":"P",
    "gn:feature_code":"PPL",
    "gn:name":"Kuruke Yilaike",
    "gn:population":0,
    "gn:timezone":"Asia/Shanghai",
    "iso:country":"CN",
    "name:zho_x_preferred":[
        "\u5e93\u5982\u514b\u4f9d\u6765\u514b"
    ],
    "wof:name":"Kuruke Yilaike",
    "wof:placetype":"locality"
},
  "geometry": {"coordinates":[80.50461999999997,36.06855],"type":"Point"}
}