{
  "type": "Feature",
  "properties": {
    "gn:admin1_code":"2.0",
    "gn:asciiname":"Louqi",
    "gn:country_code":"CN",
    "gn:dem":538,
    "gn:feature_class":"P",
    "gn:feature_code":"PPL",
    "gn:name":"Louqi",
    "gn:population":0,
    "gn:timezone":"Asia/Shanghai",
    "iso:country":"CN",
    "name:zho_x_preferred":[
        "\u697c\u65d7"
    ],
    "wof:name":"Louqi",
    "wof:placetype":"locality"
},
  "geometry": {"coordinates":[119.71283,27.57855],"type":"Point"}
}