{
  "type": "Feature",
  "properties": {
    "gn:admin1_code":"10",
    "gn:asciiname":"Cuijiazhuang",
    "gn:country_code":"CN",
    "gn:dem":120,
    "gn:feature_class":"P",
    "gn:feature_code":"PPL",
    "gn:name":"Cuijiazhuang",
    "gn:population":0,
    "gn:timezone":"Asia/Shanghai",
    "iso:country":"CN",
    "name:und_x_variant":[
        "\u5d14\u5bb6\u5e84"
    ],
    "wof:name":"Cuijiazhuang",
    "wof:placetype":"locality"
},
  "geometry": {"coordinates":[114.62287000000001,38.5938],"type":"Point"}
}