{
  "type": "Feature",
  "properties": {
    "gn:admin1_code":"18",
    "gn:asciiname":"Tianjia Yakou",
    "gn:country_code":"CN",
    "gn:dem":1162,
    "gn:feature_class":"P",
    "gn:feature_code":"PPL",
    "gn:name":"Tianjia Yakou",
    "gn:population":0,
    "gn:timezone":"Asia/Shanghai",
    "iso:country":"CN",
    "name:zho_x_preferred":[
        "\u7530\u5bb6\u57ad\u53e3"
    ],
    "wof:name":"Tianjia Yakou",
    "wof:placetype":"locality"
},
  "geometry": {"coordinates":[107.01600000000001,27.911],"type":"Point"}
}