{
  "type": "Feature",
  "properties": {
    "gn:admin1_code":"4.0",
    "gn:asciiname":"Dongyetian",
    "gn:country_code":"CN",
    "gn:dem":7,
    "gn:feature_class":"P",
    "gn:feature_code":"PPL",
    "gn:name":"Dongyetian",
    "gn:population":0,
    "gn:timezone":"Asia/Shanghai",
    "iso:country":"CN",
    "name:zho_x_preferred":[
        "\u4e1c\u91ce\u7530"
    ],
    "wof:name":"Dongyetian",
    "wof:placetype":"locality"
},
  "geometry": {"coordinates":[119.96856,32.30189],"type":"Point"}
}