{
  "type": "Feature",
  "properties": {
    "gn:admin1_code":"2.0",
    "gn:asciiname":"Lilan",
    "gn:country_code":"CN",
    "gn:dem":260,
    "gn:feature_class":"P",
    "gn:feature_code":"PPL",
    "gn:name":"Lilan",
    "gn:population":0,
    "gn:timezone":"Asia/Shanghai",
    "iso:country":"CN",
    "name:zho_x_preferred":[
        "\u5229\u5170"
    ],
    "wof:name":"Lilan",
    "wof:placetype":"locality"
},
  "geometry": {"coordinates":[120.11266999999999,28.40675],"type":"Point"}
}