{
  "type": "Feature",
  "properties": {
    "gn:admin1_code":"15.0",
    "gn:asciiname":"Xiwan",
    "gn:country_code":"CN",
    "gn:dem":1529,
    "gn:feature_class":"P",
    "gn:feature_code":"PPL",
    "gn:name":"Xiwan",
    "gn:population":0,
    "gn:timezone":"Asia/Shanghai",
    "iso:country":"CN",
    "name:und_x_variant":[
        "\u7ec6\u6e7e"
    ],
    "wof:name":"Xiwan",
    "wof:placetype":"locality"
},
  "geometry": {"coordinates":[105.71093999999999,35.23229],"type":"Point"}
}