{
  "type": "Feature",
  "properties": {
    "gn:admin1_code":"9.0",
    "gn:asciiname":"Shangluoguchong",
    "gn:country_code":"CN",
    "gn:dem":139,
    "gn:feature_class":"P",
    "gn:feature_code":"PPL",
    "gn:name":"Shangluoguchong",
    "gn:population":0,
    "gn:timezone":"Asia/Shanghai",
    "iso:country":"CN",
    "name:zho_x_preferred":[
        "\u4e0a\u9523\u9f13\u51b2"
    ],
    "wof:name":"Shangluoguchong",
    "wof:placetype":"locality"
},
  "geometry": {"coordinates":[113.92654,32.60907],"type":"Point"}
}