{
  "type": "Feature",
  "properties": {
    "gn:admin1_code":"10.0",
    "gn:asciiname":"Xinyaozi",
    "gn:country_code":"CN",
    "gn:dem":1077,
    "gn:feature_class":"P",
    "gn:feature_code":"PPL",
    "gn:name":"Xinyaozi",
    "gn:population":0,
    "gn:timezone":"Asia/Shanghai",
    "iso:country":"CN",
    "name:zho_x_preferred":[
        "\u8f9b\u7a91\u5b50"
    ],
    "wof:name":"Xinyaozi",
    "wof:placetype":"locality"
},
  "geometry": {"coordinates":[114.5471,39.94938],"type":"Point"}
}