{
  "type": "Feature",
  "properties": {
    "gn:admin1_code":"30",
    "gn:asciiname":"Pingtan",
    "gn:country_code":"CN",
    "gn:dem":72,
    "gn:feature_class":"P",
    "gn:feature_code":"PPL",
    "gn:name":"Pingtan",
    "gn:population":0,
    "gn:timezone":"Asia/Urumqi",
    "iso:country":"CN",
    "name:zho_x_preferred":[
        "\u5e73\u5766"
    ],
    "wof:name":"Pingtan",
    "wof:placetype":"locality"
},
  "geometry": {"coordinates":[110.01788000000001,21.8298],"type":"Point"}
}