{
  "type": "Feature",
  "properties": {
    "gn:admin1_code":"32.0",
    "gn:asciiname":"Longdongbang",
    "gn:country_code":"CN",
    "gn:dem":781,
    "gn:feature_class":"P",
    "gn:feature_code":"PPL",
    "gn:name":"Longdongbang",
    "gn:population":0,
    "gn:timezone":"Asia/Shanghai",
    "iso:country":"CN",
    "name:zho_x_preferred":[
        "\u9f99\u6d1e\u585d"
    ],
    "wof:name":"Longdongbang",
    "wof:placetype":"locality"
},
  "geometry": {"coordinates":[104.62779,28.00694],"type":"Point"}
}