{
  "type": "Feature",
  "properties": {
    "gn:admin1_code":"11",
    "gn:asciiname":"Heishitou",
    "gn:country_code":"CN",
    "gn:dem":607,
    "gn:feature_class":"P",
    "gn:feature_code":"PPL",
    "gn:name":"Heishitou",
    "gn:population":0,
    "gn:timezone":"Asia/Shanghai",
    "iso:country":"CN",
    "name:und_x_variant":[
        "\u9ed1\u77f3\u5934",
        "Heishitou"
    ],
    "wof:name":"Heishitou",
    "wof:placetype":"locality"
},
  "geometry": {"coordinates":[112.10778000000001,25.81389],"type":"Point"}
}