{
  "type": "Feature",
  "properties": {
    "gn:admin1_code":"11.0",
    "gn:asciiname":"Zhishan",
    "gn:country_code":"CN",
    "gn:dem":60,
    "gn:feature_class":"P",
    "gn:feature_code":"PPL",
    "gn:name":"Zhishan",
    "gn:population":0,
    "gn:timezone":"Asia/Shanghai",
    "iso:country":"CN",
    "name:zho_x_preferred":[
        "\u690d\u5c71"
    ],
    "wof:name":"Zhishan",
    "wof:placetype":"locality"
},
  "geometry": {"coordinates":[113.18182,29.12046],"type":"Point"}
}