{
  "type": "Feature",
  "properties": {
    "gn:admin1_code":"16.0",
    "gn:asciiname":"Zhili",
    "gn:country_code":"CN",
    "gn:dem":154,
    "gn:feature_class":"P",
    "gn:feature_code":"PPL",
    "gn:name":"Zhili",
    "gn:population":0,
    "gn:timezone":"Asia/Shanghai",
    "iso:country":"CN",
    "name:ces_x_preferred":[
        "\u010c\u2019-li"
    ],
    "name:deu_x_preferred":[
        "Zhili"
    ],
    "name:fra_x_preferred":[
        "Zhili"
    ],
    "name:ind_x_preferred":[
        "Zhili"
    ],
    "name:ita_x_preferred":[
        "Zhili"
    ],
    "name:oss_x_preferred":[
        "\u0427\u0436\u0438\u043b\u0438"
    ],
    "name:pol_x_preferred":[
        "Zhili"
    ],
    "name:rus_x_preferred":[
        "\u0427\u0436\u0438\u043b\u0438"
    ],
    "name:srp_x_preferred":[
        "\u040f\u0438\u043b\u0438"
    ],
    "name:ukr_x_preferred":[
        "\u0427\u0436\u0438\u043b\u0456"
    ],
    "name:vie_x_preferred":[
        "Tr\u1ef1c L\u1ec7"
    ],
    "name:zho_x_preferred":[
        "\u6b62\u793c"
    ],
    "wof:name":"Zhili",
    "wof:placetype":"locality"
},
  "geometry": {"coordinates":[109.461,23.4299],"type":"Point"}
}