{
  "type": "Feature",
  "properties": {
    "gn:admin1_code":"18.0",
    "gn:asciiname":"Yadouwan",
    "gn:country_code":"CN",
    "gn:dem":1051,
    "gn:feature_class":"P",
    "gn:feature_code":"PPL",
    "gn:name":"Yadouwan",
    "gn:population":0,
    "gn:timezone":"Asia/Shanghai",
    "iso:country":"CN",
    "name:zho_x_preferred":[
        "\u9e2d\u8c46\u6e7e"
    ],
    "wof:name":"Yadouwan",
    "wof:placetype":"locality"
},
  "geometry": {"coordinates":[107.169,26.3493],"type":"Point"}
}