{
  "type": "Feature",
  "properties": {
    "gn:admin1_code":"19.0",
    "gn:asciiname":"Wujiapu",
    "gn:country_code":"CN",
    "gn:dem":6,
    "gn:feature_class":"P",
    "gn:feature_code":"PPL",
    "gn:name":"Wujiapu",
    "gn:population":0,
    "gn:timezone":"Asia/Shanghai",
    "iso:country":"CN",
    "name:zho_x_preferred":[
        "\u4e94\u5bb6\u94fa"
    ],
    "wof:name":"Wujiapu",
    "wof:placetype":"locality"
},
  "geometry": {"coordinates":[121.997,41.4128],"type":"Point"}
}