{
  "type": "Feature",
  "properties": {
    "gn:admin1_code":"19.0",
    "gn:asciiname":"Hanjiajie",
    "gn:country_code":"CN",
    "gn:dem":9,
    "gn:feature_class":"P",
    "gn:feature_code":"PPL",
    "gn:name":"Hanjiajie",
    "gn:population":0,
    "gn:timezone":"Asia/Shanghai",
    "iso:country":"CN",
    "name:zho_x_preferred":[
        "\u97e9\u5bb6\u8857"
    ],
    "wof:name":"Hanjiajie",
    "wof:placetype":"locality"
},
  "geometry": {"coordinates":[122.00888,41.50143],"type":"Point"}
}