{
  "type": "Feature",
  "properties": {
    "gn:admin1_code":"04",
    "gn:asciiname":"Mazhuanghu",
    "gn:cc2":"CN",
    "gn:country_code":"CN",
    "gn:dem":18,
    "gn:feature_class":"P",
    "gn:feature_code":"PPL",
    "gn:name":"Mazhuanghu",
    "gn:population":0,
    "gn:timezone":"Asia/Shanghai",
    "iso:country":"CN",
    "name:und_x_variant":[
        "Ma-chuang-hu",
        "Suan-chuang-hu",
        "Mazhuanghu"
    ],
    "wof:name":"Mazhuanghu",
    "wof:placetype":"locality"
},
  "geometry": {"coordinates":[118.81667,34.66667],"type":"Point"}
}