{
  "type": "Feature",
  "properties": {
    "gn:admin1_code":"8.0",
    "gn:asciiname":"Qunfucun",
    "gn:country_code":"CN",
    "gn:dem":214,
    "gn:feature_class":"P",
    "gn:feature_code":"PPL",
    "gn:name":"Qunfucun",
    "gn:population":0,
    "gn:timezone":"Asia/Shanghai",
    "iso:country":"CN",
    "name:zho_x_preferred":[
        "\u7fa4\u5bcc\u6751"
    ],
    "wof:name":"Qunfucun",
    "wof:placetype":"locality"
},
  "geometry": {"coordinates":[127.41279,44.63752],"type":"Point"}
}