{
  "type": "Feature",
  "properties": {
    "gn:admin1_code":"24",
    "gn:asciiname":"Donglu",
    "gn:cc2":"CN",
    "gn:country_code":"CN",
    "gn:dem":525,
    "gn:feature_class":"P",
    "gn:feature_code":"PPL",
    "gn:name":"Donglu",
    "gn:population":0,
    "gn:timezone":"Asia/Shanghai",
    "iso:country":"CN",
    "name:und_x_variant":[
        "Tung-lu",
        "Tung-lu-ts\u2019un",
        "Donglu"
    ],
    "wof:name":"Donglu",
    "wof:placetype":"locality"
},
  "geometry": {"coordinates":[110.81667,34.71667],"type":"Point"}
}