{
  "type": "Feature",
  "properties": {
    "gn:admin1_code":"25",
    "gn:asciiname":"Sunzhifang",
    "gn:country_code":"CN",
    "gn:dem":45,
    "gn:feature_class":"P",
    "gn:feature_code":"PPL",
    "gn:name":"Sunzhifang",
    "gn:population":0,
    "gn:timezone":"Asia/Shanghai",
    "iso:country":"CN",
    "name:zho_x_preferred":[
        "\u5b59\u7eb8\u574a"
    ],
    "wof:name":"Sunzhifang",
    "wof:placetype":"locality"
},
  "geometry": {"coordinates":[116.354,35.8902],"type":"Point"}
}