{
  "type": "Feature",
  "properties": {
    "gn:admin1_code":"2.0",
    "gn:asciiname":"Banhe",
    "gn:country_code":"CN",
    "gn:dem":119,
    "gn:feature_class":"P",
    "gn:feature_code":"PPL",
    "gn:name":"Banhe",
    "gn:population":0,
    "gn:timezone":"Asia/Shanghai",
    "iso:country":"CN",
    "name:zho_x_preferred":[
        "\u575d\u8d3a"
    ],
    "wof:name":"Banhe",
    "wof:placetype":"locality"
},
  "geometry": {"coordinates":[118.52594999999999,28.6564],"type":"Point"}
}