{
  "type": "Feature",
  "properties": {
    "gn:admin1_code":"29.0",
    "gn:asciiname":"Suoluo",
    "gn:country_code":"CN",
    "gn:dem":1375,
    "gn:feature_class":"P",
    "gn:feature_code":"PPL",
    "gn:name":"Suoluo",
    "gn:population":0,
    "gn:timezone":"Asia/Shanghai",
    "iso:country":"CN",
    "name:zho_x_preferred":[
        "\u68ad\u7f57"
    ],
    "wof:name":"Suoluo",
    "wof:placetype":"locality"
},
  "geometry": {"coordinates":[102.376,23.1656],"type":"Point"}
}