{
  "type": "Feature",
  "properties": {
    "gn:admin1_code":"7.0",
    "gn:asciiname":"Taocuncun",
    "gn:country_code":"CN",
    "gn:dem":186,
    "gn:feature_class":"P",
    "gn:feature_code":"PPL",
    "gn:name":"Taocuncun",
    "gn:population":0,
    "gn:timezone":"Asia/Shanghai",
    "iso:country":"CN",
    "name:zho_x_preferred":[
        "\u6843\u6751\u6751"
    ],
    "wof:name":"Taocuncun",
    "wof:placetype":"locality"
},
  "geometry": {"coordinates":[117.41997000000001,26.72007],"type":"Point"}
}