{
  "type": "Feature",
  "properties": {
    "gn:admin1_code":"32",
    "gn:asciiname":"Lantian",
    "gn:country_code":"CN",
    "gn:dem":250,
    "gn:feature_class":"P",
    "gn:feature_code":"PPL",
    "gn:name":"Lantian",
    "gn:population":0,
    "gn:timezone":"Asia/Shanghai",
    "iso:country":"CN",
    "name:und_x_variant":[
        "Lantianba",
        "Lan-t\u2019ien-pa",
        "Lantian"
    ],
    "name:zho_x_preferred":[
        "\u84dd\u7530"
    ],
    "wof:name":"Lantian",
    "wof:placetype":"locality"
},
  "geometry": {"coordinates":[105.41287,28.85775],"type":"Point"}
}