{
  "type": "Feature",
  "properties": {
    "gn:admin1_code":"4.0",
    "gn:asciiname":"Hatuocun",
    "gn:country_code":"CN",
    "gn:dem":0,
    "gn:feature_class":"P",
    "gn:feature_code":"PPL",
    "gn:name":"Hatuocun",
    "gn:population":0,
    "gn:timezone":"Asia/Shanghai",
    "iso:country":"CN",
    "name:zho_x_preferred":[
        "\u86e4\u62d6\u6751"
    ],
    "wof:name":"Hatuocun",
    "wof:placetype":"locality"
},
  "geometry": {"coordinates":[119.43071999999999,33.2655],"type":"Point"}
}