{
  "type": "Feature",
  "properties": {
    "gn:admin1_code":"24.0",
    "gn:asciiname":"Sanlizhuang",
    "gn:country_code":"CN",
    "gn:dem":1028,
    "gn:feature_class":"P",
    "gn:feature_code":"PPL",
    "gn:name":"Sanlizhuang",
    "gn:population":0,
    "gn:timezone":"Asia/Shanghai",
    "iso:country":"CN",
    "name:und_x_variant":[
        "\u4e09\u91cc\u5e84"
    ],
    "wof:name":"Sanlizhuang",
    "wof:placetype":"locality"
},
  "geometry": {"coordinates":[113.12488,39.83945],"type":"Point"}
}