{
  "type": "Feature",
  "properties": {
    "gn:admin1_code":"26.0",
    "gn:asciiname":"Baiyaoxian",
    "gn:country_code":"CN",
    "gn:dem":1732,
    "gn:feature_class":"P",
    "gn:feature_code":"PPL",
    "gn:name":"Baiyaoxian",
    "gn:population":0,
    "gn:timezone":"Asia/Shanghai",
    "iso:country":"CN",
    "name:zho_x_preferred":[
        "\u767d\u5d3e\u5c98"
    ],
    "wof:name":"Baiyaoxian",
    "wof:placetype":"locality"
},
  "geometry": {"coordinates":[107.40007,37.36848],"type":"Point"}
}