{
  "type": "Feature",
  "properties": {
    "gn:admin1_code":"32.0",
    "gn:asciiname":"Fengwuchang",
    "gn:country_code":"CN",
    "gn:dem":390,
    "gn:feature_class":"P",
    "gn:feature_code":"PPL",
    "gn:name":"Fengwuchang",
    "gn:population":0,
    "gn:timezone":"Asia/Shanghai",
    "iso:country":"CN",
    "name:zho_x_preferred":[
        "\u51e4\u68a7\u573a"
    ],
    "wof:name":"Fengwuchang",
    "wof:placetype":"locality"
},
  "geometry": {"coordinates":[104.36192,30.11393],"type":"Point"}
}