{
  "type": "Feature",
  "properties": {
    "gn:admin1_code":"25",
    "gn:asciiname":"Jijia",
    "gn:country_code":"CN",
    "gn:dem":28,
    "gn:feature_class":"P",
    "gn:feature_code":"PPL",
    "gn:name":"Jijia",
    "gn:population":0,
    "gn:timezone":"Asia/Shanghai",
    "iso:country":"CN",
    "name:zho_x_preferred":[
        "\u5180\u5bb6"
    ],
    "wof:name":"Jijia",
    "wof:placetype":"locality"
},
  "geometry": {"coordinates":[118.655,36.8584],"type":"Point"}
}