{
  "type": "Feature",
  "properties": {
    "gn:admin1_code":"29.0",
    "gn:asciiname":"Jilimie",
    "gn:country_code":"CN",
    "gn:dem":2134,
    "gn:feature_class":"P",
    "gn:feature_code":"PPL",
    "gn:name":"Jilimie",
    "gn:population":0,
    "gn:timezone":"Asia/Shanghai",
    "iso:country":"CN",
    "name:zho_x_preferred":[
        "\u9e21\u54e9\u54a9"
    ],
    "wof:name":"Jilimie",
    "wof:placetype":"locality"
},
  "geometry": {"coordinates":[102.97499999999999,25.7799],"type":"Point"}
}