{
  "type": "Feature",
  "properties": {
    "gn:admin1_code":"26.0",
    "gn:asciiname":"Yanjiahe",
    "gn:cc2":"CN",
    "gn:country_code":"CN",
    "gn:dem":969,
    "gn:feature_class":"P",
    "gn:feature_code":"PPL",
    "gn:name":"Yanjiahe",
    "gn:population":0,
    "gn:timezone":"Asia/Shanghai",
    "iso:country":"CN",
    "name:und_x_variant":[
        "Yen-chia-ho",
        "Yanjiahe"
    ],
    "wof:name":"Yanjiahe",
    "wof:placetype":"locality"
},
  "geometry": {"coordinates":[106.78333000000001,34.38333],"type":"Point"}
}