{
  "type": "Feature",
  "properties": {
    "gn:admin1_code":"30",
    "gn:asciiname":"Qianhe",
    "gn:country_code":"CN",
    "gn:dem":3,
    "gn:feature_class":"P",
    "gn:feature_code":"PPL",
    "gn:name":"Qianhe",
    "gn:population":0,
    "gn:timezone":"Asia/Shanghai",
    "iso:country":"CN",
    "name:und_x_variant":[
        "Qianhecun",
        "Qianhe"
    ],
    "name:zho_x_preferred":[
        "\u524d\u4f55\u6751"
    ],
    "name:zho_x_variant":[
        "\u524d\u4f55"
    ],
    "wof:name":"Qianhe",
    "wof:placetype":"locality"
},
  "geometry": {"coordinates":[116.31108,23.02015],"type":"Point"}
}