{
  "type": "Feature",
  "properties": {
    "gn:admin1_code":"03",
    "gn:asciiname":"Lingang",
    "gn:country_code":"CN",
    "gn:dem":34,
    "gn:feature_class":"P",
    "gn:feature_code":"PPLA4",
    "gn:name":"Lingang",
    "gn:population":0,
    "gn:timezone":"Asia/Shanghai",
    "iso:country":"CN",
    "name:und_x_variant":[
        "Lin-Kang",
        "Lin-chiang",
        "Lingang",
        "\u4e34\u6e2f",
        "Lingang Zhen",
        "\u4e34\u6e2f\u9547"
    ],
    "wof:name":"Lingang",
    "wof:placetype":"locality"
},
  "geometry": {"coordinates":[117.30837,29.02889],"type":"Point"}
}