{
  "type": "Feature",
  "properties": {
    "gn:admin1_code":"30.0",
    "gn:asciiname":"Chatingjing",
    "gn:country_code":"CN",
    "gn:dem":159,
    "gn:feature_class":"P",
    "gn:feature_code":"PPL",
    "gn:name":"Chatingjing",
    "gn:population":0,
    "gn:timezone":"Asia/Shanghai",
    "iso:country":"CN",
    "name:zho_x_preferred":[
        "Chatingjing"
    ],
    "name:zho_x_variant":[
        "\u8336\u4ead\u5f84"
    ],
    "wof:name":"Chatingjing",
    "wof:placetype":"locality"
},
  "geometry": {"coordinates":[115.29944,24.37389],"type":"Point"}
}