{
  "type": "Feature",
  "properties": {
    "gn:admin1_code":"15.0",
    "gn:asciiname":"Dayangjia",
    "gn:country_code":"CN",
    "gn:dem":1986,
    "gn:feature_class":"P",
    "gn:feature_code":"PPL",
    "gn:name":"Dayangjia",
    "gn:population":0,
    "gn:timezone":"Asia/Shanghai",
    "iso:country":"CN",
    "name:zho_x_preferred":[
        "\u5927\u6768\u5bb6"
    ],
    "wof:name":"Dayangjia",
    "wof:placetype":"locality"
},
  "geometry": {"coordinates":[103.526,35.4742],"type":"Point"}
}