{
  "type": "Feature",
  "properties": {
    "gn:admin1_code":"4.0",
    "gn:asciiname":"Gaoxu",
    "gn:country_code":"CN",
    "gn:dem":4,
    "gn:feature_class":"P",
    "gn:feature_code":"PPL",
    "gn:name":"Gaoxu",
    "gn:population":0,
    "gn:timezone":"Asia/Shanghai",
    "iso:country":"CN",
    "name:zho_x_preferred":[
        "Gaoxu"
    ],
    "name:zho_x_variant":[
        "\u9ad8\u5729"
    ],
    "wof:name":"Gaoxu",
    "wof:placetype":"locality"
},
  "geometry": {"coordinates":[119.10448,33.17264],"type":"Point"}
}