{
  "type": "Feature",
  "properties": {
    "gn:admin1_code":"4.0",
    "gn:asciiname":"Dingducun",
    "gn:country_code":"CN",
    "gn:dem":0,
    "gn:feature_class":"P",
    "gn:feature_code":"PPL",
    "gn:name":"Dingducun",
    "gn:population":0,
    "gn:timezone":"Asia/Shanghai",
    "iso:country":"CN",
    "name:zho_x_preferred":[
        "\u4e01\u6e21\u6751"
    ],
    "wof:name":"Dingducun",
    "wof:placetype":"locality"
},
  "geometry": {"coordinates":[119.88012999999999,33.56891],"type":"Point"}
}