{
  "type": "Feature",
  "properties": {
    "gn:admin1_code":"24.0",
    "gn:asciiname":"Guanzhuang",
    "gn:country_code":"CN",
    "gn:dem":1382,
    "gn:feature_class":"P",
    "gn:feature_code":"PPL",
    "gn:name":"Guanzhuang",
    "gn:population":0,
    "gn:timezone":"Asia/Shanghai",
    "iso:country":"CN",
    "name:zho_x_preferred":[
        "\u5b98\u5e84"
    ],
    "wof:name":"Guanzhuang",
    "wof:placetype":"locality"
},
  "geometry": {"coordinates":[113.47490000000001,37.34345],"type":"Point"}
}