{
  "type": "Feature",
  "properties": {
    "gn:admin1_code":"7.0",
    "gn:asciiname":"Yangtou",
    "gn:country_code":"CN",
    "gn:dem":739,
    "gn:feature_class":"P",
    "gn:feature_code":"PPL",
    "gn:name":"Yangtou",
    "gn:population":0,
    "gn:timezone":"Asia/Shanghai",
    "iso:country":"CN",
    "name:zho_x_preferred":[
        "\u6d0b\u5934"
    ],
    "wof:name":"Yangtou",
    "wof:placetype":"locality"
},
  "geometry": {"coordinates":[119.13979,26.80217],"type":"Point"}
}