{
  "type": "Feature",
  "properties": {
    "gn:admin1_code":"4.0",
    "gn:asciiname":"Dali",
    "gn:country_code":"CN",
    "gn:dem":18,
    "gn:feature_class":"P",
    "gn:feature_code":"PPL",
    "gn:name":"Dali",
    "gn:population":0,
    "gn:timezone":"Asia/Shanghai",
    "iso:country":"CN",
    "name:bul_x_preferred":[
        "\u0414\u0430\u043b\u0438"
    ],
    "name:cat_x_preferred":[
        "Dali"
    ],
    "name:ceb_x_preferred":[
        "Dali"
    ],
    "name:dan_x_preferred":[
        "Dali"
    ],
    "name:deu_x_preferred":[
        "Dali"
    ],
    "name:fin_x_preferred":[
        "Dali"
    ],
    "name:fra_x_preferred":[
        "Dali"
    ],
    "name:heb_x_preferred":[
        "\u05d3\u05d0\u05dc\u05d9"
    ],
    "name:ita_x_preferred":[
        "Dali"
    ],
    "name:kat_x_preferred":[
        "\u10d3\u10d0\u10da\u10d8"
    ],
    "name:lit_x_preferred":[
        "Dali"
    ],
    "name:mlg_x_preferred":[
        "Dali"
    ],
    "name:nld_x_preferred":[
        "Dali"
    ],
    "name:nor_x_preferred":[
        "Dali"
    ],
    "name:pol_x_preferred":[
        "Dali"
    ],
    "name:por_x_preferred":[
        "Dali"
    ],
    "name:rus_x_preferred":[
        "\u0440\u0435\u043a\u0430 \u0414\u0430\u043b\u0438"
    ],
    "name:rus_x_variant":[
        "\u0414\u0430\u043b\u0438"
    ],
    "name:spa_x_preferred":[
        "Dali"
    ],
    "name:swe_x_preferred":[
        "Dali"
    ],
    "name:tat_x_preferred":[
        "\u0414\u0430\u043b\u0438"
    ],
    "name:tgl_x_preferred":[
        "Dali"
    ],
    "name:tur_x_preferred":[
        "Dali"
    ],
    "name:ukr_x_preferred":[
        "\u0414\u0430\u043b\u0456"
    ],
    "name:urd_x_preferred":[
        "\u0688\u0627\u0644\u06cc"
    ],
    "name:vie_x_preferred":[
        "S\u00f4ng Dali"
    ],
    "name:zho_cn_x_preferred":[
        "\u5927\u91cc\u6eaa"
    ],
    "name:zho_tw_x_preferred":[
        "\u5927\u7406\u6cb3"
    ],
    "name:zho_x_preferred":[
        "\u5927\u674e"
    ],
    "wof:name":"Dali",
    "wof:placetype":"locality"
},
  "geometry": {"coordinates":[117.971,33.2857],"type":"Point"}
}