{
  "type": "Feature",
  "properties": {
    "gn:admin1_code":"11",
    "gn:asciiname":"Yeniuguilan",
    "gn:country_code":"CN",
    "gn:dem":488,
    "gn:feature_class":"P",
    "gn:feature_code":"PPL",
    "gn:name":"Yeniuguilan",
    "gn:population":0,
    "gn:timezone":"Asia/Shanghai",
    "iso:country":"CN",
    "name:und_x_variant":[
        "\u591c\u725b\u5f52\u680f",
        "Yeniuguilan"
    ],
    "wof:name":"Yeniuguilan",
    "wof:placetype":"locality"
},
  "geometry": {"coordinates":[112.05833,25.95194],"type":"Point"}
}