{
  "type": "Feature",
  "properties": {
    "gn:admin1_code":"10",
    "gn:asciiname":"Donghoufang",
    "gn:country_code":"CN",
    "gn:dem":52,
    "gn:feature_class":"P",
    "gn:feature_code":"PPLA4",
    "gn:name":"Donghoufang",
    "gn:population":0,
    "gn:timezone":"Asia/Shanghai",
    "iso:country":"CN",
    "name:fas_x_preferred":[
        "\u0634\u0647\u0631 \u062f\u0648\u0646\u06af\u0647\u0648\u0641\u0627\u0646\u06af"
    ],
    "name:und_x_variant":[
        "\u4e1c\u4faf\u574a",
        "Donghoufang Xiang",
        "\u4e1c\u4faf\u574a\u4e61"
    ],
    "name:zho_x_preferred":[
        "\u4e1c\u4faf\u574a\u4e61"
    ],
    "wof:name":"Donghoufang",
    "wof:placetype":"locality"
},
  "geometry": {"coordinates":[114.89778,38.1825],"type":"Point"}
}