{
  "type": "Feature",
  "properties": {
    "gn:admin1_code":"3.0",
    "gn:asciiname":"Yibeitang",
    "gn:country_code":"CN",
    "gn:dem":29,
    "gn:feature_class":"P",
    "gn:feature_code":"PPL",
    "gn:name":"Yibeitang",
    "gn:population":0,
    "gn:timezone":"Asia/Shanghai",
    "iso:country":"CN",
    "name:und_x_variant":[
        "\u6613\u9642\u5858"
    ],
    "wof:name":"Yibeitang",
    "wof:placetype":"locality"
},
  "geometry": {"coordinates":[116.09331,28.40845],"type":"Point"}
}