{
  "type": "Feature",
  "properties": {
    "gn:admin1_code":"19.0",
    "gn:asciiname":"Houshagangzi",
    "gn:country_code":"CN",
    "gn:dem":32,
    "gn:feature_class":"P",
    "gn:feature_code":"PPL",
    "gn:name":"Houshagangzi",
    "gn:population":0,
    "gn:timezone":"Asia/Shanghai",
    "iso:country":"CN",
    "name:zho_x_preferred":[
        "\u540e\u6c99\u5c97\u5b50"
    ],
    "wof:name":"Houshagangzi",
    "wof:placetype":"locality"
},
  "geometry": {"coordinates":[122.91800000000001,42.0272],"type":"Point"}
}