{
  "type": "Feature",
  "properties": {
    "gn:admin1_code":"7.0",
    "gn:asciiname":"Chuanshan",
    "gn:country_code":"CN",
    "gn:dem":751,
    "gn:feature_class":"P",
    "gn:feature_code":"PPL",
    "gn:name":"Chuanshan",
    "gn:population":0,
    "gn:timezone":"Asia/Shanghai",
    "iso:country":"CN",
    "name:zho_x_preferred":[
        "\u8239\u5c71"
    ],
    "wof:name":"Chuanshan",
    "wof:placetype":"locality"
},
  "geometry": {"coordinates":[118.58748,28.08118],"type":"Point"}
}