{
  "type": "Feature",
  "properties": {
    "gn:admin1_code":"16.0",
    "gn:asciiname":"Jihuai",
    "gn:country_code":"CN",
    "gn:dem":212,
    "gn:feature_class":"P",
    "gn:feature_code":"PPL",
    "gn:name":"Jihuai",
    "gn:population":0,
    "gn:timezone":"Asia/Shanghai",
    "iso:country":"CN",
    "name:zho_x_preferred":[
        "\u8ba1\u6000"
    ],
    "wof:name":"Jihuai",
    "wof:placetype":"locality"
},
  "geometry": {"coordinates":[107.937,22.1647],"type":"Point"}
}