{
  "type": "Feature",
  "properties": {
    "gn:admin1_code":"32.0",
    "gn:asciiname":"Lizibang",
    "gn:country_code":"CN",
    "gn:dem":950,
    "gn:feature_class":"P",
    "gn:feature_code":"PPL",
    "gn:name":"Lizibang",
    "gn:population":0,
    "gn:timezone":"Asia/Shanghai",
    "iso:country":"CN",
    "name:zho_x_preferred":[
        "\u68a8\u5b50\u585d"
    ],
    "wof:name":"Lizibang",
    "wof:placetype":"locality"
},
  "geometry": {"coordinates":[105.11251,28.25076],"type":"Point"}
}