{
  "type": "Feature",
  "properties": {
    "gn:admin1_code":"9.0",
    "gn:asciiname":"Zhaodongcun",
    "gn:country_code":"CN",
    "gn:dem":168,
    "gn:feature_class":"P",
    "gn:feature_code":"PPL",
    "gn:name":"Zhaodongcun",
    "gn:population":0,
    "gn:timezone":"Asia/Shanghai",
    "iso:country":"CN",
    "name:zho_x_preferred":[
        "\u8d75\u4e1c\u6751"
    ],
    "wof:name":"Zhaodongcun",
    "wof:placetype":"locality"
},
  "geometry": {"coordinates":[112.97562000000001,34.08264],"type":"Point"}
}