{
  "type": "Feature",
  "properties": {
    "gn:admin1_code":"12.0",
    "gn:asciiname":"Pipaping",
    "gn:country_code":"CN",
    "gn:dem":256,
    "gn:feature_class":"P",
    "gn:feature_code":"PPL",
    "gn:name":"Pipaping",
    "gn:population":0,
    "gn:timezone":"Asia/Shanghai",
    "iso:country":"CN",
    "name:zho_x_preferred":[
        "\u7435\u7436\u576a"
    ],
    "wof:name":"Pipaping",
    "wof:placetype":"locality"
},
  "geometry": {"coordinates":[110.51208,32.38006],"type":"Point"}
}