{
  "type": "Feature",
  "properties": {
    "gn:admin1_code":"12.0",
    "gn:asciiname":"Tianjiashan",
    "gn:country_code":"CN",
    "gn:dem":1604,
    "gn:feature_class":"P",
    "gn:feature_code":"PPL",
    "gn:name":"Tianjiashan",
    "gn:population":0,
    "gn:timezone":"Asia/Shanghai",
    "iso:country":"CN",
    "name:zho_x_preferred":[
        "\u7530\u5bb6\u5c71"
    ],
    "wof:name":"Tianjiashan",
    "wof:placetype":"locality"
},
  "geometry": {"coordinates":[110.43219000000001,31.64098],"type":"Point"}
}