{
  "type": "Feature",
  "properties": {
    "gn:admin1_code":"32.0",
    "gn:asciiname":"Shirengou",
    "gn:country_code":"CN",
    "gn:dem":692,
    "gn:feature_class":"P",
    "gn:feature_code":"PPL",
    "gn:name":"Shirengou",
    "gn:population":0,
    "gn:timezone":"Asia/Shanghai",
    "iso:country":"CN",
    "name:zho_x_preferred":[
        "\u6c0f\u4eba\u6c9f"
    ],
    "wof:name":"Shirengou",
    "wof:placetype":"locality"
},
  "geometry": {"coordinates":[103.19799999999999,30.3017],"type":"Point"}
}