{
  "type": "Feature",
  "properties": {
    "gn:admin1_code":"2.0",
    "gn:asciiname":"Zhilin",
    "gn:country_code":"CN",
    "gn:dem":161,
    "gn:feature_class":"P",
    "gn:feature_code":"PPL",
    "gn:name":"Zhilin",
    "gn:population":0,
    "gn:timezone":"Asia/Shanghai",
    "iso:country":"CN",
    "name:rus_x_preferred":[
        "\u0416\u0438\u043b\u0438\u043d"
    ],
    "name:ukr_x_preferred":[
        "\u0416\u0438\u043b\u0456\u043d"
    ],
    "name:zho_x_preferred":[
        "\u829d\u6797"
    ],
    "wof:name":"Zhilin",
    "wof:placetype":"locality"
},
  "geometry": {"coordinates":[121.29912,29.93004],"type":"Point"}
}