{
  "type": "Feature",
  "properties": {
    "gn:admin1_code":"11",
    "gn:asciiname":"Tianzhongjian",
    "gn:country_code":"CN",
    "gn:dem":265,
    "gn:feature_class":"P",
    "gn:feature_code":"PPL",
    "gn:name":"Tianzhongjian",
    "gn:population":0,
    "gn:timezone":"Asia/Shanghai",
    "iso:country":"CN",
    "name:zho_x_preferred":[
        "\u7530\u4e2d\u95f4"
    ],
    "wof:name":"Tianzhongjian",
    "wof:placetype":"locality"
},
  "geometry": {"coordinates":[111.00675,26.64629],"type":"Point"}
}