{
  "type": "Feature",
  "properties": {
    "gn:admin1_code":"1.0",
    "gn:asciiname":"Sanxu",
    "gn:country_code":"CN",
    "gn:dem":8,
    "gn:feature_class":"P",
    "gn:feature_code":"PPL",
    "gn:name":"Sanxu",
    "gn:population":0,
    "gn:timezone":"Asia/Shanghai",
    "iso:country":"CN",
    "name:und_x_variant":[
        "Sanlian",
        "Sanxu"
    ],
    "name:zho_x_preferred":[
        "\u4e09\u5f90"
    ],
    "wof:name":"Sanxu",
    "wof:placetype":"locality"
},
  "geometry": {"coordinates":[118.40922,31.61178],"type":"Point"}
}