{
  "type": "Feature",
  "properties": {
    "gn:admin1_code":"2.0",
    "gn:asciiname":"Qinyong",
    "gn:country_code":"CN",
    "gn:dem":100,
    "gn:feature_class":"P",
    "gn:feature_code":"PPL",
    "gn:name":"Qinyong",
    "gn:population":0,
    "gn:timezone":"Asia/Shanghai",
    "iso:country":"CN",
    "name:zho_x_preferred":[
        "\u52e4\u52c7"
    ],
    "wof:name":"Qinyong",
    "wof:placetype":"locality"
},
  "geometry": {"coordinates":[121.80247,29.77142000000001],"type":"Point"}
}