{
  "type": "Feature",
  "properties": {
    "gn:admin1_code":"29.0",
    "gn:asciiname":"Luoxi Dacun",
    "gn:country_code":"CN",
    "gn:dem":1771,
    "gn:feature_class":"P",
    "gn:feature_code":"PPL",
    "gn:name":"Luoxi Dacun",
    "gn:population":0,
    "gn:timezone":"Asia/Shanghai",
    "iso:country":"CN",
    "name:zho_x_preferred":[
        "\u7f57\u6eaa\u5927\u6751"
    ],
    "wof:name":"Luoxi Dacun",
    "wof:placetype":"locality"
},
  "geometry": {"coordinates":[100.747,25.3421],"type":"Point"}
}