{
  "type": "Feature",
  "properties": {
    "gn:admin1_code":"12.0",
    "gn:asciiname":"Yujiayan",
    "gn:country_code":"CN",
    "gn:dem":45,
    "gn:feature_class":"P",
    "gn:feature_code":"PPL",
    "gn:name":"Yujiayan",
    "gn:population":0,
    "gn:timezone":"Asia/Shanghai",
    "iso:country":"CN",
    "name:zho_x_preferred":[
        "Yujiayan"
    ],
    "name:zho_x_variant":[
        "\u4f59\u5bb6\u5830"
    ],
    "wof:name":"Yujiayan",
    "wof:placetype":"locality"
},
  "geometry": {"coordinates":[115.35946,30.47509],"type":"Point"}
}