{
  "type": "Feature",
  "properties": {
    "gn:admin1_code":"30.0",
    "gn:asciiname":"Huakengwei",
    "gn:country_code":"CN",
    "gn:dem":84,
    "gn:feature_class":"P",
    "gn:feature_code":"PPL",
    "gn:name":"Huakengwei",
    "gn:population":0,
    "gn:timezone":"Asia/Shanghai",
    "iso:country":"CN",
    "name:zho_x_preferred":[
        "\u82b1\u5751\u5c3e"
    ],
    "wof:name":"Huakengwei",
    "wof:placetype":"locality"
},
  "geometry": {"coordinates":[114.80016000000001,23.72694],"type":"Point"}
}