{
  "type": "Feature",
  "properties": {
    "gn:admin1_code":"16.0",
    "gn:asciiname":"Badang",
    "gn:country_code":"CN",
    "gn:dem":311,
    "gn:feature_class":"P",
    "gn:feature_code":"PPL",
    "gn:name":"Badang",
    "gn:population":0,
    "gn:timezone":"Asia/Shanghai",
    "iso:country":"CN",
    "name:msa_x_preferred":[
        "Badang"
    ],
    "name:zho_x_preferred":[
        "\u5c9c\u5f53"
    ],
    "wof:name":"Badang",
    "wof:placetype":"locality"
},
  "geometry": {"coordinates":[107.15000000000001,23.3589],"type":"Point"}
}