{
  "type": "Feature",
  "properties": {
    "gn:admin1_code":"02",
    "gn:asciiname":"Machecun",
    "gn:country_code":"CN",
    "gn:dem":23,
    "gn:feature_class":"P",
    "gn:feature_code":"PPL",
    "gn:name":"Machecun",
    "gn:population":0,
    "gn:timezone":"Asia/Shanghai",
    "iso:country":"CN",
    "name:und_x_variant":[
        "Mache",
        "Machecun"
    ],
    "name:zho_x_preferred":[
        "\u9ebb\u8f66\u6751"
    ],
    "wof:name":"Machecun",
    "wof:placetype":"locality"
},
  "geometry": {"coordinates":[121.47931,28.78931],"type":"Point"}
}