{
  "type": "Feature",
  "properties": {
    "gn:admin1_code":"5.0",
    "gn:asciiname":"Houtumucun",
    "gn:country_code":"CN",
    "gn:dem":137,
    "gn:feature_class":"P",
    "gn:feature_code":"PPL",
    "gn:name":"Houtumucun",
    "gn:population":0,
    "gn:timezone":"Asia/Shanghai",
    "iso:country":"CN",
    "name:zho_x_preferred":[
        "\u540e\u571f\u6728\u6751"
    ],
    "wof:name":"Houtumucun",
    "wof:placetype":"locality"
},
  "geometry": {"coordinates":[125.00543999999999,45.37319],"type":"Point"}
}