{
  "type": "Feature",
  "properties": {
    "gn:admin1_code":"5.0",
    "gn:asciiname":"Zhangkuicun",
    "gn:country_code":"CN",
    "gn:dem":212,
    "gn:feature_class":"P",
    "gn:feature_code":"PPL",
    "gn:name":"Zhangkuicun",
    "gn:population":0,
    "gn:timezone":"Asia/Shanghai",
    "iso:country":"CN",
    "name:zho_x_preferred":[
        "\u5f20\u594e\u6751"
    ],
    "wof:name":"Zhangkuicun",
    "wof:placetype":"locality"
},
  "geometry": {"coordinates":[126.50541,44.75155],"type":"Point"}
}