{
  "type": "Feature",
  "properties": {
    "gn:admin1_code":"29",
    "gn:asciiname":"Micheng",
    "gn:country_code":"CN",
    "gn:dem":1662,
    "gn:feature_class":"P",
    "gn:feature_code":"PPLA3",
    "gn:name":"Micheng",
    "gn:population":0,
    "gn:timezone":"Asia/Shanghai",
    "iso:country":"CN",
    "name:und_x_variant":[
        "Mi-tu-chen",
        "Mi-tu-chieh",
        "Mi-tu-hsien",
        "Mi-tu",
        "Midu",
        "Micheng"
    ],
    "name:zho_x_preferred":[
        "Mi-ch\u2019eng-chen"
    ],
    "name:zho_x_variant":[
        "\u5f25\u57ce"
    ],
    "wof:name":"Micheng",
    "wof:placetype":"locality"
},
  "geometry": {"coordinates":[100.49930999999999,25.32037],"type":"Point"}
}