{
  "type": "Feature",
  "properties": {
    "gn:admin1_code":"30",
    "gn:asciiname":"Xulu",
    "gn:country_code":"CN",
    "gn:dem":56,
    "gn:feature_class":"P",
    "gn:feature_code":"PPL",
    "gn:name":"Xulu",
    "gn:population":0,
    "gn:timezone":"Asia/Urumqi",
    "iso:country":"CN",
    "name:zho_x_preferred":[
        "\u5f90\u7984"
    ],
    "wof:name":"Xulu",
    "wof:placetype":"locality"
},
  "geometry": {"coordinates":[109.96507,20.57628],"type":"Point"}
}