{
  "type": "Feature",
  "properties": {
    "gn:admin1_code":"10.0",
    "gn:asciiname":"Gaoluo",
    "gn:country_code":"CN",
    "gn:dem":39,
    "gn:feature_class":"P",
    "gn:feature_code":"PPL",
    "gn:name":"Gaoluo",
    "gn:population":0,
    "gn:timezone":"Asia/Shanghai",
    "iso:country":"CN",
    "name:zho_x_preferred":[
        "\u9ad8\u843d"
    ],
    "wof:name":"Gaoluo",
    "wof:placetype":"locality"
},
  "geometry": {"coordinates":[115.74590000000001,39.32621],"type":"Point"}
}