{
  "type": "Feature",
  "properties": {
    "gn:admin1_code":"12.0",
    "gn:asciiname":"Quanyangping",
    "gn:country_code":"CN",
    "gn:dem":46,
    "gn:feature_class":"P",
    "gn:feature_code":"PPL",
    "gn:name":"Quanyangping",
    "gn:population":0,
    "gn:timezone":"Asia/Shanghai",
    "iso:country":"CN",
    "name:zho_x_preferred":[
        "Quanyangping"
    ],
    "name:zho_x_variant":[
        "\u5168\u7f8a\u576a"
    ],
    "wof:name":"Quanyangping",
    "wof:placetype":"locality"
},
  "geometry": {"coordinates":[111.79586,29.91805],"type":"Point"}
}