{
  "type": "Feature",
  "properties": {
    "gn:admin1_code":"16.0",
    "gn:asciiname":"Qinhuai",
    "gn:country_code":"CN",
    "gn:dem":340,
    "gn:feature_class":"P",
    "gn:feature_code":"PPL",
    "gn:name":"Qinhuai",
    "gn:population":0,
    "gn:timezone":"Asia/Shanghai",
    "iso:country":"CN",
    "name:zho_x_preferred":[
        "\u7434\u6000"
    ],
    "wof:name":"Qinhuai",
    "wof:placetype":"locality"
},
  "geometry": {"coordinates":[108.992,24.2095],"type":"Point"}
}