{
  "type": "Feature",
  "properties": {
    "gn:admin1_code":"29.0",
    "gn:asciiname":"Sanxiangu",
    "gn:country_code":"CN",
    "gn:dem":1852,
    "gn:feature_class":"P",
    "gn:feature_code":"PPL",
    "gn:name":"Sanxiangu",
    "gn:population":0,
    "gn:timezone":"Asia/Shanghai",
    "iso:country":"CN",
    "name:zho_x_preferred":[
        "\u4e09\u4ed9\u59d1"
    ],
    "wof:name":"Sanxiangu",
    "wof:placetype":"locality"
},
  "geometry": {"coordinates":[99.941,26.9963],"type":"Point"}
}