{
  "type": "Feature",
  "properties": {
    "gn:admin1_code":"15.0",
    "gn:asciiname":"Laoshengou",
    "gn:country_code":"CN",
    "gn:dem":1024,
    "gn:feature_class":"P",
    "gn:feature_code":"PPL",
    "gn:name":"Laoshengou",
    "gn:population":0,
    "gn:timezone":"Asia/Shanghai",
    "iso:country":"CN",
    "name:und_x_variant":[
        "\u8001\u6df1\u6c9f"
    ],
    "wof:name":"Laoshengou",
    "wof:placetype":"locality"
},
  "geometry": {"coordinates":[106.18303,33.71267],"type":"Point"}
}