{
  "type": "Feature",
  "properties": {
    "gn:admin1_code":"3.0",
    "gn:asciiname":"Taxia'an",
    "gn:country_code":"CN",
    "gn:dem":81,
    "gn:feature_class":"P",
    "gn:feature_code":"PPL",
    "gn:name":"Taxia\u2019an",
    "gn:population":0,
    "gn:timezone":"Asia/Shanghai",
    "iso:country":"CN",
    "name:und_x_variant":[
        "Taxia\u2019an",
        "\u5854\u4e0b\u5eb5"
    ],
    "wof:name":"Taxia'an",
    "wof:placetype":"locality"
},
  "geometry": {"coordinates":[115.83197,28.81783],"type":"Point"}
}