{
  "type": "Feature",
  "properties": {
    "gn:admin1_code":"16.0",
    "gn:asciiname":"Futang",
    "gn:country_code":"CN",
    "gn:dem":399,
    "gn:feature_class":"P",
    "gn:feature_code":"PPL",
    "gn:name":"Futang",
    "gn:population":0,
    "gn:timezone":"Asia/Shanghai",
    "iso:country":"CN",
    "name:zho_x_preferred":[
        "\u798f\u5802"
    ],
    "wof:name":"Futang",
    "wof:placetype":"locality"
},
  "geometry": {"coordinates":[110.221,24.5588],"type":"Point"}
}