{
  "type": "Feature",
  "properties": {
    "gn:admin1_code":"11",
    "gn:asciiname":"Zhaqiao",
    "gn:country_code":"CN",
    "gn:dem":79,
    "gn:feature_class":"P",
    "gn:feature_code":"PPL",
    "gn:name":"Zhaqiao",
    "gn:population":0,
    "gn:timezone":"Asia/Shanghai",
    "iso:country":"CN",
    "name:zho_x_preferred":[
        "\u8f67\u6865"
    ],
    "wof:name":"Zhaqiao",
    "wof:placetype":"locality"
},
  "geometry": {"coordinates":[112.39870999999999,27.82113],"type":"Point"}
}