{
  "type": "Feature",
  "properties": {
    "gn:admin1_code":"29.0",
    "gn:asciiname":"Nanxilu",
    "gn:country_code":"CN",
    "gn:dem":2496,
    "gn:feature_class":"P",
    "gn:feature_code":"PPL",
    "gn:name":"Nanxilu",
    "gn:population":0,
    "gn:timezone":"Asia/Shanghai",
    "iso:country":"CN",
    "name:zho_x_preferred":[
        "\u5357\u6eaa\u9c81"
    ],
    "wof:name":"Nanxilu",
    "wof:placetype":"locality"
},
  "geometry": {"coordinates":[100.13500000000001,26.3117],"type":"Point"}
}