{
  "type": "Feature",
  "properties": {
    "gn:admin1_code":"26.0",
    "gn:asciiname":"Xiangshandian",
    "gn:country_code":"CN",
    "gn:dem":1964,
    "gn:feature_class":"P",
    "gn:feature_code":"PPL",
    "gn:name":"Xiangshandian",
    "gn:population":0,
    "gn:timezone":"Asia/Shanghai",
    "iso:country":"CN",
    "name:zho_x_preferred":[
        "\u9999\u5c71\u6bbf"
    ],
    "wof:name":"Xiangshandian",
    "wof:placetype":"locality"
},
  "geometry": {"coordinates":[106.55671,34.57969],"type":"Point"}
}