{
  "type": "Feature",
  "properties": {
    "gn:admin1_code":"2.0",
    "gn:asciiname":"Nongjian",
    "gn:country_code":"CN",
    "gn:dem":100,
    "gn:feature_class":"P",
    "gn:feature_code":"PPLF",
    "gn:name":"Nongjian",
    "gn:population":0,
    "gn:timezone":"Asia/Shanghai",
    "iso:country":"CN",
    "name:zho_x_preferred":[
        "\u519c\u5efa"
    ],
    "wof:name":"Nongjian",
    "wof:placetype":"locality"
},
  "geometry": {"coordinates":[120.17663,29.17598],"type":"Point"}
}