{
  "type": "Feature",
  "properties": {
    "gn:admin1_code":"29.0",
    "gn:asciiname":"Yangshan Heba",
    "gn:country_code":"CN",
    "gn:dem":1724,
    "gn:feature_class":"P",
    "gn:feature_code":"PPL",
    "gn:name":"Yangshan Heba",
    "gn:population":0,
    "gn:timezone":"Asia/Shanghai",
    "iso:country":"CN",
    "name:und_x_variant":[
        "\u9633\u5c71\u6cb3\u575d"
    ],
    "wof:name":"Yangshan Heba",
    "wof:placetype":"locality"
},
  "geometry": {"coordinates":[103.99236000000001,28.2087],"type":"Point"}
}