{
  "type": "Feature",
  "properties": {
    "gn:admin1_code":"18",
    "gn:asciiname":"Daduba",
    "gn:country_code":"CN",
    "gn:dem":827,
    "gn:feature_class":"P",
    "gn:feature_code":"PPL",
    "gn:name":"Daduba",
    "gn:population":0,
    "gn:timezone":"Asia/Shanghai",
    "iso:country":"CN",
    "name:zho_x_preferred":[
        "\u5927\u90fd\u575d"
    ],
    "wof:name":"Daduba",
    "wof:placetype":"locality"
},
  "geometry": {"coordinates":[107.73699999999999,27.6591],"type":"Point"}
}