{
  "type": "Feature",
  "properties": {
    "gn:admin1_code":"19.0",
    "gn:asciiname":"Songmubucun",
    "gn:country_code":"CN",
    "gn:dem":100,
    "gn:feature_class":"P",
    "gn:feature_code":"PPL",
    "gn:name":"Songmubucun",
    "gn:population":0,
    "gn:timezone":"Asia/Shanghai",
    "iso:country":"CN",
    "name:zho_x_preferred":[
        "\u677e\u6728\u5821\u6751"
    ],
    "wof:name":"Songmubucun",
    "wof:placetype":"locality"
},
  "geometry": {"coordinates":[123.66018,41.50834],"type":"Point"}
}