{
  "type": "Feature",
  "properties": {
    "gn:admin1_code":"18",
    "gn:asciiname":"Weijizhai",
    "gn:country_code":"CN",
    "gn:dem":1915,
    "gn:feature_class":"P",
    "gn:feature_code":"PPL",
    "gn:name":"Weijizhai",
    "gn:population":0,
    "gn:timezone":"Asia/Shanghai",
    "iso:country":"CN",
    "name:zho_x_preferred":[
        "\u5a01\u57fa\u5be8"
    ],
    "wof:name":"Weijizhai",
    "wof:placetype":"locality"
},
  "geometry": {"coordinates":[104.685,27.1845],"type":"Point"}
}