{
  "type": "Feature",
  "properties": {
    "gn:admin1_code":"8.0",
    "gn:asciiname":"Pingquan",
    "gn:country_code":"CN",
    "gn:dem":202,
    "gn:feature_class":"P",
    "gn:feature_code":"PPL",
    "gn:name":"Pingquan",
    "gn:population":0,
    "gn:timezone":"Asia/Shanghai",
    "iso:country":"CN",
    "name:zho_x_preferred":[
        "\u5e73\u6743"
    ],
    "wof:name":"Pingquan",
    "wof:placetype":"locality"
},
  "geometry": {"coordinates":[126.04300000000001,46.91407],"type":"Point"}
}