{
  "type": "Feature",
  "properties": {
    "gn:admin1_code":"32.0",
    "gn:asciiname":"Yongxincun",
    "gn:country_code":"CN",
    "gn:dem":754,
    "gn:feature_class":"P",
    "gn:feature_code":"PPL",
    "gn:name":"Yongxincun",
    "gn:population":0,
    "gn:timezone":"Asia/Shanghai",
    "iso:country":"CN",
    "name:zho_x_preferred":[
        "\u6c38\u65b0\u6751"
    ],
    "wof:name":"Yongxincun",
    "wof:placetype":"locality"
},
  "geometry": {"coordinates":[106.51375,32.34705],"type":"Point"}
}