{
  "type": "Feature",
  "properties": {
    "gn:admin1_code":"11.0",
    "gn:asciiname":"Zheguoping",
    "gn:country_code":"CN",
    "gn:dem":838,
    "gn:feature_class":"P",
    "gn:feature_code":"PPL",
    "gn:name":"Zheguoping",
    "gn:population":0,
    "gn:timezone":"Asia/Shanghai",
    "iso:country":"CN",
    "name:zho_x_preferred":[
        "\u8005\u679c\u576a"
    ],
    "wof:name":"Zheguoping",
    "wof:placetype":"locality"
},
  "geometry": {"coordinates":[109.4242,29.09289],"type":"Point"}
}