{
  "type": "Feature",
  "properties": {
    "gn:admin1_code":"29",
    "gn:asciiname":"Dashipu",
    "gn:country_code":"CN",
    "gn:dem":1873,
    "gn:feature_class":"P",
    "gn:feature_code":"PPL",
    "gn:name":"Dashipu",
    "gn:population":0,
    "gn:timezone":"Asia/Shanghai",
    "iso:country":"CN",
    "wof:name":"Dashipu",
    "wof:placetype":"locality"
},
  "geometry": {"coordinates":[101.4525,25.09333],"type":"Point"}
}