{
  "type": "Feature",
  "properties": {
    "gn:admin1_code":"10",
    "gn:asciiname":"Xizhuanchenghao",
    "gn:country_code":"CN",
    "gn:dem":301,
    "gn:feature_class":"P",
    "gn:feature_code":"PPL",
    "gn:name":"Xizhuanchenghao",
    "gn:population":0,
    "gn:timezone":"Asia/Shanghai",
    "iso:country":"CN",
    "name:zho_x_preferred":[
        "\u897f\u8f6c\u57ce\u53f7"
    ],
    "wof:name":"Xizhuanchenghao",
    "wof:placetype":"locality"
},
  "geometry": {"coordinates":[119.40568,40.43866],"type":"Point"}
}