{
  "type": "Feature",
  "properties": {
    "gn:admin1_code":"20.0",
    "gn:asciiname":"Dongbeigang",
    "gn:country_code":"CN",
    "gn:dem":231,
    "gn:feature_class":"P",
    "gn:feature_code":"PPL",
    "gn:name":"Dongbeigang",
    "gn:population":0,
    "gn:timezone":"Asia/Shanghai",
    "iso:country":"CN",
    "name:zho_x_preferred":[
        "\u4e1c\u5317\u5c97"
    ],
    "wof:name":"Dongbeigang",
    "wof:placetype":"locality"
},
  "geometry": {"coordinates":[124.41298,48.46115],"type":"Point"}
}