{
  "type": "Feature",
  "properties": {
    "gn:admin1_code":"29.0",
    "gn:asciiname":"Shangshiqiang",
    "gn:country_code":"CN",
    "gn:dem":1647,
    "gn:feature_class":"P",
    "gn:feature_code":"PPL",
    "gn:name":"Shangshiqiang",
    "gn:population":0,
    "gn:timezone":"Asia/Shanghai",
    "iso:country":"CN",
    "name:zho_x_preferred":[
        "\u4e0a\u77f3\u5899"
    ],
    "wof:name":"Shangshiqiang",
    "wof:placetype":"locality"
},
  "geometry": {"coordinates":[98.61620000000001,25.3689],"type":"Point"}
}