{
  "type": "Feature",
  "properties": {
    "gn:admin1_code":"8.0",
    "gn:asciiname":"Jilingcun",
    "gn:country_code":"CN",
    "gn:dem":345,
    "gn:feature_class":"P",
    "gn:feature_code":"PPL",
    "gn:name":"Jilingcun",
    "gn:population":0,
    "gn:timezone":"Asia/Shanghai",
    "iso:country":"CN",
    "name:zho_x_preferred":[
        "\u9e21\u5cad\u6751"
    ],
    "wof:name":"Jilingcun",
    "wof:placetype":"locality"
},
  "geometry": {"coordinates":[128.59654,47.02098],"type":"Point"}
}