{
  "type": "Feature",
  "properties": {
    "gn:admin1_code":"5.0",
    "gn:asciiname":"Zhaojiaduan",
    "gn:country_code":"CN",
    "gn:dem":147,
    "gn:feature_class":"P",
    "gn:feature_code":"PPL",
    "gn:name":"Zhaojiaduan",
    "gn:population":0,
    "gn:timezone":"Asia/Shanghai",
    "iso:country":"CN",
    "name:zho_x_preferred":[
        "\u8d75\u5bb6\u6bb5"
    ],
    "wof:name":"Zhaojiaduan",
    "wof:placetype":"locality"
},
  "geometry": {"coordinates":[122.81423999999998,45.44745],"type":"Point"}
}