{
  "type": "Feature",
  "properties": {
    "gn:admin1_code":"12.0",
    "gn:asciiname":"Jiangjiapo",
    "gn:country_code":"CN",
    "gn:dem":254,
    "gn:feature_class":"P",
    "gn:feature_code":"PPL",
    "gn:name":"Jiangjiapo",
    "gn:population":0,
    "gn:timezone":"Asia/Shanghai",
    "iso:country":"CN",
    "name:zho_x_preferred":[
        "\u59dc\u5bb6\u5761"
    ],
    "wof:name":"Jiangjiapo",
    "wof:placetype":"locality"
},
  "geometry": {"coordinates":[110.68357,32.8366],"type":"Point"}
}