{
  "type": "Feature",
  "properties": {
    "gn:admin1_code":"10",
    "gn:asciiname":"Nanliyuan",
    "gn:country_code":"CN",
    "gn:dem":384,
    "gn:feature_class":"P",
    "gn:feature_code":"PPL",
    "gn:name":"Nanliyuan",
    "gn:population":0,
    "gn:timezone":"Asia/Shanghai",
    "iso:country":"CN",
    "name:zho_x_preferred":[
        "\u5357\u68a8\u56ed"
    ],
    "wof:name":"Nanliyuan",
    "wof:placetype":"locality"
},
  "geometry": {"coordinates":[118.96944999999999,40.61078],"type":"Point"}
}