{
  "type": "Feature",
  "properties": {
    "gn:admin1_code":"11.0",
    "gn:asciiname":"Bantangzhai",
    "gn:country_code":"CN",
    "gn:dem":537,
    "gn:feature_class":"P",
    "gn:feature_code":"PPL",
    "gn:name":"Bantangzhai",
    "gn:population":0,
    "gn:timezone":"Asia/Shanghai",
    "iso:country":"CN",
    "name:zho_x_preferred":[
        "\u677f\u5858\u5be8"
    ],
    "wof:name":"Bantangzhai",
    "wof:placetype":"locality"
},
  "geometry": {"coordinates":[109.39892,28.47068],"type":"Point"}
}