{
  "type": "Feature",
  "properties": {
    "gn:admin1_code":"4.0",
    "gn:asciiname":"Xiaofengzhuang Liuzu",
    "gn:country_code":"CN",
    "gn:dem":6,
    "gn:feature_class":"P",
    "gn:feature_code":"PPLF",
    "gn:name":"Xiaofengzhuang Liuzu",
    "gn:population":0,
    "gn:timezone":"Asia/Shanghai",
    "iso:country":"CN",
    "name:zho_x_preferred":[
        "\u5c0f\u51af\u5e84\u516d\u7ec4"
    ],
    "wof:name":"Xiaofengzhuang Liuzu",
    "wof:placetype":"locality"
},
  "geometry": {"coordinates":[120.85778000000001,32.37277],"type":"Point"}
}