{
  "type": "Feature",
  "properties": {
    "gn:admin1_code":"5.0",
    "gn:asciiname":"Baihala",
    "gn:country_code":"CN",
    "gn:dem":136,
    "gn:feature_class":"P",
    "gn:feature_code":"PPL",
    "gn:name":"Baihala",
    "gn:population":0,
    "gn:timezone":"Asia/Shanghai",
    "iso:country":"CN",
    "name:zho_x_preferred":[
        "\u767d\u54c8\u62c9"
    ],
    "wof:name":"Baihala",
    "wof:placetype":"locality"
},
  "geometry": {"coordinates":[123.67328999999999,45.5511],"type":"Point"}
}