{
  "type": "Feature",
  "properties": {
    "gn:admin1_code":"7.0",
    "gn:asciiname":"Waixiaojing",
    "gn:country_code":"CN",
    "gn:dem":296,
    "gn:feature_class":"P",
    "gn:feature_code":"PPL",
    "gn:name":"Waixiaojing",
    "gn:population":0,
    "gn:timezone":"Asia/Shanghai",
    "iso:country":"CN",
    "name:und_x_variant":[
        "\u5916\u5c0f\u5f84"
    ],
    "name:zho_x_preferred":[
        "\u5916\u5c0f\u5f84"
    ],
    "wof:name":"Waixiaojing",
    "wof:placetype":"locality"
},
  "geometry": {"coordinates":[116.35431,25.51213],"type":"Point"}
}