{
  "type": "Feature",
  "properties": {
    "gn:admin1_code":"8.0",
    "gn:asciiname":"Shengwangcun",
    "gn:country_code":"CN",
    "gn:dem":194,
    "gn:feature_class":"P",
    "gn:feature_code":"PPL",
    "gn:name":"Shengwangcun",
    "gn:population":0,
    "gn:timezone":"Asia/Shanghai",
    "iso:country":"CN",
    "name:zho_x_preferred":[
        "\u80dc\u65fa\u6751"
    ],
    "wof:name":"Shengwangcun",
    "wof:placetype":"locality"
},
  "geometry": {"coordinates":[125.54572,45.78797],"type":"Point"}
}