{
  "type": "Feature",
  "properties": {
    "gn:admin1_code":"26.0",
    "gn:asciiname":"Shaxixiang",
    "gn:country_code":"CN",
    "gn:dem":581,
    "gn:feature_class":"P",
    "gn:feature_code":"PPL",
    "gn:name":"Shaxixiang",
    "gn:population":0,
    "gn:timezone":"Asia/Shanghai",
    "iso:country":"CN",
    "name:und_x_variant":[
        "\u6c99\u6eaa\u4e61"
    ],
    "wof:name":"Shaxixiang",
    "wof:placetype":"locality"
},
  "geometry": {"coordinates":[107.52967,33.08578],"type":"Point"}
}