{
  "type": "Feature",
  "properties": {
    "gn:admin1_code":"3",
    "gn:asciiname":"Changpu",
    "gn:country_code":"CN",
    "gn:dem":252,
    "gn:feature_class":"P",
    "gn:feature_code":"PPLA4",
    "gn:name":"Changpu",
    "gn:population":0,
    "gn:timezone":"Asia/Shanghai",
    "iso:country":"CN",
    "name:und_x_variant":[
        "Changpuxu",
        "Changpu",
        "Changpu Xiang"
    ],
    "name:zho_x_preferred":[
        "\u83d6\u84b2"
    ],
    "name:zho_x_variant":[
        "\u83d6\u84b2\u4e61"
    ],
    "wof:name":"Changpu",
    "wof:placetype":"locality"
},
  "geometry": {"coordinates":[115.52278,24.74178],"type":"Point"}
}