{
  "type": "Feature",
  "properties": {
    "gn:admin1_code":"10.0",
    "gn:asciiname":"Beigala",
    "gn:country_code":"CN",
    "gn:dem":517,
    "gn:feature_class":"P",
    "gn:feature_code":"PPL",
    "gn:name":"Beigala",
    "gn:population":0,
    "gn:timezone":"Asia/Shanghai",
    "iso:country":"CN",
    "name:zho_x_preferred":[
        "\u5317\u65ee\u65ef"
    ],
    "wof:name":"Beigala",
    "wof:placetype":"locality"
},
  "geometry": {"coordinates":[115.02593,39.30158],"type":"Point"}
}