{
  "type": "Feature",
  "properties": {
    "gn:admin1_code":"14.0",
    "gn:asciiname":"Gadugong",
    "gn:country_code":"CN",
    "gn:dem":3716,
    "gn:feature_class":"P",
    "gn:feature_code":"PPL",
    "gn:name":"Gadugong",
    "gn:population":0,
    "gn:timezone":"Asia/Urumqi",
    "iso:country":"CN",
    "name:zho_x_preferred":[
        "\u560e\u90fd\u516c"
    ],
    "wof:name":"Gadugong",
    "wof:placetype":"locality"
},
  "geometry": {"coordinates":[98.02813999999999,29.95372],"type":"Point"}
}