{
  "type": "Feature",
  "properties": {
    "gn:admin1_code":"16",
    "gn:asciiname":"Baicaoping",
    "gn:country_code":"CN",
    "gn:dem":169,
    "gn:feature_class":"P",
    "gn:feature_code":"PPL",
    "gn:name":"Baicaoping",
    "gn:population":0,
    "gn:timezone":"Asia/Shanghai",
    "iso:country":"CN",
    "name:zho_x_preferred":[
        "\u767d\u8349\u576a"
    ],
    "wof:name":"Baicaoping",
    "wof:placetype":"locality"
},
  "geometry": {"coordinates":[110.47,25.2128],"type":"Point"}
}