{
  "type": "Feature",
  "properties": {
    "gn:admin1_code":"26.0",
    "gn:asciiname":"Tianjiagoucun",
    "gn:country_code":"CN",
    "gn:dem":1162,
    "gn:feature_class":"P",
    "gn:feature_code":"PPL",
    "gn:name":"Tianjiagoucun",
    "gn:population":0,
    "gn:timezone":"Asia/Shanghai",
    "iso:country":"CN",
    "name:zho_x_preferred":[
        "\u7530\u5bb6\u6c9f\u6751"
    ],
    "wof:name":"Tianjiagoucun",
    "wof:placetype":"locality"
},
  "geometry": {"coordinates":[109.0742,36.42499],"type":"Point"}
}