{
  "type": "Feature",
  "properties": {
    "gn:admin1_code":"18",
    "gn:asciiname":"Qiaoma",
    "gn:country_code":"CN",
    "gn:dem":1079,
    "gn:feature_class":"P",
    "gn:feature_code":"PPL",
    "gn:name":"Qiaoma",
    "gn:population":0,
    "gn:timezone":"Asia/Shanghai",
    "iso:country":"CN",
    "wof:name":"Qiaoma",
    "wof:placetype":"locality"
},
  "geometry": {"coordinates":[105.65000000000001,24.95],"type":"Point"}
}