{
  "type": "Feature",
  "properties": {
    "gn:admin1_code":"10",
    "gn:asciiname":"Xinying",
    "gn:country_code":"CN",
    "gn:dem":1131,
    "gn:feature_class":"P",
    "gn:feature_code":"PPL",
    "gn:name":"Xinying",
    "gn:population":0,
    "gn:timezone":"Asia/Shanghai",
    "iso:country":"CN",
    "name:und_x_variant":[
        "Hsin-ying-tzu"
    ],
    "name:zho_x_preferred":[
        "\u8f9b\u8425"
    ],
    "wof:name":"Xinying",
    "wof:placetype":"locality"
},
  "geometry": {"coordinates":[116.1375,41.15694000000001],"type":"Point"}
}