{
  "type": "Feature",
  "properties": {
    "gn:admin1_code":"1.0",
    "gn:asciiname":"Hedazhuangcun",
    "gn:country_code":"CN",
    "gn:dem":42,
    "gn:feature_class":"P",
    "gn:feature_code":"PPL",
    "gn:name":"Hedazhuangcun",
    "gn:population":0,
    "gn:timezone":"Asia/Shanghai",
    "iso:country":"CN",
    "name:zho_x_preferred":[
        "\u4f55\u5927\u5e84\u6751"
    ],
    "wof:name":"Hedazhuangcun",
    "wof:placetype":"locality"
},
  "geometry": {"coordinates":[116.20761,32.04931],"type":"Point"}
}