{
  "type": "Feature",
  "properties": {
    "gn:admin1_code":"29.0",
    "gn:asciiname":"Ruidian",
    "gn:cc2":"CN",
    "gn:country_code":"CN",
    "gn:dem":1809,
    "gn:feature_class":"P",
    "gn:feature_code":"PPL",
    "gn:name":"Ruidian",
    "gn:population":0,
    "gn:timezone":"Asia/Shanghai",
    "iso:country":"CN",
    "name:und_x_variant":[
        "Diantan\u2019ai",
        "Tien-t\u2019an-ai",
        "Jui-tien",
        "Ruidian"
    ],
    "wof:name":"Ruidian",
    "wof:placetype":"locality"
},
  "geometry": {"coordinates":[98.45,25.48333],"type":"Point"}
}