{
  "type": "Feature",
  "properties": {
    "gn:admin1_code":"32.0",
    "gn:asciiname":"Siwa",
    "gn:country_code":"CN",
    "gn:dem":2797,
    "gn:feature_class":"P",
    "gn:feature_code":"PPL",
    "gn:name":"Siwa",
    "gn:population":0,
    "gn:timezone":"Asia/Shanghai",
    "iso:country":"CN",
    "name:zho_x_preferred":[
        "\u56db\u74e6"
    ],
    "wof:name":"Siwa",
    "wof:placetype":"locality"
},
  "geometry": {"coordinates":[103.23,31.8678],"type":"Point"}
}