{
  "type": "Feature",
  "properties": {
    "gn:admin1_code":"32.0",
    "gn:asciiname":"Siwa",
    "gn:country_code":"CN",
    "gn:dem":2797,
    "gn:feature_class":"P",
    "gn:feature_code":"PPL",
    "gn:name":"Siwa",
    "gn:population":0,
    "gn:timezone":"Asia/Shanghai",
    "iso:country":"CN",
    "name:cat_x_preferred":[
        "Siwa"
    ],
    "name:ceb_x_preferred":[
        "Siwa"
    ],
    "name:deu_x_preferred":[
        "Siwa"
    ],
    "name:fra_x_preferred":[
        "Siwa"
    ],
    "name:hun_x_preferred":[
        "Sziva"
    ],
    "name:ita_x_preferred":[
        "Siwa"
    ],
    "name:kat_x_preferred":[
        "\u10e1\u10d8\u10d5\u10d0"
    ],
    "name:kaz_x_preferred":[
        "\u0421\u0438\u0432\u0430 \u049b\u0430\u043b\u0430\u0441\u044b"
    ],
    "name:lat_x_preferred":[
        "Siwa"
    ],
    "name:nds_x_preferred":[
        "Siwa"
    ],
    "name:new_x_preferred":[
        "\u0936\u093f\u0935\u093e"
    ],
    "name:pol_x_preferred":[
        "Siwa"
    ],
    "name:rus_x_preferred":[
        "\u0421\u0438\u0432\u0430"
    ],
    "name:slk_x_preferred":[
        "Siwa"
    ],
    "name:swe_x_preferred":[
        "Siwa"
    ],
    "name:ukr_x_preferred":[
        "\u0421\u0456\u0432\u0430"
    ],
    "name:zho_x_preferred":[
        "\u56db\u74e6"
    ],
    "wof:name":"Siwa",
    "wof:placetype":"locality"
},
  "geometry": {"coordinates":[103.23,31.8678],"type":"Point"}
}