{
  "type": "Feature",
  "properties": {
    "gn:admin1_code":"14.0",
    "gn:asciiname":"Shangricun",
    "gn:country_code":"CN",
    "gn:dem":3827,
    "gn:feature_class":"P",
    "gn:feature_code":"PPL",
    "gn:name":"Shangricun",
    "gn:population":0,
    "gn:timezone":"Asia/Urumqi",
    "iso:country":"CN",
    "name:zho_x_preferred":[
        "\u5c1a\u65e5\u6751"
    ],
    "wof:name":"Shangricun",
    "wof:placetype":"locality"
},
  "geometry": {"coordinates":[90.18071,29.45364],"type":"Point"}
}