{
  "type": "Feature",
  "properties": {
    "gn:admin1_code":"7.0",
    "gn:asciiname":"Xiamingyang",
    "gn:country_code":"CN",
    "gn:dem":884,
    "gn:feature_class":"P",
    "gn:feature_code":"PPL",
    "gn:name":"Xiamingyang",
    "gn:population":0,
    "gn:timezone":"Asia/Shanghai",
    "iso:country":"CN",
    "name:und_x_variant":[
        "\u4e0b\u660e\u6d0b"
    ],
    "name:zho_x_preferred":[
        "\u4e0b\u660e\u6d0b"
    ],
    "wof:name":"Xiamingyang",
    "wof:placetype":"locality"
},
  "geometry": {"coordinates":[118.40321000000002,26.68334],"type":"Point"}
}