{
  "type": "Feature",
  "properties": {
    "gn:admin1_code":"10",
    "gn:asciiname":"Lijiadonggou",
    "gn:country_code":"CN",
    "gn:dem":590,
    "gn:feature_class":"P",
    "gn:feature_code":"PPL",
    "gn:name":"Lijiadonggou",
    "gn:population":0,
    "gn:timezone":"Asia/Shanghai",
    "iso:country":"CN",
    "name:zho_x_preferred":[
        "\u674e\u5bb6\u4e1c\u6c9f"
    ],
    "wof:name":"Lijiadonggou",
    "wof:placetype":"locality"
},
  "geometry": {"coordinates":[117.73711000000002,40.52371],"type":"Point"}
}