{
  "type": "Feature",
  "properties": {
    "gn:admin1_code":"32.0",
    "gn:asciiname":"Xiazhulinwan",
    "gn:country_code":"CN",
    "gn:dem":751,
    "gn:feature_class":"P",
    "gn:feature_code":"PPL",
    "gn:name":"Xiazhulinwan",
    "gn:population":0,
    "gn:timezone":"Asia/Shanghai",
    "iso:country":"CN",
    "name:zho_x_preferred":[
        "\u4e0b\u7af9\u6797\u6e7e"
    ],
    "wof:name":"Xiazhulinwan",
    "wof:placetype":"locality"
},
  "geometry": {"coordinates":[105.74087,32.16444],"type":"Point"}
}