{
  "type": "Feature",
  "properties": {
    "gn:admin1_code":"19.0",
    "gn:asciiname":"Xintingcun",
    "gn:country_code":"CN",
    "gn:dem":197,
    "gn:feature_class":"P",
    "gn:feature_code":"PPL",
    "gn:name":"Xintingcun",
    "gn:population":0,
    "gn:timezone":"Asia/Shanghai",
    "iso:country":"CN",
    "name:zho_x_preferred":[
        "\u65b0\u4ead\u6751"
    ],
    "wof:name":"Xintingcun",
    "wof:placetype":"locality"
},
  "geometry": {"coordinates":[120.5253,41.71237],"type":"Point"}
}