{
  "type": "Feature",
  "properties": {
    "gn:admin1_code":"14.0",
    "gn:asciiname":"Munaikema",
    "gn:country_code":"CN",
    "gn:dem":4737,
    "gn:feature_class":"P",
    "gn:feature_code":"PPL",
    "gn:name":"Munaikema",
    "gn:population":0,
    "gn:timezone":"Asia/Urumqi",
    "iso:country":"CN",
    "name:bod_x_preferred":[
        "Mun\u00eakaimar"
    ],
    "name:zho_x_preferred":[
        "Munaikema"
    ],
    "name:zho_x_variant":[
        "\u6728\u4e43\u514b\u739b",
        "Buqu Gongshe",
        "\u5e03\u66f2\u516c\u793e"
    ],
    "wof:name":"Munaikema",
    "wof:placetype":"locality"
},
  "geometry": {"coordinates":[93.20099999999999,33.001],"type":"Point"}
}