{
  "type": "Feature",
  "properties": {
    "gn:admin1_code":"19.0",
    "gn:asciiname":"Huahonggou",
    "gn:country_code":"CN",
    "gn:dem":152,
    "gn:feature_class":"P",
    "gn:feature_code":"PPL",
    "gn:name":"Huahonggou",
    "gn:population":0,
    "gn:timezone":"Asia/Shanghai",
    "iso:country":"CN",
    "name:und_x_variant":[
        "\u82b1\u7ea2\u6c9f"
    ],
    "wof:name":"Huahonggou",
    "wof:placetype":"locality"
},
  "geometry": {"coordinates":[122.96622000000001,40.8462],"type":"Point"}
}