{
  "type": "Feature",
  "properties": {
    "gn:admin1_code":"11.0",
    "gn:asciiname":"Tujia Wuchang",
    "gn:country_code":"CN",
    "gn:dem":36,
    "gn:feature_class":"P",
    "gn:feature_code":"PPL",
    "gn:name":"Tujia Wuchang",
    "gn:population":0,
    "gn:timezone":"Asia/Shanghai",
    "iso:country":"CN",
    "name:zho_x_preferred":[
        "\u6d82\u5bb6\u5c4b\u573a"
    ],
    "wof:name":"Tujia Wuchang",
    "wof:placetype":"locality"
},
  "geometry": {"coordinates":[112.95218,27.89669],"type":"Point"}
}