{
  "type": "Feature",
  "properties": {
    "gn:admin1_code":"19",
    "gn:asciiname":"Yuji",
    "gn:cc2":"CN",
    "gn:country_code":"CN",
    "gn:dem":33,
    "gn:feature_class":"P",
    "gn:feature_code":"PPL",
    "gn:name":"Yuji",
    "gn:population":0,
    "gn:timezone":"Asia/Shanghai",
    "iso:country":"CN",
    "name:und_x_variant":[
        "Jiyu",
        "Yuji Zhen",
        "Y\u00fc-chia-t\u2019un",
        "Yuji"
    ],
    "wof:name":"Yuji",
    "wof:placetype":"locality"
},
  "geometry": {"coordinates":[121.28417,41.29639],"type":"Point"}
}