{
  "type": "Feature",
  "properties": {
    "gn:admin1_code":"29.0",
    "gn:asciiname":"Langwaihe",
    "gn:country_code":"CN",
    "gn:dem":1053,
    "gn:feature_class":"P",
    "gn:feature_code":"PPL",
    "gn:name":"Langwaihe",
    "gn:population":0,
    "gn:timezone":"Asia/Shanghai",
    "iso:country":"CN",
    "name:zho_x_preferred":[
        "\u6717\u5916\u6cb3"
    ],
    "wof:name":"Langwaihe",
    "wof:placetype":"locality"
},
  "geometry": {"coordinates":[98.1473,24.906],"type":"Point"}
}