{
  "type": "Feature",
  "properties": {
    "gn:admin1_code":"26.0",
    "gn:asciiname":"Yaodianzi",
    "gn:country_code":"CN",
    "gn:dem":1531,
    "gn:feature_class":"P",
    "gn:feature_code":"PPL",
    "gn:name":"Yaodianzi",
    "gn:population":0,
    "gn:timezone":"Asia/Shanghai",
    "iso:country":"CN",
    "name:und_x_variant":[
        "\u8170\u5e97\u5b50"
    ],
    "wof:name":"Yaodianzi",
    "wof:placetype":"locality"
},
  "geometry": {"coordinates":[106.66509000000001,33.7828],"type":"Point"}
}