{
  "type": "Feature",
  "properties": {
    "gn:admin1_code":"15.0",
    "gn:asciiname":"Shixia",
    "gn:country_code":"CN",
    "gn:dem":2075,
    "gn:feature_class":"P",
    "gn:feature_code":"PPL",
    "gn:name":"Shixia",
    "gn:population":0,
    "gn:timezone":"Asia/Shanghai",
    "iso:country":"CN",
    "name:deu_x_preferred":[
        "Shixia"
    ],
    "name:zho_x_preferred":[
        "\u77f3\u5ce1"
    ],
    "wof:name":"Shixia",
    "wof:placetype":"locality"
},
  "geometry": {"coordinates":[103.80500000000001,37.469],"type":"Point"}
}