{
  "type": "Feature",
  "properties": {
    "gn:admin1_code":"3.0",
    "gn:asciiname":"Hongyi",
    "gn:country_code":"CN",
    "gn:dem":72,
    "gn:feature_class":"P",
    "gn:feature_code":"PPLA4",
    "gn:name":"Hongyi",
    "gn:population":0,
    "gn:timezone":"Asia/Shanghai",
    "iso:country":"CN",
    "name:und_x_variant":[
        "\u6d2a\u4e00",
        "Hongyi Xiang",
        "\u6d2a\u4e00\u4e61"
    ],
    "wof:name":"Hongyi",
    "wof:placetype":"locality"
},
  "geometry": {"coordinates":[115.19879,29.62357],"type":"Point"}
}