{
  "type": "Feature",
  "properties": {
    "gn:admin1_code":"11",
    "gn:asciiname":"Qiaokou",
    "gn:cc2":"CN",
    "gn:country_code":"CN",
    "gn:dem":154,
    "gn:feature_class":"P",
    "gn:feature_code":"PPL",
    "gn:name":"Qiaokou",
    "gn:population":0,
    "gn:timezone":"Asia/Shanghai",
    "iso:country":"CN",
    "name:und_x_variant":[
        "Ch\u2019iao-k\u2019ou",
        "Ch\u2019iao-k\u2019ou-hs\u00fc",
        "Qiaokou"
    ],
    "wof:name":"Qiaokou",
    "wof:placetype":"locality"
},
  "geometry": {"coordinates":[113.18333,25.91167],"type":"Point"}
}