{
  "type": "Feature",
  "properties": {
    "gn:admin1_code":"11.0",
    "gn:asciiname":"Cuoshuilong",
    "gn:country_code":"CN",
    "gn:dem":179,
    "gn:feature_class":"P",
    "gn:feature_code":"PPL",
    "gn:name":"Cuoshuilong",
    "gn:population":0,
    "gn:timezone":"Asia/Shanghai",
    "iso:country":"CN",
    "name:zho_x_preferred":[
        "\u9509\u6c34\u5785"
    ],
    "wof:name":"Cuoshuilong",
    "wof:placetype":"locality"
},
  "geometry": {"coordinates":[109.83382,27.84615],"type":"Point"}
}