{
  "type": "Feature",
  "properties": {
    "gn:admin1_code":"26.0",
    "gn:asciiname":"Shaokeyuan",
    "gn:country_code":"CN",
    "gn:dem":1192,
    "gn:feature_class":"P",
    "gn:feature_code":"PPL",
    "gn:name":"Shaokeyuan",
    "gn:population":0,
    "gn:timezone":"Asia/Shanghai",
    "iso:country":"CN",
    "name:zho_x_preferred":[
        "\u70e7\u79d1\u9662"
    ],
    "wof:name":"Shaokeyuan",
    "wof:placetype":"locality"
},
  "geometry": {"coordinates":[109.15831,35.7854],"type":"Point"}
}