{
  "type": "Feature",
  "properties": {
    "gn:admin1_code":"1.0",
    "gn:asciiname":"Kangwangcun",
    "gn:country_code":"CN",
    "gn:dem":41,
    "gn:feature_class":"P",
    "gn:feature_code":"PPL",
    "gn:name":"Kangwangcun",
    "gn:population":0,
    "gn:timezone":"Asia/Shanghai",
    "iso:country":"CN",
    "name:zho_x_preferred":[
        "\u5eb7\u738b\u6751"
    ],
    "wof:name":"Kangwangcun",
    "wof:placetype":"locality"
},
  "geometry": {"coordinates":[115.75732000000001,33.89621],"type":"Point"}
}