{
  "type": "Feature",
  "properties": {
    "gn:admin1_code":"18",
    "gn:asciiname":"Dongsang",
    "gn:country_code":"CN",
    "gn:dem":776,
    "gn:feature_class":"P",
    "gn:feature_code":"PPL",
    "gn:name":"Dongsang",
    "gn:population":0,
    "gn:timezone":"Asia/Shanghai",
    "iso:country":"CN",
    "name:zho_x_preferred":[
        "\u61c2\u6851"
    ],
    "wof:name":"Dongsang",
    "wof:placetype":"locality"
},
  "geometry": {"coordinates":[106.02800000000001,25.7135],"type":"Point"}
}