{
  "type": "Feature",
  "properties": {
    "gn:admin1_code":"8.0",
    "gn:asciiname":"Xiaochengzicun",
    "gn:country_code":"CN",
    "gn:dem":126,
    "gn:feature_class":"P",
    "gn:feature_code":"PPL",
    "gn:name":"Xiaochengzicun",
    "gn:population":0,
    "gn:timezone":"Asia/Shanghai",
    "iso:country":"CN",
    "name:zho_x_preferred":[
        "\u5c0f\u57ce\u5b50\u6751"
    ],
    "wof:name":"Xiaochengzicun",
    "wof:placetype":"locality"
},
  "geometry": {"coordinates":[125.28979,45.46267],"type":"Point"}
}