{
  "type": "Feature",
  "properties": {
    "gn:admin1_code":"18",
    "gn:asciiname":"Yaoshang",
    "gn:country_code":"CN",
    "gn:dem":1616,
    "gn:feature_class":"P",
    "gn:feature_code":"PPL",
    "gn:name":"Yaoshang",
    "gn:population":0,
    "gn:timezone":"Asia/Shanghai",
    "iso:country":"CN",
    "name:zho_x_preferred":[
        "\u7a91\u4e0a"
    ],
    "wof:name":"Yaoshang",
    "wof:placetype":"locality"
},
  "geometry": {"coordinates":[105.508,25.852],"type":"Point"}
}