{
  "type": "Feature",
  "properties": {
    "gn:admin1_code":"24.0",
    "gn:asciiname":"Nanqianggan",
    "gn:country_code":"CN",
    "gn:dem":1647,
    "gn:feature_class":"P",
    "gn:feature_code":"PPL",
    "gn:name":"Nanqianggan",
    "gn:population":0,
    "gn:timezone":"Asia/Shanghai",
    "iso:country":"CN",
    "name:zho_x_preferred":[
        "\u5357\u67aa\u6746"
    ],
    "wof:name":"Nanqianggan",
    "wof:placetype":"locality"
},
  "geometry": {"coordinates":[112.2538,38.41729],"type":"Point"}
}