{
  "type": "Feature",
  "properties": {
    "gn:admin1_code":"2.0",
    "gn:asciiname":"Xiangxiaqiao",
    "gn:country_code":"CN",
    "gn:dem":629,
    "gn:feature_class":"P",
    "gn:feature_code":"PPL",
    "gn:name":"Xiangxiaqiao",
    "gn:population":0,
    "gn:timezone":"Asia/Shanghai",
    "iso:country":"CN",
    "name:zho_x_preferred":[
        "\u9999\u4e0b\u6865"
    ],
    "wof:name":"Xiangxiaqiao",
    "wof:placetype":"locality"
},
  "geometry": {"coordinates":[119.37841,28.21229000000001],"type":"Point"}
}