{
  "type": "Feature",
  "properties": {
    "gn:admin1_code":"18",
    "gn:asciiname":"Daojiao",
    "gn:country_code":"CN",
    "gn:dem":841,
    "gn:feature_class":"P",
    "gn:feature_code":"PPL",
    "gn:name":"Daojiao",
    "gn:population":0,
    "gn:timezone":"Asia/Shanghai",
    "iso:country":"CN",
    "name:zho_x_preferred":[
        "\u9053\u89d2"
    ],
    "wof:name":"Daojiao",
    "wof:placetype":"locality"
},
  "geometry": {"coordinates":[107.51900000000001,28.2889],"type":"Point"}
}