{
  "type": "Feature",
  "properties": {
    "gn:admin1_code":"11.0",
    "gn:asciiname":"Shangwuchou",
    "gn:country_code":"CN",
    "gn:dem":47,
    "gn:feature_class":"P",
    "gn:feature_code":"PPL",
    "gn:name":"Shangwuchou",
    "gn:population":0,
    "gn:timezone":"Asia/Shanghai",
    "iso:country":"CN",
    "name:zho_x_preferred":[
        "\u4e0a\u5c4b\u4ec7"
    ],
    "wof:name":"Shangwuchou",
    "wof:placetype":"locality"
},
  "geometry": {"coordinates":[113.08409,28.74789],"type":"Point"}
}