{
  "type": "Feature",
  "properties": {
    "gn:admin1_code":"21.0",
    "gn:asciiname":"Yujiabu",
    "gn:country_code":"CN",
    "gn:dem":1538,
    "gn:feature_class":"P",
    "gn:feature_code":"PPL",
    "gn:name":"Yujiabu",
    "gn:population":0,
    "gn:timezone":"Asia/Shanghai",
    "iso:country":"CN",
    "name:und_x_variant":[
        "\u4f59\u5bb6\u5821"
    ],
    "name:zho_x_preferred":[
        "\u4f59\u5bb6\u5821"
    ],
    "wof:name":"Yujiabu",
    "wof:placetype":"locality"
},
  "geometry": {"coordinates":[106.10072,36.46043],"type":"Point"}
}