{
  "type": "Feature",
  "properties": {
    "gn:admin1_code":"9.0",
    "gn:asciiname":"Laohudian",
    "gn:country_code":"CN",
    "gn:dem":124,
    "gn:feature_class":"P",
    "gn:feature_code":"PPL",
    "gn:name":"Laohudian",
    "gn:population":0,
    "gn:timezone":"Asia/Shanghai",
    "iso:country":"CN",
    "name:zho_x_preferred":[
        "\u8001\u864e\u5e97"
    ],
    "wof:name":"Laohudian",
    "wof:placetype":"locality"
},
  "geometry": {"coordinates":[114.1789,31.96954],"type":"Point"}
}