{
  "type": "Feature",
  "properties": {
    "gn:admin1_code":"21.0",
    "gn:asciiname":"Yangjizhai",
    "gn:country_code":"CN",
    "gn:dem":1411,
    "gn:feature_class":"P",
    "gn:feature_code":"PPL",
    "gn:name":"Yangjizhai",
    "gn:population":0,
    "gn:timezone":"Asia/Shanghai",
    "iso:country":"CN",
    "name:zho_x_preferred":[
        "\u6768\u8bb0\u5be8"
    ],
    "wof:name":"Yangjizhai",
    "wof:placetype":"locality"
},
  "geometry": {"coordinates":[107.47,37.8231],"type":"Point"}
}