{
  "type": "Feature",
  "properties": {
    "gn:admin1_code":"8.0",
    "gn:asciiname":"Laodesheng",
    "gn:country_code":"CN",
    "gn:dem":157,
    "gn:feature_class":"P",
    "gn:feature_code":"PPL",
    "gn:name":"Laodesheng",
    "gn:population":0,
    "gn:timezone":"Asia/Shanghai",
    "iso:country":"CN",
    "name:zho_x_preferred":[
        "\u6d9d\u5f97\u80dc"
    ],
    "wof:name":"Laodesheng",
    "wof:placetype":"locality"
},
  "geometry": {"coordinates":[125.21377,45.99386],"type":"Point"}
}