{
  "type": "Feature",
  "properties": {
    "gn:admin1_code":"32.0",
    "gn:asciiname":"Jijia",
    "gn:country_code":"CN",
    "gn:dem":3980,
    "gn:feature_class":"P",
    "gn:feature_code":"PPL",
    "gn:name":"Jijia",
    "gn:population":0,
    "gn:timezone":"Asia/Shanghai",
    "iso:country":"CN",
    "name:zho_x_preferred":[
        "\u5409\u7532"
    ],
    "wof:name":"Jijia",
    "wof:placetype":"locality"
},
  "geometry": {"coordinates":[100.94538,30.8604],"type":"Point"}
}