{
  "type": "Feature",
  "properties": {
    "gn:admin1_code":"12.0",
    "gn:asciiname":"Zhanggou",
    "gn:country_code":"CN",
    "gn:dem":31,
    "gn:feature_class":"P",
    "gn:feature_code":"PPLA4",
    "gn:name":"Zhanggou",
    "gn:population":0,
    "gn:timezone":"Asia/Shanghai",
    "iso:country":"CN",
    "name:und_x_variant":[
        "Zhanggou Zhen"
    ],
    "name:zho_x_preferred":[
        "\u5f20\u6c9f"
    ],
    "name:zho_x_variant":[
        "\u5f20\u6c9f\u9547"
    ],
    "wof:name":"Zhanggou",
    "wof:placetype":"locality"
},
  "geometry": {"coordinates":[113.37264,30.24953],"type":"Point"}
}