{
  "type": "Feature",
  "properties": {
    "gn:admin1_code":"8.0",
    "gn:asciiname":"Guanglecun",
    "gn:country_code":"CN",
    "gn:dem":182,
    "gn:feature_class":"P",
    "gn:feature_code":"PPL",
    "gn:name":"Guanglecun",
    "gn:population":0,
    "gn:timezone":"Asia/Shanghai",
    "iso:country":"CN",
    "name:zho_x_preferred":[
        "\u5149\u4e50\u6751"
    ],
    "wof:name":"Guanglecun",
    "wof:placetype":"locality"
},
  "geometry": {"coordinates":[127.07238,46.46124],"type":"Point"}
}