{
  "type": "Feature",
  "properties": {
    "gn:admin1_code":"19.0",
    "gn:asciiname":"Jujiajie",
    "gn:country_code":"CN",
    "gn:dem":86,
    "gn:feature_class":"P",
    "gn:feature_code":"PPL",
    "gn:name":"Jujiajie",
    "gn:population":0,
    "gn:timezone":"Asia/Shanghai",
    "iso:country":"CN",
    "name:zho_x_preferred":[
        "\u97a0\u5bb6\u8857"
    ],
    "wof:name":"Jujiajie",
    "wof:placetype":"locality"
},
  "geometry": {"coordinates":[124.65661,40.48363],"type":"Point"}
}