{
  "type": "Feature",
  "properties": {
    "gn:admin1_code":"5.0",
    "gn:asciiname":"Shaode Wopeng",
    "gn:country_code":"CN",
    "gn:dem":139,
    "gn:feature_class":"P",
    "gn:feature_code":"PPL",
    "gn:name":"Shaode Wopeng",
    "gn:population":0,
    "gn:timezone":"Asia/Shanghai",
    "iso:country":"CN",
    "name:zho_x_preferred":[
        "\u90b5\u5f97\u7a9d\u68da"
    ],
    "wof:name":"Shaode Wopeng",
    "wof:placetype":"locality"
},
  "geometry": {"coordinates":[123.57002,45.66024],"type":"Point"}
}