{
  "type": "Feature",
  "properties": {
    "gn:admin1_code":"12.0",
    "gn:asciiname":"Zhongduan",
    "gn:country_code":"CN",
    "gn:dem":262,
    "gn:feature_class":"P",
    "gn:feature_code":"PPL",
    "gn:name":"Zhongduan",
    "gn:population":0,
    "gn:timezone":"Asia/Shanghai",
    "iso:country":"CN",
    "name:zho_x_preferred":[
        "\u4e2d\u5845"
    ],
    "wof:name":"Zhongduan",
    "wof:placetype":"locality"
},
  "geometry": {"coordinates":[113.74139,29.07861],"type":"Point"}
}