{
  "type": "Feature",
  "properties": {
    "gn:admin1_code":"3.0",
    "gn:asciiname":"Yuejiazhuang",
    "gn:country_code":"CN",
    "gn:dem":909,
    "gn:feature_class":"P",
    "gn:feature_code":"PPL",
    "gn:name":"Yuejiazhuang",
    "gn:population":0,
    "gn:timezone":"Asia/Shanghai",
    "iso:country":"CN",
    "name:und_x_variant":[
        "\u5cb3\u5bb6\u5e84"
    ],
    "wof:name":"Yuejiazhuang",
    "wof:placetype":"locality"
},
  "geometry": {"coordinates":[116.27221000000002,27.23189],"type":"Point"}
}