{
  "type": "Feature",
  "properties": {
    "gn:admin1_code":"16",
    "gn:asciiname":"Chenping",
    "gn:country_code":"CN",
    "gn:dem":298,
    "gn:feature_class":"P",
    "gn:feature_code":"PPL",
    "gn:name":"Chenping",
    "gn:population":0,
    "gn:timezone":"Asia/Shanghai",
    "iso:country":"CN",
    "wof:name":"Chenping",
    "wof:placetype":"locality"
},
  "geometry": {"coordinates":[108.78333000000001,23.03333],"type":"Point"}
}