{
  "type": "Feature",
  "properties": {
    "gn:admin1_code":"1.0",
    "gn:asciiname":"Rongxi",
    "gn:country_code":"CN",
    "gn:dem":237,
    "gn:feature_class":"P",
    "gn:feature_code":"PPL",
    "gn:name":"Rongxi",
    "gn:population":0,
    "gn:timezone":"Asia/Shanghai",
    "iso:country":"CN",
    "name:zho_x_preferred":[
        "\u5bb9\u6eaa"
    ],
    "wof:name":"Rongxi",
    "wof:placetype":"locality"
},
  "geometry": {"coordinates":[118.26132,29.91168],"type":"Point"}
}