{
  "type": "Feature",
  "properties": {
    "gn:admin1_code":"9.0",
    "gn:asciiname":"Baijigou",
    "gn:country_code":"CN",
    "gn:dem":291,
    "gn:feature_class":"P",
    "gn:feature_code":"PPL",
    "gn:name":"Baijigou",
    "gn:population":0,
    "gn:timezone":"Asia/Shanghai",
    "iso:country":"CN",
    "name:zho_x_preferred":[
        "\u767d\u9e21\u6c9f"
    ],
    "wof:name":"Baijigou",
    "wof:placetype":"locality"
},
  "geometry": {"coordinates":[114.33153,31.79977],"type":"Point"}
}