{
  "type": "Feature",
  "properties": {
    "gn:admin1_code":"20.0",
    "gn:asciiname":"Houmadengqian",
    "gn:country_code":"CN",
    "gn:dem":182,
    "gn:feature_class":"P",
    "gn:feature_code":"PPL",
    "gn:name":"Houmadengqian",
    "gn:population":0,
    "gn:timezone":"Asia/Shanghai",
    "iso:country":"CN",
    "name:zho_x_preferred":[
        "\u540e\u9a6c\u767b\u6d45"
    ],
    "wof:name":"Houmadengqian",
    "wof:placetype":"locality"
},
  "geometry": {"coordinates":[124.49231,48.32391],"type":"Point"}
}