{
  "type": "Feature",
  "properties": {
    "gn:admin1_code":"25",
    "gn:asciiname":"Wangzepu",
    "gn:country_code":"CN",
    "gn:dem":54,
    "gn:feature_class":"P",
    "gn:feature_code":"PPL",
    "gn:name":"Wangzepu",
    "gn:population":0,
    "gn:timezone":"Asia/Shanghai",
    "iso:country":"CN",
    "name:zho_x_preferred":[
        "\u738b\u6cfd\u94fa"
    ],
    "wof:name":"Wangzepu",
    "wof:placetype":"locality"
},
  "geometry": {"coordinates":[115.41800000000001,34.8806],"type":"Point"}
}