{
  "type": "Feature",
  "properties": {
    "gn:admin1_code":"2.0",
    "gn:asciiname":"Huangzuitou",
    "gn:country_code":"CN",
    "gn:dem":74,
    "gn:feature_class":"P",
    "gn:feature_code":"PPL",
    "gn:name":"Huangzuitou",
    "gn:population":0,
    "gn:timezone":"Asia/Shanghai",
    "iso:country":"CN",
    "name:zho_x_preferred":[
        "\u9ec4\u5634\u5934"
    ],
    "wof:name":"Huangzuitou",
    "wof:placetype":"locality"
},
  "geometry": {"coordinates":[122.21702000000001,30.33108],"type":"Point"}
}