{
  "type": "Feature",
  "properties": {
    "gn:admin1_code":"15.0",
    "gn:asciiname":"Heihuya",
    "gn:country_code":"CN",
    "gn:dem":2112,
    "gn:feature_class":"P",
    "gn:feature_code":"PPL",
    "gn:name":"Heihuya",
    "gn:population":0,
    "gn:timezone":"Asia/Shanghai",
    "iso:country":"CN",
    "name:zho_x_preferred":[
        "\u9ed1\u864e\u5d16"
    ],
    "wof:name":"Heihuya",
    "wof:placetype":"locality"
},
  "geometry": {"coordinates":[105.06413999999999,33.56863],"type":"Point"}
}