{
  "type": "Feature",
  "properties": {
    "gn:admin1_code":"32.0",
    "gn:asciiname":"Luojianpo",
    "gn:country_code":"CN",
    "gn:dem":452,
    "gn:feature_class":"P",
    "gn:feature_code":"PPL",
    "gn:name":"Luojianpo",
    "gn:population":0,
    "gn:timezone":"Asia/Shanghai",
    "iso:country":"CN",
    "name:zho_x_preferred":[
        "\u843d\u7bad\u5761"
    ],
    "wof:name":"Luojianpo",
    "wof:placetype":"locality"
},
  "geometry": {"coordinates":[107.10388,31.3933],"type":"Point"}
}