{
  "type": "Feature",
  "properties": {
    "gn:admin1_code":"26",
    "gn:asciiname":"Chenjia'ao",
    "gn:country_code":"CN",
    "gn:dem":807,
    "gn:feature_class":"P",
    "gn:feature_code":"PPL",
    "gn:name":"Chenjia\u2019ao",
    "gn:population":0,
    "gn:timezone":"Asia/Shanghai",
    "iso:country":"CN",
    "name:und_x_variant":[
        "Chenjia\u2019ao",
        "\u9648\u5bb6\u5773"
    ],
    "name:zho_x_preferred":[
        "\u9648\u5bb6\u5773"
    ],
    "wof:name":"Chenjia'ao",
    "wof:placetype":"locality"
},
  "geometry": {"coordinates":[108.2625,34.5875],"type":"Point"}
}