{
  "type": "Feature",
  "properties": {
    "gn:admin1_code":"8.0",
    "gn:asciiname":"Liangjingzitun",
    "gn:country_code":"CN",
    "gn:dem":163,
    "gn:feature_class":"P",
    "gn:feature_code":"PPL",
    "gn:name":"Liangjingzitun",
    "gn:population":0,
    "gn:timezone":"Asia/Shanghai",
    "iso:country":"CN",
    "name:zho_x_preferred":[
        "\u4e24\u4e95\u5b50\u5c6f"
    ],
    "wof:name":"Liangjingzitun",
    "wof:placetype":"locality"
},
  "geometry": {"coordinates":[123.00855,46.56353],"type":"Point"}
}