{
  "type": "Feature",
  "properties": {
    "gn:admin1_code":"5.0",
    "gn:asciiname":"Lizhitun",
    "gn:country_code":"CN",
    "gn:dem":160,
    "gn:feature_class":"P",
    "gn:feature_code":"PPL",
    "gn:name":"Lizhitun",
    "gn:population":0,
    "gn:timezone":"Asia/Shanghai",
    "iso:country":"CN",
    "name:zho_x_preferred":[
        "\u7acb\u5fd7\u5c6f"
    ],
    "wof:name":"Lizhitun",
    "wof:placetype":"locality"
},
  "geometry": {"coordinates":[122.53203000000001,44.26332],"type":"Point"}
}