{
  "type": "Feature",
  "properties": {
    "gn:admin1_code":"32.0",
    "gn:asciiname":"Miaogouwan",
    "gn:country_code":"CN",
    "gn:dem":457,
    "gn:feature_class":"P",
    "gn:feature_code":"PPL",
    "gn:name":"Miaogouwan",
    "gn:population":0,
    "gn:timezone":"Asia/Shanghai",
    "iso:country":"CN",
    "name:zho_x_preferred":[
        "\u5e99\u6c9f\u6e7e"
    ],
    "wof:name":"Miaogouwan",
    "wof:placetype":"locality"
},
  "geometry": {"coordinates":[105.56152,31.08107],"type":"Point"}
}