{
  "type": "Feature",
  "properties": {
    "gn:admin1_code":"25.0",
    "gn:asciiname":"Donglaotai",
    "gn:country_code":"CN",
    "gn:dem":9,
    "gn:feature_class":"P",
    "gn:feature_code":"PPL",
    "gn:name":"Donglaotai",
    "gn:population":0,
    "gn:timezone":"Asia/Shanghai",
    "iso:country":"CN",
    "name:zho_x_preferred":[
        "\u4e1c\u6d9d\u53f0"
    ],
    "wof:name":"Donglaotai",
    "wof:placetype":"locality"
},
  "geometry": {"coordinates":[122.05294000000001,37.5087],"type":"Point"}
}