{
  "type": "Feature",
  "properties": {
    "gn:admin1_code":"25.0",
    "gn:asciiname":"Lucun",
    "gn:country_code":"CN",
    "gn:dem":48,
    "gn:feature_class":"P",
    "gn:feature_code":"PPL",
    "gn:name":"L\u00fccun",
    "gn:population":0,
    "gn:timezone":"Asia/Shanghai",
    "iso:country":"CN",
    "name:und_x_variant":[
        "L\u00fccun"
    ],
    "name:zho_x_preferred":[
        "\u5415\u6751"
    ],
    "wof:name":"Lucun",
    "wof:placetype":"locality"
},
  "geometry": {"coordinates":[120.09453000000001,37.25653],"type":"Point"}
}