{
  "type": "Feature",
  "properties": {
    "gn:admin1_code":"19.0",
    "gn:asciiname":"Nanhai",
    "gn:country_code":"CN",
    "gn:dem":6,
    "gn:feature_class":"P",
    "gn:feature_code":"PPL",
    "gn:name":"Nanhai",
    "gn:population":0,
    "gn:timezone":"Asia/Shanghai",
    "iso:country":"CN",
    "name:deu_x_preferred":[
        "Nanhai"
    ],
    "name:und_x_variant":[
        "\u5357\u6d77"
    ],
    "name:zho_x_preferred":[
        "\u5357\u6d77"
    ],
    "wof:name":"Nanhai",
    "wof:placetype":"locality"
},
  "geometry": {"coordinates":[121.67488,39.37515],"type":"Point"}
}