{
  "type": "Feature",
  "properties": {
    "gn:admin1_code":"32.0",
    "gn:asciiname":"Zhongfang",
    "gn:country_code":"CN",
    "gn:dem":298,
    "gn:feature_class":"P",
    "gn:feature_code":"PPL",
    "gn:name":"Zhongfang",
    "gn:population":0,
    "gn:timezone":"Asia/Shanghai",
    "iso:country":"CN",
    "name:zho_x_preferred":[
        "\u949f\u623f"
    ],
    "wof:name":"Zhongfang",
    "wof:placetype":"locality"
},
  "geometry": {"coordinates":[105.47313,29.24924],"type":"Point"}
}