{
  "type": "Feature",
  "properties": {
    "gn:admin1_code":"29.0",
    "gn:asciiname":"Hunshuitang",
    "gn:country_code":"CN",
    "gn:dem":2450,
    "gn:feature_class":"P",
    "gn:feature_code":"PPL",
    "gn:name":"Hunshuitang",
    "gn:population":0,
    "gn:timezone":"Asia/Shanghai",
    "iso:country":"CN",
    "name:zho_x_preferred":[
        "\u6d51\u6c34\u5858"
    ],
    "wof:name":"Hunshuitang",
    "wof:placetype":"locality"
},
  "geometry": {"coordinates":[101.059,25.2847],"type":"Point"}
}