{
  "type": "Feature",
  "properties": {
    "gn:admin1_code":"9.0",
    "gn:asciiname":"Dongxiaozhang",
    "gn:country_code":"CN",
    "gn:dem":72,
    "gn:feature_class":"P",
    "gn:feature_code":"PPL",
    "gn:name":"Dongxiaozhang",
    "gn:population":0,
    "gn:timezone":"Asia/Shanghai",
    "iso:country":"CN",
    "name:zho_x_preferred":[
        "\u4e1c\u5c0f\u5f20"
    ],
    "wof:name":"Dongxiaozhang",
    "wof:placetype":"locality"
},
  "geometry": {"coordinates":[113.73554,33.68119],"type":"Point"}
}