{
  "type": "Feature",
  "properties": {
    "gn:admin1_code":"4.0",
    "gn:asciiname":"Shifeng",
    "gn:country_code":"CN",
    "gn:dem":4,
    "gn:feature_class":"P",
    "gn:feature_code":"PPL",
    "gn:name":"Shifeng",
    "gn:population":0,
    "gn:timezone":"Asia/Shanghai",
    "iso:country":"CN",
    "name:zho_x_preferred":[
        "Shifeng"
    ],
    "name:zho_x_variant":[
        "\u77f3\u51af"
    ],
    "wof:name":"Shifeng",
    "wof:placetype":"locality"
},
  "geometry": {"coordinates":[121.16112,32.4372],"type":"Point"}
}