{
  "type": "Feature",
  "properties": {
    "gn:admin1_code":"2.0",
    "gn:asciiname":"Laoshuta",
    "gn:country_code":"CN",
    "gn:dem":293,
    "gn:feature_class":"P",
    "gn:feature_code":"PPL",
    "gn:name":"Laoshuta",
    "gn:population":0,
    "gn:timezone":"Asia/Shanghai",
    "iso:country":"CN",
    "name:zho_x_preferred":[
        "\u8001\u9f20\u5854"
    ],
    "wof:name":"Laoshuta",
    "wof:placetype":"locality"
},
  "geometry": {"coordinates":[119.25526000000001,29.80594],"type":"Point"}
}