{
  "type": "Feature",
  "properties": {
    "gn:admin1_code":"32.0",
    "gn:asciiname":"Kang'aigang",
    "gn:country_code":"CN",
    "gn:dem":3740,
    "gn:feature_class":"P",
    "gn:feature_code":"PPL",
    "gn:name":"Kang\u2019aigang",
    "gn:population":0,
    "gn:timezone":"Asia/Shanghai",
    "iso:country":"CN",
    "name:und_x_variant":[
        "Kang\u2019aigang"
    ],
    "name:zho_x_preferred":[
        "\u6297\u827e\u5c97"
    ],
    "wof:name":"Kang'aigang",
    "wof:placetype":"locality"
},
  "geometry": {"coordinates":[101.057,29.816],"type":"Point"}
}