{
  "type": "Feature",
  "properties": {
    "gn:admin1_code":"24.0",
    "gn:asciiname":"Nanzhaizi",
    "gn:country_code":"CN",
    "gn:dem":420,
    "gn:feature_class":"P",
    "gn:feature_code":"PPL",
    "gn:name":"Nanzhaizi",
    "gn:population":0,
    "gn:timezone":"Asia/Shanghai",
    "iso:country":"CN",
    "name:zho_x_preferred":[
        "\u5357\u5be8\u5b50"
    ],
    "wof:name":"Nanzhaizi",
    "wof:placetype":"locality"
},
  "geometry": {"coordinates":[110.4944,35.35314],"type":"Point"}
}