{
  "type": "Feature",
  "properties": {
    "gn:admin1_code":"19",
    "gn:asciiname":"Hou-p'a-t'ou-tzu",
    "gn:country_code":"CN",
    "gn:dem":122,
    "gn:feature_class":"P",
    "gn:feature_code":"PPL",
    "gn:name":"Hou-p\u2019a-t\u2019ou-tzu",
    "gn:population":0,
    "gn:timezone":"Asia/Shanghai",
    "iso:country":"CN",
    "wof:name":"Hou-p'a-t'ou-tzu",
    "wof:placetype":"locality"
},
  "geometry": {"coordinates":[125.57722,40.91361],"type":"Point"}
}