{
  "type": "Feature",
  "properties": {
    "gn:admin1_code":"18.0",
    "gn:asciiname":"Daoba",
    "gn:country_code":"CN",
    "gn:dem":770,
    "gn:feature_class":"P",
    "gn:feature_code":"PPLA4",
    "gn:name":"Daoba",
    "gn:population":0,
    "gn:timezone":"Asia/Shanghai",
    "iso:country":"CN",
    "name:und_x_variant":[
        "Daoba Xiang"
    ],
    "name:zho_x_preferred":[
        "\u5200\u575d"
    ],
    "name:zho_x_variant":[
        "\u5200\u575d\u4e61"
    ],
    "wof:name":"Daoba",
    "wof:placetype":"locality"
},
  "geometry": {"coordinates":[108.5849,28.24019],"type":"Point"}
}