{
  "type": "Feature",
  "properties": {
    "gn:admin1_code":"12.0",
    "gn:asciiname":"Panjiatai",
    "gn:country_code":"CN",
    "gn:dem":26,
    "gn:feature_class":"P",
    "gn:feature_code":"PPL",
    "gn:name":"Panjiatai",
    "gn:population":0,
    "gn:timezone":"Asia/Shanghai",
    "iso:country":"CN",
    "name:zho_x_preferred":[
        "\u6f58\u5bb6\u53f0"
    ],
    "wof:name":"Panjiatai",
    "wof:placetype":"locality"
},
  "geometry": {"coordinates":[113.50227,30.01367],"type":"Point"}
}