{
  "type": "Feature",
  "properties": {
    "gn:admin1_code":"30.0",
    "gn:asciiname":"Aodu",
    "gn:country_code":"CN",
    "gn:dem":683,
    "gn:feature_class":"P",
    "gn:feature_code":"PPL",
    "gn:name":"Aodu",
    "gn:population":0,
    "gn:timezone":"Asia/Shanghai",
    "iso:country":"CN",
    "name:und_x_variant":[
        "\u5787\u809a"
    ],
    "wof:name":"Aodu",
    "wof:placetype":"locality"
},
  "geometry": {"coordinates":[114.58358,24.29743],"type":"Point"}
}