{
  "type": "Feature",
  "properties": {
    "gn:admin1_code":"2.0",
    "gn:asciiname":"Pansancun",
    "gn:country_code":"CN",
    "gn:dem":93,
    "gn:feature_class":"P",
    "gn:feature_code":"PPL",
    "gn:name":"Pansancun",
    "gn:population":0,
    "gn:timezone":"Asia/Shanghai",
    "iso:country":"CN",
    "name:zho_x_preferred":[
        "\u6f58\u4e09\u6751"
    ],
    "wof:name":"Pansancun",
    "wof:placetype":"locality"
},
  "geometry": {"coordinates":[119.78821000000001,29.22647000000001],"type":"Point"}
}