{
  "type": "Feature",
  "properties": {
    "iso:country":"CN",
    "qs:name":"\u5141\u666f\u6d2a",
    "qs:name_adm0":"\u4e2d\u570b",
    "qs:name_adm1":"\u4e91\u5357\u7701",
    "qs:photos":1704,
    "qs:photos_1k":345,
    "qs:photos_9k":8,
    "qs:photos_9r":8,
    "qs:photos_all":1704,
    "qs:photos_sr":14,
    "qs:placetype":"Town",
    "qs:pop_sr":"0",
    "wof:name":"\u5141\u666f\u6d2a",
    "wof:placetype":"locality"
},
  "geometry": {"coordinates":[100.811576,21.972021],"type":"Point"}
}