{
  "type": "Feature",
  "properties": {
    "gn:admin1_code":"19.0",
    "gn:asciiname":"Shimenzi",
    "gn:country_code":"CN",
    "gn:dem":330,
    "gn:feature_class":"P",
    "gn:feature_code":"PPL",
    "gn:name":"Shimenzi",
    "gn:population":0,
    "gn:timezone":"Asia/Shanghai",
    "iso:country":"CN",
    "name:zho_x_preferred":[
        "\u77f3\u95e8\u5b50"
    ],
    "wof:name":"Shimenzi",
    "wof:placetype":"locality"
},
  "geometry": {"coordinates":[121.25602000000001,41.75476],"type":"Point"}
}