{
  "type": "Feature",
  "properties": {
    "gn:admin1_code":"29.0",
    "gn:asciiname":"Wenxing",
    "gn:country_code":"CN",
    "gn:dem":2128,
    "gn:feature_class":"P",
    "gn:feature_code":"PPL",
    "gn:name":"Wenxing",
    "gn:population":0,
    "gn:timezone":"Asia/Shanghai",
    "iso:country":"CN",
    "name:mlg_x_preferred":[
        "Wenxing"
    ],
    "name:zho_x_preferred":[
        "\u6587\u5174"
    ],
    "name:zho_x_variant":[
        "\u6587\u661f\u9547"
    ],
    "wof:name":"Wenxing",
    "wof:placetype":"locality"
},
  "geometry": {"coordinates":[99.2782,26.1303],"type":"Point"}
}