{
  "type": "Feature",
  "properties": {
    "gn:admin1_code":"12.0",
    "gn:asciiname":"Xiaojinzhuyuan",
    "gn:country_code":"CN",
    "gn:dem":1533,
    "gn:feature_class":"P",
    "gn:feature_code":"PPL",
    "gn:name":"Xiaojinzhuyuan",
    "gn:population":0,
    "gn:timezone":"Asia/Shanghai",
    "iso:country":"CN",
    "name:zho_x_preferred":[
        "\u5c0f\u91d1\u7af9\u56ed"
    ],
    "wof:name":"Xiaojinzhuyuan",
    "wof:placetype":"locality"
},
  "geometry": {"coordinates":[110.40922999999999,31.47548],"type":"Point"}
}