{
  "type": "Feature",
  "properties": {
    "gn:admin1_code":"29",
    "gn:asciiname":"Hujiazhai",
    "gn:country_code":"CN",
    "gn:dem":1277,
    "gn:feature_class":"P",
    "gn:feature_code":"PPL",
    "gn:name":"Hujiazhai",
    "gn:population":0,
    "gn:timezone":"Asia/Shanghai",
    "iso:country":"CN",
    "name:zho_x_preferred":[
        "\u80e1\u5bb6\u5be8"
    ],
    "wof:name":"Hujiazhai",
    "wof:placetype":"locality"
},
  "geometry": {"coordinates":[105.164,23.7868],"type":"Point"}
}