{
  "type": "Feature",
  "properties": {
    "gn:admin1_code":"24.0",
    "gn:asciiname":"Hongchan",
    "gn:country_code":"CN",
    "gn:dem":1507,
    "gn:feature_class":"P",
    "gn:feature_code":"PPL",
    "gn:name":"Hongchan",
    "gn:population":0,
    "gn:timezone":"Asia/Shanghai",
    "iso:country":"CN",
    "name:zho_x_preferred":[
        "\u7ea2\u8fbf"
    ],
    "wof:name":"Hongchan",
    "wof:placetype":"locality"
},
  "geometry": {"coordinates":[113.54776,37.52833],"type":"Point"}
}