{
  "type": "Feature",
  "properties": {
    "gn:admin1_code":"11",
    "gn:asciiname":"Laowuli",
    "gn:country_code":"CN",
    "gn:dem":71,
    "gn:feature_class":"P",
    "gn:feature_code":"PPL",
    "gn:name":"Laowuli",
    "gn:population":0,
    "gn:timezone":"Asia/Shanghai",
    "iso:country":"CN",
    "name:zho_x_preferred":[
        "\u8001\u5c4b\u91cc"
    ],
    "wof:name":"Laowuli",
    "wof:placetype":"locality"
},
  "geometry": {"coordinates":[112.34789000000001,27.70394000000001],"type":"Point"}
}