{
  "type": "Feature",
  "properties": {
    "gn:admin1_code":"1.0",
    "gn:asciiname":"Zhujiakeng",
    "gn:country_code":"CN",
    "gn:dem":434,
    "gn:feature_class":"P",
    "gn:feature_code":"PPL",
    "gn:name":"Zhujiakeng",
    "gn:population":0,
    "gn:timezone":"Asia/Shanghai",
    "iso:country":"CN",
    "name:zho_x_preferred":[
        "\u6731\u5bb6\u5751"
    ],
    "wof:name":"Zhujiakeng",
    "wof:placetype":"locality"
},
  "geometry": {"coordinates":[117.69004,29.61797],"type":"Point"}
}