{
  "type": "Feature",
  "properties": {
    "gn:admin1_code":"32.0",
    "gn:asciiname":"Daowo",
    "gn:country_code":"CN",
    "gn:dem":3395,
    "gn:feature_class":"P",
    "gn:feature_code":"PPL",
    "gn:name":"Daowo",
    "gn:population":0,
    "gn:timezone":"Asia/Shanghai",
    "iso:country":"CN",
    "name:zho_x_preferred":[
        "\u9053\u6c83"
    ],
    "wof:name":"Daowo",
    "wof:placetype":"locality"
},
  "geometry": {"coordinates":[101.004,30.7454],"type":"Point"}
}