{
  "type": "Feature",
  "properties": {
    "gn:admin1_code":"32.0",
    "gn:asciiname":"Waqujuecun",
    "gn:country_code":"CN",
    "gn:dem":2151,
    "gn:feature_class":"P",
    "gn:feature_code":"PPL",
    "gn:name":"Waqujuecun",
    "gn:population":0,
    "gn:timezone":"Asia/Shanghai",
    "iso:country":"CN",
    "name:zho_x_preferred":[
        "\u74e6\u66f2\u89c9\u6751"
    ],
    "wof:name":"Waqujuecun",
    "wof:placetype":"locality"
},
  "geometry": {"coordinates":[103.09885,28.55601],"type":"Point"}
}