{
  "type": "Feature",
  "properties": {
    "iso:country":"CN",
    "name:ara_x_preferred":[
        "\u0644\u0648\u064a\u0627\u0646\u063a"
    ],
    "name:bel_x_preferred":[
        "\u0413\u043e\u0440\u0430\u0434 \u041b\u0430\u044f\u043d"
    ],
    "name:bod_x_preferred":[
        "\u0f63\u0f74\u0f60\u0f7c\u0f0b\u0f51\u0f56\u0fb1\u0f44\u0f0b\u0f0d"
    ],
    "name:bul_x_preferred":[
        "\u041b\u0443\u043e\u044f\u043d"
    ],
    "name:cat_x_preferred":[
        "Luoyang"
    ],
    "name:cdo_x_preferred":[
        "L\u014fk-i\u00f2ng"
    ],
    "name:ces_x_preferred":[
        "Luo-jang"
    ],
    "name:deu_x_preferred":[
        "Luoyang"
    ],
    "name:eng_x_preferred":[
        "Luoyang"
    ],
    "name:epo_x_preferred":[
        "L\u016dojango"
    ],
    "name:fas_x_preferred":[
        "\u0644\u0648\u0626\u0648\u06cc\u0627\u0646\u06af"
    ],
    "name:fra_x_preferred":[
        "Luoyang"
    ],
    "name:gan_x_preferred":[
        "\u7f57\u9633\u9547"
    ],
    "name:heb_x_preferred":[
        "\u05dc\u05d5\u05d5-\u05d9\u05d0\u05e0\u05d2"
    ],
    "name:hin_x_preferred":[
        "\u0932\u0941\u0913\u092f\u093e\u0902\u0917"
    ],
    "name:hun_x_preferred":[
        "Lojang"
    ],
    "name:ind_x_preferred":[
        "Luoyang"
    ],
    "name:ita_x_preferred":[
        "Luoyang"
    ],
    "name:jpn_x_preferred":[
        "\u6d1b\u967d\u5e02"
    ],
    "name:jpn_x_variant":[
        "\u7f85\u967d\u93ae"
    ],
    "name:kat_x_preferred":[
        "\u10da\u10dd\u10d8\u10d0\u10dc\u10d8"
    ],
    "name:kir_x_preferred":[
        "\u041b\u043e\u044f\u043d \u0448\u0430\u0430\u0440\u044b"
    ],
    "name:kor_x_preferred":[
        "\ub904\uc591 \uc2dc"
    ],
    "name:lit_x_preferred":[
        "Luojangas"
    ],
    "name:lzh_x_preferred":[
        "\u6d1b\u967d"
    ],
    "name:mkd_x_preferred":[
        "\u041b\u0443\u043e\u0458\u0430\u043d\u0433"
    ],
    "name:nan_x_preferred":[
        "Lo\u030dk-i\u00f4ng-chh\u012b"
    ],
    "name:nld_x_preferred":[
        "Luoyang"
    ],
    "name:nor_x_preferred":[
        "Luoyang"
    ],
    "name:pol_x_preferred":[
        "Luoyang"
    ],
    "name:por_x_preferred":[
        "Luoyang"
    ],
    "name:rus_x_preferred":[
        "\u041b\u043e\u044f\u043d"
    ],
    "name:spa_x_preferred":[
        "Luoyang"
    ],
    "name:srp_x_preferred":[
        "\u041b\u0443\u043e\u0458\u0430\u043d\u0433"
    ],
    "name:tha_x_preferred":[
        "\u0e25\u0e01\u0e40\u0e2d\u0e35\u0e4b\u0e22\u0e07"
    ],
    "name:uig_x_preferred":[
        "\u0644\u0648\u064a\u0627\u06ad \u0634\u06d5\u06be\u0649\u0631\u0649"
    ],
    "name:ukr_x_preferred":[
        "\u041b\u043e\u044f\u043d"
    ],
    "name:unk_x_variant":[
        "Honanfu"
    ],
    "name:urd_x_preferred":[
        "\u0644\u0648\u0648\u06cc\u0627\u0646\u06af"
    ],
    "name:vie_x_preferred":[
        "L\u1ea1c D\u01b0\u01a1ng"
    ],
    "name:wuu_x_preferred":[
        "\u6d1b\u9633"
    ],
    "name:wuu_x_variant":[
        "\u7f57\u9633\u9547"
    ],
    "name:yue_x_preferred":[
        "\u6d1b\u967d"
    ],
    "name:zho_x_preferred":[
        "\u6d1b\u9633\u5e02"
    ],
    "name:zho_x_variant":[
        "\u7f57\u9633\u9547"
    ],
    "qs:name":"\u6d1b\u9633",
    "qs:name_adm0":"\u4e2d\u570b",
    "qs:name_adm1":"\u5e7f\u4e1c\u7701",
    "qs:photos":136,
    "qs:photos_1k":28,
    "qs:photos_9k":1,
    "qs:photos_9r":3,
    "qs:photos_all":136,
    "qs:photos_sr":3,
    "qs:placetype":"Town",
    "qs:pop_sr":"0",
    "wof:name":"\u6d1b\u9633",
    "wof:placetype":"locality"
},
  "geometry": {"coordinates":[114.279121,23.170945],"type":"Point"}
}