{
  "type": "Feature",
  "properties": {
    "gn:admin1_code":"24.0",
    "gn:asciiname":"Yanwu",
    "gn:country_code":"CN",
    "gn:dem":787,
    "gn:feature_class":"P",
    "gn:feature_code":"PPL",
    "gn:name":"Yanwu",
    "gn:population":0,
    "gn:timezone":"Asia/Shanghai",
    "iso:country":"CN",
    "name:zho_x_preferred":[
        "\u6f14\u6b66"
    ],
    "wof:name":"Yanwu",
    "wof:placetype":"locality"
},
  "geometry": {"coordinates":[112.69495999999999,37.62433],"type":"Point"}
}