{
  "type": "Feature",
  "properties": {
    "gn:admin1_code":"11.0",
    "gn:asciiname":"Yuexiawan",
    "gn:country_code":"CN",
    "gn:dem":97,
    "gn:feature_class":"P",
    "gn:feature_code":"PPL",
    "gn:name":"Yuexiawan",
    "gn:population":0,
    "gn:timezone":"Asia/Shanghai",
    "iso:country":"CN",
    "name:zho_x_preferred":[
        "\u6708\u4e0b\u6e7e"
    ],
    "wof:name":"Yuexiawan",
    "wof:placetype":"locality"
},
  "geometry": {"coordinates":[113.42628999999999,26.99451],"type":"Point"}
}