{
  "type": "Feature",
  "properties": {
    "gn:admin1_code":"32.0",
    "gn:asciiname":"Maili",
    "gn:country_code":"CN",
    "gn:dem":2821,
    "gn:feature_class":"P",
    "gn:feature_code":"PPL",
    "gn:name":"Maili",
    "gn:population":0,
    "gn:timezone":"Asia/Shanghai",
    "iso:country":"CN",
    "name:zho_x_preferred":[
        "\u9ea6\u91cc"
    ],
    "wof:name":"Maili",
    "wof:placetype":"locality"
},
  "geometry": {"coordinates":[101.041,30.5039],"type":"Point"}
}