{
  "type": "Feature",
  "properties": {
    "gn:admin1_code":"26",
    "gn:asciiname":"Jiaozhen",
    "gn:country_code":"CN",
    "gn:dem":338,
    "gn:feature_class":"P",
    "gn:feature_code":"PPL",
    "gn:name":"Jiaozhen",
    "gn:population":0,
    "gn:timezone":"Asia/Shanghai",
    "iso:country":"CN",
    "name:und_x_variant":[
        "\u7126\u9547",
        "Jiaozhen"
    ],
    "wof:name":"Jiaozhen",
    "wof:placetype":"locality"
},
  "geometry": {"coordinates":[109.92267,34.59833],"type":"Point"}
}