{
  "type": "Feature",
  "properties": {
    "gn:admin1_code":"18",
    "gn:asciiname":"Jianao",
    "gn:country_code":"CN",
    "gn:dem":783,
    "gn:feature_class":"P",
    "gn:feature_code":"PPL",
    "gn:name":"Jianao",
    "gn:population":0,
    "gn:timezone":"Asia/Shanghai",
    "iso:country":"CN",
    "name:zho_x_preferred":[
        "\u7532\u95f9"
    ],
    "wof:name":"Jianao",
    "wof:placetype":"locality"
},
  "geometry": {"coordinates":[105.84,25.7934],"type":"Point"}
}