{
  "type": "Feature",
  "properties": {
    "gn:admin1_code":"12.0",
    "gn:asciiname":"Yanziba",
    "gn:country_code":"CN",
    "gn:dem":1302,
    "gn:feature_class":"P",
    "gn:feature_code":"PPL",
    "gn:name":"Yanziba",
    "gn:population":0,
    "gn:timezone":"Asia/Shanghai",
    "iso:country":"CN",
    "name:zho_x_preferred":[
        "\u71d5\u5b50\u575d"
    ],
    "wof:name":"Yanziba",
    "wof:placetype":"locality"
},
  "geometry": {"coordinates":[108.98043,29.43132],"type":"Point"}
}