{
  "type": "Feature",
  "properties": {
    "gn:admin1_code":"8.0",
    "gn:asciiname":"Xingnongcun",
    "gn:country_code":"CN",
    "gn:dem":200,
    "gn:feature_class":"P",
    "gn:feature_code":"PPL",
    "gn:name":"Xingnongcun",
    "gn:population":0,
    "gn:timezone":"Asia/Shanghai",
    "iso:country":"CN",
    "name:zho_x_preferred":[
        "\u5174\u519c\u6751"
    ],
    "wof:name":"Xingnongcun",
    "wof:placetype":"locality"
},
  "geometry": {"coordinates":[129.99687,45.98842],"type":"Point"}
}