{
  "type": "Feature",
  "properties": {
    "gn:admin1_code":"4.0",
    "gn:asciiname":"Xindun",
    "gn:country_code":"CN",
    "gn:dem":0,
    "gn:feature_class":"P",
    "gn:feature_code":"PPL",
    "gn:name":"Xindun",
    "gn:population":0,
    "gn:timezone":"Asia/Shanghai",
    "iso:country":"CN",
    "name:zho_x_preferred":[
        "\u65b0\u58a9"
    ],
    "wof:name":"Xindun",
    "wof:placetype":"locality"
},
  "geometry": {"coordinates":[120.64140999999999,32.78037],"type":"Point"}
}