{
  "type": "Feature",
  "properties": {
    "gn:admin1_code":"10",
    "gn:asciiname":"Guanchaigou",
    "gn:country_code":"CN",
    "gn:dem":894,
    "gn:feature_class":"P",
    "gn:feature_code":"PPL",
    "gn:name":"Guanchaigou",
    "gn:population":0,
    "gn:timezone":"Asia/Shanghai",
    "iso:country":"CN",
    "name:zho_x_preferred":[
        "\u5b98\u67f4\u6c9f"
    ],
    "wof:name":"Guanchaigou",
    "wof:placetype":"locality"
},
  "geometry": {"coordinates":[117.88639999999999,41.9076],"type":"Point"}
}