{
  "type": "Feature",
  "properties": {
    "gn:admin1_code":"19.0",
    "gn:asciiname":"Shangwentun",
    "gn:country_code":"CN",
    "gn:dem":201,
    "gn:feature_class":"P",
    "gn:feature_code":"PPL",
    "gn:name":"Shangwentun",
    "gn:population":0,
    "gn:timezone":"Asia/Shanghai",
    "iso:country":"CN",
    "name:und_x_variant":[
        "\u5c1a\u6587\u5c6f"
    ],
    "name:zho_x_preferred":[
        "\u5c1a\u6587\u5c6f"
    ],
    "wof:name":"Shangwentun",
    "wof:placetype":"locality"
},
  "geometry": {"coordinates":[124.49145,42.77575],"type":"Point"}
}