{
  "type": "Feature",
  "properties": {
    "gn:admin1_code":"32.0",
    "gn:asciiname":"Mi'er",
    "gn:country_code":"CN",
    "gn:dem":1779,
    "gn:feature_class":"P",
    "gn:feature_code":"PPL",
    "gn:name":"Mi\u2019er",
    "gn:population":0,
    "gn:timezone":"Asia/Shanghai",
    "iso:country":"CN",
    "name:und_x_variant":[
        "Mi\u2019er"
    ],
    "name:zho_x_preferred":[
        "\u7c73\u5c14"
    ],
    "wof:name":"Mi'er",
    "wof:placetype":"locality"
},
  "geometry": {"coordinates":[102.611,27.5428],"type":"Point"}
}