{
  "type": "Feature",
  "properties": {
    "gn:admin1_code":"16",
    "gn:asciiname":"Sheling",
    "gn:country_code":"CN",
    "gn:dem":513,
    "gn:feature_class":"P",
    "gn:feature_code":"PPL",
    "gn:name":"Sheling",
    "gn:population":0,
    "gn:timezone":"Asia/Shanghai",
    "iso:country":"CN",
    "name:zho_x_preferred":[
        "\u793e\u5cad"
    ],
    "wof:name":"Sheling",
    "wof:placetype":"locality"
},
  "geometry": {"coordinates":[110.55500000000001,25.8848],"type":"Point"}
}