{
  "type": "Feature",
  "properties": {
    "gn:admin1_code":"11.0",
    "gn:asciiname":"Maochangping",
    "gn:country_code":"CN",
    "gn:dem":494,
    "gn:feature_class":"P",
    "gn:feature_code":"PPL",
    "gn:name":"Maochangping",
    "gn:population":0,
    "gn:timezone":"Asia/Shanghai",
    "iso:country":"CN",
    "name:zho_x_preferred":[
        "\u6bdb\u957f\u576a"
    ],
    "wof:name":"Maochangping",
    "wof:placetype":"locality"
},
  "geometry": {"coordinates":[109.64766000000002,28.56089],"type":"Point"}
}