{
  "type": "Feature",
  "properties": {
    "gn:admin1_code":"15.0",
    "gn:asciiname":"Dangbu",
    "gn:country_code":"CN",
    "gn:dem":2092,
    "gn:feature_class":"P",
    "gn:feature_code":"PPL",
    "gn:name":"Dangbu",
    "gn:population":0,
    "gn:timezone":"Asia/Shanghai",
    "iso:country":"CN",
    "name:und_x_variant":[
        "\u515a\u5821"
    ],
    "wof:name":"Dangbu",
    "wof:placetype":"locality"
},
  "geometry": {"coordinates":[105.1178,35.17001],"type":"Point"}
}