{
  "type": "Feature",
  "properties": {
    "gn:admin1_code":"16.0",
    "gn:asciiname":"Ma'anchong",
    "gn:country_code":"CN",
    "gn:dem":219,
    "gn:feature_class":"P",
    "gn:feature_code":"PPL",
    "gn:name":"Ma\u2019anchong",
    "gn:population":0,
    "gn:timezone":"Asia/Shanghai",
    "iso:country":"CN",
    "name:und_x_variant":[
        "Ma\u2019anchong"
    ],
    "name:zho_x_preferred":[
        "\u9a6c\u5b89\u51b2"
    ],
    "wof:name":"Ma'anchong",
    "wof:placetype":"locality"
},
  "geometry": {"coordinates":[110.453,23.0179],"type":"Point"}
}