{
  "type": "Feature",
  "properties": {
    "gn:admin1_code":"9.0",
    "gn:asciiname":"Laomiaozhuang",
    "gn:country_code":"CN",
    "gn:dem":187,
    "gn:feature_class":"P",
    "gn:feature_code":"PPL",
    "gn:name":"Laomiaozhuang",
    "gn:population":0,
    "gn:timezone":"Asia/Shanghai",
    "iso:country":"CN",
    "name:und_x_variant":[
        "\u8001\u5e99\u5e84",
        "Laomiaozhuang"
    ],
    "wof:name":"Laomiaozhuang",
    "wof:placetype":"locality"
},
  "geometry": {"coordinates":[112.82402,33.65026],"type":"Point"}
}