{
  "type": "Feature",
  "properties": {
    "gn:admin1_code":"12.0",
    "gn:asciiname":"Ta'ergang",
    "gn:country_code":"CN",
    "gn:dem":118,
    "gn:feature_class":"P",
    "gn:feature_code":"PPL",
    "gn:name":"Ta\u2019ergang",
    "gn:population":0,
    "gn:timezone":"Asia/Shanghai",
    "iso:country":"CN",
    "name:und_x_variant":[
        "Ta\u2019ergang"
    ],
    "name:zho_x_preferred":[
        "\u5854\u8033\u5c97"
    ],
    "wof:name":"Ta'ergang",
    "wof:placetype":"locality"
},
  "geometry": {"coordinates":[114.87979,31.45304],"type":"Point"}
}