{
  "type": "Feature",
  "properties": {
    "gn:admin1_code":"2.0",
    "gn:asciiname":"Xiejiaqiao",
    "gn:country_code":"CN",
    "gn:dem":50,
    "gn:feature_class":"P",
    "gn:feature_code":"PPL",
    "gn:name":"Xiejiaqiao",
    "gn:population":0,
    "gn:timezone":"Asia/Shanghai",
    "iso:country":"CN",
    "name:zho_x_preferred":[
        "\u8c22\u5bb6\u6865"
    ],
    "wof:name":"Xiejiaqiao",
    "wof:placetype":"locality"
},
  "geometry": {"coordinates":[120.49791999999999,29.88664],"type":"Point"}
}