{
  "type": "Feature",
  "properties": {
    "gn:admin1_code":"19.0",
    "gn:asciiname":"Huaniubuzicun",
    "gn:country_code":"CN",
    "gn:dem":30,
    "gn:feature_class":"P",
    "gn:feature_code":"PPL",
    "gn:name":"Huaniubuzicun",
    "gn:population":0,
    "gn:timezone":"Asia/Shanghai",
    "iso:country":"CN",
    "name:und_x_variant":[
        "Huaniubao",
        "Huaniubu"
    ],
    "name:zho_x_preferred":[
        "\u82b1\u725b\u5821\u5b50\u6751"
    ],
    "name:zho_x_variant":[
        "\u82b1\u725b\u5821"
    ],
    "wof:name":"Huaniubuzicun",
    "wof:placetype":"locality"
},
  "geometry": {"coordinates":[123.114,41.7547],"type":"Point"}
}