{
  "type": "Feature",
  "properties": {
    "gn:admin1_code":"13",
    "gn:asciiname":"Qilian",
    "gn:country_code":"CN",
    "gn:dem":1277,
    "gn:feature_class":"P",
    "gn:feature_code":"PPLF",
    "gn:name":"Qilian",
    "gn:population":0,
    "gn:timezone":"Asia/Shanghai",
    "iso:country":"CN",
    "name:zho_x_preferred":[
        "\u4e03\u8fde"
    ],
    "wof:name":"Qilian",
    "wof:placetype":"locality"
},
  "geometry": {"coordinates":[76.07779000000002,39.25358],"type":"Point"}
}