{
  "type": "Feature",
  "properties": {
    "gn:admin1_code":"14.0",
    "gn:asciiname":"Duoxuema",
    "gn:country_code":"CN",
    "gn:dem":3998,
    "gn:feature_class":"P",
    "gn:feature_code":"PPL",
    "gn:name":"Duoxuema",
    "gn:population":0,
    "gn:timezone":"Asia/Urumqi",
    "iso:country":"CN",
    "name:zho_x_preferred":[
        "\u593a\u5b66\u739b"
    ],
    "wof:name":"Duoxuema",
    "wof:placetype":"locality"
},
  "geometry": {"coordinates":[93.80188,29.59868],"type":"Point"}
}