{
  "type": "Feature",
  "properties": {
    "gn:admin1_code":"2.0",
    "gn:asciiname":"Xishantou",
    "gn:country_code":"CN",
    "gn:dem":11,
    "gn:feature_class":"P",
    "gn:feature_code":"PPL",
    "gn:name":"Xishantou",
    "gn:population":0,
    "gn:timezone":"Asia/Shanghai",
    "iso:country":"CN",
    "name:und_x_variant":[
        "\u897f\u5c71\u5934"
    ],
    "wof:name":"Xishantou",
    "wof:placetype":"locality"
},
  "geometry": {"coordinates":[120.57528000000001,30.09741],"type":"Point"}
}