{
  "type": "Feature",
  "properties": {
    "gn:admin1_code":"3.0",
    "gn:asciiname":"Wangchuan",
    "gn:country_code":"CN",
    "gn:dem":101,
    "gn:feature_class":"P",
    "gn:feature_code":"PPL",
    "gn:name":"Wangchuan",
    "gn:population":0,
    "gn:timezone":"Asia/Shanghai",
    "iso:country":"CN",
    "name:zho_x_preferred":[
        "\u8f8b\u5ddd"
    ],
    "wof:name":"Wangchuan",
    "wof:placetype":"locality"
},
  "geometry": {"coordinates":[114.554,27.9216],"type":"Point"}
}