{
  "type": "Feature",
  "properties": {
    "gn:admin1_code":"15.0",
    "gn:asciiname":"Hejia Wannao",
    "gn:country_code":"CN",
    "gn:dem":2107,
    "gn:feature_class":"P",
    "gn:feature_code":"PPL",
    "gn:name":"Hejia Wannao",
    "gn:population":0,
    "gn:timezone":"Asia/Shanghai",
    "iso:country":"CN",
    "name:zho_x_preferred":[
        "\u4f55\u5bb6\u6e7e\u8111"
    ],
    "wof:name":"Hejia Wannao",
    "wof:placetype":"locality"
},
  "geometry": {"coordinates":[104.73399999999999,35.8348],"type":"Point"}
}