{
  "type": "Feature",
  "properties": {
    "gn:admin1_code":"19.0",
    "gn:asciiname":"Lamagou",
    "gn:country_code":"CN",
    "gn:dem":433,
    "gn:feature_class":"P",
    "gn:feature_code":"PPL",
    "gn:name":"Lamagou",
    "gn:population":0,
    "gn:timezone":"Asia/Shanghai",
    "iso:country":"CN",
    "name:zho_x_preferred":[
        "\u5587\u561b\u6c9f"
    ],
    "wof:name":"Lamagou",
    "wof:placetype":"locality"
},
  "geometry": {"coordinates":[119.88023,40.93318],"type":"Point"}
}