{
  "type": "Feature",
  "properties": {
    "gn:admin1_code":"32.0",
    "gn:asciiname":"Luyide",
    "gn:country_code":"CN",
    "gn:dem":2653,
    "gn:feature_class":"P",
    "gn:feature_code":"PPL",
    "gn:name":"Luyide",
    "gn:population":0,
    "gn:timezone":"Asia/Shanghai",
    "iso:country":"CN",
    "name:zho_x_preferred":[
        "\u9c81\u4f9d\u5f97"
    ],
    "wof:name":"Luyide",
    "wof:placetype":"locality"
},
  "geometry": {"coordinates":[101.551,27.6902],"type":"Point"}
}