{
  "type": "Feature",
  "properties": {
    "gn:admin1_code":"8.0",
    "gn:asciiname":"Laowopeng",
    "gn:country_code":"CN",
    "gn:dem":271,
    "gn:feature_class":"P",
    "gn:feature_code":"PPL",
    "gn:name":"Laowopeng",
    "gn:population":0,
    "gn:timezone":"Asia/Shanghai",
    "iso:country":"CN",
    "name:zho_x_preferred":[
        "\u8001\u7a9d\u68da"
    ],
    "wof:name":"Laowopeng",
    "wof:placetype":"locality"
},
  "geometry": {"coordinates":[126.11675,47.83788],"type":"Point"}
}