{
  "type": "Feature",
  "properties": {
    "gn:admin1_code":"25",
    "gn:asciiname":"Luxi",
    "gn:country_code":"CN",
    "gn:dem":155,
    "gn:feature_class":"P",
    "gn:feature_code":"PPL",
    "gn:name":"L\u00fcxi",
    "gn:population":0,
    "gn:timezone":"Asia/Shanghai",
    "iso:country":"CN",
    "name:ceb_x_preferred":[
        "Luxi"
    ],
    "name:deu_x_preferred":[
        "Luxi"
    ],
    "name:fra_x_preferred":[
        "Luxi"
    ],
    "name:kor_x_preferred":[
        "\ub8e8\uc2dc\ud604"
    ],
    "name:nor_x_preferred":[
        "Luxi"
    ],
    "name:swe_x_preferred":[
        "Luxi"
    ],
    "name:und_x_variant":[
        "L\u00fcxi"
    ],
    "name:zho_x_preferred":[
        "\u5415\u897f"
    ],
    "wof:name":"Luxi",
    "wof:placetype":"locality"
},
  "geometry": {"coordinates":[118.872,35.4227],"type":"Point"}
}