{
  "type": "Feature",
  "properties": {
    "gn:admin1_code":"16.0",
    "gn:asciiname":"Gena",
    "gn:country_code":"CN",
    "gn:dem":564,
    "gn:feature_class":"P",
    "gn:feature_code":"PPL",
    "gn:name":"Gena",
    "gn:population":0,
    "gn:timezone":"Asia/Shanghai",
    "iso:country":"CN",
    "name:zho_x_preferred":[
        "\u5404\u7eb3"
    ],
    "wof:name":"Gena",
    "wof:placetype":"locality"
},
  "geometry": {"coordinates":[105.57599999999999,23.2599],"type":"Point"}
}