{
  "type": "Feature",
  "properties": {
    "gn:admin1_code":"19.0",
    "gn:asciiname":"Luhuacun",
    "gn:country_code":"CN",
    "gn:dem":63,
    "gn:feature_class":"P",
    "gn:feature_code":"PPL",
    "gn:name":"L\u00fchuacun",
    "gn:population":0,
    "gn:timezone":"Asia/Shanghai",
    "iso:country":"CN",
    "name:und_x_variant":[
        "L\u00fchuacun"
    ],
    "name:zho_x_preferred":[
        "\u7eff\u5316\u6751"
    ],
    "wof:name":"Luhuacun",
    "wof:placetype":"locality"
},
  "geometry": {"coordinates":[120.56301000000001,40.72172],"type":"Point"}
}