{
  "type": "Feature",
  "properties": {
    "gn:admin1_code":"15.0",
    "gn:asciiname":"Datiaokou",
    "gn:country_code":"CN",
    "gn:dem":2838,
    "gn:feature_class":"P",
    "gn:feature_code":"PPL",
    "gn:name":"Datiaokou",
    "gn:population":0,
    "gn:timezone":"Asia/Shanghai",
    "iso:country":"CN",
    "name:und_x_variant":[
        "\u5927\u6761\u53e3"
    ],
    "wof:name":"Datiaokou",
    "wof:placetype":"locality"
},
  "geometry": {"coordinates":[104.13181,34.62246],"type":"Point"}
}