{
  "type": "Feature",
  "properties": {
    "gn:admin1_code":"19.0",
    "gn:asciiname":"Fangshengou",
    "gn:country_code":"CN",
    "gn:dem":211,
    "gn:feature_class":"P",
    "gn:feature_code":"PPL",
    "gn:name":"Fangshengou",
    "gn:population":0,
    "gn:timezone":"Asia/Shanghai",
    "iso:country":"CN",
    "name:und_x_variant":[
        "\u623f\u8eab\u6c9f"
    ],
    "wof:name":"Fangshengou",
    "wof:placetype":"locality"
},
  "geometry": {"coordinates":[122.69199999999999,40.0285],"type":"Point"}
}