{
  "type": "Feature",
  "properties": {
    "gn:admin1_code":"29.0",
    "gn:asciiname":"Luotang",
    "gn:country_code":"CN",
    "gn:dem":1162,
    "gn:feature_class":"P",
    "gn:feature_code":"PPL",
    "gn:name":"Luotang",
    "gn:population":0,
    "gn:timezone":"Asia/Shanghai",
    "iso:country":"CN",
    "name:zho_x_preferred":[
        "\u87ba\u5858"
    ],
    "wof:name":"Luotang",
    "wof:placetype":"locality"
},
  "geometry": {"coordinates":[103.91500000000001,23.0018],"type":"Point"}
}