{
  "type": "Feature",
  "properties": {
    "gn:admin1_code":"20.0",
    "gn:asciiname":"Pijianggou",
    "gn:country_code":"CN",
    "gn:dem":1788,
    "gn:feature_class":"P",
    "gn:feature_code":"PPL",
    "gn:name":"Pijianggou",
    "gn:population":0,
    "gn:timezone":"Asia/Shanghai",
    "iso:country":"CN",
    "name:und_x_variant":[
        "\u76ae\u5320\u6c9f"
    ],
    "wof:name":"Pijianggou",
    "wof:placetype":"locality"
},
  "geometry": {"coordinates":[110.93891000000001,41.08248],"type":"Point"}
}