{
  "type": "Feature",
  "properties": {
    "gn:admin1_code":"14.0",
    "gn:asciiname":"Dangka",
    "gn:country_code":"CN",
    "gn:dem":3421,
    "gn:feature_class":"P",
    "gn:feature_code":"PPL",
    "gn:name":"Dangka",
    "gn:population":0,
    "gn:timezone":"Asia/Urumqi",
    "iso:country":"CN",
    "name:zho_x_preferred":[
        "\u5f53\u5361"
    ],
    "wof:name":"Dangka",
    "wof:placetype":"locality"
},
  "geometry": {"coordinates":[95.47324999999999,31.02738],"type":"Point"}
}