{
  "type": "Feature",
  "properties": {
    "gn:admin1_code":"9",
    "gn:asciiname":"Shunhebei",
    "gn:country_code":"CN",
    "gn:dem":47,
    "gn:feature_class":"P",
    "gn:feature_code":"PPL",
    "gn:name":"Shunhebei",
    "gn:population":0,
    "gn:timezone":"Asia/Shanghai",
    "iso:country":"CN",
    "name:zho_x_preferred":[
        "\u987a\u6cb3\u5317"
    ],
    "wof:name":"Shunhebei",
    "wof:placetype":"locality"
},
  "geometry": {"coordinates":[115.616,34.2043],"type":"Point"}
}