{
  "type": "Feature",
  "properties": {
    "gn:admin1_code":"2.0",
    "gn:asciiname":"Lujia",
    "gn:country_code":"CN",
    "gn:dem":74,
    "gn:feature_class":"P",
    "gn:feature_code":"PPL",
    "gn:name":"Lujia",
    "gn:population":0,
    "gn:timezone":"Asia/Shanghai",
    "iso:country":"CN",
    "name:und_x_variant":[
        "\u5362\u5bb6",
        "Lujia"
    ],
    "wof:name":"Lujia",
    "wof:placetype":"locality"
},
  "geometry": {"coordinates":[119.53273,29.03736],"type":"Point"}
}