{
  "type": "Feature",
  "properties": {
    "gn:admin1_code":"23.0",
    "gn:asciiname":"Xiaotang",
    "gn:country_code":"CN",
    "gn:dem":5,
    "gn:feature_class":"P",
    "gn:feature_code":"PPL",
    "gn:name":"Xiaotang",
    "gn:population":0,
    "gn:timezone":"Asia/Shanghai",
    "iso:country":"CN",
    "name:und_x_variant":[
        "Hsiao-t\u2019ang",
        "Xiaotang",
        "\u8096\u5858"
    ],
    "wof:name":"Xiaotang",
    "wof:placetype":"locality"
},
  "geometry": {"coordinates":[121.43348,30.9741],"type":"Point"}
}