{
  "type": "Feature",
  "properties": {
    "gn:admin1_code":"24.0",
    "gn:asciiname":"Ganyao",
    "gn:country_code":"CN",
    "gn:dem":1186,
    "gn:feature_class":"P",
    "gn:feature_code":"PPL",
    "gn:name":"Ganyao",
    "gn:population":0,
    "gn:timezone":"Asia/Shanghai",
    "iso:country":"CN",
    "name:zho_x_preferred":[
        "\u7518\u7a91"
    ],
    "wof:name":"Ganyao",
    "wof:placetype":"locality"
},
  "geometry": {"coordinates":[111.47020000000001,37.14441],"type":"Point"}
}