{
  "type": "Feature",
  "properties": {
    "gn:admin1_code":"4.0",
    "gn:asciiname":"Damatou",
    "gn:country_code":"CN",
    "gn:dem":10,
    "gn:feature_class":"P",
    "gn:feature_code":"PPL",
    "gn:name":"Damatou",
    "gn:population":0,
    "gn:timezone":"Asia/Shanghai",
    "iso:country":"CN",
    "name:swe_x_preferred":[
        "Damatou"
    ],
    "name:zho_x_preferred":[
        "\u5927\u7801\u5934"
    ],
    "name:zho_x_variant":[
        "\u5927\u7801\u5934\u4e61"
    ],
    "wof:name":"Damatou",
    "wof:placetype":"locality"
},
  "geometry": {"coordinates":[118.83499999999999,33.1601],"type":"Point"}
}