{
  "type": "Feature",
  "properties": {
    "gn:admin1_code":"18.0",
    "gn:asciiname":"Manluo",
    "gn:country_code":"CN",
    "gn:dem":931,
    "gn:feature_class":"P",
    "gn:feature_code":"PPL",
    "gn:name":"Manluo",
    "gn:population":0,
    "gn:timezone":"Asia/Shanghai",
    "iso:country":"CN",
    "name:zho_x_preferred":[
        "\u6ee1\u7f57"
    ],
    "wof:name":"Manluo",
    "wof:placetype":"locality"
},
  "geometry": {"coordinates":[107.53100000000001,25.9801],"type":"Point"}
}