{
  "type": "Feature",
  "properties": {
    "gn:admin1_code":"4.0",
    "gn:asciiname":"Yuxing",
    "gn:country_code":"CN",
    "gn:dem":6,
    "gn:feature_class":"P",
    "gn:feature_code":"PPL",
    "gn:name":"Yuxing",
    "gn:population":0,
    "gn:timezone":"Asia/Shanghai",
    "iso:country":"CN",
    "name:zho_x_preferred":[
        "\u88d5\u5174"
    ],
    "wof:name":"Yuxing",
    "wof:placetype":"locality"
},
  "geometry": {"coordinates":[119.78631,32.28361],"type":"Point"}
}