{
  "type": "Feature",
  "properties": {
    "gn:admin1_code":"10.0",
    "gn:asciiname":"Tianzhuangzi",
    "gn:country_code":"CN",
    "gn:dem":35,
    "gn:feature_class":"P",
    "gn:feature_code":"PPL",
    "gn:name":"Tianzhuangzi",
    "gn:population":0,
    "gn:timezone":"Asia/Shanghai",
    "iso:country":"CN",
    "name:zho_x_preferred":[
        "\u7530\u5e84\u5b50"
    ],
    "wof:name":"Tianzhuangzi",
    "wof:placetype":"locality"
},
  "geometry": {"coordinates":[118.84563,39.86079],"type":"Point"}
}