{
  "type": "Feature",
  "properties": {
    "gn:admin1_code":"26.0",
    "gn:asciiname":"Fangmaocun",
    "gn:country_code":"CN",
    "gn:dem":1135,
    "gn:feature_class":"P",
    "gn:feature_code":"PPL",
    "gn:name":"Fangmaocun",
    "gn:population":0,
    "gn:timezone":"Asia/Shanghai",
    "iso:country":"CN",
    "name:zho_x_preferred":[
        "\u653e\u5cc1\u6751"
    ],
    "wof:name":"Fangmaocun",
    "wof:placetype":"locality"
},
  "geometry": {"coordinates":[110.48802999999999,38.62],"type":"Point"}
}