{
  "type": "Feature",
  "properties": {
    "gn:admin1_code":"26.0",
    "gn:asciiname":"Shanyangcun",
    "gn:country_code":"CN",
    "gn:dem":766,
    "gn:feature_class":"P",
    "gn:feature_code":"PPL",
    "gn:name":"Shanyangcun",
    "gn:population":0,
    "gn:timezone":"Asia/Shanghai",
    "iso:country":"CN",
    "name:zho_x_preferred":[
        "\u5c71\u9633\u6751"
    ],
    "wof:name":"Shanyangcun",
    "wof:placetype":"locality"
},
  "geometry": {"coordinates":[110.07022000000001,35.2537],"type":"Point"}
}