{
  "type": "Feature",
  "properties": {
    "gn:admin1_code":"02",
    "gn:asciiname":"Ch'ien-yao-ts'un",
    "gn:country_code":"CN",
    "gn:dem":8,
    "gn:feature_class":"P",
    "gn:feature_code":"PPL",
    "gn:name":"Ch\u2019ien-yao-ts\u2019un",
    "gn:population":0,
    "gn:timezone":"Asia/Shanghai",
    "iso:country":"CN",
    "name:zho_x_preferred":[
        "Ch\u2019ien-yao-ts\u2019un"
    ],
    "wof:name":"Ch'ien-yao-ts'un",
    "wof:placetype":"locality"
},
  "geometry": {"coordinates":[120.8725,28.07694],"type":"Point"}
}