{
  "type": "Feature",
  "properties": {
    "gn:admin1_code":"29",
    "gn:asciiname":"Yangyutang",
    "gn:country_code":"CN",
    "gn:dem":1802,
    "gn:feature_class":"P",
    "gn:feature_code":"PPL",
    "gn:name":"Yangyutang",
    "gn:population":0,
    "gn:timezone":"Asia/Shanghai",
    "iso:country":"CN",
    "name:zho_x_preferred":[
        "\u517b\u9c7c\u5858"
    ],
    "wof:name":"Yangyutang",
    "wof:placetype":"locality"
},
  "geometry": {"coordinates":[104.87,23.7955],"type":"Point"}
}