{
  "type": "Feature",
  "properties": {
    "gn:admin1_code":"9.0",
    "gn:asciiname":"Wanzao",
    "gn:country_code":"CN",
    "gn:dem":66,
    "gn:feature_class":"P",
    "gn:feature_code":"PPL",
    "gn:name":"Wanzao",
    "gn:population":0,
    "gn:timezone":"Asia/Shanghai",
    "iso:country":"CN",
    "name:zho_x_preferred":[
        "\u5f2f\u67a3"
    ],
    "wof:name":"Wanzao",
    "wof:placetype":"locality"
},
  "geometry": {"coordinates":[115.51947,32.23218],"type":"Point"}
}