{
  "type": "Feature",
  "properties": {
    "gn:admin1_code":"16.0",
    "gn:asciiname":"Houdong",
    "gn:country_code":"CN",
    "gn:dem":567,
    "gn:feature_class":"P",
    "gn:feature_code":"PPL",
    "gn:name":"Houdong",
    "gn:population":0,
    "gn:timezone":"Asia/Shanghai",
    "iso:country":"CN",
    "name:zho_x_preferred":[
        "\u540e\u5cd2"
    ],
    "wof:name":"Houdong",
    "wof:placetype":"locality"
},
  "geometry": {"coordinates":[108.562,25.0793],"type":"Point"}
}