{
  "type": "Feature",
  "properties": {
    "gn:admin1_code":"19.0",
    "gn:asciiname":"Peidancun",
    "gn:country_code":"CN",
    "gn:dem":12,
    "gn:feature_class":"P",
    "gn:feature_code":"PPL",
    "gn:name":"Peidancun",
    "gn:population":0,
    "gn:timezone":"Asia/Shanghai",
    "iso:country":"CN",
    "name:zho_x_preferred":[
        "\u88f4\u5355\u6751"
    ],
    "wof:name":"Peidancun",
    "wof:placetype":"locality"
},
  "geometry": {"coordinates":[121.15056,40.98004],"type":"Point"}
}