{
  "type": "Feature",
  "properties": {
    "gn:admin1_code":"19.0",
    "gn:asciiname":"Gaomaguan",
    "gn:country_code":"CN",
    "gn:dem":77,
    "gn:feature_class":"P",
    "gn:feature_code":"PPL",
    "gn:name":"Gaomaguan",
    "gn:population":0,
    "gn:timezone":"Asia/Shanghai",
    "iso:country":"CN",
    "name:zho_x_preferred":[
        "\u9ad8\u9a6c\u5b98"
    ],
    "wof:name":"Gaomaguan",
    "wof:placetype":"locality"
},
  "geometry": {"coordinates":[121.29011,41.42492],"type":"Point"}
}