{
  "type": "Feature",
  "properties": {
    "gn:admin1_code":"30.0",
    "gn:asciiname":"Chikengcun",
    "gn:country_code":"CN",
    "gn:dem":39,
    "gn:feature_class":"P",
    "gn:feature_code":"PPL",
    "gn:name":"Chikengcun",
    "gn:population":0,
    "gn:timezone":"Asia/Shanghai",
    "iso:country":"CN",
    "name:und_x_variant":[
        "Chikeng"
    ],
    "name:zho_x_preferred":[
        "\u8d64\u5751\u6751"
    ],
    "name:zho_x_variant":[
        "\u8d64\u5751"
    ],
    "wof:name":"Chikengcun",
    "wof:placetype":"locality"
},
  "geometry": {"coordinates":[117.02417,23.76938],"type":"Point"}
}