{
  "type": "Feature",
  "properties": {
    "gn:admin1_code":"29.0",
    "gn:asciiname":"Daxiechang",
    "gn:country_code":"CN",
    "gn:dem":874,
    "gn:feature_class":"P",
    "gn:feature_code":"PPL",
    "gn:name":"Daxiechang",
    "gn:population":0,
    "gn:timezone":"Asia/Shanghai",
    "iso:country":"CN",
    "name:zho_x_preferred":[
        "\u5927\u534f\u573a"
    ],
    "wof:name":"Daxiechang",
    "wof:placetype":"locality"
},
  "geometry": {"coordinates":[102.048,22.636],"type":"Point"}
}