{
  "type": "Feature",
  "properties": {
    "gn:admin1_code":"29.0",
    "gn:asciiname":"Jinzhushui",
    "gn:country_code":"CN",
    "gn:dem":1876,
    "gn:feature_class":"P",
    "gn:feature_code":"PPL",
    "gn:name":"Jinzhushui",
    "gn:population":0,
    "gn:timezone":"Asia/Shanghai",
    "iso:country":"CN",
    "name:zho_x_preferred":[
        "\u91d1\u7af9\u6c34"
    ],
    "wof:name":"Jinzhushui",
    "wof:placetype":"locality"
},
  "geometry": {"coordinates":[98.8901,24.0958],"type":"Point"}
}