{
  "type": "Feature",
  "properties": {
    "gn:admin1_code":"30",
    "gn:asciiname":"Maoping",
    "gn:country_code":"CN",
    "gn:dem":245,
    "gn:feature_class":"P",
    "gn:feature_code":"PPLA4",
    "gn:name":"Maoping",
    "gn:population":0,
    "gn:timezone":"Asia/Shanghai",
    "iso:country":"CN",
    "name:ceb_x_preferred":[
        "Maoping"
    ],
    "name:deu_x_preferred":[
        "Maoping"
    ],
    "name:swe_x_preferred":[
        "Maoping"
    ],
    "name:und_x_variant":[
        "Maoping Zhen"
    ],
    "name:zho_x_preferred":[
        "\u8305\u576a"
    ],
    "name:zho_x_variant":[
        "\u8305\u576a\u9547"
    ],
    "wof:name":"Maoping",
    "wof:placetype":"locality"
},
  "geometry": {"coordinates":[115.98336,24.64758],"type":"Point"}
}