{
  "type": "Feature",
  "properties": {
    "gn:admin1_code":"2.0",
    "gn:asciiname":"Dajun",
    "gn:country_code":"CN",
    "gn:dem":88,
    "gn:feature_class":"P",
    "gn:feature_code":"PPL",
    "gn:name":"Dajun",
    "gn:population":0,
    "gn:timezone":"Asia/Shanghai",
    "iso:country":"CN",
    "name:zho_x_preferred":[
        "\u5927\u90e1"
    ],
    "wof:name":"Dajun",
    "wof:placetype":"locality"
},
  "geometry": {"coordinates":[121.33399,28.84615],"type":"Point"}
}