{
  "type": "Feature",
  "properties": {
    "gn:admin1_code":"20.0",
    "gn:asciiname":"Wujiazhuang",
    "gn:country_code":"CN",
    "gn:dem":1495,
    "gn:feature_class":"P",
    "gn:feature_code":"PPL",
    "gn:name":"Wujiazhuang",
    "gn:population":0,
    "gn:timezone":"Asia/Shanghai",
    "iso:country":"CN",
    "name:und_x_variant":[
        "\u6b66\u5bb6\u5e84"
    ],
    "wof:name":"Wujiazhuang",
    "wof:placetype":"locality"
},
  "geometry": {"coordinates":[111.91933,39.72579],"type":"Point"}
}