{
  "type": "Feature",
  "properties": {
    "gn:admin1_code":"15.0",
    "gn:asciiname":"Yangpojia",
    "gn:country_code":"CN",
    "gn:dem":1772,
    "gn:feature_class":"P",
    "gn:feature_code":"PPL",
    "gn:name":"Yangpojia",
    "gn:population":0,
    "gn:timezone":"Asia/Shanghai",
    "iso:country":"CN",
    "name:zho_x_preferred":[
        "\u9633\u5761\u5bb6"
    ],
    "wof:name":"Yangpojia",
    "wof:placetype":"locality"
},
  "geometry": {"coordinates":[104.902,35.8081],"type":"Point"}
}