{
  "type": "Feature",
  "properties": {
    "gn:admin1_code":"1.0",
    "gn:asciiname":"Yuanqiaocun",
    "gn:country_code":"CN",
    "gn:dem":29,
    "gn:feature_class":"P",
    "gn:feature_code":"PPL",
    "gn:name":"Yuanqiaocun",
    "gn:population":0,
    "gn:timezone":"Asia/Shanghai",
    "iso:country":"CN",
    "name:zho_x_preferred":[
        "\u82d1\u6865\u6751"
    ],
    "wof:name":"Yuanqiaocun",
    "wof:placetype":"locality"
},
  "geometry": {"coordinates":[115.97484,32.93565],"type":"Point"}
}