{
  "type": "Feature",
  "properties": {
    "gn:admin1_code":"12.0",
    "gn:asciiname":"Yanjiabao",
    "gn:country_code":"CN",
    "gn:dem":1259,
    "gn:feature_class":"P",
    "gn:feature_code":"PPL",
    "gn:name":"Yanjiabao",
    "gn:population":0,
    "gn:timezone":"Asia/Shanghai",
    "iso:country":"CN",
    "name:zho_x_preferred":[
        "Yanjiabao"
    ],
    "name:zho_x_variant":[
        "\u71d5\u5bb6\u5305"
    ],
    "wof:name":"Yanjiabao",
    "wof:placetype":"locality"
},
  "geometry": {"coordinates":[110.42381,29.99408],"type":"Point"}
}