{
  "type": "Feature",
  "properties": {
    "gn:admin1_code":"24.0",
    "gn:asciiname":"Shayadong",
    "gn:country_code":"CN",
    "gn:dem":1623,
    "gn:feature_class":"P",
    "gn:feature_code":"PPL",
    "gn:name":"Shayadong",
    "gn:population":0,
    "gn:timezone":"Asia/Shanghai",
    "iso:country":"CN",
    "name:und_x_variant":[
        "\u6c99\u5d16\u6d1e"
    ],
    "name:zho_x_preferred":[
        "\u6c99\u5d16\u6d1e"
    ],
    "wof:name":"Shayadong",
    "wof:placetype":"locality"
},
  "geometry": {"coordinates":[113.79828000000001,39.73266],"type":"Point"}
}