{
  "type": "Feature",
  "properties": {
    "gn:admin1_code":"16.0",
    "gn:asciiname":"Cong'e",
    "gn:country_code":"CN",
    "gn:dem":231,
    "gn:feature_class":"P",
    "gn:feature_code":"PPL",
    "gn:name":"Cong\u2019e",
    "gn:population":0,
    "gn:timezone":"Asia/Shanghai",
    "iso:country":"CN",
    "name:und_x_variant":[
        "Cong\u2019e"
    ],
    "name:zho_x_preferred":[
        "\u4ece\u989d"
    ],
    "wof:name":"Cong'e",
    "wof:placetype":"locality"
},
  "geometry": {"coordinates":[108.19799999999999,23.638],"type":"Point"}
}