{
  "type": "Feature",
  "properties": {
    "gn:admin1_code":"16",
    "gn:asciiname":"Shangshenjiangyuan",
    "gn:country_code":"CN",
    "gn:dem":784,
    "gn:feature_class":"P",
    "gn:feature_code":"PPL",
    "gn:name":"Shangshenjiangyuan",
    "gn:population":0,
    "gn:timezone":"Asia/Shanghai",
    "iso:country":"CN",
    "name:zho_x_preferred":[
        "\u4e0a\u6df1\u6c5f\u6e90"
    ],
    "wof:name":"Shangshenjiangyuan",
    "wof:placetype":"locality"
},
  "geometry": {"coordinates":[110.777,25.3542],"type":"Point"}
}