{
  "type": "Feature",
  "properties": {
    "gn:admin1_code":"19.0",
    "gn:asciiname":"Huahong Goumen",
    "gn:country_code":"CN",
    "gn:dem":313,
    "gn:feature_class":"P",
    "gn:feature_code":"PPL",
    "gn:name":"Huahong Goumen",
    "gn:population":0,
    "gn:timezone":"Asia/Shanghai",
    "iso:country":"CN",
    "name:zho_x_preferred":[
        "\u82b1\u7ea2\u6c9f\u95e8"
    ],
    "wof:name":"Huahong Goumen",
    "wof:placetype":"locality"
},
  "geometry": {"coordinates":[123.41681,40.87745],"type":"Point"}
}