{
  "type": "Feature",
  "properties": {
    "gn:admin1_code":"11.0",
    "gn:asciiname":"Niu'eshi",
    "gn:country_code":"CN",
    "gn:dem":619,
    "gn:feature_class":"P",
    "gn:feature_code":"PPL",
    "gn:name":"Niu\u2019eshi",
    "gn:population":0,
    "gn:timezone":"Asia/Shanghai",
    "iso:country":"CN",
    "name:und_x_variant":[
        "Niu\u2019eshi"
    ],
    "name:zho_x_preferred":[
        "\u725b\u8f6d\u77f3"
    ],
    "wof:name":"Niu'eshi",
    "wof:placetype":"locality"
},
  "geometry": {"coordinates":[110.50484,26.7543],"type":"Point"}
}