{
  "type": "Feature",
  "properties": {
    "gn:admin1_code":"5.0",
    "gn:asciiname":"Wulitun",
    "gn:country_code":"CN",
    "gn:dem":485,
    "gn:feature_class":"P",
    "gn:feature_code":"PPL",
    "gn:name":"Wulitun",
    "gn:population":0,
    "gn:timezone":"Asia/Shanghai",
    "iso:country":"CN",
    "name:und_x_variant":[
        "\u4e94\u91cc\u5c6f"
    ],
    "wof:name":"Wulitun",
    "wof:placetype":"locality"
},
  "geometry": {"coordinates":[126.14412,41.68264],"type":"Point"}
}