{
  "type": "Feature",
  "properties": {
    "gn:admin1_code":"32.0",
    "gn:asciiname":"Tian'er",
    "gn:country_code":"CN",
    "gn:dem":3493,
    "gn:feature_class":"P",
    "gn:feature_code":"PPL",
    "gn:name":"Tian\u2019er",
    "gn:population":0,
    "gn:timezone":"Asia/Shanghai",
    "iso:country":"CN",
    "name:zho_x_preferred":[
        "\u5929\u8033"
    ],
    "name:zho_x_variant":[
        "Tian\u2019er"
    ],
    "wof:name":"Tian'er",
    "wof:placetype":"locality"
},
  "geometry": {"coordinates":[101.13818999999999,28.67339],"type":"Point"}
}