{
  "type": "Feature",
  "properties": {
    "gn:admin1_code":"30",
    "gn:asciiname":"Puzai",
    "gn:cc2":"CN",
    "gn:country_code":"CN",
    "gn:dem":31,
    "gn:feature_class":"P",
    "gn:feature_code":"PPL",
    "gn:name":"Puzai",
    "gn:population":0,
    "gn:timezone":"Asia/Urumqi",
    "iso:country":"CN",
    "name:und_x_variant":[
        "P\u2019u-tsai",
        "Puzai"
    ],
    "wof:name":"Puzai",
    "wof:placetype":"locality"
},
  "geometry": {"coordinates":[110.25,21.16667],"type":"Point"}
}