{
  "type": "Feature",
  "properties": {
    "gn:admin1_code":"20.0",
    "gn:asciiname":"Sujia Buzi",
    "gn:country_code":"CN",
    "gn:dem":1629,
    "gn:feature_class":"P",
    "gn:feature_code":"PPL",
    "gn:name":"Sujia Buzi",
    "gn:population":0,
    "gn:timezone":"Asia/Shanghai",
    "iso:country":"CN",
    "name:und_x_variant":[
        "\u82cf\u5bb6\u535c\u5b50"
    ],
    "wof:name":"Sujia Buzi",
    "wof:placetype":"locality"
},
  "geometry": {"coordinates":[112.2608,41.64859000000001],"type":"Point"}
}