{
  "type": "Feature",
  "properties": {
    "gn:admin1_code":"12.0",
    "gn:asciiname":"Xunjiaya",
    "gn:cc2":"CN",
    "gn:country_code":"CN",
    "gn:dem":469,
    "gn:feature_class":"P",
    "gn:feature_code":"PPL",
    "gn:name":"Xunjiaya",
    "gn:population":0,
    "gn:timezone":"Asia/Shanghai",
    "iso:country":"CN",
    "name:und_x_variant":[
        "Hs\u00fcn-chia-ya",
        "Xunjiaya"
    ],
    "wof:name":"Xunjiaya",
    "wof:placetype":"locality"
},
  "geometry": {"coordinates":[111.41639000000001,31.18528],"type":"Point"}
}