{
  "type": "Feature",
  "properties": {
    "gn:admin1_code":"12.0",
    "gn:asciiname":"Baojia Xiangzi",
    "gn:country_code":"CN",
    "gn:dem":91,
    "gn:feature_class":"P",
    "gn:feature_code":"PPL",
    "gn:name":"Baojia Xiangzi",
    "gn:population":0,
    "gn:timezone":"Asia/Shanghai",
    "iso:country":"CN",
    "name:zho_x_preferred":[
        "\u5305\u5bb6\u5df7\u5b50"
    ],
    "wof:name":"Baojia Xiangzi",
    "wof:placetype":"locality"
},
  "geometry": {"coordinates":[113.15783999999999,31.62326],"type":"Point"}
}