{
  "type": "Feature",
  "properties": {
    "gn:admin1_code":"9.0",
    "gn:asciiname":"Shizhangzhuang",
    "gn:country_code":"CN",
    "gn:dem":415,
    "gn:feature_class":"P",
    "gn:feature_code":"PPL",
    "gn:name":"Shizhangzhuang",
    "gn:population":0,
    "gn:timezone":"Asia/Shanghai",
    "iso:country":"CN",
    "name:zho_x_preferred":[
        "\u77f3\u5f20\u5e84"
    ],
    "wof:name":"Shizhangzhuang",
    "wof:placetype":"locality"
},
  "geometry": {"coordinates":[112.66401999999999,34.40728],"type":"Point"}
}