{
  "type": "Feature",
  "properties": {
    "gn:admin1_code":"19.0",
    "gn:asciiname":"Houtougou",
    "gn:country_code":"CN",
    "gn:dem":11,
    "gn:feature_class":"P",
    "gn:feature_code":"PPL",
    "gn:name":"Houtougou",
    "gn:population":0,
    "gn:timezone":"Asia/Shanghai",
    "iso:country":"CN",
    "name:zho_x_preferred":[
        "\u4faf\u5934\u6c9f"
    ],
    "wof:name":"Houtougou",
    "wof:placetype":"locality"
},
  "geometry": {"coordinates":[122.66525,41.35641],"type":"Point"}
}