{
  "type": "Feature",
  "properties": {
    "gn:admin1_code":"32.0",
    "gn:asciiname":"Zhuanlunsi",
    "gn:country_code":"CN",
    "gn:dem":360,
    "gn:feature_class":"P",
    "gn:feature_code":"PPL",
    "gn:name":"Zhuanlunsi",
    "gn:population":0,
    "gn:timezone":"Asia/Shanghai",
    "iso:country":"CN",
    "name:zho_x_preferred":[
        "\u8f6c\u8f6e\u5bfa"
    ],
    "wof:name":"Zhuanlunsi",
    "wof:placetype":"locality"
},
  "geometry": {"coordinates":[105.23174,30.50584000000001],"type":"Point"}
}