{
  "type": "Feature",
  "properties": {
    "gn:admin1_code":"12",
    "gn:asciiname":"Baokang Chengguanzhen",
    "gn:country_code":"CN",
    "gn:dem":306,
    "gn:feature_class":"P",
    "gn:feature_code":"PPLA3",
    "gn:name":"Baokang Chengguanzhen",
    "gn:population":0,
    "gn:timezone":"Asia/Shanghai",
    "iso:country":"CN",
    "name:und_x_variant":[
        "Baokang",
        "Baokang Chengguanzhen"
    ],
    "name:zho_x_preferred":[
        "Pao-k\u2019ang"
    ],
    "name:zho_x_variant":[
        "Pao-k\u2019ang-hsien"
    ],
    "wof:name":"Baokang Chengguanzhen",
    "wof:placetype":"locality"
},
  "geometry": {"coordinates":[111.25639,31.87806],"type":"Point"}
}