{
  "type": "Feature",
  "properties": {
    "gn:admin1_code":"12.0",
    "gn:asciiname":"Zhongjianjiashan",
    "gn:country_code":"CN",
    "gn:dem":94,
    "gn:feature_class":"P",
    "gn:feature_code":"PPL",
    "gn:name":"Zhongjianjiashan",
    "gn:population":0,
    "gn:timezone":"Asia/Shanghai",
    "iso:country":"CN",
    "name:zho_x_preferred":[
        "\u4e2d\u7b80\u5bb6\u5c71"
    ],
    "wof:name":"Zhongjianjiashan",
    "wof:placetype":"locality"
},
  "geometry": {"coordinates":[113.94540000000001,29.3998],"type":"Point"}
}