{
  "type": "Feature",
  "properties": {
    "gn:admin1_code":"25.0",
    "gn:asciiname":"Sujiacun",
    "gn:country_code":"CN",
    "gn:dem":8,
    "gn:feature_class":"P",
    "gn:feature_code":"PPL",
    "gn:name":"Sujiacun",
    "gn:population":0,
    "gn:timezone":"Asia/Shanghai",
    "iso:country":"CN",
    "name:zho_x_preferred":[
        "\u82cf\u5bb6\u6751"
    ],
    "wof:name":"Sujiacun",
    "wof:placetype":"locality"
},
  "geometry": {"coordinates":[117.56074,37.86618],"type":"Point"}
}