{
  "type": "Feature",
  "properties": {
    "gn:admin1_code":"10",
    "gn:asciiname":"Dingzhangzi",
    "gn:country_code":"CN",
    "gn:dem":183,
    "gn:feature_class":"P",
    "gn:feature_code":"PPL",
    "gn:name":"Dingzhangzi",
    "gn:population":0,
    "gn:timezone":"Asia/Shanghai",
    "iso:country":"CN",
    "name:zho_x_preferred":[
        "\u4e01\u6756\u5b50"
    ],
    "wof:name":"Dingzhangzi",
    "wof:placetype":"locality"
},
  "geometry": {"coordinates":[118.78297999999999,40.3592],"type":"Point"}
}