{
  "type": "Feature",
  "properties": {
    "gn:admin1_code":"26.0",
    "gn:asciiname":"Zhuangshuanggou",
    "gn:country_code":"CN",
    "gn:dem":1820,
    "gn:feature_class":"P",
    "gn:feature_code":"PPL",
    "gn:name":"Zhuangshuanggou",
    "gn:population":0,
    "gn:timezone":"Asia/Shanghai",
    "iso:country":"CN",
    "name:und_x_variant":[
        "\u5e84\u53cc\u6c9f"
    ],
    "wof:name":"Zhuangshuanggou",
    "wof:placetype":"locality"
},
  "geometry": {"coordinates":[107.36241,34.11806],"type":"Point"}
}