{
  "type": "Feature",
  "properties": {
    "gn:admin1_code":"18",
    "gn:asciiname":"Huajiazhuang",
    "gn:country_code":"CN",
    "gn:dem":1594,
    "gn:feature_class":"P",
    "gn:feature_code":"PPL",
    "gn:name":"Huajiazhuang",
    "gn:population":0,
    "gn:timezone":"Asia/Shanghai",
    "iso:country":"CN",
    "name:zho_x_preferred":[
        "\u82b1\u5bb6\u5e84"
    ],
    "wof:name":"Huajiazhuang",
    "wof:placetype":"locality"
},
  "geometry": {"coordinates":[104.48699999999999,25.7927],"type":"Point"}
}