{
  "type": "Feature",
  "properties": {
    "gn:admin1_code":"18",
    "gn:asciiname":"Gugu",
    "gn:country_code":"CN",
    "gn:dem":1339,
    "gn:feature_class":"P",
    "gn:feature_code":"PPL",
    "gn:name":"Gugu",
    "gn:population":0,
    "gn:timezone":"Asia/Shanghai",
    "iso:country":"CN",
    "name:zho_x_preferred":[
        "\u6545\u53e4"
    ],
    "wof:name":"Gugu",
    "wof:placetype":"locality"
},
  "geometry": {"coordinates":[104.959,25.2231],"type":"Point"}
}