{
  "type": "Feature",
  "properties": {
    "gn:admin1_code":"26.0",
    "gn:asciiname":"Wenjiayuancun",
    "gn:country_code":"CN",
    "gn:dem":892,
    "gn:feature_class":"P",
    "gn:feature_code":"PPL",
    "gn:name":"Wenjiayuancun",
    "gn:population":0,
    "gn:timezone":"Asia/Shanghai",
    "iso:country":"CN",
    "name:zho_x_preferred":[
        "\u6e29\u5bb6\u586c\u6751"
    ],
    "wof:name":"Wenjiayuancun",
    "wof:placetype":"locality"
},
  "geometry": {"coordinates":[110.35474000000001,36.75363],"type":"Point"}
}