{
  "type": "Feature",
  "properties": {
    "gn:admin1_code":"13",
    "gn:asciiname":"Qiaka",
    "gn:country_code":"CN",
    "gn:dem":1251,
    "gn:feature_class":"P",
    "gn:feature_code":"PPL",
    "gn:name":"Qiaka",
    "gn:population":0,
    "gn:timezone":"Asia/Shanghai",
    "iso:country":"CN",
    "name:zho_x_preferred":[
        "\u6070\u5580"
    ],
    "wof:name":"Qiaka",
    "wof:placetype":"locality"
},
  "geometry": {"coordinates":[76.33459000000001,39.09297],"type":"Point"}
}