{
  "type": "Feature",
  "properties": {
    "gn:admin1_code":"7.0",
    "gn:asciiname":"Likenggang",
    "gn:country_code":"CN",
    "gn:dem":392,
    "gn:feature_class":"P",
    "gn:feature_code":"PPL",
    "gn:name":"Likenggang",
    "gn:population":0,
    "gn:timezone":"Asia/Shanghai",
    "iso:country":"CN",
    "name:und_x_variant":[
        "\u91cc\u5751\u5c97"
    ],
    "wof:name":"Likenggang",
    "wof:placetype":"locality"
},
  "geometry": {"coordinates":[116.44629,26.19563],"type":"Point"}
}