{
  "type": "Feature",
  "properties": {
    "gn:admin1_code":"29",
    "gn:asciiname":"Zoujiawanzi",
    "gn:country_code":"CN",
    "gn:dem":1594,
    "gn:feature_class":"P",
    "gn:feature_code":"PPL",
    "gn:name":"Zoujiawanzi",
    "gn:population":0,
    "gn:timezone":"Asia/Shanghai",
    "iso:country":"CN",
    "name:zho_x_preferred":[
        "\u90b9\u5bb6\u5f2f\u5b50"
    ],
    "wof:name":"Zoujiawanzi",
    "wof:placetype":"locality"
},
  "geometry": {"coordinates":[105.113,23.2901],"type":"Point"}
}