{
  "type": "Feature",
  "properties": {
    "gn:admin1_code":"32",
    "gn:asciiname":"Liangshui",
    "gn:country_code":"CN",
    "gn:dem":623,
    "gn:feature_class":"P",
    "gn:feature_code":"PPLA4",
    "gn:name":"Liangshui",
    "gn:population":0,
    "gn:timezone":"Asia/Shanghai",
    "iso:country":"CN",
    "name:und_x_variant":[
        "\u51c9\u6c34",
        "Liangshui Zhen",
        "\u51c9\u6c34\u9547"
    ],
    "wof:name":"Liangshui",
    "wof:placetype":"locality"
},
  "geometry": {"coordinates":[105.21832999999999,32.38333],"type":"Point"}
}