{
  "type": "Feature",
  "properties": {
    "gn:admin1_code":"8.0",
    "gn:asciiname":"Lijia Tangzi",
    "gn:country_code":"CN",
    "gn:dem":414,
    "gn:feature_class":"P",
    "gn:feature_code":"PPL",
    "gn:name":"Lijia Tangzi",
    "gn:population":0,
    "gn:timezone":"Asia/Shanghai",
    "iso:country":"CN",
    "name:und_x_variant":[
        "\u674e\u5bb6\u8d9f\u5b50"
    ],
    "wof:name":"Lijia Tangzi",
    "wof:placetype":"locality"
},
  "geometry": {"coordinates":[131.1019,43.68514],"type":"Point"}
}