{
  "type": "Feature",
  "properties": {
    "gn:admin1_code":"19.0",
    "gn:asciiname":"Dawangjiagou",
    "gn:country_code":"CN",
    "gn:dem":194,
    "gn:feature_class":"P",
    "gn:feature_code":"PPL",
    "gn:name":"Dawangjiagou",
    "gn:population":0,
    "gn:timezone":"Asia/Shanghai",
    "iso:country":"CN",
    "name:zho_x_preferred":[
        "\u5927\u738b\u5bb6\u6c9f"
    ],
    "wof:name":"Dawangjiagou",
    "wof:placetype":"locality"
},
  "geometry": {"coordinates":[122.91800000000001,39.9985],"type":"Point"}
}