{
  "type": "Feature",
  "properties": {
    "gn:admin1_code":"30",
    "gn:asciiname":"Haoshan",
    "gn:country_code":"CN",
    "gn:dem":6,
    "gn:feature_class":"P",
    "gn:feature_code":"PPL",
    "gn:name":"Haoshan",
    "gn:population":0,
    "gn:timezone":"Asia/Shanghai",
    "iso:country":"CN",
    "name:zho_x_preferred":[
        "\u6fe0\u5c71"
    ],
    "wof:name":"Haoshan",
    "wof:placetype":"locality"
},
  "geometry": {"coordinates":[111.7283,21.76918],"type":"Point"}
}