{
  "type": "Feature",
  "properties": {
    "gn:admin1_code":"8.0",
    "gn:asciiname":"Wujiatun",
    "gn:country_code":"CN",
    "gn:dem":170,
    "gn:feature_class":"P",
    "gn:feature_code":"PPL",
    "gn:name":"Wujiatun",
    "gn:population":0,
    "gn:timezone":"Asia/Shanghai",
    "iso:country":"CN",
    "name:zho_x_preferred":[
        "\u4e94\u7532\u5c6f"
    ],
    "wof:name":"Wujiatun",
    "wof:placetype":"locality"
},
  "geometry": {"coordinates":[128.12641000000002,45.33638],"type":"Point"}
}