{
  "type": "Feature",
  "properties": {
    "gn:admin1_code":"32.0",
    "gn:asciiname":"Damulin",
    "gn:country_code":"CN",
    "gn:dem":1116,
    "gn:feature_class":"P",
    "gn:feature_code":"PPL",
    "gn:name":"Damulin",
    "gn:population":0,
    "gn:timezone":"Asia/Shanghai",
    "iso:country":"CN",
    "name:zho_x_preferred":[
        "\u5927\u6728\u6797"
    ],
    "wof:name":"Damulin",
    "wof:placetype":"locality"
},
  "geometry": {"coordinates":[102.73099999999999,29.826],"type":"Point"}
}