{
  "type": "Feature",
  "properties": {
    "gn:admin1_code":"3.0",
    "gn:asciiname":"Xiangjialong",
    "gn:country_code":"CN",
    "gn:dem":23,
    "gn:feature_class":"P",
    "gn:feature_code":"PPL",
    "gn:name":"Xiangjialong",
    "gn:population":0,
    "gn:timezone":"Asia/Shanghai",
    "iso:country":"CN",
    "name:und_x_variant":[
        "\u5411\u5bb6\u5784"
    ],
    "wof:name":"Xiangjialong",
    "wof:placetype":"locality"
},
  "geometry": {"coordinates":[115.74498,29.74298],"type":"Point"}
}