{
  "type": "Feature",
  "properties": {
    "gn:admin1_code":"32.0",
    "gn:asciiname":"Dangla",
    "gn:country_code":"CN",
    "gn:dem":4540,
    "gn:feature_class":"P",
    "gn:feature_code":"PPL",
    "gn:name":"Dangla",
    "gn:population":0,
    "gn:timezone":"Asia/Shanghai",
    "iso:country":"CN",
    "name:zho_x_preferred":[
        "\u5f53\u62c9"
    ],
    "wof:name":"Dangla",
    "wof:placetype":"locality"
},
  "geometry": {"coordinates":[97.5547,33.5072],"type":"Point"}
}