{
  "type": "Feature",
  "properties": {
    "gn:admin1_code":"26.0",
    "gn:asciiname":"Shuijingbao",
    "gn:country_code":"CN",
    "gn:dem":1142,
    "gn:feature_class":"P",
    "gn:feature_code":"PPL",
    "gn:name":"Shuijingbao",
    "gn:population":0,
    "gn:timezone":"Asia/Shanghai",
    "iso:country":"CN",
    "name:und_x_variant":[
        "\u6c34\u4e95\u5305"
    ],
    "wof:name":"Shuijingbao",
    "wof:placetype":"locality"
},
  "geometry": {"coordinates":[107.99459,32.92248],"type":"Point"}
}