{
  "type": "Feature",
  "properties": {
    "gn:admin1_code":"8.0",
    "gn:asciiname":"Gongfucun",
    "gn:country_code":"CN",
    "gn:dem":248,
    "gn:feature_class":"P",
    "gn:feature_code":"PPL",
    "gn:name":"Gongfucun",
    "gn:population":0,
    "gn:timezone":"Asia/Shanghai",
    "iso:country":"CN",
    "name:zho_x_preferred":[
        "\u5171\u798f\u6751"
    ],
    "wof:name":"Gongfucun",
    "wof:placetype":"locality"
},
  "geometry": {"coordinates":[125.05907000000001,48.66064],"type":"Point"}
}