{
  "type": "Feature",
  "properties": {
    "gn:admin1_code":"29.0",
    "gn:asciiname":"Fawen",
    "gn:country_code":"CN",
    "gn:dem":2215,
    "gn:feature_class":"P",
    "gn:feature_code":"PPL",
    "gn:name":"Fawen",
    "gn:population":0,
    "gn:timezone":"Asia/Shanghai",
    "iso:country":"CN",
    "name:zho_x_preferred":[
        "\u6cd5\u6587"
    ],
    "wof:name":"Fawen",
    "wof:placetype":"locality"
},
  "geometry": {"coordinates":[102.59399999999999,25.8626],"type":"Point"}
}