{
  "type": "Feature",
  "properties": {
    "gn:admin1_code":"8.0",
    "gn:asciiname":"Erbeicun",
    "gn:country_code":"CN",
    "gn:dem":142,
    "gn:feature_class":"P",
    "gn:feature_code":"PPL",
    "gn:name":"Erbeicun",
    "gn:population":0,
    "gn:timezone":"Asia/Shanghai",
    "iso:country":"CN",
    "name:zho_x_preferred":[
        "\u4e8c\u5317\u6751"
    ],
    "wof:name":"Erbeicun",
    "wof:placetype":"locality"
},
  "geometry": {"coordinates":[126.31910000000001,46.7356],"type":"Point"}
}