{
  "type": "Feature",
  "properties": {
    "gn:admin1_code":"1.0",
    "gn:asciiname":"Zhanwacun",
    "gn:country_code":"CN",
    "gn:dem":24,
    "gn:feature_class":"P",
    "gn:feature_code":"PPL",
    "gn:name":"Zhanwacun",
    "gn:population":0,
    "gn:timezone":"Asia/Shanghai",
    "iso:country":"CN",
    "name:zho_x_preferred":[
        "\u5c55\u6d3c\u6751"
    ],
    "wof:name":"Zhanwacun",
    "wof:placetype":"locality"
},
  "geometry": {"coordinates":[116.47533,32.55755],"type":"Point"}
}