{
  "type": "Feature",
  "properties": {
    "gn:admin1_code":"30",
    "gn:asciiname":"Tianbeicun",
    "gn:country_code":"CN",
    "gn:dem":37,
    "gn:feature_class":"P",
    "gn:feature_code":"PPL",
    "gn:name":"Tianbeicun",
    "gn:population":0,
    "gn:timezone":"Asia/Urumqi",
    "iso:country":"CN",
    "name:und_x_variant":[
        "Tien-pei",
        "Tianbeicun"
    ],
    "name:zho_x_preferred":[
        "\u7530\u5317\u6751"
    ],
    "wof:name":"Tianbeicun",
    "wof:placetype":"locality"
},
  "geometry": {"coordinates":[110.44186000000001,20.52555],"type":"Point"}
}