{
  "type": "Feature",
  "properties": {
    "gn:admin1_code":"32.0",
    "gn:asciiname":"Kaluocun",
    "gn:country_code":"CN",
    "gn:dem":3987,
    "gn:feature_class":"P",
    "gn:feature_code":"PPL",
    "gn:name":"Kaluocun",
    "gn:population":0,
    "gn:timezone":"Asia/Shanghai",
    "iso:country":"CN",
    "name:zho_x_preferred":[
        "\u5361\u6d1b\u6751"
    ],
    "wof:name":"Kaluocun",
    "wof:placetype":"locality"
},
  "geometry": {"coordinates":[98.21064,32.38853],"type":"Point"}
}