{
  "type": "Feature",
  "properties": {
    "gn:admin1_code":"23.0",
    "gn:asciiname":"Zhangjiang",
    "gn:cc2":"CN",
    "gn:country_code":"CN",
    "gn:dem":6,
    "gn:feature_class":"P",
    "gn:feature_code":"PPL",
    "gn:name":"Zhangjiang",
    "gn:population":0,
    "gn:timezone":"Asia/Shanghai",
    "iso:country":"CN",
    "name:und_x_variant":[
        "Chang-chiang-chen",
        "Chang-chiang-cha",
        "Chang-chiang-cha-chen",
        "Zhangjiang",
        "\u5f20\u6c5f"
    ],
    "wof:name":"Zhangjiang",
    "wof:placetype":"locality"
},
  "geometry": {"coordinates":[121.60889,31.20861],"type":"Point"}
}