{
  "type": "Feature",
  "properties": {
    "gn:admin1_code":"29",
    "gn:asciiname":"Shangmaowei",
    "gn:country_code":"CN",
    "gn:dem":1709,
    "gn:feature_class":"P",
    "gn:feature_code":"PPL",
    "gn:name":"Shangmaowei",
    "gn:population":0,
    "gn:timezone":"Asia/Shanghai",
    "iso:country":"CN",
    "name:zho_x_preferred":[
        "\u4e0a\u8302\u4f4d"
    ],
    "wof:name":"Shangmaowei",
    "wof:placetype":"locality"
},
  "geometry": {"coordinates":[102.24156000000001,24.24805],"type":"Point"}
}