{
  "type": "Feature",
  "properties": {
    "gn:admin1_code":"30.0",
    "gn:asciiname":"Shiliuqing",
    "gn:country_code":"CN",
    "gn:dem":-3,
    "gn:feature_class":"P",
    "gn:feature_code":"PPL",
    "gn:name":"Shiliuqing",
    "gn:population":0,
    "gn:timezone":"Asia/Shanghai",
    "iso:country":"CN",
    "name:und_x_variant":[
        "\u5341\u516d\u9877"
    ],
    "name:zho_x_preferred":[
        "\u5341\u516d\u9877"
    ],
    "wof:name":"Shiliuqing",
    "wof:placetype":"locality"
},
  "geometry": {"coordinates":[113.56865999999999,22.62178],"type":"Point"}
}