{
  "type": "Feature",
  "properties": {
    "gn:admin1_code":"29.0",
    "gn:asciiname":"Xiaoxiben",
    "gn:country_code":"CN",
    "gn:dem":1265,
    "gn:feature_class":"P",
    "gn:feature_code":"PPL",
    "gn:name":"Xiaoxiben",
    "gn:population":0,
    "gn:timezone":"Asia/Shanghai",
    "iso:country":"CN",
    "name:zho_x_preferred":[
        "\u5c0f\u6614\u672c"
    ],
    "wof:name":"Xiaoxiben",
    "wof:placetype":"locality"
},
  "geometry": {"coordinates":[100.503,22.8794],"type":"Point"}
}