{
  "type": "Feature",
  "properties": {
    "gn:admin1_code":"19.0",
    "gn:asciiname":"Sankuaidi",
    "gn:country_code":"CN",
    "gn:dem":69,
    "gn:feature_class":"P",
    "gn:feature_code":"PPL",
    "gn:name":"Sankuaidi",
    "gn:population":0,
    "gn:timezone":"Asia/Shanghai",
    "iso:country":"CN",
    "name:und_x_variant":[
        "\u4e09\u5757\u5730"
    ],
    "name:zho_x_preferred":[
        "\u4e09\u5757\u5730"
    ],
    "wof:name":"Sankuaidi",
    "wof:placetype":"locality"
},
  "geometry": {"coordinates":[123.94821,40.08728],"type":"Point"}
}