{
  "type": "Feature",
  "properties": {
    "gn:admin1_code":"8.0",
    "gn:asciiname":"Dongfa Sidui",
    "gn:country_code":"CN",
    "gn:dem":173,
    "gn:feature_class":"P",
    "gn:feature_code":"PPLF",
    "gn:name":"Dongfa Sidui",
    "gn:population":0,
    "gn:timezone":"Asia/Shanghai",
    "iso:country":"CN",
    "name:zho_x_preferred":[
        "\u4e1c\u53d1\u56db\u961f"
    ],
    "wof:name":"Dongfa Sidui",
    "wof:placetype":"locality"
},
  "geometry": {"coordinates":[124.1454,48.06109],"type":"Point"}
}