{
  "type": "Feature",
  "properties": {
    "gn:admin1_code":"2.0",
    "gn:asciiname":"Dashan'an",
    "gn:country_code":"CN",
    "gn:dem":119,
    "gn:feature_class":"P",
    "gn:feature_code":"PPL",
    "gn:name":"Dashan\u2019an",
    "gn:population":0,
    "gn:timezone":"Asia/Shanghai",
    "iso:country":"CN",
    "name:und_x_variant":[
        "Dashan\u2019an"
    ],
    "name:zho_x_preferred":[
        "\u5927\u5c71\u5eb5"
    ],
    "wof:name":"Dashan'an",
    "wof:placetype":"locality"
},
  "geometry": {"coordinates":[120.75677,29.77128],"type":"Point"}
}