{
  "type": "Feature",
  "properties": {
    "gn:admin1_code":"1.0",
    "gn:asciiname":"Fancun",
    "gn:country_code":"CN",
    "gn:dem":191,
    "gn:feature_class":"P",
    "gn:feature_code":"PPL",
    "gn:name":"Fancun",
    "gn:population":0,
    "gn:timezone":"Asia/Shanghai",
    "iso:country":"CN",
    "name:zho_x_preferred":[
        "\u8543\u6751"
    ],
    "wof:name":"Fancun",
    "wof:placetype":"locality"
},
  "geometry": {"coordinates":[118.36468000000001,29.9975],"type":"Point"}
}