{
  "type": "Feature",
  "properties": {
    "gn:admin1_code":"19.0",
    "gn:asciiname":"Xiangshugou",
    "gn:country_code":"CN",
    "gn:dem":110,
    "gn:feature_class":"P",
    "gn:feature_code":"PPL",
    "gn:name":"Xiangshugou",
    "gn:population":0,
    "gn:timezone":"Asia/Shanghai",
    "iso:country":"CN",
    "name:zho_x_preferred":[
        "\u6a61\u6811\u6c9f"
    ],
    "wof:name":"Xiangshugou",
    "wof:placetype":"locality"
},
  "geometry": {"coordinates":[124.07299999999999,42.50899999999999],"type":"Point"}
}