{
  "type": "Feature",
  "properties": {
    "gn:admin1_code":"14.0",
    "gn:asciiname":"Jiangdong",
    "gn:country_code":"CN",
    "gn:dem":4460,
    "gn:feature_class":"P",
    "gn:feature_code":"PPL",
    "gn:name":"Jiangdong",
    "gn:population":0,
    "gn:timezone":"Asia/Urumqi",
    "iso:country":"CN",
    "name:deu_x_preferred":[
        "Jiangdong"
    ],
    "name:fra_x_preferred":[
        "Jiangdong"
    ],
    "name:zho_x_preferred":[
        "\u6c5f\u4e1c"
    ],
    "wof:name":"Jiangdong",
    "wof:placetype":"locality"
},
  "geometry": {"coordinates":[87.0855,28.7447],"type":"Point"}
}