{
  "type": "Feature",
  "properties": {
    "gn:admin1_code":"32.0",
    "gn:asciiname":"Shaluohetie",
    "gn:country_code":"CN",
    "gn:dem":2452,
    "gn:feature_class":"P",
    "gn:feature_code":"PPL",
    "gn:name":"Shaluohetie",
    "gn:population":0,
    "gn:timezone":"Asia/Shanghai",
    "iso:country":"CN",
    "name:zho_x_preferred":[
        "\u6c99\u6d1b\u6838\u94c1"
    ],
    "wof:name":"Shaluohetie",
    "wof:placetype":"locality"
},
  "geometry": {"coordinates":[103.08566999999999,27.75866],"type":"Point"}
}