{
  "type": "Feature",
  "properties": {
    "gn:admin1_code":"15.0",
    "gn:asciiname":"Moqiang",
    "gn:country_code":"CN",
    "gn:dem":2098,
    "gn:feature_class":"P",
    "gn:feature_code":"PPL",
    "gn:name":"Moqiang",
    "gn:population":0,
    "gn:timezone":"Asia/Shanghai",
    "iso:country":"CN",
    "name:zho_x_preferred":[
        "\u78e8\u7f8c"
    ],
    "wof:name":"Moqiang",
    "wof:placetype":"locality"
},
  "geometry": {"coordinates":[103.682,35.3433],"type":"Point"}
}