{
  "type": "Feature",
  "properties": {
    "gn:admin1_code":"14.0",
    "gn:asciiname":"Cangdacun",
    "gn:country_code":"CN",
    "gn:dem":4247,
    "gn:feature_class":"P",
    "gn:feature_code":"PPL",
    "gn:name":"Cangdacun",
    "gn:population":0,
    "gn:timezone":"Asia/Urumqi",
    "iso:country":"CN",
    "name:zho_x_preferred":[
        "\u85cf\u8fbe\u6751"
    ],
    "wof:name":"Cangdacun",
    "wof:placetype":"locality"
},
  "geometry": {"coordinates":[91.21662000000001,28.32778],"type":"Point"}
}