{
  "type": "Feature",
  "properties": {
    "gn:admin1_code":"3",
    "gn:asciiname":"Gebang",
    "gn:country_code":"CN",
    "gn:dem":249,
    "gn:feature_class":"P",
    "gn:feature_code":"PPL",
    "gn:name":"Gebang",
    "gn:population":0,
    "gn:timezone":"Asia/Shanghai",
    "iso:country":"CN",
    "name:bih_x_preferred":[
        "\u0917\u0947\u092c\u093e\u0902\u0917"
    ],
    "name:ind_x_preferred":[
        "Candi Gebang"
    ],
    "name:jav_x_preferred":[
        "Candhi Gebang"
    ],
    "name:tat_x_preferred":[
        "\u0413\u0435\u0431\u0430\u043d\u0433"
    ],
    "name:zho_x_preferred":[
        "\u5404\u5e2e"
    ],
    "wof:name":"Gebang",
    "wof:placetype":"locality"
},
  "geometry": {"coordinates":[114.633,26.1144],"type":"Point"}
}