{
  "type": "Feature",
  "properties": {
    "gn:admin1_code":"3",
    "gn:asciiname":"Gebang",
    "gn:country_code":"CN",
    "gn:dem":249,
    "gn:feature_class":"P",
    "gn:feature_code":"PPL",
    "gn:name":"Gebang",
    "gn:population":0,
    "gn:timezone":"Asia/Shanghai",
    "iso:country":"CN",
    "name:zho_x_preferred":[
        "\u5404\u5e2e"
    ],
    "wof:name":"Gebang",
    "wof:placetype":"locality"
},
  "geometry": {"coordinates":[114.633,26.1144],"type":"Point"}
}