{
  "type": "Feature",
  "properties": {
    "gn:admin1_code":"16.0",
    "gn:asciiname":"Dongzou",
    "gn:country_code":"CN",
    "gn:dem":365,
    "gn:feature_class":"P",
    "gn:feature_code":"PPL",
    "gn:name":"Dongzou",
    "gn:population":0,
    "gn:timezone":"Asia/Shanghai",
    "iso:country":"CN",
    "name:zho_x_preferred":[
        "\u6d1e\u8d70"
    ],
    "wof:name":"Dongzou",
    "wof:placetype":"locality"
},
  "geometry": {"coordinates":[105.64100000000001,24.1043],"type":"Point"}
}