{
  "type": "Feature",
  "properties": {
    "gn:admin1_code":"32.0",
    "gn:asciiname":"Datuowan",
    "gn:country_code":"CN",
    "gn:dem":325,
    "gn:feature_class":"P",
    "gn:feature_code":"PPL",
    "gn:name":"Datuowan",
    "gn:population":0,
    "gn:timezone":"Asia/Shanghai",
    "iso:country":"CN",
    "name:zho_x_preferred":[
        "\u5927\u6cb1\u6e7e"
    ],
    "wof:name":"Datuowan",
    "wof:placetype":"locality"
},
  "geometry": {"coordinates":[105.37262,28.39961],"type":"Point"}
}