{
  "type": "Feature",
  "properties": {
    "gn:admin1_code":"5.0",
    "gn:asciiname":"Xianjincun",
    "gn:country_code":"CN",
    "gn:dem":155,
    "gn:feature_class":"P",
    "gn:feature_code":"PPL",
    "gn:name":"Xianjincun",
    "gn:population":0,
    "gn:timezone":"Asia/Shanghai",
    "iso:country":"CN",
    "name:zho_x_preferred":[
        "\u5148\u8fdb\u6751"
    ],
    "wof:name":"Xianjincun",
    "wof:placetype":"locality"
},
  "geometry": {"coordinates":[123.40535,44.21808],"type":"Point"}
}