{
  "type": "Feature",
  "properties": {
    "gn:admin1_code":"02",
    "gn:asciiname":"Longshan",
    "gn:country_code":"CN",
    "gn:dem":14,
    "gn:feature_class":"P",
    "gn:feature_code":"PPL",
    "gn:name":"Longshan",
    "gn:population":0,
    "gn:timezone":"Asia/Shanghai",
    "iso:country":"CN",
    "name:zho_x_preferred":[
        "\u9686\u5c71"
    ],
    "wof:name":"Longshan",
    "wof:placetype":"locality"
},
  "geometry": {"coordinates":[120.64521000000001,27.77706],"type":"Point"}
}