{
  "type": "Feature",
  "properties": {
    "gn:admin1_code":"29.0",
    "gn:asciiname":"Shuilaoping",
    "gn:country_code":"CN",
    "gn:dem":1013,
    "gn:feature_class":"P",
    "gn:feature_code":"PPL",
    "gn:name":"Shuilaoping",
    "gn:population":0,
    "gn:timezone":"Asia/Shanghai",
    "iso:country":"CN",
    "name:zho_x_preferred":[
        "\u6c34\u8001\u576a"
    ],
    "wof:name":"Shuilaoping",
    "wof:placetype":"locality"
},
  "geometry": {"coordinates":[104.97799999999999,27.8879],"type":"Point"}
}