{
  "type": "Feature",
  "properties": {
    "gn:admin1_code":"32.0",
    "gn:asciiname":"Tangjiashan",
    "gn:country_code":"CN",
    "gn:dem":688,
    "gn:feature_class":"P",
    "gn:feature_code":"PPL",
    "gn:name":"Tangjiashan",
    "gn:population":0,
    "gn:timezone":"Asia/Shanghai",
    "iso:country":"CN",
    "name:pol_x_preferred":[
        "Tangjiashan"
    ],
    "name:zho_x_preferred":[
        "\u5510\u5bb6\u5c71"
    ],
    "wof:name":"Tangjiashan",
    "wof:placetype":"locality"
},
  "geometry": {"coordinates":[104.66200000000001,29.679],"type":"Point"}
}