{
  "type": "Feature",
  "properties": {
    "gn:admin1_code":"2.0",
    "gn:asciiname":"Shigengbei",
    "gn:country_code":"CN",
    "gn:dem":74,
    "gn:feature_class":"P",
    "gn:feature_code":"PPL",
    "gn:name":"Shigengbei",
    "gn:population":0,
    "gn:timezone":"Asia/Shanghai",
    "iso:country":"CN",
    "name:zho_x_preferred":[
        "\u77f3\u8015\u80cc"
    ],
    "wof:name":"Shigengbei",
    "wof:placetype":"locality"
},
  "geometry": {"coordinates":[119.69256,29.15903],"type":"Point"}
}