{
  "type": "Feature",
  "properties": {
    "gn:admin1_code":"26",
    "gn:asciiname":"Duanjia",
    "gn:country_code":"CN",
    "gn:dem":480,
    "gn:feature_class":"P",
    "gn:feature_code":"PPLA4",
    "gn:name":"Duanjia",
    "gn:population":0,
    "gn:timezone":"Asia/Shanghai",
    "iso:country":"CN",
    "name:und_x_variant":[
        "Tuan-chia",
        "Tuan-chia-chai",
        "Duanjia"
    ],
    "name:zho_x_preferred":[
        "\u6bb5\u5bb6"
    ],
    "wof:name":"Duanjia",
    "wof:placetype":"locality"
},
  "geometry": {"coordinates":[109.81844,34.87256],"type":"Point"}
}