{
  "type": "Feature",
  "properties": {
    "gn:admin1_code":"11.0",
    "gn:asciiname":"Jingchongpu",
    "gn:country_code":"CN",
    "gn:dem":144,
    "gn:feature_class":"P",
    "gn:feature_code":"PPL",
    "gn:name":"Jingchongpu",
    "gn:population":0,
    "gn:timezone":"Asia/Shanghai",
    "iso:country":"CN",
    "name:zho_x_preferred":[
        "\u4e95\u51b2\u94fa"
    ],
    "wof:name":"Jingchongpu",
    "wof:placetype":"locality"
},
  "geometry": {"coordinates":[112.12931,28.09191],"type":"Point"}
}