{
  "type": "Feature",
  "properties": {
    "gn:admin1_code":"9.0",
    "gn:asciiname":"Yangjia Laowan",
    "gn:country_code":"CN",
    "gn:dem":102,
    "gn:feature_class":"P",
    "gn:feature_code":"PPL",
    "gn:name":"Yangjia Laowan",
    "gn:population":0,
    "gn:timezone":"Asia/Shanghai",
    "iso:country":"CN",
    "name:zho_x_preferred":[
        "\u6768\u5bb6\u8001\u5846"
    ],
    "wof:name":"Yangjia Laowan",
    "wof:placetype":"locality"
},
  "geometry": {"coordinates":[113.9473,32.2124],"type":"Point"}
}