{
  "type": "Feature",
  "properties": {
    "gn:admin1_code":"15.0",
    "gn:asciiname":"Caijiangtou",
    "gn:country_code":"CN",
    "gn:dem":1570,
    "gn:feature_class":"P",
    "gn:feature_code":"PPL",
    "gn:name":"Caijiangtou",
    "gn:population":0,
    "gn:timezone":"Asia/Shanghai",
    "iso:country":"CN",
    "name:und_x_variant":[
        "\u8521\u6c5f\u5934"
    ],
    "name:zho_x_preferred":[
        "\u8521\u6c5f\u5934"
    ],
    "wof:name":"Caijiangtou",
    "wof:placetype":"locality"
},
  "geometry": {"coordinates":[104.51221,33.95009],"type":"Point"}
}