{
  "type": "Feature",
  "properties": {
    "gn:admin1_code":"14.0",
    "gn:asciiname":"Naricocha",
    "gn:country_code":"CN",
    "gn:dem":4893,
    "gn:feature_class":"P",
    "gn:feature_code":"PPL",
    "gn:name":"Naricocha",
    "gn:population":0,
    "gn:timezone":"Asia/Urumqi",
    "iso:country":"CN",
    "name:bod_x_preferred":[
        "Naricocha"
    ],
    "name:zho_x_preferred":[
        "Naricuocha"
    ],
    "name:zho_x_variant":[
        "\u7eb3\u65e5\u63aa\u67e5"
    ],
    "wof:name":"Naricocha",
    "wof:placetype":"locality"
},
  "geometry": {"coordinates":[92.105,32.005],"type":"Point"}
}