{
  "type": "Feature",
  "properties": {
    "gn:admin1_code":"2.0",
    "gn:asciiname":"Mapu",
    "gn:country_code":"CN",
    "gn:dem":227,
    "gn:feature_class":"P",
    "gn:feature_code":"PPL",
    "gn:name":"Mapu",
    "gn:population":0,
    "gn:timezone":"Asia/Shanghai",
    "iso:country":"CN",
    "name:ceb_x_preferred":[
        "Mapu"
    ],
    "name:deu_x_preferred":[
        "Mapu"
    ],
    "name:spa_x_preferred":[
        "Mapu"
    ],
    "name:swe_x_preferred":[
        "Mapu"
    ],
    "name:zho_x_preferred":[
        "\u9ebb\u94fa"
    ],
    "wof:name":"Mapu",
    "wof:placetype":"locality"
},
  "geometry": {"coordinates":[119.75489,28.5404],"type":"Point"}
}