{
  "type": "Feature",
  "properties": {
    "gn:admin1_code":"19.0",
    "gn:asciiname":"Xidaozhangzi",
    "gn:country_code":"CN",
    "gn:dem":399,
    "gn:feature_class":"P",
    "gn:feature_code":"PPL",
    "gn:name":"Xidaozhangzi",
    "gn:population":0,
    "gn:timezone":"Asia/Shanghai",
    "iso:country":"CN",
    "name:zho_x_preferred":[
        "\u897f\u9053\u6756\u5b50"
    ],
    "wof:name":"Xidaozhangzi",
    "wof:placetype":"locality"
},
  "geometry": {"coordinates":[119.00784,40.75051],"type":"Point"}
}