{
  "type": "Feature",
  "properties": {
    "gn:admin1_code":"26.0",
    "gn:asciiname":"Zhanma",
    "gn:country_code":"CN",
    "gn:dem":881,
    "gn:feature_class":"P",
    "gn:feature_code":"PPL",
    "gn:name":"Zhanma",
    "gn:population":0,
    "gn:timezone":"Asia/Shanghai",
    "iso:country":"CN",
    "name:zho_x_preferred":[
        "\u7ad9\u9a6c"
    ],
    "wof:name":"Zhanma",
    "wof:placetype":"locality"
},
  "geometry": {"coordinates":[108.60241000000001,34.00632],"type":"Point"}
}