{
  "type": "Feature",
  "properties": {
    "gn:admin1_code":"22",
    "gn:asciiname":"Xiaozhuanghugou",
    "gn:country_code":"CN",
    "gn:dem":653,
    "gn:feature_class":"P",
    "gn:feature_code":"PPL",
    "gn:name":"Xiaozhuanghugou",
    "gn:population":0,
    "gn:timezone":"Asia/Shanghai",
    "iso:country":"CN",
    "name:zho_x_preferred":[
        "\u5c0f\u5e84\u6237\u6c9f"
    ],
    "wof:name":"Xiaozhuanghugou",
    "wof:placetype":"locality"
},
  "geometry": {"coordinates":[116.53377999999999,40.88809000000001],"type":"Point"}
}