{
  "type": "Feature",
  "properties": {
    "gn:admin1_code":"19.0",
    "gn:asciiname":"Donglacun",
    "gn:country_code":"CN",
    "gn:dem":40,
    "gn:feature_class":"P",
    "gn:feature_code":"PPL",
    "gn:name":"Donglacun",
    "gn:population":0,
    "gn:timezone":"Asia/Shanghai",
    "iso:country":"CN",
    "name:zho_x_preferred":[
        "\u4e1c\u62c9\u6751"
    ],
    "wof:name":"Donglacun",
    "wof:placetype":"locality"
},
  "geometry": {"coordinates":[121.997,41.7363],"type":"Point"}
}