{
  "type": "Feature",
  "properties": {
    "gn:admin1_code":"20.0",
    "gn:asciiname":"Linjia Xiaofang",
    "gn:country_code":"CN",
    "gn:dem":261,
    "gn:feature_class":"P",
    "gn:feature_code":"PPL",
    "gn:name":"Linjia Xiaofang",
    "gn:population":0,
    "gn:timezone":"Asia/Shanghai",
    "iso:country":"CN",
    "name:zho_x_preferred":[
        "\u6797\u5bb6\u5c0f\u623f"
    ],
    "wof:name":"Linjia Xiaofang",
    "wof:placetype":"locality"
},
  "geometry": {"coordinates":[123.20972999999999,48.21322],"type":"Point"}
}