{
  "type": "Feature",
  "properties": {
    "gn:admin1_code":"25",
    "gn:asciiname":"Nanchuma",
    "gn:country_code":"CN",
    "gn:dem":30,
    "gn:feature_class":"P",
    "gn:feature_code":"PPL",
    "gn:name":"Nanchuma",
    "gn:population":0,
    "gn:timezone":"Asia/Shanghai",
    "iso:country":"CN",
    "name:zho_x_preferred":[
        "\u5357\u891a\u9a6c"
    ],
    "wof:name":"Nanchuma",
    "wof:placetype":"locality"
},
  "geometry": {"coordinates":[118.56100000000001,36.848],"type":"Point"}
}