{
  "type": "Feature",
  "properties": {
    "gn:admin1_code":"32.0",
    "gn:asciiname":"Jiangjia Citang",
    "gn:country_code":"CN",
    "gn:dem":391,
    "gn:feature_class":"P",
    "gn:feature_code":"PPL",
    "gn:name":"Jiangjia Citang",
    "gn:population":0,
    "gn:timezone":"Asia/Shanghai",
    "iso:country":"CN",
    "name:zho_x_preferred":[
        "\u848b\u5bb6\u7960\u5802"
    ],
    "wof:name":"Jiangjia Citang",
    "wof:placetype":"locality"
},
  "geometry": {"coordinates":[106.63303999999999,30.69922],"type":"Point"}
}