{
  "type": "Feature",
  "properties": {
    "gn:admin1_code":"19.0",
    "gn:asciiname":"Wenjiatun",
    "gn:country_code":"CN",
    "gn:dem":56,
    "gn:feature_class":"P",
    "gn:feature_code":"PPL",
    "gn:name":"Wenjiatun",
    "gn:population":0,
    "gn:timezone":"Asia/Shanghai",
    "iso:country":"CN",
    "name:zho_x_preferred":[
        "\u6e29\u5bb6\u5c6f"
    ],
    "wof:name":"Wenjiatun",
    "wof:placetype":"locality"
},
  "geometry": {"coordinates":[120.91428000000001,40.96597],"type":"Point"}
}