{
  "type": "Feature",
  "properties": {
    "gn:admin1_code":"11.0",
    "gn:asciiname":"Jianlipai",
    "gn:country_code":"CN",
    "gn:dem":410,
    "gn:feature_class":"P",
    "gn:feature_code":"PPL",
    "gn:name":"Jianlipai",
    "gn:population":0,
    "gn:timezone":"Asia/Shanghai",
    "iso:country":"CN",
    "name:zho_x_preferred":[
        "\u5065\u91cc\u6392"
    ],
    "wof:name":"Jianlipai",
    "wof:placetype":"locality"
},
  "geometry": {"coordinates":[112.64727000000001,27.16239],"type":"Point"}
}