{
  "type": "Feature",
  "properties": {
    "gn:admin1_code":"30",
    "gn:asciiname":"Jiaopo",
    "gn:country_code":"CN",
    "gn:dem":58,
    "gn:feature_class":"P",
    "gn:feature_code":"PPL",
    "gn:name":"Jiaopo",
    "gn:population":0,
    "gn:timezone":"Asia/Shanghai",
    "iso:country":"CN",
    "name:zho_x_preferred":[
        "\u89d2\u5761"
    ],
    "wof:name":"Jiaopo",
    "wof:placetype":"locality"
},
  "geometry": {"coordinates":[111.39064999999999,21.95637],"type":"Point"}
}