{
  "type": "Feature",
  "properties": {
    "gn:admin1_code":"18.0",
    "gn:asciiname":"Fanzhao",
    "gn:country_code":"CN",
    "gn:dem":934,
    "gn:feature_class":"P",
    "gn:feature_code":"PPL",
    "gn:name":"Fanzhao",
    "gn:population":0,
    "gn:timezone":"Asia/Shanghai",
    "iso:country":"CN",
    "name:zho_x_preferred":[
        "\u756a\u53ec"
    ],
    "wof:name":"Fanzhao",
    "wof:placetype":"locality"
},
  "geometry": {"coordinates":[108.393,26.6639],"type":"Point"}
}