{
  "type": "Feature",
  "properties": {
    "gn:admin1_code":"3.0",
    "gn:asciiname":"Yanggushan",
    "gn:country_code":"CN",
    "gn:dem":388,
    "gn:feature_class":"P",
    "gn:feature_code":"PPL",
    "gn:name":"Yanggushan",
    "gn:population":0,
    "gn:timezone":"Asia/Shanghai",
    "iso:country":"CN",
    "name:zho_x_preferred":[
        "\u6768\u8c37\u5c71"
    ],
    "wof:name":"Yanggushan",
    "wof:placetype":"locality"
},
  "geometry": {"coordinates":[117.01297,27.34526],"type":"Point"}
}