{
  "type": "Feature",
  "properties": {
    "gn:admin1_code":"14.0",
    "gn:asciiname":"Balangcun",
    "gn:country_code":"CN",
    "gn:dem":4673,
    "gn:feature_class":"P",
    "gn:feature_code":"PPL",
    "gn:name":"Balangcun",
    "gn:population":0,
    "gn:timezone":"Asia/Urumqi",
    "iso:country":"CN",
    "name:zho_x_preferred":[
        "\u5df4\u6717\u6751"
    ],
    "wof:name":"Balangcun",
    "wof:placetype":"locality"
},
  "geometry": {"coordinates":[93.08869,29.63498],"type":"Point"}
}