{
  "type": "Feature",
  "properties": {
    "gn:admin1_code":"30",
    "gn:asciiname":"Yunxiao",
    "gn:country_code":"CN",
    "gn:dem":89,
    "gn:feature_class":"P",
    "gn:feature_code":"PPL",
    "gn:name":"Yunxiao",
    "gn:population":0,
    "gn:timezone":"Asia/Urumqi",
    "iso:country":"CN",
    "name:zho_x_preferred":[
        "\u4e91\u9704"
    ],
    "wof:name":"Yunxiao",
    "wof:placetype":"locality"
},
  "geometry": {"coordinates":[111.02372,22.10989],"type":"Point"}
}