{
  "type": "Feature",
  "properties": {
    "gn:admin1_code":"30.0",
    "gn:asciiname":"Baoshancun",
    "gn:country_code":"CN",
    "gn:dem":204,
    "gn:feature_class":"P",
    "gn:feature_code":"PPL",
    "gn:name":"Baoshancun",
    "gn:population":0,
    "gn:timezone":"Asia/Shanghai",
    "iso:country":"CN",
    "name:zho_x_preferred":[
        "\u5b9d\u5c71\u6751"
    ],
    "wof:name":"Baoshancun",
    "wof:placetype":"locality"
},
  "geometry": {"coordinates":[113.5506,24.04924],"type":"Point"}
}