{
  "type": "Feature",
  "properties": {
    "gn:admin1_code":"4.0",
    "gn:asciiname":"Lai'ancun",
    "gn:country_code":"CN",
    "gn:dem":31,
    "gn:feature_class":"P",
    "gn:feature_code":"PPL",
    "gn:name":"Lai\u2019ancun",
    "gn:population":0,
    "gn:timezone":"Asia/Shanghai",
    "iso:country":"CN",
    "name:und_x_variant":[
        "Lai\u2019ancun"
    ],
    "name:zho_x_preferred":[
        "\u6765\u5b89\u6751"
    ],
    "wof:name":"Lai'ancun",
    "wof:placetype":"locality"
},
  "geometry": {"coordinates":[117.49353000000001,34.28448],"type":"Point"}
}