{
  "type": "Feature",
  "properties": {
    "gn:admin1_code":"3.0",
    "gn:asciiname":"Jinzhuping",
    "gn:country_code":"CN",
    "gn:dem":327,
    "gn:feature_class":"P",
    "gn:feature_code":"PPL",
    "gn:name":"Jinzhuping",
    "gn:population":0,
    "gn:timezone":"Asia/Shanghai",
    "iso:country":"CN",
    "name:und_x_variant":[
        "\u91d1\u7af9\u576a"
    ],
    "wof:name":"Jinzhuping",
    "wof:placetype":"locality"
},
  "geometry": {"coordinates":[114.24227,28.74404],"type":"Point"}
}