{
  "type": "Feature",
  "properties": {
    "gn:admin1_code":"10",
    "gn:asciiname":"Xiawazi",
    "gn:country_code":"CN",
    "gn:dem":1298,
    "gn:feature_class":"P",
    "gn:feature_code":"PPL",
    "gn:name":"Xiawazi",
    "gn:population":0,
    "gn:timezone":"Asia/Shanghai",
    "iso:country":"CN",
    "name:zho_x_preferred":[
        "\u4e0b\u6d3c\u5b50"
    ],
    "wof:name":"Xiawazi",
    "wof:placetype":"locality"
},
  "geometry": {"coordinates":[116.39530999999999,41.8154],"type":"Point"}
}