{
  "type": "Feature",
  "properties": {
    "gn:admin1_code":"2.0",
    "gn:asciiname":"Xijia",
    "gn:country_code":"CN",
    "gn:dem":269,
    "gn:feature_class":"P",
    "gn:feature_code":"PPL",
    "gn:name":"Xijia",
    "gn:population":0,
    "gn:timezone":"Asia/Shanghai",
    "iso:country":"CN",
    "name:und_x_variant":[
        "\u5e2d\u5bb6"
    ],
    "wof:name":"Xijia",
    "wof:placetype":"locality"
},
  "geometry": {"coordinates":[119.33851,30.15261],"type":"Point"}
}