{
  "type": "Feature",
  "properties": {
    "gn:admin1_code":"25.0",
    "gn:asciiname":"Shijiananbucun",
    "gn:country_code":"CN",
    "gn:dem":16,
    "gn:feature_class":"P",
    "gn:feature_code":"PPL",
    "gn:name":"Shijiananbucun",
    "gn:population":0,
    "gn:timezone":"Asia/Shanghai",
    "iso:country":"CN",
    "name:zho_x_preferred":[
        "\u77f3\u5bb6\u5357\u57e0\u6751"
    ],
    "wof:name":"Shijiananbucun",
    "wof:placetype":"locality"
},
  "geometry": {"coordinates":[120.00888,36.55762],"type":"Point"}
}