{
  "type": "Feature",
  "properties": {
    "gn:admin1_code":"3",
    "gn:asciiname":"Qingyuan",
    "gn:country_code":"CN",
    "gn:dem":413,
    "gn:feature_class":"P",
    "gn:feature_code":"PPL",
    "gn:name":"Qingyuan",
    "gn:population":0,
    "gn:timezone":"Asia/Shanghai",
    "iso:country":"CN",
    "name:zho_x_preferred":[
        "\u6e05\u6c85"
    ],
    "wof:name":"Qingyuan",
    "wof:placetype":"locality"
},
  "geometry": {"coordinates":[114.72199999999999,26.1174],"type":"Point"}
}