{
  "type": "Feature",
  "properties": {
    "gn:admin1_code":"24.0",
    "gn:asciiname":"Beiyugou",
    "gn:country_code":"CN",
    "gn:dem":1376,
    "gn:feature_class":"P",
    "gn:feature_code":"PPL",
    "gn:name":"Beiyugou",
    "gn:population":0,
    "gn:timezone":"Asia/Shanghai",
    "iso:country":"CN",
    "name:zho_x_preferred":[
        "\u5317\u5cea\u6c9f"
    ],
    "wof:name":"Beiyugou",
    "wof:placetype":"locality"
},
  "geometry": {"coordinates":[113.14558999999998,37.24895],"type":"Point"}
}