{
  "type": "Feature",
  "properties": {
    "gn:admin1_code":"7.0",
    "gn:asciiname":"Zhegulong",
    "gn:country_code":"CN",
    "gn:dem":291,
    "gn:feature_class":"P",
    "gn:feature_code":"PPL",
    "gn:name":"Zhegulong",
    "gn:population":0,
    "gn:timezone":"Asia/Shanghai",
    "iso:country":"CN",
    "name:zho_x_preferred":[
        "\u9e67\u9e2a\u5785"
    ],
    "wof:name":"Zhegulong",
    "wof:placetype":"locality"
},
  "geometry": {"coordinates":[118.4592,27.61029000000001],"type":"Point"}
}