{
  "type": "Feature",
  "properties": {
    "gn:admin1_code":"12.0",
    "gn:asciiname":"Leishici",
    "gn:country_code":"CN",
    "gn:dem":168,
    "gn:feature_class":"P",
    "gn:feature_code":"PPL",
    "gn:name":"Leishici",
    "gn:population":0,
    "gn:timezone":"Asia/Shanghai",
    "iso:country":"CN",
    "name:zho_x_preferred":[
        "Leishici"
    ],
    "name:zho_x_variant":[
        "\u96f7\u6c0f\u7960"
    ],
    "wof:name":"Leishici",
    "wof:placetype":"locality"
},
  "geometry": {"coordinates":[115.22436999999999,30.94427],"type":"Point"}
}