{
  "type": "Feature",
  "properties": {
    "gn:admin1_code":"13.0",
    "gn:asciiname":"Yengiawat",
    "gn:country_code":"CN",
    "gn:dem":1310,
    "gn:feature_class":"P",
    "gn:feature_code":"PPLA4",
    "gn:name":"Yengiawat",
    "gn:population":0,
    "gn:timezone":"Asia/Shanghai",
    "iso:country":"CN",
    "name:uig_x_preferred":[
        "Y\u00e9ngiawat"
    ],
    "name:uig_x_variant":[
        "\u064a\u06d0\u06ad\u0649\u0626\u0627\u06cb\u0627\u062a",
        "\u0415\u04a3\u0438\u0430\u0432\u0430\u0442"
    ],
    "name:und_x_variant":[
        "Ying\u2019awati",
        "Ying\u2019awati Xiang"
    ],
    "name:zho_x_preferred":[
        "\u82f1\u963f\u74e6\u63d0"
    ],
    "name:zho_x_variant":[
        "\u82f1\u963f\u74e6\u63d0\u4e61"
    ],
    "wof:name":"Yengiawat",
    "wof:placetype":"locality"
},
  "geometry": {"coordinates":[79.46861,41.3525],"type":"Point"}
}