{
  "type": "Feature",
  "properties": {
    "gn:admin1_code":"19.0",
    "gn:asciiname":"Dexingbucun",
    "gn:country_code":"CN",
    "gn:dem":22,
    "gn:feature_class":"P",
    "gn:feature_code":"PPL",
    "gn:name":"Dexingbucun",
    "gn:population":0,
    "gn:timezone":"Asia/Shanghai",
    "iso:country":"CN",
    "name:zho_x_preferred":[
        "\u5fb7\u5174\u5821\u6751"
    ],
    "wof:name":"Dexingbucun",
    "wof:placetype":"locality"
},
  "geometry": {"coordinates":[122.89400000000001,41.7316],"type":"Point"}
}