{
  "type": "Feature",
  "properties": {
    "gn:admin1_code":"3.0",
    "gn:asciiname":"Matitan",
    "gn:country_code":"CN",
    "gn:dem":86,
    "gn:feature_class":"P",
    "gn:feature_code":"PPL",
    "gn:name":"Matitan",
    "gn:population":0,
    "gn:timezone":"Asia/Shanghai",
    "iso:country":"CN",
    "name:und_x_variant":[
        "\u9a6c\u8e44\u6f6d"
    ],
    "wof:name":"Matitan",
    "wof:placetype":"locality"
},
  "geometry": {"coordinates":[115.81171000000001,27.5781],"type":"Point"}
}