{
  "type": "Feature",
  "properties": {
    "gn:admin1_code":"19.0",
    "gn:asciiname":"Guopingfang",
    "gn:country_code":"CN",
    "gn:dem":144,
    "gn:feature_class":"P",
    "gn:feature_code":"PPL",
    "gn:name":"Guopingfang",
    "gn:population":0,
    "gn:timezone":"Asia/Shanghai",
    "iso:country":"CN",
    "name:zho_x_preferred":[
        "\u90ed\u5e73\u623f"
    ],
    "wof:name":"Guopingfang",
    "wof:placetype":"locality"
},
  "geometry": {"coordinates":[123.83487,43.32343],"type":"Point"}
}