{
  "type": "Feature",
  "properties": {
    "gn:admin1_code":"15.0",
    "gn:asciiname":"Huaixing",
    "gn:country_code":"CN",
    "gn:dem":1893,
    "gn:feature_class":"P",
    "gn:feature_code":"PPL",
    "gn:name":"Huaixing",
    "gn:population":0,
    "gn:timezone":"Asia/Shanghai",
    "iso:country":"CN",
    "name:zho_x_preferred":[
        "\u6000\u661f"
    ],
    "wof:name":"Huaixing",
    "wof:placetype":"locality"
},
  "geometry": {"coordinates":[104.551,37.0906],"type":"Point"}
}