{
  "type": "Feature",
  "properties": {
    "gn:admin1_code":"4.0",
    "gn:asciiname":"Beizhangjiadai",
    "gn:country_code":"CN",
    "gn:dem":7,
    "gn:feature_class":"P",
    "gn:feature_code":"PPL",
    "gn:name":"Beizhangjiadai",
    "gn:population":0,
    "gn:timezone":"Asia/Shanghai",
    "iso:country":"CN",
    "name:zho_x_preferred":[
        "\u5317\u5f20\u5bb6\u5788"
    ],
    "wof:name":"Beizhangjiadai",
    "wof:placetype":"locality"
},
  "geometry": {"coordinates":[120.16718,32.02927],"type":"Point"}
}