{
  "type": "Feature",
  "properties": {
    "gn:admin1_code":"02",
    "gn:asciiname":"Shang-shan-ti",
    "gn:country_code":"CN",
    "gn:dem":38,
    "gn:feature_class":"P",
    "gn:feature_code":"PPL",
    "gn:name":"Shang-shan-ti",
    "gn:population":0,
    "gn:timezone":"Asia/Shanghai",
    "iso:country":"CN",
    "wof:name":"Shang-shan-ti",
    "wof:placetype":"locality"
},
  "geometry": {"coordinates":[121.48193999999999,29.63806],"type":"Point"}
}