{
  "type": "Feature",
  "properties": {
    "gn:admin1_code":"19.0",
    "gn:asciiname":"Dajiatun",
    "gn:country_code":"CN",
    "gn:dem":82,
    "gn:feature_class":"P",
    "gn:feature_code":"PPL",
    "gn:name":"Dajiatun",
    "gn:population":0,
    "gn:timezone":"Asia/Shanghai",
    "iso:country":"CN",
    "name:und_x_variant":[
        "\u5927\u8d3e\u5c6f"
    ],
    "name:zho_x_preferred":[
        "\u5927\u8d3e\u5c6f"
    ],
    "wof:name":"Dajiatun",
    "wof:placetype":"locality"
},
  "geometry": {"coordinates":[121.90549,39.50812],"type":"Point"}
}