{
  "type": "Feature",
  "properties": {
    "gn:admin1_code":"14.0",
    "gn:asciiname":"Zhipuqi",
    "gn:country_code":"CN",
    "gn:dem":4337,
    "gn:feature_class":"P",
    "gn:feature_code":"PPL",
    "gn:name":"Zhipuqi",
    "gn:population":0,
    "gn:timezone":"Asia/Shanghai",
    "iso:country":"CN",
    "name:zho_x_preferred":[
        "\u652f\u666e\u9f50"
    ],
    "wof:name":"Zhipuqi",
    "wof:placetype":"locality"
},
  "geometry": {"coordinates":[78.6056,32.5723],"type":"Point"}
}