{
  "type": "Feature",
  "properties": {
    "gn:admin1_code":"16.0",
    "gn:asciiname":"Cenlin",
    "gn:country_code":"CN",
    "gn:dem":100,
    "gn:feature_class":"P",
    "gn:feature_code":"PPL",
    "gn:name":"Cenlin",
    "gn:population":0,
    "gn:timezone":"Asia/Shanghai",
    "iso:country":"CN",
    "name:zho_x_preferred":[
        "\u6d94\u6dcb"
    ],
    "wof:name":"Cenlin",
    "wof:placetype":"locality"
},
  "geometry": {"coordinates":[107.869,22.7255],"type":"Point"}
}