{
  "type": "Feature",
  "properties": {
    "gn:admin1_code":"26.0",
    "gn:asciiname":"Moujiagou",
    "gn:country_code":"CN",
    "gn:dem":1452,
    "gn:feature_class":"P",
    "gn:feature_code":"PPL",
    "gn:name":"Moujiagou",
    "gn:population":0,
    "gn:timezone":"Asia/Shanghai",
    "iso:country":"CN",
    "name:zho_x_preferred":[
        "\u725f\u5bb6\u6c9f"
    ],
    "wof:name":"Moujiagou",
    "wof:placetype":"locality"
},
  "geometry": {"coordinates":[109.48495,33.85994],"type":"Point"}
}