{
  "type": "Feature",
  "properties": {
    "gn:admin1_code":"19.0",
    "gn:asciiname":"Shanyoutun",
    "gn:country_code":"CN",
    "gn:dem":94,
    "gn:feature_class":"P",
    "gn:feature_code":"PPL",
    "gn:name":"Shanyoutun",
    "gn:population":0,
    "gn:timezone":"Asia/Shanghai",
    "iso:country":"CN",
    "name:zho_x_preferred":[
        "\u5584\u53cb\u5c6f"
    ],
    "wof:name":"Shanyoutun",
    "wof:placetype":"locality"
},
  "geometry": {"coordinates":[123.08968,42.6056],"type":"Point"}
}