{
  "type": "Feature",
  "properties": {
    "gn:admin1_code":"15.0",
    "gn:asciiname":"Xiangjiaping",
    "gn:country_code":"CN",
    "gn:dem":1254,
    "gn:feature_class":"P",
    "gn:feature_code":"PPL",
    "gn:name":"Xiangjiaping",
    "gn:population":0,
    "gn:timezone":"Asia/Shanghai",
    "iso:country":"CN",
    "name:und_x_variant":[
        "\u5411\u5bb6\u576a"
    ],
    "wof:name":"Xiangjiaping",
    "wof:placetype":"locality"
},
  "geometry": {"coordinates":[106.38061999999999,34.03371],"type":"Point"}
}