{
  "type": "Feature",
  "properties": {
    "gn:admin1_code":"32.0",
    "gn:asciiname":"Xindianzi",
    "gn:country_code":"CN",
    "gn:dem":382,
    "gn:feature_class":"P",
    "gn:feature_code":"PPL",
    "gn:name":"Xindianzi",
    "gn:population":0,
    "gn:timezone":"Asia/Shanghai",
    "iso:country":"CN",
    "name:zho_x_preferred":[
        "\u65b0\u5e97\u5b50"
    ],
    "wof:name":"Xindianzi",
    "wof:placetype":"locality"
},
  "geometry": {"coordinates":[106.377,30.5263],"type":"Point"}
}