{
  "type": "Feature",
  "properties": {
    "gn:admin1_code":"15.0",
    "gn:asciiname":"Zhaojiazhuang",
    "gn:country_code":"CN",
    "gn:dem":1485,
    "gn:feature_class":"P",
    "gn:feature_code":"PPL",
    "gn:name":"Zhaojiazhuang",
    "gn:population":0,
    "gn:timezone":"Asia/Shanghai",
    "iso:country":"CN",
    "name:zho_x_preferred":[
        "\u8d75\u5bb6\u5e84"
    ],
    "wof:name":"Zhaojiazhuang",
    "wof:placetype":"locality"
},
  "geometry": {"coordinates":[102.634,38.0944],"type":"Point"}
}