{
  "type": "Feature",
  "properties": {
    "gn:admin1_code":"32.0",
    "gn:asciiname":"Wu'an",
    "gn:country_code":"CN",
    "gn:dem":613,
    "gn:feature_class":"P",
    "gn:feature_code":"PPL",
    "gn:name":"Wu\u2019an",
    "gn:population":0,
    "gn:timezone":"Asia/Shanghai",
    "iso:country":"CN",
    "name:und_x_variant":[
        "Wu\u2019an"
    ],
    "name:zho_x_preferred":[
        "\u6b66\u5eb5"
    ],
    "wof:name":"Wu'an",
    "wof:placetype":"locality"
},
  "geometry": {"coordinates":[105.253,31.7978],"type":"Point"}
}