{
  "type": "Feature",
  "properties": {
    "gn:admin1_code":"32.0",
    "gn:asciiname":"Wu'an",
    "gn:country_code":"CN",
    "gn:dem":613,
    "gn:feature_class":"P",
    "gn:feature_code":"PPL",
    "gn:name":"Wu\u2019an",
    "gn:population":0,
    "gn:timezone":"Asia/Shanghai",
    "iso:country":"CN",
    "name:ara_x_preferred":[
        "\u0648\u0648\u0627\u0646"
    ],
    "name:deu_x_preferred":[
        "Wu\u2019an"
    ],
    "name:fra_x_preferred":[
        "Wu'an"
    ],
    "name:ita_x_preferred":[
        "Wu'an"
    ],
    "name:jpn_x_preferred":[
        "\u6b66\u5b89\u5e02"
    ],
    "name:kik_x_preferred":[
        "Wu'an"
    ],
    "name:kor_x_preferred":[
        "\uc6b0\uc548\uc2dc"
    ],
    "name:nor_x_preferred":[
        "Wu'an"
    ],
    "name:pam_x_preferred":[
        "Wu'an"
    ],
    "name:rus_x_preferred":[
        "\u0423\u0430\u043d\u044c"
    ],
    "name:swe_x_preferred":[
        "Wu'an"
    ],
    "name:urd_x_preferred":[
        "\u0648\u0648\u0622\u0646"
    ],
    "name:vie_x_preferred":[
        "V\u0169 An"
    ],
    "name:war_x_preferred":[
        "Wu'an"
    ],
    "name:zho_x_preferred":[
        "\u6b66\u5eb5"
    ],
    "name:zho_x_variant":[
        "\u6b66\u5b89\u5e02"
    ],
    "wof:name":"Wu'an",
    "wof:placetype":"locality"
},
  "geometry": {"coordinates":[105.253,31.7978],"type":"Point"}
}