{
  "type": "Feature",
  "properties": {
    "gn:admin1_code":"26.0",
    "gn:asciiname":"Yuejiayaozi",
    "gn:country_code":"CN",
    "gn:dem":1168,
    "gn:feature_class":"P",
    "gn:feature_code":"PPL",
    "gn:name":"Yuejiayaozi",
    "gn:population":0,
    "gn:timezone":"Asia/Shanghai",
    "iso:country":"CN",
    "name:zho_x_preferred":[
        "\u5cb3\u5bb6\u7a91\u5b50"
    ],
    "wof:name":"Yuejiayaozi",
    "wof:placetype":"locality"
},
  "geometry": {"coordinates":[109.42398,36.83768],"type":"Point"}
}