{
  "type": "Feature",
  "properties": {
    "gn:admin1_code":"18",
    "gn:asciiname":"Cuntang",
    "gn:country_code":"CN",
    "gn:dem":521,
    "gn:feature_class":"P",
    "gn:feature_code":"PPL",
    "gn:name":"Cuntang",
    "gn:population":0,
    "gn:timezone":"Asia/Shanghai",
    "iso:country":"CN",
    "name:zho_x_preferred":[
        "\u6751\u5858"
    ],
    "wof:name":"Cuntang",
    "wof:placetype":"locality"
},
  "geometry": {"coordinates":[108.27800000000001,28.3564],"type":"Point"}
}