{
  "type": "Feature",
  "properties": {
    "gn:admin1_code":"29.0",
    "gn:asciiname":"Xinfa",
    "gn:country_code":"CN",
    "gn:dem":2331,
    "gn:feature_class":"P",
    "gn:feature_code":"PPL",
    "gn:name":"Xinfa",
    "gn:population":0,
    "gn:timezone":"Asia/Shanghai",
    "iso:country":"CN",
    "name:zho_x_preferred":[
        "\u65b0\u53d1"
    ],
    "wof:name":"Xinfa",
    "wof:placetype":"locality"
},
  "geometry": {"coordinates":[100.29600000000001,26.1555],"type":"Point"}
}