{
  "type": "Feature",
  "properties": {
    "gn:admin1_code":"18.0",
    "gn:asciiname":"Huangjiadong",
    "gn:country_code":"CN",
    "gn:dem":673,
    "gn:feature_class":"P",
    "gn:feature_code":"PPL",
    "gn:name":"Huangjiadong",
    "gn:population":0,
    "gn:timezone":"Asia/Shanghai",
    "iso:country":"CN",
    "name:zho_x_preferred":[
        "\u9ec4\u5bb6\u6d1e"
    ],
    "wof:name":"Huangjiadong",
    "wof:placetype":"locality"
},
  "geometry": {"coordinates":[108.565,28.5612],"type":"Point"}
}