{
  "type": "Feature",
  "properties": {
    "gn:admin1_code":"29.0",
    "gn:asciiname":"Dazhizu",
    "gn:country_code":"CN",
    "gn:dem":1947,
    "gn:feature_class":"P",
    "gn:feature_code":"PPL",
    "gn:name":"Dazhizu",
    "gn:population":0,
    "gn:timezone":"Asia/Shanghai",
    "iso:country":"CN",
    "name:zho_x_preferred":[
        "\u5927\u6cbb\u7956"
    ],
    "wof:name":"Dazhizu",
    "wof:placetype":"locality"
},
  "geometry": {"coordinates":[103.035,25.695],"type":"Point"}
}