{
  "type": "Feature",
  "properties": {
    "gn:admin1_code":"08",
    "gn:asciiname":"Sanchakou",
    "gn:cc2":"CN",
    "gn:country_code":"CN",
    "gn:dem":93,
    "gn:feature_class":"P",
    "gn:feature_code":"PPL",
    "gn:name":"Sanchakou",
    "gn:population":0,
    "gn:timezone":"Asia/Shanghai",
    "iso:country":"CN",
    "name:ceb_x_preferred":[
        "Sanchakou"
    ],
    "name:swe_x_preferred":[
        "Sanchakou"
    ],
    "name:und_x_variant":[
        "Tung-ning-hsien",
        "Tung-ning",
        "Sanchakou"
    ],
    "name:zho_x_preferred":[
        "\u4e09\u5c94\u53e3"
    ],
    "wof:name":"Sanchakou",
    "wof:placetype":"locality"
},
  "geometry": {"coordinates":[131.26111,44.02444000000001],"type":"Point"}
}