{
  "type": "Feature",
  "properties": {
    "gn:admin1_code":"4.0",
    "gn:asciiname":"Yangjiawan",
    "gn:country_code":"CN",
    "gn:dem":2,
    "gn:feature_class":"P",
    "gn:feature_code":"PPL",
    "gn:name":"Yangjiawan",
    "gn:population":0,
    "gn:timezone":"Asia/Shanghai",
    "iso:country":"CN",
    "name:zho_x_preferred":[
        "Yangjiawan"
    ],
    "name:zho_x_variant":[
        "\u6768\u5bb6\u6e7e"
    ],
    "wof:name":"Yangjiawan",
    "wof:placetype":"locality"
},
  "geometry": {"coordinates":[119.84551999999999,33.38025],"type":"Point"}
}