{
  "type": "Feature",
  "properties": {
    "gn:admin1_code":"24.0",
    "gn:asciiname":"Puzigou",
    "gn:country_code":"CN",
    "gn:dem":1361,
    "gn:feature_class":"P",
    "gn:feature_code":"PPL",
    "gn:name":"Puzigou",
    "gn:population":0,
    "gn:timezone":"Asia/Shanghai",
    "iso:country":"CN",
    "name:und_x_variant":[
        "\u6734\u5b50\u6c9f"
    ],
    "name:zho_x_preferred":[
        "\u6734\u5b50\u6c9f"
    ],
    "wof:name":"Puzigou",
    "wof:placetype":"locality"
},
  "geometry": {"coordinates":[113.93698999999999,39.27963],"type":"Point"}
}