{
  "type": "Feature",
  "properties": {
    "gn:admin1_code":"29.0",
    "gn:asciiname":"Yiluode",
    "gn:country_code":"CN",
    "gn:dem":1616,
    "gn:feature_class":"P",
    "gn:feature_code":"PPL",
    "gn:name":"Yiluode",
    "gn:population":0,
    "gn:timezone":"Asia/Shanghai",
    "iso:country":"CN",
    "name:zho_x_preferred":[
        "\u77e3\u502e\u5f97"
    ],
    "wof:name":"Yiluode",
    "wof:placetype":"locality"
},
  "geometry": {"coordinates":[104.215,23.8917],"type":"Point"}
}