{
  "type": "Feature",
  "properties": {
    "gn:admin1_code":"23",
    "gn:asciiname":"Gaohang",
    "gn:country_code":"CN",
    "gn:dem":5,
    "gn:feature_class":"P",
    "gn:feature_code":"PPL",
    "gn:name":"Gaohang",
    "gn:population":0,
    "gn:timezone":"Asia/Shanghai",
    "iso:country":"CN",
    "name:und_x_variant":[
        "Pei-kao-hang-chen",
        "Kao-hang",
        "Gaohang",
        "Kao-hang-chen",
        "Gaohangzhen",
        "\u9ad8\u884c"
    ],
    "wof:name":"Gaohang",
    "wof:placetype":"locality"
},
  "geometry": {"coordinates":[121.60222,31.29722000000001],"type":"Point"}
}