{
  "type": "Feature",
  "properties": {
    "gn:admin1_code":"07",
    "gn:asciiname":"Shaxikou",
    "gn:cc2":"CN",
    "gn:country_code":"CN",
    "gn:dem":235,
    "gn:feature_class":"P",
    "gn:feature_code":"PPL",
    "gn:name":"Shaxikou",
    "gn:population":0,
    "gn:timezone":"Asia/Shanghai",
    "iso:country":"CN",
    "name:und_x_variant":[
        "Sha-ch\u2019i-k\u2019ou",
        "Sha-hsi-k\u2019ou",
        "Sha-ch\u2019i",
        "Shaxikou",
        "\u6c99\u6eaa\u53e3"
    ],
    "wof:name":"Shaxikou",
    "wof:placetype":"locality"
},
  "geometry": {"coordinates":[118.03333000000001,26.56667],"type":"Point"}
}