{
  "type": "Feature",
  "properties": {
    "gn:admin1_code":"16.0",
    "gn:asciiname":"Zhoutian",
    "gn:country_code":"CN",
    "gn:dem":291,
    "gn:feature_class":"P",
    "gn:feature_code":"PPL",
    "gn:name":"Zhoutian",
    "gn:population":0,
    "gn:timezone":"Asia/Shanghai",
    "iso:country":"CN",
    "name:zho_x_preferred":[
        "\u6d32\u7530"
    ],
    "wof:name":"Zhoutian",
    "wof:placetype":"locality"
},
  "geometry": {"coordinates":[110.19499999999999,24.6544],"type":"Point"}
}