{
  "type": "Feature",
  "properties": {
    "gn:admin1_code":"8.0",
    "gn:asciiname":"Tailaicun",
    "gn:country_code":"CN",
    "gn:dem":235,
    "gn:feature_class":"P",
    "gn:feature_code":"PPL",
    "gn:name":"Tailaicun",
    "gn:population":0,
    "gn:timezone":"Asia/Shanghai",
    "iso:country":"CN",
    "name:zho_x_preferred":[
        "\u6cf0\u6765\u6751"
    ],
    "wof:name":"Tailaicun",
    "wof:placetype":"locality"
},
  "geometry": {"coordinates":[125.57125000000001,47.68662],"type":"Point"}
}