{
  "type": "Feature",
  "properties": {
    "gn:admin1_code":"14.0",
    "gn:asciiname":"Rinco",
    "gn:country_code":"CN",
    "gn:dem":3999,
    "gn:feature_class":"P",
    "gn:feature_code":"PPLF",
    "gn:name":"Rinco",
    "gn:population":0,
    "gn:timezone":"Asia/Urumqi",
    "iso:country":"CN",
    "name:bod_x_preferred":[
        "Rinco"
    ],
    "name:zho_x_preferred":[
        "Ricuo"
    ],
    "name:zho_x_variant":[
        "\u65e5\u63aa"
    ],
    "wof:name":"Rinco",
    "wof:placetype":"locality"
},
  "geometry": {"coordinates":[90.10599999999999,29.406],"type":"Point"}
}