{
  "type": "Feature",
  "properties": {
    "gn:admin1_code":"21.0",
    "gn:asciiname":"Zhamichuan",
    "gn:country_code":"CN",
    "gn:dem":1569,
    "gn:feature_class":"P",
    "gn:feature_code":"PPL",
    "gn:name":"Zhamichuan",
    "gn:population":0,
    "gn:timezone":"Asia/Shanghai",
    "iso:country":"CN",
    "name:zho_x_preferred":[
        "\u624e\u7c73\u5ddd"
    ],
    "wof:name":"Zhamichuan",
    "wof:placetype":"locality"
},
  "geometry": {"coordinates":[105.82899999999999,36.8602],"type":"Point"}
}