{
  "type": "Feature",
  "properties": {
    "gn:admin1_code":"33.0",
    "gn:asciiname":"Zhong'an",
    "gn:country_code":"CN",
    "gn:dem":332,
    "gn:feature_class":"P",
    "gn:feature_code":"PPL",
    "gn:name":"Zhong\u2019an",
    "gn:population":0,
    "gn:timezone":"Asia/Shanghai",
    "iso:country":"CN",
    "name:und_x_variant":[
        "Zhong\u2019an"
    ],
    "name:zho_x_preferred":[
        "\u4e2d\u5b89"
    ],
    "wof:name":"Zhong'an",
    "wof:placetype":"locality"
},
  "geometry": {"coordinates":[108.08721,31.12163],"type":"Point"}
}