{
  "type": "Feature",
  "properties": {
    "gn:admin1_code":"10",
    "gn:asciiname":"Huangjiayao",
    "gn:country_code":"CN",
    "gn:dem":1570,
    "gn:feature_class":"P",
    "gn:feature_code":"PPL",
    "gn:name":"Huangjiayao",
    "gn:population":0,
    "gn:timezone":"Asia/Shanghai",
    "iso:country":"CN",
    "name:zho_x_preferred":[
        "\u9ec4\u5bb6\u7a91"
    ],
    "wof:name":"Huangjiayao",
    "wof:placetype":"locality"
},
  "geometry": {"coordinates":[115.21338,41.19085],"type":"Point"}
}