{
  "type": "Feature",
  "properties": {
    "gn:admin1_code":"15.0",
    "gn:asciiname":"Dongbu",
    "gn:country_code":"CN",
    "gn:dem":1766,
    "gn:feature_class":"P",
    "gn:feature_code":"PPL",
    "gn:name":"Dongbu",
    "gn:population":0,
    "gn:timezone":"Asia/Shanghai",
    "iso:country":"CN",
    "name:und_x_variant":[
        "\u8463\u5821"
    ],
    "wof:name":"Dongbu",
    "wof:placetype":"locality"
},
  "geometry": {"coordinates":[105.22736999999999,33.99227],"type":"Point"}
}