{
  "type": "Feature",
  "properties": {
    "gn:admin1_code":"10.0",
    "gn:asciiname":"Damanggou",
    "gn:country_code":"CN",
    "gn:dem":1146,
    "gn:feature_class":"P",
    "gn:feature_code":"PPL",
    "gn:name":"Damanggou",
    "gn:population":0,
    "gn:timezone":"Asia/Shanghai",
    "iso:country":"CN",
    "name:zho_x_preferred":[
        "\u5927\u87d2\u6c9f"
    ],
    "wof:name":"Damanggou",
    "wof:placetype":"locality"
},
  "geometry": {"coordinates":[114.52871,40.27461],"type":"Point"}
}