{
  "type": "Feature",
  "properties": {
    "gn:admin1_code":"8.0",
    "gn:asciiname":"Yongchengcun",
    "gn:country_code":"CN",
    "gn:dem":53,
    "gn:feature_class":"P",
    "gn:feature_code":"PPL",
    "gn:name":"Yongchengcun",
    "gn:population":0,
    "gn:timezone":"Asia/Shanghai",
    "iso:country":"CN",
    "name:zho_x_preferred":[
        "\u6c38\u57ce\u6751"
    ],
    "wof:name":"Yongchengcun",
    "wof:placetype":"locality"
},
  "geometry": {"coordinates":[132.86930000000001,47.65911],"type":"Point"}
}