{
  "type": "Feature",
  "properties": {
    "gn:admin1_code":"30",
    "gn:asciiname":"Gaoping",
    "gn:country_code":"CN",
    "gn:dem":4,
    "gn:feature_class":"P",
    "gn:feature_code":"PPL",
    "gn:name":"Gaoping",
    "gn:population":0,
    "gn:timezone":"Asia/Shanghai",
    "iso:country":"CN",
    "name:ara_x_preferred":[
        "\u0642\u0627\u0648\u0628\u064a\u0646\u063a"
    ],
    "name:ceb_x_preferred":[
        "Gaoping Shi"
    ],
    "name:deu_x_preferred":[
        "Gaoping"
    ],
    "name:fra_x_preferred":[
        "Gaoping"
    ],
    "name:ita_x_preferred":[
        "Gaoping"
    ],
    "name:jpn_x_preferred":[
        "\u9ad8\u5e73\u5e02"
    ],
    "name:kik_x_preferred":[
        "Gaoping"
    ],
    "name:kor_x_preferred":[
        "\uac00\uc624\ud551\uc2dc"
    ],
    "name:mlg_x_preferred":[
        "Gaoping"
    ],
    "name:nld_x_preferred":[
        "Gaoping"
    ],
    "name:nor_x_preferred":[
        "Gaoping"
    ],
    "name:rus_x_preferred":[
        "\u0413\u0430\u043e\u043f\u0438\u043d"
    ],
    "name:swe_x_preferred":[
        "Gaoping"
    ],
    "name:und_x_variant":[
        "Ta-li",
        "Dali"
    ],
    "name:urd_x_preferred":[
        "\u06af\u0627\u0648\u067e\u0646\u06af"
    ],
    "name:vie_x_preferred":[
        "Cao B\u00ecnh"
    ],
    "name:zho_x_preferred":[
        "\u9ad8\u5e73"
    ],
    "name:zho_x_variant":[
        "\u9ad8\u5e73\u5e02"
    ],
    "wof:name":"Gaoping",
    "wof:placetype":"locality"
},
  "geometry": {"coordinates":[112.83646,23.14974],"type":"Point"}
}