{
  "type": "Feature",
  "properties": {
    "gn:admin1_code":"19.0",
    "gn:asciiname":"Ligangzi",
    "gn:country_code":"CN",
    "gn:dem":25,
    "gn:feature_class":"P",
    "gn:feature_code":"PPL",
    "gn:name":"Ligangzi",
    "gn:population":0,
    "gn:timezone":"Asia/Shanghai",
    "iso:country":"CN",
    "name:und_x_variant":[
        "\u674e\u5c97\u5b50"
    ],
    "name:zho_x_preferred":[
        "\u674e\u5c97\u5b50"
    ],
    "wof:name":"Ligangzi",
    "wof:placetype":"locality"
},
  "geometry": {"coordinates":[122.39189,41.82196],"type":"Point"}
}