{
  "type": "Feature",
  "properties": {
    "gn:admin1_code":"3",
    "gn:asciiname":"Zhukeng",
    "gn:country_code":"CN",
    "gn:dem":259,
    "gn:feature_class":"P",
    "gn:feature_code":"PPL",
    "gn:name":"Zhukeng",
    "gn:population":0,
    "gn:timezone":"Asia/Shanghai",
    "iso:country":"CN",
    "name:zho_x_preferred":[
        "\u7af9\u5751"
    ],
    "wof:name":"Zhukeng",
    "wof:placetype":"locality"
},
  "geometry": {"coordinates":[114.19771,25.83442],"type":"Point"}
}