{
  "type": "Feature",
  "properties": {
    "gn:admin1_code":"14",
    "gn:asciiname":"Luncun",
    "gn:country_code":"CN",
    "gn:dem":4536,
    "gn:feature_class":"P",
    "gn:feature_code":"PPL",
    "gn:name":"Luncun",
    "gn:population":0,
    "gn:timezone":"Asia/Urumqi",
    "iso:country":"CN",
    "name:zho_x_preferred":[
        "\u4f26\u6751"
    ],
    "wof:name":"Luncun",
    "wof:placetype":"locality"
},
  "geometry": {"coordinates":[89.8562,28.494],"type":"Point"}
}