{
  "type": "Feature",
  "properties": {
    "gn:admin1_code":"11.0",
    "gn:asciiname":"Shanghengzhou",
    "gn:country_code":"CN",
    "gn:dem":32,
    "gn:feature_class":"P",
    "gn:feature_code":"PPL",
    "gn:name":"Shanghengzhou",
    "gn:population":0,
    "gn:timezone":"Asia/Shanghai",
    "iso:country":"CN",
    "name:zho_x_preferred":[
        "\u4e0a\u6a2a\u6d32"
    ],
    "wof:name":"Shanghengzhou",
    "wof:placetype":"locality"
},
  "geometry": {"coordinates":[112.49235,29.32366],"type":"Point"}
}