{
  "type": "Feature",
  "properties": {
    "gn:admin1_code":"14.0",
    "gn:asciiname":"Tuosangmulin",
    "gn:country_code":"CN",
    "gn:dem":4118,
    "gn:feature_class":"P",
    "gn:feature_code":"PPL",
    "gn:name":"Tuosangmulin",
    "gn:population":0,
    "gn:timezone":"Asia/Urumqi",
    "iso:country":"CN",
    "name:zho_x_preferred":[
        "\u6258\u6851\u6728\u6797"
    ],
    "wof:name":"Tuosangmulin",
    "wof:placetype":"locality"
},
  "geometry": {"coordinates":[87.0461,28.412],"type":"Point"}
}