{
  "type": "Feature",
  "properties": {
    "gn:admin1_code":"14.0",
    "gn:asciiname":"Tongsacun",
    "gn:country_code":"CN",
    "gn:dem":3426,
    "gn:feature_class":"P",
    "gn:feature_code":"PPL",
    "gn:name":"Tongsacun",
    "gn:population":0,
    "gn:timezone":"Asia/Urumqi",
    "iso:country":"CN",
    "name:zho_x_preferred":[
        "\u901a\u8428\u6751"
    ],
    "wof:name":"Tongsacun",
    "wof:placetype":"locality"
},
  "geometry": {"coordinates":[98.08342,29.99167000000001],"type":"Point"}
}