{
  "type": "Feature",
  "properties": {
    "gn:admin1_code":"23.0",
    "gn:asciiname":"Bayao Wudui",
    "gn:country_code":"CN",
    "gn:dem":2,
    "gn:feature_class":"P",
    "gn:feature_code":"PPLF",
    "gn:name":"Bayao Wudui",
    "gn:population":0,
    "gn:timezone":"Asia/Shanghai",
    "iso:country":"CN",
    "name:zho_x_preferred":[
        "Bayao Wudui"
    ],
    "name:zho_x_variant":[
        "\u516b\u6ee7\u4e94\u961f"
    ],
    "wof:name":"Bayao Wudui",
    "wof:placetype":"locality"
},
  "geometry": {"coordinates":[121.76299,31.47975],"type":"Point"}
}