{
  "type": "Feature",
  "properties": {
    "gn:admin1_code":"25",
    "gn:asciiname":"Xiahe",
    "gn:country_code":"CN",
    "gn:dem":108,
    "gn:feature_class":"P",
    "gn:feature_code":"PPL",
    "gn:name":"Xiahe",
    "gn:population":0,
    "gn:timezone":"Asia/Shanghai",
    "iso:country":"CN",
    "name:und_x_variant":[
        "\u4e0b\u6cb3"
    ],
    "wof:name":"Xiahe",
    "wof:placetype":"locality"
},
  "geometry": {"coordinates":[119.13021000000001,35.82419],"type":"Point"}
}