{
  "type": "Feature",
  "properties": {
    "gn:admin1_code":"14.0",
    "gn:asciiname":"Zhongwencun",
    "gn:country_code":"CN",
    "gn:dem":3144,
    "gn:feature_class":"P",
    "gn:feature_code":"PPL",
    "gn:name":"Zhongwencun",
    "gn:population":0,
    "gn:timezone":"Asia/Urumqi",
    "iso:country":"CN",
    "name:zho_x_preferred":[
        "\u4ef2\u6e29\u6751"
    ],
    "wof:name":"Zhongwencun",
    "wof:placetype":"locality"
},
  "geometry": {"coordinates":[92.85469000000001,29.08139000000001],"type":"Point"}
}