{
  "type": "Feature",
  "properties": {
    "gn:admin1_code":"16.0",
    "gn:asciiname":"Luosunchong",
    "gn:country_code":"CN",
    "gn:dem":181,
    "gn:feature_class":"P",
    "gn:feature_code":"PPL",
    "gn:name":"Luosunchong",
    "gn:population":0,
    "gn:timezone":"Asia/Shanghai",
    "iso:country":"CN",
    "name:zho_x_preferred":[
        "\u7f57\u7b0b\u51b2"
    ],
    "wof:name":"Luosunchong",
    "wof:placetype":"locality"
},
  "geometry": {"coordinates":[110.64700000000001,23.1139],"type":"Point"}
}