{
  "type": "Feature",
  "properties": {
    "gn:admin1_code":"7.0",
    "gn:asciiname":"Jiangshekeng",
    "gn:country_code":"CN",
    "gn:dem":645,
    "gn:feature_class":"P",
    "gn:feature_code":"PPL",
    "gn:name":"Jiangshekeng",
    "gn:population":0,
    "gn:timezone":"Asia/Shanghai",
    "iso:country":"CN",
    "name:und_x_variant":[
        "\u59dc\u7572\u5751"
    ],
    "name:zho_x_preferred":[
        "\u59dc\u7572\u5751"
    ],
    "wof:name":"Jiangshekeng",
    "wof:placetype":"locality"
},
  "geometry": {"coordinates":[116.06796,25.68351],"type":"Point"}
}