{
  "type": "Feature",
  "properties": {
    "gn:admin1_code":"32.0",
    "gn:asciiname":"Tujia",
    "gn:country_code":"CN",
    "gn:dem":441,
    "gn:feature_class":"P",
    "gn:feature_code":"PPL",
    "gn:name":"Tujia",
    "gn:population":0,
    "gn:timezone":"Asia/Shanghai",
    "iso:country":"CN",
    "name:nld_x_preferred":[
        "Tujia"
    ],
    "name:tur_x_preferred":[
        "Tujia"
    ],
    "name:zho_x_preferred":[
        "\u6d82\u5bb6"
    ],
    "wof:name":"Tujia",
    "wof:placetype":"locality"
},
  "geometry": {"coordinates":[104.28746,29.77263],"type":"Point"}
}