{
  "type": "Feature",
  "properties": {
    "gn:admin1_code":"18",
    "gn:asciiname":"Qingxi",
    "gn:country_code":"CN",
    "gn:dem":909,
    "gn:feature_class":"P",
    "gn:feature_code":"PPL",
    "gn:name":"Qingxi",
    "gn:population":0,
    "gn:timezone":"Asia/Shanghai",
    "iso:country":"CN",
    "name:ceb_x_preferred":[
        "Qingxi"
    ],
    "name:deu_x_preferred":[
        "Qingxi"
    ],
    "name:swe_x_preferred":[
        "Qingxi"
    ],
    "name:zho_x_preferred":[
        "\u6e05\u6eaa"
    ],
    "wof:name":"Qingxi",
    "wof:placetype":"locality"
},
  "geometry": {"coordinates":[106.435,28.4613],"type":"Point"}
}