{
  "type": "Feature",
  "properties": {
    "gn:admin1_code":"29.0",
    "gn:asciiname":"Lanbakou",
    "gn:country_code":"CN",
    "gn:dem":1315,
    "gn:feature_class":"P",
    "gn:feature_code":"PPL",
    "gn:name":"Lanbakou",
    "gn:population":0,
    "gn:timezone":"Asia/Shanghai",
    "iso:country":"CN",
    "name:und_x_variant":[
        "\u70c2\u575d\u53e3"
    ],
    "wof:name":"Lanbakou",
    "wof:placetype":"locality"
},
  "geometry": {"coordinates":[104.988,27.8307],"type":"Point"}
}