{
  "type": "Feature",
  "properties": {
    "gn:admin1_code":"19.0",
    "gn:asciiname":"Nan'ancun",
    "gn:country_code":"CN",
    "gn:dem":50,
    "gn:feature_class":"P",
    "gn:feature_code":"PPL",
    "gn:name":"Nan\u2019ancun",
    "gn:population":0,
    "gn:timezone":"Asia/Shanghai",
    "iso:country":"CN",
    "name:und_x_variant":[
        "Nan\u2019ancun"
    ],
    "name:zho_x_preferred":[
        "\u5357\u5b89\u6751"
    ],
    "wof:name":"Nan'ancun",
    "wof:placetype":"locality"
},
  "geometry": {"coordinates":[120.90009999999999,41.01898],"type":"Point"}
}