{
  "type": "Feature",
  "properties": {
    "gn:admin1_code":"14.0",
    "gn:asciiname":"Ruolangka",
    "gn:country_code":"CN",
    "gn:dem":4196,
    "gn:feature_class":"P",
    "gn:feature_code":"PPL",
    "gn:name":"Ruolangka",
    "gn:population":0,
    "gn:timezone":"Asia/Urumqi",
    "iso:country":"CN",
    "name:zho_x_preferred":[
        "\u5f31\u90ce\u5361"
    ],
    "wof:name":"Ruolangka",
    "wof:placetype":"locality"
},
  "geometry": {"coordinates":[97.49119,32.29855],"type":"Point"}
}