{
  "type": "Feature",
  "properties": {
    "gn:admin1_code":"32.0",
    "gn:asciiname":"Moyi",
    "gn:country_code":"CN",
    "gn:dem":3677,
    "gn:feature_class":"P",
    "gn:feature_code":"PPL",
    "gn:name":"Moyi",
    "gn:population":0,
    "gn:timezone":"Asia/Shanghai",
    "iso:country":"CN",
    "name:zho_x_preferred":[
        "\u672b\u4f9d"
    ],
    "wof:name":"Moyi",
    "wof:placetype":"locality"
},
  "geometry": {"coordinates":[100.315,31.9225],"type":"Point"}
}