{
  "type": "Feature",
  "properties": {
    "gn:admin1_code":"3",
    "gn:asciiname":"Bali",
    "gn:country_code":"CN",
    "gn:dem":492,
    "gn:feature_class":"P",
    "gn:feature_code":"PPL",
    "gn:name":"Bali",
    "gn:population":0,
    "gn:timezone":"Asia/Shanghai",
    "iso:country":"CN",
    "name:ace_x_preferred":[
        "Bali"
    ],
    "name:ceb_x_preferred":[
        "Provinsi Bali"
    ],
    "name:est_x_preferred":[
        "Bali provints"
    ],
    "name:fra_x_preferred":[
        "Bali"
    ],
    "name:gor_x_preferred":[
        "Bali"
    ],
    "name:hin_x_preferred":[
        "\u092c\u093e\u0932\u0940"
    ],
    "name:ind_x_preferred":[
        "Bali"
    ],
    "name:jav_x_preferred":[
        "Bali"
    ],
    "name:jpn_x_preferred":[
        "\u30d0\u30ea\u5dde"
    ],
    "name:kor_x_preferred":[
        "\ubc1c\ub9ac\uc8fc"
    ],
    "name:lav_x_preferred":[
        "Bali"
    ],
    "name:pol_x_preferred":[
        "Bali"
    ],
    "name:rus_x_preferred":[
        "\u0411\u0430\u043b\u0438"
    ],
    "name:swe_x_preferred":[
        "Bali"
    ],
    "name:tur_x_preferred":[
        "Bali"
    ],
    "name:urd_x_preferred":[
        "\u0628\u0627\u0644\u06cc"
    ],
    "name:war_x_preferred":[
        "Bali"
    ],
    "name:zho_x_preferred":[
        "\u5df4\u5398\u5c9b"
    ],
    "wof:name":"Bali",
    "wof:placetype":"locality"
},
  "geometry": {"coordinates":[114.36833,25.65111],"type":"Point"}
}