{
  "type": "Feature",
  "properties": {
    "gn:admin1_code":"11.0",
    "gn:asciiname":"Yihuai Wuchang",
    "gn:country_code":"CN",
    "gn:dem":125,
    "gn:feature_class":"P",
    "gn:feature_code":"PPL",
    "gn:name":"Yihuai Wuchang",
    "gn:population":0,
    "gn:timezone":"Asia/Shanghai",
    "iso:country":"CN",
    "name:zho_x_preferred":[
        "\u5fc6\u6000\u5c4b\u573a"
    ],
    "wof:name":"Yihuai Wuchang",
    "wof:placetype":"locality"
},
  "geometry": {"coordinates":[113.36669000000001,28.40979],"type":"Point"}
}