{
  "type": "Feature",
  "properties": {
    "gn:admin1_code":"14.0",
    "gn:asciiname":"Ganduo",
    "gn:country_code":"CN",
    "gn:dem":4605,
    "gn:feature_class":"P",
    "gn:feature_code":"PPL",
    "gn:name":"Ganduo",
    "gn:population":0,
    "gn:timezone":"Asia/Urumqi",
    "iso:country":"CN",
    "name:zho_x_preferred":[
        "\u5e72\u591a"
    ],
    "wof:name":"Ganduo",
    "wof:placetype":"locality"
},
  "geometry": {"coordinates":[90.40188000000001,28.70896],"type":"Point"}
}