{
  "type": "Feature",
  "properties": {
    "gn:admin1_code":"30.0",
    "gn:asciiname":"Shuijing",
    "gn:country_code":"CN",
    "gn:dem":530,
    "gn:feature_class":"P",
    "gn:feature_code":"PPL",
    "gn:name":"Shuijing",
    "gn:population":0,
    "gn:timezone":"Asia/Shanghai",
    "iso:country":"CN",
    "name:zho_x_preferred":[
        "Shuijing"
    ],
    "name:zho_x_variant":[
        "\u6c34\u8ff3"
    ],
    "wof:name":"Shuijing",
    "wof:placetype":"locality"
},
  "geometry": {"coordinates":[112.435,24.74444],"type":"Point"}
}