{
  "type": "Feature",
  "properties": {
    "gn:admin1_code":"3",
    "gn:asciiname":"Diaojinshanxia",
    "gn:country_code":"CN",
    "gn:dem":294,
    "gn:feature_class":"P",
    "gn:feature_code":"PPL",
    "gn:name":"Diaojinshanxia",
    "gn:population":0,
    "gn:timezone":"Asia/Shanghai",
    "iso:country":"CN",
    "name:zho_x_preferred":[
        "\u540a\u91d1\u5c71\u4e0b"
    ],
    "wof:name":"Diaojinshanxia",
    "wof:placetype":"locality"
},
  "geometry": {"coordinates":[114.986,25.5063],"type":"Point"}
}