{
  "type": "Feature",
  "properties": {
    "gn:admin1_code":"19.0",
    "gn:asciiname":"Laocanchang",
    "gn:country_code":"CN",
    "gn:dem":51,
    "gn:feature_class":"P",
    "gn:feature_code":"PPL",
    "gn:name":"Laocanchang",
    "gn:population":0,
    "gn:timezone":"Asia/Shanghai",
    "iso:country":"CN",
    "name:und_x_variant":[
        "\u8001\u8695\u573a"
    ],
    "name:zho_x_preferred":[
        "\u8001\u8695\u573a"
    ],
    "wof:name":"Laocanchang",
    "wof:placetype":"locality"
},
  "geometry": {"coordinates":[123.16316,39.99356],"type":"Point"}
}