{
  "type": "Feature",
  "properties": {
    "gn:admin1_code":"3.0",
    "gn:asciiname":"Gaotan",
    "gn:country_code":"CN",
    "gn:dem":129,
    "gn:feature_class":"P",
    "gn:feature_code":"PPL",
    "gn:name":"Gaotan",
    "gn:population":0,
    "gn:timezone":"Asia/Shanghai",
    "iso:country":"CN",
    "name:zho_x_preferred":[
        "\u9ad8\u6ee9"
    ],
    "wof:name":"Gaotan",
    "wof:placetype":"locality"
},
  "geometry": {"coordinates":[115.292,25.9094],"type":"Point"}
}