{
  "type": "Feature",
  "properties": {
    "gn:admin1_code":"29.0",
    "gn:asciiname":"Xinshengyi",
    "gn:country_code":"CN",
    "gn:dem":2204,
    "gn:feature_class":"P",
    "gn:feature_code":"PPL",
    "gn:name":"Xinshengyi",
    "gn:population":0,
    "gn:timezone":"Asia/Shanghai",
    "iso:country":"CN",
    "name:zho_x_preferred":[
        "\u65b0\u751f\u9091"
    ],
    "wof:name":"Xinshengyi",
    "wof:placetype":"locality"
},
  "geometry": {"coordinates":[100.17100000000001,26.5526],"type":"Point"}
}