{
  "type": "Feature",
  "properties": {
    "gn:admin1_code":"11.0",
    "gn:asciiname":"Baimaochong",
    "gn:country_code":"CN",
    "gn:dem":232,
    "gn:feature_class":"P",
    "gn:feature_code":"PPL",
    "gn:name":"Baimaochong",
    "gn:population":0,
    "gn:timezone":"Asia/Shanghai",
    "iso:country":"CN",
    "name:zho_x_preferred":[
        "\u767d\u6bdb\u51b2"
    ],
    "wof:name":"Baimaochong",
    "wof:placetype":"locality"
},
  "geometry": {"coordinates":[113.73188,27.29847],"type":"Point"}
}