{
  "type": "Feature",
  "properties": {
    "gn:admin1_code":"19.0",
    "gn:asciiname":"Ye'erxing",
    "gn:country_code":"CN",
    "gn:dem":227,
    "gn:feature_class":"P",
    "gn:feature_code":"PPL",
    "gn:name":"Ye\u2019erxing",
    "gn:population":0,
    "gn:timezone":"Asia/Shanghai",
    "iso:country":"CN",
    "name:zho_x_preferred":[
        "Ye\u2019erxing"
    ],
    "name:zho_x_variant":[
        "\u4e1a\u5c14\u5174"
    ],
    "wof:name":"Ye'erxing",
    "wof:placetype":"locality"
},
  "geometry": {"coordinates":[124.21247,42.08051],"type":"Point"}
}