{
  "type": "Feature",
  "properties": {
    "gn:admin1_code":"3.0",
    "gn:asciiname":"Zengwu",
    "gn:country_code":"CN",
    "gn:dem":208,
    "gn:feature_class":"P",
    "gn:feature_code":"PPL",
    "gn:name":"Zengwu",
    "gn:population":0,
    "gn:timezone":"Asia/Shanghai",
    "iso:country":"CN",
    "name:und_x_variant":[
        "\u66fe\u5c4b"
    ],
    "wof:name":"Zengwu",
    "wof:placetype":"locality"
},
  "geometry": {"coordinates":[115.069,25.17299],"type":"Point"}
}