{
  "type": "Feature",
  "properties": {
    "gn:admin1_code":"30",
    "gn:asciiname":"Maopo",
    "gn:country_code":"CN",
    "gn:dem":49,
    "gn:feature_class":"P",
    "gn:feature_code":"PPL",
    "gn:name":"Maopo",
    "gn:population":0,
    "gn:timezone":"Asia/Urumqi",
    "iso:country":"CN",
    "name:zho_x_preferred":[
        "\u8305\u5761"
    ],
    "wof:name":"Maopo",
    "wof:placetype":"locality"
},
  "geometry": {"coordinates":[110.24120000000001,21.76102],"type":"Point"}
}