{
  "type": "Feature",
  "properties": {
    "gn:admin1_code":"32.0",
    "gn:asciiname":"Huafang",
    "gn:country_code":"CN",
    "gn:dem":1359,
    "gn:feature_class":"P",
    "gn:feature_code":"PPL",
    "gn:name":"Huafang",
    "gn:population":0,
    "gn:timezone":"Asia/Shanghai",
    "iso:country":"CN",
    "name:zho_x_preferred":[
        "\u82b1\u623f"
    ],
    "wof:name":"Huafang",
    "wof:placetype":"locality"
},
  "geometry": {"coordinates":[102.727,27.0053],"type":"Point"}
}