{
  "type": "Feature",
  "properties": {
    "gn:admin1_code":"10.0",
    "gn:asciiname":"Qilinyuan",
    "gn:country_code":"CN",
    "gn:dem":319,
    "gn:feature_class":"P",
    "gn:feature_code":"PPL",
    "gn:name":"Qilinyuan",
    "gn:population":0,
    "gn:timezone":"Asia/Shanghai",
    "iso:country":"CN",
    "name:und_x_variant":[
        "\u9e92\u9e9f\u9662"
    ],
    "wof:name":"Qilinyuan",
    "wof:placetype":"locality"
},
  "geometry": {"coordinates":[114.03308,38.57936],"type":"Point"}
}