{
  "type": "Feature",
  "properties": {
    "gn:admin1_code":"08",
    "gn:asciiname":"Yahe",
    "gn:country_code":"CN",
    "gn:dem":304,
    "gn:feature_class":"P",
    "gn:feature_code":"PPLA4",
    "gn:name":"Yahe",
    "gn:population":0,
    "gn:timezone":"Asia/Shanghai",
    "iso:country":"CN",
    "name:und_x_variant":[
        "Ya-ho",
        "Yahe",
        "Yahe Xiang"
    ],
    "name:zho_x_preferred":[
        "\u4e9a\u6cb3"
    ],
    "name:zho_x_variant":[
        "\u4e9a\u6cb3\u4e61"
    ],
    "wof:name":"Yahe",
    "wof:placetype":"locality"
},
  "geometry": {"coordinates":[130.42767000000001,45.39563],"type":"Point"}
}