{
  "type": "Feature",
  "properties": {
    "gn:admin1_code":"31.0",
    "gn:asciiname":"Nanpaipo",
    "gn:country_code":"CN",
    "gn:dem":5,
    "gn:feature_class":"P",
    "gn:feature_code":"PPL",
    "gn:name":"Nanpaipo",
    "gn:population":0,
    "gn:timezone":"Asia/Shanghai",
    "iso:country":"CN",
    "name:zho_x_preferred":[
        "Nanpaipo"
    ],
    "name:zho_x_variant":[
        "\u5357\u6392\u5761"
    ],
    "wof:name":"Nanpaipo",
    "wof:placetype":"locality"
},
  "geometry": {"coordinates":[110.65539,19.97347],"type":"Point"}
}