{
  "type": "Feature",
  "properties": {
    "gn:admin1_code":"13.0",
    "gn:asciiname":"Shirenzi",
    "gn:country_code":"CN",
    "gn:dem":1676,
    "gn:feature_class":"P",
    "gn:feature_code":"PPL",
    "gn:name":"Shirenzi",
    "gn:population":0,
    "gn:timezone":"Asia/Urumqi",
    "iso:country":"CN",
    "name:kaz_x_preferred":[
        "\u0634\u0649\u0631\u0649\u0646\u0632\u0649 \u0627\u06cb\u0649\u0644\u0649"
    ],
    "name:uig_x_preferred":[
        "\u0634\u0649\u0631\u0649\u0646\u0632\u0627 \u064a\u06d0\u0632\u0649\u0633\u0649"
    ],
    "name:und_x_variant":[
        "Shirenzi Xiang"
    ],
    "name:zho_x_preferred":[
        "\u77f3\u4eba\u5b50\u4e61"
    ],
    "wof:name":"Shirenzi",
    "wof:placetype":"locality"
},
  "geometry": {"coordinates":[93.17453,43.60899000000001],"type":"Point"}
}