{
  "type": "Feature",
  "properties": {
    "gn:admin1_code":"18.0",
    "gn:asciiname":"Pingmang",
    "gn:country_code":"CN",
    "gn:dem":986,
    "gn:feature_class":"P",
    "gn:feature_code":"PPL",
    "gn:name":"Pingmang",
    "gn:population":0,
    "gn:timezone":"Asia/Shanghai",
    "iso:country":"CN",
    "name:zho_x_preferred":[
        "\u5e73\u5fd9"
    ],
    "wof:name":"Pingmang",
    "wof:placetype":"locality"
},
  "geometry": {"coordinates":[108.42100000000001,25.5228],"type":"Point"}
}