{
  "type": "Feature",
  "properties": {
    "gn:admin1_code":"11.0",
    "gn:asciiname":"Dahanxi",
    "gn:country_code":"CN",
    "gn:dem":339,
    "gn:feature_class":"P",
    "gn:feature_code":"PPL",
    "gn:name":"Dahanxi",
    "gn:population":0,
    "gn:timezone":"Asia/Shanghai",
    "iso:country":"CN",
    "name:zho_x_preferred":[
        "\u5927\u6c49\u6eaa"
    ],
    "wof:name":"Dahanxi",
    "wof:placetype":"locality"
},
  "geometry": {"coordinates":[110.89561999999999,29.38087],"type":"Point"}
}