{
  "type": "Feature",
  "properties": {
    "gn:admin1_code":"9.0",
    "gn:asciiname":"Pengweizi",
    "gn:country_code":"CN",
    "gn:dem":41,
    "gn:feature_class":"P",
    "gn:feature_code":"PPL",
    "gn:name":"Pengweizi",
    "gn:population":0,
    "gn:timezone":"Asia/Shanghai",
    "iso:country":"CN",
    "name:zho_x_preferred":[
        "\u5f6d\u56f4\u5b5c"
    ],
    "wof:name":"Pengweizi",
    "wof:placetype":"locality"
},
  "geometry": {"coordinates":[115.00127000000001,32.2775],"type":"Point"}
}