{
  "type": "Feature",
  "properties": {
    "gn:admin1_code":"5.0",
    "gn:asciiname":"Changchunlingcun",
    "gn:country_code":"CN",
    "gn:dem":137,
    "gn:feature_class":"P",
    "gn:feature_code":"PPL",
    "gn:name":"Changchunlingcun",
    "gn:population":0,
    "gn:timezone":"Asia/Shanghai",
    "iso:country":"CN",
    "name:zho_x_preferred":[
        "\u957f\u6625\u5cad\u6751"
    ],
    "wof:name":"Changchunlingcun",
    "wof:placetype":"locality"
},
  "geometry": {"coordinates":[123.67679,45.10852],"type":"Point"}
}