{
  "type": "Feature",
  "properties": {
    "gn:admin1_code":"32.0",
    "gn:asciiname":"Heijia Puzi",
    "gn:country_code":"CN",
    "gn:dem":2546,
    "gn:feature_class":"P",
    "gn:feature_code":"PPL",
    "gn:name":"Heijia Puzi",
    "gn:population":0,
    "gn:timezone":"Asia/Shanghai",
    "iso:country":"CN",
    "name:zho_x_preferred":[
        "\u9ed1\u5bb6\u94fa\u5b50"
    ],
    "wof:name":"Heijia Puzi",
    "wof:placetype":"locality"
},
  "geometry": {"coordinates":[102.989,27.7589],"type":"Point"}
}