{
  "type": "Feature",
  "properties": {
    "gn:admin1_code":"33.0",
    "gn:asciiname":"Danzi",
    "gn:country_code":"CN",
    "gn:dem":410,
    "gn:feature_class":"P",
    "gn:feature_code":"PPL",
    "gn:name":"Danzi",
    "gn:population":0,
    "gn:timezone":"Asia/Shanghai",
    "iso:country":"CN",
    "name:deu_x_preferred":[
        "Danzi"
    ],
    "name:fra_x_preferred":[
        "Danzi"
    ],
    "name:ita_x_preferred":[
        "Danzi"
    ],
    "name:zho_x_preferred":[
        "\u5f39\u5b50"
    ],
    "wof:name":"Danzi",
    "wof:placetype":"locality"
},
  "geometry": {"coordinates":[108.28932,30.44315],"type":"Point"}
}