{
  "type": "Feature",
  "properties": {
    "gn:admin1_code":"4.0",
    "gn:asciiname":"Huajian",
    "gn:country_code":"CN",
    "gn:dem":2,
    "gn:feature_class":"P",
    "gn:feature_code":"PPL",
    "gn:name":"Huajian",
    "gn:population":0,
    "gn:timezone":"Asia/Shanghai",
    "iso:country":"CN",
    "name:zho_x_preferred":[
        "Huajian"
    ],
    "name:zho_x_variant":[
        "\u82b1\u5c16"
    ],
    "wof:name":"Huajian",
    "wof:placetype":"locality"
},
  "geometry": {"coordinates":[119.40352,33.41108],"type":"Point"}
}