{
  "type": "Feature",
  "properties": {
    "gn:admin1_code":"15.0",
    "gn:asciiname":"Dongpo Zhangjia",
    "gn:country_code":"CN",
    "gn:dem":1758,
    "gn:feature_class":"P",
    "gn:feature_code":"PPL",
    "gn:name":"Dongpo Zhangjia",
    "gn:population":0,
    "gn:timezone":"Asia/Shanghai",
    "iso:country":"CN",
    "name:zho_x_preferred":[
        "\u4e1c\u5761\u5f20\u5bb6"
    ],
    "wof:name":"Dongpo Zhangjia",
    "wof:placetype":"locality"
},
  "geometry": {"coordinates":[106.03,34.9282],"type":"Point"}
}