{
  "type": "Feature",
  "properties": {
    "gn:admin1_code":"4.0",
    "gn:asciiname":"Caohuangcun",
    "gn:country_code":"CN",
    "gn:dem":3,
    "gn:feature_class":"P",
    "gn:feature_code":"PPL",
    "gn:name":"Caohuangcun",
    "gn:population":0,
    "gn:timezone":"Asia/Shanghai",
    "iso:country":"CN",
    "name:zho_x_preferred":[
        "\u66f9\u9ec4\u6751"
    ],
    "wof:name":"Caohuangcun",
    "wof:placetype":"locality"
},
  "geometry": {"coordinates":[119.88330000000001,32.78388],"type":"Point"}
}