{
  "type": "Feature",
  "properties": {
    "gn:admin1_code":"12.0",
    "gn:asciiname":"Jiangjia'ao",
    "gn:country_code":"CN",
    "gn:dem":167,
    "gn:feature_class":"P",
    "gn:feature_code":"PPL",
    "gn:name":"Jiangjia\u2019ao",
    "gn:population":0,
    "gn:timezone":"Asia/Shanghai",
    "iso:country":"CN",
    "name:und_x_variant":[
        "Jiangjia\u2019ao"
    ],
    "name:zho_x_preferred":[
        "\u6c5f\u5bb6\u5773"
    ],
    "wof:name":"Jiangjia'ao",
    "wof:placetype":"locality"
},
  "geometry": {"coordinates":[114.92894,31.41129],"type":"Point"}
}