{
  "type": "Feature",
  "properties": {
    "gn:admin1_code":"4.0",
    "gn:asciiname":"Danqiao",
    "gn:country_code":"CN",
    "gn:dem":8,
    "gn:feature_class":"P",
    "gn:feature_code":"PPL",
    "gn:name":"Danqiao",
    "gn:population":0,
    "gn:timezone":"Asia/Shanghai",
    "iso:country":"CN",
    "name:und_x_variant":[
        "\u5355\u6865"
    ],
    "wof:name":"Danqiao",
    "wof:placetype":"locality"
},
  "geometry": {"coordinates":[118.89091999999999,32.26488],"type":"Point"}
}