{
  "type": "Feature",
  "properties": {
    "gn:admin1_code":"7.0",
    "gn:asciiname":"Guanchangcun",
    "gn:country_code":"CN",
    "gn:dem":425,
    "gn:feature_class":"P",
    "gn:feature_code":"PPL",
    "gn:name":"Guanchangcun",
    "gn:population":0,
    "gn:timezone":"Asia/Shanghai",
    "iso:country":"CN",
    "name:zho_x_preferred":[
        "\u5b98\u660c\u6751"
    ],
    "wof:name":"Guanchangcun",
    "wof:placetype":"locality"
},
  "geometry": {"coordinates":[117.7945,26.2375],"type":"Point"}
}