{
  "type": "Feature",
  "properties": {
    "gn:admin1_code":"2",
    "gn:asciiname":"Dieshi",
    "gn:country_code":"CN",
    "gn:dem":108,
    "gn:feature_class":"P",
    "gn:feature_code":"PPL",
    "gn:name":"Dieshi",
    "gn:population":0,
    "gn:timezone":"Asia/Shanghai",
    "iso:country":"CN",
    "name:zho_x_preferred":[
        "\u53e0\u77f3"
    ],
    "wof:name":"Dieshi",
    "wof:placetype":"locality"
},
  "geometry": {"coordinates":[120.90996,29.73408],"type":"Point"}
}