{
  "type": "Feature",
  "properties": {
    "gn:admin1_code":"13.0",
    "gn:asciiname":"Keqike Sareyi",
    "gn:country_code":"CN",
    "gn:dem":2908,
    "gn:feature_class":"P",
    "gn:feature_code":"PPL",
    "gn:name":"Keqike Sareyi",
    "gn:population":0,
    "gn:timezone":"Asia/Urumqi",
    "iso:country":"CN",
    "name:zho_x_preferred":[
        "\u514b\u5176\u514b\u8428\u70ed\u4f9d"
    ],
    "wof:name":"Keqike Sareyi",
    "wof:placetype":"locality"
},
  "geometry": {"coordinates":[82.97674000000001,36.59738],"type":"Point"}
}