{
  "type": "Feature",
  "properties": {
    "gn:admin1_code":"25",
    "gn:asciiname":"Ludongyedong",
    "gn:country_code":"CN",
    "gn:dem":184,
    "gn:feature_class":"P",
    "gn:feature_code":"PPL",
    "gn:name":"Ludongyedong",
    "gn:population":0,
    "gn:timezone":"Asia/Shanghai",
    "iso:country":"CN",
    "name:zho_x_preferred":[
        "\u9c81\u4e1c\u51b6\u4e1c"
    ],
    "wof:name":"Ludongyedong",
    "wof:placetype":"locality"
},
  "geometry": {"coordinates":[117.46299999999999,36.1621],"type":"Point"}
}