{
  "type": "Feature",
  "properties": {
    "gn:admin1_code":"11.0",
    "gn:asciiname":"Shangtaodong",
    "gn:country_code":"CN",
    "gn:dem":683,
    "gn:feature_class":"P",
    "gn:feature_code":"PPL",
    "gn:name":"Shangtaodong",
    "gn:population":0,
    "gn:timezone":"Asia/Shanghai",
    "iso:country":"CN",
    "name:zho_x_preferred":[
        "\u4e0a\u6843\u6d1e"
    ],
    "wof:name":"Shangtaodong",
    "wof:placetype":"locality"
},
  "geometry": {"coordinates":[113.74266,25.80907],"type":"Point"}
}