{
  "type": "Feature",
  "properties": {
    "gn:admin1_code":"16",
    "gn:asciiname":"Xiafutang",
    "gn:country_code":"CN",
    "gn:dem":547,
    "gn:feature_class":"P",
    "gn:feature_code":"PPL",
    "gn:name":"Xiafutang",
    "gn:population":0,
    "gn:timezone":"Asia/Shanghai",
    "iso:country":"CN",
    "name:zho_x_preferred":[
        "\u4e0b\u798f\u5858"
    ],
    "wof:name":"Xiafutang",
    "wof:placetype":"locality"
},
  "geometry": {"coordinates":[111.315,25.8833],"type":"Point"}
}