{
  "type": "Feature",
  "properties": {
    "gn:admin1_code":"7",
    "gn:asciiname":"Tianzhu",
    "gn:country_code":"CN",
    "gn:dem":541,
    "gn:feature_class":"P",
    "gn:feature_code":"PPL",
    "gn:name":"Tianzhu",
    "gn:population":0,
    "gn:timezone":"Asia/Shanghai",
    "iso:country":"CN",
    "name:und_x_variant":[
        "\u5929\u7af9",
        "Tianzhu"
    ],
    "wof:name":"Tianzhu",
    "wof:placetype":"locality"
},
  "geometry": {"coordinates":[119.96552,27.34022],"type":"Point"}
}