{
  "type": "Feature",
  "properties": {
    "gn:admin1_code":"8.0",
    "gn:asciiname":"Wangdaniu Wopeng",
    "gn:country_code":"CN",
    "gn:dem":172,
    "gn:feature_class":"P",
    "gn:feature_code":"PPL",
    "gn:name":"Wangdaniu Wopeng",
    "gn:population":0,
    "gn:timezone":"Asia/Shanghai",
    "iso:country":"CN",
    "name:zho_x_preferred":[
        "\u738b\u5927\u725b\u7a9d\u68da"
    ],
    "wof:name":"Wangdaniu Wopeng",
    "wof:placetype":"locality"
},
  "geometry": {"coordinates":[124.09416,48.01564000000001],"type":"Point"}
}