{
  "type": "Feature",
  "properties": {
    "gn:admin1_code":"1.0",
    "gn:asciiname":"Miaoqiancun",
    "gn:country_code":"CN",
    "gn:dem":29,
    "gn:feature_class":"P",
    "gn:feature_code":"PPL",
    "gn:name":"Miaoqiancun",
    "gn:population":0,
    "gn:timezone":"Asia/Shanghai",
    "iso:country":"CN",
    "name:zho_x_preferred":[
        "\u5e99\u524d\u6751"
    ],
    "wof:name":"Miaoqiancun",
    "wof:placetype":"locality"
},
  "geometry": {"coordinates":[116.24815,32.99589],"type":"Point"}
}