{
  "type": "Feature",
  "properties": {
    "gn:admin1_code":"16.0",
    "gn:asciiname":"Dashuidong",
    "gn:country_code":"CN",
    "gn:dem":115,
    "gn:feature_class":"P",
    "gn:feature_code":"PPL",
    "gn:name":"Dashuidong",
    "gn:population":0,
    "gn:timezone":"Asia/Shanghai",
    "iso:country":"CN",
    "name:zho_x_preferred":[
        "\u5927\u6c34\u6d1e"
    ],
    "wof:name":"Dashuidong",
    "wof:placetype":"locality"
},
  "geometry": {"coordinates":[109.27800000000001,22.3103],"type":"Point"}
}