{
  "type": "Feature",
  "properties": {
    "gn:admin1_code":"5.0",
    "gn:asciiname":"Yaotuan",
    "gn:country_code":"CN",
    "gn:dem":576,
    "gn:feature_class":"P",
    "gn:feature_code":"PPL",
    "gn:name":"Yaotuan",
    "gn:population":0,
    "gn:timezone":"Asia/Shanghai",
    "iso:country":"CN",
    "name:und_x_variant":[
        "\u8170\u56e2"
    ],
    "wof:name":"Yaotuan",
    "wof:placetype":"locality"
},
  "geometry": {"coordinates":[128.40669,42.71559],"type":"Point"}
}