{
  "type": "Feature",
  "properties": {
    "gn:admin1_code":"2.0",
    "gn:asciiname":"Tianyang",
    "gn:country_code":"CN",
    "gn:dem":296,
    "gn:feature_class":"P",
    "gn:feature_code":"PPL",
    "gn:name":"Tianyang",
    "gn:population":0,
    "gn:timezone":"Asia/Shanghai",
    "iso:country":"CN",
    "name:zho_x_preferred":[
        "\u7530\u6d0b"
    ],
    "wof:name":"Tianyang",
    "wof:placetype":"locality"
},
  "geometry": {"coordinates":[120.21926999999999,28.62882],"type":"Point"}
}