{
  "type": "Feature",
  "properties": {
    "gn:admin1_code":"3.0",
    "gn:asciiname":"Liyuan Gongjia",
    "gn:country_code":"CN",
    "gn:dem":81,
    "gn:feature_class":"P",
    "gn:feature_code":"PPL",
    "gn:name":"Liyuan Gongjia",
    "gn:population":0,
    "gn:timezone":"Asia/Shanghai",
    "iso:country":"CN",
    "name:zho_x_preferred":[
        "\u91cc\u6e90\u9f9a\u5bb6"
    ],
    "wof:name":"Liyuan Gongjia",
    "wof:placetype":"locality"
},
  "geometry": {"coordinates":[117.22951,28.06896],"type":"Point"}
}