{
  "type": "Feature",
  "properties": {
    "gn:admin1_code":"29.0",
    "gn:asciiname":"Muwacun",
    "gn:country_code":"CN",
    "gn:dem":2914,
    "gn:feature_class":"P",
    "gn:feature_code":"PPL",
    "gn:name":"Muwacun",
    "gn:population":0,
    "gn:timezone":"Asia/Shanghai",
    "iso:country":"CN",
    "name:zho_x_preferred":[
        "\u6728\u74e6\u6751"
    ],
    "wof:name":"Muwacun",
    "wof:placetype":"locality"
},
  "geometry": {"coordinates":[103.101,27.0905],"type":"Point"}
}