{
  "type": "Feature",
  "properties": {
    "gn:admin1_code":"19.0",
    "gn:asciiname":"Guoyoufangcun",
    "gn:country_code":"CN",
    "gn:dem":24,
    "gn:feature_class":"P",
    "gn:feature_code":"PPL",
    "gn:name":"Guoyoufangcun",
    "gn:population":0,
    "gn:timezone":"Asia/Shanghai",
    "iso:country":"CN",
    "name:zho_x_preferred":[
        "\u90ed\u6cb9\u574a\u6751"
    ],
    "wof:name":"Guoyoufangcun",
    "wof:placetype":"locality"
},
  "geometry": {"coordinates":[122.40000000000001,41.7731],"type":"Point"}
}