{
  "type": "Feature",
  "properties": {
    "iso:country":"CN",
    "qs:name":"\u6f84\u6d77",
    "qs:name_adm0":"\u4e2d\u570b",
    "qs:name_adm1":"\u5e7f\u4e1c\u7701",
    "qs:photos":187,
    "qs:photos_1k":38,
    "qs:photos_9k":1,
    "qs:photos_9r":4,
    "qs:photos_all":187,
    "qs:photos_sr":4,
    "qs:placetype":"Town",
    "qs:pop_sr":"0",
    "wd:wordcount":1586,
    "wof:name":"\u6f84\u6d77",
    "wof:placetype":"locality"
},
  "geometry": {"coordinates":[116.76475499999999,23.471906],"type":"Point"}
}