{
  "type": "Feature",
  "properties": {
    "iso:country":"CN",
    "name:ceb_x_preferred":[
        "Chenghai Qu"
    ],
    "name:cym_x_preferred":[
        "Ardal Chenghai"
    ],
    "name:deu_x_preferred":[
        "Chenghai"
    ],
    "name:eng_x_preferred":[
        "Chenghai District"
    ],
    "name:fas_x_preferred":[
        "\u0686\u0646\u06af\u0647\u0627\u06cc"
    ],
    "name:gan_x_preferred":[
        "\u6f84\u6d77\u533a"
    ],
    "name:hak_x_preferred":[
        "Tsh\u00een-h\u00f3i-kh\u00ee"
    ],
    "name:jpn_x_preferred":[
        "\u6f84\u6d77\u533a"
    ],
    "name:kor_x_preferred":[
        "\uccad\ud558\uc774\uad6c"
    ],
    "name:mwl_x_preferred":[
        "Chenghai"
    ],
    "name:nan_x_preferred":[
        "T\u00eang-h\u00e1i-khu"
    ],
    "name:nld_x_preferred":[
        "Chenghai"
    ],
    "name:nob_x_preferred":[
        "Chenghai"
    ],
    "name:swe_x_preferred":[
        "Chenghai"
    ],
    "name:vie_x_preferred":[
        "Tr\u1eebng H\u1ea3i"
    ],
    "name:wuu_x_preferred":[
        "\u6f84\u6d77\u533a"
    ],
    "name:yue_x_preferred":[
        "\u6f84\u6d77"
    ],
    "name:zho_x_preferred":[
        "\u6f84\u6d77\u533a"
    ],
    "qs:name":"\u6f84\u6d77",
    "qs:name_adm0":"\u4e2d\u570b",
    "qs:name_adm1":"\u5e7f\u4e1c\u7701",
    "qs:photos":187,
    "qs:photos_1k":38,
    "qs:photos_9k":1,
    "qs:photos_9r":4,
    "qs:photos_all":187,
    "qs:photos_sr":4,
    "qs:placetype":"Town",
    "qs:pop_sr":"0",
    "wd:wordcount":1586,
    "wof:name":"\u6f84\u6d77",
    "wof:placetype":"locality"
},
  "geometry": {"coordinates":[116.76475499999999,23.471906],"type":"Point"}
}