{
  "type": "Feature",
  "properties": {
    "gn:admin1_code":"8.0",
    "gn:asciiname":"Wangsanwu",
    "gn:country_code":"CN",
    "gn:dem":307,
    "gn:feature_class":"P",
    "gn:feature_code":"PPL",
    "gn:name":"Wangsanwu",
    "gn:population":0,
    "gn:timezone":"Asia/Shanghai",
    "iso:country":"CN",
    "name:zho_x_preferred":[
        "\u738b\u4e09\u4e94"
    ],
    "wof:name":"Wangsanwu",
    "wof:placetype":"locality"
},
  "geometry": {"coordinates":[125.76888,48.36414],"type":"Point"}
}