{
  "type": "Feature",
  "properties": {
    "gn:admin1_code":"9.0",
    "gn:asciiname":"Dongfan",
    "gn:country_code":"CN",
    "gn:dem":82,
    "gn:feature_class":"P",
    "gn:feature_code":"PPL",
    "gn:name":"Dongfan",
    "gn:population":0,
    "gn:timezone":"Asia/Shanghai",
    "iso:country":"CN",
    "name:zho_x_preferred":[
        "\u4e1c\u51e1"
    ],
    "wof:name":"Dongfan",
    "wof:placetype":"locality"
},
  "geometry": {"coordinates":[114.06901999999999,34.40098],"type":"Point"}
}