{
  "type": "Feature",
  "properties": {
    "gn:admin1_code":"9.0",
    "gn:asciiname":"Zhuquan",
    "gn:country_code":"CN",
    "gn:dem":298,
    "gn:feature_class":"P",
    "gn:feature_code":"PPL",
    "gn:name":"Zhuquan",
    "gn:population":0,
    "gn:timezone":"Asia/Shanghai",
    "iso:country":"CN",
    "name:zho_x_preferred":[
        "\u7af9\u6cc9"
    ],
    "name:zho_x_variant":[
        "\u73e0\u6cc9\u9547"
    ],
    "wof:name":"Zhuquan",
    "wof:placetype":"locality"
},
  "geometry": {"coordinates":[112.17158999999999,35.11107],"type":"Point"}
}