{
  "type": "Feature",
  "properties": {
    "gn:admin1_code":"15.0",
    "gn:asciiname":"Zhaomianwa",
    "gn:country_code":"CN",
    "gn:dem":2569,
    "gn:feature_class":"P",
    "gn:feature_code":"PPL",
    "gn:name":"Zhaomianwa",
    "gn:population":0,
    "gn:timezone":"Asia/Shanghai",
    "iso:country":"CN",
    "name:zho_x_preferred":[
        "\u53ec\u9762\u6d3c"
    ],
    "wof:name":"Zhaomianwa",
    "wof:placetype":"locality"
},
  "geometry": {"coordinates":[102.471,37.6869],"type":"Point"}
}