{
  "type": "Feature",
  "properties": {
    "gn:admin1_code":"8.0",
    "gn:asciiname":"Nenbei Wudui",
    "gn:country_code":"CN",
    "gn:dem":343,
    "gn:feature_class":"P",
    "gn:feature_code":"PPLF",
    "gn:name":"Nenbei Wudui",
    "gn:population":0,
    "gn:timezone":"Asia/Shanghai",
    "iso:country":"CN",
    "name:zho_x_preferred":[
        "\u5ae9\u5317\u4e94\u961f"
    ],
    "wof:name":"Nenbei Wudui",
    "wof:placetype":"locality"
},
  "geometry": {"coordinates":[125.55398,49.57679],"type":"Point"}
}