{
  "type": "Feature",
  "properties": {
    "gn:admin1_code":"16.0",
    "gn:asciiname":"Duobanxia",
    "gn:country_code":"CN",
    "gn:dem":898,
    "gn:feature_class":"P",
    "gn:feature_code":"PPL",
    "gn:name":"Duobanxia",
    "gn:population":0,
    "gn:timezone":"Asia/Shanghai",
    "iso:country":"CN",
    "name:zho_x_preferred":[
        "\u591a\u73ed\u4e0b"
    ],
    "wof:name":"Duobanxia",
    "wof:placetype":"locality"
},
  "geometry": {"coordinates":[106.39700000000001,23.386],"type":"Point"}
}