{
  "type": "Feature",
  "properties": {
    "gn:admin1_code":"15.0",
    "gn:asciiname":"Majiatai",
    "gn:country_code":"CN",
    "gn:dem":2347,
    "gn:feature_class":"P",
    "gn:feature_code":"PPL",
    "gn:name":"Majiatai",
    "gn:population":0,
    "gn:timezone":"Asia/Shanghai",
    "iso:country":"CN",
    "name:und_x_variant":[
        "\u9ebb\u5bb6\u53f0"
    ],
    "wof:name":"Majiatai",
    "wof:placetype":"locality"
},
  "geometry": {"coordinates":[104.38864,34.55934],"type":"Point"}
}