{
  "type": "Feature",
  "properties": {
    "gn:admin1_code":"11.0",
    "gn:asciiname":"Pingsongpo",
    "gn:country_code":"CN",
    "gn:dem":928,
    "gn:feature_class":"P",
    "gn:feature_code":"PPL",
    "gn:name":"Pingsongpo",
    "gn:population":0,
    "gn:timezone":"Asia/Shanghai",
    "iso:country":"CN",
    "name:zho_x_preferred":[
        "\u576a\u9001\u5761"
    ],
    "wof:name":"Pingsongpo",
    "wof:placetype":"locality"
},
  "geometry": {"coordinates":[108.90738,27.0253],"type":"Point"}
}