{
  "type": "Feature",
  "properties": {
    "gn:admin1_code":"3.0",
    "gn:asciiname":"Dingjia",
    "gn:country_code":"CN",
    "gn:dem":49,
    "gn:feature_class":"P",
    "gn:feature_code":"PPL",
    "gn:name":"Dingjia",
    "gn:population":0,
    "gn:timezone":"Asia/Shanghai",
    "iso:country":"CN",
    "name:und_x_variant":[
        "\u4e01\u5bb6"
    ],
    "wof:name":"Dingjia",
    "wof:placetype":"locality"
},
  "geometry": {"coordinates":[114.96554999999999,27.78334000000001],"type":"Point"}
}