{
  "type": "Feature",
  "properties": {
    "gn:admin1_code":"32",
    "gn:asciiname":"Shituan",
    "gn:country_code":"CN",
    "gn:dem":420,
    "gn:feature_class":"P",
    "gn:feature_code":"PPL",
    "gn:name":"Shituan",
    "gn:population":0,
    "gn:timezone":"Asia/Shanghai",
    "iso:country":"CN",
    "name:und_x_variant":[
        "Shih-t\u2019uan",
        "Shih-tuan-chen",
        "Shituan\u2019chzhen\u2019",
        "Shituan"
    ],
    "name:zho_x_preferred":[
        "\u77f3\u6e4d"
    ],
    "wof:name":"Shituan",
    "wof:placetype":"locality"
},
  "geometry": {"coordinates":[105.03731000000001,30.14598],"type":"Point"}
}