{
  "type": "Feature",
  "properties": {
    "gn:admin1_code":"14.0",
    "gn:asciiname":"Xarru",
    "gn:country_code":"CN",
    "gn:dem":5102,
    "gn:feature_class":"P",
    "gn:feature_code":"PPLF",
    "gn:name":"Xarru",
    "gn:population":0,
    "gn:timezone":"Asia/Urumqi",
    "iso:country":"CN",
    "name:bod_x_preferred":[
        "Xarru"
    ],
    "name:zho_x_preferred":[
        "Xiaru"
    ],
    "name:zho_x_variant":[
        "\u590f\u5982"
    ],
    "wof:name":"Xarru",
    "wof:placetype":"locality"
},
  "geometry": {"coordinates":[86.102,29.102],"type":"Point"}
}