{
  "type": "Feature",
  "properties": {
    "gn:admin1_code":"32.0",
    "gn:asciiname":"An'ang",
    "gn:country_code":"CN",
    "gn:dem":2842,
    "gn:feature_class":"P",
    "gn:feature_code":"PPL",
    "gn:name":"An\u2019ang",
    "gn:population":0,
    "gn:timezone":"Asia/Shanghai",
    "iso:country":"CN",
    "name:und_x_variant":[
        "An\u2019ang"
    ],
    "name:zho_x_preferred":[
        "\u963f\u6602"
    ],
    "wof:name":"An'ang",
    "wof:placetype":"locality"
},
  "geometry": {"coordinates":[100.76300000000001,30.1946],"type":"Point"}
}