{
  "type": "Feature",
  "properties": {
    "gn:admin1_code":"30.0",
    "gn:asciiname":"Nanwan",
    "gn:country_code":"CN",
    "gn:dem":65,
    "gn:feature_class":"P",
    "gn:feature_code":"PPLA4",
    "gn:name":"Nanwan",
    "gn:population":0,
    "gn:timezone":"Asia/Shanghai",
    "iso:country":"CN",
    "name:und_x_variant":[
        "Nanwan Jiedao"
    ],
    "name:zho_x_preferred":[
        "\u5357\u6e7e"
    ],
    "name:zho_x_variant":[
        "\u5357\u6e7e\u8857\u9053"
    ],
    "wof:name":"Nanwan",
    "wof:placetype":"locality"
},
  "geometry": {"coordinates":[114.13039999999999,22.59882],"type":"Point"}
}