{
  "type": "Feature",
  "properties": {
    "gn:admin1_code":"11.0",
    "gn:asciiname":"Tangjiaqiao",
    "gn:country_code":"CN",
    "gn:dem":52,
    "gn:feature_class":"P",
    "gn:feature_code":"PPL",
    "gn:name":"Tangjiaqiao",
    "gn:population":0,
    "gn:timezone":"Asia/Shanghai",
    "iso:country":"CN",
    "name:zho_x_preferred":[
        "Tangjiaqiao"
    ],
    "name:zho_x_variant":[
        "\u5510\u5bb6\u6865"
    ],
    "wof:name":"Tangjiaqiao",
    "wof:placetype":"locality"
},
  "geometry": {"coordinates":[111.76949,29.12907],"type":"Point"}
}