{
  "type": "Feature",
  "properties": {
    "gn:admin1_code":"21",
    "gn:asciiname":"Huangjiataozi",
    "gn:country_code":"CN",
    "gn:dem":1793,
    "gn:feature_class":"P",
    "gn:feature_code":"PPL",
    "gn:name":"Huangjiataozi",
    "gn:population":0,
    "gn:timezone":"Asia/Shanghai",
    "iso:country":"CN",
    "wof:name":"Huangjiataozi",
    "wof:placetype":"locality"
},
  "geometry": {"coordinates":[105.09999999999999,37.31667],"type":"Point"}
}