{
  "type": "Feature",
  "properties": {
    "gn:admin1_code":"8.0",
    "gn:asciiname":"Mahuayang Wopeng",
    "gn:country_code":"CN",
    "gn:dem":151,
    "gn:feature_class":"P",
    "gn:feature_code":"PPL",
    "gn:name":"Mahuayang Wopeng",
    "gn:population":0,
    "gn:timezone":"Asia/Shanghai",
    "iso:country":"CN",
    "name:zho_x_preferred":[
        "\u9a6c\u5316\u6768\u7a9d\u68da"
    ],
    "wof:name":"Mahuayang Wopeng",
    "wof:placetype":"locality"
},
  "geometry": {"coordinates":[124.911,47.09192],"type":"Point"}
}