{
  "type": "Feature",
  "properties": {
    "gn:admin1_code":"19.0",
    "gn:asciiname":"Qijia Wobu",
    "gn:country_code":"CN",
    "gn:dem":28,
    "gn:feature_class":"P",
    "gn:feature_code":"PPL",
    "gn:name":"Qijia Wobu",
    "gn:population":0,
    "gn:timezone":"Asia/Shanghai",
    "iso:country":"CN",
    "name:zho_x_preferred":[
        "\u9f50\u5bb6\u7a9d\u5821"
    ],
    "wof:name":"Qijia Wobu",
    "wof:placetype":"locality"
},
  "geometry": {"coordinates":[122.744,41.9023],"type":"Point"}
}