{
  "type": "Feature",
  "properties": {
    "gn:admin1_code":"4.0",
    "gn:asciiname":"Zhouzhaogang",
    "gn:country_code":"CN",
    "gn:dem":5,
    "gn:feature_class":"P",
    "gn:feature_code":"PPL",
    "gn:name":"Zhouzhaogang",
    "gn:population":0,
    "gn:timezone":"Asia/Shanghai",
    "iso:country":"CN",
    "name:zho_x_preferred":[
        "\u5468\u7167\u6e2f"
    ],
    "wof:name":"Zhouzhaogang",
    "wof:placetype":"locality"
},
  "geometry": {"coordinates":[120.99102000000001,32.03767],"type":"Point"}
}