{
  "type": "Feature",
  "properties": {
    "gn:admin1_code":"7.0",
    "gn:asciiname":"Meiyang",
    "gn:country_code":"CN",
    "gn:dem":513,
    "gn:feature_class":"P",
    "gn:feature_code":"PPL",
    "gn:name":"Meiyang",
    "gn:population":0,
    "gn:timezone":"Asia/Shanghai",
    "iso:country":"CN",
    "name:zho_x_preferred":[
        "\u6885\u6d0b"
    ],
    "wof:name":"Meiyang",
    "wof:placetype":"locality"
},
  "geometry": {"coordinates":[119.47172999999999,26.15646],"type":"Point"}
}