{
  "type": "Feature",
  "properties": {
    "gn:admin1_code":"29.0",
    "gn:asciiname":"Anji",
    "gn:country_code":"CN",
    "gn:dem":1569,
    "gn:feature_class":"P",
    "gn:feature_code":"PPL",
    "gn:name":"Anji",
    "gn:population":0,
    "gn:timezone":"Asia/Shanghai",
    "iso:country":"CN",
    "name:zho_x_preferred":[
        "\u5b89\u57fa"
    ],
    "wof:name":"Anji",
    "wof:placetype":"locality"
},
  "geometry": {"coordinates":[104.631,24.9361],"type":"Point"}
}