{
  "type": "Feature",
  "properties": {
    "gn:admin1_code":"15.0",
    "gn:asciiname":"Yatouzhuang",
    "gn:country_code":"CN",
    "gn:dem":994,
    "gn:feature_class":"P",
    "gn:feature_code":"PPL",
    "gn:name":"Yatouzhuang",
    "gn:population":0,
    "gn:timezone":"Asia/Shanghai",
    "iso:country":"CN",
    "name:und_x_variant":[
        "\u5d16\u5934\u5e84"
    ],
    "wof:name":"Yatouzhuang",
    "wof:placetype":"locality"
},
  "geometry": {"coordinates":[106.2983,33.92972],"type":"Point"}
}