{
  "type": "Feature",
  "properties": {
    "gn:admin1_code":"26.0",
    "gn:asciiname":"Xinhongpu",
    "gn:country_code":"CN",
    "gn:dem":1501,
    "gn:feature_class":"P",
    "gn:feature_code":"PPL",
    "gn:name":"Xinhongpu",
    "gn:population":0,
    "gn:timezone":"Asia/Shanghai",
    "iso:country":"CN",
    "name:und_x_variant":[
        "\u5fc3\u7ea2\u94fa"
    ],
    "wof:name":"Xinhongpu",
    "wof:placetype":"locality"
},
  "geometry": {"coordinates":[106.66972,33.88308],"type":"Point"}
}