{
  "type": "Feature",
  "properties": {
    "gn:admin1_code":"11.0",
    "gn:asciiname":"Yuemochang",
    "gn:country_code":"CN",
    "gn:dem":847,
    "gn:feature_class":"P",
    "gn:feature_code":"PPL",
    "gn:name":"Yuemochang",
    "gn:population":0,
    "gn:timezone":"Asia/Shanghai",
    "iso:country":"CN",
    "name:zho_x_preferred":[
        "\u8dc3\u672b\u573a"
    ],
    "wof:name":"Yuemochang",
    "wof:placetype":"locality"
},
  "geometry": {"coordinates":[110.12900999999999,29.71296],"type":"Point"}
}