{
  "type": "Feature",
  "properties": {
    "gn:admin1_code":"8.0",
    "gn:asciiname":"Sanzhuang",
    "gn:country_code":"CN",
    "gn:dem":235,
    "gn:feature_class":"P",
    "gn:feature_code":"PPL",
    "gn:name":"Sanzhuang",
    "gn:population":0,
    "gn:timezone":"Asia/Shanghai",
    "iso:country":"CN",
    "name:zho_x_preferred":[
        "\u4e09\u5e84"
    ],
    "wof:name":"Sanzhuang",
    "wof:placetype":"locality"
},
  "geometry": {"coordinates":[127.54653999999999,47.39364000000001],"type":"Point"}
}