{
  "type": "Feature",
  "properties": {
    "gn:admin1_code":"33.0",
    "gn:asciiname":"Jiangao",
    "gn:country_code":"CN",
    "gn:dem":237,
    "gn:feature_class":"P",
    "gn:feature_code":"PPL",
    "gn:name":"Jiangao",
    "gn:population":0,
    "gn:timezone":"Asia/Shanghai",
    "iso:country":"CN",
    "name:zho_x_preferred":[
        "\u7bad\u9ad8"
    ],
    "wof:name":"Jiangao",
    "wof:placetype":"locality"
},
  "geometry": {"coordinates":[106.23768,29.90679],"type":"Point"}
}