{
  "type": "Feature",
  "properties": {
    "gn:admin1_code":"31.0",
    "gn:asciiname":"Liancheng",
    "gn:country_code":"CN",
    "gn:dem":41,
    "gn:feature_class":"P",
    "gn:feature_code":"PPL",
    "gn:name":"Liancheng",
    "gn:population":0,
    "gn:timezone":"Asia/Shanghai",
    "iso:country":"CN",
    "name:ceb_x_preferred":[
        "Liancheng"
    ],
    "name:deu_x_preferred":[
        "Liancheng"
    ],
    "name:zho_x_preferred":[
        "Liancheng"
    ],
    "name:zho_x_variant":[
        "\u8054\u6210"
    ],
    "wof:name":"Liancheng",
    "wof:placetype":"locality"
},
  "geometry": {"coordinates":[110.89078000000001,19.80343],"type":"Point"}
}