{
  "type": "Feature",
  "properties": {
    "gn:admin1_code":"21.0",
    "gn:asciiname":"Xiangdong Dadui",
    "gn:country_code":"CN",
    "gn:dem":1139,
    "gn:feature_class":"P",
    "gn:feature_code":"PPLF",
    "gn:name":"Xiangdong Dadui",
    "gn:population":0,
    "gn:timezone":"Asia/Shanghai",
    "iso:country":"CN",
    "name:zho_x_preferred":[
        "\u5411\u4e1c\u5927\u961f"
    ],
    "wof:name":"Xiangdong Dadui",
    "wof:placetype":"locality"
},
  "geometry": {"coordinates":[106.068,37.9291],"type":"Point"}
}