{
  "type": "Feature",
  "properties": {
    "gn:admin1_code":"26.0",
    "gn:asciiname":"Xiliangwan",
    "gn:country_code":"CN",
    "gn:dem":1170,
    "gn:feature_class":"P",
    "gn:feature_code":"PPL",
    "gn:name":"Xiliangwan",
    "gn:population":0,
    "gn:timezone":"Asia/Shanghai",
    "iso:country":"CN",
    "name:und_x_variant":[
        "\u897f\u51c9\u6e7e"
    ],
    "wof:name":"Xiliangwan",
    "wof:placetype":"locality"
},
  "geometry": {"coordinates":[107.07550000000001,34.95567],"type":"Point"}
}