{
  "type": "Feature",
  "properties": {
    "gn:admin1_code":"26.0",
    "gn:asciiname":"Yangzhuangke",
    "gn:country_code":"CN",
    "gn:dem":1355,
    "gn:feature_class":"P",
    "gn:feature_code":"PPL",
    "gn:name":"Yangzhuangke",
    "gn:population":0,
    "gn:timezone":"Asia/Shanghai",
    "iso:country":"CN",
    "name:zho_x_preferred":[
        "\u6768\u5e84\u79d1"
    ],
    "wof:name":"Yangzhuangke",
    "wof:placetype":"locality"
},
  "geometry": {"coordinates":[108.63037,36.50959],"type":"Point"}
}