{
  "type": "Feature",
  "properties": {
    "gn:admin1_code":"19.0",
    "gn:asciiname":"Wuhutun",
    "gn:country_code":"CN",
    "gn:dem":127,
    "gn:feature_class":"P",
    "gn:feature_code":"PPL",
    "gn:name":"Wuhutun",
    "gn:population":0,
    "gn:timezone":"Asia/Shanghai",
    "iso:country":"CN",
    "name:zho_x_preferred":[
        "\u4e94\u864e\u5c6f"
    ],
    "wof:name":"Wuhutun",
    "wof:placetype":"locality"
},
  "geometry": {"coordinates":[120.663,41.2112],"type":"Point"}
}