{
  "type": "Feature",
  "properties": {
    "gn:admin1_code":"19.0",
    "gn:asciiname":"Sunlucun",
    "gn:country_code":"CN",
    "gn:dem":100,
    "gn:feature_class":"P",
    "gn:feature_code":"PPL",
    "gn:name":"Sunlucun",
    "gn:population":0,
    "gn:timezone":"Asia/Shanghai",
    "iso:country":"CN",
    "name:zho_x_preferred":[
        "\u5b59\u7089\u6751"
    ],
    "wof:name":"Sunlucun",
    "wof:placetype":"locality"
},
  "geometry": {"coordinates":[122.16568999999998,39.64671],"type":"Point"}
}