{
  "type": "Feature",
  "properties": {
    "gn:admin1_code":"01",
    "gn:asciiname":"Caozhuang",
    "gn:cc2":"CN",
    "gn:country_code":"CN",
    "gn:dem":27,
    "gn:feature_class":"P",
    "gn:feature_code":"PPL",
    "gn:name":"Caozhuang",
    "gn:population":0,
    "gn:timezone":"Asia/Shanghai",
    "iso:country":"CN",
    "name:ceb_x_preferred":[
        "Caozhuang"
    ],
    "name:swe_x_preferred":[
        "Caozhuang"
    ],
    "name:und_x_variant":[
        "Ts\u2019ao-chuang",
        "Ts\u2019ao-chi"
    ],
    "wof:name":"Caozhuang",
    "wof:placetype":"locality"
},
  "geometry": {"coordinates":[116.38333,33.08333],"type":"Point"}
}