{
  "type": "Feature",
  "properties": {
    "gn:admin1_code":"4.0",
    "gn:asciiname":"Zhaowu",
    "gn:country_code":"CN",
    "gn:dem":19,
    "gn:feature_class":"P",
    "gn:feature_code":"PPL",
    "gn:name":"Zhaowu",
    "gn:population":0,
    "gn:timezone":"Asia/Shanghai",
    "iso:country":"CN",
    "name:zho_x_preferred":[
        "\u53ec\u4e94"
    ],
    "wof:name":"Zhaowu",
    "wof:placetype":"locality"
},
  "geometry": {"coordinates":[118.261,32.9976],"type":"Point"}
}