{
  "type": "Feature",
  "properties": {
    "gn:admin1_code":"21.0",
    "gn:asciiname":"Yangwan",
    "gn:country_code":"CN",
    "gn:dem":1869,
    "gn:feature_class":"P",
    "gn:feature_code":"PPL",
    "gn:name":"Yangwan",
    "gn:population":0,
    "gn:timezone":"Asia/Shanghai",
    "iso:country":"CN",
    "name:zho_x_preferred":[
        "\u6768\u6e7e"
    ],
    "wof:name":"Yangwan",
    "wof:placetype":"locality"
},
  "geometry": {"coordinates":[105.75845,35.7351],"type":"Point"}
}