{
  "type": "Feature",
  "properties": {
    "gn:admin1_code":"02",
    "gn:asciiname":"Meiyuancun",
    "gn:country_code":"CN",
    "gn:dem":15,
    "gn:feature_class":"P",
    "gn:feature_code":"PPL",
    "gn:name":"Meiyuancun",
    "gn:population":0,
    "gn:timezone":"Asia/Shanghai",
    "iso:country":"CN",
    "name:und_x_variant":[
        "Meiyuan",
        "Meiyuancun"
    ],
    "name:zho_x_preferred":[
        "\u6885\u56ed"
    ],
    "name:zho_x_variant":[
        "\u6885\u56ed\u6751"
    ],
    "wof:name":"Meiyuancun",
    "wof:placetype":"locality"
},
  "geometry": {"coordinates":[120.71545999999999,28.04215],"type":"Point"}
}