{
  "type": "Feature",
  "properties": {
    "gn:admin1_code":"26.0",
    "gn:asciiname":"Gaojia Touxia",
    "gn:country_code":"CN",
    "gn:dem":775,
    "gn:feature_class":"P",
    "gn:feature_code":"PPL",
    "gn:name":"Gaojia Touxia",
    "gn:population":0,
    "gn:timezone":"Asia/Shanghai",
    "iso:country":"CN",
    "name:zho_x_preferred":[
        "\u9ad8\u5bb6\u5934\u4e0b"
    ],
    "wof:name":"Gaojia Touxia",
    "wof:placetype":"locality"
},
  "geometry": {"coordinates":[106.86678000000001,34.3727],"type":"Point"}
}