{
  "type": "Feature",
  "properties": {
    "gn:admin1_code":"15.0",
    "gn:asciiname":"Shaofangzhuang",
    "gn:country_code":"CN",
    "gn:dem":1955,
    "gn:feature_class":"P",
    "gn:feature_code":"PPL",
    "gn:name":"Shaofangzhuang",
    "gn:population":0,
    "gn:timezone":"Asia/Shanghai",
    "iso:country":"CN",
    "name:zho_x_preferred":[
        "\u70e7\u623f\u5e84"
    ],
    "wof:name":"Shaofangzhuang",
    "wof:placetype":"locality"
},
  "geometry": {"coordinates":[102.90000000000001,37.5424],"type":"Point"}
}