{
  "type": "Feature",
  "properties": {
    "gn:admin1_code":"29.0",
    "gn:asciiname":"Liuyang",
    "gn:country_code":"CN",
    "gn:dem":1598,
    "gn:feature_class":"P",
    "gn:feature_code":"PPL",
    "gn:name":"Liuyang",
    "gn:population":0,
    "gn:timezone":"Asia/Shanghai",
    "iso:country":"CN",
    "name:zho_x_preferred":[
        "\u516d\u4ef0"
    ],
    "wof:name":"Liuyang",
    "wof:placetype":"locality"
},
  "geometry": {"coordinates":[98.2792,24.4393],"type":"Point"}
}