{
  "type": "Feature",
  "properties": {
    "gn:admin1_code":"30",
    "gn:asciiname":"Nandoucun",
    "gn:country_code":"CN",
    "gn:dem":21,
    "gn:feature_class":"P",
    "gn:feature_code":"PPL",
    "gn:name":"Nandoucun",
    "gn:population":0,
    "gn:timezone":"Asia/Urumqi",
    "iso:country":"CN",
    "name:zho_x_preferred":[
        "\u90a3\u6597\u6751"
    ],
    "wof:name":"Nandoucun",
    "wof:placetype":"locality"
},
  "geometry": {"coordinates":[110.02649,20.34805],"type":"Point"}
}