{
  "type": "Feature",
  "properties": {
    "gn:admin1_code":"3.0",
    "gn:asciiname":"Aoshang",
    "gn:country_code":"CN",
    "gn:dem":281,
    "gn:feature_class":"P",
    "gn:feature_code":"PPL",
    "gn:name":"Aoshang",
    "gn:population":0,
    "gn:timezone":"Asia/Shanghai",
    "iso:country":"CN",
    "name:und_x_variant":[
        "\u5773\u4e0a"
    ],
    "wof:name":"Aoshang",
    "wof:placetype":"locality"
},
  "geometry": {"coordinates":[114.46268000000001,27.35244],"type":"Point"}
}