{
  "type": "Feature",
  "properties": {
    "gn:admin1_code":"25.0",
    "gn:asciiname":"Jinjiaokou",
    "gn:country_code":"CN",
    "gn:dem":13,
    "gn:feature_class":"P",
    "gn:feature_code":"PPL",
    "gn:name":"Jinjiaokou",
    "gn:population":0,
    "gn:timezone":"Asia/Shanghai",
    "iso:country":"CN",
    "name:zho_x_preferred":[
        "\u91d1\u89d2\u53e3"
    ],
    "wof:name":"Jinjiaokou",
    "wof:placetype":"locality"
},
  "geometry": {"coordinates":[122.52852,37.29335],"type":"Point"}
}