{
  "type": "Feature",
  "properties": {
    "gn:admin1_code":"21.0",
    "gn:asciiname":"Xiwei Zhuangzi",
    "gn:country_code":"CN",
    "gn:dem":1424,
    "gn:feature_class":"P",
    "gn:feature_code":"PPL",
    "gn:name":"Xiwei Zhuangzi",
    "gn:population":0,
    "gn:timezone":"Asia/Shanghai",
    "iso:country":"CN",
    "name:zho_x_preferred":[
        "\u897f\u9b4f\u5e84\u5b50"
    ],
    "wof:name":"Xiwei Zhuangzi",
    "wof:placetype":"locality"
},
  "geometry": {"coordinates":[106.443,37.2449],"type":"Point"}
}