{
  "type": "Feature",
  "properties": {
    "gn:admin1_code":"15.0",
    "gn:asciiname":"Rimanggaoba",
    "gn:country_code":"CN",
    "gn:dem":3191,
    "gn:feature_class":"P",
    "gn:feature_code":"PPL",
    "gn:name":"Rimanggaoba",
    "gn:population":0,
    "gn:timezone":"Asia/Shanghai",
    "iso:country":"CN",
    "name:und_x_variant":[
        "\u65e5\u8292\u544a\u5df4"
    ],
    "wof:name":"Rimanggaoba",
    "wof:placetype":"locality"
},
  "geometry": {"coordinates":[102.36968,35.0725],"type":"Point"}
}