{
  "type": "Feature",
  "properties": {
    "gn:admin1_code":"14.0",
    "gn:asciiname":"Jirongcun",
    "gn:country_code":"CN",
    "gn:dem":4152,
    "gn:feature_class":"P",
    "gn:feature_code":"PPL",
    "gn:name":"Jirongcun",
    "gn:population":0,
    "gn:timezone":"Asia/Urumqi",
    "iso:country":"CN",
    "name:zho_x_preferred":[
        "\u51e0\u8363\u6751"
    ],
    "wof:name":"Jirongcun",
    "wof:placetype":"locality"
},
  "geometry": {"coordinates":[94.24746,31.54462],"type":"Point"}
}