{
  "type": "Feature",
  "properties": {
    "gn:admin1_code":"4.0",
    "gn:asciiname":"Houshangwang",
    "gn:country_code":"CN",
    "gn:dem":19,
    "gn:feature_class":"P",
    "gn:feature_code":"PPL",
    "gn:name":"Houshangwang",
    "gn:population":0,
    "gn:timezone":"Asia/Shanghai",
    "iso:country":"CN",
    "name:zho_x_preferred":[
        "\u540e\u4e0a\u65fa"
    ],
    "wof:name":"Houshangwang",
    "wof:placetype":"locality"
},
  "geometry": {"coordinates":[118.623,34.3308],"type":"Point"}
}