{
  "type": "Feature",
  "properties": {
    "gn:admin1_code":"10.0",
    "gn:asciiname":"Landaoshi",
    "gn:country_code":"CN",
    "gn:dem":530,
    "gn:feature_class":"P",
    "gn:feature_code":"PPL",
    "gn:name":"Landaoshi",
    "gn:population":0,
    "gn:timezone":"Asia/Shanghai",
    "iso:country":"CN",
    "name:zho_x_preferred":[
        "\u62e6\u9053\u77f3"
    ],
    "wof:name":"Landaoshi",
    "wof:placetype":"locality"
},
  "geometry": {"coordinates":[113.75897000000001,38.5391],"type":"Point"}
}