{
  "type": "Feature",
  "properties": {
    "gn:admin1_code":"8.0",
    "gn:asciiname":"Congshan",
    "gn:country_code":"CN",
    "gn:dem":293,
    "gn:feature_class":"P",
    "gn:feature_code":"PPL",
    "gn:name":"Congshan",
    "gn:population":0,
    "gn:timezone":"Asia/Shanghai",
    "iso:country":"CN",
    "name:zho_x_preferred":[
        "\u4e1b\u5c71"
    ],
    "wof:name":"Congshan",
    "wof:placetype":"locality"
},
  "geometry": {"coordinates":[128.85341,49.05133],"type":"Point"}
}