{
  "type": "Feature",
  "properties": {
    "gn:admin1_code":"4.0",
    "gn:asciiname":"Biaoguzhuang",
    "gn:country_code":"CN",
    "gn:dem":12,
    "gn:feature_class":"P",
    "gn:feature_code":"PPL",
    "gn:name":"Biaoguzhuang",
    "gn:population":0,
    "gn:timezone":"Asia/Shanghai",
    "iso:country":"CN",
    "name:zho_x_preferred":[
        "\u6753\u80a1\u5e84"
    ],
    "wof:name":"Biaoguzhuang",
    "wof:placetype":"locality"
},
  "geometry": {"coordinates":[118.896,33.6416],"type":"Point"}
}