{
  "type": "Feature",
  "properties": {
    "gn:admin1_code":"19.0",
    "gn:asciiname":"Liutiaogou",
    "gn:country_code":"CN",
    "gn:dem":765,
    "gn:feature_class":"P",
    "gn:feature_code":"PPL",
    "gn:name":"Liutiaogou",
    "gn:population":0,
    "gn:timezone":"Asia/Shanghai",
    "iso:country":"CN",
    "name:zho_x_preferred":[
        "\u67f3\u6761\u6c9f"
    ],
    "wof:name":"Liutiaogou",
    "wof:placetype":"locality"
},
  "geometry": {"coordinates":[119.84798000000001,41.89645],"type":"Point"}
}