{
  "type": "Feature",
  "properties": {
    "gn:admin1_code":"12.0",
    "gn:asciiname":"Houdoupo",
    "gn:country_code":"CN",
    "gn:dem":51,
    "gn:feature_class":"P",
    "gn:feature_code":"PPL",
    "gn:name":"Houdoupo",
    "gn:population":0,
    "gn:timezone":"Asia/Shanghai",
    "iso:country":"CN",
    "name:zho_x_preferred":[
        "\u540e\u9661\u5761"
    ],
    "wof:name":"Houdoupo",
    "wof:placetype":"locality"
},
  "geometry": {"coordinates":[114.02485,31.02947],"type":"Point"}
}