{
  "type": "Feature",
  "properties": {
    "gn:admin1_code":"30.0",
    "gn:asciiname":"Shedeng",
    "gn:country_code":"CN",
    "gn:dem":163,
    "gn:feature_class":"P",
    "gn:feature_code":"PPL",
    "gn:name":"Shedeng",
    "gn:population":0,
    "gn:timezone":"Asia/Shanghai",
    "iso:country":"CN",
    "name:zho_x_preferred":[
        "\u793e\u9093"
    ],
    "wof:name":"Shedeng",
    "wof:placetype":"locality"
},
  "geometry": {"coordinates":[112.10093999999999,23.66389],"type":"Point"}
}