{
  "type": "Feature",
  "properties": {
    "gn:admin1_code":"7",
    "gn:asciiname":"Xiahexi",
    "gn:country_code":"CN",
    "gn:dem":496,
    "gn:feature_class":"P",
    "gn:feature_code":"PPL",
    "gn:name":"Xiahexi",
    "gn:population":0,
    "gn:timezone":"Asia/Shanghai",
    "iso:country":"CN",
    "name:zho_x_preferred":[
        "\u4e0b\u5408\u6eaa"
    ],
    "wof:name":"Xiahexi",
    "wof:placetype":"locality"
},
  "geometry": {"coordinates":[117.13276999999999,24.79823],"type":"Point"}
}