{
  "type": "Feature",
  "properties": {
    "gn:admin1_code":"25.0",
    "gn:asciiname":"Xinfu Shisicun",
    "gn:country_code":"CN",
    "gn:dem":5,
    "gn:feature_class":"P",
    "gn:feature_code":"PPL",
    "gn:name":"Xinfu Shisicun",
    "gn:population":0,
    "gn:timezone":"Asia/Shanghai",
    "iso:country":"CN",
    "name:zho_x_preferred":[
        "\u8f9b\u798f\u5341\u56db\u6751"
    ],
    "wof:name":"Xinfu Shisicun",
    "wof:placetype":"locality"
},
  "geometry": {"coordinates":[121.31064000000001,37.56375],"type":"Point"}
}