{
  "type": "Feature",
  "properties": {
    "gn:admin1_code":"19.0",
    "gn:asciiname":"Laobiancun",
    "gn:country_code":"CN",
    "gn:dem":107,
    "gn:feature_class":"P",
    "gn:feature_code":"PPL",
    "gn:name":"Laobiancun",
    "gn:population":0,
    "gn:timezone":"Asia/Shanghai",
    "iso:country":"CN",
    "name:zho_x_preferred":[
        "\u8001\u8fb9\u6751"
    ],
    "wof:name":"Laobiancun",
    "wof:placetype":"locality"
},
  "geometry": {"coordinates":[123.47602999999999,42.59411],"type":"Point"}
}