{
  "type": "Feature",
  "properties": {
    "gn:admin1_code":"26.0",
    "gn:asciiname":"Hanzhaicun",
    "gn:country_code":"CN",
    "gn:dem":937,
    "gn:feature_class":"P",
    "gn:feature_code":"PPL",
    "gn:name":"Hanzhaicun",
    "gn:population":0,
    "gn:timezone":"Asia/Shanghai",
    "iso:country":"CN",
    "name:zho_x_preferred":[
        "\u6c49\u5be8\u6751"
    ],
    "wof:name":"Hanzhaicun",
    "wof:placetype":"locality"
},
  "geometry": {"coordinates":[109.51049999999999,35.2622],"type":"Point"}
}