{
  "type": "Feature",
  "properties": {
    "gn:admin1_code":"26.0",
    "gn:asciiname":"Tanjiazhuang",
    "gn:country_code":"CN",
    "gn:dem":837,
    "gn:feature_class":"P",
    "gn:feature_code":"PPL",
    "gn:name":"Tanjiazhuang",
    "gn:population":0,
    "gn:timezone":"Asia/Shanghai",
    "iso:country":"CN",
    "name:und_x_variant":[
        "\u8c2d\u5bb6\u5e84"
    ],
    "wof:name":"Tanjiazhuang",
    "wof:placetype":"locality"
},
  "geometry": {"coordinates":[107.38590000000001,34.55279],"type":"Point"}
}