{
  "type": "Feature",
  "properties": {
    "gn:admin1_code":"12.0",
    "gn:asciiname":"Liuxifan",
    "gn:country_code":"CN",
    "gn:dem":30,
    "gn:feature_class":"P",
    "gn:feature_code":"PPL",
    "gn:name":"Liuxifan",
    "gn:population":0,
    "gn:timezone":"Asia/Shanghai",
    "iso:country":"CN",
    "name:und_x_variant":[
        "\u5218\u6eaa\u7548"
    ],
    "wof:name":"Liuxifan",
    "wof:placetype":"locality"
},
  "geometry": {"coordinates":[114.6776,30.90995],"type":"Point"}
}