{
  "type": "Feature",
  "properties": {
    "gn:admin1_code":"16.0",
    "gn:asciiname":"Tanglin",
    "gn:country_code":"CN",
    "gn:dem":142,
    "gn:feature_class":"P",
    "gn:feature_code":"PPL",
    "gn:name":"Tanglin",
    "gn:population":0,
    "gn:timezone":"Asia/Shanghai",
    "iso:country":"CN",
    "name:fas_x_preferred":[
        "\u062a\u0627\u0646\u06af\u0644\u06cc\u0646"
    ],
    "name:fin_x_preferred":[
        "Tanglin"
    ],
    "name:nld_x_preferred":[
        "Tanglin"
    ],
    "name:zho_x_preferred":[
        "\u5858\u6797"
    ],
    "wof:name":"Tanglin",
    "wof:placetype":"locality"
},
  "geometry": {"coordinates":[107.054,23.7093],"type":"Point"}
}