{
  "type": "Feature",
  "properties": {
    "gn:admin1_code":"26.0",
    "gn:asciiname":"Dongchengdi",
    "gn:country_code":"CN",
    "gn:dem":979,
    "gn:feature_class":"P",
    "gn:feature_code":"PPL",
    "gn:name":"Dongchengdi",
    "gn:population":0,
    "gn:timezone":"Asia/Shanghai",
    "iso:country":"CN",
    "name:zho_x_preferred":[
        "\u4e1c\u6491\u5e95"
    ],
    "wof:name":"Dongchengdi",
    "wof:placetype":"locality"
},
  "geometry": {"coordinates":[108.55562999999999,34.81405],"type":"Point"}
}