{
  "type": "Feature",
  "properties": {
    "gn:admin1_code":"16.0",
    "gn:asciiname":"Naren",
    "gn:country_code":"CN",
    "gn:dem":147,
    "gn:feature_class":"P",
    "gn:feature_code":"PPL",
    "gn:name":"Naren",
    "gn:population":0,
    "gn:timezone":"Asia/Shanghai",
    "iso:country":"CN",
    "name:zho_x_preferred":[
        "\u90a3\u4efb"
    ],
    "wof:name":"Naren",
    "wof:placetype":"locality"
},
  "geometry": {"coordinates":[108.053,22.4518],"type":"Point"}
}