{
  "type": "Feature",
  "properties": {
    "gn:admin1_code":"20.0",
    "gn:asciiname":"Shangdao Jialiang",
    "gn:country_code":"CN",
    "gn:dem":1267,
    "gn:feature_class":"P",
    "gn:feature_code":"PPL",
    "gn:name":"Shangdao Jialiang",
    "gn:population":0,
    "gn:timezone":"Asia/Shanghai",
    "iso:country":"CN",
    "name:und_x_variant":[
        "\u4e0a\u5201\u5bb6\u6881"
    ],
    "wof:name":"Shangdao Jialiang",
    "wof:placetype":"locality"
},
  "geometry": {"coordinates":[111.50757,39.89476],"type":"Point"}
}