{
  "type": "Feature",
  "properties": {
    "gn:admin1_code":"26",
    "gn:asciiname":"Mujiazhai",
    "gn:country_code":"CN",
    "gn:dem":441,
    "gn:feature_class":"P",
    "gn:feature_code":"PPL",
    "gn:name":"Mujiazhai",
    "gn:population":0,
    "gn:timezone":"Asia/Shanghai",
    "iso:country":"CN",
    "name:zho_x_preferred":[
        "\u7a46\u5bb6\u5be8"
    ],
    "wof:name":"Mujiazhai",
    "wof:placetype":"locality"
},
  "geometry": {"coordinates":[108.0772,34.2447],"type":"Point"}
}