{
  "type": "Feature",
  "properties": {
    "gn:admin1_code":"25",
    "gn:asciiname":"Daminghu",
    "gn:country_code":"CN",
    "gn:dem":23,
    "gn:feature_class":"P",
    "gn:feature_code":"PPL",
    "gn:name":"Daminghu",
    "gn:population":0,
    "gn:timezone":"Asia/Shanghai",
    "iso:country":"CN",
    "name:zho_x_preferred":[
        "\u5927\u660e\u6e56"
    ],
    "wof:name":"Daminghu",
    "wof:placetype":"locality"
},
  "geometry": {"coordinates":[117.017,36.6753],"type":"Point"}
}