{
  "type": "Feature",
  "properties": {
    "gn:admin1_code":"26.0",
    "gn:asciiname":"Xiabu",
    "gn:country_code":"CN",
    "gn:dem":562,
    "gn:feature_class":"P",
    "gn:feature_code":"PPL",
    "gn:name":"Xiabu",
    "gn:population":0,
    "gn:timezone":"Asia/Shanghai",
    "iso:country":"CN",
    "name:und_x_variant":[
        "Xiabuci"
    ],
    "name:zho_x_preferred":[
        "\u4e0b\u5821"
    ],
    "name:zho_x_variant":[
        "\u4e0b\u5821\u5790"
    ],
    "wof:name":"Xiabu",
    "wof:placetype":"locality"
},
  "geometry": {"coordinates":[109.91064,34.992],"type":"Point"}
}