{
  "type": "Feature",
  "properties": {
    "gn:admin1_code":"12.0",
    "gn:asciiname":"Zhangdongtai",
    "gn:country_code":"CN",
    "gn:dem":33,
    "gn:feature_class":"P",
    "gn:feature_code":"PPL",
    "gn:name":"Zhangdongtai",
    "gn:population":0,
    "gn:timezone":"Asia/Shanghai",
    "iso:country":"CN",
    "name:zho_x_preferred":[
        "\u5f20\u8463\u53f0"
    ],
    "wof:name":"Zhangdongtai",
    "wof:placetype":"locality"
},
  "geometry": {"coordinates":[112.75915999999999,30.62637],"type":"Point"}
}