{
  "type": "Feature",
  "properties": {
    "gn:admin1_code":"5.0",
    "gn:asciiname":"Gongpengzicun",
    "gn:country_code":"CN",
    "gn:dem":229,
    "gn:feature_class":"P",
    "gn:feature_code":"PPL",
    "gn:name":"Gongpengzicun",
    "gn:population":0,
    "gn:timezone":"Asia/Shanghai",
    "iso:country":"CN",
    "name:zho_x_preferred":[
        "\u5f13\u68da\u5b50\u6751"
    ],
    "wof:name":"Gongpengzicun",
    "wof:placetype":"locality"
},
  "geometry": {"coordinates":[124.48309,44.07964000000001],"type":"Point"}
}