{
  "type": "Feature",
  "properties": {
    "gn:admin1_code":"12.0",
    "gn:asciiname":"Liaojiadawan",
    "gn:country_code":"CN",
    "gn:dem":80,
    "gn:feature_class":"P",
    "gn:feature_code":"PPL",
    "gn:name":"Liaojiadawan",
    "gn:population":0,
    "gn:timezone":"Asia/Shanghai",
    "iso:country":"CN",
    "name:zho_x_preferred":[
        "\u5ed6\u5bb6\u5927\u6e7e"
    ],
    "wof:name":"Liaojiadawan",
    "wof:placetype":"locality"
},
  "geometry": {"coordinates":[112.06332999999999,30.79092],"type":"Point"}
}