{
  "type": "Feature",
  "properties": {
    "iso:country":"CN",
    "name:ceb_x_preferred":[
        "Zhengding Xian"
    ],
    "name:ces_x_preferred":[
        "\u010cen-ting"
    ],
    "name:deu_x_preferred":[
        "Zhengding"
    ],
    "name:eng_x_preferred":[
        "Zhengding County"
    ],
    "name:eus_x_preferred":[
        "Zhengding konderria"
    ],
    "name:fas_x_preferred":[
        "\u0634\u0647\u0631\u0633\u062a\u0627\u0646 \u0698\u0646\u06af\u062f\u06cc\u0646\u06af"
    ],
    "name:gan_x_preferred":[
        "\u6b63\u5b9a\u53bf"
    ],
    "name:ind_x_preferred":[
        "Zhengding"
    ],
    "name:jpn_x_preferred":[
        "\u6b63\u5b9a\u770c"
    ],
    "name:kor_x_preferred":[
        "\uc815\ub529\ud604"
    ],
    "name:nan_x_preferred":[
        "Ch\u00e8ng-t\u0113ng-ko\u0101n"
    ],
    "name:nld_x_preferred":[
        "Zhengding"
    ],
    "name:nob_x_preferred":[
        "Zhengding"
    ],
    "name:pol_x_preferred":[
        "Zhengding"
    ],
    "name:rus_x_preferred":[
        "\u0427\u0436\u044d\u043d\u0434\u0438\u043d"
    ],
    "name:spa_x_preferred":[
        "Zhengding"
    ],
    "name:swe_x_preferred":[
        "Zhengding"
    ],
    "name:vie_x_preferred":[
        "Ch\u00ednh \u0110\u1ecbnh"
    ],
    "name:wuu_x_preferred":[
        "\u6b63\u5b9a\u53bf"
    ],
    "name:zho_x_preferred":[
        "\u6b63\u5b9a\u53bf"
    ],
    "qs:name":"\u6b63\u5b9a\u53bf",
    "qs:name_adm0":"\u4e2d\u570b",
    "qs:name_adm1":"\u6cb3\u5317\u7701",
    "qs:photos":3,
    "qs:photos_1k":1,
    "qs:photos_9k":1,
    "qs:photos_9r":2,
    "qs:photos_all":39,
    "qs:photos_sr":1,
    "qs:placetype":"LocalAdmin",
    "qs:pop_sr":"0",
    "wd:wordcount":1375,
    "wof:name":"\u6b63\u5b9a\u53bf",
    "wof:placetype":"localadmin"
},
  "geometry": {"coordinates":[114.56830549999999,38.143201],"type":"Point"}
}