{
  "type": "Feature",
  "properties": {
    "iso:country":"CN",
    "qs:name":"\u6b63\u5b9a\u53bf",
    "qs:name_adm0":"\u4e2d\u570b",
    "qs:name_adm1":"\u6cb3\u5317\u7701",
    "qs:photos":3,
    "qs:photos_1k":1,
    "qs:photos_9k":1,
    "qs:photos_9r":2,
    "qs:photos_all":39,
    "qs:photos_sr":1,
    "qs:placetype":"LocalAdmin",
    "qs:pop_sr":"0",
    "wd:wordcount":1375,
    "wof:name":"\u6b63\u5b9a\u53bf",
    "wof:placetype":"localadmin"
},
  "geometry": {"coordinates":[114.56830549999999,38.143201],"type":"Point"}
}