{
  "type": "Feature",
  "properties": {
    "gn:admin1_code":"19.0",
    "gn:asciiname":"Heqigou",
    "gn:country_code":"CN",
    "gn:dem":10,
    "gn:feature_class":"P",
    "gn:feature_code":"PPL",
    "gn:name":"Heqigou",
    "gn:population":0,
    "gn:timezone":"Asia/Shanghai",
    "iso:country":"CN",
    "name:zho_x_preferred":[
        "\u548c\u6c14\u6c9f"
    ],
    "wof:name":"Heqigou",
    "wof:placetype":"locality"
},
  "geometry": {"coordinates":[122.358,39.1769],"type":"Point"}
}