{
  "type": "Feature",
  "properties": {
    "gn:admin1_code":"2.0",
    "gn:asciiname":"Yangdingkeng",
    "gn:country_code":"CN",
    "gn:dem":390,
    "gn:feature_class":"P",
    "gn:feature_code":"PPL",
    "gn:name":"Yangdingkeng",
    "gn:population":0,
    "gn:timezone":"Asia/Shanghai",
    "iso:country":"CN",
    "name:zho_x_preferred":[
        "\u6d0b\u5b9a\u5751"
    ],
    "wof:name":"Yangdingkeng",
    "wof:placetype":"locality"
},
  "geometry": {"coordinates":[118.84715,28.56224000000001],"type":"Point"}
}