{
  "type": "Feature",
  "properties": {
    "gn:admin1_code":"16",
    "gn:asciiname":"Longshantang",
    "gn:country_code":"CN",
    "gn:dem":154,
    "gn:feature_class":"P",
    "gn:feature_code":"PPL",
    "gn:name":"Longshantang",
    "gn:population":0,
    "gn:timezone":"Asia/Shanghai",
    "iso:country":"CN",
    "name:zho_x_preferred":[
        "\u9f99\u5c71\u5858"
    ],
    "wof:name":"Longshantang",
    "wof:placetype":"locality"
},
  "geometry": {"coordinates":[110.027,25.0948],"type":"Point"}
}