{
  "type": "Feature",
  "properties": {
    "gn:admin1_code":"24.0",
    "gn:asciiname":"Jijiazhuang",
    "gn:country_code":"CN",
    "gn:dem":1160,
    "gn:feature_class":"P",
    "gn:feature_code":"PPL",
    "gn:name":"Jijiazhuang",
    "gn:population":0,
    "gn:timezone":"Asia/Shanghai",
    "iso:country":"CN",
    "name:zho_x_preferred":[
        "\u5409\u5bb6\u5e84"
    ],
    "wof:name":"Jijiazhuang",
    "wof:placetype":"locality"
},
  "geometry": {"coordinates":[111.20335,37.76785],"type":"Point"}
}