{
  "type": "Feature",
  "properties": {
    "gn:admin1_code":"26.0",
    "gn:asciiname":"Haobazi",
    "gn:country_code":"CN",
    "gn:dem":880,
    "gn:feature_class":"P",
    "gn:feature_code":"PPL",
    "gn:name":"Haobazi",
    "gn:population":0,
    "gn:timezone":"Asia/Shanghai",
    "iso:country":"CN",
    "name:und_x_variant":[
        "\u597d\u575d\u5b50"
    ],
    "wof:name":"Haobazi",
    "wof:placetype":"locality"
},
  "geometry": {"coordinates":[106.10666000000001,33.17558],"type":"Point"}
}