{
  "type": "Feature",
  "properties": {
    "gn:admin1_code":"32",
    "gn:asciiname":"Qeyi",
    "gn:cc2":"CN",
    "gn:country_code":"CN",
    "gn:dem":4235,
    "gn:feature_class":"P",
    "gn:feature_code":"PPL",
    "gn:name":"Q\u00eayi",
    "gn:population":0,
    "gn:timezone":"Asia/Shanghai",
    "iso:country":"CN",
    "name:und_x_variant":[
        "Ch\u2019ieh-i",
        "Q\u00eayi"
    ],
    "wof:name":"Qeyi",
    "wof:placetype":"locality"
},
  "geometry": {"coordinates":[100.18333,31.23333],"type":"Point"}
}