{
  "type": "Feature",
  "properties": {
    "gn:admin1_code":"33.0",
    "gn:asciiname":"Lianglu",
    "gn:country_code":"CN",
    "gn:dem":457,
    "gn:feature_class":"P",
    "gn:feature_code":"PPL",
    "gn:name":"Lianglu",
    "gn:population":0,
    "gn:timezone":"Asia/Shanghai",
    "iso:country":"CN",
    "name:zho_x_preferred":[
        "\u4e24\u8def"
    ],
    "wof:name":"Lianglu",
    "wof:placetype":"locality"
},
  "geometry": {"coordinates":[107.77244,30.69722],"type":"Point"}
}