{
  "type": "Feature",
  "properties": {
    "gn:admin1_code":"12.0",
    "gn:asciiname":"Gunzihe",
    "gn:country_code":"CN",
    "gn:dem":46,
    "gn:feature_class":"P",
    "gn:feature_code":"PPL",
    "gn:name":"Gunzihe",
    "gn:population":0,
    "gn:timezone":"Asia/Shanghai",
    "iso:country":"CN",
    "name:zho_x_preferred":[
        "\u78d9\u5b50\u6cb3"
    ],
    "wof:name":"Gunzihe",
    "wof:placetype":"locality"
},
  "geometry": {"coordinates":[114.94511,30.72211],"type":"Point"}
}