{
  "type": "Feature",
  "properties": {
    "gn:admin1_code":"30.0",
    "gn:asciiname":"Kunlunshan",
    "gn:country_code":"CN",
    "gn:dem":254,
    "gn:feature_class":"P",
    "gn:feature_code":"PPL",
    "gn:name":"Kunlunshan",
    "gn:population":0,
    "gn:timezone":"Asia/Shanghai",
    "iso:country":"CN",
    "name:zho_x_preferred":[
        "\u6606\u4ed1\u5c71"
    ],
    "wof:name":"Kunlunshan",
    "wof:placetype":"locality"
},
  "geometry": {"coordinates":[116.87522,24.14544],"type":"Point"}
}