{
  "type": "Feature",
  "properties": {
    "gn:admin1_code":"8.0",
    "gn:asciiname":"Zhangjingfangtun",
    "gn:country_code":"CN",
    "gn:dem":214,
    "gn:feature_class":"P",
    "gn:feature_code":"PPL",
    "gn:name":"Zhangjingfangtun",
    "gn:population":0,
    "gn:timezone":"Asia/Shanghai",
    "iso:country":"CN",
    "name:zho_x_preferred":[
        "\u5f20\u666f\u82b3\u5c6f"
    ],
    "wof:name":"Zhangjingfangtun",
    "wof:placetype":"locality"
},
  "geometry": {"coordinates":[125.78825999999999,47.03874],"type":"Point"}
}