{
  "type": "Feature",
  "properties": {
    "gn:admin1_code":"5.0",
    "gn:asciiname":"Liangjiazi",
    "gn:country_code":"CN",
    "gn:dem":152,
    "gn:feature_class":"P",
    "gn:feature_code":"PPL",
    "gn:name":"Liangjiazi",
    "gn:population":0,
    "gn:timezone":"Asia/Shanghai",
    "iso:country":"CN",
    "name:zho_x_preferred":[
        "\u4e24\u5bb6\u5b50"
    ],
    "wof:name":"Liangjiazi",
    "wof:placetype":"locality"
},
  "geometry": {"coordinates":[122.99281999999999,44.54281],"type":"Point"}
}