{
  "type": "Feature",
  "properties": {
    "gn:admin1_code":"15.0",
    "gn:asciiname":"Wayaoli",
    "gn:country_code":"CN",
    "gn:dem":2014,
    "gn:feature_class":"P",
    "gn:feature_code":"PPL",
    "gn:name":"Wayaoli",
    "gn:population":0,
    "gn:timezone":"Asia/Shanghai",
    "iso:country":"CN",
    "name:und_x_variant":[
        "\u74e6\u7a91\u91cc"
    ],
    "name:zho_x_preferred":[
        "\u74e6\u7a91\u91cc"
    ],
    "wof:name":"Wayaoli",
    "wof:placetype":"locality"
},
  "geometry": {"coordinates":[104.89834999999999,33.90025],"type":"Point"}
}