{
  "type": "Feature",
  "properties": {
    "gn:admin1_code":"30.0",
    "gn:asciiname":"Huangyong",
    "gn:country_code":"CN",
    "gn:dem":6,
    "gn:feature_class":"P",
    "gn:feature_code":"PPL",
    "gn:name":"Huangyong",
    "gn:population":0,
    "gn:timezone":"Asia/Shanghai",
    "iso:country":"CN",
    "name:zho_x_preferred":[
        "\u6f62\u6d8c"
    ],
    "wof:name":"Huangyong",
    "wof:placetype":"locality"
},
  "geometry": {"coordinates":[113.72951999999999,23.12383],"type":"Point"}
}