{
  "type": "Feature",
  "properties": {
    "gn:admin1_code":"16.0",
    "gn:asciiname":"Neizhao",
    "gn:country_code":"CN",
    "gn:dem":339,
    "gn:feature_class":"P",
    "gn:feature_code":"PPL",
    "gn:name":"Neizhao",
    "gn:population":0,
    "gn:timezone":"Asia/Shanghai",
    "iso:country":"CN",
    "name:zho_x_preferred":[
        "\u5185\u8d75"
    ],
    "wof:name":"Neizhao",
    "wof:placetype":"locality"
},
  "geometry": {"coordinates":[108.57899999999999,23.6903],"type":"Point"}
}