{
  "type": "Feature",
  "properties": {
    "gn:admin1_code":"9.0",
    "gn:asciiname":"Houjia Zhongwan",
    "gn:country_code":"CN",
    "gn:dem":250,
    "gn:feature_class":"P",
    "gn:feature_code":"PPL",
    "gn:name":"Houjia Zhongwan",
    "gn:population":0,
    "gn:timezone":"Asia/Shanghai",
    "iso:country":"CN",
    "name:zho_x_preferred":[
        "\u4faf\u5bb6\u4e2d\u6e7e"
    ],
    "wof:name":"Houjia Zhongwan",
    "wof:placetype":"locality"
},
  "geometry": {"coordinates":[111.3339,32.93241],"type":"Point"}
}