{
  "type": "Feature",
  "properties": {
    "gn:admin1_code":"10",
    "gn:asciiname":"Hualinzi",
    "gn:country_code":"CN",
    "gn:dem":1583,
    "gn:feature_class":"P",
    "gn:feature_code":"PPL",
    "gn:name":"Hualinzi",
    "gn:population":0,
    "gn:timezone":"Asia/Shanghai",
    "iso:country":"CN",
    "name:zho_x_preferred":[
        "\u6866\u6797\u5b50"
    ],
    "wof:name":"Hualinzi",
    "wof:placetype":"locality"
},
  "geometry": {"coordinates":[115.36827,40.80988],"type":"Point"}
}