{
  "type": "Feature",
  "properties": {
    "gn:admin1_code":"29.0",
    "gn:asciiname":"Shangbanyou",
    "gn:country_code":"CN",
    "gn:dem":1943,
    "gn:feature_class":"P",
    "gn:feature_code":"PPL",
    "gn:name":"Shangbanyou",
    "gn:population":0,
    "gn:timezone":"Asia/Shanghai",
    "iso:country":"CN",
    "name:zho_x_preferred":[
        "\u4e0a\u73ed\u53f3"
    ],
    "wof:name":"Shangbanyou",
    "wof:placetype":"locality"
},
  "geometry": {"coordinates":[99.2616,23.3291],"type":"Point"}
}