{
  "type": "Feature",
  "properties": {
    "gn:admin1_code":"10",
    "gn:asciiname":"Dongjiaocun",
    "gn:country_code":"CN",
    "gn:dem":196,
    "gn:feature_class":"P",
    "gn:feature_code":"PPL",
    "gn:name":"Dongjiaocun",
    "gn:population":0,
    "gn:timezone":"Asia/Shanghai",
    "iso:country":"CN",
    "name:zho_x_preferred":[
        "\u4e1c\u7126\u6751"
    ],
    "wof:name":"Dongjiaocun",
    "wof:placetype":"locality"
},
  "geometry": {"coordinates":[114.2175,38.19333],"type":"Point"}
}