{
  "type": "Feature",
  "properties": {
    "gn:admin1_code":"16",
    "gn:asciiname":"Wumashan",
    "gn:country_code":"CN",
    "gn:dem":666,
    "gn:feature_class":"P",
    "gn:feature_code":"PPL",
    "gn:name":"Wumashan",
    "gn:population":0,
    "gn:timezone":"Asia/Shanghai",
    "iso:country":"CN",
    "name:zho_x_preferred":[
        "\u4e94\u9a6c\u5c71"
    ],
    "wof:name":"Wumashan",
    "wof:placetype":"locality"
},
  "geometry": {"coordinates":[110.958,25.3718],"type":"Point"}
}