{
  "type": "Feature",
  "properties": {
    "gn:admin1_code":"11.0",
    "gn:asciiname":"Chuanxikou",
    "gn:country_code":"CN",
    "gn:dem":636,
    "gn:feature_class":"P",
    "gn:feature_code":"PPL",
    "gn:name":"Chuanxikou",
    "gn:population":0,
    "gn:timezone":"Asia/Shanghai",
    "iso:country":"CN",
    "name:zho_x_preferred":[
        "\u5ddd\u6eaa\u53e3"
    ],
    "wof:name":"Chuanxikou",
    "wof:placetype":"locality"
},
  "geometry": {"coordinates":[109.21316000000002,27.1368],"type":"Point"}
}