{
  "type": "Feature",
  "properties": {
    "gn:admin1_code":"11.0",
    "gn:asciiname":"Dengcaowan",
    "gn:country_code":"CN",
    "gn:dem":733,
    "gn:feature_class":"P",
    "gn:feature_code":"PPL",
    "gn:name":"Dengcaowan",
    "gn:population":0,
    "gn:timezone":"Asia/Shanghai",
    "iso:country":"CN",
    "name:zho_x_preferred":[
        "\u706f\u8349\u6e7e"
    ],
    "wof:name":"Dengcaowan",
    "wof:placetype":"locality"
},
  "geometry": {"coordinates":[108.91488,27.15917],"type":"Point"}
}