{
  "type": "Feature",
  "properties": {
    "gn:admin1_code":"2.0",
    "gn:asciiname":"Dashanxia",
    "gn:country_code":"CN",
    "gn:dem":469,
    "gn:feature_class":"P",
    "gn:feature_code":"PPL",
    "gn:name":"Dashanxia",
    "gn:population":0,
    "gn:timezone":"Asia/Shanghai",
    "iso:country":"CN",
    "name:zho_x_preferred":[
        "\u5927\u5c71\u4e0b"
    ],
    "wof:name":"Dashanxia",
    "wof:placetype":"locality"
},
  "geometry": {"coordinates":[120.58129,29.3383],"type":"Point"}
}