{
  "type": "Feature",
  "properties": {
    "gn:admin1_code":"11",
    "gn:asciiname":"Shuangbanqiao",
    "gn:cc2":"CN",
    "gn:country_code":"CN",
    "gn:dem":162,
    "gn:feature_class":"P",
    "gn:feature_code":"PPL",
    "gn:name":"Shuangbanqiao",
    "gn:population":0,
    "gn:timezone":"Asia/Shanghai",
    "iso:country":"CN",
    "name:und_x_variant":[
        "Shuang-pan-ch\u2019iao",
        "Shuangbanqiao"
    ],
    "wof:name":"Shuangbanqiao",
    "wof:placetype":"locality"
},
  "geometry": {"coordinates":[112.23333,27.91667],"type":"Point"}
}