{
  "type": "Feature",
  "properties": {
    "gn:admin1_code":"10.0",
    "gn:asciiname":"Shenzhuangzi",
    "gn:country_code":"CN",
    "gn:dem":10,
    "gn:feature_class":"P",
    "gn:feature_code":"PPL",
    "gn:name":"Shenzhuangzi",
    "gn:population":0,
    "gn:timezone":"Asia/Shanghai",
    "iso:country":"CN",
    "name:zho_x_preferred":[
        "\u7533\u5e84\u5b50"
    ],
    "wof:name":"Shenzhuangzi",
    "wof:placetype":"locality"
},
  "geometry": {"coordinates":[116.819,38.4036],"type":"Point"}
}