{
  "type": "Feature",
  "properties": {
    "gn:admin1_code":"9.0",
    "gn:asciiname":"Zhoujialing",
    "gn:country_code":"CN",
    "gn:dem":656,
    "gn:feature_class":"P",
    "gn:feature_code":"PPL",
    "gn:name":"Zhoujialing",
    "gn:population":0,
    "gn:timezone":"Asia/Shanghai",
    "iso:country":"CN",
    "name:zho_x_preferred":[
        "\u5468\u5bb6\u5cad"
    ],
    "wof:name":"Zhoujialing",
    "wof:placetype":"locality"
},
  "geometry": {"coordinates":[111.69669,34.93308],"type":"Point"}
}