{
  "type": "Feature",
  "properties": {
    "gn:admin1_code":"1.0",
    "gn:asciiname":"Lailongcun",
    "gn:country_code":"CN",
    "gn:dem":42,
    "gn:feature_class":"P",
    "gn:feature_code":"PPL",
    "gn:name":"Lailongcun",
    "gn:population":0,
    "gn:timezone":"Asia/Shanghai",
    "iso:country":"CN",
    "name:zho_x_preferred":[
        "\u6765\u9f99\u6751"
    ],
    "wof:name":"Lailongcun",
    "wof:placetype":"locality"
},
  "geometry": {"coordinates":[118.76868,31.58569],"type":"Point"}
}