{
  "type": "Feature",
  "properties": {
    "gn:admin1_code":"3.0",
    "gn:asciiname":"Cuntou",
    "gn:country_code":"CN",
    "gn:dem":64,
    "gn:feature_class":"P",
    "gn:feature_code":"PPL",
    "gn:name":"Cuntou",
    "gn:population":0,
    "gn:timezone":"Asia/Shanghai",
    "iso:country":"CN",
    "name:und_x_variant":[
        "\u6751\u5934"
    ],
    "wof:name":"Cuntou",
    "wof:placetype":"locality"
},
  "geometry": {"coordinates":[115.95769,27.72419],"type":"Point"}
}