{
  "type": "Feature",
  "properties": {
    "gn:admin1_code":"7.0",
    "gn:asciiname":"Liuzhong",
    "gn:country_code":"CN",
    "gn:dem":218,
    "gn:feature_class":"P",
    "gn:feature_code":"PPL",
    "gn:name":"Liuzhong",
    "gn:population":0,
    "gn:timezone":"Asia/Shanghai",
    "iso:country":"CN",
    "name:zho_x_preferred":[
        "\u7559\u4e2d"
    ],
    "wof:name":"Liuzhong",
    "wof:placetype":"locality"
},
  "geometry": {"coordinates":[118.28578,27.48992],"type":"Point"}
}