{
  "type": "Feature",
  "properties": {
    "gn:admin1_code":"29.0",
    "gn:asciiname":"Fuminyi",
    "gn:country_code":"CN",
    "gn:dem":2414,
    "gn:feature_class":"P",
    "gn:feature_code":"PPL",
    "gn:name":"Fuminyi",
    "gn:population":0,
    "gn:timezone":"Asia/Shanghai",
    "iso:country":"CN",
    "name:zho_x_preferred":[
        "\u5bcc\u6c11\u9091"
    ],
    "wof:name":"Fuminyi",
    "wof:placetype":"locality"
},
  "geometry": {"coordinates":[99.5855,26.5334],"type":"Point"}
}