{
  "type": "Feature",
  "properties": {
    "gn:admin1_code":"10",
    "gn:asciiname":"Qihao",
    "gn:country_code":"CN",
    "gn:dem":1381,
    "gn:feature_class":"P",
    "gn:feature_code":"PPLF",
    "gn:name":"Qihao",
    "gn:population":0,
    "gn:timezone":"Asia/Shanghai",
    "iso:country":"CN",
    "name:zho_x_preferred":[
        "\u4e03\u53f7"
    ],
    "wof:name":"Qihao",
    "wof:placetype":"locality"
},
  "geometry": {"coordinates":[117.78119,42.25551],"type":"Point"}
}