{
  "type": "Feature",
  "properties": {
    "gn:admin1_code":"29",
    "gn:asciiname":"Bachai",
    "gn:country_code":"CN",
    "gn:dem":1105,
    "gn:feature_class":"P",
    "gn:feature_code":"PPL",
    "gn:name":"Bachai",
    "gn:population":0,
    "gn:timezone":"Asia/Shanghai",
    "iso:country":"CN",
    "name:urd_x_preferred":[
        "\u0628\u0627\u0686\u0626\u06cc"
    ],
    "name:zho_x_preferred":[
        "\u516b\u67f4"
    ],
    "wof:name":"Bachai",
    "wof:placetype":"locality"
},
  "geometry": {"coordinates":[105.202,23.8429],"type":"Point"}
}