{
  "type": "Feature",
  "properties": {
    "gn:admin1_code":"3.0",
    "gn:asciiname":"Huakengwu",
    "gn:country_code":"CN",
    "gn:dem":577,
    "gn:feature_class":"P",
    "gn:feature_code":"PPL",
    "gn:name":"Huakengwu",
    "gn:population":0,
    "gn:timezone":"Asia/Shanghai",
    "iso:country":"CN",
    "name:zho_x_preferred":[
        "\u82b1\u5751\u575e"
    ],
    "wof:name":"Huakengwu",
    "wof:placetype":"locality"
},
  "geometry": {"coordinates":[117.77222999999999,28.8491],"type":"Point"}
}