{
  "type": "Feature",
  "properties": {
    "gn:admin1_code":"9",
    "gn:asciiname":"Dalangzhong",
    "gn:country_code":"CN",
    "gn:dem":59,
    "gn:feature_class":"P",
    "gn:feature_code":"PPL",
    "gn:name":"Dalangzhong",
    "gn:population":0,
    "gn:timezone":"Asia/Shanghai",
    "iso:country":"CN",
    "name:zho_x_preferred":[
        "\u5927\u90ce\u4e2d"
    ],
    "wof:name":"Dalangzhong",
    "wof:placetype":"locality"
},
  "geometry": {"coordinates":[115.087,35.4593],"type":"Point"}
}