{
  "type": "Feature",
  "properties": {
    "gn:admin1_code":"9.0",
    "gn:asciiname":"Wangxiaomiao",
    "gn:country_code":"CN",
    "gn:dem":84,
    "gn:feature_class":"P",
    "gn:feature_code":"PPL",
    "gn:name":"Wangxiaomiao",
    "gn:population":0,
    "gn:timezone":"Asia/Shanghai",
    "iso:country":"CN",
    "name:zho_x_preferred":[
        "\u6c6a\u5c0f\u5e99"
    ],
    "wof:name":"Wangxiaomiao",
    "wof:placetype":"locality"
},
  "geometry": {"coordinates":[115.32384,31.94779],"type":"Point"}
}