{
  "type": "Feature",
  "properties": {
    "gn:admin1_code":"8.0",
    "gn:asciiname":"Silingsi Linchang Nanyaodi",
    "gn:country_code":"CN",
    "gn:dem":331,
    "gn:feature_class":"P",
    "gn:feature_code":"PPLF",
    "gn:name":"Silingsi Linchang Nanyaodi",
    "gn:population":0,
    "gn:timezone":"Asia/Shanghai",
    "iso:country":"CN",
    "name:zho_x_preferred":[
        "\u56db\u96f6\u56db\u6797\u573a\u5357\u7a91\u5730"
    ],
    "wof:name":"Silingsi Linchang Nanyaodi",
    "wof:placetype":"locality"
},
  "geometry": {"coordinates":[127.10983,48.31551],"type":"Point"}
}