{
  "type": "Feature",
  "properties": {
    "gn:admin1_code":"11.0",
    "gn:asciiname":"Shimaoping",
    "gn:country_code":"CN",
    "gn:dem":767,
    "gn:feature_class":"P",
    "gn:feature_code":"PPL",
    "gn:name":"Shimaoping",
    "gn:population":0,
    "gn:timezone":"Asia/Shanghai",
    "iso:country":"CN",
    "name:zho_x_preferred":[
        "\u8bd7\u6bdb\u576a"
    ],
    "wof:name":"Shimaoping",
    "wof:placetype":"locality"
},
  "geometry": {"coordinates":[112.39955999999999,26.16811],"type":"Point"}
}