{
  "type": "Feature",
  "properties": {
    "gn:admin1_code":"5.0",
    "gn:asciiname":"Nijia Yingzi",
    "gn:country_code":"CN",
    "gn:dem":136,
    "gn:feature_class":"P",
    "gn:feature_code":"PPL",
    "gn:name":"Nijia Yingzi",
    "gn:population":0,
    "gn:timezone":"Asia/Shanghai",
    "iso:country":"CN",
    "name:zho_x_preferred":[
        "\u502a\u5bb6\u8425\u5b50"
    ],
    "wof:name":"Nijia Yingzi",
    "wof:placetype":"locality"
},
  "geometry": {"coordinates":[123.89534999999999,43.44462],"type":"Point"}
}