{
  "type": "Feature",
  "properties": {
    "gn:admin1_code":"18",
    "gn:asciiname":"Kaiyan",
    "gn:country_code":"CN",
    "gn:dem":920,
    "gn:feature_class":"P",
    "gn:feature_code":"PPL",
    "gn:name":"Kaiyan",
    "gn:population":0,
    "gn:timezone":"Asia/Shanghai",
    "iso:country":"CN",
    "name:zho_x_preferred":[
        "\u5f00\u5ca9"
    ],
    "wof:name":"Kaiyan",
    "wof:placetype":"locality"
},
  "geometry": {"coordinates":[106.40300000000001,25.56900000000001],"type":"Point"}
}