{
  "type": "Feature",
  "properties": {
    "gn:admin1_code":"30.0",
    "gn:asciiname":"Maoshanling",
    "gn:country_code":"CN",
    "gn:dem":536,
    "gn:feature_class":"P",
    "gn:feature_code":"PPL",
    "gn:name":"Maoshanling",
    "gn:population":0,
    "gn:timezone":"Asia/Shanghai",
    "iso:country":"CN",
    "name:zho_x_preferred":[
        "Maoshanling"
    ],
    "name:zho_x_variant":[
        "\u8305\u5c71\u5cad"
    ],
    "wof:name":"Maoshanling",
    "wof:placetype":"locality"
},
  "geometry": {"coordinates":[112.80222000000001,24.73972],"type":"Point"}
}