{
  "type": "Feature",
  "properties": {
    "gn:admin1_code":"02",
    "gn:asciiname":"Jinshi",
    "gn:country_code":"CN",
    "gn:dem":763,
    "gn:feature_class":"P",
    "gn:feature_code":"PPL",
    "gn:name":"Jinshi",
    "gn:population":0,
    "gn:timezone":"Asia/Shanghai",
    "iso:country":"CN",
    "name:zho_x_preferred":[
        "\u8fdb\u58eb"
    ],
    "wof:name":"Jinshi",
    "wof:placetype":"locality"
},
  "geometry": {"coordinates":[120.11311000000001,27.64147],"type":"Point"}
}