{
  "type": "Feature",
  "properties": {
    "gn:admin1_code":"18.0",
    "gn:asciiname":"Yingpan'ao",
    "gn:country_code":"CN",
    "gn:dem":983,
    "gn:feature_class":"P",
    "gn:feature_code":"PPL",
    "gn:name":"Yingpan\u2019ao",
    "gn:population":0,
    "gn:timezone":"Asia/Shanghai",
    "iso:country":"CN",
    "name:und_x_variant":[
        "Yingpan\u2019ao"
    ],
    "name:zho_x_preferred":[
        "\u8425\u76d8\u5773"
    ],
    "wof:name":"Yingpan'ao",
    "wof:placetype":"locality"
},
  "geometry": {"coordinates":[108.496,27.5214],"type":"Point"}
}