{
  "type": "Feature",
  "properties": {
    "gn:admin1_code":"19.0",
    "gn:asciiname":"Xiaolongmiao",
    "gn:country_code":"CN",
    "gn:dem":105,
    "gn:feature_class":"P",
    "gn:feature_code":"PPL",
    "gn:name":"Xiaolongmiao",
    "gn:population":0,
    "gn:timezone":"Asia/Shanghai",
    "iso:country":"CN",
    "name:und_x_variant":[
        "\u5c0f\u9f99\u5e99"
    ],
    "wof:name":"Xiaolongmiao",
    "wof:placetype":"locality"
},
  "geometry": {"coordinates":[122.61259,40.40577],"type":"Point"}
}