{
  "type": "Feature",
  "properties": {
    "gn:admin1_code":"3.0",
    "gn:asciiname":"Yi'an",
    "gn:country_code":"CN",
    "gn:dem":523,
    "gn:feature_class":"P",
    "gn:feature_code":"PPL",
    "gn:name":"Yi\u2019an",
    "gn:population":0,
    "gn:timezone":"Asia/Shanghai",
    "iso:country":"CN",
    "name:und_x_variant":[
        "Yi\u2019an",
        "\u4e49\u5b89"
    ],
    "wof:name":"Yi'an",
    "wof:placetype":"locality"
},
  "geometry": {"coordinates":[115.3933,25.23197],"type":"Point"}
}