{
  "type": "Feature",
  "properties": {
    "gn:admin1_code":"19.0",
    "gn:asciiname":"Banzituncun",
    "gn:country_code":"CN",
    "gn:dem":119,
    "gn:feature_class":"P",
    "gn:feature_code":"PPL",
    "gn:name":"Banzituncun",
    "gn:population":0,
    "gn:timezone":"Asia/Shanghai",
    "iso:country":"CN",
    "name:zho_x_preferred":[
        "\u677f\u5b50\u5c6f\u6751"
    ],
    "wof:name":"Banzituncun",
    "wof:placetype":"locality"
},
  "geometry": {"coordinates":[122.9092,40.62938],"type":"Point"}
}