{
  "type": "Feature",
  "properties": {
    "gn:admin1_code":"8.0",
    "gn:asciiname":"Hepingfengdian",
    "gn:country_code":"CN",
    "gn:dem":545,
    "gn:feature_class":"P",
    "gn:feature_code":"PPL",
    "gn:name":"Hepingfengdian",
    "gn:population":0,
    "gn:timezone":"Asia/Shanghai",
    "iso:country":"CN",
    "name:zho_x_preferred":[
        "\u548c\u5e73\u8702\u70b9"
    ],
    "wof:name":"Hepingfengdian",
    "wof:placetype":"locality"
},
  "geometry": {"coordinates":[130.20376000000002,44.75165],"type":"Point"}
}