{
  "type": "Feature",
  "properties": {
    "gn:admin1_code":"33.0",
    "gn:asciiname":"Laoxiong",
    "gn:country_code":"CN",
    "gn:dem":955,
    "gn:feature_class":"P",
    "gn:feature_code":"PPL",
    "gn:name":"Laoxiong",
    "gn:population":0,
    "gn:timezone":"Asia/Shanghai",
    "iso:country":"CN",
    "name:zho_x_preferred":[
        "\u8001\u718a"
    ],
    "wof:name":"Laoxiong",
    "wof:placetype":"locality"
},
  "geometry": {"coordinates":[108.46419,28.78073],"type":"Point"}
}