{
  "type": "Feature",
  "properties": {
    "gn:admin1_code":"22.0",
    "gn:asciiname":"Zhengpengzi",
    "gn:country_code":"CN",
    "gn:dem":799,
    "gn:feature_class":"P",
    "gn:feature_code":"PPL",
    "gn:name":"Zhengpengzi",
    "gn:population":0,
    "gn:timezone":"Asia/Shanghai",
    "iso:country":"CN",
    "name:zho_x_preferred":[
        "\u90d1\u68da\u5b50"
    ],
    "wof:name":"Zhengpengzi",
    "wof:placetype":"locality"
},
  "geometry": {"coordinates":[116.36672,40.8941],"type":"Point"}
}