{
  "type": "Feature",
  "properties": {
    "gn:admin1_code":"1.0",
    "gn:asciiname":"Lingquancun",
    "gn:country_code":"CN",
    "gn:dem":61,
    "gn:feature_class":"P",
    "gn:feature_code":"PPL",
    "gn:name":"Lingquancun",
    "gn:population":0,
    "gn:timezone":"Asia/Shanghai",
    "iso:country":"CN",
    "name:zho_x_preferred":[
        "\u7075\u6cc9\u6751"
    ],
    "wof:name":"Lingquancun",
    "wof:placetype":"locality"
},
  "geometry": {"coordinates":[117.30431000000002,32.70327],"type":"Point"}
}