{
  "type": "Feature",
  "properties": {
    "gn:admin1_code":"16",
    "gn:asciiname":"Taizushan",
    "gn:country_code":"CN",
    "gn:dem":911,
    "gn:feature_class":"P",
    "gn:feature_code":"PPL",
    "gn:name":"Taizushan",
    "gn:population":0,
    "gn:timezone":"Asia/Shanghai",
    "iso:country":"CN",
    "name:zho_x_preferred":[
        "\u592a\u7956\u5c71"
    ],
    "wof:name":"Taizushan",
    "wof:placetype":"locality"
},
  "geometry": {"coordinates":[110.89100000000001,25.3457],"type":"Point"}
}