{
  "type": "Feature",
  "properties": {
    "gn:admin1_code":"6.0",
    "gn:asciiname":"Bag Belqer",
    "gn:country_code":"CN",
    "gn:dem":4313,
    "gn:feature_class":"P",
    "gn:feature_code":"PPL",
    "gn:name":"Bag Belqer",
    "gn:population":0,
    "gn:timezone":"Asia/Urumqi",
    "iso:country":"CN",
    "wof:name":"Bag Belqer",
    "wof:placetype":"locality"
},
  "geometry": {"coordinates":[98.53333000000001,35.83333],"type":"Point"}
}