{
  "type": "Feature",
  "properties": {
    "gn:admin1_code":"5.0",
    "gn:asciiname":"Xitaipingchuan",
    "gn:country_code":"CN",
    "gn:dem":135,
    "gn:feature_class":"P",
    "gn:feature_code":"PPL",
    "gn:name":"Xitaipingchuan",
    "gn:population":0,
    "gn:timezone":"Asia/Shanghai",
    "iso:country":"CN",
    "name:zho_x_preferred":[
        "\u897f\u592a\u5e73\u5ddd"
    ],
    "wof:name":"Xitaipingchuan",
    "wof:placetype":"locality"
},
  "geometry": {"coordinates":[123.60321,45.45913],"type":"Point"}
}