{
  "type": "Feature",
  "properties": {
    "gn:admin1_code":"18",
    "gn:asciiname":"Emaozhai",
    "gn:country_code":"CN",
    "gn:dem":1649,
    "gn:feature_class":"P",
    "gn:feature_code":"PPL",
    "gn:name":"Emaozhai",
    "gn:population":0,
    "gn:timezone":"Asia/Shanghai",
    "iso:country":"CN",
    "name:zho_x_preferred":[
        "\u9e45\u6bdb\u5be8"
    ],
    "wof:name":"Emaozhai",
    "wof:placetype":"locality"
},
  "geometry": {"coordinates":[104.67400000000001,25.4118],"type":"Point"}
}