{
  "type": "Feature",
  "properties": {
    "gn:admin1_code":"30.0",
    "gn:asciiname":"Rezhecun",
    "gn:country_code":"CN",
    "gn:dem":125,
    "gn:feature_class":"P",
    "gn:feature_code":"PPL",
    "gn:name":"Rezhecun",
    "gn:population":0,
    "gn:timezone":"Asia/Shanghai",
    "iso:country":"CN",
    "name:zho_x_preferred":[
        "\u70ed\u67d8\u6751"
    ],
    "wof:name":"Rezhecun",
    "wof:placetype":"locality"
},
  "geometry": {"coordinates":[115.98188,24.53681],"type":"Point"}
}