{
  "type": "Feature",
  "properties": {
    "gn:admin1_code":"19.0",
    "gn:asciiname":"Xiaoshangwuqi",
    "gn:country_code":"CN",
    "gn:dem":17,
    "gn:feature_class":"P",
    "gn:feature_code":"PPL",
    "gn:name":"Xiaoshangwuqi",
    "gn:population":0,
    "gn:timezone":"Asia/Shanghai",
    "iso:country":"CN",
    "name:zho_x_preferred":[
        "\u5c0f\u4e0a\u4e94\u65d7"
    ],
    "wof:name":"Xiaoshangwuqi",
    "wof:placetype":"locality"
},
  "geometry": {"coordinates":[121.63126,41.34083],"type":"Point"}
}