{
  "type": "Feature",
  "properties": {
    "gn:admin1_code":"20.0",
    "gn:asciiname":"Fude Nantun",
    "gn:country_code":"CN",
    "gn:dem":308,
    "gn:feature_class":"P",
    "gn:feature_code":"PPL",
    "gn:name":"Fude Nantun",
    "gn:population":0,
    "gn:timezone":"Asia/Shanghai",
    "iso:country":"CN",
    "name:zho_x_preferred":[
        "\u798f\u5fb7\u5357\u5c6f"
    ],
    "wof:name":"Fude Nantun",
    "wof:placetype":"locality"
},
  "geometry": {"coordinates":[123.95717999999999,48.61513],"type":"Point"}
}