{
  "type": "Feature",
  "properties": {
    "gn:admin1_code":"4.0",
    "gn:asciiname":"Tianxingcun",
    "gn:country_code":"CN",
    "gn:dem":6,
    "gn:feature_class":"P",
    "gn:feature_code":"PPL",
    "gn:name":"Tianxingcun",
    "gn:population":0,
    "gn:timezone":"Asia/Shanghai",
    "iso:country":"CN",
    "name:zho_x_preferred":[
        "\u5929\u661f\u6751"
    ],
    "wof:name":"Tianxingcun",
    "wof:placetype":"locality"
},
  "geometry": {"coordinates":[119.95208999999998,32.10529],"type":"Point"}
}