{
  "type": "Feature",
  "properties": {
    "gn:admin1_code":"19.0",
    "gn:asciiname":"Zhaojia Buzi",
    "gn:country_code":"CN",
    "gn:dem":263,
    "gn:feature_class":"P",
    "gn:feature_code":"PPL",
    "gn:name":"Zhaojia Buzi",
    "gn:population":0,
    "gn:timezone":"Asia/Shanghai",
    "iso:country":"CN",
    "name:und_x_variant":[
        "Zhaojiabaozi",
        "\u8d75\u5bb6\u5821\u5b50",
        "Zhaojia Buzi"
    ],
    "name:zho_x_preferred":[
        "\u8d75\u5bb6\u5821\u5b50"
    ],
    "wof:name":"Zhaojia Buzi",
    "wof:placetype":"locality"
},
  "geometry": {"coordinates":[123.12942,40.97195],"type":"Point"}
}