{
  "type": "Feature",
  "properties": {
    "gn:admin1_code":"9.0",
    "gn:asciiname":"Kangzhai",
    "gn:country_code":"CN",
    "gn:dem":135,
    "gn:feature_class":"P",
    "gn:feature_code":"PPL",
    "gn:name":"Kangzhai",
    "gn:population":0,
    "gn:timezone":"Asia/Shanghai",
    "iso:country":"CN",
    "name:zho_x_preferred":[
        "\u4ea2\u5be8"
    ],
    "wof:name":"Kangzhai",
    "wof:placetype":"locality"
},
  "geometry": {"coordinates":[112.7209,32.38462],"type":"Point"}
}