{
  "type": "Feature",
  "properties": {
    "gn:admin1_code":"8.0",
    "gn:asciiname":"Huanshancun",
    "gn:country_code":"CN",
    "gn:dem":204,
    "gn:feature_class":"P",
    "gn:feature_code":"PPL",
    "gn:name":"Huanshancun",
    "gn:population":0,
    "gn:timezone":"Asia/Shanghai",
    "iso:country":"CN",
    "name:zho_x_preferred":[
        "\u73af\u5c71\u6751"
    ],
    "wof:name":"Huanshancun",
    "wof:placetype":"locality"
},
  "geometry": {"coordinates":[131.73204999999999,46.06056],"type":"Point"}
}