{
  "type": "Feature",
  "properties": {
    "gn:admin1_code":"4.0",
    "gn:asciiname":"Fuchacun",
    "gn:country_code":"CN",
    "gn:dem":4,
    "gn:feature_class":"P",
    "gn:feature_code":"PPL",
    "gn:name":"Fuchacun",
    "gn:population":0,
    "gn:timezone":"Asia/Shanghai",
    "iso:country":"CN",
    "name:zho_x_preferred":[
        "\u4ed8\u5c94\u6751"
    ],
    "wof:name":"Fuchacun",
    "wof:placetype":"locality"
},
  "geometry": {"coordinates":[119.53386999999999,34.42633],"type":"Point"}
}