{
  "type": "Feature",
  "properties": {
    "gn:admin1_code":"1.0",
    "gn:asciiname":"Cuijizicun",
    "gn:country_code":"CN",
    "gn:dem":36,
    "gn:feature_class":"P",
    "gn:feature_code":"PPL",
    "gn:name":"Cuijizicun",
    "gn:population":0,
    "gn:timezone":"Asia/Shanghai",
    "iso:country":"CN",
    "name:zho_x_preferred":[
        "\u5d14\u96c6\u5b50\u6751"
    ],
    "wof:name":"Cuijizicun",
    "wof:placetype":"locality"
},
  "geometry": {"coordinates":[115.61774,32.4186],"type":"Point"}
}