{
  "type": "Feature",
  "properties": {
    "gn:admin1_code":"30.0",
    "gn:asciiname":"Hongkan",
    "gn:country_code":"CN",
    "gn:dem":22,
    "gn:feature_class":"P",
    "gn:feature_code":"PPL",
    "gn:name":"Hongkan",
    "gn:population":0,
    "gn:timezone":"Asia/Urumqi",
    "iso:country":"CN",
    "name:zho_x_preferred":[
        "\u7ea2\u574e"
    ],
    "wof:name":"Hongkan",
    "wof:placetype":"locality"
},
  "geometry": {"coordinates":[110.25716,20.27152],"type":"Point"}
}