{
  "type": "Feature",
  "properties": {
    "gn:admin1_code":"20.0",
    "gn:asciiname":"Qianxi Lajin",
    "gn:country_code":"CN",
    "gn:dem":181,
    "gn:feature_class":"P",
    "gn:feature_code":"PPL",
    "gn:name":"Qianxi Lajin",
    "gn:population":0,
    "gn:timezone":"Asia/Shanghai",
    "iso:country":"CN",
    "name:zho_x_preferred":[
        "\u524d\u897f\u62c9\u91d1"
    ],
    "wof:name":"Qianxi Lajin",
    "wof:placetype":"locality"
},
  "geometry": {"coordinates":[124.49634,48.35719],"type":"Point"}
}