{
  "type": "Feature",
  "properties": {
    "gn:admin1_code":"3.0",
    "gn:asciiname":"Sanlicun",
    "gn:country_code":"CN",
    "gn:dem":112,
    "gn:feature_class":"P",
    "gn:feature_code":"PPL",
    "gn:name":"Sanlicun",
    "gn:population":0,
    "gn:timezone":"Asia/Shanghai",
    "iso:country":"CN",
    "name:und_x_variant":[
        "\u4e09\u91cc\u6751"
    ],
    "wof:name":"Sanlicun",
    "wof:placetype":"locality"
},
  "geometry": {"coordinates":[116.60355,28.10038],"type":"Point"}
}