{
  "type": "Feature",
  "properties": {
    "gn:admin1_code":"11.0",
    "gn:asciiname":"Hexiping",
    "gn:country_code":"CN",
    "gn:dem":219,
    "gn:feature_class":"P",
    "gn:feature_code":"PPL",
    "gn:name":"Hexiping",
    "gn:population":0,
    "gn:timezone":"Asia/Shanghai",
    "iso:country":"CN",
    "name:zho_x_preferred":[
        "\u8d3a\u559c\u576a"
    ],
    "wof:name":"Hexiping",
    "wof:placetype":"locality"
},
  "geometry": {"coordinates":[110.13634999999999,28.83486],"type":"Point"}
}