{
  "type": "Feature",
  "properties": {
    "gn:admin1_code":"29.0",
    "gn:asciiname":"Kangliang",
    "gn:country_code":"CN",
    "gn:dem":1344,
    "gn:feature_class":"P",
    "gn:feature_code":"PPL",
    "gn:name":"Kangliang",
    "gn:population":0,
    "gn:timezone":"Asia/Shanghai",
    "iso:country":"CN",
    "name:zho_x_preferred":[
        "\u6297\u826f"
    ],
    "wof:name":"Kangliang",
    "wof:placetype":"locality"
},
  "geometry": {"coordinates":[101.20699999999999,23.278],"type":"Point"}
}