{
  "type": "Feature",
  "properties": {
    "gn:admin1_code":"6.0",
    "gn:asciiname":"Erzhongduii",
    "gn:country_code":"CN",
    "gn:dem":2991,
    "gn:feature_class":"P",
    "gn:feature_code":"PPLF",
    "gn:name":"Erzhongduii",
    "gn:population":0,
    "gn:timezone":"Asia/Urumqi",
    "iso:country":"CN",
    "name:zho_x_preferred":[
        "\u4e8c\u4e2d\u961f"
    ],
    "wof:name":"Erzhongduii",
    "wof:placetype":"locality"
},
  "geometry": {"coordinates":[97.76734999999999,36.06669],"type":"Point"}
}