{
  "type": "Feature",
  "properties": {
    "gn:admin1_code":"7",
    "gn:asciiname":"Neikeng",
    "gn:country_code":"CN",
    "gn:dem":470,
    "gn:feature_class":"P",
    "gn:feature_code":"PPL",
    "gn:name":"Neikeng",
    "gn:population":0,
    "gn:timezone":"Asia/Shanghai",
    "iso:country":"CN",
    "name:zho_x_preferred":[
        "\u5185\u5751"
    ],
    "wof:name":"Neikeng",
    "wof:placetype":"locality"
},
  "geometry": {"coordinates":[117.14421000000002,24.32807],"type":"Point"}
}