{
  "type": "Feature",
  "properties": {
    "gn:admin1_code":"11.0",
    "gn:asciiname":"Tudiwu",
    "gn:country_code":"CN",
    "gn:dem":318,
    "gn:feature_class":"P",
    "gn:feature_code":"PPL",
    "gn:name":"Tudiwu",
    "gn:population":0,
    "gn:timezone":"Asia/Shanghai",
    "iso:country":"CN",
    "name:zho_x_preferred":[
        "\u571f\u5730\u5c4b"
    ],
    "wof:name":"Tudiwu",
    "wof:placetype":"locality"
},
  "geometry": {"coordinates":[113.09468,28.58593],"type":"Point"}
}