{
  "type": "Feature",
  "properties": {
    "gn:admin1_code":"2.0",
    "gn:asciiname":"Wangcunban",
    "gn:country_code":"CN",
    "gn:dem":269,
    "gn:feature_class":"P",
    "gn:feature_code":"PPL",
    "gn:name":"Wangcunban",
    "gn:population":0,
    "gn:timezone":"Asia/Shanghai",
    "iso:country":"CN",
    "name:zho_x_preferred":[
        "\u738b\u6751\u5742"
    ],
    "wof:name":"Wangcunban",
    "wof:placetype":"locality"
},
  "geometry": {"coordinates":[118.71680000000001,28.60453],"type":"Point"}
}