{
  "type": "Feature",
  "properties": {
    "gn:admin1_code":"18",
    "gn:asciiname":"Bakan",
    "gn:country_code":"CN",
    "gn:dem":579,
    "gn:feature_class":"P",
    "gn:feature_code":"PPL",
    "gn:name":"Bakan",
    "gn:population":0,
    "gn:timezone":"Asia/Shanghai",
    "iso:country":"CN",
    "name:ceb_x_preferred":[
        "Bakan"
    ],
    "name:deu_x_preferred":[
        "Bakan"
    ],
    "name:swe_x_preferred":[
        "Bakan"
    ],
    "name:zho_x_preferred":[
        "\u575d\u574e"
    ],
    "wof:name":"Bakan",
    "wof:placetype":"locality"
},
  "geometry": {"coordinates":[105.726,25.7477],"type":"Point"}
}