{
  "type": "Feature",
  "properties": {
    "gn:admin1_code":"14.0",
    "gn:asciiname":"Cala",
    "gn:country_code":"CN",
    "gn:dem":4491,
    "gn:feature_class":"P",
    "gn:feature_code":"PPLF",
    "gn:name":"Cala",
    "gn:population":0,
    "gn:timezone":"Asia/Urumqi",
    "iso:country":"CN",
    "name:bod_x_preferred":[
        "Cala"
    ],
    "name:zho_x_preferred":[
        "Chala"
    ],
    "name:zho_x_variant":[
        "\u5bdf\u62c9"
    ],
    "wof:name":"Cala",
    "wof:placetype":"locality"
},
  "geometry": {"coordinates":[96.901,31.901],"type":"Point"}
}