{
  "type": "Feature",
  "properties": {
    "gn:admin1_code":"16.0",
    "gn:asciiname":"Qingzi",
    "gn:country_code":"CN",
    "gn:dem":219,
    "gn:feature_class":"P",
    "gn:feature_code":"PPL",
    "gn:name":"Qingzi",
    "gn:population":0,
    "gn:timezone":"Asia/Shanghai",
    "iso:country":"CN",
    "name:zho_x_preferred":[
        "\u9752\u5b50"
    ],
    "wof:name":"Qingzi",
    "wof:placetype":"locality"
},
  "geometry": {"coordinates":[110.533,24.2453],"type":"Point"}
}