{
  "type": "Feature",
  "properties": {
    "gn:admin1_code":"5.0",
    "gn:asciiname":"Hetianshan",
    "gn:country_code":"CN",
    "gn:dem":497,
    "gn:feature_class":"P",
    "gn:feature_code":"PPL",
    "gn:name":"Hetianshan",
    "gn:population":0,
    "gn:timezone":"Asia/Shanghai",
    "iso:country":"CN",
    "name:und_x_variant":[
        "Ho-t\u2019ien-shan"
    ],
    "wof:name":"Hetianshan",
    "wof:placetype":"locality"
},
  "geometry": {"coordinates":[130.44108,42.68233],"type":"Point"}
}