{
  "type": "Feature",
  "properties": {
    "gn:admin1_code":"29.0",
    "gn:asciiname":"Bajiaoping",
    "gn:country_code":"CN",
    "gn:dem":2136,
    "gn:feature_class":"P",
    "gn:feature_code":"PPL",
    "gn:name":"Bajiaoping",
    "gn:population":0,
    "gn:timezone":"Asia/Shanghai",
    "iso:country":"CN",
    "name:zho_x_preferred":[
        "\u82ad\u8549\u576a"
    ],
    "wof:name":"Bajiaoping",
    "wof:placetype":"locality"
},
  "geometry": {"coordinates":[101.253,26.4474],"type":"Point"}
}