{
  "type": "Feature",
  "properties": {
    "gn:admin1_code":"2.0",
    "gn:asciiname":"Shijingtan",
    "gn:country_code":"CN",
    "gn:dem":2,
    "gn:feature_class":"P",
    "gn:feature_code":"PPL",
    "gn:name":"Shijingtan",
    "gn:population":0,
    "gn:timezone":"Asia/Shanghai",
    "iso:country":"CN",
    "name:zho_x_preferred":[
        "\u77f3\u4e95\u6f6d"
    ],
    "wof:name":"Shijingtan",
    "wof:placetype":"locality"
},
  "geometry": {"coordinates":[122.16024,30.1579],"type":"Point"}
}