{
  "type": "Feature",
  "properties": {
    "gn:admin1_code":"12.0",
    "gn:asciiname":"Xuejiabian",
    "gn:country_code":"CN",
    "gn:dem":230,
    "gn:feature_class":"P",
    "gn:feature_code":"PPL",
    "gn:name":"Xuejiabian",
    "gn:population":0,
    "gn:timezone":"Asia/Shanghai",
    "iso:country":"CN",
    "name:zho_x_preferred":[
        "\u859b\u5bb6\u8fb9"
    ],
    "wof:name":"Xuejiabian",
    "wof:placetype":"locality"
},
  "geometry": {"coordinates":[110.87318999999999,32.57668],"type":"Point"}
}