{
  "type": "Feature",
  "properties": {
    "gn:admin1_code":"10",
    "gn:asciiname":"Xiaoshimen",
    "gn:country_code":"CN",
    "gn:dem":292,
    "gn:feature_class":"P",
    "gn:feature_code":"PPL",
    "gn:name":"Xiaoshimen",
    "gn:population":0,
    "gn:timezone":"Asia/Shanghai",
    "iso:country":"CN",
    "name:zho_x_preferred":[
        "\u5c0f\u77f3\u95e8"
    ],
    "wof:name":"Xiaoshimen",
    "wof:placetype":"locality"
},
  "geometry": {"coordinates":[114.232,37.519],"type":"Point"}
}