{
  "type": "Feature",
  "properties": {
    "gn:admin1_code":"3.0",
    "gn:asciiname":"Dachayuan",
    "gn:country_code":"CN",
    "gn:dem":324,
    "gn:feature_class":"P",
    "gn:feature_code":"PPL",
    "gn:name":"Dachayuan",
    "gn:population":0,
    "gn:timezone":"Asia/Shanghai",
    "iso:country":"CN",
    "name:und_x_variant":[
        "\u5927\u8336\u56ed"
    ],
    "wof:name":"Dachayuan",
    "wof:placetype":"locality"
},
  "geometry": {"coordinates":[115.51282,25.54062],"type":"Point"}
}