{
  "type": "Feature",
  "properties": {
    "gn:admin1_code":"30.0",
    "gn:asciiname":"Ao'cun",
    "gn:country_code":"CN",
    "gn:dem":21,
    "gn:feature_class":"P",
    "gn:feature_code":"PPL",
    "gn:name":"Ao\u2019cun",
    "gn:population":0,
    "gn:timezone":"Asia/Shanghai",
    "iso:country":"CN",
    "name:und_x_variant":[
        "Ao\u2019cun"
    ],
    "name:zho_x_preferred":[
        "\u6fb3\u6751"
    ],
    "wof:name":"Ao'cun",
    "wof:placetype":"locality"
},
  "geometry": {"coordinates":[112.58423999999999,21.87827],"type":"Point"}
}