{
  "type": "Feature",
  "properties": {
    "gn:admin1_code":"26",
    "gn:asciiname":"Majiayuan",
    "gn:country_code":"CN",
    "gn:dem":1194,
    "gn:feature_class":"P",
    "gn:feature_code":"PPL",
    "gn:name":"Majiayuan",
    "gn:population":0,
    "gn:timezone":"Asia/Shanghai",
    "iso:country":"CN",
    "name:zho_x_preferred":[
        "\u9a6c\u5bb6\u586c"
    ],
    "wof:name":"Majiayuan",
    "wof:placetype":"locality"
},
  "geometry": {"coordinates":[108.03278,34.89083],"type":"Point"}
}