{
  "type": "Feature",
  "properties": {
    "gn:admin1_code":"29.0",
    "gn:asciiname":"Gaohe",
    "gn:country_code":"CN",
    "gn:dem":2080,
    "gn:feature_class":"P",
    "gn:feature_code":"PPL",
    "gn:name":"Gaohe",
    "gn:population":0,
    "gn:timezone":"Asia/Shanghai",
    "iso:country":"CN",
    "name:zho_x_preferred":[
        "\u9ad8\u6cb3"
    ],
    "wof:name":"Gaohe",
    "wof:placetype":"locality"
},
  "geometry": {"coordinates":[101.503,25.3967],"type":"Point"}
}