{
  "type": "Feature",
  "properties": {
    "gn:admin1_code":"3",
    "gn:asciiname":"Cheyuan",
    "gn:country_code":"CN",
    "gn:dem":119,
    "gn:feature_class":"P",
    "gn:feature_code":"PPL",
    "gn:name":"Cheyuan",
    "gn:population":0,
    "gn:timezone":"Asia/Shanghai",
    "iso:country":"CN",
    "name:zho_x_preferred":[
        "\u8f66\u6e90"
    ],
    "wof:name":"Cheyuan",
    "wof:placetype":"locality"
},
  "geometry": {"coordinates":[114.65000000000001,26.8275],"type":"Point"}
}