{
  "type": "Feature",
  "properties": {
    "gn:admin1_code":"22.0",
    "gn:asciiname":"Chengezhuangcun",
    "gn:country_code":"CN",
    "gn:dem":165,
    "gn:feature_class":"P",
    "gn:feature_code":"PPL",
    "gn:name":"Chengezhuangcun",
    "gn:population":0,
    "gn:timezone":"Asia/Shanghai",
    "iso:country":"CN",
    "name:zho_x_preferred":[
        "\u9648\u5404\u5e84\u6751"
    ],
    "wof:name":"Chengezhuangcun",
    "wof:placetype":"locality"
},
  "geometry": {"coordinates":[117.00633000000001,40.54312],"type":"Point"}
}