{
  "type": "Feature",
  "properties": {
    "gn:admin1_code":"15.0",
    "gn:asciiname":"Puwa",
    "gn:country_code":"CN",
    "gn:dem":2810,
    "gn:feature_class":"P",
    "gn:feature_code":"PPL",
    "gn:name":"Puwa",
    "gn:population":0,
    "gn:timezone":"Asia/Shanghai",
    "iso:country":"CN",
    "name:zho_x_preferred":[
        "\u666e\u54c7"
    ],
    "wof:name":"Puwa",
    "wof:placetype":"locality"
},
  "geometry": {"coordinates":[103.289,33.8871],"type":"Point"}
}