{
  "type": "Feature",
  "properties": {
    "gn:admin1_code":"31",
    "gn:asciiname":"Fengtang",
    "gn:country_code":"CN",
    "gn:dem":6,
    "gn:feature_class":"P",
    "gn:feature_code":"PPL",
    "gn:name":"Fengtang",
    "gn:population":0,
    "gn:timezone":"Asia/Shanghai",
    "iso:country":"CN",
    "name:und_x_variant":[
        "Hsin-feng-t\u2019ang",
        "Fengtang",
        "\u4e30\u5858"
    ],
    "wof:name":"Fengtang",
    "wof:placetype":"locality"
},
  "geometry": {"coordinates":[108.709,18.5397],"type":"Point"}
}