{
  "type": "Feature",
  "properties": {
    "gn:admin1_code":"19.0",
    "gn:asciiname":"Yangjiatun",
    "gn:country_code":"CN",
    "gn:dem":12,
    "gn:feature_class":"P",
    "gn:feature_code":"PPL",
    "gn:name":"Yangjiatun",
    "gn:population":0,
    "gn:timezone":"Asia/Shanghai",
    "iso:country":"CN",
    "name:und_x_variant":[
        "\u6768\u5bb6\u5c6f"
    ],
    "name:zho_x_preferred":[
        "\u6768\u5bb6\u5c6f"
    ],
    "wof:name":"Yangjiatun",
    "wof:placetype":"locality"
},
  "geometry": {"coordinates":[123.56328999999999,40.00623],"type":"Point"}
}