{
  "type": "Feature",
  "properties": {
    "gn:admin1_code":"13",
    "gn:asciiname":"Fengshou'erchang Sanlian",
    "gn:country_code":"CN",
    "gn:dem":1037,
    "gn:feature_class":"P",
    "gn:feature_code":"PPL",
    "gn:name":"Fengshou\u2019erchang Sanlian",
    "gn:population":0,
    "gn:timezone":"Asia/Shanghai",
    "iso:country":"CN",
    "name:und_x_variant":[
        "Fengshou\u2019erchang Sanlian"
    ],
    "name:zho_x_preferred":[
        "\u4e30\u6536\u4e8c\u573a\u4e09\u8fde"
    ],
    "wof:name":"Fengshou'erchang Sanlian",
    "wof:placetype":"locality"
},
  "geometry": {"coordinates":[80.37779,40.45272],"type":"Point"}
}