{
  "type": "Feature",
  "properties": {
    "gn:admin1_code":"26.0",
    "gn:asciiname":"Nanshuncun",
    "gn:country_code":"CN",
    "gn:dem":577,
    "gn:feature_class":"P",
    "gn:feature_code":"PPL",
    "gn:name":"Nanshuncun",
    "gn:population":0,
    "gn:timezone":"Asia/Shanghai",
    "iso:country":"CN",
    "name:zho_x_preferred":[
        "\u5357\u987a\u6751"
    ],
    "wof:name":"Nanshuncun",
    "wof:placetype":"locality"
},
  "geometry": {"coordinates":[110.28802,35.12057],"type":"Point"}
}