{
  "type": "Feature",
  "properties": {
    "gn:admin1_code":"14.0",
    "gn:asciiname":"Wutongcun",
    "gn:country_code":"CN",
    "gn:dem":3495,
    "gn:feature_class":"P",
    "gn:feature_code":"PPL",
    "gn:name":"Wutongcun",
    "gn:population":0,
    "gn:timezone":"Asia/Urumqi",
    "iso:country":"CN",
    "name:zho_x_preferred":[
        "\u543e\u901a\u6751"
    ],
    "wof:name":"Wutongcun",
    "wof:placetype":"locality"
},
  "geometry": {"coordinates":[98.10372,29.20492],"type":"Point"}
}