{
  "type": "Feature",
  "properties": {
    "gn:gn_country":"CN",
    "gn:gn_fcode":"ADM3",
    "gn:gn_pop":0,
    "iso:country":"CN",
    "name:unk_x_variant":[
        "Kao-chou Hsien"
    ],
    "name:zho_x_preferred":[
        "\u9ad8\u5dde\u5e02"
    ],
    "name:zho_x_variant":[
        "\u9ad8\u5dde"
    ],
    "qs_pg:aaroncc":"CN",
    "qs_pg:gn_country":"CN",
    "qs_pg:gn_fcode":"ADM3",
    "qs_pg:gn_pop":0,
    "qs_pg:name":"Gaozhou Shi",
    "qs_pg:photos_9r":0,
    "qs_pg:photos_sr":0,
    "qs_pg:pop_sr":0,
    "qs_pg:qs_pg_placetype":"localadmin",
    "wof:name":"Gaozhou Shi",
    "wof:placetype":"localadmin"
},
  "geometry": {"coordinates":[110.93826,22.05425],"type":"Point"}
}