{
  "type": "Feature",
  "properties": {
    "gn:admin1_code":"32.0",
    "gn:asciiname":"Zhoujia Citang",
    "gn:country_code":"CN",
    "gn:dem":305,
    "gn:feature_class":"P",
    "gn:feature_code":"PPL",
    "gn:name":"Zhoujia Citang",
    "gn:population":0,
    "gn:timezone":"Asia/Shanghai",
    "iso:country":"CN",
    "name:zho_x_preferred":[
        "\u5468\u5bb6\u7960\u5802"
    ],
    "wof:name":"Zhoujia Citang",
    "wof:placetype":"locality"
},
  "geometry": {"coordinates":[105.04564000000001,29.54057],"type":"Point"}
}