{
  "type": "Feature",
  "properties": {
    "gn:admin1_code":"9.0",
    "gn:asciiname":"Dawangcungou",
    "gn:country_code":"CN",
    "gn:dem":180,
    "gn:feature_class":"P",
    "gn:feature_code":"PPL",
    "gn:name":"Dawangcungou",
    "gn:population":0,
    "gn:timezone":"Asia/Shanghai",
    "iso:country":"CN",
    "name:zho_x_preferred":[
        "\u5927\u738b\u6751\u6c9f"
    ],
    "wof:name":"Dawangcungou",
    "wof:placetype":"locality"
},
  "geometry": {"coordinates":[113.30982,34.77907],"type":"Point"}
}