{
  "type": "Feature",
  "properties": {
    "gn:admin1_code":"18",
    "gn:asciiname":"Longzizhai",
    "gn:country_code":"CN",
    "gn:dem":1831,
    "gn:feature_class":"P",
    "gn:feature_code":"PPL",
    "gn:name":"Longzizhai",
    "gn:population":0,
    "gn:timezone":"Asia/Shanghai",
    "iso:country":"CN",
    "name:zho_x_preferred":[
        "\u804b\u5b50\u5be8"
    ],
    "wof:name":"Longzizhai",
    "wof:placetype":"locality"
},
  "geometry": {"coordinates":[104.39,27.2068],"type":"Point"}
}