{
  "type": "Feature",
  "properties": {
    "gn:admin1_code":"18",
    "gn:asciiname":"Xiaoxiyuan",
    "gn:country_code":"CN",
    "gn:dem":967,
    "gn:feature_class":"P",
    "gn:feature_code":"PPL",
    "gn:name":"Xiaoxiyuan",
    "gn:population":0,
    "gn:timezone":"Asia/Shanghai",
    "iso:country":"CN",
    "name:zho_x_preferred":[
        "\u5c0f\u6eaa\u56ed"
    ],
    "wof:name":"Xiaoxiyuan",
    "wof:placetype":"locality"
},
  "geometry": {"coordinates":[106.547,27.54300000000001],"type":"Point"}
}