{
  "type": "Feature",
  "properties": {
    "gn:admin1_code":"12.0",
    "gn:asciiname":"Liangshuijing",
    "gn:country_code":"CN",
    "gn:dem":110,
    "gn:feature_class":"P",
    "gn:feature_code":"PPL",
    "gn:name":"Liangshuijing",
    "gn:population":0,
    "gn:timezone":"Asia/Shanghai",
    "iso:country":"CN",
    "name:zho_x_preferred":[
        "Liangshuijing"
    ],
    "name:zho_x_variant":[
        "\u51c9\u6c34\u4e95"
    ],
    "wof:name":"Liangshuijing",
    "wof:placetype":"locality"
},
  "geometry": {"coordinates":[111.60431,30.25561],"type":"Point"}
}