{
  "type": "Feature",
  "properties": {
    "gn:admin1_code":"11",
    "gn:asciiname":"Waquankou",
    "gn:country_code":"CN",
    "gn:dem":79,
    "gn:feature_class":"P",
    "gn:feature_code":"PPL",
    "gn:name":"Waquankou",
    "gn:population":0,
    "gn:timezone":"Asia/Shanghai",
    "iso:country":"CN",
    "name:zho_x_preferred":[
        "\u6316\u6cc9\u53e3"
    ],
    "wof:name":"Waquankou",
    "wof:placetype":"locality"
},
  "geometry": {"coordinates":[112.36036,27.7588],"type":"Point"}
}