{
  "type": "Feature",
  "properties": {
    "gn:admin1_code":"2.0",
    "gn:asciiname":"Shuiheqiao",
    "gn:country_code":"CN",
    "gn:dem":9,
    "gn:feature_class":"P",
    "gn:feature_code":"PPL",
    "gn:name":"Shuiheqiao",
    "gn:population":0,
    "gn:timezone":"Asia/Shanghai",
    "iso:country":"CN",
    "name:und_x_variant":[
        "\u6c34\u6cb3\u6865"
    ],
    "wof:name":"Shuiheqiao",
    "wof:placetype":"locality"
},
  "geometry": {"coordinates":[119.95950999999999,30.3704],"type":"Point"}
}