{
  "type": "Feature",
  "properties": {
    "gn:country":"CN",
    "gn:fcode":"PPL",
    "gn:population":140909,
    "iso:country":"CN",
    "name:rus_x_preferred":[
        "\u0413\u0443\u043d\u0447\u0436\u0443\u043b\u0438\u043d\u0430"
    ],
    "name:und_x_variant":[
        "Huai-to-hsien"
    ],
    "qs:name":"\u516c\u4e3b\u5cad",
    "qs:name_adm0":"\u4e2d\u570b",
    "qs:name_adm1":"\u5409\u6797\u7701",
    "qs:photos_9k":1,
    "qs:photos_9r":1,
    "qs:photos_all":1,
    "qs:photos_sr":0,
    "qs:placetype":"Town",
    "qs:pop_sr":"9",
    "wof:name":"\u516c\u4e3b\u5cad",
    "wof:placetype":"locality",
    "wof:population":140909
},
  "geometry": {"coordinates":[124.81979,43.50075],"type":"Point"}
}