{
  "type": "Feature",
  "properties": {
    "gn:admin1_code":"19.0",
    "gn:asciiname":"Ningzigou",
    "gn:country_code":"CN",
    "gn:dem":170,
    "gn:feature_class":"P",
    "gn:feature_code":"PPL",
    "gn:name":"Ningzigou",
    "gn:population":0,
    "gn:timezone":"Asia/Shanghai",
    "iso:country":"CN",
    "name:zho_x_preferred":[
        "\u5b81\u5b50\u6c9f"
    ],
    "wof:name":"Ningzigou",
    "wof:placetype":"locality"
},
  "geometry": {"coordinates":[119.892,40.2054],"type":"Point"}
}