{
  "type": "Feature",
  "properties": {
    "gn:admin1_code":"13.0",
    "gn:asciiname":"Xianmilie",
    "gn:country_code":"CN",
    "gn:dem":1571,
    "gn:feature_class":"P",
    "gn:feature_code":"PPL",
    "gn:name":"Xianmilie",
    "gn:population":0,
    "gn:timezone":"Asia/Shanghai",
    "iso:country":"CN",
    "name:und_x_variant":[
        "\u5148\u7c73\u6765"
    ],
    "wof:name":"Xianmilie",
    "wof:placetype":"locality"
},
  "geometry": {"coordinates":[75.94355999999998,38.88362],"type":"Point"}
}