{
  "type": "Feature",
  "properties": {
    "gn:admin1_code":"25",
    "gn:asciiname":"Balizhuang Dongcun",
    "gn:country_code":"CN",
    "gn:dem":9,
    "gn:feature_class":"P",
    "gn:feature_code":"PPL",
    "gn:name":"Balizhuang Dongcun",
    "gn:population":0,
    "gn:timezone":"Asia/Shanghai",
    "iso:country":"CN",
    "name:zho_x_preferred":[
        "\u516b\u91cc\u5e84\u4e1c\u6751"
    ],
    "wof:name":"Balizhuang Dongcun",
    "wof:placetype":"locality"
},
  "geometry": {"coordinates":[118.42601000000001,37.69883],"type":"Point"}
}