{
  "type": "Feature",
  "properties": {
    "gn:admin1_code":"29.0",
    "gn:asciiname":"Xiaoyangchang",
    "gn:country_code":"CN",
    "gn:dem":1893,
    "gn:feature_class":"P",
    "gn:feature_code":"PPLF",
    "gn:name":"Xiaoyangchang",
    "gn:population":0,
    "gn:timezone":"Asia/Shanghai",
    "iso:country":"CN",
    "name:zho_x_preferred":[
        "\u5c0f\u7f8a\u573a"
    ],
    "wof:name":"Xiaoyangchang",
    "wof:placetype":"locality"
},
  "geometry": {"coordinates":[104.565,25.3207],"type":"Point"}
}