{
  "type": "Feature",
  "properties": {
    "gn:admin1_code":"16.0",
    "gn:asciiname":"Nongqiancun",
    "gn:country_code":"CN",
    "gn:dem":610,
    "gn:feature_class":"P",
    "gn:feature_code":"PPL",
    "gn:name":"Nongqiancun",
    "gn:population":0,
    "gn:timezone":"Asia/Shanghai",
    "iso:country":"CN",
    "name:zho_x_preferred":[
        "\u5f04\u5343\u6751"
    ],
    "wof:name":"Nongqiancun",
    "wof:placetype":"locality"
},
  "geometry": {"coordinates":[108.303,24.0789],"type":"Point"}
}