{
  "type": "Feature",
  "properties": {
    "gn:admin1_code":"16.0",
    "gn:asciiname":"Pinduan",
    "gn:country_code":"CN",
    "gn:dem":490,
    "gn:feature_class":"P",
    "gn:feature_code":"PPL",
    "gn:name":"Pinduan",
    "gn:population":0,
    "gn:timezone":"Asia/Shanghai",
    "iso:country":"CN",
    "name:zho_x_preferred":[
        "\u54c1\u7aef"
    ],
    "wof:name":"Pinduan",
    "wof:placetype":"locality"
},
  "geometry": {"coordinates":[105.974,23.4659],"type":"Point"}
}