{
  "type": "Feature",
  "properties": {
    "gn:admin1_code":"3.0",
    "gn:asciiname":"Zaoshuxia",
    "gn:country_code":"CN",
    "gn:dem":278,
    "gn:feature_class":"P",
    "gn:feature_code":"PPL",
    "gn:name":"Zaoshuxia",
    "gn:population":0,
    "gn:timezone":"Asia/Shanghai",
    "iso:country":"CN",
    "name:und_x_variant":[
        "\u67a3\u6811\u4e0b"
    ],
    "wof:name":"Zaoshuxia",
    "wof:placetype":"locality"
},
  "geometry": {"coordinates":[116.21916,27.23577],"type":"Point"}
}