{
  "type": "Feature",
  "properties": {
    "gn:admin1_code":"10",
    "gn:asciiname":"Baitaizi",
    "gn:country_code":"CN",
    "gn:dem":487,
    "gn:feature_class":"P",
    "gn:feature_code":"PPL",
    "gn:name":"Baitaizi",
    "gn:population":0,
    "gn:timezone":"Asia/Shanghai",
    "iso:country":"CN",
    "name:zho_x_preferred":[
        "\u767d\u53f0\u5b50"
    ],
    "wof:name":"Baitaizi",
    "wof:placetype":"locality"
},
  "geometry": {"coordinates":[119.38046,40.20437],"type":"Point"}
}