{
  "type": "Feature",
  "properties": {
    "gn:admin1_code":"23.0",
    "gn:asciiname":"Dayu Jiazhai",
    "gn:country_code":"CN",
    "gn:dem":4,
    "gn:feature_class":"P",
    "gn:feature_code":"PPL",
    "gn:name":"Dayu Jiazhai",
    "gn:population":0,
    "gn:timezone":"Asia/Shanghai",
    "iso:country":"CN",
    "name:zho_x_preferred":[
        "Dayu Jiazhai"
    ],
    "name:zho_x_variant":[
        "\u5927\u90c1\u5bb6\u5b85"
    ],
    "wof:name":"Dayu Jiazhai",
    "wof:placetype":"locality"
},
  "geometry": {"coordinates":[121.54595999999999,31.04704000000001],"type":"Point"}
}