{
  "type": "Feature",
  "properties": {
    "gn:admin1_code":"15.0",
    "gn:asciiname":"Shaozipo",
    "gn:country_code":"CN",
    "gn:dem":1677,
    "gn:feature_class":"P",
    "gn:feature_code":"PPL",
    "gn:name":"Shaozipo",
    "gn:population":0,
    "gn:timezone":"Asia/Shanghai",
    "iso:country":"CN",
    "name:zho_x_preferred":[
        "\u7a0d\u5b50\u5761"
    ],
    "wof:name":"Shaozipo",
    "wof:placetype":"locality"
},
  "geometry": {"coordinates":[105.785,34.3574],"type":"Point"}
}