{
  "type": "Feature",
  "properties": {
    "gn:admin1_code":"29.0",
    "gn:asciiname":"Zuomeiguo",
    "gn:country_code":"CN",
    "gn:dem":2189,
    "gn:feature_class":"P",
    "gn:feature_code":"PPL",
    "gn:name":"Zuomeiguo",
    "gn:population":0,
    "gn:timezone":"Asia/Shanghai",
    "iso:country":"CN",
    "name:zho_x_preferred":[
        "\u5de6\u7f8e\u679c"
    ],
    "wof:name":"Zuomeiguo",
    "wof:placetype":"locality"
},
  "geometry": {"coordinates":[103.514,23.626],"type":"Point"}
}