{
  "type": "Feature",
  "properties": {
    "gn:admin1_code":"19.0",
    "gn:asciiname":"Xindihao",
    "gn:country_code":"CN",
    "gn:dem":11,
    "gn:feature_class":"P",
    "gn:feature_code":"PPL",
    "gn:name":"Xindihao",
    "gn:population":0,
    "gn:timezone":"Asia/Shanghai",
    "iso:country":"CN",
    "name:und_x_variant":[
        "\u65b0\u5730\u53f7"
    ],
    "name:zho_x_preferred":[
        "\u65b0\u5730\u53f7"
    ],
    "wof:name":"Xindihao",
    "wof:placetype":"locality"
},
  "geometry": {"coordinates":[120.71007,40.60215],"type":"Point"}
}