{
  "type": "Feature",
  "properties": {
    "gn:admin1_code":"8.0",
    "gn:asciiname":"Taishancun",
    "gn:country_code":"CN",
    "gn:dem":249,
    "gn:feature_class":"P",
    "gn:feature_code":"PPL",
    "gn:name":"Taishancun",
    "gn:population":0,
    "gn:timezone":"Asia/Shanghai",
    "iso:country":"CN",
    "name:zho_x_preferred":[
        "\u592a\u5c71\u6751"
    ],
    "wof:name":"Taishancun",
    "wof:placetype":"locality"
},
  "geometry": {"coordinates":[126.36355,47.87838],"type":"Point"}
}