{
  "type": "Feature",
  "properties": {
    "gn:admin1_code":"1.0",
    "gn:asciiname":"Shangyuancun",
    "gn:country_code":"CN",
    "gn:dem":37,
    "gn:feature_class":"P",
    "gn:feature_code":"PPL",
    "gn:name":"Shangyuancun",
    "gn:population":0,
    "gn:timezone":"Asia/Shanghai",
    "iso:country":"CN",
    "name:zho_x_preferred":[
        "\u4e0a\u8881\u6751"
    ],
    "wof:name":"Shangyuancun",
    "wof:placetype":"locality"
},
  "geometry": {"coordinates":[118.17583999999999,32.01391],"type":"Point"}
}