{
  "type": "Feature",
  "properties": {
    "gn:admin1_code":"14.0",
    "gn:asciiname":"Tongmen",
    "gn:country_code":"CN",
    "gn:dem":4229,
    "gn:feature_class":"P",
    "gn:feature_code":"PPL",
    "gn:name":"Tongmen",
    "gn:population":0,
    "gn:timezone":"Asia/Urumqi",
    "iso:country":"CN",
    "name:zho_x_preferred":[
        "\u901a\u95e8"
    ],
    "wof:name":"Tongmen",
    "wof:placetype":"locality"
},
  "geometry": {"coordinates":[87.87090000000001,28.5963],"type":"Point"}
}