{
  "type": "Feature",
  "properties": {
    "gn:admin1_code":"11.0",
    "gn:asciiname":"Liubaimu",
    "gn:country_code":"CN",
    "gn:dem":30,
    "gn:feature_class":"P",
    "gn:feature_code":"PPL",
    "gn:name":"Liubaimu",
    "gn:population":0,
    "gn:timezone":"Asia/Shanghai",
    "iso:country":"CN",
    "name:zho_x_preferred":[
        "\u516d\u767e\u4ea9"
    ],
    "wof:name":"Liubaimu",
    "wof:placetype":"locality"
},
  "geometry": {"coordinates":[112.55717,29.24134],"type":"Point"}
}