{
  "type": "Feature",
  "properties": {
    "gn:admin1_code":"11.0",
    "gn:asciiname":"Chushantang",
    "gn:country_code":"CN",
    "gn:dem":151,
    "gn:feature_class":"P",
    "gn:feature_code":"PPL",
    "gn:name":"Chushantang",
    "gn:population":0,
    "gn:timezone":"Asia/Shanghai",
    "iso:country":"CN",
    "name:zho_x_preferred":[
        "\u695a\u5584\u5802"
    ],
    "wof:name":"Chushantang",
    "wof:placetype":"locality"
},
  "geometry": {"coordinates":[112.01833000000001,27.30799],"type":"Point"}
}