{
  "type": "Feature",
  "properties": {
    "gn:admin1_code":"29.0",
    "gn:asciiname":"Wolonggang",
    "gn:country_code":"CN",
    "gn:dem":1746,
    "gn:feature_class":"P",
    "gn:feature_code":"PPL",
    "gn:name":"Wolonggang",
    "gn:population":0,
    "gn:timezone":"Asia/Shanghai",
    "iso:country":"CN",
    "name:zho_x_preferred":[
        "\u5367\u9f99\u5c97"
    ],
    "wof:name":"Wolonggang",
    "wof:placetype":"locality"
},
  "geometry": {"coordinates":[103.803,23.5128],"type":"Point"}
}