{
  "type": "Feature",
  "properties": {
    "gn:admin1_code":"26.0",
    "gn:asciiname":"Yangqukou",
    "gn:country_code":"CN",
    "gn:dem":1739,
    "gn:feature_class":"P",
    "gn:feature_code":"PPL",
    "gn:name":"Yangqukou",
    "gn:population":0,
    "gn:timezone":"Asia/Shanghai",
    "iso:country":"CN",
    "name:zho_x_preferred":[
        "\u7f8a\u6e20\u53e3"
    ],
    "wof:name":"Yangqukou",
    "wof:placetype":"locality"
},
  "geometry": {"coordinates":[107.55907000000001,37.02402],"type":"Point"}
}