{
  "type": "Feature",
  "properties": {
    "gn:admin1_code":"16.0",
    "gn:asciiname":"Xiasiliu",
    "gn:country_code":"CN",
    "gn:dem":152,
    "gn:feature_class":"P",
    "gn:feature_code":"PPL",
    "gn:name":"Xiasiliu",
    "gn:population":0,
    "gn:timezone":"Asia/Shanghai",
    "iso:country":"CN",
    "name:zho_x_preferred":[
        "\u4e0b\u6cd7\u67f3"
    ],
    "wof:name":"Xiasiliu",
    "wof:placetype":"locality"
},
  "geometry": {"coordinates":[109.29600000000001,25.0448],"type":"Point"}
}