{
  "type": "Feature",
  "properties": {
    "gn:admin1_code":"24.0",
    "gn:asciiname":"Dianliang",
    "gn:country_code":"CN",
    "gn:dem":1493,
    "gn:feature_class":"P",
    "gn:feature_code":"PPL",
    "gn:name":"Dianliang",
    "gn:population":0,
    "gn:timezone":"Asia/Shanghai",
    "iso:country":"CN",
    "name:und_x_variant":[
        "\u5e97\u6881"
    ],
    "name:zho_x_preferred":[
        "\u5e97\u6881"
    ],
    "wof:name":"Dianliang",
    "wof:placetype":"locality"
},
  "geometry": {"coordinates":[112.26982,39.58864000000001],"type":"Point"}
}