{
  "type": "Feature",
  "properties": {
    "gn:admin1_code":"19.0",
    "gn:asciiname":"Dasankuaishi",
    "gn:country_code":"CN",
    "gn:dem":59,
    "gn:feature_class":"P",
    "gn:feature_code":"PPL",
    "gn:name":"Dasankuaishi",
    "gn:population":0,
    "gn:timezone":"Asia/Shanghai",
    "iso:country":"CN",
    "name:zho_x_preferred":[
        "\u5927\u4e09\u5757\u77f3"
    ],
    "wof:name":"Dasankuaishi",
    "wof:placetype":"locality"
},
  "geometry": {"coordinates":[121.70935,41.52114],"type":"Point"}
}