{
  "type": "Feature",
  "properties": {
    "gn:admin1_code":"11.0",
    "gn:asciiname":"Jinlouchong",
    "gn:country_code":"CN",
    "gn:dem":272,
    "gn:feature_class":"P",
    "gn:feature_code":"PPL",
    "gn:name":"Jinlouchong",
    "gn:population":0,
    "gn:timezone":"Asia/Shanghai",
    "iso:country":"CN",
    "name:zho_x_preferred":[
        "\u91d1\u697c\u51b2"
    ],
    "wof:name":"Jinlouchong",
    "wof:placetype":"locality"
},
  "geometry": {"coordinates":[112.31635,27.3284],"type":"Point"}
}