{
  "type": "Feature",
  "properties": {
    "gn:admin1_code":"02",
    "gn:asciiname":"Tongpu",
    "gn:country_code":"CN",
    "gn:dem":19,
    "gn:feature_class":"P",
    "gn:feature_code":"PPL",
    "gn:name":"Tongpu",
    "gn:population":0,
    "gn:timezone":"Asia/Shanghai",
    "iso:country":"CN",
    "name:und_x_variant":[
        "Tongxi",
        "Tongpu"
    ],
    "name:zho_x_preferred":[
        "T\u2019ung-p\u2019u-ts\u2019un"
    ],
    "name:zho_x_variant":[
        "\u6850\u6d66"
    ],
    "wof:name":"Tongpu",
    "wof:placetype":"locality"
},
  "geometry": {"coordinates":[120.56263,27.85359],"type":"Point"}
}