{
  "type": "Feature",
  "properties": {
    "gn:admin1_code":"4.0",
    "gn:asciiname":"Beixinglou",
    "gn:country_code":"CN",
    "gn:dem":32,
    "gn:feature_class":"P",
    "gn:feature_code":"PPL",
    "gn:name":"Beixinglou",
    "gn:population":0,
    "gn:timezone":"Asia/Shanghai",
    "iso:country":"CN",
    "name:zho_x_preferred":[
        "\u5317\u90a2\u697c"
    ],
    "wof:name":"Beixinglou",
    "wof:placetype":"locality"
},
  "geometry": {"coordinates":[117.88500000000001,34.6258],"type":"Point"}
}