{
  "type": "Feature",
  "properties": {
    "gn:admin1_code":"30.0",
    "gn:asciiname":"Sansha",
    "gn:country_code":"CN",
    "gn:dem":-3,
    "gn:feature_class":"P",
    "gn:feature_code":"PPL",
    "gn:name":"Sansha",
    "gn:population":0,
    "gn:timezone":"Asia/Shanghai",
    "iso:country":"CN",
    "name:ara_x_preferred":[
        "\u0633\u0627\u0646\u0634\u0627"
    ],
    "name:cat_x_preferred":[
        "Sansha"
    ],
    "name:cdo_x_preferred":[
        "S\u0103ng-s\u0103"
    ],
    "name:deu_x_preferred":[
        "Sansha"
    ],
    "name:fas_x_preferred":[
        "\u0633\u0627\u0646\u0634\u0627"
    ],
    "name:fin_x_preferred":[
        "Sansha"
    ],
    "name:fra_x_preferred":[
        "Sansha"
    ],
    "name:hak_x_preferred":[
        "S\u00e2m-s\u00e2-s\u1e73"
    ],
    "name:ita_x_preferred":[
        "Sansha"
    ],
    "name:jpn_x_preferred":[
        "\u4e09\u6c99\u5e02"
    ],
    "name:kik_x_preferred":[
        "Sansha"
    ],
    "name:kor_x_preferred":[
        "\uc2fc\uc0ac\uc2dc"
    ],
    "name:msa_x_preferred":[
        "Sansha"
    ],
    "name:nor_x_preferred":[
        "Sansha"
    ],
    "name:pam_x_preferred":[
        "Sansha"
    ],
    "name:pol_x_preferred":[
        "Sansha"
    ],
    "name:por_x_preferred":[
        "Sansha"
    ],
    "name:rus_x_preferred":[
        "\u0421\u0430\u043d\u044c\u0448\u0430"
    ],
    "name:swe_x_preferred":[
        "Sansha"
    ],
    "name:tgl_x_preferred":[
        "Sansha"
    ],
    "name:tha_x_preferred":[
        "\u0e0b\u0e31\u0e19\u0e0a\u0e32"
    ],
    "name:tur_x_preferred":[
        "Sansha"
    ],
    "name:urd_x_preferred":[
        "\u0633\u0627\u0646\u0634\u0627"
    ],
    "name:vie_x_preferred":[
        "Tam Sa"
    ],
    "name:wuu_x_preferred":[
        "\u4e09\u6c99\u5e02"
    ],
    "name:zho_x_preferred":[
        "\u4e09\u6c99"
    ],
    "name:zho_x_variant":[
        "\u4e09\u6c99\u5e02"
    ],
    "wof:name":"Sansha",
    "wof:placetype":"locality"
},
  "geometry": {"coordinates":[112.54170999999999,21.81965],"type":"Point"}
}