{
  "type": "Feature",
  "properties": {
    "gn:admin1_code":"12.0",
    "gn:asciiname":"Xujiachong",
    "gn:country_code":"CN",
    "gn:dem":279,
    "gn:feature_class":"P",
    "gn:feature_code":"PPL",
    "gn:name":"Xujiachong",
    "gn:population":0,
    "gn:timezone":"Asia/Shanghai",
    "iso:country":"CN",
    "name:zho_x_preferred":[
        "Xujiachong"
    ],
    "name:zho_x_variant":[
        "\u5f90\u5bb6\u51b2"
    ],
    "wof:name":"Xujiachong",
    "wof:placetype":"locality"
},
  "geometry": {"coordinates":[115.4543,30.9585],"type":"Point"}
}