{
  "type": "Feature",
  "properties": {
    "gn:admin1_code":"5.0",
    "gn:asciiname":"Zhixincun",
    "gn:country_code":"CN",
    "gn:dem":260,
    "gn:feature_class":"P",
    "gn:feature_code":"PPL",
    "gn:name":"Zhixincun",
    "gn:population":0,
    "gn:timezone":"Asia/Shanghai",
    "iso:country":"CN",
    "name:zho_x_preferred":[
        "\u6cbb\u65b0\u6751"
    ],
    "wof:name":"Zhixincun",
    "wof:placetype":"locality"
},
  "geometry": {"coordinates":[126.28187,43.80632],"type":"Point"}
}