{
  "type": "Feature",
  "properties": {
    "gn:admin1_code":"8.0",
    "gn:asciiname":"Beixinmin",
    "gn:country_code":"CN",
    "gn:dem":78,
    "gn:feature_class":"P",
    "gn:feature_code":"PPL",
    "gn:name":"Beixinmin",
    "gn:population":0,
    "gn:timezone":"Asia/Shanghai",
    "iso:country":"CN",
    "name:zho_x_preferred":[
        "\u5317\u65b0\u6c11"
    ],
    "wof:name":"Beixinmin",
    "wof:placetype":"locality"
},
  "geometry": {"coordinates":[130.36738,46.94195],"type":"Point"}
}