{
  "type": "Feature",
  "properties": {
    "gn:admin1_code":"7",
    "gn:asciiname":"Gaozhou",
    "gn:country_code":"CN",
    "gn:dem":457,
    "gn:feature_class":"P",
    "gn:feature_code":"PPL",
    "gn:name":"Gaozhou",
    "gn:population":0,
    "gn:timezone":"Asia/Shanghai",
    "iso:country":"CN",
    "name:ara_x_preferred":[
        "\u063a\u0627\u0648\u0632\u0648"
    ],
    "name:ceb_x_preferred":[
        "Gaozhou"
    ],
    "name:deu_x_preferred":[
        "Gaozhou"
    ],
    "name:fas_x_preferred":[
        "\u06af\u0627\u0648\u0698\u0648"
    ],
    "name:fra_x_preferred":[
        "Gaozhou"
    ],
    "name:hak_x_preferred":[
        "K\u00f4-ch\u00fb-s\u1e73"
    ],
    "name:ita_x_preferred":[
        "Gaozhou"
    ],
    "name:jpn_x_preferred":[
        "\u9ad8\u5dde\u5e02"
    ],
    "name:kik_x_preferred":[
        "Gaozhou"
    ],
    "name:kor_x_preferred":[
        "\uac00\uc624\uc800\uc6b0\uc2dc"
    ],
    "name:mlg_x_preferred":[
        "Gaozhou"
    ],
    "name:mwl_x_preferred":[
        "Gaozhou"
    ],
    "name:nld_x_preferred":[
        "Gaozhou"
    ],
    "name:nor_x_preferred":[
        "Gaozhou"
    ],
    "name:pam_x_preferred":[
        "Gaozhou"
    ],
    "name:pnb_x_preferred":[
        "\u06af\u0627\u0624\u0698\u0648\u0624"
    ],
    "name:swe_x_preferred":[
        "Gaozhou"
    ],
    "name:urd_x_preferred":[
        "\u06af\u0627\u0648\u0698\u0648\u0648"
    ],
    "name:vie_x_preferred":[
        "Cao Ch\u00e2u"
    ],
    "name:zho_x_preferred":[
        "\u9ad8\u5dde\u5e02"
    ],
    "wof:name":"Gaozhou",
    "wof:placetype":"locality"
},
  "geometry": {"coordinates":[117.78111,25.63111],"type":"Point"}
}