{
  "type": "Feature",
  "properties": {
    "gn:admin1_code":"4.0",
    "gn:asciiname":"Guohucun",
    "gn:country_code":"CN",
    "gn:dem":20,
    "gn:feature_class":"P",
    "gn:feature_code":"PPL",
    "gn:name":"Guohucun",
    "gn:population":0,
    "gn:timezone":"Asia/Shanghai",
    "iso:country":"CN",
    "name:zho_x_preferred":[
        "\u90ed\u6e56\u6751"
    ],
    "wof:name":"Guohucun",
    "wof:placetype":"locality"
},
  "geometry": {"coordinates":[118.55432,34.09009],"type":"Point"}
}