{
  "type": "Feature",
  "properties": {
    "gn:admin1_code":"26.0",
    "gn:asciiname":"Wucangbu",
    "gn:cc2":"CN",
    "gn:country_code":"CN",
    "gn:dem":1431,
    "gn:feature_class":"P",
    "gn:feature_code":"PPL",
    "gn:name":"Wucangbu",
    "gn:population":0,
    "gn:timezone":"Asia/Shanghai",
    "iso:country":"CN",
    "name:und_x_variant":[
        "Wu-ts\u2019ang-pu",
        "Wucangbu"
    ],
    "wof:name":"Wucangbu",
    "wof:placetype":"locality"
},
  "geometry": {"coordinates":[108.1425,37.0575],"type":"Point"}
}