{
  "type": "Feature",
  "properties": {
    "gn:admin1_code":"4.0",
    "gn:asciiname":"Tongdun",
    "gn:country_code":"CN",
    "gn:dem":32,
    "gn:feature_class":"P",
    "gn:feature_code":"PPL",
    "gn:name":"Tongdun",
    "gn:population":0,
    "gn:timezone":"Asia/Shanghai",
    "iso:country":"CN",
    "name:zho_x_preferred":[
        "\u7ae5\u6566"
    ],
    "wof:name":"Tongdun",
    "wof:placetype":"locality"
},
  "geometry": {"coordinates":[118.75744,32.47906],"type":"Point"}
}