{
  "type": "Feature",
  "properties": {
    "gn:admin1_code":"18.0",
    "gn:asciiname":"Fuzhongcun",
    "gn:country_code":"CN",
    "gn:dem":476,
    "gn:feature_class":"P",
    "gn:feature_code":"PPL",
    "gn:name":"Fuzhongcun",
    "gn:population":0,
    "gn:timezone":"Asia/Shanghai",
    "iso:country":"CN",
    "name:zho_x_preferred":[
        "\u4ed8\u4e2d\u6751"
    ],
    "wof:name":"Fuzhongcun",
    "wof:placetype":"locality"
},
  "geometry": {"coordinates":[108.89700000000001,25.8384],"type":"Point"}
}