{
  "type": "Feature",
  "properties": {
    "gn:admin1_code":"14.0",
    "gn:asciiname":"Zhaxigujian",
    "gn:country_code":"CN",
    "gn:dem":4946,
    "gn:feature_class":"P",
    "gn:feature_code":"PPL",
    "gn:name":"Zhaxigujian",
    "gn:population":0,
    "gn:timezone":"Asia/Urumqi",
    "iso:country":"CN",
    "name:zho_x_preferred":[
        "\u624e\u897f\u6545\u575a"
    ],
    "wof:name":"Zhaxigujian",
    "wof:placetype":"locality"
},
  "geometry": {"coordinates":[84.53279999999999,30.1296],"type":"Point"}
}