{
  "type": "Feature",
  "properties": {
    "gn:admin1_code":"9.0",
    "gn:asciiname":"Zaojiaowan",
    "gn:country_code":"CN",
    "gn:dem":220,
    "gn:feature_class":"P",
    "gn:feature_code":"PPL",
    "gn:name":"Zaojiaowan",
    "gn:population":0,
    "gn:timezone":"Asia/Shanghai",
    "iso:country":"CN",
    "name:zho_x_preferred":[
        "\u7682\u89d2\u6e7e"
    ],
    "wof:name":"Zaojiaowan",
    "wof:placetype":"locality"
},
  "geometry": {"coordinates":[112.20813,34.94801],"type":"Point"}
}