{
  "type": "Feature",
  "properties": {
    "gn:admin1_code":"20",
    "gn:asciiname":"Pa-fen-ti",
    "gn:country_code":"CN",
    "gn:dem":732,
    "gn:feature_class":"P",
    "gn:feature_code":"PPL",
    "gn:name":"Pa-fen-ti",
    "gn:population":0,
    "gn:timezone":"Asia/Shanghai",
    "iso:country":"CN",
    "wof:name":"Pa-fen-ti",
    "wof:placetype":"locality"
},
  "geometry": {"coordinates":[118.81139,42.84389],"type":"Point"}
}