{
  "type": "Feature",
  "properties": {
    "gn:admin1_code":"32.0",
    "gn:asciiname":"Sanguzhuang",
    "gn:country_code":"CN",
    "gn:dem":2341,
    "gn:feature_class":"P",
    "gn:feature_code":"PPL",
    "gn:name":"Sanguzhuang",
    "gn:population":0,
    "gn:timezone":"Asia/Shanghai",
    "iso:country":"CN",
    "name:zho_x_preferred":[
        "\u4e09\u53e4\u5e84"
    ],
    "wof:name":"Sanguzhuang",
    "wof:placetype":"locality"
},
  "geometry": {"coordinates":[102.05588,28.01534],"type":"Point"}
}