{
  "type": "Feature",
  "properties": {
    "gn:admin1_code":"2.0",
    "gn:asciiname":"Taiyangwu",
    "gn:country_code":"CN",
    "gn:dem":151,
    "gn:feature_class":"P",
    "gn:feature_code":"PPL",
    "gn:name":"Taiyangwu",
    "gn:population":0,
    "gn:timezone":"Asia/Shanghai",
    "iso:country":"CN",
    "name:und_x_variant":[
        "\u592a\u9633\u575e",
        "Taiyangwu"
    ],
    "wof:name":"Taiyangwu",
    "wof:placetype":"locality"
},
  "geometry": {"coordinates":[119.54470000000001,29.98965],"type":"Point"}
}