{
  "type": "Feature",
  "properties": {
    "gn:admin1_code":"21.0",
    "gn:asciiname":"Yinggecha",
    "gn:country_code":"CN",
    "gn:dem":1712,
    "gn:feature_class":"P",
    "gn:feature_code":"PPL",
    "gn:name":"Yinggecha",
    "gn:population":0,
    "gn:timezone":"Asia/Shanghai",
    "iso:country":"CN",
    "name:und_x_variant":[
        "\u9e66\u9e3d\u5c94"
    ],
    "name:zho_x_preferred":[
        "\u9e66\u9e3d\u5c94"
    ],
    "wof:name":"Yinggecha",
    "wof:placetype":"locality"
},
  "geometry": {"coordinates":[106.52669,36.12159000000001],"type":"Point"}
}