{
  "type": "Feature",
  "properties": {
    "gn:admin1_code":"15.0",
    "gn:asciiname":"Badu",
    "gn:country_code":"CN",
    "gn:dem":2776,
    "gn:feature_class":"P",
    "gn:feature_code":"PPL",
    "gn:name":"Badu",
    "gn:population":0,
    "gn:timezone":"Asia/Shanghai",
    "iso:country":"CN",
    "name:ceb_x_preferred":[
        "Badu"
    ],
    "name:deu_x_preferred":[
        "Badu"
    ],
    "name:fra_x_preferred":[
        "Badu"
    ],
    "name:rus_x_preferred":[
        "\u0411\u0430\u0434\u0443"
    ],
    "name:swe_x_preferred":[
        "Badu"
    ],
    "name:zho_x_preferred":[
        "\u575d\u5835"
    ],
    "wof:name":"Badu",
    "wof:placetype":"locality"
},
  "geometry": {"coordinates":[103.123,37.3163],"type":"Point"}
}