{
  "type": "Feature",
  "properties": {
    "gn:admin1_code":"3.0",
    "gn:asciiname":"Caojiawu",
    "gn:country_code":"CN",
    "gn:dem":75,
    "gn:feature_class":"P",
    "gn:feature_code":"PPL",
    "gn:name":"Caojiawu",
    "gn:population":0,
    "gn:timezone":"Asia/Shanghai",
    "iso:country":"CN",
    "name:und_x_variant":[
        "\u64cd\u5bb6\u575e"
    ],
    "wof:name":"Caojiawu",
    "wof:placetype":"locality"
},
  "geometry": {"coordinates":[117.16737000000001,29.09968],"type":"Point"}
}