{
  "type": "Feature",
  "properties": {
    "gn:admin1_code":"8.0",
    "gn:asciiname":"Changlongcun",
    "gn:country_code":"CN",
    "gn:dem":155,
    "gn:feature_class":"P",
    "gn:feature_code":"PPL",
    "gn:name":"Changlongcun",
    "gn:population":0,
    "gn:timezone":"Asia/Shanghai",
    "iso:country":"CN",
    "name:zho_x_preferred":[
        "\u957f\u9686\u6751"
    ],
    "wof:name":"Changlongcun",
    "wof:placetype":"locality"
},
  "geometry": {"coordinates":[123.05386,46.50763],"type":"Point"}
}