{
  "type": "Feature",
  "properties": {
    "gn:admin1_code":"30.0",
    "gn:asciiname":"Yangdongcun",
    "gn:country_code":"CN",
    "gn:dem":7,
    "gn:feature_class":"P",
    "gn:feature_code":"PPL",
    "gn:name":"Yangdongcun",
    "gn:population":0,
    "gn:timezone":"Asia/Shanghai",
    "iso:country":"CN",
    "name:zho_x_preferred":[
        "\u6d0b\u4e1c\u6751"
    ],
    "wof:name":"Yangdongcun",
    "wof:placetype":"locality"
},
  "geometry": {"coordinates":[116.69795000000001,23.48635],"type":"Point"}
}