{
  "type": "Feature",
  "properties": {
    "gn:admin1_code":"29.0",
    "gn:asciiname":"Yingpanshang",
    "gn:country_code":"CN",
    "gn:dem":2403,
    "gn:feature_class":"P",
    "gn:feature_code":"PPL",
    "gn:name":"Yingpanshang",
    "gn:population":0,
    "gn:timezone":"Asia/Shanghai",
    "iso:country":"CN",
    "name:zho_x_preferred":[
        "\u8425\u76d8\u4e0a"
    ],
    "wof:name":"Yingpanshang",
    "wof:placetype":"locality"
},
  "geometry": {"coordinates":[103.57599999999999,27.7375],"type":"Point"}
}