{
  "type": "Feature",
  "properties": {
    "gn:admin1_code":"19",
    "gn:asciiname":"Ma-chuan-tzu",
    "gn:country_code":"CN",
    "gn:dem":498,
    "gn:feature_class":"P",
    "gn:feature_code":"PPL",
    "gn:name":"Ma-ch\u00fcan-tzu",
    "gn:population":0,
    "gn:timezone":"Asia/Shanghai",
    "iso:country":"CN",
    "wof:name":"Ma-chuan-tzu",
    "wof:placetype":"locality"
},
  "geometry": {"coordinates":[119.38028,42.01222],"type":"Point"}
}