{
  "type": "Feature",
  "properties": {
    "gn:admin1_code":"15.0",
    "gn:asciiname":"Randazhuang",
    "gn:country_code":"CN",
    "gn:dem":1154,
    "gn:feature_class":"P",
    "gn:feature_code":"PPL",
    "gn:name":"Randazhuang",
    "gn:population":0,
    "gn:timezone":"Asia/Shanghai",
    "iso:country":"CN",
    "name:zho_x_preferred":[
        "\u5189\u5927\u5e84"
    ],
    "wof:name":"Randazhuang",
    "wof:placetype":"locality"
},
  "geometry": {"coordinates":[107.336,35.5011],"type":"Point"}
}