{
  "type": "Feature",
  "properties": {
    "gn:admin1_code":"07",
    "gn:asciiname":"Meizhou",
    "gn:country_code":"CN",
    "gn:dem":11,
    "gn:feature_class":"P",
    "gn:feature_code":"PPLA4",
    "gn:name":"Meizhou",
    "gn:population":0,
    "gn:timezone":"Asia/Shanghai",
    "iso:country":"CN",
    "name:und_x_variant":[
        "Mei-chou",
        "Mei-chou-hs\u00fcn",
        "Meizhou"
    ],
    "name:zho_x_preferred":[
        "\u6885\u6d32"
    ],
    "wof:name":"Meizhou",
    "wof:placetype":"locality"
},
  "geometry": {"coordinates":[117.31331000000002,23.80856],"type":"Point"}
}