{
  "type": "Feature",
  "properties": {
    "gn:admin1_code":"25",
    "gn:asciiname":"Wangjia Wuzi",
    "gn:country_code":"CN",
    "gn:dem":2,
    "gn:feature_class":"P",
    "gn:feature_code":"PPL",
    "gn:name":"Wangjia Wuzi",
    "gn:population":0,
    "gn:timezone":"Asia/Shanghai",
    "iso:country":"CN",
    "name:zho_x_preferred":[
        "\u738b\u5bb6\u5c4b\u5b50"
    ],
    "wof:name":"Wangjia Wuzi",
    "wof:placetype":"locality"
},
  "geometry": {"coordinates":[118.411,38.0172],"type":"Point"}
}