{
  "type": "Feature",
  "properties": {
    "gn:admin1_code":"3",
    "gn:asciiname":"Zhongqi",
    "gn:country_code":"CN",
    "gn:dem":493,
    "gn:feature_class":"P",
    "gn:feature_code":"PPL",
    "gn:name":"Zhongqi",
    "gn:population":0,
    "gn:timezone":"Asia/Shanghai",
    "iso:country":"CN",
    "name:und_x_variant":[
        "\u4e2d\u789b"
    ],
    "wof:name":"Zhongqi",
    "wof:placetype":"locality"
},
  "geometry": {"coordinates":[115.46517,25.13401],"type":"Point"}
}