{
  "type": "Feature",
  "properties": {
    "gn:admin1_code":"24.0",
    "gn:asciiname":"Mao'erjian",
    "gn:country_code":"CN",
    "gn:dem":1424,
    "gn:feature_class":"P",
    "gn:feature_code":"PPL",
    "gn:name":"Mao\u2019erjian",
    "gn:population":0,
    "gn:timezone":"Asia/Shanghai",
    "iso:country":"CN",
    "name:und_x_variant":[
        "Mao\u2019erjian"
    ],
    "name:zho_x_preferred":[
        "\u732b\u513f\u5c16"
    ],
    "wof:name":"Mao'erjian",
    "wof:placetype":"locality"
},
  "geometry": {"coordinates":[112.11688999999998,38.05697],"type":"Point"}
}