{
  "type": "Feature",
  "properties": {
    "gn:admin1_code":"4.0",
    "gn:asciiname":"Zhujiashe",
    "gn:country_code":"CN",
    "gn:dem":0,
    "gn:feature_class":"P",
    "gn:feature_code":"PPL",
    "gn:name":"Zhujiashe",
    "gn:population":0,
    "gn:timezone":"Asia/Shanghai",
    "iso:country":"CN",
    "name:zho_x_preferred":[
        "Zhujiashe"
    ],
    "name:zho_x_variant":[
        "\u6731\u5bb6\u820d"
    ],
    "wof:name":"Zhujiashe",
    "wof:placetype":"locality"
},
  "geometry": {"coordinates":[119.65788000000001,33.32380999999999],"type":"Point"}
}