{
  "type": "Feature",
  "properties": {
    "gn:admin1_code":"13.0",
    "gn:asciiname":"Bulake",
    "gn:country_code":"CN",
    "gn:dem":1374,
    "gn:feature_class":"P",
    "gn:feature_code":"PPL",
    "gn:name":"Bulake",
    "gn:population":0,
    "gn:timezone":"Asia/Shanghai",
    "iso:country":"CN",
    "name:zho_x_preferred":[
        "\u5e03\u62c9\u514b"
    ],
    "wof:name":"Bulake",
    "wof:placetype":"locality"
},
  "geometry": {"coordinates":[78.71814999999999,37.41381],"type":"Point"}
}