{
  "type": "Feature",
  "properties": {
    "gn:admin1_code":"32.0",
    "gn:asciiname":"Tudi Miaozui",
    "gn:country_code":"CN",
    "gn:dem":329,
    "gn:feature_class":"P",
    "gn:feature_code":"PPL",
    "gn:name":"Tudi Miaozui",
    "gn:population":0,
    "gn:timezone":"Asia/Shanghai",
    "iso:country":"CN",
    "name:zho_x_preferred":[
        "\u571f\u5730\u5e99\u5480"
    ],
    "wof:name":"Tudi Miaozui",
    "wof:placetype":"locality"
},
  "geometry": {"coordinates":[105.49097,30.45706],"type":"Point"}
}