{
  "type": "Feature",
  "properties": {
    "gn:admin1_code":"21.0",
    "gn:asciiname":"Huangcaowa",
    "gn:country_code":"CN",
    "gn:dem":1794,
    "gn:feature_class":"P",
    "gn:feature_code":"PPL",
    "gn:name":"Huangcaowa",
    "gn:population":0,
    "gn:timezone":"Asia/Shanghai",
    "iso:country":"CN",
    "name:zho_x_preferred":[
        "\u9ec4\u8349\u6d3c"
    ],
    "wof:name":"Huangcaowa",
    "wof:placetype":"locality"
},
  "geometry": {"coordinates":[105.995,36.3786],"type":"Point"}
}