{
  "type": "Feature",
  "properties": {
    "gn:admin1_code":"2",
    "gn:asciiname":"Wangli",
    "gn:country_code":"CN",
    "gn:dem":8,
    "gn:feature_class":"P",
    "gn:feature_code":"PPL",
    "gn:name":"Wangli",
    "gn:population":0,
    "gn:timezone":"Asia/Shanghai",
    "iso:country":"CN",
    "name:und_x_variant":[
        "Nanchaliao"
    ],
    "name:zho_x_preferred":[
        "\u671b\u91cc"
    ],
    "name:zho_x_variant":[
        "Wangli"
    ],
    "wof:name":"Wangli",
    "wof:placetype":"locality"
},
  "geometry": {"coordinates":[120.52325,27.47705],"type":"Point"}
}