{
  "type": "Feature",
  "properties": {
    "gn:admin1_code":"7.0",
    "gn:asciiname":"Baojuyang",
    "gn:country_code":"CN",
    "gn:dem":601,
    "gn:feature_class":"P",
    "gn:feature_code":"PPL",
    "gn:name":"Baojuyang",
    "gn:population":0,
    "gn:timezone":"Asia/Shanghai",
    "iso:country":"CN",
    "name:zho_x_preferred":[
        "\u5b9d\u805a\u6d0b"
    ],
    "wof:name":"Baojuyang",
    "wof:placetype":"locality"
},
  "geometry": {"coordinates":[119.85384999999999,27.20594],"type":"Point"}
}