{
  "type": "Feature",
  "properties": {
    "gn:admin1_code":"19.0",
    "gn:asciiname":"Linjia Wobu",
    "gn:country_code":"CN",
    "gn:dem":236,
    "gn:feature_class":"P",
    "gn:feature_code":"PPL",
    "gn:name":"Linjia Wobu",
    "gn:population":0,
    "gn:timezone":"Asia/Shanghai",
    "iso:country":"CN",
    "name:und_x_variant":[
        "Linjiawobao",
        "Linjia Wobu"
    ],
    "name:zho_x_preferred":[
        "\u6797\u5bb6\u7a9d\u5821"
    ],
    "wof:name":"Linjia Wobu",
    "wof:placetype":"locality"
},
  "geometry": {"coordinates":[121.94858000000001,42.55115],"type":"Point"}
}