{
  "type": "Feature",
  "properties": {
    "gn:admin1_code":"20.0",
    "gn:asciiname":"Saihannao'er Gacha",
    "gn:country_code":"CN",
    "gn:dem":934,
    "gn:feature_class":"P",
    "gn:feature_code":"PPL",
    "gn:name":"Saihannao\u2019er Gacha",
    "gn:population":0,
    "gn:timezone":"Asia/Shanghai",
    "iso:country":"CN",
    "name:und_x_variant":[
        "Saihannao\u2019er Gacha"
    ],
    "name:zho_x_preferred":[
        "\u8d5b\u7f55\u6dd6\u5c14\u560e\u67e5"
    ],
    "wof:name":"Saihannao'er Gacha",
    "wof:placetype":"locality"
},
  "geometry": {"coordinates":[100.84085,42.12832],"type":"Point"}
}