{
  "type": "Feature",
  "properties": {
    "gn:admin1_code":"16",
    "gn:asciiname":"Zhulatou",
    "gn:country_code":"CN",
    "gn:dem":284,
    "gn:feature_class":"P",
    "gn:feature_code":"PPL",
    "gn:name":"Zhulatou",
    "gn:population":0,
    "gn:timezone":"Asia/Shanghai",
    "iso:country":"CN",
    "name:zho_x_preferred":[
        "\u7af9\u814a\u5934"
    ],
    "wof:name":"Zhulatou",
    "wof:placetype":"locality"
},
  "geometry": {"coordinates":[110.63,25.449],"type":"Point"}
}