{
  "type": "Feature",
  "properties": {
    "gn:admin1_code":"24",
    "gn:asciiname":"Luandaogou",
    "gn:cc2":"CN",
    "gn:country_code":"CN",
    "gn:dem":1330,
    "gn:feature_class":"P",
    "gn:feature_code":"PPL",
    "gn:name":"Luandaogou",
    "gn:population":0,
    "gn:timezone":"Asia/Shanghai",
    "iso:country":"CN",
    "name:und_x_variant":[
        "Luan-tao-kou",
        "Luandaogou"
    ],
    "wof:name":"Luandaogou",
    "wof:placetype":"locality"
},
  "geometry": {"coordinates":[112.47,39.59194],"type":"Point"}
}