{
  "type": "Feature",
  "properties": {
    "gn:admin1_code":"10",
    "gn:asciiname":"Xisan Chakou",
    "gn:country_code":"CN",
    "gn:dem":428,
    "gn:feature_class":"P",
    "gn:feature_code":"PPL",
    "gn:name":"Xisan Chakou",
    "gn:population":0,
    "gn:timezone":"Asia/Shanghai",
    "iso:country":"CN",
    "name:zho_x_preferred":[
        "\u897f\u4e09\u5c94\u53e3"
    ],
    "wof:name":"Xisan Chakou",
    "wof:placetype":"locality"
},
  "geometry": {"coordinates":[116.87756,40.91123],"type":"Point"}
}