{
  "type": "Feature",
  "properties": {
    "gn:admin1_code":"30",
    "gn:asciiname":"Jinchang",
    "gn:country_code":"CN",
    "gn:dem":2,
    "gn:feature_class":"P",
    "gn:feature_code":"PPL",
    "gn:name":"Jinchang",
    "gn:population":0,
    "gn:timezone":"Asia/Shanghai",
    "iso:country":"CN",
    "name:ara_x_preferred":[
        "\u062c\u064a\u0646\u0634\u0627\u0646\u063a"
    ],
    "name:cdo_x_preferred":[
        "G\u012dng-chi\u014fng"
    ],
    "name:ceb_x_preferred":[
        "Jinchang"
    ],
    "name:ces_x_preferred":[
        "\u0164in-\u010dchang"
    ],
    "name:dan_x_preferred":[
        "Jinchang"
    ],
    "name:deu_x_preferred":[
        "Jinchang"
    ],
    "name:eus_x_preferred":[
        "Jinchang"
    ],
    "name:fas_x_preferred":[
        "\u062c\u06cc\u0646\u0686\u0627\u0646\u06af"
    ],
    "name:fin_x_preferred":[
        "Jinchang"
    ],
    "name:fra_x_preferred":[
        "Jinchang"
    ],
    "name:hye_x_preferred":[
        "\u0551\u0566\u056b\u0576\u0579\u0561\u0576"
    ],
    "name:ind_x_preferred":[
        "Jinchang"
    ],
    "name:ita_x_preferred":[
        "Jinchang"
    ],
    "name:jpn_x_preferred":[
        "\u91d1\u660c\u5e02"
    ],
    "name:kik_x_preferred":[
        "Jinchang"
    ],
    "name:kor_x_preferred":[
        "\uc9c4\ucc3d\uc2dc"
    ],
    "name:mlg_x_preferred":[
        "Jinchang"
    ],
    "name:nld_x_preferred":[
        "Jinchang"
    ],
    "name:nno_x_preferred":[
        "Jinchang"
    ],
    "name:nor_x_preferred":[
        "Jinchang"
    ],
    "name:pam_x_preferred":[
        "Jinchang"
    ],
    "name:pnb_x_preferred":[
        "\u062c\u0646\u0686\u0627\u0646\u06af"
    ],
    "name:pol_x_preferred":[
        "Jinchang"
    ],
    "name:por_x_preferred":[
        "Jinchang"
    ],
    "name:rus_x_preferred":[
        "\u0426\u0437\u0438\u043d\u044c\u0447\u0430\u043d"
    ],
    "name:spa_x_preferred":[
        "Jinchang"
    ],
    "name:swe_x_preferred":[
        "Jinchang"
    ],
    "name:tgl_x_preferred":[
        "Jinchang"
    ],
    "name:tur_x_preferred":[
        "Jinchang"
    ],
    "name:urd_x_preferred":[
        "\u062c\u0646\u0686\u0627\u0646\u06af"
    ],
    "name:vie_x_preferred":[
        "Kim X\u01b0\u01a1ng"
    ],
    "name:war_x_preferred":[
        "Jinchang"
    ],
    "name:wuu_x_preferred":[
        "\u91d1\u660c\u5e02"
    ],
    "name:zho_x_preferred":[
        "\u91d1\u573a"
    ],
    "name:zho_x_variant":[
        "\u91d1\u660c\u5e02"
    ],
    "wof:name":"Jinchang",
    "wof:placetype":"locality"
},
  "geometry": {"coordinates":[116.61257999999999,23.39376],"type":"Point"}
}