{
  "type": "Feature",
  "properties": {
    "gn:admin1_code":"7.0",
    "gn:asciiname":"Zoushan",
    "gn:country_code":"CN",
    "gn:dem":922,
    "gn:feature_class":"P",
    "gn:feature_code":"PPL",
    "gn:name":"Zoushan",
    "gn:population":0,
    "gn:timezone":"Asia/Shanghai",
    "iso:country":"CN",
    "name:zho_x_preferred":[
        "\u90b9\u5c71"
    ],
    "wof:name":"Zoushan",
    "wof:placetype":"locality"
},
  "geometry": {"coordinates":[117.26004,25.49295],"type":"Point"}
}