{
  "type": "Feature",
  "properties": {
    "gn:admin1_code":"9.0",
    "gn:asciiname":"Dazhongzipo",
    "gn:country_code":"CN",
    "gn:dem":171,
    "gn:feature_class":"P",
    "gn:feature_code":"PPL",
    "gn:name":"Dazhongzipo",
    "gn:population":0,
    "gn:timezone":"Asia/Shanghai",
    "iso:country":"CN",
    "name:zho_x_preferred":[
        "\u5927\u51a2\u5b50\u5761"
    ],
    "wof:name":"Dazhongzipo",
    "wof:placetype":"locality"
},
  "geometry": {"coordinates":[113.19249000000001,32.5756],"type":"Point"}
}