{
  "type": "Feature",
  "properties": {
    "gn:admin1_code":"2.0",
    "gn:asciiname":"Tianlongli",
    "gn:country_code":"CN",
    "gn:dem":292,
    "gn:feature_class":"P",
    "gn:feature_code":"PPL",
    "gn:name":"Tianlongli",
    "gn:population":0,
    "gn:timezone":"Asia/Shanghai",
    "iso:country":"CN",
    "name:zho_x_preferred":[
        "\u7530\u5784\u91cc"
    ],
    "wof:name":"Tianlongli",
    "wof:placetype":"locality"
},
  "geometry": {"coordinates":[118.86785,29.62349],"type":"Point"}
}