{
  "type": "Feature",
  "properties": {
    "gn:admin1_code":"19",
    "gn:asciiname":"Aiyang",
    "gn:country_code":"CN",
    "gn:dem":255,
    "gn:feature_class":"P",
    "gn:feature_code":"PPL",
    "gn:name":"Aiyang",
    "gn:population":0,
    "gn:timezone":"Asia/Shanghai",
    "iso:country":"CN",
    "wof:name":"Aiyang",
    "wof:placetype":"locality"
},
  "geometry": {"coordinates":[124.43861,40.89556],"type":"Point"}
}