{
  "type": "Feature",
  "properties": {
    "gn:admin1_code":"33.0",
    "gn:asciiname":"Jiangansi",
    "gn:country_code":"CN",
    "gn:dem":390,
    "gn:feature_class":"P",
    "gn:feature_code":"PPL",
    "gn:name":"Jiangansi",
    "gn:population":0,
    "gn:timezone":"Asia/Shanghai",
    "iso:country":"CN",
    "name:zho_x_preferred":[
        "\u7bad\u6746\u5bfa"
    ],
    "wof:name":"Jiangansi",
    "wof:placetype":"locality"
},
  "geometry": {"coordinates":[105.80512,29.18075],"type":"Point"}
}