{
  "type": "Feature",
  "properties": {
    "gn:admin1_code":"19.0",
    "gn:asciiname":"Dongxiaofang Shencun",
    "gn:country_code":"CN",
    "gn:dem":119,
    "gn:feature_class":"P",
    "gn:feature_code":"PPL",
    "gn:name":"Dongxiaofang Shencun",
    "gn:population":0,
    "gn:timezone":"Asia/Shanghai",
    "iso:country":"CN",
    "name:und_x_variant":[
        "Dongxiaofangshencun",
        "Dongxiaofang Shencun"
    ],
    "name:zho_x_preferred":[
        "\u4e1c\u5c0f\u623f\u8eab\u6751"
    ],
    "wof:name":"Dongxiaofang Shencun",
    "wof:placetype":"locality"
},
  "geometry": {"coordinates":[123.28153,42.62205],"type":"Point"}
}