{
  "type": "Feature",
  "properties": {
    "gn:admin1_code":"14.0",
    "gn:asciiname":"Xiaka",
    "gn:country_code":"CN",
    "gn:dem":4699,
    "gn:feature_class":"P",
    "gn:feature_code":"PPL",
    "gn:name":"Xiaka",
    "gn:population":0,
    "gn:timezone":"Asia/Urumqi",
    "iso:country":"CN",
    "name:zho_x_preferred":[
        "\u590f\u5361"
    ],
    "wof:name":"Xiaka",
    "wof:placetype":"locality"
},
  "geometry": {"coordinates":[86.3382,30.5591],"type":"Point"}
}