{
  "type": "Feature",
  "properties": {
    "gn:admin1_code":"19.0",
    "gn:asciiname":"Xiaoqijiazi",
    "gn:country_code":"CN",
    "gn:dem":162,
    "gn:feature_class":"P",
    "gn:feature_code":"PPL",
    "gn:name":"Xiaoqijiazi",
    "gn:population":0,
    "gn:timezone":"Asia/Shanghai",
    "iso:country":"CN",
    "name:zho_x_preferred":[
        "\u5c0f\u4e03\u5bb6\u5b50"
    ],
    "wof:name":"Xiaoqijiazi",
    "wof:placetype":"locality"
},
  "geometry": {"coordinates":[121.55698,41.99649],"type":"Point"}
}