{
  "type": "Feature",
  "properties": {
    "gn:admin1_code":"12.0",
    "gn:asciiname":"Guihua Wuchang",
    "gn:country_code":"CN",
    "gn:dem":56,
    "gn:feature_class":"P",
    "gn:feature_code":"PPL",
    "gn:name":"Guihua Wuchang",
    "gn:population":0,
    "gn:timezone":"Asia/Shanghai",
    "iso:country":"CN",
    "name:zho_x_preferred":[
        "Guihua Wuchang"
    ],
    "name:zho_x_variant":[
        "\u6842\u82b1\u5c4b\u573a"
    ],
    "wof:name":"Guihua Wuchang",
    "wof:placetype":"locality"
},
  "geometry": {"coordinates":[111.77036,29.94068],"type":"Point"}
}