{
  "type": "Feature",
  "properties": {
    "gn:admin1_code":"30",
    "gn:asciiname":"Wushi",
    "gn:country_code":"CN",
    "gn:dem":6,
    "gn:feature_class":"P",
    "gn:feature_code":"PPL",
    "gn:name":"Wushi",
    "gn:population":0,
    "gn:timezone":"Asia/Shanghai",
    "iso:country":"CN",
    "name:ceb_x_preferred":[
        "Wushi"
    ],
    "name:deu_x_preferred":[
        "Wushi"
    ],
    "name:fra_x_preferred":[
        "Wushi"
    ],
    "name:swe_x_preferred":[
        "Wushi"
    ],
    "wof:name":"Wushi",
    "wof:placetype":"locality"
},
  "geometry": {"coordinates":[116.5112,23.35854],"type":"Point"}
}