{
  "type": "Feature",
  "properties": {
    "gn:admin1_code":"8.0",
    "gn:asciiname":"Wusanling",
    "gn:country_code":"CN",
    "gn:dem":358,
    "gn:feature_class":"P",
    "gn:feature_code":"PPL",
    "gn:name":"Wusanling",
    "gn:population":0,
    "gn:timezone":"Asia/Shanghai",
    "iso:country":"CN",
    "name:zho_x_preferred":[
        "\u4e94\u4e09\u96f6"
    ],
    "wof:name":"Wusanling",
    "wof:placetype":"locality"
},
  "geometry": {"coordinates":[128.98944,47.47617],"type":"Point"}
}