{
  "type": "Feature",
  "properties": {
    "gn:admin1_code":"11.0",
    "gn:asciiname":"Shangxiaopu",
    "gn:country_code":"CN",
    "gn:dem":177,
    "gn:feature_class":"P",
    "gn:feature_code":"PPL",
    "gn:name":"Shangxiaopu",
    "gn:population":0,
    "gn:timezone":"Asia/Shanghai",
    "iso:country":"CN",
    "name:zho_x_preferred":[
        "\u4e0a\u5c0f\u94fa"
    ],
    "wof:name":"Shangxiaopu",
    "wof:placetype":"locality"
},
  "geometry": {"coordinates":[113.2141,26.34349000000001],"type":"Point"}
}