{
  "type": "Feature",
  "properties": {
    "gn:admin1_code":"1.0",
    "gn:asciiname":"Xinghuacun",
    "gn:country_code":"CN",
    "gn:dem":42,
    "gn:feature_class":"P",
    "gn:feature_code":"PPL",
    "gn:name":"Xinghuacun",
    "gn:population":0,
    "gn:timezone":"Asia/Shanghai",
    "iso:country":"CN",
    "name:zho_x_preferred":[
        "\u5174\u5316\u6751"
    ],
    "wof:name":"Xinghuacun",
    "wof:placetype":"locality"
},
  "geometry": {"coordinates":[117.88018,30.87503],"type":"Point"}
}