{
  "type": "Feature",
  "properties": {
    "gn:admin1_code":"3.0",
    "gn:asciiname":"Guanyuanshan",
    "gn:country_code":"CN",
    "gn:dem":383,
    "gn:feature_class":"P",
    "gn:feature_code":"PPL",
    "gn:name":"Guanyuanshan",
    "gn:population":0,
    "gn:timezone":"Asia/Shanghai",
    "iso:country":"CN",
    "name:und_x_variant":[
        "\u5b98\u5143\u5c71"
    ],
    "wof:name":"Guanyuanshan",
    "wof:placetype":"locality"
},
  "geometry": {"coordinates":[114.30949,28.35441],"type":"Point"}
}