{
  "type": "Feature",
  "properties": {
    "gn:admin1_code":"1.0",
    "gn:asciiname":"Wuliduncun",
    "gn:country_code":"CN",
    "gn:dem":33,
    "gn:feature_class":"P",
    "gn:feature_code":"PPL",
    "gn:name":"Wuliduncun",
    "gn:population":0,
    "gn:timezone":"Asia/Shanghai",
    "iso:country":"CN",
    "name:zho_x_preferred":[
        "\u4e94\u91cc\u58a9\u6751"
    ],
    "wof:name":"Wuliduncun",
    "wof:placetype":"locality"
},
  "geometry": {"coordinates":[116.27557,32.36992],"type":"Point"}
}