{
  "type": "Feature",
  "properties": {
    "gn:admin1_code":"3.0",
    "gn:asciiname":"Litoujiao",
    "gn:country_code":"CN",
    "gn:dem":119,
    "gn:feature_class":"P",
    "gn:feature_code":"PPL",
    "gn:name":"Litoujiao",
    "gn:population":0,
    "gn:timezone":"Asia/Shanghai",
    "iso:country":"CN",
    "name:und_x_variant":[
        "\u7281\u5934\u89d2"
    ],
    "wof:name":"Litoujiao",
    "wof:placetype":"locality"
},
  "geometry": {"coordinates":[116.68919,28.34795],"type":"Point"}
}