{
  "type": "Feature",
  "properties": {
    "gn:admin1_code":"05",
    "gn:asciiname":"Wu-ming-t'un",
    "gn:country_code":"CN",
    "gn:dem":359,
    "gn:feature_class":"P",
    "gn:feature_code":"PPL",
    "gn:name":"Wu-ming-t\u2019un",
    "gn:population":0,
    "gn:timezone":"Asia/Shanghai",
    "iso:country":"CN",
    "wof:name":"Wu-ming-t'un",
    "wof:placetype":"locality"
},
  "geometry": {"coordinates":[125.03306000000001,42.66722],"type":"Point"}
}