{
  "type": "Feature",
  "properties": {
    "gn:admin1_code":"3",
    "gn:asciiname":"Zhaixia",
    "gn:country_code":"CN",
    "gn:dem":301,
    "gn:feature_class":"P",
    "gn:feature_code":"PPL",
    "gn:name":"Zhaixia",
    "gn:population":0,
    "gn:timezone":"Asia/Shanghai",
    "iso:country":"CN",
    "name:zho_x_preferred":[
        "\u5be8\u4e0b"
    ],
    "wof:name":"Zhaixia",
    "wof:placetype":"locality"
},
  "geometry": {"coordinates":[114.242,26.7313],"type":"Point"}
}