{
  "type": "Feature",
  "properties": {
    "gn:admin1_code":"7.0",
    "gn:asciiname":"Xiaohuocun",
    "gn:country_code":"CN",
    "gn:dem":262,
    "gn:feature_class":"P",
    "gn:feature_code":"PPL",
    "gn:name":"Xiaohuocun",
    "gn:population":0,
    "gn:timezone":"Asia/Shanghai",
    "iso:country":"CN",
    "name:und_x_variant":[
        "\u5c0f\u4f19\u6751"
    ],
    "name:zho_x_preferred":[
        "\u5c0f\u4f19\u6751"
    ],
    "wof:name":"Xiaohuocun",
    "wof:placetype":"locality"
},
  "geometry": {"coordinates":[117.19164000000001,26.04987],"type":"Point"}
}