{
  "type": "Feature",
  "properties": {
    "gn:admin1_code":"4.0",
    "gn:asciiname":"Shatangcun",
    "gn:country_code":"CN",
    "gn:dem":6,
    "gn:feature_class":"P",
    "gn:feature_code":"PPL",
    "gn:name":"Shatangcun",
    "gn:population":0,
    "gn:timezone":"Asia/Shanghai",
    "iso:country":"CN",
    "name:zho_x_preferred":[
        "\u6c99\u5858\u6751"
    ],
    "wof:name":"Shatangcun",
    "wof:placetype":"locality"
},
  "geometry": {"coordinates":[120.01390000000001,31.42413],"type":"Point"}
}