{
  "type": "Feature",
  "properties": {
    "gn:admin1_code":"5.0",
    "gn:asciiname":"Longfengcun",
    "gn:country_code":"CN",
    "gn:dem":206,
    "gn:feature_class":"P",
    "gn:feature_code":"PPL",
    "gn:name":"Longfengcun",
    "gn:population":0,
    "gn:timezone":"Asia/Shanghai",
    "iso:country":"CN",
    "name:zho_x_preferred":[
        "\u9f99\u51e4\u6751"
    ],
    "wof:name":"Longfengcun",
    "wof:placetype":"locality"
},
  "geometry": {"coordinates":[125.67836,44.22258],"type":"Point"}
}