{
  "type": "Feature",
  "properties": {
    "gn:admin1_code":"14.0",
    "gn:asciiname":"Zhuoqingcun",
    "gn:country_code":"CN",
    "gn:dem":4826,
    "gn:feature_class":"P",
    "gn:feature_code":"PPL",
    "gn:name":"Zhuoqingcun",
    "gn:population":0,
    "gn:timezone":"Asia/Urumqi",
    "iso:country":"CN",
    "name:zho_x_preferred":[
        "\u5353\u9752\u6751"
    ],
    "wof:name":"Zhuoqingcun",
    "wof:placetype":"locality"
},
  "geometry": {"coordinates":[91.90884,31.78305],"type":"Point"}
}