{
  "type": "Feature",
  "properties": {
    "gn:admin1_code":"13.0",
    "gn:asciiname":"Aigelekuole",
    "gn:country_code":"CN",
    "gn:dem":3153,
    "gn:feature_class":"P",
    "gn:feature_code":"PPL",
    "gn:name":"Aigelekuole",
    "gn:population":0,
    "gn:timezone":"Asia/Urumqi",
    "iso:country":"CN",
    "name:zho_x_preferred":[
        "\u827e\u683c\u52d2\u9614\u52d2"
    ],
    "wof:name":"Aigelekuole",
    "wof:placetype":"locality"
},
  "geometry": {"coordinates":[83.94633,36.75688],"type":"Point"}
}