{
  "type": "Feature",
  "properties": {
    "gn:admin1_code":"18",
    "gn:asciiname":"Yujiapo",
    "gn:country_code":"CN",
    "gn:dem":862,
    "gn:feature_class":"P",
    "gn:feature_code":"PPL",
    "gn:name":"Yujiapo",
    "gn:population":0,
    "gn:timezone":"Asia/Shanghai",
    "iso:country":"CN",
    "name:zho_x_preferred":[
        "\u90c1\u5bb6\u5761"
    ],
    "wof:name":"Yujiapo",
    "wof:placetype":"locality"
},
  "geometry": {"coordinates":[106.776,27.2128],"type":"Point"}
}