{
  "type": "Feature",
  "properties": {
    "gn:admin1_code":"7.0",
    "gn:asciiname":"Jiaojialing",
    "gn:country_code":"CN",
    "gn:dem":682,
    "gn:feature_class":"P",
    "gn:feature_code":"PPL",
    "gn:name":"Jiaojialing",
    "gn:population":0,
    "gn:timezone":"Asia/Shanghai",
    "iso:country":"CN",
    "name:und_x_variant":[
        "\u7126\u5bb6\u5cad"
    ],
    "name:zho_x_preferred":[
        "\u7126\u5bb6\u5cad"
    ],
    "wof:name":"Jiaojialing",
    "wof:placetype":"locality"
},
  "geometry": {"coordinates":[116.98690000000001,26.76839],"type":"Point"}
}