{
  "type": "Feature",
  "properties": {
    "gn:admin1_code":"19",
    "gn:asciiname":"Huangjiaquan",
    "gn:country_code":"CN",
    "gn:dem":20,
    "gn:feature_class":"P",
    "gn:feature_code":"PPL",
    "gn:name":"Huangjiaquan",
    "gn:population":0,
    "gn:timezone":"Asia/Shanghai",
    "iso:country":"CN",
    "name:zho_x_preferred":[
        "\u9ec4\u5bb6\u5708"
    ],
    "wof:name":"Huangjiaquan",
    "wof:placetype":"locality"
},
  "geometry": {"coordinates":[123.202,39.6802],"type":"Point"}
}