{
  "type": "Feature",
  "properties": {
    "gn:admin1_code":"5.0",
    "gn:asciiname":"Xiwu Jingzi",
    "gn:country_code":"CN",
    "gn:dem":149,
    "gn:feature_class":"P",
    "gn:feature_code":"PPL",
    "gn:name":"Xiwu Jingzi",
    "gn:population":0,
    "gn:timezone":"Asia/Shanghai",
    "iso:country":"CN",
    "name:zho_x_preferred":[
        "\u897f\u4e94\u4e95\u5b50"
    ],
    "wof:name":"Xiwu Jingzi",
    "wof:placetype":"locality"
},
  "geometry": {"coordinates":[123.06053,44.60942],"type":"Point"}
}