{
  "type": "Feature",
  "properties": {
    "gn:admin1_code":"29.0",
    "gn:asciiname":"Ningjiawan",
    "gn:country_code":"CN",
    "gn:dem":1840,
    "gn:feature_class":"P",
    "gn:feature_code":"PPL",
    "gn:name":"Ningjiawan",
    "gn:population":0,
    "gn:timezone":"Asia/Shanghai",
    "iso:country":"CN",
    "name:zho_x_preferred":[
        "\u5b81\u5bb6\u6e7e"
    ],
    "wof:name":"Ningjiawan",
    "wof:placetype":"locality"
},
  "geometry": {"coordinates":[103.849,26.236],"type":"Point"}
}