{
  "type": "Feature",
  "properties": {
    "gn:admin1_code":"29.0",
    "gn:asciiname":"Huayudong",
    "gn:country_code":"CN",
    "gn:dem":1316,
    "gn:feature_class":"P",
    "gn:feature_code":"PPL",
    "gn:name":"Huayudong",
    "gn:population":0,
    "gn:timezone":"Asia/Shanghai",
    "iso:country":"CN",
    "name:zho_x_preferred":[
        "\u82b1\u9c7c\u6d1e"
    ],
    "wof:name":"Huayudong",
    "wof:placetype":"locality"
},
  "geometry": {"coordinates":[99.2937,25.6101],"type":"Point"}
}