{
  "type": "Feature",
  "properties": {
    "gn:admin1_code":"10",
    "gn:asciiname":"Taixinzhuang",
    "gn:country_code":"CN",
    "gn:dem":23,
    "gn:feature_class":"P",
    "gn:feature_code":"PPL",
    "gn:name":"Taixinzhuang",
    "gn:population":0,
    "gn:timezone":"Asia/Shanghai",
    "iso:country":"CN",
    "name:zho_x_preferred":[
        "\u53f0\u8f9b\u5e84"
    ],
    "wof:name":"Taixinzhuang",
    "wof:placetype":"locality"
},
  "geometry": {"coordinates":[116.03273,37.62198],"type":"Point"}
}