{
  "type": "Feature",
  "properties": {
    "gn:admin1_code":"5.0",
    "gn:asciiname":"Xinshengcun",
    "gn:country_code":"CN",
    "gn:dem":353,
    "gn:feature_class":"P",
    "gn:feature_code":"PPL",
    "gn:name":"Xinshengcun",
    "gn:population":0,
    "gn:timezone":"Asia/Shanghai",
    "iso:country":"CN",
    "name:zho_x_preferred":[
        "\u65b0\u80dc\u6751"
    ],
    "wof:name":"Xinshengcun",
    "wof:placetype":"locality"
},
  "geometry": {"coordinates":[125.42142,42.71397],"type":"Point"}
}