{
  "type": "Feature",
  "properties": {
    "gn:admin1_code":"30.0",
    "gn:asciiname":"Xiamatang",
    "gn:country_code":"CN",
    "gn:dem":113,
    "gn:feature_class":"P",
    "gn:feature_code":"PPL",
    "gn:name":"Xiamatang",
    "gn:population":0,
    "gn:timezone":"Asia/Shanghai",
    "iso:country":"CN",
    "name:und_x_variant":[
        "\u4e0b\u9ebb\u5858"
    ],
    "name:zho_x_preferred":[
        "\u4e0b\u9ebb\u5858"
    ],
    "wof:name":"Xiamatang",
    "wof:placetype":"locality"
},
  "geometry": {"coordinates":[115.15651,23.93339],"type":"Point"}
}