{
  "type": "Feature",
  "properties": {
    "gn:admin1_code":"4.0",
    "gn:asciiname":"Dongxiazao",
    "gn:country_code":"CN",
    "gn:dem":0,
    "gn:feature_class":"P",
    "gn:feature_code":"PPL",
    "gn:name":"Dongxiazao",
    "gn:population":0,
    "gn:timezone":"Asia/Shanghai",
    "iso:country":"CN",
    "name:und_x_variant":[
        "\u4e1c\u590f\u7076"
    ],
    "name:zho_x_preferred":[
        "\u4e1c\u590f\u7076"
    ],
    "wof:name":"Dongxiazao",
    "wof:placetype":"locality"
},
  "geometry": {"coordinates":[120.56371,32.93428],"type":"Point"}
}