{
  "type": "Feature",
  "properties": {
    "gn:admin1_code":"5.0",
    "gn:asciiname":"Lazigou",
    "gn:country_code":"CN",
    "gn:dem":257,
    "gn:feature_class":"P",
    "gn:feature_code":"PPL",
    "gn:name":"Lazigou",
    "gn:population":0,
    "gn:timezone":"Asia/Shanghai",
    "iso:country":"CN",
    "name:und_x_variant":[
        "\u782c\u5b50\u6c9f"
    ],
    "wof:name":"Lazigou",
    "wof:placetype":"locality"
},
  "geometry": {"coordinates":[126.10415999999999,41.07981],"type":"Point"}
}