{
  "type": "Feature",
  "properties": {
    "gn:admin1_code":"29.0",
    "gn:asciiname":"Mixiba",
    "gn:country_code":"CN",
    "gn:dem":1598,
    "gn:feature_class":"P",
    "gn:feature_code":"PPL",
    "gn:name":"Mixiba",
    "gn:population":0,
    "gn:timezone":"Asia/Shanghai",
    "iso:country":"CN",
    "name:zho_x_preferred":[
        "\u5bc6\u559c\u5df4"
    ],
    "wof:name":"Mixiba",
    "wof:placetype":"locality"
},
  "geometry": {"coordinates":[99.97920000000001,25.2832],"type":"Point"}
}