{
  "type": "Feature",
  "properties": {
    "gn:admin1_code":"4.0",
    "gn:asciiname":"Jing'an",
    "gn:country_code":"CN",
    "gn:dem":4,
    "gn:feature_class":"P",
    "gn:feature_code":"PPLA4",
    "gn:name":"Jing\u2019an",
    "gn:population":0,
    "gn:timezone":"Asia/Shanghai",
    "iso:country":"CN",
    "name:und_x_variant":[
        "\u9756\u5b89\u9547"
    ],
    "name:zho_x_preferred":[
        "\u9756\u5b89"
    ],
    "name:zho_x_variant":[
        "Jing\u2019an Zhen",
        "Jing\u2019an"
    ],
    "wof:name":"Jing'an",
    "wof:placetype":"locality"
},
  "geometry": {"coordinates":[119.14299,32.22855999999999],"type":"Point"}
}