{
  "type": "Feature",
  "properties": {
    "gn:admin1_code":"18",
    "gn:asciiname":"Heizhikuai",
    "gn:country_code":"CN",
    "gn:dem":2031,
    "gn:feature_class":"P",
    "gn:feature_code":"PPL",
    "gn:name":"Heizhikuai",
    "gn:population":0,
    "gn:timezone":"Asia/Shanghai",
    "iso:country":"CN",
    "name:zho_x_preferred":[
        "\u9ed1\u829d\u5757"
    ],
    "wof:name":"Heizhikuai",
    "wof:placetype":"locality"
},
  "geometry": {"coordinates":[103.76900000000001,27.1412],"type":"Point"}
}