{
  "type": "Feature",
  "properties": {
    "gn:admin1_code":"16",
    "gn:asciiname":"Xiaoduling",
    "gn:country_code":"CN",
    "gn:dem":313,
    "gn:feature_class":"P",
    "gn:feature_code":"PPL",
    "gn:name":"Xiaoduling",
    "gn:population":0,
    "gn:timezone":"Asia/Shanghai",
    "iso:country":"CN",
    "name:zho_x_preferred":[
        "\u5c0f\u809a\u5cad"
    ],
    "wof:name":"Xiaoduling",
    "wof:placetype":"locality"
},
  "geometry": {"coordinates":[111.11199999999999,25.8367],"type":"Point"}
}