{
  "type": "Feature",
  "properties": {
    "gn:admin1_code":"9",
    "gn:asciiname":"Shimutou",
    "gn:country_code":"CN",
    "gn:dem":54,
    "gn:feature_class":"P",
    "gn:feature_code":"PPL",
    "gn:name":"Shimutou",
    "gn:population":0,
    "gn:timezone":"Asia/Shanghai",
    "iso:country":"CN",
    "name:zho_x_preferred":[
        "\u77f3\u6728\u5934"
    ],
    "wof:name":"Shimutou",
    "wof:placetype":"locality"
},
  "geometry": {"coordinates":[115.348,35.6608],"type":"Point"}
}