{
  "type": "Feature",
  "properties": {
    "gn:admin1_code":"1.0",
    "gn:asciiname":"Qiansuncun",
    "gn:country_code":"CN",
    "gn:dem":54,
    "gn:feature_class":"P",
    "gn:feature_code":"PPL",
    "gn:name":"Qiansuncun",
    "gn:population":0,
    "gn:timezone":"Asia/Shanghai",
    "iso:country":"CN",
    "name:zho_x_preferred":[
        "\u524d\u5b59\u6751"
    ],
    "wof:name":"Qiansuncun",
    "wof:placetype":"locality"
},
  "geometry": {"coordinates":[117.54586,32.37042],"type":"Point"}
}