{
  "type": "Feature",
  "properties": {
    "gn:admin1_code":"3.0",
    "gn:asciiname":"Liangkou",
    "gn:country_code":"CN",
    "gn:dem":553,
    "gn:feature_class":"P",
    "gn:feature_code":"PPL",
    "gn:name":"Liangkou",
    "gn:population":0,
    "gn:timezone":"Asia/Shanghai",
    "iso:country":"CN",
    "name:und_x_variant":[
        "\u6881\u53e3"
    ],
    "wof:name":"Liangkou",
    "wof:placetype":"locality"
},
  "geometry": {"coordinates":[114.35026000000001,29.23051],"type":"Point"}
}