{
  "type": "Feature",
  "properties": {
    "gn:admin1_code":"26.0",
    "gn:asciiname":"Wayaoping",
    "gn:country_code":"CN",
    "gn:dem":1220,
    "gn:feature_class":"P",
    "gn:feature_code":"PPL",
    "gn:name":"Wayaoping",
    "gn:population":0,
    "gn:timezone":"Asia/Shanghai",
    "iso:country":"CN",
    "name:und_x_variant":[
        "\u74e6\u7a91\u576a"
    ],
    "wof:name":"Wayaoping",
    "wof:placetype":"locality"
},
  "geometry": {"coordinates":[106.95621,33.88456],"type":"Point"}
}