{
  "type": "Feature",
  "properties": {
    "gn:admin1_code":"10.0",
    "gn:asciiname":"Nanzhuang",
    "gn:country_code":"CN",
    "gn:dem":225,
    "gn:feature_class":"P",
    "gn:feature_code":"PPL",
    "gn:name":"Nanzhuang",
    "gn:population":0,
    "gn:timezone":"Asia/Shanghai",
    "iso:country":"CN",
    "name:fra_x_preferred":[
        "Nanzhuang"
    ],
    "name:hak_x_preferred":[
        "N\u00e0m-ch\u00f4ng-hi\u00f4ng"
    ],
    "name:jpn_x_preferred":[
        "\u5357\u5e84\u90f7"
    ],
    "name:kor_x_preferred":[
        "\ub09c\uc8a1\ud5a5"
    ],
    "name:und_x_variant":[
        "\u5357\u5e84"
    ],
    "name:vie_x_preferred":[
        "Nam Trang"
    ],
    "name:zho_x_preferred":[
        "\u5357\u5e84\u9109"
    ],
    "wof:name":"Nanzhuang",
    "wof:placetype":"locality"
},
  "geometry": {"coordinates":[114.19308999999998,38.45438],"type":"Point"}
}