{
  "type": "Feature",
  "properties": {
    "gn:admin1_code":"32.0",
    "gn:asciiname":"Sanwangmiao",
    "gn:country_code":"CN",
    "gn:dem":728,
    "gn:feature_class":"P",
    "gn:feature_code":"PPL",
    "gn:name":"Sanwangmiao",
    "gn:population":0,
    "gn:timezone":"Asia/Shanghai",
    "iso:country":"CN",
    "name:zho_x_preferred":[
        "\u4e09\u738b\u5e99"
    ],
    "wof:name":"Sanwangmiao",
    "wof:placetype":"locality"
},
  "geometry": {"coordinates":[103.41983999999999,29.78623],"type":"Point"}
}