{
  "type": "Feature",
  "properties": {
    "gn:admin1_code":"15.0",
    "gn:asciiname":"Liangshuiya",
    "gn:country_code":"CN",
    "gn:dem":1212,
    "gn:feature_class":"P",
    "gn:feature_code":"PPL",
    "gn:name":"Liangshuiya",
    "gn:population":0,
    "gn:timezone":"Asia/Shanghai",
    "iso:country":"CN",
    "name:und_x_variant":[
        "\u4e24\u6c34\u5d16"
    ],
    "wof:name":"Liangshuiya",
    "wof:placetype":"locality"
},
  "geometry": {"coordinates":[105.74395,33.40162],"type":"Point"}
}