{
  "type": "Feature",
  "properties": {
    "gn:admin1_code":"32.0",
    "gn:asciiname":"Chenjiazui",
    "gn:country_code":"CN",
    "gn:dem":654,
    "gn:feature_class":"P",
    "gn:feature_code":"PPL",
    "gn:name":"Chenjiazui",
    "gn:population":0,
    "gn:timezone":"Asia/Shanghai",
    "iso:country":"CN",
    "name:zho_x_preferred":[
        "\u9648\u5bb6\u5480"
    ],
    "wof:name":"Chenjiazui",
    "wof:placetype":"locality"
},
  "geometry": {"coordinates":[104.881,31.9601],"type":"Point"}
}