{
  "type": "Feature",
  "properties": {
    "gn:admin1_code":"15",
    "gn:asciiname":"Chankou",
    "gn:cc2":"CN",
    "gn:country_code":"CN",
    "gn:dem":1833,
    "gn:feature_class":"P",
    "gn:feature_code":"PPL",
    "gn:name":"Chankou",
    "gn:population":0,
    "gn:timezone":"Asia/Shanghai",
    "iso:country":"CN",
    "name:und_x_variant":[
        "Tsch\u2019an-k\u2019ou",
        "Chankou"
    ],
    "wof:name":"Chankou",
    "wof:placetype":"locality"
},
  "geometry": {"coordinates":[104.52194,35.71222],"type":"Point"}
}