{
  "type": "Feature",
  "properties": {
    "gn:admin1_code":"32.0",
    "gn:asciiname":"Daniuchang",
    "gn:country_code":"CN",
    "gn:dem":3274,
    "gn:feature_class":"P",
    "gn:feature_code":"PPLF",
    "gn:name":"Daniuchang",
    "gn:population":0,
    "gn:timezone":"Asia/Shanghai",
    "iso:country":"CN",
    "name:zho_x_preferred":[
        "\u5927\u725b\u573a"
    ],
    "wof:name":"Daniuchang",
    "wof:placetype":"locality"
},
  "geometry": {"coordinates":[103.48399999999999,31.6106],"type":"Point"}
}