{
  "type": "Feature",
  "properties": {
    "gn:admin1_code":"29",
    "gn:asciiname":"Daliantang",
    "gn:country_code":"CN",
    "gn:dem":1167,
    "gn:feature_class":"P",
    "gn:feature_code":"PPL",
    "gn:name":"Daliantang",
    "gn:population":0,
    "gn:timezone":"Asia/Shanghai",
    "iso:country":"CN",
    "name:zho_x_preferred":[
        "\u8fbe\u8fde\u5858"
    ],
    "wof:name":"Daliantang",
    "wof:placetype":"locality"
},
  "geometry": {"coordinates":[105.083,24.1254],"type":"Point"}
}