{
  "type": "Feature",
  "properties": {
    "gn:admin1_code":"14.0",
    "gn:asciiname":"Ruobaze",
    "gn:country_code":"CN",
    "gn:dem":4585,
    "gn:feature_class":"P",
    "gn:feature_code":"PPL",
    "gn:name":"Ruobaze",
    "gn:population":0,
    "gn:timezone":"Asia/Urumqi",
    "iso:country":"CN",
    "name:zho_x_preferred":[
        "\u82e5\u5df4\u5219"
    ],
    "wof:name":"Ruobaze",
    "wof:placetype":"locality"
},
  "geometry": {"coordinates":[94.18317,31.16162000000001],"type":"Point"}
}