{
  "type": "Feature",
  "properties": {
    "gn:admin1_code":"26",
    "gn:asciiname":"Nanzhai",
    "gn:country_code":"CN",
    "gn:dem":398,
    "gn:feature_class":"P",
    "gn:feature_code":"PPL",
    "gn:name":"Nanzhai",
    "gn:population":0,
    "gn:timezone":"Asia/Shanghai",
    "iso:country":"CN",
    "name:zho_x_preferred":[
        "\u5357\u5be8"
    ],
    "wof:name":"Nanzhai",
    "wof:placetype":"locality"
},
  "geometry": {"coordinates":[108.64028,34.27889],"type":"Point"}
}