{
  "type": "Feature",
  "properties": {
    "gn:admin1_code":"16.0",
    "gn:asciiname":"Dingban",
    "gn:country_code":"CN",
    "gn:dem":111,
    "gn:feature_class":"P",
    "gn:feature_code":"PPL",
    "gn:name":"Dingban",
    "gn:population":0,
    "gn:timezone":"Asia/Shanghai",
    "iso:country":"CN",
    "name:zho_x_preferred":[
        "\u5b9a\u677f"
    ],
    "wof:name":"Dingban",
    "wof:placetype":"locality"
},
  "geometry": {"coordinates":[109.119,23.34800000000001],"type":"Point"}
}