{
  "type": "Feature",
  "properties": {
    "gn:admin1_code":"11.0",
    "gn:asciiname":"Jieli",
    "gn:country_code":"CN",
    "gn:dem":195,
    "gn:feature_class":"P",
    "gn:feature_code":"PPL",
    "gn:name":"Jieli",
    "gn:population":0,
    "gn:timezone":"Asia/Shanghai",
    "iso:country":"CN",
    "name:zho_x_preferred":[
        "\u754c\u91cc"
    ],
    "wof:name":"Jieli",
    "wof:placetype":"locality"
},
  "geometry": {"coordinates":[113.84404000000001,27.00734000000001],"type":"Point"}
}