{
  "type": "Feature",
  "properties": {
    "gn:admin1_code":"4.0",
    "gn:asciiname":"Liulin",
    "gn:country_code":"CN",
    "gn:dem":11,
    "gn:feature_class":"P",
    "gn:feature_code":"PPL",
    "gn:name":"Liulin",
    "gn:population":0,
    "gn:timezone":"Asia/Shanghai",
    "iso:country":"CN",
    "name:zho_x_preferred":[
        "\u5218\u6797"
    ],
    "wof:name":"Liulin",
    "wof:placetype":"locality"
},
  "geometry": {"coordinates":[118.75557000000001,32.31446],"type":"Point"}
}