{
  "type": "Feature",
  "properties": {
    "gn:admin1_code":"15.0",
    "gn:asciiname":"Dazhanghe",
    "gn:country_code":"CN",
    "gn:dem":939,
    "gn:feature_class":"P",
    "gn:feature_code":"PPL",
    "gn:name":"Dazhanghe",
    "gn:population":0,
    "gn:timezone":"Asia/Shanghai",
    "iso:country":"CN",
    "name:und_x_variant":[
        "\u5927\u5f20\u5408"
    ],
    "wof:name":"Dazhanghe",
    "wof:placetype":"locality"
},
  "geometry": {"coordinates":[105.49169999999999,33.60172],"type":"Point"}
}