{
  "type": "Feature",
  "properties": {
    "gn:country":"CN",
    "gn:fcode":"PPL",
    "gn:pop":1110,
    "iso:country":"CN",
    "name:unk_x_variant":[
        "Sang-mu-ch\u2019ang"
    ],
    "name:zho_x_preferred":[
        "\u6851\u6728"
    ],
    "name:zho_x_variant":[
        "\u6851\u6728\u9547"
    ],
    "qs:name":"Sangmu",
    "qs:photos_9r":0,
    "qs:photos_sr":0,
    "qs:pop_sr":"3",
    "wof:name":"Sangmu",
    "wof:placetype":"locality",
    "wof:population":1110
},
  "geometry": {"coordinates":[106.26889,28.21528],"type":"Point"}
}