{
  "type": "Feature",
  "properties": {
    "gn:admin1_code":"7.0",
    "gn:asciiname":"Duiziqian",
    "gn:country_code":"CN",
    "gn:dem":189,
    "gn:feature_class":"P",
    "gn:feature_code":"PPL",
    "gn:name":"Duiziqian",
    "gn:population":0,
    "gn:timezone":"Asia/Shanghai",
    "iso:country":"CN",
    "name:zho_x_preferred":[
        "\u7893\u4ed4\u524d"
    ],
    "wof:name":"Duiziqian",
    "wof:placetype":"locality"
},
  "geometry": {"coordinates":[118.74402000000001,27.32731],"type":"Point"}
}