{
  "type": "Feature",
  "properties": {
    "gn:admin1_code":"2.0",
    "gn:asciiname":"Suoyitian",
    "gn:country_code":"CN",
    "gn:dem":817,
    "gn:feature_class":"P",
    "gn:feature_code":"PPL",
    "gn:name":"Suoyitian",
    "gn:population":0,
    "gn:timezone":"Asia/Shanghai",
    "iso:country":"CN",
    "name:zho_x_preferred":[
        "\u84d1\u8863\u7530"
    ],
    "wof:name":"Suoyitian",
    "wof:placetype":"locality"
},
  "geometry": {"coordinates":[120.29824000000001,28.18397],"type":"Point"}
}