{
  "type": "Feature",
  "properties": {
    "gn:admin1_code":"04",
    "gn:asciiname":"Dayou",
    "gn:country_code":"CN",
    "gn:dem":2,
    "gn:feature_class":"P",
    "gn:feature_code":"PPLA4",
    "gn:name":"Dayou",
    "gn:population":0,
    "gn:timezone":"Asia/Shanghai",
    "iso:country":"CN",
    "name:und_x_variant":[
        "Li Y\u00fc",
        "Dayu",
        "Ta-yu",
        "Dayou",
        "\u5927\u6709",
        "Dayou Zhen",
        "\u5927\u6709\u9547"
    ],
    "wof:name":"Dayou",
    "wof:placetype":"locality"
},
  "geometry": {"coordinates":[119.88111000000001,34.22056],"type":"Point"}
}