{
  "type": "Feature",
  "properties": {
    "gn:admin1_code":"18",
    "gn:asciiname":"Daobashui",
    "gn:country_code":"CN",
    "gn:dem":932,
    "gn:feature_class":"P",
    "gn:feature_code":"PPL",
    "gn:name":"Daobashui",
    "gn:population":0,
    "gn:timezone":"Asia/Shanghai",
    "iso:country":"CN",
    "name:und_x_variant":[
        "Tao-pa-shui",
        "Daoba",
        "Daobashui"
    ],
    "name:zho_x_preferred":[
        "\u5200\u9776"
    ],
    "wof:name":"Daobashui",
    "wof:placetype":"locality"
},
  "geometry": {"coordinates":[106.75,27.3702],"type":"Point"}
}