{
  "type": "Feature",
  "properties": {
    "gn:admin1_code":"30",
    "gn:asciiname":"Zhaoshi",
    "gn:country_code":"CN",
    "gn:dem":200,
    "gn:feature_class":"P",
    "gn:feature_code":"PPL",
    "gn:name":"Zhaoshi",
    "gn:population":0,
    "gn:timezone":"Asia/Shanghai",
    "iso:country":"CN",
    "name:und_x_variant":[
        "Zhaoshi"
    ],
    "name:zho_x_preferred":[
        "\u627e\u77f3"
    ],
    "wof:name":"Zhaoshi",
    "wof:placetype":"locality"
},
  "geometry": {"coordinates":[115.56009,24.19445],"type":"Point"}
}