{
  "type": "Feature",
  "properties": {
    "gn:admin1_code":"1.0",
    "gn:asciiname":"Tuolingcun",
    "gn:country_code":"CN",
    "gn:dem":840,
    "gn:feature_class":"P",
    "gn:feature_code":"PPL",
    "gn:name":"Tuolingcun",
    "gn:population":0,
    "gn:timezone":"Asia/Shanghai",
    "iso:country":"CN",
    "name:zho_x_preferred":[
        "\u9a7c\u5cad\u6751"
    ],
    "wof:name":"Tuolingcun",
    "wof:placetype":"locality"
},
  "geometry": {"coordinates":[116.58704,31.06686],"type":"Point"}
}