{
  "type": "Feature",
  "properties": {
    "gn:admin1_code":"18",
    "gn:asciiname":"Anjiazhai",
    "gn:country_code":"CN",
    "gn:dem":935,
    "gn:feature_class":"P",
    "gn:feature_code":"PPL",
    "gn:name":"Anjiazhai",
    "gn:population":0,
    "gn:timezone":"Asia/Shanghai",
    "iso:country":"CN",
    "name:zho_x_preferred":[
        "\u5b89\u5bb6\u5be8"
    ],
    "wof:name":"Anjiazhai",
    "wof:placetype":"locality"
},
  "geometry": {"coordinates":[107.714,27.7356],"type":"Point"}
}