{
  "type": "Feature",
  "properties": {
    "gn:admin1_code":"11",
    "gn:asciiname":"Guiziqiao",
    "gn:country_code":"CN",
    "gn:dem":88,
    "gn:feature_class":"P",
    "gn:feature_code":"PPL",
    "gn:name":"Guiziqiao",
    "gn:population":0,
    "gn:timezone":"Asia/Shanghai",
    "iso:country":"CN",
    "name:zho_x_preferred":[
        "\u6842\u5b50\u6865"
    ],
    "wof:name":"Guiziqiao",
    "wof:placetype":"locality"
},
  "geometry": {"coordinates":[112.21259000000001,26.40281],"type":"Point"}
}