{
  "type": "Feature",
  "properties": {
    "gn:admin1_code":"3",
    "gn:asciiname":"Aizi",
    "gn:country_code":"CN",
    "gn:dem":133,
    "gn:feature_class":"P",
    "gn:feature_code":"PPL",
    "gn:name":"Aizi",
    "gn:population":0,
    "gn:timezone":"Asia/Shanghai",
    "iso:country":"CN",
    "name:fra_x_preferred":[
        "A\u00efzi"
    ],
    "name:zho_x_preferred":[
        "\u9698\u5b5c"
    ],
    "wof:name":"Aizi",
    "wof:placetype":"locality"
},
  "geometry": {"coordinates":[114.74327,25.86869],"type":"Point"}
}