{
  "type": "Feature",
  "properties": {
    "gn:admin1_code":"32.0",
    "gn:asciiname":"Kaiyuan",
    "gn:country_code":"CN",
    "gn:dem":516,
    "gn:feature_class":"P",
    "gn:feature_code":"PPL",
    "gn:name":"Kaiyuan",
    "gn:population":0,
    "gn:timezone":"Asia/Shanghai",
    "iso:country":"CN",
    "name:zho_x_preferred":[
        "\u5f00\u56ed"
    ],
    "wof:name":"Kaiyuan",
    "wof:placetype":"locality"
},
  "geometry": {"coordinates":[104.009,30.1258],"type":"Point"}
}