{
  "type": "Feature",
  "properties": {
    "gn:admin1_code":"30",
    "gn:asciiname":"Jiaobei",
    "gn:country_code":"CN",
    "gn:dem":46,
    "gn:feature_class":"P",
    "gn:feature_code":"PPL",
    "gn:name":"Jiaobei",
    "gn:population":0,
    "gn:timezone":"Asia/Shanghai",
    "iso:country":"CN",
    "name:fin_x_preferred":[
        "Jiaobei"
    ],
    "name:zho_x_preferred":[
        "\u89d2\u80cc"
    ],
    "wof:name":"Jiaobei",
    "wof:placetype":"locality"
},
  "geometry": {"coordinates":[114.25,23.29333],"type":"Point"}
}