{
  "type": "Feature",
  "properties": {
    "gn:admin1_code":"4.0",
    "gn:asciiname":"Qiaoxiangcun",
    "gn:country_code":"CN",
    "gn:dem":6,
    "gn:feature_class":"P",
    "gn:feature_code":"PPL",
    "gn:name":"Qiaoxiangcun",
    "gn:population":0,
    "gn:timezone":"Asia/Shanghai",
    "iso:country":"CN",
    "name:und_x_variant":[
        "\u4e54\u5df7\u6751"
    ],
    "name:zho_x_preferred":[
        "\u4e54\u5df7\u6751"
    ],
    "wof:name":"Qiaoxiangcun",
    "wof:placetype":"locality"
},
  "geometry": {"coordinates":[120.50045,31.6432],"type":"Point"}
}