{
  "type": "Feature",
  "properties": {
    "gn:admin1_code":"12.0",
    "gn:asciiname":"Panjiaya",
    "gn:country_code":"CN",
    "gn:dem":579,
    "gn:feature_class":"P",
    "gn:feature_code":"PPL",
    "gn:name":"Panjiaya",
    "gn:population":0,
    "gn:timezone":"Asia/Shanghai",
    "iso:country":"CN",
    "name:zho_x_preferred":[
        "\u6f58\u5bb6\u57ad"
    ],
    "wof:name":"Panjiaya",
    "wof:placetype":"locality"
},
  "geometry": {"coordinates":[111.7869,31.43336],"type":"Point"}
}