{
  "type": "Feature",
  "properties": {
    "gn:admin1_code":"12.0",
    "gn:asciiname":"Wansi",
    "gn:country_code":"CN",
    "gn:dem":1392,
    "gn:feature_class":"P",
    "gn:feature_code":"PPL",
    "gn:name":"Wansi",
    "gn:population":0,
    "gn:timezone":"Asia/Shanghai",
    "iso:country":"CN",
    "name:zho_x_preferred":[
        "Wansi"
    ],
    "name:zho_x_variant":[
        "\u4e07\u5bfa"
    ],
    "wof:name":"Wansi",
    "wof:placetype":"locality"
},
  "geometry": {"coordinates":[110.55579,29.81557],"type":"Point"}
}