{
  "type": "Feature",
  "properties": {
    "gn:admin1_code":"29",
    "gn:asciiname":"Xikezhang",
    "gn:country_code":"CN",
    "gn:dem":1715,
    "gn:feature_class":"P",
    "gn:feature_code":"PPL",
    "gn:name":"Xikezhang",
    "gn:population":0,
    "gn:timezone":"Asia/Shanghai",
    "iso:country":"CN",
    "name:zho_x_preferred":[
        "\u4e60\u514b\u4e08"
    ],
    "wof:name":"Xikezhang",
    "wof:placetype":"locality"
},
  "geometry": {"coordinates":[103.208,24.6334],"type":"Point"}
}