{
  "type": "Feature",
  "properties": {
    "gn:admin1_code":"14.0",
    "gn:asciiname":"Depo",
    "gn:country_code":"CN",
    "gn:dem":3834,
    "gn:feature_class":"P",
    "gn:feature_code":"PPL",
    "gn:name":"Depo",
    "gn:population":0,
    "gn:timezone":"Asia/Urumqi",
    "iso:country":"CN",
    "name:zho_x_preferred":[
        "\u5fb7\u5761"
    ],
    "wof:name":"Depo",
    "wof:placetype":"locality"
},
  "geometry": {"coordinates":[95.82924,30.67807],"type":"Point"}
}