{
  "type": "Feature",
  "properties": {
    "gn:admin1_code":"29.0",
    "gn:asciiname":"Lachu",
    "gn:country_code":"CN",
    "gn:dem":2282,
    "gn:feature_class":"P",
    "gn:feature_code":"PPL",
    "gn:name":"Lachu",
    "gn:population":0,
    "gn:timezone":"Asia/Shanghai",
    "iso:country":"CN",
    "name:zho_x_preferred":[
        "\u814a\u5904"
    ],
    "wof:name":"Lachu",
    "wof:placetype":"locality"
},
  "geometry": {"coordinates":[103.80200000000001,24.9658],"type":"Point"}
}