{
  "type": "Feature",
  "properties": {
    "gn:admin1_code":"11.0",
    "gn:asciiname":"Dafuxi",
    "gn:country_code":"CN",
    "gn:dem":470,
    "gn:feature_class":"P",
    "gn:feature_code":"PPL",
    "gn:name":"Dafuxi",
    "gn:population":0,
    "gn:timezone":"Asia/Shanghai",
    "iso:country":"CN",
    "name:zho_x_preferred":[
        "Dafuxi"
    ],
    "name:zho_x_variant":[
        "\u5927\u798f\u6eaa"
    ],
    "wof:name":"Dafuxi",
    "wof:placetype":"locality"
},
  "geometry": {"coordinates":[114.00543999999999,28.56551],"type":"Point"}
}