{
  "type": "Feature",
  "properties": {
    "gn:admin1_code":"12.0",
    "gn:asciiname":"Mianyangdong",
    "gn:country_code":"CN",
    "gn:dem":1032,
    "gn:feature_class":"P",
    "gn:feature_code":"PPL",
    "gn:name":"Mianyangdong",
    "gn:population":0,
    "gn:timezone":"Asia/Shanghai",
    "iso:country":"CN",
    "name:zho_x_preferred":[
        "Mianyangdong"
    ],
    "name:zho_x_variant":[
        "\u7ef5\u7f8a\u6d1e"
    ],
    "wof:name":"Mianyangdong",
    "wof:placetype":"locality"
},
  "geometry": {"coordinates":[109.04656,29.85326],"type":"Point"}
}