{
  "type": "Feature",
  "properties": {
    "gn:admin1_code":"14.0",
    "gn:asciiname":"Kugka Lhai",
    "gn:country_code":"CN",
    "gn:dem":4565,
    "gn:feature_class":"P",
    "gn:feature_code":"PPL",
    "gn:name":"Kugka Lhai",
    "gn:population":0,
    "gn:timezone":"Asia/Urumqi",
    "iso:country":"CN",
    "name:bod_x_preferred":[
        "Kugka Lhai"
    ],
    "wof:name":"Kugka Lhai",
    "wof:placetype":"locality"
},
  "geometry": {"coordinates":[88.33333,31.98333],"type":"Point"}
}