{
  "type": "Feature",
  "properties": {
    "gn:admin1_code":"2.0",
    "gn:asciiname":"Yusi",
    "gn:country_code":"CN",
    "gn:dem":161,
    "gn:feature_class":"P",
    "gn:feature_code":"PPL",
    "gn:name":"Yusi",
    "gn:population":0,
    "gn:timezone":"Asia/Shanghai",
    "iso:country":"CN",
    "name:zho_x_preferred":[
        "\u55bb\u65af"
    ],
    "wof:name":"Yusi",
    "wof:placetype":"locality"
},
  "geometry": {"coordinates":[119.69392000000001,28.94297000000001],"type":"Point"}
}