{
  "type": "Feature",
  "properties": {
    "gn:admin1_code":"19.0",
    "gn:asciiname":"Wangjiawobucun",
    "gn:country_code":"CN",
    "gn:dem":171,
    "gn:feature_class":"P",
    "gn:feature_code":"PPL",
    "gn:name":"Wangjiawobucun",
    "gn:population":0,
    "gn:timezone":"Asia/Shanghai",
    "iso:country":"CN",
    "name:zho_x_preferred":[
        "\u738b\u5bb6\u7a9d\u5821\u6751"
    ],
    "wof:name":"Wangjiawobucun",
    "wof:placetype":"locality"
},
  "geometry": {"coordinates":[122.655,42.6446],"type":"Point"}
}