{
  "type": "Feature",
  "properties": {
    "gn:admin1_code":"14.0",
    "gn:asciiname":"Kyangmartang",
    "gn:country_code":"CN",
    "gn:dem":5143,
    "gn:feature_class":"P",
    "gn:feature_code":"PPL",
    "gn:name":"Kyangmartang",
    "gn:population":0,
    "gn:timezone":"Asia/Urumqi",
    "iso:country":"CN",
    "name:bod_x_preferred":[
        "Kyangmartang"
    ],
    "name:zho_x_preferred":[
        "Qiangmatang"
    ],
    "name:zho_x_variant":[
        "\u5f3a\u9a6c\u5858"
    ],
    "wof:name":"Kyangmartang",
    "wof:placetype":"locality"
},
  "geometry": {"coordinates":[97.401,30.001],"type":"Point"}
}