{
  "type": "Feature",
  "properties": {
    "gn:admin1_code":"3.0",
    "gn:asciiname":"Mingjialun",
    "gn:country_code":"CN",
    "gn:dem":368,
    "gn:feature_class":"P",
    "gn:feature_code":"PPL",
    "gn:name":"Mingjialun",
    "gn:population":0,
    "gn:timezone":"Asia/Shanghai",
    "iso:country":"CN",
    "name:und_x_variant":[
        "\u660e\u5bb6\u4ed1"
    ],
    "wof:name":"Mingjialun",
    "wof:placetype":"locality"
},
  "geometry": {"coordinates":[115.01509,29.11832],"type":"Point"}
}