{
  "type": "Feature",
  "properties": {
    "gn:admin1_code":"11.0",
    "gn:asciiname":"Dapu",
    "gn:country_code":"CN",
    "gn:dem":51,
    "gn:feature_class":"P",
    "gn:feature_code":"PPL",
    "gn:name":"Dapu",
    "gn:population":0,
    "gn:timezone":"Asia/Shanghai",
    "iso:country":"CN",
    "name:ceb_x_preferred":[
        "Dapu"
    ],
    "name:swe_x_preferred":[
        "Dapu"
    ],
    "name:zho_x_preferred":[
        "\u5927\u94fa"
    ],
    "wof:name":"Dapu",
    "wof:placetype":"locality"
},
  "geometry": {"coordinates":[112.66199,26.59107],"type":"Point"}
}