{
  "type": "Feature",
  "properties": {
    "gn:admin1_code":"26.0",
    "gn:asciiname":"Xialubucun",
    "gn:country_code":"CN",
    "gn:dem":1052,
    "gn:feature_class":"P",
    "gn:feature_code":"PPL",
    "gn:name":"Xialubucun",
    "gn:population":0,
    "gn:timezone":"Asia/Shanghai",
    "iso:country":"CN",
    "name:zho_x_preferred":[
        "\u4e0b\u82a6\u5821\u6751"
    ],
    "wof:name":"Xialubucun",
    "wof:placetype":"locality"
},
  "geometry": {"coordinates":[108.21080000000001,34.90179000000001],"type":"Point"}
}