{
  "type": "Feature",
  "properties": {
    "gn:admin1_code":"11.0",
    "gn:asciiname":"Tanglongjie",
    "gn:country_code":"CN",
    "gn:dem":752,
    "gn:feature_class":"P",
    "gn:feature_code":"PPL",
    "gn:name":"Tanglongjie",
    "gn:population":0,
    "gn:timezone":"Asia/Shanghai",
    "iso:country":"CN",
    "name:zho_x_preferred":[
        "\u5858\u9f99\u754c"
    ],
    "wof:name":"Tanglongjie",
    "wof:placetype":"locality"
},
  "geometry": {"coordinates":[110.77536000000001,27.31958],"type":"Point"}
}