{
  "type": "Feature",
  "properties": {
    "gn:admin1_code":"9.0",
    "gn:asciiname":"Chenzhouying",
    "gn:country_code":"CN",
    "gn:dem":42,
    "gn:feature_class":"P",
    "gn:feature_code":"PPL",
    "gn:name":"Chenzhouying",
    "gn:population":0,
    "gn:timezone":"Asia/Shanghai",
    "iso:country":"CN",
    "name:zho_x_preferred":[
        "\u9648\u5dde\u8425"
    ],
    "wof:name":"Chenzhouying",
    "wof:placetype":"locality"
},
  "geometry": {"coordinates":[114.96554,33.3629],"type":"Point"}
}