{
  "type": "Feature",
  "properties": {
    "gn:admin1_code":"23.0",
    "gn:asciiname":"Guanjiatang",
    "gn:country_code":"CN",
    "gn:dem":7,
    "gn:feature_class":"P",
    "gn:feature_code":"PPL",
    "gn:name":"Guanjiatang",
    "gn:population":0,
    "gn:timezone":"Asia/Shanghai",
    "iso:country":"CN",
    "name:und_x_variant":[
        "\u7ba1\u5bb6\u5802"
    ],
    "wof:name":"Guanjiatang",
    "wof:placetype":"locality"
},
  "geometry": {"coordinates":[121.44534,30.93996],"type":"Point"}
}