{
  "type": "Feature",
  "properties": {
    "gn:admin1_code":"30.0",
    "gn:asciiname":"Shaguli",
    "gn:country_code":"CN",
    "gn:dem":3,
    "gn:feature_class":"P",
    "gn:feature_code":"PPL",
    "gn:name":"Shaguli",
    "gn:population":0,
    "gn:timezone":"Asia/Shanghai",
    "iso:country":"CN",
    "name:zho_x_preferred":[
        "\u6c99\u53e4\u575c"
    ],
    "wof:name":"Shaguli",
    "wof:placetype":"locality"
},
  "geometry": {"coordinates":[115.56214,22.85342],"type":"Point"}
}