{
  "type": "Feature",
  "properties": {
    "gn:admin1_code":"12.0",
    "gn:asciiname":"Zhuzhihai",
    "gn:country_code":"CN",
    "gn:dem":45,
    "gn:feature_class":"P",
    "gn:feature_code":"PPL",
    "gn:name":"Zhuzhihai",
    "gn:population":0,
    "gn:timezone":"Asia/Shanghai",
    "iso:country":"CN",
    "name:und_x_variant":[
        "\u7af9\u679d\u6d77"
    ],
    "wof:name":"Zhuzhihai",
    "wof:placetype":"locality"
},
  "geometry": {"coordinates":[114.69055,30.11233],"type":"Point"}
}