{
  "type": "Feature",
  "properties": {
    "gn:admin1_code":"4.0",
    "gn:asciiname":"Zhangjialitou",
    "gn:country_code":"CN",
    "gn:dem":7,
    "gn:feature_class":"P",
    "gn:feature_code":"PPL",
    "gn:name":"Zhangjialitou",
    "gn:population":0,
    "gn:timezone":"Asia/Shanghai",
    "iso:country":"CN",
    "name:zho_x_preferred":[
        "\u5f20\u5bb6\u91cc\u5934"
    ],
    "wof:name":"Zhangjialitou",
    "wof:placetype":"locality"
},
  "geometry": {"coordinates":[119.97758,32.11833],"type":"Point"}
}