{
  "type": "Feature",
  "properties": {
    "gn:admin1_code":"29.0",
    "gn:asciiname":"Peng'ercun",
    "gn:country_code":"CN",
    "gn:dem":1154,
    "gn:feature_class":"P",
    "gn:feature_code":"PPL",
    "gn:name":"Peng\u2019ercun",
    "gn:population":0,
    "gn:timezone":"Asia/Shanghai",
    "iso:country":"CN",
    "name:und_x_variant":[
        "Peng\u2019ercun"
    ],
    "name:zho_x_preferred":[
        "\u670b\u4e8c\u6751"
    ],
    "wof:name":"Peng'ercun",
    "wof:placetype":"locality"
},
  "geometry": {"coordinates":[103.348,23.9611],"type":"Point"}
}