{
  "type": "Feature",
  "properties": {
    "gn:admin1_code":"2.0",
    "gn:asciiname":"Chelutou",
    "gn:country_code":"CN",
    "gn:dem":23,
    "gn:feature_class":"P",
    "gn:feature_code":"PPL",
    "gn:name":"Chelutou",
    "gn:population":0,
    "gn:timezone":"Asia/Shanghai",
    "iso:country":"CN",
    "name:zho_x_preferred":[
        "\u8f66\u8def\u5934"
    ],
    "wof:name":"Chelutou",
    "wof:placetype":"locality"
},
  "geometry": {"coordinates":[121.22028,28.83505],"type":"Point"}
}