{
  "type": "Feature",
  "properties": {
    "gn:admin1_code":"29.0",
    "gn:asciiname":"Changpuchang",
    "gn:country_code":"CN",
    "gn:dem":1775,
    "gn:feature_class":"P",
    "gn:feature_code":"PPL",
    "gn:name":"Changpuchang",
    "gn:population":0,
    "gn:timezone":"Asia/Shanghai",
    "iso:country":"CN",
    "name:zho_x_preferred":[
        "\u83d6\u84b2\u573a"
    ],
    "wof:name":"Changpuchang",
    "wof:placetype":"locality"
},
  "geometry": {"coordinates":[99.776,25.9858],"type":"Point"}
}