{
  "type": "Feature",
  "properties": {
    "gn:admin1_code":"32.0",
    "gn:asciiname":"Zelongtong",
    "gn:country_code":"CN",
    "gn:dem":3907,
    "gn:feature_class":"P",
    "gn:feature_code":"PPL",
    "gn:name":"Zelongtong",
    "gn:population":0,
    "gn:timezone":"Asia/Shanghai",
    "iso:country":"CN",
    "name:zho_x_preferred":[
        "\u5219\u9686\u901a"
    ],
    "wof:name":"Zelongtong",
    "wof:placetype":"locality"
},
  "geometry": {"coordinates":[100.65018999999999,30.88397],"type":"Point"}
}