{
  "type": "Feature",
  "properties": {
    "gn:admin1_code":"19.0",
    "gn:asciiname":"Zhong?tun",
    "gn:country_code":"CN",
    "gn:dem":129,
    "gn:feature_class":"P",
    "gn:feature_code":"PPL",
    "gn:name":"Zhong\uff1ftun",
    "gn:population":0,
    "gn:timezone":"Asia/Shanghai",
    "iso:country":"CN",
    "name:und_x_variant":[
        "Zhong\uff1ftun",
        "\u4e2d\uff1f\u5c6f"
    ],
    "wof:name":"Zhong?tun",
    "wof:placetype":"locality"
},
  "geometry": {"coordinates":[122.73716,40.60024],"type":"Point"}
}