{
  "type": "Feature",
  "properties": {
    "gn:admin1_code":"21.0",
    "gn:asciiname":"Haoziwan",
    "gn:country_code":"CN",
    "gn:dem":2061,
    "gn:feature_class":"P",
    "gn:feature_code":"PPL",
    "gn:name":"Haoziwan",
    "gn:population":0,
    "gn:timezone":"Asia/Shanghai",
    "iso:country":"CN",
    "name:und_x_variant":[
        "\u84bf\u5b50\u6e7e"
    ],
    "name:zho_x_preferred":[
        "\u84bf\u5b50\u6e7e"
    ],
    "wof:name":"Haoziwan",
    "wof:placetype":"locality"
},
  "geometry": {"coordinates":[105.5765,36.00189],"type":"Point"}
}