{
  "type": "Feature",
  "properties": {
    "gn:admin1_code":"1.0",
    "gn:asciiname":"Tanlingcun",
    "gn:country_code":"CN",
    "gn:dem":136,
    "gn:feature_class":"P",
    "gn:feature_code":"PPL",
    "gn:name":"Tanlingcun",
    "gn:population":0,
    "gn:timezone":"Asia/Shanghai",
    "iso:country":"CN",
    "name:zho_x_preferred":[
        "\u8c2d\u5cad\u6751"
    ],
    "wof:name":"Tanlingcun",
    "wof:placetype":"locality"
},
  "geometry": {"coordinates":[116.83475,31.22222],"type":"Point"}
}