{
  "type": "Feature",
  "properties": {
    "gn:admin1_code":"19.0",
    "gn:asciiname":"Yubanyingzi",
    "gn:country_code":"CN",
    "gn:dem":120,
    "gn:feature_class":"P",
    "gn:feature_code":"PPL",
    "gn:name":"Yubanyingzi",
    "gn:population":0,
    "gn:timezone":"Asia/Shanghai",
    "iso:country":"CN",
    "name:und_x_variant":[
        "\u4e8e\u73ed\u8425\u5b50"
    ],
    "name:zho_x_preferred":[
        "\u4e8e\u73ed\u8425\u5b50"
    ],
    "wof:name":"Yubanyingzi",
    "wof:placetype":"locality"
},
  "geometry": {"coordinates":[120.57532999999999,41.21792],"type":"Point"}
}