{
  "type": "Feature",
  "properties": {
    "gn:admin1_code":"9",
    "gn:asciiname":"Wangxindian",
    "gn:country_code":"CN",
    "gn:dem":50,
    "gn:feature_class":"P",
    "gn:feature_code":"PPL",
    "gn:name":"Wangxindian",
    "gn:population":0,
    "gn:timezone":"Asia/Shanghai",
    "iso:country":"CN",
    "name:zho_x_preferred":[
        "\u738b\u8f9b\u5e97"
    ],
    "wof:name":"Wangxindian",
    "wof:placetype":"locality"
},
  "geometry": {"coordinates":[115.42628000000001,35.74018],"type":"Point"}
}