{
  "type": "Feature",
  "properties": {
    "gn:admin1_code":"20.0",
    "gn:asciiname":"Dashui Quanzi",
    "gn:country_code":"CN",
    "gn:dem":223,
    "gn:feature_class":"P",
    "gn:feature_code":"PPL",
    "gn:name":"Dashui Quanzi",
    "gn:population":0,
    "gn:timezone":"Asia/Shanghai",
    "iso:country":"CN",
    "name:zho_x_preferred":[
        "\u5927\u6c34\u6cc9\u5b50"
    ],
    "wof:name":"Dashui Quanzi",
    "wof:placetype":"locality"
},
  "geometry": {"coordinates":[123.51062,48.04452],"type":"Point"}
}