{
  "type": "Feature",
  "properties": {
    "gn:admin1_code":"10",
    "gn:asciiname":"Shiyihao",
    "gn:country_code":"CN",
    "gn:dem":959,
    "gn:feature_class":"P",
    "gn:feature_code":"PPLF",
    "gn:name":"Shiyihao",
    "gn:population":0,
    "gn:timezone":"Asia/Shanghai",
    "iso:country":"CN",
    "name:zho_x_preferred":[
        "\u5341\u4e00\u53f7"
    ],
    "wof:name":"Shiyihao",
    "wof:placetype":"locality"
},
  "geometry": {"coordinates":[117.60760000000001,41.99619000000001],"type":"Point"}
}