{
  "type": "Feature",
  "properties": {
    "gn:admin1_code":"30.0",
    "gn:asciiname":"Duntou",
    "gn:country_code":"CN",
    "gn:dem":247,
    "gn:feature_class":"P",
    "gn:feature_code":"PPL",
    "gn:name":"Duntou",
    "gn:population":0,
    "gn:timezone":"Asia/Shanghai",
    "iso:country":"CN",
    "name:zho_x_preferred":[
        "Duntou"
    ],
    "name:zho_x_variant":[
        "\u58a9\u5934"
    ],
    "wof:name":"Duntou",
    "wof:placetype":"locality"
},
  "geometry": {"coordinates":[114.08865,24.21009],"type":"Point"}
}