{
  "type": "Feature",
  "properties": {
    "gn:admin1_code":"10.0",
    "gn:asciiname":"Ansu",
    "gn:cc2":"CN",
    "gn:country_code":"CN",
    "gn:dem":22,
    "gn:feature_class":"P",
    "gn:feature_code":"PPL",
    "gn:name":"Ansu",
    "gn:population":0,
    "gn:timezone":"Asia/Shanghai",
    "iso:country":"CN",
    "name:und_x_variant":[
        "S\u00fcshuhsien",
        "Hs\u00fc-shui",
        "Syuishuy",
        "Ansuhsien",
        "Hs\u00fc-shui-ch\u2019eng-kuan",
        "Xushui",
        "Hs\u00fc-shui-ch\u2019eng-hsien",
        "Hs\u00fc-shui-hsien",
        "Ansu"
    ],
    "wof:name":"Ansu",
    "wof:placetype":"locality"
},
  "geometry": {"coordinates":[115.64388999999998,39.01917],"type":"Point"}
}