{
  "type": "Feature",
  "properties": {
    "gn:admin1_code":"15.0",
    "gn:asciiname":"Mouba",
    "gn:country_code":"CN",
    "gn:dem":887,
    "gn:feature_class":"P",
    "gn:feature_code":"PPL",
    "gn:name":"Mouba",
    "gn:population":0,
    "gn:timezone":"Asia/Shanghai",
    "iso:country":"CN",
    "name:und_x_variant":[
        "\u725f\u575d"
    ],
    "wof:name":"Mouba",
    "wof:placetype":"locality"
},
  "geometry": {"coordinates":[106.09986000000001,33.74572],"type":"Point"}
}