{
  "type": "Feature",
  "properties": {
    "gn:admin1_code":"7.0",
    "gn:asciiname":"Chensikeng",
    "gn:country_code":"CN",
    "gn:dem":385,
    "gn:feature_class":"P",
    "gn:feature_code":"PPL",
    "gn:name":"Chensikeng",
    "gn:population":0,
    "gn:timezone":"Asia/Shanghai",
    "iso:country":"CN",
    "name:zho_x_preferred":[
        "\u9648\u56db\u5751"
    ],
    "wof:name":"Chensikeng",
    "wof:placetype":"locality"
},
  "geometry": {"coordinates":[116.97676,26.19749],"type":"Point"}
}