{
  "type": "Feature",
  "properties": {
    "gn:admin1_code":"10",
    "gn:asciiname":"Tuanbokou",
    "gn:country_code":"CN",
    "gn:dem":379,
    "gn:feature_class":"P",
    "gn:feature_code":"PPL",
    "gn:name":"Tuanbokou",
    "gn:population":0,
    "gn:timezone":"Asia/Shanghai",
    "iso:country":"CN",
    "name:zho_x_preferred":[
        "\u56e2\u6cca\u53e3"
    ],
    "wof:name":"Tuanbokou",
    "wof:placetype":"locality"
},
  "geometry": {"coordinates":[113.98345999999999,38.59489],"type":"Point"}
}