{
  "type": "Feature",
  "properties": {
    "gn:admin1_code":"19.0",
    "gn:asciiname":"Huajiaofangcun",
    "gn:country_code":"CN",
    "gn:dem":42,
    "gn:feature_class":"P",
    "gn:feature_code":"PPL",
    "gn:name":"Huajiaofangcun",
    "gn:population":0,
    "gn:timezone":"Asia/Shanghai",
    "iso:country":"CN",
    "name:zho_x_preferred":[
        "\u82b1\u6912\u623f\u6751"
    ],
    "wof:name":"Huajiaofangcun",
    "wof:placetype":"locality"
},
  "geometry": {"coordinates":[121.30200000000001,39.5483],"type":"Point"}
}