{
  "type": "Feature",
  "properties": {
    "gn:admin1_code":"8.0",
    "gn:asciiname":"Zhangxiatun",
    "gn:country_code":"CN",
    "gn:dem":185,
    "gn:feature_class":"P",
    "gn:feature_code":"PPL",
    "gn:name":"Zhangxiatun",
    "gn:population":0,
    "gn:timezone":"Asia/Shanghai",
    "iso:country":"CN",
    "name:zho_x_preferred":[
        "\u5f20\u778e\u5c6f"
    ],
    "wof:name":"Zhangxiatun",
    "wof:placetype":"locality"
},
  "geometry": {"coordinates":[126.13766,47.02427],"type":"Point"}
}