{
  "type": "Feature",
  "properties": {
    "gn:admin1_code":"1.0",
    "gn:asciiname":"Wangjiaxiang",
    "gn:country_code":"CN",
    "gn:dem":13,
    "gn:feature_class":"P",
    "gn:feature_code":"PPL",
    "gn:name":"Wangjiaxiang",
    "gn:population":0,
    "gn:timezone":"Asia/Shanghai",
    "iso:country":"CN",
    "name:zho_x_preferred":[
        "\u738b\u5bb6\u5df7"
    ],
    "wof:name":"Wangjiaxiang",
    "wof:placetype":"locality"
},
  "geometry": {"coordinates":[118.34833,31.36169000000001],"type":"Point"}
}