{
  "type": "Feature",
  "properties": {
    "gn:admin1_code":"10",
    "gn:asciiname":"Huanzigou",
    "gn:country_code":"CN",
    "gn:dem":895,
    "gn:feature_class":"P",
    "gn:feature_code":"PPL",
    "gn:name":"Huanzigou",
    "gn:population":0,
    "gn:timezone":"Asia/Shanghai",
    "iso:country":"CN",
    "name:zho_x_preferred":[
        "\u737e\u5b50\u6c9f"
    ],
    "wof:name":"Huanzigou",
    "wof:placetype":"locality"
},
  "geometry": {"coordinates":[117.83644,41.48668],"type":"Point"}
}