{
  "type": "Feature",
  "properties": {
    "gn:admin1_code":"14.0",
    "gn:asciiname":"Reduicun",
    "gn:country_code":"CN",
    "gn:dem":3730,
    "gn:feature_class":"P",
    "gn:feature_code":"PPL",
    "gn:name":"Reduicun",
    "gn:population":0,
    "gn:timezone":"Asia/Urumqi",
    "iso:country":"CN",
    "name:zho_x_preferred":[
        "\u70ed\u5806\u6751"
    ],
    "wof:name":"Reduicun",
    "wof:placetype":"locality"
},
  "geometry": {"coordinates":[90.91556,29.53494],"type":"Point"}
}