{
  "type": "Feature",
  "properties": {
    "gn:admin1_code":"26.0",
    "gn:asciiname":"Muwanggou",
    "gn:country_code":"CN",
    "gn:dem":652,
    "gn:feature_class":"P",
    "gn:feature_code":"PPL",
    "gn:name":"Muwanggou",
    "gn:population":0,
    "gn:timezone":"Asia/Shanghai",
    "iso:country":"CN",
    "name:zho_x_preferred":[
        "\u6728\u738b\u6c9f"
    ],
    "wof:name":"Muwanggou",
    "wof:placetype":"locality"
},
  "geometry": {"coordinates":[107.82265,32.25933],"type":"Point"}
}