{
  "type": "Feature",
  "properties": {
    "gn:admin1_code":"33.0",
    "gn:asciiname":"Zhide",
    "gn:country_code":"CN",
    "gn:dem":612,
    "gn:feature_class":"P",
    "gn:feature_code":"PPL",
    "gn:name":"Zhide",
    "gn:population":0,
    "gn:timezone":"Asia/Shanghai",
    "iso:country":"CN",
    "name:zho_x_preferred":[
        "\u667a\u5fb7"
    ],
    "wof:name":"Zhide",
    "wof:placetype":"locality"
},
  "geometry": {"coordinates":[108.10906,30.75376],"type":"Point"}
}