{
  "type": "Feature",
  "properties": {
    "gn:admin1_code":"24.0",
    "gn:asciiname":"Haoyi",
    "gn:country_code":"CN",
    "gn:dem":1237,
    "gn:feature_class":"P",
    "gn:feature_code":"PPL",
    "gn:name":"Haoyi",
    "gn:population":0,
    "gn:timezone":"Asia/Shanghai",
    "iso:country":"CN",
    "name:zho_x_preferred":[
        "\u597d\u4e49"
    ],
    "wof:name":"Haoyi",
    "wof:placetype":"locality"
},
  "geometry": {"coordinates":[111.05907999999999,36.54084],"type":"Point"}
}