{
  "type": "Feature",
  "properties": {
    "gn:admin1_code":"29",
    "gn:asciiname":"Luomodian",
    "gn:country_code":"CN",
    "gn:dem":1711,
    "gn:feature_class":"P",
    "gn:feature_code":"PPL",
    "gn:name":"Luomodian",
    "gn:population":0,
    "gn:timezone":"Asia/Shanghai",
    "iso:country":"CN",
    "name:zho_x_preferred":[
        "\u6d1b\u83ab\u7538"
    ],
    "wof:name":"Luomodian",
    "wof:placetype":"locality"
},
  "geometry": {"coordinates":[101.77500000000001,24.5144],"type":"Point"}
}