{
  "type": "Feature",
  "properties": {
    "gn:admin1_code":"26.0",
    "gn:asciiname":"Mujiayuancun",
    "gn:country_code":"CN",
    "gn:dem":1344,
    "gn:feature_class":"P",
    "gn:feature_code":"PPL",
    "gn:name":"Mujiayuancun",
    "gn:population":0,
    "gn:timezone":"Asia/Shanghai",
    "iso:country":"CN",
    "name:zho_x_preferred":[
        "\u6728\u5bb6\u586c\u6751"
    ],
    "wof:name":"Mujiayuancun",
    "wof:placetype":"locality"
},
  "geometry": {"coordinates":[109.60843,35.99913],"type":"Point"}
}