{
  "type": "Feature",
  "properties": {
    "gn:admin1_code":"18.0",
    "gn:asciiname":"Baiyanping",
    "gn:country_code":"CN",
    "gn:dem":755,
    "gn:feature_class":"P",
    "gn:feature_code":"PPL",
    "gn:name":"Baiyanping",
    "gn:population":0,
    "gn:timezone":"Asia/Shanghai",
    "iso:country":"CN",
    "name:zho_x_preferred":[
        "\u767d\u5ca9\u576a"
    ],
    "wof:name":"Baiyanping",
    "wof:placetype":"locality"
},
  "geometry": {"coordinates":[108.66,27.378],"type":"Point"}
}