{
  "type": "Feature",
  "properties": {
    "gn:admin1_code":"07",
    "gn:asciiname":"Majia",
    "gn:country_code":"CN",
    "gn:dem":102,
    "gn:feature_class":"P",
    "gn:feature_code":"PPL",
    "gn:name":"Majia",
    "gn:population":0,
    "gn:timezone":"Asia/Shanghai",
    "iso:country":"CN",
    "name:und_x_variant":[
        "Ma-chia",
        "Majia"
    ],
    "name:zho_x_preferred":[
        "\u9a6c\u7532"
    ],
    "wof:name":"Majia",
    "wof:placetype":"locality"
},
  "geometry": {"coordinates":[118.61642000000001,25.12163],"type":"Point"}
}