{
  "type": "Feature",
  "properties": {
    "gn:admin1_code":"19.0",
    "gn:asciiname":"Sunjia Gouli",
    "gn:country_code":"CN",
    "gn:dem":141,
    "gn:feature_class":"P",
    "gn:feature_code":"PPL",
    "gn:name":"Sunjia Gouli",
    "gn:population":0,
    "gn:timezone":"Asia/Shanghai",
    "iso:country":"CN",
    "name:zho_x_preferred":[
        "\u5b59\u5bb6\u6c9f\u91cc"
    ],
    "wof:name":"Sunjia Gouli",
    "wof:placetype":"locality"
},
  "geometry": {"coordinates":[120.678,40.7531],"type":"Point"}
}