{
  "type": "Feature",
  "properties": {
    "gn:admin1_code":"29.0",
    "gn:asciiname":"Xinzhuangke",
    "gn:country_code":"CN",
    "gn:dem":1191,
    "gn:feature_class":"P",
    "gn:feature_code":"PPL",
    "gn:name":"Xinzhuangke",
    "gn:population":0,
    "gn:timezone":"Asia/Shanghai",
    "iso:country":"CN",
    "name:zho_x_preferred":[
        "\u65b0\u5e84\u79d1"
    ],
    "wof:name":"Xinzhuangke",
    "wof:placetype":"locality"
},
  "geometry": {"coordinates":[104.262,24.6502],"type":"Point"}
}