{
  "type": "Feature",
  "properties": {
    "gn:admin1_code":"1.0",
    "gn:asciiname":"Lihuayuancun",
    "gn:country_code":"CN",
    "gn:dem":26,
    "gn:feature_class":"P",
    "gn:feature_code":"PPL",
    "gn:name":"Lihuayuancun",
    "gn:population":0,
    "gn:timezone":"Asia/Shanghai",
    "iso:country":"CN",
    "name:zho_x_preferred":[
        "\u674e\u82b1\u56ed\u6751"
    ],
    "wof:name":"Lihuayuancun",
    "wof:placetype":"locality"
},
  "geometry": {"coordinates":[116.2337,32.5216],"type":"Point"}
}