{
  "type": "Feature",
  "properties": {
    "gn:admin1_code":"29.0",
    "gn:asciiname":"Lixiangzhuang",
    "gn:country_code":"CN",
    "gn:dem":1441,
    "gn:feature_class":"P",
    "gn:feature_code":"PPL",
    "gn:name":"Lixiangzhuang",
    "gn:population":0,
    "gn:timezone":"Asia/Shanghai",
    "iso:country":"CN",
    "name:zho_x_preferred":[
        "\u674e\u76f8\u5e84"
    ],
    "wof:name":"Lixiangzhuang",
    "wof:placetype":"locality"
},
  "geometry": {"coordinates":[100.592,25.8406],"type":"Point"}
}