{
  "type": "Feature",
  "properties": {
    "gn:admin1_code":"9",
    "gn:asciiname":"Xiniuqiao",
    "gn:country_code":"CN",
    "gn:dem":51,
    "gn:feature_class":"P",
    "gn:feature_code":"PPL",
    "gn:name":"Xiniuqiao",
    "gn:population":0,
    "gn:timezone":"Asia/Shanghai",
    "iso:country":"CN",
    "name:zho_x_preferred":[
        "\u897f\u725b\u6865"
    ],
    "wof:name":"Xiniuqiao",
    "wof:placetype":"locality"
},
  "geometry": {"coordinates":[115.468,35.736],"type":"Point"}
}