{
  "type": "Feature",
  "properties": {
    "gn:admin1_code":"8.0",
    "gn:asciiname":"Zhandoucun",
    "gn:country_code":"CN",
    "gn:dem":139,
    "gn:feature_class":"P",
    "gn:feature_code":"PPL",
    "gn:name":"Zhandoucun",
    "gn:population":0,
    "gn:timezone":"Asia/Shanghai",
    "iso:country":"CN",
    "name:zho_x_preferred":[
        "\u6218\u6597\u6751"
    ],
    "wof:name":"Zhandoucun",
    "wof:placetype":"locality"
},
  "geometry": {"coordinates":[123.54609000000001,46.57044000000001],"type":"Point"}
}