{
  "type": "Feature",
  "properties": {
    "gn:admin1_code":"19.0",
    "gn:asciiname":"Huangzhangzi",
    "gn:country_code":"CN",
    "gn:dem":464,
    "gn:feature_class":"P",
    "gn:feature_code":"PPL",
    "gn:name":"Huangzhangzi",
    "gn:population":0,
    "gn:timezone":"Asia/Shanghai",
    "iso:country":"CN",
    "name:zho_x_preferred":[
        "\u9ec4\u6756\u5b50"
    ],
    "wof:name":"Huangzhangzi",
    "wof:placetype":"locality"
},
  "geometry": {"coordinates":[120.13272000000001,41.55675],"type":"Point"}
}