{
  "type": "Feature",
  "properties": {
    "gn:admin1_code":"29",
    "gn:asciiname":"Gebaikong",
    "gn:country_code":"CN",
    "gn:dem":1358,
    "gn:feature_class":"P",
    "gn:feature_code":"PPL",
    "gn:name":"Gebaikong",
    "gn:population":0,
    "gn:timezone":"Asia/Shanghai",
    "iso:country":"CN",
    "name:zho_x_preferred":[
        "\u54e5\u767d\u5b54"
    ],
    "wof:name":"Gebaikong",
    "wof:placetype":"locality"
},
  "geometry": {"coordinates":[102.191,23.712],"type":"Point"}
}