{
  "type": "Feature",
  "properties": {
    "gn:admin1_code":"16.0",
    "gn:asciiname":"Jiacandi",
    "gn:country_code":"CN",
    "gn:dem":294,
    "gn:feature_class":"P",
    "gn:feature_code":"PPL",
    "gn:name":"Jiacandi",
    "gn:population":0,
    "gn:timezone":"Asia/Shanghai",
    "iso:country":"CN",
    "name:zho_x_preferred":[
        "\u52a0\u53c2\u5e95"
    ],
    "wof:name":"Jiacandi",
    "wof:placetype":"locality"
},
  "geometry": {"coordinates":[108.36,24.2662],"type":"Point"}
}