{
  "type": "Feature",
  "properties": {
    "gn:admin1_code":"16.0",
    "gn:asciiname":"Mingzhengcao",
    "gn:country_code":"CN",
    "gn:dem":296,
    "gn:feature_class":"P",
    "gn:feature_code":"PPL",
    "gn:name":"Mingzhengcao",
    "gn:population":0,
    "gn:timezone":"Asia/Shanghai",
    "iso:country":"CN",
    "name:zho_x_preferred":[
        "\u660e\u6b63\u6f15"
    ],
    "wof:name":"Mingzhengcao",
    "wof:placetype":"locality"
},
  "geometry": {"coordinates":[109.995,24.7597],"type":"Point"}
}