{
  "type": "Feature",
  "properties": {
    "gn:admin1_code":"02",
    "gn:asciiname":"Sanjiaotou",
    "gn:country_code":"CN",
    "gn:dem":388,
    "gn:feature_class":"P",
    "gn:feature_code":"PPL",
    "gn:name":"Sanjiaotou",
    "gn:population":0,
    "gn:timezone":"Asia/Shanghai",
    "iso:country":"CN",
    "name:zho_x_preferred":[
        "\u4e09\u89d2\u5934"
    ],
    "wof:name":"Sanjiaotou",
    "wof:placetype":"locality"
},
  "geometry": {"coordinates":[120.37649,27.95155],"type":"Point"}
}