{
  "type": "Feature",
  "properties": {
    "gn:admin1_code":"18.0",
    "gn:asciiname":"Hanglong",
    "gn:country_code":"CN",
    "gn:dem":849,
    "gn:feature_class":"P",
    "gn:feature_code":"PPL",
    "gn:name":"Hanglong",
    "gn:population":0,
    "gn:timezone":"Asia/Shanghai",
    "iso:country":"CN",
    "name:zho_x_preferred":[
        "\u822a\u9f99"
    ],
    "wof:name":"Hanglong",
    "wof:placetype":"locality"
},
  "geometry": {"coordinates":[106.88800000000001,25.6951],"type":"Point"}
}