{
  "type": "Feature",
  "properties": {
    "gn:admin1_code":"7.0",
    "gn:asciiname":"Zhenshan",
    "gn:country_code":"CN",
    "gn:dem":526,
    "gn:feature_class":"P",
    "gn:feature_code":"PPL",
    "gn:name":"Zhenshan",
    "gn:population":0,
    "gn:timezone":"Asia/Shanghai",
    "iso:country":"CN",
    "name:zho_x_preferred":[
        "\u73cd\u5c71"
    ],
    "wof:name":"Zhenshan",
    "wof:placetype":"locality"
},
  "geometry": {"coordinates":[119.02218000000001,26.29765],"type":"Point"}
}