{
  "type": "Feature",
  "properties": {
    "gn:admin1_code":"29.0",
    "gn:asciiname":"Gaomeigu",
    "gn:country_code":"CN",
    "gn:dem":3192,
    "gn:feature_class":"P",
    "gn:feature_code":"PPL",
    "gn:name":"Gaomeigu",
    "gn:population":0,
    "gn:timezone":"Asia/Shanghai",
    "iso:country":"CN",
    "name:zho_x_preferred":[
        "\u9ad8\u7f8e\u53e4"
    ],
    "wof:name":"Gaomeigu",
    "wof:placetype":"locality"
},
  "geometry": {"coordinates":[100.035,26.7069],"type":"Point"}
}