{
  "type": "Feature",
  "properties": {
    "gn:admin1_code":"26.0",
    "gn:asciiname":"Huangcaoping",
    "gn:country_code":"CN",
    "gn:dem":2193,
    "gn:feature_class":"P",
    "gn:feature_code":"PPL",
    "gn:name":"Huangcaoping",
    "gn:population":0,
    "gn:timezone":"Asia/Shanghai",
    "iso:country":"CN",
    "name:und_x_variant":[
        "\u9ec4\u8349\u576a"
    ],
    "wof:name":"Huangcaoping",
    "wof:placetype":"locality"
},
  "geometry": {"coordinates":[107.65367000000001,33.74644],"type":"Point"}
}