{
  "type": "Feature",
  "properties": {
    "gn:admin1_code":"8.0",
    "gn:asciiname":"Jinjiawopeng",
    "gn:country_code":"CN",
    "gn:dem":152,
    "gn:feature_class":"P",
    "gn:feature_code":"PPL",
    "gn:name":"Jinjiawopeng",
    "gn:population":0,
    "gn:timezone":"Asia/Shanghai",
    "iso:country":"CN",
    "name:zho_x_preferred":[
        "\u91d1\u5bb6\u7a9d\u68da"
    ],
    "wof:name":"Jinjiawopeng",
    "wof:placetype":"locality"
},
  "geometry": {"coordinates":[126.92428999999998,45.78608],"type":"Point"}
}