{
  "type": "Feature",
  "properties": {
    "gn:admin1_code":"25",
    "gn:asciiname":"Laopo",
    "gn:country_code":"CN",
    "gn:dem":375,
    "gn:feature_class":"P",
    "gn:feature_code":"PPL",
    "gn:name":"Laopo",
    "gn:population":0,
    "gn:timezone":"Asia/Shanghai",
    "iso:country":"CN",
    "name:zho_x_preferred":[
        "\u6d9d\u5761"
    ],
    "wof:name":"Laopo",
    "wof:placetype":"locality"
},
  "geometry": {"coordinates":[117.959,36.1328],"type":"Point"}
}