{
  "type": "Feature",
  "properties": {
    "gn:admin1_code":"14.0",
    "gn:asciiname":"Oiga",
    "gn:cc2":"CN",
    "gn:country_code":"CN",
    "gn:dem":3923,
    "gn:feature_class":"P",
    "gn:feature_code":"PPL",
    "gn:name":"Oiga",
    "gn:population":0,
    "gn:timezone":"Asia/Urumqi",
    "iso:country":"CN",
    "name:bod_x_preferred":[
        "\u0f60\u0f7c\u0f63\u0f0b\u0f51\u0f42\u0f60"
    ],
    "name:und_x_variant":[
        "Wo-ka",
        "Woga",
        "Woka"
    ],
    "name:zho_x_preferred":[
        "\u6c83\u560e"
    ],
    "name:zho_x_variant":[
        "\u6c83\u5361"
    ],
    "wof:name":"Oiga",
    "wof:placetype":"locality"
},
  "geometry": {"coordinates":[92.32069,29.37844],"type":"Point"}
}