{
  "type": "Feature",
  "properties": {
    "gn:admin1_code":"26.0",
    "gn:asciiname":"Laodong",
    "gn:country_code":"CN",
    "gn:dem":1260,
    "gn:feature_class":"P",
    "gn:feature_code":"PPL",
    "gn:name":"Laodong",
    "gn:population":0,
    "gn:timezone":"Asia/Shanghai",
    "iso:country":"CN",
    "name:und_x_variant":[
        "\u52b3\u52a8"
    ],
    "wof:name":"Laodong",
    "wof:placetype":"locality"
},
  "geometry": {"coordinates":[106.63424000000001,33.50764],"type":"Point"}
}