{
  "type": "Feature",
  "properties": {
    "gn:admin1_code":"26.0",
    "gn:asciiname":"Shaluocun",
    "gn:country_code":"CN",
    "gn:dem":1494,
    "gn:feature_class":"P",
    "gn:feature_code":"PPL",
    "gn:name":"Shaluocun",
    "gn:population":0,
    "gn:timezone":"Asia/Shanghai",
    "iso:country":"CN",
    "name:zho_x_preferred":[
        "\u6c99\u6d1b\u6751"
    ],
    "wof:name":"Shaluocun",
    "wof:placetype":"locality"
},
  "geometry": {"coordinates":[108.87976999999999,33.76064],"type":"Point"}
}