{
  "type": "Feature",
  "properties": {
    "gn:admin1_code":"4.0",
    "gn:asciiname":"Yangtancun",
    "gn:country_code":"CN",
    "gn:dem":26,
    "gn:feature_class":"P",
    "gn:feature_code":"PPL",
    "gn:name":"Yangtancun",
    "gn:population":0,
    "gn:timezone":"Asia/Shanghai",
    "iso:country":"CN",
    "name:zho_x_preferred":[
        "\u6768\u6ee9\u6751"
    ],
    "wof:name":"Yangtancun",
    "wof:placetype":"locality"
},
  "geometry": {"coordinates":[117.81171000000001,34.42871],"type":"Point"}
}