{
  "type": "Feature",
  "properties": {
    "gn:admin1_code":"12.0",
    "gn:asciiname":"Huangjingkou",
    "gn:country_code":"CN",
    "gn:dem":31,
    "gn:feature_class":"P",
    "gn:feature_code":"PPL",
    "gn:name":"Huangjingkou",
    "gn:population":0,
    "gn:timezone":"Asia/Shanghai",
    "iso:country":"CN",
    "name:zho_x_preferred":[
        "\u9ec4\u8346\u53e3"
    ],
    "wof:name":"Huangjingkou",
    "wof:placetype":"locality"
},
  "geometry": {"coordinates":[113.47022,30.36275],"type":"Point"}
}