{
  "type": "Feature",
  "properties": {
    "gn:admin1_code":"29.0",
    "gn:asciiname":"Ahengzhai",
    "gn:country_code":"CN",
    "gn:dem":2406,
    "gn:feature_class":"P",
    "gn:feature_code":"PPL",
    "gn:name":"Ahengzhai",
    "gn:population":0,
    "gn:timezone":"Asia/Shanghai",
    "iso:country":"CN",
    "name:zho_x_preferred":[
        "\u963f\u6052\u5b85"
    ],
    "wof:name":"Ahengzhai",
    "wof:placetype":"locality"
},
  "geometry": {"coordinates":[99.8306,25.8065],"type":"Point"}
}