{
  "type": "Feature",
  "properties": {
    "gn:admin1_code":"32.0",
    "gn:asciiname":"Bishan",
    "gn:country_code":"CN",
    "gn:dem":512,
    "gn:feature_class":"P",
    "gn:feature_code":"PPL",
    "gn:name":"Bishan",
    "gn:population":0,
    "gn:timezone":"Asia/Shanghai",
    "iso:country":"CN",
    "name:zho_x_preferred":[
        "\u58c1\u5c71"
    ],
    "wof:name":"Bishan",
    "wof:placetype":"locality"
},
  "geometry": {"coordinates":[103.57899999999999,30.5496],"type":"Point"}
}