{
  "type": "Feature",
  "properties": {
    "gn:admin1_code":"5.0",
    "gn:asciiname":"Erlama Wopeng",
    "gn:country_code":"CN",
    "gn:dem":150,
    "gn:feature_class":"P",
    "gn:feature_code":"PPL",
    "gn:name":"Erlama Wopeng",
    "gn:population":0,
    "gn:timezone":"Asia/Shanghai",
    "iso:country":"CN",
    "name:zho_x_preferred":[
        "\u4e8c\u5587\u561b\u7a9d\u68da"
    ],
    "wof:name":"Erlama Wopeng",
    "wof:placetype":"locality"
},
  "geometry": {"coordinates":[122.64106,45.39368],"type":"Point"}
}