{
  "type": "Feature",
  "properties": {
    "gn:admin1_code":"30",
    "gn:asciiname":"Haishan",
    "gn:country_code":"CN",
    "gn:dem":10,
    "gn:feature_class":"P",
    "gn:feature_code":"PPL",
    "gn:name":"Haishan",
    "gn:population":0,
    "gn:timezone":"Asia/Urumqi",
    "iso:country":"CN",
    "name:zho_x_preferred":[
        "\u6d77\u5c71"
    ],
    "wof:name":"Haishan",
    "wof:placetype":"locality"
},
  "geometry": {"coordinates":[110.6814,21.32561],"type":"Point"}
}