{
  "type": "Feature",
  "properties": {
    "gn:admin1_code":"13",
    "gn:asciiname":"Yangjuangou",
    "gn:country_code":"CN",
    "gn:dem":1858,
    "gn:feature_class":"P",
    "gn:feature_code":"PPL",
    "gn:name":"Yangjuangou",
    "gn:population":0,
    "gn:timezone":"Asia/Urumqi",
    "iso:country":"CN",
    "name:zho_x_preferred":[
        "\u7f8a\u5708\u6c9f"
    ],
    "wof:name":"Yangjuangou",
    "wof:placetype":"locality"
},
  "geometry": {"coordinates":[87.64731999999999,43.35885],"type":"Point"}
}