{
  "type": "Feature",
  "properties": {
    "gn:admin1_code":"10.0",
    "gn:asciiname":"Nanwuhe",
    "gn:country_code":"CN",
    "gn:dem":172,
    "gn:feature_class":"P",
    "gn:feature_code":"PPL",
    "gn:name":"Nanwuhe",
    "gn:population":0,
    "gn:timezone":"Asia/Shanghai",
    "iso:country":"CN",
    "name:und_x_variant":[
        "\u5357\u4f0d\u6cb3"
    ],
    "wof:name":"Nanwuhe",
    "wof:placetype":"locality"
},
  "geometry": {"coordinates":[114.2859,38.48126],"type":"Point"}
}