{
  "type": "Feature",
  "properties": {
    "gn:admin1_code":"12.0",
    "gn:asciiname":"Zhongtaisi",
    "gn:country_code":"CN",
    "gn:dem":765,
    "gn:feature_class":"P",
    "gn:feature_code":"PPL",
    "gn:name":"Zhongtaisi",
    "gn:population":0,
    "gn:timezone":"Asia/Shanghai",
    "iso:country":"CN",
    "name:zho_x_preferred":[
        "\u4e2d\u53f0\u5bfa"
    ],
    "wof:name":"Zhongtaisi",
    "wof:placetype":"locality"
},
  "geometry": {"coordinates":[108.74826000000002,30.47943],"type":"Point"}
}