{
  "type": "Feature",
  "properties": {
    "gn:admin1_code":"4.0",
    "gn:asciiname":"Dacaozhuangcun",
    "gn:country_code":"CN",
    "gn:dem":-2,
    "gn:feature_class":"P",
    "gn:feature_code":"PPL",
    "gn:name":"Dacaozhuangcun",
    "gn:population":0,
    "gn:timezone":"Asia/Shanghai",
    "iso:country":"CN",
    "name:zho_x_preferred":[
        "\u5927\u66f9\u5e84\u6751"
    ],
    "wof:name":"Dacaozhuangcun",
    "wof:placetype":"locality"
},
  "geometry": {"coordinates":[119.84229000000001,33.65631],"type":"Point"}
}