{
  "type": "Feature",
  "properties": {
    "gn:admin1_code":"30.0",
    "gn:asciiname":"Gangbei",
    "gn:country_code":"CN",
    "gn:dem":35,
    "gn:feature_class":"P",
    "gn:feature_code":"PPL",
    "gn:name":"Gangbei",
    "gn:population":0,
    "gn:timezone":"Asia/Shanghai",
    "iso:country":"CN",
    "name:zho_x_preferred":[
        "\u5188\u8d1d"
    ],
    "wof:name":"Gangbei",
    "wof:placetype":"locality"
},
  "geometry": {"coordinates":[114.23520000000001,22.70845],"type":"Point"}
}