{
  "type": "Feature",
  "properties": {
    "gn:admin1_code":"14.0",
    "gn:asciiname":"Jiedidangga",
    "gn:country_code":"CN",
    "gn:dem":3457,
    "gn:feature_class":"P",
    "gn:feature_code":"PPL",
    "gn:name":"Jiedidangga",
    "gn:population":0,
    "gn:timezone":"Asia/Urumqi",
    "iso:country":"CN",
    "name:zho_x_preferred":[
        "\u63a5\u5730\u5f53\u560e"
    ],
    "wof:name":"Jiedidangga",
    "wof:placetype":"locality"
},
  "geometry": {"coordinates":[94.96061,29.59675],"type":"Point"}
}