{
  "type": "Feature",
  "properties": {
    "gn:admin1_code":"5.0",
    "gn:asciiname":"Dadingzi",
    "gn:country_code":"CN",
    "gn:dem":470,
    "gn:feature_class":"P",
    "gn:feature_code":"PPL",
    "gn:name":"Dadingzi",
    "gn:population":0,
    "gn:timezone":"Asia/Shanghai",
    "iso:country":"CN",
    "name:und_x_variant":[
        "\u5927\u9876\u5b50"
    ],
    "wof:name":"Dadingzi",
    "wof:placetype":"locality"
},
  "geometry": {"coordinates":[125.93458,41.24105],"type":"Point"}
}