{
  "type": "Feature",
  "properties": {
    "gn:admin1_code":"11.0",
    "gn:asciiname":"Heshangjie",
    "gn:country_code":"CN",
    "gn:dem":29,
    "gn:feature_class":"P",
    "gn:feature_code":"PPL",
    "gn:name":"Heshangjie",
    "gn:population":0,
    "gn:timezone":"Asia/Shanghai",
    "iso:country":"CN",
    "name:zho_x_preferred":[
        "\u548c\u5c1a\u754c"
    ],
    "wof:name":"Heshangjie",
    "wof:placetype":"locality"
},
  "geometry": {"coordinates":[112.35908000000001,29.26002],"type":"Point"}
}