{
  "type": "Feature",
  "properties": {
    "gn:admin1_code":"16.0",
    "gn:asciiname":"Hongdujie",
    "gn:country_code":"CN",
    "gn:dem":190,
    "gn:feature_class":"P",
    "gn:feature_code":"PPL",
    "gn:name":"Hongdujie",
    "gn:population":0,
    "gn:timezone":"Asia/Shanghai",
    "iso:country":"CN",
    "name:zho_x_preferred":[
        "\u7ea2\u6e21\u8857"
    ],
    "wof:name":"Hongdujie",
    "wof:placetype":"locality"
},
  "geometry": {"coordinates":[108.60899999999999,23.949],"type":"Point"}
}