{
  "type": "Feature",
  "properties": {
    "gn:admin1_code":"3.0",
    "gn:asciiname":"Wenjia",
    "gn:country_code":"CN",
    "gn:dem":38,
    "gn:feature_class":"P",
    "gn:feature_code":"PPL",
    "gn:name":"Wenjia",
    "gn:population":0,
    "gn:timezone":"Asia/Shanghai",
    "iso:country":"CN",
    "name:und_x_variant":[
        "\u6587\u5bb6"
    ],
    "wof:name":"Wenjia",
    "wof:placetype":"locality"
},
  "geometry": {"coordinates":[115.26636000000001,28.38994000000001],"type":"Point"}
}