{
  "type": "Feature",
  "properties": {
    "gn:admin1_code":"30.0",
    "gn:asciiname":"Zhuzai",
    "gn:country_code":"CN",
    "gn:dem":38,
    "gn:feature_class":"P",
    "gn:feature_code":"PPL",
    "gn:name":"Zhuzai",
    "gn:population":0,
    "gn:timezone":"Asia/Urumqi",
    "iso:country":"CN",
    "name:zho_x_preferred":[
        "\u7af9\u4ed4"
    ],
    "wof:name":"Zhuzai",
    "wof:placetype":"locality"
},
  "geometry": {"coordinates":[110.07067000000001,20.41228],"type":"Point"}
}