{
  "type": "Feature",
  "properties": {
    "gn:admin1_code":"16.0",
    "gn:asciiname":"Xiaoshechong",
    "gn:country_code":"CN",
    "gn:dem":596,
    "gn:feature_class":"P",
    "gn:feature_code":"PPL",
    "gn:name":"Xiaoshechong",
    "gn:population":0,
    "gn:timezone":"Asia/Shanghai",
    "iso:country":"CN",
    "name:zho_x_preferred":[
        "\u5c0f\u793e\u51b2"
    ],
    "wof:name":"Xiaoshechong",
    "wof:placetype":"locality"
},
  "geometry": {"coordinates":[110.95999999999999,24.8356],"type":"Point"}
}