{
  "type": "Feature",
  "properties": {
    "gn:admin1_code":"32.0",
    "gn:asciiname":"Exi",
    "gn:country_code":"CN",
    "gn:dem":410,
    "gn:feature_class":"P",
    "gn:feature_code":"PPL",
    "gn:name":"Exi",
    "gn:population":0,
    "gn:timezone":"Asia/Shanghai",
    "iso:country":"CN",
    "name:ell_x_preferred":[
        "\u0388\u03be\u03b9"
    ],
    "name:zho_x_preferred":[
        "\u5ce8\u6eaa"
    ],
    "wof:name":"Exi",
    "wof:placetype":"locality"
},
  "geometry": {"coordinates":[106.078,31.8112],"type":"Point"}
}