{
  "type": "Feature",
  "properties": {
    "gn:admin1_code":"16.0",
    "gn:asciiname":"Nonglang",
    "gn:country_code":"CN",
    "gn:dem":360,
    "gn:feature_class":"P",
    "gn:feature_code":"PPL",
    "gn:name":"Nonglang",
    "gn:population":0,
    "gn:timezone":"Asia/Shanghai",
    "iso:country":"CN",
    "name:zho_x_preferred":[
        "\u5f04\u6d6a"
    ],
    "wof:name":"Nonglang",
    "wof:placetype":"locality"
},
  "geometry": {"coordinates":[107.94499999999999,23.7328],"type":"Point"}
}