{
  "type": "Feature",
  "properties": {
    "gn:admin1_code":"29.0",
    "gn:asciiname":"Daxianba",
    "gn:country_code":"CN",
    "gn:dem":1903,
    "gn:feature_class":"P",
    "gn:feature_code":"PPL",
    "gn:name":"Daxianba",
    "gn:population":0,
    "gn:timezone":"Asia/Shanghai",
    "iso:country":"CN",
    "name:zho_x_preferred":[
        "\u5927\u9677\u575d"
    ],
    "wof:name":"Daxianba",
    "wof:placetype":"locality"
},
  "geometry": {"coordinates":[99.0613,25.3426],"type":"Point"}
}