{
  "type": "Feature",
  "properties": {
    "gn:admin1_code":"26.0",
    "gn:asciiname":"Guanxizhen",
    "gn:country_code":"CN",
    "gn:dem":468,
    "gn:feature_class":"P",
    "gn:feature_code":"PPL",
    "gn:name":"Guanxizhen",
    "gn:population":0,
    "gn:timezone":"Asia/Shanghai",
    "iso:country":"CN",
    "name:und_x_variant":[
        "\u8d2f\u6eaa\u9547"
    ],
    "wof:name":"Guanxizhen",
    "wof:placetype":"locality"
},
  "geometry": {"coordinates":[107.56577,33.21935],"type":"Point"}
}