{
  "type": "Feature",
  "properties": {
    "gn:admin1_code":"29.0",
    "gn:asciiname":"Xiaowanzi",
    "gn:country_code":"CN",
    "gn:dem":2662,
    "gn:feature_class":"P",
    "gn:feature_code":"PPL",
    "gn:name":"Xiaowanzi",
    "gn:population":0,
    "gn:timezone":"Asia/Shanghai",
    "iso:country":"CN",
    "name:zho_x_preferred":[
        "\u5c0f\u5f2f\u5b50"
    ],
    "wof:name":"Xiaowanzi",
    "wof:placetype":"locality"
},
  "geometry": {"coordinates":[99.92610000000001,26.9167],"type":"Point"}
}