{
  "type": "Feature",
  "properties": {
    "gn:admin1_code":"3.0",
    "gn:asciiname":"Lehezhen",
    "gn:country_code":"CN",
    "gn:dem":40,
    "gn:feature_class":"P",
    "gn:feature_code":"PPL",
    "gn:name":"Lehezhen",
    "gn:population":0,
    "gn:timezone":"Asia/Shanghai",
    "iso:country":"CN",
    "name:und_x_variant":[
        "\u4e50\u6cb3\u9547"
    ],
    "wof:name":"Lehezhen",
    "wof:placetype":"locality"
},
  "geometry": {"coordinates":[117.35177,29.05537],"type":"Point"}
}