{
  "type": "Feature",
  "properties": {
    "gn:admin1_code":"10.0",
    "gn:asciiname":"Langwuzhuang",
    "gn:country_code":"CN",
    "gn:dem":24,
    "gn:feature_class":"P",
    "gn:feature_code":"PPL",
    "gn:name":"Langwuzhuang",
    "gn:population":0,
    "gn:timezone":"Asia/Shanghai",
    "iso:country":"CN",
    "name:zho_x_preferred":[
        "\u90ce\u4e94\u5e84"
    ],
    "wof:name":"Langwuzhuang",
    "wof:placetype":"locality"
},
  "geometry": {"coordinates":[115.61494,39.07358],"type":"Point"}
}