{
  "type": "Feature",
  "properties": {
    "gn:country":"CN",
    "gn:fcode":"PPL",
    "gn:population":166507,
    "iso:country":"CN",
    "name:cdo_x_preferred":[
        "H\u00f9-l\u00ecng-k\u1e73\u0306"
    ],
    "name:ceb_x_preferred":[
        "Fuling Qu"
    ],
    "name:cym_x_preferred":[
        "Ardal Fuling"
    ],
    "name:deu_x_preferred":[
        "Fuling"
    ],
    "name:eng_x_preferred":[
        "Fuling District"
    ],
    "name:eus_x_preferred":[
        "Fuling Barrutia"
    ],
    "name:fas_x_preferred":[
        "\u0641\u06cc\u0648\u0644\u06cc\u0646\u06af"
    ],
    "name:gan_x_preferred":[
        "\u6daa\u9675\u533a"
    ],
    "name:hye_x_preferred":[
        "\u0556\u0578\u0582\u056c\u056b\u0576"
    ],
    "name:ind_x_preferred":[
        "Fuling"
    ],
    "name:jpn_x_preferred":[
        "\u30d5\u9675\u533a"
    ],
    "name:kor_x_preferred":[
        "\ud478\ub9c1\uad6c"
    ],
    "name:mwl_x_preferred":[
        "Fuling"
    ],
    "name:nan_x_preferred":[
        "H\u00f4\u0358-l\u00eang-khu"
    ],
    "name:nld_x_preferred":[
        "Fuling District"
    ],
    "name:nob_x_preferred":[
        "Fuling"
    ],
    "name:rus_x_preferred":[
        "\u0424\u0443\u043b\u0438\u043d"
    ],
    "name:spa_x_preferred":[
        "Fuling"
    ],
    "name:swe_x_preferred":[
        "Fuling"
    ],
    "name:tur_x_preferred":[
        "Fuling"
    ],
    "name:und_x_variant":[
        "Pei-ling"
    ],
    "name:urd_x_preferred":[
        "\u0641\u0648\u0644\u06cc\u0646\u06af \u0636\u0644\u0639"
    ],
    "name:vie_x_preferred":[
        "Ph\u00f9 L\u0103ng"
    ],
    "name:war_x_preferred":[
        "Fuling"
    ],
    "name:wuu_x_preferred":[
        "\u6daa\u9675\u533a"
    ],
    "name:yue_x_preferred":[
        "\u6daa\u9675"
    ],
    "name:zho_x_preferred":[
        "\u6daa\u9675"
    ],
    "name:zho_x_variant":[
        "\u6daa\u9675\u5340"
    ],
    "qs:name":"\u6daa\u9675",
    "qs:name_adm0":"\u4e2d\u570b",
    "qs:name_adm1":"\u91cd\u5e86\u76f4\u8f96\u5e02",
    "qs:photos":244,
    "qs:photos_1k":49,
    "qs:photos_9k":1,
    "qs:photos_9r":4,
    "qs:photos_all":244,
    "qs:photos_sr":4,
    "qs:placetype":"Town",
    "qs:pop_sr":"9",
    "wd:wordcount":1195,
    "wof:name":"\u6daa\u9675",
    "wof:placetype":"locality",
    "wof:population":166507
},
  "geometry": {"coordinates":[107.39575000000001,29.706],"type":"Point"}
}