{
  "type": "Feature",
  "properties": {
    "gn:country":"CN",
    "gn:fcode":"PPL",
    "gn:pop":166507,
    "iso:country":"CN",
    "name:rus_x_preferred":[
        "\u0424\u0443\u043b\u0438\u043d"
    ],
    "name:unk_x_variant":[
        "Pei-ling"
    ],
    "name:zho_x_preferred":[
        "\u6daa\u9675"
    ],
    "qs:name":"\u6daa\u9675",
    "qs:name_adm0":"\u4e2d\u570b",
    "qs:name_adm1":"\u91cd\u5e86\u76f4\u8f96\u5e02",
    "qs:photos":244,
    "qs:photos_1k":49,
    "qs:photos_9k":1,
    "qs:photos_9r":4,
    "qs:photos_all":244,
    "qs:photos_sr":4,
    "qs:placetype":"Town",
    "qs:pop_sr":"9",
    "wd:wordcount":1195,
    "wof:name":"\u6daa\u9675",
    "wof:placetype":"locality",
    "wof:population":166507
},
  "geometry": {"coordinates":[107.39575000000001,29.706],"type":"Point"}
}