{
  "type": "Feature",
  "properties": {
    "gn:admin1_code":"26.0",
    "gn:asciiname":"Xiaobazigou",
    "gn:country_code":"CN",
    "gn:dem":1054,
    "gn:feature_class":"P",
    "gn:feature_code":"PPL",
    "gn:name":"Xiaobazigou",
    "gn:population":0,
    "gn:timezone":"Asia/Shanghai",
    "iso:country":"CN",
    "name:und_x_variant":[
        "\u5c0f\u575d\u5b50\u6c9f"
    ],
    "wof:name":"Xiaobazigou",
    "wof:placetype":"locality"
},
  "geometry": {"coordinates":[105.93172,33.09303],"type":"Point"}
}