{
  "type": "Feature",
  "properties": {
    "gn:admin1_code":"02",
    "gn:asciiname":"Baochong",
    "gn:cc2":"CN",
    "gn:country_code":"CN",
    "gn:dem":5,
    "gn:feature_class":"P",
    "gn:feature_code":"PPL",
    "gn:name":"Baochong",
    "gn:population":0,
    "gn:timezone":"Asia/Shanghai",
    "iso:country":"CN",
    "name:und_x_variant":[
        "Pao-ch\u2019ung-chen",
        "Baochong"
    ],
    "wof:name":"Baochong",
    "wof:placetype":"locality"
},
  "geometry": {"coordinates":[121.72611000000001,29.84333],"type":"Point"}
}