{
  "type": "Feature",
  "properties": {
    "gn:admin1_code":"9.0",
    "gn:asciiname":"Mashigou",
    "gn:country_code":"CN",
    "gn:dem":582,
    "gn:feature_class":"P",
    "gn:feature_code":"PPL",
    "gn:name":"Mashigou",
    "gn:population":0,
    "gn:timezone":"Asia/Shanghai",
    "iso:country":"CN",
    "name:zho_x_preferred":[
        "\u9a6c\u77f3\u6c9f"
    ],
    "wof:name":"Mashigou",
    "wof:placetype":"locality"
},
  "geometry": {"coordinates":[111.91987,33.96899000000001],"type":"Point"}
}