{
  "type": "Feature",
  "properties": {
    "gn:admin1_code":"16",
    "gn:asciiname":"Pingle",
    "gn:country_code":"CN",
    "gn:dem":102,
    "gn:feature_class":"P",
    "gn:feature_code":"PPLA3",
    "gn:name":"Pingle",
    "gn:population":0,
    "gn:timezone":"Asia/Shanghai",
    "iso:country":"CN",
    "name:zho_x_preferred":[
        "Chiu-p\u2019ing-lo"
    ],
    "name:zho_x_variant":[
        "P\u2019ing-lo-hsien",
        "P\u2019ing-lo",
        "P\u2019ing-lo-chen",
        "\u5e73\u4e50"
    ],
    "wof:name":"Pingle",
    "wof:placetype":"locality"
},
  "geometry": {"coordinates":[110.64306000000001,24.64522],"type":"Point"}
}