{
  "type": "Feature",
  "properties": {
    "gn:admin1_code":"16",
    "gn:asciiname":"Pingle",
    "gn:country_code":"CN",
    "gn:dem":102,
    "gn:feature_class":"P",
    "gn:feature_code":"PPLA3",
    "gn:name":"Pingle",
    "gn:population":0,
    "gn:timezone":"Asia/Shanghai",
    "iso:country":"CN",
    "name:deu_x_preferred":[
        "Pingle"
    ],
    "name:fas_x_preferred":[
        "\u0634\u0647\u0631\u0633\u062a\u0627\u0646 \u067e\u06cc\u0646\u06af\u0644\u0647"
    ],
    "name:hak_x_preferred":[
        "Ph\u00ecn-lo\u030dk-yen"
    ],
    "name:jpn_x_preferred":[
        "\u5e73\u697d\u770c"
    ],
    "name:kor_x_preferred":[
        "\ud551\ub7ec\ud604"
    ],
    "name:nor_x_preferred":[
        "Pingle"
    ],
    "name:swe_x_preferred":[
        "Pingle"
    ],
    "name:vie_x_preferred":[
        "B\u00ecnh L\u1ea1c"
    ],
    "name:zho_x_preferred":[
        "Chiu-p\u2019ing-lo"
    ],
    "name:zho_x_variant":[
        "P\u2019ing-lo-hsien",
        "P\u2019ing-lo",
        "P\u2019ing-lo-chen",
        "\u5e73\u4e50",
        "\u5e73\u4e50\u53bf"
    ],
    "wof:name":"Pingle",
    "wof:placetype":"locality"
},
  "geometry": {"coordinates":[110.64306000000001,24.64522],"type":"Point"}
}