{
  "type": "Feature",
  "properties": {
    "gn:admin1_code":"29.0",
    "gn:asciiname":"Shanyangping",
    "gn:country_code":"CN",
    "gn:dem":1691,
    "gn:feature_class":"P",
    "gn:feature_code":"PPL",
    "gn:name":"Shanyangping",
    "gn:population":0,
    "gn:timezone":"Asia/Shanghai",
    "iso:country":"CN",
    "name:zho_x_preferred":[
        "\u5c71\u7f8a\u576a"
    ],
    "wof:name":"Shanyangping",
    "wof:placetype":"locality"
},
  "geometry": {"coordinates":[99.88200000000001,25.8527],"type":"Point"}
}