{
  "type": "Feature",
  "properties": {
    "gn:admin1_code":"4.0",
    "gn:asciiname":"Donglinzi",
    "gn:country_code":"CN",
    "gn:dem":4,
    "gn:feature_class":"P",
    "gn:feature_code":"PPL",
    "gn:name":"Donglinzi",
    "gn:population":0,
    "gn:timezone":"Asia/Shanghai",
    "iso:country":"CN",
    "name:zho_x_preferred":[
        "\u4e1c\u6797\u5b50"
    ],
    "wof:name":"Donglinzi",
    "wof:placetype":"locality"
},
  "geometry": {"coordinates":[119.25563,35.08069],"type":"Point"}
}