{
  "type": "Feature",
  "properties": {
    "gn:admin1_code":"15.0",
    "gn:asciiname":"Yanshahe",
    "gn:country_code":"CN",
    "gn:dem":2033,
    "gn:feature_class":"P",
    "gn:feature_code":"PPL",
    "gn:name":"Yanshahe",
    "gn:population":0,
    "gn:timezone":"Asia/Shanghai",
    "iso:country":"CN",
    "name:zho_x_preferred":[
        "\u960e\u7802\u6cb3"
    ],
    "wof:name":"Yanshahe",
    "wof:placetype":"locality"
},
  "geometry": {"coordinates":[104.586,37.0743],"type":"Point"}
}