{
  "type": "Feature",
  "properties": {
    "gn:admin1_code":"3.0",
    "gn:asciiname":"Xiapu",
    "gn:country_code":"CN",
    "gn:dem":82,
    "gn:feature_class":"P",
    "gn:feature_code":"PPLA4",
    "gn:name":"Xiapu",
    "gn:population":0,
    "gn:timezone":"Asia/Shanghai",
    "iso:country":"CN",
    "name:und_x_variant":[
        "Hsia-p\u2019u",
        "Xiapu",
        "\u4e0b\u6d66",
        "Xiapu Xiang",
        "\u4e0b\u6d66\u4e61"
    ],
    "wof:name":"Xiapu",
    "wof:placetype":"locality"
},
  "geometry": {"coordinates":[114.44316000000001,27.79642],"type":"Point"}
}