{
  "type": "Feature",
  "properties": {
    "gn:admin1_code":"19.0",
    "gn:asciiname":"Manzhicao",
    "gn:country_code":"CN",
    "gn:dem":157,
    "gn:feature_class":"P",
    "gn:feature_code":"PPL",
    "gn:name":"Manzhicao",
    "gn:population":0,
    "gn:timezone":"Asia/Shanghai",
    "iso:country":"CN",
    "name:zho_x_preferred":[
        "\u8513\u679d\u8349"
    ],
    "wof:name":"Manzhicao",
    "wof:placetype":"locality"
},
  "geometry": {"coordinates":[119.804,40.2243],"type":"Point"}
}