{
  "type": "Feature",
  "properties": {
    "gn:admin1_code":"5.0",
    "gn:asciiname":"Yushukecun",
    "gn:country_code":"CN",
    "gn:dem":206,
    "gn:feature_class":"P",
    "gn:feature_code":"PPL",
    "gn:name":"Yushukecun",
    "gn:population":0,
    "gn:timezone":"Asia/Shanghai",
    "iso:country":"CN",
    "name:zho_x_preferred":[
        "\u6986\u6811\u68f5\u6751"
    ],
    "wof:name":"Yushukecun",
    "wof:placetype":"locality"
},
  "geometry": {"coordinates":[125.83005,44.02058],"type":"Point"}
}