{
  "type": "Feature",
  "properties": {
    "gn:admin1_code":"3.0",
    "gn:asciiname":"Fantian",
    "gn:country_code":"CN",
    "gn:dem":32,
    "gn:feature_class":"P",
    "gn:feature_code":"PPL",
    "gn:name":"Fantian",
    "gn:population":0,
    "gn:timezone":"Asia/Shanghai",
    "iso:country":"CN",
    "name:und_x_variant":[
        "\u8303\u7530"
    ],
    "wof:name":"Fantian",
    "wof:placetype":"locality"
},
  "geometry": {"coordinates":[116.78943999999998,29.25182],"type":"Point"}
}