{
  "type": "Feature",
  "properties": {
    "gn:admin1_code":"29.0",
    "gn:asciiname":"Sanjia",
    "gn:country_code":"CN",
    "gn:dem":1977,
    "gn:feature_class":"P",
    "gn:feature_code":"PPL",
    "gn:name":"Sanjia",
    "gn:population":0,
    "gn:timezone":"Asia/Shanghai",
    "iso:country":"CN",
    "name:ceb_x_preferred":[
        "Sanjia"
    ],
    "name:swe_x_preferred":[
        "Sanjia"
    ],
    "name:zho_x_preferred":[
        "\u4e09\u5bb6"
    ],
    "wof:name":"Sanjia",
    "wof:placetype":"locality"
},
  "geometry": {"coordinates":[100.374,24.3011],"type":"Point"}
}