{
  "type": "Feature",
  "properties": {
    "gn:admin1_code":"14.0",
    "gn:asciiname":"Mengacun",
    "gn:country_code":"CN",
    "gn:dem":4501,
    "gn:feature_class":"P",
    "gn:feature_code":"PPL",
    "gn:name":"Mengacun",
    "gn:population":0,
    "gn:timezone":"Asia/Urumqi",
    "iso:country":"CN",
    "name:zho_x_preferred":[
        "\u95e8\u560e\u6751"
    ],
    "wof:name":"Mengacun",
    "wof:placetype":"locality"
},
  "geometry": {"coordinates":[91.23532,28.8118],"type":"Point"}
}