{
  "type": "Feature",
  "properties": {
    "gn:admin1_code":"3.0",
    "gn:asciiname":"Shangshegong",
    "gn:country_code":"CN",
    "gn:dem":361,
    "gn:feature_class":"P",
    "gn:feature_code":"PPL",
    "gn:name":"Shangshegong",
    "gn:population":0,
    "gn:timezone":"Asia/Shanghai",
    "iso:country":"CN",
    "name:und_x_variant":[
        "\u4e0a\u793e\u516c"
    ],
    "wof:name":"Shangshegong",
    "wof:placetype":"locality"
},
  "geometry": {"coordinates":[115.90210999999999,26.90187],"type":"Point"}
}