{
  "type": "Feature",
  "properties": {
    "gn:admin1_code":"12.0",
    "gn:asciiname":"Zhusifang",
    "gn:country_code":"CN",
    "gn:dem":58,
    "gn:feature_class":"P",
    "gn:feature_code":"PPL",
    "gn:name":"Zhusifang",
    "gn:population":0,
    "gn:timezone":"Asia/Shanghai",
    "iso:country":"CN",
    "name:zho_x_preferred":[
        "Zhusifang"
    ],
    "name:zho_x_variant":[
        "\u6731\u56db\u623f"
    ],
    "wof:name":"Zhusifang",
    "wof:placetype":"locality"
},
  "geometry": {"coordinates":[115.47248,30.17142],"type":"Point"}
}