{
  "type": "Feature",
  "properties": {
    "gn:admin1_code":"33.0",
    "gn:asciiname":"Yantan",
    "gn:country_code":"CN",
    "gn:dem":459,
    "gn:feature_class":"P",
    "gn:feature_code":"PPL",
    "gn:name":"Yantan",
    "gn:population":0,
    "gn:timezone":"Asia/Shanghai",
    "iso:country":"CN",
    "name:zho_x_preferred":[
        "\u6cbf\u6ee9"
    ],
    "wof:name":"Yantan",
    "wof:placetype":"locality"
},
  "geometry": {"coordinates":[108.28968999999999,29.14612],"type":"Point"}
}