{
  "type": "Feature",
  "properties": {
    "gn:admin1_code":"32.0",
    "gn:asciiname":"Paofang",
    "gn:country_code":"CN",
    "gn:dem":1159,
    "gn:feature_class":"P",
    "gn:feature_code":"PPL",
    "gn:name":"Paofang",
    "gn:population":0,
    "gn:timezone":"Asia/Shanghai",
    "iso:country":"CN",
    "name:zho_x_preferred":[
        "\u70ae\u623f"
    ],
    "wof:name":"Paofang",
    "wof:placetype":"locality"
},
  "geometry": {"coordinates":[103.563,29.0828],"type":"Point"}
}