{
  "type": "Feature",
  "properties": {
    "gn:admin1_code":"02",
    "gn:asciiname":"Si'an",
    "gn:country_code":"CN",
    "gn:dem":16,
    "gn:feature_class":"P",
    "gn:feature_code":"PPLA4",
    "gn:name":"Si\u2019an",
    "gn:population":0,
    "gn:timezone":"Asia/Shanghai",
    "iso:country":"CN",
    "name:und_x_variant":[
        "Szean",
        "Ssu-an",
        "Ssu-an-chen",
        "Si\u2019an",
        "\u6cd7\u5b89",
        "Si\u2019an Zhen",
        "\u6cd7\u5b89\u9547"
    ],
    "wof:name":"Si'an",
    "wof:placetype":"locality"
},
  "geometry": {"coordinates":[119.65361,30.89833],"type":"Point"}
}