{
  "type": "Feature",
  "properties": {
    "gn:admin1_code":"6.0",
    "gn:asciiname":"Za'er Ama",
    "gn:country_code":"CN",
    "gn:dem":4188,
    "gn:feature_class":"P",
    "gn:feature_code":"PPL",
    "gn:name":"Za\u2019er Ama",
    "gn:population":0,
    "gn:timezone":"Asia/Urumqi",
    "iso:country":"CN",
    "name:und_x_variant":[
        "Za\u2019er Ama"
    ],
    "name:zho_x_preferred":[
        "\u6742\u513f\u963f\u739b"
    ],
    "wof:name":"Za'er Ama",
    "wof:placetype":"locality"
},
  "geometry": {"coordinates":[95.71477,32.43579],"type":"Point"}
}