{
  "type": "Feature",
  "properties": {
    "gn:admin1_code":"12",
    "gn:asciiname":"Tonghaikou",
    "gn:country_code":"CN",
    "gn:dem":34,
    "gn:feature_class":"P",
    "gn:feature_code":"PPLA4",
    "gn:name":"Tonghaikou",
    "gn:population":0,
    "gn:timezone":"Asia/Shanghai",
    "iso:country":"CN",
    "name:und_x_variant":[
        "T\u2019ung-hai-k\u2019ou",
        "Tonghaikou",
        "Tonghaikou Zhen"
    ],
    "name:zho_x_preferred":[
        "\u901a\u6d77\u53e3"
    ],
    "name:zho_x_variant":[
        "\u901a\u6d77\u53e3\u9547"
    ],
    "wof:name":"Tonghaikou",
    "wof:placetype":"locality"
},
  "geometry": {"coordinates":[113.15046,30.1971],"type":"Point"}
}