{
  "type": "Feature",
  "properties": {
    "gn:admin1_code":"29.0",
    "gn:asciiname":"Laojie",
    "gn:country_code":"CN",
    "gn:dem":1507,
    "gn:feature_class":"P",
    "gn:feature_code":"PPL",
    "gn:name":"Laojie",
    "gn:population":0,
    "gn:timezone":"Asia/Shanghai",
    "iso:country":"CN",
    "name:zho_x_preferred":[
        "\u8001\u8857"
    ],
    "wof:name":"Laojie",
    "wof:placetype":"locality"
},
  "geometry": {"coordinates":[99.4794,24.0116],"type":"Point"}
}