{
  "type": "Feature",
  "properties": {
    "gn:admin1_code":"30.0",
    "gn:asciiname":"Hehuatang",
    "gn:country_code":"CN",
    "gn:dem":142,
    "gn:feature_class":"P",
    "gn:feature_code":"PPL",
    "gn:name":"Hehuatang",
    "gn:population":0,
    "gn:timezone":"Asia/Shanghai",
    "iso:country":"CN",
    "name:zho_x_preferred":[
        "Hehuatang"
    ],
    "name:zho_x_variant":[
        "\u79be\u82b1\u5858"
    ],
    "wof:name":"Hehuatang",
    "wof:placetype":"locality"
},
  "geometry": {"coordinates":[114.09052,24.84941],"type":"Point"}
}