{
  "type": "Feature",
  "properties": {
    "gn:admin1_code":"9.0",
    "gn:asciiname":"Dengzhai",
    "gn:country_code":"CN",
    "gn:dem":139,
    "gn:feature_class":"P",
    "gn:feature_code":"PPL",
    "gn:name":"Dengzhai",
    "gn:population":0,
    "gn:timezone":"Asia/Shanghai",
    "iso:country":"CN",
    "name:und_x_variant":[
        "\u9093\u5be8",
        "Dengzhai"
    ],
    "wof:name":"Dengzhai",
    "wof:placetype":"locality"
},
  "geometry": {"coordinates":[112.87532,33.69799],"type":"Point"}
}