{
  "type": "Feature",
  "properties": {
    "gn:admin1_code":"15.0",
    "gn:asciiname":"Xiashanpo",
    "gn:country_code":"CN",
    "gn:dem":1889,
    "gn:feature_class":"P",
    "gn:feature_code":"PPL",
    "gn:name":"Xiashanpo",
    "gn:population":0,
    "gn:timezone":"Asia/Shanghai",
    "iso:country":"CN",
    "name:zho_x_preferred":[
        "\u4e0b\u5c71\u5761"
    ],
    "wof:name":"Xiashanpo",
    "wof:placetype":"locality"
},
  "geometry": {"coordinates":[102.83,37.6106],"type":"Point"}
}