{
  "type": "Feature",
  "properties": {
    "gn:admin1_code":"16.0",
    "gn:asciiname":"Sipo",
    "gn:country_code":"CN",
    "gn:dem":222,
    "gn:feature_class":"P",
    "gn:feature_code":"PPL",
    "gn:name":"Sipo",
    "gn:population":0,
    "gn:timezone":"Asia/Shanghai",
    "iso:country":"CN",
    "name:zho_x_preferred":[
        "\u56db\u5761"
    ],
    "wof:name":"Sipo",
    "wof:placetype":"locality"
},
  "geometry": {"coordinates":[111.175,24.17],"type":"Point"}
}