{
  "type": "Feature",
  "properties": {
    "gn:admin1_code":"21.0",
    "gn:asciiname":"Laohu",
    "gn:country_code":"CN",
    "gn:dem":2241,
    "gn:feature_class":"P",
    "gn:feature_code":"PPL",
    "gn:name":"Laohu",
    "gn:population":0,
    "gn:timezone":"Asia/Shanghai",
    "iso:country":"CN",
    "name:zho_x_preferred":[
        "\u8001\u864e"
    ],
    "wof:name":"Laohu",
    "wof:placetype":"locality"
},
  "geometry": {"coordinates":[105.676,36.3845],"type":"Point"}
}