{
  "type": "Feature",
  "properties": {
    "gn:admin1_code":"12.0",
    "gn:asciiname":"Huanglinbian",
    "gn:country_code":"CN",
    "gn:dem":36,
    "gn:feature_class":"P",
    "gn:feature_code":"PPL",
    "gn:name":"Huanglinbian",
    "gn:population":0,
    "gn:timezone":"Asia/Shanghai",
    "iso:country":"CN",
    "name:und_x_variant":[
        "\u9ec4\u6797\u8fb9"
    ],
    "wof:name":"Huanglinbian",
    "wof:placetype":"locality"
},
  "geometry": {"coordinates":[114.36247,30.11273],"type":"Point"}
}