{
  "type": "Feature",
  "properties": {
    "gn:admin1_code":"3",
    "gn:asciiname":"Ganzhu",
    "gn:country_code":"CN",
    "gn:dem":121,
    "gn:feature_class":"P",
    "gn:feature_code":"PPL",
    "gn:name":"Ganzhu",
    "gn:population":0,
    "gn:timezone":"Asia/Shanghai",
    "iso:country":"CN",
    "name:und_x_variant":[
        "\u7518\u7af9",
        "Ganzhubei"
    ],
    "wof:name":"Ganzhu",
    "wof:placetype":"locality"
},
  "geometry": {"coordinates":[115.67167999999999,27.53636],"type":"Point"}
}