{
  "type": "Feature",
  "properties": {
    "gn:admin1_code":"12.0",
    "gn:asciiname":"Fengjiachang",
    "gn:country_code":"CN",
    "gn:dem":72,
    "gn:feature_class":"P",
    "gn:feature_code":"PPL",
    "gn:name":"Fengjiachang",
    "gn:population":0,
    "gn:timezone":"Asia/Shanghai",
    "iso:country":"CN",
    "name:zho_x_preferred":[
        "Fengjiachang"
    ],
    "name:zho_x_variant":[
        "\u51af\u5bb6\u573a"
    ],
    "wof:name":"Fengjiachang",
    "wof:placetype":"locality"
},
  "geometry": {"coordinates":[112.01452,30.77741],"type":"Point"}
}