{
  "type": "Feature",
  "properties": {
    "gn:admin1_code":"32.0",
    "gn:asciiname":"Aihua",
    "gn:country_code":"CN",
    "gn:dem":522,
    "gn:feature_class":"P",
    "gn:feature_code":"PPL",
    "gn:name":"Aihua",
    "gn:population":0,
    "gn:timezone":"Asia/Shanghai",
    "iso:country":"CN",
    "name:zho_x_preferred":[
        "\u7231\u534e"
    ],
    "wof:name":"Aihua",
    "wof:placetype":"locality"
},
  "geometry": {"coordinates":[105.26600000000001,31.484],"type":"Point"}
}