{
  "type": "Feature",
  "properties": {
    "gn:admin1_code":"15.0",
    "gn:asciiname":"Caojia Shanpo",
    "gn:country_code":"CN",
    "gn:dem":2517,
    "gn:feature_class":"P",
    "gn:feature_code":"PPL",
    "gn:name":"Caojia Shanpo",
    "gn:population":0,
    "gn:timezone":"Asia/Shanghai",
    "iso:country":"CN",
    "name:zho_x_preferred":[
        "\u66f9\u5bb6\u5c71\u5761"
    ],
    "wof:name":"Caojia Shanpo",
    "wof:placetype":"locality"
},
  "geometry": {"coordinates":[103.56399999999999,36.9762],"type":"Point"}
}