{
  "type": "Feature",
  "properties": {
    "gn:admin1_code":"26",
    "gn:asciiname":"Goulijia",
    "gn:country_code":"CN",
    "gn:dem":726,
    "gn:feature_class":"P",
    "gn:feature_code":"PPL",
    "gn:name":"Goulijia",
    "gn:population":0,
    "gn:timezone":"Asia/Shanghai",
    "iso:country":"CN",
    "name:zho_x_preferred":[
        "\u6c9f\u674e\u5bb6"
    ],
    "wof:name":"Goulijia",
    "wof:placetype":"locality"
},
  "geometry": {"coordinates":[108.09412,34.5077],"type":"Point"}
}