{
  "type": "Feature",
  "properties": {
    "gn:admin1_code":"14.0",
    "gn:asciiname":"Zaba",
    "gn:country_code":"CN",
    "gn:dem":3657,
    "gn:feature_class":"P",
    "gn:feature_code":"PPL",
    "gn:name":"Zaba",
    "gn:population":0,
    "gn:timezone":"Asia/Urumqi",
    "iso:country":"CN",
    "name:zho_x_preferred":[
        "\u6742\u5df4"
    ],
    "wof:name":"Zaba",
    "wof:placetype":"locality"
},
  "geometry": {"coordinates":[92.10167,29.2745],"type":"Point"}
}