{
  "type": "Feature",
  "properties": {
    "gn:admin1_code":"4.0",
    "gn:asciiname":"Fasitang",
    "gn:country_code":"CN",
    "gn:dem":30,
    "gn:feature_class":"P",
    "gn:feature_code":"PPL",
    "gn:name":"Fasitang",
    "gn:population":0,
    "gn:timezone":"Asia/Shanghai",
    "iso:country":"CN",
    "name:zho_x_preferred":[
        "\u6cd5\u53f8\u5858"
    ],
    "wof:name":"Fasitang",
    "wof:placetype":"locality"
},
  "geometry": {"coordinates":[119.19182000000001,31.49599000000001],"type":"Point"}
}