{
  "type": "Feature",
  "properties": {
    "gn:admin1_code":"5.0",
    "gn:asciiname":"Yilihada Nangou",
    "gn:country_code":"CN",
    "gn:dem":131,
    "gn:feature_class":"P",
    "gn:feature_code":"PPL",
    "gn:name":"Yilihada Nangou",
    "gn:population":0,
    "gn:timezone":"Asia/Shanghai",
    "iso:country":"CN",
    "name:und_x_variant":[
        "\u4f9d\u91cc\u54c8\u8fbe\u5357\u6c9f"
    ],
    "wof:name":"Yilihada Nangou",
    "wof:placetype":"locality"
},
  "geometry": {"coordinates":[130.49185,42.8297],"type":"Point"}
}