{
  "type": "Feature",
  "properties": {
    "gn:admin1_code":"24.0",
    "gn:asciiname":"Qiaohou",
    "gn:country_code":"CN",
    "gn:dem":1358,
    "gn:feature_class":"P",
    "gn:feature_code":"PPL",
    "gn:name":"Qiaohou",
    "gn:population":0,
    "gn:timezone":"Asia/Shanghai",
    "iso:country":"CN",
    "name:zho_x_preferred":[
        "\u4e54\u540e"
    ],
    "wof:name":"Qiaohou",
    "wof:placetype":"locality"
},
  "geometry": {"coordinates":[112.46258,39.57147],"type":"Point"}
}