{
  "type": "Feature",
  "properties": {
    "gn:admin1_code":"29",
    "gn:asciiname":"Xiyang",
    "gn:country_code":"CN",
    "gn:dem":659,
    "gn:feature_class":"P",
    "gn:feature_code":"PPL",
    "gn:name":"Xiyang",
    "gn:population":0,
    "gn:timezone":"Asia/Shanghai",
    "iso:country":"CN",
    "name:zho_x_preferred":[
        "\u897f\u6d0b"
    ],
    "wof:name":"Xiyang",
    "wof:placetype":"locality"
},
  "geometry": {"coordinates":[105.33199999999999,23.8914],"type":"Point"}
}