{
  "type": "Feature",
  "properties": {
    "gn:admin1_code":"26.0",
    "gn:asciiname":"Luojiayingcun",
    "gn:country_code":"CN",
    "gn:dem":593,
    "gn:feature_class":"P",
    "gn:feature_code":"PPL",
    "gn:name":"Luojiayingcun",
    "gn:population":0,
    "gn:timezone":"Asia/Shanghai",
    "iso:country":"CN",
    "name:zho_x_preferred":[
        "\u7f57\u5bb6\u8425\u6751"
    ],
    "wof:name":"Luojiayingcun",
    "wof:placetype":"locality"
},
  "geometry": {"coordinates":[108.86870999999999,33.4435],"type":"Point"}
}