{
  "type": "Feature",
  "properties": {
    "gn:admin1_code":"29",
    "gn:asciiname":"Lianshanpo",
    "gn:country_code":"CN",
    "gn:dem":1914,
    "gn:feature_class":"P",
    "gn:feature_code":"PPL",
    "gn:name":"Lianshanpo",
    "gn:population":0,
    "gn:timezone":"Asia/Shanghai",
    "iso:country":"CN",
    "name:zho_x_preferred":[
        "\u8fde\u5c71\u5761"
    ],
    "wof:name":"Lianshanpo",
    "wof:placetype":"locality"
},
  "geometry": {"coordinates":[102.36799999999999,24.3067],"type":"Point"}
}