{
  "type": "Feature",
  "properties": {
    "gn:admin1_code":"21.0",
    "gn:asciiname":"Huitai",
    "gn:country_code":"CN",
    "gn:dem":1932,
    "gn:feature_class":"P",
    "gn:feature_code":"PPL",
    "gn:name":"Huitai",
    "gn:population":0,
    "gn:timezone":"Asia/Shanghai",
    "iso:country":"CN",
    "name:zho_x_preferred":[
        "\u60e0\u53f0"
    ],
    "wof:name":"Huitai",
    "wof:placetype":"locality"
},
  "geometry": {"coordinates":[106.301,35.5458],"type":"Point"}
}