{
  "type": "Feature",
  "properties": {
    "gn:admin1_code":"32.0",
    "gn:asciiname":"Wenfengting",
    "gn:country_code":"CN",
    "gn:dem":373,
    "gn:feature_class":"P",
    "gn:feature_code":"PPL",
    "gn:name":"Wenfengting",
    "gn:population":0,
    "gn:timezone":"Asia/Shanghai",
    "iso:country":"CN",
    "name:zho_x_preferred":[
        "\u6587\u98ce\u4ead"
    ],
    "wof:name":"Wenfengting",
    "wof:placetype":"locality"
},
  "geometry": {"coordinates":[105.31,30.8379],"type":"Point"}
}