{
  "type": "Feature",
  "properties": {
    "gn:admin1_code":"25",
    "gn:asciiname":"Shangtang",
    "gn:cc2":"CN",
    "gn:country_code":"CN",
    "gn:dem":11,
    "gn:feature_class":"P",
    "gn:feature_code":"PPL",
    "gn:name":"Shangtang",
    "gn:population":0,
    "gn:timezone":"Asia/Shanghai",
    "iso:country":"CN",
    "name:und_x_variant":[
        "Shang-chia-chai",
        "Shangjiatang",
        "Shang-chia-t\u2019ang",
        "Shangtang"
    ],
    "wof:name":"Shangtang",
    "wof:placetype":"locality"
},
  "geometry": {"coordinates":[117.42389,37.70528],"type":"Point"}
}