{
  "type": "Feature",
  "properties": {
    "gn:admin1_code":"1.0",
    "gn:asciiname":"Zishucun",
    "gn:country_code":"CN",
    "gn:dem":221,
    "gn:feature_class":"P",
    "gn:feature_code":"PPL",
    "gn:name":"Zishucun",
    "gn:population":0,
    "gn:timezone":"Asia/Shanghai",
    "iso:country":"CN",
    "name:zho_x_preferred":[
        "\u6893\u6811\u6751"
    ],
    "wof:name":"Zishucun",
    "wof:placetype":"locality"
},
  "geometry": {"coordinates":[115.48792,31.46332],"type":"Point"}
}