{
  "type": "Feature",
  "properties": {
    "gn:admin1_code":"9.0",
    "gn:asciiname":"Nanshizhai",
    "gn:country_code":"CN",
    "gn:dem":181,
    "gn:feature_class":"P",
    "gn:feature_code":"PPL",
    "gn:name":"Nanshizhai",
    "gn:population":0,
    "gn:timezone":"Asia/Shanghai",
    "iso:country":"CN",
    "name:zho_x_preferred":[
        "\u5357\u77f3\u5be8"
    ],
    "wof:name":"Nanshizhai",
    "wof:placetype":"locality"
},
  "geometry": {"coordinates":[112.79025,33.23993],"type":"Point"}
}