{
  "type": "Feature",
  "properties": {
    "gn:admin1_code":"9.0",
    "gn:asciiname":"Kaolao",
    "gn:country_code":"CN",
    "gn:dem":211,
    "gn:feature_class":"P",
    "gn:feature_code":"PPL",
    "gn:name":"Kaolao",
    "gn:population":0,
    "gn:timezone":"Asia/Shanghai",
    "iso:country":"CN",
    "name:zho_x_preferred":[
        "\u6832\u6833"
    ],
    "wof:name":"Kaolao",
    "wof:placetype":"locality"
},
  "geometry": {"coordinates":[112.49614,35.05741],"type":"Point"}
}