{
  "type": "Feature",
  "properties": {
    "gn:admin1_code":"30",
    "gn:asciiname":"Bajiaotang",
    "gn:country_code":"CN",
    "gn:dem":187,
    "gn:feature_class":"P",
    "gn:feature_code":"PPL",
    "gn:name":"Bajiaotang",
    "gn:population":0,
    "gn:timezone":"Asia/Urumqi",
    "iso:country":"CN",
    "name:zho_x_preferred":[
        "\u516b\u89d2\u5858"
    ],
    "wof:name":"Bajiaotang",
    "wof:placetype":"locality"
},
  "geometry": {"coordinates":[110.21208,20.4882],"type":"Point"}
}