{
  "type": "Feature",
  "properties": {
    "gn:admin1_code":"32.0",
    "gn:asciiname":"Sali",
    "gn:country_code":"CN",
    "gn:dem":3012,
    "gn:feature_class":"P",
    "gn:feature_code":"PPL",
    "gn:name":"Sali",
    "gn:population":0,
    "gn:timezone":"Asia/Shanghai",
    "iso:country":"CN",
    "name:bul_x_preferred":[
        "\u0421\u0430\u043b\u0438"
    ],
    "name:ceb_x_preferred":[
        "Sali"
    ],
    "name:ces_x_preferred":[
        "Sali"
    ],
    "name:deu_x_preferred":[
        "Sali"
    ],
    "name:fra_x_preferred":[
        "Sali"
    ],
    "name:hun_x_preferred":[
        "Sali"
    ],
    "name:ita_x_preferred":[
        "Sali"
    ],
    "name:por_x_preferred":[
        "Sali"
    ],
    "name:rus_x_preferred":[
        "\u0421\u0430\u043b\u0438"
    ],
    "name:swe_x_preferred":[
        "Sali"
    ],
    "name:ukr_x_preferred":[
        "\u0421\u0430\u043b\u0456"
    ],
    "name:zho_x_preferred":[
        "\u8428\u529b"
    ],
    "wof:name":"Sali",
    "wof:placetype":"locality"
},
  "geometry": {"coordinates":[101.902,31.8419],"type":"Point"}
}