{
  "type": "Feature",
  "properties": {
    "gn:admin1_code":"32.0",
    "gn:asciiname":"Sali",
    "gn:country_code":"CN",
    "gn:dem":3012,
    "gn:feature_class":"P",
    "gn:feature_code":"PPL",
    "gn:name":"Sali",
    "gn:population":0,
    "gn:timezone":"Asia/Shanghai",
    "iso:country":"CN",
    "name:zho_x_preferred":[
        "\u8428\u529b"
    ],
    "wof:name":"Sali",
    "wof:placetype":"locality"
},
  "geometry": {"coordinates":[101.902,31.8419],"type":"Point"}
}