{
  "type": "Feature",
  "properties": {
    "gn:admin1_code":"03",
    "gn:asciiname":"Mulan",
    "gn:country_code":"CN",
    "gn:dem":278,
    "gn:feature_class":"P",
    "gn:feature_code":"PPLA4",
    "gn:name":"Mulan",
    "gn:population":0,
    "gn:timezone":"Asia/Shanghai",
    "iso:country":"CN",
    "name:und_x_variant":[
        "\u6728\u5170",
        "Mulan Xiang",
        "\u6728\u5170\u4e61"
    ],
    "wof:name":"Mulan",
    "wof:placetype":"locality"
},
  "geometry": {"coordinates":[116.39019,26.49603],"type":"Point"}
}