{
  "type": "Feature",
  "properties": {
    "gn:admin1_code":"16.0",
    "gn:asciiname":"Gubu'ao",
    "gn:country_code":"CN",
    "gn:dem":326,
    "gn:feature_class":"P",
    "gn:feature_code":"PPL",
    "gn:name":"Gubu\u2019ao",
    "gn:population":0,
    "gn:timezone":"Asia/Shanghai",
    "iso:country":"CN",
    "name:und_x_variant":[
        "Gubu\u2019ao"
    ],
    "name:zho_x_preferred":[
        "\u53e4\u535c\u5773"
    ],
    "wof:name":"Gubu'ao",
    "wof:placetype":"locality"
},
  "geometry": {"coordinates":[109.855,23.6717],"type":"Point"}
}