{
  "type": "Feature",
  "properties": {
    "gn:admin1_code":"5.0",
    "gn:asciiname":"Duanjiacun",
    "gn:country_code":"CN",
    "gn:dem":183,
    "gn:feature_class":"P",
    "gn:feature_code":"PPL",
    "gn:name":"Duanjiacun",
    "gn:population":0,
    "gn:timezone":"Asia/Shanghai",
    "iso:country":"CN",
    "name:zho_x_preferred":[
        "\u6bb5\u5bb6\u6751"
    ],
    "wof:name":"Duanjiacun",
    "wof:placetype":"locality"
},
  "geometry": {"coordinates":[125.32026999999999,44.36078],"type":"Point"}
}