{
  "type": "Feature",
  "properties": {
    "gn:admin1_code":"3.0",
    "gn:asciiname":"Tailing",
    "gn:country_code":"CN",
    "gn:dem":171,
    "gn:feature_class":"P",
    "gn:feature_code":"PPL",
    "gn:name":"Tailing",
    "gn:population":0,
    "gn:timezone":"Asia/Shanghai",
    "iso:country":"CN",
    "name:deu_x_preferred":[
        "Tailing"
    ],
    "name:und_x_variant":[
        "\u53f0\u5cad"
    ],
    "wof:name":"Tailing",
    "wof:placetype":"locality"
},
  "geometry": {"coordinates":[115.22045,29.23139],"type":"Point"}
}