{
  "type": "Feature",
  "properties": {
    "gn:admin1_code":"4.0",
    "gn:asciiname":"Zhousiqiao",
    "gn:country_code":"CN",
    "gn:dem":6,
    "gn:feature_class":"P",
    "gn:feature_code":"PPL",
    "gn:name":"Zhousiqiao",
    "gn:population":0,
    "gn:timezone":"Asia/Shanghai",
    "iso:country":"CN",
    "name:und_x_variant":[
        "\u5468\u53f8\u6865"
    ],
    "name:zho_x_preferred":[
        "\u5468\u53f8\u6865"
    ],
    "wof:name":"Zhousiqiao",
    "wof:placetype":"locality"
},
  "geometry": {"coordinates":[120.28268,31.47983],"type":"Point"}
}