{
  "type": "Feature",
  "properties": {
    "gn:admin1_code":"09",
    "gn:asciiname":"Puxi",
    "gn:country_code":"CN",
    "gn:dem":64,
    "gn:feature_class":"P",
    "gn:feature_code":"PPLA3",
    "gn:name":"Puxi",
    "gn:population":0,
    "gn:timezone":"Asia/Shanghai",
    "iso:country":"CN",
    "name:und_x_variant":[
        "Ch\u2019ang-y\u00fcan-hsien",
        "Changyuan",
        "Puxi"
    ],
    "name:zho_x_preferred":[
        "\u84b2\u897f"
    ],
    "wof:name":"Puxi",
    "wof:placetype":"locality"
},
  "geometry": {"coordinates":[114.685,35.19583],"type":"Point"}
}