{
  "type": "Feature",
  "properties": {
    "gn:admin1_code":"29.0",
    "gn:asciiname":"Chari",
    "gn:country_code":"CN",
    "gn:dem":2547,
    "gn:feature_class":"P",
    "gn:feature_code":"PPL",
    "gn:name":"Chari",
    "gn:population":0,
    "gn:timezone":"Asia/Shanghai",
    "iso:country":"CN",
    "name:ben_x_preferred":[
        "\u099a\u09be\u09b0\u09bf"
    ],
    "name:ceb_x_preferred":[
        "Chari"
    ],
    "name:fin_x_preferred":[
        "Chari"
    ],
    "name:hin_x_preferred":[
        "\u091a\u0930\u0940"
    ],
    "name:ita_x_preferred":[
        "Chari"
    ],
    "name:urd_x_preferred":[
        "\u0686\u0627\u0631\u06cc"
    ],
    "name:zho_x_preferred":[
        "\u67e5\u65e5"
    ],
    "wof:name":"Chari",
    "wof:placetype":"locality"
},
  "geometry": {"coordinates":[99.20229999999999,26.949],"type":"Point"}
}