{
  "type": "Feature",
  "properties": {
    "gn:admin1_code":"16.0",
    "gn:asciiname":"Yangdong",
    "gn:country_code":"CN",
    "gn:dem":483,
    "gn:feature_class":"P",
    "gn:feature_code":"PPL",
    "gn:name":"Yangdong",
    "gn:population":0,
    "gn:timezone":"Asia/Shanghai",
    "iso:country":"CN",
    "name:fra_x_preferred":[
        "Yangdong"
    ],
    "name:zho_x_preferred":[
        "\u7f8a\u5cd2"
    ],
    "wof:name":"Yangdong",
    "wof:placetype":"locality"
},
  "geometry": {"coordinates":[108.003,24.4686],"type":"Point"}
}