{
  "type": "Feature",
  "properties": {
    "gn:admin1_code":"15.0",
    "gn:asciiname":"Houqi",
    "gn:country_code":"CN",
    "gn:dem":2424,
    "gn:feature_class":"P",
    "gn:feature_code":"PPL",
    "gn:name":"Houqi",
    "gn:population":0,
    "gn:timezone":"Asia/Shanghai",
    "iso:country":"CN",
    "name:und_x_variant":[
        "\u4faf\u65d7"
    ],
    "wof:name":"Houqi",
    "wof:placetype":"locality"
},
  "geometry": {"coordinates":[103.90657,34.87306],"type":"Point"}
}