{
  "type": "Feature",
  "properties": {
    "gn:admin1_code":"22.0",
    "gn:asciiname":"Qianlingoucun",
    "gn:country_code":"CN",
    "gn:dem":40,
    "gn:feature_class":"P",
    "gn:feature_code":"PPL",
    "gn:name":"Qianlingoucun",
    "gn:population":0,
    "gn:timezone":"Asia/Shanghai",
    "iso:country":"CN",
    "name:zho_x_preferred":[
        "\u524d\u853a\u6c9f\u6751"
    ],
    "wof:name":"Qianlingoucun",
    "wof:placetype":"locality"
},
  "geometry": {"coordinates":[116.44175,40.15302],"type":"Point"}
}