{
  "type": "Feature",
  "properties": {
    "gn:admin1_code":"29",
    "gn:asciiname":"Jinggujie",
    "gn:cc2":"CN",
    "gn:country_code":"CN",
    "gn:dem":1487,
    "gn:feature_class":"P",
    "gn:feature_code":"PPL",
    "gn:name":"Jinggujie",
    "gn:population":0,
    "gn:timezone":"Asia/Shanghai",
    "iso:country":"CN",
    "name:und_x_variant":[
        "Chingku",
        "Ching-ku-chieh",
        "Jinggujie"
    ],
    "wof:name":"Jinggujie",
    "wof:placetype":"locality"
},
  "geometry": {"coordinates":[100.65000000000001,23.75],"type":"Point"}
}