{
  "type": "Feature",
  "properties": {
    "gn:admin1_code":"21.0",
    "gn:asciiname":"Wangjiatai",
    "gn:country_code":"CN",
    "gn:dem":2052,
    "gn:feature_class":"P",
    "gn:feature_code":"PPL",
    "gn:name":"Wangjiatai",
    "gn:population":0,
    "gn:timezone":"Asia/Shanghai",
    "iso:country":"CN",
    "name:zho_x_preferred":[
        "\u738b\u5bb6\u53f0"
    ],
    "wof:name":"Wangjiatai",
    "wof:placetype":"locality"
},
  "geometry": {"coordinates":[105.74299999999999,36.1923],"type":"Point"}
}