{
  "type": "Feature",
  "properties": {
    "gn:admin1_code":"19.0",
    "gn:asciiname":"Nanchaotiecun",
    "gn:country_code":"CN",
    "gn:dem":54,
    "gn:feature_class":"P",
    "gn:feature_code":"PPL",
    "gn:name":"Nanchaotiecun",
    "gn:population":0,
    "gn:timezone":"Asia/Shanghai",
    "iso:country":"CN",
    "name:zho_x_preferred":[
        "\u5357\u7092\u94c1\u6751"
    ],
    "wof:name":"Nanchaotiecun",
    "wof:placetype":"locality"
},
  "geometry": {"coordinates":[122.78042000000001,40.76118],"type":"Point"}
}