{
  "type": "Feature",
  "properties": {
    "gn:admin1_code":"18.0",
    "gn:asciiname":"Xiaowengjia",
    "gn:country_code":"CN",
    "gn:dem":1028,
    "gn:feature_class":"P",
    "gn:feature_code":"PPL",
    "gn:name":"Xiaowengjia",
    "gn:population":0,
    "gn:timezone":"Asia/Shanghai",
    "iso:country":"CN",
    "name:zho_x_preferred":[
        "\u5c0f\u7fc1\u67b6"
    ],
    "wof:name":"Xiaowengjia",
    "wof:placetype":"locality"
},
  "geometry": {"coordinates":[107.242,26.0521],"type":"Point"}
}