{
  "type": "Feature",
  "properties": {
    "gn:admin1_code":"30.0",
    "gn:asciiname":"Koupucun",
    "gn:country_code":"CN",
    "gn:dem":9,
    "gn:feature_class":"P",
    "gn:feature_code":"PPL",
    "gn:name":"Koupucun",
    "gn:population":0,
    "gn:timezone":"Asia/Shanghai",
    "iso:country":"CN",
    "name:zho_x_preferred":[
        "\u53e3\u57d4\u6751"
    ],
    "wof:name":"Koupucun",
    "wof:placetype":"locality"
},
  "geometry": {"coordinates":[116.48515,23.04051],"type":"Point"}
}