{
  "type": "Feature",
  "properties": {
    "gn:admin1_code":"25.0",
    "gn:asciiname":"Liuguzhuangcun",
    "gn:country_code":"CN",
    "gn:dem":68,
    "gn:feature_class":"P",
    "gn:feature_code":"PPL",
    "gn:name":"Liuguzhuangcun",
    "gn:population":0,
    "gn:timezone":"Asia/Shanghai",
    "iso:country":"CN",
    "name:zho_x_preferred":[
        "\u67f3\u53e4\u5e84\u6751"
    ],
    "wof:name":"Liuguzhuangcun",
    "wof:placetype":"locality"
},
  "geometry": {"coordinates":[120.66349,37.0197],"type":"Point"}
}