{
  "type": "Feature",
  "properties": {
    "gn:admin1_code":"2.0",
    "gn:asciiname":"Bamu",
    "gn:country_code":"CN",
    "gn:dem":160,
    "gn:feature_class":"P",
    "gn:feature_code":"PPL",
    "gn:name":"Bamu",
    "gn:population":0,
    "gn:timezone":"Asia/Shanghai",
    "iso:country":"CN",
    "name:ceb_x_preferred":[
        "Bamu"
    ],
    "name:swe_x_preferred":[
        "Bamu"
    ],
    "name:und_x_variant":[
        "\u516b\u4ea9"
    ],
    "wof:name":"Bamu",
    "wof:placetype":"locality"
},
  "geometry": {"coordinates":[119.30115000000001,30.21199],"type":"Point"}
}