{
  "type": "Feature",
  "properties": {
    "gn:admin1_code":"19.0",
    "gn:asciiname":"Maojiagangzi",
    "gn:country_code":"CN",
    "gn:dem":3,
    "gn:feature_class":"P",
    "gn:feature_code":"PPL",
    "gn:name":"Maojiagangzi",
    "gn:population":0,
    "gn:timezone":"Asia/Shanghai",
    "iso:country":"CN",
    "name:und_x_variant":[
        "\u6bdb\u5bb6\u5c97\u5b50"
    ],
    "name:zho_x_preferred":[
        "\u6bdb\u5bb6\u5c97\u5b50"
    ],
    "wof:name":"Maojiagangzi",
    "wof:placetype":"locality"
},
  "geometry": {"coordinates":[122.29557,41.29412],"type":"Point"}
}