{
  "type": "Feature",
  "properties": {
    "gn:admin1_code":"04",
    "gn:asciiname":"Lingkou",
    "gn:country_code":"CN",
    "gn:dem":8,
    "gn:feature_class":"P",
    "gn:feature_code":"PPLA4",
    "gn:name":"Lingkou",
    "gn:population":0,
    "gn:timezone":"Asia/Shanghai",
    "iso:country":"CN",
    "name:und_x_variant":[
        "Ling-k\u2019ou-chen",
        "Lingkou",
        "Lingkou Zhen"
    ],
    "name:zho_x_preferred":[
        "\u9675\u53e3"
    ],
    "name:zho_x_variant":[
        "\u9675\u53e3\u9547"
    ],
    "wof:name":"Lingkou",
    "wof:placetype":"locality"
},
  "geometry": {"coordinates":[119.65373,31.95008],"type":"Point"}
}