{
  "type": "Feature",
  "properties": {
    "gn:admin1_code":"9.0",
    "gn:asciiname":"Dachenzhai",
    "gn:country_code":"CN",
    "gn:dem":113,
    "gn:feature_class":"P",
    "gn:feature_code":"PPL",
    "gn:name":"Dachenzhai",
    "gn:population":0,
    "gn:timezone":"Asia/Shanghai",
    "iso:country":"CN",
    "name:zho_x_preferred":[
        "\u5927\u9648\u7826"
    ],
    "wof:name":"Dachenzhai",
    "wof:placetype":"locality"
},
  "geometry": {"coordinates":[112.56665,32.83219],"type":"Point"}
}