{
  "type": "Feature",
  "properties": {
    "gn:admin1_code":"8.0",
    "gn:asciiname":"Xunke Sanshibadui",
    "gn:country_code":"CN",
    "gn:dem":252,
    "gn:feature_class":"P",
    "gn:feature_code":"PPLF",
    "gn:name":"Xunke Sanshibadui",
    "gn:population":0,
    "gn:timezone":"Asia/Shanghai",
    "iso:country":"CN",
    "name:zho_x_preferred":[
        "\u900a\u514b\u4e09\u5341\u516b\u961f"
    ],
    "wof:name":"Xunke Sanshibadui",
    "wof:placetype":"locality"
},
  "geometry": {"coordinates":[128.06882999999999,49.31303],"type":"Point"}
}