{
  "type": "Feature",
  "properties": {
    "gn:admin1_code":"2.0",
    "gn:asciiname":"Nanyuan",
    "gn:country_code":"CN",
    "gn:dem":52,
    "gn:feature_class":"P",
    "gn:feature_code":"PPL",
    "gn:name":"Nanyuan",
    "gn:population":0,
    "gn:timezone":"Asia/Shanghai",
    "iso:country":"CN",
    "name:zho_x_preferred":[
        "\u5357\u56ed"
    ],
    "wof:name":"Nanyuan",
    "wof:placetype":"locality"
},
  "geometry": {"coordinates":[121.12734,28.38674],"type":"Point"}
}