{
  "type": "Feature",
  "properties": {
    "gn:admin1_code":"9.0",
    "gn:asciiname":"Sanlizhuang",
    "gn:country_code":"CN",
    "gn:dem":49,
    "gn:feature_class":"P",
    "gn:feature_code":"PPL",
    "gn:name":"Sanlizhuang",
    "gn:population":0,
    "gn:timezone":"Asia/Shanghai",
    "iso:country":"CN",
    "name:zho_x_preferred":[
        "\u4e09\u91cc\u5e84"
    ],
    "wof:name":"Sanlizhuang",
    "wof:placetype":"locality"
},
  "geometry": {"coordinates":[114.84742,33.56417],"type":"Point"}
}