{
  "type": "Feature",
  "properties": {
    "gn:admin1_code":"21",
    "gn:asciiname":"Guanmenshan",
    "gn:country_code":"CN",
    "gn:dem":2272,
    "gn:feature_class":"P",
    "gn:feature_code":"PPL",
    "gn:name":"Guanmenshan",
    "gn:population":0,
    "gn:timezone":"Asia/Shanghai",
    "iso:country":"CN",
    "wof:name":"Guanmenshan",
    "wof:placetype":"locality"
},
  "geometry": {"coordinates":[105.55611,36.42778],"type":"Point"}
}