{
  "type": "Feature",
  "properties": {
    "gn:admin1_code":"6.0",
    "gn:asciiname":"Banggusi",
    "gn:country_code":"CN",
    "gn:dem":3652,
    "gn:feature_class":"P",
    "gn:feature_code":"PPL",
    "gn:name":"Banggusi",
    "gn:population":0,
    "gn:timezone":"Asia/Urumqi",
    "iso:country":"CN",
    "name:zho_x_preferred":[
        "\u90a6\u53e4\u5bfa"
    ],
    "wof:name":"Banggusi",
    "wof:placetype":"locality"
},
  "geometry": {"coordinates":[97.36573,32.80106],"type":"Point"}
}