{
  "type": "Feature",
  "properties": {
    "gn:admin1_code":"4.0",
    "gn:asciiname":"Hazhuangcun",
    "gn:country_code":"CN",
    "gn:dem":23,
    "gn:feature_class":"P",
    "gn:feature_code":"PPL",
    "gn:name":"Hazhuangcun",
    "gn:population":0,
    "gn:timezone":"Asia/Shanghai",
    "iso:country":"CN",
    "name:zho_x_preferred":[
        "\u86e4\u5e84\u6751"
    ],
    "wof:name":"Hazhuangcun",
    "wof:placetype":"locality"
},
  "geometry": {"coordinates":[118.7077,34.58069],"type":"Point"}
}