{
  "type": "Feature",
  "properties": {
    "gn:admin1_code":"30",
    "gn:asciiname":"Jiangkou",
    "gn:country_code":"CN",
    "gn:dem":89,
    "gn:feature_class":"P",
    "gn:feature_code":"PPL",
    "gn:name":"Jiangkou",
    "gn:population":0,
    "gn:timezone":"Asia/Shanghai",
    "iso:country":"CN",
    "name:und_x_variant":[
        "\u6c5f\u53e3"
    ],
    "wof:name":"Jiangkou",
    "wof:placetype":"locality"
},
  "geometry": {"coordinates":[113.99769999999999,24.98469],"type":"Point"}
}