{
  "type": "Feature",
  "properties": {
    "gn:admin1_code":"32.0",
    "gn:asciiname":"Xinping",
    "gn:country_code":"CN",
    "gn:dem":1100,
    "gn:feature_class":"P",
    "gn:feature_code":"PPL",
    "gn:name":"Xinping",
    "gn:population":0,
    "gn:timezone":"Asia/Shanghai",
    "iso:country":"CN",
    "name:zho_x_preferred":[
        "\u65b0\u576a"
    ],
    "wof:name":"Xinping",
    "wof:placetype":"locality"
},
  "geometry": {"coordinates":[104.913,32.2554],"type":"Point"}
}