{
  "type": "Feature",
  "properties": {
    "gn:admin1_code":"4.0",
    "gn:asciiname":"Changweijia",
    "gn:country_code":"CN",
    "gn:dem":6,
    "gn:feature_class":"P",
    "gn:feature_code":"PPL",
    "gn:name":"Changweijia",
    "gn:population":0,
    "gn:timezone":"Asia/Shanghai",
    "iso:country":"CN",
    "name:zho_x_preferred":[
        "\u957f\u9b4f\u5bb6"
    ],
    "wof:name":"Changweijia",
    "wof:placetype":"locality"
},
  "geometry": {"coordinates":[119.79201,32.09629],"type":"Point"}
}