{
  "type": "Feature",
  "properties": {
    "gn:admin1_code":"4.0",
    "gn:asciiname":"Luojian",
    "gn:country_code":"CN",
    "gn:dem":40,
    "gn:feature_class":"P",
    "gn:feature_code":"PPL",
    "gn:name":"Luojian",
    "gn:population":0,
    "gn:timezone":"Asia/Shanghai",
    "iso:country":"CN",
    "name:zho_x_preferred":[
        "\u6d1b\u6da7"
    ],
    "wof:name":"Luojian",
    "wof:placetype":"locality"
},
  "geometry": {"coordinates":[119.27029,31.57504],"type":"Point"}
}