{
  "type": "Feature",
  "properties": {
    "gn:admin1_code":"1.0",
    "gn:asciiname":"Yushan",
    "gn:country_code":"CN",
    "gn:dem":19,
    "gn:feature_class":"P",
    "gn:feature_code":"PPLA3",
    "gn:name":"Yushan",
    "gn:population":0,
    "gn:timezone":"Asia/Shanghai",
    "iso:country":"CN",
    "name:ceb_x_preferred":[
        "Yushan"
    ],
    "name:deu_x_preferred":[
        "Yushan"
    ],
    "name:fra_x_preferred":[
        "Yushan"
    ],
    "name:nld_x_preferred":[
        "Yushan"
    ],
    "name:nor_x_preferred":[
        "Yushan"
    ],
    "name:und_x_variant":[
        "Yushan Jiedao",
        "Yushan Qu"
    ],
    "name:zho_x_preferred":[
        "\u96e8\u5c71"
    ],
    "name:zho_x_variant":[
        "\u96e8\u5c71\u8857\u9053",
        "\u96e8\u5c71\u533a"
    ],
    "wof:name":"Yushan",
    "wof:placetype":"locality"
},
  "geometry": {"coordinates":[118.48456000000002,31.67265],"type":"Point"}
}