{
  "type": "Feature",
  "properties": {
    "gn:admin1_code":"2.0",
    "gn:asciiname":"Shangxujia",
    "gn:country_code":"CN",
    "gn:dem":64,
    "gn:feature_class":"P",
    "gn:feature_code":"PPL",
    "gn:name":"Shangxujia",
    "gn:population":0,
    "gn:timezone":"Asia/Shanghai",
    "iso:country":"CN",
    "name:und_x_variant":[
        "\u4e0a\u8bb8\u5bb6"
    ],
    "wof:name":"Shangxujia",
    "wof:placetype":"locality"
},
  "geometry": {"coordinates":[119.74249,30.08542000000001],"type":"Point"}
}