{
  "type": "Feature",
  "properties": {
    "gn:admin1_code":"9.0",
    "gn:asciiname":"Zhangchanggou",
    "gn:country_code":"CN",
    "gn:dem":429,
    "gn:feature_class":"P",
    "gn:feature_code":"PPL",
    "gn:name":"Zhangchanggou",
    "gn:population":0,
    "gn:timezone":"Asia/Shanghai",
    "iso:country":"CN",
    "name:zho_x_preferred":[
        "\u5f20\u957f\u6c9f"
    ],
    "wof:name":"Zhangchanggou",
    "wof:placetype":"locality"
},
  "geometry": {"coordinates":[112.51567,33.62791],"type":"Point"}
}