{
  "type": "Feature",
  "properties": {
    "gn:admin1_code":"8.0",
    "gn:asciiname":"Jiaxingcun",
    "gn:country_code":"CN",
    "gn:dem":81,
    "gn:feature_class":"P",
    "gn:feature_code":"PPL",
    "gn:name":"Jiaxingcun",
    "gn:population":0,
    "gn:timezone":"Asia/Shanghai",
    "iso:country":"CN",
    "name:zho_x_preferred":[
        "\u4f73\u5174\u6751"
    ],
    "wof:name":"Jiaxingcun",
    "wof:placetype":"locality"
},
  "geometry": {"coordinates":[130.16931,46.83683],"type":"Point"}
}