{
  "type": "Feature",
  "properties": {
    "gn:admin1_code":"8.0",
    "gn:asciiname":"Xingmin Yidui",
    "gn:country_code":"CN",
    "gn:dem":225,
    "gn:feature_class":"P",
    "gn:feature_code":"PPLF",
    "gn:name":"Xingmin Yidui",
    "gn:population":0,
    "gn:timezone":"Asia/Shanghai",
    "iso:country":"CN",
    "name:zho_x_preferred":[
        "\u5174\u6c11\u4e00\u961f"
    ],
    "wof:name":"Xingmin Yidui",
    "wof:placetype":"locality"
},
  "geometry": {"coordinates":[125.50922,47.53894],"type":"Point"}
}