{
  "type": "Feature",
  "properties": {
    "gn:admin1_code":"7",
    "gn:asciiname":"Houyuan",
    "gn:country_code":"CN",
    "gn:dem":200,
    "gn:feature_class":"P",
    "gn:feature_code":"PPL",
    "gn:name":"Houyuan",
    "gn:population":0,
    "gn:timezone":"Asia/Shanghai",
    "iso:country":"CN",
    "name:zho_x_preferred":[
        "\u540e\u56ed"
    ],
    "wof:name":"Houyuan",
    "wof:placetype":"locality"
},
  "geometry": {"coordinates":[118.35553,24.74304],"type":"Point"}
}