{
  "type": "Feature",
  "properties": {
    "gn:admin1_code":"9.0",
    "gn:asciiname":"Zhuangke",
    "gn:country_code":"CN",
    "gn:dem":317,
    "gn:feature_class":"P",
    "gn:feature_code":"PPL",
    "gn:name":"Zhuangke",
    "gn:population":0,
    "gn:timezone":"Asia/Shanghai",
    "iso:country":"CN",
    "name:und_x_variant":[
        "\u5e84\u79d1",
        "Zhuangke"
    ],
    "wof:name":"Zhuangke",
    "wof:placetype":"locality"
},
  "geometry": {"coordinates":[112.79156999999999,33.99025],"type":"Point"}
}