{
  "type": "Feature",
  "properties": {
    "gn:admin1_code":"10",
    "gn:asciiname":"Zhaokuagou",
    "gn:country_code":"CN",
    "gn:dem":1465,
    "gn:feature_class":"P",
    "gn:feature_code":"PPL",
    "gn:name":"Zhaokuagou",
    "gn:population":0,
    "gn:timezone":"Asia/Shanghai",
    "iso:country":"CN",
    "name:zho_x_preferred":[
        "\u8d75\u4f89\u6c9f"
    ],
    "wof:name":"Zhaokuagou",
    "wof:placetype":"locality"
},
  "geometry": {"coordinates":[115.24132,41.13166],"type":"Point"}
}