{
  "type": "Feature",
  "properties": {
    "gn:admin1_code":"19.0",
    "gn:asciiname":"Chagannai",
    "gn:country_code":"CN",
    "gn:dem":249,
    "gn:feature_class":"P",
    "gn:feature_code":"PPL",
    "gn:name":"Chagannai",
    "gn:population":0,
    "gn:timezone":"Asia/Shanghai",
    "iso:country":"CN",
    "name:zho_x_preferred":[
        "\u67e5\u5e72\u4e43"
    ],
    "wof:name":"Chagannai",
    "wof:placetype":"locality"
},
  "geometry": {"coordinates":[121.944,42.1525],"type":"Point"}
}