{
  "type": "Feature",
  "properties": {
    "gn:admin1_code":"11.0",
    "gn:asciiname":"Chenpitang",
    "gn:country_code":"CN",
    "gn:dem":63,
    "gn:feature_class":"P",
    "gn:feature_code":"PPL",
    "gn:name":"Chenpitang",
    "gn:population":0,
    "gn:timezone":"Asia/Shanghai",
    "iso:country":"CN",
    "name:zho_x_preferred":[
        "\u9648\u76ae\u5802"
    ],
    "wof:name":"Chenpitang",
    "wof:placetype":"locality"
},
  "geometry": {"coordinates":[113.21819000000001,28.49505],"type":"Point"}
}