{
  "type": "Feature",
  "properties": {
    "gn:admin1_code":"9",
    "gn:asciiname":"Guanzhai",
    "gn:country_code":"CN",
    "gn:dem":56,
    "gn:feature_class":"P",
    "gn:feature_code":"PPL",
    "gn:name":"Guanzhai",
    "gn:population":0,
    "gn:timezone":"Asia/Shanghai",
    "iso:country":"CN",
    "name:zho_x_preferred":[
        "\u8d2f\u5be8"
    ],
    "wof:name":"Guanzhai",
    "wof:placetype":"locality"
},
  "geometry": {"coordinates":[115.11799999999999,35.607],"type":"Point"}
}