{
  "type": "Feature",
  "properties": {
    "gn:admin1_code":"19.0",
    "gn:asciiname":"Chaijiabuzicun",
    "gn:country_code":"CN",
    "gn:dem":151,
    "gn:feature_class":"P",
    "gn:feature_code":"PPL",
    "gn:name":"Chaijiabuzicun",
    "gn:population":0,
    "gn:timezone":"Asia/Shanghai",
    "iso:country":"CN",
    "name:zho_x_preferred":[
        "\u67f4\u5bb6\u5821\u5b50\u6751"
    ],
    "wof:name":"Chaijiabuzicun",
    "wof:placetype":"locality"
},
  "geometry": {"coordinates":[123.902,42.081],"type":"Point"}
}