{
  "type": "Feature",
  "properties": {
    "gn:admin1_code":"24.0",
    "gn:asciiname":"Dongqicun",
    "gn:country_code":"CN",
    "gn:dem":711,
    "gn:feature_class":"P",
    "gn:feature_code":"PPL",
    "gn:name":"Dongqicun",
    "gn:population":0,
    "gn:timezone":"Asia/Shanghai",
    "iso:country":"CN",
    "name:zho_x_preferred":[
        "\u4e1c\u7941\u6751"
    ],
    "wof:name":"Dongqicun",
    "wof:placetype":"locality"
},
  "geometry": {"coordinates":[111.14268,34.90588],"type":"Point"}
}