{
  "type": "Feature",
  "properties": {
    "gn:admin1_code":"29",
    "gn:asciiname":"Xiandong",
    "gn:country_code":"CN",
    "gn:dem":971,
    "gn:feature_class":"P",
    "gn:feature_code":"PPL",
    "gn:name":"Xiandong",
    "gn:population":0,
    "gn:timezone":"Asia/Shanghai",
    "iso:country":"CN",
    "name:zho_x_preferred":[
        "\u8d24\u6d1e"
    ],
    "wof:name":"Xiandong",
    "wof:placetype":"locality"
},
  "geometry": {"coordinates":[105.572,23.7138],"type":"Point"}
}