{
  "type": "Feature",
  "properties": {
    "gn:admin1_code":"20.0",
    "gn:asciiname":"Bayin Cuogang Sumu",
    "gn:country_code":"CN",
    "gn:dem":690,
    "gn:feature_class":"P",
    "gn:feature_code":"PPL",
    "gn:name":"Bayin Cuogang Sumu",
    "gn:population":0,
    "gn:timezone":"Asia/Shanghai",
    "iso:country":"CN",
    "name:zho_x_preferred":[
        "\u5df4\u97f3\u78cb\u5c97\u82cf\u6728"
    ],
    "wof:name":"Bayin Cuogang Sumu",
    "wof:placetype":"locality"
},
  "geometry": {"coordinates":[120.36127999999999,49.08888],"type":"Point"}
}