{
  "type": "Feature",
  "properties": {
    "gn:admin1_code":"02",
    "gn:asciiname":"Dazhe",
    "gn:country_code":"CN",
    "gn:dem":358,
    "gn:feature_class":"P",
    "gn:feature_code":"PPL",
    "gn:name":"Dazhe",
    "gn:population":0,
    "gn:timezone":"Asia/Shanghai",
    "iso:country":"CN",
    "name:und_x_variant":[
        "Ta-che",
        "Dazhe"
    ],
    "name:zho_x_preferred":[
        "\u5927\u67d8"
    ],
    "wof:name":"Dazhe",
    "wof:placetype":"locality"
},
  "geometry": {"coordinates":[119.10717,28.53023],"type":"Point"}
}