{
  "type": "Feature",
  "properties": {
    "gn:admin1_code":"24.0",
    "gn:asciiname":"Dongxinzhai",
    "gn:country_code":"CN",
    "gn:dem":1006,
    "gn:feature_class":"P",
    "gn:feature_code":"PPL",
    "gn:name":"Dongxinzhai",
    "gn:population":0,
    "gn:timezone":"Asia/Shanghai",
    "iso:country":"CN",
    "name:und_x_variant":[
        "\u4e1c\u8f9b\u5be8"
    ],
    "wof:name":"Dongxinzhai",
    "wof:placetype":"locality"
},
  "geometry": {"coordinates":[113.00933000000001,39.50728],"type":"Point"}
}