{
  "type": "Feature",
  "properties": {
    "gn:admin1_code":"10",
    "gn:asciiname":"Jiehedian",
    "gn:cc2":"CN",
    "gn:country_code":"CN",
    "gn:dem":60,
    "gn:feature_class":"P",
    "gn:feature_code":"PPL",
    "gn:name":"Jiehedian",
    "gn:population":0,
    "gn:timezone":"Asia/Shanghai",
    "iso:country":"CN",
    "name:und_x_variant":[
        "Chieh-ho-tien",
        "Jiehedian"
    ],
    "wof:name":"Jiehedian",
    "wof:placetype":"locality"
},
  "geometry": {"coordinates":[114.48611,36.74889],"type":"Point"}
}