{
  "type": "Feature",
  "properties": {
    "gn:admin1_code":"12.0",
    "gn:asciiname":"Huanglinshu",
    "gn:country_code":"CN",
    "gn:dem":50,
    "gn:feature_class":"P",
    "gn:feature_code":"PPL",
    "gn:name":"Huanglinshu",
    "gn:population":0,
    "gn:timezone":"Asia/Shanghai",
    "iso:country":"CN",
    "name:und_x_variant":[
        "\u9ec4\u6797\u6811"
    ],
    "wof:name":"Huanglinshu",
    "wof:placetype":"locality"
},
  "geometry": {"coordinates":[114.8976,30.80992],"type":"Point"}
}