{
  "type": "Feature",
  "properties": {
    "gn:admin1_code":"20.0",
    "gn:asciiname":"Hong Erdui",
    "gn:country_code":"CN",
    "gn:dem":656,
    "gn:feature_class":"P",
    "gn:feature_code":"PPLF",
    "gn:name":"Hong Erdui",
    "gn:population":0,
    "gn:timezone":"Asia/Shanghai",
    "iso:country":"CN",
    "name:zho_x_preferred":[
        "\u7ea2\u4e8c\u961f"
    ],
    "wof:name":"Hong Erdui",
    "wof:placetype":"locality"
},
  "geometry": {"coordinates":[122.61621,50.67332],"type":"Point"}
}