{
  "type": "Feature",
  "properties": {
    "gn:admin1_code":"11.0",
    "gn:asciiname":"Zhanggu",
    "gn:country_code":"CN",
    "gn:dem":141,
    "gn:feature_class":"P",
    "gn:feature_code":"PPL",
    "gn:name":"Zhanggu",
    "gn:population":0,
    "gn:timezone":"Asia/Shanghai",
    "iso:country":"CN",
    "name:zho_x_preferred":[
        "\u5f20\u53e4"
    ],
    "wof:name":"Zhanggu",
    "wof:placetype":"locality"
},
  "geometry": {"coordinates":[113.41297,26.57012000000001],"type":"Point"}
}