{
  "type": "Feature",
  "properties": {
    "gn:country":"CN",
    "gn:fcode":"ADM3",
    "gn:pop":0,
    "iso:country":"CN",
    "name:mon_x_preferred":[
        "Chen Barag Qi"
    ],
    "name:mon_x_variant":[
        "Chen Barag"
    ],
    "name:unk_x_variant":[
        "Old Barga Banner"
    ],
    "name:zho_x_preferred":[
        "\u9648\u5df4\u5c14\u864e\u65d7"
    ],
    "name:zho_x_variant":[
        "Chenba\u2019erhu Qi",
        "\u9648\u5df4\u5c14\u864e"
    ],
    "qs:name":"Chen Barag Qi",
    "qs:photos_9r":0,
    "qs:photos_sr":0,
    "qs:pop_sr":"0",
    "wof:name":"Chen Barag Qi",
    "wof:placetype":"localadmin",
    "wof:population":0
},
  "geometry": {"coordinates":[119.4246,49.33873],"type":"Point"}
}