{
  "type": "Feature",
  "properties": {
    "gn:admin1_code":"7",
    "gn:asciiname":"Mawei",
    "gn:country_code":"CN",
    "gn:dem":114,
    "gn:feature_class":"P",
    "gn:feature_code":"PPL",
    "gn:name":"Mawei",
    "gn:population":0,
    "gn:timezone":"Asia/Shanghai",
    "iso:country":"CN",
    "name:cdo_x_preferred":[
        "M\u0101-mu\u014di"
    ],
    "name:deu_x_preferred":[
        "Mawei"
    ],
    "name:eus_x_preferred":[
        "Mawei Barrutia"
    ],
    "name:fas_x_preferred":[
        "\u0645\u0627\u0648\u0627\u06cc"
    ],
    "name:hak_x_preferred":[
        "M\u00e2-m\u00ee-kh\u00ee"
    ],
    "name:jpn_x_preferred":[
        "\u99ac\u5c3e\u533a"
    ],
    "name:kor_x_preferred":[
        "\ub9c8\uc6e8\uc774\uad6c"
    ],
    "name:mwl_x_preferred":[
        "Mawei"
    ],
    "name:nor_x_preferred":[
        "Mawei"
    ],
    "name:spa_x_preferred":[
        "M\u0103w\u0115i Q\u016b"
    ],
    "name:swe_x_preferred":[
        "Mawei"
    ],
    "name:vie_x_preferred":[
        "M\u00e3 V\u0129"
    ],
    "name:zho_x_preferred":[
        "\u9a6c\u5c3e\u533a"
    ],
    "wof:name":"Mawei",
    "wof:placetype":"locality"
},
  "geometry": {"coordinates":[119.43917,26.00972],"type":"Point"}
}