{
  "type": "Feature",
  "properties": {
    "gn:admin1_code":"11.0",
    "gn:asciiname":"Langyiyan",
    "gn:country_code":"CN",
    "gn:dem":198,
    "gn:feature_class":"P",
    "gn:feature_code":"PPL",
    "gn:name":"Langyiyan",
    "gn:population":0,
    "gn:timezone":"Asia/Shanghai",
    "iso:country":"CN",
    "name:zho_x_preferred":[
        "Langyiyan"
    ],
    "name:zho_x_variant":[
        "\u6d6a\u8863\u5ca9"
    ],
    "wof:name":"Langyiyan",
    "wof:placetype":"locality"
},
  "geometry": {"coordinates":[111.05928,29.55202],"type":"Point"}
}