{
  "type": "Feature",
  "properties": {
    "gn:admin1_code":"7.0",
    "gn:asciiname":"Shi'anqian",
    "gn:country_code":"CN",
    "gn:dem":356,
    "gn:feature_class":"P",
    "gn:feature_code":"PPL",
    "gn:name":"Shi\u2019anqian",
    "gn:population":0,
    "gn:timezone":"Asia/Shanghai",
    "iso:country":"CN",
    "name:und_x_variant":[
        "\u77f3\u5eb5\u524d"
    ],
    "name:zho_x_preferred":[
        "Shi\u2019anqian"
    ],
    "name:zho_x_variant":[
        "\u77f3\u5eb5\u524d"
    ],
    "wof:name":"Shi'anqian",
    "wof:placetype":"locality"
},
  "geometry": {"coordinates":[116.71989000000001,25.55292],"type":"Point"}
}