{
  "type": "Feature",
  "properties": {
    "gn:admin1_code":"30.0",
    "gn:asciiname":"Nanxicun",
    "gn:country_code":"CN",
    "gn:dem":292,
    "gn:feature_class":"P",
    "gn:feature_code":"PPL",
    "gn:name":"Nanxicun",
    "gn:population":0,
    "gn:timezone":"Asia/Shanghai",
    "iso:country":"CN",
    "name:zho_x_preferred":[
        "\u5357\u6eaa\u6751"
    ],
    "wof:name":"Nanxicun",
    "wof:placetype":"locality"
},
  "geometry": {"coordinates":[116.68129999999999,23.82884],"type":"Point"}
}