{
  "type": "Feature",
  "properties": {
    "gn:admin1_code":"26.0",
    "gn:asciiname":"Laoyinpo",
    "gn:country_code":"CN",
    "gn:dem":789,
    "gn:feature_class":"P",
    "gn:feature_code":"PPL",
    "gn:name":"Laoyinpo",
    "gn:population":0,
    "gn:timezone":"Asia/Shanghai",
    "iso:country":"CN",
    "name:zho_x_preferred":[
        "\u8001\u9634\u5761"
    ],
    "wof:name":"Laoyinpo",
    "wof:placetype":"locality"
},
  "geometry": {"coordinates":[108.96442,32.46155],"type":"Point"}
}