{
  "type": "Feature",
  "properties": {
    "gn:admin1_code":"8.0",
    "gn:asciiname":"Nianfeng Shouliedui",
    "gn:country_code":"CN",
    "gn:dem":253,
    "gn:feature_class":"P",
    "gn:feature_code":"PPLF",
    "gn:name":"Nianfeng Shouliedui",
    "gn:population":0,
    "gn:timezone":"Asia/Shanghai",
    "iso:country":"CN",
    "name:zho_x_preferred":[
        "\u5e74\u4e30\u72e9\u730e\u961f"
    ],
    "wof:name":"Nianfeng Shouliedui",
    "wof:placetype":"locality"
},
  "geometry": {"coordinates":[128.07830000000001,46.8099],"type":"Point"}
}