{
  "type": "Feature",
  "properties": {
    "gn:admin1_code":"4.0",
    "gn:asciiname":"Shuangyingcun",
    "gn:country_code":"CN",
    "gn:dem":-2,
    "gn:feature_class":"P",
    "gn:feature_code":"PPL",
    "gn:name":"Shuangyingcun",
    "gn:population":0,
    "gn:timezone":"Asia/Shanghai",
    "iso:country":"CN",
    "name:zho_x_preferred":[
        "\u53cc\u8425\u6751"
    ],
    "wof:name":"Shuangyingcun",
    "wof:placetype":"locality"
},
  "geometry": {"coordinates":[119.66388000000001,33.76868],"type":"Point"}
}