{
  "type": "Feature",
  "properties": {
    "gn:admin1_code":"29.0",
    "gn:asciiname":"Tuanqing",
    "gn:country_code":"CN",
    "gn:dem":2532,
    "gn:feature_class":"P",
    "gn:feature_code":"PPL",
    "gn:name":"Tuanqing",
    "gn:population":0,
    "gn:timezone":"Asia/Shanghai",
    "iso:country":"CN",
    "name:zho_x_preferred":[
        "\u56e2\u7b90"
    ],
    "wof:name":"Tuanqing",
    "wof:placetype":"locality"
},
  "geometry": {"coordinates":[103.42700000000001,25.9879],"type":"Point"}
}