{
  "type": "Feature",
  "properties": {
    "gn:admin1_code":"5.0",
    "gn:asciiname":"Hou'erlongshan",
    "gn:country_code":"CN",
    "gn:dem":146,
    "gn:feature_class":"P",
    "gn:feature_code":"PPL",
    "gn:name":"Hou\u2019erlongshan",
    "gn:population":0,
    "gn:timezone":"Asia/Shanghai",
    "iso:country":"CN",
    "name:und_x_variant":[
        "Hou\u2019erlongshan"
    ],
    "name:zho_x_preferred":[
        "\u540e\u4e8c\u9f99\u5c71"
    ],
    "wof:name":"Hou'erlongshan",
    "wof:placetype":"locality"
},
  "geometry": {"coordinates":[123.62909999999999,43.84475],"type":"Point"}
}