{
  "type": "Feature",
  "properties": {
    "gn:admin1_code":"25.0",
    "gn:asciiname":"Dongtingcun",
    "gn:country_code":"CN",
    "gn:dem":40,
    "gn:feature_class":"P",
    "gn:feature_code":"PPL",
    "gn:name":"Dongtingcun",
    "gn:population":0,
    "gn:timezone":"Asia/Shanghai",
    "iso:country":"CN",
    "name:zho_x_preferred":[
        "\u4e1c\u5385\u6751"
    ],
    "wof:name":"Dongtingcun",
    "wof:placetype":"locality"
},
  "geometry": {"coordinates":[121.19576000000001,37.47178],"type":"Point"}
}