{
  "type": "Feature",
  "properties": {
    "gn:admin1_code":"26.0",
    "gn:asciiname":"Wokengzi",
    "gn:country_code":"CN",
    "gn:dem":1243,
    "gn:feature_class":"P",
    "gn:feature_code":"PPL",
    "gn:name":"Wokengzi",
    "gn:population":0,
    "gn:timezone":"Asia/Shanghai",
    "iso:country":"CN",
    "name:und_x_variant":[
        "\u7a9d\u5751\u5b50"
    ],
    "wof:name":"Wokengzi",
    "wof:placetype":"locality"
},
  "geometry": {"coordinates":[106.36499999999999,33.25646],"type":"Point"}
}