{
  "type": "Feature",
  "properties": {
    "gn:admin1_code":"7",
    "gn:asciiname":"Jianli",
    "gn:country_code":"CN",
    "gn:dem":280,
    "gn:feature_class":"P",
    "gn:feature_code":"PPL",
    "gn:name":"Jianli",
    "gn:population":0,
    "gn:timezone":"Asia/Shanghai",
    "iso:country":"CN",
    "name:und_x_variant":[
        "\u7b15\u91cc",
        "Jianli"
    ],
    "wof:name":"Jianli",
    "wof:placetype":"locality"
},
  "geometry": {"coordinates":[117.97889000000001,24.76056],"type":"Point"}
}