{
  "type": "Feature",
  "properties": {
    "gn:admin1_code":"14.0",
    "gn:asciiname":"Xarqog",
    "gn:country_code":"CN",
    "gn:dem":4118,
    "gn:feature_class":"P",
    "gn:feature_code":"PPLF",
    "gn:name":"Xarqog",
    "gn:population":0,
    "gn:timezone":"Asia/Urumqi",
    "iso:country":"CN",
    "name:bod_x_preferred":[
        "Xarqog"
    ],
    "name:zho_x_preferred":[
        "Xiajue"
    ],
    "name:zho_x_variant":[
        "\u4e0b\u89c9",
        "Pachong",
        "\u5e15\u51b2"
    ],
    "wof:name":"Xarqog",
    "wof:placetype":"locality"
},
  "geometry": {"coordinates":[89.304,29.004],"type":"Point"}
}