{
  "type": "Feature",
  "properties": {
    "gn:admin1_code":"14.0",
    "gn:asciiname":"Xinshacun",
    "gn:country_code":"CN",
    "gn:dem":3509,
    "gn:feature_class":"P",
    "gn:feature_code":"PPL",
    "gn:name":"Xinshacun",
    "gn:population":0,
    "gn:timezone":"Asia/Urumqi",
    "iso:country":"CN",
    "name:zho_x_preferred":[
        "\u65b0\u6c99\u6751"
    ],
    "wof:name":"Xinshacun",
    "wof:placetype":"locality"
},
  "geometry": {"coordinates":[92.64407,29.05892],"type":"Point"}
}