{
  "type": "Feature",
  "properties": {
    "gn:admin1_code":"24",
    "gn:asciiname":"Guobeicun",
    "gn:country_code":"CN",
    "gn:dem":993,
    "gn:feature_class":"P",
    "gn:feature_code":"PPL",
    "gn:name":"Guobeicun",
    "gn:population":0,
    "gn:timezone":"Asia/Shanghai",
    "iso:country":"CN",
    "name:und_x_variant":[
        "Kuo-pei",
        "Guobei",
        "Guobeicun"
    ],
    "name:zho_x_preferred":[
        "\u90ed\u80cc\u6751"
    ],
    "wof:name":"Guobeicun",
    "wof:placetype":"locality"
},
  "geometry": {"coordinates":[113.02855,35.53605],"type":"Point"}
}