{
  "type": "Feature",
  "properties": {
    "gn:admin1_code":"1.0",
    "gn:asciiname":"Hongtangcun",
    "gn:country_code":"CN",
    "gn:dem":88,
    "gn:feature_class":"P",
    "gn:feature_code":"PPL",
    "gn:name":"Hongtangcun",
    "gn:population":0,
    "gn:timezone":"Asia/Shanghai",
    "iso:country":"CN",
    "name:zho_x_preferred":[
        "\u6d2a\u5858\u6751"
    ],
    "wof:name":"Hongtangcun",
    "wof:placetype":"locality"
},
  "geometry": {"coordinates":[118.17308,32.4867],"type":"Point"}
}