{
  "type": "Feature",
  "properties": {
    "gn:admin1_code":"25",
    "gn:asciiname":"Guojiazhai",
    "gn:cc2":"CN",
    "gn:country_code":"CN",
    "gn:dem":53,
    "gn:feature_class":"P",
    "gn:feature_code":"PPL",
    "gn:name":"Guojiazhai",
    "gn:population":0,
    "gn:timezone":"Asia/Shanghai",
    "iso:country":"CN",
    "name:und_x_variant":[
        "Kuo-chia-chai",
        "Guojiazhai"
    ],
    "wof:name":"Guojiazhai",
    "wof:placetype":"locality"
},
  "geometry": {"coordinates":[120.21111000000001,36.83333],"type":"Point"}
}