{
  "type": "Feature",
  "properties": {
    "gn:admin1_code":"10",
    "gn:asciiname":"Disantun",
    "gn:country_code":"CN",
    "gn:dem":22,
    "gn:feature_class":"P",
    "gn:feature_code":"PPL",
    "gn:name":"Disantun",
    "gn:population":0,
    "gn:timezone":"Asia/Shanghai",
    "iso:country":"CN",
    "name:zho_x_preferred":[
        "\u7b2c\u4e09\u5c6f"
    ],
    "wof:name":"Disantun",
    "wof:placetype":"locality"
},
  "geometry": {"coordinates":[116.3218,37.59546],"type":"Point"}
}