{
  "type": "Feature",
  "properties": {
    "gn:admin1_code":"29.0",
    "gn:asciiname":"Nilagu",
    "gn:country_code":"CN",
    "gn:dem":1348,
    "gn:feature_class":"P",
    "gn:feature_code":"PPL",
    "gn:name":"Nilagu",
    "gn:population":0,
    "gn:timezone":"Asia/Shanghai",
    "iso:country":"CN",
    "name:zho_x_preferred":[
        "\u5c3c\u62c9\u59d1"
    ],
    "wof:name":"Nilagu",
    "wof:placetype":"locality"
},
  "geometry": {"coordinates":[103.19499999999999,26.0903],"type":"Point"}
}