{
  "type": "Feature",
  "properties": {
    "gn:admin1_code":"5.0",
    "gn:asciiname":"Humiling",
    "gn:country_code":"CN",
    "gn:dem":622,
    "gn:feature_class":"P",
    "gn:feature_code":"PPL",
    "gn:name":"Humiling",
    "gn:population":0,
    "gn:timezone":"Asia/Shanghai",
    "iso:country":"CN",
    "name:und_x_variant":[
        "\u80e1\u8ff7\u5cad"
    ],
    "wof:name":"Humiling",
    "wof:placetype":"locality"
},
  "geometry": {"coordinates":[125.43431,41.91252],"type":"Point"}
}