{
  "type": "Feature",
  "properties": {
    "gn:admin1_code":"25",
    "gn:asciiname":"Beihenghe",
    "gn:country_code":"CN",
    "gn:dem":329,
    "gn:feature_class":"P",
    "gn:feature_code":"PPL",
    "gn:name":"Beihenghe",
    "gn:population":0,
    "gn:timezone":"Asia/Shanghai",
    "iso:country":"CN",
    "name:zho_x_preferred":[
        "\u5317\u6a2a\u6cb3"
    ],
    "wof:name":"Beihenghe",
    "wof:placetype":"locality"
},
  "geometry": {"coordinates":[117.416,36.5482],"type":"Point"}
}