{
  "type": "Feature",
  "properties": {
    "gn:admin1_code":"25.0",
    "gn:asciiname":"Daguxiancun",
    "gn:country_code":"CN",
    "gn:dem":51,
    "gn:feature_class":"P",
    "gn:feature_code":"PPL",
    "gn:name":"Daguxiancun",
    "gn:population":0,
    "gn:timezone":"Asia/Shanghai",
    "iso:country":"CN",
    "name:zho_x_preferred":[
        "\u5927\u53e4\u53bf\u6751"
    ],
    "wof:name":"Daguxiancun",
    "wof:placetype":"locality"
},
  "geometry": {"coordinates":[119.43436,36.2166],"type":"Point"}
}