{
  "type": "Feature",
  "properties": {
    "gn:admin1_code":"25",
    "gn:asciiname":"Liguanzhuang",
    "gn:country_code":"CN",
    "gn:dem":228,
    "gn:feature_class":"P",
    "gn:feature_code":"PPL",
    "gn:name":"Liguanzhuang",
    "gn:population":0,
    "gn:timezone":"Asia/Shanghai",
    "iso:country":"CN",
    "name:zho_x_preferred":[
        "\u674e\u5b98\u5e84"
    ],
    "wof:name":"Liguanzhuang",
    "wof:placetype":"locality"
},
  "geometry": {"coordinates":[117.88200000000001,35.7915],"type":"Point"}
}