{
  "type": "Feature",
  "properties": {
    "gn:admin1_code":"5.0",
    "gn:asciiname":"Dashibahaocun",
    "gn:country_code":"CN",
    "gn:dem":178,
    "gn:feature_class":"P",
    "gn:feature_code":"PPL",
    "gn:name":"Dashibahaocun",
    "gn:population":0,
    "gn:timezone":"Asia/Shanghai",
    "iso:country":"CN",
    "name:zho_x_preferred":[
        "\u5927\u5341\u516b\u53f7\u6751"
    ],
    "wof:name":"Dashibahaocun",
    "wof:placetype":"locality"
},
  "geometry": {"coordinates":[126.09059999999999,45.08256],"type":"Point"}
}