{
  "type": "Feature",
  "properties": {
    "gn:admin1_code":"16",
    "gn:asciiname":"Hongjiang",
    "gn:country_code":"CN",
    "gn:dem":154,
    "gn:feature_class":"P",
    "gn:feature_code":"PPL",
    "gn:name":"Hongjiang",
    "gn:population":0,
    "gn:timezone":"Asia/Shanghai",
    "iso:country":"CN",
    "name:ceb_x_preferred":[
        "Hongjiang"
    ],
    "name:deu_x_preferred":[
        "Hongjiang"
    ],
    "name:fra_x_preferred":[
        "Hongjiang"
    ],
    "name:ita_x_preferred":[
        "Hongjiang"
    ],
    "name:jpn_x_preferred":[
        "\u6d2a\u6c5f\u5e02"
    ],
    "name:kik_x_preferred":[
        "Hongjiang"
    ],
    "name:kor_x_preferred":[
        "\ud6d9\uc7a5\uc2dc"
    ],
    "name:mlg_x_preferred":[
        "Hongjiang"
    ],
    "name:nld_x_preferred":[
        "Hongjiang"
    ],
    "name:nor_x_preferred":[
        "Hongjiang"
    ],
    "name:pam_x_preferred":[
        "Hongjiang"
    ],
    "name:swe_x_preferred":[
        "Hongjiang"
    ],
    "name:vie_x_preferred":[
        "H\u1ed3ng Giang"
    ],
    "name:zho_x_preferred":[
        "\u6d2a\u6c5f"
    ],
    "name:zho_x_variant":[
        "\u6d2a\u6c5f\u5e02"
    ],
    "wof:name":"Hongjiang",
    "wof:placetype":"locality"
},
  "geometry": {"coordinates":[107.167,22.0636],"type":"Point"}
}