{
  "type": "Feature",
  "properties": {
    "gn:admin1_code":"13.0",
    "gn:asciiname":"Ergong",
    "gn:country_code":"CN",
    "gn:dem":784,
    "gn:feature_class":"P",
    "gn:feature_code":"PPLA4",
    "gn:name":"Ergong",
    "gn:population":0,
    "gn:timezone":"Asia/Urumqi",
    "iso:country":"CN",
    "name:und_x_variant":[
        "\u4e8c\u5de5",
        "Ergong Jiedao",
        "\u4e8c\u5de5\u8857\u9053"
    ],
    "wof:name":"Ergong",
    "wof:placetype":"locality"
},
  "geometry": {"coordinates":[87.56667,43.85],"type":"Point"}
}