{
  "type": "Feature",
  "properties": {
    "gn:admin1_code":"8.0",
    "gn:asciiname":"Baiyanghe",
    "gn:country_code":"CN",
    "gn:dem":623,
    "gn:feature_class":"P",
    "gn:feature_code":"PPLA4",
    "gn:name":"Baiyanghe",
    "gn:population":0,
    "gn:timezone":"Asia/Urumqi",
    "iso:country":"CN",
    "name:und_x_variant":[
        "Baiyanghe Hasakezu Xiang",
        "Baiyanghe Hasakezu"
    ],
    "name:zho_x_preferred":[
        "\u67cf\u6768\u6cb3"
    ],
    "name:zho_x_variant":[
        "\u67cf\u6768\u6cb3\u54c8\u8428\u514b\u65cf\u4e61",
        "\u67cf\u6768\u6cb3\u54c8\u8428\u514b\u65cf"
    ],
    "wof:name":"Baiyanghe",
    "wof:placetype":"locality"
},
  "geometry": {"coordinates":[87.76464,44.01886],"type":"Point"}
}