{
  "type": "Feature",
  "properties": {
    "gn:admin1_code":"21.0",
    "gn:asciiname":"Huanghaowan",
    "gn:country_code":"CN",
    "gn:dem":1995,
    "gn:feature_class":"P",
    "gn:feature_code":"PPL",
    "gn:name":"Huanghaowan",
    "gn:population":0,
    "gn:timezone":"Asia/Shanghai",
    "iso:country":"CN",
    "name:zho_x_preferred":[
        "\u9ec4\u84bf\u6e7e"
    ],
    "wof:name":"Huanghaowan",
    "wof:placetype":"locality"
},
  "geometry": {"coordinates":[105.81399999999999,36.2775],"type":"Point"}
}