{
  "type": "Feature",
  "properties": {
    "gn:admin1_code":"26.0",
    "gn:asciiname":"Taoquyuancun",
    "gn:country_code":"CN",
    "gn:dem":1297,
    "gn:feature_class":"P",
    "gn:feature_code":"PPL",
    "gn:name":"Taoquyuancun",
    "gn:population":0,
    "gn:timezone":"Asia/Shanghai",
    "iso:country":"CN",
    "name:zho_x_preferred":[
        "\u6843\u6e20\u586c\u6751"
    ],
    "wof:name":"Taoquyuancun",
    "wof:placetype":"locality"
},
  "geometry": {"coordinates":[108.61405000000001,34.9564],"type":"Point"}
}