{
  "type": "Feature",
  "properties": {
    "gn:admin1_code":"15.0",
    "gn:asciiname":"Baiya",
    "gn:country_code":"CN",
    "gn:dem":1554,
    "gn:feature_class":"P",
    "gn:feature_code":"PPL",
    "gn:name":"Baiya",
    "gn:population":0,
    "gn:timezone":"Asia/Shanghai",
    "iso:country":"CN",
    "name:und_x_variant":[
        "\u767d\u5d16"
    ],
    "wof:name":"Baiya",
    "wof:placetype":"locality"
},
  "geometry": {"coordinates":[106.00826000000001,33.71047],"type":"Point"}
}