{
  "type": "Feature",
  "properties": {
    "gn:admin1_code":"11.0",
    "gn:asciiname":"Yunxi",
    "gn:country_code":"CN",
    "gn:dem":47,
    "gn:feature_class":"P",
    "gn:feature_code":"PPLA3",
    "gn:name":"Yunxi",
    "gn:population":0,
    "gn:timezone":"Asia/Shanghai",
    "iso:country":"CN",
    "name:ceb_x_preferred":[
        "Yunxi"
    ],
    "name:deu_x_preferred":[
        "Yunxi"
    ],
    "name:fra_x_preferred":[
        "Yunxi"
    ],
    "name:nor_x_preferred":[
        "Yunxi"
    ],
    "name:swe_x_preferred":[
        "Yunxi"
    ],
    "name:und_x_variant":[
        "Y\u00fcn-hsi",
        "Yunxi",
        "Yunxi Qu"
    ],
    "name:zho_x_preferred":[
        "\u4e91\u6eaa"
    ],
    "name:zho_x_variant":[
        "Y\u00fcn-hsi",
        "\u4e91\u6eaa\u533a"
    ],
    "wof:name":"Yunxi",
    "wof:placetype":"locality"
},
  "geometry": {"coordinates":[113.2458,29.47328],"type":"Point"}
}