{
  "type": "Feature",
  "properties": {
    "gn:admin1_code":"12.0",
    "gn:asciiname":"Magang",
    "gn:country_code":"CN",
    "gn:dem":142,
    "gn:feature_class":"P",
    "gn:feature_code":"PPLA4",
    "gn:name":"Magang",
    "gn:population":0,
    "gn:timezone":"Asia/Shanghai",
    "iso:country":"CN",
    "name:ceb_x_preferred":[
        "Magang"
    ],
    "name:swe_x_preferred":[
        "Magang"
    ],
    "name:und_x_variant":[
        "Magang Zhen"
    ],
    "name:zho_x_preferred":[
        "\u9a6c\u6e2f"
    ],
    "name:zho_x_variant":[
        "\u9a6c\u6e2f\u9547"
    ],
    "wof:name":"Magang",
    "wof:placetype":"locality"
},
  "geometry": {"coordinates":[113.77337,29.18406],"type":"Point"}
}