{
  "type": "Feature",
  "properties": {
    "gn:admin1_code":"23.0",
    "gn:asciiname":"Beiqiao",
    "gn:country_code":"CN",
    "gn:dem":6,
    "gn:feature_class":"P",
    "gn:feature_code":"PPL",
    "gn:name":"Beiqiao",
    "gn:population":0,
    "gn:timezone":"Asia/Shanghai",
    "iso:country":"CN",
    "name:zho_x_preferred":[
        "Beiqiao"
    ],
    "name:zho_x_variant":[
        "\u5317\u6865"
    ],
    "wof:name":"Beiqiao",
    "wof:placetype":"locality"
},
  "geometry": {"coordinates":[121.29116,31.80032000000001],"type":"Point"}
}