{
  "type": "Feature",
  "properties": {
    "gn:admin1_code":"19.0",
    "gn:asciiname":"Shangjuntai",
    "gn:country_code":"CN",
    "gn:dem":5,
    "gn:feature_class":"P",
    "gn:feature_code":"PPL",
    "gn:name":"Shangjuntai",
    "gn:population":0,
    "gn:timezone":"Asia/Shanghai",
    "iso:country":"CN",
    "name:zho_x_preferred":[
        "\u8d4f\u519b\u53f0"
    ],
    "wof:name":"Shangjuntai",
    "wof:placetype":"locality"
},
  "geometry": {"coordinates":[122.19212,40.82974],"type":"Point"}
}