{
  "type": "Feature",
  "properties": {
    "gn:admin1_code":"32.0",
    "gn:asciiname":"Xifengsi",
    "gn:country_code":"CN",
    "gn:dem":355,
    "gn:feature_class":"P",
    "gn:feature_code":"PPL",
    "gn:name":"Xifengsi",
    "gn:population":0,
    "gn:timezone":"Asia/Shanghai",
    "iso:country":"CN",
    "name:zho_x_preferred":[
        "\u897f\u5cf0\u5bfa"
    ],
    "wof:name":"Xifengsi",
    "wof:placetype":"locality"
},
  "geometry": {"coordinates":[105.14349,30.78854],"type":"Point"}
}