{
  "type": "Feature",
  "properties": {
    "gn:admin1_code":"3",
    "gn:asciiname":"Xiaguanli",
    "gn:country_code":"CN",
    "gn:dem":76,
    "gn:feature_class":"P",
    "gn:feature_code":"PPL",
    "gn:name":"Xiaguanli",
    "gn:population":0,
    "gn:timezone":"Asia/Shanghai",
    "iso:country":"CN",
    "name:zho_x_preferred":[
        "\u4e0b\u5b98\u4fda"
    ],
    "wof:name":"Xiaguanli",
    "wof:placetype":"locality"
},
  "geometry": {"coordinates":[114.768,26.4904],"type":"Point"}
}