{
  "type": "Feature",
  "properties": {
    "gn:admin1_code":"02",
    "gn:asciiname":"Jitou",
    "gn:country_code":"CN",
    "gn:dem":518,
    "gn:feature_class":"P",
    "gn:feature_code":"PPL",
    "gn:name":"Jitou",
    "gn:population":0,
    "gn:timezone":"Asia/Shanghai",
    "iso:country":"CN",
    "name:und_x_variant":[
        "\u6f08\u5934",
        "Jitou"
    ],
    "wof:name":"Jitou",
    "wof:placetype":"locality"
},
  "geometry": {"coordinates":[119.63039000000001,27.88816],"type":"Point"}
}