{
  "type": "Feature",
  "properties": {
    "gn:admin1_code":"24.0",
    "gn:asciiname":"Yaowan",
    "gn:country_code":"CN",
    "gn:dem":1275,
    "gn:feature_class":"P",
    "gn:feature_code":"PPL",
    "gn:name":"Yaowan",
    "gn:population":0,
    "gn:timezone":"Asia/Shanghai",
    "iso:country":"CN",
    "name:und_x_variant":[
        "Yao-wan-ts\u2019un",
        "Yaowan"
    ],
    "name:zho_x_preferred":[
        "\u7a91\u6e7e"
    ],
    "wof:name":"Yaowan",
    "wof:placetype":"locality"
},
  "geometry": {"coordinates":[113.25984,36.83294],"type":"Point"}
}