{
  "type": "Feature",
  "properties": {
    "gn:admin1_code":"20.0",
    "gn:asciiname":"Ne'er Keqi",
    "gn:country_code":"CN",
    "gn:dem":405,
    "gn:feature_class":"P",
    "gn:feature_code":"PPL",
    "gn:name":"Ne\u2019er Keqi",
    "gn:population":0,
    "gn:timezone":"Asia/Shanghai",
    "iso:country":"CN",
    "name:und_x_variant":[
        "Ne\u2019er Keqi"
    ],
    "name:zho_x_preferred":[
        "\u8bb7\u5c14\u514b\u6c14"
    ],
    "wof:name":"Ne'er Keqi",
    "wof:placetype":"locality"
},
  "geometry": {"coordinates":[124.26503,50.14117],"type":"Point"}
}