{
  "type": "Feature",
  "properties": {
    "gn:admin1_code":"1.0",
    "gn:asciiname":"Shijicun",
    "gn:country_code":"CN",
    "gn:dem":74,
    "gn:feature_class":"P",
    "gn:feature_code":"PPL",
    "gn:name":"Shijicun",
    "gn:population":0,
    "gn:timezone":"Asia/Shanghai",
    "iso:country":"CN",
    "name:zho_x_preferred":[
        "\u77f3\u96c6\u6751"
    ],
    "wof:name":"Shijicun",
    "wof:placetype":"locality"
},
  "geometry": {"coordinates":[117.16101999999999,32.088],"type":"Point"}
}