{
  "type": "Feature",
  "properties": {
    "gn:admin1_code":"32.0",
    "gn:asciiname":"San'ao'an",
    "gn:country_code":"CN",
    "gn:dem":427,
    "gn:feature_class":"P",
    "gn:feature_code":"PPL",
    "gn:name":"San\u2019ao\u2019an",
    "gn:population":0,
    "gn:timezone":"Asia/Shanghai",
    "iso:country":"CN",
    "name:zho_x_preferred":[
        "\u4e09\u6556\u5eb5"
    ],
    "name:zho_x_variant":[
        "San\u2019ao\u2019an"
    ],
    "wof:name":"San'ao'an",
    "wof:placetype":"locality"
},
  "geometry": {"coordinates":[105.10602,30.00406],"type":"Point"}
}