{
  "type": "Feature",
  "properties": {
    "gn:admin1_code":"24",
    "gn:asciiname":"Nan'an",
    "gn:country_code":"CN",
    "gn:dem":753,
    "gn:feature_class":"P",
    "gn:feature_code":"PPL",
    "gn:name":"Nan\u2019an",
    "gn:population":0,
    "gn:timezone":"Asia/Shanghai",
    "iso:country":"CN",
    "name:und_x_variant":[
        "Nan-an-ts\u2019un",
        "Nan\u2019an"
    ],
    "wof:name":"Nan'an",
    "wof:placetype":"locality"
},
  "geometry": {"coordinates":[112.24778000000001,37.48417],"type":"Point"}
}