{
  "type": "Feature",
  "properties": {
    "gn:admin1_code":"19.0",
    "gn:asciiname":"Lijiatuozi",
    "gn:country_code":"CN",
    "gn:dem":84,
    "gn:feature_class":"P",
    "gn:feature_code":"PPL",
    "gn:name":"Lijiatuozi",
    "gn:population":0,
    "gn:timezone":"Asia/Shanghai",
    "iso:country":"CN",
    "name:zho_x_preferred":[
        "\u674e\u5bb6\u5768\u5b50"
    ],
    "wof:name":"Lijiatuozi",
    "wof:placetype":"locality"
},
  "geometry": {"coordinates":[123.578,42.9119],"type":"Point"}
}