{
  "type": "Feature",
  "properties": {
    "gn:admin1_code":"15.0",
    "gn:asciiname":"Jiuyuanli",
    "gn:country_code":"CN",
    "gn:dem":1717,
    "gn:feature_class":"P",
    "gn:feature_code":"PPL",
    "gn:name":"Jiuyuanli",
    "gn:population":0,
    "gn:timezone":"Asia/Shanghai",
    "iso:country":"CN",
    "name:zho_x_preferred":[
        "\u4e5d\u9662\u91cc"
    ],
    "wof:name":"Jiuyuanli",
    "wof:placetype":"locality"
},
  "geometry": {"coordinates":[105.09368000000001,33.17412],"type":"Point"}
}