{
  "type": "Feature",
  "properties": {
    "gn:admin1_code":"15.0",
    "gn:asciiname":"Yujiazhuang",
    "gn:country_code":"CN",
    "gn:dem":2165,
    "gn:feature_class":"P",
    "gn:feature_code":"PPL",
    "gn:name":"Yujiazhuang",
    "gn:population":0,
    "gn:timezone":"Asia/Shanghai",
    "iso:country":"CN",
    "name:zho_x_preferred":[
        "\u4f59\u5bb6\u5e84"
    ],
    "wof:name":"Yujiazhuang",
    "wof:placetype":"locality"
},
  "geometry": {"coordinates":[103.07599999999999,36.5154],"type":"Point"}
}