{
  "type": "Feature",
  "properties": {
    "gn:admin1_code":"29.0",
    "gn:asciiname":"Zichu",
    "gn:country_code":"CN",
    "gn:dem":2033,
    "gn:feature_class":"P",
    "gn:feature_code":"PPL",
    "gn:name":"Zichu",
    "gn:population":0,
    "gn:timezone":"Asia/Shanghai",
    "iso:country":"CN",
    "name:zho_x_preferred":[
        "\u7d2b\u5904"
    ],
    "wof:name":"Zichu",
    "wof:placetype":"locality"
},
  "geometry": {"coordinates":[103.55800000000001,24.8446],"type":"Point"}
}