{
  "type": "Feature",
  "properties": {
    "gn:admin1_code":"03",
    "gn:asciiname":"Caijialing",
    "gn:country_code":"CN",
    "gn:dem":49,
    "gn:feature_class":"P",
    "gn:feature_code":"PPL",
    "gn:name":"Caijialing",
    "gn:population":0,
    "gn:timezone":"Asia/Shanghai",
    "iso:country":"CN",
    "name:und_x_variant":[
        "\u8521\u5bb6\u5cad"
    ],
    "wof:name":"Caijialing",
    "wof:placetype":"locality"
},
  "geometry": {"coordinates":[116.40354000000001,29.47641],"type":"Point"}
}