{
  "type": "Feature",
  "properties": {
    "gn:admin1_code":"10.0",
    "gn:asciiname":"Yangguanzhuang",
    "gn:country_code":"CN",
    "gn:dem":4,
    "gn:feature_class":"P",
    "gn:feature_code":"PPL",
    "gn:name":"Yangguanzhuang",
    "gn:population":0,
    "gn:timezone":"Asia/Shanghai",
    "iso:country":"CN",
    "name:zho_x_preferred":[
        "\u6768\u5b98\u5e84"
    ],
    "wof:name":"Yangguanzhuang",
    "wof:placetype":"locality"
},
  "geometry": {"coordinates":[117.21299999999999,38.5511],"type":"Point"}
}