{
  "type": "Feature",
  "properties": {
    "gn:admin1_code":"19.0",
    "gn:asciiname":"Tangjia Wobu",
    "gn:country_code":"CN",
    "gn:dem":13,
    "gn:feature_class":"P",
    "gn:feature_code":"PPL",
    "gn:name":"Tangjia Wobu",
    "gn:population":0,
    "gn:timezone":"Asia/Shanghai",
    "iso:country":"CN",
    "name:zho_x_preferred":[
        "\u5510\u5bb6\u7a9d\u5821"
    ],
    "wof:name":"Tangjia Wobu",
    "wof:placetype":"locality"
},
  "geometry": {"coordinates":[122.544,41.5428],"type":"Point"}
}