{
  "type": "Feature",
  "properties": {
    "gn:admin1_code":"16.0",
    "gn:asciiname":"Tangli",
    "gn:country_code":"CN",
    "gn:dem":164,
    "gn:feature_class":"P",
    "gn:feature_code":"PPL",
    "gn:name":"Tangli",
    "gn:population":0,
    "gn:timezone":"Asia/Shanghai",
    "iso:country":"CN",
    "name:zho_x_preferred":[
        "\u68e0\u68a8"
    ],
    "wof:name":"Tangli",
    "wof:placetype":"locality"
},
  "geometry": {"coordinates":[109.67100000000001,22.5326],"type":"Point"}
}