{
  "type": "Feature",
  "properties": {
    "gn:admin1_code":"03",
    "gn:asciiname":"Huangjinbu",
    "gn:country_code":"CN",
    "gn:dem":25,
    "gn:feature_class":"P",
    "gn:feature_code":"PPLA4",
    "gn:name":"Huangjinbu",
    "gn:population":0,
    "gn:timezone":"Asia/Shanghai",
    "iso:country":"CN",
    "name:und_x_variant":[
        "Hwangkinfow",
        "Huang-chin-pu",
        "Huang-chin-fou",
        "Huangjinbu",
        "\u9ec4\u91d1\u57e0",
        "Huangjinbu Zhen",
        "\u9ec4\u91d1\u57e0\u9547"
    ],
    "wof:name":"Huangjinbu",
    "wof:placetype":"locality"
},
  "geometry": {"coordinates":[116.80286,28.47922],"type":"Point"}
}