{
  "type": "Feature",
  "properties": {
    "gn:admin1_code":"9.0",
    "gn:asciiname":"Huanglongmiaogou",
    "gn:country_code":"CN",
    "gn:dem":409,
    "gn:feature_class":"P",
    "gn:feature_code":"PPL",
    "gn:name":"Huanglongmiaogou",
    "gn:population":0,
    "gn:timezone":"Asia/Shanghai",
    "iso:country":"CN",
    "name:zho_x_preferred":[
        "\u9ec4\u9f99\u5e99\u6c9f"
    ],
    "wof:name":"Huanglongmiaogou",
    "wof:placetype":"locality"
},
  "geometry": {"coordinates":[111.4131,33.39241],"type":"Point"}
}