{
  "type": "Feature",
  "properties": {
    "gn:admin1_code":"9.0",
    "gn:asciiname":"Zhenzishu",
    "gn:country_code":"CN",
    "gn:dem":1319,
    "gn:feature_class":"P",
    "gn:feature_code":"PPL",
    "gn:name":"Zhenzishu",
    "gn:population":0,
    "gn:timezone":"Asia/Shanghai",
    "iso:country":"CN",
    "name:zho_x_preferred":[
        "\u699b\u5b50\u6811"
    ],
    "wof:name":"Zhenzishu",
    "wof:placetype":"locality"
},
  "geometry": {"coordinates":[112.0605,33.73464],"type":"Point"}
}