{
  "type": "Feature",
  "properties": {
    "gn:admin1_code":"19.0",
    "gn:asciiname":"Ejia Buzi",
    "gn:country_code":"CN",
    "gn:dem":217,
    "gn:feature_class":"P",
    "gn:feature_code":"PPL",
    "gn:name":"Ejia Buzi",
    "gn:population":0,
    "gn:timezone":"Asia/Shanghai",
    "iso:country":"CN",
    "name:und_x_variant":[
        "Ejia Puzi",
        "\u9102\u5bb6\u5821\u5b50",
        "Ejia Buzi"
    ],
    "wof:name":"Ejia Buzi",
    "wof:placetype":"locality"
},
  "geometry": {"coordinates":[123.89431,40.53233],"type":"Point"}
}