{
  "type": "Feature",
  "properties": {
    "gn:admin1_code":"3.0",
    "gn:asciiname":"Yuhu",
    "gn:country_code":"CN",
    "gn:dem":48,
    "gn:feature_class":"P",
    "gn:feature_code":"PPL",
    "gn:name":"Yuhu",
    "gn:population":0,
    "gn:timezone":"Asia/Shanghai",
    "iso:country":"CN",
    "name:und_x_variant":[
        "\u7389\u6e56"
    ],
    "wof:name":"Yuhu",
    "wof:placetype":"locality"
},
  "geometry": {"coordinates":[116.46381,27.86031],"type":"Point"}
}