{
  "type": "Feature",
  "properties": {
    "gn:admin1_code":"20.0",
    "gn:asciiname":"Gongjiajie",
    "gn:country_code":"CN",
    "gn:dem":303,
    "gn:feature_class":"P",
    "gn:feature_code":"PPL",
    "gn:name":"Gongjiajie",
    "gn:population":0,
    "gn:timezone":"Asia/Shanghai",
    "iso:country":"CN",
    "name:zho_x_preferred":[
        "\u5bab\u5bb6\u8857"
    ],
    "wof:name":"Gongjiajie",
    "wof:placetype":"locality"
},
  "geometry": {"coordinates":[122.64308,47.69041],"type":"Point"}
}