{
  "type": "Feature",
  "properties": {
    "gn:admin1_code":"9.0",
    "gn:asciiname":"Yuanzhuang",
    "gn:country_code":"CN",
    "gn:dem":201,
    "gn:feature_class":"P",
    "gn:feature_code":"PPL",
    "gn:name":"Yuanzhuang",
    "gn:population":0,
    "gn:timezone":"Asia/Shanghai",
    "iso:country":"CN",
    "name:und_x_variant":[
        "\u8881\u5e84",
        "Yuanzhuang"
    ],
    "wof:name":"Yuanzhuang",
    "wof:placetype":"locality"
},
  "geometry": {"coordinates":[112.79513,33.32968],"type":"Point"}
}