{
  "type": "Feature",
  "properties": {
    "gn:admin1_code":"24.0",
    "gn:asciiname":"Housongjiazhaicun",
    "gn:country_code":"CN",
    "gn:dem":648,
    "gn:feature_class":"P",
    "gn:feature_code":"PPL",
    "gn:name":"Housongjiazhaicun",
    "gn:population":0,
    "gn:timezone":"Asia/Shanghai",
    "iso:country":"CN",
    "name:zho_x_preferred":[
        "\u540e\u5b8b\u5bb6\u5be8\u6751"
    ],
    "wof:name":"Housongjiazhaicun",
    "wof:placetype":"locality"
},
  "geometry": {"coordinates":[110.6803,37.35707],"type":"Point"}
}