{
  "type": "Feature",
  "properties": {
    "gn:admin1_code":"16.0",
    "gn:asciiname":"Gongju",
    "gn:country_code":"CN",
    "gn:dem":139,
    "gn:feature_class":"P",
    "gn:feature_code":"PPL",
    "gn:name":"Gongju",
    "gn:population":0,
    "gn:timezone":"Asia/Shanghai",
    "iso:country":"CN",
    "name:ara_x_preferred":[
        "\u062c\u0648\u0646\u062c\u0648"
    ],
    "name:cat_x_preferred":[
        "Gongju"
    ],
    "name:ceb_x_preferred":[
        "Gongju"
    ],
    "name:ces_x_preferred":[
        "Kongd\u017eu"
    ],
    "name:ckb_x_preferred":[
        "\u06af\u06c6\u0646\u06af\u062c\u0648"
    ],
    "name:deu_x_preferred":[
        "Gongju"
    ],
    "name:epo_x_preferred":[
        "Kon\u011du"
    ],
    "name:fas_x_preferred":[
        "\u06af\u0646\u06af\u062c\u0648"
    ],
    "name:fra_x_preferred":[
        "Gongju"
    ],
    "name:hak_x_preferred":[
        "Gongju S\u1e73"
    ],
    "name:hun_x_preferred":[
        "Kongdzsu"
    ],
    "name:ido_x_preferred":[
        "Gongju"
    ],
    "name:ind_x_preferred":[
        "Gongju"
    ],
    "name:ita_x_preferred":[
        "Gongju"
    ],
    "name:jpn_x_preferred":[
        "\u516c\u5dde\u5e02"
    ],
    "name:kor_x_preferred":[
        "\uacf5\uc8fc\uc2dc"
    ],
    "name:mon_x_preferred":[
        "\u041a\u0443\u043d\u0436\u04af"
    ],
    "name:nld_x_preferred":[
        "Gongju"
    ],
    "name:nor_x_preferred":[
        "Gongju"
    ],
    "name:pol_x_preferred":[
        "Gongju"
    ],
    "name:rus_x_preferred":[
        "\u041a\u043e\u043d\u0434\u0436\u0443"
    ],
    "name:spa_x_preferred":[
        "Gongju"
    ],
    "name:swe_x_preferred":[
        "Gongju"
    ],
    "name:tgl_x_preferred":[
        "Gongju"
    ],
    "name:tur_x_preferred":[
        "Gongju"
    ],
    "name:urd_x_preferred":[
        "\u06af\u0648\u0646\u06af\u062c\u0648"
    ],
    "name:vie_x_preferred":[
        "Gongju"
    ],
    "name:war_x_preferred":[
        "Gongju"
    ],
    "name:zho_x_preferred":[
        "\u516c\u4e3e"
    ],
    "name:zho_x_variant":[
        "\u516c\u5dde\u5e02"
    ],
    "wof:name":"Gongju",
    "wof:placetype":"locality"
},
  "geometry": {"coordinates":[109.90900000000001,24.197],"type":"Point"}
}