{
  "type": "Feature",
  "properties": {
    "gn:admin1_code":"16.0",
    "gn:asciiname":"Gongju",
    "gn:country_code":"CN",
    "gn:dem":139,
    "gn:feature_class":"P",
    "gn:feature_code":"PPL",
    "gn:name":"Gongju",
    "gn:population":0,
    "gn:timezone":"Asia/Shanghai",
    "iso:country":"CN",
    "name:zho_x_preferred":[
        "\u516c\u4e3e"
    ],
    "wof:name":"Gongju",
    "wof:placetype":"locality"
},
  "geometry": {"coordinates":[109.90900000000001,24.197],"type":"Point"}
}