{
  "type": "Feature",
  "properties": {
    "gn:admin1_code":"32.0",
    "gn:asciiname":"Jichuan",
    "gn:country_code":"CN",
    "gn:dem":324,
    "gn:feature_class":"P",
    "gn:feature_code":"PPL",
    "gn:name":"Jichuan",
    "gn:population":0,
    "gn:timezone":"Asia/Shanghai",
    "iso:country":"CN",
    "name:zho_x_preferred":[
        "\u6d4e\u5ddd"
    ],
    "wof:name":"Jichuan",
    "wof:placetype":"locality"
},
  "geometry": {"coordinates":[106.61617,31.08062],"type":"Point"}
}