{
  "type": "Feature",
  "properties": {
    "gn:admin1_code":"9.0",
    "gn:asciiname":"Beijiannao",
    "gn:country_code":"CN",
    "gn:dem":666,
    "gn:feature_class":"P",
    "gn:feature_code":"PPL",
    "gn:name":"Beijiannao",
    "gn:population":0,
    "gn:timezone":"Asia/Shanghai",
    "iso:country":"CN",
    "name:zho_x_preferred":[
        "\u5317\u5c16\u8111"
    ],
    "wof:name":"Beijiannao",
    "wof:placetype":"locality"
},
  "geometry": {"coordinates":[113.48738,35.46954],"type":"Point"}
}