{
  "type": "Feature",
  "properties": {
    "gn:admin1_code":"2.0",
    "gn:asciiname":"Juyukeng",
    "gn:country_code":"CN",
    "gn:dem":6,
    "gn:feature_class":"P",
    "gn:feature_code":"PPL",
    "gn:name":"Juyukeng",
    "gn:population":0,
    "gn:timezone":"Asia/Shanghai",
    "iso:country":"CN",
    "name:und_x_variant":[
        "\u4e3e\u6de4\u5751"
    ],
    "wof:name":"Juyukeng",
    "wof:placetype":"locality"
},
  "geometry": {"coordinates":[120.62712000000001,30.54487],"type":"Point"}
}