{
  "type": "Feature",
  "properties": {
    "gn:admin1_code":"16.0",
    "gn:asciiname":"Kunlun",
    "gn:country_code":"CN",
    "gn:dem":245,
    "gn:feature_class":"P",
    "gn:feature_code":"PPL",
    "gn:name":"Kunlun",
    "gn:population":0,
    "gn:timezone":"Asia/Shanghai",
    "iso:country":"CN",
    "name:zho_x_preferred":[
        "\u6606\u4ed1"
    ],
    "wof:name":"Kunlun",
    "wof:placetype":"locality"
},
  "geometry": {"coordinates":[106.673,22.3573],"type":"Point"}
}