{
  "type": "Feature",
  "properties": {
    "gn:admin1_code":"21.0",
    "gn:asciiname":"Youfang Zhuangzi",
    "gn:country_code":"CN",
    "gn:dem":1092,
    "gn:feature_class":"P",
    "gn:feature_code":"PPL",
    "gn:name":"Youfang Zhuangzi",
    "gn:population":0,
    "gn:timezone":"Asia/Shanghai",
    "iso:country":"CN",
    "name:zho_x_preferred":[
        "\u6cb9\u574a\u5e84\u5b50"
    ],
    "wof:name":"Youfang Zhuangzi",
    "wof:placetype":"locality"
},
  "geometry": {"coordinates":[106.711,39.1487],"type":"Point"}
}