{
  "type": "Feature",
  "properties": {
    "gn:admin1_code":"15.0",
    "gn:asciiname":"Baiciwan",
    "gn:country_code":"CN",
    "gn:dem":1575,
    "gn:feature_class":"P",
    "gn:feature_code":"PPL",
    "gn:name":"Baiciwan",
    "gn:population":0,
    "gn:timezone":"Asia/Shanghai",
    "iso:country":"CN",
    "name:zho_x_preferred":[
        "\u767d\u8328\u6e7e"
    ],
    "wof:name":"Baiciwan",
    "wof:placetype":"locality"
},
  "geometry": {"coordinates":[104.86799999999999,36.3587],"type":"Point"}
}