{
  "type": "Feature",
  "properties": {
    "gn:admin1_code":"32.0",
    "gn:asciiname":"Shamuwan",
    "gn:country_code":"CN",
    "gn:dem":570,
    "gn:feature_class":"P",
    "gn:feature_code":"PPL",
    "gn:name":"Shamuwan",
    "gn:population":0,
    "gn:timezone":"Asia/Shanghai",
    "iso:country":"CN",
    "name:zho_x_preferred":[
        "\u6c99\u6728\u5f2f"
    ],
    "wof:name":"Shamuwan",
    "wof:placetype":"locality"
},
  "geometry": {"coordinates":[104.977,28.3614],"type":"Point"}
}