{
  "type": "Feature",
  "properties": {
    "gn:admin1_code":"10.0",
    "gn:asciiname":"Songshan",
    "gn:country_code":"CN",
    "gn:dem":144,
    "gn:feature_class":"P",
    "gn:feature_code":"PPL",
    "gn:name":"Songshan",
    "gn:population":0,
    "gn:timezone":"Asia/Shanghai",
    "iso:country":"CN",
    "name:ceb_x_preferred":[
        "Songshan"
    ],
    "name:deu_x_preferred":[
        "Songshan"
    ],
    "name:fra_x_preferred":[
        "Songshan"
    ],
    "name:pol_x_preferred":[
        "Songshan"
    ],
    "name:rus_x_preferred":[
        "\u0421\u0443\u043d\u0448\u0430\u043d\u044c"
    ],
    "name:sco_x_preferred":[
        "Songshan"
    ],
    "name:zho_x_preferred":[
        "\u677e\u5c71"
    ],
    "wof:name":"Songshan",
    "wof:placetype":"locality"
},
  "geometry": {"coordinates":[115.21219000000001,39.10963],"type":"Point"}
}