{
  "type": "Feature",
  "properties": {
    "gn:admin1_code":"1.0",
    "gn:asciiname":"Baixing",
    "gn:country_code":"CN",
    "gn:dem":21,
    "gn:feature_class":"P",
    "gn:feature_code":"PPL",
    "gn:name":"Baixing",
    "gn:population":0,
    "gn:timezone":"Asia/Shanghai",
    "iso:country":"CN",
    "name:vie_x_preferred":[
        "B\u00e1 t\u00e1nh"
    ],
    "name:zho_x_preferred":[
        "\u767e\u59d3"
    ],
    "wof:name":"Baixing",
    "wof:placetype":"locality"
},
  "geometry": {"coordinates":[118.4325,31.88745],"type":"Point"}
}