{
  "type": "Feature",
  "properties": {
    "gn:admin1_code":"29",
    "gn:asciiname":"Ganhai",
    "gn:country_code":"CN",
    "gn:dem":2067,
    "gn:feature_class":"P",
    "gn:feature_code":"PPL",
    "gn:name":"Ganhai",
    "gn:population":0,
    "gn:timezone":"Asia/Shanghai",
    "iso:country":"CN",
    "name:zho_x_preferred":[
        "\u5e72\u6d77"
    ],
    "wof:name":"Ganhai",
    "wof:placetype":"locality"
},
  "geometry": {"coordinates":[102.72,24.4888],"type":"Point"}
}