{
  "type": "Feature",
  "properties": {
    "gn:admin1_code":"4.0",
    "gn:asciiname":"Nanzhong",
    "gn:country_code":"CN",
    "gn:dem":6,
    "gn:feature_class":"P",
    "gn:feature_code":"PPL",
    "gn:name":"Nanzhong",
    "gn:population":0,
    "gn:timezone":"Asia/Shanghai",
    "iso:country":"CN",
    "name:cat_x_preferred":[
        "Nanzhong"
    ],
    "name:ind_x_preferred":[
        "Nanzhong"
    ],
    "name:ita_x_preferred":[
        "Nanzhong"
    ],
    "name:nor_x_preferred":[
        "Nanzhong"
    ],
    "name:vie_x_preferred":[
        "Nam Trung"
    ],
    "name:zho_x_preferred":[
        "\u5357\u4e2d"
    ],
    "wof:name":"Nanzhong",
    "wof:placetype":"locality"
},
  "geometry": {"coordinates":[119.16862999999999,32.21702],"type":"Point"}
}