{
  "type": "Feature",
  "properties": {
    "gn:admin1_code":"19.0",
    "gn:asciiname":"Diaokangou",
    "gn:country_code":"CN",
    "gn:dem":193,
    "gn:feature_class":"P",
    "gn:feature_code":"PPL",
    "gn:name":"Diaokangou",
    "gn:population":0,
    "gn:timezone":"Asia/Shanghai",
    "iso:country":"CN",
    "name:zho_x_preferred":[
        "\u540a\u574e\u6c9f"
    ],
    "wof:name":"Diaokangou",
    "wof:placetype":"locality"
},
  "geometry": {"coordinates":[120.65127,41.1744],"type":"Point"}
}