{
  "type": "Feature",
  "properties": {
    "gn:admin1_code":"19.0",
    "gn:asciiname":"Xibalitai",
    "gn:country_code":"CN",
    "gn:dem":150,
    "gn:feature_class":"P",
    "gn:feature_code":"PPL",
    "gn:name":"Xibalitai",
    "gn:population":0,
    "gn:timezone":"Asia/Shanghai",
    "iso:country":"CN",
    "name:zho_x_preferred":[
        "\u897f\u516b\u91cc\u53f0"
    ],
    "wof:name":"Xibalitai",
    "wof:placetype":"locality"
},
  "geometry": {"coordinates":[123.97499999999999,42.8442],"type":"Point"}
}