{
  "type": "Feature",
  "properties": {
    "gn:admin1_code":"26.0",
    "gn:asciiname":"Baoquan",
    "gn:country_code":"CN",
    "gn:dem":1397,
    "gn:feature_class":"P",
    "gn:feature_code":"PPL",
    "gn:name":"Baoquan",
    "gn:population":0,
    "gn:timezone":"Asia/Shanghai",
    "iso:country":"CN",
    "name:zho_x_preferred":[
        "\u5305\u5708"
    ],
    "wof:name":"Baoquan",
    "wof:placetype":"locality"
},
  "geometry": {"coordinates":[108.15125,37.50014],"type":"Point"}
}