{
  "type": "Feature",
  "properties": {
    "gn:admin1_code":"24.0",
    "gn:asciiname":"Dongshiweng",
    "gn:country_code":"CN",
    "gn:dem":771,
    "gn:feature_class":"P",
    "gn:feature_code":"PPL",
    "gn:name":"Dongshiweng",
    "gn:population":0,
    "gn:timezone":"Asia/Shanghai",
    "iso:country":"CN",
    "name:zho_x_preferred":[
        "\u4e1c\u77f3\u74ee"
    ],
    "wof:name":"Dongshiweng",
    "wof:placetype":"locality"
},
  "geometry": {"coordinates":[113.05397000000001,35.40136],"type":"Point"}
}