{
  "type": "Feature",
  "properties": {
    "gn:admin1_code":"24.0",
    "gn:asciiname":"Wayaotu",
    "gn:country_code":"CN",
    "gn:dem":980,
    "gn:feature_class":"P",
    "gn:feature_code":"PPL",
    "gn:name":"Wayaotu",
    "gn:population":0,
    "gn:timezone":"Asia/Shanghai",
    "iso:country":"CN",
    "name:zho_x_preferred":[
        "\u74e6\u7a91\u51f8"
    ],
    "wof:name":"Wayaotu",
    "wof:placetype":"locality"
},
  "geometry": {"coordinates":[111.34739999999999,34.94138],"type":"Point"}
}