{
  "type": "Feature",
  "properties": {
    "gn:admin1_code":"16.0",
    "gn:asciiname":"Fuzhao",
    "gn:country_code":"CN",
    "gn:dem":408,
    "gn:feature_class":"P",
    "gn:feature_code":"PPL",
    "gn:name":"Fuzhao",
    "gn:population":0,
    "gn:timezone":"Asia/Shanghai",
    "iso:country":"CN",
    "name:zho_x_preferred":[
        "\u752b\u53ec"
    ],
    "wof:name":"Fuzhao",
    "wof:placetype":"locality"
},
  "geometry": {"coordinates":[107.157,23.7756],"type":"Point"}
}