{
  "type": "Feature",
  "properties": {
    "gn:admin1_code":"19.0",
    "gn:asciiname":"Xiaolaorengou",
    "gn:country_code":"CN",
    "gn:dem":143,
    "gn:feature_class":"P",
    "gn:feature_code":"PPL",
    "gn:name":"Xiaolaorengou",
    "gn:population":0,
    "gn:timezone":"Asia/Shanghai",
    "iso:country":"CN",
    "name:und_x_variant":[
        "\u5c0f\u8001\u4eba\u6c9f"
    ],
    "name:zho_x_preferred":[
        "\u5c0f\u8001\u4eba\u6c9f"
    ],
    "wof:name":"Xiaolaorengou",
    "wof:placetype":"locality"
},
  "geometry": {"coordinates":[125.06061,40.62228],"type":"Point"}
}