{
  "type": "Feature",
  "properties": {
    "gn:admin1_code":"16.0",
    "gn:asciiname":"Wanxincun",
    "gn:country_code":"CN",
    "gn:dem":62,
    "gn:feature_class":"P",
    "gn:feature_code":"PPL",
    "gn:name":"Wanxincun",
    "gn:population":0,
    "gn:timezone":"Asia/Shanghai",
    "iso:country":"CN",
    "name:zho_x_preferred":[
        "\u4e07\u65b0\u6751"
    ],
    "wof:name":"Wanxincun",
    "wof:placetype":"locality"
},
  "geometry": {"coordinates":[109.751,23.2999],"type":"Point"}
}