{
  "type": "Feature",
  "properties": {
    "gn:admin1_code":"8.0",
    "gn:asciiname":"Huzhu",
    "gn:country_code":"CN",
    "gn:dem":192,
    "gn:feature_class":"P",
    "gn:feature_code":"PPL",
    "gn:name":"Huzhu",
    "gn:population":0,
    "gn:timezone":"Asia/Shanghai",
    "iso:country":"CN",
    "name:zho_x_preferred":[
        "\u4e92\u52a9"
    ],
    "wof:name":"Huzhu",
    "wof:placetype":"locality"
},
  "geometry": {"coordinates":[125.94777999999999,46.69319],"type":"Point"}
}