{
  "type": "Feature",
  "properties": {
    "gn:admin1_code":"19.0",
    "gn:asciiname":"Xiyang Zigou",
    "gn:country_code":"CN",
    "gn:dem":448,
    "gn:feature_class":"P",
    "gn:feature_code":"PPL",
    "gn:name":"Xiyang Zigou",
    "gn:population":0,
    "gn:timezone":"Asia/Shanghai",
    "iso:country":"CN",
    "name:und_x_variant":[
        "\u897f\u6837\u5b50\u6c9f"
    ],
    "wof:name":"Xiyang Zigou",
    "wof:placetype":"locality"
},
  "geometry": {"coordinates":[124.66002,41.82811],"type":"Point"}
}