{
  "type": "Feature",
  "properties": {
    "gn:admin1_code":"15.0",
    "gn:asciiname":"Shaliushui",
    "gn:country_code":"CN",
    "gn:dem":2009,
    "gn:feature_class":"P",
    "gn:feature_code":"PPL",
    "gn:name":"Shaliushui",
    "gn:population":0,
    "gn:timezone":"Asia/Shanghai",
    "iso:country":"CN",
    "name:zho_x_preferred":[
        "\u6c99\u6d41\u6c34"
    ],
    "wof:name":"Shaliushui",
    "wof:placetype":"locality"
},
  "geometry": {"coordinates":[104.59999999999999,36.9291],"type":"Point"}
}