{
  "type": "Feature",
  "properties": {
    "gn:admin1_code":"30",
    "gn:asciiname":"Liantangce",
    "gn:country_code":"CN",
    "gn:dem":56,
    "gn:feature_class":"P",
    "gn:feature_code":"PPL",
    "gn:name":"Liantangce",
    "gn:population":0,
    "gn:timezone":"Asia/Shanghai",
    "iso:country":"CN",
    "name:zho_x_preferred":[
        "\u83b2\u5858\u4fa7"
    ],
    "wof:name":"Liantangce",
    "wof:placetype":"locality"
},
  "geometry": {"coordinates":[111.96982,22.44526],"type":"Point"}
}