{
  "type": "Feature",
  "properties": {
    "gn:admin1_code":"11.0",
    "gn:asciiname":"Xiaoxigang",
    "gn:country_code":"CN",
    "gn:dem":29,
    "gn:feature_class":"P",
    "gn:feature_code":"PPL",
    "gn:name":"Xiaoxigang",
    "gn:population":0,
    "gn:timezone":"Asia/Shanghai",
    "iso:country":"CN",
    "name:zho_x_preferred":[
        "\u5c0f\u897f\u6e2f"
    ],
    "wof:name":"Xiaoxigang",
    "wof:placetype":"locality"
},
  "geometry": {"coordinates":[112.40712000000001,29.12732],"type":"Point"}
}