{
  "type": "Feature",
  "properties": {
    "gn:admin1_code":"02",
    "gn:asciiname":"Huangjiabang",
    "gn:cc2":"CN",
    "gn:country_code":"CN",
    "gn:dem":5,
    "gn:feature_class":"P",
    "gn:feature_code":"PPL",
    "gn:name":"Huangjiabang",
    "gn:population":0,
    "gn:timezone":"Asia/Shanghai",
    "iso:country":"CN",
    "name:und_x_variant":[
        "Huang-chia-pang",
        "Huangjiabang"
    ],
    "wof:name":"Huangjiabang",
    "wof:placetype":"locality"
},
  "geometry": {"coordinates":[121.14528,30.77472],"type":"Point"}
}