{
  "type": "Feature",
  "properties": {
    "gn:admin1_code":"9.0",
    "gn:asciiname":"Xicangtun",
    "gn:country_code":"CN",
    "gn:dem":73,
    "gn:feature_class":"P",
    "gn:feature_code":"PPL",
    "gn:name":"Xicangtun",
    "gn:population":0,
    "gn:timezone":"Asia/Shanghai",
    "iso:country":"CN",
    "name:zho_x_preferred":[
        "\u897f\u85cf\u5c6f"
    ],
    "wof:name":"Xicangtun",
    "wof:placetype":"locality"
},
  "geometry": {"coordinates":[114.00664999999999,35.39747],"type":"Point"}
}