{
  "type": "Feature",
  "properties": {
    "gn:admin1_code":"29.0",
    "gn:asciiname":"Dahanjiazhai",
    "gn:country_code":"CN",
    "gn:dem":1544,
    "gn:feature_class":"P",
    "gn:feature_code":"PPL",
    "gn:name":"Dahanjiazhai",
    "gn:population":0,
    "gn:timezone":"Asia/Shanghai",
    "iso:country":"CN",
    "name:zho_x_preferred":[
        "\u5927\u97e9\u5bb6\u5be8"
    ],
    "wof:name":"Dahanjiazhai",
    "wof:placetype":"locality"
},
  "geometry": {"coordinates":[103.26900000000001,23.9623],"type":"Point"}
}