{
  "type": "Feature",
  "properties": {
    "gn:admin1_code":"31.0",
    "gn:asciiname":"Liaoyuandui",
    "gn:country_code":"CN",
    "gn:dem":77,
    "gn:feature_class":"P",
    "gn:feature_code":"PPL",
    "gn:name":"Liaoyuandui",
    "gn:population":0,
    "gn:timezone":"Asia/Shanghai",
    "iso:country":"CN",
    "name:zho_x_preferred":[
        "\u71ce\u539f\u961f"
    ],
    "wof:name":"Liaoyuandui",
    "wof:placetype":"locality"
},
  "geometry": {"coordinates":[110.26788999999999,19.00871],"type":"Point"}
}