{
  "type": "Feature",
  "properties": {
    "gn:admin1_code":"11",
    "gn:asciiname":"Dapingli",
    "gn:country_code":"CN",
    "gn:dem":215,
    "gn:feature_class":"P",
    "gn:feature_code":"PPL",
    "gn:name":"Dapingli",
    "gn:population":0,
    "gn:timezone":"Asia/Shanghai",
    "iso:country":"CN",
    "wof:name":"Dapingli",
    "wof:placetype":"locality"
},
  "geometry": {"coordinates":[113.7075,26.49639],"type":"Point"}
}