{
  "type": "Feature",
  "properties": {
    "gn:admin1_code":"12.0",
    "gn:asciiname":"Chalukou",
    "gn:country_code":"CN",
    "gn:dem":96,
    "gn:feature_class":"P",
    "gn:feature_code":"PPL",
    "gn:name":"Chalukou",
    "gn:population":0,
    "gn:timezone":"Asia/Shanghai",
    "iso:country":"CN",
    "name:zho_x_preferred":[
        "\u5c94\u8def\u53e3"
    ],
    "wof:name":"Chalukou",
    "wof:placetype":"locality"
},
  "geometry": {"coordinates":[113.55389,31.34526],"type":"Point"}
}