{
  "type": "Feature",
  "properties": {
    "gn:admin1_code":"15.0",
    "gn:asciiname":"Shuixia Dadui",
    "gn:country_code":"CN",
    "gn:dem":2015,
    "gn:feature_class":"P",
    "gn:feature_code":"PPLF",
    "gn:name":"Shuixia Dadui",
    "gn:population":0,
    "gn:timezone":"Asia/Shanghai",
    "iso:country":"CN",
    "name:zho_x_preferred":[
        "\u6c34\u5ce1\u5927\u961f"
    ],
    "wof:name":"Shuixia Dadui",
    "wof:placetype":"locality"
},
  "geometry": {"coordinates":[96.7911,39.9072],"type":"Point"}
}