{
  "type": "Feature",
  "properties": {
    "gn:admin1_code":"14.0",
    "gn:asciiname":"Tangrongcun",
    "gn:country_code":"CN",
    "gn:dem":4918,
    "gn:feature_class":"P",
    "gn:feature_code":"PPL",
    "gn:name":"Tangrongcun",
    "gn:population":0,
    "gn:timezone":"Asia/Urumqi",
    "iso:country":"CN",
    "name:zho_x_preferred":[
        "\u5510\u8363\u6751"
    ],
    "wof:name":"Tangrongcun",
    "wof:placetype":"locality"
},
  "geometry": {"coordinates":[87.7389,33.2466],"type":"Point"}
}