{
  "type": "Feature",
  "properties": {
    "gn:admin1_code":"9.0",
    "gn:asciiname":"Xiaolianzhuang",
    "gn:country_code":"CN",
    "gn:dem":188,
    "gn:feature_class":"P",
    "gn:feature_code":"PPL",
    "gn:name":"Xiaolianzhuang",
    "gn:population":0,
    "gn:timezone":"Asia/Shanghai",
    "iso:country":"CN",
    "name:und_x_variant":[
        "\u5c0f\u8fde\u5e84",
        "Xiaolianzhuang"
    ],
    "wof:name":"Xiaolianzhuang",
    "wof:placetype":"locality"
},
  "geometry": {"coordinates":[112.93751,33.9694],"type":"Point"}
}