{
  "type": "Feature",
  "properties": {
    "gn:admin1_code":"32.0",
    "gn:asciiname":"Dehousi",
    "gn:country_code":"CN",
    "gn:dem":3610,
    "gn:feature_class":"P",
    "gn:feature_code":"PPL",
    "gn:name":"Dehousi",
    "gn:population":0,
    "gn:timezone":"Asia/Shanghai",
    "iso:country":"CN",
    "name:zho_x_preferred":[
        "\u5fb7\u5019\u5bfa"
    ],
    "wof:name":"Dehousi",
    "wof:placetype":"locality"
},
  "geometry": {"coordinates":[100.60084000000001,31.69772],"type":"Point"}
}