{
  "type": "Feature",
  "properties": {
    "gn:admin1_code":"9",
    "gn:asciiname":"Liuxianggongzhuang",
    "gn:country_code":"CN",
    "gn:dem":239,
    "gn:feature_class":"P",
    "gn:feature_code":"PPL",
    "gn:name":"Liuxianggongzhuang",
    "gn:population":0,
    "gn:timezone":"Asia/Shanghai",
    "iso:country":"CN",
    "name:und_x_variant":[
        "\u5218\u76f8\u516c\u5e84",
        "Liuxianggong",
        "Liuxianggongzhuang"
    ],
    "wof:name":"Liuxianggongzhuang",
    "wof:placetype":"locality"
},
  "geometry": {"coordinates":[112.68698999999999,33.82461],"type":"Point"}
}