{
  "type": "Feature",
  "properties": {
    "gn:admin1_code":"4.0",
    "gn:asciiname":"Luxucun",
    "gn:country_code":"CN",
    "gn:dem":3,
    "gn:feature_class":"P",
    "gn:feature_code":"PPL",
    "gn:name":"Luxucun",
    "gn:population":0,
    "gn:timezone":"Asia/Shanghai",
    "iso:country":"CN",
    "name:zho_x_preferred":[
        "\u9646\u80e5\u6751"
    ],
    "wof:name":"Luxucun",
    "wof:placetype":"locality"
},
  "geometry": {"coordinates":[119.94347999999999,33.11029],"type":"Point"}
}