{
  "type": "Feature",
  "properties": {
    "gn:admin1_code":"9.0",
    "gn:asciiname":"Caiyuan",
    "gn:country_code":"CN",
    "gn:dem":193,
    "gn:feature_class":"P",
    "gn:feature_code":"PPL",
    "gn:name":"Caiyuan",
    "gn:population":0,
    "gn:timezone":"Asia/Shanghai",
    "iso:country":"CN",
    "name:zho_x_preferred":[
        "\u83dc\u56ed"
    ],
    "wof:name":"Caiyuan",
    "wof:placetype":"locality"
},
  "geometry": {"coordinates":[113.36511000000002,32.89153],"type":"Point"}
}