{
  "type": "Feature",
  "properties": {
    "gn:admin1_code":"4.0",
    "gn:asciiname":"Songxiaolou",
    "gn:country_code":"CN",
    "gn:dem":35,
    "gn:feature_class":"P",
    "gn:feature_code":"PPL",
    "gn:name":"Songxiaolou",
    "gn:population":0,
    "gn:timezone":"Asia/Shanghai",
    "iso:country":"CN",
    "name:zho_x_preferred":[
        "\u5b8b\u5c0f\u697c"
    ],
    "wof:name":"Songxiaolou",
    "wof:placetype":"locality"
},
  "geometry": {"coordinates":[117.93300000000001,34.0923],"type":"Point"}
}