{
  "type": "Feature",
  "properties": {
    "gn:admin1_code":"5.0",
    "gn:asciiname":"Fumaocun",
    "gn:country_code":"CN",
    "gn:dem":316,
    "gn:feature_class":"P",
    "gn:feature_code":"PPL",
    "gn:name":"Fumaocun",
    "gn:population":0,
    "gn:timezone":"Asia/Shanghai",
    "iso:country":"CN",
    "name:zho_x_preferred":[
        "\u590d\u8302\u6751"
    ],
    "wof:name":"Fumaocun",
    "wof:placetype":"locality"
},
  "geometry": {"coordinates":[121.84701,45.88343],"type":"Point"}
}