{
  "type": "Feature",
  "properties": {
    "gn:admin1_code":"5.0",
    "gn:asciiname":"Niejiajie",
    "gn:country_code":"CN",
    "gn:dem":266,
    "gn:feature_class":"P",
    "gn:feature_code":"PPL",
    "gn:name":"Niejiajie",
    "gn:population":0,
    "gn:timezone":"Asia/Shanghai",
    "iso:country":"CN",
    "name:zho_x_preferred":[
        "\u8042\u5bb6\u8857"
    ],
    "wof:name":"Niejiajie",
    "wof:placetype":"locality"
},
  "geometry": {"coordinates":[125.85375000000001,43.37995],"type":"Point"}
}