{
  "type": "Feature",
  "properties": {
    "gn:admin1_code":"29.0",
    "gn:asciiname":"Aweidadi",
    "gn:country_code":"CN",
    "gn:dem":2144,
    "gn:feature_class":"P",
    "gn:feature_code":"PPL",
    "gn:name":"Aweidadi",
    "gn:population":0,
    "gn:timezone":"Asia/Shanghai",
    "iso:country":"CN",
    "name:zho_x_preferred":[
        "\u963f\u7ef4\u5927\u5730"
    ],
    "wof:name":"Aweidadi",
    "wof:placetype":"locality"
},
  "geometry": {"coordinates":[98.944,26.2114],"type":"Point"}
}