{
  "type": "Feature",
  "properties": {
    "gn:admin1_code":"26.0",
    "gn:asciiname":"Liuxigou",
    "gn:country_code":"CN",
    "gn:dem":683,
    "gn:feature_class":"P",
    "gn:feature_code":"PPL",
    "gn:name":"Liuxigou",
    "gn:population":0,
    "gn:timezone":"Asia/Shanghai",
    "iso:country":"CN",
    "name:und_x_variant":[
        "\u6d41\u6eaa\u6c9f"
    ],
    "wof:name":"Liuxigou",
    "wof:placetype":"locality"
},
  "geometry": {"coordinates":[106.0967,33.0717],"type":"Point"}
}