{
  "type": "Feature",
  "properties": {
    "gn:admin1_code":"26.0",
    "gn:asciiname":"Kangshipan",
    "gn:country_code":"CN",
    "gn:dem":1112,
    "gn:feature_class":"P",
    "gn:feature_code":"PPL",
    "gn:name":"Kangshipan",
    "gn:population":0,
    "gn:timezone":"Asia/Shanghai",
    "iso:country":"CN",
    "name:zho_x_preferred":[
        "\u5eb7\u77f3\u7554"
    ],
    "wof:name":"Kangshipan",
    "wof:placetype":"locality"
},
  "geometry": {"coordinates":[110.34078999999998,38.61024000000001],"type":"Point"}
}