{
  "type": "Feature",
  "properties": {
    "gn:admin1_code":"4.0",
    "gn:asciiname":"Rensancun",
    "gn:country_code":"CN",
    "gn:dem":3,
    "gn:feature_class":"P",
    "gn:feature_code":"PPL",
    "gn:name":"Rensancun",
    "gn:population":0,
    "gn:timezone":"Asia/Shanghai",
    "iso:country":"CN",
    "name:zho_x_preferred":[
        "\u4efb\u4e09\u6751"
    ],
    "wof:name":"Rensancun",
    "wof:placetype":"locality"
},
  "geometry": {"coordinates":[119.87878000000001,32.84951],"type":"Point"}
}