{
  "type": "Feature",
  "properties": {
    "gn:admin1_code":"16.0",
    "gn:asciiname":"Donghuang",
    "gn:country_code":"CN",
    "gn:dem":339,
    "gn:feature_class":"P",
    "gn:feature_code":"PPL",
    "gn:name":"Donghuang",
    "gn:population":0,
    "gn:timezone":"Asia/Shanghai",
    "iso:country":"CN",
    "name:zho_x_preferred":[
        "\u5cd2\u7687"
    ],
    "wof:name":"Donghuang",
    "wof:placetype":"locality"
},
  "geometry": {"coordinates":[105.745,23.0788],"type":"Point"}
}