{
  "type": "Feature",
  "properties": {
    "gn:admin1_code":"5.0",
    "gn:asciiname":"Xingchengcun",
    "gn:country_code":"CN",
    "gn:dem":235,
    "gn:feature_class":"P",
    "gn:feature_code":"PPL",
    "gn:name":"Xingchengcun",
    "gn:population":0,
    "gn:timezone":"Asia/Shanghai",
    "iso:country":"CN",
    "name:zho_x_preferred":[
        "\u5174\u57ce\u6751"
    ],
    "wof:name":"Xingchengcun",
    "wof:placetype":"locality"
},
  "geometry": {"coordinates":[124.67052,43.99484],"type":"Point"}
}