{
  "type": "Feature",
  "properties": {
    "gn:admin1_code":"11.0",
    "gn:asciiname":"Shazhoutou",
    "gn:country_code":"CN",
    "gn:dem":264,
    "gn:feature_class":"P",
    "gn:feature_code":"PPL",
    "gn:name":"Shazhoutou",
    "gn:population":0,
    "gn:timezone":"Asia/Shanghai",
    "iso:country":"CN",
    "name:zho_x_preferred":[
        "\u6c99\u6d32\u5934"
    ],
    "wof:name":"Shazhoutou",
    "wof:placetype":"locality"
},
  "geometry": {"coordinates":[111.28008,27.36622],"type":"Point"}
}