{
  "type": "Feature",
  "properties": {
    "gn:admin1_code":"19",
    "gn:asciiname":"Yanshuigoucun",
    "gn:country_code":"CN",
    "gn:dem":307,
    "gn:feature_class":"P",
    "gn:feature_code":"PPL",
    "gn:name":"Yanshuigoucun",
    "gn:population":0,
    "gn:timezone":"Asia/Shanghai",
    "iso:country":"CN",
    "name:und_x_variant":[
        "\u6cbf\u6c34\u6c9f\u6751",
        "Yanshuigou",
        "\u6cbf\u6c34\u6c9f"
    ],
    "wof:name":"Yanshuigoucun",
    "wof:placetype":"locality"
},
  "geometry": {"coordinates":[124.54300000000001,41.8983],"type":"Point"}
}