{
  "type": "Feature",
  "properties": {
    "gn:admin1_code":"02",
    "gn:asciiname":"Erjiacun",
    "gn:country_code":"CN",
    "gn:dem":7,
    "gn:feature_class":"P",
    "gn:feature_code":"PPL",
    "gn:name":"Erjiacun",
    "gn:population":0,
    "gn:timezone":"Asia/Shanghai",
    "iso:country":"CN",
    "name:und_x_variant":[
        "Er-chia",
        "Erjia",
        "Erjiacun"
    ],
    "name:zho_x_preferred":[
        "\u4e8c\u7532"
    ],
    "name:zho_x_variant":[
        "\u4e8c\u7532\u6751"
    ],
    "wof:name":"Erjiacun",
    "wof:placetype":"locality"
},
  "geometry": {"coordinates":[120.7807,27.86169000000001],"type":"Point"}
}