{
  "type": "Feature",
  "properties": {
    "gn:admin1_code":"8.0",
    "gn:asciiname":"Xinchangcun",
    "gn:country_code":"CN",
    "gn:dem":63,
    "gn:feature_class":"P",
    "gn:feature_code":"PPL",
    "gn:name":"Xinchangcun",
    "gn:population":0,
    "gn:timezone":"Asia/Shanghai",
    "iso:country":"CN",
    "name:zho_x_preferred":[
        "\u65b0\u660c\u6751"
    ],
    "wof:name":"Xinchangcun",
    "wof:placetype":"locality"
},
  "geometry": {"coordinates":[131.50243999999998,47.40113],"type":"Point"}
}