{
  "type": "Feature",
  "properties": {
    "gn:admin1_code":"32.0",
    "gn:asciiname":"Xianfengwan",
    "gn:country_code":"CN",
    "gn:dem":331,
    "gn:feature_class":"P",
    "gn:feature_code":"PPL",
    "gn:name":"Xianfengwan",
    "gn:population":0,
    "gn:timezone":"Asia/Shanghai",
    "iso:country":"CN",
    "name:zho_x_preferred":[
        "\u4ed9\u98ce\u6e7e"
    ],
    "wof:name":"Xianfengwan",
    "wof:placetype":"locality"
},
  "geometry": {"coordinates":[105.33261,29.16826],"type":"Point"}
}