{
  "type": "Feature",
  "properties": {
    "gn:admin1_code":"29",
    "gn:asciiname":"Pengzuba",
    "gn:country_code":"CN",
    "gn:dem":1484,
    "gn:feature_class":"P",
    "gn:feature_code":"PPL",
    "gn:name":"Pengzuba",
    "gn:population":0,
    "gn:timezone":"Asia/Shanghai",
    "iso:country":"CN",
    "name:zho_x_preferred":[
        "\u68da\u79df\u575d"
    ],
    "wof:name":"Pengzuba",
    "wof:placetype":"locality"
},
  "geometry": {"coordinates":[102.26524999999999,24.26541],"type":"Point"}
}