{
  "type": "Feature",
  "properties": {
    "gn:admin1_code":"1.0",
    "gn:asciiname":"Hainingcun",
    "gn:country_code":"CN",
    "gn:dem":140,
    "gn:feature_class":"P",
    "gn:feature_code":"PPL",
    "gn:name":"Hainingcun",
    "gn:population":0,
    "gn:timezone":"Asia/Shanghai",
    "iso:country":"CN",
    "name:zho_x_preferred":[
        "\u6d77\u5b81\u6751"
    ],
    "wof:name":"Hainingcun",
    "wof:placetype":"locality"
},
  "geometry": {"coordinates":[118.23468,29.77112],"type":"Point"}
}