{
  "type": "Feature",
  "properties": {
    "gn:admin1_code":"29.0",
    "gn:asciiname":"Rendianhe",
    "gn:country_code":"CN",
    "gn:dem":1976,
    "gn:feature_class":"P",
    "gn:feature_code":"PPL",
    "gn:name":"Rendianhe",
    "gn:population":0,
    "gn:timezone":"Asia/Shanghai",
    "iso:country":"CN",
    "name:zho_x_preferred":[
        "\u4ec1\u7538\u6cb3"
    ],
    "wof:name":"Rendianhe",
    "wof:placetype":"locality"
},
  "geometry": {"coordinates":[99.2045,26.7068],"type":"Point"}
}