{
  "type": "Feature",
  "properties": {
    "gn:admin1_code":"3",
    "gn:asciiname":"Hetuan",
    "gn:country_code":"CN",
    "gn:dem":183,
    "gn:feature_class":"P",
    "gn:feature_code":"PPL",
    "gn:name":"Hetuan",
    "gn:population":0,
    "gn:timezone":"Asia/Shanghai",
    "iso:country":"CN",
    "name:zho_x_preferred":[
        "\u5408\u56e2"
    ],
    "wof:name":"Hetuan",
    "wof:placetype":"locality"
},
  "geometry": {"coordinates":[114.15573000000001,26.85408],"type":"Point"}
}