{
  "type": "Feature",
  "properties": {
    "gn:admin1_code":"05",
    "gn:asciiname":"Jile",
    "gn:cc2":"CN",
    "gn:country_code":"CN",
    "gn:dem":393,
    "gn:feature_class":"P",
    "gn:feature_code":"PPL",
    "gn:name":"Jile",
    "gn:population":0,
    "gn:timezone":"Asia/Shanghai",
    "iso:country":"CN",
    "name:und_x_variant":[
        "Chi-le",
        "Jile"
    ],
    "wof:name":"Jile",
    "wof:placetype":"locality"
},
  "geometry": {"coordinates":[125.48333,42.25],"type":"Point"}
}