{
  "type": "Feature",
  "properties": {
    "gn:admin1_code":"9.0",
    "gn:asciiname":"Yuchuansi",
    "gn:country_code":"CN",
    "gn:dem":169,
    "gn:feature_class":"P",
    "gn:feature_code":"PPL",
    "gn:name":"Yuchuansi",
    "gn:population":0,
    "gn:timezone":"Asia/Shanghai",
    "iso:country":"CN",
    "name:und_x_variant":[
        "\u4f59\u5ddd\u5bfa",
        "Yuchuansi"
    ],
    "wof:name":"Yuchuansi",
    "wof:placetype":"locality"
},
  "geometry": {"coordinates":[112.59304,33.25443],"type":"Point"}
}