{
  "type": "Feature",
  "properties": {
    "gn:admin1_code":"3",
    "gn:asciiname":"Taxing",
    "gn:country_code":"CN",
    "gn:dem":187,
    "gn:feature_class":"P",
    "gn:feature_code":"PPL",
    "gn:name":"Taxing",
    "gn:population":0,
    "gn:timezone":"Asia/Shanghai",
    "iso:country":"CN",
    "name:zho_x_preferred":[
        "\u736d\u5f62"
    ],
    "wof:name":"Taxing",
    "wof:placetype":"locality"
},
  "geometry": {"coordinates":[114.38500000000001,26.6016],"type":"Point"}
}