{
  "type": "Feature",
  "properties": {
    "gn:admin1_code":"24.0",
    "gn:asciiname":"Jiuying",
    "gn:country_code":"CN",
    "gn:dem":1037,
    "gn:feature_class":"P",
    "gn:feature_code":"PPL",
    "gn:name":"Jiuying",
    "gn:population":0,
    "gn:timezone":"Asia/Shanghai",
    "iso:country":"CN",
    "name:und_x_variant":[
        "\u65e7\u8425"
    ],
    "wof:name":"Jiuying",
    "wof:placetype":"locality"
},
  "geometry": {"coordinates":[112.73063999999999,39.31066],"type":"Point"}
}