{
  "type": "Feature",
  "properties": {
    "gn:admin1_code":"16.0",
    "gn:asciiname":"Lianbeicun",
    "gn:country_code":"CN",
    "gn:dem":24,
    "gn:feature_class":"P",
    "gn:feature_code":"PPL",
    "gn:name":"Lianbeicun",
    "gn:population":0,
    "gn:timezone":"Asia/Shanghai",
    "iso:country":"CN",
    "name:zho_x_preferred":[
        "\u8fde\u5317\u6751"
    ],
    "wof:name":"Lianbeicun",
    "wof:placetype":"locality"
},
  "geometry": {"coordinates":[109.42100000000001,21.8228],"type":"Point"}
}