{
  "type": "Feature",
  "properties": {
    "gn:admin1_code":"18.0",
    "gn:asciiname":"Leidayan",
    "gn:country_code":"CN",
    "gn:dem":454,
    "gn:feature_class":"P",
    "gn:feature_code":"PPL",
    "gn:name":"Leidayan",
    "gn:population":0,
    "gn:timezone":"Asia/Shanghai",
    "iso:country":"CN",
    "name:zho_x_preferred":[
        "\u96f7\u6253\u5ca9"
    ],
    "wof:name":"Leidayan",
    "wof:placetype":"locality"
},
  "geometry": {"coordinates":[109.20099999999999,26.9246],"type":"Point"}
}