{
  "type": "Feature",
  "properties": {
    "gn:admin1_code":"19.0",
    "gn:asciiname":"Tongtuncun",
    "gn:country_code":"CN",
    "gn:dem":14,
    "gn:feature_class":"P",
    "gn:feature_code":"PPL",
    "gn:name":"Tongtuncun",
    "gn:population":0,
    "gn:timezone":"Asia/Shanghai",
    "iso:country":"CN",
    "name:zho_x_preferred":[
        "\u4f5f\u5c6f\u6751"
    ],
    "wof:name":"Tongtuncun",
    "wof:placetype":"locality"
},
  "geometry": {"coordinates":[120.68113,40.60879],"type":"Point"}
}