{
  "type": "Feature",
  "properties": {
    "gn:admin1_code":"25",
    "gn:asciiname":"Huanglianyu",
    "gn:country_code":"CN",
    "gn:dem":566,
    "gn:feature_class":"P",
    "gn:feature_code":"PPL",
    "gn:name":"Huanglianyu",
    "gn:population":0,
    "gn:timezone":"Asia/Shanghai",
    "iso:country":"CN",
    "name:zho_x_preferred":[
        "\u9ec4\u8fde\u5cea"
    ],
    "wof:name":"Huanglianyu",
    "wof:placetype":"locality"
},
  "geometry": {"coordinates":[117.745,36.5607],"type":"Point"}
}