{
  "type": "Feature",
  "properties": {
    "gn:admin1_code":"9.0",
    "gn:asciiname":"Beiyangbukou",
    "gn:country_code":"CN",
    "gn:dem":113,
    "gn:feature_class":"P",
    "gn:feature_code":"PPL",
    "gn:name":"Beiyangbukou",
    "gn:population":0,
    "gn:timezone":"Asia/Shanghai",
    "iso:country":"CN",
    "name:zho_x_preferred":[
        "\u5317\u6768\u57e0\u53e3"
    ],
    "wof:name":"Beiyangbukou",
    "wof:placetype":"locality"
},
  "geometry": {"coordinates":[112.07510000000001,32.70183],"type":"Point"}
}