{
  "type": "Feature",
  "properties": {
    "gn:admin1_code":"24.0",
    "gn:asciiname":"Qiumugou",
    "gn:country_code":"CN",
    "gn:dem":718,
    "gn:feature_class":"P",
    "gn:feature_code":"PPL",
    "gn:name":"Qiumugou",
    "gn:population":0,
    "gn:timezone":"Asia/Shanghai",
    "iso:country":"CN",
    "name:zho_x_preferred":[
        "\u79cb\u6728\u6c9f"
    ],
    "wof:name":"Qiumugou",
    "wof:placetype":"locality"
},
  "geometry": {"coordinates":[111.62033,35.04666],"type":"Point"}
}