{
  "type": "Feature",
  "properties": {
    "gn:admin1_code":"29.0",
    "gn:asciiname":"Wusachang",
    "gn:country_code":"CN",
    "gn:dem":2092,
    "gn:feature_class":"P",
    "gn:feature_code":"PPL",
    "gn:name":"Wusachang",
    "gn:population":0,
    "gn:timezone":"Asia/Shanghai",
    "iso:country":"CN",
    "name:zho_x_preferred":[
        "\u4e4c\u6492\u5382"
    ],
    "wof:name":"Wusachang",
    "wof:placetype":"locality"
},
  "geometry": {"coordinates":[103.64400000000001,25.4689],"type":"Point"}
}