{
  "type": "Feature",
  "properties": {
    "gn:admin1_code":"32.0",
    "gn:asciiname":"Mahuangchang",
    "gn:country_code":"CN",
    "gn:dem":550,
    "gn:feature_class":"P",
    "gn:feature_code":"PPL",
    "gn:name":"Mahuangchang",
    "gn:population":0,
    "gn:timezone":"Asia/Shanghai",
    "iso:country":"CN",
    "name:zho_x_preferred":[
        "\u8682\u87e5\u5382"
    ],
    "wof:name":"Mahuangchang",
    "wof:placetype":"locality"
},
  "geometry": {"coordinates":[105.81999999999999,28.0366],"type":"Point"}
}