{
  "type": "Feature",
  "properties": {
    "gn:admin1_code":"19.0",
    "gn:asciiname":"Haitangcun",
    "gn:country_code":"CN",
    "gn:dem":591,
    "gn:feature_class":"P",
    "gn:feature_code":"PPL",
    "gn:name":"Haitangcun",
    "gn:population":0,
    "gn:timezone":"Asia/Shanghai",
    "iso:country":"CN",
    "name:zho_x_preferred":[
        "\u6d77\u68e0\u6751"
    ],
    "wof:name":"Haitangcun",
    "wof:placetype":"locality"
},
  "geometry": {"coordinates":[119.58235000000001,41.79083],"type":"Point"}
}