{
  "type": "Feature",
  "properties": {
    "gn:admin1_code":"8.0",
    "gn:asciiname":"Jundongcun",
    "gn:country_code":"CN",
    "gn:dem":249,
    "gn:feature_class":"P",
    "gn:feature_code":"PPL",
    "gn:name":"Jundongcun",
    "gn:population":0,
    "gn:timezone":"Asia/Shanghai",
    "iso:country":"CN",
    "name:zho_x_preferred":[
        "\u4fca\u4e1c\u6751"
    ],
    "wof:name":"Jundongcun",
    "wof:placetype":"locality"
},
  "geometry": {"coordinates":[131.66846000000001,46.06225],"type":"Point"}
}