{
  "type": "Feature",
  "properties": {
    "gn:admin1_code":"10.0",
    "gn:asciiname":"Fang'anyu",
    "gn:country_code":"CN",
    "gn:dem":1044,
    "gn:feature_class":"P",
    "gn:feature_code":"PPL",
    "gn:name":"Fang\u2019anyu",
    "gn:population":0,
    "gn:timezone":"Asia/Shanghai",
    "iso:country":"CN",
    "name:und_x_variant":[
        "Fang\u2019anyu"
    ],
    "name:zho_x_preferred":[
        "\u574a\u5b89\u5cea"
    ],
    "wof:name":"Fang'anyu",
    "wof:placetype":"locality"
},
  "geometry": {"coordinates":[115.87485,40.22306],"type":"Point"}
}