{
  "type": "Feature",
  "properties": {
    "gn:admin1_code":"14.0",
    "gn:asciiname":"Nadi",
    "gn:country_code":"CN",
    "gn:dem":4756,
    "gn:feature_class":"P",
    "gn:feature_code":"PPL",
    "gn:name":"Nadi",
    "gn:population":0,
    "gn:timezone":"Asia/Urumqi",
    "iso:country":"CN",
    "name:ara_x_preferred":[
        "\u0646\u0627\u062f\u064a"
    ],
    "name:ceb_x_preferred":[
        "Nadi"
    ],
    "name:ces_x_preferred":[
        "Nadi"
    ],
    "name:deu_x_preferred":[
        "Nadi"
    ],
    "name:ell_x_preferred":[
        "\u039d\u03ac\u03bd\u03c4\u03b9 \u03a6\u03af\u03c4\u03b6\u03b9"
    ],
    "name:fas_x_preferred":[
        "\u0646\u0627\u062f\u06cc"
    ],
    "name:fij_x_preferred":[
        "Nadi"
    ],
    "name:fin_x_preferred":[
        "Nadi"
    ],
    "name:fra_x_preferred":[
        "Nadi"
    ],
    "name:hif_x_preferred":[
        "Nadi"
    ],
    "name:hin_x_preferred":[
        "\u0928\u093e\u0928\u094d\u0926\u0940"
    ],
    "name:ita_x_preferred":[
        "Nadi"
    ],
    "name:jpn_x_preferred":[
        "\u30ca\u30f3\u30c7\u30a3"
    ],
    "name:lit_x_preferred":[
        "Nadis"
    ],
    "name:nld_x_preferred":[
        "Nadi"
    ],
    "name:pol_x_preferred":[
        "Nadi"
    ],
    "name:por_x_preferred":[
        "Nadi"
    ],
    "name:rus_x_preferred":[
        "\u041d\u0430\u043d\u0434\u0438"
    ],
    "name:spa_x_preferred":[
        "Nadi"
    ],
    "name:swe_x_preferred":[
        "Nadi"
    ],
    "name:tam_x_preferred":[
        "\u0ba8\u0ba3\u0bcd\u0b9f\u0bbf"
    ],
    "name:zho_x_preferred":[
        "\u90a3\u5730"
    ],
    "wof:name":"Nadi",
    "wof:placetype":"locality"
},
  "geometry": {"coordinates":[89.88211,31.47786],"type":"Point"}
}