{
  "type": "Feature",
  "properties": {
    "gn:admin1_code":"29",
    "gn:asciiname":"Langshi",
    "gn:country_code":"CN",
    "gn:dem":1834,
    "gn:feature_class":"P",
    "gn:feature_code":"PPL",
    "gn:name":"Langshi",
    "gn:population":0,
    "gn:timezone":"Asia/Shanghai",
    "iso:country":"CN",
    "name:zho_x_preferred":[
        "\u6d6a\u65bd"
    ],
    "wof:name":"Langshi",
    "wof:placetype":"locality"
},
  "geometry": {"coordinates":[102.111,23.3831],"type":"Point"}
}