{
  "type": "Feature",
  "properties": {
    "gn:admin1_code":"32.0",
    "gn:asciiname":"Yanhe",
    "gn:country_code":"CN",
    "gn:dem":420,
    "gn:feature_class":"P",
    "gn:feature_code":"PPL",
    "gn:name":"Yanhe",
    "gn:population":0,
    "gn:timezone":"Asia/Shanghai",
    "iso:country":"CN",
    "name:ceb_x_preferred":[
        "Yanhe"
    ],
    "name:deu_x_preferred":[
        "Yanhe"
    ],
    "name:fra_x_preferred":[
        "Yanhe"
    ],
    "name:zho_x_preferred":[
        "\u6cbf\u6cb3"
    ],
    "wof:name":"Yanhe",
    "wof:placetype":"locality"
},
  "geometry": {"coordinates":[104.83,31.018],"type":"Point"}
}