{
  "type": "Feature",
  "properties": {
    "gn:admin1_code":"8.0",
    "gn:asciiname":"Liangjiatun",
    "gn:country_code":"CN",
    "gn:dem":152,
    "gn:feature_class":"P",
    "gn:feature_code":"PPL",
    "gn:name":"Liangjiatun",
    "gn:population":0,
    "gn:timezone":"Asia/Shanghai",
    "iso:country":"CN",
    "name:zho_x_preferred":[
        "\u6881\u5bb6\u5c6f"
    ],
    "wof:name":"Liangjiatun",
    "wof:placetype":"locality"
},
  "geometry": {"coordinates":[124.70198000000001,47.09723],"type":"Point"}
}