{
  "type": "Feature",
  "properties": {
    "gn:admin1_code":"5.0",
    "gn:asciiname":"Bawai",
    "gn:country_code":"CN",
    "gn:dem":133,
    "gn:feature_class":"P",
    "gn:feature_code":"PPL",
    "gn:name":"Bawai",
    "gn:population":0,
    "gn:timezone":"Asia/Shanghai",
    "iso:country":"CN",
    "name:zho_x_preferred":[
        "\u575d\u5916"
    ],
    "wof:name":"Bawai",
    "wof:placetype":"locality"
},
  "geometry": {"coordinates":[123.81780999999999,46.217],"type":"Point"}
}