{
  "type": "Feature",
  "properties": {
    "gn:admin1_code":"29",
    "gn:asciiname":"Jiudu",
    "gn:country_code":"CN",
    "gn:dem":1853,
    "gn:feature_class":"P",
    "gn:feature_code":"PPL",
    "gn:name":"Jiudu",
    "gn:population":0,
    "gn:timezone":"Asia/Shanghai",
    "iso:country":"CN",
    "name:zho_x_preferred":[
        "\u4e5d\u5ea6"
    ],
    "wof:name":"Jiudu",
    "wof:placetype":"locality"
},
  "geometry": {"coordinates":[102.30500000000001,24.8987],"type":"Point"}
}