{
  "type": "Feature",
  "properties": {
    "gn:admin1_code":"16.0",
    "gn:asciiname":"Bawu",
    "gn:country_code":"CN",
    "gn:dem":476,
    "gn:feature_class":"P",
    "gn:feature_code":"PPL",
    "gn:name":"Bawu",
    "gn:population":0,
    "gn:timezone":"Asia/Shanghai",
    "iso:country":"CN",
    "name:ces_x_preferred":[
        "Pa-wu"
    ],
    "name:deu_x_preferred":[
        "Bawu"
    ],
    "name:fra_x_preferred":[
        "Bawu"
    ],
    "name:hye_x_preferred":[
        "\u0532\u0561\u0578\u0582"
    ],
    "name:nld_x_preferred":[
        "Bawu"
    ],
    "name:nor_x_preferred":[
        "Bawu"
    ],
    "name:rus_x_preferred":[
        "\u0411\u0430\u0443"
    ],
    "name:swe_x_preferred":[
        "Bawu"
    ],
    "name:zho_x_preferred":[
        "\u5df4\u52ff"
    ],
    "wof:name":"Bawu",
    "wof:placetype":"locality"
},
  "geometry": {"coordinates":[106.842,23.0372],"type":"Point"}
}