{
  "type": "Feature",
  "properties": {
    "iso:country":"CN",
    "name:eng_x_preferred":[
        "Zhuzhou"
    ],
    "name:zho_x_preferred":[
        "\u682a\u6d32 \u5e02"
    ],
    "qs:name":"\u682a\u6d32 \u5e02",
    "qs:name_adm0":"\u4e2d\u570b",
    "qs:name_adm1":"\u6e56\u5357\u7701",
    "qs:photos":50,
    "qs:photos_1k":10,
    "qs:photos_9k":4,
    "qs:photos_9r":6,
    "qs:photos_all":812,
    "qs:photos_sr":2,
    "qs:placetype":"LocalAdmin",
    "qs:pop_sr":"0",
    "wof:name":"Zhuzhou",
    "wof:placetype":"localadmin"
},
  "geometry": {"coordinates":[113.14675099999999,27.831486],"type":"Point"}
}