{
  "type": "Feature",
  "properties": {
    "gn:admin1_code":"19.0",
    "gn:asciiname":"Dongganggang",
    "gn:country_code":"CN",
    "gn:dem":492,
    "gn:feature_class":"P",
    "gn:feature_code":"PPL",
    "gn:name":"Dongganggang",
    "gn:population":0,
    "gn:timezone":"Asia/Shanghai",
    "iso:country":"CN",
    "name:zho_x_preferred":[
        "\u4e1c\u5c97\u5c97"
    ],
    "wof:name":"Dongganggang",
    "wof:placetype":"locality"
},
  "geometry": {"coordinates":[119.35275,42.11486],"type":"Point"}
}