{
  "type": "Feature",
  "properties": {
    "gn:admin1_code":"32.0",
    "gn:asciiname":"Chunxincun",
    "gn:country_code":"CN",
    "gn:dem":704,
    "gn:feature_class":"P",
    "gn:feature_code":"PPL",
    "gn:name":"Chunxincun",
    "gn:population":0,
    "gn:timezone":"Asia/Shanghai",
    "iso:country":"CN",
    "name:zho_x_preferred":[
        "\u6625\u65b0\u6751"
    ],
    "wof:name":"Chunxincun",
    "wof:placetype":"locality"
},
  "geometry": {"coordinates":[103.36,30.6256],"type":"Point"}
}