{
  "type": "Feature",
  "properties": {
    "gn:admin1_code":"9",
    "gn:asciiname":"Gaolu",
    "gn:country_code":"CN",
    "gn:dem":48,
    "gn:feature_class":"P",
    "gn:feature_code":"PPL",
    "gn:name":"Gaol\u00fc",
    "gn:population":0,
    "gn:timezone":"Asia/Shanghai",
    "iso:country":"CN",
    "name:und_x_variant":[
        "Gaol\u00fc"
    ],
    "name:zho_x_preferred":[
        "\u9ad8\u4fa3"
    ],
    "wof:name":"Gaolu",
    "wof:placetype":"locality"
},
  "geometry": {"coordinates":[115.50551000000002,35.76896],"type":"Point"}
}