{
  "type": "Feature",
  "properties": {
    "gn:admin1_code":"10.0",
    "gn:asciiname":"Datongxin",
    "gn:country_code":"CN",
    "gn:dem":30,
    "gn:feature_class":"P",
    "gn:feature_code":"PPL",
    "gn:name":"Datongxin",
    "gn:population":0,
    "gn:timezone":"Asia/Shanghai",
    "iso:country":"CN",
    "name:zho_x_preferred":[
        "\u5927\u540c\u65b0"
    ],
    "wof:name":"Datongxin",
    "wof:placetype":"locality"
},
  "geometry": {"coordinates":[115.511,38.1989],"type":"Point"}
}