{
  "type": "Feature",
  "properties": {
    "gn:admin1_code":"4.0",
    "gn:asciiname":"Zeguanmiao",
    "gn:country_code":"CN",
    "gn:dem":5,
    "gn:feature_class":"P",
    "gn:feature_code":"PPL",
    "gn:name":"Zeguanmiao",
    "gn:population":0,
    "gn:timezone":"Asia/Shanghai",
    "iso:country":"CN",
    "name:zho_x_preferred":[
        "Zeguanmiao"
    ],
    "name:zho_x_variant":[
        "\u8fee\u5173\u5e99"
    ],
    "wof:name":"Zeguanmiao",
    "wof:placetype":"locality"
},
  "geometry": {"coordinates":[121.05922,32.39442],"type":"Point"}
}