{
  "type": "Feature",
  "properties": {
    "gn:admin1_code":"9.0",
    "gn:asciiname":"Lejuzhuang",
    "gn:country_code":"CN",
    "gn:dem":340,
    "gn:feature_class":"P",
    "gn:feature_code":"PPL",
    "gn:name":"Lejuzhuang",
    "gn:population":0,
    "gn:timezone":"Asia/Shanghai",
    "iso:country":"CN",
    "name:zho_x_preferred":[
        "\u4e50\u5c45\u5e84"
    ],
    "wof:name":"Lejuzhuang",
    "wof:placetype":"locality"
},
  "geometry": {"coordinates":[112.16012000000001,34.75585],"type":"Point"}
}