{
  "type": "Feature",
  "properties": {
    "gn:admin1_code":"8.0",
    "gn:asciiname":"Fanshengcun",
    "gn:country_code":"CN",
    "gn:dem":197,
    "gn:feature_class":"P",
    "gn:feature_code":"PPL",
    "gn:name":"Fanshengcun",
    "gn:population":0,
    "gn:timezone":"Asia/Shanghai",
    "iso:country":"CN",
    "name:zho_x_preferred":[
        "\u7e41\u80dc\u6751"
    ],
    "wof:name":"Fanshengcun",
    "wof:placetype":"locality"
},
  "geometry": {"coordinates":[127.36436,46.57875],"type":"Point"}
}