{
  "type": "Feature",
  "properties": {
    "gn:admin1_code":"01",
    "gn:asciiname":"Hucheng",
    "gn:cc2":"CN",
    "gn:country_code":"CN",
    "gn:dem":30,
    "gn:feature_class":"P",
    "gn:feature_code":"PPL",
    "gn:name":"Hucheng",
    "gn:population":0,
    "gn:timezone":"Asia/Shanghai",
    "iso:country":"CN",
    "name:und_x_variant":[
        "Hu-hsien",
        "Hucheng"
    ],
    "wof:name":"Hucheng",
    "wof:placetype":"locality"
},
  "geometry": {"coordinates":[116.16667,33.38333],"type":"Point"}
}