{
  "type": "Feature",
  "properties": {
    "gn:admin1_code":"25",
    "gn:asciiname":"Yangliuzhuang",
    "gn:country_code":"CN",
    "gn:dem":21,
    "gn:feature_class":"P",
    "gn:feature_code":"PPL",
    "gn:name":"Yangliuzhuang",
    "gn:population":0,
    "gn:timezone":"Asia/Shanghai",
    "iso:country":"CN",
    "name:zho_x_preferred":[
        "\u6768\u67f3\u5e84"
    ],
    "wof:name":"Yangliuzhuang",
    "wof:placetype":"locality"
},
  "geometry": {"coordinates":[117.458,37.252],"type":"Point"}
}