{
  "type": "Feature",
  "properties": {
    "gn:admin1_code":"2.0",
    "gn:asciiname":"Tangwu",
    "gn:country_code":"CN",
    "gn:dem":99,
    "gn:feature_class":"P",
    "gn:feature_code":"PPL",
    "gn:name":"Tangwu",
    "gn:population":0,
    "gn:timezone":"Asia/Shanghai",
    "iso:country":"CN",
    "name:zho_x_preferred":[
        "\u5858\u575e"
    ],
    "wof:name":"Tangwu",
    "wof:placetype":"locality"
},
  "geometry": {"coordinates":[120.10048999999999,29.44512000000001],"type":"Point"}
}