{
  "type": "Feature",
  "properties": {
    "gn:admin1_code":"10.0",
    "gn:asciiname":"Nancaozhuang",
    "gn:country_code":"CN",
    "gn:dem":7,
    "gn:feature_class":"P",
    "gn:feature_code":"PPL",
    "gn:name":"Nancaozhuang",
    "gn:population":0,
    "gn:timezone":"Asia/Shanghai",
    "iso:country":"CN",
    "name:zho_x_preferred":[
        "\u5357\u66f9\u5e84"
    ],
    "wof:name":"Nancaozhuang",
    "wof:placetype":"locality"
},
  "geometry": {"coordinates":[117.97781999999999,39.58703],"type":"Point"}
}