{
  "type": "Feature",
  "properties": {
    "gn:admin1_code":"24.0",
    "gn:asciiname":"Xiaodegou",
    "gn:country_code":"CN",
    "gn:dem":1841,
    "gn:feature_class":"P",
    "gn:feature_code":"PPL",
    "gn:name":"Xiaodegou",
    "gn:population":0,
    "gn:timezone":"Asia/Shanghai",
    "iso:country":"CN",
    "name:zho_x_preferred":[
        "\u5c0f\u5fb7\u6c9f"
    ],
    "wof:name":"Xiaodegou",
    "wof:placetype":"locality"
},
  "geometry": {"coordinates":[112.27504999999999,38.54129],"type":"Point"}
}