{
  "type": "Feature",
  "properties": {
    "gn:admin1_code":"07",
    "gn:asciiname":"Caoyuan",
    "gn:country_code":"CN",
    "gn:dem":216,
    "gn:feature_class":"P",
    "gn:feature_code":"PPLA4",
    "gn:name":"Caoyuan",
    "gn:population":0,
    "gn:timezone":"Asia/Shanghai",
    "iso:country":"CN",
    "name:und_x_variant":[
        "\u66f9\u8fdc",
        "Caoyuan Zhen",
        "\u66f9\u8fdc\u9547"
    ],
    "name:zho_x_preferred":[
        "\u66f9\u8fdc"
    ],
    "wof:name":"Caoyuan",
    "wof:placetype":"locality"
},
  "geometry": {"coordinates":[117.33304,26.03268],"type":"Point"}
}