{
  "type": "Feature",
  "properties": {
    "gn:admin1_code":"2.0",
    "gn:asciiname":"Qingshanwu",
    "gn:country_code":"CN",
    "gn:dem":40,
    "gn:feature_class":"P",
    "gn:feature_code":"PPL",
    "gn:name":"Qingshanwu",
    "gn:population":0,
    "gn:timezone":"Asia/Shanghai",
    "iso:country":"CN",
    "name:zho_x_preferred":[
        "\u6e05\u5c71\u575e"
    ],
    "wof:name":"Qingshanwu",
    "wof:placetype":"locality"
},
  "geometry": {"coordinates":[120.03543999999999,29.47006],"type":"Point"}
}