{
  "type": "Feature",
  "properties": {
    "gn:admin1_code":"7.0",
    "gn:asciiname":"Songnan",
    "gn:country_code":"CN",
    "gn:dem":26,
    "gn:feature_class":"P",
    "gn:feature_code":"PPL",
    "gn:name":"Songnan",
    "gn:population":0,
    "gn:timezone":"Asia/Shanghai",
    "iso:country":"CN",
    "name:zho_x_preferred":[
        "\u677e\u5357"
    ],
    "wof:name":"Songnan",
    "wof:placetype":"locality"
},
  "geometry": {"coordinates":[119.79709,25.54915],"type":"Point"}
}