{
  "type": "Feature",
  "properties": {
    "gn:admin1_code":"4.0",
    "gn:asciiname":"Zhujia Xuzi",
    "gn:country_code":"CN",
    "gn:dem":3,
    "gn:feature_class":"P",
    "gn:feature_code":"PPLF",
    "gn:name":"Zhujia Xuzi",
    "gn:population":0,
    "gn:timezone":"Asia/Shanghai",
    "iso:country":"CN",
    "name:und_x_variant":[
        "\u795d\u5bb6\u5729\u5b50"
    ],
    "name:zho_x_preferred":[
        "\u795d\u5bb6\u5729\u5b50"
    ],
    "wof:name":"Zhujia Xuzi",
    "wof:placetype":"locality"
},
  "geometry": {"coordinates":[120.40219999999999,32.57259000000001],"type":"Point"}
}