{
  "type": "Feature",
  "properties": {
    "gn:admin1_code":"18.0",
    "gn:asciiname":"Natun",
    "gn:country_code":"CN",
    "gn:dem":889,
    "gn:feature_class":"P",
    "gn:feature_code":"PPL",
    "gn:name":"Natun",
    "gn:population":0,
    "gn:timezone":"Asia/Shanghai",
    "iso:country":"CN",
    "wof:name":"Natun",
    "wof:placetype":"locality"
},
  "geometry": {"coordinates":[105.125,25.96667],"type":"Point"}
}