{
  "type": "Feature",
  "properties": {
    "gn:admin1_code":"1.0",
    "gn:asciiname":"Luxucun",
    "gn:country_code":"CN",
    "gn:dem":38,
    "gn:feature_class":"P",
    "gn:feature_code":"PPL",
    "gn:name":"Luxucun",
    "gn:population":0,
    "gn:timezone":"Asia/Shanghai",
    "iso:country":"CN",
    "name:und_x_variant":[
        "Luwei"
    ],
    "name:zho_x_preferred":[
        "\u5362\u5729\u6751"
    ],
    "wof:name":"Luxucun",
    "wof:placetype":"locality"
},
  "geometry": {"coordinates":[116.58568,31.8643],"type":"Point"}
}