{
  "type": "Feature",
  "properties": {
    "gn:admin1_code":"18",
    "gn:asciiname":"Qiao'e",
    "gn:country_code":"CN",
    "gn:dem":935,
    "gn:feature_class":"P",
    "gn:feature_code":"PPL",
    "gn:name":"Qiao\u2019e",
    "gn:population":0,
    "gn:timezone":"Asia/Shanghai",
    "iso:country":"CN",
    "name:und_x_variant":[
        "Qiao\u2019e"
    ],
    "name:zho_x_preferred":[
        "\u5de7\u4fc4"
    ],
    "wof:name":"Qiao'e",
    "wof:placetype":"locality"
},
  "geometry": {"coordinates":[105.959,25.2603],"type":"Point"}
}