{
  "type": "Feature",
  "properties": {
    "gn:admin1_code":"11.0",
    "gn:asciiname":"Hanshou",
    "gn:country_code":"CN",
    "gn:dem":144,
    "gn:feature_class":"P",
    "gn:feature_code":"PPL",
    "gn:name":"Hanshou",
    "gn:population":0,
    "gn:timezone":"Asia/Shanghai",
    "iso:country":"CN",
    "name:zho_x_preferred":[
        "\u6c49\u5bff"
    ],
    "wof:name":"Hanshou",
    "wof:placetype":"locality"
},
  "geometry": {"coordinates":[111.45331000000002,26.4724],"type":"Point"}
}