{
  "type": "Feature",
  "properties": {
    "gn:admin1_code":"33.0",
    "gn:asciiname":"Jiaoxichang",
    "gn:country_code":"CN",
    "gn:dem":618,
    "gn:feature_class":"P",
    "gn:feature_code":"PPL",
    "gn:name":"Jiaoxichang",
    "gn:population":0,
    "gn:timezone":"Asia/Shanghai",
    "iso:country":"CN",
    "name:zho_x_preferred":[
        "\u4ea4\u6eaa\u573a"
    ],
    "wof:name":"Jiaoxichang",
    "wof:placetype":"locality"
},
  "geometry": {"coordinates":[108.77778000000001,28.42353],"type":"Point"}
}