{
  "type": "Feature",
  "properties": {
    "gn:admin1_code":"8.0",
    "gn:asciiname":"Xuejiagoucun",
    "gn:country_code":"CN",
    "gn:dem":329,
    "gn:feature_class":"P",
    "gn:feature_code":"PPL",
    "gn:name":"Xuejiagoucun",
    "gn:population":0,
    "gn:timezone":"Asia/Shanghai",
    "iso:country":"CN",
    "name:zho_x_preferred":[
        "\u859b\u5bb6\u6c9f\u6751"
    ],
    "wof:name":"Xuejiagoucun",
    "wof:placetype":"locality"
},
  "geometry": {"coordinates":[130.41211999999999,44.66405],"type":"Point"}
}