{
  "type": "Feature",
  "properties": {
    "gn:admin1_code":"10",
    "gn:asciiname":"Jingziyu",
    "gn:country_code":"CN",
    "gn:dem":103,
    "gn:feature_class":"P",
    "gn:feature_code":"PPL",
    "gn:name":"Jingziyu",
    "gn:population":0,
    "gn:timezone":"Asia/Shanghai",
    "iso:country":"CN",
    "name:zho_x_preferred":[
        "\u7cb3\u5b50\u5cea"
    ],
    "wof:name":"Jingziyu",
    "wof:placetype":"locality"
},
  "geometry": {"coordinates":[118.11197,40.21428],"type":"Point"}
}