{
  "type": "Feature",
  "properties": {
    "gn:admin1_code":"2.0",
    "gn:asciiname":"Yikeng",
    "gn:country_code":"CN",
    "gn:dem":503,
    "gn:feature_class":"P",
    "gn:feature_code":"PPL",
    "gn:name":"Yikeng",
    "gn:population":0,
    "gn:timezone":"Asia/Shanghai",
    "iso:country":"CN",
    "name:zho_x_preferred":[
        "\u79fb\u5751"
    ],
    "wof:name":"Yikeng",
    "wof:placetype":"locality"
},
  "geometry": {"coordinates":[118.98479,28.55852],"type":"Point"}
}