{
  "type": "Feature",
  "properties": {
    "gn:admin1_code":"32.0",
    "gn:asciiname":"Sha'erdi",
    "gn:country_code":"CN",
    "gn:dem":3528,
    "gn:feature_class":"P",
    "gn:feature_code":"PPL",
    "gn:name":"Sha\u2019erdi",
    "gn:population":0,
    "gn:timezone":"Asia/Shanghai",
    "iso:country":"CN",
    "name:und_x_variant":[
        "Sha\u2019erdi"
    ],
    "name:zho_x_preferred":[
        "\u6c99\u5c14\u5e95"
    ],
    "wof:name":"Sha'erdi",
    "wof:placetype":"locality"
},
  "geometry": {"coordinates":[100.652,32.0207],"type":"Point"}
}