{
  "type": "Feature",
  "properties": {
    "gn:admin1_code":"30.0",
    "gn:asciiname":"Qinzhaiyangcun",
    "gn:country_code":"CN",
    "gn:dem":63,
    "gn:feature_class":"P",
    "gn:feature_code":"PPL",
    "gn:name":"Qinzhaiyangcun",
    "gn:population":0,
    "gn:timezone":"Asia/Shanghai",
    "iso:country":"CN",
    "name:zho_x_preferred":[
        "\u82b9\u5be8\u6d0b\u6751"
    ],
    "wof:name":"Qinzhaiyangcun",
    "wof:placetype":"locality"
},
  "geometry": {"coordinates":[116.40017,23.9477],"type":"Point"}
}