{
  "type": "Feature",
  "properties": {
    "gn:admin1_code":"4.0",
    "gn:asciiname":"Zhengjiazhuang",
    "gn:country_code":"CN",
    "gn:dem":5,
    "gn:feature_class":"P",
    "gn:feature_code":"PPL",
    "gn:name":"Zhengjiazhuang",
    "gn:population":0,
    "gn:timezone":"Asia/Shanghai",
    "iso:country":"CN",
    "name:zho_x_preferred":[
        "Zhengjiazhuang"
    ],
    "name:zho_x_variant":[
        "\u90d1\u5bb6\u5e84"
    ],
    "wof:name":"Zhengjiazhuang",
    "wof:placetype":"locality"
},
  "geometry": {"coordinates":[119.55728000000001,33.2919],"type":"Point"}
}