{
  "type": "Feature",
  "properties": {
    "gn:admin1_code":"19.0",
    "gn:asciiname":"Yujialiangcun",
    "gn:country_code":"CN",
    "gn:dem":204,
    "gn:feature_class":"P",
    "gn:feature_code":"PPL",
    "gn:name":"Yujialiangcun",
    "gn:population":0,
    "gn:timezone":"Asia/Shanghai",
    "iso:country":"CN",
    "name:zho_x_preferred":[
        "\u4e8e\u5bb6\u6881\u6751"
    ],
    "wof:name":"Yujialiangcun",
    "wof:placetype":"locality"
},
  "geometry": {"coordinates":[122.02200000000001,42.4483],"type":"Point"}
}