{
  "type": "Feature",
  "properties": {
    "gn:admin1_code":"4.0",
    "gn:asciiname":"Wangengcun",
    "gn:country_code":"CN",
    "gn:dem":1,
    "gn:feature_class":"P",
    "gn:feature_code":"PPL",
    "gn:name":"Wangengcun",
    "gn:population":0,
    "gn:timezone":"Asia/Shanghai",
    "iso:country":"CN",
    "name:zho_x_preferred":[
        "\u4e07\u803f\u6751"
    ],
    "wof:name":"Wangengcun",
    "wof:placetype":"locality"
},
  "geometry": {"coordinates":[120.10529,33.03027],"type":"Point"}
}