{
  "type": "Feature",
  "properties": {
    "gn:admin1_code":"4.0",
    "gn:asciiname":"Zhabei",
    "gn:country_code":"CN",
    "gn:dem":20,
    "gn:feature_class":"P",
    "gn:feature_code":"PPL",
    "gn:name":"Zhabei",
    "gn:population":0,
    "gn:timezone":"Asia/Shanghai",
    "iso:country":"CN",
    "name:ceb_x_preferred":[
        "Zhabei Qu"
    ],
    "name:deu_x_preferred":[
        "Zhabei"
    ],
    "name:eus_x_preferred":[
        "Zhabei Barrutia"
    ],
    "name:jpn_x_preferred":[
        "\u9598\u5317\u533a"
    ],
    "name:kor_x_preferred":[
        "\uc790\ubca0\uc774\uad6c"
    ],
    "name:nld_x_preferred":[
        "Zhabei"
    ],
    "name:nor_x_preferred":[
        "Zhabei"
    ],
    "name:ron_x_preferred":[
        "Districtul Zhabei"
    ],
    "name:rus_x_preferred":[
        "\u0427\u0436\u0430\u0431\u044d\u0439"
    ],
    "name:spa_x_preferred":[
        "Zhabei"
    ],
    "name:swe_x_preferred":[
        "Zhabei"
    ],
    "name:ukr_x_preferred":[
        "\u0420\u0430\u0439\u043e\u043d \u0427\u0436\u0430\u0431\u0435\u0439"
    ],
    "name:vie_x_preferred":[
        "\u00c1p B\u1eafc"
    ],
    "name:wuu_x_preferred":[
        "\u95f8\u5317\u533a"
    ],
    "name:zho_x_preferred":[
        "\u95f8\u5317"
    ],
    "name:zho_x_variant":[
        "\u95f8\u5317\u533a"
    ],
    "wof:name":"Zhabei",
    "wof:placetype":"locality"
},
  "geometry": {"coordinates":[118.319,33.9943],"type":"Point"}
}