{
  "type": "Feature",
  "properties": {
    "gn:admin1_code":"26.0",
    "gn:asciiname":"Zhichanggou",
    "gn:country_code":"CN",
    "gn:dem":1234,
    "gn:feature_class":"P",
    "gn:feature_code":"PPL",
    "gn:name":"Zhichanggou",
    "gn:population":0,
    "gn:timezone":"Asia/Shanghai",
    "iso:country":"CN",
    "name:zho_x_preferred":[
        "\u7eb8\u5382\u6c9f"
    ],
    "wof:name":"Zhichanggou",
    "wof:placetype":"locality"
},
  "geometry": {"coordinates":[107.07210000000001,32.81851],"type":"Point"}
}