{
  "type": "Feature",
  "properties": {
    "gn:admin1_code":"11.0",
    "gn:asciiname":"Gaotang",
    "gn:country_code":"CN",
    "gn:dem":372,
    "gn:feature_class":"P",
    "gn:feature_code":"PPL",
    "gn:name":"Gaotang",
    "gn:population":0,
    "gn:timezone":"Asia/Shanghai",
    "iso:country":"CN",
    "name:zho_x_preferred":[
        "Gaotang"
    ],
    "name:zho_x_variant":[
        "\u9ad8\u5802"
    ],
    "wof:name":"Gaotang",
    "wof:placetype":"locality"
},
  "geometry": {"coordinates":[114.10404,28.82287],"type":"Point"}
}