{
  "type": "Feature",
  "properties": {
    "gn:admin1_code":"32.0",
    "gn:asciiname":"Maolin'ao",
    "gn:country_code":"CN",
    "gn:dem":430,
    "gn:feature_class":"P",
    "gn:feature_code":"PPL",
    "gn:name":"Maolin\u2019ao",
    "gn:population":0,
    "gn:timezone":"Asia/Shanghai",
    "iso:country":"CN",
    "name:zho_x_preferred":[
        "\u6bdb\u6797\u5787"
    ],
    "name:zho_x_variant":[
        "Maolin\u2019ao"
    ],
    "wof:name":"Maolin'ao",
    "wof:placetype":"locality"
},
  "geometry": {"coordinates":[104.84402,29.00082],"type":"Point"}
}