{
  "type": "Feature",
  "properties": {
    "gn:admin1_code":"15.0",
    "gn:asciiname":"Shangshaigutai",
    "gn:country_code":"CN",
    "gn:dem":2394,
    "gn:feature_class":"P",
    "gn:feature_code":"PPL",
    "gn:name":"Shangshaigutai",
    "gn:population":0,
    "gn:timezone":"Asia/Shanghai",
    "iso:country":"CN",
    "name:zho_x_preferred":[
        "\u4e0a\u6652\u8c37\u53f0"
    ],
    "wof:name":"Shangshaigutai",
    "wof:placetype":"locality"
},
  "geometry": {"coordinates":[102.333,37.7732],"type":"Point"}
}