{
  "type": "Feature",
  "properties": {
    "gn:admin1_code":"11.0",
    "gn:asciiname":"Wenxi",
    "gn:country_code":"CN",
    "gn:dem":346,
    "gn:feature_class":"P",
    "gn:feature_code":"PPL",
    "gn:name":"Wenxi",
    "gn:population":0,
    "gn:timezone":"Asia/Shanghai",
    "iso:country":"CN",
    "name:zho_x_preferred":[
        "\u6e29\u6eaa"
    ],
    "wof:name":"Wenxi",
    "wof:placetype":"locality"
},
  "geometry": {"coordinates":[110.41956,27.62216],"type":"Point"}
}