{
  "type": "Feature",
  "properties": {
    "gn:admin1_code":"19.0",
    "gn:asciiname":"Hugujiazi",
    "gn:country_code":"CN",
    "gn:dem":49,
    "gn:feature_class":"P",
    "gn:feature_code":"PPL",
    "gn:name":"Hugujiazi",
    "gn:population":0,
    "gn:timezone":"Asia/Shanghai",
    "iso:country":"CN",
    "name:zho_x_preferred":[
        "\u80e1\u53e4\u5bb6\u5b50"
    ],
    "wof:name":"Hugujiazi",
    "wof:placetype":"locality"
},
  "geometry": {"coordinates":[123.44444,41.52845],"type":"Point"}
}