{
  "type": "Feature",
  "properties": {
    "gn:admin1_code":"12.0",
    "gn:asciiname":"Xihepu",
    "gn:country_code":"CN",
    "gn:dem":24,
    "gn:feature_class":"P",
    "gn:feature_code":"PPL",
    "gn:name":"Xihepu",
    "gn:population":0,
    "gn:timezone":"Asia/Shanghai",
    "iso:country":"CN",
    "name:und_x_variant":[
        "\u897f\u6cb3\u94fa"
    ],
    "wof:name":"Xihepu",
    "wof:placetype":"locality"
},
  "geometry": {"coordinates":[114.84524,30.56854],"type":"Point"}
}