{
  "type": "Feature",
  "properties": {
    "gn:admin1_code":"32",
    "gn:asciiname":"Qiaobianhe",
    "gn:country_code":"CN",
    "gn:dem":521,
    "gn:feature_class":"P",
    "gn:feature_code":"PPL",
    "gn:name":"Qiaobianhe",
    "gn:population":0,
    "gn:timezone":"Asia/Shanghai",
    "iso:country":"CN",
    "name:zho_x_preferred":[
        "\u6865\u8fb9\u6cb3"
    ],
    "wof:name":"Qiaobianhe",
    "wof:placetype":"locality"
},
  "geometry": {"coordinates":[105.45802999999999,31.99385],"type":"Point"}
}