{
  "type": "Feature",
  "properties": {
    "gn:admin1_code":"16.0",
    "gn:asciiname":"Yanzao",
    "gn:country_code":"CN",
    "gn:dem":19,
    "gn:feature_class":"P",
    "gn:feature_code":"PPL",
    "gn:name":"Yanzao",
    "gn:population":0,
    "gn:timezone":"Asia/Shanghai",
    "iso:country":"CN",
    "name:zho_x_preferred":[
        "\u76d0\u7076"
    ],
    "wof:name":"Yanzao",
    "wof:placetype":"locality"
},
  "geometry": {"coordinates":[109.456,21.4928],"type":"Point"}
}