{
  "type": "Feature",
  "properties": {
    "gn:admin1_code":"4.0",
    "gn:asciiname":"Shanglongjing",
    "gn:country_code":"CN",
    "gn:dem":6,
    "gn:feature_class":"P",
    "gn:feature_code":"PPL",
    "gn:name":"Shanglongjing",
    "gn:population":0,
    "gn:timezone":"Asia/Shanghai",
    "iso:country":"CN",
    "name:und_x_variant":[
        "\u4e0a\u9f99\u6cfe"
    ],
    "name:zho_x_preferred":[
        "\u4e0a\u9f99\u6cfe"
    ],
    "wof:name":"Shanglongjing",
    "wof:placetype":"locality"
},
  "geometry": {"coordinates":[120.71901,31.56085],"type":"Point"}
}