{
  "type": "Feature",
  "properties": {
    "gn:admin1_code":"9.0",
    "gn:asciiname":"Mingzhu",
    "gn:country_code":"CN",
    "gn:dem":309,
    "gn:feature_class":"P",
    "gn:feature_code":"PPL",
    "gn:name":"Mingzhu",
    "gn:population":0,
    "gn:timezone":"Asia/Shanghai",
    "iso:country":"CN",
    "name:zho_x_preferred":[
        "\u660e\u73e0"
    ],
    "wof:name":"Mingzhu",
    "wof:placetype":"locality"
},
  "geometry": {"coordinates":[111.68447,34.36486],"type":"Point"}
}