{
  "type": "Feature",
  "properties": {
    "gn:admin1_code":"11",
    "gn:asciiname":"Chenjiaping",
    "gn:country_code":"CN",
    "gn:dem":474,
    "gn:feature_class":"P",
    "gn:feature_code":"PPL",
    "gn:name":"Chenjiaping",
    "gn:population":0,
    "gn:timezone":"Asia/Shanghai",
    "iso:country":"CN",
    "wof:name":"Chenjiaping",
    "wof:placetype":"locality"
},
  "geometry": {"coordinates":[113.78167000000001,27.20972],"type":"Point"}
}