{
  "type": "Feature",
  "properties": {
    "gn:admin1_code":"8.0",
    "gn:asciiname":"Xiaobeijingtun",
    "gn:country_code":"CN",
    "gn:dem":231,
    "gn:feature_class":"P",
    "gn:feature_code":"PPL",
    "gn:name":"Xiaobeijingtun",
    "gn:population":0,
    "gn:timezone":"Asia/Shanghai",
    "iso:country":"CN",
    "name:zho_x_preferred":[
        "\u5c0f\u5317\u4e95\u5c6f"
    ],
    "wof:name":"Xiaobeijingtun",
    "wof:placetype":"locality"
},
  "geometry": {"coordinates":[124.74148999999998,48.14416],"type":"Point"}
}