{
  "type": "Feature",
  "properties": {
    "gn:admin1_code":"3.0",
    "gn:asciiname":"Zongshupai",
    "gn:country_code":"CN",
    "gn:dem":338,
    "gn:feature_class":"P",
    "gn:feature_code":"PPL",
    "gn:name":"Zongshupai",
    "gn:population":0,
    "gn:timezone":"Asia/Shanghai",
    "iso:country":"CN",
    "name:und_x_variant":[
        "\u68d5\u6811\u6392"
    ],
    "wof:name":"Zongshupai",
    "wof:placetype":"locality"
},
  "geometry": {"coordinates":[115.27415999999999,25.49692000000001],"type":"Point"}
}