{
  "type": "Feature",
  "properties": {
    "gn:admin1_code":"29",
    "gn:asciiname":"Ayulin",
    "gn:country_code":"CN",
    "gn:dem":1771,
    "gn:feature_class":"P",
    "gn:feature_code":"PPL",
    "gn:name":"Ayulin",
    "gn:population":0,
    "gn:timezone":"Asia/Shanghai",
    "iso:country":"CN",
    "name:zho_x_preferred":[
        "\u554a\u7389\u6797"
    ],
    "wof:name":"Ayulin",
    "wof:placetype":"locality"
},
  "geometry": {"coordinates":[103.318,24.8571],"type":"Point"}
}