{
  "type": "Feature",
  "properties": {
    "gn:admin1_code":"14",
    "gn:asciiname":"Yuzhu'ema",
    "gn:country_code":"CN",
    "gn:dem":4662,
    "gn:feature_class":"P",
    "gn:feature_code":"PPL",
    "gn:name":"Yuzhu\u2019ema",
    "gn:population":0,
    "gn:timezone":"Asia/Urumqi",
    "iso:country":"CN",
    "name:und_x_variant":[
        "Yuzhu\u2019ema"
    ],
    "name:zho_x_preferred":[
        "\u7389\u73e0\u4fc4\u739b"
    ],
    "wof:name":"Yuzhu'ema",
    "wof:placetype":"locality"
},
  "geometry": {"coordinates":[88.7413,31.2231],"type":"Point"}
}