{
  "type": "Feature",
  "properties": {
    "gn:admin1_code":"19",
    "gn:asciiname":"Xiyingzi",
    "gn:country_code":"CN",
    "gn:dem":190,
    "gn:feature_class":"P",
    "gn:feature_code":"PPL",
    "gn:name":"Xiyingzi",
    "gn:population":0,
    "gn:timezone":"Asia/Shanghai",
    "iso:country":"CN",
    "wof:name":"Xiyingzi",
    "wof:placetype":"locality"
},
  "geometry": {"coordinates":[120.52722,41.35528],"type":"Point"}
}