{
  "type": "Feature",
  "properties": {
    "gn:admin1_code":"3.0",
    "gn:asciiname":"Guohoucun",
    "gn:country_code":"CN",
    "gn:dem":27,
    "gn:feature_class":"P",
    "gn:feature_code":"PPL",
    "gn:name":"Guohoucun",
    "gn:population":0,
    "gn:timezone":"Asia/Shanghai",
    "iso:country":"CN",
    "name:und_x_variant":[
        "\u90ed\u539a\u6751"
    ],
    "wof:name":"Guohoucun",
    "wof:placetype":"locality"
},
  "geometry": {"coordinates":[115.63092,28.10936],"type":"Point"}
}