{
  "type": "Feature",
  "properties": {
    "gn:admin1_code":"14.0",
    "gn:asciiname":"Anbacun",
    "gn:country_code":"CN",
    "gn:dem":2349,
    "gn:feature_class":"P",
    "gn:feature_code":"PPL",
    "gn:name":"Anbacun",
    "gn:population":0,
    "gn:timezone":"Asia/Urumqi",
    "iso:country":"CN",
    "name:zho_x_preferred":[
        "\u5b89\u5df4\u6751"
    ],
    "wof:name":"Anbacun",
    "wof:placetype":"locality"
},
  "geometry": {"coordinates":[97.97955,29.04197000000001],"type":"Point"}
}