{
  "type": "Feature",
  "properties": {
    "gn:admin1_code":"25",
    "gn:asciiname":"Quanzhuangcun",
    "gn:country_code":"CN",
    "gn:dem":222,
    "gn:feature_class":"P",
    "gn:feature_code":"PPL",
    "gn:name":"Quanzhuangcun",
    "gn:population":0,
    "gn:timezone":"Asia/Shanghai",
    "iso:country":"CN",
    "name:und_x_variant":[
        "Quanzhuang",
        "Quanzhuangcun"
    ],
    "name:zho_x_preferred":[
        "\u6cc9\u5e84"
    ],
    "name:zho_x_variant":[
        "\u6cc9\u5e84\u6751"
    ],
    "wof:name":"Quanzhuangcun",
    "wof:placetype":"locality"
},
  "geometry": {"coordinates":[118.39100000000001,35.9428],"type":"Point"}
}