{
  "type": "Feature",
  "properties": {
    "gn:admin1_code":"1.0",
    "gn:asciiname":"Yuanjiadian",
    "gn:cc2":"CN",
    "gn:country_code":"CN",
    "gn:dem":15,
    "gn:feature_class":"P",
    "gn:feature_code":"PPL",
    "gn:name":"Yuanjiadian",
    "gn:population":0,
    "gn:timezone":"Asia/Shanghai",
    "iso:country":"CN",
    "name:und_x_variant":[
        "Y\u00fcan-chia-tien",
        "Yuanjiadian"
    ],
    "wof:name":"Yuanjiadian",
    "wof:placetype":"locality"
},
  "geometry": {"coordinates":[116.89943999999998,31.5475],"type":"Point"}
}