{
  "type": "Feature",
  "properties": {
    "gn:admin1_code":"8.0",
    "gn:asciiname":"Chuangzaocun",
    "gn:country_code":"CN",
    "gn:dem":174,
    "gn:feature_class":"P",
    "gn:feature_code":"PPL",
    "gn:name":"Chuangzaocun",
    "gn:population":0,
    "gn:timezone":"Asia/Shanghai",
    "iso:country":"CN",
    "name:zho_x_preferred":[
        "\u521b\u9020\u6751"
    ],
    "wof:name":"Chuangzaocun",
    "wof:placetype":"locality"
},
  "geometry": {"coordinates":[124.97753,47.73434],"type":"Point"}
}