{
  "type": "Feature",
  "properties": {
    "gn:admin1_code":"26.0",
    "gn:asciiname":"Yuantuomao",
    "gn:country_code":"CN",
    "gn:dem":1539,
    "gn:feature_class":"P",
    "gn:feature_code":"PPL",
    "gn:name":"Yuantuomao",
    "gn:population":0,
    "gn:timezone":"Asia/Shanghai",
    "iso:country":"CN",
    "name:zho_x_preferred":[
        "\u5143\u5768\u5cc1"
    ],
    "wof:name":"Yuantuomao",
    "wof:placetype":"locality"
},
  "geometry": {"coordinates":[108.7718,36.89916],"type":"Point"}
}