{
  "type": "Feature",
  "properties": {
    "gn:admin1_code":"21.0",
    "gn:asciiname":"Baonancun",
    "gn:country_code":"CN",
    "gn:dem":1112,
    "gn:feature_class":"P",
    "gn:feature_code":"PPL",
    "gn:name":"Baonancun",
    "gn:population":0,
    "gn:timezone":"Asia/Shanghai",
    "iso:country":"CN",
    "name:zho_x_preferred":[
        "\u4fdd\u5357\u6751"
    ],
    "wof:name":"Baonancun",
    "wof:placetype":"locality"
},
  "geometry": {"coordinates":[106.407,38.4868],"type":"Point"}
}