{
  "type": "Feature",
  "properties": {
    "gn:admin1_code":"31.0",
    "gn:asciiname":"Shimo",
    "gn:country_code":"CN",
    "gn:dem":76,
    "gn:feature_class":"P",
    "gn:feature_code":"PPL",
    "gn:name":"Shimo",
    "gn:population":0,
    "gn:timezone":"Asia/Shanghai",
    "iso:country":"CN",
    "name:und_x_variant":[
        "\u4ec0\u78e8"
    ],
    "wof:name":"Shimo",
    "wof:placetype":"locality"
},
  "geometry": {"coordinates":[109.77892,18.68201],"type":"Point"}
}