{
  "type": "Feature",
  "properties": {
    "gn:admin1_code":"29.0",
    "gn:asciiname":"Beiyinshan",
    "gn:country_code":"CN",
    "gn:dem":1899,
    "gn:feature_class":"P",
    "gn:feature_code":"PPL",
    "gn:name":"Beiyinshan",
    "gn:population":0,
    "gn:timezone":"Asia/Shanghai",
    "iso:country":"CN",
    "name:zho_x_preferred":[
        "\u80cc\u9634\u5c71"
    ],
    "wof:name":"Beiyinshan",
    "wof:placetype":"locality"
},
  "geometry": {"coordinates":[100.71599999999999,24.2323],"type":"Point"}
}