{
  "type": "Feature",
  "properties": {
    "gn:admin1_code":"11.0",
    "gn:asciiname":"Muyuchong",
    "gn:country_code":"CN",
    "gn:dem":786,
    "gn:feature_class":"P",
    "gn:feature_code":"PPL",
    "gn:name":"Muyuchong",
    "gn:population":0,
    "gn:timezone":"Asia/Shanghai",
    "iso:country":"CN",
    "name:zho_x_preferred":[
        "\u6728\u9c7c\u51b2"
    ],
    "wof:name":"Muyuchong",
    "wof:placetype":"locality"
},
  "geometry": {"coordinates":[113.80775,25.64845],"type":"Point"}
}