{
  "type": "Feature",
  "properties": {
    "gn:admin1_code":"26.0",
    "gn:asciiname":"Guozhuangcun",
    "gn:country_code":"CN",
    "gn:dem":1522,
    "gn:feature_class":"P",
    "gn:feature_code":"PPL",
    "gn:name":"Guozhuangcun",
    "gn:population":0,
    "gn:timezone":"Asia/Shanghai",
    "iso:country":"CN",
    "name:zho_x_preferred":[
        "\u90ed\u5e84\u6751"
    ],
    "wof:name":"Guozhuangcun",
    "wof:placetype":"locality"
},
  "geometry": {"coordinates":[108.04786,36.61064],"type":"Point"}
}