{
  "type": "Feature",
  "properties": {
    "gn:admin1_code":"26",
    "gn:asciiname":"Huoshiliang",
    "gn:country_code":"CN",
    "gn:dem":959,
    "gn:feature_class":"P",
    "gn:feature_code":"PPL",
    "gn:name":"Huoshiliang",
    "gn:population":0,
    "gn:timezone":"Asia/Shanghai",
    "iso:country":"CN",
    "name:und_x_variant":[
        "\u706b\u77f3\u6881"
    ],
    "name:zho_x_preferred":[
        "\u706b\u77f3\u6881"
    ],
    "wof:name":"Huoshiliang",
    "wof:placetype":"locality"
},
  "geometry": {"coordinates":[108.35222,34.8475],"type":"Point"}
}