{
  "type": "Feature",
  "properties": {
    "gn:admin1_code":"14.0",
    "gn:asciiname":"Jila",
    "gn:country_code":"CN",
    "gn:dem":4240,
    "gn:feature_class":"P",
    "gn:feature_code":"PPL",
    "gn:name":"Jila",
    "gn:population":0,
    "gn:timezone":"Asia/Urumqi",
    "iso:country":"CN",
    "name:zho_x_preferred":[
        "\u673a\u62c9"
    ],
    "wof:name":"Jila",
    "wof:placetype":"locality"
},
  "geometry": {"coordinates":[92.45782,28.66072],"type":"Point"}
}