{
  "type": "Feature",
  "properties": {
    "gn:admin1_code":"2.0",
    "gn:asciiname":"Menlou'ao",
    "gn:country_code":"CN",
    "gn:dem":576,
    "gn:feature_class":"P",
    "gn:feature_code":"PPLA4",
    "gn:name":"Menlou\u2019ao",
    "gn:population":0,
    "gn:timezone":"Asia/Shanghai",
    "iso:country":"CN",
    "name:zho_x_preferred":[
        "Menlou\u2019ao"
    ],
    "wof:name":"Menlou'ao",
    "wof:placetype":"locality"
},
  "geometry": {"coordinates":[119.87482,27.43363],"type":"Point"}
}