{
  "type": "Feature",
  "properties": {
    "gn:admin1_code":"29.0",
    "gn:asciiname":"Xiadeng",
    "gn:country_code":"CN",
    "gn:dem":2480,
    "gn:feature_class":"P",
    "gn:feature_code":"PPL",
    "gn:name":"Xiadeng",
    "gn:population":0,
    "gn:timezone":"Asia/Shanghai",
    "iso:country":"CN",
    "name:zho_x_preferred":[
        "\u4e0b\u767b"
    ],
    "wof:name":"Xiadeng",
    "wof:placetype":"locality"
},
  "geometry": {"coordinates":[99.55370000000001,26.2705],"type":"Point"}
}