{
  "type": "Feature",
  "properties": {
    "gn:admin1_code":"14.0",
    "gn:asciiname":"Dasha",
    "gn:country_code":"CN",
    "gn:dem":4917,
    "gn:feature_class":"P",
    "gn:feature_code":"PPL",
    "gn:name":"Dasha",
    "gn:population":0,
    "gn:timezone":"Asia/Urumqi",
    "iso:country":"CN",
    "name:zho_x_preferred":[
        "\u6253\u6c99"
    ],
    "wof:name":"Dasha",
    "wof:placetype":"locality"
},
  "geometry": {"coordinates":[91.47857999999999,31.01285],"type":"Point"}
}