{
  "type": "Feature",
  "properties": {
    "gn:admin1_code":"32.0",
    "gn:asciiname":"Huangbo",
    "gn:country_code":"CN",
    "gn:dem":390,
    "gn:feature_class":"P",
    "gn:feature_code":"PPL",
    "gn:name":"Huangbo",
    "gn:population":0,
    "gn:timezone":"Asia/Shanghai",
    "iso:country":"CN",
    "name:zho_x_preferred":[
        "\u9ec4\u94b5"
    ],
    "wof:name":"Huangbo",
    "wof:placetype":"locality"
},
  "geometry": {"coordinates":[104.04075,29.48348],"type":"Point"}
}