{
  "type": "Feature",
  "properties": {
    "gn:admin1_code":"4.0",
    "gn:asciiname":"Guanye",
    "gn:country_code":"CN",
    "gn:dem":7,
    "gn:feature_class":"P",
    "gn:feature_code":"PPL",
    "gn:name":"Guanye",
    "gn:population":0,
    "gn:timezone":"Asia/Shanghai",
    "iso:country":"CN",
    "name:zho_x_preferred":[
        "\u5b98\u91ce"
    ],
    "wof:name":"Guanye",
    "wof:placetype":"locality"
},
  "geometry": {"coordinates":[120.13908000000001,32.41228],"type":"Point"}
}