{
  "type": "Feature",
  "properties": {
    "gn:admin1_code":"4.0",
    "gn:asciiname":"Qiligeng",
    "gn:country_code":"CN",
    "gn:dem":26,
    "gn:feature_class":"P",
    "gn:feature_code":"PPL",
    "gn:name":"Qiligeng",
    "gn:population":0,
    "gn:timezone":"Asia/Shanghai",
    "iso:country":"CN",
    "name:zho_x_preferred":[
        "\u4e03\u91cc\u57c2"
    ],
    "wof:name":"Qiligeng",
    "wof:placetype":"locality"
},
  "geometry": {"coordinates":[119.05473000000001,31.46534],"type":"Point"}
}