{
  "type": "Feature",
  "properties": {
    "gn:admin1_code":"16.0",
    "gn:asciiname":"Nahe",
    "gn:country_code":"CN",
    "gn:dem":285,
    "gn:feature_class":"P",
    "gn:feature_code":"PPL",
    "gn:name":"Nahe",
    "gn:population":0,
    "gn:timezone":"Asia/Ho_Chi_Minh",
    "iso:country":"CN",
    "name:zho_x_preferred":[
        "\u90a3\u8377"
    ],
    "wof:name":"Nahe",
    "wof:placetype":"locality"
},
  "geometry": {"coordinates":[106.64700000000001,22.5722],"type":"Point"}
}