{
  "type": "Feature",
  "properties": {
    "gn:admin1_code":"29.0",
    "gn:asciiname":"Zhangwuzhuang",
    "gn:country_code":"CN",
    "gn:dem":1910,
    "gn:feature_class":"P",
    "gn:feature_code":"PPL",
    "gn:name":"Zhangwuzhuang",
    "gn:population":0,
    "gn:timezone":"Asia/Shanghai",
    "iso:country":"CN",
    "name:zho_x_preferred":[
        "\u5f20\u6b66\u5e84"
    ],
    "wof:name":"Zhangwuzhuang",
    "wof:placetype":"locality"
},
  "geometry": {"coordinates":[101.92100000000001,25.1374],"type":"Point"}
}