{
  "type": "Feature",
  "properties": {
    "gn:admin1_code":"6.0",
    "gn:asciiname":"Wufeng",
    "gn:country_code":"CN",
    "gn:dem":2516,
    "gn:feature_class":"P",
    "gn:feature_code":"PPLA4",
    "gn:name":"Wufeng",
    "gn:population":0,
    "gn:timezone":"Asia/Shanghai",
    "iso:country":"CN",
    "name:und_x_variant":[
        "Wufeng Xiang"
    ],
    "name:zho_x_preferred":[
        "\u4e94\u5cf0"
    ],
    "name:zho_x_variant":[
        "\u4e94\u5cf0\u4e61"
    ],
    "wof:name":"Wufeng",
    "wof:placetype":"locality"
},
  "geometry": {"coordinates":[101.84986000000001,36.87188],"type":"Point"}
}