{
  "type": "Feature",
  "properties": {
    "gn:admin1_code":"19.0",
    "gn:asciiname":"Yinliangling",
    "gn:country_code":"CN",
    "gn:dem":4,
    "gn:feature_class":"P",
    "gn:feature_code":"PPL",
    "gn:name":"Yinliangling",
    "gn:population":0,
    "gn:timezone":"Asia/Shanghai",
    "iso:country":"CN",
    "name:zho_x_preferred":[
        "\u836b\u51c9\u5cad"
    ],
    "wof:name":"Yinliangling",
    "wof:placetype":"locality"
},
  "geometry": {"coordinates":[121.88500000000001,39.4213],"type":"Point"}
}