{
  "type": "Feature",
  "properties": {
    "gn:admin1_code":"3.0",
    "gn:asciiname":"Yuanbei",
    "gn:country_code":"CN",
    "gn:dem":79,
    "gn:feature_class":"P",
    "gn:feature_code":"PPL",
    "gn:name":"Yuanbei",
    "gn:population":0,
    "gn:timezone":"Asia/Shanghai",
    "iso:country":"CN",
    "name:und_x_variant":[
        "\u9662\u80cc"
    ],
    "wof:name":"Yuanbei",
    "wof:placetype":"locality"
},
  "geometry": {"coordinates":[116.47171000000002,27.76566],"type":"Point"}
}