{
  "type": "Feature",
  "properties": {
    "gn:admin1_code":"4.0",
    "gn:asciiname":"Maqiaocun",
    "gn:country_code":"CN",
    "gn:dem":3,
    "gn:feature_class":"P",
    "gn:feature_code":"PPL",
    "gn:name":"Maqiaocun",
    "gn:population":0,
    "gn:timezone":"Asia/Shanghai",
    "iso:country":"CN",
    "name:zho_x_preferred":[
        "\u9a6c\u6865\u6751"
    ],
    "wof:name":"Maqiaocun",
    "wof:placetype":"locality"
},
  "geometry": {"coordinates":[119.40009000000001,33.53052],"type":"Point"}
}