{
  "type": "Feature",
  "properties": {
    "gn:admin1_code":"12.0",
    "gn:asciiname":"Wangnitang",
    "gn:country_code":"CN",
    "gn:dem":76,
    "gn:feature_class":"P",
    "gn:feature_code":"PPL",
    "gn:name":"Wangnitang",
    "gn:population":0,
    "gn:timezone":"Asia/Shanghai",
    "iso:country":"CN",
    "name:zho_x_preferred":[
        "\u738b\u6ce5\u5858"
    ],
    "wof:name":"Wangnitang",
    "wof:placetype":"locality"
},
  "geometry": {"coordinates":[114.88985,31.29408],"type":"Point"}
}