{
  "type": "Feature",
  "properties": {
    "gn:admin1_code":"14.0",
    "gn:asciiname":"Jiamai",
    "gn:country_code":"CN",
    "gn:dem":4124,
    "gn:feature_class":"P",
    "gn:feature_code":"PPL",
    "gn:name":"Jiamai",
    "gn:population":0,
    "gn:timezone":"Asia/Urumqi",
    "iso:country":"CN",
    "name:zho_x_preferred":[
        "\u52a0\u9ea6"
    ],
    "wof:name":"Jiamai",
    "wof:placetype":"locality"
},
  "geometry": {"coordinates":[92.34266,28.38635],"type":"Point"}
}