{
  "type": "Feature",
  "properties": {
    "gn:admin1_code":"30",
    "gn:asciiname":"Shengjiang",
    "gn:country_code":"CN",
    "gn:dem":64,
    "gn:feature_class":"P",
    "gn:feature_code":"PPLA4",
    "gn:name":"Shengjiang",
    "gn:population":0,
    "gn:timezone":"Asia/Shanghai",
    "iso:country":"CN",
    "name:und_x_variant":[
        "Shengjiang Zhen",
        "\u751f\u6c5f\u9547"
    ],
    "name:zho_x_preferred":[
        "\u751f\u6c5f"
    ],
    "wof:name":"Shengjiang",
    "wof:placetype":"locality"
},
  "geometry": {"coordinates":[111.50943999999998,22.70752],"type":"Point"}
}