{
  "type": "Feature",
  "properties": {
    "gn:admin1_code":"02",
    "gn:asciiname":"Henghucun",
    "gn:country_code":"CN",
    "gn:dem":6,
    "gn:feature_class":"P",
    "gn:feature_code":"PPL",
    "gn:name":"Henghucun",
    "gn:population":0,
    "gn:timezone":"Asia/Shanghai",
    "iso:country":"CN",
    "name:und_x_variant":[
        "Heng-ho",
        "Henghu",
        "Henghucun"
    ],
    "name:zho_x_preferred":[
        "\u6a2a\u6e56\u6751"
    ],
    "wof:name":"Henghucun",
    "wof:placetype":"locality"
},
  "geometry": {"coordinates":[121.47772000000001,28.35852],"type":"Point"}
}