{
  "type": "Feature",
  "properties": {
    "gn:admin1_code":"11.0",
    "gn:asciiname":"Jiangjiaxi",
    "gn:country_code":"CN",
    "gn:dem":363,
    "gn:feature_class":"P",
    "gn:feature_code":"PPL",
    "gn:name":"Jiangjiaxi",
    "gn:population":0,
    "gn:timezone":"Asia/Shanghai",
    "iso:country":"CN",
    "name:zho_x_preferred":[
        "\u848b\u5bb6\u6eaa"
    ],
    "wof:name":"Jiangjiaxi",
    "wof:placetype":"locality"
},
  "geometry": {"coordinates":[109.56111,27.01279000000001],"type":"Point"}
}