{
  "type": "Feature",
  "properties": {
    "iso:country":"CN",
    "name:ceb_x_preferred":[
        "Tunxi Qu"
    ],
    "name:cym_x_preferred":[
        "Ardal Tunxi"
    ],
    "name:deu_x_preferred":[
        "Tunxi"
    ],
    "name:eng_x_preferred":[
        "Tunxi District"
    ],
    "name:gan_x_preferred":[
        "\u5c6f\u6eaa\u533a"
    ],
    "name:jpn_x_preferred":[
        "\u5c6f\u6e13\u533a"
    ],
    "name:kor_x_preferred":[
        "\ud230\uc2dc\uad6c"
    ],
    "name:mwl_x_preferred":[
        "Tunxi"
    ],
    "name:nan_x_preferred":[
        "T\u00fbn-khe-khu"
    ],
    "name:nld_x_preferred":[
        "Tunxi"
    ],
    "name:nob_x_preferred":[
        "Tunxi"
    ],
    "name:spa_x_preferred":[
        "T\u00fanx\u012b Q\u016b"
    ],
    "name:swe_x_preferred":[
        "Tunxi"
    ],
    "name:vie_x_preferred":[
        "\u0110\u1ed3n Kh\u00ea"
    ],
    "name:wuu_x_preferred":[
        "\u5c6f\u6eaa\u533a"
    ],
    "name:yue_x_preferred":[
        "\u5c6f\u6eaa\u5340"
    ],
    "name:zho_x_preferred":[
        "\u5c6f\u6eaa\u533a"
    ],
    "qs:name":"\u5c6f\u6eaa\u533a",
    "qs:name_adm0":"\u4e2d\u570b",
    "qs:name_adm1":"\u5b89\u5fbd\u7701",
    "qs:photos":1411,
    "qs:photos_1k":286,
    "qs:photos_9k":6,
    "qs:photos_9r":7,
    "qs:photos_all":1411,
    "qs:photos_sr":12,
    "qs:placetype":"Town",
    "qs:pop_sr":"0",
    "wd:wordcount":101,
    "wof:name":"\u5c6f\u6eaa\u533a",
    "wof:placetype":"locality"
},
  "geometry": {"coordinates":[118.307222,29.712432],"type":"Point"}
}