{
  "type": "Feature",
  "properties": {
    "gn:admin1_code":"12.0",
    "gn:asciiname":"Xujiazhuang",
    "gn:country_code":"CN",
    "gn:dem":134,
    "gn:feature_class":"P",
    "gn:feature_code":"PPL",
    "gn:name":"Xujiazhuang",
    "gn:population":0,
    "gn:timezone":"Asia/Shanghai",
    "iso:country":"CN",
    "name:zho_x_preferred":[
        "\u5f90\u5bb6\u5e84"
    ],
    "wof:name":"Xujiazhuang",
    "wof:placetype":"locality"
},
  "geometry": {"coordinates":[111.57732,31.16165],"type":"Point"}
}