{
  "type": "Feature",
  "properties": {
    "gn:admin1_code":"12.0",
    "gn:asciiname":"Lijia Dawan",
    "gn:country_code":"CN",
    "gn:dem":159,
    "gn:feature_class":"P",
    "gn:feature_code":"PPL",
    "gn:name":"Lijia Dawan",
    "gn:population":0,
    "gn:timezone":"Asia/Shanghai",
    "iso:country":"CN",
    "name:und_x_variant":[
        "\u674e\u5bb6\u5927\u5846"
    ],
    "wof:name":"Lijia Dawan",
    "wof:placetype":"locality"
},
  "geometry": {"coordinates":[115.0172,30.81316],"type":"Point"}
}