{
  "type": "Feature",
  "properties": {
    "gn:admin1_code":"7.0",
    "gn:asciiname":"Xianmei",
    "gn:country_code":"CN",
    "gn:dem":87,
    "gn:feature_class":"P",
    "gn:feature_code":"PPL",
    "gn:name":"Xianmei",
    "gn:population":0,
    "gn:timezone":"Asia/Shanghai",
    "iso:country":"CN",
    "name:zho_x_preferred":[
        "\u4ed9\u7f8e"
    ],
    "wof:name":"Xianmei",
    "wof:placetype":"locality"
},
  "geometry": {"coordinates":[118.30674999999999,25.19407],"type":"Point"}
}