{
  "type": "Feature",
  "properties": {
    "gn:admin1_code":"14.0",
    "gn:asciiname":"Sogdoi",
    "gn:country_code":"CN",
    "gn:dem":4544,
    "gn:feature_class":"P",
    "gn:feature_code":"PPLF",
    "gn:name":"Sogdoi",
    "gn:population":0,
    "gn:timezone":"Asia/Shanghai",
    "iso:country":"CN",
    "name:bod_x_preferred":[
        "Sogdoi"
    ],
    "name:msa_x_preferred":[
        "Sogdoi"
    ],
    "name:zho_x_preferred":[
        "Suoduo"
    ],
    "name:zho_x_variant":[
        "\u7d22\u591a",
        "Wucang",
        "\u543e\u4ed3"
    ],
    "wof:name":"Sogdoi",
    "wof:placetype":"locality"
},
  "geometry": {"coordinates":[80.38333,31.63333],"type":"Point"}
}