{
  "type": "Feature",
  "properties": {
    "gn:admin1_code":"15.0",
    "gn:asciiname":"Yemaogoumen",
    "gn:country_code":"CN",
    "gn:dem":1221,
    "gn:feature_class":"P",
    "gn:feature_code":"PPL",
    "gn:name":"Yemaogoumen",
    "gn:population":0,
    "gn:timezone":"Asia/Shanghai",
    "iso:country":"CN",
    "name:und_x_variant":[
        "\u53f6\u8302\u6c9f\u95e8"
    ],
    "wof:name":"Yemaogoumen",
    "wof:placetype":"locality"
},
  "geometry": {"coordinates":[105.917,33.9265],"type":"Point"}
}