{
  "type": "Feature",
  "properties": {
    "gn:admin1_code":"12.0",
    "gn:asciiname":"Qiniangshan",
    "gn:country_code":"CN",
    "gn:dem":488,
    "gn:feature_class":"P",
    "gn:feature_code":"PPL",
    "gn:name":"Qiniangshan",
    "gn:population":0,
    "gn:timezone":"Asia/Shanghai",
    "iso:country":"CN",
    "name:zho_x_preferred":[
        "\u4e03\u5a18\u5c71"
    ],
    "wof:name":"Qiniangshan",
    "wof:placetype":"locality"
},
  "geometry": {"coordinates":[115.68742,31.03749],"type":"Point"}
}