{
  "type": "Feature",
  "properties": {
    "gn:admin1_code":"32.0",
    "gn:asciiname":"Dujiapo",
    "gn:country_code":"CN",
    "gn:dem":2349,
    "gn:feature_class":"P",
    "gn:feature_code":"PPL",
    "gn:name":"Dujiapo",
    "gn:population":0,
    "gn:timezone":"Asia/Shanghai",
    "iso:country":"CN",
    "name:zho_x_preferred":[
        "\u675c\u5bb6\u5761"
    ],
    "wof:name":"Dujiapo",
    "wof:placetype":"locality"
},
  "geometry": {"coordinates":[102.398,26.7608],"type":"Point"}
}