{
  "type": "Feature",
  "properties": {
    "gn:admin1_code":"5.0",
    "gn:asciiname":"Xiaoxindian",
    "gn:country_code":"CN",
    "gn:dem":220,
    "gn:feature_class":"P",
    "gn:feature_code":"PPL",
    "gn:name":"Xiaoxindian",
    "gn:population":0,
    "gn:timezone":"Asia/Shanghai",
    "iso:country":"CN",
    "name:zho_x_preferred":[
        "\u5c0f\u8f9b\u5e97"
    ],
    "wof:name":"Xiaoxindian",
    "wof:placetype":"locality"
},
  "geometry": {"coordinates":[124.75445000000001,44.61153],"type":"Point"}
}