{
  "type": "Feature",
  "properties": {
    "gn:admin1_code":"16.0",
    "gn:asciiname":"Shanglongxing",
    "gn:country_code":"CN",
    "gn:dem":146,
    "gn:feature_class":"P",
    "gn:feature_code":"PPL",
    "gn:name":"Shanglongxing",
    "gn:population":0,
    "gn:timezone":"Asia/Shanghai",
    "iso:country":"CN",
    "name:zho_x_preferred":[
        "\u4e0a\u9f99\u5174"
    ],
    "wof:name":"Shanglongxing",
    "wof:placetype":"locality"
},
  "geometry": {"coordinates":[109.622,24.6058],"type":"Point"}
}