{
  "type": "Feature",
  "properties": {
    "gn:admin1_code":"25",
    "gn:asciiname":"Beiliumiao",
    "gn:country_code":"CN",
    "gn:dem":35,
    "gn:feature_class":"P",
    "gn:feature_code":"PPL",
    "gn:name":"Beiliumiao",
    "gn:population":0,
    "gn:timezone":"Asia/Shanghai",
    "iso:country":"CN",
    "name:und_x_variant":[
        "Liumiao"
    ],
    "name:zho_x_preferred":[
        "\u5317\u5218\u5e99"
    ],
    "name:zho_x_variant":[
        "\u5218\u5e99"
    ],
    "wof:name":"Beiliumiao",
    "wof:placetype":"locality"
},
  "geometry": {"coordinates":[115.91334999999999,36.5474],"type":"Point"}
}