{
  "type": "Feature",
  "properties": {
    "gn:admin1_code":"2.0",
    "gn:asciiname":"Shuiduitou",
    "gn:country_code":"CN",
    "gn:dem":115,
    "gn:feature_class":"P",
    "gn:feature_code":"PPL",
    "gn:name":"Shuiduitou",
    "gn:population":0,
    "gn:timezone":"Asia/Shanghai",
    "iso:country":"CN",
    "name:zho_x_preferred":[
        "\u6c34\u7893\u5934"
    ],
    "wof:name":"Shuiduitou",
    "wof:placetype":"locality"
},
  "geometry": {"coordinates":[120.03023,28.95193],"type":"Point"}
}