{
  "type": "Feature",
  "properties": {
    "gn:admin1_code":"14.0",
    "gn:asciiname":"Purgadala",
    "gn:country_code":"CN",
    "gn:dem":4614,
    "gn:feature_class":"P",
    "gn:feature_code":"PPL",
    "gn:name":"Purgadala",
    "gn:population":0,
    "gn:timezone":"Asia/Urumqi",
    "iso:country":"CN",
    "name:msa_x_preferred":[
        "Purgadala"
    ],
    "wof:name":"Purgadala",
    "wof:placetype":"locality"
},
  "geometry": {"coordinates":[84.33333,33.63333],"type":"Point"}
}