{
  "type": "Feature",
  "properties": {
    "gn:admin1_code":"04",
    "gn:asciiname":"Xiaolujing",
    "gn:cc2":"CN",
    "gn:country_code":"CN",
    "gn:dem":5,
    "gn:feature_class":"P",
    "gn:feature_code":"PPL",
    "gn:name":"Xiaolujing",
    "gn:population":0,
    "gn:timezone":"Asia/Shanghai",
    "iso:country":"CN",
    "name:und_x_variant":[
        "Hsiao-liu-ching",
        "Xiaolujing"
    ],
    "wof:name":"Xiaolujing",
    "wof:placetype":"locality"
},
  "geometry": {"coordinates":[120.8625,31.6575],"type":"Point"}
}