{
  "type": "Feature",
  "properties": {
    "gn:admin1_code":"15.0",
    "gn:asciiname":"Laoyashan",
    "gn:country_code":"CN",
    "gn:dem":2614,
    "gn:feature_class":"P",
    "gn:feature_code":"PPL",
    "gn:name":"Laoyashan",
    "gn:population":0,
    "gn:timezone":"Asia/Shanghai",
    "iso:country":"CN",
    "name:und_x_variant":[
        "\u8001\u9e26\u5c71"
    ],
    "wof:name":"Laoyashan",
    "wof:placetype":"locality"
},
  "geometry": {"coordinates":[104.13167,34.37672],"type":"Point"}
}