{
  "type": "Feature",
  "properties": {
    "gn:admin1_code":"8.0",
    "gn:asciiname":"Wuqicun",
    "gn:country_code":"CN",
    "gn:dem":190,
    "gn:feature_class":"P",
    "gn:feature_code":"PPL",
    "gn:name":"Wuqicun",
    "gn:population":0,
    "gn:timezone":"Asia/Shanghai",
    "iso:country":"CN",
    "name:zho_x_preferred":[
        "\u4e94\u4e03\u6751"
    ],
    "wof:name":"Wuqicun",
    "wof:placetype":"locality"
},
  "geometry": {"coordinates":[130.39511000000002,46.62313],"type":"Point"}
}