{
  "type": "Feature",
  "properties": {
    "gn:admin1_code":"29",
    "gn:asciiname":"Tangpen",
    "gn:country_code":"CN",
    "gn:dem":1325,
    "gn:feature_class":"P",
    "gn:feature_code":"PPL",
    "gn:name":"Tangpen",
    "gn:population":0,
    "gn:timezone":"Asia/Shanghai",
    "iso:country":"CN",
    "name:zho_x_preferred":[
        "\u6c64\u76c6"
    ],
    "wof:name":"Tangpen",
    "wof:placetype":"locality"
},
  "geometry": {"coordinates":[104.89100000000001,23.9128],"type":"Point"}
}