{
  "type": "Feature",
  "properties": {
    "gn:admin1_code":"29.0",
    "gn:asciiname":"Jiaojiaqing",
    "gn:country_code":"CN",
    "gn:dem":1570,
    "gn:feature_class":"P",
    "gn:feature_code":"PPL",
    "gn:name":"Jiaojiaqing",
    "gn:population":0,
    "gn:timezone":"Asia/Shanghai",
    "iso:country":"CN",
    "name:zho_x_preferred":[
        "\u811a\u5bb6\u7b90"
    ],
    "wof:name":"Jiaojiaqing",
    "wof:placetype":"locality"
},
  "geometry": {"coordinates":[104.239,24.7195],"type":"Point"}
}