{
  "type": "Feature",
  "properties": {
    "gn:admin1_code":"9.0",
    "gn:asciiname":"Yashang",
    "gn:country_code":"CN",
    "gn:dem":475,
    "gn:feature_class":"P",
    "gn:feature_code":"PPL",
    "gn:name":"Yashang",
    "gn:population":0,
    "gn:timezone":"Asia/Shanghai",
    "iso:country":"CN",
    "name:und_x_variant":[
        "\u5d16\u4e0a",
        "Yashang"
    ],
    "wof:name":"Yashang",
    "wof:placetype":"locality"
},
  "geometry": {"coordinates":[112.43998000000001,33.57787],"type":"Point"}
}