{
  "type": "Feature",
  "properties": {
    "gn:admin1_code":"12.0",
    "gn:asciiname":"Chenguohui",
    "gn:country_code":"CN",
    "gn:dem":72,
    "gn:feature_class":"P",
    "gn:feature_code":"PPL",
    "gn:name":"Chenguohui",
    "gn:population":0,
    "gn:timezone":"Asia/Shanghai",
    "iso:country":"CN",
    "name:zho_x_preferred":[
        "Chenguohui"
    ],
    "name:zho_x_variant":[
        "\u9648\u56fd\u8f89"
    ],
    "wof:name":"Chenguohui",
    "wof:placetype":"locality"
},
  "geometry": {"coordinates":[114.44014,29.91884000000001],"type":"Point"}
}