{
  "type": "Feature",
  "properties": {
    "gn:admin1_code":"9",
    "gn:asciiname":"Dongshenshi",
    "gn:country_code":"CN",
    "gn:dem":53,
    "gn:feature_class":"P",
    "gn:feature_code":"PPL",
    "gn:name":"Dongshenshi",
    "gn:population":0,
    "gn:timezone":"Asia/Shanghai",
    "iso:country":"CN",
    "name:zho_x_preferred":[
        "\u4e1c\u5ba1\u4ec0"
    ],
    "wof:name":"Dongshenshi",
    "wof:placetype":"locality"
},
  "geometry": {"coordinates":[115.03198,36.06452],"type":"Point"}
}