{
  "type": "Feature",
  "properties": {
    "gn:admin1_code":"14.0",
    "gn:asciiname":"Bulai",
    "gn:country_code":"CN",
    "gn:dem":3644,
    "gn:feature_class":"P",
    "gn:feature_code":"PPLF",
    "gn:name":"Bulai",
    "gn:population":0,
    "gn:timezone":"Asia/Urumqi",
    "iso:country":"CN",
    "name:bod_x_preferred":[
        "Bul\u00eag"
    ],
    "name:zho_x_preferred":[
        "Bulai"
    ],
    "name:zho_x_variant":[
        "\u5e03\u6765",
        "Ranmu",
        "\u7136\u6728"
    ],
    "wof:name":"Bulai",
    "wof:placetype":"locality"
},
  "geometry": {"coordinates":[98.301,30.801],"type":"Point"}
}