{
  "type": "Feature",
  "properties": {
    "gn:admin1_code":"7.0",
    "gn:asciiname":"Qiantang",
    "gn:country_code":"CN",
    "gn:dem":215,
    "gn:feature_class":"P",
    "gn:feature_code":"PPL",
    "gn:name":"Qiantang",
    "gn:population":0,
    "gn:timezone":"Asia/Shanghai",
    "iso:country":"CN",
    "name:deu_x_preferred":[
        "Qiantang"
    ],
    "name:ita_x_preferred":[
        "Qiantang"
    ],
    "name:zho_x_preferred":[
        "\u524d\u5858"
    ],
    "wof:name":"Qiantang",
    "wof:placetype":"locality"
},
  "geometry": {"coordinates":[118.03661,26.63377],"type":"Point"}
}