{
  "type": "Feature",
  "properties": {
    "gn:admin1_code":"19.0",
    "gn:asciiname":"Lisantun",
    "gn:country_code":"CN",
    "gn:dem":143,
    "gn:feature_class":"P",
    "gn:feature_code":"PPL",
    "gn:name":"Lisantun",
    "gn:population":0,
    "gn:timezone":"Asia/Shanghai",
    "iso:country":"CN",
    "name:und_x_variant":[
        "\u674e\u4e09\u5c6f"
    ],
    "name:zho_x_preferred":[
        "\u674e\u4e09\u5c6f"
    ],
    "wof:name":"Lisantun",
    "wof:placetype":"locality"
},
  "geometry": {"coordinates":[120.96622000000001,41.35093],"type":"Point"}
}