{
  "type": "Feature",
  "properties": {
    "gn:admin1_code":"25.0",
    "gn:asciiname":"Miaoxicun",
    "gn:country_code":"CN",
    "gn:dem":24,
    "gn:feature_class":"P",
    "gn:feature_code":"PPL",
    "gn:name":"Miaoxicun",
    "gn:population":0,
    "gn:timezone":"Asia/Shanghai",
    "iso:country":"CN",
    "name:zho_x_preferred":[
        "\u5e99\u897f\u6751"
    ],
    "wof:name":"Miaoxicun",
    "wof:placetype":"locality"
},
  "geometry": {"coordinates":[120.0689,36.60006],"type":"Point"}
}