{
  "type": "Feature",
  "properties": {
    "gn:admin1_code":"11.0",
    "gn:asciiname":"Jijiapo",
    "gn:country_code":"CN",
    "gn:dem":698,
    "gn:feature_class":"P",
    "gn:feature_code":"PPL",
    "gn:name":"Jijiapo",
    "gn:population":0,
    "gn:timezone":"Asia/Shanghai",
    "iso:country":"CN",
    "name:zho_x_preferred":[
        "\u7eaa\u5bb6\u5761"
    ],
    "wof:name":"Jijiapo",
    "wof:placetype":"locality"
},
  "geometry": {"coordinates":[109.57635999999999,27.5691],"type":"Point"}
}