{
  "type": "Feature",
  "properties": {
    "gn:admin1_code":"10",
    "gn:asciiname":"Weizi Goumen",
    "gn:country_code":"CN",
    "gn:dem":1058,
    "gn:feature_class":"P",
    "gn:feature_code":"PPL",
    "gn:name":"Weizi Goumen",
    "gn:population":0,
    "gn:timezone":"Asia/Shanghai",
    "iso:country":"CN",
    "name:zho_x_preferred":[
        "\u82c7\u5b50\u6c9f\u95e8"
    ],
    "wof:name":"Weizi Goumen",
    "wof:placetype":"locality"
},
  "geometry": {"coordinates":[116.88115999999999,41.74688],"type":"Point"}
}