{
  "type": "Feature",
  "properties": {
    "gn:admin1_code":"5.0",
    "gn:asciiname":"Shuangbaodaicun",
    "gn:country_code":"CN",
    "gn:dem":135,
    "gn:feature_class":"P",
    "gn:feature_code":"PPL",
    "gn:name":"Shuangbaodaicun",
    "gn:population":0,
    "gn:timezone":"Asia/Shanghai",
    "iso:country":"CN",
    "name:zho_x_preferred":[
        "\u53cc\u5b9d\u5cb1\u6751"
    ],
    "wof:name":"Shuangbaodaicun",
    "wof:placetype":"locality"
},
  "geometry": {"coordinates":[123.40024,46.2197],"type":"Point"}
}