{
  "type": "Feature",
  "properties": {
    "gn:admin1_code":"5.0",
    "gn:asciiname":"Qudaxianshengtun",
    "gn:country_code":"CN",
    "gn:dem":218,
    "gn:feature_class":"P",
    "gn:feature_code":"PPL",
    "gn:name":"Qudaxianshengtun",
    "gn:population":0,
    "gn:timezone":"Asia/Shanghai",
    "iso:country":"CN",
    "name:zho_x_preferred":[
        "\u66f2\u5927\u5148\u751f\u5c6f"
    ],
    "wof:name":"Qudaxianshengtun",
    "wof:placetype":"locality"
},
  "geometry": {"coordinates":[124.83879,44.54789],"type":"Point"}
}