{
  "type": "Feature",
  "properties": {
    "gn:admin1_code":"4.0",
    "gn:asciiname":"Fucha Erzu",
    "gn:country_code":"CN",
    "gn:dem":17,
    "gn:feature_class":"P",
    "gn:feature_code":"PPL",
    "gn:name":"Fucha Erzu",
    "gn:population":0,
    "gn:timezone":"Asia/Shanghai",
    "iso:country":"CN",
    "name:zho_x_preferred":[
        "\u4ed8\u5c94\u4e8c\u7ec4"
    ],
    "wof:name":"Fucha Erzu",
    "wof:placetype":"locality"
},
  "geometry": {"coordinates":[118.93638,31.32311],"type":"Point"}
}