{
  "type": "Feature",
  "properties": {
    "gn:admin1_code":"29",
    "gn:asciiname":"Xiaomolang",
    "gn:country_code":"CN",
    "gn:dem":1627,
    "gn:feature_class":"P",
    "gn:feature_code":"PPL",
    "gn:name":"Xiaomolang",
    "gn:population":0,
    "gn:timezone":"Asia/Shanghai",
    "iso:country":"CN",
    "name:zho_x_preferred":[
        "\u5c0f\u83ab\u90ce"
    ],
    "wof:name":"Xiaomolang",
    "wof:placetype":"locality"
},
  "geometry": {"coordinates":[101.95099999999999,23.5248],"type":"Point"}
}