{
  "type": "Feature",
  "properties": {
    "gn:admin1_code":"15.0",
    "gn:asciiname":"Shuangxian",
    "gn:country_code":"CN",
    "gn:dem":1379,
    "gn:feature_class":"P",
    "gn:feature_code":"PPL",
    "gn:name":"Shuangxian",
    "gn:population":0,
    "gn:timezone":"Asia/Shanghai",
    "iso:country":"CN",
    "name:zho_x_preferred":[
        "\u53cc\u5c98"
    ],
    "wof:name":"Shuangxian",
    "wof:placetype":"locality"
},
  "geometry": {"coordinates":[107.236,35.6159],"type":"Point"}
}