{
  "type": "Feature",
  "properties": {
    "gn:admin1_code":"15.0",
    "gn:asciiname":"Houchuan",
    "gn:country_code":"CN",
    "gn:dem":1143,
    "gn:feature_class":"P",
    "gn:feature_code":"PPL",
    "gn:name":"Houchuan",
    "gn:population":0,
    "gn:timezone":"Asia/Shanghai",
    "iso:country":"CN",
    "name:zho_x_preferred":[
        "\u540e\u5ddd"
    ],
    "wof:name":"Houchuan",
    "wof:placetype":"locality"
},
  "geometry": {"coordinates":[108.086,35.6603],"type":"Point"}
}