{
  "type": "Feature",
  "properties": {
    "gn:admin1_code":"11.0",
    "gn:asciiname":"Shichaipo",
    "gn:country_code":"CN",
    "gn:dem":76,
    "gn:feature_class":"P",
    "gn:feature_code":"PPL",
    "gn:name":"Shichaipo",
    "gn:population":0,
    "gn:timezone":"Asia/Shanghai",
    "iso:country":"CN",
    "name:zho_x_preferred":[
        "Shichaipo"
    ],
    "name:zho_x_variant":[
        "\u62fe\u67f4\u5761"
    ],
    "wof:name":"Shichaipo",
    "wof:placetype":"locality"
},
  "geometry": {"coordinates":[111.67726,29.18734000000001],"type":"Point"}
}