{
  "type": "Feature",
  "properties": {
    "gn:admin1_code":"4.0",
    "gn:asciiname":"Ganqiaozhuang",
    "gn:country_code":"CN",
    "gn:dem":1,
    "gn:feature_class":"P",
    "gn:feature_code":"PPL",
    "gn:name":"Ganqiaozhuang",
    "gn:population":0,
    "gn:timezone":"Asia/Shanghai",
    "iso:country":"CN",
    "name:zho_x_preferred":[
        "Ganqiaozhuang"
    ],
    "name:zho_x_variant":[
        "\u5e72\u6865\u5e84"
    ],
    "wof:name":"Ganqiaozhuang",
    "wof:placetype":"locality"
},
  "geometry": {"coordinates":[119.41434,34.55593],"type":"Point"}
}