{
  "type": "Feature",
  "properties": {
    "gn:admin1_code":"18",
    "gn:asciiname":"Ejia",
    "gn:country_code":"CN",
    "gn:dem":1956,
    "gn:feature_class":"P",
    "gn:feature_code":"PPL",
    "gn:name":"Ejia",
    "gn:population":0,
    "gn:timezone":"Asia/Shanghai",
    "iso:country":"CN",
    "name:zho_x_preferred":[
        "\u9e45\u621b"
    ],
    "wof:name":"Ejia",
    "wof:placetype":"locality"
},
  "geometry": {"coordinates":[104.607,26.5452],"type":"Point"}
}