{
  "type": "Feature",
  "properties": {
    "gn:admin1_code":"3.0",
    "gn:asciiname":"Zhushanqiao",
    "gn:cc2":"CN",
    "gn:country_code":"CN",
    "gn:dem":199,
    "gn:feature_class":"P",
    "gn:feature_code":"PPL",
    "gn:name":"Zhushanqiao",
    "gn:population":0,
    "gn:timezone":"Asia/Shanghai",
    "iso:country":"CN",
    "name:und_x_variant":[
        "Chu-shan-ch\u2019iao",
        "Zhushanqiao"
    ],
    "wof:name":"Zhushanqiao",
    "wof:placetype":"locality"
},
  "geometry": {"coordinates":[115.15000000000001,27.25],"type":"Point"}
}