{
  "type": "Feature",
  "properties": {
    "gn:admin1_code":"24.0",
    "gn:asciiname":"Lujiawan",
    "gn:country_code":"CN",
    "gn:dem":1017,
    "gn:feature_class":"P",
    "gn:feature_code":"PPL",
    "gn:name":"L\u00fcjiawan",
    "gn:population":0,
    "gn:timezone":"Asia/Shanghai",
    "iso:country":"CN",
    "name:zho_x_preferred":[
        "L\u00fcjiawan"
    ],
    "name:zho_x_variant":[
        "\u5415\u5bb6\u6e7e"
    ],
    "wof:name":"Lujiawan",
    "wof:placetype":"locality"
},
  "geometry": {"coordinates":[111.00185,35.35969],"type":"Point"}
}