{
  "type": "Feature",
  "properties": {
    "gn:admin1_code":"14.0",
    "gn:asciiname":"Genyao",
    "gn:country_code":"CN",
    "gn:dem":2730,
    "gn:feature_class":"P",
    "gn:feature_code":"PPL",
    "gn:name":"Genyao",
    "gn:population":0,
    "gn:timezone":"Asia/Urumqi",
    "iso:country":"CN",
    "name:zho_x_preferred":[
        "\u6839\u8981"
    ],
    "wof:name":"Genyao",
    "wof:placetype":"locality"
},
  "geometry": {"coordinates":[97.27585000000001,30.07275],"type":"Point"}
}