{
  "type": "Feature",
  "properties": {
    "gn:admin1_code":"10.0",
    "gn:asciiname":"Shandongli",
    "gn:country_code":"CN",
    "gn:dem":5,
    "gn:feature_class":"P",
    "gn:feature_code":"PPL",
    "gn:name":"Shandongli",
    "gn:population":0,
    "gn:timezone":"Asia/Shanghai",
    "iso:country":"CN",
    "name:zho_x_preferred":[
        "\u5c71\u4e1c\u91cc"
    ],
    "wof:name":"Shandongli",
    "wof:placetype":"locality"
},
  "geometry": {"coordinates":[119.60683,39.93225],"type":"Point"}
}