{
  "type": "Feature",
  "properties": {
    "gn:admin1_code":"8.0",
    "gn:asciiname":"Liujuntun",
    "gn:country_code":"CN",
    "gn:dem":203,
    "gn:feature_class":"P",
    "gn:feature_code":"PPL",
    "gn:name":"Liujuntun",
    "gn:population":0,
    "gn:timezone":"Asia/Shanghai",
    "iso:country":"CN",
    "name:zho_x_preferred":[
        "\u5218\u4fca\u5c6f"
    ],
    "wof:name":"Liujuntun",
    "wof:placetype":"locality"
},
  "geometry": {"coordinates":[125.48285,47.9215],"type":"Point"}
}