{
  "type": "Feature",
  "properties": {
    "gn:admin1_code":"5.0",
    "gn:asciiname":"Qianwengquan",
    "gn:country_code":"CN",
    "gn:dem":229,
    "gn:feature_class":"P",
    "gn:feature_code":"PPL",
    "gn:name":"Qianwengquan",
    "gn:population":0,
    "gn:timezone":"Asia/Shanghai",
    "iso:country":"CN",
    "name:zho_x_preferred":[
        "\u524d\u74ee\u5708"
    ],
    "wof:name":"Qianwengquan",
    "wof:placetype":"locality"
},
  "geometry": {"coordinates":[125.37257,43.47584000000001],"type":"Point"}
}