{
  "type": "Feature",
  "properties": {
    "gn:admin1_code":"4.0",
    "gn:asciiname":"Dingxinzhuangcun",
    "gn:country_code":"CN",
    "gn:dem":37,
    "gn:feature_class":"P",
    "gn:feature_code":"PPL",
    "gn:name":"Dingxinzhuangcun",
    "gn:population":0,
    "gn:timezone":"Asia/Shanghai",
    "iso:country":"CN",
    "name:zho_x_preferred":[
        "\u4e01\u8f9b\u5e84\u6751"
    ],
    "wof:name":"Dingxinzhuangcun",
    "wof:placetype":"locality"
},
  "geometry": {"coordinates":[116.93872,34.61493],"type":"Point"}
}