{
  "type": "Feature",
  "properties": {
    "gn:admin1_code":"24.0",
    "gn:asciiname":"Lemagou",
    "gn:country_code":"CN",
    "gn:dem":1758,
    "gn:feature_class":"P",
    "gn:feature_code":"PPL",
    "gn:name":"Lemagou",
    "gn:population":0,
    "gn:timezone":"Asia/Shanghai",
    "iso:country":"CN",
    "name:zho_x_preferred":[
        "\u52d2\u9a6c\u6c9f"
    ],
    "wof:name":"Lemagou",
    "wof:placetype":"locality"
},
  "geometry": {"coordinates":[112.07102999999999,39.32509],"type":"Point"}
}