{
  "type": "Feature",
  "properties": {
    "gn:admin1_code":"29.0",
    "gn:asciiname":"Huoshidi",
    "gn:country_code":"CN",
    "gn:dem":1634,
    "gn:feature_class":"P",
    "gn:feature_code":"PPL",
    "gn:name":"Huoshidi",
    "gn:population":0,
    "gn:timezone":"Asia/Shanghai",
    "iso:country":"CN",
    "name:zho_x_preferred":[
        "\u706b\u77f3\u5730"
    ],
    "wof:name":"Huoshidi",
    "wof:placetype":"locality"
},
  "geometry": {"coordinates":[103.24299999999999,27.3308],"type":"Point"}
}