{
  "type": "Feature",
  "properties": {
    "gn:admin1_code":"4.0",
    "gn:asciiname":"Qiaohuaxin",
    "gn:country_code":"CN",
    "gn:dem":7,
    "gn:feature_class":"P",
    "gn:feature_code":"PPL",
    "gn:name":"Qiaohuaxin",
    "gn:population":0,
    "gn:timezone":"Asia/Shanghai",
    "iso:country":"CN",
    "name:zho_x_preferred":[
        "Qiaohuaxin"
    ],
    "name:zho_x_variant":[
        "\u4e54\u82b1\u65b0"
    ],
    "wof:name":"Qiaohuaxin",
    "wof:placetype":"locality"
},
  "geometry": {"coordinates":[119.22534,33.11367],"type":"Point"}
}