{
  "type": "Feature",
  "properties": {
    "gn:admin1_code":"32.0",
    "gn:asciiname":"Fuziping",
    "gn:country_code":"CN",
    "gn:dem":1423,
    "gn:feature_class":"P",
    "gn:feature_code":"PPL",
    "gn:name":"Fuziping",
    "gn:population":0,
    "gn:timezone":"Asia/Shanghai",
    "iso:country":"CN",
    "name:zho_x_preferred":[
        "\u99a5\u5b50\u576a"
    ],
    "wof:name":"Fuziping",
    "wof:placetype":"locality"
},
  "geometry": {"coordinates":[104.84828,32.23015],"type":"Point"}
}