{
  "type": "Feature",
  "properties": {
    "gn:admin1_code":"3",
    "gn:asciiname":"Yanbei",
    "gn:country_code":"CN",
    "gn:dem":194,
    "gn:feature_class":"P",
    "gn:feature_code":"PPL",
    "gn:name":"Yanbei",
    "gn:population":0,
    "gn:timezone":"Asia/Shanghai",
    "iso:country":"CN",
    "name:zho_x_preferred":[
        "\u9122\u80cc"
    ],
    "wof:name":"Yanbei",
    "wof:placetype":"locality"
},
  "geometry": {"coordinates":[114.301,26.3347],"type":"Point"}
}