{
  "type": "Feature",
  "properties": {
    "gn:admin1_code":"32.0",
    "gn:asciiname":"Huijia",
    "gn:country_code":"CN",
    "gn:dem":347,
    "gn:feature_class":"P",
    "gn:feature_code":"PPL",
    "gn:name":"Huijia",
    "gn:population":0,
    "gn:timezone":"Asia/Shanghai",
    "iso:country":"CN",
    "name:zho_x_preferred":[
        "\u4f1a\u5bb6"
    ],
    "wof:name":"Huijia",
    "wof:placetype":"locality"
},
  "geometry": {"coordinates":[105.048,29.3396],"type":"Point"}
}