{
  "type": "Feature",
  "properties": {
    "gn:admin1_code":"7",
    "gn:asciiname":"Yibaoshan",
    "gn:country_code":"CN",
    "gn:dem":11,
    "gn:feature_class":"P",
    "gn:feature_code":"PPL",
    "gn:name":"Yibaoshan",
    "gn:population":0,
    "gn:timezone":"Asia/Shanghai",
    "iso:country":"CN",
    "name:und_x_variant":[
        "Yizhuangshan"
    ],
    "name:zho_x_preferred":[
        "\u76ca\u5b9d\u5c71"
    ],
    "wof:name":"Yibaoshan",
    "wof:placetype":"locality"
},
  "geometry": {"coordinates":[117.37194,23.89889],"type":"Point"}
}