{
  "type": "Feature",
  "properties": {
    "gn:admin1_code":"22",
    "gn:asciiname":"Hongshuikou",
    "gn:country_code":"CN",
    "gn:dem":929,
    "gn:feature_class":"P",
    "gn:feature_code":"PPL",
    "gn:name":"Hongshuikou",
    "gn:population":0,
    "gn:timezone":"Asia/Shanghai",
    "iso:country":"CN",
    "name:zho_x_preferred":[
        "\u6d2a\u6c34\u53e3"
    ],
    "wof:name":"Hongshuikou",
    "wof:placetype":"locality"
},
  "geometry": {"coordinates":[115.47933,39.99094],"type":"Point"}
}