{
  "type": "Feature",
  "properties": {
    "gn:admin1_code":"2.0",
    "gn:asciiname":"Taipingqiao",
    "gn:country_code":"CN",
    "gn:dem":7,
    "gn:feature_class":"P",
    "gn:feature_code":"PPL",
    "gn:name":"Taipingqiao",
    "gn:population":0,
    "gn:timezone":"Asia/Shanghai",
    "iso:country":"CN",
    "name:und_x_variant":[
        "\u592a\u5e73\u6865"
    ],
    "wof:name":"Taipingqiao",
    "wof:placetype":"locality"
},
  "geometry": {"coordinates":[120.42246000000002,30.70152],"type":"Point"}
}