{
  "type": "Feature",
  "properties": {
    "gn:admin1_code":"25",
    "gn:asciiname":"Qianshihuiyao",
    "gn:country_code":"CN",
    "gn:dem":119,
    "gn:feature_class":"P",
    "gn:feature_code":"PPL",
    "gn:name":"Qianshihuiyao",
    "gn:population":0,
    "gn:timezone":"Asia/Shanghai",
    "iso:country":"CN",
    "name:zho_x_preferred":[
        "\u524d\u77f3\u7070\u7a91"
    ],
    "wof:name":"Qianshihuiyao",
    "wof:placetype":"locality"
},
  "geometry": {"coordinates":[118.744,35.5724],"type":"Point"}
}