{
  "type": "Feature",
  "properties": {
    "gn:admin1_code":"11",
    "gn:asciiname":"Zhuyewan",
    "gn:country_code":"CN",
    "gn:dem":244,
    "gn:feature_class":"P",
    "gn:feature_code":"PPL",
    "gn:name":"Zhuyewan",
    "gn:population":0,
    "gn:timezone":"Asia/Shanghai",
    "iso:country":"CN",
    "name:zho_x_preferred":[
        "\u7af9\u53f6\u6e7e"
    ],
    "wof:name":"Zhuyewan",
    "wof:placetype":"locality"
},
  "geometry": {"coordinates":[111.03986999999999,28.30412],"type":"Point"}
}