{
  "type": "Feature",
  "properties": {
    "gn:admin1_code":"9.0",
    "gn:asciiname":"Daping",
    "gn:country_code":"CN",
    "gn:dem":969,
    "gn:feature_class":"P",
    "gn:feature_code":"PPL",
    "gn:name":"Daping",
    "gn:population":0,
    "gn:timezone":"Asia/Shanghai",
    "iso:country":"CN",
    "name:zho_x_preferred":[
        "\u5927\u576a"
    ],
    "wof:name":"Daping",
    "wof:placetype":"locality"
},
  "geometry": {"coordinates":[111.95307,33.83856],"type":"Point"}
}