{
  "type": "Feature",
  "properties": {
    "gn:admin1_code":"5.0",
    "gn:asciiname":"Dabanfang",
    "gn:country_code":"CN",
    "gn:dem":1002,
    "gn:feature_class":"P",
    "gn:feature_code":"PPL",
    "gn:name":"Dabanfang",
    "gn:population":0,
    "gn:timezone":"Asia/Shanghai",
    "iso:country":"CN",
    "name:und_x_variant":[
        "\u5927\u677f\u623f"
    ],
    "wof:name":"Dabanfang",
    "wof:placetype":"locality"
},
  "geometry": {"coordinates":[127.61870999999999,41.49115],"type":"Point"}
}