{
  "type": "Feature",
  "properties": {
    "gn:admin1_code":"8.0",
    "gn:asciiname":"Xinzhuangcun",
    "gn:country_code":"CN",
    "gn:dem":173,
    "gn:feature_class":"P",
    "gn:feature_code":"PPL",
    "gn:name":"Xinzhuangcun",
    "gn:population":0,
    "gn:timezone":"Asia/Shanghai",
    "iso:country":"CN",
    "name:zho_x_preferred":[
        "\u65b0\u5e84\u6751"
    ],
    "wof:name":"Xinzhuangcun",
    "wof:placetype":"locality"
},
  "geometry": {"coordinates":[127.17157,45.08692],"type":"Point"}
}