{
  "type": "Feature",
  "properties": {
    "gn:admin1_code":"02",
    "gn:asciiname":"Guanyinyan",
    "gn:country_code":"CN",
    "gn:dem":574,
    "gn:feature_class":"P",
    "gn:feature_code":"PPL",
    "gn:name":"Guanyinyan",
    "gn:population":0,
    "gn:timezone":"Asia/Shanghai",
    "iso:country":"CN",
    "name:und_x_variant":[
        "Kuan-yin-yen",
        "Guanyinyan"
    ],
    "name:zho_x_preferred":[
        "\u89c2\u97f3\u5ca9"
    ],
    "wof:name":"Guanyinyan",
    "wof:placetype":"locality"
},
  "geometry": {"coordinates":[120.92081,28.13465],"type":"Point"}
}