{
  "type": "Feature",
  "properties": {
    "gn:admin1_code":"7",
    "gn:asciiname":"Lubei",
    "gn:country_code":"CN",
    "gn:dem":17,
    "gn:feature_class":"P",
    "gn:feature_code":"PPL",
    "gn:name":"Lubei",
    "gn:population":0,
    "gn:timezone":"Asia/Shanghai",
    "iso:country":"CN",
    "name:und_x_variant":[
        "Lu-pei",
        "Lubei"
    ],
    "name:zho_x_preferred":[
        "\u8def\u5317"
    ],
    "wof:name":"Lubei",
    "wof:placetype":"locality"
},
  "geometry": {"coordinates":[119.54288,25.92956],"type":"Point"}
}