{
  "type": "Feature",
  "properties": {
    "gn:admin1_code":"29.0",
    "gn:asciiname":"Shahe",
    "gn:country_code":"CN",
    "gn:dem":2485,
    "gn:feature_class":"P",
    "gn:feature_code":"PPL",
    "gn:name":"Shahe",
    "gn:population":0,
    "gn:timezone":"Asia/Shanghai",
    "iso:country":"CN",
    "name:zho_x_preferred":[
        "\u6c99\u6cb3"
    ],
    "wof:name":"Shahe",
    "wof:placetype":"locality"
},
  "geometry": {"coordinates":[99.0736,25.2312],"type":"Point"}
}