{
  "type": "Feature",
  "properties": {
    "gn:country":"CN",
    "gn:fcode":"PPLA3",
    "gn:population":67820,
    "iso:country":"CN",
    "name:ast_x_preferred":[
        "Dongfeng"
    ],
    "name:ceb_x_preferred":[
        "Dongfeng"
    ],
    "name:eng_x_preferred":[
        "Dongfeng"
    ],
    "name:gan_x_preferred":[
        "\u4e1c\u4e30\u9547"
    ],
    "name:swe_x_preferred":[
        "Dongfeng"
    ],
    "name:und_x_variant":[
        "Tung-feng"
    ],
    "name:wuu_x_preferred":[
        "\u4e1c\u4e30\u9547"
    ],
    "name:zho_x_preferred":[
        "Tung-p\u2019ing-hsien"
    ],
    "name:zho_x_variant":[
        "Ta-tu-ch\u2019uan",
        "\u4e1c\u4e30\u9547"
    ],
    "qs:name":"Dongfeng",
    "qs:photos_9r":0,
    "qs:photos_sr":0,
    "qs:pop_sr":"8",
    "wd:wordcount":287,
    "wof:name":"Dongfeng",
    "wof:placetype":"locality",
    "wof:population":67820
},
  "geometry": {"coordinates":[125.51176,42.64031],"type":"Point"}
}