{
  "type": "Feature",
  "properties": {
    "gn:admin1_code":"19.0",
    "gn:asciiname":"Caifenggoucun",
    "gn:country_code":"CN",
    "gn:dem":281,
    "gn:feature_class":"P",
    "gn:feature_code":"PPL",
    "gn:name":"Caifenggoucun",
    "gn:population":0,
    "gn:timezone":"Asia/Shanghai",
    "iso:country":"CN",
    "name:zho_x_preferred":[
        "\u5f69\u51e4\u6c9f\u6751"
    ],
    "wof:name":"Caifenggoucun",
    "wof:placetype":"locality"
},
  "geometry": {"coordinates":[120.70077999999999,41.50306],"type":"Point"}
}