{
  "type": "Feature",
  "properties": {
    "gn:admin1_code":"32.0",
    "gn:asciiname":"Xiongjia Wayao",
    "gn:country_code":"CN",
    "gn:dem":565,
    "gn:feature_class":"P",
    "gn:feature_code":"PPL",
    "gn:name":"Xiongjia Wayao",
    "gn:population":0,
    "gn:timezone":"Asia/Shanghai",
    "iso:country":"CN",
    "name:zho_x_preferred":[
        "\u718a\u5bb6\u74e6\u7a91"
    ],
    "wof:name":"Xiongjia Wayao",
    "wof:placetype":"locality"
},
  "geometry": {"coordinates":[104.19199999999999,31.3003],"type":"Point"}
}