{
  "type": "Feature",
  "properties": {
    "gn:admin1_code":"15.0",
    "gn:asciiname":"Bingcaojing",
    "gn:country_code":"CN",
    "gn:dem":1297,
    "gn:feature_class":"P",
    "gn:feature_code":"PPL",
    "gn:name":"Bingcaojing",
    "gn:population":0,
    "gn:timezone":"Asia/Shanghai",
    "iso:country":"CN",
    "name:zho_x_preferred":[
        "\u51b0\u8349\u4e95"
    ],
    "wof:name":"Bingcaojing",
    "wof:placetype":"locality"
},
  "geometry": {"coordinates":[104.19799999999999,39.0847],"type":"Point"}
}