{
  "type": "Feature",
  "properties": {
    "gn:admin1_code":"11.0",
    "gn:asciiname":"Chuanxingli",
    "gn:country_code":"CN",
    "gn:dem":153,
    "gn:feature_class":"P",
    "gn:feature_code":"PPL",
    "gn:name":"Chuanxingli",
    "gn:population":0,
    "gn:timezone":"Asia/Shanghai",
    "iso:country":"CN",
    "name:zho_x_preferred":[
        "\u8239\u5f62\u91cc"
    ],
    "wof:name":"Chuanxingli",
    "wof:placetype":"locality"
},
  "geometry": {"coordinates":[111.7529,27.61008],"type":"Point"}
}