{
  "type": "Feature",
  "properties": {
    "gn:admin1_code":"24.0",
    "gn:asciiname":"Liwangjian",
    "gn:country_code":"CN",
    "gn:dem":1009,
    "gn:feature_class":"P",
    "gn:feature_code":"PPL",
    "gn:name":"Liwangjian",
    "gn:population":0,
    "gn:timezone":"Asia/Shanghai",
    "iso:country":"CN",
    "name:zho_x_preferred":[
        "\u674e\u6c6a\u6da7"
    ],
    "wof:name":"Liwangjian",
    "wof:placetype":"locality"
},
  "geometry": {"coordinates":[113.53131999999999,40.00624000000001],"type":"Point"}
}