{
  "type": "Feature",
  "properties": {
    "gn:admin1_code":"8.0",
    "gn:asciiname":"Junchuan Sanshiqidui",
    "gn:country_code":"CN",
    "gn:dem":67,
    "gn:feature_class":"P",
    "gn:feature_code":"PPLF",
    "gn:name":"Junchuan Sanshiqidui",
    "gn:population":0,
    "gn:timezone":"Asia/Shanghai",
    "iso:country":"CN",
    "name:zho_x_preferred":[
        "\u519b\u5ddd\u4e09\u5341\u4e03\u961f"
    ],
    "wof:name":"Junchuan Sanshiqidui",
    "wof:placetype":"locality"
},
  "geometry": {"coordinates":[131.13211999999999,47.52239],"type":"Point"}
}