{
  "type": "Feature",
  "properties": {
    "gn:admin1_code":"2.0",
    "gn:asciiname":"Laotangshan",
    "gn:country_code":"CN",
    "gn:dem":66,
    "gn:feature_class":"P",
    "gn:feature_code":"PPL",
    "gn:name":"Laotangshan",
    "gn:population":0,
    "gn:timezone":"Asia/Shanghai",
    "iso:country":"CN",
    "name:zho_x_preferred":[
        "\u8001\u5858\u5c71"
    ],
    "wof:name":"Laotangshan",
    "wof:placetype":"locality"
},
  "geometry": {"coordinates":[121.98399999999999,30.0505],"type":"Point"}
}