{
  "type": "Feature",
  "properties": {
    "gn:admin1_code":"2.0",
    "gn:asciiname":"Meiwukou",
    "gn:country_code":"CN",
    "gn:dem":624,
    "gn:feature_class":"P",
    "gn:feature_code":"PPL",
    "gn:name":"Meiwukou",
    "gn:population":0,
    "gn:timezone":"Asia/Shanghai",
    "iso:country":"CN",
    "name:und_x_variant":[
        "\u6885\u575e\u53e3"
    ],
    "wof:name":"Meiwukou",
    "wof:placetype":"locality"
},
  "geometry": {"coordinates":[118.95653,30.34447],"type":"Point"}
}