{
  "type": "Feature",
  "properties": {
    "gn:admin1_code":"20.0",
    "gn:asciiname":"Nanyingzi",
    "gn:country_code":"CN",
    "gn:dem":1549,
    "gn:feature_class":"P",
    "gn:feature_code":"PPL",
    "gn:name":"Nanyingzi",
    "gn:population":0,
    "gn:timezone":"Asia/Shanghai",
    "iso:country":"CN",
    "name:und_x_variant":[
        "\u5357\u8425\u5b50"
    ],
    "wof:name":"Nanyingzi",
    "wof:placetype":"locality"
},
  "geometry": {"coordinates":[112.28858,41.59186],"type":"Point"}
}