{
  "type": "Feature",
  "properties": {
    "gn:admin1_code":"32.0",
    "gn:asciiname":"Gongqiaonian",
    "gn:country_code":"CN",
    "gn:dem":503,
    "gn:feature_class":"P",
    "gn:feature_code":"PPL",
    "gn:name":"Gongqiaonian",
    "gn:population":0,
    "gn:timezone":"Asia/Shanghai",
    "iso:country":"CN",
    "name:zho_x_preferred":[
        "\u62f1\u6865\u78be"
    ],
    "wof:name":"Gongqiaonian",
    "wof:placetype":"locality"
},
  "geometry": {"coordinates":[104.15895999999999,31.03311],"type":"Point"}
}