{
  "type": "Feature",
  "properties": {
    "gn:admin1_code":"8.0",
    "gn:asciiname":"Qijingcun",
    "gn:country_code":"CN",
    "gn:dem":134,
    "gn:feature_class":"P",
    "gn:feature_code":"PPL",
    "gn:name":"Qijingcun",
    "gn:population":0,
    "gn:timezone":"Asia/Shanghai",
    "iso:country":"CN",
    "name:zho_x_preferred":[
        "\u7941\u4e95\u6751"
    ],
    "wof:name":"Qijingcun",
    "wof:placetype":"locality"
},
  "geometry": {"coordinates":[126.84583000000001,46.09413],"type":"Point"}
}