{
  "type": "Feature",
  "properties": {
    "gn:admin1_code":"29.0",
    "gn:asciiname":"Jinchangbu",
    "gn:country_code":"CN",
    "gn:dem":1504,
    "gn:feature_class":"P",
    "gn:feature_code":"PPL",
    "gn:name":"Jinchangbu",
    "gn:population":0,
    "gn:timezone":"Asia/Shanghai",
    "iso:country":"CN",
    "name:zho_x_preferred":[
        "\u91d1\u5382\u5821"
    ],
    "wof:name":"Jinchangbu",
    "wof:placetype":"locality"
},
  "geometry": {"coordinates":[103.09999999999999,22.7858],"type":"Point"}
}