{
  "type": "Feature",
  "properties": {
    "gn:admin1_code":"15.0",
    "gn:asciiname":"Jinping",
    "gn:country_code":"CN",
    "gn:dem":1998,
    "gn:feature_class":"P",
    "gn:feature_code":"PPL",
    "gn:name":"Jinping",
    "gn:population":0,
    "gn:timezone":"Asia/Shanghai",
    "iso:country":"CN",
    "name:ceb_x_preferred":[
        "Jinping"
    ],
    "name:deu_x_preferred":[
        "Jinping"
    ],
    "name:fra_x_preferred":[
        "Jinping"
    ],
    "name:nor_x_preferred":[
        "Jinping"
    ],
    "name:swe_x_preferred":[
        "Jinping"
    ],
    "name:ukr_x_preferred":[
        "\u0426\u0437\u0456\u043d\u044c\u043f\u0456\u043d"
    ],
    "name:und_x_variant":[
        "\u9526\u5c4f"
    ],
    "wof:name":"Jinping",
    "wof:placetype":"locality"
},
  "geometry": {"coordinates":[105.08913,35.26198],"type":"Point"}
}