{
  "type": "Feature",
  "properties": {
    "gn:admin1_code":"19.0",
    "gn:asciiname":"Dayingzicun",
    "gn:country_code":"CN",
    "gn:dem":94,
    "gn:feature_class":"P",
    "gn:feature_code":"PPL",
    "gn:name":"Dayingzicun",
    "gn:population":0,
    "gn:timezone":"Asia/Shanghai",
    "iso:country":"CN",
    "name:zho_x_preferred":[
        "\u5927\u8425\u5b50\u6751"
    ],
    "wof:name":"Dayingzicun",
    "wof:placetype":"locality"
},
  "geometry": {"coordinates":[121.19781999999999,41.46303],"type":"Point"}
}