{
  "type": "Feature",
  "properties": {
    "gn:admin1_code":"26.0",
    "gn:asciiname":"Kuangoukou",
    "gn:country_code":"CN",
    "gn:dem":1099,
    "gn:feature_class":"P",
    "gn:feature_code":"PPL",
    "gn:name":"Kuangoukou",
    "gn:population":0,
    "gn:timezone":"Asia/Shanghai",
    "iso:country":"CN",
    "name:zho_x_preferred":[
        "\u5bbd\u6c9f\u53e3"
    ],
    "wof:name":"Kuangoukou",
    "wof:placetype":"locality"
},
  "geometry": {"coordinates":[109.34917,33.80242],"type":"Point"}
}