{
  "type": "Feature",
  "properties": {
    "gn:admin1_code":"10",
    "gn:asciiname":"Kuihua",
    "gn:country_code":"CN",
    "gn:dem":1247,
    "gn:feature_class":"P",
    "gn:feature_code":"PPL",
    "gn:name":"Kuihua",
    "gn:population":0,
    "gn:timezone":"Asia/Shanghai",
    "iso:country":"CN",
    "name:zho_x_preferred":[
        "\u8475\u82b1"
    ],
    "wof:name":"Kuihua",
    "wof:placetype":"locality"
},
  "geometry": {"coordinates":[115.56304,40.97484],"type":"Point"}
}