{
  "type": "Feature",
  "properties": {
    "gn:admin1_code":"03",
    "gn:asciiname":"Hengshi",
    "gn:cc2":"CN",
    "gn:country_code":"CN",
    "gn:dem":225,
    "gn:feature_class":"P",
    "gn:feature_code":"PPL",
    "gn:name":"Hengshi",
    "gn:population":0,
    "gn:timezone":"Asia/Shanghai",
    "iso:country":"CN",
    "name:jpn_x_preferred":[
        "\u6a2a\u5e02\u93ae"
    ],
    "name:und_x_variant":[
        "Heng-shih",
        "Heng-shih-ching",
        "Hengshi"
    ],
    "name:zho_x_preferred":[
        "\u6a2a\u5e02\u9547"
    ],
    "wof:name":"Hengshi",
    "wof:placetype":"locality"
},
  "geometry": {"coordinates":[114.68333,26.05],"type":"Point"}
}