{
  "type": "Feature",
  "properties": {
    "gn:admin1_code":"11.0",
    "gn:asciiname":"Huachuantang",
    "gn:country_code":"CN",
    "gn:dem":508,
    "gn:feature_class":"P",
    "gn:feature_code":"PPL",
    "gn:name":"Huachuantang",
    "gn:population":0,
    "gn:timezone":"Asia/Shanghai",
    "iso:country":"CN",
    "name:zho_x_preferred":[
        "\u5212\u8239\u5858"
    ],
    "wof:name":"Huachuantang",
    "wof:placetype":"locality"
},
  "geometry": {"coordinates":[110.85892,26.75931],"type":"Point"}
}