{
  "type": "Feature",
  "properties": {
    "gn:admin1_code":"19.0",
    "gn:asciiname":"Qinputun",
    "gn:country_code":"CN",
    "gn:dem":272,
    "gn:feature_class":"P",
    "gn:feature_code":"PPL",
    "gn:name":"Qinputun",
    "gn:population":0,
    "gn:timezone":"Asia/Shanghai",
    "iso:country":"CN",
    "name:und_x_variant":[
        "\u52e4\u666e\u5c6f"
    ],
    "name:zho_x_preferred":[
        "\u52e4\u666e\u5c6f"
    ],
    "wof:name":"Qinputun",
    "wof:placetype":"locality"
},
  "geometry": {"coordinates":[124.813,42.8091],"type":"Point"}
}