{
  "type": "Feature",
  "properties": {
    "gn:admin1_code":"6.0",
    "gn:asciiname":"Duocai",
    "gn:country_code":"CN",
    "gn:dem":4294,
    "gn:feature_class":"P",
    "gn:feature_code":"PPLA4",
    "gn:name":"Duocai",
    "gn:population":0,
    "gn:timezone":"Asia/Urumqi",
    "iso:country":"CN",
    "name:mon_x_preferred":[
        "Doic\u00ea"
    ],
    "name:und_x_variant":[
        "Duocai Xiang",
        "Saimoyong"
    ],
    "name:zho_x_preferred":[
        "\u591a\u91c7"
    ],
    "name:zho_x_variant":[
        "\u591a\u91c7\u4e61",
        "\u8d5b\u83ab\u6d8c"
    ],
    "wof:name":"Duocai",
    "wof:placetype":"locality"
},
  "geometry": {"coordinates":[95.42127000000001,33.81034],"type":"Point"}
}