{
  "type": "Feature",
  "properties": {
    "gn:admin1_code":"8.0",
    "gn:asciiname":"Zhanwangcun",
    "gn:country_code":"CN",
    "gn:dem":274,
    "gn:feature_class":"P",
    "gn:feature_code":"PPL",
    "gn:name":"Zhanwangcun",
    "gn:population":0,
    "gn:timezone":"Asia/Shanghai",
    "iso:country":"CN",
    "name:zho_x_preferred":[
        "\u5c55\u671b\u6751"
    ],
    "wof:name":"Zhanwangcun",
    "wof:placetype":"locality"
},
  "geometry": {"coordinates":[126.04705,47.49905],"type":"Point"}
}