{
  "type": "Feature",
  "properties": {
    "gn:admin1_code":"3.0",
    "gn:asciiname":"Yifeng",
    "gn:country_code":"CN",
    "gn:dem":66,
    "gn:feature_class":"P",
    "gn:feature_code":"PPL",
    "gn:name":"Yifeng",
    "gn:population":0,
    "gn:timezone":"Asia/Shanghai",
    "iso:country":"CN",
    "name:und_x_variant":[
        "\u4e49\u4e30"
    ],
    "wof:name":"Yifeng",
    "wof:placetype":"locality"
},
  "geometry": {"coordinates":[114.93404,27.36601],"type":"Point"}
}