{
  "type": "Feature",
  "properties": {
    "gn:admin1_code":"1.0",
    "gn:asciiname":"Qigancun",
    "gn:country_code":"CN",
    "gn:dem":15,
    "gn:feature_class":"P",
    "gn:feature_code":"PPL",
    "gn:name":"Qigancun",
    "gn:population":0,
    "gn:timezone":"Asia/Shanghai",
    "iso:country":"CN",
    "name:zho_x_preferred":[
        "\u65d7\u6746\u6751"
    ],
    "wof:name":"Qigancun",
    "wof:placetype":"locality"
},
  "geometry": {"coordinates":[117.36360000000001,31.44233],"type":"Point"}
}