{
  "type": "Feature",
  "properties": {
    "gn:admin1_code":"15.0",
    "gn:asciiname":"Lugou",
    "gn:country_code":"CN",
    "gn:dem":1602,
    "gn:feature_class":"P",
    "gn:feature_code":"PPL",
    "gn:name":"Lugou",
    "gn:population":0,
    "gn:timezone":"Asia/Shanghai",
    "iso:country":"CN",
    "name:zho_x_preferred":[
        "\u5362\u6c9f"
    ],
    "wof:name":"Lugou",
    "wof:placetype":"locality"
},
  "geometry": {"coordinates":[105.512,34.8371],"type":"Point"}
}