{
  "type": "Feature",
  "properties": {
    "gn:admin1_code":"29",
    "gn:asciiname":"Yangshanzhuang",
    "gn:country_code":"CN",
    "gn:dem":1899,
    "gn:feature_class":"P",
    "gn:feature_code":"PPL",
    "gn:name":"Yangshanzhuang",
    "gn:population":0,
    "gn:timezone":"Asia/Shanghai",
    "iso:country":"CN",
    "name:zho_x_preferred":[
        "\u9633\u5c71\u5e84"
    ],
    "wof:name":"Yangshanzhuang",
    "wof:placetype":"locality"
},
  "geometry": {"coordinates":[102.596,24.2989],"type":"Point"}
}