{
  "type": "Feature",
  "properties": {
    "gn:admin1_code":"9.0",
    "gn:asciiname":"Xinyingli",
    "gn:country_code":"CN",
    "gn:dem":405,
    "gn:feature_class":"P",
    "gn:feature_code":"PPL",
    "gn:name":"Xinyingli",
    "gn:population":0,
    "gn:timezone":"Asia/Shanghai",
    "iso:country":"CN",
    "name:zho_x_preferred":[
        "\u65b0\u8425\u91cc"
    ],
    "wof:name":"Xinyingli",
    "wof:placetype":"locality"
},
  "geometry": {"coordinates":[110.6379,34.55560999999999],"type":"Point"}
}