{
  "type": "Feature",
  "properties": {
    "gn:admin1_code":"03",
    "gn:asciiname":"Lieqiao",
    "gn:country_code":"CN",
    "gn:dem":81,
    "gn:feature_class":"P",
    "gn:feature_code":"PPLA4",
    "gn:name":"Lieqiao",
    "gn:population":0,
    "gn:timezone":"Asia/Shanghai",
    "iso:country":"CN",
    "name:und_x_variant":[
        "Lieh-ch\u2019iao",
        "Lieqiao Xiang",
        "\u70c8\u6865\u4e61",
        "Lieqiao"
    ],
    "name:zho_x_preferred":[
        "\u70c8\u6865"
    ],
    "wof:name":"Lieqiao",
    "wof:placetype":"locality"
},
  "geometry": {"coordinates":[117.52231999999999,28.56377],"type":"Point"}
}