{
  "type": "Feature",
  "properties": {
    "gn:admin1_code":"08",
    "gn:asciiname":"Jiansanjiang Nongchang Guanliju",
    "gn:country_code":"CN",
    "gn:dem":62,
    "gn:feature_class":"P",
    "gn:feature_code":"PPLF",
    "gn:name":"Jiansanjiang Nongchang Guanliju",
    "gn:population":0,
    "gn:timezone":"Asia/Shanghai",
    "iso:country":"CN",
    "name:und_x_variant":[
        "Chiensanchiang",
        "Jiansanjiang",
        "Jiansanjiang Nongchang Guanliju"
    ],
    "wof:name":"Jiansanjiang Nongchang Guanliju",
    "wof:placetype":"locality"
},
  "geometry": {"coordinates":[132.62638999999999,47.25583],"type":"Point"}
}