{
  "type": "Feature",
  "properties": {
    "gn:admin1_code":"8.0",
    "gn:asciiname":"Xincun Shiyihao",
    "gn:country_code":"CN",
    "gn:dem":151,
    "gn:feature_class":"P",
    "gn:feature_code":"PPL",
    "gn:name":"Xincun Shiyihao",
    "gn:population":0,
    "gn:timezone":"Asia/Shanghai",
    "iso:country":"CN",
    "name:zho_x_preferred":[
        "\u65b0\u6751\u5341\u4e00\u53f7"
    ],
    "wof:name":"Xincun Shiyihao",
    "wof:placetype":"locality"
},
  "geometry": {"coordinates":[124.81753999999999,47.0024],"type":"Point"}
}