{
  "type": "Feature",
  "properties": {
    "gn:admin1_code":"29.0",
    "gn:asciiname":"Mibawangji",
    "gn:country_code":"CN",
    "gn:dem":1721,
    "gn:feature_class":"P",
    "gn:feature_code":"PPL",
    "gn:name":"Mibawangji",
    "gn:population":0,
    "gn:timezone":"Asia/Shanghai",
    "iso:country":"CN",
    "name:zho_x_preferred":[
        "\u7c73\u628a\u738b\u57fa"
    ],
    "wof:name":"Mibawangji",
    "wof:placetype":"locality"
},
  "geometry": {"coordinates":[98.8411,26.2337],"type":"Point"}
}