{
  "type": "Feature",
  "properties": {
    "gn:admin1_code":"1.0",
    "gn:asciiname":"Zhejiakeng",
    "gn:country_code":"CN",
    "gn:dem":382,
    "gn:feature_class":"P",
    "gn:feature_code":"PPL",
    "gn:name":"Zhejiakeng",
    "gn:population":0,
    "gn:timezone":"Asia/Shanghai",
    "iso:country":"CN",
    "name:zho_x_preferred":[
        "\u8005\u5bb6\u5751"
    ],
    "wof:name":"Zhejiakeng",
    "wof:placetype":"locality"
},
  "geometry": {"coordinates":[118.87796000000002,30.35796],"type":"Point"}
}