{
  "type": "Feature",
  "properties": {
    "gn:admin1_code":"13.0",
    "gn:asciiname":"Shaqiuhe",
    "gn:cc2":"CN",
    "gn:country_code":"CN",
    "gn:dem":532,
    "gn:feature_class":"P",
    "gn:feature_code":"PPL",
    "gn:name":"Shaqiuhe",
    "gn:population":0,
    "gn:timezone":"Asia/Urumqi",
    "iso:country":"CN",
    "name:und_x_variant":[
        "Sha-ch\u2019iu-ho",
        "Shaqiuhe"
    ],
    "wof:name":"Shaqiuhe",
    "wof:placetype":"locality"
},
  "geometry": {"coordinates":[88.88333,44.96667],"type":"Point"}
}