{
  "type": "Feature",
  "properties": {
    "gn:admin1_code":"5.0",
    "gn:asciiname":"Dongshengshuiquan",
    "gn:country_code":"CN",
    "gn:dem":186,
    "gn:feature_class":"P",
    "gn:feature_code":"PPL",
    "gn:name":"Dongshengshuiquan",
    "gn:population":0,
    "gn:timezone":"Asia/Shanghai",
    "iso:country":"CN",
    "name:zho_x_preferred":[
        "\u4e1c\u80dc\u6c34\u6cc9"
    ],
    "wof:name":"Dongshengshuiquan",
    "wof:placetype":"locality"
},
  "geometry": {"coordinates":[125.82098999999999,45.12013],"type":"Point"}
}