{
  "type": "Feature",
  "properties": {
    "gn:admin1_code":"07",
    "gn:asciiname":"Bancun",
    "gn:country_code":"CN",
    "gn:dem":672,
    "gn:feature_class":"P",
    "gn:feature_code":"PPL",
    "gn:name":"Bancun",
    "gn:population":0,
    "gn:timezone":"Asia/Shanghai",
    "iso:country":"CN",
    "name:und_x_variant":[
        "Shangbancun"
    ],
    "name:zho_x_preferred":[
        "\u4e0a\u534a\u6751"
    ],
    "name:zho_x_variant":[
        "\u534a\u6751"
    ],
    "wof:name":"Bancun",
    "wof:placetype":"locality"
},
  "geometry": {"coordinates":[117.09617,25.87854],"type":"Point"}
}