{
  "type": "Feature",
  "properties": {
    "gn:admin1_code":"14.0",
    "gn:asciiname":"Xiaxicun",
    "gn:country_code":"CN",
    "gn:dem":4466,
    "gn:feature_class":"P",
    "gn:feature_code":"PPL",
    "gn:name":"Xiaxicun",
    "gn:population":0,
    "gn:timezone":"Asia/Urumqi",
    "iso:country":"CN",
    "name:zho_x_preferred":[
        "\u4e0b\u897f\u6751"
    ],
    "wof:name":"Xiaxicun",
    "wof:placetype":"locality"
},
  "geometry": {"coordinates":[91.05665999999999,28.90905],"type":"Point"}
}