{
  "type": "Feature",
  "properties": {
    "gn:admin1_code":"1.0",
    "gn:asciiname":"Shang'ancun",
    "gn:country_code":"CN",
    "gn:dem":35,
    "gn:feature_class":"P",
    "gn:feature_code":"PPL",
    "gn:name":"Shang\u2019ancun",
    "gn:population":0,
    "gn:timezone":"Asia/Shanghai",
    "iso:country":"CN",
    "name:und_x_variant":[
        "Shang\u2019ancun"
    ],
    "name:zho_x_preferred":[
        "\u5c1a\u5eb5\u6751"
    ],
    "wof:name":"Shang'ancun",
    "wof:placetype":"locality"
},
  "geometry": {"coordinates":[116.87307,32.5648],"type":"Point"}
}