{
  "type": "Feature",
  "properties": {
    "gn:admin1_code":"8.0",
    "gn:asciiname":"Zhangzhentun",
    "gn:country_code":"CN",
    "gn:dem":221,
    "gn:feature_class":"P",
    "gn:feature_code":"PPL",
    "gn:name":"Zhangzhentun",
    "gn:population":0,
    "gn:timezone":"Asia/Shanghai",
    "iso:country":"CN",
    "name:zho_x_preferred":[
        "\u5f20\u632f\u5c6f"
    ],
    "wof:name":"Zhangzhentun",
    "wof:placetype":"locality"
},
  "geometry": {"coordinates":[127.30101999999999,45.30795],"type":"Point"}
}