{
  "type": "Feature",
  "properties": {
    "gn:admin1_code":"5.0",
    "gn:asciiname":"Fangniugoucun",
    "gn:country_code":"CN",
    "gn:dem":199,
    "gn:feature_class":"P",
    "gn:feature_code":"PPL",
    "gn:name":"Fangniugoucun",
    "gn:population":0,
    "gn:timezone":"Asia/Shanghai",
    "iso:country":"CN",
    "name:zho_x_preferred":[
        "\u653e\u725b\u6c9f\u6751"
    ],
    "wof:name":"Fangniugoucun",
    "wof:placetype":"locality"
},
  "geometry": {"coordinates":[125.03582,44.46394],"type":"Point"}
}