{
  "type": "Feature",
  "properties": {
    "gn:admin1_code":"21.0",
    "gn:asciiname":"Shigou",
    "gn:country_code":"CN",
    "gn:dem":1706,
    "gn:feature_class":"P",
    "gn:feature_code":"PPL",
    "gn:name":"Shigou",
    "gn:population":0,
    "gn:timezone":"Asia/Shanghai",
    "iso:country":"CN",
    "name:und_x_variant":[
        "\u77f3\u6c9f"
    ],
    "name:zho_x_preferred":[
        "\u77f3\u6c9f"
    ],
    "wof:name":"Shigou",
    "wof:placetype":"locality"
},
  "geometry": {"coordinates":[106.66437999999999,36.1601],"type":"Point"}
}