{
  "type": "Feature",
  "properties": {
    "gn:admin1_code":"30.0",
    "gn:asciiname":"Xiangtian",
    "gn:country_code":"CN",
    "gn:dem":69,
    "gn:feature_class":"P",
    "gn:feature_code":"PPL",
    "gn:name":"Xiangtian",
    "gn:population":0,
    "gn:timezone":"Asia/Shanghai",
    "iso:country":"CN",
    "name:zho_x_preferred":[
        "\u6e58\u7530"
    ],
    "wof:name":"Xiangtian",
    "wof:placetype":"locality"
},
  "geometry": {"coordinates":[112.04783999999999,23.95736],"type":"Point"}
}