{
  "type": "Feature",
  "properties": {
    "gn:admin1_code":"30.0",
    "gn:asciiname":"Lannijing",
    "gn:country_code":"CN",
    "gn:dem":328,
    "gn:feature_class":"P",
    "gn:feature_code":"PPL",
    "gn:name":"Lannijing",
    "gn:population":0,
    "gn:timezone":"Asia/Shanghai",
    "iso:country":"CN",
    "name:zho_x_preferred":[
        "Lannijing"
    ],
    "name:zho_x_variant":[
        "\u70c2\u576d\u5f84"
    ],
    "wof:name":"Lannijing",
    "wof:placetype":"locality"
},
  "geometry": {"coordinates":[114.55034000000001,24.41906],"type":"Point"}
}