{
  "type": "Feature",
  "properties": {
    "gn:admin1_code":"21.0",
    "gn:asciiname":"Shifengou",
    "gn:country_code":"CN",
    "gn:dem":1098,
    "gn:feature_class":"P",
    "gn:feature_code":"PPL",
    "gn:name":"Shifengou",
    "gn:population":0,
    "gn:timezone":"Asia/Shanghai",
    "iso:country":"CN",
    "name:zho_x_preferred":[
        "\u5341\u5206\u6c9f"
    ],
    "wof:name":"Shifengou",
    "wof:placetype":"locality"
},
  "geometry": {"coordinates":[106.40900000000001,38.9553],"type":"Point"}
}