{
  "type": "Feature",
  "properties": {
    "gn:admin1_code":"29.0",
    "gn:asciiname":"Mangdongshan",
    "gn:country_code":"CN",
    "gn:dem":1696,
    "gn:feature_class":"P",
    "gn:feature_code":"PPL",
    "gn:name":"Mangdongshan",
    "gn:population":0,
    "gn:timezone":"Asia/Shanghai",
    "iso:country":"CN",
    "name:zho_x_preferred":[
        "\u8292\u4e1c\u5c71"
    ],
    "wof:name":"Mangdongshan",
    "wof:placetype":"locality"
},
  "geometry": {"coordinates":[98.3385,24.1844],"type":"Point"}
}