{
  "type": "Feature",
  "properties": {
    "gn:admin1_code":"1.0",
    "gn:asciiname":"Huaifei",
    "gn:country_code":"CN",
    "gn:dem":30,
    "gn:feature_class":"P",
    "gn:feature_code":"PPL",
    "gn:name":"Huaifei",
    "gn:population":0,
    "gn:timezone":"Asia/Shanghai",
    "iso:country":"CN",
    "name:zho_x_preferred":[
        "\u6dee\u80a5"
    ],
    "wof:name":"Huaifei",
    "wof:placetype":"locality"
},
  "geometry": {"coordinates":[117.33032,31.9245],"type":"Point"}
}