{
  "type": "Feature",
  "properties": {
    "gn:admin1_code":"11",
    "gn:asciiname":"Sijiaomenlou",
    "gn:country_code":"CN",
    "gn:dem":207,
    "gn:feature_class":"P",
    "gn:feature_code":"PPL",
    "gn:name":"Sijiaomenlou",
    "gn:population":0,
    "gn:timezone":"Asia/Shanghai",
    "iso:country":"CN",
    "name:zho_x_preferred":[
        "\u56db\u811a\u95e8\u697c"
    ],
    "wof:name":"Sijiaomenlou",
    "wof:placetype":"locality"
},
  "geometry": {"coordinates":[111.43803,25.33116],"type":"Point"}
}