{
  "type": "Feature",
  "properties": {
    "gn:admin1_code":"16",
    "gn:asciiname":"Chengzhong",
    "gn:country_code":"CN",
    "gn:dem":335,
    "gn:feature_class":"P",
    "gn:feature_code":"PPLA3",
    "gn:name":"Chengzhong",
    "gn:population":0,
    "gn:timezone":"Asia/Shanghai",
    "iso:country":"CN",
    "name:ceb_x_preferred":[
        "Chengzhong"
    ],
    "name:deu_x_preferred":[
        "Chengzhong"
    ],
    "name:eus_x_preferred":[
        "Chengzhong"
    ],
    "name:fra_x_preferred":[
        "Chengzhong"
    ],
    "name:jpn_x_preferred":[
        "\u57ce\u4e2d\u533a"
    ],
    "name:kor_x_preferred":[
        "\uccad\uc911\uad6c"
    ],
    "name:mlg_x_preferred":[
        "Chengzhong"
    ],
    "name:swe_x_preferred":[
        "Chengzhong"
    ],
    "name:und_x_variant":[
        "Ning-ming-hsien",
        "Ningming"
    ],
    "name:zho_x_preferred":[
        "\u57ce\u4e2d"
    ],
    "name:zho_x_variant":[
        "\u57ce\u4e2d\u533a"
    ],
    "wof:name":"Chengzhong",
    "wof:placetype":"locality"
},
  "geometry": {"coordinates":[107.0073,22.16824],"type":"Point"}
}