{
  "type": "Feature",
  "properties": {
    "gn:admin1_code":"18",
    "gn:asciiname":"Shuiniudong",
    "gn:country_code":"CN",
    "gn:dem":988,
    "gn:feature_class":"P",
    "gn:feature_code":"PPL",
    "gn:name":"Shuiniudong",
    "gn:population":0,
    "gn:timezone":"Asia/Shanghai",
    "iso:country":"CN",
    "name:zho_x_preferred":[
        "\u6c34\u725b\u6d1e"
    ],
    "wof:name":"Shuiniudong",
    "wof:placetype":"locality"
},
  "geometry": {"coordinates":[106.69,27.1285],"type":"Point"}
}