{
  "type": "Feature",
  "properties": {
    "gn:admin1_code":"1.0",
    "gn:asciiname":"Shaoqiaocun",
    "gn:country_code":"CN",
    "gn:dem":32,
    "gn:feature_class":"P",
    "gn:feature_code":"PPL",
    "gn:name":"Shaoqiaocun",
    "gn:population":0,
    "gn:timezone":"Asia/Shanghai",
    "iso:country":"CN",
    "name:zho_x_preferred":[
        "\u90b5\u6865\u6751"
    ],
    "wof:name":"Shaoqiaocun",
    "wof:placetype":"locality"
},
  "geometry": {"coordinates":[116.31332999999999,33.49843],"type":"Point"}
}