{
  "type": "Feature",
  "properties": {
    "gn:admin1_code":"3.0",
    "gn:asciiname":"Baigaobei",
    "gn:country_code":"CN",
    "gn:dem":145,
    "gn:feature_class":"P",
    "gn:feature_code":"PPL",
    "gn:name":"Baigaobei",
    "gn:population":0,
    "gn:timezone":"Asia/Shanghai",
    "iso:country":"CN",
    "name:und_x_variant":[
        "\u767d\u9ad8\u9642"
    ],
    "wof:name":"Baigaobei",
    "wof:placetype":"locality"
},
  "geometry": {"coordinates":[115.43635,26.0242],"type":"Point"}
}