{
  "type": "Feature",
  "properties": {
    "gn:admin1_code":"11.0",
    "gn:asciiname":"Qiyanshan",
    "gn:country_code":"CN",
    "gn:dem":980,
    "gn:feature_class":"P",
    "gn:feature_code":"PPL",
    "gn:name":"Qiyanshan",
    "gn:population":0,
    "gn:timezone":"Asia/Shanghai",
    "iso:country":"CN",
    "name:zho_x_preferred":[
        "\u6c7d\u5ca9\u5c71"
    ],
    "wof:name":"Qiyanshan",
    "wof:placetype":"locality"
},
  "geometry": {"coordinates":[111.23071000000002,28.17202],"type":"Point"}
}