{
  "type": "Feature",
  "properties": {
    "gn:admin1_code":"29.0",
    "gn:asciiname":"Shisuo",
    "gn:country_code":"CN",
    "gn:dem":1939,
    "gn:feature_class":"P",
    "gn:feature_code":"PPL",
    "gn:name":"Shisuo",
    "gn:population":0,
    "gn:timezone":"Asia/Shanghai",
    "iso:country":"CN",
    "name:zho_x_preferred":[
        "\u77f3\u7d22"
    ],
    "wof:name":"Shisuo",
    "wof:placetype":"locality"
},
  "geometry": {"coordinates":[98.8747,25.9517],"type":"Point"}
}