{
  "type": "Feature",
  "properties": {
    "gn:admin1_code":"14.0",
    "gn:asciiname":"Kailahor",
    "gn:country_code":"CN",
    "gn:dem":3934,
    "gn:feature_class":"P",
    "gn:feature_code":"PPLF",
    "gn:name":"Kailahor",
    "gn:population":0,
    "gn:timezone":"Asia/Urumqi",
    "iso:country":"CN",
    "name:bod_x_preferred":[
        "Kailahor"
    ],
    "name:bod_x_variant":[
        "\u0f42\u0f51\u0f0b\u0f63\u0f0b\u0f67\u0f7c\u0f62"
    ],
    "name:zho_x_preferred":[
        "Gelawo"
    ],
    "name:zho_x_variant":[
        "\u683c\u62c9\u6c83",
        "\u683c\u8001\u7a9d",
        "\u683c\u8356\u7a9d",
        "Gelaowo",
        "\u6539\u62c9\u970d",
        "Gailahuo"
    ],
    "wof:name":"Kailahor",
    "wof:placetype":"locality"
},
  "geometry": {"coordinates":[91.75841,30.07998],"type":"Point"}
}