{
  "type": "Feature",
  "properties": {
    "gn:admin1_code":"19.0",
    "gn:asciiname":"Zengjia Weizi",
    "gn:country_code":"CN",
    "gn:dem":191,
    "gn:feature_class":"P",
    "gn:feature_code":"PPL",
    "gn:name":"Zengjia Weizi",
    "gn:population":0,
    "gn:timezone":"Asia/Shanghai",
    "iso:country":"CN",
    "name:zho_x_preferred":[
        "\u66fe\u5bb6\u9688\u5b50"
    ],
    "wof:name":"Zengjia Weizi",
    "wof:placetype":"locality"
},
  "geometry": {"coordinates":[124.2381,40.76008],"type":"Point"}
}