{
  "type": "Feature",
  "properties": {
    "gn:admin1_code":"26.0",
    "gn:asciiname":"Meijiazhuang",
    "gn:country_code":"CN",
    "gn:dem":393,
    "gn:feature_class":"P",
    "gn:feature_code":"PPL",
    "gn:name":"Meijiazhuang",
    "gn:population":0,
    "gn:timezone":"Asia/Shanghai",
    "iso:country":"CN",
    "name:zho_x_preferred":[
        "\u6885\u5bb6\u5e84"
    ],
    "wof:name":"Meijiazhuang",
    "wof:placetype":"locality"
},
  "geometry": {"coordinates":[108.67874,34.23488],"type":"Point"}
}