{
  "type": "Feature",
  "properties": {
    "gn:admin1_code":"25",
    "gn:asciiname":"Haifeng Weizi",
    "gn:country_code":"CN",
    "gn:dem":4,
    "gn:feature_class":"P",
    "gn:feature_code":"PPL",
    "gn:name":"Haifeng Weizi",
    "gn:population":0,
    "gn:timezone":"Asia/Shanghai",
    "iso:country":"CN",
    "name:zho_x_preferred":[
        "\u6d77\u4e30\u56f4\u5b50"
    ],
    "wof:name":"Haifeng Weizi",
    "wof:placetype":"locality"
},
  "geometry": {"coordinates":[118.307,38.0099],"type":"Point"}
}