{
  "type": "Feature",
  "properties": {
    "gn:admin1_code":"02",
    "gn:asciiname":"Gumiao",
    "gn:cc2":"CN",
    "gn:country_code":"CN",
    "gn:dem":48,
    "gn:feature_class":"P",
    "gn:feature_code":"PPL",
    "gn:name":"Gumiao",
    "gn:population":0,
    "gn:timezone":"Asia/Shanghai",
    "iso:country":"CN",
    "name:und_x_variant":[
        "Ku-miao",
        "Yang-lu-yang",
        "Shangluyang"
    ],
    "wof:name":"Gumiao",
    "wof:placetype":"locality"
},
  "geometry": {"coordinates":[120.80694,28.23667],"type":"Point"}
}