{
  "type": "Feature",
  "properties": {
    "gn:admin1_code":"26.0",
    "gn:asciiname":"Kejiayuan",
    "gn:country_code":"CN",
    "gn:dem":629,
    "gn:feature_class":"P",
    "gn:feature_code":"PPL",
    "gn:name":"Kejiayuan",
    "gn:population":0,
    "gn:timezone":"Asia/Shanghai",
    "iso:country":"CN",
    "name:zho_x_preferred":[
        "\u67ef\u5bb6\u9662"
    ],
    "wof:name":"Kejiayuan",
    "wof:placetype":"locality"
},
  "geometry": {"coordinates":[109.35417,32.59245],"type":"Point"}
}