{
  "type": "Feature",
  "properties": {
    "gn:admin1_code":"2.0",
    "gn:asciiname":"Yuelinghou",
    "gn:country_code":"CN",
    "gn:dem":619,
    "gn:feature_class":"P",
    "gn:feature_code":"PPL",
    "gn:name":"Yuelinghou",
    "gn:population":0,
    "gn:timezone":"Asia/Shanghai",
    "iso:country":"CN",
    "name:zho_x_preferred":[
        "\u5cb3\u5cad\u540e"
    ],
    "wof:name":"Yuelinghou",
    "wof:placetype":"locality"
},
  "geometry": {"coordinates":[119.93455,27.93166],"type":"Point"}
}