{
  "type": "Feature",
  "properties": {
    "gn:admin1_code":"1.0",
    "gn:asciiname":"Huanghuacun",
    "gn:country_code":"CN",
    "gn:dem":12,
    "gn:feature_class":"P",
    "gn:feature_code":"PPL",
    "gn:name":"Huanghuacun",
    "gn:population":0,
    "gn:timezone":"Asia/Shanghai",
    "iso:country":"CN",
    "name:zho_x_preferred":[
        "\u9ec4\u82b1\u6751"
    ],
    "wof:name":"Huanghuacun",
    "wof:placetype":"locality"
},
  "geometry": {"coordinates":[117.1003,30.59812],"type":"Point"}
}