{
  "type": "Feature",
  "properties": {
    "gn:admin1_code":"15.0",
    "gn:asciiname":"Laomiaotai",
    "gn:country_code":"CN",
    "gn:dem":1442,
    "gn:feature_class":"P",
    "gn:feature_code":"PPL",
    "gn:name":"Laomiaotai",
    "gn:population":0,
    "gn:timezone":"Asia/Shanghai",
    "iso:country":"CN",
    "name:und_x_variant":[
        "\u8001\u5e99\u53f0"
    ],
    "wof:name":"Laomiaotai",
    "wof:placetype":"locality"
},
  "geometry": {"coordinates":[107.10897,36.86232],"type":"Point"}
}