{
  "type": "Feature",
  "properties": {
    "gn:admin1_code":"4.0",
    "gn:asciiname":"Yinxiaoqiao",
    "gn:country_code":"CN",
    "gn:dem":5,
    "gn:feature_class":"P",
    "gn:feature_code":"PPL",
    "gn:name":"Yinxiaoqiao",
    "gn:population":0,
    "gn:timezone":"Asia/Shanghai",
    "iso:country":"CN",
    "name:zho_x_preferred":[
        "Yinxiaoqiao"
    ],
    "name:zho_x_variant":[
        "\u6bb7\u5c0f\u6865"
    ],
    "wof:name":"Yinxiaoqiao",
    "wof:placetype":"locality"
},
  "geometry": {"coordinates":[119.50053,33.06533],"type":"Point"}
}