{
  "type": "Feature",
  "properties": {
    "gn:admin1_code":"3.0",
    "gn:asciiname":"Caoling",
    "gn:country_code":"CN",
    "gn:dem":332,
    "gn:feature_class":"P",
    "gn:feature_code":"PPL",
    "gn:name":"Caoling",
    "gn:population":0,
    "gn:timezone":"Asia/Shanghai",
    "iso:country":"CN",
    "name:ceb_x_preferred":[
        "Caoling"
    ],
    "name:und_x_variant":[
        "\u69fd\u5cad"
    ],
    "wof:name":"Caoling",
    "wof:placetype":"locality"
},
  "geometry": {"coordinates":[114.11747,28.20622],"type":"Point"}
}