{
  "type": "Feature",
  "properties": {
    "gn:admin1_code":"12.0",
    "gn:asciiname":"Songshugang",
    "gn:country_code":"CN",
    "gn:dem":52,
    "gn:feature_class":"P",
    "gn:feature_code":"PPL",
    "gn:name":"Songshugang",
    "gn:population":0,
    "gn:timezone":"Asia/Shanghai",
    "iso:country":"CN",
    "name:zho_x_preferred":[
        "Songshugang"
    ],
    "name:zho_x_variant":[
        "\u677e\u6811\u5c97"
    ],
    "wof:name":"Songshugang",
    "wof:placetype":"locality"
},
  "geometry": {"coordinates":[111.45703,30.42545],"type":"Point"}
}