{
  "type": "Feature",
  "properties": {
    "gn:admin1_code":"5.0",
    "gn:asciiname":"Laifucun",
    "gn:country_code":"CN",
    "gn:dem":134,
    "gn:feature_class":"P",
    "gn:feature_code":"PPL",
    "gn:name":"Laifucun",
    "gn:population":0,
    "gn:timezone":"Asia/Shanghai",
    "iso:country":"CN",
    "name:zho_x_preferred":[
        "\u6765\u5bcc\u6751"
    ],
    "wof:name":"Laifucun",
    "wof:placetype":"locality"
},
  "geometry": {"coordinates":[123.93863,45.53619000000001],"type":"Point"}
}