{
  "type": "Feature",
  "properties": {
    "gn:admin1_code":"10.0",
    "gn:asciiname":"Dazhujia",
    "gn:country_code":"CN",
    "gn:dem":35,
    "gn:feature_class":"P",
    "gn:feature_code":"PPL",
    "gn:name":"Dazhujia",
    "gn:population":0,
    "gn:timezone":"Asia/Shanghai",
    "iso:country":"CN",
    "name:zho_x_preferred":[
        "\u5927\u4f4f\u9a7e"
    ],
    "wof:name":"Dazhujia",
    "wof:placetype":"locality"
},
  "geometry": {"coordinates":[115.94325000000001,39.51416],"type":"Point"}
}