{
  "type": "Feature",
  "properties": {
    "gn:admin1_code":"19.0",
    "gn:asciiname":"Jiapigou",
    "gn:country_code":"CN",
    "gn:dem":463,
    "gn:feature_class":"P",
    "gn:feature_code":"PPL",
    "gn:name":"Jiapigou",
    "gn:population":0,
    "gn:timezone":"Asia/Shanghai",
    "iso:country":"CN",
    "name:zho_x_preferred":[
        "\u5939\u76ae\u6c9f"
    ],
    "wof:name":"Jiapigou",
    "wof:placetype":"locality"
},
  "geometry": {"coordinates":[123.696,41.0773],"type":"Point"}
}