{
  "type": "Feature",
  "properties": {
    "gn:admin1_code":"15.0",
    "gn:asciiname":"Ouqiang",
    "gn:country_code":"CN",
    "gn:dem":3425,
    "gn:feature_class":"P",
    "gn:feature_code":"PPL",
    "gn:name":"Ouqiang",
    "gn:population":0,
    "gn:timezone":"Asia/Shanghai",
    "iso:country":"CN",
    "name:zho_x_preferred":[
        "\u6b27\u5f3a"
    ],
    "wof:name":"Ouqiang",
    "wof:placetype":"locality"
},
  "geometry": {"coordinates":[101.94283,33.99413],"type":"Point"}
}