{
  "type": "Feature",
  "properties": {
    "gn:admin1_code":"15.0",
    "gn:asciiname":"Qingshan",
    "gn:country_code":"CN",
    "gn:dem":2466,
    "gn:feature_class":"P",
    "gn:feature_code":"PPL",
    "gn:name":"Qingshan",
    "gn:population":0,
    "gn:timezone":"Asia/Shanghai",
    "iso:country":"CN",
    "name:ceb_x_preferred":[
        "Qingshan"
    ],
    "name:deu_x_preferred":[
        "Qingshan"
    ],
    "name:fra_x_preferred":[
        "Qingshan"
    ],
    "name:nor_x_preferred":[
        "Qingshan"
    ],
    "name:rus_x_preferred":[
        "\u0426\u0438\u043d\u0448\u0430\u043d\u044c"
    ],
    "name:swe_x_preferred":[
        "Qingshan"
    ],
    "name:zho_x_preferred":[
        "\u9752\u5c71"
    ],
    "wof:name":"Qingshan",
    "wof:placetype":"locality"
},
  "geometry": {"coordinates":[103.601,35.946],"type":"Point"}
}