{
  "type": "Feature",
  "properties": {
    "gn:admin1_code":"16.0",
    "gn:asciiname":"Gumu",
    "gn:country_code":"CN",
    "gn:dem":893,
    "gn:feature_class":"P",
    "gn:feature_code":"PPL",
    "gn:name":"Gumu",
    "gn:population":0,
    "gn:timezone":"Asia/Shanghai",
    "iso:country":"CN",
    "name:zho_x_preferred":[
        "\u53e4\u6728"
    ],
    "wof:name":"Gumu",
    "wof:placetype":"locality"
},
  "geometry": {"coordinates":[105.501,24.2823],"type":"Point"}
}