{
  "type": "Feature",
  "properties": {
    "gn:admin1_code":"8.0",
    "gn:asciiname":"Baodiancun",
    "gn:country_code":"CN",
    "gn:dem":338,
    "gn:feature_class":"P",
    "gn:feature_code":"PPL",
    "gn:name":"Baodiancun",
    "gn:population":0,
    "gn:timezone":"Asia/Shanghai",
    "iso:country":"CN",
    "name:zho_x_preferred":[
        "\u5305\u7538\u6751"
    ],
    "wof:name":"Baodiancun",
    "wof:placetype":"locality"
},
  "geometry": {"coordinates":[130.10287,44.99027],"type":"Point"}
}