{
  "type": "Feature",
  "properties": {
    "gn:admin1_code":"9.0",
    "gn:asciiname":"Beimazhuang",
    "gn:country_code":"CN",
    "gn:dem":219,
    "gn:feature_class":"P",
    "gn:feature_code":"PPL",
    "gn:name":"Beimazhuang",
    "gn:population":0,
    "gn:timezone":"Asia/Shanghai",
    "iso:country":"CN",
    "name:und_x_variant":[
        "\u5317\u9a6c\u5e84",
        "Beimazhuang"
    ],
    "wof:name":"Beimazhuang",
    "wof:placetype":"locality"
},
  "geometry": {"coordinates":[112.36108,33.4697],"type":"Point"}
}