{
  "type": "Feature",
  "properties": {
    "gn:admin1_code":"7.0",
    "gn:asciiname":"Panshi",
    "gn:country_code":"CN",
    "gn:dem":13,
    "gn:feature_class":"P",
    "gn:feature_code":"PPL",
    "gn:name":"Panshi",
    "gn:population":0,
    "gn:timezone":"Asia/Shanghai",
    "iso:country":"CN",
    "name:zho_x_preferred":[
        "Panshi"
    ],
    "name:zho_x_variant":[
        "\u78d0\u77f3"
    ],
    "wof:name":"Panshi",
    "wof:placetype":"locality"
},
  "geometry": {"coordinates":[119.30656,26.13167],"type":"Point"}
}