{
  "type": "Feature",
  "properties": {
    "gn:admin1_code":"3.0",
    "gn:asciiname":"Hualing",
    "gn:country_code":"CN",
    "gn:dem":37,
    "gn:feature_class":"P",
    "gn:feature_code":"PPL",
    "gn:name":"Hualing",
    "gn:population":0,
    "gn:timezone":"Asia/Shanghai",
    "iso:country":"CN",
    "name:und_x_variant":[
        "\u534e\u5cad"
    ],
    "wof:name":"Hualing",
    "wof:placetype":"locality"
},
  "geometry": {"coordinates":[116.78456,29.10594],"type":"Point"}
}