{
  "type": "Feature",
  "properties": {
    "gn:admin1_code":"14.0",
    "gn:asciiname":"Duode",
    "gn:country_code":"CN",
    "gn:dem":4804,
    "gn:feature_class":"P",
    "gn:feature_code":"PPL",
    "gn:name":"Duode",
    "gn:population":0,
    "gn:timezone":"Asia/Urumqi",
    "iso:country":"CN",
    "name:bod_x_preferred":[
        "Dod\u00ea"
    ],
    "name:zho_x_preferred":[
        "Duode"
    ],
    "name:zho_x_variant":[
        "\u591a\u5fb7",
        "Bazha Qu",
        "\u5df4\u624e\u533a"
    ],
    "wof:name":"Duode",
    "wof:placetype":"locality"
},
  "geometry": {"coordinates":[88.70100000000002,30.501],"type":"Point"}
}