{
  "type": "Feature",
  "properties": {
    "gn:admin1_code":"8.0",
    "gn:asciiname":"Ma'anshancun",
    "gn:country_code":"CN",
    "gn:dem":121,
    "gn:feature_class":"P",
    "gn:feature_code":"PPL",
    "gn:name":"Ma\u2019anshancun",
    "gn:population":0,
    "gn:timezone":"Asia/Shanghai",
    "iso:country":"CN",
    "name:und_x_variant":[
        "Ma\u2019anshancun"
    ],
    "name:zho_x_preferred":[
        "\u9a6c\u978d\u5c71\u6751"
    ],
    "wof:name":"Ma'anshancun",
    "wof:placetype":"locality"
},
  "geometry": {"coordinates":[129.62492,46.35335],"type":"Point"}
}