{
  "type": "Feature",
  "properties": {
    "gn:admin1_code":"30.0",
    "gn:asciiname":"Dongfen",
    "gn:country_code":"CN",
    "gn:dem":90,
    "gn:feature_class":"P",
    "gn:feature_code":"PPL",
    "gn:name":"Dongfen",
    "gn:population":0,
    "gn:timezone":"Asia/Shanghai",
    "iso:country":"CN",
    "name:zho_x_preferred":[
        "Dongfen"
    ],
    "name:zho_x_variant":[
        "\u4e1c\u7c89"
    ],
    "wof:name":"Dongfen",
    "wof:placetype":"locality"
},
  "geometry": {"coordinates":[113.36896000000002,24.76797],"type":"Point"}
}