{
  "type": "Feature",
  "properties": {
    "gn:admin1_code":"31.0",
    "gn:asciiname":"Penglai",
    "gn:country_code":"CN",
    "gn:dem":8,
    "gn:feature_class":"P",
    "gn:feature_code":"PPL",
    "gn:name":"Penglai",
    "gn:population":0,
    "gn:timezone":"Asia/Shanghai",
    "iso:country":"CN",
    "name:ceb_x_preferred":[
        "Penglai"
    ],
    "name:deu_x_preferred":[
        "Penglai"
    ],
    "name:fra_x_preferred":[
        "Penglai"
    ],
    "name:jpn_x_preferred":[
        "\u84ec\u83b1"
    ],
    "name:nor_x_preferred":[
        "Penglai"
    ],
    "name:pol_x_preferred":[
        "Penglai"
    ],
    "name:zho_x_preferred":[
        "\u84ec\u83b1"
    ],
    "wof:name":"Penglai",
    "wof:placetype":"locality"
},
  "geometry": {"coordinates":[110.4637,19.19442],"type":"Point"}
}