{
  "type": "Feature",
  "properties": {
    "gn:admin1_code":"6.0",
    "gn:asciiname":"Shaningda",
    "gn:country_code":"CN",
    "gn:dem":4113,
    "gn:feature_class":"P",
    "gn:feature_code":"PPL",
    "gn:name":"Shaningda",
    "gn:population":0,
    "gn:timezone":"Asia/Urumqi",
    "iso:country":"CN",
    "name:zho_x_preferred":[
        "\u6c99\u5b81\u8fbe"
    ],
    "wof:name":"Shaningda",
    "wof:placetype":"locality"
},
  "geometry": {"coordinates":[96.5556,32.80412],"type":"Point"}
}