{
  "type": "Feature",
  "properties": {
    "gn:admin1_code":"7.0",
    "gn:asciiname":"Qiaoyang",
    "gn:country_code":"CN",
    "gn:dem":331,
    "gn:feature_class":"P",
    "gn:feature_code":"PPL",
    "gn:name":"Qiaoyang",
    "gn:population":0,
    "gn:timezone":"Asia/Shanghai",
    "iso:country":"CN",
    "name:zho_x_preferred":[
        "\u5de7\u6d0b"
    ],
    "wof:name":"Qiaoyang",
    "wof:placetype":"locality"
},
  "geometry": {"coordinates":[116.75263,26.90205],"type":"Point"}
}