{
  "type": "Feature",
  "properties": {
    "gn:admin1_code":"11.0",
    "gn:asciiname":"Jiutangchong",
    "gn:country_code":"CN",
    "gn:dem":185,
    "gn:feature_class":"P",
    "gn:feature_code":"PPL",
    "gn:name":"Jiutangchong",
    "gn:population":0,
    "gn:timezone":"Asia/Shanghai",
    "iso:country":"CN",
    "name:zho_x_preferred":[
        "\u4e5d\u5858\u51b2"
    ],
    "wof:name":"Jiutangchong",
    "wof:placetype":"locality"
},
  "geometry": {"coordinates":[113.28058,26.40631],"type":"Point"}
}