{
  "type": "Feature",
  "properties": {
    "gn:admin1_code":"29",
    "gn:asciiname":"Erdaoyan",
    "gn:country_code":"CN",
    "gn:dem":1345,
    "gn:feature_class":"P",
    "gn:feature_code":"PPL",
    "gn:name":"Erdaoyan",
    "gn:population":0,
    "gn:timezone":"Asia/Shanghai",
    "iso:country":"CN",
    "name:zho_x_preferred":[
        "\u4e8c\u9053\u5ca9"
    ],
    "wof:name":"Erdaoyan",
    "wof:placetype":"locality"
},
  "geometry": {"coordinates":[103.07899999999999,24.4116],"type":"Point"}
}