{
  "type": "Feature",
  "properties": {
    "gn:admin1_code":"30",
    "gn:asciiname":"Dalangtou",
    "gn:country_code":"CN",
    "gn:dem":466,
    "gn:feature_class":"P",
    "gn:feature_code":"PPL",
    "gn:name":"Dalangtou",
    "gn:population":0,
    "gn:timezone":"Asia/Shanghai",
    "iso:country":"CN",
    "name:zho_x_preferred":[
        "\u5927\u5d00\u5934"
    ],
    "wof:name":"Dalangtou",
    "wof:placetype":"locality"
},
  "geometry": {"coordinates":[112.27861,23.4575],"type":"Point"}
}