{
  "type": "Feature",
  "properties": {
    "gn:admin1_code":"9.0",
    "gn:asciiname":"Donghuayuan",
    "gn:country_code":"CN",
    "gn:dem":687,
    "gn:feature_class":"P",
    "gn:feature_code":"PPL",
    "gn:name":"Donghuayuan",
    "gn:population":0,
    "gn:timezone":"Asia/Shanghai",
    "iso:country":"CN",
    "name:und_x_variant":[
        "\u4e1c\u82b1\u56ed",
        "Donghuayuan"
    ],
    "wof:name":"Donghuayuan",
    "wof:placetype":"locality"
},
  "geometry": {"coordinates":[112.18015,33.66602],"type":"Point"}
}