{
  "type": "Feature",
  "properties": {
    "gn:admin1_code":"33.0",
    "gn:asciiname":"Longjing",
    "gn:country_code":"CN",
    "gn:dem":248,
    "gn:feature_class":"P",
    "gn:feature_code":"PPL",
    "gn:name":"Longjing",
    "gn:population":0,
    "gn:timezone":"Asia/Shanghai",
    "iso:country":"CN",
    "name:ceb_x_preferred":[
        "Longjing"
    ],
    "name:deu_x_preferred":[
        "Longjing"
    ],
    "name:mlg_x_preferred":[
        "Longjing"
    ],
    "name:nld_x_preferred":[
        "Longjing"
    ],
    "name:nor_x_preferred":[
        "Longjing"
    ],
    "name:pol_x_preferred":[
        "Longjing"
    ],
    "name:zho_x_preferred":[
        "\u9f99\u4e95"
    ],
    "wof:name":"Longjing",
    "wof:placetype":"locality"
},
  "geometry": {"coordinates":[106.42804,29.2375],"type":"Point"}
}