{
  "type": "Feature",
  "properties": {
    "gn:admin1_code":"19.0",
    "gn:asciiname":"Deshengtai",
    "gn:country_code":"CN",
    "gn:dem":53,
    "gn:feature_class":"P",
    "gn:feature_code":"PPL",
    "gn:name":"Deshengtai",
    "gn:population":0,
    "gn:timezone":"Asia/Shanghai",
    "iso:country":"CN",
    "name:und_x_variant":[
        "\u5f97\u80dc\u53f0"
    ],
    "name:zho_x_preferred":[
        "\u5f97\u80dc\u53f0"
    ],
    "wof:name":"Deshengtai",
    "wof:placetype":"locality"
},
  "geometry": {"coordinates":[123.44754,42.04414000000001],"type":"Point"}
}