{
  "type": "Feature",
  "properties": {
    "gn:admin1_code":"9.0",
    "gn:asciiname":"Diangou",
    "gn:country_code":"CN",
    "gn:dem":514,
    "gn:feature_class":"P",
    "gn:feature_code":"PPL",
    "gn:name":"Diangou",
    "gn:population":0,
    "gn:timezone":"Asia/Shanghai",
    "iso:country":"CN",
    "name:zho_x_preferred":[
        "\u5e97\u6c9f"
    ],
    "wof:name":"Diangou",
    "wof:placetype":"locality"
},
  "geometry": {"coordinates":[111.93933,34.8003],"type":"Point"}
}