{
  "type": "Feature",
  "properties": {
    "gn:admin1_code":"13.0",
    "gn:asciiname":"Nuoneng A'yige",
    "gn:country_code":"CN",
    "gn:dem":1251,
    "gn:feature_class":"P",
    "gn:feature_code":"PPL",
    "gn:name":"Nuoneng A\u2019yige",
    "gn:population":0,
    "gn:timezone":"Asia/Shanghai",
    "iso:country":"CN",
    "name:und_x_variant":[
        "Nuoneng A\u2019yige",
        "\u8bfa\u80fd\u963f\u4f9d\u683c"
    ],
    "wof:name":"Nuoneng A'yige",
    "wof:placetype":"locality"
},
  "geometry": {"coordinates":[76.37626,38.92059],"type":"Point"}
}