{
  "type": "Feature",
  "properties": {
    "gn:admin1_code":"30.0",
    "gn:asciiname":"Pantiancun",
    "gn:country_code":"CN",
    "gn:dem":81,
    "gn:feature_class":"P",
    "gn:feature_code":"PPL",
    "gn:name":"Pantiancun",
    "gn:population":0,
    "gn:timezone":"Asia/Shanghai",
    "iso:country":"CN",
    "name:zho_x_preferred":[
        "\u6f58\u7530\u6751"
    ],
    "wof:name":"Pantiancun",
    "wof:placetype":"locality"
},
  "geometry": {"coordinates":[116.13818000000001,24.53412],"type":"Point"}
}