{
  "type": "Feature",
  "properties": {
    "gn:admin1_code":"29.0",
    "gn:asciiname":"Haijishi",
    "gn:country_code":"CN",
    "gn:dem":1709,
    "gn:feature_class":"P",
    "gn:feature_code":"PPL",
    "gn:name":"Haijishi",
    "gn:population":0,
    "gn:timezone":"Asia/Shanghai",
    "iso:country":"CN",
    "name:zho_x_preferred":[
        "\u5bb3\u57fa\u53f2"
    ],
    "wof:name":"Haijishi",
    "wof:placetype":"locality"
},
  "geometry": {"coordinates":[98.8972,26.23],"type":"Point"}
}