{
  "type": "Feature",
  "properties": {
    "gn:admin1_code":"14.0",
    "gn:asciiname":"Leshagong",
    "gn:country_code":"CN",
    "gn:dem":4644,
    "gn:feature_class":"P",
    "gn:feature_code":"PPL",
    "gn:name":"Leshagong",
    "gn:population":0,
    "gn:timezone":"Asia/Urumqi",
    "iso:country":"CN",
    "name:zho_x_preferred":[
        "\u52d2\u6c99\u8d21"
    ],
    "wof:name":"Leshagong",
    "wof:placetype":"locality"
},
  "geometry": {"coordinates":[90.45299,28.29593],"type":"Point"}
}