{
  "type": "Feature",
  "properties": {
    "gn:admin1_code":"14.0",
    "gn:asciiname":"Meilongnangcun",
    "gn:country_code":"CN",
    "gn:dem":4522,
    "gn:feature_class":"P",
    "gn:feature_code":"PPL",
    "gn:name":"Meilongnangcun",
    "gn:population":0,
    "gn:timezone":"Asia/Urumqi",
    "iso:country":"CN",
    "name:zho_x_preferred":[
        "\u7f8e\u9f99\u56ca\u6751"
    ],
    "wof:name":"Meilongnangcun",
    "wof:placetype":"locality"
},
  "geometry": {"coordinates":[94.26082,31.79221],"type":"Point"}
}