{
  "type": "Feature",
  "properties": {
    "gn:admin1_code":"2.0",
    "gn:asciiname":"Zuojian",
    "gn:country_code":"CN",
    "gn:dem":229,
    "gn:feature_class":"P",
    "gn:feature_code":"PPL",
    "gn:name":"Zuojian",
    "gn:population":0,
    "gn:timezone":"Asia/Shanghai",
    "iso:country":"CN",
    "name:zho_x_preferred":[
        "\u5de6\u80a9"
    ],
    "wof:name":"Zuojian",
    "wof:placetype":"locality"
},
  "geometry": {"coordinates":[118.93904000000001,28.53917],"type":"Point"}
}