{
  "type": "Feature",
  "properties": {
    "gn:admin1_code":"30.0",
    "gn:asciiname":"Dengzhangang",
    "gn:country_code":"CN",
    "gn:dem":23,
    "gn:feature_class":"P",
    "gn:feature_code":"PPL",
    "gn:name":"Dengzhangang",
    "gn:population":0,
    "gn:timezone":"Asia/Shanghai",
    "iso:country":"CN",
    "name:zho_x_preferred":[
        "Dengzhangang"
    ],
    "name:zho_x_variant":[
        "\u706f\u76cf\u5c97"
    ],
    "wof:name":"Dengzhangang",
    "wof:placetype":"locality"
},
  "geometry": {"coordinates":[112.905,23.71056],"type":"Point"}
}