{
  "type": "Feature",
  "properties": {
    "gn:admin1_code":"19.0",
    "gn:asciiname":"Zhujiabu",
    "gn:country_code":"CN",
    "gn:dem":18,
    "gn:feature_class":"P",
    "gn:feature_code":"PPL",
    "gn:name":"Zhujiabu",
    "gn:population":0,
    "gn:timezone":"Asia/Shanghai",
    "iso:country":"CN",
    "name:und_x_variant":[
        "Zhujiabao",
        "\u6731\u5bb6\u5821",
        "Zhujiabu"
    ],
    "wof:name":"Zhujiabu",
    "wof:placetype":"locality"
},
  "geometry": {"coordinates":[123.64579000000001,40.16171],"type":"Point"}
}