{
  "type": "Feature",
  "properties": {
    "gn:admin1_code":"30",
    "gn:asciiname":"Xinyan",
    "gn:country_code":"CN",
    "gn:dem":333,
    "gn:feature_class":"P",
    "gn:feature_code":"PPL",
    "gn:name":"Xinyan",
    "gn:population":0,
    "gn:timezone":"Asia/Shanghai",
    "iso:country":"CN",
    "wof:name":"Xinyan",
    "wof:placetype":"locality"
},
  "geometry": {"coordinates":[115.52083,23.47778],"type":"Point"}
}