{
  "type": "Feature",
  "properties": {
    "gn:admin1_code":"3",
    "gn:asciiname":"Pengcun",
    "gn:country_code":"CN",
    "gn:dem":210,
    "gn:feature_class":"P",
    "gn:feature_code":"PPL",
    "gn:name":"Pengcun",
    "gn:population":0,
    "gn:timezone":"Asia/Shanghai",
    "iso:country":"CN",
    "name:zho_x_preferred":[
        "\u84ec\u6751"
    ],
    "wof:name":"Pengcun",
    "wof:placetype":"locality"
},
  "geometry": {"coordinates":[114.79362999999999,25.99134],"type":"Point"}
}