{
  "type": "Feature",
  "properties": {
    "gn:admin1_code":"11",
    "gn:asciiname":"Tangtian",
    "gn:country_code":"CN",
    "gn:dem":344,
    "gn:feature_class":"P",
    "gn:feature_code":"PPL",
    "gn:name":"Tangtian",
    "gn:population":0,
    "gn:timezone":"Asia/Shanghai",
    "iso:country":"CN",
    "wof:name":"Tangtian",
    "wof:placetype":"locality"
},
  "geometry": {"coordinates":[110.66361000000001,26.645],"type":"Point"}
}