{
  "type": "Feature",
  "properties": {
    "gn:admin1_code":"4.0",
    "gn:asciiname":"Fuxu",
    "gn:country_code":"CN",
    "gn:dem":8,
    "gn:feature_class":"P",
    "gn:feature_code":"PPL",
    "gn:name":"Fuxu",
    "gn:population":0,
    "gn:timezone":"Asia/Shanghai",
    "iso:country":"CN",
    "name:zho_x_preferred":[
        "Fuxu"
    ],
    "name:zho_x_variant":[
        "\u5085\u5729"
    ],
    "wof:name":"Fuxu",
    "wof:placetype":"locality"
},
  "geometry": {"coordinates":[119.16313999999998,33.95602],"type":"Point"}
}