{
  "type": "Feature",
  "properties": {
    "gn:admin1_code":"8.0",
    "gn:asciiname":"Chunfengcun",
    "gn:country_code":"CN",
    "gn:dem":211,
    "gn:feature_class":"P",
    "gn:feature_code":"PPL",
    "gn:name":"Chunfengcun",
    "gn:population":0,
    "gn:timezone":"Asia/Shanghai",
    "iso:country":"CN",
    "name:zho_x_preferred":[
        "\u6625\u98ce\u6751"
    ],
    "wof:name":"Chunfengcun",
    "wof:placetype":"locality"
},
  "geometry": {"coordinates":[127.87081000000001,46.86327],"type":"Point"}
}