{
  "type": "Feature",
  "properties": {
    "gn:admin1_code":"30.0",
    "gn:asciiname":"Shangwoli",
    "gn:country_code":"CN",
    "gn:dem":126,
    "gn:feature_class":"P",
    "gn:feature_code":"PPL",
    "gn:name":"Shangwoli",
    "gn:population":0,
    "gn:timezone":"Asia/Shanghai",
    "iso:country":"CN",
    "name:zho_x_preferred":[
        "\u4e0a\u7a9d\u91cc"
    ],
    "wof:name":"Shangwoli",
    "wof:placetype":"locality"
},
  "geometry": {"coordinates":[115.79937,23.92229],"type":"Point"}
}