{
  "type": "Feature",
  "properties": {
    "gn:admin1_code":"19.0",
    "gn:asciiname":"Yingshougou",
    "gn:country_code":"CN",
    "gn:dem":90,
    "gn:feature_class":"P",
    "gn:feature_code":"PPL",
    "gn:name":"Yingshougou",
    "gn:population":0,
    "gn:timezone":"Asia/Shanghai",
    "iso:country":"CN",
    "name:zho_x_preferred":[
        "\u82f1\u5b88\u6c9f"
    ],
    "wof:name":"Yingshougou",
    "wof:placetype":"locality"
},
  "geometry": {"coordinates":[122.8672,40.65424],"type":"Point"}
}