{
  "type": "Feature",
  "properties": {
    "gn:admin1_code":"31",
    "gn:asciiname":"Sandao Nongchang",
    "gn:country_code":"CN",
    "gn:dem":35,
    "gn:feature_class":"P",
    "gn:feature_code":"PPLF",
    "gn:name":"Sandao Nongchang",
    "gn:population":0,
    "gn:timezone":"Asia/Shanghai",
    "iso:country":"CN",
    "name:und_x_variant":[
        "\u4e09\u9053\u519c\u573a"
    ],
    "wof:name":"Sandao Nongchang",
    "wof:placetype":"locality"
},
  "geometry": {"coordinates":[109.67836,18.44365],"type":"Point"}
}