{
  "type": "Feature",
  "properties": {
    "gn:admin1_code":"12.0",
    "gn:asciiname":"Huanggang",
    "gn:country_code":"CN",
    "gn:dem":46,
    "gn:feature_class":"P",
    "gn:feature_code":"PPLA2",
    "gn:name":"Huanggang",
    "gn:population":0,
    "gn:timezone":"Asia/Shanghai",
    "iso:country":"CN",
    "name:bul_x_preferred":[
        "\u0425\u0443\u0430\u043d\u0433\u0430\u043d"
    ],
    "name:cdo_x_preferred":[
        "U\u00f2ng-g\u014fng"
    ],
    "name:ces_x_preferred":[
        "Chuang-kang"
    ],
    "name:eng_x_historical":[
        "Hwang Chow",
        "Wangchau",
        "Hwang Chau"
    ],
    "name:eng_x_preferred":[
        "Hwang Chow"
    ],
    "name:eng_x_variant":[
        "Wangchau",
        "Hwang Chau"
    ],
    "name:fas_x_preferred":[
        "\u0647\u0648\u0627\u0646\u06af\u0627\u0646\u06af"
    ],
    "name:jpn_x_preferred":[
        "\u9ec4\u5ca1\u5e02"
    ],
    "name:jpn_x_variant":[
        "\u9ec4\u5ca1"
    ],
    "name:kor_x_preferred":[
        "\ud669\uac15 \uc2dc"
    ],
    "name:mya_x_preferred":[
        "\u101f\u1014\u103a\u1000\u1031\u102c\u1004\u103a\u1019\u103c\u102d\u102f\u1037"
    ],
    "name:nan_x_preferred":[
        "N\u0302g-kng-chh\u012b"
    ],
    "name:rus_x_preferred":[
        "\u0425\u0443\u0430\u043d\u0433\u0430\u043d"
    ],
    "name:srp_x_preferred":[
        "\u0425\u0443\u0430\u043d\u0433\u0430\u043d\u0433"
    ],
    "name:und_x_variant":[
        "\u9ec4\u5188",
        "Huanggang Shi",
        "\u9ec4\u5188\u5e02"
    ],
    "name:urd_x_preferred":[
        "\u06c1\u0648\u0627\u0646\u06af\u06af\u0627\u0646\u06af"
    ],
    "name:vie_x_preferred":[
        "Ho\u00e0ng C\u01b0\u01a1ng"
    ],
    "name:yue_x_preferred":[
        "\u9ec3\u5ca1"
    ],
    "wof:name":"Huanggang",
    "wof:placetype":"locality"
},
  "geometry": {"coordinates":[114.87035,30.45143],"type":"Point"}
}