{
  "type": "Feature",
  "properties": {
    "gn:admin1_code":"4.0",
    "gn:asciiname":"Qingchengcun",
    "gn:country_code":"CN",
    "gn:dem":4,
    "gn:feature_class":"P",
    "gn:feature_code":"PPL",
    "gn:name":"Qingchengcun",
    "gn:population":0,
    "gn:timezone":"Asia/Shanghai",
    "iso:country":"CN",
    "name:und_x_variant":[
        "Qingchen",
        "\u9752\u57ce"
    ],
    "name:zho_x_preferred":[
        "\u9752\u57ce\u6751"
    ],
    "wof:name":"Qingchengcun",
    "wof:placetype":"locality"
},
  "geometry": {"coordinates":[121.02721,31.97492],"type":"Point"}
}