{
  "type": "Feature",
  "properties": {
    "gn:admin1_code":"29",
    "gn:asciiname":"Jidichong",
    "gn:country_code":"CN",
    "gn:dem":1358,
    "gn:feature_class":"P",
    "gn:feature_code":"PPL",
    "gn:name":"Jidichong",
    "gn:population":0,
    "gn:timezone":"Asia/Shanghai",
    "iso:country":"CN",
    "name:zho_x_preferred":[
        "\u53ca\u5e95\u51b2"
    ],
    "wof:name":"Jidichong",
    "wof:placetype":"locality"
},
  "geometry": {"coordinates":[101.905,23.8888],"type":"Point"}
}