{
  "type": "Feature",
  "properties": {
    "gn:admin1_code":"4.0",
    "gn:asciiname":"Zhundi'an",
    "gn:country_code":"CN",
    "gn:dem":5,
    "gn:feature_class":"P",
    "gn:feature_code":"PPL",
    "gn:name":"Zhundi\u2019an",
    "gn:population":0,
    "gn:timezone":"Asia/Shanghai",
    "iso:country":"CN",
    "name:und_x_variant":[
        "\u51c6\u5824\u5eb5"
    ],
    "name:zho_x_preferred":[
        "Zhundi\u2019an"
    ],
    "name:zho_x_variant":[
        "\u51c6\u5824\u5eb5"
    ],
    "wof:name":"Zhundi'an",
    "wof:placetype":"locality"
},
  "geometry": {"coordinates":[120.88523000000001,32.12583],"type":"Point"}
}