{
  "type": "Feature",
  "properties": {
    "gn:admin1_code":"29.0",
    "gn:asciiname":"Luguotianba",
    "gn:country_code":"CN",
    "gn:dem":927,
    "gn:feature_class":"P",
    "gn:feature_code":"PPL",
    "gn:name":"Luguotianba",
    "gn:population":0,
    "gn:timezone":"Asia/Shanghai",
    "iso:country":"CN",
    "name:zho_x_preferred":[
        "\u7089\u9505\u7530\u575d"
    ],
    "wof:name":"Luguotianba",
    "wof:placetype":"locality"
},
  "geometry": {"coordinates":[99.5277,24.1725],"type":"Point"}
}