{
  "type": "Feature",
  "properties": {
    "gn:admin1_code":"26.0",
    "gn:asciiname":"Xiawencai",
    "gn:country_code":"CN",
    "gn:dem":885,
    "gn:feature_class":"P",
    "gn:feature_code":"PPL",
    "gn:name":"Xiawencai",
    "gn:population":0,
    "gn:timezone":"Asia/Shanghai",
    "iso:country":"CN",
    "name:zho_x_preferred":[
        "\u4e0b\u6587\u91c7"
    ],
    "wof:name":"Xiawencai",
    "wof:placetype":"locality"
},
  "geometry": {"coordinates":[109.52824,31.917],"type":"Point"}
}