{
  "type": "Feature",
  "properties": {
    "gn:admin1_code":"24.0",
    "gn:asciiname":"Jiaojiayingcun",
    "gn:country_code":"CN",
    "gn:dem":632,
    "gn:feature_class":"P",
    "gn:feature_code":"PPL",
    "gn:name":"Jiaojiayingcun",
    "gn:population":0,
    "gn:timezone":"Asia/Shanghai",
    "iso:country":"CN",
    "name:zho_x_preferred":[
        "\u7126\u5bb6\u8425\u6751"
    ],
    "wof:name":"Jiaojiayingcun",
    "wof:placetype":"locality"
},
  "geometry": {"coordinates":[110.75874,35.29258],"type":"Point"}
}