{
  "type": "Feature",
  "properties": {
    "gn:admin1_code":"4.0",
    "gn:asciiname":"Wushengdian",
    "gn:country_code":"CN",
    "gn:dem":4,
    "gn:feature_class":"P",
    "gn:feature_code":"PPL",
    "gn:name":"Wushengdian",
    "gn:population":0,
    "gn:timezone":"Asia/Shanghai",
    "iso:country":"CN",
    "name:und_x_variant":[
        "\u4e94\u5723\u6bbf"
    ],
    "name:zho_x_preferred":[
        "\u4e94\u5723\u6bbf"
    ],
    "wof:name":"Wushengdian",
    "wof:placetype":"locality"
},
  "geometry": {"coordinates":[120.7453,32.61012],"type":"Point"}
}