{
  "type": "Feature",
  "properties": {
    "gn:admin1_code":"16.0",
    "gn:asciiname":"Liusicun",
    "gn:country_code":"CN",
    "gn:dem":420,
    "gn:feature_class":"P",
    "gn:feature_code":"PPL",
    "gn:name":"Liusicun",
    "gn:population":0,
    "gn:timezone":"Asia/Shanghai",
    "iso:country":"CN",
    "name:zho_x_preferred":[
        "\u516d\u56db\u6751"
    ],
    "wof:name":"Liusicun",
    "wof:placetype":"locality"
},
  "geometry": {"coordinates":[110.81399999999999,22.7355],"type":"Point"}
}