{
  "type": "Feature",
  "properties": {
    "gn:admin1_code":"21.0",
    "gn:asciiname":"Xialaoguanping",
    "gn:country_code":"CN",
    "gn:dem":1617,
    "gn:feature_class":"P",
    "gn:feature_code":"PPL",
    "gn:name":"Xialaoguanping",
    "gn:population":0,
    "gn:timezone":"Asia/Shanghai",
    "iso:country":"CN",
    "name:und_x_variant":[
        "\u4e0b\u8001\u5b98\u576a"
    ],
    "name:zho_x_preferred":[
        "\u4e0b\u8001\u5b98\u576a"
    ],
    "wof:name":"Xialaoguanping",
    "wof:placetype":"locality"
},
  "geometry": {"coordinates":[106.25106,36.20799],"type":"Point"}
}