{
  "type": "Feature",
  "properties": {
    "gn:admin1_code":"29.0",
    "gn:asciiname":"Changputang",
    "gn:country_code":"CN",
    "gn:dem":1274,
    "gn:feature_class":"P",
    "gn:feature_code":"PPL",
    "gn:name":"Changputang",
    "gn:population":0,
    "gn:timezone":"Asia/Shanghai",
    "iso:country":"CN",
    "name:zho_x_preferred":[
        "\u83d6\u84b2\u5858"
    ],
    "wof:name":"Changputang",
    "wof:placetype":"locality"
},
  "geometry": {"coordinates":[99.6065,24.498],"type":"Point"}
}