{
  "type": "Feature",
  "properties": {
    "gn:admin1_code":"26.0",
    "gn:asciiname":"Beitianguocun",
    "gn:country_code":"CN",
    "gn:dem":570,
    "gn:feature_class":"P",
    "gn:feature_code":"PPL",
    "gn:name":"Beitianguocun",
    "gn:population":0,
    "gn:timezone":"Asia/Shanghai",
    "iso:country":"CN",
    "name:zho_x_preferred":[
        "\u5317\u7530\u679c\u6751"
    ],
    "wof:name":"Beitianguocun",
    "wof:placetype":"locality"
},
  "geometry": {"coordinates":[108.30858000000001,34.3979],"type":"Point"}
}