{
  "type": "Feature",
  "properties": {
    "gn:admin1_code":"3",
    "gn:asciiname":"Dalingxia",
    "gn:country_code":"CN",
    "gn:dem":140,
    "gn:feature_class":"P",
    "gn:feature_code":"PPL",
    "gn:name":"Dalingxia",
    "gn:population":0,
    "gn:timezone":"Asia/Shanghai",
    "iso:country":"CN",
    "name:und_x_variant":[
        "\u5927\u5cad\u4e0b"
    ],
    "wof:name":"Dalingxia",
    "wof:placetype":"locality"
},
  "geometry": {"coordinates":[115.41439,26.00794],"type":"Point"}
}