{
  "type": "Feature",
  "properties": {
    "gn:admin1_code":"31.0",
    "gn:asciiname":"Baochong",
    "gn:country_code":"CN",
    "gn:dem":378,
    "gn:feature_class":"P",
    "gn:feature_code":"PPL",
    "gn:name":"Baochong",
    "gn:population":0,
    "gn:timezone":"Asia/Shanghai",
    "iso:country":"CN",
    "name:und_x_variant":[
        "\u4fdd\u51b2"
    ],
    "wof:name":"Baochong",
    "wof:placetype":"locality"
},
  "geometry": {"coordinates":[109.35057999999999,18.63405],"type":"Point"}
}