{
  "type": "Feature",
  "properties": {
    "gn:admin1_code":"19.0",
    "gn:asciiname":"Shanghao Zigoucun",
    "gn:country_code":"CN",
    "gn:dem":319,
    "gn:feature_class":"P",
    "gn:feature_code":"PPL",
    "gn:name":"Shanghao Zigoucun",
    "gn:population":0,
    "gn:timezone":"Asia/Shanghai",
    "iso:country":"CN",
    "name:und_x_variant":[
        "Shanghaozigoucun",
        "Shanghao Zigoucun"
    ],
    "name:zho_x_preferred":[
        "\u4e0a\u84bf\u5b50\u6c9f\u6751"
    ],
    "wof:name":"Shanghao Zigoucun",
    "wof:placetype":"locality"
},
  "geometry": {"coordinates":[124.97506,40.71527],"type":"Point"}
}