{
  "type": "Feature",
  "properties": {
    "gn:admin1_code":"14.0",
    "gn:asciiname":"Sentangcun",
    "gn:country_code":"CN",
    "gn:dem":4230,
    "gn:feature_class":"P",
    "gn:feature_code":"PPL",
    "gn:name":"Sentangcun",
    "gn:population":0,
    "gn:timezone":"Asia/Urumqi",
    "iso:country":"CN",
    "name:zho_x_preferred":[
        "\u68ee\u5858\u6751"
    ],
    "wof:name":"Sentangcun",
    "wof:placetype":"locality"
},
  "geometry": {"coordinates":[92.95878999999999,31.55417000000001],"type":"Point"}
}