{
  "type": "Feature",
  "properties": {
    "gn:admin1_code":"32.0",
    "gn:asciiname":"Zhongqiaozi",
    "gn:country_code":"CN",
    "gn:dem":465,
    "gn:feature_class":"P",
    "gn:feature_code":"PPL",
    "gn:name":"Zhongqiaozi",
    "gn:population":0,
    "gn:timezone":"Asia/Shanghai",
    "iso:country":"CN",
    "name:zho_x_preferred":[
        "\u4e2d\u6865\u5b50"
    ],
    "wof:name":"Zhongqiaozi",
    "wof:placetype":"locality"
},
  "geometry": {"coordinates":[103.504,29.8283],"type":"Point"}
}