{
  "type": "Feature",
  "properties": {
    "gn:admin1_code":"32.0",
    "gn:asciiname":"Ranluo Yidui",
    "gn:country_code":"CN",
    "gn:dem":4411,
    "gn:feature_class":"P",
    "gn:feature_code":"PPLF",
    "gn:name":"Ranluo Yidui",
    "gn:population":0,
    "gn:timezone":"Asia/Shanghai",
    "iso:country":"CN",
    "name:zho_x_preferred":[
        "\u7136\u6d1b\u4e00\u961f"
    ],
    "wof:name":"Ranluo Yidui",
    "wof:placetype":"locality"
},
  "geometry": {"coordinates":[100.07299999999999,31.7062],"type":"Point"}
}