{
  "type": "Feature",
  "properties": {
    "gn:admin1_code":"25.0",
    "gn:asciiname":"Dongwang Jiazhuang",
    "gn:country_code":"CN",
    "gn:dem":21,
    "gn:feature_class":"P",
    "gn:feature_code":"PPL",
    "gn:name":"Dongwang Jiazhuang",
    "gn:population":0,
    "gn:timezone":"Asia/Shanghai",
    "iso:country":"CN",
    "name:zho_x_preferred":[
        "\u4e1c\u738b\u5bb6\u5e84"
    ],
    "wof:name":"Dongwang Jiazhuang",
    "wof:placetype":"locality"
},
  "geometry": {"coordinates":[121.75518999999998,36.91295],"type":"Point"}
}