{
  "type": "Feature",
  "properties": {
    "gn:admin1_code":"29.0",
    "gn:asciiname":"Wumuzu",
    "gn:country_code":"CN",
    "gn:dem":1319,
    "gn:feature_class":"P",
    "gn:feature_code":"PPL",
    "gn:name":"Wumuzu",
    "gn:population":0,
    "gn:timezone":"Asia/Shanghai",
    "iso:country":"CN",
    "name:zho_x_preferred":[
        "\u4e94\u4ea9\u79df"
    ],
    "wof:name":"Wumuzu",
    "wof:placetype":"locality"
},
  "geometry": {"coordinates":[102.63500000000001,23.057],"type":"Point"}
}