{
  "type": "Feature",
  "properties": {
    "gn:admin1_code":"7.0",
    "gn:asciiname":"Xiulong",
    "gn:country_code":"CN",
    "gn:dem":406,
    "gn:feature_class":"P",
    "gn:feature_code":"PPL",
    "gn:name":"Xiulong",
    "gn:population":0,
    "gn:timezone":"Asia/Shanghai",
    "iso:country":"CN",
    "name:zho_x_preferred":[
        "\u79c0\u5784"
    ],
    "wof:name":"Xiulong",
    "wof:placetype":"locality"
},
  "geometry": {"coordinates":[118.042,25.99165],"type":"Point"}
}