{
  "type": "Feature",
  "properties": {
    "gn:admin1_code":"18",
    "gn:asciiname":"Tuoduo",
    "gn:country_code":"CN",
    "gn:dem":2073,
    "gn:feature_class":"P",
    "gn:feature_code":"PPL",
    "gn:name":"Tuoduo",
    "gn:population":0,
    "gn:timezone":"Asia/Shanghai",
    "iso:country":"CN",
    "name:zho_x_preferred":[
        "\u62d6\u591a"
    ],
    "wof:name":"Tuoduo",
    "wof:placetype":"locality"
},
  "geometry": {"coordinates":[103.907,26.8931],"type":"Point"}
}