{
  "type": "Feature",
  "properties": {
    "gn:admin1_code":"16",
    "gn:asciiname":"Shangguying",
    "gn:country_code":"CN",
    "gn:dem":203,
    "gn:feature_class":"P",
    "gn:feature_code":"PPL",
    "gn:name":"Shangguying",
    "gn:population":0,
    "gn:timezone":"Asia/Shanghai",
    "iso:country":"CN",
    "name:zho_x_preferred":[
        "\u4e0a\u53e4\u8425"
    ],
    "wof:name":"Shangguying",
    "wof:placetype":"locality"
},
  "geometry": {"coordinates":[109.55,25.3215],"type":"Point"}
}