{
  "type": "Feature",
  "properties": {
    "gn:admin1_code":"24.0",
    "gn:asciiname":"Panmachi",
    "gn:country_code":"CN",
    "gn:dem":1563,
    "gn:feature_class":"P",
    "gn:feature_code":"PPL",
    "gn:name":"Panmachi",
    "gn:population":0,
    "gn:timezone":"Asia/Shanghai",
    "iso:country":"CN",
    "name:zho_x_preferred":[
        "\u76d8\u9a6c\u6c60"
    ],
    "wof:name":"Panmachi",
    "wof:placetype":"locality"
},
  "geometry": {"coordinates":[113.39839000000001,36.01835],"type":"Point"}
}