{
  "type": "Feature",
  "properties": {
    "gn:admin1_code":"18",
    "gn:asciiname":"Yuyuzi",
    "gn:country_code":"CN",
    "gn:dem":920,
    "gn:feature_class":"P",
    "gn:feature_code":"PPL",
    "gn:name":"Yuyuzi",
    "gn:population":0,
    "gn:timezone":"Asia/Shanghai",
    "iso:country":"CN",
    "name:zho_x_preferred":[
        "\u9c7c\u9c7c\u5b50"
    ],
    "wof:name":"Yuyuzi",
    "wof:placetype":"locality"
},
  "geometry": {"coordinates":[106.49299999999999,27.3508],"type":"Point"}
}