{
  "type": "Feature",
  "properties": {
    "gn:admin1_code":"32.0",
    "gn:asciiname":"Lishu",
    "gn:country_code":"CN",
    "gn:dem":637,
    "gn:feature_class":"P",
    "gn:feature_code":"PPL",
    "gn:name":"Lishu",
    "gn:population":0,
    "gn:timezone":"Asia/Shanghai",
    "iso:country":"CN",
    "name:zho_x_preferred":[
        "\u7281\u6811"
    ],
    "wof:name":"Lishu",
    "wof:placetype":"locality"
},
  "geometry": {"coordinates":[105.482,28.0992],"type":"Point"}
}