{
  "type": "Feature",
  "properties": {
    "gn:admin1_code":"19",
    "gn:asciiname":"Chezhangzi",
    "gn:country_code":"CN",
    "gn:dem":629,
    "gn:feature_class":"P",
    "gn:feature_code":"PPL",
    "gn:name":"Chezhangzi",
    "gn:population":0,
    "gn:timezone":"Asia/Shanghai",
    "iso:country":"CN",
    "wof:name":"Chezhangzi",
    "wof:placetype":"locality"
},
  "geometry": {"coordinates":[119.5775,42.25972],"type":"Point"}
}