{
  "type": "Feature",
  "properties": {
    "gn:admin1_code":"07",
    "gn:asciiname":"Jiajianyu",
    "gn:country_code":"CN",
    "gn:dem":864,
    "gn:feature_class":"P",
    "gn:feature_code":"PPL",
    "gn:name":"Jiajianyu",
    "gn:population":0,
    "gn:timezone":"Asia/Shanghai",
    "iso:country":"CN",
    "name:zho_x_preferred":[
        "\u52a0\u526a\u76c2"
    ],
    "wof:name":"Jiajianyu",
    "wof:placetype":"locality"
},
  "geometry": {"coordinates":[117.87806,25.56556],"type":"Point"}
}