{
  "type": "Feature",
  "properties": {
    "gn:admin1_code":"29.0",
    "gn:asciiname":"Daopo",
    "gn:country_code":"CN",
    "gn:dem":1986,
    "gn:feature_class":"P",
    "gn:feature_code":"PPL",
    "gn:name":"Daopo",
    "gn:population":0,
    "gn:timezone":"Asia/Shanghai",
    "iso:country":"CN",
    "name:zho_x_preferred":[
        "\u5230\u5761"
    ],
    "wof:name":"Daopo",
    "wof:placetype":"locality"
},
  "geometry": {"coordinates":[103.485,26.6722],"type":"Point"}
}