{
  "type": "Feature",
  "properties": {
    "gn:admin1_code":"32.0",
    "gn:asciiname":"Zhengjiaba",
    "gn:country_code":"CN",
    "gn:dem":428,
    "gn:feature_class":"P",
    "gn:feature_code":"PPL",
    "gn:name":"Zhengjiaba",
    "gn:population":0,
    "gn:timezone":"Asia/Shanghai",
    "iso:country":"CN",
    "name:zho_x_preferred":[
        "\u90d1\u5bb6\u575d"
    ],
    "wof:name":"Zhengjiaba",
    "wof:placetype":"locality"
},
  "geometry": {"coordinates":[104.63500000000001,29.1775],"type":"Point"}
}