{
  "type": "Feature",
  "properties": {
    "gn:admin1_code":"10",
    "gn:asciiname":"Qianshangzhuang",
    "gn:country_code":"CN",
    "gn:dem":39,
    "gn:feature_class":"P",
    "gn:feature_code":"PPL",
    "gn:name":"Qianshangzhuang",
    "gn:population":0,
    "gn:timezone":"Asia/Shanghai",
    "iso:country":"CN",
    "name:zho_x_preferred":[
        "\u524d\u5c1a\u5e84"
    ],
    "wof:name":"Qianshangzhuang",
    "wof:placetype":"locality"
},
  "geometry": {"coordinates":[115.54928999999998,36.80776],"type":"Point"}
}