{
  "type": "Feature",
  "properties": {
    "gn:admin1_code":"30",
    "gn:asciiname":"Kuishuiwei",
    "gn:country_code":"CN",
    "gn:dem":450,
    "gn:feature_class":"P",
    "gn:feature_code":"PPL",
    "gn:name":"Kuishuiwei",
    "gn:population":0,
    "gn:timezone":"Asia/Shanghai",
    "iso:country":"CN",
    "name:zho_x_preferred":[
        "\u8475\u6c34\u5c3e"
    ],
    "wof:name":"Kuishuiwei",
    "wof:placetype":"locality"
},
  "geometry": {"coordinates":[111.40531,21.7971],"type":"Point"}
}