{
  "type": "Feature",
  "properties": {
    "gn:admin1_code":"26.0",
    "gn:asciiname":"Yuanjunmiao",
    "gn:country_code":"CN",
    "gn:dem":647,
    "gn:feature_class":"P",
    "gn:feature_code":"PPL",
    "gn:name":"Yuanjunmiao",
    "gn:population":0,
    "gn:timezone":"Asia/Shanghai",
    "iso:country":"CN",
    "name:und_x_variant":[
        "\u5143\u541b\u5e99",
        "Xumiao",
        "Yuanjunmiao"
    ],
    "wof:name":"Yuanjunmiao",
    "wof:placetype":"locality"
},
  "geometry": {"coordinates":[109.47083000000001,34.18814],"type":"Point"}
}