{
  "type": "Feature",
  "properties": {
    "gn:admin1_code":"30",
    "gn:asciiname":"Zhitou",
    "gn:country_code":"CN",
    "gn:dem":9,
    "gn:feature_class":"P",
    "gn:feature_code":"PPL",
    "gn:name":"Zhitou",
    "gn:population":0,
    "gn:timezone":"Asia/Shanghai",
    "iso:country":"CN",
    "name:zho_x_preferred":[
        "\u5cd9\u5934"
    ],
    "wof:name":"Zhitou",
    "wof:placetype":"locality"
},
  "geometry": {"coordinates":[116.90351,23.63922],"type":"Point"}
}