{
  "type": "Feature",
  "properties": {
    "gn:admin1_code":"12.0",
    "gn:asciiname":"Tanjiahe",
    "gn:country_code":"CN",
    "gn:dem":120,
    "gn:feature_class":"P",
    "gn:feature_code":"PPL",
    "gn:name":"Tanjiahe",
    "gn:population":0,
    "gn:timezone":"Asia/Shanghai",
    "iso:country":"CN",
    "name:zho_x_preferred":[
        "\u8c08\u5bb6\u6cb3"
    ],
    "wof:name":"Tanjiahe",
    "wof:placetype":"locality"
},
  "geometry": {"coordinates":[114.23724,31.69957],"type":"Point"}
}