{
  "type": "Feature",
  "properties": {
    "gn:admin1_code":"12",
    "gn:asciiname":"Duodaoshi",
    "gn:country_code":"CN",
    "gn:dem":109,
    "gn:feature_class":"P",
    "gn:feature_code":"PPLA4",
    "gn:name":"Duodaoshi",
    "gn:population":0,
    "gn:timezone":"Asia/Shanghai",
    "iso:country":"CN",
    "name:deu_x_preferred":[
        "Duodao"
    ],
    "name:jpn_x_preferred":[
        "\u30bf\u30c4\u5200\u533a"
    ],
    "name:kor_x_preferred":[
        "\ub46c\ub2e4\uc624\uad6c"
    ],
    "name:nor_x_preferred":[
        "Duodao"
    ],
    "name:swe_x_preferred":[
        "Duodao"
    ],
    "name:und_x_variant":[
        "To-tao",
        "Duodaoshi",
        "To-tao-shih",
        "Duodao",
        "\u6387\u5200\u77f3",
        "Duodaoshi Jiedao",
        "\u6387\u5200\u77f3\u8857\u9053"
    ],
    "name:vie_x_preferred":[
        "Xuy\u1ebft \u0110ao"
    ],
    "name:zho_x_preferred":[
        "\u6387\u5200\u533a"
    ],
    "wof:name":"Duodaoshi",
    "wof:placetype":"locality"
},
  "geometry": {"coordinates":[112.18476,30.96174],"type":"Point"}
}