{
  "type": "Feature",
  "properties": {
    "gn:admin1_code":"26.0",
    "gn:asciiname":"Anhua",
    "gn:country_code":"CN",
    "gn:dem":1161,
    "gn:feature_class":"P",
    "gn:feature_code":"PPL",
    "gn:name":"Anhua",
    "gn:population":0,
    "gn:timezone":"Asia/Shanghai",
    "iso:country":"CN",
    "name:und_x_variant":[
        "\u5b89\u534e"
    ],
    "wof:name":"Anhua",
    "wof:placetype":"locality"
},
  "geometry": {"coordinates":[106.51588,33.4404],"type":"Point"}
}