{
  "type": "Feature",
  "properties": {
    "gn:admin1_code":"14.0",
    "gn:asciiname":"Ling'age",
    "gn:country_code":"CN",
    "gn:dem":4069,
    "gn:feature_class":"P",
    "gn:feature_code":"PPL",
    "gn:name":"Ling\u2019age",
    "gn:population":0,
    "gn:timezone":"Asia/Urumqi",
    "iso:country":"CN",
    "name:und_x_variant":[
        "Ling\u2019age"
    ],
    "name:zho_x_preferred":[
        "\u5cad\u963f\u683c"
    ],
    "wof:name":"Ling'age",
    "wof:placetype":"locality"
},
  "geometry": {"coordinates":[93.99142999999999,30.68695],"type":"Point"}
}