{
  "type": "Feature",
  "properties": {
    "gn:admin1_code":"23.0",
    "gn:asciiname":"Minjian",
    "gn:country_code":"CN",
    "gn:dem":6,
    "gn:feature_class":"P",
    "gn:feature_code":"PPL",
    "gn:name":"Minjian",
    "gn:population":0,
    "gn:timezone":"Asia/Shanghai",
    "iso:country":"CN",
    "name:und_x_variant":[
        "\u6c11\u5efa"
    ],
    "wof:name":"Minjian",
    "wof:placetype":"locality"
},
  "geometry": {"coordinates":[121.45526,31.09947],"type":"Point"}
}