{
  "type": "Feature",
  "properties": {
    "gn:admin1_code":"19.0",
    "gn:asciiname":"Shuanglong",
    "gn:country_code":"CN",
    "gn:dem":14,
    "gn:feature_class":"P",
    "gn:feature_code":"PPL",
    "gn:name":"Shuanglong",
    "gn:population":0,
    "gn:timezone":"Asia/Shanghai",
    "iso:country":"CN",
    "name:ceb_x_preferred":[
        "Shuanglong"
    ],
    "name:deu_x_preferred":[
        "Shuanglong"
    ],
    "name:swe_x_preferred":[
        "Shuanglong"
    ],
    "name:und_x_variant":[
        "\u53cc\u9f99"
    ],
    "wof:name":"Shuanglong",
    "wof:placetype":"locality"
},
  "geometry": {"coordinates":[122.64912,40.92698],"type":"Point"}
}