{
  "type": "Feature",
  "properties": {
    "gn:admin1_code":"02",
    "gn:asciiname":"Hengdu",
    "gn:cc2":"CN",
    "gn:country_code":"CN",
    "gn:dem":70,
    "gn:feature_class":"P",
    "gn:feature_code":"PPL",
    "gn:name":"Hengdu",
    "gn:population":0,
    "gn:timezone":"Asia/Shanghai",
    "iso:country":"CN",
    "name:und_x_variant":[
        "Ta-heng-tu-shih",
        "Hengdu"
    ],
    "wof:name":"Hengdu",
    "wof:placetype":"locality"
},
  "geometry": {"coordinates":[121.49833,29.00722],"type":"Point"}
}