{
  "type": "Feature",
  "properties": {
    "gn:admin1_code":"7.0",
    "gn:asciiname":"Zhengban",
    "gn:country_code":"CN",
    "gn:dem":10,
    "gn:feature_class":"P",
    "gn:feature_code":"PPL",
    "gn:name":"Zhengban",
    "gn:population":0,
    "gn:timezone":"Asia/Shanghai",
    "iso:country":"CN",
    "name:zho_x_preferred":[
        "\u90d1\u5742"
    ],
    "wof:name":"Zhengban",
    "wof:placetype":"locality"
},
  "geometry": {"coordinates":[119.00856,25.40492],"type":"Point"}
}