{
  "type": "Feature",
  "properties": {
    "gn:admin1_code":"14.0",
    "gn:asciiname":"Korra",
    "gn:country_code":"CN",
    "gn:dem":4518,
    "gn:feature_class":"P",
    "gn:feature_code":"PPLF",
    "gn:name":"Korra",
    "gn:population":0,
    "gn:timezone":"Asia/Urumqi",
    "iso:country":"CN",
    "name:ara_x_preferred":[
        "\u0643\u0648\u0631\u0627"
    ],
    "name:aze_x_preferred":[
        "Korra"
    ],
    "name:bod_x_preferred":[
        "Korra"
    ],
    "name:fra_x_preferred":[
        "Korra"
    ],
    "name:ind_x_preferred":[
        "Korra"
    ],
    "name:ita_x_preferred":[
        "Korra"
    ],
    "name:nld_x_preferred":[
        "Korra"
    ],
    "name:rus_x_preferred":[
        "\u041a\u043e\u0440\u0440\u0430"
    ],
    "name:spa_x_preferred":[
        "Korra"
    ],
    "name:zho_x_preferred":[
        "Kuore"
    ],
    "name:zho_x_variant":[
        "\u62ec\u70ed",
        "Wada",
        "\u74e6\u8fbe"
    ],
    "wof:name":"Korra",
    "wof:placetype":"locality"
},
  "geometry": {"coordinates":[97.83333,30.86667000000001],"type":"Point"}
}