{
  "type": "Feature",
  "properties": {
    "gn:admin1_code":"32.0",
    "gn:asciiname":"Qingmingqiao",
    "gn:country_code":"CN",
    "gn:dem":372,
    "gn:feature_class":"P",
    "gn:feature_code":"PPL",
    "gn:name":"Qingmingqiao",
    "gn:population":0,
    "gn:timezone":"Asia/Shanghai",
    "iso:country":"CN",
    "name:zho_x_preferred":[
        "\u6e05\u660e\u6865"
    ],
    "wof:name":"Qingmingqiao",
    "wof:placetype":"locality"
},
  "geometry": {"coordinates":[106.381,31.2898],"type":"Point"}
}