{
  "type": "Feature",
  "properties": {
    "gn:admin1_code":"12",
    "gn:asciiname":"Libu",
    "gn:country_code":"CN",
    "gn:dem":33,
    "gn:feature_class":"P",
    "gn:feature_code":"PPLA4",
    "gn:name":"Libu",
    "gn:population":0,
    "gn:timezone":"Asia/Shanghai",
    "iso:country":"CN",
    "name:und_x_variant":[
        "Li-chia-pu",
        "Libu",
        "\u674e\u57e0",
        "Libu Zhen",
        "\u674e\u57e0\u9547"
    ],
    "wof:name":"Libu",
    "wof:placetype":"locality"
},
  "geometry": {"coordinates":[112.06667,30.32223],"type":"Point"}
}