{
  "type": "Feature",
  "properties": {
    "gn:admin1_code":"12",
    "gn:asciiname":"Libu",
    "gn:country_code":"CN",
    "gn:dem":33,
    "gn:feature_class":"P",
    "gn:feature_code":"PPLA4",
    "gn:name":"Libu",
    "gn:population":0,
    "gn:timezone":"Asia/Shanghai",
    "iso:country":"CN",
    "name:ara_x_preferred":[
        "\u0627\u0644\u0644\u064a\u0628\u0648"
    ],
    "name:bel_x_preferred":[
        "\u0421\u0442\u0430\u0440\u0430\u0436\u044b\u0442\u043d\u044b\u044f \u043b\u0456\u0432\u0456\u0439\u0446\u044b"
    ],
    "name:cat_x_preferred":[
        "Libu"
    ],
    "name:dan_x_preferred":[
        "Libu"
    ],
    "name:ell_x_preferred":[
        "\u039b\u03af\u03bc\u03c0\u03bf\u03c5"
    ],
    "name:fin_x_preferred":[
        "Libu"
    ],
    "name:fra_x_preferred":[
        "Libou"
    ],
    "name:ita_x_preferred":[
        "Libu"
    ],
    "name:jpn_x_preferred":[
        "\u30ea\u30d6"
    ],
    "name:nld_x_preferred":[
        "Liboe"
    ],
    "name:nor_x_preferred":[
        "Libu"
    ],
    "name:spa_x_preferred":[
        "Libu"
    ],
    "name:und_x_variant":[
        "Li-chia-pu",
        "Libu",
        "\u674e\u57e0",
        "Libu Zhen",
        "\u674e\u57e0\u9547"
    ],
    "wof:name":"Libu",
    "wof:placetype":"locality"
},
  "geometry": {"coordinates":[112.06667,30.32223],"type":"Point"}
}