{
  "type": "Feature",
  "properties": {
    "gn:admin1_code":"29.0",
    "gn:asciiname":"Puji",
    "gn:country_code":"CN",
    "gn:dem":2467,
    "gn:feature_class":"P",
    "gn:feature_code":"PPL",
    "gn:name":"Puji",
    "gn:population":0,
    "gn:timezone":"Asia/Shanghai",
    "iso:country":"CN",
    "name:zho_x_preferred":[
        "\u666e\u6d4e"
    ],
    "wof:name":"Puji",
    "wof:placetype":"locality"
},
  "geometry": {"coordinates":[100.185,26.9006],"type":"Point"}
}