{
  "type": "Feature",
  "properties": {
    "gn:admin1_code":"8.0",
    "gn:asciiname":"Leyecun",
    "gn:country_code":"CN",
    "gn:dem":244,
    "gn:feature_class":"P",
    "gn:feature_code":"PPL",
    "gn:name":"Leyecun",
    "gn:population":0,
    "gn:timezone":"Asia/Shanghai",
    "iso:country":"CN",
    "name:zho_x_preferred":[
        "\u4e50\u4e1a\u6751"
    ],
    "wof:name":"Leyecun",
    "wof:placetype":"locality"
},
  "geometry": {"coordinates":[124.93446000000002,48.15446],"type":"Point"}
}