{
  "type": "Feature",
  "properties": {
    "gn:admin1_code":"12.0",
    "gn:asciiname":"Hujiatai",
    "gn:country_code":"CN",
    "gn:dem":127,
    "gn:feature_class":"P",
    "gn:feature_code":"PPL",
    "gn:name":"Hujiatai",
    "gn:population":0,
    "gn:timezone":"Asia/Shanghai",
    "iso:country":"CN",
    "name:zho_x_preferred":[
        "Hujiatai"
    ],
    "name:zho_x_variant":[
        "\u80e1\u5bb6\u53f0"
    ],
    "wof:name":"Hujiatai",
    "wof:placetype":"locality"
},
  "geometry": {"coordinates":[111.1803,30.64087],"type":"Point"}
}