{
  "type": "Feature",
  "properties": {
    "gn:admin1_code":"16.0",
    "gn:asciiname":"Mengguo",
    "gn:country_code":"CN",
    "gn:dem":816,
    "gn:feature_class":"P",
    "gn:feature_code":"PPL",
    "gn:name":"Mengguo",
    "gn:population":0,
    "gn:timezone":"Asia/Shanghai",
    "iso:country":"CN",
    "name:zho_x_preferred":[
        "\u8499\u56fd"
    ],
    "wof:name":"Mengguo",
    "wof:placetype":"locality"
},
  "geometry": {"coordinates":[107.629,25.2344],"type":"Point"}
}