{
  "type": "Feature",
  "properties": {
    "gn:admin1_code":"11.0",
    "gn:asciiname":"Jiajiantian",
    "gn:country_code":"CN",
    "gn:dem":548,
    "gn:feature_class":"P",
    "gn:feature_code":"PPL",
    "gn:name":"Jiajiantian",
    "gn:population":0,
    "gn:timezone":"Asia/Shanghai",
    "iso:country":"CN",
    "name:zho_x_preferred":[
        "\u67b6\u67a7\u7530"
    ],
    "wof:name":"Jiajiantian",
    "wof:placetype":"locality"
},
  "geometry": {"coordinates":[110.40035,27.53811],"type":"Point"}
}