{
  "type": "Feature",
  "properties": {
    "gn:admin1_code":"16.0",
    "gn:asciiname":"Xingcheng",
    "gn:country_code":"CN",
    "gn:dem":115,
    "gn:feature_class":"P",
    "gn:feature_code":"PPL",
    "gn:name":"Xingcheng",
    "gn:population":0,
    "gn:timezone":"Asia/Shanghai",
    "iso:country":"CN",
    "name:ara_x_preferred":[
        "\u0634\u064a\u0646\u063a\u062a\u0634\u064a\u0646\u063a"
    ],
    "name:ceb_x_preferred":[
        "Xingcheng"
    ],
    "name:deu_x_preferred":[
        "Xingcheng"
    ],
    "name:fra_x_preferred":[
        "Xingcheng"
    ],
    "name:ita_x_preferred":[
        "Xingcheng"
    ],
    "name:jpn_x_preferred":[
        "\u8208\u57ce\u5e02"
    ],
    "name:kik_x_preferred":[
        "Xingcheng"
    ],
    "name:kor_x_preferred":[
        "\uc2f1\uccad\uc2dc"
    ],
    "name:mlg_x_preferred":[
        "Xingcheng"
    ],
    "name:nor_x_preferred":[
        "Xingcheng"
    ],
    "name:rus_x_preferred":[
        "\u0421\u0438\u043d\u0447\u044d\u043d"
    ],
    "name:swe_x_preferred":[
        "Xingcheng"
    ],
    "name:urd_x_preferred":[
        "\u0634\u0646\u06af\u0686\u06cc\u0646\u06af"
    ],
    "name:vie_x_preferred":[
        "H\u01b0ng Th\u00e0nh"
    ],
    "name:war_x_preferred":[
        "Xingcheng"
    ],
    "name:zho_x_preferred":[
        "\u5174\u57ce"
    ],
    "name:zho_x_variant":[
        "\u5174\u57ce\u5e02"
    ],
    "wof:name":"Xingcheng",
    "wof:placetype":"locality"
},
  "geometry": {"coordinates":[106.887,23.7266],"type":"Point"}
}