{
  "type": "Feature",
  "properties": {
    "gn:admin1_code":"10",
    "gn:asciiname":"Fuping",
    "gn:cc2":"CN",
    "gn:country_code":"CN",
    "gn:dem":259,
    "gn:feature_class":"P",
    "gn:feature_code":"PPL",
    "gn:name":"Fuping",
    "gn:population":0,
    "gn:timezone":"Asia/Shanghai",
    "iso:country":"CN",
    "name:ceb_x_preferred":[
        "Fuping"
    ],
    "name:deu_x_preferred":[
        "Fuping"
    ],
    "name:fra_x_preferred":[
        "Fuping"
    ],
    "name:kor_x_preferred":[
        "\ud478\ud551\ud604"
    ],
    "name:nor_x_preferred":[
        "Fuping"
    ],
    "name:rus_x_preferred":[
        "\u0424\u0443\u043f\u0438\u043d"
    ],
    "name:swe_x_preferred":[
        "Fuping"
    ],
    "name:und_x_variant":[
        "Pupinghsien",
        "Fou-p\u2019ing",
        "Fou-p\u2019ing-ch\u2019eng-kuan",
        "Fowping",
        "Fou-p\u2019ing-hsien"
    ],
    "wof:name":"Fuping",
    "wof:placetype":"locality"
},
  "geometry": {"coordinates":[114.18667000000001,38.84694],"type":"Point"}
}