{
  "type": "Feature",
  "properties": {
    "gn:admin1_code":"4.0",
    "gn:asciiname":"Yunjia",
    "gn:country_code":"CN",
    "gn:dem":10,
    "gn:feature_class":"P",
    "gn:feature_code":"PPL",
    "gn:name":"Yunjia",
    "gn:population":0,
    "gn:timezone":"Asia/Shanghai",
    "iso:country":"CN",
    "name:zho_x_preferred":[
        "\u607d\u5bb6"
    ],
    "wof:name":"Yunjia",
    "wof:placetype":"locality"
},
  "geometry": {"coordinates":[119.83987,32.02567],"type":"Point"}
}