{
  "type": "Feature",
  "properties": {
    "gn:admin1_code":"3.0",
    "gn:asciiname":"Neigaobei",
    "gn:country_code":"CN",
    "gn:dem":441,
    "gn:feature_class":"P",
    "gn:feature_code":"PPL",
    "gn:name":"Neigaobei",
    "gn:population":0,
    "gn:timezone":"Asia/Shanghai",
    "iso:country":"CN",
    "name:und_x_variant":[
        "\u5185\u9ad8\u80cc"
    ],
    "wof:name":"Neigaobei",
    "wof:placetype":"locality"
},
  "geometry": {"coordinates":[115.74263000000001,26.73886],"type":"Point"}
}