{
  "type": "Feature",
  "properties": {
    "gn:admin1_code":"9",
    "gn:asciiname":"Xiaosuzhuang",
    "gn:country_code":"CN",
    "gn:dem":33,
    "gn:feature_class":"P",
    "gn:feature_code":"PPL",
    "gn:name":"Xiaosuzhuang",
    "gn:population":0,
    "gn:timezone":"Asia/Shanghai",
    "iso:country":"CN",
    "name:zho_x_preferred":[
        "\u5c0f\u82cf\u5e84"
    ],
    "wof:name":"Xiaosuzhuang",
    "wof:placetype":"locality"
},
  "geometry": {"coordinates":[116.19799999999999,33.8228],"type":"Point"}
}