{
  "type": "Feature",
  "properties": {
    "gn:admin1_code":"3.0",
    "gn:asciiname":"Litangshan",
    "gn:country_code":"CN",
    "gn:dem":132,
    "gn:feature_class":"P",
    "gn:feature_code":"PPL",
    "gn:name":"Litangshan",
    "gn:population":0,
    "gn:timezone":"Asia/Shanghai",
    "iso:country":"CN",
    "name:zho_x_preferred":[
        "\u91cc\u5802\u5c71"
    ],
    "wof:name":"Litangshan",
    "wof:placetype":"locality"
},
  "geometry": {"coordinates":[117.29841999999999,28.16039],"type":"Point"}
}