{
  "type": "Feature",
  "properties": {
    "gn:admin1_code":"04",
    "gn:asciiname":"Qiaozi",
    "gn:country_code":"CN",
    "gn:dem":4,
    "gn:feature_class":"P",
    "gn:feature_code":"PPL",
    "gn:name":"Qiaozi",
    "gn:population":0,
    "gn:timezone":"Asia/Shanghai",
    "iso:country":"CN",
    "name:und_x_variant":[
        "Ch\u2019iao-tzu-t\u2019ou",
        "Qiaozitou",
        "Qiaozi"
    ],
    "name:zho_x_preferred":[
        "\u6865\u6893"
    ],
    "wof:name":"Qiaozi",
    "wof:placetype":"locality"
},
  "geometry": {"coordinates":[120.54608,32.72693],"type":"Point"}
}