{
  "type": "Feature",
  "properties": {
    "gn:admin1_code":"10",
    "gn:asciiname":"Ma'anjia",
    "gn:country_code":"CN",
    "gn:dem":1418,
    "gn:feature_class":"P",
    "gn:feature_code":"PPL",
    "gn:name":"Ma\u2019anjia",
    "gn:population":0,
    "gn:timezone":"Asia/Shanghai",
    "iso:country":"CN",
    "name:und_x_variant":[
        "Ma\u2019anjia"
    ],
    "name:zho_x_preferred":[
        "\u9a6c\u978d\u67b6"
    ],
    "wof:name":"Ma'anjia",
    "wof:placetype":"locality"
},
  "geometry": {"coordinates":[114.90935,41.837],"type":"Point"}
}