{
  "type": "Feature",
  "properties": {
    "iso:country":"CN",
    "qs:name":"\u53f6\u57ce",
    "qs:name_adm0":"\u4e2d\u570b",
    "qs:name_adm1":"\u65b0\u7586\u7ef4\u543e\u5c14\u81ea\u6cbb\u533a",
    "qs:photos":52,
    "qs:photos_1k":11,
    "qs:photos_9k":1,
    "qs:photos_9r":2,
    "qs:photos_all":52,
    "qs:photos_sr":2,
    "qs:placetype":"Town",
    "qs:pop_sr":"0",
    "wd:wordcount":66,
    "wof:name":"\u53f6\u57ce",
    "wof:placetype":"locality"
},
  "geometry": {"coordinates":[77.413873,37.884258],"type":"Point"}
}