{
  "type": "Feature",
  "properties": {
    "gn:admin1_code":"19.0",
    "gn:asciiname":"Nanzhang Jiagou",
    "gn:country_code":"CN",
    "gn:dem":49,
    "gn:feature_class":"P",
    "gn:feature_code":"PPL",
    "gn:name":"Nanzhang Jiagou",
    "gn:population":0,
    "gn:timezone":"Asia/Shanghai",
    "iso:country":"CN",
    "name:und_x_variant":[
        "\u5357\u5f20\u5bb6\u6c9f"
    ],
    "wof:name":"Nanzhang Jiagou",
    "wof:placetype":"locality"
},
  "geometry": {"coordinates":[123.87282,40.0891],"type":"Point"}
}