{
  "type": "Feature",
  "properties": {
    "gn:admin1_code":"24.0",
    "gn:asciiname":"Junjiashan",
    "gn:country_code":"CN",
    "gn:dem":1660,
    "gn:feature_class":"P",
    "gn:feature_code":"PPL",
    "gn:name":"Junjiashan",
    "gn:population":0,
    "gn:timezone":"Asia/Shanghai",
    "iso:country":"CN",
    "name:zho_x_preferred":[
        "\u541b\u5bb6\u5c71"
    ],
    "wof:name":"Junjiashan",
    "wof:placetype":"locality"
},
  "geometry": {"coordinates":[111.21495,36.52186],"type":"Point"}
}