{
  "type": "Feature",
  "properties": {
    "gn:admin1_code":"10",
    "gn:asciiname":"Douyu",
    "gn:cc2":"CN",
    "gn:country_code":"CN",
    "gn:dem":66,
    "gn:feature_class":"P",
    "gn:feature_code":"PPL",
    "gn:name":"Douyu",
    "gn:population":0,
    "gn:timezone":"Asia/Shanghai",
    "iso:country":"CN",
    "name:und_x_variant":[
        "Tou-y\u00fc",
        "Tou-yu-ts\u2019un",
        "Tou-y\u00fc-chen",
        "Towy\u00fc",
        "Douyu"
    ],
    "name:zho_x_preferred":[
        "\u7aa6\u59aa\u9547"
    ],
    "wof:name":"Douyu",
    "wof:placetype":"locality"
},
  "geometry": {"coordinates":[114.50082999999999,37.89639],"type":"Point"}
}