{
  "type": "Feature",
  "properties": {
    "gn:admin1_code":"7.0",
    "gn:asciiname":"Longtan",
    "gn:country_code":"CN",
    "gn:dem":995,
    "gn:feature_class":"P",
    "gn:feature_code":"PPL",
    "gn:name":"Longtan",
    "gn:population":0,
    "gn:timezone":"Asia/Shanghai",
    "iso:country":"CN",
    "name:ceb_x_preferred":[
        "Longtan"
    ],
    "name:deu_x_preferred":[
        "Longtan"
    ],
    "name:fra_x_preferred":[
        "Longtan"
    ],
    "name:und_x_variant":[
        "\u9f99\u6f6d",
        "Longtan"
    ],
    "wof:name":"Longtan",
    "wof:placetype":"locality"
},
  "geometry": {"coordinates":[118.9417,27.10293],"type":"Point"}
}