{
  "type": "Feature",
  "properties": {
    "gn:admin1_code":"30.0",
    "gn:asciiname":"Xianghesheng",
    "gn:country_code":"CN",
    "gn:dem":-2,
    "gn:feature_class":"P",
    "gn:feature_code":"PPL",
    "gn:name":"Xianghesheng",
    "gn:population":0,
    "gn:timezone":"Asia/Shanghai",
    "iso:country":"CN",
    "name:und_x_variant":[
        "\u7965\u548c\u751f"
    ],
    "name:zho_x_preferred":[
        "\u7965\u548c\u751f"
    ],
    "wof:name":"Xianghesheng",
    "wof:placetype":"locality"
},
  "geometry": {"coordinates":[113.55459999999999,22.63453],"type":"Point"}
}