{
  "type": "Feature",
  "properties": {
    "gn:admin1_code":"29.0",
    "gn:asciiname":"Ganshidong",
    "gn:country_code":"CN",
    "gn:dem":1543,
    "gn:feature_class":"P",
    "gn:feature_code":"PPL",
    "gn:name":"Ganshidong",
    "gn:population":0,
    "gn:timezone":"Asia/Shanghai",
    "iso:country":"CN",
    "name:zho_x_preferred":[
        "\u5e72\u77f3\u6d1e"
    ],
    "wof:name":"Ganshidong",
    "wof:placetype":"locality"
},
  "geometry": {"coordinates":[104.48,24.3024],"type":"Point"}
}