{
  "type": "Feature",
  "properties": {
    "gn:admin1_code":"2.0",
    "gn:asciiname":"Jiaoshuixi",
    "gn:country_code":"CN",
    "gn:dem":38,
    "gn:feature_class":"P",
    "gn:feature_code":"PPL",
    "gn:name":"Jiaoshuixi",
    "gn:population":0,
    "gn:timezone":"Asia/Shanghai",
    "iso:country":"CN",
    "name:zho_x_preferred":[
        "\u4ea4\u6c34\u6eaa"
    ],
    "wof:name":"Jiaoshuixi",
    "wof:placetype":"locality"
},
  "geometry": {"coordinates":[120.95403,29.84208],"type":"Point"}
}