{
  "type": "Feature",
  "properties": {
    "gn:admin1_code":"25.0",
    "gn:asciiname":"Huizhancun",
    "gn:country_code":"CN",
    "gn:dem":64,
    "gn:feature_class":"P",
    "gn:feature_code":"PPL",
    "gn:name":"Huizhancun",
    "gn:population":0,
    "gn:timezone":"Asia/Shanghai",
    "iso:country":"CN",
    "name:zho_x_preferred":[
        "\u8f89\u6e5b\u6751"
    ],
    "wof:name":"Huizhancun",
    "wof:placetype":"locality"
},
  "geometry": {"coordinates":[121.52070999999999,37.04543],"type":"Point"}
}