{
  "type": "Feature",
  "properties": {
    "gn:admin1_code":"7",
    "gn:asciiname":"Dongyuan",
    "gn:country_code":"CN",
    "gn:dem":269,
    "gn:feature_class":"P",
    "gn:feature_code":"PPL",
    "gn:name":"Dongyuan",
    "gn:population":0,
    "gn:timezone":"Asia/Shanghai",
    "iso:country":"CN",
    "name:ceb_x_preferred":[
        "Dongyuan"
    ],
    "name:deu_x_preferred":[
        "Dongyuan"
    ],
    "name:nor_x_preferred":[
        "Dongyuan"
    ],
    "name:zho_x_preferred":[
        "\u4e1c\u6e90"
    ],
    "wof:name":"Dongyuan",
    "wof:placetype":"locality"
},
  "geometry": {"coordinates":[118.13055,27.58415],"type":"Point"}
}