{
  "type": "Feature",
  "properties": {
    "gn:admin1_code":"30",
    "gn:asciiname":"Hetai",
    "gn:country_code":"CN",
    "gn:dem":132,
    "gn:feature_class":"P",
    "gn:feature_code":"PPLA4",
    "gn:name":"Hetai",
    "gn:population":0,
    "gn:timezone":"Asia/Shanghai",
    "iso:country":"CN",
    "name:und_x_variant":[
        "Hetai Zhen",
        "\u6cb3\u53f0\u9547"
    ],
    "name:zho_x_preferred":[
        "\u6cb3\u53f0"
    ],
    "wof:name":"Hetai",
    "wof:placetype":"locality"
},
  "geometry": {"coordinates":[112.27409,23.34962],"type":"Point"}
}