{
  "type": "Feature",
  "properties": {
    "gn:admin1_code":"3.0",
    "gn:asciiname":"Gantoucun",
    "gn:country_code":"CN",
    "gn:dem":209,
    "gn:feature_class":"P",
    "gn:feature_code":"PPL",
    "gn:name":"Gantoucun",
    "gn:population":0,
    "gn:timezone":"Asia/Shanghai",
    "iso:country":"CN",
    "name:und_x_variant":[
        "\u5e72\u5934\u6751"
    ],
    "wof:name":"Gantoucun",
    "wof:placetype":"locality"
},
  "geometry": {"coordinates":[116.06927,26.64123],"type":"Point"}
}