{
  "type": "Feature",
  "properties": {
    "gn:admin1_code":"18",
    "gn:asciiname":"Jizhongcun",
    "gn:country_code":"CN",
    "gn:dem":871,
    "gn:feature_class":"P",
    "gn:feature_code":"PPL",
    "gn:name":"Jizhongcun",
    "gn:population":0,
    "gn:timezone":"Asia/Shanghai",
    "iso:country":"CN",
    "name:zho_x_preferred":[
        "\u96c6\u4e2d\u6751"
    ],
    "wof:name":"Jizhongcun",
    "wof:placetype":"locality"
},
  "geometry": {"coordinates":[107.681,29.0868],"type":"Point"}
}