{
  "type": "Feature",
  "properties": {
    "gn:admin1_code":"29.0",
    "gn:asciiname":"Fanicun",
    "gn:country_code":"CN",
    "gn:dem":2330,
    "gn:feature_class":"P",
    "gn:feature_code":"PPL",
    "gn:name":"Fanicun",
    "gn:population":0,
    "gn:timezone":"Asia/Shanghai",
    "iso:country":"CN",
    "name:zho_x_preferred":[
        "\u53d1\u6ce5\u6751"
    ],
    "wof:name":"Fanicun",
    "wof:placetype":"locality"
},
  "geometry": {"coordinates":[103.063,27.0232],"type":"Point"}
}