{
  "type": "Feature",
  "properties": {
    "gn:admin1_code":"18",
    "gn:asciiname":"Guojiawan",
    "gn:country_code":"CN",
    "gn:dem":1601,
    "gn:feature_class":"P",
    "gn:feature_code":"PPL",
    "gn:name":"Guojiawan",
    "gn:population":0,
    "gn:timezone":"Asia/Shanghai",
    "iso:country":"CN",
    "name:zho_x_preferred":[
        "\u90ed\u5bb6\u6e7e"
    ],
    "wof:name":"Guojiawan",
    "wof:placetype":"locality"
},
  "geometry": {"coordinates":[104.834,24.917],"type":"Point"}
}