{
  "type": "Feature",
  "properties": {
    "gn:admin1_code":"11.0",
    "gn:asciiname":"Ebaotang",
    "gn:country_code":"CN",
    "gn:dem":429,
    "gn:feature_class":"P",
    "gn:feature_code":"PPL",
    "gn:name":"Ebaotang",
    "gn:population":0,
    "gn:timezone":"Asia/Shanghai",
    "iso:country":"CN",
    "name:zho_x_preferred":[
        "\u9e45\u62b1\u5858"
    ],
    "wof:name":"Ebaotang",
    "wof:placetype":"locality"
},
  "geometry": {"coordinates":[111.46393,28.6159],"type":"Point"}
}