{
  "type": "Feature",
  "properties": {
    "gn:admin1_code":"16.0",
    "gn:asciiname":"Naliao",
    "gn:country_code":"CN",
    "gn:dem":143,
    "gn:feature_class":"P",
    "gn:feature_code":"PPL",
    "gn:name":"Naliao",
    "gn:population":0,
    "gn:timezone":"Asia/Shanghai",
    "iso:country":"CN",
    "name:zho_x_preferred":[
        "\u90a3\u5ed6"
    ],
    "wof:name":"Naliao",
    "wof:placetype":"locality"
},
  "geometry": {"coordinates":[107.182,23.6337],"type":"Point"}
}