{
  "type": "Feature",
  "properties": {
    "gn:admin1_code":"7.0",
    "gn:asciiname":"Folingtang",
    "gn:country_code":"CN",
    "gn:dem":247,
    "gn:feature_class":"P",
    "gn:feature_code":"PPL",
    "gn:name":"Folingtang",
    "gn:population":0,
    "gn:timezone":"Asia/Shanghai",
    "iso:country":"CN",
    "name:zho_x_preferred":[
        "\u4f5b\u5cad\u5858"
    ],
    "wof:name":"Folingtang",
    "wof:placetype":"locality"
},
  "geometry": {"coordinates":[117.79194,27.43686],"type":"Point"}
}