{
  "type": "Feature",
  "properties": {
    "gn:admin1_code":"04",
    "gn:asciiname":"Sanguandian",
    "gn:country_code":"CN",
    "gn:dem":10,
    "gn:feature_class":"P",
    "gn:feature_code":"PPL",
    "gn:name":"Sanguandian",
    "gn:population":0,
    "gn:timezone":"Asia/Shanghai",
    "iso:country":"CN",
    "name:und_x_variant":[
        "San-kuan-t\u2019ou",
        "San-kuan-tien",
        "Sanguandian"
    ],
    "wof:name":"Sanguandian",
    "wof:placetype":"locality"
},
  "geometry": {"coordinates":[120.34448999999999,31.9236],"type":"Point"}
}