{
  "type": "Feature",
  "properties": {
    "gn:admin1_code":"5.0",
    "gn:asciiname":"Erlongshan",
    "gn:country_code":"CN",
    "gn:dem":143,
    "gn:feature_class":"P",
    "gn:feature_code":"PPL",
    "gn:name":"Erlongshan",
    "gn:population":0,
    "gn:timezone":"Asia/Shanghai",
    "iso:country":"CN",
    "name:zho_x_preferred":[
        "\u4e8c\u9f99\u5c71"
    ],
    "wof:name":"Erlongshan",
    "wof:placetype":"locality"
},
  "geometry": {"coordinates":[123.29303,44.7173],"type":"Point"}
}