{
  "type": "Feature",
  "properties": {
    "gn:admin1_code":"19.0",
    "gn:asciiname":"Tangjiagou",
    "gn:country_code":"CN",
    "gn:dem":80,
    "gn:feature_class":"P",
    "gn:feature_code":"PPL",
    "gn:name":"Tangjiagou",
    "gn:population":0,
    "gn:timezone":"Asia/Shanghai",
    "iso:country":"CN",
    "name:und_x_variant":[
        "\u5510\u5bb6\u6c9f"
    ],
    "wof:name":"Tangjiagou",
    "wof:placetype":"locality"
},
  "geometry": {"coordinates":[123.86329000000001,40.29942],"type":"Point"}
}