{
  "type": "Feature",
  "properties": {
    "gn:admin1_code":"26.0",
    "gn:asciiname":"Shejiacun",
    "gn:country_code":"CN",
    "gn:dem":1022,
    "gn:feature_class":"P",
    "gn:feature_code":"PPL",
    "gn:name":"Shejiacun",
    "gn:population":0,
    "gn:timezone":"Asia/Shanghai",
    "iso:country":"CN",
    "name:zho_x_preferred":[
        "\u820d\u5bb6\u6751"
    ],
    "wof:name":"Shejiacun",
    "wof:placetype":"locality"
},
  "geometry": {"coordinates":[110.07928,36.57249],"type":"Point"}
}