{
  "type": "Feature",
  "properties": {
    "gn:admin1_code":"11.0",
    "gn:asciiname":"Daqiubei",
    "gn:country_code":"CN",
    "gn:dem":445,
    "gn:feature_class":"P",
    "gn:feature_code":"PPL",
    "gn:name":"Daqiubei",
    "gn:population":0,
    "gn:timezone":"Asia/Shanghai",
    "iso:country":"CN",
    "name:zho_x_preferred":[
        "\u5927\u4e18\u80cc"
    ],
    "wof:name":"Daqiubei",
    "wof:placetype":"locality"
},
  "geometry": {"coordinates":[109.67982000000001,27.08289000000001],"type":"Point"}
}