{
  "type": "Feature",
  "properties": {
    "gn:admin1_code":"05",
    "gn:asciiname":"Paoziyuan",
    "gn:country_code":"CN",
    "gn:dem":154,
    "gn:feature_class":"P",
    "gn:feature_code":"PPL",
    "gn:name":"Paoziyuan",
    "gn:population":0,
    "gn:timezone":"Asia/Shanghai",
    "iso:country":"CN",
    "name:und_x_variant":[
        "\u72cd\u5b50\u56ed",
        "P\u2019ao-tzu-ch\u2019\u00fcan"
    ],
    "wof:name":"Paoziyuan",
    "wof:placetype":"locality"
},
  "geometry": {"coordinates":[125.77212,40.91496],"type":"Point"}
}