{
  "type": "Feature",
  "properties": {
    "gn:admin1_code":"29",
    "gn:asciiname":"Nalao",
    "gn:country_code":"CN",
    "gn:dem":977,
    "gn:feature_class":"P",
    "gn:feature_code":"PPL",
    "gn:name":"Nalao",
    "gn:population":0,
    "gn:timezone":"Asia/Shanghai",
    "iso:country":"CN",
    "name:zho_x_preferred":[
        "\u90a3\u52b3"
    ],
    "wof:name":"Nalao",
    "wof:placetype":"locality"
},
  "geometry": {"coordinates":[105.41200000000001,23.9599],"type":"Point"}
}