{
  "type": "Feature",
  "properties": {
    "gn:admin1_code":"6.0",
    "gn:asciiname":"Caodan",
    "gn:country_code":"CN",
    "gn:dem":2356,
    "gn:feature_class":"P",
    "gn:feature_code":"PPL",
    "gn:name":"Caodan",
    "gn:population":0,
    "gn:timezone":"Asia/Shanghai",
    "iso:country":"CN",
    "name:und_x_variant":[
        "\u66f9\u65e6"
    ],
    "wof:name":"Caodan",
    "wof:placetype":"locality"
},
  "geometry": {"coordinates":[102.66252,35.91909000000001],"type":"Point"}
}