{
  "type": "Feature",
  "properties": {
    "gn:admin1_code":"32.0",
    "gn:asciiname":"Mujiaokeng",
    "gn:country_code":"CN",
    "gn:dem":339,
    "gn:feature_class":"P",
    "gn:feature_code":"PPL",
    "gn:name":"Mujiaokeng",
    "gn:population":0,
    "gn:timezone":"Asia/Shanghai",
    "iso:country":"CN",
    "name:zho_x_preferred":[
        "\u6728\u89d2\u5751"
    ],
    "wof:name":"Mujiaokeng",
    "wof:placetype":"locality"
},
  "geometry": {"coordinates":[106.39700000000001,30.8754],"type":"Point"}
}