{
  "type": "Feature",
  "properties": {
    "gn:admin1_code":"13",
    "gn:asciiname":"Boqi",
    "gn:country_code":"CN",
    "gn:dem":1188,
    "gn:feature_class":"P",
    "gn:feature_code":"PPL",
    "gn:name":"Boqi",
    "gn:population":0,
    "gn:timezone":"Asia/Shanghai",
    "iso:country":"CN",
    "name:und_x_variant":[
        "\u535a\u5176"
    ],
    "wof:name":"Boqi",
    "wof:placetype":"locality"
},
  "geometry": {"coordinates":[80.34047,41.28184],"type":"Point"}
}