{
  "type": "Feature",
  "properties": {
    "gn:admin1_code":"16.0",
    "gn:asciiname":"Yexian",
    "gn:country_code":"CN",
    "gn:dem":125,
    "gn:feature_class":"P",
    "gn:feature_code":"PPL",
    "gn:name":"Yexian",
    "gn:population":0,
    "gn:timezone":"Asia/Shanghai",
    "iso:country":"CN",
    "name:zho_x_preferred":[
        "\u91ce\u4ed9"
    ],
    "wof:name":"Yexian",
    "wof:placetype":"locality"
},
  "geometry": {"coordinates":[110.571,23.82800000000001],"type":"Point"}
}