{
  "type": "Feature",
  "properties": {
    "gn:admin1_code":"30.0",
    "gn:asciiname":"Leigongba",
    "gn:country_code":"CN",
    "gn:dem":324,
    "gn:feature_class":"P",
    "gn:feature_code":"PPL",
    "gn:name":"Leigongba",
    "gn:population":0,
    "gn:timezone":"Asia/Shanghai",
    "iso:country":"CN",
    "name:zho_x_preferred":[
        "\u96f7\u516c\u575d"
    ],
    "wof:name":"Leigongba",
    "wof:placetype":"locality"
},
  "geometry": {"coordinates":[113.95921,24.40702000000001],"type":"Point"}
}