{
  "type": "Feature",
  "properties": {
    "gn:admin1_code":"30.0",
    "gn:asciiname":"Suxi Ercun",
    "gn:country_code":"CN",
    "gn:dem":16,
    "gn:feature_class":"P",
    "gn:feature_code":"PPL",
    "gn:name":"Suxi Ercun",
    "gn:population":0,
    "gn:timezone":"Asia/Shanghai",
    "iso:country":"CN",
    "name:zho_x_preferred":[
        "\u8607\u897f\u4e8c\u6751"
    ],
    "wof:name":"Suxi Ercun",
    "wof:placetype":"locality"
},
  "geometry": {"coordinates":[112.69484,23.12371],"type":"Point"}
}