{
  "type": "Feature",
  "properties": {
    "gn:admin1_code":"32.0",
    "gn:asciiname":"Jiefangcun",
    "gn:country_code":"CN",
    "gn:dem":376,
    "gn:feature_class":"P",
    "gn:feature_code":"PPL",
    "gn:name":"Jiefangcun",
    "gn:population":0,
    "gn:timezone":"Asia/Shanghai",
    "iso:country":"CN",
    "name:zho_x_preferred":[
        "\u89e3\u653e\u6751"
    ],
    "wof:name":"Jiefangcun",
    "wof:placetype":"locality"
},
  "geometry": {"coordinates":[104.98699999999999,30.7135],"type":"Point"}
}