{
  "type": "Feature",
  "properties": {
    "gn:admin1_code":"11",
    "gn:asciiname":"Hexietang",
    "gn:country_code":"CN",
    "gn:dem":359,
    "gn:feature_class":"P",
    "gn:feature_code":"PPL",
    "gn:name":"Hexietang",
    "gn:population":0,
    "gn:timezone":"Asia/Shanghai",
    "iso:country":"CN",
    "name:und_x_variant":[
        "\u8377\u53f6\u5858",
        "Hexietang"
    ],
    "wof:name":"Hexietang",
    "wof:placetype":"locality"
},
  "geometry": {"coordinates":[111.60944000000001,25.695],"type":"Point"}
}