{
  "type": "Feature",
  "properties": {
    "gn:admin1_code":"26.0",
    "gn:asciiname":"Tudigou",
    "gn:country_code":"CN",
    "gn:dem":945,
    "gn:feature_class":"P",
    "gn:feature_code":"PPL",
    "gn:name":"Tudigou",
    "gn:population":0,
    "gn:timezone":"Asia/Shanghai",
    "iso:country":"CN",
    "name:zho_x_preferred":[
        "\u571f\u5730\u6c9f"
    ],
    "wof:name":"Tudigou",
    "wof:placetype":"locality"
},
  "geometry": {"coordinates":[108.92912,33.51417],"type":"Point"}
}