{
  "type": "Feature",
  "properties": {
    "gn:admin1_code":"32.0",
    "gn:asciiname":"Tanggang",
    "gn:country_code":"CN",
    "gn:dem":3364,
    "gn:feature_class":"P",
    "gn:feature_code":"PPL",
    "gn:name":"Tanggang",
    "gn:population":0,
    "gn:timezone":"Asia/Shanghai",
    "iso:country":"CN",
    "name:zho_x_preferred":[
        "\u5510\u5c97"
    ],
    "wof:name":"Tanggang",
    "wof:placetype":"locality"
},
  "geometry": {"coordinates":[101.05826,29.71016],"type":"Point"}
}