{
  "type": "Feature",
  "properties": {
    "gn:admin1_code":"31",
    "gn:asciiname":"Sanjiaoting Nongchang",
    "gn:country_code":"CN",
    "gn:dem":48,
    "gn:feature_class":"P",
    "gn:feature_code":"PPLF",
    "gn:name":"Sanjiaoting Nongchang",
    "gn:population":0,
    "gn:timezone":"Asia/Shanghai",
    "iso:country":"CN",
    "wof:name":"Sanjiaoting Nongchang",
    "wof:placetype":"locality"
},
  "geometry": {"coordinates":[110.57971999999999,19.4175],"type":"Point"}
}