{
  "type": "Feature",
  "properties": {
    "gn:admin1_code":"26.0",
    "gn:asciiname":"Huangbaicun",
    "gn:country_code":"CN",
    "gn:dem":550,
    "gn:feature_class":"P",
    "gn:feature_code":"PPL",
    "gn:name":"Huangbaicun",
    "gn:population":0,
    "gn:timezone":"Asia/Shanghai",
    "iso:country":"CN",
    "name:zho_x_preferred":[
        "\u9ec4\u67cf\u6751"
    ],
    "wof:name":"Huangbaicun",
    "wof:placetype":"locality"
},
  "geometry": {"coordinates":[110.91594000000001,33.44974000000001],"type":"Point"}
}