{
  "type": "Feature",
  "properties": {
    "gn:admin1_code":"11",
    "gn:asciiname":"Longzhu",
    "gn:country_code":"CN",
    "gn:dem":254,
    "gn:feature_class":"P",
    "gn:feature_code":"PPL",
    "gn:name":"Longzhu",
    "gn:population":0,
    "gn:timezone":"Asia/Shanghai",
    "iso:country":"CN",
    "name:zho_x_preferred":[
        "\u9f99\u73e0"
    ],
    "wof:name":"Longzhu",
    "wof:placetype":"locality"
},
  "geometry": {"coordinates":[112.28417,25.97694],"type":"Point"}
}