{
  "type": "Feature",
  "properties": {
    "gn:admin1_code":"26.0",
    "gn:asciiname":"Guaizaoba",
    "gn:country_code":"CN",
    "gn:dem":1074,
    "gn:feature_class":"P",
    "gn:feature_code":"PPL",
    "gn:name":"Guaizaoba",
    "gn:population":0,
    "gn:timezone":"Asia/Shanghai",
    "iso:country":"CN",
    "name:zho_x_preferred":[
        "\u62d0\u67a3\u575d"
    ],
    "wof:name":"Guaizaoba",
    "wof:placetype":"locality"
},
  "geometry": {"coordinates":[109.54187,31.7682],"type":"Point"}
}