{
  "type": "Feature",
  "properties": {
    "gn:admin1_code":"15.0",
    "gn:asciiname":"Bama",
    "gn:country_code":"CN",
    "gn:dem":2378,
    "gn:feature_class":"P",
    "gn:feature_code":"PPL",
    "gn:name":"Bama",
    "gn:population":0,
    "gn:timezone":"Asia/Shanghai",
    "iso:country":"CN",
    "name:ben_x_preferred":[
        "\u09ac\u09be\u09ae\u09be"
    ],
    "name:cat_x_preferred":[
        "Bama"
    ],
    "name:ceb_x_preferred":[
        "Bama"
    ],
    "name:deu_x_preferred":[
        "Bama"
    ],
    "name:ell_x_preferred":[
        "\u039c\u03c0\u03ac\u03bc\u03b1"
    ],
    "name:fas_x_preferred":[
        "\u0628\u0627\u0645\u0627"
    ],
    "name:fra_x_preferred":[
        "Bama"
    ],
    "name:glg_x_preferred":[
        "Bama"
    ],
    "name:heb_x_preferred":[
        "\u05d1\u05de\u05d4"
    ],
    "name:hin_x_preferred":[
        "\u092c\u093e\u092e\u093e"
    ],
    "name:hun_x_preferred":[
        "Bama"
    ],
    "name:ind_x_preferred":[
        "Bama"
    ],
    "name:ita_x_preferred":[
        "Bama"
    ],
    "name:jpn_x_preferred":[
        "\u30d0\u30de"
    ],
    "name:kor_x_preferred":[
        "\ubc14\ub9c8"
    ],
    "name:nld_x_preferred":[
        "Bama"
    ],
    "name:nor_x_preferred":[
        "Bama"
    ],
    "name:rus_x_preferred":[
        "\u0411\u0430\u043c\u0430"
    ],
    "name:swe_x_preferred":[
        "Bama"
    ],
    "name:tur_x_preferred":[
        "Bama"
    ],
    "name:ukr_x_preferred":[
        "\u0411\u0430\u043c\u0430"
    ],
    "name:und_x_variant":[
        "\u53ed\u561b"
    ],
    "name:urd_x_preferred":[
        "\u0628\u0627\u0645\u0627"
    ],
    "name:vie_x_preferred":[
        "Bama"
    ],
    "name:zho_cn_x_preferred":[
        "\u5df4\u9a6c"
    ],
    "name:zho_tw_x_preferred":[
        "\u5df4\u99ac"
    ],
    "wof:name":"Bama",
    "wof:placetype":"locality"
},
  "geometry": {"coordinates":[104.48521,34.63681],"type":"Point"}
}