{
  "type": "Feature",
  "properties": {
    "gn:admin1_code":"15.0",
    "gn:asciiname":"Bama",
    "gn:country_code":"CN",
    "gn:dem":2378,
    "gn:feature_class":"P",
    "gn:feature_code":"PPL",
    "gn:name":"Bama",
    "gn:population":0,
    "gn:timezone":"Asia/Shanghai",
    "iso:country":"CN",
    "name:cat_x_preferred":[
        "Bama"
    ],
    "name:ceb_x_preferred":[
        "Bama"
    ],
    "name:deu_x_preferred":[
        "Bama"
    ],
    "name:fra_x_preferred":[
        "Bama"
    ],
    "name:glg_x_preferred":[
        "Bama"
    ],
    "name:ita_x_preferred":[
        "Bama"
    ],
    "name:nld_x_preferred":[
        "Bama"
    ],
    "name:nor_x_preferred":[
        "Bama"
    ],
    "name:swe_x_preferred":[
        "Bama"
    ],
    "name:und_x_variant":[
        "\u53ed\u561b"
    ],
    "wof:name":"Bama",
    "wof:placetype":"locality"
},
  "geometry": {"coordinates":[104.48521,34.63681],"type":"Point"}
}