{
  "type": "Feature",
  "properties": {
    "gn:admin1_code":"7.0",
    "gn:asciiname":"Suilin",
    "gn:country_code":"CN",
    "gn:dem":173,
    "gn:feature_class":"P",
    "gn:feature_code":"PPL",
    "gn:name":"Suilin",
    "gn:population":0,
    "gn:timezone":"Asia/Shanghai",
    "iso:country":"CN",
    "name:zho_x_preferred":[
        "\u9042\u6797"
    ],
    "wof:name":"Suilin",
    "wof:placetype":"locality"
},
  "geometry": {"coordinates":[117.36818,25.34622],"type":"Point"}
}