{
  "type": "Feature",
  "properties": {
    "gn:admin1_code":"16.0",
    "gn:asciiname":"Liushu",
    "gn:country_code":"CN",
    "gn:dem":134,
    "gn:feature_class":"P",
    "gn:feature_code":"PPL",
    "gn:name":"Liushu",
    "gn:population":0,
    "gn:timezone":"Asia/Shanghai",
    "iso:country":"CN",
    "name:zho_x_preferred":[
        "\u67f3\u6811"
    ],
    "wof:name":"Liushu",
    "wof:placetype":"locality"
},
  "geometry": {"coordinates":[108.101,23.3723],"type":"Point"}
}