{
  "type": "Feature",
  "properties": {
    "gn:admin1_code":"5.0",
    "gn:asciiname":"Qiansanhetun",
    "gn:country_code":"CN",
    "gn:dem":145,
    "gn:feature_class":"P",
    "gn:feature_code":"PPL",
    "gn:name":"Qiansanhetun",
    "gn:population":0,
    "gn:timezone":"Asia/Shanghai",
    "iso:country":"CN",
    "name:zho_x_preferred":[
        "\u524d\u4e09\u5408\u5c6f"
    ],
    "wof:name":"Qiansanhetun",
    "wof:placetype":"locality"
},
  "geometry": {"coordinates":[123.29075,44.64463],"type":"Point"}
}