{
  "type": "Feature",
  "properties": {
    "gn:admin1_code":"26.0",
    "gn:asciiname":"Niangniangmiaocun",
    "gn:country_code":"CN",
    "gn:dem":1063,
    "gn:feature_class":"P",
    "gn:feature_code":"PPL",
    "gn:name":"Niangniangmiaocun",
    "gn:population":0,
    "gn:timezone":"Asia/Shanghai",
    "iso:country":"CN",
    "name:und_x_variant":[
        "\u5a18\u5a18\u5e99\u6751"
    ],
    "wof:name":"Niangniangmiaocun",
    "wof:placetype":"locality"
},
  "geometry": {"coordinates":[106.92021,33.72077],"type":"Point"}
}