{
  "type": "Feature",
  "properties": {
    "gn:admin1_code":"32.0",
    "gn:asciiname":"Sandaping",
    "gn:country_code":"CN",
    "gn:dem":3140,
    "gn:feature_class":"P",
    "gn:feature_code":"PPL",
    "gn:name":"Sandaping",
    "gn:population":0,
    "gn:timezone":"Asia/Shanghai",
    "iso:country":"CN",
    "name:zho_x_preferred":[
        "\u4e09\u5927\u576a"
    ],
    "wof:name":"Sandaping",
    "wof:placetype":"locality"
},
  "geometry": {"coordinates":[101.97145,32.181],"type":"Point"}
}