{
  "type": "Feature",
  "properties": {
    "gn:admin1_code":"7.0",
    "gn:asciiname":"Chengxi",
    "gn:country_code":"CN",
    "gn:dem":401,
    "gn:feature_class":"P",
    "gn:feature_code":"PPL",
    "gn:name":"Chengxi",
    "gn:population":0,
    "gn:timezone":"Asia/Shanghai",
    "iso:country":"CN",
    "name:und_x_variant":[
        "\u57ce\u6eaa"
    ],
    "name:zho_x_preferred":[
        "\u57ce\u6eaa"
    ],
    "wof:name":"Chengxi",
    "wof:placetype":"locality"
},
  "geometry": {"coordinates":[116.61503999999999,25.61362],"type":"Point"}
}