{
  "type": "Feature",
  "properties": {
    "gn:admin1_code":"14.0",
    "gn:asciiname":"Zhelai",
    "gn:country_code":"CN",
    "gn:dem":4398,
    "gn:feature_class":"P",
    "gn:feature_code":"PPL",
    "gn:name":"Zhelai",
    "gn:population":0,
    "gn:timezone":"Asia/Urumqi",
    "iso:country":"CN",
    "name:zho_x_preferred":[
        "\u54f2\u6765"
    ],
    "wof:name":"Zhelai",
    "wof:placetype":"locality"
},
  "geometry": {"coordinates":[86.4323,28.7746],"type":"Point"}
}