{
  "type": "Feature",
  "properties": {
    "gn:admin1_code":"4.0",
    "gn:asciiname":"Zhuzhuang",
    "gn:country_code":"CN",
    "gn:dem":3,
    "gn:feature_class":"P",
    "gn:feature_code":"PPL",
    "gn:name":"Zhuzhuang",
    "gn:population":0,
    "gn:timezone":"Asia/Shanghai",
    "iso:country":"CN",
    "name:zho_x_preferred":[
        "Zhuzhuang"
    ],
    "name:zho_x_variant":[
        "\u6731\u5e84"
    ],
    "wof:name":"Zhuzhuang",
    "wof:placetype":"locality"
},
  "geometry": {"coordinates":[119.011,34.50891],"type":"Point"}
}