{
  "type": "Feature",
  "properties": {
    "gn:admin1_code":"25.0",
    "gn:asciiname":"Xishen Mazhuang",
    "gn:country_code":"CN",
    "gn:dem":27,
    "gn:feature_class":"P",
    "gn:feature_code":"PPL",
    "gn:name":"Xishen Mazhuang",
    "gn:population":0,
    "gn:timezone":"Asia/Shanghai",
    "iso:country":"CN",
    "name:zho_x_preferred":[
        "\u897f\u6c88\u9a6c\u5e84"
    ],
    "wof:name":"Xishen Mazhuang",
    "wof:placetype":"locality"
},
  "geometry": {"coordinates":[119.33301000000002,35.46175],"type":"Point"}
}