{
  "type": "Feature",
  "properties": {
    "gn:admin1_code":"31.0",
    "gn:asciiname":"Taiping Shidui",
    "gn:country_code":"CN",
    "gn:dem":382,
    "gn:feature_class":"P",
    "gn:feature_code":"PPLF",
    "gn:name":"Taiping Shidui",
    "gn:population":0,
    "gn:timezone":"Asia/Shanghai",
    "iso:country":"CN",
    "name:und_x_variant":[
        "\u592a\u5e73\u5341\u961f"
    ],
    "wof:name":"Taiping Shidui",
    "wof:placetype":"locality"
},
  "geometry": {"coordinates":[109.93908,18.78112],"type":"Point"}
}