{
  "type": "Feature",
  "properties": {
    "gn:admin1_code":"7.0",
    "gn:asciiname":"Chailing",
    "gn:country_code":"CN",
    "gn:dem":590,
    "gn:feature_class":"P",
    "gn:feature_code":"PPL",
    "gn:name":"Chailing",
    "gn:population":0,
    "gn:timezone":"Asia/Shanghai",
    "iso:country":"CN",
    "name:zho_x_preferred":[
        "\u67f4\u5cad"
    ],
    "wof:name":"Chailing",
    "wof:placetype":"locality"
},
  "geometry": {"coordinates":[118.68913000000001,25.9583],"type":"Point"}
}