{
  "type": "Feature",
  "properties": {
    "gn:admin1_code":"19.0",
    "gn:asciiname":"Dianxinzi",
    "gn:country_code":"CN",
    "gn:dem":166,
    "gn:feature_class":"P",
    "gn:feature_code":"PPL",
    "gn:name":"Dianxinzi",
    "gn:population":0,
    "gn:timezone":"Asia/Shanghai",
    "iso:country":"CN",
    "name:und_x_variant":[
        "Lizifangxiadui",
        "\u6817\u5b50\u623f\u4e0b\u961f",
        "Dianxinzi",
        "\u7538\u5fc3\u5b50"
    ],
    "name:zho_x_preferred":[
        "\u6817\u5b50\u623f\u4e0b\u961f"
    ],
    "wof:name":"Dianxinzi",
    "wof:placetype":"locality"
},
  "geometry": {"coordinates":[122.93592,40.04845],"type":"Point"}
}