{
  "type": "Feature",
  "properties": {
    "gn:admin1_code":"25",
    "gn:asciiname":"Chaihushan",
    "gn:country_code":"CN",
    "gn:dem":123,
    "gn:feature_class":"P",
    "gn:feature_code":"PPL",
    "gn:name":"Chaihushan",
    "gn:population":0,
    "gn:timezone":"Asia/Shanghai",
    "iso:country":"CN",
    "name:zho_x_preferred":[
        "\u67f4\u80e1\u5c71"
    ],
    "wof:name":"Chaihushan",
    "wof:placetype":"locality"
},
  "geometry": {"coordinates":[118.27200000000001,35.3724],"type":"Point"}
}