{
  "type": "Feature",
  "properties": {
    "gn:admin1_code":"16.0",
    "gn:asciiname":"Yangchengtang",
    "gn:country_code":"CN",
    "gn:dem":54,
    "gn:feature_class":"P",
    "gn:feature_code":"PPL",
    "gn:name":"Yangchengtang",
    "gn:population":0,
    "gn:timezone":"Asia/Shanghai",
    "iso:country":"CN",
    "name:zho_x_preferred":[
        "\u6d0b\u57ce\u5858"
    ],
    "wof:name":"Yangchengtang",
    "wof:placetype":"locality"
},
  "geometry": {"coordinates":[110.423,23.398],"type":"Point"}
}