{
  "type": "Feature",
  "properties": {
    "gn:admin1_code":"19.0",
    "gn:asciiname":"Zhangtuncun",
    "gn:country_code":"CN",
    "gn:dem":28,
    "gn:feature_class":"P",
    "gn:feature_code":"PPL",
    "gn:name":"Zhangtuncun",
    "gn:population":0,
    "gn:timezone":"Asia/Shanghai",
    "iso:country":"CN",
    "name:zho_x_preferred":[
        "\u5f20\u5c6f\u6751"
    ],
    "wof:name":"Zhangtuncun",
    "wof:placetype":"locality"
},
  "geometry": {"coordinates":[123.01600000000001,41.8328],"type":"Point"}
}