{
  "type": "Feature",
  "properties": {
    "gn:admin1_code":"10",
    "gn:asciiname":"Zhangbei Muchang",
    "gn:country_code":"CN",
    "gn:dem":1379,
    "gn:feature_class":"P",
    "gn:feature_code":"PPLF",
    "gn:name":"Zhangbei Muchang",
    "gn:population":0,
    "gn:timezone":"Asia/Shanghai",
    "iso:country":"CN",
    "wof:name":"Zhangbei Muchang",
    "wof:placetype":"locality"
},
  "geometry": {"coordinates":[114.96666999999999,41.41667],"type":"Point"}
}