{
  "type": "Feature",
  "properties": {
    "gn:admin1_code":"29.0",
    "gn:asciiname":"Xiaoduohong",
    "gn:country_code":"CN",
    "gn:dem":2136,
    "gn:feature_class":"P",
    "gn:feature_code":"PPL",
    "gn:name":"Xiaoduohong",
    "gn:population":0,
    "gn:timezone":"Asia/Shanghai",
    "iso:country":"CN",
    "name:zho_x_preferred":[
        "\u5c0f\u591a\u7ea2"
    ],
    "wof:name":"Xiaoduohong",
    "wof:placetype":"locality"
},
  "geometry": {"coordinates":[103.15900000000001,25.9216],"type":"Point"}
}