{
  "type": "Feature",
  "properties": {
    "gn:admin1_code":"33.0",
    "gn:asciiname":"Xuyangqiao",
    "gn:country_code":"CN",
    "gn:dem":326,
    "gn:feature_class":"P",
    "gn:feature_code":"PPL",
    "gn:name":"Xuyangqiao",
    "gn:population":0,
    "gn:timezone":"Asia/Shanghai",
    "iso:country":"CN",
    "name:zho_x_preferred":[
        "\u5f90\u6768\u6865"
    ],
    "wof:name":"Xuyangqiao",
    "wof:placetype":"locality"
},
  "geometry": {"coordinates":[108.97756,28.71599],"type":"Point"}
}