{
  "type": "Feature",
  "properties": {
    "gn:admin1_code":"14.0",
    "gn:asciiname":"Zaku",
    "gn:country_code":"CN",
    "gn:dem":4067,
    "gn:feature_class":"P",
    "gn:feature_code":"PPL",
    "gn:name":"Zaku",
    "gn:population":0,
    "gn:timezone":"Asia/Urumqi",
    "iso:country":"CN",
    "name:tha_x_preferred":[
        "\u0e0b\u0e32\u0e04\u0e38\u0e17\u0e39\u0e27\u0e4c"
    ],
    "name:zho_x_preferred":[
        "\u6742\u5e93"
    ],
    "wof:name":"Zaku",
    "wof:placetype":"locality"
},
  "geometry": {"coordinates":[98.08101000000001,30.86432000000001],"type":"Point"}
}