{
  "type": "Feature",
  "properties": {
    "gn:admin1_code":"16.0",
    "gn:asciiname":"Guilong",
    "gn:country_code":"CN",
    "gn:dem":296,
    "gn:feature_class":"P",
    "gn:feature_code":"PPL",
    "gn:name":"Guilong",
    "gn:population":0,
    "gn:timezone":"Asia/Shanghai",
    "iso:country":"CN",
    "name:zho_x_preferred":[
        "\u8d35\u9f99"
    ],
    "wof:name":"Guilong",
    "wof:placetype":"locality"
},
  "geometry": {"coordinates":[108.63200000000001,23.1374],"type":"Point"}
}