{
  "type": "Feature",
  "properties": {
    "gn:admin1_code":"5.0",
    "gn:asciiname":"Liushibacun",
    "gn:country_code":"CN",
    "gn:dem":149,
    "gn:feature_class":"P",
    "gn:feature_code":"PPL",
    "gn:name":"Liushibacun",
    "gn:population":0,
    "gn:timezone":"Asia/Shanghai",
    "iso:country":"CN",
    "name:zho_x_preferred":[
        "\u516d\u5341\u516b\u6751"
    ],
    "wof:name":"Liushibacun",
    "wof:placetype":"locality"
},
  "geometry": {"coordinates":[123.53898999999998,44.4231],"type":"Point"}
}