{
  "type": "Feature",
  "properties": {
    "gn:admin1_code":"15.0",
    "gn:asciiname":"Yuanjialeng",
    "gn:country_code":"CN",
    "gn:dem":1813,
    "gn:feature_class":"P",
    "gn:feature_code":"PPL",
    "gn:name":"Yuanjialeng",
    "gn:population":0,
    "gn:timezone":"Asia/Shanghai",
    "iso:country":"CN",
    "name:zho_x_preferred":[
        "\u8881\u5bb6\u5844"
    ],
    "wof:name":"Yuanjialeng",
    "wof:placetype":"locality"
},
  "geometry": {"coordinates":[105.02202,33.45685],"type":"Point"}
}