{
  "type": "Feature",
  "properties": {
    "gn:admin1_code":"30.0",
    "gn:asciiname":"Dafen",
    "gn:country_code":"CN",
    "gn:dem":-1,
    "gn:feature_class":"P",
    "gn:feature_code":"PPL",
    "gn:name":"Dafen",
    "gn:population":0,
    "gn:timezone":"Asia/Shanghai",
    "iso:country":"CN",
    "name:fra_x_preferred":[
        "Dafen"
    ],
    "name:nld_x_preferred":[
        "Dafen"
    ],
    "name:zho_x_preferred":[
        "\u5927\u6c7e"
    ],
    "wof:name":"Dafen",
    "wof:placetype":"locality"
},
  "geometry": {"coordinates":[113.67998,23.04564],"type":"Point"}
}