{
  "type": "Feature",
  "properties": {
    "gn:admin1_code":"11.0",
    "gn:asciiname":"Xiaotang",
    "gn:country_code":"CN",
    "gn:dem":198,
    "gn:feature_class":"P",
    "gn:feature_code":"PPL",
    "gn:name":"Xiaotang",
    "gn:population":0,
    "gn:timezone":"Asia/Shanghai",
    "iso:country":"CN",
    "name:und_x_variant":[
        "Xiaocha"
    ],
    "name:zho_x_preferred":[
        "\u6653\u5858"
    ],
    "name:zho_x_variant":[
        "\u6653\u69ce"
    ],
    "wof:name":"Xiaotang",
    "wof:placetype":"locality"
},
  "geometry": {"coordinates":[113.87819,26.96466],"type":"Point"}
}