{
  "type": "Feature",
  "properties": {
    "gn:admin1_code":"11.0",
    "gn:asciiname":"Songxikou",
    "gn:country_code":"CN",
    "gn:dem":172,
    "gn:feature_class":"P",
    "gn:feature_code":"PPL",
    "gn:name":"Songxikou",
    "gn:population":0,
    "gn:timezone":"Asia/Shanghai",
    "iso:country":"CN",
    "name:und_x_variant":[
        "Songxi"
    ],
    "name:zho_x_preferred":[
        "\u677e\u6eaa\u53e3"
    ],
    "wof:name":"Songxikou",
    "wof:placetype":"locality"
},
  "geometry": {"coordinates":[110.53057,28.60184000000001],"type":"Point"}
}