{
  "type": "Feature",
  "properties": {
    "gn:admin1_code":"9.0",
    "gn:asciiname":"Guoliang",
    "gn:country_code":"CN",
    "gn:dem":1067,
    "gn:feature_class":"P",
    "gn:feature_code":"PPL",
    "gn:name":"Guoliang",
    "gn:population":0,
    "gn:timezone":"Asia/Shanghai",
    "iso:country":"CN",
    "name:deu_x_preferred":[
        "Guoliang"
    ],
    "name:zho_x_preferred":[
        "\u90ed\u4eae"
    ],
    "wof:name":"Guoliang",
    "wof:placetype":"locality"
},
  "geometry": {"coordinates":[113.59589,35.73155],"type":"Point"}
}