{
  "type": "Feature",
  "properties": {
    "gn:admin1_code":"29.0",
    "gn:asciiname":"Qujia Yingpan",
    "gn:country_code":"CN",
    "gn:dem":1285,
    "gn:feature_class":"P",
    "gn:feature_code":"PPL",
    "gn:name":"Qujia Yingpan",
    "gn:population":0,
    "gn:timezone":"Asia/Shanghai",
    "iso:country":"CN",
    "name:zho_x_preferred":[
        "\u77bf\u5bb6\u8425\u76d8"
    ],
    "wof:name":"Qujia Yingpan",
    "wof:placetype":"locality"
},
  "geometry": {"coordinates":[103.89,27.8298],"type":"Point"}
}