{
  "type": "Feature",
  "properties": {
    "gn:admin1_code":"33.0",
    "gn:asciiname":"Gujingwan",
    "gn:country_code":"CN",
    "gn:dem":252,
    "gn:feature_class":"P",
    "gn:feature_code":"PPL",
    "gn:name":"Gujingwan",
    "gn:population":0,
    "gn:timezone":"Asia/Shanghai",
    "iso:country":"CN",
    "name:zho_x_preferred":[
        "\u9f13\u4e95\u6e7e"
    ],
    "wof:name":"Gujingwan",
    "wof:placetype":"locality"
},
  "geometry": {"coordinates":[107.85345,29.98661],"type":"Point"}
}