{
  "type": "Feature",
  "properties": {
    "gn:admin1_code":"26.0",
    "gn:asciiname":"Zhoujia",
    "gn:country_code":"CN",
    "gn:dem":379,
    "gn:feature_class":"P",
    "gn:feature_code":"PPL",
    "gn:name":"Zhoujia",
    "gn:population":0,
    "gn:timezone":"Asia/Shanghai",
    "iso:country":"CN",
    "name:zho_x_preferred":[
        "\u5468\u5bb6"
    ],
    "wof:name":"Zhoujia",
    "wof:placetype":"locality"
},
  "geometry": {"coordinates":[109.48641000000001,34.79932],"type":"Point"}
}