{
  "type": "Feature",
  "properties": {
    "gn:admin1_code":"16.0",
    "gn:asciiname":"Liu'ai",
    "gn:country_code":"CN",
    "gn:dem":585,
    "gn:feature_class":"P",
    "gn:feature_code":"PPL",
    "gn:name":"Liu\u2019ai",
    "gn:population":0,
    "gn:timezone":"Asia/Shanghai",
    "iso:country":"CN",
    "name:und_x_variant":[
        "Liu\u2019ai"
    ],
    "name:zho_x_preferred":[
        "\u516d\u7231"
    ],
    "wof:name":"Liu'ai",
    "wof:placetype":"locality"
},
  "geometry": {"coordinates":[106.29600000000001,24.3365],"type":"Point"}
}