{
  "type": "Feature",
  "properties": {
    "gn:admin1_code":"32.0",
    "gn:asciiname":"Guanyinqiao",
    "gn:country_code":"CN",
    "gn:dem":1810,
    "gn:feature_class":"P",
    "gn:feature_code":"PPL",
    "gn:name":"Guanyinqiao",
    "gn:population":0,
    "gn:timezone":"Asia/Shanghai",
    "iso:country":"CN",
    "name:zho_x_preferred":[
        "\u89c2\u97f3\u6865"
    ],
    "wof:name":"Guanyinqiao",
    "wof:placetype":"locality"
},
  "geometry": {"coordinates":[102.256,26.6786],"type":"Point"}
}