{
  "type": "Feature",
  "properties": {
    "gn:admin1_code":"14.0",
    "gn:asciiname":"Gatog",
    "gn:country_code":"CN",
    "gn:dem":4726,
    "gn:feature_class":"P",
    "gn:feature_code":"PPL",
    "gn:name":"Gatog",
    "gn:population":0,
    "gn:timezone":"Asia/Urumqi",
    "iso:country":"CN",
    "name:bod_x_preferred":[
        "Gatog"
    ],
    "name:zho_x_preferred":[
        "Gaduo"
    ],
    "name:zho_x_variant":[
        "\u560e\u591a"
    ],
    "wof:name":"Gatog",
    "wof:placetype":"locality"
},
  "geometry": {"coordinates":[89.301,28.701],"type":"Point"}
}