{
  "type": "Feature",
  "properties": {
    "gn:admin1_code":"30.0",
    "gn:asciiname":"Ma'aobei",
    "gn:country_code":"CN",
    "gn:dem":287,
    "gn:feature_class":"P",
    "gn:feature_code":"PPL",
    "gn:name":"Ma\u2019aobei",
    "gn:population":0,
    "gn:timezone":"Asia/Shanghai",
    "iso:country":"CN",
    "name:zho_x_preferred":[
        "Ma\u2019aobei"
    ],
    "name:zho_x_variant":[
        "\u9a6c\u5773\u80cc"
    ],
    "wof:name":"Ma'aobei",
    "wof:placetype":"locality"
},
  "geometry": {"coordinates":[113.02278,25.185],"type":"Point"}
}