{
  "type": "Feature",
  "properties": {
    "gn:admin1_code":"4.0",
    "gn:asciiname":"Xuanxu",
    "gn:country_code":"CN",
    "gn:dem":3,
    "gn:feature_class":"P",
    "gn:feature_code":"PPL",
    "gn:name":"Xuanxu",
    "gn:population":0,
    "gn:timezone":"Asia/Shanghai",
    "iso:country":"CN",
    "name:zho_x_preferred":[
        "Xuanxu"
    ],
    "name:zho_x_variant":[
        "\u5ba3\u5729"
    ],
    "wof:name":"Xuanxu",
    "wof:placetype":"locality"
},
  "geometry": {"coordinates":[119.62022,34.19236],"type":"Point"}
}