{
  "type": "Feature",
  "properties": {
    "gn:admin1_code":"9.0",
    "gn:asciiname":"Bailiping",
    "gn:country_code":"CN",
    "gn:dem":275,
    "gn:feature_class":"P",
    "gn:feature_code":"PPL",
    "gn:name":"Bailiping",
    "gn:population":0,
    "gn:timezone":"Asia/Shanghai",
    "iso:country":"CN",
    "name:und_x_variant":[
        "\u767d\u6817\u576a",
        "Bailiping"
    ],
    "wof:name":"Bailiping",
    "wof:placetype":"locality"
},
  "geometry": {"coordinates":[112.38706000000001,33.29756],"type":"Point"}
}