{
  "type": "Feature",
  "properties": {
    "gn:admin1_code":"10",
    "gn:asciiname":"Mingyuedian",
    "gn:country_code":"CN",
    "gn:dem":64,
    "gn:feature_class":"P",
    "gn:feature_code":"PPLA4",
    "gn:name":"Mingyuedian",
    "gn:population":0,
    "gn:timezone":"Asia/Shanghai",
    "iso:country":"CN",
    "name:und_x_variant":[
        "Ming-y\u00fceh-tien",
        "Mingyuedian",
        "\u660e\u6708\u5e97",
        "Mingyuedian Zhen",
        "\u660e\u6708\u5e97\u9547"
    ],
    "wof:name":"Mingyuedian",
    "wof:placetype":"locality"
},
  "geometry": {"coordinates":[114.89113,38.45602],"type":"Point"}
}