{
  "type": "Feature",
  "properties": {
    "gn:admin1_code":"3.0",
    "gn:asciiname":"Zhangzhou",
    "gn:country_code":"CN",
    "gn:dem":82,
    "gn:feature_class":"P",
    "gn:feature_code":"PPL",
    "gn:name":"Zhangzhou",
    "gn:population":0,
    "gn:timezone":"Asia/Shanghai",
    "iso:country":"CN",
    "name:afr_x_preferred":[
        "Zhangzhou"
    ],
    "name:ara_x_preferred":[
        "\u0632\u0647\u0627\u0646\u063a\u0632\u0647\u0648"
    ],
    "name:bul_x_preferred":[
        "\u0414\u0436\u0430\u043d\u0434\u0436\u043e\u0443"
    ],
    "name:cdo_x_preferred":[
        "Ci\u014fng-ci\u016d"
    ],
    "name:ceb_x_preferred":[
        "Zhangzhou"
    ],
    "name:ces_x_preferred":[
        "\u010cang-\u010dou"
    ],
    "name:dan_x_preferred":[
        "Zhangzhou"
    ],
    "name:deu_x_preferred":[
        "Zhangzhou"
    ],
    "name:epo_x_preferred":[
        "\u011can\u011dou"
    ],
    "name:est_x_preferred":[
        "Zhangzhou"
    ],
    "name:eus_x_preferred":[
        "Zhangzhou"
    ],
    "name:fas_x_preferred":[
        "\u062c\u0627\u0646\u06af\u062c\u0627\u0648"
    ],
    "name:fin_x_preferred":[
        "Zhangzhou"
    ],
    "name:fra_x_preferred":[
        "Zhangzhou"
    ],
    "name:hak_x_preferred":[
        "Ch\u00f4ng-ch\u00fb-s\u1e73"
    ],
    "name:hrv_x_preferred":[
        "Zhangzhou"
    ],
    "name:ind_x_preferred":[
        "Zhangzhou"
    ],
    "name:ita_x_preferred":[
        "Zhangzhou"
    ],
    "name:jpn_x_preferred":[
        "\u30b7\u30e7\u30a6\u5dde\u5e02"
    ],
    "name:kik_x_preferred":[
        "Zhangzhou"
    ],
    "name:kor_x_preferred":[
        "\uc7a5\uc800\uc6b0\uc2dc"
    ],
    "name:mlg_x_preferred":[
        "Zhangzhou"
    ],
    "name:nld_x_preferred":[
        "Zhangzhou"
    ],
    "name:nno_x_preferred":[
        "Zhangzhou"
    ],
    "name:nor_x_preferred":[
        "Zhangzhou"
    ],
    "name:pam_x_preferred":[
        "Zhangzhou"
    ],
    "name:pnb_x_preferred":[
        "\u0698\u0627\u0646\u06af\u0698\u0648"
    ],
    "name:pol_x_preferred":[
        "Zhangzhou"
    ],
    "name:por_x_preferred":[
        "Zhangzhou"
    ],
    "name:rus_x_preferred":[
        "\u0427\u0436\u0430\u043d\u0447\u0436\u043e\u0443"
    ],
    "name:sco_x_preferred":[
        "Zhangzhou"
    ],
    "name:spa_x_preferred":[
        "Zhangzhou"
    ],
    "name:srp_x_preferred":[
        "\u040f\u0430\u043d\u0433\u045f\u043e\u0443"
    ],
    "name:swe_x_preferred":[
        "Zhangzhou"
    ],
    "name:tgl_x_preferred":[
        "Zhangzhou"
    ],
    "name:tur_x_preferred":[
        "Zhangzhou"
    ],
    "name:uig_x_preferred":[
        "Jyangju shehiri"
    ],
    "name:und_x_variant":[
        "\u6a1f\u6d32"
    ],
    "name:urd_x_preferred":[
        "\u0698\u0627\u0646\u06af\u0698\u0648"
    ],
    "name:uzb_x_preferred":[
        "Chjenchjou"
    ],
    "name:vie_x_preferred":[
        "Ch\u01b0\u01a1ng Ch\u00e2u"
    ],
    "name:war_x_preferred":[
        "Zhangzhou"
    ],
    "name:wuu_x_preferred":[
        "\u6f33\u5dde\u5e02"
    ],
    "name:zho_x_preferred":[
        "\u6f33\u5dde\u5e02"
    ],
    "wof:name":"Zhangzhou",
    "wof:placetype":"locality"
},
  "geometry": {"coordinates":[117.44114,29.52653],"type":"Point"}
}