{
  "type": "Feature",
  "properties": {
    "gn:admin1_code":"16.0",
    "gn:asciiname":"Baida",
    "gn:country_code":"CN",
    "gn:dem":834,
    "gn:feature_class":"P",
    "gn:feature_code":"PPL",
    "gn:name":"Baida",
    "gn:population":0,
    "gn:timezone":"Asia/Shanghai",
    "iso:country":"CN",
    "name:zho_x_preferred":[
        "\u767e\u5927"
    ],
    "wof:name":"Baida",
    "wof:placetype":"locality"
},
  "geometry": {"coordinates":[105.837,23.3541],"type":"Point"}
}