{
  "type": "Feature",
  "properties": {
    "gn:admin1_code":"26.0",
    "gn:asciiname":"Daguocun",
    "gn:country_code":"CN",
    "gn:dem":691,
    "gn:feature_class":"P",
    "gn:feature_code":"PPL",
    "gn:name":"Daguocun",
    "gn:population":0,
    "gn:timezone":"Asia/Shanghai",
    "iso:country":"CN",
    "name:zho_x_preferred":[
        "\u5927\u90ed\u6751"
    ],
    "wof:name":"Daguocun",
    "wof:placetype":"locality"
},
  "geometry": {"coordinates":[110.16674999999999,35.20221],"type":"Point"}
}