{
  "type": "Feature",
  "properties": {
    "gn:admin1_code":"5.0",
    "gn:asciiname":"Suizicun",
    "gn:country_code":"CN",
    "gn:dem":150,
    "gn:feature_class":"P",
    "gn:feature_code":"PPL",
    "gn:name":"Suizicun",
    "gn:population":0,
    "gn:timezone":"Asia/Shanghai",
    "iso:country":"CN",
    "name:zho_x_preferred":[
        "\u968f\u5b57\u6751"
    ],
    "wof:name":"Suizicun",
    "wof:placetype":"locality"
},
  "geometry": {"coordinates":[123.92485000000001,44.80183],"type":"Point"}
}