{
  "type": "Feature",
  "properties": {
    "gn:admin1_code":"4.0",
    "gn:asciiname":"Xingoucun",
    "gn:country_code":"CN",
    "gn:dem":-3,
    "gn:feature_class":"P",
    "gn:feature_code":"PPL",
    "gn:name":"Xingoucun",
    "gn:population":0,
    "gn:timezone":"Asia/Shanghai",
    "iso:country":"CN",
    "name:zho_x_preferred":[
        "\u65b0\u6c9f\u6751"
    ],
    "wof:name":"Xingoucun",
    "wof:placetype":"locality"
},
  "geometry": {"coordinates":[119.71550999999999,33.74793],"type":"Point"}
}