{
  "type": "Feature",
  "properties": {
    "gn:admin1_code":"31",
    "gn:asciiname":"Shanliang",
    "gn:country_code":"CN",
    "gn:dem":-1,
    "gn:feature_class":"P",
    "gn:feature_code":"PPL",
    "gn:name":"Shanliang",
    "gn:population":0,
    "gn:timezone":"Asia/Shanghai",
    "iso:country":"CN",
    "name:und_x_variant":[
        "\u5c71\u826f"
    ],
    "wof:name":"Shanliang",
    "wof:placetype":"locality"
},
  "geometry": {"coordinates":[110.61458,19.98774],"type":"Point"}
}