{
  "type": "Feature",
  "properties": {
    "gn:admin1_code":"14.0",
    "gn:asciiname":"Suochicun",
    "gn:country_code":"CN",
    "gn:dem":3646,
    "gn:feature_class":"P",
    "gn:feature_code":"PPL",
    "gn:name":"Suochicun",
    "gn:population":0,
    "gn:timezone":"Asia/Urumqi",
    "iso:country":"CN",
    "name:zho_x_preferred":[
        "\u7d22\u5c3a\u6751"
    ],
    "wof:name":"Suochicun",
    "wof:placetype":"locality"
},
  "geometry": {"coordinates":[97.49916,30.56765],"type":"Point"}
}