{
  "type": "Feature",
  "properties": {
    "gn:admin1_code":"9",
    "gn:asciiname":"Nandizhuang",
    "gn:country_code":"CN",
    "gn:dem":72,
    "gn:feature_class":"P",
    "gn:feature_code":"PPL",
    "gn:name":"Nandizhuang",
    "gn:population":0,
    "gn:timezone":"Asia/Shanghai",
    "iso:country":"CN",
    "name:zho_x_preferred":[
        "\u5357\u7fdf\u5e84"
    ],
    "wof:name":"Nandizhuang",
    "wof:placetype":"locality"
},
  "geometry": {"coordinates":[115.10299999999999,34.78],"type":"Point"}
}