{
  "type": "Feature",
  "properties": {
    "gn:admin1_code":"19.0",
    "gn:asciiname":"Nianpangou",
    "gn:country_code":"CN",
    "gn:dem":215,
    "gn:feature_class":"P",
    "gn:feature_code":"PPL",
    "gn:name":"Nianpangou",
    "gn:population":0,
    "gn:timezone":"Asia/Shanghai",
    "iso:country":"CN",
    "name:und_x_variant":[
        "\u78be\u76d8\u6c9f"
    ],
    "wof:name":"Nianpangou",
    "wof:placetype":"locality"
},
  "geometry": {"coordinates":[124.30006000000002,41.86027],"type":"Point"}
}