{
  "type": "Feature",
  "properties": {
    "gn:admin1_code":"1.0",
    "gn:asciiname":"Shagangcun",
    "gn:country_code":"CN",
    "gn:dem":85,
    "gn:feature_class":"P",
    "gn:feature_code":"PPL",
    "gn:name":"Shagangcun",
    "gn:population":0,
    "gn:timezone":"Asia/Shanghai",
    "iso:country":"CN",
    "name:zho_x_preferred":[
        "\u7802\u5c97\u6751"
    ],
    "wof:name":"Shagangcun",
    "wof:placetype":"locality"
},
  "geometry": {"coordinates":[117.48189000000001,32.56646],"type":"Point"}
}