{
  "type": "Feature",
  "properties": {
    "gn:admin1_code":"14.0",
    "gn:asciiname":"Cibu",
    "gn:country_code":"CN",
    "gn:dem":4471,
    "gn:feature_class":"P",
    "gn:feature_code":"PPL",
    "gn:name":"Cibu",
    "gn:population":0,
    "gn:timezone":"Asia/Urumqi",
    "iso:country":"CN",
    "name:zho_x_preferred":[
        "\u6b21\u90e8"
    ],
    "wof:name":"Cibu",
    "wof:placetype":"locality"
},
  "geometry": {"coordinates":[91.15649000000001,30.45118],"type":"Point"}
}