{
  "type": "Feature",
  "properties": {
    "gn:admin1_code":"11.0",
    "gn:asciiname":"Dawanli",
    "gn:country_code":"CN",
    "gn:dem":400,
    "gn:feature_class":"P",
    "gn:feature_code":"PPL",
    "gn:name":"Dawanli",
    "gn:population":0,
    "gn:timezone":"Asia/Shanghai",
    "iso:country":"CN",
    "name:zho_x_preferred":[
        "Dawanli"
    ],
    "name:zho_x_variant":[
        "\u5927\u6e7e\u91cc"
    ],
    "wof:name":"Dawanli",
    "wof:placetype":"locality"
},
  "geometry": {"coordinates":[111.11599,29.15816],"type":"Point"}
}