{
  "type": "Feature",
  "properties": {
    "gn:admin1_code":"3.0",
    "gn:asciiname":"Gongpokeng",
    "gn:country_code":"CN",
    "gn:dem":69,
    "gn:feature_class":"P",
    "gn:feature_code":"PPL",
    "gn:name":"Gongpokeng",
    "gn:population":0,
    "gn:timezone":"Asia/Shanghai",
    "iso:country":"CN",
    "name:und_x_variant":[
        "\u516c\u5a46\u5751"
    ],
    "wof:name":"Gongpokeng",
    "wof:placetype":"locality"
},
  "geometry": {"coordinates":[115.07134000000001,28.39889],"type":"Point"}
}