{
  "type": "Feature",
  "properties": {
    "gn:admin1_code":"19.0",
    "gn:asciiname":"Bangchuigou",
    "gn:country_code":"CN",
    "gn:dem":101,
    "gn:feature_class":"P",
    "gn:feature_code":"PPL",
    "gn:name":"Bangchuigou",
    "gn:population":0,
    "gn:timezone":"Asia/Shanghai",
    "iso:country":"CN",
    "name:und_x_variant":[
        "\u68d2\u69cc\u6c9f"
    ],
    "wof:name":"Bangchuigou",
    "wof:placetype":"locality"
},
  "geometry": {"coordinates":[123.13776,40.06343],"type":"Point"}
}