{
  "type": "Feature",
  "properties": {
    "gn:admin1_code":"18",
    "gn:asciiname":"Mabukuai",
    "gn:country_code":"CN",
    "gn:dem":1862,
    "gn:feature_class":"P",
    "gn:feature_code":"PPL",
    "gn:name":"Mabukuai",
    "gn:population":0,
    "gn:timezone":"Asia/Shanghai",
    "iso:country":"CN",
    "name:zho_x_preferred":[
        "\u9ebb\u5e03\u5757"
    ],
    "wof:name":"Mabukuai",
    "wof:placetype":"locality"
},
  "geometry": {"coordinates":[104.55500000000001,27.1783],"type":"Point"}
}