{
  "type": "Feature",
  "properties": {
    "gn:admin1_code":"8.0",
    "gn:asciiname":"Zhangtun",
    "gn:country_code":"CN",
    "gn:dem":306,
    "gn:feature_class":"P",
    "gn:feature_code":"PPL",
    "gn:name":"Zhangtun",
    "gn:population":0,
    "gn:timezone":"Asia/Shanghai",
    "iso:country":"CN",
    "name:zho_x_preferred":[
        "\u5f20\u5c6f"
    ],
    "wof:name":"Zhangtun",
    "wof:placetype":"locality"
},
  "geometry": {"coordinates":[126.26966000000002,47.92388],"type":"Point"}
}