{
  "type": "Feature",
  "properties": {
    "gn:admin1_code":"26.0",
    "gn:asciiname":"Leibeicun",
    "gn:country_code":"CN",
    "gn:dem":1095,
    "gn:feature_class":"P",
    "gn:feature_code":"PPL",
    "gn:name":"Leibeicun",
    "gn:population":0,
    "gn:timezone":"Asia/Shanghai",
    "iso:country":"CN",
    "name:zho_x_preferred":[
        "\u96f7\u5317\u6751"
    ],
    "wof:name":"Leibeicun",
    "wof:placetype":"locality"
},
  "geometry": {"coordinates":[108.14576,35.05968],"type":"Point"}
}