{
  "type": "Feature",
  "properties": {
    "gn:admin1_code":"1.0",
    "gn:asciiname":"Cuijiawan",
    "gn:cc2":"CN",
    "gn:country_code":"CN",
    "gn:dem":90,
    "gn:feature_class":"P",
    "gn:feature_code":"PPL",
    "gn:name":"Cuijiawan",
    "gn:population":0,
    "gn:timezone":"Asia/Shanghai",
    "iso:country":"CN",
    "name:und_x_variant":[
        "Ts\u2019ui-chia-wan",
        "Cuijiawan"
    ],
    "wof:name":"Cuijiawan",
    "wof:placetype":"locality"
},
  "geometry": {"coordinates":[118.16222,32.595],"type":"Point"}
}