{
  "type": "Feature",
  "properties": {
    "gn:admin1_code":"31.0",
    "gn:asciiname":"Jiabao",
    "gn:country_code":"CN",
    "gn:dem":116,
    "gn:feature_class":"P",
    "gn:feature_code":"PPL",
    "gn:name":"Jiabao",
    "gn:population":0,
    "gn:timezone":"Asia/Shanghai",
    "iso:country":"CN",
    "name:zho_x_preferred":[
        "\u52a0\u5b9d"
    ],
    "wof:name":"Jiabao",
    "wof:placetype":"locality"
},
  "geometry": {"coordinates":[110.12803999999998,19.36108],"type":"Point"}
}