{
  "type": "Feature",
  "properties": {
    "gn:admin1_code":"9.0",
    "gn:asciiname":"Qushou",
    "gn:country_code":"CN",
    "gn:dem":558,
    "gn:feature_class":"P",
    "gn:feature_code":"PPL",
    "gn:name":"Qushou",
    "gn:population":0,
    "gn:timezone":"Asia/Shanghai",
    "iso:country":"CN",
    "name:zho_x_preferred":[
        "\u6e20\u9996"
    ],
    "wof:name":"Qushou",
    "wof:placetype":"locality"
},
  "geometry": {"coordinates":[112.62327999999999,35.25145999999999],"type":"Point"}
}