{
  "type": "Feature",
  "properties": {
    "gn:admin1_code":"31",
    "gn:asciiname":"Xinshi",
    "gn:cc2":"CN",
    "gn:country_code":"CN",
    "gn:dem":3,
    "gn:feature_class":"P",
    "gn:feature_code":"PPL",
    "gn:name":"Xinshi",
    "gn:population":0,
    "gn:timezone":"Asia/Shanghai",
    "iso:country":"CN",
    "name:und_x_variant":[
        "Hsin-hs\u00fc",
        "Xinshi",
        "\u65b0\u5e02"
    ],
    "wof:name":"Xinshi",
    "wof:placetype":"locality"
},
  "geometry": {"coordinates":[110.41139,20.03278],"type":"Point"}
}