{
  "type": "Feature",
  "properties": {
    "gn:admin1_code":"32.0",
    "gn:asciiname":"Huashiban",
    "gn:country_code":"CN",
    "gn:dem":425,
    "gn:feature_class":"P",
    "gn:feature_code":"PPL",
    "gn:name":"Huashiban",
    "gn:population":0,
    "gn:timezone":"Asia/Shanghai",
    "iso:country":"CN",
    "name:zho_x_preferred":[
        "\u6ed1\u77f3\u677f"
    ],
    "wof:name":"Huashiban",
    "wof:placetype":"locality"
},
  "geometry": {"coordinates":[105.39977,29.81705],"type":"Point"}
}