{
  "type": "Feature",
  "properties": {
    "gn:admin1_code":"11.0",
    "gn:asciiname":"Xiantailing",
    "gn:country_code":"CN",
    "gn:dem":179,
    "gn:feature_class":"P",
    "gn:feature_code":"PPL",
    "gn:name":"Xiantailing",
    "gn:population":0,
    "gn:timezone":"Asia/Shanghai",
    "iso:country":"CN",
    "name:zho_x_preferred":[
        "\u4ed9\u53f0\u5cad"
    ],
    "wof:name":"Xiantailing",
    "wof:placetype":"locality"
},
  "geometry": {"coordinates":[113.64485000000001,28.2642],"type":"Point"}
}