{
  "type": "Feature",
  "properties": {
    "gn:admin1_code":"11",
    "gn:asciiname":"Fujiawan",
    "gn:country_code":"CN",
    "gn:dem":133,
    "gn:feature_class":"P",
    "gn:feature_code":"PPL",
    "gn:name":"Fujiawan",
    "gn:population":0,
    "gn:timezone":"Asia/Shanghai",
    "iso:country":"CN",
    "wof:name":"Fujiawan",
    "wof:placetype":"locality"
},
  "geometry": {"coordinates":[110.2475,27.91611],"type":"Point"}
}