{
  "type": "Feature",
  "properties": {
    "gn:admin1_code":"12.0",
    "gn:asciiname":"Shaojiadun",
    "gn:country_code":"CN",
    "gn:dem":27,
    "gn:feature_class":"P",
    "gn:feature_code":"PPL",
    "gn:name":"Shaojiadun",
    "gn:population":0,
    "gn:timezone":"Asia/Shanghai",
    "iso:country":"CN",
    "name:zho_x_preferred":[
        "\u90b5\u5bb6\u58a9"
    ],
    "wof:name":"Shaojiadun",
    "wof:placetype":"locality"
},
  "geometry": {"coordinates":[113.12918999999999,29.64695],"type":"Point"}
}