{
  "type": "Feature",
  "properties": {
    "gn:admin1_code":"3",
    "gn:asciiname":"Jinjishixia",
    "gn:country_code":"CN",
    "gn:dem":841,
    "gn:feature_class":"P",
    "gn:feature_code":"PPL",
    "gn:name":"Jinjishixia",
    "gn:population":0,
    "gn:timezone":"Asia/Shanghai",
    "iso:country":"CN",
    "name:zho_x_preferred":[
        "\u91d1\u9e21\u77f3\u4e0b"
    ],
    "wof:name":"Jinjishixia",
    "wof:placetype":"locality"
},
  "geometry": {"coordinates":[114.096,26.2866],"type":"Point"}
}