{
  "type": "Feature",
  "properties": {
    "gn:admin1_code":"26.0",
    "gn:asciiname":"Zhanghewan",
    "gn:country_code":"CN",
    "gn:dem":1561,
    "gn:feature_class":"P",
    "gn:feature_code":"PPL",
    "gn:name":"Zhanghewan",
    "gn:population":0,
    "gn:timezone":"Asia/Shanghai",
    "iso:country":"CN",
    "name:zho_x_preferred":[
        "\u5f20\u6cb3\u6e7e"
    ],
    "wof:name":"Zhanghewan",
    "wof:placetype":"locality"
},
  "geometry": {"coordinates":[108.09778,37.32247],"type":"Point"}
}