{
  "type": "Feature",
  "properties": {
    "gn:admin1_code":"3.0",
    "gn:asciiname":"Qiaohuang",
    "gn:country_code":"CN",
    "gn:dem":22,
    "gn:feature_class":"P",
    "gn:feature_code":"PPL",
    "gn:name":"Qiaohuang",
    "gn:population":0,
    "gn:timezone":"Asia/Shanghai",
    "iso:country":"CN",
    "name:zho_x_preferred":[
        "\u6865\u9ec4"
    ],
    "wof:name":"Qiaohuang",
    "wof:placetype":"locality"
},
  "geometry": {"coordinates":[117.05200000000001,28.9029],"type":"Point"}
}