{
  "type": "Feature",
  "properties": {
    "gn:admin1_code":"30",
    "gn:asciiname":"Xiacuocun",
    "gn:country_code":"CN",
    "gn:dem":279,
    "gn:feature_class":"P",
    "gn:feature_code":"PPL",
    "gn:name":"Xiacuocun",
    "gn:population":0,
    "gn:timezone":"Asia/Shanghai",
    "iso:country":"CN",
    "name:zho_x_preferred":[
        "\u971e\u539d\u6751"
    ],
    "wof:name":"Xiacuocun",
    "wof:placetype":"locality"
},
  "geometry": {"coordinates":[116.3305,23.1073],"type":"Point"}
}