{
  "type": "Feature",
  "properties": {
    "gn:admin1_code":"19.0",
    "gn:asciiname":"Changxingdian",
    "gn:country_code":"CN",
    "gn:dem":46,
    "gn:feature_class":"P",
    "gn:feature_code":"PPL",
    "gn:name":"Changxingdian",
    "gn:population":0,
    "gn:timezone":"Asia/Shanghai",
    "iso:country":"CN",
    "name:zho_x_preferred":[
        "\u957f\u5174\u5e97"
    ],
    "wof:name":"Changxingdian",
    "wof:placetype":"locality"
},
  "geometry": {"coordinates":[123.39078000000001,41.556],"type":"Point"}
}