{
  "type": "Feature",
  "properties": {
    "gn:admin1_code":"19.0",
    "gn:asciiname":"Wangmatai",
    "gn:country_code":"CN",
    "gn:dem":14,
    "gn:feature_class":"P",
    "gn:feature_code":"PPL",
    "gn:name":"Wangmatai",
    "gn:population":0,
    "gn:timezone":"Asia/Shanghai",
    "iso:country":"CN",
    "name:und_x_variant":[
        "\u671b\u9a6c\u53f0"
    ],
    "wof:name":"Wangmatai",
    "wof:placetype":"locality"
},
  "geometry": {"coordinates":[122.47605,40.55928],"type":"Point"}
}