{
  "type": "Feature",
  "properties": {
    "gn:admin1_code":"13.0",
    "gn:asciiname":"Dashitou",
    "gn:cc2":"CN",
    "gn:country_code":"CN",
    "gn:dem":1430,
    "gn:feature_class":"P",
    "gn:feature_code":"PPL",
    "gn:name":"Dashitou",
    "gn:population":0,
    "gn:timezone":"Asia/Urumqi",
    "iso:country":"CN",
    "name:und_x_variant":[
        "Ta-shih-t\u2019o",
        "Dashitou"
    ],
    "wof:name":"Dashitou",
    "wof:placetype":"locality"
},
  "geometry": {"coordinates":[91.16667,43.75],"type":"Point"}
}