{
  "type": "Feature",
  "properties": {
    "gn:admin1_code":"32.0",
    "gn:asciiname":"Sanjiazhai",
    "gn:country_code":"CN",
    "gn:dem":2258,
    "gn:feature_class":"P",
    "gn:feature_code":"PPL",
    "gn:name":"Sanjiazhai",
    "gn:population":0,
    "gn:timezone":"Asia/Shanghai",
    "iso:country":"CN",
    "name:zho_x_preferred":[
        "\u4e09\u5bb6\u5be8"
    ],
    "wof:name":"Sanjiazhai",
    "wof:placetype":"locality"
},
  "geometry": {"coordinates":[103.146,31.6743],"type":"Point"}
}