{
  "type": "Feature",
  "properties": {
    "gn:admin1_code":"07",
    "gn:asciiname":"Meilingtou",
    "gn:country_code":"CN",
    "gn:dem":928,
    "gn:feature_class":"P",
    "gn:feature_code":"PPL",
    "gn:name":"Meilingtou",
    "gn:population":0,
    "gn:timezone":"Asia/Shanghai",
    "iso:country":"CN",
    "wof:name":"Meilingtou",
    "wof:placetype":"locality"
},
  "geometry": {"coordinates":[118.52222,25.63028],"type":"Point"}
}