{
  "type": "Feature",
  "properties": {
    "gn:admin1_code":"6.0",
    "gn:asciiname":"Luohexiang",
    "gn:country_code":"CN",
    "gn:dem":2838,
    "gn:feature_class":"P",
    "gn:feature_code":"PPL",
    "gn:name":"Luohexiang",
    "gn:population":0,
    "gn:timezone":"Asia/Shanghai",
    "iso:country":"CN",
    "name:und_x_variant":[
        "\u6d1b\u5408\u76f8"
    ],
    "wof:name":"Luohexiang",
    "wof:placetype":"locality"
},
  "geometry": {"coordinates":[100.99614,35.89254000000001],"type":"Point"}
}