{
  "type": "Feature",
  "properties": {
    "gn:admin1_code":"19.0",
    "gn:asciiname":"Houwangliangtun",
    "gn:country_code":"CN",
    "gn:dem":101,
    "gn:feature_class":"P",
    "gn:feature_code":"PPL",
    "gn:name":"Houwangliangtun",
    "gn:population":0,
    "gn:timezone":"Asia/Shanghai",
    "iso:country":"CN",
    "name:zho_x_preferred":[
        "\u540e\u6c6a\u826f\u5c6f"
    ],
    "wof:name":"Houwangliangtun",
    "wof:placetype":"locality"
},
  "geometry": {"coordinates":[123.83896,41.8289],"type":"Point"}
}