{
  "type": "Feature",
  "properties": {
    "gn:admin1_code":"24",
    "gn:asciiname":"Zhuyu",
    "gn:country_code":"CN",
    "gn:dem":1032,
    "gn:feature_class":"P",
    "gn:feature_code":"PPL",
    "gn:name":"Zhuyu",
    "gn:population":0,
    "gn:timezone":"Asia/Shanghai",
    "iso:country":"CN",
    "name:und_x_variant":[
        "Chu-y\u00fc",
        "Zhuyu"
    ],
    "name:zho_x_preferred":[
        "\u6731\u5cea"
    ],
    "wof:name":"Zhuyu",
    "wof:placetype":"locality"
},
  "geometry": {"coordinates":[113.84876,37.71542],"type":"Point"}
}