{
  "type": "Feature",
  "properties": {
    "gn:admin1_code":"18",
    "gn:asciiname":"Jiayi",
    "gn:country_code":"CN",
    "gn:dem":750,
    "gn:feature_class":"P",
    "gn:feature_code":"PPL",
    "gn:name":"Jiayi",
    "gn:population":0,
    "gn:timezone":"Asia/Shanghai",
    "iso:country":"CN",
    "name:ceb_x_preferred":[
        "Jiayi"
    ],
    "name:zho_x_preferred":[
        "\u52a0\u5b9c"
    ],
    "wof:name":"Jiayi",
    "wof:placetype":"locality"
},
  "geometry": {"coordinates":[108.389,25.7559],"type":"Point"}
}