{
  "type": "Feature",
  "properties": {
    "gn:admin1_code":"26.0",
    "gn:asciiname":"Shanggoucun",
    "gn:country_code":"CN",
    "gn:dem":1091,
    "gn:feature_class":"P",
    "gn:feature_code":"PPL",
    "gn:name":"Shanggoucun",
    "gn:population":0,
    "gn:timezone":"Asia/Shanghai",
    "iso:country":"CN",
    "name:zho_x_preferred":[
        "\u4e0a\u6c9f\u6751"
    ],
    "wof:name":"Shanggoucun",
    "wof:placetype":"locality"
},
  "geometry": {"coordinates":[110.21167,34.1721],"type":"Point"}
}