{
  "type": "Feature",
  "properties": {
    "gn:admin1_code":"32.0",
    "gn:asciiname":"Zexiu",
    "gn:country_code":"CN",
    "gn:dem":3426,
    "gn:feature_class":"P",
    "gn:feature_code":"PPL",
    "gn:name":"Zexiu",
    "gn:population":0,
    "gn:timezone":"Asia/Shanghai",
    "iso:country":"CN",
    "name:zho_x_preferred":[
        "\u6cfd\u4fee"
    ],
    "wof:name":"Zexiu",
    "wof:placetype":"locality"
},
  "geometry": {"coordinates":[102.28100000000001,33.9677],"type":"Point"}
}