{
  "type": "Feature",
  "properties": {
    "gn:admin1_code":"6.0",
    "gn:asciiname":"Ganggan",
    "gn:country_code":"CN",
    "gn:dem":3181,
    "gn:feature_class":"P",
    "gn:feature_code":"PPL",
    "gn:name":"Ganggan",
    "gn:population":0,
    "gn:timezone":"Asia/Urumqi",
    "iso:country":"CN",
    "name:und_x_variant":[
        "\u5188\u5e72"
    ],
    "wof:name":"Ganggan",
    "wof:placetype":"locality"
},
  "geometry": {"coordinates":[99.08977,36.84],"type":"Point"}
}