{
  "type": "Feature",
  "properties": {
    "gn:admin1_code":"3.0",
    "gn:asciiname":"Jianjia",
    "gn:country_code":"CN",
    "gn:dem":174,
    "gn:feature_class":"P",
    "gn:feature_code":"PPL",
    "gn:name":"Jianjia",
    "gn:population":0,
    "gn:timezone":"Asia/Shanghai",
    "iso:country":"CN",
    "name:und_x_variant":[
        "\u7b80\u5bb6"
    ],
    "wof:name":"Jianjia",
    "wof:placetype":"locality"
},
  "geometry": {"coordinates":[115.17665,27.16368],"type":"Point"}
}