{
  "type": "Feature",
  "properties": {
    "gn:admin1_code":"08",
    "gn:asciiname":"Baikui",
    "gn:country_code":"CN",
    "gn:dem":179,
    "gn:feature_class":"P",
    "gn:feature_code":"PPLA4",
    "gn:name":"Baikui",
    "gn:population":0,
    "gn:timezone":"Asia/Shanghai",
    "iso:country":"CN",
    "name:und_x_variant":[
        "Pai-k\u2019uei-p\u2019u",
        "Baikui",
        "Baikui Zhen"
    ],
    "name:zho_x_preferred":[
        "\u767d\u594e"
    ],
    "name:zho_x_variant":[
        "\u767d\u594e\u9547"
    ],
    "wof:name":"Baikui",
    "wof:placetype":"locality"
},
  "geometry": {"coordinates":[126.99636,46.36432],"type":"Point"}
}