{
  "type": "Feature",
  "properties": {
    "gn:admin1_code":"25",
    "gn:asciiname":"Huangsheng",
    "gn:cc2":"CN",
    "gn:country_code":"CN",
    "gn:dem":9,
    "gn:feature_class":"P",
    "gn:feature_code":"PPL",
    "gn:name":"Huangsheng",
    "gn:population":0,
    "gn:timezone":"Asia/Shanghai",
    "iso:country":"CN",
    "name:und_x_variant":[
        "Huang-sheng-chen",
        "Huangsheng"
    ],
    "wof:name":"Huangsheng",
    "wof:placetype":"locality"
},
  "geometry": {"coordinates":[117.95,37.61667],"type":"Point"}
}