{
  "type": "Feature",
  "properties": {
    "gn:admin1_code":"32.0",
    "gn:asciiname":"Tanggou",
    "gn:country_code":"CN",
    "gn:dem":619,
    "gn:feature_class":"P",
    "gn:feature_code":"PPL",
    "gn:name":"Tanggou",
    "gn:population":0,
    "gn:timezone":"Asia/Shanghai",
    "iso:country":"CN",
    "name:zho_x_preferred":[
        "\u5510\u6c9f"
    ],
    "wof:name":"Tanggou",
    "wof:placetype":"locality"
},
  "geometry": {"coordinates":[103.35299000000001,30.53169],"type":"Point"}
}