{
  "type": "Feature",
  "properties": {
    "gn:admin1_code":"10",
    "gn:asciiname":"Sandaogoumen",
    "gn:cc2":"CN",
    "gn:country_code":"CN",
    "gn:dem":1347,
    "gn:feature_class":"P",
    "gn:feature_code":"PPL",
    "gn:name":"Sandaogoumen",
    "gn:population":0,
    "gn:timezone":"Asia/Shanghai",
    "iso:country":"CN",
    "name:und_x_variant":[
        "San-tao-kou",
        "Sandaogoumen"
    ],
    "wof:name":"Sandaogoumen",
    "wof:placetype":"locality"
},
  "geometry": {"coordinates":[117.51222,42.38389],"type":"Point"}
}