{
  "type": "Feature",
  "properties": {
    "gn:admin1_code":"30.0",
    "gn:asciiname":"Hengjiang",
    "gn:country_code":"CN",
    "gn:dem":0,
    "gn:feature_class":"P",
    "gn:feature_code":"PPL",
    "gn:name":"Hengjiang",
    "gn:population":0,
    "gn:timezone":"Asia/Shanghai",
    "iso:country":"CN",
    "name:zho_x_preferred":[
        "\u6a6b\u6c5f"
    ],
    "wof:name":"Hengjiang",
    "wof:placetype":"locality"
},
  "geometry": {"coordinates":[112.70555,22.47277],"type":"Point"}
}