{
  "type": "Feature",
  "properties": {
    "gn:admin1_code":"33.0",
    "gn:asciiname":"Dachayuan",
    "gn:country_code":"CN",
    "gn:dem":903,
    "gn:feature_class":"P",
    "gn:feature_code":"PPL",
    "gn:name":"Dachayuan",
    "gn:population":0,
    "gn:timezone":"Asia/Shanghai",
    "iso:country":"CN",
    "name:zho_x_preferred":[
        "\u5927\u8336\u56ed"
    ],
    "wof:name":"Dachayuan",
    "wof:placetype":"locality"
},
  "geometry": {"coordinates":[108.88929,28.70004],"type":"Point"}
}