{
  "type": "Feature",
  "properties": {
    "gn:admin1_code":"2.0",
    "gn:asciiname":"Zuoshui Banqiao",
    "gn:country_code":"CN",
    "gn:dem":7,
    "gn:feature_class":"P",
    "gn:feature_code":"PPL",
    "gn:name":"Zuoshui Banqiao",
    "gn:population":0,
    "gn:timezone":"Asia/Shanghai",
    "iso:country":"CN",
    "name:und_x_variant":[
        "\u4f5c\u6c34\u677f\u6865"
    ],
    "wof:name":"Zuoshui Banqiao",
    "wof:placetype":"locality"
},
  "geometry": {"coordinates":[120.58711,30.54539],"type":"Point"}
}