{
  "type": "Feature",
  "properties": {
    "gn:admin1_code":"18.0",
    "gn:asciiname":"Guiya",
    "gn:country_code":"CN",
    "gn:dem":520,
    "gn:feature_class":"P",
    "gn:feature_code":"PPL",
    "gn:name":"Guiya",
    "gn:population":0,
    "gn:timezone":"Asia/Shanghai",
    "iso:country":"CN",
    "name:zho_x_preferred":[
        "\u6842\u82bd"
    ],
    "wof:name":"Guiya",
    "wof:placetype":"locality"
},
  "geometry": {"coordinates":[108.955,28.1685],"type":"Point"}
}