{
  "type": "Feature",
  "properties": {
    "gn:admin1_code":"02",
    "gn:asciiname":"Xiaopumencun",
    "gn:country_code":"CN",
    "gn:dem":1,
    "gn:feature_class":"P",
    "gn:feature_code":"PPL",
    "gn:name":"Xiaopumencun",
    "gn:population":0,
    "gn:timezone":"Asia/Shanghai",
    "iso:country":"CN",
    "name:und_x_variant":[
        "P\u2019u-men",
        "Xiaopumen",
        "\u5c0f\u6d66\u95e8",
        "Xiaopumencun"
    ],
    "name:zho_x_preferred":[
        "\u5c0f\u84b2\u95e8\u6751"
    ],
    "wof:name":"Xiaopumencun",
    "wof:placetype":"locality"
},
  "geometry": {"coordinates":[122.21472,30.23969],"type":"Point"}
}