{
  "type": "Feature",
  "properties": {
    "gn:admin1_code":"11.0",
    "gn:asciiname":"Yanying'an",
    "gn:country_code":"CN",
    "gn:dem":606,
    "gn:feature_class":"P",
    "gn:feature_code":"PPL",
    "gn:name":"Yanying\u2019an",
    "gn:population":0,
    "gn:timezone":"Asia/Shanghai",
    "iso:country":"CN",
    "name:und_x_variant":[
        "Yanying\u2019an"
    ],
    "name:zho_x_preferred":[
        "\u5ca9\u9e70\u5eb5"
    ],
    "wof:name":"Yanying'an",
    "wof:placetype":"locality"
},
  "geometry": {"coordinates":[109.6558,27.03405],"type":"Point"}
}