{
  "type": "Feature",
  "properties": {
    "gn:admin1_code":"32.0",
    "gn:asciiname":"Asima",
    "gn:country_code":"CN",
    "gn:dem":3655,
    "gn:feature_class":"P",
    "gn:feature_code":"PPL",
    "gn:name":"Asima",
    "gn:population":0,
    "gn:timezone":"Asia/Shanghai",
    "iso:country":"CN",
    "name:zho_x_preferred":[
        "\u963f\u65af\u739b"
    ],
    "wof:name":"Asima",
    "wof:placetype":"locality"
},
  "geometry": {"coordinates":[100.926,32.5742],"type":"Point"}
}