{
  "type": "Feature",
  "properties": {
    "gn:admin1_code":"32.0",
    "gn:asciiname":"Shangbianwan",
    "gn:country_code":"CN",
    "gn:dem":381,
    "gn:feature_class":"P",
    "gn:feature_code":"PPL",
    "gn:name":"Shangbianwan",
    "gn:population":0,
    "gn:timezone":"Asia/Shanghai",
    "iso:country":"CN",
    "name:zho_x_preferred":[
        "\u4e0a\u8fb9\u6e7e"
    ],
    "wof:name":"Shangbianwan",
    "wof:placetype":"locality"
},
  "geometry": {"coordinates":[103.85518,29.47258],"type":"Point"}
}