{
  "type": "Feature",
  "properties": {
    "gn:admin1_code":"16.0",
    "gn:asciiname":"Pojiaowai",
    "gn:country_code":"CN",
    "gn:dem":465,
    "gn:feature_class":"P",
    "gn:feature_code":"PPL",
    "gn:name":"Pojiaowai",
    "gn:population":0,
    "gn:timezone":"Asia/Shanghai",
    "iso:country":"CN",
    "name:zho_x_preferred":[
        "\u5761\u811a\u5916"
    ],
    "wof:name":"Pojiaowai",
    "wof:placetype":"locality"
},
  "geometry": {"coordinates":[105.679,23.0924],"type":"Point"}
}