{
  "type": "Feature",
  "properties": {
    "gn:admin1_code":"30.0",
    "gn:asciiname":"Lijiukeng",
    "gn:country_code":"CN",
    "gn:dem":74,
    "gn:feature_class":"P",
    "gn:feature_code":"PPL",
    "gn:name":"Lijiukeng",
    "gn:population":0,
    "gn:timezone":"Asia/Shanghai",
    "iso:country":"CN",
    "name:zho_x_preferred":[
        "\u674e\u4e5d\u5751"
    ],
    "wof:name":"Lijiukeng",
    "wof:placetype":"locality"
},
  "geometry": {"coordinates":[112.95829000000001,22.70607],"type":"Point"}
}