{
  "type": "Feature",
  "properties": {
    "gn:admin1_code":"3.0",
    "gn:asciiname":"Xiadong",
    "gn:country_code":"CN",
    "gn:dem":379,
    "gn:feature_class":"P",
    "gn:feature_code":"PPL",
    "gn:name":"Xiadong",
    "gn:population":0,
    "gn:timezone":"Asia/Shanghai",
    "iso:country":"CN",
    "name:und_x_variant":[
        "\u971e\u6d1e"
    ],
    "wof:name":"Xiadong",
    "wof:placetype":"locality"
},
  "geometry": {"coordinates":[115.45976,26.13342],"type":"Point"}
}