{
  "type": "Feature",
  "properties": {
    "gn:admin1_code":"11.0",
    "gn:asciiname":"Raojiachong",
    "gn:country_code":"CN",
    "gn:dem":75,
    "gn:feature_class":"P",
    "gn:feature_code":"PPL",
    "gn:name":"Raojiachong",
    "gn:population":0,
    "gn:timezone":"Asia/Shanghai",
    "iso:country":"CN",
    "name:zho_x_preferred":[
        "\u9976\u5bb6\u51b2"
    ],
    "wof:name":"Raojiachong",
    "wof:placetype":"locality"
},
  "geometry": {"coordinates":[111.66969,28.82653],"type":"Point"}
}