{
  "type": "Feature",
  "properties": {
    "gn:admin1_code":"10",
    "gn:asciiname":"Danancha",
    "gn:country_code":"CN",
    "gn:dem":1471,
    "gn:feature_class":"P",
    "gn:feature_code":"PPL",
    "gn:name":"Danancha",
    "gn:population":0,
    "gn:timezone":"Asia/Shanghai",
    "iso:country":"CN",
    "name:zho_x_preferred":[
        "\u5927\u5357\u5c94"
    ],
    "wof:name":"Danancha",
    "wof:placetype":"locality"
},
  "geometry": {"coordinates":[117.54201999999999,42.48506],"type":"Point"}
}