{
  "type": "Feature",
  "properties": {
    "gn:admin1_code":"2",
    "gn:asciiname":"Shangchuyang",
    "gn:country_code":"CN",
    "gn:dem":868,
    "gn:feature_class":"P",
    "gn:feature_code":"PPL",
    "gn:name":"Shangchuyang",
    "gn:population":0,
    "gn:timezone":"Asia/Shanghai",
    "iso:country":"CN",
    "name:zho_x_preferred":[
        "\u4e0a\u5904\u579f"
    ],
    "wof:name":"Shangchuyang",
    "wof:placetype":"locality"
},
  "geometry": {"coordinates":[119.3925,27.83056],"type":"Point"}
}