{
  "type": "Feature",
  "properties": {
    "gn:admin1_code":"29.0",
    "gn:asciiname":"Aichang",
    "gn:country_code":"CN",
    "gn:dem":1134,
    "gn:feature_class":"P",
    "gn:feature_code":"PPL",
    "gn:name":"Aichang",
    "gn:population":0,
    "gn:timezone":"Asia/Shanghai",
    "iso:country":"CN",
    "name:zho_x_preferred":[
        "\u6328\u660c"
    ],
    "wof:name":"Aichang",
    "wof:placetype":"locality"
},
  "geometry": {"coordinates":[101.754,25.8137],"type":"Point"}
}