{
  "type": "Feature",
  "properties": {
    "gn:admin1_code":"14.0",
    "gn:asciiname":"Gapucun",
    "gn:country_code":"CN",
    "gn:dem":4445,
    "gn:feature_class":"P",
    "gn:feature_code":"PPL",
    "gn:name":"Gapucun",
    "gn:population":0,
    "gn:timezone":"Asia/Urumqi",
    "iso:country":"CN",
    "name:zho_x_preferred":[
        "\u560e\u666e\u6751"
    ],
    "wof:name":"Gapucun",
    "wof:placetype":"locality"
},
  "geometry": {"coordinates":[89.096,28.75369],"type":"Point"}
}