{
  "type": "Feature",
  "properties": {
    "gn:admin1_code":"19.0",
    "gn:asciiname":"Shenjia Dianzi",
    "gn:country_code":"CN",
    "gn:dem":53,
    "gn:feature_class":"P",
    "gn:feature_code":"PPL",
    "gn:name":"Shenjia Dianzi",
    "gn:population":0,
    "gn:timezone":"Asia/Shanghai",
    "iso:country":"CN",
    "name:zho_x_preferred":[
        "\u6c88\u5bb6\u7538\u5b50"
    ],
    "wof:name":"Shenjia Dianzi",
    "wof:placetype":"locality"
},
  "geometry": {"coordinates":[123.88916,40.1799],"type":"Point"}
}