{
  "type": "Feature",
  "properties": {
    "gn:admin1_code":"14",
    "gn:asciiname":"Pujiu",
    "gn:country_code":"CN",
    "gn:dem":4596,
    "gn:feature_class":"P",
    "gn:feature_code":"PPL",
    "gn:name":"Pujiu",
    "gn:population":0,
    "gn:timezone":"Asia/Urumqi",
    "iso:country":"CN",
    "name:zho_x_preferred":[
        "\u666e\u4e45"
    ],
    "wof:name":"Pujiu",
    "wof:placetype":"locality"
},
  "geometry": {"coordinates":[89.1096,28.6293],"type":"Point"}
}