{
  "type": "Feature",
  "properties": {
    "gn:admin1_code":"19.0",
    "gn:asciiname":"Jiaojia Wopucun",
    "gn:country_code":"CN",
    "gn:dem":206,
    "gn:feature_class":"P",
    "gn:feature_code":"PPL",
    "gn:name":"Jiaojia Wopucun",
    "gn:population":0,
    "gn:timezone":"Asia/Shanghai",
    "iso:country":"CN",
    "name:zho_x_preferred":[
        "\u7126\u5bb6\u7a9d\u94fa\u6751"
    ],
    "wof:name":"Jiaojia Wopucun",
    "wof:placetype":"locality"
},
  "geometry": {"coordinates":[120.637,41.3659],"type":"Point"}
}