{
  "type": "Feature",
  "properties": {
    "gn:admin1_code":"20.0",
    "gn:asciiname":"Xiyaozi",
    "gn:country_code":"CN",
    "gn:dem":1478,
    "gn:feature_class":"P",
    "gn:feature_code":"PPL",
    "gn:name":"Xiyaozi",
    "gn:population":0,
    "gn:timezone":"Asia/Shanghai",
    "iso:country":"CN",
    "name:und_x_variant":[
        "\u897f\u7a91\u5b50"
    ],
    "wof:name":"Xiyaozi",
    "wof:placetype":"locality"
},
  "geometry": {"coordinates":[111.32171,40.9215],"type":"Point"}
}