{
  "type": "Feature",
  "properties": {
    "gn:country":"CN",
    "gn:fcode":"PPL",
    "gn:pop":720,
    "iso:country":"CN",
    "name:unk_x_variant":[
        "T\u2019an-ch\u2019i"
    ],
    "name:zho_x_preferred":[
        "\u6f6d\u6eaa"
    ],
    "qs:name":"Tanxi",
    "qs:photos_9r":0,
    "qs:photos_sr":0,
    "qs:pop_sr":"2",
    "wof:name":"Tanxi",
    "wof:placetype":"locality",
    "wof:population":720
},
  "geometry": {"coordinates":[109.20556000000001,26.31],"type":"Point"}
}