{
  "type": "Feature",
  "properties": {
    "gn:admin1_code":"11.0",
    "gn:asciiname":"Zhuotang",
    "gn:country_code":"CN",
    "gn:dem":316,
    "gn:feature_class":"P",
    "gn:feature_code":"PPL",
    "gn:name":"Zhuotang",
    "gn:population":0,
    "gn:timezone":"Asia/Shanghai",
    "iso:country":"CN",
    "name:zho_x_preferred":[
        "\u6d4a\u5858"
    ],
    "wof:name":"Zhuotang",
    "wof:placetype":"locality"
},
  "geometry": {"coordinates":[110.6786,26.98325],"type":"Point"}
}