{
  "type": "Feature",
  "properties": {
    "gn:admin1_code":"14.0",
    "gn:asciiname":"Yixicun",
    "gn:country_code":"CN",
    "gn:dem":3859,
    "gn:feature_class":"P",
    "gn:feature_code":"PPL",
    "gn:name":"Yixicun",
    "gn:population":0,
    "gn:timezone":"Asia/Urumqi",
    "iso:country":"CN",
    "name:zho_x_preferred":[
        "\u76ca\u897f\u6751"
    ],
    "wof:name":"Yixicun",
    "wof:placetype":"locality"
},
  "geometry": {"coordinates":[97.99342,29.99883],"type":"Point"}
}