{
  "type": "Feature",
  "properties": {
    "gn:admin1_code":"8.0",
    "gn:asciiname":"Qinlaocun",
    "gn:country_code":"CN",
    "gn:dem":131,
    "gn:feature_class":"P",
    "gn:feature_code":"PPL",
    "gn:name":"Qinlaocun",
    "gn:population":0,
    "gn:timezone":"Asia/Shanghai",
    "iso:country":"CN",
    "name:zho_x_preferred":[
        "\u52e4\u52b3\u6751"
    ],
    "wof:name":"Qinlaocun",
    "wof:placetype":"locality"
},
  "geometry": {"coordinates":[126.70202999999999,46.0057],"type":"Point"}
}