{
  "type": "Feature",
  "properties": {
    "gn:admin1_code":"21.0",
    "gn:asciiname":"Xintan",
    "gn:country_code":"CN",
    "gn:dem":1226,
    "gn:feature_class":"P",
    "gn:feature_code":"PPL",
    "gn:name":"Xintan",
    "gn:population":0,
    "gn:timezone":"Asia/Shanghai",
    "iso:country":"CN",
    "name:zho_x_preferred":[
        "\u65b0\u6ee9"
    ],
    "wof:name":"Xintan",
    "wof:placetype":"locality"
},
  "geometry": {"coordinates":[105.206,37.5739],"type":"Point"}
}