{
  "type": "Feature",
  "properties": {
    "gn:admin1_code":"18",
    "gn:asciiname":"Tunshang",
    "gn:country_code":"CN",
    "gn:dem":1275,
    "gn:feature_class":"P",
    "gn:feature_code":"PPL",
    "gn:name":"Tunshang",
    "gn:population":0,
    "gn:timezone":"Asia/Shanghai",
    "iso:country":"CN",
    "name:zho_x_preferred":[
        "\u5c6f\u4e0a"
    ],
    "wof:name":"Tunshang",
    "wof:placetype":"locality"
},
  "geometry": {"coordinates":[105.30500000000001,25.0593],"type":"Point"}
}