{
  "type": "Feature",
  "properties": {
    "gn:admin1_code":"25.0",
    "gn:asciiname":"Dadugezhuang",
    "gn:country_code":"CN",
    "gn:dem":21,
    "gn:feature_class":"P",
    "gn:feature_code":"PPL",
    "gn:name":"Dadugezhuang",
    "gn:population":0,
    "gn:timezone":"Asia/Shanghai",
    "iso:country":"CN",
    "name:zho_x_preferred":[
        "\u5927\u675c\u6208\u5e84"
    ],
    "wof:name":"Dadugezhuang",
    "wof:placetype":"locality"
},
  "geometry": {"coordinates":[119.98797999999999,36.41542000000001],"type":"Point"}
}