{
  "type": "Feature",
  "properties": {
    "gn:admin1_code":"02",
    "gn:asciiname":"Yuchencun",
    "gn:country_code":"CN",
    "gn:dem":11,
    "gn:feature_class":"P",
    "gn:feature_code":"PPL",
    "gn:name":"Yuchencun",
    "gn:population":0,
    "gn:timezone":"Asia/Shanghai",
    "iso:country":"CN",
    "name:und_x_variant":[
        "Yuchen"
    ],
    "name:zho_x_preferred":[
        "\u9c7c\u6c89\u6751"
    ],
    "wof:name":"Yuchencun",
    "wof:placetype":"locality"
},
  "geometry": {"coordinates":[121.2941,28.59218],"type":"Point"}
}