{
  "type": "Feature",
  "properties": {
    "gn:admin1_code":"29.0",
    "gn:asciiname":"Xiewen",
    "gn:country_code":"CN",
    "gn:dem":1668,
    "gn:feature_class":"P",
    "gn:feature_code":"PPL",
    "gn:name":"Xiewen",
    "gn:population":0,
    "gn:timezone":"Asia/Shanghai",
    "iso:country":"CN",
    "name:und_x_variant":[
        "\u659c\u6587"
    ],
    "wof:name":"Xiewen",
    "wof:placetype":"locality"
},
  "geometry": {"coordinates":[103.95614,27.90398],"type":"Point"}
}