{
  "type": "Feature",
  "properties": {
    "gn:admin1_code":"7",
    "gn:asciiname":"Xitou",
    "gn:country_code":"CN",
    "gn:dem":4,
    "gn:feature_class":"P",
    "gn:feature_code":"PPL",
    "gn:name":"Xitou",
    "gn:population":0,
    "gn:timezone":"Asia/Shanghai",
    "iso:country":"CN",
    "name:deu_x_preferred":[
        "Xitou"
    ],
    "name:zho_x_preferred":[
        "\u6eaa\u5934"
    ],
    "wof:name":"Xitou",
    "wof:placetype":"locality"
},
  "geometry": {"coordinates":[117.67111,24.05944],"type":"Point"}
}