{
  "type": "Feature",
  "properties": {
    "gn:admin1_code":"25",
    "gn:asciiname":"Chutianji",
    "gn:country_code":"CN",
    "gn:dem":57,
    "gn:feature_class":"P",
    "gn:feature_code":"PPL",
    "gn:name":"Chutianji",
    "gn:population":0,
    "gn:timezone":"Asia/Shanghai",
    "iso:country":"CN",
    "name:zho_x_preferred":[
        "\u695a\u5929\u96c6"
    ],
    "wof:name":"Chutianji",
    "wof:placetype":"locality"
},
  "geometry": {"coordinates":[115.706,34.7023],"type":"Point"}
}