{
  "type": "Feature",
  "properties": {
    "gn:admin1_code":"06",
    "gn:asciiname":"Tangnag",
    "gn:country_code":"CN",
    "gn:dem":3174,
    "gn:feature_class":"P",
    "gn:feature_code":"PPL",
    "gn:name":"Tangnag",
    "gn:population":0,
    "gn:timezone":"Asia/Shanghai",
    "iso:country":"CN",
    "name:bod_x_preferred":[
        "Tangnag"
    ],
    "name:und_x_variant":[
        "T\u2019ang-nai-hai",
        "Tangnaihai",
        "\u5510\u4e43\u4ea5"
    ],
    "name:zho_x_preferred":[
        "\u5510\u4e43\u4ea5"
    ],
    "wof:name":"Tangnag",
    "wof:placetype":"locality"
},
  "geometry": {"coordinates":[100.10471,35.56595],"type":"Point"}
}