{
  "type": "Feature",
  "properties": {
    "gn:admin1_code":"30.0",
    "gn:asciiname":"Shibangxia",
    "gn:country_code":"CN",
    "gn:dem":143,
    "gn:feature_class":"P",
    "gn:feature_code":"PPL",
    "gn:name":"Shibangxia",
    "gn:population":0,
    "gn:timezone":"Asia/Shanghai",
    "iso:country":"CN",
    "name:zho_x_preferred":[
        "\u77f3\u699c\u4e0b"
    ],
    "wof:name":"Shibangxia",
    "wof:placetype":"locality"
},
  "geometry": {"coordinates":[114.4205,25.20945],"type":"Point"}
}