{
  "type": "Feature",
  "properties": {
    "gn:admin1_code":"15",
    "gn:asciiname":"Wangcheng",
    "gn:country_code":"CN",
    "gn:dem":1498,
    "gn:feature_class":"P",
    "gn:feature_code":"PPL",
    "gn:name":"Wangcheng",
    "gn:population":0,
    "gn:timezone":"Asia/Shanghai",
    "iso:country":"CN",
    "name:deu_x_preferred":[
        "Wangcheng"
    ],
    "name:und_x_variant":[
        "Wangchuan"
    ],
    "name:zho_x_preferred":[
        "\u738b\u57ce"
    ],
    "wof:name":"Wangcheng",
    "wof:placetype":"locality"
},
  "geometry": {"coordinates":[105.425,34.2521],"type":"Point"}
}