{
  "type": "Feature",
  "properties": {
    "gn:admin1_code":"12.0",
    "gn:asciiname":"Jingbatiaowan",
    "gn:country_code":"CN",
    "gn:dem":47,
    "gn:feature_class":"P",
    "gn:feature_code":"PPL",
    "gn:name":"Jingbatiaowan",
    "gn:population":0,
    "gn:timezone":"Asia/Shanghai",
    "iso:country":"CN",
    "name:zho_x_preferred":[
        "\u8346\u516b\u6761\u6e7e"
    ],
    "wof:name":"Jingbatiaowan",
    "wof:placetype":"locality"
},
  "geometry": {"coordinates":[112.28743,30.61687],"type":"Point"}
}