{
  "type": "Feature",
  "properties": {
    "gn:admin1_code":"1.0",
    "gn:asciiname":"Luobucun",
    "gn:country_code":"CN",
    "gn:dem":26,
    "gn:feature_class":"P",
    "gn:feature_code":"PPL",
    "gn:name":"Luobucun",
    "gn:population":0,
    "gn:timezone":"Asia/Shanghai",
    "iso:country":"CN",
    "name:zho_x_preferred":[
        "\u7f57\u57e0\u6751"
    ],
    "wof:name":"Luobucun",
    "wof:placetype":"locality"
},
  "geometry": {"coordinates":[117.00258999999998,32.36518],"type":"Point"}
}