{
  "type": "Feature",
  "properties": {
    "gn:admin1_code":"22.0",
    "gn:asciiname":"Baiyutaicun",
    "gn:country_code":"CN",
    "gn:dem":879,
    "gn:feature_class":"P",
    "gn:feature_code":"PPL",
    "gn:name":"Baiyutaicun",
    "gn:population":0,
    "gn:timezone":"Asia/Shanghai",
    "iso:country":"CN",
    "name:zho_x_preferred":[
        "\u67cf\u5cea\u53f0\u6751"
    ],
    "wof:name":"Baiyutaicun",
    "wof:placetype":"locality"
},
  "geometry": {"coordinates":[115.63628,40.00794000000001],"type":"Point"}
}