{
  "type": "Feature",
  "properties": {
    "gn:admin1_code":"29.0",
    "gn:asciiname":"Sangezhuang",
    "gn:country_code":"CN",
    "gn:dem":2433,
    "gn:feature_class":"P",
    "gn:feature_code":"PPL",
    "gn:name":"Sangezhuang",
    "gn:population":0,
    "gn:timezone":"Asia/Shanghai",
    "iso:country":"CN",
    "name:zho_x_preferred":[
        "\u4e09\u6208\u5e84"
    ],
    "wof:name":"Sangezhuang",
    "wof:placetype":"locality"
},
  "geometry": {"coordinates":[100.333,26.4941],"type":"Point"}
}