{
  "type": "Feature",
  "properties": {
    "gn:admin1_code":"11.0",
    "gn:asciiname":"Chaping",
    "gn:country_code":"CN",
    "gn:dem":554,
    "gn:feature_class":"P",
    "gn:feature_code":"PPL",
    "gn:name":"Chaping",
    "gn:population":0,
    "gn:timezone":"Asia/Shanghai",
    "iso:country":"CN",
    "name:zho_x_preferred":[
        "\u8336\u576a"
    ],
    "wof:name":"Chaping",
    "wof:placetype":"locality"
},
  "geometry": {"coordinates":[109.79667000000001,28.47337000000001],"type":"Point"}
}