{
  "type": "Feature",
  "properties": {
    "gn:admin1_code":"15.0",
    "gn:asciiname":"Heluo",
    "gn:country_code":"CN",
    "gn:dem":2212,
    "gn:feature_class":"P",
    "gn:feature_code":"PPL",
    "gn:name":"Heluo",
    "gn:population":0,
    "gn:timezone":"Asia/Shanghai",
    "iso:country":"CN",
    "name:zho_x_preferred":[
        "\u58d1\u843d"
    ],
    "wof:name":"Heluo",
    "wof:placetype":"locality"
},
  "geometry": {"coordinates":[103.68899999999999,35.242],"type":"Point"}
}