{
  "type": "Feature",
  "properties": {
    "gn:admin1_code":"1.0",
    "gn:asciiname":"Jianghuang Minzu Jiedao",
    "gn:country_code":"CN",
    "gn:dem":32,
    "gn:feature_class":"P",
    "gn:feature_code":"PPL",
    "gn:name":"Jianghuang Minzu Jiedao",
    "gn:population":0,
    "gn:timezone":"Asia/Shanghai",
    "iso:country":"CN",
    "name:zho_x_preferred":[
        "\u6c5f\u9ec4\u6c11\u65cf\u8857\u9053"
    ],
    "wof:name":"Jianghuang Minzu Jiedao",
    "wof:placetype":"locality"
},
  "geometry": {"coordinates":[116.8233,32.32629],"type":"Point"}
}