{
  "type": "Feature",
  "properties": {
    "gn:admin1_code":"1.0",
    "gn:asciiname":"Beilingcun",
    "gn:country_code":"CN",
    "gn:dem":484,
    "gn:feature_class":"P",
    "gn:feature_code":"PPL",
    "gn:name":"Beilingcun",
    "gn:population":0,
    "gn:timezone":"Asia/Shanghai",
    "iso:country":"CN",
    "name:zho_x_preferred":[
        "\u5317\u5cad\u6751"
    ],
    "wof:name":"Beilingcun",
    "wof:placetype":"locality"
},
  "geometry": {"coordinates":[117.37938,30.26089],"type":"Point"}
}