{
  "type": "Feature",
  "properties": {
    "gn:admin1_code":"18",
    "gn:asciiname":"Fangjianping",
    "gn:country_code":"CN",
    "gn:dem":1559,
    "gn:feature_class":"P",
    "gn:feature_code":"PPL",
    "gn:name":"Fangjianping",
    "gn:population":0,
    "gn:timezone":"Asia/Shanghai",
    "iso:country":"CN",
    "name:zho_x_preferred":[
        "\u653e\u5efa\u576a"
    ],
    "wof:name":"Fangjianping",
    "wof:placetype":"locality"
},
  "geometry": {"coordinates":[105.181,25.6929],"type":"Point"}
}