{
  "type": "Feature",
  "properties": {
    "gn:admin1_code":"14.0",
    "gn:asciiname":"Wuqunggai",
    "gn:country_code":"CN",
    "gn:dem":4531,
    "gn:feature_class":"P",
    "gn:feature_code":"PPL",
    "gn:name":"Wuqunggai",
    "gn:population":0,
    "gn:timezone":"Asia/Urumqi",
    "iso:country":"CN",
    "name:bod_x_preferred":[
        "Wuqunggai"
    ],
    "name:zho_x_preferred":[
        "Wuqiongge"
    ],
    "name:zho_x_variant":[
        "\u4e4c\u743c\u683c"
    ],
    "wof:name":"Wuqunggai",
    "wof:placetype":"locality"
},
  "geometry": {"coordinates":[97.301,32.301],"type":"Point"}
}