{
  "type": "Feature",
  "properties": {
    "gn:admin1_code":"33.0",
    "gn:asciiname":"Zhuanlong",
    "gn:country_code":"CN",
    "gn:dem":398,
    "gn:feature_class":"P",
    "gn:feature_code":"PPL",
    "gn:name":"Zhuanlong",
    "gn:population":0,
    "gn:timezone":"Asia/Shanghai",
    "iso:country":"CN",
    "name:zho_x_preferred":[
        "\u8f6c\u9f99"
    ],
    "wof:name":"Zhuanlong",
    "wof:placetype":"locality"
},
  "geometry": {"coordinates":[105.52912999999999,29.58076],"type":"Point"}
}