{
  "type": "Feature",
  "properties": {
    "gn:admin1_code":"32",
    "gn:asciiname":"Jiuyuan",
    "gn:country_code":"CN",
    "gn:dem":663,
    "gn:feature_class":"P",
    "gn:feature_code":"PPL",
    "gn:name":"Jiuyuan",
    "gn:population":0,
    "gn:timezone":"Asia/Shanghai",
    "iso:country":"CN",
    "name:zho_x_preferred":[
        "\u65e7\u9662"
    ],
    "wof:name":"Jiuyuan",
    "wof:placetype":"locality"
},
  "geometry": {"coordinates":[108.20601000000001,31.83834],"type":"Point"}
}