{
  "type": "Feature",
  "properties": {
    "gn:admin1_code":"29.0",
    "gn:asciiname":"Songshan Xiazhai",
    "gn:country_code":"CN",
    "gn:dem":1830,
    "gn:feature_class":"P",
    "gn:feature_code":"PPL",
    "gn:name":"Songshan Xiazhai",
    "gn:population":0,
    "gn:timezone":"Asia/Shanghai",
    "iso:country":"CN",
    "name:zho_x_preferred":[
        "\u677e\u5c71\u4e0b\u5be8"
    ],
    "wof:name":"Songshan Xiazhai",
    "wof:placetype":"locality"
},
  "geometry": {"coordinates":[99.89919999999999,24.4516],"type":"Point"}
}