{
  "type": "Feature",
  "properties": {
    "gn:admin1_code":"10",
    "gn:asciiname":"Anzigou",
    "gn:country_code":"CN",
    "gn:dem":268,
    "gn:feature_class":"P",
    "gn:feature_code":"PPL",
    "gn:name":"Anzigou",
    "gn:population":0,
    "gn:timezone":"Asia/Shanghai",
    "iso:country":"CN",
    "name:zho_x_preferred":[
        "\u5b89\u5b50\u6c9f"
    ],
    "wof:name":"Anzigou",
    "wof:placetype":"locality"
},
  "geometry": {"coordinates":[119.33847,40.45143],"type":"Point"}
}