{
  "type": "Feature",
  "properties": {
    "gn:admin1_code":"14.0",
    "gn:asciiname":"Gelong",
    "gn:country_code":"CN",
    "gn:dem":4180,
    "gn:feature_class":"P",
    "gn:feature_code":"PPL",
    "gn:name":"Gelong",
    "gn:population":0,
    "gn:timezone":"Asia/Urumqi",
    "iso:country":"CN",
    "name:zho_x_preferred":[
        "\u683c\u9647"
    ],
    "wof:name":"Gelong",
    "wof:placetype":"locality"
},
  "geometry": {"coordinates":[97.51853,31.94879],"type":"Point"}
}