{
  "type": "Feature",
  "properties": {
    "gn:admin1_code":"3.0",
    "gn:asciiname":"Lingnaocun",
    "gn:country_code":"CN",
    "gn:dem":313,
    "gn:feature_class":"P",
    "gn:feature_code":"PPL",
    "gn:name":"Lingnaocun",
    "gn:population":0,
    "gn:timezone":"Asia/Shanghai",
    "iso:country":"CN",
    "name:und_x_variant":[
        "\u5cad\u8111\u6751"
    ],
    "wof:name":"Lingnaocun",
    "wof:placetype":"locality"
},
  "geometry": {"coordinates":[115.21287,26.12109],"type":"Point"}
}