{
  "type": "Feature",
  "properties": {
    "gn:admin1_code":"3",
    "gn:asciiname":"Guizixing",
    "gn:country_code":"CN",
    "gn:dem":440,
    "gn:feature_class":"P",
    "gn:feature_code":"PPL",
    "gn:name":"Guizixing",
    "gn:population":0,
    "gn:timezone":"Asia/Shanghai",
    "iso:country":"CN",
    "name:zho_x_preferred":[
        "\u9f9f\u5b50\u5f62"
    ],
    "wof:name":"Guizixing",
    "wof:placetype":"locality"
},
  "geometry": {"coordinates":[114.55200000000001,26.2698],"type":"Point"}
}