{
  "type": "Feature",
  "properties": {
    "gn:admin1_code":"14.0",
    "gn:asciiname":"Dizhong",
    "gn:country_code":"CN",
    "gn:dem":3247,
    "gn:feature_class":"P",
    "gn:feature_code":"PPL",
    "gn:name":"Dizhong",
    "gn:population":0,
    "gn:timezone":"Asia/Urumqi",
    "iso:country":"CN",
    "name:zho_x_preferred":[
        "\u8fea\u4e2d"
    ],
    "wof:name":"Dizhong",
    "wof:placetype":"locality"
},
  "geometry": {"coordinates":[98.65375,31.04285],"type":"Point"}
}