{
  "type": "Feature",
  "properties": {
    "gn:admin1_code":"5.0",
    "gn:asciiname":"Hengdao Qidui",
    "gn:country_code":"CN",
    "gn:dem":540,
    "gn:feature_class":"P",
    "gn:feature_code":"PPLF",
    "gn:name":"Hengdao Qidui",
    "gn:population":0,
    "gn:timezone":"Asia/Shanghai",
    "iso:country":"CN",
    "name:zho_x_preferred":[
        "\u6a2a\u9053\u4e03\u961f"
    ],
    "wof:name":"Hengdao Qidui",
    "wof:placetype":"locality"
},
  "geometry": {"coordinates":[126.05098999999998,41.66917],"type":"Point"}
}