{
  "type": "Feature",
  "properties": {
    "gn:admin1_code":"9.0",
    "gn:asciiname":"Wangshenmiao",
    "gn:country_code":"CN",
    "gn:dem":278,
    "gn:feature_class":"P",
    "gn:feature_code":"PPL",
    "gn:name":"Wangshenmiao",
    "gn:population":0,
    "gn:timezone":"Asia/Shanghai",
    "iso:country":"CN",
    "name:zho_x_preferred":[
        "\u6c6a\u795e\u5e99"
    ],
    "wof:name":"Wangshenmiao",
    "wof:placetype":"locality"
},
  "geometry": {"coordinates":[115.20622,31.65402000000001],"type":"Point"}
}