{
  "type": "Feature",
  "properties": {
    "gn:admin1_code":"10",
    "gn:asciiname":"Beiluodian",
    "gn:country_code":"CN",
    "gn:dem":10,
    "gn:feature_class":"P",
    "gn:feature_code":"PPL",
    "gn:name":"Beiluodian",
    "gn:population":0,
    "gn:timezone":"Asia/Shanghai",
    "iso:country":"CN",
    "wof:name":"Beiluodian",
    "wof:placetype":"locality"
},
  "geometry": {"coordinates":[116.35611000000002,39.18389000000001],"type":"Point"}
}