{
  "type": "Feature",
  "properties": {
    "gn:admin1_code":"12.0",
    "gn:asciiname":"Dayejiawan",
    "gn:country_code":"CN",
    "gn:dem":117,
    "gn:feature_class":"P",
    "gn:feature_code":"PPL",
    "gn:name":"Dayejiawan",
    "gn:population":0,
    "gn:timezone":"Asia/Shanghai",
    "iso:country":"CN",
    "name:zho_x_preferred":[
        "\u5927\u53f6\u5bb6\u5846"
    ],
    "wof:name":"Dayejiawan",
    "wof:placetype":"locality"
},
  "geometry": {"coordinates":[112.76014000000001,32.04806],"type":"Point"}
}