{
  "type": "Feature",
  "properties": {
    "gn:admin1_code":"30.0",
    "gn:asciiname":"Dechang",
    "gn:country_code":"CN",
    "gn:dem":1,
    "gn:feature_class":"P",
    "gn:feature_code":"PPL",
    "gn:name":"Dechang",
    "gn:population":0,
    "gn:timezone":"Asia/Shanghai",
    "iso:country":"CN",
    "name:zho_x_preferred":[
        "\u5fb7\u660c"
    ],
    "wof:name":"Dechang",
    "wof:placetype":"locality"
},
  "geometry": {"coordinates":[112.91791000000001,22.50187],"type":"Point"}
}