{
  "type": "Feature",
  "properties": {
    "gn:admin1_code":"16.0",
    "gn:asciiname":"Chuanxin",
    "gn:country_code":"CN",
    "gn:dem":106,
    "gn:feature_class":"P",
    "gn:feature_code":"PPL",
    "gn:name":"Chuanxin",
    "gn:population":0,
    "gn:timezone":"Asia/Shanghai",
    "iso:country":"CN",
    "name:zho_x_preferred":[
        "\u5ddd\u5fc3"
    ],
    "wof:name":"Chuanxin",
    "wof:placetype":"locality"
},
  "geometry": {"coordinates":[109.346,22.573],"type":"Point"}
}