{
  "type": "Feature",
  "properties": {
    "gn:admin1_code":"4.0",
    "gn:asciiname":"Chengxin Shi'erzu",
    "gn:country_code":"CN",
    "gn:dem":2,
    "gn:feature_class":"P",
    "gn:feature_code":"PPLF",
    "gn:name":"Chengxin Shi\u2019erzu",
    "gn:population":0,
    "gn:timezone":"Asia/Shanghai",
    "iso:country":"CN",
    "name:und_x_variant":[
        "Chengxin Shi\u2019erzu"
    ],
    "name:zho_x_preferred":[
        "\u8bda\u5fc3\u5341\u4e8c\u7ec4"
    ],
    "wof:name":"Chengxin Shi'erzu",
    "wof:placetype":"locality"
},
  "geometry": {"coordinates":[120.509,33.1598],"type":"Point"}
}