{
  "type": "Feature",
  "properties": {
    "gn:admin1_code":"8.0",
    "gn:asciiname":"Xinxingying Linzhan",
    "gn:country_code":"CN",
    "gn:dem":309,
    "gn:feature_class":"P",
    "gn:feature_code":"PPLF",
    "gn:name":"Xinxingying Linzhan",
    "gn:population":0,
    "gn:timezone":"Asia/Shanghai",
    "iso:country":"CN",
    "name:und_x_variant":[
        "\u65b0\u5174\u8425l\u6797\u7ad9"
    ],
    "wof:name":"Xinxingying Linzhan",
    "wof:placetype":"locality"
},
  "geometry": {"coordinates":[126.53642000000001,47.9916],"type":"Point"}
}