{
  "type": "Feature",
  "properties": {
    "gn:admin1_code":"32.0",
    "gn:asciiname":"Dadongshui",
    "gn:country_code":"CN",
    "gn:dem":865,
    "gn:feature_class":"P",
    "gn:feature_code":"PPL",
    "gn:name":"Dadongshui",
    "gn:population":0,
    "gn:timezone":"Asia/Shanghai",
    "iso:country":"CN",
    "name:zho_x_preferred":[
        "\u5927\u51ac\u6c34"
    ],
    "wof:name":"Dadongshui",
    "wof:placetype":"locality"
},
  "geometry": {"coordinates":[103.78474,31.13433],"type":"Point"}
}