{
  "type": "Feature",
  "properties": {
    "gn:admin1_code":"5",
    "gn:asciiname":"Shidaohezi",
    "gn:country_code":"CN",
    "gn:dem":400,
    "gn:feature_class":"P",
    "gn:feature_code":"PPL",
    "gn:name":"Shidaohezi",
    "gn:population":0,
    "gn:timezone":"Asia/Shanghai",
    "iso:country":"CN",
    "name:zho_x_preferred":[
        "\u77f3\u9053\u6cb3\u5b50"
    ],
    "wof:name":"Shidaohezi",
    "wof:placetype":"locality"
},
  "geometry": {"coordinates":[127.56999999999999,43.4119],"type":"Point"}
}