{
  "type": "Feature",
  "properties": {
    "gn:admin1_code":"3.0",
    "gn:asciiname":"Hengbacun",
    "gn:country_code":"CN",
    "gn:dem":49,
    "gn:feature_class":"P",
    "gn:feature_code":"PPL",
    "gn:name":"Hengbacun",
    "gn:population":0,
    "gn:timezone":"Asia/Shanghai",
    "iso:country":"CN",
    "name:und_x_variant":[
        "\u6a2a\u575d\u6751"
    ],
    "wof:name":"Hengbacun",
    "wof:placetype":"locality"
},
  "geometry": {"coordinates":[116.66248,28.03963],"type":"Point"}
}