{
  "type": "Feature",
  "properties": {
    "gn:admin1_code":"26.0",
    "gn:asciiname":"Guchengcun",
    "gn:country_code":"CN",
    "gn:dem":495,
    "gn:feature_class":"P",
    "gn:feature_code":"PPL",
    "gn:name":"Guchengcun",
    "gn:population":0,
    "gn:timezone":"Asia/Shanghai",
    "iso:country":"CN",
    "name:und_x_variant":[
        "\u53e4\u57ce\u6751"
    ],
    "wof:name":"Guchengcun",
    "wof:placetype":"locality"
},
  "geometry": {"coordinates":[107.23039,33.13112],"type":"Point"}
}