{
  "type": "Feature",
  "properties": {
    "gn:admin1_code":"8.0",
    "gn:asciiname":"Funongcun",
    "gn:country_code":"CN",
    "gn:dem":225,
    "gn:feature_class":"P",
    "gn:feature_code":"PPL",
    "gn:name":"Funongcun",
    "gn:population":0,
    "gn:timezone":"Asia/Shanghai",
    "iso:country":"CN",
    "name:zho_x_preferred":[
        "\u798f\u519c\u6751"
    ],
    "wof:name":"Funongcun",
    "wof:placetype":"locality"
},
  "geometry": {"coordinates":[125.89015999999999,47.03442],"type":"Point"}
}