{
  "type": "Feature",
  "properties": {
    "gn:admin1_code":"29.0",
    "gn:asciiname":"Duohu",
    "gn:country_code":"CN",
    "gn:dem":2353,
    "gn:feature_class":"P",
    "gn:feature_code":"PPL",
    "gn:name":"Duohu",
    "gn:population":0,
    "gn:timezone":"Asia/Shanghai",
    "iso:country":"CN",
    "name:zho_x_preferred":[
        "\u591a\u795c"
    ],
    "wof:name":"Duohu",
    "wof:placetype":"locality"
},
  "geometry": {"coordinates":[100.419,25.229],"type":"Point"}
}