{
  "type": "Feature",
  "properties": {
    "gn:admin1_code":"2.0",
    "gn:asciiname":"Yuzhao",
    "gn:country_code":"CN",
    "gn:dem":28,
    "gn:feature_class":"P",
    "gn:feature_code":"PPL",
    "gn:name":"Yuzhao",
    "gn:population":0,
    "gn:timezone":"Asia/Shanghai",
    "iso:country":"CN",
    "name:und_x_variant":[
        "\u4fde\u8d75",
        "Yuzhao"
    ],
    "wof:name":"Yuzhao",
    "wof:placetype":"locality"
},
  "geometry": {"coordinates":[119.63115999999999,29.75364],"type":"Point"}
}