{
  "type": "Feature",
  "properties": {
    "gn:admin1_code":"24",
    "gn:asciiname":"Jiajiamao",
    "gn:cc2":"CN",
    "gn:country_code":"CN",
    "gn:dem":1068,
    "gn:feature_class":"P",
    "gn:feature_code":"PPL",
    "gn:name":"Jiajiamao",
    "gn:population":0,
    "gn:timezone":"Asia/Shanghai",
    "iso:country":"CN",
    "name:und_x_variant":[
        "Chia-chia-mao",
        "Jiajiamao"
    ],
    "wof:name":"Jiajiamao",
    "wof:placetype":"locality"
},
  "geometry": {"coordinates":[111.16667,39.03333],"type":"Point"}
}