{
  "type": "Feature",
  "properties": {
    "gn:admin1_code":"32.0",
    "gn:asciiname":"Xuenongtang",
    "gn:country_code":"CN",
    "gn:dem":289,
    "gn:feature_class":"P",
    "gn:feature_code":"PPL",
    "gn:name":"Xuenongtang",
    "gn:population":0,
    "gn:timezone":"Asia/Shanghai",
    "iso:country":"CN",
    "name:zho_x_preferred":[
        "\u5b66\u519c\u5802"
    ],
    "wof:name":"Xuenongtang",
    "wof:placetype":"locality"
},
  "geometry": {"coordinates":[105.00508000000001,29.15592],"type":"Point"}
}