{
  "type": "Feature",
  "properties": {
    "gn:admin1_code":"14.0",
    "gn:asciiname":"Keqingcun",
    "gn:country_code":"CN",
    "gn:dem":3903,
    "gn:feature_class":"P",
    "gn:feature_code":"PPL",
    "gn:name":"Keqingcun",
    "gn:population":0,
    "gn:timezone":"Asia/Urumqi",
    "iso:country":"CN",
    "name:zho_x_preferred":[
        "\u79d1\u9752\u6751"
    ],
    "wof:name":"Keqingcun",
    "wof:placetype":"locality"
},
  "geometry": {"coordinates":[98.39829,30.70574],"type":"Point"}
}