{
  "type": "Feature",
  "properties": {
    "gn:admin1_code":"24",
    "gn:asciiname":"Diaoquancun",
    "gn:country_code":"CN",
    "gn:dem":1714,
    "gn:feature_class":"P",
    "gn:feature_code":"PPL",
    "gn:name":"Diaoquancun",
    "gn:population":0,
    "gn:timezone":"Asia/Shanghai",
    "iso:country":"CN",
    "name:und_x_variant":[
        "Tiao-ch\u2019\u00fcan",
        "Tiao-ch\u2019\u00fcan-ts\u2019un",
        "Diaoquan",
        "Diaoquancun"
    ],
    "name:zho_x_preferred":[
        "\u5201\u6cc9\u6751"
    ],
    "wof:name":"Diaoquancun",
    "wof:placetype":"locality"
},
  "geometry": {"coordinates":[114.50261999999999,39.52869000000001],"type":"Point"}
}