{
  "type": "Feature",
  "properties": {
    "gn:admin1_code":"26.0",
    "gn:asciiname":"Zuojiagou",
    "gn:country_code":"CN",
    "gn:dem":681,
    "gn:feature_class":"P",
    "gn:feature_code":"PPL",
    "gn:name":"Zuojiagou",
    "gn:population":0,
    "gn:timezone":"Asia/Shanghai",
    "iso:country":"CN",
    "name:und_x_variant":[
        "\u5de6\u5bb6\u6c9f"
    ],
    "wof:name":"Zuojiagou",
    "wof:placetype":"locality"
},
  "geometry": {"coordinates":[107.84419,33.11047],"type":"Point"}
}