{
  "type": "Feature",
  "properties": {
    "gn:admin1_code":"4.0",
    "gn:asciiname":"Zhoudong",
    "gn:country_code":"CN",
    "gn:dem":3,
    "gn:feature_class":"P",
    "gn:feature_code":"PPL",
    "gn:name":"Zhoudong",
    "gn:population":0,
    "gn:timezone":"Asia/Shanghai",
    "iso:country":"CN",
    "name:zho_x_preferred":[
        "\u6d32\u4e1c"
    ],
    "wof:name":"Zhoudong",
    "wof:placetype":"locality"
},
  "geometry": {"coordinates":[121.01769,31.24264],"type":"Point"}
}