{
  "type": "Feature",
  "properties": {
    "gn:admin1_code":"30.0",
    "gn:asciiname":"Tonggutang",
    "gn:country_code":"CN",
    "gn:dem":15,
    "gn:feature_class":"P",
    "gn:feature_code":"PPL",
    "gn:name":"Tonggutang",
    "gn:population":0,
    "gn:timezone":"Asia/Shanghai",
    "iso:country":"CN",
    "name:zho_x_preferred":[
        "\u94dc\u9f13\u5858"
    ],
    "wof:name":"Tonggutang",
    "wof:placetype":"locality"
},
  "geometry": {"coordinates":[111.8339,23.17921],"type":"Point"}
}