{
  "type": "Feature",
  "properties": {
    "gn:admin1_code":"4.0",
    "gn:asciiname":"Mingjiucun",
    "gn:country_code":"CN",
    "gn:dem":18,
    "gn:feature_class":"P",
    "gn:feature_code":"PPL",
    "gn:name":"Mingjiucun",
    "gn:population":0,
    "gn:timezone":"Asia/Shanghai",
    "iso:country":"CN",
    "name:zho_x_preferred":[
        "\u9e23\u4e5d\u6751"
    ],
    "wof:name":"Mingjiucun",
    "wof:placetype":"locality"
},
  "geometry": {"coordinates":[118.57671999999999,34.32928],"type":"Point"}
}