{
  "type": "Feature",
  "properties": {
    "gn:admin1_code":"8.0",
    "gn:asciiname":"Dabacun",
    "gn:country_code":"CN",
    "gn:dem":189,
    "gn:feature_class":"P",
    "gn:feature_code":"PPL",
    "gn:name":"Dabacun",
    "gn:population":0,
    "gn:timezone":"Asia/Shanghai",
    "iso:country":"CN",
    "name:zho_x_preferred":[
        "\u5927\u5df4\u6751"
    ],
    "wof:name":"Dabacun",
    "wof:placetype":"locality"
},
  "geometry": {"coordinates":[131.64538999999999,45.66378],"type":"Point"}
}