{
  "type": "Feature",
  "properties": {
    "gn:admin1_code":"1.0",
    "gn:asciiname":"Ganyingsicun",
    "gn:country_code":"CN",
    "gn:dem":30,
    "gn:feature_class":"P",
    "gn:feature_code":"PPL",
    "gn:name":"Ganyingsicun",
    "gn:population":0,
    "gn:timezone":"Asia/Shanghai",
    "iso:country":"CN",
    "name:zho_x_preferred":[
        "\u611f\u5e94\u5bfa\u6751"
    ],
    "wof:name":"Ganyingsicun",
    "wof:placetype":"locality"
},
  "geometry": {"coordinates":[116.56647,32.00234],"type":"Point"}
}