{
  "type": "Feature",
  "properties": {
    "gn:admin1_code":"3",
    "gn:asciiname":"Ben'an",
    "gn:country_code":"CN",
    "gn:dem":438,
    "gn:feature_class":"P",
    "gn:feature_code":"PPL",
    "gn:name":"Ben\u2019an",
    "gn:population":0,
    "gn:timezone":"Asia/Shanghai",
    "iso:country":"CN",
    "name:und_x_variant":[
        "Ben\u2019an"
    ],
    "name:zho_x_preferred":[
        "\u672c\u5b89"
    ],
    "wof:name":"Ben'an",
    "wof:placetype":"locality"
},
  "geometry": {"coordinates":[114.10745,26.66972],"type":"Point"}
}