{
  "type": "Feature",
  "properties": {
    "gn:admin1_code":"29",
    "gn:asciiname":"Heshangdi",
    "gn:country_code":"CN",
    "gn:dem":2133,
    "gn:feature_class":"P",
    "gn:feature_code":"PPL",
    "gn:name":"Heshangdi",
    "gn:population":0,
    "gn:timezone":"Asia/Shanghai",
    "iso:country":"CN",
    "name:zho_x_preferred":[
        "\u548c\u5c1a\u5730"
    ],
    "wof:name":"Heshangdi",
    "wof:placetype":"locality"
},
  "geometry": {"coordinates":[101.797,24.5444],"type":"Point"}
}