{
  "type": "Feature",
  "properties": {
    "gn:admin1_code":"30",
    "gn:asciiname":"Fulukeng",
    "gn:country_code":"CN",
    "gn:dem":261,
    "gn:feature_class":"P",
    "gn:feature_code":"PPL",
    "gn:name":"Fulukeng",
    "gn:population":0,
    "gn:timezone":"Asia/Shanghai",
    "iso:country":"CN",
    "name:zho_x_preferred":[
        "\u798f\u7984\u5751"
    ],
    "wof:name":"Fulukeng",
    "wof:placetype":"locality"
},
  "geometry": {"coordinates":[116.39878,24.63238],"type":"Point"}
}