{
  "type": "Feature",
  "properties": {
    "gn:admin1_code":"4.0",
    "gn:asciiname":"Houxia",
    "gn:country_code":"CN",
    "gn:dem":6,
    "gn:feature_class":"P",
    "gn:feature_code":"PPL",
    "gn:name":"Houxia",
    "gn:population":0,
    "gn:timezone":"Asia/Shanghai",
    "iso:country":"CN",
    "name:zho_x_preferred":[
        "Houxia"
    ],
    "name:zho_x_variant":[
        "\u540e\u590f"
    ],
    "wof:name":"Houxia",
    "wof:placetype":"locality"
},
  "geometry": {"coordinates":[119.25189,33.54589],"type":"Point"}
}