{
  "type": "Feature",
  "properties": {
    "gn:admin1_code":"14.0",
    "gn:asciiname":"Xieji",
    "gn:country_code":"CN",
    "gn:dem":3907,
    "gn:feature_class":"P",
    "gn:feature_code":"PPL",
    "gn:name":"Xieji",
    "gn:population":0,
    "gn:timezone":"Asia/Urumqi",
    "iso:country":"CN",
    "name:zho_x_preferred":[
        "\u978b\u5409"
    ],
    "wof:name":"Xieji",
    "wof:placetype":"locality"
},
  "geometry": {"coordinates":[90.83069999999999,28.3913],"type":"Point"}
}