{
  "type": "Feature",
  "properties": {
    "gn:admin1_code":"4.0",
    "gn:asciiname":"Jiaodongcun",
    "gn:country_code":"CN",
    "gn:dem":4,
    "gn:feature_class":"P",
    "gn:feature_code":"PPL",
    "gn:name":"Jiaodongcun",
    "gn:population":0,
    "gn:timezone":"Asia/Shanghai",
    "iso:country":"CN",
    "name:zho_x_preferred":[
        "\u80f6\u4e1c\u6751"
    ],
    "wof:name":"Jiaodongcun",
    "wof:placetype":"locality"
},
  "geometry": {"coordinates":[120.47911000000001,31.63785],"type":"Point"}
}