{
  "type": "Feature",
  "properties": {
    "gn:admin1_code":"3.0",
    "gn:asciiname":"Xiabuji",
    "gn:country_code":"CN",
    "gn:dem":21,
    "gn:feature_class":"P",
    "gn:feature_code":"PPLA4",
    "gn:name":"Xiabuji",
    "gn:population":0,
    "gn:timezone":"Asia/Shanghai",
    "iso:country":"CN",
    "name:und_x_variant":[
        "Hsia-pu-chi",
        "Xiabuji",
        "\u4e0b\u57e0\u96c6",
        "Xiabuji Xiang",
        "\u4e0b\u57e0\u96c6\u4e61"
    ],
    "wof:name":"Xiabuji",
    "wof:placetype":"locality"
},
  "geometry": {"coordinates":[116.38205000000001,28.30858],"type":"Point"}
}