{
  "type": "Feature",
  "properties": {
    "gn:admin1_code":"15.0",
    "gn:asciiname":"Huoshaowan",
    "gn:country_code":"CN",
    "gn:dem":1655,
    "gn:feature_class":"P",
    "gn:feature_code":"PPL",
    "gn:name":"Huoshaowan",
    "gn:population":0,
    "gn:timezone":"Asia/Shanghai",
    "iso:country":"CN",
    "name:zho_x_preferred":[
        "\u706b\u70e7\u6e7e"
    ],
    "wof:name":"Huoshaowan",
    "wof:placetype":"locality"
},
  "geometry": {"coordinates":[104.84399999999999,37.0695],"type":"Point"}
}