{
  "type": "Feature",
  "properties": {
    "gn:admin1_code":"4.0",
    "gn:asciiname":"Chenqicun",
    "gn:country_code":"CN",
    "gn:dem":0,
    "gn:feature_class":"P",
    "gn:feature_code":"PPL",
    "gn:name":"Chenqicun",
    "gn:population":0,
    "gn:timezone":"Asia/Shanghai",
    "iso:country":"CN",
    "name:zho_x_preferred":[
        "\u9648\u7941\u6751"
    ],
    "wof:name":"Chenqicun",
    "wof:placetype":"locality"
},
  "geometry": {"coordinates":[119.86908,33.34131],"type":"Point"}
}