{
  "type": "Feature",
  "properties": {
    "gn:admin1_code":"13.0",
    "gn:asciiname":"Taxdian",
    "gn:country_code":"CN",
    "gn:dem":1104,
    "gn:feature_class":"P",
    "gn:feature_code":"PPL",
    "gn:name":"Taxdian",
    "gn:population":0,
    "gn:timezone":"Asia/Urumqi",
    "iso:country":"CN",
    "name:uig_x_preferred":[
        "Taxd\u0259n"
    ],
    "name:uig_x_variant":[
        "Tashden",
        "\u062a\u0627\u0634\u062f\u06d5\u0646",
        "\u0422\u0430\u0448\u0434\u04d9\u043d"
    ],
    "name:und_x_variant":[
        "Pu-shih-a-k\u2019en",
        "T\u2019a-shih-tien",
        "Tashidyan\u2019",
        "Taxdian"
    ],
    "wof:name":"Taxdian",
    "wof:placetype":"locality"
},
  "geometry": {"coordinates":[86.29838000000002,41.85956],"type":"Point"}
}