{
  "type": "Feature",
  "properties": {
    "gn:admin1_code":"5.0",
    "gn:asciiname":"Bianjia Weizi",
    "gn:country_code":"CN",
    "gn:dem":129,
    "gn:feature_class":"P",
    "gn:feature_code":"PPL",
    "gn:name":"Bianjia Weizi",
    "gn:population":0,
    "gn:timezone":"Asia/Shanghai",
    "iso:country":"CN",
    "name:zho_x_preferred":[
        "\u8fb9\u5bb6\u56f4\u5b50"
    ],
    "wof:name":"Bianjia Weizi",
    "wof:placetype":"locality"
},
  "geometry": {"coordinates":[124.03749000000001,45.34003],"type":"Point"}
}