{
  "type": "Feature",
  "properties": {
    "gn:admin1_code":"18",
    "gn:asciiname":"Guoshuijiang",
    "gn:country_code":"CN",
    "gn:dem":980,
    "gn:feature_class":"P",
    "gn:feature_code":"PPL",
    "gn:name":"Guoshuijiang",
    "gn:population":0,
    "gn:timezone":"Asia/Shanghai",
    "iso:country":"CN",
    "name:zho_x_preferred":[
        "\u8fc7\u6c34\u6c5f"
    ],
    "wof:name":"Guoshuijiang",
    "wof:placetype":"locality"
},
  "geometry": {"coordinates":[108.23399999999999,27.1444],"type":"Point"}
}