{
  "type": "Feature",
  "properties": {
    "gn:admin1_code":"5.0",
    "gn:asciiname":"Shangjiedong",
    "gn:country_code":"CN",
    "gn:dem":35,
    "gn:feature_class":"P",
    "gn:feature_code":"PPL",
    "gn:name":"Shangjiedong",
    "gn:population":0,
    "gn:timezone":"Asia/Shanghai",
    "iso:country":"CN",
    "name:und_x_variant":[
        "\u4e0a\u754c\u6d1e"
    ],
    "wof:name":"Shangjiedong",
    "wof:placetype":"locality"
},
  "geometry": {"coordinates":[130.28391000000002,42.70507],"type":"Point"}
}