{
  "type": "Feature",
  "properties": {
    "gn:admin1_code":"7.0",
    "gn:asciiname":"Lixishan",
    "gn:country_code":"CN",
    "gn:dem":24,
    "gn:feature_class":"P",
    "gn:feature_code":"PPL",
    "gn:name":"Lixishan",
    "gn:population":0,
    "gn:timezone":"Asia/Shanghai",
    "iso:country":"CN",
    "name:zho_x_preferred":[
        "\u91cc\u897f\u5c71"
    ],
    "wof:name":"Lixishan",
    "wof:placetype":"locality"
},
  "geometry": {"coordinates":[119.16750999999999,26.13769],"type":"Point"}
}