{
  "type": "Feature",
  "properties": {
    "gn:admin1_code":"5.0",
    "gn:asciiname":"Aolijiuri",
    "gn:country_code":"CN",
    "gn:dem":148,
    "gn:feature_class":"P",
    "gn:feature_code":"PPL",
    "gn:name":"Aolijiuri",
    "gn:population":0,
    "gn:timezone":"Asia/Shanghai",
    "iso:country":"CN",
    "name:zho_x_preferred":[
        "\u6556\u529b\u4e5d\u65e5"
    ],
    "wof:name":"Aolijiuri",
    "wof:placetype":"locality"
},
  "geometry": {"coordinates":[123.09875,44.67788],"type":"Point"}
}