{
  "type": "Feature",
  "properties": {
    "gn:admin1_code":"16",
    "gn:asciiname":"Lingcheng",
    "gn:country_code":"CN",
    "gn:dem":168,
    "gn:feature_class":"P",
    "gn:feature_code":"PPL",
    "gn:name":"Lingcheng",
    "gn:population":0,
    "gn:timezone":"Asia/Shanghai",
    "iso:country":"CN",
    "name:deu_x_preferred":[
        "Lingcheng"
    ],
    "wof:name":"Lingcheng",
    "wof:placetype":"locality"
},
  "geometry": {"coordinates":[107.71556,22.27889],"type":"Point"}
}