{
  "type": "Feature",
  "properties": {
    "gn:admin1_code":"14.0",
    "gn:asciiname":"Dengmoze",
    "gn:country_code":"CN",
    "gn:dem":4307,
    "gn:feature_class":"P",
    "gn:feature_code":"PPL",
    "gn:name":"Dengmoze",
    "gn:population":0,
    "gn:timezone":"Asia/Urumqi",
    "iso:country":"CN",
    "name:zho_x_preferred":[
        "\u706f\u83ab\u5219"
    ],
    "wof:name":"Dengmoze",
    "wof:placetype":"locality"
},
  "geometry": {"coordinates":[94.26381000000001,31.49209],"type":"Point"}
}