{
  "type": "Feature",
  "properties": {
    "gn:admin1_code":"10",
    "gn:asciiname":"Xiaocui Huagong",
    "gn:country_code":"CN",
    "gn:dem":1560,
    "gn:feature_class":"P",
    "gn:feature_code":"PPL",
    "gn:name":"Xiaocui Huagong",
    "gn:population":0,
    "gn:timezone":"Asia/Shanghai",
    "iso:country":"CN",
    "name:zho_x_preferred":[
        "\u5c0f\u7fe0\u82b1\u5bab"
    ],
    "wof:name":"Xiaocui Huagong",
    "wof:placetype":"locality"
},
  "geometry": {"coordinates":[115.21347,41.28661],"type":"Point"}
}