{
  "type": "Feature",
  "properties": {
    "gn:admin1_code":"22.0",
    "gn:asciiname":"Simataicun",
    "gn:country_code":"CN",
    "gn:dem":284,
    "gn:feature_class":"P",
    "gn:feature_code":"PPL",
    "gn:name":"Simataicun",
    "gn:population":0,
    "gn:timezone":"Asia/Shanghai",
    "iso:country":"CN",
    "name:zho_x_preferred":[
        "\u53f8\u9a6c\u53f0\u6751"
    ],
    "wof:name":"Simataicun",
    "wof:placetype":"locality"
},
  "geometry": {"coordinates":[117.25605,40.64324000000001],"type":"Point"}
}