{
  "type": "Feature",
  "properties": {
    "gn:admin1_code":"12.0",
    "gn:asciiname":"Dahuajian",
    "gn:country_code":"CN",
    "gn:dem":1054,
    "gn:feature_class":"P",
    "gn:feature_code":"PPL",
    "gn:name":"Dahuajian",
    "gn:population":0,
    "gn:timezone":"Asia/Shanghai",
    "iso:country":"CN",
    "name:zho_x_preferred":[
        "\u5927\u6866\u5c16"
    ],
    "wof:name":"Dahuajian",
    "wof:placetype":"locality"
},
  "geometry": {"coordinates":[108.9289,29.45394000000001],"type":"Point"}
}