{
  "type": "Feature",
  "properties": {
    "gn:admin1_code":"4.0",
    "gn:asciiname":"Nanwangcun",
    "gn:country_code":"CN",
    "gn:dem":1,
    "gn:feature_class":"P",
    "gn:feature_code":"PPL",
    "gn:name":"Nanwangcun",
    "gn:population":0,
    "gn:timezone":"Asia/Shanghai",
    "iso:country":"CN",
    "name:zho_x_preferred":[
        "\u5357\u65fa\u6751"
    ],
    "wof:name":"Nanwangcun",
    "wof:placetype":"locality"
},
  "geometry": {"coordinates":[119.88892,33.0755],"type":"Point"}
}