{
  "type": "Feature",
  "properties": {
    "gn:admin1_code":"29.0",
    "gn:asciiname":"Duikuai",
    "gn:country_code":"CN",
    "gn:dem":1849,
    "gn:feature_class":"P",
    "gn:feature_code":"PPL",
    "gn:name":"Duikuai",
    "gn:population":0,
    "gn:timezone":"Asia/Shanghai",
    "iso:country":"CN",
    "name:zho_x_preferred":[
        "\u5bf9\u5757"
    ],
    "wof:name":"Duikuai",
    "wof:placetype":"locality"
},
  "geometry": {"coordinates":[104.608,27.4532],"type":"Point"}
}