{
  "type": "Feature",
  "properties": {
    "gn:admin1_code":"30",
    "gn:asciiname":"Hekeng",
    "gn:country_code":"CN",
    "gn:dem":35,
    "gn:feature_class":"P",
    "gn:feature_code":"PPL",
    "gn:name":"Hekeng",
    "gn:population":0,
    "gn:timezone":"Asia/Urumqi",
    "iso:country":"CN",
    "name:zho_x_preferred":[
        "\u548c\u5751"
    ],
    "wof:name":"Hekeng",
    "wof:placetype":"locality"
},
  "geometry": {"coordinates":[110.71378,21.92048],"type":"Point"}
}