{
  "type": "Feature",
  "properties": {
    "gn:admin1_code":"3.0",
    "gn:asciiname":"Gaoqiao",
    "gn:country_code":"CN",
    "gn:dem":297,
    "gn:feature_class":"P",
    "gn:feature_code":"PPLA4",
    "gn:name":"Gaoqiao",
    "gn:population":0,
    "gn:timezone":"Asia/Shanghai",
    "iso:country":"CN",
    "name:ceb_x_preferred":[
        "Gaoqiao"
    ],
    "name:deu_x_preferred":[
        "Gaoqiao"
    ],
    "name:swe_x_preferred":[
        "Gaoqiao"
    ],
    "name:und_x_variant":[
        "\u9ad8\u6865",
        "Gaoqiao Xiang",
        "\u9ad8\u6865\u4e61"
    ],
    "wof:name":"Gaoqiao",
    "wof:placetype":"locality"
},
  "geometry": {"coordinates":[114.20728,28.60756],"type":"Point"}
}