{
  "type": "Feature",
  "properties": {
    "gn:admin1_code":"19.0",
    "gn:asciiname":"Guojia Wobu",
    "gn:country_code":"CN",
    "gn:dem":79,
    "gn:feature_class":"P",
    "gn:feature_code":"PPL",
    "gn:name":"Guojia Wobu",
    "gn:population":0,
    "gn:timezone":"Asia/Shanghai",
    "iso:country":"CN",
    "name:zho_x_preferred":[
        "\u90ed\u5bb6\u7a9d\u5821"
    ],
    "wof:name":"Guojia Wobu",
    "wof:placetype":"locality"
},
  "geometry": {"coordinates":[122.649,42.4033],"type":"Point"}
}