{
  "type": "Feature",
  "properties": {
    "gn:admin1_code":"1.0",
    "gn:asciiname":"Chenxucun",
    "gn:country_code":"CN",
    "gn:dem":24,
    "gn:feature_class":"P",
    "gn:feature_code":"PPL",
    "gn:name":"Chenxucun",
    "gn:population":0,
    "gn:timezone":"Asia/Shanghai",
    "iso:country":"CN",
    "name:zho_x_preferred":[
        "\u9648\u5729\u6751"
    ],
    "wof:name":"Chenxucun",
    "wof:placetype":"locality"
},
  "geometry": {"coordinates":[117.53021,33.41698],"type":"Point"}
}