{
  "type": "Feature",
  "properties": {
    "gn:admin1_code":"32.0",
    "gn:asciiname":"Wang'aojing",
    "gn:country_code":"CN",
    "gn:dem":422,
    "gn:feature_class":"P",
    "gn:feature_code":"PPL",
    "gn:name":"Wang\u2019aojing",
    "gn:population":0,
    "gn:timezone":"Asia/Shanghai",
    "iso:country":"CN",
    "name:zho_x_preferred":[
        "\u738b\u5773\u4e95"
    ],
    "name:zho_x_variant":[
        "Wang\u2019aojing"
    ],
    "wof:name":"Wang'aojing",
    "wof:placetype":"locality"
},
  "geometry": {"coordinates":[103.74497,29.70127],"type":"Point"}
}