{
  "type": "Feature",
  "properties": {
    "gn:admin1_code":"1.0",
    "gn:asciiname":"Yuenancun",
    "gn:country_code":"CN",
    "gn:dem":33,
    "gn:feature_class":"P",
    "gn:feature_code":"PPL",
    "gn:name":"Yuenancun",
    "gn:population":0,
    "gn:timezone":"Asia/Shanghai",
    "iso:country":"CN",
    "name:zho_x_preferred":[
        "\u5cb3\u5357\u6751"
    ],
    "wof:name":"Yuenancun",
    "wof:placetype":"locality"
},
  "geometry": {"coordinates":[115.71895000000001,32.65824],"type":"Point"}
}