{
  "type": "Feature",
  "properties": {
    "gn:admin1_code":"1.0",
    "gn:asciiname":"Liangwancun",
    "gn:country_code":"CN",
    "gn:dem":189,
    "gn:feature_class":"P",
    "gn:feature_code":"PPL",
    "gn:name":"Liangwancun",
    "gn:population":0,
    "gn:timezone":"Asia/Shanghai",
    "iso:country":"CN",
    "name:zho_x_preferred":[
        "\u4e24\u6e7e\u6751"
    ],
    "wof:name":"Liangwancun",
    "wof:placetype":"locality"
},
  "geometry": {"coordinates":[115.74018,31.50543],"type":"Point"}
}