{
  "type": "Feature",
  "properties": {
    "gn:admin1_code":"11.0",
    "gn:asciiname":"Yinpodong",
    "gn:country_code":"CN",
    "gn:dem":900,
    "gn:feature_class":"P",
    "gn:feature_code":"PPL",
    "gn:name":"Yinpodong",
    "gn:population":0,
    "gn:timezone":"Asia/Shanghai",
    "iso:country":"CN",
    "name:zho_x_preferred":[
        "\u9634\u5761\u680b"
    ],
    "wof:name":"Yinpodong",
    "wof:placetype":"locality"
},
  "geometry": {"coordinates":[110.58709,29.46156],"type":"Point"}
}