{
  "type": "Feature",
  "properties": {
    "gn:admin1_code":"32.0",
    "gn:asciiname":"Daochaochong",
    "gn:country_code":"CN",
    "gn:dem":503,
    "gn:feature_class":"P",
    "gn:feature_code":"PPL",
    "gn:name":"Daochaochong",
    "gn:population":0,
    "gn:timezone":"Asia/Shanghai",
    "iso:country":"CN",
    "name:zho_x_preferred":[
        "\u5012\u6f6e\u51b2"
    ],
    "wof:name":"Daochaochong",
    "wof:placetype":"locality"
},
  "geometry": {"coordinates":[104.15900000000001,30.6602],"type":"Point"}
}