{
  "type": "Feature",
  "properties": {
    "gn:admin1_code":"11.0",
    "gn:asciiname":"Guluoping",
    "gn:country_code":"CN",
    "gn:dem":1181,
    "gn:feature_class":"P",
    "gn:feature_code":"PPL",
    "gn:name":"Guluoping",
    "gn:population":0,
    "gn:timezone":"Asia/Shanghai",
    "iso:country":"CN",
    "name:zho_x_preferred":[
        "Guluoping"
    ],
    "name:zho_x_variant":[
        "\u9f13\u9523\u576a"
    ],
    "wof:name":"Guluoping",
    "wof:placetype":"locality"
},
  "geometry": {"coordinates":[110.62618000000001,29.9213],"type":"Point"}
}