{
  "type": "Feature",
  "properties": {
    "gn:admin1_code":"19.0",
    "gn:asciiname":"Jiamiangou",
    "gn:country_code":"CN",
    "gn:dem":241,
    "gn:feature_class":"P",
    "gn:feature_code":"PPL",
    "gn:name":"Jiamiangou",
    "gn:population":0,
    "gn:timezone":"Asia/Shanghai",
    "iso:country":"CN",
    "name:zho_x_preferred":[
        "\u5939\u9762\u6c9f"
    ],
    "wof:name":"Jiamiangou",
    "wof:placetype":"locality"
},
  "geometry": {"coordinates":[125.077,40.9265],"type":"Point"}
}