{
  "type": "Feature",
  "properties": {
    "gn:admin1_code":"1.0",
    "gn:asciiname":"Sanguaicun",
    "gn:country_code":"CN",
    "gn:dem":39,
    "gn:feature_class":"P",
    "gn:feature_code":"PPL",
    "gn:name":"Sanguaicun",
    "gn:population":0,
    "gn:timezone":"Asia/Shanghai",
    "iso:country":"CN",
    "name:zho_x_preferred":[
        "\u4e09\u62d0\u6751"
    ],
    "wof:name":"Sanguaicun",
    "wof:placetype":"locality"
},
  "geometry": {"coordinates":[117.05652000000001,31.34967],"type":"Point"}
}