{
  "type": "Feature",
  "properties": {
    "gn:admin1_code":"9.0",
    "gn:asciiname":"Lujia",
    "gn:country_code":"CN",
    "gn:dem":837,
    "gn:feature_class":"P",
    "gn:feature_code":"PPL",
    "gn:name":"Lujia",
    "gn:population":0,
    "gn:timezone":"Asia/Shanghai",
    "iso:country":"CN",
    "name:und_x_variant":[
        "\u9646\u5bb6",
        "Lujia"
    ],
    "wof:name":"Lujia",
    "wof:placetype":"locality"
},
  "geometry": {"coordinates":[112.26683,33.98233],"type":"Point"}
}