{
  "type": "Feature",
  "properties": {
    "gn:admin1_code":"12.0",
    "gn:asciiname":"Liujia'ao",
    "gn:country_code":"CN",
    "gn:dem":547,
    "gn:feature_class":"P",
    "gn:feature_code":"PPL",
    "gn:name":"Liujia\u2019ao",
    "gn:population":0,
    "gn:timezone":"Asia/Shanghai",
    "iso:country":"CN",
    "name:und_x_variant":[
        "Liujia\u2019ao"
    ],
    "name:zho_x_preferred":[
        "\u5218\u5bb6\u51f9"
    ],
    "wof:name":"Liujia'ao",
    "wof:placetype":"locality"
},
  "geometry": {"coordinates":[110.48989,32.54483],"type":"Point"}
}