{
  "type": "Feature",
  "properties": {
    "gn:admin1_code":"16",
    "gn:asciiname":"Laobaxinzhai",
    "gn:country_code":"CN",
    "gn:dem":233,
    "gn:feature_class":"P",
    "gn:feature_code":"PPL",
    "gn:name":"Laobaxinzhai",
    "gn:population":0,
    "gn:timezone":"Asia/Shanghai",
    "iso:country":"CN",
    "name:zho_x_preferred":[
        "\u8001\u5df4\u65b0\u5be8"
    ],
    "wof:name":"Laobaxinzhai",
    "wof:placetype":"locality"
},
  "geometry": {"coordinates":[109.434,25.6452],"type":"Point"}
}