{
  "type": "Feature",
  "properties": {
    "gn:admin1_code":"31.0",
    "gn:asciiname":"Fenyuecun",
    "gn:country_code":"CN",
    "gn:dem":226,
    "gn:feature_class":"P",
    "gn:feature_code":"PPL",
    "gn:name":"Fenyuecun",
    "gn:population":0,
    "gn:timezone":"Asia/Shanghai",
    "iso:country":"CN",
    "name:zho_x_preferred":[
        "\u594b\u8dc3\u6751"
    ],
    "wof:name":"Fenyuecun",
    "wof:placetype":"locality"
},
  "geometry": {"coordinates":[109.10899999999999,18.4982],"type":"Point"}
}