{
  "type": "Feature",
  "properties": {
    "gn:admin1_code":"15.0",
    "gn:asciiname":"Yihatuoli",
    "gn:country_code":"CN",
    "gn:dem":1231,
    "gn:feature_class":"P",
    "gn:feature_code":"PPL",
    "gn:name":"Yihatuoli",
    "gn:population":0,
    "gn:timezone":"Asia/Urumqi",
    "iso:country":"CN",
    "wof:name":"Yihatuoli",
    "wof:placetype":"locality"
},
  "geometry": {"coordinates":[96.90000000000001,42.75],"type":"Point"}
}