{
  "type": "Feature",
  "properties": {
    "gn:admin1_code":"25",
    "gn:asciiname":"Nanyu",
    "gn:country_code":"CN",
    "gn:dem":266,
    "gn:feature_class":"P",
    "gn:feature_code":"PPL",
    "gn:name":"Nanyu",
    "gn:population":0,
    "gn:timezone":"Asia/Shanghai",
    "iso:country":"CN",
    "name:deu_x_preferred":[
        "Nanyu"
    ],
    "name:zho_x_preferred":[
        "\u5357\u5cea"
    ],
    "wof:name":"Nanyu",
    "wof:placetype":"locality"
},
  "geometry": {"coordinates":[118.42700000000001,35.8176],"type":"Point"}
}