{
  "type": "Feature",
  "properties": {
    "gn:admin1_code":"9.0",
    "gn:asciiname":"Zhenggounao",
    "gn:country_code":"CN",
    "gn:dem":1435,
    "gn:feature_class":"P",
    "gn:feature_code":"PPL",
    "gn:name":"Zhenggounao",
    "gn:population":0,
    "gn:timezone":"Asia/Shanghai",
    "iso:country":"CN",
    "name:zho_x_preferred":[
        "\u6b63\u6c9f\u8111"
    ],
    "wof:name":"Zhenggounao",
    "wof:placetype":"locality"
},
  "geometry": {"coordinates":[111.24499,33.80631],"type":"Point"}
}