{
  "type": "Feature",
  "properties": {
    "gn:admin1_code":"13.0",
    "gn:asciiname":"Tu'er Bulong",
    "gn:country_code":"CN",
    "gn:dem":5095,
    "gn:feature_class":"P",
    "gn:feature_code":"PPL",
    "gn:name":"Tu\u2019er Bulong",
    "gn:population":0,
    "gn:timezone":"Asia/Shanghai",
    "iso:country":"CN",
    "name:und_x_variant":[
        "Tu\u2019er Bulong",
        "\u5410\u5c14\u5e03\u9686"
    ],
    "wof:name":"Tu'er Bulong",
    "wof:placetype":"locality"
},
  "geometry": {"coordinates":[75.35887,38.26019],"type":"Point"}
}