{
  "type": "Feature",
  "properties": {
    "gn:admin1_code":"9.0",
    "gn:asciiname":"Luogou",
    "gn:country_code":"CN",
    "gn:dem":187,
    "gn:feature_class":"P",
    "gn:feature_code":"PPL",
    "gn:name":"Luogou",
    "gn:population":0,
    "gn:timezone":"Asia/Shanghai",
    "iso:country":"CN",
    "name:und_x_variant":[
        "\u7f57\u6c9f",
        "Luogou"
    ],
    "wof:name":"Luogou",
    "wof:placetype":"locality"
},
  "geometry": {"coordinates":[112.65278000000001,33.34603],"type":"Point"}
}