{
  "type": "Feature",
  "properties": {
    "gn:admin1_code":"15.0",
    "gn:asciiname":"Duojiawan",
    "gn:country_code":"CN",
    "gn:dem":1971,
    "gn:feature_class":"P",
    "gn:feature_code":"PPL",
    "gn:name":"Duojiawan",
    "gn:population":0,
    "gn:timezone":"Asia/Shanghai",
    "iso:country":"CN",
    "name:und_x_variant":[
        "\u591a\u5bb6\u6e7e"
    ],
    "wof:name":"Duojiawan",
    "wof:placetype":"locality"
},
  "geometry": {"coordinates":[104.98496000000002,34.91624],"type":"Point"}
}