{
  "type": "Feature",
  "properties": {
    "gn:admin1_code":"16.0",
    "gn:asciiname":"Menglian",
    "gn:country_code":"CN",
    "gn:dem":77,
    "gn:feature_class":"P",
    "gn:feature_code":"PPL",
    "gn:name":"Menglian",
    "gn:population":0,
    "gn:timezone":"Asia/Shanghai",
    "iso:country":"CN",
    "name:zho_x_preferred":[
        "\u5b5f\u83b2"
    ],
    "wof:name":"Menglian",
    "wof:placetype":"locality"
},
  "geometry": {"coordinates":[108.444,22.7105],"type":"Point"}
}