{
  "type": "Feature",
  "properties": {
    "gn:admin1_code":"29.0",
    "gn:asciiname":"Gongdonghe",
    "gn:country_code":"CN",
    "gn:dem":1665,
    "gn:feature_class":"P",
    "gn:feature_code":"PPL",
    "gn:name":"Gongdonghe",
    "gn:population":0,
    "gn:timezone":"Asia/Shanghai",
    "iso:country":"CN",
    "name:zho_x_preferred":[
        "\u62f1\u6d1e\u6cb3"
    ],
    "wof:name":"Gongdonghe",
    "wof:placetype":"locality"
},
  "geometry": {"coordinates":[98.8128,24.87],"type":"Point"}
}