{
  "type": "Feature",
  "properties": {
    "gn:admin1_code":"9.0",
    "gn:asciiname":"Fengbeilou",
    "gn:country_code":"CN",
    "gn:dem":80,
    "gn:feature_class":"P",
    "gn:feature_code":"PPL",
    "gn:name":"Fengbeilou",
    "gn:population":0,
    "gn:timezone":"Asia/Shanghai",
    "iso:country":"CN",
    "name:zho_x_preferred":[
        "\u51af\u5317\u697c"
    ],
    "wof:name":"Fengbeilou",
    "wof:placetype":"locality"
},
  "geometry": {"coordinates":[115.13697000000001,31.93532],"type":"Point"}
}