{
  "type": "Feature",
  "properties": {
    "gn:admin1_code":"15.0",
    "gn:asciiname":"Potou",
    "gn:country_code":"CN",
    "gn:dem":1265,
    "gn:feature_class":"P",
    "gn:feature_code":"PPL",
    "gn:name":"Potou",
    "gn:population":0,
    "gn:timezone":"Asia/Shanghai",
    "iso:country":"CN",
    "name:zho_x_preferred":[
        "\u5761\u5934"
    ],
    "wof:name":"Potou",
    "wof:placetype":"locality"
},
  "geometry": {"coordinates":[107.63800000000001,35.3201],"type":"Point"}
}