{
  "type": "Feature",
  "properties": {
    "gn:admin1_code":"25",
    "gn:asciiname":"Lizhuangxiacun",
    "gn:country_code":"CN",
    "gn:dem":161,
    "gn:feature_class":"P",
    "gn:feature_code":"PPL",
    "gn:name":"Lizhuangxiacun",
    "gn:population":0,
    "gn:timezone":"Asia/Shanghai",
    "iso:country":"CN",
    "name:zho_x_preferred":[
        "\u91cc\u5e84\u4e0b\u6751"
    ],
    "wof:name":"Lizhuangxiacun",
    "wof:placetype":"locality"
},
  "geometry": {"coordinates":[119.004,35.7174],"type":"Point"}
}