{
  "type": "Feature",
  "properties": {
    "gn:admin1_code":"2.0",
    "gn:asciiname":"Huangtangting",
    "gn:country_code":"CN",
    "gn:dem":505,
    "gn:feature_class":"P",
    "gn:feature_code":"PPL",
    "gn:name":"Huangtangting",
    "gn:population":0,
    "gn:timezone":"Asia/Shanghai",
    "iso:country":"CN",
    "name:zho_x_preferred":[
        "\u9ec4\u5858\u6c40"
    ],
    "wof:name":"Huangtangting",
    "wof:placetype":"locality"
},
  "geometry": {"coordinates":[118.84573,28.39236],"type":"Point"}
}