{
  "type": "Feature",
  "properties": {
    "gn:admin1_code":"9.0",
    "gn:asciiname":"Duchenggang",
    "gn:country_code":"CN",
    "gn:dem":55,
    "gn:feature_class":"P",
    "gn:feature_code":"PPL",
    "gn:name":"Duchenggang",
    "gn:population":0,
    "gn:timezone":"Asia/Shanghai",
    "iso:country":"CN",
    "name:zho_x_preferred":[
        "\u90fd\u57ce\u5c97"
    ],
    "wof:name":"Duchenggang",
    "wof:placetype":"locality"
},
  "geometry": {"coordinates":[114.39008,33.81314],"type":"Point"}
}