{
  "type": "Feature",
  "properties": {
    "gn:admin1_code":"32.0",
    "gn:asciiname":"Yisheng",
    "gn:country_code":"CN",
    "gn:dem":3300,
    "gn:feature_class":"P",
    "gn:feature_code":"PPL",
    "gn:name":"Yisheng",
    "gn:population":0,
    "gn:timezone":"Asia/Shanghai",
    "iso:country":"CN",
    "name:zho_x_preferred":[
        "\u4f9d\u751f"
    ],
    "wof:name":"Yisheng",
    "wof:placetype":"locality"
},
  "geometry": {"coordinates":[101.56399999999999,31.7226],"type":"Point"}
}