{
  "type": "Feature",
  "properties": {
    "gn:admin1_code":"14.0",
    "gn:asciiname":"Langqiannong",
    "gn:country_code":"CN",
    "gn:dem":4610,
    "gn:feature_class":"P",
    "gn:feature_code":"PPL",
    "gn:name":"Langqiannong",
    "gn:population":0,
    "gn:timezone":"Asia/Urumqi",
    "iso:country":"CN",
    "name:zho_x_preferred":[
        "\u6717\u8fc1\u5f04"
    ],
    "wof:name":"Langqiannong",
    "wof:placetype":"locality"
},
  "geometry": {"coordinates":[91.62,31.73095],"type":"Point"}
}