{
  "type": "Feature",
  "properties": {
    "gn:admin1_code":"14.0",
    "gn:asciiname":"Baidengge",
    "gn:country_code":"CN",
    "gn:dem":4230,
    "gn:feature_class":"P",
    "gn:feature_code":"PPL",
    "gn:name":"Baidengge",
    "gn:population":0,
    "gn:timezone":"Asia/Urumqi",
    "iso:country":"CN",
    "name:zho_x_preferred":[
        "\u767d\u706f\u5404"
    ],
    "wof:name":"Baidengge",
    "wof:placetype":"locality"
},
  "geometry": {"coordinates":[95.86942999999999,30.99505],"type":"Point"}
}