{
  "type": "Feature",
  "properties": {
    "gn:admin1_code":"18",
    "gn:asciiname":"Shangweilao",
    "gn:country_code":"CN",
    "gn:dem":827,
    "gn:feature_class":"P",
    "gn:feature_code":"PPL",
    "gn:name":"Shangweilao",
    "gn:population":0,
    "gn:timezone":"Asia/Shanghai",
    "iso:country":"CN",
    "name:zho_x_preferred":[
        "\u4e0a\u5c3e\u52b3"
    ],
    "wof:name":"Shangweilao",
    "wof:placetype":"locality"
},
  "geometry": {"coordinates":[105.971,24.8299],"type":"Point"}
}