{
  "type": "Feature",
  "properties": {
    "gn:admin1_code":"26.0",
    "gn:asciiname":"Jiaquancun",
    "gn:country_code":"CN",
    "gn:dem":1340,
    "gn:feature_class":"P",
    "gn:feature_code":"PPL",
    "gn:name":"Jiaquancun",
    "gn:population":0,
    "gn:timezone":"Asia/Shanghai",
    "iso:country":"CN",
    "name:zho_x_preferred":[
        "\u8d3e\u5708\u6751"
    ],
    "wof:name":"Jiaquancun",
    "wof:placetype":"locality"
},
  "geometry": {"coordinates":[107.64335,37.68147],"type":"Point"}
}