{
  "type": "Feature",
  "properties": {
    "gn:admin1_code":"8.0",
    "gn:asciiname":"Dahexicun",
    "gn:country_code":"CN",
    "gn:dem":257,
    "gn:feature_class":"P",
    "gn:feature_code":"PPL",
    "gn:name":"Dahexicun",
    "gn:population":0,
    "gn:timezone":"Asia/Shanghai",
    "iso:country":"CN",
    "name:zho_x_preferred":[
        "\u5927\u6cb3\u897f\u6751"
    ],
    "wof:name":"Dahexicun",
    "wof:placetype":"locality"
},
  "geometry": {"coordinates":[124.02173999999999,53.37941],"type":"Point"}
}