{
  "type": "Feature",
  "properties": {
    "gn:admin1_code":"19.0",
    "gn:asciiname":"Wanghaicun",
    "gn:country_code":"CN",
    "gn:dem":7,
    "gn:feature_class":"P",
    "gn:feature_code":"PPL",
    "gn:name":"Wanghaicun",
    "gn:population":0,
    "gn:timezone":"Asia/Shanghai",
    "iso:country":"CN",
    "name:zho_x_preferred":[
        "\u671b\u6d77\u6751"
    ],
    "wof:name":"Wanghaicun",
    "wof:placetype":"locality"
},
  "geometry": {"coordinates":[121.523,39.7069],"type":"Point"}
}