{
  "type": "Feature",
  "properties": {
    "gn:admin1_code":"11.0",
    "gn:asciiname":"Xiagongtang",
    "gn:country_code":"CN",
    "gn:dem":79,
    "gn:feature_class":"P",
    "gn:feature_code":"PPL",
    "gn:name":"Xiagongtang",
    "gn:population":0,
    "gn:timezone":"Asia/Shanghai",
    "iso:country":"CN",
    "name:zho_x_preferred":[
        "\u867e\u516c\u5858"
    ],
    "wof:name":"Xiagongtang",
    "wof:placetype":"locality"
},
  "geometry": {"coordinates":[112.62602,26.77544],"type":"Point"}
}