{
  "type": "Feature",
  "properties": {
    "gn:admin1_code":"16",
    "gn:asciiname":"Linhe",
    "gn:country_code":"CN",
    "gn:dem":87,
    "gn:feature_class":"P",
    "gn:feature_code":"PPL",
    "gn:name":"Linhe",
    "gn:population":0,
    "gn:timezone":"Asia/Shanghai",
    "iso:country":"CN",
    "name:ceb_x_preferred":[
        "Linhe"
    ],
    "name:deu_x_preferred":[
        "Linhe"
    ],
    "name:zho_x_preferred":[
        "\u6dcb\u548c"
    ],
    "wof:name":"Linhe",
    "wof:placetype":"locality"
},
  "geometry": {"coordinates":[107.941,22.8091],"type":"Point"}
}