{
  "type": "Feature",
  "properties": {
    "gn:admin1_code":"25",
    "gn:asciiname":"Xingsi",
    "gn:country_code":"CN",
    "gn:dem":31,
    "gn:feature_class":"P",
    "gn:feature_code":"PPL",
    "gn:name":"Xingsi",
    "gn:population":0,
    "gn:timezone":"Asia/Shanghai",
    "iso:country":"CN",
    "name:zho_x_preferred":[
        "\u90a2\u5bfa"
    ],
    "wof:name":"Xingsi",
    "wof:placetype":"locality"
},
  "geometry": {"coordinates":[116.233,36.7178],"type":"Point"}
}