{
  "type": "Feature",
  "properties": {
    "gn:admin1_code":"04",
    "gn:asciiname":"Huashi",
    "gn:country_code":"CN",
    "gn:dem":8,
    "gn:feature_class":"P",
    "gn:feature_code":"PPLA4",
    "gn:name":"Huashi",
    "gn:population":0,
    "gn:timezone":"Asia/Shanghai",
    "iso:country":"CN",
    "name:deu_x_preferred":[
        "Huashi"
    ],
    "name:und_x_variant":[
        "Hua-shu",
        "Hua-shih",
        "Hua-shu-chen",
        "Huashi Zhen"
    ],
    "name:zho_x_preferred":[
        "\u534e\u58eb"
    ],
    "name:zho_x_variant":[
        "\u534e\u58eb\u9547"
    ],
    "wof:name":"Huashi",
    "wof:placetype":"locality"
},
  "geometry": {"coordinates":[120.46335000000001,31.83439000000001],"type":"Point"}
}