{
  "type": "Feature",
  "properties": {
    "gn:admin1_code":"25",
    "gn:asciiname":"Zhangdarenjia",
    "gn:country_code":"CN",
    "gn:dem":19,
    "gn:feature_class":"P",
    "gn:feature_code":"PPL",
    "gn:name":"Zhangdarenjia",
    "gn:population":0,
    "gn:timezone":"Asia/Shanghai",
    "iso:country":"CN",
    "name:zho_x_preferred":[
        "\u5f20\u5927\u4eba\u5bb6"
    ],
    "wof:name":"Zhangdarenjia",
    "wof:placetype":"locality"
},
  "geometry": {"coordinates":[117.099,37.2267],"type":"Point"}
}