{
  "type": "Feature",
  "properties": {
    "gn:admin1_code":"24.0",
    "gn:asciiname":"Jiducun",
    "gn:country_code":"CN",
    "gn:dem":599,
    "gn:feature_class":"P",
    "gn:feature_code":"PPL",
    "gn:name":"Jiducun",
    "gn:population":0,
    "gn:timezone":"Asia/Shanghai",
    "iso:country":"CN",
    "name:zho_x_preferred":[
        "\u8ba1\u90fd\u6751"
    ],
    "wof:name":"Jiducun",
    "wof:placetype":"locality"
},
  "geometry": {"coordinates":[111.16524,34.86685],"type":"Point"}
}