{
  "type": "Feature",
  "properties": {
    "gn:admin1_code":"2.0",
    "gn:asciiname":"Raochuan",
    "gn:country_code":"CN",
    "gn:dem":149,
    "gn:feature_class":"P",
    "gn:feature_code":"PPL",
    "gn:name":"Raochuan",
    "gn:population":0,
    "gn:timezone":"Asia/Shanghai",
    "iso:country":"CN",
    "name:zho_x_preferred":[
        "\u7ed5\u5ddd"
    ],
    "wof:name":"Raochuan",
    "wof:placetype":"locality"
},
  "geometry": {"coordinates":[120.14891,29.10815],"type":"Point"}
}