{
  "type": "Feature",
  "properties": {
    "gn:admin1_code":"15.0",
    "gn:asciiname":"Xiadongzigou",
    "gn:country_code":"CN",
    "gn:dem":1443,
    "gn:feature_class":"P",
    "gn:feature_code":"PPL",
    "gn:name":"Xiadongzigou",
    "gn:population":0,
    "gn:timezone":"Asia/Shanghai",
    "iso:country":"CN",
    "name:zho_x_preferred":[
        "\u4e0b\u6d1e\u5b50\u6c9f"
    ],
    "wof:name":"Xiadongzigou",
    "wof:placetype":"locality"
},
  "geometry": {"coordinates":[108.539,35.4049],"type":"Point"}
}