{
  "type": "Feature",
  "properties": {
    "gn:admin1_code":"26.0",
    "gn:asciiname":"Pingxihejie",
    "gn:country_code":"CN",
    "gn:dem":1254,
    "gn:feature_class":"P",
    "gn:feature_code":"PPL",
    "gn:name":"Pingxihejie",
    "gn:population":0,
    "gn:timezone":"Asia/Shanghai",
    "iso:country":"CN",
    "name:zho_x_preferred":[
        "\u5e73\u6eaa\u6cb3\u8857"
    ],
    "wof:name":"Pingxihejie",
    "wof:placetype":"locality"
},
  "geometry": {"coordinates":[109.33993999999998,31.86631],"type":"Point"}
}