{
  "type": "Feature",
  "properties": {
    "gn:admin1_code":"19.0",
    "gn:asciiname":"Shuangmiaocun",
    "gn:country_code":"CN",
    "gn:dem":79,
    "gn:feature_class":"P",
    "gn:feature_code":"PPL",
    "gn:name":"Shuangmiaocun",
    "gn:population":0,
    "gn:timezone":"Asia/Shanghai",
    "iso:country":"CN",
    "name:zho_x_preferred":[
        "\u53cc\u5e99\u6751"
    ],
    "wof:name":"Shuangmiaocun",
    "wof:placetype":"locality"
},
  "geometry": {"coordinates":[123.98999999999999,40.2026],"type":"Point"}
}