{
  "type": "Feature",
  "properties": {
    "gn:admin1_code":"29",
    "gn:asciiname":"Jincheng",
    "gn:country_code":"CN",
    "gn:dem":1911,
    "gn:feature_class":"P",
    "gn:feature_code":"PPLA4",
    "gn:name":"Jincheng",
    "gn:population":0,
    "gn:timezone":"Asia/Shanghai",
    "iso:country":"CN",
    "name:und_x_variant":[
        "Chin-ning",
        "Chin-ch\u2019eng",
        "\u664b\u57ce",
        "Jincheng Zhen",
        "\u664b\u57ce\u9547",
        "Jincheng"
    ],
    "wof:name":"Jincheng",
    "wof:placetype":"locality"
},
  "geometry": {"coordinates":[102.74417,24.70222],"type":"Point"}
}