{
  "type": "Feature",
  "properties": {
    "gn:admin1_code":"18",
    "gn:asciiname":"Mulian",
    "gn:country_code":"CN",
    "gn:dem":644,
    "gn:feature_class":"P",
    "gn:feature_code":"PPL",
    "gn:name":"Mulian",
    "gn:population":0,
    "gn:timezone":"Asia/Shanghai",
    "iso:country":"CN",
    "name:zho_x_preferred":[
        "\u6bcd\u7ec3"
    ],
    "wof:name":"Mulian",
    "wof:placetype":"locality"
},
  "geometry": {"coordinates":[106.886,25.2511],"type":"Point"}
}