{
  "type": "Feature",
  "properties": {
    "gn:admin1_code":"4.0",
    "gn:asciiname":"Jinxi",
    "gn:country_code":"CN",
    "gn:dem":6,
    "gn:feature_class":"P",
    "gn:feature_code":"PPLA4",
    "gn:name":"Jinxi",
    "gn:population":0,
    "gn:timezone":"Asia/Shanghai",
    "iso:country":"CN",
    "name:ceb_x_preferred":[
        "Jinxi"
    ],
    "name:deu_x_preferred":[
        "Jinxi"
    ],
    "name:und_x_variant":[
        "Jinxi Zhen"
    ],
    "name:zho_x_preferred":[
        "\u9526\u6eaa"
    ],
    "name:zho_x_variant":[
        "\u9526\u6eaa\u9547"
    ],
    "wof:name":"Jinxi",
    "wof:placetype":"locality"
},
  "geometry": {"coordinates":[120.8933,31.1793],"type":"Point"}
}