{
  "type": "Feature",
  "properties": {
    "gn:admin1_code":"26.0",
    "gn:asciiname":"Anmencun",
    "gn:country_code":"CN",
    "gn:dem":1556,
    "gn:feature_class":"P",
    "gn:feature_code":"PPL",
    "gn:name":"Anmencun",
    "gn:population":0,
    "gn:timezone":"Asia/Shanghai",
    "iso:country":"CN",
    "name:zho_x_preferred":[
        "\u5b89\u95e8\u6751"
    ],
    "wof:name":"Anmencun",
    "wof:placetype":"locality"
},
  "geometry": {"coordinates":[108.38523000000001,37.27395],"type":"Point"}
}