{
  "type": "Feature",
  "properties": {
    "gn:admin1_code":"4.0",
    "gn:asciiname":"Lijialing",
    "gn:country_code":"CN",
    "gn:dem":2,
    "gn:feature_class":"P",
    "gn:feature_code":"PPL",
    "gn:name":"Lijialing",
    "gn:population":0,
    "gn:timezone":"Asia/Shanghai",
    "iso:country":"CN",
    "name:und_x_variant":[
        "\u674e\u5bb6\u51cc"
    ],
    "name:zho_x_preferred":[
        "\u674e\u5bb6\u51cc"
    ],
    "wof:name":"Lijialing",
    "wof:placetype":"locality"
},
  "geometry": {"coordinates":[120.73436,32.53076],"type":"Point"}
}