{
  "type": "Feature",
  "properties": {
    "gn:admin1_code":"11.0",
    "gn:asciiname":"Guanzhuba",
    "gn:country_code":"CN",
    "gn:dem":424,
    "gn:feature_class":"P",
    "gn:feature_code":"PPL",
    "gn:name":"Guanzhuba",
    "gn:population":0,
    "gn:timezone":"Asia/Shanghai",
    "iso:country":"CN",
    "name:zho_x_preferred":[
        "\u7ba1\u7af9\u575d"
    ],
    "wof:name":"Guanzhuba",
    "wof:placetype":"locality"
},
  "geometry": {"coordinates":[113.8946,25.62378],"type":"Point"}
}