{
  "type": "Feature",
  "properties": {
    "gn:admin1_code":"12.0",
    "gn:asciiname":"Zhoucaidun",
    "gn:country_code":"CN",
    "gn:dem":28,
    "gn:feature_class":"P",
    "gn:feature_code":"PPL",
    "gn:name":"Zhoucaidun",
    "gn:population":0,
    "gn:timezone":"Asia/Shanghai",
    "iso:country":"CN",
    "name:und_x_variant":[
        "\u5468\u8521\u58a9"
    ],
    "wof:name":"Zhoucaidun",
    "wof:placetype":"locality"
},
  "geometry": {"coordinates":[114.10984999999999,30.14103],"type":"Point"}
}