{
  "type": "Feature",
  "properties": {
    "gn:admin1_code":"24.0",
    "gn:asciiname":"Xinbicun",
    "gn:country_code":"CN",
    "gn:dem":773,
    "gn:feature_class":"P",
    "gn:feature_code":"PPL",
    "gn:name":"Xinbicun",
    "gn:population":0,
    "gn:timezone":"Asia/Shanghai",
    "iso:country":"CN",
    "name:zho_x_preferred":[
        "\u8f9b\u58c1\u6751"
    ],
    "wof:name":"Xinbicun",
    "wof:placetype":"locality"
},
  "geometry": {"coordinates":[112.6892,35.5511],"type":"Point"}
}