{
  "type": "Feature",
  "properties": {
    "gn:admin1_code":"7",
    "gn:asciiname":"Meilingtou",
    "gn:country_code":"CN",
    "gn:dem":967,
    "gn:feature_class":"P",
    "gn:feature_code":"PPL",
    "gn:name":"Meilingtou",
    "gn:population":0,
    "gn:timezone":"Asia/Shanghai",
    "iso:country":"CN",
    "name:und_x_variant":[
        "\u6885\u5cad\u5934"
    ],
    "wof:name":"Meilingtou",
    "wof:placetype":"locality"
},
  "geometry": {"coordinates":[118.52106000000001,25.63063],"type":"Point"}
}