{
  "type": "Feature",
  "properties": {
    "gn:admin1_code":"03",
    "gn:asciiname":"Chengshang",
    "gn:country_code":"CN",
    "gn:dem":93,
    "gn:feature_class":"P",
    "gn:feature_code":"PPLA4",
    "gn:name":"Chengshang",
    "gn:population":0,
    "gn:timezone":"Asia/Shanghai",
    "iso:country":"CN",
    "name:und_x_variant":[
        "\u57ce\u4e0a",
        "Chengshang Xiang",
        "\u57ce\u4e0a\u4e61"
    ],
    "wof:name":"Chengshang",
    "wof:placetype":"locality"
},
  "geometry": {"coordinates":[115.64648,27.67928],"type":"Point"}
}