{
  "type": "Feature",
  "properties": {
    "gn:admin1_code":"8.0",
    "gn:asciiname":"Sanshisangongli Linchang",
    "gn:country_code":"CN",
    "gn:dem":438,
    "gn:feature_class":"P",
    "gn:feature_code":"PPLF",
    "gn:name":"Sanshisangongli Linchang",
    "gn:population":0,
    "gn:timezone":"Asia/Shanghai",
    "iso:country":"CN",
    "name:und_x_variant":[
        "\u4e09\u5341\u4e09\u516c\u91cc\u6797\u573a"
    ],
    "wof:name":"Sanshisangongli Linchang",
    "wof:placetype":"locality"
},
  "geometry": {"coordinates":[130.98781,43.83832],"type":"Point"}
}