{
  "type": "Feature",
  "properties": {
    "gn:admin1_code":"25.0",
    "gn:asciiname":"Tiantai",
    "gn:cc2":"CN",
    "gn:country_code":"CN",
    "gn:dem":83,
    "gn:feature_class":"P",
    "gn:feature_code":"PPL",
    "gn:name":"Tiantai",
    "gn:population":0,
    "gn:timezone":"Asia/Shanghai",
    "iso:country":"CN",
    "name:zho_x_preferred":[
        "\u5929\u53f0"
    ],
    "wof:name":"Tiantai",
    "wof:placetype":"locality"
},
  "geometry": {"coordinates":[119.65817,36.1183],"type":"Point"}
}