{
  "type": "Feature",
  "properties": {
    "gn:admin1_code":"09",
    "gn:asciiname":"Ranghe",
    "gn:country_code":"CN",
    "gn:dem":144,
    "gn:feature_class":"P",
    "gn:feature_code":"PPLA4",
    "gn:name":"Ranghe",
    "gn:population":0,
    "gn:timezone":"Asia/Shanghai",
    "iso:country":"CN",
    "name:und_x_variant":[
        "Kun-ho",
        "Jang-ho",
        "Jang-ho-chen",
        "Jangho Cheno",
        "\u703c\u6cb3",
        "Ranghe"
    ],
    "wof:name":"Ranghe",
    "wof:placetype":"locality"
},
  "geometry": {"coordinates":[112.85082,33.69223],"type":"Point"}
}