{
  "type": "Feature",
  "properties": {
    "gn:admin1_code":"33.0",
    "gn:asciiname":"Liaoye",
    "gn:country_code":"CN",
    "gn:dem":582,
    "gn:feature_class":"P",
    "gn:feature_code":"PPL",
    "gn:name":"Liaoye",
    "gn:population":0,
    "gn:timezone":"Asia/Shanghai",
    "iso:country":"CN",
    "name:zho_x_preferred":[
        "\u84fc\u53f6"
    ],
    "wof:name":"Liaoye",
    "wof:placetype":"locality"
},
  "geometry": {"coordinates":[109.27193,31.03789],"type":"Point"}
}