{
  "type": "Feature",
  "properties": {
    "gn:admin1_code":"32.0",
    "gn:asciiname":"Heipitan",
    "gn:country_code":"CN",
    "gn:dem":460,
    "gn:feature_class":"P",
    "gn:feature_code":"PPL",
    "gn:name":"Heipitan",
    "gn:population":0,
    "gn:timezone":"Asia/Shanghai",
    "iso:country":"CN",
    "name:zho_x_preferred":[
        "\u9ed1\u76ae\u6ee9"
    ],
    "wof:name":"Heipitan",
    "wof:placetype":"locality"
},
  "geometry": {"coordinates":[105.17072,28.65193],"type":"Point"}
}