{
  "type": "Feature",
  "properties": {
    "gn:admin1_code":"32.0",
    "gn:asciiname":"Huangjiaqing",
    "gn:country_code":"CN",
    "gn:dem":2450,
    "gn:feature_class":"P",
    "gn:feature_code":"PPL",
    "gn:name":"Huangjiaqing",
    "gn:population":0,
    "gn:timezone":"Asia/Shanghai",
    "iso:country":"CN",
    "name:zho_x_preferred":[
        "\u9ec4\u5bb6\u7b90"
    ],
    "wof:name":"Huangjiaqing",
    "wof:placetype":"locality"
},
  "geometry": {"coordinates":[102.78400000000001,26.5236],"type":"Point"}
}