{
  "type": "Feature",
  "properties": {
    "gn:admin1_code":"29.0",
    "gn:asciiname":"Bajiaduo",
    "gn:country_code":"CN",
    "gn:dem":1681,
    "gn:feature_class":"P",
    "gn:feature_code":"PPL",
    "gn:name":"Bajiaduo",
    "gn:population":0,
    "gn:timezone":"Asia/Shanghai",
    "iso:country":"CN",
    "name:zho_x_preferred":[
        "\u5df4\u7532\u6735"
    ],
    "wof:name":"Bajiaduo",
    "wof:placetype":"locality"
},
  "geometry": {"coordinates":[98.86750000000001,27.0496],"type":"Point"}
}