{
  "type": "Feature",
  "properties": {
    "gn:admin1_code":"1.0",
    "gn:asciiname":"Hekoucun",
    "gn:country_code":"CN",
    "gn:dem":30,
    "gn:feature_class":"P",
    "gn:feature_code":"PPL",
    "gn:name":"Hekoucun",
    "gn:population":0,
    "gn:timezone":"Asia/Shanghai",
    "iso:country":"CN",
    "name:und_x_variant":[
        "Hekou"
    ],
    "name:zho_x_preferred":[
        "\u6cb3\u53e3\u6751"
    ],
    "wof:name":"Hekoucun",
    "wof:placetype":"locality"
},
  "geometry": {"coordinates":[115.68965,32.52929],"type":"Point"}
}