{
  "type": "Feature",
  "properties": {
    "gn:admin1_code":"33.0",
    "gn:asciiname":"Dashashu",
    "gn:country_code":"CN",
    "gn:dem":449,
    "gn:feature_class":"P",
    "gn:feature_code":"PPL",
    "gn:name":"Dashashu",
    "gn:population":0,
    "gn:timezone":"Asia/Shanghai",
    "iso:country":"CN",
    "name:zho_x_preferred":[
        "\u5927\u6749\u6811"
    ],
    "wof:name":"Dashashu",
    "wof:placetype":"locality"
},
  "geometry": {"coordinates":[109.07340000000001,28.5007],"type":"Point"}
}