{
  "type": "Feature",
  "properties": {
    "gn:admin1_code":"4.0",
    "gn:asciiname":"Dongningqiao",
    "gn:country_code":"CN",
    "gn:dem":4,
    "gn:feature_class":"P",
    "gn:feature_code":"PPL",
    "gn:name":"Dongningqiao",
    "gn:population":0,
    "gn:timezone":"Asia/Shanghai",
    "iso:country":"CN",
    "name:zho_x_preferred":[
        "Dongningqiao"
    ],
    "name:zho_x_variant":[
        "\u4e1c\u5b81\u6865"
    ],
    "wof:name":"Dongningqiao",
    "wof:placetype":"locality"
},
  "geometry": {"coordinates":[121.11696000000001,32.44807],"type":"Point"}
}