{
  "type": "Feature",
  "properties": {
    "gn:admin1_code":"29.0",
    "gn:asciiname":"Gudibao",
    "gn:country_code":"CN",
    "gn:dem":1356,
    "gn:feature_class":"P",
    "gn:feature_code":"PPL",
    "gn:name":"Gudibao",
    "gn:population":0,
    "gn:timezone":"Asia/Shanghai",
    "iso:country":"CN",
    "name:zho_x_preferred":[
        "\u8c37\u5730\u5305"
    ],
    "wof:name":"Gudibao",
    "wof:placetype":"locality"
},
  "geometry": {"coordinates":[98.14230000000001,24.8812],"type":"Point"}
}