{
  "type": "Feature",
  "properties": {
    "gn:admin1_code":"3",
    "gn:asciiname":"Gaochuan",
    "gn:country_code":"CN",
    "gn:dem":107,
    "gn:feature_class":"P",
    "gn:feature_code":"PPL",
    "gn:name":"Gaochuan",
    "gn:population":0,
    "gn:timezone":"Asia/Shanghai",
    "iso:country":"CN",
    "name:zho_x_preferred":[
        "\u9ad8\u5ddd"
    ],
    "wof:name":"Gaochuan",
    "wof:placetype":"locality"
},
  "geometry": {"coordinates":[114.298,27.0163],"type":"Point"}
}