{
  "type": "Feature",
  "properties": {
    "gn:admin1_code":"24.0",
    "gn:asciiname":"Yulin",
    "gn:country_code":"CN",
    "gn:dem":1202,
    "gn:feature_class":"P",
    "gn:feature_code":"PPL",
    "gn:name":"Yulin",
    "gn:population":0,
    "gn:timezone":"Asia/Shanghai",
    "iso:country":"CN",
    "name:zho_x_preferred":[
        "\u6986\u6797"
    ],
    "wof:name":"Yulin",
    "wof:placetype":"locality"
},
  "geometry": {"coordinates":[111.9181,37.64931],"type":"Point"}
}