{
  "type": "Feature",
  "properties": {
    "gn:admin1_code":"9.0",
    "gn:asciiname":"Sanlikou",
    "gn:country_code":"CN",
    "gn:dem":55,
    "gn:feature_class":"P",
    "gn:feature_code":"PPL",
    "gn:name":"Sanlikou",
    "gn:population":0,
    "gn:timezone":"Asia/Shanghai",
    "iso:country":"CN",
    "name:zho_x_preferred":[
        "\u4e09\u91cc\u53e3"
    ],
    "wof:name":"Sanlikou",
    "wof:placetype":"locality"
},
  "geometry": {"coordinates":[114.7163,34.0239],"type":"Point"}
}