{
  "type": "Feature",
  "properties": {
    "gn:country":"CN",
    "gn:fcode":"ADM3",
    "gn:pop":0,
    "iso:country":"CN",
    "name:deu_x_preferred":[
        "Baishui"
    ],
    "name:eng_x_preferred":[
        "Baishui County"
    ],
    "name:fas_x_preferred":[
        "\u0634\u0647\u0631\u0633\u062a\u0627\u0646 \u0628\u0627\u06cc\u0634\u0648\u06cc"
    ],
    "name:gan_x_preferred":[
        "\u767d\u6c34\u53bf"
    ],
    "name:jpn_x_preferred":[
        "\u767d\u6c34\u770c"
    ],
    "name:kor_x_preferred":[
        "\ubc14\uc774\uc218\uc774\ud604"
    ],
    "name:nan_x_preferred":[
        "Pe\u030dk-s\u00fai-ko\u0101n"
    ],
    "name:nld_x_preferred":[
        "Baishui"
    ],
    "name:nob_x_preferred":[
        "Baishui"
    ],
    "name:rus_x_preferred":[
        "\u0411\u0430\u0439\u0448\u0443\u0439"
    ],
    "name:swe_x_preferred":[
        "Baishui"
    ],
    "name:unk_x_variant":[
        "Pai-shui Hsien"
    ],
    "name:vie_x_preferred":[
        "B\u1ea1ch Th\u1ee7y"
    ],
    "name:wuu_x_preferred":[
        "\u767d\u6c34\u53bf"
    ],
    "name:yue_x_preferred":[
        "\u767d\u6c34"
    ],
    "name:zho_x_preferred":[
        "\u767d\u6c34\u53bf"
    ],
    "name:zho_x_variant":[
        "\u767d\u6c34"
    ],
    "qs:name":"Baishui Xian",
    "qs:photos_9r":0,
    "qs:photos_sr":0,
    "qs:pop_sr":"0",
    "wd:wordcount":194,
    "wof:name":"Baishui Xian",
    "wof:placetype":"localadmin",
    "wof:population":0
},
  "geometry": {"coordinates":[109.51721999999999,35.22222],"type":"Point"}
}