{
  "type": "Feature",
  "properties": {
    "gn:country":"CN",
    "gn:fcode":"ADM3",
    "gn:pop":0,
    "iso:country":"CN",
    "name:unk_x_variant":[
        "Pai-shui Hsien"
    ],
    "name:zho_x_preferred":[
        "\u767d\u6c34\u53bf"
    ],
    "name:zho_x_variant":[
        "\u767d\u6c34"
    ],
    "qs:name":"Baishui Xian",
    "qs:photos_9r":0,
    "qs:photos_sr":0,
    "qs:pop_sr":"0",
    "wd:wordcount":194,
    "wof:name":"Baishui Xian",
    "wof:placetype":"localadmin",
    "wof:population":0
},
  "geometry": {"coordinates":[109.51721999999999,35.22222],"type":"Point"}
}