{
  "type": "Feature",
  "properties": {
    "gn:admin1_code":"9",
    "gn:asciiname":"Liangshuangmiao",
    "gn:country_code":"CN",
    "gn:dem":47,
    "gn:feature_class":"P",
    "gn:feature_code":"PPL",
    "gn:name":"Liangshuangmiao",
    "gn:population":0,
    "gn:timezone":"Asia/Shanghai",
    "iso:country":"CN",
    "name:zho_x_preferred":[
        "\u6881\u53cc\u5e99"
    ],
    "wof:name":"Liangshuangmiao",
    "wof:placetype":"locality"
},
  "geometry": {"coordinates":[115.515,34.0443],"type":"Point"}
}