{
  "type": "Feature",
  "properties": {
    "gn:admin1_code":"3.0",
    "gn:asciiname":"Shuangqiaoshan",
    "gn:country_code":"CN",
    "gn:dem":421,
    "gn:feature_class":"P",
    "gn:feature_code":"PPL",
    "gn:name":"Shuangqiaoshan",
    "gn:population":0,
    "gn:timezone":"Asia/Shanghai",
    "iso:country":"CN",
    "name:und_x_variant":[
        "\u53cc\u6865\u5c71"
    ],
    "wof:name":"Shuangqiaoshan",
    "wof:placetype":"locality"
},
  "geometry": {"coordinates":[115.09088,29.37568],"type":"Point"}
}