{
  "type": "Feature",
  "properties": {
    "gn:admin1_code":"29.0",
    "gn:asciiname":"Nuqu",
    "gn:country_code":"CN",
    "gn:dem":1842,
    "gn:feature_class":"P",
    "gn:feature_code":"PPL",
    "gn:name":"Nuqu",
    "gn:population":0,
    "gn:timezone":"Asia/Shanghai",
    "iso:country":"CN",
    "name:zho_x_preferred":[
        "\u6012\u66f2"
    ],
    "wof:name":"Nuqu",
    "wof:placetype":"locality"
},
  "geometry": {"coordinates":[98.89279999999999,27.2706],"type":"Point"}
}