{
  "type": "Feature",
  "properties": {
    "gn:admin1_code":"8.0",
    "gn:asciiname":"Hashihahoutun",
    "gn:country_code":"CN",
    "gn:dem":158,
    "gn:feature_class":"P",
    "gn:feature_code":"PPL",
    "gn:name":"Hashihahoutun",
    "gn:population":0,
    "gn:timezone":"Asia/Shanghai",
    "iso:country":"CN",
    "name:zho_x_preferred":[
        "\u54c8\u4ec0\u54c8\u540e\u5c6f"
    ],
    "wof:name":"Hashihahoutun",
    "wof:placetype":"locality"
},
  "geometry": {"coordinates":[123.66643999999999,47.59334000000001],"type":"Point"}
}