{
  "type": "Feature",
  "properties": {
    "gn:admin1_code":"29.0",
    "gn:asciiname":"Nuomi",
    "gn:country_code":"CN",
    "gn:dem":2240,
    "gn:feature_class":"P",
    "gn:feature_code":"PPL",
    "gn:name":"Nuomi",
    "gn:population":0,
    "gn:timezone":"Asia/Shanghai",
    "iso:country":"CN",
    "name:zho_x_preferred":[
        "\u632a\u54aa"
    ],
    "wof:name":"Nuomi",
    "wof:placetype":"locality"
},
  "geometry": {"coordinates":[102.392,25.9369],"type":"Point"}
}