{
  "type": "Feature",
  "properties": {
    "gn:admin1_code":"5.0",
    "gn:asciiname":"Sijianfang",
    "gn:country_code":"CN",
    "gn:dem":320,
    "gn:feature_class":"P",
    "gn:feature_code":"PPL",
    "gn:name":"Sijianfang",
    "gn:population":0,
    "gn:timezone":"Asia/Shanghai",
    "iso:country":"CN",
    "name:zho_x_preferred":[
        "\u56db\u95f4\u623f"
    ],
    "wof:name":"Sijianfang",
    "wof:placetype":"locality"
},
  "geometry": {"coordinates":[124.94298000000001,42.86236],"type":"Point"}
}