{
  "type": "Feature",
  "properties": {
    "gn:admin1_code":"29.0",
    "gn:asciiname":"Keli",
    "gn:country_code":"CN",
    "gn:dem":1381,
    "gn:feature_class":"P",
    "gn:feature_code":"PPL",
    "gn:name":"Keli",
    "gn:population":0,
    "gn:timezone":"Asia/Shanghai",
    "iso:country":"CN",
    "name:zho_x_preferred":[
        "\u79d1\u7acb"
    ],
    "wof:name":"Keli",
    "wof:placetype":"locality"
},
  "geometry": {"coordinates":[99.12869999999999,26.0635],"type":"Point"}
}