{
  "type": "Feature",
  "properties": {
    "gn:admin1_code":"1.0",
    "gn:asciiname":"Baolicun",
    "gn:country_code":"CN",
    "gn:dem":31,
    "gn:feature_class":"P",
    "gn:feature_code":"PPL",
    "gn:name":"Baolicun",
    "gn:population":0,
    "gn:timezone":"Asia/Shanghai",
    "iso:country":"CN",
    "name:zho_x_preferred":[
        "\u5b9d\u91cc\u6751"
    ],
    "wof:name":"Baolicun",
    "wof:placetype":"locality"
},
  "geometry": {"coordinates":[117.37663000000001,34.04676],"type":"Point"}
}