{
  "type": "Feature",
  "properties": {
    "gn:admin1_code":"14.0",
    "gn:asciiname":"Tikang",
    "gn:country_code":"CN",
    "gn:dem":3861,
    "gn:feature_class":"P",
    "gn:feature_code":"PPL",
    "gn:name":"Tikang",
    "gn:population":0,
    "gn:timezone":"Asia/Urumqi",
    "iso:country":"CN",
    "name:zho_x_preferred":[
        "\u68af\u5eb7"
    ],
    "wof:name":"Tikang",
    "wof:placetype":"locality"
},
  "geometry": {"coordinates":[91.65665,29.23172000000001],"type":"Point"}
}