{
  "type": "Feature",
  "properties": {
    "gn:admin1_code":"8.0",
    "gn:asciiname":"Wohushancun",
    "gn:country_code":"CN",
    "gn:dem":121,
    "gn:feature_class":"P",
    "gn:feature_code":"PPL",
    "gn:name":"Wohushancun",
    "gn:population":0,
    "gn:timezone":"Asia/Shanghai",
    "iso:country":"CN",
    "name:zho_x_preferred":[
        "\u5367\u864e\u5c71\u6751"
    ],
    "wof:name":"Wohushancun",
    "wof:placetype":"locality"
},
  "geometry": {"coordinates":[130.05248999999998,46.44722],"type":"Point"}
}