{
  "type": "Feature",
  "properties": {
    "gn:admin1_code":"1.0",
    "gn:asciiname":"Dataowan",
    "gn:country_code":"CN",
    "gn:dem":7,
    "gn:feature_class":"P",
    "gn:feature_code":"PPL",
    "gn:name":"Dataowan",
    "gn:population":0,
    "gn:timezone":"Asia/Shanghai",
    "iso:country":"CN",
    "name:zho_x_preferred":[
        "\u5927\u9676\u6e7e"
    ],
    "wof:name":"Dataowan",
    "wof:placetype":"locality"
},
  "geometry": {"coordinates":[118.4635,31.39792000000001],"type":"Point"}
}