{
  "type": "Feature",
  "properties": {
    "gn:admin1_code":"2.0",
    "gn:asciiname":"Datoubang",
    "gn:country_code":"CN",
    "gn:dem":5,
    "gn:feature_class":"P",
    "gn:feature_code":"PPL",
    "gn:name":"Datoubang",
    "gn:population":0,
    "gn:timezone":"Asia/Shanghai",
    "iso:country":"CN",
    "name:und_x_variant":[
        "\u5927\u5934\u6d5c"
    ],
    "wof:name":"Datoubang",
    "wof:placetype":"locality"
},
  "geometry": {"coordinates":[121.25138,30.71279],"type":"Point"}
}