{
  "type": "Feature",
  "properties": {
    "gn:admin1_code":"30.0",
    "gn:asciiname":"Mintiancun",
    "gn:country_code":"CN",
    "gn:dem":73,
    "gn:feature_class":"P",
    "gn:feature_code":"PPL",
    "gn:name":"Mintiancun",
    "gn:population":0,
    "gn:timezone":"Asia/Shanghai",
    "iso:country":"CN",
    "name:zho_x_preferred":[
        "\u6c11\u7530\u6751"
    ],
    "wof:name":"Mintiancun",
    "wof:placetype":"locality"
},
  "geometry": {"coordinates":[112.00156,23.94459],"type":"Point"}
}