{
  "type": "Feature",
  "properties": {
    "gn:admin1_code":"32.0",
    "gn:asciiname":"Xuelizhai",
    "gn:country_code":"CN",
    "gn:dem":3173,
    "gn:feature_class":"P",
    "gn:feature_code":"PPL",
    "gn:name":"Xuelizhai",
    "gn:population":0,
    "gn:timezone":"Asia/Shanghai",
    "iso:country":"CN",
    "name:zho_x_preferred":[
        "\u96ea\u68a8\u5be8"
    ],
    "wof:name":"Xuelizhai",
    "wof:placetype":"locality"
},
  "geometry": {"coordinates":[103.55200000000001,32.188],"type":"Point"}
}