{
  "type": "Feature",
  "properties": {
    "gn:admin1_code":"16.0",
    "gn:asciiname":"Longtoujiang",
    "gn:country_code":"CN",
    "gn:dem":249,
    "gn:feature_class":"P",
    "gn:feature_code":"PPL",
    "gn:name":"Longtoujiang",
    "gn:population":0,
    "gn:timezone":"Asia/Shanghai",
    "iso:country":"CN",
    "name:zho_x_preferred":[
        "\u9f99\u5934\u6c5f"
    ],
    "wof:name":"Longtoujiang",
    "wof:placetype":"locality"
},
  "geometry": {"coordinates":[108.54600000000001,24.4337],"type":"Point"}
}