{
  "type": "Feature",
  "properties": {
    "gn:admin1_code":"29",
    "gn:asciiname":"Yongjingshao",
    "gn:country_code":"CN",
    "gn:dem":1972,
    "gn:feature_class":"P",
    "gn:feature_code":"PPL",
    "gn:name":"Yongjingshao",
    "gn:population":0,
    "gn:timezone":"Asia/Shanghai",
    "iso:country":"CN",
    "name:zho_x_preferred":[
        "\u6c38\u9756\u54e8"
    ],
    "wof:name":"Yongjingshao",
    "wof:placetype":"locality"
},
  "geometry": {"coordinates":[102.107,24.6778],"type":"Point"}
}