{
  "type": "Feature",
  "properties": {
    "gn:admin1_code":"10.0",
    "gn:asciiname":"Liusantun",
    "gn:country_code":"CN",
    "gn:dem":13,
    "gn:feature_class":"P",
    "gn:feature_code":"PPL",
    "gn:name":"Liusantun",
    "gn:population":0,
    "gn:timezone":"Asia/Shanghai",
    "iso:country":"CN",
    "name:zho_x_preferred":[
        "\u5218\u4e09\u5c6f"
    ],
    "wof:name":"Liusantun",
    "wof:placetype":"locality"
},
  "geometry": {"coordinates":[117.89261999999999,39.77002],"type":"Point"}
}