{
  "type": "Feature",
  "properties": {
    "gn:admin1_code":"8.0",
    "gn:asciiname":"Qinfucun",
    "gn:country_code":"CN",
    "gn:dem":183,
    "gn:feature_class":"P",
    "gn:feature_code":"PPL",
    "gn:name":"Qinfucun",
    "gn:population":0,
    "gn:timezone":"Asia/Shanghai",
    "iso:country":"CN",
    "name:zho_x_preferred":[
        "\u52e4\u5bcc\u6751"
    ],
    "wof:name":"Qinfucun",
    "wof:placetype":"locality"
},
  "geometry": {"coordinates":[127.48782,46.98238],"type":"Point"}
}