{
  "type": "Feature",
  "properties": {
    "gn:admin1_code":"25.0",
    "gn:asciiname":"Daxizhuangcun",
    "gn:country_code":"CN",
    "gn:dem":14,
    "gn:feature_class":"P",
    "gn:feature_code":"PPL",
    "gn:name":"Daxizhuangcun",
    "gn:population":0,
    "gn:timezone":"Asia/Shanghai",
    "iso:country":"CN",
    "name:zho_x_preferred":[
        "\u5927\u897f\u5e84\u6751"
    ],
    "wof:name":"Daxizhuangcun",
    "wof:placetype":"locality"
},
  "geometry": {"coordinates":[122.00662,37.4309],"type":"Point"}
}