{
  "type": "Feature",
  "properties": {
    "gn:admin1_code":"24.0",
    "gn:asciiname":"Nanyingcun",
    "gn:country_code":"CN",
    "gn:dem":1309,
    "gn:feature_class":"P",
    "gn:feature_code":"PPL",
    "gn:name":"Nanyingcun",
    "gn:population":0,
    "gn:timezone":"Asia/Shanghai",
    "iso:country":"CN",
    "name:zho_x_preferred":[
        "\u5357\u8425\u6751"
    ],
    "wof:name":"Nanyingcun",
    "wof:placetype":"locality"
},
  "geometry": {"coordinates":[110.83347000000001,35.75802],"type":"Point"}
}