{
  "type": "Feature",
  "properties": {
    "gn:admin1_code":"3.0",
    "gn:asciiname":"Gaomingshan",
    "gn:country_code":"CN",
    "gn:dem":255,
    "gn:feature_class":"P",
    "gn:feature_code":"PPL",
    "gn:name":"Gaomingshan",
    "gn:population":0,
    "gn:timezone":"Asia/Shanghai",
    "iso:country":"CN",
    "name:und_x_variant":[
        "\u9ad8\u660e\u5c71"
    ],
    "wof:name":"Gaomingshan",
    "wof:placetype":"locality"
},
  "geometry": {"coordinates":[115.20836,26.55553],"type":"Point"}
}