{
  "type": "Feature",
  "properties": {
    "gn:admin1_code":"29.0",
    "gn:asciiname":"Juerong",
    "gn:country_code":"CN",
    "gn:dem":3274,
    "gn:feature_class":"P",
    "gn:feature_code":"PPL",
    "gn:name":"Juerong",
    "gn:population":0,
    "gn:timezone":"Asia/Shanghai",
    "iso:country":"CN",
    "name:zho_x_preferred":[
        "\u89c9\u8338"
    ],
    "wof:name":"Juerong",
    "wof:placetype":"locality"
},
  "geometry": {"coordinates":[99.6319,27.8368],"type":"Point"}
}