{
  "type": "Feature",
  "properties": {
    "gn:admin1_code":"30",
    "gn:asciiname":"Haiwanshi",
    "gn:country_code":"CN",
    "gn:dem":7,
    "gn:feature_class":"P",
    "gn:feature_code":"PPL",
    "gn:name":"Haiwanshi",
    "gn:population":0,
    "gn:timezone":"Asia/Shanghai",
    "iso:country":"CN",
    "name:zho_x_preferred":[
        "\u6d77\u6e7e\u77f3"
    ],
    "wof:name":"Haiwanshi",
    "wof:placetype":"locality"
},
  "geometry": {"coordinates":[116.56502,23.01809],"type":"Point"}
}