{
  "type": "Feature",
  "properties": {
    "gn:admin1_code":"9.0",
    "gn:asciiname":"Shenjingou",
    "gn:country_code":"CN",
    "gn:dem":1073,
    "gn:feature_class":"P",
    "gn:feature_code":"PPL",
    "gn:name":"Shenjingou",
    "gn:population":0,
    "gn:timezone":"Asia/Shanghai",
    "iso:country":"CN",
    "name:zho_x_preferred":[
        "\u751a\u91d1\u6c9f"
    ],
    "wof:name":"Shenjingou",
    "wof:placetype":"locality"
},
  "geometry": {"coordinates":[110.84334,33.85906],"type":"Point"}
}