{
  "type": "Feature",
  "properties": {
    "gn:admin1_code":"4.0",
    "gn:asciiname":"Dafeng Linchang Erdui",
    "gn:country_code":"CN",
    "gn:dem":3,
    "gn:feature_class":"P",
    "gn:feature_code":"PPLF",
    "gn:name":"Dafeng Linchang Erdui",
    "gn:population":0,
    "gn:timezone":"Asia/Shanghai",
    "iso:country":"CN",
    "name:und_x_variant":[
        "\u5927\u4e30\u6797\u573a\u4e8c\u961f"
    ],
    "name:zho_x_preferred":[
        "\u5927\u4e30\u6797\u573a\u4e8c\u961f"
    ],
    "wof:name":"Dafeng Linchang Erdui",
    "wof:placetype":"locality"
},
  "geometry": {"coordinates":[120.80883,32.98448],"type":"Point"}
}