{
  "type": "Feature",
  "properties": {
    "gn:admin1_code":"24.0",
    "gn:asciiname":"Erlangshengou",
    "gn:country_code":"CN",
    "gn:dem":1507,
    "gn:feature_class":"P",
    "gn:feature_code":"PPL",
    "gn:name":"Erlangshengou",
    "gn:population":0,
    "gn:timezone":"Asia/Shanghai",
    "iso:country":"CN",
    "name:zho_x_preferred":[
        "\u4e8c\u90ce\u795e\u6c9f"
    ],
    "wof:name":"Erlangshengou",
    "wof:placetype":"locality"
},
  "geometry": {"coordinates":[112.11789,36.72673],"type":"Point"}
}