{
  "type": "Feature",
  "properties": {
    "gn:admin1_code":"30.0",
    "gn:asciiname":"Tangjiaokou",
    "gn:country_code":"CN",
    "gn:dem":43,
    "gn:feature_class":"P",
    "gn:feature_code":"PPL",
    "gn:name":"Tangjiaokou",
    "gn:population":0,
    "gn:timezone":"Asia/Shanghai",
    "iso:country":"CN",
    "name:zho_x_preferred":[
        "\u5858\u89d2\u53e3"
    ],
    "wof:name":"Tangjiaokou",
    "wof:placetype":"locality"
},
  "geometry": {"coordinates":[113.27110999999999,23.9625],"type":"Point"}
}