{
  "type": "Feature",
  "properties": {
    "gn:admin1_code":"5.0",
    "gn:asciiname":"Changxingcun",
    "gn:country_code":"CN",
    "gn:dem":314,
    "gn:feature_class":"P",
    "gn:feature_code":"PPL",
    "gn:name":"Changxingcun",
    "gn:population":0,
    "gn:timezone":"Asia/Shanghai",
    "iso:country":"CN",
    "name:zho_x_preferred":[
        "\u5e38\u5174\u6751"
    ],
    "wof:name":"Changxingcun",
    "wof:placetype":"locality"
},
  "geometry": {"coordinates":[125.95835,42.71372],"type":"Point"}
}