{
  "type": "Feature",
  "properties": {
    "gn:admin1_code":"32.0",
    "gn:asciiname":"Mingfeng",
    "gn:country_code":"CN",
    "gn:dem":332,
    "gn:feature_class":"P",
    "gn:feature_code":"PPL",
    "gn:name":"Mingfeng",
    "gn:population":0,
    "gn:timezone":"Asia/Shanghai",
    "iso:country":"CN",
    "name:zho_x_preferred":[
        "\u9e23\u51e4"
    ],
    "wof:name":"Mingfeng",
    "wof:placetype":"locality"
},
  "geometry": {"coordinates":[105.7239,30.67923],"type":"Point"}
}