{
  "type": "Feature",
  "properties": {
    "gn:admin1_code":"15.0",
    "gn:asciiname":"Shalaoba",
    "gn:country_code":"CN",
    "gn:dem":1771,
    "gn:feature_class":"P",
    "gn:feature_code":"PPL",
    "gn:name":"Shalaoba",
    "gn:population":0,
    "gn:timezone":"Asia/Urumqi",
    "iso:country":"CN",
    "name:zho_x_preferred":[
        "\u6c99\u6d9d\u575d"
    ],
    "wof:name":"Shalaoba",
    "wof:placetype":"locality"
},
  "geometry": {"coordinates":[94.85639999999999,39.866],"type":"Point"}
}