{
  "type": "Feature",
  "properties": {
    "gn:admin1_code":"4.0",
    "gn:asciiname":"Dongxiayang",
    "gn:country_code":"CN",
    "gn:dem":4,
    "gn:feature_class":"P",
    "gn:feature_code":"PPL",
    "gn:name":"Dongxiayang",
    "gn:population":0,
    "gn:timezone":"Asia/Shanghai",
    "iso:country":"CN",
    "name:und_x_variant":[
        "\u4e1c\u4e0b\u6d0b"
    ],
    "name:zho_x_preferred":[
        "\u4e1c\u4e0b\u6d0b"
    ],
    "wof:name":"Dongxiayang",
    "wof:placetype":"locality"
},
  "geometry": {"coordinates":[120.44053,32.43745],"type":"Point"}
}