{
  "type": "Feature",
  "properties": {
    "gn:admin1_code":"14.0",
    "gn:asciiname":"Dawangtuo",
    "gn:country_code":"CN",
    "gn:dem":3909,
    "gn:feature_class":"P",
    "gn:feature_code":"PPL",
    "gn:name":"Dawangtuo",
    "gn:population":0,
    "gn:timezone":"Asia/Urumqi",
    "iso:country":"CN",
    "name:zho_x_preferred":[
        "\u6253\u65fa\u6cb1"
    ],
    "wof:name":"Dawangtuo",
    "wof:placetype":"locality"
},
  "geometry": {"coordinates":[97.75694,32.48546],"type":"Point"}
}