{
  "type": "Feature",
  "properties": {
    "gn:admin1_code":"20.0",
    "gn:asciiname":"Huangjiqu",
    "gn:country_code":"CN",
    "gn:dem":1616,
    "gn:feature_class":"P",
    "gn:feature_code":"PPL",
    "gn:name":"Huangjiqu",
    "gn:population":0,
    "gn:timezone":"Asia/Shanghai",
    "iso:country":"CN",
    "name:und_x_variant":[
        "\u9ec4\u82a8\u6e20"
    ],
    "wof:name":"Huangjiqu",
    "wof:placetype":"locality"
},
  "geometry": {"coordinates":[112.73126999999999,41.4785],"type":"Point"}
}