{
  "type": "Feature",
  "properties": {
    "gn:admin1_code":"5.0",
    "gn:asciiname":"Tianqiwei",
    "gn:country_code":"CN",
    "gn:dem":224,
    "gn:feature_class":"P",
    "gn:feature_code":"PPL",
    "gn:name":"Tianqiwei",
    "gn:population":0,
    "gn:timezone":"Asia/Shanghai",
    "iso:country":"CN",
    "name:zho_x_preferred":[
        "\u5929\u5176\u4f4d"
    ],
    "wof:name":"Tianqiwei",
    "wof:placetype":"locality"
},
  "geometry": {"coordinates":[126.25987000000001,44.47818],"type":"Point"}
}