{
  "type": "Feature",
  "properties": {
    "gn:admin1_code":"24.0",
    "gn:asciiname":"Nanmingyang",
    "gn:country_code":"CN",
    "gn:dem":747,
    "gn:feature_class":"P",
    "gn:feature_code":"PPL",
    "gn:name":"Nanmingyang",
    "gn:population":0,
    "gn:timezone":"Asia/Shanghai",
    "iso:country":"CN",
    "name:zho_x_preferred":[
        "\u5357\u660e\u9633"
    ],
    "wof:name":"Nanmingyang",
    "wof:placetype":"locality"
},
  "geometry": {"coordinates":[112.08541,37.39211],"type":"Point"}
}