{
  "type": "Feature",
  "properties": {
    "gn:admin1_code":"11.0",
    "gn:asciiname":"Renjiawan",
    "gn:country_code":"CN",
    "gn:dem":556,
    "gn:feature_class":"P",
    "gn:feature_code":"PPL",
    "gn:name":"Renjiawan",
    "gn:population":0,
    "gn:timezone":"Asia/Shanghai",
    "iso:country":"CN",
    "name:zho_x_preferred":[
        "\u4efb\u5bb6\u6e7e"
    ],
    "wof:name":"Renjiawan",
    "wof:placetype":"locality"
},
  "geometry": {"coordinates":[110.73192,29.76229],"type":"Point"}
}