{
  "type": "Feature",
  "properties": {
    "gn:admin1_code":"10.0",
    "gn:asciiname":"Yaoshunkou",
    "gn:country_code":"CN",
    "gn:dem":108,
    "gn:feature_class":"P",
    "gn:feature_code":"PPL",
    "gn:name":"Yaoshunkou",
    "gn:population":0,
    "gn:timezone":"Asia/Shanghai",
    "iso:country":"CN",
    "name:zho_x_preferred":[
        "\u5c27\u821c\u53e3"
    ],
    "wof:name":"Yaoshunkou",
    "wof:placetype":"locality"
},
  "geometry": {"coordinates":[115.27664,39.30081],"type":"Point"}
}