{
  "type": "Feature",
  "properties": {
    "gn:admin1_code":"29.0",
    "gn:asciiname":"Dengjiashan",
    "gn:country_code":"CN",
    "gn:dem":2222,
    "gn:feature_class":"P",
    "gn:feature_code":"PPL",
    "gn:name":"Dengjiashan",
    "gn:population":0,
    "gn:timezone":"Asia/Shanghai",
    "iso:country":"CN",
    "name:und_x_variant":[
        "\u9093\u5bb6\u5c71"
    ],
    "wof:name":"Dengjiashan",
    "wof:placetype":"locality"
},
  "geometry": {"coordinates":[103.47073,27.4515],"type":"Point"}
}