{
  "type": "Feature",
  "properties": {
    "gn:admin1_code":"11.0",
    "gn:asciiname":"Tanglishang",
    "gn:country_code":"CN",
    "gn:dem":140,
    "gn:feature_class":"P",
    "gn:feature_code":"PPL",
    "gn:name":"Tanglishang",
    "gn:population":0,
    "gn:timezone":"Asia/Shanghai",
    "iso:country":"CN",
    "name:zho_x_preferred":[
        "\u5858\u91cc\u4e0a"
    ],
    "wof:name":"Tanglishang",
    "wof:placetype":"locality"
},
  "geometry": {"coordinates":[113.64490000000001,26.5952],"type":"Point"}
}