{
  "type": "Feature",
  "properties": {
    "gn:admin1_code":"5.0",
    "gn:asciiname":"Hou'erhao",
    "gn:country_code":"CN",
    "gn:dem":173,
    "gn:feature_class":"P",
    "gn:feature_code":"PPL",
    "gn:name":"Hou\u2019erhao",
    "gn:population":0,
    "gn:timezone":"Asia/Shanghai",
    "iso:country":"CN",
    "name:und_x_variant":[
        "Hou\u2019erhao"
    ],
    "name:zho_x_preferred":[
        "\u540e\u4e8c\u53f7"
    ],
    "wof:name":"Hou'erhao",
    "wof:placetype":"locality"
},
  "geometry": {"coordinates":[126.48023999999999,45.11998],"type":"Point"}
}