{
  "type": "Feature",
  "properties": {
    "gn:admin1_code":"18",
    "gn:asciiname":"Banpao",
    "gn:country_code":"CN",
    "gn:dem":659,
    "gn:feature_class":"P",
    "gn:feature_code":"PPL",
    "gn:name":"Banpao",
    "gn:population":0,
    "gn:timezone":"Asia/Shanghai",
    "iso:country":"CN",
    "name:zho_x_preferred":[
        "\u677f\u888d"
    ],
    "wof:name":"Banpao",
    "wof:placetype":"locality"
},
  "geometry": {"coordinates":[105.84,25.6068],"type":"Point"}
}