{
  "type": "Feature",
  "properties": {
    "gn:admin1_code":"16.0",
    "gn:asciiname":"Shangji",
    "gn:country_code":"CN",
    "gn:dem":253,
    "gn:feature_class":"P",
    "gn:feature_code":"PPL",
    "gn:name":"Shangji",
    "gn:population":0,
    "gn:timezone":"Asia/Shanghai",
    "iso:country":"CN",
    "name:zho_x_preferred":[
        "\u4e0a\u7ea7"
    ],
    "wof:name":"Shangji",
    "wof:placetype":"locality"
},
  "geometry": {"coordinates":[108.328,23.6289],"type":"Point"}
}