{
  "type": "Feature",
  "properties": {
    "gn:admin1_code":"16.0",
    "gn:asciiname":"Shan'er",
    "gn:country_code":"CN",
    "gn:dem":99,
    "gn:feature_class":"P",
    "gn:feature_code":"PPL",
    "gn:name":"Shan\u2019er",
    "gn:population":0,
    "gn:timezone":"Asia/Shanghai",
    "iso:country":"CN",
    "name:und_x_variant":[
        "Shan\u2019er"
    ],
    "name:zho_x_preferred":[
        "\u5c71\u513f"
    ],
    "wof:name":"Shan'er",
    "wof:placetype":"locality"
},
  "geometry": {"coordinates":[108.833,23.4476],"type":"Point"}
}