{
  "type": "Feature",
  "properties": {
    "gn:admin1_code":"18",
    "gn:asciiname":"Xiaoliujing",
    "gn:country_code":"CN",
    "gn:dem":695,
    "gn:feature_class":"P",
    "gn:feature_code":"PPL",
    "gn:name":"Xiaoliujing",
    "gn:population":0,
    "gn:timezone":"Asia/Shanghai",
    "iso:country":"CN",
    "name:zho_x_preferred":[
        "\u5c0f\u516d\u4e95"
    ],
    "wof:name":"Xiaoliujing",
    "wof:placetype":"locality"
},
  "geometry": {"coordinates":[107.845,28.8969],"type":"Point"}
}