{
  "type": "Feature",
  "properties": {
    "gn:admin1_code":"2.0",
    "gn:asciiname":"Tashanjiao",
    "gn:country_code":"CN",
    "gn:dem":74,
    "gn:feature_class":"P",
    "gn:feature_code":"PPL",
    "gn:name":"Tashanjiao",
    "gn:population":0,
    "gn:timezone":"Asia/Shanghai",
    "iso:country":"CN",
    "name:und_x_variant":[
        "\u5854\u5c71\u811a",
        "Tashanjiao"
    ],
    "wof:name":"Tashanjiao",
    "wof:placetype":"locality"
},
  "geometry": {"coordinates":[119.70771999999999,29.32683],"type":"Point"}
}