{
  "type": "Feature",
  "properties": {
    "gn:admin1_code":"3.0",
    "gn:asciiname":"Shuanggangkou",
    "gn:country_code":"CN",
    "gn:dem":162,
    "gn:feature_class":"P",
    "gn:feature_code":"PPL",
    "gn:name":"Shuanggangkou",
    "gn:population":0,
    "gn:timezone":"Asia/Shanghai",
    "iso:country":"CN",
    "name:und_x_variant":[
        "\u53cc\u6e2f\u53e3"
    ],
    "wof:name":"Shuanggangkou",
    "wof:placetype":"locality"
},
  "geometry": {"coordinates":[114.13403999999998,29.05023],"type":"Point"}
}