{
  "type": "Feature",
  "properties": {
    "gn:admin1_code":"10.0",
    "gn:asciiname":"Nantangmei",
    "gn:country_code":"CN",
    "gn:dem":175,
    "gn:feature_class":"P",
    "gn:feature_code":"PPL",
    "gn:name":"Nantangmei",
    "gn:population":0,
    "gn:timezone":"Asia/Shanghai",
    "iso:country":"CN",
    "name:und_x_variant":[
        "\u5357\u5510\u6885"
    ],
    "wof:name":"Nantangmei",
    "wof:placetype":"locality"
},
  "geometry": {"coordinates":[114.88164999999999,38.8658],"type":"Point"}
}