{
  "type": "Feature",
  "properties": {
    "gn:admin1_code":"4.0",
    "gn:asciiname":"Hualincun",
    "gn:country_code":"CN",
    "gn:dem":3,
    "gn:feature_class":"P",
    "gn:feature_code":"PPL",
    "gn:name":"Hualincun",
    "gn:population":0,
    "gn:timezone":"Asia/Shanghai",
    "iso:country":"CN",
    "name:zho_x_preferred":[
        "\u534e\u6797\u6751"
    ],
    "wof:name":"Hualincun",
    "wof:placetype":"locality"
},
  "geometry": {"coordinates":[119.93671000000001,33.48273],"type":"Point"}
}