{
  "type": "Feature",
  "properties": {
    "gn:admin1_code":"31.0",
    "gn:asciiname":"Jinchangyuan",
    "gn:country_code":"CN",
    "gn:dem":88,
    "gn:feature_class":"P",
    "gn:feature_code":"PPL",
    "gn:name":"Jinchangyuan",
    "gn:population":0,
    "gn:timezone":"Asia/Shanghai",
    "iso:country":"CN",
    "name:zho_x_preferred":[
        "\u91d1\u660c\u56ed"
    ],
    "wof:name":"Jinchangyuan",
    "wof:placetype":"locality"
},
  "geometry": {"coordinates":[110.12075,19.54775],"type":"Point"}
}