{
  "type": "Feature",
  "properties": {
    "gn:admin1_code":"3",
    "gn:asciiname":"Wuli",
    "gn:country_code":"CN",
    "gn:dem":285,
    "gn:feature_class":"P",
    "gn:feature_code":"PPL",
    "gn:name":"Wuli",
    "gn:population":0,
    "gn:timezone":"Asia/Shanghai",
    "iso:country":"CN",
    "name:ceb_x_preferred":[
        "Wuli"
    ],
    "name:deu_x_preferred":[
        "Wuli"
    ],
    "name:fra_x_preferred":[
        "Wuli"
    ],
    "name:swe_x_preferred":[
        "Wuli"
    ],
    "name:zho_x_preferred":[
        "\u4e94\u91cc"
    ],
    "wof:name":"Wuli",
    "wof:placetype":"locality"
},
  "geometry": {"coordinates":[114.3751,26.34962],"type":"Point"}
}