{
  "type": "Feature",
  "properties": {
    "gn:admin1_code":"12.0",
    "gn:asciiname":"Wujiatai",
    "gn:country_code":"CN",
    "gn:dem":31,
    "gn:feature_class":"P",
    "gn:feature_code":"PPL",
    "gn:name":"Wujiatai",
    "gn:population":0,
    "gn:timezone":"Asia/Shanghai",
    "iso:country":"CN",
    "name:zho_x_preferred":[
        "\u4f0d\u5bb6\u53f0"
    ],
    "wof:name":"Wujiatai",
    "wof:placetype":"locality"
},
  "geometry": {"coordinates":[113.13254999999999,30.68365],"type":"Point"}
}