{
  "type": "Feature",
  "properties": {
    "gn:admin1_code":"16.0",
    "gn:asciiname":"Gezishi",
    "gn:country_code":"CN",
    "gn:dem":870,
    "gn:feature_class":"P",
    "gn:feature_code":"PPL",
    "gn:name":"Gezishi",
    "gn:population":0,
    "gn:timezone":"Asia/Shanghai",
    "iso:country":"CN",
    "name:zho_x_preferred":[
        "\u9e3d\u5b50\u77f3"
    ],
    "wof:name":"Gezishi",
    "wof:placetype":"locality"
},
  "geometry": {"coordinates":[107.474,25.2018],"type":"Point"}
}