{
  "type": "Feature",
  "properties": {
    "gn:admin1_code":"16",
    "gn:asciiname":"Zhai'an",
    "gn:country_code":"CN",
    "gn:dem":120,
    "gn:feature_class":"P",
    "gn:feature_code":"PPL",
    "gn:name":"Zhai\u2019an",
    "gn:population":0,
    "gn:timezone":"Asia/Shanghai",
    "iso:country":"CN",
    "name:und_x_variant":[
        "Chai-han",
        "Zhai\u2019an"
    ],
    "wof:name":"Zhai'an",
    "wof:placetype":"locality"
},
  "geometry": {"coordinates":[107.08194,22.11917],"type":"Point"}
}