{
  "type": "Feature",
  "properties": {
    "gn:admin1_code":"3.0",
    "gn:asciiname":"Kantiancun",
    "gn:country_code":"CN",
    "gn:dem":384,
    "gn:feature_class":"P",
    "gn:feature_code":"PPL",
    "gn:name":"Kantiancun",
    "gn:population":0,
    "gn:timezone":"Asia/Shanghai",
    "iso:country":"CN",
    "name:und_x_variant":[
        "\u574e\u7530\u6751"
    ],
    "wof:name":"Kantiancun",
    "wof:placetype":"locality"
},
  "geometry": {"coordinates":[115.88571,26.54463],"type":"Point"}
}