{
  "type": "Feature",
  "properties": {
    "gn:admin1_code":"25.0",
    "gn:asciiname":"Nanwangjia",
    "gn:country_code":"CN",
    "gn:dem":85,
    "gn:feature_class":"P",
    "gn:feature_code":"PPL",
    "gn:name":"Nanwangjia",
    "gn:population":0,
    "gn:timezone":"Asia/Shanghai",
    "iso:country":"CN",
    "name:zho_x_preferred":[
        "\u5357\u738b\u5bb6"
    ],
    "wof:name":"Nanwangjia",
    "wof:placetype":"locality"
},
  "geometry": {"coordinates":[119.88227999999999,37.10479],"type":"Point"}
}