{
  "type": "Feature",
  "properties": {
    "gn:admin1_code":"16.0",
    "gn:asciiname":"Sha'an",
    "gn:country_code":"CN",
    "gn:dem":457,
    "gn:feature_class":"P",
    "gn:feature_code":"PPL",
    "gn:name":"Sha\u2019an",
    "gn:population":0,
    "gn:timezone":"Asia/Shanghai",
    "iso:country":"CN",
    "name:und_x_variant":[
        "Sha\u2019an"
    ],
    "name:zho_x_preferred":[
        "\u6c99\u5b89"
    ],
    "wof:name":"Sha'an",
    "wof:placetype":"locality"
},
  "geometry": {"coordinates":[107.42,24.6687],"type":"Point"}
}