{
  "type": "Feature",
  "properties": {
    "gn:admin1_code":"19.0",
    "gn:asciiname":"Gelaocun",
    "gn:country_code":"CN",
    "gn:dem":167,
    "gn:feature_class":"P",
    "gn:feature_code":"PPL",
    "gn:name":"Gelaocun",
    "gn:population":0,
    "gn:timezone":"Asia/Shanghai",
    "iso:country":"CN",
    "name:zho_x_preferred":[
        "\u9601\u8001\u6751"
    ],
    "wof:name":"Gelaocun",
    "wof:placetype":"locality"
},
  "geometry": {"coordinates":[123.91313999999998,41.62971],"type":"Point"}
}