{
  "type": "Feature",
  "properties": {
    "gn:admin1_code":"16.0",
    "gn:asciiname":"Shangshuole",
    "gn:country_code":"CN",
    "gn:dem":224,
    "gn:feature_class":"P",
    "gn:feature_code":"PPL",
    "gn:name":"Shangshuole",
    "gn:population":0,
    "gn:timezone":"Asia/Shanghai",
    "iso:country":"CN",
    "name:zho_x_preferred":[
        "\u4e0a\u6714\u4e50"
    ],
    "wof:name":"Shangshuole",
    "wof:placetype":"locality"
},
  "geometry": {"coordinates":[107.03700000000001,23.7998],"type":"Point"}
}