{
  "type": "Feature",
  "properties": {
    "gn:admin1_code":"30.0",
    "gn:asciiname":"Lianwu",
    "gn:country_code":"CN",
    "gn:dem":725,
    "gn:feature_class":"P",
    "gn:feature_code":"PPL",
    "gn:name":"Lianwu",
    "gn:population":0,
    "gn:timezone":"Asia/Shanghai",
    "iso:country":"CN",
    "name:zho_x_preferred":[
        "Lianwu"
    ],
    "name:zho_x_variant":[
        "\u8fde\u5c4b"
    ],
    "wof:name":"Lianwu",
    "wof:placetype":"locality"
},
  "geometry": {"coordinates":[113.55806,25.25139],"type":"Point"}
}