{
  "type": "Feature",
  "properties": {
    "gn:admin1_code":"7.0",
    "gn:asciiname":"Shuiyuansi",
    "gn:country_code":"CN",
    "gn:dem":416,
    "gn:feature_class":"P",
    "gn:feature_code":"PPL",
    "gn:name":"Shuiyuansi",
    "gn:population":0,
    "gn:timezone":"Asia/Shanghai",
    "iso:country":"CN",
    "name:zho_x_preferred":[
        "\u6c34\u6e90\u5bfa"
    ],
    "wof:name":"Shuiyuansi",
    "wof:placetype":"locality"
},
  "geometry": {"coordinates":[118.29673,27.78424],"type":"Point"}
}