{
  "type": "Feature",
  "properties": {
    "gn:admin1_code":"19",
    "gn:asciiname":"Liqianhutun",
    "gn:cc2":"CN",
    "gn:country_code":"CN",
    "gn:dem":110,
    "gn:feature_class":"P",
    "gn:feature_code":"PPL",
    "gn:name":"Liqianhutun",
    "gn:population":0,
    "gn:timezone":"Asia/Shanghai",
    "iso:country":"CN",
    "name:und_x_variant":[
        "Li-ch\u2019ien-hu",
        "Li-ch\u2019ien-hu-t\u2019un-ts\u2019un",
        "Li-ch\u2019ien-hu-t\u2019un",
        "Liqianhutun"
    ],
    "wof:name":"Liqianhutun",
    "wof:placetype":"locality"
},
  "geometry": {"coordinates":[123.84999999999999,42.15],"type":"Point"}
}