{
  "type": "Feature",
  "properties": {
    "gn:admin1_code":"25",
    "gn:asciiname":"Xigoutou",
    "gn:country_code":"CN",
    "gn:dem":125,
    "gn:feature_class":"P",
    "gn:feature_code":"PPL",
    "gn:name":"Xigoutou",
    "gn:population":0,
    "gn:timezone":"Asia/Shanghai",
    "iso:country":"CN",
    "name:zho_x_preferred":[
        "\u897f\u6c9f\u5934"
    ],
    "wof:name":"Xigoutou",
    "wof:placetype":"locality"
},
  "geometry": {"coordinates":[118.91800000000001,35.6029],"type":"Point"}
}