{
  "type": "Feature",
  "properties": {
    "gn:admin1_code":"1.0",
    "gn:asciiname":"Jingangshan",
    "gn:country_code":"CN",
    "gn:dem":58,
    "gn:feature_class":"P",
    "gn:feature_code":"PPL",
    "gn:name":"Jingangshan",
    "gn:population":0,
    "gn:timezone":"Asia/Shanghai",
    "iso:country":"CN",
    "name:zho_x_preferred":[
        "Jingangshan"
    ],
    "name:zho_x_variant":[
        "\u91d1\u5c97\u5c71"
    ],
    "wof:name":"Jingangshan",
    "wof:placetype":"locality"
},
  "geometry": {"coordinates":[119.48018,31.05153],"type":"Point"}
}