{
  "type": "Feature",
  "properties": {
    "gn:admin1_code":"8.0",
    "gn:asciiname":"Yongyuancun",
    "gn:country_code":"CN",
    "gn:dem":171,
    "gn:feature_class":"P",
    "gn:feature_code":"PPL",
    "gn:name":"Yongyuancun",
    "gn:population":0,
    "gn:timezone":"Asia/Shanghai",
    "iso:country":"CN",
    "name:zho_x_preferred":[
        "\u6c38\u8fdc\u6751"
    ],
    "wof:name":"Yongyuancun",
    "wof:placetype":"locality"
},
  "geometry": {"coordinates":[126.52670999999999,47.43103],"type":"Point"}
}