{
  "type": "Feature",
  "properties": {
    "gn:admin1_code":"7.0",
    "gn:asciiname":"Huangling",
    "gn:country_code":"CN",
    "gn:dem":549,
    "gn:feature_class":"P",
    "gn:feature_code":"PPL",
    "gn:name":"Huangling",
    "gn:population":0,
    "gn:timezone":"Asia/Shanghai",
    "iso:country":"CN",
    "name:und_x_variant":[
        "\u9ec4\u5cad"
    ],
    "name:zho_x_preferred":[
        "\u9ec4\u5cad"
    ],
    "wof:name":"Huangling",
    "wof:placetype":"locality"
},
  "geometry": {"coordinates":[117.17601000000001,26.0353],"type":"Point"}
}