{
  "type": "Feature",
  "properties": {
    "gn:admin1_code":"19.0",
    "gn:asciiname":"Xiaoyangjiatun",
    "gn:country_code":"CN",
    "gn:dem":4,
    "gn:feature_class":"P",
    "gn:feature_code":"PPL",
    "gn:name":"Xiaoyangjiatun",
    "gn:population":0,
    "gn:timezone":"Asia/Shanghai",
    "iso:country":"CN",
    "name:zho_x_preferred":[
        "\u5c0f\u6768\u5bb6\u5c6f"
    ],
    "wof:name":"Xiaoyangjiatun",
    "wof:placetype":"locality"
},
  "geometry": {"coordinates":[119.90228,40.01153],"type":"Point"}
}