{
  "type": "Feature",
  "properties": {
    "gn:admin1_code":"32.0",
    "gn:asciiname":"Xiaoyanjing",
    "gn:country_code":"CN",
    "gn:dem":2095,
    "gn:feature_class":"P",
    "gn:feature_code":"PPL",
    "gn:name":"Xiaoyanjing",
    "gn:population":0,
    "gn:timezone":"Asia/Shanghai",
    "iso:country":"CN",
    "name:zho_x_preferred":[
        "\u5c0f\u76d0\u4e95"
    ],
    "wof:name":"Xiaoyanjing",
    "wof:placetype":"locality"
},
  "geometry": {"coordinates":[102.218,28.6491],"type":"Point"}
}