{
  "type": "Feature",
  "properties": {
    "gn:admin1_code":"19.0",
    "gn:asciiname":"Luquanzicun",
    "gn:country_code":"CN",
    "gn:dem":316,
    "gn:feature_class":"P",
    "gn:feature_code":"PPL",
    "gn:name":"Luquanzicun",
    "gn:population":0,
    "gn:timezone":"Asia/Shanghai",
    "iso:country":"CN",
    "name:zho_x_preferred":[
        "\u9e7f\u5708\u5b50\u6751"
    ],
    "wof:name":"Luquanzicun",
    "wof:placetype":"locality"
},
  "geometry": {"coordinates":[122.934,40.2102],"type":"Point"}
}