{
  "type": "Feature",
  "properties": {
    "gn:admin1_code":"25.0",
    "gn:asciiname":"Zhanjiakuang",
    "gn:country_code":"CN",
    "gn:dem":58,
    "gn:feature_class":"P",
    "gn:feature_code":"PPL",
    "gn:name":"Zhanjiakuang",
    "gn:population":0,
    "gn:timezone":"Asia/Shanghai",
    "iso:country":"CN",
    "name:zho_x_preferred":[
        "\u6218\u5bb6\u593c"
    ],
    "wof:name":"Zhanjiakuang",
    "wof:placetype":"locality"
},
  "geometry": {"coordinates":[121.50185999999999,36.98894],"type":"Point"}
}