{
  "type": "Feature",
  "properties": {
    "gn:admin1_code":"7.0",
    "gn:asciiname":"Huoshaoyan",
    "gn:country_code":"CN",
    "gn:dem":869,
    "gn:feature_class":"P",
    "gn:feature_code":"PPL",
    "gn:name":"Huoshaoyan",
    "gn:population":0,
    "gn:timezone":"Asia/Shanghai",
    "iso:country":"CN",
    "name:zho_x_preferred":[
        "\u706b\u70e7\u5ca9"
    ],
    "wof:name":"Huoshaoyan",
    "wof:placetype":"locality"
},
  "geometry": {"coordinates":[119.26875,26.83513],"type":"Point"}
}