{
  "type": "Feature",
  "properties": {
    "gn:admin1_code":"21.0",
    "gn:asciiname":"Minle Sidui",
    "gn:country_code":"CN",
    "gn:dem":1102,
    "gn:feature_class":"P",
    "gn:feature_code":"PPLF",
    "gn:name":"Minle Sidui",
    "gn:population":0,
    "gn:timezone":"Asia/Shanghai",
    "iso:country":"CN",
    "name:zho_x_preferred":[
        "\u6c11\u4e50\u56db\u961f"
    ],
    "wof:name":"Minle Sidui",
    "wof:placetype":"locality"
},
  "geometry": {"coordinates":[106.497,38.6936],"type":"Point"}
}