{
  "type": "Feature",
  "properties": {
    "gn:admin1_code":"11.0",
    "gn:asciiname":"Daluwan",
    "gn:country_code":"CN",
    "gn:dem":111,
    "gn:feature_class":"P",
    "gn:feature_code":"PPL",
    "gn:name":"Daluwan",
    "gn:population":0,
    "gn:timezone":"Asia/Shanghai",
    "iso:country":"CN",
    "name:zho_x_preferred":[
        "\u5927\u8def\u6e7e"
    ],
    "wof:name":"Daluwan",
    "wof:placetype":"locality"
},
  "geometry": {"coordinates":[113.267,26.64046],"type":"Point"}
}