{
  "type": "Feature",
  "properties": {
    "gn:admin1_code":"10",
    "gn:asciiname":"Huojiaqiao",
    "gn:cc2":"CN",
    "gn:country_code":"CN",
    "gn:dem":38,
    "gn:feature_class":"P",
    "gn:feature_code":"PPL",
    "gn:name":"Huojiaqiao",
    "gn:population":0,
    "gn:timezone":"Asia/Shanghai",
    "iso:country":"CN",
    "name:und_x_variant":[
        "Huo-chia-ch\u2019iao",
        "Huojiaqiao"
    ],
    "wof:name":"Huojiaqiao",
    "wof:placetype":"locality"
},
  "geometry": {"coordinates":[114.96666999999999,36.81667],"type":"Point"}
}