{
  "type": "Feature",
  "properties": {
    "gn:admin1_code":"11.0",
    "gn:asciiname":"Zhoulijia",
    "gn:country_code":"CN",
    "gn:dem":43,
    "gn:feature_class":"P",
    "gn:feature_code":"PPL",
    "gn:name":"Zhoulijia",
    "gn:population":0,
    "gn:timezone":"Asia/Shanghai",
    "iso:country":"CN",
    "name:zho_x_preferred":[
        "Zhoulijia"
    ],
    "name:zho_x_variant":[
        "\u5468\u674e\u5bb6"
    ],
    "wof:name":"Zhoulijia",
    "wof:placetype":"locality"
},
  "geometry": {"coordinates":[111.85844,29.22076],"type":"Point"}
}