{
  "type": "Feature",
  "properties": {
    "gn:admin1_code":"18",
    "gn:asciiname":"Yanshan",
    "gn:country_code":"CN",
    "gn:dem":1456,
    "gn:feature_class":"P",
    "gn:feature_code":"PPL",
    "gn:name":"Yanshan",
    "gn:population":0,
    "gn:timezone":"Asia/Shanghai",
    "iso:country":"CN",
    "name:zho_x_preferred":[
        "\u70df\u5c71"
    ],
    "wof:name":"Yanshan",
    "wof:placetype":"locality"
},
  "geometry": {"coordinates":[105.50700000000001,26.7483],"type":"Point"}
}