{
  "type": "Feature",
  "properties": {
    "gn:admin1_code":"29.0",
    "gn:asciiname":"Jiguanshan",
    "gn:country_code":"CN",
    "gn:dem":1575,
    "gn:feature_class":"P",
    "gn:feature_code":"PPL",
    "gn:name":"Jiguanshan",
    "gn:population":0,
    "gn:timezone":"Asia/Shanghai",
    "iso:country":"CN",
    "name:zho_x_preferred":[
        "\u9e21\u51a0\u5c71"
    ],
    "wof:name":"Jiguanshan",
    "wof:placetype":"locality"
},
  "geometry": {"coordinates":[101.92,25.8632],"type":"Point"}
}