{
  "type": "Feature",
  "properties": {
    "gn:admin1_code":"18",
    "gn:asciiname":"Goukanshang",
    "gn:country_code":"CN",
    "gn:dem":1274,
    "gn:feature_class":"P",
    "gn:feature_code":"PPL",
    "gn:name":"Goukanshang",
    "gn:population":0,
    "gn:timezone":"Asia/Shanghai",
    "iso:country":"CN",
    "name:zho_x_preferred":[
        "\u6c9f\u574e\u4e0a"
    ],
    "wof:name":"Goukanshang",
    "wof:placetype":"locality"
},
  "geometry": {"coordinates":[106.84,26.8782],"type":"Point"}
}