{
  "type": "Feature",
  "properties": {
    "gn:admin1_code":"12.0",
    "gn:asciiname":"Liaojia",
    "gn:country_code":"CN",
    "gn:dem":148,
    "gn:feature_class":"P",
    "gn:feature_code":"PPL",
    "gn:name":"Liaojia",
    "gn:population":0,
    "gn:timezone":"Asia/Shanghai",
    "iso:country":"CN",
    "name:zho_x_preferred":[
        "Liaojia"
    ],
    "name:zho_x_variant":[
        "\u5ed6\u5bb6"
    ],
    "wof:name":"Liaojia",
    "wof:placetype":"locality"
},
  "geometry": {"coordinates":[114.13401,29.74437],"type":"Point"}
}