{
  "type": "Feature",
  "properties": {
    "gn:admin1_code":"1.0",
    "gn:asciiname":"Juntianzhuang",
    "gn:country_code":"CN",
    "gn:dem":9,
    "gn:feature_class":"P",
    "gn:feature_code":"PPL",
    "gn:name":"Juntianzhuang",
    "gn:population":0,
    "gn:timezone":"Asia/Shanghai",
    "iso:country":"CN",
    "name:zho_x_preferred":[
        "\u519b\u7530\u5e84"
    ],
    "wof:name":"Juntianzhuang",
    "wof:placetype":"locality"
},
  "geometry": {"coordinates":[119.18459,32.68786],"type":"Point"}
}