{
  "type": "Feature",
  "properties": {
    "gn:admin1_code":"29.0",
    "gn:asciiname":"Lanbazhai",
    "gn:country_code":"CN",
    "gn:dem":1561,
    "gn:feature_class":"P",
    "gn:feature_code":"PPL",
    "gn:name":"Lanbazhai",
    "gn:population":0,
    "gn:timezone":"Asia/Shanghai",
    "iso:country":"CN",
    "name:zho_x_preferred":[
        "\u70c2\u5df4\u5be8"
    ],
    "wof:name":"Lanbazhai",
    "wof:placetype":"locality"
},
  "geometry": {"coordinates":[99.4948,24.0424],"type":"Point"}
}