{
  "type": "Feature",
  "properties": {
    "gn:admin1_code":"14.0",
    "gn:asciiname":"Bazhongma",
    "gn:country_code":"CN",
    "gn:dem":4055,
    "gn:feature_class":"P",
    "gn:feature_code":"PPL",
    "gn:name":"Bazhongma",
    "gn:population":0,
    "gn:timezone":"Asia/Urumqi",
    "iso:country":"CN",
    "name:zho_x_preferred":[
        "\u5df4\u4e2d\u9a6c"
    ],
    "wof:name":"Bazhongma",
    "wof:placetype":"locality"
},
  "geometry": {"coordinates":[95.34733,31.58057],"type":"Point"}
}