{
  "type": "Feature",
  "properties": {
    "gn:admin1_code":"11.0",
    "gn:asciiname":"Fengxiangping",
    "gn:country_code":"CN",
    "gn:dem":296,
    "gn:feature_class":"P",
    "gn:feature_code":"PPL",
    "gn:name":"Fengxiangping",
    "gn:population":0,
    "gn:timezone":"Asia/Shanghai",
    "iso:country":"CN",
    "name:zho_x_preferred":[
        "\u98ce\u9999\u576a"
    ],
    "wof:name":"Fengxiangping",
    "wof:placetype":"locality"
},
  "geometry": {"coordinates":[110.16321000000001,27.4785],"type":"Point"}
}