{
  "type": "Feature",
  "properties": {
    "gn:admin1_code":"30.0",
    "gn:asciiname":"Bangang",
    "gn:country_code":"CN",
    "gn:dem":105,
    "gn:feature_class":"P",
    "gn:feature_code":"PPL",
    "gn:name":"Bangang",
    "gn:population":0,
    "gn:timezone":"Asia/Shanghai",
    "iso:country":"CN",
    "name:und_x_variant":[
        "\u534a\u5c97"
    ],
    "name:zho_x_preferred":[
        "\u534a\u5c97"
    ],
    "wof:name":"Bangang",
    "wof:placetype":"locality"
},
  "geometry": {"coordinates":[115.11854,23.55533],"type":"Point"}
}