{
  "type": "Feature",
  "properties": {
    "gn:admin1_code":"4.0",
    "gn:asciiname":"Shiducun",
    "gn:country_code":"CN",
    "gn:dem":13,
    "gn:feature_class":"P",
    "gn:feature_code":"PPL",
    "gn:name":"Shiducun",
    "gn:population":0,
    "gn:timezone":"Asia/Shanghai",
    "iso:country":"CN",
    "name:zho_x_preferred":[
        "\u77f3\u6e21\u6751"
    ],
    "wof:name":"Shiducun",
    "wof:placetype":"locality"
},
  "geometry": {"coordinates":[118.74791999999999,33.8067],"type":"Point"}
}