{
  "type": "Feature",
  "properties": {
    "gn:admin1_code":"3.0",
    "gn:asciiname":"Bangluo",
    "gn:country_code":"CN",
    "gn:dem":70,
    "gn:feature_class":"P",
    "gn:feature_code":"PPLA4",
    "gn:name":"Bangluo",
    "gn:population":0,
    "gn:timezone":"Asia/Shanghai",
    "iso:country":"CN",
    "name:und_x_variant":[
        "Bangluo Xiang",
        "\u508d\u7f57\u4e61",
        "Bangluo"
    ],
    "name:zho_x_preferred":[
        "\u508d\u7f57"
    ],
    "wof:name":"Bangluo",
    "wof:placetype":"locality"
},
  "geometry": {"coordinates":[117.79378,28.30575],"type":"Point"}
}