{
  "type": "Feature",
  "properties": {
    "gn:admin1_code":"7.0",
    "gn:asciiname":"Xiajingshan",
    "gn:country_code":"CN",
    "gn:dem":334,
    "gn:feature_class":"P",
    "gn:feature_code":"PPL",
    "gn:name":"Xiajingshan",
    "gn:population":0,
    "gn:timezone":"Asia/Shanghai",
    "iso:country":"CN",
    "name:zho_x_preferred":[
        "\u4e0b\u5f84\u5c71"
    ],
    "wof:name":"Xiajingshan",
    "wof:placetype":"locality"
},
  "geometry": {"coordinates":[116.30495000000001,25.61485],"type":"Point"}
}