{
  "type": "Feature",
  "properties": {
    "gn:admin1_code":"16.0",
    "gn:asciiname":"Dala",
    "gn:country_code":"CN",
    "gn:dem":358,
    "gn:feature_class":"P",
    "gn:feature_code":"PPL",
    "gn:name":"Dala",
    "gn:population":0,
    "gn:timezone":"Asia/Shanghai",
    "iso:country":"CN",
    "name:ceb_x_preferred":[
        "Dala"
    ],
    "name:deu_x_preferred":[
        "Dala"
    ],
    "name:fin_x_preferred":[
        "Dala"
    ],
    "name:fra_x_preferred":[
        "Dala"
    ],
    "name:ita_x_preferred":[
        "Dala"
    ],
    "name:nld_x_preferred":[
        "Dala"
    ],
    "name:swe_x_preferred":[
        "Dala"
    ],
    "name:zho_x_preferred":[
        "\u6253\u814a"
    ],
    "wof:name":"Dala",
    "wof:placetype":"locality"
},
  "geometry": {"coordinates":[107.00700000000001,25.41800000000001],"type":"Point"}
}