{
  "type": "Feature",
  "properties": {
    "gn:admin1_code":"02",
    "gn:asciiname":"Shenbao",
    "gn:country_code":"CN",
    "gn:dem":11,
    "gn:feature_class":"P",
    "gn:feature_code":"PPL",
    "gn:name":"Shenbao",
    "gn:population":0,
    "gn:timezone":"Asia/Shanghai",
    "iso:country":"CN",
    "name:und_x_variant":[
        "Shen-chia-chuang",
        "Shenbao",
        "\u6c88\u9c8d"
    ],
    "name:zho_x_preferred":[
        "\u6c88\u9c8d"
    ],
    "wof:name":"Shenbao",
    "wof:placetype":"locality"
},
  "geometry": {"coordinates":[121.44861000000002,29.67682000000001],"type":"Point"}
}