{
  "type": "Feature",
  "properties": {
    "gn:admin1_code":"32.0",
    "gn:asciiname":"Mingguang",
    "gn:country_code":"CN",
    "gn:dem":308,
    "gn:feature_class":"P",
    "gn:feature_code":"PPL",
    "gn:name":"Mingguang",
    "gn:population":0,
    "gn:timezone":"Asia/Shanghai",
    "iso:country":"CN",
    "name:zho_x_preferred":[
        "\u660e\u5149"
    ],
    "wof:name":"Mingguang",
    "wof:placetype":"locality"
},
  "geometry": {"coordinates":[106.08,30.6896],"type":"Point"}
}