{
  "type": "Feature",
  "properties": {
    "gn:admin1_code":"32.0",
    "gn:asciiname":"Mingguang",
    "gn:country_code":"CN",
    "gn:dem":308,
    "gn:feature_class":"P",
    "gn:feature_code":"PPL",
    "gn:name":"Mingguang",
    "gn:population":0,
    "gn:timezone":"Asia/Shanghai",
    "iso:country":"CN",
    "name:ara_x_preferred":[
        "\u0645\u064a\u0646\u063a\u0648\u0627\u0646\u063a"
    ],
    "name:deu_x_preferred":[
        "Mingguang"
    ],
    "name:fas_x_preferred":[
        "\u0645\u06cc\u0646\u06af\u0648\u0627\u0646\u06af"
    ],
    "name:fra_x_preferred":[
        "Mingguang"
    ],
    "name:ita_x_preferred":[
        "Mingguang"
    ],
    "name:jpn_x_preferred":[
        "\u660e\u5149\u5e02"
    ],
    "name:kik_x_preferred":[
        "Mingguang"
    ],
    "name:kor_x_preferred":[
        "\ubc0d\uad11\uc2dc"
    ],
    "name:mlg_x_preferred":[
        "Mingguang"
    ],
    "name:mwl_x_preferred":[
        "Mingguang"
    ],
    "name:nor_x_preferred":[
        "Mingguang"
    ],
    "name:pam_x_preferred":[
        "Mingguang"
    ],
    "name:pnb_x_preferred":[
        "\u0645\u0646\u06af\u06af\u0648\u0622\u0646\u06af"
    ],
    "name:pol_x_preferred":[
        "Mingguang"
    ],
    "name:spa_x_preferred":[
        "M\u00ednggu\u0101ng Sh\u00ec"
    ],
    "name:swe_x_preferred":[
        "Mingguang"
    ],
    "name:urd_x_preferred":[
        "\u0645\u0646\u06af\u06af\u0648\u0627\u0646\u06af"
    ],
    "name:vie_x_preferred":[
        "Minh Quang"
    ],
    "name:zho_x_preferred":[
        "\u660e\u5149"
    ],
    "name:zho_x_variant":[
        "\u660e\u5149\u5e02"
    ],
    "wof:name":"Mingguang",
    "wof:placetype":"locality"
},
  "geometry": {"coordinates":[106.08,30.6896],"type":"Point"}
}