{
  "type": "Feature",
  "properties": {
    "gn:admin1_code":"18",
    "gn:asciiname":"Liziba",
    "gn:country_code":"CN",
    "gn:dem":2315,
    "gn:feature_class":"P",
    "gn:feature_code":"PPL",
    "gn:name":"Liziba",
    "gn:population":0,
    "gn:timezone":"Asia/Shanghai",
    "iso:country":"CN",
    "name:zho_x_preferred":[
        "\u68a8\u5b50\u628a"
    ],
    "wof:name":"Liziba",
    "wof:placetype":"locality"
},
  "geometry": {"coordinates":[104.331,26.9363],"type":"Point"}
}