{
  "type": "Feature",
  "properties": {
    "gn:admin1_code":"14.0",
    "gn:asciiname":"Nyilogka",
    "gn:country_code":"CN",
    "gn:dem":3903,
    "gn:feature_class":"P",
    "gn:feature_code":"PPL",
    "gn:name":"Nyilogka",
    "gn:population":0,
    "gn:timezone":"Asia/Urumqi",
    "iso:country":"CN",
    "name:bod_x_preferred":[
        "Nyilogka"
    ],
    "name:zho_x_preferred":[
        "Niluoka"
    ],
    "name:zho_x_variant":[
        "\u5c3c\u843d\u5361",
        "Yusha Gongshe",
        "\u7389\u6c99\u516c\u793e"
    ],
    "wof:name":"Nyilogka",
    "wof:placetype":"locality"
},
  "geometry": {"coordinates":[95.401,30.101],"type":"Point"}
}