{
  "type": "Feature",
  "properties": {
    "gn:admin1_code":"16.0",
    "gn:asciiname":"Xia'ou",
    "gn:country_code":"CN",
    "gn:dem":266,
    "gn:feature_class":"P",
    "gn:feature_code":"PPL",
    "gn:name":"Xia\u2019ou",
    "gn:population":0,
    "gn:timezone":"Asia/Shanghai",
    "iso:country":"CN",
    "name:und_x_variant":[
        "Xia\u2019ou"
    ],
    "name:zho_x_preferred":[
        "\u4e0b\u6b27"
    ],
    "wof:name":"Xia'ou",
    "wof:placetype":"locality"
},
  "geometry": {"coordinates":[108.13200000000001,25.0724],"type":"Point"}
}