{
  "type": "Feature",
  "properties": {
    "gn:admin1_code":"10",
    "gn:asciiname":"Xiashilu",
    "gn:country_code":"CN",
    "gn:dem":261,
    "gn:feature_class":"P",
    "gn:feature_code":"PPL",
    "gn:name":"Xiashilu",
    "gn:population":0,
    "gn:timezone":"Asia/Shanghai",
    "iso:country":"CN",
    "name:zho_x_preferred":[
        "\u4e0b\u77f3\u8def"
    ],
    "wof:name":"Xiashilu",
    "wof:placetype":"locality"
},
  "geometry": {"coordinates":[114.24299999999999,37.5499],"type":"Point"}
}