{
  "type": "Feature",
  "properties": {
    "gn:admin1_code":"8.0",
    "gn:asciiname":"Anpingcun",
    "gn:country_code":"CN",
    "gn:dem":134,
    "gn:feature_class":"P",
    "gn:feature_code":"PPL",
    "gn:name":"Anpingcun",
    "gn:population":0,
    "gn:timezone":"Asia/Shanghai",
    "iso:country":"CN",
    "name:zho_x_preferred":[
        "\u5b89\u5e73\u6751"
    ],
    "wof:name":"Anpingcun",
    "wof:placetype":"locality"
},
  "geometry": {"coordinates":[124.07903,46.10066],"type":"Point"}
}