{
  "type": "Feature",
  "properties": {
    "gn:admin1_code":"24.0",
    "gn:asciiname":"Linhai",
    "gn:country_code":"CN",
    "gn:dem":1285,
    "gn:feature_class":"P",
    "gn:feature_code":"PPL",
    "gn:name":"Linhai",
    "gn:population":0,
    "gn:timezone":"Asia/Shanghai",
    "iso:country":"CN",
    "name:zho_x_preferred":[
        "\u6797\u6d77"
    ],
    "wof:name":"Linhai",
    "wof:placetype":"locality"
},
  "geometry": {"coordinates":[111.76524999999999,37.52363],"type":"Point"}
}