{
  "type": "Feature",
  "properties": {
    "gn:admin1_code":"19.0",
    "gn:asciiname":"Liulinzicun",
    "gn:country_code":"CN",
    "gn:dem":341,
    "gn:feature_class":"P",
    "gn:feature_code":"PPL",
    "gn:name":"Liulinzicun",
    "gn:population":0,
    "gn:timezone":"Asia/Shanghai",
    "iso:country":"CN",
    "name:zho_x_preferred":[
        "\u67f3\u6797\u5b50\u6751"
    ],
    "wof:name":"Liulinzicun",
    "wof:placetype":"locality"
},
  "geometry": {"coordinates":[125.09350000000001,41.34151],"type":"Point"}
}