{
  "type": "Feature",
  "properties": {
    "gn:admin1_code":"08",
    "gn:asciiname":"Qianjin",
    "gn:country_code":"CN",
    "gn:dem":56,
    "gn:feature_class":"P",
    "gn:feature_code":"PPL",
    "gn:name":"Qianjin",
    "gn:population":0,
    "gn:timezone":"Asia/Shanghai",
    "iso:country":"CN",
    "name:ceb_x_preferred":[
        "Qianjin"
    ],
    "name:deu_x_preferred":[
        "Qianjin"
    ],
    "name:eus_x_preferred":[
        "Qianjin"
    ],
    "name:kor_x_preferred":[
        "\uccb8\uc9c4\uad6c"
    ],
    "name:rus_x_preferred":[
        "\u0426\u044f\u043d\u044c\u0446\u0437\u0438\u043d\u044c"
    ],
    "name:zho_x_preferred":[
        "\u524d\u8fdb"
    ],
    "wof:name":"Qianjin",
    "wof:placetype":"locality"
},
  "geometry": {"coordinates":[134.41642999999999,48.00844],"type":"Point"}
}