{
  "type": "Feature",
  "properties": {
    "gn:admin1_code":"8.0",
    "gn:asciiname":"Erzhancun",
    "gn:country_code":"CN",
    "gn:dem":376,
    "gn:feature_class":"P",
    "gn:feature_code":"PPL",
    "gn:name":"Erzhancun",
    "gn:population":0,
    "gn:timezone":"Asia/Shanghai",
    "iso:country":"CN",
    "name:zho_x_preferred":[
        "\u5c14\u7ad9\u6751"
    ],
    "wof:name":"Erzhancun",
    "wof:placetype":"locality"
},
  "geometry": {"coordinates":[128.75176999999999,43.96095],"type":"Point"}
}