{
  "type": "Feature",
  "properties": {
    "gn:admin1_code":"30.0",
    "gn:asciiname":"Yanggongkeng",
    "gn:country_code":"CN",
    "gn:dem":162,
    "gn:feature_class":"P",
    "gn:feature_code":"PPL",
    "gn:name":"Yanggongkeng",
    "gn:population":0,
    "gn:timezone":"Asia/Shanghai",
    "iso:country":"CN",
    "name:zho_x_preferred":[
        "\u6768\u516c\u5751"
    ],
    "wof:name":"Yanggongkeng",
    "wof:placetype":"locality"
},
  "geometry": {"coordinates":[114.56677999999999,25.22416],"type":"Point"}
}