{
  "type": "Feature",
  "properties": {
    "gn:admin1_code":"4.0",
    "gn:asciiname":"Jijiadai",
    "gn:country_code":"CN",
    "gn:dem":7,
    "gn:feature_class":"P",
    "gn:feature_code":"PPL",
    "gn:name":"Jijiadai",
    "gn:population":0,
    "gn:timezone":"Asia/Shanghai",
    "iso:country":"CN",
    "name:zho_x_preferred":[
        "\u5b63\u5bb6\u5788"
    ],
    "wof:name":"Jijiadai",
    "wof:placetype":"locality"
},
  "geometry": {"coordinates":[120.15976999999999,32.0447],"type":"Point"}
}