{
  "type": "Feature",
  "properties": {
    "gn:admin1_code":"11",
    "gn:asciiname":"Dayuandong",
    "gn:country_code":"CN",
    "gn:dem":446,
    "gn:feature_class":"P",
    "gn:feature_code":"PPL",
    "gn:name":"Dayuandong",
    "gn:population":0,
    "gn:timezone":"Asia/Shanghai",
    "iso:country":"CN",
    "name:zho_x_preferred":[
        "\u5927\u6e90\u6d1e"
    ],
    "wof:name":"Dayuandong",
    "wof:placetype":"locality"
},
  "geometry": {"coordinates":[111.46460999999999,25.17476],"type":"Point"}
}