{
  "type": "Feature",
  "properties": {
    "gn:admin1_code":"32.0",
    "gn:asciiname":"Xinyi",
    "gn:country_code":"CN",
    "gn:dem":436,
    "gn:feature_class":"P",
    "gn:feature_code":"PPL",
    "gn:name":"Xinyi",
    "gn:population":0,
    "gn:timezone":"Asia/Shanghai",
    "iso:country":"CN",
    "name:ceb_x_preferred":[
        "Xinyi"
    ],
    "name:deu_x_preferred":[
        "Xinyi"
    ],
    "name:fas_x_preferred":[
        "\u0634\u06cc\u0646\u06cc"
    ],
    "name:fra_x_preferred":[
        "Xinyi"
    ],
    "name:heb_x_preferred":[
        "\u05e7\u05e1\u05d9\u05e0\u05d9\u05d9"
    ],
    "name:hun_x_preferred":[
        "Xinyi"
    ],
    "name:jpn_x_preferred":[
        "\u30b7\u30f3\u30a4\u30fc"
    ],
    "name:kor_x_preferred":[
        "\uc2e0\uc774\uc2dc"
    ],
    "name:mlg_x_preferred":[
        "Xinyi"
    ],
    "name:nor_x_preferred":[
        "Xinyi"
    ],
    "name:rus_x_preferred":[
        "\u0421\u0438\u043d\u044c\u0438"
    ],
    "name:swe_x_preferred":[
        "Xinyi"
    ],
    "name:zho_x_preferred":[
        "\u4fe1\u4e49"
    ],
    "wof:name":"Xinyi",
    "wof:placetype":"locality"
},
  "geometry": {"coordinates":[107.06999999999999,31.5814],"type":"Point"}
}