{
  "type": "Feature",
  "properties": {
    "gn:admin1_code":"2.0",
    "gn:asciiname":"Luotang",
    "gn:country_code":"CN",
    "gn:dem":123,
    "gn:feature_class":"P",
    "gn:feature_code":"PPL",
    "gn:name":"Luotang",
    "gn:population":0,
    "gn:timezone":"Asia/Shanghai",
    "iso:country":"CN",
    "name:und_x_variant":[
        "\u7f57\u5858",
        "Luotang"
    ],
    "wof:name":"Luotang",
    "wof:placetype":"locality"
},
  "geometry": {"coordinates":[119.83778999999998,29.46822],"type":"Point"}
}