{
  "type": "Feature",
  "properties": {
    "gn:admin1_code":"18",
    "gn:asciiname":"Chenjiazhai",
    "gn:country_code":"CN",
    "gn:dem":1848,
    "gn:feature_class":"P",
    "gn:feature_code":"PPL",
    "gn:name":"Chenjiazhai",
    "gn:population":0,
    "gn:timezone":"Asia/Shanghai",
    "iso:country":"CN",
    "name:zho_x_preferred":[
        "\u9648\u5bb6\u5be8"
    ],
    "wof:name":"Chenjiazhai",
    "wof:placetype":"locality"
},
  "geometry": {"coordinates":[105.217,26.7876],"type":"Point"}
}