{
  "type": "Feature",
  "properties": {
    "gn:admin1_code":"0.0",
    "gn:asciiname":"Shunhe",
    "gn:country_code":"CN",
    "gn:dem":1265,
    "gn:feature_class":"P",
    "gn:feature_code":"PPL",
    "gn:name":"Shunhe",
    "gn:population":0,
    "gn:timezone":"Asia/Shanghai",
    "iso:country":"CN",
    "name:zho_x_preferred":[
        "\u987a\u6cb3"
    ],
    "wof:name":"Shunhe",
    "wof:placetype":"locality"
},
  "geometry": {"coordinates":[102.82608,29.28972000000001],"type":"Point"}
}