{
  "type": "Feature",
  "properties": {
    "gn:admin1_code":"10",
    "gn:asciiname":"Shuimowan",
    "gn:country_code":"CN",
    "gn:dem":677,
    "gn:feature_class":"P",
    "gn:feature_code":"PPL",
    "gn:name":"Shuimowan",
    "gn:population":0,
    "gn:timezone":"Asia/Shanghai",
    "iso:country":"CN",
    "name:zho_x_preferred":[
        "\u6c34\u78e8\u6e7e"
    ],
    "wof:name":"Shuimowan",
    "wof:placetype":"locality"
},
  "geometry": {"coordinates":[116.22017,40.88629],"type":"Point"}
}