{
  "type": "Feature",
  "properties": {
    "gn:admin1_code":"32.0",
    "gn:asciiname":"Molin",
    "gn:country_code":"CN",
    "gn:dem":713,
    "gn:feature_class":"P",
    "gn:feature_code":"PPL",
    "gn:name":"Molin",
    "gn:population":0,
    "gn:timezone":"Asia/Shanghai",
    "iso:country":"CN",
    "name:deu_x_preferred":[
        "Molin"
    ],
    "name:rus_x_preferred":[
        "\u041c\u043e\u043b\u0438\u043d"
    ],
    "name:srp_x_preferred":[
        "\u041c\u043e\u043b\u0438\u043d"
    ],
    "name:swe_x_preferred":[
        "Molin"
    ],
    "name:zho_x_preferred":[
        "\u58a8\u6797"
    ],
    "wof:name":"Molin",
    "wof:placetype":"locality"
},
  "geometry": {"coordinates":[104.45977000000001,29.54779000000001],"type":"Point"}
}