{
  "type": "Feature",
  "properties": {
    "gn:admin1_code":"15.0",
    "gn:asciiname":"Dougouwa",
    "gn:country_code":"CN",
    "gn:dem":1717,
    "gn:feature_class":"P",
    "gn:feature_code":"PPL",
    "gn:name":"Dougouwa",
    "gn:population":0,
    "gn:timezone":"Asia/Shanghai",
    "iso:country":"CN",
    "name:zho_x_preferred":[
        "\u9661\u6c9f\u6d3c"
    ],
    "wof:name":"Dougouwa",
    "wof:placetype":"locality"
},
  "geometry": {"coordinates":[106.547,35.6764],"type":"Point"}
}