{
  "type": "Feature",
  "properties": {
    "gn:admin1_code":"18",
    "gn:asciiname":"Liuwan",
    "gn:country_code":"CN",
    "gn:dem":1121,
    "gn:feature_class":"P",
    "gn:feature_code":"PPL",
    "gn:name":"Liuwan",
    "gn:population":0,
    "gn:timezone":"Asia/Shanghai",
    "iso:country":"CN",
    "name:zho_x_preferred":[
        "\u67f3\u6e7e"
    ],
    "wof:name":"Liuwan",
    "wof:placetype":"locality"
},
  "geometry": {"coordinates":[105.619,27.6063],"type":"Point"}
}