{
  "type": "Feature",
  "properties": {
    "gn:admin1_code":"14.0",
    "gn:asciiname":"Nailung",
    "gn:country_code":"CN",
    "gn:dem":4934,
    "gn:feature_class":"P",
    "gn:feature_code":"PPLF",
    "gn:name":"Nailung",
    "gn:population":0,
    "gn:timezone":"Asia/Urumqi",
    "iso:country":"CN",
    "name:bod_x_preferred":[
        "Nailung"
    ],
    "name:zho_x_preferred":[
        "Nailong"
    ],
    "name:zho_x_variant":[
        "\u4e43\u9686",
        "Nieru Qu",
        "\u6d85\u5982\u533a"
    ],
    "wof:name":"Nailung",
    "wof:placetype":"locality"
},
  "geometry": {"coordinates":[89.801,28.501],"type":"Point"}
}