{
  "type": "Feature",
  "properties": {
    "gn:admin1_code":"2.0",
    "gn:asciiname":"Xinqiaotou",
    "gn:country_code":"CN",
    "gn:dem":487,
    "gn:feature_class":"P",
    "gn:feature_code":"PPL",
    "gn:name":"Xinqiaotou",
    "gn:population":0,
    "gn:timezone":"Asia/Shanghai",
    "iso:country":"CN",
    "name:und_x_variant":[
        "\u65b0\u6865\u5934"
    ],
    "wof:name":"Xinqiaotou",
    "wof:placetype":"locality"
},
  "geometry": {"coordinates":[118.93917999999999,30.26574],"type":"Point"}
}