{
  "type": "Feature",
  "properties": {
    "gn:admin1_code":"32.0",
    "gn:asciiname":"Laigan",
    "gn:country_code":"CN",
    "gn:dem":2434,
    "gn:feature_class":"P",
    "gn:feature_code":"PPL",
    "gn:name":"Laigan",
    "gn:population":0,
    "gn:timezone":"Asia/Shanghai",
    "iso:country":"CN",
    "name:zho_x_preferred":[
        "\u6765\u7518"
    ],
    "wof:name":"Laigan",
    "wof:placetype":"locality"
},
  "geometry": {"coordinates":[102.557,28.1325],"type":"Point"}
}