{
  "type": "Feature",
  "properties": {
    "gn:admin1_code":"1.0",
    "gn:asciiname":"Qiaokoucun",
    "gn:country_code":"CN",
    "gn:dem":25,
    "gn:feature_class":"P",
    "gn:feature_code":"PPL",
    "gn:name":"Qiaokoucun",
    "gn:population":0,
    "gn:timezone":"Asia/Shanghai",
    "iso:country":"CN",
    "name:zho_x_preferred":[
        "\u6865\u53e3\u6751"
    ],
    "wof:name":"Qiaokoucun",
    "wof:placetype":"locality"
},
  "geometry": {"coordinates":[117.15434999999999,33.19260999999999],"type":"Point"}
}