{
  "type": "Feature",
  "properties": {
    "gn:admin1_code":"16.0",
    "gn:asciiname":"Liuliao",
    "gn:country_code":"CN",
    "gn:dem":123,
    "gn:feature_class":"P",
    "gn:feature_code":"PPL",
    "gn:name":"Liuliao",
    "gn:population":0,
    "gn:timezone":"Asia/Shanghai",
    "iso:country":"CN",
    "name:zho_x_preferred":[
        "\u516d\u8fbd"
    ],
    "wof:name":"Liuliao",
    "wof:placetype":"locality"
},
  "geometry": {"coordinates":[109.27500000000001,22.5435],"type":"Point"}
}