{
  "type": "Feature",
  "properties": {
    "gn:admin1_code":"15.0",
    "gn:asciiname":"zuiwanli",
    "gn:country_code":"CN",
    "gn:dem":1963,
    "gn:feature_class":"P",
    "gn:feature_code":"PPL",
    "gn:name":"zuiwanli",
    "gn:population":0,
    "gn:timezone":"Asia/Shanghai",
    "iso:country":"CN",
    "name:und_x_variant":[
        "\u83ca\u6e7e\u91cc"
    ],
    "wof:name":"zuiwanli",
    "wof:placetype":"locality"
},
  "geometry": {"coordinates":[104.73663999999999,34.67029],"type":"Point"}
}