{
  "type": "Feature",
  "properties": {
    "gn:admin1_code":"30",
    "gn:asciiname":"Dawuxia",
    "gn:country_code":"CN",
    "gn:dem":96,
    "gn:feature_class":"P",
    "gn:feature_code":"PPL",
    "gn:name":"Dawuxia",
    "gn:population":0,
    "gn:timezone":"Asia/Shanghai",
    "iso:country":"CN",
    "name:zho_x_preferred":[
        "\u5927\u5c4b\u4e0b"
    ],
    "wof:name":"Dawuxia",
    "wof:placetype":"locality"
},
  "geometry": {"coordinates":[116.13937,24.62962000000001],"type":"Point"}
}