{
  "type": "Feature",
  "properties": {
    "gn:admin1_code":"32.0",
    "gn:asciiname":"Jiya'ergeng",
    "gn:country_code":"CN",
    "gn:dem":3462,
    "gn:feature_class":"P",
    "gn:feature_code":"PPL",
    "gn:name":"Jiya\u2019ergeng",
    "gn:population":0,
    "gn:timezone":"Asia/Shanghai",
    "iso:country":"CN",
    "name:und_x_variant":[
        "Jiya\u2019ergeng"
    ],
    "name:zho_x_preferred":[
        "\u7ed9\u4e9a\u5c14\u66f4"
    ],
    "wof:name":"Jiya'ergeng",
    "wof:placetype":"locality"
},
  "geometry": {"coordinates":[101.01600000000001,32.189],"type":"Point"}
}