{
  "type": "Feature",
  "properties": {
    "gn:admin1_code":"16",
    "gn:asciiname":"Baikang",
    "gn:country_code":"CN",
    "gn:dem":207,
    "gn:feature_class":"P",
    "gn:feature_code":"PPL",
    "gn:name":"Baikang",
    "gn:population":0,
    "gn:timezone":"Asia/Shanghai",
    "iso:country":"CN",
    "name:zho_x_preferred":[
        "\u767e\u5eb7"
    ],
    "wof:name":"Baikang",
    "wof:placetype":"locality"
},
  "geometry": {"coordinates":[106.20399999999999,23.9248],"type":"Point"}
}