{
  "type": "Feature",
  "properties": {
    "gn:admin1_code":"12.0",
    "gn:asciiname":"Ximaping",
    "gn:country_code":"CN",
    "gn:dem":870,
    "gn:feature_class":"P",
    "gn:feature_code":"PPL",
    "gn:name":"Ximaping",
    "gn:population":0,
    "gn:timezone":"Asia/Shanghai",
    "iso:country":"CN",
    "name:zho_x_preferred":[
        "\u6d17\u9a6c\u576a"
    ],
    "wof:name":"Ximaping",
    "wof:placetype":"locality"
},
  "geometry": {"coordinates":[109.63751999999999,29.90893],"type":"Point"}
}