{
  "type": "Feature",
  "properties": {
    "gn:admin1_code":"21.0",
    "gn:asciiname":"Fenghuodun",
    "gn:country_code":"CN",
    "gn:dem":1177,
    "gn:feature_class":"P",
    "gn:feature_code":"PPL",
    "gn:name":"Fenghuodun",
    "gn:population":0,
    "gn:timezone":"Asia/Shanghai",
    "iso:country":"CN",
    "name:zho_x_preferred":[
        "\u70fd\u706b\u58a9"
    ],
    "wof:name":"Fenghuodun",
    "wof:placetype":"locality"
},
  "geometry": {"coordinates":[106.194,37.7884],"type":"Point"}
}