{
  "type": "Feature",
  "properties": {
    "gn:admin1_code":"9.0",
    "gn:asciiname":"Beishaomai",
    "gn:country_code":"CN",
    "gn:dem":665,
    "gn:feature_class":"P",
    "gn:feature_code":"PPL",
    "gn:name":"Beishaomai",
    "gn:population":0,
    "gn:timezone":"Asia/Shanghai",
    "iso:country":"CN",
    "name:zho_x_preferred":[
        "\u5317\u97f6\u8109"
    ],
    "wof:name":"Beishaomai",
    "wof:placetype":"locality"
},
  "geometry": {"coordinates":[111.76528,34.82287],"type":"Point"}
}