{
  "type": "Feature",
  "properties": {
    "gn:admin1_code":"10",
    "gn:asciiname":"Nanxing",
    "gn:country_code":"CN",
    "gn:dem":236,
    "gn:feature_class":"P",
    "gn:feature_code":"PPLA4",
    "gn:name":"Nanxing",
    "gn:population":0,
    "gn:timezone":"Asia/Shanghai",
    "iso:country":"CN",
    "name:fas_x_preferred":[
        "\u0634\u0647\u0631\u06a9 \u0646\u0627\u0634\u06cc\u0646\u06af"
    ],
    "name:und_x_variant":[
        "\u5357\u9649",
        "Nanxing Xiang"
    ],
    "name:zho_x_preferred":[
        "\u5357\u9649\u4e61"
    ],
    "wof:name":"Nanxing",
    "wof:placetype":"locality"
},
  "geometry": {"coordinates":[114.05273,38.18193],"type":"Point"}
}