{
  "type": "Feature",
  "properties": {
    "gn:admin1_code":"10",
    "gn:asciiname":"Nanxing",
    "gn:country_code":"CN",
    "gn:dem":236,
    "gn:feature_class":"P",
    "gn:feature_code":"PPLA4",
    "gn:name":"Nanxing",
    "gn:population":0,
    "gn:timezone":"Asia/Shanghai",
    "iso:country":"CN",
    "name:und_x_variant":[
        "\u5357\u9649",
        "Nanxing Xiang",
        "\u5357\u9649\u4e61"
    ],
    "wof:name":"Nanxing",
    "wof:placetype":"locality"
},
  "geometry": {"coordinates":[114.05273,38.18193],"type":"Point"}
}