{
  "type": "Feature",
  "properties": {
    "gn:admin1_code":"10",
    "gn:asciiname":"Maozhou",
    "gn:cc2":"CN",
    "gn:country_code":"CN",
    "gn:dem":8,
    "gn:feature_class":"P",
    "gn:feature_code":"PPL",
    "gn:name":"Maozhou",
    "gn:population":0,
    "gn:timezone":"Asia/Shanghai",
    "iso:country":"CN",
    "name:und_x_variant":[
        "Mo-chou",
        "Maochow",
        "Maozhou"
    ],
    "name:zho_x_preferred":[
        "\u911a\u5dde\u9547"
    ],
    "wof:name":"Maozhou",
    "wof:placetype":"locality"
},
  "geometry": {"coordinates":[116.11472000000001,38.84833],"type":"Point"}
}