{
  "type": "Feature",
  "properties": {
    "gn:admin1_code":"29",
    "gn:asciiname":"Songlongqing",
    "gn:country_code":"CN",
    "gn:dem":2056,
    "gn:feature_class":"P",
    "gn:feature_code":"PPL",
    "gn:name":"Songlongqing",
    "gn:population":0,
    "gn:timezone":"Asia/Shanghai",
    "iso:country":"CN",
    "name:zho_x_preferred":[
        "\u5b8b\u9f99\u7b90"
    ],
    "wof:name":"Songlongqing",
    "wof:placetype":"locality"
},
  "geometry": {"coordinates":[102.58869,25.00221],"type":"Point"}
}