{
  "type": "Feature",
  "properties": {
    "gn:admin1_code":"12.0",
    "gn:asciiname":"Fengdongziwan",
    "gn:country_code":"CN",
    "gn:dem":1464,
    "gn:feature_class":"P",
    "gn:feature_code":"PPL",
    "gn:name":"Fengdongziwan",
    "gn:population":0,
    "gn:timezone":"Asia/Shanghai",
    "iso:country":"CN",
    "name:zho_x_preferred":[
        "\u98ce\u6d1e\u5b50\u6e7e"
    ],
    "wof:name":"Fengdongziwan",
    "wof:placetype":"locality"
},
  "geometry": {"coordinates":[109.97429,30.76199],"type":"Point"}
}