{
  "type": "Feature",
  "properties": {
    "gn:admin1_code":"18",
    "gn:asciiname":"Dongzitou",
    "gn:country_code":"CN",
    "gn:dem":958,
    "gn:feature_class":"P",
    "gn:feature_code":"PPL",
    "gn:name":"Dongzitou",
    "gn:population":0,
    "gn:timezone":"Asia/Shanghai",
    "iso:country":"CN",
    "name:zho_x_preferred":[
        "\u6d1e\u5b50\u5934"
    ],
    "wof:name":"Dongzitou",
    "wof:placetype":"locality"
},
  "geometry": {"coordinates":[107.95699999999999,28.0208],"type":"Point"}
}