{
  "type": "Feature",
  "properties": {
    "gn:admin1_code":"32.0",
    "gn:asciiname":"Zhaiqiao",
    "gn:country_code":"CN",
    "gn:dem":499,
    "gn:feature_class":"P",
    "gn:feature_code":"PPL",
    "gn:name":"Zhaiqiao",
    "gn:population":0,
    "gn:timezone":"Asia/Shanghai",
    "iso:country":"CN",
    "name:zho_x_preferred":[
        "\u5be8\u6865"
    ],
    "wof:name":"Zhaiqiao",
    "wof:placetype":"locality"
},
  "geometry": {"coordinates":[105.244,31.8649],"type":"Point"}
}