{
  "type": "Feature",
  "properties": {
    "gn:admin1_code":"10.0",
    "gn:asciiname":"Dingguantun",
    "gn:country_code":"CN",
    "gn:dem":14,
    "gn:feature_class":"P",
    "gn:feature_code":"PPL",
    "gn:name":"Dingguantun",
    "gn:population":0,
    "gn:timezone":"Asia/Shanghai",
    "iso:country":"CN",
    "name:zho_x_preferred":[
        "\u4e01\u5b98\u5c6f"
    ],
    "wof:name":"Dingguantun",
    "wof:placetype":"locality"
},
  "geometry": {"coordinates":[117.87734,39.8028],"type":"Point"}
}