{
  "type": "Feature",
  "properties": {
    "gn:admin1_code":"29.0",
    "gn:asciiname":"Baimazhai",
    "gn:country_code":"CN",
    "gn:dem":1533,
    "gn:feature_class":"P",
    "gn:feature_code":"PPL",
    "gn:name":"Baimazhai",
    "gn:population":0,
    "gn:timezone":"Asia/Shanghai",
    "iso:country":"CN",
    "name:zho_x_preferred":[
        "\u767d\u9a6c\u5be8"
    ],
    "wof:name":"Baimazhai",
    "wof:placetype":"locality"
},
  "geometry": {"coordinates":[103.899,23.5347],"type":"Point"}
}