{
  "type": "Feature",
  "properties": {
    "gn:admin1_code":"2.0",
    "gn:asciiname":"Hongcun",
    "gn:country_code":"CN",
    "gn:dem":47,
    "gn:feature_class":"P",
    "gn:feature_code":"PPL",
    "gn:name":"Hongcun",
    "gn:population":0,
    "gn:timezone":"Asia/Shanghai",
    "iso:country":"CN",
    "name:ast_x_preferred":[
        "Hongcun"
    ],
    "name:ces_x_preferred":[
        "Chung-cchun"
    ],
    "name:eus_x_preferred":[
        "Hongcun"
    ],
    "name:fas_x_preferred":[
        "\u0647\u0627\u0646\u06af\u06a9\u0646"
    ],
    "name:fin_x_preferred":[
        "Hongcun"
    ],
    "name:fra_x_preferred":[
        "Hongcun"
    ],
    "name:heb_x_preferred":[
        "\u05d4\u05d5\u05e0\u05d2\u05e6\u05d5\u05df"
    ],
    "name:hrv_x_preferred":[
        "Hongcun"
    ],
    "name:ita_x_preferred":[
        "Hongcun"
    ],
    "name:kat_x_preferred":[
        "\u10ee\u10e3\u10dc\u10ea\u10e3\u10dc\u10d8"
    ],
    "name:mal_x_preferred":[
        "\u0d39\u0d4b\u0d19\u0d4d\u0d38\u0d41\u0d7b"
    ],
    "name:nld_x_preferred":[
        "Hongcun"
    ],
    "name:por_x_preferred":[
        "Hongcun"
    ],
    "name:slk_x_preferred":[
        "Chung-cchun"
    ],
    "name:spa_x_preferred":[
        "Hongcun"
    ],
    "name:swe_x_preferred":[
        "Hongcun"
    ],
    "name:tur_x_preferred":[
        "Hongcun"
    ],
    "name:vie_x_preferred":[
        "Ho\u00e0nh th\u00f4n"
    ],
    "name:zho_x_preferred":[
        "\u6d2a\u6751"
    ],
    "wof:name":"Hongcun",
    "wof:placetype":"locality"
},
  "geometry": {"coordinates":[119.78351000000001,29.10413],"type":"Point"}
}