{
  "type": "Feature",
  "properties": {
    "gn:admin1_code":"8.0",
    "gn:asciiname":"Gong'ancun",
    "gn:country_code":"CN",
    "gn:dem":253,
    "gn:feature_class":"P",
    "gn:feature_code":"PPL",
    "gn:name":"Gong\u2019ancun",
    "gn:population":0,
    "gn:timezone":"Asia/Shanghai",
    "iso:country":"CN",
    "name:und_x_variant":[
        "Gong\u2019ancun"
    ],
    "name:zho_x_preferred":[
        "\u516c\u5b89\u6751"
    ],
    "wof:name":"Gong'ancun",
    "wof:placetype":"locality"
},
  "geometry": {"coordinates":[125.06571,48.08205],"type":"Point"}
}