{
  "type": "Feature",
  "properties": {
    "gn:admin1_code":"3.0",
    "gn:asciiname":"Qishuxia",
    "gn:country_code":"CN",
    "gn:dem":640,
    "gn:feature_class":"P",
    "gn:feature_code":"PPL",
    "gn:name":"Qishuxia",
    "gn:population":0,
    "gn:timezone":"Asia/Shanghai",
    "iso:country":"CN",
    "name:und_x_variant":[
        "\u675e\u6811\u4e0b"
    ],
    "wof:name":"Qishuxia",
    "wof:placetype":"locality"
},
  "geometry": {"coordinates":[115.01918000000001,28.79474],"type":"Point"}
}