{
  "type": "Feature",
  "properties": {
    "gn:admin1_code":"10",
    "gn:asciiname":"Liuduanzhai",
    "gn:country_code":"CN",
    "gn:dem":42,
    "gn:feature_class":"P",
    "gn:feature_code":"PPL",
    "gn:name":"Liuduanzhai",
    "gn:population":0,
    "gn:timezone":"Asia/Shanghai",
    "iso:country":"CN",
    "name:zho_x_preferred":[
        "\u5218\u6bb5\u5be8"
    ],
    "wof:name":"Liuduanzhai",
    "wof:placetype":"locality"
},
  "geometry": {"coordinates":[115.28205,36.71673],"type":"Point"}
}