{
  "type": "Feature",
  "properties": {
    "gn:admin1_code":"04",
    "gn:asciiname":"Li-chia-t'ang",
    "gn:country_code":"CN",
    "gn:dem":3,
    "gn:feature_class":"P",
    "gn:feature_code":"PPL",
    "gn:name":"Li-chia-t\u2019ang",
    "gn:population":0,
    "gn:timezone":"Asia/Shanghai",
    "iso:country":"CN",
    "wof:name":"Li-chia-t'ang",
    "wof:placetype":"locality"
},
  "geometry": {"coordinates":[120.14221999999999,31.74944],"type":"Point"}
}