{
  "type": "Feature",
  "properties": {
    "gn:admin1_code":"26.0",
    "gn:asciiname":"Dongdili",
    "gn:country_code":"CN",
    "gn:dem":957,
    "gn:feature_class":"P",
    "gn:feature_code":"PPL",
    "gn:name":"Dongdili",
    "gn:population":0,
    "gn:timezone":"Asia/Shanghai",
    "iso:country":"CN",
    "name:zho_x_preferred":[
        "\u6d1e\u5e95\u91cc"
    ],
    "wof:name":"Dongdili",
    "wof:placetype":"locality"
},
  "geometry": {"coordinates":[109.56285,33.37722],"type":"Point"}
}