{
  "type": "Feature",
  "properties": {
    "gn:admin1_code":"8.0",
    "gn:asciiname":"Fengtian Shouliedui Beiying",
    "gn:country_code":"CN",
    "gn:dem":292,
    "gn:feature_class":"P",
    "gn:feature_code":"PPLF",
    "gn:name":"Fengtian Shouliedui Beiying",
    "gn:population":0,
    "gn:timezone":"Asia/Shanghai",
    "iso:country":"CN",
    "name:zho_x_preferred":[
        "\u4e30\u7530\u72e9\u730e\u961f\u5317\u8425"
    ],
    "wof:name":"Fengtian Shouliedui Beiying",
    "wof:placetype":"locality"
},
  "geometry": {"coordinates":[127.82177,47.40805],"type":"Point"}
}