{
  "type": "Feature",
  "properties": {
    "gn:admin1_code":"14.0",
    "gn:asciiname":"Lhanacha",
    "gn:country_code":"CN",
    "gn:dem":4707,
    "gn:feature_class":"P",
    "gn:feature_code":"PPL",
    "gn:name":"Lhanacha",
    "gn:population":0,
    "gn:timezone":"Asia/Urumqi",
    "iso:country":"CN",
    "name:bod_x_preferred":[
        "Lhanacha"
    ],
    "name:zho_x_preferred":[
        "Lanazha"
    ],
    "name:zho_x_variant":[
        "\u62c9\u90a3\u624e"
    ],
    "wof:name":"Lhanacha",
    "wof:placetype":"locality"
},
  "geometry": {"coordinates":[90.70099999999999,30.301],"type":"Point"}
}