{
  "type": "Feature",
  "properties": {
    "gn:admin1_code":"15.0",
    "gn:asciiname":"Taihe Dadui",
    "gn:country_code":"CN",
    "gn:dem":1571,
    "gn:feature_class":"P",
    "gn:feature_code":"PPLF",
    "gn:name":"Taihe Dadui",
    "gn:population":0,
    "gn:timezone":"Asia/Shanghai",
    "iso:country":"CN",
    "name:zho_x_preferred":[
        "\u592a\u548c\u5927\u961f"
    ],
    "wof:name":"Taihe Dadui",
    "wof:placetype":"locality"
},
  "geometry": {"coordinates":[104.15000000000001,37.251],"type":"Point"}
}