{
  "type": "Feature",
  "properties": {
    "gn:admin1_code":"16.0",
    "gn:asciiname":"Bailong",
    "gn:country_code":"CN",
    "gn:dem":385,
    "gn:feature_class":"P",
    "gn:feature_code":"PPL",
    "gn:name":"Bailong",
    "gn:population":0,
    "gn:timezone":"Asia/Shanghai",
    "iso:country":"CN",
    "name:zho_x_preferred":[
        "\u767e\u9f99"
    ],
    "wof:name":"Bailong",
    "wof:placetype":"locality"
},
  "geometry": {"coordinates":[107.10599999999999,23.366],"type":"Point"}
}