{
  "type": "Feature",
  "properties": {
    "gn:admin1_code":"24.0",
    "gn:asciiname":"Wanglaogou",
    "gn:country_code":"CN",
    "gn:dem":1506,
    "gn:feature_class":"P",
    "gn:feature_code":"PPL",
    "gn:name":"Wanglaogou",
    "gn:population":0,
    "gn:timezone":"Asia/Shanghai",
    "iso:country":"CN",
    "name:und_x_variant":[
        "Wang-lao-kou",
        "Wanglaogou",
        "Laogou",
        "\u8001\u6c9f",
        "\u738b\u8001\u6c9f"
    ],
    "wof:name":"Wanglaogou",
    "wof:placetype":"locality"
},
  "geometry": {"coordinates":[112.56744999999999,39.63238],"type":"Point"}
}