{
  "type": "Feature",
  "properties": {
    "gn:admin1_code":"19.0",
    "gn:asciiname":"Gaolintun",
    "gn:country_code":"CN",
    "gn:dem":122,
    "gn:feature_class":"P",
    "gn:feature_code":"PPL",
    "gn:name":"Gaolintun",
    "gn:population":0,
    "gn:timezone":"Asia/Shanghai",
    "iso:country":"CN",
    "name:zho_x_preferred":[
        "\u9ad8\u6797\u5c6f"
    ],
    "wof:name":"Gaolintun",
    "wof:placetype":"locality"
},
  "geometry": {"coordinates":[121.86632,41.77483],"type":"Point"}
}