{
  "type": "Feature",
  "properties": {
    "gn:admin1_code":"14.0",
    "gn:asciiname":"Nei Xincun",
    "gn:country_code":"CN",
    "gn:dem":3912,
    "gn:feature_class":"P",
    "gn:feature_code":"PPL",
    "gn:name":"Nei Xincun",
    "gn:population":0,
    "gn:timezone":"Asia/Urumqi",
    "iso:country":"CN",
    "name:zho_x_preferred":[
        "\u5185\u897f\u6751"
    ],
    "wof:name":"Nei Xincun",
    "wof:placetype":"locality"
},
  "geometry": {"coordinates":[95.0052,31.166],"type":"Point"}
}