{
  "type": "Feature",
  "properties": {
    "gn:admin1_code":"12.0",
    "gn:asciiname":"Bushang",
    "gn:country_code":"CN",
    "gn:dem":116,
    "gn:feature_class":"P",
    "gn:feature_code":"PPL",
    "gn:name":"Bushang",
    "gn:population":0,
    "gn:timezone":"Asia/Shanghai",
    "iso:country":"CN",
    "name:zho_x_preferred":[
        "Bushang"
    ],
    "name:zho_x_variant":[
        "\u57e0\u4e0a"
    ],
    "wof:name":"Bushang",
    "wof:placetype":"locality"
},
  "geometry": {"coordinates":[115.08335,30.91862],"type":"Point"}
}