{
  "type": "Feature",
  "properties": {
    "gn:admin1_code":"1.0",
    "gn:asciiname":"Songdayingcun",
    "gn:country_code":"CN",
    "gn:dem":79,
    "gn:feature_class":"P",
    "gn:feature_code":"PPL",
    "gn:name":"Songdayingcun",
    "gn:population":0,
    "gn:timezone":"Asia/Shanghai",
    "iso:country":"CN",
    "name:zho_x_preferred":[
        "\u5b8b\u5927\u90e2\u6751"
    ],
    "wof:name":"Songdayingcun",
    "wof:placetype":"locality"
},
  "geometry": {"coordinates":[116.74695,31.7065],"type":"Point"}
}