{
  "type": "Feature",
  "properties": {
    "gn:admin1_code":"10.0",
    "gn:asciiname":"Pingshibei",
    "gn:country_code":"CN",
    "gn:dem":39,
    "gn:feature_class":"P",
    "gn:feature_code":"PPL",
    "gn:name":"Pingshibei",
    "gn:population":0,
    "gn:timezone":"Asia/Shanghai",
    "iso:country":"CN",
    "name:zho_x_preferred":[
        "\u5e73\u5e02\u5317"
    ],
    "wof:name":"Pingshibei",
    "wof:placetype":"locality"
},
  "geometry": {"coordinates":[119.38479,39.96513],"type":"Point"}
}