{
  "type": "Feature",
  "properties": {
    "gn:admin1_code":"29",
    "gn:asciiname":"Mazhuang",
    "gn:country_code":"CN",
    "gn:dem":2044,
    "gn:feature_class":"P",
    "gn:feature_code":"PPL",
    "gn:name":"Mazhuang",
    "gn:population":0,
    "gn:timezone":"Asia/Shanghai",
    "iso:country":"CN",
    "name:zho_x_preferred":[
        "\u9a6c\u5e84"
    ],
    "wof:name":"Mazhuang",
    "wof:placetype":"locality"
},
  "geometry": {"coordinates":[102.96997,24.78971],"type":"Point"}
}