{
  "type": "Feature",
  "properties": {
    "gn:admin1_code":"11.0",
    "gn:asciiname":"Dagushan",
    "gn:country_code":"CN",
    "gn:dem":474,
    "gn:feature_class":"P",
    "gn:feature_code":"PPL",
    "gn:name":"Dagushan",
    "gn:population":0,
    "gn:timezone":"Asia/Shanghai",
    "iso:country":"CN",
    "name:zho_x_preferred":[
        "Dagushan"
    ],
    "name:zho_x_variant":[
        "\u6253\u8c37\u5c71"
    ],
    "wof:name":"Dagushan",
    "wof:placetype":"locality"
},
  "geometry": {"coordinates":[111.14366,29.1533],"type":"Point"}
}