{
  "type": "Feature",
  "properties": {
    "gn:admin1_code":"30",
    "gn:asciiname":"Hengjiangbei",
    "gn:country_code":"CN",
    "gn:dem":164,
    "gn:feature_class":"P",
    "gn:feature_code":"PPL",
    "gn:name":"Hengjiangbei",
    "gn:population":0,
    "gn:timezone":"Asia/Shanghai",
    "iso:country":"CN",
    "name:zho_x_preferred":[
        "\u6a2a\u6c5f\u80cc"
    ],
    "wof:name":"Hengjiangbei",
    "wof:placetype":"locality"
},
  "geometry": {"coordinates":[115.70820999999999,24.33585],"type":"Point"}
}