{
  "type": "Feature",
  "properties": {
    "gn:admin1_code":"19.0",
    "gn:asciiname":"Bianwai",
    "gn:country_code":"CN",
    "gn:dem":538,
    "gn:feature_class":"P",
    "gn:feature_code":"PPL",
    "gn:name":"Bianwai",
    "gn:population":0,
    "gn:timezone":"Asia/Shanghai",
    "iso:country":"CN",
    "name:und_x_variant":[
        "\u8fb9\u5916"
    ],
    "wof:name":"Bianwai",
    "wof:placetype":"locality"
},
  "geometry": {"coordinates":[124.73453000000001,41.57273],"type":"Point"}
}