{
  "type": "Feature",
  "properties": {
    "gn:admin1_code":"22.0",
    "gn:asciiname":"Qianxinzhuang",
    "gn:country_code":"CN",
    "gn:dem":69,
    "gn:feature_class":"P",
    "gn:feature_code":"PPL",
    "gn:name":"Qianxinzhuang",
    "gn:population":0,
    "gn:timezone":"Asia/Shanghai",
    "iso:country":"CN",
    "name:zho_x_preferred":[
        "\u524d\u8f9b\u5e84"
    ],
    "wof:name":"Qianxinzhuang",
    "wof:placetype":"locality"
},
  "geometry": {"coordinates":[116.55825,40.32061],"type":"Point"}
}