{
  "type": "Feature",
  "properties": {
    "gn:admin1_code":"3.0",
    "gn:asciiname":"Baijiashe",
    "gn:country_code":"CN",
    "gn:dem":1172,
    "gn:feature_class":"P",
    "gn:feature_code":"PPL",
    "gn:name":"Baijiashe",
    "gn:population":0,
    "gn:timezone":"Asia/Shanghai",
    "iso:country":"CN",
    "name:und_x_variant":[
        "\u767e\u5bb6\u7572"
    ],
    "wof:name":"Baijiashe",
    "wof:placetype":"locality"
},
  "geometry": {"coordinates":[116.98465,27.08354000000001],"type":"Point"}
}