{
  "type": "Feature",
  "properties": {
    "gn:admin1_code":"5.0",
    "gn:asciiname":"Chengzixia",
    "gn:country_code":"CN",
    "gn:dem":173,
    "gn:feature_class":"P",
    "gn:feature_code":"PPL",
    "gn:name":"Chengzixia",
    "gn:population":0,
    "gn:timezone":"Asia/Shanghai",
    "iso:country":"CN",
    "name:zho_x_preferred":[
        "\u57ce\u5b50\u4e0b"
    ],
    "wof:name":"Chengzixia",
    "wof:placetype":"locality"
},
  "geometry": {"coordinates":[126.00161,44.53712],"type":"Point"}
}