{
  "type": "Feature",
  "properties": {
    "gn:admin1_code":"20.0",
    "gn:asciiname":"Zhenxing",
    "gn:country_code":"CN",
    "gn:dem":343,
    "gn:feature_class":"P",
    "gn:feature_code":"PPL",
    "gn:name":"Zhenxing",
    "gn:population":0,
    "gn:timezone":"Asia/Shanghai",
    "iso:country":"CN",
    "name:zho_x_preferred":[
        "\u632f\u5174"
    ],
    "wof:name":"Zhenxing",
    "wof:placetype":"locality"
},
  "geometry": {"coordinates":[124.41912000000001,49.40382],"type":"Point"}
}