{
  "type": "Feature",
  "properties": {
    "gn:admin1_code":"33.0",
    "gn:asciiname":"Wangjiacao",
    "gn:country_code":"CN",
    "gn:dem":873,
    "gn:feature_class":"P",
    "gn:feature_code":"PPL",
    "gn:name":"Wangjiacao",
    "gn:population":0,
    "gn:timezone":"Asia/Shanghai",
    "iso:country":"CN",
    "name:zho_x_preferred":[
        "\u738b\u5bb6\u69fd"
    ],
    "wof:name":"Wangjiacao",
    "wof:placetype":"locality"
},
  "geometry": {"coordinates":[109.7804,31.19426],"type":"Point"}
}