{
  "type": "Feature",
  "properties": {
    "gn:admin1_code":"3.0",
    "gn:asciiname":"Gantangguo",
    "gn:country_code":"CN",
    "gn:dem":302,
    "gn:feature_class":"P",
    "gn:feature_code":"PPL",
    "gn:name":"Gantangguo",
    "gn:population":0,
    "gn:timezone":"Asia/Shanghai",
    "iso:country":"CN",
    "name:und_x_variant":[
        "\u7518\u5858\u57da"
    ],
    "wof:name":"Gantangguo",
    "wof:placetype":"locality"
},
  "geometry": {"coordinates":[114.03646999999999,29.00622000000001],"type":"Point"}
}