{
  "type": "Feature",
  "properties": {
    "gn:admin1_code":"11",
    "gn:asciiname":"Gaoqiao",
    "gn:country_code":"CN",
    "gn:dem":70,
    "gn:feature_class":"P",
    "gn:feature_code":"PPL",
    "gn:name":"Gaoqiao",
    "gn:population":0,
    "gn:timezone":"Asia/Shanghai",
    "iso:country":"CN",
    "name:ceb_x_preferred":[
        "Gaoqiao"
    ],
    "name:deu_x_preferred":[
        "Gaoqiao"
    ],
    "name:swe_x_preferred":[
        "Gaoqiao"
    ],
    "wof:name":"Gaoqiao",
    "wof:placetype":"locality"
},
  "geometry": {"coordinates":[113.30278,28.47167],"type":"Point"}
}