{
  "type": "Feature",
  "properties": {
    "gn:admin1_code":"6.0",
    "gn:asciiname":"Yecangtang",
    "gn:country_code":"CN",
    "gn:dem":3181,
    "gn:feature_class":"P",
    "gn:feature_code":"PPL",
    "gn:name":"Yecangtang",
    "gn:population":0,
    "gn:timezone":"Asia/Shanghai",
    "iso:country":"CN",
    "name:zho_x_preferred":[
        "\u91ce\u85cf\u5858"
    ],
    "wof:name":"Yecangtang",
    "wof:placetype":"locality"
},
  "geometry": {"coordinates":[101.44689,35.8065],"type":"Point"}
}