{
  "type": "Feature",
  "properties": {
    "gn:admin1_code":"2.0",
    "gn:asciiname":"Xinhe",
    "gn:country_code":"CN",
    "gn:dem":10,
    "gn:feature_class":"P",
    "gn:feature_code":"PPLA4",
    "gn:name":"Xinhe",
    "gn:population":0,
    "gn:timezone":"Asia/Shanghai",
    "iso:country":"CN",
    "name:und_x_variant":[
        "Hsin-ho",
        "Xinhe Zhen"
    ],
    "name:zho_x_preferred":[
        "Hsin-ho-so-ch\u2019eng"
    ],
    "name:zho_x_variant":[
        "\u65b0\u6cb3",
        "\u65b0\u6cb3\u9547"
    ],
    "wof:name":"Xinhe",
    "wof:placetype":"locality"
},
  "geometry": {"coordinates":[121.45103,28.48123],"type":"Point"}
}