{
  "type": "Feature",
  "properties": {
    "gn:admin1_code":"11",
    "gn:asciiname":"Congyangshu",
    "gn:country_code":"CN",
    "gn:dem":80,
    "gn:feature_class":"P",
    "gn:feature_code":"PPL",
    "gn:name":"Congyangshu",
    "gn:population":0,
    "gn:timezone":"Asia/Shanghai",
    "iso:country":"CN",
    "name:zho_x_preferred":[
        "\u4e1b\u9633\u6811"
    ],
    "wof:name":"Congyangshu",
    "wof:placetype":"locality"
},
  "geometry": {"coordinates":[112.48759,26.7078],"type":"Point"}
}