{
  "type": "Feature",
  "properties": {
    "gn:admin1_code":"24",
    "gn:asciiname":"Pianliang",
    "gn:country_code":"CN",
    "gn:dem":1177,
    "gn:feature_class":"P",
    "gn:feature_code":"PPL",
    "gn:name":"Pianliang",
    "gn:population":0,
    "gn:timezone":"Asia/Shanghai",
    "iso:country":"CN",
    "name:und_x_variant":[
        "\u504f\u6881"
    ],
    "wof:name":"Pianliang",
    "wof:placetype":"locality"
},
  "geometry": {"coordinates":[113.89722,39.45833],"type":"Point"}
}