{
  "type": "Feature",
  "properties": {
    "gn:admin1_code":"4.0",
    "gn:asciiname":"Jiwagou",
    "gn:country_code":"CN",
    "gn:dem":7,
    "gn:feature_class":"P",
    "gn:feature_code":"PPL",
    "gn:name":"Jiwagou",
    "gn:population":0,
    "gn:timezone":"Asia/Shanghai",
    "iso:country":"CN",
    "name:zho_x_preferred":[
        "\u5b63\u74e6\u6c9f"
    ],
    "wof:name":"Jiwagou",
    "wof:placetype":"locality"
},
  "geometry": {"coordinates":[118.956,34.7909],"type":"Point"}
}