{
  "type": "Feature",
  "properties": {
    "gn:admin1_code":"3.0",
    "gn:asciiname":"Dapingshan",
    "gn:country_code":"CN",
    "gn:dem":240,
    "gn:feature_class":"P",
    "gn:feature_code":"PPL",
    "gn:name":"Dapingshan",
    "gn:population":0,
    "gn:timezone":"Asia/Shanghai",
    "iso:country":"CN",
    "name:und_x_variant":[
        "\u5927\u576a\u5c71"
    ],
    "wof:name":"Dapingshan",
    "wof:placetype":"locality"
},
  "geometry": {"coordinates":[115.91329,25.67338],"type":"Point"}
}