{
  "type": "Feature",
  "properties": {
    "gn:admin1_code":"29.0",
    "gn:asciiname":"Ma'antian",
    "gn:country_code":"CN",
    "gn:dem":1061,
    "gn:feature_class":"P",
    "gn:feature_code":"PPL",
    "gn:name":"Ma\u2019antian",
    "gn:population":0,
    "gn:timezone":"Asia/Shanghai",
    "iso:country":"CN",
    "name:und_x_variant":[
        "Ma\u2019antian"
    ],
    "name:zho_x_preferred":[
        "\u9a6c\u978d\u7530"
    ],
    "wof:name":"Ma'antian",
    "wof:placetype":"locality"
},
  "geometry": {"coordinates":[104.267,24.5501],"type":"Point"}
}