{
  "type": "Feature",
  "properties": {
    "gn:admin1_code":"8.0",
    "gn:asciiname":"Fanshentun",
    "gn:country_code":"CN",
    "gn:dem":183,
    "gn:feature_class":"P",
    "gn:feature_code":"PPL",
    "gn:name":"Fanshentun",
    "gn:population":0,
    "gn:timezone":"Asia/Shanghai",
    "iso:country":"CN",
    "name:zho_x_preferred":[
        "\u7ffb\u8eab\u5c6f"
    ],
    "wof:name":"Fanshentun",
    "wof:placetype":"locality"
},
  "geometry": {"coordinates":[126.41258999999999,52.03089],"type":"Point"}
}