{
  "type": "Feature",
  "properties": {
    "gn:admin1_code":"1.0",
    "gn:asciiname":"Mazongling Linchang",
    "gn:country_code":"CN",
    "gn:dem":749,
    "gn:feature_class":"P",
    "gn:feature_code":"PPLF",
    "gn:name":"Mazongling Linchang",
    "gn:population":0,
    "gn:timezone":"Asia/Shanghai",
    "iso:country":"CN",
    "wof:name":"Mazongling Linchang",
    "wof:placetype":"locality"
},
  "geometry": {"coordinates":[115.65000000000001,31.28333],"type":"Point"}
}