{
  "type": "Feature",
  "properties": {
    "gn:admin1_code":"11.0",
    "gn:asciiname":"Zhonghuluo",
    "gn:country_code":"CN",
    "gn:dem":390,
    "gn:feature_class":"P",
    "gn:feature_code":"PPL",
    "gn:name":"Zhonghuluo",
    "gn:population":0,
    "gn:timezone":"Asia/Shanghai",
    "iso:country":"CN",
    "name:zho_x_preferred":[
        "\u4e2d\u864e\u843d"
    ],
    "wof:name":"Zhonghuluo",
    "wof:placetype":"locality"
},
  "geometry": {"coordinates":[109.85793,29.07527],"type":"Point"}
}