{
  "type": "Feature",
  "properties": {
    "gn:admin1_code":"2.0",
    "gn:asciiname":"Xingpu",
    "gn:country_code":"CN",
    "gn:dem":10,
    "gn:feature_class":"P",
    "gn:feature_code":"PPL",
    "gn:name":"Xingpu",
    "gn:population":0,
    "gn:timezone":"Asia/Shanghai",
    "iso:country":"CN",
    "name:und_x_variant":[
        "\u5174\u6d66"
    ],
    "wof:name":"Xingpu",
    "wof:placetype":"locality"
},
  "geometry": {"coordinates":[120.51963000000001,30.11149],"type":"Point"}
}