{
  "type": "Feature",
  "properties": {
    "gn:admin1_code":"30",
    "gn:asciiname":"Andawei",
    "gn:country_code":"CN",
    "gn:dem":165,
    "gn:feature_class":"P",
    "gn:feature_code":"PPL",
    "gn:name":"Andawei",
    "gn:population":0,
    "gn:timezone":"Asia/Shanghai",
    "iso:country":"CN",
    "name:zho_x_preferred":[
        "\u5b89\u5927\u56f4"
    ],
    "wof:name":"Andawei",
    "wof:placetype":"locality"
},
  "geometry": {"coordinates":[115.72283,24.40038],"type":"Point"}
}