{
  "type": "Feature",
  "properties": {
    "gn:admin1_code":"16.0",
    "gn:asciiname":"Bacha",
    "gn:country_code":"CN",
    "gn:dem":375,
    "gn:feature_class":"P",
    "gn:feature_code":"PPL",
    "gn:name":"Bacha",
    "gn:population":0,
    "gn:timezone":"Asia/Shanghai",
    "iso:country":"CN",
    "name:deu_x_preferred":[
        "Bacha"
    ],
    "name:fra_x_preferred":[
        "Bacha"
    ],
    "name:zho_x_preferred":[
        "\u5df4\u67e5"
    ],
    "wof:name":"Bacha",
    "wof:placetype":"locality"
},
  "geometry": {"coordinates":[107.146,23.9678],"type":"Point"}
}