{
  "type": "Feature",
  "properties": {
    "gn:admin1_code":"11.0",
    "gn:asciiname":"Fangjiawan",
    "gn:country_code":"CN",
    "gn:dem":535,
    "gn:feature_class":"P",
    "gn:feature_code":"PPL",
    "gn:name":"Fangjiawan",
    "gn:population":0,
    "gn:timezone":"Asia/Shanghai",
    "iso:country":"CN",
    "name:zho_x_preferred":[
        "\u65b9\u5bb6\u6e7e"
    ],
    "wof:name":"Fangjiawan",
    "wof:placetype":"locality"
},
  "geometry": {"coordinates":[110.94392000000001,29.72300000000001],"type":"Point"}
}