{
  "type": "Feature",
  "properties": {
    "gn:admin1_code":"29",
    "gn:asciiname":"Limeng",
    "gn:country_code":"CN",
    "gn:dem":1553,
    "gn:feature_class":"P",
    "gn:feature_code":"PPL",
    "gn:name":"Limeng",
    "gn:population":0,
    "gn:timezone":"Asia/Shanghai",
    "iso:country":"CN",
    "name:zho_x_preferred":[
        "\u91cc\u8499"
    ],
    "wof:name":"Limeng",
    "wof:placetype":"locality"
},
  "geometry": {"coordinates":[104.95699999999999,23.8239],"type":"Point"}
}