{
  "type": "Feature",
  "properties": {
    "gn:admin1_code":"18",
    "gn:asciiname":"Dahengbu",
    "gn:country_code":"CN",
    "gn:dem":1820,
    "gn:feature_class":"P",
    "gn:feature_code":"PPL",
    "gn:name":"Dahengbu",
    "gn:population":0,
    "gn:timezone":"Asia/Shanghai",
    "iso:country":"CN",
    "name:zho_x_preferred":[
        "\u5927\u4ea8\u5e03"
    ],
    "wof:name":"Dahengbu",
    "wof:placetype":"locality"
},
  "geometry": {"coordinates":[104.744,25.4645],"type":"Point"}
}