{
  "type": "Feature",
  "properties": {
    "gn:admin1_code":"15",
    "gn:asciiname":"Huocheng",
    "gn:country_code":"CN",
    "gn:dem":2391,
    "gn:feature_class":"P",
    "gn:feature_code":"PPLA4",
    "gn:name":"Huocheng",
    "gn:population":0,
    "gn:timezone":"Asia/Shanghai",
    "iso:country":"CN",
    "name:und_x_variant":[
        "Huocheng Zhen"
    ],
    "name:zho_x_preferred":[
        "\u970d\u57ce"
    ],
    "name:zho_x_variant":[
        "\u970d\u57ce\u9547"
    ],
    "wof:name":"Huocheng",
    "wof:placetype":"locality"
},
  "geometry": {"coordinates":[101.05486999999999,38.40318],"type":"Point"}
}