{
  "type": "Feature",
  "properties": {
    "gn:admin1_code":"11.0",
    "gn:asciiname":"Xiwuping",
    "gn:country_code":"CN",
    "gn:dem":572,
    "gn:feature_class":"P",
    "gn:feature_code":"PPL",
    "gn:name":"Xiwuping",
    "gn:population":0,
    "gn:timezone":"Asia/Shanghai",
    "iso:country":"CN",
    "name:zho_x_preferred":[
        "\u897f\u5434\u576a"
    ],
    "wof:name":"Xiwuping",
    "wof:placetype":"locality"
},
  "geometry": {"coordinates":[109.49455,29.04626],"type":"Point"}
}