{
  "type": "Feature",
  "properties": {
    "gn:admin1_code":"29.0",
    "gn:asciiname":"Dalinggang",
    "gn:country_code":"CN",
    "gn:dem":1533,
    "gn:feature_class":"P",
    "gn:feature_code":"PPL",
    "gn:name":"Dalinggang",
    "gn:population":0,
    "gn:timezone":"Asia/Shanghai",
    "iso:country":"CN",
    "name:zho_x_preferred":[
        "\u5927\u5cad\u5c97"
    ],
    "wof:name":"Dalinggang",
    "wof:placetype":"locality"
},
  "geometry": {"coordinates":[99.1311,24.5118],"type":"Point"}
}