{
  "type": "Feature",
  "properties": {
    "gn:admin1_code":"24.0",
    "gn:asciiname":"Dahuyuan",
    "gn:country_code":"CN",
    "gn:dem":816,
    "gn:feature_class":"P",
    "gn:feature_code":"PPL",
    "gn:name":"Dahuyuan",
    "gn:population":0,
    "gn:timezone":"Asia/Shanghai",
    "iso:country":"CN",
    "name:zho_x_preferred":[
        "\u5927\u6237\u57a3"
    ],
    "wof:name":"Dahuyuan",
    "wof:placetype":"locality"
},
  "geometry": {"coordinates":[111.87159,36.09149],"type":"Point"}
}