{
  "type": "Feature",
  "properties": {
    "gn:admin1_code":"18.0",
    "gn:asciiname":"Baisai",
    "gn:country_code":"CN",
    "gn:dem":438,
    "gn:feature_class":"P",
    "gn:feature_code":"PPL",
    "gn:name":"Baisai",
    "gn:population":0,
    "gn:timezone":"Asia/Shanghai",
    "iso:country":"CN",
    "name:zho_x_preferred":[
        "\u6446\u816e"
    ],
    "wof:name":"Baisai",
    "wof:placetype":"locality"
},
  "geometry": {"coordinates":[108.262,25.8235],"type":"Point"}
}