{
  "type": "Feature",
  "properties": {
    "gn:admin1_code":"19.0",
    "gn:asciiname":"Baolongcun",
    "gn:country_code":"CN",
    "gn:dem":116,
    "gn:feature_class":"P",
    "gn:feature_code":"PPL",
    "gn:name":"Baolongcun",
    "gn:population":0,
    "gn:timezone":"Asia/Shanghai",
    "iso:country":"CN",
    "name:zho_x_preferred":[
        "\u5b9d\u9f99\u6751"
    ],
    "wof:name":"Baolongcun",
    "wof:placetype":"locality"
},
  "geometry": {"coordinates":[123.81022,43.37599],"type":"Point"}
}