{
  "type": "Feature",
  "properties": {
    "gn:admin1_code":"26.0",
    "gn:asciiname":"Zhangpingcun",
    "gn:country_code":"CN",
    "gn:dem":675,
    "gn:feature_class":"P",
    "gn:feature_code":"PPL",
    "gn:name":"Zhangpingcun",
    "gn:population":0,
    "gn:timezone":"Asia/Shanghai",
    "iso:country":"CN",
    "name:und_x_variant":[
        "\u5f20\u576a\u6751"
    ],
    "wof:name":"Zhangpingcun",
    "wof:placetype":"locality"
},
  "geometry": {"coordinates":[107.33696,32.97932],"type":"Point"}
}