{
  "type": "Feature",
  "properties": {
    "gn:admin1_code":"19.0",
    "gn:asciiname":"Xiamacun",
    "gn:country_code":"CN",
    "gn:dem":207,
    "gn:feature_class":"P",
    "gn:feature_code":"PPL",
    "gn:name":"Xiamacun",
    "gn:population":0,
    "gn:timezone":"Asia/Shanghai",
    "iso:country":"CN",
    "name:zho_x_preferred":[
        "\u4e0b\u9a6c\u6751"
    ],
    "wof:name":"Xiamacun",
    "wof:placetype":"locality"
},
  "geometry": {"coordinates":[124.17700000000001,41.7178],"type":"Point"}
}