{
  "type": "Feature",
  "properties": {
    "gn:admin1_code":"3.0",
    "gn:asciiname":"Yujiacun",
    "gn:country_code":"CN",
    "gn:dem":38,
    "gn:feature_class":"P",
    "gn:feature_code":"PPL",
    "gn:name":"Yujiacun",
    "gn:population":0,
    "gn:timezone":"Asia/Shanghai",
    "iso:country":"CN",
    "name:und_x_variant":[
        "\u4f59\u5bb6\u6751"
    ],
    "wof:name":"Yujiacun",
    "wof:placetype":"locality"
},
  "geometry": {"coordinates":[116.93550999999999,28.99653],"type":"Point"}
}