{
  "type": "Feature",
  "properties": {
    "gn:admin1_code":"14.0",
    "gn:asciiname":"Dungzha",
    "gn:country_code":"CN",
    "gn:dem":4248,
    "gn:feature_class":"P",
    "gn:feature_code":"PPLF",
    "gn:name":"Dungzha",
    "gn:population":0,
    "gn:timezone":"Asia/Urumqi",
    "iso:country":"CN",
    "name:bod_x_preferred":[
        "Dungzha"
    ],
    "name:zho_x_preferred":[
        "Dongzha"
    ],
    "name:zho_x_variant":[
        "\u51ac\u624e"
    ],
    "wof:name":"Dungzha",
    "wof:placetype":"locality"
},
  "geometry": {"coordinates":[97.73324,30.54626],"type":"Point"}
}