{
  "type": "Feature",
  "properties": {
    "gn:admin1_code":"30.0",
    "gn:asciiname":"Tongyouping",
    "gn:country_code":"CN",
    "gn:dem":440,
    "gn:feature_class":"P",
    "gn:feature_code":"PPL",
    "gn:name":"Tongyouping",
    "gn:population":0,
    "gn:timezone":"Asia/Shanghai",
    "iso:country":"CN",
    "name:zho_x_preferred":[
        "\u6850\u6cb9\u576a"
    ],
    "wof:name":"Tongyouping",
    "wof:placetype":"locality"
},
  "geometry": {"coordinates":[112.02042,23.41512],"type":"Point"}
}