{
  "type": "Feature",
  "properties": {
    "gn:admin1_code":"15.0",
    "gn:asciiname":"Pingtaoli",
    "gn:country_code":"CN",
    "gn:dem":2047,
    "gn:feature_class":"P",
    "gn:feature_code":"PPL",
    "gn:name":"Pingtaoli",
    "gn:population":0,
    "gn:timezone":"Asia/Shanghai",
    "iso:country":"CN",
    "name:und_x_variant":[
        "\u5e73\u5957\u91cc"
    ],
    "wof:name":"Pingtaoli",
    "wof:placetype":"locality"
},
  "geometry": {"coordinates":[105.2313,33.5068],"type":"Point"}
}