{
  "type": "Feature",
  "properties": {
    "gn:admin1_code":"30.0",
    "gn:asciiname":"Qiangya",
    "gn:country_code":"CN",
    "gn:dem":5,
    "gn:feature_class":"P",
    "gn:feature_code":"PPL",
    "gn:name":"Qiangya",
    "gn:population":0,
    "gn:timezone":"Asia/Shanghai",
    "iso:country":"CN",
    "name:zho_x_preferred":[
        "\u5f37\u4e9e"
    ],
    "wof:name":"Qiangya",
    "wof:placetype":"locality"
},
  "geometry": {"coordinates":[112.57783000000001,22.37273],"type":"Point"}
}