{
  "type": "Feature",
  "properties": {
    "gn:admin1_code":"24.0",
    "gn:asciiname":"Beiyangbucun",
    "gn:country_code":"CN",
    "gn:dem":478,
    "gn:feature_class":"P",
    "gn:feature_code":"PPL",
    "gn:name":"Beiyangbucun",
    "gn:population":0,
    "gn:timezone":"Asia/Shanghai",
    "iso:country":"CN",
    "name:zho_x_preferred":[
        "\u5317\u9633\u5821\u6751"
    ],
    "wof:name":"Beiyangbucun",
    "wof:placetype":"locality"
},
  "geometry": {"coordinates":[110.78812000000001,35.5173],"type":"Point"}
}