{
  "type": "Feature",
  "properties": {
    "gn:admin1_code":"19.0",
    "gn:asciiname":"Xinshengcun",
    "gn:country_code":"CN",
    "gn:dem":83,
    "gn:feature_class":"P",
    "gn:feature_code":"PPL",
    "gn:name":"Xinshengcun",
    "gn:population":0,
    "gn:timezone":"Asia/Shanghai",
    "iso:country":"CN",
    "name:zho_x_preferred":[
        "\u65b0\u5347\u6751"
    ],
    "name:zho_x_variant":[
        "\u65b0\u751f\u6751"
    ],
    "wof:name":"Xinshengcun",
    "wof:placetype":"locality"
},
  "geometry": {"coordinates":[123.60680000000001,42.77192],"type":"Point"}
}