{
  "type": "Feature",
  "properties": {
    "gn:admin1_code":"32.0",
    "gn:asciiname":"Laifeng",
    "gn:country_code":"CN",
    "gn:dem":527,
    "gn:feature_class":"P",
    "gn:feature_code":"PPL",
    "gn:name":"Laifeng",
    "gn:population":0,
    "gn:timezone":"Asia/Shanghai",
    "iso:country":"CN",
    "name:zho_x_preferred":[
        "\u6765\u51e4"
    ],
    "wof:name":"Laifeng",
    "wof:placetype":"locality"
},
  "geometry": {"coordinates":[107.282,31.5139],"type":"Point"}
}