{
  "type": "Feature",
  "properties": {
    "gn:admin1_code":"30",
    "gn:asciiname":"Fu'anguo",
    "gn:country_code":"CN",
    "gn:dem":51,
    "gn:feature_class":"P",
    "gn:feature_code":"PPL",
    "gn:name":"Fu\u2019anguo",
    "gn:population":0,
    "gn:timezone":"Asia/Urumqi",
    "iso:country":"CN",
    "name:zho_x_preferred":[
        "\u798f\u5b89\u57da"
    ],
    "name:zho_x_variant":[
        "Fu\u2019anguo"
    ],
    "wof:name":"Fu'anguo",
    "wof:placetype":"locality"
},
  "geometry": {"coordinates":[110.28635,20.31664],"type":"Point"}
}