{
  "type": "Feature",
  "properties": {
    "gn:admin1_code":"19",
    "gn:asciiname":"Pa-pan-chieh",
    "gn:country_code":"CN",
    "gn:dem":431,
    "gn:feature_class":"P",
    "gn:feature_code":"PPL",
    "gn:name":"Pa-pan-chieh",
    "gn:population":0,
    "gn:timezone":"Asia/Shanghai",
    "iso:country":"CN",
    "wof:name":"Pa-pan-chieh",
    "wof:placetype":"locality"
},
  "geometry": {"coordinates":[125.09111,41.81722],"type":"Point"}
}