{
  "type": "Feature",
  "properties": {
    "gn:admin1_code":"24.0",
    "gn:asciiname":"Dongluo",
    "gn:country_code":"CN",
    "gn:dem":955,
    "gn:feature_class":"P",
    "gn:feature_code":"PPL",
    "gn:name":"Dongluo",
    "gn:population":0,
    "gn:timezone":"Asia/Shanghai",
    "iso:country":"CN",
    "name:fas_x_preferred":[
        "\u062f\u0648\u0646\u06af\u0644\u0648"
    ],
    "name:zha_x_preferred":[
        "Dunghloz"
    ],
    "name:zho_x_preferred":[
        "\u4e1c\u903b"
    ],
    "name:zho_x_variant":[
        "\u4e1c\u7f57\u9547"
    ],
    "wof:name":"Dongluo",
    "wof:placetype":"locality"
},
  "geometry": {"coordinates":[111.53612,36.96877],"type":"Point"}
}