{
  "type": "Feature",
  "properties": {
    "gn:admin1_code":"12.0",
    "gn:asciiname":"Huayuling",
    "gn:country_code":"CN",
    "gn:dem":1333,
    "gn:feature_class":"P",
    "gn:feature_code":"PPL",
    "gn:name":"Huayuling",
    "gn:population":0,
    "gn:timezone":"Asia/Shanghai",
    "iso:country":"CN",
    "name:zho_x_preferred":[
        "\u5316\u80b2\u5cad"
    ],
    "wof:name":"Huayuling",
    "wof:placetype":"locality"
},
  "geometry": {"coordinates":[110.69182000000001,30.3951],"type":"Point"}
}