{
  "type": "Feature",
  "properties": {
    "gn:admin1_code":"25",
    "gn:asciiname":"Huashishanzi",
    "gn:country_code":"CN",
    "gn:dem":164,
    "gn:feature_class":"P",
    "gn:feature_code":"PPL",
    "gn:name":"Huashishanzi",
    "gn:population":0,
    "gn:timezone":"Asia/Shanghai",
    "iso:country":"CN",
    "name:zho_x_preferred":[
        "\u534e\u77f3\u5c71\u5b50"
    ],
    "wof:name":"Huashishanzi",
    "wof:placetype":"locality"
},
  "geometry": {"coordinates":[118.214,35.5277],"type":"Point"}
}