{
  "type": "Feature",
  "properties": {
    "gn:admin1_code":"10",
    "gn:asciiname":"Shimen",
    "gn:cc2":"CN",
    "gn:country_code":"CN",
    "gn:dem":45,
    "gn:feature_class":"P",
    "gn:feature_code":"PPL",
    "gn:name":"Shimen",
    "gn:population":0,
    "gn:timezone":"Asia/Shanghai",
    "iso:country":"CN",
    "name:ceb_x_preferred":[
        "Shimen"
    ],
    "name:deu_x_preferred":[
        "Shimen"
    ],
    "name:nor_x_preferred":[
        "Shimen"
    ],
    "name:und_x_variant":[
        "Shih-men",
        "Shih-men-chen",
        "Shimen"
    ],
    "wof:name":"Shimen",
    "wof:placetype":"locality"
},
  "geometry": {"coordinates":[117.69444,40.11083],"type":"Point"}
}