{
  "type": "Feature",
  "properties": {
    "gn:admin1_code":"14.0",
    "gn:asciiname":"Rexucun",
    "gn:country_code":"CN",
    "gn:dem":4611,
    "gn:feature_class":"P",
    "gn:feature_code":"PPL",
    "gn:name":"Rexucun",
    "gn:population":0,
    "gn:timezone":"Asia/Urumqi",
    "iso:country":"CN",
    "name:zho_x_preferred":[
        "\u70ed\u987b\u6751"
    ],
    "wof:name":"Rexucun",
    "wof:placetype":"locality"
},
  "geometry": {"coordinates":[92.45937000000001,30.49887],"type":"Point"}
}