{
  "type": "Feature",
  "properties": {
    "gn:admin1_code":"7.0",
    "gn:asciiname":"Niulouping",
    "gn:country_code":"CN",
    "gn:dem":889,
    "gn:feature_class":"P",
    "gn:feature_code":"PPL",
    "gn:name":"Niulouping",
    "gn:population":0,
    "gn:timezone":"Asia/Shanghai",
    "iso:country":"CN",
    "name:zho_x_preferred":[
        "\u725b\u697c\u576a"
    ],
    "wof:name":"Niulouping",
    "wof:placetype":"locality"
},
  "geometry": {"coordinates":[119.17789,26.43616],"type":"Point"}
}