{
  "type": "Feature",
  "properties": {
    "gn:admin1_code":"24.0",
    "gn:asciiname":"Qianqinglian",
    "gn:country_code":"CN",
    "gn:dem":483,
    "gn:feature_class":"P",
    "gn:feature_code":"PPL",
    "gn:name":"Qianqinglian",
    "gn:population":0,
    "gn:timezone":"Asia/Shanghai",
    "iso:country":"CN",
    "name:zho_x_preferred":[
        "\u524d\u9752\u5ec9"
    ],
    "wof:name":"Qianqinglian",
    "wof:placetype":"locality"
},
  "geometry": {"coordinates":[111.70075,35.22205],"type":"Point"}
}