{
  "type": "Feature",
  "properties": {
    "gn:admin1_code":"19",
    "gn:asciiname":"Nao-pao-t'u",
    "gn:country_code":"CN",
    "gn:dem":681,
    "gn:feature_class":"P",
    "gn:feature_code":"PPL",
    "gn:name":"Nao-pao-t\u2019u",
    "gn:population":0,
    "gn:timezone":"Asia/Shanghai",
    "iso:country":"CN",
    "wof:name":"Nao-pao-t'u",
    "wof:placetype":"locality"
},
  "geometry": {"coordinates":[119.81056,42.14833],"type":"Point"}
}