{
  "type": "Feature",
  "properties": {
    "gn:admin1_code":"29.0",
    "gn:asciiname":"Yibasan",
    "gn:country_code":"CN",
    "gn:dem":1591,
    "gn:feature_class":"P",
    "gn:feature_code":"PPL",
    "gn:name":"Yibasan",
    "gn:population":0,
    "gn:timezone":"Asia/Shanghai",
    "iso:country":"CN",
    "name:zho_x_preferred":[
        "\u4e00\u628a\u4f1e"
    ],
    "wof:name":"Yibasan",
    "wof:placetype":"locality"
},
  "geometry": {"coordinates":[104.90900000000001,27.662],"type":"Point"}
}