{
  "type": "Feature",
  "properties": {
    "gn:admin1_code":"11",
    "gn:asciiname":"Luotangpai",
    "gn:country_code":"CN",
    "gn:dem":117,
    "gn:feature_class":"P",
    "gn:feature_code":"PPL",
    "gn:name":"Luotangpai",
    "gn:population":0,
    "gn:timezone":"Asia/Shanghai",
    "iso:country":"CN",
    "name:zho_x_preferred":[
        "\u7f57\u5802\u724c"
    ],
    "wof:name":"Luotangpai",
    "wof:placetype":"locality"
},
  "geometry": {"coordinates":[112.02083,27.42078],"type":"Point"}
}