{
  "type": "Feature",
  "properties": {
    "gn:admin1_code":"19.0",
    "gn:asciiname":"Xiaonianqi Gouli",
    "gn:country_code":"CN",
    "gn:dem":254,
    "gn:feature_class":"P",
    "gn:feature_code":"PPL",
    "gn:name":"Xiaonianqi Gouli",
    "gn:population":0,
    "gn:timezone":"Asia/Shanghai",
    "iso:country":"CN",
    "name:und_x_variant":[
        "\u5c0f\u78be\u8110\u6c9f\u91cc"
    ],
    "wof:name":"Xiaonianqi Gouli",
    "wof:placetype":"locality"
},
  "geometry": {"coordinates":[123.84649,40.73651],"type":"Point"}
}