{
  "type": "Feature",
  "properties": {
    "gn:admin1_code":"11.0",
    "gn:asciiname":"Wugongmiao",
    "gn:country_code":"CN",
    "gn:dem":70,
    "gn:feature_class":"P",
    "gn:feature_code":"PPL",
    "gn:name":"Wugongmiao",
    "gn:population":0,
    "gn:timezone":"Asia/Shanghai",
    "iso:country":"CN",
    "name:zho_x_preferred":[
        "\u8708\u86a3\u5e99"
    ],
    "wof:name":"Wugongmiao",
    "wof:placetype":"locality"
},
  "geometry": {"coordinates":[112.25662,28.57397000000001],"type":"Point"}
}