{
  "type": "Feature",
  "properties": {
    "gn:admin1_code":"12.0",
    "gn:asciiname":"Baiquan",
    "gn:country_code":"CN",
    "gn:dem":117,
    "gn:feature_class":"P",
    "gn:feature_code":"PPL",
    "gn:name":"Baiquan",
    "gn:population":0,
    "gn:timezone":"Asia/Shanghai",
    "iso:country":"CN",
    "name:ara_x_preferred":[
        "\u0628\u0627\u064a\u0643\u0648\u0627\u0646"
    ],
    "name:ben_x_preferred":[
        "\u09ac\u09be\u0987\u0995\u09c1\u09df\u09be\u09a8"
    ],
    "name:ell_x_preferred":[
        "\u039c\u03c0\u03b1\u03ca\u03ba\u03bf\u03c5\u03ac\u03bd"
    ],
    "name:heb_x_preferred":[
        "\u05d1\u05d0\u05d9\u05e0\u05d2\u05d5\u05d0\u05df"
    ],
    "name:hin_x_preferred":[
        "\u092c\u093e\u0907\u0915\u0941\u0906\u0928"
    ],
    "name:hun_x_preferred":[
        "Baiquan"
    ],
    "name:ind_x_preferred":[
        "Baiquan"
    ],
    "name:pol_x_preferred":[
        "Baiquan"
    ],
    "name:por_x_preferred":[
        "Baiquan"
    ],
    "name:spa_x_preferred":[
        "Baiquan"
    ],
    "name:tur_x_preferred":[
        "Baiquan"
    ],
    "name:ukr_x_preferred":[
        "\u0411\u0430\u0439\u0446\u044e\u0430\u043d\u044c"
    ],
    "name:zho_x_preferred":[
        "Baiquan"
    ],
    "name:zho_x_variant":[
        "\u767d\u6cc9"
    ],
    "wof:name":"Baiquan",
    "wof:placetype":"locality"
},
  "geometry": {"coordinates":[114.40025,29.69134],"type":"Point"}
}