{
  "type": "Feature",
  "properties": {
    "gn:admin1_code":"12.0",
    "gn:asciiname":"Baiquan",
    "gn:country_code":"CN",
    "gn:dem":117,
    "gn:feature_class":"P",
    "gn:feature_code":"PPL",
    "gn:name":"Baiquan",
    "gn:population":0,
    "gn:timezone":"Asia/Shanghai",
    "iso:country":"CN",
    "name:zho_x_preferred":[
        "Baiquan"
    ],
    "name:zho_x_variant":[
        "\u767d\u6cc9"
    ],
    "wof:name":"Baiquan",
    "wof:placetype":"locality"
},
  "geometry": {"coordinates":[114.40025,29.69134],"type":"Point"}
}