{
  "type": "Feature",
  "properties": {
    "gn:admin1_code":"22.0",
    "gn:asciiname":"Langxinzhuang",
    "gn:country_code":"CN",
    "gn:dem":32,
    "gn:feature_class":"P",
    "gn:feature_code":"PPL",
    "gn:name":"Langxinzhuang",
    "gn:population":0,
    "gn:timezone":"Asia/Shanghai",
    "iso:country":"CN",
    "name:zho_x_preferred":[
        "\u90ce\u8f9b\u5e84"
    ],
    "wof:name":"Langxinzhuang",
    "wof:placetype":"locality"
},
  "geometry": {"coordinates":[116.56921,39.85227],"type":"Point"}
}