{
  "type": "Feature",
  "properties": {
    "gn:admin1_code":"3.0",
    "gn:asciiname":"Yuxian",
    "gn:country_code":"CN",
    "gn:dem":323,
    "gn:feature_class":"P",
    "gn:feature_code":"PPL",
    "gn:name":"Yuxian",
    "gn:population":0,
    "gn:timezone":"Asia/Shanghai",
    "iso:country":"CN",
    "name:ceb_x_preferred":[
        "Yuxian"
    ],
    "name:und_x_variant":[
        "\u80b2\u8d24"
    ],
    "wof:name":"Yuxian",
    "wof:placetype":"locality"
},
  "geometry": {"coordinates":[115.37564,26.82893],"type":"Point"}
}