{
  "type": "Feature",
  "properties": {
    "gn:admin1_code":"4.0",
    "gn:asciiname":"Datuan",
    "gn:country_code":"CN",
    "gn:dem":1,
    "gn:feature_class":"P",
    "gn:feature_code":"PPL",
    "gn:name":"Datuan",
    "gn:population":0,
    "gn:timezone":"Asia/Shanghai",
    "iso:country":"CN",
    "name:zho_x_preferred":[
        "\u5927\u56e2"
    ],
    "name:zho_x_variant":[
        "\u5927\u7583\u9547"
    ],
    "wof:name":"Datuan",
    "wof:placetype":"locality"
},
  "geometry": {"coordinates":[120.04022000000001,33.50305],"type":"Point"}
}