{
  "type": "Feature",
  "properties": {
    "gn:admin1_code":"19.0",
    "gn:asciiname":"Bingjiaweizi",
    "gn:country_code":"CN",
    "gn:dem":133,
    "gn:feature_class":"P",
    "gn:feature_code":"PPL",
    "gn:name":"Bingjiaweizi",
    "gn:population":0,
    "gn:timezone":"Asia/Shanghai",
    "iso:country":"CN",
    "name:und_x_variant":[
        "\u90b4\u5bb6\u5d34\u5b50"
    ],
    "wof:name":"Bingjiaweizi",
    "wof:placetype":"locality"
},
  "geometry": {"coordinates":[124.34062,41.93856],"type":"Point"}
}