{
  "type": "Feature",
  "properties": {
    "gn:admin1_code":"11.0",
    "gn:asciiname":"Xifuyuan",
    "gn:country_code":"CN",
    "gn:dem":31,
    "gn:feature_class":"P",
    "gn:feature_code":"PPL",
    "gn:name":"Xifuyuan",
    "gn:population":0,
    "gn:timezone":"Asia/Shanghai",
    "iso:country":"CN",
    "name:zho_x_preferred":[
        "\u897f\u798f\u57b8"
    ],
    "wof:name":"Xifuyuan",
    "wof:placetype":"locality"
},
  "geometry": {"coordinates":[112.45962,29.27413],"type":"Point"}
}