{
  "type": "Feature",
  "properties": {
    "gn:admin1_code":"11",
    "gn:asciiname":"Qiaoziping",
    "gn:country_code":"CN",
    "gn:dem":194,
    "gn:feature_class":"P",
    "gn:feature_code":"PPL",
    "gn:name":"Qiaoziping",
    "gn:population":0,
    "gn:timezone":"Asia/Shanghai",
    "iso:country":"CN",
    "name:zho_x_preferred":[
        "\u6865\u6893\u576a"
    ],
    "wof:name":"Qiaoziping",
    "wof:placetype":"locality"
},
  "geometry": {"coordinates":[110.81674,28.68974],"type":"Point"}
}