{
  "type": "Feature",
  "properties": {
    "gn:admin1_code":"19.0",
    "gn:asciiname":"Dataicun",
    "gn:country_code":"CN",
    "gn:dem":73,
    "gn:feature_class":"P",
    "gn:feature_code":"PPL",
    "gn:name":"Dataicun",
    "gn:population":0,
    "gn:timezone":"Asia/Shanghai",
    "iso:country":"CN",
    "name:zho_x_preferred":[
        "\u5927\u53f0\u6751"
    ],
    "wof:name":"Dataicun",
    "wof:placetype":"locality"
},
  "geometry": {"coordinates":[123.57299999999999,42.3392],"type":"Point"}
}