{
  "type": "Feature",
  "properties": {
    "gn:admin1_code":"15.0",
    "gn:asciiname":"Lachaipo",
    "gn:country_code":"CN",
    "gn:dem":2447,
    "gn:feature_class":"P",
    "gn:feature_code":"PPL",
    "gn:name":"Lachaipo",
    "gn:population":0,
    "gn:timezone":"Asia/Shanghai",
    "iso:country":"CN",
    "name:und_x_variant":[
        "\u62c9\u67f4\u5761"
    ],
    "wof:name":"Lachaipo",
    "wof:placetype":"locality"
},
  "geometry": {"coordinates":[103.94908,34.66787],"type":"Point"}
}