{
  "type": "Feature",
  "properties": {
    "gn:admin1_code":"25.0",
    "gn:asciiname":"Xixujia",
    "gn:country_code":"CN",
    "gn:dem":33,
    "gn:feature_class":"P",
    "gn:feature_code":"PPL",
    "gn:name":"Xixujia",
    "gn:population":0,
    "gn:timezone":"Asia/Shanghai",
    "iso:country":"CN",
    "name:zho_x_preferred":[
        "\u897f\u5f90\u5bb6"
    ],
    "wof:name":"Xixujia",
    "wof:placetype":"locality"
},
  "geometry": {"coordinates":[122.25874,37.08215],"type":"Point"}
}