{
  "type": "Feature",
  "properties": {
    "gn:admin1_code":"21.0",
    "gn:asciiname":"Zhuxinzhuang",
    "gn:country_code":"CN",
    "gn:dem":1519,
    "gn:feature_class":"P",
    "gn:feature_code":"PPL",
    "gn:name":"Zhuxinzhuang",
    "gn:population":0,
    "gn:timezone":"Asia/Shanghai",
    "iso:country":"CN",
    "name:zho_x_preferred":[
        "\u6731\u65b0\u5e84"
    ],
    "wof:name":"Zhuxinzhuang",
    "wof:placetype":"locality"
},
  "geometry": {"coordinates":[106.913,37.483],"type":"Point"}
}