{
  "type": "Feature",
  "properties": {
    "gn:admin1_code":"1.0",
    "gn:asciiname":"He'ancun",
    "gn:country_code":"CN",
    "gn:dem":45,
    "gn:feature_class":"P",
    "gn:feature_code":"PPL",
    "gn:name":"He\u2019ancun",
    "gn:population":0,
    "gn:timezone":"Asia/Shanghai",
    "iso:country":"CN",
    "name:und_x_variant":[
        "He\u2019ancun"
    ],
    "name:zho_x_preferred":[
        "\u5408\u5b89\u6751"
    ],
    "wof:name":"He'ancun",
    "wof:placetype":"locality"
},
  "geometry": {"coordinates":[116.90973,31.0022],"type":"Point"}
}