{
  "type": "Feature",
  "properties": {
    "gn:admin1_code":"16",
    "gn:asciiname":"Shangyumiao",
    "gn:country_code":"CN",
    "gn:dem":916,
    "gn:feature_class":"P",
    "gn:feature_code":"PPL",
    "gn:name":"Shangyumiao",
    "gn:population":0,
    "gn:timezone":"Asia/Shanghai",
    "iso:country":"CN",
    "name:zho_x_preferred":[
        "\u4e0a\u5b87\u82d7"
    ],
    "wof:name":"Shangyumiao",
    "wof:placetype":"locality"
},
  "geometry": {"coordinates":[109.727,25.5827],"type":"Point"}
}