{
  "type": "Feature",
  "properties": {
    "gn:admin1_code":"32.0",
    "gn:asciiname":"Zonglong",
    "gn:country_code":"CN",
    "gn:dem":3827,
    "gn:feature_class":"P",
    "gn:feature_code":"PPL",
    "gn:name":"Zonglong",
    "gn:population":0,
    "gn:timezone":"Asia/Shanghai",
    "iso:country":"CN",
    "name:zho_x_preferred":[
        "\u5b97\u9647"
    ],
    "wof:name":"Zonglong",
    "wof:placetype":"locality"
},
  "geometry": {"coordinates":[97.68297,32.56151],"type":"Point"}
}