{
  "type": "Feature",
  "properties": {
    "gn:admin1_code":"14.0",
    "gn:asciiname":"Dikonglong",
    "gn:country_code":"CN",
    "gn:dem":4535,
    "gn:feature_class":"P",
    "gn:feature_code":"PPL",
    "gn:name":"Dikonglong",
    "gn:population":0,
    "gn:timezone":"Asia/Urumqi",
    "iso:country":"CN",
    "name:zho_x_preferred":[
        "\u654c\u7a7a\u9686"
    ],
    "wof:name":"Dikonglong",
    "wof:placetype":"locality"
},
  "geometry": {"coordinates":[94.54043,31.13751],"type":"Point"}
}