{
  "type": "Feature",
  "properties": {
    "gn:admin1_code":"13",
    "gn:asciiname":"Muziluke",
    "gn:country_code":"CN",
    "gn:dem":1036,
    "gn:feature_class":"P",
    "gn:feature_code":"PPL",
    "gn:name":"Muziluke",
    "gn:population":0,
    "gn:timezone":"Asia/Shanghai",
    "iso:country":"CN",
    "name:und_x_variant":[
        "\u6728\u5b5c\u9c81\u514b"
    ],
    "wof:name":"Muziluke",
    "wof:placetype":"locality"
},
  "geometry": {"coordinates":[80.51914000000002,40.42789000000001],"type":"Point"}
}