{
  "type": "Feature",
  "properties": {
    "gn:admin1_code":"29.0",
    "gn:asciiname":"Ganpingzi",
    "gn:country_code":"CN",
    "gn:dem":1456,
    "gn:feature_class":"P",
    "gn:feature_code":"PPL",
    "gn:name":"Ganpingzi",
    "gn:population":0,
    "gn:timezone":"Asia/Shanghai",
    "iso:country":"CN",
    "name:zho_x_preferred":[
        "\u5e72\u576a\u5b50"
    ],
    "wof:name":"Ganpingzi",
    "wof:placetype":"locality"
},
  "geometry": {"coordinates":[103.16,26.3556],"type":"Point"}
}