{
  "type": "Feature",
  "properties": {
    "gn:admin1_code":"16.0",
    "gn:asciiname":"Linlang",
    "gn:country_code":"CN",
    "gn:dem":131,
    "gn:feature_class":"P",
    "gn:feature_code":"PPL",
    "gn:name":"Linlang",
    "gn:population":0,
    "gn:timezone":"Asia/Shanghai",
    "iso:country":"CN",
    "name:tgl_x_preferred":[
        "Linlang"
    ],
    "name:zho_x_preferred":[
        "\u7433\u746f"
    ],
    "wof:name":"Linlang",
    "wof:placetype":"locality"
},
  "geometry": {"coordinates":[108.384,24.1294],"type":"Point"}
}