{
  "type": "Feature",
  "properties": {
    "gn:admin1_code":"5.0",
    "gn:asciiname":"Liezicun",
    "gn:country_code":"CN",
    "gn:dem":135,
    "gn:feature_class":"P",
    "gn:feature_code":"PPL",
    "gn:name":"Liezicun",
    "gn:population":0,
    "gn:timezone":"Asia/Shanghai",
    "iso:country":"CN",
    "name:zho_x_preferred":[
        "\u5217\u5b57\u6751"
    ],
    "wof:name":"Liezicun",
    "wof:placetype":"locality"
},
  "geometry": {"coordinates":[124.12143,45.19483],"type":"Point"}
}