{
  "type": "Feature",
  "properties": {
    "gn:admin1_code":"25",
    "gn:asciiname":"Guojianigou",
    "gn:country_code":"CN",
    "gn:dem":163,
    "gn:feature_class":"P",
    "gn:feature_code":"PPL",
    "gn:name":"Guojianigou",
    "gn:population":0,
    "gn:timezone":"Asia/Shanghai",
    "iso:country":"CN",
    "name:zho_x_preferred":[
        "\u90ed\u5bb6\u6ce5\u6c9f"
    ],
    "wof:name":"Guojianigou",
    "wof:placetype":"locality"
},
  "geometry": {"coordinates":[118.84,35.7761],"type":"Point"}
}