{
  "type": "Feature",
  "properties": {
    "gn:admin1_code":"4.0",
    "gn:asciiname":"Fuyuancun",
    "gn:country_code":"CN",
    "gn:dem":2,
    "gn:feature_class":"P",
    "gn:feature_code":"PPL",
    "gn:name":"Fuyuancun",
    "gn:population":0,
    "gn:timezone":"Asia/Shanghai",
    "iso:country":"CN",
    "name:zho_x_preferred":[
        "\u5bcc\u56ed\u6751"
    ],
    "wof:name":"Fuyuancun",
    "wof:placetype":"locality"
},
  "geometry": {"coordinates":[119.09473,34.7981],"type":"Point"}
}