{
  "type": "Feature",
  "properties": {
    "gn:admin1_code":"7.0",
    "gn:asciiname":"Dakeng",
    "gn:country_code":"CN",
    "gn:dem":450,
    "gn:feature_class":"P",
    "gn:feature_code":"PPL",
    "gn:name":"Dakeng",
    "gn:population":0,
    "gn:timezone":"Asia/Shanghai",
    "iso:country":"CN",
    "name:zho_x_preferred":[
        "\u5927\u5751"
    ],
    "wof:name":"Dakeng",
    "wof:placetype":"locality"
},
  "geometry": {"coordinates":[117.29318000000001,25.5816],"type":"Point"}
}