{
  "type": "Feature",
  "properties": {
    "gn:admin1_code":"9.0",
    "gn:asciiname":"Laoyazhang",
    "gn:country_code":"CN",
    "gn:dem":86,
    "gn:feature_class":"P",
    "gn:feature_code":"PPL",
    "gn:name":"Laoyazhang",
    "gn:population":0,
    "gn:timezone":"Asia/Shanghai",
    "iso:country":"CN",
    "name:zho_x_preferred":[
        "\u8001\u9e26\u5f20"
    ],
    "wof:name":"Laoyazhang",
    "wof:placetype":"locality"
},
  "geometry": {"coordinates":[114.27611,34.96202],"type":"Point"}
}