{
  "type": "Feature",
  "properties": {
    "gn:admin1_code":"6.0",
    "gn:asciiname":"Nixia",
    "gn:country_code":"CN",
    "gn:dem":4362,
    "gn:feature_class":"P",
    "gn:feature_code":"PPL",
    "gn:name":"Nixia",
    "gn:population":0,
    "gn:timezone":"Asia/Urumqi",
    "iso:country":"CN",
    "name:zho_x_preferred":[
        "\u5c3c\u4e0b"
    ],
    "wof:name":"Nixia",
    "wof:placetype":"locality"
},
  "geometry": {"coordinates":[97.15600999999999,32.93132],"type":"Point"}
}