{
  "type": "Feature",
  "properties": {
    "gn:admin1_code":"16.0",
    "gn:asciiname":"Maoshan",
    "gn:country_code":"CN",
    "gn:dem":298,
    "gn:feature_class":"P",
    "gn:feature_code":"PPL",
    "gn:name":"Maoshan",
    "gn:population":0,
    "gn:timezone":"Asia/Shanghai",
    "iso:country":"CN",
    "name:zho_x_preferred":[
        "\u5e3d\u5c71"
    ],
    "wof:name":"Maoshan",
    "wof:placetype":"locality"
},
  "geometry": {"coordinates":[108.79900000000001,23.7931],"type":"Point"}
}