{
  "type": "Feature",
  "properties": {
    "gn:admin1_code":"32.0",
    "gn:asciiname":"Yalabo",
    "gn:country_code":"CN",
    "gn:dem":3042,
    "gn:feature_class":"P",
    "gn:feature_code":"PPL",
    "gn:name":"Yalabo",
    "gn:population":0,
    "gn:timezone":"Asia/Shanghai",
    "iso:country":"CN",
    "name:zho_x_preferred":[
        "\u7259\u62c9\u4f2f"
    ],
    "wof:name":"Yalabo",
    "wof:placetype":"locality"
},
  "geometry": {"coordinates":[101.967,31.197],"type":"Point"}
}