{
  "type": "Feature",
  "properties": {
    "gn:admin1_code":"30",
    "gn:asciiname":"Yanlai",
    "gn:country_code":"CN",
    "gn:dem":68,
    "gn:feature_class":"P",
    "gn:feature_code":"PPL",
    "gn:name":"Yanlai",
    "gn:population":0,
    "gn:timezone":"Asia/Shanghai",
    "iso:country":"CN",
    "name:zho_x_preferred":[
        "\u96c1\u8d56"
    ],
    "wof:name":"Yanlai",
    "wof:placetype":"locality"
},
  "geometry": {"coordinates":[116.46155,24.48772],"type":"Point"}
}