{
  "type": "Feature",
  "properties": {
    "gn:admin1_code":"33.0",
    "gn:asciiname":"Zhilu",
    "gn:country_code":"CN",
    "gn:dem":723,
    "gn:feature_class":"P",
    "gn:feature_code":"PPL",
    "gn:name":"Zhilu",
    "gn:population":0,
    "gn:timezone":"Asia/Shanghai",
    "iso:country":"CN",
    "name:zho_x_preferred":[
        "\u6307\u8def"
    ],
    "wof:name":"Zhilu",
    "wof:placetype":"locality"
},
  "geometry": {"coordinates":[108.57583,31.97171],"type":"Point"}
}