{
  "type": "Feature",
  "properties": {
    "gn:admin1_code":"5.0",
    "gn:asciiname":"Bushitu",
    "gn:country_code":"CN",
    "gn:dem":137,
    "gn:feature_class":"P",
    "gn:feature_code":"PPL",
    "gn:name":"Bushitu",
    "gn:population":0,
    "gn:timezone":"Asia/Shanghai",
    "iso:country":"CN",
    "name:zho_x_preferred":[
        "\u5821\u77f3\u56fe"
    ],
    "wof:name":"Bushitu",
    "wof:placetype":"locality"
},
  "geometry": {"coordinates":[123.49476,43.87851],"type":"Point"}
}