{
  "type": "Feature",
  "properties": {
    "gn:admin1_code":"8.0",
    "gn:asciiname":"Xilecun",
    "gn:country_code":"CN",
    "gn:dem":115,
    "gn:feature_class":"P",
    "gn:feature_code":"PPL",
    "gn:name":"Xilecun",
    "gn:population":0,
    "gn:timezone":"Asia/Shanghai",
    "iso:country":"CN",
    "name:zho_x_preferred":[
        "\u897f\u4e50\u6751"
    ],
    "wof:name":"Xilecun",
    "wof:placetype":"locality"
},
  "geometry": {"coordinates":[128.22174999999999,45.97775],"type":"Point"}
}