{
  "type": "Feature",
  "properties": {
    "gn:admin1_code":"10",
    "gn:asciiname":"Xindongkeng",
    "gn:country_code":"CN",
    "gn:dem":1938,
    "gn:feature_class":"P",
    "gn:feature_code":"PPL",
    "gn:name":"Xindongkeng",
    "gn:population":0,
    "gn:timezone":"Asia/Shanghai",
    "iso:country":"CN",
    "wof:name":"Xindongkeng",
    "wof:placetype":"locality"
},
  "geometry": {"coordinates":[115.51611,40.93083],"type":"Point"}
}