{
  "type": "Feature",
  "properties": {
    "gn:admin1_code":"24.0",
    "gn:asciiname":"Xidangzhuang",
    "gn:country_code":"CN",
    "gn:dem":866,
    "gn:feature_class":"P",
    "gn:feature_code":"PPL",
    "gn:name":"Xidangzhuang",
    "gn:population":0,
    "gn:timezone":"Asia/Shanghai",
    "iso:country":"CN",
    "name:zho_x_preferred":[
        "\u897f\u515a\u5e84"
    ],
    "wof:name":"Xidangzhuang",
    "wof:placetype":"locality"
},
  "geometry": {"coordinates":[113.00436999999999,35.60527000000001],"type":"Point"}
}