{
  "type": "Feature",
  "properties": {
    "gn:admin1_code":"18.0",
    "gn:asciiname":"Libazhai",
    "gn:country_code":"CN",
    "gn:dem":994,
    "gn:feature_class":"P",
    "gn:feature_code":"PPL",
    "gn:name":"Libazhai",
    "gn:population":0,
    "gn:timezone":"Asia/Shanghai",
    "iso:country":"CN",
    "name:zho_x_preferred":[
        "\u7bf1\u7b06\u5be8"
    ],
    "wof:name":"Libazhai",
    "wof:placetype":"locality"
},
  "geometry": {"coordinates":[107.807,26.8837],"type":"Point"}
}