{
  "type": "Feature",
  "properties": {
    "gn:admin1_code":"26.0",
    "gn:asciiname":"Xuetangping",
    "gn:country_code":"CN",
    "gn:dem":1112,
    "gn:feature_class":"P",
    "gn:feature_code":"PPL",
    "gn:name":"Xuetangping",
    "gn:population":0,
    "gn:timezone":"Asia/Shanghai",
    "iso:country":"CN",
    "name:und_x_variant":[
        "\u5b66\u5802\u576a"
    ],
    "wof:name":"Xuetangping",
    "wof:placetype":"locality"
},
  "geometry": {"coordinates":[106.89288000000001,33.7742],"type":"Point"}
}