{
  "type": "Feature",
  "properties": {
    "gn:admin1_code":"16.0",
    "gn:asciiname":"Fuji",
    "gn:country_code":"CN",
    "gn:dem":93,
    "gn:feature_class":"P",
    "gn:feature_code":"PPL",
    "gn:name":"Fuji",
    "gn:population":0,
    "gn:timezone":"Asia/Shanghai",
    "iso:country":"CN",
    "name:zho_x_preferred":[
        "\u6276\u6d4e"
    ],
    "wof:name":"Fuji",
    "wof:placetype":"locality"
},
  "geometry": {"coordinates":[108.985,23.6525],"type":"Point"}
}