{
  "type": "Feature",
  "properties": {
    "gn:admin1_code":"16.0",
    "gn:asciiname":"Fuji",
    "gn:country_code":"CN",
    "gn:dem":93,
    "gn:feature_class":"P",
    "gn:feature_code":"PPL",
    "gn:name":"Fuji",
    "gn:population":0,
    "gn:timezone":"Asia/Shanghai",
    "iso:country":"CN",
    "name:ben_x_preferred":[
        "\u09ab\u09c1\u099c\u09bf"
    ],
    "name:cat_x_preferred":[
        "Fuji"
    ],
    "name:ceb_x_preferred":[
        "Fuji"
    ],
    "name:ces_x_preferred":[
        "Fud\u017ei"
    ],
    "name:deu_x_preferred":[
        "Fuji"
    ],
    "name:fas_x_preferred":[
        "\u0641\u0648\u062c\u06cc"
    ],
    "name:fin_x_preferred":[
        "Fuji"
    ],
    "name:fra_x_preferred":[
        "Fuji"
    ],
    "name:glg_x_preferred":[
        "Fuji"
    ],
    "name:heb_x_preferred":[
        "\u05e4\u05d5\u05d2'\u05d9"
    ],
    "name:hun_x_preferred":[
        "Fuji"
    ],
    "name:ind_x_preferred":[
        "Fuji"
    ],
    "name:ita_x_preferred":[
        "Fuji"
    ],
    "name:lav_x_preferred":[
        "Fuji"
    ],
    "name:lit_x_preferred":[
        "Fud\u017eis"
    ],
    "name:mlg_x_preferred":[
        "Fuji"
    ],
    "name:nds_x_preferred":[
        "Fuji"
    ],
    "name:nld_x_preferred":[
        "Fuji"
    ],
    "name:nor_x_preferred":[
        "Fuji"
    ],
    "name:pol_x_preferred":[
        "Fuji"
    ],
    "name:por_x_preferred":[
        "Fuji"
    ],
    "name:ron_x_preferred":[
        "Fuji"
    ],
    "name:rus_x_preferred":[
        "\u0424\u0443\u0434\u0437\u0438"
    ],
    "name:slk_x_preferred":[
        "Fuji"
    ],
    "name:spa_x_preferred":[
        "Fuji"
    ],
    "name:srp_x_preferred":[
        "\u0424\u0443\u045f\u0438"
    ],
    "name:swe_x_preferred":[
        "Fuji"
    ],
    "name:tha_x_preferred":[
        "\u0e1f\u0e39\u0e08\u0e34"
    ],
    "name:ukr_x_preferred":[
        "\u0424\u0443\u0434\u0437\u0456"
    ],
    "name:urd_x_preferred":[
        "\u0641\u06cc\u0648\u062c\u06cc"
    ],
    "name:zho_x_preferred":[
        "\u6276\u6d4e"
    ],
    "wof:name":"Fuji",
    "wof:placetype":"locality"
},
  "geometry": {"coordinates":[108.985,23.6525],"type":"Point"}
}