{
  "type": "Feature",
  "properties": {
    "gn:admin1_code":"2.0",
    "gn:asciiname":"Shuimentang",
    "gn:country_code":"CN",
    "gn:dem":491,
    "gn:feature_class":"P",
    "gn:feature_code":"PPL",
    "gn:name":"Shuimentang",
    "gn:population":0,
    "gn:timezone":"Asia/Shanghai",
    "iso:country":"CN",
    "name:zho_x_preferred":[
        "\u6c34\u95e8\u5858"
    ],
    "wof:name":"Shuimentang",
    "wof:placetype":"locality"
},
  "geometry": {"coordinates":[121.18505,29.17771],"type":"Point"}
}