{
  "type": "Feature",
  "properties": {
    "gn:admin1_code":"7.0",
    "gn:asciiname":"Wujia",
    "gn:country_code":"CN",
    "gn:dem":576,
    "gn:feature_class":"P",
    "gn:feature_code":"PPL",
    "gn:name":"Wujia",
    "gn:population":0,
    "gn:timezone":"Asia/Shanghai",
    "iso:country":"CN",
    "name:und_x_variant":[
        "\u5434\u5bb6"
    ],
    "name:zho_x_preferred":[
        "\u5434\u5bb6"
    ],
    "wof:name":"Wujia",
    "wof:placetype":"locality"
},
  "geometry": {"coordinates":[116.57080999999999,26.60251],"type":"Point"}
}