{
  "type": "Feature",
  "properties": {
    "gn:admin1_code":"08",
    "gn:asciiname":"Fan-chia-ying-tzu",
    "gn:country_code":"CN",
    "gn:dem":152,
    "gn:feature_class":"P",
    "gn:feature_code":"PPL",
    "gn:name":"Fan-chia-ying-tzu",
    "gn:population":0,
    "gn:timezone":"Asia/Shanghai",
    "iso:country":"CN",
    "wof:name":"Fan-chia-ying-tzu",
    "wof:placetype":"locality"
},
  "geometry": {"coordinates":[124.60056000000002,47.27722],"type":"Point"}
}