{
  "type": "Feature",
  "properties": {
    "gn:admin1_code":"14.0",
    "gn:asciiname":"Yangduo",
    "gn:country_code":"CN",
    "gn:dem":4710,
    "gn:feature_class":"P",
    "gn:feature_code":"PPL",
    "gn:name":"Yangduo",
    "gn:population":0,
    "gn:timezone":"Asia/Urumqi",
    "iso:country":"CN",
    "name:zho_x_preferred":[
        "\u592e\u593a"
    ],
    "wof:name":"Yangduo",
    "wof:placetype":"locality"
},
  "geometry": {"coordinates":[93.75976,30.99021],"type":"Point"}
}