{
  "type": "Feature",
  "properties": {
    "gn:admin1_code":"01",
    "gn:asciiname":"Guangou",
    "gn:cc2":"CN",
    "gn:country_code":"CN",
    "gn:dem":53,
    "gn:feature_class":"P",
    "gn:feature_code":"PPL",
    "gn:name":"Guangou",
    "gn:population":0,
    "gn:timezone":"Asia/Shanghai",
    "iso:country":"CN",
    "name:und_x_variant":[
        "Kuan-kou",
        "Guangouji",
        "Kuan-kou-chi",
        "Guangou"
    ],
    "wof:name":"Guangou",
    "wof:placetype":"locality"
},
  "geometry": {"coordinates":[117.41667,32.81667],"type":"Point"}
}