{
  "type": "Feature",
  "properties": {
    "gn:admin1_code":"20.0",
    "gn:asciiname":"Gaojiadi",
    "gn:country_code":"CN",
    "gn:dem":1439,
    "gn:feature_class":"P",
    "gn:feature_code":"PPL",
    "gn:name":"Gaojiadi",
    "gn:population":0,
    "gn:timezone":"Asia/Shanghai",
    "iso:country":"CN",
    "name:und_x_variant":[
        "\u9ad8\u5bb6\u5730"
    ],
    "wof:name":"Gaojiadi",
    "wof:placetype":"locality"
},
  "geometry": {"coordinates":[113.1579,41.43379],"type":"Point"}
}