{
  "type": "Feature",
  "properties": {
    "gn:admin1_code":"4.0",
    "gn:asciiname":"Nianxi",
    "gn:country_code":"CN",
    "gn:dem":8,
    "gn:feature_class":"P",
    "gn:feature_code":"PPL",
    "gn:name":"Nianxi",
    "gn:population":0,
    "gn:timezone":"Asia/Shanghai",
    "iso:country":"CN",
    "name:zho_x_preferred":[
        "\u57dd\u897f"
    ],
    "wof:name":"Nianxi",
    "wof:placetype":"locality"
},
  "geometry": {"coordinates":[119.46745,31.34659000000001],"type":"Point"}
}