{
  "type": "Feature",
  "properties": {
    "gn:admin1_code":"1.0",
    "gn:asciiname":"Mabukoucun",
    "gn:country_code":"CN",
    "gn:dem":33,
    "gn:feature_class":"P",
    "gn:feature_code":"PPL",
    "gn:name":"Mabukoucun",
    "gn:population":0,
    "gn:timezone":"Asia/Shanghai",
    "iso:country":"CN",
    "name:zho_x_preferred":[
        "\u9a6c\u6b65\u53e3\u6751"
    ],
    "wof:name":"Mabukoucun",
    "wof:placetype":"locality"
},
  "geometry": {"coordinates":[116.0822,33.46834],"type":"Point"}
}