{
  "type": "Feature",
  "properties": {
    "gn:admin1_code":"5.0",
    "gn:asciiname":"Sipingcun",
    "gn:country_code":"CN",
    "gn:dem":723,
    "gn:feature_class":"P",
    "gn:feature_code":"PPL",
    "gn:name":"Sipingcun",
    "gn:population":0,
    "gn:timezone":"Asia/Shanghai",
    "iso:country":"CN",
    "name:zho_x_preferred":[
        "\u56db\u5e73\u6751"
    ],
    "wof:name":"Sipingcun",
    "wof:placetype":"locality"
},
  "geometry": {"coordinates":[126.88799,41.99918],"type":"Point"}
}