{
  "type": "Feature",
  "properties": {
    "gn:admin1_code":"9.0",
    "gn:asciiname":"Xiabiying",
    "gn:country_code":"CN",
    "gn:dem":120,
    "gn:feature_class":"P",
    "gn:feature_code":"PPL",
    "gn:name":"Xiabiying",
    "gn:population":0,
    "gn:timezone":"Asia/Shanghai",
    "iso:country":"CN",
    "name:zho_x_preferred":[
        "\u590f\u6bd5\u8425"
    ],
    "wof:name":"Xiabiying",
    "wof:placetype":"locality"
},
  "geometry": {"coordinates":[112.67321,32.88612],"type":"Point"}
}