{
  "type": "Feature",
  "properties": {
    "gn:admin1_code":"32.0",
    "gn:asciiname":"Qibu",
    "gn:country_code":"CN",
    "gn:dem":2872,
    "gn:feature_class":"P",
    "gn:feature_code":"PPL",
    "gn:name":"Qibu",
    "gn:population":0,
    "gn:timezone":"Asia/Shanghai",
    "iso:country":"CN",
    "name:zho_x_preferred":[
        "\u5947\u6b65"
    ],
    "wof:name":"Qibu",
    "wof:placetype":"locality"
},
  "geometry": {"coordinates":[102.02,30.7507],"type":"Point"}
}