{
  "type": "Feature",
  "properties": {
    "gn:admin1_code":"7.0",
    "gn:asciiname":"Shibi",
    "gn:country_code":"CN",
    "gn:dem":251,
    "gn:feature_class":"P",
    "gn:feature_code":"PPL",
    "gn:name":"Shibi",
    "gn:population":0,
    "gn:timezone":"Asia/Shanghai",
    "iso:country":"CN",
    "name:ceb_x_preferred":[
        "Shibi"
    ],
    "name:deu_x_preferred":[
        "Shibi"
    ],
    "name:swe_x_preferred":[
        "Shibi"
    ],
    "name:und_x_variant":[
        "\u77f3\u58c1"
    ],
    "name:zho_x_preferred":[
        "Shibi"
    ],
    "wof:name":"Shibi",
    "wof:placetype":"locality"
},
  "geometry": {"coordinates":[119.35398000000001,26.14958],"type":"Point"}
}