{
  "type": "Feature",
  "properties": {
    "gn:admin1_code":"6.0",
    "gn:asciiname":"Ma'erpo",
    "gn:country_code":"CN",
    "gn:dem":1879,
    "gn:feature_class":"P",
    "gn:feature_code":"PPL",
    "gn:name":"Ma\u2019erpo",
    "gn:population":0,
    "gn:timezone":"Asia/Shanghai",
    "iso:country":"CN",
    "name:und_x_variant":[
        "Ma\u2019erpo",
        "\u9a6c\u5c14\u5761"
    ],
    "wof:name":"Ma'erpo",
    "wof:placetype":"locality"
},
  "geometry": {"coordinates":[102.57114,35.83194],"type":"Point"}
}