{
  "type": "Feature",
  "properties": {
    "gn:admin1_code":"15.0",
    "gn:asciiname":"Shiyuanwan",
    "gn:country_code":"CN",
    "gn:dem":1693,
    "gn:feature_class":"P",
    "gn:feature_code":"PPL",
    "gn:name":"Shiyuanwan",
    "gn:population":0,
    "gn:timezone":"Asia/Shanghai",
    "iso:country":"CN",
    "name:und_x_variant":[
        "\u77f3\u586c\u6e7e"
    ],
    "wof:name":"Shiyuanwan",
    "wof:placetype":"locality"
},
  "geometry": {"coordinates":[105.86336,35.32412],"type":"Point"}
}