{
  "type": "Feature",
  "properties": {
    "gn:admin1_code":"12.0",
    "gn:asciiname":"Yangshandian",
    "gn:country_code":"CN",
    "gn:dem":247,
    "gn:feature_class":"P",
    "gn:feature_code":"PPL",
    "gn:name":"Yangshandian",
    "gn:population":0,
    "gn:timezone":"Asia/Shanghai",
    "iso:country":"CN",
    "name:zho_x_preferred":[
        "Yangshandian"
    ],
    "name:zho_x_variant":[
        "\u4ef0\u5c71\u6bbf"
    ],
    "wof:name":"Yangshandian",
    "wof:placetype":"locality"
},
  "geometry": {"coordinates":[114.15134999999999,29.36949000000001],"type":"Point"}
}