{
  "type": "Feature",
  "properties": {
    "gn:country":"CN",
    "gn:fcode":"ADM3",
    "gn:pop":0,
    "iso:country":"CN",
    "name:bod_x_preferred":[
        "\u0f66\u0fa3\u0f0b\u0f51\u0f40\u0f62\u0f0b\u0f62\u0fa9\u0f7a\u0f0b\u0f62\u0fab\u0f7c\u0f44"
    ],
    "name:bod_x_variant":[
        "Nanggarz\u00ea Xian",
        "Nanggarz\u00ea"
    ],
    "name:unk_x_variant":[
        "Lang-k\u2019a-tzu Hsien"
    ],
    "name:zho_x_preferred":[
        "\u6d6a\u5361\u5b50\u53bf"
    ],
    "name:zho_x_variant":[
        "Nagarz\u00ea Xian",
        "Langkazi",
        "\u6d6a\u5361\u5b50"
    ],
    "qs:name":"Langkazi Xian",
    "qs:photos_9r":0,
    "qs:photos_sr":0,
    "qs:pop_sr":"0",
    "wd:wordcount":75,
    "wof:name":"Langkazi Xian",
    "wof:placetype":"localadmin",
    "wof:population":0
},
  "geometry": {"coordinates":[90.74908000000001,28.72736],"type":"Point"}
}