{
  "type": "Feature",
  "properties": {
    "gn:country":"CN",
    "gn:fcode":"ADM3",
    "gn:pop":0,
    "iso:country":"CN",
    "name:bod_x_preferred":[
        "\u0f66\u0fa3\u0f0b\u0f51\u0f40\u0f62\u0f0b\u0f62\u0fa9\u0f7a\u0f0b\u0f62\u0fab\u0f7c\u0f44"
    ],
    "name:bod_x_variant":[
        "Nanggarz\u00ea Xian",
        "Nanggarz\u00ea",
        "\u0f66\u0fa3\u0f0b\u0f51\u0f40\u0f62\u0f0b\u0f62\u0fa9\u0f7a\u0f0b\u0f62\u0fab\u0f7c\u0f44\u0f0b\u0f0d"
    ],
    "name:ceb_x_preferred":[
        "Langkazi Xian"
    ],
    "name:deu_x_preferred":[
        "Nagarz\u00ea"
    ],
    "name:eng_x_preferred":[
        "Nagarz\u00ea County"
    ],
    "name:fas_x_preferred":[
        "\u0634\u0647\u0631\u0633\u062a\u0627\u0646 \u0646\u0627\u06af\u0627\u0631\u0632\u0647"
    ],
    "name:gan_x_preferred":[
        "\u6d6a\u5361\u5b50\u53bf"
    ],
    "name:hin_x_preferred":[
        "\u0928\u0917\u0930\u094d\u091c\u093c\u0947 \u092a\u094d\u0930\u0926\u0947\u0936"
    ],
    "name:jpn_x_preferred":[
        "\u30ca\u30f3\u30ab\u30eb\u30c4\u30a7\u770c"
    ],
    "name:kan_x_preferred":[
        "\u0ca8\u0c97\u0cb0\u0ccd\u0c9c\u0cbc\u0cc6"
    ],
    "name:kor_x_preferred":[
        "\ub791\uce74\ucbd4\ud604"
    ],
    "name:nan_x_preferred":[
        "Nagarz\u00ea-ko\u0101n"
    ],
    "name:nld_x_preferred":[
        "Nakartse"
    ],
    "name:pol_x_preferred":[
        "Nagarz\u00ea"
    ],
    "name:rus_x_preferred":[
        "\u041d\u0430\u0433\u0430\u0440\u0434\u0437\u0435"
    ],
    "name:swe_x_preferred":[
        "Nakartse"
    ],
    "name:unk_x_variant":[
        "Lang-k\u2019a-tzu Hsien"
    ],
    "name:vie_x_preferred":[
        "Nagarz\u00ea"
    ],
    "name:wuu_x_preferred":[
        "\u6d6a\u5361\u5b50\u53bf"
    ],
    "name:zho_x_preferred":[
        "\u6d6a\u5361\u5b50\u53bf"
    ],
    "name:zho_x_variant":[
        "Nagarz\u00ea Xian",
        "Langkazi",
        "\u6d6a\u5361\u5b50"
    ],
    "qs:name":"Langkazi Xian",
    "qs:photos_9r":0,
    "qs:photos_sr":0,
    "qs:pop_sr":"0",
    "wd:wordcount":75,
    "wof:name":"Langkazi Xian",
    "wof:placetype":"localadmin",
    "wof:population":0
},
  "geometry": {"coordinates":[90.74908000000001,28.72736],"type":"Point"}
}