{
  "type": "Feature",
  "properties": {
    "gn:admin1_code":"24.0",
    "gn:asciiname":"Nanhouzhuang",
    "gn:country_code":"CN",
    "gn:dem":1195,
    "gn:feature_class":"P",
    "gn:feature_code":"PPL",
    "gn:name":"Nanhouzhuang",
    "gn:population":0,
    "gn:timezone":"Asia/Shanghai",
    "iso:country":"CN",
    "name:zho_x_preferred":[
        "\u5357\u540e\u5e84"
    ],
    "wof:name":"Nanhouzhuang",
    "wof:placetype":"locality"
},
  "geometry": {"coordinates":[111.12560999999999,37.83796],"type":"Point"}
}