{
  "type": "Feature",
  "properties": {
    "gn:admin1_code":"10",
    "gn:asciiname":"Xiaogaomiao",
    "gn:country_code":"CN",
    "gn:dem":38,
    "gn:feature_class":"P",
    "gn:feature_code":"PPL",
    "gn:name":"Xiaogaomiao",
    "gn:population":0,
    "gn:timezone":"Asia/Shanghai",
    "iso:country":"CN",
    "name:und_x_variant":[
        "\u5c0f\u9ad8\u5e99"
    ],
    "wof:name":"Xiaogaomiao",
    "wof:placetype":"locality"
},
  "geometry": {"coordinates":[115.22992000000001,37.01013],"type":"Point"}
}