{
  "type": "Feature",
  "properties": {
    "gn:admin1_code":"11.0",
    "gn:asciiname":"Jiangcun",
    "gn:country_code":"CN",
    "gn:dem":383,
    "gn:feature_class":"P",
    "gn:feature_code":"PPL",
    "gn:name":"Jiangcun",
    "gn:population":0,
    "gn:timezone":"Asia/Shanghai",
    "iso:country":"CN",
    "name:zho_x_preferred":[
        "\u6d46\u6751"
    ],
    "wof:name":"Jiangcun",
    "wof:placetype":"locality"
},
  "geometry": {"coordinates":[113.84238000000001,26.33452],"type":"Point"}
}