{
  "type": "Feature",
  "properties": {
    "gn:admin1_code":"13.0",
    "gn:asciiname":"Toksun",
    "gn:country_code":"CN",
    "gn:dem":1217,
    "gn:feature_class":"P",
    "gn:feature_code":"PPL",
    "gn:name":"Toksun",
    "gn:population":0,
    "gn:timezone":"Asia/Shanghai",
    "iso:country":"CN",
    "name:uig_x_preferred":[
        "Tok\u0329sun"
    ],
    "name:uig_x_variant":[
        "Toqsun",
        "\u062a\u0648\u0642\u0633\u06c7\u0646",
        "\u0422\u043e\u049b\u0441\u0443\u043d"
    ],
    "wof:name":"Toksun",
    "wof:placetype":"locality"
},
  "geometry": {"coordinates":[82.07833000000002,41.74333],"type":"Point"}
}