{
  "type": "Feature",
  "properties": {
    "gn:admin1_code":"07",
    "gn:asciiname":"Xianforen",
    "gn:country_code":"CN",
    "gn:dem":515,
    "gn:feature_class":"P",
    "gn:feature_code":"PPL",
    "gn:name":"Xianforen",
    "gn:population":0,
    "gn:timezone":"Asia/Shanghai",
    "iso:country":"CN",
    "name:zho_x_preferred":[
        "\u4ed9\u4f5b\u4eba"
    ],
    "wof:name":"Xianforen",
    "wof:placetype":"locality"
},
  "geometry": {"coordinates":[118.34180000000001,25.28714],"type":"Point"}
}