{
  "type": "Feature",
  "properties": {
    "gn:admin1_code":"30",
    "gn:asciiname":"Gaojia",
    "gn:country_code":"CN",
    "gn:dem":30,
    "gn:feature_class":"P",
    "gn:feature_code":"PPL",
    "gn:name":"Gaojia",
    "gn:population":0,
    "gn:timezone":"Asia/Urumqi",
    "iso:country":"CN",
    "name:zho_x_preferred":[
        "\u9ad8\u5bb6"
    ],
    "wof:name":"Gaojia",
    "wof:placetype":"locality"
},
  "geometry": {"coordinates":[109.82612,20.88078],"type":"Point"}
}