{
  "type": "Feature",
  "properties": {
    "gn:admin1_code":"12.0",
    "gn:asciiname":"Bailashugou",
    "gn:country_code":"CN",
    "gn:dem":352,
    "gn:feature_class":"P",
    "gn:feature_code":"PPL",
    "gn:name":"Bailashugou",
    "gn:population":0,
    "gn:timezone":"Asia/Shanghai",
    "iso:country":"CN",
    "name:zho_x_preferred":[
        "\u767d\u814a\u6811\u6c9f"
    ],
    "wof:name":"Bailashugou",
    "wof:placetype":"locality"
},
  "geometry": {"coordinates":[110.91153,32.79752],"type":"Point"}
}