{
  "type": "Feature",
  "properties": {
    "gn:admin1_code":"18.0",
    "gn:asciiname":"Hunshuidong",
    "gn:country_code":"CN",
    "gn:dem":376,
    "gn:feature_class":"P",
    "gn:feature_code":"PPL",
    "gn:name":"Hunshuidong",
    "gn:population":0,
    "gn:timezone":"Asia/Shanghai",
    "iso:country":"CN",
    "name:zho_x_preferred":[
        "\u6d51\u6c34\u6d1e"
    ],
    "wof:name":"Hunshuidong",
    "wof:placetype":"locality"
},
  "geometry": {"coordinates":[108.929,27.9259],"type":"Point"}
}