{
  "type": "Feature",
  "properties": {
    "gn:admin1_code":"25",
    "gn:asciiname":"Xinzhuangzi",
    "gn:country_code":"CN",
    "gn:dem":7,
    "gn:feature_class":"P",
    "gn:feature_code":"PPL",
    "gn:name":"Xinzhuangzi",
    "gn:population":0,
    "gn:timezone":"Asia/Shanghai",
    "iso:country":"CN",
    "name:zho_x_preferred":[
        "\u8f9b\u5e84\u5b50"
    ],
    "wof:name":"Xinzhuangzi",
    "wof:placetype":"locality"
},
  "geometry": {"coordinates":[117.84999999999999,37.9551],"type":"Point"}
}