{
  "type": "Feature",
  "properties": {
    "gn:admin1_code":"7.0",
    "gn:asciiname":"Caikeng",
    "gn:country_code":"CN",
    "gn:dem":406,
    "gn:feature_class":"P",
    "gn:feature_code":"PPL",
    "gn:name":"Caikeng",
    "gn:population":0,
    "gn:timezone":"Asia/Shanghai",
    "iso:country":"CN",
    "name:und_x_variant":[
        "\u8521\u5751"
    ],
    "name:zho_x_preferred":[
        "\u8521\u5751"
    ],
    "wof:name":"Caikeng",
    "wof:placetype":"locality"
},
  "geometry": {"coordinates":[116.22192,25.72271],"type":"Point"}
}