{
  "type": "Feature",
  "properties": {
    "gn:admin1_code":"9.0",
    "gn:asciiname":"Zhonglicun",
    "gn:country_code":"CN",
    "gn:dem":67,
    "gn:feature_class":"P",
    "gn:feature_code":"PPL",
    "gn:name":"Zhonglicun",
    "gn:population":0,
    "gn:timezone":"Asia/Shanghai",
    "iso:country":"CN",
    "name:und_x_variant":[
        "\u4ef2\u674e\u6751"
    ],
    "name:zho_x_preferred":[
        "\u4ef2\u674e\u6751"
    ],
    "wof:name":"Zhonglicun",
    "wof:placetype":"locality"
},
  "geometry": {"coordinates":[113.90569000000001,33.65954],"type":"Point"}
}