{
  "type": "Feature",
  "properties": {
    "gn:admin1_code":"30",
    "gn:asciiname":"Donggangzhai",
    "gn:country_code":"CN",
    "gn:dem":17,
    "gn:feature_class":"P",
    "gn:feature_code":"PPL",
    "gn:name":"Donggangzhai",
    "gn:population":0,
    "gn:timezone":"Asia/Shanghai",
    "iso:country":"CN",
    "name:zho_x_preferred":[
        "\u4e1c\u5c97\u5be8"
    ],
    "wof:name":"Donggangzhai",
    "wof:placetype":"locality"
},
  "geometry": {"coordinates":[116.54756999999999,23.70456],"type":"Point"}
}