{
  "type": "Feature",
  "properties": {
    "gn:admin1_code":"8.0",
    "gn:asciiname":"Limincun",
    "gn:country_code":"CN",
    "gn:dem":174,
    "gn:feature_class":"P",
    "gn:feature_code":"PPL",
    "gn:name":"Limincun",
    "gn:population":0,
    "gn:timezone":"Asia/Shanghai",
    "iso:country":"CN",
    "name:zho_x_preferred":[
        "\u5229\u6c11\u6751"
    ],
    "wof:name":"Limincun",
    "wof:placetype":"locality"
},
  "geometry": {"coordinates":[127.16417,46.31304],"type":"Point"}
}