{
  "type": "Feature",
  "properties": {
    "gn:admin1_code":"19.0",
    "gn:asciiname":"Guankoucun",
    "gn:country_code":"CN",
    "gn:dem":207,
    "gn:feature_class":"P",
    "gn:feature_code":"PPL",
    "gn:name":"Guankoucun",
    "gn:population":0,
    "gn:timezone":"Asia/Shanghai",
    "iso:country":"CN",
    "name:zho_x_preferred":[
        "\u5173\u53e3\u6751"
    ],
    "wof:name":"Guankoucun",
    "wof:placetype":"locality"
},
  "geometry": {"coordinates":[124.02452,40.89417],"type":"Point"}
}