{
  "type": "Feature",
  "properties": {
    "gn:admin1_code":"15.0",
    "gn:asciiname":"Zoujiagou",
    "gn:country_code":"CN",
    "gn:dem":1261,
    "gn:feature_class":"P",
    "gn:feature_code":"PPL",
    "gn:name":"Zoujiagou",
    "gn:population":0,
    "gn:timezone":"Asia/Shanghai",
    "iso:country":"CN",
    "name:und_x_variant":[
        "\u90b9\u5bb6\u6c9f"
    ],
    "wof:name":"Zoujiagou",
    "wof:placetype":"locality"
},
  "geometry": {"coordinates":[107.84744000000001,36.4435],"type":"Point"}
}