{
  "type": "Feature",
  "properties": {
    "gn:admin1_code":"3.0",
    "gn:asciiname":"Diaoyuling",
    "gn:country_code":"CN",
    "gn:dem":280,
    "gn:feature_class":"P",
    "gn:feature_code":"PPL",
    "gn:name":"Diaoyuling",
    "gn:population":0,
    "gn:timezone":"Asia/Shanghai",
    "iso:country":"CN",
    "name:und_x_variant":[
        "\u9493\u9c7c\u5cad"
    ],
    "wof:name":"Diaoyuling",
    "wof:placetype":"locality"
},
  "geometry": {"coordinates":[115.85894,25.53659],"type":"Point"}
}