{
  "type": "Feature",
  "properties": {
    "gn:admin1_code":"11",
    "gn:asciiname":"Yaolinwan",
    "gn:country_code":"CN",
    "gn:dem":1064,
    "gn:feature_class":"P",
    "gn:feature_code":"PPL",
    "gn:name":"Yaolinwan",
    "gn:population":0,
    "gn:timezone":"Asia/Shanghai",
    "iso:country":"CN",
    "name:zho_x_preferred":[
        "\u7476\u7433\u6e7e"
    ],
    "wof:name":"Yaolinwan",
    "wof:placetype":"locality"
},
  "geometry": {"coordinates":[111.80768999999999,25.1861],"type":"Point"}
}