{
  "type": "Feature",
  "properties": {
    "gn:admin1_code":"2.0",
    "gn:asciiname":"Choucheng",
    "gn:country_code":"CN",
    "gn:dem":72,
    "gn:feature_class":"P",
    "gn:feature_code":"PPL",
    "gn:name":"Choucheng",
    "gn:population":0,
    "gn:timezone":"Asia/Shanghai",
    "iso:country":"CN",
    "name:zho_x_preferred":[
        "\u7a20\u57ce"
    ],
    "wof:name":"Choucheng",
    "wof:placetype":"locality"
},
  "geometry": {"coordinates":[120.1054,29.34468],"type":"Point"}
}