{
  "type": "Feature",
  "properties": {
    "gn:admin1_code":"19.0",
    "gn:asciiname":"Jiahebei",
    "gn:country_code":"CN",
    "gn:dem":434,
    "gn:feature_class":"P",
    "gn:feature_code":"PPL",
    "gn:name":"Jiahebei",
    "gn:population":0,
    "gn:timezone":"Asia/Shanghai",
    "iso:country":"CN",
    "name:zho_x_preferred":[
        "\u5939\u6cb3\u5317"
    ],
    "wof:name":"Jiahebei",
    "wof:placetype":"locality"
},
  "geometry": {"coordinates":[125.28843999999999,41.73323],"type":"Point"}
}