{
  "type": "Feature",
  "properties": {
    "iso:country":"CN",
    "qs:name":"\u5d07\u660e\u53bf",
    "qs:name_adm0":"\u4e2d\u570b",
    "qs:name_adm1":"\u4e0a\u6d77\u76f4\u8f96\u5e02",
    "qs:photos":431,
    "qs:photos_1k":87,
    "qs:photos_9k":4,
    "qs:photos_9r":6,
    "qs:photos_all":796,
    "qs:photos_sr":6,
    "qs:placetype":"LocalAdmin",
    "qs:pop_sr":"0",
    "wd:wordcount":1416,
    "wof:name":"\u5d07\u660e\u53bf",
    "wof:placetype":"localadmin"
},
  "geometry": {"coordinates":[121.469993,31.628244],"type":"Point"}
}