{
  "type": "Feature",
  "properties": {
    "iso:country":"CN",
    "name:ceb_x_preferred":[
        "Chongming Xian"
    ],
    "name:ces_x_preferred":[
        "\u010cchung-ming"
    ],
    "name:cym_x_preferred":[
        "Ardal Chongming"
    ],
    "name:dan_x_preferred":[
        "Chongming"
    ],
    "name:deu_x_preferred":[
        "Chongming"
    ],
    "name:eng_x_preferred":[
        "Chongming District"
    ],
    "name:eus_x_preferred":[
        "Chongming Konderria"
    ],
    "name:fas_x_preferred":[
        "\u0646\u0627\u062d\u06cc\u0647 \u0686\u0648\u0646\u06af\u0645\u06cc\u0646\u06af"
    ],
    "name:fra_x_preferred":[
        "Chongming"
    ],
    "name:gan_x_preferred":[
        "\u5d07\u660e\u533a"
    ],
    "name:heb_x_preferred":[
        "\u05e9\u05d0\u05e0\u05d2\u05d7\u05d0\u05d9/\u05de\u05d7\u05d5\u05d6 \u05e6'\u05d5\u05e0\u05d2\u05de\u05d9\u05e0\u05d2"
    ],
    "name:jpn_x_preferred":[
        "\u5d07\u660e\u533a"
    ],
    "name:kor_x_preferred":[
        "\ucda9\ubc0d\uad6c"
    ],
    "name:lzh_x_preferred":[
        "\u5d07\u660e\u5340"
    ],
    "name:nan_x_preferred":[
        "Ch\u00f4ng-b\u00eang-khu"
    ],
    "name:nld_x_preferred":[
        "Chongming"
    ],
    "name:nob_x_preferred":[
        "Chongming"
    ],
    "name:pol_x_preferred":[
        "Chongming"
    ],
    "name:por_x_preferred":[
        "Chongming"
    ],
    "name:rus_x_preferred":[
        "\u0427\u0443\u043d\u043c\u0438\u043d"
    ],
    "name:swe_x_preferred":[
        "Chongming"
    ],
    "name:tur_x_preferred":[
        "Chongming"
    ],
    "name:ukr_x_preferred":[
        "\u0427\u0443\u043d\u043c\u0456\u043d"
    ],
    "name:vie_x_preferred":[
        "S\u00f9ng Minh"
    ],
    "name:wuu_x_preferred":[
        "\u5d07\u660e\u53bf"
    ],
    "name:yue_x_preferred":[
        "\u5d07\u660e\u7e23"
    ],
    "name:zho_x_preferred":[
        "\u5d07\u660e\u533a"
    ],
    "qs:name":"\u5d07\u660e\u53bf",
    "qs:name_adm0":"\u4e2d\u570b",
    "qs:name_adm1":"\u4e0a\u6d77\u76f4\u8f96\u5e02",
    "qs:photos":431,
    "qs:photos_1k":87,
    "qs:photos_9k":4,
    "qs:photos_9r":6,
    "qs:photos_all":796,
    "qs:photos_sr":6,
    "qs:placetype":"LocalAdmin",
    "qs:pop_sr":"0",
    "wd:wordcount":1416,
    "wof:name":"\u5d07\u660e\u53bf",
    "wof:placetype":"localadmin"
},
  "geometry": {"coordinates":[121.469993,31.628244],"type":"Point"}
}