{
  "type": "Feature",
  "properties": {
    "gn:admin1_code":"4.0",
    "gn:asciiname":"Xishiqiao",
    "gn:country_code":"CN",
    "gn:dem":28,
    "gn:feature_class":"P",
    "gn:feature_code":"PPL",
    "gn:name":"Xishiqiao",
    "gn:population":0,
    "gn:timezone":"Asia/Shanghai",
    "iso:country":"CN",
    "name:zho_x_preferred":[
        "\u897f\u77f3\u6865"
    ],
    "wof:name":"Xishiqiao",
    "wof:placetype":"locality"
},
  "geometry": {"coordinates":[118.76728,32.99483],"type":"Point"}
}