{
  "type": "Feature",
  "properties": {
    "gn:admin1_code":"18.0",
    "gn:asciiname":"Jiala",
    "gn:country_code":"CN",
    "gn:dem":1510,
    "gn:feature_class":"P",
    "gn:feature_code":"PPL",
    "gn:name":"Jiala",
    "gn:population":0,
    "gn:timezone":"Asia/Shanghai",
    "iso:country":"CN",
    "wof:name":"Jiala",
    "wof:placetype":"locality"
},
  "geometry": {"coordinates":[105.2375,25.20833],"type":"Point"}
}