{
  "type": "Feature",
  "properties": {
    "gn:admin1_code":"12.0",
    "gn:asciiname":"Sanguquan",
    "gn:country_code":"CN",
    "gn:dem":285,
    "gn:feature_class":"P",
    "gn:feature_code":"PPL",
    "gn:name":"Sanguquan",
    "gn:population":0,
    "gn:timezone":"Asia/Shanghai",
    "iso:country":"CN",
    "name:zho_x_preferred":[
        "\u4e09\u80a1\u6cc9"
    ],
    "wof:name":"Sanguquan",
    "wof:placetype":"locality"
},
  "geometry": {"coordinates":[111.94343000000001,31.44893],"type":"Point"}
}