{
  "type": "Feature",
  "properties": {
    "gn:admin1_code":"16.0",
    "gn:asciiname":"Dongpai",
    "gn:country_code":"CN",
    "gn:dem":611,
    "gn:feature_class":"P",
    "gn:feature_code":"PPL",
    "gn:name":"Dongpai",
    "gn:population":0,
    "gn:timezone":"Asia/Shanghai",
    "iso:country":"CN",
    "name:zho_x_preferred":[
        "\u5cd2\u724c"
    ],
    "wof:name":"Dongpai",
    "wof:placetype":"locality"
},
  "geometry": {"coordinates":[106.61499999999999,23.0048],"type":"Point"}
}