{
  "type": "Feature",
  "properties": {
    "gn:admin1_code":"10",
    "gn:asciiname":"Erzhangzi",
    "gn:country_code":"CN",
    "gn:dem":597,
    "gn:feature_class":"P",
    "gn:feature_code":"PPL",
    "gn:name":"Erzhangzi",
    "gn:population":0,
    "gn:timezone":"Asia/Shanghai",
    "iso:country":"CN",
    "name:zho_x_preferred":[
        "\u4e8c\u6756\u5b50"
    ],
    "wof:name":"Erzhangzi",
    "wof:placetype":"locality"
},
  "geometry": {"coordinates":[118.59576,41.03349],"type":"Point"}
}