{
  "type": "Feature",
  "properties": {
    "gn:admin1_code":"4.0",
    "gn:asciiname":"Qingxin",
    "gn:country_code":"CN",
    "gn:dem":28,
    "gn:feature_class":"P",
    "gn:feature_code":"PPL",
    "gn:name":"Qingxin",
    "gn:population":0,
    "gn:timezone":"Asia/Shanghai",
    "iso:country":"CN",
    "name:und_x_variant":[
        "\u9752\u65b0"
    ],
    "wof:name":"Qingxin",
    "wof:placetype":"locality"
},
  "geometry": {"coordinates":[118.79971999999999,34.67908],"type":"Point"}
}