{
  "type": "Feature",
  "properties": {
    "gn:admin1_code":"2.0",
    "gn:asciiname":"Zhangqiao",
    "gn:country_code":"CN",
    "gn:dem":646,
    "gn:feature_class":"P",
    "gn:feature_code":"PPL",
    "gn:name":"Zhangqiao",
    "gn:population":0,
    "gn:timezone":"Asia/Shanghai",
    "iso:country":"CN",
    "name:zho_x_preferred":[
        "\u7ae0\u6865"
    ],
    "wof:name":"Zhangqiao",
    "wof:placetype":"locality"
},
  "geometry": {"coordinates":[120.36374000000001,28.21531],"type":"Point"}
}