{
  "type": "Feature",
  "properties": {
    "gn:admin1_code":"10.0",
    "gn:asciiname":"Hanxinzhuangzi",
    "gn:country_code":"CN",
    "gn:dem":52,
    "gn:feature_class":"P",
    "gn:feature_code":"PPL",
    "gn:name":"Hanxinzhuangzi",
    "gn:population":0,
    "gn:timezone":"Asia/Shanghai",
    "iso:country":"CN",
    "name:zho_x_preferred":[
        "\u97e9\u65b0\u5e84\u5b50"
    ],
    "wof:name":"Hanxinzhuangzi",
    "wof:placetype":"locality"
},
  "geometry": {"coordinates":[118.41595,39.85224],"type":"Point"}
}