{
  "type": "Feature",
  "properties": {
    "gn:admin1_code":"19.0",
    "gn:asciiname":"Dajiazi",
    "gn:country_code":"CN",
    "gn:dem":7,
    "gn:feature_class":"P",
    "gn:feature_code":"PPL",
    "gn:name":"Dajiazi",
    "gn:population":0,
    "gn:timezone":"Asia/Shanghai",
    "iso:country":"CN",
    "name:zho_x_preferred":[
        "\u5927\u67b6\u5b50"
    ],
    "wof:name":"Dajiazi",
    "wof:placetype":"locality"
},
  "geometry": {"coordinates":[121.646,41.1087],"type":"Point"}
}