{
  "type": "Feature",
  "properties": {
    "gn:admin1_code":"30",
    "gn:asciiname":"Shangping",
    "gn:country_code":"CN",
    "gn:dem":238,
    "gn:feature_class":"P",
    "gn:feature_code":"PPLA4",
    "gn:name":"Shangping",
    "gn:population":0,
    "gn:timezone":"Asia/Shanghai",
    "iso:country":"CN",
    "name:und_x_variant":[
        "Shang-p\u2019ing-y\u00fc",
        "Shang-p\u2019ing-hs\u00fc",
        "Shangping",
        "\u4e0a\u576a",
        "Shangping Zhen",
        "\u4e0a\u576a\u9547"
    ],
    "wof:name":"Shangping",
    "wof:placetype":"locality"
},
  "geometry": {"coordinates":[115.44573,24.7031],"type":"Point"}
}