{
  "type": "Feature",
  "properties": {
    "gn:admin1_code":"32.0",
    "gn:asciiname":"Gonghe",
    "gn:country_code":"CN",
    "gn:dem":411,
    "gn:feature_class":"P",
    "gn:feature_code":"PPL",
    "gn:name":"Gonghe",
    "gn:population":0,
    "gn:timezone":"Asia/Shanghai",
    "iso:country":"CN",
    "name:ceb_x_preferred":[
        "Gonghe"
    ],
    "name:deu_x_preferred":[
        "Gonghe"
    ],
    "name:zho_x_preferred":[
        "\u5171\u548c"
    ],
    "wof:name":"Gonghe",
    "wof:placetype":"locality"
},
  "geometry": {"coordinates":[105.3653,29.95023],"type":"Point"}
}