{
  "type": "Feature",
  "properties": {
    "gn:admin1_code":"10",
    "gn:asciiname":"Qingliangcheng",
    "gn:country_code":"CN",
    "gn:dem":19,
    "gn:feature_class":"P",
    "gn:feature_code":"PPL",
    "gn:name":"Qingliangcheng",
    "gn:population":0,
    "gn:timezone":"Asia/Shanghai",
    "iso:country":"CN",
    "name:zho_x_preferred":[
        "\u6e05\u51c9\u57ce"
    ],
    "wof:name":"Qingliangcheng",
    "wof:placetype":"locality"
},
  "geometry": {"coordinates":[115.527,38.6879],"type":"Point"}
}