{
  "type": "Feature",
  "properties": {
    "gn:admin1_code":"19.0",
    "gn:asciiname":"Ximinzhu",
    "gn:country_code":"CN",
    "gn:dem":51,
    "gn:feature_class":"P",
    "gn:feature_code":"PPL",
    "gn:name":"Ximinzhu",
    "gn:population":0,
    "gn:timezone":"Asia/Shanghai",
    "iso:country":"CN",
    "name:und_x_variant":[
        "\u897f\u6c11\u4e3b"
    ],
    "name:zho_x_preferred":[
        "\u897f\u6c11\u4e3b"
    ],
    "wof:name":"Ximinzhu",
    "wof:placetype":"locality"
},
  "geometry": {"coordinates":[124.36624,40.29423],"type":"Point"}
}