{
  "type": "Feature",
  "properties": {
    "gn:admin1_code":"8.0",
    "gn:asciiname":"Miaoshan",
    "gn:country_code":"CN",
    "gn:dem":159,
    "gn:feature_class":"P",
    "gn:feature_code":"PPL",
    "gn:name":"Miaoshan",
    "gn:population":0,
    "gn:timezone":"Asia/Shanghai",
    "iso:country":"CN",
    "name:zho_x_preferred":[
        "\u5e99\u5c71"
    ],
    "wof:name":"Miaoshan",
    "wof:placetype":"locality"
},
  "geometry": {"coordinates":[131.49959999999999,45.39744],"type":"Point"}
}