{
  "type": "Feature",
  "properties": {
    "gn:admin1_code":"16.0",
    "gn:asciiname":"Xianteng",
    "gn:country_code":"CN",
    "gn:dem":141,
    "gn:feature_class":"P",
    "gn:feature_code":"PPL",
    "gn:name":"Xianteng",
    "gn:population":0,
    "gn:timezone":"Asia/Shanghai",
    "iso:country":"CN",
    "name:zho_x_preferred":[
        "\u663e\u6ed5"
    ],
    "wof:name":"Xianteng",
    "wof:placetype":"locality"
},
  "geometry": {"coordinates":[109.31399999999999,23.3381],"type":"Point"}
}