{
  "type": "Feature",
  "properties": {
    "gn:admin1_code":"33.0",
    "gn:asciiname":"Tongmuyan",
    "gn:country_code":"CN",
    "gn:dem":595,
    "gn:feature_class":"P",
    "gn:feature_code":"PPL",
    "gn:name":"Tongmuyan",
    "gn:population":0,
    "gn:timezone":"Asia/Shanghai",
    "iso:country":"CN",
    "name:zho_x_preferred":[
        "\u6850\u6728\u5ca9"
    ],
    "wof:name":"Tongmuyan",
    "wof:placetype":"locality"
},
  "geometry": {"coordinates":[108.06685,29.1514],"type":"Point"}
}