{
  "type": "Feature",
  "properties": {
    "gn:admin1_code":"24.0",
    "gn:asciiname":"Douzui",
    "gn:country_code":"CN",
    "gn:dem":1228,
    "gn:feature_class":"P",
    "gn:feature_code":"PPL",
    "gn:name":"Douzui",
    "gn:population":0,
    "gn:timezone":"Asia/Shanghai",
    "iso:country":"CN",
    "name:zho_x_preferred":[
        "\u9661\u5480"
    ],
    "wof:name":"Douzui",
    "wof:placetype":"locality"
},
  "geometry": {"coordinates":[111.51154,39.51563],"type":"Point"}
}