{
  "type": "Feature",
  "properties": {
    "gn:admin1_code":"5.0",
    "gn:asciiname":"Donglianjia",
    "gn:country_code":"CN",
    "gn:dem":160,
    "gn:feature_class":"P",
    "gn:feature_code":"PPL",
    "gn:name":"Donglianjia",
    "gn:population":0,
    "gn:timezone":"Asia/Shanghai",
    "iso:country":"CN",
    "name:zho_x_preferred":[
        "\u4e1c\u8fde\u5bb6"
    ],
    "wof:name":"Donglianjia",
    "wof:placetype":"locality"
},
  "geometry": {"coordinates":[125.5488,45.2652],"type":"Point"}
}