{
  "type": "Feature",
  "properties": {
    "gn:admin1_code":"32.0",
    "gn:asciiname":"Yaocun",
    "gn:country_code":"CN",
    "gn:dem":1813,
    "gn:feature_class":"P",
    "gn:feature_code":"PPL",
    "gn:name":"Yaocun",
    "gn:population":0,
    "gn:timezone":"Asia/Shanghai",
    "iso:country":"CN",
    "name:zho_x_preferred":[
        "\u7a91\u6751"
    ],
    "wof:name":"Yaocun",
    "wof:placetype":"locality"
},
  "geometry": {"coordinates":[102.5407,28.7694],"type":"Point"}
}