{
  "type": "Feature",
  "properties": {
    "gn:admin1_code":"14.0",
    "gn:asciiname":"Xoma",
    "gn:country_code":"CN",
    "gn:dem":4427,
    "gn:feature_class":"P",
    "gn:feature_code":"PPLF",
    "gn:name":"Xoma",
    "gn:population":0,
    "gn:timezone":"Asia/Urumqi",
    "iso:country":"CN",
    "name:bod_x_preferred":[
        "Xoma"
    ],
    "name:zho_x_preferred":[
        "Xuema"
    ],
    "name:zho_x_variant":[
        "\u5b66\u9a6c",
        "Bianba Qu",
        "\u8fb9\u5df4\u533a"
    ],
    "wof:name":"Xoma",
    "wof:placetype":"locality"
},
  "geometry": {"coordinates":[91.202,28.102],"type":"Point"}
}