{
  "type": "Feature",
  "properties": {
    "gn:admin1_code":"19.0",
    "gn:asciiname":"Gaoling Dixigou",
    "gn:country_code":"CN",
    "gn:dem":237,
    "gn:feature_class":"P",
    "gn:feature_code":"PPL",
    "gn:name":"Gaoling Dixigou",
    "gn:population":0,
    "gn:timezone":"Asia/Shanghai",
    "iso:country":"CN",
    "name:und_x_variant":[
        "\u9ad8\u5cad\u5730\u897f\u6c9f"
    ],
    "name:zho_x_preferred":[
        "\u9ad8\u5cad\u5730\u897f\u6c9f"
    ],
    "wof:name":"Gaoling Dixigou",
    "wof:placetype":"locality"
},
  "geometry": {"coordinates":[125.39054,40.98735],"type":"Point"}
}