{
  "type": "Feature",
  "properties": {
    "gn:admin1_code":"12.0",
    "gn:asciiname":"Gejiamiao",
    "gn:country_code":"CN",
    "gn:dem":82,
    "gn:feature_class":"P",
    "gn:feature_code":"PPL",
    "gn:name":"Gejiamiao",
    "gn:population":0,
    "gn:timezone":"Asia/Shanghai",
    "iso:country":"CN",
    "name:zho_x_preferred":[
        "Gejiamiao"
    ],
    "name:zho_x_variant":[
        "\u845b\u5bb6\u5e99"
    ],
    "wof:name":"Gejiamiao",
    "wof:placetype":"locality"
},
  "geometry": {"coordinates":[111.84480000000001,30.70558],"type":"Point"}
}