{
  "type": "Feature",
  "properties": {
    "gn:admin1_code":"29.0",
    "gn:asciiname":"Chizhang",
    "gn:country_code":"CN",
    "gn:dem":2017,
    "gn:feature_class":"P",
    "gn:feature_code":"PPL",
    "gn:name":"Chizhang",
    "gn:population":0,
    "gn:timezone":"Asia/Shanghai",
    "iso:country":"CN",
    "name:und_x_variant":[
        "\u8d64\u7ae0"
    ],
    "wof:name":"Chizhang",
    "wof:placetype":"locality"
},
  "geometry": {"coordinates":[103.69795000000001,25.79968],"type":"Point"}
}