{
  "type": "Feature",
  "properties": {
    "gn:admin1_code":"3.0",
    "gn:asciiname":"Xiagaokeng",
    "gn:country_code":"CN",
    "gn:dem":34,
    "gn:feature_class":"P",
    "gn:feature_code":"PPL",
    "gn:name":"Xiagaokeng",
    "gn:population":0,
    "gn:timezone":"Asia/Shanghai",
    "iso:country":"CN",
    "name:und_x_variant":[
        "\u4e0b\u9ad8\u5751"
    ],
    "wof:name":"Xiagaokeng",
    "wof:placetype":"locality"
},
  "geometry": {"coordinates":[116.34927999999999,28.61323],"type":"Point"}
}