{
  "type": "Feature",
  "properties": {
    "gn:admin1_code":"14.0",
    "gn:asciiname":"Dejiao",
    "gn:country_code":"CN",
    "gn:dem":4458,
    "gn:feature_class":"P",
    "gn:feature_code":"PPL",
    "gn:name":"Dejiao",
    "gn:population":0,
    "gn:timezone":"Asia/Shanghai",
    "iso:country":"CN",
    "name:zho_x_preferred":[
        "\u5fb7\u89d2"
    ],
    "wof:name":"Dejiao",
    "wof:placetype":"locality"
},
  "geometry": {"coordinates":[79.6657,33.2998],"type":"Point"}
}