{
  "type": "Feature",
  "properties": {
    "gn:admin1_code":"25",
    "gn:asciiname":"Dingtang",
    "gn:country_code":"CN",
    "gn:dem":41,
    "gn:feature_class":"P",
    "gn:feature_code":"PPL",
    "gn:name":"Dingtang",
    "gn:population":0,
    "gn:timezone":"Asia/Shanghai",
    "iso:country":"CN",
    "name:zho_x_preferred":[
        "\u4e01\u5802"
    ],
    "wof:name":"Dingtang",
    "wof:placetype":"locality"
},
  "geometry": {"coordinates":[116.139,35.7768],"type":"Point"}
}