{
  "type": "Feature",
  "properties": {
    "gn:admin1_code":"30.0",
    "gn:asciiname":"Maliuqiao",
    "gn:country_code":"CN",
    "gn:dem":362,
    "gn:feature_class":"P",
    "gn:feature_code":"PPL",
    "gn:name":"Maliuqiao",
    "gn:population":0,
    "gn:timezone":"Asia/Shanghai",
    "iso:country":"CN",
    "name:zho_x_preferred":[
        "\u9a6c\u7559\u6865"
    ],
    "wof:name":"Maliuqiao",
    "wof:placetype":"locality"
},
  "geometry": {"coordinates":[113.98135000000001,23.74716],"type":"Point"}
}