{
  "type": "Feature",
  "properties": {
    "gn:admin1_code":"20.0",
    "gn:asciiname":"Shuguang",
    "gn:country_code":"CN",
    "gn:dem":263,
    "gn:feature_class":"P",
    "gn:feature_code":"PPL",
    "gn:name":"Shuguang",
    "gn:population":0,
    "gn:timezone":"Asia/Shanghai",
    "iso:country":"CN",
    "name:zho_x_preferred":[
        "\u66d9\u5149"
    ],
    "wof:name":"Shuguang",
    "wof:placetype":"locality"
},
  "geometry": {"coordinates":[123.80712,48.3623],"type":"Point"}
}