{
  "type": "Feature",
  "properties": {
    "gn:admin1_code":"32.0",
    "gn:asciiname":"Erduola",
    "gn:country_code":"CN",
    "gn:dem":3820,
    "gn:feature_class":"P",
    "gn:feature_code":"PPL",
    "gn:name":"Erduola",
    "gn:population":0,
    "gn:timezone":"Asia/Shanghai",
    "iso:country":"CN",
    "name:zho_x_preferred":[
        "\u4e8c\u591a\u62c9"
    ],
    "wof:name":"Erduola",
    "wof:placetype":"locality"
},
  "geometry": {"coordinates":[101.13675000000001,31.86963],"type":"Point"}
}