{
  "type": "Feature",
  "properties": {
    "gn:admin1_code":"21.0",
    "gn:asciiname":"Shibeiwan",
    "gn:country_code":"CN",
    "gn:dem":1860,
    "gn:feature_class":"P",
    "gn:feature_code":"PPL",
    "gn:name":"Shibeiwan",
    "gn:population":0,
    "gn:timezone":"Asia/Shanghai",
    "iso:country":"CN",
    "name:zho_x_preferred":[
        "\u77f3\u7891\u6e7e"
    ],
    "wof:name":"Shibeiwan",
    "wof:placetype":"locality"
},
  "geometry": {"coordinates":[105.393,36.7425],"type":"Point"}
}