{
  "type": "Feature",
  "properties": {
    "gn:admin1_code":"10.0",
    "gn:asciiname":"Chenxinzhuang",
    "gn:country_code":"CN",
    "gn:dem":22,
    "gn:feature_class":"P",
    "gn:feature_code":"PPL",
    "gn:name":"Chenxinzhuang",
    "gn:population":0,
    "gn:timezone":"Asia/Shanghai",
    "iso:country":"CN",
    "name:zho_x_preferred":[
        "\u9648\u8f9b\u5e84"
    ],
    "wof:name":"Chenxinzhuang",
    "wof:placetype":"locality"
},
  "geometry": {"coordinates":[116.31914999999999,37.72234],"type":"Point"}
}