{
  "type": "Feature",
  "properties": {
    "gn:admin1_code":"4.0",
    "gn:asciiname":"Anding",
    "gn:country_code":"CN",
    "gn:dem":4,
    "gn:feature_class":"P",
    "gn:feature_code":"PPL",
    "gn:name":"Anding",
    "gn:population":0,
    "gn:timezone":"Asia/Shanghai",
    "iso:country":"CN",
    "name:ceb_x_preferred":[
        "Anding"
    ],
    "name:deu_x_preferred":[
        "Anding"
    ],
    "name:fra_x_preferred":[
        "Anding"
    ],
    "name:nor_x_preferred":[
        "Anding"
    ],
    "name:und_x_variant":[
        "\u5b89\u5b9a"
    ],
    "wof:name":"Anding",
    "wof:placetype":"locality"
},
  "geometry": {"coordinates":[121.09836,31.98502],"type":"Point"}
}