{
  "type": "Feature",
  "properties": {
    "gn:admin1_code":"18",
    "gn:asciiname":"Qiaxi",
    "gn:country_code":"CN",
    "gn:dem":1782,
    "gn:feature_class":"P",
    "gn:feature_code":"PPL",
    "gn:name":"Qiaxi",
    "gn:population":0,
    "gn:timezone":"Asia/Shanghai",
    "iso:country":"CN",
    "name:zho_x_preferred":[
        "\u6070\u897f"
    ],
    "wof:name":"Qiaxi",
    "wof:placetype":"locality"
},
  "geometry": {"coordinates":[103.798,26.6538],"type":"Point"}
}