{
  "type": "Feature",
  "properties": {
    "gn:admin1_code":"15.0",
    "gn:asciiname":"Dangjiashan",
    "gn:country_code":"CN",
    "gn:dem":2060,
    "gn:feature_class":"P",
    "gn:feature_code":"PPL",
    "gn:name":"Dangjiashan",
    "gn:population":0,
    "gn:timezone":"Asia/Shanghai",
    "iso:country":"CN",
    "name:und_x_variant":[
        "\u515a\u5bb6\u5c71"
    ],
    "wof:name":"Dangjiashan",
    "wof:placetype":"locality"
},
  "geometry": {"coordinates":[102.925,35.7991],"type":"Point"}
}