{
  "type": "Feature",
  "properties": {
    "gn:admin1_code":"10.0",
    "gn:asciiname":"Yuangu",
    "gn:cc2":"CN",
    "gn:country_code":"CN",
    "gn:dem":50,
    "gn:feature_class":"P",
    "gn:feature_code":"PPL",
    "gn:name":"Yuangu",
    "gn:population":0,
    "gn:timezone":"Asia/Shanghai",
    "iso:country":"CN",
    "name:und_x_variant":[
        "Tung-meng-ku",
        "Dongyuangu",
        "Yuangu"
    ],
    "wof:name":"Yuangu",
    "wof:placetype":"locality"
},
  "geometry": {"coordinates":[114.85389000000001,36.50444],"type":"Point"}
}