{
  "type": "Feature",
  "properties": {
    "gn:admin1_code":"29.0",
    "gn:asciiname":"Shejiao",
    "gn:country_code":"CN",
    "gn:dem":2732,
    "gn:feature_class":"P",
    "gn:feature_code":"PPL",
    "gn:name":"Shejiao",
    "gn:population":0,
    "gn:timezone":"Asia/Shanghai",
    "iso:country":"CN",
    "name:und_x_variant":[
        "\u8d4a\u89d2"
    ],
    "wof:name":"Shejiao",
    "wof:placetype":"locality"
},
  "geometry": {"coordinates":[102.5134,26.13255],"type":"Point"}
}