{
  "type": "Feature",
  "properties": {
    "gn:admin1_code":"8.0",
    "gn:asciiname":"Jiangdalitun",
    "gn:country_code":"CN",
    "gn:dem":316,
    "gn:feature_class":"P",
    "gn:feature_code":"PPL",
    "gn:name":"Jiangdalitun",
    "gn:population":0,
    "gn:timezone":"Asia/Shanghai",
    "iso:country":"CN",
    "name:zho_x_preferred":[
        "\u59dc\u5927\u7281\u5c6f"
    ],
    "wof:name":"Jiangdalitun",
    "wof:placetype":"locality"
},
  "geometry": {"coordinates":[125.67482,48.41515],"type":"Point"}
}