{
  "type": "Feature",
  "properties": {
    "gn:admin1_code":"29",
    "gn:asciiname":"Shangluojiao",
    "gn:country_code":"CN",
    "gn:dem":1185,
    "gn:feature_class":"P",
    "gn:feature_code":"PPL",
    "gn:name":"Shangluojiao",
    "gn:population":0,
    "gn:timezone":"Asia/Shanghai",
    "iso:country":"CN",
    "name:zho_x_preferred":[
        "\u4e0a\u843d\u89d2"
    ],
    "wof:name":"Shangluojiao",
    "wof:placetype":"locality"
},
  "geometry": {"coordinates":[104.59399999999999,24.4144],"type":"Point"}
}