{
  "type": "Feature",
  "properties": {
    "gn:admin1_code":"10",
    "gn:asciiname":"Dongjianchangou",
    "gn:country_code":"CN",
    "gn:dem":1295,
    "gn:feature_class":"P",
    "gn:feature_code":"PPL",
    "gn:name":"Dongjianchangou",
    "gn:population":0,
    "gn:timezone":"Asia/Shanghai",
    "iso:country":"CN",
    "name:zho_x_preferred":[
        "\u4e1c\u78b1\u4ea7\u6c9f"
    ],
    "wof:name":"Dongjianchangou",
    "wof:placetype":"locality"
},
  "geometry": {"coordinates":[116.55564,41.60185],"type":"Point"}
}