{
  "type": "Feature",
  "properties": {
    "gn:admin1_code":"11",
    "gn:asciiname":"Qihe",
    "gn:country_code":"CN",
    "gn:dem":61,
    "gn:feature_class":"P",
    "gn:feature_code":"PPLA4",
    "gn:name":"Qihe",
    "gn:population":0,
    "gn:timezone":"Asia/Shanghai",
    "iso:country":"CN",
    "name:und_x_variant":[
        "Ch\u2019i-chia-ho",
        "Qijiahe",
        "Qihe",
        "\u6f06\u6cb3",
        "Qihe Zhen",
        "\u6f06\u5bb6\u6cb3",
        "\u6f06\u6cb3\u9547"
    ],
    "wof:name":"Qihe",
    "wof:placetype":"locality"
},
  "geometry": {"coordinates":[111.37539,29.13278],"type":"Point"}
}