{
  "type": "Feature",
  "properties": {
    "gn:admin1_code":"16.0",
    "gn:asciiname":"Pingli",
    "gn:country_code":"CN",
    "gn:dem":454,
    "gn:feature_class":"P",
    "gn:feature_code":"PPL",
    "gn:name":"Pingli",
    "gn:population":0,
    "gn:timezone":"Asia/Shanghai",
    "iso:country":"CN",
    "name:zho_x_preferred":[
        "\u5e73\u91cc"
    ],
    "wof:name":"Pingli",
    "wof:placetype":"locality"
},
  "geometry": {"coordinates":[105.974,24.2101],"type":"Point"}
}