{
  "type": "Feature",
  "properties": {
    "gn:admin1_code":"2.0",
    "gn:asciiname":"Shijinggang",
    "gn:country_code":"CN",
    "gn:dem":7,
    "gn:feature_class":"P",
    "gn:feature_code":"PPL",
    "gn:name":"Shijinggang",
    "gn:population":0,
    "gn:timezone":"Asia/Shanghai",
    "iso:country":"CN",
    "name:und_x_variant":[
        "\u5e02\u6cfe\u6e2f"
    ],
    "wof:name":"Shijinggang",
    "wof:placetype":"locality"
},
  "geometry": {"coordinates":[120.72096000000001,30.93303],"type":"Point"}
}