{
  "type": "Feature",
  "properties": {
    "gn:admin1_code":"9.0",
    "gn:asciiname":"Huliuying",
    "gn:country_code":"CN",
    "gn:dem":159,
    "gn:feature_class":"P",
    "gn:feature_code":"PPL",
    "gn:name":"Huliuying",
    "gn:population":0,
    "gn:timezone":"Asia/Shanghai",
    "iso:country":"CN",
    "name:zho_x_preferred":[
        "\u80e1\u5218\u8425"
    ],
    "wof:name":"Huliuying",
    "wof:placetype":"locality"
},
  "geometry": {"coordinates":[111.91951,32.99659],"type":"Point"}
}