{
  "type": "Feature",
  "properties": {
    "gn:admin1_code":"26.0",
    "gn:asciiname":"Nianzigou",
    "gn:country_code":"CN",
    "gn:dem":1074,
    "gn:feature_class":"P",
    "gn:feature_code":"PPL",
    "gn:name":"Nianzigou",
    "gn:population":0,
    "gn:timezone":"Asia/Shanghai",
    "iso:country":"CN",
    "name:zho_x_preferred":[
        "\u78be\u5b50\u6c9f"
    ],
    "wof:name":"Nianzigou",
    "wof:placetype":"locality"
},
  "geometry": {"coordinates":[110.52786999999999,33.88343],"type":"Point"}
}