{
  "type": "Feature",
  "properties": {
    "gn:admin1_code":"19.0",
    "gn:asciiname":"Xiaoheishan",
    "gn:country_code":"CN",
    "gn:dem":205,
    "gn:feature_class":"P",
    "gn:feature_code":"PPL",
    "gn:name":"Xiaoheishan",
    "gn:population":0,
    "gn:timezone":"Asia/Shanghai",
    "iso:country":"CN",
    "name:und_x_variant":[
        "\u5c0f\u9ed1\u5c71"
    ],
    "wof:name":"Xiaoheishan",
    "wof:placetype":"locality"
},
  "geometry": {"coordinates":[123.94135,40.78818],"type":"Point"}
}