{
  "type": "Feature",
  "properties": {
    "gn:admin1_code":"19.0",
    "gn:asciiname":"Xiyuehe",
    "gn:country_code":"CN",
    "gn:dem":14,
    "gn:feature_class":"P",
    "gn:feature_code":"PPL",
    "gn:name":"Xiyuehe",
    "gn:population":0,
    "gn:timezone":"Asia/Shanghai",
    "iso:country":"CN",
    "name:und_x_variant":[
        "\u897f\u6708\u6cb3"
    ],
    "name:zho_x_preferred":[
        "\u897f\u6708\u6cb3"
    ],
    "wof:name":"Xiyuehe",
    "wof:placetype":"locality"
},
  "geometry": {"coordinates":[122.93755,41.35966],"type":"Point"}
}