{
  "type": "Feature",
  "properties": {
    "gn:admin1_code":"11",
    "gn:asciiname":"Ganzhuang",
    "gn:country_code":"CN",
    "gn:dem":221,
    "gn:feature_class":"P",
    "gn:feature_code":"PPL",
    "gn:name":"Ganzhuang",
    "gn:population":0,
    "gn:timezone":"Asia/Shanghai",
    "iso:country":"CN",
    "name:zho_x_preferred":[
        "\u7518\u5e84"
    ],
    "wof:name":"Ganzhuang",
    "wof:placetype":"locality"
},
  "geometry": {"coordinates":[111.86891,27.93227000000001],"type":"Point"}
}