{
  "type": "Feature",
  "properties": {
    "gn:admin1_code":"3.0",
    "gn:asciiname":"Luxia",
    "gn:country_code":"CN",
    "gn:dem":76,
    "gn:feature_class":"P",
    "gn:feature_code":"PPL",
    "gn:name":"Luxia",
    "gn:population":0,
    "gn:timezone":"Asia/Shanghai",
    "iso:country":"CN",
    "name:zho_x_preferred":[
        "\u8def\u4e0b"
    ],
    "wof:name":"Luxia",
    "wof:placetype":"locality"
},
  "geometry": {"coordinates":[115.02500000000001,28.4513],"type":"Point"}
}