{
  "type": "Feature",
  "properties": {
    "gn:admin1_code":"2.0",
    "gn:asciiname":"Cang'ao",
    "gn:country_code":"CN",
    "gn:dem":71,
    "gn:feature_class":"P",
    "gn:feature_code":"PPL",
    "gn:name":"Cang\u2019ao",
    "gn:population":0,
    "gn:timezone":"Asia/Shanghai",
    "iso:country":"CN",
    "name:und_x_variant":[
        "Cang\u2019ao"
    ],
    "name:zho_x_preferred":[
        "\u82cd\u5c99"
    ],
    "wof:name":"Cang'ao",
    "wof:placetype":"locality"
},
  "geometry": {"coordinates":[120.73784999999999,28.3783],"type":"Point"}
}