{
  "type": "Feature",
  "properties": {
    "gn:admin1_code":"11.0",
    "gn:asciiname":"Jianshangcun",
    "gn:country_code":"CN",
    "gn:dem":255,
    "gn:feature_class":"P",
    "gn:feature_code":"PPL",
    "gn:name":"Jianshangcun",
    "gn:population":0,
    "gn:timezone":"Asia/Shanghai",
    "iso:country":"CN",
    "name:zho_x_preferred":[
        "\u67a7\u4e0a\u6751"
    ],
    "wof:name":"Jianshangcun",
    "wof:placetype":"locality"
},
  "geometry": {"coordinates":[111.29944999999999,26.18303],"type":"Point"}
}