{
  "type": "Feature",
  "properties": {
    "gn:admin1_code":"18",
    "gn:asciiname":"Changmushu",
    "gn:country_code":"CN",
    "gn:dem":1850,
    "gn:feature_class":"P",
    "gn:feature_code":"PPL",
    "gn:name":"Changmushu",
    "gn:population":0,
    "gn:timezone":"Asia/Shanghai",
    "iso:country":"CN",
    "name:zho_x_preferred":[
        "\u957f\u6728\u6811"
    ],
    "wof:name":"Changmushu",
    "wof:placetype":"locality"
},
  "geometry": {"coordinates":[104.919,26.9924],"type":"Point"}
}