{
  "type": "Feature",
  "properties": {
    "gn:admin1_code":"16.0",
    "gn:asciiname":"Qiqi",
    "gn:country_code":"CN",
    "gn:dem":172,
    "gn:feature_class":"P",
    "gn:feature_code":"PPL",
    "gn:name":"Qiqi",
    "gn:population":0,
    "gn:timezone":"Asia/Shanghai",
    "iso:country":"CN",
    "name:zho_x_preferred":[
        "\u4e03\u9f50"
    ],
    "wof:name":"Qiqi",
    "wof:placetype":"locality"
},
  "geometry": {"coordinates":[108.21599999999999,22.3345],"type":"Point"}
}