{
  "type": "Feature",
  "properties": {
    "gn:admin1_code":"08",
    "gn:asciiname":"Xinsheng Elunchunzu",
    "gn:country_code":"CN",
    "gn:dem":304,
    "gn:feature_class":"P",
    "gn:feature_code":"PPLA4",
    "gn:name":"Xinsheng Elunchunzu",
    "gn:population":0,
    "gn:timezone":"Asia/Shanghai",
    "iso:country":"CN",
    "name:und_x_variant":[
        "Xinshengcun",
        "Xinsheng Elunchunzu Xiang",
        "Xinsheng Elunchunzu"
    ],
    "name:zho_x_preferred":[
        "\u65b0\u751f\u9102\u4f26\u6625\u65cf"
    ],
    "name:zho_x_variant":[
        "\u65b0\u751f\u9102\u4f26\u6625\u65cf\u4e61"
    ],
    "wof:name":"Xinsheng Elunchunzu",
    "wof:placetype":"locality"
},
  "geometry": {"coordinates":[126.79147,50.50993],"type":"Point"}
}