{
  "type": "Feature",
  "properties": {
    "gn:admin1_code":"29.0",
    "gn:asciiname":"Xiaopingba",
    "gn:country_code":"CN",
    "gn:dem":1767,
    "gn:feature_class":"P",
    "gn:feature_code":"PPLA4",
    "gn:name":"Xiaopingba",
    "gn:population":0,
    "gn:timezone":"Asia/Shanghai",
    "iso:country":"CN",
    "name:und_x_variant":[
        "\u5c0f\u5e73\u575d",
        "Chongde",
        "Chongde Xiang",
        "\u5d07\u5fb7",
        "\u5d07\u5fb7\u4e61"
    ],
    "wof:name":"Xiaopingba",
    "wof:placetype":"locality"
},
  "geometry": {"coordinates":[102.51226,25.49486],"type":"Point"}
}