{
  "type": "Feature",
  "properties": {
    "gn:admin1_code":"7",
    "gn:asciiname":"Jinshetou",
    "gn:country_code":"CN",
    "gn:dem":37,
    "gn:feature_class":"P",
    "gn:feature_code":"PPL",
    "gn:name":"Jinshetou",
    "gn:population":0,
    "gn:timezone":"Asia/Shanghai",
    "iso:country":"CN",
    "name:zho_x_preferred":[
        "\u91d1\u86c7\u5934"
    ],
    "wof:name":"Jinshetou",
    "wof:placetype":"locality"
},
  "geometry": {"coordinates":[119.57082,26.6461],"type":"Point"}
}