{
  "type": "Feature",
  "properties": {
    "gn:admin1_code":"19.0",
    "gn:asciiname":"Houliuhe",
    "gn:country_code":"CN",
    "gn:dem":30,
    "gn:feature_class":"P",
    "gn:feature_code":"PPL",
    "gn:name":"Houliuhe",
    "gn:population":0,
    "gn:timezone":"Asia/Shanghai",
    "iso:country":"CN",
    "name:und_x_variant":[
        "\u540e\u67f3\u6cb3"
    ],
    "wof:name":"Houliuhe",
    "wof:placetype":"locality"
},
  "geometry": {"coordinates":[122.79789,40.9479],"type":"Point"}
}