{
  "type": "Feature",
  "properties": {
    "gn:admin1_code":"18.0",
    "gn:asciiname":"Suntang",
    "gn:country_code":"CN",
    "gn:dem":1311,
    "gn:feature_class":"P",
    "gn:feature_code":"PPL",
    "gn:name":"Suntang",
    "gn:population":0,
    "gn:timezone":"Asia/Shanghai",
    "iso:country":"CN",
    "name:zho_x_preferred":[
        "\u7b0b\u5858"
    ],
    "wof:name":"Suntang",
    "wof:placetype":"locality"
},
  "geometry": {"coordinates":[107.396,26.3823],"type":"Point"}
}