{
  "type": "Feature",
  "properties": {
    "gn:admin1_code":"22.0",
    "gn:asciiname":"Shiyanjingcun",
    "gn:country_code":"CN",
    "gn:dem":373,
    "gn:feature_class":"P",
    "gn:feature_code":"PPL",
    "gn:name":"Shiyanjingcun",
    "gn:population":0,
    "gn:timezone":"Asia/Shanghai",
    "iso:country":"CN",
    "name:zho_x_preferred":[
        "\u77f3\u5ca9\u4e95\u6751"
    ],
    "wof:name":"Shiyanjingcun",
    "wof:placetype":"locality"
},
  "geometry": {"coordinates":[117.26142,40.5748],"type":"Point"}
}