{
  "type": "Feature",
  "properties": {
    "gn:admin1_code":"31.0",
    "gn:asciiname":"Dalie",
    "gn:country_code":"CN",
    "gn:dem":40,
    "gn:feature_class":"P",
    "gn:feature_code":"PPL",
    "gn:name":"Dalie",
    "gn:population":0,
    "gn:timezone":"Asia/Shanghai",
    "iso:country":"CN",
    "name:zho_x_preferred":[
        "\u5927\u57d2"
    ],
    "wof:name":"Dalie",
    "wof:placetype":"locality"
},
  "geometry": {"coordinates":[109.35169,19.68527000000001],"type":"Point"}
}