{
  "type": "Feature",
  "properties": {
    "gn:admin1_code":"9.0",
    "gn:asciiname":"Shangtanggou",
    "gn:country_code":"CN",
    "gn:dem":220,
    "gn:feature_class":"P",
    "gn:feature_code":"PPL",
    "gn:name":"Shangtanggou",
    "gn:population":0,
    "gn:timezone":"Asia/Shanghai",
    "iso:country":"CN",
    "name:zho_x_preferred":[
        "\u4e0a\u6c64\u6c9f"
    ],
    "wof:name":"Shangtanggou",
    "wof:placetype":"locality"
},
  "geometry": {"coordinates":[112.63123,34.97293],"type":"Point"}
}