{
  "type": "Feature",
  "properties": {
    "gn:admin1_code":"25",
    "gn:asciiname":"Qianxu",
    "gn:country_code":"CN",
    "gn:dem":38,
    "gn:feature_class":"P",
    "gn:feature_code":"PPL",
    "gn:name":"Qianxu",
    "gn:population":0,
    "gn:timezone":"Asia/Shanghai",
    "iso:country":"CN",
    "name:zho_x_preferred":[
        "\u524d\u5f90"
    ],
    "wof:name":"Qianxu",
    "wof:placetype":"locality"
},
  "geometry": {"coordinates":[120.08199999999999,37.2655],"type":"Point"}
}