{
  "type": "Feature",
  "properties": {
    "gn:admin1_code":"11.0",
    "gn:asciiname":"Daxijian",
    "gn:country_code":"CN",
    "gn:dem":114,
    "gn:feature_class":"P",
    "gn:feature_code":"PPL",
    "gn:name":"Daxijian",
    "gn:population":0,
    "gn:timezone":"Asia/Shanghai",
    "iso:country":"CN",
    "name:zho_x_preferred":[
        "\u5927\u897f\u95f4"
    ],
    "wof:name":"Daxijian",
    "wof:placetype":"locality"
},
  "geometry": {"coordinates":[111.46773,26.30052],"type":"Point"}
}