{
  "type": "Feature",
  "properties": {
    "gn:admin1_code":"12.0",
    "gn:asciiname":"Dapengjialing",
    "gn:country_code":"CN",
    "gn:dem":31,
    "gn:feature_class":"P",
    "gn:feature_code":"PPL",
    "gn:name":"Dapengjialing",
    "gn:population":0,
    "gn:timezone":"Asia/Shanghai",
    "iso:country":"CN",
    "name:zho_x_preferred":[
        "Dapengjialing"
    ],
    "name:zho_x_variant":[
        "\u5927\u5f6d\u5bb6\u5cad"
    ],
    "wof:name":"Dapengjialing",
    "wof:placetype":"locality"
},
  "geometry": {"coordinates":[112.66137000000001,30.51589],"type":"Point"}
}