{
  "type": "Feature",
  "properties": {
    "gn:admin1_code":"14.0",
    "gn:asciiname":"Dishabu",
    "gn:country_code":"CN",
    "gn:dem":4943,
    "gn:feature_class":"P",
    "gn:feature_code":"PPL",
    "gn:name":"Dishabu",
    "gn:population":0,
    "gn:timezone":"Asia/Urumqi",
    "iso:country":"CN",
    "name:zho_x_preferred":[
        "\u5730\u6c99\u5e03"
    ],
    "wof:name":"Dishabu",
    "wof:placetype":"locality"
},
  "geometry": {"coordinates":[86.876,30.3765],"type":"Point"}
}