{
  "type": "Feature",
  "properties": {
    "gn:admin1_code":"7",
    "gn:asciiname":"Dicunwei",
    "gn:country_code":"CN",
    "gn:dem":465,
    "gn:feature_class":"P",
    "gn:feature_code":"PPL",
    "gn:name":"Dicunwei",
    "gn:population":0,
    "gn:timezone":"Asia/Shanghai",
    "iso:country":"CN",
    "name:und_x_variant":[
        "Dicun",
        "Dicunwei"
    ],
    "name:zho_x_preferred":[
        "\u5730\u6751\u5c3e"
    ],
    "wof:name":"Dicunwei",
    "wof:placetype":"locality"
},
  "geometry": {"coordinates":[117.00946999999999,25.41145],"type":"Point"}
}