{
  "type": "Feature",
  "properties": {
    "gn:admin1_code":"32.0",
    "gn:asciiname":"Zhaya",
    "gn:country_code":"CN",
    "gn:dem":3809,
    "gn:feature_class":"P",
    "gn:feature_code":"PPL",
    "gn:name":"Zhaya",
    "gn:population":0,
    "gn:timezone":"Asia/Shanghai",
    "iso:country":"CN",
    "name:zho_x_preferred":[
        "\u624e\u4e9a"
    ],
    "wof:name":"Zhaya",
    "wof:placetype":"locality"
},
  "geometry": {"coordinates":[101.66342,30.20911],"type":"Point"}
}