{
  "type": "Feature",
  "properties": {
    "gn:admin1_code":"26.0",
    "gn:asciiname":"Wangjia Yuanzi",
    "gn:country_code":"CN",
    "gn:dem":518,
    "gn:feature_class":"P",
    "gn:feature_code":"PPL",
    "gn:name":"Wangjia Yuanzi",
    "gn:population":0,
    "gn:timezone":"Asia/Shanghai",
    "iso:country":"CN",
    "name:zho_x_preferred":[
        "\u738b\u5bb6\u9662\u5b50"
    ],
    "wof:name":"Wangjia Yuanzi",
    "wof:placetype":"locality"
},
  "geometry": {"coordinates":[109.2694,32.58075],"type":"Point"}
}