{
  "type": "Feature",
  "properties": {
    "gn:admin1_code":"24.0",
    "gn:asciiname":"Jingjianping",
    "gn:country_code":"CN",
    "gn:dem":1414,
    "gn:feature_class":"P",
    "gn:feature_code":"PPL",
    "gn:name":"Jingjianping",
    "gn:population":0,
    "gn:timezone":"Asia/Shanghai",
    "iso:country":"CN",
    "name:zho_x_preferred":[
        "\u83c1\u83c5\u576a"
    ],
    "wof:name":"Jingjianping",
    "wof:placetype":"locality"
},
  "geometry": {"coordinates":[111.96465000000001,38.13629],"type":"Point"}
}