{
  "type": "Feature",
  "properties": {
    "gn:admin1_code":"7",
    "gn:asciiname":"Qiaotouxi Famuchang",
    "gn:country_code":"CN",
    "gn:dem":544,
    "gn:feature_class":"P",
    "gn:feature_code":"PPL",
    "gn:name":"Qiaotouxi Famuchang",
    "gn:population":0,
    "gn:timezone":"Asia/Shanghai",
    "iso:country":"CN",
    "wof:name":"Qiaotouxi Famuchang",
    "wof:placetype":"locality"
},
  "geometry": {"coordinates":[117.51222,27.53222],"type":"Point"}
}