{
  "type": "Feature",
  "properties": {
    "gn:admin1_code":"1.0",
    "gn:asciiname":"Fenglingcun",
    "gn:country_code":"CN",
    "gn:dem":60,
    "gn:feature_class":"P",
    "gn:feature_code":"PPL",
    "gn:name":"Fenglingcun",
    "gn:population":0,
    "gn:timezone":"Asia/Shanghai",
    "iso:country":"CN",
    "name:zho_x_preferred":[
        "\u67ab\u5cad\u6751"
    ],
    "wof:name":"Fenglingcun",
    "wof:placetype":"locality"
},
  "geometry": {"coordinates":[116.80539,31.31099],"type":"Point"}
}