{
  "type": "Feature",
  "properties": {
    "gn:admin1_code":"13.0",
    "gn:asciiname":"Qimugan",
    "gn:country_code":"CN",
    "gn:dem":1743,
    "gn:feature_class":"P",
    "gn:feature_code":"PPL",
    "gn:name":"Qimugan",
    "gn:population":0,
    "gn:timezone":"Asia/Shanghai",
    "iso:country":"CN",
    "name:und_x_variant":[
        "\u5176\u6728\u5e72"
    ],
    "wof:name":"Qimugan",
    "wof:placetype":"locality"
},
  "geometry": {"coordinates":[76.44349,38.46252],"type":"Point"}
}