{
  "type": "Feature",
  "properties": {
    "gn:admin1_code":"16",
    "gn:asciiname":"Xiapingling",
    "gn:country_code":"CN",
    "gn:dem":488,
    "gn:feature_class":"P",
    "gn:feature_code":"PPL",
    "gn:name":"Xiapingling",
    "gn:population":0,
    "gn:timezone":"Asia/Shanghai",
    "iso:country":"CN",
    "name:zho_x_preferred":[
        "\u4e0b\u576a\u5cad"
    ],
    "wof:name":"Xiapingling",
    "wof:placetype":"locality"
},
  "geometry": {"coordinates":[109.899,25.234],"type":"Point"}
}