{
  "type": "Feature",
  "properties": {
    "gn:admin1_code":"29",
    "gn:asciiname":"Shigoutou",
    "gn:country_code":"CN",
    "gn:dem":1760,
    "gn:feature_class":"P",
    "gn:feature_code":"PPL",
    "gn:name":"Shigoutou",
    "gn:population":0,
    "gn:timezone":"Asia/Shanghai",
    "iso:country":"CN",
    "name:zho_x_preferred":[
        "\u77f3\u72d7\u5934"
    ],
    "wof:name":"Shigoutou",
    "wof:placetype":"locality"
},
  "geometry": {"coordinates":[102.56699999999999,24.4884],"type":"Point"}
}