{
  "type": "Feature",
  "properties": {
    "gn:admin1_code":"32.0",
    "gn:asciiname":"Gongli",
    "gn:country_code":"CN",
    "gn:dem":3171,
    "gn:feature_class":"P",
    "gn:feature_code":"PPL",
    "gn:name":"Gongli",
    "gn:population":0,
    "gn:timezone":"Asia/Shanghai",
    "iso:country":"CN",
    "name:zho_x_preferred":[
        "\u529f\u529b"
    ],
    "wof:name":"Gongli",
    "wof:placetype":"locality"
},
  "geometry": {"coordinates":[102.489,27.7602],"type":"Point"}
}