{
  "type": "Feature",
  "properties": {
    "gn:admin1_code":"2.0",
    "gn:asciiname":"Zhengushan",
    "gn:country_code":"CN",
    "gn:dem":73,
    "gn:feature_class":"P",
    "gn:feature_code":"PPL",
    "gn:name":"Zhengushan",
    "gn:population":0,
    "gn:timezone":"Asia/Shanghai",
    "iso:country":"CN",
    "name:und_x_variant":[
        "\u8d1e\u59d1\u5c71",
        "Zhengushan"
    ],
    "wof:name":"Zhengushan",
    "wof:placetype":"locality"
},
  "geometry": {"coordinates":[119.41023,29.02733],"type":"Point"}
}