{
  "type": "Feature",
  "properties": {
    "gn:admin1_code":"12.0",
    "gn:asciiname":"Maocaoling",
    "gn:country_code":"CN",
    "gn:dem":25,
    "gn:feature_class":"P",
    "gn:feature_code":"PPL",
    "gn:name":"Maocaoling",
    "gn:population":0,
    "gn:timezone":"Asia/Shanghai",
    "iso:country":"CN",
    "name:zho_x_preferred":[
        "\u8305\u8349\u5cad"
    ],
    "wof:name":"Maocaoling",
    "wof:placetype":"locality"
},
  "geometry": {"coordinates":[113.32983,29.92419000000001],"type":"Point"}
}