{
  "type": "Feature",
  "properties": {
    "gn:admin1_code":"26.0",
    "gn:asciiname":"Dangjiayangpo",
    "gn:country_code":"CN",
    "gn:dem":1104,
    "gn:feature_class":"P",
    "gn:feature_code":"PPL",
    "gn:name":"Dangjiayangpo",
    "gn:population":0,
    "gn:timezone":"Asia/Shanghai",
    "iso:country":"CN",
    "name:zho_x_preferred":[
        "\u515a\u5bb6\u9633\u5761"
    ],
    "wof:name":"Dangjiayangpo",
    "wof:placetype":"locality"
},
  "geometry": {"coordinates":[108.17212000000001,33.97905],"type":"Point"}
}