{
  "type": "Feature",
  "properties": {
    "gn:admin1_code":"12.0",
    "gn:asciiname":"Yanglaozhuang",
    "gn:country_code":"CN",
    "gn:dem":220,
    "gn:feature_class":"P",
    "gn:feature_code":"PPL",
    "gn:name":"Yanglaozhuang",
    "gn:population":0,
    "gn:timezone":"Asia/Shanghai",
    "iso:country":"CN",
    "name:zho_x_preferred":[
        "\u6768\u8001\u5e84"
    ],
    "wof:name":"Yanglaozhuang",
    "wof:placetype":"locality"
},
  "geometry": {"coordinates":[113.61747,32.27670999999999],"type":"Point"}
}