{
  "type": "Feature",
  "properties": {
    "gn:admin1_code":"3.0",
    "gn:asciiname":"Daruishan",
    "gn:country_code":"CN",
    "gn:dem":326,
    "gn:feature_class":"P",
    "gn:feature_code":"PPL",
    "gn:name":"Daruishan",
    "gn:population":0,
    "gn:timezone":"Asia/Shanghai",
    "iso:country":"CN",
    "name:und_x_variant":[
        "\u5927\u745e\u5c71"
    ],
    "wof:name":"Daruishan",
    "wof:placetype":"locality"
},
  "geometry": {"coordinates":[114.66398,24.93105],"type":"Point"}
}