{
  "type": "Feature",
  "properties": {
    "gn:admin1_code":"24.0",
    "gn:asciiname":"Shayugou",
    "gn:country_code":"CN",
    "gn:dem":1420,
    "gn:feature_class":"P",
    "gn:feature_code":"PPL",
    "gn:name":"Shayugou",
    "gn:population":0,
    "gn:timezone":"Asia/Shanghai",
    "iso:country":"CN",
    "name:zho_x_preferred":[
        "\u6c99\u5cea\u6c9f"
    ],
    "wof:name":"Shayugou",
    "wof:placetype":"locality"
},
  "geometry": {"coordinates":[113.24309,37.27759],"type":"Point"}
}