{
  "type": "Feature",
  "properties": {
    "gn:admin1_code":"31.0",
    "gn:asciiname":"Qunpo",
    "gn:country_code":"CN",
    "gn:dem":16,
    "gn:feature_class":"P",
    "gn:feature_code":"PPL",
    "gn:name":"Qunpo",
    "gn:population":0,
    "gn:timezone":"Asia/Shanghai",
    "iso:country":"CN",
    "name:zho_x_preferred":[
        "\u7fa4\u5761"
    ],
    "wof:name":"Qunpo",
    "wof:placetype":"locality"
},
  "geometry": {"coordinates":[110.3342,18.74815],"type":"Point"}
}