{
  "type": "Feature",
  "properties": {
    "gn:admin1_code":"26.0",
    "gn:asciiname":"Luziping",
    "gn:country_code":"CN",
    "gn:dem":1052,
    "gn:feature_class":"P",
    "gn:feature_code":"PPL",
    "gn:name":"Luziping",
    "gn:population":0,
    "gn:timezone":"Asia/Shanghai",
    "iso:country":"CN",
    "name:zho_x_preferred":[
        "\u8def\u5b50\u576a"
    ],
    "wof:name":"Luziping",
    "wof:placetype":"locality"
},
  "geometry": {"coordinates":[108.78821000000001,33.21594],"type":"Point"}
}