{
  "type": "Feature",
  "properties": {
    "gn:admin1_code":"21.0",
    "gn:asciiname":"Masha Guoyao",
    "gn:country_code":"CN",
    "gn:dem":1541,
    "gn:feature_class":"P",
    "gn:feature_code":"PPL",
    "gn:name":"Masha Guoyao",
    "gn:population":0,
    "gn:timezone":"Asia/Shanghai",
    "iso:country":"CN",
    "name:zho_x_preferred":[
        "\u9a6c\u6c99\u9505\u7a91"
    ],
    "wof:name":"Masha Guoyao",
    "wof:placetype":"locality"
},
  "geometry": {"coordinates":[106.637,37.8973],"type":"Point"}
}