{
  "type": "Feature",
  "properties": {
    "gn:admin1_code":"07",
    "gn:asciiname":"Dingrong",
    "gn:country_code":"CN",
    "gn:dem":662,
    "gn:feature_class":"P",
    "gn:feature_code":"PPL",
    "gn:name":"Dingrong",
    "gn:population":0,
    "gn:timezone":"Asia/Shanghai",
    "iso:country":"CN",
    "name:zho_x_preferred":[
        "\u4e01\u8363"
    ],
    "wof:name":"Dingrong",
    "wof:placetype":"locality"
},
  "geometry": {"coordinates":[118.34251999999999,25.85472],"type":"Point"}
}