{
  "type": "Feature",
  "properties": {
    "gn:admin1_code":"11.0",
    "gn:asciiname":"Guojiangkou",
    "gn:country_code":"CN",
    "gn:dem":207,
    "gn:feature_class":"P",
    "gn:feature_code":"PPL",
    "gn:name":"Guojiangkou",
    "gn:population":0,
    "gn:timezone":"Asia/Shanghai",
    "iso:country":"CN",
    "name:zho_x_preferred":[
        "\u90ed\u6c5f\u53e3"
    ],
    "wof:name":"Guojiangkou",
    "wof:placetype":"locality"
},
  "geometry": {"coordinates":[111.67066,25.6777],"type":"Point"}
}