{
  "type": "Feature",
  "properties": {
    "gn:admin1_code":"21.0",
    "gn:asciiname":"Xinjia Buzi",
    "gn:country_code":"CN",
    "gn:dem":1817,
    "gn:feature_class":"P",
    "gn:feature_code":"PPL",
    "gn:name":"Xinjia Buzi",
    "gn:population":0,
    "gn:timezone":"Asia/Shanghai",
    "iso:country":"CN",
    "name:zho_x_preferred":[
        "\u8f9b\u5bb6\u5821\u5b50"
    ],
    "wof:name":"Xinjia Buzi",
    "wof:placetype":"locality"
},
  "geometry": {"coordinates":[105.92451,35.55381],"type":"Point"}
}