{
  "type": "Feature",
  "properties": {
    "gn:admin1_code":"19.0",
    "gn:asciiname":"Hailibancun",
    "gn:country_code":"CN",
    "gn:dem":306,
    "gn:feature_class":"P",
    "gn:feature_code":"PPL",
    "gn:name":"Hailibancun",
    "gn:population":0,
    "gn:timezone":"Asia/Shanghai",
    "iso:country":"CN",
    "name:zho_x_preferred":[
        "\u6d77\u529b\u677f\u6751"
    ],
    "wof:name":"Hailibancun",
    "wof:placetype":"locality"
},
  "geometry": {"coordinates":[121.59099999999999,42.3425],"type":"Point"}
}