{
  "type": "Feature",
  "properties": {
    "gn:admin1_code":"30",
    "gn:asciiname":"Dapoping",
    "gn:country_code":"CN",
    "gn:dem":119,
    "gn:feature_class":"P",
    "gn:feature_code":"PPL",
    "gn:name":"Dapoping",
    "gn:population":0,
    "gn:timezone":"Asia/Urumqi",
    "iso:country":"CN",
    "name:zho_x_preferred":[
        "\u5927\u5761\u5e73"
    ],
    "wof:name":"Dapoping",
    "wof:placetype":"locality"
},
  "geometry": {"coordinates":[110.76618999999999,22.15209],"type":"Point"}
}