{
  "type": "Feature",
  "properties": {
    "gn:admin1_code":"4.0",
    "gn:asciiname":"Xiaoge",
    "gn:country_code":"CN",
    "gn:dem":14,
    "gn:feature_class":"P",
    "gn:feature_code":"PPL",
    "gn:name":"Xiaoge",
    "gn:population":0,
    "gn:timezone":"Asia/Shanghai",
    "iso:country":"CN",
    "name:zho_x_preferred":[
        "Xiaoge"
    ],
    "name:zho_x_variant":[
        "\u5c0f\u845b"
    ],
    "wof:name":"Xiaoge",
    "wof:placetype":"locality"
},
  "geometry": {"coordinates":[119.14165,34.30659],"type":"Point"}
}