{
  "type": "Feature",
  "properties": {
    "gn:admin1_code":"7.0",
    "gn:asciiname":"Huangzhukeng",
    "gn:country_code":"CN",
    "gn:dem":540,
    "gn:feature_class":"P",
    "gn:feature_code":"PPL",
    "gn:name":"Huangzhukeng",
    "gn:population":0,
    "gn:timezone":"Asia/Shanghai",
    "iso:country":"CN",
    "name:zho_x_preferred":[
        "\u9ec4\u7af9\u5751"
    ],
    "wof:name":"Huangzhukeng",
    "wof:placetype":"locality"
},
  "geometry": {"coordinates":[118.33842,27.47942],"type":"Point"}
}