{
  "type": "Feature",
  "properties": {
    "gn:admin1_code":"19.0",
    "gn:asciiname":"Waishaoguo Xigou",
    "gn:country_code":"CN",
    "gn:dem":239,
    "gn:feature_class":"P",
    "gn:feature_code":"PPL",
    "gn:name":"Waishaoguo Xigou",
    "gn:population":0,
    "gn:timezone":"Asia/Shanghai",
    "iso:country":"CN",
    "name:und_x_variant":[
        "\u5916\u70e7\u9505\u897f\u6c9f"
    ],
    "wof:name":"Waishaoguo Xigou",
    "wof:placetype":"locality"
},
  "geometry": {"coordinates":[124.69077,41.72137],"type":"Point"}
}