{
  "type": "Feature",
  "properties": {
    "gn:admin1_code":"02",
    "gn:asciiname":"Gaokantou",
    "gn:cc2":"CN",
    "gn:country_code":"CN",
    "gn:dem":7,
    "gn:feature_class":"P",
    "gn:feature_code":"PPL",
    "gn:name":"Gaokantou",
    "gn:population":0,
    "gn:timezone":"Asia/Shanghai",
    "iso:country":"CN",
    "name:und_x_variant":[
        "Kao-k\u2019an-t\u2019ou",
        "Gaokantou",
        "\u9ad8\u574e\u5934"
    ],
    "wof:name":"Gaokantou",
    "wof:placetype":"locality"
},
  "geometry": {"coordinates":[121.37333,28.6775],"type":"Point"}
}