{
  "type": "Feature",
  "properties": {
    "gn:admin1_code":"7.0",
    "gn:asciiname":"Xiazaihou",
    "gn:country_code":"CN",
    "gn:dem":258,
    "gn:feature_class":"P",
    "gn:feature_code":"PPL",
    "gn:name":"Xiazaihou",
    "gn:population":0,
    "gn:timezone":"Asia/Shanghai",
    "iso:country":"CN",
    "name:zho_x_preferred":[
        "\u4e0b\u8f7d\u539a"
    ],
    "wof:name":"Xiazaihou",
    "wof:placetype":"locality"
},
  "geometry": {"coordinates":[116.64167,24.90878],"type":"Point"}
}