{
  "type": "Feature",
  "properties": {
    "gn:admin1_code":"3.0",
    "gn:asciiname":"Wudoujiang",
    "gn:country_code":"CN",
    "gn:dem":214,
    "gn:feature_class":"P",
    "gn:feature_code":"PPL",
    "gn:name":"Wudoujiang",
    "gn:population":0,
    "gn:timezone":"Asia/Shanghai",
    "iso:country":"CN",
    "name:zho_x_preferred":[
        "\u4e94\u6597\u6c5f"
    ],
    "wof:name":"Wudoujiang",
    "wof:placetype":"locality"
},
  "geometry": {"coordinates":[114.3355,26.52464],"type":"Point"}
}