{
  "type": "Feature",
  "properties": {
    "gn:admin1_code":"14.0",
    "gn:asciiname":"Gujitan",
    "gn:country_code":"CN",
    "gn:dem":3376,
    "gn:feature_class":"P",
    "gn:feature_code":"PPL",
    "gn:name":"Gujitan",
    "gn:population":0,
    "gn:timezone":"Asia/Urumqi",
    "iso:country":"CN",
    "name:zho_x_preferred":[
        "\u8c37\u51e0\u6f6d"
    ],
    "wof:name":"Gujitan",
    "wof:placetype":"locality"
},
  "geometry": {"coordinates":[98.31856999999999,29.8044],"type":"Point"}
}