{
  "type": "Feature",
  "properties": {
    "gn:admin1_code":"19.0",
    "gn:asciiname":"Xiaotangnangou",
    "gn:country_code":"CN",
    "gn:dem":693,
    "gn:feature_class":"P",
    "gn:feature_code":"PPL",
    "gn:name":"Xiaotangnangou",
    "gn:population":0,
    "gn:timezone":"Asia/Shanghai",
    "iso:country":"CN",
    "name:zho_x_preferred":[
        "\u5c0f\u5858\u5357\u6c9f"
    ],
    "wof:name":"Xiaotangnangou",
    "wof:placetype":"locality"
},
  "geometry": {"coordinates":[119.59965,41.6145],"type":"Point"}
}