{
  "type": "Feature",
  "properties": {
    "gn:admin1_code":"30.0",
    "gn:asciiname":"Yangwu",
    "gn:country_code":"CN",
    "gn:dem":136,
    "gn:feature_class":"P",
    "gn:feature_code":"PPL",
    "gn:name":"Yangwu",
    "gn:population":0,
    "gn:timezone":"Asia/Shanghai",
    "iso:country":"CN",
    "name:zho_x_preferred":[
        "Yangwu"
    ],
    "name:zho_x_variant":[
        "\u6768\u5c4b"
    ],
    "wof:name":"Yangwu",
    "wof:placetype":"locality"
},
  "geometry": {"coordinates":[115.17556,24.40139],"type":"Point"}
}