{
  "type": "Feature",
  "properties": {
    "gn:admin1_code":"32.0",
    "gn:asciiname":"Luodao",
    "gn:country_code":"CN",
    "gn:dem":1797,
    "gn:feature_class":"P",
    "gn:feature_code":"PPL",
    "gn:name":"Luodao",
    "gn:population":0,
    "gn:timezone":"Asia/Shanghai",
    "iso:country":"CN",
    "name:zho_x_preferred":[
        "\u843d\u5200"
    ],
    "wof:name":"Luodao",
    "wof:placetype":"locality"
},
  "geometry": {"coordinates":[102.181,29.4361],"type":"Point"}
}