{
  "type": "Feature",
  "properties": {
    "gn:admin1_code":"18",
    "gn:asciiname":"Zhangshao",
    "gn:country_code":"CN",
    "gn:dem":1139,
    "gn:feature_class":"P",
    "gn:feature_code":"PPL",
    "gn:name":"Zhangshao",
    "gn:population":0,
    "gn:timezone":"Asia/Shanghai",
    "iso:country":"CN",
    "name:zho_x_preferred":[
        "\u638c\u54e8"
    ],
    "wof:name":"Zhangshao",
    "wof:placetype":"locality"
},
  "geometry": {"coordinates":[107.01300000000001,26.0411],"type":"Point"}
}