{
  "type": "Feature",
  "properties": {
    "gn:admin1_code":"29.0",
    "gn:asciiname":"Dida",
    "gn:country_code":"CN",
    "gn:dem":1052,
    "gn:feature_class":"P",
    "gn:feature_code":"PPL",
    "gn:name":"Dida",
    "gn:population":0,
    "gn:timezone":"Asia/Shanghai",
    "iso:country":"CN",
    "name:cat_x_preferred":[
        "Dida"
    ],
    "name:ceb_x_preferred":[
        "Dida"
    ],
    "name:dan_x_preferred":[
        "Dida"
    ],
    "name:deu_x_preferred":[
        "Dida"
    ],
    "name:fin_x_preferred":[
        "Dida"
    ],
    "name:fra_x_preferred":[
        "Dida"
    ],
    "name:hrv_x_preferred":[
        "Dida"
    ],
    "name:jpn_x_preferred":[
        "\u30b8\u30fc\u30c0"
    ],
    "name:nld_x_preferred":[
        "Dida"
    ],
    "name:pol_x_preferred":[
        "Dida"
    ],
    "name:por_x_preferred":[
        "Dida"
    ],
    "name:rus_x_preferred":[
        "\u0414\u0438\u0434\u0430"
    ],
    "name:slk_x_preferred":[
        "Dida"
    ],
    "name:swe_x_preferred":[
        "Dida"
    ],
    "name:tur_x_preferred":[
        "Dida"
    ],
    "name:zho_x_preferred":[
        "\u5e95\u6253"
    ],
    "wof:name":"Dida",
    "wof:placetype":"locality"
},
  "geometry": {"coordinates":[103.449,23.9462],"type":"Point"}
}