{
  "type": "Feature",
  "properties": {
    "gn:admin1_code":"16.0",
    "gn:asciiname":"Geliu",
    "gn:country_code":"CN",
    "gn:dem":393,
    "gn:feature_class":"P",
    "gn:feature_code":"PPL",
    "gn:name":"Geliu",
    "gn:population":0,
    "gn:timezone":"Asia/Shanghai",
    "iso:country":"CN",
    "name:zho_x_preferred":[
        "\u5404\u67f3"
    ],
    "wof:name":"Geliu",
    "wof:placetype":"locality"
},
  "geometry": {"coordinates":[106.154,24.395],"type":"Point"}
}