{
  "type": "Feature",
  "properties": {
    "gn:admin1_code":"31.0",
    "gn:asciiname":"Longbeicun",
    "gn:country_code":"CN",
    "gn:dem":18,
    "gn:feature_class":"P",
    "gn:feature_code":"PPL",
    "gn:name":"Longbeicun",
    "gn:population":0,
    "gn:timezone":"Asia/Shanghai",
    "iso:country":"CN",
    "name:zho_x_preferred":[
        "\u9f99\u5317\u6751"
    ],
    "wof:name":"Longbeicun",
    "wof:placetype":"locality"
},
  "geometry": {"coordinates":[110.931,19.8975],"type":"Point"}
}