{
  "type": "Feature",
  "properties": {
    "gn:admin1_code":"2.0",
    "gn:asciiname":"Wudalu",
    "gn:country_code":"CN",
    "gn:dem":86,
    "gn:feature_class":"P",
    "gn:feature_code":"PPL",
    "gn:name":"Wudalu",
    "gn:population":0,
    "gn:timezone":"Asia/Shanghai",
    "iso:country":"CN",
    "name:zho_x_preferred":[
        "\u5434\u5927\u8def"
    ],
    "wof:name":"Wudalu",
    "wof:placetype":"locality"
},
  "geometry": {"coordinates":[120.04604999999999,29.44392],"type":"Point"}
}