{
  "type": "Feature",
  "properties": {
    "gn:admin1_code":"8.0",
    "gn:asciiname":"Kangshiba",
    "gn:country_code":"CN",
    "gn:dem":131,
    "gn:feature_class":"P",
    "gn:feature_code":"PPL",
    "gn:name":"Kangshiba",
    "gn:population":0,
    "gn:timezone":"Asia/Shanghai",
    "iso:country":"CN",
    "name:zho_x_preferred":[
        "\u4ea2\u4ec0\u5df4"
    ],
    "wof:name":"Kangshiba",
    "wof:placetype":"locality"
},
  "geometry": {"coordinates":[124.50922,45.64734],"type":"Point"}
}