{
  "type": "Feature",
  "properties": {
    "gn:admin1_code":"1.0",
    "gn:asciiname":"Xiangshancun",
    "gn:country_code":"CN",
    "gn:dem":24,
    "gn:feature_class":"P",
    "gn:feature_code":"PPL",
    "gn:name":"Xiangshancun",
    "gn:population":0,
    "gn:timezone":"Asia/Shanghai",
    "iso:country":"CN",
    "name:zho_x_preferred":[
        "\u9999\u5c71\u6751"
    ],
    "wof:name":"Xiangshancun",
    "wof:placetype":"locality"
},
  "geometry": {"coordinates":[116.86364,30.88531],"type":"Point"}
}