{
  "type": "Feature",
  "properties": {
    "gn:admin1_code":"2.0",
    "gn:asciiname":"Shengdong",
    "gn:country_code":"CN",
    "gn:dem":10,
    "gn:feature_class":"P",
    "gn:feature_code":"PPL",
    "gn:name":"Shengdong",
    "gn:population":0,
    "gn:timezone":"Asia/Shanghai",
    "iso:country":"CN",
    "name:und_x_variant":[
        "\u76db\u4e1c"
    ],
    "wof:name":"Shengdong",
    "wof:placetype":"locality"
},
  "geometry": {"coordinates":[120.32947,30.21085],"type":"Point"}
}