{
  "type": "Feature",
  "properties": {
    "gn:admin1_code":"01",
    "gn:asciiname":"Liujiawei",
    "gn:cc2":"CN",
    "gn:country_code":"CN",
    "gn:dem":23,
    "gn:feature_class":"P",
    "gn:feature_code":"PPL",
    "gn:name":"Liujiawei",
    "gn:population":0,
    "gn:timezone":"Asia/Shanghai",
    "iso:country":"CN",
    "name:und_x_variant":[
        "Liu-chia-y\u00fc",
        "Liu-chia-wei",
        "Liu-chia-lou",
        "Liujiawei"
    ],
    "wof:name":"Liujiawei",
    "wof:placetype":"locality"
},
  "geometry": {"coordinates":[116.81667,32.95],"type":"Point"}
}