{
  "type": "Feature",
  "properties": {
    "gn:admin1_code":"10",
    "gn:asciiname":"Gouli",
    "gn:country_code":"CN",
    "gn:dem":149,
    "gn:feature_class":"P",
    "gn:feature_code":"PPL",
    "gn:name":"Gouli",
    "gn:population":0,
    "gn:timezone":"Asia/Shanghai",
    "iso:country":"CN",
    "name:und_x_variant":[
        "Kou-li",
        "Kou-li-chen",
        "Gouli"
    ],
    "wof:name":"Gouli",
    "wof:placetype":"locality"
},
  "geometry": {"coordinates":[114.57156999999999,38.73654000000001],"type":"Point"}
}