{
  "type": "Feature",
  "properties": {
    "gn:admin1_code":"26.0",
    "gn:asciiname":"Heilongshan",
    "gn:country_code":"CN",
    "gn:dem":1193,
    "gn:feature_class":"P",
    "gn:feature_code":"PPL",
    "gn:name":"Heilongshan",
    "gn:population":0,
    "gn:timezone":"Asia/Shanghai",
    "iso:country":"CN",
    "name:zho_x_preferred":[
        "\u9ed1\u9f99\u5c71"
    ],
    "wof:name":"Heilongshan",
    "wof:placetype":"locality"
},
  "geometry": {"coordinates":[109.46534,37.78234000000001],"type":"Point"}
}