{
  "type": "Feature",
  "properties": {
    "gn:admin1_code":"4.0",
    "gn:asciiname":"Xiting",
    "gn:country_code":"CN",
    "gn:dem":5,
    "gn:feature_class":"P",
    "gn:feature_code":"PPLA4",
    "gn:name":"Xiting",
    "gn:population":0,
    "gn:timezone":"Asia/Shanghai",
    "iso:country":"CN",
    "name:und_x_variant":[
        "Hsi-t\u2019ing",
        "Hsi-t\u2019ing-chen",
        "Xiting",
        "\u897f\u4ead",
        "Xiting Zhen",
        "\u897f\u4ead\u9547"
    ],
    "wof:name":"Xiting",
    "wof:placetype":"locality"
},
  "geometry": {"coordinates":[121.00462,32.11857],"type":"Point"}
}