{
  "type": "Feature",
  "properties": {
    "gn:admin1_code":"29.0",
    "gn:asciiname":"Henrenzhi",
    "gn:country_code":"CN",
    "gn:dem":2345,
    "gn:feature_class":"P",
    "gn:feature_code":"PPL",
    "gn:name":"Henrenzhi",
    "gn:population":0,
    "gn:timezone":"Asia/Shanghai",
    "iso:country":"CN",
    "name:zho_x_preferred":[
        "\u6068\u4eba\u77e5"
    ],
    "wof:name":"Henrenzhi",
    "wof:placetype":"locality"
},
  "geometry": {"coordinates":[100.91200000000001,26.3761],"type":"Point"}
}