{
  "type": "Feature",
  "properties": {
    "gn:admin1_code":"11",
    "gn:asciiname":"Lushui",
    "gn:country_code":"CN",
    "gn:dem":210,
    "gn:feature_class":"P",
    "gn:feature_code":"PPLA4",
    "gn:name":"Lushui",
    "gn:population":0,
    "gn:timezone":"Asia/Shanghai",
    "iso:country":"CN",
    "name:und_x_variant":[
        "Zhuzishan",
        "Lushui Zhen"
    ],
    "name:zho_x_preferred":[
        "\u6f5e\u6c34"
    ],
    "name:zho_x_variant":[
        "\u7af9\u5b50\u5c71",
        "\u6f5e\u6c34\u9547"
    ],
    "wof:name":"Lushui",
    "wof:placetype":"locality"
},
  "geometry": {"coordinates":[113.55580999999999,26.95975],"type":"Point"}
}