{
  "type": "Feature",
  "properties": {
    "gn:admin1_code":"5.0",
    "gn:asciiname":"Quanzicun",
    "gn:country_code":"CN",
    "gn:dem":195,
    "gn:feature_class":"P",
    "gn:feature_code":"PPL",
    "gn:name":"Quanzicun",
    "gn:population":0,
    "gn:timezone":"Asia/Shanghai",
    "iso:country":"CN",
    "name:zho_x_preferred":[
        "\u6cc9\u5b50\u6751"
    ],
    "wof:name":"Quanzicun",
    "wof:placetype":"locality"
},
  "geometry": {"coordinates":[125.58750999999999,44.6281],"type":"Point"}
}