{
  "type": "Feature",
  "properties": {
    "gn:admin1_code":"12.0",
    "gn:asciiname":"Wudadui",
    "gn:country_code":"CN",
    "gn:dem":25,
    "gn:feature_class":"P",
    "gn:feature_code":"PPLF",
    "gn:name":"Wudadui",
    "gn:population":0,
    "gn:timezone":"Asia/Shanghai",
    "iso:country":"CN",
    "name:und_x_variant":[
        "\u4e94\u5927\u961f"
    ],
    "wof:name":"Wudadui",
    "wof:placetype":"locality"
},
  "geometry": {"coordinates":[114.50736999999999,30.7114],"type":"Point"}
}