{
  "type": "Feature",
  "properties": {
    "gn:admin1_code":"32.0",
    "gn:asciiname":"Chunyang",
    "gn:country_code":"CN",
    "gn:dem":510,
    "gn:feature_class":"P",
    "gn:feature_code":"PPL",
    "gn:name":"Chunyang",
    "gn:population":0,
    "gn:timezone":"Asia/Shanghai",
    "iso:country":"CN",
    "name:zho_x_preferred":[
        "\u7eaf\u9633"
    ],
    "wof:name":"Chunyang",
    "wof:placetype":"locality"
},
  "geometry": {"coordinates":[105.32599999999999,31.7937],"type":"Point"}
}