{
  "type": "Feature",
  "properties": {
    "gn:admin1_code":"2.0",
    "gn:asciiname":"Nianyushan",
    "gn:country_code":"CN",
    "gn:dem":18,
    "gn:feature_class":"P",
    "gn:feature_code":"PPL",
    "gn:name":"Nianyushan",
    "gn:population":0,
    "gn:timezone":"Asia/Shanghai",
    "iso:country":"CN",
    "name:zho_x_preferred":[
        "\u9c87\u9c7c\u5c71"
    ],
    "name:zho_x_variant":[
        "\u9cb6\u9c7c\u5c71"
    ],
    "wof:name":"Nianyushan",
    "wof:placetype":"locality"
},
  "geometry": {"coordinates":[120.94741,29.92447],"type":"Point"}
}