{
  "type": "Feature",
  "properties": {
    "gn:admin1_code":"8.0",
    "gn:asciiname":"Gaofeng Linchang",
    "gn:country_code":"CN",
    "gn:dem":287,
    "gn:feature_class":"P",
    "gn:feature_code":"PPLF",
    "gn:name":"Gaofeng Linchang",
    "gn:population":0,
    "gn:timezone":"Asia/Shanghai",
    "iso:country":"CN",
    "name:zho_x_preferred":[
        "\u9ad8\u5cf0\u6797\u573a"
    ],
    "wof:name":"Gaofeng Linchang",
    "wof:placetype":"locality"
},
  "geometry": {"coordinates":[129.83139,47.8813],"type":"Point"}
}