{
  "type": "Feature",
  "properties": {
    "gn:admin1_code":"19.0",
    "gn:asciiname":"Baiguantun",
    "gn:country_code":"CN",
    "gn:dem":121,
    "gn:feature_class":"P",
    "gn:feature_code":"PPL",
    "gn:name":"Baiguantun",
    "gn:population":0,
    "gn:timezone":"Asia/Shanghai",
    "iso:country":"CN",
    "name:und_x_variant":[
        "\u767e\u8d2f\u5c6f"
    ],
    "name:zho_x_preferred":[
        "\u767e\u8d2f\u5c6f"
    ],
    "wof:name":"Baiguantun",
    "wof:placetype":"locality"
},
  "geometry": {"coordinates":[123.77449,42.00474000000001],"type":"Point"}
}