{
  "type": "Feature",
  "properties": {
    "gn:admin1_code":"09",
    "gn:asciiname":"Luanchuan Chengguanzhen",
    "gn:country_code":"CN",
    "gn:dem":742,
    "gn:feature_class":"P",
    "gn:feature_code":"PPLA3",
    "gn:name":"Luanchuan Chengguanzhen",
    "gn:population":0,
    "gn:timezone":"Asia/Shanghai",
    "iso:country":"CN",
    "name:deu_x_preferred":[
        "Luanchuan"
    ],
    "name:fas_x_preferred":[
        "\u0634\u0647\u0631\u0633\u062a\u0627\u0646 \u0644\u0648\u0627\u0646\u0686\u0648\u0627\u0646"
    ],
    "name:jpn_x_preferred":[
        "\u6b12\u5ddd\u770c"
    ],
    "name:kor_x_preferred":[
        "\ub87c\ucd28\ud604"
    ],
    "name:nor_x_preferred":[
        "Luanchuan"
    ],
    "name:rus_x_preferred":[
        "\u041b\u0443\u0430\u043d\u044c\u0447\u0443\u0430\u043d\u044c"
    ],
    "name:swe_x_preferred":[
        "Luanchuan"
    ],
    "name:und_x_variant":[
        "Luan-ch\u2019uan-chen",
        "Luanchuan",
        "Luanchuan Chengguanzhen",
        "Luanchuan Xiang"
    ],
    "name:urd_x_preferred":[
        "\u0644\u0648\u0627\u0646\u0686\u0648\u0627\u0646 \u06a9\u0627\u0624\u0646\u0679\u06cc"
    ],
    "name:vie_x_preferred":[
        "Loan Xuy\u00ean"
    ],
    "name:zho_x_preferred":[
        "\u683e\u5ddd\u57ce\u5173\u9547"
    ],
    "name:zho_x_variant":[
        "\u683e\u5ddd",
        "\u683e\u5ddd\u4e61",
        "\u683e\u5ddd\u53bf"
    ],
    "wof:name":"Luanchuan Chengguanzhen",
    "wof:placetype":"locality"
},
  "geometry": {"coordinates":[111.613,33.7808],"type":"Point"}
}