{
  "type": "Feature",
  "properties": {
    "gn:admin1_code":"09",
    "gn:asciiname":"Luanchuan Chengguanzhen",
    "gn:country_code":"CN",
    "gn:dem":742,
    "gn:feature_class":"P",
    "gn:feature_code":"PPLA3",
    "gn:name":"Luanchuan Chengguanzhen",
    "gn:population":0,
    "gn:timezone":"Asia/Shanghai",
    "iso:country":"CN",
    "name:und_x_variant":[
        "Luan-ch\u2019uan-chen",
        "Luanchuan",
        "Luanchuan Chengguanzhen",
        "Luanchuan Xiang"
    ],
    "name:zho_x_preferred":[
        "\u683e\u5ddd\u57ce\u5173\u9547"
    ],
    "name:zho_x_variant":[
        "\u683e\u5ddd",
        "\u683e\u5ddd\u4e61"
    ],
    "wof:name":"Luanchuan Chengguanzhen",
    "wof:placetype":"locality"
},
  "geometry": {"coordinates":[111.613,33.7808],"type":"Point"}
}