{
  "type": "Feature",
  "properties": {
    "gn:admin1_code":"19.0",
    "gn:asciiname":"Nankangzhuang",
    "gn:country_code":"CN",
    "gn:dem":170,
    "gn:feature_class":"P",
    "gn:feature_code":"PPL",
    "gn:name":"Nankangzhuang",
    "gn:population":0,
    "gn:timezone":"Asia/Shanghai",
    "iso:country":"CN",
    "name:und_x_variant":[
        "\u5357\u5eb7\u5e84"
    ],
    "name:zho_x_preferred":[
        "\u5357\u5eb7\u5e84"
    ],
    "wof:name":"Nankangzhuang",
    "wof:placetype":"locality"
},
  "geometry": {"coordinates":[124.06456,42.1384],"type":"Point"}
}