{
  "type": "Feature",
  "properties": {
    "gn:admin1_code":"24.0",
    "gn:asciiname":"Sanling",
    "gn:country_code":"CN",
    "gn:dem":1388,
    "gn:feature_class":"P",
    "gn:feature_code":"PPL",
    "gn:name":"Sanling",
    "gn:population":0,
    "gn:timezone":"Asia/Shanghai",
    "iso:country":"CN",
    "name:und_x_variant":[
        "\u4e09\u5cad"
    ],
    "name:zho_x_preferred":[
        "\u4e09\u5cad"
    ],
    "wof:name":"Sanling",
    "wof:placetype":"locality"
},
  "geometry": {"coordinates":[113.57523,39.78097],"type":"Point"}
}