{
  "type": "Feature",
  "properties": {
    "gn:admin1_code":"11.0",
    "gn:asciiname":"Lanqiao",
    "gn:country_code":"CN",
    "gn:dem":531,
    "gn:feature_class":"P",
    "gn:feature_code":"PPL",
    "gn:name":"Lanqiao",
    "gn:population":0,
    "gn:timezone":"Asia/Shanghai",
    "iso:country":"CN",
    "name:zho_x_preferred":[
        "\u680f\u6865"
    ],
    "wof:name":"Lanqiao",
    "wof:placetype":"locality"
},
  "geometry": {"coordinates":[110.48788,27.40042],"type":"Point"}
}