{
  "type": "Feature",
  "properties": {
    "gn:admin1_code":"12.0",
    "gn:asciiname":"Cailiyuan",
    "gn:country_code":"CN",
    "gn:dem":88,
    "gn:feature_class":"P",
    "gn:feature_code":"PPL",
    "gn:name":"Cailiyuan",
    "gn:population":0,
    "gn:timezone":"Asia/Shanghai",
    "iso:country":"CN",
    "name:zho_x_preferred":[
        "\u8521\u674e\u9662"
    ],
    "wof:name":"Cailiyuan",
    "wof:placetype":"locality"
},
  "geometry": {"coordinates":[112.27442000000001,31.11581],"type":"Point"}
}