{
  "type": "Feature",
  "properties": {
    "gn:admin1_code":"4.0",
    "gn:asciiname":"Qianmayangzhuang",
    "gn:country_code":"CN",
    "gn:dem":4,
    "gn:feature_class":"P",
    "gn:feature_code":"PPL",
    "gn:name":"Qianmayangzhuang",
    "gn:population":0,
    "gn:timezone":"Asia/Shanghai",
    "iso:country":"CN",
    "name:und_x_variant":[
        "\u524d\u9a6c\u6768\u5e84"
    ],
    "name:zho_x_preferred":[
        "\u524d\u9a6c\u6768\u5e84"
    ],
    "wof:name":"Qianmayangzhuang",
    "wof:placetype":"locality"
},
  "geometry": {"coordinates":[120.79537000000001,32.38609],"type":"Point"}
}