{
  "type": "Feature",
  "properties": {
    "gn:admin1_code":"4.0",
    "gn:asciiname":"Hengfengcun",
    "gn:country_code":"CN",
    "gn:dem":4,
    "gn:feature_class":"P",
    "gn:feature_code":"PPL",
    "gn:name":"Hengfengcun",
    "gn:population":0,
    "gn:timezone":"Asia/Shanghai",
    "iso:country":"CN",
    "name:zho_x_preferred":[
        "\u6052\u4e30\u6751"
    ],
    "wof:name":"Hengfengcun",
    "wof:placetype":"locality"
},
  "geometry": {"coordinates":[119.55688000000001,32.6543],"type":"Point"}
}