{
  "type": "Feature",
  "properties": {
    "gn:admin1_code":"15.0",
    "gn:asciiname":"Xihu Nongchang",
    "gn:country_code":"CN",
    "gn:dem":1081,
    "gn:feature_class":"P",
    "gn:feature_code":"PPLF",
    "gn:name":"Xihu Nongchang",
    "gn:population":0,
    "gn:timezone":"Asia/Urumqi",
    "iso:country":"CN",
    "name:zho_x_preferred":[
        "\u897f\u6e56\u519c\u573a"
    ],
    "wof:name":"Xihu Nongchang",
    "wof:placetype":"locality"
},
  "geometry": {"coordinates":[95.08304,40.58363],"type":"Point"}
}