{
  "type": "Feature",
  "properties": {
    "gn:admin1_code":"2.0",
    "gn:asciiname":"Longtoudian",
    "gn:country_code":"CN",
    "gn:dem":562,
    "gn:feature_class":"P",
    "gn:feature_code":"PPL",
    "gn:name":"Longtoudian",
    "gn:population":0,
    "gn:timezone":"Asia/Shanghai",
    "iso:country":"CN",
    "name:zho_x_preferred":[
        "\u9f99\u5934\u5e97"
    ],
    "wof:name":"Longtoudian",
    "wof:placetype":"locality"
},
  "geometry": {"coordinates":[118.67097,28.44478],"type":"Point"}
}