{
  "type": "Feature",
  "properties": {
    "gn:admin1_code":"21.0",
    "gn:asciiname":"Daidi Goumen",
    "gn:country_code":"CN",
    "gn:dem":1739,
    "gn:feature_class":"P",
    "gn:feature_code":"PPL",
    "gn:name":"Daidi Goumen",
    "gn:population":0,
    "gn:timezone":"Asia/Shanghai",
    "iso:country":"CN",
    "name:zho_x_preferred":[
        "\u6234\u5730\u6c9f\u95e8"
    ],
    "wof:name":"Daidi Goumen",
    "wof:placetype":"locality"
},
  "geometry": {"coordinates":[105.908,36.2091],"type":"Point"}
}