{
  "type": "Feature",
  "properties": {
    "gn:admin1_code":"32.0",
    "gn:asciiname":"Wa'e'er",
    "gn:country_code":"CN",
    "gn:dem":2299,
    "gn:feature_class":"P",
    "gn:feature_code":"PPL",
    "gn:name":"Wa\u2019e\u2019er",
    "gn:population":0,
    "gn:timezone":"Asia/Shanghai",
    "iso:country":"CN",
    "name:zho_x_preferred":[
        "\u74e6\u5ce8\u5c14"
    ],
    "name:zho_x_variant":[
        "Wa\u2019e\u2019er"
    ],
    "wof:name":"Wa'e'er",
    "wof:placetype":"locality"
},
  "geometry": {"coordinates":[102.80947,28.18824],"type":"Point"}
}