{
  "type": "Feature",
  "properties": {
    "gn:admin1_code":"13.0",
    "gn:asciiname":"Bachu Sanchang",
    "gn:cc2":"CN",
    "gn:country_code":"CN",
    "gn:dem":1106,
    "gn:feature_class":"P",
    "gn:feature_code":"PPL",
    "gn:name":"Bachu Sanchang",
    "gn:population":0,
    "gn:timezone":"Asia/Shanghai",
    "iso:country":"CN",
    "name:und_x_variant":[
        "Pa-ch\u2019u-san-ch\u2019ang",
        "Bachu Sanchang"
    ],
    "wof:name":"Bachu Sanchang",
    "wof:placetype":"locality"
},
  "geometry": {"coordinates":[78.96666999999999,39.66667],"type":"Point"}
}