{
  "type": "Feature",
  "properties": {
    "gn:admin1_code":"32.0",
    "gn:asciiname":"Gezangmiya",
    "gn:country_code":"CN",
    "gn:dem":4015,
    "gn:feature_class":"P",
    "gn:feature_code":"PPL",
    "gn:name":"Gezangmiya",
    "gn:population":0,
    "gn:timezone":"Asia/Shanghai",
    "iso:country":"CN",
    "name:zho_x_preferred":[
        "\u5404\u85cf\u7c73\u57ad"
    ],
    "wof:name":"Gezangmiya",
    "wof:placetype":"locality"
},
  "geometry": {"coordinates":[101.05145,28.34278],"type":"Point"}
}