{
  "type": "Feature",
  "properties": {
    "gn:admin1_code":"15.0",
    "gn:asciiname":"Sigouhe",
    "gn:country_code":"CN",
    "gn:dem":1848,
    "gn:feature_class":"P",
    "gn:feature_code":"PPL",
    "gn:name":"Sigouhe",
    "gn:population":0,
    "gn:timezone":"Asia/Shanghai",
    "iso:country":"CN",
    "name:und_x_variant":[
        "\u56db\u6c9f\u6cb3"
    ],
    "wof:name":"Sigouhe",
    "wof:placetype":"locality"
},
  "geometry": {"coordinates":[105.45923999999999,35.46138],"type":"Point"}
}