{
  "type": "Feature",
  "properties": {
    "gn:admin1_code":"4.0",
    "gn:asciiname":"Lianhoucun",
    "gn:country_code":"CN",
    "gn:dem":33,
    "gn:feature_class":"P",
    "gn:feature_code":"PPL",
    "gn:name":"Lianhoucun",
    "gn:population":0,
    "gn:timezone":"Asia/Shanghai",
    "iso:country":"CN",
    "name:zho_x_preferred":[
        "\u8fde\u540e\u6751"
    ],
    "wof:name":"Lianhoucun",
    "wof:placetype":"locality"
},
  "geometry": {"coordinates":[117.99469000000001,34.53632],"type":"Point"}
}