{
  "type": "Feature",
  "properties": {
    "gn:admin1_code":"10",
    "gn:asciiname":"Wangerxiang",
    "gn:country_code":"CN",
    "gn:dem":40,
    "gn:feature_class":"P",
    "gn:feature_code":"PPL",
    "gn:name":"Wangerxiang",
    "gn:population":0,
    "gn:timezone":"Asia/Shanghai",
    "iso:country":"CN",
    "name:zho_x_preferred":[
        "\u738b\u4e8c\u53a2"
    ],
    "wof:name":"Wangerxiang",
    "wof:placetype":"locality"
},
  "geometry": {"coordinates":[115.33883,36.74135],"type":"Point"}
}