{
  "type": "Feature",
  "properties": {
    "gn:admin1_code":"7.0",
    "gn:asciiname":"Shangqi",
    "gn:country_code":"CN",
    "gn:dem":789,
    "gn:feature_class":"P",
    "gn:feature_code":"PPL",
    "gn:name":"Shangqi",
    "gn:population":0,
    "gn:timezone":"Asia/Shanghai",
    "iso:country":"CN",
    "name:und_x_variant":[
        "\u4e0a\u78dc"
    ],
    "name:zho_x_preferred":[
        "\u4e0a\u78dc"
    ],
    "wof:name":"Shangqi",
    "wof:placetype":"locality"
},
  "geometry": {"coordinates":[116.67646000000001,25.69225],"type":"Point"}
}