{
  "type": "Feature",
  "properties": {
    "gn:admin1_code":"16.0",
    "gn:asciiname":"Taoma",
    "gn:country_code":"CN",
    "gn:dem":94,
    "gn:feature_class":"P",
    "gn:feature_code":"PPL",
    "gn:name":"Taoma",
    "gn:population":0,
    "gn:timezone":"Asia/Shanghai",
    "iso:country":"CN",
    "name:zho_x_preferred":[
        "\u9676\u9a6c"
    ],
    "wof:name":"Taoma",
    "wof:placetype":"locality"
},
  "geometry": {"coordinates":[109.22799999999999,23.5798],"type":"Point"}
}