{
  "type": "Feature",
  "properties": {
    "gn:admin1_code":"31",
    "gn:asciiname":"Tuolei",
    "gn:country_code":"CN",
    "gn:dem":151,
    "gn:feature_class":"P",
    "gn:feature_code":"PPL",
    "gn:name":"Tuolei",
    "gn:population":0,
    "gn:timezone":"Asia/Shanghai",
    "iso:country":"CN",
    "name:und_x_variant":[
        "\u9640\u7c7b"
    ],
    "wof:name":"Tuolei",
    "wof:placetype":"locality"
},
  "geometry": {"coordinates":[108.86499999999999,18.9277],"type":"Point"}
}