{
  "type": "Feature",
  "properties": {
    "gn:admin1_code":"25",
    "gn:asciiname":"Diliqiao",
    "gn:country_code":"CN",
    "gn:dem":25,
    "gn:feature_class":"P",
    "gn:feature_code":"PPL",
    "gn:name":"Diliqiao",
    "gn:population":0,
    "gn:timezone":"Asia/Shanghai",
    "iso:country":"CN",
    "name:zho_x_preferred":[
        "\u5824\u674e\u6865"
    ],
    "wof:name":"Diliqiao",
    "wof:placetype":"locality"
},
  "geometry": {"coordinates":[116.488,36.914],"type":"Point"}
}