{
  "type": "Feature",
  "properties": {
    "gn:admin1_code":"12.0",
    "gn:asciiname":"Longfengwan",
    "gn:country_code":"CN",
    "gn:dem":697,
    "gn:feature_class":"P",
    "gn:feature_code":"PPL",
    "gn:name":"Longfengwan",
    "gn:population":0,
    "gn:timezone":"Asia/Shanghai",
    "iso:country":"CN",
    "name:zho_x_preferred":[
        "\u9f99\u51e4\u6e7e"
    ],
    "wof:name":"Longfengwan",
    "wof:placetype":"locality"
},
  "geometry": {"coordinates":[111.48757999999999,31.79818],"type":"Point"}
}