{
  "type": "Feature",
  "properties": {
    "gn:admin1_code":"02",
    "gn:asciiname":"Baoshancun",
    "gn:country_code":"CN",
    "gn:dem":76,
    "gn:feature_class":"P",
    "gn:feature_code":"PPL",
    "gn:name":"Baoshancun",
    "gn:population":0,
    "gn:timezone":"Asia/Shanghai",
    "iso:country":"CN",
    "name:und_x_variant":[
        "Pao-shan",
        "Baoshan",
        "Baoshancun"
    ],
    "name:zho_x_preferred":[
        "\u5305\u5c71"
    ],
    "name:zho_x_variant":[
        "\u5305\u5c71\u6751"
    ],
    "wof:name":"Baoshancun",
    "wof:placetype":"locality"
},
  "geometry": {"coordinates":[121.43709,28.84876],"type":"Point"}
}