{
  "type": "Feature",
  "properties": {
    "gn:admin1_code":"33.0",
    "gn:asciiname":"Caiyuanzi",
    "gn:country_code":"CN",
    "gn:dem":826,
    "gn:feature_class":"P",
    "gn:feature_code":"PPL",
    "gn:name":"Caiyuanzi",
    "gn:population":0,
    "gn:timezone":"Asia/Shanghai",
    "iso:country":"CN",
    "name:zho_x_preferred":[
        "\u83dc\u56ed\u5b50"
    ],
    "wof:name":"Caiyuanzi",
    "wof:placetype":"locality"
},
  "geometry": {"coordinates":[109.53946999999999,31.69846],"type":"Point"}
}