{
  "type": "Feature",
  "properties": {
    "gn:admin1_code":"16.0",
    "gn:asciiname":"Zhaiming",
    "gn:country_code":"CN",
    "gn:dem":258,
    "gn:feature_class":"P",
    "gn:feature_code":"PPL",
    "gn:name":"Zhaiming",
    "gn:population":0,
    "gn:timezone":"Asia/Shanghai",
    "iso:country":"CN",
    "name:zho_x_preferred":[
        "\u5be8\u660e"
    ],
    "wof:name":"Zhaiming",
    "wof:placetype":"locality"
},
  "geometry": {"coordinates":[108.857,25.2361],"type":"Point"}
}