{
  "type": "Feature",
  "properties": {
    "gn:admin1_code":"5.0",
    "gn:asciiname":"Baimujiangcun",
    "gn:country_code":"CN",
    "gn:dem":211,
    "gn:feature_class":"P",
    "gn:feature_code":"PPL",
    "gn:name":"Baimujiangcun",
    "gn:population":0,
    "gn:timezone":"Asia/Shanghai",
    "iso:country":"CN",
    "name:zho_x_preferred":[
        "\u767d\u6728\u5320\u6751"
    ],
    "wof:name":"Baimujiangcun",
    "wof:placetype":"locality"
},
  "geometry": {"coordinates":[124.48025,42.88583],"type":"Point"}
}