{
  "type": "Feature",
  "properties": {
    "gn:admin1_code":"7.0",
    "gn:asciiname":"Hefeng",
    "gn:country_code":"CN",
    "gn:dem":684,
    "gn:feature_class":"P",
    "gn:feature_code":"PPL",
    "gn:name":"Hefeng",
    "gn:population":0,
    "gn:timezone":"Asia/Shanghai",
    "iso:country":"CN",
    "name:und_x_variant":[
        "\u548c\u5cf0"
    ],
    "name:zho_x_preferred":[
        "\u548c\u5cf0"
    ],
    "wof:name":"Hefeng",
    "wof:placetype":"locality"
},
  "geometry": {"coordinates":[117.54121000000001,26.09837000000001],"type":"Point"}
}