{
  "type": "Feature",
  "properties": {
    "gn:admin1_code":"3.0",
    "gn:asciiname":"Lutingshan",
    "gn:country_code":"CN",
    "gn:dem":158,
    "gn:feature_class":"P",
    "gn:feature_code":"PPL",
    "gn:name":"Lutingshan",
    "gn:population":0,
    "gn:timezone":"Asia/Shanghai",
    "iso:country":"CN",
    "name:zho_x_preferred":[
        "\u8def\u4ead\u5c71"
    ],
    "wof:name":"Lutingshan",
    "wof:placetype":"locality"
},
  "geometry": {"coordinates":[118.325,28.5513],"type":"Point"}
}