{
  "type": "Feature",
  "properties": {
    "gn:admin1_code":"19.0",
    "gn:asciiname":"Caochanggou",
    "gn:country_code":"CN",
    "gn:dem":68,
    "gn:feature_class":"P",
    "gn:feature_code":"PPL",
    "gn:name":"Caochanggou",
    "gn:population":0,
    "gn:timezone":"Asia/Shanghai",
    "iso:country":"CN",
    "name:und_x_variant":[
        "\u8349\u573a\u6c9f"
    ],
    "wof:name":"Caochanggou",
    "wof:placetype":"locality"
},
  "geometry": {"coordinates":[122.90136,40.90896],"type":"Point"}
}