{
  "type": "Feature",
  "properties": {
    "gn:admin1_code":"15.0",
    "gn:asciiname":"Xiepoli",
    "gn:country_code":"CN",
    "gn:dem":1304,
    "gn:feature_class":"P",
    "gn:feature_code":"PPL",
    "gn:name":"Xiepoli",
    "gn:population":0,
    "gn:timezone":"Asia/Shanghai",
    "iso:country":"CN",
    "name:zho_x_preferred":[
        "\u6b47\u5761\u91cc"
    ],
    "wof:name":"Xiepoli",
    "wof:placetype":"locality"
},
  "geometry": {"coordinates":[104.941,32.7028],"type":"Point"}
}