{
  "type": "Feature",
  "properties": {
    "gn:admin1_code":"9.0",
    "gn:asciiname":"Jiuxiancun",
    "gn:country_code":"CN",
    "gn:dem":58,
    "gn:feature_class":"P",
    "gn:feature_code":"PPL",
    "gn:name":"Jiuxiancun",
    "gn:population":0,
    "gn:timezone":"Asia/Shanghai",
    "iso:country":"CN",
    "name:zho_x_preferred":[
        "\u65e7\u53bf\u6751"
    ],
    "wof:name":"Jiuxiancun",
    "wof:placetype":"locality"
},
  "geometry": {"coordinates":[114.74584,35.94867],"type":"Point"}
}