{
  "type": "Feature",
  "properties": {
    "gn:admin1_code":"19.0",
    "gn:asciiname":"Dongshanzuicun",
    "gn:country_code":"CN",
    "gn:dem":357,
    "gn:feature_class":"P",
    "gn:feature_code":"PPL",
    "gn:name":"Dongshanzuicun",
    "gn:population":0,
    "gn:timezone":"Asia/Shanghai",
    "iso:country":"CN",
    "name:zho_x_preferred":[
        "\u4e1c\u5c71\u5634\u6751"
    ],
    "wof:name":"Dongshanzuicun",
    "wof:placetype":"locality"
},
  "geometry": {"coordinates":[120.53959999999999,41.98771],"type":"Point"}
}