{
  "type": "Feature",
  "properties": {
    "gn:admin1_code":"11",
    "gn:asciiname":"Lingjiaotang",
    "gn:country_code":"CN",
    "gn:dem":188,
    "gn:feature_class":"P",
    "gn:feature_code":"PPL",
    "gn:name":"Lingjiaotang",
    "gn:population":0,
    "gn:timezone":"Asia/Shanghai",
    "iso:country":"CN",
    "name:zho_x_preferred":[
        "\u83f1\u89d2\u5858"
    ],
    "wof:name":"Lingjiaotang",
    "wof:placetype":"locality"
},
  "geometry": {"coordinates":[112.07229,27.87033],"type":"Point"}
}