{
  "type": "Feature",
  "properties": {
    "gn:admin1_code":"15.0",
    "gn:asciiname":"Mahuangba",
    "gn:country_code":"CN",
    "gn:dem":1309,
    "gn:feature_class":"P",
    "gn:feature_code":"PPL",
    "gn:name":"Mahuangba",
    "gn:population":0,
    "gn:timezone":"Asia/Shanghai",
    "iso:country":"CN",
    "name:und_x_variant":[
        "\u9a6c\u9ec4\u575d"
    ],
    "wof:name":"Mahuangba",
    "wof:placetype":"locality"
},
  "geometry": {"coordinates":[106.06626,33.70296],"type":"Point"}
}