{
  "type": "Feature",
  "properties": {
    "gn:admin1_code":"14.0",
    "gn:asciiname":"Xulonglong",
    "gn:country_code":"CN",
    "gn:dem":2472,
    "gn:feature_class":"P",
    "gn:feature_code":"PPL",
    "gn:name":"Xulonglong",
    "gn:population":0,
    "gn:timezone":"Asia/Urumqi",
    "iso:country":"CN",
    "name:zho_x_preferred":[
        "\u9700\u804b\u9f99"
    ],
    "wof:name":"Xulonglong",
    "wof:placetype":"locality"
},
  "geometry": {"coordinates":[99.0497,29.48536],"type":"Point"}
}