{
  "type": "Feature",
  "properties": {
    "gn:admin1_code":"24",
    "gn:asciiname":"Dasu",
    "gn:country_code":"CN",
    "gn:dem":585,
    "gn:feature_class":"P",
    "gn:feature_code":"PPL",
    "gn:name":"Dasu",
    "gn:population":0,
    "gn:timezone":"Asia/Shanghai",
    "iso:country":"CN",
    "name:fas_x_preferred":[
        "\u062f\u0627\u0633\u0648"
    ],
    "name:fra_x_preferred":[
        "Dassu"
    ],
    "name:msa_x_preferred":[
        "Dassu"
    ],
    "name:rus_x_preferred":[
        "\u0414\u0430\u0441\u0443"
    ],
    "name:swe_x_preferred":[
        "Dassu"
    ],
    "name:urd_x_preferred":[
        "\u062f\u0627\u0633\u0648"
    ],
    "name:zho_x_preferred":[
        "\u5927\u82cf"
    ],
    "wof:name":"Dasu",
    "wof:placetype":"locality"
},
  "geometry": {"coordinates":[111.57644000000001,35.94927],"type":"Point"}
}