{
  "type": "Feature",
  "properties": {
    "gn:admin1_code":"24",
    "gn:asciiname":"Dasu",
    "gn:country_code":"CN",
    "gn:dem":585,
    "gn:feature_class":"P",
    "gn:feature_code":"PPL",
    "gn:name":"Dasu",
    "gn:population":0,
    "gn:timezone":"Asia/Shanghai",
    "iso:country":"CN",
    "name:zho_x_preferred":[
        "\u5927\u82cf"
    ],
    "wof:name":"Dasu",
    "wof:placetype":"locality"
},
  "geometry": {"coordinates":[111.57644000000001,35.94927],"type":"Point"}
}