{
  "type": "Feature",
  "properties": {
    "gn:admin1_code":"2.0",
    "gn:asciiname":"Songxiangji",
    "gn:country_code":"CN",
    "gn:dem":237,
    "gn:feature_class":"P",
    "gn:feature_code":"PPL",
    "gn:name":"Songxiangji",
    "gn:population":0,
    "gn:timezone":"Asia/Shanghai",
    "iso:country":"CN",
    "name:und_x_variant":[
        "\u677e\u9999\u9e21",
        "Songxiangji"
    ],
    "wof:name":"Songxiangji",
    "wof:placetype":"locality"
},
  "geometry": {"coordinates":[119.84050000000001,29.74529],"type":"Point"}
}