{
  "type": "Feature",
  "properties": {
    "gn:admin1_code":"18",
    "gn:asciiname":"Shuitang",
    "gn:country_code":"CN",
    "gn:dem":2034,
    "gn:feature_class":"P",
    "gn:feature_code":"PPL",
    "gn:name":"Shuitang",
    "gn:population":0,
    "gn:timezone":"Asia/Shanghai",
    "iso:country":"CN",
    "wof:name":"Shuitang",
    "wof:placetype":"locality"
},
  "geometry": {"coordinates":[104.63444,27.08667],"type":"Point"}
}