{
  "type": "Feature",
  "properties": {
    "gn:admin1_code":"1.0",
    "gn:asciiname":"Xitiancun",
    "gn:country_code":"CN",
    "gn:dem":152,
    "gn:feature_class":"P",
    "gn:feature_code":"PPL",
    "gn:name":"Xitiancun",
    "gn:population":0,
    "gn:timezone":"Asia/Shanghai",
    "iso:country":"CN",
    "name:zho_x_preferred":[
        "\u897f\u7530\u6751"
    ],
    "wof:name":"Xitiancun",
    "wof:placetype":"locality"
},
  "geometry": {"coordinates":[118.16949,29.59448],"type":"Point"}
}