{
  "type": "Feature",
  "properties": {
    "gn:admin1_code":"33.0",
    "gn:asciiname":"Miaoquan",
    "gn:country_code":"CN",
    "gn:dem":292,
    "gn:feature_class":"P",
    "gn:feature_code":"PPLA4",
    "gn:name":"Miaoquan",
    "gn:population":0,
    "gn:timezone":"Asia/Shanghai",
    "iso:country":"CN",
    "name:und_x_variant":[
        "Miaoquan Xiang"
    ],
    "name:zho_x_preferred":[
        "\u5999\u6cc9"
    ],
    "name:zho_x_variant":[
        "\u5999\u6cc9\u4e61"
    ],
    "wof:name":"Miaoquan",
    "wof:placetype":"locality"
},
  "geometry": {"coordinates":[109.00399,28.64037],"type":"Point"}
}