{
  "type": "Feature",
  "properties": {
    "gn:admin1_code":"29.0",
    "gn:asciiname":"Dajinheshui",
    "gn:country_code":"CN",
    "gn:dem":1058,
    "gn:feature_class":"P",
    "gn:feature_code":"PPL",
    "gn:name":"Dajinheshui",
    "gn:population":0,
    "gn:timezone":"Asia/Shanghai",
    "iso:country":"CN",
    "name:zho_x_preferred":[
        "\u5927\u91d1\u6cb3\u6c34"
    ],
    "wof:name":"Dajinheshui",
    "wof:placetype":"locality"
},
  "geometry": {"coordinates":[101.84999999999999,25.8369],"type":"Point"}
}