{
  "type": "Feature",
  "properties": {
    "gn:admin1_code":"18",
    "gn:asciiname":"Shangbai",
    "gn:country_code":"CN",
    "gn:dem":1426,
    "gn:feature_class":"P",
    "gn:feature_code":"PPL",
    "gn:name":"Shangbai",
    "gn:population":0,
    "gn:timezone":"Asia/Shanghai",
    "iso:country":"CN",
    "name:zho_x_preferred":[
        "\u4e0a\u6446"
    ],
    "wof:name":"Shangbai",
    "wof:placetype":"locality"
},
  "geometry": {"coordinates":[106.925,26.0245],"type":"Point"}
}