{
  "type": "Feature",
  "properties": {
    "gn:admin1_code":"14.0",
    "gn:asciiname":"Sedeng",
    "gn:country_code":"CN",
    "gn:dem":4893,
    "gn:feature_class":"P",
    "gn:feature_code":"PPL",
    "gn:name":"Sedeng",
    "gn:population":0,
    "gn:timezone":"Asia/Urumqi",
    "iso:country":"CN",
    "name:zho_x_preferred":[
        "\u8272\u706f"
    ],
    "wof:name":"Sedeng",
    "wof:placetype":"locality"
},
  "geometry": {"coordinates":[90.50230000000001,31.50874],"type":"Point"}
}