{
  "type": "Feature",
  "properties": {
    "gn:admin1_code":"20.0",
    "gn:asciiname":"Fujiazhuang",
    "gn:country_code":"CN",
    "gn:dem":1603,
    "gn:feature_class":"P",
    "gn:feature_code":"PPL",
    "gn:name":"Fujiazhuang",
    "gn:population":0,
    "gn:timezone":"Asia/Shanghai",
    "iso:country":"CN",
    "name:und_x_variant":[
        "\u798f\u5bb6\u5e84"
    ],
    "wof:name":"Fujiazhuang",
    "wof:placetype":"locality"
},
  "geometry": {"coordinates":[112.30088000000001,41.49477],"type":"Point"}
}