{
  "type": "Feature",
  "properties": {
    "gn:admin1_code":"31",
    "gn:asciiname":"Zhongjian Erdui",
    "gn:country_code":"CN",
    "gn:dem":123,
    "gn:feature_class":"P",
    "gn:feature_code":"PPLF",
    "gn:name":"Zhongjian Erdui",
    "gn:population":0,
    "gn:timezone":"Asia/Shanghai",
    "iso:country":"CN",
    "wof:name":"Zhongjian Erdui",
    "wof:placetype":"locality"
},
  "geometry": {"coordinates":[110.17972,19.29361],"type":"Point"}
}