{
  "type": "Feature",
  "properties": {
    "gn:admin1_code":"11",
    "gn:asciiname":"Shuangjing",
    "gn:country_code":"CN",
    "gn:dem":181,
    "gn:feature_class":"P",
    "gn:feature_code":"PPL",
    "gn:name":"Shuangjing",
    "gn:population":0,
    "gn:timezone":"Asia/Shanghai",
    "iso:country":"CN",
    "name:ceb_x_preferred":[
        "Shuangjing"
    ],
    "name:swe_x_preferred":[
        "Shuangjing"
    ],
    "wof:name":"Shuangjing",
    "wof:placetype":"locality"
},
  "geometry": {"coordinates":[110.68306,28.00944],"type":"Point"}
}