{
  "type": "Feature",
  "properties": {
    "gn:admin1_code":"8.0",
    "gn:asciiname":"Houlicun",
    "gn:country_code":"CN",
    "gn:dem":175,
    "gn:feature_class":"P",
    "gn:feature_code":"PPL",
    "gn:name":"Houlicun",
    "gn:population":0,
    "gn:timezone":"Asia/Shanghai",
    "iso:country":"CN",
    "name:zho_x_preferred":[
        "\u540e\u68a8\u6751"
    ],
    "wof:name":"Houlicun",
    "wof:placetype":"locality"
},
  "geometry": {"coordinates":[127.05329,45.31708],"type":"Point"}
}