{
  "type": "Feature",
  "properties": {
    "gn:admin1_code":"09",
    "gn:asciiname":"Huaihelu",
    "gn:country_code":"CN",
    "gn:dem":112,
    "gn:feature_class":"P",
    "gn:feature_code":"PPLA3",
    "gn:name":"Huaihelu",
    "gn:population":0,
    "gn:timezone":"Asia/Shanghai",
    "iso:country":"CN",
    "name:zho_x_preferred":[
        "\u6dee\u6cb3\u8def"
    ],
    "wof:name":"Huaihelu",
    "wof:placetype":"locality"
},
  "geometry": {"coordinates":[113.64138,34.71638],"type":"Point"}
}