{
  "type": "Feature",
  "properties": {
    "gn:admin1_code":"29.0",
    "gn:asciiname":"Jinzigou",
    "gn:country_code":"CN",
    "gn:dem":2704,
    "gn:feature_class":"P",
    "gn:feature_code":"PPL",
    "gn:name":"Jinzigou",
    "gn:population":0,
    "gn:timezone":"Asia/Shanghai",
    "iso:country":"CN",
    "name:zho_x_preferred":[
        "\u91d1\u5b50\u6c9f"
    ],
    "wof:name":"Jinzigou",
    "wof:placetype":"locality"
},
  "geometry": {"coordinates":[100.749,27.3575],"type":"Point"}
}