{
  "type": "Feature",
  "properties": {
    "gn:admin1_code":"29",
    "gn:asciiname":"Sala",
    "gn:country_code":"CN",
    "gn:dem":1801,
    "gn:feature_class":"P",
    "gn:feature_code":"PPL",
    "gn:name":"Sala",
    "gn:population":0,
    "gn:timezone":"Asia/Shanghai",
    "iso:country":"CN",
    "name:zho_x_preferred":[
        "\u6d12\u814a"
    ],
    "wof:name":"Sala",
    "wof:placetype":"locality"
},
  "geometry": {"coordinates":[103.08199999999999,24.4951],"type":"Point"}
}