{
  "type": "Feature",
  "properties": {
    "gn:admin1_code":"3",
    "gn:asciiname":"Shantianlong",
    "gn:country_code":"CN",
    "gn:dem":277,
    "gn:feature_class":"P",
    "gn:feature_code":"PPL",
    "gn:name":"Shantianlong",
    "gn:population":0,
    "gn:timezone":"Asia/Shanghai",
    "iso:country":"CN",
    "name:zho_x_preferred":[
        "\u5c71\u7530\u5784"
    ],
    "wof:name":"Shantianlong",
    "wof:placetype":"locality"
},
  "geometry": {"coordinates":[114.321,26.7326],"type":"Point"}
}