{
  "type": "Feature",
  "properties": {
    "gn:admin1_code":"3.0",
    "gn:asciiname":"Xialugang",
    "gn:country_code":"CN",
    "gn:dem":34,
    "gn:feature_class":"P",
    "gn:feature_code":"PPL",
    "gn:name":"Xialugang",
    "gn:population":0,
    "gn:timezone":"Asia/Shanghai",
    "iso:country":"CN",
    "name:und_x_variant":[
        "\u4e0b\u8def\u6e2f"
    ],
    "wof:name":"Xialugang",
    "wof:placetype":"locality"
},
  "geometry": {"coordinates":[116.35102000000001,28.27478],"type":"Point"}
}