{
  "type": "Feature",
  "properties": {
    "gn:admin1_code":"12.0",
    "gn:asciiname":"Xinwuchang",
    "gn:country_code":"CN",
    "gn:dem":1385,
    "gn:feature_class":"P",
    "gn:feature_code":"PPL",
    "gn:name":"Xinwuchang",
    "gn:population":0,
    "gn:timezone":"Asia/Shanghai",
    "iso:country":"CN",
    "name:zho_x_preferred":[
        "Xinwuchang"
    ],
    "name:zho_x_variant":[
        "\u65b0\u5c4b\u573a"
    ],
    "wof:name":"Xinwuchang",
    "wof:placetype":"locality"
},
  "geometry": {"coordinates":[109.51066000000002,29.87214],"type":"Point"}
}