{
  "type": "Feature",
  "properties": {
    "gn:admin1_code":"5.0",
    "gn:asciiname":"Shahezhencun",
    "gn:country_code":"CN",
    "gn:dem":500,
    "gn:feature_class":"P",
    "gn:feature_code":"PPL",
    "gn:name":"Shahezhencun",
    "gn:population":0,
    "gn:timezone":"Asia/Shanghai",
    "iso:country":"CN",
    "name:zho_x_preferred":[
        "\u6c99\u6cb3\u9547\u6751"
    ],
    "wof:name":"Shahezhencun",
    "wof:placetype":"locality"
},
  "geometry": {"coordinates":[128.39004,43.40744],"type":"Point"}
}