{
  "type": "Feature",
  "properties": {
    "gn:admin1_code":"15.0",
    "gn:asciiname":"Xixiacun",
    "gn:country_code":"CN",
    "gn:dem":1278,
    "gn:feature_class":"P",
    "gn:feature_code":"PPL",
    "gn:name":"Xixiacun",
    "gn:population":0,
    "gn:timezone":"Asia/Shanghai",
    "iso:country":"CN",
    "name:zho_x_preferred":[
        "\u897f\u4e0b\u6751"
    ],
    "wof:name":"Xixiacun",
    "wof:placetype":"locality"
},
  "geometry": {"coordinates":[107.783,35.5378],"type":"Point"}
}