{
  "type": "Feature",
  "properties": {
    "gn:admin1_code":"12.0",
    "gn:asciiname":"Langshugang",
    "gn:country_code":"CN",
    "gn:dem":65,
    "gn:feature_class":"P",
    "gn:feature_code":"PPL",
    "gn:name":"Langshugang",
    "gn:population":0,
    "gn:timezone":"Asia/Shanghai",
    "iso:country":"CN",
    "name:zho_x_preferred":[
        "\u6994\u6811\u5c97"
    ],
    "wof:name":"Langshugang",
    "wof:placetype":"locality"
},
  "geometry": {"coordinates":[113.73146,31.38422000000001],"type":"Point"}
}