{
  "type": "Feature",
  "properties": {
    "gn:admin1_code":"1.0",
    "gn:asciiname":"Konghecun",
    "gn:country_code":"CN",
    "gn:dem":29,
    "gn:feature_class":"P",
    "gn:feature_code":"PPL",
    "gn:name":"Konghecun",
    "gn:population":0,
    "gn:timezone":"Asia/Shanghai",
    "iso:country":"CN",
    "name:zho_x_preferred":[
        "\u5b54\u6cb3\u6751"
    ],
    "wof:name":"Konghecun",
    "wof:placetype":"locality"
},
  "geometry": {"coordinates":[116.416,30.50328],"type":"Point"}
}