{
  "type": "Feature",
  "properties": {
    "gn:admin1_code":"19.0",
    "gn:asciiname":"Jigangzicun",
    "gn:country_code":"CN",
    "gn:dem":80,
    "gn:feature_class":"P",
    "gn:feature_code":"PPL",
    "gn:name":"Jigangzicun",
    "gn:population":0,
    "gn:timezone":"Asia/Shanghai",
    "iso:country":"CN",
    "name:zho_x_preferred":[
        "\u5409\u5c97\u5b50\u6751"
    ],
    "wof:name":"Jigangzicun",
    "wof:placetype":"locality"
},
  "geometry": {"coordinates":[122.54600000000001,42.3659],"type":"Point"}
}