{
  "type": "Feature",
  "properties": {
    "gn:admin1_code":"32.0",
    "gn:asciiname":"Zuowagong",
    "gn:country_code":"CN",
    "gn:dem":3792,
    "gn:feature_class":"P",
    "gn:feature_code":"PPL",
    "gn:name":"Zuowagong",
    "gn:population":0,
    "gn:timezone":"Asia/Shanghai",
    "iso:country":"CN",
    "name:zho_x_preferred":[
        "\u5ea7\u6d3c\u4f9b"
    ],
    "wof:name":"Zuowagong",
    "wof:placetype":"locality"
},
  "geometry": {"coordinates":[99.3528,30.2029],"type":"Point"}
}