{
  "type": "Feature",
  "properties": {
    "gn:admin1_code":"6.0",
    "gn:asciiname":"Jiarikou",
    "gn:country_code":"CN",
    "gn:dem":3848,
    "gn:feature_class":"P",
    "gn:feature_code":"PPL",
    "gn:name":"Jiarikou",
    "gn:population":0,
    "gn:timezone":"Asia/Urumqi",
    "iso:country":"CN",
    "name:zho_x_preferred":[
        "\u4f73\u65e5\u6263"
    ],
    "wof:name":"Jiarikou",
    "wof:placetype":"locality"
},
  "geometry": {"coordinates":[96.92202,33.03583],"type":"Point"}
}