{
  "type": "Feature",
  "properties": {
    "gn:admin1_code":"18",
    "gn:asciiname":"Ganjiatai",
    "gn:country_code":"CN",
    "gn:dem":1069,
    "gn:feature_class":"P",
    "gn:feature_code":"PPL",
    "gn:name":"Ganjiatai",
    "gn:population":0,
    "gn:timezone":"Asia/Shanghai",
    "iso:country":"CN",
    "name:zho_x_preferred":[
        "\u8d76\u5bb6\u53f0"
    ],
    "wof:name":"Ganjiatai",
    "wof:placetype":"locality"
},
  "geometry": {"coordinates":[107.41800000000001,28.0025],"type":"Point"}
}