{
  "type": "Feature",
  "properties": {
    "gn:admin1_code":"15",
    "gn:asciiname":"Lujing",
    "gn:cc2":"CN",
    "gn:country_code":"CN",
    "gn:dem":2597,
    "gn:feature_class":"P",
    "gn:feature_code":"PPL",
    "gn:name":"L\u00fcjing",
    "gn:population":0,
    "gn:timezone":"Asia/Shanghai",
    "iso:country":"CN",
    "name:und_x_variant":[
        "L\u00fc-ching",
        "L\u00fcjing"
    ],
    "wof:name":"Lujing",
    "wof:placetype":"locality"
},
  "geometry": {"coordinates":[104.55333,34.32],"type":"Point"}
}