{
  "type": "Feature",
  "properties": {
    "gn:admin1_code":"24.0",
    "gn:asciiname":"Shayaocun",
    "gn:country_code":"CN",
    "gn:dem":603,
    "gn:feature_class":"P",
    "gn:feature_code":"PPL",
    "gn:name":"Shayaocun",
    "gn:population":0,
    "gn:timezone":"Asia/Shanghai",
    "iso:country":"CN",
    "name:zho_x_preferred":[
        "\u6c99\u7a91\u6751"
    ],
    "wof:name":"Shayaocun",
    "wof:placetype":"locality"
},
  "geometry": {"coordinates":[111.73208,36.3685],"type":"Point"}
}