{
  "type": "Feature",
  "properties": {
    "gn:admin1_code":"26.0",
    "gn:asciiname":"Duiziping",
    "gn:country_code":"CN",
    "gn:dem":1548,
    "gn:feature_class":"P",
    "gn:feature_code":"PPL",
    "gn:name":"Duiziping",
    "gn:population":0,
    "gn:timezone":"Asia/Shanghai",
    "iso:country":"CN",
    "name:und_x_variant":[
        "\u5bf9\u5b50\u576a"
    ],
    "wof:name":"Duiziping",
    "wof:placetype":"locality"
},
  "geometry": {"coordinates":[106.58984,33.62614],"type":"Point"}
}