{
  "type": "Feature",
  "properties": {
    "gn:admin1_code":"18.0",
    "gn:asciiname":"Mahuangchong",
    "gn:country_code":"CN",
    "gn:dem":648,
    "gn:feature_class":"P",
    "gn:feature_code":"PPL",
    "gn:name":"Mahuangchong",
    "gn:population":0,
    "gn:timezone":"Asia/Shanghai",
    "iso:country":"CN",
    "name:zho_x_preferred":[
        "\u8682\u87e5\u51b2"
    ],
    "wof:name":"Mahuangchong",
    "wof:placetype":"locality"
},
  "geometry": {"coordinates":[109.151,27.5953],"type":"Point"}
}