{
  "type": "Feature",
  "properties": {
    "gn:admin1_code":"16",
    "gn:asciiname":"Dazhushan",
    "gn:country_code":"CN",
    "gn:dem":215,
    "gn:feature_class":"P",
    "gn:feature_code":"PPL",
    "gn:name":"Dazhushan",
    "gn:population":0,
    "gn:timezone":"Asia/Shanghai",
    "iso:country":"CN",
    "name:zho_x_preferred":[
        "\u5927\u7af9\u5c71"
    ],
    "wof:name":"Dazhushan",
    "wof:placetype":"locality"
},
  "geometry": {"coordinates":[111.15900000000001,25.6869],"type":"Point"}
}