{
  "type": "Feature",
  "properties": {
    "gn:admin1_code":"4.0",
    "gn:asciiname":"Matoushancun",
    "gn:country_code":"CN",
    "gn:dem":11,
    "gn:feature_class":"P",
    "gn:feature_code":"PPL",
    "gn:name":"Matoushancun",
    "gn:population":0,
    "gn:timezone":"Asia/Shanghai",
    "iso:country":"CN",
    "name:zho_x_preferred":[
        "\u9a6c\u5934\u5c71\u6751"
    ],
    "wof:name":"Matoushancun",
    "wof:placetype":"locality"
},
  "geometry": {"coordinates":[118.94989,32.42633],"type":"Point"}
}