{
  "type": "Feature",
  "properties": {
    "gn:admin1_code":"14.0",
    "gn:asciiname":"Caiqinmu",
    "gn:country_code":"CN",
    "gn:dem":4439,
    "gn:feature_class":"P",
    "gn:feature_code":"PPL",
    "gn:name":"Caiqinmu",
    "gn:population":0,
    "gn:timezone":"Asia/Urumqi",
    "iso:country":"CN",
    "name:zho_x_preferred":[
        "\u624d\u94a6\u6bcd"
    ],
    "wof:name":"Caiqinmu",
    "wof:placetype":"locality"
},
  "geometry": {"coordinates":[94.14803000000001,29.55198],"type":"Point"}
}