{
  "type": "Feature",
  "properties": {
    "gn:admin1_code":"32.0",
    "gn:asciiname":"Yinghuang",
    "gn:country_code":"CN",
    "gn:dem":521,
    "gn:feature_class":"P",
    "gn:feature_code":"PPL",
    "gn:name":"Yinghuang",
    "gn:population":0,
    "gn:timezone":"Asia/Shanghai",
    "iso:country":"CN",
    "name:zho_x_preferred":[
        "\u8424\u714c"
    ],
    "wof:name":"Yinghuang",
    "wof:placetype":"locality"
},
  "geometry": {"coordinates":[104.648,31.3317],"type":"Point"}
}