{
  "type": "Feature",
  "properties": {
    "gn:admin1_code":"5.0",
    "gn:asciiname":"Jiefang",
    "gn:country_code":"CN",
    "gn:dem":98,
    "gn:feature_class":"P",
    "gn:feature_code":"PPL",
    "gn:name":"Jiefang",
    "gn:population":0,
    "gn:timezone":"Asia/Shanghai",
    "iso:country":"CN",
    "name:ceb_x_preferred":[
        "Jiefang"
    ],
    "name:deu_x_preferred":[
        "Jiefang"
    ],
    "name:und_x_variant":[
        "\u89e3\u653e",
        "Jiefangcun",
        "\u89e3\u653e\u6751"
    ],
    "wof:name":"Jiefang",
    "wof:placetype":"locality"
},
  "geometry": {"coordinates":[130.16586000000001,43.02054],"type":"Point"}
}