{
  "type": "Feature",
  "properties": {
    "gn:admin1_code":"3.0",
    "gn:asciiname":"Chouchuan",
    "gn:country_code":"CN",
    "gn:dem":59,
    "gn:feature_class":"P",
    "gn:feature_code":"PPL",
    "gn:name":"Chouchuan",
    "gn:population":0,
    "gn:timezone":"Asia/Shanghai",
    "iso:country":"CN",
    "name:und_x_variant":[
        "\u7a20\u5ddd"
    ],
    "wof:name":"Chouchuan",
    "wof:placetype":"locality"
},
  "geometry": {"coordinates":[114.98268,27.83927000000001],"type":"Point"}
}