{
  "type": "Feature",
  "properties": {
    "gn:admin1_code":"26.0",
    "gn:asciiname":"Shiyansi",
    "gn:country_code":"CN",
    "gn:dem":753,
    "gn:feature_class":"P",
    "gn:feature_code":"PPL",
    "gn:name":"Shiyansi",
    "gn:population":0,
    "gn:timezone":"Asia/Shanghai",
    "iso:country":"CN",
    "name:und_x_variant":[
        "\u77f3\u5830\u5bfa"
    ],
    "wof:name":"Shiyansi",
    "wof:placetype":"locality"
},
  "geometry": {"coordinates":[107.04574,33.23263],"type":"Point"}
}