{
  "type": "Feature",
  "properties": {
    "gn:admin1_code":"32.0",
    "gn:asciiname":"Huishuping",
    "gn:country_code":"CN",
    "gn:dem":1172,
    "gn:feature_class":"P",
    "gn:feature_code":"PPL",
    "gn:name":"Huishuping",
    "gn:population":0,
    "gn:timezone":"Asia/Shanghai",
    "iso:country":"CN",
    "name:zho_x_preferred":[
        "\u6bc1\u6811\u576a"
    ],
    "wof:name":"Huishuping",
    "wof:placetype":"locality"
},
  "geometry": {"coordinates":[107.523,32.3515],"type":"Point"}
}