{
  "type": "Feature",
  "properties": {
    "gn:admin1_code":"20.0",
    "gn:asciiname":"Chepugou",
    "gn:country_code":"CN",
    "gn:dem":1465,
    "gn:feature_class":"P",
    "gn:feature_code":"PPL",
    "gn:name":"Chepugou",
    "gn:population":0,
    "gn:timezone":"Asia/Shanghai",
    "iso:country":"CN",
    "name:und_x_variant":[
        "\u8f66\u94fa\u6c9f"
    ],
    "wof:name":"Chepugou",
    "wof:placetype":"locality"
},
  "geometry": {"coordinates":[109.99509,40.8781],"type":"Point"}
}