{
  "type": "Feature",
  "properties": {
    "gn:admin1_code":"15.0",
    "gn:asciiname":"Zhaojia Zuizi",
    "gn:country_code":"CN",
    "gn:dem":1201,
    "gn:feature_class":"P",
    "gn:feature_code":"PPL",
    "gn:name":"Zhaojia Zuizi",
    "gn:population":0,
    "gn:timezone":"Asia/Shanghai",
    "iso:country":"CN",
    "name:zho_x_preferred":[
        "\u8d75\u5bb6\u5480\u5b50"
    ],
    "wof:name":"Zhaojia Zuizi",
    "wof:placetype":"locality"
},
  "geometry": {"coordinates":[108.10899999999999,36.0707],"type":"Point"}
}