{
  "type": "Feature",
  "properties": {
    "gn:admin1_code":"19.0",
    "gn:asciiname":"Qianfan Shishan",
    "gn:country_code":"CN",
    "gn:dem":46,
    "gn:feature_class":"P",
    "gn:feature_code":"PPL",
    "gn:name":"Qianfan Shishan",
    "gn:population":0,
    "gn:timezone":"Asia/Shanghai",
    "iso:country":"CN",
    "name:zho_x_preferred":[
        "\u524d\u77fe\u77f3\u5c71"
    ],
    "wof:name":"Qianfan Shishan",
    "wof:placetype":"locality"
},
  "geometry": {"coordinates":[120.24068,40.33836],"type":"Point"}
}