{
  "type": "Feature",
  "properties": {
    "gn:admin1_code":"20.0",
    "gn:asciiname":"Tiegedan",
    "gn:country_code":"CN",
    "gn:dem":1875,
    "gn:feature_class":"P",
    "gn:feature_code":"PPL",
    "gn:name":"Tiegedan",
    "gn:population":0,
    "gn:timezone":"Asia/Shanghai",
    "iso:country":"CN",
    "name:und_x_variant":[
        "\u94c1\u572a\u65e6"
    ],
    "wof:name":"Tiegedan",
    "wof:placetype":"locality"
},
  "geometry": {"coordinates":[111.98992,41.36201],"type":"Point"}
}