{
  "type": "Feature",
  "properties": {
    "gn:admin1_code":"7",
    "gn:asciiname":"Fozaixi",
    "gn:country_code":"CN",
    "gn:dem":420,
    "gn:feature_class":"P",
    "gn:feature_code":"PPL",
    "gn:name":"Fozaixi",
    "gn:population":0,
    "gn:timezone":"Asia/Shanghai",
    "iso:country":"CN",
    "name:zho_x_preferred":[
        "\u4f5b\u4ed4\u6eaa"
    ],
    "wof:name":"Fozaixi",
    "wof:placetype":"locality"
},
  "geometry": {"coordinates":[117.45508,24.89439],"type":"Point"}
}