{
  "type": "Feature",
  "properties": {
    "gn:admin1_code":"32.0",
    "gn:asciiname":"Zezhu",
    "gn:country_code":"CN",
    "gn:dem":2271,
    "gn:feature_class":"P",
    "gn:feature_code":"PPL",
    "gn:name":"Zezhu",
    "gn:population":0,
    "gn:timezone":"Asia/Shanghai",
    "iso:country":"CN",
    "name:zho_x_preferred":[
        "\u5219\u73e0"
    ],
    "wof:name":"Zezhu",
    "wof:placetype":"locality"
},
  "geometry": {"coordinates":[102.548,28.4689],"type":"Point"}
}