{
  "type": "Feature",
  "properties": {
    "gn:admin1_code":"8.0",
    "gn:asciiname":"Anquancun",
    "gn:country_code":"CN",
    "gn:dem":239,
    "gn:feature_class":"P",
    "gn:feature_code":"PPL",
    "gn:name":"Anquancun",
    "gn:population":0,
    "gn:timezone":"Asia/Shanghai",
    "iso:country":"CN",
    "name:zho_x_preferred":[
        "\u5b89\u5168\u6751"
    ],
    "wof:name":"Anquancun",
    "wof:placetype":"locality"
},
  "geometry": {"coordinates":[128.00111000000001,44.9357],"type":"Point"}
}