{
  "type": "Feature",
  "properties": {
    "gn:admin1_code":"24.0",
    "gn:asciiname":"Taoshugou",
    "gn:country_code":"CN",
    "gn:dem":1036,
    "gn:feature_class":"P",
    "gn:feature_code":"PPL",
    "gn:name":"Taoshugou",
    "gn:population":0,
    "gn:timezone":"Asia/Shanghai",
    "iso:country":"CN",
    "name:zho_x_preferred":[
        "\u6843\u6811\u6c9f"
    ],
    "wof:name":"Taoshugou",
    "wof:placetype":"locality"
},
  "geometry": {"coordinates":[111.58817999999999,37.15974],"type":"Point"}
}