{
  "type": "Feature",
  "properties": {
    "gn:admin1_code":"30.0",
    "gn:asciiname":"Zhangdongkeng",
    "gn:country_code":"CN",
    "gn:dem":71,
    "gn:feature_class":"P",
    "gn:feature_code":"PPL",
    "gn:name":"Zhangdongkeng",
    "gn:population":0,
    "gn:timezone":"Asia/Shanghai",
    "iso:country":"CN",
    "name:zho_x_preferred":[
        "\u5f20\u6d1e\u5751"
    ],
    "wof:name":"Zhangdongkeng",
    "wof:placetype":"locality"
},
  "geometry": {"coordinates":[114.3168,23.68733],"type":"Point"}
}