{
  "type": "Feature",
  "properties": {
    "gn:admin1_code":"9",
    "gn:asciiname":"Linlou",
    "gn:country_code":"CN",
    "gn:dem":50,
    "gn:feature_class":"P",
    "gn:feature_code":"PPL",
    "gn:name":"Linlou",
    "gn:population":0,
    "gn:timezone":"Asia/Shanghai",
    "iso:country":"CN",
    "name:zho_x_preferred":[
        "\u6797\u697c"
    ],
    "wof:name":"Linlou",
    "wof:placetype":"locality"
},
  "geometry": {"coordinates":[116.03400000000001,35.9782],"type":"Point"}
}