{
  "type": "Feature",
  "properties": {
    "gn:admin1_code":"10",
    "gn:asciiname":"Liangwo",
    "gn:country_code":"CN",
    "gn:dem":272,
    "gn:feature_class":"P",
    "gn:feature_code":"PPL",
    "gn:name":"Liangwo",
    "gn:population":0,
    "gn:timezone":"Asia/Shanghai",
    "iso:country":"CN",
    "name:zho_x_preferred":[
        "\u7cae\u7a9d"
    ],
    "wof:name":"Liangwo",
    "wof:placetype":"locality"
},
  "geometry": {"coordinates":[117.25341,40.70898],"type":"Point"}
}