{
  "type": "Feature",
  "properties": {
    "gn:admin1_code":"30.0",
    "gn:asciiname":"Shanjiaokeng",
    "gn:country_code":"CN",
    "gn:dem":3,
    "gn:feature_class":"P",
    "gn:feature_code":"PPL",
    "gn:name":"Shanjiaokeng",
    "gn:population":0,
    "gn:timezone":"Asia/Shanghai",
    "iso:country":"CN",
    "name:zho_x_preferred":[
        "\u5c71\u8549\u5751"
    ],
    "wof:name":"Shanjiaokeng",
    "wof:placetype":"locality"
},
  "geometry": {"coordinates":[112.48313,21.95419],"type":"Point"}
}