{
  "type": "Feature",
  "properties": {
    "gn:admin1_code":"12.0",
    "gn:asciiname":"Yuanjiachong",
    "gn:country_code":"CN",
    "gn:dem":336,
    "gn:feature_class":"P",
    "gn:feature_code":"PPL",
    "gn:name":"Yuanjiachong",
    "gn:population":0,
    "gn:timezone":"Asia/Shanghai",
    "iso:country":"CN",
    "name:zho_x_preferred":[
        "\u8881\u5bb6\u51b2"
    ],
    "wof:name":"Yuanjiachong",
    "wof:placetype":"locality"
},
  "geometry": {"coordinates":[112.89107,31.27314],"type":"Point"}
}