{
  "type": "Feature",
  "properties": {
    "gn:admin1_code":"11.0",
    "gn:asciiname":"Shangjiaochong",
    "gn:country_code":"CN",
    "gn:dem":131,
    "gn:feature_class":"P",
    "gn:feature_code":"PPL",
    "gn:name":"Shangjiaochong",
    "gn:population":0,
    "gn:timezone":"Asia/Shanghai",
    "iso:country":"CN",
    "name:zho_x_preferred":[
        "\u4e0a\u89d2\u51b2"
    ],
    "wof:name":"Shangjiaochong",
    "wof:placetype":"locality"
},
  "geometry": {"coordinates":[112.32753,27.94758],"type":"Point"}
}