{
  "type": "Feature",
  "properties": {
    "gn:admin1_code":"3.0",
    "gn:asciiname":"Gangdong",
    "gn:country_code":"CN",
    "gn:dem":429,
    "gn:feature_class":"P",
    "gn:feature_code":"PPL",
    "gn:name":"Gangdong",
    "gn:population":0,
    "gn:timezone":"Asia/Shanghai",
    "iso:country":"CN",
    "name:zho_x_preferred":[
        "\u6e2f\u4e1c"
    ],
    "wof:name":"Gangdong",
    "wof:placetype":"locality"
},
  "geometry": {"coordinates":[117.19953,27.86808],"type":"Point"}
}