{
  "type": "Feature",
  "properties": {
    "gn:admin1_code":"4.0",
    "gn:asciiname":"Wangsanxu",
    "gn:country_code":"CN",
    "gn:dem":4,
    "gn:feature_class":"P",
    "gn:feature_code":"PPL",
    "gn:name":"Wangsanxu",
    "gn:population":0,
    "gn:timezone":"Asia/Shanghai",
    "iso:country":"CN",
    "name:zho_x_preferred":[
        "Wangsanxu"
    ],
    "name:zho_x_variant":[
        "\u738b\u4e09\u5729"
    ],
    "wof:name":"Wangsanxu",
    "wof:placetype":"locality"
},
  "geometry": {"coordinates":[119.26728,34.06434],"type":"Point"}
}