{
  "type": "Feature",
  "properties": {
    "gn:admin1_code":"26.0",
    "gn:asciiname":"Gaosongshu",
    "gn:country_code":"CN",
    "gn:dem":1112,
    "gn:feature_class":"P",
    "gn:feature_code":"PPL",
    "gn:name":"Gaosongshu",
    "gn:population":0,
    "gn:timezone":"Asia/Shanghai",
    "iso:country":"CN",
    "name:zho_x_preferred":[
        "\u9ad8\u677e\u6811"
    ],
    "wof:name":"Gaosongshu",
    "wof:placetype":"locality"
},
  "geometry": {"coordinates":[108.91942,35.5041],"type":"Point"}
}