{
  "type": "Feature",
  "properties": {
    "gn:admin1_code":"5.0",
    "gn:asciiname":"Xilaidong Shangcun",
    "gn:country_code":"CN",
    "gn:dem":512,
    "gn:feature_class":"P",
    "gn:feature_code":"PPL",
    "gn:name":"Xilaidong Shangcun",
    "gn:population":0,
    "gn:timezone":"Asia/Shanghai",
    "iso:country":"CN",
    "wof:name":"Xilaidong Shangcun",
    "wof:placetype":"locality"
},
  "geometry": {"coordinates":[129.64994999999999,42.53507000000001],"type":"Point"}
}