{
  "type": "Feature",
  "properties": {
    "gn:admin1_code":"8.0",
    "gn:asciiname":"Yugong Sidui Qiangzi",
    "gn:country_code":"CN",
    "gn:dem":122,
    "gn:feature_class":"P",
    "gn:feature_code":"PPLF",
    "gn:name":"Yugong Sidui Qiangzi",
    "gn:population":0,
    "gn:timezone":"Asia/Shanghai",
    "iso:country":"CN",
    "name:zho_x_preferred":[
        "\u611a\u516c\u56db\u961f\u62a2\u5b50"
    ],
    "wof:name":"Yugong Sidui Qiangzi",
    "wof:placetype":"locality"
},
  "geometry": {"coordinates":[130.02432999999999,46.44584],"type":"Point"}
}