{
  "type": "Feature",
  "properties": {
    "gn:admin1_code":"11",
    "gn:asciiname":"Doushan",
    "gn:country_code":"CN",
    "gn:dem":347,
    "gn:feature_class":"P",
    "gn:feature_code":"PPL",
    "gn:name":"Doushan",
    "gn:population":0,
    "gn:timezone":"Asia/Shanghai",
    "iso:country":"CN",
    "wof:name":"Doushan",
    "wof:placetype":"locality"
},
  "geometry": {"coordinates":[112.26917,27.30139],"type":"Point"}
}