{
  "type": "Feature",
  "properties": {
    "gn:admin1_code":"30",
    "gn:asciiname":"Ma'an'ao",
    "gn:country_code":"CN",
    "gn:dem":417,
    "gn:feature_class":"P",
    "gn:feature_code":"PPL",
    "gn:name":"Ma\u2019an\u2019ao",
    "gn:population":0,
    "gn:timezone":"Asia/Urumqi",
    "iso:country":"CN",
    "name:zho_x_preferred":[
        "\u9a6c\u978d\u5773"
    ],
    "name:zho_x_variant":[
        "Ma\u2019an\u2019ao"
    ],
    "wof:name":"Ma'an'ao",
    "wof:placetype":"locality"
},
  "geometry": {"coordinates":[111.24867,22.12443],"type":"Point"}
}