{
  "type": "Feature",
  "properties": {
    "gn:admin1_code":"14",
    "gn:asciiname":"Jiangmo",
    "gn:country_code":"CN",
    "gn:dem":4707,
    "gn:feature_class":"P",
    "gn:feature_code":"PPL",
    "gn:name":"Jiangmo",
    "gn:population":0,
    "gn:timezone":"Asia/Urumqi",
    "iso:country":"CN",
    "name:zho_x_preferred":[
        "\u6c5f\u6478"
    ],
    "wof:name":"Jiangmo",
    "wof:placetype":"locality"
},
  "geometry": {"coordinates":[88.944,29.6405],"type":"Point"}
}