{
  "type": "Feature",
  "properties": {
    "gn:admin1_code":"4.0",
    "gn:asciiname":"Xiaowengzhuang",
    "gn:country_code":"CN",
    "gn:dem":14,
    "gn:feature_class":"P",
    "gn:feature_code":"PPL",
    "gn:name":"Xiaowengzhuang",
    "gn:population":0,
    "gn:timezone":"Asia/Shanghai",
    "iso:country":"CN",
    "name:zho_x_preferred":[
        "\u5c0f\u7fc1\u5e84"
    ],
    "wof:name":"Xiaowengzhuang",
    "wof:placetype":"locality"
},
  "geometry": {"coordinates":[118.72499999999999,33.7655],"type":"Point"}
}