{
  "type": "Feature",
  "properties": {
    "gn:admin1_code":"5.0",
    "gn:asciiname":"Shuangshanzi",
    "gn:country_code":"CN",
    "gn:dem":150,
    "gn:feature_class":"P",
    "gn:feature_code":"PPL",
    "gn:name":"Shuangshanzi",
    "gn:population":0,
    "gn:timezone":"Asia/Shanghai",
    "iso:country":"CN",
    "name:zho_x_preferred":[
        "\u53cc\u5c71\u5b50"
    ],
    "wof:name":"Shuangshanzi",
    "wof:placetype":"locality"
},
  "geometry": {"coordinates":[122.87973,45.03619000000001],"type":"Point"}
}