{
  "type": "Feature",
  "properties": {
    "gn:admin1_code":"16.0",
    "gn:asciiname":"Sheng'an",
    "gn:country_code":"CN",
    "gn:dem":39,
    "gn:feature_class":"P",
    "gn:feature_code":"PPL",
    "gn:name":"Sheng\u2019an",
    "gn:population":0,
    "gn:timezone":"Asia/Shanghai",
    "iso:country":"CN",
    "name:und_x_variant":[
        "Sheng\u2019an"
    ],
    "name:zho_x_preferred":[
        "\u80dc\u5b89"
    ],
    "wof:name":"Sheng'an",
    "wof:placetype":"locality"
},
  "geometry": {"coordinates":[110.798,23.1923],"type":"Point"}
}