{
  "type": "Feature",
  "properties": {
    "gn:admin1_code":"29.0",
    "gn:asciiname":"Nuopushan",
    "gn:country_code":"CN",
    "gn:dem":1716,
    "gn:feature_class":"P",
    "gn:feature_code":"PPL",
    "gn:name":"Nuopushan",
    "gn:population":0,
    "gn:timezone":"Asia/Shanghai",
    "iso:country":"CN",
    "name:zho_x_preferred":[
        "\u7cef\u666e\u5c71"
    ],
    "wof:name":"Nuopushan",
    "wof:placetype":"locality"
},
  "geometry": {"coordinates":[101.23999999999999,23.7419],"type":"Point"}
}