{
  "type": "Feature",
  "properties": {
    "gn:admin1_code":"33.0",
    "gn:asciiname":"Lijia",
    "gn:country_code":"CN",
    "gn:dem":396,
    "gn:feature_class":"P",
    "gn:feature_code":"PPLA4",
    "gn:name":"Lijia",
    "gn:population":0,
    "gn:timezone":"Asia/Shanghai",
    "iso:country":"CN",
    "name:deu_x_preferred":[
        "Lijia"
    ],
    "name:und_x_variant":[
        "Lijia Zhen"
    ],
    "name:zho_x_preferred":[
        "\u674e\u5bb6"
    ],
    "name:zho_x_variant":[
        "\u674e\u5bb6\u9547"
    ],
    "wof:name":"Lijia",
    "wof:placetype":"locality"
},
  "geometry": {"coordinates":[105.53491,29.63201],"type":"Point"}
}