{
  "type": "Feature",
  "properties": {
    "gn:admin1_code":"10.0",
    "gn:asciiname":"Xiema",
    "gn:country_code":"CN",
    "gn:dem":166,
    "gn:feature_class":"P",
    "gn:feature_code":"PPL",
    "gn:name":"Xiema",
    "gn:population":0,
    "gn:timezone":"Asia/Shanghai",
    "iso:country":"CN",
    "name:und_x_variant":[
        "\u6b47\u9a6c"
    ],
    "wof:name":"Xiema",
    "wof:placetype":"locality"
},
  "geometry": {"coordinates":[114.85343,38.8623],"type":"Point"}
}