{
  "type": "Feature",
  "properties": {
    "gn:admin1_code":"11.0",
    "gn:asciiname":"Zhulingxia",
    "gn:country_code":"CN",
    "gn:dem":82,
    "gn:feature_class":"P",
    "gn:feature_code":"PPL",
    "gn:name":"Zhulingxia",
    "gn:population":0,
    "gn:timezone":"Asia/Shanghai",
    "iso:country":"CN",
    "name:zho_x_preferred":[
        "\u6731\u5cad\u4e0b"
    ],
    "wof:name":"Zhulingxia",
    "wof:placetype":"locality"
},
  "geometry": {"coordinates":[113.24244,26.87289],"type":"Point"}
}