{
  "type": "Feature",
  "properties": {
    "gn:admin1_code":"10.0",
    "gn:asciiname":"Xiwuquan",
    "gn:country_code":"CN",
    "gn:dem":41,
    "gn:feature_class":"P",
    "gn:feature_code":"PPL",
    "gn:name":"Xiwuquan",
    "gn:population":0,
    "gn:timezone":"Asia/Shanghai",
    "iso:country":"CN",
    "name:zho_x_preferred":[
        "\u897f\u6b66\u6cc9"
    ],
    "wof:name":"Xiwuquan",
    "wof:placetype":"locality"
},
  "geometry": {"coordinates":[115.69723,39.34149],"type":"Point"}
}