{
  "type": "Feature",
  "properties": {
    "gn:admin1_code":"2.0",
    "gn:asciiname":"Si'an Linchang",
    "gn:country_code":"CN",
    "gn:dem":88,
    "gn:feature_class":"P",
    "gn:feature_code":"PPLF",
    "gn:name":"Si\u2019an Linchang",
    "gn:population":0,
    "gn:timezone":"Asia/Shanghai",
    "iso:country":"CN",
    "name:und_x_variant":[
        "\u6cd7\u5b89\u6797\u573a"
    ],
    "name:zho_x_preferred":[
        "Si\u2019an Linchang"
    ],
    "wof:name":"Si'an Linchang",
    "wof:placetype":"locality"
},
  "geometry": {"coordinates":[119.60899999999999,30.97517],"type":"Point"}
}