{
  "type": "Feature",
  "properties": {
    "gn:admin1_code":"25",
    "gn:asciiname":"Dicijie",
    "gn:country_code":"CN",
    "gn:dem":7,
    "gn:feature_class":"P",
    "gn:feature_code":"PPL",
    "gn:name":"Dicijie",
    "gn:population":0,
    "gn:timezone":"Asia/Shanghai",
    "iso:country":"CN",
    "name:zho_x_preferred":[
        "\u5e1d\u8d50\u8857"
    ],
    "wof:name":"Dicijie",
    "wof:placetype":"locality"
},
  "geometry": {"coordinates":[117.755,38.0047],"type":"Point"}
}