{
  "type": "Feature",
  "properties": {
    "gn:admin1_code":"2.0",
    "gn:asciiname":"Yanshousi",
    "gn:country_code":"CN",
    "gn:dem":326,
    "gn:feature_class":"P",
    "gn:feature_code":"PPL",
    "gn:name":"Yanshousi",
    "gn:population":0,
    "gn:timezone":"Asia/Shanghai",
    "iso:country":"CN",
    "name:zho_x_preferred":[
        "\u5ef6\u5bff\u5bfa"
    ],
    "wof:name":"Yanshousi",
    "wof:placetype":"locality"
},
  "geometry": {"coordinates":[120.62416,28.10626],"type":"Point"}
}