{
  "type": "Feature",
  "properties": {
    "gn:admin1_code":"14.0",
    "gn:asciiname":"Bula",
    "gn:country_code":"CN",
    "gn:dem":3194,
    "gn:feature_class":"P",
    "gn:feature_code":"PPL",
    "gn:name":"Bula",
    "gn:population":0,
    "gn:timezone":"Asia/Urumqi",
    "iso:country":"CN",
    "name:zho_x_preferred":[
        "\u5e03\u62c9"
    ],
    "wof:name":"Bula",
    "wof:placetype":"locality"
},
  "geometry": {"coordinates":[92.72472999999999,29.08618],"type":"Point"}
}