{
  "type": "Feature",
  "properties": {
    "gn:admin1_code":"23.0",
    "gn:asciiname":"Xiaocenzhuang",
    "gn:country_code":"CN",
    "gn:dem":6,
    "gn:feature_class":"P",
    "gn:feature_code":"PPL",
    "gn:name":"Xiaocenzhuang",
    "gn:population":0,
    "gn:timezone":"Asia/Shanghai",
    "iso:country":"CN",
    "name:zho_x_preferred":[
        "Xiaocenzhuang"
    ],
    "name:zho_x_variant":[
        "\u5c0f\u5c91\u5e84"
    ],
    "wof:name":"Xiaocenzhuang",
    "wof:placetype":"locality"
},
  "geometry": {"coordinates":[120.93456,31.06001],"type":"Point"}
}