{
  "type": "Feature",
  "properties": {
    "gn:admin1_code":"7",
    "gn:asciiname":"Chouling",
    "gn:country_code":"CN",
    "gn:dem":757,
    "gn:feature_class":"P",
    "gn:feature_code":"PPL",
    "gn:name":"Chouling",
    "gn:population":0,
    "gn:timezone":"Asia/Shanghai",
    "iso:country":"CN",
    "name:und_x_variant":[
        "\u7ef8\u5cad"
    ],
    "wof:name":"Chouling",
    "wof:placetype":"locality"
},
  "geometry": {"coordinates":[119.91694,27.18944],"type":"Point"}
}