{
  "type": "Feature",
  "properties": {
    "gn:admin1_code":"29.0",
    "gn:asciiname":"Lantian",
    "gn:country_code":"CN",
    "gn:dem":1072,
    "gn:feature_class":"P",
    "gn:feature_code":"PPL",
    "gn:name":"Lantian",
    "gn:population":0,
    "gn:timezone":"Asia/Shanghai",
    "iso:country":"CN",
    "name:zho_x_preferred":[
        "\u6ee5\u7530"
    ],
    "wof:name":"Lantian",
    "wof:placetype":"locality"
},
  "geometry": {"coordinates":[101.471,22.0794],"type":"Point"}
}