{
  "type": "Feature",
  "properties": {
    "gn:admin1_code":"7.0",
    "gn:asciiname":"Liufang",
    "gn:country_code":"CN",
    "gn:dem":371,
    "gn:feature_class":"P",
    "gn:feature_code":"PPL",
    "gn:name":"Liufang",
    "gn:population":0,
    "gn:timezone":"Asia/Shanghai",
    "iso:country":"CN",
    "name:und_x_variant":[
        "\u5218\u574a"
    ],
    "name:zho_x_preferred":[
        "\u5218\u574a"
    ],
    "wof:name":"Liufang",
    "wof:placetype":"locality"
},
  "geometry": {"coordinates":[116.49309,25.92463],"type":"Point"}
}