{
  "type": "Feature",
  "properties": {
    "gn:admin1_code":"19.0",
    "gn:asciiname":"Cilinzicun",
    "gn:country_code":"CN",
    "gn:dem":27,
    "gn:feature_class":"P",
    "gn:feature_code":"PPL",
    "gn:name":"Cilinzicun",
    "gn:population":0,
    "gn:timezone":"Asia/Shanghai",
    "iso:country":"CN",
    "name:zho_x_preferred":[
        "\u8328\u6797\u5b50\u6751"
    ],
    "wof:name":"Cilinzicun",
    "wof:placetype":"locality"
},
  "geometry": {"coordinates":[122.812,41.8105],"type":"Point"}
}