{
  "type": "Feature",
  "properties": {
    "gn:admin1_code":"24.0",
    "gn:asciiname":"Bangou",
    "gn:country_code":"CN",
    "gn:dem":1164,
    "gn:feature_class":"P",
    "gn:feature_code":"PPL",
    "gn:name":"Bangou",
    "gn:population":0,
    "gn:timezone":"Asia/Shanghai",
    "iso:country":"CN",
    "name:ceb_x_preferred":[
        "Bangou"
    ],
    "name:fra_x_preferred":[
        "Bangou"
    ],
    "name:ita_x_preferred":[
        "Bangou"
    ],
    "name:spa_x_preferred":[
        "Bangou"
    ],
    "name:swe_x_preferred":[
        "Bangou"
    ],
    "name:zho_x_preferred":[
        "\u534a\u6c9f"
    ],
    "wof:name":"Bangou",
    "wof:placetype":"locality"
},
  "geometry": {"coordinates":[111.40617,36.70235],"type":"Point"}
}