{
  "type": "Feature",
  "properties": {
    "gn:admin1_code":"19.0",
    "gn:asciiname":"Tianjiatuncun",
    "gn:country_code":"CN",
    "gn:dem":32,
    "gn:feature_class":"P",
    "gn:feature_code":"PPL",
    "gn:name":"Tianjiatuncun",
    "gn:population":0,
    "gn:timezone":"Asia/Shanghai",
    "iso:country":"CN",
    "name:zho_x_preferred":[
        "\u7530\u5bb6\u5c6f\u6751"
    ],
    "wof:name":"Tianjiatuncun",
    "wof:placetype":"locality"
},
  "geometry": {"coordinates":[120.70878,40.70361],"type":"Point"}
}