{
  "type": "Feature",
  "properties": {
    "gn:admin1_code":"24.0",
    "gn:asciiname":"Modaohe",
    "gn:country_code":"CN",
    "gn:dem":1027,
    "gn:feature_class":"P",
    "gn:feature_code":"PPL",
    "gn:name":"Modaohe",
    "gn:population":0,
    "gn:timezone":"Asia/Shanghai",
    "iso:country":"CN",
    "name:und_x_variant":[
        "\u78e8\u9053\u6cb3"
    ],
    "wof:name":"Modaohe",
    "wof:placetype":"locality"
},
  "geometry": {"coordinates":[113.04656,39.79584000000001],"type":"Point"}
}