{
  "type": "Feature",
  "properties": {
    "gn:admin1_code":"19.0",
    "gn:asciiname":"Xiaokoumentou",
    "gn:country_code":"CN",
    "gn:dem":9,
    "gn:feature_class":"P",
    "gn:feature_code":"PPL",
    "gn:name":"Xiaokoumentou",
    "gn:population":0,
    "gn:timezone":"Asia/Shanghai",
    "iso:country":"CN",
    "name:und_x_variant":[
        "\u5c0f\u53e3\u95e8\u5934"
    ],
    "name:zho_x_preferred":[
        "\u5c0f\u53e3\u95e8\u5934"
    ],
    "wof:name":"Xiaokoumentou",
    "wof:placetype":"locality"
},
  "geometry": {"coordinates":[121.47199999999999,39.4496],"type":"Point"}
}