{
  "type": "Feature",
  "properties": {
    "gn:admin1_code":"8.0",
    "gn:asciiname":"Hualugoutun",
    "gn:country_code":"CN",
    "gn:dem":258,
    "gn:feature_class":"P",
    "gn:feature_code":"PPL",
    "gn:name":"Hualugoutun",
    "gn:population":0,
    "gn:timezone":"Asia/Shanghai",
    "iso:country":"CN",
    "name:zho_x_preferred":[
        "\u82b1\u9e7f\u6c9f\u5c6f"
    ],
    "wof:name":"Hualugoutun",
    "wof:placetype":"locality"
},
  "geometry": {"coordinates":[127.91363,45.61761],"type":"Point"}
}