{
  "type": "Feature",
  "properties": {
    "gn:admin1_code":"15.0",
    "gn:asciiname":"Gaxicun",
    "gn:country_code":"CN",
    "gn:dem":3142,
    "gn:feature_class":"P",
    "gn:feature_code":"PPL",
    "gn:name":"Gaxicun",
    "gn:population":0,
    "gn:timezone":"Asia/Shanghai",
    "iso:country":"CN",
    "name:zho_x_preferred":[
        "\u5c15\u897f\u6751"
    ],
    "wof:name":"Gaxicun",
    "wof:placetype":"locality"
},
  "geometry": {"coordinates":[102.95099999999999,34.9443],"type":"Point"}
}