{
  "type": "Feature",
  "properties": {
    "gn:admin1_code":"25.0",
    "gn:asciiname":"Liushibucun",
    "gn:country_code":"CN",
    "gn:dem":27,
    "gn:feature_class":"P",
    "gn:feature_code":"PPL",
    "gn:name":"Liushibucun",
    "gn:population":0,
    "gn:timezone":"Asia/Shanghai",
    "iso:country":"CN",
    "name:und_x_variant":[
        "Liushilibao",
        "Liushilibu"
    ],
    "name:zho_x_preferred":[
        "\u516d\u5341\u5821\u6751"
    ],
    "name:zho_x_variant":[
        "\u516d\u5341\u91cc\u5821"
    ],
    "wof:name":"Liushibucun",
    "wof:placetype":"locality"
},
  "geometry": {"coordinates":[120.98556000000001,37.70856],"type":"Point"}
}