{
  "type": "Feature",
  "properties": {
    "gn:admin1_code":"11.0",
    "gn:asciiname":"Tanghechong",
    "gn:country_code":"CN",
    "gn:dem":100,
    "gn:feature_class":"P",
    "gn:feature_code":"PPL",
    "gn:name":"Tanghechong",
    "gn:population":0,
    "gn:timezone":"Asia/Shanghai",
    "iso:country":"CN",
    "name:zho_x_preferred":[
        "\u5858\u8377\u51b2"
    ],
    "wof:name":"Tanghechong",
    "wof:placetype":"locality"
},
  "geometry": {"coordinates":[113.04236000000002,27.25017],"type":"Point"}
}