{
  "type": "Feature",
  "properties": {
    "gn:admin1_code":"29",
    "gn:asciiname":"Dagan",
    "gn:country_code":"CN",
    "gn:dem":556,
    "gn:feature_class":"P",
    "gn:feature_code":"PPL",
    "gn:name":"Dagan",
    "gn:population":0,
    "gn:timezone":"Asia/Shanghai",
    "iso:country":"CN",
    "name:deu_x_preferred":[
        "Dagan"
    ],
    "name:fra_x_preferred":[
        "Dagan"
    ],
    "name:heb_x_preferred":[
        "\u05d3\u05d2\u05df"
    ],
    "name:zho_x_preferred":[
        "\u8fbe\u5e72"
    ],
    "wof:name":"Dagan",
    "wof:placetype":"locality"
},
  "geometry": {"coordinates":[104.95099999999999,23.1998],"type":"Point"}
}