{
  "type": "Feature",
  "properties": {
    "gn:admin1_code":"19.0",
    "gn:asciiname":"Chengjiagou",
    "gn:country_code":"CN",
    "gn:dem":14,
    "gn:feature_class":"P",
    "gn:feature_code":"PPL",
    "gn:name":"Chengjiagou",
    "gn:population":0,
    "gn:timezone":"Asia/Shanghai",
    "iso:country":"CN",
    "name:und_x_variant":[
        "\u7a0b\u5bb6\u6c9f"
    ],
    "name:zho_x_preferred":[
        "\u7a0b\u5bb6\u6c9f"
    ],
    "wof:name":"Chengjiagou",
    "wof:placetype":"locality"
},
  "geometry": {"coordinates":[121.489,39.7823],"type":"Point"}
}