{
  "type": "Feature",
  "properties": {
    "gn:admin1_code":"12.0",
    "gn:asciiname":"Xiayoujiazui",
    "gn:country_code":"CN",
    "gn:dem":25,
    "gn:feature_class":"P",
    "gn:feature_code":"PPL",
    "gn:name":"Xiayoujiazui",
    "gn:population":0,
    "gn:timezone":"Asia/Shanghai",
    "iso:country":"CN",
    "name:zho_x_preferred":[
        "\u4e0b\u6e38\u5bb6\u5480"
    ],
    "wof:name":"Xiayoujiazui",
    "wof:placetype":"locality"
},
  "geometry": {"coordinates":[113.30596,30.71822],"type":"Point"}
}