{
  "type": "Feature",
  "properties": {
    "gn:admin1_code":"14.0",
    "gn:asciiname":"Jieba",
    "gn:country_code":"CN",
    "gn:dem":4403,
    "gn:feature_class":"P",
    "gn:feature_code":"PPL",
    "gn:name":"Jieba",
    "gn:population":0,
    "gn:timezone":"Asia/Urumqi",
    "iso:country":"CN",
    "name:zho_x_preferred":[
        "\u7ed3\u5df4"
    ],
    "wof:name":"Jieba",
    "wof:placetype":"locality"
},
  "geometry": {"coordinates":[91.93613000000001,28.02638],"type":"Point"}
}