{
  "type": "Feature",
  "properties": {
    "gn:admin1_code":"29.0",
    "gn:asciiname":"Zhuyuan",
    "gn:country_code":"CN",
    "gn:dem":1834,
    "gn:feature_class":"P",
    "gn:feature_code":"PPL",
    "gn:name":"Zhuyuan",
    "gn:population":0,
    "gn:timezone":"Asia/Shanghai",
    "iso:country":"CN",
    "name:zho_x_preferred":[
        "\u7af9\u56ed"
    ],
    "wof:name":"Zhuyuan",
    "wof:placetype":"locality"
},
  "geometry": {"coordinates":[104.306,25.4012],"type":"Point"}
}