{
  "type": "Feature",
  "properties": {
    "gn:admin1_code":"19.0",
    "gn:asciiname":"Gaojia Buzi",
    "gn:country_code":"CN",
    "gn:dem":150,
    "gn:feature_class":"P",
    "gn:feature_code":"PPL",
    "gn:name":"Gaojia Buzi",
    "gn:population":0,
    "gn:timezone":"Asia/Shanghai",
    "iso:country":"CN",
    "name:und_x_variant":[
        "Gaojiabaozi",
        "Gaojia Buzi"
    ],
    "name:zho_x_preferred":[
        "\u9ad8\u5bb6\u5821\u5b50"
    ],
    "wof:name":"Gaojia Buzi",
    "wof:placetype":"locality"
},
  "geometry": {"coordinates":[124.33019,40.63723],"type":"Point"}
}