{
  "type": "Feature",
  "properties": {
    "gn:admin1_code":"29.0",
    "gn:asciiname":"Hekou",
    "gn:country_code":"CN",
    "gn:dem":1848,
    "gn:feature_class":"P",
    "gn:feature_code":"PPL",
    "gn:name":"Hekou",
    "gn:population":0,
    "gn:timezone":"Asia/Shanghai",
    "iso:country":"CN",
    "name:zho_x_preferred":[
        "\u6cb3\u53e3"
    ],
    "wof:name":"Hekou",
    "wof:placetype":"locality"
},
  "geometry": {"coordinates":[98.5394,25.4494],"type":"Point"}
}