{
  "type": "Feature",
  "properties": {
    "gn:admin1_code":"16.0",
    "gn:asciiname":"Tanhuai",
    "gn:country_code":"CN",
    "gn:dem":173,
    "gn:feature_class":"P",
    "gn:feature_code":"PPL",
    "gn:name":"Tanhuai",
    "gn:population":0,
    "gn:timezone":"Asia/Shanghai",
    "iso:country":"CN",
    "name:zho_x_preferred":[
        "\u575b\u69d0"
    ],
    "wof:name":"Tanhuai",
    "wof:placetype":"locality"
},
  "geometry": {"coordinates":[108.672,22.4889],"type":"Point"}
}