{
  "type": "Feature",
  "properties": {
    "gn:admin1_code":"11.0",
    "gn:asciiname":"Laowangkou",
    "gn:country_code":"CN",
    "gn:dem":413,
    "gn:feature_class":"P",
    "gn:feature_code":"PPL",
    "gn:name":"Laowangkou",
    "gn:population":0,
    "gn:timezone":"Asia/Shanghai",
    "iso:country":"CN",
    "name:zho_x_preferred":[
        "\u8001\u738b\u53e3"
    ],
    "wof:name":"Laowangkou",
    "wof:placetype":"locality"
},
  "geometry": {"coordinates":[109.43109,26.68291],"type":"Point"}
}