{
  "type": "Feature",
  "properties": {
    "gn:admin1_code":"18",
    "gn:asciiname":"Baobaozhai",
    "gn:country_code":"CN",
    "gn:dem":1252,
    "gn:feature_class":"P",
    "gn:feature_code":"PPL",
    "gn:name":"Baobaozhai",
    "gn:population":0,
    "gn:timezone":"Asia/Shanghai",
    "iso:country":"CN",
    "name:zho_x_preferred":[
        "\u5305\u5305\u5be8"
    ],
    "wof:name":"Baobaozhai",
    "wof:placetype":"locality"
},
  "geometry": {"coordinates":[105.497,26.0249],"type":"Point"}
}