{
  "type": "Feature",
  "properties": {
    "gn:admin1_code":"7.0",
    "gn:asciiname":"Huaiyang",
    "gn:country_code":"CN",
    "gn:dem":531,
    "gn:feature_class":"P",
    "gn:feature_code":"PPL",
    "gn:name":"Huaiyang",
    "gn:population":0,
    "gn:timezone":"Asia/Shanghai",
    "iso:country":"CN",
    "name:deu_x_preferred":[
        "Huaiyang"
    ],
    "name:zho_x_preferred":[
        "\u69d0\u6768"
    ],
    "wof:name":"Huaiyang",
    "wof:placetype":"locality"
},
  "geometry": {"coordinates":[117.8446,25.26759],"type":"Point"}
}