{
  "type": "Feature",
  "properties": {
    "gn:admin1_code":"8.0",
    "gn:asciiname":"Quanshengcun",
    "gn:country_code":"CN",
    "gn:dem":185,
    "gn:feature_class":"P",
    "gn:feature_code":"PPL",
    "gn:name":"Quanshengcun",
    "gn:population":0,
    "gn:timezone":"Asia/Shanghai",
    "iso:country":"CN",
    "name:zho_x_preferred":[
        "\u5168\u80dc\u6751"
    ],
    "wof:name":"Quanshengcun",
    "wof:placetype":"locality"
},
  "geometry": {"coordinates":[131.27343999999999,45.13651],"type":"Point"}
}