{
  "type": "Feature",
  "properties": {
    "gn:admin1_code":"33.0",
    "gn:asciiname":"Liangfeng'ao",
    "gn:country_code":"CN",
    "gn:dem":910,
    "gn:feature_class":"P",
    "gn:feature_code":"PPL",
    "gn:name":"Liangfeng\u2019ao",
    "gn:population":0,
    "gn:timezone":"Asia/Shanghai",
    "iso:country":"CN",
    "name:und_x_variant":[
        "Liangfeng\u2019ao"
    ],
    "name:zho_x_preferred":[
        "\u51c9\u98ce\u5773"
    ],
    "wof:name":"Liangfeng'ao",
    "wof:placetype":"locality"
},
  "geometry": {"coordinates":[108.8156,28.61605],"type":"Point"}
}