{
  "type": "Feature",
  "properties": {
    "gn:admin1_code":"30.0",
    "gn:asciiname":"Nanting",
    "gn:country_code":"CN",
    "gn:dem":4,
    "gn:feature_class":"P",
    "gn:feature_code":"PPL",
    "gn:name":"Nanting",
    "gn:population":0,
    "gn:timezone":"Asia/Shanghai",
    "iso:country":"CN",
    "name:und_x_variant":[
        "\u5357\u4ead"
    ],
    "name:zho_x_preferred":[
        "\u5357\u4ead"
    ],
    "wof:name":"Nanting",
    "wof:placetype":"locality"
},
  "geometry": {"coordinates":[113.38227999999999,23.03849],"type":"Point"}
}