{
  "type": "Feature",
  "properties": {
    "gn:admin1_code":"11.0",
    "gn:asciiname":"Dawu Meijia",
    "gn:country_code":"CN",
    "gn:dem":79,
    "gn:feature_class":"P",
    "gn:feature_code":"PPL",
    "gn:name":"Dawu Meijia",
    "gn:population":0,
    "gn:timezone":"Asia/Shanghai",
    "iso:country":"CN",
    "name:zho_x_preferred":[
        "\u5927\u5c4b\u6885\u5bb6"
    ],
    "wof:name":"Dawu Meijia",
    "wof:placetype":"locality"
},
  "geometry": {"coordinates":[113.44110999999999,29.38211],"type":"Point"}
}