{
  "type": "Feature",
  "properties": {
    "gn:admin1_code":"20",
    "gn:asciiname":"Shi'er Gongli Nongchang",
    "gn:country_code":"CN",
    "gn:dem":688,
    "gn:feature_class":"P",
    "gn:feature_code":"PPLF",
    "gn:name":"Shi\u2019er Gongli Nongchang",
    "gn:population":0,
    "gn:timezone":"Asia/Shanghai",
    "iso:country":"CN",
    "name:und_x_variant":[
        "Shi\u2019er Gongli Nongchang"
    ],
    "name:zho_x_preferred":[
        "\u5341\u4e8c\u516c\u91cc\u519c\u573a"
    ],
    "wof:name":"Shi'er Gongli Nongchang",
    "wof:placetype":"locality"
},
  "geometry": {"coordinates":[121.33972,50.65917],"type":"Point"}
}