{
  "type": "Feature",
  "properties": {
    "gn:admin1_code":"24",
    "gn:asciiname":"Sijiao",
    "gn:cc2":"CN",
    "gn:country_code":"CN",
    "gn:dem":971,
    "gn:feature_class":"P",
    "gn:feature_code":"PPL",
    "gn:name":"Sijiao",
    "gn:population":0,
    "gn:timezone":"Asia/Shanghai",
    "iso:country":"CN",
    "name:und_x_variant":[
        "Ssu-chiao-ts\u2019un",
        "Ssu-chiao",
        "Sijiao"
    ],
    "wof:name":"Sijiao",
    "wof:placetype":"locality"
},
  "geometry": {"coordinates":[111.39722,35.10528],"type":"Point"}
}