{
  "type": "Feature",
  "properties": {
    "gn:admin1_code":"26.0",
    "gn:asciiname":"Yadanhecun",
    "gn:country_code":"CN",
    "gn:dem":762,
    "gn:feature_class":"P",
    "gn:feature_code":"PPL",
    "gn:name":"Yadanhecun",
    "gn:population":0,
    "gn:timezone":"Asia/Shanghai",
    "iso:country":"CN",
    "name:zho_x_preferred":[
        "\u9e2d\u86cb\u6cb3\u6751"
    ],
    "wof:name":"Yadanhecun",
    "wof:placetype":"locality"
},
  "geometry": {"coordinates":[109.00295,32.88394],"type":"Point"}
}