{
  "type": "Feature",
  "properties": {
    "gn:admin1_code":"9",
    "gn:asciiname":"Zilufen",
    "gn:country_code":"CN",
    "gn:dem":57,
    "gn:feature_class":"P",
    "gn:feature_code":"PPL",
    "gn:name":"Zilufen",
    "gn:population":0,
    "gn:timezone":"Asia/Shanghai",
    "iso:country":"CN",
    "name:zho_x_preferred":[
        "\u5b50\u8def\u575f"
    ],
    "wof:name":"Zilufen",
    "wof:placetype":"locality"
},
  "geometry": {"coordinates":[115.03,35.7553],"type":"Point"}
}