{
  "type": "Feature",
  "properties": {
    "gn:admin1_code":"16.0",
    "gn:asciiname":"Wangdun",
    "gn:country_code":"CN",
    "gn:dem":329,
    "gn:feature_class":"P",
    "gn:feature_code":"PPL",
    "gn:name":"Wangdun",
    "gn:population":0,
    "gn:timezone":"Asia/Shanghai",
    "iso:country":"CN",
    "name:zho_x_preferred":[
        "\u6c6a\u58a9"
    ],
    "wof:name":"Wangdun",
    "wof:placetype":"locality"
},
  "geometry": {"coordinates":[107.22199999999999,21.87],"type":"Point"}
}