{
  "type": "Feature",
  "properties": {
    "gn:admin1_code":"8.0",
    "gn:asciiname":"Shuangqiaozicun",
    "gn:country_code":"CN",
    "gn:dem":261,
    "gn:feature_class":"P",
    "gn:feature_code":"PPL",
    "gn:name":"Shuangqiaozicun",
    "gn:population":0,
    "gn:timezone":"Asia/Shanghai",
    "iso:country":"CN",
    "name:zho_x_preferred":[
        "\u53cc\u6865\u5b50\u6751"
    ],
    "wof:name":"Shuangqiaozicun",
    "wof:placetype":"locality"
},
  "geometry": {"coordinates":[129.43226000000001,44.41533],"type":"Point"}
}