{
  "type": "Feature",
  "properties": {
    "gn:admin1_code":"9.0",
    "gn:asciiname":"Luoluogou",
    "gn:country_code":"CN",
    "gn:dem":552,
    "gn:feature_class":"P",
    "gn:feature_code":"PPL",
    "gn:name":"Luoluogou",
    "gn:population":0,
    "gn:timezone":"Asia/Shanghai",
    "iso:country":"CN",
    "name:zho_x_preferred":[
        "\u7f57\u7f57\u6c9f"
    ],
    "wof:name":"Luoluogou",
    "wof:placetype":"locality"
},
  "geometry": {"coordinates":[111.89564,34.14488],"type":"Point"}
}