{
  "type": "Feature",
  "properties": {
    "gn:admin1_code":"1.0",
    "gn:asciiname":"Huadengcun",
    "gn:country_code":"CN",
    "gn:dem":50,
    "gn:feature_class":"P",
    "gn:feature_code":"PPL",
    "gn:name":"Huadengcun",
    "gn:population":0,
    "gn:timezone":"Asia/Shanghai",
    "iso:country":"CN",
    "name:zho_x_preferred":[
        "\u82b1\u706f\u6751"
    ],
    "wof:name":"Huadengcun",
    "wof:placetype":"locality"
},
  "geometry": {"coordinates":[117.40167,31.9939],"type":"Point"}
}