{
  "type": "Feature",
  "properties": {
    "gn:admin1_code":"26.0",
    "gn:asciiname":"Nianfangtan",
    "gn:country_code":"CN",
    "gn:dem":1215,
    "gn:feature_class":"P",
    "gn:feature_code":"PPL",
    "gn:name":"Nianfangtan",
    "gn:population":0,
    "gn:timezone":"Asia/Shanghai",
    "iso:country":"CN",
    "name:zho_x_preferred":[
        "\u78be\u623f\u6ee9"
    ],
    "wof:name":"Nianfangtan",
    "wof:placetype":"locality"
},
  "geometry": {"coordinates":[109.73393,38.55076],"type":"Point"}
}