{
  "type": "Feature",
  "properties": {
    "gn:admin1_code":"2.0",
    "gn:asciiname":"Yongjiang",
    "gn:country_code":"CN",
    "gn:dem":4,
    "gn:feature_class":"P",
    "gn:feature_code":"PPLA4",
    "gn:name":"Yongjiang",
    "gn:population":0,
    "gn:timezone":"Asia/Shanghai",
    "iso:country":"CN",
    "name:und_x_variant":[
        "Yongjiang Zhen",
        "Yongjiang"
    ],
    "name:zho_x_preferred":[
        "\u752c\u6c5f"
    ],
    "name:zho_x_variant":[
        "\u752c\u6c5f\u9547"
    ],
    "wof:name":"Yongjiang",
    "wof:placetype":"locality"
},
  "geometry": {"coordinates":[121.57865,29.90387],"type":"Point"}
}