{
  "type": "Feature",
  "properties": {
    "gn:admin1_code":"10",
    "gn:asciiname":"Qianshuiquan",
    "gn:country_code":"CN",
    "gn:dem":1387,
    "gn:feature_class":"P",
    "gn:feature_code":"PPL",
    "gn:name":"Qianshuiquan",
    "gn:population":0,
    "gn:timezone":"Asia/Shanghai",
    "iso:country":"CN",
    "name:zho_x_preferred":[
        "\u524d\u6c34\u6cc9"
    ],
    "wof:name":"Qianshuiquan",
    "wof:placetype":"locality"
},
  "geometry": {"coordinates":[115.74509999999999,41.77116],"type":"Point"}
}