{
  "type": "Feature",
  "properties": {
    "gn:admin1_code":"5.0",
    "gn:asciiname":"Qianhongshila",
    "gn:country_code":"CN",
    "gn:dem":174,
    "gn:feature_class":"P",
    "gn:feature_code":"PPL",
    "gn:name":"Qianhongshila",
    "gn:population":0,
    "gn:timezone":"Asia/Shanghai",
    "iso:country":"CN",
    "name:zho_x_preferred":[
        "\u524d\u7ea2\u77f3\u782c"
    ],
    "wof:name":"Qianhongshila",
    "wof:placetype":"locality"
},
  "geometry": {"coordinates":[126.66515,45.03297],"type":"Point"}
}