{
  "type": "Feature",
  "properties": {
    "gn:admin1_code":"26.0",
    "gn:asciiname":"Wangmangzhai",
    "gn:country_code":"CN",
    "gn:dem":594,
    "gn:feature_class":"P",
    "gn:feature_code":"PPL",
    "gn:name":"Wangmangzhai",
    "gn:population":0,
    "gn:timezone":"Asia/Shanghai",
    "iso:country":"CN",
    "name:zho_x_preferred":[
        "\u738b\u83bd\u5be8"
    ],
    "wof:name":"Wangmangzhai",
    "wof:placetype":"locality"
},
  "geometry": {"coordinates":[109.65419,35.2929],"type":"Point"}
}