{
  "type": "Feature",
  "properties": {
    "gn:admin1_code":"19.0",
    "gn:asciiname":"Yiquan",
    "gn:cc2":"CN",
    "gn:country_code":"CN",
    "gn:dem":4,
    "gn:feature_class":"P",
    "gn:feature_code":"PPL",
    "gn:name":"Yiquan",
    "gn:population":0,
    "gn:timezone":"Asia/Shanghai",
    "iso:country":"CN",
    "name:ast_x_preferred":[
        "Yiquan"
    ],
    "name:deu_x_preferred":[
        "Yiquan"
    ],
    "name:ita_x_preferred":[
        "Yiquan"
    ],
    "name:nld_x_preferred":[
        "Yi Quan"
    ],
    "name:pol_x_preferred":[
        "Yiquan"
    ],
    "name:por_x_preferred":[
        "I-chuan"
    ],
    "name:rus_x_preferred":[
        "\u0418\u0446\u044e\u0430\u043d\u044c"
    ],
    "name:ukr_x_preferred":[
        "\u0407\u0446\u044e\u0430\u043d\u044c"
    ],
    "name:und_x_variant":[
        "Xiaoyiquan",
        "Hsiao-i-tzu-ch\u2019\u00fcan"
    ],
    "wof:name":"Yiquan",
    "wof:placetype":"locality"
},
  "geometry": {"coordinates":[123.77889,39.90028],"type":"Point"}
}