{
  "type": "Feature",
  "properties": {
    "gn:admin1_code":"19.0",
    "gn:asciiname":"Yiquan",
    "gn:cc2":"CN",
    "gn:country_code":"CN",
    "gn:dem":4,
    "gn:feature_class":"P",
    "gn:feature_code":"PPL",
    "gn:name":"Yiquan",
    "gn:population":0,
    "gn:timezone":"Asia/Shanghai",
    "iso:country":"CN",
    "name:und_x_variant":[
        "Xiaoyiquan",
        "Hsiao-i-tzu-ch\u2019\u00fcan",
        "Yiquan"
    ],
    "wof:name":"Yiquan",
    "wof:placetype":"locality"
},
  "geometry": {"coordinates":[123.77889,39.90028],"type":"Point"}
}