{
  "type": "Feature",
  "properties": {
    "gn:admin1_code":"32.0",
    "gn:asciiname":"Sesehe",
    "gn:country_code":"CN",
    "gn:dem":2673,
    "gn:feature_class":"P",
    "gn:feature_code":"PPL",
    "gn:name":"Sesehe",
    "gn:population":0,
    "gn:timezone":"Asia/Shanghai",
    "iso:country":"CN",
    "name:zho_x_preferred":[
        "\u8272\u8272\u5408"
    ],
    "wof:name":"Sesehe",
    "wof:placetype":"locality"
},
  "geometry": {"coordinates":[102.718,28.4595],"type":"Point"}
}