{
  "type": "Feature",
  "properties": {
    "gn:admin1_code":"24.0",
    "gn:asciiname":"Xialichuan",
    "gn:country_code":"CN",
    "gn:dem":832,
    "gn:feature_class":"P",
    "gn:feature_code":"PPL",
    "gn:name":"Xialichuan",
    "gn:population":0,
    "gn:timezone":"Asia/Shanghai",
    "iso:country":"CN",
    "name:zho_x_preferred":[
        "\u4e0b\u7281\u5ddd"
    ],
    "wof:name":"Xialichuan",
    "wof:placetype":"locality"
},
  "geometry": {"coordinates":[112.74573999999998,35.36963],"type":"Point"}
}