{
  "type": "Feature",
  "properties": {
    "gn:admin1_code":"33.0",
    "gn:asciiname":"Linjiang",
    "gn:country_code":"CN",
    "gn:dem":464,
    "gn:feature_class":"P",
    "gn:feature_code":"PPL",
    "gn:name":"Linjiang",
    "gn:population":0,
    "gn:timezone":"Asia/Shanghai",
    "iso:country":"CN",
    "name:zho_x_preferred":[
        "\u4e34\u6c5f"
    ],
    "wof:name":"Linjiang",
    "wof:placetype":"locality"
},
  "geometry": {"coordinates":[109.00333999999999,30.95617],"type":"Point"}
}