{
  "type": "Feature",
  "properties": {
    "gn:admin1_code":"10",
    "gn:asciiname":"Shuangnaobao",
    "gn:country_code":"CN",
    "gn:dem":1423,
    "gn:feature_class":"P",
    "gn:feature_code":"PPL",
    "gn:name":"Shuangnaobao",
    "gn:population":0,
    "gn:timezone":"Asia/Shanghai",
    "iso:country":"CN",
    "name:und_x_variant":[
        "Shuang-nao-pao",
        "Shuangnaobao"
    ],
    "name:zho_x_preferred":[
        "\u53cc\u8111\u5305"
    ],
    "wof:name":"Shuangnaobao",
    "wof:placetype":"locality"
},
  "geometry": {"coordinates":[115.80894000000001,41.62621],"type":"Point"}
}