{
  "type": "Feature",
  "properties": {
    "gn:admin1_code":"14.0",
    "gn:asciiname":"Moba",
    "gn:country_code":"CN",
    "gn:dem":4284,
    "gn:feature_class":"P",
    "gn:feature_code":"PPL",
    "gn:name":"Moba",
    "gn:population":0,
    "gn:timezone":"Asia/Urumqi",
    "iso:country":"CN",
    "name:bod_x_preferred":[
        "Moba"
    ],
    "name:zho_x_preferred":[
        "Muba"
    ],
    "name:zho_x_variant":[
        "\u6728\u5df4"
    ],
    "wof:name":"Moba",
    "wof:placetype":"locality"
},
  "geometry": {"coordinates":[97.303,31.103],"type":"Point"}
}