{
  "type": "Feature",
  "properties": {
    "gn:admin1_code":"14.0",
    "gn:asciiname":"Moba",
    "gn:country_code":"CN",
    "gn:dem":4284,
    "gn:feature_class":"P",
    "gn:feature_code":"PPL",
    "gn:name":"Moba",
    "gn:population":0,
    "gn:timezone":"Asia/Urumqi",
    "iso:country":"CN",
    "name:ben_x_preferred":[
        "\u09ae\u09cb\u09ac\u09be"
    ],
    "name:bod_x_preferred":[
        "Moba"
    ],
    "name:ceb_x_preferred":[
        "Moba"
    ],
    "name:deu_x_preferred":[
        "Moba"
    ],
    "name:fas_x_preferred":[
        "\u0645\u0648\u0628\u0627"
    ],
    "name:fra_x_preferred":[
        "Moba"
    ],
    "name:heb_x_preferred":[
        "\u05de\u05d5\u05d1\u05d4"
    ],
    "name:hin_x_preferred":[
        "\u092e\u094b\u092c\u093e"
    ],
    "name:hun_x_preferred":[
        "Moba"
    ],
    "name:ind_x_preferred":[
        "Moba"
    ],
    "name:ita_x_preferred":[
        "Moba"
    ],
    "name:kor_x_preferred":[
        "\ubaa8\ubc14"
    ],
    "name:nld_x_preferred":[
        "Moba"
    ],
    "name:ron_x_preferred":[
        "Moba"
    ],
    "name:rus_x_preferred":[
        "MOBA"
    ],
    "name:spa_x_preferred":[
        "Moba"
    ],
    "name:swe_x_preferred":[
        "Moba"
    ],
    "name:tur_x_preferred":[
        "Moba"
    ],
    "name:urd_x_preferred":[
        "\u0645\u0648\u0628\u0627"
    ],
    "name:vie_x_preferred":[
        "Moba"
    ],
    "name:zho_x_preferred":[
        "Muba"
    ],
    "name:zho_x_variant":[
        "\u6728\u5df4"
    ],
    "wof:name":"Moba",
    "wof:placetype":"locality"
},
  "geometry": {"coordinates":[97.303,31.103],"type":"Point"}
}