{
  "type": "Feature",
  "properties": {
    "gn:admin1_code":"32.0",
    "gn:asciiname":"Jielongqiao",
    "gn:country_code":"CN",
    "gn:dem":387,
    "gn:feature_class":"P",
    "gn:feature_code":"PPL",
    "gn:name":"Jielongqiao",
    "gn:population":0,
    "gn:timezone":"Asia/Shanghai",
    "iso:country":"CN",
    "name:zho_x_preferred":[
        "\u63a5\u9f99\u6865"
    ],
    "wof:name":"Jielongqiao",
    "wof:placetype":"locality"
},
  "geometry": {"coordinates":[104.76832,30.39907],"type":"Point"}
}