{
  "type": "Feature",
  "properties": {
    "gn:admin1_code":"32.0",
    "gn:asciiname":"Malaxia",
    "gn:country_code":"CN",
    "gn:dem":3148,
    "gn:feature_class":"P",
    "gn:feature_code":"PPL",
    "gn:name":"Malaxia",
    "gn:population":0,
    "gn:timezone":"Asia/Shanghai",
    "iso:country":"CN",
    "name:zho_x_preferred":[
        "\u9a6c\u62c9\u5477"
    ],
    "wof:name":"Malaxia",
    "wof:placetype":"locality"
},
  "geometry": {"coordinates":[102.57405,28.02807],"type":"Point"}
}