{
  "type": "Feature",
  "properties": {
    "gn:admin1_code":"29.0",
    "gn:asciiname":"Heyicheng",
    "gn:country_code":"CN",
    "gn:dem":1971,
    "gn:feature_class":"P",
    "gn:feature_code":"PPL",
    "gn:name":"Heyicheng",
    "gn:population":0,
    "gn:timezone":"Asia/Shanghai",
    "iso:country":"CN",
    "name:zho_x_preferred":[
        "\u6cb3\u77e3\u57ce"
    ],
    "wof:name":"Heyicheng",
    "wof:placetype":"locality"
},
  "geometry": {"coordinates":[100.151,25.8554],"type":"Point"}
}