{
  "type": "Feature",
  "properties": {
    "gn:admin1_code":"18",
    "gn:asciiname":"Guihua",
    "gn:country_code":"CN",
    "gn:dem":1385,
    "gn:feature_class":"P",
    "gn:feature_code":"PPL",
    "gn:name":"Guihua",
    "gn:population":0,
    "gn:timezone":"Asia/Shanghai",
    "iso:country":"CN",
    "name:ceb_x_preferred":[
        "Guihua"
    ],
    "name:deu_x_preferred":[
        "Guihua"
    ],
    "name:swe_x_preferred":[
        "Guihua"
    ],
    "name:zho_x_preferred":[
        "\u5f52\u5316"
    ],
    "wof:name":"Guihua",
    "wof:placetype":"locality"
},
  "geometry": {"coordinates":[105.432,27.2479],"type":"Point"}
}