{
  "type": "Feature",
  "properties": {
    "gn:admin1_code":"30.0",
    "gn:asciiname":"Chating",
    "gn:country_code":"CN",
    "gn:dem":53,
    "gn:feature_class":"P",
    "gn:feature_code":"PPL",
    "gn:name":"Chating",
    "gn:population":0,
    "gn:timezone":"Asia/Shanghai",
    "iso:country":"CN",
    "name:zho_x_preferred":[
        "\u8336\u4ead"
    ],
    "name:zho_x_variant":[
        "\u8336\u4ead\u9547"
    ],
    "wof:name":"Chating",
    "wof:placetype":"locality"
},
  "geometry": {"coordinates":[111.77381,23.19863],"type":"Point"}
}