{
  "type": "Feature",
  "properties": {
    "gn:admin1_code":"7.0",
    "gn:asciiname":"Laicuo",
    "gn:country_code":"CN",
    "gn:dem":71,
    "gn:feature_class":"P",
    "gn:feature_code":"PPL",
    "gn:name":"Laicuo",
    "gn:population":0,
    "gn:timezone":"Asia/Shanghai",
    "iso:country":"CN",
    "name:zho_x_preferred":[
        "\u6fd1\u539d"
    ],
    "wof:name":"Laicuo",
    "wof:placetype":"locality"
},
  "geometry": {"coordinates":[118.88011000000002,25.39971],"type":"Point"}
}