{
  "type": "Feature",
  "properties": {
    "gn:admin1_code":"04",
    "gn:asciiname":"Cuizhai",
    "gn:country_code":"CN",
    "gn:dem":40,
    "gn:feature_class":"P",
    "gn:feature_code":"PPL",
    "gn:name":"Cuizhai",
    "gn:population":0,
    "gn:timezone":"Asia/Shanghai",
    "iso:country":"CN",
    "name:zho_x_preferred":[
        "\u5d14\u5be8"
    ],
    "wof:name":"Cuizhai",
    "wof:placetype":"locality"
},
  "geometry": {"coordinates":[116.98090000000001,34.57349],"type":"Point"}
}