{
  "type": "Feature",
  "properties": {
    "gn:admin1_code":"29.0",
    "gn:asciiname":"Analuo",
    "gn:country_code":"CN",
    "gn:dem":2980,
    "gn:feature_class":"P",
    "gn:feature_code":"PPL",
    "gn:name":"Analuo",
    "gn:population":0,
    "gn:timezone":"Asia/Shanghai",
    "iso:country":"CN",
    "name:zho_x_preferred":[
        "\u963f\u7eb3\u6d1b"
    ],
    "wof:name":"Analuo",
    "wof:placetype":"locality"
},
  "geometry": {"coordinates":[100.134,27.6025],"type":"Point"}
}