{
  "type": "Feature",
  "properties": {
    "gn:admin1_code":"29.0",
    "gn:asciiname":"Jibaibai",
    "gn:country_code":"CN",
    "gn:dem":1758,
    "gn:feature_class":"P",
    "gn:feature_code":"PPL",
    "gn:name":"Jibaibai",
    "gn:population":0,
    "gn:timezone":"Asia/Shanghai",
    "iso:country":"CN",
    "name:zho_x_preferred":[
        "\u673a\u767d\u767d"
    ],
    "wof:name":"Jibaibai",
    "wof:placetype":"locality"
},
  "geometry": {"coordinates":[103.97,24.2318],"type":"Point"}
}