{
  "type": "Feature",
  "properties": {
    "gn:admin1_code":"7.0",
    "gn:asciiname":"Xiangxi",
    "gn:country_code":"CN",
    "gn:dem":947,
    "gn:feature_class":"P",
    "gn:feature_code":"PPL",
    "gn:name":"Xiangxi",
    "gn:population":0,
    "gn:timezone":"Asia/Shanghai",
    "iso:country":"CN",
    "name:zho_x_preferred":[
        "\u9999\u6eaa"
    ],
    "wof:name":"Xiangxi",
    "wof:placetype":"locality"
},
  "geometry": {"coordinates":[119.19517999999999,27.30791],"type":"Point"}
}