{
  "type": "Feature",
  "properties": {
    "gn:admin1_code":"19.0",
    "gn:asciiname":"Yihetun",
    "gn:country_code":"CN",
    "gn:dem":134,
    "gn:feature_class":"P",
    "gn:feature_code":"PPL",
    "gn:name":"Yihetun",
    "gn:population":0,
    "gn:timezone":"Asia/Shanghai",
    "iso:country":"CN",
    "name:zho_x_preferred":[
        "\u4e49\u548c\u5c6f"
    ],
    "wof:name":"Yihetun",
    "wof:placetype":"locality"
},
  "geometry": {"coordinates":[121.899,41.8341],"type":"Point"}
}