{
  "type": "Feature",
  "properties": {
    "gn:admin1_code":"20",
    "gn:asciiname":"Har Huxu",
    "gn:country_code":"CN",
    "gn:dem":1248,
    "gn:feature_class":"P",
    "gn:feature_code":"PPL",
    "gn:name":"Har Huxu",
    "gn:population":0,
    "gn:timezone":"Asia/Shanghai",
    "iso:country":"CN",
    "wof:name":"Har Huxu",
    "wof:placetype":"locality"
},
  "geometry": {"coordinates":[116.90000000000001,43.36667],"type":"Point"}
}