{
  "type": "Feature",
  "properties": {
    "gn:admin1_code":"08",
    "gn:asciiname":"Qixinggang",
    "gn:cc2":"CN",
    "gn:country_code":"CN",
    "gn:dem":57,
    "gn:feature_class":"P",
    "gn:feature_code":"PPL",
    "gn:name":"Qixinggang",
    "gn:population":0,
    "gn:timezone":"Asia/Shanghai",
    "iso:country":"CN",
    "name:eng_x_preferred":[
        "Qixinggang"
    ],
    "name:rus_x_preferred":[
        "\u0426\u0438\u0441\u0438\u043d\u0433\u0430\u043d"
    ],
    "name:und_x_variant":[
        "Ch\u2019i-li-kang",
        "Ch\u2019i-hsing-kang"
    ],
    "wof:name":"Qixinggang",
    "wof:placetype":"locality"
},
  "geometry": {"coordinates":[132.78333000000001,47.18333],"type":"Point"}
}