{
  "type": "Feature",
  "properties": {
    "gn:admin1_code":"29.0",
    "gn:asciiname":"Tianhe",
    "gn:country_code":"CN",
    "gn:dem":1961,
    "gn:feature_class":"P",
    "gn:feature_code":"PPL",
    "gn:name":"Tianhe",
    "gn:population":0,
    "gn:timezone":"Asia/Shanghai",
    "iso:country":"CN",
    "name:ceb_x_preferred":[
        "Tianhe"
    ],
    "name:deu_x_preferred":[
        "Tianhe"
    ],
    "name:fra_x_preferred":[
        "Tianhe"
    ],
    "name:rus_x_preferred":[
        "\u0422\u044f\u043d\u044c\u0445\u044d"
    ],
    "name:und_x_variant":[
        "\u7530\u5408"
    ],
    "wof:name":"Tianhe",
    "wof:placetype":"locality"
},
  "geometry": {"coordinates":[103.5566,27.25934],"type":"Point"}
}