{
  "type": "Feature",
  "properties": {
    "gn:admin1_code":"4.0",
    "gn:asciiname":"Xintan Sanzu",
    "gn:country_code":"CN",
    "gn:dem":1,
    "gn:feature_class":"P",
    "gn:feature_code":"PPLF",
    "gn:name":"Xintan Sanzu",
    "gn:population":0,
    "gn:timezone":"Asia/Shanghai",
    "iso:country":"CN",
    "name:zho_x_preferred":[
        "\u65b0\u6ee9\u4e09\u7ec4"
    ],
    "wof:name":"Xintan Sanzu",
    "wof:placetype":"locality"
},
  "geometry": {"coordinates":[120.39100000000001,33.5898],"type":"Point"}
}