{
  "type": "Feature",
  "properties": {
    "gn:admin1_code":"7",
    "gn:asciiname":"Kujian",
    "gn:country_code":"CN",
    "gn:dem":338,
    "gn:feature_class":"P",
    "gn:feature_code":"PPL",
    "gn:name":"Kujian",
    "gn:population":0,
    "gn:timezone":"Asia/Shanghai",
    "iso:country":"CN",
    "name:zho_x_preferred":[
        "\u67af\u5c16"
    ],
    "wof:name":"Kujian",
    "wof:placetype":"locality"
},
  "geometry": {"coordinates":[118.64610999999999,25.82694],"type":"Point"}
}