{
  "type": "Feature",
  "properties": {
    "gn:admin1_code":"9.0",
    "gn:asciiname":"Jianglaozhuang",
    "gn:country_code":"CN",
    "gn:dem":140,
    "gn:feature_class":"P",
    "gn:feature_code":"PPL",
    "gn:name":"Jianglaozhuang",
    "gn:population":0,
    "gn:timezone":"Asia/Shanghai",
    "iso:country":"CN",
    "name:zho_x_preferred":[
        "\u59dc\u8001\u5e84"
    ],
    "wof:name":"Jianglaozhuang",
    "wof:placetype":"locality"
},
  "geometry": {"coordinates":[112.22914,32.89737],"type":"Point"}
}