{
  "type": "Feature",
  "properties": {
    "gn:admin1_code":"8.0",
    "gn:asciiname":"Chenjiashan",
    "gn:country_code":"CN",
    "gn:dem":274,
    "gn:feature_class":"P",
    "gn:feature_code":"PPL",
    "gn:name":"Chenjiashan",
    "gn:population":0,
    "gn:timezone":"Asia/Shanghai",
    "iso:country":"CN",
    "name:zho_x_preferred":[
        "\u9648\u7532\u5c71"
    ],
    "wof:name":"Chenjiashan",
    "wof:placetype":"locality"
},
  "geometry": {"coordinates":[125.12858,48.25798],"type":"Point"}
}