{
  "type": "Feature",
  "properties": {
    "gn:admin1_code":"16.0",
    "gn:asciiname":"Banxiu",
    "gn:country_code":"CN",
    "gn:dem":466,
    "gn:feature_class":"P",
    "gn:feature_code":"PPL",
    "gn:name":"Banxiu",
    "gn:population":0,
    "gn:timezone":"Asia/Shanghai",
    "iso:country":"CN",
    "name:zho_x_preferred":[
        "\u677f\u79c0"
    ],
    "wof:name":"Banxiu",
    "wof:placetype":"locality"
},
  "geometry": {"coordinates":[107.39400000000001,25.0535],"type":"Point"}
}