{
  "type": "Feature",
  "properties": {
    "gn:admin1_code":"2.0",
    "gn:asciiname":"Tang'an",
    "gn:country_code":"CN",
    "gn:dem":343,
    "gn:feature_class":"P",
    "gn:feature_code":"PPL",
    "gn:name":"Tang\u2019an",
    "gn:population":0,
    "gn:timezone":"Asia/Shanghai",
    "iso:country":"CN",
    "name:und_x_variant":[
        "Tang\u2019an"
    ],
    "name:zho_x_preferred":[
        "\u5858\u5cb8"
    ],
    "wof:name":"Tang'an",
    "wof:placetype":"locality"
},
  "geometry": {"coordinates":[120.22533,28.60804000000001],"type":"Point"}
}