{
  "type": "Feature",
  "properties": {
    "gn:admin1_code":"24.0",
    "gn:asciiname":"Nanwashan",
    "gn:country_code":"CN",
    "gn:dem":988,
    "gn:feature_class":"P",
    "gn:feature_code":"PPL",
    "gn:name":"Nanwashan",
    "gn:population":0,
    "gn:timezone":"Asia/Shanghai",
    "iso:country":"CN",
    "name:zho_x_preferred":[
        "\u5357\u7a8a\u5c71"
    ],
    "wof:name":"Nanwashan",
    "wof:placetype":"locality"
},
  "geometry": {"coordinates":[111.50251000000002,36.8905],"type":"Point"}
}