{
  "type": "Feature",
  "properties": {
    "gn:admin1_code":"2.0",
    "gn:asciiname":"Gaofan",
    "gn:country_code":"CN",
    "gn:dem":182,
    "gn:feature_class":"P",
    "gn:feature_code":"PPL",
    "gn:name":"Gaofan",
    "gn:population":0,
    "gn:timezone":"Asia/Shanghai",
    "iso:country":"CN",
    "name:zho_x_preferred":[
        "\u9ad8\u7548"
    ],
    "wof:name":"Gaofan",
    "wof:placetype":"locality"
},
  "geometry": {"coordinates":[119.64037999999999,28.83232000000001],"type":"Point"}
}