{
  "type": "Feature",
  "properties": {
    "gn:admin1_code":"14.0",
    "gn:asciiname":"Zhongguo",
    "gn:country_code":"CN",
    "gn:dem":3380,
    "gn:feature_class":"P",
    "gn:feature_code":"PPL",
    "gn:name":"Zhongguo",
    "gn:population":0,
    "gn:timezone":"Asia/Urumqi",
    "iso:country":"CN",
    "name:zho_x_preferred":[
        "\u4ef2\u679c"
    ],
    "wof:name":"Zhongguo",
    "wof:placetype":"locality"
},
  "geometry": {"coordinates":[94.72799000000001,29.77092],"type":"Point"}
}