{
  "type": "Feature",
  "properties": {
    "gn:admin1_code":"08",
    "gn:asciiname":"Huamin",
    "gn:country_code":"CN",
    "gn:dem":151,
    "gn:feature_class":"P",
    "gn:feature_code":"PPLA4",
    "gn:name":"Huamin",
    "gn:population":0,
    "gn:timezone":"Asia/Shanghai",
    "iso:country":"CN",
    "name:und_x_variant":[
        "Huamin Xiang"
    ],
    "name:zho_x_preferred":[
        "\u534e\u6c11"
    ],
    "name:zho_x_variant":[
        "\u534e\u6c11\u4e61"
    ],
    "wof:name":"Huamin",
    "wof:placetype":"locality"
},
  "geometry": {"coordinates":[123.45314999999999,47.12316],"type":"Point"}
}