{
  "type": "Feature",
  "properties": {
    "gn:admin1_code":"4.0",
    "gn:asciiname":"Duanjiaqiao",
    "gn:country_code":"CN",
    "gn:dem":5,
    "gn:feature_class":"P",
    "gn:feature_code":"PPL",
    "gn:name":"Duanjiaqiao",
    "gn:population":0,
    "gn:timezone":"Asia/Shanghai",
    "iso:country":"CN",
    "name:zho_x_preferred":[
        "\u6bb5\u5bb6\u6865"
    ],
    "wof:name":"Duanjiaqiao",
    "wof:placetype":"locality"
},
  "geometry": {"coordinates":[119.80719000000001,32.0988],"type":"Point"}
}