{
  "type": "Feature",
  "properties": {
    "gn:admin1_code":"18",
    "gn:asciiname":"Dalian",
    "gn:cc2":"CN",
    "gn:country_code":"CN",
    "gn:dem":1131,
    "gn:feature_class":"P",
    "gn:feature_code":"PPL",
    "gn:name":"Dalian",
    "gn:population":0,
    "gn:timezone":"Asia/Shanghai",
    "iso:country":"CN",
    "name:rus_x_preferred":[
        "\u0414\u0430\u043b\u044f\u043d\u044c"
    ],
    "name:und_x_variant":[
        "Ta-lien",
        "Dalian"
    ],
    "wof:name":"Dalian",
    "wof:placetype":"locality"
},
  "geometry": {"coordinates":[107.53333000000001,28.98333],"type":"Point"}
}