{
  "type": "Feature",
  "properties": {
    "gn:admin1_code":"13.0",
    "gn:asciiname":"Bositan Aigele",
    "gn:country_code":"CN",
    "gn:dem":1094,
    "gn:feature_class":"P",
    "gn:feature_code":"PPL",
    "gn:name":"Bositan Aigele",
    "gn:population":0,
    "gn:timezone":"Asia/Urumqi",
    "iso:country":"CN",
    "name:uig_x_preferred":[
        "Bostan Aigele"
    ],
    "name:zho_x_preferred":[
        "\u535a\u65af\u5766\u827e\u683c\u52d2"
    ],
    "wof:name":"Bositan Aigele",
    "wof:placetype":"locality"
},
  "geometry": {"coordinates":[86.06728000000003,38.55572],"type":"Point"}
}