{
  "type": "Feature",
  "properties": {
    "gn:admin1_code":"3.0",
    "gn:asciiname":"Xiangxing",
    "gn:country_code":"CN",
    "gn:dem":215,
    "gn:feature_class":"P",
    "gn:feature_code":"PPL",
    "gn:name":"Xiangxing",
    "gn:population":0,
    "gn:timezone":"Asia/Shanghai",
    "iso:country":"CN",
    "name:und_x_variant":[
        "\u8c61\u5f62"
    ],
    "wof:name":"Xiangxing",
    "wof:placetype":"locality"
},
  "geometry": {"coordinates":[115.36257000000001,26.7966],"type":"Point"}
}