{
  "type": "Feature",
  "properties": {
    "gn:admin1_code":"19.0",
    "gn:asciiname":"Erdaohezi Linchang",
    "gn:country_code":"CN",
    "gn:dem":128,
    "gn:feature_class":"P",
    "gn:feature_code":"PPLF",
    "gn:name":"Erdaohezi Linchang",
    "gn:population":0,
    "gn:timezone":"Asia/Shanghai",
    "iso:country":"CN",
    "name:zho_x_preferred":[
        "\u4e8c\u9053\u6cb3\u5b50\u6797\u573a"
    ],
    "wof:name":"Erdaohezi Linchang",
    "wof:placetype":"locality"
},
  "geometry": {"coordinates":[122.727,42.371],"type":"Point"}
}