{
  "type": "Feature",
  "properties": {
    "gn:admin1_code":"25",
    "gn:asciiname":"Lujiazhuang",
    "gn:country_code":"CN",
    "gn:dem":165,
    "gn:feature_class":"P",
    "gn:feature_code":"PPL",
    "gn:name":"Lujiazhuang",
    "gn:population":0,
    "gn:timezone":"Asia/Shanghai",
    "iso:country":"CN",
    "name:zho_x_preferred":[
        "\u8def\u5bb6\u5e84"
    ],
    "wof:name":"Lujiazhuang",
    "wof:placetype":"locality"
},
  "geometry": {"coordinates":[117.233,35.7942],"type":"Point"}
}