{
  "type": "Feature",
  "properties": {
    "gn:admin1_code":"7",
    "gn:asciiname":"Ma'angang",
    "gn:country_code":"CN",
    "gn:dem":643,
    "gn:feature_class":"P",
    "gn:feature_code":"PPL",
    "gn:name":"Ma\u2019angang",
    "gn:population":0,
    "gn:timezone":"Asia/Shanghai",
    "iso:country":"CN",
    "name:und_x_variant":[
        "Ma\u2019angang",
        "\u9a6c\u5b89\u5c97"
    ],
    "wof:name":"Ma'angang",
    "wof:placetype":"locality"
},
  "geometry": {"coordinates":[118.94,27.37611],"type":"Point"}
}