{
  "type": "Feature",
  "properties": {
    "gn:admin1_code":"24.0",
    "gn:asciiname":"Gejiashan",
    "gn:country_code":"CN",
    "gn:dem":1131,
    "gn:feature_class":"P",
    "gn:feature_code":"PPL",
    "gn:name":"Gejiashan",
    "gn:population":0,
    "gn:timezone":"Asia/Shanghai",
    "iso:country":"CN",
    "name:zho_x_preferred":[
        "\u845b\u5bb6\u5c71"
    ],
    "wof:name":"Gejiashan",
    "wof:placetype":"locality"
},
  "geometry": {"coordinates":[110.60835,36.93361],"type":"Point"}
}