{
  "type": "Feature",
  "properties": {
    "gn:admin1_code":"25",
    "gn:asciiname":"Lianhuachi Yicun",
    "gn:country_code":"CN",
    "gn:dem":45,
    "gn:feature_class":"P",
    "gn:feature_code":"PPL",
    "gn:name":"Lianhuachi Yicun",
    "gn:population":0,
    "gn:timezone":"Asia/Shanghai",
    "iso:country":"CN",
    "name:und_x_variant":[
        "Lianhuachi"
    ],
    "name:zho_x_preferred":[
        "\u83b2\u82b1\u6c60\u4e00\u6751"
    ],
    "wof:name":"Lianhuachi Yicun",
    "wof:placetype":"locality"
},
  "geometry": {"coordinates":[115.71599999999999,35.9733],"type":"Point"}
}