{
  "type": "Feature",
  "properties": {
    "gn:admin1_code":"8.0",
    "gn:asciiname":"Chengdongcun",
    "gn:country_code":"CN",
    "gn:dem":163,
    "gn:feature_class":"P",
    "gn:feature_code":"PPL",
    "gn:name":"Chengdongcun",
    "gn:population":0,
    "gn:timezone":"Asia/Shanghai",
    "iso:country":"CN",
    "name:zho_x_preferred":[
        "\u8bda\u4e1c\u6751"
    ],
    "wof:name":"Chengdongcun",
    "wof:placetype":"locality"
},
  "geometry": {"coordinates":[126.35105,45.3093],"type":"Point"}
}