{
  "type": "Feature",
  "properties": {
    "gn:admin1_code":"20.0",
    "gn:asciiname":"Ergongli",
    "gn:country_code":"CN",
    "gn:dem":627,
    "gn:feature_class":"P",
    "gn:feature_code":"PPL",
    "gn:name":"Ergongli",
    "gn:population":0,
    "gn:timezone":"Asia/Shanghai",
    "iso:country":"CN",
    "name:zho_x_preferred":[
        "\u4e8c\u516c\u91cc"
    ],
    "wof:name":"Ergongli",
    "wof:placetype":"locality"
},
  "geometry": {"coordinates":[121.98990000000001,48.68175],"type":"Point"}
}