{
  "type": "Feature",
  "properties": {
    "gn:admin1_code":"11.0",
    "gn:asciiname":"Wuyuan",
    "gn:country_code":"CN",
    "gn:dem":31,
    "gn:feature_class":"P",
    "gn:feature_code":"PPL",
    "gn:name":"Wuyuan",
    "gn:population":0,
    "gn:timezone":"Asia/Shanghai",
    "iso:country":"CN",
    "name:ceb_x_preferred":[
        "Wuyuan"
    ],
    "name:deu_x_preferred":[
        "Wuyuan"
    ],
    "name:fra_x_preferred":[
        "Wuyuan"
    ],
    "name:kor_x_preferred":[
        "\uc6b0\uc704\uc548\ud604"
    ],
    "name:nor_x_preferred":[
        "Wuyuan"
    ],
    "name:pol_x_preferred":[
        "Wuyuan"
    ],
    "name:rus_x_preferred":[
        "\u0423\u044e\u0430\u043d\u044c"
    ],
    "name:swe_x_preferred":[
        "Wuyuan"
    ],
    "name:zho_x_preferred":[
        "\u4e94\u57b8"
    ],
    "wof:name":"Wuyuan",
    "wof:placetype":"locality"
},
  "geometry": {"coordinates":[113.05501,29.42668],"type":"Point"}
}