{
  "type": "Feature",
  "properties": {
    "gn:admin1_code":"20.0",
    "gn:asciiname":"Zhenmaogou",
    "gn:country_code":"CN",
    "gn:dem":1273,
    "gn:feature_class":"P",
    "gn:feature_code":"PPL",
    "gn:name":"Zhenmaogou",
    "gn:population":0,
    "gn:timezone":"Asia/Shanghai",
    "iso:country":"CN",
    "name:und_x_variant":[
        "\u6b63\u5cc1\u6c9f"
    ],
    "wof:name":"Zhenmaogou",
    "wof:placetype":"locality"
},
  "geometry": {"coordinates":[111.51192,39.76073],"type":"Point"}
}