{
  "type": "Feature",
  "properties": {
    "gn:admin1_code":"24",
    "gn:asciiname":"Renyi",
    "gn:country_code":"CN",
    "gn:dem":770,
    "gn:feature_class":"P",
    "gn:feature_code":"PPL",
    "gn:name":"Renyi",
    "gn:population":0,
    "gn:timezone":"Asia/Shanghai",
    "iso:country":"CN",
    "name:und_x_variant":[
        "Jen-i",
        "Jen-i-chen",
        "Renyi"
    ],
    "name:zho_x_preferred":[
        "\u4ec1\u4e49"
    ],
    "wof:name":"Renyi",
    "wof:placetype":"locality"
},
  "geometry": {"coordinates":[111.76954000000001,36.74177],"type":"Point"}
}