{
  "type": "Feature",
  "properties": {
    "gn:admin1_code":"25.0",
    "gn:asciiname":"Xiyueshi",
    "gn:country_code":"CN",
    "gn:dem":60,
    "gn:feature_class":"P",
    "gn:feature_code":"PPL",
    "gn:name":"Xiyueshi",
    "gn:population":0,
    "gn:timezone":"Asia/Shanghai",
    "iso:country":"CN",
    "name:zho_x_preferred":[
        "\u897f\u5cb3\u77f3"
    ],
    "wof:name":"Xiyueshi",
    "wof:placetype":"locality"
},
  "geometry": {"coordinates":[119.87927000000001,36.98784000000001],"type":"Point"}
}