{
  "type": "Feature",
  "properties": {
    "gn:admin1_code":"30.0",
    "gn:asciiname":"Qiaobeicun",
    "gn:country_code":"CN",
    "gn:dem":140,
    "gn:feature_class":"P",
    "gn:feature_code":"PPL",
    "gn:name":"Qiaobeicun",
    "gn:population":0,
    "gn:timezone":"Asia/Shanghai",
    "iso:country":"CN",
    "name:zho_x_preferred":[
        "\u6865\u80cc\u6751"
    ],
    "wof:name":"Qiaobeicun",
    "wof:placetype":"locality"
},
  "geometry": {"coordinates":[116.40192999999999,24.70783],"type":"Point"}
}