{
  "type": "Feature",
  "properties": {
    "gn:admin1_code":"9.0",
    "gn:asciiname":"Fenduiwang",
    "gn:country_code":"CN",
    "gn:dem":154,
    "gn:feature_class":"P",
    "gn:feature_code":"PPL",
    "gn:name":"Fenduiwang",
    "gn:population":0,
    "gn:timezone":"Asia/Shanghai",
    "iso:country":"CN",
    "name:zho_x_preferred":[
        "\u7caa\u5806\u738b"
    ],
    "wof:name":"Fenduiwang",
    "wof:placetype":"locality"
},
  "geometry": {"coordinates":[113.0373,32.68308],"type":"Point"}
}