{
  "type": "Feature",
  "properties": {
    "gn:admin1_code":"5.0",
    "gn:asciiname":"Xinglongshancun",
    "gn:country_code":"CN",
    "gn:dem":145,
    "gn:feature_class":"P",
    "gn:feature_code":"PPL",
    "gn:name":"Xinglongshancun",
    "gn:population":0,
    "gn:timezone":"Asia/Shanghai",
    "iso:country":"CN",
    "name:zho_x_preferred":[
        "\u5174\u9686\u5c71\u6751"
    ],
    "wof:name":"Xinglongshancun",
    "wof:placetype":"locality"
},
  "geometry": {"coordinates":[123.01598,45.14593],"type":"Point"}
}