{
  "type": "Feature",
  "properties": {
    "gn:admin1_code":"29.0",
    "gn:asciiname":"Mijiazhuang",
    "gn:country_code":"CN",
    "gn:dem":2051,
    "gn:feature_class":"P",
    "gn:feature_code":"PPL",
    "gn:name":"Mijiazhuang",
    "gn:population":0,
    "gn:timezone":"Asia/Shanghai",
    "iso:country":"CN",
    "name:zho_x_preferred":[
        "\u7c73\u5bb6\u5e84"
    ],
    "wof:name":"Mijiazhuang",
    "wof:placetype":"locality"
},
  "geometry": {"coordinates":[103.645,25.6294],"type":"Point"}
}