{
  "type": "Feature",
  "properties": {
    "gn:admin1_code":"14.0",
    "gn:asciiname":"Xueba Nongchang Sanlian",
    "gn:country_code":"CN",
    "gn:dem":2993,
    "gn:feature_class":"P",
    "gn:feature_code":"PPLF",
    "gn:name":"Xueba Nongchang Sanlian",
    "gn:population":0,
    "gn:timezone":"Asia/Urumqi",
    "iso:country":"CN",
    "name:zho_x_preferred":[
        "\u96ea\u5df4\u519c\u573a\u4e09\u8fde"
    ],
    "wof:name":"Xueba Nongchang Sanlian",
    "wof:placetype":"locality"
},
  "geometry": {"coordinates":[94.37488999999999,29.64129],"type":"Point"}
}