{
  "type": "Feature",
  "properties": {
    "gn:admin1_code":"4.0",
    "gn:asciiname":"Xichenzhuangcun",
    "gn:country_code":"CN",
    "gn:dem":1,
    "gn:feature_class":"P",
    "gn:feature_code":"PPL",
    "gn:name":"Xichenzhuangcun",
    "gn:population":0,
    "gn:timezone":"Asia/Shanghai",
    "iso:country":"CN",
    "name:zho_x_preferred":[
        "\u897f\u9648\u5e84\u6751"
    ],
    "wof:name":"Xichenzhuangcun",
    "wof:placetype":"locality"
},
  "geometry": {"coordinates":[120.05571999999999,32.68829],"type":"Point"}
}