{
  "type": "Feature",
  "properties": {
    "gn:admin1_code":"30.0",
    "gn:asciiname":"Honggang",
    "gn:country_code":"CN",
    "gn:dem":5,
    "gn:feature_class":"P",
    "gn:feature_code":"PPL",
    "gn:name":"Honggang",
    "gn:population":0,
    "gn:timezone":"Asia/Shanghai",
    "iso:country":"CN",
    "name:zho_x_preferred":[
        "\u7d05\u5c97"
    ],
    "wof:name":"Honggang",
    "wof:placetype":"locality"
},
  "geometry": {"coordinates":[113.24348999999999,22.82692],"type":"Point"}
}