{
  "type": "Feature",
  "properties": {
    "gn:admin1_code":"33.0",
    "gn:asciiname":"Xiangzi",
    "gn:country_code":"CN",
    "gn:dem":336,
    "gn:feature_class":"P",
    "gn:feature_code":"PPL",
    "gn:name":"Xiangzi",
    "gn:population":0,
    "gn:timezone":"Asia/Shanghai",
    "iso:country":"CN",
    "name:zho_x_preferred":[
        "\u5df7\u5b50"
    ],
    "wof:name":"Xiangzi",
    "wof:placetype":"locality"
},
  "geometry": {"coordinates":[105.61622,29.48079],"type":"Point"}
}