{
  "type": "Feature",
  "properties": {
    "gn:admin1_code":"3",
    "gn:asciiname":"Lejia",
    "gn:country_code":"CN",
    "gn:dem":113,
    "gn:feature_class":"P",
    "gn:feature_code":"PPL",
    "gn:name":"Lejia",
    "gn:population":0,
    "gn:timezone":"Asia/Shanghai",
    "iso:country":"CN",
    "name:zho_x_preferred":[
        "\u4e50\u5bb6"
    ],
    "wof:name":"Lejia",
    "wof:placetype":"locality"
},
  "geometry": {"coordinates":[114.788,26.8373],"type":"Point"}
}