{
  "type": "Feature",
  "properties": {
    "gn:admin1_code":"2.0",
    "gn:asciiname":"Xin'anjiang",
    "gn:country_code":"CN",
    "gn:dem":49,
    "gn:feature_class":"P",
    "gn:feature_code":"PPLA3",
    "gn:name":"Xin\u2019anjiang",
    "gn:population":0,
    "gn:timezone":"Asia/Shanghai",
    "iso:country":"CN",
    "name:und_x_variant":[
        "Hsin-an-chiang",
        "Xin\u2019anjiang",
        "Xin\u2019anjiang Jiedao",
        "Jiande Shi"
    ],
    "name:zho_x_preferred":[
        "\u65b0\u5b89\u6c5f"
    ],
    "name:zho_x_variant":[
        "\u65b0\u5b89\u6c5f\u8857\u9053",
        "\u5efa\u5fb7\u5e02"
    ],
    "wof:name":"Xin'anjiang",
    "wof:placetype":"locality"
},
  "geometry": {"coordinates":[119.27148,29.47478],"type":"Point"}
}