{
  "type": "Feature",
  "properties": {
    "gn:admin1_code":"2.0",
    "gn:asciiname":"He'ao",
    "gn:country_code":"CN",
    "gn:dem":501,
    "gn:feature_class":"P",
    "gn:feature_code":"PPL",
    "gn:name":"He\u2019ao",
    "gn:population":0,
    "gn:timezone":"Asia/Shanghai",
    "iso:country":"CN",
    "name:und_x_variant":[
        "He\u2019ao"
    ],
    "name:zho_x_preferred":[
        "\u6cb3\u5c99"
    ],
    "wof:name":"He'ao",
    "wof:placetype":"locality"
},
  "geometry": {"coordinates":[119.17116,28.74218],"type":"Point"}
}