{
  "type": "Feature",
  "properties": {
    "gn:admin1_code":"16.0",
    "gn:asciiname":"Qiaolaocun",
    "gn:country_code":"CN",
    "gn:dem":270,
    "gn:feature_class":"P",
    "gn:feature_code":"PPL",
    "gn:name":"Qiaolaocun",
    "gn:population":0,
    "gn:timezone":"Asia/Shanghai",
    "iso:country":"CN",
    "name:zho_x_preferred":[
        "\u6865\u8001\u6751"
    ],
    "wof:name":"Qiaolaocun",
    "wof:placetype":"locality"
},
  "geometry": {"coordinates":[108.259,23.6694],"type":"Point"}
}