{
  "type": "Feature",
  "properties": {
    "gn:admin1_code":"7.0",
    "gn:asciiname":"Lingnancun",
    "gn:country_code":"CN",
    "gn:dem":790,
    "gn:feature_class":"P",
    "gn:feature_code":"PPL",
    "gn:name":"Lingnancun",
    "gn:population":0,
    "gn:timezone":"Asia/Shanghai",
    "iso:country":"CN",
    "name:zho_x_preferred":[
        "\u5cad\u5357\u6751"
    ],
    "wof:name":"Lingnancun",
    "wof:placetype":"locality"
},
  "geometry": {"coordinates":[118.93778,26.58389],"type":"Point"}
}