{
  "type": "Feature",
  "properties": {
    "gn:admin1_code":"08",
    "gn:asciiname":"Beigou",
    "gn:cc2":"CN",
    "gn:country_code":"CN",
    "gn:dem":365,
    "gn:feature_class":"P",
    "gn:feature_code":"PPL",
    "gn:name":"Beigou",
    "gn:population":0,
    "gn:timezone":"Asia/Shanghai",
    "iso:country":"CN",
    "name:und_x_variant":[
        "Pei-kou",
        "Beigou"
    ],
    "wof:name":"Beigou",
    "wof:placetype":"locality"
},
  "geometry": {"coordinates":[129.96666999999999,48.41667],"type":"Point"}
}