{
  "type": "Feature",
  "properties": {
    "gn:admin1_code":"25",
    "gn:asciiname":"Shibahu",
    "gn:country_code":"CN",
    "gn:dem":8,
    "gn:feature_class":"P",
    "gn:feature_code":"PPL",
    "gn:name":"Shibahu",
    "gn:population":0,
    "gn:timezone":"Asia/Shanghai",
    "iso:country":"CN",
    "name:zho_x_preferred":[
        "\u5341\u516b\u6237"
    ],
    "wof:name":"Shibahu",
    "wof:placetype":"locality"
},
  "geometry": {"coordinates":[118.63800000000001,37.6557],"type":"Point"}
}