{
  "type": "Feature",
  "properties": {
    "gn:admin1_code":"4.0",
    "gn:asciiname":"Sandai",
    "gn:country_code":"CN",
    "gn:dem":5,
    "gn:feature_class":"P",
    "gn:feature_code":"PPL",
    "gn:name":"Sandai",
    "gn:population":0,
    "gn:timezone":"Asia/Shanghai",
    "iso:country":"CN",
    "name:tam_x_preferred":[
        "\u0b9a\u0ba3\u0bcd\u0b9f\u0bc8"
    ],
    "name:zho_x_preferred":[
        "\u4e09\u5788"
    ],
    "wof:name":"Sandai",
    "wof:placetype":"locality"
},
  "geometry": {"coordinates":[120.15195,32.07424],"type":"Point"}
}