{
  "type": "Feature",
  "properties": {
    "gn:admin1_code":"25",
    "gn:asciiname":"Beizhaojia",
    "gn:country_code":"CN",
    "gn:dem":4,
    "gn:feature_class":"P",
    "gn:feature_code":"PPL",
    "gn:name":"Beizhaojia",
    "gn:population":0,
    "gn:timezone":"Asia/Shanghai",
    "iso:country":"CN",
    "name:zho_x_preferred":[
        "\u5317\u8d75\u5bb6"
    ],
    "wof:name":"Beizhaojia",
    "wof:placetype":"locality"
},
  "geometry": {"coordinates":[119.539,36.9833],"type":"Point"}
}