{
  "type": "Feature",
  "properties": {
    "gn:admin1_code":"14.0",
    "gn:asciiname":"Quguotangcun",
    "gn:country_code":"CN",
    "gn:dem":4135,
    "gn:feature_class":"P",
    "gn:feature_code":"PPL",
    "gn:name":"Quguotangcun",
    "gn:population":0,
    "gn:timezone":"Asia/Urumqi",
    "iso:country":"CN",
    "name:zho_x_preferred":[
        "\u66f2\u679c\u5510\u6751"
    ],
    "wof:name":"Quguotangcun",
    "wof:placetype":"locality"
},
  "geometry": {"coordinates":[92.28259,28.48837],"type":"Point"}
}