{
  "type": "Feature",
  "properties": {
    "gn:admin1_code":"19.0",
    "gn:asciiname":"Dashigou",
    "gn:country_code":"CN",
    "gn:dem":344,
    "gn:feature_class":"P",
    "gn:feature_code":"PPL",
    "gn:name":"Dashigou",
    "gn:population":0,
    "gn:timezone":"Asia/Shanghai",
    "iso:country":"CN",
    "name:zho_x_preferred":[
        "Dashigou"
    ],
    "name:zho_x_variant":[
        "\u6253\u77f3\u6c9f"
    ],
    "wof:name":"Dashigou",
    "wof:placetype":"locality"
},
  "geometry": {"coordinates":[124.5033,41.91004],"type":"Point"}
}