{
  "type": "Feature",
  "properties": {
    "gn:admin1_code":"12.0",
    "gn:asciiname":"Jinyinchong",
    "gn:country_code":"CN",
    "gn:dem":147,
    "gn:feature_class":"P",
    "gn:feature_code":"PPL",
    "gn:name":"Jinyinchong",
    "gn:population":0,
    "gn:timezone":"Asia/Shanghai",
    "iso:country":"CN",
    "name:zho_x_preferred":[
        "Jinyinchong"
    ],
    "name:zho_x_variant":[
        "\u91d1\u94f6\u51b2"
    ],
    "wof:name":"Jinyinchong",
    "wof:placetype":"locality"
},
  "geometry": {"coordinates":[111.25536,30.41035],"type":"Point"}
}