{
  "type": "Feature",
  "properties": {
    "gn:admin1_code":"25",
    "gn:asciiname":"Houxuezhuang",
    "gn:country_code":"CN",
    "gn:dem":160,
    "gn:feature_class":"P",
    "gn:feature_code":"PPL",
    "gn:name":"Houxuezhuang",
    "gn:population":0,
    "gn:timezone":"Asia/Shanghai",
    "iso:country":"CN",
    "name:zho_x_preferred":[
        "\u540e\u5b66\u5e84"
    ],
    "wof:name":"Houxuezhuang",
    "wof:placetype":"locality"
},
  "geometry": {"coordinates":[119.102,35.7195],"type":"Point"}
}