{
  "type": "Feature",
  "properties": {
    "gn:admin1_code":"11.0",
    "gn:asciiname":"Shipiwan",
    "gn:country_code":"CN",
    "gn:dem":104,
    "gn:feature_class":"P",
    "gn:feature_code":"PPL",
    "gn:name":"Shipiwan",
    "gn:population":0,
    "gn:timezone":"Asia/Shanghai",
    "iso:country":"CN",
    "name:zho_x_preferred":[
        "\u77f3\u76ae\u6e7e"
    ],
    "wof:name":"Shipiwan",
    "wof:placetype":"locality"
},
  "geometry": {"coordinates":[112.70305,28.06334],"type":"Point"}
}