{
  "type": "Feature",
  "properties": {
    "gn:admin1_code":"2.0",
    "gn:asciiname":"Xiacun",
    "gn:country_code":"CN",
    "gn:dem":27,
    "gn:feature_class":"P",
    "gn:feature_code":"PPL",
    "gn:name":"Xiacun",
    "gn:population":0,
    "gn:timezone":"Asia/Shanghai",
    "iso:country":"CN",
    "name:zho_x_preferred":[
        "\u971e\u6751"
    ],
    "wof:name":"Xiacun",
    "wof:placetype":"locality"
},
  "geometry": {"coordinates":[121.00949,28.24565],"type":"Point"}
}