{
  "type": "Feature",
  "properties": {
    "gn:admin1_code":"18.0",
    "gn:asciiname":"Kaitianpu",
    "gn:country_code":"CN",
    "gn:dem":584,
    "gn:feature_class":"P",
    "gn:feature_code":"PPL",
    "gn:name":"Kaitianpu",
    "gn:population":0,
    "gn:timezone":"Asia/Shanghai",
    "iso:country":"CN",
    "name:zho_x_preferred":[
        "\u5f00\u7530\u94fa"
    ],
    "wof:name":"Kaitianpu",
    "wof:placetype":"locality"
},
  "geometry": {"coordinates":[109.15900000000001,27.6434],"type":"Point"}
}