{
  "type": "Feature",
  "properties": {
    "gn:admin1_code":"2.0",
    "gn:asciiname":"Yinqiuwu",
    "gn:country_code":"CN",
    "gn:dem":134,
    "gn:feature_class":"P",
    "gn:feature_code":"PPL",
    "gn:name":"Yinqiuwu",
    "gn:population":0,
    "gn:timezone":"Asia/Shanghai",
    "iso:country":"CN",
    "name:und_x_variant":[
        "\u94f6\u7403\u575e"
    ],
    "wof:name":"Yinqiuwu",
    "wof:placetype":"locality"
},
  "geometry": {"coordinates":[119.61817000000001,30.16034],"type":"Point"}
}