{
  "type": "Feature",
  "properties": {
    "gn:admin1_code":"29.0",
    "gn:asciiname":"Lamaishi",
    "gn:country_code":"CN",
    "gn:dem":1693,
    "gn:feature_class":"P",
    "gn:feature_code":"PPL",
    "gn:name":"Lamaishi",
    "gn:population":0,
    "gn:timezone":"Asia/Shanghai",
    "iso:country":"CN",
    "name:zho_x_preferred":[
        "\u62c9\u9ea6\u77f3"
    ],
    "wof:name":"Lamaishi",
    "wof:placetype":"locality"
},
  "geometry": {"coordinates":[101.58,25.8921],"type":"Point"}
}