{
  "type": "Feature",
  "properties": {
    "gn:admin1_code":"22.0",
    "gn:asciiname":"Yushuyaocun",
    "gn:country_code":"CN",
    "gn:dem":490,
    "gn:feature_class":"P",
    "gn:feature_code":"PPL",
    "gn:name":"Yushuyaocun",
    "gn:population":0,
    "gn:timezone":"Asia/Shanghai",
    "iso:country":"CN",
    "name:zho_x_preferred":[
        "\u6986\u6811\u7a91\u6751"
    ],
    "wof:name":"Yushuyaocun",
    "wof:placetype":"locality"
},
  "geometry": {"coordinates":[115.70401,39.68586],"type":"Point"}
}