{
  "type": "Feature",
  "properties": {
    "gn:admin1_code":"25",
    "gn:asciiname":"Daili",
    "gn:country_code":"CN",
    "gn:dem":39,
    "gn:feature_class":"P",
    "gn:feature_code":"PPL",
    "gn:name":"Daili",
    "gn:population":0,
    "gn:timezone":"Asia/Shanghai",
    "iso:country":"CN",
    "name:zho_x_preferred":[
        "\u6234\u91cc"
    ],
    "wof:name":"Daili",
    "wof:placetype":"locality"
},
  "geometry": {"coordinates":[115.66968,36.60136],"type":"Point"}
}