{
  "type": "Feature",
  "properties": {
    "gn:admin1_code":"19.0",
    "gn:asciiname":"Langtoushang",
    "gn:country_code":"CN",
    "gn:dem":129,
    "gn:feature_class":"P",
    "gn:feature_code":"PPL",
    "gn:name":"Langtoushang",
    "gn:population":0,
    "gn:timezone":"Asia/Shanghai",
    "iso:country":"CN",
    "name:zho_x_preferred":[
        "\u6d6a\u5934\u4e0a"
    ],
    "wof:name":"Langtoushang",
    "wof:placetype":"locality"
},
  "geometry": {"coordinates":[125.673,40.7678],"type":"Point"}
}