{
  "type": "Feature",
  "properties": {
    "gn:admin1_code":"2.0",
    "gn:asciiname":"Qianjiashan",
    "gn:country_code":"CN",
    "gn:dem":68,
    "gn:feature_class":"P",
    "gn:feature_code":"PPL",
    "gn:name":"Qianjiashan",
    "gn:population":0,
    "gn:timezone":"Asia/Shanghai",
    "iso:country":"CN",
    "name:zho_x_preferred":[
        "\u94b1\u5bb6\u5c71"
    ],
    "wof:name":"Qianjiashan",
    "wof:placetype":"locality"
},
  "geometry": {"coordinates":[118.84569,28.95376],"type":"Point"}
}