{
  "type": "Feature",
  "properties": {
    "gn:admin1_code":"19.0",
    "gn:asciiname":"Shabaozicun",
    "gn:country_code":"CN",
    "gn:dem":6,
    "gn:feature_class":"P",
    "gn:feature_code":"PPL",
    "gn:name":"Shabaozicun",
    "gn:population":0,
    "gn:timezone":"Asia/Shanghai",
    "iso:country":"CN",
    "name:zho_x_preferred":[
        "\u6c99\u5305\u5b50\u6751"
    ],
    "wof:name":"Shabaozicun",
    "wof:placetype":"locality"
},
  "geometry": {"coordinates":[122.732,39.0296],"type":"Point"}
}