{
  "type": "Feature",
  "properties": {
    "gn:admin1_code":"02",
    "gn:asciiname":"Xiaojiaqiaocun",
    "gn:country_code":"CN",
    "gn:dem":3,
    "gn:feature_class":"P",
    "gn:feature_code":"PPL",
    "gn:name":"Xiaojiaqiaocun",
    "gn:population":0,
    "gn:timezone":"Asia/Shanghai",
    "iso:country":"CN",
    "name:und_x_variant":[
        "Xiaojiaqiao",
        "Xiaojiaqiaocun"
    ],
    "name:zho_x_preferred":[
        "\u8096\u6865"
    ],
    "name:zho_x_variant":[
        "\u8096\u5bb6\u6865",
        "\u8096\u5bb6\u6865\u6751"
    ],
    "wof:name":"Xiaojiaqiaocun",
    "wof:placetype":"locality"
},
  "geometry": {"coordinates":[121.48869999999999,28.45645],"type":"Point"}
}