{
  "type": "Feature",
  "properties": {
    "gn:country":"CN",
    "gn:fcode":"PPLA4",
    "gn:pop":1167,
    "iso:country":"CN",
    "name:unk_x_variant":[
        "Dasi Zhen"
    ],
    "name:zho_x_preferred":[
        "\u5927\u5bfa"
    ],
    "name:zho_x_variant":[
        "\u5927\u5bfa\u9547"
    ],
    "qs:name":"Dasi",
    "qs:photos_9r":0,
    "qs:photos_sr":0,
    "qs:pop_sr":"3",
    "wd:wordcount":140,
    "wof:name":"Dasi",
    "wof:placetype":"locality",
    "wof:population":1167
},
  "geometry": {"coordinates":[117.23768,39.01821],"type":"Point"}
}