{
  "type": "Feature",
  "properties": {
    "gn:admin1_code":"7",
    "gn:asciiname":"Yueju",
    "gn:country_code":"CN",
    "gn:dem":78,
    "gn:feature_class":"P",
    "gn:feature_code":"PPL",
    "gn:name":"Yueju",
    "gn:population":0,
    "gn:timezone":"Asia/Shanghai",
    "iso:country":"CN",
    "name:fra_x_preferred":[
        "Yueju"
    ],
    "name:und_x_variant":[
        "Y\u00fceh-ch\u00fc"
    ],
    "name:zho_x_preferred":[
        "\u6708\u4e3e"
    ],
    "wof:name":"Yueju",
    "wof:placetype":"locality"
},
  "geometry": {"coordinates":[119.70921,25.65857],"type":"Point"}
}