{
  "type": "Feature",
  "properties": {
    "gn:admin1_code":"1.0",
    "gn:asciiname":"Yuzhucun",
    "gn:country_code":"CN",
    "gn:dem":8,
    "gn:feature_class":"P",
    "gn:feature_code":"PPL",
    "gn:name":"Yuzhucun",
    "gn:population":0,
    "gn:timezone":"Asia/Shanghai",
    "iso:country":"CN",
    "name:zho_x_preferred":[
        "\u88d5\u73e0\u6751"
    ],
    "wof:name":"Yuzhucun",
    "wof:placetype":"locality"
},
  "geometry": {"coordinates":[118.27406999999999,31.43901],"type":"Point"}
}