{
  "type": "Feature",
  "properties": {
    "gn:admin1_code":"8.0",
    "gn:asciiname":"Xinchengcun",
    "gn:country_code":"CN",
    "gn:dem":215,
    "gn:feature_class":"P",
    "gn:feature_code":"PPL",
    "gn:name":"Xinchengcun",
    "gn:population":0,
    "gn:timezone":"Asia/Shanghai",
    "iso:country":"CN",
    "name:zho_x_preferred":[
        "\u65b0\u6210\u6751"
    ],
    "wof:name":"Xinchengcun",
    "wof:placetype":"locality"
},
  "geometry": {"coordinates":[127.77746,46.74532],"type":"Point"}
}