{
  "type": "Feature",
  "properties": {
    "gn:admin1_code":"12.0",
    "gn:asciiname":"Piandao Gou",
    "gn:country_code":"CN",
    "gn:dem":1051,
    "gn:feature_class":"P",
    "gn:feature_code":"PPL",
    "gn:name":"Piandao Gou",
    "gn:population":0,
    "gn:timezone":"Asia/Shanghai",
    "iso:country":"CN",
    "name:zho_x_preferred":[
        "Piandao Gou"
    ],
    "name:zho_x_variant":[
        "\u504f\u9053\u6c9f"
    ],
    "wof:name":"Piandao Gou",
    "wof:placetype":"locality"
},
  "geometry": {"coordinates":[109.71875,29.69576],"type":"Point"}
}