{
  "type": "Feature",
  "properties": {
    "gn:admin1_code":"11.0",
    "gn:asciiname":"Zoujianao",
    "gn:country_code":"CN",
    "gn:dem":510,
    "gn:feature_class":"P",
    "gn:feature_code":"PPL",
    "gn:name":"Zoujianao",
    "gn:population":0,
    "gn:timezone":"Asia/Shanghai",
    "iso:country":"CN",
    "name:zho_x_preferred":[
        "\u90b9\u5bb6\u57b4"
    ],
    "wof:name":"Zoujianao",
    "wof:placetype":"locality"
},
  "geometry": {"coordinates":[110.35630999999999,28.07763],"type":"Point"}
}