{
  "type": "Feature",
  "properties": {
    "gn:admin1_code":"16.0",
    "gn:asciiname":"Luopan",
    "gn:country_code":"CN",
    "gn:dem":225,
    "gn:feature_class":"P",
    "gn:feature_code":"PPL",
    "gn:name":"Luopan",
    "gn:population":0,
    "gn:timezone":"Asia/Shanghai",
    "iso:country":"CN",
    "name:zho_x_preferred":[
        "\u6d1b\u6f58"
    ],
    "wof:name":"Luopan",
    "wof:placetype":"locality"
},
  "geometry": {"coordinates":[109.492,25.4347],"type":"Point"}
}