{
  "type": "Feature",
  "properties": {
    "gn:admin1_code":"4.0",
    "gn:asciiname":"Huanglongxian",
    "gn:country_code":"CN",
    "gn:dem":64,
    "gn:feature_class":"P",
    "gn:feature_code":"PPL",
    "gn:name":"Huanglongxian",
    "gn:population":0,
    "gn:timezone":"Asia/Shanghai",
    "iso:country":"CN",
    "name:zho_x_preferred":[
        "\u9ec4\u9f99\u5c98"
    ],
    "wof:name":"Huanglongxian",
    "wof:placetype":"locality"
},
  "geometry": {"coordinates":[118.68317999999999,31.78134],"type":"Point"}
}