{
  "type": "Feature",
  "properties": {
    "gn:admin1_code":"24.0",
    "gn:asciiname":"Nanxinzhuang",
    "gn:country_code":"CN",
    "gn:dem":1417,
    "gn:feature_class":"P",
    "gn:feature_code":"PPL",
    "gn:name":"Nanxinzhuang",
    "gn:population":0,
    "gn:timezone":"Asia/Shanghai",
    "iso:country":"CN",
    "name:zho_x_preferred":[
        "\u5357\u8f9b\u5e84"
    ],
    "wof:name":"Nanxinzhuang",
    "wof:placetype":"locality"
},
  "geometry": {"coordinates":[111.94959,39.50817],"type":"Point"}
}