{
  "type": "Feature",
  "properties": {
    "gn:admin1_code":"14.0",
    "gn:asciiname":"Lawengwa",
    "gn:country_code":"CN",
    "gn:dem":3460,
    "gn:feature_class":"P",
    "gn:feature_code":"PPL",
    "gn:name":"Lawengwa",
    "gn:population":0,
    "gn:timezone":"Asia/Urumqi",
    "iso:country":"CN",
    "name:zho_x_preferred":[
        "\u62c9\u7fc1\u74e6"
    ],
    "wof:name":"Lawengwa",
    "wof:placetype":"locality"
},
  "geometry": {"coordinates":[97.80710999999999,30.56853],"type":"Point"}
}