{
  "type": "Feature",
  "properties": {
    "gn:admin1_code":"29.0",
    "gn:asciiname":"Baimushan",
    "gn:country_code":"CN",
    "gn:dem":1955,
    "gn:feature_class":"P",
    "gn:feature_code":"PPL",
    "gn:name":"Baimushan",
    "gn:population":0,
    "gn:timezone":"Asia/Shanghai",
    "iso:country":"CN",
    "name:zho_x_preferred":[
        "\u67cf\u6728\u5c71"
    ],
    "wof:name":"Baimushan",
    "wof:placetype":"locality"
},
  "geometry": {"coordinates":[99.8676,24.3594],"type":"Point"}
}