{
  "type": "Feature",
  "properties": {
    "gn:admin1_code":"32.0",
    "gn:asciiname":"Shuangguisi",
    "gn:country_code":"CN",
    "gn:dem":496,
    "gn:feature_class":"P",
    "gn:feature_code":"PPL",
    "gn:name":"Shuangguisi",
    "gn:population":0,
    "gn:timezone":"Asia/Shanghai",
    "iso:country":"CN",
    "name:zho_x_preferred":[
        "\u53cc\u6842\u5bfa"
    ],
    "wof:name":"Shuangguisi",
    "wof:placetype":"locality"
},
  "geometry": {"coordinates":[103.95520999999999,30.57642],"type":"Point"}
}