{
  "type": "Feature",
  "properties": {
    "gn:admin1_code":"8.0",
    "gn:asciiname":"Xianfeng",
    "gn:country_code":"CN",
    "gn:dem":445,
    "gn:feature_class":"P",
    "gn:feature_code":"PPL",
    "gn:name":"Xianfeng",
    "gn:population":0,
    "gn:timezone":"Asia/Shanghai",
    "iso:country":"CN",
    "name:ceb_x_preferred":[
        "Xianfeng"
    ],
    "name:deu_x_preferred":[
        "Xianfeng"
    ],
    "name:fra_x_preferred":[
        "Xianfeng"
    ],
    "name:nor_x_preferred":[
        "Xianfeng"
    ],
    "name:zho_x_preferred":[
        "\u5148\u950b"
    ],
    "wof:name":"Xianfeng",
    "wof:placetype":"locality"
},
  "geometry": {"coordinates":[128.77133000000001,47.4813],"type":"Point"}
}