{
  "type": "Feature",
  "properties": {
    "gn:admin1_code":"19.0",
    "gn:asciiname":"Houpangtun",
    "gn:country_code":"CN",
    "gn:dem":8,
    "gn:feature_class":"P",
    "gn:feature_code":"PPL",
    "gn:name":"Houpangtun",
    "gn:population":0,
    "gn:timezone":"Asia/Shanghai",
    "iso:country":"CN",
    "name:zho_x_preferred":[
        "\u540e\u5e9e\u5c6f"
    ],
    "wof:name":"Houpangtun",
    "wof:placetype":"locality"
},
  "geometry": {"coordinates":[120.166,40.1504],"type":"Point"}
}