{
  "type": "Feature",
  "properties": {
    "gn:admin1_code":"16.0",
    "gn:asciiname":"Tanglingkou",
    "gn:country_code":"CN",
    "gn:dem":140,
    "gn:feature_class":"P",
    "gn:feature_code":"PPL",
    "gn:name":"Tanglingkou",
    "gn:population":0,
    "gn:timezone":"Asia/Shanghai",
    "iso:country":"CN",
    "name:zho_x_preferred":[
        "\u5858\u5cad\u53e3"
    ],
    "wof:name":"Tanglingkou",
    "wof:placetype":"locality"
},
  "geometry": {"coordinates":[109.41,25.3267],"type":"Point"}
}