{
  "type": "Feature",
  "properties": {
    "gn:admin1_code":"32.0",
    "gn:asciiname":"Bieli",
    "gn:country_code":"CN",
    "gn:dem":1884,
    "gn:feature_class":"P",
    "gn:feature_code":"PPL",
    "gn:name":"Bieli",
    "gn:population":0,
    "gn:timezone":"Asia/Shanghai",
    "iso:country":"CN",
    "name:zho_x_preferred":[
        "\u522b\u7acb"
    ],
    "wof:name":"Bieli",
    "wof:placetype":"locality"
},
  "geometry": {"coordinates":[103.75700000000001,31.5764],"type":"Point"}
}