{
  "type": "Feature",
  "properties": {
    "gn:admin1_code":"30",
    "gn:asciiname":"Yanggutian",
    "gn:country_code":"CN",
    "gn:dem":119,
    "gn:feature_class":"P",
    "gn:feature_code":"PPL",
    "gn:name":"Yanggutian",
    "gn:population":0,
    "gn:timezone":"Asia/Shanghai",
    "iso:country":"CN",
    "name:zho_x_preferred":[
        "\u6d0b\u53e4\u7530"
    ],
    "wof:name":"Yanggutian",
    "wof:placetype":"locality"
},
  "geometry": {"coordinates":[116.38858999999999,24.06018],"type":"Point"}
}