{
  "type": "Feature",
  "properties": {
    "gn:admin1_code":"3.0",
    "gn:asciiname":"Hejiang",
    "gn:country_code":"CN",
    "gn:dem":539,
    "gn:feature_class":"P",
    "gn:feature_code":"PPL",
    "gn:name":"Hejiang",
    "gn:population":0,
    "gn:timezone":"Asia/Shanghai",
    "iso:country":"CN",
    "name:nor_x_preferred":[
        "Hejiang"
    ],
    "name:pol_x_preferred":[
        "Hejiang"
    ],
    "name:swe_x_preferred":[
        "Hejiang"
    ],
    "name:zho_x_preferred":[
        "\u6cb3\u6c5f"
    ],
    "wof:name":"Hejiang",
    "wof:placetype":"locality"
},
  "geometry": {"coordinates":[113.919,27.3913],"type":"Point"}
}