{
  "type": "Feature",
  "properties": {
    "gn:admin1_code":"11.0",
    "gn:asciiname":"Wangli Gongtang",
    "gn:country_code":"CN",
    "gn:dem":51,
    "gn:feature_class":"P",
    "gn:feature_code":"PPL",
    "gn:name":"Wangli Gongtang",
    "gn:population":0,
    "gn:timezone":"Asia/Shanghai",
    "iso:country":"CN",
    "name:zho_x_preferred":[
        "\u738b\u674e\u516c\u5802"
    ],
    "wof:name":"Wangli Gongtang",
    "wof:placetype":"locality"
},
  "geometry": {"coordinates":[112.56689,28.24668],"type":"Point"}
}