{
  "type": "Feature",
  "properties": {
    "gn:admin1_code":"1.0",
    "gn:asciiname":"Liuwucun",
    "gn:country_code":"CN",
    "gn:dem":42,
    "gn:feature_class":"P",
    "gn:feature_code":"PPL",
    "gn:name":"Liuwucun",
    "gn:population":0,
    "gn:timezone":"Asia/Shanghai",
    "iso:country":"CN",
    "name:zho_x_preferred":[
        "\u5218\u6b66\u6751"
    ],
    "wof:name":"Liuwucun",
    "wof:placetype":"locality"
},
  "geometry": {"coordinates":[118.09323999999999,31.65281],"type":"Point"}
}