{
  "type": "Feature",
  "properties": {
    "gn:admin1_code":"15.0",
    "gn:asciiname":"Fenpingzi",
    "gn:country_code":"CN",
    "gn:dem":1355,
    "gn:feature_class":"P",
    "gn:feature_code":"PPL",
    "gn:name":"Fenpingzi",
    "gn:population":0,
    "gn:timezone":"Asia/Shanghai",
    "iso:country":"CN",
    "name:und_x_variant":[
        "\u575f\u576a\u5b50"
    ],
    "wof:name":"Fenpingzi",
    "wof:placetype":"locality"
},
  "geometry": {"coordinates":[105.34577,32.97778],"type":"Point"}
}