{
  "type": "Feature",
  "properties": {
    "gn:admin1_code":"12.0",
    "gn:asciiname":"Suoziyuan",
    "gn:country_code":"CN",
    "gn:dem":31,
    "gn:feature_class":"P",
    "gn:feature_code":"PPL",
    "gn:name":"Suoziyuan",
    "gn:population":0,
    "gn:timezone":"Asia/Shanghai",
    "iso:country":"CN",
    "name:zho_x_preferred":[
        "\u68ad\u5b50\u9662"
    ],
    "wof:name":"Suoziyuan",
    "wof:placetype":"locality"
},
  "geometry": {"coordinates":[113.03399,30.57942],"type":"Point"}
}