{
  "type": "Feature",
  "properties": {
    "gn:admin1_code":"32.0",
    "gn:asciiname":"Chiluoshan",
    "gn:country_code":"CN",
    "gn:dem":1874,
    "gn:feature_class":"P",
    "gn:feature_code":"PPL",
    "gn:name":"Chiluoshan",
    "gn:population":0,
    "gn:timezone":"Asia/Shanghai",
    "iso:country":"CN",
    "name:zho_x_preferred":[
        "\u8d64\u843d\u5c71"
    ],
    "wof:name":"Chiluoshan",
    "wof:placetype":"locality"
},
  "geometry": {"coordinates":[104.52607,32.53663],"type":"Point"}
}