{
  "type": "Feature",
  "properties": {
    "gn:admin1_code":"2.0",
    "gn:asciiname":"Lingzhangkeng",
    "gn:country_code":"CN",
    "gn:dem":260,
    "gn:feature_class":"P",
    "gn:feature_code":"PPL",
    "gn:name":"Lingzhangkeng",
    "gn:population":0,
    "gn:timezone":"Asia/Shanghai",
    "iso:country":"CN",
    "name:zho_x_preferred":[
        "\u5cad\u4e08\u5751"
    ],
    "wof:name":"Lingzhangkeng",
    "wof:placetype":"locality"
},
  "geometry": {"coordinates":[118.60174000000001,28.44848],"type":"Point"}
}