{
  "type": "Feature",
  "properties": {
    "gn:admin1_code":"32.0",
    "gn:asciiname":"Rekou'ajue",
    "gn:country_code":"CN",
    "gn:dem":2108,
    "gn:feature_class":"P",
    "gn:feature_code":"PPL",
    "gn:name":"Rekou\u2019ajue",
    "gn:population":0,
    "gn:timezone":"Asia/Shanghai",
    "iso:country":"CN",
    "name:und_x_variant":[
        "Rekou\u2019ajue"
    ],
    "name:zho_x_preferred":[
        "\u70ed\u53e3\u963f\u89c9"
    ],
    "wof:name":"Rekou'ajue",
    "wof:placetype":"locality"
},
  "geometry": {"coordinates":[103.002,28.2419],"type":"Point"}
}