{
  "type": "Feature",
  "properties": {
    "gn:admin1_code":"02",
    "gn:asciiname":"Meiyuan",
    "gn:country_code":"CN",
    "gn:dem":22,
    "gn:feature_class":"P",
    "gn:feature_code":"PPL",
    "gn:name":"Meiyuan",
    "gn:population":0,
    "gn:timezone":"Asia/Shanghai",
    "iso:country":"CN",
    "name:und_x_variant":[
        "Caobao",
        "Meiyuan"
    ],
    "name:zho_x_preferred":[
        "\u6885\u6e90"
    ],
    "wof:name":"Meiyuan",
    "wof:placetype":"locality"
},
  "geometry": {"coordinates":[120.43548,27.65142],"type":"Point"}
}