{
  "type": "Feature",
  "properties": {
    "gn:admin1_code":"26.0",
    "gn:asciiname":"Shijia Shancun",
    "gn:country_code":"CN",
    "gn:dem":1048,
    "gn:feature_class":"P",
    "gn:feature_code":"PPL",
    "gn:name":"Shijia Shancun",
    "gn:population":0,
    "gn:timezone":"Asia/Shanghai",
    "iso:country":"CN",
    "name:zho_x_preferred":[
        "\u77f3\u5bb6\u5c71\u6751"
    ],
    "wof:name":"Shijia Shancun",
    "wof:placetype":"locality"
},
  "geometry": {"coordinates":[110.259,37.9097],"type":"Point"}
}