{
  "type": "Feature",
  "properties": {
    "gn:admin1_code":"1.0",
    "gn:asciiname":"Fangbangcun",
    "gn:country_code":"CN",
    "gn:dem":26,
    "gn:feature_class":"P",
    "gn:feature_code":"PPL",
    "gn:name":"Fangbangcun",
    "gn:population":0,
    "gn:timezone":"Asia/Shanghai",
    "iso:country":"CN",
    "name:zho_x_preferred":[
        "\u65b9\u699c\u6751"
    ],
    "wof:name":"Fangbangcun",
    "wof:placetype":"locality"
},
  "geometry": {"coordinates":[116.53458999999999,30.60318],"type":"Point"}
}