{
  "type": "Feature",
  "properties": {
    "gn:admin1_code":"15.0",
    "gn:asciiname":"Zhuantaixia",
    "gn:country_code":"CN",
    "gn:dem":1605,
    "gn:feature_class":"P",
    "gn:feature_code":"PPL",
    "gn:name":"Zhuantaixia",
    "gn:population":0,
    "gn:timezone":"Asia/Shanghai",
    "iso:country":"CN",
    "name:zho_x_preferred":[
        "\u7816\u53f0\u4e0b"
    ],
    "wof:name":"Zhuantaixia",
    "wof:placetype":"locality"
},
  "geometry": {"coordinates":[104.75734,33.86214],"type":"Point"}
}