{
  "type": "Feature",
  "properties": {
    "gn:admin1_code":"19.0",
    "gn:asciiname":"Yutun",
    "gn:country_code":"CN",
    "gn:dem":286,
    "gn:feature_class":"P",
    "gn:feature_code":"PPL",
    "gn:name":"Yutun",
    "gn:population":0,
    "gn:timezone":"Asia/Shanghai",
    "iso:country":"CN",
    "name:und_x_variant":[
        "\u4e8e\u5c6f"
    ],
    "name:zho_x_preferred":[
        "\u4e8e\u5c6f"
    ],
    "wof:name":"Yutun",
    "wof:placetype":"locality"
},
  "geometry": {"coordinates":[122.36286,40.24195],"type":"Point"}
}