{
  "type": "Feature",
  "properties": {
    "gn:admin1_code":"24.0",
    "gn:asciiname":"Foyu",
    "gn:country_code":"CN",
    "gn:dem":664,
    "gn:feature_class":"P",
    "gn:feature_code":"PPL",
    "gn:name":"Foyu",
    "gn:population":0,
    "gn:timezone":"Asia/Shanghai",
    "iso:country":"CN",
    "name:zho_x_preferred":[
        "\u4f5b\u5cea"
    ],
    "wof:name":"Foyu",
    "wof:placetype":"locality"
},
  "geometry": {"coordinates":[111.6361,35.02272],"type":"Point"}
}