{
  "type": "Feature",
  "properties": {
    "gn:admin1_code":"29.0",
    "gn:asciiname":"Shudege",
    "gn:country_code":"CN",
    "gn:dem":1645,
    "gn:feature_class":"P",
    "gn:feature_code":"PPL",
    "gn:name":"Shudege",
    "gn:population":0,
    "gn:timezone":"Asia/Shanghai",
    "iso:country":"CN",
    "name:zho_x_preferred":[
        "\u6811\u7684\u5404"
    ],
    "wof:name":"Shudege",
    "wof:placetype":"locality"
},
  "geometry": {"coordinates":[100.426,27.4915],"type":"Point"}
}