{
  "type": "Feature",
  "properties": {
    "gn:admin1_code":"3.0",
    "gn:asciiname":"Jinzhuta",
    "gn:country_code":"CN",
    "gn:dem":184,
    "gn:feature_class":"P",
    "gn:feature_code":"PPL",
    "gn:name":"Jinzhuta",
    "gn:population":0,
    "gn:timezone":"Asia/Shanghai",
    "iso:country":"CN",
    "name:und_x_variant":[
        "\u91d1\u7af9\u5854"
    ],
    "wof:name":"Jinzhuta",
    "wof:placetype":"locality"
},
  "geometry": {"coordinates":[117.39224,29.58887],"type":"Point"}
}