{
  "type": "Feature",
  "properties": {
    "gn:admin1_code":"9.0",
    "gn:asciiname":"Dajinxiang",
    "gn:country_code":"CN",
    "gn:dem":123,
    "gn:feature_class":"P",
    "gn:feature_code":"PPL",
    "gn:name":"Dajinxiang",
    "gn:population":0,
    "gn:timezone":"Asia/Shanghai",
    "iso:country":"CN",
    "name:zho_x_preferred":[
        "\u5927\u91d1\u9999"
    ],
    "wof:name":"Dajinxiang",
    "wof:placetype":"locality"
},
  "geometry": {"coordinates":[112.87725,35.0058],"type":"Point"}
}