{
  "type": "Feature",
  "properties": {
    "gn:admin1_code":"8.0",
    "gn:asciiname":"Dongyongtun",
    "gn:country_code":"CN",
    "gn:dem":169,
    "gn:feature_class":"P",
    "gn:feature_code":"PPL",
    "gn:name":"Dongyongtun",
    "gn:population":0,
    "gn:timezone":"Asia/Shanghai",
    "iso:country":"CN",
    "name:zho_x_preferred":[
        "\u8463\u6c38\u5c6f"
    ],
    "wof:name":"Dongyongtun",
    "wof:placetype":"locality"
},
  "geometry": {"coordinates":[123.09235,47.1504],"type":"Point"}
}