{
  "type": "Feature",
  "properties": {
    "gn:admin1_code":"16.0",
    "gn:asciiname":"Shangpingzhong",
    "gn:country_code":"CN",
    "gn:dem":900,
    "gn:feature_class":"P",
    "gn:feature_code":"PPL",
    "gn:name":"Shangpingzhong",
    "gn:population":0,
    "gn:timezone":"Asia/Shanghai",
    "iso:country":"CN",
    "name:zho_x_preferred":[
        "\u4e0a\u5e73\u4e2d"
    ],
    "wof:name":"Shangpingzhong",
    "wof:placetype":"locality"
},
  "geometry": {"coordinates":[108.63500000000001,25.1395],"type":"Point"}
}