{
  "type": "Feature",
  "properties": {
    "gn:admin1_code":"10.0",
    "gn:asciiname":"Nanpingwang",
    "gn:country_code":"CN",
    "gn:dem":260,
    "gn:feature_class":"P",
    "gn:feature_code":"PPL",
    "gn:name":"Nanpingwang",
    "gn:population":0,
    "gn:timezone":"Asia/Shanghai",
    "iso:country":"CN",
    "name:und_x_variant":[
        "\u5357\u5e73\u671b"
    ],
    "wof:name":"Nanpingwang",
    "wof:placetype":"locality"
},
  "geometry": {"coordinates":[114.19844000000001,38.09642],"type":"Point"}
}