{
  "type": "Feature",
  "properties": {
    "gn:admin1_code":"5.0",
    "gn:asciiname":"Xingmucun",
    "gn:country_code":"CN",
    "gn:dem":277,
    "gn:feature_class":"P",
    "gn:feature_code":"PPL",
    "gn:name":"Xingmucun",
    "gn:population":0,
    "gn:timezone":"Asia/Shanghai",
    "iso:country":"CN",
    "name:zho_x_preferred":[
        "\u674f\u6728\u6751"
    ],
    "wof:name":"Xingmucun",
    "wof:placetype":"locality"
},
  "geometry": {"coordinates":[125.22875999999999,43.26682],"type":"Point"}
}