{
  "type": "Feature",
  "properties": {
    "gn:admin1_code":"24",
    "gn:asciiname":"Changxing",
    "gn:cc2":"CN",
    "gn:country_code":"CN",
    "gn:dem":740,
    "gn:feature_class":"P",
    "gn:feature_code":"PPL",
    "gn:name":"Changxing",
    "gn:population":0,
    "gn:timezone":"Asia/Shanghai",
    "iso:country":"CN",
    "name:und_x_variant":[
        "Ch\u2019ang-hsing",
        "Changxing"
    ],
    "wof:name":"Changxing",
    "wof:placetype":"locality"
},
  "geometry": {"coordinates":[111.81667,37.13333],"type":"Point"}
}