{
  "type": "Feature",
  "properties": {
    "gn:admin1_code":"05",
    "gn:asciiname":"Laojinchang",
    "gn:country_code":"CN",
    "gn:dem":335,
    "gn:feature_class":"P",
    "gn:feature_code":"PPLA4",
    "gn:name":"Laojinchang",
    "gn:population":0,
    "gn:timezone":"Asia/Shanghai",
    "iso:country":"CN",
    "name:und_x_variant":[
        "\u8001\u91d1\u5382",
        "Laojinchang Zhen",
        "\u8001\u91d1\u5382\u9547"
    ],
    "wof:name":"Laojinchang",
    "wof:placetype":"locality"
},
  "geometry": {"coordinates":[127.35361,42.9075],"type":"Point"}
}