{
  "type": "Feature",
  "properties": {
    "gn:admin1_code":"32.0",
    "gn:asciiname":"Mulintang",
    "gn:country_code":"CN",
    "gn:dem":566,
    "gn:feature_class":"P",
    "gn:feature_code":"PPL",
    "gn:name":"Mulintang",
    "gn:population":0,
    "gn:timezone":"Asia/Shanghai",
    "iso:country":"CN",
    "name:zho_x_preferred":[
        "\u6728\u6797\u5858"
    ],
    "wof:name":"Mulintang",
    "wof:placetype":"locality"
},
  "geometry": {"coordinates":[105.80200000000001,31.6199],"type":"Point"}
}