{
  "type": "Feature",
  "properties": {
    "gn:admin1_code":"1.0",
    "gn:asciiname":"Xianchengcun",
    "gn:country_code":"CN",
    "gn:dem":43,
    "gn:feature_class":"P",
    "gn:feature_code":"PPL",
    "gn:name":"Xianchengcun",
    "gn:population":0,
    "gn:timezone":"Asia/Shanghai",
    "iso:country":"CN",
    "name:zho_x_preferred":[
        "\u53bf\u57ce\u6751"
    ],
    "wof:name":"Xianchengcun",
    "wof:placetype":"locality"
},
  "geometry": {"coordinates":[117.54327000000001,32.87854],"type":"Point"}
}