{
  "type": "Feature",
  "properties": {
    "gn:admin1_code":"14.0",
    "gn:asciiname":"Xiamacun",
    "gn:country_code":"CN",
    "gn:dem":4383,
    "gn:feature_class":"P",
    "gn:feature_code":"PPL",
    "gn:name":"Xiamacun",
    "gn:population":0,
    "gn:timezone":"Asia/Urumqi",
    "iso:country":"CN",
    "name:zho_x_preferred":[
        "\u590f\u739b\u6751"
    ],
    "wof:name":"Xiamacun",
    "wof:placetype":"locality"
},
  "geometry": {"coordinates":[92.4821,31.48718],"type":"Point"}
}