{
  "type": "Feature",
  "properties": {
    "gn:admin1_code":"14.0",
    "gn:asciiname":"Bangda",
    "gn:country_code":"CN",
    "gn:dem":4297,
    "gn:feature_class":"P",
    "gn:feature_code":"PPL",
    "gn:name":"Bangda",
    "gn:population":0,
    "gn:timezone":"Asia/Urumqi",
    "iso:country":"CN",
    "name:zho_x_preferred":[
        "\u90a6\u6253"
    ],
    "wof:name":"Bangda",
    "wof:placetype":"locality"
},
  "geometry": {"coordinates":[91.62177,29.05437],"type":"Point"}
}