{
  "type": "Feature",
  "properties": {
    "gn:admin1_code":"21.0",
    "gn:asciiname":"Caizigou",
    "gn:country_code":"CN",
    "gn:dem":2114,
    "gn:feature_class":"P",
    "gn:feature_code":"PPL",
    "gn:name":"Caizigou",
    "gn:population":0,
    "gn:timezone":"Asia/Shanghai",
    "iso:country":"CN",
    "name:zho_x_preferred":[
        "\u8521\u5b50\u6c9f"
    ],
    "wof:name":"Caizigou",
    "wof:placetype":"locality"
},
  "geometry": {"coordinates":[106.069,35.7022],"type":"Point"}
}