{
  "type": "Feature",
  "properties": {
    "gn:admin1_code":"33.0",
    "gn:asciiname":"Gonghe",
    "gn:country_code":"CN",
    "gn:dem":266,
    "gn:feature_class":"P",
    "gn:feature_code":"PPL",
    "gn:name":"Gonghe",
    "gn:population":0,
    "gn:timezone":"Asia/Shanghai",
    "iso:country":"CN",
    "name:zho_x_preferred":[
        "\u5171\u548c"
    ],
    "wof:name":"Gonghe",
    "wof:placetype":"locality"
},
  "geometry": {"coordinates":[106.89681000000002,29.68809000000001],"type":"Point"}
}