{
  "type": "Feature",
  "properties": {
    "gn:admin1_code":"20.0",
    "gn:asciiname":"Sanhezhuang",
    "gn:country_code":"CN",
    "gn:dem":330,
    "gn:feature_class":"P",
    "gn:feature_code":"PPL",
    "gn:name":"Sanhezhuang",
    "gn:population":0,
    "gn:timezone":"Asia/Shanghai",
    "iso:country":"CN",
    "name:zho_x_preferred":[
        "\u4e09\u5408\u5e84"
    ],
    "wof:name":"Sanhezhuang",
    "wof:placetype":"locality"
},
  "geometry": {"coordinates":[124.00042000000001,49.05649],"type":"Point"}
}