{
  "type": "Feature",
  "properties": {
    "gn:admin1_code":"3.0",
    "gn:asciiname":"Xinwuxia",
    "gn:country_code":"CN",
    "gn:dem":152,
    "gn:feature_class":"P",
    "gn:feature_code":"PPL",
    "gn:name":"Xinwuxia",
    "gn:population":0,
    "gn:timezone":"Asia/Shanghai",
    "iso:country":"CN",
    "name:und_x_variant":[
        "\u65b0\u5c4b\u4e0b"
    ],
    "wof:name":"Xinwuxia",
    "wof:placetype":"locality"
},
  "geometry": {"coordinates":[114.82585,27.61791],"type":"Point"}
}