{
  "type": "Feature",
  "properties": {
    "gn:admin1_code":"31.0",
    "gn:asciiname":"Mukai",
    "gn:country_code":"CN",
    "gn:dem":308,
    "gn:feature_class":"P",
    "gn:feature_code":"PPL",
    "gn:name":"Mukai",
    "gn:population":0,
    "gn:timezone":"Asia/Shanghai",
    "iso:country":"CN",
    "name:und_x_variant":[
        "\u6728\u5f00"
    ],
    "name:zho_x_preferred":[
        "\u6728\u5f00"
    ],
    "wof:name":"Mukai",
    "wof:placetype":"locality"
},
  "geometry": {"coordinates":[109.3614,19.17991],"type":"Point"}
}