{
  "type": "Feature",
  "properties": {
    "gn:admin1_code":"12.0",
    "gn:asciiname":"Yanghe",
    "gn:country_code":"CN",
    "gn:dem":40,
    "gn:feature_class":"P",
    "gn:feature_code":"PPLA4",
    "gn:name":"Yanghe",
    "gn:population":0,
    "gn:timezone":"Asia/Shanghai",
    "iso:country":"CN",
    "name:ceb_x_preferred":[
        "Yanghe"
    ],
    "name:deu_x_preferred":[
        "Yanghe"
    ],
    "name:swe_x_preferred":[
        "Yanghe"
    ],
    "name:und_x_variant":[
        "Yang-chia-ho",
        "Yanghe",
        "\u6768\u6cb3",
        "Yanghe Zhen",
        "\u6768\u6cb3\u9547"
    ],
    "wof:name":"Yanghe",
    "wof:placetype":"locality"
},
  "geometry": {"coordinates":[113.58089,31.09625],"type":"Point"}
}