{
  "type": "Feature",
  "properties": {
    "gn:admin1_code":"4.0",
    "gn:asciiname":"Dongwancun",
    "gn:country_code":"CN",
    "gn:dem":9,
    "gn:feature_class":"P",
    "gn:feature_code":"PPL",
    "gn:name":"Dongwancun",
    "gn:population":0,
    "gn:timezone":"Asia/Shanghai",
    "iso:country":"CN",
    "name:zho_x_preferred":[
        "\u4e1c\u6e7e\u6751"
    ],
    "wof:name":"Dongwancun",
    "wof:placetype":"locality"
},
  "geometry": {"coordinates":[120.04891000000001,31.48309],"type":"Point"}
}