{
  "type": "Feature",
  "properties": {
    "gn:admin1_code":"10",
    "gn:asciiname":"Dawangmaogou",
    "gn:country_code":"CN",
    "gn:dem":1435,
    "gn:feature_class":"P",
    "gn:feature_code":"PPL",
    "gn:name":"Dawangmaogou",
    "gn:population":0,
    "gn:timezone":"Asia/Shanghai",
    "iso:country":"CN",
    "name:zho_x_preferred":[
        "\u5927\u738b\u8302\u6c9f"
    ],
    "wof:name":"Dawangmaogou",
    "wof:placetype":"locality"
},
  "geometry": {"coordinates":[114.01115,41.0448],"type":"Point"}
}