{
  "type": "Feature",
  "properties": {
    "gn:admin1_code":"5.0",
    "gn:asciiname":"Qiansan Xianbu",
    "gn:country_code":"CN",
    "gn:dem":203,
    "gn:feature_class":"P",
    "gn:feature_code":"PPL",
    "gn:name":"Qiansan Xianbu",
    "gn:population":0,
    "gn:timezone":"Asia/Shanghai",
    "iso:country":"CN",
    "name:zho_x_preferred":[
        "\u524d\u4e09\u53bf\u5821"
    ],
    "wof:name":"Qiansan Xianbu",
    "wof:placetype":"locality"
},
  "geometry": {"coordinates":[124.37652,44.04315],"type":"Point"}
}