{
  "type": "Feature",
  "properties": {
    "gn:admin1_code":"18",
    "gn:asciiname":"Duimenpo",
    "gn:country_code":"CN",
    "gn:dem":1005,
    "gn:feature_class":"P",
    "gn:feature_code":"PPL",
    "gn:name":"Duimenpo",
    "gn:population":0,
    "gn:timezone":"Asia/Shanghai",
    "iso:country":"CN",
    "name:zho_x_preferred":[
        "\u5bf9\u95e8\u5761"
    ],
    "wof:name":"Duimenpo",
    "wof:placetype":"locality"
},
  "geometry": {"coordinates":[107.13800000000001,27.2693],"type":"Point"}
}