{
  "type": "Feature",
  "properties": {
    "gn:admin1_code":"26.0",
    "gn:asciiname":"Zhuxinyao",
    "gn:country_code":"CN",
    "gn:dem":1270,
    "gn:feature_class":"P",
    "gn:feature_code":"PPL",
    "gn:name":"Zhuxinyao",
    "gn:population":0,
    "gn:timezone":"Asia/Shanghai",
    "iso:country":"CN",
    "name:zho_x_preferred":[
        "\u6731\u65b0\u7a91"
    ],
    "wof:name":"Zhuxinyao",
    "wof:placetype":"locality"
},
  "geometry": {"coordinates":[108.93026,37.88184],"type":"Point"}
}