{
  "type": "Feature",
  "properties": {
    "gn:admin1_code":"29.0",
    "gn:asciiname":"Xiaomushe",
    "gn:country_code":"CN",
    "gn:dem":2019,
    "gn:feature_class":"P",
    "gn:feature_code":"PPL",
    "gn:name":"Xiaomushe",
    "gn:population":0,
    "gn:timezone":"Asia/Shanghai",
    "iso:country":"CN",
    "name:zho_x_preferred":[
        "\u5c0f\u7267\u820d"
    ],
    "wof:name":"Xiaomushe",
    "wof:placetype":"locality"
},
  "geometry": {"coordinates":[100.563,25.5121],"type":"Point"}
}