{
  "type": "Feature",
  "properties": {
    "gn:admin1_code":"12.0",
    "gn:asciiname":"Caojiawan",
    "gn:country_code":"CN",
    "gn:dem":151,
    "gn:feature_class":"P",
    "gn:feature_code":"PPL",
    "gn:name":"Caojiawan",
    "gn:population":0,
    "gn:timezone":"Asia/Shanghai",
    "iso:country":"CN",
    "name:zho_x_preferred":[
        "Caojiawan"
    ],
    "name:zho_x_variant":[
        "\u66f9\u5bb6\u6e7e"
    ],
    "wof:name":"Caojiawan",
    "wof:placetype":"locality"
},
  "geometry": {"coordinates":[114.45419,29.70559],"type":"Point"}
}