{
  "type": "Feature",
  "properties": {
    "gn:admin1_code":"26.0",
    "gn:asciiname":"Shangzhuangzi",
    "gn:country_code":"CN",
    "gn:dem":1113,
    "gn:feature_class":"P",
    "gn:feature_code":"PPL",
    "gn:name":"Shangzhuangzi",
    "gn:population":0,
    "gn:timezone":"Asia/Shanghai",
    "iso:country":"CN",
    "name:zho_x_preferred":[
        "\u4e0a\u5e84\u5b50"
    ],
    "wof:name":"Shangzhuangzi",
    "wof:placetype":"locality"
},
  "geometry": {"coordinates":[108.85415999999999,36.03973],"type":"Point"}
}