{
  "type": "Feature",
  "properties": {
    "gn:admin1_code":"14.0",
    "gn:asciiname":"Tanglongmacun",
    "gn:country_code":"CN",
    "gn:dem":4625,
    "gn:feature_class":"P",
    "gn:feature_code":"PPL",
    "gn:name":"Tanglongmacun",
    "gn:population":0,
    "gn:timezone":"Asia/Urumqi",
    "iso:country":"CN",
    "name:zho_x_preferred":[
        "\u5510\u9686\u739b\u6751"
    ],
    "wof:name":"Tanglongmacun",
    "wof:placetype":"locality"
},
  "geometry": {"coordinates":[89.26718000000002,32.06652],"type":"Point"}
}