{
  "type": "Feature",
  "properties": {
    "gn:admin1_code":"11.0",
    "gn:asciiname":"Xiuchi Sizu",
    "gn:country_code":"CN",
    "gn:dem":28,
    "gn:feature_class":"P",
    "gn:feature_code":"PPLF",
    "gn:name":"Xiuchi Sizu",
    "gn:population":0,
    "gn:timezone":"Asia/Shanghai",
    "iso:country":"CN",
    "name:zho_x_preferred":[
        "\u79c0\u6c60\u56db\u7ec4"
    ],
    "wof:name":"Xiuchi Sizu",
    "wof:placetype":"locality"
},
  "geometry": {"coordinates":[112.58418,28.60181],"type":"Point"}
}