{
  "type": "Feature",
  "properties": {
    "gn:admin1_code":"10",
    "gn:asciiname":"Yongtaixing Nangou",
    "gn:country_code":"CN",
    "gn:dem":1369,
    "gn:feature_class":"P",
    "gn:feature_code":"PPL",
    "gn:name":"Yongtaixing Nangou",
    "gn:population":0,
    "gn:timezone":"Asia/Shanghai",
    "iso:country":"CN",
    "name:zho_x_preferred":[
        "\u6c38\u592a\u5174\u5357\u6c9f"
    ],
    "wof:name":"Yongtaixing Nangou",
    "wof:placetype":"locality"
},
  "geometry": {"coordinates":[116.73063999999999,41.89195],"type":"Point"}
}