{
  "type": "Feature",
  "properties": {
    "gn:admin1_code":"15.0",
    "gn:asciiname":"Jihelanmu",
    "gn:country_code":"CN",
    "gn:dem":3073,
    "gn:feature_class":"P",
    "gn:feature_code":"PPL",
    "gn:name":"Jihelanmu",
    "gn:population":0,
    "gn:timezone":"Asia/Shanghai",
    "iso:country":"CN",
    "name:zho_x_preferred":[
        "\u5409\u5408\u5170\u6728"
    ],
    "wof:name":"Jihelanmu",
    "wof:placetype":"locality"
},
  "geometry": {"coordinates":[102.88800000000001,34.8402],"type":"Point"}
}