{
  "type": "Feature",
  "properties": {
    "gn:admin1_code":"29",
    "gn:asciiname":"Huangnigou",
    "gn:country_code":"CN",
    "gn:dem":2214,
    "gn:feature_class":"P",
    "gn:feature_code":"PPL",
    "gn:name":"Huangnigou",
    "gn:population":0,
    "gn:timezone":"Asia/Shanghai",
    "iso:country":"CN",
    "name:zho_x_preferred":[
        "\u9ec4\u6ce5\u6c9f"
    ],
    "wof:name":"Huangnigou",
    "wof:placetype":"locality"
},
  "geometry": {"coordinates":[102.467,24.7884],"type":"Point"}
}