{
  "type": "Feature",
  "properties": {
    "gn:admin1_code":"15.0",
    "gn:asciiname":"Yanghuwan",
    "gn:country_code":"CN",
    "gn:dem":1449,
    "gn:feature_class":"P",
    "gn:feature_code":"PPL",
    "gn:name":"Yanghuwan",
    "gn:population":0,
    "gn:timezone":"Asia/Shanghai",
    "iso:country":"CN",
    "name:und_x_variant":[
        "\u6768\u864e\u6e7e"
    ],
    "wof:name":"Yanghuwan",
    "wof:placetype":"locality"
},
  "geometry": {"coordinates":[107.31977999999999,36.09843],"type":"Point"}
}