{
  "type": "Feature",
  "properties": {
    "gn:admin1_code":"14.0",
    "gn:asciiname":"Bayicun",
    "gn:country_code":"CN",
    "gn:dem":3468,
    "gn:feature_class":"P",
    "gn:feature_code":"PPL",
    "gn:name":"Bayicun",
    "gn:population":0,
    "gn:timezone":"Asia/Urumqi",
    "iso:country":"CN",
    "name:zho_x_preferred":[
        "\u575d\u76ca\u6751"
    ],
    "wof:name":"Bayicun",
    "wof:placetype":"locality"
},
  "geometry": {"coordinates":[98.25434,29.03991],"type":"Point"}
}