{
  "type": "Feature",
  "properties": {
    "gn:admin1_code":"19.0",
    "gn:asciiname":"Taitun",
    "gn:country_code":"CN",
    "gn:dem":9,
    "gn:feature_class":"P",
    "gn:feature_code":"PPL",
    "gn:name":"Taitun",
    "gn:population":0,
    "gn:timezone":"Asia/Shanghai",
    "iso:country":"CN",
    "name:zho_x_preferred":[
        "\u90b0\u5c6f"
    ],
    "wof:name":"Taitun",
    "wof:placetype":"locality"
},
  "geometry": {"coordinates":[121.17787,40.96094],"type":"Point"}
}