{
  "type": "Feature",
  "properties": {
    "gn:admin1_code":"1.0",
    "gn:asciiname":"Shuangma",
    "gn:country_code":"CN",
    "gn:dem":38,
    "gn:feature_class":"P",
    "gn:feature_code":"PPL",
    "gn:name":"Shuangma",
    "gn:population":0,
    "gn:timezone":"Asia/Shanghai",
    "iso:country":"CN",
    "name:zho_x_preferred":[
        "\u53cc\u9a6c"
    ],
    "wof:name":"Shuangma",
    "wof:placetype":"locality"
},
  "geometry": {"coordinates":[118.66428999999999,31.15291],"type":"Point"}
}