{
  "type": "Feature",
  "properties": {
    "gn:admin1_code":"32.0",
    "gn:asciiname":"Dingguangchang",
    "gn:country_code":"CN",
    "gn:dem":389,
    "gn:feature_class":"P",
    "gn:feature_code":"PPL",
    "gn:name":"Dingguangchang",
    "gn:population":0,
    "gn:timezone":"Asia/Shanghai",
    "iso:country":"CN",
    "name:zho_x_preferred":[
        "\u5b9a\u5149\u573a"
    ],
    "wof:name":"Dingguangchang",
    "wof:placetype":"locality"
},
  "geometry": {"coordinates":[105.44162,31.17408],"type":"Point"}
}