{
  "type": "Feature",
  "properties": {
    "gn:admin1_code":"15.0",
    "gn:asciiname":"Chelu",
    "gn:country_code":"CN",
    "gn:dem":2699,
    "gn:feature_class":"P",
    "gn:feature_code":"PPL",
    "gn:name":"Chelu",
    "gn:population":0,
    "gn:timezone":"Asia/Shanghai",
    "iso:country":"CN",
    "name:und_x_variant":[
        "\u8f66\u8def"
    ],
    "wof:name":"Chelu",
    "wof:placetype":"locality"
},
  "geometry": {"coordinates":[104.13928,34.53193],"type":"Point"}
}