{
  "type": "Feature",
  "properties": {
    "gn:admin1_code":"2.0",
    "gn:asciiname":"Jiangtang",
    "gn:country_code":"CN",
    "gn:dem":11,
    "gn:feature_class":"P",
    "gn:feature_code":"PPL",
    "gn:name":"Jiangtang",
    "gn:population":0,
    "gn:timezone":"Asia/Shanghai",
    "iso:country":"CN",
    "name:und_x_variant":[
        "\u6c5f\u5858"
    ],
    "wof:name":"Jiangtang",
    "wof:placetype":"locality"
},
  "geometry": {"coordinates":[120.33611000000001,30.11947],"type":"Point"}
}