{
  "type": "Feature",
  "properties": {
    "gn:admin1_code":"9",
    "gn:asciiname":"Baiyangshan",
    "gn:country_code":"CN",
    "gn:dem":666,
    "gn:feature_class":"P",
    "gn:feature_code":"PPL",
    "gn:name":"Baiyangshan",
    "gn:population":0,
    "gn:timezone":"Asia/Shanghai",
    "iso:country":"CN",
    "name:zho_x_preferred":[
        "\u767d\u7f8a\u5c71"
    ],
    "wof:name":"Baiyangshan",
    "wof:placetype":"locality"
},
  "geometry": {"coordinates":[111.70587,34.96073],"type":"Point"}
}