{
  "type": "Feature",
  "properties": {
    "gn:admin1_code":"1.0",
    "gn:asciiname":"Zoutaicun",
    "gn:country_code":"CN",
    "gn:dem":25,
    "gn:feature_class":"P",
    "gn:feature_code":"PPL",
    "gn:name":"Zoutaicun",
    "gn:population":0,
    "gn:timezone":"Asia/Shanghai",
    "iso:country":"CN",
    "name:zho_x_preferred":[
        "\u90b9\u53f0\u6751"
    ],
    "wof:name":"Zoutaicun",
    "wof:placetype":"locality"
},
  "geometry": {"coordinates":[116.1767,32.4281],"type":"Point"}
}