{
  "type": "Feature",
  "properties": {
    "gn:admin1_code":"1.0",
    "gn:asciiname":"Yueqiaocun",
    "gn:country_code":"CN",
    "gn:dem":34,
    "gn:feature_class":"P",
    "gn:feature_code":"PPL",
    "gn:name":"Yueqiaocun",
    "gn:population":0,
    "gn:timezone":"Asia/Shanghai",
    "iso:country":"CN",
    "name:zho_x_preferred":[
        "\u5cb3\u6865\u6751"
    ],
    "wof:name":"Yueqiaocun",
    "wof:placetype":"locality"
},
  "geometry": {"coordinates":[115.71713,32.66961],"type":"Point"}
}