{
  "type": "Feature",
  "properties": {
    "gn:admin1_code":"18.0",
    "gn:asciiname":"Guilong",
    "gn:country_code":"CN",
    "gn:dem":646,
    "gn:feature_class":"P",
    "gn:feature_code":"PPL",
    "gn:name":"Guilong",
    "gn:population":0,
    "gn:timezone":"Asia/Shanghai",
    "iso:country":"CN",
    "name:zho_x_preferred":[
        "\u5f52\u9f99"
    ],
    "wof:name":"Guilong",
    "wof:placetype":"locality"
},
  "geometry": {"coordinates":[109.252,25.9929],"type":"Point"}
}