{
  "type": "Feature",
  "properties": {
    "gn:admin1_code":"07",
    "gn:asciiname":"Niuyikeng",
    "gn:country_code":"CN",
    "gn:dem":766,
    "gn:feature_class":"P",
    "gn:feature_code":"PPL",
    "gn:name":"Niuyikeng",
    "gn:population":0,
    "gn:timezone":"Asia/Shanghai",
    "iso:country":"CN",
    "name:zho_x_preferred":[
        "\u725b\u76ca\u5751"
    ],
    "wof:name":"Niuyikeng",
    "wof:placetype":"locality"
},
  "geometry": {"coordinates":[117.07193999999998,25.82722],"type":"Point"}
}