{
  "type": "Feature",
  "properties": {
    "gn:admin1_code":"2.0",
    "gn:asciiname":"Jianhu",
    "gn:country_code":"CN",
    "gn:dem":18,
    "gn:feature_class":"P",
    "gn:feature_code":"PPLA4",
    "gn:name":"Jianhu",
    "gn:population":0,
    "gn:timezone":"Asia/Shanghai",
    "iso:country":"CN",
    "name:und_x_variant":[
        "Jianhu Zhen",
        "Jianhu"
    ],
    "name:zho_x_preferred":[
        "\u9274\u6e56"
    ],
    "name:zho_x_variant":[
        "\u9274\u6e56\u9547"
    ],
    "wof:name":"Jianhu",
    "wof:placetype":"locality"
},
  "geometry": {"coordinates":[120.57124,29.97986],"type":"Point"}
}