{
  "type": "Feature",
  "properties": {
    "gn:admin1_code":"30",
    "gn:asciiname":"Qianpo",
    "gn:country_code":"CN",
    "gn:dem":51,
    "gn:feature_class":"P",
    "gn:feature_code":"PPL",
    "gn:name":"Qianpo",
    "gn:population":0,
    "gn:timezone":"Asia/Urumqi",
    "iso:country":"CN",
    "name:zho_x_preferred":[
        "\u4e7e\u5761"
    ],
    "wof:name":"Qianpo",
    "wof:placetype":"locality"
},
  "geometry": {"coordinates":[110.86044,22.15245],"type":"Point"}
}