{
  "type": "Feature",
  "properties": {
    "gn:admin1_code":"30.0",
    "gn:asciiname":"Xinlong",
    "gn:country_code":"CN",
    "gn:dem":6,
    "gn:feature_class":"P",
    "gn:feature_code":"PPL",
    "gn:name":"Xinlong",
    "gn:population":0,
    "gn:timezone":"Asia/Shanghai",
    "iso:country":"CN",
    "name:zho_x_preferred":[
        "\u65b0\u9f99"
    ],
    "wof:name":"Xinlong",
    "wof:placetype":"locality"
},
  "geometry": {"coordinates":[112.85966999999999,22.03465],"type":"Point"}
}