{
  "type": "Feature",
  "properties": {
    "gn:admin1_code":"10.0",
    "gn:asciiname":"Sangyuan",
    "gn:country_code":"CN",
    "gn:dem":10,
    "gn:feature_class":"P",
    "gn:feature_code":"PPL",
    "gn:name":"Sangyuan",
    "gn:population":0,
    "gn:timezone":"Asia/Shanghai",
    "iso:country":"CN",
    "name:ceb_x_preferred":[
        "Sangyuan"
    ],
    "name:swe_x_preferred":[
        "Sangyuan"
    ],
    "name:zho_x_preferred":[
        "\u6851\u56ed"
    ],
    "name:zho_x_variant":[
        "\u6851\u56ed\u9547"
    ],
    "wof:name":"Sangyuan",
    "wof:placetype":"locality"
},
  "geometry": {"coordinates":[116.35747000000001,39.07659],"type":"Point"}
}