{
  "type": "Feature",
  "properties": {
    "gn:admin1_code":"30.0",
    "gn:asciiname":"Modaokeng",
    "gn:country_code":"CN",
    "gn:dem":593,
    "gn:feature_class":"P",
    "gn:feature_code":"PPL",
    "gn:name":"Modaokeng",
    "gn:population":0,
    "gn:timezone":"Asia/Shanghai",
    "iso:country":"CN",
    "name:zho_x_preferred":[
        "Modaokeng"
    ],
    "name:zho_x_variant":[
        "\u78e8\u5200\u5751"
    ],
    "wof:name":"Modaokeng",
    "wof:placetype":"locality"
},
  "geometry": {"coordinates":[112.21528000000001,24.61778],"type":"Point"}
}