{
  "type": "Feature",
  "properties": {
    "gn:admin1_code":"30.0",
    "gn:asciiname":"Shanzhuwo",
    "gn:country_code":"CN",
    "gn:dem":71,
    "gn:feature_class":"P",
    "gn:feature_code":"PPL",
    "gn:name":"Shanzhuwo",
    "gn:population":0,
    "gn:timezone":"Asia/Shanghai",
    "iso:country":"CN",
    "name:zho_x_preferred":[
        "\u5c71\u732a\u7a9d"
    ],
    "wof:name":"Shanzhuwo",
    "wof:placetype":"locality"
},
  "geometry": {"coordinates":[114.86955,23.82497],"type":"Point"}
}