{
  "type": "Feature",
  "properties": {
    "gn:admin1_code":"10",
    "gn:asciiname":"Pendikeng",
    "gn:country_code":"CN",
    "gn:dem":1713,
    "gn:feature_class":"P",
    "gn:feature_code":"PPL",
    "gn:name":"Pendikeng",
    "gn:population":0,
    "gn:timezone":"Asia/Shanghai",
    "iso:country":"CN",
    "name:zho_x_preferred":[
        "\u76c6\u5e95\u5751"
    ],
    "wof:name":"Pendikeng",
    "wof:placetype":"locality"
},
  "geometry": {"coordinates":[115.42777,41.01055],"type":"Point"}
}