{
  "type": "Feature",
  "properties": {
    "gn:admin1_code":"26.0",
    "gn:asciiname":"Baiyanggou",
    "gn:country_code":"CN",
    "gn:dem":1026,
    "gn:feature_class":"P",
    "gn:feature_code":"PPL",
    "gn:name":"Baiyanggou",
    "gn:population":0,
    "gn:timezone":"Asia/Shanghai",
    "iso:country":"CN",
    "name:zho_x_preferred":[
        "\u767d\u6768\u6c9f"
    ],
    "wof:name":"Baiyanggou",
    "wof:placetype":"locality"
},
  "geometry": {"coordinates":[108.26536000000002,33.26399],"type":"Point"}
}