{
  "type": "Feature",
  "properties": {
    "gn:admin1_code":"33",
    "gn:asciiname":"Daguan",
    "gn:cc2":"CN",
    "gn:country_code":"CN",
    "gn:dem":734,
    "gn:feature_class":"P",
    "gn:feature_code":"PPL",
    "gn:name":"Daguan",
    "gn:population":0,
    "gn:timezone":"Asia/Shanghai",
    "iso:country":"CN",
    "name:und_x_variant":[
        "Ta-kuan",
        "Daguan"
    ],
    "wof:name":"Daguan",
    "wof:placetype":"locality"
},
  "geometry": {"coordinates":[106.97693999999998,29.255],"type":"Point"}
}