{
  "type": "Feature",
  "properties": {
    "gn:admin1_code":"33",
    "gn:asciiname":"Daguan",
    "gn:cc2":"CN",
    "gn:country_code":"CN",
    "gn:dem":734,
    "gn:feature_class":"P",
    "gn:feature_code":"PPL",
    "gn:name":"Daguan",
    "gn:population":0,
    "gn:timezone":"Asia/Shanghai",
    "iso:country":"CN",
    "name:ceb_x_preferred":[
        "Daguan"
    ],
    "name:deu_x_preferred":[
        "Daguan"
    ],
    "name:fra_x_preferred":[
        "Daguan"
    ],
    "name:nor_x_preferred":[
        "Daguan"
    ],
    "name:rus_x_preferred":[
        "\u0414\u0430\u0433\u0443\u0430\u043d\u044c"
    ],
    "name:swe_x_preferred":[
        "Daguan"
    ],
    "name:und_x_variant":[
        "Ta-kuan"
    ],
    "wof:name":"Daguan",
    "wof:placetype":"locality"
},
  "geometry": {"coordinates":[106.97693999999998,29.255],"type":"Point"}
}