{
  "type": "Feature",
  "properties": {
    "gn:admin1_code":"2.0",
    "gn:asciiname":"Kengtoufan",
    "gn:country_code":"CN",
    "gn:dem":112,
    "gn:feature_class":"P",
    "gn:feature_code":"PPL",
    "gn:name":"Kengtoufan",
    "gn:population":0,
    "gn:timezone":"Asia/Shanghai",
    "iso:country":"CN",
    "name:zho_x_preferred":[
        "\u5751\u5934\u7548"
    ],
    "wof:name":"Kengtoufan",
    "wof:placetype":"locality"
},
  "geometry": {"coordinates":[118.95581,28.86919],"type":"Point"}
}