{
  "type": "Feature",
  "properties": {
    "gn:admin1_code":"14.0",
    "gn:asciiname":"Rongyue",
    "gn:country_code":"CN",
    "gn:dem":4259,
    "gn:feature_class":"P",
    "gn:feature_code":"PPL",
    "gn:name":"Rongyue",
    "gn:population":0,
    "gn:timezone":"Asia/Urumqi",
    "iso:country":"CN",
    "name:zho_x_preferred":[
        "\u5bb9\u7ea6"
    ],
    "wof:name":"Rongyue",
    "wof:placetype":"locality"
},
  "geometry": {"coordinates":[91.46638,28.43856],"type":"Point"}
}