{
  "type": "Feature",
  "properties": {
    "gn:admin1_code":"4.0",
    "gn:asciiname":"Bibeizhuang",
    "gn:country_code":"CN",
    "gn:dem":6,
    "gn:feature_class":"P",
    "gn:feature_code":"PPL",
    "gn:name":"Bibeizhuang",
    "gn:population":0,
    "gn:timezone":"Asia/Shanghai",
    "iso:country":"CN",
    "name:zho_x_preferred":[
        "\u859c\u5317\u5e84"
    ],
    "wof:name":"Bibeizhuang",
    "wof:placetype":"locality"
},
  "geometry": {"coordinates":[119.55955,32.97694],"type":"Point"}
}