{
  "type": "Feature",
  "properties": {
    "gn:admin1_code":"7.0",
    "gn:asciiname":"Fengping",
    "gn:country_code":"CN",
    "gn:dem":672,
    "gn:feature_class":"P",
    "gn:feature_code":"PPL",
    "gn:name":"Fengping",
    "gn:population":0,
    "gn:timezone":"Asia/Shanghai",
    "iso:country":"CN",
    "name:zho_x_preferred":[
        "\u51e4\u576a"
    ],
    "wof:name":"Fengping",
    "wof:placetype":"locality"
},
  "geometry": {"coordinates":[118.40340999999999,25.77191],"type":"Point"}
}