{
  "type": "Feature",
  "properties": {
    "gn:admin1_code":"1.0",
    "gn:asciiname":"Chumiaocun",
    "gn:country_code":"CN",
    "gn:dem":28,
    "gn:feature_class":"P",
    "gn:feature_code":"PPL",
    "gn:name":"Chumiaocun",
    "gn:population":0,
    "gn:timezone":"Asia/Shanghai",
    "iso:country":"CN",
    "name:zho_x_preferred":[
        "\u695a\u5e99\u6751"
    ],
    "wof:name":"Chumiaocun",
    "wof:placetype":"locality"
},
  "geometry": {"coordinates":[116.56426999999999,33.08392],"type":"Point"}
}