{
  "type": "Feature",
  "properties": {
    "gn:admin1_code":"30.0",
    "gn:asciiname":"Xiangqian",
    "gn:country_code":"CN",
    "gn:dem":3,
    "gn:feature_class":"P",
    "gn:feature_code":"PPL",
    "gn:name":"Xiangqian",
    "gn:population":0,
    "gn:timezone":"Asia/Shanghai",
    "iso:country":"CN",
    "name:zho_x_preferred":[
        "\u5411\u524d"
    ],
    "wof:name":"Xiangqian",
    "wof:placetype":"locality"
},
  "geometry": {"coordinates":[113.12105,22.54043],"type":"Point"}
}