{
  "type": "Feature",
  "properties": {
    "gn:admin1_code":"14.0",
    "gn:asciiname":"Rekaduo",
    "gn:country_code":"CN",
    "gn:dem":4534,
    "gn:feature_class":"P",
    "gn:feature_code":"PPL",
    "gn:name":"Rekaduo",
    "gn:population":0,
    "gn:timezone":"Asia/Urumqi",
    "iso:country":"CN",
    "name:zho_x_preferred":[
        "\u70ed\u5580\u591a"
    ],
    "wof:name":"Rekaduo",
    "wof:placetype":"locality"
},
  "geometry": {"coordinates":[94.09591,31.12421],"type":"Point"}
}