{
  "type": "Feature",
  "properties": {
    "gn:admin1_code":"8.0",
    "gn:asciiname":"Shuangdengzhao",
    "gn:country_code":"CN",
    "gn:dem":133,
    "gn:feature_class":"P",
    "gn:feature_code":"PPL",
    "gn:name":"Shuangdengzhao",
    "gn:population":0,
    "gn:timezone":"Asia/Shanghai",
    "iso:country":"CN",
    "name:zho_x_preferred":[
        "\u53cc\u706f\u7167"
    ],
    "wof:name":"Shuangdengzhao",
    "wof:placetype":"locality"
},
  "geometry": {"coordinates":[127.36865,50.28355],"type":"Point"}
}