{
  "type": "Feature",
  "properties": {
    "gn:admin1_code":"05",
    "gn:asciiname":"Sandaohezi",
    "gn:country_code":"CN",
    "gn:dem":142,
    "gn:feature_class":"P",
    "gn:feature_code":"PPL",
    "gn:name":"Sandaohezi",
    "gn:population":0,
    "gn:timezone":"Asia/Shanghai",
    "iso:country":"CN",
    "name:und_x_variant":[
        "\u4e09\u9053\u6cb3\u5b50",
        "San-tao-ho-tzu"
    ],
    "wof:name":"Sandaohezi",
    "wof:placetype":"locality"
},
  "geometry": {"coordinates":[125.75861,40.93028],"type":"Point"}
}