{
  "type": "Feature",
  "properties": {
    "gn:admin1_code":"24.0",
    "gn:asciiname":"Changqiyingcun",
    "gn:country_code":"CN",
    "gn:dem":353,
    "gn:feature_class":"P",
    "gn:feature_code":"PPL",
    "gn:name":"Changqiyingcun",
    "gn:population":0,
    "gn:timezone":"Asia/Shanghai",
    "iso:country":"CN",
    "name:zho_x_preferred":[
        "\u5e38\u65d7\u8425\u6751"
    ],
    "wof:name":"Changqiyingcun",
    "wof:placetype":"locality"
},
  "geometry": {"coordinates":[110.57959,34.91558],"type":"Point"}
}