{
  "type": "Feature",
  "properties": {
    "gn:admin1_code":"25.0",
    "gn:asciiname":"Haduihou",
    "gn:country_code":"CN",
    "gn:dem":19,
    "gn:feature_class":"P",
    "gn:feature_code":"PPL",
    "gn:name":"Haduihou",
    "gn:population":0,
    "gn:timezone":"Asia/Shanghai",
    "iso:country":"CN",
    "name:zho_x_preferred":[
        "\u86e4\u5806\u540e"
    ],
    "wof:name":"Haduihou",
    "wof:placetype":"locality"
},
  "geometry": {"coordinates":[121.69423,37.43478],"type":"Point"}
}