{
  "type": "Feature",
  "properties": {
    "gn:admin1_code":"7",
    "gn:asciiname":"Beixi",
    "gn:country_code":"CN",
    "gn:dem":179,
    "gn:feature_class":"P",
    "gn:feature_code":"PPL",
    "gn:name":"Beixi",
    "gn:population":0,
    "gn:timezone":"Asia/Shanghai",
    "iso:country":"CN",
    "name:zho_x_preferred":[
        "\u5317\u6eaa"
    ],
    "wof:name":"Beixi",
    "wof:placetype":"locality"
},
  "geometry": {"coordinates":[117.39552999999999,24.30594],"type":"Point"}
}