{
  "type": "Feature",
  "properties": {
    "gn:admin1_code":"9.0",
    "gn:asciiname":"Qianwangzhuang",
    "gn:country_code":"CN",
    "gn:dem":410,
    "gn:feature_class":"P",
    "gn:feature_code":"PPL",
    "gn:name":"Qianwangzhuang",
    "gn:population":0,
    "gn:timezone":"Asia/Shanghai",
    "iso:country":"CN",
    "name:zho_x_preferred":[
        "\u524d\u738b\u5e84"
    ],
    "wof:name":"Qianwangzhuang",
    "wof:placetype":"locality"
},
  "geometry": {"coordinates":[112.38036,34.1568],"type":"Point"}
}