{
  "type": "Feature",
  "properties": {
    "gn:admin1_code":"26.0",
    "gn:asciiname":"Meijialiang",
    "gn:country_code":"CN",
    "gn:dem":814,
    "gn:feature_class":"P",
    "gn:feature_code":"PPL",
    "gn:name":"Meijialiang",
    "gn:population":0,
    "gn:timezone":"Asia/Shanghai",
    "iso:country":"CN",
    "name:zho_x_preferred":[
        "\u6885\u5bb6\u6881"
    ],
    "wof:name":"Meijialiang",
    "wof:placetype":"locality"
},
  "geometry": {"coordinates":[108.33215,33.08534],"type":"Point"}
}