{
  "type": "Feature",
  "properties": {
    "gn:admin1_code":"10.0",
    "gn:asciiname":"Dongchen Jiajian",
    "gn:country_code":"CN",
    "gn:dem":924,
    "gn:feature_class":"P",
    "gn:feature_code":"PPL",
    "gn:name":"Dongchen Jiajian",
    "gn:population":0,
    "gn:timezone":"Asia/Shanghai",
    "iso:country":"CN",
    "name:zho_x_preferred":[
        "\u4e1c\u9648\u5bb6\u6da7"
    ],
    "wof:name":"Dongchen Jiajian",
    "wof:placetype":"locality"
},
  "geometry": {"coordinates":[114.54428,39.86694],"type":"Point"}
}