{
  "type": "Feature",
  "properties": {
    "gn:admin1_code":"7.0",
    "gn:asciiname":"Yuankengshang",
    "gn:country_code":"CN",
    "gn:dem":390,
    "gn:feature_class":"P",
    "gn:feature_code":"PPL",
    "gn:name":"Yuankengshang",
    "gn:population":0,
    "gn:timezone":"Asia/Shanghai",
    "iso:country":"CN",
    "name:zho_x_preferred":[
        "\u56ed\u5751\u4e0a"
    ],
    "wof:name":"Yuankengshang",
    "wof:placetype":"locality"
},
  "geometry": {"coordinates":[116.39167,25.36724],"type":"Point"}
}