{
  "type": "Feature",
  "properties": {
    "gn:admin1_code":"11.0",
    "gn:asciiname":"Pianshui",
    "gn:country_code":"CN",
    "gn:dem":415,
    "gn:feature_class":"P",
    "gn:feature_code":"PPL",
    "gn:name":"Pianshui",
    "gn:population":0,
    "gn:timezone":"Asia/Shanghai",
    "iso:country":"CN",
    "name:zho_x_preferred":[
        "\u504f\u6c34"
    ],
    "wof:name":"Pianshui",
    "wof:placetype":"locality"
},
  "geometry": {"coordinates":[109.67867,29.22344],"type":"Point"}
}