{
  "type": "Feature",
  "properties": {
    "gn:admin1_code":"29.0",
    "gn:asciiname":"Wanshouzhai",
    "gn:country_code":"CN",
    "gn:dem":1637,
    "gn:feature_class":"P",
    "gn:feature_code":"PPL",
    "gn:name":"Wanshouzhai",
    "gn:population":0,
    "gn:timezone":"Asia/Shanghai",
    "iso:country":"CN",
    "name:zho_x_preferred":[
        "\u4e07\u5bff\u5be8"
    ],
    "wof:name":"Wanshouzhai",
    "wof:placetype":"locality"
},
  "geometry": {"coordinates":[98.601,24.3051],"type":"Point"}
}