{
  "type": "Feature",
  "properties": {
    "gn:admin1_code":"18.0",
    "gn:asciiname":"Yangxi",
    "gn:country_code":"CN",
    "gn:dem":1117,
    "gn:feature_class":"P",
    "gn:feature_code":"PPLA4",
    "gn:name":"Yangxi",
    "gn:population":0,
    "gn:timezone":"Asia/Shanghai",
    "iso:country":"CN",
    "name:ceb_x_preferred":[
        "Yangxi"
    ],
    "name:deu_x_preferred":[
        "Yangxi"
    ],
    "name:und_x_variant":[
        "Yangxi Zhen"
    ],
    "name:zho_x_preferred":[
        "\u9633\u6eaa"
    ],
    "name:zho_x_variant":[
        "\u9633\u6eaa\u9547",
        "\u6d0b\u6eaa\u9547"
    ],
    "wof:name":"Yangxi",
    "wof:placetype":"locality"
},
  "geometry": {"coordinates":[107.58194,29.09],"type":"Point"}
}