{
  "type": "Feature",
  "properties": {
    "gn:admin1_code":"02",
    "gn:asciiname":"Wudi",
    "gn:country_code":"CN",
    "gn:dem":862,
    "gn:feature_class":"P",
    "gn:feature_code":"PPL",
    "gn:name":"Wudi",
    "gn:population":0,
    "gn:timezone":"Asia/Shanghai",
    "iso:country":"CN",
    "wof:name":"Wudi",
    "wof:placetype":"locality"
},
  "geometry": {"coordinates":[120.05382,27.59022],"type":"Point"}
}