{
  "type": "Feature",
  "properties": {
    "gn:admin1_code":"19.0",
    "gn:asciiname":"Taojia",
    "gn:country_code":"CN",
    "gn:dem":14,
    "gn:feature_class":"P",
    "gn:feature_code":"PPL",
    "gn:name":"Taojia",
    "gn:population":0,
    "gn:timezone":"Asia/Shanghai",
    "iso:country":"CN",
    "name:und_x_variant":[
        "\u9676\u5bb6"
    ],
    "name:zho_x_preferred":[
        "\u9676\u5bb6"
    ],
    "wof:name":"Taojia",
    "wof:placetype":"locality"
},
  "geometry": {"coordinates":[122.42818,41.60007],"type":"Point"}
}