{
  "type": "Feature",
  "properties": {
    "gn:admin1_code":"30.0",
    "gn:asciiname":"Changang",
    "gn:country_code":"CN",
    "gn:dem":9,
    "gn:feature_class":"P",
    "gn:feature_code":"PPL",
    "gn:name":"Changang",
    "gn:population":0,
    "gn:timezone":"Asia/Shanghai",
    "iso:country":"CN",
    "name:und_x_variant":[
        "\u7f20\u5c97"
    ],
    "name:zho_x_preferred":[
        "\u7f20\u5c97"
    ],
    "wof:name":"Changang",
    "wof:placetype":"locality"
},
  "geometry": {"coordinates":[113.02065,23.45249],"type":"Point"}
}