{
  "type": "Feature",
  "properties": {
    "gn:admin1_code":"25.0",
    "gn:asciiname":"Erfucun",
    "gn:country_code":"CN",
    "gn:dem":45,
    "gn:feature_class":"P",
    "gn:feature_code":"PPL",
    "gn:name":"Erfucun",
    "gn:population":0,
    "gn:timezone":"Asia/Shanghai",
    "iso:country":"CN",
    "name:zho_x_preferred":[
        "\u4e8c\u5e9c\u6751"
    ],
    "wof:name":"Erfucun",
    "wof:placetype":"locality"
},
  "geometry": {"coordinates":[118.61637,36.76535],"type":"Point"}
}