{
  "type": "Feature",
  "properties": {
    "gn:admin1_code":"24.0",
    "gn:asciiname":"Yezhuwa Muchang",
    "gn:country_code":"CN",
    "gn:dem":2042,
    "gn:feature_class":"P",
    "gn:feature_code":"PPLF",
    "gn:name":"Yezhuwa Muchang",
    "gn:population":0,
    "gn:timezone":"Asia/Shanghai",
    "iso:country":"CN",
    "name:zho_x_preferred":[
        "\u91ce\u732a\u7a8a\u7267\u573a"
    ],
    "wof:name":"Yezhuwa Muchang",
    "wof:placetype":"locality"
},
  "geometry": {"coordinates":[112.70184,39.08644],"type":"Point"}
}