{
  "type": "Feature",
  "properties": {
    "gn:admin1_code":"02",
    "gn:asciiname":"Zhikou",
    "gn:country_code":"CN",
    "gn:dem":15,
    "gn:feature_class":"P",
    "gn:feature_code":"PPL",
    "gn:name":"Zhikou",
    "gn:population":0,
    "gn:timezone":"Asia/Shanghai",
    "iso:country":"CN",
    "name:und_x_variant":[
        "Chih-k\u2019ou-ts\u2019un",
        "Zhikou"
    ],
    "name:zho_x_preferred":[
        "\u5cd9\u53e3"
    ],
    "wof:name":"Zhikou",
    "wof:placetype":"locality"
},
  "geometry": {"coordinates":[120.7517,28.16535],"type":"Point"}
}