{
  "type": "Feature",
  "properties": {
    "gn:admin1_code":"12.0",
    "gn:asciiname":"Gaojiabian",
    "gn:country_code":"CN",
    "gn:dem":996,
    "gn:feature_class":"P",
    "gn:feature_code":"PPL",
    "gn:name":"Gaojiabian",
    "gn:population":0,
    "gn:timezone":"Asia/Shanghai",
    "iso:country":"CN",
    "name:zho_x_preferred":[
        "\u9ad8\u5bb6\u97ad"
    ],
    "wof:name":"Gaojiabian",
    "wof:placetype":"locality"
},
  "geometry": {"coordinates":[109.60996000000002,32.47685999999999],"type":"Point"}
}