{
  "type": "Feature",
  "properties": {
    "gn:admin1_code":"29.0",
    "gn:asciiname":"Wangjia",
    "gn:country_code":"CN",
    "gn:dem":1063,
    "gn:feature_class":"P",
    "gn:feature_code":"PPL",
    "gn:name":"Wangjia",
    "gn:population":0,
    "gn:timezone":"Asia/Shanghai",
    "iso:country":"CN",
    "name:zho_x_preferred":[
        "\u4ea1\u621b"
    ],
    "wof:name":"Wangjia",
    "wof:placetype":"locality"
},
  "geometry": {"coordinates":[99.83410000000001,23.5294],"type":"Point"}
}