{
  "type": "Feature",
  "properties": {
    "gn:admin1_code":"25",
    "gn:asciiname":"Xiahouhe",
    "gn:country_code":"CN",
    "gn:dem":217,
    "gn:feature_class":"P",
    "gn:feature_code":"PPL",
    "gn:name":"Xiahouhe",
    "gn:population":0,
    "gn:timezone":"Asia/Shanghai",
    "iso:country":"CN",
    "name:zho_x_preferred":[
        "\u4e0b\u540e\u6cb3"
    ],
    "wof:name":"Xiahouhe",
    "wof:placetype":"locality"
},
  "geometry": {"coordinates":[117.601,35.3146],"type":"Point"}
}