{
  "type": "Feature",
  "properties": {
    "gn:admin1_code":"1.0",
    "gn:asciiname":"Luchai'an",
    "gn:country_code":"CN",
    "gn:dem":6,
    "gn:feature_class":"P",
    "gn:feature_code":"PPL",
    "gn:name":"Luchai\u2019an",
    "gn:population":0,
    "gn:timezone":"Asia/Shanghai",
    "iso:country":"CN",
    "name:zho_x_preferred":[
        "\u82a6\u67f4\u5eb5"
    ],
    "name:zho_x_variant":[
        "Luchai\u2019an"
    ],
    "wof:name":"Luchai'an",
    "wof:placetype":"locality"
},
  "geometry": {"coordinates":[118.63243,31.39496],"type":"Point"}
}