{
  "type": "Feature",
  "properties": {
    "gn:admin1_code":"16.0",
    "gn:asciiname":"Yinfeng",
    "gn:country_code":"CN",
    "gn:dem":175,
    "gn:feature_class":"P",
    "gn:feature_code":"PPL",
    "gn:name":"Yinfeng",
    "gn:population":0,
    "gn:timezone":"Asia/Shanghai",
    "iso:country":"CN",
    "name:zho_x_preferred":[
        "\u94f6\u5cf0"
    ],
    "wof:name":"Yinfeng",
    "wof:placetype":"locality"
},
  "geometry": {"coordinates":[108.15000000000001,23.7067],"type":"Point"}
}