{
  "type": "Feature",
  "properties": {
    "gn:admin1_code":"10.0",
    "gn:asciiname":"Bamudi",
    "gn:country_code":"CN",
    "gn:dem":1228,
    "gn:feature_class":"P",
    "gn:feature_code":"PPL",
    "gn:name":"Bamudi",
    "gn:population":0,
    "gn:timezone":"Asia/Shanghai",
    "iso:country":"CN",
    "name:zho_x_preferred":[
        "\u516b\u4ea9\u5730"
    ],
    "wof:name":"Bamudi",
    "wof:placetype":"locality"
},
  "geometry": {"coordinates":[114.83839,39.47272],"type":"Point"}
}