{
  "type": "Feature",
  "properties": {
    "gn:admin1_code":"11.0",
    "gn:asciiname":"Dengjiayuan",
    "gn:country_code":"CN",
    "gn:dem":30,
    "gn:feature_class":"P",
    "gn:feature_code":"PPL",
    "gn:name":"Dengjiayuan",
    "gn:population":0,
    "gn:timezone":"Asia/Shanghai",
    "iso:country":"CN",
    "name:zho_x_preferred":[
        "\u9093\u5bb6\u57b8"
    ],
    "wof:name":"Dengjiayuan",
    "wof:placetype":"locality"
},
  "geometry": {"coordinates":[112.28006999999999,29.18045],"type":"Point"}
}