{
  "type": "Feature",
  "properties": {
    "gn:admin1_code":"5.0",
    "gn:asciiname":"Yangshulincun",
    "gn:country_code":"CN",
    "gn:dem":204,
    "gn:feature_class":"P",
    "gn:feature_code":"PPL",
    "gn:name":"Yangshulincun",
    "gn:population":0,
    "gn:timezone":"Asia/Shanghai",
    "iso:country":"CN",
    "name:zho_x_preferred":[
        "\u6768\u6811\u6797\u6751"
    ],
    "wof:name":"Yangshulincun",
    "wof:placetype":"locality"
},
  "geometry": {"coordinates":[124.51730000000001,43.85605],"type":"Point"}
}