{
  "type": "Feature",
  "properties": {
    "gn:admin1_code":"25",
    "gn:asciiname":"Zhanghuanzhuang",
    "gn:country_code":"CN",
    "gn:dem":19,
    "gn:feature_class":"P",
    "gn:feature_code":"PPL",
    "gn:name":"Zhanghuanzhuang",
    "gn:population":0,
    "gn:timezone":"Asia/Shanghai",
    "iso:country":"CN",
    "name:zho_x_preferred":[
        "\u5f20\u7115\u5e84"
    ],
    "wof:name":"Zhanghuanzhuang",
    "wof:placetype":"locality"
},
  "geometry": {"coordinates":[116.67700000000001,37.0759],"type":"Point"}
}