{
  "type": "Feature",
  "properties": {
    "gn:admin1_code":"9.0",
    "gn:asciiname":"Hongtangcun",
    "gn:country_code":"CN",
    "gn:dem":101,
    "gn:feature_class":"P",
    "gn:feature_code":"PPL",
    "gn:name":"Hongtangcun",
    "gn:population":0,
    "gn:timezone":"Asia/Shanghai",
    "iso:country":"CN",
    "name:und_x_variant":[
        "\u6d2a\u5802\u6751"
    ],
    "name:zho_x_preferred":[
        "\u6d2a\u5802\u6751"
    ],
    "wof:name":"Hongtangcun",
    "wof:placetype":"locality"
},
  "geometry": {"coordinates":[113.95471999999999,33.03562],"type":"Point"}
}