{
  "type": "Feature",
  "properties": {
    "gn:admin1_code":"12.0",
    "gn:asciiname":"Maojiawan",
    "gn:country_code":"CN",
    "gn:dem":50,
    "gn:feature_class":"P",
    "gn:feature_code":"PPL",
    "gn:name":"Maojiawan",
    "gn:population":0,
    "gn:timezone":"Asia/Shanghai",
    "iso:country":"CN",
    "name:zho_x_preferred":[
        "Maojiawan"
    ],
    "name:zho_x_variant":[
        "\u6bdb\u5bb6\u6e7e"
    ],
    "wof:name":"Maojiawan",
    "wof:placetype":"locality"
},
  "geometry": {"coordinates":[111.5284,30.29972],"type":"Point"}
}