{
  "type": "Feature",
  "properties": {
    "gn:admin1_code":"30.0",
    "gn:asciiname":"Daping",
    "gn:country_code":"CN",
    "gn:dem":805,
    "gn:feature_class":"P",
    "gn:feature_code":"PPLA4",
    "gn:name":"Daping",
    "gn:population":0,
    "gn:timezone":"Asia/Shanghai",
    "iso:country":"CN",
    "name:ceb_x_preferred":[
        "Daping"
    ],
    "name:deu_x_preferred":[
        "Daping"
    ],
    "name:swe_x_preferred":[
        "Daping"
    ],
    "name:und_x_variant":[
        "\u5927\u5e73\u9547",
        "Daping Zhen"
    ],
    "name:zho_x_preferred":[
        "Daping"
    ],
    "name:zho_x_variant":[
        "\u5927\u5e73"
    ],
    "wof:name":"Daping",
    "wof:placetype":"locality"
},
  "geometry": {"coordinates":[112.15779999999999,24.65136],"type":"Point"}
}