{
  "type": "Feature",
  "properties": {
    "gn:admin1_code":"18",
    "gn:asciiname":"Dafazhong",
    "gn:country_code":"CN",
    "gn:dem":1696,
    "gn:feature_class":"P",
    "gn:feature_code":"PPL",
    "gn:name":"Dafazhong",
    "gn:population":0,
    "gn:timezone":"Asia/Shanghai",
    "iso:country":"CN",
    "name:zho_x_preferred":[
        "\u5927\u53d1\u4ef2"
    ],
    "wof:name":"Dafazhong",
    "wof:placetype":"locality"
},
  "geometry": {"coordinates":[104.98999999999999,26.7821],"type":"Point"}
}