{
  "type": "Feature",
  "properties": {
    "gn:admin1_code":"15.0",
    "gn:asciiname":"Fengjiaxia",
    "gn:country_code":"CN",
    "gn:dem":1362,
    "gn:feature_class":"P",
    "gn:feature_code":"PPL",
    "gn:name":"Fengjiaxia",
    "gn:population":0,
    "gn:timezone":"Asia/Shanghai",
    "iso:country":"CN",
    "name:und_x_variant":[
        "\u51af\u5bb6\u5ce1"
    ],
    "wof:name":"Fengjiaxia",
    "wof:placetype":"locality"
},
  "geometry": {"coordinates":[105.61150000000001,33.37421],"type":"Point"}
}