{
  "type": "Feature",
  "properties": {
    "gn:admin1_code":"19.0",
    "gn:asciiname":"Longtangou",
    "gn:country_code":"CN",
    "gn:dem":278,
    "gn:feature_class":"P",
    "gn:feature_code":"PPL",
    "gn:name":"Longtangou",
    "gn:population":0,
    "gn:timezone":"Asia/Shanghai",
    "iso:country":"CN",
    "name:zho_x_preferred":[
        "\u9f99\u6f6d\u6c9f"
    ],
    "wof:name":"Longtangou",
    "wof:placetype":"locality"
},
  "geometry": {"coordinates":[120.28700000000001,41.1992],"type":"Point"}
}