{
  "type": "Feature",
  "properties": {
    "gn:admin1_code":"4.0",
    "gn:asciiname":"Tongxingxu",
    "gn:country_code":"CN",
    "gn:dem":-1,
    "gn:feature_class":"P",
    "gn:feature_code":"PPL",
    "gn:name":"Tongxingxu",
    "gn:population":0,
    "gn:timezone":"Asia/Shanghai",
    "iso:country":"CN",
    "name:und_x_variant":[
        "\u540c\u5174\u5729"
    ],
    "name:zho_x_preferred":[
        "\u540c\u5174\u5729"
    ],
    "wof:name":"Tongxingxu",
    "wof:placetype":"locality"
},
  "geometry": {"coordinates":[120.17489999999999,31.96593],"type":"Point"}
}