{
  "type": "Feature",
  "properties": {
    "gn:admin1_code":"4.0",
    "gn:asciiname":"Yulongcun",
    "gn:country_code":"CN",
    "gn:dem":5,
    "gn:feature_class":"P",
    "gn:feature_code":"PPL",
    "gn:name":"Yulongcun",
    "gn:population":0,
    "gn:timezone":"Asia/Shanghai",
    "iso:country":"CN",
    "name:zho_x_preferred":[
        "\u7389\u9f99\u6751"
    ],
    "wof:name":"Yulongcun",
    "wof:placetype":"locality"
},
  "geometry": {"coordinates":[119.91228999999998,34.18573],"type":"Point"}
}