{
  "type": "Feature",
  "properties": {
    "gn:admin1_code":"33.0",
    "gn:asciiname":"Shanghualishu",
    "gn:country_code":"CN",
    "gn:dem":475,
    "gn:feature_class":"P",
    "gn:feature_code":"PPL",
    "gn:name":"Shanghualishu",
    "gn:population":0,
    "gn:timezone":"Asia/Shanghai",
    "iso:country":"CN",
    "name:zho_x_preferred":[
        "\u4e0a\u82b1\u6817\u6811"
    ],
    "wof:name":"Shanghualishu",
    "wof:placetype":"locality"
},
  "geometry": {"coordinates":[109.63999,31.65233],"type":"Point"}
}