{
  "type": "Feature",
  "properties": {
    "gn:admin1_code":"19.0",
    "gn:asciiname":"Yanjiangcun",
    "gn:country_code":"CN",
    "gn:dem":131,
    "gn:feature_class":"P",
    "gn:feature_code":"PPL",
    "gn:name":"Yanjiangcun",
    "gn:population":0,
    "gn:timezone":"Asia/Shanghai",
    "iso:country":"CN",
    "name:zho_x_preferred":[
        "\u6cbf\u6c5f\u6751"
    ],
    "wof:name":"Yanjiangcun",
    "wof:placetype":"locality"
},
  "geometry": {"coordinates":[125.22459000000001,40.66315],"type":"Point"}
}