{
  "type": "Feature",
  "properties": {
    "gn:admin1_code":"26.0",
    "gn:asciiname":"Guzhai",
    "gn:country_code":"CN",
    "gn:dem":349,
    "gn:feature_class":"P",
    "gn:feature_code":"PPL",
    "gn:name":"Guzhai",
    "gn:population":0,
    "gn:timezone":"Asia/Shanghai",
    "iso:country":"CN",
    "name:zho_x_preferred":[
        "\u6545\u5be8"
    ],
    "wof:name":"Guzhai",
    "wof:placetype":"locality"
},
  "geometry": {"coordinates":[109.57875,34.65677],"type":"Point"}
}