{
  "type": "Feature",
  "properties": {
    "gn:admin1_code":"23.0",
    "gn:asciiname":"Shatiaobang",
    "gn:country_code":"CN",
    "gn:dem":5,
    "gn:feature_class":"P",
    "gn:feature_code":"PPL",
    "gn:name":"Shatiaobang",
    "gn:population":0,
    "gn:timezone":"Asia/Shanghai",
    "iso:country":"CN",
    "name:und_x_variant":[
        "\u6c99\u6761\u6d5c"
    ],
    "wof:name":"Shatiaobang",
    "wof:placetype":"locality"
},
  "geometry": {"coordinates":[121.27567000000001,30.87482],"type":"Point"}
}