{
  "type": "Feature",
  "properties": {
    "gn:admin1_code":"23.0",
    "gn:asciiname":"Beizhangjiao",
    "gn:country_code":"CN",
    "gn:dem":8,
    "gn:feature_class":"P",
    "gn:feature_code":"PPL",
    "gn:name":"Beizhangjiao",
    "gn:population":0,
    "gn:timezone":"Asia/Shanghai",
    "iso:country":"CN",
    "name:zho_x_preferred":[
        "Beizhangjiao"
    ],
    "name:zho_x_variant":[
        "\u5317\u5f20\u89d2"
    ],
    "wof:name":"Beizhangjiao",
    "wof:placetype":"locality"
},
  "geometry": {"coordinates":[121.23245,31.23585],"type":"Point"}
}