{
  "type": "Feature",
  "properties": {
    "gn:admin1_code":"14.0",
    "gn:asciiname":"Juelongcun",
    "gn:country_code":"CN",
    "gn:dem":3430,
    "gn:feature_class":"P",
    "gn:feature_code":"PPL",
    "gn:name":"Juelongcun",
    "gn:population":0,
    "gn:timezone":"Asia/Urumqi",
    "iso:country":"CN",
    "name:zho_x_preferred":[
        "\u89c9\u9f99\u6751"
    ],
    "wof:name":"Juelongcun",
    "wof:placetype":"locality"
},
  "geometry": {"coordinates":[96.42968,30.67834],"type":"Point"}
}