{
  "type": "Feature",
  "properties": {
    "gn:admin1_code":"4.0",
    "gn:asciiname":"Zaofangcun",
    "gn:country_code":"CN",
    "gn:dem":7,
    "gn:feature_class":"P",
    "gn:feature_code":"PPL",
    "gn:name":"Zaofangcun",
    "gn:population":0,
    "gn:timezone":"Asia/Shanghai",
    "iso:country":"CN",
    "name:zho_x_preferred":[
        "\u7cdf\u574a\u6751"
    ],
    "wof:name":"Zaofangcun",
    "wof:placetype":"locality"
},
  "geometry": {"coordinates":[119.32229,32.68151],"type":"Point"}
}