{
  "type": "Feature",
  "properties": {
    "gn:admin1_code":"32.0",
    "gn:asciiname":"Yexiangzi",
    "gn:country_code":"CN",
    "gn:dem":488,
    "gn:feature_class":"P",
    "gn:feature_code":"PPL",
    "gn:name":"Yexiangzi",
    "gn:population":0,
    "gn:timezone":"Asia/Shanghai",
    "iso:country":"CN",
    "name:zho_x_preferred":[
        "\u53f6\u5df7\u5b50"
    ],
    "wof:name":"Yexiangzi",
    "wof:placetype":"locality"
},
  "geometry": {"coordinates":[103.61799999999999,30.3445],"type":"Point"}
}