{
  "type": "Feature",
  "properties": {
    "gn:admin1_code":"30.0",
    "gn:asciiname":"Hubikeng",
    "gn:country_code":"CN",
    "gn:dem":524,
    "gn:feature_class":"P",
    "gn:feature_code":"PPL",
    "gn:name":"Hubikeng",
    "gn:population":0,
    "gn:timezone":"Asia/Shanghai",
    "iso:country":"CN",
    "name:zho_x_preferred":[
        "\u80e1\u5fc5\u5751"
    ],
    "wof:name":"Hubikeng",
    "wof:placetype":"locality"
},
  "geometry": {"coordinates":[112.39487,24.04272000000001],"type":"Point"}
}