{
  "type": "Feature",
  "properties": {
    "gn:admin1_code":"26.0",
    "gn:asciiname":"Dengcaoba",
    "gn:country_code":"CN",
    "gn:dem":757,
    "gn:feature_class":"P",
    "gn:feature_code":"PPL",
    "gn:name":"Dengcaoba",
    "gn:population":0,
    "gn:timezone":"Asia/Shanghai",
    "iso:country":"CN",
    "name:und_x_variant":[
        "\u706f\u8349\u575d"
    ],
    "wof:name":"Dengcaoba",
    "wof:placetype":"locality"
},
  "geometry": {"coordinates":[106.07447999999999,32.90395],"type":"Point"}
}