{
  "type": "Feature",
  "properties": {
    "gn:admin1_code":"26.0",
    "gn:asciiname":"Jingjiagou",
    "gn:country_code":"CN",
    "gn:dem":1289,
    "gn:feature_class":"P",
    "gn:feature_code":"PPL",
    "gn:name":"Jingjiagou",
    "gn:population":0,
    "gn:timezone":"Asia/Shanghai",
    "iso:country":"CN",
    "name:und_x_variant":[
        "\u656c\u5bb6\u6c9f"
    ],
    "wof:name":"Jingjiagou",
    "wof:placetype":"locality"
},
  "geometry": {"coordinates":[107.68725999999999,34.71381],"type":"Point"}
}