{
  "type": "Feature",
  "properties": {
    "gn:admin1_code":"9.0",
    "gn:asciiname":"Huiquangou",
    "gn:country_code":"CN",
    "gn:dem":302,
    "gn:feature_class":"P",
    "gn:feature_code":"PPL",
    "gn:name":"Huiquangou",
    "gn:population":0,
    "gn:timezone":"Asia/Shanghai",
    "iso:country":"CN",
    "name:zho_x_preferred":[
        "\u8f89\u6cc9\u6c9f"
    ],
    "wof:name":"Huiquangou",
    "wof:placetype":"locality"
},
  "geometry": {"coordinates":[114.05475,35.81571],"type":"Point"}
}