{
  "type": "Feature",
  "properties": {
    "gn:admin1_code":"1.0",
    "gn:asciiname":"Shangguancun",
    "gn:country_code":"CN",
    "gn:dem":48,
    "gn:feature_class":"P",
    "gn:feature_code":"PPL",
    "gn:name":"Shangguancun",
    "gn:population":0,
    "gn:timezone":"Asia/Shanghai",
    "iso:country":"CN",
    "name:zho_x_preferred":[
        "\u5c1a\u5b98\u6751"
    ],
    "wof:name":"Shangguancun",
    "wof:placetype":"locality"
},
  "geometry": {"coordinates":[117.78977,32.39858],"type":"Point"}
}