{
  "type": "Feature",
  "properties": {
    "gn:admin1_code":"3.0",
    "gn:asciiname":"Jianshan",
    "gn:country_code":"CN",
    "gn:dem":149,
    "gn:feature_class":"P",
    "gn:feature_code":"PPL",
    "gn:name":"Jianshan",
    "gn:population":0,
    "gn:timezone":"Asia/Shanghai",
    "iso:country":"CN",
    "name:zho_x_preferred":[
        "\u9274\u5c71"
    ],
    "wof:name":"Jianshan",
    "wof:placetype":"locality"
},
  "geometry": {"coordinates":[113.955,27.678],"type":"Point"}
}