{
  "type": "Feature",
  "properties": {
    "gn:admin1_code":"29.0",
    "gn:asciiname":"Xiabaida",
    "gn:country_code":"CN",
    "gn:dem":1648,
    "gn:feature_class":"P",
    "gn:feature_code":"PPL",
    "gn:name":"Xiabaida",
    "gn:population":0,
    "gn:timezone":"Asia/Shanghai",
    "iso:country":"CN",
    "name:zho_x_preferred":[
        "\u4e0b\u767d\u8fbe"
    ],
    "wof:name":"Xiabaida",
    "wof:placetype":"locality"
},
  "geometry": {"coordinates":[102.944,24.0118],"type":"Point"}
}