{
  "type": "Feature",
  "properties": {
    "gn:admin1_code":"30",
    "gn:asciiname":"Jiang'ouwei",
    "gn:country_code":"CN",
    "gn:dem":-2,
    "gn:feature_class":"P",
    "gn:feature_code":"PPL",
    "gn:name":"Jiang\u2019ouwei",
    "gn:population":0,
    "gn:timezone":"Asia/Shanghai",
    "iso:country":"CN",
    "name:zho_x_preferred":[
        "Jiang\u2019ouwei"
    ],
    "wof:name":"Jiang'ouwei",
    "wof:placetype":"locality"
},
  "geometry": {"coordinates":[113.53333000000001,22.88333],"type":"Point"}
}