{
  "type": "Feature",
  "properties": {
    "gn:admin1_code":"8.0",
    "gn:asciiname":"Jiuli Jiubeigang",
    "gn:country_code":"CN",
    "gn:dem":275,
    "gn:feature_class":"P",
    "gn:feature_code":"PPL",
    "gn:name":"Jiuli Jiubeigang",
    "gn:population":0,
    "gn:timezone":"Asia/Shanghai",
    "iso:country":"CN",
    "name:zho_x_preferred":[
        "\u4e5d\u91cc\u4e5d\u5317\u5c97"
    ],
    "wof:name":"Jiuli Jiubeigang",
    "wof:placetype":"locality"
},
  "geometry": {"coordinates":[127.3717,47.67642],"type":"Point"}
}