{
  "type": "Feature",
  "properties": {
    "gn:admin1_code":"29.0",
    "gn:asciiname":"Qingmiaoshan",
    "gn:country_code":"CN",
    "gn:dem":1980,
    "gn:feature_class":"P",
    "gn:feature_code":"PPL",
    "gn:name":"Qingmiaoshan",
    "gn:population":0,
    "gn:timezone":"Asia/Shanghai",
    "iso:country":"CN",
    "name:zho_x_preferred":[
        "\u9752\u82d7\u5c71"
    ],
    "wof:name":"Qingmiaoshan",
    "wof:placetype":"locality"
},
  "geometry": {"coordinates":[102.514,25.1564],"type":"Point"}
}