{
  "type": "Feature",
  "properties": {
    "gn:admin1_code":"16.0",
    "gn:asciiname":"Wentaidu",
    "gn:country_code":"CN",
    "gn:dem":399,
    "gn:feature_class":"P",
    "gn:feature_code":"PPL",
    "gn:name":"Wentaidu",
    "gn:population":0,
    "gn:timezone":"Asia/Shanghai",
    "iso:country":"CN",
    "name:zho_x_preferred":[
        "\u6587\u53f0\u809a"
    ],
    "wof:name":"Wentaidu",
    "wof:placetype":"locality"
},
  "geometry": {"coordinates":[110.47799999999999,22.875],"type":"Point"}
}