{
  "type": "Feature",
  "properties": {
    "gn:admin1_code":"19.0",
    "gn:asciiname":"Zhangjia Wobu",
    "gn:country_code":"CN",
    "gn:dem":114,
    "gn:feature_class":"P",
    "gn:feature_code":"PPL",
    "gn:name":"Zhangjia Wobu",
    "gn:population":0,
    "gn:timezone":"Asia/Shanghai",
    "iso:country":"CN",
    "name:und_x_variant":[
        "Zhangjiawobao",
        "Zhangjia Wobu"
    ],
    "name:zho_x_preferred":[
        "\u5f20\u5bb6\u7a9d\u5821"
    ],
    "wof:name":"Zhangjia Wobu",
    "wof:placetype":"locality"
},
  "geometry": {"coordinates":[123.83996999999999,43.04717],"type":"Point"}
}