{
  "type": "Feature",
  "properties": {
    "gn:admin1_code":"30",
    "gn:asciiname":"Henglan",
    "gn:country_code":"CN",
    "gn:dem":5,
    "gn:feature_class":"P",
    "gn:feature_code":"PPLA4",
    "gn:name":"Henglan",
    "gn:population":0,
    "gn:timezone":"Asia/Shanghai",
    "iso:country":"CN",
    "name:und_x_variant":[
        "Henglan Zhen",
        "\u6a2a\u680f\u9547"
    ],
    "name:zho_x_preferred":[
        "\u6a2a\u680f"
    ],
    "wof:name":"Henglan",
    "wof:placetype":"locality"
},
  "geometry": {"coordinates":[113.24845999999999,22.53372],"type":"Point"}
}