{
  "type": "Feature",
  "properties": {
    "gn:admin1_code":"24.0",
    "gn:asciiname":"Daxingcun",
    "gn:country_code":"CN",
    "gn:dem":492,
    "gn:feature_class":"P",
    "gn:feature_code":"PPL",
    "gn:name":"Daxingcun",
    "gn:population":0,
    "gn:timezone":"Asia/Shanghai",
    "iso:country":"CN",
    "name:zho_x_preferred":[
        "\u5927\u5174\u6751"
    ],
    "wof:name":"Daxingcun",
    "wof:placetype":"locality"
},
  "geometry": {"coordinates":[110.55522000000001,35.41647000000001],"type":"Point"}
}