{
  "type": "Feature",
  "properties": {
    "gn:admin1_code":"19.0",
    "gn:asciiname":"Hejiaxinzi",
    "gn:country_code":"CN",
    "gn:dem":105,
    "gn:feature_class":"P",
    "gn:feature_code":"PPL",
    "gn:name":"Hejiaxinzi",
    "gn:population":0,
    "gn:timezone":"Asia/Shanghai",
    "iso:country":"CN",
    "name:zho_x_preferred":[
        "\u4f55\u5bb6\u4fe1\u5b50"
    ],
    "wof:name":"Hejiaxinzi",
    "wof:placetype":"locality"
},
  "geometry": {"coordinates":[123.24601,42.83643],"type":"Point"}
}