{
  "type": "Feature",
  "properties": {
    "gn:admin1_code":"29.0",
    "gn:asciiname":"Hongshaping",
    "gn:country_code":"CN",
    "gn:dem":772,
    "gn:feature_class":"P",
    "gn:feature_code":"PPL",
    "gn:name":"Hongshaping",
    "gn:population":0,
    "gn:timezone":"Asia/Shanghai",
    "iso:country":"CN",
    "name:zho_x_preferred":[
        "\u7ea2\u6c99\u576a"
    ],
    "wof:name":"Hongshaping",
    "wof:placetype":"locality"
},
  "geometry": {"coordinates":[104.08199999999999,28.0297],"type":"Point"}
}