{
  "type": "Feature",
  "properties": {
    "gn:admin1_code":"26.0",
    "gn:asciiname":"Liujiazhuangcun",
    "gn:country_code":"CN",
    "gn:dem":829,
    "gn:feature_class":"P",
    "gn:feature_code":"PPL",
    "gn:name":"Liujiazhuangcun",
    "gn:population":0,
    "gn:timezone":"Asia/Shanghai",
    "iso:country":"CN",
    "name:zho_x_preferred":[
        "\u5218\u5bb6\u5e84\u6751"
    ],
    "wof:name":"Liujiazhuangcun",
    "wof:placetype":"locality"
},
  "geometry": {"coordinates":[110.12845,33.51709],"type":"Point"}
}