{
  "type": "Feature",
  "properties": {
    "gn:admin1_code":"2",
    "gn:asciiname":"Banluyang",
    "gn:country_code":"CN",
    "gn:dem":538,
    "gn:feature_class":"P",
    "gn:feature_code":"PPL",
    "gn:name":"Banluyang",
    "gn:population":0,
    "gn:timezone":"Asia/Shanghai",
    "iso:country":"CN",
    "name:zho_x_preferred":[
        "\u534a\u8def\u579f"
    ],
    "wof:name":"Banluyang",
    "wof:placetype":"locality"
},
  "geometry": {"coordinates":[119.75539000000001,27.40321],"type":"Point"}
}