{
  "type": "Feature",
  "properties": {
    "gn:admin1_code":"22",
    "gn:asciiname":"Badaohe",
    "gn:country_code":"CN",
    "gn:dem":405,
    "gn:feature_class":"P",
    "gn:feature_code":"PPL",
    "gn:name":"Badaohe",
    "gn:population":0,
    "gn:timezone":"Asia/Shanghai",
    "iso:country":"CN",
    "name:zho_x_preferred":[
        "\u516b\u9053\u6cb3"
    ],
    "wof:name":"Badaohe",
    "wof:placetype":"locality"
},
  "geometry": {"coordinates":[116.70117999999999,40.85582],"type":"Point"}
}