{
  "type": "Feature",
  "properties": {
    "gn:admin1_code":"4.0",
    "gn:asciiname":"Panwan Wuzu",
    "gn:country_code":"CN",
    "gn:dem":0,
    "gn:feature_class":"P",
    "gn:feature_code":"PPLF",
    "gn:name":"Panwan Wuzu",
    "gn:population":0,
    "gn:timezone":"Asia/Shanghai",
    "iso:country":"CN",
    "name:zho_x_preferred":[
        "\u76d8\u6e7e\u4e94\u7ec4"
    ],
    "wof:name":"Panwan Wuzu",
    "wof:placetype":"locality"
},
  "geometry": {"coordinates":[120.202,33.5525],"type":"Point"}
}