{
  "type": "Feature",
  "properties": {
    "gn:admin1_code":"9.0",
    "gn:asciiname":"Xiaoshimen",
    "gn:country_code":"CN",
    "gn:dem":153,
    "gn:feature_class":"P",
    "gn:feature_code":"PPL",
    "gn:name":"Xiaoshimen",
    "gn:population":0,
    "gn:timezone":"Asia/Shanghai",
    "iso:country":"CN",
    "name:und_x_variant":[
        "\u5c0f\u77f3\u95e8",
        "Xiaoshimen"
    ],
    "wof:name":"Xiaoshimen",
    "wof:placetype":"locality"
},
  "geometry": {"coordinates":[112.94905,33.65534],"type":"Point"}
}