{
  "type": "Feature",
  "properties": {
    "gn:admin1_code":"32",
    "gn:asciiname":"Hengxichang",
    "gn:country_code":"CN",
    "gn:dem":275,
    "gn:feature_class":"P",
    "gn:feature_code":"PPL",
    "gn:name":"Hengxichang",
    "gn:population":0,
    "gn:timezone":"Asia/Shanghai",
    "iso:country":"CN",
    "name:und_x_variant":[
        "Hengxi",
        "Hengxichang"
    ],
    "name:zho_x_preferred":[
        "\u6a2a\u6eaa\u573a"
    ],
    "wof:name":"Hengxichang",
    "wof:placetype":"locality"
},
  "geometry": {"coordinates":[105.01615,29.0807],"type":"Point"}
}