{
  "type": "Feature",
  "properties": {
    "gn:admin1_code":"1.0",
    "gn:asciiname":"Guanyaocun",
    "gn:country_code":"CN",
    "gn:dem":57,
    "gn:feature_class":"P",
    "gn:feature_code":"PPL",
    "gn:name":"Guanyaocun",
    "gn:population":0,
    "gn:timezone":"Asia/Shanghai",
    "iso:country":"CN",
    "name:zho_x_preferred":[
        "\u7f50\u7a91\u6751"
    ],
    "wof:name":"Guanyaocun",
    "wof:placetype":"locality"
},
  "geometry": {"coordinates":[116.82111999999999,31.29754],"type":"Point"}
}