{
  "type": "Feature",
  "properties": {
    "gn:admin1_code":"6.0",
    "gn:asciiname":"Zanxiazhuang",
    "gn:country_code":"CN",
    "gn:dem":1950,
    "gn:feature_class":"P",
    "gn:feature_code":"PPL",
    "gn:name":"Zanxiazhuang",
    "gn:population":0,
    "gn:timezone":"Asia/Shanghai",
    "iso:country":"CN",
    "name:und_x_variant":[
        "\u8d5e\u4e0b\u5e84"
    ],
    "wof:name":"Zanxiazhuang",
    "wof:placetype":"locality"
},
  "geometry": {"coordinates":[102.24243,35.87325999999999],"type":"Point"}
}