{
  "type": "Feature",
  "properties": {
    "gn:admin1_code":"19.0",
    "gn:asciiname":"Hemu",
    "gn:country_code":"CN",
    "gn:dem":95,
    "gn:feature_class":"P",
    "gn:feature_code":"PPL",
    "gn:name":"Hemu",
    "gn:population":0,
    "gn:timezone":"Asia/Shanghai",
    "iso:country":"CN",
    "name:und_x_variant":[
        "\u548c\u7766"
    ],
    "name:zho_x_preferred":[
        "\u548c\u7766"
    ],
    "wof:name":"Hemu",
    "wof:placetype":"locality"
},
  "geometry": {"coordinates":[122.17418000000001,42.25992],"type":"Point"}
}