{
  "type": "Feature",
  "properties": {
    "gn:admin1_code":"02",
    "gn:asciiname":"Balingtoucun",
    "gn:country_code":"CN",
    "gn:dem":217,
    "gn:feature_class":"P",
    "gn:feature_code":"PPL",
    "gn:name":"Balingtoucun",
    "gn:population":0,
    "gn:timezone":"Asia/Shanghai",
    "iso:country":"CN",
    "name:und_x_variant":[
        "Pa-ling-tien",
        "Balingtou",
        "Balingtoucun"
    ],
    "name:zho_x_preferred":[
        "\u516b\u5cad\u5934"
    ],
    "name:zho_x_variant":[
        "\u516b\u5cad\u5934\u6751"
    ],
    "wof:name":"Balingtoucun",
    "wof:placetype":"locality"
},
  "geometry": {"coordinates":[121.47405999999999,28.95282000000001],"type":"Point"}
}