{
  "type": "Feature",
  "properties": {
    "gn:admin1_code":"14",
    "gn:asciiname":"Sangnong",
    "gn:country_code":"CN",
    "gn:dem":4812,
    "gn:feature_class":"P",
    "gn:feature_code":"PPL",
    "gn:name":"Sangnong",
    "gn:population":0,
    "gn:timezone":"Asia/Urumqi",
    "iso:country":"CN",
    "name:zho_x_preferred":[
        "\u6851\u5f04"
    ],
    "wof:name":"Sangnong",
    "wof:placetype":"locality"
},
  "geometry": {"coordinates":[87.76860000000001,31.1434],"type":"Point"}
}