{
  "type": "Feature",
  "properties": {
    "gn:admin1_code":"28.0",
    "gn:asciiname":"Machang",
    "gn:country_code":"CN",
    "gn:dem":7,
    "gn:feature_class":"P",
    "gn:feature_code":"PPLA4",
    "gn:name":"Machang",
    "gn:population":0,
    "gn:timezone":"Asia/Shanghai",
    "iso:country":"CN",
    "name:ceb_x_preferred":[
        "Machang"
    ],
    "name:deu_x_preferred":[
        "Machang"
    ],
    "name:nld_x_preferred":[
        "Machang"
    ],
    "name:nor_x_preferred":[
        "Machang"
    ],
    "name:swe_x_preferred":[
        "Machang"
    ],
    "name:und_x_variant":[
        "Machang Jiedao"
    ],
    "name:vie_x_preferred":[
        "Machang"
    ],
    "name:zho_x_preferred":[
        "\u9a6c\u573a"
    ],
    "name:zho_x_variant":[
        "\u9a6c\u573a\u8857\u9053",
        "\u9a6c\u5382\u9547"
    ],
    "wof:name":"Machang",
    "wof:placetype":"locality"
},
  "geometry": {"coordinates":[117.19253,39.09855],"type":"Point"}
}