{
  "type": "Feature",
  "properties": {
    "gn:admin1_code":"8.0",
    "gn:asciiname":"Xingpingcun",
    "gn:country_code":"CN",
    "gn:dem":168,
    "gn:feature_class":"P",
    "gn:feature_code":"PPL",
    "gn:name":"Xingpingcun",
    "gn:population":0,
    "gn:timezone":"Asia/Shanghai",
    "iso:country":"CN",
    "name:zho_x_preferred":[
        "\u5174\u5e73\u6751"
    ],
    "wof:name":"Xingpingcun",
    "wof:placetype":"locality"
},
  "geometry": {"coordinates":[127.06999999999999,46.51413],"type":"Point"}
}