{
  "type": "Feature",
  "properties": {
    "gn:admin1_code":"2.0",
    "gn:asciiname":"Shuanggui",
    "gn:country_code":"CN",
    "gn:dem":6,
    "gn:feature_class":"P",
    "gn:feature_code":"PPL",
    "gn:name":"Shuanggui",
    "gn:population":0,
    "gn:timezone":"Asia/Shanghai",
    "iso:country":"CN",
    "name:fra_x_preferred":[
        "Shuanggui"
    ],
    "name:und_x_variant":[
        "\u53cc\u6842"
    ],
    "wof:name":"Shuanggui",
    "wof:placetype":"locality"
},
  "geometry": {"coordinates":[119.80829,30.98761],"type":"Point"}
}