{
  "type": "Feature",
  "properties": {
    "gn:admin1_code":"11.0",
    "gn:asciiname":"Baishuwan",
    "gn:country_code":"CN",
    "gn:dem":42,
    "gn:feature_class":"P",
    "gn:feature_code":"PPL",
    "gn:name":"Baishuwan",
    "gn:population":0,
    "gn:timezone":"Asia/Shanghai",
    "iso:country":"CN",
    "name:zho_x_preferred":[
        "\u67cf\u6811\u6e7e"
    ],
    "wof:name":"Baishuwan",
    "wof:placetype":"locality"
},
  "geometry": {"coordinates":[113.02831999999999,27.80729],"type":"Point"}
}