{
  "type": "Feature",
  "properties": {
    "gn:admin1_code":"11",
    "gn:asciiname":"Yantouping",
    "gn:country_code":"CN",
    "gn:dem":370,
    "gn:feature_class":"P",
    "gn:feature_code":"PPL",
    "gn:name":"Yantouping",
    "gn:population":0,
    "gn:timezone":"Asia/Shanghai",
    "iso:country":"CN",
    "name:zho_x_preferred":[
        "\u5ca9\u5934\u576a"
    ],
    "wof:name":"Yantouping",
    "wof:placetype":"locality"
},
  "geometry": {"coordinates":[109.50108,26.88957000000001],"type":"Point"}
}