{
  "type": "Feature",
  "properties": {
    "gn:admin1_code":"29.0",
    "gn:asciiname":"Keluoyu",
    "gn:country_code":"CN",
    "gn:dem":1990,
    "gn:feature_class":"P",
    "gn:feature_code":"PPL",
    "gn:name":"Keluoyu",
    "gn:population":0,
    "gn:timezone":"Asia/Shanghai",
    "iso:country":"CN",
    "name:zho_x_preferred":[
        "\u68f5\u843d\u96e8"
    ],
    "wof:name":"Keluoyu",
    "wof:placetype":"locality"
},
  "geometry": {"coordinates":[104.515,26.2911],"type":"Point"}
}