{
  "type": "Feature",
  "properties": {
    "gn:admin1_code":"8.0",
    "gn:asciiname":"Chenwenqingtun",
    "gn:country_code":"CN",
    "gn:dem":193,
    "gn:feature_class":"P",
    "gn:feature_code":"PPL",
    "gn:name":"Chenwenqingtun",
    "gn:population":0,
    "gn:timezone":"Asia/Shanghai",
    "iso:country":"CN",
    "name:zho_x_preferred":[
        "\u9648\u6587\u5e86\u5c6f"
    ],
    "wof:name":"Chenwenqingtun",
    "wof:placetype":"locality"
},
  "geometry": {"coordinates":[125.79456999999999,46.92194],"type":"Point"}
}