{
  "type": "Feature",
  "properties": {
    "gn:admin1_code":"15.0",
    "gn:asciiname":"Taiyangsi",
    "gn:country_code":"CN",
    "gn:dem":1322,
    "gn:feature_class":"P",
    "gn:feature_code":"PPL",
    "gn:name":"Taiyangsi",
    "gn:population":0,
    "gn:timezone":"Asia/Shanghai",
    "iso:country":"CN",
    "name:zho_x_preferred":[
        "\u592a\u9633\u5bfa"
    ],
    "wof:name":"Taiyangsi",
    "wof:placetype":"locality"
},
  "geometry": {"coordinates":[108.337,35.9433],"type":"Point"}
}