{
  "type": "Feature",
  "properties": {
    "gn:admin1_code":"11.0",
    "gn:asciiname":"Shijiatuan",
    "gn:country_code":"CN",
    "gn:dem":312,
    "gn:feature_class":"P",
    "gn:feature_code":"PPL",
    "gn:name":"Shijiatuan",
    "gn:population":0,
    "gn:timezone":"Asia/Shanghai",
    "iso:country":"CN",
    "name:zho_x_preferred":[
        "\u77f3\u5bb6\u56e2"
    ],
    "wof:name":"Shijiatuan",
    "wof:placetype":"locality"
},
  "geometry": {"coordinates":[109.76000000000001,26.69582],"type":"Point"}
}