{
  "type": "Feature",
  "properties": {
    "gn:admin1_code":"10",
    "gn:asciiname":"Laoyangjia",
    "gn:country_code":"CN",
    "gn:dem":544,
    "gn:feature_class":"P",
    "gn:feature_code":"PPL",
    "gn:name":"Laoyangjia",
    "gn:population":0,
    "gn:timezone":"Asia/Shanghai",
    "iso:country":"CN",
    "name:zho_x_preferred":[
        "\u8001\u6768\u5bb6"
    ],
    "wof:name":"Laoyangjia",
    "wof:placetype":"locality"
},
  "geometry": {"coordinates":[119.57405,40.36414],"type":"Point"}
}