{
  "type": "Feature",
  "properties": {
    "gn:admin1_code":"29.0",
    "gn:asciiname":"Heiyizhao",
    "gn:country_code":"CN",
    "gn:dem":2233,
    "gn:feature_class":"P",
    "gn:feature_code":"PPL",
    "gn:name":"Heiyizhao",
    "gn:population":0,
    "gn:timezone":"Asia/Shanghai",
    "iso:country":"CN",
    "name:zho_x_preferred":[
        "\u9ed1\u4f9d\u7167"
    ],
    "wof:name":"Heiyizhao",
    "wof:placetype":"locality"
},
  "geometry": {"coordinates":[104.182,25.5705],"type":"Point"}
}