{
  "type": "Feature",
  "properties": {
    "gn:admin1_code":"24",
    "gn:asciiname":"Dazuocun",
    "gn:country_code":"CN",
    "gn:dem":957,
    "gn:feature_class":"P",
    "gn:feature_code":"PPL",
    "gn:name":"Dazuocun",
    "gn:population":0,
    "gn:timezone":"Asia/Shanghai",
    "iso:country":"CN",
    "name:und_x_variant":[
        "Ta-tso",
        "Ta-tso-ts\u2019un",
        "Dazuo",
        "Dazuocun"
    ],
    "name:zho_x_preferred":[
        "\u5927\u4f5c\u6751"
    ],
    "wof:name":"Dazuocun",
    "wof:placetype":"locality"
},
  "geometry": {"coordinates":[114.1651,39.43953],"type":"Point"}
}