{
  "type": "Feature",
  "properties": {
    "gn:admin1_code":"25.0",
    "gn:asciiname":"Gushantuncun",
    "gn:country_code":"CN",
    "gn:dem":148,
    "gn:feature_class":"P",
    "gn:feature_code":"PPL",
    "gn:name":"Gushantuncun",
    "gn:population":0,
    "gn:timezone":"Asia/Shanghai",
    "iso:country":"CN",
    "name:zho_x_preferred":[
        "\u53e4\u5c71\u5c6f\u6751"
    ],
    "wof:name":"Gushantuncun",
    "wof:placetype":"locality"
},
  "geometry": {"coordinates":[120.50563,37.24427],"type":"Point"}
}