{
  "type": "Feature",
  "properties": {
    "gn:admin1_code":"9.0",
    "gn:asciiname":"Xilingtou",
    "gn:country_code":"CN",
    "gn:dem":749,
    "gn:feature_class":"P",
    "gn:feature_code":"PPL",
    "gn:name":"Xilingtou",
    "gn:population":0,
    "gn:timezone":"Asia/Shanghai",
    "iso:country":"CN",
    "name:zho_x_preferred":[
        "\u897f\u5cad\u5934"
    ],
    "wof:name":"Xilingtou",
    "wof:placetype":"locality"
},
  "geometry": {"coordinates":[111.19103,34.24799],"type":"Point"}
}