{
  "type": "Feature",
  "properties": {
    "gn:admin1_code":"16.0",
    "gn:asciiname":"Banmai",
    "gn:country_code":"CN",
    "gn:dem":139,
    "gn:feature_class":"P",
    "gn:feature_code":"PPL",
    "gn:name":"Banmai",
    "gn:population":0,
    "gn:timezone":"Asia/Shanghai",
    "iso:country":"CN",
    "name:zho_x_preferred":[
        "\u677f\u8109"
    ],
    "wof:name":"Banmai",
    "wof:placetype":"locality"
},
  "geometry": {"coordinates":[108.36799999999999,23.087],"type":"Point"}
}