{
  "type": "Feature",
  "properties": {
    "gn:admin1_code":"18",
    "gn:asciiname":"Luoweiqi",
    "gn:country_code":"CN",
    "gn:dem":2036,
    "gn:feature_class":"P",
    "gn:feature_code":"PPL",
    "gn:name":"Luoweiqi",
    "gn:population":0,
    "gn:timezone":"Asia/Shanghai",
    "iso:country":"CN",
    "name:zho_x_preferred":[
        "\u7f57\u5473\u671f"
    ],
    "wof:name":"Luoweiqi",
    "wof:placetype":"locality"
},
  "geometry": {"coordinates":[104.828,26.5271],"type":"Point"}
}