{
  "type": "Feature",
  "properties": {
    "gn:admin1_code":"7",
    "gn:asciiname":"Darenmiao",
    "gn:country_code":"CN",
    "gn:dem":16,
    "gn:feature_class":"P",
    "gn:feature_code":"PPL",
    "gn:name":"Darenmiao",
    "gn:population":0,
    "gn:timezone":"Asia/Shanghai",
    "iso:country":"CN",
    "name:zho_x_preferred":[
        "\u5927\u4eba\u5e99"
    ],
    "wof:name":"Darenmiao",
    "wof:placetype":"locality"
},
  "geometry": {"coordinates":[117.8359,24.51633],"type":"Point"}
}