{
  "type": "Feature",
  "properties": {
    "gn:admin1_code":"29.0",
    "gn:asciiname":"Wuheiyao",
    "gn:country_code":"CN",
    "gn:dem":1631,
    "gn:feature_class":"P",
    "gn:feature_code":"PPL",
    "gn:name":"Wuheiyao",
    "gn:population":0,
    "gn:timezone":"Asia/Shanghai",
    "iso:country":"CN",
    "name:und_x_variant":[
        "Wuheime"
    ],
    "name:zho_x_preferred":[
        "\u52a1\u9ed1\u4e48"
    ],
    "wof:name":"Wuheiyao",
    "wof:placetype":"locality"
},
  "geometry": {"coordinates":[101.63500000000001,26.0846],"type":"Point"}
}