{
  "type": "Feature",
  "properties": {
    "gn:admin1_code":"3.0",
    "gn:asciiname":"Shangfanluo",
    "gn:country_code":"CN",
    "gn:dem":398,
    "gn:feature_class":"P",
    "gn:feature_code":"PPL",
    "gn:name":"Shangfanluo",
    "gn:population":0,
    "gn:timezone":"Asia/Shanghai",
    "iso:country":"CN",
    "name:und_x_variant":[
        "\u4e0a\u996d\u7f57"
    ],
    "wof:name":"Shangfanluo",
    "wof:placetype":"locality"
},
  "geometry": {"coordinates":[114.49222,24.62059],"type":"Point"}
}