{
  "type": "Feature",
  "properties": {
    "gn:admin1_code":"25.0",
    "gn:asciiname":"Zhichu",
    "gn:country_code":"CN",
    "gn:dem":12,
    "gn:feature_class":"P",
    "gn:feature_code":"PPLA4",
    "gn:name":"Zhichu",
    "gn:population":0,
    "gn:timezone":"Asia/Shanghai",
    "iso:country":"CN",
    "name:und_x_variant":[
        "Zhichu Jiedao"
    ],
    "name:zho_x_preferred":[
        "\u829d\u695a"
    ],
    "name:zho_x_variant":[
        "\u829d\u695a\u8857\u9053"
    ],
    "wof:name":"Zhichu",
    "wof:placetype":"locality"
},
  "geometry": {"coordinates":[121.30867000000001,37.51769],"type":"Point"}
}