{
  "type": "Feature",
  "properties": {
    "gn:admin1_code":"16.0",
    "gn:asciiname":"Layou",
    "gn:country_code":"CN",
    "gn:dem":195,
    "gn:feature_class":"P",
    "gn:feature_code":"PPL",
    "gn:name":"Layou",
    "gn:population":0,
    "gn:timezone":"Asia/Shanghai",
    "iso:country":"CN",
    "name:ara_x_preferred":[
        "\u0644\u0627\u064a\u0648"
    ],
    "name:ceb_x_preferred":[
        "Layou"
    ],
    "name:deu_x_preferred":[
        "Layou"
    ],
    "name:fra_x_preferred":[
        "Layou"
    ],
    "name:lit_x_preferred":[
        "Laju"
    ],
    "name:pol_x_preferred":[
        "Layou"
    ],
    "name:ron_x_preferred":[
        "Layou"
    ],
    "name:rus_x_preferred":[
        "\u041b\u0435\u044e"
    ],
    "name:urd_x_preferred":[
        "\u0644\u0627\u06cc\u0648"
    ],
    "name:zho_x_preferred":[
        "\u62c9\u5e7d"
    ],
    "wof:name":"Layou",
    "wof:placetype":"locality"
},
  "geometry": {"coordinates":[109.94799999999999,24.9587],"type":"Point"}
}