{
  "type": "Feature",
  "properties": {
    "gn:admin1_code":"01",
    "gn:asciiname":"Shencun",
    "gn:country_code":"CN",
    "gn:dem":18,
    "gn:feature_class":"P",
    "gn:feature_code":"PPLA4",
    "gn:name":"Shencun",
    "gn:population":0,
    "gn:timezone":"Asia/Shanghai",
    "iso:country":"CN",
    "name:und_x_variant":[
        "Shen-ts\u2019un-chen",
        "Shen-ts\u2019un-p\u2019u",
        "Shen-ts\u2019un",
        "Shen-chia-chen",
        "Shencun Zhen",
        "\u6c88\u6751\u9547",
        "Shencun"
    ],
    "name:zho_x_preferred":[
        "\u6c88\u6751"
    ],
    "wof:name":"Shencun",
    "wof:placetype":"locality"
},
  "geometry": {"coordinates":[118.85115,31.05168],"type":"Point"}
}