{
  "type": "Feature",
  "properties": {
    "gn:admin1_code":"16.0",
    "gn:asciiname":"Nongpeng",
    "gn:country_code":"CN",
    "gn:dem":545,
    "gn:feature_class":"P",
    "gn:feature_code":"PPL",
    "gn:name":"Nongpeng",
    "gn:population":0,
    "gn:timezone":"Asia/Shanghai",
    "iso:country":"CN",
    "name:zho_x_preferred":[
        "\u5f04\u68da"
    ],
    "wof:name":"Nongpeng",
    "wof:placetype":"locality"
},
  "geometry": {"coordinates":[107.88500000000001,24.0641],"type":"Point"}
}