{
  "type": "Feature",
  "properties": {
    "gn:admin1_code":"5.0",
    "gn:asciiname":"Linzitou",
    "gn:country_code":"CN",
    "gn:dem":470,
    "gn:feature_class":"P",
    "gn:feature_code":"PPL",
    "gn:name":"Linzitou",
    "gn:population":0,
    "gn:timezone":"Asia/Shanghai",
    "iso:country":"CN",
    "name:und_x_variant":[
        "\u6797\u5b50\u5934"
    ],
    "wof:name":"Linzitou",
    "wof:placetype":"locality"
},
  "geometry": {"coordinates":[125.76428,41.74104000000001],"type":"Point"}
}