{
  "type": "Feature",
  "properties": {
    "gn:admin1_code":"33.0",
    "gn:asciiname":"Mingyan",
    "gn:country_code":"CN",
    "gn:dem":719,
    "gn:feature_class":"P",
    "gn:feature_code":"PPL",
    "gn:name":"Mingyan",
    "gn:population":0,
    "gn:timezone":"Asia/Shanghai",
    "iso:country":"CN",
    "name:zho_x_preferred":[
        "\u660e\u5ca9"
    ],
    "wof:name":"Mingyan",
    "wof:placetype":"locality"
},
  "geometry": {"coordinates":[109.32168,31.08122],"type":"Point"}
}