{
  "type": "Feature",
  "properties": {
    "gn:admin1_code":"25",
    "gn:asciiname":"Wangjiaqiling",
    "gn:country_code":"CN",
    "gn:dem":58,
    "gn:feature_class":"P",
    "gn:feature_code":"PPL",
    "gn:name":"Wangjiaqiling",
    "gn:population":0,
    "gn:timezone":"Asia/Shanghai",
    "iso:country":"CN",
    "name:zho_x_preferred":[
        "\u738b\u5bb6\u9f50\u9675"
    ],
    "wof:name":"Wangjiaqiling",
    "wof:placetype":"locality"
},
  "geometry": {"coordinates":[118.407,36.7996],"type":"Point"}
}