{
  "type": "Feature",
  "properties": {
    "gn:admin1_code":"20.0",
    "gn:asciiname":"Xingzhuanggou",
    "gn:country_code":"CN",
    "gn:dem":1482,
    "gn:feature_class":"P",
    "gn:feature_code":"PPL",
    "gn:name":"Xingzhuanggou",
    "gn:population":0,
    "gn:timezone":"Asia/Shanghai",
    "iso:country":"CN",
    "name:und_x_variant":[
        "\u5174\u5e84\u6c9f"
    ],
    "wof:name":"Xingzhuanggou",
    "wof:placetype":"locality"
},
  "geometry": {"coordinates":[111.77688999999999,39.85261],"type":"Point"}
}