{
  "type": "Feature",
  "properties": {
    "gn:admin1_code":"24.0",
    "gn:asciiname":"Zhaowashan",
    "gn:country_code":"CN",
    "gn:dem":884,
    "gn:feature_class":"P",
    "gn:feature_code":"PPL",
    "gn:name":"Zhaowashan",
    "gn:population":0,
    "gn:timezone":"Asia/Shanghai",
    "iso:country":"CN",
    "name:zho_x_preferred":[
        "\u8d75\u6d3c\u5c71"
    ],
    "wof:name":"Zhaowashan",
    "wof:placetype":"locality"
},
  "geometry": {"coordinates":[111.7111,36.65698],"type":"Point"}
}