{
  "type": "Feature",
  "properties": {
    "gn:admin1_code":"12.0",
    "gn:asciiname":"Dabagou",
    "gn:country_code":"CN",
    "gn:dem":607,
    "gn:feature_class":"P",
    "gn:feature_code":"PPL",
    "gn:name":"Dabagou",
    "gn:population":0,
    "gn:timezone":"Asia/Shanghai",
    "iso:country":"CN",
    "name:zho_x_preferred":[
        "Dabagou"
    ],
    "name:zho_x_variant":[
        "\u5927\u575d\u6c9f"
    ],
    "wof:name":"Dabagou",
    "wof:placetype":"locality"
},
  "geometry": {"coordinates":[109.47817999999999,29.94364],"type":"Point"}
}