{
  "type": "Feature",
  "properties": {
    "gn:admin1_code":"16.0",
    "gn:asciiname":"Liangdang",
    "gn:country_code":"CN",
    "gn:dem":131,
    "gn:feature_class":"P",
    "gn:feature_code":"PPL",
    "gn:name":"Liangdang",
    "gn:population":0,
    "gn:timezone":"Asia/Shanghai",
    "iso:country":"CN",
    "name:zho_x_preferred":[
        "\u826f\u515a"
    ],
    "wof:name":"Liangdang",
    "wof:placetype":"locality"
},
  "geometry": {"coordinates":[110.492,23.2056],"type":"Point"}
}