{
  "type": "Feature",
  "properties": {
    "gn:admin1_code":"01",
    "gn:asciiname":"Fangang",
    "gn:cc2":"CN",
    "gn:country_code":"CN",
    "gn:dem":82,
    "gn:feature_class":"P",
    "gn:feature_code":"PPL",
    "gn:name":"Fangang",
    "gn:population":0,
    "gn:timezone":"Asia/Shanghai",
    "iso:country":"CN",
    "name:und_x_variant":[
        "Fan-kang",
        "Fanjiagang",
        "Fan-chia-kang",
        "Fangang"
    ],
    "wof:name":"Fangang",
    "wof:placetype":"locality"
},
  "geometry": {"coordinates":[117.72360999999999,32.59694],"type":"Point"}
}