{
  "type": "Feature",
  "properties": {
    "gn:admin1_code":"15.0",
    "gn:asciiname":"Xijia Wannao",
    "gn:country_code":"CN",
    "gn:dem":2269,
    "gn:feature_class":"P",
    "gn:feature_code":"PPL",
    "gn:name":"Xijia Wannao",
    "gn:population":0,
    "gn:timezone":"Asia/Shanghai",
    "iso:country":"CN",
    "name:zho_x_preferred":[
        "\u5e2d\u5bb6\u6e7e\u8111"
    ],
    "wof:name":"Xijia Wannao",
    "wof:placetype":"locality"
},
  "geometry": {"coordinates":[104.405,35.5508],"type":"Point"}
}