{
  "type": "Feature",
  "properties": {
    "gn:admin1_code":"22",
    "gn:asciiname":"Guojiawan",
    "gn:country_code":"CN",
    "gn:dem":742,
    "gn:feature_class":"P",
    "gn:feature_code":"PPL",
    "gn:name":"Guojiawan",
    "gn:population":0,
    "gn:timezone":"Asia/Shanghai",
    "iso:country":"CN",
    "name:zho_x_preferred":[
        "\u90ed\u5bb6\u6e7e"
    ],
    "wof:name":"Guojiawan",
    "wof:placetype":"locality"
},
  "geometry": {"coordinates":[116.44986000000002,40.50254],"type":"Point"}
}