{
  "type": "Feature",
  "properties": {
    "gn:admin1_code":"25",
    "gn:asciiname":"Shiwanggou",
    "gn:country_code":"CN",
    "gn:dem":84,
    "gn:feature_class":"P",
    "gn:feature_code":"PPL",
    "gn:name":"Shiwanggou",
    "gn:population":0,
    "gn:timezone":"Asia/Shanghai",
    "iso:country":"CN",
    "name:und_x_variant":[
        "\u77f3\u65fa\u6c9f"
    ],
    "wof:name":"Shiwanggou",
    "wof:placetype":"locality"
},
  "geometry": {"coordinates":[119.22297,35.52847],"type":"Point"}
}