{
  "type": "Feature",
  "properties": {
    "gn:admin1_code":"19",
    "gn:asciiname":"Xiafangshencun",
    "gn:country_code":"CN",
    "gn:dem":89,
    "gn:feature_class":"P",
    "gn:feature_code":"PPL",
    "gn:name":"Xiafangshencun",
    "gn:population":0,
    "gn:timezone":"Asia/Shanghai",
    "iso:country":"CN",
    "name:und_x_variant":[
        "Hsia-fang-shen",
        "Xiafangshen",
        "\u4e0b\u623f\u8eab",
        "Xiafangshencun"
    ],
    "name:zho_x_preferred":[
        "\u4e0b\u623f\u8eab\u6751"
    ],
    "wof:name":"Xiafangshencun",
    "wof:placetype":"locality"
},
  "geometry": {"coordinates":[122.81896999999999,40.722],"type":"Point"}
}