{
  "type": "Feature",
  "properties": {
    "gn:admin1_code":"15.0",
    "gn:asciiname":"Daquantan",
    "gn:country_code":"CN",
    "gn:dem":2754,
    "gn:feature_class":"P",
    "gn:feature_code":"PPL",
    "gn:name":"Daquantan",
    "gn:population":0,
    "gn:timezone":"Asia/Shanghai",
    "iso:country":"CN",
    "name:zho_x_preferred":[
        "\u5927\u5708\u6ee9"
    ],
    "wof:name":"Daquantan",
    "wof:placetype":"locality"
},
  "geometry": {"coordinates":[102.221,37.7769],"type":"Point"}
}