{
  "type": "Feature",
  "properties": {
    "gn:admin1_code":"8.0",
    "gn:asciiname":"Wangfulin",
    "gn:country_code":"CN",
    "gn:dem":275,
    "gn:feature_class":"P",
    "gn:feature_code":"PPL",
    "gn:name":"Wangfulin",
    "gn:population":0,
    "gn:timezone":"Asia/Shanghai",
    "iso:country":"CN",
    "name:zho_x_preferred":[
        "\u738b\u798f\u6797"
    ],
    "wof:name":"Wangfulin",
    "wof:placetype":"locality"
},
  "geometry": {"coordinates":[126.32890999999999,47.58307],"type":"Point"}
}