{
  "type": "Feature",
  "properties": {
    "gn:admin1_code":"21.0",
    "gn:asciiname":"Shangshiqiaozi",
    "gn:country_code":"CN",
    "gn:dem":1511,
    "gn:feature_class":"P",
    "gn:feature_code":"PPL",
    "gn:name":"Shangshiqiaozi",
    "gn:population":0,
    "gn:timezone":"Asia/Shanghai",
    "iso:country":"CN",
    "name:und_x_variant":[
        "\u4e0a\u77f3\u6865\u5b50"
    ],
    "name:zho_x_preferred":[
        "\u4e0a\u77f3\u6865\u5b50"
    ],
    "wof:name":"Shangshiqiaozi",
    "wof:placetype":"locality"
},
  "geometry": {"coordinates":[106.89422,36.0482],"type":"Point"}
}