{
  "type": "Feature",
  "properties": {
    "gn:admin1_code":"26.0",
    "gn:asciiname":"Yangdimao",
    "gn:country_code":"CN",
    "gn:dem":1202,
    "gn:feature_class":"P",
    "gn:feature_code":"PPL",
    "gn:name":"Yangdimao",
    "gn:population":0,
    "gn:timezone":"Asia/Shanghai",
    "iso:country":"CN",
    "name:zho_x_preferred":[
        "\u6768\u5730\u5cc1"
    ],
    "wof:name":"Yangdimao",
    "wof:placetype":"locality"
},
  "geometry": {"coordinates":[110.87222,39.22055],"type":"Point"}
}