{
  "type": "Feature",
  "properties": {
    "gn:admin1_code":"29.0",
    "gn:asciiname":"Gudi Xinzhai",
    "gn:country_code":"CN",
    "gn:dem":1833,
    "gn:feature_class":"P",
    "gn:feature_code":"PPL",
    "gn:name":"Gudi Xinzhai",
    "gn:population":0,
    "gn:timezone":"Asia/Shanghai",
    "iso:country":"CN",
    "name:zho_x_preferred":[
        "\u8c37\u5730\u65b0\u5be8"
    ],
    "wof:name":"Gudi Xinzhai",
    "wof:placetype":"locality"
},
  "geometry": {"coordinates":[102.931,22.8417],"type":"Point"}
}