{
  "type": "Feature",
  "properties": {
    "gn:admin1_code":"26.0",
    "gn:asciiname":"Gaowu Goucun",
    "gn:country_code":"CN",
    "gn:dem":1119,
    "gn:feature_class":"P",
    "gn:feature_code":"PPL",
    "gn:name":"Gaowu Goucun",
    "gn:population":0,
    "gn:timezone":"Asia/Shanghai",
    "iso:country":"CN",
    "name:zho_x_preferred":[
        "\u9ad8\u6b66\u6c9f\u6751"
    ],
    "wof:name":"Gaowu Goucun",
    "wof:placetype":"locality"
},
  "geometry": {"coordinates":[110.206,38.1874],"type":"Point"}
}