{
  "type": "Feature",
  "properties": {
    "gn:admin1_code":"30.0",
    "gn:asciiname":"Changjiaocun",
    "gn:country_code":"CN",
    "gn:dem":240,
    "gn:feature_class":"P",
    "gn:feature_code":"PPL",
    "gn:name":"Changjiaocun",
    "gn:population":0,
    "gn:timezone":"Asia/Shanghai",
    "iso:country":"CN",
    "name:und_x_variant":[
        "Changjiao"
    ],
    "name:zho_x_preferred":[
        "\u957f\u6559\u6751"
    ],
    "name:zho_x_variant":[
        "\u957f\u6559"
    ],
    "wof:name":"Changjiaocun",
    "wof:placetype":"locality"
},
  "geometry": {"coordinates":[116.36897999999999,24.37532],"type":"Point"}
}