{
  "type": "Feature",
  "properties": {
    "gn:admin1_code":"4.0",
    "gn:asciiname":"Lanzhi Sizu",
    "gn:country_code":"CN",
    "gn:dem":4,
    "gn:feature_class":"P",
    "gn:feature_code":"PPL",
    "gn:name":"Lanzhi Sizu",
    "gn:population":0,
    "gn:timezone":"Asia/Shanghai",
    "iso:country":"CN",
    "name:zho_x_preferred":[
        "\u5170\u5740\u56db\u7ec4"
    ],
    "wof:name":"Lanzhi Sizu",
    "wof:placetype":"locality"
},
  "geometry": {"coordinates":[120.70563,32.76121],"type":"Point"}
}