{
  "type": "Feature",
  "properties": {
    "gn:admin1_code":"32.0",
    "gn:asciiname":"Luomeiba",
    "gn:country_code":"CN",
    "gn:dem":683,
    "gn:feature_class":"P",
    "gn:feature_code":"PPL",
    "gn:name":"Luomeiba",
    "gn:population":0,
    "gn:timezone":"Asia/Shanghai",
    "iso:country":"CN",
    "name:zho_x_preferred":[
        "\u843d\u59b9\u575d"
    ],
    "wof:name":"Luomeiba",
    "wof:placetype":"locality"
},
  "geometry": {"coordinates":[105.39700000000001,27.9945],"type":"Point"}
}