{
  "type": "Feature",
  "properties": {
    "gn:admin1_code":"02",
    "gn:asciiname":"Songjiadaicun",
    "gn:country_code":"CN",
    "gn:dem":7,
    "gn:feature_class":"P",
    "gn:feature_code":"PPL",
    "gn:name":"Songjiadaicun",
    "gn:population":0,
    "gn:timezone":"Asia/Shanghai",
    "iso:country":"CN",
    "name:und_x_variant":[
        "Sung-chiang-tai",
        "Songjiadai",
        "Songjiadaicun"
    ],
    "name:zho_x_preferred":[
        "\u5b8b\u5bb6\u57ed"
    ],
    "name:zho_x_variant":[
        "\u5b8b\u5bb6\u57ed\u6751"
    ],
    "wof:name":"Songjiadaicun",
    "wof:placetype":"locality"
},
  "geometry": {"coordinates":[120.62909000000001,27.74091],"type":"Point"}
}