{
  "type": "Feature",
  "properties": {
    "gn:admin1_code":"16.0",
    "gn:asciiname":"Liubuchong",
    "gn:country_code":"CN",
    "gn:dem":405,
    "gn:feature_class":"P",
    "gn:feature_code":"PPL",
    "gn:name":"Liubuchong",
    "gn:population":0,
    "gn:timezone":"Asia/Shanghai",
    "iso:country":"CN",
    "name:zho_x_preferred":[
        "\u516d\u6b65\u51b2"
    ],
    "wof:name":"Liubuchong",
    "wof:placetype":"locality"
},
  "geometry": {"coordinates":[110.19799999999999,24.5251],"type":"Point"}
}