{
  "type": "Feature",
  "properties": {
    "gn:admin1_code":"32.0",
    "gn:asciiname":"Xiaoguanshan",
    "gn:country_code":"CN",
    "gn:dem":379,
    "gn:feature_class":"P",
    "gn:feature_code":"PPL",
    "gn:name":"Xiaoguanshan",
    "gn:population":0,
    "gn:timezone":"Asia/Shanghai",
    "iso:country":"CN",
    "name:zho_x_preferred":[
        "\u5c0f\u5b98\u5c71"
    ],
    "wof:name":"Xiaoguanshan",
    "wof:placetype":"locality"
},
  "geometry": {"coordinates":[103.99471,29.51597000000001],"type":"Point"}
}