{
  "type": "Feature",
  "properties": {
    "gn:admin1_code":"29.0",
    "gn:asciiname":"Mankong Dazhai",
    "gn:country_code":"CN",
    "gn:dem":1223,
    "gn:feature_class":"P",
    "gn:feature_code":"PPL",
    "gn:name":"Mankong Dazhai",
    "gn:population":0,
    "gn:timezone":"Asia/Shanghai",
    "iso:country":"CN",
    "name:zho_x_preferred":[
        "\u66fc\u7a7a\u5927\u5be8"
    ],
    "wof:name":"Mankong Dazhai",
    "wof:placetype":"locality"
},
  "geometry": {"coordinates":[101.199,22.0083],"type":"Point"}
}