{
  "type": "Feature",
  "properties": {
    "gn:admin1_code":"26",
    "gn:asciiname":"Gouqutou",
    "gn:country_code":"CN",
    "gn:dem":1157,
    "gn:feature_class":"P",
    "gn:feature_code":"PPL",
    "gn:name":"Gouqutou",
    "gn:population":0,
    "gn:timezone":"Asia/Shanghai",
    "iso:country":"CN",
    "name:zho_x_preferred":[
        "\u6c9f\u6e20\u5934"
    ],
    "wof:name":"Gouqutou",
    "wof:placetype":"locality"
},
  "geometry": {"coordinates":[108.11750000000001,34.94778],"type":"Point"}
}