{
  "type": "Feature",
  "properties": {
    "gn:admin1_code":"32.0",
    "gn:asciiname":"Taiyang",
    "gn:country_code":"CN",
    "gn:dem":314,
    "gn:feature_class":"P",
    "gn:feature_code":"PPL",
    "gn:name":"Taiyang",
    "gn:population":0,
    "gn:timezone":"Asia/Shanghai",
    "iso:country":"CN",
    "name:zho_x_preferred":[
        "\u592a\u9633"
    ],
    "wof:name":"Taiyang",
    "wof:placetype":"locality"
},
  "geometry": {"coordinates":[105.42700000000001,30.0707],"type":"Point"}
}