{
  "type": "Feature",
  "properties": {
    "gn:admin1_code":"16.0",
    "gn:asciiname":"Xiajiaoli",
    "gn:country_code":"CN",
    "gn:dem":439,
    "gn:feature_class":"P",
    "gn:feature_code":"PPL",
    "gn:name":"Xiajiaoli",
    "gn:population":0,
    "gn:timezone":"Asia/Shanghai",
    "iso:country":"CN",
    "name:zho_x_preferred":[
        "\u4e0b\u7ede\u91cc"
    ],
    "wof:name":"Xiajiaoli",
    "wof:placetype":"locality"
},
  "geometry": {"coordinates":[107.15300000000001,25.4409],"type":"Point"}
}