{
  "type": "Feature",
  "properties": {
    "gn:admin1_code":"22.0",
    "gn:asciiname":"Nanliang Gezhuangcun",
    "gn:country_code":"CN",
    "gn:dem":41,
    "gn:feature_class":"P",
    "gn:feature_code":"PPL",
    "gn:name":"Nanliang Gezhuangcun",
    "gn:population":0,
    "gn:timezone":"Asia/Shanghai",
    "iso:country":"CN",
    "name:zho_x_preferred":[
        "\u5357\u826f\u5404\u5e84\u6751"
    ],
    "wof:name":"Nanliang Gezhuangcun",
    "wof:placetype":"locality"
},
  "geometry": {"coordinates":[115.87538000000001,39.55631],"type":"Point"}
}