{
  "type": "Feature",
  "properties": {
    "gn:admin1_code":"11.0",
    "gn:asciiname":"Niejiaping",
    "gn:country_code":"CN",
    "gn:dem":235,
    "gn:feature_class":"P",
    "gn:feature_code":"PPL",
    "gn:name":"Niejiaping",
    "gn:population":0,
    "gn:timezone":"Asia/Shanghai",
    "iso:country":"CN",
    "name:zho_x_preferred":[
        "\u8042\u5bb6\u576a"
    ],
    "wof:name":"Niejiaping",
    "wof:placetype":"locality"
},
  "geometry": {"coordinates":[109.50664999999999,27.73685],"type":"Point"}
}