{
  "type": "Feature",
  "properties": {
    "gn:admin1_code":"32",
    "gn:asciiname":"Xiuguan",
    "gn:country_code":"CN",
    "gn:dem":273,
    "gn:feature_class":"P",
    "gn:feature_code":"PPL",
    "gn:name":"Xiuguan",
    "gn:population":0,
    "gn:timezone":"Asia/Shanghai",
    "iso:country":"CN",
    "name:zho_x_preferred":[
        "\u79c0\u89c2"
    ],
    "wof:name":"Xiuguan",
    "wof:placetype":"locality"
},
  "geometry": {"coordinates":[106.22443,30.30064],"type":"Point"}
}