{
  "type": "Feature",
  "properties": {
    "gn:admin1_code":"25.0",
    "gn:asciiname":"Lugentan",
    "gn:country_code":"CN",
    "gn:dem":9,
    "gn:feature_class":"P",
    "gn:feature_code":"PPL",
    "gn:name":"Lugentan",
    "gn:population":0,
    "gn:timezone":"Asia/Shanghai",
    "iso:country":"CN",
    "name:zho_x_preferred":[
        "\u82a6\u6839\u6ee9"
    ],
    "wof:name":"Lugentan",
    "wof:placetype":"locality"
},
  "geometry": {"coordinates":[121.43595999999999,36.87222],"type":"Point"}
}