{
  "type": "Feature",
  "properties": {
    "gn:admin1_code":"26.0",
    "gn:asciiname":"Langwogoucun",
    "gn:country_code":"CN",
    "gn:dem":957,
    "gn:feature_class":"P",
    "gn:feature_code":"PPL",
    "gn:name":"Langwogoucun",
    "gn:population":0,
    "gn:timezone":"Asia/Shanghai",
    "iso:country":"CN",
    "name:zho_x_preferred":[
        "\u72fc\u5367\u6c9f\u6751"
    ],
    "wof:name":"Langwogoucun",
    "wof:placetype":"locality"
},
  "geometry": {"coordinates":[109.7107,36.67877],"type":"Point"}
}