{
  "type": "Feature",
  "properties": {
    "gn:admin1_code":"11.0",
    "gn:asciiname":"Nuli",
    "gn:country_code":"CN",
    "gn:dem":140,
    "gn:feature_class":"P",
    "gn:feature_code":"PPL",
    "gn:name":"Nuli",
    "gn:population":0,
    "gn:timezone":"Asia/Shanghai",
    "iso:country":"CN",
    "name:zho_x_preferred":[
        "Nuli"
    ],
    "name:zho_x_variant":[
        "\u52aa\u529b"
    ],
    "wof:name":"Nuli",
    "wof:placetype":"locality"
},
  "geometry": {"coordinates":[111.56677999999999,29.86248],"type":"Point"}
}