{
  "type": "Feature",
  "properties": {
    "gn:admin1_code":"04",
    "gn:asciiname":"Jing'anyi",
    "gn:country_code":"CN",
    "gn:dem":39,
    "gn:feature_class":"P",
    "gn:feature_code":"PPL",
    "gn:name":"Jing\u2019anyi",
    "gn:population":0,
    "gn:timezone":"Asia/Shanghai",
    "iso:country":"CN",
    "name:und_x_variant":[
        "Kinganchen",
        "Ching-an-chi",
        "Kingantsi",
        "Jing\u2019anji",
        "Jing\u2019anyi"
    ],
    "name:zho_x_preferred":[
        "\u656c\u5b89\u4e00"
    ],
    "wof:name":"Jing'anyi",
    "wof:placetype":"locality"
},
  "geometry": {"coordinates":[116.91748,34.49451],"type":"Point"}
}