{
  "type": "Feature",
  "properties": {
    "gn:admin1_code":"16.0",
    "gn:asciiname":"Tongzhi",
    "gn:country_code":"CN",
    "gn:dem":151,
    "gn:feature_class":"P",
    "gn:feature_code":"PPL",
    "gn:name":"Tongzhi",
    "gn:population":0,
    "gn:timezone":"Asia/Shanghai",
    "iso:country":"CN",
    "name:zho_x_preferred":[
        "\u6850\u679d"
    ],
    "wof:name":"Tongzhi",
    "wof:placetype":"locality"
},
  "geometry": {"coordinates":[107.63500000000001,22.3112],"type":"Point"}
}