{
  "type": "Feature",
  "properties": {
    "gn:admin1_code":"5.0",
    "gn:asciiname":"Yingshan",
    "gn:country_code":"CN",
    "gn:dem":468,
    "gn:feature_class":"P",
    "gn:feature_code":"PPL",
    "gn:name":"Yingshan",
    "gn:population":0,
    "gn:timezone":"Asia/Shanghai",
    "iso:country":"CN",
    "name:und_x_variant":[
        "\u82f1\u5c71"
    ],
    "wof:name":"Yingshan",
    "wof:placetype":"locality"
},
  "geometry": {"coordinates":[125.56178,41.74968],"type":"Point"}
}