{
  "type": "Feature",
  "properties": {
    "gn:admin1_code":"19.0",
    "gn:asciiname":"Wuhaotang",
    "gn:country_code":"CN",
    "gn:dem":8,
    "gn:feature_class":"P",
    "gn:feature_code":"PPL",
    "gn:name":"Wuhaotang",
    "gn:population":0,
    "gn:timezone":"Asia/Shanghai",
    "iso:country":"CN",
    "name:zho_x_preferred":[
        "\u4e94\u53f7\u5858"
    ],
    "wof:name":"Wuhaotang",
    "wof:placetype":"locality"
},
  "geometry": {"coordinates":[124.184,39.8616],"type":"Point"}
}