{
  "type": "Feature",
  "properties": {
    "gn:admin1_code":"19.0",
    "gn:asciiname":"Qiushanggou",
    "gn:country_code":"CN",
    "gn:dem":33,
    "gn:feature_class":"P",
    "gn:feature_code":"PPL",
    "gn:name":"Qiushanggou",
    "gn:population":0,
    "gn:timezone":"Asia/Shanghai",
    "iso:country":"CN",
    "name:zho_x_preferred":[
        "\u90b1\u4e0a\u6c9f"
    ],
    "wof:name":"Qiushanggou",
    "wof:placetype":"locality"
},
  "geometry": {"coordinates":[122.038,39.1543],"type":"Point"}
}