{
  "type": "Feature",
  "properties": {
    "gn:admin1_code":"21.0",
    "gn:asciiname":"Shatan",
    "gn:country_code":"CN",
    "gn:dem":1578,
    "gn:feature_class":"P",
    "gn:feature_code":"PPL",
    "gn:name":"Shatan",
    "gn:population":0,
    "gn:timezone":"Asia/Shanghai",
    "iso:country":"CN",
    "name:ceb_x_preferred":[
        "Shatan"
    ],
    "name:swe_x_preferred":[
        "Shatan"
    ],
    "name:und_x_variant":[
        "\u6c99\u6ee9"
    ],
    "name:zho_x_preferred":[
        "\u6c99\u6ee9"
    ],
    "wof:name":"Shatan",
    "wof:placetype":"locality"
},
  "geometry": {"coordinates":[106.31312,36.83546],"type":"Point"}
}