{
  "type": "Feature",
  "properties": {
    "gn:admin1_code":"15.0",
    "gn:asciiname":"Huanghe",
    "gn:country_code":"CN",
    "gn:dem":2167,
    "gn:feature_class":"P",
    "gn:feature_code":"PPL",
    "gn:name":"Huanghe",
    "gn:population":0,
    "gn:timezone":"Asia/Shanghai",
    "iso:country":"CN",
    "name:und_x_variant":[
        "\u9ec4\u6cb3"
    ],
    "wof:name":"Huanghe",
    "wof:placetype":"locality"
},
  "geometry": {"coordinates":[105.10936,35.38679000000001],"type":"Point"}
}