{
  "type": "Feature",
  "properties": {
    "gn:admin1_code":"4.0",
    "gn:asciiname":"Xuzhuang",
    "gn:country_code":"CN",
    "gn:dem":28,
    "gn:feature_class":"P",
    "gn:feature_code":"PPL",
    "gn:name":"Xuzhuang",
    "gn:population":0,
    "gn:timezone":"Asia/Shanghai",
    "iso:country":"CN",
    "name:und_x_variant":[
        "\u5f90\u5e84"
    ],
    "wof:name":"Xuzhuang",
    "wof:placetype":"locality"
},
  "geometry": {"coordinates":[118.88149,32.08266],"type":"Point"}
}