{
  "type": "Feature",
  "properties": {
    "gn:admin1_code":"11.0",
    "gn:asciiname":"Qin'ai",
    "gn:country_code":"CN",
    "gn:dem":181,
    "gn:feature_class":"P",
    "gn:feature_code":"PPL",
    "gn:name":"Qin\u2019ai",
    "gn:population":0,
    "gn:timezone":"Asia/Shanghai",
    "iso:country":"CN",
    "name:und_x_variant":[
        "Qin\u2019ai"
    ],
    "name:zho_x_preferred":[
        "\u4eb2\u7231"
    ],
    "wof:name":"Qin'ai",
    "wof:placetype":"locality"
},
  "geometry": {"coordinates":[109.98537,27.87458],"type":"Point"}
}