{
  "type": "Feature",
  "properties": {
    "gn:admin1_code":"25",
    "gn:asciiname":"Qianzilitun",
    "gn:country_code":"CN",
    "gn:dem":34,
    "gn:feature_class":"P",
    "gn:feature_code":"PPL",
    "gn:name":"Qianzilitun",
    "gn:population":0,
    "gn:timezone":"Asia/Shanghai",
    "iso:country":"CN",
    "name:zho_x_preferred":[
        "\u524d\u7c7d\u7c92\u5c6f"
    ],
    "wof:name":"Qianzilitun",
    "wof:placetype":"locality"
},
  "geometry": {"coordinates":[116.07899999999999,36.9975],"type":"Point"}
}