{
  "type": "Feature",
  "properties": {
    "gn:admin1_code":"4.0",
    "gn:asciiname":"Xilianwan",
    "gn:country_code":"CN",
    "gn:dem":39,
    "gn:feature_class":"P",
    "gn:feature_code":"PPL",
    "gn:name":"Xilianwan",
    "gn:population":0,
    "gn:timezone":"Asia/Shanghai",
    "iso:country":"CN",
    "name:und_x_variant":[
        "\u897f\u8fde\u6e7e"
    ],
    "wof:name":"Xilianwan",
    "wof:placetype":"locality"
},
  "geometry": {"coordinates":[118.71545,34.68588],"type":"Point"}
}