{
  "type": "Feature",
  "properties": {
    "gn:admin1_code":"22",
    "gn:asciiname":"Mulin",
    "gn:country_code":"CN",
    "gn:dem":46,
    "gn:feature_class":"P",
    "gn:feature_code":"PPLA4",
    "gn:name":"Mulin",
    "gn:population":0,
    "gn:timezone":"Asia/Shanghai",
    "iso:country":"CN",
    "name:und_x_variant":[
        "Mulin Zhen"
    ],
    "name:zho_x_preferred":[
        "\u6728\u6797"
    ],
    "name:zho_x_variant":[
        "\u6728\u6797\u9547"
    ],
    "wof:name":"Mulin",
    "wof:placetype":"locality"
},
  "geometry": {"coordinates":[116.78185999999999,40.2429],"type":"Point"}
}