{
  "type": "Feature",
  "properties": {
    "gn:admin1_code":"30.0",
    "gn:asciiname":"Liyudong",
    "gn:country_code":"CN",
    "gn:dem":518,
    "gn:feature_class":"P",
    "gn:feature_code":"PPL",
    "gn:name":"Liyudong",
    "gn:population":0,
    "gn:timezone":"Asia/Shanghai",
    "iso:country":"CN",
    "name:zho_x_preferred":[
        "\u9ca4\u9c7c\u6d1e"
    ],
    "wof:name":"Liyudong",
    "wof:placetype":"locality"
},
  "geometry": {"coordinates":[114.02118,23.77986],"type":"Point"}
}