{
  "type": "Feature",
  "properties": {
    "gn:admin1_code":"5.0",
    "gn:asciiname":"Liubaishang",
    "gn:country_code":"CN",
    "gn:dem":178,
    "gn:feature_class":"P",
    "gn:feature_code":"PPL",
    "gn:name":"Liubaishang",
    "gn:population":0,
    "gn:timezone":"Asia/Shanghai",
    "iso:country":"CN",
    "name:zho_x_preferred":[
        "\u516d\u767e\u57a7"
    ],
    "wof:name":"Liubaishang",
    "wof:placetype":"locality"
},
  "geometry": {"coordinates":[124.31725,44.47795],"type":"Point"}
}