{
  "type": "Feature",
  "properties": {
    "gn:admin1_code":"15",
    "gn:asciiname":"Huanghala",
    "gn:country_code":"CN",
    "gn:dem":2076,
    "gn:feature_class":"P",
    "gn:feature_code":"PPL",
    "gn:name":"Huanghala",
    "gn:population":0,
    "gn:timezone":"Asia/Shanghai",
    "iso:country":"CN",
    "name:zho_x_preferred":[
        "\u9ec4\u54c8\u5587"
    ],
    "wof:name":"Huanghala",
    "wof:placetype":"locality"
},
  "geometry": {"coordinates":[103.834,36.7137],"type":"Point"}
}