{
  "type": "Feature",
  "properties": {
    "gn:admin1_code":"2.0",
    "gn:asciiname":"Jingwucun",
    "gn:country_code":"CN",
    "gn:dem":101,
    "gn:feature_class":"P",
    "gn:feature_code":"PPL",
    "gn:name":"Jingwucun",
    "gn:population":0,
    "gn:timezone":"Asia/Shanghai",
    "iso:country":"CN",
    "name:zho_x_preferred":[
        "\u666f\u575e\u6751"
    ],
    "wof:name":"Jingwucun",
    "wof:placetype":"locality"
},
  "geometry": {"coordinates":[119.52457,30.75959000000001],"type":"Point"}
}