{
  "type": "Feature",
  "properties": {
    "gn:admin1_code":"26.0",
    "gn:asciiname":"Yangpo",
    "gn:country_code":"CN",
    "gn:dem":995,
    "gn:feature_class":"P",
    "gn:feature_code":"PPL",
    "gn:name":"Yangpo",
    "gn:population":0,
    "gn:timezone":"Asia/Shanghai",
    "iso:country":"CN",
    "name:und_x_variant":[
        "\u9633\u5761"
    ],
    "wof:name":"Yangpo",
    "wof:placetype":"locality"
},
  "geometry": {"coordinates":[106.96822,33.75769],"type":"Point"}
}