{
  "type": "Feature",
  "properties": {
    "gn:admin1_code":"11",
    "gn:asciiname":"Baixichong",
    "gn:country_code":"CN",
    "gn:dem":328,
    "gn:feature_class":"P",
    "gn:feature_code":"PPL",
    "gn:name":"Baixichong",
    "gn:population":0,
    "gn:timezone":"Asia/Shanghai",
    "iso:country":"CN",
    "name:zho_x_preferred":[
        "\u767d\u6eaa\u51b2"
    ],
    "wof:name":"Baixichong",
    "wof:placetype":"locality"
},
  "geometry": {"coordinates":[111.86324999999999,26.97108],"type":"Point"}
}