{
  "type": "Feature",
  "properties": {
    "gn:admin1_code":"32.0",
    "gn:asciiname":"Shuipingzi",
    "gn:country_code":"CN",
    "gn:dem":2101,
    "gn:feature_class":"P",
    "gn:feature_code":"PPL",
    "gn:name":"Shuipingzi",
    "gn:population":0,
    "gn:timezone":"Asia/Shanghai",
    "iso:country":"CN",
    "name:zho_x_preferred":[
        "\u6c34\u5e73\u5b50"
    ],
    "wof:name":"Shuipingzi",
    "wof:placetype":"locality"
},
  "geometry": {"coordinates":[102.75830999999999,26.73468],"type":"Point"}
}