{
  "type": "Feature",
  "properties": {
    "gn:admin1_code":"26.0",
    "gn:asciiname":"Yangmaojian",
    "gn:country_code":"CN",
    "gn:dem":1160,
    "gn:feature_class":"P",
    "gn:feature_code":"PPL",
    "gn:name":"Yangmaojian",
    "gn:population":0,
    "gn:timezone":"Asia/Shanghai",
    "iso:country":"CN",
    "name:und_x_variant":[
        "\u7f8a\u6bdb\u5c16"
    ],
    "wof:name":"Yangmaojian",
    "wof:placetype":"locality"
},
  "geometry": {"coordinates":[106.54859,33.29677],"type":"Point"}
}