{
  "type": "Feature",
  "properties": {
    "gn:admin1_code":"32.0",
    "gn:asciiname":"Ma'anshi",
    "gn:country_code":"CN",
    "gn:dem":725,
    "gn:feature_class":"P",
    "gn:feature_code":"PPL",
    "gn:name":"Ma\u2019anshi",
    "gn:population":0,
    "gn:timezone":"Asia/Shanghai",
    "iso:country":"CN",
    "name:und_x_variant":[
        "Ma\u2019anshi"
    ],
    "name:zho_x_preferred":[
        "\u9a6c\u978d\u77f3"
    ],
    "wof:name":"Ma'anshi",
    "wof:placetype":"locality"
},
  "geometry": {"coordinates":[103.127,29.1911],"type":"Point"}
}