{
  "type": "Feature",
  "properties": {
    "gn:admin1_code":"4.0",
    "gn:asciiname":"Tongfengcun",
    "gn:country_code":"CN",
    "gn:dem":-2,
    "gn:feature_class":"P",
    "gn:feature_code":"PPL",
    "gn:name":"Tongfengcun",
    "gn:population":0,
    "gn:timezone":"Asia/Shanghai",
    "iso:country":"CN",
    "name:zho_x_preferred":[
        "\u540c\u4e30\u6751"
    ],
    "wof:name":"Tongfengcun",
    "wof:placetype":"locality"
},
  "geometry": {"coordinates":[119.96111999999999,33.8299],"type":"Point"}
}