{
  "type": "Feature",
  "properties": {
    "gn:admin1_code":"18",
    "gn:asciiname":"Shangjiku",
    "gn:country_code":"CN",
    "gn:dem":2098,
    "gn:feature_class":"P",
    "gn:feature_code":"PPL",
    "gn:name":"Shangjiku",
    "gn:population":0,
    "gn:timezone":"Asia/Shanghai",
    "iso:country":"CN",
    "name:zho_x_preferred":[
        "\u4e0a\u9e21\u5e93"
    ],
    "wof:name":"Shangjiku",
    "wof:placetype":"locality"
},
  "geometry": {"coordinates":[104.58799999999999,26.065],"type":"Point"}
}