{
  "type": "Feature",
  "properties": {
    "gn:admin1_code":"26.0",
    "gn:asciiname":"Dianzicun",
    "gn:country_code":"CN",
    "gn:dem":752,
    "gn:feature_class":"P",
    "gn:feature_code":"PPL",
    "gn:name":"Dianzicun",
    "gn:population":0,
    "gn:timezone":"Asia/Shanghai",
    "iso:country":"CN",
    "name:zho_x_preferred":[
        "\u5e97\u5b50\u6751"
    ],
    "wof:name":"Dianzicun",
    "wof:placetype":"locality"
},
  "geometry": {"coordinates":[107.78201,32.87901],"type":"Point"}
}