{
  "type": "Feature",
  "properties": {
    "gn:admin1_code":"11.0",
    "gn:asciiname":"Dongqishan",
    "gn:country_code":"CN",
    "gn:dem":108,
    "gn:feature_class":"P",
    "gn:feature_code":"PPL",
    "gn:name":"Dongqishan",
    "gn:population":0,
    "gn:timezone":"Asia/Shanghai",
    "iso:country":"CN",
    "name:zho_x_preferred":[
        "\u680b\u65d7\u5c71"
    ],
    "wof:name":"Dongqishan",
    "wof:placetype":"locality"
},
  "geometry": {"coordinates":[112.40264000000001,28.25896],"type":"Point"}
}