{
  "type": "Feature",
  "properties": {
    "gn:admin1_code":"32.0",
    "gn:asciiname":"Tongxin",
    "gn:country_code":"CN",
    "gn:dem":537,
    "gn:feature_class":"P",
    "gn:feature_code":"PPL",
    "gn:name":"Tongxin",
    "gn:population":0,
    "gn:timezone":"Asia/Shanghai",
    "iso:country":"CN",
    "name:und_x_variant":[
        "\u540c\u5fc3"
    ],
    "wof:name":"Tongxin",
    "wof:placetype":"locality"
},
  "geometry": {"coordinates":[106.03704999999999,32.25383],"type":"Point"}
}