{
  "type": "Feature",
  "properties": {
    "gn:admin1_code":"18",
    "gn:asciiname":"Yangao",
    "gn:country_code":"CN",
    "gn:dem":825,
    "gn:feature_class":"P",
    "gn:feature_code":"PPL",
    "gn:name":"Yangao",
    "gn:population":0,
    "gn:timezone":"Asia/Shanghai",
    "iso:country":"CN",
    "name:zho_x_preferred":[
        "\u5ca9\u544a"
    ],
    "wof:name":"Yangao",
    "wof:placetype":"locality"
},
  "geometry": {"coordinates":[105.749,25.1239],"type":"Point"}
}