{
  "type": "Feature",
  "properties": {
    "gn:admin1_code":"14.0",
    "gn:asciiname":"Gentian",
    "gn:country_code":"CN",
    "gn:dem":3623,
    "gn:feature_class":"P",
    "gn:feature_code":"PPL",
    "gn:name":"Gentian",
    "gn:population":0,
    "gn:timezone":"Asia/Urumqi",
    "iso:country":"CN",
    "name:zho_x_preferred":[
        "\u6839\u7530"
    ],
    "wof:name":"Gentian",
    "wof:placetype":"locality"
},
  "geometry": {"coordinates":[93.35352,30.12975],"type":"Point"}
}