{
  "type": "Feature",
  "properties": {
    "gn:admin1_code":"24",
    "gn:asciiname":"Shangzhai",
    "gn:cc2":"CN",
    "gn:country_code":"CN",
    "gn:dem":866,
    "gn:feature_class":"P",
    "gn:feature_code":"PPL",
    "gn:name":"Shangzhai",
    "gn:population":0,
    "gn:timezone":"Asia/Shanghai",
    "iso:country":"CN",
    "name:und_x_variant":[
        "Shang-chai",
        "Shang-chai-chen",
        "Shangzhai"
    ],
    "wof:name":"Shangzhai",
    "wof:placetype":"locality"
},
  "geometry": {"coordinates":[114.30861000000002,39.21722000000001],"type":"Point"}
}