{
  "type": "Feature",
  "properties": {
    "gn:admin1_code":"18",
    "gn:asciiname":"Zhangshizhuang",
    "gn:country_code":"CN",
    "gn:dem":1268,
    "gn:feature_class":"P",
    "gn:feature_code":"PPL",
    "gn:name":"Zhangshizhuang",
    "gn:population":0,
    "gn:timezone":"Asia/Shanghai",
    "iso:country":"CN",
    "name:zho_x_preferred":[
        "\u5f20\u77f3\u5e84"
    ],
    "wof:name":"Zhangshizhuang",
    "wof:placetype":"locality"
},
  "geometry": {"coordinates":[106.608,27.7222],"type":"Point"}
}