{
  "type": "Feature",
  "properties": {
    "gn:admin1_code":"12.0",
    "gn:asciiname":"Tanziping",
    "gn:country_code":"CN",
    "gn:dem":990,
    "gn:feature_class":"P",
    "gn:feature_code":"PPL",
    "gn:name":"Tanziping",
    "gn:population":0,
    "gn:timezone":"Asia/Shanghai",
    "iso:country":"CN",
    "name:zho_x_preferred":[
        "\u575b\u5b50\u576a"
    ],
    "wof:name":"Tanziping",
    "wof:placetype":"locality"
},
  "geometry": {"coordinates":[110.66719000000001,31.38921],"type":"Point"}
}