{
  "type": "Feature",
  "properties": {
    "gn:admin1_code":"14.0",
    "gn:asciiname":"Azhaikucun",
    "gn:country_code":"CN",
    "gn:dem":4854,
    "gn:feature_class":"P",
    "gn:feature_code":"PPL",
    "gn:name":"Azhaikucun",
    "gn:population":0,
    "gn:timezone":"Asia/Urumqi",
    "iso:country":"CN",
    "name:zho_x_preferred":[
        "\u963f\u5be8\u5e93\u6751"
    ],
    "wof:name":"Azhaikucun",
    "wof:placetype":"locality"
},
  "geometry": {"coordinates":[92.64978000000001,30.92231],"type":"Point"}
}