{
  "type": "Feature",
  "properties": {
    "gn:admin1_code":"1.0",
    "gn:asciiname":"Ledaocun",
    "gn:country_code":"CN",
    "gn:dem":565,
    "gn:feature_class":"P",
    "gn:feature_code":"PPL",
    "gn:name":"Ledaocun",
    "gn:population":0,
    "gn:timezone":"Asia/Shanghai",
    "iso:country":"CN",
    "name:zho_x_preferred":[
        "\u4e50\u9053\u6751"
    ],
    "wof:name":"Ledaocun",
    "wof:placetype":"locality"
},
  "geometry": {"coordinates":[116.38186,31.06805],"type":"Point"}
}