{
  "type": "Feature",
  "properties": {
    "gn:admin1_code":"1.0",
    "gn:asciiname":"Bianzhuangcun",
    "gn:country_code":"CN",
    "gn:dem":29,
    "gn:feature_class":"P",
    "gn:feature_code":"PPL",
    "gn:name":"Bianzhuangcun",
    "gn:population":0,
    "gn:timezone":"Asia/Shanghai",
    "iso:country":"CN",
    "name:zho_x_preferred":[
        "\u535e\u5e84\u6751"
    ],
    "wof:name":"Bianzhuangcun",
    "wof:placetype":"locality"
},
  "geometry": {"coordinates":[117.52811,33.89465],"type":"Point"}
}