{
  "type": "Feature",
  "properties": {
    "gn:admin1_code":"32.0",
    "gn:asciiname":"Fengmingya",
    "gn:country_code":"CN",
    "gn:dem":395,
    "gn:feature_class":"P",
    "gn:feature_code":"PPL",
    "gn:name":"Fengmingya",
    "gn:population":0,
    "gn:timezone":"Asia/Shanghai",
    "iso:country":"CN",
    "name:zho_x_preferred":[
        "\u51e4\u9e23\u57ad"
    ],
    "wof:name":"Fengmingya",
    "wof:placetype":"locality"
},
  "geometry": {"coordinates":[106.54300000000001,31.7085],"type":"Point"}
}