{
  "type": "Feature",
  "properties": {
    "gn:admin1_code":"29.0",
    "gn:asciiname":"Hongmuling",
    "gn:country_code":"CN",
    "gn:dem":2129,
    "gn:feature_class":"P",
    "gn:feature_code":"PPL",
    "gn:name":"Hongmuling",
    "gn:population":0,
    "gn:timezone":"Asia/Shanghai",
    "iso:country":"CN",
    "name:zho_x_preferred":[
        "\u7ea2\u6728\u5cad"
    ],
    "wof:name":"Hongmuling",
    "wof:placetype":"locality"
},
  "geometry": {"coordinates":[98.6246,25.5446],"type":"Point"}
}