{
  "type": "Feature",
  "properties": {
    "gn:admin1_code":"1.0",
    "gn:asciiname":"Linqiaocun",
    "gn:country_code":"CN",
    "gn:dem":24,
    "gn:feature_class":"P",
    "gn:feature_code":"PPL",
    "gn:name":"Linqiaocun",
    "gn:population":0,
    "gn:timezone":"Asia/Shanghai",
    "iso:country":"CN",
    "name:zho_x_preferred":[
        "\u6797\u6865\u6751"
    ],
    "wof:name":"Linqiaocun",
    "wof:placetype":"locality"
},
  "geometry": {"coordinates":[116.99552,30.93773],"type":"Point"}
}