{
  "type": "Feature",
  "properties": {
    "gn:admin1_code":"16.0",
    "gn:asciiname":"Xiatianba",
    "gn:country_code":"CN",
    "gn:dem":1134,
    "gn:feature_class":"P",
    "gn:feature_code":"PPL",
    "gn:name":"Xiatianba",
    "gn:population":0,
    "gn:timezone":"Asia/Shanghai",
    "iso:country":"CN",
    "name:zho_x_preferred":[
        "\u4e0b\u7530\u575d"
    ],
    "wof:name":"Xiatianba",
    "wof:placetype":"locality"
},
  "geometry": {"coordinates":[106.30800000000001,24.5878],"type":"Point"}
}