{
  "type": "Feature",
  "properties": {
    "gn:admin1_code":"18",
    "gn:asciiname":"Xingziqiao",
    "gn:country_code":"CN",
    "gn:dem":1262,
    "gn:feature_class":"P",
    "gn:feature_code":"PPL",
    "gn:name":"Xingziqiao",
    "gn:population":0,
    "gn:timezone":"Asia/Shanghai",
    "iso:country":"CN",
    "name:zho_x_preferred":[
        "\u5174\u5b50\u6865"
    ],
    "wof:name":"Xingziqiao",
    "wof:placetype":"locality"
},
  "geometry": {"coordinates":[105.35599999999999,25.3109],"type":"Point"}
}