{
  "type": "Feature",
  "properties": {
    "gn:admin1_code":"20.0",
    "gn:asciiname":"Hong'anwan",
    "gn:country_code":"CN",
    "gn:dem":1443,
    "gn:feature_class":"P",
    "gn:feature_code":"PPL",
    "gn:name":"Hong\u2019anwan",
    "gn:population":0,
    "gn:timezone":"Asia/Shanghai",
    "iso:country":"CN",
    "name:und_x_variant":[
        "Hong\u2019anwan",
        "\u7ea2\u5cb8\u6e7e"
    ],
    "wof:name":"Hong'anwan",
    "wof:placetype":"locality"
},
  "geometry": {"coordinates":[110.13132,40.94272],"type":"Point"}
}