{
  "type": "Feature",
  "properties": {
    "gn:admin1_code":"28.0",
    "gn:asciiname":"Xiaowangbu",
    "gn:country_code":"CN",
    "gn:dem":13,
    "gn:feature_class":"P",
    "gn:feature_code":"PPL",
    "gn:name":"Xiaowangbu",
    "gn:population":0,
    "gn:timezone":"Asia/Shanghai",
    "iso:country":"CN",
    "name:zho_x_preferred":[
        "\u5c0f\u738b\u5821"
    ],
    "wof:name":"Xiaowangbu",
    "wof:placetype":"locality"
},
  "geometry": {"coordinates":[116.94670000000001,39.20292],"type":"Point"}
}