{
  "type": "Feature",
  "properties": {
    "gn:admin1_code":"04",
    "gn:asciiname":"Qidaogoucun",
    "gn:country_code":"CN",
    "gn:dem":0,
    "gn:feature_class":"P",
    "gn:feature_code":"PPL",
    "gn:name":"Qidaogoucun",
    "gn:population":0,
    "gn:timezone":"Asia/Shanghai",
    "iso:country":"CN",
    "name:und_x_variant":[
        "Ch\u2019i-tao-kou",
        "Qidaogou",
        "\u4e03\u9053\u6c9f",
        "Qidaogoucun"
    ],
    "name:zho_x_preferred":[
        "\u4e03\u9053\u6c9f\u6751"
    ],
    "wof:name":"Qidaogoucun",
    "wof:placetype":"locality"
},
  "geometry": {"coordinates":[119.61248999999999,34.35468],"type":"Point"}
}