{
  "type": "Feature",
  "properties": {
    "gn:admin1_code":"7.0",
    "gn:asciiname":"Jingnancun",
    "gn:country_code":"CN",
    "gn:dem":51,
    "gn:feature_class":"P",
    "gn:feature_code":"PPL",
    "gn:name":"Jingnancun",
    "gn:population":0,
    "gn:timezone":"Asia/Shanghai",
    "iso:country":"CN",
    "name:zho_x_preferred":[
        "\u51c0\u5357\u6751"
    ],
    "wof:name":"Jingnancun",
    "wof:placetype":"locality"
},
  "geometry": {"coordinates":[118.95078999999998,24.98079],"type":"Point"}
}