{
  "type": "Feature",
  "properties": {
    "gn:admin1_code":"7.0",
    "gn:asciiname":"Huangshapu",
    "gn:country_code":"CN",
    "gn:dem":221,
    "gn:feature_class":"P",
    "gn:feature_code":"PPL",
    "gn:name":"Huangshapu",
    "gn:population":0,
    "gn:timezone":"Asia/Shanghai",
    "iso:country":"CN",
    "name:zho_x_preferred":[
        "\u9ec4\u6c99\u57d4"
    ],
    "wof:name":"Huangshapu",
    "wof:placetype":"locality"
},
  "geometry": {"coordinates":[116.58456,24.82848],"type":"Point"}
}