{
  "type": "Feature",
  "properties": {
    "gn:admin1_code":"2.0",
    "gn:asciiname":"Jingwu",
    "gn:country_code":"CN",
    "gn:dem":42,
    "gn:feature_class":"P",
    "gn:feature_code":"PPL",
    "gn:name":"Jingwu",
    "gn:population":0,
    "gn:timezone":"Asia/Shanghai",
    "iso:country":"CN",
    "name:zho_x_preferred":[
        "\u6676\u5c4b"
    ],
    "wof:name":"Jingwu",
    "wof:placetype":"locality"
},
  "geometry": {"coordinates":[122.01479999999999,30.0935],"type":"Point"}
}