{
  "type": "Feature",
  "properties": {
    "gn:admin1_code":"2.0",
    "gn:asciiname":"Dongwuli",
    "gn:country_code":"CN",
    "gn:dem":399,
    "gn:feature_class":"P",
    "gn:feature_code":"PPL",
    "gn:name":"Dongwuli",
    "gn:population":0,
    "gn:timezone":"Asia/Shanghai",
    "iso:country":"CN",
    "name:zho_x_preferred":[
        "\u4e1c\u575e\u91cc"
    ],
    "wof:name":"Dongwuli",
    "wof:placetype":"locality"
},
  "geometry": {"coordinates":[119.99024,29.85073],"type":"Point"}
}