{
  "type": "Feature",
  "properties": {
    "gn:admin1_code":"32.0",
    "gn:asciiname":"Shuidongzi",
    "gn:country_code":"CN",
    "gn:dem":1189,
    "gn:feature_class":"P",
    "gn:feature_code":"PPL",
    "gn:name":"Shuidongzi",
    "gn:population":0,
    "gn:timezone":"Asia/Shanghai",
    "iso:country":"CN",
    "name:zho_x_preferred":[
        "\u6c34\u6d1e\u5b50"
    ],
    "wof:name":"Shuidongzi",
    "wof:placetype":"locality"
},
  "geometry": {"coordinates":[103.35250000000001,29.36013],"type":"Point"}
}