{
  "type": "Feature",
  "properties": {
    "gn:admin1_code":"31",
    "gn:asciiname":"Yandun",
    "gn:country_code":"CN",
    "gn:dem":2,
    "gn:feature_class":"P",
    "gn:feature_code":"PPL",
    "gn:name":"Yandun",
    "gn:population":0,
    "gn:timezone":"Asia/Shanghai",
    "iso:country":"CN",
    "name:ceb_x_preferred":[
        "Yandun"
    ],
    "name:swe_x_preferred":[
        "Yandun"
    ],
    "name:und_x_variant":[
        "\u76d0\u58a9"
    ],
    "wof:name":"Yandun",
    "wof:placetype":"locality"
},
  "geometry": {"coordinates":[110.497,18.8846],"type":"Point"}
}