{
  "type": "Feature",
  "properties": {
    "gn:admin1_code":"4.0",
    "gn:asciiname":"Shiyuanchang",
    "gn:country_code":"CN",
    "gn:dem":5,
    "gn:feature_class":"P",
    "gn:feature_code":"PPL",
    "gn:name":"Shiyuanchang",
    "gn:population":0,
    "gn:timezone":"Asia/Shanghai",
    "iso:country":"CN",
    "name:zho_x_preferred":[
        "\u65bd\u5143\u573a"
    ],
    "wof:name":"Shiyuanchang",
    "wof:placetype":"locality"
},
  "geometry": {"coordinates":[120.25217000000001,31.85183],"type":"Point"}
}