{
  "type": "Feature",
  "properties": {
    "gn:admin1_code":"4.0",
    "gn:asciiname":"Jushuang",
    "gn:country_code":"CN",
    "gn:dem":7,
    "gn:feature_class":"P",
    "gn:feature_code":"PPL",
    "gn:name":"Jushuang",
    "gn:population":0,
    "gn:timezone":"Asia/Shanghai",
    "iso:country":"CN",
    "name:zho_x_preferred":[
        "\u97a0\u53cc"
    ],
    "wof:name":"Jushuang",
    "wof:placetype":"locality"
},
  "geometry": {"coordinates":[120.15402,32.05537],"type":"Point"}
}