{
  "type": "Feature",
  "properties": {
    "gn:admin1_code":"19.0",
    "gn:asciiname":"Yuanmaying",
    "gn:country_code":"CN",
    "gn:dem":670,
    "gn:feature_class":"P",
    "gn:feature_code":"PPL",
    "gn:name":"Yuanmaying",
    "gn:population":0,
    "gn:timezone":"Asia/Shanghai",
    "iso:country":"CN",
    "name:zho_x_preferred":[
        "\u8881\u9a6c\u8425"
    ],
    "wof:name":"Yuanmaying",
    "wof:placetype":"locality"
},
  "geometry": {"coordinates":[119.52698999999998,41.97916],"type":"Point"}
}