{
  "type": "Feature",
  "properties": {
    "gn:admin1_code":"1.0",
    "gn:asciiname":"Yanghecun",
    "gn:country_code":"CN",
    "gn:dem":44,
    "gn:feature_class":"P",
    "gn:feature_code":"PPL",
    "gn:name":"Yanghecun",
    "gn:population":0,
    "gn:timezone":"Asia/Shanghai",
    "iso:country":"CN",
    "name:zho_x_preferred":[
        "\u9633\u548c\u6751"
    ],
    "wof:name":"Yanghecun",
    "wof:placetype":"locality"
},
  "geometry": {"coordinates":[117.15136,31.01605],"type":"Point"}
}