{
  "type": "Feature",
  "properties": {
    "gn:admin1_code":"12.0",
    "gn:asciiname":"Gengpengya",
    "gn:country_code":"CN",
    "gn:dem":262,
    "gn:feature_class":"P",
    "gn:feature_code":"PPL",
    "gn:name":"Gengpengya",
    "gn:population":0,
    "gn:timezone":"Asia/Shanghai",
    "iso:country":"CN",
    "name:zho_x_preferred":[
        "\u66f4\u68da\u57ad"
    ],
    "wof:name":"Gengpengya",
    "wof:placetype":"locality"
},
  "geometry": {"coordinates":[111.852,31.08477],"type":"Point"}
}