{
  "type": "Feature",
  "properties": {
    "gn:admin1_code":"16.0",
    "gn:asciiname":"Liukuaitian",
    "gn:country_code":"CN",
    "gn:dem":59,
    "gn:feature_class":"P",
    "gn:feature_code":"PPL",
    "gn:name":"Liukuaitian",
    "gn:population":0,
    "gn:timezone":"Asia/Shanghai",
    "iso:country":"CN",
    "name:zho_x_preferred":[
        "\u516d\u5757\u7530"
    ],
    "wof:name":"Liukuaitian",
    "wof:placetype":"locality"
},
  "geometry": {"coordinates":[109.721,22.0954],"type":"Point"}
}