{
  "type": "Feature",
  "properties": {
    "gn:admin1_code":"18.0",
    "gn:asciiname":"Langmo",
    "gn:country_code":"CN",
    "gn:dem":879,
    "gn:feature_class":"P",
    "gn:feature_code":"PPL",
    "gn:name":"Langmo",
    "gn:population":0,
    "gn:timezone":"Asia/Shanghai",
    "iso:country":"CN",
    "name:zho_x_preferred":[
        "\u6d6a\u83ab"
    ],
    "wof:name":"Langmo",
    "wof:placetype":"locality"
},
  "geometry": {"coordinates":[107.699,25.3715],"type":"Point"}
}