{
  "type": "Feature",
  "properties": {
    "gn:admin1_code":"29.0",
    "gn:asciiname":"Xiaofazhao",
    "gn:country_code":"CN",
    "gn:dem":2023,
    "gn:feature_class":"P",
    "gn:feature_code":"PPL",
    "gn:name":"Xiaofazhao",
    "gn:population":0,
    "gn:timezone":"Asia/Shanghai",
    "iso:country":"CN",
    "name:zho_x_preferred":[
        "\u5c0f\u6cd5\u53ec"
    ],
    "wof:name":"Xiaofazhao",
    "wof:placetype":"locality"
},
  "geometry": {"coordinates":[103.938,24.9761],"type":"Point"}
}