{
  "type": "Feature",
  "properties": {
    "gn:admin1_code":"19.0",
    "gn:asciiname":"Wang'ergangcun",
    "gn:country_code":"CN",
    "gn:dem":5,
    "gn:feature_class":"P",
    "gn:feature_code":"PPL",
    "gn:name":"Wang\u2019ergangcun",
    "gn:population":0,
    "gn:timezone":"Asia/Shanghai",
    "iso:country":"CN",
    "name:und_x_variant":[
        "Wang\u2019ergangcun"
    ],
    "name:zho_x_preferred":[
        "\u738b\u800c\u5c97\u6751"
    ],
    "wof:name":"Wang'ergangcun",
    "wof:placetype":"locality"
},
  "geometry": {"coordinates":[122.30163,40.38747],"type":"Point"}
}