{
  "type": "Feature",
  "properties": {
    "gn:admin1_code":"03",
    "gn:asciiname":"Jiangyi",
    "gn:country_code":"CN",
    "gn:dem":33,
    "gn:feature_class":"P",
    "gn:feature_code":"PPLA4",
    "gn:name":"Jiangyi",
    "gn:population":0,
    "gn:timezone":"Asia/Shanghai",
    "iso:country":"CN",
    "name:und_x_variant":[
        "Chiang-i",
        "Jiangyi",
        "\u6c5f\u76ca",
        "Jiangyi Zhen",
        "\u6c5f\u76ca\u9547"
    ],
    "wof:name":"Jiangyi",
    "wof:placetype":"locality"
},
  "geometry": {"coordinates":[115.77263000000001,29.21162],"type":"Point"}
}