{
  "type": "Feature",
  "properties": {
    "gn:admin1_code":"21.0",
    "gn:asciiname":"Dongshan",
    "gn:country_code":"CN",
    "gn:dem":1834,
    "gn:feature_class":"P",
    "gn:feature_code":"PPL",
    "gn:name":"Dongshan",
    "gn:population":0,
    "gn:timezone":"Asia/Shanghai",
    "iso:country":"CN",
    "name:und_x_variant":[
        "\u4e1c\u5c71"
    ],
    "name:zho_x_preferred":[
        "\u4e1c\u5c71"
    ],
    "wof:name":"Dongshan",
    "wof:placetype":"locality"
},
  "geometry": {"coordinates":[105.63482,35.88273],"type":"Point"}
}