{
  "type": "Feature",
  "properties": {
    "gn:admin1_code":"19.0",
    "gn:asciiname":"Sanbali",
    "gn:country_code":"CN",
    "gn:dem":33,
    "gn:feature_class":"P",
    "gn:feature_code":"PPL",
    "gn:name":"Sanbali",
    "gn:population":0,
    "gn:timezone":"Asia/Shanghai",
    "iso:country":"CN",
    "name:zho_x_preferred":[
        "\u4e09\u516b\u91cc"
    ],
    "wof:name":"Sanbali",
    "wof:placetype":"locality"
},
  "geometry": {"coordinates":[121.26300000000001,38.8494],"type":"Point"}
}