{
  "type": "Feature",
  "properties": {
    "gn:admin1_code":"32.0",
    "gn:asciiname":"Dishuiyan",
    "gn:country_code":"CN",
    "gn:dem":420,
    "gn:feature_class":"P",
    "gn:feature_code":"PPL",
    "gn:name":"Dishuiyan",
    "gn:population":0,
    "gn:timezone":"Asia/Shanghai",
    "iso:country":"CN",
    "name:zho_x_preferred":[
        "\u6ef4\u6c34\u5ca9"
    ],
    "wof:name":"Dishuiyan",
    "wof:placetype":"locality"
},
  "geometry": {"coordinates":[104.27500000000001,29.7919],"type":"Point"}
}