{
  "type": "Feature",
  "properties": {
    "gn:admin1_code":"16.0",
    "gn:asciiname":"Nongxiao",
    "gn:country_code":"CN",
    "gn:dem":201,
    "gn:feature_class":"P",
    "gn:feature_code":"PPL",
    "gn:name":"Nongxiao",
    "gn:population":0,
    "gn:timezone":"Asia/Shanghai",
    "iso:country":"CN",
    "name:zho_x_preferred":[
        "\u5f04\u7b11"
    ],
    "wof:name":"Nongxiao",
    "wof:placetype":"locality"
},
  "geometry": {"coordinates":[107.34099999999999,22.2778],"type":"Point"}
}