{
  "type": "Feature",
  "properties": {
    "gn:admin1_code":"8.0",
    "gn:asciiname":"Fendou",
    "gn:country_code":"CN",
    "gn:dem":138,
    "gn:feature_class":"P",
    "gn:feature_code":"PPL",
    "gn:name":"Fendou",
    "gn:population":0,
    "gn:timezone":"Asia/Shanghai",
    "iso:country":"CN",
    "name:zho_x_preferred":[
        "\u594b\u6597"
    ],
    "wof:name":"Fendou",
    "wof:placetype":"locality"
},
  "geometry": {"coordinates":[130.52881000000002,47.6945],"type":"Point"}
}