{
  "type": "Feature",
  "properties": {
    "gn:admin1_code":"10.0",
    "gn:asciiname":"Yancun",
    "gn:country_code":"CN",
    "gn:dem":18,
    "gn:feature_class":"P",
    "gn:feature_code":"PPL",
    "gn:name":"Yancun",
    "gn:population":0,
    "gn:timezone":"Asia/Shanghai",
    "iso:country":"CN",
    "name:und_x_variant":[
        "Yang-ts\u2019un",
        "Yang-t\u2019sun-chen",
        "Yangcun",
        "Yancun"
    ],
    "name:zho_x_preferred":[
        "\u6cbf\u6751"
    ],
    "wof:name":"Yancun",
    "wof:placetype":"locality"
},
  "geometry": {"coordinates":[115.70662,39.0314],"type":"Point"}
}