{
  "type": "Feature",
  "properties": {
    "gn:admin1_code":"26.0",
    "gn:asciiname":"Qipangou",
    "gn:country_code":"CN",
    "gn:dem":1094,
    "gn:feature_class":"P",
    "gn:feature_code":"PPL",
    "gn:name":"Qipangou",
    "gn:population":0,
    "gn:timezone":"Asia/Shanghai",
    "iso:country":"CN",
    "name:und_x_variant":[
        "\u68cb\u76d8\u6c9f"
    ],
    "wof:name":"Qipangou",
    "wof:placetype":"locality"
},
  "geometry": {"coordinates":[107.70923999999999,33.46126],"type":"Point"}
}