{
  "type": "Feature",
  "properties": {
    "gn:admin1_code":"19.0",
    "gn:asciiname":"Rongzhangzicun",
    "gn:country_code":"CN",
    "gn:dem":433,
    "gn:feature_class":"P",
    "gn:feature_code":"PPL",
    "gn:name":"Rongzhangzicun",
    "gn:population":0,
    "gn:timezone":"Asia/Shanghai",
    "iso:country":"CN",
    "name:zho_x_preferred":[
        "\u8363\u6756\u5b50\u6751"
    ],
    "wof:name":"Rongzhangzicun",
    "wof:placetype":"locality"
},
  "geometry": {"coordinates":[119.38200000000001,41.1636],"type":"Point"}
}