{
  "type": "Feature",
  "properties": {
    "gn:admin1_code":"16.0",
    "gn:asciiname":"Shuijun",
    "gn:country_code":"CN",
    "gn:dem":215,
    "gn:feature_class":"P",
    "gn:feature_code":"PPL",
    "gn:name":"Shuijun",
    "gn:population":0,
    "gn:timezone":"Asia/Shanghai",
    "iso:country":"CN",
    "name:zho_x_preferred":[
        "\u6c34\u5747"
    ],
    "wof:name":"Shuijun",
    "wof:placetype":"locality"
},
  "geometry": {"coordinates":[110.19799999999999,23.8035],"type":"Point"}
}