{
  "type": "Feature",
  "properties": {
    "gn:admin1_code":"11.0",
    "gn:asciiname":"Lilin",
    "gn:country_code":"CN",
    "gn:dem":186,
    "gn:feature_class":"P",
    "gn:feature_code":"PPL",
    "gn:name":"Lilin",
    "gn:population":0,
    "gn:timezone":"Asia/Shanghai",
    "iso:country":"CN",
    "name:zho_x_preferred":[
        "\u680e\u6797"
    ],
    "wof:name":"Lilin",
    "wof:placetype":"locality"
},
  "geometry": {"coordinates":[110.63182999999999,27.99777000000001],"type":"Point"}
}