{
  "type": "Feature",
  "properties": {
    "gn:admin1_code":"26.0",
    "gn:asciiname":"Yuangetacun",
    "gn:country_code":"CN",
    "gn:dem":1197,
    "gn:feature_class":"P",
    "gn:feature_code":"PPL",
    "gn:name":"Yuangetacun",
    "gn:population":0,
    "gn:timezone":"Asia/Shanghai",
    "iso:country":"CN",
    "name:zho_x_preferred":[
        "\u5143\u572a\u5854\u6751"
    ],
    "wof:name":"Yuangetacun",
    "wof:placetype":"locality"
},
  "geometry": {"coordinates":[109.66896,35.55608],"type":"Point"}
}