{
  "type": "Feature",
  "properties": {
    "gn:admin1_code":"7.0",
    "gn:asciiname":"Anziqian",
    "gn:country_code":"CN",
    "gn:dem":319,
    "gn:feature_class":"P",
    "gn:feature_code":"PPL",
    "gn:name":"Anziqian",
    "gn:population":0,
    "gn:timezone":"Asia/Shanghai",
    "iso:country":"CN",
    "name:zho_x_preferred":[
        "\u5eb5\u5b50\u524d"
    ],
    "wof:name":"Anziqian",
    "wof:placetype":"locality"
},
  "geometry": {"coordinates":[116.88636,24.7972],"type":"Point"}
}