{
  "type": "Feature",
  "properties": {
    "gn:admin1_code":"04",
    "gn:asciiname":"Beixin",
    "gn:country_code":"CN",
    "gn:dem":4,
    "gn:feature_class":"P",
    "gn:feature_code":"PPLA4",
    "gn:name":"Beixin",
    "gn:population":0,
    "gn:timezone":"Asia/Shanghai",
    "iso:country":"CN",
    "name:und_x_variant":[
        "Pei-hsin-chen",
        "Beixinzhen",
        "Beixin",
        "\u5317\u65b0",
        "Beixin Zhen",
        "\u5317\u65b0\u9547"
    ],
    "wof:name":"Beixin",
    "wof:placetype":"locality"
},
  "geometry": {"coordinates":[121.50881,31.82509000000001],"type":"Point"}
}