{
  "type": "Feature",
  "properties": {
    "gn:admin1_code":"30",
    "gn:asciiname":"Baiji",
    "gn:country_code":"CN",
    "gn:dem":25,
    "gn:feature_class":"P",
    "gn:feature_code":"PPL",
    "gn:name":"Baiji",
    "gn:population":0,
    "gn:timezone":"Asia/Urumqi",
    "iso:country":"CN",
    "name:zho_x_preferred":[
        "\u67cf\u57fa"
    ],
    "wof:name":"Baiji",
    "wof:placetype":"locality"
},
  "geometry": {"coordinates":[109.9455,21.22512],"type":"Point"}
}