{
  "type": "Feature",
  "properties": {
    "gn:admin1_code":"25",
    "gn:asciiname":"Heiyu",
    "gn:country_code":"CN",
    "gn:dem":354,
    "gn:feature_class":"P",
    "gn:feature_code":"PPL",
    "gn:name":"Heiyu",
    "gn:population":0,
    "gn:timezone":"Asia/Shanghai",
    "iso:country":"CN",
    "name:zho_x_preferred":[
        "\u9ed1\u5cea"
    ],
    "wof:name":"Heiyu",
    "wof:placetype":"locality"
},
  "geometry": {"coordinates":[117.20399999999999,36.4926],"type":"Point"}
}