{
  "type": "Feature",
  "properties": {
    "gn:admin1_code":"30.0",
    "gn:asciiname":"Dongshengyong",
    "gn:country_code":"CN",
    "gn:dem":-1,
    "gn:feature_class":"P",
    "gn:feature_code":"PPL",
    "gn:name":"Dongshengyong",
    "gn:population":0,
    "gn:timezone":"Asia/Shanghai",
    "iso:country":"CN",
    "name:zho_x_preferred":[
        "\u4e1c\u751f\u6d8c"
    ],
    "wof:name":"Dongshengyong",
    "wof:placetype":"locality"
},
  "geometry": {"coordinates":[113.37520000000001,22.74228],"type":"Point"}
}