{
  "type": "Feature",
  "properties": {
    "gn:admin1_code":"26.0",
    "gn:asciiname":"Zhongjia Jiancun",
    "gn:country_code":"CN",
    "gn:dem":984,
    "gn:feature_class":"P",
    "gn:feature_code":"PPL",
    "gn:name":"Zhongjia Jiancun",
    "gn:population":0,
    "gn:timezone":"Asia/Shanghai",
    "iso:country":"CN",
    "name:zho_x_preferred":[
        "\u949f\u5bb6\u7877\u6751"
    ],
    "wof:name":"Zhongjia Jiancun",
    "wof:placetype":"locality"
},
  "geometry": {"coordinates":[110.021,37.5685],"type":"Point"}
}