{
  "type": "Feature",
  "properties": {
    "gn:admin1_code":"32.0",
    "gn:asciiname":"Xibeigong",
    "gn:country_code":"CN",
    "gn:dem":2471,
    "gn:feature_class":"P",
    "gn:feature_code":"PPL",
    "gn:name":"Xibeigong",
    "gn:population":0,
    "gn:timezone":"Asia/Shanghai",
    "iso:country":"CN",
    "name:zho_x_preferred":[
        "\u897f\u5317\u5bab"
    ],
    "wof:name":"Xibeigong",
    "wof:placetype":"locality"
},
  "geometry": {"coordinates":[101.224,28.7057],"type":"Point"}
}