{
  "type": "Feature",
  "properties": {
    "gn:admin1_code":"8.0",
    "gn:asciiname":"Wangdianyuan",
    "gn:country_code":"CN",
    "gn:dem":247,
    "gn:feature_class":"P",
    "gn:feature_code":"PPL",
    "gn:name":"Wangdianyuan",
    "gn:population":0,
    "gn:timezone":"Asia/Shanghai",
    "iso:country":"CN",
    "name:zho_x_preferred":[
        "\u738b\u6bbf\u5143"
    ],
    "wof:name":"Wangdianyuan",
    "wof:placetype":"locality"
},
  "geometry": {"coordinates":[126.69347,47.76029000000001],"type":"Point"}
}