{
  "type": "Feature",
  "properties": {
    "gn:admin1_code":"2.0",
    "gn:asciiname":"Xuexiazhuang",
    "gn:country_code":"CN",
    "gn:dem":269,
    "gn:feature_class":"P",
    "gn:feature_code":"PPL",
    "gn:name":"Xuexiazhuang",
    "gn:population":0,
    "gn:timezone":"Asia/Shanghai",
    "iso:country":"CN",
    "name:und_x_variant":[
        "\u859b\u4e0b\u5e84",
        "Xuexiazhuang"
    ],
    "wof:name":"Xuexiazhuang",
    "wof:placetype":"locality"
},
  "geometry": {"coordinates":[119.85733,29.53811],"type":"Point"}
}