{
  "type": "Feature",
  "properties": {
    "gn:admin1_code":"26.0",
    "gn:asciiname":"Guangmeigoukou",
    "gn:country_code":"CN",
    "gn:dem":697,
    "gn:feature_class":"P",
    "gn:feature_code":"PPL",
    "gn:name":"Guangmeigoukou",
    "gn:population":0,
    "gn:timezone":"Asia/Shanghai",
    "iso:country":"CN",
    "name:zho_x_preferred":[
        "\u5e7f\u6885\u6c9f\u53e3"
    ],
    "wof:name":"Guangmeigoukou",
    "wof:placetype":"locality"
},
  "geometry": {"coordinates":[109.76683,33.42882],"type":"Point"}
}