{
  "type": "Feature",
  "properties": {
    "gn:admin1_code":"26.0",
    "gn:asciiname":"Tiefosicun",
    "gn:country_code":"CN",
    "gn:dem":595,
    "gn:feature_class":"P",
    "gn:feature_code":"PPL",
    "gn:name":"Tiefosicun",
    "gn:population":0,
    "gn:timezone":"Asia/Shanghai",
    "iso:country":"CN",
    "name:und_x_variant":[
        "\u94c1\u4f5b\u5bfa\u6751"
    ],
    "wof:name":"Tiefosicun",
    "wof:placetype":"locality"
},
  "geometry": {"coordinates":[107.55903000000001,32.9954],"type":"Point"}
}