{
  "type": "Feature",
  "properties": {
    "gn:admin1_code":"29",
    "gn:asciiname":"Lutu",
    "gn:country_code":"CN",
    "gn:dem":2097,
    "gn:feature_class":"P",
    "gn:feature_code":"PPL",
    "gn:name":"Lutu",
    "gn:population":0,
    "gn:timezone":"Asia/Shanghai",
    "iso:country":"CN",
    "wof:name":"Lutu",
    "wof:placetype":"locality"
},
  "geometry": {"coordinates":[102.97211,25.48652],"type":"Point"}
}