{
  "type": "Feature",
  "properties": {
    "gn:admin1_code":"18",
    "gn:asciiname":"Chadian",
    "gn:country_code":"CN",
    "gn:dem":1275,
    "gn:feature_class":"P",
    "gn:feature_code":"PPL",
    "gn:name":"Chadian",
    "gn:population":0,
    "gn:timezone":"Asia/Shanghai",
    "iso:country":"CN",
    "name:ceb_x_preferred":[
        "Chadian"
    ],
    "name:swe_x_preferred":[
        "Chadian"
    ],
    "name:zho_x_preferred":[
        "\u8336\u5e97"
    ],
    "wof:name":"Chadian",
    "wof:placetype":"locality"
},
  "geometry": {"coordinates":[106.18899999999999,26.8451],"type":"Point"}
}