{
  "type": "Feature",
  "properties": {
    "gn:admin1_code":"26.0",
    "gn:asciiname":"Jinfo Pingcun",
    "gn:country_code":"CN",
    "gn:dem":1274,
    "gn:feature_class":"P",
    "gn:feature_code":"PPL",
    "gn:name":"Jinfo Pingcun",
    "gn:population":0,
    "gn:timezone":"Asia/Shanghai",
    "iso:country":"CN",
    "name:zho_x_preferred":[
        "\u91d1\u4f5b\u576a\u6751"
    ],
    "wof:name":"Jinfo Pingcun",
    "wof:placetype":"locality"
},
  "geometry": {"coordinates":[108.199,36.8423],"type":"Point"}
}