{
  "type": "Feature",
  "properties": {
    "gn:admin1_code":"10",
    "gn:asciiname":"Haozhangzi",
    "gn:country_code":"CN",
    "gn:dem":590,
    "gn:feature_class":"P",
    "gn:feature_code":"PPL",
    "gn:name":"Haozhangzi",
    "gn:population":0,
    "gn:timezone":"Asia/Shanghai",
    "iso:country":"CN",
    "name:zho_x_preferred":[
        "\u90dd\u6756\u5b50"
    ],
    "wof:name":"Haozhangzi",
    "wof:placetype":"locality"
},
  "geometry": {"coordinates":[118.7709,40.70412],"type":"Point"}
}