{
  "type": "Feature",
  "properties": {
    "gn:admin1_code":"3.0",
    "gn:asciiname":"Zhalin",
    "gn:country_code":"CN",
    "gn:dem":131,
    "gn:feature_class":"P",
    "gn:feature_code":"PPL",
    "gn:name":"Zhalin",
    "gn:population":0,
    "gn:timezone":"Asia/Shanghai",
    "iso:country":"CN",
    "name:zho_x_preferred":[
        "\u6e23\u6797"
    ],
    "wof:name":"Zhalin",
    "wof:placetype":"locality"
},
  "geometry": {"coordinates":[114.09399999999999,27.7659],"type":"Point"}
}