{
  "type": "Feature",
  "properties": {
    "gn:admin1_code":"32.0",
    "gn:asciiname":"Zhonghuazui",
    "gn:country_code":"CN",
    "gn:dem":964,
    "gn:feature_class":"P",
    "gn:feature_code":"PPL",
    "gn:name":"Zhonghuazui",
    "gn:population":0,
    "gn:timezone":"Asia/Shanghai",
    "iso:country":"CN",
    "name:und_x_variant":[
        "\u4e2d\u534e\u5480"
    ],
    "wof:name":"Zhonghuazui",
    "wof:placetype":"locality"
},
  "geometry": {"coordinates":[106.10890000000001,32.14757],"type":"Point"}
}