{
  "type": "Feature",
  "properties": {
    "gn:admin1_code":"5.0",
    "gn:asciiname":"Aijiagoucun",
    "gn:country_code":"CN",
    "gn:dem":205,
    "gn:feature_class":"P",
    "gn:feature_code":"PPL",
    "gn:name":"Aijiagoucun",
    "gn:population":0,
    "gn:timezone":"Asia/Shanghai",
    "iso:country":"CN",
    "name:zho_x_preferred":[
        "\u827e\u5bb6\u6c9f\u6751"
    ],
    "wof:name":"Aijiagoucun",
    "wof:placetype":"locality"
},
  "geometry": {"coordinates":[125.97765,45.04061],"type":"Point"}
}