{
  "type": "Feature",
  "properties": {
    "gn:admin1_code":"18",
    "gn:asciiname":"Niuzhai",
    "gn:country_code":"CN",
    "gn:dem":1133,
    "gn:feature_class":"P",
    "gn:feature_code":"PPL",
    "gn:name":"Niuzhai",
    "gn:population":0,
    "gn:timezone":"Asia/Shanghai",
    "iso:country":"CN",
    "name:zho_x_preferred":[
        "\u725b\u5be8"
    ],
    "wof:name":"Niuzhai",
    "wof:placetype":"locality"
},
  "geometry": {"coordinates":[106.348,25.6886],"type":"Point"}
}