{
  "type": "Feature",
  "properties": {
    "gn:admin1_code":"24.0",
    "gn:asciiname":"Ganghe",
    "gn:country_code":"CN",
    "gn:dem":757,
    "gn:feature_class":"P",
    "gn:feature_code":"PPL",
    "gn:name":"Ganghe",
    "gn:population":0,
    "gn:timezone":"Asia/Shanghai",
    "iso:country":"CN",
    "name:zho_x_preferred":[
        "\u5c97\u6cb3"
    ],
    "wof:name":"Ganghe",
    "wof:placetype":"locality"
},
  "geometry": {"coordinates":[112.85481,35.43868],"type":"Point"}
}