{
  "type": "Feature",
  "properties": {
    "gn:admin1_code":"30",
    "gn:asciiname":"Liuyun",
    "gn:country_code":"CN",
    "gn:dem":245,
    "gn:feature_class":"P",
    "gn:feature_code":"PPL",
    "gn:name":"Liuyun",
    "gn:population":0,
    "gn:timezone":"Asia/Urumqi",
    "iso:country":"CN",
    "name:zho_x_preferred":[
        "\u516d\u4e91"
    ],
    "wof:name":"Liuyun",
    "wof:placetype":"locality"
},
  "geometry": {"coordinates":[110.82883,22.37364],"type":"Point"}
}