{
  "type": "Feature",
  "properties": {
    "gn:admin1_code":"29",
    "gn:asciiname":"Dengloushan",
    "gn:country_code":"CN",
    "gn:dem":2031,
    "gn:feature_class":"P",
    "gn:feature_code":"PPL",
    "gn:name":"Dengloushan",
    "gn:population":0,
    "gn:timezone":"Asia/Shanghai",
    "iso:country":"CN",
    "name:zho_x_preferred":[
        "\u767b\u697c\u5c71"
    ],
    "wof:name":"Dengloushan",
    "wof:placetype":"locality"
},
  "geometry": {"coordinates":[103.002,24.1533],"type":"Point"}
}