{
  "type": "Feature",
  "properties": {
    "gn:admin1_code":"29.0",
    "gn:asciiname":"Baiyicun",
    "gn:country_code":"CN",
    "gn:dem":1875,
    "gn:feature_class":"P",
    "gn:feature_code":"PPL",
    "gn:name":"Baiyicun",
    "gn:population":0,
    "gn:timezone":"Asia/Shanghai",
    "iso:country":"CN",
    "name:zho_x_preferred":[
        "\u767d\u5937\u6751"
    ],
    "wof:name":"Baiyicun",
    "wof:placetype":"locality"
},
  "geometry": {"coordinates":[100.762,26.018],"type":"Point"}
}