{
  "type": "Feature",
  "properties": {
    "gn:admin1_code":"18",
    "gn:asciiname":"Chuduping",
    "gn:country_code":"CN",
    "gn:dem":1577,
    "gn:feature_class":"P",
    "gn:feature_code":"PPL",
    "gn:name":"Chuduping",
    "gn:population":0,
    "gn:timezone":"Asia/Shanghai",
    "iso:country":"CN",
    "name:zho_x_preferred":[
        "\u521d\u90fd\u576a"
    ],
    "wof:name":"Chuduping",
    "wof:placetype":"locality"
},
  "geometry": {"coordinates":[104.955,27.3435],"type":"Point"}
}