{
  "type": "Feature",
  "properties": {
    "gn:admin1_code":"25",
    "gn:asciiname":"Fangdi",
    "gn:country_code":"CN",
    "gn:dem":35,
    "gn:feature_class":"P",
    "gn:feature_code":"PPL",
    "gn:name":"Fangdi",
    "gn:population":0,
    "gn:timezone":"Asia/Shanghai",
    "iso:country":"CN",
    "name:zho_x_preferred":[
        "\u65b9\u7fdf"
    ],
    "wof:name":"Fangdi",
    "wof:placetype":"locality"
},
  "geometry": {"coordinates":[116.55500000000001,36.4188],"type":"Point"}
}