{
  "type": "Feature",
  "properties": {
    "gn:admin1_code":"16.0",
    "gn:asciiname":"Pingjiang",
    "gn:country_code":"CN",
    "gn:dem":91,
    "gn:feature_class":"P",
    "gn:feature_code":"PPL",
    "gn:name":"Pingjiang",
    "gn:population":0,
    "gn:timezone":"Asia/Shanghai",
    "iso:country":"CN",
    "name:ceb_x_preferred":[
        "Pingjiang"
    ],
    "name:deu_x_preferred":[
        "Pingjiang"
    ],
    "name:fra_x_preferred":[
        "Pingjiang"
    ],
    "name:nor_x_preferred":[
        "Pingjiang"
    ],
    "name:zho_x_preferred":[
        "\u5e73\u6c5f"
    ],
    "wof:name":"Pingjiang",
    "wof:placetype":"locality"
},
  "geometry": {"coordinates":[109.503,22.1803],"type":"Point"}
}