{
  "type": "Feature",
  "properties": {
    "gn:admin1_code":"15.0",
    "gn:asciiname":"Fushuzhuang",
    "gn:country_code":"CN",
    "gn:dem":1829,
    "gn:feature_class":"P",
    "gn:feature_code":"PPL",
    "gn:name":"Fushuzhuang",
    "gn:population":0,
    "gn:timezone":"Asia/Shanghai",
    "iso:country":"CN",
    "name:zho_x_preferred":[
        "\u5bcc\u6811\u5e84"
    ],
    "wof:name":"Fushuzhuang",
    "wof:placetype":"locality"
},
  "geometry": {"coordinates":[100.81399999999999,38.6691],"type":"Point"}
}