{
  "type": "Feature",
  "properties": {
    "gn:admin1_code":"32.0",
    "gn:asciiname":"Nanjiashan",
    "gn:country_code":"CN",
    "gn:dem":739,
    "gn:feature_class":"P",
    "gn:feature_code":"PPL",
    "gn:name":"Nanjiashan",
    "gn:population":0,
    "gn:timezone":"Asia/Shanghai",
    "iso:country":"CN",
    "name:zho_x_preferred":[
        "\u5357\u5bb6\u5c71"
    ],
    "wof:name":"Nanjiashan",
    "wof:placetype":"locality"
},
  "geometry": {"coordinates":[103.79764,29.08978],"type":"Point"}
}