{
  "type": "Feature",
  "properties": {
    "gn:admin1_code":"19.0",
    "gn:asciiname":"Gaokan Qingnian Nongchang",
    "gn:country_code":"CN",
    "gn:dem":3,
    "gn:feature_class":"P",
    "gn:feature_code":"PPLF",
    "gn:name":"Gaokan Qingnian Nongchang",
    "gn:population":0,
    "gn:timezone":"Asia/Shanghai",
    "iso:country":"CN",
    "name:und_x_variant":[
        "\u9ad8\u574e\u9752\u5e74\u519c\u573a"
    ],
    "wof:name":"Gaokan Qingnian Nongchang",
    "wof:placetype":"locality"
},
  "geometry": {"coordinates":[122.50388,40.78281],"type":"Point"}
}