{
  "type": "Feature",
  "properties": {
    "gn:admin1_code":"12.0",
    "gn:asciiname":"Nanchansi",
    "gn:country_code":"CN",
    "gn:dem":29,
    "gn:feature_class":"P",
    "gn:feature_code":"PPL",
    "gn:name":"Nanchansi",
    "gn:population":0,
    "gn:timezone":"Asia/Shanghai",
    "iso:country":"CN",
    "name:zho_x_preferred":[
        "\u5357\u7985\u5bfa"
    ],
    "wof:name":"Nanchansi",
    "wof:placetype":"locality"
},
  "geometry": {"coordinates":[112.94138,30.1162],"type":"Point"}
}