{
  "type": "Feature",
  "properties": {
    "gn:admin1_code":"3.0",
    "gn:asciiname":"Xiabian Zhangjia",
    "gn:country_code":"CN",
    "gn:dem":157,
    "gn:feature_class":"P",
    "gn:feature_code":"PPL",
    "gn:name":"Xiabian Zhangjia",
    "gn:population":0,
    "gn:timezone":"Asia/Shanghai",
    "iso:country":"CN",
    "name:und_x_variant":[
        "\u4e0b\u8fb9\u5f20\u5bb6"
    ],
    "wof:name":"Xiabian Zhangjia",
    "wof:placetype":"locality"
},
  "geometry": {"coordinates":[114.60388,27.05667],"type":"Point"}
}