{
  "type": "Feature",
  "properties": {
    "gn:admin1_code":"02",
    "gn:asciiname":"Liutiaoxi",
    "gn:country_code":"CN",
    "gn:dem":22,
    "gn:feature_class":"P",
    "gn:feature_code":"PPL",
    "gn:name":"Liutiaoxi",
    "gn:population":0,
    "gn:timezone":"Asia/Shanghai",
    "iso:country":"CN",
    "name:und_x_variant":[
        "Lu-t\u2019iao-hsi",
        "Liutiaoxi",
        "\u516d\u6761\u6eaa",
        "Liutiaoxicun",
        "\u516d\u6761\u6eaa\u6751"
    ],
    "wof:name":"Liutiaoxi",
    "wof:placetype":"locality"
},
  "geometry": {"coordinates":[122.40978,30.45193],"type":"Point"}
}