{
  "type": "Feature",
  "properties": {
    "gn:admin1_code":"25.0",
    "gn:asciiname":"Jiangbocun",
    "gn:country_code":"CN",
    "gn:dem":10,
    "gn:feature_class":"P",
    "gn:feature_code":"PPL",
    "gn:name":"Jiangbocun",
    "gn:population":0,
    "gn:timezone":"Asia/Shanghai",
    "iso:country":"CN",
    "name:zho_x_preferred":[
        "\u59dc\u6cca\u6751"
    ],
    "wof:name":"Jiangbocun",
    "wof:placetype":"locality"
},
  "geometry": {"coordinates":[119.43653,36.9401],"type":"Point"}
}