{
  "type": "Feature",
  "properties": {
    "gn:admin1_code":"11",
    "gn:asciiname":"Tangjiayuan",
    "gn:country_code":"CN",
    "gn:dem":95,
    "gn:feature_class":"P",
    "gn:feature_code":"PPL",
    "gn:name":"Tangjiayuan",
    "gn:population":0,
    "gn:timezone":"Asia/Shanghai",
    "iso:country":"CN",
    "name:zho_x_preferred":[
        "\u5510\u5bb6\u9662"
    ],
    "wof:name":"Tangjiayuan",
    "wof:placetype":"locality"
},
  "geometry": {"coordinates":[111.90631999999999,26.51028],"type":"Point"}
}