{
  "type": "Feature",
  "properties": {
    "gn:admin1_code":"26.0",
    "gn:asciiname":"Dengjiaheba",
    "gn:country_code":"CN",
    "gn:dem":1214,
    "gn:feature_class":"P",
    "gn:feature_code":"PPL",
    "gn:name":"Dengjiaheba",
    "gn:population":0,
    "gn:timezone":"Asia/Shanghai",
    "iso:country":"CN",
    "name:und_x_variant":[
        "\u9093\u5bb6\u6cb3\u575d"
    ],
    "wof:name":"Dengjiaheba",
    "wof:placetype":"locality"
},
  "geometry": {"coordinates":[105.76826,33.30447],"type":"Point"}
}