{
  "type": "Feature",
  "properties": {
    "gn:admin1_code":"20.0",
    "gn:asciiname":"Wentugaole",
    "gn:country_code":"CN",
    "gn:dem":945,
    "gn:feature_class":"P",
    "gn:feature_code":"PPLA4",
    "gn:name":"Wentugaole",
    "gn:population":0,
    "gn:timezone":"Asia/Shanghai",
    "iso:country":"CN",
    "name:und_x_variant":[
        "Wentugaole Sumu"
    ],
    "name:zho_x_preferred":[
        "\u6e29\u56fe\u9ad8\u52d2"
    ],
    "name:zho_x_variant":[
        "\u6e29\u56fe\u9ad8\u52d2\u82cf\u6728"
    ],
    "wof:name":"Wentugaole",
    "wof:placetype":"locality"
},
  "geometry": {"coordinates":[102.11586,41.42646],"type":"Point"}
}