{
  "type": "Feature",
  "properties": {
    "gn:admin1_code":"11.0",
    "gn:asciiname":"Dapingkou",
    "gn:country_code":"CN",
    "gn:dem":440,
    "gn:feature_class":"P",
    "gn:feature_code":"PPL",
    "gn:name":"Dapingkou",
    "gn:population":0,
    "gn:timezone":"Asia/Shanghai",
    "iso:country":"CN",
    "name:zho_x_preferred":[
        "\u5927\u576a\u53e3"
    ],
    "wof:name":"Dapingkou",
    "wof:placetype":"locality"
},
  "geometry": {"coordinates":[110.92116,26.69611],"type":"Point"}
}