{
  "type": "Feature",
  "properties": {
    "gn:admin1_code":"26.0",
    "gn:asciiname":"Wenshuibian",
    "gn:country_code":"CN",
    "gn:dem":936,
    "gn:feature_class":"P",
    "gn:feature_code":"PPL",
    "gn:name":"Wenshuibian",
    "gn:population":0,
    "gn:timezone":"Asia/Shanghai",
    "iso:country":"CN",
    "name:zho_x_preferred":[
        "\u6e29\u6c34\u782d"
    ],
    "wof:name":"Wenshuibian",
    "wof:placetype":"locality"
},
  "geometry": {"coordinates":[109.17827,32.12560999999999],"type":"Point"}
}