{
  "type": "Feature",
  "properties": {
    "gn:admin1_code":"16.0",
    "gn:asciiname":"Datuo",
    "gn:country_code":"CN",
    "gn:dem":1397,
    "gn:feature_class":"P",
    "gn:feature_code":"PPL",
    "gn:name":"Datuo",
    "gn:population":0,
    "gn:timezone":"Asia/Shanghai",
    "iso:country":"CN",
    "name:zho_x_preferred":[
        "\u5927\u5768"
    ],
    "wof:name":"Datuo",
    "wof:placetype":"locality"
},
  "geometry": {"coordinates":[106.377,24.5957],"type":"Point"}
}