{
  "type": "Feature",
  "properties": {
    "gn:admin1_code":"29.0",
    "gn:asciiname":"Shaniu",
    "gn:country_code":"CN",
    "gn:dem":1616,
    "gn:feature_class":"P",
    "gn:feature_code":"PPL",
    "gn:name":"Shaniu",
    "gn:population":0,
    "gn:timezone":"Asia/Shanghai",
    "iso:country":"CN",
    "name:zho_x_preferred":[
        "\u6740\u725b"
    ],
    "wof:name":"Shaniu",
    "wof:placetype":"locality"
},
  "geometry": {"coordinates":[100.58199999999999,24.555],"type":"Point"}
}