{
  "type": "Feature",
  "properties": {
    "gn:admin1_code":"6.0",
    "gn:asciiname":"Tongmenda",
    "gn:country_code":"CN",
    "gn:dem":3876,
    "gn:feature_class":"P",
    "gn:feature_code":"PPL",
    "gn:name":"Tongmenda",
    "gn:population":0,
    "gn:timezone":"Asia/Urumqi",
    "iso:country":"CN",
    "name:zho_x_preferred":[
        "\u540c\u95e8\u8fbe"
    ],
    "wof:name":"Tongmenda",
    "wof:placetype":"locality"
},
  "geometry": {"coordinates":[96.98681000000001,33.15298],"type":"Point"}
}