{
  "type": "Feature",
  "properties": {
    "gn:admin1_code":"29.0",
    "gn:asciiname":"Leila",
    "gn:country_code":"CN",
    "gn:dem":1055,
    "gn:feature_class":"P",
    "gn:feature_code":"PPL",
    "gn:name":"Leila",
    "gn:population":0,
    "gn:timezone":"Asia/Shanghai",
    "iso:country":"CN",
    "name:ara_x_preferred":[
        "\u0644\u064a\u0644\u0649"
    ],
    "name:bre_x_preferred":[
        "Leila"
    ],
    "name:deu_x_preferred":[
        "Leila"
    ],
    "name:epo_x_preferred":[
        "Leila"
    ],
    "name:fas_x_preferred":[
        "\u0644\u06cc\u0644\u0627"
    ],
    "name:fra_x_preferred":[
        "Leila"
    ],
    "name:ita_x_preferred":[
        "Leila"
    ],
    "name:spa_x_preferred":[
        "Leila"
    ],
    "name:zho_x_preferred":[
        "\u96f7\u62c9"
    ],
    "wof:name":"Leila",
    "wof:placetype":"locality"
},
  "geometry": {"coordinates":[98.11620000000001,24.3054],"type":"Point"}
}