{
  "type": "Feature",
  "properties": {
    "gn:admin1_code":"20.0",
    "gn:asciiname":"Shanghamao Bulang",
    "gn:country_code":"CN",
    "gn:dem":1587,
    "gn:feature_class":"P",
    "gn:feature_code":"PPL",
    "gn:name":"Shanghamao Bulang",
    "gn:population":0,
    "gn:timezone":"Asia/Shanghai",
    "iso:country":"CN",
    "name:und_x_variant":[
        "\u4e0a\u54c8\u6bdb\u4e0d\u6d6a"
    ],
    "wof:name":"Shanghamao Bulang",
    "wof:placetype":"locality"
},
  "geometry": {"coordinates":[113.19398,41.22283],"type":"Point"}
}