{
  "type": "Feature",
  "properties": {
    "gn:admin1_code":"24.0",
    "gn:asciiname":"Niangnianghui",
    "gn:country_code":"CN",
    "gn:dem":1601,
    "gn:feature_class":"P",
    "gn:feature_code":"PPL",
    "gn:name":"Niangnianghui",
    "gn:population":0,
    "gn:timezone":"Asia/Shanghai",
    "iso:country":"CN",
    "name:und_x_variant":[
        "\u5a18\u5a18\u4f1a"
    ],
    "name:zho_x_preferred":[
        "\u5a18\u5a18\u4f1a"
    ],
    "wof:name":"Niangnianghui",
    "wof:placetype":"locality"
},
  "geometry": {"coordinates":[113.42874999999999,39.06591],"type":"Point"}
}