{
  "type": "Feature",
  "properties": {
    "gn:admin1_code":"13",
    "gn:asciiname":"Keqikeke Shilake",
    "gn:country_code":"CN",
    "gn:dem":2596,
    "gn:feature_class":"P",
    "gn:feature_code":"PPL",
    "gn:name":"Keqikeke Shilake",
    "gn:population":0,
    "gn:timezone":"Asia/Urumqi",
    "iso:country":"CN",
    "name:und_x_variant":[
        "\u514b\u5176\u514b\u514b\u4ec0\u62c9\u514b"
    ],
    "wof:name":"Keqikeke Shilake",
    "wof:placetype":"locality"
},
  "geometry": {"coordinates":[89.79236999999998,43.29405],"type":"Point"}
}