{
  "type": "Feature",
  "properties": {
    "gn:admin1_code":"29.0",
    "gn:asciiname":"Dongwu",
    "gn:country_code":"CN",
    "gn:dem":1851,
    "gn:feature_class":"P",
    "gn:feature_code":"PPL",
    "gn:name":"Dongwu",
    "gn:population":0,
    "gn:timezone":"Asia/Shanghai",
    "iso:country":"CN",
    "name:zho_x_preferred":[
        "\u4e1c\u52a1"
    ],
    "wof:name":"Dongwu",
    "wof:placetype":"locality"
},
  "geometry": {"coordinates":[99.6934,22.7347],"type":"Point"}
}