{
  "type": "Feature",
  "properties": {
    "gn:admin1_code":"11.0",
    "gn:asciiname":"Baifenzui",
    "gn:country_code":"CN",
    "gn:dem":34,
    "gn:feature_class":"P",
    "gn:feature_code":"PPL",
    "gn:name":"Baifenzui",
    "gn:population":0,
    "gn:timezone":"Asia/Shanghai",
    "iso:country":"CN",
    "name:zho_x_preferred":[
        "\u767d\u7c89\u5480"
    ],
    "wof:name":"Baifenzui",
    "wof:placetype":"locality"
},
  "geometry": {"coordinates":[112.21147000000001,29.48511],"type":"Point"}
}