{
  "type": "Feature",
  "properties": {
    "gn:admin1_code":"30.0",
    "gn:asciiname":"Dongtou Dacun",
    "gn:country_code":"CN",
    "gn:dem":0,
    "gn:feature_class":"P",
    "gn:feature_code":"PPL",
    "gn:name":"Dongtou Dacun",
    "gn:population":0,
    "gn:timezone":"Asia/Shanghai",
    "iso:country":"CN",
    "name:zho_x_preferred":[
        "\u4e1c\u5934\u5927\u6751"
    ],
    "wof:name":"Dongtou Dacun",
    "wof:placetype":"locality"
},
  "geometry": {"coordinates":[112.60825,21.82704],"type":"Point"}
}