{
  "type": "Feature",
  "properties": {
    "gn:admin1_code":"6.0",
    "gn:asciiname":"Jiangji",
    "gn:country_code":"CN",
    "gn:dem":3769,
    "gn:feature_class":"P",
    "gn:feature_code":"PPL",
    "gn:name":"Jiangji",
    "gn:population":0,
    "gn:timezone":"Asia/Urumqi",
    "iso:country":"CN",
    "name:zho_x_preferred":[
        "\u6c5f\u7ed9"
    ],
    "wof:name":"Jiangji",
    "wof:placetype":"locality"
},
  "geometry": {"coordinates":[96.58772,31.75832],"type":"Point"}
}