{
  "type": "Feature",
  "properties": {
    "gn:admin1_code":"18.0",
    "gn:asciiname":"Jiangchong",
    "gn:country_code":"CN",
    "gn:dem":457,
    "gn:feature_class":"P",
    "gn:feature_code":"PPL",
    "gn:name":"Jiangchong",
    "gn:population":0,
    "gn:timezone":"Asia/Shanghai",
    "iso:country":"CN",
    "name:zho_x_preferred":[
        "\u6c5f\u51b2"
    ],
    "wof:name":"Jiangchong",
    "wof:placetype":"locality"
},
  "geometry": {"coordinates":[108.33499999999999,26.0738],"type":"Point"}
}