{
  "type": "Feature",
  "properties": {
    "gn:admin1_code":"2.0",
    "gn:asciiname":"Liliaoshan",
    "gn:country_code":"CN",
    "gn:dem":218,
    "gn:feature_class":"P",
    "gn:feature_code":"PPL",
    "gn:name":"Liliaoshan",
    "gn:population":0,
    "gn:timezone":"Asia/Shanghai",
    "iso:country":"CN",
    "name:zho_x_preferred":[
        "\u91cc\u4e86\u5c71"
    ],
    "wof:name":"Liliaoshan",
    "wof:placetype":"locality"
},
  "geometry": {"coordinates":[120.83936,29.40427],"type":"Point"}
}