{
  "type": "Feature",
  "properties": {
    "gn:admin1_code":"19.0",
    "gn:asciiname":"Luoshuizhai",
    "gn:country_code":"CN",
    "gn:dem":59,
    "gn:feature_class":"P",
    "gn:feature_code":"PPL",
    "gn:name":"Luoshuizhai",
    "gn:population":0,
    "gn:timezone":"Asia/Shanghai",
    "iso:country":"CN",
    "name:und_x_variant":[
        "\u6d1b\u6c34\u5be8"
    ],
    "wof:name":"Luoshuizhai",
    "wof:placetype":"locality"
},
  "geometry": {"coordinates":[122.59775,40.44483],"type":"Point"}
}