{
  "type": "Feature",
  "properties": {
    "gn:admin1_code":"33.0",
    "gn:asciiname":"Lianfeng",
    "gn:country_code":"CN",
    "gn:dem":436,
    "gn:feature_class":"P",
    "gn:feature_code":"PPL",
    "gn:name":"Lianfeng",
    "gn:population":0,
    "gn:timezone":"Asia/Shanghai",
    "iso:country":"CN",
    "name:zho_x_preferred":[
        "\u8054\u4e30"
    ],
    "wof:name":"Lianfeng",
    "wof:placetype":"locality"
},
  "geometry": {"coordinates":[108.0077,30.59633],"type":"Point"}
}