{
  "type": "Feature",
  "properties": {
    "gn:admin1_code":"29.0",
    "gn:asciiname":"Hongbeng",
    "gn:country_code":"CN",
    "gn:dem":970,
    "gn:feature_class":"P",
    "gn:feature_code":"PPL",
    "gn:name":"Hongbeng",
    "gn:population":0,
    "gn:timezone":"Asia/Shanghai",
    "iso:country":"CN",
    "name:zho_x_preferred":[
        "\u7ea2\u868c"
    ],
    "wof:name":"Hongbeng",
    "wof:placetype":"locality"
},
  "geometry": {"coordinates":[104.30800000000001,24.5943],"type":"Point"}
}