{
  "type": "Feature",
  "properties": {
    "gn:admin1_code":"3.0",
    "gn:asciiname":"Sijiaotang",
    "gn:country_code":"CN",
    "gn:dem":157,
    "gn:feature_class":"P",
    "gn:feature_code":"PPL",
    "gn:name":"Sijiaotang",
    "gn:population":0,
    "gn:timezone":"Asia/Shanghai",
    "iso:country":"CN",
    "name:und_x_variant":[
        "\u56db\u6559\u5802"
    ],
    "wof:name":"Sijiaotang",
    "wof:placetype":"locality"
},
  "geometry": {"coordinates":[114.08620999999999,28.96532],"type":"Point"}
}