{
  "type": "Feature",
  "properties": {
    "gn:admin1_code":"32.0",
    "gn:asciiname":"Tingduo",
    "gn:country_code":"CN",
    "gn:dem":3469,
    "gn:feature_class":"P",
    "gn:feature_code":"PPL",
    "gn:name":"Tingduo",
    "gn:population":0,
    "gn:timezone":"Asia/Shanghai",
    "iso:country":"CN",
    "name:zho_x_preferred":[
        "\u4ead\u591a"
    ],
    "wof:name":"Tingduo",
    "wof:placetype":"locality"
},
  "geometry": {"coordinates":[101.17100000000001,28.5294],"type":"Point"}
}