{
  "type": "Feature",
  "properties": {
    "gn:admin1_code":"19",
    "gn:asciiname":"Luyang",
    "gn:country_code":"CN",
    "gn:dem":16,
    "gn:elevation":"0.0",
    "gn:feature_class":"P",
    "gn:feature_code":"PPLA4",
    "gn:name":"L\u00fcyang",
    "gn:population":0,
    "gn:timezone":"Asia/Shanghai",
    "iso:country":"CN",
    "name:und_x_variant":[
        "Yen-yang-tse",
        "L\u00fcyangyi",
        "L\u00fc-yang-i",
        "L\u00fcyang"
    ],
    "name:zho_x_preferred":[
        "\u95fe\u9633"
    ],
    "name:zho_x_variant":[
        "L\u00fcyang Zhen",
        "\u95fe\u9633\u9547"
    ],
    "wof:name":"Luyang",
    "wof:placetype":"locality"
},
  "geometry": {"coordinates":[121.66632,41.38193],"type":"Point"}
}