{
  "type": "Feature",
  "properties": {
    "gn:admin1_code":"3.0",
    "gn:asciiname":"Pingbeinao",
    "gn:country_code":"CN",
    "gn:dem":335,
    "gn:feature_class":"P",
    "gn:feature_code":"PPL",
    "gn:name":"Pingbeinao",
    "gn:population":0,
    "gn:timezone":"Asia/Shanghai",
    "iso:country":"CN",
    "name:und_x_variant":[
        "\u576a\u80cc\u8111"
    ],
    "wof:name":"Pingbeinao",
    "wof:placetype":"locality"
},
  "geometry": {"coordinates":[115.81738,26.27053],"type":"Point"}
}