{
  "type": "Feature",
  "properties": {
    "gn:admin1_code":"08",
    "gn:asciiname":"Changjiatun",
    "gn:cc2":"CN",
    "gn:country_code":"CN",
    "gn:dem":87,
    "gn:feature_class":"P",
    "gn:feature_code":"PPL",
    "gn:name":"Changjiatun",
    "gn:population":0,
    "gn:timezone":"Asia/Shanghai",
    "iso:country":"CN",
    "name:und_x_variant":[
        "Ch\u2019ang-chia-t\u2019un",
        "Changjiatun"
    ],
    "wof:name":"Changjiatun",
    "wof:placetype":"locality"
},
  "geometry": {"coordinates":[129.53333000000001,49.41667],"type":"Point"}
}