{
  "type": "Feature",
  "properties": {
    "gn:admin1_code":"32.0",
    "gn:asciiname":"Gudu",
    "gn:country_code":"CN",
    "gn:dem":2712,
    "gn:feature_class":"P",
    "gn:feature_code":"PPL",
    "gn:name":"Gudu",
    "gn:population":0,
    "gn:timezone":"Asia/Shanghai",
    "iso:country":"CN",
    "name:zho_x_preferred":[
        "\u53e4\u90fd"
    ],
    "wof:name":"Gudu",
    "wof:placetype":"locality"
},
  "geometry": {"coordinates":[100.952,28.1079],"type":"Point"}
}