{
  "type": "Feature",
  "properties": {
    "gn:admin1_code":"10.0",
    "gn:asciiname":"Pingshitou",
    "gn:country_code":"CN",
    "gn:dem":781,
    "gn:feature_class":"P",
    "gn:feature_code":"PPL",
    "gn:name":"Pingshitou",
    "gn:population":0,
    "gn:timezone":"Asia/Shanghai",
    "iso:country":"CN",
    "name:zho_x_preferred":[
        "\u5e73\u77f3\u5934"
    ],
    "wof:name":"Pingshitou",
    "wof:placetype":"locality"
},
  "geometry": {"coordinates":[113.8972,38.91176],"type":"Point"}
}