{
  "type": "Feature",
  "properties": {
    "gn:admin1_code":"11.0",
    "gn:asciiname":"Xiaotangpu",
    "gn:country_code":"CN",
    "gn:dem":284,
    "gn:feature_class":"P",
    "gn:feature_code":"PPL",
    "gn:name":"Xiaotangpu",
    "gn:population":0,
    "gn:timezone":"Asia/Shanghai",
    "iso:country":"CN",
    "name:zho_x_preferred":[
        "\u6653\u5858\u94fa"
    ],
    "wof:name":"Xiaotangpu",
    "wof:placetype":"locality"
},
  "geometry": {"coordinates":[111.93179000000001,25.90036],"type":"Point"}
}