{
  "type": "Feature",
  "properties": {
    "gn:admin1_code":"12.0",
    "gn:asciiname":"Lujiadun",
    "gn:country_code":"CN",
    "gn:dem":28,
    "gn:feature_class":"P",
    "gn:feature_code":"PPL",
    "gn:name":"Lujiadun",
    "gn:population":0,
    "gn:timezone":"Asia/Shanghai",
    "iso:country":"CN",
    "name:zho_x_preferred":[
        "\u9c81\u5bb6\u58a9"
    ],
    "wof:name":"Lujiadun",
    "wof:placetype":"locality"
},
  "geometry": {"coordinates":[113.81389,29.97381],"type":"Point"}
}