{
  "type": "Feature",
  "properties": {
    "gn:admin1_code":"19.0",
    "gn:asciiname":"Dongsandaogoucun",
    "gn:country_code":"CN",
    "gn:dem":373,
    "gn:feature_class":"P",
    "gn:feature_code":"PPL",
    "gn:name":"Dongsandaogoucun",
    "gn:population":0,
    "gn:timezone":"Asia/Shanghai",
    "iso:country":"CN",
    "name:zho_x_preferred":[
        "\u4e1c\u4e09\u9053\u6c9f\u6751"
    ],
    "wof:name":"Dongsandaogoucun",
    "wof:placetype":"locality"
},
  "geometry": {"coordinates":[122.797,40.2805],"type":"Point"}
}