{
  "type": "Feature",
  "properties": {
    "gn:admin1_code":"07",
    "gn:asciiname":"Chexu",
    "gn:country_code":"CN",
    "gn:dem":80,
    "gn:feature_class":"P",
    "gn:feature_code":"PPL",
    "gn:name":"Chexu",
    "gn:population":0,
    "gn:timezone":"Asia/Shanghai",
    "iso:country":"CN",
    "name:und_x_variant":[
        "Ch\u2019e-hs\u00fc",
        "Chexu"
    ],
    "name:zho_x_preferred":[
        "\u8f66\u5729"
    ],
    "wof:name":"Chexu",
    "wof:placetype":"locality"
},
  "geometry": {"coordinates":[117.21305,24.04202],"type":"Point"}
}