{
  "type": "Feature",
  "properties": {
    "gn:admin1_code":"29.0",
    "gn:asciiname":"Dajiuzu",
    "gn:country_code":"CN",
    "gn:dem":2478,
    "gn:feature_class":"P",
    "gn:feature_code":"PPL",
    "gn:name":"Dajiuzu",
    "gn:population":0,
    "gn:timezone":"Asia/Shanghai",
    "iso:country":"CN",
    "name:zho_x_preferred":[
        "\u5927\u65e7\u7956"
    ],
    "wof:name":"Dajiuzu",
    "wof:placetype":"locality"
},
  "geometry": {"coordinates":[99.54130000000001,25.8963],"type":"Point"}
}