{
  "type": "Feature",
  "properties": {
    "gn:admin1_code":"14.0",
    "gn:asciiname":"Xiare",
    "gn:country_code":"CN",
    "gn:dem":4633,
    "gn:feature_class":"P",
    "gn:feature_code":"PPL",
    "gn:name":"Xiare",
    "gn:population":0,
    "gn:timezone":"Asia/Urumqi",
    "iso:country":"CN",
    "name:zho_x_preferred":[
        "\u5413\u70ed"
    ],
    "wof:name":"Xiare",
    "wof:placetype":"locality"
},
  "geometry": {"coordinates":[88.2758,28.9543],"type":"Point"}
}