{
  "type": "Feature",
  "properties": {
    "gn:admin1_code":"25",
    "gn:asciiname":"Houpu",
    "gn:country_code":"CN",
    "gn:dem":33,
    "gn:feature_class":"P",
    "gn:feature_code":"PPL",
    "gn:name":"Houpu",
    "gn:population":0,
    "gn:timezone":"Asia/Shanghai",
    "iso:country":"CN",
    "name:zho_x_preferred":[
        "\u540e\u94fa"
    ],
    "wof:name":"Houpu",
    "wof:placetype":"locality"
},
  "geometry": {"coordinates":[116.09399999999999,36.5054],"type":"Point"}
}