{
  "type": "Feature",
  "properties": {
    "gn:admin1_code":"18",
    "gn:asciiname":"Shilunzi",
    "gn:country_code":"CN",
    "gn:dem":745,
    "gn:feature_class":"P",
    "gn:feature_code":"PPL",
    "gn:name":"Shilunzi",
    "gn:population":0,
    "gn:timezone":"Asia/Shanghai",
    "iso:country":"CN",
    "name:zho_x_preferred":[
        "\u77f3\u8f6e\u5b50"
    ],
    "wof:name":"Shilunzi",
    "wof:placetype":"locality"
},
  "geometry": {"coordinates":[107.17100000000001,28.3719],"type":"Point"}
}