{
  "type": "Feature",
  "properties": {
    "gn:admin1_code":"14.0",
    "gn:asciiname":"Lamuxue",
    "gn:country_code":"CN",
    "gn:dem":3805,
    "gn:feature_class":"P",
    "gn:feature_code":"PPL",
    "gn:name":"Lamuxue",
    "gn:population":0,
    "gn:timezone":"Asia/Urumqi",
    "iso:country":"CN",
    "name:zho_x_preferred":[
        "\u62c9\u6728\u859b"
    ],
    "wof:name":"Lamuxue",
    "wof:placetype":"locality"
},
  "geometry": {"coordinates":[92.51642,28.97652],"type":"Point"}
}