{
  "type": "Feature",
  "properties": {
    "gn:admin1_code":"18",
    "gn:asciiname":"Yanbengkou",
    "gn:country_code":"CN",
    "gn:dem":781,
    "gn:feature_class":"P",
    "gn:feature_code":"PPL",
    "gn:name":"Yanbengkou",
    "gn:population":0,
    "gn:timezone":"Asia/Shanghai",
    "iso:country":"CN",
    "name:zho_x_preferred":[
        "\u5ca9\u5d29\u53e3"
    ],
    "wof:name":"Yanbengkou",
    "wof:placetype":"locality"
},
  "geometry": {"coordinates":[105.65000000000001,28.3365],"type":"Point"}
}