{
  "type": "Feature",
  "properties": {
    "gn:admin1_code":"16.0",
    "gn:asciiname":"Wansheng",
    "gn:country_code":"CN",
    "gn:dem":461,
    "gn:feature_class":"P",
    "gn:feature_code":"PPL",
    "gn:name":"Wansheng",
    "gn:population":0,
    "gn:timezone":"Asia/Shanghai",
    "iso:country":"CN",
    "name:zho_x_preferred":[
        "\u4e07\u76db"
    ],
    "wof:name":"Wansheng",
    "wof:placetype":"locality"
},
  "geometry": {"coordinates":[107.11199999999999,23.1774],"type":"Point"}
}