{
  "type": "Feature",
  "properties": {
    "gn:admin1_code":"11.0",
    "gn:asciiname":"Qizhuhe",
    "gn:country_code":"CN",
    "gn:dem":395,
    "gn:feature_class":"P",
    "gn:feature_code":"PPL",
    "gn:name":"Qizhuhe",
    "gn:population":0,
    "gn:timezone":"Asia/Shanghai",
    "iso:country":"CN",
    "name:zho_x_preferred":[
        "\u6f06\u7af9\u6cb3"
    ],
    "wof:name":"Qizhuhe",
    "wof:placetype":"locality"
},
  "geometry": {"coordinates":[109.70531,29.12991],"type":"Point"}
}