{
  "type": "Feature",
  "properties": {
    "gn:admin1_code":"02",
    "gn:asciiname":"Jiepaitoucun",
    "gn:country_code":"CN",
    "gn:dem":7,
    "gn:feature_class":"P",
    "gn:feature_code":"PPL",
    "gn:name":"Jiepaitoucun",
    "gn:population":0,
    "gn:timezone":"Asia/Shanghai",
    "iso:country":"CN",
    "name:und_x_variant":[
        "Chieh-p\u2019ai-t\u2019ou-shih",
        "Jiepaitou",
        "Jiepaitoucun"
    ],
    "name:zho_x_preferred":[
        "\u754c\u724c\u5934"
    ],
    "name:zho_x_variant":[
        "\u754c\u724c\u5934\u6751"
    ],
    "wof:name":"Jiepaitoucun",
    "wof:placetype":"locality"
},
  "geometry": {"coordinates":[121.41937,28.6446],"type":"Point"}
}