{
  "type": "Feature",
  "properties": {
    "gn:admin1_code":"26.0",
    "gn:asciiname":"Zuofangwan",
    "gn:country_code":"CN",
    "gn:dem":1179,
    "gn:feature_class":"P",
    "gn:feature_code":"PPL",
    "gn:name":"Zuofangwan",
    "gn:population":0,
    "gn:timezone":"Asia/Shanghai",
    "iso:country":"CN",
    "name:zho_x_preferred":[
        "\u4f5c\u574a\u6e7e"
    ],
    "wof:name":"Zuofangwan",
    "wof:placetype":"locality"
},
  "geometry": {"coordinates":[108.0943,32.5636],"type":"Point"}
}