{
  "type": "Feature",
  "properties": {
    "gn:admin1_code":"10.0",
    "gn:asciiname":"Shiyaogou",
    "gn:country_code":"CN",
    "gn:dem":678,
    "gn:feature_class":"P",
    "gn:feature_code":"PPL",
    "gn:name":"Shiyaogou",
    "gn:population":0,
    "gn:timezone":"Asia/Shanghai",
    "iso:country":"CN",
    "name:zho_x_preferred":[
        "\u77f3\u7a91\u6c9f"
    ],
    "wof:name":"Shiyaogou",
    "wof:placetype":"locality"
},
  "geometry": {"coordinates":[114.18925,39.00315],"type":"Point"}
}