{
  "type": "Feature",
  "properties": {
    "gn:admin1_code":"33.0",
    "gn:asciiname":"Tuya",
    "gn:country_code":"CN",
    "gn:dem":525,
    "gn:feature_class":"P",
    "gn:feature_code":"PPL",
    "gn:name":"Tuya",
    "gn:population":0,
    "gn:timezone":"Asia/Shanghai",
    "iso:country":"CN",
    "name:deu_x_preferred":[
        "Tafelvulkan"
    ],
    "name:fra_x_preferred":[
        "Tuya"
    ],
    "name:ind_x_preferred":[
        "Tuya"
    ],
    "name:isl_x_preferred":[
        "Stapi"
    ],
    "name:ita_x_preferred":[
        "Tuya"
    ],
    "name:por_x_preferred":[
        "Tuya"
    ],
    "name:spa_x_preferred":[
        "Tuya"
    ],
    "name:ukr_x_preferred":[
        "\u0422\u0443\u0439\u044f"
    ],
    "name:zho_x_preferred":[
        "\u571f\u57ad"
    ],
    "wof:name":"Tuya",
    "wof:placetype":"locality"
},
  "geometry": {"coordinates":[108.17121000000002,30.5367],"type":"Point"}
}