{
  "type": "Feature",
  "properties": {
    "gn:admin1_code":"25.0",
    "gn:asciiname":"Huanggoucun",
    "gn:country_code":"CN",
    "gn:dem":97,
    "gn:feature_class":"P",
    "gn:feature_code":"PPL",
    "gn:name":"Huanggoucun",
    "gn:population":0,
    "gn:timezone":"Asia/Shanghai",
    "iso:country":"CN",
    "name:zho_x_preferred":[
        "\u9ec4\u6c9f\u6751"
    ],
    "wof:name":"Huanggoucun",
    "wof:placetype":"locality"
},
  "geometry": {"coordinates":[119.46728,35.93035],"type":"Point"}
}