{
  "type": "Feature",
  "properties": {
    "gn:admin1_code":"3.0",
    "gn:asciiname":"Yingjia",
    "gn:country_code":"CN",
    "gn:dem":74,
    "gn:feature_class":"P",
    "gn:feature_code":"PPL",
    "gn:name":"Yingjia",
    "gn:population":0,
    "gn:timezone":"Asia/Shanghai",
    "iso:country":"CN",
    "name:zho_x_preferred":[
        "\u5e94\u5bb6"
    ],
    "wof:name":"Yingjia",
    "wof:placetype":"locality"
},
  "geometry": {"coordinates":[117.47939,28.65776],"type":"Point"}
}