{
  "type": "Feature",
  "properties": {
    "gn:admin1_code":"19.0",
    "gn:asciiname":"Mamahuoluo",
    "gn:country_code":"CN",
    "gn:dem":390,
    "gn:feature_class":"P",
    "gn:feature_code":"PPL",
    "gn:name":"Mamahuoluo",
    "gn:population":0,
    "gn:timezone":"Asia/Shanghai",
    "iso:country":"CN",
    "name:und_x_variant":[
        "\u5988\u5988\u4f19\u6d1b"
    ],
    "name:zho_x_preferred":[
        "\u5988\u5988\u4f19\u6d1b"
    ],
    "wof:name":"Mamahuoluo",
    "wof:placetype":"locality"
},
  "geometry": {"coordinates":[125.09314000000001,41.67903],"type":"Point"}
}