{
  "type": "Feature",
  "properties": {
    "gn:admin1_code":"29.0",
    "gn:asciiname":"Shuinitang",
    "gn:country_code":"CN",
    "gn:dem":1029,
    "gn:feature_class":"P",
    "gn:feature_code":"PPL",
    "gn:name":"Shuinitang",
    "gn:population":0,
    "gn:timezone":"Asia/Shanghai",
    "iso:country":"CN",
    "name:zho_x_preferred":[
        "\u6c34\u6ce5\u5858"
    ],
    "wof:name":"Shuinitang",
    "wof:placetype":"locality"
},
  "geometry": {"coordinates":[105.015,27.9547],"type":"Point"}
}