{
  "type": "Feature",
  "properties": {
    "gn:admin1_code":"02",
    "gn:asciiname":"Shulangcun",
    "gn:country_code":"CN",
    "gn:dem":-9999,
    "gn:feature_class":"P",
    "gn:feature_code":"PPL",
    "gn:name":"Shulangcun",
    "gn:population":0,
    "gn:timezone":"Asia/Shanghai",
    "iso:country":"CN",
    "name:und_x_variant":[
        "Shu-lang-hu",
        "Shulang",
        "\u9f20\u6d6a",
        "Shulangcun"
    ],
    "name:zho_x_preferred":[
        "\u9f20\u6d6a\u6751"
    ],
    "wof:name":"Shulangcun",
    "wof:placetype":"locality"
},
  "geometry": {"coordinates":[122.46878,30.4253],"type":"Point"}
}