{
  "type": "Feature",
  "properties": {
    "gn:admin1_code":"13",
    "gn:asciiname":"Kexisare Bulake",
    "gn:country_code":"CN",
    "gn:dem":1389,
    "gn:feature_class":"P",
    "gn:feature_code":"PPL",
    "gn:name":"Kexisare Bulake",
    "gn:population":0,
    "gn:timezone":"Asia/Urumqi",
    "iso:country":"CN",
    "name:und_x_variant":[
        "\u514b\u5e0c\u8428\u70ed\u5e03\u62c9\u514b"
    ],
    "wof:name":"Kexisare Bulake",
    "wof:placetype":"locality"
},
  "geometry": {"coordinates":[91.79536,44.58447],"type":"Point"}
}