{
  "type": "Feature",
  "properties": {
    "gn:admin1_code":"4.0",
    "gn:asciiname":"Xigongqi",
    "gn:country_code":"CN",
    "gn:dem":17,
    "gn:feature_class":"P",
    "gn:feature_code":"PPL",
    "gn:name":"Xigongqi",
    "gn:population":0,
    "gn:timezone":"Asia/Shanghai",
    "iso:country":"CN",
    "name:zho_x_preferred":[
        "\u897f\u62f1\u9f50"
    ],
    "wof:name":"Xigongqi",
    "wof:placetype":"locality"
},
  "geometry": {"coordinates":[119.13551,35.01314],"type":"Point"}
}