{
  "type": "Feature",
  "properties": {
    "gn:admin1_code":"3",
    "gn:asciiname":"Yangjiadong",
    "gn:country_code":"CN",
    "gn:dem":475,
    "gn:feature_class":"P",
    "gn:feature_code":"PPL",
    "gn:name":"Yangjiadong",
    "gn:population":0,
    "gn:timezone":"Asia/Shanghai",
    "iso:country":"CN",
    "name:zho_x_preferred":[
        "\u6d0b\u5bb6\u6d1e"
    ],
    "wof:name":"Yangjiadong",
    "wof:placetype":"locality"
},
  "geometry": {"coordinates":[114.715,26.2633],"type":"Point"}
}