{
  "type": "Feature",
  "properties": {
    "gn:admin1_code":"19.0",
    "gn:asciiname":"Guanjiabu",
    "gn:country_code":"CN",
    "gn:dem":66,
    "gn:feature_class":"P",
    "gn:feature_code":"PPL",
    "gn:name":"Guanjiabu",
    "gn:population":0,
    "gn:timezone":"Asia/Shanghai",
    "iso:country":"CN",
    "name:und_x_variant":[
        "Guanjiabao",
        "\u5173\u5bb6\u5821",
        "Guanjiabu"
    ],
    "name:zho_x_preferred":[
        "\u5173\u5bb6\u5821"
    ],
    "wof:name":"Guanjiabu",
    "wof:placetype":"locality"
},
  "geometry": {"coordinates":[123.30867000000001,40.2277],"type":"Point"}
}