{
  "type": "Feature",
  "properties": {
    "gn:admin1_code":"8.0",
    "gn:asciiname":"Shanquancun",
    "gn:country_code":"CN",
    "gn:dem":214,
    "gn:feature_class":"P",
    "gn:feature_code":"PPL",
    "gn:name":"Shanquancun",
    "gn:population":0,
    "gn:timezone":"Asia/Shanghai",
    "iso:country":"CN",
    "name:zho_x_preferred":[
        "\u5c71\u6cc9\u6751"
    ],
    "wof:name":"Shanquancun",
    "wof:placetype":"locality"
},
  "geometry": {"coordinates":[131.71265,46.0356],"type":"Point"}
}