{
  "type": "Feature",
  "properties": {
    "gn:admin1_code":"16.0",
    "gn:asciiname":"Lingqiang",
    "gn:country_code":"CN",
    "gn:dem":863,
    "gn:feature_class":"P",
    "gn:feature_code":"PPL",
    "gn:name":"Lingqiang",
    "gn:population":0,
    "gn:timezone":"Asia/Shanghai",
    "iso:country":"CN",
    "name:zho_x_preferred":[
        "\u51cc\u5f3a"
    ],
    "wof:name":"Lingqiang",
    "wof:placetype":"locality"
},
  "geometry": {"coordinates":[106.184,23.3046],"type":"Point"}
}