{
  "type": "Feature",
  "properties": {
    "gn:admin1_code":"9.0",
    "gn:asciiname":"Nanhongqiao",
    "gn:country_code":"CN",
    "gn:dem":101,
    "gn:feature_class":"P",
    "gn:feature_code":"PPL",
    "gn:name":"Nanhongqiao",
    "gn:population":0,
    "gn:timezone":"Asia/Shanghai",
    "iso:country":"CN",
    "name:zho_x_preferred":[
        "\u5357\u8679\u6865"
    ],
    "wof:name":"Nanhongqiao",
    "wof:placetype":"locality"
},
  "geometry": {"coordinates":[113.26907,35.0444],"type":"Point"}
}