{
  "type": "Feature",
  "properties": {
    "gn:admin1_code":"4.0",
    "gn:asciiname":"Zhouhuo",
    "gn:country_code":"CN",
    "gn:dem":1,
    "gn:feature_class":"P",
    "gn:feature_code":"PPL",
    "gn:name":"Zhouhuo",
    "gn:population":0,
    "gn:timezone":"Asia/Shanghai",
    "iso:country":"CN",
    "name:zho_x_preferred":[
        "Zhouhuo"
    ],
    "name:zho_x_variant":[
        "\u5468\u4f19"
    ],
    "wof:name":"Zhouhuo",
    "wof:placetype":"locality"
},
  "geometry": {"coordinates":[119.92783,33.34978],"type":"Point"}
}