{
  "type": "Feature",
  "properties": {
    "gn:admin1_code":"10",
    "gn:asciiname":"Liqilong",
    "gn:country_code":"CN",
    "gn:dem":1313,
    "gn:feature_class":"P",
    "gn:feature_code":"PPL",
    "gn:name":"Liqilong",
    "gn:population":0,
    "gn:timezone":"Asia/Shanghai",
    "iso:country":"CN",
    "name:zho_x_preferred":[
        "\u674e\u8d77\u9f99"
    ],
    "wof:name":"Liqilong",
    "wof:placetype":"locality"
},
  "geometry": {"coordinates":[116.35637,41.60618],"type":"Point"}
}