{
  "type": "Feature",
  "properties": {
    "gn:admin1_code":"19.0",
    "gn:asciiname":"Yejia Wopeng",
    "gn:country_code":"CN",
    "gn:dem":46,
    "gn:feature_class":"P",
    "gn:feature_code":"PPL",
    "gn:name":"Yejia Wopeng",
    "gn:population":0,
    "gn:timezone":"Asia/Shanghai",
    "iso:country":"CN",
    "name:zho_x_preferred":[
        "\u53f6\u5bb6\u7a9d\u68da"
    ],
    "wof:name":"Yejia Wopeng",
    "wof:placetype":"locality"
},
  "geometry": {"coordinates":[120.2146,40.27352],"type":"Point"}
}