{
  "type": "Feature",
  "properties": {
    "gn:admin1_code":"32.0",
    "gn:asciiname":"Linpinglie",
    "gn:country_code":"CN",
    "gn:dem":3765,
    "gn:feature_class":"P",
    "gn:feature_code":"PPL",
    "gn:name":"Linpinglie",
    "gn:population":0,
    "gn:timezone":"Asia/Shanghai",
    "iso:country":"CN",
    "name:zho_x_preferred":[
        "\u6797\u5e73\u5217"
    ],
    "wof:name":"Linpinglie",
    "wof:placetype":"locality"
},
  "geometry": {"coordinates":[101.217,28.0828],"type":"Point"}
}