{
  "type": "Feature",
  "properties": {
    "gn:admin1_code":"19.0",
    "gn:asciiname":"Bajiazi",
    "gn:country_code":"CN",
    "gn:dem":46,
    "gn:feature_class":"P",
    "gn:feature_code":"PPL",
    "gn:name":"Bajiazi",
    "gn:population":0,
    "gn:timezone":"Asia/Shanghai",
    "iso:country":"CN",
    "name:und_x_variant":[
        "\u516b\u5bb6\u5b50"
    ],
    "name:zho_x_preferred":[
        "\u516b\u5bb6\u5b50"
    ],
    "wof:name":"Bajiazi",
    "wof:placetype":"locality"
},
  "geometry": {"coordinates":[123.36972,41.87256],"type":"Point"}
}