{
  "type": "Feature",
  "properties": {
    "gn:admin1_code":"30.0",
    "gn:asciiname":"Changpuzi",
    "gn:country_code":"CN",
    "gn:dem":104,
    "gn:feature_class":"P",
    "gn:feature_code":"PPL",
    "gn:name":"Changpuzi",
    "gn:population":0,
    "gn:timezone":"Asia/Shanghai",
    "iso:country":"CN",
    "name:zho_x_preferred":[
        "\u957f\u94fa\u5b50"
    ],
    "wof:name":"Changpuzi",
    "wof:placetype":"locality"
},
  "geometry": {"coordinates":[113.90205,24.29684],"type":"Point"}
}