{
  "type": "Feature",
  "properties": {
    "gn:admin1_code":"2.0",
    "gn:asciiname":"Shangxu",
    "gn:country_code":"CN",
    "gn:dem":196,
    "gn:feature_class":"P",
    "gn:feature_code":"PPL",
    "gn:name":"Shangxu",
    "gn:population":0,
    "gn:timezone":"Asia/Shanghai",
    "iso:country":"CN",
    "name:und_x_variant":[
        "\u4e0a\u8bb8"
    ],
    "name:zho_x_preferred":[
        "Shangxu"
    ],
    "wof:name":"Shangxu",
    "wof:placetype":"locality"
},
  "geometry": {"coordinates":[119.07856,30.17159],"type":"Point"}
}