{
  "type": "Feature",
  "properties": {
    "gn:admin1_code":"19.0",
    "gn:asciiname":"Tangfang",
    "gn:country_code":"CN",
    "gn:dem":23,
    "gn:feature_class":"P",
    "gn:feature_code":"PPL",
    "gn:name":"Tangfang",
    "gn:population":0,
    "gn:timezone":"Asia/Shanghai",
    "iso:country":"CN",
    "name:zho_x_preferred":[
        "\u7cd6\u623f"
    ],
    "wof:name":"Tangfang",
    "wof:placetype":"locality"
},
  "geometry": {"coordinates":[122.98699999999999,39.5166],"type":"Point"}
}