{
  "type": "Feature",
  "properties": {
    "gn:admin1_code":"3.0",
    "gn:asciiname":"Zhewei",
    "gn:country_code":"CN",
    "gn:dem":139,
    "gn:feature_class":"P",
    "gn:feature_code":"PPL",
    "gn:name":"Zhewei",
    "gn:population":0,
    "gn:timezone":"Asia/Shanghai",
    "iso:country":"CN",
    "name:und_x_variant":[
        "\u67d8\u5c3e"
    ],
    "wof:name":"Zhewei",
    "wof:placetype":"locality"
},
  "geometry": {"coordinates":[114.916,27.59304],"type":"Point"}
}