{
  "type": "Feature",
  "properties": {
    "gn:admin1_code":"30",
    "gn:asciiname":"Baishikuai",
    "gn:country_code":"CN",
    "gn:dem":252,
    "gn:feature_class":"P",
    "gn:feature_code":"PPL",
    "gn:name":"Baishikuai",
    "gn:population":0,
    "gn:timezone":"Asia/Shanghai",
    "iso:country":"CN",
    "name:zho_x_preferred":[
        "\u767d\u77f3\u5757"
    ],
    "wof:name":"Baishikuai",
    "wof:placetype":"locality"
},
  "geometry": {"coordinates":[116.80826,23.93465],"type":"Point"}
}