{
  "type": "Feature",
  "properties": {
    "gn:admin1_code":"29.0",
    "gn:asciiname":"Luosha",
    "gn:country_code":"CN",
    "gn:dem":1333,
    "gn:feature_class":"P",
    "gn:feature_code":"PPL",
    "gn:name":"Luosha",
    "gn:population":0,
    "gn:timezone":"Asia/Shanghai",
    "iso:country":"CN",
    "name:zho_x_preferred":[
        "\u502e\u6c99"
    ],
    "wof:name":"Luosha",
    "wof:placetype":"locality"
},
  "geometry": {"coordinates":[102.328,22.6501],"type":"Point"}
}