{
  "type": "Feature",
  "properties": {
    "gn:admin1_code":"10.0",
    "gn:asciiname":"Houcaozhuang",
    "gn:country_code":"CN",
    "gn:dem":9,
    "gn:feature_class":"P",
    "gn:feature_code":"PPL",
    "gn:name":"Houcaozhuang",
    "gn:population":0,
    "gn:timezone":"Asia/Shanghai",
    "iso:country":"CN",
    "name:zho_x_preferred":[
        "\u540e\u66f9\u5e84"
    ],
    "wof:name":"Houcaozhuang",
    "wof:placetype":"locality"
},
  "geometry": {"coordinates":[117.107,38.234],"type":"Point"}
}