{
  "type": "Feature",
  "properties": {
    "gn:admin1_code":"29.0",
    "gn:asciiname":"Weililuo",
    "gn:country_code":"CN",
    "gn:dem":2123,
    "gn:feature_class":"P",
    "gn:feature_code":"PPL",
    "gn:name":"Weililuo",
    "gn:population":0,
    "gn:timezone":"Asia/Shanghai",
    "iso:country":"CN",
    "name:zho_x_preferred":[
        "\u672a\u91cc\u843d"
    ],
    "wof:name":"Weililuo",
    "wof:placetype":"locality"
},
  "geometry": {"coordinates":[100.491,27.3487],"type":"Point"}
}