{
  "type": "Feature",
  "properties": {
    "gn:admin1_code":"26",
    "gn:asciiname":"Yongfeng",
    "gn:country_code":"CN",
    "gn:dem":1042,
    "gn:feature_class":"P",
    "gn:feature_code":"PPL",
    "gn:name":"Yongfeng",
    "gn:population":0,
    "gn:timezone":"Asia/Shanghai",
    "iso:country":"CN",
    "name:und_x_variant":[
        "\u6c38\u4e30"
    ],
    "name:zho_x_preferred":[
        "\u6c38\u4e30"
    ],
    "wof:name":"Yongfeng",
    "wof:placetype":"locality"
},
  "geometry": {"coordinates":[108.48528,34.83583],"type":"Point"}
}