{
  "type": "Feature",
  "properties": {
    "gn:admin1_code":"21",
    "gn:asciiname":"Huangduobu",
    "gn:country_code":"CN",
    "gn:dem":1565,
    "gn:feature_class":"P",
    "gn:feature_code":"PPLA4",
    "gn:name":"Huangduobu",
    "gn:population":0,
    "gn:timezone":"Asia/Shanghai",
    "iso:country":"CN",
    "name:und_x_variant":[
        "\u9ec4\u94ce\u5821",
        "Huangduobu Xiang",
        "\u9ec4\u94ce\u5821\u4e61"
    ],
    "wof:name":"Huangduobu",
    "wof:placetype":"locality"
},
  "geometry": {"coordinates":[106.06617,36.30678],"type":"Point"}
}