{
  "type": "Feature",
  "properties": {
    "gn:admin1_code":"29.0",
    "gn:asciiname":"Chewan",
    "gn:country_code":"CN",
    "gn:dem":2203,
    "gn:feature_class":"P",
    "gn:feature_code":"PPL",
    "gn:name":"Chewan",
    "gn:population":0,
    "gn:timezone":"Asia/Shanghai",
    "iso:country":"CN",
    "name:zho_x_preferred":[
        "\u8f66\u5b8c"
    ],
    "wof:name":"Chewan",
    "wof:placetype":"locality"
},
  "geometry": {"coordinates":[102.446,25.2045],"type":"Point"}
}