{
  "type": "Feature",
  "properties": {
    "gn:admin1_code":"2.0",
    "gn:asciiname":"Xijingwu",
    "gn:country_code":"CN",
    "gn:dem":209,
    "gn:feature_class":"P",
    "gn:feature_code":"PPL",
    "gn:name":"Xijingwu",
    "gn:population":0,
    "gn:timezone":"Asia/Shanghai",
    "iso:country":"CN",
    "name:zho_x_preferred":[
        "\u897f\u4eac\u575e"
    ],
    "wof:name":"Xijingwu",
    "wof:placetype":"locality"
},
  "geometry": {"coordinates":[119.20515,28.90061],"type":"Point"}
}