{
  "type": "Feature",
  "properties": {
    "gn:admin1_code":"24",
    "gn:asciiname":"Fengyi",
    "gn:cc2":"CN",
    "gn:country_code":"CN",
    "gn:dem":1000,
    "gn:feature_class":"P",
    "gn:feature_code":"PPL",
    "gn:name":"Fengyi",
    "gn:population":0,
    "gn:timezone":"Asia/Shanghai",
    "iso:country":"CN",
    "name:und_x_variant":[
        "Feng-i-chen",
        "Feng-i",
        "Fengyi"
    ],
    "wof:name":"Fengyi",
    "wof:placetype":"locality"
},
  "geometry": {"coordinates":[112.72056000000001,36.245],"type":"Point"}
}