{
  "type": "Feature",
  "properties": {
    "gn:admin1_code":"7.0",
    "gn:asciiname":"Mingyang",
    "gn:country_code":"CN",
    "gn:dem":961,
    "gn:feature_class":"P",
    "gn:feature_code":"PPL",
    "gn:name":"Mingyang",
    "gn:population":0,
    "gn:timezone":"Asia/Shanghai",
    "iso:country":"CN",
    "name:und_x_variant":[
        "\u660e\u6d0b"
    ],
    "name:zho_x_preferred":[
        "\u660e\u6d0b"
    ],
    "wof:name":"Mingyang",
    "wof:placetype":"locality"
},
  "geometry": {"coordinates":[118.42344,26.66987],"type":"Point"}
}