{
  "type": "Feature",
  "properties": {
    "gn:admin1_code":"18",
    "gn:asciiname":"Mianbu",
    "gn:country_code":"CN",
    "gn:dem":1366,
    "gn:feature_class":"P",
    "gn:feature_code":"PPL",
    "gn:name":"Mianbu",
    "gn:population":0,
    "gn:timezone":"Asia/Shanghai",
    "iso:country":"CN",
    "name:zho_x_preferred":[
        "\u514d\u8865"
    ],
    "wof:name":"Mianbu",
    "wof:placetype":"locality"
},
  "geometry": {"coordinates":[105.29900000000001,25.2636],"type":"Point"}
}