{
  "type": "Feature",
  "properties": {
    "gn:admin1_code":"19.0",
    "gn:asciiname":"Dongjia Buzi",
    "gn:country_code":"CN",
    "gn:dem":79,
    "gn:feature_class":"P",
    "gn:feature_code":"PPL",
    "gn:name":"Dongjia Buzi",
    "gn:population":0,
    "gn:timezone":"Asia/Shanghai",
    "iso:country":"CN",
    "name:und_x_variant":[
        "Dongjia Baozi",
        "\u8463\u5bb6\u5821\u5b50",
        "Dongjia Buzi"
    ],
    "name:zho_x_preferred":[
        "\u8463\u5bb6\u5821\u5b50"
    ],
    "wof:name":"Dongjia Buzi",
    "wof:placetype":"locality"
},
  "geometry": {"coordinates":[124.14874,40.41682],"type":"Point"}
}