{
  "type": "Feature",
  "properties": {
    "gn:admin1_code":"7.0",
    "gn:asciiname":"Wuxing",
    "gn:country_code":"CN",
    "gn:dem":372,
    "gn:feature_class":"P",
    "gn:feature_code":"PPL",
    "gn:name":"Wuxing",
    "gn:population":0,
    "gn:timezone":"Asia/Shanghai",
    "iso:country":"CN",
    "name:und_x_variant":[
        "\u4e94\u661f"
    ],
    "name:zho_x_preferred":[
        "\u4e94\u661f"
    ],
    "wof:name":"Wuxing",
    "wof:placetype":"locality"
},
  "geometry": {"coordinates":[116.43038,26.1721],"type":"Point"}
}