{
  "type": "Feature",
  "properties": {
    "gn:admin1_code":"9.0",
    "gn:asciiname":"Xiangtoumiao",
    "gn:country_code":"CN",
    "gn:dem":493,
    "gn:feature_class":"P",
    "gn:feature_code":"PPL",
    "gn:name":"Xiangtoumiao",
    "gn:population":0,
    "gn:timezone":"Asia/Shanghai",
    "iso:country":"CN",
    "name:zho_x_preferred":[
        "\u9999\u5934\u5e99"
    ],
    "wof:name":"Xiangtoumiao",
    "wof:placetype":"locality"
},
  "geometry": {"coordinates":[112.08364,35.00785],"type":"Point"}
}