{
  "type": "Feature",
  "properties": {
    "gn:admin1_code":"24",
    "gn:asciiname":"Shuinan",
    "gn:country_code":"CN",
    "gn:dem":1258,
    "gn:feature_class":"P",
    "gn:feature_code":"PPL",
    "gn:name":"Shuinan",
    "gn:population":0,
    "gn:timezone":"Asia/Shanghai",
    "iso:country":"CN",
    "wof:name":"Shuinan",
    "wof:placetype":"locality"
},
  "geometry": {"coordinates":[111.43333,36.46667],"type":"Point"}
}