{
  "type": "Feature",
  "properties": {
    "gn:admin1_code":"26.0",
    "gn:asciiname":"Gaofanggou",
    "gn:country_code":"CN",
    "gn:dem":1198,
    "gn:feature_class":"P",
    "gn:feature_code":"PPL",
    "gn:name":"Gaofanggou",
    "gn:population":0,
    "gn:timezone":"Asia/Shanghai",
    "iso:country":"CN",
    "name:zho_x_preferred":[
        "\u9ad8\u65b9\u6c9f"
    ],
    "wof:name":"Gaofanggou",
    "wof:placetype":"locality"
},
  "geometry": {"coordinates":[110.07051,38.20355],"type":"Point"}
}