{
  "type": "Feature",
  "properties": {
    "gn:admin1_code":"18.0",
    "gn:asciiname":"Kouwen",
    "gn:country_code":"CN",
    "gn:dem":711,
    "gn:feature_class":"P",
    "gn:feature_code":"PPL",
    "gn:name":"Kouwen",
    "gn:population":0,
    "gn:timezone":"Asia/Shanghai",
    "iso:country":"CN",
    "name:zho_x_preferred":[
        "\u6263\u6587"
    ],
    "wof:name":"Kouwen",
    "wof:placetype":"locality"
},
  "geometry": {"coordinates":[108.836,26.459],"type":"Point"}
}