{
  "type": "Feature",
  "properties": {
    "gn:admin1_code":"10.0",
    "gn:asciiname":"Caojiazhuang",
    "gn:country_code":"CN",
    "gn:dem":570,
    "gn:feature_class":"P",
    "gn:feature_code":"PPL",
    "gn:name":"Caojiazhuang",
    "gn:population":0,
    "gn:timezone":"Asia/Shanghai",
    "iso:country":"CN",
    "name:zho_x_preferred":[
        "\u66f9\u5bb6\u5e84"
    ],
    "wof:name":"Caojiazhuang",
    "wof:placetype":"locality"
},
  "geometry": {"coordinates":[113.89400000000001,38.48093],"type":"Point"}
}