{
  "type": "Feature",
  "properties": {
    "gn:admin1_code":"11.0",
    "gn:asciiname":"Kuangkou",
    "gn:country_code":"CN",
    "gn:dem":374,
    "gn:feature_class":"P",
    "gn:feature_code":"PPL",
    "gn:name":"Kuangkou",
    "gn:population":0,
    "gn:timezone":"Asia/Shanghai",
    "iso:country":"CN",
    "name:zho_x_preferred":[
        "\u5739\u53e3"
    ],
    "wof:name":"Kuangkou",
    "wof:placetype":"locality"
},
  "geometry": {"coordinates":[110.014,29.45868],"type":"Point"}
}