{
  "type": "Feature",
  "properties": {
    "gn:admin1_code":"31.0",
    "gn:asciiname":"Luoji",
    "gn:country_code":"CN",
    "gn:dem":27,
    "gn:feature_class":"P",
    "gn:feature_code":"PPL",
    "gn:name":"Luoji",
    "gn:population":0,
    "gn:timezone":"Asia/Shanghai",
    "iso:country":"CN",
    "name:zho_x_preferred":[
        "\u843d\u57fa"
    ],
    "wof:name":"Luoji",
    "wof:placetype":"locality"
},
  "geometry": {"coordinates":[109.19280999999999,18.42062],"type":"Point"}
}