{
  "type": "Feature",
  "properties": {
    "gn:admin1_code":"14",
    "gn:asciiname":"Zongjijie",
    "gn:country_code":"CN",
    "gn:dem":4871,
    "gn:feature_class":"P",
    "gn:feature_code":"PPL",
    "gn:name":"Zongjijie",
    "gn:population":0,
    "gn:timezone":"Asia/Urumqi",
    "iso:country":"CN",
    "name:zho_x_preferred":[
        "\u5b97\u5409\u6770"
    ],
    "wof:name":"Zongjijie",
    "wof:placetype":"locality"
},
  "geometry": {"coordinates":[87.75279999999999,30.9701],"type":"Point"}
}