{
  "type": "Feature",
  "properties": {
    "gn:admin1_code":"25.0",
    "gn:asciiname":"Nanduokuang",
    "gn:country_code":"CN",
    "gn:dem":51,
    "gn:feature_class":"P",
    "gn:feature_code":"PPL",
    "gn:name":"Nanduokuang",
    "gn:population":0,
    "gn:timezone":"Asia/Shanghai",
    "iso:country":"CN",
    "name:zho_x_preferred":[
        "\u5357\u591a\u593c"
    ],
    "wof:name":"Nanduokuang",
    "wof:placetype":"locality"
},
  "geometry": {"coordinates":[121.90885,37.18241],"type":"Point"}
}