{
  "type": "Feature",
  "properties": {
    "gn:admin1_code":"7",
    "gn:asciiname":"Jiakeng",
    "gn:country_code":"CN",
    "gn:dem":929,
    "gn:feature_class":"P",
    "gn:feature_code":"PPL",
    "gn:name":"Jiakeng",
    "gn:population":0,
    "gn:timezone":"Asia/Shanghai",
    "iso:country":"CN",
    "name:und_x_variant":[
        "\u7532\u5751"
    ],
    "wof:name":"Jiakeng",
    "wof:placetype":"locality"
},
  "geometry": {"coordinates":[118.82256,27.00449],"type":"Point"}
}