{
  "type": "Feature",
  "properties": {
    "gn:admin1_code":"24.0",
    "gn:asciiname":"Yulicun",
    "gn:country_code":"CN",
    "gn:dem":1007,
    "gn:feature_class":"P",
    "gn:feature_code":"PPL",
    "gn:name":"Yulicun",
    "gn:population":0,
    "gn:timezone":"Asia/Shanghai",
    "iso:country":"CN",
    "name:zho_x_preferred":[
        "\u5cea\u91cc\u6751"
    ],
    "wof:name":"Yulicun",
    "wof:placetype":"locality"
},
  "geometry": {"coordinates":[110.63058999999998,36.55155],"type":"Point"}
}