{
  "type": "Feature",
  "properties": {
    "gn:admin1_code":"4.0",
    "gn:asciiname":"Gugaoqiao",
    "gn:country_code":"CN",
    "gn:dem":4,
    "gn:feature_class":"P",
    "gn:feature_code":"PPL",
    "gn:name":"Gugaoqiao",
    "gn:population":0,
    "gn:timezone":"Asia/Shanghai",
    "iso:country":"CN",
    "name:zho_x_preferred":[
        "\u987e\u9ad8\u6865"
    ],
    "wof:name":"Gugaoqiao",
    "wof:placetype":"locality"
},
  "geometry": {"coordinates":[120.866,32.2575],"type":"Point"}
}