{
  "type": "Feature",
  "properties": {
    "gn:admin1_code":"9",
    "gn:asciiname":"Anzhuang",
    "gn:country_code":"CN",
    "gn:dem":88,
    "gn:feature_class":"P",
    "gn:feature_code":"PPL",
    "gn:name":"Anzhuang",
    "gn:population":0,
    "gn:timezone":"Asia/Shanghai",
    "iso:country":"CN",
    "name:zho_x_preferred":[
        "\u5b89\u5e84"
    ],
    "wof:name":"Anzhuang",
    "wof:placetype":"locality"
},
  "geometry": {"coordinates":[113.55217,35.10527],"type":"Point"}
}