{
  "type": "Feature",
  "properties": {
    "gn:admin1_code":"29.0",
    "gn:asciiname":"Shiba",
    "gn:country_code":"CN",
    "gn:dem":1471,
    "gn:feature_class":"P",
    "gn:feature_code":"PPL",
    "gn:name":"Shiba",
    "gn:population":0,
    "gn:timezone":"Asia/Shanghai",
    "iso:country":"CN",
    "name:zho_x_preferred":[
        "\u77f3\u575d"
    ],
    "wof:name":"Shiba",
    "wof:placetype":"locality"
},
  "geometry": {"coordinates":[104.044,24.1495],"type":"Point"}
}