{
  "type": "Feature",
  "properties": {
    "gn:admin1_code":"18",
    "gn:asciiname":"Fenpo",
    "gn:country_code":"CN",
    "gn:dem":1096,
    "gn:feature_class":"P",
    "gn:feature_code":"PPL",
    "gn:name":"Fenpo",
    "gn:population":0,
    "gn:timezone":"Asia/Shanghai",
    "iso:country":"CN",
    "name:zho_x_preferred":[
        "\u575f\u5761"
    ],
    "wof:name":"Fenpo",
    "wof:placetype":"locality"
},
  "geometry": {"coordinates":[106.19199999999999,27.5508],"type":"Point"}
}