{
  "type": "Feature",
  "properties": {
    "gn:admin1_code":"20.0",
    "gn:asciiname":"Guoni Wudui",
    "gn:country_code":"CN",
    "gn:dem":298,
    "gn:feature_class":"P",
    "gn:feature_code":"PPLF",
    "gn:name":"Guoni Wudui",
    "gn:population":0,
    "gn:timezone":"Asia/Shanghai",
    "iso:country":"CN",
    "name:zho_x_preferred":[
        "\u90ed\u5c3c\u4e94\u961f"
    ],
    "wof:name":"Guoni Wudui",
    "wof:placetype":"locality"
},
  "geometry": {"coordinates":[124.51286,48.76562],"type":"Point"}
}