{
  "type": "Feature",
  "properties": {
    "gn:admin1_code":"10",
    "gn:asciiname":"Laoniugou",
    "gn:country_code":"CN",
    "gn:dem":1037,
    "gn:feature_class":"P",
    "gn:feature_code":"PPL",
    "gn:name":"Laoniugou",
    "gn:population":0,
    "gn:timezone":"Asia/Shanghai",
    "iso:country":"CN",
    "name:zho_x_preferred":[
        "\u8001\u725b\u6c9f"
    ],
    "wof:name":"Laoniugou",
    "wof:placetype":"locality"
},
  "geometry": {"coordinates":[116.00167999999999,41.07718],"type":"Point"}
}