{
  "type": "Feature",
  "properties": {
    "gn:admin1_code":"26.0",
    "gn:asciiname":"Dianziyancun",
    "gn:country_code":"CN",
    "gn:dem":974,
    "gn:feature_class":"P",
    "gn:feature_code":"PPL",
    "gn:name":"Dianziyancun",
    "gn:population":0,
    "gn:timezone":"Asia/Shanghai",
    "iso:country":"CN",
    "name:zho_x_preferred":[
        "\u7535\u5b50\u5895\u6751"
    ],
    "wof:name":"Dianziyancun",
    "wof:placetype":"locality"
},
  "geometry": {"coordinates":[110.50136999999999,38.26062],"type":"Point"}
}