{
  "type": "Feature",
  "properties": {
    "gn:admin1_code":"20.0",
    "gn:asciiname":"Guo'enhe",
    "gn:country_code":"CN",
    "gn:dem":259,
    "gn:feature_class":"P",
    "gn:feature_code":"PPL",
    "gn:name":"Guo\u2019enhe",
    "gn:population":0,
    "gn:timezone":"Asia/Shanghai",
    "iso:country":"CN",
    "name:und_x_variant":[
        "Guo\u2019enhe"
    ],
    "name:zho_x_preferred":[
        "\u90ed\u6069\u6cb3"
    ],
    "wof:name":"Guo'enhe",
    "wof:placetype":"locality"
},
  "geometry": {"coordinates":[124.46791,49.10146],"type":"Point"}
}