{
  "type": "Feature",
  "properties": {
    "gn:admin1_code":"1.0",
    "gn:asciiname":"Jingoukoucun",
    "gn:country_code":"CN",
    "gn:dem":32,
    "gn:feature_class":"P",
    "gn:feature_code":"PPL",
    "gn:name":"Jingoukoucun",
    "gn:population":0,
    "gn:timezone":"Asia/Shanghai",
    "iso:country":"CN",
    "name:zho_x_preferred":[
        "\u9773\u6c9f\u53e3\u6751"
    ],
    "wof:name":"Jingoukoucun",
    "wof:placetype":"locality"
},
  "geometry": {"coordinates":[115.87921,33.36518],"type":"Point"}
}