{
  "type": "Feature",
  "properties": {
    "gn:admin1_code":"18",
    "gn:asciiname":"Shaowotang",
    "gn:country_code":"CN",
    "gn:dem":1912,
    "gn:feature_class":"P",
    "gn:feature_code":"PPL",
    "gn:name":"Shaowotang",
    "gn:population":0,
    "gn:timezone":"Asia/Shanghai",
    "iso:country":"CN",
    "name:zho_x_preferred":[
        "\u52fa\u7a9d\u5802"
    ],
    "wof:name":"Shaowotang",
    "wof:placetype":"locality"
},
  "geometry": {"coordinates":[104.375,27.2161],"type":"Point"}
}