{
  "type": "Feature",
  "properties": {
    "gn:admin1_code":"5.0",
    "gn:asciiname":"Weizuizicun",
    "gn:country_code":"CN",
    "gn:dem":162,
    "gn:feature_class":"P",
    "gn:feature_code":"PPL",
    "gn:name":"Weizuizicun",
    "gn:population":0,
    "gn:timezone":"Asia/Shanghai",
    "iso:country":"CN",
    "name:zho_x_preferred":[
        "\u82c7\u5480\u5b50\u6751"
    ],
    "wof:name":"Weizuizicun",
    "wof:placetype":"locality"
},
  "geometry": {"coordinates":[125.81903,44.58237],"type":"Point"}
}