{
  "type": "Feature",
  "properties": {
    "gn:admin1_code":"26",
    "gn:asciiname":"Diaojiagou",
    "gn:country_code":"CN",
    "gn:dem":510,
    "gn:feature_class":"P",
    "gn:feature_code":"PPL",
    "gn:name":"Diaojiagou",
    "gn:population":0,
    "gn:timezone":"Asia/Shanghai",
    "iso:country":"CN",
    "name:zho_x_preferred":[
        "\u96d5\u5bb6\u6c9f"
    ],
    "wof:name":"Diaojiagou",
    "wof:placetype":"locality"
},
  "geometry": {"coordinates":[108.09524,34.31612],"type":"Point"}
}