{
  "type": "Feature",
  "properties": {
    "gn:admin1_code":"29.0",
    "gn:asciiname":"Bisongjiu",
    "gn:country_code":"CN",
    "gn:dem":1422,
    "gn:feature_class":"P",
    "gn:feature_code":"PPL",
    "gn:name":"Bisongjiu",
    "gn:population":0,
    "gn:timezone":"Asia/Shanghai",
    "iso:country":"CN",
    "name:zho_x_preferred":[
        "\u78a7\u677e\u5c31"
    ],
    "wof:name":"Bisongjiu",
    "wof:placetype":"locality"
},
  "geometry": {"coordinates":[104.26900000000001,24.0423],"type":"Point"}
}