{
  "type": "Feature",
  "properties": {
    "gn:admin1_code":"12.0",
    "gn:asciiname":"Ertang",
    "gn:country_code":"CN",
    "gn:dem":267,
    "gn:feature_class":"P",
    "gn:feature_code":"PPL",
    "gn:name":"Ertang",
    "gn:population":0,
    "gn:timezone":"Asia/Shanghai",
    "iso:country":"CN",
    "name:deu_x_preferred":[
        "Ertang"
    ],
    "name:zho_x_preferred":[
        "\u4e8c\u5802"
    ],
    "wof:name":"Ertang",
    "wof:placetype":"locality"
},
  "geometry": {"coordinates":[111.25261999999999,31.92488],"type":"Point"}
}