{
  "type": "Feature",
  "properties": {
    "gn:admin1_code":"18.0",
    "gn:asciiname":"Cuobajing",
    "gn:country_code":"CN",
    "gn:dem":776,
    "gn:feature_class":"P",
    "gn:feature_code":"PPL",
    "gn:name":"Cuobajing",
    "gn:population":0,
    "gn:timezone":"Asia/Shanghai",
    "iso:country":"CN",
    "name:zho_x_preferred":[
        "\u9519\u575d\u4e95"
    ],
    "wof:name":"Cuobajing",
    "wof:placetype":"locality"
},
  "geometry": {"coordinates":[108.66200000000001,28.4591],"type":"Point"}
}