{
  "type": "Feature",
  "properties": {
    "gn:admin1_code":"32.0",
    "gn:asciiname":"Shadai",
    "gn:country_code":"CN",
    "gn:dem":1875,
    "gn:feature_class":"P",
    "gn:feature_code":"PPL",
    "gn:name":"Shadai",
    "gn:population":0,
    "gn:timezone":"Asia/Shanghai",
    "iso:country":"CN",
    "name:zho_x_preferred":[
        "\u6c99\u5cb1"
    ],
    "wof:name":"Shadai",
    "wof:placetype":"locality"
},
  "geometry": {"coordinates":[102.77281000000001,29.11618],"type":"Point"}
}