{
  "type": "Feature",
  "properties": {
    "gn:admin1_code":"26",
    "gn:asciiname":"Weizicun",
    "gn:country_code":"CN",
    "gn:dem":606,
    "gn:feature_class":"P",
    "gn:feature_code":"PPL",
    "gn:name":"Weizicun",
    "gn:population":0,
    "gn:timezone":"Asia/Shanghai",
    "iso:country":"CN",
    "name:zho_x_preferred":[
        "\u97e6\u5b50\u6751"
    ],
    "name:zho_x_variant":[
        "\u82c7\u5b50\u6751"
    ],
    "wof:name":"Weizicun",
    "wof:placetype":"locality"
},
  "geometry": {"coordinates":[108.05225,34.45174],"type":"Point"}
}