{
  "type": "Feature",
  "properties": {
    "gn:admin1_code":"19.0",
    "gn:asciiname":"Xishao Daogou",
    "gn:country_code":"CN",
    "gn:dem":113,
    "gn:feature_class":"P",
    "gn:feature_code":"PPL",
    "gn:name":"Xishao Daogou",
    "gn:population":0,
    "gn:timezone":"Asia/Shanghai",
    "iso:country":"CN",
    "name:und_x_variant":[
        "\u897f\u7a0d\u9053\u6c9f"
    ],
    "wof:name":"Xishao Daogou",
    "wof:placetype":"locality"
},
  "geometry": {"coordinates":[122.6268,40.61321],"type":"Point"}
}