{
  "type": "Feature",
  "properties": {
    "gn:admin1_code":"22.0",
    "gn:asciiname":"Dapangcun",
    "gn:country_code":"CN",
    "gn:dem":29,
    "gn:feature_class":"P",
    "gn:feature_code":"PPL",
    "gn:name":"Dapangcun",
    "gn:population":0,
    "gn:timezone":"Asia/Shanghai",
    "iso:country":"CN",
    "name:zho_x_preferred":[
        "\u5927\u5e9e\u6751"
    ],
    "wof:name":"Dapangcun",
    "wof:placetype":"locality"
},
  "geometry": {"coordinates":[116.69748,39.98428],"type":"Point"}
}