{
  "type": "Feature",
  "properties": {
    "gn:admin1_code":"30.0",
    "gn:asciiname":"Dongkengwei",
    "gn:country_code":"CN",
    "gn:dem":315,
    "gn:feature_class":"P",
    "gn:feature_code":"PPL",
    "gn:name":"Dongkengwei",
    "gn:population":0,
    "gn:timezone":"Asia/Shanghai",
    "iso:country":"CN",
    "name:zho_x_preferred":[
        "Dongkengwei"
    ],
    "name:zho_x_variant":[
        "\u4e1c\u5751\u5c3e"
    ],
    "wof:name":"Dongkengwei",
    "wof:placetype":"locality"
},
  "geometry": {"coordinates":[115.07889,24.61306],"type":"Point"}
}