{
  "type": "Feature",
  "properties": {
    "gn:admin1_code":"29.0",
    "gn:asciiname":"Guigang",
    "gn:country_code":"CN",
    "gn:dem":2559,
    "gn:feature_class":"P",
    "gn:feature_code":"PPL",
    "gn:name":"Guigang",
    "gn:population":0,
    "gn:timezone":"Asia/Shanghai",
    "iso:country":"CN",
    "name:zho_x_preferred":[
        "\u8d35\u5c97"
    ],
    "wof:name":"Guigang",
    "wof:placetype":"locality"
},
  "geometry": {"coordinates":[99.4627,27.9322],"type":"Point"}
}