{
  "type": "Feature",
  "properties": {
    "gn:admin1_code":"29.0",
    "gn:asciiname":"Guigang",
    "gn:country_code":"CN",
    "gn:dem":2559,
    "gn:feature_class":"P",
    "gn:feature_code":"PPL",
    "gn:name":"Guigang",
    "gn:population":0,
    "gn:timezone":"Asia/Shanghai",
    "iso:country":"CN",
    "name:afr_x_preferred":[
        "Guigang"
    ],
    "name:ara_x_preferred":[
        "\u062c\u0648\u064a\u063a\u0627\u0646\u063a"
    ],
    "name:cdo_x_preferred":[
        "G\u00f3i-g\u0113\u0324ng"
    ],
    "name:ceb_x_preferred":[
        "Guigang"
    ],
    "name:ces_x_preferred":[
        "Kuej-kang"
    ],
    "name:dan_x_preferred":[
        "Guigang"
    ],
    "name:deu_x_preferred":[
        "Guigang"
    ],
    "name:eus_x_preferred":[
        "Guigang"
    ],
    "name:fas_x_preferred":[
        "\u06af\u0648\u06cc\u06af\u0627\u0646\u06af"
    ],
    "name:fin_x_preferred":[
        "Guigang"
    ],
    "name:fra_x_preferred":[
        "Guigang"
    ],
    "name:hak_x_preferred":[
        "Kui-k\u00f3ng-s\u1e73"
    ],
    "name:ind_x_preferred":[
        "Guigang"
    ],
    "name:ita_x_preferred":[
        "Guigang"
    ],
    "name:jpn_x_preferred":[
        "\u8cb4\u6e2f\u5e02"
    ],
    "name:kik_x_preferred":[
        "Guigang"
    ],
    "name:kor_x_preferred":[
        "\uad6c\uc774\uac15\uc2dc"
    ],
    "name:mlg_x_preferred":[
        "Guigang"
    ],
    "name:nld_x_preferred":[
        "Guigang"
    ],
    "name:nno_x_preferred":[
        "Guigang"
    ],
    "name:nor_x_preferred":[
        "Guigang"
    ],
    "name:pnb_x_preferred":[
        "\u06af\u0648\u0626\u06cc\u06af\u0627\u0646\u06af"
    ],
    "name:pol_x_preferred":[
        "Guigang"
    ],
    "name:por_x_preferred":[
        "Guigang"
    ],
    "name:rus_x_preferred":[
        "\u0413\u0443\u0439\u0433\u0430\u043d"
    ],
    "name:spa_x_preferred":[
        "Guigang"
    ],
    "name:swe_x_preferred":[
        "Guigang"
    ],
    "name:tur_x_preferred":[
        "Guigang"
    ],
    "name:ukr_x_preferred":[
        "\u0413\u0443\u0439\u0433\u0430\u043d"
    ],
    "name:urd_x_preferred":[
        "\u06af\u0648\u0626\u06af\u0627\u0646\u06af"
    ],
    "name:vie_x_preferred":[
        "Qu\u00fd C\u1ea3ng"
    ],
    "name:war_x_preferred":[
        "Guigang"
    ],
    "name:zha_x_preferred":[
        "Gveigangj"
    ],
    "name:zho_x_preferred":[
        "\u8d35\u5c97"
    ],
    "name:zho_x_variant":[
        "\u8d35\u6e2f\u5e02"
    ],
    "wof:name":"Guigang",
    "wof:placetype":"locality"
},
  "geometry": {"coordinates":[99.4627,27.9322],"type":"Point"}
}