{
  "type": "Feature",
  "properties": {
    "gn:admin1_code":"9.0",
    "gn:asciiname":"Mengbang",
    "gn:country_code":"CN",
    "gn:dem":80,
    "gn:feature_class":"P",
    "gn:feature_code":"PPL",
    "gn:name":"Mengbang",
    "gn:population":0,
    "gn:timezone":"Asia/Shanghai",
    "iso:country":"CN",
    "name:zho_x_preferred":[
        "\u5b5f\u585d"
    ],
    "wof:name":"Mengbang",
    "wof:placetype":"locality"
},
  "geometry": {"coordinates":[114.41168999999999,32.01447],"type":"Point"}
}