{
  "type": "Feature",
  "properties": {
    "gn:admin1_code":"10.0",
    "gn:asciiname":"Houpang Gezhuang",
    "gn:country_code":"CN",
    "gn:dem":38,
    "gn:feature_class":"P",
    "gn:feature_code":"PPL",
    "gn:name":"Houpang Gezhuang",
    "gn:population":0,
    "gn:timezone":"Asia/Shanghai",
    "iso:country":"CN",
    "name:zho_x_preferred":[
        "\u540e\u5e9e\u5404\u5e84"
    ],
    "wof:name":"Houpang Gezhuang",
    "wof:placetype":"locality"
},
  "geometry": {"coordinates":[118.64190000000001,39.62409],"type":"Point"}
}