{
  "type": "Feature",
  "properties": {
    "gn:admin1_code":"29.0",
    "gn:asciiname":"Shuiqing",
    "gn:country_code":"CN",
    "gn:dem":2088,
    "gn:feature_class":"P",
    "gn:feature_code":"PPL",
    "gn:name":"Shuiqing",
    "gn:population":0,
    "gn:timezone":"Asia/Shanghai",
    "iso:country":"CN",
    "name:zho_x_preferred":[
        "\u6c34\u7b90"
    ],
    "wof:name":"Shuiqing",
    "wof:placetype":"locality"
},
  "geometry": {"coordinates":[104.17700000000001,26.3646],"type":"Point"}
}