{
  "type": "Feature",
  "properties": {
    "gn:admin1_code":"29",
    "gn:asciiname":"Shayilang",
    "gn:country_code":"CN",
    "gn:dem":1508,
    "gn:feature_class":"P",
    "gn:feature_code":"PPL",
    "gn:name":"Shayilang",
    "gn:population":0,
    "gn:timezone":"Asia/Shanghai",
    "iso:country":"CN",
    "name:zho_x_preferred":[
        "\u6c99\u77e3\u90ce"
    ],
    "wof:name":"Shayilang",
    "wof:placetype":"locality"
},
  "geometry": {"coordinates":[102.036,24.9318],"type":"Point"}
}