{
  "type": "Feature",
  "properties": {
    "gn:admin1_code":"10",
    "gn:asciiname":"Dongzi Goumen",
    "gn:country_code":"CN",
    "gn:dem":613,
    "gn:feature_class":"P",
    "gn:feature_code":"PPL",
    "gn:name":"Dongzi Goumen",
    "gn:population":0,
    "gn:timezone":"Asia/Shanghai",
    "iso:country":"CN",
    "name:zho_x_preferred":[
        "\u6d1e\u5b50\u6c9f\u95e8"
    ],
    "wof:name":"Dongzi Goumen",
    "wof:placetype":"locality"
},
  "geometry": {"coordinates":[117.56574000000001,41.39776],"type":"Point"}
}