{
  "type": "Feature",
  "properties": {
    "gn:admin1_code":"15.0",
    "gn:asciiname":"Hewan",
    "gn:country_code":"CN",
    "gn:dem":2344,
    "gn:feature_class":"P",
    "gn:feature_code":"PPL",
    "gn:name":"Hewan",
    "gn:population":0,
    "gn:timezone":"Asia/Shanghai",
    "iso:country":"CN",
    "name:zho_x_preferred":[
        "\u6cb3\u6e7e"
    ],
    "wof:name":"Hewan",
    "wof:placetype":"locality"
},
  "geometry": {"coordinates":[102.59699999999999,37.4695],"type":"Point"}
}