{
  "type": "Feature",
  "properties": {
    "gn:admin1_code":"11.0",
    "gn:asciiname":"Sanbaimu",
    "gn:country_code":"CN",
    "gn:dem":27,
    "gn:feature_class":"P",
    "gn:feature_code":"PPL",
    "gn:name":"Sanbaimu",
    "gn:population":0,
    "gn:timezone":"Asia/Shanghai",
    "iso:country":"CN",
    "name:zho_x_preferred":[
        "\u4e09\u767e\u4ea9"
    ],
    "wof:name":"Sanbaimu",
    "wof:placetype":"locality"
},
  "geometry": {"coordinates":[112.88272000000001,29.54332],"type":"Point"}
}