{
  "type": "Feature",
  "properties": {
    "gn:admin1_code":"15.0",
    "gn:asciiname":"Shidatan",
    "gn:country_code":"CN",
    "gn:dem":2909,
    "gn:feature_class":"P",
    "gn:feature_code":"PPL",
    "gn:name":"Shidatan",
    "gn:population":0,
    "gn:timezone":"Asia/Shanghai",
    "iso:country":"CN",
    "name:und_x_variant":[
        "\u77f3\u8fbe\u6ee9"
    ],
    "wof:name":"Shidatan",
    "wof:placetype":"locality"
},
  "geometry": {"coordinates":[103.95919000000001,34.75986],"type":"Point"}
}