{
  "type": "Feature",
  "properties": {
    "gn:admin1_code":"1.0",
    "gn:asciiname":"Xindianhecun",
    "gn:country_code":"CN",
    "gn:dem":91,
    "gn:feature_class":"P",
    "gn:feature_code":"PPL",
    "gn:name":"Xindianhecun",
    "gn:population":0,
    "gn:timezone":"Asia/Shanghai",
    "iso:country":"CN",
    "name:und_x_variant":[
        "Xindianhe"
    ],
    "name:zho_x_preferred":[
        "\u65b0\u5e97\u6cb3\u6751"
    ],
    "wof:name":"Xindianhecun",
    "wof:placetype":"locality"
},
  "geometry": {"coordinates":[116.21988,31.43638],"type":"Point"}
}