{
  "type": "Feature",
  "properties": {
    "gn:admin1_code":"12.0",
    "gn:asciiname":"Zhongfan",
    "gn:country_code":"CN",
    "gn:dem":25,
    "gn:feature_class":"P",
    "gn:feature_code":"PPL",
    "gn:name":"Zhongfan",
    "gn:population":0,
    "gn:timezone":"Asia/Shanghai",
    "iso:country":"CN",
    "name:zho_x_preferred":[
        "Zhongfan"
    ],
    "name:zho_x_variant":[
        "\u4e2d\u7548"
    ],
    "wof:name":"Zhongfan",
    "wof:placetype":"locality"
},
  "geometry": {"coordinates":[114.03234,29.99862000000001],"type":"Point"}
}