{
  "type": "Feature",
  "properties": {
    "gn:admin1_code":"11",
    "gn:asciiname":"Tuqiao",
    "gn:country_code":"CN",
    "gn:dem":473,
    "gn:feature_class":"P",
    "gn:feature_code":"PPL",
    "gn:name":"Tuqiao",
    "gn:population":0,
    "gn:timezone":"Asia/Shanghai",
    "iso:country":"CN",
    "name:und_x_variant":[
        "T\u2019u-ch\u2019iao",
        "Tuqiao"
    ],
    "name:zho_x_preferred":[
        "\u571f\u6865"
    ],
    "wof:name":"Tuqiao",
    "wof:placetype":"locality"
},
  "geometry": {"coordinates":[110.39943999999998,26.50214],"type":"Point"}
}