{
  "type": "Feature",
  "properties": {
    "gn:admin1_code":"10.0",
    "gn:asciiname":"Yeli",
    "gn:country_code":"CN",
    "gn:dem":26,
    "gn:feature_class":"P",
    "gn:feature_code":"PPL",
    "gn:name":"Yeli",
    "gn:population":0,
    "gn:timezone":"Asia/Shanghai",
    "iso:country":"CN",
    "name:ceb_x_preferred":[
        "Yeli"
    ],
    "name:swe_x_preferred":[
        "Yeli"
    ],
    "name:zho_x_preferred":[
        "\u51b6\u91cc"
    ],
    "wof:name":"Yeli",
    "wof:placetype":"locality"
},
  "geometry": {"coordinates":[118.28010999999999,39.72617],"type":"Point"}
}