{
  "type": "Feature",
  "properties": {
    "gn:admin1_code":"19",
    "gn:asciiname":"Pingdingpu",
    "gn:cc2":"CN",
    "gn:country_code":"CN",
    "gn:dem":61,
    "gn:feature_class":"P",
    "gn:feature_code":"PPL",
    "gn:name":"Pingdingpu",
    "gn:population":0,
    "gn:timezone":"Asia/Shanghai",
    "iso:country":"CN",
    "name:und_x_variant":[
        "P\u2019ing-ting-pao",
        "P\u2019ing-ting-p\u2019u",
        "Pingdingpu"
    ],
    "wof:name":"Pingdingpu",
    "wof:placetype":"locality"
},
  "geometry": {"coordinates":[123.91667,42.36667],"type":"Point"}
}