{
  "type": "Feature",
  "properties": {
    "gn:admin1_code":"9",
    "gn:asciiname":"Caodazhuang",
    "gn:country_code":"CN",
    "gn:dem":42,
    "gn:feature_class":"P",
    "gn:feature_code":"PPL",
    "gn:name":"Caodazhuang",
    "gn:population":0,
    "gn:timezone":"Asia/Shanghai",
    "iso:country":"CN",
    "name:zho_x_preferred":[
        "\u66f9\u5927\u5e84"
    ],
    "wof:name":"Caodazhuang",
    "wof:placetype":"locality"
},
  "geometry": {"coordinates":[116.44199999999999,34.1068],"type":"Point"}
}