{
  "type": "Feature",
  "properties": {
    "gn:admin1_code":"8.0",
    "gn:asciiname":"Dongxiawa",
    "gn:country_code":"CN",
    "gn:dem":189,
    "gn:feature_class":"P",
    "gn:feature_code":"PPL",
    "gn:name":"Dongxiawa",
    "gn:population":0,
    "gn:timezone":"Asia/Shanghai",
    "iso:country":"CN",
    "name:zho_x_preferred":[
        "\u4e1c\u4e0b\u6d3c"
    ],
    "wof:name":"Dongxiawa",
    "wof:placetype":"locality"
},
  "geometry": {"coordinates":[125.64923,47.08155],"type":"Point"}
}