{
  "type": "Feature",
  "properties": {
    "gn:admin1_code":"25.0",
    "gn:asciiname":"Yukecun",
    "gn:country_code":"CN",
    "gn:dem":416,
    "gn:feature_class":"P",
    "gn:feature_code":"PPL",
    "gn:name":"Yukecun",
    "gn:population":0,
    "gn:timezone":"Asia/Shanghai",
    "iso:country":"CN",
    "name:zho_x_preferred":[
        "\u4e8e\u79d1\u6751"
    ],
    "wof:name":"Yukecun",
    "wof:placetype":"locality"
},
  "geometry": {"coordinates":[117.1553,36.36907],"type":"Point"}
}