{
  "type": "Feature",
  "properties": {
    "gn:admin1_code":"29.0",
    "gn:asciiname":"Luoshuidong",
    "gn:country_code":"CN",
    "gn:dem":1617,
    "gn:feature_class":"P",
    "gn:feature_code":"PPL",
    "gn:name":"Luoshuidong",
    "gn:population":0,
    "gn:timezone":"Asia/Shanghai",
    "iso:country":"CN",
    "name:zho_x_preferred":[
        "\u843d\u6c34\u6d1e"
    ],
    "wof:name":"Luoshuidong",
    "wof:placetype":"locality"
},
  "geometry": {"coordinates":[103.892,23.4755],"type":"Point"}
}