{
  "type": "Feature",
  "properties": {
    "gn:admin1_code":"5.0",
    "gn:asciiname":"Hulutougou",
    "gn:country_code":"CN",
    "gn:dem":486,
    "gn:feature_class":"P",
    "gn:feature_code":"PPL",
    "gn:name":"Hulutougou",
    "gn:population":0,
    "gn:timezone":"Asia/Shanghai",
    "iso:country":"CN",
    "name:zho_x_preferred":[
        "\u846b\u82a6\u5934\u6c9f"
    ],
    "wof:name":"Hulutougou",
    "wof:placetype":"locality"
},
  "geometry": {"coordinates":[126.64794999999999,42.61485],"type":"Point"}
}