{
  "type": "Feature",
  "properties": {
    "gn:admin1_code":"9",
    "gn:asciiname":"Dongsishang",
    "gn:country_code":"CN",
    "gn:dem":56,
    "gn:feature_class":"P",
    "gn:feature_code":"PPL",
    "gn:name":"Dongsishang",
    "gn:population":0,
    "gn:timezone":"Asia/Shanghai",
    "iso:country":"CN",
    "name:zho_x_preferred":[
        "\u4e1c\u5bfa\u4e0a"
    ],
    "wof:name":"Dongsishang",
    "wof:placetype":"locality"
},
  "geometry": {"coordinates":[115.199,35.6513],"type":"Point"}
}