{
  "type": "Feature",
  "properties": {
    "gn:admin1_code":"3.0",
    "gn:asciiname":"Yikeng",
    "gn:country_code":"CN",
    "gn:dem":299,
    "gn:feature_class":"P",
    "gn:feature_code":"PPL",
    "gn:name":"Yikeng",
    "gn:population":0,
    "gn:timezone":"Asia/Shanghai",
    "iso:country":"CN",
    "name:und_x_variant":[
        "\u6613\u5751"
    ],
    "wof:name":"Yikeng",
    "wof:placetype":"locality"
},
  "geometry": {"coordinates":[116.48765,26.87325],"type":"Point"}
}