{
  "type": "Feature",
  "properties": {
    "gn:admin1_code":"18.0",
    "gn:asciiname":"Gulang",
    "gn:country_code":"CN",
    "gn:dem":471,
    "gn:feature_class":"P",
    "gn:feature_code":"PPL",
    "gn:name":"Gulang",
    "gn:population":0,
    "gn:timezone":"Asia/Shanghai",
    "iso:country":"CN",
    "name:zho_x_preferred":[
        "\u6545\u90ce"
    ],
    "wof:name":"Gulang",
    "wof:placetype":"locality"
},
  "geometry": {"coordinates":[108.401,26.0385],"type":"Point"}
}