{
  "type": "Feature",
  "properties": {
    "gn:admin1_code":"15.0",
    "gn:asciiname":"Daquanshui",
    "gn:country_code":"CN",
    "gn:dem":1986,
    "gn:feature_class":"P",
    "gn:feature_code":"PPL",
    "gn:name":"Daquanshui",
    "gn:population":0,
    "gn:timezone":"Asia/Shanghai",
    "iso:country":"CN",
    "name:zho_x_preferred":[
        "\u5927\u6cc9\u6c34"
    ],
    "wof:name":"Daquanshui",
    "wof:placetype":"locality"
},
  "geometry": {"coordinates":[103.714,37.4924],"type":"Point"}
}