{
  "type": "Feature",
  "properties": {
    "gn:admin1_code":"15.0",
    "gn:asciiname":"Luojiawan",
    "gn:country_code":"CN",
    "gn:dem":963,
    "gn:feature_class":"P",
    "gn:feature_code":"PPL",
    "gn:name":"Luojiawan",
    "gn:population":0,
    "gn:timezone":"Asia/Shanghai",
    "iso:country":"CN",
    "name:zho_x_preferred":[
        "\u7f57\u5bb6\u6e7e"
    ],
    "wof:name":"Luojiawan",
    "wof:placetype":"locality"
},
  "geometry": {"coordinates":[107.634,35.068],"type":"Point"}
}