{
  "type": "Feature",
  "properties": {
    "gn:admin1_code":"32.0",
    "gn:asciiname":"Lanjiagou",
    "gn:country_code":"CN",
    "gn:dem":388,
    "gn:feature_class":"P",
    "gn:feature_code":"PPL",
    "gn:name":"Lanjiagou",
    "gn:population":0,
    "gn:timezone":"Asia/Shanghai",
    "iso:country":"CN",
    "name:zho_x_preferred":[
        "\u5170\u5bb6\u6c9f"
    ],
    "wof:name":"Lanjiagou",
    "wof:placetype":"locality"
},
  "geometry": {"coordinates":[106.39677,30.95779000000001],"type":"Point"}
}