{
  "type": "Feature",
  "properties": {
    "gn:admin1_code":"32.0",
    "gn:asciiname":"Yanglouzi",
    "gn:country_code":"CN",
    "gn:dem":828,
    "gn:feature_class":"P",
    "gn:feature_code":"PPL",
    "gn:name":"Yanglouzi",
    "gn:population":0,
    "gn:timezone":"Asia/Shanghai",
    "iso:country":"CN",
    "name:zho_x_preferred":[
        "\u7f8a\u697c\u5b50"
    ],
    "wof:name":"Yanglouzi",
    "wof:placetype":"locality"
},
  "geometry": {"coordinates":[103.511,28.6985],"type":"Point"}
}