{
  "type": "Feature",
  "properties": {
    "gn:admin1_code":"24.0",
    "gn:asciiname":"Mayinghe",
    "gn:country_code":"CN",
    "gn:dem":1276,
    "gn:feature_class":"P",
    "gn:feature_code":"PPL",
    "gn:name":"Mayinghe",
    "gn:population":0,
    "gn:timezone":"Asia/Shanghai",
    "iso:country":"CN",
    "name:und_x_variant":[
        "\u9a6c\u8425\u6cb3"
    ],
    "name:zho_x_preferred":[
        "\u9a6c\u8425\u6cb3"
    ],
    "wof:name":"Mayinghe",
    "wof:placetype":"locality"
},
  "geometry": {"coordinates":[112.33231000000001,40.20121],"type":"Point"}
}