{
  "type": "Feature",
  "properties": {
    "gn:admin1_code":"30",
    "gn:asciiname":"Youjiankeng",
    "gn:country_code":"CN",
    "gn:dem":227,
    "gn:feature_class":"P",
    "gn:feature_code":"PPL",
    "gn:name":"Youjiankeng",
    "gn:population":0,
    "gn:timezone":"Asia/Shanghai",
    "iso:country":"CN",
    "name:zho_x_preferred":[
        "\u6cb9\u5065\u5751"
    ],
    "wof:name":"Youjiankeng",
    "wof:placetype":"locality"
},
  "geometry": {"coordinates":[116.05732,24.59945],"type":"Point"}
}