{
  "type": "Feature",
  "properties": {
    "gn:admin1_code":"26.0",
    "gn:asciiname":"Guangounaoshang",
    "gn:country_code":"CN",
    "gn:dem":1158,
    "gn:feature_class":"P",
    "gn:feature_code":"PPL",
    "gn:name":"Guangounaoshang",
    "gn:population":0,
    "gn:timezone":"Asia/Shanghai",
    "iso:country":"CN",
    "name:zho_x_preferred":[
        "\u704c\u6c9f\u8111\u4e0a"
    ],
    "wof:name":"Guangounaoshang",
    "wof:placetype":"locality"
},
  "geometry": {"coordinates":[108.82732,32.43212],"type":"Point"}
}