{
  "type": "Feature",
  "properties": {
    "gn:admin1_code":"18",
    "gn:asciiname":"Yutang",
    "gn:country_code":"CN",
    "gn:dem":1849,
    "gn:feature_class":"P",
    "gn:feature_code":"PPL",
    "gn:name":"Yutang",
    "gn:population":0,
    "gn:timezone":"Asia/Shanghai",
    "iso:country":"CN",
    "name:zho_x_preferred":[
        "\u9c7c\u5858"
    ],
    "wof:name":"Yutang",
    "wof:placetype":"locality"
},
  "geometry": {"coordinates":[104.84399999999999,26.4986],"type":"Point"}
}