{
  "type": "Feature",
  "properties": {
    "gn:admin1_code":"11.0",
    "gn:asciiname":"Xiaozichong",
    "gn:country_code":"CN",
    "gn:dem":120,
    "gn:feature_class":"P",
    "gn:feature_code":"PPL",
    "gn:name":"Xiaozichong",
    "gn:population":0,
    "gn:timezone":"Asia/Shanghai",
    "iso:country":"CN",
    "name:zho_x_preferred":[
        "\u5b5d\u5b50\u51b2"
    ],
    "wof:name":"Xiaozichong",
    "wof:placetype":"locality"
},
  "geometry": {"coordinates":[113.38495,26.90051],"type":"Point"}
}