{
  "type": "Feature",
  "properties": {
    "gn:admin1_code":"04",
    "gn:asciiname":"Jinjiazhai",
    "gn:country_code":"CN",
    "gn:dem":1,
    "gn:feature_class":"P",
    "gn:feature_code":"PPL",
    "gn:name":"Jinjiazhai",
    "gn:population":0,
    "gn:timezone":"Asia/Shanghai",
    "iso:country":"CN",
    "name:und_x_variant":[
        "Chin-chia",
        "Jinjiazhai",
        "\u91d1\u5bb6\u5b85"
    ],
    "wof:name":"Jinjiazhai",
    "wof:placetype":"locality"
},
  "geometry": {"coordinates":[121.17447,31.55577000000001],"type":"Point"}
}