{
  "type": "Feature",
  "properties": {
    "gn:admin1_code":"7.0",
    "gn:asciiname":"Sijiaoqiu",
    "gn:country_code":"CN",
    "gn:dem":471,
    "gn:feature_class":"P",
    "gn:feature_code":"PPL",
    "gn:name":"Sijiaoqiu",
    "gn:population":0,
    "gn:timezone":"Asia/Shanghai",
    "iso:country":"CN",
    "name:zho_x_preferred":[
        "\u56db\u89d2\u4e18"
    ],
    "wof:name":"Sijiaoqiu",
    "wof:placetype":"locality"
},
  "geometry": {"coordinates":[118.79559,26.48667],"type":"Point"}
}