{
  "type": "Feature",
  "properties": {
    "gn:admin1_code":"8.0",
    "gn:asciiname":"Jiangyong Qingtun",
    "gn:country_code":"CN",
    "gn:dem":202,
    "gn:feature_class":"P",
    "gn:feature_code":"PPL",
    "gn:name":"Jiangyong Qingtun",
    "gn:population":0,
    "gn:timezone":"Asia/Shanghai",
    "iso:country":"CN",
    "name:zho_x_preferred":[
        "\u59dc\u6c38\u6e05\u5c6f"
    ],
    "wof:name":"Jiangyong Qingtun",
    "wof:placetype":"locality"
},
  "geometry": {"coordinates":[123.99787000000001,48.2129],"type":"Point"}
}