{
  "type": "Feature",
  "properties": {
    "gn:admin1_code":"15.0",
    "gn:asciiname":"Yujiashan",
    "gn:country_code":"CN",
    "gn:dem":2137,
    "gn:feature_class":"P",
    "gn:feature_code":"PPL",
    "gn:name":"Yujiashan",
    "gn:population":0,
    "gn:timezone":"Asia/Shanghai",
    "iso:country":"CN",
    "name:zho_x_preferred":[
        "\u4f59\u5bb6\u5c71"
    ],
    "wof:name":"Yujiashan",
    "wof:placetype":"locality"
},
  "geometry": {"coordinates":[104.7754,33.92151],"type":"Point"}
}