{
  "type": "Feature",
  "properties": {
    "gn:admin1_code":"29",
    "gn:asciiname":"Zhekuang",
    "gn:country_code":"CN",
    "gn:dem":1294,
    "gn:feature_class":"P",
    "gn:feature_code":"PPL",
    "gn:name":"Zhekuang",
    "gn:population":0,
    "gn:timezone":"Asia/Shanghai",
    "iso:country":"CN",
    "name:zho_x_preferred":[
        "\u8005\u51b5"
    ],
    "wof:name":"Zhekuang",
    "wof:placetype":"locality"
},
  "geometry": {"coordinates":[104.995,24.0857],"type":"Point"}
}