{
  "type": "Feature",
  "properties": {
    "gn:admin1_code":"26.0",
    "gn:asciiname":"Wangzewancun",
    "gn:country_code":"CN",
    "gn:dem":1109,
    "gn:feature_class":"P",
    "gn:feature_code":"PPL",
    "gn:name":"Wangzewancun",
    "gn:population":0,
    "gn:timezone":"Asia/Shanghai",
    "iso:country":"CN",
    "name:zho_x_preferred":[
        "\u738b\u5219\u6e7e\u6751"
    ],
    "wof:name":"Wangzewancun",
    "wof:placetype":"locality"
},
  "geometry": {"coordinates":[109.69819,38.39218],"type":"Point"}
}