{
  "type": "Feature",
  "properties": {
    "gn:admin1_code":"11.0",
    "gn:asciiname":"Chendi Yashang",
    "gn:country_code":"CN",
    "gn:dem":565,
    "gn:feature_class":"P",
    "gn:feature_code":"PPL",
    "gn:name":"Chendi Yashang",
    "gn:population":0,
    "gn:timezone":"Asia/Shanghai",
    "iso:country":"CN",
    "name:zho_x_preferred":[
        "\u9648\u5824\u57ad\u4e0a"
    ],
    "wof:name":"Chendi Yashang",
    "wof:placetype":"locality"
},
  "geometry": {"coordinates":[110.94495999999999,28.49665],"type":"Point"}
}