{
  "type": "Feature",
  "properties": {
    "gn:admin1_code":"33.0",
    "gn:asciiname":"Qujiage",
    "gn:country_code":"CN",
    "gn:dem":443,
    "gn:feature_class":"P",
    "gn:feature_code":"PPL",
    "gn:name":"Qujiage",
    "gn:population":0,
    "gn:timezone":"Asia/Shanghai",
    "iso:country":"CN",
    "name:zho_x_preferred":[
        "\u5c48\u5bb6\u9601"
    ],
    "wof:name":"Qujiage",
    "wof:placetype":"locality"
},
  "geometry": {"coordinates":[109.20744999999999,28.57979000000001],"type":"Point"}
}