{
  "type": "Feature",
  "properties": {
    "gn:admin1_code":"21.0",
    "gn:asciiname":"Tuhuanggounao",
    "gn:country_code":"CN",
    "gn:dem":1935,
    "gn:feature_class":"P",
    "gn:feature_code":"PPL",
    "gn:name":"Tuhuanggounao",
    "gn:population":0,
    "gn:timezone":"Asia/Shanghai",
    "iso:country":"CN",
    "name:und_x_variant":[
        "\u571f\u9ec4\u6c9f\u57b4"
    ],
    "name:zho_x_preferred":[
        "\u571f\u9ec4\u6c9f\u57b4"
    ],
    "wof:name":"Tuhuanggounao",
    "wof:placetype":"locality"
},
  "geometry": {"coordinates":[105.79858,35.82936],"type":"Point"}
}