{
  "type": "Feature",
  "properties": {
    "gn:admin1_code":"14.0",
    "gn:asciiname":"Zuoxicun",
    "gn:country_code":"CN",
    "gn:dem":4299,
    "gn:feature_class":"P",
    "gn:feature_code":"PPL",
    "gn:name":"Zuoxicun",
    "gn:population":0,
    "gn:timezone":"Asia/Urumqi",
    "iso:country":"CN",
    "name:zho_x_preferred":[
        "\u5de6\u897f\u6751"
    ],
    "wof:name":"Zuoxicun",
    "wof:placetype":"locality"
},
  "geometry": {"coordinates":[96.43850999999999,30.36108],"type":"Point"}
}