{
  "type": "Feature",
  "properties": {
    "gn:admin1_code":"32.0",
    "gn:asciiname":"Rubo",
    "gn:country_code":"CN",
    "gn:dem":3482,
    "gn:feature_class":"P",
    "gn:feature_code":"PPL",
    "gn:name":"Rubo",
    "gn:population":0,
    "gn:timezone":"Asia/Shanghai",
    "iso:country":"CN",
    "name:zho_x_preferred":[
        "\u5982\u6ce2"
    ],
    "wof:name":"Rubo",
    "wof:placetype":"locality"
},
  "geometry": {"coordinates":[101.04300000000001,30.7762],"type":"Point"}
}