{
  "type": "Feature",
  "properties": {
    "gn:admin1_code":"29.0",
    "gn:asciiname":"Baluo",
    "gn:country_code":"CN",
    "gn:dem":968,
    "gn:feature_class":"P",
    "gn:feature_code":"PPL",
    "gn:name":"Baluo",
    "gn:population":0,
    "gn:timezone":"Asia/Shanghai",
    "iso:country":"CN",
    "name:zho_x_preferred":[
        "\u5df4\u7f57"
    ],
    "wof:name":"Baluo",
    "wof:placetype":"locality"
},
  "geometry": {"coordinates":[101.31,21.7097],"type":"Point"}
}