{
  "type": "Feature",
  "properties": {
    "gn:admin1_code":"4.0",
    "gn:asciiname":"Qianhuang",
    "gn:country_code":"CN",
    "gn:dem":6,
    "gn:feature_class":"P",
    "gn:feature_code":"PPL",
    "gn:name":"Qianhuang",
    "gn:population":0,
    "gn:timezone":"Asia/Shanghai",
    "iso:country":"CN",
    "name:zho_x_preferred":[
        "Qianhuang"
    ],
    "name:zho_x_variant":[
        "\u524d\u7687",
        "\u524d\u9ec4\u9547"
    ],
    "wof:name":"Qianhuang",
    "wof:placetype":"locality"
},
  "geometry": {"coordinates":[119.41611,33.83936],"type":"Point"}
}