{
  "type": "Feature",
  "properties": {
    "gn:admin1_code":"3.0",
    "gn:asciiname":"Xinwuli",
    "gn:country_code":"CN",
    "gn:dem":503,
    "gn:feature_class":"P",
    "gn:feature_code":"PPL",
    "gn:name":"Xinwuli",
    "gn:population":0,
    "gn:timezone":"Asia/Shanghai",
    "iso:country":"CN",
    "name:und_x_variant":[
        "\u65b0\u5c4b\u91cc"
    ],
    "wof:name":"Xinwuli",
    "wof:placetype":"locality"
},
  "geometry": {"coordinates":[115.42350999999999,25.73207],"type":"Point"}
}