{
  "type": "Feature",
  "properties": {
    "gn:admin1_code":"24",
    "gn:asciiname":"Hubei",
    "gn:country_code":"CN",
    "gn:dem":1552,
    "gn:feature_class":"P",
    "gn:feature_code":"PPLA4",
    "gn:name":"Hubei",
    "gn:population":0,
    "gn:timezone":"Asia/Shanghai",
    "iso:country":"CN",
    "name:rus_x_preferred":[
        "\u0425\u0443\u0431\u044d\u0439"
    ],
    "name:und_x_variant":[
        "Hu-pei-ts\u2019un",
        "Hu-pei",
        "Hubei",
        "\u864e\u5317",
        "Hubei Xiang",
        "\u864e\u5317\u4e61"
    ],
    "wof:name":"Hubei",
    "wof:placetype":"locality"
},
  "geometry": {"coordinates":[112.01143999999999,38.99842],"type":"Point"}
}