{
  "type": "Feature",
  "properties": {
    "gn:admin1_code":"8.0",
    "gn:asciiname":"Bacuocun",
    "gn:country_code":"CN",
    "gn:dem":187,
    "gn:feature_class":"P",
    "gn:feature_code":"PPL",
    "gn:name":"Bacuocun",
    "gn:population":0,
    "gn:timezone":"Asia/Shanghai",
    "iso:country":"CN",
    "name:zho_x_preferred":[
        "\u516b\u64ae\u6751"
    ],
    "wof:name":"Bacuocun",
    "wof:placetype":"locality"
},
  "geometry": {"coordinates":[125.5224,46.14696],"type":"Point"}
}