{
  "type": "Feature",
  "properties": {
    "gn:admin1_code":"32.0",
    "gn:asciiname":"Shaofangwan",
    "gn:country_code":"CN",
    "gn:dem":443,
    "gn:feature_class":"P",
    "gn:feature_code":"PPL",
    "gn:name":"Shaofangwan",
    "gn:population":0,
    "gn:timezone":"Asia/Shanghai",
    "iso:country":"CN",
    "name:zho_x_preferred":[
        "\u70e7\u623f\u6e7e"
    ],
    "wof:name":"Shaofangwan",
    "wof:placetype":"locality"
},
  "geometry": {"coordinates":[104.8323,31.24048],"type":"Point"}
}