{
  "type": "Feature",
  "properties": {
    "gn:admin1_code":"24.0",
    "gn:asciiname":"Heilonghecun",
    "gn:country_code":"CN",
    "gn:dem":966,
    "gn:feature_class":"P",
    "gn:feature_code":"PPL",
    "gn:name":"Heilonghecun",
    "gn:population":0,
    "gn:timezone":"Asia/Shanghai",
    "iso:country":"CN",
    "name:zho_x_preferred":[
        "\u9ed1\u9f99\u6cb3\u6751"
    ],
    "wof:name":"Heilonghecun",
    "wof:placetype":"locality"
},
  "geometry": {"coordinates":[114.18716999999999,39.44578],"type":"Point"}
}