{
  "type": "Feature",
  "properties": {
    "gn:admin1_code":"10",
    "gn:asciiname":"Manhantu",
    "gn:country_code":"CN",
    "gn:dem":1121,
    "gn:feature_class":"P",
    "gn:feature_code":"PPL",
    "gn:name":"Manhantu",
    "gn:population":0,
    "gn:timezone":"Asia/Shanghai",
    "iso:country":"CN",
    "name:zho_x_preferred":[
        "\u6ee1\u6c49\u571f"
    ],
    "wof:name":"Manhantu",
    "wof:placetype":"locality"
},
  "geometry": {"coordinates":[117.52097999999999,42.08603],"type":"Point"}
}