{
  "type": "Feature",
  "properties": {
    "gn:admin1_code":"19.0",
    "gn:asciiname":"Xiaojia Buzicun",
    "gn:country_code":"CN",
    "gn:dem":228,
    "gn:feature_class":"P",
    "gn:feature_code":"PPL",
    "gn:name":"Xiaojia Buzicun",
    "gn:population":0,
    "gn:timezone":"Asia/Shanghai",
    "iso:country":"CN",
    "name:zho_x_preferred":[
        "\u8096\u5bb6\u5821\u5b50\u6751"
    ],
    "wof:name":"Xiaojia Buzicun",
    "wof:placetype":"locality"
},
  "geometry": {"coordinates":[124.599,40.6447],"type":"Point"}
}