{
  "type": "Feature",
  "properties": {
    "gn:admin1_code":"10",
    "gn:asciiname":"Jiangyingzi",
    "gn:country_code":"CN",
    "gn:dem":710,
    "gn:feature_class":"P",
    "gn:feature_code":"PPL",
    "gn:name":"Jiangyingzi",
    "gn:population":0,
    "gn:timezone":"Asia/Shanghai",
    "iso:country":"CN",
    "name:zho_x_preferred":[
        "\u59dc\u8425\u5b50"
    ],
    "wof:name":"Jiangyingzi",
    "wof:placetype":"locality"
},
  "geometry": {"coordinates":[116.88234,41.21486],"type":"Point"}
}