{
  "type": "Feature",
  "properties": {
    "gn:admin1_code":"20.0",
    "gn:asciiname":"Mingdeng",
    "gn:country_code":"CN",
    "gn:dem":1434,
    "gn:feature_class":"P",
    "gn:feature_code":"PPL",
    "gn:name":"Mingdeng",
    "gn:population":0,
    "gn:timezone":"Asia/Shanghai",
    "iso:country":"CN",
    "name:und_x_variant":[
        "\u660e\u706f"
    ],
    "wof:name":"Mingdeng",
    "wof:placetype":"locality"
},
  "geometry": {"coordinates":[110.12520000000001,40.97085],"type":"Point"}
}