{
  "type": "Feature",
  "properties": {
    "gn:admin1_code":"2.0",
    "gn:asciiname":"Qudou",
    "gn:country_code":"CN",
    "gn:dem":101,
    "gn:feature_class":"P",
    "gn:feature_code":"PPL",
    "gn:name":"Qudou",
    "gn:population":0,
    "gn:timezone":"Asia/Shanghai",
    "iso:country":"CN",
    "name:zho_x_preferred":[
        "\u66f2\u6597"
    ],
    "wof:name":"Qudou",
    "wof:placetype":"locality"
},
  "geometry": {"coordinates":[119.15622,29.26433],"type":"Point"}
}