{
  "type": "Feature",
  "properties": {
    "gn:admin1_code":"12.0",
    "gn:asciiname":"Baomaochong",
    "gn:country_code":"CN",
    "gn:dem":216,
    "gn:feature_class":"P",
    "gn:feature_code":"PPL",
    "gn:name":"Baomaochong",
    "gn:population":0,
    "gn:timezone":"Asia/Shanghai",
    "iso:country":"CN",
    "name:zho_x_preferred":[
        "\u82de\u8305\u51b2"
    ],
    "wof:name":"Baomaochong",
    "wof:placetype":"locality"
},
  "geometry": {"coordinates":[115.76076999999999,30.96317],"type":"Point"}
}