{
  "type": "Feature",
  "properties": {
    "gn:admin1_code":"6.0",
    "gn:asciiname":"Dongte",
    "gn:country_code":"CN",
    "gn:dem":4050,
    "gn:feature_class":"P",
    "gn:feature_code":"PPL",
    "gn:name":"Dongte",
    "gn:population":0,
    "gn:timezone":"Asia/Urumqi",
    "iso:country":"CN",
    "name:zho_x_preferred":[
        "\u51ac\u7279"
    ],
    "wof:name":"Dongte",
    "wof:placetype":"locality"
},
  "geometry": {"coordinates":[95.91968,33.91785],"type":"Point"}
}