{
  "type": "Feature",
  "properties": {
    "gn:admin1_code":"24.0",
    "gn:asciiname":"Donggoumencun",
    "gn:country_code":"CN",
    "gn:dem":1209,
    "gn:feature_class":"P",
    "gn:feature_code":"PPL",
    "gn:name":"Donggoumencun",
    "gn:population":0,
    "gn:timezone":"Asia/Shanghai",
    "iso:country":"CN",
    "name:zho_x_preferred":[
        "\u4e1c\u6c9f\u95e8\u6751"
    ],
    "wof:name":"Donggoumencun",
    "wof:placetype":"locality"
},
  "geometry": {"coordinates":[110.94907000000001,35.82683],"type":"Point"}
}