{
  "type": "Feature",
  "properties": {
    "gn:admin1_code":"12.0",
    "gn:asciiname":"Baxianqiao",
    "gn:country_code":"CN",
    "gn:dem":1585,
    "gn:feature_class":"P",
    "gn:feature_code":"PPL",
    "gn:name":"Baxianqiao",
    "gn:population":0,
    "gn:timezone":"Asia/Shanghai",
    "iso:country":"CN",
    "name:zho_x_preferred":[
        "\u516b\u4ed9\u6865"
    ],
    "wof:name":"Baxianqiao",
    "wof:placetype":"locality"
},
  "geometry": {"coordinates":[109.82978,30.1284],"type":"Point"}
}