{
  "type": "Feature",
  "properties": {
    "gn:admin1_code":"30.0",
    "gn:asciiname":"Funancun",
    "gn:country_code":"CN",
    "gn:dem":347,
    "gn:feature_class":"P",
    "gn:feature_code":"PPL",
    "gn:name":"Funancun",
    "gn:population":0,
    "gn:timezone":"Asia/Shanghai",
    "iso:country":"CN",
    "name:zho_x_preferred":[
        "\u798f\u5357\u6751"
    ],
    "wof:name":"Funancun",
    "wof:placetype":"locality"
},
  "geometry": {"coordinates":[116.69646000000002,23.9073],"type":"Point"}
}