{
  "type": "Feature",
  "properties": {
    "gn:admin1_code":"4.0",
    "gn:asciiname":"Changgoushao",
    "gn:country_code":"CN",
    "gn:dem":6,
    "gn:feature_class":"P",
    "gn:feature_code":"PPL",
    "gn:name":"Changgoushao",
    "gn:population":0,
    "gn:timezone":"Asia/Shanghai",
    "iso:country":"CN",
    "name:zho_x_preferred":[
        "\u957f\u6c9f\u7a0d"
    ],
    "wof:name":"Changgoushao",
    "wof:placetype":"locality"
},
  "geometry": {"coordinates":[119.76482,32.01305],"type":"Point"}
}