{
  "type": "Feature",
  "properties": {
    "gn:admin1_code":"30.0",
    "gn:asciiname":"Chaotangcun",
    "gn:country_code":"CN",
    "gn:dem":417,
    "gn:feature_class":"P",
    "gn:feature_code":"PPL",
    "gn:name":"Chaotangcun",
    "gn:population":0,
    "gn:timezone":"Asia/Shanghai",
    "iso:country":"CN",
    "name:zho_x_preferred":[
        "\u6f6e\u5858\u6751"
    ],
    "wof:name":"Chaotangcun",
    "wof:placetype":"locality"
},
  "geometry": {"coordinates":[116.16871999999999,24.3631],"type":"Point"}
}