{
  "type": "Feature",
  "properties": {
    "gn:admin1_code":"02",
    "gn:asciiname":"Shanchangcun",
    "gn:country_code":"CN",
    "gn:dem":22,
    "gn:feature_class":"P",
    "gn:feature_code":"PPL",
    "gn:name":"Shanchangcun",
    "gn:population":0,
    "gn:timezone":"Asia/Shanghai",
    "iso:country":"CN",
    "name:und_x_variant":[
        "Shanchang",
        "Shanchangcun"
    ],
    "name:zho_x_preferred":[
        "Shan-ch\u2019ang-shih"
    ],
    "name:zho_x_variant":[
        "\u5c71\u573a",
        "\u5c71\u573a\u6751"
    ],
    "wof:name":"Shanchangcun",
    "wof:placetype":"locality"
},
  "geometry": {"coordinates":[121.51612,28.87004],"type":"Point"}
}