{
  "type": "Feature",
  "properties": {
    "gn:admin1_code":"18",
    "gn:asciiname":"Wuken",
    "gn:country_code":"CN",
    "gn:dem":727,
    "gn:feature_class":"P",
    "gn:feature_code":"PPL",
    "gn:name":"Wuken",
    "gn:population":0,
    "gn:timezone":"Asia/Shanghai",
    "iso:country":"CN",
    "name:zho_x_preferred":[
        "\u52a1\u57a6"
    ],
    "wof:name":"Wuken",
    "wof:placetype":"locality"
},
  "geometry": {"coordinates":[109.158,25.7904],"type":"Point"}
}