{
  "type": "Feature",
  "properties": {
    "gn:admin1_code":"30.0",
    "gn:asciiname":"Weichangxia",
    "gn:country_code":"CN",
    "gn:dem":103,
    "gn:feature_class":"P",
    "gn:feature_code":"PPL",
    "gn:name":"Weichangxia",
    "gn:population":0,
    "gn:timezone":"Asia/Shanghai",
    "iso:country":"CN",
    "name:zho_x_preferred":[
        "\u56f4\u573a\u5413"
    ],
    "wof:name":"Weichangxia",
    "wof:placetype":"locality"
},
  "geometry": {"coordinates":[113.70358,23.43822],"type":"Point"}
}