{
  "type": "Feature",
  "properties": {
    "gn:admin1_code":"30",
    "gn:asciiname":"Luoxi",
    "gn:country_code":"CN",
    "gn:dem":-3,
    "gn:feature_class":"P",
    "gn:feature_code":"PPL",
    "gn:name":"Luoxi",
    "gn:population":0,
    "gn:timezone":"Asia/Shanghai",
    "iso:country":"CN",
    "name:und_x_variant":[
        "\u6d1b\u6eaa"
    ],
    "wof:name":"Luoxi",
    "wof:placetype":"locality"
},
  "geometry": {"coordinates":[113.28366,23.0505],"type":"Point"}
}