{
  "type": "Feature",
  "properties": {
    "gn:admin1_code":"7",
    "gn:asciiname":"Liwu",
    "gn:country_code":"CN",
    "gn:dem":781,
    "gn:feature_class":"P",
    "gn:feature_code":"PPLA4",
    "gn:name":"Liwu",
    "gn:population":0,
    "gn:timezone":"Asia/Shanghai",
    "iso:country":"CN",
    "name:und_x_variant":[
        "Liwu Xiang",
        "\u674e\u5c4b\u4e61"
    ],
    "name:zho_x_preferred":[
        "\u674e\u5c4b"
    ],
    "wof:name":"Liwu",
    "wof:placetype":"locality"
},
  "geometry": {"coordinates":[116.86917,25.64917],"type":"Point"}
}