{
  "type": "Feature",
  "properties": {
    "gn:admin1_code":"4.0",
    "gn:asciiname":"Gaojiawa",
    "gn:country_code":"CN",
    "gn:dem":22,
    "gn:feature_class":"P",
    "gn:feature_code":"PPL",
    "gn:name":"Gaojiawa",
    "gn:population":0,
    "gn:timezone":"Asia/Shanghai",
    "iso:country":"CN",
    "name:zho_x_preferred":[
        "\u9ad8\u5bb6\u6d3c"
    ],
    "wof:name":"Gaojiawa",
    "wof:placetype":"locality"
},
  "geometry": {"coordinates":[118.72871000000001,32.21874],"type":"Point"}
}