{
  "type": "Feature",
  "properties": {
    "gn:admin1_code":"24.0",
    "gn:asciiname":"Wanhu",
    "gn:country_code":"CN",
    "gn:dem":1104,
    "gn:feature_class":"P",
    "gn:feature_code":"PPL",
    "gn:name":"Wanhu",
    "gn:population":0,
    "gn:timezone":"Asia/Shanghai",
    "iso:country":"CN",
    "name:zho_x_preferred":[
        "\u4e07\u659b"
    ],
    "wof:name":"Wanhu",
    "wof:placetype":"locality"
},
  "geometry": {"coordinates":[111.35567,39.40507],"type":"Point"}
}