{
  "type": "Feature",
  "properties": {
    "gn:admin1_code":"24",
    "gn:asciiname":"Pandaoliang",
    "gn:country_code":"CN",
    "gn:dem":1995,
    "gn:feature_class":"P",
    "gn:feature_code":"PPL",
    "gn:name":"Pandaoliang",
    "gn:population":0,
    "gn:timezone":"Asia/Shanghai",
    "iso:country":"CN",
    "name:und_x_variant":[
        "P\u2019an-tao-liang",
        "Pandaoliang",
        "\u76d8\u9053\u6881"
    ],
    "wof:name":"Pandaoliang",
    "wof:placetype":"locality"
},
  "geometry": {"coordinates":[112.55925999999999,39.08487],"type":"Point"}
}