{
  "type": "Feature",
  "properties": {
    "gn:admin1_code":"10.0",
    "gn:asciiname":"Beijuyou",
    "gn:country_code":"CN",
    "gn:dem":45,
    "gn:feature_class":"P",
    "gn:feature_code":"PPL",
    "gn:name":"Beijuyou",
    "gn:population":0,
    "gn:timezone":"Asia/Shanghai",
    "iso:country":"CN",
    "name:zho_x_preferred":[
        "\u5317\u4ff1\u4f51"
    ],
    "wof:name":"Beijuyou",
    "wof:placetype":"locality"
},
  "geometry": {"coordinates":[115.069,38.2899],"type":"Point"}
}