{
  "type": "Feature",
  "properties": {
    "gn:admin1_code":"25.0",
    "gn:asciiname":"Dalu",
    "gn:country_code":"CN",
    "gn:dem":27,
    "gn:feature_class":"P",
    "gn:feature_code":"PPL",
    "gn:name":"Dal\u00fc",
    "gn:population":0,
    "gn:timezone":"Asia/Shanghai",
    "iso:country":"CN",
    "name:ceb_x_preferred":[
        "Dalu"
    ],
    "name:deu_x_preferred":[
        "Dalu"
    ],
    "name:und_x_variant":[
        "Dal\u00fc"
    ],
    "name:zho_x_preferred":[
        "\u5927\u5415"
    ],
    "wof:name":"Dalu",
    "wof:placetype":"locality"
},
  "geometry": {"coordinates":[119.80343000000001,36.34583],"type":"Point"}
}