{
  "type": "Feature",
  "properties": {
    "gn:admin1_code":"1.0",
    "gn:asciiname":"Daokoucun",
    "gn:country_code":"CN",
    "gn:dem":26,
    "gn:feature_class":"P",
    "gn:feature_code":"PPL",
    "gn:name":"Daokoucun",
    "gn:population":0,
    "gn:timezone":"Asia/Shanghai",
    "iso:country":"CN",
    "name:zho_x_preferred":[
        "\u9053\u53e3\u6751"
    ],
    "wof:name":"Daokoucun",
    "wof:placetype":"locality"
},
  "geometry": {"coordinates":[117.69537,33.75025],"type":"Point"}
}