{
  "type": "Feature",
  "properties": {
    "gn:admin1_code":"18.0",
    "gn:asciiname":"Mubiao",
    "gn:country_code":"CN",
    "gn:dem":854,
    "gn:feature_class":"P",
    "gn:feature_code":"PPL",
    "gn:name":"Mubiao",
    "gn:population":0,
    "gn:timezone":"Asia/Shanghai",
    "iso:country":"CN",
    "name:zho_x_preferred":[
        "\u6728\u8868"
    ],
    "wof:name":"Mubiao",
    "wof:placetype":"locality"
},
  "geometry": {"coordinates":[107.483,26.3076],"type":"Point"}
}