{
  "type": "Feature",
  "properties": {
    "gn:admin1_code":"10",
    "gn:asciiname":"Te-sheng-kou",
    "gn:country_code":"CN",
    "gn:dem":1271,
    "gn:feature_class":"P",
    "gn:feature_code":"PPL",
    "gn:name":"Te-sheng-kou",
    "gn:population":0,
    "gn:timezone":"Asia/Shanghai",
    "iso:country":"CN",
    "wof:name":"Te-sheng-kou",
    "wof:placetype":"locality"
},
  "geometry": {"coordinates":[117.42055999999999,42.10972],"type":"Point"}
}