{
  "type": "Feature",
  "properties": {
    "gn:admin1_code":"24.0",
    "gn:asciiname":"Xingzhuang",
    "gn:country_code":"CN",
    "gn:dem":1167,
    "gn:feature_class":"P",
    "gn:feature_code":"PPL",
    "gn:name":"Xingzhuang",
    "gn:population":0,
    "gn:timezone":"Asia/Shanghai",
    "iso:country":"CN",
    "name:zho_x_preferred":[
        "\u5211\u5e84"
    ],
    "wof:name":"Xingzhuang",
    "wof:placetype":"locality"
},
  "geometry": {"coordinates":[111.97512999999999,35.94284000000001],"type":"Point"}
}