{
  "type": "Feature",
  "properties": {
    "gn:admin1_code":"1.0",
    "gn:asciiname":"Zhangmangcun",
    "gn:country_code":"CN",
    "gn:dem":40,
    "gn:feature_class":"P",
    "gn:feature_code":"PPL",
    "gn:name":"Zhangmangcun",
    "gn:population":0,
    "gn:timezone":"Asia/Shanghai",
    "iso:country":"CN",
    "name:zho_x_preferred":[
        "\u5f20\u5fd9\u6751"
    ],
    "wof:name":"Zhangmangcun",
    "wof:placetype":"locality"
},
  "geometry": {"coordinates":[115.34990999999999,33.41909],"type":"Point"}
}