{
  "type": "Feature",
  "properties": {
    "gn:admin1_code":"18",
    "gn:asciiname":"Danjiazhai",
    "gn:country_code":"CN",
    "gn:dem":545,
    "gn:feature_class":"P",
    "gn:feature_code":"PPL",
    "gn:name":"Danjiazhai",
    "gn:population":0,
    "gn:timezone":"Asia/Shanghai",
    "iso:country":"CN",
    "name:zho_x_preferred":[
        "\u4f46\u5bb6\u5be8"
    ],
    "wof:name":"Danjiazhai",
    "wof:placetype":"locality"
},
  "geometry": {"coordinates":[108.208,27.9437],"type":"Point"}
}