{
  "type": "Feature",
  "properties": {
    "gn:admin1_code":"26.0",
    "gn:asciiname":"Quanziwan",
    "gn:country_code":"CN",
    "gn:dem":1053,
    "gn:feature_class":"P",
    "gn:feature_code":"PPL",
    "gn:name":"Quanziwan",
    "gn:population":0,
    "gn:timezone":"Asia/Shanghai",
    "iso:country":"CN",
    "name:zho_x_preferred":[
        "\u6cc9\u5b50\u6e7e"
    ],
    "wof:name":"Quanziwan",
    "wof:placetype":"locality"
},
  "geometry": {"coordinates":[109.43943,35.31993],"type":"Point"}
}