{
  "type": "Feature",
  "properties": {
    "gn:admin1_code":"12.0",
    "gn:asciiname":"Min'anji",
    "gn:country_code":"CN",
    "gn:dem":55,
    "gn:feature_class":"P",
    "gn:feature_code":"PPL",
    "gn:name":"Min\u2019anji",
    "gn:population":0,
    "gn:timezone":"Asia/Shanghai",
    "iso:country":"CN",
    "name:und_x_variant":[
        "Min\u2019anji"
    ],
    "name:zho_x_preferred":[
        "\u6c11\u5b89\u96c6"
    ],
    "wof:name":"Min'anji",
    "wof:placetype":"locality"
},
  "geometry": {"coordinates":[114.23475999999999,30.9779],"type":"Point"}
}