{
  "type": "Feature",
  "properties": {
    "gn:admin1_code":"7",
    "gn:asciiname":"Tingtou",
    "gn:country_code":"CN",
    "gn:dem":282,
    "gn:feature_class":"P",
    "gn:feature_code":"PPL",
    "gn:name":"Tingtou",
    "gn:population":0,
    "gn:timezone":"Asia/Shanghai",
    "iso:country":"CN",
    "name:und_x_variant":[
        "\u4ead\u5934"
    ],
    "wof:name":"Tingtou",
    "wof:placetype":"locality"
},
  "geometry": {"coordinates":[116.18083,25.3271],"type":"Point"}
}