{
  "type": "Feature",
  "properties": {
    "gn:admin1_code":"26.0",
    "gn:asciiname":"Wuligou",
    "gn:country_code":"CN",
    "gn:dem":596,
    "gn:feature_class":"P",
    "gn:feature_code":"PPL",
    "gn:name":"Wuligou",
    "gn:population":0,
    "gn:timezone":"Asia/Shanghai",
    "iso:country":"CN",
    "name:und_x_variant":[
        "\u4e94\u91cc\u6c9f"
    ],
    "wof:name":"Wuligou",
    "wof:placetype":"locality"
},
  "geometry": {"coordinates":[107.05204000000001,32.92559],"type":"Point"}
}