{
  "type": "Feature",
  "properties": {
    "gn:admin1_code":"3.0",
    "gn:asciiname":"Shiliutang",
    "gn:country_code":"CN",
    "gn:dem":375,
    "gn:feature_class":"P",
    "gn:feature_code":"PPL",
    "gn:name":"Shiliutang",
    "gn:population":0,
    "gn:timezone":"Asia/Shanghai",
    "iso:country":"CN",
    "name:und_x_variant":[
        "\u77f3\u6d41\u5858"
    ],
    "wof:name":"Shiliutang",
    "wof:placetype":"locality"
},
  "geometry": {"coordinates":[115.85057999999999,26.63043],"type":"Point"}
}