{
  "type": "Feature",
  "properties": {
    "gn:admin1_code":"12.0",
    "gn:asciiname":"Gumianhe",
    "gn:country_code":"CN",
    "gn:dem":121,
    "gn:feature_class":"P",
    "gn:feature_code":"PPL",
    "gn:name":"Gumianhe",
    "gn:population":0,
    "gn:timezone":"Asia/Shanghai",
    "iso:country":"CN",
    "name:und_x_variant":[
        "\u53e4\u5e99\u6cb3"
    ],
    "wof:name":"Gumianhe",
    "wof:placetype":"locality"
},
  "geometry": {"coordinates":[115.50864,30.6698],"type":"Point"}
}