{
  "type": "Feature",
  "properties": {
    "gn:admin1_code":"5.0",
    "gn:asciiname":"Shangyoufangdong",
    "gn:country_code":"CN",
    "gn:dem":445,
    "gn:feature_class":"P",
    "gn:feature_code":"PPL",
    "gn:name":"Shangyoufangdong",
    "gn:population":0,
    "gn:timezone":"Asia/Shanghai",
    "iso:country":"CN",
    "name:und_x_variant":[
        "\u4e0a\u6cb9\u623f\u6d1e"
    ],
    "wof:name":"Shangyoufangdong",
    "wof:placetype":"locality"
},
  "geometry": {"coordinates":[129.58826999999999,43.69461],"type":"Point"}
}