{
  "type": "Feature",
  "properties": {
    "gn:admin1_code":"10.0",
    "gn:asciiname":"Dongyejiamiao",
    "gn:country_code":"CN",
    "gn:dem":10,
    "gn:feature_class":"P",
    "gn:feature_code":"PPL",
    "gn:name":"Dongyejiamiao",
    "gn:population":0,
    "gn:timezone":"Asia/Shanghai",
    "iso:country":"CN",
    "name:zho_x_preferred":[
        "\u4e1c\u53f6\u5bb6\u5e99"
    ],
    "wof:name":"Dongyejiamiao",
    "wof:placetype":"locality"
},
  "geometry": {"coordinates":[116.887,38.1979],"type":"Point"}
}