{
  "type": "Feature",
  "properties": {
    "gn:admin1_code":"32.0",
    "gn:asciiname":"Xiashanzui",
    "gn:country_code":"CN",
    "gn:dem":367,
    "gn:feature_class":"P",
    "gn:feature_code":"PPL",
    "gn:name":"Xiashanzui",
    "gn:population":0,
    "gn:timezone":"Asia/Shanghai",
    "iso:country":"CN",
    "name:zho_x_preferred":[
        "\u4e0b\u5c71\u5634"
    ],
    "wof:name":"Xiashanzui",
    "wof:placetype":"locality"
},
  "geometry": {"coordinates":[105.76599,30.6075],"type":"Point"}
}