{
  "type": "Feature",
  "properties": {
    "gn:admin1_code":"30",
    "gn:asciiname":"Rongtang",
    "gn:country_code":"CN",
    "gn:dem":22,
    "gn:feature_class":"P",
    "gn:feature_code":"PPL",
    "gn:name":"Rongtang",
    "gn:population":0,
    "gn:timezone":"Asia/Urumqi",
    "iso:country":"CN",
    "name:zho_x_preferred":[
        "\u6995\u5858"
    ],
    "wof:name":"Rongtang",
    "wof:placetype":"locality"
},
  "geometry": {"coordinates":[110.59226,21.70495],"type":"Point"}
}