{
  "type": "Feature",
  "properties": {
    "gn:admin1_code":"29.0",
    "gn:asciiname":"Mangguan",
    "gn:country_code":"CN",
    "gn:dem":1537,
    "gn:feature_class":"P",
    "gn:feature_code":"PPL",
    "gn:name":"Mangguan",
    "gn:population":0,
    "gn:timezone":"Asia/Shanghai",
    "iso:country":"CN",
    "name:zho_x_preferred":[
        "\u8292\u5173"
    ],
    "wof:name":"Mangguan",
    "wof:placetype":"locality"
},
  "geometry": {"coordinates":[99.6157,23.3694],"type":"Point"}
}