{
  "type": "Feature",
  "properties": {
    "gn:admin1_code":"5.0",
    "gn:asciiname":"Shanzui Yidui",
    "gn:country_code":"CN",
    "gn:dem":205,
    "gn:feature_class":"P",
    "gn:feature_code":"PPLF",
    "gn:name":"Shanzui Yidui",
    "gn:population":0,
    "gn:timezone":"Asia/Shanghai",
    "iso:country":"CN",
    "name:zho_x_preferred":[
        "\u5c71\u5480\u4e00\u961f"
    ],
    "wof:name":"Shanzui Yidui",
    "wof:placetype":"locality"
},
  "geometry": {"coordinates":[125.93702999999999,44.09848],"type":"Point"}
}