{
  "type": "Feature",
  "properties": {
    "gn:admin1_code":"18.0",
    "gn:asciiname":"Majiang",
    "gn:country_code":"CN",
    "gn:dem":869,
    "gn:feature_class":"P",
    "gn:feature_code":"PPL",
    "gn:name":"Majiang",
    "gn:population":0,
    "gn:timezone":"Asia/Shanghai",
    "iso:country":"CN",
    "name:ceb_x_preferred":[
        "Majiang"
    ],
    "name:deu_x_preferred":[
        "Majiang"
    ],
    "name:zho_x_preferred":[
        "\u9ebb\u6c5f"
    ],
    "wof:name":"Majiang",
    "wof:placetype":"locality"
},
  "geometry": {"coordinates":[107.682,25.4454],"type":"Point"}
}