{
  "type": "Feature",
  "properties": {
    "gn:admin1_code":"6.0",
    "gn:asciiname":"Laiyu",
    "gn:country_code":"CN",
    "gn:dem":3018,
    "gn:feature_class":"P",
    "gn:feature_code":"PPL",
    "gn:name":"Laiyu",
    "gn:population":0,
    "gn:timezone":"Asia/Shanghai",
    "iso:country":"CN",
    "name:und_x_variant":[
        "\u6765\u7389"
    ],
    "wof:name":"Laiyu",
    "wof:placetype":"locality"
},
  "geometry": {"coordinates":[102.03277,35.72843],"type":"Point"}
}