{
  "type": "Feature",
  "properties": {
    "gn:admin1_code":"32.0",
    "gn:asciiname":"Shawan",
    "gn:country_code":"CN",
    "gn:dem":2273,
    "gn:feature_class":"P",
    "gn:feature_code":"PPL",
    "gn:name":"Shawan",
    "gn:population":0,
    "gn:timezone":"Asia/Shanghai",
    "iso:country":"CN",
    "name:ceb_x_preferred":[
        "Shawan"
    ],
    "name:deu_x_preferred":[
        "Shawan"
    ],
    "name:fra_x_preferred":[
        "Shawan"
    ],
    "name:nor_x_preferred":[
        "Shawan"
    ],
    "name:rus_x_preferred":[
        "\u0428\u0430\u0432\u0430\u043d\u044c"
    ],
    "name:swe_x_preferred":[
        "Shawan"
    ],
    "name:ukr_x_preferred":[
        "\u0428\u0430\u0432\u0430\u043d\u044c"
    ],
    "name:zho_x_preferred":[
        "\u6c99\u6e7e"
    ],
    "wof:name":"Shawan",
    "wof:placetype":"locality"
},
  "geometry": {"coordinates":[103.714,32.0677],"type":"Point"}
}