{
  "type": "Feature",
  "properties": {
    "gn:admin1_code":"4.0",
    "gn:asciiname":"Tangzhangcun",
    "gn:country_code":"CN",
    "gn:dem":29,
    "gn:feature_class":"P",
    "gn:feature_code":"PPL",
    "gn:name":"Tangzhangcun",
    "gn:population":0,
    "gn:timezone":"Asia/Shanghai",
    "iso:country":"CN",
    "name:zho_x_preferred":[
        "\u68e0\u5f20\u6751"
    ],
    "wof:name":"Tangzhangcun",
    "wof:placetype":"locality"
},
  "geometry": {"coordinates":[117.25749,34.14706],"type":"Point"}
}