{
  "type": "Feature",
  "properties": {
    "gn:admin1_code":"1.0",
    "gn:asciiname":"Houwangcun",
    "gn:country_code":"CN",
    "gn:dem":40,
    "gn:feature_class":"P",
    "gn:feature_code":"PPL",
    "gn:name":"Houwangcun",
    "gn:population":0,
    "gn:timezone":"Asia/Shanghai",
    "iso:country":"CN",
    "name:zho_x_preferred":[
        "\u540e\u738b\u6751"
    ],
    "wof:name":"Houwangcun",
    "wof:placetype":"locality"
},
  "geometry": {"coordinates":[117.82246000000001,32.45818],"type":"Point"}
}