{
  "type": "Feature",
  "properties": {
    "gn:admin1_code":"2.0",
    "gn:asciiname":"Xiaojiang",
    "gn:country_code":"CN",
    "gn:dem":5,
    "gn:feature_class":"P",
    "gn:feature_code":"PPL",
    "gn:name":"Xiaojiang",
    "gn:population":0,
    "gn:timezone":"Asia/Shanghai",
    "iso:country":"CN",
    "name:und_x_variant":[
        "Hsiao-chiang",
        "Xiaojiang"
    ],
    "name:zho_x_preferred":[
        "\u8427\u6c5f"
    ],
    "wof:name":"Xiaojiang",
    "wof:placetype":"locality"
},
  "geometry": {"coordinates":[120.47506,27.56341],"type":"Point"}
}