{
  "type": "Feature",
  "properties": {
    "gn:admin1_code":"30",
    "gn:asciiname":"Jianzai'ao",
    "gn:country_code":"CN",
    "gn:dem":628,
    "gn:feature_class":"P",
    "gn:feature_code":"PPL",
    "gn:name":"Jianzai\u2019ao",
    "gn:population":0,
    "gn:timezone":"Asia/Shanghai",
    "iso:country":"CN",
    "name:und_x_variant":[
        "\u7bad\u4ed4\u51f9",
        "Jianzai\u2019ao"
    ],
    "wof:name":"Jianzai'ao",
    "wof:placetype":"locality"
},
  "geometry": {"coordinates":[116.46559000000001,24.20125],"type":"Point"}
}