{
  "type": "Feature",
  "properties": {
    "gn:admin1_code":"9",
    "gn:asciiname":"Menlouwang",
    "gn:country_code":"CN",
    "gn:dem":54,
    "gn:feature_class":"P",
    "gn:feature_code":"PPL",
    "gn:name":"Menlouwang",
    "gn:population":0,
    "gn:timezone":"Asia/Shanghai",
    "iso:country":"CN",
    "name:zho_x_preferred":[
        "\u95e8\u697c\u738b"
    ],
    "wof:name":"Menlouwang",
    "wof:placetype":"locality"
},
  "geometry": {"coordinates":[115.22,34.1116],"type":"Point"}
}