{
  "type": "Feature",
  "properties": {
    "gn:admin1_code":"3.0",
    "gn:asciiname":"Hongsiqiao",
    "gn:country_code":"CN",
    "gn:dem":61,
    "gn:feature_class":"P",
    "gn:feature_code":"PPL",
    "gn:name":"Hongsiqiao",
    "gn:population":0,
    "gn:timezone":"Asia/Shanghai",
    "iso:country":"CN",
    "name:und_x_variant":[
        "\u6d2a\u6cd7\u6865"
    ],
    "wof:name":"Hongsiqiao",
    "wof:placetype":"locality"
},
  "geometry": {"coordinates":[116.72614,27.97642],"type":"Point"}
}