{
  "type": "Feature",
  "properties": {
    "gn:admin1_code":"26",
    "gn:asciiname":"Xiqiao",
    "gn:country_code":"CN",
    "gn:dem":414,
    "gn:feature_class":"P",
    "gn:feature_code":"PPL",
    "gn:name":"Xiqiao",
    "gn:population":0,
    "gn:timezone":"Asia/Shanghai",
    "iso:country":"CN",
    "name:ceb_x_preferred":[
        "Xiqiao"
    ],
    "name:swe_x_preferred":[
        "Xiqiao"
    ],
    "name:und_x_variant":[
        "\u897f\u6865"
    ],
    "name:zho_x_preferred":[
        "\u897f\u6865"
    ],
    "wof:name":"Xiqiao",
    "wof:placetype":"locality"
},
  "geometry": {"coordinates":[108.30861000000002,34.21944000000001],"type":"Point"}
}