{
  "type": "Feature",
  "properties": {
    "gn:admin1_code":"26.0",
    "gn:asciiname":"Luoshugounao",
    "gn:country_code":"CN",
    "gn:dem":915,
    "gn:feature_class":"P",
    "gn:feature_code":"PPL",
    "gn:name":"Luoshugounao",
    "gn:population":0,
    "gn:timezone":"Asia/Shanghai",
    "iso:country":"CN",
    "name:zho_x_preferred":[
        "\u843d\u68b3\u6c9f\u8111"
    ],
    "wof:name":"Luoshugounao",
    "wof:placetype":"locality"
},
  "geometry": {"coordinates":[110.49081,33.55671],"type":"Point"}
}