{
  "type": "Feature",
  "properties": {
    "gn:admin1_code":"12.0",
    "gn:asciiname":"Xiangyuan",
    "gn:country_code":"CN",
    "gn:dem":1354,
    "gn:feature_class":"P",
    "gn:feature_code":"PPL",
    "gn:name":"Xiangyuan",
    "gn:population":0,
    "gn:timezone":"Asia/Shanghai",
    "iso:country":"CN",
    "name:zho_x_preferred":[
        "\u9999\u56ed"
    ],
    "wof:name":"Xiangyuan",
    "wof:placetype":"locality"
},
  "geometry": {"coordinates":[108.77412,30.45913],"type":"Point"}
}