{
  "type": "Feature",
  "properties": {
    "gn:admin1_code":"12.0",
    "gn:asciiname":"Heshimiao",
    "gn:country_code":"CN",
    "gn:dem":752,
    "gn:feature_class":"P",
    "gn:feature_code":"PPL",
    "gn:name":"Heshimiao",
    "gn:population":0,
    "gn:timezone":"Asia/Shanghai",
    "iso:country":"CN",
    "name:zho_x_preferred":[
        "\u79be\u77f3\u5e99"
    ],
    "wof:name":"Heshimiao",
    "wof:placetype":"locality"
},
  "geometry": {"coordinates":[110.75458999999999,32.39615],"type":"Point"}
}