{
  "type": "Feature",
  "properties": {
    "gn:admin1_code":"02",
    "gn:asciiname":"Shanhecun",
    "gn:country_code":"CN",
    "gn:dem":6,
    "gn:feature_class":"P",
    "gn:feature_code":"PPL",
    "gn:name":"Shanhecun",
    "gn:population":0,
    "gn:timezone":"Asia/Shanghai",
    "iso:country":"CN",
    "name:und_x_variant":[
        "Shanhe"
    ],
    "name:zho_x_preferred":[
        "\u5c71\u6cb3\u6751"
    ],
    "wof:name":"Shanhecun",
    "wof:placetype":"locality"
},
  "geometry": {"coordinates":[121.39673000000001,28.40289000000001],"type":"Point"}
}