{
  "type": "Feature",
  "properties": {
    "gn:admin1_code":"4.0",
    "gn:asciiname":"Chudian",
    "gn:country_code":"CN",
    "gn:dem":6,
    "gn:feature_class":"P",
    "gn:feature_code":"PPL",
    "gn:name":"Chudian",
    "gn:population":0,
    "gn:timezone":"Asia/Shanghai",
    "iso:country":"CN",
    "name:zho_x_preferred":[
        "\u891a\u5e97"
    ],
    "wof:name":"Chudian",
    "wof:placetype":"locality"
},
  "geometry": {"coordinates":[120.00843999999999,31.47625],"type":"Point"}
}