{
  "type": "Feature",
  "properties": {
    "gn:admin1_code":"29.0",
    "gn:asciiname":"Daxingpo",
    "gn:country_code":"CN",
    "gn:dem":1261,
    "gn:feature_class":"P",
    "gn:feature_code":"PPL",
    "gn:name":"Daxingpo",
    "gn:population":0,
    "gn:timezone":"Asia/Shanghai",
    "iso:country":"CN",
    "name:zho_x_preferred":[
        "\u5927\u5174\u5761"
    ],
    "wof:name":"Daxingpo",
    "wof:placetype":"locality"
},
  "geometry": {"coordinates":[100.539,22.7263],"type":"Point"}
}