{
  "type": "Feature",
  "properties": {
    "gn:admin1_code":"10",
    "gn:asciiname":"Dasanyanjing",
    "gn:country_code":"CN",
    "gn:dem":1535,
    "gn:feature_class":"P",
    "gn:feature_code":"PPL",
    "gn:name":"Dasanyanjing",
    "gn:population":0,
    "gn:timezone":"Asia/Shanghai",
    "iso:country":"CN",
    "name:und_x_variant":[
        "Ta-san-yen-ching",
        "Dasanyanjing"
    ],
    "name:zho_x_preferred":[
        "\u5927\u4e09\u773c\u4e95"
    ],
    "wof:name":"Dasanyanjing",
    "wof:placetype":"locality"
},
  "geometry": {"coordinates":[115.33007000000001,41.32646],"type":"Point"}
}