{
  "type": "Feature",
  "properties": {
    "gn:admin1_code":"4.0",
    "gn:asciiname":"Xingyicun",
    "gn:country_code":"CN",
    "gn:dem":6,
    "gn:feature_class":"P",
    "gn:feature_code":"PPL",
    "gn:name":"Xingyicun",
    "gn:population":0,
    "gn:timezone":"Asia/Shanghai",
    "iso:country":"CN",
    "name:zho_x_preferred":[
        "\u5174\u4e49\u6751"
    ],
    "wof:name":"Xingyicun",
    "wof:placetype":"locality"
},
  "geometry": {"coordinates":[118.80627,34.16968],"type":"Point"}
}