{
  "type": "Feature",
  "properties": {
    "gn:admin1_code":"30.0",
    "gn:asciiname":"Xinyu",
    "gn:country_code":"CN",
    "gn:dem":22,
    "gn:feature_class":"P",
    "gn:feature_code":"PPL",
    "gn:name":"Xinyu",
    "gn:population":0,
    "gn:timezone":"Asia/Shanghai",
    "iso:country":"CN",
    "name:ara_x_preferred":[
        "\u0634\u064a\u0646\u064a\u0648"
    ],
    "name:cdo_x_preferred":[
        "S\u012dng-\u1e73\u0300"
    ],
    "name:ceb_x_preferred":[
        "Xinyu"
    ],
    "name:ces_x_preferred":[
        "Sin-j\u00fc"
    ],
    "name:dan_x_preferred":[
        "Xinyu"
    ],
    "name:deu_x_preferred":[
        "Xinyu"
    ],
    "name:eus_x_preferred":[
        "Xinyu"
    ],
    "name:fas_x_preferred":[
        "\u0634\u06cc\u0646\u06cc\u0648"
    ],
    "name:fin_x_preferred":[
        "Xinyu"
    ],
    "name:fra_x_preferred":[
        "Xinyu"
    ],
    "name:hak_x_preferred":[
        "S\u00een-y\u00ec-s\u1e73"
    ],
    "name:ita_x_preferred":[
        "Xinyu"
    ],
    "name:jpn_x_preferred":[
        "\u65b0\u4f59\u5e02"
    ],
    "name:kik_x_preferred":[
        "Xinyu"
    ],
    "name:kor_x_preferred":[
        "\uc2e0\uc704\uc2dc"
    ],
    "name:mlg_x_preferred":[
        "Xinyu"
    ],
    "name:nld_x_preferred":[
        "Xinyu"
    ],
    "name:nno_x_preferred":[
        "Xinyu"
    ],
    "name:nor_x_preferred":[
        "Xinyu"
    ],
    "name:pol_x_preferred":[
        "Xinyu"
    ],
    "name:rus_x_preferred":[
        "\u0421\u0438\u043d\u044c\u044e\u0439"
    ],
    "name:spa_x_preferred":[
        "Xinyu"
    ],
    "name:swe_x_preferred":[
        "Xinyu"
    ],
    "name:tur_x_preferred":[
        "Xinyu"
    ],
    "name:urd_x_preferred":[
        "\u0634\u06cc\u0646\u06cc\u0648"
    ],
    "name:vie_x_preferred":[
        "T\u00e2n D\u01b0"
    ],
    "name:war_x_preferred":[
        "Xinyu"
    ],
    "name:wuu_x_preferred":[
        "\u65b0\u4f59\u5e02"
    ],
    "name:zho_x_preferred":[
        "\u65b0\u4f59"
    ],
    "name:zho_x_variant":[
        "\u65b0\u4f59\u5e02"
    ],
    "wof:name":"Xinyu",
    "wof:placetype":"locality"
},
  "geometry": {"coordinates":[112.70090999999999,22.27236],"type":"Point"}
}