{
  "type": "Feature",
  "properties": {
    "gn:admin1_code":"29.0",
    "gn:asciiname":"Wangzuo",
    "gn:country_code":"CN",
    "gn:dem":1426,
    "gn:feature_class":"P",
    "gn:feature_code":"PPL",
    "gn:name":"Wangzuo",
    "gn:population":0,
    "gn:timezone":"Asia/Shanghai",
    "iso:country":"CN",
    "name:zho_x_preferred":[
        "\u738b\u4f50"
    ],
    "wof:name":"Wangzuo",
    "wof:placetype":"locality"
},
  "geometry": {"coordinates":[100.02500000000001,24.9785],"type":"Point"}
}