{
  "type": "Feature",
  "properties": {
    "gn:admin1_code":"19.0",
    "gn:asciiname":"Xihougou",
    "gn:country_code":"CN",
    "gn:dem":133,
    "gn:feature_class":"P",
    "gn:feature_code":"PPL",
    "gn:name":"Xihougou",
    "gn:population":0,
    "gn:timezone":"Asia/Shanghai",
    "iso:country":"CN",
    "name:zho_x_preferred":[
        "\u897f\u540e\u6c9f"
    ],
    "wof:name":"Xihougou",
    "wof:placetype":"locality"
},
  "geometry": {"coordinates":[124.285,42.541],"type":"Point"}
}