{
  "type": "Feature",
  "properties": {
    "gn:admin1_code":"15.0",
    "gn:asciiname":"Balang",
    "gn:country_code":"CN",
    "gn:dem":2604,
    "gn:feature_class":"P",
    "gn:feature_code":"PPL",
    "gn:name":"Balang",
    "gn:population":0,
    "gn:timezone":"Asia/Shanghai",
    "iso:country":"CN",
    "name:und_x_variant":[
        "\u516b\u90ce"
    ],
    "wof:name":"Balang",
    "wof:placetype":"locality"
},
  "geometry": {"coordinates":[104.50479,34.34144000000001],"type":"Point"}
}