{
  "type": "Feature",
  "properties": {
    "gn:admin1_code":"23",
    "gn:asciiname":"Shen-hsing-ch'ien",
    "gn:country_code":"CN",
    "gn:dem":5,
    "gn:feature_class":"P",
    "gn:feature_code":"PPL",
    "gn:name":"Shen-hsing-ch\u2019ien",
    "gn:population":0,
    "gn:timezone":"Asia/Shanghai",
    "iso:country":"CN",
    "wof:name":"Shen-hsing-ch'ien",
    "wof:placetype":"locality"
},
  "geometry": {"coordinates":[121.51222,30.93583],"type":"Point"}
}