{
  "type": "Feature",
  "properties": {
    "gn:admin1_code":"8.0",
    "gn:asciiname":"Guangxingcun",
    "gn:country_code":"CN",
    "gn:dem":205,
    "gn:feature_class":"P",
    "gn:feature_code":"PPL",
    "gn:name":"Guangxingcun",
    "gn:population":0,
    "gn:timezone":"Asia/Shanghai",
    "iso:country":"CN",
    "name:zho_x_preferred":[
        "\u5149\u661f\u6751"
    ],
    "wof:name":"Guangxingcun",
    "wof:placetype":"locality"
},
  "geometry": {"coordinates":[125.62690000000001,47.25394],"type":"Point"}
}