{
  "type": "Feature",
  "properties": {
    "gn:admin1_code":"29.0",
    "gn:asciiname":"Muduo",
    "gn:country_code":"CN",
    "gn:dem":2109,
    "gn:feature_class":"P",
    "gn:feature_code":"PPL",
    "gn:name":"Muduo",
    "gn:population":0,
    "gn:timezone":"Asia/Shanghai",
    "iso:country":"CN",
    "name:zho_x_preferred":[
        "\u6728\u591a"
    ],
    "wof:name":"Muduo",
    "wof:placetype":"locality"
},
  "geometry": {"coordinates":[103.236,25.8403],"type":"Point"}
}