{
  "type": "Feature",
  "properties": {
    "gn:admin1_code":"24",
    "gn:asciiname":"Fengrun",
    "gn:cc2":"CN",
    "gn:country_code":"CN",
    "gn:dem":1160,
    "gn:feature_class":"P",
    "gn:feature_code":"PPL",
    "gn:name":"Fengrun",
    "gn:population":0,
    "gn:timezone":"Asia/Shanghai",
    "iso:country":"CN",
    "name:und_x_variant":[
        "Feng-jun",
        "Feng-jun-ts\u2019un",
        "Fengrun"
    ],
    "wof:name":"Fengrun",
    "wof:placetype":"locality"
},
  "geometry": {"coordinates":[111.86139,38.23722],"type":"Point"}
}