{
  "type": "Feature",
  "properties": {
    "gn:admin1_code":"3.0",
    "gn:asciiname":"Yangfancun",
    "gn:country_code":"CN",
    "gn:dem":26,
    "gn:feature_class":"P",
    "gn:feature_code":"PPL",
    "gn:name":"Yangfancun",
    "gn:population":0,
    "gn:timezone":"Asia/Shanghai",
    "iso:country":"CN",
    "name:und_x_variant":[
        "\u79e7\u7548\u6751"
    ],
    "wof:name":"Yangfancun",
    "wof:placetype":"locality"
},
  "geometry": {"coordinates":[116.88805000000001,28.35196],"type":"Point"}
}