{
  "type": "Feature",
  "properties": {
    "gn:admin1_code":"24.0",
    "gn:asciiname":"Laoyaotoucun",
    "gn:country_code":"CN",
    "gn:dem":767,
    "gn:feature_class":"P",
    "gn:feature_code":"PPL",
    "gn:name":"Laoyaotoucun",
    "gn:population":0,
    "gn:timezone":"Asia/Shanghai",
    "iso:country":"CN",
    "name:zho_x_preferred":[
        "\u8001\u7a91\u5934\u6751"
    ],
    "wof:name":"Laoyaotoucun",
    "wof:placetype":"locality"
},
  "geometry": {"coordinates":[110.68323999999998,35.75683],"type":"Point"}
}