{
  "type": "Feature",
  "properties": {
    "gn:admin1_code":"11.0",
    "gn:asciiname":"Tongshan",
    "gn:country_code":"CN",
    "gn:dem":59,
    "gn:feature_class":"P",
    "gn:feature_code":"PPL",
    "gn:name":"Tongshan",
    "gn:population":0,
    "gn:timezone":"Asia/Shanghai",
    "iso:country":"CN",
    "name:ceb_x_preferred":[
        "Tongshan"
    ],
    "name:deu_x_preferred":[
        "Tongshan"
    ],
    "name:fra_x_preferred":[
        "Tongshan"
    ],
    "name:mlg_x_preferred":[
        "Tongshan"
    ],
    "name:nor_x_preferred":[
        "Tongshan"
    ],
    "name:rus_x_preferred":[
        "\u0422\u0443\u043d\u0448\u0430\u043d\u044c"
    ],
    "name:swe_x_preferred":[
        "Tongshan"
    ],
    "name:zho_x_preferred":[
        "\u6850\u5c71"
    ],
    "wof:name":"Tongshan",
    "wof:placetype":"locality"
},
  "geometry": {"coordinates":[112.64643,26.97138],"type":"Point"}
}