{
  "type": "Feature",
  "properties": {
    "gn:admin1_code":"4.0",
    "gn:asciiname":"Xinyang",
    "gn:country_code":"CN",
    "gn:dem":3,
    "gn:feature_class":"P",
    "gn:feature_code":"PPL",
    "gn:name":"Xinyang",
    "gn:population":0,
    "gn:timezone":"Asia/Shanghai",
    "iso:country":"CN",
    "name:und_x_variant":[
        "\u65b0\u6d0b"
    ],
    "name:zho_x_preferred":[
        "\u65b0\u6d0b"
    ],
    "wof:name":"Xinyang",
    "wof:placetype":"locality"
},
  "geometry": {"coordinates":[120.14093,32.93249],"type":"Point"}
}