{
  "type": "Feature",
  "properties": {
    "gn:admin1_code":"16.0",
    "gn:asciiname":"Jiangcheng",
    "gn:country_code":"CN",
    "gn:dem":48,
    "gn:feature_class":"P",
    "gn:feature_code":"PPL",
    "gn:name":"Jiangcheng",
    "gn:population":0,
    "gn:timezone":"Asia/Shanghai",
    "iso:country":"CN",
    "name:ceb_x_preferred":[
        "Jiangcheng"
    ],
    "name:deu_x_preferred":[
        "Jiangcheng"
    ],
    "name:fra_x_preferred":[
        "Jiangcheng"
    ],
    "name:zho_x_preferred":[
        "\u6c5f\u57ce"
    ],
    "wof:name":"Jiangcheng",
    "wof:placetype":"locality"
},
  "geometry": {"coordinates":[109.755,23.1002],"type":"Point"}
}