{
  "type": "Feature",
  "properties": {
    "gn:admin1_code":"9.0",
    "gn:asciiname":"Dalu",
    "gn:country_code":"CN",
    "gn:dem":230,
    "gn:feature_class":"P",
    "gn:feature_code":"PPL",
    "gn:name":"Dalu",
    "gn:population":0,
    "gn:timezone":"Asia/Shanghai",
    "iso:country":"CN",
    "name:zho_x_preferred":[
        "\u5927\u8def"
    ],
    "wof:name":"Dalu",
    "wof:placetype":"locality"
},
  "geometry": {"coordinates":[111.58913,33.08123],"type":"Point"}
}