{
  "type": "Feature",
  "properties": {
    "gn:admin1_code":"32.0",
    "gn:asciiname":"Taiwuji",
    "gn:country_code":"CN",
    "gn:dem":671,
    "gn:feature_class":"P",
    "gn:feature_code":"PPL",
    "gn:name":"Taiwuji",
    "gn:population":0,
    "gn:timezone":"Asia/Shanghai",
    "iso:country":"CN",
    "name:zho_x_preferred":[
        "\u80ce\u5c4b\u810a"
    ],
    "wof:name":"Taiwuji",
    "wof:placetype":"locality"
},
  "geometry": {"coordinates":[107.73096,31.82835],"type":"Point"}
}