{
  "type": "Feature",
  "properties": {
    "gn:admin1_code":"3",
    "gn:asciiname":"Bankeng",
    "gn:country_code":"CN",
    "gn:dem":272,
    "gn:feature_class":"P",
    "gn:feature_code":"PPL",
    "gn:name":"Bankeng",
    "gn:population":0,
    "gn:timezone":"Asia/Shanghai",
    "iso:country":"CN",
    "name:zho_x_preferred":[
        "\u5742\u5751"
    ],
    "wof:name":"Bankeng",
    "wof:placetype":"locality"
},
  "geometry": {"coordinates":[114.39863,26.43777],"type":"Point"}
}