{
  "type": "Feature",
  "properties": {
    "gn:admin1_code":"4.0",
    "gn:asciiname":"Wuniucun",
    "gn:country_code":"CN",
    "gn:dem":4,
    "gn:feature_class":"P",
    "gn:feature_code":"PPL",
    "gn:name":"Wuniucun",
    "gn:population":0,
    "gn:timezone":"Asia/Shanghai",
    "iso:country":"CN",
    "name:zho_x_preferred":[
        "\u90ac\u725b\u6751"
    ],
    "wof:name":"Wuniucun",
    "wof:placetype":"locality"
},
  "geometry": {"coordinates":[119.86713,32.72748],"type":"Point"}
}