{
  "type": "Feature",
  "properties": {
    "gn:admin1_code":"7.0",
    "gn:asciiname":"Daxie",
    "gn:country_code":"CN",
    "gn:dem":1310,
    "gn:feature_class":"P",
    "gn:feature_code":"PPL",
    "gn:name":"Daxie",
    "gn:population":0,
    "gn:timezone":"Asia/Shanghai",
    "iso:country":"CN",
    "name:zho_x_preferred":[
        "\u5927\u659c"
    ],
    "wof:name":"Daxie",
    "wof:placetype":"locality"
},
  "geometry": {"coordinates":[116.88337,25.36873],"type":"Point"}
}