{
  "type": "Feature",
  "properties": {
    "gn:admin1_code":"26.0",
    "gn:asciiname":"Dongsanyaocun",
    "gn:country_code":"CN",
    "gn:dem":440,
    "gn:feature_class":"P",
    "gn:feature_code":"PPL",
    "gn:name":"Dongsanyaocun",
    "gn:population":0,
    "gn:timezone":"Asia/Shanghai",
    "iso:country":"CN",
    "name:zho_x_preferred":[
        "\u4e1c\u4e09\u723b\u6751"
    ],
    "wof:name":"Dongsanyaocun",
    "wof:placetype":"locality"
},
  "geometry": {"coordinates":[108.94376,34.18766],"type":"Point"}
}