{
  "type": "Feature",
  "properties": {
    "gn:admin1_code":"1.0",
    "gn:asciiname":"Wangdiancun",
    "gn:country_code":"CN",
    "gn:dem":28,
    "gn:feature_class":"P",
    "gn:feature_code":"PPL",
    "gn:name":"Wangdiancun",
    "gn:population":0,
    "gn:timezone":"Asia/Shanghai",
    "iso:country":"CN",
    "name:zho_x_preferred":[
        "\u738b\u5e97\u6751"
    ],
    "wof:name":"Wangdiancun",
    "wof:placetype":"locality"
},
  "geometry": {"coordinates":[116.55389,32.53607],"type":"Point"}
}