{
  "type": "Feature",
  "properties": {
    "gn:admin1_code":"8.0",
    "gn:asciiname":"Sunhuatun",
    "gn:country_code":"CN",
    "gn:dem":142,
    "gn:feature_class":"P",
    "gn:feature_code":"PPL",
    "gn:name":"Sunhuatun",
    "gn:population":0,
    "gn:timezone":"Asia/Shanghai",
    "iso:country":"CN",
    "name:zho_x_preferred":[
        "\u5b59\u82b1\u5c6f"
    ],
    "wof:name":"Sunhuatun",
    "wof:placetype":"locality"
},
  "geometry": {"coordinates":[128.02846,45.85878],"type":"Point"}
}