{
  "type": "Feature",
  "properties": {
    "gn:admin1_code":"9.0",
    "gn:asciiname":"Haitangba",
    "gn:country_code":"CN",
    "gn:dem":1504,
    "gn:feature_class":"P",
    "gn:feature_code":"PPL",
    "gn:name":"Haitangba",
    "gn:population":0,
    "gn:timezone":"Asia/Shanghai",
    "iso:country":"CN",
    "name:zho_x_preferred":[
        "\u6d77\u5802\u6252"
    ],
    "wof:name":"Haitangba",
    "wof:placetype":"locality"
},
  "geometry": {"coordinates":[111.19963,33.79753],"type":"Point"}
}