{
  "type": "Feature",
  "properties": {
    "gn:country":"CN",
    "gn:fcode":"ADM3",
    "gn:pop":0,
    "iso:country":"CN",
    "name:eng_x_preferred":[
        "Wenling County"
    ],
    "name:zho_x_preferred":[
        "Wenling Xian"
    ],
    "name:zho_x_variant":[
        "\u6e29\u5cad\u5e02",
        "\u6e29\u5cad"
    ],
    "qs:name":"Wenling Shi",
    "qs:photos_9r":0,
    "qs:photos_sr":0,
    "qs:pop_sr":"0",
    "wd:wordcount":550,
    "wof:name":"Wenling Shi",
    "wof:placetype":"localadmin",
    "wof:population":0
},
  "geometry": {"coordinates":[121.4075,28.3982],"type":"Point"}
}