{
  "type": "Feature",
  "properties": {
    "gn:admin1_code":"29.0",
    "gn:asciiname":"Lugaoba",
    "gn:country_code":"CN",
    "gn:dem":1188,
    "gn:feature_class":"P",
    "gn:feature_code":"PPL",
    "gn:name":"Lugaoba",
    "gn:population":0,
    "gn:timezone":"Asia/Shanghai",
    "iso:country":"CN",
    "name:zho_x_preferred":[
        "\u82a6\u641e\u575d"
    ],
    "wof:name":"Lugaoba",
    "wof:placetype":"locality"
},
  "geometry": {"coordinates":[99.4849,23.6148],"type":"Point"}
}