{
  "type": "Feature",
  "properties": {
    "gn:admin1_code":"33.0",
    "gn:asciiname":"Yangping",
    "gn:country_code":"CN",
    "gn:dem":497,
    "gn:feature_class":"P",
    "gn:feature_code":"PPL",
    "gn:name":"Yangping",
    "gn:population":0,
    "gn:timezone":"Asia/Shanghai",
    "iso:country":"CN",
    "name:ceb_x_preferred":[
        "Yangping"
    ],
    "name:swe_x_preferred":[
        "Yangping"
    ],
    "name:zho_x_preferred":[
        "\u9633\u576a"
    ],
    "wof:name":"Yangping",
    "wof:placetype":"locality"
},
  "geometry": {"coordinates":[107.64173999999998,30.3521],"type":"Point"}
}