{
  "type": "Feature",
  "properties": {
    "gn:admin1_code":"5.0",
    "gn:asciiname":"Yulang",
    "gn:country_code":"CN",
    "gn:dem":492,
    "gn:feature_class":"P",
    "gn:feature_code":"PPL",
    "gn:name":"Yulang",
    "gn:population":0,
    "gn:timezone":"Asia/Shanghai",
    "iso:country":"CN",
    "name:und_x_variant":[
        "\u6e14\u6d6a",
        "Yulangcun",
        "\u6e14\u6d6a\u6751"
    ],
    "wof:name":"Yulang",
    "wof:placetype":"locality"
},
  "geometry": {"coordinates":[128.93896999999998,42.68812],"type":"Point"}
}