{
  "type": "Feature",
  "properties": {
    "gn:admin1_code":"4.0",
    "gn:asciiname":"Guanzhuangcun",
    "gn:country_code":"CN",
    "gn:dem":5,
    "gn:feature_class":"P",
    "gn:feature_code":"PPL",
    "gn:name":"Guanzhuangcun",
    "gn:population":0,
    "gn:timezone":"Asia/Shanghai",
    "iso:country":"CN",
    "name:zho_x_preferred":[
        "\u5b98\u5e84\u6751"
    ],
    "wof:name":"Guanzhuangcun",
    "wof:placetype":"locality"
},
  "geometry": {"coordinates":[120.2983,32.26783],"type":"Point"}
}