{
  "type": "Feature",
  "properties": {
    "gn:admin1_code":"24.0",
    "gn:asciiname":"Qianqiancun",
    "gn:country_code":"CN",
    "gn:dem":999,
    "gn:feature_class":"P",
    "gn:feature_code":"PPL",
    "gn:name":"Qianqiancun",
    "gn:population":0,
    "gn:timezone":"Asia/Shanghai",
    "iso:country":"CN",
    "name:und_x_variant":[
        "\u5343\u5343\u6751"
    ],
    "name:zho_x_preferred":[
        "\u5343\u5343\u6751"
    ],
    "wof:name":"Qianqiancun",
    "wof:placetype":"locality"
},
  "geometry": {"coordinates":[113.49836999999999,39.95439],"type":"Point"}
}