{
  "type": "Feature",
  "properties": {
    "gn:admin1_code":"8.0",
    "gn:asciiname":"Rongshengcun",
    "gn:country_code":"CN",
    "gn:dem":84,
    "gn:feature_class":"P",
    "gn:feature_code":"PPL",
    "gn:name":"Rongshengcun",
    "gn:population":0,
    "gn:timezone":"Asia/Shanghai",
    "iso:country":"CN",
    "name:zho_x_preferred":[
        "\u8363\u5347\u6751"
    ],
    "wof:name":"Rongshengcun",
    "wof:placetype":"locality"
},
  "geometry": {"coordinates":[129.94200000000001,46.76011],"type":"Point"}
}