{
  "type": "Feature",
  "properties": {
    "gn:admin1_code":"5.0",
    "gn:asciiname":"Wudao Yingzi Wopu",
    "gn:country_code":"CN",
    "gn:dem":163,
    "gn:feature_class":"P",
    "gn:feature_code":"PPL",
    "gn:name":"Wudao Yingzi Wopu",
    "gn:population":0,
    "gn:timezone":"Asia/Shanghai",
    "iso:country":"CN",
    "name:zho_x_preferred":[
        "\u4e94\u9053\u8425\u5b50\u7a9d\u94fa"
    ],
    "wof:name":"Wudao Yingzi Wopu",
    "wof:placetype":"locality"
},
  "geometry": {"coordinates":[122.33826000000001,44.31921],"type":"Point"}
}