{
  "type": "Feature",
  "properties": {
    "gn:admin1_code":"12.0",
    "gn:asciiname":"Liluoping",
    "gn:country_code":"CN",
    "gn:dem":997,
    "gn:feature_class":"P",
    "gn:feature_code":"PPL",
    "gn:name":"Liluoping",
    "gn:population":0,
    "gn:timezone":"Asia/Shanghai",
    "iso:country":"CN",
    "name:zho_x_preferred":[
        "\u68a8\u7f57\u576a"
    ],
    "wof:name":"Liluoping",
    "wof:placetype":"locality"
},
  "geometry": {"coordinates":[110.53892,31.34501],"type":"Point"}
}