{
  "type": "Feature",
  "properties": {
    "gn:admin1_code":"2.0",
    "gn:asciiname":"Jinjiadian",
    "gn:country_code":"CN",
    "gn:dem":7,
    "gn:feature_class":"P",
    "gn:feature_code":"PPL",
    "gn:name":"Jinjiadian",
    "gn:population":0,
    "gn:timezone":"Asia/Shanghai",
    "iso:country":"CN",
    "name:und_x_variant":[
        "\u91d1\u5bb6\u7538"
    ],
    "wof:name":"Jinjiadian",
    "wof:placetype":"locality"
},
  "geometry": {"coordinates":[120.21314,30.66268],"type":"Point"}
}