{
  "type": "Feature",
  "properties": {
    "gn:admin1_code":"16",
    "gn:asciiname":"Bainong",
    "gn:country_code":"CN",
    "gn:dem":140,
    "gn:feature_class":"P",
    "gn:feature_code":"PPL",
    "gn:name":"Bainong",
    "gn:population":0,
    "gn:timezone":"Asia/Shanghai",
    "iso:country":"CN",
    "name:zho_x_preferred":[
        "\u767e\u519c"
    ],
    "wof:name":"Bainong",
    "wof:placetype":"locality"
},
  "geometry": {"coordinates":[106.889,22.2936],"type":"Point"}
}