{
  "type": "Feature",
  "properties": {
    "gn:admin1_code":"18",
    "gn:asciiname":"Maojiazhai",
    "gn:country_code":"CN",
    "gn:dem":1241,
    "gn:feature_class":"P",
    "gn:feature_code":"PPL",
    "gn:name":"Maojiazhai",
    "gn:population":0,
    "gn:timezone":"Asia/Shanghai",
    "iso:country":"CN",
    "name:zho_x_preferred":[
        "\u6bdb\u5bb6\u5be8"
    ],
    "wof:name":"Maojiazhai",
    "wof:placetype":"locality"
},
  "geometry": {"coordinates":[105.31699999999999,25.1556],"type":"Point"}
}