{
  "type": "Feature",
  "properties": {
    "gn:admin1_code":"16.0",
    "gn:asciiname":"Zhelai",
    "gn:country_code":"CN",
    "gn:dem":930,
    "gn:feature_class":"P",
    "gn:feature_code":"PPL",
    "gn:name":"Zhelai",
    "gn:population":0,
    "gn:timezone":"Asia/Shanghai",
    "iso:country":"CN",
    "name:zho_x_preferred":[
        "\u8005\u6765"
    ],
    "wof:name":"Zhelai",
    "wof:placetype":"locality"
},
  "geometry": {"coordinates":[107.41500000000001,25.2663],"type":"Point"}
}