{
  "type": "Feature",
  "properties": {
    "gn:admin1_code":"33.0",
    "gn:asciiname":"Wadianzi",
    "gn:country_code":"CN",
    "gn:dem":885,
    "gn:feature_class":"P",
    "gn:feature_code":"PPL",
    "gn:name":"Wadianzi",
    "gn:population":0,
    "gn:timezone":"Asia/Shanghai",
    "iso:country":"CN",
    "name:zho_x_preferred":[
        "\u74e6\u5e97\u5b50"
    ],
    "wof:name":"Wadianzi",
    "wof:placetype":"locality"
},
  "geometry": {"coordinates":[109.64959,31.21469],"type":"Point"}
}