{
  "type": "Feature",
  "properties": {
    "gn:admin1_code":"7.0",
    "gn:asciiname":"Pingyang Nongchang",
    "gn:country_code":"CN",
    "gn:dem":118,
    "gn:feature_class":"P",
    "gn:feature_code":"PPLF",
    "gn:name":"Pingyang Nongchang",
    "gn:population":0,
    "gn:timezone":"Asia/Shanghai",
    "iso:country":"CN",
    "name:und_x_variant":[
        "\u5e73\u9633\u519c\u573a"
    ],
    "wof:name":"Pingyang Nongchang",
    "wof:placetype":"locality"
},
  "geometry": {"coordinates":[118.30466,26.90535],"type":"Point"}
}