{
  "type": "Feature",
  "properties": {
    "gn:admin1_code":"2.0",
    "gn:asciiname":"Baoshan",
    "gn:country_code":"CN",
    "gn:dem":127,
    "gn:feature_class":"P",
    "gn:feature_code":"PPL",
    "gn:name":"Baoshan",
    "gn:population":0,
    "gn:timezone":"Asia/Shanghai",
    "iso:country":"CN",
    "name:und_x_variant":[
        "\u5b9d\u5c71"
    ],
    "wof:name":"Baoshan",
    "wof:placetype":"locality"
},
  "geometry": {"coordinates":[119.7954,29.98341],"type":"Point"}
}