{
  "type": "Feature",
  "properties": {
    "gn:admin1_code":"13.0",
    "gn:asciiname":"Qili Gongbaizi",
    "gn:country_code":"CN",
    "gn:dem":3653,
    "gn:feature_class":"P",
    "gn:feature_code":"PPL",
    "gn:name":"Qili Gongbaizi",
    "gn:population":0,
    "gn:timezone":"Asia/Shanghai",
    "iso:country":"CN",
    "name:und_x_variant":[
        "\u5176\u91cc\u62f1\u62dc\u5b5c"
    ],
    "wof:name":"Qili Gongbaizi",
    "wof:placetype":"locality"
},
  "geometry": {"coordinates":[75.80041,38.13506],"type":"Point"}
}