{
  "type": "Feature",
  "properties": {
    "gn:admin1_code":"20.0",
    "gn:asciiname":"Xiaogangfang",
    "gn:country_code":"CN",
    "gn:dem":1144,
    "gn:feature_class":"P",
    "gn:feature_code":"PPL",
    "gn:name":"Xiaogangfang",
    "gn:population":0,
    "gn:timezone":"Asia/Shanghai",
    "iso:country":"CN",
    "name:und_x_variant":[
        "\u5c0f\u7f38\u623f"
    ],
    "wof:name":"Xiaogangfang",
    "wof:placetype":"locality"
},
  "geometry": {"coordinates":[111.44767,39.89306],"type":"Point"}
}