{
  "type": "Feature",
  "properties": {
    "gn:admin1_code":"7.0",
    "gn:asciiname":"Guanzhong",
    "gn:country_code":"CN",
    "gn:dem":81,
    "gn:feature_class":"P",
    "gn:feature_code":"PPL",
    "gn:name":"Guanzhong",
    "gn:population":0,
    "gn:timezone":"Asia/Shanghai",
    "iso:country":"CN",
    "name:zho_x_preferred":[
        "\u5173\u4e2d"
    ],
    "wof:name":"Guanzhong",
    "wof:placetype":"locality"
},
  "geometry": {"coordinates":[119.18461000000001,26.20861],"type":"Point"}
}