{
  "type": "Feature",
  "properties": {
    "gn:admin1_code":"7.0",
    "gn:asciiname":"Guanzhong",
    "gn:country_code":"CN",
    "gn:dem":81,
    "gn:feature_class":"P",
    "gn:feature_code":"PPL",
    "gn:name":"Guanzhong",
    "gn:population":0,
    "gn:timezone":"Asia/Shanghai",
    "iso:country":"CN",
    "name:bul_x_preferred":[
        "\u0413\u0443\u0430\u043d\u0434\u0436\u0443\u043d"
    ],
    "name:cat_x_preferred":[
        "Guanzhong"
    ],
    "name:dan_x_preferred":[
        "Guanzhongsletten"
    ],
    "name:deu_x_preferred":[
        "Zentral-Shaanxi-Ebene"
    ],
    "name:fra_x_preferred":[
        "Guanzhong"
    ],
    "name:kor_x_preferred":[
        "\uad00\uc911"
    ],
    "name:nor_x_preferred":[
        "Guanzhong"
    ],
    "name:rus_x_preferred":[
        "\u0413\u0443\u0430\u043d\u044c\u0447\u0436\u0443\u043d"
    ],
    "name:swe_x_preferred":[
        "Guanzhong"
    ],
    "name:ukr_x_preferred":[
        "\u0413\u0443\u0430\u043d\u044c\u0447\u0436\u0443\u043d"
    ],
    "name:vie_x_preferred":[
        "Quan Trung"
    ],
    "name:zho_x_preferred":[
        "\u5173\u4e2d"
    ],
    "name:zho_x_variant":[
        "\u6e2d\u6cb3\u5e73\u539f"
    ],
    "wof:name":"Guanzhong",
    "wof:placetype":"locality"
},
  "geometry": {"coordinates":[119.18461000000001,26.20861],"type":"Point"}
}