{
  "type": "Feature",
  "properties": {
    "gn:admin1_code":"9.0",
    "gn:asciiname":"Lijia Huayuan",
    "gn:country_code":"CN",
    "gn:dem":40,
    "gn:feature_class":"P",
    "gn:feature_code":"PPL",
    "gn:name":"Lijia Huayuan",
    "gn:population":0,
    "gn:timezone":"Asia/Shanghai",
    "iso:country":"CN",
    "name:zho_x_preferred":[
        "\u674e\u5bb6\u82b1\u56ed"
    ],
    "wof:name":"Lijia Huayuan",
    "wof:placetype":"locality"
},
  "geometry": {"coordinates":[115.68548,32.1533],"type":"Point"}
}