{
  "type": "Feature",
  "properties": {
    "gn:admin1_code":"29.0",
    "gn:asciiname":"Danghatu",
    "gn:country_code":"CN",
    "gn:dem":3204,
    "gn:feature_class":"P",
    "gn:feature_code":"PPL",
    "gn:name":"Danghatu",
    "gn:population":0,
    "gn:timezone":"Asia/Shanghai",
    "iso:country":"CN",
    "name:zho_x_preferred":[
        "\u6321\u54c8\u571f"
    ],
    "wof:name":"Danghatu",
    "wof:placetype":"locality"
},
  "geometry": {"coordinates":[98.4693,27.7794],"type":"Point"}
}