{
  "type": "Feature",
  "properties": {
    "gn:admin1_code":"25.0",
    "gn:asciiname":"Qinjiaguanzhuangcun",
    "gn:country_code":"CN",
    "gn:dem":44,
    "gn:feature_class":"P",
    "gn:feature_code":"PPL",
    "gn:name":"Qinjiaguanzhuangcun",
    "gn:population":0,
    "gn:timezone":"Asia/Shanghai",
    "iso:country":"CN",
    "name:zho_x_preferred":[
        "\u79e6\u5bb6\u5b98\u5e84\u6751"
    ],
    "wof:name":"Qinjiaguanzhuangcun",
    "wof:placetype":"locality"
},
  "geometry": {"coordinates":[119.56176000000001,35.50298],"type":"Point"}
}