{
  "type": "Feature",
  "properties": {
    "gn:admin1_code":"24.0",
    "gn:asciiname":"Gaojiageduo",
    "gn:country_code":"CN",
    "gn:dem":941,
    "gn:feature_class":"P",
    "gn:feature_code":"PPL",
    "gn:name":"Gaojiageduo",
    "gn:population":0,
    "gn:timezone":"Asia/Shanghai",
    "iso:country":"CN",
    "name:zho_x_preferred":[
        "\u9ad8\u5bb6\u572a\u579b"
    ],
    "wof:name":"Gaojiageduo",
    "wof:placetype":"locality"
},
  "geometry": {"coordinates":[110.57189,37.98881],"type":"Point"}
}