{
  "type": "Feature",
  "properties": {
    "gn:admin1_code":"4.0",
    "gn:asciiname":"Nanliushe",
    "gn:country_code":"CN",
    "gn:dem":3,
    "gn:feature_class":"P",
    "gn:feature_code":"PPL",
    "gn:name":"Nanliushe",
    "gn:population":0,
    "gn:timezone":"Asia/Shanghai",
    "iso:country":"CN",
    "name:zho_x_preferred":[
        "\u5357\u5218\u820d"
    ],
    "wof:name":"Nanliushe",
    "wof:placetype":"locality"
},
  "geometry": {"coordinates":[119.75297999999999,32.79987],"type":"Point"}
}