{
  "type": "Feature",
  "properties": {
    "gn:admin1_code":"16.0",
    "gn:asciiname":"Laze",
    "gn:country_code":"CN",
    "gn:dem":376,
    "gn:feature_class":"P",
    "gn:feature_code":"PPL",
    "gn:name":"Laze",
    "gn:population":0,
    "gn:timezone":"Asia/Shanghai",
    "iso:country":"CN",
    "name:bos_x_preferred":[
        "Laze"
    ],
    "name:ceb_x_preferred":[
        "Laze"
    ],
    "name:fra_x_preferred":[
        "Laze"
    ],
    "name:hrv_x_preferred":[
        "Laze"
    ],
    "name:ita_x_preferred":[
        "Laze"
    ],
    "name:nld_x_preferred":[
        "Laze"
    ],
    "name:pol_x_preferred":[
        "Laze"
    ],
    "name:sco_x_preferred":[
        "Laze"
    ],
    "name:slv_x_preferred":[
        "Laze"
    ],
    "name:srp_x_preferred":[
        "\u041b\u0430\u0437\u0435"
    ],
    "name:swe_x_preferred":[
        "Laze"
    ],
    "name:zho_x_preferred":[
        "\u62c9\u5219"
    ],
    "wof:name":"Laze",
    "wof:placetype":"locality"
},
  "geometry": {"coordinates":[107.22199999999999,24.8938],"type":"Point"}
}