{
  "type": "Feature",
  "properties": {
    "gn:admin1_code":"8.0",
    "gn:asciiname":"Minlecun",
    "gn:country_code":"CN",
    "gn:dem":275,
    "gn:feature_class":"P",
    "gn:feature_code":"PPL",
    "gn:name":"Minlecun",
    "gn:population":0,
    "gn:timezone":"Asia/Shanghai",
    "iso:country":"CN",
    "name:zho_x_preferred":[
        "\u6c11\u4e50\u6751"
    ],
    "wof:name":"Minlecun",
    "wof:placetype":"locality"
},
  "geometry": {"coordinates":[126.45449000000001,48.10966],"type":"Point"}
}