{
  "type": "Feature",
  "properties": {
    "gn:admin1_code":"7.0",
    "gn:asciiname":"Guling",
    "gn:country_code":"CN",
    "gn:dem":500,
    "gn:feature_class":"P",
    "gn:feature_code":"PPL",
    "gn:name":"Guling",
    "gn:population":0,
    "gn:timezone":"Asia/Shanghai",
    "iso:country":"CN",
    "name:und_x_variant":[
        "\u83c7\u5cad"
    ],
    "wof:name":"Guling",
    "wof:placetype":"locality"
},
  "geometry": {"coordinates":[116.87144000000001,27.01438],"type":"Point"}
}