{
  "type": "Feature",
  "properties": {
    "gn:admin1_code":"3.0",
    "gn:asciiname":"Chengshangcun",
    "gn:country_code":"CN",
    "gn:dem":31,
    "gn:feature_class":"P",
    "gn:feature_code":"PPL",
    "gn:name":"Chengshangcun",
    "gn:population":0,
    "gn:timezone":"Asia/Shanghai",
    "iso:country":"CN",
    "name:zho_x_preferred":[
        "\u57ce\u4e0a\u6751"
    ],
    "wof:name":"Chengshangcun",
    "wof:placetype":"locality"
},
  "geometry": {"coordinates":[115.32299999999999,28.1554],"type":"Point"}
}