{
  "type": "Feature",
  "properties": {
    "gn:admin1_code":"26.0",
    "gn:asciiname":"Angoucun",
    "gn:country_code":"CN",
    "gn:dem":1297,
    "gn:feature_class":"P",
    "gn:feature_code":"PPL",
    "gn:name":"Angoucun",
    "gn:population":0,
    "gn:timezone":"Asia/Shanghai",
    "iso:country":"CN",
    "name:zho_x_preferred":[
        "\u5b89\u6c9f\u6751"
    ],
    "wof:name":"Angoucun",
    "wof:placetype":"locality"
},
  "geometry": {"coordinates":[108.33158,33.19761],"type":"Point"}
}