{
  "type": "Feature",
  "properties": {
    "gn:admin1_code":"33.0",
    "gn:asciiname":"Maoling",
    "gn:country_code":"CN",
    "gn:dem":312,
    "gn:feature_class":"P",
    "gn:feature_code":"PPL",
    "gn:name":"Maoling",
    "gn:population":0,
    "gn:timezone":"Asia/Shanghai",
    "iso:country":"CN",
    "name:deu_x_preferred":[
        "Maoling-Mausoleum"
    ],
    "name:nor_x_preferred":[
        "Maolingmausoleet"
    ],
    "name:swe_x_preferred":[
        "Maoling"
    ],
    "name:zho_x_preferred":[
        "\u8305\u5cad"
    ],
    "name:zho_x_variant":[
        "\u6c49\u8302\u9675"
    ],
    "wof:name":"Maoling",
    "wof:placetype":"locality"
},
  "geometry": {"coordinates":[108.23909,30.55627],"type":"Point"}
}