{
  "type": "Feature",
  "properties": {
    "gn:admin1_code":"29.0",
    "gn:asciiname":"Wencang",
    "gn:country_code":"CN",
    "gn:dem":1163,
    "gn:feature_class":"P",
    "gn:feature_code":"PPL",
    "gn:name":"Wencang",
    "gn:population":0,
    "gn:timezone":"Asia/Shanghai",
    "iso:country":"CN",
    "name:zho_x_preferred":[
        "\u6587\u4ed3"
    ],
    "wof:name":"Wencang",
    "wof:placetype":"locality"
},
  "geometry": {"coordinates":[100.899,24.3597],"type":"Point"}
}