{
  "type": "Feature",
  "properties": {
    "gn:admin1_code":"19.0",
    "gn:asciiname":"Gu'angou",
    "gn:country_code":"CN",
    "gn:dem":204,
    "gn:feature_class":"P",
    "gn:feature_code":"PPL",
    "gn:name":"Gu\u2019angou",
    "gn:population":0,
    "gn:timezone":"Asia/Shanghai",
    "iso:country":"CN",
    "name:und_x_variant":[
        "Gu\u2019angou",
        "\u59d1\u5eb5\u6c9f"
    ],
    "wof:name":"Gu'angou",
    "wof:placetype":"locality"
},
  "geometry": {"coordinates":[122.76997,40.67482],"type":"Point"}
}