{
  "type": "Feature",
  "properties": {
    "gn:admin1_code":"16.0",
    "gn:asciiname":"Kuixicun",
    "gn:country_code":"CN",
    "gn:dem":142,
    "gn:feature_class":"P",
    "gn:feature_code":"PPL",
    "gn:name":"Kuixicun",
    "gn:population":0,
    "gn:timezone":"Asia/Shanghai",
    "iso:country":"CN",
    "name:zho_x_preferred":[
        "\u8475\u897f\u6751"
    ],
    "wof:name":"Kuixicun",
    "wof:placetype":"locality"
},
  "geometry": {"coordinates":[109.807,22.7226],"type":"Point"}
}