{
  "type": "Feature",
  "properties": {
    "gn:admin1_code":"29",
    "gn:asciiname":"Baibiao",
    "gn:country_code":"CN",
    "gn:dem":192,
    "gn:feature_class":"P",
    "gn:feature_code":"PPL",
    "gn:name":"Baibiao",
    "gn:population":0,
    "gn:timezone":"Asia/Shanghai",
    "iso:country":"CN",
    "name:zho_x_preferred":[
        "\u767e\u6807"
    ],
    "wof:name":"Baibiao",
    "wof:placetype":"locality"
},
  "geometry": {"coordinates":[106.089,23.9449],"type":"Point"}
}