{
  "type": "Feature",
  "properties": {
    "gn:admin1_code":"8.0",
    "gn:asciiname":"Bajiazi",
    "gn:country_code":"CN",
    "gn:dem":122,
    "gn:feature_class":"P",
    "gn:feature_code":"PPL",
    "gn:name":"Bajiazi",
    "gn:population":0,
    "gn:timezone":"Asia/Shanghai",
    "iso:country":"CN",
    "name:zho_x_preferred":[
        "\u516b\u5bb6\u5b50"
    ],
    "wof:name":"Bajiazi",
    "wof:placetype":"locality"
},
  "geometry": {"coordinates":[132.30351999999999,45.61219000000001],"type":"Point"}
}