{
  "type": "Feature",
  "properties": {
    "gn:admin1_code":"26.0",
    "gn:asciiname":"Xiaoxigoucun",
    "gn:country_code":"CN",
    "gn:dem":1067,
    "gn:feature_class":"P",
    "gn:feature_code":"PPL",
    "gn:name":"Xiaoxigoucun",
    "gn:population":0,
    "gn:timezone":"Asia/Shanghai",
    "iso:country":"CN",
    "name:und_x_variant":[
        "\u5c0f\u897f\u6c9f\u6751"
    ],
    "wof:name":"Xiaoxigoucun",
    "wof:placetype":"locality"
},
  "geometry": {"coordinates":[107.42513999999998,33.47539],"type":"Point"}
}