{
  "type": "Feature",
  "properties": {
    "gn:admin1_code":"11.0",
    "gn:asciiname":"Xianghuatang",
    "gn:country_code":"CN",
    "gn:dem":111,
    "gn:feature_class":"P",
    "gn:feature_code":"PPL",
    "gn:name":"Xianghuatang",
    "gn:population":0,
    "gn:timezone":"Asia/Shanghai",
    "iso:country":"CN",
    "name:zho_x_preferred":[
        "\u9999\u82b1\u5802"
    ],
    "wof:name":"Xianghuatang",
    "wof:placetype":"locality"
},
  "geometry": {"coordinates":[112.22682,27.12316],"type":"Point"}
}