{
  "type": "Feature",
  "properties": {
    "gn:admin1_code":"14.0",
    "gn:asciiname":"Darang",
    "gn:country_code":"CN",
    "gn:dem":1632,
    "gn:feature_class":"P",
    "gn:feature_code":"PPL",
    "gn:name":"Darang",
    "gn:population":0,
    "gn:timezone":"Asia/Urumqi",
    "iso:country":"CN",
    "name:zho_x_preferred":[
        "\u6253\u8ba9"
    ],
    "wof:name":"Darang",
    "wof:placetype":"locality"
},
  "geometry": {"coordinates":[95.0241,29.19377],"type":"Point"}
}