{
  "type": "Feature",
  "properties": {
    "gn:admin1_code":"24.0",
    "gn:asciiname":"Hannangou",
    "gn:country_code":"CN",
    "gn:dem":1252,
    "gn:feature_class":"P",
    "gn:feature_code":"PPL",
    "gn:name":"Hannangou",
    "gn:population":0,
    "gn:timezone":"Asia/Shanghai",
    "iso:country":"CN",
    "name:zho_x_preferred":[
        "\u97e9\u5357\u6c9f"
    ],
    "wof:name":"Hannangou",
    "wof:placetype":"locality"
},
  "geometry": {"coordinates":[112.40748000000001,38.04474],"type":"Point"}
}