{
  "type": "Feature",
  "properties": {
    "gn:admin1_code":"26",
    "gn:asciiname":"Ganxi",
    "gn:cc2":"CN",
    "gn:country_code":"CN",
    "gn:dem":285,
    "gn:feature_class":"P",
    "gn:feature_code":"PPL",
    "gn:name":"Ganxi",
    "gn:population":0,
    "gn:timezone":"Asia/Shanghai",
    "iso:country":"CN",
    "name:und_x_variant":[
        "Kan-chi-p\u2019u",
        "Kan-hsi",
        "Kan-hsi-p\u2019u",
        "Kan-hsi-ho",
        "Ganxi"
    ],
    "wof:name":"Ganxi",
    "wof:placetype":"locality"
},
  "geometry": {"coordinates":[109.25528,32.87778],"type":"Point"}
}