{
  "type": "Feature",
  "properties": {
    "gn:admin1_code":"4.0",
    "gn:asciiname":"Yangxu",
    "gn:country_code":"CN",
    "gn:dem":2,
    "gn:feature_class":"P",
    "gn:feature_code":"PPL",
    "gn:name":"Yangxu",
    "gn:population":0,
    "gn:timezone":"Asia/Shanghai",
    "iso:country":"CN",
    "name:zho_x_preferred":[
        "Yangxu"
    ],
    "name:zho_x_variant":[
        "\u6768\u5729"
    ],
    "wof:name":"Yangxu",
    "wof:placetype":"locality"
},
  "geometry": {"coordinates":[119.38894000000001,34.57558],"type":"Point"}
}