{
  "type": "Feature",
  "properties": {
    "gn:admin1_code":"29.0",
    "gn:asciiname":"Xindianzi",
    "gn:country_code":"CN",
    "gn:dem":2379,
    "gn:feature_class":"P",
    "gn:feature_code":"PPL",
    "gn:name":"Xindianzi",
    "gn:population":0,
    "gn:timezone":"Asia/Shanghai",
    "iso:country":"CN",
    "wof:name":"Xindianzi",
    "wof:placetype":"locality"
},
  "geometry": {"coordinates":[103.58333,27.61667000000001],"type":"Point"}
}