{
  "type": "Feature",
  "properties": {
    "gn:admin1_code":"32.0",
    "gn:asciiname":"Shizhu",
    "gn:country_code":"CN",
    "gn:dem":418,
    "gn:feature_class":"P",
    "gn:feature_code":"PPL",
    "gn:name":"Shizhu",
    "gn:population":0,
    "gn:timezone":"Asia/Shanghai",
    "iso:country":"CN",
    "name:zho_x_preferred":[
        "\u77f3\u67f1"
    ],
    "wof:name":"Shizhu",
    "wof:placetype":"locality"
},
  "geometry": {"coordinates":[104.648,30.039],"type":"Point"}
}