{
  "type": "Feature",
  "properties": {
    "gn:admin1_code":"18",
    "gn:asciiname":"Ganyanjiao",
    "gn:country_code":"CN",
    "gn:dem":1984,
    "gn:feature_class":"P",
    "gn:feature_code":"PPL",
    "gn:name":"Ganyanjiao",
    "gn:population":0,
    "gn:timezone":"Asia/Shanghai",
    "iso:country":"CN",
    "name:zho_x_preferred":[
        "\u5e72\u5ca9\u811a"
    ],
    "wof:name":"Ganyanjiao",
    "wof:placetype":"locality"
},
  "geometry": {"coordinates":[105.295,26.6787],"type":"Point"}
}