{
  "type": "Feature",
  "properties": {
    "gn:admin1_code":"32.0",
    "gn:asciiname":"Qingcheng",
    "gn:country_code":"CN",
    "gn:dem":782,
    "gn:feature_class":"P",
    "gn:feature_code":"PPL",
    "gn:name":"Qingcheng",
    "gn:population":0,
    "gn:timezone":"Asia/Shanghai",
    "iso:country":"CN",
    "name:ceb_x_preferred":[
        "Qingcheng"
    ],
    "name:deu_x_preferred":[
        "Qingcheng"
    ],
    "name:fra_x_preferred":[
        "Qingcheng"
    ],
    "name:nor_x_preferred":[
        "Qingcheng"
    ],
    "name:rus_x_preferred":[
        "\u0426\u0438\u043d\u0447\u044d\u043d"
    ],
    "name:swe_x_preferred":[
        "Qingcheng"
    ],
    "name:zho_x_preferred":[
        "\u9752\u57ce"
    ],
    "wof:name":"Qingcheng",
    "wof:placetype":"locality"
},
  "geometry": {"coordinates":[104.99299999999999,32.4064],"type":"Point"}
}