{
  "type": "Feature",
  "properties": {
    "gn:admin1_code":"19.0",
    "gn:asciiname":"Yujiajie",
    "gn:country_code":"CN",
    "gn:dem":355,
    "gn:feature_class":"P",
    "gn:feature_code":"PPL",
    "gn:name":"Yujiajie",
    "gn:population":0,
    "gn:timezone":"Asia/Shanghai",
    "iso:country":"CN",
    "name:und_x_variant":[
        "\u4e8e\u5bb6\u8857"
    ],
    "wof:name":"Yujiajie",
    "wof:placetype":"locality"
},
  "geometry": {"coordinates":[124.01065,41.50055],"type":"Point"}
}