{
  "type": "Feature",
  "properties": {
    "gn:admin1_code":"30",
    "gn:asciiname":"Dongpingxu",
    "gn:country_code":"CN",
    "gn:dem":24,
    "gn:feature_class":"P",
    "gn:feature_code":"PPL",
    "gn:name":"Dongpingxu",
    "gn:population":0,
    "gn:timezone":"Asia/Urumqi",
    "iso:country":"CN",
    "name:zho_x_preferred":[
        "\u4e1c\u5e73\u5729"
    ],
    "wof:name":"Dongpingxu",
    "wof:placetype":"locality"
},
  "geometry": {"coordinates":[110.31811,20.75784],"type":"Point"}
}