{
  "type": "Feature",
  "properties": {
    "gn:admin1_code":"26.0",
    "gn:asciiname":"Jijiamao",
    "gn:country_code":"CN",
    "gn:dem":1091,
    "gn:feature_class":"P",
    "gn:feature_code":"PPL",
    "gn:name":"Jijiamao",
    "gn:population":0,
    "gn:timezone":"Asia/Shanghai",
    "iso:country":"CN",
    "name:zho_x_preferred":[
        "\u5409\u5bb6\u5cc1"
    ],
    "wof:name":"Jijiamao",
    "wof:placetype":"locality"
},
  "geometry": {"coordinates":[109.93000000000001,38.12777],"type":"Point"}
}