{
  "type": "Feature",
  "properties": {
    "gn:admin1_code":"18",
    "gn:asciiname":"Shuaiyichong",
    "gn:country_code":"CN",
    "gn:dem":1238,
    "gn:feature_class":"P",
    "gn:feature_code":"PPL",
    "gn:name":"Shuaiyichong",
    "gn:population":0,
    "gn:timezone":"Asia/Shanghai",
    "iso:country":"CN",
    "name:zho_x_preferred":[
        "\u8870\u8863\u51b2"
    ],
    "wof:name":"Shuaiyichong",
    "wof:placetype":"locality"
},
  "geometry": {"coordinates":[106.051,26.9679],"type":"Point"}
}