{
  "type": "Feature",
  "properties": {
    "gn:admin1_code":"2.0",
    "gn:asciiname":"Shanliqiao",
    "gn:country_code":"CN",
    "gn:dem":30,
    "gn:feature_class":"P",
    "gn:feature_code":"PPL",
    "gn:name":"Shanliqiao",
    "gn:population":0,
    "gn:timezone":"Asia/Shanghai",
    "iso:country":"CN",
    "name:zho_x_preferred":[
        "\u5c71\u91cc\u6865"
    ],
    "wof:name":"Shanliqiao",
    "wof:placetype":"locality"
},
  "geometry": {"coordinates":[121.63385,28.98445],"type":"Point"}
}