{
  "type": "Feature",
  "properties": {
    "gn:admin1_code":"29.0",
    "gn:asciiname":"Pingzhangzhai",
    "gn:country_code":"CN",
    "gn:dem":1708,
    "gn:feature_class":"P",
    "gn:feature_code":"PPL",
    "gn:name":"Pingzhangzhai",
    "gn:population":0,
    "gn:timezone":"Asia/Shanghai",
    "iso:country":"CN",
    "name:zho_x_preferred":[
        "\u5e73\u638c\u5be8"
    ],
    "wof:name":"Pingzhangzhai",
    "wof:placetype":"locality"
},
  "geometry": {"coordinates":[100.661,22.738],"type":"Point"}
}