{
  "type": "Feature",
  "properties": {
    "gn:admin1_code":"16.0",
    "gn:asciiname":"Xiaping",
    "gn:country_code":"CN",
    "gn:dem":1174,
    "gn:feature_class":"P",
    "gn:feature_code":"PPL",
    "gn:name":"Xiaping",
    "gn:population":0,
    "gn:timezone":"Asia/Shanghai",
    "iso:country":"CN",
    "name:zho_x_preferred":[
        "\u4e0b\u5e73"
    ],
    "wof:name":"Xiaping",
    "wof:placetype":"locality"
},
  "geometry": {"coordinates":[105.18000000000001,24.9098],"type":"Point"}
}