{
  "type": "Feature",
  "properties": {
    "gn:admin1_code":"29",
    "gn:asciiname":"Huasai Jiuzhai",
    "gn:country_code":"CN",
    "gn:dem":1404,
    "gn:feature_class":"P",
    "gn:feature_code":"PPL",
    "gn:name":"Huasai Jiuzhai",
    "gn:population":0,
    "gn:timezone":"Asia/Shanghai",
    "iso:country":"CN",
    "name:zho_x_preferred":[
        "\u82b1\u8d5b\u65e7\u5be8"
    ],
    "wof:name":"Huasai Jiuzhai",
    "wof:placetype":"locality"
},
  "geometry": {"coordinates":[105.08199999999999,23.8282],"type":"Point"}
}