{
  "type": "Feature",
  "properties": {
    "gn:admin1_code":"10.0",
    "gn:asciiname":"Huzhangtuo",
    "gn:country_code":"CN",
    "gn:dem":6,
    "gn:feature_class":"P",
    "gn:feature_code":"PPL",
    "gn:name":"Huzhangtuo",
    "gn:population":0,
    "gn:timezone":"Asia/Shanghai",
    "iso:country":"CN",
    "name:zho_x_preferred":[
        "\u80e1\u5f20\u5768"
    ],
    "wof:name":"Huzhangtuo",
    "wof:placetype":"locality"
},
  "geometry": {"coordinates":[117.90752000000001,39.6647],"type":"Point"}
}