{
  "type": "Feature",
  "properties": {
    "gn:admin1_code":"16.0",
    "gn:asciiname":"Ganmen",
    "gn:country_code":"CN",
    "gn:dem":589,
    "gn:feature_class":"P",
    "gn:feature_code":"PPL",
    "gn:name":"Ganmen",
    "gn:population":0,
    "gn:timezone":"Asia/Shanghai",
    "iso:country":"CN",
    "name:zho_x_preferred":[
        "\u6562\u95e8"
    ],
    "wof:name":"Ganmen",
    "wof:placetype":"locality"
},
  "geometry": {"coordinates":[106.68300000000001,22.3214],"type":"Point"}
}