{
  "type": "Feature",
  "properties": {
    "gn:admin1_code":"2.0",
    "gn:asciiname":"Chekouxi",
    "gn:country_code":"CN",
    "gn:dem":138,
    "gn:feature_class":"P",
    "gn:feature_code":"PPL",
    "gn:name":"Chekouxi",
    "gn:population":0,
    "gn:timezone":"Asia/Shanghai",
    "iso:country":"CN",
    "name:zho_x_preferred":[
        "\u8f66\u53e3\u6eaa"
    ],
    "wof:name":"Chekouxi",
    "wof:placetype":"locality"
},
  "geometry": {"coordinates":[120.9919,28.80004000000001],"type":"Point"}
}