{
  "type": "Feature",
  "properties": {
    "gn:admin1_code":"24",
    "gn:asciiname":"Beiguang",
    "gn:country_code":"CN",
    "gn:dem":798,
    "gn:feature_class":"P",
    "gn:feature_code":"PPL",
    "gn:name":"Beiguang",
    "gn:population":0,
    "gn:timezone":"Asia/Shanghai",
    "iso:country":"CN",
    "wof:name":"Beiguang",
    "wof:placetype":"locality"
},
  "geometry": {"coordinates":[112.50972,37.37722],"type":"Point"}
}