{
  "type": "Feature",
  "properties": {
    "gn:admin1_code":"3.0",
    "gn:asciiname":"Tiantaishan",
    "gn:country_code":"CN",
    "gn:dem":26,
    "gn:feature_class":"P",
    "gn:feature_code":"PPL",
    "gn:name":"Tiantaishan",
    "gn:population":0,
    "gn:timezone":"Asia/Shanghai",
    "iso:country":"CN",
    "name:und_x_variant":[
        "\u5929\u53f0\u5c71"
    ],
    "wof:name":"Tiantaishan",
    "wof:placetype":"locality"
},
  "geometry": {"coordinates":[116.08261,28.27101],"type":"Point"}
}