{
  "type": "Feature",
  "properties": {
    "gn:admin1_code":"12.0",
    "gn:asciiname":"Xiongjia'ao",
    "gn:country_code":"CN",
    "gn:dem":182,
    "gn:feature_class":"P",
    "gn:feature_code":"PPL",
    "gn:name":"Xiongjia\u2019ao",
    "gn:population":0,
    "gn:timezone":"Asia/Shanghai",
    "iso:country":"CN",
    "name:zho_x_preferred":[
        "Xiongjia\u2019ao"
    ],
    "name:zho_x_variant":[
        "\u718a\u5bb6\u5773"
    ],
    "wof:name":"Xiongjia'ao",
    "wof:placetype":"locality"
},
  "geometry": {"coordinates":[111.33725,30.40822],"type":"Point"}
}