{
  "type": "Feature",
  "properties": {
    "gn:admin1_code":"32.0",
    "gn:asciiname":"Da'erniao",
    "gn:country_code":"CN",
    "gn:dem":1736,
    "gn:feature_class":"P",
    "gn:feature_code":"PPL",
    "gn:name":"Da\u2019erniao",
    "gn:population":0,
    "gn:timezone":"Asia/Shanghai",
    "iso:country":"CN",
    "name:zho_x_preferred":[
        "\u5927\u8033\u9e1f"
    ],
    "name:zho_x_variant":[
        "Da\u2019erniao"
    ],
    "wof:name":"Da'erniao",
    "wof:placetype":"locality"
},
  "geometry": {"coordinates":[102.3605,27.88868],"type":"Point"}
}