{
  "type": "Feature",
  "properties": {
    "gn:admin1_code":"29",
    "gn:asciiname":"Maomao'ao",
    "gn:country_code":"CN",
    "gn:dem":2034,
    "gn:feature_class":"P",
    "gn:feature_code":"PPL",
    "gn:name":"Maomao\u2019ao",
    "gn:population":0,
    "gn:timezone":"Asia/Shanghai",
    "iso:country":"CN",
    "name:zho_x_preferred":[
        "\u6bdb\u6bdb\u51f9"
    ],
    "name:zho_x_variant":[
        "Maomao\u2019ao"
    ],
    "wof:name":"Maomao'ao",
    "wof:placetype":"locality"
},
  "geometry": {"coordinates":[102.13518000000001,24.74728],"type":"Point"}
}