{
  "type": "Feature",
  "properties": {
    "gn:admin1_code":"4.0",
    "gn:asciiname":"Zhangbali",
    "gn:country_code":"CN",
    "gn:dem":4,
    "gn:feature_class":"P",
    "gn:feature_code":"PPL",
    "gn:name":"Zhangbali",
    "gn:population":0,
    "gn:timezone":"Asia/Shanghai",
    "iso:country":"CN",
    "name:und_x_variant":[
        "\u5f20\u516b\u91cc"
    ],
    "name:zho_x_preferred":[
        "\u5f20\u516b\u91cc"
    ],
    "wof:name":"Zhangbali",
    "wof:placetype":"locality"
},
  "geometry": {"coordinates":[120.61493,32.38287],"type":"Point"}
}