{
  "type": "Feature",
  "properties": {
    "gn:admin1_code":"29.0",
    "gn:asciiname":"Renmaoshan",
    "gn:country_code":"CN",
    "gn:dem":2117,
    "gn:feature_class":"P",
    "gn:feature_code":"PPL",
    "gn:name":"Renmaoshan",
    "gn:population":0,
    "gn:timezone":"Asia/Shanghai",
    "iso:country":"CN",
    "name:zho_x_preferred":[
        "\u4ec1\u8302\u5c71"
    ],
    "wof:name":"Renmaoshan",
    "wof:placetype":"locality"
},
  "geometry": {"coordinates":[99.2882,26.1543],"type":"Point"}
}