{
  "type": "Feature",
  "properties": {
    "gn:admin1_code":"11.0",
    "gn:asciiname":"Xiajia Laowu",
    "gn:country_code":"CN",
    "gn:dem":66,
    "gn:feature_class":"P",
    "gn:feature_code":"PPL",
    "gn:name":"Xiajia Laowu",
    "gn:population":0,
    "gn:timezone":"Asia/Shanghai",
    "iso:country":"CN",
    "name:zho_x_preferred":[
        "\u590f\u5bb6\u8001\u5c4b"
    ],
    "wof:name":"Xiajia Laowu",
    "wof:placetype":"locality"
},
  "geometry": {"coordinates":[113.23084,28.40926],"type":"Point"}
}