{
  "type": "Feature",
  "properties": {
    "gn:admin1_code":"12.0",
    "gn:asciiname":"Shiziling",
    "gn:country_code":"CN",
    "gn:dem":36,
    "gn:feature_class":"P",
    "gn:feature_code":"PPL",
    "gn:name":"Shiziling",
    "gn:population":0,
    "gn:timezone":"Asia/Shanghai",
    "iso:country":"CN",
    "name:und_x_variant":[
        "\u72ee\u5b50\u5cad"
    ],
    "name:zho_x_preferred":[
        "Shiziling"
    ],
    "wof:name":"Shiziling",
    "wof:placetype":"locality"
},
  "geometry": {"coordinates":[114.07008999999999,30.5761],"type":"Point"}
}