{
  "type": "Feature",
  "properties": {
    "gn:admin1_code":"4.0",
    "gn:asciiname":"Sunxiang",
    "gn:country_code":"CN",
    "gn:dem":-1,
    "gn:feature_class":"P",
    "gn:feature_code":"PPL",
    "gn:name":"Sunxiang",
    "gn:population":0,
    "gn:timezone":"Asia/Shanghai",
    "iso:country":"CN",
    "name:zho_x_preferred":[
        "Sunxiang"
    ],
    "name:zho_x_variant":[
        "\u5b59\u5df7"
    ],
    "wof:name":"Sunxiang",
    "wof:placetype":"locality"
},
  "geometry": {"coordinates":[120.16495999999999,34.10328],"type":"Point"}
}