{
  "type": "Feature",
  "properties": {
    "gn:admin1_code":"12.0",
    "gn:asciiname":"Minzhugou",
    "gn:country_code":"CN",
    "gn:dem":35,
    "gn:feature_class":"P",
    "gn:feature_code":"PPL",
    "gn:name":"Minzhugou",
    "gn:population":0,
    "gn:timezone":"Asia/Shanghai",
    "iso:country":"CN",
    "name:zho_x_preferred":[
        "\u6c11\u4e3b\u6c9f"
    ],
    "wof:name":"Minzhugou",
    "wof:placetype":"locality"
},
  "geometry": {"coordinates":[112.53185000000001,29.88847],"type":"Point"}
}