{
  "type": "Feature",
  "properties": {
    "gn:admin1_code":"15.0",
    "gn:asciiname":"Bami Shangou",
    "gn:country_code":"CN",
    "gn:dem":2152,
    "gn:feature_class":"P",
    "gn:feature_code":"PPL",
    "gn:name":"Bami Shangou",
    "gn:population":0,
    "gn:timezone":"Asia/Shanghai",
    "iso:country":"CN",
    "name:zho_x_preferred":[
        "\u5df4\u7c73\u5c71\u6c9f"
    ],
    "wof:name":"Bami Shangou",
    "wof:placetype":"locality"
},
  "geometry": {"coordinates":[103.474,35.9487],"type":"Point"}
}