{
  "type": "Feature",
  "properties": {
    "gn:admin1_code":"3.0",
    "gn:asciiname":"Dachi",
    "gn:country_code":"CN",
    "gn:dem":161,
    "gn:feature_class":"P",
    "gn:feature_code":"PPL",
    "gn:name":"Dachi",
    "gn:population":0,
    "gn:timezone":"Asia/Shanghai",
    "iso:country":"CN",
    "name:und_x_variant":[
        "\u5927\u6c60"
    ],
    "wof:name":"Dachi",
    "wof:placetype":"locality"
},
  "geometry": {"coordinates":[115.61958,27.49279000000001],"type":"Point"}
}