{
  "type": "Feature",
  "properties": {
    "gn:admin1_code":"14",
    "gn:asciiname":"Medog",
    "gn:country_code":"CN",
    "gn:dem":4446,
    "gn:feature_class":"P",
    "gn:feature_code":"PPL",
    "gn:name":"M\u00eadog",
    "gn:population":0,
    "gn:timezone":"Asia/Urumqi",
    "iso:country":"CN",
    "name:bod_x_preferred":[
        "\u0f58\u0f7a\u0f0b\u0f4f\u0f7c\u0f42"
    ],
    "name:ita_x_preferred":[
        "M\u00eadog"
    ],
    "wof:name":"Medog",
    "wof:placetype":"locality"
},
  "geometry": {"coordinates":[91.00516,28.85866],"type":"Point"}
}