{
  "type": "Feature",
  "properties": {
    "gn:admin1_code":"16",
    "gn:asciiname":"Dengzhanwan",
    "gn:country_code":"CN",
    "gn:dem":196,
    "gn:feature_class":"P",
    "gn:feature_code":"PPL",
    "gn:name":"Dengzhanwan",
    "gn:population":0,
    "gn:timezone":"Asia/Shanghai",
    "iso:country":"CN",
    "name:zho_x_preferred":[
        "\u706f\u76cf\u5f2f"
    ],
    "wof:name":"Dengzhanwan",
    "wof:placetype":"locality"
},
  "geometry": {"coordinates":[110.355,24.8304],"type":"Point"}
}