{
  "type": "Feature",
  "properties": {
    "gn:admin1_code":"26.0",
    "gn:asciiname":"Xutaizi Goucun",
    "gn:country_code":"CN",
    "gn:dem":1502,
    "gn:feature_class":"P",
    "gn:feature_code":"PPL",
    "gn:name":"Xutaizi Goucun",
    "gn:population":0,
    "gn:timezone":"Asia/Shanghai",
    "iso:country":"CN",
    "name:zho_x_preferred":[
        "\u5f90\u53f0\u5b50\u6c9f\u6751"
    ],
    "wof:name":"Xutaizi Goucun",
    "wof:placetype":"locality"
},
  "geometry": {"coordinates":[108.31,37.2369],"type":"Point"}
}