{
  "type": "Feature",
  "properties": {
    "gn:admin1_code":"24",
    "gn:asciiname":"Zhiyu",
    "gn:country_code":"CN",
    "gn:dem":1259,
    "gn:feature_class":"P",
    "gn:feature_code":"PPL",
    "gn:name":"Zhiyu",
    "gn:population":0,
    "gn:timezone":"Asia/Shanghai",
    "iso:country":"CN",
    "name:und_x_variant":[
        "Chih-y\u00fc-ts\u2019un",
        "Ssu-y\u00fc-ts\u2019un",
        "Ssu-y\u00fc",
        "Zhiyu",
        "\u5cd9\u5cea"
    ],
    "wof:name":"Zhiyu",
    "wof:placetype":"locality"
},
  "geometry": {"coordinates":[112.3486,39.39908],"type":"Point"}
}