{
  "type": "Feature",
  "properties": {
    "gn:admin1_code":"3.0",
    "gn:asciiname":"Jinjiang",
    "gn:country_code":"CN",
    "gn:dem":38,
    "gn:feature_class":"P",
    "gn:feature_code":"PPL",
    "gn:name":"Jinjiang",
    "gn:population":0,
    "gn:timezone":"Asia/Shanghai",
    "iso:country":"CN",
    "name:ceb_x_preferred":[
        "Jinjiang"
    ],
    "name:ces_x_preferred":[
        "\u0164in-\u0165iang"
    ],
    "name:deu_x_preferred":[
        "Jinjiang"
    ],
    "name:fra_x_preferred":[
        "Jinjiang"
    ],
    "name:mlg_x_preferred":[
        "Jinjiang"
    ],
    "name:nor_x_preferred":[
        "Jinjiang"
    ],
    "name:rus_x_preferred":[
        "\u0426\u0437\u0438\u043d\u044c\u0446\u0437\u044f\u043d"
    ],
    "name:swe_x_preferred":[
        "Jinjiang"
    ],
    "name:und_x_variant":[
        "\u9526\u6c5f"
    ],
    "wof:name":"Jinjiang",
    "wof:placetype":"locality"
},
  "geometry": {"coordinates":[115.22076,28.29507000000001],"type":"Point"}
}