{
  "type": "Feature",
  "properties": {
    "gn:admin1_code":"3.0",
    "gn:asciiname":"Jinjiang",
    "gn:country_code":"CN",
    "gn:dem":38,
    "gn:feature_class":"P",
    "gn:feature_code":"PPL",
    "gn:name":"Jinjiang",
    "gn:population":0,
    "gn:timezone":"Asia/Shanghai",
    "iso:country":"CN",
    "name:und_x_variant":[
        "\u9526\u6c5f"
    ],
    "wof:name":"Jinjiang",
    "wof:placetype":"locality"
},
  "geometry": {"coordinates":[115.22076,28.29507000000001],"type":"Point"}
}