{
  "type": "Feature",
  "properties": {
    "gn:admin1_code":"15.0",
    "gn:asciiname":"Sheguping",
    "gn:country_code":"CN",
    "gn:dem":1846,
    "gn:feature_class":"P",
    "gn:feature_code":"PPL",
    "gn:name":"Sheguping",
    "gn:population":0,
    "gn:timezone":"Asia/Shanghai",
    "iso:country":"CN",
    "name:und_x_variant":[
        "\u820d\u53e4\u576a"
    ],
    "name:zho_x_preferred":[
        "\u820d\u53e4\u576a"
    ],
    "wof:name":"Sheguping",
    "wof:placetype":"locality"
},
  "geometry": {"coordinates":[104.74742999999999,33.17896],"type":"Point"}
}