{
  "type": "Feature",
  "properties": {
    "gn:admin1_code":"1.0",
    "gn:asciiname":"Xinchongcun",
    "gn:country_code":"CN",
    "gn:dem":130,
    "gn:feature_class":"P",
    "gn:feature_code":"PPL",
    "gn:name":"Xinchongcun",
    "gn:population":0,
    "gn:timezone":"Asia/Shanghai",
    "iso:country":"CN",
    "name:zho_x_preferred":[
        "\u8f9b\u51b2\u6751"
    ],
    "wof:name":"Xinchongcun",
    "wof:placetype":"locality"
},
  "geometry": {"coordinates":[116.12187,30.5027],"type":"Point"}
}