{
  "type": "Feature",
  "properties": {
    "gn:admin1_code":"25.0",
    "gn:asciiname":"Nansizhuangcun",
    "gn:country_code":"CN",
    "gn:dem":70,
    "gn:feature_class":"P",
    "gn:feature_code":"PPL",
    "gn:name":"Nansizhuangcun",
    "gn:population":0,
    "gn:timezone":"Asia/Shanghai",
    "iso:country":"CN",
    "name:zho_x_preferred":[
        "\u5357\u6cd7\u5e84\u6751"
    ],
    "wof:name":"Nansizhuangcun",
    "wof:placetype":"locality"
},
  "geometry": {"coordinates":[120.91503,36.90295],"type":"Point"}
}