{
  "type": "Feature",
  "properties": {
    "gn:admin1_code":"9.0",
    "gn:asciiname":"Erliperng",
    "gn:country_code":"CN",
    "gn:dem":81,
    "gn:feature_class":"P",
    "gn:feature_code":"PPL",
    "gn:name":"Erliperng",
    "gn:population":0,
    "gn:timezone":"Asia/Shanghai",
    "iso:country":"CN",
    "name:zho_x_preferred":[
        "\u4e8c\u91cc\u68da"
    ],
    "wof:name":"Erliperng",
    "wof:placetype":"locality"
},
  "geometry": {"coordinates":[115.10748,31.92608],"type":"Point"}
}