{
  "type": "Feature",
  "properties": {
    "gn:admin1_code":"19.0",
    "gn:asciiname":"Xiatangchi",
    "gn:country_code":"CN",
    "gn:dem":68,
    "gn:feature_class":"P",
    "gn:feature_code":"PPL",
    "gn:name":"Xiatangchi",
    "gn:population":0,
    "gn:timezone":"Asia/Shanghai",
    "iso:country":"CN",
    "name:und_x_variant":[
        "\u4e0b\u6c64\u6c60"
    ],
    "name:zho_x_preferred":[
        "\u4e0b\u6c64\u6c60"
    ],
    "wof:name":"Xiatangchi",
    "wof:placetype":"locality"
},
  "geometry": {"coordinates":[122.63058999999998,40.49565],"type":"Point"}
}