{
  "type": "Feature",
  "properties": {
    "gn:admin1_code":"8.0",
    "gn:asciiname":"Quanhe Sidui",
    "gn:country_code":"CN",
    "gn:dem":543,
    "gn:feature_class":"P",
    "gn:feature_code":"PPLF",
    "gn:name":"Quanhe Sidui",
    "gn:population":0,
    "gn:timezone":"Asia/Shanghai",
    "iso:country":"CN",
    "name:zho_x_preferred":[
        "\u6cc9\u6cb3\u56db\u961f"
    ],
    "wof:name":"Quanhe Sidui",
    "wof:placetype":"locality"
},
  "geometry": {"coordinates":[129.44418000000002,48.02477],"type":"Point"}
}