{
  "type": "Feature",
  "properties": {
    "gn:admin1_code":"26.0",
    "gn:asciiname":"Nianlingcun",
    "gn:country_code":"CN",
    "gn:dem":1457,
    "gn:feature_class":"P",
    "gn:feature_code":"PPL",
    "gn:name":"Nianlingcun",
    "gn:population":0,
    "gn:timezone":"Asia/Shanghai",
    "iso:country":"CN",
    "name:zho_x_preferred":[
        "\u57dd\u5cad\u6751"
    ],
    "wof:name":"Nianlingcun",
    "wof:placetype":"locality"
},
  "geometry": {"coordinates":[108.52092,35.04488],"type":"Point"}
}