{
  "type": "Feature",
  "properties": {
    "gn:admin1_code":"18.0",
    "gn:asciiname":"Bifou",
    "gn:country_code":"CN",
    "gn:dem":630,
    "gn:feature_class":"P",
    "gn:feature_code":"PPL",
    "gn:name":"Bifou",
    "gn:population":0,
    "gn:timezone":"Asia/Shanghai",
    "iso:country":"CN",
    "name:zho_x_preferred":[
        "\u4ffe\u5426"
    ],
    "wof:name":"Bifou",
    "wof:placetype":"locality"
},
  "geometry": {"coordinates":[109.29900000000001,25.7845],"type":"Point"}
}