{
  "type": "Feature",
  "properties": {
    "gn:admin1_code":"32.0",
    "gn:asciiname":"Xianiusha",
    "gn:country_code":"CN",
    "gn:dem":3341,
    "gn:feature_class":"P",
    "gn:feature_code":"PPL",
    "gn:name":"Xianiusha",
    "gn:population":0,
    "gn:timezone":"Asia/Shanghai",
    "iso:country":"CN",
    "name:zho_x_preferred":[
        "\u4e0b\u725b\u6c99"
    ],
    "wof:name":"Xianiusha",
    "wof:placetype":"locality"
},
  "geometry": {"coordinates":[99.1444,31.3483],"type":"Point"}
}