{
  "type": "Feature",
  "properties": {
    "gn:admin1_code":"7.0",
    "gn:asciiname":"Baiyang",
    "gn:country_code":"CN",
    "gn:dem":318,
    "gn:feature_class":"P",
    "gn:feature_code":"PPL",
    "gn:name":"Baiyang",
    "gn:population":0,
    "gn:timezone":"Asia/Shanghai",
    "iso:country":"CN",
    "name:ceb_x_preferred":[
        "Baiyang"
    ],
    "name:deu_x_preferred":[
        "Baiyang"
    ],
    "name:swe_x_preferred":[
        "Baiyang"
    ],
    "name:zho_x_preferred":[
        "\u767d\u6d0b"
    ],
    "wof:name":"Baiyang",
    "wof:placetype":"locality"
},
  "geometry": {"coordinates":[118.94673,25.43234],"type":"Point"}
}