{
  "type": "Feature",
  "properties": {
    "gn:admin1_code":"25",
    "gn:asciiname":"Dongyuanzhuang",
    "gn:country_code":"CN",
    "gn:dem":191,
    "gn:feature_class":"P",
    "gn:feature_code":"PPL",
    "gn:name":"Dongyuanzhuang",
    "gn:population":0,
    "gn:timezone":"Asia/Shanghai",
    "iso:country":"CN",
    "name:zho_x_preferred":[
        "\u4e1c\u82d1\u5e84"
    ],
    "wof:name":"Dongyuanzhuang",
    "wof:placetype":"locality"
},
  "geometry": {"coordinates":[119.078,35.6549],"type":"Point"}
}