{
  "type": "Feature",
  "properties": {
    "gn:admin1_code":"11",
    "gn:asciiname":"Dongxia",
    "gn:country_code":"CN",
    "gn:dem":483,
    "gn:feature_class":"P",
    "gn:feature_code":"PPL",
    "gn:name":"Dongxia",
    "gn:population":0,
    "gn:timezone":"Asia/Shanghai",
    "iso:country":"CN",
    "name:zho_x_preferred":[
        "\u6d1e\u4e0b"
    ],
    "wof:name":"Dongxia",
    "wof:placetype":"locality"
},
  "geometry": {"coordinates":[110.91916999999999,27.55528],"type":"Point"}
}