{
  "type": "Feature",
  "properties": {
    "gn:admin1_code":"16.0",
    "gn:asciiname":"Wuyou",
    "gn:country_code":"CN",
    "gn:dem":101,
    "gn:feature_class":"P",
    "gn:feature_code":"PPL",
    "gn:name":"Wuyou",
    "gn:population":0,
    "gn:timezone":"Asia/Shanghai",
    "iso:country":"CN",
    "name:zho_x_preferred":[
        "\u65e0\u5fe7"
    ],
    "wof:name":"Wuyou",
    "wof:placetype":"locality"
},
  "geometry": {"coordinates":[109.253,24.4581],"type":"Point"}
}