{
  "type": "Feature",
  "properties": {
    "gn:admin1_code":"16.0",
    "gn:asciiname":"Mulu",
    "gn:country_code":"CN",
    "gn:dem":760,
    "gn:feature_class":"P",
    "gn:feature_code":"PPL",
    "gn:name":"Mulu",
    "gn:population":0,
    "gn:timezone":"Asia/Shanghai",
    "iso:country":"CN",
    "name:ceb_x_preferred":[
        "Mulu"
    ],
    "name:fas_x_preferred":[
        "\u0645\u0648\u0644\u0648"
    ],
    "name:swe_x_preferred":[
        "Mulu"
    ],
    "name:zho_x_preferred":[
        "\u6bcd\u9c81"
    ],
    "wof:name":"Mulu",
    "wof:placetype":"locality"
},
  "geometry": {"coordinates":[105.389,24.1512],"type":"Point"}
}