{
  "type": "Feature",
  "properties": {
    "gn:admin1_code":"30",
    "gn:asciiname":"Shanghua",
    "gn:country_code":"CN",
    "gn:dem":5,
    "gn:feature_class":"P",
    "gn:feature_code":"PPLA4",
    "gn:name":"Shanghua",
    "gn:population":0,
    "gn:timezone":"Asia/Shanghai",
    "iso:country":"CN",
    "name:und_x_variant":[
        "Shanghua Zhen",
        "\u4e0a\u534e\u9547"
    ],
    "wof:name":"Shanghua",
    "wof:placetype":"locality"
},
  "geometry": {"coordinates":[116.70914999999999,23.52387],"type":"Point"}
}