{
  "type": "Feature",
  "properties": {
    "gn:admin1_code":"16.0",
    "gn:asciiname":"Lusheng",
    "gn:country_code":"CN",
    "gn:dem":195,
    "gn:feature_class":"P",
    "gn:feature_code":"PPL",
    "gn:name":"Lusheng",
    "gn:population":0,
    "gn:timezone":"Asia/Shanghai",
    "iso:country":"CN",
    "name:deu_x_preferred":[
        "Qeej"
    ],
    "name:zho_x_preferred":[
        "\u6e0c\u751f"
    ],
    "wof:name":"Lusheng",
    "wof:placetype":"locality"
},
  "geometry": {"coordinates":[108.077,22.6499],"type":"Point"}
}