{
  "type": "Feature",
  "properties": {
    "gn:admin1_code":"11.0",
    "gn:asciiname":"Yifenchang Badui",
    "gn:country_code":"CN",
    "gn:dem":28,
    "gn:feature_class":"P",
    "gn:feature_code":"PPLF",
    "gn:name":"Yifenchang Badui",
    "gn:population":0,
    "gn:timezone":"Asia/Shanghai",
    "iso:country":"CN",
    "name:zho_x_preferred":[
        "\u4e00\u5206\u573a\u516b\u961f"
    ],
    "wof:name":"Yifenchang Badui",
    "wof:placetype":"locality"
},
  "geometry": {"coordinates":[112.90812,28.87708],"type":"Point"}
}