{
  "type": "Feature",
  "properties": {
    "gn:admin1_code":"29.0",
    "gn:asciiname":"Yeguzhai",
    "gn:country_code":"CN",
    "gn:dem":1559,
    "gn:feature_class":"P",
    "gn:feature_code":"PPL",
    "gn:name":"Yeguzhai",
    "gn:population":0,
    "gn:timezone":"Asia/Shanghai",
    "iso:country":"CN",
    "name:zho_x_preferred":[
        "\u91ce\u53e4\u5be8"
    ],
    "wof:name":"Yeguzhai",
    "wof:placetype":"locality"
},
  "geometry": {"coordinates":[104.429,27.6224],"type":"Point"}
}