{
  "type": "Feature",
  "properties": {
    "gn:admin1_code":"32.0",
    "gn:asciiname":"Tianbao",
    "gn:country_code":"CN",
    "gn:dem":751,
    "gn:feature_class":"P",
    "gn:feature_code":"PPL",
    "gn:name":"Tianbao",
    "gn:population":0,
    "gn:timezone":"Asia/Shanghai",
    "iso:country":"CN",
    "name:zho_x_preferred":[
        "\u5929\u5b9d"
    ],
    "wof:name":"Tianbao",
    "wof:placetype":"locality"
},
  "geometry": {"coordinates":[103.04300000000001,29.9971],"type":"Point"}
}