{
  "type": "Feature",
  "properties": {
    "gn:admin1_code":"26.0",
    "gn:asciiname":"Zhanggelaocun",
    "gn:country_code":"CN",
    "gn:dem":1164,
    "gn:feature_class":"P",
    "gn:feature_code":"PPL",
    "gn:name":"Zhanggelaocun",
    "gn:population":0,
    "gn:timezone":"Asia/Shanghai",
    "iso:country":"CN",
    "name:zho_x_preferred":[
        "\u5f20\u572a\u635e\u6751"
    ],
    "wof:name":"Zhanggelaocun",
    "wof:placetype":"locality"
},
  "geometry": {"coordinates":[110.81574999999999,38.97881],"type":"Point"}
}