{
  "type": "Feature",
  "properties": {
    "gn:admin1_code":"3.0",
    "gn:asciiname":"Shanbicun",
    "gn:country_code":"CN",
    "gn:dem":21,
    "gn:feature_class":"P",
    "gn:feature_code":"PPL",
    "gn:name":"Shanbicun",
    "gn:population":0,
    "gn:timezone":"Asia/Shanghai",
    "iso:country":"CN",
    "name:und_x_variant":[
        "\u73ca\u58c1\u6751"
    ],
    "wof:name":"Shanbicun",
    "wof:placetype":"locality"
},
  "geometry": {"coordinates":[116.42475,28.86268],"type":"Point"}
}