{
  "type": "Feature",
  "properties": {
    "gn:admin1_code":"16.0",
    "gn:asciiname":"Shangmin",
    "gn:country_code":"CN",
    "gn:dem":683,
    "gn:feature_class":"P",
    "gn:feature_code":"PPL",
    "gn:name":"Shangmin",
    "gn:population":0,
    "gn:timezone":"Asia/Shanghai",
    "iso:country":"CN",
    "name:zho_x_preferred":[
        "\u4e0a\u654f"
    ],
    "wof:name":"Shangmin",
    "wof:placetype":"locality"
},
  "geometry": {"coordinates":[106.367,22.9057],"type":"Point"}
}