{
  "type": "Feature",
  "properties": {
    "gn:admin1_code":"30.0",
    "gn:asciiname":"Chedongcun",
    "gn:country_code":"CN",
    "gn:dem":59,
    "gn:feature_class":"P",
    "gn:feature_code":"PPL",
    "gn:name":"Chedongcun",
    "gn:population":0,
    "gn:timezone":"Asia/Urumqi",
    "iso:country":"CN",
    "name:zho_x_preferred":[
        "\u8f66\u578c\u6751"
    ],
    "wof:name":"Chedongcun",
    "wof:placetype":"locality"
},
  "geometry": {"coordinates":[110.7765,22.08778],"type":"Point"}
}