{
  "type": "Feature",
  "properties": {
    "gn:admin1_code":"19.0",
    "gn:asciiname":"Changbaigang",
    "gn:country_code":"CN",
    "gn:dem":188,
    "gn:feature_class":"P",
    "gn:feature_code":"PPL",
    "gn:name":"Changbaigang",
    "gn:population":0,
    "gn:timezone":"Asia/Shanghai",
    "iso:country":"CN",
    "name:zho_x_preferred":[
        "\u957f\u767d\u5c97"
    ],
    "wof:name":"Changbaigang",
    "wof:placetype":"locality"
},
  "geometry": {"coordinates":[122.73699999999999,39.9207],"type":"Point"}
}