{
  "type": "Feature",
  "properties": {
    "gn:admin1_code":"30.0",
    "gn:asciiname":"Shenquan Yuyecun",
    "gn:country_code":"CN",
    "gn:dem":6,
    "gn:feature_class":"P",
    "gn:feature_code":"PPLF",
    "gn:name":"Shenquan Yuyecun",
    "gn:population":0,
    "gn:timezone":"Asia/Shanghai",
    "iso:country":"CN",
    "name:zho_x_preferred":[
        "\u795e\u6cc9\u6e14\u4e1a\u6751"
    ],
    "wof:name":"Shenquan Yuyecun",
    "wof:placetype":"locality"
},
  "geometry": {"coordinates":[116.30148,22.96873],"type":"Point"}
}