{
  "type": "Feature",
  "properties": {
    "gn:admin1_code":"29.0",
    "gn:asciiname":"Handeng",
    "gn:country_code":"CN",
    "gn:dem":2061,
    "gn:feature_class":"P",
    "gn:feature_code":"PPL",
    "gn:name":"Handeng",
    "gn:population":0,
    "gn:timezone":"Asia/Shanghai",
    "iso:country":"CN",
    "name:zho_x_preferred":[
        "\u6c57\u767b"
    ],
    "wof:name":"Handeng",
    "wof:placetype":"locality"
},
  "geometry": {"coordinates":[99.93429999999999,26.1321],"type":"Point"}
}