{
  "type": "Feature",
  "properties": {
    "gn:admin1_code":"32.0",
    "gn:asciiname":"Poxiu",
    "gn:country_code":"CN",
    "gn:dem":3075,
    "gn:feature_class":"P",
    "gn:feature_code":"PPL",
    "gn:name":"Poxiu",
    "gn:population":0,
    "gn:timezone":"Asia/Shanghai",
    "iso:country":"CN",
    "name:zho_x_preferred":[
        "\u5761\u4fee"
    ],
    "wof:name":"Poxiu",
    "wof:placetype":"locality"
},
  "geometry": {"coordinates":[101.102,30.9561],"type":"Point"}
}