{
  "type": "Feature",
  "properties": {
    "gn:admin1_code":"25.0",
    "gn:asciiname":"Gaojiazhaicun",
    "gn:country_code":"CN",
    "gn:dem":38,
    "gn:feature_class":"P",
    "gn:feature_code":"PPL",
    "gn:name":"Gaojiazhaicun",
    "gn:population":0,
    "gn:timezone":"Asia/Shanghai",
    "iso:country":"CN",
    "name:zho_x_preferred":[
        "\u9ad8\u5bb6\u5be8\u6751"
    ],
    "wof:name":"Gaojiazhaicun",
    "wof:placetype":"locality"
},
  "geometry": {"coordinates":[119.81310999999999,36.92631],"type":"Point"}
}