{
  "type": "Feature",
  "properties": {
    "gn:admin1_code":"3.0",
    "gn:asciiname":"Diexiang",
    "gn:country_code":"CN",
    "gn:dem":21,
    "gn:feature_class":"P",
    "gn:feature_code":"PPL",
    "gn:name":"Diexiang",
    "gn:population":0,
    "gn:timezone":"Asia/Shanghai",
    "iso:country":"CN",
    "name:und_x_variant":[
        "\u8fed\u7965"
    ],
    "wof:name":"Diexiang",
    "wof:placetype":"locality"
},
  "geometry": {"coordinates":[116.27491999999999,29.24104],"type":"Point"}
}