{
  "type": "Feature",
  "properties": {
    "gn:admin1_code":"12.0",
    "gn:asciiname":"Hujiachang",
    "gn:country_code":"CN",
    "gn:dem":41,
    "gn:feature_class":"P",
    "gn:feature_code":"PPL",
    "gn:name":"Hujiachang",
    "gn:population":0,
    "gn:timezone":"Asia/Shanghai",
    "iso:country":"CN",
    "name:zho_x_preferred":[
        "Hujiachang"
    ],
    "name:zho_x_variant":[
        "\u80e1\u5bb6\u573a"
    ],
    "wof:name":"Hujiachang",
    "wof:placetype":"locality"
},
  "geometry": {"coordinates":[111.92614,30.10063],"type":"Point"}
}