{
  "type": "Feature",
  "properties": {
    "gn:admin1_code":"18",
    "gn:asciiname":"Guanjia Datu",
    "gn:country_code":"CN",
    "gn:dem":1582,
    "gn:feature_class":"P",
    "gn:feature_code":"PPL",
    "gn:name":"Guanjia Datu",
    "gn:population":0,
    "gn:timezone":"Asia/Shanghai",
    "iso:country":"CN",
    "name:zho_x_preferred":[
        "\u5b98\u5bb6\u5927\u571f"
    ],
    "wof:name":"Guanjia Datu",
    "wof:placetype":"locality"
},
  "geometry": {"coordinates":[105.815,27.3157],"type":"Point"}
}