{
  "type": "Feature",
  "properties": {
    "gn:admin1_code":"5.0",
    "gn:asciiname":"Chuanzigoucun",
    "gn:country_code":"CN",
    "gn:dem":307,
    "gn:feature_class":"P",
    "gn:feature_code":"PPL",
    "gn:name":"Chuanzigoucun",
    "gn:population":0,
    "gn:timezone":"Asia/Shanghai",
    "iso:country":"CN",
    "name:zho_x_preferred":[
        "\u693d\u5b50\u6c9f\u6751"
    ],
    "wof:name":"Chuanzigoucun",
    "wof:placetype":"locality"
},
  "geometry": {"coordinates":[125.28655999999999,43.15288],"type":"Point"}
}