{
  "type": "Feature",
  "properties": {
    "gn:admin1_code":"30.0",
    "gn:asciiname":"Xianrenji",
    "gn:country_code":"CN",
    "gn:dem":95,
    "gn:feature_class":"P",
    "gn:feature_code":"PPL",
    "gn:name":"Xianrenji",
    "gn:population":0,
    "gn:timezone":"Asia/Shanghai",
    "iso:country":"CN",
    "name:zho_x_preferred":[
        "\u4ed9\u4eba\u8ff9"
    ],
    "wof:name":"Xianrenji",
    "wof:placetype":"locality"
},
  "geometry": {"coordinates":[113.60359,23.42318],"type":"Point"}
}