{
  "type": "Feature",
  "properties": {
    "gn:admin1_code":"19.0",
    "gn:asciiname":"Qianzhaojungou",
    "gn:country_code":"CN",
    "gn:dem":200,
    "gn:feature_class":"P",
    "gn:feature_code":"PPL",
    "gn:name":"Qianzhaojungou",
    "gn:population":0,
    "gn:timezone":"Asia/Shanghai",
    "iso:country":"CN",
    "name:zho_x_preferred":[
        "\u524d\u62db\u519b\u6c9f"
    ],
    "wof:name":"Qianzhaojungou",
    "wof:placetype":"locality"
},
  "geometry": {"coordinates":[121.113,41.3614],"type":"Point"}
}