{
  "type": "Feature",
  "properties": {
    "gn:admin1_code":"19.0",
    "gn:asciiname":"Xitacun",
    "gn:country_code":"CN",
    "gn:dem":114,
    "gn:feature_class":"P",
    "gn:feature_code":"PPL",
    "gn:name":"Xitacun",
    "gn:population":0,
    "gn:timezone":"Asia/Shanghai",
    "iso:country":"CN",
    "name:zho_x_preferred":[
        "\u897f\u5854\u6751"
    ],
    "wof:name":"Xitacun",
    "wof:placetype":"locality"
},
  "geometry": {"coordinates":[120.59699999999999,40.7241],"type":"Point"}
}