{
  "type": "Feature",
  "properties": {
    "gn:admin1_code":"29.0",
    "gn:asciiname":"Zaotang",
    "gn:country_code":"CN",
    "gn:dem":764,
    "gn:feature_class":"P",
    "gn:feature_code":"PPL",
    "gn:name":"Zaotang",
    "gn:population":0,
    "gn:timezone":"Asia/Shanghai",
    "iso:country":"CN",
    "name:zho_x_preferred":[
        "\u6fa1\u5858"
    ],
    "wof:name":"Zaotang",
    "wof:placetype":"locality"
},
  "geometry": {"coordinates":[98.9085,24.9628],"type":"Point"}
}