{
  "type": "Feature",
  "properties": {
    "gn:admin1_code":"25",
    "gn:asciiname":"Nandongzhuang",
    "gn:country_code":"CN",
    "gn:dem":57,
    "gn:feature_class":"P",
    "gn:feature_code":"PPL",
    "gn:name":"Nandongzhuang",
    "gn:population":0,
    "gn:timezone":"Asia/Shanghai",
    "iso:country":"CN",
    "name:zho_x_preferred":[
        "\u5357\u8463\u5e84"
    ],
    "wof:name":"Nandongzhuang",
    "wof:placetype":"locality"
},
  "geometry": {"coordinates":[115.36199999999999,34.8652],"type":"Point"}
}