{
  "type": "Feature",
  "properties": {
    "gn:admin1_code":"29.0",
    "gn:asciiname":"Wumulan",
    "gn:country_code":"CN",
    "gn:dem":1506,
    "gn:feature_class":"P",
    "gn:feature_code":"PPL",
    "gn:name":"Wumulan",
    "gn:population":0,
    "gn:timezone":"Asia/Shanghai",
    "iso:country":"CN",
    "name:zho_x_preferred":[
        "\u4e4c\u6728\u5170"
    ],
    "wof:name":"Wumulan",
    "wof:placetype":"locality"
},
  "geometry": {"coordinates":[99.1204,23.8227],"type":"Point"}
}