{
  "type": "Feature",
  "properties": {
    "gn:admin1_code":"9.0",
    "gn:asciiname":"Lianshuzhuang",
    "gn:country_code":"CN",
    "gn:dem":171,
    "gn:feature_class":"P",
    "gn:feature_code":"PPL",
    "gn:name":"Lianshuzhuang",
    "gn:population":0,
    "gn:timezone":"Asia/Shanghai",
    "iso:country":"CN",
    "name:zho_x_preferred":[
        "\u695d\u6811\u5e84"
    ],
    "wof:name":"Lianshuzhuang",
    "wof:placetype":"locality"
},
  "geometry": {"coordinates":[112.8766,33.78379],"type":"Point"}
}