{
  "type": "Feature",
  "properties": {
    "gn:admin1_code":"29.0",
    "gn:asciiname":"Licheda Xinzhai",
    "gn:country_code":"CN",
    "gn:dem":1881,
    "gn:feature_class":"P",
    "gn:feature_code":"PPL",
    "gn:name":"Licheda Xinzhai",
    "gn:population":0,
    "gn:timezone":"Asia/Shanghai",
    "iso:country":"CN",
    "name:zho_x_preferred":[
        "\u91cc\u626f\u5927\u65b0\u5be8"
    ],
    "wof:name":"Licheda Xinzhai",
    "wof:placetype":"locality"
},
  "geometry": {"coordinates":[103.839,23.9751],"type":"Point"}
}