{
  "type": "Feature",
  "properties": {
    "gn:admin1_code":"26.0",
    "gn:asciiname":"Shaoguoyuan",
    "gn:country_code":"CN",
    "gn:dem":1129,
    "gn:feature_class":"P",
    "gn:feature_code":"PPL",
    "gn:name":"Shaoguoyuan",
    "gn:population":0,
    "gn:timezone":"Asia/Shanghai",
    "iso:country":"CN",
    "name:zho_x_preferred":[
        "\u70e7\u9505\u9662"
    ],
    "wof:name":"Shaoguoyuan",
    "wof:placetype":"locality"
},
  "geometry": {"coordinates":[108.94204000000001,35.43916],"type":"Point"}
}