{
  "type": "Feature",
  "properties": {
    "gn:admin1_code":"1.0",
    "gn:asciiname":"Mawuzuicun",
    "gn:country_code":"CN",
    "gn:dem":21,
    "gn:feature_class":"P",
    "gn:feature_code":"PPL",
    "gn:name":"Mawuzuicun",
    "gn:population":0,
    "gn:timezone":"Asia/Shanghai",
    "iso:country":"CN",
    "name:zho_x_preferred":[
        "\u9a6c\u5434\u5480\u6751"
    ],
    "wof:name":"Mawuzuicun",
    "wof:placetype":"locality"
},
  "geometry": {"coordinates":[117.05823999999998,33.02813],"type":"Point"}
}