{
  "type": "Feature",
  "properties": {
    "gn:admin1_code":"29",
    "gn:asciiname":"Dilu",
    "gn:country_code":"CN",
    "gn:dem":798,
    "gn:feature_class":"P",
    "gn:feature_code":"PPL",
    "gn:name":"Dilu",
    "gn:population":0,
    "gn:timezone":"Asia/Shanghai",
    "iso:country":"CN",
    "name:zho_x_preferred":[
        "\u5e95\u9c81"
    ],
    "wof:name":"Dilu",
    "wof:placetype":"locality"
},
  "geometry": {"coordinates":[105.65000000000001,23.5346],"type":"Point"}
}