{
  "type": "Feature",
  "properties": {
    "gn:admin1_code":"4.0",
    "gn:asciiname":"Qinxing Shidui",
    "gn:country_code":"CN",
    "gn:dem":5,
    "gn:feature_class":"P",
    "gn:feature_code":"PPLF",
    "gn:name":"Qinxing Shidui",
    "gn:population":0,
    "gn:timezone":"Asia/Shanghai",
    "iso:country":"CN",
    "name:zho_x_preferred":[
        "\u52e4\u5174\u5341\u961f"
    ],
    "wof:name":"Qinxing Shidui",
    "wof:placetype":"locality"
},
  "geometry": {"coordinates":[120.22261,32.0054],"type":"Point"}
}