{
  "type": "Feature",
  "properties": {
    "gn:admin1_code":"2.0",
    "gn:asciiname":"Weifeng",
    "gn:country_code":"CN",
    "gn:dem":241,
    "gn:feature_class":"P",
    "gn:feature_code":"PPL",
    "gn:name":"Weifeng",
    "gn:population":0,
    "gn:timezone":"Asia/Shanghai",
    "iso:country":"CN",
    "name:zho_x_preferred":[
        "\u9b4f\u4e30"
    ],
    "wof:name":"Weifeng",
    "wof:placetype":"locality"
},
  "geometry": {"coordinates":[119.49208,29.74597],"type":"Point"}
}