{
  "type": "Feature",
  "properties": {
    "gn:admin1_code":"25.0",
    "gn:asciiname":"Dazhang Jiakuang",
    "gn:country_code":"CN",
    "gn:dem":58,
    "gn:feature_class":"P",
    "gn:feature_code":"PPL",
    "gn:name":"Dazhang Jiakuang",
    "gn:population":0,
    "gn:timezone":"Asia/Shanghai",
    "iso:country":"CN",
    "name:zho_x_preferred":[
        "\u5927\u5f20\u5bb6\u593c"
    ],
    "wof:name":"Dazhang Jiakuang",
    "wof:placetype":"locality"
},
  "geometry": {"coordinates":[121.56944,37.32059],"type":"Point"}
}