{
  "type": "Feature",
  "properties": {
    "gn:admin1_code":"30",
    "gn:asciiname":"Daduitou",
    "gn:country_code":"CN",
    "gn:dem":335,
    "gn:feature_class":"P",
    "gn:feature_code":"PPL",
    "gn:name":"Daduitou",
    "gn:population":0,
    "gn:timezone":"Asia/Urumqi",
    "iso:country":"CN",
    "name:zho_x_preferred":[
        "\u5927\u5bf9\u5934"
    ],
    "wof:name":"Daduitou",
    "wof:placetype":"locality"
},
  "geometry": {"coordinates":[111.19815,21.93092],"type":"Point"}
}