{
  "type": "Feature",
  "properties": {
    "gn:admin1_code":"15.0",
    "gn:asciiname":"Zui'er",
    "gn:country_code":"CN",
    "gn:dem":1750,
    "gn:feature_class":"P",
    "gn:feature_code":"PPL",
    "gn:name":"Zui\u2019er",
    "gn:population":0,
    "gn:timezone":"Asia/Shanghai",
    "iso:country":"CN",
    "name:und_x_variant":[
        "Zui\u2019er"
    ],
    "name:zho_x_preferred":[
        "\u5480\u513f"
    ],
    "wof:name":"Zui'er",
    "wof:placetype":"locality"
},
  "geometry": {"coordinates":[105.008,34.6895],"type":"Point"}
}