{
  "type": "Feature",
  "properties": {
    "gn:admin1_code":"30",
    "gn:asciiname":"Huatingcun",
    "gn:country_code":"CN",
    "gn:dem":8,
    "gn:feature_class":"P",
    "gn:feature_code":"PPL",
    "gn:name":"Huatingcun",
    "gn:population":0,
    "gn:timezone":"Asia/Urumqi",
    "iso:country":"CN",
    "name:zho_x_preferred":[
        "\u534e\u505c\u6751"
    ],
    "wof:name":"Huatingcun",
    "wof:placetype":"locality"
},
  "geometry": {"coordinates":[109.80291,20.84],"type":"Point"}
}