{
  "type": "Feature",
  "properties": {
    "gn:admin1_code":"8.0",
    "gn:asciiname":"Nenjiang Caifaduan",
    "gn:country_code":"CN",
    "gn:dem":364,
    "gn:feature_class":"P",
    "gn:feature_code":"PPLF",
    "gn:name":"Nenjiang Caifaduan",
    "gn:population":0,
    "gn:timezone":"Asia/Shanghai",
    "iso:country":"CN",
    "name:zho_x_preferred":[
        "\u5ae9\u6c5f\u91c7\u4f10\u6bb5"
    ],
    "wof:name":"Nenjiang Caifaduan",
    "wof:placetype":"locality"
},
  "geometry": {"coordinates":[125.81356,50.72933],"type":"Point"}
}