{
  "type": "Feature",
  "properties": {
    "gn:admin1_code":"11.0",
    "gn:asciiname":"Yaojialong",
    "gn:country_code":"CN",
    "gn:dem":276,
    "gn:feature_class":"P",
    "gn:feature_code":"PPL",
    "gn:name":"Yaojialong",
    "gn:population":0,
    "gn:timezone":"Asia/Shanghai",
    "iso:country":"CN",
    "name:zho_x_preferred":[
        "\u59da\u5bb6\u5784"
    ],
    "wof:name":"Yaojialong",
    "wof:placetype":"locality"
},
  "geometry": {"coordinates":[109.78089,27.40579],"type":"Point"}
}