{
  "type": "Feature",
  "properties": {
    "gn:admin1_code":"8.0",
    "gn:asciiname":"Qianyangcun",
    "gn:country_code":"CN",
    "gn:dem":325,
    "gn:feature_class":"P",
    "gn:feature_code":"PPL",
    "gn:name":"Qianyangcun",
    "gn:population":0,
    "gn:timezone":"Asia/Shanghai",
    "iso:country":"CN",
    "name:zho_x_preferred":[
        "\u524d\u9633\u6751"
    ],
    "wof:name":"Qianyangcun",
    "wof:placetype":"locality"
},
  "geometry": {"coordinates":[129.21386999999999,44.38041],"type":"Point"}
}