{
  "type": "Feature",
  "properties": {
    "gn:admin1_code":"19.0",
    "gn:asciiname":"Xiabajiazicun",
    "gn:country_code":"CN",
    "gn:dem":200,
    "gn:feature_class":"P",
    "gn:feature_code":"PPL",
    "gn:name":"Xiabajiazicun",
    "gn:population":0,
    "gn:timezone":"Asia/Shanghai",
    "iso:country":"CN",
    "name:zho_x_preferred":[
        "\u4e0b\u516b\u5bb6\u5b50\u6751"
    ],
    "wof:name":"Xiabajiazicun",
    "wof:placetype":"locality"
},
  "geometry": {"coordinates":[121.51300000000001,42.0892],"type":"Point"}
}