{
  "type": "Feature",
  "properties": {
    "gn:admin1_code":"26.0",
    "gn:asciiname":"Wafangzi",
    "gn:country_code":"CN",
    "gn:dem":1296,
    "gn:feature_class":"P",
    "gn:feature_code":"PPL",
    "gn:name":"Wafangzi",
    "gn:population":0,
    "gn:timezone":"Asia/Shanghai",
    "iso:country":"CN",
    "name:und_x_variant":[
        "\u74e6\u623f\u5b50"
    ],
    "wof:name":"Wafangzi",
    "wof:placetype":"locality"
},
  "geometry": {"coordinates":[106.81782,32.75418],"type":"Point"}
}