{
  "type": "Feature",
  "properties": {
    "gn:admin1_code":"25",
    "gn:asciiname":"Matou Dianzi",
    "gn:country_code":"CN",
    "gn:dem":330,
    "gn:feature_class":"P",
    "gn:feature_code":"PPL",
    "gn:name":"Matou Dianzi",
    "gn:population":0,
    "gn:timezone":"Asia/Shanghai",
    "iso:country":"CN",
    "name:zho_x_preferred":[
        "\u9a6c\u5934\u5e97\u5b50"
    ],
    "wof:name":"Matou Dianzi",
    "wof:placetype":"locality"
},
  "geometry": {"coordinates":[118.55200000000001,36.1398],"type":"Point"}
}