{
  "type": "Feature",
  "properties": {
    "gn:admin1_code":"4.0",
    "gn:asciiname":"Jizhuangcun",
    "gn:country_code":"CN",
    "gn:dem":36,
    "gn:feature_class":"P",
    "gn:feature_code":"PPL",
    "gn:name":"Jizhuangcun",
    "gn:population":0,
    "gn:timezone":"Asia/Shanghai",
    "iso:country":"CN",
    "name:zho_x_preferred":[
        "\u7eaa\u5e84\u6751"
    ],
    "wof:name":"Jizhuangcun",
    "wof:placetype":"locality"
},
  "geometry": {"coordinates":[116.98633,34.74010999999999],"type":"Point"}
}