{
  "type": "Feature",
  "properties": {
    "gn:admin1_code":"4.0",
    "gn:asciiname":"Maogongpucun",
    "gn:country_code":"CN",
    "gn:dem":26,
    "gn:feature_class":"P",
    "gn:feature_code":"PPL",
    "gn:name":"Maogongpucun",
    "gn:population":0,
    "gn:timezone":"Asia/Shanghai",
    "iso:country":"CN",
    "name:zho_x_preferred":[
        "\u6bdb\u516c\u57d4\u6751"
    ],
    "wof:name":"Maogongpucun",
    "wof:placetype":"locality"
},
  "geometry": {"coordinates":[119.0025,31.4231],"type":"Point"}
}