{
  "type": "Feature",
  "properties": {
    "gn:admin1_code":"5.0",
    "gn:asciiname":"Qianjiacun",
    "gn:country_code":"CN",
    "gn:dem":222,
    "gn:feature_class":"P",
    "gn:feature_code":"PPL",
    "gn:name":"Qianjiacun",
    "gn:population":0,
    "gn:timezone":"Asia/Shanghai",
    "iso:country":"CN",
    "name:zho_x_preferred":[
        "\u94b1\u5bb6\u6751"
    ],
    "wof:name":"Qianjiacun",
    "wof:placetype":"locality"
},
  "geometry": {"coordinates":[125.71341,43.89022],"type":"Point"}
}