{
  "type": "Feature",
  "properties": {
    "gn:admin1_code":"12.0",
    "gn:asciiname":"Botang",
    "gn:country_code":"CN",
    "gn:dem":26,
    "gn:feature_class":"P",
    "gn:feature_code":"PPL",
    "gn:name":"Botang",
    "gn:population":0,
    "gn:timezone":"Asia/Shanghai",
    "iso:country":"CN",
    "name:zho_x_preferred":[
        "\u6cca\u5858"
    ],
    "wof:name":"Botang",
    "wof:placetype":"locality"
},
  "geometry": {"coordinates":[113.90313999999999,30.04749],"type":"Point"}
}