{
  "type": "Feature",
  "properties": {
    "gn:admin1_code":"31.0",
    "gn:asciiname":"Lanxi",
    "gn:country_code":"CN",
    "gn:dem":83,
    "gn:feature_class":"P",
    "gn:feature_code":"PPL",
    "gn:name":"Lanxi",
    "gn:population":0,
    "gn:timezone":"Asia/Shanghai",
    "iso:country":"CN",
    "name:ara_x_preferred":[
        "\u0644\u0627\u0646\u0643\u0633\u064a"
    ],
    "name:ben_x_preferred":[
        "\u09b2\u09cd\u09af\u09be\u09a8\u09b6\u09bf"
    ],
    "name:ceb_x_preferred":[
        "Lanxi"
    ],
    "name:deu_x_preferred":[
        "Lanxi"
    ],
    "name:ell_x_preferred":[
        "\u039b\u03ac\u03bd\u03be\u03b9"
    ],
    "name:eng_x_preferred":[
        "Lanxi"
    ],
    "name:fas_x_preferred":[
        "\u0644\u0627\u0646\u06a9\u0633\u06cc"
    ],
    "name:fra_x_preferred":[
        "Lanxi"
    ],
    "name:heb_x_preferred":[
        "\u05dc\u05e0\u05e7\u05e1\u05d9"
    ],
    "name:hin_x_preferred":[
        "\u0932\u0948\u0902\u0915\u094d\u0938\u0940"
    ],
    "name:hun_x_preferred":[
        "Lanxi"
    ],
    "name:ind_x_preferred":[
        "Lanxi"
    ],
    "name:ita_x_preferred":[
        "Lanxi"
    ],
    "name:kor_x_preferred":[
        "\ub780\uc2dc"
    ],
    "name:mlg_x_preferred":[
        "Lanxi"
    ],
    "name:nld_x_preferred":[
        "Lanxi"
    ],
    "name:nor_x_preferred":[
        "Lanxi"
    ],
    "name:pol_x_preferred":[
        "Lanxi"
    ],
    "name:por_x_preferred":[
        "Lanxi"
    ],
    "name:rus_x_preferred":[
        "\u041b\u0430\u043d\u044c\u0441\u0438"
    ],
    "name:spa_x_preferred":[
        "Lanxi"
    ],
    "name:tur_x_preferred":[
        "Lanxi"
    ],
    "name:ukr_x_preferred":[
        "\u041b\u0430\u043d\u044c\u0441\u0456"
    ],
    "name:urd_x_preferred":[
        "\u0644\u06cc\u0646\u0632\u06cc"
    ],
    "name:vie_x_preferred":[
        "Lan Kh\u00ea"
    ],
    "name:zho_x_preferred":[
        "\u5170\u6eaa"
    ],
    "wof:name":"Lanxi",
    "wof:placetype":"locality"
},
  "geometry": {"coordinates":[110.50445999999999,19.54404],"type":"Point"}
}