{
  "type": "Feature",
  "properties": {
    "gn:admin1_code":"29.0",
    "gn:asciiname":"Jiada",
    "gn:country_code":"CN",
    "gn:dem":1853,
    "gn:feature_class":"P",
    "gn:feature_code":"PPL",
    "gn:name":"Jiada",
    "gn:population":0,
    "gn:timezone":"Asia/Shanghai",
    "iso:country":"CN",
    "name:zho_x_preferred":[
        "\u621b\u8fbe"
    ],
    "wof:name":"Jiada",
    "wof:placetype":"locality"
},
  "geometry": {"coordinates":[104.224,25.4819],"type":"Point"}
}