{
  "type": "Feature",
  "properties": {
    "gn:admin1_code":"32.0",
    "gn:asciiname":"Fengjiagou",
    "gn:country_code":"CN",
    "gn:dem":649,
    "gn:feature_class":"P",
    "gn:feature_code":"PPL",
    "gn:name":"Fengjiagou",
    "gn:population":0,
    "gn:timezone":"Asia/Shanghai",
    "iso:country":"CN",
    "name:zho_x_preferred":[
        "\u5c01\u5bb6\u6c9f"
    ],
    "wof:name":"Fengjiagou",
    "wof:placetype":"locality"
},
  "geometry": {"coordinates":[103.02311,30.01953],"type":"Point"}
}