{
  "type": "Feature",
  "properties": {
    "gn:admin1_code":"30.0",
    "gn:asciiname":"Jiangjucun",
    "gn:country_code":"CN",
    "gn:dem":317,
    "gn:feature_class":"P",
    "gn:feature_code":"PPL",
    "gn:name":"Jiangjucun",
    "gn:population":0,
    "gn:timezone":"Asia/Shanghai",
    "iso:country":"CN",
    "name:zho_x_preferred":[
        "\u6c5f\u5480\u6751"
    ],
    "wof:name":"Jiangjucun",
    "wof:placetype":"locality"
},
  "geometry": {"coordinates":[112.48826,24.21039],"type":"Point"}
}