{
  "type": "Feature",
  "properties": {
    "gn:admin1_code":"32.0",
    "gn:asciiname":"Niudi",
    "gn:country_code":"CN",
    "gn:dem":2551,
    "gn:feature_class":"P",
    "gn:feature_code":"PPL",
    "gn:name":"Niudi",
    "gn:population":0,
    "gn:timezone":"Asia/Shanghai",
    "iso:country":"CN",
    "name:zho_x_preferred":[
        "\u7ebd\u5e95"
    ],
    "wof:name":"Niudi",
    "wof:placetype":"locality"
},
  "geometry": {"coordinates":[101.092,29.7585],"type":"Point"}
}