{
  "type": "Feature",
  "properties": {
    "gn:admin1_code":"32.0",
    "gn:asciiname":"Jianfengding",
    "gn:country_code":"CN",
    "gn:dem":530,
    "gn:feature_class":"P",
    "gn:feature_code":"PPL",
    "gn:name":"Jianfengding",
    "gn:population":0,
    "gn:timezone":"Asia/Shanghai",
    "iso:country":"CN",
    "name:zho_x_preferred":[
        "\u5c16\u5cf0\u9876"
    ],
    "wof:name":"Jianfengding",
    "wof:placetype":"locality"
},
  "geometry": {"coordinates":[103.51000000000001,29.71],"type":"Point"}
}