{
  "type": "Feature",
  "properties": {
    "gn:admin1_code":"16.0",
    "gn:asciiname":"Taixing",
    "gn:country_code":"CN",
    "gn:dem":47,
    "gn:feature_class":"P",
    "gn:feature_code":"PPL",
    "gn:name":"Taixing",
    "gn:population":0,
    "gn:timezone":"Asia/Shanghai",
    "iso:country":"CN",
    "name:ceb_x_preferred":[
        "Taixing Shi"
    ],
    "name:cym_x_preferred":[
        "Taixing"
    ],
    "name:deu_x_preferred":[
        "Taixing"
    ],
    "name:fas_x_preferred":[
        "\u062a\u0627\u06cc\u0634\u06cc\u0646\u06af"
    ],
    "name:fra_x_preferred":[
        "Taixing"
    ],
    "name:ita_x_preferred":[
        "Taixing"
    ],
    "name:jpn_x_preferred":[
        "\u6cf0\u8208\u5e02"
    ],
    "name:kik_x_preferred":[
        "Taixing"
    ],
    "name:kor_x_preferred":[
        "\ud0c0\uc774\uc2f1\uc2dc"
    ],
    "name:mlg_x_preferred":[
        "Taixing"
    ],
    "name:nld_x_preferred":[
        "Taixing"
    ],
    "name:nor_x_preferred":[
        "Taixing"
    ],
    "name:rus_x_preferred":[
        "\u0422\u0430\u0439\u0441\u0438\u043d"
    ],
    "name:swe_x_preferred":[
        "Taixing"
    ],
    "name:tgl_x_preferred":[
        "Taixing"
    ],
    "name:urd_x_preferred":[
        "\u062a\u0627\u0626\u06cc\u0634\u0646\u06af"
    ],
    "name:vie_x_preferred":[
        "Th\u00e1i H\u01b0ng"
    ],
    "name:zho_x_preferred":[
        "\u592a\u5174"
    ],
    "name:zho_x_variant":[
        "\u6cf0\u5174\u5e02"
    ],
    "wof:name":"Taixing",
    "wof:placetype":"locality"
},
  "geometry": {"coordinates":[109.80500000000001,23.2543],"type":"Point"}
}