{
  "type": "Feature",
  "properties": {
    "gn:admin1_code":"05",
    "gn:asciiname":"Fuxian",
    "gn:cc2":"CN",
    "gn:country_code":"CN",
    "gn:dem":184,
    "gn:feature_class":"P",
    "gn:feature_code":"PPL",
    "gn:name":"Fuxian",
    "gn:population":0,
    "gn:timezone":"Asia/Shanghai",
    "iso:country":"CN",
    "name:und_x_variant":[
        "Fu-hsien",
        "Fuxian"
    ],
    "wof:name":"Fuxian",
    "wof:placetype":"locality"
},
  "geometry": {"coordinates":[123.85639,43.95389],"type":"Point"}
}