{
  "type": "Feature",
  "properties": {
    "gn:admin1_code":"11.0",
    "gn:asciiname":"Huangjingang",
    "gn:country_code":"CN",
    "gn:dem":114,
    "gn:feature_class":"P",
    "gn:feature_code":"PPL",
    "gn:name":"Huangjingang",
    "gn:population":0,
    "gn:timezone":"Asia/Shanghai",
    "iso:country":"CN",
    "name:zho_x_preferred":[
        "\u9ec4\u91d1\u6e2f"
    ],
    "wof:name":"Huangjingang",
    "wof:placetype":"locality"
},
  "geometry": {"coordinates":[113.57249,29.2234],"type":"Point"}
}