{
  "type": "Feature",
  "properties": {
    "gn:admin1_code":"20.0",
    "gn:asciiname":"Haolibao Gacha",
    "gn:country_code":"CN",
    "gn:dem":646,
    "gn:feature_class":"P",
    "gn:feature_code":"PPL",
    "gn:name":"Haolibao Gacha",
    "gn:population":0,
    "gn:timezone":"Asia/Shanghai",
    "iso:country":"CN",
    "name:zho_x_preferred":[
        "\u6d69\u529b\u4fdd\u560e\u67e5"
    ],
    "wof:name":"Haolibao Gacha",
    "wof:placetype":"locality"
},
  "geometry": {"coordinates":[119.43517,48.90709],"type":"Point"}
}