{
  "type": "Feature",
  "properties": {
    "gn:admin1_code":"31.0",
    "gn:asciiname":"Baopang",
    "gn:country_code":"CN",
    "gn:dem":118,
    "gn:feature_class":"P",
    "gn:feature_code":"PPL",
    "gn:name":"Baopang",
    "gn:population":0,
    "gn:timezone":"Asia/Shanghai",
    "iso:country":"CN",
    "name:zho_x_preferred":[
        "\u62b1\u5e9e"
    ],
    "wof:name":"Baopang",
    "wof:placetype":"locality"
},
  "geometry": {"coordinates":[109.59448,19.77991],"type":"Point"}
}