{
  "type": "Feature",
  "properties": {
    "gn:admin1_code":"8.0",
    "gn:asciiname":"Xiangyang",
    "gn:country_code":"CN",
    "gn:dem":96,
    "gn:feature_class":"P",
    "gn:feature_code":"PPLA4",
    "gn:name":"Xiangyang",
    "gn:population":0,
    "gn:timezone":"Asia/Shanghai",
    "iso:country":"CN",
    "name:und_x_variant":[
        "Xiangyang Xiang"
    ],
    "name:zho_x_preferred":[
        "\u5411\u9633"
    ],
    "name:zho_x_variant":[
        "\u5411\u9633\u4e61"
    ],
    "wof:name":"Xiangyang",
    "wof:placetype":"locality"
},
  "geometry": {"coordinates":[129.75706,49.18081],"type":"Point"}
}