{
  "type": "Feature",
  "properties": {
    "gn:admin1_code":"3.0",
    "gn:asciiname":"Dianqian",
    "gn:country_code":"CN",
    "gn:dem":199,
    "gn:feature_class":"P",
    "gn:feature_code":"PPL",
    "gn:name":"Dianqian",
    "gn:population":0,
    "gn:timezone":"Asia/Shanghai",
    "iso:country":"CN",
    "name:zho_x_preferred":[
        "\u5e97\u524d"
    ],
    "wof:name":"Dianqian",
    "wof:placetype":"locality"
},
  "geometry": {"coordinates":[115.096,28.6579],"type":"Point"}
}