{
  "type": "Feature",
  "properties": {
    "gn:admin1_code":"5.0",
    "gn:asciiname":"Qianchaoyangpo",
    "gn:country_code":"CN",
    "gn:dem":135,
    "gn:feature_class":"P",
    "gn:feature_code":"PPL",
    "gn:name":"Qianchaoyangpo",
    "gn:population":0,
    "gn:timezone":"Asia/Shanghai",
    "iso:country":"CN",
    "name:zho_x_preferred":[
        "\u524d\u671d\u9633\u5761"
    ],
    "wof:name":"Qianchaoyangpo",
    "wof:placetype":"locality"
},
  "geometry": {"coordinates":[123.5411,45.44385],"type":"Point"}
}