{
  "type": "Feature",
  "properties": {
    "gn:admin1_code":"30",
    "gn:asciiname":"Luma",
    "gn:country_code":"CN",
    "gn:dem":44,
    "gn:feature_class":"P",
    "gn:feature_code":"PPL",
    "gn:name":"Luma",
    "gn:population":0,
    "gn:timezone":"Asia/Urumqi",
    "iso:country":"CN",
    "name:zho_x_preferred":[
        "\u7984\u9a6c"
    ],
    "wof:name":"Luma",
    "wof:placetype":"locality"
},
  "geometry": {"coordinates":[109.94826,20.64595],"type":"Point"}
}