{
  "type": "Feature",
  "properties": {
    "gn:admin1_code":"3.0",
    "gn:asciiname":"Huangyuan",
    "gn:country_code":"CN",
    "gn:dem":233,
    "gn:feature_class":"P",
    "gn:feature_code":"PPL",
    "gn:name":"Huangyuan",
    "gn:population":0,
    "gn:timezone":"Asia/Shanghai",
    "iso:country":"CN",
    "name:und_x_variant":[
        "\u749c\u6e90"
    ],
    "wof:name":"Huangyuan",
    "wof:placetype":"locality"
},
  "geometry": {"coordinates":[114.56204,27.08275],"type":"Point"}
}