{
  "type": "Feature",
  "properties": {
    "gn:admin1_code":"5.0",
    "gn:asciiname":"Tuanjietun",
    "gn:country_code":"CN",
    "gn:dem":143,
    "gn:feature_class":"P",
    "gn:feature_code":"PPL",
    "gn:name":"Tuanjietun",
    "gn:population":0,
    "gn:timezone":"Asia/Shanghai",
    "iso:country":"CN",
    "name:zho_x_preferred":[
        "\u56e2\u7ed3\u5c6f"
    ],
    "wof:name":"Tuanjietun",
    "wof:placetype":"locality"
},
  "geometry": {"coordinates":[123.50834999999999,44.00741],"type":"Point"}
}