{
  "type": "Feature",
  "properties": {
    "gn:admin1_code":"15.0",
    "gn:asciiname":"Zuoweiying",
    "gn:country_code":"CN",
    "gn:dem":2043,
    "gn:feature_class":"P",
    "gn:feature_code":"PPL",
    "gn:name":"Zuoweiying",
    "gn:population":0,
    "gn:timezone":"Asia/Shanghai",
    "iso:country":"CN",
    "name:zho_x_preferred":[
        "\u5de6\u536b\u8425"
    ],
    "wof:name":"Zuoweiying",
    "wof:placetype":"locality"
},
  "geometry": {"coordinates":[100.501,38.5893],"type":"Point"}
}