{
  "type": "Feature",
  "properties": {
    "gn:admin1_code":"29.0",
    "gn:asciiname":"Shitouzhai",
    "gn:country_code":"CN",
    "gn:dem":1788,
    "gn:feature_class":"P",
    "gn:feature_code":"PPL",
    "gn:name":"Shitouzhai",
    "gn:population":0,
    "gn:timezone":"Asia/Shanghai",
    "iso:country":"CN",
    "name:zho_x_preferred":[
        "\u77f3\u5934\u5be8"
    ],
    "wof:name":"Shitouzhai",
    "wof:placetype":"locality"
},
  "geometry": {"coordinates":[100.53700000000001,21.8999],"type":"Point"}
}