{
  "type": "Feature",
  "properties": {
    "gn:admin1_code":"12.0",
    "gn:asciiname":"Lishiwan",
    "gn:country_code":"CN",
    "gn:dem":480,
    "gn:feature_class":"P",
    "gn:feature_code":"PPL",
    "gn:name":"Lishiwan",
    "gn:population":0,
    "gn:timezone":"Asia/Shanghai",
    "iso:country":"CN",
    "name:zho_x_preferred":[
        "\u674e\u67ff\u6e7e"
    ],
    "wof:name":"Lishiwan",
    "wof:placetype":"locality"
},
  "geometry": {"coordinates":[111.82196,31.56183],"type":"Point"}
}