{
  "type": "Feature",
  "properties": {
    "gn:admin1_code":"6.0",
    "gn:asciiname":"WaLongwa",
    "gn:country_code":"CN",
    "gn:dem":2365,
    "gn:feature_class":"P",
    "gn:feature_code":"PPL",
    "gn:name":"WaLongwa",
    "gn:population":0,
    "gn:timezone":"Asia/Shanghai",
    "iso:country":"CN",
    "name:und_x_variant":[
        "\u6d3c\u9f99\u6d3c"
    ],
    "wof:name":"WaLongwa",
    "wof:placetype":"locality"
},
  "geometry": {"coordinates":[102.40412999999999,35.75257],"type":"Point"}
}