{
  "type": "Feature",
  "properties": {
    "gn:admin1_code":"12.0",
    "gn:asciiname":"Yaowan",
    "gn:country_code":"CN",
    "gn:dem":144,
    "gn:feature_class":"P",
    "gn:feature_code":"PPLA4",
    "gn:name":"Yaowan",
    "gn:population":0,
    "gn:timezone":"Asia/Shanghai",
    "iso:country":"CN",
    "name:und_x_variant":[
        "\u7a91\u6e7e",
        "Yaowan Xiang"
    ],
    "name:zho_x_preferred":[
        "\u7a91\u6e7e\u4e61"
    ],
    "wof:name":"Yaowan",
    "wof:placetype":"locality"
},
  "geometry": {"coordinates":[111.30043999999999,30.7142],"type":"Point"}
}