{
  "type": "Feature",
  "properties": {
    "gn:admin1_code":"32",
    "gn:asciiname":"Xiuzhong",
    "gn:country_code":"CN",
    "gn:dem":914,
    "gn:feature_class":"P",
    "gn:feature_code":"PPL",
    "gn:name":"Xiuzhong",
    "gn:population":0,
    "gn:timezone":"Asia/Shanghai",
    "iso:country":"CN",
    "name:zho_x_preferred":[
        "\u79c0\u949f"
    ],
    "wof:name":"Xiuzhong",
    "wof:placetype":"locality"
},
  "geometry": {"coordinates":[105.28679,32.00127],"type":"Point"}
}