{
  "type": "Feature",
  "properties": {
    "gn:admin1_code":"32",
    "gn:asciiname":"Gaocao",
    "gn:country_code":"CN",
    "gn:dem":1489,
    "gn:feature_class":"P",
    "gn:feature_code":"PPL",
    "gn:name":"Gaocao",
    "gn:population":0,
    "gn:timezone":"Asia/Shanghai",
    "iso:country":"CN",
    "name:und_x_variant":[
        "Kao-ts\u2019ao-pa",
        "Gaocaoba",
        "Gaocao"
    ],
    "name:zho_x_preferred":[
        "\u9ad8\u8349"
    ],
    "wof:name":"Gaocao",
    "wof:placetype":"locality"
},
  "geometry": {"coordinates":[102.16941,27.79216],"type":"Point"}
}