{
  "type": "Feature",
  "properties": {
    "gn:admin1_code":"3.0",
    "gn:asciiname":"Yuantou",
    "gn:country_code":"CN",
    "gn:dem":245,
    "gn:feature_class":"P",
    "gn:feature_code":"PPL",
    "gn:name":"Yuantou",
    "gn:population":0,
    "gn:timezone":"Asia/Shanghai",
    "iso:country":"CN",
    "name:und_x_variant":[
        "\u6e90\u5934"
    ],
    "wof:name":"Yuantou",
    "wof:placetype":"locality"
},
  "geometry": {"coordinates":[115.36021,26.83202],"type":"Point"}
}