{
  "type": "Feature",
  "properties": {
    "gn:admin1_code":"24.0",
    "gn:asciiname":"Zhanghupocun",
    "gn:country_code":"CN",
    "gn:dem":652,
    "gn:feature_class":"P",
    "gn:feature_code":"PPL",
    "gn:name":"Zhanghupocun",
    "gn:population":0,
    "gn:timezone":"Asia/Shanghai",
    "iso:country":"CN",
    "name:zho_x_preferred":[
        "\u5f20\u6237\u5761\u6751"
    ],
    "wof:name":"Zhanghupocun",
    "wof:placetype":"locality"
},
  "geometry": {"coordinates":[110.86788,35.46003],"type":"Point"}
}