{
  "type": "Feature",
  "properties": {
    "gn:admin1_code":"11.0",
    "gn:asciiname":"Shengtangpu",
    "gn:country_code":"CN",
    "gn:dem":114,
    "gn:feature_class":"P",
    "gn:feature_code":"PPL",
    "gn:name":"Shengtangpu",
    "gn:population":0,
    "gn:timezone":"Asia/Shanghai",
    "iso:country":"CN",
    "name:zho_x_preferred":[
        "\u7b19\u5858\u94fa"
    ],
    "wof:name":"Shengtangpu",
    "wof:placetype":"locality"
},
  "geometry": {"coordinates":[113.46616000000002,27.27802],"type":"Point"}
}