{
  "type": "Feature",
  "properties": {
    "gn:admin1_code":"30",
    "gn:asciiname":"Tianxinlou",
    "gn:country_code":"CN",
    "gn:dem":148,
    "gn:feature_class":"P",
    "gn:feature_code":"PPL",
    "gn:name":"Tianxinlou",
    "gn:population":0,
    "gn:timezone":"Asia/Shanghai",
    "iso:country":"CN",
    "name:und_x_variant":[
        "\u7530\u5fc3\u697c"
    ],
    "wof:name":"Tianxinlou",
    "wof:placetype":"locality"
},
  "geometry": {"coordinates":[115.11546,23.73967],"type":"Point"}
}