{
  "type": "Feature",
  "properties": {
    "gn:admin1_code":"25",
    "gn:asciiname":"Baoningcun",
    "gn:country_code":"CN",
    "gn:dem":51,
    "gn:feature_class":"P",
    "gn:feature_code":"PPL",
    "gn:name":"Baoningcun",
    "gn:population":0,
    "gn:timezone":"Asia/Shanghai",
    "iso:country":"CN",
    "name:und_x_variant":[
        "Baoning",
        "Baoningcun"
    ],
    "name:zho_x_preferred":[
        "\u4fdd\u5b81"
    ],
    "name:zho_x_variant":[
        "\u4fdd\u5b81\u6751"
    ],
    "wof:name":"Baoningcun",
    "wof:placetype":"locality"
},
  "geometry": {"coordinates":[115.56901999999999,35.17522],"type":"Point"}
}