{
  "type": "Feature",
  "properties": {
    "gn:admin1_code":"29.0",
    "gn:asciiname":"Gaojiaoyan",
    "gn:country_code":"CN",
    "gn:dem":1852,
    "gn:feature_class":"P",
    "gn:feature_code":"PPL",
    "gn:name":"Gaojiaoyan",
    "gn:population":0,
    "gn:timezone":"Asia/Shanghai",
    "iso:country":"CN",
    "name:zho_x_preferred":[
        "\u9ad8\u811a\u5ca9"
    ],
    "wof:name":"Gaojiaoyan",
    "wof:placetype":"locality"
},
  "geometry": {"coordinates":[98.6797,25.69400000000001],"type":"Point"}
}