{
  "type": "Feature",
  "properties": {
    "gn:admin1_code":"32.0",
    "gn:asciiname":"Murong",
    "gn:country_code":"CN",
    "gn:dem":3192,
    "gn:feature_class":"P",
    "gn:feature_code":"PPL",
    "gn:name":"Murong",
    "gn:population":0,
    "gn:timezone":"Asia/Shanghai",
    "iso:country":"CN",
    "name:zho_x_preferred":[
        "\u6728\u7ed2"
    ],
    "wof:name":"Murong",
    "wof:placetype":"locality"
},
  "geometry": {"coordinates":[101.12644,30.38167],"type":"Point"}
}