{
  "type": "Feature",
  "properties": {
    "gn:admin1_code":"32.0",
    "gn:asciiname":"Murong",
    "gn:country_code":"CN",
    "gn:dem":3192,
    "gn:feature_class":"P",
    "gn:feature_code":"PPL",
    "gn:name":"Murong",
    "gn:population":0,
    "gn:timezone":"Asia/Shanghai",
    "iso:country":"CN",
    "name:bul_x_preferred":[
        "\u041c\u0443\u0436\u0443\u043d"
    ],
    "name:fra_x_preferred":[
        "Murong"
    ],
    "name:kor_x_preferred":[
        "\ubaa8\uc6a9\uc528"
    ],
    "name:mon_x_preferred":[
        "\u041c\u0443\u044e\u043d"
    ],
    "name:rus_x_preferred":[
        "\u041c\u0443\u0436\u0443\u043d"
    ],
    "name:vie_x_preferred":[
        "M\u1ed9 Dung"
    ],
    "name:zho_x_preferred":[
        "\u6728\u7ed2"
    ],
    "name:zho_x_variant":[
        "\u6155\u5bb9\u90e8"
    ],
    "wof:name":"Murong",
    "wof:placetype":"locality"
},
  "geometry": {"coordinates":[101.12644,30.38167],"type":"Point"}
}