{
  "type": "Feature",
  "properties": {
    "gn:admin1_code":"18",
    "gn:asciiname":"Wangtuo",
    "gn:country_code":"CN",
    "gn:dem":463,
    "gn:feature_class":"P",
    "gn:feature_code":"PPL",
    "gn:name":"Wangtuo",
    "gn:population":0,
    "gn:timezone":"Asia/Shanghai",
    "iso:country":"CN",
    "name:zho_x_preferred":[
        "\u738b\u5768"
    ],
    "wof:name":"Wangtuo",
    "wof:placetype":"locality"
},
  "geometry": {"coordinates":[108.29600000000001,29.0206],"type":"Point"}
}