{
  "type": "Feature",
  "properties": {
    "gn:admin1_code":"3.0",
    "gn:asciiname":"Huairen",
    "gn:country_code":"CN",
    "gn:dem":177,
    "gn:feature_class":"P",
    "gn:feature_code":"PPL",
    "gn:name":"Huairen",
    "gn:population":0,
    "gn:timezone":"Asia/Shanghai",
    "iso:country":"CN",
    "name:ceb_x_preferred":[
        "Huairen Xian"
    ],
    "name:deu_x_preferred":[
        "Huairen"
    ],
    "name:fas_x_preferred":[
        "\u0634\u0647\u0631\u0633\u062a\u0627\u0646 \u0647\u0648\u0627\u06cc\u0631\u0646"
    ],
    "name:ita_x_preferred":[
        "Huairen"
    ],
    "name:jpn_x_preferred":[
        "\u61d0\u4ec1\u5e02"
    ],
    "name:kor_x_preferred":[
        "\ud654\uc774\ub7f0\uc2dc"
    ],
    "name:nor_x_preferred":[
        "Huairen"
    ],
    "name:rus_x_preferred":[
        "\u0425\u0443\u0430\u0439\u0436\u044d\u043d\u044c"
    ],
    "name:swe_x_preferred":[
        "Huairen"
    ],
    "name:und_x_variant":[
        "\u6000\u4ec1"
    ],
    "name:urd_x_preferred":[
        "\u06c1\u0648\u0627\u06cc\u0631\u06cc\u0646"
    ],
    "name:vie_x_preferred":[
        "Ho\u00e0i Nh\u00e2n"
    ],
    "name:zho_x_preferred":[
        "\u6000\u4ec1\u5e02"
    ],
    "wof:name":"Huairen",
    "wof:placetype":"locality"
},
  "geometry": {"coordinates":[115.73623000000001,25.62543],"type":"Point"}
}