{
  "type": "Feature",
  "properties": {
    "gn:admin1_code":"30.0",
    "gn:asciiname":"Jiaoling",
    "gn:country_code":"CN",
    "gn:dem":16,
    "gn:feature_class":"P",
    "gn:feature_code":"PPL",
    "gn:name":"Jiaoling",
    "gn:population":0,
    "gn:timezone":"Asia/Shanghai",
    "iso:country":"CN",
    "name:zho_x_preferred":[
        "\u8f7f\u5cad"
    ],
    "wof:name":"Jiaoling",
    "wof:placetype":"locality"
},
  "geometry": {"coordinates":[114.89821999999999,22.84194],"type":"Point"}
}