{
  "type": "Feature",
  "properties": {
    "gn:admin1_code":"7.0",
    "gn:asciiname":"Linxi",
    "gn:country_code":"CN",
    "gn:dem":119,
    "gn:feature_class":"P",
    "gn:feature_code":"PPL",
    "gn:name":"Linxi",
    "gn:population":0,
    "gn:timezone":"Asia/Shanghai",
    "iso:country":"CN",
    "name:ceb_x_preferred":[
        "Linxi"
    ],
    "name:deu_x_preferred":[
        "Linxi"
    ],
    "name:fra_x_preferred":[
        "Linxi"
    ],
    "name:kor_x_preferred":[
        "\ub9b0\uc2dc\ud604"
    ],
    "name:mlg_x_preferred":[
        "Linxi"
    ],
    "name:nor_x_preferred":[
        "Linxi"
    ],
    "name:pol_x_preferred":[
        "Linxi"
    ],
    "name:rus_x_preferred":[
        "\u041b\u0438\u043d\u044c\u0441\u0438"
    ],
    "name:swe_x_preferred":[
        "Linxi"
    ],
    "name:ukr_x_preferred":[
        "\u041b\u0456\u043d\u044c\u0446\u0437\u0438"
    ],
    "name:ukr_x_variant":[
        "\u041b\u0456\u043d\u044c\u0441\u0456"
    ],
    "name:urd_x_preferred":[
        "\u0644\u06cc\u0632\u06cc"
    ],
    "name:vie_x_preferred":[
        "L\u00e2m T\u00e2y"
    ],
    "name:zho_x_preferred":[
        "\u6797\u6eaa"
    ],
    "wof:name":"Linxi",
    "wof:placetype":"locality"
},
  "geometry": {"coordinates":[117.90963000000001,24.78662],"type":"Point"}
}