{
  "type": "Feature",
  "properties": {
    "gn:admin1_code":"4.0",
    "gn:asciiname":"Luduncun",
    "gn:country_code":"CN",
    "gn:dem":7,
    "gn:feature_class":"P",
    "gn:feature_code":"PPL",
    "gn:name":"Luduncun",
    "gn:population":0,
    "gn:timezone":"Asia/Shanghai",
    "iso:country":"CN",
    "name:und_x_variant":[
        "\u82a6\u58a9\u6751"
    ],
    "name:zho_x_preferred":[
        "\u82a6\u58a9\u6751"
    ],
    "wof:name":"Luduncun",
    "wof:placetype":"locality"
},
  "geometry": {"coordinates":[120.02808,31.90631],"type":"Point"}
}