{
  "type": "Feature",
  "properties": {
    "gn:admin1_code":"16",
    "gn:asciiname":"Lucun",
    "gn:country_code":"CN",
    "gn:dem":82,
    "gn:feature_class":"P",
    "gn:feature_code":"PPL",
    "gn:name":"Lucun",
    "gn:population":0,
    "gn:timezone":"Asia/Shanghai",
    "iso:country":"CN",
    "name:ceb_x_preferred":[
        "Lucun"
    ],
    "name:swe_x_preferred":[
        "Lucun"
    ],
    "name:und_x_variant":[
        "Lu-ts\u2019un",
        "Lucun"
    ],
    "name:zho_x_preferred":[
        "\u82a6\u6751"
    ],
    "wof:name":"Lucun",
    "wof:placetype":"locality"
},
  "geometry": {"coordinates":[108.986,22.894],"type":"Point"}
}