{
  "type": "Feature",
  "properties": {
    "gn:admin1_code":"3.0",
    "gn:asciiname":"Wangcunfan",
    "gn:country_code":"CN",
    "gn:dem":103,
    "gn:feature_class":"P",
    "gn:feature_code":"PPL",
    "gn:name":"Wangcunfan",
    "gn:population":0,
    "gn:timezone":"Asia/Shanghai",
    "iso:country":"CN",
    "name:zho_x_preferred":[
        "\u65fa\u6751\u7548"
    ],
    "wof:name":"Wangcunfan",
    "wof:placetype":"locality"
},
  "geometry": {"coordinates":[117.89993,28.54384000000001],"type":"Point"}
}