{
  "type": "Feature",
  "properties": {
    "gn:admin1_code":"3.0",
    "gn:asciiname":"Da'anshang",
    "gn:country_code":"CN",
    "gn:dem":95,
    "gn:feature_class":"P",
    "gn:feature_code":"PPL",
    "gn:name":"Da\u2019anshang",
    "gn:population":0,
    "gn:timezone":"Asia/Shanghai",
    "iso:country":"CN",
    "name:und_x_variant":[
        "Da\u2019anshang",
        "\u5927\u5cb8\u4e0a"
    ],
    "wof:name":"Da'anshang",
    "wof:placetype":"locality"
},
  "geometry": {"coordinates":[114.6409,27.36399],"type":"Point"}
}