{
  "type": "Feature",
  "properties": {
    "gn:admin1_code":"9.0",
    "gn:asciiname":"Douhuying",
    "gn:country_code":"CN",
    "gn:dem":72,
    "gn:feature_class":"P",
    "gn:feature_code":"PPL",
    "gn:name":"Douhuying",
    "gn:population":0,
    "gn:timezone":"Asia/Shanghai",
    "iso:country":"CN",
    "name:zho_x_preferred":[
        "\u7aa6\u864e\u8425"
    ],
    "wof:name":"Douhuying",
    "wof:placetype":"locality"
},
  "geometry": {"coordinates":[114.20101,34.42177],"type":"Point"}
}