{
  "type": "Feature",
  "properties": {
    "gn:admin1_code":"1.0",
    "gn:asciiname":"Lixucun",
    "gn:country_code":"CN",
    "gn:dem":28,
    "gn:feature_class":"P",
    "gn:feature_code":"PPL",
    "gn:name":"Lixucun",
    "gn:population":0,
    "gn:timezone":"Asia/Shanghai",
    "iso:country":"CN",
    "name:zho_x_preferred":[
        "\u674e\u5729\u6751"
    ],
    "wof:name":"Lixucun",
    "wof:placetype":"locality"
},
  "geometry": {"coordinates":[116.59632000000001,32.99674],"type":"Point"}
}