{
  "type": "Feature",
  "properties": {
    "gn:admin1_code":"2.0",
    "gn:asciiname":"Dangli",
    "gn:country_code":"CN",
    "gn:dem":148,
    "gn:feature_class":"P",
    "gn:feature_code":"PPL",
    "gn:name":"Dangli",
    "gn:population":0,
    "gn:timezone":"Asia/Shanghai",
    "iso:country":"CN",
    "name:und_x_variant":[
        "\u5b95\u91cc",
        "Dangli"
    ],
    "wof:name":"Dangli",
    "wof:placetype":"locality"
},
  "geometry": {"coordinates":[119.13557,29.61792],"type":"Point"}
}