{
  "type": "Feature",
  "properties": {
    "gn:admin1_code":"5.0",
    "gn:asciiname":"Dongfeng Linchang",
    "gn:country_code":"CN",
    "gn:dem":795,
    "gn:feature_class":"P",
    "gn:feature_code":"PPLF",
    "gn:name":"Dongfeng Linchang",
    "gn:population":0,
    "gn:timezone":"Asia/Shanghai",
    "iso:country":"CN",
    "name:und_x_variant":[
        "\u4e1c\u98ce\u6797\u573a"
    ],
    "wof:name":"Dongfeng Linchang",
    "wof:placetype":"locality"
},
  "geometry": {"coordinates":[127.37795,42.00978],"type":"Point"}
}