{
  "type": "Feature",
  "properties": {
    "gn:admin1_code":"14",
    "gn:asciiname":"Cangdong",
    "gn:country_code":"CN",
    "gn:dem":4431,
    "gn:feature_class":"P",
    "gn:feature_code":"PPL",
    "gn:name":"Cangdong",
    "gn:population":0,
    "gn:timezone":"Asia/Urumqi",
    "iso:country":"CN",
    "name:zho_x_preferred":[
        "\u85cf\u680b"
    ],
    "wof:name":"Cangdong",
    "wof:placetype":"locality"
},
  "geometry": {"coordinates":[88.9533,29.6591],"type":"Point"}
}