{
  "type": "Feature",
  "properties": {
    "gn:admin1_code":"12.0",
    "gn:asciiname":"Yuheping",
    "gn:country_code":"CN",
    "gn:dem":843,
    "gn:feature_class":"P",
    "gn:feature_code":"PPL",
    "gn:name":"Yuheping",
    "gn:population":0,
    "gn:timezone":"Asia/Shanghai",
    "iso:country":"CN",
    "name:zho_x_preferred":[
        "\u828b\u8377\u576a"
    ],
    "wof:name":"Yuheping",
    "wof:placetype":"locality"
},
  "geometry": {"coordinates":[109.55342,30.101],"type":"Point"}
}