{
  "type": "Feature",
  "properties": {
    "gn:admin1_code":"15.0",
    "gn:asciiname":"Hongyashan",
    "gn:country_code":"CN",
    "gn:dem":1377,
    "gn:feature_class":"P",
    "gn:feature_code":"PPL",
    "gn:name":"Hongyashan",
    "gn:population":0,
    "gn:timezone":"Asia/Shanghai",
    "iso:country":"CN",
    "name:zho_x_preferred":[
        "\u7ea2\u5d16\u5c71"
    ],
    "wof:name":"Hongyashan",
    "wof:placetype":"locality"
},
  "geometry": {"coordinates":[107.501,35.2921],"type":"Point"}
}