{
  "type": "Feature",
  "properties": {
    "gn:admin1_code":"5.0",
    "gn:asciiname":"Sandaogoucun",
    "gn:country_code":"CN",
    "gn:dem":424,
    "gn:feature_class":"P",
    "gn:feature_code":"PPL",
    "gn:name":"Sandaogoucun",
    "gn:population":0,
    "gn:timezone":"Asia/Shanghai",
    "iso:country":"CN",
    "name:zho_x_preferred":[
        "\u4e09\u9053\u6c9f\u6751"
    ],
    "wof:name":"Sandaogoucun",
    "wof:placetype":"locality"
},
  "geometry": {"coordinates":[125.76981000000001,42.11691],"type":"Point"}
}