{
  "type": "Feature",
  "properties": {
    "gn:admin1_code":"2.0",
    "gn:asciiname":"Yangshutangxia",
    "gn:country_code":"CN",
    "gn:dem":149,
    "gn:feature_class":"P",
    "gn:feature_code":"PPL",
    "gn:name":"Yangshutangxia",
    "gn:population":0,
    "gn:timezone":"Asia/Shanghai",
    "iso:country":"CN",
    "name:zho_x_preferred":[
        "\u6768\u6811\u5858\u4e0b"
    ],
    "wof:name":"Yangshutangxia",
    "wof:placetype":"locality"
},
  "geometry": {"coordinates":[120.30352000000001,29.18063],"type":"Point"}
}