{
  "type": "Feature",
  "properties": {
    "gn:admin1_code":"31.0",
    "gn:asciiname":"Meibao",
    "gn:country_code":"CN",
    "gn:dem":21,
    "gn:feature_class":"P",
    "gn:feature_code":"PPL",
    "gn:name":"Meibao",
    "gn:population":0,
    "gn:timezone":"Asia/Shanghai",
    "iso:country":"CN",
    "name:zho_x_preferred":[
        "Meibao"
    ],
    "name:zho_x_variant":[
        "\u7f8e\u5b9d"
    ],
    "wof:name":"Meibao",
    "wof:placetype":"locality"
},
  "geometry": {"coordinates":[110.67856999999999,20.06576],"type":"Point"}
}