{
  "type": "Feature",
  "properties": {
    "gn:admin1_code":"29.0",
    "gn:asciiname":"Changqibu",
    "gn:country_code":"CN",
    "gn:dem":1948,
    "gn:feature_class":"P",
    "gn:feature_code":"PPL",
    "gn:name":"Changqibu",
    "gn:population":0,
    "gn:timezone":"Asia/Shanghai",
    "iso:country":"CN",
    "name:zho_x_preferred":[
        "\u5e38\u65d7\u5821"
    ],
    "wof:name":"Changqibu",
    "wof:placetype":"locality"
},
  "geometry": {"coordinates":[103.557,25.0584],"type":"Point"}
}