{
  "type": "Feature",
  "properties": {
    "gn:admin1_code":"29.0",
    "gn:asciiname":"Pumi",
    "gn:country_code":"CN",
    "gn:dem":1516,
    "gn:feature_class":"P",
    "gn:feature_code":"PPL",
    "gn:name":"Pumi",
    "gn:population":0,
    "gn:timezone":"Asia/Shanghai",
    "iso:country":"CN",
    "name:deu_x_preferred":[
        "Pumi"
    ],
    "name:nld_x_preferred":[
        "Pumi"
    ],
    "name:pol_x_preferred":[
        "Pumi"
    ],
    "name:swe_x_preferred":[
        "Pumi"
    ],
    "name:zho_x_preferred":[
        "\u84b2\u7c73"
    ],
    "wof:name":"Pumi",
    "wof:placetype":"locality"
},
  "geometry": {"coordinates":[100.69,26.5702],"type":"Point"}
}