{
  "type": "Feature",
  "properties": {
    "gn:admin1_code":"21.0",
    "gn:asciiname":"Wujia Xiaokouzi",
    "gn:country_code":"CN",
    "gn:dem":1482,
    "gn:feature_class":"P",
    "gn:feature_code":"PPL",
    "gn:name":"Wujia Xiaokouzi",
    "gn:population":0,
    "gn:timezone":"Asia/Shanghai",
    "iso:country":"CN",
    "name:zho_x_preferred":[
        "\u5434\u5bb6\u5c0f\u53e3\u5b50"
    ],
    "wof:name":"Wujia Xiaokouzi",
    "wof:placetype":"locality"
},
  "geometry": {"coordinates":[106.98,37.5317],"type":"Point"}
}