{
  "type": "Feature",
  "properties": {
    "gn:admin1_code":"9.0",
    "gn:asciiname":"Cangfangzhuang",
    "gn:country_code":"CN",
    "gn:dem":118,
    "gn:feature_class":"P",
    "gn:feature_code":"PPL",
    "gn:name":"Cangfangzhuang",
    "gn:population":0,
    "gn:timezone":"Asia/Shanghai",
    "iso:country":"CN",
    "name:und_x_variant":[
        "\u4ed3\u623f\u5e84",
        "Cangfangzhuang"
    ],
    "wof:name":"Cangfangzhuang",
    "wof:placetype":"locality"
},
  "geometry": {"coordinates":[112.99267999999999,33.70408],"type":"Point"}
}