{
  "type": "Feature",
  "properties": {
    "gn:admin1_code":"19.0",
    "gn:asciiname":"Xiaolingzi",
    "gn:country_code":"CN",
    "gn:dem":83,
    "gn:feature_class":"P",
    "gn:feature_code":"PPL",
    "gn:name":"Xiaolingzi",
    "gn:population":0,
    "gn:timezone":"Asia/Shanghai",
    "iso:country":"CN",
    "name:und_x_variant":[
        "Xiaolingbaozi",
        "Xiaoling Puzi",
        "Xiaoling Buzi"
    ],
    "name:zho_x_preferred":[
        "\u5c0f\u5cad\u5b50"
    ],
    "name:zho_x_variant":[
        "\u5c0f\u5cad\u5821\u5b50"
    ],
    "wof:name":"Xiaolingzi",
    "wof:placetype":"locality"
},
  "geometry": {"coordinates":[124.27200000000001,40.4446],"type":"Point"}
}