{
  "type": "Feature",
  "properties": {
    "gn:admin1_code":"24.0",
    "gn:asciiname":"Manjing",
    "gn:country_code":"CN",
    "gn:dem":1382,
    "gn:feature_class":"P",
    "gn:feature_code":"PPL",
    "gn:name":"Manjing",
    "gn:population":0,
    "gn:timezone":"Asia/Shanghai",
    "iso:country":"CN",
    "name:zho_x_preferred":[
        "\u8513\u83c1"
    ],
    "wof:name":"Manjing",
    "wof:placetype":"locality"
},
  "geometry": {"coordinates":[112.32053999999999,38.18308],"type":"Point"}
}