{
  "type": "Feature",
  "properties": {
    "gn:admin1_code":"9.0",
    "gn:asciiname":"Hanshiyao",
    "gn:country_code":"CN",
    "gn:dem":1134,
    "gn:feature_class":"P",
    "gn:feature_code":"PPL",
    "gn:name":"Hanshiyao",
    "gn:population":0,
    "gn:timezone":"Asia/Shanghai",
    "iso:country":"CN",
    "name:zho_x_preferred":[
        "\u5bd2\u77f3\u7a91"
    ],
    "wof:name":"Hanshiyao",
    "wof:placetype":"locality"
},
  "geometry": {"coordinates":[111.72732999999999,34.19221],"type":"Point"}
}