{
  "type": "Feature",
  "properties": {
    "gn:admin1_code":"11.0",
    "gn:asciiname":"Hanhu",
    "gn:country_code":"CN",
    "gn:dem":25,
    "gn:feature_class":"P",
    "gn:feature_code":"PPL",
    "gn:name":"Hanhu",
    "gn:population":0,
    "gn:timezone":"Asia/Shanghai",
    "iso:country":"CN",
    "name:zho_x_preferred":[
        "\u5bd2\u6e56"
    ],
    "wof:name":"Hanhu",
    "wof:placetype":"locality"
},
  "geometry": {"coordinates":[112.99120000000001,29.05288],"type":"Point"}
}