{
  "type": "Feature",
  "properties": {
    "gn:admin1_code":"11",
    "gn:asciiname":"Luojiatian",
    "gn:country_code":"CN",
    "gn:dem":481,
    "gn:feature_class":"P",
    "gn:feature_code":"PPL",
    "gn:name":"Luojiatian",
    "gn:population":0,
    "gn:timezone":"Asia/Shanghai",
    "iso:country":"CN",
    "name:und_x_variant":[
        "\u7f57\u5bb6\u7530",
        "Luojiatian"
    ],
    "wof:name":"Luojiatian",
    "wof:placetype":"locality"
},
  "geometry": {"coordinates":[111.75082999999999,25.78056],"type":"Point"}
}