{
  "type": "Feature",
  "properties": {
    "gn:admin1_code":"11.0",
    "gn:asciiname":"Fenshantan",
    "gn:country_code":"CN",
    "gn:dem":103,
    "gn:feature_class":"P",
    "gn:feature_code":"PPL",
    "gn:name":"Fenshantan",
    "gn:population":0,
    "gn:timezone":"Asia/Shanghai",
    "iso:country":"CN",
    "name:zho_x_preferred":[
        "\u575f\u5c71\u5766"
    ],
    "wof:name":"Fenshantan",
    "wof:placetype":"locality"
},
  "geometry": {"coordinates":[112.66704,27.07876],"type":"Point"}
}