{
  "type": "Feature",
  "properties": {
    "gn:admin1_code":"12.0",
    "gn:asciiname":"Datanjiawan",
    "gn:country_code":"CN",
    "gn:dem":717,
    "gn:feature_class":"P",
    "gn:feature_code":"PPL",
    "gn:name":"Datanjiawan",
    "gn:population":0,
    "gn:timezone":"Asia/Shanghai",
    "iso:country":"CN",
    "name:zho_x_preferred":[
        "\u5927\u8c2d\u5bb6\u6e7e"
    ],
    "wof:name":"Datanjiawan",
    "wof:placetype":"locality"
},
  "geometry": {"coordinates":[110.69687999999999,31.97953],"type":"Point"}
}