{
  "type": "Feature",
  "properties": {
    "gn:admin1_code":"26.0",
    "gn:asciiname":"Jiufengcun",
    "gn:country_code":"CN",
    "gn:dem":1142,
    "gn:feature_class":"P",
    "gn:feature_code":"PPL",
    "gn:name":"Jiufengcun",
    "gn:population":0,
    "gn:timezone":"Asia/Shanghai",
    "iso:country":"CN",
    "name:zho_x_preferred":[
        "\u4e5d\u5cf0\u6751"
    ],
    "wof:name":"Jiufengcun",
    "wof:placetype":"locality"
},
  "geometry": {"coordinates":[106.6086,34.51608],"type":"Point"}
}