{
  "type": "Feature",
  "properties": {
    "gn:admin1_code":"3.0",
    "gn:asciiname":"Daxicun",
    "gn:country_code":"CN",
    "gn:dem":21,
    "gn:feature_class":"P",
    "gn:feature_code":"PPL",
    "gn:name":"Daxicun",
    "gn:population":0,
    "gn:timezone":"Asia/Shanghai",
    "iso:country":"CN",
    "name:und_x_variant":[
        "\u5927\u559c\u6751"
    ],
    "wof:name":"Daxicun",
    "wof:placetype":"locality"
},
  "geometry": {"coordinates":[115.94414,28.94098],"type":"Point"}
}