{
  "type": "Feature",
  "properties": {
    "gn:admin1_code":"32.0",
    "gn:asciiname":"Jingji",
    "gn:country_code":"CN",
    "gn:dem":419,
    "gn:feature_class":"P",
    "gn:feature_code":"PPL",
    "gn:name":"Jingji",
    "gn:population":0,
    "gn:timezone":"Asia/Shanghai",
    "iso:country":"CN",
    "name:zho_x_preferred":[
        "\u7ecf\u6d4e"
    ],
    "wof:name":"Jingji",
    "wof:placetype":"locality"
},
  "geometry": {"coordinates":[104.745,30.5522],"type":"Point"}
}