{
  "type": "Feature",
  "properties": {
    "gn:country":"CN",
    "gn:fcode":"PPL",
    "gn:pop":109881,
    "iso:country":"CN",
    "name:unk_x_variant":[
        "T\u2019ung-ken"
    ],
    "name:zho_x_preferred":[
        "\u6d77\u4f26"
    ],
    "name:zho_x_variant":[
        "\u6d77\u4f26\u9547",
        "\u6d77\u4f26\u5e02"
    ],
    "ne:ADM0CAP":0.0,
    "ne:ADM0NAME":"China",
    "ne:ADM0_A3":"CHN",
    "ne:ADM1NAME":"Heilongjiang",
    "ne:ADMIN1_COD":8,
    "ne:CAPALT":0,
    "ne:CHANGED":0,
    "ne:CHECKME":0,
    "ne:COMPARE":0,
    "ne:DIFFASCII":0,
    "ne:ELEVATION":0.0,
    "ne:FEATURECLA":"Populated place",
    "ne:FEATURE_CL":"P",
    "ne:FEATURE_CO":"PPL",
    "ne:GEONAMEID":2037069,
    "ne:GEONAMESNO":"GeoNames match with ascii name + lat + long whole numbers.",
    "ne:GN_ASCII":"Hailun",
    "ne:GN_POP":109881,
    "ne:GTOPO30":227.0,
    "ne:ISO_A2":"CN",
    "ne:LABELRANK":1,
    "ne:LATITUDE":47.450423,
    "ne:LONGITUDE":126.930019,
    "ne:LS_MATCH":1,
    "ne:LS_NAME":"Hailun",
    "ne:MAX_AREAKM":37.0,
    "ne:MAX_AREAMI":14.0,
    "ne:MAX_BBXMAX":127.008333,
    "ne:MAX_BBXMIN":126.883333,
    "ne:MAX_BBYMAX":47.5,
    "ne:MAX_BBYMIN":47.441667,
    "ne:MAX_NATSCA":20.0,
    "ne:MAX_PERKM":49.0,
    "ne:MAX_PERMI":30.0,
    "ne:MAX_POP10":99816,
    "ne:MAX_POP20":99816,
    "ne:MAX_POP300":0,
    "ne:MAX_POP310":0,
    "ne:MAX_POP50":0,
    "ne:MEAN_BBXC":126.941468,
    "ne:MEAN_BBYC":47.466601,
    "ne:MEGACITY":0,
    "ne:MIN_AREAKM":37.0,
    "ne:MIN_AREAMI":14.0,
    "ne:MIN_BBXMAX":127.008333,
    "ne:MIN_BBXMIN":126.883333,
    "ne:MIN_BBYMAX":47.5,
    "ne:MIN_BBYMIN":47.441667,
    "ne:MIN_PERKM":49.0,
    "ne:MIN_PERMI":30.0,
    "ne:NAME":"Hailun",
    "ne:NAMEASCII":"Hailun",
    "ne:NAMEDIFF":0,
    "ne:NATSCALE":20,
    "ne:POP1950":0,
    "ne:POP1955":0,
    "ne:POP1960":0,
    "ne:POP1965":0,
    "ne:POP1970":0,
    "ne:POP1975":0,
    "ne:POP1980":0,
    "ne:POP1985":0,
    "ne:POP1990":0,
    "ne:POP1995":0,
    "ne:POP2000":0,
    "ne:POP2005":0,
    "ne:POP2010":0,
    "ne:POP2015":0,
    "ne:POP2020":0,
    "ne:POP2025":0,
    "ne:POP2050":0,
    "ne:POP_MAX":109881,
    "ne:POP_MIN":99816,
    "ne:POP_OTHER":90848,
    "ne:RANK_MAX":9,
    "ne:RANK_MIN":8,
    "ne:SCALERANK":7,
    "ne:SOV0NAME":"China",
    "ne:SOV_A3":"CHN",
    "ne:TIMEZONE":"Asia/Harbin",
    "ne:UN_FID":0,
    "ne:UN_LAT":0.0,
    "ne:UN_LONG":0.0,
    "ne:WORLDCITY":0,
    "qs:name":"Hailun",
    "qs:photos_9r":0,
    "qs:photos_sr":0,
    "qs:pop_sr":"9",
    "wd:wordcount":180,
    "wof:name":"Hailun",
    "wof:placetype":"locality",
    "wof:population":109881
},
  "geometry": {"coordinates":[126.93333,47.45],"type":"Point"}
}