{
  "type": "Feature",
  "properties": {
    "gn:admin1_code":"32.0",
    "gn:asciiname":"Gendu",
    "gn:country_code":"CN",
    "gn:dem":3407,
    "gn:feature_class":"P",
    "gn:feature_code":"PPL",
    "gn:name":"Gendu",
    "gn:population":0,
    "gn:timezone":"Asia/Shanghai",
    "iso:country":"CN",
    "name:zho_x_preferred":[
        "\u6839\u90fd"
    ],
    "wof:name":"Gendu",
    "wof:placetype":"locality"
},
  "geometry": {"coordinates":[100.23999999999999,31.3381],"type":"Point"}
}