{
  "type": "Feature",
  "properties": {
    "gn:admin1_code":"15.0",
    "gn:asciiname":"Xingshumao",
    "gn:country_code":"CN",
    "gn:dem":1454,
    "gn:feature_class":"P",
    "gn:feature_code":"PPL",
    "gn:name":"Xingshumao",
    "gn:population":0,
    "gn:timezone":"Asia/Shanghai",
    "iso:country":"CN",
    "name:zho_x_preferred":[
        "\u674f\u6811\u5cc1"
    ],
    "wof:name":"Xingshumao",
    "wof:placetype":"locality"
},
  "geometry": {"coordinates":[108.09,36.4203],"type":"Point"}
}