{
  "type": "Feature",
  "properties": {
    "gn:admin1_code":"5.0",
    "gn:asciiname":"Quanfacun",
    "gn:country_code":"CN",
    "gn:dem":499,
    "gn:feature_class":"P",
    "gn:feature_code":"PPL",
    "gn:name":"Quanfacun",
    "gn:population":0,
    "gn:timezone":"Asia/Shanghai",
    "iso:country":"CN",
    "name:zho_x_preferred":[
        "\u5168\u53d1\u6751"
    ],
    "wof:name":"Quanfacun",
    "wof:placetype":"locality"
},
  "geometry": {"coordinates":[128.34585000000001,43.46382],"type":"Point"}
}