{
  "type": "Feature",
  "properties": {
    "gn:admin1_code":"10",
    "gn:asciiname":"Hongshilingshang",
    "gn:country_code":"CN",
    "gn:dem":218,
    "gn:feature_class":"P",
    "gn:feature_code":"PPL",
    "gn:name":"Hongshilingshang",
    "gn:population":0,
    "gn:timezone":"Asia/Shanghai",
    "iso:country":"CN",
    "name:zho_x_preferred":[
        "\u7ea2\u77f3\u5cad\u4e0a"
    ],
    "wof:name":"Hongshilingshang",
    "wof:placetype":"locality"
},
  "geometry": {"coordinates":[119.18077,40.35176],"type":"Point"}
}