{
  "type": "Feature",
  "properties": {
    "gn:admin1_code":"10",
    "gn:asciiname":"Xinminbu",
    "gn:country_code":"CN",
    "gn:dem":1421,
    "gn:feature_class":"P",
    "gn:feature_code":"PPL",
    "gn:name":"Xinminbu",
    "gn:population":0,
    "gn:timezone":"Asia/Shanghai",
    "iso:country":"CN",
    "name:zho_x_preferred":[
        "\u65b0\u6c11\u5821"
    ],
    "wof:name":"Xinminbu",
    "wof:placetype":"locality"
},
  "geometry": {"coordinates":[114.54129,41.8156],"type":"Point"}
}