{
  "type": "Feature",
  "properties": {
    "gn:admin1_code":"02",
    "gn:asciiname":"Chen'aocun",
    "gn:country_code":"CN",
    "gn:dem":57,
    "gn:feature_class":"P",
    "gn:feature_code":"PPL",
    "gn:name":"Chen\u2019aocun",
    "gn:population":0,
    "gn:timezone":"Asia/Shanghai",
    "iso:country":"CN",
    "name:und_x_variant":[
        "Chen\u2019ao",
        "Chen\u2019aocun"
    ],
    "name:zho_x_preferred":[
        "\u9648\u5c99"
    ],
    "name:zho_x_variant":[
        "\u9648\u5c99\u6751"
    ],
    "wof:name":"Chen'aocun",
    "wof:placetype":"locality"
},
  "geometry": {"coordinates":[120.76049999999999,28.39287],"type":"Point"}
}