{
  "type": "Feature",
  "properties": {
    "gn:admin1_code":"7",
    "gn:asciiname":"Bantou",
    "gn:country_code":"CN",
    "gn:dem":863,
    "gn:feature_class":"P",
    "gn:feature_code":"PPL",
    "gn:name":"Bantou",
    "gn:population":0,
    "gn:timezone":"Asia/Shanghai",
    "iso:country":"CN",
    "name:und_x_variant":[
        "\u5742\u5934"
    ],
    "wof:name":"Bantou",
    "wof:placetype":"locality"
},
  "geometry": {"coordinates":[119.10972,27.14083],"type":"Point"}
}