{
  "type": "Feature",
  "properties": {
    "gn:admin1_code":"29",
    "gn:asciiname":"Yangnaicaipo",
    "gn:country_code":"CN",
    "gn:dem":977,
    "gn:feature_class":"P",
    "gn:feature_code":"PPL",
    "gn:name":"Yangnaicaipo",
    "gn:population":0,
    "gn:timezone":"Asia/Shanghai",
    "iso:country":"CN",
    "name:zho_x_preferred":[
        "\u7f8a\u5976\u83dc\u5761"
    ],
    "wof:name":"Yangnaicaipo",
    "wof:placetype":"locality"
},
  "geometry": {"coordinates":[102.327,23.5649],"type":"Point"}
}