{
  "type": "Feature",
  "properties": {
    "gn:admin1_code":"4.0",
    "gn:asciiname":"Bozhucun",
    "gn:country_code":"CN",
    "gn:dem":3,
    "gn:feature_class":"P",
    "gn:feature_code":"PPL",
    "gn:name":"Bozhucun",
    "gn:population":0,
    "gn:timezone":"Asia/Shanghai",
    "iso:country":"CN",
    "name:zho_x_preferred":[
        "\u67cf\u6731\u6751"
    ],
    "wof:name":"Bozhucun",
    "wof:placetype":"locality"
},
  "geometry": {"coordinates":[119.97669999999999,32.81788],"type":"Point"}
}