{
  "type": "Feature",
  "properties": {
    "gn:admin1_code":"3.0",
    "gn:asciiname":"Changsheng",
    "gn:country_code":"CN",
    "gn:dem":91,
    "gn:feature_class":"P",
    "gn:feature_code":"PPL",
    "gn:name":"Changsheng",
    "gn:population":0,
    "gn:timezone":"Asia/Shanghai",
    "iso:country":"CN",
    "name:zho_x_preferred":[
        "\u957f\u751f"
    ],
    "wof:name":"Changsheng",
    "wof:placetype":"locality"
},
  "geometry": {"coordinates":[117.70099999999999,28.1766],"type":"Point"}
}