{
  "type": "Feature",
  "properties": {
    "gn:admin1_code":"31",
    "gn:asciiname":"Xincun",
    "gn:country_code":"CN",
    "gn:dem":59,
    "gn:feature_class":"P",
    "gn:feature_code":"PPL",
    "gn:name":"Xincun",
    "gn:population":0,
    "gn:timezone":"Asia/Shanghai",
    "iso:country":"CN",
    "name:ceb_x_preferred":[
        "Xincun"
    ],
    "name:deu_x_preferred":[
        "Xincun"
    ],
    "name:swe_x_preferred":[
        "Xincun"
    ],
    "name:und_x_variant":[
        "\u65b0\u6751"
    ],
    "wof:name":"Xincun",
    "wof:placetype":"locality"
},
  "geometry": {"coordinates":[108.90364,19.4383],"type":"Point"}
}