{
  "type": "Feature",
  "properties": {
    "gn:admin1_code":"32.0",
    "gn:asciiname":"Guanglongba",
    "gn:country_code":"CN",
    "gn:dem":463,
    "gn:feature_class":"P",
    "gn:feature_code":"PPL",
    "gn:name":"Guanglongba",
    "gn:population":0,
    "gn:timezone":"Asia/Shanghai",
    "iso:country":"CN",
    "name:zho_x_preferred":[
        "\u5149\u9f99\u575d"
    ],
    "wof:name":"Guanglongba",
    "wof:placetype":"locality"
},
  "geometry": {"coordinates":[104.16802,28.98741],"type":"Point"}
}