{
  "type": "Feature",
  "properties": {
    "gn:admin1_code":"15.0",
    "gn:asciiname":"Guoqi",
    "gn:country_code":"CN",
    "gn:dem":1492,
    "gn:feature_class":"P",
    "gn:feature_code":"PPL",
    "gn:name":"Guoqi",
    "gn:population":0,
    "gn:timezone":"Asia/Shanghai",
    "iso:country":"CN",
    "name:zho_x_preferred":[
        "\u90ed\u65d7"
    ],
    "wof:name":"Guoqi",
    "wof:placetype":"locality"
},
  "geometry": {"coordinates":[107.53724,35.99739],"type":"Point"}
}