{
  "type": "Feature",
  "properties": {
    "gn:admin1_code":"26.0",
    "gn:asciiname":"Yangjiaping",
    "gn:country_code":"CN",
    "gn:dem":929,
    "gn:feature_class":"P",
    "gn:feature_code":"PPL",
    "gn:name":"Yangjiaping",
    "gn:population":0,
    "gn:timezone":"Asia/Shanghai",
    "iso:country":"CN",
    "name:zho_x_preferred":[
        "\u6768\u5bb6\u576a"
    ],
    "wof:name":"Yangjiaping",
    "wof:placetype":"locality"
},
  "geometry": {"coordinates":[106.83071,34.42954],"type":"Point"}
}