{
  "type": "Feature",
  "properties": {
    "gn:admin1_code":"25.0",
    "gn:asciiname":"Nanhuangtong",
    "gn:country_code":"CN",
    "gn:dem":72,
    "gn:feature_class":"P",
    "gn:feature_code":"PPL",
    "gn:name":"Nanhuangtong",
    "gn:population":0,
    "gn:timezone":"Asia/Shanghai",
    "iso:country":"CN",
    "name:zho_x_preferred":[
        "\u5357\u9ec4\u540c"
    ],
    "wof:name":"Nanhuangtong",
    "wof:placetype":"locality"
},
  "geometry": {"coordinates":[120.26158999999998,36.94205],"type":"Point"}
}