{
  "type": "Feature",
  "properties": {
    "gn:admin1_code":"02",
    "gn:asciiname":"Lijincun",
    "gn:country_code":"CN",
    "gn:dem":112,
    "gn:feature_class":"P",
    "gn:feature_code":"PPL",
    "gn:name":"Lijincun",
    "gn:population":0,
    "gn:timezone":"Asia/Shanghai",
    "iso:country":"CN",
    "name:und_x_variant":[
        "Lijin",
        "\u91cc\u91d1",
        "Lijincun"
    ],
    "name:zho_x_preferred":[
        "\u91cc\u91d1"
    ],
    "name:zho_x_variant":[
        "\u91cc\u91d1\u6751"
    ],
    "wof:name":"Lijincun",
    "wof:placetype":"locality"
},
  "geometry": {"coordinates":[121.29082,29.01989],"type":"Point"}
}