{
  "type": "Feature",
  "properties": {
    "gn:admin1_code":"7",
    "gn:asciiname":"Xiakekeng",
    "gn:country_code":"CN",
    "gn:dem":18,
    "gn:feature_class":"P",
    "gn:feature_code":"PPL",
    "gn:name":"Xiakekeng",
    "gn:population":0,
    "gn:timezone":"Asia/Shanghai",
    "iso:country":"CN",
    "name:und_x_variant":[
        "\u4e0b\u67ef\u5751"
    ],
    "wof:name":"Xiakekeng",
    "wof:placetype":"locality"
},
  "geometry": {"coordinates":[118.58499999999999,24.62167],"type":"Point"}
}