{
  "type": "Feature",
  "properties": {
    "gn:admin1_code":"26.0",
    "gn:asciiname":"Gaopingcun",
    "gn:country_code":"CN",
    "gn:dem":1180,
    "gn:feature_class":"P",
    "gn:feature_code":"PPL",
    "gn:name":"Gaopingcun",
    "gn:population":0,
    "gn:timezone":"Asia/Shanghai",
    "iso:country":"CN",
    "name:zho_x_preferred":[
        "\u9ad8\u576a\u6751"
    ],
    "wof:name":"Gaopingcun",
    "wof:placetype":"locality"
},
  "geometry": {"coordinates":[108.26385000000001,35.06239],"type":"Point"}
}