{
  "type": "Feature",
  "properties": {
    "gn:admin1_code":"30",
    "gn:asciiname":"Mianhu",
    "gn:country_code":"CN",
    "gn:dem":14,
    "gn:feature_class":"P",
    "gn:feature_code":"PPLA4",
    "gn:name":"Mianhu",
    "gn:population":0,
    "gn:timezone":"Asia/Shanghai",
    "iso:country":"CN",
    "name:und_x_variant":[
        "Mienfu",
        "Mien-hu-hs\u00fc",
        "Mien-hu",
        "Mianhu",
        "\u68c9\u6e56",
        "Mianhu Zhen",
        "\u68c9\u6e56\u9547"
    ],
    "wof:name":"Mianhu",
    "wof:placetype":"locality"
},
  "geometry": {"coordinates":[116.13872000000001,23.44104],"type":"Point"}
}