{
  "type": "Feature",
  "properties": {
    "gn:admin1_code":"29",
    "gn:asciiname":"Jiaodimo",
    "gn:country_code":"CN",
    "gn:dem":1524,
    "gn:feature_class":"P",
    "gn:feature_code":"PPL",
    "gn:name":"Jiaodimo",
    "gn:population":0,
    "gn:timezone":"Asia/Shanghai",
    "iso:country":"CN",
    "name:zho_x_preferred":[
        "\u811a\u5e95\u83ab"
    ],
    "wof:name":"Jiaodimo",
    "wof:placetype":"locality"
},
  "geometry": {"coordinates":[101.85299999999999,23.9339],"type":"Point"}
}