{
  "type": "Feature",
  "properties": {
    "gn:admin1_code":"29",
    "gn:asciiname":"Dixu",
    "gn:country_code":"CN",
    "gn:dem":1063,
    "gn:feature_class":"P",
    "gn:feature_code":"PPL",
    "gn:name":"Dixu",
    "gn:population":0,
    "gn:timezone":"Asia/Shanghai",
    "iso:country":"CN",
    "name:zho_x_preferred":[
        "\u5e95\u65ed"
    ],
    "wof:name":"Dixu",
    "wof:placetype":"locality"
},
  "geometry": {"coordinates":[104.566,24.4111],"type":"Point"}
}