{
  "type": "Feature",
  "properties": {
    "gn:admin1_code":"24.0",
    "gn:asciiname":"Yangmingbu",
    "gn:country_code":"CN",
    "gn:dem":849,
    "gn:feature_class":"P",
    "gn:feature_code":"PPLA4",
    "gn:name":"Yangmingbu",
    "gn:population":0,
    "gn:timezone":"Asia/Shanghai",
    "iso:country":"CN",
    "name:und_x_variant":[
        "Yang-ming-pao",
        "Yanminbao",
        "Yangmingbu",
        "\u9633\u660e\u5821",
        "Yangmingbu Zhen",
        "\u9633\u660e\u5821\u9547"
    ],
    "wof:name":"Yangmingbu",
    "wof:placetype":"locality"
},
  "geometry": {"coordinates":[112.87222,39.0125],"type":"Point"}
}