{
  "type": "Feature",
  "properties": {
    "gn:admin1_code":"3.0",
    "gn:asciiname":"Caoli",
    "gn:country_code":"CN",
    "gn:dem":149,
    "gn:feature_class":"P",
    "gn:feature_code":"PPL",
    "gn:name":"Caoli",
    "gn:population":0,
    "gn:timezone":"Asia/Shanghai",
    "iso:country":"CN",
    "name:und_x_variant":[
        "\u69fd\u91cc"
    ],
    "wof:name":"Caoli",
    "wof:placetype":"locality"
},
  "geometry": {"coordinates":[114.7244,29.24143],"type":"Point"}
}