{
  "type": "Feature",
  "properties": {
    "gn:admin1_code":"31",
    "gn:asciiname":"Nanliu",
    "gn:country_code":"CN",
    "gn:dem":275,
    "gn:feature_class":"P",
    "gn:feature_code":"PPL",
    "gn:name":"Nanliu",
    "gn:population":0,
    "gn:timezone":"Asia/Shanghai",
    "iso:country":"CN",
    "name:und_x_variant":[
        "\u5357\u6d41"
    ],
    "wof:name":"Nanliu",
    "wof:placetype":"locality"
},
  "geometry": {"coordinates":[109.60209999999999,18.96702],"type":"Point"}
}