{
  "type": "Feature",
  "properties": {
    "gn:admin1_code":"11.0",
    "gn:asciiname":"Heli",
    "gn:country_code":"CN",
    "gn:dem":56,
    "gn:feature_class":"P",
    "gn:feature_code":"PPL",
    "gn:name":"Heli",
    "gn:population":0,
    "gn:timezone":"Asia/Shanghai",
    "iso:country":"CN",
    "name:cat_x_preferred":[
        "Heli"
    ],
    "name:deu_x_preferred":[
        "Heli"
    ],
    "name:fin_x_preferred":[
        "Heli"
    ],
    "name:nld_x_preferred":[
        "Heli"
    ],
    "name:zho_x_preferred":[
        "\u5408\u529b"
    ],
    "wof:name":"Heli",
    "wof:placetype":"locality"
},
  "geometry": {"coordinates":[112.06828,28.49805],"type":"Point"}
}