{
  "type": "Feature",
  "properties": {
    "gn:admin1_code":"19.0",
    "gn:asciiname":"Lujiacun",
    "gn:country_code":"CN",
    "gn:dem":22,
    "gn:feature_class":"P",
    "gn:feature_code":"PPL",
    "gn:name":"Lujiacun",
    "gn:population":0,
    "gn:timezone":"Asia/Shanghai",
    "iso:country":"CN",
    "name:zho_x_preferred":[
        "\u9646\u5bb6\u6751"
    ],
    "wof:name":"Lujiacun",
    "wof:placetype":"locality"
},
  "geometry": {"coordinates":[121.13303999999999,40.96229],"type":"Point"}
}