{
  "type": "Feature",
  "properties": {
    "gn:admin1_code":"23.0",
    "gn:asciiname":"Xuxiang",
    "gn:country_code":"CN",
    "gn:dem":5,
    "gn:feature_class":"P",
    "gn:feature_code":"PPL",
    "gn:name":"Xuxiang",
    "gn:population":0,
    "gn:timezone":"Asia/Shanghai",
    "iso:country":"CN",
    "name:zho_x_preferred":[
        "Xuxiang"
    ],
    "name:zho_x_variant":[
        "\u8bb8\u5df7"
    ],
    "wof:name":"Xuxiang",
    "wof:placetype":"locality"
},
  "geometry": {"coordinates":[121.08593,31.08092000000001],"type":"Point"}
}