{
  "type": "Feature",
  "properties": {
    "gn:admin1_code":"24.0",
    "gn:asciiname":"Shanggangang",
    "gn:country_code":"CN",
    "gn:dem":1023,
    "gn:feature_class":"P",
    "gn:feature_code":"PPL",
    "gn:name":"Shanggangang",
    "gn:population":0,
    "gn:timezone":"Asia/Shanghai",
    "iso:country":"CN",
    "name:und_x_variant":[
        "\u4e0a\u7518\u6e2f"
    ],
    "name:zho_x_preferred":[
        "\u4e0a\u7518\u6e2f"
    ],
    "wof:name":"Shanggangang",
    "wof:placetype":"locality"
},
  "geometry": {"coordinates":[113.1558,39.45614000000001],"type":"Point"}
}