{
  "type": "Feature",
  "properties": {
    "gn:admin1_code":"2.0",
    "gn:asciiname":"Qingshanguan",
    "gn:country_code":"CN",
    "gn:dem":59,
    "gn:feature_class":"P",
    "gn:feature_code":"PPL",
    "gn:name":"Qingshanguan",
    "gn:population":0,
    "gn:timezone":"Asia/Shanghai",
    "iso:country":"CN",
    "name:und_x_variant":[
        "\u9752\u5c71\u5173"
    ],
    "wof:name":"Qingshanguan",
    "wof:placetype":"locality"
},
  "geometry": {"coordinates":[119.98309,30.61171],"type":"Point"}
}