{
  "type": "Feature",
  "properties": {
    "gn:admin1_code":"30",
    "gn:asciiname":"Dubei",
    "gn:country_code":"CN",
    "gn:dem":34,
    "gn:feature_class":"P",
    "gn:feature_code":"PPL",
    "gn:name":"Dubei",
    "gn:population":0,
    "gn:timezone":"Asia/Urumqi",
    "iso:country":"CN",
    "name:zho_x_preferred":[
        "\u8bfb\u7891"
    ],
    "wof:name":"Dubei",
    "wof:placetype":"locality"
},
  "geometry": {"coordinates":[110.24332,21.55589],"type":"Point"}
}