{
  "type": "Feature",
  "properties": {
    "gn:admin1_code":"10",
    "gn:asciiname":"Toubaihu",
    "gn:country_code":"CN",
    "gn:dem":1420,
    "gn:feature_class":"P",
    "gn:feature_code":"PPL",
    "gn:name":"Toubaihu",
    "gn:population":0,
    "gn:timezone":"Asia/Shanghai",
    "iso:country":"CN",
    "name:zho_x_preferred":[
        "\u5934\u767e\u6237"
    ],
    "wof:name":"Toubaihu",
    "wof:placetype":"locality"
},
  "geometry": {"coordinates":[115.30868999999998,41.52383],"type":"Point"}
}