{
  "type": "Feature",
  "properties": {
    "gn:admin1_code":"19.0",
    "gn:asciiname":"Qigangou",
    "gn:country_code":"CN",
    "gn:dem":486,
    "gn:feature_class":"P",
    "gn:feature_code":"PPL",
    "gn:name":"Qigangou",
    "gn:population":0,
    "gn:timezone":"Asia/Shanghai",
    "iso:country":"CN",
    "name:zho_x_preferred":[
        "\u65d7\u6746\u6c9f"
    ],
    "wof:name":"Qigangou",
    "wof:placetype":"locality"
},
  "geometry": {"coordinates":[125.06949,41.90663],"type":"Point"}
}