{
  "type": "Feature",
  "properties": {
    "gn:admin1_code":"10.0",
    "gn:asciiname":"Shaodi",
    "gn:country_code":"CN",
    "gn:dem":87,
    "gn:feature_class":"P",
    "gn:feature_code":"PPL",
    "gn:name":"Shaodi",
    "gn:population":0,
    "gn:timezone":"Asia/Shanghai",
    "iso:country":"CN",
    "name:und_x_variant":[
        "\u52fa\u5824"
    ],
    "wof:name":"Shaodi",
    "wof:placetype":"locality"
},
  "geometry": {"coordinates":[114.81871,38.64783],"type":"Point"}
}