{
  "type": "Feature",
  "properties": {
    "gn:admin1_code":"2.0",
    "gn:asciiname":"Lujiatou",
    "gn:country_code":"CN",
    "gn:dem":6,
    "gn:feature_class":"P",
    "gn:feature_code":"PPL",
    "gn:name":"Lujiatou",
    "gn:population":0,
    "gn:timezone":"Asia/Shanghai",
    "iso:country":"CN",
    "name:und_x_variant":[
        "\u9c81\u5bb6\u5934"
    ],
    "wof:name":"Lujiatou",
    "wof:placetype":"locality"
},
  "geometry": {"coordinates":[121.05324,30.71732],"type":"Point"}
}