{
  "type": "Feature",
  "properties": {
    "gn:admin1_code":"19.0",
    "gn:asciiname":"Huangtukanzicun",
    "gn:country_code":"CN",
    "gn:dem":156,
    "gn:feature_class":"P",
    "gn:feature_code":"PPL",
    "gn:name":"Huangtukanzicun",
    "gn:population":0,
    "gn:timezone":"Asia/Shanghai",
    "iso:country":"CN",
    "name:zho_x_preferred":[
        "\u9ec4\u571f\u574e\u5b50\u6751"
    ],
    "wof:name":"Huangtukanzicun",
    "wof:placetype":"locality"
},
  "geometry": {"coordinates":[120.877,41.6914],"type":"Point"}
}