{
  "type": "Feature",
  "properties": {
    "gn:admin1_code":"18.0",
    "gn:asciiname":"Daxi",
    "gn:country_code":"CN",
    "gn:dem":548,
    "gn:feature_class":"P",
    "gn:feature_code":"PPL",
    "gn:name":"Daxi",
    "gn:population":0,
    "gn:timezone":"Asia/Shanghai",
    "iso:country":"CN",
    "name:zho_x_preferred":[
        "\u5927\u6eaa"
    ],
    "wof:name":"Daxi",
    "wof:placetype":"locality"
},
  "geometry": {"coordinates":[108.94499999999999,28.1778],"type":"Point"}
}