{
  "type": "Feature",
  "properties": {
    "gn:admin1_code":"19.0",
    "gn:asciiname":"Toudao Yingzicun",
    "gn:country_code":"CN",
    "gn:dem":447,
    "gn:feature_class":"P",
    "gn:feature_code":"PPL",
    "gn:name":"Toudao Yingzicun",
    "gn:population":0,
    "gn:timezone":"Asia/Shanghai",
    "iso:country":"CN",
    "name:zho_x_preferred":[
        "\u5934\u9053\u8425\u5b50\u6751"
    ],
    "wof:name":"Toudao Yingzicun",
    "wof:placetype":"locality"
},
  "geometry": {"coordinates":[120.271,41.8073],"type":"Point"}
}