{
  "type": "Feature",
  "properties": {
    "gn:admin1_code":"14.0",
    "gn:asciiname":"Zhaxizi",
    "gn:country_code":"CN",
    "gn:dem":4437,
    "gn:feature_class":"P",
    "gn:feature_code":"PPL",
    "gn:name":"Zhaxizi",
    "gn:population":0,
    "gn:timezone":"Asia/Urumqi",
    "iso:country":"CN",
    "name:zho_x_preferred":[
        "\u624e\u897f\u5b5c"
    ],
    "wof:name":"Zhaxizi",
    "wof:placetype":"locality"
},
  "geometry": {"coordinates":[88.17319999999999,28.4211],"type":"Point"}
}