{
  "type": "Feature",
  "properties": {
    "gn:admin1_code":"8.0",
    "gn:asciiname":"Lijia Wopeng",
    "gn:country_code":"CN",
    "gn:dem":222,
    "gn:feature_class":"P",
    "gn:feature_code":"PPL",
    "gn:name":"Lijia Wopeng",
    "gn:population":0,
    "gn:timezone":"Asia/Shanghai",
    "iso:country":"CN",
    "name:zho_x_preferred":[
        "\u674e\u5bb6\u7a9d\u68da"
    ],
    "wof:name":"Lijia Wopeng",
    "wof:placetype":"locality"
},
  "geometry": {"coordinates":[124.88836999999999,48.35215],"type":"Point"}
}