{
  "type": "Feature",
  "properties": {
    "gn:admin1_code":"26.0",
    "gn:asciiname":"Zhongshancun",
    "gn:country_code":"CN",
    "gn:dem":1126,
    "gn:feature_class":"P",
    "gn:feature_code":"PPL",
    "gn:name":"Zhongshancun",
    "gn:population":0,
    "gn:timezone":"Asia/Shanghai",
    "iso:country":"CN",
    "name:zho_x_preferred":[
        "\u4e2d\u5c71\u6751"
    ],
    "wof:name":"Zhongshancun",
    "wof:placetype":"locality"
},
  "geometry": {"coordinates":[109.45977999999999,33.4409],"type":"Point"}
}