{
  "type": "Feature",
  "properties": {
    "gn:admin1_code":"3.0",
    "gn:asciiname":"Changyuancun",
    "gn:country_code":"CN",
    "gn:dem":49,
    "gn:feature_class":"P",
    "gn:feature_code":"PPL",
    "gn:name":"Changyuancun",
    "gn:population":0,
    "gn:timezone":"Asia/Shanghai",
    "iso:country":"CN",
    "name:und_x_variant":[
        "\u957f\u539f\u6751"
    ],
    "wof:name":"Changyuancun",
    "wof:placetype":"locality"
},
  "geometry": {"coordinates":[115.52312999999999,28.52642],"type":"Point"}
}