{
  "type": "Feature",
  "properties": {
    "gn:admin1_code":"2.0",
    "gn:asciiname":"Baokengwu",
    "gn:country_code":"CN",
    "gn:dem":275,
    "gn:feature_class":"P",
    "gn:feature_code":"PPL",
    "gn:name":"Baokengwu",
    "gn:population":0,
    "gn:timezone":"Asia/Shanghai",
    "iso:country":"CN",
    "name:und_x_variant":[
        "\u8584\u5751\u575e"
    ],
    "wof:name":"Baokengwu",
    "wof:placetype":"locality"
},
  "geometry": {"coordinates":[119.1345,30.09699],"type":"Point"}
}