{
  "type": "Feature",
  "properties": {
    "gn:admin1_code":"11.0",
    "gn:asciiname":"Fanjiaguai",
    "gn:country_code":"CN",
    "gn:dem":31,
    "gn:feature_class":"P",
    "gn:feature_code":"PPL",
    "gn:name":"Fanjiaguai",
    "gn:population":0,
    "gn:timezone":"Asia/Shanghai",
    "iso:country":"CN",
    "name:zho_x_preferred":[
        "\u8303\u5bb6\u62d0"
    ],
    "wof:name":"Fanjiaguai",
    "wof:placetype":"locality"
},
  "geometry": {"coordinates":[112.34314999999999,29.47307],"type":"Point"}
}