{
  "type": "Feature",
  "properties": {
    "gn:admin1_code":"25",
    "gn:asciiname":"Dongdongling",
    "gn:country_code":"CN",
    "gn:dem":40,
    "gn:feature_class":"P",
    "gn:feature_code":"PPL",
    "gn:name":"Dongdongling",
    "gn:population":0,
    "gn:timezone":"Asia/Shanghai",
    "iso:country":"CN",
    "name:zho_x_preferred":[
        "\u4e1c\u5cd2\u5cad"
    ],
    "wof:name":"Dongdongling",
    "wof:placetype":"locality"
},
  "geometry": {"coordinates":[121.718,36.9163],"type":"Point"}
}