{
  "type": "Feature",
  "properties": {
    "gn:admin1_code":"32.0",
    "gn:asciiname":"Zhiwo",
    "gn:country_code":"CN",
    "gn:dem":3116,
    "gn:feature_class":"P",
    "gn:feature_code":"PPL",
    "gn:name":"Zhiwo",
    "gn:population":0,
    "gn:timezone":"Asia/Shanghai",
    "iso:country":"CN",
    "name:zho_x_preferred":[
        "\u76f4\u7a9d"
    ],
    "wof:name":"Zhiwo",
    "wof:placetype":"locality"
},
  "geometry": {"coordinates":[102.92100000000001,32.0583],"type":"Point"}
}