{
  "type": "Feature",
  "properties": {
    "gn:admin1_code":"23.0",
    "gn:asciiname":"Huangqiang",
    "gn:country_code":"CN",
    "gn:dem":5,
    "gn:feature_class":"P",
    "gn:feature_code":"PPL",
    "gn:name":"Huangqiang",
    "gn:population":0,
    "gn:timezone":"Asia/Shanghai",
    "iso:country":"CN",
    "name:und_x_variant":[
        "\u9ec4\u5899"
    ],
    "wof:name":"Huangqiang",
    "wof:placetype":"locality"
},
  "geometry": {"coordinates":[121.24118,31.33412],"type":"Point"}
}