{
  "type": "Feature",
  "properties": {
    "gn:admin1_code":"29.0",
    "gn:asciiname":"Dilizhao",
    "gn:country_code":"CN",
    "gn:dem":1858,
    "gn:feature_class":"P",
    "gn:feature_code":"PPL",
    "gn:name":"Dilizhao",
    "gn:population":0,
    "gn:timezone":"Asia/Shanghai",
    "iso:country":"CN",
    "name:zho_x_preferred":[
        "\u5730\u5229\u53ec"
    ],
    "wof:name":"Dilizhao",
    "wof:placetype":"locality"
},
  "geometry": {"coordinates":[103.795,24.7727],"type":"Point"}
}