{
  "type": "Feature",
  "properties": {
    "gn:admin1_code":"3.0",
    "gn:asciiname":"Hehe",
    "gn:country_code":"CN",
    "gn:dem":318,
    "gn:feature_class":"P",
    "gn:feature_code":"PPL",
    "gn:name":"Hehe",
    "gn:population":0,
    "gn:timezone":"Asia/Shanghai",
    "iso:country":"CN",
    "name:fra_x_preferred":[
        "Hehe"
    ],
    "name:spa_x_preferred":[
        "Hehe"
    ],
    "name:und_x_variant":[
        "\u5408\u548c"
    ],
    "wof:name":"Hehe",
    "wof:placetype":"locality"
},
  "geometry": {"coordinates":[114.52261,29.17214],"type":"Point"}
}