{
  "type": "Feature",
  "properties": {
    "gn:admin1_code":"32.0",
    "gn:asciiname":"Cuosanglong",
    "gn:country_code":"CN",
    "gn:dem":2883,
    "gn:feature_class":"P",
    "gn:feature_code":"PPL",
    "gn:name":"Cuosanglong",
    "gn:population":0,
    "gn:timezone":"Asia/Shanghai",
    "iso:country":"CN",
    "name:zho_x_preferred":[
        "\u9519\u6851\u9f99"
    ],
    "wof:name":"Cuosanglong",
    "wof:placetype":"locality"
},
  "geometry": {"coordinates":[99.21380000000001,30.2335],"type":"Point"}
}