{
  "type": "Feature",
  "properties": {
    "gn:admin1_code":"30",
    "gn:asciiname":"Huangtou",
    "gn:country_code":"CN",
    "gn:dem":34,
    "gn:feature_class":"P",
    "gn:feature_code":"PPL",
    "gn:name":"Huangtou",
    "gn:population":0,
    "gn:timezone":"Asia/Urumqi",
    "iso:country":"CN",
    "name:zho_x_preferred":[
        "\u9ec4\u5934"
    ],
    "wof:name":"Huangtou",
    "wof:placetype":"locality"
},
  "geometry": {"coordinates":[110.76179999999999,21.85446],"type":"Point"}
}