{
  "type": "Feature",
  "properties": {
    "gn:admin1_code":"32.0",
    "gn:asciiname":"Jimi",
    "gn:country_code":"CN",
    "gn:dem":2820,
    "gn:feature_class":"P",
    "gn:feature_code":"PPL",
    "gn:name":"Jimi",
    "gn:population":0,
    "gn:timezone":"Asia/Shanghai",
    "iso:country":"CN",
    "name:zho_x_preferred":[
        "\u5409\u7c73"
    ],
    "wof:name":"Jimi",
    "wof:placetype":"locality"
},
  "geometry": {"coordinates":[101.474,27.9305],"type":"Point"}
}