{
  "type": "Feature",
  "properties": {
    "gn:admin1_code":"5.0",
    "gn:asciiname":"Chengzicun",
    "gn:country_code":"CN",
    "gn:dem":138,
    "gn:feature_class":"P",
    "gn:feature_code":"PPL",
    "gn:name":"Chengzicun",
    "gn:population":0,
    "gn:timezone":"Asia/Shanghai",
    "iso:country":"CN",
    "name:zho_x_preferred":[
        "\u79f0\u5b57\u6751"
    ],
    "wof:name":"Chengzicun",
    "wof:placetype":"locality"
},
  "geometry": {"coordinates":[124.10397,45.07957],"type":"Point"}
}