{
  "type": "Feature",
  "properties": {
    "gn:admin1_code":"29.0",
    "gn:asciiname":"Dapingdi",
    "gn:country_code":"CN",
    "gn:dem":2412,
    "gn:feature_class":"P",
    "gn:feature_code":"PPL",
    "gn:name":"Dapingdi",
    "gn:population":0,
    "gn:timezone":"Asia/Shanghai",
    "iso:country":"CN",
    "name:zho_x_preferred":[
        "\u5927\u5e73\u5730"
    ],
    "wof:name":"Dapingdi",
    "wof:placetype":"locality"
},
  "geometry": {"coordinates":[99.8673,25.6226],"type":"Point"}
}