{
  "type": "Feature",
  "properties": {
    "gn:admin1_code":"1.0",
    "gn:asciiname":"Bailiancun",
    "gn:country_code":"CN",
    "gn:dem":21,
    "gn:feature_class":"P",
    "gn:feature_code":"PPL",
    "gn:name":"Bailiancun",
    "gn:population":0,
    "gn:timezone":"Asia/Shanghai",
    "iso:country":"CN",
    "name:zho_x_preferred":[
        "\u767d\u83b2\u6751"
    ],
    "wof:name":"Bailiancun",
    "wof:placetype":"locality"
},
  "geometry": {"coordinates":[116.89643,30.79743],"type":"Point"}
}