{
  "type": "Feature",
  "properties": {
    "gn:admin1_code":"19.0",
    "gn:asciiname":"Jinshanbu",
    "gn:country_code":"CN",
    "gn:dem":145,
    "gn:feature_class":"P",
    "gn:feature_code":"PPL",
    "gn:name":"Jinshanbu",
    "gn:population":0,
    "gn:timezone":"Asia/Shanghai",
    "iso:country":"CN",
    "name:und_x_variant":[
        "Jinshanbao",
        "Jinshanbu"
    ],
    "name:zho_x_preferred":[
        "\u91d1\u5c71\u5821"
    ],
    "wof:name":"Jinshanbu",
    "wof:placetype":"locality"
},
  "geometry": {"coordinates":[124.07973,42.84013],"type":"Point"}
}