{
  "type": "Feature",
  "properties": {
    "gn:admin1_code":"1.0",
    "gn:asciiname":"Aimin",
    "gn:country_code":"CN",
    "gn:dem":179,
    "gn:feature_class":"P",
    "gn:feature_code":"PPLA4",
    "gn:name":"Aimin",
    "gn:population":0,
    "gn:timezone":"Asia/Shanghai",
    "iso:country":"CN",
    "name:und_x_variant":[
        "\u7231\u6c11",
        "Aimin Xiang",
        "\u7231\u6c11\u4e61"
    ],
    "wof:name":"Aimin",
    "wof:placetype":"locality"
},
  "geometry": {"coordinates":[118.61724,30.64748],"type":"Point"}
}