{
  "type": "Feature",
  "properties": {
    "gn:admin1_code":"21.0",
    "gn:asciiname":"Liyanzi",
    "gn:country_code":"CN",
    "gn:dem":1299,
    "gn:feature_class":"P",
    "gn:feature_code":"PPL",
    "gn:name":"Liyanzi",
    "gn:population":0,
    "gn:timezone":"Asia/Shanghai",
    "iso:country":"CN",
    "name:zho_x_preferred":[
        "\u674e\u6cbf\u5b50"
    ],
    "wof:name":"Liyanzi",
    "wof:placetype":"locality"
},
  "geometry": {"coordinates":[105.81699999999999,37.1387],"type":"Point"}
}