{
  "type": "Feature",
  "properties": {
    "gn:admin1_code":"26.0",
    "gn:asciiname":"Tangdongcun",
    "gn:country_code":"CN",
    "gn:dem":413,
    "gn:feature_class":"P",
    "gn:feature_code":"PPL",
    "gn:name":"Tangdongcun",
    "gn:population":0,
    "gn:timezone":"Asia/Shanghai",
    "iso:country":"CN",
    "name:zho_x_preferred":[
        "\u6c64\u4e1c\u6751"
    ],
    "wof:name":"Tangdongcun",
    "wof:placetype":"locality"
},
  "geometry": {"coordinates":[108.96505000000001,34.57609],"type":"Point"}
}