{
  "type": "Feature",
  "properties": {
    "gn:admin1_code":"3.0",
    "gn:asciiname":"Yincun",
    "gn:country_code":"CN",
    "gn:dem":84,
    "gn:feature_class":"P",
    "gn:feature_code":"PPL",
    "gn:name":"Yincun",
    "gn:population":0,
    "gn:timezone":"Asia/Shanghai",
    "iso:country":"CN",
    "name:und_x_variant":[
        "\u94f6\u6751"
    ],
    "wof:name":"Yincun",
    "wof:placetype":"locality"
},
  "geometry": {"coordinates":[115.22443,27.47605],"type":"Point"}
}