{
  "type": "Feature",
  "properties": {
    "gn:admin1_code":"16.0",
    "gn:asciiname":"Xindi",
    "gn:cc2":"CN",
    "gn:country_code":"CN",
    "gn:dem":60,
    "gn:feature_class":"P",
    "gn:feature_code":"PPL",
    "gn:name":"Xindi",
    "gn:population":0,
    "gn:timezone":"Asia/Shanghai",
    "iso:country":"CN",
    "name:ceb_x_preferred":[
        "Xindi"
    ],
    "name:deu_x_preferred":[
        "Xindi"
    ],
    "name:und_x_variant":[
        "Hsin-ti",
        "Hsin-li-chieh",
        "Hsin-ti-hs\u00fc",
        "Hsin-li",
        "Hsin-li-hs\u00fc"
    ],
    "wof:name":"Xindi",
    "wof:placetype":"locality"
},
  "geometry": {"coordinates":[111.18333,23.23333],"type":"Point"}
}