{
  "type": "Feature",
  "properties": {
    "gn:admin1_code":"25",
    "gn:asciiname":"Linpanzhai",
    "gn:country_code":"CN",
    "gn:dem":42,
    "gn:feature_class":"P",
    "gn:feature_code":"PPL",
    "gn:name":"Linpanzhai",
    "gn:population":0,
    "gn:timezone":"Asia/Shanghai",
    "iso:country":"CN",
    "name:zho_x_preferred":[
        "\u6797\u6f58\u5be8"
    ],
    "wof:name":"Linpanzhai",
    "wof:placetype":"locality"
},
  "geometry": {"coordinates":[115.58177999999999,36.73485],"type":"Point"}
}