{
  "type": "Feature",
  "properties": {
    "gn:admin1_code":"32.0",
    "gn:asciiname":"Xuesongba",
    "gn:country_code":"CN",
    "gn:dem":3088,
    "gn:feature_class":"P",
    "gn:feature_code":"PPL",
    "gn:name":"Xuesongba",
    "gn:population":0,
    "gn:timezone":"Asia/Shanghai",
    "iso:country":"CN",
    "name:zho_x_preferred":[
        "\u96ea\u677e\u575d"
    ],
    "wof:name":"Xuesongba",
    "wof:placetype":"locality"
},
  "geometry": {"coordinates":[103.21955,33.55727],"type":"Point"}
}