{
  "type": "Feature",
  "properties": {
    "gn:admin1_code":"0.0",
    "gn:asciiname":"Lung-o-ch'eng",
    "gn:country_code":"CN",
    "gn:dem":1385,
    "gn:feature_class":"P",
    "gn:feature_code":"PPL",
    "gn:name":"Lung-o-ch\u2019eng",
    "gn:population":0,
    "gn:timezone":"Asia/Shanghai",
    "iso:country":"CN",
    "wof:name":"Lung-o-ch'eng",
    "wof:placetype":"locality"
},
  "geometry": {"coordinates":[99.18510999999999,23.51042],"type":"Point"}
}