{
  "type": "Feature",
  "properties": {
    "gn:admin1_code":"1.0",
    "gn:asciiname":"Yishancun",
    "gn:country_code":"CN",
    "gn:dem":15,
    "gn:feature_class":"P",
    "gn:feature_code":"PPL",
    "gn:name":"Yishancun",
    "gn:population":0,
    "gn:timezone":"Asia/Shanghai",
    "iso:country":"CN",
    "name:zho_x_preferred":[
        "\u4eea\u5c71\u6751"
    ],
    "wof:name":"Yishancun",
    "wof:placetype":"locality"
},
  "geometry": {"coordinates":[117.4354,30.76971],"type":"Point"}
}