{
  "type": "Feature",
  "properties": {
    "gn:admin1_code":"25",
    "gn:asciiname":"Gaowangzhuang",
    "gn:country_code":"CN",
    "gn:dem":15,
    "gn:feature_class":"P",
    "gn:feature_code":"PPL",
    "gn:name":"Gaowangzhuang",
    "gn:population":0,
    "gn:timezone":"Asia/Shanghai",
    "iso:country":"CN",
    "name:zho_x_preferred":[
        "\u9ad8\u738b\u5e84"
    ],
    "wof:name":"Gaowangzhuang",
    "wof:placetype":"locality"
},
  "geometry": {"coordinates":[117.58,37.3135],"type":"Point"}
}