{
  "type": "Feature",
  "properties": {
    "gn:admin1_code":"15.0",
    "gn:asciiname":"Awancang",
    "gn:country_code":"CN",
    "gn:dem":3504,
    "gn:feature_class":"P",
    "gn:feature_code":"PPLA4",
    "gn:name":"Awancang",
    "gn:population":0,
    "gn:timezone":"Asia/Shanghai",
    "iso:country":"CN",
    "name:und_x_variant":[
        "Awancang Xiang"
    ],
    "name:zho_x_preferred":[
        "\u963f\u4e07\u4ed3"
    ],
    "name:zho_x_variant":[
        "\u963f\u4e07\u4ed3\u4e61"
    ],
    "wof:name":"Awancang",
    "wof:placetype":"locality"
},
  "geometry": {"coordinates":[101.69716,33.77093],"type":"Point"}
}