{
  "type": "Feature",
  "properties": {
    "gn:admin1_code":"33.0",
    "gn:asciiname":"Dashuixi",
    "gn:country_code":"CN",
    "gn:dem":887,
    "gn:feature_class":"P",
    "gn:feature_code":"PPL",
    "gn:name":"Dashuixi",
    "gn:population":0,
    "gn:timezone":"Asia/Shanghai",
    "iso:country":"CN",
    "name:zho_x_preferred":[
        "\u5927\u6c34\u6eaa"
    ],
    "wof:name":"Dashuixi",
    "wof:placetype":"locality"
},
  "geometry": {"coordinates":[108.78606000000001,28.27966],"type":"Point"}
}