{
  "type": "Feature",
  "properties": {
    "gn:admin1_code":"1.0",
    "gn:asciiname":"Lianhua'ancun",
    "gn:country_code":"CN",
    "gn:dem":45,
    "gn:feature_class":"P",
    "gn:feature_code":"PPL",
    "gn:name":"Lianhua\u2019ancun",
    "gn:population":0,
    "gn:timezone":"Asia/Shanghai",
    "iso:country":"CN",
    "name:und_x_variant":[
        "Lianhua\u2019ancun",
        "Lianhua\u2019an"
    ],
    "name:zho_x_preferred":[
        "\u83b2\u82b1\u5eb5\u6751"
    ],
    "wof:name":"Lianhua'ancun",
    "wof:placetype":"locality"
},
  "geometry": {"coordinates":[116.38012999999999,31.73907],"type":"Point"}
}