{
  "type": "Feature",
  "properties": {
    "gn:admin1_code":"16.0",
    "gn:asciiname":"Zhaibao",
    "gn:country_code":"CN",
    "gn:dem":954,
    "gn:feature_class":"P",
    "gn:feature_code":"PPL",
    "gn:name":"Zhaibao",
    "gn:population":0,
    "gn:timezone":"Asia/Shanghai",
    "iso:country":"CN",
    "name:zho_x_preferred":[
        "\u5be8\u4fdd"
    ],
    "wof:name":"Zhaibao",
    "wof:placetype":"locality"
},
  "geometry": {"coordinates":[110.21299999999999,24.2142],"type":"Point"}
}