{
  "type": "Feature",
  "properties": {
    "gn:admin1_code":"16.0",
    "gn:asciiname":"Lunlou",
    "gn:country_code":"CN",
    "gn:dem":333,
    "gn:feature_class":"P",
    "gn:feature_code":"PPL",
    "gn:name":"Lunlou",
    "gn:population":0,
    "gn:timezone":"Asia/Shanghai",
    "iso:country":"CN",
    "name:zho_x_preferred":[
        "\u4f26\u697c"
    ],
    "wof:name":"Lunlou",
    "wof:placetype":"locality"
},
  "geometry": {"coordinates":[106.271,23.995],"type":"Point"}
}