{
  "type": "Feature",
  "properties": {
    "gn:admin1_code":"24.0",
    "gn:asciiname":"Shageta",
    "gn:country_code":"CN",
    "gn:dem":1325,
    "gn:feature_class":"P",
    "gn:feature_code":"PPL",
    "gn:name":"Shageta",
    "gn:population":0,
    "gn:timezone":"Asia/Shanghai",
    "iso:country":"CN",
    "name:zho_x_preferred":[
        "\u7802\u572a\u5854"
    ],
    "wof:name":"Shageta",
    "wof:placetype":"locality"
},
  "geometry": {"coordinates":[112.45349,36.70736],"type":"Point"}
}