{
  "type": "Feature",
  "properties": {
    "gn:admin1_code":"30",
    "gn:asciiname":"Zhangshuzai",
    "gn:country_code":"CN",
    "gn:dem":124,
    "gn:feature_class":"P",
    "gn:feature_code":"PPL",
    "gn:name":"Zhangshuzai",
    "gn:population":0,
    "gn:timezone":"Asia/Shanghai",
    "iso:country":"CN",
    "name:zho_x_preferred":[
        "\u6a1f\u6811\u4ed4"
    ],
    "wof:name":"Zhangshuzai",
    "wof:placetype":"locality"
},
  "geometry": {"coordinates":[115.87369,23.20573],"type":"Point"}
}