{
  "type": "Feature",
  "properties": {
    "gn:admin1_code":"1.0",
    "gn:asciiname":"Zhuoliucun",
    "gn:country_code":"CN",
    "gn:dem":29,
    "gn:feature_class":"P",
    "gn:feature_code":"PPL",
    "gn:name":"Zhuoliucun",
    "gn:population":0,
    "gn:timezone":"Asia/Shanghai",
    "iso:country":"CN",
    "name:zho_x_preferred":[
        "\u5353\u5218\u6751"
    ],
    "wof:name":"Zhuoliucun",
    "wof:placetype":"locality"
},
  "geometry": {"coordinates":[117.16116,33.62034],"type":"Point"}
}