{
  "type": "Feature",
  "properties": {
    "gn:admin1_code":"25",
    "gn:asciiname":"Dajiang",
    "gn:country_code":"CN",
    "gn:dem":31,
    "gn:feature_class":"P",
    "gn:feature_code":"PPL",
    "gn:name":"Dajiang",
    "gn:population":0,
    "gn:timezone":"Asia/Shanghai",
    "iso:country":"CN",
    "name:zho_x_preferred":[
        "\u5927\u59dc"
    ],
    "wof:name":"Dajiang",
    "wof:placetype":"locality"
},
  "geometry": {"coordinates":[117.914,36.8634],"type":"Point"}
}