{
  "type": "Feature",
  "properties": {
    "gn:admin1_code":"24.0",
    "gn:asciiname":"Qianshiyu",
    "gn:country_code":"CN",
    "gn:dem":1491,
    "gn:feature_class":"P",
    "gn:feature_code":"PPL",
    "gn:name":"Qianshiyu",
    "gn:population":0,
    "gn:timezone":"Asia/Shanghai",
    "iso:country":"CN",
    "name:zho_x_preferred":[
        "\u524d\u5e08\u5cea"
    ],
    "wof:name":"Qianshiyu",
    "wof:placetype":"locality"
},
  "geometry": {"coordinates":[111.35975999999999,37.28004],"type":"Point"}
}