{
  "type": "Feature",
  "properties": {
    "gn:admin1_code":"31.0",
    "gn:asciiname":"Jiadongtian",
    "gn:country_code":"CN",
    "gn:dem":96,
    "gn:feature_class":"P",
    "gn:feature_code":"PPL",
    "gn:name":"Jiadongtian",
    "gn:population":0,
    "gn:timezone":"Asia/Shanghai",
    "iso:country":"CN",
    "name:zho_x_preferred":[
        "\u52a0\u4e1c\u7530"
    ],
    "wof:name":"Jiadongtian",
    "wof:placetype":"locality"
},
  "geometry": {"coordinates":[110.24321999999999,19.19283],"type":"Point"}
}