{
  "type": "Feature",
  "properties": {
    "gn:admin1_code":"12.0",
    "gn:asciiname":"Shujiawan",
    "gn:country_code":"CN",
    "gn:dem":25,
    "gn:feature_class":"P",
    "gn:feature_code":"PPL",
    "gn:name":"Shujiawan",
    "gn:population":0,
    "gn:timezone":"Asia/Shanghai",
    "iso:country":"CN",
    "name:zho_x_preferred":[
        "\u675f\u5bb6\u6e7e"
    ],
    "wof:name":"Shujiawan",
    "wof:placetype":"locality"
},
  "geometry": {"coordinates":[113.60841000000001,30.23879],"type":"Point"}
}