{
  "type": "Feature",
  "properties": {
    "gn:admin1_code":"5.0",
    "gn:asciiname":"Qijianfangcun",
    "gn:country_code":"CN",
    "gn:dem":263,
    "gn:feature_class":"P",
    "gn:feature_code":"PPL",
    "gn:name":"Qijianfangcun",
    "gn:population":0,
    "gn:timezone":"Asia/Shanghai",
    "iso:country":"CN",
    "name:zho_x_preferred":[
        "\u4e03\u95f4\u623f\u6751"
    ],
    "wof:name":"Qijianfangcun",
    "wof:placetype":"locality"
},
  "geometry": {"coordinates":[125.96623,43.48717],"type":"Point"}
}