{
  "type": "Feature",
  "properties": {
    "gn:admin1_code":"12.0",
    "gn:asciiname":"Leizutang",
    "gn:country_code":"CN",
    "gn:dem":29,
    "gn:feature_class":"P",
    "gn:feature_code":"PPL",
    "gn:name":"Leizutang",
    "gn:population":0,
    "gn:timezone":"Asia/Shanghai",
    "iso:country":"CN",
    "name:zho_x_preferred":[
        "\u96f7\u7956\u5802"
    ],
    "wof:name":"Leizutang",
    "wof:placetype":"locality"
},
  "geometry": {"coordinates":[113.76772,30.60824],"type":"Point"}
}