{
  "type": "Feature",
  "properties": {
    "gn:admin1_code":"15.0",
    "gn:asciiname":"Xiawan",
    "gn:country_code":"CN",
    "gn:dem":1956,
    "gn:feature_class":"P",
    "gn:feature_code":"PPL",
    "gn:name":"Xiawan",
    "gn:population":0,
    "gn:timezone":"Asia/Shanghai",
    "iso:country":"CN",
    "name:und_x_variant":[
        "\u4e0b\u6e7e"
    ],
    "wof:name":"Xiawan",
    "wof:placetype":"locality"
},
  "geometry": {"coordinates":[105.12864999999999,35.71907],"type":"Point"}
}