{
  "type": "Feature",
  "properties": {
    "gn:admin1_code":"14.0",
    "gn:asciiname":"Xiadang",
    "gn:country_code":"CN",
    "gn:dem":4262,
    "gn:feature_class":"P",
    "gn:feature_code":"PPL",
    "gn:name":"Xiadang",
    "gn:population":0,
    "gn:timezone":"Asia/Urumqi",
    "iso:country":"CN",
    "name:zho_x_preferred":[
        "\u867e\u5f53"
    ],
    "wof:name":"Xiadang",
    "wof:placetype":"locality"
},
  "geometry": {"coordinates":[85.4688,28.5458],"type":"Point"}
}