{
  "type": "Feature",
  "properties": {
    "gn:admin1_code":"2.0",
    "gn:asciiname":"Shangrenbang",
    "gn:country_code":"CN",
    "gn:dem":8,
    "gn:feature_class":"P",
    "gn:feature_code":"PPL",
    "gn:name":"Shangrenbang",
    "gn:population":0,
    "gn:timezone":"Asia/Shanghai",
    "iso:country":"CN",
    "name:und_x_variant":[
        "\u4e0a\u4ec1\u6d5c"
    ],
    "wof:name":"Shangrenbang",
    "wof:placetype":"locality"
},
  "geometry": {"coordinates":[120.60729000000001,30.74449000000001],"type":"Point"}
}