{
  "type": "Feature",
  "properties": {
    "gn:admin1_code":"8.0",
    "gn:asciiname":"Xibeicun",
    "gn:country_code":"CN",
    "gn:dem":57,
    "gn:feature_class":"P",
    "gn:feature_code":"PPL",
    "gn:name":"Xibeicun",
    "gn:population":0,
    "gn:timezone":"Asia/Shanghai",
    "iso:country":"CN",
    "name:zho_x_preferred":[
        "\u897f\u5317\u6751"
    ],
    "wof:name":"Xibeicun",
    "wof:placetype":"locality"
},
  "geometry": {"coordinates":[132.18903,47.37797],"type":"Point"}
}