{
  "type": "Feature",
  "properties": {
    "gn:admin1_code":"29.0",
    "gn:asciiname":"Yangtianqing",
    "gn:country_code":"CN",
    "gn:dem":2044,
    "gn:feature_class":"P",
    "gn:feature_code":"PPL",
    "gn:name":"Yangtianqing",
    "gn:population":0,
    "gn:timezone":"Asia/Shanghai",
    "iso:country":"CN",
    "name:zho_x_preferred":[
        "\u79e7\u7530\u7b90"
    ],
    "wof:name":"Yangtianqing",
    "wof:placetype":"locality"
},
  "geometry": {"coordinates":[100.05,25.1043],"type":"Point"}
}