{
  "type": "Feature",
  "properties": {
    "gn:admin1_code":"32.0",
    "gn:asciiname":"Daojiaolin",
    "gn:country_code":"CN",
    "gn:dem":554,
    "gn:feature_class":"P",
    "gn:feature_code":"PPL",
    "gn:name":"Daojiaolin",
    "gn:population":0,
    "gn:timezone":"Asia/Shanghai",
    "iso:country":"CN",
    "name:zho_x_preferred":[
        "\u5012\u89d2\u6797"
    ],
    "wof:name":"Daojiaolin",
    "wof:placetype":"locality"
},
  "geometry": {"coordinates":[105.28171,31.67898],"type":"Point"}
}