{
  "type": "Feature",
  "properties": {
    "gn:admin1_code":"30",
    "gn:asciiname":"Yidongcun",
    "gn:country_code":"CN",
    "gn:dem":58,
    "gn:feature_class":"P",
    "gn:feature_code":"PPL",
    "gn:name":"Yidongcun",
    "gn:population":0,
    "gn:timezone":"Asia/Shanghai",
    "iso:country":"CN",
    "name:und_x_variant":[
        "Yitong",
        "Yidong",
        "Yidongcun"
    ],
    "name:zho_x_preferred":[
        "\u5b9c\u6d1e"
    ],
    "name:zho_x_variant":[
        "\u5b9c\u578c\u6751"
    ],
    "wof:name":"Yidongcun",
    "wof:placetype":"locality"
},
  "geometry": {"coordinates":[112.45417,23.58189],"type":"Point"}
}