{
  "type": "Feature",
  "properties": {
    "gn:admin1_code":"24.0",
    "gn:asciiname":"Wanbaoshan",
    "gn:country_code":"CN",
    "gn:dem":670,
    "gn:feature_class":"P",
    "gn:feature_code":"PPL",
    "gn:name":"Wanbaoshan",
    "gn:population":0,
    "gn:timezone":"Asia/Shanghai",
    "iso:country":"CN",
    "name:zho_x_preferred":[
        "\u4e07\u5b9d\u5c71"
    ],
    "wof:name":"Wanbaoshan",
    "wof:placetype":"locality"
},
  "geometry": {"coordinates":[110.51579,35.88316],"type":"Point"}
}