{
  "type": "Feature",
  "properties": {
    "gn:admin1_code":"7.0",
    "gn:asciiname":"Beizhai",
    "gn:country_code":"CN",
    "gn:dem":294,
    "gn:feature_class":"P",
    "gn:feature_code":"PPL",
    "gn:name":"Beizhai",
    "gn:population":0,
    "gn:timezone":"Asia/Shanghai",
    "iso:country":"CN",
    "name:zho_x_preferred":[
        "\u80cc\u5be8"
    ],
    "wof:name":"Beizhai",
    "wof:placetype":"locality"
},
  "geometry": {"coordinates":[115.8621,25.18725],"type":"Point"}
}