{
  "type": "Feature",
  "properties": {
    "gn:admin1_code":"25",
    "gn:asciiname":"Yangchengbanan",
    "gn:country_code":"CN",
    "gn:dem":43,
    "gn:feature_class":"P",
    "gn:feature_code":"PPL",
    "gn:name":"Yangchengbanan",
    "gn:population":0,
    "gn:timezone":"Asia/Shanghai",
    "iso:country":"CN",
    "name:zho_x_preferred":[
        "\u9633\u57ce\u575d\u5357"
    ],
    "wof:name":"Yangchengbanan",
    "wof:placetype":"locality"
},
  "geometry": {"coordinates":[116.334,35.7855],"type":"Point"}
}