{
  "type": "Feature",
  "properties": {
    "gn:admin1_code":"32.0",
    "gn:asciiname":"Juren",
    "gn:country_code":"CN",
    "gn:dem":514,
    "gn:feature_class":"P",
    "gn:feature_code":"PPL",
    "gn:name":"Juren",
    "gn:population":0,
    "gn:timezone":"Asia/Shanghai",
    "iso:country":"CN",
    "name:kor_x_preferred":[
        "\uac70\uc778"
    ],
    "name:zho_x_preferred":[
        "\u4e3e\u4eba"
    ],
    "wof:name":"Juren",
    "wof:placetype":"locality"
},
  "geometry": {"coordinates":[107.348,31.1953],"type":"Point"}
}