{
  "type": "Feature",
  "properties": {
    "gn:admin1_code":"18",
    "gn:asciiname":"Gerong",
    "gn:country_code":"CN",
    "gn:dem":1230,
    "gn:feature_class":"P",
    "gn:feature_code":"PPL",
    "gn:name":"Gerong",
    "gn:population":0,
    "gn:timezone":"Asia/Shanghai",
    "iso:country":"CN",
    "name:zho_x_preferred":[
        "\u683c\u5197"
    ],
    "wof:name":"Gerong",
    "wof:placetype":"locality"
},
  "geometry": {"coordinates":[106.36199999999999,25.8458],"type":"Point"}
}