{
  "type": "Feature",
  "properties": {
    "gn:admin1_code":"19.0",
    "gn:asciiname":"Houdaluyao",
    "gn:country_code":"CN",
    "gn:dem":14,
    "gn:feature_class":"P",
    "gn:feature_code":"PPL",
    "gn:name":"Houdaluyao",
    "gn:population":0,
    "gn:timezone":"Asia/Shanghai",
    "iso:country":"CN",
    "name:zho_x_preferred":[
        "\u540e\u6253\u8def\u8170"
    ],
    "wof:name":"Houdaluyao",
    "wof:placetype":"locality"
},
  "geometry": {"coordinates":[122.27500000000001,39.4562],"type":"Point"}
}