{
  "type": "Feature",
  "properties": {
    "gn:admin1_code":"21.0",
    "gn:asciiname":"Shangmawa",
    "gn:country_code":"CN",
    "gn:dem":1600,
    "gn:feature_class":"P",
    "gn:feature_code":"PPL",
    "gn:name":"Shangmawa",
    "gn:population":0,
    "gn:timezone":"Asia/Shanghai",
    "iso:country":"CN",
    "name:zho_x_preferred":[
        "\u4e0a\u9a6c\u6d3c"
    ],
    "wof:name":"Shangmawa",
    "wof:placetype":"locality"
},
  "geometry": {"coordinates":[106.52500000000001,35.8098],"type":"Point"}
}