{
  "type": "Feature",
  "properties": {
    "gn:admin1_code":"19.0",
    "gn:asciiname":"Dianzi",
    "gn:country_code":"CN",
    "gn:dem":95,
    "gn:feature_class":"P",
    "gn:feature_code":"PPL",
    "gn:name":"Dianzi",
    "gn:population":0,
    "gn:timezone":"Asia/Shanghai",
    "iso:country":"CN",
    "name:und_x_variant":[
        "\u7538\u5b50"
    ],
    "wof:name":"Dianzi",
    "wof:placetype":"locality"
},
  "geometry": {"coordinates":[123.25941,40.17423],"type":"Point"}
}