{
  "type": "Feature",
  "properties": {
    "gn:admin1_code":"5.0",
    "gn:asciiname":"Pingbaocun",
    "gn:country_code":"CN",
    "gn:dem":138,
    "gn:feature_class":"P",
    "gn:feature_code":"PPL",
    "gn:name":"Pingbaocun",
    "gn:population":0,
    "gn:timezone":"Asia/Shanghai",
    "iso:country":"CN",
    "name:zho_x_preferred":[
        "\u5e73\u4fdd\u6751"
    ],
    "wof:name":"Pingbaocun",
    "wof:placetype":"locality"
},
  "geometry": {"coordinates":[123.18153999999998,45.90726],"type":"Point"}
}