{
  "type": "Feature",
  "properties": {
    "gn:admin1_code":"3.0",
    "gn:asciiname":"Zhushandi",
    "gn:country_code":"CN",
    "gn:dem":28,
    "gn:feature_class":"P",
    "gn:feature_code":"PPL",
    "gn:name":"Zhushandi",
    "gn:population":0,
    "gn:timezone":"Asia/Shanghai",
    "iso:country":"CN",
    "name:und_x_variant":[
        "\u7af9\u5c71\u5e95"
    ],
    "wof:name":"Zhushandi",
    "wof:placetype":"locality"
},
  "geometry": {"coordinates":[116.94517,28.33166],"type":"Point"}
}