{
  "type": "Feature",
  "properties": {
    "gn:admin1_code":"29.0",
    "gn:asciiname":"Sanwenbi",
    "gn:country_code":"CN",
    "gn:dem":2065,
    "gn:feature_class":"P",
    "gn:feature_code":"PPL",
    "gn:name":"Sanwenbi",
    "gn:population":0,
    "gn:timezone":"Asia/Shanghai",
    "iso:country":"CN",
    "name:zho_x_preferred":[
        "\u4e09\u6587\u7b14"
    ],
    "wof:name":"Sanwenbi",
    "wof:placetype":"locality"
},
  "geometry": {"coordinates":[100.14400000000001,25.7069],"type":"Point"}
}