{
  "type": "Feature",
  "properties": {
    "gn:admin1_code":"3",
    "gn:asciiname":"Wudang",
    "gn:country_code":"CN",
    "gn:dem":382,
    "gn:feature_class":"P",
    "gn:feature_code":"PPLA4",
    "gn:name":"Wudang",
    "gn:population":0,
    "gn:timezone":"Asia/Shanghai",
    "iso:country":"CN",
    "name:und_x_variant":[
        "\u6b66\u5f53",
        "Wudang Zhen",
        "\u6b66\u5f53\u9547"
    ],
    "wof:name":"Wudang",
    "wof:placetype":"locality"
},
  "geometry": {"coordinates":[114.75217000000001,24.63993],"type":"Point"}
}