{
  "type": "Feature",
  "properties": {
    "gn:admin1_code":"20",
    "gn:asciiname":"Daliuhao",
    "gn:country_code":"CN",
    "gn:dem":1457,
    "gn:feature_class":"P",
    "gn:feature_code":"PPLA4",
    "gn:name":"Daliuhao",
    "gn:population":0,
    "gn:timezone":"Asia/Shanghai",
    "iso:country":"CN",
    "name:und_x_variant":[
        "Ta-liu-hao",
        "Ta-lu-hao",
        "Daliuhao",
        "\u5927\u516d\u53f7"
    ],
    "wof:name":"Daliuhao",
    "wof:placetype":"locality"
},
  "geometry": {"coordinates":[113.29058000000001,41.22594],"type":"Point"}
}