{
  "type": "Feature",
  "properties": {
    "gn:admin1_code":"12.0",
    "gn:asciiname":"Lilinpeng",
    "gn:country_code":"CN",
    "gn:dem":80,
    "gn:feature_class":"P",
    "gn:feature_code":"PPL",
    "gn:name":"Lilinpeng",
    "gn:population":0,
    "gn:timezone":"Asia/Shanghai",
    "iso:country":"CN",
    "name:zho_x_preferred":[
        "\u6817\u6797\u5f6d"
    ],
    "wof:name":"Lilinpeng",
    "wof:placetype":"locality"
},
  "geometry": {"coordinates":[114.76922,31.20532],"type":"Point"}
}