{
  "type": "Feature",
  "properties": {
    "gn:admin1_code":"8.0",
    "gn:asciiname":"Beixingcun",
    "gn:country_code":"CN",
    "gn:dem":229,
    "gn:feature_class":"P",
    "gn:feature_code":"PPL",
    "gn:name":"Beixingcun",
    "gn:population":0,
    "gn:timezone":"Asia/Shanghai",
    "iso:country":"CN",
    "name:zho_x_preferred":[
        "\u5317\u661f\u6751"
    ],
    "wof:name":"Beixingcun",
    "wof:placetype":"locality"
},
  "geometry": {"coordinates":[128.19783000000001,47.08103],"type":"Point"}
}