{
  "type": "Feature",
  "properties": {
    "gn:admin1_code":"31",
    "gn:asciiname":"Yari",
    "gn:country_code":"CN",
    "gn:dem":284,
    "gn:feature_class":"P",
    "gn:feature_code":"PPL",
    "gn:name":"Yari",
    "gn:population":0,
    "gn:timezone":"Asia/Shanghai",
    "iso:country":"CN",
    "name:ast_x_preferred":[
        "Yari"
    ],
    "name:bul_x_preferred":[
        "\u042f\u0440\u0438"
    ],
    "name:cat_x_preferred":[
        "Yari"
    ],
    "name:dan_x_preferred":[
        "Yari"
    ],
    "name:deu_x_preferred":[
        "Yari"
    ],
    "name:eus_x_preferred":[
        "Yari"
    ],
    "name:fin_x_preferred":[
        "Yari"
    ],
    "name:fra_x_preferred":[
        "Yari"
    ],
    "name:heb_x_preferred":[
        "\u05d9\u05d0\u05e8\u05d9"
    ],
    "name:ind_x_preferred":[
        "Yari"
    ],
    "name:ita_x_preferred":[
        "Yari"
    ],
    "name:kor_x_preferred":[
        "\ucc3d"
    ],
    "name:mkd_x_preferred":[
        "\u0408\u0430\u0440\u0438"
    ],
    "name:nld_x_preferred":[
        "Yari"
    ],
    "name:pol_x_preferred":[
        "Yari"
    ],
    "name:por_x_preferred":[
        "Yari"
    ],
    "name:rus_x_preferred":[
        "\u042f\u0440\u0438"
    ],
    "name:spa_x_preferred":[
        "Yari"
    ],
    "name:srp_x_preferred":[
        "\u0408\u0430\u0440\u0438"
    ],
    "name:swe_x_preferred":[
        "Yari"
    ],
    "name:tur_x_preferred":[
        "Yari"
    ],
    "name:ukr_x_preferred":[
        "\u042f\u0440\u0456"
    ],
    "name:und_x_variant":[
        "\u7259\u65e5"
    ],
    "name:vie_x_preferred":[
        "Yari"
    ],
    "wof:name":"Yari",
    "wof:placetype":"locality"
},
  "geometry": {"coordinates":[109.437,18.7937],"type":"Point"}
}