{
  "type": "Feature",
  "properties": {
    "gn:admin1_code":"1.0",
    "gn:asciiname":"Mawan",
    "gn:country_code":"CN",
    "gn:dem":38,
    "gn:feature_class":"P",
    "gn:feature_code":"PPL",
    "gn:name":"Mawan",
    "gn:population":0,
    "gn:timezone":"Asia/Shanghai",
    "iso:country":"CN",
    "name:ceb_x_preferred":[
        "Mawan"
    ],
    "name:swe_x_preferred":[
        "Mawan"
    ],
    "wof:name":"Mawan",
    "wof:placetype":"locality"
},
  "geometry": {"coordinates":[115.55,33.51667],"type":"Point"}
}