{
  "type": "Feature",
  "properties": {
    "gn:admin1_code":"16.0",
    "gn:asciiname":"Bizhouwei",
    "gn:country_code":"CN",
    "gn:dem":74,
    "gn:feature_class":"P",
    "gn:feature_code":"PPL",
    "gn:name":"Bizhouwei",
    "gn:population":0,
    "gn:timezone":"Asia/Shanghai",
    "iso:country":"CN",
    "name:zho_x_preferred":[
        "\u5fc5\u6d32\u5c3e"
    ],
    "wof:name":"Bizhouwei",
    "wof:placetype":"locality"
},
  "geometry": {"coordinates":[110.845,24.0372],"type":"Point"}
}