{
  "type": "Feature",
  "properties": {
    "gn:admin1_code":"30.0",
    "gn:asciiname":"Lidong",
    "gn:country_code":"CN",
    "gn:dem":125,
    "gn:feature_class":"P",
    "gn:feature_code":"PPL",
    "gn:name":"Lidong",
    "gn:population":0,
    "gn:timezone":"Asia/Shanghai",
    "iso:country":"CN",
    "name:zho_x_preferred":[
        "\u5229\u578c"
    ],
    "wof:name":"Lidong",
    "wof:placetype":"locality"
},
  "geometry": {"coordinates":[111.99742999999999,23.18544],"type":"Point"}
}