{
  "type": "Feature",
  "properties": {
    "gn:admin1_code":"29.0",
    "gn:asciiname":"Fengyidian",
    "gn:country_code":"CN",
    "gn:dem":2595,
    "gn:feature_class":"P",
    "gn:feature_code":"PPL",
    "gn:name":"Fengyidian",
    "gn:population":0,
    "gn:timezone":"Asia/Shanghai",
    "iso:country":"CN",
    "name:zho_x_preferred":[
        "\u4e30\u9091\u7538"
    ],
    "wof:name":"Fengyidian",
    "wof:placetype":"locality"
},
  "geometry": {"coordinates":[99.4272,26.3156],"type":"Point"}
}