{
  "type": "Feature",
  "properties": {
    "gn:admin1_code":"19.0",
    "gn:asciiname":"Youjia Buzi",
    "gn:country_code":"CN",
    "gn:dem":203,
    "gn:feature_class":"P",
    "gn:feature_code":"PPL",
    "gn:name":"Youjia Buzi",
    "gn:population":0,
    "gn:timezone":"Asia/Shanghai",
    "iso:country":"CN",
    "name:und_x_variant":[
        "Youjiabaozi",
        "Youjia Buzi"
    ],
    "name:zho_x_preferred":[
        "\u5c24\u5bb6\u5821\u5b50"
    ],
    "wof:name":"Youjia Buzi",
    "wof:placetype":"locality"
},
  "geometry": {"coordinates":[123.12278999999999,40.88008],"type":"Point"}
}