{
  "type": "Feature",
  "properties": {
    "gn:admin1_code":"30.0",
    "gn:asciiname":"Wangpo",
    "gn:country_code":"CN",
    "gn:dem":282,
    "gn:feature_class":"P",
    "gn:feature_code":"PPL",
    "gn:name":"Wangpo",
    "gn:population":0,
    "gn:timezone":"Asia/Urumqi",
    "iso:country":"CN",
    "name:zho_x_preferred":[
        "\u65fa\u5761"
    ],
    "wof:name":"Wangpo",
    "wof:placetype":"locality"
},
  "geometry": {"coordinates":[110.90738,22.49386],"type":"Point"}
}