{
  "type": "Feature",
  "properties": {
    "gn:admin1_code":"29.0",
    "gn:asciiname":"Xiniutang",
    "gn:country_code":"CN",
    "gn:dem":1906,
    "gn:feature_class":"P",
    "gn:feature_code":"PPL",
    "gn:name":"Xiniutang",
    "gn:population":0,
    "gn:timezone":"Asia/Shanghai",
    "iso:country":"CN",
    "name:zho_x_preferred":[
        "\u7280\u725b\u5858"
    ],
    "wof:name":"Xiniutang",
    "wof:placetype":"locality"
},
  "geometry": {"coordinates":[103.447,25.8193],"type":"Point"}
}