{
  "type": "Feature",
  "properties": {
    "gn:admin1_code":"18",
    "gn:asciiname":"Wujiafen",
    "gn:country_code":"CN",
    "gn:dem":1118,
    "gn:feature_class":"P",
    "gn:feature_code":"PPL",
    "gn:name":"Wujiafen",
    "gn:population":0,
    "gn:timezone":"Asia/Shanghai",
    "iso:country":"CN",
    "name:zho_x_preferred":[
        "\u5434\u5bb6\u575f"
    ],
    "wof:name":"Wujiafen",
    "wof:placetype":"locality"
},
  "geometry": {"coordinates":[107.599,27.2511],"type":"Point"}
}