{
  "type": "Feature",
  "properties": {
    "gn:admin1_code":"9",
    "gn:asciiname":"Houjiagou",
    "gn:country_code":"CN",
    "gn:dem":1177,
    "gn:feature_class":"P",
    "gn:feature_code":"PPL",
    "gn:name":"Houjiagou",
    "gn:population":0,
    "gn:timezone":"Asia/Shanghai",
    "iso:country":"CN",
    "wof:name":"Houjiagou",
    "wof:placetype":"locality"
},
  "geometry": {"coordinates":[110.60417,34.11083],"type":"Point"}
}