{
  "type": "Feature",
  "properties": {
    "gn:admin1_code":"30.0",
    "gn:asciiname":"Fengshuxia",
    "gn:country_code":"CN",
    "gn:dem":68,
    "gn:feature_class":"P",
    "gn:feature_code":"PPL",
    "gn:name":"Fengshuxia",
    "gn:population":0,
    "gn:timezone":"Asia/Shanghai",
    "iso:country":"CN",
    "name:und_x_variant":[
        "\u67ab\u6811\u4e0b"
    ],
    "name:zho_x_preferred":[
        "\u67ab\u6811\u4e0b"
    ],
    "wof:name":"Fengshuxia",
    "wof:placetype":"locality"
},
  "geometry": {"coordinates":[114.81086000000001,23.41293],"type":"Point"}
}