{
  "type": "Feature",
  "properties": {
    "gn:admin1_code":"18",
    "gn:asciiname":"Longgu",
    "gn:country_code":"CN",
    "gn:dem":2413,
    "gn:feature_class":"P",
    "gn:feature_code":"PPL",
    "gn:name":"Longgu",
    "gn:population":0,
    "gn:timezone":"Asia/Shanghai",
    "iso:country":"CN",
    "name:zho_x_preferred":[
        "\u9f99\u59d1"
    ],
    "wof:name":"Longgu",
    "wof:placetype":"locality"
},
  "geometry": {"coordinates":[104.09099999999999,27.1765],"type":"Point"}
}