{
  "type": "Feature",
  "properties": {
    "gn:admin1_code":"08",
    "gn:asciiname":"San-chia-tzu",
    "gn:country_code":"CN",
    "gn:dem":132,
    "gn:feature_class":"P",
    "gn:feature_code":"PPL",
    "gn:name":"San-chia-tzu",
    "gn:population":0,
    "gn:timezone":"Asia/Shanghai",
    "iso:country":"CN",
    "wof:name":"San-chia-tzu",
    "wof:placetype":"locality"
},
  "geometry": {"coordinates":[126.81222,46.09222000000001],"type":"Point"}
}