{
  "type": "Feature",
  "properties": {
    "gn:admin1_code":"7",
    "gn:asciiname":"Gaiwei",
    "gn:country_code":"CN",
    "gn:dem":36,
    "gn:feature_class":"P",
    "gn:feature_code":"PPLA4",
    "gn:name":"Gaiwei",
    "gn:population":0,
    "gn:timezone":"Asia/Shanghai",
    "iso:country":"CN",
    "name:und_x_variant":[
        "Gaiwei Zhen"
    ],
    "name:zho_x_preferred":[
        "\u76d6\u5c3e"
    ],
    "name:zho_x_variant":[
        "\u76d6\u5c3e\u9547"
    ],
    "wof:name":"Gaiwei",
    "wof:placetype":"locality"
},
  "geometry": {"coordinates":[118.80652000000001,25.35184],"type":"Point"}
}