{
  "type": "Feature",
  "properties": {
    "gn:admin1_code":"25",
    "gn:asciiname":"Sunjing",
    "gn:country_code":"CN",
    "gn:dem":53,
    "gn:feature_class":"P",
    "gn:feature_code":"PPL",
    "gn:name":"Sunjing",
    "gn:population":0,
    "gn:timezone":"Asia/Shanghai",
    "iso:country":"CN",
    "name:zho_x_preferred":[
        "\u5b59\u4e95"
    ],
    "wof:name":"Sunjing",
    "wof:placetype":"locality"
},
  "geometry": {"coordinates":[115.65600000000001,34.6694],"type":"Point"}
}