{
  "type": "Feature",
  "properties": {
    "gn:admin1_code":"05",
    "gn:asciiname":"Hsiao-chien-ch'ang-kou",
    "gn:country_code":"CN",
    "gn:dem":528,
    "gn:feature_class":"P",
    "gn:feature_code":"PPL",
    "gn:name":"Hsiao-chien-ch\u2019ang-kou",
    "gn:population":0,
    "gn:timezone":"Asia/Shanghai",
    "iso:country":"CN",
    "wof:name":"Hsiao-chien-ch'ang-kou",
    "wof:placetype":"locality"
},
  "geometry": {"coordinates":[125.3275,41.895],"type":"Point"}
}