{
  "type": "Feature",
  "properties": {
    "gn:admin1_code":"16.0",
    "gn:asciiname":"Gaotouling",
    "gn:country_code":"CN",
    "gn:dem":130,
    "gn:feature_class":"P",
    "gn:feature_code":"PPL",
    "gn:name":"Gaotouling",
    "gn:population":0,
    "gn:timezone":"Asia/Shanghai",
    "iso:country":"CN",
    "name:zho_x_preferred":[
        "\u9ad8\u5934\u5cad"
    ],
    "wof:name":"Gaotouling",
    "wof:placetype":"locality"
},
  "geometry": {"coordinates":[110.818,24.6647],"type":"Point"}
}