{
  "type": "Feature",
  "properties": {
    "gn:admin1_code":"16.0",
    "gn:asciiname":"Longdong",
    "gn:country_code":"CN",
    "gn:dem":270,
    "gn:feature_class":"P",
    "gn:feature_code":"PPL",
    "gn:name":"Longdong",
    "gn:population":0,
    "gn:timezone":"Asia/Shanghai",
    "iso:country":"CN",
    "name:ceb_x_preferred":[
        "Longdong"
    ],
    "name:swe_x_preferred":[
        "Longdong"
    ],
    "name:zho_x_preferred":[
        "\u9f99\u4e1c"
    ],
    "wof:name":"Longdong",
    "wof:placetype":"locality"
},
  "geometry": {"coordinates":[108.95399999999999,24.0013],"type":"Point"}
}