{
  "type": "Feature",
  "properties": {
    "gn:admin1_code":"19.0",
    "gn:asciiname":"Daxinglong Gangzi",
    "gn:country_code":"CN",
    "gn:dem":13,
    "gn:feature_class":"P",
    "gn:feature_code":"PPL",
    "gn:name":"Daxinglong Gangzi",
    "gn:population":0,
    "gn:timezone":"Asia/Shanghai",
    "iso:country":"CN",
    "name:zho_x_preferred":[
        "\u5927\u5174\u9686\u5c97\u5b50"
    ],
    "wof:name":"Daxinglong Gangzi",
    "wof:placetype":"locality"
},
  "geometry": {"coordinates":[122.47799999999999,41.5289],"type":"Point"}
}