{
  "type": "Feature",
  "properties": {
    "gn:admin1_code":"12.0",
    "gn:asciiname":"Dingjiawan",
    "gn:country_code":"CN",
    "gn:dem":83,
    "gn:feature_class":"P",
    "gn:feature_code":"PPL",
    "gn:name":"Dingjiawan",
    "gn:population":0,
    "gn:timezone":"Asia/Shanghai",
    "iso:country":"CN",
    "name:zho_x_preferred":[
        "\u4e01\u5bb6\u6e7e"
    ],
    "wof:name":"Dingjiawan",
    "wof:placetype":"locality"
},
  "geometry": {"coordinates":[113.80493,31.57588],"type":"Point"}
}