{
  "type": "Feature",
  "properties": {
    "gn:admin1_code":"13",
    "gn:asciiname":"Chakaitunge",
    "gn:country_code":"CN",
    "gn:dem":1644,
    "gn:feature_class":"P",
    "gn:feature_code":"PPL",
    "gn:name":"Chakaitunge",
    "gn:population":0,
    "gn:timezone":"Asia/Urumqi",
    "iso:country":"CN",
    "name:und_x_variant":[
        "\u67e5\u5f00\u5c6f\u683c"
    ],
    "wof:name":"Chakaitunge",
    "wof:placetype":"locality"
},
  "geometry": {"coordinates":[87.33259,42.38006],"type":"Point"}
}