{
  "type": "Feature",
  "properties": {
    "gn:admin1_code":"5.0",
    "gn:asciiname":"Yangxiangcun",
    "gn:country_code":"CN",
    "gn:dem":147,
    "gn:feature_class":"P",
    "gn:feature_code":"PPL",
    "gn:name":"Yangxiangcun",
    "gn:population":0,
    "gn:timezone":"Asia/Shanghai",
    "iso:country":"CN",
    "name:zho_x_preferred":[
        "\u6768\u4e61\u6751"
    ],
    "wof:name":"Yangxiangcun",
    "wof:placetype":"locality"
},
  "geometry": {"coordinates":[126.40325,45.18185],"type":"Point"}
}