{
  "type": "Feature",
  "properties": {
    "gn:admin1_code":"16.0",
    "gn:asciiname":"Ganlong",
    "gn:country_code":"CN",
    "gn:dem":95,
    "gn:feature_class":"P",
    "gn:feature_code":"PPL",
    "gn:name":"Ganlong",
    "gn:population":0,
    "gn:timezone":"Asia/Shanghai",
    "iso:country":"CN",
    "name:zho_x_preferred":[
        "\u611f\u9f99"
    ],
    "wof:name":"Ganlong",
    "wof:placetype":"locality"
},
  "geometry": {"coordinates":[108.898,23.4804],"type":"Point"}
}