{
  "type": "Feature",
  "properties": {
    "gn:admin1_code":"3.0",
    "gn:asciiname":"Wufangling",
    "gn:country_code":"CN",
    "gn:dem":51,
    "gn:feature_class":"P",
    "gn:feature_code":"PPL",
    "gn:name":"Wufangling",
    "gn:population":0,
    "gn:timezone":"Asia/Shanghai",
    "iso:country":"CN",
    "name:und_x_variant":[
        "\u4e94\u623f\u5cad"
    ],
    "wof:name":"Wufangling",
    "wof:placetype":"locality"
},
  "geometry": {"coordinates":[115.82894,29.50733],"type":"Point"}
}