{
  "type": "Feature",
  "properties": {
    "gn:admin1_code":"10",
    "gn:asciiname":"Qidaohe",
    "gn:country_code":"CN",
    "gn:dem":634,
    "gn:feature_class":"P",
    "gn:feature_code":"PPL",
    "gn:name":"Qidaohe",
    "gn:population":0,
    "gn:timezone":"Asia/Shanghai",
    "iso:country":"CN",
    "name:zho_x_preferred":[
        "\u4e03\u9053\u6cb3"
    ],
    "wof:name":"Qidaohe",
    "wof:placetype":"locality"
},
  "geometry": {"coordinates":[116.72287,41.18976],"type":"Point"}
}