{
  "type": "Feature",
  "properties": {
    "gn:admin1_code":"02",
    "gn:asciiname":"Sandu",
    "gn:country_code":"CN",
    "gn:dem":38,
    "gn:feature_class":"P",
    "gn:feature_code":"PPL",
    "gn:name":"Sandu",
    "gn:population":0,
    "gn:timezone":"Asia/Shanghai",
    "iso:country":"CN",
    "name:ceb_x_preferred":[
        "Sandu"
    ],
    "name:deu_x_preferred":[
        "Sandu"
    ],
    "name:fra_x_preferred":[
        "Sandu"
    ],
    "name:ita_x_preferred":[
        "Sandu"
    ],
    "name:pol_x_preferred":[
        "Sandu"
    ],
    "name:por_x_preferred":[
        "Sandu"
    ],
    "name:ron_x_preferred":[
        "Sandu"
    ],
    "name:rus_x_preferred":[
        "\u0421\u0430\u043d\u0434\u0443"
    ],
    "name:swe_x_preferred":[
        "Sandu"
    ],
    "name:ukr_x_preferred":[
        "\u0421\u0430\u043d\u0434\u0443"
    ],
    "name:und_x_variant":[
        "San-tu",
        "San-tu-shih",
        "Sandu"
    ],
    "name:zho_x_preferred":[
        "\u4e09\u90fd"
    ],
    "wof:name":"Sandu",
    "wof:placetype":"locality"
},
  "geometry": {"coordinates":[120.17109000000001,29.75728],"type":"Point"}
}