{
  "type": "Feature",
  "properties": {
    "gn:admin1_code":"14.0",
    "gn:asciiname":"Yognagtang",
    "gn:country_code":"CN",
    "gn:dem":4572,
    "gn:feature_class":"P",
    "gn:feature_code":"PPL",
    "gn:name":"Yognagtang",
    "gn:population":0,
    "gn:timezone":"Asia/Urumqi",
    "iso:country":"CN",
    "name:bod_x_preferred":[
        "Yognagtang"
    ],
    "name:zho_x_preferred":[
        "Yongnatang"
    ],
    "name:zho_x_variant":[
        "\u6c38\u7eb3\u5858",
        "Yongna Gongshe",
        "\u6c38\u7eb3\u516c\u793e"
    ],
    "wof:name":"Yognagtang",
    "wof:placetype":"locality"
},
  "geometry": {"coordinates":[93.703,31.903],"type":"Point"}
}