{
  "type": "Feature",
  "properties": {
    "gn:admin1_code":"21.0",
    "gn:asciiname":"Houxia",
    "gn:country_code":"CN",
    "gn:dem":1898,
    "gn:feature_class":"P",
    "gn:feature_code":"PPL",
    "gn:name":"Houxia",
    "gn:population":0,
    "gn:timezone":"Asia/Shanghai",
    "iso:country":"CN",
    "name:zho_x_preferred":[
        "\u540e\u5ce1"
    ],
    "wof:name":"Houxia",
    "wof:placetype":"locality"
},
  "geometry": {"coordinates":[106.35299999999999,35.9044],"type":"Point"}
}