{
  "type": "Feature",
  "properties": {
    "gn:admin1_code":"19.0",
    "gn:asciiname":"Xibeiyingou",
    "gn:country_code":"CN",
    "gn:dem":75,
    "gn:feature_class":"P",
    "gn:feature_code":"PPL",
    "gn:name":"Xibeiyingou",
    "gn:population":0,
    "gn:timezone":"Asia/Shanghai",
    "iso:country":"CN",
    "name:zho_x_preferred":[
        "\u897f\u80cc\u9634\u6c9f"
    ],
    "wof:name":"Xibeiyingou",
    "wof:placetype":"locality"
},
  "geometry": {"coordinates":[120.31100000000001,40.5044],"type":"Point"}
}