{
  "type": "Feature",
  "properties": {
    "gn:admin1_code":"11.0",
    "gn:asciiname":"Xiaozhushan",
    "gn:country_code":"CN",
    "gn:dem":378,
    "gn:feature_class":"P",
    "gn:feature_code":"PPL",
    "gn:name":"Xiaozhushan",
    "gn:population":0,
    "gn:timezone":"Asia/Shanghai",
    "iso:country":"CN",
    "name:zho_x_preferred":[
        "\u5c0f\u7af9\u5c71"
    ],
    "wof:name":"Xiaozhushan",
    "wof:placetype":"locality"
},
  "geometry": {"coordinates":[109.77466,28.0759],"type":"Point"}
}