{
  "type": "Feature",
  "properties": {
    "gn:admin1_code":"1.0",
    "gn:asciiname":"Honghecun",
    "gn:country_code":"CN",
    "gn:dem":221,
    "gn:feature_class":"P",
    "gn:feature_code":"PPL",
    "gn:name":"Honghecun",
    "gn:population":0,
    "gn:timezone":"Asia/Shanghai",
    "iso:country":"CN",
    "name:zho_x_preferred":[
        "\u6d2a\u6cb3\u6751"
    ],
    "wof:name":"Honghecun",
    "wof:placetype":"locality"
},
  "geometry": {"coordinates":[115.97499000000001,30.39408],"type":"Point"}
}