{
  "type": "Feature",
  "properties": {
    "gn:admin1_code":"32.0",
    "gn:asciiname":"Meiziping",
    "gn:country_code":"CN",
    "gn:dem":1038,
    "gn:feature_class":"P",
    "gn:feature_code":"PPL",
    "gn:name":"Meiziping",
    "gn:population":0,
    "gn:timezone":"Asia/Shanghai",
    "iso:country":"CN",
    "name:zho_x_preferred":[
        "\u7164\u5b50\u576a"
    ],
    "wof:name":"Meiziping",
    "wof:placetype":"locality"
},
  "geometry": {"coordinates":[103.88106000000001,31.14283],"type":"Point"}
}