{
  "type": "Feature",
  "properties": {
    "gn:admin1_code":"2.0",
    "gn:asciiname":"Beiyangdai",
    "gn:country_code":"CN",
    "gn:dem":4,
    "gn:feature_class":"P",
    "gn:feature_code":"PPL",
    "gn:name":"Beiyangdai",
    "gn:population":0,
    "gn:timezone":"Asia/Shanghai",
    "iso:country":"CN",
    "name:und_x_variant":[
        "\u5317\u6d0b\u57ed"
    ],
    "wof:name":"Beiyangdai",
    "wof:placetype":"locality"
},
  "geometry": {"coordinates":[120.73865000000001,30.91801],"type":"Point"}
}