{
  "type": "Feature",
  "properties": {
    "gn:admin1_code":"29.0",
    "gn:asciiname":"Haozhuqing",
    "gn:country_code":"CN",
    "gn:dem":2474,
    "gn:feature_class":"P",
    "gn:feature_code":"PPL",
    "gn:name":"Haozhuqing",
    "gn:population":0,
    "gn:timezone":"Asia/Shanghai",
    "iso:country":"CN",
    "name:zho_x_preferred":[
        "\u8c6a\u732a\u7b90"
    ],
    "wof:name":"Haozhuqing",
    "wof:placetype":"locality"
},
  "geometry": {"coordinates":[99.2705,27.17],"type":"Point"}
}