{
  "type": "Feature",
  "properties": {
    "gn:admin1_code":"16",
    "gn:asciiname":"Pingle",
    "gn:country_code":"CN",
    "gn:dem":680,
    "gn:feature_class":"P",
    "gn:feature_code":"PPL",
    "gn:name":"Pingle",
    "gn:population":0,
    "gn:timezone":"Asia/Shanghai",
    "iso:country":"CN",
    "name:ceb_x_preferred":[
        "Pingle"
    ],
    "name:deu_x_preferred":[
        "Pingle"
    ],
    "wof:name":"Pingle",
    "wof:placetype":"locality"
},
  "geometry": {"coordinates":[106.95,24.48333],"type":"Point"}
}