{
  "type": "Feature",
  "properties": {
    "gn:admin1_code":"24.0",
    "gn:asciiname":"Zhangyagou",
    "gn:country_code":"CN",
    "gn:dem":1330,
    "gn:feature_class":"P",
    "gn:feature_code":"PPL",
    "gn:name":"Zhangyagou",
    "gn:population":0,
    "gn:timezone":"Asia/Shanghai",
    "iso:country":"CN",
    "name:zho_x_preferred":[
        "\u5f20\u5d16\u6c9f"
    ],
    "wof:name":"Zhangyagou",
    "wof:placetype":"locality"
},
  "geometry": {"coordinates":[112.53395,39.55164],"type":"Point"}
}