{
  "type": "Feature",
  "properties": {
    "gn:admin1_code":"18",
    "gn:asciiname":"Yu'ao",
    "gn:country_code":"CN",
    "gn:dem":1275,
    "gn:feature_class":"P",
    "gn:feature_code":"PPL",
    "gn:name":"Yu\u2019ao",
    "gn:population":0,
    "gn:timezone":"Asia/Shanghai",
    "iso:country":"CN",
    "name:und_x_variant":[
        "Yu\u2019ao"
    ],
    "name:zho_x_preferred":[
        "\u9c7c\u51f9"
    ],
    "wof:name":"Yu'ao",
    "wof:placetype":"locality"
},
  "geometry": {"coordinates":[105.982,25.9008],"type":"Point"}
}