{
  "type": "Feature",
  "properties": {
    "gn:admin1_code":"12.0",
    "gn:asciiname":"Aoxia",
    "gn:country_code":"CN",
    "gn:dem":171,
    "gn:feature_class":"P",
    "gn:feature_code":"PPL",
    "gn:name":"Aoxia",
    "gn:population":0,
    "gn:timezone":"Asia/Shanghai",
    "iso:country":"CN",
    "name:zho_x_preferred":[
        "Aoxia"
    ],
    "name:zho_x_variant":[
        "\u5773\u4e0b"
    ],
    "wof:name":"Aoxia",
    "wof:placetype":"locality"
},
  "geometry": {"coordinates":[114.65656,29.46912],"type":"Point"}
}