{
  "type": "Feature",
  "properties": {
    "gn:admin1_code":"16.0",
    "gn:asciiname":"Rulang",
    "gn:country_code":"CN",
    "gn:dem":262,
    "gn:feature_class":"P",
    "gn:feature_code":"PPL",
    "gn:name":"Rulang",
    "gn:population":0,
    "gn:timezone":"Asia/Shanghai",
    "iso:country":"CN",
    "name:zho_x_preferred":[
        "\u5112\u90ce"
    ],
    "wof:name":"Rulang",
    "wof:placetype":"locality"
},
  "geometry": {"coordinates":[108.84399999999999,24.8954],"type":"Point"}
}