{
  "type": "Feature",
  "properties": {
    "gn:admin1_code":"20.0",
    "gn:asciiname":"Yuchangwandian",
    "gn:country_code":"CN",
    "gn:dem":356,
    "gn:feature_class":"P",
    "gn:feature_code":"PPL",
    "gn:name":"Yuchangwandian",
    "gn:population":0,
    "gn:timezone":"Asia/Shanghai",
    "iso:country":"CN",
    "name:zho_x_preferred":[
        "\u4e8e\u957f\u4e07\u70b9"
    ],
    "wof:name":"Yuchangwandian",
    "wof:placetype":"locality"
},
  "geometry": {"coordinates":[123.04667999999999,48.18446],"type":"Point"}
}