{
  "type": "Feature",
  "properties": {
    "gn:admin1_code":"4.0",
    "gn:asciiname":"Xingang",
    "gn:country_code":"CN",
    "gn:dem":-2,
    "gn:feature_class":"P",
    "gn:feature_code":"PPL",
    "gn:name":"Xingang",
    "gn:population":0,
    "gn:timezone":"Asia/Shanghai",
    "iso:country":"CN",
    "name:zho_x_preferred":[
        "Xingang"
    ],
    "name:zho_x_variant":[
        "\u65b0\u5188"
    ],
    "wof:name":"Xingang",
    "wof:placetype":"locality"
},
  "geometry": {"coordinates":[119.97702,33.58103],"type":"Point"}
}