{
  "type": "Feature",
  "properties": {
    "gn:admin1_code":"32.0",
    "gn:asciiname":"Ganyuba",
    "gn:country_code":"CN",
    "gn:dem":949,
    "gn:feature_class":"P",
    "gn:feature_code":"PPL",
    "gn:name":"Ganyuba",
    "gn:population":0,
    "gn:timezone":"Asia/Shanghai",
    "iso:country":"CN",
    "name:zho_x_preferred":[
        "\u5e72\u9c7c\u575d"
    ],
    "wof:name":"Ganyuba",
    "wof:placetype":"locality"
},
  "geometry": {"coordinates":[104.24669,31.98716],"type":"Point"}
}