{
  "type": "Feature",
  "properties": {
    "gn:admin1_code":"32.0",
    "gn:asciiname":"Tuoluo",
    "gn:country_code":"CN",
    "gn:dem":3002,
    "gn:feature_class":"P",
    "gn:feature_code":"PPL",
    "gn:name":"Tuoluo",
    "gn:population":0,
    "gn:timezone":"Asia/Shanghai",
    "iso:country":"CN",
    "name:zho_x_preferred":[
        "\u62d6\u843d"
    ],
    "wof:name":"Tuoluo",
    "wof:placetype":"locality"
},
  "geometry": {"coordinates":[100.93300000000001,27.7826],"type":"Point"}
}