{
  "type": "Feature",
  "properties": {
    "gn:admin1_code":"8.0",
    "gn:asciiname":"Sishuntang",
    "gn:country_code":"CN",
    "gn:dem":266,
    "gn:feature_class":"P",
    "gn:feature_code":"PPL",
    "gn:name":"Sishuntang",
    "gn:population":0,
    "gn:timezone":"Asia/Shanghai",
    "iso:country":"CN",
    "name:zho_x_preferred":[
        "\u56db\u987a\u5802"
    ],
    "wof:name":"Sishuntang",
    "wof:placetype":"locality"
},
  "geometry": {"coordinates":[128.53888999999998,44.92996],"type":"Point"}
}