{
  "type": "Feature",
  "properties": {
    "gn:admin1_code":"30",
    "gn:asciiname":"Chipotang",
    "gn:country_code":"CN",
    "gn:dem":60,
    "gn:feature_class":"P",
    "gn:feature_code":"PPL",
    "gn:name":"Chipotang",
    "gn:population":0,
    "gn:timezone":"Asia/Urumqi",
    "iso:country":"CN",
    "name:zho_x_preferred":[
        "\u8d64\u5761\u5858"
    ],
    "wof:name":"Chipotang",
    "wof:placetype":"locality"
},
  "geometry": {"coordinates":[109.96881,20.74298],"type":"Point"}
}