{
  "type": "Feature",
  "properties": {
    "gn:admin1_code":"15.0",
    "gn:asciiname":"Mutashan",
    "gn:country_code":"CN",
    "gn:dem":1414,
    "gn:feature_class":"P",
    "gn:feature_code":"PPL",
    "gn:name":"Mutashan",
    "gn:population":0,
    "gn:timezone":"Asia/Shanghai",
    "iso:country":"CN",
    "name:und_x_variant":[
        "\u6155\u584c\u5c71"
    ],
    "wof:name":"Mutashan",
    "wof:placetype":"locality"
},
  "geometry": {"coordinates":[107.28215,35.99712],"type":"Point"}
}