{
  "type": "Feature",
  "properties": {
    "gn:admin1_code":"23.0",
    "gn:asciiname":"Sanxing",
    "gn:country_code":"CN",
    "gn:dem":3,
    "gn:feature_class":"P",
    "gn:feature_code":"PPL",
    "gn:name":"Sanxing",
    "gn:population":0,
    "gn:timezone":"Asia/Shanghai",
    "iso:country":"CN",
    "name:zho_x_preferred":[
        "Sanxing"
    ],
    "name:zho_x_variant":[
        "\u4e09\u661f"
    ],
    "wof:name":"Sanxing",
    "wof:placetype":"locality"
},
  "geometry": {"coordinates":[121.34593,31.31324],"type":"Point"}
}