{
  "type": "Feature",
  "properties": {
    "gn:admin1_code":"16.0",
    "gn:asciiname":"Zhoufu",
    "gn:country_code":"CN",
    "gn:dem":51,
    "gn:feature_class":"P",
    "gn:feature_code":"PPL",
    "gn:name":"Zhoufu",
    "gn:population":0,
    "gn:timezone":"Asia/Shanghai",
    "iso:country":"CN",
    "name:zho_x_preferred":[
        "\u5468\u798f"
    ],
    "wof:name":"Zhoufu",
    "wof:placetype":"locality"
},
  "geometry": {"coordinates":[110.423,23.3895],"type":"Point"}
}