{
  "type": "Feature",
  "properties": {
    "gn:admin1_code":"15.0",
    "gn:asciiname":"Jiangjunya",
    "gn:country_code":"CN",
    "gn:dem":1782,
    "gn:feature_class":"P",
    "gn:feature_code":"PPL",
    "gn:name":"Jiangjunya",
    "gn:population":0,
    "gn:timezone":"Asia/Shanghai",
    "iso:country":"CN",
    "name:zho_x_preferred":[
        "\u5c06\u519b\u5d16"
    ],
    "wof:name":"Jiangjunya",
    "wof:placetype":"locality"
},
  "geometry": {"coordinates":[106.482,35.4549],"type":"Point"}
}