{
  "type": "Feature",
  "properties": {
    "gn:admin1_code":"7",
    "gn:asciiname":"Jingbaoshan",
    "gn:country_code":"CN",
    "gn:dem":40,
    "gn:feature_class":"P",
    "gn:feature_code":"PPLA4",
    "gn:name":"Jingbaoshan",
    "gn:population":0,
    "gn:timezone":"Asia/Shanghai",
    "iso:country":"CN",
    "name:und_x_variant":[
        "Jianshe",
        "Jingbaoshan"
    ],
    "name:zho_x_preferred":[
        "\u8fdb\u5b9d\u5c71"
    ],
    "wof:name":"Jingbaoshan",
    "wof:placetype":"locality"
},
  "geometry": {"coordinates":[117.09643,23.80853],"type":"Point"}
}