{
  "type": "Feature",
  "properties": {
    "gn:admin1_code":"1.0",
    "gn:asciiname":"Shahaogao",
    "gn:country_code":"CN",
    "gn:dem":11,
    "gn:feature_class":"P",
    "gn:feature_code":"PPL",
    "gn:name":"Shahaogao",
    "gn:population":0,
    "gn:timezone":"Asia/Shanghai",
    "iso:country":"CN",
    "name:zho_x_preferred":[
        "\u6c99\u90dd\u9ad8"
    ],
    "wof:name":"Shahaogao",
    "wof:placetype":"locality"
},
  "geometry": {"coordinates":[118.31619999999999,31.79025],"type":"Point"}
}