{
  "type": "Feature",
  "properties": {
    "gn:admin1_code":"5.0",
    "gn:asciiname":"Maojiatun",
    "gn:country_code":"CN",
    "gn:dem":194,
    "gn:feature_class":"P",
    "gn:feature_code":"PPL",
    "gn:name":"Maojiatun",
    "gn:population":0,
    "gn:timezone":"Asia/Shanghai",
    "iso:country":"CN",
    "name:zho_x_preferred":[
        "\u6bdb\u5bb6\u5c6f"
    ],
    "wof:name":"Maojiatun",
    "wof:placetype":"locality"
},
  "geometry": {"coordinates":[124.4109,44.45404],"type":"Point"}
}