{
  "type": "Feature",
  "properties": {
    "gn:admin1_code":"15.0",
    "gn:asciiname":"Xiaoyuan",
    "gn:country_code":"CN",
    "gn:dem":2026,
    "gn:feature_class":"P",
    "gn:feature_code":"PPL",
    "gn:name":"Xiaoyuan",
    "gn:population":0,
    "gn:timezone":"Asia/Shanghai",
    "iso:country":"CN",
    "name:zho_x_preferred":[
        "\u5c0f\u586c"
    ],
    "wof:name":"Xiaoyuan",
    "wof:placetype":"locality"
},
  "geometry": {"coordinates":[104.72499999999999,36.099],"type":"Point"}
}