{
  "type": "Feature",
  "properties": {
    "gn:admin1_code":"30.0",
    "gn:asciiname":"Jiaolindong",
    "gn:country_code":"CN",
    "gn:dem":408,
    "gn:feature_class":"P",
    "gn:feature_code":"PPL",
    "gn:name":"Jiaolindong",
    "gn:population":0,
    "gn:timezone":"Asia/Shanghai",
    "iso:country":"CN",
    "name:zho_x_preferred":[
        "\u8549\u6797\u6d1e"
    ],
    "wof:name":"Jiaolindong",
    "wof:placetype":"locality"
},
  "geometry": {"coordinates":[112.79917,24.21167],"type":"Point"}
}