{
  "type": "Feature",
  "properties": {
    "gn:admin1_code":"30",
    "gn:asciiname":"Rizhong",
    "gn:country_code":"CN",
    "gn:dem":28,
    "gn:feature_class":"P",
    "gn:feature_code":"PPL",
    "gn:name":"Rizhong",
    "gn:population":0,
    "gn:timezone":"Asia/Shanghai",
    "iso:country":"CN",
    "name:und_x_variant":[
        "Pingdong",
        "Rizhongxu",
        "Rizhong"
    ],
    "name:zho_x_preferred":[
        "\u65e5\u4e2d"
    ],
    "wof:name":"Rizhong",
    "wof:placetype":"locality"
},
  "geometry": {"coordinates":[115.47853000000001,23.1037],"type":"Point"}
}