{
  "type": "Feature",
  "properties": {
    "gn:admin1_code":"24.0",
    "gn:asciiname":"Beiyadi",
    "gn:country_code":"CN",
    "gn:dem":918,
    "gn:feature_class":"P",
    "gn:feature_code":"PPL",
    "gn:name":"Beiyadi",
    "gn:population":0,
    "gn:timezone":"Asia/Shanghai",
    "iso:country":"CN",
    "name:zho_x_preferred":[
        "\u5317\u5d16\u5e95"
    ],
    "wof:name":"Beiyadi",
    "wof:placetype":"locality"
},
  "geometry": {"coordinates":[112.26676999999999,36.31274000000001],"type":"Point"}
}