{
  "type": "Feature",
  "properties": {
    "gn:admin1_code":"1.0",
    "gn:asciiname":"Zheng'ancun",
    "gn:country_code":"CN",
    "gn:dem":46,
    "gn:feature_class":"P",
    "gn:feature_code":"PPL",
    "gn:name":"Zheng\u2019ancun",
    "gn:population":0,
    "gn:timezone":"Asia/Shanghai",
    "iso:country":"CN",
    "name:und_x_variant":[
        "Zheng\u2019ancun"
    ],
    "name:zho_x_preferred":[
        "\u6b63\u5eb5\u6751"
    ],
    "wof:name":"Zheng'ancun",
    "wof:placetype":"locality"
},
  "geometry": {"coordinates":[116.89973000000001,31.38999],"type":"Point"}
}