{
  "type": "Feature",
  "properties": {
    "gn:admin1_code":"29.0",
    "gn:asciiname":"Zuoshe",
    "gn:country_code":"CN",
    "gn:dem":1887,
    "gn:feature_class":"P",
    "gn:feature_code":"PPL",
    "gn:name":"Zuoshe",
    "gn:population":0,
    "gn:timezone":"Asia/Shanghai",
    "iso:country":"CN",
    "name:zho_x_preferred":[
        "\u5de6\u820d"
    ],
    "wof:name":"Zuoshe",
    "wof:placetype":"locality"
},
  "geometry": {"coordinates":[103.937,24.6559],"type":"Point"}
}