{
  "type": "Feature",
  "properties": {
    "gn:admin1_code":"30.0",
    "gn:asciiname":"Shuangliancun",
    "gn:country_code":"CN",
    "gn:dem":173,
    "gn:feature_class":"P",
    "gn:feature_code":"PPL",
    "gn:name":"Shuangliancun",
    "gn:population":0,
    "gn:timezone":"Asia/Shanghai",
    "iso:country":"CN",
    "name:zho_x_preferred":[
        "\u53cc\u8054\u6751"
    ],
    "wof:name":"Shuangliancun",
    "wof:placetype":"locality"
},
  "geometry": {"coordinates":[115.65319,23.91047],"type":"Point"}
}