{
  "type": "Feature",
  "properties": {
    "gn:admin1_code":"18.0",
    "gn:asciiname":"Yangketian",
    "gn:country_code":"CN",
    "gn:dem":1073,
    "gn:feature_class":"P",
    "gn:feature_code":"PPL",
    "gn:name":"Yangketian",
    "gn:population":0,
    "gn:timezone":"Asia/Shanghai",
    "iso:country":"CN",
    "name:zho_x_preferred":[
        "\u517b\u5ba2\u7530"
    ],
    "wof:name":"Yangketian",
    "wof:placetype":"locality"
},
  "geometry": {"coordinates":[107.239,26.7107],"type":"Point"}
}