{
  "type": "Feature",
  "properties": {
    "gn:admin1_code":"6.0",
    "gn:asciiname":"Xing'ergousi",
    "gn:country_code":"CN",
    "gn:dem":2537,
    "gn:feature_class":"P",
    "gn:feature_code":"PPL",
    "gn:name":"Xing\u2019ergousi",
    "gn:population":0,
    "gn:timezone":"Asia/Shanghai",
    "iso:country":"CN",
    "name:und_x_variant":[
        "Xing\u2019ergousi",
        "\u674f\u513f\u6c9f\u5bfa"
    ],
    "wof:name":"Xing'ergousi",
    "wof:placetype":"locality"
},
  "geometry": {"coordinates":[102.68794,35.92994],"type":"Point"}
}