{
  "type": "Feature",
  "properties": {
    "gn:admin1_code":"2.0",
    "gn:asciiname":"Xiadongxi",
    "gn:country_code":"CN",
    "gn:dem":155,
    "gn:feature_class":"P",
    "gn:feature_code":"PPL",
    "gn:name":"Xiadongxi",
    "gn:population":0,
    "gn:timezone":"Asia/Shanghai",
    "iso:country":"CN",
    "name:und_x_variant":[
        "\u4e0b\u4e1c\u6eaa"
    ],
    "wof:name":"Xiadongxi",
    "wof:placetype":"locality"
},
  "geometry": {"coordinates":[119.32023,30.57594000000001],"type":"Point"}
}