{
  "type": "Feature",
  "properties": {
    "gn:admin1_code":"8.0",
    "gn:asciiname":"Zhangfengge",
    "gn:country_code":"CN",
    "gn:dem":151,
    "gn:feature_class":"P",
    "gn:feature_code":"PPL",
    "gn:name":"Zhangfengge",
    "gn:population":0,
    "gn:timezone":"Asia/Shanghai",
    "iso:country":"CN",
    "name:zho_x_preferred":[
        "\u5f20\u98ce\u9601"
    ],
    "wof:name":"Zhangfengge",
    "wof:placetype":"locality"
},
  "geometry": {"coordinates":[124.79897,47.13702],"type":"Point"}
}