{
  "type": "Feature",
  "properties": {
    "gn:admin1_code":"16",
    "gn:asciiname":"Fuyang",
    "gn:country_code":"CN",
    "gn:dem":222,
    "gn:feature_class":"P",
    "gn:feature_code":"PPLA3",
    "gn:name":"Fuyang",
    "gn:population":0,
    "gn:timezone":"Asia/Shanghai",
    "iso:country":"CN",
    "name:und_x_variant":[
        "Fuchuan",
        "Fuchwan",
        "Fu-yang-chen",
        "Fuchwan-hsien",
        "Fuyang"
    ],
    "name:zho_x_preferred":[
        "Chiu-fu-ch\u2019uan"
    ],
    "name:zho_x_variant":[
        "Fu-ch\u2019uan-hsien"
    ],
    "wof:name":"Fuyang",
    "wof:placetype":"locality"
},
  "geometry": {"coordinates":[111.25802,24.83441],"type":"Point"}
}