{
  "type": "Feature",
  "properties": {
    "gn:admin1_code":"16",
    "gn:asciiname":"Fuyang",
    "gn:country_code":"CN",
    "gn:dem":222,
    "gn:feature_class":"P",
    "gn:feature_code":"PPLA3",
    "gn:name":"Fuyang",
    "gn:population":0,
    "gn:timezone":"Asia/Shanghai",
    "iso:country":"CN",
    "name:afr_x_preferred":[
        "Fuyang"
    ],
    "name:ara_x_preferred":[
        "\u0641\u0648\u064a\u0627\u0646\u063a"
    ],
    "name:cdo_x_preferred":[
        "P\u00e2iu-i\u00f2ng"
    ],
    "name:ceb_x_preferred":[
        "Fuyang Shi"
    ],
    "name:ces_x_preferred":[
        "Fu-jang"
    ],
    "name:cym_x_preferred":[
        "Fuyang"
    ],
    "name:dan_x_preferred":[
        "Fuyang"
    ],
    "name:deu_x_preferred":[
        "Fuyang"
    ],
    "name:eus_x_preferred":[
        "Fuyang"
    ],
    "name:fas_x_preferred":[
        "\u0641\u0648\u06cc\u0627\u0646\u06af"
    ],
    "name:fin_x_preferred":[
        "Fuyang"
    ],
    "name:fra_x_preferred":[
        "Fuyang"
    ],
    "name:hak_x_preferred":[
        "Fu-y\u00f2ng-s\u1e73"
    ],
    "name:hye_x_preferred":[
        "\u0556\u0578\u0582\u0575\u0561\u0576"
    ],
    "name:ita_x_preferred":[
        "Fuyang"
    ],
    "name:jpn_x_preferred":[
        "\u961c\u967d\u5e02"
    ],
    "name:kik_x_preferred":[
        "Fuyang"
    ],
    "name:kor_x_preferred":[
        "\ud478\uc591\uc2dc"
    ],
    "name:mlg_x_preferred":[
        "Fuyang"
    ],
    "name:nld_x_preferred":[
        "Fuyang"
    ],
    "name:nno_x_preferred":[
        "Fuyang"
    ],
    "name:nor_x_preferred":[
        "Fuyang"
    ],
    "name:pam_x_preferred":[
        "Fuyang"
    ],
    "name:pnb_x_preferred":[
        "\u0641\u0648\u06cc\u0627\u0646\u06af"
    ],
    "name:pol_x_preferred":[
        "Fuyang"
    ],
    "name:rus_x_preferred":[
        "\u0424\u0443\u044f\u043d"
    ],
    "name:spa_x_preferred":[
        "Fuyang"
    ],
    "name:swe_x_preferred":[
        "Fuyang"
    ],
    "name:tgl_x_preferred":[
        "Fuyang"
    ],
    "name:tur_x_preferred":[
        "Fuyang"
    ],
    "name:und_x_variant":[
        "Fuchuan",
        "Fuchwan",
        "Fu-yang-chen",
        "Fuchwan-hsien"
    ],
    "name:urd_x_preferred":[
        "\u0641\u0648\u06cc\u0627\u0646\u06af"
    ],
    "name:vie_x_preferred":[
        "Ph\u1ee5 D\u01b0\u01a1ng"
    ],
    "name:war_x_preferred":[
        "Fuyang"
    ],
    "name:wuu_x_preferred":[
        "\u961c\u9633\u5e02"
    ],
    "name:zho_x_preferred":[
        "Chiu-fu-ch\u2019uan"
    ],
    "name:zho_x_variant":[
        "Fu-ch\u2019uan-hsien",
        "\u961c\u9633\u5e02"
    ],
    "wof:name":"Fuyang",
    "wof:placetype":"locality"
},
  "geometry": {"coordinates":[111.25802,24.83441],"type":"Point"}
}