{
  "type": "Feature",
  "properties": {
    "gn:admin1_code":"10.0",
    "gn:asciiname":"Beilizikou",
    "gn:country_code":"CN",
    "gn:dem":13,
    "gn:feature_class":"P",
    "gn:feature_code":"PPL",
    "gn:name":"Beilizikou",
    "gn:population":0,
    "gn:timezone":"Asia/Shanghai",
    "iso:country":"CN",
    "name:zho_x_preferred":[
        "\u5317\u674e\u5b50\u53e3"
    ],
    "wof:name":"Beilizikou",
    "wof:placetype":"locality"
},
  "geometry": {"coordinates":[116.035,38.4558],"type":"Point"}
}