{
  "type": "Feature",
  "properties": {
    "gn:admin1_code":"32.0",
    "gn:asciiname":"Tandunyan",
    "gn:country_code":"CN",
    "gn:dem":364,
    "gn:feature_class":"P",
    "gn:feature_code":"PPL",
    "gn:name":"Tandunyan",
    "gn:population":0,
    "gn:timezone":"Asia/Shanghai",
    "iso:country":"CN",
    "name:zho_x_preferred":[
        "\u575b\u58a9\u5ca9"
    ],
    "wof:name":"Tandunyan",
    "wof:placetype":"locality"
},
  "geometry": {"coordinates":[104.95999999999999,29.7118],"type":"Point"}
}