{
  "type": "Feature",
  "properties": {
    "gn:admin1_code":"9",
    "gn:asciiname":"Dayang",
    "gn:country_code":"CN",
    "gn:dem":52,
    "gn:feature_class":"P",
    "gn:feature_code":"PPL",
    "gn:name":"Dayang",
    "gn:population":0,
    "gn:timezone":"Asia/Shanghai",
    "iso:country":"CN",
    "name:ceb_x_preferred":[
        "Dayang"
    ],
    "name:msa_x_preferred":[
        "Dayang"
    ],
    "name:swe_x_preferred":[
        "Dayang"
    ],
    "name:zho_x_preferred":[
        "\u5927\u6768"
    ],
    "wof:name":"Dayang",
    "wof:placetype":"locality"
},
  "geometry": {"coordinates":[115.057,34.1442],"type":"Point"}
}