{
  "type": "Feature",
  "properties": {
    "gn:admin1_code":"8.0",
    "gn:asciiname":"Zhongxingcun",
    "gn:country_code":"CN",
    "gn:dem":198,
    "gn:feature_class":"P",
    "gn:feature_code":"PPL",
    "gn:name":"Zhongxingcun",
    "gn:population":0,
    "gn:timezone":"Asia/Shanghai",
    "iso:country":"CN",
    "name:zho_x_preferred":[
        "\u4e2d\u5174\u6751"
    ],
    "wof:name":"Zhongxingcun",
    "wof:placetype":"locality"
},
  "geometry": {"coordinates":[127.09766999999999,44.73909],"type":"Point"}
}