{
  "type": "Feature",
  "properties": {
    "gn:admin1_code":"2.0",
    "gn:asciiname":"Meihuabang",
    "gn:country_code":"CN",
    "gn:dem":6,
    "gn:feature_class":"P",
    "gn:feature_code":"PPL",
    "gn:name":"Meihuabang",
    "gn:population":0,
    "gn:timezone":"Asia/Shanghai",
    "iso:country":"CN",
    "name:und_x_variant":[
        "\u6885\u82b1\u6d5c"
    ],
    "wof:name":"Meihuabang",
    "wof:placetype":"locality"
},
  "geometry": {"coordinates":[120.93657,30.81584],"type":"Point"}
}