{
  "type": "Feature",
  "properties": {
    "gn:admin1_code":"5.0",
    "gn:asciiname":"Sihetun",
    "gn:country_code":"CN",
    "gn:dem":201,
    "gn:feature_class":"P",
    "gn:feature_code":"PPL",
    "gn:name":"Sihetun",
    "gn:population":0,
    "gn:timezone":"Asia/Shanghai",
    "iso:country":"CN",
    "name:zho_x_preferred":[
        "\u56db\u5408\u5c6f"
    ],
    "wof:name":"Sihetun",
    "wof:placetype":"locality"
},
  "geometry": {"coordinates":[124.07973,44.08782],"type":"Point"}
}