{
  "type": "Feature",
  "properties": {
    "gn:admin1_code":"9.0",
    "gn:asciiname":"Chenlaozhuang",
    "gn:country_code":"CN",
    "gn:dem":60,
    "gn:feature_class":"P",
    "gn:feature_code":"PPL",
    "gn:name":"Chenlaozhuang",
    "gn:population":0,
    "gn:timezone":"Asia/Shanghai",
    "iso:country":"CN",
    "name:zho_x_preferred":[
        "\u9648\u8001\u5e84"
    ],
    "wof:name":"Chenlaozhuang",
    "wof:placetype":"locality"
},
  "geometry": {"coordinates":[114.11360999999999,33.35247],"type":"Point"}
}