{
  "type": "Feature",
  "properties": {
    "gn:admin1_code":"30",
    "gn:asciiname":"Duheshi",
    "gn:country_code":"CN",
    "gn:dem":177,
    "gn:feature_class":"P",
    "gn:feature_code":"PPL",
    "gn:name":"Duheshi",
    "gn:population":0,
    "gn:timezone":"Asia/Shanghai",
    "iso:country":"CN",
    "name:zho_x_preferred":[
        "\u809a\u6cb3\u77f3"
    ],
    "wof:name":"Duheshi",
    "wof:placetype":"locality"
},
  "geometry": {"coordinates":[115.60124999999999,23.62842],"type":"Point"}
}