{
  "type": "Feature",
  "properties": {
    "gn:admin1_code":"32.0",
    "gn:asciiname":"Gazhi",
    "gn:country_code":"CN",
    "gn:dem":4172,
    "gn:feature_class":"P",
    "gn:feature_code":"PPL",
    "gn:name":"Gazhi",
    "gn:population":0,
    "gn:timezone":"Asia/Shanghai",
    "iso:country":"CN",
    "name:zho_x_preferred":[
        "\u560e\u829d"
    ],
    "wof:name":"Gazhi",
    "wof:placetype":"locality"
},
  "geometry": {"coordinates":[100.20214,27.97814],"type":"Point"}
}