{
  "type": "Feature",
  "properties": {
    "gn:admin1_code":"9.0",
    "gn:asciiname":"Qiaozhuang",
    "gn:country_code":"CN",
    "gn:dem":227,
    "gn:feature_class":"P",
    "gn:feature_code":"PPL",
    "gn:name":"Qiaozhuang",
    "gn:population":0,
    "gn:timezone":"Asia/Shanghai",
    "iso:country":"CN",
    "name:zho_x_preferred":[
        "\u4e54\u5e84"
    ],
    "wof:name":"Qiaozhuang",
    "wof:placetype":"locality"
},
  "geometry": {"coordinates":[112.71232000000001,33.84734],"type":"Point"}
}