{
  "type": "Feature",
  "properties": {
    "gn:admin1_code":"32.0",
    "gn:asciiname":"Xinqiaohe",
    "gn:country_code":"CN",
    "gn:dem":400,
    "gn:feature_class":"P",
    "gn:feature_code":"PPL",
    "gn:name":"Xinqiaohe",
    "gn:population":0,
    "gn:timezone":"Asia/Shanghai",
    "iso:country":"CN",
    "name:zho_x_preferred":[
        "\u65b0\u6865\u6cb3"
    ],
    "wof:name":"Xinqiaohe",
    "wof:placetype":"locality"
},
  "geometry": {"coordinates":[107.746,31.2451],"type":"Point"}
}