{
  "type": "Feature",
  "properties": {
    "gn:admin1_code":"4.0",
    "gn:asciiname":"Xijiaduo",
    "gn:country_code":"CN",
    "gn:dem":3,
    "gn:feature_class":"P",
    "gn:feature_code":"PPL",
    "gn:name":"Xijiaduo",
    "gn:population":0,
    "gn:timezone":"Asia/Shanghai",
    "iso:country":"CN",
    "name:zho_x_preferred":[
        "\u5e2d\u5bb6\u579b"
    ],
    "wof:name":"Xijiaduo",
    "wof:placetype":"locality"
},
  "geometry": {"coordinates":[119.67931000000002,32.74765],"type":"Point"}
}