{
  "type": "Feature",
  "properties": {
    "gn:admin1_code":"15.0",
    "gn:asciiname":"Pingtouchuanxiang",
    "gn:country_code":"CN",
    "gn:dem":1825,
    "gn:feature_class":"P",
    "gn:feature_code":"PPL",
    "gn:name":"Pingtouchuanxiang",
    "gn:population":0,
    "gn:timezone":"Asia/Shanghai",
    "iso:country":"CN",
    "name:und_x_variant":[
        "\u5e73\u5934\u5ddd\u4e61"
    ],
    "wof:name":"Pingtouchuanxiang",
    "wof:placetype":"locality"
},
  "geometry": {"coordinates":[105.32219000000001,35.87569000000001],"type":"Point"}
}