{
  "type": "Feature",
  "properties": {
    "gn:admin1_code":"32.0",
    "gn:asciiname":"Zhulingang",
    "gn:country_code":"CN",
    "gn:dem":925,
    "gn:feature_class":"P",
    "gn:feature_code":"PPL",
    "gn:name":"Zhulingang",
    "gn:population":0,
    "gn:timezone":"Asia/Shanghai",
    "iso:country":"CN",
    "name:zho_x_preferred":[
        "\u7af9\u6797\u5c97"
    ],
    "wof:name":"Zhulingang",
    "wof:placetype":"locality"
},
  "geometry": {"coordinates":[102.983,30.1853],"type":"Point"}
}