{
  "type": "Feature",
  "properties": {
    "gn:admin1_code":"12.0",
    "gn:asciiname":"Huanggaizui",
    "gn:country_code":"CN",
    "gn:dem":29,
    "gn:feature_class":"P",
    "gn:feature_code":"PPL",
    "gn:name":"Huanggaizui",
    "gn:population":0,
    "gn:timezone":"Asia/Shanghai",
    "iso:country":"CN",
    "name:zho_x_preferred":[
        "\u9ec4\u76d6\u5480"
    ],
    "wof:name":"Huanggaizui",
    "wof:placetype":"locality"
},
  "geometry": {"coordinates":[113.56831,29.76623],"type":"Point"}
}