{
  "type": "Feature",
  "properties": {
    "gn:admin1_code":"21.0",
    "gn:asciiname":"Qinjia Laozi",
    "gn:country_code":"CN",
    "gn:dem":1671,
    "gn:feature_class":"P",
    "gn:feature_code":"PPL",
    "gn:name":"Qinjia Laozi",
    "gn:population":0,
    "gn:timezone":"Asia/Shanghai",
    "iso:country":"CN",
    "name:zho_x_preferred":[
        "\u79e6\u5bb6\u8001\u5b50"
    ],
    "wof:name":"Qinjia Laozi",
    "wof:placetype":"locality"
},
  "geometry": {"coordinates":[106.593,37.0865],"type":"Point"}
}