{
  "type": "Feature",
  "properties": {
    "gn:admin1_code":"4.0",
    "gn:asciiname":"Zhongying",
    "gn:country_code":"CN",
    "gn:dem":4,
    "gn:feature_class":"P",
    "gn:feature_code":"PPL",
    "gn:name":"Zhongying",
    "gn:population":0,
    "gn:timezone":"Asia/Shanghai",
    "iso:country":"CN",
    "name:zho_x_preferred":[
        "Zhongying"
    ],
    "name:zho_x_variant":[
        "\u4e2d\u8425"
    ],
    "wof:name":"Zhongying",
    "wof:placetype":"locality"
},
  "geometry": {"coordinates":[119.55531000000001,33.92731],"type":"Point"}
}