{
  "type": "Feature",
  "properties": {
    "gn:admin1_code":"4.0",
    "gn:asciiname":"Wuxudai",
    "gn:country_code":"CN",
    "gn:dem":4,
    "gn:feature_class":"P",
    "gn:feature_code":"PPL",
    "gn:name":"Wuxudai",
    "gn:population":0,
    "gn:timezone":"Asia/Shanghai",
    "iso:country":"CN",
    "name:zho_x_preferred":[
        "\u4e94\u5729\u5788"
    ],
    "wof:name":"Wuxudai",
    "wof:placetype":"locality"
},
  "geometry": {"coordinates":[120.41688000000001,32.11755],"type":"Point"}
}