{
  "type": "Feature",
  "properties": {
    "gn:admin1_code":"32.0",
    "gn:asciiname":"Xinshi",
    "gn:country_code":"CN",
    "gn:dem":370,
    "gn:feature_class":"P",
    "gn:feature_code":"PPL",
    "gn:name":"Xinshi",
    "gn:population":0,
    "gn:timezone":"Asia/Shanghai",
    "iso:country":"CN",
    "name:und_x_variant":[
        "Man-i-ssu",
        "Hsin-shih-chen",
        "Man-li-t\u2019u-ssu",
        "Ping-i-ch\u2019ang",
        "Man-i-sze",
        "Pingyichang",
        "Man-i",
        "Xinshizhen",
        "Xinshi"
    ],
    "name:zho_x_preferred":[
        "\u65b0\u5e02"
    ],
    "wof:name":"Xinshi",
    "wof:placetype":"locality"
},
  "geometry": {"coordinates":[103.84236,28.67141],"type":"Point"}
}