{
  "type": "Feature",
  "properties": {
    "gn:admin1_code":"32.0",
    "gn:asciiname":"Xinshi",
    "gn:country_code":"CN",
    "gn:dem":370,
    "gn:feature_class":"P",
    "gn:feature_code":"PPL",
    "gn:name":"Xinshi",
    "gn:population":0,
    "gn:timezone":"Asia/Shanghai",
    "iso:country":"CN",
    "name:ceb_x_preferred":[
        "Xinshi"
    ],
    "name:deu_x_preferred":[
        "Xinshi"
    ],
    "name:eus_x_preferred":[
        "Xinshi"
    ],
    "name:fra_x_preferred":[
        "Xinshi"
    ],
    "name:mlg_x_preferred":[
        "Xinshi"
    ],
    "name:nor_x_preferred":[
        "Xinshi"
    ],
    "name:rus_x_preferred":[
        "\u0421\u0438\u043d\u044c\u0448\u0438"
    ],
    "name:swe_x_preferred":[
        "Xinshi"
    ],
    "name:und_x_variant":[
        "Man-i-ssu",
        "Hsin-shih-chen",
        "Man-li-t\u2019u-ssu",
        "Ping-i-ch\u2019ang",
        "Man-i-sze",
        "Pingyichang",
        "Man-i",
        "Xinshizhen",
        "Xinshi"
    ],
    "name:vie_x_preferred":[
        "T\u00e2n Th\u1ecb"
    ],
    "name:zho_x_preferred":[
        "\u65b0\u5e02"
    ],
    "wof:name":"Xinshi",
    "wof:placetype":"locality"
},
  "geometry": {"coordinates":[103.84236,28.67141],"type":"Point"}
}