{
  "type": "Feature",
  "properties": {
    "gn:admin1_code":"25",
    "gn:asciiname":"Quliuzhuang",
    "gn:country_code":"CN",
    "gn:dem":36,
    "gn:feature_class":"P",
    "gn:feature_code":"PPL",
    "gn:name":"Quliuzhuang",
    "gn:population":0,
    "gn:timezone":"Asia/Shanghai",
    "iso:country":"CN",
    "name:zho_x_preferred":[
        "\u5c48\u5218\u5e84"
    ],
    "wof:name":"Quliuzhuang",
    "wof:placetype":"locality"
},
  "geometry": {"coordinates":[116.515,35.3496],"type":"Point"}
}