{
  "type": "Feature",
  "properties": {
    "gn:admin1_code":"09",
    "gn:asciiname":"Lianzhuang",
    "gn:cc2":"CN",
    "gn:country_code":"CN",
    "gn:dem":232,
    "gn:feature_class":"P",
    "gn:feature_code":"PPL",
    "gn:name":"Lianzhuang",
    "gn:population":0,
    "gn:timezone":"Asia/Shanghai",
    "iso:country":"CN",
    "name:und_x_variant":[
        "Lien-chuang",
        "Lianzhuang"
    ],
    "wof:name":"Lianzhuang",
    "wof:placetype":"locality"
},
  "geometry": {"coordinates":[111.97750000000001,34.48583],"type":"Point"}
}