{
  "type": "Feature",
  "properties": {
    "gn:admin1_code":"29.0",
    "gn:asciiname":"Mucaowan",
    "gn:country_code":"CN",
    "gn:dem":1657,
    "gn:feature_class":"P",
    "gn:feature_code":"PPL",
    "gn:name":"Mucaowan",
    "gn:population":0,
    "gn:timezone":"Asia/Shanghai",
    "iso:country":"CN",
    "name:zho_x_preferred":[
        "\u6728\u8349\u6e7e"
    ],
    "wof:name":"Mucaowan",
    "wof:placetype":"locality"
},
  "geometry": {"coordinates":[103.831,28.0624],"type":"Point"}
}