{
  "type": "Feature",
  "properties": {
    "gn:admin1_code":"32.0",
    "gn:asciiname":"Shanda'ao",
    "gn:country_code":"CN",
    "gn:dem":341,
    "gn:feature_class":"P",
    "gn:feature_code":"PPL",
    "gn:name":"Shanda\u2019ao",
    "gn:population":0,
    "gn:timezone":"Asia/Shanghai",
    "iso:country":"CN",
    "name:zho_x_preferred":[
        "\u6749\u5927\u5787"
    ],
    "name:zho_x_variant":[
        "Shanda\u2019ao"
    ],
    "wof:name":"Shanda'ao",
    "wof:placetype":"locality"
},
  "geometry": {"coordinates":[104.61230999999999,29.02214],"type":"Point"}
}