{
  "type": "Feature",
  "properties": {
    "gn:admin1_code":"32.0",
    "gn:asciiname":"Maomaodong",
    "gn:country_code":"CN",
    "gn:dem":1235,
    "gn:feature_class":"P",
    "gn:feature_code":"PPL",
    "gn:name":"Maomaodong",
    "gn:population":0,
    "gn:timezone":"Asia/Shanghai",
    "iso:country":"CN",
    "name:zho_x_preferred":[
        "\u732b\u732b\u6d1e"
    ],
    "wof:name":"Maomaodong",
    "wof:placetype":"locality"
},
  "geometry": {"coordinates":[106.202,27.8503],"type":"Point"}
}