{
  "type": "Feature",
  "properties": {
    "gn:admin1_code":"12.0",
    "gn:asciiname":"Huanglianbao",
    "gn:country_code":"CN",
    "gn:dem":194,
    "gn:feature_class":"P",
    "gn:feature_code":"PPL",
    "gn:name":"Huanglianbao",
    "gn:population":0,
    "gn:timezone":"Asia/Shanghai",
    "iso:country":"CN",
    "name:zho_x_preferred":[
        "Huanglianbao"
    ],
    "name:zho_x_variant":[
        "\u9ec4\u8fde\u5305"
    ],
    "wof:name":"Huanglianbao",
    "wof:placetype":"locality"
},
  "geometry": {"coordinates":[114.66409,29.53403],"type":"Point"}
}