{
  "type": "Feature",
  "properties": {
    "gn:admin1_code":"16.0",
    "gn:asciiname":"Conghao",
    "gn:country_code":"CN",
    "gn:dem":158,
    "gn:feature_class":"P",
    "gn:feature_code":"PPL",
    "gn:name":"Conghao",
    "gn:population":0,
    "gn:timezone":"Asia/Shanghai",
    "iso:country":"CN",
    "name:zho_x_preferred":[
        "\u4ece\u597d"
    ],
    "wof:name":"Conghao",
    "wof:placetype":"locality"
},
  "geometry": {"coordinates":[107.55800000000001,22.2729],"type":"Point"}
}