{
  "type": "Feature",
  "properties": {
    "gn:admin1_code":"30",
    "gn:asciiname":"Jiulong",
    "gn:country_code":"CN",
    "gn:dem":96,
    "gn:feature_class":"P",
    "gn:feature_code":"PPLA4",
    "gn:name":"Jiulong",
    "gn:population":0,
    "gn:timezone":"Asia/Shanghai",
    "iso:country":"CN",
    "name:ceb_x_preferred":[
        "Jiulong"
    ],
    "name:deu_x_preferred":[
        "Jiulong"
    ],
    "name:fra_x_preferred":[
        "Jiulong"
    ],
    "name:nor_x_preferred":[
        "Jiulong"
    ],
    "name:swe_x_preferred":[
        "Jiulong"
    ],
    "name:und_x_variant":[
        "\u4e5d\u9f99",
        "Jiulong Zhen",
        "\u4e5d\u9f99\u9547"
    ],
    "name:vie_x_preferred":[
        "C\u1eedu Long"
    ],
    "name:zho_x_preferred":[
        "\u4e5d\u9f8d"
    ],
    "wof:name":"Jiulong",
    "wof:placetype":"locality"
},
  "geometry": {"coordinates":[112.90595999999999,24.13937],"type":"Point"}
}