{
  "type": "Feature",
  "properties": {
    "gn:admin1_code":"32.0",
    "gn:asciiname":"Hongbao",
    "gn:country_code":"CN",
    "gn:dem":750,
    "gn:feature_class":"P",
    "gn:feature_code":"PPL",
    "gn:name":"Hongbao",
    "gn:population":0,
    "gn:timezone":"Asia/Shanghai",
    "iso:country":"CN",
    "name:zho_x_preferred":[
        "\u7ea2\u5b9d"
    ],
    "wof:name":"Hongbao",
    "wof:placetype":"locality"
},
  "geometry": {"coordinates":[107.247,31.5191],"type":"Point"}
}