{
  "type": "Feature",
  "properties": {
    "gn:admin1_code":"33.0",
    "gn:asciiname":"Zhalupan",
    "gn:country_code":"CN",
    "gn:dem":1788,
    "gn:feature_class":"P",
    "gn:feature_code":"PPL",
    "gn:name":"Zhalupan",
    "gn:population":0,
    "gn:timezone":"Asia/Shanghai",
    "iso:country":"CN",
    "name:zho_x_preferred":[
        "\u624e\u9e7f\u76d8"
    ],
    "wof:name":"Zhalupan",
    "wof:placetype":"locality"
},
  "geometry": {"coordinates":[109.03163000000001,31.54792],"type":"Point"}
}