{
  "type": "Feature",
  "properties": {
    "gn:admin1_code":"11.0",
    "gn:asciiname":"Liangjiachong",
    "gn:country_code":"CN",
    "gn:dem":90,
    "gn:feature_class":"P",
    "gn:feature_code":"PPL",
    "gn:name":"Liangjiachong",
    "gn:population":0,
    "gn:timezone":"Asia/Shanghai",
    "iso:country":"CN",
    "name:zho_x_preferred":[
        "\u4e24\u5bb6\u51b2"
    ],
    "wof:name":"Liangjiachong",
    "wof:placetype":"locality"
},
  "geometry": {"coordinates":[111.37300999999999,28.68089],"type":"Point"}
}