{
  "type": "Feature",
  "properties": {
    "gn:admin1_code":"16.0",
    "gn:asciiname":"Bairen",
    "gn:country_code":"CN",
    "gn:dem":327,
    "gn:feature_class":"P",
    "gn:feature_code":"PPL",
    "gn:name":"Bairen",
    "gn:population":0,
    "gn:timezone":"Asia/Shanghai",
    "iso:country":"CN",
    "name:zho_x_preferred":[
        "\u767e\u4ec1"
    ],
    "wof:name":"Bairen",
    "wof:placetype":"locality"
},
  "geometry": {"coordinates":[106.86,23.9507],"type":"Point"}
}