{
  "type": "Feature",
  "properties": {
    "gn:admin1_code":"15.0",
    "gn:asciiname":"Yanleng",
    "gn:country_code":"CN",
    "gn:dem":1725,
    "gn:feature_class":"P",
    "gn:feature_code":"PPL",
    "gn:name":"Yanleng",
    "gn:population":0,
    "gn:timezone":"Asia/Shanghai",
    "iso:country":"CN",
    "name:und_x_variant":[
        "\u4e25\u5844"
    ],
    "name:zho_x_preferred":[
        "\u4e25\u5844"
    ],
    "wof:name":"Yanleng",
    "wof:placetype":"locality"
},
  "geometry": {"coordinates":[105.01443999999999,33.94667],"type":"Point"}
}