{
  "type": "Feature",
  "properties": {
    "gn:admin1_code":"16.0",
    "gn:asciiname":"Pingfei",
    "gn:country_code":"CN",
    "gn:dem":263,
    "gn:feature_class":"P",
    "gn:feature_code":"PPL",
    "gn:name":"Pingfei",
    "gn:population":0,
    "gn:timezone":"Asia/Shanghai",
    "iso:country":"CN",
    "name:zho_x_preferred":[
        "\u5e73\u80a5"
    ],
    "wof:name":"Pingfei",
    "wof:placetype":"locality"
},
  "geometry": {"coordinates":[107.57299999999999,21.8627],"type":"Point"}
}