{
  "type": "Feature",
  "properties": {
    "gn:admin1_code":"18",
    "gn:asciiname":"Lancaoba",
    "gn:country_code":"CN",
    "gn:dem":1322,
    "gn:feature_class":"P",
    "gn:feature_code":"PPL",
    "gn:name":"Lancaoba",
    "gn:population":0,
    "gn:timezone":"Asia/Shanghai",
    "iso:country":"CN",
    "name:zho_x_preferred":[
        "\u70c2\u8349\u575d"
    ],
    "wof:name":"Lancaoba",
    "wof:placetype":"locality"
},
  "geometry": {"coordinates":[106.48,27.9391],"type":"Point"}
}