{
  "type": "Feature",
  "properties": {
    "gn:admin1_code":"3.0",
    "gn:asciiname":"Panshan",
    "gn:country_code":"CN",
    "gn:dem":331,
    "gn:feature_class":"P",
    "gn:feature_code":"PPL",
    "gn:name":"Panshan",
    "gn:population":0,
    "gn:timezone":"Asia/Shanghai",
    "iso:country":"CN",
    "name:und_x_variant":[
        "\u76d8\u5c71"
    ],
    "wof:name":"Panshan",
    "wof:placetype":"locality"
},
  "geometry": {"coordinates":[115.22615999999999,28.83614],"type":"Point"}
}