{
  "type": "Feature",
  "properties": {
    "gn:admin1_code":"19.0",
    "gn:asciiname":"Miaodong",
    "gn:country_code":"CN",
    "gn:dem":431,
    "gn:feature_class":"P",
    "gn:feature_code":"PPLA4",
    "gn:name":"Miaodong",
    "gn:population":0,
    "gn:timezone":"Asia/Shanghai",
    "iso:country":"CN",
    "name:und_x_variant":[
        "Lingbei Zhen"
    ],
    "name:zho_x_preferred":[
        "\u5e99\u4e1c"
    ],
    "name:zho_x_variant":[
        "\u51cc\u5317\u9547"
    ],
    "wof:name":"Miaodong",
    "wof:placetype":"locality"
},
  "geometry": {"coordinates":[119.43553,41.28073],"type":"Point"}
}