{
  "type": "Feature",
  "properties": {
    "gn:admin1_code":"26.0",
    "gn:asciiname":"Panjiagou",
    "gn:country_code":"CN",
    "gn:dem":599,
    "gn:feature_class":"P",
    "gn:feature_code":"PPL",
    "gn:name":"Panjiagou",
    "gn:population":0,
    "gn:timezone":"Asia/Shanghai",
    "iso:country":"CN",
    "name:und_x_variant":[
        "\u6f58\u5bb6\u6c9f"
    ],
    "wof:name":"Panjiagou",
    "wof:placetype":"locality"
},
  "geometry": {"coordinates":[106.89973000000001,32.93977],"type":"Point"}
}