{
  "type": "Feature",
  "properties": {
    "gn:admin1_code":"25",
    "gn:asciiname":"Rentun",
    "gn:country_code":"CN",
    "gn:dem":44,
    "gn:feature_class":"P",
    "gn:feature_code":"PPL",
    "gn:name":"Rentun",
    "gn:population":0,
    "gn:timezone":"Asia/Shanghai",
    "iso:country":"CN",
    "name:zho_x_preferred":[
        "\u4efb\u5c6f"
    ],
    "wof:name":"Rentun",
    "wof:placetype":"locality"
},
  "geometry": {"coordinates":[115.92,35.7003],"type":"Point"}
}