{
  "type": "Feature",
  "properties": {
    "gn:admin1_code":"12.0",
    "gn:asciiname":"Chijiaping",
    "gn:country_code":"CN",
    "gn:dem":707,
    "gn:feature_class":"P",
    "gn:feature_code":"PPL",
    "gn:name":"Chijiaping",
    "gn:population":0,
    "gn:timezone":"Asia/Shanghai",
    "iso:country":"CN",
    "name:zho_x_preferred":[
        "\u6c60\u5bb6\u576a"
    ],
    "wof:name":"Chijiaping",
    "wof:placetype":"locality"
},
  "geometry": {"coordinates":[109.80376,30.63535],"type":"Point"}
}