{
  "type": "Feature",
  "properties": {
    "gn:admin1_code":"4.0",
    "gn:asciiname":"Yibaocun",
    "gn:country_code":"CN",
    "gn:dem":7,
    "gn:feature_class":"P",
    "gn:feature_code":"PPL",
    "gn:name":"Yibaocun",
    "gn:population":0,
    "gn:timezone":"Asia/Shanghai",
    "iso:country":"CN",
    "name:zho_x_preferred":[
        "\u4e49\u4fdd\u6751"
    ],
    "wof:name":"Yibaocun",
    "wof:placetype":"locality"
},
  "geometry": {"coordinates":[119.01709,31.28931],"type":"Point"}
}