{
  "type": "Feature",
  "properties": {
    "gn:admin1_code":"1.0",
    "gn:asciiname":"Xiaogangcun",
    "gn:country_code":"CN",
    "gn:dem":38,
    "gn:feature_class":"P",
    "gn:feature_code":"PPL",
    "gn:name":"Xiaogangcun",
    "gn:population":0,
    "gn:timezone":"Asia/Shanghai",
    "iso:country":"CN",
    "name:zho_x_preferred":[
        "\u8427\u5c97\u6751"
    ],
    "name:zho_x_variant":[
        "\u8096\u5c97\u6751"
    ],
    "wof:name":"Xiaogangcun",
    "wof:placetype":"locality"
},
  "geometry": {"coordinates":[117.76508,32.28448],"type":"Point"}
}