{
  "type": "Feature",
  "properties": {
    "gn:admin1_code":"18.0",
    "gn:asciiname":"Bangao",
    "gn:country_code":"CN",
    "gn:dem":856,
    "gn:feature_class":"P",
    "gn:feature_code":"PPL",
    "gn:name":"Bangao",
    "gn:population":0,
    "gn:timezone":"Asia/Shanghai",
    "iso:country":"CN",
    "name:zho_x_preferred":[
        "\u677f\u544a"
    ],
    "wof:name":"Bangao",
    "wof:placetype":"locality"
},
  "geometry": {"coordinates":[107.78400000000001,25.2029],"type":"Point"}
}