{
  "type": "Feature",
  "properties": {
    "gn:admin1_code":"25.0",
    "gn:asciiname":"Xichanghecun",
    "gn:country_code":"CN",
    "gn:dem":3,
    "gn:feature_class":"P",
    "gn:feature_code":"PPL",
    "gn:name":"Xichanghecun",
    "gn:population":0,
    "gn:timezone":"Asia/Shanghai",
    "iso:country":"CN",
    "name:zho_x_preferred":[
        "\u897f\u957f\u6cb3\u6751"
    ],
    "wof:name":"Xichanghecun",
    "wof:placetype":"locality"
},
  "geometry": {"coordinates":[119.41128999999999,35.3349],"type":"Point"}
}