{
  "type": "Feature",
  "properties": {
    "gn:admin1_code":"16",
    "gn:asciiname":"Qiaopi",
    "gn:country_code":"CN",
    "gn:dem":442,
    "gn:feature_class":"P",
    "gn:feature_code":"PPL",
    "gn:name":"Qiaopi",
    "gn:population":0,
    "gn:timezone":"Asia/Shanghai",
    "iso:country":"CN",
    "name:zho_x_preferred":[
        "\u6865\u76ae"
    ],
    "wof:name":"Qiaopi",
    "wof:placetype":"locality"
},
  "geometry": {"coordinates":[107.102,23.0297],"type":"Point"}
}