{
  "type": "Feature",
  "properties": {
    "gn:admin1_code":"4.0",
    "gn:asciiname":"Yuandong",
    "gn:country_code":"CN",
    "gn:dem":6,
    "gn:feature_class":"P",
    "gn:feature_code":"PPL",
    "gn:name":"Yuandong",
    "gn:population":0,
    "gn:timezone":"Asia/Shanghai",
    "iso:country":"CN",
    "name:zho_x_preferred":[
        "\u5143\u4e1c"
    ],
    "wof:name":"Yuandong",
    "wof:placetype":"locality"
},
  "geometry": {"coordinates":[120.69692000000001,32.70542],"type":"Point"}
}