{
  "type": "Feature",
  "properties": {
    "gn:admin1_code":"25",
    "gn:asciiname":"Datan",
    "gn:country_code":"CN",
    "gn:dem":29,
    "gn:feature_class":"P",
    "gn:feature_code":"PPL",
    "gn:name":"Datan",
    "gn:population":0,
    "gn:timezone":"Asia/Shanghai",
    "iso:country":"CN",
    "name:deu_x_preferred":[
        "Datan"
    ],
    "name:ita_x_preferred":[
        "Datan"
    ],
    "name:zho_x_preferred":[
        "\u5927\u6ee9"
    ],
    "wof:name":"Datan",
    "wof:placetype":"locality"
},
  "geometry": {"coordinates":[118.221,34.4608],"type":"Point"}
}