{
  "type": "Feature",
  "properties": {
    "gn:admin1_code":"4.0",
    "gn:asciiname":"Sanli",
    "gn:country_code":"CN",
    "gn:dem":5,
    "gn:feature_class":"P",
    "gn:feature_code":"PPL",
    "gn:name":"Sanli",
    "gn:population":0,
    "gn:timezone":"Asia/Shanghai",
    "iso:country":"CN",
    "name:deu_x_preferred":[
        "Sanli"
    ],
    "name:zho_x_preferred":[
        "Sanli"
    ],
    "name:zho_x_variant":[
        "\u4e09\u91cc"
    ],
    "wof:name":"Sanli",
    "wof:placetype":"locality"
},
  "geometry": {"coordinates":[119.07505999999999,33.22167],"type":"Point"}
}