{
  "type": "Feature",
  "properties": {
    "gn:admin1_code":"25",
    "gn:asciiname":"Chenjiamazhuang",
    "gn:country_code":"CN",
    "gn:dem":7,
    "gn:feature_class":"P",
    "gn:feature_code":"PPL",
    "gn:name":"Chenjiamazhuang",
    "gn:population":0,
    "gn:timezone":"Asia/Shanghai",
    "iso:country":"CN",
    "name:zho_x_preferred":[
        "\u9648\u5bb6\u9a6c\u5e84"
    ],
    "wof:name":"Chenjiamazhuang",
    "wof:placetype":"locality"
},
  "geometry": {"coordinates":[118.745,37.014],"type":"Point"}
}