{
  "type": "Feature",
  "properties": {
    "gn:admin1_code":"8.0",
    "gn:asciiname":"Dongchaoyangtun",
    "gn:country_code":"CN",
    "gn:dem":193,
    "gn:feature_class":"P",
    "gn:feature_code":"PPL",
    "gn:name":"Dongchaoyangtun",
    "gn:population":0,
    "gn:timezone":"Asia/Shanghai",
    "iso:country":"CN",
    "name:zho_x_preferred":[
        "\u4e1c\u671d\u9633\u5c6f"
    ],
    "wof:name":"Dongchaoyangtun",
    "wof:placetype":"locality"
},
  "geometry": {"coordinates":[124.8468,48.39561],"type":"Point"}
}