{
  "type": "Feature",
  "properties": {
    "gn:admin1_code":"01",
    "gn:asciiname":"Qingshanjie",
    "gn:country_code":"CN",
    "gn:dem":12,
    "gn:feature_class":"P",
    "gn:feature_code":"PPL",
    "gn:name":"Qingshanjie",
    "gn:population":0,
    "gn:timezone":"Asia/Shanghai",
    "iso:country":"CN",
    "name:und_x_variant":[
        "Ch\u2019ing-shan-chieh",
        "Qingshan",
        "Qingshanjie"
    ],
    "name:zho_x_preferred":[
        "\u9752\u5c71\u8857"
    ],
    "wof:name":"Qingshanjie",
    "wof:placetype":"locality"
},
  "geometry": {"coordinates":[118.54425999999999,31.45032],"type":"Point"}
}