{
  "type": "Feature",
  "properties": {
    "gn:admin1_code":"02",
    "gn:asciiname":"Zhong'ao",
    "gn:country_code":"CN",
    "gn:dem":8,
    "gn:feature_class":"P",
    "gn:feature_code":"PPL",
    "gn:name":"Zhong\u2019ao",
    "gn:population":0,
    "gn:timezone":"Asia/Shanghai",
    "iso:country":"CN",
    "name:und_x_variant":[
        "Chung-ao"
    ],
    "name:zho_x_preferred":[
        "Zhong\u2019ao"
    ],
    "wof:name":"Zhong'ao",
    "wof:placetype":"locality"
},
  "geometry": {"coordinates":[120.55028,27.97056],"type":"Point"}
}