{
  "type": "Feature",
  "properties": {
    "gn:admin1_code":"11",
    "gn:asciiname":"Jiangjiapai",
    "gn:country_code":"CN",
    "gn:dem":335,
    "gn:feature_class":"P",
    "gn:feature_code":"PPL",
    "gn:name":"Jiangjiapai",
    "gn:population":0,
    "gn:timezone":"Asia/Shanghai",
    "iso:country":"CN",
    "name:zho_x_preferred":[
        "\u6c5f\u5bb6\u6392"
    ],
    "wof:name":"Jiangjiapai",
    "wof:placetype":"locality"
},
  "geometry": {"coordinates":[112.23096,26.22596],"type":"Point"}
}