{
  "type": "Feature",
  "properties": {
    "gn:admin1_code":"25.0",
    "gn:asciiname":"Xinbaiyu",
    "gn:country_code":"CN",
    "gn:dem":59,
    "gn:feature_class":"P",
    "gn:feature_code":"PPL",
    "gn:name":"Xinbaiyu",
    "gn:population":0,
    "gn:timezone":"Asia/Shanghai",
    "iso:country":"CN",
    "name:zho_x_preferred":[
        "\u65b0\u767d\u7389"
    ],
    "wof:name":"Xinbaiyu",
    "wof:placetype":"locality"
},
  "geometry": {"coordinates":[121.97351999999999,37.24971],"type":"Point"}
}