{
  "type": "Feature",
  "properties": {
    "gn:admin1_code":"8.0",
    "gn:asciiname":"Wudahu",
    "gn:country_code":"CN",
    "gn:dem":135,
    "gn:feature_class":"P",
    "gn:feature_code":"PPL",
    "gn:name":"Wudahu",
    "gn:population":0,
    "gn:timezone":"Asia/Shanghai",
    "iso:country":"CN",
    "name:zho_x_preferred":[
        "\u4e94\u5927\u6237"
    ],
    "wof:name":"Wudahu",
    "wof:placetype":"locality"
},
  "geometry": {"coordinates":[124.75802,46.02914000000001],"type":"Point"}
}