{
  "type": "Feature",
  "properties": {
    "gn:admin1_code":"4.0",
    "gn:asciiname":"Xifeng",
    "gn:country_code":"CN",
    "gn:dem":5,
    "gn:feature_class":"P",
    "gn:feature_code":"PPL",
    "gn:name":"Xifeng",
    "gn:population":0,
    "gn:timezone":"Asia/Shanghai",
    "iso:country":"CN",
    "name:ceb_x_preferred":[
        "Xifeng"
    ],
    "name:deu_x_preferred":[
        "Xifeng"
    ],
    "name:eus_x_preferred":[
        "Xifeng"
    ],
    "name:fra_x_preferred":[
        "Xifeng"
    ],
    "name:mlg_x_preferred":[
        "Xifeng"
    ],
    "name:nor_x_preferred":[
        "Xifeng"
    ],
    "name:swe_x_preferred":[
        "Xifeng"
    ],
    "name:zho_x_preferred":[
        "\u897f\u51af"
    ],
    "wof:name":"Xifeng",
    "wof:placetype":"locality"
},
  "geometry": {"coordinates":[119.84766999999999,32.52246],"type":"Point"}
}