{
  "type": "Feature",
  "properties": {
    "gn:admin1_code":"4.0",
    "gn:asciiname":"Maowu",
    "gn:country_code":"CN",
    "gn:dem":2,
    "gn:feature_class":"P",
    "gn:feature_code":"PPL",
    "gn:name":"Maowu",
    "gn:population":0,
    "gn:timezone":"Asia/Shanghai",
    "iso:country":"CN",
    "name:zho_x_preferred":[
        "\u8306\u5434"
    ],
    "wof:name":"Maowu",
    "wof:placetype":"locality"
},
  "geometry": {"coordinates":[119.64751,32.82674],"type":"Point"}
}