{
  "type": "Feature",
  "properties": {
    "gn:admin1_code":"22.0",
    "gn:asciiname":"Nanwancun",
    "gn:country_code":"CN",
    "gn:dem":528,
    "gn:feature_class":"P",
    "gn:feature_code":"PPL",
    "gn:name":"Nanwancun",
    "gn:population":0,
    "gn:timezone":"Asia/Shanghai",
    "iso:country":"CN",
    "name:zho_x_preferred":[
        "\u5357\u6e7e\u6751"
    ],
    "wof:name":"Nanwancun",
    "wof:placetype":"locality"
},
  "geometry": {"coordinates":[116.48118999999998,40.59432],"type":"Point"}
}