{
  "type": "Feature",
  "properties": {
    "gn:admin1_code":"11.0",
    "gn:asciiname":"Paili'ao",
    "gn:country_code":"CN",
    "gn:dem":325,
    "gn:feature_class":"P",
    "gn:feature_code":"PPL",
    "gn:name":"Paili\u2019ao",
    "gn:population":0,
    "gn:timezone":"Asia/Shanghai",
    "iso:country":"CN",
    "name:und_x_variant":[
        "Paili\u2019ao"
    ],
    "name:zho_x_preferred":[
        "\u6392\u91cc\u5773"
    ],
    "wof:name":"Paili'ao",
    "wof:placetype":"locality"
},
  "geometry": {"coordinates":[110.03257000000001,27.30372],"type":"Point"}
}