{
  "type": "Feature",
  "properties": {
    "gn:admin1_code":"15.0",
    "gn:asciiname":"Daquanwan",
    "gn:country_code":"CN",
    "gn:dem":2288,
    "gn:feature_class":"P",
    "gn:feature_code":"PPL",
    "gn:name":"Daquanwan",
    "gn:population":0,
    "gn:timezone":"Asia/Shanghai",
    "iso:country":"CN",
    "name:zho_x_preferred":[
        "\u5927\u5708\u6e7e"
    ],
    "wof:name":"Daquanwan",
    "wof:placetype":"locality"
},
  "geometry": {"coordinates":[104.43899999999999,36.0988],"type":"Point"}
}