{
  "type": "Feature",
  "properties": {
    "gn:admin1_code":"26.0",
    "gn:asciiname":"Zhoujiayazi",
    "gn:country_code":"CN",
    "gn:dem":635,
    "gn:feature_class":"P",
    "gn:feature_code":"PPL",
    "gn:name":"Zhoujiayazi",
    "gn:population":0,
    "gn:timezone":"Asia/Shanghai",
    "iso:country":"CN",
    "name:zho_x_preferred":[
        "\u5468\u5bb6\u57ad\u5b50"
    ],
    "wof:name":"Zhoujiayazi",
    "wof:placetype":"locality"
},
  "geometry": {"coordinates":[109.25436999999999,32.51938],"type":"Point"}
}