{
  "type": "Feature",
  "properties": {
    "gn:admin1_code":"26.0",
    "gn:asciiname":"Fotangyancun",
    "gn:country_code":"CN",
    "gn:dem":1043,
    "gn:feature_class":"P",
    "gn:feature_code":"PPL",
    "gn:name":"Fotangyancun",
    "gn:population":0,
    "gn:timezone":"Asia/Shanghai",
    "iso:country":"CN",
    "name:zho_x_preferred":[
        "\u4f5b\u5802\u5895\u6751"
    ],
    "wof:name":"Fotangyancun",
    "wof:placetype":"locality"
},
  "geometry": {"coordinates":[110.05953,37.64857],"type":"Point"}
}