{
  "type": "Feature",
  "properties": {
    "gn:admin1_code":"29.0",
    "gn:asciiname":"Baijiacun",
    "gn:country_code":"CN",
    "gn:dem":1879,
    "gn:feature_class":"P",
    "gn:feature_code":"PPL",
    "gn:name":"Baijiacun",
    "gn:population":0,
    "gn:timezone":"Asia/Shanghai",
    "iso:country":"CN",
    "name:zho_x_preferred":[
        "\u767d\u5bb6\u6751"
    ],
    "wof:name":"Baijiacun",
    "wof:placetype":"locality"
},
  "geometry": {"coordinates":[103.25,25.4891],"type":"Point"}
}