{
  "type": "Feature",
  "properties": {
    "gn:admin1_code":"20.0",
    "gn:asciiname":"Choujiagou",
    "gn:country_code":"CN",
    "gn:dem":1333,
    "gn:feature_class":"P",
    "gn:feature_code":"PPL",
    "gn:name":"Choujiagou",
    "gn:population":0,
    "gn:timezone":"Asia/Shanghai",
    "iso:country":"CN",
    "name:und_x_variant":[
        "\u4ec7\u5bb6\u6c9f"
    ],
    "wof:name":"Choujiagou",
    "wof:placetype":"locality"
},
  "geometry": {"coordinates":[111.69479,39.74385],"type":"Point"}
}