{
  "type": "Feature",
  "properties": {
    "gn:admin1_code":"11.0",
    "gn:asciiname":"Mailong",
    "gn:country_code":"CN",
    "gn:dem":606,
    "gn:feature_class":"P",
    "gn:feature_code":"PPL",
    "gn:name":"Mailong",
    "gn:population":0,
    "gn:timezone":"Asia/Shanghai",
    "iso:country":"CN",
    "name:zho_x_preferred":[
        "\u8109\u9f99"
    ],
    "wof:name":"Mailong",
    "wof:placetype":"locality"
},
  "geometry": {"coordinates":[109.37378,29.05193],"type":"Point"}
}