{
  "type": "Feature",
  "properties": {
    "gn:admin1_code":"16",
    "gn:asciiname":"Tabei",
    "gn:country_code":"CN",
    "gn:dem":527,
    "gn:feature_class":"P",
    "gn:feature_code":"PPL",
    "gn:name":"Tabei",
    "gn:population":0,
    "gn:timezone":"Asia/Shanghai",
    "iso:country":"CN",
    "name:deu_x_preferred":[
        "Tabei"
    ],
    "name:por_x_preferred":[
        "Tabei"
    ],
    "wof:name":"Tabei",
    "wof:placetype":"locality"
},
  "geometry": {"coordinates":[110.11028,25.57639],"type":"Point"}
}