{
  "type": "Feature",
  "properties": {
    "gn:admin1_code":"5.0",
    "gn:asciiname":"Mijiatun",
    "gn:country_code":"CN",
    "gn:dem":168,
    "gn:feature_class":"P",
    "gn:feature_code":"PPL",
    "gn:name":"Mijiatun",
    "gn:population":0,
    "gn:timezone":"Asia/Shanghai",
    "iso:country":"CN",
    "name:zho_x_preferred":[
        "\u7c73\u5bb6\u5c6f"
    ],
    "wof:name":"Mijiatun",
    "wof:placetype":"locality"
},
  "geometry": {"coordinates":[126.9744,45.02111],"type":"Point"}
}