{
  "type": "Feature",
  "properties": {
    "gn:admin1_code":"21.0",
    "gn:asciiname":"Liuqingdi",
    "gn:country_code":"CN",
    "gn:dem":1103,
    "gn:feature_class":"P",
    "gn:feature_code":"PPL",
    "gn:name":"Liuqingdi",
    "gn:population":0,
    "gn:timezone":"Asia/Shanghai",
    "iso:country":"CN",
    "name:und_x_variant":[
        "Liuqingdi Xiang"
    ],
    "name:zho_x_preferred":[
        "\u516d\u9877\u5730"
    ],
    "name:zho_x_variant":[
        "\u516d\u9877\u5730\u4e61"
    ],
    "wof:name":"Liuqingdi",
    "wof:placetype":"locality"
},
  "geometry": {"coordinates":[106.64100000000001,38.7619],"type":"Point"}
}