{
  "type": "Feature",
  "properties": {
    "gn:admin1_code":"8.0",
    "gn:asciiname":"Tianwenmaotun",
    "gn:country_code":"CN",
    "gn:dem":216,
    "gn:feature_class":"P",
    "gn:feature_code":"PPL",
    "gn:name":"Tianwenmaotun",
    "gn:population":0,
    "gn:timezone":"Asia/Shanghai",
    "iso:country":"CN",
    "name:zho_x_preferred":[
        "\u7530\u6587\u8302\u5c6f"
    ],
    "wof:name":"Tianwenmaotun",
    "wof:placetype":"locality"
},
  "geometry": {"coordinates":[125.68574,47.17182],"type":"Point"}
}