{
  "type": "Feature",
  "properties": {
    "gn:admin1_code":"14.0",
    "gn:asciiname":"Waji",
    "gn:country_code":"CN",
    "gn:dem":3759,
    "gn:feature_class":"P",
    "gn:feature_code":"PPL",
    "gn:name":"Waji",
    "gn:population":0,
    "gn:timezone":"Asia/Urumqi",
    "iso:country":"CN",
    "name:zho_x_preferred":[
        "\u5a03\u7ed9"
    ],
    "wof:name":"Waji",
    "wof:placetype":"locality"
},
  "geometry": {"coordinates":[95.85281000000001,31.27338],"type":"Point"}
}