{
  "type": "Feature",
  "properties": {
    "gn:admin1_code":"18",
    "gn:asciiname":"Daliangzi",
    "gn:country_code":"CN",
    "gn:dem":1971,
    "gn:feature_class":"P",
    "gn:feature_code":"PPL",
    "gn:name":"Daliangzi",
    "gn:population":0,
    "gn:timezone":"Asia/Shanghai",
    "iso:country":"CN",
    "name:zho_x_preferred":[
        "\u5927\u6881\u5b50"
    ],
    "wof:name":"Daliangzi",
    "wof:placetype":"locality"
},
  "geometry": {"coordinates":[103.69499999999999,27.1178],"type":"Point"}
}