{
  "type": "Feature",
  "properties": {
    "gn:admin1_code":"7",
    "gn:asciiname":"Yuantankeng",
    "gn:country_code":"CN",
    "gn:dem":716,
    "gn:feature_class":"P",
    "gn:feature_code":"PPL",
    "gn:name":"Yuantankeng",
    "gn:population":0,
    "gn:timezone":"Asia/Shanghai",
    "iso:country":"CN",
    "name:zho_x_preferred":[
        "\u5458\u6f6d\u5751"
    ],
    "wof:name":"Yuantankeng",
    "wof:placetype":"locality"
},
  "geometry": {"coordinates":[117.90389,24.9475],"type":"Point"}
}