{
  "type": "Feature",
  "properties": {
    "gn:admin1_code":"8.0",
    "gn:asciiname":"Taipingchuan",
    "gn:country_code":"CN",
    "gn:dem":102,
    "gn:feature_class":"P",
    "gn:feature_code":"PPLA4",
    "gn:name":"Taipingchuan",
    "gn:population":0,
    "gn:timezone":"Asia/Shanghai",
    "iso:country":"CN",
    "name:und_x_variant":[
        "Taipingchuan Xiang"
    ],
    "name:zho_x_preferred":[
        "\u592a\u5e73\u5ddd"
    ],
    "name:zho_x_variant":[
        "\u592a\u5e73\u5ddd\u4e61"
    ],
    "wof:name":"Taipingchuan",
    "wof:placetype":"locality"
},
  "geometry": {"coordinates":[129.99223999999998,46.87224000000001],"type":"Point"}
}