{
  "type": "Feature",
  "properties": {
    "gn:admin1_code":"15.0",
    "gn:asciiname":"Linkouli",
    "gn:country_code":"CN",
    "gn:dem":1458,
    "gn:feature_class":"P",
    "gn:feature_code":"PPL",
    "gn:name":"Linkouli",
    "gn:population":0,
    "gn:timezone":"Asia/Shanghai",
    "iso:country":"CN",
    "name:und_x_variant":[
        "\u6797\u53e3\u91cc"
    ],
    "wof:name":"Linkouli",
    "wof:placetype":"locality"
},
  "geometry": {"coordinates":[105.43714,33.25085],"type":"Point"}
}