{
  "type": "Feature",
  "properties": {
    "gn:admin1_code":"3",
    "gn:asciiname":"Jianxi Gongjia",
    "gn:country_code":"CN",
    "gn:dem":37,
    "gn:feature_class":"P",
    "gn:feature_code":"PPL",
    "gn:name":"Jianxi Gongjia",
    "gn:population":0,
    "gn:timezone":"Asia/Shanghai",
    "iso:country":"CN",
    "name:und_x_variant":[
        "\u5251\u6eaa\u9f9a\u5bb6"
    ],
    "wof:name":"Jianxi Gongjia",
    "wof:placetype":"locality"
},
  "geometry": {"coordinates":[116.31085,28.27384],"type":"Point"}
}