{
  "type": "Feature",
  "properties": {
    "gn:admin1_code":"12.0",
    "gn:asciiname":"Maojiafan",
    "gn:country_code":"CN",
    "gn:dem":16,
    "gn:feature_class":"P",
    "gn:feature_code":"PPL",
    "gn:name":"Maojiafan",
    "gn:population":0,
    "gn:timezone":"Asia/Shanghai",
    "iso:country":"CN",
    "name:zho_x_preferred":[
        "\u6bdb\u5bb6\u7548"
    ],
    "wof:name":"Maojiafan",
    "wof:placetype":"locality"
},
  "geometry": {"coordinates":[115.73421,29.93254],"type":"Point"}
}