{
  "type": "Feature",
  "properties": {
    "gn:admin1_code":"16",
    "gn:asciiname":"Shangpengyan",
    "gn:country_code":"CN",
    "gn:dem":372,
    "gn:feature_class":"P",
    "gn:feature_code":"PPL",
    "gn:name":"Shangpengyan",
    "gn:population":0,
    "gn:timezone":"Asia/Shanghai",
    "iso:country":"CN",
    "name:zho_x_preferred":[
        "\u4e0a\u84ec\u5ca9"
    ],
    "wof:name":"Shangpengyan",
    "wof:placetype":"locality"
},
  "geometry": {"coordinates":[110.908,25.2276],"type":"Point"}
}