{
  "type": "Feature",
  "properties": {
    "gn:admin1_code":"22.0",
    "gn:asciiname":"Dajiaoyucun",
    "gn:country_code":"CN",
    "gn:dem":526,
    "gn:feature_class":"P",
    "gn:feature_code":"PPL",
    "gn:name":"Dajiaoyucun",
    "gn:population":0,
    "gn:timezone":"Asia/Shanghai",
    "iso:country":"CN",
    "name:zho_x_preferred":[
        "\u5927\u89d2\u5cea\u6751"
    ],
    "wof:name":"Dajiaoyucun",
    "wof:placetype":"locality"
},
  "geometry": {"coordinates":[117.43979,40.66195],"type":"Point"}
}