{
  "type": "Feature",
  "properties": {
    "gn:admin1_code":"10",
    "gn:asciiname":"Yiziquan",
    "gn:country_code":"CN",
    "gn:dem":469,
    "gn:feature_class":"P",
    "gn:feature_code":"PPL",
    "gn:name":"Yiziquan",
    "gn:population":0,
    "gn:timezone":"Asia/Shanghai",
    "iso:country":"CN",
    "name:zho_x_preferred":[
        "\u6905\u5b50\u5708"
    ],
    "wof:name":"Yiziquan",
    "wof:placetype":"locality"
},
  "geometry": {"coordinates":[118.63866000000002,40.48153],"type":"Point"}
}