{
  "type": "Feature",
  "properties": {
    "gn:admin1_code":"26.0",
    "gn:asciiname":"Daping",
    "gn:country_code":"CN",
    "gn:dem":1288,
    "gn:feature_class":"P",
    "gn:feature_code":"PPL",
    "gn:name":"Daping",
    "gn:population":0,
    "gn:timezone":"Asia/Shanghai",
    "iso:country":"CN",
    "name:ceb_x_preferred":[
        "Daping"
    ],
    "name:deu_x_preferred":[
        "Daping"
    ],
    "name:swe_x_preferred":[
        "Daping"
    ],
    "name:und_x_variant":[
        "\u5927\u576a"
    ],
    "wof:name":"Daping",
    "wof:placetype":"locality"
},
  "geometry": {"coordinates":[107.55985,34.84257],"type":"Point"}
}