{
  "type": "Feature",
  "properties": {
    "gn:admin1_code":"32.0",
    "gn:asciiname":"Ejia",
    "gn:country_code":"CN",
    "gn:dem":4011,
    "gn:feature_class":"P",
    "gn:feature_code":"PPL",
    "gn:name":"Ejia",
    "gn:population":0,
    "gn:timezone":"Asia/Shanghai",
    "iso:country":"CN",
    "name:zho_x_preferred":[
        "\u4fc4\u52a0"
    ],
    "wof:name":"Ejia",
    "wof:placetype":"locality"
},
  "geometry": {"coordinates":[98.4248,32.9132],"type":"Point"}
}