{
  "type": "Feature",
  "properties": {
    "gn:admin1_code":"29.0",
    "gn:asciiname":"Daiping",
    "gn:country_code":"CN",
    "gn:dem":2052,
    "gn:feature_class":"P",
    "gn:feature_code":"PPL",
    "gn:name":"Daiping",
    "gn:population":0,
    "gn:timezone":"Asia/Shanghai",
    "iso:country":"CN",
    "name:und_x_variant":[
        "\u4ee3\u576a"
    ],
    "wof:name":"Daiping",
    "wof:placetype":"locality"
},
  "geometry": {"coordinates":[104.35665,26.04487],"type":"Point"}
}