{
  "type": "Feature",
  "properties": {
    "gn:admin1_code":"8.0",
    "gn:asciiname":"Ping'antun",
    "gn:country_code":"CN",
    "gn:dem":126,
    "gn:feature_class":"P",
    "gn:feature_code":"PPL",
    "gn:name":"Ping\u2019antun",
    "gn:population":0,
    "gn:timezone":"Asia/Shanghai",
    "iso:country":"CN",
    "name:und_x_variant":[
        "Ping\u2019antun"
    ],
    "name:zho_x_preferred":[
        "\u5e73\u5b89\u5c6f"
    ],
    "wof:name":"Ping'antun",
    "wof:placetype":"locality"
},
  "geometry": {"coordinates":[128.85683,45.82363],"type":"Point"}
}