{
  "type": "Feature",
  "properties": {
    "gn:admin1_code":"32.0",
    "gn:asciiname":"Lannihao",
    "gn:country_code":"CN",
    "gn:dem":410,
    "gn:feature_class":"P",
    "gn:feature_code":"PPL",
    "gn:name":"Lannihao",
    "gn:population":0,
    "gn:timezone":"Asia/Shanghai",
    "iso:country":"CN",
    "name:zho_x_preferred":[
        "\u62e6\u6ce5\u6d69"
    ],
    "wof:name":"Lannihao",
    "wof:placetype":"locality"
},
  "geometry": {"coordinates":[105.896,31.7892],"type":"Point"}
}