{
  "type": "Feature",
  "properties": {
    "gn:admin1_code":"1.0",
    "gn:asciiname":"Shenzhuangcun",
    "gn:country_code":"CN",
    "gn:dem":37,
    "gn:feature_class":"P",
    "gn:feature_code":"PPL",
    "gn:name":"Shenzhuangcun",
    "gn:population":0,
    "gn:timezone":"Asia/Shanghai",
    "iso:country":"CN",
    "name:zho_x_preferred":[
        "\u6c88\u5e84\u6751"
    ],
    "wof:name":"Shenzhuangcun",
    "wof:placetype":"locality"
},
  "geometry": {"coordinates":[117.01466000000001,34.21508],"type":"Point"}
}