{
  "type": "Feature",
  "properties": {
    "gn:admin1_code":"26.0",
    "gn:asciiname":"Longwangmiao",
    "gn:country_code":"CN",
    "gn:dem":718,
    "gn:feature_class":"P",
    "gn:feature_code":"PPL",
    "gn:name":"Longwangmiao",
    "gn:population":0,
    "gn:timezone":"Asia/Shanghai",
    "iso:country":"CN",
    "name:und_x_variant":[
        "\u9f99\u738b\u5e99"
    ],
    "wof:name":"Longwangmiao",
    "wof:placetype":"locality"
},
  "geometry": {"coordinates":[107.76130000000001,34.16934000000001],"type":"Point"}
}