{
  "type": "Feature",
  "properties": {
    "gn:admin1_code":"19.0",
    "gn:asciiname":"Hongtonggou",
    "gn:country_code":"CN",
    "gn:dem":508,
    "gn:feature_class":"P",
    "gn:feature_code":"PPL",
    "gn:name":"Hongtonggou",
    "gn:population":0,
    "gn:timezone":"Asia/Shanghai",
    "iso:country":"CN",
    "name:zho_x_preferred":[
        "\u7ea2\u94dc\u6c9f"
    ],
    "wof:name":"Hongtonggou",
    "wof:placetype":"locality"
},
  "geometry": {"coordinates":[124.6067,41.13099],"type":"Point"}
}