{
  "type": "Feature",
  "properties": {
    "gn:admin1_code":"3.0",
    "gn:asciiname":"Changkeng",
    "gn:country_code":"CN",
    "gn:dem":547,
    "gn:feature_class":"P",
    "gn:feature_code":"PPL",
    "gn:name":"Changkeng",
    "gn:population":0,
    "gn:timezone":"Asia/Shanghai",
    "iso:country":"CN",
    "name:und_x_variant":[
        "\u660c\u5751"
    ],
    "wof:name":"Changkeng",
    "wof:placetype":"locality"
},
  "geometry": {"coordinates":[114.63853,28.57104],"type":"Point"}
}