{
  "type": "Feature",
  "properties": {
    "gn:admin1_code":"32.0",
    "gn:asciiname":"Daligong",
    "gn:country_code":"CN",
    "gn:dem":518,
    "gn:feature_class":"P",
    "gn:feature_code":"PPL",
    "gn:name":"Daligong",
    "gn:population":0,
    "gn:timezone":"Asia/Shanghai",
    "iso:country":"CN",
    "name:zho_x_preferred":[
        "\u5927\u529b\u5bab"
    ],
    "wof:name":"Daligong",
    "wof:placetype":"locality"
},
  "geometry": {"coordinates":[106.11499999999999,31.6529],"type":"Point"}
}