{
  "type": "Feature",
  "properties": {
    "gn:admin1_code":"29.0",
    "gn:asciiname":"Xitaoping",
    "gn:country_code":"CN",
    "gn:dem":2413,
    "gn:feature_class":"P",
    "gn:feature_code":"PPL",
    "gn:name":"Xitaoping",
    "gn:population":0,
    "gn:timezone":"Asia/Shanghai",
    "iso:country":"CN",
    "name:zho_x_preferred":[
        "\u897f\u6843\u576a"
    ],
    "wof:name":"Xitaoping",
    "wof:placetype":"locality"
},
  "geometry": {"coordinates":[99.7186,26.2195],"type":"Point"}
}