{
  "type": "Feature",
  "properties": {
    "gn:admin1_code":"19.0",
    "gn:asciiname":"Songzhangzi",
    "gn:country_code":"CN",
    "gn:dem":216,
    "gn:feature_class":"P",
    "gn:feature_code":"PPL",
    "gn:name":"Songzhangzi",
    "gn:population":0,
    "gn:timezone":"Asia/Shanghai",
    "iso:country":"CN",
    "name:zho_x_preferred":[
        "\u5b8b\u6756\u5b50"
    ],
    "wof:name":"Songzhangzi",
    "wof:placetype":"locality"
},
  "geometry": {"coordinates":[120.38999,41.65318],"type":"Point"}
}