{
  "type": "Feature",
  "properties": {
    "gn:admin1_code":"9.0",
    "gn:asciiname":"Dongliuchong",
    "gn:country_code":"CN",
    "gn:dem":160,
    "gn:feature_class":"P",
    "gn:feature_code":"PPL",
    "gn:name":"Dongliuchong",
    "gn:population":0,
    "gn:timezone":"Asia/Shanghai",
    "iso:country":"CN",
    "name:zho_x_preferred":[
        "\u4e1c\u5218\u51b2"
    ],
    "wof:name":"Dongliuchong",
    "wof:placetype":"locality"
},
  "geometry": {"coordinates":[112.79132,32.47346],"type":"Point"}
}