{
  "type": "Feature",
  "properties": {
    "gn:admin1_code":"19.0",
    "gn:asciiname":"Nanfangshen",
    "gn:country_code":"CN",
    "gn:dem":74,
    "gn:feature_class":"P",
    "gn:feature_code":"PPL",
    "gn:name":"Nanfangshen",
    "gn:population":0,
    "gn:timezone":"Asia/Shanghai",
    "iso:country":"CN",
    "name:zho_x_preferred":[
        "\u5357\u623f\u8eab"
    ],
    "wof:name":"Nanfangshen",
    "wof:placetype":"locality"
},
  "geometry": {"coordinates":[121.907,39.5426],"type":"Point"}
}