{
  "type": "Feature",
  "properties": {
    "gn:admin1_code":"3",
    "gn:asciiname":"Pingshan",
    "gn:country_code":"CN",
    "gn:dem":228,
    "gn:feature_class":"P",
    "gn:feature_code":"PPL",
    "gn:name":"Pingshan",
    "gn:population":0,
    "gn:timezone":"Asia/Shanghai",
    "iso:country":"CN",
    "name:zho_x_preferred":[
        "\u576a\u5c71"
    ],
    "wof:name":"Pingshan",
    "wof:placetype":"locality"
},
  "geometry": {"coordinates":[114.64100000000001,26.0631],"type":"Point"}
}