{
  "type": "Feature",
  "properties": {
    "gn:admin1_code":"11.0",
    "gn:asciiname":"Heyechong",
    "gn:country_code":"CN",
    "gn:dem":91,
    "gn:feature_class":"P",
    "gn:feature_code":"PPL",
    "gn:name":"Heyechong",
    "gn:population":0,
    "gn:timezone":"Asia/Shanghai",
    "iso:country":"CN",
    "name:zho_x_preferred":[
        "\u8377\u53f6\u51b2"
    ],
    "wof:name":"Heyechong",
    "wof:placetype":"locality"
},
  "geometry": {"coordinates":[113.05468,28.09996],"type":"Point"}
}