{
  "type": "Feature",
  "properties": {
    "gn:admin1_code":"3.0",
    "gn:asciiname":"Shitoukeng",
    "gn:country_code":"CN",
    "gn:dem":284,
    "gn:feature_class":"P",
    "gn:feature_code":"PPL",
    "gn:name":"Shitoukeng",
    "gn:population":0,
    "gn:timezone":"Asia/Shanghai",
    "iso:country":"CN",
    "name:und_x_variant":[
        "\u77f3\u5934\u5751"
    ],
    "wof:name":"Shitoukeng",
    "wof:placetype":"locality"
},
  "geometry": {"coordinates":[114.81075,28.11906],"type":"Point"}
}