{
  "type": "Feature",
  "properties": {
    "gn:admin1_code":"4.0",
    "gn:asciiname":"Dashu",
    "gn:country_code":"CN",
    "gn:dem":3,
    "gn:feature_class":"P",
    "gn:feature_code":"PPL",
    "gn:name":"Dashu",
    "gn:population":0,
    "gn:timezone":"Asia/Shanghai",
    "iso:country":"CN",
    "name:zho_x_preferred":[
        "Dashu"
    ],
    "name:zho_x_variant":[
        "\u5927\u6811"
    ],
    "wof:name":"Dashu",
    "wof:placetype":"locality"
},
  "geometry": {"coordinates":[119.45218,33.24878],"type":"Point"}
}