{
  "type": "Feature",
  "properties": {
    "gn:admin1_code":"29.0",
    "gn:asciiname":"Manbang",
    "gn:country_code":"CN",
    "gn:dem":1416,
    "gn:feature_class":"P",
    "gn:feature_code":"PPL",
    "gn:name":"Manbang",
    "gn:population":0,
    "gn:timezone":"Asia/Shanghai",
    "iso:country":"CN",
    "name:zho_x_preferred":[
        "\u66fc\u68d2"
    ],
    "wof:name":"Manbang",
    "wof:placetype":"locality"
},
  "geometry": {"coordinates":[97.812,24.4209],"type":"Point"}
}