{
  "type": "Feature",
  "properties": {
    "gn:admin1_code":"1.0",
    "gn:asciiname":"Luyuancun",
    "gn:country_code":"CN",
    "gn:dem":51,
    "gn:feature_class":"P",
    "gn:feature_code":"PPL",
    "gn:name":"Luyuancun",
    "gn:population":0,
    "gn:timezone":"Asia/Shanghai",
    "iso:country":"CN",
    "name:zho_x_preferred":[
        "\u9e7f\u82d1\u6751"
    ],
    "wof:name":"Luyuancun",
    "wof:placetype":"locality"
},
  "geometry": {"coordinates":[116.73012,30.74155],"type":"Point"}
}