{
  "type": "Feature",
  "properties": {
    "gn:admin1_code":"24.0",
    "gn:asciiname":"Qianmaoshang",
    "gn:country_code":"CN",
    "gn:dem":1350,
    "gn:feature_class":"P",
    "gn:feature_code":"PPL",
    "gn:name":"Qianmaoshang",
    "gn:population":0,
    "gn:timezone":"Asia/Shanghai",
    "iso:country":"CN",
    "name:zho_x_preferred":[
        "\u524d\u5cc1\u4e0a"
    ],
    "wof:name":"Qianmaoshang",
    "wof:placetype":"locality"
},
  "geometry": {"coordinates":[111.03443,37.59377],"type":"Point"}
}