{
  "type": "Feature",
  "properties": {
    "gn:admin1_code":"13",
    "gn:asciiname":"Dongtouqu",
    "gn:country_code":"CN",
    "gn:dem":1646,
    "gn:feature_class":"P",
    "gn:feature_code":"PPL",
    "gn:name":"Dongtouqu",
    "gn:population":0,
    "gn:timezone":"Asia/Urumqi",
    "iso:country":"CN",
    "name:und_x_variant":[
        "\u4e1c\u5934\u6e20"
    ],
    "wof:name":"Dongtouqu",
    "wof:placetype":"locality"
},
  "geometry": {"coordinates":[93.16932,43.67735],"type":"Point"}
}