{
  "type": "Feature",
  "properties": {
    "gn:admin1_code":"14.0",
    "gn:asciiname":"Parco",
    "gn:country_code":"CN",
    "gn:dem":4418,
    "gn:feature_class":"P",
    "gn:feature_code":"PPLF",
    "gn:name":"Parco",
    "gn:population":0,
    "gn:timezone":"Asia/Urumqi",
    "iso:country":"CN",
    "name:bod_x_preferred":[
        "Parco"
    ],
    "name:ceb_x_preferred":[
        "Parco"
    ],
    "name:ita_x_preferred":[
        "Parco"
    ],
    "name:srp_x_preferred":[
        "Parco"
    ],
    "name:swe_x_preferred":[
        "Parco"
    ],
    "name:zho_x_preferred":[
        "Pacuo"
    ],
    "name:zho_x_variant":[
        "\u5e15\u9519"
    ],
    "wof:name":"Parco",
    "wof:placetype":"locality"
},
  "geometry": {"coordinates":[86.601,28.701],"type":"Point"}
}