{
  "type": "Feature",
  "properties": {
    "gn:admin1_code":"33.0",
    "gn:asciiname":"Shuyuan",
    "gn:country_code":"CN",
    "gn:dem":300,
    "gn:feature_class":"P",
    "gn:feature_code":"PPL",
    "gn:name":"Shuyuan",
    "gn:population":0,
    "gn:timezone":"Asia/Shanghai",
    "iso:country":"CN",
    "name:zho_x_preferred":[
        "\u4e66\u9662"
    ],
    "wof:name":"Shuyuan",
    "wof:placetype":"locality"
},
  "geometry": {"coordinates":[106.54346,29.82335],"type":"Point"}
}