{
  "type": "Feature",
  "properties": {
    "gn:admin1_code":"12.0",
    "gn:asciiname":"Caijia Yuanzi",
    "gn:country_code":"CN",
    "gn:dem":43,
    "gn:feature_class":"P",
    "gn:feature_code":"PPL",
    "gn:name":"Caijia Yuanzi",
    "gn:population":0,
    "gn:timezone":"Asia/Shanghai",
    "iso:country":"CN",
    "name:und_x_variant":[
        "\u8521\u5bb6\u9662\u5b50"
    ],
    "wof:name":"Caijia Yuanzi",
    "wof:placetype":"locality"
},
  "geometry": {"coordinates":[111.92158999999999,29.84969],"type":"Point"}
}