{
  "type": "Feature",
  "properties": {
    "gn:admin1_code":"25.0",
    "gn:asciiname":"Qianzhujiazhuang",
    "gn:country_code":"CN",
    "gn:dem":13,
    "gn:feature_class":"P",
    "gn:feature_code":"PPL",
    "gn:name":"Qianzhujiazhuang",
    "gn:population":0,
    "gn:timezone":"Asia/Shanghai",
    "iso:country":"CN",
    "name:zho_x_preferred":[
        "\u524d\u6731\u5bb6\u5e84"
    ],
    "wof:name":"Qianzhujiazhuang",
    "wof:placetype":"locality"
},
  "geometry": {"coordinates":[119.5519,36.6182],"type":"Point"}
}