{
  "type": "Feature",
  "properties": {
    "gn:admin1_code":"30.0",
    "gn:asciiname":"Kengding",
    "gn:country_code":"CN",
    "gn:dem":165,
    "gn:feature_class":"P",
    "gn:feature_code":"PPL",
    "gn:name":"Kengding",
    "gn:population":0,
    "gn:timezone":"Asia/Shanghai",
    "iso:country":"CN",
    "name:zho_x_preferred":[
        "\u5751\u9876"
    ],
    "wof:name":"Kengding",
    "wof:placetype":"locality"
},
  "geometry": {"coordinates":[111.99509,23.69498],"type":"Point"}
}