{
  "type": "Feature",
  "properties": {
    "gn:admin1_code":"1.0",
    "gn:asciiname":"Xinghuocun",
    "gn:country_code":"CN",
    "gn:dem":17,
    "gn:feature_class":"P",
    "gn:feature_code":"PPL",
    "gn:name":"Xinghuocun",
    "gn:population":0,
    "gn:timezone":"Asia/Shanghai",
    "iso:country":"CN",
    "name:zho_x_preferred":[
        "\u661f\u706b\u6751"
    ],
    "wof:name":"Xinghuocun",
    "wof:placetype":"locality"
},
  "geometry": {"coordinates":[117.74011000000002,31.77429],"type":"Point"}
}