{
  "type": "Feature",
  "properties": {
    "gn:admin1_code":"13",
    "gn:asciiname":"Kendeke",
    "gn:country_code":"CN",
    "gn:dem":171,
    "gn:feature_class":"P",
    "gn:feature_code":"PPL",
    "gn:name":"Kendeke",
    "gn:population":0,
    "gn:timezone":"Asia/Urumqi",
    "iso:country":"CN",
    "name:und_x_variant":[
        "\u80af\u5fb7\u514b"
    ],
    "wof:name":"Kendeke",
    "wof:placetype":"locality"
},
  "geometry": {"coordinates":[88.96548,42.98925],"type":"Point"}
}