{
  "type": "Feature",
  "properties": {
    "gn:admin1_code":"11.0",
    "gn:asciiname":"Beibang",
    "gn:country_code":"CN",
    "gn:dem":173,
    "gn:feature_class":"P",
    "gn:feature_code":"PPL",
    "gn:name":"Beibang",
    "gn:population":0,
    "gn:timezone":"Asia/Shanghai",
    "iso:country":"CN",
    "name:zho_x_preferred":[
        "\u80cc\u90a6"
    ],
    "wof:name":"Beibang",
    "wof:placetype":"locality"
},
  "geometry": {"coordinates":[112.95508999999998,26.09439],"type":"Point"}
}