{
  "type": "Feature",
  "properties": {
    "gn:admin1_code":"15.0",
    "gn:asciiname":"Shanglilin",
    "gn:country_code":"CN",
    "gn:dem":2595,
    "gn:feature_class":"P",
    "gn:feature_code":"PPL",
    "gn:name":"Shanglilin",
    "gn:population":0,
    "gn:timezone":"Asia/Shanghai",
    "iso:country":"CN",
    "name:und_x_variant":[
        "\u4e0a\u7acb\u6797"
    ],
    "wof:name":"Shanglilin",
    "wof:placetype":"locality"
},
  "geometry": {"coordinates":[103.99755,34.29395],"type":"Point"}
}