{
  "type": "Feature",
  "properties": {
    "gn:admin1_code":"30",
    "gn:asciiname":"Shijie",
    "gn:country_code":"CN",
    "gn:dem":252,
    "gn:feature_class":"P",
    "gn:feature_code":"PPL",
    "gn:name":"Shijie",
    "gn:population":0,
    "gn:timezone":"Asia/Shanghai",
    "iso:country":"CN",
    "name:deu_x_preferred":[
        "Shijie"
    ],
    "name:und_x_variant":[
        "\u77f3\u6770"
    ],
    "name:zho_x_preferred":[
        "\u77f3\u6770"
    ],
    "wof:name":"Shijie",
    "wof:placetype":"locality"
},
  "geometry": {"coordinates":[112.39028,23.68778],"type":"Point"}
}