{
  "type": "Feature",
  "properties": {
    "gn:admin1_code":"25.0",
    "gn:asciiname":"Xiagezhuang",
    "gn:cc2":"CN",
    "gn:country_code":"CN",
    "gn:dem":35,
    "gn:feature_class":"P",
    "gn:feature_code":"PPL",
    "gn:name":"Xiagezhuang",
    "gn:population":0,
    "gn:timezone":"Asia/Shanghai",
    "iso:country":"CN",
    "name:und_x_variant":[
        "Hsia-ko-chuang",
        "Xiagezhuang"
    ],
    "wof:name":"Xiagezhuang",
    "wof:placetype":"locality"
},
  "geometry": {"coordinates":[120.43472,36.69306],"type":"Point"}
}