{
  "type": "Feature",
  "properties": {
    "gn:admin1_code":"29.0",
    "gn:asciiname":"Hujiezi",
    "gn:country_code":"CN",
    "gn:dem":1900,
    "gn:feature_class":"P",
    "gn:feature_code":"PPL",
    "gn:name":"Hujiezi",
    "gn:population":0,
    "gn:timezone":"Asia/Shanghai",
    "iso:country":"CN",
    "name:zho_x_preferred":[
        "\u864e\u8857\u5b50"
    ],
    "wof:name":"Hujiezi",
    "wof:placetype":"locality"
},
  "geometry": {"coordinates":[99.8578,24.9929],"type":"Point"}
}