{
  "type": "Feature",
  "properties": {
    "gn:admin1_code":"3.0",
    "gn:asciiname":"Fengjia",
    "gn:country_code":"CN",
    "gn:dem":112,
    "gn:feature_class":"P",
    "gn:feature_code":"PPL",
    "gn:name":"Fengjia",
    "gn:population":0,
    "gn:timezone":"Asia/Shanghai",
    "iso:country":"CN",
    "name:zho_x_preferred":[
        "\u5c01\u5bb6"
    ],
    "wof:name":"Fengjia",
    "wof:placetype":"locality"
},
  "geometry": {"coordinates":[117.88,28.4659],"type":"Point"}
}