{
  "type": "Feature",
  "properties": {
    "gn:admin1_code":"1.0",
    "gn:asciiname":"Yanzhuangcun",
    "gn:country_code":"CN",
    "gn:dem":41,
    "gn:feature_class":"P",
    "gn:feature_code":"PPL",
    "gn:name":"Yanzhuangcun",
    "gn:population":0,
    "gn:timezone":"Asia/Shanghai",
    "iso:country":"CN",
    "name:und_x_variant":[
        "Yanzhuang"
    ],
    "name:zho_x_preferred":[
        "\u960e\u5e84\u6751"
    ],
    "wof:name":"Yanzhuangcun",
    "wof:placetype":"locality"
},
  "geometry": {"coordinates":[115.73333,33.93333],"type":"Point"}
}