{
  "type": "Feature",
  "properties": {
    "gn:admin1_code":"15.0",
    "gn:asciiname":"Honggao'er",
    "gn:country_code":"CN",
    "gn:dem":2833,
    "gn:feature_class":"P",
    "gn:feature_code":"PPL",
    "gn:name":"Honggao\u2019er",
    "gn:population":0,
    "gn:timezone":"Asia/Shanghai",
    "iso:country":"CN",
    "name:und_x_variant":[
        "Honggao\u2019er",
        "\u5b8f\u544a\u5c14"
    ],
    "wof:name":"Honggao'er",
    "wof:placetype":"locality"
},
  "geometry": {"coordinates":[102.68241,35.31895],"type":"Point"}
}