{
  "type": "Feature",
  "properties": {
    "gn:admin1_code":"11.0",
    "gn:asciiname":"Kuzhuchong",
    "gn:country_code":"CN",
    "gn:dem":190,
    "gn:feature_class":"P",
    "gn:feature_code":"PPL",
    "gn:name":"Kuzhuchong",
    "gn:population":0,
    "gn:timezone":"Asia/Shanghai",
    "iso:country":"CN",
    "name:zho_x_preferred":[
        "\u82e6\u7af9\u51b2"
    ],
    "wof:name":"Kuzhuchong",
    "wof:placetype":"locality"
},
  "geometry": {"coordinates":[113.11798,27.24563],"type":"Point"}
}