{
  "type": "Feature",
  "properties": {
    "gn:admin1_code":"3.0",
    "gn:asciiname":"Wushan",
    "gn:country_code":"CN",
    "gn:dem":325,
    "gn:feature_class":"P",
    "gn:feature_code":"PPL",
    "gn:name":"Wushan",
    "gn:population":0,
    "gn:timezone":"Asia/Shanghai",
    "iso:country":"CN",
    "name:zho_x_preferred":[
        "\u68a7\u5c71"
    ],
    "wof:name":"Wushan",
    "wof:placetype":"locality"
},
  "geometry": {"coordinates":[117.18985000000001,27.99638],"type":"Point"}
}