{
  "type": "Feature",
  "properties": {
    "gn:admin1_code":"19.0",
    "gn:asciiname":"Sijiazicun",
    "gn:country_code":"CN",
    "gn:dem":72,
    "gn:feature_class":"P",
    "gn:feature_code":"PPL",
    "gn:name":"Sijiazicun",
    "gn:population":0,
    "gn:timezone":"Asia/Shanghai",
    "iso:country":"CN",
    "name:zho_x_preferred":[
        "\u56db\u5bb6\u5b50\u6751"
    ],
    "wof:name":"Sijiazicun",
    "wof:placetype":"locality"
},
  "geometry": {"coordinates":[122.179,42.0595],"type":"Point"}
}