{
  "type": "Feature",
  "properties": {
    "gn:admin1_code":"18",
    "gn:asciiname":"Baijin",
    "gn:cc2":"CN",
    "gn:country_code":"CN",
    "gn:dem":1227,
    "gn:feature_class":"P",
    "gn:feature_code":"PPL",
    "gn:name":"Baijin",
    "gn:population":0,
    "gn:timezone":"Asia/Shanghai",
    "iso:country":"CN",
    "name:und_x_variant":[
        "Pai-chin",
        "Baijin"
    ],
    "wof:name":"Baijin",
    "wof:placetype":"locality"
},
  "geometry": {"coordinates":[106.81667,26.11667000000001],"type":"Point"}
}