{
  "type": "Feature",
  "properties": {
    "gn:admin1_code":"9",
    "gn:asciiname":"Dongludou",
    "gn:country_code":"CN",
    "gn:dem":57,
    "gn:feature_class":"P",
    "gn:feature_code":"PPL",
    "gn:name":"Dongludou",
    "gn:population":0,
    "gn:timezone":"Asia/Shanghai",
    "iso:country":"CN",
    "name:zho_x_preferred":[
        "\u4e1c\u9e7f\u6597"
    ],
    "wof:name":"Dongludou",
    "wof:placetype":"locality"
},
  "geometry": {"coordinates":[114.93899999999999,35.6431],"type":"Point"}
}