{
  "type": "Feature",
  "properties": {
    "gn:admin1_code":"2",
    "gn:asciiname":"Weiping",
    "gn:country_code":"CN",
    "gn:dem":172,
    "gn:feature_class":"P",
    "gn:feature_code":"PPLA4",
    "gn:name":"Weiping",
    "gn:population":0,
    "gn:timezone":"Asia/Shanghai",
    "iso:country":"CN",
    "name:und_x_variant":[
        "Weiping Zhen",
        "Weiping"
    ],
    "name:zho_x_preferred":[
        "\u5a01\u576a"
    ],
    "name:zho_x_variant":[
        "\u5a01\u576a\u9547"
    ],
    "wof:name":"Weiping",
    "wof:placetype":"locality"
},
  "geometry": {"coordinates":[118.78442,29.72699],"type":"Point"}
}