{
  "type": "Feature",
  "properties": {
    "gn:admin1_code":"26.0",
    "gn:asciiname":"Wulongshan",
    "gn:cc2":"CN",
    "gn:country_code":"CN",
    "gn:dem":1095,
    "gn:feature_class":"P",
    "gn:feature_code":"PPL",
    "gn:name":"Wulongshan",
    "gn:population":0,
    "gn:timezone":"Asia/Shanghai",
    "iso:country":"CN",
    "name:und_x_variant":[
        "Wu-lung-shan",
        "Wulongshan"
    ],
    "wof:name":"Wulongshan",
    "wof:placetype":"locality"
},
  "geometry": {"coordinates":[109.51222,37.96472],"type":"Point"}
}