{
  "type": "Feature",
  "properties": {
    "gn:admin1_code":"26.0",
    "gn:asciiname":"Macuncun",
    "gn:country_code":"CN",
    "gn:dem":756,
    "gn:feature_class":"P",
    "gn:feature_code":"PPL",
    "gn:name":"Macuncun",
    "gn:population":0,
    "gn:timezone":"Asia/Shanghai",
    "iso:country":"CN",
    "name:zho_x_preferred":[
        "\u9a6c\u6751\u6751"
    ],
    "wof:name":"Macuncun",
    "wof:placetype":"locality"
},
  "geometry": {"coordinates":[110.25528,35.36223],"type":"Point"}
}