{
  "type": "Feature",
  "properties": {
    "gn:admin1_code":"14.0",
    "gn:asciiname":"Daqiucun",
    "gn:country_code":"CN",
    "gn:dem":3756,
    "gn:feature_class":"P",
    "gn:feature_code":"PPL",
    "gn:name":"Daqiucun",
    "gn:population":0,
    "gn:timezone":"Asia/Urumqi",
    "iso:country":"CN",
    "name:zho_x_preferred":[
        "\u8fbe\u79cb\u6751"
    ],
    "wof:name":"Daqiucun",
    "wof:placetype":"locality"
},
  "geometry": {"coordinates":[96.4609,30.2126],"type":"Point"}
}