{
  "type": "Feature",
  "properties": {
    "gn:admin1_code":"29.0",
    "gn:asciiname":"Yizimu",
    "gn:country_code":"CN",
    "gn:dem":1880,
    "gn:feature_class":"P",
    "gn:feature_code":"PPL",
    "gn:name":"Yizimu",
    "gn:population":0,
    "gn:timezone":"Asia/Shanghai",
    "iso:country":"CN",
    "name:zho_x_preferred":[
        "\u77e3\u5b50\u6bcd"
    ],
    "wof:name":"Yizimu",
    "wof:placetype":"locality"
},
  "geometry": {"coordinates":[102.081,25.2799],"type":"Point"}
}