{
  "type": "Feature",
  "properties": {
    "gn:admin1_code":"18.0",
    "gn:asciiname":"Yaomi",
    "gn:country_code":"CN",
    "gn:dem":992,
    "gn:feature_class":"P",
    "gn:feature_code":"PPL",
    "gn:name":"Yaomi",
    "gn:population":0,
    "gn:timezone":"Asia/Shanghai",
    "iso:country":"CN",
    "name:zho_x_preferred":[
        "\u5c27\u8ff7"
    ],
    "wof:name":"Yaomi",
    "wof:placetype":"locality"
},
  "geometry": {"coordinates":[107.511,25.6362],"type":"Point"}
}