{
  "type": "Feature",
  "properties": {
    "gn:admin1_code":"9.0",
    "gn:asciiname":"Xichaizhuang",
    "gn:country_code":"CN",
    "gn:dem":781,
    "gn:feature_class":"P",
    "gn:feature_code":"PPL",
    "gn:name":"Xichaizhuang",
    "gn:population":0,
    "gn:timezone":"Asia/Shanghai",
    "iso:country":"CN",
    "name:zho_x_preferred":[
        "\u897f\u67f4\u5e84"
    ],
    "wof:name":"Xichaizhuang",
    "wof:placetype":"locality"
},
  "geometry": {"coordinates":[111.38442999999999,34.21942],"type":"Point"}
}