{
  "type": "Feature",
  "properties": {
    "gn:admin1_code":"15.0",
    "gn:asciiname":"Shifangzi",
    "gn:country_code":"CN",
    "gn:dem":1694,
    "gn:feature_class":"P",
    "gn:feature_code":"PPL",
    "gn:name":"Shifangzi",
    "gn:population":0,
    "gn:timezone":"Asia/Shanghai",
    "iso:country":"CN",
    "name:zho_x_preferred":[
        "\u77f3\u623f\u5b50"
    ],
    "wof:name":"Shifangzi",
    "wof:placetype":"locality"
},
  "geometry": {"coordinates":[104.316,36.757],"type":"Point"}
}