{
  "type": "Feature",
  "properties": {
    "gn:admin1_code":"8.0",
    "gn:asciiname":"Helicun",
    "gn:country_code":"CN",
    "gn:dem":124,
    "gn:feature_class":"P",
    "gn:feature_code":"PPL",
    "gn:name":"Helicun",
    "gn:population":0,
    "gn:timezone":"Asia/Shanghai",
    "iso:country":"CN",
    "name:zho_x_preferred":[
        "\u5408\u529b\u6751"
    ],
    "wof:name":"Helicun",
    "wof:placetype":"locality"
},
  "geometry": {"coordinates":[130.20283000000001,46.26024],"type":"Point"}
}