{
  "type": "Feature",
  "properties": {
    "gn:admin1_code":"3.0",
    "gn:asciiname":"Anshan Ba",
    "gn:country_code":"CN",
    "gn:dem":226,
    "gn:feature_class":"P",
    "gn:feature_code":"PPL",
    "gn:name":"Anshan Ba",
    "gn:population":0,
    "gn:timezone":"Asia/Shanghai",
    "iso:country":"CN",
    "name:und_x_variant":[
        "\u6848\u5c71\u575d"
    ],
    "wof:name":"Anshan Ba",
    "wof:placetype":"locality"
},
  "geometry": {"coordinates":[116.29206000000001,26.64115],"type":"Point"}
}