{
  "type": "Feature",
  "properties": {
    "gn:admin1_code":"14.0",
    "gn:asciiname":"Naishacun",
    "gn:country_code":"CN",
    "gn:dem":3525,
    "gn:feature_class":"P",
    "gn:feature_code":"PPL",
    "gn:name":"Naishacun",
    "gn:population":0,
    "gn:timezone":"Asia/Urumqi",
    "iso:country":"CN",
    "name:zho_x_preferred":[
        "\u4e43\u6c99\u6751"
    ],
    "wof:name":"Naishacun",
    "wof:placetype":"locality"
},
  "geometry": {"coordinates":[97.13198,31.44521],"type":"Point"}
}