{
  "type": "Feature",
  "properties": {
    "gn:admin1_code":"2.0",
    "gn:asciiname":"Xiqingtou",
    "gn:country_code":"CN",
    "gn:dem":555,
    "gn:feature_class":"P",
    "gn:feature_code":"PPL",
    "gn:name":"Xiqingtou",
    "gn:population":0,
    "gn:timezone":"Asia/Shanghai",
    "iso:country":"CN",
    "name:zho_x_preferred":[
        "\u897f\u9752\u5934"
    ],
    "wof:name":"Xiqingtou",
    "wof:placetype":"locality"
},
  "geometry": {"coordinates":[120.00039,28.77999],"type":"Point"}
}