{
  "type": "Feature",
  "properties": {
    "gn:admin1_code":"9",
    "gn:asciiname":"Xiaozhaolou",
    "gn:country_code":"CN",
    "gn:dem":45,
    "gn:feature_class":"P",
    "gn:feature_code":"PPL",
    "gn:name":"Xiaozhaolou",
    "gn:population":0,
    "gn:timezone":"Asia/Shanghai",
    "iso:country":"CN",
    "name:zho_x_preferred":[
        "\u5c0f\u8d75\u697c"
    ],
    "wof:name":"Xiaozhaolou",
    "wof:placetype":"locality"
},
  "geometry": {"coordinates":[115.006,33.6932],"type":"Point"}
}