{
  "type": "Feature",
  "properties": {
    "gn:admin1_code":"14.0",
    "gn:asciiname":"Resong",
    "gn:country_code":"CN",
    "gn:dem":4073,
    "gn:feature_class":"P",
    "gn:feature_code":"PPL",
    "gn:name":"Resong",
    "gn:population":0,
    "gn:timezone":"Asia/Urumqi",
    "iso:country":"CN",
    "name:zho_x_preferred":[
        "\u60f9\u677e"
    ],
    "wof:name":"Resong",
    "wof:placetype":"locality"
},
  "geometry": {"coordinates":[98.01904999999999,31.1963],"type":"Point"}
}