{
  "type": "Feature",
  "properties": {
    "gn:admin1_code":"8.0",
    "gn:asciiname":"Huanghuagou",
    "gn:country_code":"CN",
    "gn:dem":143,
    "gn:feature_class":"P",
    "gn:feature_code":"PPL",
    "gn:name":"Huanghuagou",
    "gn:population":0,
    "gn:timezone":"Asia/Shanghai",
    "iso:country":"CN",
    "name:zho_x_preferred":[
        "\u9ec4\u82b1\u6c9f"
    ],
    "wof:name":"Huanghuagou",
    "wof:placetype":"locality"
},
  "geometry": {"coordinates":[123.95695000000001,46.69409],"type":"Point"}
}