{
  "type": "Feature",
  "properties": {
    "gn:admin1_code":"8.0",
    "gn:asciiname":"Hongshilazi",
    "gn:country_code":"CN",
    "gn:dem":213,
    "gn:feature_class":"P",
    "gn:feature_code":"PPL",
    "gn:name":"Hongshilazi",
    "gn:population":0,
    "gn:timezone":"Asia/Shanghai",
    "iso:country":"CN",
    "name:und_x_variant":[
        "\u7ea2\u77f3\u782c\u5b50"
    ],
    "wof:name":"Hongshilazi",
    "wof:placetype":"locality"
},
  "geometry": {"coordinates":[130.79689999999999,43.99947],"type":"Point"}
}