{
  "type": "Feature",
  "properties": {
    "gn:country":"CN",
    "gn:fcode":"PPL",
    "gn:population":127225,
    "iso:country":"CN",
    "name:eng_x_preferred":[
        "Jiangyou"
    ],
    "name:zho_x_preferred":[
        "\u6c5f\u6cb9\u5e02"
    ],
    "qs:name":"\u6c5f\u6cb9\u5e02",
    "qs:name_adm0":"\u4e2d\u570b",
    "qs:name_adm1":"\u56db\u5ddd\u7701",
    "qs:photos_9k":1,
    "qs:photos_9r":2,
    "qs:photos_all":43,
    "qs:photos_sr":0,
    "qs:placetype":"Town",
    "qs:pop_sr":"9",
    "wof:name":"Jiangyou",
    "wof:placetype":"locality",
    "wof:population":127225
},
  "geometry": {"coordinates":[104.71666999999999,31.76667],"type":"Point"}
}