{
  "type": "Feature",
  "properties": {
    "gn:admin1_code":"15.0",
    "gn:asciiname":"Qinpu",
    "gn:country_code":"CN",
    "gn:dem":1453,
    "gn:feature_class":"P",
    "gn:feature_code":"PPL",
    "gn:name":"Qinpu",
    "gn:population":0,
    "gn:timezone":"Asia/Shanghai",
    "iso:country":"CN",
    "name:zho_x_preferred":[
        "\u79e6\u94fa"
    ],
    "wof:name":"Qinpu",
    "wof:placetype":"locality"
},
  "geometry": {"coordinates":[107.09399999999999,35.613],"type":"Point"}
}