{
  "type": "Feature",
  "properties": {
    "gn:admin1_code":"32.0",
    "gn:asciiname":"Aizishan",
    "gn:country_code":"CN",
    "gn:dem":313,
    "gn:feature_class":"P",
    "gn:feature_code":"PPL",
    "gn:name":"Aizishan",
    "gn:population":0,
    "gn:timezone":"Asia/Shanghai",
    "iso:country":"CN",
    "name:zho_x_preferred":[
        "\u77ee\u5b50\u5c71"
    ],
    "wof:name":"Aizishan",
    "wof:placetype":"locality"
},
  "geometry": {"coordinates":[104.964,28.8667],"type":"Point"}
}