{
  "type": "Feature",
  "properties": {
    "gn:admin1_code":"11.0",
    "gn:asciiname":"Mao'erjie",
    "gn:country_code":"CN",
    "gn:dem":728,
    "gn:feature_class":"P",
    "gn:feature_code":"PPL",
    "gn:name":"Mao\u2019erjie",
    "gn:population":0,
    "gn:timezone":"Asia/Shanghai",
    "iso:country":"CN",
    "name:und_x_variant":[
        "Mao\u2019erjie"
    ],
    "name:zho_x_preferred":[
        "\u732b\u513f\u754c"
    ],
    "wof:name":"Mao'erjie",
    "wof:placetype":"locality"
},
  "geometry": {"coordinates":[110.56729,26.55508],"type":"Point"}
}