{
  "type": "Feature",
  "properties": {
    "gn:admin1_code":"19.0",
    "gn:asciiname":"Wagou",
    "gn:country_code":"CN",
    "gn:dem":262,
    "gn:feature_class":"P",
    "gn:feature_code":"PPL",
    "gn:name":"Wagou",
    "gn:population":0,
    "gn:timezone":"Asia/Shanghai",
    "iso:country":"CN",
    "name:fra_x_preferred":[
        "Wagou"
    ],
    "name:und_x_variant":[
        "\u74e6\u6c9f"
    ],
    "wof:name":"Wagou",
    "wof:placetype":"locality"
},
  "geometry": {"coordinates":[123.77734,40.78918],"type":"Point"}
}