{
  "type": "Feature",
  "properties": {
    "gn:admin1_code":"4.0",
    "gn:asciiname":"Zhadongcun",
    "gn:country_code":"CN",
    "gn:dem":19,
    "gn:feature_class":"P",
    "gn:feature_code":"PPL",
    "gn:name":"Zhadongcun",
    "gn:population":0,
    "gn:timezone":"Asia/Shanghai",
    "iso:country":"CN",
    "name:zho_x_preferred":[
        "\u95f8\u4e1c\u6751"
    ],
    "wof:name":"Zhadongcun",
    "wof:placetype":"locality"
},
  "geometry": {"coordinates":[118.312,33.9852],"type":"Point"}
}