{
  "type": "Feature",
  "properties": {
    "gn:admin1_code":"10",
    "gn:asciiname":"Halagoucun",
    "gn:country_code":"CN",
    "gn:dem":1382,
    "gn:feature_class":"P",
    "gn:feature_code":"PPL",
    "gn:name":"Halagoucun",
    "gn:population":0,
    "gn:timezone":"Asia/Shanghai",
    "iso:country":"CN",
    "name:zho_x_preferred":[
        "\u54c8\u62c9\u6c9f\u6751"
    ],
    "wof:name":"Halagoucun",
    "wof:placetype":"locality"
},
  "geometry": {"coordinates":[113.98917,41.26889],"type":"Point"}
}