{
  "type": "Feature",
  "properties": {
    "gn:admin1_code":"11.0",
    "gn:asciiname":"Longjiangzhai",
    "gn:country_code":"CN",
    "gn:dem":324,
    "gn:feature_class":"P",
    "gn:feature_code":"PPL",
    "gn:name":"Longjiangzhai",
    "gn:population":0,
    "gn:timezone":"Asia/Shanghai",
    "iso:country":"CN",
    "name:zho_x_preferred":[
        "\u9f99\u6c5f\u5be8"
    ],
    "wof:name":"Longjiangzhai",
    "wof:placetype":"locality"
},
  "geometry": {"coordinates":[109.65694000000001,28.40146],"type":"Point"}
}