{
  "type": "Feature",
  "properties": {
    "gn:admin1_code":"29.0",
    "gn:asciiname":"Podaji",
    "gn:country_code":"CN",
    "gn:dem":2151,
    "gn:feature_class":"P",
    "gn:feature_code":"PPL",
    "gn:name":"Podaji",
    "gn:population":0,
    "gn:timezone":"Asia/Shanghai",
    "iso:country":"CN",
    "name:zho_x_preferred":[
        "\u5761\u5927\u5409"
    ],
    "wof:name":"Podaji",
    "wof:placetype":"locality"
},
  "geometry": {"coordinates":[99.75490000000001,24.8216],"type":"Point"}
}