{
  "type": "Feature",
  "properties": {
    "gn:admin1_code":"24",
    "gn:asciiname":"Yukou",
    "gn:country_code":"CN",
    "gn:dem":783,
    "gn:feature_class":"P",
    "gn:feature_code":"PPL",
    "gn:name":"Yukou",
    "gn:population":0,
    "gn:timezone":"Asia/Shanghai",
    "iso:country":"CN",
    "name:zho_x_preferred":[
        "\u592a\u5b50\u79a6\u5bc7"
    ],
    "wof:name":"Yukou",
    "wof:placetype":"locality"
},
  "geometry": {"coordinates":[112.03306000000001,37.50667],"type":"Point"}
}