{
  "type": "Feature",
  "properties": {
    "gn:admin1_code":"16.0",
    "gn:asciiname":"Shangwumei",
    "gn:country_code":"CN",
    "gn:dem":278,
    "gn:feature_class":"P",
    "gn:feature_code":"PPL",
    "gn:name":"Shangwumei",
    "gn:population":0,
    "gn:timezone":"Asia/Shanghai",
    "iso:country":"CN",
    "name:zho_x_preferred":[
        "\u4e0a\u4e4c\u6885"
    ],
    "wof:name":"Shangwumei",
    "wof:placetype":"locality"
},
  "geometry": {"coordinates":[109.444,25.5573],"type":"Point"}
}