{
  "type": "Feature",
  "properties": {
    "gn:admin1_code":"25.0",
    "gn:asciiname":"Longhuya",
    "gn:country_code":"CN",
    "gn:dem":73,
    "gn:feature_class":"P",
    "gn:feature_code":"PPLA4",
    "gn:name":"Longhuya",
    "gn:population":0,
    "gn:timezone":"Asia/Shanghai",
    "iso:country":"CN",
    "name:und_x_variant":[
        "Longhuya Zhen"
    ],
    "name:zho_x_preferred":[
        "\u9f99\u864e\u5d16"
    ],
    "name:zho_x_variant":[
        "\u9f99\u864e\u5d16\u9547"
    ],
    "wof:name":"Longhuya",
    "wof:placetype":"locality"
},
  "geometry": {"coordinates":[119.8693,37.13026],"type":"Point"}
}