{
  "type": "Feature",
  "properties": {
    "gn:admin1_code":"7.0",
    "gn:asciiname":"Longsandong",
    "gn:country_code":"CN",
    "gn:dem":463,
    "gn:feature_class":"P",
    "gn:feature_code":"PPL",
    "gn:name":"Longsandong",
    "gn:population":0,
    "gn:timezone":"Asia/Shanghai",
    "iso:country":"CN",
    "name:zho_x_preferred":[
        "\u9f99\u4f1e\u5cbd"
    ],
    "wof:name":"Longsandong",
    "wof:placetype":"locality"
},
  "geometry": {"coordinates":[117.06111,24.07452],"type":"Point"}
}