{
  "type": "Feature",
  "properties": {
    "gn:admin1_code":"12.0",
    "gn:asciiname":"Niejiachong",
    "gn:country_code":"CN",
    "gn:dem":88,
    "gn:feature_class":"P",
    "gn:feature_code":"PPL",
    "gn:name":"Niejiachong",
    "gn:population":0,
    "gn:timezone":"Asia/Shanghai",
    "iso:country":"CN",
    "name:zho_x_preferred":[
        "Niejiachong"
    ],
    "name:zho_x_variant":[
        "\u8042\u5bb6\u51b2"
    ],
    "wof:name":"Niejiachong",
    "wof:placetype":"locality"
},
  "geometry": {"coordinates":[111.35002,30.4258],"type":"Point"}
}