{
  "type": "Feature",
  "properties": {
    "gn:admin1_code":"12.0",
    "gn:asciiname":"Xinlijia",
    "gn:country_code":"CN",
    "gn:dem":75,
    "gn:feature_class":"P",
    "gn:feature_code":"PPL",
    "gn:name":"Xinlijia",
    "gn:population":0,
    "gn:timezone":"Asia/Shanghai",
    "iso:country":"CN",
    "name:zho_x_preferred":[
        "\u65b0\u674e\u5bb6"
    ],
    "wof:name":"Xinlijia",
    "wof:placetype":"locality"
},
  "geometry": {"coordinates":[114.45744000000001,31.3151],"type":"Point"}
}