{
  "type": "Feature",
  "properties": {
    "gn:admin1_code":"33.0",
    "gn:asciiname":"Luojia",
    "gn:country_code":"CN",
    "gn:dem":885,
    "gn:feature_class":"P",
    "gn:feature_code":"PPL",
    "gn:name":"Luojia",
    "gn:population":0,
    "gn:timezone":"Asia/Shanghai",
    "iso:country":"CN",
    "name:zho_x_preferred":[
        "\u7f57\u5bb6"
    ],
    "wof:name":"Luojia",
    "wof:placetype":"locality"
},
  "geometry": {"coordinates":[107.61100999999999,29.44756],"type":"Point"}
}