{
  "type": "Feature",
  "properties": {
    "gn:admin1_code":"1.0",
    "gn:asciiname":"Xilicun",
    "gn:country_code":"CN",
    "gn:dem":13,
    "gn:feature_class":"P",
    "gn:feature_code":"PPL",
    "gn:name":"Xilicun",
    "gn:population":0,
    "gn:timezone":"Asia/Shanghai",
    "iso:country":"CN",
    "name:zho_x_preferred":[
        "\u5e2d\u674e\u6751"
    ],
    "wof:name":"Xilicun",
    "wof:placetype":"locality"
},
  "geometry": {"coordinates":[118.08710000000001,31.4862],"type":"Point"}
}