{
  "type": "Feature",
  "properties": {
    "gn:admin1_code":"20.0",
    "gn:asciiname":"Hongshi Lazi",
    "gn:country_code":"CN",
    "gn:dem":253,
    "gn:feature_class":"P",
    "gn:feature_code":"PPL",
    "gn:name":"Hongshi Lazi",
    "gn:population":0,
    "gn:timezone":"Asia/Shanghai",
    "iso:country":"CN",
    "name:zho_x_preferred":[
        "\u7ea2\u77f3\u782c\u5b50"
    ],
    "wof:name":"Hongshi Lazi",
    "wof:placetype":"locality"
},
  "geometry": {"coordinates":[124.90481,49.3701],"type":"Point"}
}