{
  "type": "Feature",
  "properties": {
    "gn:admin1_code":"29.0",
    "gn:asciiname":"Wangzan",
    "gn:country_code":"CN",
    "gn:dem":2224,
    "gn:feature_class":"P",
    "gn:feature_code":"PPL",
    "gn:name":"Wangzan",
    "gn:population":0,
    "gn:timezone":"Asia/Shanghai",
    "iso:country":"CN",
    "name:zho_x_preferred":[
        "\u65fa\u54b1"
    ],
    "wof:name":"Wangzan",
    "wof:placetype":"locality"
},
  "geometry": {"coordinates":[99.1151,26.8561],"type":"Point"}
}