{
  "type": "Feature",
  "properties": {
    "gn:admin1_code":"16.0",
    "gn:asciiname":"Guanyi",
    "gn:country_code":"CN",
    "gn:dem":233,
    "gn:feature_class":"P",
    "gn:feature_code":"PPL",
    "gn:name":"Guanyi",
    "gn:population":0,
    "gn:timezone":"Asia/Shanghai",
    "iso:country":"CN",
    "name:zho_x_preferred":[
        "\u7ba1\u4e59"
    ],
    "wof:name":"Guanyi",
    "wof:placetype":"locality"
},
  "geometry": {"coordinates":[108.72199999999999,22.9822],"type":"Point"}
}