{
  "type": "Feature",
  "properties": {
    "gn:admin1_code":"15.0",
    "gn:asciiname":"Zhujiayao",
    "gn:country_code":"CN",
    "gn:dem":2258,
    "gn:feature_class":"P",
    "gn:feature_code":"PPL",
    "gn:name":"Zhujiayao",
    "gn:population":0,
    "gn:timezone":"Asia/Shanghai",
    "iso:country":"CN",
    "name:zho_x_preferred":[
        "\u6731\u5bb6\u7a91"
    ],
    "wof:name":"Zhujiayao",
    "wof:placetype":"locality"
},
  "geometry": {"coordinates":[104.26600000000001,37.0084],"type":"Point"}
}