{
  "type": "Feature",
  "properties": {
    "gn:admin1_code":"3",
    "gn:asciiname":"Weixia",
    "gn:country_code":"CN",
    "gn:dem":188,
    "gn:feature_class":"P",
    "gn:feature_code":"PPL",
    "gn:name":"Weixia",
    "gn:population":0,
    "gn:timezone":"Asia/Shanghai",
    "iso:country":"CN",
    "name:zho_x_preferred":[
        "\u56f4\u4e0b"
    ],
    "wof:name":"Weixia",
    "wof:placetype":"locality"
},
  "geometry": {"coordinates":[114.29900000000001,25.3923],"type":"Point"}
}