{
  "type": "Feature",
  "properties": {
    "gn:admin1_code":"16.0",
    "gn:asciiname":"Dongle",
    "gn:country_code":"CN",
    "gn:dem":282,
    "gn:feature_class":"P",
    "gn:feature_code":"PPL",
    "gn:name":"Dongle",
    "gn:population":0,
    "gn:timezone":"Asia/Shanghai",
    "iso:country":"CN",
    "name:bul_x_preferred":[
        "\u0414\u043e\u043d\u0433\u044a\u043b"
    ],
    "name:dan_x_preferred":[
        "Dongle"
    ],
    "name:est_x_preferred":[
        "Tongel"
    ],
    "name:fas_x_preferred":[
        "\u062f\u0627\u0646\u06af\u0644"
    ],
    "name:fra_x_preferred":[
        "Dongle"
    ],
    "name:jpn_x_preferred":[
        "\u30c9\u30f3\u30b0\u30eb"
    ],
    "name:kan_x_preferred":[
        "\u0ca1\u0cbe\u0c82\u0c97\u0cb2\u0ccd"
    ],
    "name:msa_x_preferred":[
        "Dongle"
    ],
    "name:nld_x_preferred":[
        "Dongle"
    ],
    "name:pan_x_preferred":[
        "\u0a21\u0a4c\u0a02\u0a17\u0a32"
    ],
    "name:spa_x_preferred":[
        "Dongle"
    ],
    "name:swe_x_preferred":[
        "Dongel"
    ],
    "name:tel_x_preferred":[
        "\u0c21\u0c3e\u0c02\u0c17\u0c3f\u0c32\u0c4d"
    ],
    "name:vie_x_preferred":[
        "Dongle"
    ],
    "name:zho_x_preferred":[
        "\u4e1c\u52d2"
    ],
    "wof:name":"Dongle",
    "wof:placetype":"locality"
},
  "geometry": {"coordinates":[108.315,23.651],"type":"Point"}
}