{
  "type": "Feature",
  "properties": {
    "gn:admin1_code":"32.0",
    "gn:asciiname":"Zoumalin",
    "gn:country_code":"CN",
    "gn:dem":1963,
    "gn:feature_class":"P",
    "gn:feature_code":"PPL",
    "gn:name":"Zoumalin",
    "gn:population":0,
    "gn:timezone":"Asia/Shanghai",
    "iso:country":"CN",
    "name:zho_x_preferred":[
        "\u8d70\u9a6c\u6797"
    ],
    "wof:name":"Zoumalin",
    "wof:placetype":"locality"
},
  "geometry": {"coordinates":[103.282,31.1111],"type":"Point"}
}