{
  "type": "Feature",
  "properties": {
    "gn:admin1_code":"14.0",
    "gn:asciiname":"Maba",
    "gn:country_code":"CN",
    "gn:dem":4225,
    "gn:feature_class":"P",
    "gn:feature_code":"PPL",
    "gn:name":"Maba",
    "gn:population":0,
    "gn:timezone":"Asia/Urumqi",
    "iso:country":"CN",
    "name:ceb_x_preferred":[
        "Maba"
    ],
    "name:deu_x_preferred":[
        "Maba"
    ],
    "name:fra_x_preferred":[
        "Maba"
    ],
    "name:mlg_x_preferred":[
        "Maba"
    ],
    "name:rus_x_preferred":[
        "\u041c\u0430\u0431\u0430"
    ],
    "name:swe_x_preferred":[
        "Maba"
    ],
    "name:zho_x_preferred":[
        "\u739b\u5df4"
    ],
    "wof:name":"Maba",
    "wof:placetype":"locality"
},
  "geometry": {"coordinates":[92.09865000000001,29.1126],"type":"Point"}
}