{
  "type": "Feature",
  "properties": {
    "gn:admin1_code":"2.0",
    "gn:asciiname":"Qingshengtang",
    "gn:country_code":"CN",
    "gn:dem":53,
    "gn:feature_class":"P",
    "gn:feature_code":"PPL",
    "gn:name":"Qingshengtang",
    "gn:population":0,
    "gn:timezone":"Asia/Shanghai",
    "iso:country":"CN",
    "name:und_x_variant":[
        "\u6e05\u80dc\u5858",
        "Qingshengtang"
    ],
    "wof:name":"Qingshengtang",
    "wof:placetype":"locality"
},
  "geometry": {"coordinates":[119.38567,29.23495],"type":"Point"}
}