{
  "type": "Feature",
  "properties": {
    "gn:admin1_code":"16.0",
    "gn:asciiname":"Mingxincun",
    "gn:country_code":"CN",
    "gn:dem":101,
    "gn:feature_class":"P",
    "gn:feature_code":"PPL",
    "gn:name":"Mingxincun",
    "gn:population":0,
    "gn:timezone":"Asia/Shanghai",
    "iso:country":"CN",
    "name:zho_x_preferred":[
        "\u660e\u65b0\u6751"
    ],
    "wof:name":"Mingxincun",
    "wof:placetype":"locality"
},
  "geometry": {"coordinates":[108.89700000000001,23.2516],"type":"Point"}
}