{
  "type": "Feature",
  "properties": {
    "gn:admin1_code":"32.0",
    "gn:asciiname":"Daliping",
    "gn:country_code":"CN",
    "gn:dem":707,
    "gn:feature_class":"P",
    "gn:feature_code":"PPL",
    "gn:name":"Daliping",
    "gn:population":0,
    "gn:timezone":"Asia/Shanghai",
    "iso:country":"CN",
    "name:zho_x_preferred":[
        "\u5927\u91cc\u576a"
    ],
    "wof:name":"Daliping",
    "wof:placetype":"locality"
},
  "geometry": {"coordinates":[106.1846,31.96622],"type":"Point"}
}