{
  "type": "Feature",
  "properties": {
    "gn:admin1_code":"29.0",
    "gn:asciiname":"Wanchuhe",
    "gn:country_code":"CN",
    "gn:dem":2504,
    "gn:feature_class":"P",
    "gn:feature_code":"PPL",
    "gn:name":"Wanchuhe",
    "gn:population":0,
    "gn:timezone":"Asia/Shanghai",
    "iso:country":"CN",
    "name:zho_x_preferred":[
        "\u6e7e\u695a\u6cb3"
    ],
    "wof:name":"Wanchuhe",
    "wof:placetype":"locality"
},
  "geometry": {"coordinates":[100.354,26.939],"type":"Point"}
}