{
  "type": "Feature",
  "properties": {
    "gn:admin1_code":"26",
    "gn:asciiname":"Xiwali",
    "gn:country_code":"CN",
    "gn:dem":860,
    "gn:feature_class":"P",
    "gn:feature_code":"PPL",
    "gn:name":"Xiwali",
    "gn:population":0,
    "gn:timezone":"Asia/Shanghai",
    "iso:country":"CN",
    "name:zho_x_preferred":[
        "\u897f\u6d3c\u91cc"
    ],
    "wof:name":"Xiwali",
    "wof:placetype":"locality"
},
  "geometry": {"coordinates":[108.41443999999998,34.62667],"type":"Point"}
}