{
  "type": "Feature",
  "properties": {
    "gn:admin1_code":"12.0",
    "gn:asciiname":"Huaishuwan",
    "gn:country_code":"CN",
    "gn:dem":250,
    "gn:feature_class":"P",
    "gn:feature_code":"PPL",
    "gn:name":"Huaishuwan",
    "gn:population":0,
    "gn:timezone":"Asia/Shanghai",
    "iso:country":"CN",
    "name:zho_x_preferred":[
        "\u69d0\u6811\u6e7e"
    ],
    "wof:name":"Huaishuwan",
    "wof:placetype":"locality"
},
  "geometry": {"coordinates":[111.78457,31.94723],"type":"Point"}
}