{
  "type": "Feature",
  "properties": {
    "gn:admin1_code":"32.0",
    "gn:asciiname":"Changda",
    "gn:country_code":"CN",
    "gn:dem":3242,
    "gn:feature_class":"P",
    "gn:feature_code":"PPL",
    "gn:name":"Changda",
    "gn:population":0,
    "gn:timezone":"Asia/Shanghai",
    "iso:country":"CN",
    "name:zho_x_preferred":[
        "\u660c\u8fbe"
    ],
    "wof:name":"Changda",
    "wof:placetype":"locality"
},
  "geometry": {"coordinates":[100.60599999999999,31.433],"type":"Point"}
}