{
  "type": "Feature",
  "properties": {
    "gn:admin1_code":"26.0",
    "gn:asciiname":"Wenshui",
    "gn:cc2":"CN",
    "gn:country_code":"CN",
    "gn:dem":1012,
    "gn:feature_class":"P",
    "gn:feature_code":"PPL",
    "gn:name":"Wenshui",
    "gn:population":0,
    "gn:timezone":"Asia/Shanghai",
    "iso:country":"CN",
    "name:und_x_variant":[
        "Wen-shui-tien",
        "Wenshui"
    ],
    "wof:name":"Wenshui",
    "wof:placetype":"locality"
},
  "geometry": {"coordinates":[106.81667,34.93333],"type":"Point"}
}