{
  "type": "Feature",
  "properties": {
    "gn:admin1_code":"29.0",
    "gn:asciiname":"Jinpanhe",
    "gn:country_code":"CN",
    "gn:dem":1977,
    "gn:feature_class":"P",
    "gn:feature_code":"PPL",
    "gn:name":"Jinpanhe",
    "gn:population":0,
    "gn:timezone":"Asia/Shanghai",
    "iso:country":"CN",
    "name:zho_x_preferred":[
        "\u91d1\u76d8\u6cb3"
    ],
    "wof:name":"Jinpanhe",
    "wof:placetype":"locality"
},
  "geometry": {"coordinates":[99.4306,25.6208],"type":"Point"}
}