{
  "type": "Feature",
  "properties": {
    "gn:admin1_code":"12.0",
    "gn:asciiname":"Huibaling",
    "gn:country_code":"CN",
    "gn:dem":745,
    "gn:feature_class":"P",
    "gn:feature_code":"PPL",
    "gn:name":"Huibaling",
    "gn:population":0,
    "gn:timezone":"Asia/Shanghai",
    "iso:country":"CN",
    "name:zho_x_preferred":[
        "Huibaling"
    ],
    "name:zho_x_variant":[
        "\u7070\u5df4\u5cad"
    ],
    "wof:name":"Huibaling",
    "wof:placetype":"locality"
},
  "geometry": {"coordinates":[110.03354,29.83753],"type":"Point"}
}