{
  "type": "Feature",
  "properties": {
    "gn:admin1_code":"11.0",
    "gn:asciiname":"Goupadong",
    "gn:country_code":"CN",
    "gn:dem":321,
    "gn:feature_class":"P",
    "gn:feature_code":"PPL",
    "gn:name":"Goupadong",
    "gn:population":0,
    "gn:timezone":"Asia/Shanghai",
    "iso:country":"CN",
    "name:zho_x_preferred":[
        "\u72d7\u8db4\u6d1e"
    ],
    "wof:name":"Goupadong",
    "wof:placetype":"locality"
},
  "geometry": {"coordinates":[110.64761,28.73062],"type":"Point"}
}