{
  "type": "Feature",
  "properties": {
    "gn:admin1_code":"24.0",
    "gn:asciiname":"Jiaoshanyu",
    "gn:country_code":"CN",
    "gn:dem":1455,
    "gn:feature_class":"P",
    "gn:feature_code":"PPL",
    "gn:name":"Jiaoshanyu",
    "gn:population":0,
    "gn:timezone":"Asia/Shanghai",
    "iso:country":"CN",
    "name:zho_x_preferred":[
        "\u4ea4\u5c71\u5cea"
    ],
    "wof:name":"Jiaoshanyu",
    "wof:placetype":"locality"
},
  "geometry": {"coordinates":[111.89601999999999,36.4633],"type":"Point"}
}