{
  "type": "Feature",
  "properties": {
    "gn:admin1_code":"05",
    "gn:asciiname":"Yangmulinzi",
    "gn:country_code":"CN",
    "gn:dem":63,
    "gn:feature_class":"P",
    "gn:feature_code":"PPLA4",
    "gn:name":"Yangmulinzi",
    "gn:population":0,
    "gn:timezone":"Asia/Shanghai",
    "iso:country":"CN",
    "name:und_x_variant":[
        "Yang-mu-lin",
        "Yangpao",
        "Yangpao Manzu Xiang",
        "Yangmulinzi",
        "\u6768\u6728\u6797\u5b50",
        "\u6768\u6ce1\u6ee1\u65cf\u4e61"
    ],
    "wof:name":"Yangmulinzi",
    "wof:placetype":"locality"
},
  "geometry": {"coordinates":[130.49638999999999,42.90222],"type":"Point"}
}