{
  "type": "Feature",
  "properties": {
    "gn:admin1_code":"33.0",
    "gn:asciiname":"Xincun",
    "gn:country_code":"CN",
    "gn:dem":908,
    "gn:feature_class":"P",
    "gn:feature_code":"PPLA4",
    "gn:name":"Xincun",
    "gn:population":0,
    "gn:timezone":"Asia/Shanghai",
    "iso:country":"CN",
    "name:ceb_x_preferred":[
        "Xincun"
    ],
    "name:deu_x_preferred":[
        "Xincun"
    ],
    "name:swe_x_preferred":[
        "Xincun"
    ],
    "name:und_x_variant":[
        "Xincun Xiang"
    ],
    "name:zho_x_preferred":[
        "\u65b0\u6751"
    ],
    "name:zho_x_variant":[
        "\u65b0\u6751\u4e61"
    ],
    "wof:name":"Xincun",
    "wof:placetype":"locality"
},
  "geometry": {"coordinates":[107.06525999999999,29.40699],"type":"Point"}
}