{
  "type": "Feature",
  "properties": {
    "gn:admin1_code":"15.0",
    "gn:asciiname":"Lianjiazhuang",
    "gn:country_code":"CN",
    "gn:dem":1341,
    "gn:feature_class":"P",
    "gn:feature_code":"PPL",
    "gn:name":"Lianjiazhuang",
    "gn:population":0,
    "gn:timezone":"Asia/Shanghai",
    "iso:country":"CN",
    "name:zho_x_preferred":[
        "\u8fde\u5bb6\u5e84"
    ],
    "wof:name":"Lianjiazhuang",
    "wof:placetype":"locality"
},
  "geometry": {"coordinates":[108.08199999999999,35.8647],"type":"Point"}
}