{
  "type": "Feature",
  "properties": {
    "gn:admin1_code":"7",
    "gn:asciiname":"Xingxitou",
    "gn:country_code":"CN",
    "gn:dem":1016,
    "gn:feature_class":"P",
    "gn:feature_code":"PPL",
    "gn:name":"Xingxitou",
    "gn:population":0,
    "gn:timezone":"Asia/Shanghai",
    "iso:country":"CN",
    "name:und_x_variant":[
        "\u661f\u6eaa\u5934"
    ],
    "wof:name":"Xingxitou",
    "wof:placetype":"locality"
},
  "geometry": {"coordinates":[119.11194,27.32528],"type":"Point"}
}