{
  "type": "Feature",
  "properties": {
    "gn:admin1_code":"19.0",
    "gn:asciiname":"Liujiadiancun",
    "gn:country_code":"CN",
    "gn:dem":503,
    "gn:feature_class":"P",
    "gn:feature_code":"PPL",
    "gn:name":"Liujiadiancun",
    "gn:population":0,
    "gn:timezone":"Asia/Shanghai",
    "iso:country":"CN",
    "name:zho_x_preferred":[
        "\u5218\u5bb6\u5e97\u6751"
    ],
    "wof:name":"Liujiadiancun",
    "wof:placetype":"locality"
},
  "geometry": {"coordinates":[120.218,41.799],"type":"Point"}
}