{
  "type": "Feature",
  "properties": {
    "gn:admin1_code":"9.0",
    "gn:asciiname":"Zhangxinzhai",
    "gn:country_code":"CN",
    "gn:dem":127,
    "gn:feature_class":"P",
    "gn:feature_code":"PPL",
    "gn:name":"Zhangxinzhai",
    "gn:population":0,
    "gn:timezone":"Asia/Shanghai",
    "iso:country":"CN",
    "name:zho_x_preferred":[
        "\u5f70\u65b0\u5be8"
    ],
    "wof:name":"Zhangxinzhai",
    "wof:placetype":"locality"
},
  "geometry": {"coordinates":[112.90514,33.07671],"type":"Point"}
}