{
  "type": "Feature",
  "properties": {
    "gn:admin1_code":"30.0",
    "gn:asciiname":"Dazhangwu",
    "gn:country_code":"CN",
    "gn:dem":320,
    "gn:feature_class":"P",
    "gn:feature_code":"PPL",
    "gn:name":"Dazhangwu",
    "gn:population":0,
    "gn:timezone":"Asia/Shanghai",
    "iso:country":"CN",
    "name:zho_x_preferred":[
        "\u5927\u5f20\u5c4b"
    ],
    "wof:name":"Dazhangwu",
    "wof:placetype":"locality"
},
  "geometry": {"coordinates":[113.94432999999999,24.59913],"type":"Point"}
}