{
  "type": "Feature",
  "properties": {
    "gn:admin1_code":"1.0",
    "gn:asciiname":"Duntangcun",
    "gn:country_code":"CN",
    "gn:dem":68,
    "gn:feature_class":"P",
    "gn:feature_code":"PPL",
    "gn:name":"Duntangcun",
    "gn:population":0,
    "gn:timezone":"Asia/Shanghai",
    "iso:country":"CN",
    "name:zho_x_preferred":[
        "\u58a9\u5858\u6751"
    ],
    "wof:name":"Duntangcun",
    "wof:placetype":"locality"
},
  "geometry": {"coordinates":[116.91773000000001,31.80775],"type":"Point"}
}