{
  "type": "Feature",
  "properties": {
    "gn:admin1_code":"12.0",
    "gn:asciiname":"Yinziwuchang",
    "gn:country_code":"CN",
    "gn:dem":424,
    "gn:feature_class":"P",
    "gn:feature_code":"PPL",
    "gn:name":"Yinziwuchang",
    "gn:population":0,
    "gn:timezone":"Asia/Shanghai",
    "iso:country":"CN",
    "name:zho_x_preferred":[
        "\u94f6\u5b50\u5c4b\u573a"
    ],
    "wof:name":"Yinziwuchang",
    "wof:placetype":"locality"
},
  "geometry": {"coordinates":[110.78094,30.34234],"type":"Point"}
}