{
  "type": "Feature",
  "properties": {
    "gn:admin1_code":"19.0",
    "gn:asciiname":"Xudong",
    "gn:country_code":"CN",
    "gn:dem":5,
    "gn:feature_class":"P",
    "gn:feature_code":"PPL",
    "gn:name":"Xudong",
    "gn:population":0,
    "gn:timezone":"Asia/Shanghai",
    "iso:country":"CN",
    "name:und_x_variant":[
        "\u65ed\u4e1c"
    ],
    "wof:name":"Xudong",
    "wof:placetype":"locality"
},
  "geometry": {"coordinates":[122.06019000000001,40.96939],"type":"Point"}
}