{
  "type": "Feature",
  "properties": {
    "gn:admin1_code":"3.0",
    "gn:asciiname":"Dashuinao",
    "gn:country_code":"CN",
    "gn:dem":21,
    "gn:feature_class":"P",
    "gn:feature_code":"PPL",
    "gn:name":"Dashuinao",
    "gn:population":0,
    "gn:timezone":"Asia/Shanghai",
    "iso:country":"CN",
    "name:und_x_variant":[
        "\u5927\u6c34\u8111"
    ],
    "wof:name":"Dashuinao",
    "wof:placetype":"locality"
},
  "geometry": {"coordinates":[116.01090000000001,28.44326],"type":"Point"}
}