{
  "type": "Feature",
  "properties": {
    "gn:admin1_code":"15.0",
    "gn:asciiname":"Jiajia Laoba",
    "gn:country_code":"CN",
    "gn:dem":1985,
    "gn:feature_class":"P",
    "gn:feature_code":"PPL",
    "gn:name":"Jiajia Laoba",
    "gn:population":0,
    "gn:timezone":"Asia/Shanghai",
    "iso:country":"CN",
    "name:zho_x_preferred":[
        "\u8d3e\u5bb6\u6d9d\u575d"
    ],
    "wof:name":"Jiajia Laoba",
    "wof:placetype":"locality"
},
  "geometry": {"coordinates":[105.154,36.3872],"type":"Point"}
}