{
  "type": "Feature",
  "properties": {
    "gn:admin1_code":"18.0",
    "gn:asciiname":"Gaoshan",
    "gn:country_code":"CN",
    "gn:dem":1532,
    "gn:feature_class":"P",
    "gn:feature_code":"PPL",
    "gn:name":"Gaoshan",
    "gn:population":0,
    "gn:timezone":"Asia/Shanghai",
    "iso:country":"CN",
    "name:zho_x_preferred":[
        "\u9ad8\u5c71"
    ],
    "wof:name":"Gaoshan",
    "wof:placetype":"locality"
},
  "geometry": {"coordinates":[105.76900000000001,26.5836],"type":"Point"}
}