{
  "type": "Feature",
  "properties": {
    "gn:admin1_code":"11.0",
    "gn:asciiname":"Xiaohongjiang",
    "gn:country_code":"CN",
    "gn:dem":291,
    "gn:feature_class":"P",
    "gn:feature_code":"PPL",
    "gn:name":"Xiaohongjiang",
    "gn:population":0,
    "gn:timezone":"Asia/Shanghai",
    "iso:country":"CN",
    "name:zho_x_preferred":[
        "\u5c0f\u6d2a\u6c5f"
    ],
    "wof:name":"Xiaohongjiang",
    "wof:placetype":"locality"
},
  "geometry": {"coordinates":[109.986,26.82212],"type":"Point"}
}