{
  "type": "Feature",
  "properties": {
    "gn:admin1_code":"07",
    "gn:asciiname":"Huangzhudun",
    "gn:country_code":"CN",
    "gn:dem":373,
    "gn:feature_class":"P",
    "gn:feature_code":"PPL",
    "gn:name":"Huangzhudun",
    "gn:population":0,
    "gn:timezone":"Asia/Shanghai",
    "iso:country":"CN",
    "name:zho_x_preferred":[
        "\u9ec4\u7af9\u58a9"
    ],
    "wof:name":"Huangzhudun",
    "wof:placetype":"locality"
},
  "geometry": {"coordinates":[116.61256000000002,25.02398],"type":"Point"}
}