{
  "type": "Feature",
  "properties": {
    "gn:admin1_code":"12.0",
    "gn:asciiname":"Daishangpo",
    "gn:country_code":"CN",
    "gn:dem":1412,
    "gn:feature_class":"P",
    "gn:feature_code":"PPL",
    "gn:name":"Daishangpo",
    "gn:population":0,
    "gn:timezone":"Asia/Shanghai",
    "iso:country":"CN",
    "name:zho_x_preferred":[
        "\u6234\u4e0a\u5761"
    ],
    "wof:name":"Daishangpo",
    "wof:placetype":"locality"
},
  "geometry": {"coordinates":[110.93462,31.52563],"type":"Point"}
}