{
  "type": "Feature",
  "properties": {
    "gn:admin1_code":"9.0",
    "gn:asciiname":"Jinmatun",
    "gn:country_code":"CN",
    "gn:dem":142,
    "gn:feature_class":"P",
    "gn:feature_code":"PPL",
    "gn:name":"Jinmatun",
    "gn:population":0,
    "gn:timezone":"Asia/Shanghai",
    "iso:country":"CN",
    "name:zho_x_preferred":[
        "\u91d1\u9a6c\u5c6f"
    ],
    "wof:name":"Jinmatun",
    "wof:placetype":"locality"
},
  "geometry": {"coordinates":[112.6075,33.17975999999999],"type":"Point"}
}