{
  "type": "Feature",
  "properties": {
    "gn:admin1_code":"26",
    "gn:asciiname":"Mazhen",
    "gn:cc2":"CN",
    "gn:country_code":"CN",
    "gn:dem":950,
    "gn:feature_class":"P",
    "gn:feature_code":"PPL",
    "gn:name":"Mazhen",
    "gn:population":0,
    "gn:timezone":"Asia/Shanghai",
    "iso:country":"CN",
    "name:und_x_variant":[
        "Ma-chen",
        "Mazhen"
    ],
    "wof:name":"Mazhen",
    "wof:placetype":"locality"
},
  "geometry": {"coordinates":[110.86028,38.6575],"type":"Point"}
}