{
  "type": "Feature",
  "properties": {
    "gn:admin1_code":"29.0",
    "gn:asciiname":"Jilada",
    "gn:country_code":"CN",
    "gn:dem":2190,
    "gn:feature_class":"P",
    "gn:feature_code":"PPL",
    "gn:name":"Jilada",
    "gn:population":0,
    "gn:timezone":"Asia/Shanghai",
    "iso:country":"CN",
    "name:zho_x_preferred":[
        "\u5409\u62c9\u8fbe"
    ],
    "wof:name":"Jilada",
    "wof:placetype":"locality"
},
  "geometry": {"coordinates":[99.25700000000001,27.9199],"type":"Point"}
}