{
  "type": "Feature",
  "properties": {
    "gn:admin1_code":"11.0",
    "gn:asciiname":"Donghe",
    "gn:country_code":"CN",
    "gn:dem":30,
    "gn:feature_class":"P",
    "gn:feature_code":"PPL",
    "gn:name":"Donghe",
    "gn:population":0,
    "gn:timezone":"Asia/Shanghai",
    "iso:country":"CN",
    "name:ceb_x_preferred":[
        "Donghe"
    ],
    "name:deu_x_preferred":[
        "Donghe"
    ],
    "name:zho_x_preferred":[
        "\u4e1c\u5408"
    ],
    "wof:name":"Donghe",
    "wof:placetype":"locality"
},
  "geometry": {"coordinates":[112.4933,28.9527],"type":"Point"}
}