{
  "type": "Feature",
  "properties": {
    "gn:admin1_code":"4.0",
    "gn:asciiname":"Fengshou Hezhuang",
    "gn:country_code":"CN",
    "gn:dem":11,
    "gn:feature_class":"P",
    "gn:feature_code":"PPL",
    "gn:name":"Fengshou Hezhuang",
    "gn:population":0,
    "gn:timezone":"Asia/Shanghai",
    "iso:country":"CN",
    "name:zho_x_preferred":[
        "\u4e30\u6536\u6cb3\u5e84"
    ],
    "wof:name":"Fengshou Hezhuang",
    "wof:placetype":"locality"
},
  "geometry": {"coordinates":[119.12244,32.93213],"type":"Point"}
}