{
  "type": "Feature",
  "properties": {
    "gn:admin1_code":"3.0",
    "gn:asciiname":"Dongkengwu",
    "gn:country_code":"CN",
    "gn:dem":188,
    "gn:feature_class":"P",
    "gn:feature_code":"PPL",
    "gn:name":"Dongkengwu",
    "gn:population":0,
    "gn:timezone":"Asia/Shanghai",
    "iso:country":"CN",
    "name:zho_x_preferred":[
        "\u4e1c\u5751\u575e"
    ],
    "wof:name":"Dongkengwu",
    "wof:placetype":"locality"
},
  "geometry": {"coordinates":[118.31104000000001,28.58178],"type":"Point"}
}