{
  "type": "Feature",
  "properties": {
    "gn:admin1_code":"11.0",
    "gn:asciiname":"Zhushantou",
    "gn:country_code":"CN",
    "gn:dem":158,
    "gn:feature_class":"P",
    "gn:feature_code":"PPL",
    "gn:name":"Zhushantou",
    "gn:population":0,
    "gn:timezone":"Asia/Shanghai",
    "iso:country":"CN",
    "name:zho_x_preferred":[
        "\u6731\u5c71\u5934"
    ],
    "wof:name":"Zhushantou",
    "wof:placetype":"locality"
},
  "geometry": {"coordinates":[113.25006999999999,26.19225],"type":"Point"}
}