{
  "type": "Feature",
  "properties": {
    "gn:admin1_code":"32.0",
    "gn:asciiname":"Ajizuo",
    "gn:country_code":"CN",
    "gn:dem":2523,
    "gn:feature_class":"P",
    "gn:feature_code":"PPL",
    "gn:name":"Ajizuo",
    "gn:population":0,
    "gn:timezone":"Asia/Shanghai",
    "iso:country":"CN",
    "name:zho_x_preferred":[
        "\u963f\u51e0\u5750"
    ],
    "wof:name":"Ajizuo",
    "wof:placetype":"locality"
},
  "geometry": {"coordinates":[102.405,27.696],"type":"Point"}
}