{
  "type": "Feature",
  "properties": {
    "gn:admin1_code":"19.0",
    "gn:asciiname":"Suntuncun",
    "gn:country_code":"CN",
    "gn:dem":23,
    "gn:feature_class":"P",
    "gn:feature_code":"PPL",
    "gn:name":"Suntuncun",
    "gn:population":0,
    "gn:timezone":"Asia/Shanghai",
    "iso:country":"CN",
    "name:zho_x_preferred":[
        "\u5b59\u5c6f\u6751"
    ],
    "wof:name":"Suntuncun",
    "wof:placetype":"locality"
},
  "geometry": {"coordinates":[122.142,41.7081],"type":"Point"}
}