{
  "type": "Feature",
  "properties": {
    "gn:admin1_code":"07",
    "gn:asciiname":"Xiaoxidao",
    "gn:country_code":"CN",
    "gn:dem":272,
    "gn:feature_class":"P",
    "gn:feature_code":"PPL",
    "gn:name":"Xiaoxidao",
    "gn:population":0,
    "gn:timezone":"Asia/Shanghai",
    "iso:country":"CN",
    "name:zho_x_preferred":[
        "\u5c0f\u6eaa\u5230"
    ],
    "wof:name":"Xiaoxidao",
    "wof:placetype":"locality"
},
  "geometry": {"coordinates":[117.07946,25.76692],"type":"Point"}
}