{
  "type": "Feature",
  "properties": {
    "gn:admin1_code":"20.0",
    "gn:asciiname":"Yaozimian",
    "gn:country_code":"CN",
    "gn:dem":1306,
    "gn:feature_class":"P",
    "gn:feature_code":"PPL",
    "gn:name":"Yaozimian",
    "gn:population":0,
    "gn:timezone":"Asia/Shanghai",
    "iso:country":"CN",
    "name:und_x_variant":[
        "\u7a91\u5b50\u514d"
    ],
    "wof:name":"Yaozimian",
    "wof:placetype":"locality"
},
  "geometry": {"coordinates":[111.52358,40.09353],"type":"Point"}
}