{
  "type": "Feature",
  "properties": {
    "gn:admin1_code":"11.0",
    "gn:asciiname":"Shengjing'an",
    "gn:country_code":"CN",
    "gn:dem":81,
    "gn:feature_class":"P",
    "gn:feature_code":"PPL",
    "gn:name":"Shengjing\u2019an",
    "gn:population":0,
    "gn:timezone":"Asia/Shanghai",
    "iso:country":"CN",
    "name:und_x_variant":[
        "Shengjing\u2019an"
    ],
    "name:zho_x_preferred":[
        "\u5723\u4e95\u5eb5"
    ],
    "wof:name":"Shengjing'an",
    "wof:placetype":"locality"
},
  "geometry": {"coordinates":[112.19185,28.66907],"type":"Point"}
}