{
  "type": "Feature",
  "properties": {
    "gn:admin1_code":"12.0",
    "gn:asciiname":"Xincaobu",
    "gn:country_code":"CN",
    "gn:dem":47,
    "gn:feature_class":"P",
    "gn:feature_code":"PPL",
    "gn:name":"Xincaobu",
    "gn:population":0,
    "gn:timezone":"Asia/Shanghai",
    "iso:country":"CN",
    "name:zho_x_preferred":[
        "Xincaobu"
    ],
    "name:zho_x_variant":[
        "\u65b0\u8349\u57e0"
    ],
    "wof:name":"Xincaobu",
    "wof:placetype":"locality"
},
  "geometry": {"coordinates":[111.89874,30.55412],"type":"Point"}
}