{
  "type": "Feature",
  "properties": {
    "gn:admin1_code":"15.0",
    "gn:asciiname":"Laojiashan",
    "gn:country_code":"CN",
    "gn:dem":2405,
    "gn:feature_class":"P",
    "gn:feature_code":"PPL",
    "gn:name":"Laojiashan",
    "gn:population":0,
    "gn:timezone":"Asia/Shanghai",
    "iso:country":"CN",
    "name:und_x_variant":[
        "\u8001\u5bb6\u5c71"
    ],
    "wof:name":"Laojiashan",
    "wof:placetype":"locality"
},
  "geometry": {"coordinates":[104.58996,34.14536],"type":"Point"}
}