{
  "type": "Feature",
  "properties": {
    "gn:admin1_code":"26",
    "gn:asciiname":"Dongzhugan",
    "gn:country_code":"CN",
    "gn:dem":869,
    "gn:feature_class":"P",
    "gn:feature_code":"PPL",
    "gn:name":"Dongzhugan",
    "gn:population":0,
    "gn:timezone":"Asia/Shanghai",
    "iso:country":"CN",
    "name:und_x_variant":[
        "\u4e1c\u6ce8\u6cd4"
    ],
    "name:zho_x_preferred":[
        "\u4e1c\u6ce8\u6cd4"
    ],
    "wof:name":"Dongzhugan",
    "wof:placetype":"locality"
},
  "geometry": {"coordinates":[108.32306,34.64278],"type":"Point"}
}