{
  "type": "Feature",
  "properties": {
    "gn:admin1_code":"19.0",
    "gn:asciiname":"Jingxintun",
    "gn:country_code":"CN",
    "gn:dem":360,
    "gn:feature_class":"P",
    "gn:feature_code":"PPL",
    "gn:name":"Jingxintun",
    "gn:population":0,
    "gn:timezone":"Asia/Shanghai",
    "iso:country":"CN",
    "name:und_x_variant":[
        "\u666f\u65b0\u5c6f"
    ],
    "name:zho_x_preferred":[
        "\u666f\u65b0\u5c6f"
    ],
    "wof:name":"Jingxintun",
    "wof:placetype":"locality"
},
  "geometry": {"coordinates":[125.04557,42.47981],"type":"Point"}
}