{
  "type": "Feature",
  "properties": {
    "gn:admin1_code":"5.0",
    "gn:asciiname":"Fengchengcun",
    "gn:country_code":"CN",
    "gn:dem":544,
    "gn:feature_class":"P",
    "gn:feature_code":"PPL",
    "gn:name":"Fengchengcun",
    "gn:population":0,
    "gn:timezone":"Asia/Shanghai",
    "iso:country":"CN",
    "name:zho_x_preferred":[
        "\u4e30\u6210\u6751"
    ],
    "wof:name":"Fengchengcun",
    "wof:placetype":"locality"
},
  "geometry": {"coordinates":[128.15646999999998,43.36765],"type":"Point"}
}