{
  "type": "Feature",
  "properties": {
    "gn:admin1_code":"29.0",
    "gn:asciiname":"Mianyangshan",
    "gn:country_code":"CN",
    "gn:dem":1373,
    "gn:feature_class":"P",
    "gn:feature_code":"PPL",
    "gn:name":"Mianyangshan",
    "gn:population":0,
    "gn:timezone":"Asia/Shanghai",
    "iso:country":"CN",
    "name:zho_x_preferred":[
        "\u68c9\u7f8a\u5c71"
    ],
    "wof:name":"Mianyangshan",
    "wof:placetype":"locality"
},
  "geometry": {"coordinates":[101.42,22.869],"type":"Point"}
}