{
  "type": "Feature",
  "properties": {
    "gn:admin1_code":"6.0",
    "gn:asciiname":"Zhongtiegou",
    "gn:country_code":"CN",
    "gn:dem":3080,
    "gn:feature_class":"P",
    "gn:feature_code":"PPL",
    "gn:name":"Zhongtiegou",
    "gn:population":0,
    "gn:timezone":"Asia/Shanghai",
    "iso:country":"CN",
    "name:und_x_variant":[
        "\u4e2d\u94c1\u6c9f"
    ],
    "wof:name":"Zhongtiegou",
    "wof:placetype":"locality"
},
  "geometry": {"coordinates":[100.13876,35.00806],"type":"Point"}
}