{
  "type": "Feature",
  "properties": {
    "gn:admin1_code":"30.0",
    "gn:asciiname":"Niuzaitian",
    "gn:country_code":"CN",
    "gn:dem":85,
    "gn:feature_class":"P",
    "gn:feature_code":"PPL",
    "gn:name":"Niuzaitian",
    "gn:population":0,
    "gn:timezone":"Asia/Shanghai",
    "iso:country":"CN",
    "name:zho_x_preferred":[
        "\u725b\u4ed4\u7530"
    ],
    "wof:name":"Niuzaitian",
    "wof:placetype":"locality"
},
  "geometry": {"coordinates":[114.99281000000001,23.92123],"type":"Point"}
}