{
  "type": "Feature",
  "properties": {
    "gn:admin1_code":"29.0",
    "gn:asciiname":"Mankang",
    "gn:country_code":"CN",
    "gn:dem":855,
    "gn:feature_class":"P",
    "gn:feature_code":"PPL",
    "gn:name":"Mankang",
    "gn:population":0,
    "gn:timezone":"Asia/Shanghai",
    "iso:country":"CN",
    "name:zho_x_preferred":[
        "\u86ee\u6297"
    ],
    "wof:name":"Mankang",
    "wof:placetype":"locality"
},
  "geometry": {"coordinates":[101.239,23.2775],"type":"Point"}
}