{
  "type": "Feature",
  "properties": {
    "gn:admin1_code":"7",
    "gn:asciiname":"Magu'an",
    "gn:country_code":"CN",
    "gn:dem":35,
    "gn:feature_class":"P",
    "gn:feature_code":"PPL",
    "gn:name":"Magu\u2019an",
    "gn:population":0,
    "gn:timezone":"Asia/Shanghai",
    "iso:country":"CN",
    "name:zho_x_preferred":[
        "Magu\u2019an"
    ],
    "wof:name":"Magu'an",
    "wof:placetype":"locality"
},
  "geometry": {"coordinates":[117.09081,23.76568],"type":"Point"}
}