{
  "type": "Feature",
  "properties": {
    "gn:admin1_code":"21.0",
    "gn:asciiname":"Wanyazi",
    "gn:country_code":"CN",
    "gn:dem":1885,
    "gn:feature_class":"P",
    "gn:feature_code":"PPL",
    "gn:name":"Wanyazi",
    "gn:population":0,
    "gn:timezone":"Asia/Shanghai",
    "iso:country":"CN",
    "name:zho_x_preferred":[
        "\u4e07\u5d16\u5b50"
    ],
    "wof:name":"Wanyazi",
    "wof:placetype":"locality"
},
  "geometry": {"coordinates":[106.205,35.9705],"type":"Point"}
}