{
  "type": "Feature",
  "properties": {
    "gn:admin1_code":"3.0",
    "gn:asciiname":"Yangkou",
    "gn:cc2":"CN",
    "gn:country_code":"CN",
    "gn:dem":90,
    "gn:feature_class":"P",
    "gn:feature_code":"PPL",
    "gn:name":"Yangkou",
    "gn:population":0,
    "gn:timezone":"Asia/Shanghai",
    "iso:country":"CN",
    "name:und_x_variant":[
        "Yangko",
        "Yangkou"
    ],
    "wof:name":"Yangkou",
    "wof:placetype":"locality"
},
  "geometry": {"coordinates":[118.09999999999999,28.38333],"type":"Point"}
}