{
  "type": "Feature",
  "properties": {
    "gn:admin1_code":"4.0",
    "gn:asciiname":"Gongtang",
    "gn:country_code":"CN",
    "gn:dem":29,
    "gn:feature_class":"P",
    "gn:feature_code":"PPL",
    "gn:name":"Gongtang",
    "gn:population":0,
    "gn:timezone":"Asia/Shanghai",
    "iso:country":"CN",
    "name:ceb_x_preferred":[
        "Gongtang"
    ],
    "name:fas_x_preferred":[
        "\u06af\u0648\u0646\u06af\u062a\u0627\u0646\u06af"
    ],
    "name:msa_x_preferred":[
        "Gongtang"
    ],
    "name:swe_x_preferred":[
        "Gongtang"
    ],
    "name:zho_x_preferred":[
        "\u516c\u5858"
    ],
    "name:zho_x_variant":[
        "\u516c\u5858\u4e61"
    ],
    "wof:name":"Gongtang",
    "wof:placetype":"locality"
},
  "geometry": {"coordinates":[118.70312,31.8125],"type":"Point"}
}