{
  "type": "Feature",
  "properties": {
    "gn:admin1_code":"19.0",
    "gn:asciiname":"Yibaihu",
    "gn:country_code":"CN",
    "gn:dem":26,
    "gn:feature_class":"P",
    "gn:feature_code":"PPL",
    "gn:name":"Yibaihu",
    "gn:population":0,
    "gn:timezone":"Asia/Shanghai",
    "iso:country":"CN",
    "name:zho_x_preferred":[
        "\u58f9\u767e\u6237"
    ],
    "wof:name":"Yibaihu",
    "wof:placetype":"locality"
},
  "geometry": {"coordinates":[121.19432999999999,41.16462],"type":"Point"}
}