{
  "type": "Feature",
  "properties": {
    "gn:admin1_code":"32.0",
    "gn:asciiname":"Yinjia Miaozi",
    "gn:country_code":"CN",
    "gn:dem":517,
    "gn:feature_class":"P",
    "gn:feature_code":"PPL",
    "gn:name":"Yinjia Miaozi",
    "gn:population":0,
    "gn:timezone":"Asia/Shanghai",
    "iso:country":"CN",
    "name:zho_x_preferred":[
        "\u5c39\u5bb6\u5e99\u5b50"
    ],
    "wof:name":"Yinjia Miaozi",
    "wof:placetype":"locality"
},
  "geometry": {"coordinates":[104.316,31.1981],"type":"Point"}
}