{
  "type": "Feature",
  "properties": {
    "gn:admin1_code":"18.0",
    "gn:asciiname":"Pingba",
    "gn:country_code":"CN",
    "gn:dem":2080,
    "gn:feature_class":"P",
    "gn:feature_code":"PPL",
    "gn:name":"Pingba",
    "gn:population":0,
    "gn:timezone":"Asia/Shanghai",
    "iso:country":"CN",
    "wof:name":"Pingba",
    "wof:placetype":"locality"
},
  "geometry": {"coordinates":[104.90833000000001,26.66667],"type":"Point"}
}