{
  "type": "Feature",
  "properties": {
    "gn:admin1_code":"29.0",
    "gn:asciiname":"Tiandeng",
    "gn:country_code":"CN",
    "gn:dem":2277,
    "gn:feature_class":"P",
    "gn:feature_code":"PPL",
    "gn:name":"Tiandeng",
    "gn:population":0,
    "gn:timezone":"Asia/Shanghai",
    "iso:country":"CN",
    "name:zho_x_preferred":[
        "\u5929\u767b"
    ],
    "wof:name":"Tiandeng",
    "wof:placetype":"locality"
},
  "geometry": {"coordinates":[99.34399999999999,26.1048],"type":"Point"}
}