{
  "type": "Feature",
  "properties": {
    "gn:admin1_code":"7.0",
    "gn:asciiname":"Niuyang",
    "gn:country_code":"CN",
    "gn:dem":851,
    "gn:feature_class":"P",
    "gn:feature_code":"PPL",
    "gn:name":"Niuyang",
    "gn:population":0,
    "gn:timezone":"Asia/Shanghai",
    "iso:country":"CN",
    "name:zho_x_preferred":[
        "\u725b\u4ef0"
    ],
    "wof:name":"Niuyang",
    "wof:placetype":"locality"
},
  "geometry": {"coordinates":[118.03677999999999,27.89071],"type":"Point"}
}