{
  "type": "Feature",
  "properties": {
    "gn:admin1_code":"25",
    "gn:asciiname":"Jiuxianyijie",
    "gn:country_code":"CN",
    "gn:dem":71,
    "gn:feature_class":"P",
    "gn:feature_code":"PPL",
    "gn:name":"Jiuxianyijie",
    "gn:population":0,
    "gn:timezone":"Asia/Shanghai",
    "iso:country":"CN",
    "name:zho_x_preferred":[
        "\u65e7\u53bf\u4e00\u8857"
    ],
    "wof:name":"Jiuxianyijie",
    "wof:placetype":"locality"
},
  "geometry": {"coordinates":[117.02800000000001,35.6019],"type":"Point"}
}