{
  "type": "Feature",
  "properties": {
    "gn:admin1_code":"8.0",
    "gn:asciiname":"Xinantun",
    "gn:country_code":"CN",
    "gn:dem":102,
    "gn:feature_class":"P",
    "gn:feature_code":"PPL",
    "gn:name":"Xinantun",
    "gn:population":0,
    "gn:timezone":"Asia/Shanghai",
    "iso:country":"CN",
    "name:zho_x_preferred":[
        "\u897f\u5357\u5c6f"
    ],
    "wof:name":"Xinantun",
    "wof:placetype":"locality"
},
  "geometry": {"coordinates":[128.97225,45.94355],"type":"Point"}
}