{
  "type": "Feature",
  "properties": {
    "gn:admin1_code":"02",
    "gn:asciiname":"Zhourang",
    "gn:country_code":"CN",
    "gn:dem":378,
    "gn:feature_class":"P",
    "gn:feature_code":"PPL",
    "gn:name":"Zhourang",
    "gn:population":0,
    "gn:timezone":"Asia/Shanghai",
    "iso:country":"CN",
    "name:und_x_variant":[
        "Darang",
        "Zhourang"
    ],
    "name:zho_x_preferred":[
        "\u5468\u58e4"
    ],
    "name:zho_x_variant":[
        "\u5927\u58e4"
    ],
    "wof:name":"Zhourang",
    "wof:placetype":"locality"
},
  "geometry": {"coordinates":[120.13437,27.82915],"type":"Point"}
}