{
  "type": "Feature",
  "properties": {
    "gn:admin1_code":"29.0",
    "gn:asciiname":"Yangjie",
    "gn:country_code":"CN",
    "gn:dem":1525,
    "gn:feature_class":"P",
    "gn:feature_code":"PPL",
    "gn:name":"Yangjie",
    "gn:population":0,
    "gn:timezone":"Asia/Shanghai",
    "iso:country":"CN",
    "name:zho_x_preferred":[
        "\u7f8a\u8857"
    ],
    "wof:name":"Yangjie",
    "wof:placetype":"locality"
},
  "geometry": {"coordinates":[104.355,23.6048],"type":"Point"}
}