{
  "type": "Feature",
  "properties": {
    "gn:admin1_code":"26.0",
    "gn:asciiname":"Chafangcun",
    "gn:country_code":"CN",
    "gn:dem":529,
    "gn:feature_class":"P",
    "gn:feature_code":"PPL",
    "gn:name":"Chafangcun",
    "gn:population":0,
    "gn:timezone":"Asia/Shanghai",
    "iso:country":"CN",
    "name:und_x_variant":[
        "\u8336\u574a\u6751"
    ],
    "wof:name":"Chafangcun",
    "wof:placetype":"locality"
},
  "geometry": {"coordinates":[107.73271,33.19342],"type":"Point"}
}