{
  "type": "Feature",
  "properties": {
    "gn:admin1_code":"29.0",
    "gn:asciiname":"Xiaolong",
    "gn:country_code":"CN",
    "gn:dem":1421,
    "gn:feature_class":"P",
    "gn:feature_code":"PPL",
    "gn:name":"Xiaolong",
    "gn:population":0,
    "gn:timezone":"Asia/Shanghai",
    "iso:country":"CN",
    "name:zho_x_preferred":[
        "\u5c0f\u9f99"
    ],
    "wof:name":"Xiaolong",
    "wof:placetype":"locality"
},
  "geometry": {"coordinates":[103.858,23.5599],"type":"Point"}
}