{
  "type": "Feature",
  "properties": {
    "gn:admin1_code":"30",
    "gn:asciiname":"Pingshan",
    "gn:country_code":"CN",
    "gn:dem":45,
    "gn:feature_class":"P",
    "gn:feature_code":"PPLA4",
    "gn:name":"Pingshan",
    "gn:population":0,
    "gn:timezone":"Asia/Shanghai",
    "iso:country":"CN",
    "name:ceb_x_preferred":[
        "Pingshan"
    ],
    "name:deu_x_preferred":[
        "Pingshan"
    ],
    "name:fra_x_preferred":[
        "Pingshan"
    ],
    "name:mlg_x_preferred":[
        "Pingshan"
    ],
    "name:nor_x_preferred":[
        "Pingshan"
    ],
    "name:rus_x_preferred":[
        "\u041f\u0438\u043d\u0448\u0430\u043d\u044c"
    ],
    "name:swe_x_preferred":[
        "Pingshan"
    ],
    "name:und_x_variant":[
        "P\u2019ing-shan-hs\u00fc",
        "Phyungsan",
        "Pingshan Jiedao",
        "\u576a\u5c71\u8857\u9053"
    ],
    "name:zho_x_preferred":[
        "\u576a\u5c71"
    ],
    "wof:name":"Pingshan",
    "wof:placetype":"locality"
},
  "geometry": {"coordinates":[114.33463,22.69396],"type":"Point"}
}