{
  "type": "Feature",
  "properties": {
    "gn:admin1_code":"7",
    "gn:asciiname":"Dongshanxia",
    "gn:country_code":"CN",
    "gn:dem":159,
    "gn:feature_class":"P",
    "gn:feature_code":"PPL",
    "gn:name":"Dongshanxia",
    "gn:population":0,
    "gn:timezone":"Asia/Shanghai",
    "iso:country":"CN",
    "name:zho_x_preferred":[
        "\u51bb\u5c71\u4e0b"
    ],
    "wof:name":"Dongshanxia",
    "wof:placetype":"locality"
},
  "geometry": {"coordinates":[118.63361,27.11306],"type":"Point"}
}