{
  "type": "Feature",
  "properties": {
    "gn:admin1_code":"12",
    "gn:asciiname":"Weijiadian",
    "gn:country_code":"CN",
    "gn:dem":66,
    "gn:feature_class":"P",
    "gn:feature_code":"PPL",
    "gn:name":"Weijiadian",
    "gn:population":0,
    "gn:timezone":"Asia/Shanghai",
    "iso:country":"CN",
    "name:und_x_variant":[
        "Wei-chia-tien",
        "Weidian",
        "Weijiadian",
        "\u9b4f\u5bb6\u5e97"
    ],
    "wof:name":"Weijiadian",
    "wof:placetype":"locality"
},
  "geometry": {"coordinates":[113.78079,31.17101],"type":"Point"}
}