{
  "type": "Feature",
  "properties": {
    "gn:admin1_code":"8.0",
    "gn:asciiname":"Lengjiadian",
    "gn:country_code":"CN",
    "gn:dem":176,
    "gn:feature_class":"P",
    "gn:feature_code":"PPL",
    "gn:name":"Lengjiadian",
    "gn:population":0,
    "gn:timezone":"Asia/Shanghai",
    "iso:country":"CN",
    "name:zho_x_preferred":[
        "\u51b7\u5bb6\u5e97"
    ],
    "wof:name":"Lengjiadian",
    "wof:placetype":"locality"
},
  "geometry": {"coordinates":[125.02331,47.74871],"type":"Point"}
}