{
  "type": "Feature",
  "properties": {
    "gn:admin1_code":"15.0",
    "gn:asciiname":"Huoshenmiao",
    "gn:country_code":"CN",
    "gn:dem":1189,
    "gn:feature_class":"P",
    "gn:feature_code":"PPL",
    "gn:name":"Huoshenmiao",
    "gn:population":0,
    "gn:timezone":"Asia/Shanghai",
    "iso:country":"CN",
    "name:und_x_variant":[
        "\u706b\u795e\u5e99"
    ],
    "wof:name":"Huoshenmiao",
    "wof:placetype":"locality"
},
  "geometry": {"coordinates":[106.29085000000001,34.04227],"type":"Point"}
}