{
  "type": "Feature",
  "properties": {
    "gn:admin1_code":"9.0",
    "gn:asciiname":"Xiaowang Budaigou",
    "gn:country_code":"CN",
    "gn:dem":613,
    "gn:feature_class":"P",
    "gn:feature_code":"PPL",
    "gn:name":"Xiaowang Budaigou",
    "gn:population":0,
    "gn:timezone":"Asia/Shanghai",
    "iso:country":"CN",
    "name:zho_x_preferred":[
        "\u5c0f\u738b\u5e03\u888b\u6c9f"
    ],
    "wof:name":"Xiaowang Budaigou",
    "wof:placetype":"locality"
},
  "geometry": {"coordinates":[111.73956,33.95718],"type":"Point"}
}