{
  "type": "Feature",
  "properties": {
    "gn:admin1_code":"32.0",
    "gn:asciiname":"Shipang",
    "gn:country_code":"CN",
    "gn:dem":2964,
    "gn:feature_class":"P",
    "gn:feature_code":"PPL",
    "gn:name":"Shipang",
    "gn:population":0,
    "gn:timezone":"Asia/Shanghai",
    "iso:country":"CN",
    "name:zho_x_preferred":[
        "\u77f3\u65c1"
    ],
    "wof:name":"Shipang",
    "wof:placetype":"locality"
},
  "geometry": {"coordinates":[101.621,31.8186],"type":"Point"}
}