{
  "type": "Feature",
  "properties": {
    "gn:admin1_code":"1.0",
    "gn:asciiname":"Xinjingcun",
    "gn:country_code":"CN",
    "gn:dem":39,
    "gn:feature_class":"P",
    "gn:feature_code":"PPL",
    "gn:name":"Xinjingcun",
    "gn:population":0,
    "gn:timezone":"Asia/Shanghai",
    "iso:country":"CN",
    "name:zho_x_preferred":[
        "\u65b0\u4e95\u6751"
    ],
    "wof:name":"Xinjingcun",
    "wof:placetype":"locality"
},
  "geometry": {"coordinates":[116.57089000000001,31.8564],"type":"Point"}
}