{
  "type": "Feature",
  "properties": {
    "gn:admin1_code":"10.0",
    "gn:asciiname":"Dongtuotou",
    "gn:country_code":"CN",
    "gn:dem":12,
    "gn:feature_class":"P",
    "gn:feature_code":"PPL",
    "gn:name":"Dongtuotou",
    "gn:population":0,
    "gn:timezone":"Asia/Shanghai",
    "iso:country":"CN",
    "name:zho_x_preferred":[
        "\u4e1c\u5768\u5934"
    ],
    "wof:name":"Dongtuotou",
    "wof:placetype":"locality"
},
  "geometry": {"coordinates":[119.42418000000001,39.841],"type":"Point"}
}