{
  "type": "Feature",
  "properties": {
    "gn:admin1_code":"16.0",
    "gn:asciiname":"Jiazhi",
    "gn:country_code":"CN",
    "gn:dem":385,
    "gn:feature_class":"P",
    "gn:feature_code":"PPL",
    "gn:name":"Jiazhi",
    "gn:population":0,
    "gn:timezone":"Asia/Shanghai",
    "iso:country":"CN",
    "name:zho_x_preferred":[
        "\u7532\u829d"
    ],
    "wof:name":"Jiazhi",
    "wof:placetype":"locality"
},
  "geometry": {"coordinates":[107.83199999999999,23.1696],"type":"Point"}
}