{
  "type": "Feature",
  "properties": {
    "gn:admin1_code":"25",
    "gn:asciiname":"Dongduijiu",
    "gn:country_code":"CN",
    "gn:dem":169,
    "gn:feature_class":"P",
    "gn:feature_code":"PPL",
    "gn:name":"Dongduijiu",
    "gn:population":0,
    "gn:timezone":"Asia/Shanghai",
    "iso:country":"CN",
    "name:zho_x_preferred":[
        "\u4e1c\u5bf9\u65e7"
    ],
    "wof:name":"Dongduijiu",
    "wof:placetype":"locality"
},
  "geometry": {"coordinates":[117.066,36.1227],"type":"Point"}
}