{
  "type": "Feature",
  "properties": {
    "gn:admin1_code":"16.0",
    "gn:asciiname":"Zhutoushan",
    "gn:country_code":"CN",
    "gn:dem":346,
    "gn:feature_class":"P",
    "gn:feature_code":"PPL",
    "gn:name":"Zhutoushan",
    "gn:population":0,
    "gn:timezone":"Asia/Shanghai",
    "iso:country":"CN",
    "name:zho_x_preferred":[
        "\u732a\u5934\u5c71"
    ],
    "wof:name":"Zhutoushan",
    "wof:placetype":"locality"
},
  "geometry": {"coordinates":[109.676,24.2399],"type":"Point"}
}