{
  "type": "Feature",
  "properties": {
    "gn:admin1_code":"9.0",
    "gn:asciiname":"Baihua Xigoucun",
    "gn:country_code":"CN",
    "gn:dem":951,
    "gn:feature_class":"P",
    "gn:feature_code":"PPL",
    "gn:name":"Baihua Xigoucun",
    "gn:population":0,
    "gn:timezone":"Asia/Shanghai",
    "iso:country":"CN",
    "name:zho_x_preferred":[
        "\u767d\u82b1\u897f\u6c9f\u6751"
    ],
    "wof:name":"Baihua Xigoucun",
    "wof:placetype":"locality"
},
  "geometry": {"coordinates":[112.37436,33.81895],"type":"Point"}
}