{
  "type": "Feature",
  "properties": {
    "gn:admin1_code":"32.0",
    "gn:asciiname":"Yangliu",
    "gn:country_code":"CN",
    "gn:dem":984,
    "gn:feature_class":"P",
    "gn:feature_code":"PPL",
    "gn:name":"Yangliu",
    "gn:population":0,
    "gn:timezone":"Asia/Shanghai",
    "iso:country":"CN",
    "name:zho_x_preferred":[
        "\u6768\u67f3"
    ],
    "wof:name":"Yangliu",
    "wof:placetype":"locality"
},
  "geometry": {"coordinates":[105.029,32.5304],"type":"Point"}
}