{
  "type": "Feature",
  "properties": {
    "gn:admin1_code":"12.0",
    "gn:asciiname":"Wanjiatai",
    "gn:country_code":"CN",
    "gn:dem":23,
    "gn:feature_class":"P",
    "gn:feature_code":"PPL",
    "gn:name":"Wanjiatai",
    "gn:population":0,
    "gn:timezone":"Asia/Shanghai",
    "iso:country":"CN",
    "name:zho_x_preferred":[
        "\u4e07\u5bb6\u53f0"
    ],
    "wof:name":"Wanjiatai",
    "wof:placetype":"locality"
},
  "geometry": {"coordinates":[113.46034,29.97746],"type":"Point"}
}