{
  "type": "Feature",
  "properties": {
    "gn:admin1_code":"7.0",
    "gn:asciiname":"Daqiuhou",
    "gn:country_code":"CN",
    "gn:dem":940,
    "gn:feature_class":"P",
    "gn:feature_code":"PPL",
    "gn:name":"Daqiuhou",
    "gn:population":0,
    "gn:timezone":"Asia/Shanghai",
    "iso:country":"CN",
    "name:zho_x_preferred":[
        "\u5927\u4e18\u540e"
    ],
    "wof:name":"Daqiuhou",
    "wof:placetype":"locality"
},
  "geometry": {"coordinates":[119.01817,25.7682],"type":"Point"}
}