{
  "type": "Feature",
  "properties": {
    "gn:admin1_code":"10",
    "gn:asciiname":"Dongxinzhuang",
    "gn:country_code":"CN",
    "gn:dem":125,
    "gn:feature_class":"P",
    "gn:feature_code":"PPL",
    "gn:name":"Dongxinzhuang",
    "gn:population":0,
    "gn:timezone":"Asia/Shanghai",
    "iso:country":"CN",
    "name:zho_x_preferred":[
        "\u4e1c\u8f9b\u5e84"
    ],
    "wof:name":"Dongxinzhuang",
    "wof:placetype":"locality"
},
  "geometry": {"coordinates":[118.59059999999999,40.23688],"type":"Point"}
}