{
  "type": "Feature",
  "properties": {
    "gn:country":"CN",
    "gn:fcode":"PPL",
    "gn:population":1287,
    "iso:country":"CN",
    "name:und_x_variant":[
        "Pei-li-tzu-ku"
    ],
    "qs:name":"Beilizigu",
    "qs:photos_9r":0,
    "qs:photos_sr":0,
    "qs:pop_sr":"3",
    "wof:name":"Beilizigu",
    "wof:placetype":"locality",
    "wof:population":1287
},
  "geometry": {"coordinates":[117.465,39.49139],"type":"Point"}
}