{
  "type": "Feature",
  "properties": {
    "gn:admin1_code":"19.0",
    "gn:asciiname":"Duanjiahe",
    "gn:country_code":"CN",
    "gn:dem":24,
    "gn:feature_class":"P",
    "gn:feature_code":"PPL",
    "gn:name":"Duanjiahe",
    "gn:population":0,
    "gn:timezone":"Asia/Shanghai",
    "iso:country":"CN",
    "name:zho_x_preferred":[
        "\u6bb5\u5939\u6cb3"
    ],
    "wof:name":"Duanjiahe",
    "wof:placetype":"locality"
},
  "geometry": {"coordinates":[123.19701000000001,41.32048],"type":"Point"}
}