{
  "type": "Feature",
  "properties": {
    "gn:admin1_code":"32.0",
    "gn:asciiname":"Juntian",
    "gn:country_code":"CN",
    "gn:dem":528,
    "gn:feature_class":"P",
    "gn:feature_code":"PPL",
    "gn:name":"Juntian",
    "gn:population":0,
    "gn:timezone":"Asia/Shanghai",
    "iso:country":"CN",
    "name:zho_x_preferred":[
        "\u519b\u7530"
    ],
    "wof:name":"Juntian",
    "wof:placetype":"locality"
},
  "geometry": {"coordinates":[103.56,30.3322],"type":"Point"}
}