{
  "type": "Feature",
  "properties": {
    "gn:admin1_code":"11.0",
    "gn:asciiname":"Hongshi",
    "gn:country_code":"CN",
    "gn:dem":105,
    "gn:feature_class":"P",
    "gn:feature_code":"PPL",
    "gn:name":"Hongshi",
    "gn:population":0,
    "gn:timezone":"Asia/Shanghai",
    "iso:country":"CN",
    "name:zho_x_preferred":[
        "\u5b8f\u5e02"
    ],
    "wof:name":"Hongshi",
    "wof:placetype":"locality"
},
  "geometry": {"coordinates":[113.44074000000001,27.21831],"type":"Point"}
}