{
  "type": "Feature",
  "properties": {
    "gn:admin1_code":"14",
    "gn:asciiname":"Nyimalung",
    "gn:country_code":"CN",
    "gn:dem":4525,
    "gn:feature_class":"P",
    "gn:feature_code":"PPL",
    "gn:name":"Nyimalung",
    "gn:population":0,
    "gn:timezone":"Asia/Urumqi",
    "iso:country":"CN",
    "name:bod_x_preferred":[
        "\u0f49\u0f72\u0f0b\u0f58\u0f0b\u0f63\u0f74\u0f44"
    ],
    "wof:name":"Nyimalung",
    "wof:placetype":"locality"
},
  "geometry": {"coordinates":[90.84492,28.86429],"type":"Point"}
}