{
  "type": "Feature",
  "properties": {
    "gn:admin1_code":"32.0",
    "gn:asciiname":"Xiuliwa",
    "gn:country_code":"CN",
    "gn:dem":2881,
    "gn:feature_class":"P",
    "gn:feature_code":"PPL",
    "gn:name":"Xiuliwa",
    "gn:population":0,
    "gn:timezone":"Asia/Shanghai",
    "iso:country":"CN",
    "name:zho_x_preferred":[
        "\u79c0\u4e3d\u5a03"
    ],
    "wof:name":"Xiuliwa",
    "wof:placetype":"locality"
},
  "geometry": {"coordinates":[101.02,27.42],"type":"Point"}
}