{
  "type": "Feature",
  "properties": {
    "gn:admin1_code":"18",
    "gn:asciiname":"Tangtuping",
    "gn:country_code":"CN",
    "gn:dem":958,
    "gn:feature_class":"P",
    "gn:feature_code":"PPL",
    "gn:name":"Tangtuping",
    "gn:population":0,
    "gn:timezone":"Asia/Shanghai",
    "iso:country":"CN",
    "name:zho_x_preferred":[
        "\u5858\u571f\u576a"
    ],
    "wof:name":"Tangtuping",
    "wof:placetype":"locality"
},
  "geometry": {"coordinates":[107.536,28.732],"type":"Point"}
}