{
  "type": "Feature",
  "properties": {
    "gn:admin1_code":"19.0",
    "gn:asciiname":"Banjieta",
    "gn:country_code":"CN",
    "gn:dem":124,
    "gn:feature_class":"P",
    "gn:feature_code":"PPL",
    "gn:name":"Banjieta",
    "gn:population":0,
    "gn:timezone":"Asia/Shanghai",
    "iso:country":"CN",
    "name:und_x_variant":[
        "\u534a\u622a\u5854"
    ],
    "name:zho_x_preferred":[
        "\u534a\u622a\u5854"
    ],
    "wof:name":"Banjieta",
    "wof:placetype":"locality"
},
  "geometry": {"coordinates":[121.95999999999999,42.0956],"type":"Point"}
}