{
  "type": "Feature",
  "properties": {
    "gn:admin1_code":"32.0",
    "gn:asciiname":"Guanmo",
    "gn:country_code":"CN",
    "gn:dem":1596,
    "gn:feature_class":"P",
    "gn:feature_code":"PPL",
    "gn:name":"Guanmo",
    "gn:population":0,
    "gn:timezone":"Asia/Shanghai",
    "iso:country":"CN",
    "name:zho_x_preferred":[
        "\u5173\u78e8"
    ],
    "wof:name":"Guanmo",
    "wof:placetype":"locality"
},
  "geometry": {"coordinates":[103.98999999999999,32.0192],"type":"Point"}
}