{
  "type": "Feature",
  "properties": {
    "gn:admin1_code":"19.0",
    "gn:asciiname":"Ersunzigou",
    "gn:country_code":"CN",
    "gn:dem":305,
    "gn:feature_class":"P",
    "gn:feature_code":"PPL",
    "gn:name":"Ersunzigou",
    "gn:population":0,
    "gn:timezone":"Asia/Shanghai",
    "iso:country":"CN",
    "name:zho_x_preferred":[
        "\u4e8c\u5b59\u5b50\u6c9f"
    ],
    "wof:name":"Ersunzigou",
    "wof:placetype":"locality"
},
  "geometry": {"coordinates":[124.437,40.5508],"type":"Point"}
}