{
  "type": "Feature",
  "properties": {
    "gn:admin1_code":"15.0",
    "gn:asciiname":"Zhujiayao",
    "gn:country_code":"CN",
    "gn:dem":1847,
    "gn:feature_class":"P",
    "gn:feature_code":"PPL",
    "gn:name":"Zhujiayao",
    "gn:population":0,
    "gn:timezone":"Asia/Shanghai",
    "iso:country":"CN",
    "name:und_x_variant":[
        "Chu-chia-yao",
        "Zhujiayao"
    ],
    "name:zho_x_preferred":[
        "\u6731\u5bb6\u7a91"
    ],
    "wof:name":"Zhujiayao",
    "wof:placetype":"locality"
},
  "geometry": {"coordinates":[103.97799999999999,36.4904],"type":"Point"}
}