{
  "type": "Feature",
  "properties": {
    "gn:admin1_code":"21.0",
    "gn:asciiname":"Yinjiaqu",
    "gn:country_code":"CN",
    "gn:dem":1109,
    "gn:feature_class":"P",
    "gn:feature_code":"PPL",
    "gn:name":"Yinjiaqu",
    "gn:population":0,
    "gn:timezone":"Asia/Shanghai",
    "iso:country":"CN",
    "name:zho_x_preferred":[
        "\u5c39\u5bb6\u6e20"
    ],
    "wof:name":"Yinjiaqu",
    "wof:placetype":"locality"
},
  "geometry": {"coordinates":[106.236,38.4865],"type":"Point"}
}