{
  "type": "Feature",
  "properties": {
    "gn:admin1_code":"26.0",
    "gn:asciiname":"Jiachacun",
    "gn:country_code":"CN",
    "gn:dem":1249,
    "gn:feature_class":"P",
    "gn:feature_code":"PPL",
    "gn:name":"Jiachacun",
    "gn:population":0,
    "gn:timezone":"Asia/Shanghai",
    "iso:country":"CN",
    "name:zho_x_preferred":[
        "\u8d3e\u5c94\u6751"
    ],
    "wof:name":"Jiachacun",
    "wof:placetype":"locality"
},
  "geometry": {"coordinates":[109.97338000000001,33.75072],"type":"Point"}
}