{
  "type": "Feature",
  "properties": {
    "gn:admin1_code":"30.0",
    "gn:asciiname":"Maotan",
    "gn:country_code":"CN",
    "gn:dem":79,
    "gn:feature_class":"P",
    "gn:feature_code":"PPL",
    "gn:name":"Maotan",
    "gn:population":0,
    "gn:timezone":"Asia/Shanghai",
    "iso:country":"CN",
    "name:zho_x_preferred":[
        "\u8305\u6ee9"
    ],
    "wof:name":"Maotan",
    "wof:placetype":"locality"
},
  "geometry": {"coordinates":[112.48563,22.02908],"type":"Point"}
}