{
  "type": "Feature",
  "properties": {
    "gn:admin1_code":"9.0",
    "gn:asciiname":"Dawangzhuang",
    "gn:country_code":"CN",
    "gn:dem":358,
    "gn:feature_class":"P",
    "gn:feature_code":"PPL",
    "gn:name":"Dawangzhuang",
    "gn:population":0,
    "gn:timezone":"Asia/Shanghai",
    "iso:country":"CN",
    "name:zho_x_preferred":[
        "\u5927\u738b\u5e84"
    ],
    "wof:name":"Dawangzhuang",
    "wof:placetype":"locality"
},
  "geometry": {"coordinates":[113.38282,34.56642],"type":"Point"}
}