{
  "type": "Feature",
  "properties": {
    "gn:admin1_code":"3",
    "gn:asciiname":"Xibeixiang",
    "gn:country_code":"CN",
    "gn:dem":72,
    "gn:feature_class":"P",
    "gn:feature_code":"PPL",
    "gn:name":"Xibeixiang",
    "gn:population":0,
    "gn:timezone":"Asia/Shanghai",
    "iso:country":"CN",
    "name:zho_x_preferred":[
        "\u6eaa\u80cc\u5df7"
    ],
    "wof:name":"Xibeixiang",
    "wof:placetype":"locality"
},
  "geometry": {"coordinates":[114.92,26.9508],"type":"Point"}
}