{
  "type": "Feature",
  "properties": {
    "gn:admin1_code":"16.0",
    "gn:asciiname":"Waicun",
    "gn:country_code":"CN",
    "gn:dem":96,
    "gn:feature_class":"P",
    "gn:feature_code":"PPL",
    "gn:name":"Waicun",
    "gn:population":0,
    "gn:timezone":"Asia/Shanghai",
    "iso:country":"CN",
    "name:zho_x_preferred":[
        "\u5916\u6751"
    ],
    "wof:name":"Waicun",
    "wof:placetype":"locality"
},
  "geometry": {"coordinates":[110.63200000000001,23.3493],"type":"Point"}
}