{
  "type": "Feature",
  "properties": {
    "gn:admin1_code":"5.0",
    "gn:asciiname":"Wenjia Tuozi",
    "gn:country_code":"CN",
    "gn:dem":158,
    "gn:feature_class":"P",
    "gn:feature_code":"PPL",
    "gn:name":"Wenjia Tuozi",
    "gn:population":0,
    "gn:timezone":"Asia/Shanghai",
    "iso:country":"CN",
    "name:zho_x_preferred":[
        "\u6e29\u5bb6\u5768\u5b50"
    ],
    "wof:name":"Wenjia Tuozi",
    "wof:placetype":"locality"
},
  "geometry": {"coordinates":[126.26887000000001,44.62976],"type":"Point"}
}