{
  "type": "Feature",
  "properties": {
    "gn:admin1_code":"10",
    "gn:asciiname":"Anzhou",
    "gn:cc2":"CN",
    "gn:country_code":"CN",
    "gn:dem":9,
    "gn:feature_class":"P",
    "gn:feature_code":"PPL",
    "gn:name":"Anzhou",
    "gn:population":0,
    "gn:timezone":"Asia/Shanghai",
    "iso:country":"CN",
    "name:und_x_variant":[
        "An-chou",
        "Anchow",
        "An-hsin",
        "An-hsin-hsien",
        "An\u2019sin",
        "Anzhou"
    ],
    "name:zho_x_preferred":[
        "\u5b89\u5dde\u9547"
    ],
    "wof:name":"Anzhou",
    "wof:placetype":"locality"
},
  "geometry": {"coordinates":[115.8175,38.87],"type":"Point"}
}