{
  "type": "Feature",
  "properties": {
    "gn:admin1_code":"16.0",
    "gn:asciiname":"Fengcun",
    "gn:country_code":"CN",
    "gn:dem":97,
    "gn:feature_class":"P",
    "gn:feature_code":"PPL",
    "gn:name":"Fengcun",
    "gn:population":0,
    "gn:timezone":"Asia/Shanghai",
    "iso:country":"CN",
    "name:zho_x_preferred":[
        "\u51e4\u6751"
    ],
    "wof:name":"Fengcun",
    "wof:placetype":"locality"
},
  "geometry": {"coordinates":[110.277,23.7315],"type":"Point"}
}