{
  "type": "Feature",
  "properties": {
    "gn:admin1_code":"26.0",
    "gn:asciiname":"Xifengcun",
    "gn:country_code":"CN",
    "gn:dem":970,
    "gn:feature_class":"P",
    "gn:feature_code":"PPL",
    "gn:name":"Xifengcun",
    "gn:population":0,
    "gn:timezone":"Asia/Shanghai",
    "iso:country":"CN",
    "name:zho_x_preferred":[
        "\u897f\u5cf0\u6751"
    ],
    "wof:name":"Xifengcun",
    "wof:placetype":"locality"
},
  "geometry": {"coordinates":[106.81016,34.38138],"type":"Point"}
}