{
  "type": "Feature",
  "properties": {
    "gn:admin1_code":"1.0",
    "gn:asciiname":"Buchen",
    "gn:country_code":"CN",
    "gn:dem":9,
    "gn:feature_class":"P",
    "gn:feature_code":"PPL",
    "gn:name":"Buchen",
    "gn:population":0,
    "gn:timezone":"Asia/Shanghai",
    "iso:country":"CN",
    "name:als_x_preferred":[
        "Buchen"
    ],
    "name:ara_x_preferred":[
        "\u0628\u0648\u062e\u0646"
    ],
    "name:azb_x_preferred":[
        "\u0628\u0648\u062e\u0646"
    ],
    "name:ceb_x_preferred":[
        "Buchen"
    ],
    "name:deu_x_preferred":[
        "Buchen"
    ],
    "name:eml_x_preferred":[
        "Buch\u00e8\u1e45"
    ],
    "name:epo_x_preferred":[
        "Buchen"
    ],
    "name:fas_x_preferred":[
        "\u0628\u0648\u062e\u0646"
    ],
    "name:fra_x_preferred":[
        "Buchen"
    ],
    "name:hun_x_preferred":[
        "Buchen"
    ],
    "name:ita_x_preferred":[
        "Buchen"
    ],
    "name:jpn_x_preferred":[
        "\u30d6\u30fc\u30d2\u30a7\u30f3"
    ],
    "name:kaz_x_preferred":[
        "\u0411\u0443\u0445\u0435\u043d"
    ],
    "name:kir_x_preferred":[
        "\u0411\u0443\u0445\u0435\u043d"
    ],
    "name:lat_x_preferred":[
        "Buchen"
    ],
    "name:lmo_x_preferred":[
        "Buchen"
    ],
    "name:msa_x_preferred":[
        "Buchen"
    ],
    "name:nld_x_preferred":[
        "Buchen"
    ],
    "name:pol_x_preferred":[
        "Buchen"
    ],
    "name:por_x_preferred":[
        "Buchen"
    ],
    "name:ron_x_preferred":[
        "Buchen"
    ],
    "name:rus_x_preferred":[
        "\u0411\u0443\u0445\u0435\u043d"
    ],
    "name:spa_x_preferred":[
        "Buchen"
    ],
    "name:srp_x_preferred":[
        "\u0411\u0443\u0445\u0435\u043d"
    ],
    "name:tur_x_preferred":[
        "Buchen"
    ],
    "name:ukr_x_preferred":[
        "\u0411\u0443\u0445\u0435\u043d"
    ],
    "name:uzb_x_preferred":[
        "Buchen"
    ],
    "name:vol_x_preferred":[
        "Buchen"
    ],
    "name:war_x_preferred":[
        "Buchen"
    ],
    "name:zho_x_preferred":[
        "\u535c\u9648"
    ],
    "wof:name":"Buchen",
    "wof:placetype":"locality"
},
  "geometry": {"coordinates":[118.45142,31.83132],"type":"Point"}
}