{
  "type": "Feature",
  "properties": {
    "gn:admin1_code":"1.0",
    "gn:asciiname":"Buchen",
    "gn:country_code":"CN",
    "gn:dem":9,
    "gn:feature_class":"P",
    "gn:feature_code":"PPL",
    "gn:name":"Buchen",
    "gn:population":0,
    "gn:timezone":"Asia/Shanghai",
    "iso:country":"CN",
    "name:zho_x_preferred":[
        "\u535c\u9648"
    ],
    "wof:name":"Buchen",
    "wof:placetype":"locality"
},
  "geometry": {"coordinates":[118.45142,31.83132],"type":"Point"}
}