{
  "type": "Feature",
  "properties": {
    "gn:admin1_code":"3.0",
    "gn:asciiname":"Gaosheng",
    "gn:country_code":"CN",
    "gn:dem":615,
    "gn:feature_class":"P",
    "gn:feature_code":"PPL",
    "gn:name":"Gaosheng",
    "gn:population":0,
    "gn:timezone":"Asia/Shanghai",
    "iso:country":"CN",
    "name:und_x_variant":[
        "\u9ad8\u5d4a"
    ],
    "wof:name":"Gaosheng",
    "wof:placetype":"locality"
},
  "geometry": {"coordinates":[116.22234,26.55704],"type":"Point"}
}