{
  "type": "Feature",
  "properties": {
    "gn:admin1_code":"30.0",
    "gn:asciiname":"Caojundong",
    "gn:country_code":"CN",
    "gn:dem":151,
    "gn:feature_class":"P",
    "gn:feature_code":"PPL",
    "gn:name":"Caojundong",
    "gn:population":0,
    "gn:timezone":"Asia/Shanghai",
    "iso:country":"CN",
    "name:zho_x_preferred":[
        "\u66f9\u519b\u6d1e"
    ],
    "wof:name":"Caojundong",
    "wof:placetype":"locality"
},
  "geometry": {"coordinates":[114.69746000000001,23.83026],"type":"Point"}
}