{
  "type": "Feature",
  "properties": {
    "gn:admin1_code":"15.0",
    "gn:asciiname":"Shangbingcaowan",
    "gn:country_code":"CN",
    "gn:dem":1671,
    "gn:feature_class":"P",
    "gn:feature_code":"PPL",
    "gn:name":"Shangbingcaowan",
    "gn:population":0,
    "gn:timezone":"Asia/Shanghai",
    "iso:country":"CN",
    "name:zho_x_preferred":[
        "\u4e0a\u51b0\u8349\u6e7e"
    ],
    "wof:name":"Shangbingcaowan",
    "wof:placetype":"locality"
},
  "geometry": {"coordinates":[103.732,37.6106],"type":"Point"}
}