{
  "type": "Feature",
  "properties": {
    "gn:admin1_code":"19.0",
    "gn:asciiname":"Goumenzi",
    "gn:country_code":"CN",
    "gn:dem":346,
    "gn:feature_class":"P",
    "gn:feature_code":"PPL",
    "gn:name":"Goumenzi",
    "gn:population":0,
    "gn:timezone":"Asia/Shanghai",
    "iso:country":"CN",
    "name:und_x_variant":[
        "\u6c9f\u95e8\u5b50"
    ],
    "name:zho_x_preferred":[
        "\u6c9f\u95e8\u5b50"
    ],
    "wof:name":"Goumenzi",
    "wof:placetype":"locality"
},
  "geometry": {"coordinates":[120.20936,41.157],"type":"Point"}
}