{
  "type": "Feature",
  "properties": {
    "gn:admin1_code":"9",
    "gn:asciiname":"Gaoyoufang",
    "gn:country_code":"CN",
    "gn:dem":52,
    "gn:feature_class":"P",
    "gn:feature_code":"PPL",
    "gn:name":"Gaoyoufang",
    "gn:population":0,
    "gn:timezone":"Asia/Shanghai",
    "iso:country":"CN",
    "name:zho_x_preferred":[
        "\u9ad8\u6cb9\u574a"
    ],
    "wof:name":"Gaoyoufang",
    "wof:placetype":"locality"
},
  "geometry": {"coordinates":[115.24005,35.98894],"type":"Point"}
}