{
  "type": "Feature",
  "properties": {
    "gn:admin1_code":"9.0",
    "gn:asciiname":"Xuweizi",
    "gn:country_code":"CN",
    "gn:dem":44,
    "gn:feature_class":"P",
    "gn:feature_code":"PPL",
    "gn:name":"Xuweizi",
    "gn:population":0,
    "gn:timezone":"Asia/Shanghai",
    "iso:country":"CN",
    "name:zho_x_preferred":[
        "\u5f90\u56f4\u5b50"
    ],
    "wof:name":"Xuweizi",
    "wof:placetype":"locality"
},
  "geometry": {"coordinates":[114.94338999999999,32.55648],"type":"Point"}
}