{
  "type": "Feature",
  "properties": {
    "gn:admin1_code":"29.0",
    "gn:asciiname":"Xiaomengtong",
    "gn:cc2":"CN",
    "gn:country_code":"CN",
    "gn:dem":1818,
    "gn:feature_class":"P",
    "gn:feature_code":"PPL",
    "gn:name":"Xiaomengtong",
    "gn:population":0,
    "gn:timezone":"Asia/Shanghai",
    "iso:country":"CN",
    "name:und_x_variant":[
        "Hsiao-meng-t\u2019ung",
        "Xiaomengtong"
    ],
    "wof:name":"Xiaomengtong",
    "wof:placetype":"locality"
},
  "geometry": {"coordinates":[99.31667,24.21667],"type":"Point"}
}