{
  "type": "Feature",
  "properties": {
    "gn:admin1_code":"26",
    "gn:asciiname":"Heilongkou",
    "gn:country_code":"CN",
    "gn:dem":903,
    "gn:feature_class":"P",
    "gn:feature_code":"PPLA4",
    "gn:name":"Heilongkou",
    "gn:population":0,
    "gn:timezone":"Asia/Shanghai",
    "iso:country":"CN",
    "name:und_x_variant":[
        "Hei-lung-k\u2019ou",
        "\u9ed1\u9f99\u53e3",
        "Heilongkou",
        "Heilongkou Zhen"
    ],
    "wof:name":"Heilongkou",
    "wof:placetype":"locality"
},
  "geometry": {"coordinates":[109.7306,34.00959],"type":"Point"}
}