{
  "type": "Feature",
  "properties": {
    "gn:admin1_code":"2.0",
    "gn:asciiname":"Chun'an",
    "gn:country_code":"CN",
    "gn:dem":17,
    "gn:feature_class":"P",
    "gn:feature_code":"PPL",
    "gn:name":"Chun\u2019an",
    "gn:population":0,
    "gn:timezone":"Asia/Shanghai",
    "iso:country":"CN",
    "name:und_x_variant":[
        "Chun\u2019an",
        "\u6625\u5b89"
    ],
    "wof:name":"Chun'an",
    "wof:placetype":"locality"
},
  "geometry": {"coordinates":[119.90472,29.98187],"type":"Point"}
}