{
  "type": "Feature",
  "properties": {
    "gn:admin1_code":"19.0",
    "gn:asciiname":"Dongyangjia",
    "gn:country_code":"CN",
    "gn:dem":5,
    "gn:feature_class":"P",
    "gn:feature_code":"PPL",
    "gn:name":"Dongyangjia",
    "gn:population":0,
    "gn:timezone":"Asia/Shanghai",
    "iso:country":"CN",
    "name:zho_x_preferred":[
        "\u4e1c\u6768\u5bb6"
    ],
    "wof:name":"Dongyangjia",
    "wof:placetype":"locality"
},
  "geometry": {"coordinates":[122.69499999999999,41.0801],"type":"Point"}
}