{
  "type": "Feature",
  "properties": {
    "gn:admin1_code":"32.0",
    "gn:asciiname":"Tanjiaping",
    "gn:country_code":"CN",
    "gn:dem":942,
    "gn:feature_class":"P",
    "gn:feature_code":"PPL",
    "gn:name":"Tanjiaping",
    "gn:population":0,
    "gn:timezone":"Asia/Shanghai",
    "iso:country":"CN",
    "name:zho_x_preferred":[
        "\u8c2d\u5bb6\u576a"
    ],
    "wof:name":"Tanjiaping",
    "wof:placetype":"locality"
},
  "geometry": {"coordinates":[107.74611000000002,31.70548],"type":"Point"}
}