{
  "type": "Feature",
  "properties": {
    "gn:admin1_code":"3.0",
    "gn:asciiname":"Xiaokuang",
    "gn:country_code":"CN",
    "gn:dem":340,
    "gn:feature_class":"P",
    "gn:feature_code":"PPL",
    "gn:name":"Xiaokuang",
    "gn:population":0,
    "gn:timezone":"Asia/Shanghai",
    "iso:country":"CN",
    "name:und_x_variant":[
        "\u5c0f\u77ff"
    ],
    "wof:name":"Xiaokuang",
    "wof:placetype":"locality"
},
  "geometry": {"coordinates":[115.69028,25.95482],"type":"Point"}
}