{
  "type": "Feature",
  "properties": {
    "gn:admin1_code":"25",
    "gn:asciiname":"Tongdian",
    "gn:country_code":"CN",
    "gn:dem":56,
    "gn:feature_class":"P",
    "gn:feature_code":"PPL",
    "gn:name":"Tongdian",
    "gn:population":0,
    "gn:timezone":"Asia/Shanghai",
    "iso:country":"CN",
    "name:zho_x_preferred":[
        "\u4edd\u5e97"
    ],
    "wof:name":"Tongdian",
    "wof:placetype":"locality"
},
  "geometry": {"coordinates":[115.63800000000001,34.7822],"type":"Point"}
}