{
  "type": "Feature",
  "properties": {
    "gn:admin1_code":"1.0",
    "gn:asciiname":"Gaozhangcun",
    "gn:country_code":"CN",
    "gn:dem":80,
    "gn:feature_class":"P",
    "gn:feature_code":"PPL",
    "gn:name":"Gaozhangcun",
    "gn:population":0,
    "gn:timezone":"Asia/Shanghai",
    "iso:country":"CN",
    "name:zho_x_preferred":[
        "\u9ad8\u5f20\u6751"
    ],
    "wof:name":"Gaozhangcun",
    "wof:placetype":"locality"
},
  "geometry": {"coordinates":[117.85393000000001,32.24244],"type":"Point"}
}