{
  "type": "Feature",
  "properties": {
    "gn:admin1_code":"11.0",
    "gn:asciiname":"Shijiagou",
    "gn:country_code":"CN",
    "gn:dem":671,
    "gn:feature_class":"P",
    "gn:feature_code":"PPL",
    "gn:name":"Shijiagou",
    "gn:population":0,
    "gn:timezone":"Asia/Shanghai",
    "iso:country":"CN",
    "name:zho_x_preferred":[
        "Shijiagou"
    ],
    "name:zho_x_variant":[
        "\u8bd7\u5bb6\u6c9f"
    ],
    "wof:name":"Shijiagou",
    "wof:placetype":"locality"
},
  "geometry": {"coordinates":[111.1037,29.72717],"type":"Point"}
}