{
  "type": "Feature",
  "properties": {
    "gn:admin1_code":"16.0",
    "gn:asciiname":"Lucun",
    "gn:country_code":"CN",
    "gn:dem":138,
    "gn:feature_class":"P",
    "gn:feature_code":"PPL",
    "gn:name":"Lucun",
    "gn:population":0,
    "gn:timezone":"Asia/Shanghai",
    "iso:country":"CN",
    "name:ceb_x_preferred":[
        "Lucun"
    ],
    "name:swe_x_preferred":[
        "Lucun"
    ],
    "name:zho_x_preferred":[
        "\u9646\u6751"
    ],
    "wof:name":"Lucun",
    "wof:placetype":"locality"
},
  "geometry": {"coordinates":[109.197,25.0152],"type":"Point"}
}