{
  "type": "Feature",
  "properties": {
    "gn:admin1_code":"13",
    "gn:asciiname":"Yiling'ertuannong Sanlian",
    "gn:country_code":"CN",
    "gn:dem":446,
    "gn:feature_class":"P",
    "gn:feature_code":"PPL",
    "gn:name":"Yiling\u2019ertuannong Sanlian",
    "gn:population":0,
    "gn:timezone":"Asia/Urumqi",
    "iso:country":"CN",
    "name:und_x_variant":[
        "Yiling\u2019ertuannong Sanlian"
    ],
    "name:zho_x_preferred":[
        "\u4e00\u96f6\u4e8c\u56e2\u519c\u4e09\u8fde"
    ],
    "wof:name":"Yiling'ertuannong Sanlian",
    "wof:placetype":"locality"
},
  "geometry": {"coordinates":[87.61655,44.32579000000001],"type":"Point"}
}