{
  "type": "Feature",
  "properties": {
    "gn:admin1_code":"24.0",
    "gn:asciiname":"Shekeyancun",
    "gn:country_code":"CN",
    "gn:dem":954,
    "gn:feature_class":"P",
    "gn:feature_code":"PPL",
    "gn:name":"Shekeyancun",
    "gn:population":0,
    "gn:timezone":"Asia/Shanghai",
    "iso:country":"CN",
    "name:zho_x_preferred":[
        "\u820d\u7aa0\u5895\u6751"
    ],
    "wof:name":"Shekeyancun",
    "wof:placetype":"locality"
},
  "geometry": {"coordinates":[110.78748,37.7405],"type":"Point"}
}