{
  "type": "Feature",
  "properties": {
    "gn:admin1_code":"19.0",
    "gn:asciiname":"Depei",
    "gn:country_code":"CN",
    "gn:dem":158,
    "gn:feature_class":"P",
    "gn:feature_code":"PPL",
    "gn:name":"Depei",
    "gn:population":0,
    "gn:timezone":"Asia/Shanghai",
    "iso:country":"CN",
    "name:und_x_variant":[
        "\u5fb7\u6c9b"
    ],
    "name:zho_x_preferred":[
        "\u5fb7\u6c9b"
    ],
    "wof:name":"Depei",
    "wof:placetype":"locality"
},
  "geometry": {"coordinates":[124.48854,42.73199],"type":"Point"}
}