{
  "type": "Feature",
  "properties": {
    "gn:admin1_code":"30",
    "gn:asciiname":"Liwuzhai",
    "gn:country_code":"CN",
    "gn:dem":33,
    "gn:feature_class":"P",
    "gn:feature_code":"PPL",
    "gn:name":"Liwuzhai",
    "gn:population":0,
    "gn:timezone":"Asia/Shanghai",
    "iso:country":"CN",
    "name:zho_x_preferred":[
        "\u674e\u5c4b\u5be8"
    ],
    "wof:name":"Liwuzhai",
    "wof:placetype":"locality"
},
  "geometry": {"coordinates":[111.54895,21.93883],"type":"Point"}
}