{
  "type": "Feature",
  "properties": {
    "gn:admin1_code":"24.0",
    "gn:asciiname":"Shanying",
    "gn:country_code":"CN",
    "gn:dem":1370,
    "gn:feature_class":"P",
    "gn:feature_code":"PPL",
    "gn:name":"Shanying",
    "gn:population":0,
    "gn:timezone":"Asia/Shanghai",
    "iso:country":"CN",
    "name:zho_x_preferred":[
        "\u5584\u5e94"
    ],
    "wof:name":"Shanying",
    "wof:placetype":"locality"
},
  "geometry": {"coordinates":[111.79598,38.41916],"type":"Point"}
}