{
  "type": "Feature",
  "properties": {
    "gn:admin1_code":"2.0",
    "gn:asciiname":"Wuzhangwei",
    "gn:country_code":"CN",
    "gn:dem":7,
    "gn:feature_class":"P",
    "gn:feature_code":"PPL",
    "gn:name":"Wuzhangwei",
    "gn:population":0,
    "gn:timezone":"Asia/Shanghai",
    "iso:country":"CN",
    "name:und_x_variant":[
        "\u5434\u5f20\u5729"
    ],
    "wof:name":"Wuzhangwei",
    "wof:placetype":"locality"
},
  "geometry": {"coordinates":[120.85858,30.78411],"type":"Point"}
}