{
  "type": "Feature",
  "properties": {
    "gn:admin1_code":"9.0",
    "gn:asciiname":"Chuzhuang",
    "gn:country_code":"CN",
    "gn:dem":118,
    "gn:feature_class":"P",
    "gn:feature_code":"PPL",
    "gn:name":"Chuzhuang",
    "gn:population":0,
    "gn:timezone":"Asia/Shanghai",
    "iso:country":"CN",
    "name:zho_x_preferred":[
        "\u891a\u5e84"
    ],
    "wof:name":"Chuzhuang",
    "wof:placetype":"locality"
},
  "geometry": {"coordinates":[113.48217,33.27182],"type":"Point"}
}