{
  "type": "Feature",
  "properties": {
    "gn:admin1_code":"26",
    "gn:asciiname":"Qilichuancun",
    "gn:country_code":"CN",
    "gn:dem":1700,
    "gn:feature_class":"P",
    "gn:feature_code":"PPL",
    "gn:name":"Qilichuancun",
    "gn:population":0,
    "gn:timezone":"Asia/Shanghai",
    "iso:country":"CN",
    "name:und_x_variant":[
        "Ch\u2019i-li-ch\u2019uan",
        "Qilichuan",
        "\u4e03\u91cc\u5ddd",
        "Qilichuancun"
    ],
    "name:zho_x_preferred":[
        "\u4e03\u91cc\u5ddd\u6751"
    ],
    "wof:name":"Qilichuancun",
    "wof:placetype":"locality"
},
  "geometry": {"coordinates":[107.28598,34.09514],"type":"Point"}
}