{
  "type": "Feature",
  "properties": {
    "gn:admin1_code":"32.0",
    "gn:asciiname":"Shuiziyan",
    "gn:country_code":"CN",
    "gn:dem":1774,
    "gn:feature_class":"P",
    "gn:feature_code":"PPL",
    "gn:name":"Shuiziyan",
    "gn:population":0,
    "gn:timezone":"Asia/Shanghai",
    "iso:country":"CN",
    "name:zho_x_preferred":[
        "\u6c34\u5b50\u5ca9"
    ],
    "wof:name":"Shuiziyan",
    "wof:placetype":"locality"
},
  "geometry": {"coordinates":[102.50088,29.51442],"type":"Point"}
}