{
  "type": "Feature",
  "properties": {
    "gn:admin1_code":"26.0",
    "gn:asciiname":"Lihouxiang",
    "gn:country_code":"CN",
    "gn:dem":583,
    "gn:feature_class":"P",
    "gn:feature_code":"PPL",
    "gn:name":"Lihouxiang",
    "gn:population":0,
    "gn:timezone":"Asia/Shanghai",
    "iso:country":"CN",
    "name:und_x_variant":[
        "\u674e\u540e\u4e61"
    ],
    "wof:name":"Lihouxiang",
    "wof:placetype":"locality"
},
  "geometry": {"coordinates":[109.34535,34.16275],"type":"Point"}
}