{
  "type": "Feature",
  "properties": {
    "gn:admin1_code":"30.0",
    "gn:asciiname":"Laoyangwu",
    "gn:country_code":"CN",
    "gn:dem":89,
    "gn:feature_class":"P",
    "gn:feature_code":"PPL",
    "gn:name":"Laoyangwu",
    "gn:population":0,
    "gn:timezone":"Asia/Shanghai",
    "iso:country":"CN",
    "name:zho_x_preferred":[
        "\u8001\u6768\u5c4b"
    ],
    "wof:name":"Laoyangwu",
    "wof:placetype":"locality"
},
  "geometry": {"coordinates":[113.63813,24.66175],"type":"Point"}
}