{
  "type": "Feature",
  "properties": {
    "gn:admin1_code":"2.0",
    "gn:asciiname":"Lingjiao",
    "gn:country_code":"CN",
    "gn:dem":10,
    "gn:feature_class":"P",
    "gn:feature_code":"PPL",
    "gn:name":"Lingjiao",
    "gn:population":0,
    "gn:timezone":"Asia/Shanghai",
    "iso:country":"CN",
    "name:und_x_variant":[
        "\u5cad\u811a"
    ],
    "wof:name":"Lingjiao",
    "wof:placetype":"locality"
},
  "geometry": {"coordinates":[120.43496,30.32043],"type":"Point"}
}