{
  "type": "Feature",
  "properties": {
    "gn:admin1_code":"19.0",
    "gn:asciiname":"Sanhebu",
    "gn:country_code":"CN",
    "gn:dem":110,
    "gn:feature_class":"P",
    "gn:feature_code":"PPL",
    "gn:name":"Sanhebu",
    "gn:population":0,
    "gn:timezone":"Asia/Shanghai",
    "iso:country":"CN",
    "name:und_x_variant":[
        "Sanhebao",
        "Sanhebu"
    ],
    "name:zho_x_preferred":[
        "\u4e09\u5408\u5821"
    ],
    "wof:name":"Sanhebu",
    "wof:placetype":"locality"
},
  "geometry": {"coordinates":[124.02179,42.73058],"type":"Point"}
}