{
  "type": "Feature",
  "properties": {
    "gn:admin1_code":"4.0",
    "gn:asciiname":"Dicang",
    "gn:country_code":"CN",
    "gn:dem":4,
    "gn:feature_class":"P",
    "gn:feature_code":"PPL",
    "gn:name":"Dicang",
    "gn:population":0,
    "gn:timezone":"Asia/Shanghai",
    "iso:country":"CN",
    "name:und_x_variant":[
        "\u5730\u85cf"
    ],
    "name:zho_x_preferred":[
        "\u5730\u85cf"
    ],
    "wof:name":"Dicang",
    "wof:placetype":"locality"
},
  "geometry": {"coordinates":[120.40186,32.23558],"type":"Point"}
}