{
  "type": "Feature",
  "properties": {
    "gn:admin1_code":"10",
    "gn:asciiname":"Shanzui",
    "gn:cc2":"CN",
    "gn:country_code":"CN",
    "gn:dem":510,
    "gn:feature_class":"P",
    "gn:feature_code":"PPL",
    "gn:name":"Shanzui",
    "gn:population":0,
    "gn:timezone":"Asia/Shanghai",
    "iso:country":"CN",
    "name:und_x_variant":[
        "Shan-tsui",
        "Shanzui"
    ],
    "wof:name":"Shanzui",
    "wof:placetype":"locality"
},
  "geometry": {"coordinates":[118.63333,40.93333],"type":"Point"}
}