{
  "type": "Feature",
  "properties": {
    "gn:admin1_code":"30.0",
    "gn:asciiname":"Xiafangcun",
    "gn:country_code":"CN",
    "gn:dem":334,
    "gn:feature_class":"P",
    "gn:feature_code":"PPL",
    "gn:name":"Xiafangcun",
    "gn:population":0,
    "gn:timezone":"Asia/Shanghai",
    "iso:country":"CN",
    "name:zho_x_preferred":[
        "\u4e0b\u574a\u6751"
    ],
    "wof:name":"Xiafangcun",
    "wof:placetype":"locality"
},
  "geometry": {"coordinates":[115.92818,24.86372],"type":"Point"}
}