{
  "type": "Feature",
  "properties": {
    "gn:admin1_code":"9.0",
    "gn:asciiname":"Bangedian",
    "gn:country_code":"CN",
    "gn:dem":132,
    "gn:feature_class":"P",
    "gn:feature_code":"PPL",
    "gn:name":"Bangedian",
    "gn:population":0,
    "gn:timezone":"Asia/Shanghai",
    "iso:country":"CN",
    "name:zho_x_preferred":[
        "\u534a\u4e2a\u5e97"
    ],
    "wof:name":"Bangedian",
    "wof:placetype":"locality"
},
  "geometry": {"coordinates":[112.54943,34.70461],"type":"Point"}
}