{
  "type": "Feature",
  "properties": {
    "gn:admin1_code":"18.0",
    "gn:asciiname":"Jiaolong",
    "gn:country_code":"CN",
    "gn:dem":692,
    "gn:feature_class":"P",
    "gn:feature_code":"PPL",
    "gn:name":"Jiaolong",
    "gn:population":0,
    "gn:timezone":"Asia/Shanghai",
    "iso:country":"CN",
    "name:zho_x_preferred":[
        "\u86df\u9f99"
    ],
    "wof:name":"Jiaolong",
    "wof:placetype":"locality"
},
  "geometry": {"coordinates":[107.742,27.0281],"type":"Point"}
}