{
  "type": "Feature",
  "properties": {
    "gn:admin1_code":"26.0",
    "gn:asciiname":"Nanyaoze",
    "gn:country_code":"CN",
    "gn:dem":1201,
    "gn:feature_class":"P",
    "gn:feature_code":"PPL",
    "gn:name":"Nanyaoze",
    "gn:population":0,
    "gn:timezone":"Asia/Shanghai",
    "iso:country":"CN",
    "name:zho_x_preferred":[
        "\u5357\u7a91\u5219"
    ],
    "wof:name":"Nanyaoze",
    "wof:placetype":"locality"
},
  "geometry": {"coordinates":[110.21198,38.17099],"type":"Point"}
}