{
  "type": "Feature",
  "properties": {
    "gn:admin1_code":"19.0",
    "gn:asciiname":"Beigangouzi",
    "gn:country_code":"CN",
    "gn:dem":320,
    "gn:feature_class":"P",
    "gn:feature_code":"PPL",
    "gn:name":"Beigangouzi",
    "gn:population":0,
    "gn:timezone":"Asia/Shanghai",
    "iso:country":"CN",
    "name:zho_x_preferred":[
        "\u5317\u5e72\u6c9f\u5b50"
    ],
    "wof:name":"Beigangouzi",
    "wof:placetype":"locality"
},
  "geometry": {"coordinates":[125.58351999999999,41.0878],"type":"Point"}
}