{
  "type": "Feature",
  "properties": {
    "gn:admin1_code":"29.0",
    "gn:asciiname":"Shaluochong",
    "gn:country_code":"CN",
    "gn:dem":1925,
    "gn:feature_class":"P",
    "gn:feature_code":"PPL",
    "gn:name":"Shaluochong",
    "gn:population":0,
    "gn:timezone":"Asia/Shanghai",
    "iso:country":"CN",
    "name:zho_x_preferred":[
        "\u6c99\u7f57\u51b2"
    ],
    "wof:name":"Shaluochong",
    "wof:placetype":"locality"
},
  "geometry": {"coordinates":[101.18600000000001,25.1713],"type":"Point"}
}