{
  "type": "Feature",
  "properties": {
    "gn:admin1_code":"02",
    "gn:asciiname":"Gaojian",
    "gn:cc2":"CN",
    "gn:country_code":"CN",
    "gn:dem":57,
    "gn:feature_class":"P",
    "gn:feature_code":"PPL",
    "gn:name":"Gaojian",
    "gn:population":0,
    "gn:timezone":"Asia/Shanghai",
    "iso:country":"CN",
    "name:und_x_variant":[
        "Chiao-shih",
        "Kao-chien",
        "Chiao-chien",
        "Gaojian"
    ],
    "name:zho_x_preferred":[
        "\u9ad8\u67a7"
    ],
    "wof:name":"Gaojian",
    "wof:placetype":"locality"
},
  "geometry": {"coordinates":[121.255,29.05194],"type":"Point"}
}