{
  "type": "Feature",
  "properties": {
    "gn:admin1_code":"30",
    "gn:asciiname":"Beilingjiao",
    "gn:country_code":"CN",
    "gn:dem":479,
    "gn:feature_class":"P",
    "gn:feature_code":"PPL",
    "gn:name":"Beilingjiao",
    "gn:population":0,
    "gn:timezone":"Asia/Shanghai",
    "iso:country":"CN",
    "name:und_x_variant":[
        "\u5317\u5cad\u811a"
    ],
    "wof:name":"Beilingjiao",
    "wof:placetype":"locality"
},
  "geometry": {"coordinates":[113.14578,24.48603],"type":"Point"}
}