{
  "type": "Feature",
  "properties": {
    "gn:admin1_code":"19",
    "gn:asciiname":"Wuzhangzi",
    "gn:country_code":"CN",
    "gn:dem":787,
    "gn:feature_class":"P",
    "gn:feature_code":"PPL",
    "gn:name":"Wuzhangzi",
    "gn:population":0,
    "gn:timezone":"Asia/Shanghai",
    "iso:country":"CN",
    "name:zho_x_preferred":[
        "\u5434\u6756\u5b50"
    ],
    "wof:name":"Wuzhangzi",
    "wof:placetype":"locality"
},
  "geometry": {"coordinates":[119.85794,41.91591],"type":"Point"}
}