{
  "type": "Feature",
  "properties": {
    "gn:admin1_code":"9.0",
    "gn:asciiname":"Niulizhuang",
    "gn:country_code":"CN",
    "gn:dem":63,
    "gn:feature_class":"P",
    "gn:feature_code":"PPL",
    "gn:name":"Niulizhuang",
    "gn:population":0,
    "gn:timezone":"Asia/Shanghai",
    "iso:country":"CN",
    "name:zho_x_preferred":[
        "\u725b\u674e\u5e84"
    ],
    "wof:name":"Niulizhuang",
    "wof:placetype":"locality"
},
  "geometry": {"coordinates":[114.52715000000001,35.76730999999999],"type":"Point"}
}