{
  "type": "Feature",
  "properties": {
    "gn:admin1_code":"24",
    "gn:asciiname":"Guojiashe",
    "gn:cc2":"CN",
    "gn:country_code":"CN",
    "gn:dem":1255,
    "gn:feature_class":"P",
    "gn:feature_code":"PPL",
    "gn:name":"Guojiashe",
    "gn:population":0,
    "gn:timezone":"Asia/Shanghai",
    "iso:country":"CN",
    "name:und_x_variant":[
        "Kuo-chia-she",
        "Guojiashe"
    ],
    "wof:name":"Guojiashe",
    "wof:placetype":"locality"
},
  "geometry": {"coordinates":[113.09999999999999,37.31667],"type":"Point"}
}