{
  "type": "Feature",
  "properties": {
    "gn:admin1_code":"7.0",
    "gn:asciiname":"Shuangxikou",
    "gn:country_code":"CN",
    "gn:dem":513,
    "gn:feature_class":"P",
    "gn:feature_code":"PPL",
    "gn:name":"Shuangxikou",
    "gn:population":0,
    "gn:timezone":"Asia/Shanghai",
    "iso:country":"CN",
    "name:und_x_variant":[
        "\u53cc\u6eaa\u53e3"
    ],
    "name:zho_x_preferred":[
        "\u53cc\u6eaa\u53e3"
    ],
    "wof:name":"Shuangxikou",
    "wof:placetype":"locality"
},
  "geometry": {"coordinates":[118.38809999999999,26.01142],"type":"Point"}
}