{
  "type": "Feature",
  "properties": {
    "gn:admin1_code":"5.0",
    "gn:asciiname":"Dawangcun",
    "gn:country_code":"CN",
    "gn:dem":320,
    "gn:feature_class":"P",
    "gn:feature_code":"PPL",
    "gn:name":"Dawangcun",
    "gn:population":0,
    "gn:timezone":"Asia/Shanghai",
    "iso:country":"CN",
    "name:zho_x_preferred":[
        "\u5927\u65fa\u6751"
    ],
    "wof:name":"Dawangcun",
    "wof:placetype":"locality"
},
  "geometry": {"coordinates":[125.73336999999999,43.20269],"type":"Point"}
}