{
  "type": "Feature",
  "properties": {
    "gn:admin1_code":"26.0",
    "gn:asciiname":"Zhanjiawan",
    "gn:country_code":"CN",
    "gn:dem":1336,
    "gn:feature_class":"P",
    "gn:feature_code":"PPL",
    "gn:name":"Zhanjiawan",
    "gn:population":0,
    "gn:timezone":"Asia/Shanghai",
    "iso:country":"CN",
    "name:zho_x_preferred":[
        "\u5360\u5bb6\u6e7e"
    ],
    "wof:name":"Zhanjiawan",
    "wof:placetype":"locality"
},
  "geometry": {"coordinates":[109.01288999999998,33.74186],"type":"Point"}
}