{
  "type": "Feature",
  "properties": {
    "gn:admin1_code":"01",
    "gn:asciiname":"Liyang",
    "gn:country_code":"CN",
    "gn:dem":23,
    "gn:feature_class":"P",
    "gn:feature_code":"PPLA3",
    "gn:name":"Liyang",
    "gn:population":0,
    "gn:timezone":"Asia/Shanghai",
    "iso:country":"CN",
    "name:und_x_variant":[
        "Ho",
        "Hochow",
        "Ho-hsien",
        "Ho-han",
        "Hexian",
        "Liyang",
        "Liyang Zhen"
    ],
    "name:zho_x_preferred":[
        "\u5386\u9633"
    ],
    "name:zho_x_variant":[
        "\u548c\u53bf"
    ],
    "wof:name":"Liyang",
    "wof:placetype":"locality"
},
  "geometry": {"coordinates":[118.35731,31.71772],"type":"Point"}
}