{
  "type": "Feature",
  "properties": {
    "gn:admin1_code":"8.0",
    "gn:asciiname":"Yuanjia Dagang",
    "gn:country_code":"CN",
    "gn:dem":146,
    "gn:feature_class":"P",
    "gn:feature_code":"PPL",
    "gn:name":"Yuanjia Dagang",
    "gn:population":0,
    "gn:timezone":"Asia/Shanghai",
    "iso:country":"CN",
    "name:zho_x_preferred":[
        "\u8881\u5bb6\u5927\u5c97"
    ],
    "wof:name":"Yuanjia Dagang",
    "wof:placetype":"locality"
},
  "geometry": {"coordinates":[124.81422999999999,46.58042],"type":"Point"}
}