{
  "type": "Feature",
  "properties": {
    "gn:country":"CN",
    "gn:fcode":"PPL",
    "gn:population":990,
    "iso:country":"CN",
    "name:ceb_x_preferred":[
        "Longcheng Qu"
    ],
    "name:deu_x_preferred":[
        "Longcheng"
    ],
    "name:jpn_x_preferred":[
        "\u7adc\u57ce\u533a"
    ],
    "name:kor_x_preferred":[
        "\ub8fd\uccad\uad6c"
    ],
    "name:nor_x_preferred":[
        "Longcheng"
    ],
    "name:rus_x_preferred":[
        "\u041b\u0443\u043d\u0447\u044d\u043d"
    ],
    "name:swe_x_preferred":[
        "Longcheng"
    ],
    "name:ukr_x_preferred":[
        "\u041b\u0443\u043d\u0447\u0435\u043d"
    ],
    "name:und_x_variant":[
        "Lung-ch\u2019eng"
    ],
    "name:vie_x_preferred":[
        "Long Th\u00e0nh"
    ],
    "name:zho_x_preferred":[
        "\u9f99\u57ce\u533a"
    ],
    "qs:name":"Longcheng",
    "qs:photos_9r":0,
    "qs:photos_sr":0,
    "qs:pop_sr":"2",
    "wd:wordcount":132,
    "wof:name":"Longcheng",
    "wof:placetype":"locality",
    "wof:population":990
},
  "geometry": {"coordinates":[109.77722,26.03389],"type":"Point"}
}