{
  "type": "Feature",
  "properties": {
    "gn:country":"CN",
    "gn:fcode":"PPL",
    "gn:pop":990,
    "iso:country":"CN",
    "name:unk_x_variant":[
        "Lung-ch\u2019eng"
    ],
    "qs:name":"Longcheng",
    "qs:photos_9r":0,
    "qs:photos_sr":0,
    "qs:pop_sr":"2",
    "wd:wordcount":132,
    "wof:name":"Longcheng",
    "wof:placetype":"locality",
    "wof:population":990
},
  "geometry": {"coordinates":[109.77722,26.03389],"type":"Point"}
}