{
  "type": "Feature",
  "properties": {
    "gn:admin1_code":"4.0",
    "gn:asciiname":"Qianmao Chenzhuang",
    "gn:country_code":"CN",
    "gn:dem":31,
    "gn:feature_class":"P",
    "gn:feature_code":"PPL",
    "gn:name":"Qianmao Chenzhuang",
    "gn:population":0,
    "gn:timezone":"Asia/Shanghai",
    "iso:country":"CN",
    "name:zho_x_preferred":[
        "\u524d\u8305\u9648\u5e84"
    ],
    "wof:name":"Qianmao Chenzhuang",
    "wof:placetype":"locality"
},
  "geometry": {"coordinates":[119.24985,31.7689],"type":"Point"}
}