{
  "type": "Feature",
  "properties": {
    "gn:admin1_code":"14.0",
    "gn:asciiname":"Samru",
    "gn:country_code":"CN",
    "gn:dem":3777,
    "gn:feature_class":"P",
    "gn:feature_code":"PPLF",
    "gn:name":"Samru",
    "gn:population":0,
    "gn:timezone":"Asia/Urumqi",
    "iso:country":"CN",
    "name:bod_x_preferred":[
        "Samru"
    ],
    "name:zho_x_preferred":[
        "Shangri"
    ],
    "name:zho_x_variant":[
        "\u5c1a\u65e5"
    ],
    "wof:name":"Samru",
    "wof:placetype":"locality"
},
  "geometry": {"coordinates":[96.65248,31.6529],"type":"Point"}
}