{
  "type": "Feature",
  "properties": {
    "gn:admin1_code":"2",
    "gn:asciiname":"Xiashan",
    "gn:country_code":"CN",
    "gn:dem":180,
    "gn:feature_class":"P",
    "gn:feature_code":"PPLA4",
    "gn:name":"Xiashan",
    "gn:population":0,
    "gn:timezone":"Asia/Shanghai",
    "iso:country":"CN",
    "name:zho_x_preferred":[
        "\u971e\u5c71"
    ],
    "wof:name":"Xiashan",
    "wof:placetype":"locality"
},
  "geometry": {"coordinates":[118.40595999999999,29.33198],"type":"Point"}
}