{
  "type": "Feature",
  "properties": {
    "gn:admin1_code":"24",
    "gn:asciiname":"Beilijie",
    "gn:country_code":"CN",
    "gn:dem":1053,
    "gn:feature_class":"P",
    "gn:feature_code":"PPL",
    "gn:name":"Beilijie",
    "gn:population":0,
    "gn:timezone":"Asia/Shanghai",
    "iso:country":"CN",
    "name:zho_x_preferred":[
        "\u5317\u674e\u8857"
    ],
    "wof:name":"Beilijie",
    "wof:placetype":"locality"
},
  "geometry": {"coordinates":[113.0851,35.3991],"type":"Point"}
}