{
  "type": "Feature",
  "properties": {
    "gn:admin1_code":"15.0",
    "gn:asciiname":"Shijia Wanzi",
    "gn:country_code":"CN",
    "gn:dem":1276,
    "gn:feature_class":"P",
    "gn:feature_code":"PPL",
    "gn:name":"Shijia Wanzi",
    "gn:population":0,
    "gn:timezone":"Asia/Shanghai",
    "iso:country":"CN",
    "name:zho_x_preferred":[
        "\u77f3\u5bb6\u6e7e\u5b50"
    ],
    "wof:name":"Shijia Wanzi",
    "wof:placetype":"locality"
},
  "geometry": {"coordinates":[108.053,35.6624],"type":"Point"}
}