{
  "type": "Feature",
  "properties": {
    "gn:admin1_code":"30.0",
    "gn:asciiname":"Xiaowu",
    "gn:country_code":"CN",
    "gn:dem":112,
    "gn:feature_class":"P",
    "gn:feature_code":"PPL",
    "gn:name":"Xiaowu",
    "gn:population":0,
    "gn:timezone":"Asia/Shanghai",
    "iso:country":"CN",
    "name:ceb_x_preferred":[
        "Xiaowu"
    ],
    "name:swe_x_preferred":[
        "Xiaowu"
    ],
    "name:zho_x_preferred":[
        "\u8096\u5c4b"
    ],
    "wof:name":"Xiaowu",
    "wof:placetype":"locality"
},
  "geometry": {"coordinates":[113.99178000000001,24.3082],"type":"Point"}
}