{
  "type": "Feature",
  "properties": {
    "gn:admin1_code":"8.0",
    "gn:asciiname":"Laochejiatun",
    "gn:country_code":"CN",
    "gn:dem":176,
    "gn:feature_class":"P",
    "gn:feature_code":"PPL",
    "gn:name":"Laochejiatun",
    "gn:population":0,
    "gn:timezone":"Asia/Shanghai",
    "iso:country":"CN",
    "name:zho_x_preferred":[
        "\u8001\u8f66\u5bb6\u5c6f"
    ],
    "wof:name":"Laochejiatun",
    "wof:placetype":"locality"
},
  "geometry": {"coordinates":[127.29404,46.37425],"type":"Point"}
}