{
  "type": "Feature",
  "properties": {
    "gn:admin1_code":"9.0",
    "gn:asciiname":"Xinghua",
    "gn:country_code":"CN",
    "gn:dem":74,
    "gn:feature_class":"P",
    "gn:feature_code":"PPL",
    "gn:name":"Xinghua",
    "gn:population":0,
    "gn:timezone":"Asia/Shanghai",
    "iso:country":"CN",
    "name:ceb_x_preferred":[
        "Xinghua"
    ],
    "name:deu_x_preferred":[
        "Xinghua"
    ],
    "name:fra_x_preferred":[
        "Xinghua"
    ],
    "name:swe_x_preferred":[
        "Xinghua"
    ],
    "name:zho_x_preferred":[
        "\u674f\u82b1"
    ],
    "wof:name":"Xinghua",
    "wof:placetype":"locality"
},
  "geometry": {"coordinates":[114.39225999999999,36.12268],"type":"Point"}
}