{
  "type": "Feature",
  "properties": {
    "gn:admin1_code":"24.0",
    "gn:asciiname":"Xihengshan",
    "gn:country_code":"CN",
    "gn:dem":998,
    "gn:feature_class":"P",
    "gn:feature_code":"PPL",
    "gn:name":"Xihengshan",
    "gn:population":0,
    "gn:timezone":"Asia/Shanghai",
    "iso:country":"CN",
    "name:zho_x_preferred":[
        "\u897f\u6a2a\u5c71"
    ],
    "wof:name":"Xihengshan",
    "wof:placetype":"locality"
},
  "geometry": {"coordinates":[113.79722,37.42905],"type":"Point"}
}