{
  "type": "Feature",
  "properties": {
    "gn:admin1_code":"33.0",
    "gn:asciiname":"Xuanshigou",
    "gn:country_code":"CN",
    "gn:dem":1223,
    "gn:feature_class":"P",
    "gn:feature_code":"PPL",
    "gn:name":"Xuanshigou",
    "gn:population":0,
    "gn:timezone":"Asia/Shanghai",
    "iso:country":"CN",
    "name:zho_x_preferred":[
        "\u65cb\u77f3\u6c9f"
    ],
    "wof:name":"Xuanshigou",
    "wof:placetype":"locality"
},
  "geometry": {"coordinates":[108.10576,29.82973],"type":"Point"}
}