{
  "type": "Feature",
  "properties": {
    "gn:admin1_code":"14.0",
    "gn:asciiname":"Quqarka",
    "gn:country_code":"CN",
    "gn:dem":4102,
    "gn:feature_class":"P",
    "gn:feature_code":"PPL",
    "gn:name":"Quqarka",
    "gn:population":0,
    "gn:timezone":"Asia/Urumqi",
    "iso:country":"CN",
    "name:bod_x_preferred":[
        "Quqarka"
    ],
    "name:zho_x_preferred":[
        "Quqiaka"
    ],
    "name:zho_x_variant":[
        "\u66f2\u6070\u5361"
    ],
    "wof:name":"Quqarka",
    "wof:placetype":"locality"
},
  "geometry": {"coordinates":[93.70699999999999,32.007],"type":"Point"}
}