{
  "type": "Feature",
  "properties": {
    "gn:admin1_code":"29.0",
    "gn:asciiname":"Dagumei",
    "gn:country_code":"CN",
    "gn:dem":2620,
    "gn:feature_class":"P",
    "gn:feature_code":"PPL",
    "gn:name":"Dagumei",
    "gn:population":0,
    "gn:timezone":"Asia/Shanghai",
    "iso:country":"CN",
    "name:zho_x_preferred":[
        "\u5927\u53e4\u6885"
    ],
    "wof:name":"Dagumei",
    "wof:placetype":"locality"
},
  "geometry": {"coordinates":[99.4169,26.8396],"type":"Point"}
}