{
  "type": "Feature",
  "properties": {
    "gn:admin1_code":"15.0",
    "gn:asciiname":"Dujiaquan",
    "gn:country_code":"CN",
    "gn:dem":2635,
    "gn:feature_class":"P",
    "gn:feature_code":"PPL",
    "gn:name":"Dujiaquan",
    "gn:population":0,
    "gn:timezone":"Asia/Shanghai",
    "iso:country":"CN",
    "name:zho_x_preferred":[
        "\u675c\u5bb6\u5708"
    ],
    "wof:name":"Dujiaquan",
    "wof:placetype":"locality"
},
  "geometry": {"coordinates":[101.086,38.3228],"type":"Point"}
}