{
  "type": "Feature",
  "properties": {
    "gn:admin1_code":"4.0",
    "gn:asciiname":"Xiangzhai",
    "gn:country_code":"CN",
    "gn:dem":15,
    "gn:feature_class":"P",
    "gn:feature_code":"PPL",
    "gn:name":"Xiangzhai",
    "gn:population":0,
    "gn:timezone":"Asia/Shanghai",
    "iso:country":"CN",
    "name:zho_x_preferred":[
        "\u9879\u5b85"
    ],
    "wof:name":"Xiangzhai",
    "wof:placetype":"locality"
},
  "geometry": {"coordinates":[118.562,34.1898],"type":"Point"}
}