{
  "type": "Feature",
  "properties": {
    "gn:admin1_code":"29.0",
    "gn:asciiname":"Dachushui",
    "gn:country_code":"CN",
    "gn:dem":1980,
    "gn:feature_class":"P",
    "gn:feature_code":"PPL",
    "gn:name":"Dachushui",
    "gn:population":0,
    "gn:timezone":"Asia/Shanghai",
    "iso:country":"CN",
    "name:zho_x_preferred":[
        "\u5927\u51fa\u6c34"
    ],
    "wof:name":"Dachushui",
    "wof:placetype":"locality"
},
  "geometry": {"coordinates":[99.26739999999999,23.9327],"type":"Point"}
}