{
  "type": "Feature",
  "properties": {
    "gn:admin1_code":"12.0",
    "gn:asciiname":"Jiucai",
    "gn:country_code":"CN",
    "gn:dem":959,
    "gn:feature_class":"P",
    "gn:feature_code":"PPL",
    "gn:name":"Jiucai",
    "gn:population":0,
    "gn:timezone":"Asia/Shanghai",
    "iso:country":"CN",
    "name:zho_x_preferred":[
        "Jiucai"
    ],
    "name:zho_x_variant":[
        "\u97ee\u83dc"
    ],
    "wof:name":"Jiucai",
    "wof:placetype":"locality"
},
  "geometry": {"coordinates":[109.31870000000001,29.62898],"type":"Point"}
}