{
  "type": "Feature",
  "properties": {
    "gn:admin1_code":"24.0",
    "gn:asciiname":"Liujiagelengcun",
    "gn:country_code":"CN",
    "gn:dem":1123,
    "gn:feature_class":"P",
    "gn:feature_code":"PPL",
    "gn:name":"Liujiagelengcun",
    "gn:population":0,
    "gn:timezone":"Asia/Shanghai",
    "iso:country":"CN",
    "name:zho_x_preferred":[
        "\u5218\u5bb6\u572a\u5844\u6751"
    ],
    "wof:name":"Liujiagelengcun",
    "wof:placetype":"locality"
},
  "geometry": {"coordinates":[110.87271,38.01542],"type":"Point"}
}