{
  "type": "Feature",
  "properties": {
    "gn:admin1_code":"21.0",
    "gn:asciiname":"Caojiawan",
    "gn:country_code":"CN",
    "gn:dem":1655,
    "gn:feature_class":"P",
    "gn:feature_code":"PPL",
    "gn:name":"Caojiawan",
    "gn:population":0,
    "gn:timezone":"Asia/Shanghai",
    "iso:country":"CN",
    "name:und_x_variant":[
        "\u66f9\u5bb6\u6e7e"
    ],
    "name:zho_x_preferred":[
        "\u66f9\u5bb6\u6e7e"
    ],
    "wof:name":"Caojiawan",
    "wof:placetype":"locality"
},
  "geometry": {"coordinates":[106.82407000000001,36.22107000000001],"type":"Point"}
}