{
  "type": "Feature",
  "properties": {
    "gn:admin1_code":"25.0",
    "gn:asciiname":"Liguanyingcun",
    "gn:country_code":"CN",
    "gn:dem":35,
    "gn:feature_class":"P",
    "gn:feature_code":"PPL",
    "gn:name":"Liguanyingcun",
    "gn:population":0,
    "gn:timezone":"Asia/Shanghai",
    "iso:country":"CN",
    "name:zho_x_preferred":[
        "\u674e\u5b98\u8425\u6751"
    ],
    "wof:name":"Liguanyingcun",
    "wof:placetype":"locality"
},
  "geometry": {"coordinates":[115.84174,36.73907],"type":"Point"}
}