{
  "type": "Feature",
  "properties": {
    "gn:admin1_code":"11.0",
    "gn:asciiname":"Tengli",
    "gn:country_code":"CN",
    "gn:dem":983,
    "gn:feature_class":"P",
    "gn:feature_code":"PPL",
    "gn:name":"Tengli",
    "gn:population":0,
    "gn:timezone":"Asia/Shanghai",
    "iso:country":"CN",
    "name:zho_x_preferred":[
        "\u817e\u91cc"
    ],
    "wof:name":"Tengli",
    "wof:placetype":"locality"
},
  "geometry": {"coordinates":[113.78702,26.05938],"type":"Point"}
}