{
  "type": "Feature",
  "properties": {
    "gn:admin1_code":"7.0",
    "gn:asciiname":"Dingdi",
    "gn:country_code":"CN",
    "gn:dem":225,
    "gn:feature_class":"P",
    "gn:feature_code":"PPL",
    "gn:name":"Dingdi",
    "gn:population":0,
    "gn:timezone":"Asia/Shanghai",
    "iso:country":"CN",
    "name:und_x_variant":[
        "\u4e01\u5730"
    ],
    "name:zho_x_preferred":[
        "\u4e01\u5730"
    ],
    "wof:name":"Dingdi",
    "wof:placetype":"locality"
},
  "geometry": {"coordinates":[118.18049999999999,26.33183],"type":"Point"}
}