{
  "type": "Feature",
  "properties": {
    "gn:admin1_code":"14",
    "gn:asciiname":"Xaxi",
    "gn:country_code":"CN",
    "gn:dem":4468,
    "gn:feature_class":"P",
    "gn:feature_code":"PPL",
    "gn:name":"Xaxi",
    "gn:population":0,
    "gn:timezone":"Asia/Urumqi",
    "iso:country":"CN",
    "name:bod_x_preferred":[
        "\u0f5e\u0f0b\u0f42\u0f5e\u0f72\u0f66"
    ],
    "wof:name":"Xaxi",
    "wof:placetype":"locality"
},
  "geometry": {"coordinates":[91.05932,28.89526],"type":"Point"}
}