{
  "type": "Feature",
  "properties": {
    "gn:admin1_code":"12.0",
    "gn:asciiname":"Xintai",
    "gn:country_code":"CN",
    "gn:dem":27,
    "gn:feature_class":"P",
    "gn:feature_code":"PPL",
    "gn:name":"Xintai",
    "gn:population":0,
    "gn:timezone":"Asia/Shanghai",
    "iso:country":"CN",
    "name:ceb_x_preferred":[
        "Xintai"
    ],
    "name:deu_x_preferred":[
        "Xintai"
    ],
    "name:fra_x_preferred":[
        "Xintai"
    ],
    "name:ita_x_preferred":[
        "Xintai"
    ],
    "name:jpn_x_preferred":[
        "\u65b0\u6cf0\u5e02"
    ],
    "name:kik_x_preferred":[
        "Xintai"
    ],
    "name:kor_x_preferred":[
        "\uc2e0\ud0c0\uc774\uc2dc"
    ],
    "name:mlg_x_preferred":[
        "Xintai"
    ],
    "name:nor_x_preferred":[
        "Xintai"
    ],
    "name:rus_x_preferred":[
        "\u0421\u0438\u043d\u044c\u0442\u0430\u0439"
    ],
    "name:srp_x_preferred":[
        "\u0421\u0438\u043d\u0442\u0430\u0458"
    ],
    "name:swe_x_preferred":[
        "Xintai"
    ],
    "name:ukr_x_preferred":[
        "\u0421\u0456\u043d\u044c\u0442\u0430\u0439"
    ],
    "name:vie_x_preferred":[
        "T\u00e2n Th\u00e1i"
    ],
    "name:war_x_preferred":[
        "Xintai"
    ],
    "name:zho_x_preferred":[
        "\u65b0\u53f0"
    ],
    "name:zho_x_variant":[
        "\u65b0\u6cf0\u5e02"
    ],
    "wof:name":"Xintai",
    "wof:placetype":"locality"
},
  "geometry": {"coordinates":[113.57923,30.80354],"type":"Point"}
}