{
  "type": "Feature",
  "properties": {
    "gn:admin1_code":"30.0",
    "gn:asciiname":"Panhe",
    "gn:country_code":"CN",
    "gn:dem":0,
    "gn:feature_class":"P",
    "gn:feature_code":"PPL",
    "gn:name":"Panhe",
    "gn:population":0,
    "gn:timezone":"Asia/Shanghai",
    "iso:country":"CN",
    "name:zho_x_preferred":[
        "\u6cee\u6cb3"
    ],
    "wof:name":"Panhe",
    "wof:placetype":"locality"
},
  "geometry": {"coordinates":[112.97214,22.43094],"type":"Point"}
}