{
  "type": "Feature",
  "properties": {
    "gn:admin1_code":"29.0",
    "gn:asciiname":"Zhaolaodi",
    "gn:country_code":"CN",
    "gn:dem":1982,
    "gn:feature_class":"P",
    "gn:feature_code":"PPL",
    "gn:name":"Zhaolaodi",
    "gn:population":0,
    "gn:timezone":"Asia/Shanghai",
    "iso:country":"CN",
    "name:zho_x_preferred":[
        "\u8d75\u8001\u5730"
    ],
    "wof:name":"Zhaolaodi",
    "wof:placetype":"locality"
},
  "geometry": {"coordinates":[98.3502,24.742],"type":"Point"}
}