{
  "type": "Feature",
  "properties": {
    "gn:admin1_code":"32.0",
    "gn:asciiname":"Xiagu'amo",
    "gn:country_code":"CN",
    "gn:dem":2321,
    "gn:feature_class":"P",
    "gn:feature_code":"PPL",
    "gn:name":"Xiagu\u2019amo",
    "gn:population":0,
    "gn:timezone":"Asia/Shanghai",
    "iso:country":"CN",
    "name:zho_x_preferred":[
        "\u5477\u53e4\u963f\u83ab"
    ],
    "name:zho_x_variant":[
        "Xiagu\u2019amo"
    ],
    "wof:name":"Xiagu'amo",
    "wof:placetype":"locality"
},
  "geometry": {"coordinates":[102.86749,27.91704],"type":"Point"}
}