{
  "type": "Feature",
  "properties": {
    "gn:admin1_code":"15.0",
    "gn:asciiname":"Dacha",
    "gn:country_code":"CN",
    "gn:dem":1573,
    "gn:feature_class":"P",
    "gn:feature_code":"PPL",
    "gn:name":"Dacha",
    "gn:population":0,
    "gn:timezone":"Asia/Shanghai",
    "iso:country":"CN",
    "name:zho_x_preferred":[
        "\u5927\u5c94"
    ],
    "wof:name":"Dacha",
    "wof:placetype":"locality"
},
  "geometry": {"coordinates":[106.932,35.8366],"type":"Point"}
}