{
  "type": "Feature",
  "properties": {
    "gn:admin1_code":"3.0",
    "gn:asciiname":"Peijia",
    "gn:country_code":"CN",
    "gn:dem":128,
    "gn:feature_class":"P",
    "gn:feature_code":"PPL",
    "gn:name":"Peijia",
    "gn:population":0,
    "gn:timezone":"Asia/Shanghai",
    "iso:country":"CN",
    "name:und_x_variant":[
        "\u57f9\u5bb6"
    ],
    "wof:name":"Peijia",
    "wof:placetype":"locality"
},
  "geometry": {"coordinates":[115.87569000000001,27.80159],"type":"Point"}
}