{
  "type": "Feature",
  "properties": {
    "gn:admin1_code":"5.0",
    "gn:asciiname":"Zhaojia Wopeng",
    "gn:country_code":"CN",
    "gn:dem":174,
    "gn:feature_class":"P",
    "gn:feature_code":"PPL",
    "gn:name":"Zhaojia Wopeng",
    "gn:population":0,
    "gn:timezone":"Asia/Shanghai",
    "iso:country":"CN",
    "name:zho_x_preferred":[
        "\u8d75\u5bb6\u7a9d\u68da"
    ],
    "wof:name":"Zhaojia Wopeng",
    "wof:placetype":"locality"
},
  "geometry": {"coordinates":[125.24477,44.27009],"type":"Point"}
}