{
  "type": "Feature",
  "properties": {
    "gn:admin1_code":"19.0",
    "gn:asciiname":"Songshu",
    "gn:country_code":"CN",
    "gn:dem":138,
    "gn:feature_class":"P",
    "gn:feature_code":"PPL",
    "gn:name":"Songshu",
    "gn:population":0,
    "gn:timezone":"Asia/Shanghai",
    "iso:country":"CN",
    "name:und_x_variant":[
        "\u677e\u6811"
    ],
    "name:zho_x_preferred":[
        "\u677e\u6811"
    ],
    "wof:name":"Songshu",
    "wof:placetype":"locality"
},
  "geometry": {"coordinates":[124.35697999999999,42.71113],"type":"Point"}
}