{
  "type": "Feature",
  "properties": {
    "gn:admin1_code":"24.0",
    "gn:asciiname":"Xiaohewan",
    "gn:country_code":"CN",
    "gn:dem":1517,
    "gn:feature_class":"P",
    "gn:feature_code":"PPL",
    "gn:name":"Xiaohewan",
    "gn:population":0,
    "gn:timezone":"Asia/Shanghai",
    "iso:country":"CN",
    "name:zho_x_preferred":[
        "\u5c0f\u6cb3\u6e7e"
    ],
    "wof:name":"Xiaohewan",
    "wof:placetype":"locality"
},
  "geometry": {"coordinates":[111.98283000000001,35.45721],"type":"Point"}
}