{
  "type": "Feature",
  "properties": {
    "gn:admin1_code":"26.0",
    "gn:asciiname":"Loudicun",
    "gn:country_code":"CN",
    "gn:dem":953,
    "gn:feature_class":"P",
    "gn:feature_code":"PPL",
    "gn:name":"Loudicun",
    "gn:population":0,
    "gn:timezone":"Asia/Shanghai",
    "iso:country":"CN",
    "name:zho_x_preferred":[
        "\u697c\u5e95\u6751"
    ],
    "wof:name":"Loudicun",
    "wof:placetype":"locality"
},
  "geometry": {"coordinates":[110.50507,37.80588],"type":"Point"}
}