{
  "type": "Feature",
  "properties": {
    "gn:admin1_code":"29.0",
    "gn:asciiname":"Asuogu",
    "gn:country_code":"CN",
    "gn:dem":1917,
    "gn:feature_class":"P",
    "gn:feature_code":"PPL",
    "gn:name":"Asuogu",
    "gn:population":0,
    "gn:timezone":"Asia/Shanghai",
    "iso:country":"CN",
    "name:zho_x_preferred":[
        "\u963f\u6240\u8c37"
    ],
    "wof:name":"Asuogu",
    "wof:placetype":"locality"
},
  "geometry": {"coordinates":[101.982,25.5727],"type":"Point"}
}