{
  "type": "Feature",
  "properties": {
    "gn:admin1_code":"32.0",
    "gn:asciiname":"Wufangzui",
    "gn:country_code":"CN",
    "gn:dem":364,
    "gn:feature_class":"P",
    "gn:feature_code":"PPL",
    "gn:name":"Wufangzui",
    "gn:population":0,
    "gn:timezone":"Asia/Shanghai",
    "iso:country":"CN",
    "name:zho_x_preferred":[
        "\u4e94\u623f\u5480"
    ],
    "wof:name":"Wufangzui",
    "wof:placetype":"locality"
},
  "geometry": {"coordinates":[105.938,31.2926],"type":"Point"}
}