{
  "type": "Feature",
  "properties": {
    "gn:admin1_code":"04",
    "gn:asciiname":"Dongyuemiao",
    "gn:cc2":"CN",
    "gn:country_code":"CN",
    "gn:dem":28,
    "gn:feature_class":"P",
    "gn:feature_code":"PPL",
    "gn:name":"Dongyuemiao",
    "gn:population":0,
    "gn:timezone":"Asia/Shanghai",
    "iso:country":"CN",
    "name:und_x_variant":[
        "Tung-y\u00fceh-miao",
        "Dongyuemiao"
    ],
    "wof:name":"Dongyuemiao",
    "wof:placetype":"locality"
},
  "geometry": {"coordinates":[119.23333,31.58333],"type":"Point"}
}