{
  "type": "Feature",
  "properties": {
    "gn:admin1_code":"29",
    "gn:asciiname":"Datun",
    "gn:country_code":"CN",
    "gn:dem":1892,
    "gn:feature_class":"P",
    "gn:feature_code":"PPL",
    "gn:name":"Datun",
    "gn:population":0,
    "gn:timezone":"Asia/Shanghai",
    "iso:country":"CN",
    "name:rus_x_preferred":[
        "\u0414\u0430\u0442\u0443\u043d"
    ],
    "name:zho_x_preferred":[
        "\u5927\u5c6f"
    ],
    "wof:name":"Datun",
    "wof:placetype":"locality"
},
  "geometry": {"coordinates":[102.46299999999999,24.9103],"type":"Point"}
}