{
  "type": "Feature",
  "properties": {
    "gn:admin1_code":"26.0",
    "gn:asciiname":"Houzhongjia Goucun",
    "gn:country_code":"CN",
    "gn:dem":981,
    "gn:feature_class":"P",
    "gn:feature_code":"PPL",
    "gn:name":"Houzhongjia Goucun",
    "gn:population":0,
    "gn:timezone":"Asia/Shanghai",
    "iso:country":"CN",
    "name:zho_x_preferred":[
        "\u540e\u949f\u5bb6\u6c9f\u6751"
    ],
    "wof:name":"Houzhongjia Goucun",
    "wof:placetype":"locality"
},
  "geometry": {"coordinates":[109.95699999999999,37.5638],"type":"Point"}
}