{
  "type": "Feature",
  "properties": {
    "gn:admin1_code":"32.0",
    "gn:asciiname":"Nianpanwan",
    "gn:country_code":"CN",
    "gn:dem":389,
    "gn:feature_class":"P",
    "gn:feature_code":"PPL",
    "gn:name":"Nianpanwan",
    "gn:population":0,
    "gn:timezone":"Asia/Shanghai",
    "iso:country":"CN",
    "name:zho_x_preferred":[
        "\u78be\u76d8\u6e7e"
    ],
    "wof:name":"Nianpanwan",
    "wof:placetype":"locality"
},
  "geometry": {"coordinates":[104.33799999999999,29.9533],"type":"Point"}
}