{
  "type": "Feature",
  "properties": {
    "gn:admin1_code":"1.0",
    "gn:asciiname":"Sixucun",
    "gn:country_code":"CN",
    "gn:dem":30,
    "gn:feature_class":"P",
    "gn:feature_code":"PPL",
    "gn:name":"Sixucun",
    "gn:population":0,
    "gn:timezone":"Asia/Shanghai",
    "iso:country":"CN",
    "name:zho_x_preferred":[
        "\u53f8\u5729\u6751"
    ],
    "wof:name":"Sixucun",
    "wof:placetype":"locality"
},
  "geometry": {"coordinates":[115.91118,32.49907],"type":"Point"}
}