{
  "type": "Feature",
  "properties": {
    "gn:admin1_code":"3",
    "gn:asciiname":"Zhangshuxia",
    "gn:country_code":"CN",
    "gn:dem":152,
    "gn:feature_class":"P",
    "gn:feature_code":"PPL",
    "gn:name":"Zhangshuxia",
    "gn:population":0,
    "gn:timezone":"Asia/Shanghai",
    "iso:country":"CN",
    "name:zho_x_preferred":[
        "\u6a1f\u6811\u4e0b"
    ],
    "wof:name":"Zhangshuxia",
    "wof:placetype":"locality"
},
  "geometry": {"coordinates":[114.60342,25.54902],"type":"Point"}
}