{
  "type": "Feature",
  "properties": {
    "gn:admin1_code":"29.0",
    "gn:asciiname":"Shanchashu",
    "gn:country_code":"CN",
    "gn:dem":2067,
    "gn:feature_class":"P",
    "gn:feature_code":"PPL",
    "gn:name":"Shanchashu",
    "gn:population":0,
    "gn:timezone":"Asia/Shanghai",
    "iso:country":"CN",
    "name:zho_x_preferred":[
        "\u5c71\u6942\u6811"
    ],
    "wof:name":"Shanchashu",
    "wof:placetype":"locality"
},
  "geometry": {"coordinates":[103.85899999999999,24.1537],"type":"Point"}
}