{
  "type": "Feature",
  "properties": {
    "gn:admin1_code":"12.0",
    "gn:asciiname":"Huazikou",
    "gn:country_code":"CN",
    "gn:dem":46,
    "gn:feature_class":"P",
    "gn:feature_code":"PPL",
    "gn:name":"Huazikou",
    "gn:population":0,
    "gn:timezone":"Asia/Shanghai",
    "iso:country":"CN",
    "name:zho_x_preferred":[
        "\u5212\u5b50\u53e3"
    ],
    "wof:name":"Huazikou",
    "wof:placetype":"locality"
},
  "geometry": {"coordinates":[112.56524,31.13856],"type":"Point"}
}