{
  "type": "Feature",
  "properties": {
    "gn:admin1_code":"24.0",
    "gn:asciiname":"Dingcun",
    "gn:country_code":"CN",
    "gn:dem":414,
    "gn:feature_class":"P",
    "gn:feature_code":"PPL",
    "gn:name":"Dingcun",
    "gn:population":0,
    "gn:timezone":"Asia/Shanghai",
    "iso:country":"CN",
    "name:und_x_variant":[
        "\u4e01\u6751",
        "Ting-ts\u2019un"
    ],
    "name:zho_x_preferred":[
        "\u4e01\u6751"
    ],
    "wof:name":"Dingcun",
    "wof:placetype":"locality"
},
  "geometry": {"coordinates":[111.10078,35.6217],"type":"Point"}
}