{
  "type": "Feature",
  "properties": {
    "gn:admin1_code":"10",
    "gn:asciiname":"Songwangzhuang",
    "gn:country_code":"CN",
    "gn:dem":19,
    "gn:feature_class":"P",
    "gn:feature_code":"PPL",
    "gn:name":"Songwangzhuang",
    "gn:population":0,
    "gn:timezone":"Asia/Shanghai",
    "iso:country":"CN",
    "name:zho_x_preferred":[
        "\u5b8b\u738b\u5e84"
    ],
    "wof:name":"Songwangzhuang",
    "wof:placetype":"locality"
},
  "geometry": {"coordinates":[116.25299,37.96176],"type":"Point"}
}