{
  "type": "Feature",
  "properties": {
    "gn:admin1_code":"33.0",
    "gn:asciiname":"Leiping Xinjie",
    "gn:country_code":"CN",
    "gn:dem":463,
    "gn:feature_class":"P",
    "gn:feature_code":"PPL",
    "gn:name":"Leiping Xinjie",
    "gn:population":0,
    "gn:timezone":"Asia/Shanghai",
    "iso:country":"CN",
    "name:zho_x_preferred":[
        "\u96f7\u576a\u65b0\u8857"
    ],
    "wof:name":"Leiping Xinjie",
    "wof:placetype":"locality"
},
  "geometry": {"coordinates":[109.81882,30.91738],"type":"Point"}
}