{
  "type": "Feature",
  "properties": {
    "gn:admin1_code":"29.0",
    "gn:asciiname":"Jiaxinzhai",
    "gn:country_code":"CN",
    "gn:dem":1098,
    "gn:feature_class":"P",
    "gn:feature_code":"PPL",
    "gn:name":"Jiaxinzhai",
    "gn:population":0,
    "gn:timezone":"Asia/Shanghai",
    "iso:country":"CN",
    "name:zho_x_preferred":[
        "\u5bb6\u65b0\u5be8"
    ],
    "wof:name":"Jiaxinzhai",
    "wof:placetype":"locality"
},
  "geometry": {"coordinates":[103.285,23.6896],"type":"Point"}
}