{
  "type": "Feature",
  "properties": {
    "gn:admin1_code":"1.0",
    "gn:asciiname":"Huayuanhu",
    "gn:country_code":"CN",
    "gn:dem":59,
    "gn:feature_class":"P",
    "gn:feature_code":"PPL",
    "gn:name":"Huayuanhu",
    "gn:population":0,
    "gn:timezone":"Asia/Shanghai",
    "iso:country":"CN",
    "name:zho_x_preferred":[
        "\u82b1\u56ed\u6e56"
    ],
    "wof:name":"Huayuanhu",
    "wof:placetype":"locality"
},
  "geometry": {"coordinates":[117.66446000000001,32.53261],"type":"Point"}
}