{
  "type": "Feature",
  "properties": {
    "gn:admin1_code":"20.0",
    "gn:asciiname":"Beitouhe",
    "gn:country_code":"CN",
    "gn:dem":725,
    "gn:feature_class":"P",
    "gn:feature_code":"PPL",
    "gn:name":"Beitouhe",
    "gn:population":0,
    "gn:timezone":"Asia/Shanghai",
    "iso:country":"CN",
    "name:zho_x_preferred":[
        "\u5317\u5934\u6cb3"
    ],
    "wof:name":"Beitouhe",
    "wof:placetype":"locality"
},
  "geometry": {"coordinates":[121.14199000000001,49.01043],"type":"Point"}
}