{
  "type": "Feature",
  "properties": {
    "gn:admin1_code":"5.0",
    "gn:asciiname":"Dayucun",
    "gn:country_code":"CN",
    "gn:dem":338,
    "gn:feature_class":"P",
    "gn:feature_code":"PPL",
    "gn:name":"Dayucun",
    "gn:population":0,
    "gn:timezone":"Asia/Shanghai",
    "iso:country":"CN",
    "name:zho_x_preferred":[
        "\u5927\u6986\u6751"
    ],
    "wof:name":"Dayucun",
    "wof:placetype":"locality"
},
  "geometry": {"coordinates":[125.29125000000001,42.80362],"type":"Point"}
}