{
  "type": "Feature",
  "properties": {
    "gn:admin1_code":"9",
    "gn:asciiname":"Guolou",
    "gn:country_code":"CN",
    "gn:dem":56,
    "gn:feature_class":"P",
    "gn:feature_code":"PPL",
    "gn:name":"Guolou",
    "gn:population":0,
    "gn:timezone":"Asia/Shanghai",
    "iso:country":"CN",
    "name:zho_x_preferred":[
        "\u90ed\u697c"
    ],
    "wof:name":"Guolou",
    "wof:placetype":"locality"
},
  "geometry": {"coordinates":[115.33199999999999,34.3532],"type":"Point"}
}