{
  "type": "Feature",
  "properties": {
    "gn:admin1_code":"11",
    "gn:asciiname":"Tangxia",
    "gn:cc2":"CN",
    "gn:country_code":"CN",
    "gn:dem":489,
    "gn:feature_class":"P",
    "gn:feature_code":"PPL",
    "gn:name":"Tangxia",
    "gn:population":0,
    "gn:timezone":"Asia/Shanghai",
    "iso:country":"CN",
    "name:und_x_variant":[
        "T\u2019ang-hsia",
        "Tangxia"
    ],
    "wof:name":"Tangxia",
    "wof:placetype":"locality"
},
  "geometry": {"coordinates":[113.68333,25.76667],"type":"Point"}
}