{
  "type": "Feature",
  "properties": {
    "gn:admin1_code":"5.0",
    "gn:asciiname":"Sifatun",
    "gn:country_code":"CN",
    "gn:dem":151,
    "gn:feature_class":"P",
    "gn:feature_code":"PPL",
    "gn:name":"Sifatun",
    "gn:population":0,
    "gn:timezone":"Asia/Shanghai",
    "iso:country":"CN",
    "name:zho_x_preferred":[
        "\u56db\u53d1\u5c6f"
    ],
    "wof:name":"Sifatun",
    "wof:placetype":"locality"
},
  "geometry": {"coordinates":[122.81766,45.77133],"type":"Point"}
}