{
  "type": "Feature",
  "properties": {
    "gn:admin1_code":"29.0",
    "gn:asciiname":"Tianbaodong",
    "gn:country_code":"CN",
    "gn:dem":2779,
    "gn:feature_class":"P",
    "gn:feature_code":"PPL",
    "gn:name":"Tianbaodong",
    "gn:population":0,
    "gn:timezone":"Asia/Shanghai",
    "iso:country":"CN",
    "name:zho_x_preferred":[
        "\u5929\u4fdd\u6d1e"
    ],
    "wof:name":"Tianbaodong",
    "wof:placetype":"locality"
},
  "geometry": {"coordinates":[102.497,26.1938],"type":"Point"}
}