{
  "type": "Feature",
  "properties": {
    "gn:admin1_code":"32.0",
    "gn:asciiname":"Shifosi",
    "gn:country_code":"CN",
    "gn:dem":596,
    "gn:feature_class":"P",
    "gn:feature_code":"PPL",
    "gn:name":"Shifosi",
    "gn:population":0,
    "gn:timezone":"Asia/Shanghai",
    "iso:country":"CN",
    "name:zho_x_preferred":[
        "\u77f3\u4f5b\u5bfa"
    ],
    "wof:name":"Shifosi",
    "wof:placetype":"locality"
},
  "geometry": {"coordinates":[104.38581000000001,31.57392],"type":"Point"}
}