{
  "type": "Feature",
  "properties": {
    "gn:admin1_code":"7.0",
    "gn:asciiname":"Xiadanyang",
    "gn:country_code":"CN",
    "gn:dem":76,
    "gn:feature_class":"P",
    "gn:feature_code":"PPL",
    "gn:name":"Xiadanyang",
    "gn:population":0,
    "gn:timezone":"Asia/Shanghai",
    "iso:country":"CN",
    "name:und_x_variant":[
        "\u4e0b\u4e39\u9633"
    ],
    "name:zho_x_preferred":[
        "Xiadanyang"
    ],
    "wof:name":"Xiadanyang",
    "wof:placetype":"locality"
},
  "geometry": {"coordinates":[119.23183,26.14047],"type":"Point"}
}