{
  "type": "Feature",
  "properties": {
    "gn:admin1_code":"3.0",
    "gn:asciiname":"Jiulu",
    "gn:country_code":"CN",
    "gn:dem":410,
    "gn:feature_class":"P",
    "gn:feature_code":"PPL",
    "gn:name":"Jiulu",
    "gn:population":0,
    "gn:timezone":"Asia/Shanghai",
    "iso:country":"CN",
    "name:zho_x_preferred":[
        "\u65e7\u8def"
    ],
    "wof:name":"Jiulu",
    "wof:placetype":"locality"
},
  "geometry": {"coordinates":[117.70668000000001,28.58537],"type":"Point"}
}