{
  "type": "Feature",
  "properties": {
    "gn:admin1_code":"29.0",
    "gn:asciiname":"Youfanggou",
    "gn:country_code":"CN",
    "gn:dem":2138,
    "gn:feature_class":"P",
    "gn:feature_code":"PPL",
    "gn:name":"Youfanggou",
    "gn:population":0,
    "gn:timezone":"Asia/Shanghai",
    "iso:country":"CN",
    "name:zho_x_preferred":[
        "\u6cb9\u623f\u6c9f"
    ],
    "wof:name":"Youfanggou",
    "wof:placetype":"locality"
},
  "geometry": {"coordinates":[101.124,26.2287],"type":"Point"}
}