{
  "type": "Feature",
  "properties": {
    "gn:admin1_code":"32.0",
    "gn:asciiname":"Yalong",
    "gn:country_code":"CN",
    "gn:dem":4015,
    "gn:feature_class":"P",
    "gn:feature_code":"PPL",
    "gn:name":"Yalong",
    "gn:population":0,
    "gn:timezone":"Asia/Shanghai",
    "iso:country":"CN",
    "name:ara_x_preferred":[
        "\u064a\u0627\u0644\u0648\u0646\u063a"
    ],
    "name:ben_x_preferred":[
        "\u0987\u09af\u09bc\u09be\u09b2\u0982"
    ],
    "name:ell_x_preferred":[
        "\u0393\u03b9\u03ac\u03bb\u03bf\u03bd\u03b3\u03ba"
    ],
    "name:heb_x_preferred":[
        "\u05d9\u05d0\u05dc\u05d5\u05e0\u05d2"
    ],
    "name:hin_x_preferred":[
        "\u092f\u093e\u0932\u094b\u0902\u0917"
    ],
    "name:hun_x_preferred":[
        "Yalong"
    ],
    "name:ind_x_preferred":[
        "Yalong"
    ],
    "name:nld_x_preferred":[
        "Yalong"
    ],
    "name:urd_x_preferred":[
        "\u06cc\u0627\u0644\u0648\u0646\u06af"
    ],
    "name:zho_x_preferred":[
        "\u4e9a\u62e2"
    ],
    "wof:name":"Yalong",
    "wof:placetype":"locality"
},
  "geometry": {"coordinates":[99.17589,32.00279],"type":"Point"}
}