{
  "type": "Feature",
  "properties": {
    "gn:admin1_code":"32.0",
    "gn:asciiname":"Yalong",
    "gn:country_code":"CN",
    "gn:dem":4015,
    "gn:feature_class":"P",
    "gn:feature_code":"PPL",
    "gn:name":"Yalong",
    "gn:population":0,
    "gn:timezone":"Asia/Shanghai",
    "iso:country":"CN",
    "name:nld_x_preferred":[
        "Yalong"
    ],
    "name:zho_x_preferred":[
        "\u4e9a\u62e2"
    ],
    "wof:name":"Yalong",
    "wof:placetype":"locality"
},
  "geometry": {"coordinates":[99.17589,32.00279],"type":"Point"}
}