{
  "type": "Feature",
  "properties": {
    "gn:admin1_code":"18",
    "gn:asciiname":"Huangjiaoqing",
    "gn:country_code":"CN",
    "gn:dem":1496,
    "gn:feature_class":"P",
    "gn:feature_code":"PPL",
    "gn:name":"Huangjiaoqing",
    "gn:population":0,
    "gn:timezone":"Asia/Shanghai",
    "iso:country":"CN",
    "name:zho_x_preferred":[
        "\u9ec4\u89d2\u7b90"
    ],
    "wof:name":"Huangjiaoqing",
    "wof:placetype":"locality"
},
  "geometry": {"coordinates":[105.158,25.2207],"type":"Point"}
}