{
  "type": "Feature",
  "properties": {
    "gn:admin1_code":"16",
    "gn:asciiname":"Baxianzhou",
    "gn:country_code":"CN",
    "gn:dem":222,
    "gn:feature_class":"P",
    "gn:feature_code":"PPL",
    "gn:name":"Baxianzhou",
    "gn:population":0,
    "gn:timezone":"Asia/Shanghai",
    "iso:country":"CN",
    "name:zho_x_preferred":[
        "\u516b\u4ed9\u6d32"
    ],
    "wof:name":"Baxianzhou",
    "wof:placetype":"locality"
},
  "geometry": {"coordinates":[109.93600000000001,25.0031],"type":"Point"}
}