{
  "type": "Feature",
  "properties": {
    "gn:admin1_code":"19.0",
    "gn:asciiname":"Dalazi",
    "gn:country_code":"CN",
    "gn:dem":87,
    "gn:feature_class":"P",
    "gn:feature_code":"PPL",
    "gn:name":"Dalazi",
    "gn:population":0,
    "gn:timezone":"Asia/Shanghai",
    "iso:country":"CN",
    "name:und_x_variant":[
        "\u5927\u782c\u5b50"
    ],
    "wof:name":"Dalazi",
    "wof:placetype":"locality"
},
  "geometry": {"coordinates":[122.51139999999999,40.32281],"type":"Point"}
}