{
  "type": "Feature",
  "properties": {
    "gn:admin1_code":"21",
    "gn:asciiname":"Jiulong",
    "gn:country_code":"CN",
    "gn:dem":1465,
    "gn:feature_class":"P",
    "gn:feature_code":"PPL",
    "gn:name":"Jiulong",
    "gn:population":0,
    "gn:timezone":"Asia/Shanghai",
    "iso:country":"CN",
    "name:und_x_variant":[
        "Chiu-lung-shan",
        "Jiulongshan",
        "Jiulong"
    ],
    "name:zho_x_preferred":[
        "\u4e5d\u9f99"
    ],
    "wof:name":"Jiulong",
    "wof:placetype":"locality"
},
  "geometry": {"coordinates":[106.991,35.4894],"type":"Point"}
}