{
  "type": "Feature",
  "properties": {
    "gn:admin1_code":"15.0",
    "gn:asciiname":"Mengjiazhai",
    "gn:country_code":"CN",
    "gn:dem":1183,
    "gn:feature_class":"P",
    "gn:feature_code":"PPL",
    "gn:name":"Mengjiazhai",
    "gn:population":0,
    "gn:timezone":"Asia/Shanghai",
    "iso:country":"CN",
    "name:und_x_variant":[
        "\u5b5f\u5bb6\u5be8"
    ],
    "wof:name":"Mengjiazhai",
    "wof:placetype":"locality"
},
  "geometry": {"coordinates":[107.47435,36.35672],"type":"Point"}
}