{
  "type": "Feature",
  "properties": {
    "gn:admin1_code":"24.0",
    "gn:asciiname":"Huodi",
    "gn:country_code":"CN",
    "gn:dem":1583,
    "gn:feature_class":"P",
    "gn:feature_code":"PPL",
    "gn:name":"Huodi",
    "gn:population":0,
    "gn:timezone":"Asia/Shanghai",
    "iso:country":"CN",
    "name:und_x_variant":[
        "\u4f19\u5730"
    ],
    "wof:name":"Huodi",
    "wof:placetype":"locality"
},
  "geometry": {"coordinates":[112.25891,39.73133],"type":"Point"}
}