{
  "type": "Feature",
  "properties": {
    "gn:admin1_code":"25",
    "gn:asciiname":"Gaohetun",
    "gn:country_code":"CN",
    "gn:dem":37,
    "gn:feature_class":"P",
    "gn:feature_code":"PPL",
    "gn:name":"Gaohetun",
    "gn:population":0,
    "gn:timezone":"Asia/Shanghai",
    "iso:country":"CN",
    "name:zho_x_preferred":[
        "\u9ad8\u6cb3\u5c6f"
    ],
    "wof:name":"Gaohetun",
    "wof:placetype":"locality"
},
  "geometry": {"coordinates":[116.392,35.1172],"type":"Point"}
}