{
  "type": "Feature",
  "properties": {
    "gn:admin1_code":"29.0",
    "gn:asciiname":"Xiahuolong",
    "gn:country_code":"CN",
    "gn:dem":2611,
    "gn:feature_class":"P",
    "gn:feature_code":"PPL",
    "gn:name":"Xiahuolong",
    "gn:population":0,
    "gn:timezone":"Asia/Shanghai",
    "iso:country":"CN",
    "name:zho_x_preferred":[
        "\u4e0b\u706b\u9f99"
    ],
    "wof:name":"Xiahuolong",
    "wof:placetype":"locality"
},
  "geometry": {"coordinates":[101.11199999999999,27.1436],"type":"Point"}
}