{
  "type": "Feature",
  "properties": {
    "gn:admin1_code":"10",
    "gn:asciiname":"Datun",
    "gn:country_code":"CN",
    "gn:dem":14,
    "gn:feature_class":"P",
    "gn:feature_code":"PPL",
    "gn:name":"Datun",
    "gn:population":0,
    "gn:timezone":"Asia/Shanghai",
    "iso:country":"CN",
    "name:rus_x_preferred":[
        "\u0414\u0430\u0442\u0443\u043d"
    ],
    "name:und_x_variant":[
        "Ta-t\u2019un",
        "Datun"
    ],
    "name:zho_x_preferred":[
        "\u5927\u5c6f"
    ],
    "wof:name":"Datun",
    "wof:placetype":"locality"
},
  "geometry": {"coordinates":[116.54707000000001,37.81598],"type":"Point"}
}