{
  "type": "Feature",
  "properties": {
    "gn:admin1_code":"15.0",
    "gn:asciiname":"Goujia Yinzi",
    "gn:country_code":"CN",
    "gn:dem":1313,
    "gn:feature_class":"P",
    "gn:feature_code":"PPL",
    "gn:name":"Goujia Yinzi",
    "gn:population":0,
    "gn:timezone":"Asia/Shanghai",
    "iso:country":"CN",
    "name:zho_x_preferred":[
        "\u82df\u5bb6\u7aa8\u5b50"
    ],
    "wof:name":"Goujia Yinzi",
    "wof:placetype":"locality"
},
  "geometry": {"coordinates":[107.56100000000001,35.0087],"type":"Point"}
}