{
  "type": "Feature",
  "properties": {
    "gn:admin1_code":"2.0",
    "gn:asciiname":"Meikeng",
    "gn:country_code":"CN",
    "gn:dem":242,
    "gn:feature_class":"P",
    "gn:feature_code":"PPL",
    "gn:name":"Meikeng",
    "gn:population":0,
    "gn:timezone":"Asia/Shanghai",
    "iso:country":"CN",
    "name:und_x_variant":[
        "\u6885\u5751",
        "Meikeng"
    ],
    "wof:name":"Meikeng",
    "wof:placetype":"locality"
},
  "geometry": {"coordinates":[119.85151,29.3635],"type":"Point"}
}