{
  "type": "Feature",
  "properties": {
    "gn:admin1_code":"15.0",
    "gn:asciiname":"Yaba Shangcun",
    "gn:country_code":"CN",
    "gn:dem":1695,
    "gn:feature_class":"P",
    "gn:feature_code":"PPL",
    "gn:name":"Yaba Shangcun",
    "gn:population":0,
    "gn:timezone":"Asia/Shanghai",
    "iso:country":"CN",
    "name:zho_x_preferred":[
        "\u5d16\u5df4\u4e0a\u6751"
    ],
    "wof:name":"Yaba Shangcun",
    "wof:placetype":"locality"
},
  "geometry": {"coordinates":[104.974,35.7792],"type":"Point"}
}