{
  "type": "Feature",
  "properties": {
    "gn:admin1_code":"19.0",
    "gn:asciiname":"Majiazi Beishan",
    "gn:country_code":"CN",
    "gn:dem":295,
    "gn:feature_class":"P",
    "gn:feature_code":"PPL",
    "gn:name":"Majiazi Beishan",
    "gn:population":0,
    "gn:timezone":"Asia/Shanghai",
    "iso:country":"CN",
    "name:zho_x_preferred":[
        "\u9a6c\u67b6\u5b50\u5317\u5c71"
    ],
    "wof:name":"Majiazi Beishan",
    "wof:placetype":"locality"
},
  "geometry": {"coordinates":[121.12061,41.95055],"type":"Point"}
}