{
  "type": "Feature",
  "properties": {
    "gn:admin1_code":"32.0",
    "gn:asciiname":"Shiban",
    "gn:country_code":"CN",
    "gn:dem":295,
    "gn:feature_class":"P",
    "gn:feature_code":"PPL",
    "gn:name":"Shiban",
    "gn:population":0,
    "gn:timezone":"Asia/Shanghai",
    "iso:country":"CN",
    "name:ara_x_preferred":[
        "\u0634\u064a\u0628\u0627\u0646"
    ],
    "name:aze_x_preferred":[
        "\u015eeyban xan"
    ],
    "name:cat_x_preferred":[
        "Xiban"
    ],
    "name:deu_x_preferred":[
        "Shibani Khan"
    ],
    "name:fra_x_preferred":[
        "Chayban"
    ],
    "name:ita_x_preferred":[
        "Shibani Khan"
    ],
    "name:jpn_x_preferred":[
        "\u30b7\u30d0\u30f3"
    ],
    "name:kor_x_preferred":[
        "\uc0e4\uc774\ubc18"
    ],
    "name:mon_x_preferred":[
        "\u0428\u0438\u0431\u0430\u043d"
    ],
    "name:nld_x_preferred":[
        "Siban"
    ],
    "name:rus_x_preferred":[
        "\u0428\u0438\u0431\u0430\u043d"
    ],
    "name:tat_x_preferred":[
        "\u0428\u04d9\u0439\u0431\u04d9\u043d"
    ],
    "name:tur_x_preferred":[
        "\u015eiban"
    ],
    "name:ukr_x_preferred":[
        "\u0428\u0438\u0431\u0430\u043d"
    ],
    "name:uzb_x_preferred":[
        "Shaybon"
    ],
    "name:zho_x_preferred":[
        "\u77f3\u677f"
    ],
    "wof:name":"Shiban",
    "wof:placetype":"locality"
},
  "geometry": {"coordinates":[105.706,30.3416],"type":"Point"}
}