{
  "type": "Feature",
  "properties": {
    "gn:admin1_code":"01",
    "gn:asciiname":"Jiangqiao",
    "gn:cc2":"CN",
    "gn:country_code":"CN",
    "gn:dem":24,
    "gn:feature_class":"P",
    "gn:feature_code":"PPL",
    "gn:name":"Jiangqiao",
    "gn:population":0,
    "gn:timezone":"Asia/Shanghai",
    "iso:country":"CN",
    "name:und_x_variant":[
        "Chiang-ch\u2019iao",
        "Hs\u00fc-ch\u2019iao",
        "Jiangqiao"
    ],
    "wof:name":"Jiangqiao",
    "wof:placetype":"locality"
},
  "geometry": {"coordinates":[117.34999999999999,32.86667],"type":"Point"}
}