{
  "type": "Feature",
  "properties": {
    "gn:admin1_code":"14",
    "gn:asciiname":"Xiuqiong",
    "gn:country_code":"CN",
    "gn:dem":3815,
    "gn:feature_class":"P",
    "gn:feature_code":"PPL",
    "gn:name":"Xiuqiong",
    "gn:population":0,
    "gn:timezone":"Asia/Urumqi",
    "iso:country":"CN",
    "name:zho_x_preferred":[
        "\u4fee\u7a77"
    ],
    "wof:name":"Xiuqiong",
    "wof:placetype":"locality"
},
  "geometry": {"coordinates":[89.212,29.3326],"type":"Point"}
}