{
  "type": "Feature",
  "properties": {
    "gn:admin1_code":"14.0",
    "gn:asciiname":"Zhaxuecun",
    "gn:country_code":"CN",
    "gn:dem":3356,
    "gn:feature_class":"P",
    "gn:feature_code":"PPL",
    "gn:name":"Zhaxuecun",
    "gn:population":0,
    "gn:timezone":"Asia/Urumqi",
    "iso:country":"CN",
    "name:zho_x_preferred":[
        "\u624e\u5b66\u6751"
    ],
    "wof:name":"Zhaxuecun",
    "wof:placetype":"locality"
},
  "geometry": {"coordinates":[92.70881,29.03269],"type":"Point"}
}