{
  "type": "Feature",
  "properties": {
    "gn:admin1_code":"29.0",
    "gn:asciiname":"Labugu",
    "gn:country_code":"CN",
    "gn:dem":2204,
    "gn:feature_class":"P",
    "gn:feature_code":"PPL",
    "gn:name":"Labugu",
    "gn:population":0,
    "gn:timezone":"Asia/Shanghai",
    "iso:country":"CN",
    "name:zho_x_preferred":[
        "\u62c9\u4e0d\u53e4"
    ],
    "wof:name":"Labugu",
    "wof:placetype":"locality"
},
  "geometry": {"coordinates":[99.6802,27.3351],"type":"Point"}
}