{
  "type": "Feature",
  "properties": {
    "gn:admin1_code":"1.0",
    "gn:asciiname":"Wangmiaocun",
    "gn:country_code":"CN",
    "gn:dem":39,
    "gn:feature_class":"P",
    "gn:feature_code":"PPL",
    "gn:name":"Wangmiaocun",
    "gn:population":0,
    "gn:timezone":"Asia/Shanghai",
    "iso:country":"CN",
    "name:und_x_variant":[
        "Wangmiao"
    ],
    "name:zho_x_preferred":[
        "\u738b\u5e99\u6751"
    ],
    "wof:name":"Wangmiaocun",
    "wof:placetype":"locality"
},
  "geometry": {"coordinates":[115.69568,33.68048],"type":"Point"}
}