{
  "type": "Feature",
  "properties": {
    "gn:admin1_code":"11.0",
    "gn:asciiname":"Naowuchang",
    "gn:country_code":"CN",
    "gn:dem":126,
    "gn:feature_class":"P",
    "gn:feature_code":"PPL",
    "gn:name":"Naowuchang",
    "gn:population":0,
    "gn:timezone":"Asia/Shanghai",
    "iso:country":"CN",
    "name:zho_x_preferred":[
        "\u95f9\u5c4b\u573a"
    ],
    "wof:name":"Naowuchang",
    "wof:placetype":"locality"
},
  "geometry": {"coordinates":[112.29194,27.18531],"type":"Point"}
}