{
  "type": "Feature",
  "properties": {
    "gn:admin1_code":"19.0",
    "gn:asciiname":"Xinihezi",
    "gn:country_code":"CN",
    "gn:dem":23,
    "gn:feature_class":"P",
    "gn:feature_code":"PPL",
    "gn:name":"Xinihezi",
    "gn:population":0,
    "gn:timezone":"Asia/Shanghai",
    "iso:country":"CN",
    "name:und_x_variant":[
        "\u897f\u6ce5\u6cb3\u5b50"
    ],
    "name:zho_x_preferred":[
        "\u897f\u6ce5\u6cb3\u5b50"
    ],
    "wof:name":"Xinihezi",
    "wof:placetype":"locality"
},
  "geometry": {"coordinates":[121.20729,38.89335],"type":"Point"}
}