{
  "type": "Feature",
  "properties": {
    "gn:admin1_code":"25",
    "gn:asciiname":"Liujiadongshan",
    "gn:country_code":"CN",
    "gn:dem":86,
    "gn:feature_class":"P",
    "gn:feature_code":"PPL",
    "gn:name":"Liujiadongshan",
    "gn:population":0,
    "gn:timezone":"Asia/Shanghai",
    "iso:country":"CN",
    "name:zho_x_preferred":[
        "\u5218\u5bb6\u4e1c\u5c71"
    ],
    "wof:name":"Liujiadongshan",
    "wof:placetype":"locality"
},
  "geometry": {"coordinates":[119.148,35.2817],"type":"Point"}
}