{
  "type": "Feature",
  "properties": {
    "gn:admin1_code":"26.0",
    "gn:asciiname":"Xinglongwan",
    "gn:country_code":"CN",
    "gn:dem":1547,
    "gn:feature_class":"P",
    "gn:feature_code":"PPL",
    "gn:name":"Xinglongwan",
    "gn:population":0,
    "gn:timezone":"Asia/Shanghai",
    "iso:country":"CN",
    "name:zho_x_preferred":[
        "\u5174\u9f99\u6e7e"
    ],
    "wof:name":"Xinglongwan",
    "wof:placetype":"locality"
},
  "geometry": {"coordinates":[106.72562000000001,34.23693],"type":"Point"}
}