{
  "type": "Feature",
  "properties": {
    "gn:admin1_code":"24.0",
    "gn:asciiname":"Hexitou",
    "gn:country_code":"CN",
    "gn:dem":845,
    "gn:feature_class":"P",
    "gn:feature_code":"PPL",
    "gn:name":"Hexitou",
    "gn:population":0,
    "gn:timezone":"Asia/Shanghai",
    "iso:country":"CN",
    "name:zho_x_preferred":[
        "\u6cb3\u4e60\u5934"
    ],
    "wof:name":"Hexitou",
    "wof:placetype":"locality"
},
  "geometry": {"coordinates":[112.66768999999999,38.3935],"type":"Point"}
}