{
  "type": "Feature",
  "properties": {
    "gn:admin1_code":"07",
    "gn:asciiname":"Qianting",
    "gn:cc2":"CN",
    "gn:country_code":"CN",
    "gn:dem":16,
    "gn:feature_class":"P",
    "gn:feature_code":"PPL",
    "gn:name":"Qianting",
    "gn:population":0,
    "gn:timezone":"Asia/Shanghai",
    "iso:country":"CN",
    "name:und_x_variant":[
        "Ch\u2019ien-t\u2019ing",
        "Qianting"
    ],
    "wof:name":"Qianting",
    "wof:placetype":"locality"
},
  "geometry": {"coordinates":[117.97028,24.23333],"type":"Point"}
}