{
  "type": "Feature",
  "properties": {
    "gn:admin1_code":"26.0",
    "gn:asciiname":"Xinzhuangtai",
    "gn:country_code":"CN",
    "gn:dem":1548,
    "gn:feature_class":"P",
    "gn:feature_code":"PPL",
    "gn:name":"Xinzhuangtai",
    "gn:population":0,
    "gn:timezone":"Asia/Shanghai",
    "iso:country":"CN",
    "name:zho_x_preferred":[
        "\u65b0\u5e84\u53f0"
    ],
    "wof:name":"Xinzhuangtai",
    "wof:placetype":"locality"
},
  "geometry": {"coordinates":[107.64373000000001,37.15672],"type":"Point"}
}