{
  "type": "Feature",
  "properties": {
    "gn:admin1_code":"7",
    "gn:asciiname":"Qijiao",
    "gn:country_code":"CN",
    "gn:dem":185,
    "gn:feature_class":"P",
    "gn:feature_code":"PPL",
    "gn:name":"Qijiao",
    "gn:population":0,
    "gn:timezone":"Asia/Shanghai",
    "iso:country":"CN",
    "name:zho_x_preferred":[
        "\u5d0e\u811a"
    ],
    "wof:name":"Qijiao",
    "wof:placetype":"locality"
},
  "geometry": {"coordinates":[117.52869,24.76284],"type":"Point"}
}