{
  "type": "Feature",
  "properties": {
    "gn:admin1_code":"12.0",
    "gn:asciiname":"Wachangwan",
    "gn:country_code":"CN",
    "gn:dem":1413,
    "gn:feature_class":"P",
    "gn:feature_code":"PPL",
    "gn:name":"Wachangwan",
    "gn:population":0,
    "gn:timezone":"Asia/Shanghai",
    "iso:country":"CN",
    "name:zho_x_preferred":[
        "\u74e6\u5382\u6e7e"
    ],
    "wof:name":"Wachangwan",
    "wof:placetype":"locality"
},
  "geometry": {"coordinates":[109.98455,30.74557],"type":"Point"}
}