{
  "type": "Feature",
  "properties": {
    "gn:admin1_code":"16.0",
    "gn:asciiname":"Da'en",
    "gn:country_code":"CN",
    "gn:dem":890,
    "gn:feature_class":"P",
    "gn:feature_code":"PPL",
    "gn:name":"Da\u2019en",
    "gn:population":0,
    "gn:timezone":"Asia/Shanghai",
    "iso:country":"CN",
    "name:und_x_variant":[
        "Da\u2019en"
    ],
    "name:zho_x_preferred":[
        "\u5927\u6069"
    ],
    "wof:name":"Da'en",
    "wof:placetype":"locality"
},
  "geometry": {"coordinates":[106.23099999999999,23.2852],"type":"Point"}
}