{
  "type": "Feature",
  "properties": {
    "gn:admin1_code":"11",
    "gn:asciiname":"Sanjiheba",
    "gn:cc2":"CN",
    "gn:country_code":"CN",
    "gn:dem":32,
    "gn:feature_class":"P",
    "gn:feature_code":"PPL",
    "gn:name":"Sanjiheba",
    "gn:population":0,
    "gn:timezone":"Asia/Shanghai",
    "iso:country":"CN",
    "name:und_x_variant":[
        "San-chi-ho-pa",
        "Sanjiheba"
    ],
    "wof:name":"Sanjiheba",
    "wof:placetype":"locality"
},
  "geometry": {"coordinates":[112.63333,29.18333],"type":"Point"}
}