{
  "type": "Feature",
  "properties": {
    "gn:admin1_code":"4.0",
    "gn:asciiname":"Tanggangcun",
    "gn:country_code":"CN",
    "gn:dem":8,
    "gn:feature_class":"P",
    "gn:feature_code":"PPL",
    "gn:name":"Tanggangcun",
    "gn:population":0,
    "gn:timezone":"Asia/Shanghai",
    "iso:country":"CN",
    "name:zho_x_preferred":[
        "\u5510\u6e2f\u6751"
    ],
    "wof:name":"Tanggangcun",
    "wof:placetype":"locality"
},
  "geometry": {"coordinates":[119.24791999999999,33.0885],"type":"Point"}
}