{
  "type": "Feature",
  "properties": {
    "gn:admin1_code":"29.0",
    "gn:asciiname":"Lelongzhai",
    "gn:country_code":"CN",
    "gn:dem":1281,
    "gn:feature_class":"P",
    "gn:feature_code":"PPL",
    "gn:name":"Lelongzhai",
    "gn:population":0,
    "gn:timezone":"Asia/Shanghai",
    "iso:country":"CN",
    "name:zho_x_preferred":[
        "\u4e50\u9f99\u5be8"
    ],
    "wof:name":"Lelongzhai",
    "wof:placetype":"locality"
},
  "geometry": {"coordinates":[100.367,24.7427],"type":"Point"}
}