{
  "type": "Feature",
  "properties": {
    "gn:admin1_code":"16.0",
    "gn:asciiname":"Xiaoguijing",
    "gn:country_code":"CN",
    "gn:dem":999,
    "gn:feature_class":"P",
    "gn:feature_code":"PPL",
    "gn:name":"Xiaoguijing",
    "gn:population":0,
    "gn:timezone":"Asia/Shanghai",
    "iso:country":"CN",
    "name:zho_x_preferred":[
        "\u5c0f\u89c4\u656c"
    ],
    "wof:name":"Xiaoguijing",
    "wof:placetype":"locality"
},
  "geometry": {"coordinates":[105.789,23.2423],"type":"Point"}
}