{
  "type": "Feature",
  "properties": {
    "gn:admin1_code":"24.0",
    "gn:asciiname":"Ximing",
    "gn:cc2":"CN",
    "gn:country_code":"CN",
    "gn:dem":965,
    "gn:feature_class":"P",
    "gn:feature_code":"PPL",
    "gn:name":"Ximing",
    "gn:population":0,
    "gn:timezone":"Asia/Shanghai",
    "iso:country":"CN",
    "name:und_x_variant":[
        "Hsi-ming",
        "Hsi-ming-ts\u2019un",
        "Ximing"
    ],
    "wof:name":"Ximing",
    "wof:placetype":"locality"
},
  "geometry": {"coordinates":[112.41639000000001,37.86611],"type":"Point"}
}