{
  "type": "Feature",
  "properties": {
    "gn:admin1_code":"30",
    "gn:asciiname":"Toupucun",
    "gn:country_code":"CN",
    "gn:dem":90,
    "gn:feature_class":"P",
    "gn:feature_code":"PPL",
    "gn:name":"Toupucun",
    "gn:population":0,
    "gn:timezone":"Asia/Urumqi",
    "iso:country":"CN",
    "name:zho_x_preferred":[
        "\u5934\u94fa\u6751"
    ],
    "wof:name":"Toupucun",
    "wof:placetype":"locality"
},
  "geometry": {"coordinates":[110.14388,20.35696],"type":"Point"}
}