{
  "type": "Feature",
  "properties": {
    "gn:admin1_code":"16.0",
    "gn:asciiname":"Gongtian",
    "gn:country_code":"CN",
    "gn:dem":165,
    "gn:feature_class":"P",
    "gn:feature_code":"PPL",
    "gn:name":"Gongtian",
    "gn:population":0,
    "gn:timezone":"Asia/Shanghai",
    "iso:country":"CN",
    "name:zho_x_preferred":[
        "\u516c\u7530"
    ],
    "wof:name":"Gongtian",
    "wof:placetype":"locality"
},
  "geometry": {"coordinates":[108.92100000000001,23.04300000000001],"type":"Point"}
}