{
  "type": "Feature",
  "properties": {
    "gn:admin1_code":"15.0",
    "gn:asciiname":"Yupanxiang",
    "gn:country_code":"CN",
    "gn:dem":1943,
    "gn:feature_class":"P",
    "gn:feature_code":"PPL",
    "gn:name":"Yupanxiang",
    "gn:population":0,
    "gn:timezone":"Asia/Shanghai",
    "iso:country":"CN",
    "name:und_x_variant":[
        "\u6986\u76d8\u4e61"
    ],
    "wof:name":"Yupanxiang",
    "wof:placetype":"locality"
},
  "geometry": {"coordinates":[104.91558000000001,34.91651],"type":"Point"}
}