{
  "type": "Feature",
  "properties": {
    "gn:admin1_code":"5.0",
    "gn:asciiname":"Xinfatun",
    "gn:country_code":"CN",
    "gn:dem":234,
    "gn:feature_class":"P",
    "gn:feature_code":"PPL",
    "gn:name":"Xinfatun",
    "gn:population":0,
    "gn:timezone":"Asia/Shanghai",
    "iso:country":"CN",
    "name:zho_x_preferred":[
        "\u65b0\u53d1\u5c6f"
    ],
    "wof:name":"Xinfatun",
    "wof:placetype":"locality"
},
  "geometry": {"coordinates":[126.95841,44.46929],"type":"Point"}
}