{
  "type": "Feature",
  "properties": {
    "gn:admin1_code":"4.0",
    "gn:asciiname":"Lujiaqiao",
    "gn:country_code":"CN",
    "gn:dem":4,
    "gn:feature_class":"P",
    "gn:feature_code":"PPL",
    "gn:name":"Lujiaqiao",
    "gn:population":0,
    "gn:timezone":"Asia/Shanghai",
    "iso:country":"CN",
    "name:und_x_variant":[
        "\u9646\u5bb6\u6865"
    ],
    "name:zho_x_preferred":[
        "\u9646\u5bb6\u6865"
    ],
    "wof:name":"Lujiaqiao",
    "wof:placetype":"locality"
},
  "geometry": {"coordinates":[120.90521,31.62039],"type":"Point"}
}