{
  "type": "Feature",
  "properties": {
    "gn:admin1_code":"32.0",
    "gn:asciiname":"Yang'erping",
    "gn:country_code":"CN",
    "gn:dem":533,
    "gn:feature_class":"P",
    "gn:feature_code":"PPL",
    "gn:name":"Yang\u2019erping",
    "gn:population":0,
    "gn:timezone":"Asia/Shanghai",
    "iso:country":"CN",
    "name:zho_x_preferred":[
        "\u6768\u4e8c\u576a"
    ],
    "name:zho_x_variant":[
        "Yang\u2019erping"
    ],
    "wof:name":"Yang'erping",
    "wof:placetype":"locality"
},
  "geometry": {"coordinates":[106.45215,32.22657],"type":"Point"}
}