{
  "type": "Feature",
  "properties": {
    "gn:admin1_code":"16.0",
    "gn:asciiname":"Wudi",
    "gn:country_code":"CN",
    "gn:dem":179,
    "gn:feature_class":"P",
    "gn:feature_code":"PPL",
    "gn:name":"Wudi",
    "gn:population":0,
    "gn:timezone":"Asia/Shanghai",
    "iso:country":"CN",
    "name:ceb_x_preferred":[
        "Wudi"
    ],
    "name:ces_x_preferred":[
        "Wu-ti"
    ],
    "name:deu_x_preferred":[
        "Wudi"
    ],
    "name:fra_x_preferred":[
        "Wudi"
    ],
    "name:pol_x_preferred":[
        "Wudi"
    ],
    "name:rus_x_preferred":[
        "\u0423-\u0434\u0438"
    ],
    "name:swe_x_preferred":[
        "Wudi"
    ],
    "name:zho_x_preferred":[
        "\u52a1\u5e95"
    ],
    "wof:name":"Wudi",
    "wof:placetype":"locality"
},
  "geometry": {"coordinates":[110.361,22.98],"type":"Point"}
}