{
  "type": "Feature",
  "properties": {
    "gn:admin1_code":"18",
    "gn:asciiname":"Geyan",
    "gn:country_code":"CN",
    "gn:dem":2001,
    "gn:feature_class":"P",
    "gn:feature_code":"PPL",
    "gn:name":"Geyan",
    "gn:population":0,
    "gn:timezone":"Asia/Shanghai",
    "iso:country":"CN",
    "name:zho_x_preferred":[
        "\u9e3d\u71d5"
    ],
    "wof:name":"Geyan",
    "wof:placetype":"locality"
},
  "geometry": {"coordinates":[104.65000000000001,27.2256],"type":"Point"}
}