{
  "type": "Feature",
  "properties": {
    "gn:admin1_code":"10",
    "gn:asciiname":"Jiu'anci",
    "gn:country_code":"CN",
    "gn:dem":13,
    "gn:feature_class":"P",
    "gn:feature_code":"PPL",
    "gn:name":"Jiu\u2019anci",
    "gn:population":0,
    "gn:timezone":"Asia/Shanghai",
    "iso:country":"CN",
    "name:und_x_variant":[
        "An-tz\u2019u-hsien",
        "Tung-an",
        "Chiu-an-tz\u2019u",
        "An-ts\u2019u",
        "Antze",
        "An\u2019tso",
        "An-tz\u2019u",
        "Jiu\u2019anci"
    ],
    "wof:name":"Jiu'anci",
    "wof:placetype":"locality"
},
  "geometry": {"coordinates":[116.73333,39.38333],"type":"Point"}
}