{
  "type": "Feature",
  "properties": {
    "gn:admin1_code":"07",
    "gn:asciiname":"Yanghou",
    "gn:country_code":"CN",
    "gn:dem":440,
    "gn:feature_class":"P",
    "gn:feature_code":"PPL",
    "gn:name":"Yanghou",
    "gn:population":0,
    "gn:timezone":"Asia/Shanghai",
    "iso:country":"CN",
    "name:zho_x_preferred":[
        "\u6d0b\u540e"
    ],
    "wof:name":"Yanghou",
    "wof:placetype":"locality"
},
  "geometry": {"coordinates":[118.58978999999999,26.94371],"type":"Point"}
}