{
  "type": "Feature",
  "properties": {
    "gn:admin1_code":"3.0",
    "gn:asciiname":"Qianniuling",
    "gn:country_code":"CN",
    "gn:dem":281,
    "gn:feature_class":"P",
    "gn:feature_code":"PPL",
    "gn:name":"Qianniuling",
    "gn:population":0,
    "gn:timezone":"Asia/Shanghai",
    "iso:country":"CN",
    "name:und_x_variant":[
        "\u7275\u725b\u5cad"
    ],
    "wof:name":"Qianniuling",
    "wof:placetype":"locality"
},
  "geometry": {"coordinates":[115.40103999999999,29.09454],"type":"Point"}
}