{
  "type": "Feature",
  "properties": {
    "gn:admin1_code":"29.0",
    "gn:asciiname":"Xinzhai",
    "gn:country_code":"CN",
    "gn:dem":1719,
    "gn:feature_class":"P",
    "gn:feature_code":"PPL",
    "gn:name":"Xinzhai",
    "gn:population":0,
    "gn:timezone":"Asia/Shanghai",
    "iso:country":"CN",
    "name:zho_x_preferred":[
        "\u65b0\u5be8"
    ],
    "wof:name":"Xinzhai",
    "wof:placetype":"locality"
},
  "geometry": {"coordinates":[99.53489999999999,24.4458],"type":"Point"}
}