{
  "type": "Feature",
  "properties": {
    "gn:admin1_code":"10.0",
    "gn:asciiname":"Yangliuzhuang",
    "gn:cc2":"CN",
    "gn:country_code":"CN",
    "gn:dem":86,
    "gn:feature_class":"P",
    "gn:feature_code":"PPL",
    "gn:name":"Yangliuzhuang",
    "gn:population":0,
    "gn:timezone":"Asia/Shanghai",
    "iso:country":"CN",
    "name:und_x_variant":[
        "Yang-liu-chuang",
        "Yangliuzhuang"
    ],
    "wof:name":"Yangliuzhuang",
    "wof:placetype":"locality"
},
  "geometry": {"coordinates":[118.36667,39.91667],"type":"Point"}
}