{
  "type": "Feature",
  "properties": {
    "gn:admin1_code":"12.0",
    "gn:asciiname":"Laomiaoshan",
    "gn:country_code":"CN",
    "gn:dem":1285,
    "gn:feature_class":"P",
    "gn:feature_code":"PPL",
    "gn:name":"Laomiaoshan",
    "gn:population":0,
    "gn:timezone":"Asia/Shanghai",
    "iso:country":"CN",
    "name:zho_x_preferred":[
        "\u8001\u5e99\u5c71"
    ],
    "wof:name":"Laomiaoshan",
    "wof:placetype":"locality"
},
  "geometry": {"coordinates":[109.9962,30.50385],"type":"Point"}
}