{
  "type": "Feature",
  "properties": {
    "gn:admin1_code":"26",
    "gn:asciiname":"Yijiayuan",
    "gn:country_code":"CN",
    "gn:dem":1207,
    "gn:feature_class":"P",
    "gn:feature_code":"PPL",
    "gn:name":"Yijiayuan",
    "gn:population":0,
    "gn:timezone":"Asia/Shanghai",
    "iso:country":"CN",
    "name:zho_x_preferred":[
        "\u5b9c\u5bb6\u586c"
    ],
    "wof:name":"Yijiayuan",
    "wof:placetype":"locality"
},
  "geometry": {"coordinates":[108.10693999999999,34.91222],"type":"Point"}
}