{
  "type": "Feature",
  "properties": {
    "gn:admin1_code":"14",
    "gn:asciiname":"Zhiu",
    "gn:country_code":"CN",
    "gn:dem":4409,
    "gn:feature_class":"P",
    "gn:feature_code":"PPL",
    "gn:name":"Zhiu",
    "gn:population":0,
    "gn:timezone":"Asia/Urumqi",
    "iso:country":"CN",
    "name:bod_x_preferred":[
        "\u0f60\u0f56\u0fb2\u0f72\u0f60\u0f74"
    ],
    "wof:name":"Zhiu",
    "wof:placetype":"locality"
},
  "geometry": {"coordinates":[92.32163,28.54389],"type":"Point"}
}