{
  "type": "Feature",
  "properties": {
    "gn:admin1_code":"16.0",
    "gn:asciiname":"Panlong",
    "gn:country_code":"CN",
    "gn:dem":68,
    "gn:feature_class":"P",
    "gn:feature_code":"PPL",
    "gn:name":"Panlong",
    "gn:population":0,
    "gn:timezone":"Asia/Shanghai",
    "iso:country":"CN",
    "name:zho_x_preferred":[
        "\u76d8\u9f99"
    ],
    "wof:name":"Panlong",
    "wof:placetype":"locality"
},
  "geometry": {"coordinates":[109.70399999999999,23.5875],"type":"Point"}
}