{
  "type": "Feature",
  "properties": {
    "gn:admin1_code":"26.0",
    "gn:asciiname":"Xiagaojiayuan",
    "gn:country_code":"CN",
    "gn:dem":1062,
    "gn:feature_class":"P",
    "gn:feature_code":"PPL",
    "gn:name":"Xiagaojiayuan",
    "gn:population":0,
    "gn:timezone":"Asia/Shanghai",
    "iso:country":"CN",
    "name:zho_x_preferred":[
        "\u4e0b\u9ad8\u5bb6\u586c"
    ],
    "wof:name":"Xiagaojiayuan",
    "wof:placetype":"locality"
},
  "geometry": {"coordinates":[109.67301999999999,35.45469],"type":"Point"}
}