{
  "type": "Feature",
  "properties": {
    "gn:admin1_code":"16.0",
    "gn:asciiname":"Jiuchao",
    "gn:country_code":"CN",
    "gn:dem":701,
    "gn:feature_class":"P",
    "gn:feature_code":"PPL",
    "gn:name":"Jiuchao",
    "gn:population":0,
    "gn:timezone":"Asia/Shanghai",
    "iso:country":"CN",
    "name:zho_x_preferred":[
        "\u4e45\u671d"
    ],
    "wof:name":"Jiuchao",
    "wof:placetype":"locality"
},
  "geometry": {"coordinates":[108.57299999999999,25.2935],"type":"Point"}
}