{
  "type": "Feature",
  "properties": {
    "gn:admin1_code":"29.0",
    "gn:asciiname":"Luxingcun",
    "gn:country_code":"CN",
    "gn:dem":1903,
    "gn:feature_class":"P",
    "gn:feature_code":"PPL",
    "gn:name":"Luxingcun",
    "gn:population":0,
    "gn:timezone":"Asia/Shanghai",
    "iso:country":"CN",
    "name:zho_x_preferred":[
        "\u8def\u661f\u6751"
    ],
    "wof:name":"Luxingcun",
    "wof:placetype":"locality"
},
  "geometry": {"coordinates":[103.38800000000001,24.9695],"type":"Point"}
}