{
  "type": "Feature",
  "properties": {
    "gn:admin1_code":"19.0",
    "gn:asciiname":"Guanjiahuangdi",
    "gn:country_code":"CN",
    "gn:dem":43,
    "gn:feature_class":"P",
    "gn:feature_code":"PPL",
    "gn:name":"Guanjiahuangdi",
    "gn:population":0,
    "gn:timezone":"Asia/Shanghai",
    "iso:country":"CN",
    "name:zho_x_preferred":[
        "\u5173\u5bb6\u8352\u5730"
    ],
    "wof:name":"Guanjiahuangdi",
    "wof:placetype":"locality"
},
  "geometry": {"coordinates":[123.11502,42.19703],"type":"Point"}
}