{
  "type": "Feature",
  "properties": {
    "gn:admin1_code":"11",
    "gn:asciiname":"Daping",
    "gn:country_code":"CN",
    "gn:dem":259,
    "gn:feature_class":"P",
    "gn:feature_code":"PPL",
    "gn:name":"Daping",
    "gn:population":0,
    "gn:timezone":"Asia/Shanghai",
    "iso:country":"CN",
    "wof:name":"Daping",
    "wof:placetype":"locality"
},
  "geometry": {"coordinates":[113.93639,28.94556],"type":"Point"}
}