{
  "type": "Feature",
  "properties": {
    "gn:admin1_code":"29.0",
    "gn:asciiname":"Duanjiawan",
    "gn:country_code":"CN",
    "gn:dem":1686,
    "gn:feature_class":"P",
    "gn:feature_code":"PPL",
    "gn:name":"Duanjiawan",
    "gn:population":0,
    "gn:timezone":"Asia/Shanghai",
    "iso:country":"CN",
    "name:zho_x_preferred":[
        "\u6bb5\u5bb6\u6e7e"
    ],
    "wof:name":"Duanjiawan",
    "wof:placetype":"locality"
},
  "geometry": {"coordinates":[103.57299999999999,25.9776],"type":"Point"}
}