{
  "type": "Feature",
  "properties": {
    "gn:admin1_code":"26.0",
    "gn:asciiname":"Huangjiahe",
    "gn:country_code":"CN",
    "gn:dem":1131,
    "gn:feature_class":"P",
    "gn:feature_code":"PPL",
    "gn:name":"Huangjiahe",
    "gn:population":0,
    "gn:timezone":"Asia/Shanghai",
    "iso:country":"CN",
    "name:zho_x_preferred":[
        "\u9ec4\u5bb6\u6cb3"
    ],
    "wof:name":"Huangjiahe",
    "wof:placetype":"locality"
},
  "geometry": {"coordinates":[107.9864,32.28922],"type":"Point"}
}