{
  "type": "Feature",
  "properties": {
    "gn:admin1_code":"4.0",
    "gn:asciiname":"Yongfeng Sanxu",
    "gn:country_code":"CN",
    "gn:dem":5,
    "gn:feature_class":"P",
    "gn:feature_code":"PPLF",
    "gn:name":"Yongfeng Sanxu",
    "gn:population":0,
    "gn:timezone":"Asia/Shanghai",
    "iso:country":"CN",
    "name:zho_x_preferred":[
        "\u6c38\u4e30\u4e09\u5729"
    ],
    "wof:name":"Yongfeng Sanxu",
    "wof:placetype":"locality"
},
  "geometry": {"coordinates":[120.54998999999999,31.98923],"type":"Point"}
}