{
  "type": "Feature",
  "properties": {
    "gn:admin1_code":"4.0",
    "gn:asciiname":"Qiangankou",
    "gn:country_code":"CN",
    "gn:dem":16,
    "gn:feature_class":"P",
    "gn:feature_code":"PPL",
    "gn:name":"Qiangankou",
    "gn:population":0,
    "gn:timezone":"Asia/Shanghai",
    "iso:country":"CN",
    "name:zho_x_preferred":[
        "\u524d\u5e72\u53e3"
    ],
    "wof:name":"Qiangankou",
    "wof:placetype":"locality"
},
  "geometry": {"coordinates":[118.48699999999999,34.1499],"type":"Point"}
}