{
  "type": "Feature",
  "properties": {
    "gn:admin1_code":"32.0",
    "gn:asciiname":"Jueluo",
    "gn:country_code":"CN",
    "gn:dem":3388,
    "gn:feature_class":"P",
    "gn:feature_code":"PPL",
    "gn:name":"Jueluo",
    "gn:population":0,
    "gn:timezone":"Asia/Shanghai",
    "iso:country":"CN",
    "name:zho_x_preferred":[
        "\u51b3\u6d1b"
    ],
    "wof:name":"Jueluo",
    "wof:placetype":"locality"
},
  "geometry": {"coordinates":[101.41500000000001,29.6807],"type":"Point"}
}