{
  "type": "Feature",
  "properties": {
    "gn:admin1_code":"32.0",
    "gn:asciiname":"Mawuzi",
    "gn:country_code":"CN",
    "gn:dem":1058,
    "gn:feature_class":"P",
    "gn:feature_code":"PPL",
    "gn:name":"Mawuzi",
    "gn:population":0,
    "gn:timezone":"Asia/Shanghai",
    "iso:country":"CN",
    "name:zho_x_preferred":[
        "\u9a6c\u5c4b\u5b50"
    ],
    "wof:name":"Mawuzi",
    "wof:placetype":"locality"
},
  "geometry": {"coordinates":[103.48493000000001,29.35202],"type":"Point"}
}