{
  "type": "Feature",
  "properties": {
    "gn:admin1_code":"7",
    "gn:asciiname":"Haokeng",
    "gn:country_code":"CN",
    "gn:dem":637,
    "gn:feature_class":"P",
    "gn:feature_code":"PPL",
    "gn:name":"Haokeng",
    "gn:population":0,
    "gn:timezone":"Asia/Shanghai",
    "iso:country":"CN",
    "name:und_x_variant":[
        "\u597d\u5751"
    ],
    "wof:name":"Haokeng",
    "wof:placetype":"locality"
},
  "geometry": {"coordinates":[119.67665,27.38053],"type":"Point"}
}