{
  "type": "Feature",
  "properties": {
    "gn:admin1_code":"14.0",
    "gn:asciiname":"Tangraocun",
    "gn:country_code":"CN",
    "gn:dem":3265,
    "gn:feature_class":"P",
    "gn:feature_code":"PPL",
    "gn:name":"Tangraocun",
    "gn:population":0,
    "gn:timezone":"Asia/Urumqi",
    "iso:country":"CN",
    "name:zho_x_preferred":[
        "\u5510\u7ed5\u6751"
    ],
    "wof:name":"Tangraocun",
    "wof:placetype":"locality"
},
  "geometry": {"coordinates":[94.38558999999999,29.65966],"type":"Point"}
}