{
  "type": "Feature",
  "properties": {
    "gn:admin1_code":"3.0",
    "gn:asciiname":"Pingchuan",
    "gn:country_code":"CN",
    "gn:dem":269,
    "gn:feature_class":"P",
    "gn:feature_code":"PPL",
    "gn:name":"Pingchuan",
    "gn:population":0,
    "gn:timezone":"Asia/Shanghai",
    "iso:country":"CN",
    "name:und_x_variant":[
        "\u576a\u5ddd"
    ],
    "wof:name":"Pingchuan",
    "wof:placetype":"locality"
},
  "geometry": {"coordinates":[115.98799,26.92933],"type":"Point"}
}