{
  "type": "Feature",
  "properties": {
    "gn:admin1_code":"15.0",
    "gn:asciiname":"Beidujiawan",
    "gn:country_code":"CN",
    "gn:dem":1671,
    "gn:feature_class":"P",
    "gn:feature_code":"PPL",
    "gn:name":"Beidujiawan",
    "gn:population":0,
    "gn:timezone":"Asia/Shanghai",
    "iso:country":"CN",
    "name:zho_x_preferred":[
        "\u5317\u675c\u5bb6\u6e7e"
    ],
    "wof:name":"Beidujiawan",
    "wof:placetype":"locality"
},
  "geometry": {"coordinates":[105.544,34.9066],"type":"Point"}
}