{
  "type": "Feature",
  "properties": {
    "gn:admin1_code":"26.0",
    "gn:asciiname":"Zhanlonggang",
    "gn:country_code":"CN",
    "gn:dem":1025,
    "gn:feature_class":"P",
    "gn:feature_code":"PPL",
    "gn:name":"Zhanlonggang",
    "gn:population":0,
    "gn:timezone":"Asia/Shanghai",
    "iso:country":"CN",
    "name:und_x_variant":[
        "Zhanlongya"
    ],
    "name:zho_x_preferred":[
        "\u65a9\u9f99\u5c97"
    ],
    "wof:name":"Zhanlonggang",
    "wof:placetype":"locality"
},
  "geometry": {"coordinates":[108.36328,33.14001],"type":"Point"}
}