{
  "type": "Feature",
  "properties": {
    "gn:admin1_code":"4.0",
    "gn:asciiname":"Yangying",
    "gn:country_code":"CN",
    "gn:dem":2,
    "gn:feature_class":"P",
    "gn:feature_code":"PPL",
    "gn:name":"Yangying",
    "gn:population":0,
    "gn:timezone":"Asia/Shanghai",
    "iso:country":"CN",
    "name:und_x_variant":[
        "\u6768\u8425"
    ],
    "name:zho_x_preferred":[
        "\u6768\u8425"
    ],
    "wof:name":"Yangying",
    "wof:placetype":"locality"
},
  "geometry": {"coordinates":[120.05706000000001,33.1208],"type":"Point"}
}