{
  "type": "Feature",
  "properties": {
    "gn:admin1_code":"8.0",
    "gn:asciiname":"Xiaohoujia Wopeng",
    "gn:country_code":"CN",
    "gn:dem":152,
    "gn:feature_class":"P",
    "gn:feature_code":"PPL",
    "gn:name":"Xiaohoujia Wopeng",
    "gn:population":0,
    "gn:timezone":"Asia/Shanghai",
    "iso:country":"CN",
    "name:zho_x_preferred":[
        "\u5c0f\u4faf\u5bb6\u7a9d\u68da"
    ],
    "wof:name":"Xiaohoujia Wopeng",
    "wof:placetype":"locality"
},
  "geometry": {"coordinates":[125.42569,46.43999],"type":"Point"}
}