{
  "type": "Feature",
  "properties": {
    "gn:admin1_code":"16",
    "gn:asciiname":"Fucheng",
    "gn:cc2":"CN",
    "gn:country_code":"CN",
    "gn:dem":25,
    "gn:feature_class":"P",
    "gn:feature_code":"PPL",
    "gn:name":"Fucheng",
    "gn:population":0,
    "gn:timezone":"Asia/Shanghai",
    "iso:country":"CN",
    "name:und_x_variant":[
        "Fu-ch\u2019eng-hs\u00fc",
        "Fucheng"
    ],
    "wof:name":"Fucheng",
    "wof:placetype":"locality"
},
  "geometry": {"coordinates":[109.33028,21.56972],"type":"Point"}
}