{
  "type": "Feature",
  "properties": {
    "gn:admin1_code":"9",
    "gn:asciiname":"Houcuilou",
    "gn:country_code":"CN",
    "gn:dem":54,
    "gn:feature_class":"P",
    "gn:feature_code":"PPL",
    "gn:name":"Houcuilou",
    "gn:population":0,
    "gn:timezone":"Asia/Shanghai",
    "iso:country":"CN",
    "name:zho_x_preferred":[
        "\u540e\u5d14\u697c"
    ],
    "wof:name":"Houcuilou",
    "wof:placetype":"locality"
},
  "geometry": {"coordinates":[115.452,34.3061],"type":"Point"}
}