{
  "type": "Feature",
  "properties": {
    "gn:admin1_code":"12.0",
    "gn:asciiname":"Tongqiangou",
    "gn:country_code":"CN",
    "gn:dem":298,
    "gn:feature_class":"P",
    "gn:feature_code":"PPL",
    "gn:name":"Tongqiangou",
    "gn:population":0,
    "gn:timezone":"Asia/Shanghai",
    "iso:country":"CN",
    "name:zho_x_preferred":[
        "Tongqiangou"
    ],
    "name:zho_x_variant":[
        "\u94dc\u94b1\u6c9f"
    ],
    "wof:name":"Tongqiangou",
    "wof:placetype":"locality"
},
  "geometry": {"coordinates":[111.185,30.2065],"type":"Point"}
}