{
  "type": "Feature",
  "properties": {
    "gn:admin1_code":"33.0",
    "gn:asciiname":"Luchi",
    "gn:country_code":"CN",
    "gn:dem":569,
    "gn:feature_class":"P",
    "gn:feature_code":"PPL",
    "gn:name":"Luchi",
    "gn:population":0,
    "gn:timezone":"Asia/Shanghai",
    "iso:country":"CN",
    "name:ben_x_preferred":[
        "\u09b2\u09c1\u099a\u09bf"
    ],
    "name:hin_x_preferred":[
        "\u0932\u0942\u091a\u0940"
    ],
    "name:jpn_x_preferred":[
        "\u30eb\u30c1\u30fc"
    ],
    "name:ori_x_preferred":[
        "\u0b32\u0b41\u0b1a\u0b3f"
    ],
    "name:spa_x_preferred":[
        "Luchi"
    ],
    "name:zho_x_preferred":[
        "\u82a6\u6c60"
    ],
    "wof:name":"Luchi",
    "wof:placetype":"locality"
},
  "geometry": {"coordinates":[106.98152,29.95904],"type":"Point"}
}