{
  "type": "Feature",
  "properties": {
    "gn:admin1_code":"29.0",
    "gn:asciiname":"Abai",
    "gn:country_code":"CN",
    "gn:dem":1706,
    "gn:feature_class":"P",
    "gn:feature_code":"PPL",
    "gn:name":"Abai",
    "gn:population":0,
    "gn:timezone":"Asia/Shanghai",
    "iso:country":"CN",
    "name:ceb_x_preferred":[
        "Abai"
    ],
    "name:deu_x_preferred":[
        "Abai"
    ],
    "name:est_x_preferred":[
        "Abai"
    ],
    "name:fin_x_preferred":[
        "Abai"
    ],
    "name:hsb_x_preferred":[
        "Abaj"
    ],
    "name:hye_x_preferred":[
        "\u0531\u0562\u0561\u0575"
    ],
    "name:kaz_x_preferred":[
        "\u0410\u0431\u0430\u0439"
    ],
    "name:lit_x_preferred":[
        "Abajus"
    ],
    "name:rus_x_preferred":[
        "\u0410\u0431\u0430\u0439"
    ],
    "name:swe_x_preferred":[
        "Abai"
    ],
    "name:ukr_x_preferred":[
        "\u0410\u0431\u0430\u0439"
    ],
    "name:vep_x_preferred":[
        "Abai"
    ],
    "name:zho_x_preferred":[
        "\u963f\u767d"
    ],
    "wof:name":"Abai",
    "wof:placetype":"locality"
},
  "geometry": {"coordinates":[104.14100000000001,24.9235],"type":"Point"}
}