{
  "type": "Feature",
  "properties": {
    "gn:admin1_code":"32.0",
    "gn:asciiname":"Enji",
    "gn:country_code":"CN",
    "gn:dem":3143,
    "gn:feature_class":"P",
    "gn:feature_code":"PPL",
    "gn:name":"Enji",
    "gn:population":0,
    "gn:timezone":"Asia/Shanghai",
    "iso:country":"CN",
    "name:zho_x_preferred":[
        "\u6069\u673a"
    ],
    "wof:name":"Enji",
    "wof:placetype":"locality"
},
  "geometry": {"coordinates":[101.318,28.8256],"type":"Point"}
}