{
  "type": "Feature",
  "properties": {
    "gn:admin1_code":"8.0",
    "gn:asciiname":"Guanghuicun",
    "gn:country_code":"CN",
    "gn:dem":78,
    "gn:feature_class":"P",
    "gn:feature_code":"PPL",
    "gn:name":"Guanghuicun",
    "gn:population":0,
    "gn:timezone":"Asia/Shanghai",
    "iso:country":"CN",
    "name:zho_x_preferred":[
        "\u5149\u8f89\u6751"
    ],
    "wof:name":"Guanghuicun",
    "wof:placetype":"locality"
},
  "geometry": {"coordinates":[130.27732,46.8526],"type":"Point"}
}