{
  "type": "Feature",
  "properties": {
    "gn:admin1_code":"32.0",
    "gn:asciiname":"Damu'erzhu",
    "gn:country_code":"CN",
    "gn:dem":2714,
    "gn:feature_class":"P",
    "gn:feature_code":"PPL",
    "gn:name":"Damu\u2019erzhu",
    "gn:population":0,
    "gn:timezone":"Asia/Shanghai",
    "iso:country":"CN",
    "name:und_x_variant":[
        "Damu\u2019erzhu"
    ],
    "name:zho_x_preferred":[
        "\u5927\u6728\u5c14\u6731"
    ],
    "wof:name":"Damu'erzhu",
    "wof:placetype":"locality"
},
  "geometry": {"coordinates":[102.044,31.1822],"type":"Point"}
}