{
  "type": "Feature",
  "properties": {
    "gn:admin1_code":"12.0",
    "gn:asciiname":"Xiongjiawan",
    "gn:country_code":"CN",
    "gn:dem":87,
    "gn:feature_class":"P",
    "gn:feature_code":"PPL",
    "gn:name":"Xiongjiawan",
    "gn:population":0,
    "gn:timezone":"Asia/Shanghai",
    "iso:country":"CN",
    "name:und_x_variant":[
        "\u718a\u5bb6\u5846"
    ],
    "wof:name":"Xiongjiawan",
    "wof:placetype":"locality"
},
  "geometry": {"coordinates":[115.28332,30.35046],"type":"Point"}
}