{
  "type": "Feature",
  "properties": {
    "gn:admin1_code":"18.0",
    "gn:asciiname":"Bancheng Xiazhai",
    "gn:country_code":"CN",
    "gn:dem":1070,
    "gn:feature_class":"P",
    "gn:feature_code":"PPL",
    "gn:name":"Bancheng Xiazhai",
    "gn:population":0,
    "gn:timezone":"Asia/Shanghai",
    "iso:country":"CN",
    "name:zho_x_preferred":[
        "\u677f\u6a59\u4e0b\u5be8"
    ],
    "wof:name":"Bancheng Xiazhai",
    "wof:placetype":"locality"
},
  "geometry": {"coordinates":[108.246,26.7254],"type":"Point"}
}