{
  "type": "Feature",
  "properties": {
    "gn:admin1_code":"03",
    "gn:asciiname":"Lianhe",
    "gn:country_code":"CN",
    "gn:dem":79,
    "gn:feature_class":"P",
    "gn:feature_code":"PPLA4",
    "gn:name":"Lianhe",
    "gn:population":0,
    "gn:timezone":"Asia/Shanghai",
    "iso:country":"CN",
    "name:ceb_x_preferred":[
        "Lianhe"
    ],
    "name:deu_x_preferred":[
        "Lianhe"
    ],
    "name:swe_x_preferred":[
        "Lianhe"
    ],
    "name:und_x_variant":[
        "Lien-ho",
        "Lianhe",
        "\u83b2\u8377",
        "Lianhe Xiang",
        "\u83b2\u8377\u4e61"
    ],
    "wof:name":"Lianhe",
    "wof:placetype":"locality"
},
  "geometry": {"coordinates":[117.58333,28.38333],"type":"Point"}
}