{
  "type": "Feature",
  "properties": {
    "gn:admin1_code":"7.0",
    "gn:asciiname":"Shibihou",
    "gn:country_code":"CN",
    "gn:dem":223,
    "gn:feature_class":"P",
    "gn:feature_code":"PPL",
    "gn:name":"Shibihou",
    "gn:population":0,
    "gn:timezone":"Asia/Shanghai",
    "iso:country":"CN",
    "name:zho_x_preferred":[
        "\u77f3\u58c1\u540e"
    ],
    "wof:name":"Shibihou",
    "wof:placetype":"locality"
},
  "geometry": {"coordinates":[118.47363,27.79531],"type":"Point"}
}