{
  "type": "Feature",
  "properties": {
    "gn:admin1_code":"19.0",
    "gn:asciiname":"Xiangshantun",
    "gn:country_code":"CN",
    "gn:dem":154,
    "gn:feature_class":"P",
    "gn:feature_code":"PPL",
    "gn:name":"Xiangshantun",
    "gn:population":0,
    "gn:timezone":"Asia/Shanghai",
    "iso:country":"CN",
    "name:zho_x_preferred":[
        "\u6a61\u5c71\u5c6f"
    ],
    "wof:name":"Xiangshantun",
    "wof:placetype":"locality"
},
  "geometry": {"coordinates":[124.074,42.8603],"type":"Point"}
}