{
  "type": "Feature",
  "properties": {
    "gn:admin1_code":"29.0",
    "gn:asciiname":"Shangniupeng",
    "gn:country_code":"CN",
    "gn:dem":1836,
    "gn:feature_class":"P",
    "gn:feature_code":"PPL",
    "gn:name":"Shangniupeng",
    "gn:population":0,
    "gn:timezone":"Asia/Shanghai",
    "iso:country":"CN",
    "name:zho_x_preferred":[
        "\u4e0a\u725b\u68da"
    ],
    "wof:name":"Shangniupeng",
    "wof:placetype":"locality"
},
  "geometry": {"coordinates":[103.849,23.0789],"type":"Point"}
}