{
  "type": "Feature",
  "properties": {
    "gn:admin1_code":"2.0",
    "gn:asciiname":"Baishuiyan",
    "gn:country_code":"CN",
    "gn:dem":319,
    "gn:feature_class":"P",
    "gn:feature_code":"PPL",
    "gn:name":"Baishuiyan",
    "gn:population":0,
    "gn:timezone":"Asia/Shanghai",
    "iso:country":"CN",
    "name:zho_x_preferred":[
        "\u767d\u6c34\u5ca9"
    ],
    "wof:name":"Baishuiyan",
    "wof:placetype":"locality"
},
  "geometry": {"coordinates":[120.51379,29.43483],"type":"Point"}
}