{
  "type": "Feature",
  "properties": {
    "gn:admin1_code":"04",
    "gn:asciiname":"Meiyuan",
    "gn:country_code":"CN",
    "gn:dem":6,
    "gn:feature_class":"P",
    "gn:feature_code":"PPL",
    "gn:name":"Meiyuan",
    "gn:population":0,
    "gn:timezone":"Asia/Shanghai",
    "iso:country":"CN",
    "name:und_x_variant":[
        "\u6885\u56ed",
        "Meiyuancun",
        "\u6885\u56ed\u6751"
    ],
    "wof:name":"Meiyuan",
    "wof:placetype":"locality"
},
  "geometry": {"coordinates":[120.21158,31.55338],"type":"Point"}
}