{
  "type": "Feature",
  "properties": {
    "gn:admin1_code":"24.0",
    "gn:asciiname":"Ruqu",
    "gn:country_code":"CN",
    "gn:dem":685,
    "gn:feature_class":"P",
    "gn:feature_code":"PPL",
    "gn:name":"Ruqu",
    "gn:population":0,
    "gn:timezone":"Asia/Shanghai",
    "iso:country":"CN",
    "name:zho_x_preferred":[
        "\u8339\u53bb"
    ],
    "wof:name":"Ruqu",
    "wof:placetype":"locality"
},
  "geometry": {"coordinates":[111.82164,36.26373],"type":"Point"}
}