{
  "type": "Feature",
  "properties": {
    "gn:admin1_code":"4.0",
    "gn:asciiname":"Tongyu",
    "gn:country_code":"CN",
    "gn:dem":5,
    "gn:feature_class":"P",
    "gn:feature_code":"PPL",
    "gn:name":"Tongyu",
    "gn:population":0,
    "gn:timezone":"Asia/Shanghai",
    "iso:country":"CN",
    "name:und_x_variant":[
        "\u901a\u6986"
    ],
    "name:zho_x_preferred":[
        "\u901a\u6986"
    ],
    "wof:name":"Tongyu",
    "wof:placetype":"locality"
},
  "geometry": {"coordinates":[119.97116,32.15906],"type":"Point"}
}