{
  "type": "Feature",
  "properties": {
    "gn:admin1_code":"28.0",
    "gn:asciiname":"Huayuandao",
    "gn:country_code":"CN",
    "gn:dem":7,
    "gn:feature_class":"P",
    "gn:feature_code":"PPLA4",
    "gn:name":"Huayuandao",
    "gn:population":0,
    "gn:timezone":"Asia/Shanghai",
    "iso:country":"CN",
    "name:und_x_variant":[
        "Huayuandao Jiedao"
    ],
    "name:zho_x_preferred":[
        "\u82b1\u56ed\u9053"
    ],
    "name:zho_x_variant":[
        "\u82b1\u56ed\u9053\u8857\u9053"
    ],
    "wof:name":"Huayuandao",
    "wof:placetype":"locality"
},
  "geometry": {"coordinates":[117.14229,39.14847],"type":"Point"}
}