{
  "type": "Feature",
  "properties": {
    "gn:admin1_code":"12.0",
    "gn:asciiname":"Zhengjiagang",
    "gn:country_code":"CN",
    "gn:dem":33,
    "gn:feature_class":"P",
    "gn:feature_code":"PPL",
    "gn:name":"Zhengjiagang",
    "gn:population":0,
    "gn:timezone":"Asia/Shanghai",
    "iso:country":"CN",
    "name:zho_x_preferred":[
        "Zhengjiagang"
    ],
    "name:zho_x_variant":[
        "\u90d1\u5bb6\u5c97"
    ],
    "wof:name":"Zhengjiagang",
    "wof:placetype":"locality"
},
  "geometry": {"coordinates":[115.24523000000001,30.27771],"type":"Point"}
}