{
  "type": "Feature",
  "properties": {
    "gn:admin1_code":"14.0",
    "gn:asciiname":"Niangqucun",
    "gn:country_code":"CN",
    "gn:dem":4499,
    "gn:feature_class":"P",
    "gn:feature_code":"PPL",
    "gn:name":"Niangqucun",
    "gn:population":0,
    "gn:timezone":"Asia/Urumqi",
    "iso:country":"CN",
    "name:zho_x_preferred":[
        "\u5a18\u66f2\u6751"
    ],
    "wof:name":"Niangqucun",
    "wof:placetype":"locality"
},
  "geometry": {"coordinates":[91.89319999999999,31.3756],"type":"Point"}
}