{
  "type": "Feature",
  "properties": {
    "gn:admin1_code":"24.0",
    "gn:asciiname":"Hanjiazhuang",
    "gn:country_code":"CN",
    "gn:dem":466,
    "gn:feature_class":"P",
    "gn:feature_code":"PPL",
    "gn:name":"Hanjiazhuang",
    "gn:population":0,
    "gn:timezone":"Asia/Shanghai",
    "iso:country":"CN",
    "name:und_x_variant":[
        "\u97e9\u5bb6\u5e84"
    ],
    "wof:name":"Hanjiazhuang",
    "wof:placetype":"locality"
},
  "geometry": {"coordinates":[111.22238,35.31124000000001],"type":"Point"}
}