{
  "type": "Feature",
  "properties": {
    "gn:admin1_code":"26.0",
    "gn:asciiname":"Qianbaicao",
    "gn:country_code":"CN",
    "gn:dem":910,
    "gn:feature_class":"P",
    "gn:feature_code":"PPL",
    "gn:name":"Qianbaicao",
    "gn:population":0,
    "gn:timezone":"Asia/Shanghai",
    "iso:country":"CN",
    "name:und_x_variant":[
        "\u5343\u67cf\u69fd"
    ],
    "wof:name":"Qianbaicao",
    "wof:placetype":"locality"
},
  "geometry": {"coordinates":[107.49605,33.36983],"type":"Point"}
}