{
  "type": "Feature",
  "properties": {
    "gn:admin1_code":"16.0",
    "gn:asciiname":"Xindengzhan",
    "gn:country_code":"CN",
    "gn:dem":92,
    "gn:feature_class":"P",
    "gn:feature_code":"PPL",
    "gn:name":"Xindengzhan",
    "gn:population":0,
    "gn:timezone":"Asia/Shanghai",
    "iso:country":"CN",
    "name:zho_x_preferred":[
        "\u65b0\u706f\u76cf"
    ],
    "wof:name":"Xindengzhan",
    "wof:placetype":"locality"
},
  "geometry": {"coordinates":[109.023,23.2126],"type":"Point"}
}