{
  "type": "Feature",
  "properties": {
    "gn:admin1_code":"24",
    "gn:asciiname":"Daxin",
    "gn:country_code":"CN",
    "gn:dem":752,
    "gn:feature_class":"P",
    "gn:feature_code":"PPL",
    "gn:name":"Daxin",
    "gn:population":0,
    "gn:timezone":"Asia/Shanghai",
    "iso:country":"CN",
    "name:ceb_x_preferred":[
        "Daxin"
    ],
    "name:deu_x_preferred":[
        "Daxin"
    ],
    "wof:name":"Daxin",
    "wof:placetype":"locality"
},
  "geometry": {"coordinates":[112.20917,37.49444],"type":"Point"}
}