{
  "type": "Feature",
  "properties": {
    "gn:admin1_code":"19.0",
    "gn:asciiname":"Xiaohouyao",
    "gn:country_code":"CN",
    "gn:dem":83,
    "gn:feature_class":"P",
    "gn:feature_code":"PPL",
    "gn:name":"Xiaohouyao",
    "gn:population":0,
    "gn:timezone":"Asia/Shanghai",
    "iso:country":"CN",
    "name:zho_x_preferred":[
        "\u5c0f\u540e\u7a91"
    ],
    "wof:name":"Xiaohouyao",
    "wof:placetype":"locality"
},
  "geometry": {"coordinates":[123.622,42.7819],"type":"Point"}
}