{
  "type": "Feature",
  "properties": {
    "gn:admin1_code":"02",
    "gn:asciiname":"Zhukou",
    "gn:cc2":"CN",
    "gn:country_code":"CN",
    "gn:dem":31,
    "gn:feature_class":"P",
    "gn:feature_code":"PPL",
    "gn:name":"Zhukou",
    "gn:population":0,
    "gn:timezone":"Asia/Shanghai",
    "iso:country":"CN",
    "name:und_x_variant":[
        "Chu-k\u2019ou-ts\u2019un",
        "Zhukou"
    ],
    "name:zho_x_preferred":[
        "\u7af9\u53e3"
    ],
    "wof:name":"Zhukou",
    "wof:placetype":"locality"
},
  "geometry": {"coordinates":[121.44528,29.33444],"type":"Point"}
}