{
  "type": "Feature",
  "properties": {
    "gn:admin1_code":"11.0",
    "gn:asciiname":"Lanmutang",
    "gn:country_code":"CN",
    "gn:dem":172,
    "gn:feature_class":"P",
    "gn:feature_code":"PPL",
    "gn:name":"Lanmutang",
    "gn:population":0,
    "gn:timezone":"Asia/Shanghai",
    "iso:country":"CN",
    "name:zho_x_preferred":[
        "\u680f\u6728\u5858"
    ],
    "wof:name":"Lanmutang",
    "wof:placetype":"locality"
},
  "geometry": {"coordinates":[113.27785,27.27039000000001],"type":"Point"}
}