{
  "type": "Feature",
  "properties": {
    "gn:admin1_code":"01",
    "gn:asciiname":"Dongqiao",
    "gn:cc2":"CN",
    "gn:country_code":"CN",
    "gn:dem":39,
    "gn:feature_class":"P",
    "gn:feature_code":"PPL",
    "gn:name":"Dongqiao",
    "gn:population":0,
    "gn:timezone":"Asia/Shanghai",
    "iso:country":"CN",
    "name:und_x_variant":[
        "Tung-ch\u2019iao-t\u2019ou-chi",
        "Tung-ch\u2019iao",
        "Tung-ch\u2019iao-t\u2019ou",
        "Dongqiao"
    ],
    "wof:name":"Dongqiao",
    "wof:placetype":"locality"
},
  "geometry": {"coordinates":[116.67917,31.9025],"type":"Point"}
}