{
  "type": "Feature",
  "properties": {
    "gn:admin1_code":"4.0",
    "gn:asciiname":"Xindang",
    "gn:country_code":"CN",
    "gn:dem":3,
    "gn:feature_class":"P",
    "gn:feature_code":"PPL",
    "gn:name":"Xindang",
    "gn:population":0,
    "gn:timezone":"Asia/Shanghai",
    "iso:country":"CN",
    "name:zho_x_preferred":[
        "Xindang"
    ],
    "name:zho_x_variant":[
        "\u8f9b\u8361"
    ],
    "wof:name":"Xindang",
    "wof:placetype":"locality"
},
  "geometry": {"coordinates":[119.86122,33.71073],"type":"Point"}
}