{
  "type": "Feature",
  "properties": {
    "gn:admin1_code":"10",
    "gn:asciiname":"Aihetan",
    "gn:country_code":"CN",
    "gn:dem":878,
    "gn:feature_class":"P",
    "gn:feature_code":"PPL",
    "gn:name":"Aihetan",
    "gn:population":0,
    "gn:timezone":"Asia/Shanghai",
    "iso:country":"CN",
    "name:zho_x_preferred":[
        "\u827e\u6cb3\u6ee9"
    ],
    "wof:name":"Aihetan",
    "wof:placetype":"locality"
},
  "geometry": {"coordinates":[116.07955,40.63324],"type":"Point"}
}