{
  "type": "Feature",
  "properties": {
    "gn:admin1_code":"12.0",
    "gn:asciiname":"Lijialiangzi",
    "gn:country_code":"CN",
    "gn:dem":1073,
    "gn:feature_class":"P",
    "gn:feature_code":"PPL",
    "gn:name":"Lijialiangzi",
    "gn:population":0,
    "gn:timezone":"Asia/Shanghai",
    "iso:country":"CN",
    "name:zho_x_preferred":[
        "\u674e\u5bb6\u6881\u5b50"
    ],
    "wof:name":"Lijialiangzi",
    "wof:placetype":"locality"
},
  "geometry": {"coordinates":[110.23727,31.11436],"type":"Point"}
}