{
  "type": "Feature",
  "properties": {
    "gn:admin1_code":"29",
    "gn:asciiname":"Wufengcun",
    "gn:country_code":"CN",
    "gn:dem":1939,
    "gn:feature_class":"P",
    "gn:feature_code":"PPL",
    "gn:name":"Wufengcun",
    "gn:population":0,
    "gn:timezone":"Asia/Shanghai",
    "iso:country":"CN",
    "name:zho_x_preferred":[
        "\u4e94\u4e30\u6751"
    ],
    "wof:name":"Wufengcun",
    "wof:placetype":"locality"
},
  "geometry": {"coordinates":[103.06415,24.89994],"type":"Point"}
}