{
  "type": "Feature",
  "properties": {
    "gn:admin1_code":"4.0",
    "gn:asciiname":"Shuangjingzi",
    "gn:country_code":"CN",
    "gn:dem":39,
    "gn:feature_class":"P",
    "gn:feature_code":"PPL",
    "gn:name":"Shuangjingzi",
    "gn:population":0,
    "gn:timezone":"Asia/Shanghai",
    "iso:country":"CN",
    "name:zho_x_preferred":[
        "\u53cc\u4e95\u5b50"
    ],
    "wof:name":"Shuangjingzi",
    "wof:placetype":"locality"
},
  "geometry": {"coordinates":[118.59099999999999,32.7692],"type":"Point"}
}