{
  "type": "Feature",
  "properties": {
    "gn:admin1_code":"15.0",
    "gn:asciiname":"Zhushangou",
    "gn:country_code":"CN",
    "gn:dem":2145,
    "gn:feature_class":"P",
    "gn:feature_code":"PPL",
    "gn:name":"Zhushangou",
    "gn:population":0,
    "gn:timezone":"Asia/Shanghai",
    "iso:country":"CN",
    "name:zho_x_preferred":[
        "\u7af9\u5c71\u6c9f"
    ],
    "wof:name":"Zhushangou",
    "wof:placetype":"locality"
},
  "geometry": {"coordinates":[104.63782,34.02161],"type":"Point"}
}