{
  "type": "Feature",
  "properties": {
    "gn:admin1_code":"12.0",
    "gn:asciiname":"Paifengba",
    "gn:country_code":"CN",
    "gn:dem":889,
    "gn:feature_class":"P",
    "gn:feature_code":"PPL",
    "gn:name":"Paifengba",
    "gn:population":0,
    "gn:timezone":"Asia/Shanghai",
    "iso:country":"CN",
    "name:zho_x_preferred":[
        "\u6392\u5cf0\u575d"
    ],
    "wof:name":"Paifengba",
    "wof:placetype":"locality"
},
  "geometry": {"coordinates":[109.08019,29.84385],"type":"Point"}
}