{
  "type": "Feature",
  "properties": {
    "gn:admin1_code":"26.0",
    "gn:asciiname":"Xinlucun",
    "gn:country_code":"CN",
    "gn:dem":332,
    "gn:feature_class":"P",
    "gn:feature_code":"PPL",
    "gn:name":"Xinlucun",
    "gn:population":0,
    "gn:timezone":"Asia/Shanghai",
    "iso:country":"CN",
    "name:zho_x_preferred":[
        "\u65b0\u9c81\u6751"
    ],
    "wof:name":"Xinlucun",
    "wof:placetype":"locality"
},
  "geometry": {"coordinates":[110.17017,34.86116],"type":"Point"}
}