{
  "type": "Feature",
  "properties": {
    "gn:admin1_code":"30.0",
    "gn:asciiname":"Xinpangtang",
    "gn:country_code":"CN",
    "gn:dem":129,
    "gn:feature_class":"P",
    "gn:feature_code":"PPL",
    "gn:name":"Xinpangtang",
    "gn:population":0,
    "gn:timezone":"Asia/Shanghai",
    "iso:country":"CN",
    "name:zho_x_preferred":[
        "Xinpangtang"
    ],
    "name:zho_x_variant":[
        "\u65b0\u6ec2\u5858"
    ],
    "wof:name":"Xinpangtang",
    "wof:placetype":"locality"
},
  "geometry": {"coordinates":[112.53917,24.96417000000001],"type":"Point"}
}