{
  "type": "Feature",
  "properties": {
    "gn:admin1_code":"24.0",
    "gn:asciiname":"Shidanghe",
    "gn:country_code":"CN",
    "gn:dem":1370,
    "gn:feature_class":"P",
    "gn:feature_code":"PPL",
    "gn:name":"Shidanghe",
    "gn:population":0,
    "gn:timezone":"Asia/Shanghai",
    "iso:country":"CN",
    "name:zho_x_preferred":[
        "\u77f3\u5f53\u6cb3"
    ],
    "wof:name":"Shidanghe",
    "wof:placetype":"locality"
},
  "geometry": {"coordinates":[112.20165,38.01467],"type":"Point"}
}