{
  "type": "Feature",
  "properties": {
    "gn:admin1_code":"18.0",
    "gn:asciiname":"Dongtun",
    "gn:country_code":"CN",
    "gn:dem":493,
    "gn:feature_class":"P",
    "gn:feature_code":"PPL",
    "gn:name":"Dongtun",
    "gn:population":0,
    "gn:timezone":"Asia/Shanghai",
    "iso:country":"CN",
    "name:zho_x_preferred":[
        "\u4e1c\u5c6f"
    ],
    "wof:name":"Dongtun",
    "wof:placetype":"locality"
},
  "geometry": {"coordinates":[109.194,26.2895],"type":"Point"}
}