{
  "type": "Feature",
  "properties": {
    "gn:admin1_code":"19.0",
    "gn:asciiname":"Houshuangcun",
    "gn:country_code":"CN",
    "gn:dem":6,
    "gn:feature_class":"P",
    "gn:feature_code":"PPL",
    "gn:name":"Houshuangcun",
    "gn:population":0,
    "gn:timezone":"Asia/Shanghai",
    "iso:country":"CN",
    "name:zho_x_preferred":[
        "\u540e\u53cc\u6751"
    ],
    "wof:name":"Houshuangcun",
    "wof:placetype":"locality"
},
  "geometry": {"coordinates":[122.52500000000001,41.0856],"type":"Point"}
}