{
  "type": "Feature",
  "properties": {
    "gn:admin1_code":"32.0",
    "gn:asciiname":"Tianxing",
    "gn:country_code":"CN",
    "gn:dem":492,
    "gn:feature_class":"P",
    "gn:feature_code":"PPL",
    "gn:name":"Tianxing",
    "gn:population":0,
    "gn:timezone":"Asia/Shanghai",
    "iso:country":"CN",
    "name:ceb_x_preferred":[
        "Tianxing"
    ],
    "name:deu_x_preferred":[
        "Tianxing"
    ],
    "name:swe_x_preferred":[
        "Tianxing"
    ],
    "name:zho_x_preferred":[
        "\u5929\u661f"
    ],
    "wof:name":"Tianxing",
    "wof:placetype":"locality"
},
  "geometry": {"coordinates":[105.50700000000001,29.7522],"type":"Point"}
}