{
  "type": "Feature",
  "properties": {
    "gn:admin1_code":"26.0",
    "gn:asciiname":"Gunziling",
    "gn:country_code":"CN",
    "gn:dem":666,
    "gn:feature_class":"P",
    "gn:feature_code":"PPL",
    "gn:name":"Gunziling",
    "gn:population":0,
    "gn:timezone":"Asia/Shanghai",
    "iso:country":"CN",
    "name:zho_x_preferred":[
        "\u78d9\u5b50\u5cad"
    ],
    "wof:name":"Gunziling",
    "wof:placetype":"locality"
},
  "geometry": {"coordinates":[111.01519,33.35681],"type":"Point"}
}