{
  "type": "Feature",
  "properties": {
    "gn:admin1_code":"20.0",
    "gn:asciiname":"Dasuji",
    "gn:country_code":"CN",
    "gn:dem":1705,
    "gn:feature_class":"P",
    "gn:feature_code":"PPL",
    "gn:name":"Dasuji",
    "gn:population":0,
    "gn:timezone":"Asia/Shanghai",
    "iso:country":"CN",
    "name:und_x_variant":[
        "\u5927\u82cf\u8ba1"
    ],
    "wof:name":"Dasuji",
    "wof:placetype":"locality"
},
  "geometry": {"coordinates":[112.24808,41.43606],"type":"Point"}
}