{
  "type": "Feature",
  "properties": {
    "gn:admin1_code":"22",
    "gn:asciiname":"Dashiwo",
    "gn:country_code":"CN",
    "gn:dem":75,
    "gn:feature_class":"P",
    "gn:feature_code":"PPLA4",
    "gn:name":"Dashiwo",
    "gn:population":0,
    "gn:timezone":"Asia/Shanghai",
    "iso:country":"CN",
    "name:und_x_variant":[
        "Dashiwo Zhen"
    ],
    "name:zho_x_preferred":[
        "\u5927\u77f3\u7a9d"
    ],
    "name:zho_x_variant":[
        "\u5927\u77f3\u7a9d\u9547"
    ],
    "wof:name":"Dashiwo",
    "wof:placetype":"locality"
},
  "geometry": {"coordinates":[115.81368999999999,39.55423],"type":"Point"}
}