{
  "type": "Feature",
  "properties": {
    "gn:admin1_code":"18",
    "gn:asciiname":"Maozhong",
    "gn:country_code":"CN",
    "gn:dem":1217,
    "gn:feature_class":"P",
    "gn:feature_code":"PPL",
    "gn:name":"Maozhong",
    "gn:population":0,
    "gn:timezone":"Asia/Shanghai",
    "iso:country":"CN",
    "name:zho_x_preferred":[
        "\u732b\u4e2d"
    ],
    "wof:name":"Maozhong",
    "wof:placetype":"locality"
},
  "geometry": {"coordinates":[106.85899999999999,25.9907],"type":"Point"}
}