{
  "type": "Feature",
  "properties": {
    "gn:admin1_code":"11.0",
    "gn:asciiname":"Huangsiqiao",
    "gn:country_code":"CN",
    "gn:dem":586,
    "gn:feature_class":"P",
    "gn:feature_code":"PPL",
    "gn:name":"Huangsiqiao",
    "gn:population":0,
    "gn:timezone":"Asia/Shanghai",
    "iso:country":"CN",
    "name:zho_x_preferred":[
        "\u9ec4\u4e1d\u6865"
    ],
    "wof:name":"Huangsiqiao",
    "wof:placetype":"locality"
},
  "geometry": {"coordinates":[109.36472999999999,27.91267],"type":"Point"}
}