{
  "type": "Feature",
  "properties": {
    "gn:admin1_code":"15.0",
    "gn:asciiname":"Yan'erping",
    "gn:country_code":"CN",
    "gn:dem":1677,
    "gn:feature_class":"P",
    "gn:feature_code":"PPL",
    "gn:name":"Yan\u2019erping",
    "gn:population":0,
    "gn:timezone":"Asia/Shanghai",
    "iso:country":"CN",
    "name:und_x_variant":[
        "Yan\u2019erping"
    ],
    "name:zho_x_preferred":[
        "\u71d5\u513f\u576a"
    ],
    "wof:name":"Yan'erping",
    "wof:placetype":"locality"
},
  "geometry": {"coordinates":[103.89,36.2887],"type":"Point"}
}