{
  "type": "Feature",
  "properties": {
    "gn:admin1_code":"25",
    "gn:asciiname":"Yaodezhuang",
    "gn:country_code":"CN",
    "gn:dem":23,
    "gn:feature_class":"P",
    "gn:feature_code":"PPL",
    "gn:name":"Yaodezhuang",
    "gn:population":0,
    "gn:timezone":"Asia/Shanghai",
    "iso:country":"CN",
    "name:zho_x_preferred":[
        "\u8000\u5fb7\u5e84"
    ],
    "wof:name":"Yaodezhuang",
    "wof:placetype":"locality"
},
  "geometry": {"coordinates":[116.985,37.0153],"type":"Point"}
}