{
  "type": "Feature",
  "properties": {
    "gn:admin1_code":"32.0",
    "gn:asciiname":"Anzi",
    "gn:country_code":"CN",
    "gn:dem":3902,
    "gn:feature_class":"P",
    "gn:feature_code":"PPL",
    "gn:name":"Anzi",
    "gn:population":0,
    "gn:timezone":"Asia/Shanghai",
    "iso:country":"CN",
    "name:zho_x_preferred":[
        "\u5b89\u5b5c"
    ],
    "wof:name":"Anzi",
    "wof:placetype":"locality"
},
  "geometry": {"coordinates":[99.36496,31.12529],"type":"Point"}
}