{
  "type": "Feature",
  "properties": {
    "gn:admin1_code":"4.0",
    "gn:asciiname":"Chun'ercun",
    "gn:country_code":"CN",
    "gn:dem":3,
    "gn:feature_class":"P",
    "gn:feature_code":"PPL",
    "gn:name":"Chun\u2019ercun",
    "gn:population":0,
    "gn:timezone":"Asia/Shanghai",
    "iso:country":"CN",
    "name:und_x_variant":[
        "Chun\u2019ercun"
    ],
    "name:zho_x_preferred":[
        "\u6625\u4e8c\u6751"
    ],
    "wof:name":"Chun'ercun",
    "wof:placetype":"locality"
},
  "geometry": {"coordinates":[119.41231000000001,34.27295],"type":"Point"}
}