{
  "type": "Feature",
  "properties": {
    "gn:admin1_code":"32.0",
    "gn:asciiname":"Saga",
    "gn:country_code":"CN",
    "gn:dem":2993,
    "gn:feature_class":"P",
    "gn:feature_code":"PPL",
    "gn:name":"Saga",
    "gn:population":0,
    "gn:timezone":"Asia/Shanghai",
    "iso:country":"CN",
    "name:zho_x_preferred":[
        "\u8428\u560e"
    ],
    "wof:name":"Saga",
    "wof:placetype":"locality"
},
  "geometry": {"coordinates":[102.989,27.6411],"type":"Point"}
}