{
  "type": "Feature",
  "properties": {
    "gn:admin1_code":"26.0",
    "gn:asciiname":"Banjiagou",
    "gn:country_code":"CN",
    "gn:dem":1594,
    "gn:feature_class":"P",
    "gn:feature_code":"PPL",
    "gn:name":"Banjiagou",
    "gn:population":0,
    "gn:timezone":"Asia/Shanghai",
    "iso:country":"CN",
    "name:und_x_variant":[
        "\u822c\u5bb6\u6c9f"
    ],
    "wof:name":"Banjiagou",
    "wof:placetype":"locality"
},
  "geometry": {"coordinates":[106.91807,33.88058],"type":"Point"}
}