{
  "type": "Feature",
  "properties": {
    "gn:admin1_code":"9",
    "gn:asciiname":"Sunwangzhuang",
    "gn:country_code":"CN",
    "gn:dem":41,
    "gn:feature_class":"P",
    "gn:feature_code":"PPL",
    "gn:name":"Sunwangzhuang",
    "gn:population":0,
    "gn:timezone":"Asia/Shanghai",
    "iso:country":"CN",
    "name:zho_x_preferred":[
        "\u5b59\u738b\u5e84"
    ],
    "wof:name":"Sunwangzhuang",
    "wof:placetype":"locality"
},
  "geometry": {"coordinates":[115.974,34.1429],"type":"Point"}
}