{
  "type": "Feature",
  "properties": {
    "gn:admin1_code":"26.0",
    "gn:asciiname":"Shangluo Diqu",
    "gn:country_code":"CN",
    "gn:dem":714,
    "gn:feature_class":"P",
    "gn:feature_code":"PPL",
    "gn:name":"Shangluo Diqu",
    "gn:population":0,
    "gn:timezone":"Asia/Shanghai",
    "iso:country":"CN",
    "name:zho_x_preferred":[
        "\u5546\u6d1b\u5730\u533a"
    ],
    "wof:name":"Shangluo Diqu",
    "wof:placetype":"locality"
},
  "geometry": {"coordinates":[109.93293,33.87103],"type":"Point"}
}