{
  "type": "Feature",
  "properties": {
    "gn:admin1_code":"16.0",
    "gn:asciiname":"Liumushui",
    "gn:country_code":"CN",
    "gn:dem":75,
    "gn:feature_class":"P",
    "gn:feature_code":"PPL",
    "gn:name":"Liumushui",
    "gn:population":0,
    "gn:timezone":"Asia/Shanghai",
    "iso:country":"CN",
    "name:zho_x_preferred":[
        "\u516d\u6728\u6c34"
    ],
    "wof:name":"Liumushui",
    "wof:placetype":"locality"
},
  "geometry": {"coordinates":[109.654,21.9486],"type":"Point"}
}