{
  "type": "Feature",
  "properties": {
    "gn:admin1_code":"32.0",
    "gn:asciiname":"Maoyantang",
    "gn:country_code":"CN",
    "gn:dem":446,
    "gn:feature_class":"P",
    "gn:feature_code":"PPL",
    "gn:name":"Maoyantang",
    "gn:population":0,
    "gn:timezone":"Asia/Shanghai",
    "iso:country":"CN",
    "name:zho_x_preferred":[
        "\u6bdb\u5830\u5858"
    ],
    "wof:name":"Maoyantang",
    "wof:placetype":"locality"
},
  "geometry": {"coordinates":[104.56802,30.75602],"type":"Point"}
}