{
  "type": "Feature",
  "properties": {
    "gn:admin1_code":"14.0",
    "gn:asciiname":"Cuobengcun",
    "gn:country_code":"CN",
    "gn:dem":4690,
    "gn:feature_class":"P",
    "gn:feature_code":"PPL",
    "gn:name":"Cuobengcun",
    "gn:population":0,
    "gn:timezone":"Asia/Urumqi",
    "iso:country":"CN",
    "name:zho_x_preferred":[
        "\u9519\u5d29\u6751"
    ],
    "wof:name":"Cuobengcun",
    "wof:placetype":"locality"
},
  "geometry": {"coordinates":[92.64304,31.9861],"type":"Point"}
}