{
  "type": "Feature",
  "properties": {
    "gn:admin1_code":"26.0",
    "gn:asciiname":"Saogailanabu",
    "gn:country_code":"CN",
    "gn:dem":1289,
    "gn:feature_class":"P",
    "gn:feature_code":"PPL",
    "gn:name":"Saogailanabu",
    "gn:population":0,
    "gn:timezone":"Asia/Shanghai",
    "iso:country":"CN",
    "name:zho_x_preferred":[
        "\u9a9a\u76d6\u62c9\u90a3\u5e03"
    ],
    "wof:name":"Saogailanabu",
    "wof:placetype":"locality"
},
  "geometry": {"coordinates":[109.74448999999998,38.78652],"type":"Point"}
}