{
  "type": "Feature",
  "properties": {
    "gn:admin1_code":"0.0",
    "gn:asciiname":"Hsiao-ti-fang",
    "gn:country_code":"CN",
    "gn:dem":1868,
    "gn:feature_class":"P",
    "gn:feature_code":"PPL",
    "gn:name":"Hsiao-ti-fang",
    "gn:population":0,
    "gn:timezone":"Asia/Shanghai",
    "iso:country":"CN",
    "wof:name":"Hsiao-ti-fang",
    "wof:placetype":"locality"
},
  "geometry": {"coordinates":[98.92495,24.13041],"type":"Point"}
}