{
  "type": "Feature",
  "properties": {
    "gn:admin1_code":"29.0",
    "gn:asciiname":"Dananshao",
    "gn:country_code":"CN",
    "gn:dem":1689,
    "gn:feature_class":"P",
    "gn:feature_code":"PPL",
    "gn:name":"Dananshao",
    "gn:population":0,
    "gn:timezone":"Asia/Shanghai",
    "iso:country":"CN",
    "name:zho_x_preferred":[
        "\u5927\u5357\u52fa"
    ],
    "wof:name":"Dananshao",
    "wof:placetype":"locality"
},
  "geometry": {"coordinates":[100.70099999999999,24.6153],"type":"Point"}
}