{
  "type": "Feature",
  "properties": {
    "gn:admin1_code":"11",
    "gn:asciiname":"Nanchong",
    "gn:country_code":"CN",
    "gn:dem":567,
    "gn:feature_class":"P",
    "gn:feature_code":"PPL",
    "gn:name":"Nanchong",
    "gn:population":0,
    "gn:timezone":"Asia/Shanghai",
    "iso:country":"CN",
    "name:afr_x_preferred":[
        "Nanchong"
    ],
    "name:ara_x_preferred":[
        "\u0646\u0627\u0646\u062a\u0634\u0648\u0646\u063a"
    ],
    "name:cdo_x_preferred":[
        "N\u00e0ng-ch\u1e73\u0306ng"
    ],
    "name:ceb_x_preferred":[
        "Nanchong"
    ],
    "name:ces_x_preferred":[
        "Nan-\u010dchung"
    ],
    "name:dan_x_preferred":[
        "Nanchong"
    ],
    "name:deu_x_preferred":[
        "Nanchong"
    ],
    "name:eus_x_preferred":[
        "Nanchong"
    ],
    "name:fas_x_preferred":[
        "\u0646\u0627\u0646\u0686\u0648\u0646\u06af"
    ],
    "name:fin_x_preferred":[
        "Nanchong"
    ],
    "name:fra_x_preferred":[
        "Nanchong"
    ],
    "name:ind_x_preferred":[
        "Nanchong"
    ],
    "name:ita_x_preferred":[
        "Nanchong"
    ],
    "name:jpn_x_preferred":[
        "\u5357\u5145\u5e02"
    ],
    "name:kaz_x_preferred":[
        "\u041d\u0430\u043d\u044c\u0447\u0443\u043d"
    ],
    "name:kik_x_preferred":[
        "Nanchong"
    ],
    "name:kor_x_preferred":[
        "\ub09c\ucda9\uc2dc"
    ],
    "name:mlg_x_preferred":[
        "Nanchong"
    ],
    "name:nld_x_preferred":[
        "Nanchong"
    ],
    "name:nno_x_preferred":[
        "Nanchong"
    ],
    "name:nor_x_preferred":[
        "Nanchong"
    ],
    "name:pol_x_preferred":[
        "Nanchong"
    ],
    "name:rus_x_preferred":[
        "\u041d\u0430\u043d\u044c\u0447\u0443\u043d"
    ],
    "name:spa_x_preferred":[
        "Nanchong"
    ],
    "name:srp_x_preferred":[
        "\u041d\u0430\u043d\u0447\u0443\u043d\u0433"
    ],
    "name:swe_x_preferred":[
        "Nanchong"
    ],
    "name:tur_x_preferred":[
        "Nanchong"
    ],
    "name:urd_x_preferred":[
        "\u0646\u0627\u0646\u0686\u0648\u0646\u06af"
    ],
    "name:vie_x_preferred":[
        "Nam Sung"
    ],
    "name:war_x_preferred":[
        "Nanchong"
    ],
    "name:zho_x_preferred":[
        "\u5357\u51b2"
    ],
    "name:zho_x_variant":[
        "\u5357\u5145\u5e02"
    ],
    "wof:name":"Nanchong",
    "wof:placetype":"locality"
},
  "geometry": {"coordinates":[111.05304,27.63504],"type":"Point"}
}