{
  "type": "Feature",
  "properties": {
    "gn:admin1_code":"3.0",
    "gn:asciiname":"Huangxicun",
    "gn:country_code":"CN",
    "gn:dem":41,
    "gn:feature_class":"P",
    "gn:feature_code":"PPL",
    "gn:name":"Huangxicun",
    "gn:population":0,
    "gn:timezone":"Asia/Shanghai",
    "iso:country":"CN",
    "name:und_x_variant":[
        "\u749c\u6eaa\u6751"
    ],
    "wof:name":"Huangxicun",
    "wof:placetype":"locality"
},
  "geometry": {"coordinates":[115.72262000000001,28.63123],"type":"Point"}
}