{
  "type": "Feature",
  "properties": {
    "gn:admin1_code":"19.0",
    "gn:asciiname":"Donggaotaizi",
    "gn:country_code":"CN",
    "gn:dem":34,
    "gn:feature_class":"P",
    "gn:feature_code":"PPL",
    "gn:name":"Donggaotaizi",
    "gn:population":0,
    "gn:timezone":"Asia/Shanghai",
    "iso:country":"CN",
    "name:zho_x_preferred":[
        "\u4e1c\u9ad8\u53f0\u5b50"
    ],
    "wof:name":"Donggaotaizi",
    "wof:placetype":"locality"
},
  "geometry": {"coordinates":[122.89413,42.06469],"type":"Point"}
}