{
  "type": "Feature",
  "properties": {
    "gn:admin1_code":"1.0",
    "gn:asciiname":"Daxuzhuangcun",
    "gn:country_code":"CN",
    "gn:dem":30,
    "gn:feature_class":"P",
    "gn:feature_code":"PPL",
    "gn:name":"Daxuzhuangcun",
    "gn:population":0,
    "gn:timezone":"Asia/Shanghai",
    "iso:country":"CN",
    "name:zho_x_preferred":[
        "\u5927\u8bb8\u5e84\u6751"
    ],
    "wof:name":"Daxuzhuangcun",
    "wof:placetype":"locality"
},
  "geometry": {"coordinates":[115.99281999999999,32.95347],"type":"Point"}
}