{
  "type": "Feature",
  "properties": {
    "gn:admin1_code":"3.0",
    "gn:asciiname":"Qixiansi",
    "gn:country_code":"CN",
    "gn:dem":67,
    "gn:feature_class":"P",
    "gn:feature_code":"PPL",
    "gn:name":"Qixiansi",
    "gn:population":0,
    "gn:timezone":"Asia/Shanghai",
    "iso:country":"CN",
    "name:und_x_variant":[
        "\u6816\u8d24\u5bfa"
    ],
    "wof:name":"Qixiansi",
    "wof:placetype":"locality"
},
  "geometry": {"coordinates":[114.77275,27.81086],"type":"Point"}
}