{
  "type": "Feature",
  "properties": {
    "gn:admin1_code":"11.0",
    "gn:asciiname":"Muzhai",
    "gn:country_code":"CN",
    "gn:dem":501,
    "gn:feature_class":"P",
    "gn:feature_code":"PPL",
    "gn:name":"Muzhai",
    "gn:population":0,
    "gn:timezone":"Asia/Shanghai",
    "iso:country":"CN",
    "name:zho_x_preferred":[
        "\u6bcd\u5be8"
    ],
    "wof:name":"Muzhai",
    "wof:placetype":"locality"
},
  "geometry": {"coordinates":[109.62924,28.81252000000001],"type":"Point"}
}