{
  "type": "Feature",
  "properties": {
    "gn:admin1_code":"8.0",
    "gn:asciiname":"Jiangbeicun",
    "gn:country_code":"CN",
    "gn:dem":256,
    "gn:feature_class":"P",
    "gn:feature_code":"PPL",
    "gn:name":"Jiangbeicun",
    "gn:population":0,
    "gn:timezone":"Asia/Shanghai",
    "iso:country":"CN",
    "name:zho_x_preferred":[
        "\u6c5f\u5317\u6751"
    ],
    "wof:name":"Jiangbeicun",
    "wof:placetype":"locality"
},
  "geometry": {"coordinates":[129.32288,44.56215],"type":"Point"}
}