{
  "type": "Feature",
  "properties": {
    "gn:admin1_code":"26.0",
    "gn:asciiname":"Suanciqu",
    "gn:country_code":"CN",
    "gn:dem":1329,
    "gn:feature_class":"P",
    "gn:feature_code":"PPL",
    "gn:name":"Suanciqu",
    "gn:population":0,
    "gn:timezone":"Asia/Shanghai",
    "iso:country":"CN",
    "name:zho_x_preferred":[
        "\u9178\u523a\u6e20"
    ],
    "wof:name":"Suanciqu",
    "wof:placetype":"locality"
},
  "geometry": {"coordinates":[108.81113999999999,36.85516],"type":"Point"}
}