{
  "type": "Feature",
  "properties": {
    "gn:admin1_code":"11.0",
    "gn:asciiname":"Yan'aotai",
    "gn:country_code":"CN",
    "gn:dem":109,
    "gn:feature_class":"P",
    "gn:feature_code":"PPL",
    "gn:name":"Yan\u2019aotai",
    "gn:population":0,
    "gn:timezone":"Asia/Shanghai",
    "iso:country":"CN",
    "name:und_x_variant":[
        "Yan\u2019aotai"
    ],
    "name:zho_x_preferred":[
        "\u781a\u51f9\u53f0"
    ],
    "wof:name":"Yan'aotai",
    "wof:placetype":"locality"
},
  "geometry": {"coordinates":[113.74229,28.5818],"type":"Point"}
}