{
  "type": "Feature",
  "properties": {
    "gn:admin1_code":"9.0",
    "gn:asciiname":"Shicaowang",
    "gn:country_code":"CN",
    "gn:dem":223,
    "gn:feature_class":"P",
    "gn:feature_code":"PPL",
    "gn:name":"Shicaowang",
    "gn:population":0,
    "gn:timezone":"Asia/Shanghai",
    "iso:country":"CN",
    "name:zho_x_preferred":[
        "\u77f3\u69fd\u738b"
    ],
    "wof:name":"Shicaowang",
    "wof:placetype":"locality"
},
  "geometry": {"coordinates":[112.97071,34.15762],"type":"Point"}
}