{
  "type": "Feature",
  "properties": {
    "gn:admin1_code":"29.0",
    "gn:asciiname":"Zhuilipo",
    "gn:country_code":"CN",
    "gn:dem":1891,
    "gn:feature_class":"P",
    "gn:feature_code":"PPL",
    "gn:name":"Zhuilipo",
    "gn:population":0,
    "gn:timezone":"Asia/Shanghai",
    "iso:country":"CN",
    "name:zho_x_preferred":[
        "\u9525\u6817\u5761"
    ],
    "wof:name":"Zhuilipo",
    "wof:placetype":"locality"
},
  "geometry": {"coordinates":[99.47499999999999,25.1359],"type":"Point"}
}