{
  "type": "Feature",
  "properties": {
    "gn:admin1_code":"12.0",
    "gn:asciiname":"Shuduan",
    "gn:country_code":"CN",
    "gn:dem":29,
    "gn:feature_class":"P",
    "gn:feature_code":"PPL",
    "gn:name":"Shuduan",
    "gn:population":0,
    "gn:timezone":"Asia/Shanghai",
    "iso:country":"CN",
    "name:zho_x_preferred":[
        "\u8212\u6bb5"
    ],
    "wof:name":"Shuduan",
    "wof:placetype":"locality"
},
  "geometry": {"coordinates":[114.55965,30.35585],"type":"Point"}
}