{
  "type": "Feature",
  "properties": {
    "gn:admin1_code":"10.0",
    "gn:asciiname":"Wanglinkou",
    "gn:country_code":"CN",
    "gn:dem":228,
    "gn:feature_class":"P",
    "gn:feature_code":"PPLA4",
    "gn:name":"Wanglinkou",
    "gn:population":0,
    "gn:timezone":"Asia/Shanghai",
    "iso:country":"CN",
    "name:und_x_variant":[
        "Dongwangliukou",
        "Tung-wang-liu-k\u2019ou",
        "Tung-wang-lin-k\u2019ou",
        "Wanglinkou",
        "\u738b\u6797\u53e3",
        "\u738b\u6797\u53e3\u4e61",
        "Wanglinkou Xiang"
    ],
    "wof:name":"Wanglinkou",
    "wof:placetype":"locality"
},
  "geometry": {"coordinates":[114.34219,38.82219],"type":"Point"}
}