{
  "type": "Feature",
  "properties": {
    "gn:admin1_code":"11.0",
    "gn:asciiname":"Xiadongzhou",
    "gn:country_code":"CN",
    "gn:dem":88,
    "gn:feature_class":"P",
    "gn:feature_code":"PPL",
    "gn:name":"Xiadongzhou",
    "gn:population":0,
    "gn:timezone":"Asia/Shanghai",
    "iso:country":"CN",
    "name:zho_x_preferred":[
        "\u4e0b\u6d1e\u5468"
    ],
    "wof:name":"Xiadongzhou",
    "wof:placetype":"locality"
},
  "geometry": {"coordinates":[113.36243,28.78874],"type":"Point"}
}