{
  "type": "Feature",
  "properties": {
    "gn:admin1_code":"26.0",
    "gn:asciiname":"Caizishan",
    "gn:country_code":"CN",
    "gn:dem":1246,
    "gn:feature_class":"P",
    "gn:feature_code":"PPL",
    "gn:name":"Caizishan",
    "gn:population":0,
    "gn:timezone":"Asia/Shanghai",
    "iso:country":"CN",
    "name:und_x_variant":[
        "\u83dc\u5b50\u5c71"
    ],
    "wof:name":"Caizishan",
    "wof:placetype":"locality"
},
  "geometry": {"coordinates":[107.3944,34.87034],"type":"Point"}
}