{
  "type": "Feature",
  "properties": {
    "iso:country":"CN",
    "qs:name":"\u4e09\u6c5f\u4f97\u65cf\u81ea\u6cbb\u53bf",
    "qs:name_adm0":"\u4e2d\u570b",
    "qs:name_adm1":"\u5e7f\u897f\u7701",
    "qs:photos":2,
    "qs:photos_1k":1,
    "qs:photos_9k":1,
    "qs:photos_9r":3,
    "qs:photos_all":92,
    "qs:photos_sr":1,
    "qs:placetype":"LocalAdmin",
    "qs:pop_sr":"0",
    "wd:wordcount":396,
    "wof:name":"\u4e09\u6c5f\u4f97\u65cf\u81ea\u6cbb\u53bf",
    "wof:placetype":"localadmin"
},
  "geometry": {"coordinates":[109.613857,25.81631],"type":"Point"}
}