{
  "type": "Feature",
  "properties": {
    "iso:country":"CN",
    "name:deu_x_preferred":[
        "Sanjiang"
    ],
    "name:eng_x_preferred":[
        "Sanjiang"
    ],
    "name:fas_x_preferred":[
        "\u0633\u0627\u0646\u0698\u06cc\u0627\u0646\u06af"
    ],
    "name:gan_x_preferred":[
        "\u4e09\u6c5f\u4f97\u65cf\u81ea\u6cbb\u53bf"
    ],
    "name:jpn_x_preferred":[
        "\u4e09\u6c5f\u30c8\u30f3\u65cf\u81ea\u6cbb\u770c"
    ],
    "name:nob_x_preferred":[
        "Sanjiang"
    ],
    "name:spa_x_preferred":[
        "Sanjiang"
    ],
    "name:swe_x_preferred":[
        "Sanjiang"
    ],
    "name:vie_x_preferred":[
        "Tam Giang"
    ],
    "name:wuu_x_preferred":[
        "\u4e09\u6c5f\u4f97\u65cf\u81ea\u6cbb\u53bf"
    ],
    "name:yue_x_preferred":[
        "\u4e09\u6c5f"
    ],
    "name:zho_x_preferred":[
        "\u4e09\u6c5f\u4f97\u65cf\u81ea\u6cbb\u53bf"
    ],
    "qs:name":"\u4e09\u6c5f\u4f97\u65cf\u81ea\u6cbb\u53bf",
    "qs:name_adm0":"\u4e2d\u570b",
    "qs:name_adm1":"\u5e7f\u897f\u7701",
    "qs:photos":2,
    "qs:photos_1k":1,
    "qs:photos_9k":1,
    "qs:photos_9r":3,
    "qs:photos_all":92,
    "qs:photos_sr":1,
    "qs:placetype":"LocalAdmin",
    "qs:pop_sr":"0",
    "wd:wordcount":396,
    "wof:name":"\u4e09\u6c5f\u4f97\u65cf\u81ea\u6cbb\u53bf",
    "wof:placetype":"localadmin"
},
  "geometry": {"coordinates":[109.613857,25.81631],"type":"Point"}
}