{
  "type": "Feature",
  "properties": {
    "gn:admin1_code":"14.0",
    "gn:asciiname":"Butungda",
    "gn:country_code":"CN",
    "gn:dem":4623,
    "gn:feature_class":"P",
    "gn:feature_code":"PPL",
    "gn:name":"Butungda",
    "gn:population":0,
    "gn:timezone":"Asia/Urumqi",
    "iso:country":"CN",
    "name:bod_x_preferred":[
        "Butungda"
    ],
    "name:zho_x_preferred":[
        "Bosongda"
    ],
    "name:zho_x_variant":[
        "\u6ce2\u677e\u8fbe"
    ],
    "wof:name":"Butungda",
    "wof:placetype":"locality"
},
  "geometry": {"coordinates":[93.503,32.103],"type":"Point"}
}