{
  "type": "Feature",
  "properties": {
    "gn:admin1_code":"20.0",
    "gn:asciiname":"Nantun Xiang Nongyedian",
    "gn:country_code":"CN",
    "gn:dem":620,
    "gn:feature_class":"P",
    "gn:feature_code":"PPL",
    "gn:name":"Nantun Xiang Nongyedian",
    "gn:population":0,
    "gn:timezone":"Asia/Shanghai",
    "iso:country":"CN",
    "name:zho_x_preferred":[
        "\u5357\u5c6f\u4e61\u519c\u4e1a\u70b9"
    ],
    "wof:name":"Nantun Xiang Nongyedian",
    "wof:placetype":"locality"
},
  "geometry": {"coordinates":[119.7865,49.0968],"type":"Point"}
}