{
  "type": "Feature",
  "properties": {
    "gn:admin1_code":"19.0",
    "gn:asciiname":"Yaowobu",
    "gn:country_code":"CN",
    "gn:dem":43,
    "gn:feature_class":"P",
    "gn:feature_code":"PPL",
    "gn:name":"Yaowobu",
    "gn:population":0,
    "gn:timezone":"Asia/Shanghai",
    "iso:country":"CN",
    "name:und_x_variant":[
        "Yaowobao",
        "\u8170\u7a9d\u5821",
        "Yaowobu"
    ],
    "name:zho_x_preferred":[
        "\u8170\u7a9d\u5821"
    ],
    "wof:name":"Yaowobu",
    "wof:placetype":"locality"
},
  "geometry": {"coordinates":[122.54080999999999,42.00648],"type":"Point"}
}