{
  "type": "Feature",
  "properties": {
    "gn:admin1_code":"10",
    "gn:asciiname":"Xiyuanzhuang",
    "gn:country_code":"CN",
    "gn:dem":10,
    "gn:feature_class":"P",
    "gn:feature_code":"PPL",
    "gn:name":"Xiyuanzhuang",
    "gn:population":0,
    "gn:timezone":"Asia/Shanghai",
    "iso:country":"CN",
    "name:zho_x_preferred":[
        "\u897f\u8881\u5e84"
    ],
    "wof:name":"Xiyuanzhuang",
    "wof:placetype":"locality"
},
  "geometry": {"coordinates":[116.33,38.7447],"type":"Point"}
}