{
  "type": "Feature",
  "properties": {
    "gn:admin1_code":"15.0",
    "gn:asciiname":"Agushan",
    "gn:country_code":"CN",
    "gn:dem":2403,
    "gn:feature_class":"P",
    "gn:feature_code":"PPL",
    "gn:name":"Agushan",
    "gn:population":0,
    "gn:timezone":"Asia/Shanghai",
    "iso:country":"CN",
    "name:zho_x_preferred":[
        "\u963f\u59d1\u5c71"
    ],
    "wof:name":"Agushan",
    "wof:placetype":"locality"
},
  "geometry": {"coordinates":[103.727,35.1203],"type":"Point"}
}