{
  "type": "Feature",
  "properties": {
    "gn:admin1_code":"9.0",
    "gn:asciiname":"Pitiaowan",
    "gn:country_code":"CN",
    "gn:dem":132,
    "gn:feature_class":"P",
    "gn:feature_code":"PPL",
    "gn:name":"Pitiaowan",
    "gn:population":0,
    "gn:timezone":"Asia/Shanghai",
    "iso:country":"CN",
    "name:zho_x_preferred":[
        "\u76ae\u6761\u6e7e"
    ],
    "wof:name":"Pitiaowan",
    "wof:placetype":"locality"
},
  "geometry": {"coordinates":[113.70968000000001,32.89226],"type":"Point"}
}