{
  "type": "Feature",
  "properties": {
    "gn:admin1_code":"3.0",
    "gn:asciiname":"Yangyuan",
    "gn:country_code":"CN",
    "gn:dem":112,
    "gn:feature_class":"P",
    "gn:feature_code":"PPL",
    "gn:name":"Yangyuan",
    "gn:population":0,
    "gn:timezone":"Asia/Shanghai",
    "iso:country":"CN",
    "name:zho_x_preferred":[
        "\u6d0b\u6e90"
    ],
    "wof:name":"Yangyuan",
    "wof:placetype":"locality"
},
  "geometry": {"coordinates":[117.52603000000001,28.70321],"type":"Point"}
}