{
  "type": "Feature",
  "properties": {
    "gn:admin1_code":"19",
    "gn:asciiname":"Xialuhechaoxianzu",
    "gn:cc2":"CN",
    "gn:country_code":"CN",
    "gn:dem":154,
    "gn:feature_class":"P",
    "gn:feature_code":"PPL",
    "gn:name":"Xialuhechaoxianzu",
    "gn:population":0,
    "gn:timezone":"Asia/Shanghai",
    "iso:country":"CN",
    "name:und_x_variant":[
        "Xialuhe",
        "Hsia-lu-ho",
        "Xialuhechaoxianzu"
    ],
    "wof:name":"Xialuhechaoxianzu",
    "wof:placetype":"locality"
},
  "geometry": {"coordinates":[125.52806,40.89778],"type":"Point"}
}