{
  "type": "Feature",
  "properties": {
    "gn:admin1_code":"19.0",
    "gn:asciiname":"Beizhangzicun",
    "gn:country_code":"CN",
    "gn:dem":497,
    "gn:feature_class":"P",
    "gn:feature_code":"PPL",
    "gn:name":"Beizhangzicun",
    "gn:population":0,
    "gn:timezone":"Asia/Shanghai",
    "iso:country":"CN",
    "name:zho_x_preferred":[
        "\u5317\u6756\u5b50\u6751"
    ],
    "wof:name":"Beizhangzicun",
    "wof:placetype":"locality"
},
  "geometry": {"coordinates":[119.30441999999999,40.69393],"type":"Point"}
}