{
  "type": "Feature",
  "properties": {
    "gn:admin1_code":"32.0",
    "gn:asciiname":"Zhuangyuanbei",
    "gn:country_code":"CN",
    "gn:dem":2054,
    "gn:feature_class":"P",
    "gn:feature_code":"PPL",
    "gn:name":"Zhuangyuanbei",
    "gn:population":0,
    "gn:timezone":"Asia/Shanghai",
    "iso:country":"CN",
    "name:zho_x_preferred":[
        "\u72b6\u5143\u7891"
    ],
    "wof:name":"Zhuangyuanbei",
    "wof:placetype":"locality"
},
  "geometry": {"coordinates":[108.41907,31.6594],"type":"Point"}
}