{
  "type": "Feature",
  "properties": {
    "gn:admin1_code":"23.0",
    "gn:asciiname":"Guantianlou",
    "gn:country_code":"CN",
    "gn:dem":4,
    "gn:feature_class":"P",
    "gn:feature_code":"PPL",
    "gn:name":"Guantianlou",
    "gn:population":0,
    "gn:timezone":"Asia/Shanghai",
    "iso:country":"CN",
    "name:und_x_variant":[
        "\u5b98\u7530\u697c"
    ],
    "wof:name":"Guantianlou",
    "wof:placetype":"locality"
},
  "geometry": {"coordinates":[121.04437,30.89081],"type":"Point"}
}