{
  "type": "Feature",
  "properties": {
    "gn:admin1_code":"14.0",
    "gn:asciiname":"Zhongdu",
    "gn:country_code":"CN",
    "gn:dem":3084,
    "gn:feature_class":"P",
    "gn:feature_code":"PPL",
    "gn:name":"Zhongdu",
    "gn:population":0,
    "gn:timezone":"Asia/Urumqi",
    "iso:country":"CN",
    "name:ind_x_preferred":[
        "Zhongdu"
    ],
    "name:kor_x_preferred":[
        "\uc911\ub3c4"
    ],
    "name:rus_x_preferred":[
        "\u0427\u0436\u0443\u043d\u0434\u0443"
    ],
    "name:swe_x_preferred":[
        "Zhongdu"
    ],
    "name:ukr_x_preferred":[
        "\u0427\u0436\u0443\u043d\u0434\u0443"
    ],
    "name:wuu_x_preferred":[
        "\u91d1\u4e2d\u90fd"
    ],
    "name:zho_x_preferred":[
        "\u4ef2\u5835"
    ],
    "name:zho_x_variant":[
        "\u91d1\u4e2d\u90fd"
    ],
    "wof:name":"Zhongdu",
    "wof:placetype":"locality"
},
  "geometry": {"coordinates":[94.07563,29.23705],"type":"Point"}
}