{
  "type": "Feature",
  "properties": {
    "gn:admin1_code":"11.0",
    "gn:asciiname":"Zanzhu",
    "gn:country_code":"CN",
    "gn:dem":334,
    "gn:feature_class":"P",
    "gn:feature_code":"PPL",
    "gn:name":"Zanzhu",
    "gn:population":0,
    "gn:timezone":"Asia/Shanghai",
    "iso:country":"CN",
    "name:zho_x_preferred":[
        "\u54b1\u4f4f"
    ],
    "wof:name":"Zanzhu",
    "wof:placetype":"locality"
},
  "geometry": {"coordinates":[109.79101,29.00659000000001],"type":"Point"}
}