{
  "type": "Feature",
  "properties": {
    "gn:admin1_code":"7.0",
    "gn:asciiname":"Yangdaozhuang",
    "gn:country_code":"CN",
    "gn:dem":559,
    "gn:feature_class":"P",
    "gn:feature_code":"PPL",
    "gn:name":"Yangdaozhuang",
    "gn:population":0,
    "gn:timezone":"Asia/Shanghai",
    "iso:country":"CN",
    "name:zho_x_preferred":[
        "\u6d0b\u9053\u5e84"
    ],
    "wof:name":"Yangdaozhuang",
    "wof:placetype":"locality"
},
  "geometry": {"coordinates":[118.20004,27.92732],"type":"Point"}
}