{
  "type": "Feature",
  "properties": {
    "gn:admin1_code":"9.0",
    "gn:asciiname":"Houliuguan",
    "gn:country_code":"CN",
    "gn:dem":1181,
    "gn:feature_class":"P",
    "gn:feature_code":"PPL",
    "gn:name":"Houliuguan",
    "gn:population":0,
    "gn:timezone":"Asia/Shanghai",
    "iso:country":"CN",
    "name:zho_x_preferred":[
        "\u540e\u67f3\u5173"
    ],
    "wof:name":"Houliuguan",
    "wof:placetype":"locality"
},
  "geometry": {"coordinates":[110.99547,34.1757],"type":"Point"}
}