{
  "type": "Feature",
  "properties": {
    "gn:admin1_code":"3.0",
    "gn:asciiname":"Xiajiangfang",
    "gn:country_code":"CN",
    "gn:dem":435,
    "gn:feature_class":"P",
    "gn:feature_code":"PPL",
    "gn:name":"Xiajiangfang",
    "gn:population":0,
    "gn:timezone":"Asia/Shanghai",
    "iso:country":"CN",
    "name:und_x_variant":[
        "\u4e0b\u848b\u574a"
    ],
    "wof:name":"Xiajiangfang",
    "wof:placetype":"locality"
},
  "geometry": {"coordinates":[116.28668,27.20176],"type":"Point"}
}