{
  "type": "Feature",
  "properties": {
    "gn:admin1_code":"3.0",
    "gn:asciiname":"Mingshan",
    "gn:country_code":"CN",
    "gn:dem":29,
    "gn:feature_class":"P",
    "gn:feature_code":"PPLA4",
    "gn:name":"Mingshan",
    "gn:population":0,
    "gn:timezone":"Asia/Shanghai",
    "iso:country":"CN",
    "name:ceb_x_preferred":[
        "Mingshan"
    ],
    "name:deu_x_preferred":[
        "Mingshan"
    ],
    "name:fra_x_preferred":[
        "Mingshan"
    ],
    "name:nor_x_preferred":[
        "Mingshan"
    ],
    "name:rus_x_preferred":[
        "\u041c\u0438\u043d\u0448\u0430\u043d\u044c"
    ],
    "name:swe_x_preferred":[
        "Mingshan"
    ],
    "name:und_x_variant":[
        "\u9e23\u5c71",
        "Mingshan Xiang",
        "\u9e23\u5c71\u4e61"
    ],
    "wof:name":"Mingshan",
    "wof:placetype":"locality"
},
  "geometry": {"coordinates":[116.46359,29.42103],"type":"Point"}
}