{
  "type": "Feature",
  "properties": {
    "gn:admin1_code":"24.0",
    "gn:asciiname":"Changjiazui",
    "gn:country_code":"CN",
    "gn:dem":1430,
    "gn:feature_class":"P",
    "gn:feature_code":"PPL",
    "gn:name":"Changjiazui",
    "gn:population":0,
    "gn:timezone":"Asia/Shanghai",
    "iso:country":"CN",
    "name:zho_x_preferred":[
        "\u957f\u5bb6\u5480"
    ],
    "wof:name":"Changjiazui",
    "wof:placetype":"locality"
},
  "geometry": {"coordinates":[111.18711,37.87973],"type":"Point"}
}