{
  "type": "Feature",
  "properties": {
    "gn:admin1_code":"06",
    "gn:asciiname":"Houzihe",
    "gn:cc2":"CN",
    "gn:country_code":"CN",
    "gn:dem":2295,
    "gn:feature_class":"P",
    "gn:feature_code":"PPL",
    "gn:name":"Houzihe",
    "gn:population":0,
    "gn:timezone":"Asia/Shanghai",
    "iso:country":"CN",
    "name:und_x_variant":[
        "Hou-tzu-ho",
        "Houzihe"
    ],
    "wof:name":"Houzihe",
    "wof:placetype":"locality"
},
  "geometry": {"coordinates":[101.76721999999999,36.73778],"type":"Point"}
}