{
  "type": "Feature",
  "properties": {
    "gn:admin1_code":"14.0",
    "gn:asciiname":"Jiwengmage",
    "gn:country_code":"CN",
    "gn:dem":4094,
    "gn:feature_class":"P",
    "gn:feature_code":"PPL",
    "gn:name":"Jiwengmage",
    "gn:population":0,
    "gn:timezone":"Asia/Urumqi",
    "iso:country":"CN",
    "name:zho_x_preferred":[
        "\u673a\u7fc1\u739b\u683c"
    ],
    "wof:name":"Jiwengmage",
    "wof:placetype":"locality"
},
  "geometry": {"coordinates":[95.09753000000001,31.11012],"type":"Point"}
}