{
  "type": "Feature",
  "properties": {
    "gn:admin1_code":"16.0",
    "gn:asciiname":"Natianyan",
    "gn:country_code":"CN",
    "gn:dem":40,
    "gn:feature_class":"P",
    "gn:feature_code":"PPL",
    "gn:name":"Natianyan",
    "gn:population":0,
    "gn:timezone":"Asia/Shanghai",
    "iso:country":"CN",
    "name:zho_x_preferred":[
        "\u90a3\u5929\u5ca9"
    ],
    "wof:name":"Natianyan",
    "wof:placetype":"locality"
},
  "geometry": {"coordinates":[108.145,21.7175],"type":"Point"}
}