{
  "type": "Feature",
  "properties": {
    "gn:admin1_code":"26.0",
    "gn:asciiname":"Keping",
    "gn:country_code":"CN",
    "gn:dem":1280,
    "gn:feature_class":"P",
    "gn:feature_code":"PPL",
    "gn:name":"Keping",
    "gn:population":0,
    "gn:timezone":"Asia/Shanghai",
    "iso:country":"CN",
    "name:zho_x_preferred":[
        "\u79d1\u576a"
    ],
    "wof:name":"Keping",
    "wof:placetype":"locality"
},
  "geometry": {"coordinates":[108.74211,35.11267],"type":"Point"}
}