{
  "type": "Feature",
  "properties": {
    "gn:admin1_code":"9.0",
    "gn:asciiname":"Miaotaizi",
    "gn:country_code":"CN",
    "gn:dem":339,
    "gn:feature_class":"P",
    "gn:feature_code":"PPL",
    "gn:name":"Miaotaizi",
    "gn:population":0,
    "gn:timezone":"Asia/Shanghai",
    "iso:country":"CN",
    "name:zho_x_preferred":[
        "\u5e99\u53f0\u5b50"
    ],
    "wof:name":"Miaotaizi",
    "wof:placetype":"locality"
},
  "geometry": {"coordinates":[111.19127,33.2082],"type":"Point"}
}