{
  "type": "Feature",
  "properties": {
    "gn:admin1_code":"16.0",
    "gn:asciiname":"Duwu",
    "gn:country_code":"CN",
    "gn:dem":33,
    "gn:feature_class":"P",
    "gn:feature_code":"PPL",
    "gn:name":"Duwu",
    "gn:population":0,
    "gn:timezone":"Asia/Shanghai",
    "iso:country":"CN",
    "name:zho_x_preferred":[
        "\u72ec\u5c4b"
    ],
    "wof:name":"Duwu",
    "wof:placetype":"locality"
},
  "geometry": {"coordinates":[110.36799999999999,23.613],"type":"Point"}
}