{
  "type": "Feature",
  "properties": {
    "gn:admin1_code":"16.0",
    "gn:asciiname":"Poping",
    "gn:country_code":"CN",
    "gn:dem":238,
    "gn:feature_class":"P",
    "gn:feature_code":"PPL",
    "gn:name":"Poping",
    "gn:population":0,
    "gn:timezone":"Asia/Shanghai",
    "iso:country":"CN",
    "name:zho_x_preferred":[
        "\u5761\u576a"
    ],
    "wof:name":"Poping",
    "wof:placetype":"locality"
},
  "geometry": {"coordinates":[110.438,24.1569],"type":"Point"}
}