{
  "type": "Feature",
  "properties": {
    "gn:admin1_code":"4.0",
    "gn:asciiname":"Pailou",
    "gn:country_code":"CN",
    "gn:dem":2,
    "gn:feature_class":"P",
    "gn:feature_code":"PPL",
    "gn:name":"Pailou",
    "gn:population":0,
    "gn:timezone":"Asia/Shanghai",
    "iso:country":"CN",
    "name:zho_x_preferred":[
        "Pailou"
    ],
    "name:zho_x_variant":[
        "\u724c\u697c"
    ],
    "wof:name":"Pailou",
    "wof:placetype":"locality"
},
  "geometry": {"coordinates":[119.49839,33.25513],"type":"Point"}
}