{
  "type": "Feature",
  "properties": {
    "gn:admin1_code":"29.0",
    "gn:asciiname":"Zhongyangliu",
    "gn:country_code":"CN",
    "gn:dem":2398,
    "gn:feature_class":"P",
    "gn:feature_code":"PPL",
    "gn:name":"Zhongyangliu",
    "gn:population":0,
    "gn:timezone":"Asia/Shanghai",
    "iso:country":"CN",
    "name:zho_x_preferred":[
        "\u4e2d\u6768\u67f3"
    ],
    "wof:name":"Zhongyangliu",
    "wof:placetype":"locality"
},
  "geometry": {"coordinates":[100.42400000000001,27.5282],"type":"Point"}
}