{
  "type": "Feature",
  "properties": {
    "gn:admin1_code":"3.0",
    "gn:asciiname":"Yongyang",
    "gn:cc2":"CN",
    "gn:country_code":"CN",
    "gn:dem":60,
    "gn:feature_class":"P",
    "gn:feature_code":"PPL",
    "gn:name":"Yongyang",
    "gn:population":0,
    "gn:timezone":"Asia/Shanghai",
    "iso:country":"CN",
    "name:und_x_variant":[
        "Yung-yang",
        "Yung-yang-chen",
        "Yongyang"
    ],
    "wof:name":"Yongyang",
    "wof:placetype":"locality"
},
  "geometry": {"coordinates":[114.73333,26.95],"type":"Point"}
}