{
  "type": "Feature",
  "properties": {
    "gn:admin1_code":"9.0",
    "gn:asciiname":"Dasancha",
    "gn:country_code":"CN",
    "gn:dem":1556,
    "gn:feature_class":"P",
    "gn:feature_code":"PPL",
    "gn:name":"Dasancha",
    "gn:population":0,
    "gn:timezone":"Asia/Shanghai",
    "iso:country":"CN",
    "name:zho_x_preferred":[
        "\u5927\u4e09\u5c94"
    ],
    "wof:name":"Dasancha",
    "wof:placetype":"locality"
},
  "geometry": {"coordinates":[111.48860999999999,33.73947],"type":"Point"}
}