{
  "type": "Feature",
  "properties": {
    "gn:admin1_code":"8.0",
    "gn:asciiname":"Fudecun",
    "gn:country_code":"CN",
    "gn:dem":62,
    "gn:feature_class":"P",
    "gn:feature_code":"PPL",
    "gn:name":"Fudecun",
    "gn:population":0,
    "gn:timezone":"Asia/Shanghai",
    "iso:country":"CN",
    "name:zho_x_preferred":[
        "\u798f\u5fb7\u6751"
    ],
    "wof:name":"Fudecun",
    "wof:placetype":"locality"
},
  "geometry": {"coordinates":[132.07623000000001,47.19815],"type":"Point"}
}