{
  "type": "Feature",
  "properties": {
    "gn:admin1_code":"32.0",
    "gn:asciiname":"Eluoge",
    "gn:country_code":"CN",
    "gn:dem":2856,
    "gn:feature_class":"P",
    "gn:feature_code":"PPL",
    "gn:name":"Eluoge",
    "gn:population":0,
    "gn:timezone":"Asia/Shanghai",
    "iso:country":"CN",
    "name:zho_x_preferred":[
        "\u4fc4\u7f57\u5404"
    ],
    "wof:name":"Eluoge",
    "wof:placetype":"locality"
},
  "geometry": {"coordinates":[103.11048,32.0929],"type":"Point"}
}