{
  "type": "Feature",
  "properties": {
    "gn:admin1_code":"29.0",
    "gn:asciiname":"Rongjia Xinzhai",
    "gn:country_code":"CN",
    "gn:dem":1650,
    "gn:feature_class":"P",
    "gn:feature_code":"PPL",
    "gn:name":"Rongjia Xinzhai",
    "gn:population":0,
    "gn:timezone":"Asia/Shanghai",
    "iso:country":"CN",
    "name:zho_x_preferred":[
        "\u8363\u5bb6\u65b0\u5be8"
    ],
    "wof:name":"Rongjia Xinzhai",
    "wof:placetype":"locality"
},
  "geometry": {"coordinates":[98.1461,25.0024],"type":"Point"}
}