{
  "type": "Feature",
  "properties": {
    "gn:admin1_code":"13.0",
    "gn:asciiname":"Youkuribuliman",
    "gn:country_code":"CN",
    "gn:dem":1215,
    "gn:feature_class":"P",
    "gn:feature_code":"PPL",
    "gn:name":"Youkuribuliman",
    "gn:population":0,
    "gn:timezone":"Asia/Shanghai",
    "iso:country":"CN",
    "name:zho_x_preferred":[
        "\u5c24\u5e93\u65e5\u5e03\u529b\u66fc"
    ],
    "wof:name":"Youkuribuliman",
    "wof:placetype":"locality"
},
  "geometry": {"coordinates":[76.67495,39.18081],"type":"Point"}
}