{
  "type": "Feature",
  "properties": {
    "gn:admin1_code":"6.0",
    "gn:asciiname":"Jiaru",
    "gn:country_code":"CN",
    "gn:dem":1866,
    "gn:feature_class":"P",
    "gn:feature_code":"PPL",
    "gn:name":"Jiaru",
    "gn:population":0,
    "gn:timezone":"Asia/Shanghai",
    "iso:country":"CN",
    "name:und_x_variant":[
        "\u52a0\u5165"
    ],
    "wof:name":"Jiaru",
    "wof:placetype":"locality"
},
  "geometry": {"coordinates":[102.49048000000001,35.85819],"type":"Point"}
}