{
  "type": "Feature",
  "properties": {
    "gn:admin1_code":"02",
    "gn:asciiname":"Shamen",
    "gn:country_code":"CN",
    "gn:dem":10,
    "gn:feature_class":"P",
    "gn:feature_code":"PPLA4",
    "gn:name":"Shamen",
    "gn:population":0,
    "gn:timezone":"Asia/Shanghai",
    "iso:country":"CN",
    "name:und_x_variant":[
        "Shamen Zhen"
    ],
    "name:zho_x_preferred":[
        "\u6c99\u95e8"
    ],
    "name:zho_x_variant":[
        "\u6c99\u95e8\u9547"
    ],
    "wof:name":"Shamen",
    "wof:placetype":"locality"
},
  "geometry": {"coordinates":[121.37756,28.24177],"type":"Point"}
}