{
  "type": "Feature",
  "properties": {
    "gn:admin1_code":"32.0",
    "gn:asciiname":"Biyan",
    "gn:country_code":"CN",
    "gn:dem":394,
    "gn:feature_class":"P",
    "gn:feature_code":"PPL",
    "gn:name":"Biyan",
    "gn:population":0,
    "gn:timezone":"Asia/Shanghai",
    "iso:country":"CN",
    "name:zho_x_preferred":[
        "\u58c1\u989c"
    ],
    "wof:name":"Biyan",
    "wof:placetype":"locality"
},
  "geometry": {"coordinates":[107.011,30.9843],"type":"Point"}
}