{
  "type": "Feature",
  "properties": {
    "gn:admin1_code":"26.0",
    "gn:asciiname":"Xiaoyazi",
    "gn:country_code":"CN",
    "gn:dem":1076,
    "gn:feature_class":"P",
    "gn:feature_code":"PPL",
    "gn:name":"Xiaoyazi",
    "gn:population":0,
    "gn:timezone":"Asia/Shanghai",
    "iso:country":"CN",
    "name:zho_x_preferred":[
        "\u5c0f\u57ad\u5b50"
    ],
    "wof:name":"Xiaoyazi",
    "wof:placetype":"locality"
},
  "geometry": {"coordinates":[108.49339999999999,32.78279000000001],"type":"Point"}
}