{
  "type": "Feature",
  "properties": {
    "gn:admin1_code":"29.0",
    "gn:asciiname":"Mianqiancun",
    "gn:country_code":"CN",
    "gn:dem":1556,
    "gn:feature_class":"P",
    "gn:feature_code":"PPL",
    "gn:name":"Mianqiancun",
    "gn:population":0,
    "gn:timezone":"Asia/Shanghai",
    "iso:country":"CN",
    "name:zho_x_preferred":[
        "\u9762\u524d\u6751"
    ],
    "wof:name":"Mianqiancun",
    "wof:placetype":"locality"
},
  "geometry": {"coordinates":[101.943,25.9661],"type":"Point"}
}