{
  "type": "Feature",
  "properties": {
    "gn:admin1_code":"2.0",
    "gn:asciiname":"Yeming",
    "gn:country_code":"CN",
    "gn:dem":9,
    "gn:feature_class":"P",
    "gn:feature_code":"PPL",
    "gn:name":"Yeming",
    "gn:population":0,
    "gn:timezone":"Asia/Shanghai",
    "iso:country":"CN",
    "name:und_x_variant":[
        "\u591c\u660e"
    ],
    "wof:name":"Yeming",
    "wof:placetype":"locality"
},
  "geometry": {"coordinates":[120.31715,30.57767],"type":"Point"}
}