{
  "type": "Feature",
  "properties": {
    "gn:admin1_code":"14.0",
    "gn:asciiname":"Rongyi",
    "gn:country_code":"CN",
    "gn:dem":3913,
    "gn:feature_class":"P",
    "gn:feature_code":"PPL",
    "gn:name":"Rongyi",
    "gn:population":0,
    "gn:timezone":"Asia/Urumqi",
    "iso:country":"CN",
    "name:zho_x_preferred":[
        "\u5bb9\u4f9d"
    ],
    "wof:name":"Rongyi",
    "wof:placetype":"locality"
},
  "geometry": {"coordinates":[95.52909,30.98473],"type":"Point"}
}