{
  "type": "Feature",
  "properties": {
    "gn:country":"CN",
    "gn:fcode":"ADM3",
    "gn:pop":1313222,
    "iso:country":"CN",
    "name:unk_x_variant":[
        "Yangpu District"
    ],
    "name:zho_x_preferred":[
        "\u6768\u6d66\u533a"
    ],
    "name:zho_x_variant":[
        "\u6768\u6d66"
    ],
    "qs:name":"Yangpu Qu",
    "qs:photos_9r":0,
    "qs:photos_sr":0,
    "qs:pop_sr":"12",
    "wd:wordcount":1098,
    "wof:name":"Yangpu Qu",
    "wof:placetype":"localadmin",
    "wof:population":1313222
},
  "geometry": {"coordinates":[121.50579999999999,31.29248],"type":"Point"}
}