{
  "type": "Feature",
  "properties": {
    "gn:country":"CN",
    "gn:fcode":"ADM3",
    "gn:population":1313222,
    "iso:country":"CN",
    "name:cym_x_preferred":[
        "Ardal Yangpu"
    ],
    "name:deu_x_preferred":[
        "Yangpu"
    ],
    "name:eng_x_preferred":[
        "Yangpu District"
    ],
    "name:eus_x_preferred":[
        "Yangpu Barrutia"
    ],
    "name:gan_x_preferred":[
        "\u6768\u6d66\u533a"
    ],
    "name:heb_x_preferred":[
        "\u05e9\u05d0\u05e0\u05d2\u05d7\u05d0\u05d9/\u05d9\u05d0\u05e0\u05d2\u05e4\u05d5"
    ],
    "name:jpn_x_preferred":[
        "\u694a\u6d66\u533a"
    ],
    "name:kor_x_preferred":[
        "\uc591\ud478\uad6c"
    ],
    "name:mkd_x_preferred":[
        "\u0408\u0430\u043d\u0433\u043f\u0443"
    ],
    "name:nan_x_preferred":[
        "I\u00f4ng-ph\u00f3\u0358-khu"
    ],
    "name:nld_x_preferred":[
        "Yangpu"
    ],
    "name:nob_x_preferred":[
        "Yangpu"
    ],
    "name:ron_x_preferred":[
        "Districtul Yangpu"
    ],
    "name:rus_x_preferred":[
        "\u042f\u043d\u043f\u0443"
    ],
    "name:spa_x_preferred":[
        "Yangpu"
    ],
    "name:swe_x_preferred":[
        "Yangpu"
    ],
    "name:tur_x_preferred":[
        "Yangpu"
    ],
    "name:ukr_x_preferred":[
        "\u0420\u0430\u0439\u043e\u043d \u042f\u043d\u043f\u0443"
    ],
    "name:urd_x_preferred":[
        "\u06cc\u0646\u06af\u067e\u0648 \u0636\u0644\u0639"
    ],
    "name:vie_x_preferred":[
        "D\u01b0\u01a1ng Ph\u1ed1"
    ],
    "name:wuu_x_preferred":[
        "\u6768\u6d66\u533a"
    ],
    "name:yue_x_preferred":[
        "\u694a\u6d66\u5340"
    ],
    "name:zho_x_preferred":[
        "\u6768\u6d66\u533a"
    ],
    "name:zho_x_variant":[
        "\u6768\u6d66"
    ],
    "qs:name":"Yangpu Qu",
    "qs:photos_9r":0,
    "qs:photos_sr":0,
    "qs:pop_sr":"12",
    "wd:wordcount":1098,
    "wof:name":"Yangpu Qu",
    "wof:placetype":"localadmin",
    "wof:population":1313222
},
  "geometry": {"coordinates":[121.50579999999999,31.29248],"type":"Point"}
}