{
  "type": "Feature",
  "properties": {
    "gn:admin1_code":"20.0",
    "gn:asciiname":"Shijiuhao",
    "gn:country_code":"CN",
    "gn:dem":996,
    "gn:feature_class":"P",
    "gn:feature_code":"PPL",
    "gn:name":"Shijiuhao",
    "gn:population":0,
    "gn:timezone":"Asia/Shanghai",
    "iso:country":"CN",
    "name:zho_x_preferred":[
        "\u5341\u4e5d\u53f7"
    ],
    "wof:name":"Shijiuhao",
    "wof:placetype":"locality"
},
  "geometry": {"coordinates":[99.96127,41.65835],"type":"Point"}
}