{
  "type": "Feature",
  "properties": {
    "gn:admin1_code":"3.0",
    "gn:asciiname":"Datangcun",
    "gn:country_code":"CN",
    "gn:dem":139,
    "gn:feature_class":"P",
    "gn:feature_code":"PPL",
    "gn:name":"Datangcun",
    "gn:population":0,
    "gn:timezone":"Asia/Shanghai",
    "iso:country":"CN",
    "name:und_x_variant":[
        "\u5927\u5858\u6751"
    ],
    "wof:name":"Datangcun",
    "wof:placetype":"locality"
},
  "geometry": {"coordinates":[116.33241,26.83058],"type":"Point"}
}