{
  "type": "Feature",
  "properties": {
    "gn:admin1_code":"3.0",
    "gn:asciiname":"Guankoucun",
    "gn:country_code":"CN",
    "gn:dem":19,
    "gn:feature_class":"P",
    "gn:feature_code":"PPL",
    "gn:name":"Guankoucun",
    "gn:population":0,
    "gn:timezone":"Asia/Shanghai",
    "iso:country":"CN",
    "name:und_x_variant":[
        "\u5173\u53e3\u6751"
    ],
    "wof:name":"Guankoucun",
    "wof:placetype":"locality"
},
  "geometry": {"coordinates":[115.99516,28.47823],"type":"Point"}
}