{
  "type": "Feature",
  "properties": {
    "gn:admin1_code":"2.0",
    "gn:asciiname":"Bicun",
    "gn:country_code":"CN",
    "gn:dem":97,
    "gn:feature_class":"P",
    "gn:feature_code":"PPL",
    "gn:name":"Bicun",
    "gn:population":0,
    "gn:timezone":"Asia/Shanghai",
    "iso:country":"CN",
    "name:zho_x_preferred":[
        "\u859c\u6751"
    ],
    "wof:name":"Bicun",
    "wof:placetype":"locality"
},
  "geometry": {"coordinates":[120.05218000000001,29.14346],"type":"Point"}
}