{
  "type": "Feature",
  "properties": {
    "gn:admin1_code":"07",
    "gn:asciiname":"Shouge",
    "gn:country_code":"CN",
    "gn:dem":1073,
    "gn:feature_class":"P",
    "gn:feature_code":"PPL",
    "gn:name":"Shouge",
    "gn:population":0,
    "gn:timezone":"Asia/Shanghai",
    "iso:country":"CN",
    "name:zho_x_preferred":[
        "\u5bff\u683c"
    ],
    "wof:name":"Shouge",
    "wof:placetype":"locality"
},
  "geometry": {"coordinates":[118.14506000000002,25.79842],"type":"Point"}
}