{
  "type": "Feature",
  "properties": {
    "gn:admin1_code":"16",
    "gn:asciiname":"Xiaojiangwei",
    "gn:country_code":"CN",
    "gn:dem":1050,
    "gn:feature_class":"P",
    "gn:feature_code":"PPL",
    "gn:name":"Xiaojiangwei",
    "gn:population":0,
    "gn:timezone":"Asia/Shanghai",
    "iso:country":"CN",
    "name:zho_x_preferred":[
        "\u5c0f\u6c5f\u5c3e"
    ],
    "wof:name":"Xiaojiangwei",
    "wof:placetype":"locality"
},
  "geometry": {"coordinates":[109.97199999999999,25.4611],"type":"Point"}
}