{
  "type": "Feature",
  "properties": {
    "gn:admin1_code":"06",
    "gn:asciiname":"Gemingcheng",
    "gn:cc2":"CN",
    "gn:country_code":"CN",
    "gn:dem":1912,
    "gn:feature_class":"P",
    "gn:feature_code":"PPL",
    "gn:name":"Gemingcheng",
    "gn:population":0,
    "gn:timezone":"Asia/Shanghai",
    "iso:country":"CN",
    "name:und_x_variant":[
        "Ko-ming-ch\u2019eng",
        "Gemingcheng"
    ],
    "wof:name":"Gemingcheng",
    "wof:placetype":"locality"
},
  "geometry": {"coordinates":[102.62111,36.42556],"type":"Point"}
}