{
  "type": "Feature",
  "properties": {
    "gn:admin1_code":"02",
    "gn:asciiname":"Jiaoshanxia",
    "gn:country_code":"CN",
    "gn:dem":2,
    "gn:feature_class":"P",
    "gn:feature_code":"PPL",
    "gn:name":"Jiaoshanxia",
    "gn:population":0,
    "gn:timezone":"Asia/Shanghai",
    "iso:country":"CN",
    "name:und_x_variant":[
        "Chiao-shan-hsia",
        "Jiaoshanxia"
    ],
    "name:zho_x_preferred":[
        "\u7126\u5c71\u4e0b"
    ],
    "wof:name":"Jiaoshanxia",
    "wof:placetype":"locality"
},
  "geometry": {"coordinates":[121.9734,29.8349],"type":"Point"}
}