{
  "type": "Feature",
  "properties": {
    "gn:admin1_code":"3",
    "gn:asciiname":"Gaoyi",
    "gn:country_code":"CN",
    "gn:dem":168,
    "gn:feature_class":"P",
    "gn:feature_code":"PPL",
    "gn:name":"Gaoyi",
    "gn:population":0,
    "gn:timezone":"Asia/Shanghai",
    "iso:country":"CN",
    "name:zho_x_preferred":[
        "\u9ad8\u501a"
    ],
    "wof:name":"Gaoyi",
    "wof:placetype":"locality"
},
  "geometry": {"coordinates":[114.36002000000001,26.36857],"type":"Point"}
}