{
  "type": "Feature",
  "properties": {
    "gn:admin1_code":"30.0",
    "gn:asciiname":"Yankou",
    "gn:country_code":"CN",
    "gn:dem":82,
    "gn:feature_class":"P",
    "gn:feature_code":"PPL",
    "gn:name":"Yankou",
    "gn:population":0,
    "gn:timezone":"Asia/Shanghai",
    "iso:country":"CN",
    "name:zho_x_preferred":[
        "Yankou"
    ],
    "name:zho_x_variant":[
        "\u5ca9\u53e3"
    ],
    "wof:name":"Yankou",
    "wof:placetype":"locality"
},
  "geometry": {"coordinates":[112.60917000000001,24.34556],"type":"Point"}
}