{
  "type": "Feature",
  "properties": {
    "gn:admin1_code":"15.0",
    "gn:asciiname":"Miaotai",
    "gn:country_code":"CN",
    "gn:dem":2027,
    "gn:feature_class":"P",
    "gn:feature_code":"PPL",
    "gn:name":"Miaotai",
    "gn:population":0,
    "gn:timezone":"Asia/Shanghai",
    "iso:country":"CN",
    "name:zho_x_preferred":[
        "\u5e99\u53f0"
    ],
    "wof:name":"Miaotai",
    "wof:placetype":"locality"
},
  "geometry": {"coordinates":[103.113,36.175],"type":"Point"}
}