{
  "type": "Feature",
  "properties": {
    "gn:admin1_code":"10",
    "gn:asciiname":"Nanzhuangwang",
    "gn:country_code":"CN",
    "gn:dem":1103,
    "gn:feature_class":"P",
    "gn:feature_code":"PPL",
    "gn:name":"Nanzhuangwang",
    "gn:population":0,
    "gn:timezone":"Asia/Shanghai",
    "iso:country":"CN",
    "name:und_x_variant":[
        "\u5357\u5e84\u65fa"
    ],
    "wof:name":"Nanzhuangwang",
    "wof:placetype":"locality"
},
  "geometry": {"coordinates":[113.92559,39.04266],"type":"Point"}
}