{
  "type": "Feature",
  "properties": {
    "gn:admin1_code":"02",
    "gn:asciiname":"Chengxi'aocun",
    "gn:country_code":"CN",
    "gn:dem":127,
    "gn:feature_class":"P",
    "gn:feature_code":"PPL",
    "gn:name":"Chengxi\u2019aocun",
    "gn:population":0,
    "gn:timezone":"Asia/Shanghai",
    "iso:country":"CN",
    "name:und_x_variant":[
        "Ch\u2019eng-hsi-ao-ts\u2019un",
        "\u57ce\u897f\u5c99",
        "Chengxi\u2019aocun"
    ],
    "name:zho_x_preferred":[
        "Chengxi\u2019ao"
    ],
    "name:zho_x_variant":[
        "\u57ce\u897f\u5c99",
        "\u57ce\u897f\u5c99\u6751"
    ],
    "wof:name":"Chengxi'aocun",
    "wof:placetype":"locality"
},
  "geometry": {"coordinates":[121.36188,29.63788],"type":"Point"}
}