{
  "type": "Feature",
  "properties": {
    "gn:admin1_code":"9.0",
    "gn:asciiname":"Jiabunan",
    "gn:country_code":"CN",
    "gn:dem":106,
    "gn:feature_class":"P",
    "gn:feature_code":"PPL",
    "gn:name":"Jiabunan",
    "gn:population":0,
    "gn:timezone":"Asia/Shanghai",
    "iso:country":"CN",
    "name:zho_x_preferred":[
        "\u9a7e\u90e8\u5357"
    ],
    "wof:name":"Jiabunan",
    "wof:placetype":"locality"
},
  "geometry": {"coordinates":[113.24627,34.98795],"type":"Point"}
}