{
  "type": "Feature",
  "properties": {
    "gn:admin1_code":"16.0",
    "gn:asciiname":"Zhouzhengchongwei",
    "gn:country_code":"CN",
    "gn:dem":71,
    "gn:feature_class":"P",
    "gn:feature_code":"PPL",
    "gn:name":"Zhouzhengchongwei",
    "gn:population":0,
    "gn:timezone":"Asia/Shanghai",
    "iso:country":"CN",
    "name:zho_x_preferred":[
        "\u5468\u6b63\u51b2\u5c3e"
    ],
    "wof:name":"Zhouzhengchongwei",
    "wof:placetype":"locality"
},
  "geometry": {"coordinates":[110.17700000000001,22.0177],"type":"Point"}
}