{
  "type": "Feature",
  "properties": {
    "gn:admin1_code":"19.0",
    "gn:asciiname":"Lishifang",
    "gn:country_code":"CN",
    "gn:dem":59,
    "gn:feature_class":"P",
    "gn:feature_code":"PPL",
    "gn:name":"Lishifang",
    "gn:population":0,
    "gn:timezone":"Asia/Shanghai",
    "iso:country":"CN",
    "name:zho_x_preferred":[
        "\u674e\u6c0f\u623f"
    ],
    "wof:name":"Lishifang",
    "wof:placetype":"locality"
},
  "geometry": {"coordinates":[122.96908999999999,41.00106],"type":"Point"}
}