{
  "type": "Feature",
  "properties": {
    "gn:admin1_code":"1.0",
    "gn:asciiname":"Yuhuicun",
    "gn:country_code":"CN",
    "gn:dem":22,
    "gn:feature_class":"P",
    "gn:feature_code":"PPL",
    "gn:name":"Yuhuicun",
    "gn:population":0,
    "gn:timezone":"Asia/Shanghai",
    "iso:country":"CN",
    "name:zho_x_preferred":[
        "\u79b9\u4f1a\u6751"
    ],
    "wof:name":"Yuhuicun",
    "wof:placetype":"locality"
},
  "geometry": {"coordinates":[117.19607000000001,32.8931],"type":"Point"}
}