{
  "type": "Feature",
  "properties": {
    "gn:admin1_code":"21.0",
    "gn:asciiname":"Shangwan Wanzi",
    "gn:country_code":"CN",
    "gn:dem":1698,
    "gn:feature_class":"P",
    "gn:feature_code":"PPL",
    "gn:name":"Shangwan Wanzi",
    "gn:population":0,
    "gn:timezone":"Asia/Shanghai",
    "iso:country":"CN",
    "name:zho_x_preferred":[
        "\u4e0a\u6e7e\u6e7e\u5b50"
    ],
    "wof:name":"Shangwan Wanzi",
    "wof:placetype":"locality"
},
  "geometry": {"coordinates":[105.934,36.2332],"type":"Point"}
}