{
  "type": "Feature",
  "properties": {
    "gn:admin1_code":"8.0",
    "gn:asciiname":"Bingjiajie",
    "gn:country_code":"CN",
    "gn:dem":250,
    "gn:feature_class":"P",
    "gn:feature_code":"PPL",
    "gn:name":"Bingjiajie",
    "gn:population":0,
    "gn:timezone":"Asia/Shanghai",
    "iso:country":"CN",
    "name:zho_x_preferred":[
        "\u79c9\u5bb6\u8857"
    ],
    "wof:name":"Bingjiajie",
    "wof:placetype":"locality"
},
  "geometry": {"coordinates":[122.77481,47.60305],"type":"Point"}
}