{
  "type": "Feature",
  "properties": {
    "gn:admin1_code":"16.0",
    "gn:asciiname":"Jiuguitang",
    "gn:country_code":"CN",
    "gn:dem":238,
    "gn:feature_class":"P",
    "gn:feature_code":"PPL",
    "gn:name":"Jiuguitang",
    "gn:population":0,
    "gn:timezone":"Asia/Shanghai",
    "iso:country":"CN",
    "name:zho_x_preferred":[
        "\u4e5d\u6842\u5858"
    ],
    "wof:name":"Jiuguitang",
    "wof:placetype":"locality"
},
  "geometry": {"coordinates":[111.413,23.0667],"type":"Point"}
}