{
  "type": "Feature",
  "properties": {
    "gn:admin1_code":"33.0",
    "gn:asciiname":"Tanzipo",
    "gn:country_code":"CN",
    "gn:dem":259,
    "gn:feature_class":"P",
    "gn:feature_code":"PPL",
    "gn:name":"Tanzipo",
    "gn:population":0,
    "gn:timezone":"Asia/Shanghai",
    "iso:country":"CN",
    "name:zho_x_preferred":[
        "\u575b\u5b50\u5761"
    ],
    "wof:name":"Tanzipo",
    "wof:placetype":"locality"
},
  "geometry": {"coordinates":[105.93843,29.19193],"type":"Point"}
}