{
  "type": "Feature",
  "properties": {
    "gn:admin1_code":"8.0",
    "gn:asciiname":"Waisandaogou",
    "gn:country_code":"CN",
    "gn:dem":128,
    "gn:feature_class":"P",
    "gn:feature_code":"PPL",
    "gn:name":"Waisandaogou",
    "gn:population":0,
    "gn:timezone":"Asia/Shanghai",
    "iso:country":"CN",
    "name:und_x_variant":[
        "\u5916\u4e09\u9053\u6c9f"
    ],
    "wof:name":"Waisandaogou",
    "wof:placetype":"locality"
},
  "geometry": {"coordinates":[127.49169999999999,50.06224],"type":"Point"}
}