{
  "type": "Feature",
  "properties": {
    "gn:admin1_code":"24.0",
    "gn:asciiname":"Yingtou",
    "gn:country_code":"CN",
    "gn:dem":1336,
    "gn:feature_class":"P",
    "gn:feature_code":"PPL",
    "gn:name":"Yingtou",
    "gn:population":0,
    "gn:timezone":"Asia/Shanghai",
    "iso:country":"CN",
    "name:und_x_variant":[
        "Ying-t\u2019ao-chen",
        "Yingtou",
        "\u8425\u5934",
        "Yingtou Zhen",
        "\u8425\u5934\u9547"
    ],
    "wof:name":"Yingtou",
    "wof:placetype":"locality"
},
  "geometry": {"coordinates":[111.84943,39.26373],"type":"Point"}
}