{
  "type": "Feature",
  "properties": {
    "gn:admin1_code":"32.0",
    "gn:asciiname":"Bugu",
    "gn:country_code":"CN",
    "gn:dem":2404,
    "gn:feature_class":"P",
    "gn:feature_code":"PPL",
    "gn:name":"Bugu",
    "gn:population":0,
    "gn:timezone":"Asia/Shanghai",
    "iso:country":"CN",
    "name:zho_x_preferred":[
        "\u5e03\u8c37"
    ],
    "wof:name":"Bugu",
    "wof:placetype":"locality"
},
  "geometry": {"coordinates":[101.79000000000001,30.8976],"type":"Point"}
}