{
  "type": "Feature",
  "properties": {
    "gn:admin1_code":"3",
    "gn:asciiname":"Tonglin",
    "gn:country_code":"CN",
    "gn:dem":85,
    "gn:feature_class":"P",
    "gn:feature_code":"PPLA4",
    "gn:name":"Tonglin",
    "gn:population":0,
    "gn:timezone":"Asia/Shanghai",
    "iso:country":"CN",
    "name:und_x_variant":[
        "\u6850\u6797",
        "Tonglin Xiang",
        "\u6850\u6797\u4e61"
    ],
    "wof:name":"Tonglin",
    "wof:placetype":"locality"
},
  "geometry": {"coordinates":[115.4188,27.51229],"type":"Point"}
}