{
  "type": "Feature",
  "properties": {
    "gn:admin1_code":"26.0",
    "gn:asciiname":"Zhandou",
    "gn:country_code":"CN",
    "gn:dem":540,
    "gn:feature_class":"P",
    "gn:feature_code":"PPL",
    "gn:name":"Zhandou",
    "gn:population":0,
    "gn:timezone":"Asia/Shanghai",
    "iso:country":"CN",
    "name:und_x_variant":[
        "\u6218\u6597"
    ],
    "wof:name":"Zhandou",
    "wof:placetype":"locality"
},
  "geometry": {"coordinates":[106.84143,33.00738],"type":"Point"}
}