{
  "type": "Feature",
  "properties": {
    "gn:admin1_code":"2.0",
    "gn:asciiname":"Fengxiaoling",
    "gn:country_code":"CN",
    "gn:dem":170,
    "gn:feature_class":"P",
    "gn:feature_code":"PPL",
    "gn:name":"Fengxiaoling",
    "gn:population":0,
    "gn:timezone":"Asia/Shanghai",
    "iso:country":"CN",
    "name:und_x_variant":[
        "\u98ce\u7b11\u5cad"
    ],
    "wof:name":"Fengxiaoling",
    "wof:placetype":"locality"
},
  "geometry": {"coordinates":[119.76327000000001,30.37287],"type":"Point"}
}