{
  "type": "Feature",
  "properties": {
    "gn:admin1_code":"24",
    "gn:asciiname":"Majiadongling",
    "gn:cc2":"CN",
    "gn:country_code":"CN",
    "gn:dem":1128,
    "gn:feature_class":"P",
    "gn:feature_code":"PPL",
    "gn:name":"Majiadongling",
    "gn:population":0,
    "gn:timezone":"Asia/Shanghai",
    "iso:country":"CN",
    "name:und_x_variant":[
        "Ma-chia-tung-ling",
        "Majiadongling"
    ],
    "wof:name":"Majiadongling",
    "wof:placetype":"locality"
},
  "geometry": {"coordinates":[112.83333,36.65],"type":"Point"}
}