{
  "type": "Feature",
  "properties": {
    "gn:admin1_code":"30.0",
    "gn:asciiname":"Runangeng",
    "gn:country_code":"CN",
    "gn:dem":592,
    "gn:feature_class":"P",
    "gn:feature_code":"PPL",
    "gn:name":"Runangeng",
    "gn:population":0,
    "gn:timezone":"Asia/Shanghai",
    "iso:country":"CN",
    "name:zho_x_preferred":[
        "Runangeng"
    ],
    "name:zho_x_variant":[
        "\u5982\u5357\u57c2"
    ],
    "wof:name":"Runangeng",
    "wof:placetype":"locality"
},
  "geometry": {"coordinates":[113.25811000000002,24.9809],"type":"Point"}
}