{
  "type": "Feature",
  "properties": {
    "gn:admin1_code":"30.0",
    "gn:asciiname":"Yuetan",
    "gn:country_code":"CN",
    "gn:dem":142,
    "gn:feature_class":"P",
    "gn:feature_code":"PPL",
    "gn:name":"Yuetan",
    "gn:population":0,
    "gn:timezone":"Asia/Shanghai",
    "iso:country":"CN",
    "name:zho_x_preferred":[
        "\u5cb3\u6f6d"
    ],
    "wof:name":"Yuetan",
    "wof:placetype":"locality"
},
  "geometry": {"coordinates":[116.02773000000001,23.69441],"type":"Point"}
}