{
  "type": "Feature",
  "properties": {
    "gn:admin1_code":"4.0",
    "gn:asciiname":"Dexingcun",
    "gn:country_code":"CN",
    "gn:dem":1,
    "gn:feature_class":"P",
    "gn:feature_code":"PPL",
    "gn:name":"Dexingcun",
    "gn:population":0,
    "gn:timezone":"Asia/Shanghai",
    "iso:country":"CN",
    "name:zho_x_preferred":[
        "\u5fb7\u5174\u6751"
    ],
    "wof:name":"Dexingcun",
    "wof:placetype":"locality"
},
  "geometry": {"coordinates":[119.37549,34.32269],"type":"Point"}
}