{
  "type": "Feature",
  "properties": {
    "gn:admin1_code":"30",
    "gn:asciiname":"Gaocuotang",
    "gn:country_code":"CN",
    "gn:dem":21,
    "gn:feature_class":"P",
    "gn:feature_code":"PPL",
    "gn:name":"Gaocuotang",
    "gn:population":0,
    "gn:timezone":"Asia/Shanghai",
    "iso:country":"CN",
    "name:zho_x_preferred":[
        "\u9ad8\u539d\u5858"
    ],
    "wof:name":"Gaocuotang",
    "wof:placetype":"locality"
},
  "geometry": {"coordinates":[116.60460999999999,23.71098],"type":"Point"}
}