{
  "type": "Feature",
  "properties": {
    "gn:admin1_code":"12.0",
    "gn:asciiname":"Yupize",
    "gn:cc2":"CN",
    "gn:country_code":"CN",
    "gn:dem":1560,
    "gn:feature_class":"P",
    "gn:feature_code":"PPL",
    "gn:name":"Yupize",
    "gn:population":0,
    "gn:timezone":"Asia/Shanghai",
    "iso:country":"CN",
    "name:und_x_variant":[
        "Y\u00fc-p\u2019i-tse",
        "Yupize"
    ],
    "wof:name":"Yupize",
    "wof:placetype":"locality"
},
  "geometry": {"coordinates":[109.08333,30.46667],"type":"Point"}
}