{
  "type": "Feature",
  "properties": {
    "gn:admin1_code":"24",
    "gn:asciiname":"Jishan",
    "gn:cc2":"CN",
    "gn:country_code":"CN",
    "gn:dem":399,
    "gn:feature_class":"P",
    "gn:feature_code":"PPL",
    "gn:name":"Jishan",
    "gn:population":0,
    "gn:timezone":"Asia/Shanghai",
    "iso:country":"CN",
    "name:deu_x_preferred":[
        "Jishan"
    ],
    "name:und_x_variant":[
        "Chi-shan-ts\u2019un",
        "Chi-shan"
    ],
    "wof:name":"Jishan",
    "wof:placetype":"locality"
},
  "geometry": {"coordinates":[110.48333,35.05],"type":"Point"}
}