{
  "type": "Feature",
  "properties": {
    "gn:admin1_code":"29.0",
    "gn:asciiname":"Bijialinggang",
    "gn:country_code":"CN",
    "gn:dem":2188,
    "gn:feature_class":"P",
    "gn:feature_code":"PPL",
    "gn:name":"Bijialinggang",
    "gn:population":0,
    "gn:timezone":"Asia/Shanghai",
    "iso:country":"CN",
    "name:zho_x_preferred":[
        "\u6bd5\u5bb6\u5cad\u5c97"
    ],
    "wof:name":"Bijialinggang",
    "wof:placetype":"locality"
},
  "geometry": {"coordinates":[100.864,24.7666],"type":"Point"}
}