{
  "type": "Feature",
  "properties": {
    "gn:admin1_code":"19.0",
    "gn:asciiname":"Gutaizi",
    "gn:country_code":"CN",
    "gn:dem":519,
    "gn:feature_class":"P",
    "gn:feature_code":"PPL",
    "gn:name":"Gutaizi",
    "gn:population":0,
    "gn:timezone":"Asia/Shanghai",
    "iso:country":"CN",
    "name:zho_x_preferred":[
        "\u8c37\u53f0\u5b50"
    ],
    "wof:name":"Gutaizi",
    "wof:placetype":"locality"
},
  "geometry": {"coordinates":[119.378,40.563],"type":"Point"}
}