{
  "type": "Feature",
  "properties": {
    "gn:admin1_code":"32.0",
    "gn:asciiname":"Xiahetou",
    "gn:country_code":"CN",
    "gn:dem":512,
    "gn:feature_class":"P",
    "gn:feature_code":"PPL",
    "gn:name":"Xiahetou",
    "gn:population":0,
    "gn:timezone":"Asia/Shanghai",
    "iso:country":"CN",
    "name:zho_x_preferred":[
        "\u4e0b\u6cb3\u5934"
    ],
    "wof:name":"Xiahetou",
    "wof:placetype":"locality"
},
  "geometry": {"coordinates":[105.545,31.6559],"type":"Point"}
}