{
  "type": "Feature",
  "properties": {
    "gn:admin1_code":"30.0",
    "gn:asciiname":"Shengliancun",
    "gn:country_code":"CN",
    "gn:dem":6,
    "gn:feature_class":"P",
    "gn:feature_code":"PPL",
    "gn:name":"Shengliancun",
    "gn:population":0,
    "gn:timezone":"Asia/Shanghai",
    "iso:country":"CN",
    "name:zho_x_preferred":[
        "\u80dc\u8054\u6751"
    ],
    "wof:name":"Shengliancun",
    "wof:placetype":"locality"
},
  "geometry": {"coordinates":[116.60653000000001,23.59986],"type":"Point"}
}