{
  "type": "Feature",
  "properties": {
    "gn:admin1_code":"15.0",
    "gn:asciiname":"Youhao",
    "gn:country_code":"CN",
    "gn:dem":1172,
    "gn:feature_class":"P",
    "gn:feature_code":"PPL",
    "gn:name":"Youhao",
    "gn:population":0,
    "gn:timezone":"Asia/Shanghai",
    "iso:country":"CN",
    "name:zho_x_preferred":[
        "\u53cb\u597d"
    ],
    "wof:name":"Youhao",
    "wof:placetype":"locality"
},
  "geometry": {"coordinates":[99.5776,40.3379],"type":"Point"}
}