{
  "type": "Feature",
  "properties": {
    "gn:admin1_code":"32.0",
    "gn:asciiname":"Zhuoduo",
    "gn:country_code":"CN",
    "gn:dem":2887,
    "gn:feature_class":"P",
    "gn:feature_code":"PPL",
    "gn:name":"Zhuoduo",
    "gn:population":0,
    "gn:timezone":"Asia/Shanghai",
    "iso:country":"CN",
    "name:zho_x_preferred":[
        "\u5353\u591a"
    ],
    "wof:name":"Zhuoduo",
    "wof:placetype":"locality"
},
  "geometry": {"coordinates":[103.35652,33.55240999999999],"type":"Point"}
}