{
  "type": "Feature",
  "properties": {
    "gn:admin1_code":"9.0",
    "gn:asciiname":"Shihuiyao",
    "gn:country_code":"CN",
    "gn:dem":306,
    "gn:feature_class":"P",
    "gn:feature_code":"PPL",
    "gn:name":"Shihuiyao",
    "gn:population":0,
    "gn:timezone":"Asia/Shanghai",
    "iso:country":"CN",
    "name:zho_x_preferred":[
        "\u77f3\u7070\u7a91"
    ],
    "wof:name":"Shihuiyao",
    "wof:placetype":"locality"
},
  "geometry": {"coordinates":[113.03613,33.57325],"type":"Point"}
}