{
  "type": "Feature",
  "properties": {
    "gn:admin1_code":"15.0",
    "gn:asciiname":"Dongwan",
    "gn:country_code":"CN",
    "gn:dem":1584,
    "gn:feature_class":"P",
    "gn:feature_code":"PPL",
    "gn:name":"Dongwan",
    "gn:population":0,
    "gn:timezone":"Asia/Shanghai",
    "iso:country":"CN",
    "name:deu_x_preferred":[
        "Dongwan"
    ],
    "name:und_x_variant":[
        "\u4e1c\u6e7e"
    ],
    "wof:name":"Dongwan",
    "wof:placetype":"locality"
},
  "geometry": {"coordinates":[105.76656,35.04354],"type":"Point"}
}