{
  "type": "Feature",
  "properties": {
    "gn:admin1_code":"7",
    "gn:asciiname":"Meilintou",
    "gn:country_code":"CN",
    "gn:dem":567,
    "gn:feature_class":"P",
    "gn:feature_code":"PPL",
    "gn:name":"Meilintou",
    "gn:population":0,
    "gn:timezone":"Asia/Shanghai",
    "iso:country":"CN",
    "name:zho_x_preferred":[
        "\u6885\u6797\u5934"
    ],
    "wof:name":"Meilintou",
    "wof:placetype":"locality"
},
  "geometry": {"coordinates":[118.74583,25.91778],"type":"Point"}
}