{
  "type": "Feature",
  "properties": {
    "gn:admin1_code":"7.0",
    "gn:asciiname":"Nikeng",
    "gn:country_code":"CN",
    "gn:dem":176,
    "gn:feature_class":"P",
    "gn:feature_code":"PPL",
    "gn:name":"Nikeng",
    "gn:population":0,
    "gn:timezone":"Asia/Shanghai",
    "iso:country":"CN",
    "name:und_x_variant":[
        "\u502a\u5751"
    ],
    "wof:name":"Nikeng",
    "wof:placetype":"locality"
},
  "geometry": {"coordinates":[118.2573,26.92036],"type":"Point"}
}