{
  "type": "Feature",
  "properties": {
    "gn:admin1_code":"29",
    "gn:asciiname":"Anyue",
    "gn:country_code":"CN",
    "gn:dem":521,
    "gn:feature_class":"P",
    "gn:feature_code":"PPL",
    "gn:name":"Anyue",
    "gn:population":0,
    "gn:timezone":"Asia/Shanghai",
    "iso:country":"CN",
    "name:zho_x_preferred":[
        "\u5b89\u8dc3"
    ],
    "wof:name":"Anyue",
    "wof:placetype":"locality"
},
  "geometry": {"coordinates":[105.504,23.9774],"type":"Point"}
}