{
  "type": "Feature",
  "properties": {
    "gn:admin1_code":"24.0",
    "gn:asciiname":"Nanshi",
    "gn:country_code":"CN",
    "gn:dem":411,
    "gn:feature_class":"P",
    "gn:feature_code":"PPL",
    "gn:name":"Nanshi",
    "gn:population":0,
    "gn:timezone":"Asia/Shanghai",
    "iso:country":"CN",
    "name:ceb_x_preferred":[
        "Nanshi"
    ],
    "name:deu_x_preferred":[
        "Nanshi"
    ],
    "name:swe_x_preferred":[
        "Nanshi"
    ],
    "name:zho_x_preferred":[
        "\u5357\u5e08"
    ],
    "wof:name":"Nanshi",
    "wof:placetype":"locality"
},
  "geometry": {"coordinates":[111.23976999999999,35.15366],"type":"Point"}
}