{
  "type": "Feature",
  "properties": {
    "gn:admin1_code":"11.0",
    "gn:asciiname":"Yijiahe",
    "gn:country_code":"CN",
    "gn:dem":61,
    "gn:feature_class":"P",
    "gn:feature_code":"PPL",
    "gn:name":"Yijiahe",
    "gn:population":0,
    "gn:timezone":"Asia/Shanghai",
    "iso:country":"CN",
    "name:zho_x_preferred":[
        "Yijiahe"
    ],
    "name:zho_x_variant":[
        "\u6613\u5bb6\u6cb3"
    ],
    "wof:name":"Yijiahe",
    "wof:placetype":"locality"
},
  "geometry": {"coordinates":[111.4999,29.43082],"type":"Point"}
}