{
  "type": "Feature",
  "properties": {
    "gn:admin1_code":"11.0",
    "gn:asciiname":"Liujiawan",
    "gn:country_code":"CN",
    "gn:dem":905,
    "gn:feature_class":"P",
    "gn:feature_code":"PPL",
    "gn:name":"Liujiawan",
    "gn:population":0,
    "gn:timezone":"Asia/Shanghai",
    "iso:country":"CN",
    "name:zho_x_preferred":[
        "Liujiawan"
    ],
    "name:zho_x_variant":[
        "\u5218\u5bb6\u6e7e"
    ],
    "wof:name":"Liujiawan",
    "wof:placetype":"locality"
},
  "geometry": {"coordinates":[110.13352999999999,28.91182],"type":"Point"}
}