{
  "type": "Feature",
  "properties": {
    "gn:admin1_code":"07",
    "gn:asciiname":"Hushang",
    "gn:country_code":"CN",
    "gn:dem":650,
    "gn:feature_class":"P",
    "gn:feature_code":"PPL",
    "gn:name":"Hushang",
    "gn:population":0,
    "gn:timezone":"Asia/Shanghai",
    "iso:country":"CN",
    "name:ara_x_preferred":[
        "\u0647\u0648\u0634\u0646\u063a"
    ],
    "name:cat_x_preferred":[
        "Huixang"
    ],
    "name:ceb_x_preferred":[
        "Hu\u0161ang"
    ],
    "name:deu_x_preferred":[
        "Huschang"
    ],
    "name:diq_x_preferred":[
        "Hu\u015fheng"
    ],
    "name:fas_x_preferred":[
        "\u0647\u0648\u0634\u0646\u06af"
    ],
    "name:fra_x_preferred":[
        "Houchang"
    ],
    "name:jpn_x_preferred":[
        "\u30d5\u30fc\u30b7\u30e3\u30f3\u30b0"
    ],
    "name:nld_x_preferred":[
        "Hushang"
    ],
    "name:nor_x_preferred":[
        "Hushang Pishd\u0101d"
    ],
    "name:rus_x_preferred":[
        "\u0425\u0443\u0448\u0430\u043d\u0433"
    ],
    "name:tgl_x_preferred":[
        "Hushang"
    ],
    "name:zho_x_preferred":[
        "\u6e56\u4e0a"
    ],
    "wof:name":"Hushang",
    "wof:placetype":"locality"
},
  "geometry": {"coordinates":[117.77815,25.10127],"type":"Point"}
}