{
  "type": "Feature",
  "properties": {
    "gn:admin1_code":"10.0",
    "gn:asciiname":"Shaijiahui",
    "gn:country_code":"CN",
    "gn:dem":19,
    "gn:feature_class":"P",
    "gn:feature_code":"PPL",
    "gn:name":"Shaijiahui",
    "gn:population":0,
    "gn:timezone":"Asia/Shanghai",
    "iso:country":"CN",
    "name:zho_x_preferred":[
        "\u6652\u7532\u4f1a"
    ],
    "wof:name":"Shaijiahui",
    "wof:placetype":"locality"
},
  "geometry": {"coordinates":[119.57452000000001,39.97431],"type":"Point"}
}