{
  "type": "Feature",
  "properties": {
    "gn:admin1_code":"31",
    "gn:asciiname":"Xiaozai",
    "gn:country_code":"CN",
    "gn:dem":55,
    "gn:feature_class":"P",
    "gn:feature_code":"PPL",
    "gn:name":"Xiaozai",
    "gn:population":0,
    "gn:timezone":"Asia/Shanghai",
    "iso:country":"CN",
    "name:und_x_variant":[
        "\u5c0f\u8f7d",
        "Xiaozaishangcun"
    ],
    "wof:name":"Xiaozai",
    "wof:placetype":"locality"
},
  "geometry": {"coordinates":[108.726,19.3531],"type":"Point"}
}