{
  "type": "Feature",
  "properties": {
    "gn:admin1_code":"12.0",
    "gn:asciiname":"Yiyangjia",
    "gn:country_code":"CN",
    "gn:dem":93,
    "gn:feature_class":"P",
    "gn:feature_code":"PPL",
    "gn:name":"Yiyangjia",
    "gn:population":0,
    "gn:timezone":"Asia/Shanghai",
    "iso:country":"CN",
    "name:zho_x_preferred":[
        "\u6613\u6768\u5bb6"
    ],
    "wof:name":"Yiyangjia",
    "wof:placetype":"locality"
},
  "geometry": {"coordinates":[114.71583,31.25711],"type":"Point"}
}