{
  "type": "Feature",
  "properties": {
    "gn:admin1_code":"25",
    "gn:asciiname":"Xinchenghai",
    "gn:country_code":"CN",
    "gn:dem":38,
    "gn:feature_class":"P",
    "gn:feature_code":"PPL",
    "gn:name":"Xinchenghai",
    "gn:population":0,
    "gn:timezone":"Asia/Shanghai",
    "iso:country":"CN",
    "name:zho_x_preferred":[
        "\u65b0\u57ce\u6d77"
    ],
    "wof:name":"Xinchenghai",
    "wof:placetype":"locality"
},
  "geometry": {"coordinates":[115.87932000000001,36.33034],"type":"Point"}
}