{
  "type": "Feature",
  "properties": {
    "gn:admin1_code":"12.0",
    "gn:asciiname":"Dawu Weijia",
    "gn:country_code":"CN",
    "gn:dem":60,
    "gn:feature_class":"P",
    "gn:feature_code":"PPL",
    "gn:name":"Dawu Weijia",
    "gn:population":0,
    "gn:timezone":"Asia/Shanghai",
    "iso:country":"CN",
    "name:zho_x_preferred":[
        "\u5927\u5c4b\u9b4f\u5bb6"
    ],
    "wof:name":"Dawu Weijia",
    "wof:placetype":"locality"
},
  "geometry": {"coordinates":[113.81121,29.71787],"type":"Point"}
}