{
  "type": "Feature",
  "properties": {
    "gn:admin1_code":"19.0",
    "gn:asciiname":"Nanxinqiu",
    "gn:country_code":"CN",
    "gn:dem":166,
    "gn:feature_class":"P",
    "gn:feature_code":"PPL",
    "gn:name":"Nanxinqiu",
    "gn:population":0,
    "gn:timezone":"Asia/Shanghai",
    "iso:country":"CN",
    "name:und_x_variant":[
        "\u5357\u65b0\u4e18"
    ],
    "name:zho_x_preferred":[
        "\u5357\u65b0\u4e18"
    ],
    "name:zho_x_variant":[
        "\u5357\u65b0\u90b1"
    ],
    "wof:name":"Nanxinqiu",
    "wof:placetype":"locality"
},
  "geometry": {"coordinates":[121.494,41.9933],"type":"Point"}
}