{
  "type": "Feature",
  "properties": {
    "gn:admin1_code":"7.0",
    "gn:asciiname":"Diaoqi",
    "gn:country_code":"CN",
    "gn:dem":52,
    "gn:feature_class":"P",
    "gn:feature_code":"PPL",
    "gn:name":"Diaoqi",
    "gn:population":0,
    "gn:timezone":"Asia/Shanghai",
    "iso:country":"CN",
    "name:zho_x_preferred":[
        "\u9493\u5c90"
    ],
    "wof:name":"Diaoqi",
    "wof:placetype":"locality"
},
  "geometry": {"coordinates":[119.68389000000001,26.80223],"type":"Point"}
}