{
  "type": "Feature",
  "properties": {
    "gn:admin1_code":"19.0",
    "gn:asciiname":"Laotancun",
    "gn:country_code":"CN",
    "gn:dem":-9999,
    "gn:feature_class":"P",
    "gn:feature_code":"PPL",
    "gn:name":"Laotancun",
    "gn:population":0,
    "gn:timezone":"Asia/Shanghai",
    "iso:country":"CN",
    "name:zho_x_preferred":[
        "\u8001\u6ee9\u6751"
    ],
    "wof:name":"Laotancun",
    "wof:placetype":"locality"
},
  "geometry": {"coordinates":[120.66945,40.51002],"type":"Point"}
}