{
  "type": "Feature",
  "properties": {
    "gn:admin1_code":"29.0",
    "gn:asciiname":"Dashuitang",
    "gn:country_code":"CN",
    "gn:dem":1524,
    "gn:feature_class":"P",
    "gn:feature_code":"PPL",
    "gn:name":"Dashuitang",
    "gn:population":0,
    "gn:timezone":"Asia/Shanghai",
    "iso:country":"CN",
    "name:zho_x_preferred":[
        "\u5927\u6c34\u5858"
    ],
    "wof:name":"Dashuitang",
    "wof:placetype":"locality"
},
  "geometry": {"coordinates":[99.06229999999999,24.1592],"type":"Point"}
}