{
  "type": "Feature",
  "properties": {
    "gn:admin1_code":"8.0",
    "gn:asciiname":"Xincunsanhao",
    "gn:country_code":"CN",
    "gn:dem":156,
    "gn:feature_class":"P",
    "gn:feature_code":"PPL",
    "gn:name":"Xincunsanhao",
    "gn:population":0,
    "gn:timezone":"Asia/Shanghai",
    "iso:country":"CN",
    "name:zho_x_preferred":[
        "\u65b0\u6751\u4e09\u53f7"
    ],
    "wof:name":"Xincunsanhao",
    "wof:placetype":"locality"
},
  "geometry": {"coordinates":[125.10681,47.09214],"type":"Point"}
}