{
  "type": "Feature",
  "properties": {
    "gn:admin1_code":"24",
    "gn:asciiname":"Duzhuang",
    "gn:country_code":"CN",
    "gn:dem":1002,
    "gn:feature_class":"P",
    "gn:feature_code":"PPLA4",
    "gn:name":"Duzhuang",
    "gn:population":0,
    "gn:timezone":"Asia/Shanghai",
    "iso:country":"CN",
    "name:und_x_variant":[
        "Tu-chia-chuang",
        "Tu-chuang",
        "Duzhuang",
        "\u675c\u5e84",
        "Duzhuang Zhen",
        "\u675c\u5e84\u9547"
    ],
    "wof:name":"Duzhuang",
    "wof:placetype":"locality"
},
  "geometry": {"coordinates":[113.46722,39.935],"type":"Point"}
}