{
  "type": "Feature",
  "properties": {
    "gn:admin1_code":"25",
    "gn:asciiname":"Xiaojing",
    "gn:country_code":"CN",
    "gn:dem":28,
    "gn:feature_class":"P",
    "gn:feature_code":"PPL",
    "gn:name":"Xiaojing",
    "gn:population":0,
    "gn:timezone":"Asia/Shanghai",
    "iso:country":"CN",
    "name:nld_x_preferred":[
        "Xiaojing"
    ],
    "name:swe_x_preferred":[
        "Xiaojing"
    ],
    "name:zho_x_preferred":[
        "\u5c0f\u4e95"
    ],
    "wof:name":"Xiaojing",
    "wof:placetype":"locality"
},
  "geometry": {"coordinates":[116.35599999999999,36.8108],"type":"Point"}
}