{
  "type": "Feature",
  "properties": {
    "gn:admin1_code":"32.0",
    "gn:asciiname":"Shangzhongpingxi",
    "gn:country_code":"CN",
    "gn:dem":1771,
    "gn:feature_class":"P",
    "gn:feature_code":"PPL",
    "gn:name":"Shangzhongpingxi",
    "gn:population":0,
    "gn:timezone":"Asia/Shanghai",
    "iso:country":"CN",
    "name:zho_x_preferred":[
        "\u4e0a\u4e2d\u576a\u6eaa"
    ],
    "wof:name":"Shangzhongpingxi",
    "wof:placetype":"locality"
},
  "geometry": {"coordinates":[103.04492,29.27796],"type":"Point"}
}