{
  "type": "Feature",
  "properties": {
    "gn:admin1_code":"9",
    "gn:asciiname":"Qianhanlou",
    "gn:country_code":"CN",
    "gn:dem":36,
    "gn:feature_class":"P",
    "gn:feature_code":"PPL",
    "gn:name":"Qianhanlou",
    "gn:population":0,
    "gn:timezone":"Asia/Shanghai",
    "iso:country":"CN",
    "name:zho_x_preferred":[
        "\u524d\u97e9\u697c"
    ],
    "wof:name":"Qianhanlou",
    "wof:placetype":"locality"
},
  "geometry": {"coordinates":[116.547,33.9665],"type":"Point"}
}