{
  "type": "Feature",
  "properties": {
    "gn:admin1_code":"15.0",
    "gn:asciiname":"Shijiasigou",
    "gn:country_code":"CN",
    "gn:dem":1416,
    "gn:feature_class":"P",
    "gn:feature_code":"PPL",
    "gn:name":"Shijiasigou",
    "gn:population":0,
    "gn:timezone":"Asia/Shanghai",
    "iso:country":"CN",
    "name:und_x_variant":[
        "\u77f3\u5bb6\u56db\u6c9f"
    ],
    "wof:name":"Shijiasigou",
    "wof:placetype":"locality"
},
  "geometry": {"coordinates":[107.02598,36.79356],"type":"Point"}
}