{
  "type": "Feature",
  "properties": {
    "gn:admin1_code":"07",
    "gn:asciiname":"Shangfeng",
    "gn:country_code":"CN",
    "gn:dem":753,
    "gn:feature_class":"P",
    "gn:feature_code":"PPL",
    "gn:name":"Shangfeng",
    "gn:population":0,
    "gn:timezone":"Asia/Shanghai",
    "iso:country":"CN",
    "name:zho_x_preferred":[
        "\u4e0a\u4e30"
    ],
    "wof:name":"Shangfeng",
    "wof:placetype":"locality"
},
  "geometry": {"coordinates":[117.9825,25.55917],"type":"Point"}
}