{
  "type": "Feature",
  "properties": {
    "gn:admin1_code":"22.0",
    "gn:asciiname":"Wenzhazicun",
    "gn:country_code":"CN",
    "gn:dem":797,
    "gn:feature_class":"P",
    "gn:feature_code":"PPL",
    "gn:name":"Wenzhazicun",
    "gn:population":0,
    "gn:timezone":"Asia/Shanghai",
    "iso:country":"CN",
    "name:zho_x_preferred":[
        "\u6e29\u6805\u5b50\u6751"
    ],
    "wof:name":"Wenzhazicun",
    "wof:placetype":"locality"
},
  "geometry": {"coordinates":[116.36525,40.89447],"type":"Point"}
}