{
  "type": "Feature",
  "properties": {
    "gn:admin1_code":"23",
    "gn:asciiname":"T'u-chia-ts'un",
    "gn:country_code":"CN",
    "gn:dem":2,
    "gn:feature_class":"P",
    "gn:feature_code":"PPL",
    "gn:name":"T\u2019u-chia-ts\u2019un",
    "gn:population":0,
    "gn:timezone":"Asia/Shanghai",
    "iso:country":"CN",
    "wof:name":"T'u-chia-ts'un",
    "wof:placetype":"locality"
},
  "geometry": {"coordinates":[121.06694,30.92806],"type":"Point"}
}