{
  "type": "Feature",
  "properties": {
    "gn:admin1_code":"04",
    "gn:asciiname":"Dangkou",
    "gn:country_code":"CN",
    "gn:dem":6,
    "gn:feature_class":"P",
    "gn:feature_code":"PPL",
    "gn:name":"Dangkou",
    "gn:population":0,
    "gn:timezone":"Asia/Shanghai",
    "iso:country":"CN",
    "name:und_x_variant":[
        "Tang-k\u2019ou-chen",
        "Dangkou"
    ],
    "wof:name":"Dangkou",
    "wof:placetype":"locality"
},
  "geometry": {"coordinates":[120.55502,31.52143],"type":"Point"}
}