{
  "type": "Feature",
  "properties": {
    "gn:admin1_code":"19.0",
    "gn:asciiname":"Jixiangyu",
    "gn:country_code":"CN",
    "gn:dem":212,
    "gn:feature_class":"P",
    "gn:feature_code":"PPL",
    "gn:name":"Jixiangyu",
    "gn:population":0,
    "gn:timezone":"Asia/Shanghai",
    "iso:country":"CN",
    "name:zho_x_preferred":[
        "\u5409\u7965\u5cea"
    ],
    "wof:name":"Jixiangyu",
    "wof:placetype":"locality"
},
  "geometry": {"coordinates":[123.16549000000001,40.84394],"type":"Point"}
}