{
  "type": "Feature",
  "properties": {
    "gn:admin1_code":"31",
    "gn:asciiname":"Lezhong Nongchang",
    "gn:country_code":"CN",
    "gn:dem":186,
    "gn:feature_class":"P",
    "gn:feature_code":"PPLF",
    "gn:name":"Lezhong Nongchang",
    "gn:population":0,
    "gn:timezone":"Asia/Shanghai",
    "iso:country":"CN",
    "name:und_x_variant":[
        "\u4e50\u4e2d\u519c\u573a"
    ],
    "wof:name":"Lezhong Nongchang",
    "wof:placetype":"locality"
},
  "geometry": {"coordinates":[109.31423999999998,18.85076],"type":"Point"}
}