{
  "type": "Feature",
  "properties": {
    "gn:admin1_code":"21.0",
    "gn:asciiname":"Jianshanwan",
    "gn:country_code":"CN",
    "gn:dem":1767,
    "gn:feature_class":"P",
    "gn:feature_code":"PPL",
    "gn:name":"Jianshanwan",
    "gn:population":0,
    "gn:timezone":"Asia/Shanghai",
    "iso:country":"CN",
    "name:und_x_variant":[
        "\u5c16\u5c71\u6e7e"
    ],
    "name:zho_x_preferred":[
        "\u5c16\u5c71\u6e7e"
    ],
    "wof:name":"Jianshanwan",
    "wof:placetype":"locality"
},
  "geometry": {"coordinates":[106.25207,36.92571],"type":"Point"}
}