{
  "type": "Feature",
  "properties": {
    "gn:admin1_code":"21.0",
    "gn:asciiname":"Maotao",
    "gn:country_code":"CN",
    "gn:dem":2216,
    "gn:feature_class":"P",
    "gn:feature_code":"PPL",
    "gn:name":"Maotao",
    "gn:population":0,
    "gn:timezone":"Asia/Shanghai",
    "iso:country":"CN",
    "name:zho_x_preferred":[
        "\u6bdb\u5957"
    ],
    "wof:name":"Maotao",
    "wof:placetype":"locality"
},
  "geometry": {"coordinates":[106.06100000000001,35.86199999999999],"type":"Point"}
}