{
  "type": "Feature",
  "properties": {
    "gn:admin1_code":"24",
    "gn:asciiname":"Hujiayu",
    "gn:cc2":"CN",
    "gn:country_code":"CN",
    "gn:dem":775,
    "gn:feature_class":"P",
    "gn:feature_code":"PPL",
    "gn:name":"Hujiayu",
    "gn:population":0,
    "gn:timezone":"Asia/Shanghai",
    "iso:country":"CN",
    "name:und_x_variant":[
        "Hu-chia-y\u00fc",
        "Hujiayu"
    ],
    "wof:name":"Hujiayu",
    "wof:placetype":"locality"
},
  "geometry": {"coordinates":[111.54333,35.21278],"type":"Point"}
}