{
  "type": "Feature",
  "properties": {
    "gn:admin1_code":"5.0",
    "gn:asciiname":"Chejia Youfang",
    "gn:country_code":"CN",
    "gn:dem":139,
    "gn:feature_class":"P",
    "gn:feature_code":"PPL",
    "gn:name":"Chejia Youfang",
    "gn:population":0,
    "gn:timezone":"Asia/Shanghai",
    "iso:country":"CN",
    "name:zho_x_preferred":[
        "\u8f66\u5bb6\u6cb9\u574a"
    ],
    "wof:name":"Chejia Youfang",
    "wof:placetype":"locality"
},
  "geometry": {"coordinates":[126.11083000000001,45.11783],"type":"Point"}
}