{
  "type": "Feature",
  "properties": {
    "gn:admin1_code":"26",
    "gn:asciiname":"Mingdu",
    "gn:country_code":"CN",
    "gn:dem":490,
    "gn:feature_class":"P",
    "gn:feature_code":"PPLA4",
    "gn:name":"Mingdu",
    "gn:population":0,
    "gn:timezone":"Asia/Shanghai",
    "iso:country":"CN",
    "name:und_x_variant":[
        "Wu-tu-chen",
        "Ming-tu",
        "Ming-tu-chen",
        "\u9e23\u728a",
        "Mingdu",
        "Mingdu Zhen"
    ],
    "wof:name":"Mingdu",
    "wof:placetype":"locality"
},
  "geometry": {"coordinates":[109.10263999999999,34.13052],"type":"Point"}
}