{
  "type": "Feature",
  "properties": {
    "gn:admin1_code":"2.0",
    "gn:asciiname":"Hujialou",
    "gn:country_code":"CN",
    "gn:dem":12,
    "gn:feature_class":"P",
    "gn:feature_code":"PPL",
    "gn:name":"Hujialou",
    "gn:population":0,
    "gn:timezone":"Asia/Shanghai",
    "iso:country":"CN",
    "name:und_x_variant":[
        "\u80e1\u5bb6\u6e87"
    ],
    "wof:name":"Hujialou",
    "wof:placetype":"locality"
},
  "geometry": {"coordinates":[120.80068,30.02351],"type":"Point"}
}