{
  "type": "Feature",
  "properties": {
    "gn:admin1_code":"32.0",
    "gn:asciiname":"Watuo Liangzi",
    "gn:country_code":"CN",
    "gn:dem":2229,
    "gn:feature_class":"P",
    "gn:feature_code":"PPL",
    "gn:name":"Watuo Liangzi",
    "gn:population":0,
    "gn:timezone":"Asia/Shanghai",
    "iso:country":"CN",
    "name:zho_x_preferred":[
        "\u74e6\u6258\u7cb1\u5b50"
    ],
    "wof:name":"Watuo Liangzi",
    "wof:placetype":"locality"
},
  "geometry": {"coordinates":[103.11799999999999,27.4607],"type":"Point"}
}