{
  "type": "Feature",
  "properties": {
    "gn:admin1_code":"7.0",
    "gn:asciiname":"Zhishan",
    "gn:country_code":"CN",
    "gn:dem":118,
    "gn:feature_class":"P",
    "gn:feature_code":"PPLA4",
    "gn:name":"Zhishan",
    "gn:population":0,
    "gn:timezone":"Asia/Shanghai",
    "iso:country":"CN",
    "name:und_x_variant":[
        "Zhishan Jiedao",
        "Zhishan"
    ],
    "name:zho_x_preferred":[
        "\u829d\u5c71"
    ],
    "name:zho_x_variant":[
        "\u829d\u5c71\u8857\u9053"
    ],
    "wof:name":"Zhishan",
    "wof:placetype":"locality"
},
  "geometry": {"coordinates":[118.32523,27.04373],"type":"Point"}
}