{
  "type": "Feature",
  "properties": {
    "gn:admin1_code":"5.0",
    "gn:asciiname":"Lijia Weizi",
    "gn:country_code":"CN",
    "gn:dem":198,
    "gn:feature_class":"P",
    "gn:feature_code":"PPL",
    "gn:name":"Lijia Weizi",
    "gn:population":0,
    "gn:timezone":"Asia/Shanghai",
    "iso:country":"CN",
    "name:zho_x_preferred":[
        "\u674e\u5bb6\u56f4\u5b50"
    ],
    "wof:name":"Lijia Weizi",
    "wof:placetype":"locality"
},
  "geometry": {"coordinates":[124.43128,44.54348],"type":"Point"}
}