{
  "type": "Feature",
  "properties": {
    "gn:admin1_code":"15",
    "gn:asciiname":"Tianjiawan",
    "gn:country_code":"CN",
    "gn:dem":864,
    "gn:feature_class":"P",
    "gn:feature_code":"PPL",
    "gn:name":"Tianjiawan",
    "gn:population":0,
    "gn:timezone":"Asia/Shanghai",
    "iso:country":"CN",
    "wof:name":"Tianjiawan",
    "wof:placetype":"locality"
},
  "geometry": {"coordinates":[105.12166999999999,32.73083],"type":"Point"}
}