{
  "type": "Feature",
  "properties": {
    "gn:admin1_code":"26.0",
    "gn:asciiname":"Mozishan",
    "gn:country_code":"CN",
    "gn:dem":1286,
    "gn:feature_class":"P",
    "gn:feature_code":"PPL",
    "gn:name":"Mozishan",
    "gn:population":0,
    "gn:timezone":"Asia/Shanghai",
    "iso:country":"CN",
    "name:zho_x_preferred":[
        "\u78e8\u5b50\u5c71"
    ],
    "wof:name":"Mozishan",
    "wof:placetype":"locality"
},
  "geometry": {"coordinates":[109.9943,33.77352],"type":"Point"}
}