{
  "type": "Feature",
  "properties": {
    "gn:admin1_code":"29.0",
    "gn:asciiname":"Luobudian",
    "gn:country_code":"CN",
    "gn:dem":1704,
    "gn:feature_class":"P",
    "gn:feature_code":"PPL",
    "gn:name":"Luobudian",
    "gn:population":0,
    "gn:timezone":"Asia/Shanghai",
    "iso:country":"CN",
    "name:zho_x_preferred":[
        "\u7f57\u535c\u7538"
    ],
    "wof:name":"Luobudian",
    "wof:placetype":"locality"
},
  "geometry": {"coordinates":[102.91200000000001,23.5451],"type":"Point"}
}