{
  "type": "Feature",
  "properties": {
    "gn:admin1_code":"11.0",
    "gn:asciiname":"Simawan",
    "gn:country_code":"CN",
    "gn:dem":31,
    "gn:feature_class":"P",
    "gn:feature_code":"PPL",
    "gn:name":"Simawan",
    "gn:population":0,
    "gn:timezone":"Asia/Shanghai",
    "iso:country":"CN",
    "name:zho_x_preferred":[
        "\u53f8\u9a6c\u5f2f"
    ],
    "wof:name":"Simawan",
    "wof:placetype":"locality"
},
  "geometry": {"coordinates":[112.82317,28.42993],"type":"Point"}
}