{
  "type": "Feature",
  "properties": {
    "gn:admin1_code":"15.0",
    "gn:asciiname":"Mazuidui",
    "gn:country_code":"CN",
    "gn:dem":1481,
    "gn:feature_class":"P",
    "gn:feature_code":"PPLF",
    "gn:name":"Mazuidui",
    "gn:population":0,
    "gn:timezone":"Asia/Shanghai",
    "iso:country":"CN",
    "name:zho_x_preferred":[
        "\u9a6c\u5480\u961f"
    ],
    "wof:name":"Mazuidui",
    "wof:placetype":"locality"
},
  "geometry": {"coordinates":[104.49299999999999,37.1636],"type":"Point"}
}