{
  "type": "Feature",
  "properties": {
    "gn:admin1_code":"10",
    "gn:asciiname":"Yanwang Bizigou",
    "gn:country_code":"CN",
    "gn:dem":902,
    "gn:feature_class":"P",
    "gn:feature_code":"PPL",
    "gn:name":"Yanwang Bizigou",
    "gn:population":0,
    "gn:timezone":"Asia/Shanghai",
    "iso:country":"CN",
    "name:zho_x_preferred":[
        "\u960e\u738b\u9f3b\u5b50\u6c9f"
    ],
    "wof:name":"Yanwang Bizigou",
    "wof:placetype":"locality"
},
  "geometry": {"coordinates":[117.90127,41.91794],"type":"Point"}
}