{
  "type": "Feature",
  "properties": {
    "gn:admin1_code":"15.0",
    "gn:asciiname":"Wuting",
    "gn:country_code":"CN",
    "gn:dem":1432,
    "gn:feature_class":"P",
    "gn:feature_code":"PPL",
    "gn:name":"Wuting",
    "gn:population":0,
    "gn:timezone":"Asia/Shanghai",
    "iso:country":"CN",
    "name:zho_x_preferred":[
        "\u6b66\u4ead"
    ],
    "wof:name":"Wuting",
    "wof:placetype":"locality"
},
  "geometry": {"coordinates":[107.123,35.508],"type":"Point"}
}