{
  "type": "Feature",
  "properties": {
    "gn:admin1_code":"15.0",
    "gn:asciiname":"Zao'ergou",
    "gn:country_code":"CN",
    "gn:dem":1055,
    "gn:feature_class":"P",
    "gn:feature_code":"PPL",
    "gn:name":"Zao\u2019ergou",
    "gn:population":0,
    "gn:timezone":"Asia/Shanghai",
    "iso:country":"CN",
    "name:und_x_variant":[
        "Zao\u2019ergou",
        "\u67a3\u513f\u6c9f"
    ],
    "wof:name":"Zao'ergou",
    "wof:placetype":"locality"
},
  "geometry": {"coordinates":[105.77009,33.77085],"type":"Point"}
}