{
  "type": "Feature",
  "properties": {
    "gn:admin1_code":"23.0",
    "gn:asciiname":"Yihua Qidui",
    "gn:country_code":"CN",
    "gn:dem":4,
    "gn:feature_class":"P",
    "gn:feature_code":"PPLF",
    "gn:name":"Yihua Qidui",
    "gn:population":0,
    "gn:timezone":"Asia/Shanghai",
    "iso:country":"CN",
    "name:zho_x_preferred":[
        "Yihua Qidui"
    ],
    "name:zho_x_variant":[
        "\u4e49\u5316\u4e03\u961f"
    ],
    "wof:name":"Yihua Qidui",
    "wof:placetype":"locality"
},
  "geometry": {"coordinates":[121.51683,31.6125],"type":"Point"}
}