{
  "type": "Feature",
  "properties": {
    "gn:admin1_code":"3.0",
    "gn:asciiname":"Canbeicun",
    "gn:country_code":"CN",
    "gn:dem":237,
    "gn:feature_class":"P",
    "gn:feature_code":"PPL",
    "gn:name":"Canbeicun",
    "gn:population":0,
    "gn:timezone":"Asia/Shanghai",
    "iso:country":"CN",
    "name:und_x_variant":[
        "\u53c2\u9642\u6751"
    ],
    "wof:name":"Canbeicun",
    "wof:placetype":"locality"
},
  "geometry": {"coordinates":[115.94744,26.73673],"type":"Point"}
}