{
  "type": "Feature",
  "properties": {
    "gn:admin1_code":"3.0",
    "gn:asciiname":"Fuyixing",
    "gn:country_code":"CN",
    "gn:dem":182,
    "gn:feature_class":"P",
    "gn:feature_code":"PPL",
    "gn:name":"Fuyixing",
    "gn:population":0,
    "gn:timezone":"Asia/Shanghai",
    "iso:country":"CN",
    "name:und_x_variant":[
        "\u6276\u6905\u5f62"
    ],
    "wof:name":"Fuyixing",
    "wof:placetype":"locality"
},
  "geometry": {"coordinates":[115.49233999999998,26.76172],"type":"Point"}
}