{
  "type": "Feature",
  "properties": {
    "gn:admin1_code":"11",
    "gn:asciiname":"Shizhuping",
    "gn:country_code":"CN",
    "gn:dem":301,
    "gn:feature_class":"P",
    "gn:feature_code":"PPL",
    "gn:name":"Shizhuping",
    "gn:population":0,
    "gn:timezone":"Asia/Shanghai",
    "iso:country":"CN",
    "name:zho_x_preferred":[
        "\u77f3\u67f1\u576a"
    ],
    "wof:name":"Shizhuping",
    "wof:placetype":"locality"
},
  "geometry": {"coordinates":[111.55808,27.68286],"type":"Point"}
}