{
  "type": "Feature",
  "properties": {
    "gn:admin1_code":"29.0",
    "gn:asciiname":"Lawude",
    "gn:country_code":"CN",
    "gn:dem":2188,
    "gn:feature_class":"P",
    "gn:feature_code":"PPL",
    "gn:name":"Lawude",
    "gn:population":0,
    "gn:timezone":"Asia/Shanghai",
    "iso:country":"CN",
    "name:zho_x_preferred":[
        "\u62c9\u52a1\u7684"
    ],
    "wof:name":"Lawude",
    "wof:placetype":"locality"
},
  "geometry": {"coordinates":[101.458,26.1106],"type":"Point"}
}