{
  "type": "Feature",
  "properties": {
    "gn:admin1_code":"7.0",
    "gn:asciiname":"Baiyeping",
    "gn:country_code":"CN",
    "gn:dem":518,
    "gn:feature_class":"P",
    "gn:feature_code":"PPL",
    "gn:name":"Baiyeping",
    "gn:population":0,
    "gn:timezone":"Asia/Shanghai",
    "iso:country":"CN",
    "name:zho_x_preferred":[
        "\u767d\u53f6\u576a"
    ],
    "wof:name":"Baiyeping",
    "wof:placetype":"locality"
},
  "geometry": {"coordinates":[117.78855,27.67284],"type":"Point"}
}