{
  "type": "Feature",
  "properties": {
    "gn:admin1_code":"26.0",
    "gn:asciiname":"Zongnan Linchang",
    "gn:country_code":"CN",
    "gn:dem":648,
    "gn:feature_class":"P",
    "gn:feature_code":"PPLF",
    "gn:name":"Zongnan Linchang",
    "gn:population":0,
    "gn:timezone":"Asia/Shanghai",
    "iso:country":"CN",
    "name:zho_x_preferred":[
        "\u7ec8\u5357\u6797\u573a"
    ],
    "wof:name":"Zongnan Linchang",
    "wof:placetype":"locality"
},
  "geometry": {"coordinates":[109.42458999999999,34.14382],"type":"Point"}
}