{
  "type": "Feature",
  "properties": {
    "gn:admin1_code":"11.0",
    "gn:asciiname":"Takedong",
    "gn:country_code":"CN",
    "gn:dem":723,
    "gn:feature_class":"P",
    "gn:feature_code":"PPL",
    "gn:name":"Takedong",
    "gn:population":0,
    "gn:timezone":"Asia/Shanghai",
    "iso:country":"CN",
    "name:zho_x_preferred":[
        "\u5854\u514b\u6d1e"
    ],
    "wof:name":"Takedong",
    "wof:placetype":"locality"
},
  "geometry": {"coordinates":[109.47280000000001,29.0249],"type":"Point"}
}