{
  "type": "Feature",
  "properties": {
    "gn:admin1_code":"7",
    "gn:asciiname":"Niujiankeng",
    "gn:country_code":"CN",
    "gn:dem":953,
    "gn:feature_class":"P",
    "gn:feature_code":"PPL",
    "gn:name":"Niujiankeng",
    "gn:population":0,
    "gn:timezone":"Asia/Shanghai",
    "iso:country":"CN",
    "name:und_x_variant":[
        "\u725b\u5efa\u5751"
    ],
    "wof:name":"Niujiankeng",
    "wof:placetype":"locality"
},
  "geometry": {"coordinates":[118.58658,27.48304000000001],"type":"Point"}
}