{
  "type": "Feature",
  "properties": {
    "gn:admin1_code":"7.0",
    "gn:asciiname":"Sanxincun",
    "gn:country_code":"CN",
    "gn:dem":226,
    "gn:feature_class":"P",
    "gn:feature_code":"PPL",
    "gn:name":"Sanxincun",
    "gn:population":0,
    "gn:timezone":"Asia/Shanghai",
    "iso:country":"CN",
    "name:zho_x_preferred":[
        "\u4e09\u65b0\u6751"
    ],
    "wof:name":"Sanxincun",
    "wof:placetype":"locality"
},
  "geometry": {"coordinates":[118.71160999999999,25.97596],"type":"Point"}
}