{
  "type": "Feature",
  "properties": {
    "gn:admin1_code":"31.0",
    "gn:asciiname":"Jinshan",
    "gn:country_code":"CN",
    "gn:dem":368,
    "gn:elevation":"445.0",
    "gn:feature_class":"P",
    "gn:feature_code":"PPL",
    "gn:name":"Jinshan",
    "gn:population":0,
    "gn:timezone":"Asia/Shanghai",
    "iso:country":"CN",
    "name:und_x_variant":[
        "\u91d1\u5c71"
    ],
    "wof:name":"Jinshan",
    "wof:placetype":"locality"
},
  "geometry": {"coordinates":[109.63269,18.98036],"type":"Point"}
}