{
  "type": "Feature",
  "properties": {
    "gn:admin1_code":"18",
    "gn:asciiname":"Qingshang",
    "gn:country_code":"CN",
    "gn:dem":1937,
    "gn:feature_class":"P",
    "gn:feature_code":"PPL",
    "gn:name":"Qingshang",
    "gn:population":0,
    "gn:timezone":"Asia/Shanghai",
    "iso:country":"CN",
    "name:zho_x_preferred":[
        "\u7b90\u4e0a"
    ],
    "wof:name":"Qingshang",
    "wof:placetype":"locality"
},
  "geometry": {"coordinates":[104.77500000000001,26.0929],"type":"Point"}
}