{
  "type": "Feature",
  "properties": {
    "gn:admin1_code":"30.0",
    "gn:asciiname":"Changtang",
    "gn:country_code":"CN",
    "gn:dem":188,
    "gn:feature_class":"P",
    "gn:feature_code":"PPL",
    "gn:name":"Changtang",
    "gn:population":0,
    "gn:timezone":"Asia/Shanghai",
    "iso:country":"CN",
    "name:und_x_variant":[
        "\u957f\u5858"
    ],
    "name:zho_x_preferred":[
        "\u957f\u5858"
    ],
    "wof:name":"Changtang",
    "wof:placetype":"locality"
},
  "geometry": {"coordinates":[114.39091000000001,23.84782],"type":"Point"}
}