{
  "type": "Feature",
  "properties": {
    "gn:admin1_code":"29.0",
    "gn:asciiname":"Xidengping",
    "gn:country_code":"CN",
    "gn:dem":2109,
    "gn:feature_class":"P",
    "gn:feature_code":"PPL",
    "gn:name":"Xidengping",
    "gn:population":0,
    "gn:timezone":"Asia/Shanghai",
    "iso:country":"CN",
    "name:zho_x_preferred":[
        "\u6eaa\u767b\u576a"
    ],
    "wof:name":"Xidengping",
    "wof:placetype":"locality"
},
  "geometry": {"coordinates":[99.80459999999999,26.003],"type":"Point"}
}