{
  "type": "Feature",
  "properties": {
    "gn:admin1_code":"3.0",
    "gn:asciiname":"Laiwa",
    "gn:country_code":"CN",
    "gn:dem":512,
    "gn:feature_class":"P",
    "gn:feature_code":"PPL",
    "gn:name":"Laiwa",
    "gn:population":0,
    "gn:timezone":"Asia/Shanghai",
    "iso:country":"CN",
    "name:und_x_variant":[
        "\u8d56\u74e6"
    ],
    "wof:name":"Laiwa",
    "wof:placetype":"locality"
},
  "geometry": {"coordinates":[115.90343,26.42247],"type":"Point"}
}