{
  "type": "Feature",
  "properties": {
    "gn:admin1_code":"16",
    "gn:asciiname":"Bolao",
    "gn:cc2":"CN",
    "gn:country_code":"CN",
    "gn:dem":59,
    "gn:feature_class":"P",
    "gn:feature_code":"PPL",
    "gn:name":"Bolao",
    "gn:population":0,
    "gn:timezone":"Asia/Shanghai",
    "iso:country":"CN",
    "name:und_x_variant":[
        "Po-lao",
        "Bolao"
    ],
    "wof:name":"Bolao",
    "wof:placetype":"locality"
},
  "geometry": {"coordinates":[109.11888999999999,22.12028],"type":"Point"}
}