{
  "type": "Feature",
  "properties": {
    "gn:admin1_code":"32.0",
    "gn:asciiname":"Shihui Daochang",
    "gn:country_code":"CN",
    "gn:dem":346,
    "gn:feature_class":"P",
    "gn:feature_code":"PPL",
    "gn:name":"Shihui Daochang",
    "gn:population":0,
    "gn:timezone":"Asia/Shanghai",
    "iso:country":"CN",
    "name:zho_x_preferred":[
        "\u77f3\u7070\u9053\u573a"
    ],
    "wof:name":"Shihui Daochang",
    "wof:placetype":"locality"
},
  "geometry": {"coordinates":[105.58499999999999,29.0481],"type":"Point"}
}