{
  "type": "Feature",
  "properties": {
    "gn:admin1_code":"18.0",
    "gn:asciiname":"Danglang",
    "gn:country_code":"CN",
    "gn:dem":790,
    "gn:feature_class":"P",
    "gn:feature_code":"PPL",
    "gn:name":"Danglang",
    "gn:population":0,
    "gn:timezone":"Asia/Shanghai",
    "iso:country":"CN",
    "name:zho_x_preferred":[
        "\u515a\u90ce"
    ],
    "wof:name":"Danglang",
    "wof:placetype":"locality"
},
  "geometry": {"coordinates":[108.348,25.6006],"type":"Point"}
}