{
  "type": "Feature",
  "properties": {
    "gn:admin1_code":"19.0",
    "gn:asciiname":"Dazuicun",
    "gn:country_code":"CN",
    "gn:dem":12,
    "gn:feature_class":"P",
    "gn:feature_code":"PPL",
    "gn:name":"Dazuicun",
    "gn:population":0,
    "gn:timezone":"Asia/Shanghai",
    "iso:country":"CN",
    "name:zho_x_preferred":[
        "\u5927\u5480\u6751"
    ],
    "name:zho_x_variant":[
        "\u5927\u5634\u6751"
    ],
    "wof:name":"Dazuicun",
    "wof:placetype":"locality"
},
  "geometry": {"coordinates":[121.51967999999999,39.73167],"type":"Point"}
}