{
  "type": "Feature",
  "properties": {
    "gn:admin1_code":"26.0",
    "gn:asciiname":"Yulincun",
    "gn:country_code":"CN",
    "gn:dem":516,
    "gn:feature_class":"P",
    "gn:feature_code":"PPL",
    "gn:name":"Yulincun",
    "gn:population":0,
    "gn:timezone":"Asia/Shanghai",
    "iso:country":"CN",
    "name:und_x_variant":[
        "\u6986\u6797\u6751"
    ],
    "wof:name":"Yulincun",
    "wof:placetype":"locality"
},
  "geometry": {"coordinates":[109.31489000000001,34.12062],"type":"Point"}
}