{
  "type": "Feature",
  "properties": {
    "gn:admin1_code":"4.0",
    "gn:asciiname":"Huanglicun",
    "gn:country_code":"CN",
    "gn:dem":34,
    "gn:feature_class":"P",
    "gn:feature_code":"PPL",
    "gn:name":"Huanglicun",
    "gn:population":0,
    "gn:timezone":"Asia/Shanghai",
    "iso:country":"CN",
    "name:zho_x_preferred":[
        "\u8352\u91cc\u6751"
    ],
    "wof:name":"Huanglicun",
    "wof:placetype":"locality"
},
  "geometry": {"coordinates":[117.34369,34.33569],"type":"Point"}
}