{
  "type": "Feature",
  "properties": {
    "gn:admin1_code":"19.0",
    "gn:asciiname":"Lujia Buzi",
    "gn:country_code":"CN",
    "gn:dem":436,
    "gn:feature_class":"P",
    "gn:feature_code":"PPL",
    "gn:name":"Lujia Buzi",
    "gn:population":0,
    "gn:timezone":"Asia/Shanghai",
    "iso:country":"CN",
    "name:und_x_variant":[
        "Lujia Puzi",
        "Lujia Buzi"
    ],
    "name:zho_x_preferred":[
        "\u82a6\u5bb6\u5821\u5b50"
    ],
    "wof:name":"Lujia Buzi",
    "wof:placetype":"locality"
},
  "geometry": {"coordinates":[124.96402,41.10584],"type":"Point"}
}