{
  "type": "Feature",
  "properties": {
    "gn:admin1_code":"8.0",
    "gn:asciiname":"Dong Beicun",
    "gn:country_code":"CN",
    "gn:dem":186,
    "gn:feature_class":"P",
    "gn:feature_code":"PPL",
    "gn:name":"Dong Beicun",
    "gn:population":0,
    "gn:timezone":"Asia/Shanghai",
    "iso:country":"CN",
    "name:zho_x_preferred":[
        "\u4e1c\u5317\u6751"
    ],
    "wof:name":"Dong Beicun",
    "wof:placetype":"locality"
},
  "geometry": {"coordinates":[127.34885,47.0445],"type":"Point"}
}