{
  "type": "Feature",
  "properties": {
    "gn:admin1_code":"29.0",
    "gn:asciiname":"Gamu Yakou",
    "gn:country_code":"CN",
    "gn:dem":1819,
    "gn:feature_class":"P",
    "gn:feature_code":"PPL",
    "gn:name":"Gamu Yakou",
    "gn:population":0,
    "gn:timezone":"Asia/Shanghai",
    "iso:country":"CN",
    "name:zho_x_preferred":[
        "\u560e\u6728\u57ad\u53e3"
    ],
    "wof:name":"Gamu Yakou",
    "wof:placetype":"locality"
},
  "geometry": {"coordinates":[104.81,27.4366],"type":"Point"}
}