{
  "type": "Feature",
  "properties": {
    "gn:admin1_code":"30",
    "gn:asciiname":"Shebei",
    "gn:country_code":"CN",
    "gn:dem":362,
    "gn:feature_class":"P",
    "gn:feature_code":"PPL",
    "gn:name":"Shebei",
    "gn:population":0,
    "gn:timezone":"Asia/Shanghai",
    "iso:country":"CN",
    "name:und_x_variant":[
        "\u793e\u80cc",
        "Shebei"
    ],
    "wof:name":"Shebei",
    "wof:placetype":"locality"
},
  "geometry": {"coordinates":[116.43988,24.08804],"type":"Point"}
}