{
  "type": "Feature",
  "properties": {
    "gn:admin1_code":"16.0",
    "gn:asciiname":"Dadai",
    "gn:country_code":"CN",
    "gn:dem":55,
    "gn:feature_class":"P",
    "gn:feature_code":"PPL",
    "gn:name":"Dadai",
    "gn:population":0,
    "gn:timezone":"Asia/Shanghai",
    "iso:country":"CN",
    "name:zho_x_preferred":[
        "\u5927\u5e26"
    ],
    "wof:name":"Dadai",
    "wof:placetype":"locality"
},
  "geometry": {"coordinates":[110.65300000000001,23.76],"type":"Point"}
}