{
  "type": "Feature",
  "properties": {
    "gn:admin1_code":"19.0",
    "gn:asciiname":"Taogantu",
    "gn:country_code":"CN",
    "gn:dem":100,
    "gn:feature_class":"P",
    "gn:feature_code":"PPL",
    "gn:name":"Taogantu",
    "gn:population":0,
    "gn:timezone":"Asia/Shanghai",
    "iso:country":"CN",
    "name:zho_x_preferred":[
        "\u5957\u5e72\u571f"
    ],
    "wof:name":"Taogantu",
    "wof:placetype":"locality"
},
  "geometry": {"coordinates":[123.73399999999999,43.0513],"type":"Point"}
}