{
  "type": "Feature",
  "properties": {
    "gn:admin1_code":"18",
    "gn:asciiname":"Fanhua",
    "gn:country_code":"CN",
    "gn:dem":1135,
    "gn:feature_class":"P",
    "gn:feature_code":"PPL",
    "gn:name":"Fanhua",
    "gn:population":0,
    "gn:timezone":"Asia/Shanghai",
    "iso:country":"CN",
    "name:zho_x_preferred":[
        "\u51e1\u5316"
    ],
    "wof:name":"Fanhua",
    "wof:placetype":"locality"
},
  "geometry": {"coordinates":[105.599,26.0117],"type":"Point"}
}