{
  "type": "Feature",
  "properties": {
    "gn:admin1_code":"10",
    "gn:asciiname":"Xiaonanshan",
    "gn:country_code":"CN",
    "gn:dem":221,
    "gn:feature_class":"P",
    "gn:feature_code":"PPL",
    "gn:name":"Xiaonanshan",
    "gn:population":0,
    "gn:timezone":"Asia/Shanghai",
    "iso:country":"CN",
    "name:zho_x_preferred":[
        "\u5c0f\u5357\u5c71"
    ],
    "wof:name":"Xiaonanshan",
    "wof:placetype":"locality"
},
  "geometry": {"coordinates":[119.15671,40.46186],"type":"Point"}
}