{
  "type": "Feature",
  "properties": {
    "gn:admin1_code":"19.0",
    "gn:asciiname":"Hujiashaoguo",
    "gn:country_code":"CN",
    "gn:dem":93,
    "gn:feature_class":"P",
    "gn:feature_code":"PPL",
    "gn:name":"Hujiashaoguo",
    "gn:population":0,
    "gn:timezone":"Asia/Shanghai",
    "iso:country":"CN",
    "name:zho_x_preferred":[
        "\u80e1\u5bb6\u70e7\u9505"
    ],
    "wof:name":"Hujiashaoguo",
    "wof:placetype":"locality"
},
  "geometry": {"coordinates":[123.19961000000001,42.4314],"type":"Point"}
}