{
  "type": "Feature",
  "properties": {
    "gn:admin1_code":"19.0",
    "gn:asciiname":"Gaotaizi",
    "gn:country_code":"CN",
    "gn:dem":84,
    "gn:feature_class":"P",
    "gn:feature_code":"PPL",
    "gn:name":"Gaotaizi",
    "gn:population":0,
    "gn:timezone":"Asia/Shanghai",
    "iso:country":"CN",
    "name:zho_x_preferred":[
        "\u9ad8\u53f0\u5b50"
    ],
    "wof:name":"Gaotaizi",
    "wof:placetype":"locality"
},
  "geometry": {"coordinates":[124.02800000000001,42.4858],"type":"Point"}
}