{
  "type": "Feature",
  "properties": {
    "gn:admin1_code":"3.0",
    "gn:asciiname":"Wujiakeng",
    "gn:country_code":"CN",
    "gn:dem":128,
    "gn:feature_class":"P",
    "gn:feature_code":"PPL",
    "gn:name":"Wujiakeng",
    "gn:population":0,
    "gn:timezone":"Asia/Shanghai",
    "iso:country":"CN",
    "name:und_x_variant":[
        "\u4f0d\u5bb6\u5751"
    ],
    "wof:name":"Wujiakeng",
    "wof:placetype":"locality"
},
  "geometry": {"coordinates":[114.63298,27.44656],"type":"Point"}
}