{
  "type": "Feature",
  "properties": {
    "gn:admin1_code":"32.0",
    "gn:asciiname":"Lizi",
    "gn:country_code":"CN",
    "gn:dem":2900,
    "gn:feature_class":"P",
    "gn:feature_code":"PPL",
    "gn:name":"Lizi",
    "gn:population":0,
    "gn:timezone":"Asia/Shanghai",
    "iso:country":"CN",
    "name:zho_x_preferred":[
        "\u674e\u5b50"
    ],
    "wof:name":"Lizi",
    "wof:placetype":"locality"
},
  "geometry": {"coordinates":[101.584,27.6971],"type":"Point"}
}