{
  "type": "Feature",
  "properties": {
    "gn:admin1_code":"4.0",
    "gn:asciiname":"Yinqiaocun",
    "gn:country_code":"CN",
    "gn:dem":10,
    "gn:feature_class":"P",
    "gn:feature_code":"PPL",
    "gn:name":"Yinqiaocun",
    "gn:population":0,
    "gn:timezone":"Asia/Shanghai",
    "iso:country":"CN",
    "name:und_x_variant":[
        "Yinqiao",
        "Yinqiaocun"
    ],
    "name:zho_x_preferred":[
        "\u6bb7\u6865"
    ],
    "name:zho_x_variant":[
        "\u6bb7\u6865\u6751"
    ],
    "wof:name":"Yinqiaocun",
    "wof:placetype":"locality"
},
  "geometry": {"coordinates":[119.21191,31.28027],"type":"Point"}
}