{
  "type": "Feature",
  "properties": {
    "gn:admin1_code":"32.0",
    "gn:asciiname":"Ji'ertong Zhongdui",
    "gn:country_code":"CN",
    "gn:dem":2101,
    "gn:feature_class":"P",
    "gn:feature_code":"PPL",
    "gn:name":"Ji\u2019ertong Zhongdui",
    "gn:population":0,
    "gn:timezone":"Asia/Shanghai",
    "iso:country":"CN",
    "name:und_x_variant":[
        "Ji\u2019ertong Zhongdui"
    ],
    "name:zho_x_preferred":[
        "\u5409\u5c14\u540c\u4ef2\u5806"
    ],
    "wof:name":"Ji'ertong Zhongdui",
    "wof:placetype":"locality"
},
  "geometry": {"coordinates":[100.26300000000001,28.1103],"type":"Point"}
}