{
  "type": "Feature",
  "properties": {
    "gn:admin1_code":"1.0",
    "gn:asciiname":"Daoshichongcun",
    "gn:country_code":"CN",
    "gn:dem":543,
    "gn:feature_class":"P",
    "gn:feature_code":"PPL",
    "gn:name":"Daoshichongcun",
    "gn:population":0,
    "gn:timezone":"Asia/Shanghai",
    "iso:country":"CN",
    "name:zho_x_preferred":[
        "\u9053\u58eb\u51b2\u6751"
    ],
    "wof:name":"Daoshichongcun",
    "wof:placetype":"locality"
},
  "geometry": {"coordinates":[116.02893,31.25711],"type":"Point"}
}