{
  "type": "Feature",
  "properties": {
    "gn:admin1_code":"15.0",
    "gn:asciiname":"Liudawa",
    "gn:country_code":"CN",
    "gn:dem":1145,
    "gn:feature_class":"P",
    "gn:feature_code":"PPL",
    "gn:name":"Liudawa",
    "gn:population":0,
    "gn:timezone":"Asia/Shanghai",
    "iso:country":"CN",
    "name:zho_x_preferred":[
        "\u5218\u5927\u6d3c"
    ],
    "wof:name":"Liudawa",
    "wof:placetype":"locality"
},
  "geometry": {"coordinates":[107.48399999999999,35.3185],"type":"Point"}
}