{
  "type": "Feature",
  "properties": {
    "gn:admin1_code":"07",
    "gn:asciiname":"Wen'ao",
    "gn:country_code":"CN",
    "gn:dem":28,
    "gn:feature_class":"P",
    "gn:feature_code":"PPL",
    "gn:name":"Wen\u2019ao",
    "gn:population":0,
    "gn:timezone":"Asia/Shanghai",
    "iso:country":"CN",
    "name:und_x_variant":[
        "Wen\u2019ao",
        "\u6587\u6fb3",
        "Fuying"
    ],
    "wof:name":"Wen'ao",
    "wof:placetype":"locality"
},
  "geometry": {"coordinates":[120.14348,26.57847000000001],"type":"Point"}
}