{
  "type": "Feature",
  "properties": {
    "gn:admin1_code":"7.0",
    "gn:asciiname":"Yuanqian",
    "gn:country_code":"CN",
    "gn:dem":71,
    "gn:feature_class":"P",
    "gn:feature_code":"PPL",
    "gn:name":"Yuanqian",
    "gn:population":0,
    "gn:timezone":"Asia/Shanghai",
    "iso:country":"CN",
    "name:zho_x_preferred":[
        "\u9662\u524d"
    ],
    "wof:name":"Yuanqian",
    "wof:placetype":"locality"
},
  "geometry": {"coordinates":[119.55758,26.98634],"type":"Point"}
}