{
  "type": "Feature",
  "properties": {
    "gn:admin1_code":"26.0",
    "gn:asciiname":"Yemaowa",
    "gn:country_code":"CN",
    "gn:dem":1166,
    "gn:feature_class":"P",
    "gn:feature_code":"PPL",
    "gn:name":"Yemaowa",
    "gn:population":0,
    "gn:timezone":"Asia/Shanghai",
    "iso:country":"CN",
    "name:zho_x_preferred":[
        "\u91ce\u732b\u6d3c"
    ],
    "wof:name":"Yemaowa",
    "wof:placetype":"locality"
},
  "geometry": {"coordinates":[109.93406,33.79058],"type":"Point"}
}