{
  "type": "Feature",
  "properties": {
    "gn:admin1_code":"11.0",
    "gn:asciiname":"Pingjia",
    "gn:country_code":"CN",
    "gn:dem":515,
    "gn:feature_class":"P",
    "gn:feature_code":"PPL",
    "gn:name":"Pingjia",
    "gn:population":0,
    "gn:timezone":"Asia/Shanghai",
    "iso:country":"CN",
    "name:zho_x_preferred":[
        "\u576a\u5bb6"
    ],
    "wof:name":"Pingjia",
    "wof:placetype":"locality"
},
  "geometry": {"coordinates":[110.0479,28.58246],"type":"Point"}
}