{
  "type": "Feature",
  "properties": {
    "gn:admin1_code":"26.0",
    "gn:asciiname":"Zhengyaoze",
    "gn:country_code":"CN",
    "gn:dem":1054,
    "gn:feature_class":"P",
    "gn:feature_code":"PPL",
    "gn:name":"Zhengyaoze",
    "gn:population":0,
    "gn:timezone":"Asia/Shanghai",
    "iso:country":"CN",
    "name:zho_x_preferred":[
        "\u90d1\u7a91\u5219"
    ],
    "wof:name":"Zhengyaoze",
    "wof:placetype":"locality"
},
  "geometry": {"coordinates":[109.3647,38.07823],"type":"Point"}
}