{
  "type": "Feature",
  "properties": {
    "gn:admin1_code":"26.0",
    "gn:asciiname":"Huanghepan",
    "gn:country_code":"CN",
    "gn:dem":1346,
    "gn:feature_class":"P",
    "gn:feature_code":"PPL",
    "gn:name":"Huanghepan",
    "gn:population":0,
    "gn:timezone":"Asia/Shanghai",
    "iso:country":"CN",
    "name:zho_x_preferred":[
        "\u9ec4\u6cb3\u7554"
    ],
    "wof:name":"Huanghepan",
    "wof:placetype":"locality"
},
  "geometry": {"coordinates":[108.79373,37.5667],"type":"Point"}
}