{
  "type": "Feature",
  "properties": {
    "gn:admin1_code":"19.0",
    "gn:asciiname":"Huanglingzi",
    "gn:country_code":"CN",
    "gn:dem":42,
    "gn:feature_class":"P",
    "gn:feature_code":"PPL",
    "gn:name":"Huanglingzi",
    "gn:population":0,
    "gn:timezone":"Asia/Shanghai",
    "iso:country":"CN",
    "name:und_x_variant":[
        "\u9ec4\u5cad\u5b50"
    ],
    "name:zho_x_preferred":[
        "\u9ec4\u5cad\u5b50"
    ],
    "wof:name":"Huanglingzi",
    "wof:placetype":"locality"
},
  "geometry": {"coordinates":[121.42641999999999,38.96802],"type":"Point"}
}