{
  "type": "Feature",
  "properties": {
    "gn:admin1_code":"19.0",
    "gn:asciiname":"Niujiaogoucun",
    "gn:country_code":"CN",
    "gn:dem":455,
    "gn:feature_class":"P",
    "gn:feature_code":"PPL",
    "gn:name":"Niujiaogoucun",
    "gn:population":0,
    "gn:timezone":"Asia/Shanghai",
    "iso:country":"CN",
    "name:zho_x_preferred":[
        "\u725b\u89d2\u6c9f\u6751"
    ],
    "wof:name":"Niujiaogoucun",
    "wof:placetype":"locality"
},
  "geometry": {"coordinates":[119.57859000000001,40.6216],"type":"Point"}
}