{
  "type": "Feature",
  "properties": {
    "gn:admin1_code":"11.0",
    "gn:asciiname":"Fuzhu",
    "gn:country_code":"CN",
    "gn:dem":460,
    "gn:feature_class":"P",
    "gn:feature_code":"PPL",
    "gn:name":"Fuzhu",
    "gn:population":0,
    "gn:timezone":"Asia/Shanghai",
    "iso:country":"CN",
    "name:und_x_variant":[
        "Fuzhuqiao"
    ],
    "name:zho_x_preferred":[
        "\u6276\u7af9"
    ],
    "wof:name":"Fuzhu",
    "wof:placetype":"locality"
},
  "geometry": {"coordinates":[110.9649,27.66403],"type":"Point"}
}