{
  "type": "Feature",
  "properties": {
    "gn:admin1_code":"29.0",
    "gn:asciiname":"Yuanwodang",
    "gn:country_code":"CN",
    "gn:dem":1875,
    "gn:feature_class":"P",
    "gn:feature_code":"PPL",
    "gn:name":"Yuanwodang",
    "gn:population":0,
    "gn:timezone":"Asia/Shanghai",
    "iso:country":"CN",
    "name:zho_x_preferred":[
        "\u5706\u7a9d\u6c39"
    ],
    "wof:name":"Yuanwodang",
    "wof:placetype":"locality"
},
  "geometry": {"coordinates":[104.717,27.4186],"type":"Point"}
}