{
  "type": "Feature",
  "properties": {
    "gn:admin1_code":"5.0",
    "gn:asciiname":"Dongbaotailai",
    "gn:country_code":"CN",
    "gn:dem":136,
    "gn:feature_class":"P",
    "gn:feature_code":"PPL",
    "gn:name":"Dongbaotailai",
    "gn:population":0,
    "gn:timezone":"Asia/Shanghai",
    "iso:country":"CN",
    "name:zho_x_preferred":[
        "\u4e1c\u62b1\u592a\u6765"
    ],
    "wof:name":"Dongbaotailai",
    "wof:placetype":"locality"
},
  "geometry": {"coordinates":[123.21975,45.93007],"type":"Point"}
}