{
  "type": "Feature",
  "properties": {
    "gn:admin1_code":"15.0",
    "gn:asciiname":"Jingjiaping",
    "gn:country_code":"CN",
    "gn:dem":1633,
    "gn:feature_class":"P",
    "gn:feature_code":"PPL",
    "gn:name":"Jingjiaping",
    "gn:population":0,
    "gn:timezone":"Asia/Shanghai",
    "iso:country":"CN",
    "name:zho_x_preferred":[
        "\u656c\u5bb6\u576a"
    ],
    "wof:name":"Jingjiaping",
    "wof:placetype":"locality"
},
  "geometry": {"coordinates":[104.084,36.0102],"type":"Point"}
}