{
  "type": "Feature",
  "properties": {
    "gn:admin1_code":"13.0",
    "gn:asciiname":"Quegenda Leke",
    "gn:country_code":"CN",
    "gn:dem":1970,
    "gn:feature_class":"P",
    "gn:feature_code":"PPL",
    "gn:name":"Quegenda Leke",
    "gn:population":0,
    "gn:timezone":"Asia/Shanghai",
    "iso:country":"CN",
    "name:zho_x_preferred":[
        "\u5374\u6839\u8fbe\u52d2\u514b"
    ],
    "wof:name":"Quegenda Leke",
    "wof:placetype":"locality"
},
  "geometry": {"coordinates":[80.15997,36.73538],"type":"Point"}
}