{
  "type": "Feature",
  "properties": {
    "gn:admin1_code":"26.0",
    "gn:asciiname":"Qiangjia Maocun",
    "gn:country_code":"CN",
    "gn:dem":925,
    "gn:feature_class":"P",
    "gn:feature_code":"PPL",
    "gn:name":"Qiangjia Maocun",
    "gn:population":0,
    "gn:timezone":"Asia/Shanghai",
    "iso:country":"CN",
    "name:zho_x_preferred":[
        "\u5f3a\u5bb6\u5cc1\u6751"
    ],
    "wof:name":"Qiangjia Maocun",
    "wof:placetype":"locality"
},
  "geometry": {"coordinates":[110.59699999999999,38.3291],"type":"Point"}
}