{
  "type": "Feature",
  "properties": {
    "gn:admin1_code":"10.0",
    "gn:asciiname":"Dalizhuang",
    "gn:country_code":"CN",
    "gn:dem":55,
    "gn:feature_class":"P",
    "gn:feature_code":"PPL",
    "gn:name":"Dalizhuang",
    "gn:population":0,
    "gn:timezone":"Asia/Shanghai",
    "iso:country":"CN",
    "name:zho_x_preferred":[
        "\u5927\u674e\u5e84"
    ],
    "wof:name":"Dalizhuang",
    "wof:placetype":"locality"
},
  "geometry": {"coordinates":[118.64694,39.96029],"type":"Point"}
}