{
  "type": "Feature",
  "properties": {
    "gn:admin1_code":"26.0",
    "gn:asciiname":"Jinbiancun",
    "gn:country_code":"CN",
    "gn:dem":1094,
    "gn:feature_class":"P",
    "gn:feature_code":"PPL",
    "gn:name":"Jinbiancun",
    "gn:population":0,
    "gn:timezone":"Asia/Shanghai",
    "iso:country":"CN",
    "name:zho_x_preferred":[
        "\u91d1\u782d\u6751"
    ],
    "wof:name":"Jinbiancun",
    "wof:placetype":"locality"
},
  "geometry": {"coordinates":[109.68103000000001,36.33986],"type":"Point"}
}