{
  "type": "Feature",
  "properties": {
    "gn:admin1_code":"26.0",
    "gn:asciiname":"Maobuzecun",
    "gn:country_code":"CN",
    "gn:dem":1210,
    "gn:feature_class":"P",
    "gn:feature_code":"PPL",
    "gn:name":"Maobuzecun",
    "gn:population":0,
    "gn:timezone":"Asia/Shanghai",
    "iso:country":"CN",
    "name:zho_x_preferred":[
        "\u6bdb\u5821\u5219\u6751"
    ],
    "wof:name":"Maobuzecun",
    "wof:placetype":"locality"
},
  "geometry": {"coordinates":[109.29519000000001,36.50477],"type":"Point"}
}