{
  "type": "Feature",
  "properties": {
    "gn:admin1_code":"3.0",
    "gn:asciiname":"Lingbeitan",
    "gn:country_code":"CN",
    "gn:dem":506,
    "gn:feature_class":"P",
    "gn:feature_code":"PPL",
    "gn:name":"Lingbeitan",
    "gn:population":0,
    "gn:timezone":"Asia/Shanghai",
    "iso:country":"CN",
    "name:zho_x_preferred":[
        "\u5cad\u80cc\u6ee9"
    ],
    "wof:name":"Lingbeitan",
    "wof:placetype":"locality"
},
  "geometry": {"coordinates":[117.63088999999999,27.91224],"type":"Point"}
}