{
  "type": "Feature",
  "properties": {
    "gn:admin1_code":"11.0",
    "gn:asciiname":"Maocaojie",
    "gn:country_code":"CN",
    "gn:dem":34,
    "gn:feature_class":"P",
    "gn:feature_code":"PPL",
    "gn:name":"Maocaojie",
    "gn:population":0,
    "gn:timezone":"Asia/Shanghai",
    "iso:country":"CN",
    "name:zho_x_preferred":[
        "Maocaojie"
    ],
    "name:zho_x_variant":[
        "\u8305\u8349\u8857",
        "\u8305\u8349\u8857\u9547"
    ],
    "wof:name":"Maocaojie",
    "wof:placetype":"locality"
},
  "geometry": {"coordinates":[111.92643,29.70061],"type":"Point"}
}