{
  "type": "Feature",
  "properties": {
    "gn:admin1_code":"25",
    "gn:asciiname":"Dayuegezhuang",
    "gn:country_code":"CN",
    "gn:dem":102,
    "gn:feature_class":"P",
    "gn:feature_code":"PPL",
    "gn:name":"Dayuegezhuang",
    "gn:population":0,
    "gn:timezone":"Asia/Shanghai",
    "iso:country":"CN",
    "name:zho_x_preferred":[
        "\u5927\u5cb3\u6208\u5e84"
    ],
    "wof:name":"Dayuegezhuang",
    "wof:placetype":"locality"
},
  "geometry": {"coordinates":[119.185,36.1046],"type":"Point"}
}