{
  "type": "Feature",
  "properties": {
    "gn:admin1_code":"29.0",
    "gn:asciiname":"Banglang",
    "gn:country_code":"CN",
    "gn:dem":1524,
    "gn:feature_class":"P",
    "gn:feature_code":"PPL",
    "gn:name":"Banglang",
    "gn:population":0,
    "gn:timezone":"Asia/Shanghai",
    "iso:country":"CN",
    "name:zho_x_preferred":[
        "\u90a6\u6d6a"
    ],
    "wof:name":"Banglang",
    "wof:placetype":"locality"
},
  "geometry": {"coordinates":[98.1262,25.1992],"type":"Point"}
}