{
  "type": "Feature",
  "properties": {
    "gn:admin1_code":"16.0",
    "gn:asciiname":"Anma",
    "gn:country_code":"CN",
    "gn:dem":139,
    "gn:feature_class":"P",
    "gn:feature_code":"PPL",
    "gn:name":"Anma",
    "gn:population":0,
    "gn:timezone":"Asia/Shanghai",
    "iso:country":"CN",
    "name:ara_x_preferred":[
        "\u0636\u063a\u0637 \u0625\u0628\u0631\u064a"
    ],
    "name:fra_x_preferred":[
        "Anma"
    ],
    "name:kor_x_preferred":[
        "\uc548\ub9c8"
    ],
    "name:por_x_preferred":[
        "Anma"
    ],
    "name:zho_x_preferred":[
        "\u5b89\u9a6c"
    ],
    "wof:name":"Anma",
    "wof:placetype":"locality"
},
  "geometry": {"coordinates":[107.111,22.0957],"type":"Point"}
}