{
  "type": "Feature",
  "properties": {
    "gn:admin1_code":"11.0",
    "gn:asciiname":"Xiaowangdong",
    "gn:country_code":"CN",
    "gn:dem":735,
    "gn:feature_class":"P",
    "gn:feature_code":"PPL",
    "gn:name":"Xiaowangdong",
    "gn:population":0,
    "gn:timezone":"Asia/Shanghai",
    "iso:country":"CN",
    "name:zho_x_preferred":[
        "\u5c0f\u738b\u6d1e"
    ],
    "wof:name":"Xiaowangdong",
    "wof:placetype":"locality"
},
  "geometry": {"coordinates":[112.49281000000001,25.15438],"type":"Point"}
}