{
  "type": "Feature",
  "properties": {
    "gn:admin1_code":"14.0",
    "gn:asciiname":"Anguo",
    "gn:country_code":"CN",
    "gn:dem":4155,
    "gn:feature_class":"P",
    "gn:feature_code":"PPL",
    "gn:name":"Anguo",
    "gn:population":0,
    "gn:timezone":"Asia/Urumqi",
    "iso:country":"CN",
    "name:zho_x_preferred":[
        "\u5b89\u679c"
    ],
    "wof:name":"Anguo",
    "wof:placetype":"locality"
},
  "geometry": {"coordinates":[97.43346,30.22489],"type":"Point"}
}