{
  "type": "Feature",
  "properties": {
    "gn:admin1_code":"14.0",
    "gn:asciiname":"Anguo",
    "gn:country_code":"CN",
    "gn:dem":4155,
    "gn:feature_class":"P",
    "gn:feature_code":"PPL",
    "gn:name":"Anguo",
    "gn:population":0,
    "gn:timezone":"Asia/Urumqi",
    "iso:country":"CN",
    "name:ara_x_preferred":[
        "\u0623\u0646\u063a\u0648\u0648"
    ],
    "name:deu_x_preferred":[
        "Anguo"
    ],
    "name:fra_x_preferred":[
        "Anguo"
    ],
    "name:ita_x_preferred":[
        "Anguo"
    ],
    "name:jpn_x_preferred":[
        "\u5b89\u56fd\u5e02"
    ],
    "name:kik_x_preferred":[
        "Anguo"
    ],
    "name:kor_x_preferred":[
        "\uc548\uad88\uc2dc"
    ],
    "name:nno_x_preferred":[
        "Anguo"
    ],
    "name:nor_x_preferred":[
        "Anguo"
    ],
    "name:pam_x_preferred":[
        "Anguo"
    ],
    "name:rus_x_preferred":[
        "\u0410\u043d\u044c\u0433\u043e"
    ],
    "name:swe_x_preferred":[
        "Anguo"
    ],
    "name:urd_x_preferred":[
        "\u0627\u0646\u06af\u0648\u0648"
    ],
    "name:vie_x_preferred":[
        "An Qu\u1ed1c"
    ],
    "name:zho_x_preferred":[
        "\u5b89\u679c"
    ],
    "name:zho_x_variant":[
        "\u5b89\u56fd\u5e02"
    ],
    "wof:name":"Anguo",
    "wof:placetype":"locality"
},
  "geometry": {"coordinates":[97.43346,30.22489],"type":"Point"}
}