{
  "type": "Feature",
  "properties": {
    "gn:admin1_code":"19.0",
    "gn:asciiname":"Guanyin Gexia",
    "gn:country_code":"CN",
    "gn:dem":121,
    "gn:feature_class":"P",
    "gn:feature_code":"PPL",
    "gn:name":"Guanyin Gexia",
    "gn:population":0,
    "gn:timezone":"Asia/Shanghai",
    "iso:country":"CN",
    "name:zho_x_preferred":[
        "\u89c2\u97f3\u9601\u4e0b"
    ],
    "wof:name":"Guanyin Gexia",
    "wof:placetype":"locality"
},
  "geometry": {"coordinates":[121.80800000000001,39.106],"type":"Point"}
}