{
  "type": "Feature",
  "properties": {
    "gn:admin1_code":"12.0",
    "gn:asciiname":"Luomatan",
    "gn:country_code":"CN",
    "gn:dem":588,
    "gn:feature_class":"P",
    "gn:feature_code":"PPL",
    "gn:name":"Luomatan",
    "gn:population":0,
    "gn:timezone":"Asia/Shanghai",
    "iso:country":"CN",
    "name:zho_x_preferred":[
        "\u843d\u9a6c\u6ee9"
    ],
    "wof:name":"Luomatan",
    "wof:placetype":"locality"
},
  "geometry": {"coordinates":[108.95309,29.64951],"type":"Point"}
}