{
  "type": "Feature",
  "properties": {
    "gn:admin1_code":"7.0",
    "gn:asciiname":"Chenkeng",
    "gn:country_code":"CN",
    "gn:dem":127,
    "gn:feature_class":"P",
    "gn:feature_code":"PPL",
    "gn:name":"Chenkeng",
    "gn:population":0,
    "gn:timezone":"Asia/Shanghai",
    "iso:country":"CN",
    "name:und_x_variant":[
        "\u9648\u5751"
    ],
    "name:zho_x_preferred":[
        "\u9648\u5751"
    ],
    "wof:name":"Chenkeng",
    "wof:placetype":"locality"
},
  "geometry": {"coordinates":[118.26582999999999,26.52779],"type":"Point"}
}