{
  "type": "Feature",
  "properties": {
    "gn:admin1_code":"12.0",
    "gn:asciiname":"Liaojiahu",
    "gn:country_code":"CN",
    "gn:dem":1056,
    "gn:feature_class":"P",
    "gn:feature_code":"PPL",
    "gn:name":"Liaojiahu",
    "gn:population":0,
    "gn:timezone":"Asia/Shanghai",
    "iso:country":"CN",
    "name:zho_x_preferred":[
        "\u5ed6\u5bb6\u6e56"
    ],
    "wof:name":"Liaojiahu",
    "wof:placetype":"locality"
},
  "geometry": {"coordinates":[111.24491999999999,31.70685],"type":"Point"}
}