{
  "type": "Feature",
  "properties": {
    "gn:admin1_code":"18",
    "gn:asciiname":"Wangdaliao",
    "gn:country_code":"CN",
    "gn:dem":1115,
    "gn:feature_class":"P",
    "gn:feature_code":"PPL",
    "gn:name":"Wangdaliao",
    "gn:population":0,
    "gn:timezone":"Asia/Shanghai",
    "iso:country":"CN",
    "name:zho_x_preferred":[
        "\u738b\u5927\u8fbd"
    ],
    "wof:name":"Wangdaliao",
    "wof:placetype":"locality"
},
  "geometry": {"coordinates":[106.503,27.8916],"type":"Point"}
}