{
  "type": "Feature",
  "properties": {
    "gn:country":"CN",
    "gn:fcode":"PPL",
    "gn:pop":60202,
    "iso:country":"CN",
    "name:unk_x_variant":[
        "Ju-nan"
    ],
    "name:zho_x_preferred":[
        "\u6c5d\u5b81"
    ],
    "qs:name":"\u6c5d\u5357",
    "qs:name_adm0":"\u4e2d\u570b",
    "qs:name_adm1":"\u6cb3\u5357\u7701",
    "qs:photos_9r":0,
    "qs:photos_sr":0,
    "qs:placetype":"Town",
    "qs:pop_sr":"8",
    "wd:wordcount":434,
    "wof:name":"\u6c5d\u5357",
    "wof:placetype":"locality",
    "wof:population":60202
},
  "geometry": {"coordinates":[114.35417,33.00111],"type":"Point"}
}