{
  "type": "Feature",
  "properties": {
    "gn:admin1_code":"11.0",
    "gn:asciiname":"Dazhouzi",
    "gn:country_code":"CN",
    "gn:dem":28,
    "gn:feature_class":"P",
    "gn:feature_code":"PPL",
    "gn:name":"Dazhouzi",
    "gn:population":0,
    "gn:timezone":"Asia/Shanghai",
    "iso:country":"CN",
    "name:zho_x_preferred":[
        "\u5927\u6d32\u5b50"
    ],
    "wof:name":"Dazhouzi",
    "wof:placetype":"locality"
},
  "geometry": {"coordinates":[112.61202,29.03642],"type":"Point"}
}