{
  "type": "Feature",
  "properties": {
    "gn:admin1_code":"02",
    "gn:asciiname":"Jingzhucun",
    "gn:country_code":"CN",
    "gn:dem":54,
    "gn:feature_class":"P",
    "gn:feature_code":"PPL",
    "gn:name":"Jingzhucun",
    "gn:population":0,
    "gn:timezone":"Asia/Shanghai",
    "iso:country":"CN",
    "name:und_x_variant":[
        "Ching-t\u2019ou-chu",
        "Jingzhu",
        "Jingzhucun"
    ],
    "name:zho_x_preferred":[
        "\u4e95\u6731\u6751"
    ],
    "wof:name":"Jingzhucun",
    "wof:placetype":"locality"
},
  "geometry": {"coordinates":[121.21192000000001,28.49781],"type":"Point"}
}