{
  "type": "Feature",
  "properties": {
    "gn:admin1_code":"25.0",
    "gn:asciiname":"Minfengcun",
    "gn:country_code":"CN",
    "gn:dem":7,
    "gn:feature_class":"P",
    "gn:feature_code":"PPL",
    "gn:name":"Minfengcun",
    "gn:population":0,
    "gn:timezone":"Asia/Shanghai",
    "iso:country":"CN",
    "name:und_x_variant":[
        "Hsi-shuang-ho",
        "Minfeng",
        "Xishuanghe",
        "Min-feng-chen",
        "Kenli",
        "Minfengcun"
    ],
    "name:zho_x_preferred":[
        "\u6c11\u4e30"
    ],
    "name:zho_x_variant":[
        "\u6c11\u4e30\u6751"
    ],
    "wof:name":"Minfengcun",
    "wof:placetype":"locality"
},
  "geometry": {"coordinates":[118.57256,37.57741],"type":"Point"}
}