{
  "type": "Feature",
  "properties": {
    "gn:admin1_code":"12.0",
    "gn:asciiname":"Hanhu Lushan",
    "gn:country_code":"CN",
    "gn:dem":27,
    "gn:feature_class":"P",
    "gn:feature_code":"PPL",
    "gn:name":"Hanhu Lushan",
    "gn:population":0,
    "gn:timezone":"Asia/Shanghai",
    "iso:country":"CN",
    "name:zho_x_preferred":[
        "\u97e9\u846b\u82a6\u5c71"
    ],
    "wof:name":"Hanhu Lushan",
    "wof:placetype":"locality"
},
  "geometry": {"coordinates":[115.37264999999999,30.29557],"type":"Point"}
}