{
  "type": "Feature",
  "properties": {
    "gn:admin1_code":"24.0",
    "gn:asciiname":"Huolianwa",
    "gn:country_code":"CN",
    "gn:dem":1373,
    "gn:feature_class":"P",
    "gn:feature_code":"PPL",
    "gn:name":"Huolianwa",
    "gn:population":0,
    "gn:timezone":"Asia/Shanghai",
    "iso:country":"CN",
    "name:zho_x_preferred":[
        "\u706b\u70bc\u7a8a"
    ],
    "wof:name":"Huolianwa",
    "wof:placetype":"locality"
},
  "geometry": {"coordinates":[111.85625,38.29129],"type":"Point"}
}