{
  "type": "Feature",
  "properties": {
    "gn:admin1_code":"29.0",
    "gn:asciiname":"Heixicun",
    "gn:country_code":"CN",
    "gn:dem":637,
    "gn:feature_class":"P",
    "gn:feature_code":"PPL",
    "gn:name":"Heixicun",
    "gn:population":0,
    "gn:timezone":"Asia/Shanghai",
    "iso:country":"CN",
    "name:zho_x_preferred":[
        "\u9ed1\u559c\u6751"
    ],
    "wof:name":"Heixicun",
    "wof:placetype":"locality"
},
  "geometry": {"coordinates":[104.16,28.0162],"type":"Point"}
}