{
  "type": "Feature",
  "properties": {
    "gn:admin1_code":"12.0",
    "gn:asciiname":"Balipeng",
    "gn:country_code":"CN",
    "gn:dem":45,
    "gn:feature_class":"P",
    "gn:feature_code":"PPL",
    "gn:name":"Balipeng",
    "gn:population":0,
    "gn:timezone":"Asia/Shanghai",
    "iso:country":"CN",
    "name:und_x_variant":[
        "\u516b\u91cc\u68da"
    ],
    "wof:name":"Balipeng",
    "wof:placetype":"locality"
},
  "geometry": {"coordinates":[114.25608,30.89837],"type":"Point"}
}