{
  "type": "Feature",
  "properties": {
    "gn:admin1_code":"30",
    "gn:asciiname":"Huangang",
    "gn:country_code":"CN",
    "gn:dem":19,
    "gn:feature_class":"P",
    "gn:feature_code":"PPL",
    "gn:name":"Huangang",
    "gn:population":0,
    "gn:timezone":"Asia/Shanghai",
    "iso:country":"CN",
    "name:und_x_variant":[
        "Henggang",
        "Huangang"
    ],
    "wof:name":"Huangang",
    "wof:placetype":"locality"
},
  "geometry": {"coordinates":[113.71177,22.92809],"type":"Point"}
}