{
  "type": "Feature",
  "properties": {
    "gn:admin1_code":"12.0",
    "gn:asciiname":"Sifang Taizi",
    "gn:country_code":"CN",
    "gn:dem":66,
    "gn:feature_class":"P",
    "gn:feature_code":"PPL",
    "gn:name":"Sifang Taizi",
    "gn:population":0,
    "gn:timezone":"Asia/Shanghai",
    "iso:country":"CN",
    "name:zho_x_preferred":[
        "Sifang Taizi"
    ],
    "name:zho_x_variant":[
        "\u56db\u65b9\u53f0\u5b50"
    ],
    "wof:name":"Sifang Taizi",
    "wof:placetype":"locality"
},
  "geometry": {"coordinates":[111.85781,30.73543],"type":"Point"}
}