{
  "type": "Feature",
  "properties": {
    "gn:admin1_code":"11.0",
    "gn:asciiname":"Tianhexian",
    "gn:country_code":"CN",
    "gn:dem":866,
    "gn:feature_class":"P",
    "gn:feature_code":"PPL",
    "gn:name":"Tianhexian",
    "gn:population":0,
    "gn:timezone":"Asia/Shanghai",
    "iso:country":"CN",
    "name:zho_x_preferred":[
        "\u5929\u548c\u5f26"
    ],
    "wof:name":"Tianhexian",
    "wof:placetype":"locality"
},
  "geometry": {"coordinates":[113.76746,27.0826],"type":"Point"}
}