{
  "type": "Feature",
  "properties": {
    "gn:admin1_code":"7.0",
    "gn:asciiname":"Xiadi",
    "gn:country_code":"CN",
    "gn:dem":855,
    "gn:feature_class":"P",
    "gn:feature_code":"PPL",
    "gn:name":"Xiadi",
    "gn:population":0,
    "gn:timezone":"Asia/Shanghai",
    "iso:country":"CN",
    "name:zho_x_preferred":[
        "\u53a6\u5730"
    ],
    "wof:name":"Xiadi",
    "wof:placetype":"locality"
},
  "geometry": {"coordinates":[118.92109000000001,26.89644],"type":"Point"}
}