{
  "type": "Feature",
  "properties": {
    "gn:admin1_code":"19.0",
    "gn:asciiname":"Xintuncun",
    "gn:country_code":"CN",
    "gn:dem":5,
    "gn:feature_class":"P",
    "gn:feature_code":"PPL",
    "gn:name":"Xintuncun",
    "gn:population":0,
    "gn:timezone":"Asia/Shanghai",
    "iso:country":"CN",
    "name:zho_x_preferred":[
        "\u65b0\u5c6f\u6751"
    ],
    "wof:name":"Xintuncun",
    "wof:placetype":"locality"
},
  "geometry": {"coordinates":[122.15479000000001,40.85537],"type":"Point"}
}