{
  "type": "Feature",
  "properties": {
    "gn:admin1_code":"29.0",
    "gn:asciiname":"Puzhigou",
    "gn:country_code":"CN",
    "gn:dem":1117,
    "gn:feature_class":"P",
    "gn:feature_code":"PPL",
    "gn:name":"Puzhigou",
    "gn:population":0,
    "gn:timezone":"Asia/Shanghai",
    "iso:country":"CN",
    "name:zho_x_preferred":[
        "\u84b2\u829d\u6c9f"
    ],
    "wof:name":"Puzhigou",
    "wof:placetype":"locality"
},
  "geometry": {"coordinates":[103.965,27.7856],"type":"Point"}
}