{
  "type": "Feature",
  "properties": {
    "gn:admin1_code":"8.0",
    "gn:asciiname":"Gaochao",
    "gn:country_code":"CN",
    "gn:dem":239,
    "gn:feature_class":"P",
    "gn:feature_code":"PPL",
    "gn:name":"Gaochao",
    "gn:population":0,
    "gn:timezone":"Asia/Shanghai",
    "iso:country":"CN",
    "name:zho_x_preferred":[
        "\u9ad8\u6f6e"
    ],
    "wof:name":"Gaochao",
    "wof:placetype":"locality"
},
  "geometry": {"coordinates":[128.89989,47.78964000000001],"type":"Point"}
}