{
  "type": "Feature",
  "properties": {
    "gn:admin1_code":"32.0",
    "gn:asciiname":"Baiyunchang",
    "gn:country_code":"CN",
    "gn:dem":333,
    "gn:feature_class":"P",
    "gn:feature_code":"PPL",
    "gn:name":"Baiyunchang",
    "gn:population":0,
    "gn:timezone":"Asia/Shanghai",
    "iso:country":"CN",
    "name:zho_x_preferred":[
        "\u767d\u4e91\u573a"
    ],
    "wof:name":"Baiyunchang",
    "wof:placetype":"locality"
},
  "geometry": {"coordinates":[105.69996,28.94603],"type":"Point"}
}