{
  "type": "Feature",
  "properties": {
    "gn:admin1_code":"29.0",
    "gn:asciiname":"Chashanhe",
    "gn:country_code":"CN",
    "gn:dem":1936,
    "gn:feature_class":"P",
    "gn:feature_code":"PPL",
    "gn:name":"Chashanhe",
    "gn:population":0,
    "gn:timezone":"Asia/Shanghai",
    "iso:country":"CN",
    "name:zho_x_preferred":[
        "\u8336\u5c71\u6cb3"
    ],
    "wof:name":"Chashanhe",
    "wof:placetype":"locality"
},
  "geometry": {"coordinates":[98.53959999999999,25.6712],"type":"Point"}
}