{
  "type": "Feature",
  "properties": {
    "gn:admin1_code":"30",
    "gn:asciiname":"Chizhukeng",
    "gn:country_code":"CN",
    "gn:dem":60,
    "gn:feature_class":"P",
    "gn:feature_code":"PPL",
    "gn:name":"Chizhukeng",
    "gn:population":0,
    "gn:timezone":"Asia/Urumqi",
    "iso:country":"CN",
    "name:zho_x_preferred":[
        "\u8d64\u7af9\u5751"
    ],
    "wof:name":"Chizhukeng",
    "wof:placetype":"locality"
},
  "geometry": {"coordinates":[110.39698,21.68881],"type":"Point"}
}