{
  "type": "Feature",
  "properties": {
    "gn:admin1_code":"16",
    "gn:asciiname":"Panyan",
    "gn:country_code":"CN",
    "gn:dem":162,
    "gn:feature_class":"P",
    "gn:feature_code":"PPL",
    "gn:name":"Panyan",
    "gn:population":0,
    "gn:timezone":"Asia/Shanghai",
    "iso:country":"CN",
    "name:zho_x_preferred":[
        "\u76d8\u5ca9"
    ],
    "wof:name":"Panyan",
    "wof:placetype":"locality"
},
  "geometry": {"coordinates":[110.77500000000001,24.8843],"type":"Point"}
}