{
  "type": "Feature",
  "properties": {
    "gn:admin1_code":"16.0",
    "gn:asciiname":"Gongwangling",
    "gn:country_code":"CN",
    "gn:dem":386,
    "gn:feature_class":"P",
    "gn:feature_code":"PPL",
    "gn:name":"Gongwangling",
    "gn:population":0,
    "gn:timezone":"Asia/Shanghai",
    "iso:country":"CN",
    "name:zho_x_preferred":[
        "\u516c\u671b\u5cad"
    ],
    "wof:name":"Gongwangling",
    "wof:placetype":"locality"
},
  "geometry": {"coordinates":[111.259,24.1178],"type":"Point"}
}