{
  "type": "Feature",
  "properties": {
    "gn:admin1_code":"18",
    "gn:asciiname":"Sitangxi",
    "gn:country_code":"CN",
    "gn:dem":639,
    "gn:feature_class":"P",
    "gn:feature_code":"PPL",
    "gn:name":"Sitangxi",
    "gn:population":0,
    "gn:timezone":"Asia/Shanghai",
    "iso:country":"CN",
    "name:zho_x_preferred":[
        "\u56db\u5858\u6eaa"
    ],
    "wof:name":"Sitangxi",
    "wof:placetype":"locality"
},
  "geometry": {"coordinates":[108.218,29.0462],"type":"Point"}
}