{
  "type": "Feature",
  "properties": {
    "gn:admin1_code":"8.0",
    "gn:asciiname":"Zhangxiong",
    "gn:country_code":"CN",
    "gn:dem":165,
    "gn:feature_class":"P",
    "gn:feature_code":"PPLA4",
    "gn:name":"Zhangxiong",
    "gn:population":0,
    "gn:timezone":"Asia/Shanghai",
    "iso:country":"CN",
    "name:und_x_variant":[
        "Zhangxiong Zhen"
    ],
    "name:zho_x_preferred":[
        "\u5f20\u96c4"
    ],
    "name:zho_x_variant":[
        "\u5f20\u96c4\u9547"
    ],
    "wof:name":"Zhangxiong",
    "wof:placetype":"locality"
},
  "geometry": {"coordinates":[127.002,47.05997],"type":"Point"}
}