{
  "type": "Feature",
  "properties": {
    "gn:admin1_code":"04",
    "gn:asciiname":"Jincheng",
    "gn:country_code":"CN",
    "gn:dem":13,
    "gn:feature_class":"P",
    "gn:feature_code":"PPLA3",
    "gn:name":"Jincheng",
    "gn:population":0,
    "gn:timezone":"Asia/Shanghai",
    "iso:country":"CN",
    "name:und_x_variant":[
        "Jincheng Zhen",
        "Jintan Shi"
    ],
    "name:zho_x_preferred":[
        "\u91d1\u57ce"
    ],
    "name:zho_x_variant":[
        "\u91d1\u57ce\u9547",
        "\u91d1\u575b\u5e02"
    ],
    "wof:name":"Jincheng",
    "wof:placetype":"locality"
},
  "geometry": {"coordinates":[119.57416000000001,31.74422],"type":"Point"}
}