{
  "type": "Feature",
  "properties": {
    "gn:admin1_code":"04",
    "gn:asciiname":"Jincheng",
    "gn:country_code":"CN",
    "gn:dem":13,
    "gn:feature_class":"P",
    "gn:feature_code":"PPLA3",
    "gn:name":"Jincheng",
    "gn:population":0,
    "gn:timezone":"Asia/Shanghai",
    "iso:country":"CN",
    "name:ara_x_preferred":[
        "\u062c\u064a\u0646\u062a\u0634\u0646\u063a"
    ],
    "name:bul_x_preferred":[
        "\u0414\u0437\u0438\u043d\u0447\u044a\u043d"
    ],
    "name:cdo_x_preferred":[
        "C\u00e9ng-si\u00e0ng"
    ],
    "name:ceb_x_preferred":[
        "Jincheng"
    ],
    "name:dan_x_preferred":[
        "Jincheng"
    ],
    "name:deu_x_preferred":[
        "Jincheng"
    ],
    "name:eus_x_preferred":[
        "Jincheng"
    ],
    "name:fas_x_preferred":[
        "\u062c\u06cc\u0646\u0686\u0646"
    ],
    "name:fin_x_preferred":[
        "Jincheng"
    ],
    "name:fra_x_preferred":[
        "Jincheng"
    ],
    "name:heb_x_preferred":[
        "\u05d2'\u05d9\u05e0\u05e6'\u05e0\u05d2"
    ],
    "name:hun_x_preferred":[
        "Jincheng"
    ],
    "name:ind_x_preferred":[
        "Jincheng"
    ],
    "name:ita_x_preferred":[
        "Jincheng"
    ],
    "name:jpn_x_preferred":[
        "\u664b\u57ce\u5e02"
    ],
    "name:kik_x_preferred":[
        "Jincheng"
    ],
    "name:kor_x_preferred":[
        "\uc9c4\uccad\uc2dc"
    ],
    "name:mlg_x_preferred":[
        "Jincheng"
    ],
    "name:nld_x_preferred":[
        "Jincheng"
    ],
    "name:nno_x_preferred":[
        "Jincheng"
    ],
    "name:nor_x_preferred":[
        "Jincheng"
    ],
    "name:pol_x_preferred":[
        "Jincheng"
    ],
    "name:rus_x_preferred":[
        "\u0426\u0437\u0438\u043d\u044c\u0447\u044d\u043d"
    ],
    "name:spa_x_preferred":[
        "Jincheng"
    ],
    "name:srp_x_preferred":[
        "\u0402\u0438\u043d\u0447\u0435\u043d\u0433"
    ],
    "name:swe_x_preferred":[
        "Jincheng"
    ],
    "name:tur_x_preferred":[
        "Jincheng"
    ],
    "name:und_x_variant":[
        "Jincheng Zhen",
        "Jintan Shi"
    ],
    "name:urd_x_preferred":[
        "\u062c\u0646\u0686\u06cc\u0646\u06af"
    ],
    "name:vie_x_preferred":[
        "T\u1ea5n Th\u00e0nh"
    ],
    "name:war_x_preferred":[
        "Jincheng"
    ],
    "name:wuu_x_preferred":[
        "\u664b\u57ce\u5e02"
    ],
    "name:zho_x_preferred":[
        "\u91d1\u57ce"
    ],
    "name:zho_x_variant":[
        "\u91d1\u57ce\u9547",
        "\u91d1\u575b\u5e02",
        "\u664b\u57ce\u5e02"
    ],
    "wof:name":"Jincheng",
    "wof:placetype":"locality"
},
  "geometry": {"coordinates":[119.57416000000001,31.74422],"type":"Point"}
}