{
  "type": "Feature",
  "properties": {
    "gn:admin1_code":"30.0",
    "gn:asciiname":"Shishan",
    "gn:country_code":"CN",
    "gn:dem":260,
    "gn:feature_class":"P",
    "gn:feature_code":"PPL",
    "gn:name":"Shishan",
    "gn:population":0,
    "gn:timezone":"Asia/Urumqi",
    "iso:country":"CN",
    "name:zho_x_preferred":[
        "\u72ee\u5c71"
    ],
    "wof:name":"Shishan",
    "wof:placetype":"locality"
},
  "geometry": {"coordinates":[110.99669,22.49629],"type":"Point"}
}