{
  "type": "Feature",
  "properties": {
    "gn:admin1_code":"16.0",
    "gn:asciiname":"Xiaodong",
    "gn:country_code":"CN",
    "gn:dem":463,
    "gn:feature_class":"P",
    "gn:feature_code":"PPL",
    "gn:name":"Xiaodong",
    "gn:population":0,
    "gn:timezone":"Asia/Shanghai",
    "iso:country":"CN",
    "name:zho_x_preferred":[
        "\u5c0f\u5cd2"
    ],
    "wof:name":"Xiaodong",
    "wof:placetype":"locality"
},
  "geometry": {"coordinates":[107.857,24.7562],"type":"Point"}
}