{
  "type": "Feature",
  "properties": {
    "gn:admin1_code":"12.0",
    "gn:asciiname":"Paomagang",
    "gn:country_code":"CN",
    "gn:dem":275,
    "gn:feature_class":"P",
    "gn:feature_code":"PPL",
    "gn:name":"Paomagang",
    "gn:population":0,
    "gn:timezone":"Asia/Shanghai",
    "iso:country":"CN",
    "name:zho_x_preferred":[
        "Paomagang"
    ],
    "name:zho_x_variant":[
        "\u8dd1\u9a6c\u5c97"
    ],
    "wof:name":"Paomagang",
    "wof:placetype":"locality"
},
  "geometry": {"coordinates":[111.50104,30.82434000000001],"type":"Point"}
}