{
  "type": "Feature",
  "properties": {
    "gn:admin1_code":"19.0",
    "gn:asciiname":"Guangdeyong",
    "gn:country_code":"CN",
    "gn:dem":108,
    "gn:feature_class":"P",
    "gn:feature_code":"PPL",
    "gn:name":"Guangdeyong",
    "gn:population":0,
    "gn:timezone":"Asia/Shanghai",
    "iso:country":"CN",
    "name:zho_x_preferred":[
        "\u5e7f\u5fb7\u6c38"
    ],
    "wof:name":"Guangdeyong",
    "wof:placetype":"locality"
},
  "geometry": {"coordinates":[122.348,42.4522],"type":"Point"}
}