{
  "type": "Feature",
  "properties": {
    "iso:country":"CN",
    "ne:ADM0CAP":0.0,
    "ne:ADM0NAME":"China",
    "ne:ADM0_A3":"CHN",
    "ne:ADM1NAME":"Anhui",
    "ne:ADMIN1_COD":0,
    "ne:CAPALT":0,
    "ne:CHANGED":0,
    "ne:CHECKME":0,
    "ne:COMPARE":0,
    "ne:DIFFASCII":0,
    "ne:ELEVATION":0.0,
    "ne:FEATURECLA":"Populated place",
    "ne:GEONAMEID":-1,
    "ne:GEONAMESNO":"No GeoNames match due to small population, not in GeoNames, or poor NEV placement.",
    "ne:GN_POP":0,
    "ne:GTOPO30":0.0,
    "ne:ISO_A2":"CN",
    "ne:LABELRANK":1,
    "ne:LATITUDE":31.7304,
    "ne:LONGITUDE":118.480044,
    "ne:LS_MATCH":1,
    "ne:LS_NAME":"Maanshan",
    "ne:MAX_AREAKM":211.0,
    "ne:MAX_AREAMI":81.0,
    "ne:MAX_BBXMAX":118.666667,
    "ne:MAX_BBXMIN":118.441667,
    "ne:MAX_BBYMAX":31.8,
    "ne:MAX_BBYMIN":31.527945,
    "ne:MAX_NATSCA":20.0,
    "ne:MAX_PERKM":223.0,
    "ne:MAX_PERMI":138.0,
    "ne:MAX_POP10":737428,
    "ne:MAX_POP20":737428,
    "ne:MAX_POP300":0,
    "ne:MAX_POP310":0,
    "ne:MAX_POP50":0,
    "ne:MEAN_BBXC":118.525101,
    "ne:MEAN_BBYC":31.666506,
    "ne:MEGACITY":0,
    "ne:MIN_AREAKM":211.0,
    "ne:MIN_AREAMI":81.0,
    "ne:MIN_BBXMAX":118.666667,
    "ne:MIN_BBXMIN":118.441667,
    "ne:MIN_BBYMAX":31.8,
    "ne:MIN_BBYMIN":31.527945,
    "ne:MIN_PERKM":223.0,
    "ne:MIN_PERMI":138.0,
    "ne:NAME":"Maanshan",
    "ne:NAMEASCII":"Maanshan",
    "ne:NAMEDIFF":0,
    "ne:NATSCALE":20,
    "ne:POP1950":0,
    "ne:POP1955":0,
    "ne:POP1960":0,
    "ne:POP1965":0,
    "ne:POP1970":0,
    "ne:POP1975":0,
    "ne:POP1980":0,
    "ne:POP1985":0,
    "ne:POP1990":0,
    "ne:POP1995":0,
    "ne:POP2000":0,
    "ne:POP2005":0,
    "ne:POP2010":0,
    "ne:POP2015":0,
    "ne:POP2020":0,
    "ne:POP2025":0,
    "ne:POP2050":0,
    "ne:POP_MAX":1366302,
    "ne:POP_MIN":633940,
    "ne:POP_OTHER":767371,
    "ne:RANK_MAX":12,
    "ne:RANK_MIN":11,
    "ne:SCALERANK":7,
    "ne:SOV0NAME":"China",
    "ne:SOV_A3":"CHN",
    "ne:UN_FID":0,
    "ne:UN_LAT":0.0,
    "ne:UN_LONG":0.0,
    "ne:WORLDCITY":0,
    "ne:min_zoom":6.7,
    "wof:name":"Maanshan",
    "wof:placetype":"locality"
},
  "geometry": {"coordinates":[118.4800443105828,31.73040040997404],"type":"Point"}
}