{
  "type": "Feature",
  "properties": {
    "gn:admin1_code":"24.0",
    "gn:asciiname":"Madaozui",
    "gn:country_code":"CN",
    "gn:dem":1123,
    "gn:feature_class":"P",
    "gn:feature_code":"PPL",
    "gn:name":"Madaozui",
    "gn:population":0,
    "gn:timezone":"Asia/Shanghai",
    "iso:country":"CN",
    "name:zho_x_preferred":[
        "\u9a6c\u9053\u5480"
    ],
    "wof:name":"Madaozui",
    "wof:placetype":"locality"
},
  "geometry": {"coordinates":[111.46751999999999,39.64591],"type":"Point"}
}