{
  "type": "Feature",
  "properties": {
    "gn:admin1_code":"6.0",
    "gn:asciiname":"Bari",
    "gn:country_code":"CN",
    "gn:dem":3702,
    "gn:feature_class":"P",
    "gn:feature_code":"PPL",
    "gn:name":"Bari",
    "gn:population":0,
    "gn:timezone":"Asia/Urumqi",
    "iso:country":"CN",
    "name:zho_x_preferred":[
        "\u5df4\u65e5"
    ],
    "wof:name":"Bari",
    "wof:placetype":"locality"
},
  "geometry": {"coordinates":[96.75622,32.07247],"type":"Point"}
}