{
  "type": "Feature",
  "properties": {
    "gn:admin1_code":"10",
    "gn:asciiname":"Huiyaoyu",
    "gn:country_code":"CN",
    "gn:dem":279,
    "gn:feature_class":"P",
    "gn:feature_code":"PPL",
    "gn:name":"Huiyaoyu",
    "gn:population":0,
    "gn:timezone":"Asia/Shanghai",
    "iso:country":"CN",
    "name:zho_x_preferred":[
        "\u7070\u7a91\u5cea"
    ],
    "wof:name":"Huiyaoyu",
    "wof:placetype":"locality"
},
  "geometry": {"coordinates":[118.50124,40.35301],"type":"Point"}
}