{
  "type": "Feature",
  "properties": {
    "gn:admin1_code":"6.0",
    "gn:asciiname":"Guoworuwa",
    "gn:country_code":"CN",
    "gn:dem":3752,
    "gn:feature_class":"P",
    "gn:feature_code":"PPL",
    "gn:name":"Guoworuwa",
    "gn:population":0,
    "gn:timezone":"Asia/Urumqi",
    "iso:country":"CN",
    "name:zho_x_preferred":[
        "\u679c\u6c83\u5982\u74e6"
    ],
    "wof:name":"Guoworuwa",
    "wof:placetype":"locality"
},
  "geometry": {"coordinates":[96.80566,33.37794],"type":"Point"}
}