{
  "type": "Feature",
  "properties": {
    "gn:admin1_code":"32.0",
    "gn:asciiname":"Yuanbazi",
    "gn:country_code":"CN",
    "gn:dem":1111,
    "gn:feature_class":"P",
    "gn:feature_code":"PPL",
    "gn:name":"Yuanbazi",
    "gn:population":0,
    "gn:timezone":"Asia/Shanghai",
    "iso:country":"CN",
    "name:zho_x_preferred":[
        "\u8881\u575d\u5b50"
    ],
    "wof:name":"Yuanbazi",
    "wof:placetype":"locality"
},
  "geometry": {"coordinates":[106.89243999999999,32.27531],"type":"Point"}
}