{
  "type": "Feature",
  "properties": {
    "gn:admin1_code":"12.0",
    "gn:asciiname":"Erlipo",
    "gn:country_code":"CN",
    "gn:dem":263,
    "gn:feature_class":"P",
    "gn:feature_code":"PPL",
    "gn:name":"Erlipo",
    "gn:population":0,
    "gn:timezone":"Asia/Shanghai",
    "iso:country":"CN",
    "name:zho_x_preferred":[
        "\u4e8c\u91cc\u5761"
    ],
    "wof:name":"Erlipo",
    "wof:placetype":"locality"
},
  "geometry": {"coordinates":[111.34823,32.2729],"type":"Point"}
}