{
  "type": "Feature",
  "properties": {
    "gn:admin1_code":"29.0",
    "gn:asciiname":"Pazha",
    "gn:country_code":"CN",
    "gn:dem":1721,
    "gn:feature_class":"P",
    "gn:feature_code":"PPL",
    "gn:name":"Pazha",
    "gn:population":0,
    "gn:timezone":"Asia/Shanghai",
    "iso:country":"CN",
    "name:zho_x_preferred":[
        "\u6015\u672d"
    ],
    "wof:name":"Pazha",
    "wof:placetype":"locality"
},
  "geometry": {"coordinates":[100.065,23.4857],"type":"Point"}
}