{
  "type": "Feature",
  "properties": {
    "gn:admin1_code":"9.0",
    "gn:asciiname":"Shibukou",
    "gn:country_code":"CN",
    "gn:dem":54,
    "gn:feature_class":"P",
    "gn:feature_code":"PPL",
    "gn:name":"Shibukou",
    "gn:population":0,
    "gn:timezone":"Asia/Shanghai",
    "iso:country":"CN",
    "name:zho_x_preferred":[
        "\u65f6\u57e0\u53e3"
    ],
    "wof:name":"Shibukou",
    "wof:placetype":"locality"
},
  "geometry": {"coordinates":[114.56887,33.61903],"type":"Point"}
}