{
  "type": "Feature",
  "properties": {
    "gn:admin1_code":"8.0",
    "gn:asciiname":"Hongyuan",
    "gn:country_code":"CN",
    "gn:dem":191,
    "gn:feature_class":"P",
    "gn:feature_code":"PPL",
    "gn:name":"Hongyuan",
    "gn:population":0,
    "gn:timezone":"Asia/Shanghai",
    "iso:country":"CN",
    "name:ceb_x_preferred":[
        "Hongyuan"
    ],
    "name:zho_x_preferred":[
        "\u5b8f\u6e90"
    ],
    "wof:name":"Hongyuan",
    "wof:placetype":"locality"
},
  "geometry": {"coordinates":[127.64284000000001,45.00411],"type":"Point"}
}