{
  "type": "Feature",
  "properties": {
    "gn:admin1_code":"4.0",
    "gn:asciiname":"Douwancun",
    "gn:country_code":"CN",
    "gn:dem":3,
    "gn:feature_class":"P",
    "gn:feature_code":"PPL",
    "gn:name":"Douwancun",
    "gn:population":0,
    "gn:timezone":"Asia/Shanghai",
    "iso:country":"CN",
    "name:zho_x_preferred":[
        "\u9661\u6e7e\u6751"
    ],
    "wof:name":"Douwancun",
    "wof:placetype":"locality"
},
  "geometry": {"coordinates":[119.46307,34.12909000000001],"type":"Point"}
}