{
  "type": "Feature",
  "properties": {
    "gn:admin1_code":"18.0",
    "gn:asciiname":"Xiaoguanzhou",
    "gn:country_code":"CN",
    "gn:dem":440,
    "gn:feature_class":"P",
    "gn:feature_code":"PPL",
    "gn:name":"Xiaoguanzhou",
    "gn:population":0,
    "gn:timezone":"Asia/Shanghai",
    "iso:country":"CN",
    "name:zho_x_preferred":[
        "\u5c0f\u5b98\u6d32"
    ],
    "wof:name":"Xiaoguanzhou",
    "wof:placetype":"locality"
},
  "geometry": {"coordinates":[109.148,26.4986],"type":"Point"}
}