{
  "type": "Feature",
  "properties": {
    "gn:admin1_code":"32.0",
    "gn:asciiname":"Mumo",
    "gn:country_code":"CN",
    "gn:dem":3788,
    "gn:feature_class":"P",
    "gn:feature_code":"PPL",
    "gn:name":"Mumo",
    "gn:population":0,
    "gn:timezone":"Asia/Shanghai",
    "iso:country":"CN",
    "name:ell_x_preferred":[
        "\u039c\u03bf\u03cd\u03bc\u03bf"
    ],
    "name:zho_x_preferred":[
        "\u6728\u83ab"
    ],
    "wof:name":"Mumo",
    "wof:placetype":"locality"
},
  "geometry": {"coordinates":[100.455,29.6315],"type":"Point"}
}