{
  "type": "Feature",
  "properties": {
    "gn:admin1_code":"12.0",
    "gn:asciiname":"Renhanzhuang",
    "gn:country_code":"CN",
    "gn:dem":105,
    "gn:feature_class":"P",
    "gn:feature_code":"PPL",
    "gn:name":"Renhanzhuang",
    "gn:population":0,
    "gn:timezone":"Asia/Shanghai",
    "iso:country":"CN",
    "name:zho_x_preferred":[
        "\u4efb\u97e9\u5e84"
    ],
    "wof:name":"Renhanzhuang",
    "wof:placetype":"locality"
},
  "geometry": {"coordinates":[111.70799,32.45476],"type":"Point"}
}