{
  "type": "Feature",
  "properties": {
    "gn:admin1_code":"1.0",
    "gn:asciiname":"Fenhongjiang Linchang",
    "gn:country_code":"CN",
    "gn:dem":22,
    "gn:feature_class":"P",
    "gn:feature_code":"PPLF",
    "gn:name":"Fenhongjiang Linchang",
    "gn:population":0,
    "gn:timezone":"Asia/Shanghai",
    "iso:country":"CN",
    "wof:name":"Fenhongjiang Linchang",
    "wof:placetype":"locality"
},
  "geometry": {"coordinates":[117.16943999999999,33.33611],"type":"Point"}
}