{
  "type": "Feature",
  "properties": {
    "gn:admin1_code":"26",
    "gn:asciiname":"Yuanqu",
    "gn:country_code":"CN",
    "gn:dem":633,
    "gn:feature_class":"P",
    "gn:feature_code":"PPL",
    "gn:name":"Yuanqu",
    "gn:population":0,
    "gn:timezone":"Asia/Shanghai",
    "iso:country":"CN",
    "name:zho_x_preferred":[
        "\u5458\u66f2"
    ],
    "wof:name":"Yuanqu",
    "wof:placetype":"locality"
},
  "geometry": {"coordinates":[109.47042,34.38228],"type":"Point"}
}