{
  "type": "Feature",
  "properties": {
    "gn:admin1_code":"32.0",
    "gn:asciiname":"Guoyaogong",
    "gn:country_code":"CN",
    "gn:dem":3490,
    "gn:feature_class":"P",
    "gn:feature_code":"PPL",
    "gn:name":"Guoyaogong",
    "gn:population":0,
    "gn:timezone":"Asia/Shanghai",
    "iso:country":"CN",
    "name:zho_x_preferred":[
        "\u679c\u4e48\u8d21"
    ],
    "wof:name":"Guoyaogong",
    "wof:placetype":"locality"
},
  "geometry": {"coordinates":[98.4323,32.1146],"type":"Point"}
}