{
  "type": "Feature",
  "properties": {
    "gn:admin1_code":"29.0",
    "gn:asciiname":"Xiaolihei",
    "gn:country_code":"CN",
    "gn:dem":1964,
    "gn:feature_class":"P",
    "gn:feature_code":"PPL",
    "gn:name":"Xiaolihei",
    "gn:population":0,
    "gn:timezone":"Asia/Shanghai",
    "iso:country":"CN",
    "name:zho_x_preferred":[
        "\u5c0f\u91cc\u9ed1"
    ],
    "wof:name":"Xiaolihei",
    "wof:placetype":"locality"
},
  "geometry": {"coordinates":[100.613,25.0992],"type":"Point"}
}