{
  "type": "Feature",
  "properties": {
    "gn:admin1_code":"33",
    "gn:asciiname":"Baojia",
    "gn:country_code":"CN",
    "gn:dem":311,
    "gn:feature_class":"P",
    "gn:feature_code":"PPLA4",
    "gn:name":"Baojia",
    "gn:population":0,
    "gn:timezone":"Asia/Shanghai",
    "iso:country":"CN",
    "name:und_x_variant":[
        "Paochialo",
        "Pao-chia-lou",
        "Baojia",
        "Baojia Zhen"
    ],
    "name:zho_x_preferred":[
        "\u4fdd\u5bb6"
    ],
    "name:zho_x_variant":[
        "\u4fdd\u5bb6\u9547"
    ],
    "wof:name":"Baojia",
    "wof:placetype":"locality"
},
  "geometry": {"coordinates":[108.31323999999999,29.43869],"type":"Point"}
}