{
  "type": "Feature",
  "properties": {
    "gn:admin1_code":"29.0",
    "gn:asciiname":"Baoziwo",
    "gn:country_code":"CN",
    "gn:dem":1759,
    "gn:feature_class":"P",
    "gn:feature_code":"PPL",
    "gn:name":"Baoziwo",
    "gn:population":0,
    "gn:timezone":"Asia/Shanghai",
    "iso:country":"CN",
    "name:zho_x_preferred":[
        "\u8c79\u5b50\u7a9d"
    ],
    "wof:name":"Baoziwo",
    "wof:placetype":"locality"
},
  "geometry": {"coordinates":[103.496,23.37],"type":"Point"}
}