{
  "type": "Feature",
  "properties": {
    "gn:admin1_code":"7.0",
    "gn:asciiname":"Xinji",
    "gn:country_code":"CN",
    "gn:dem":277,
    "gn:feature_class":"P",
    "gn:feature_code":"PPL",
    "gn:name":"Xinji",
    "gn:population":0,
    "gn:timezone":"Asia/Shanghai",
    "iso:country":"CN",
    "name:und_x_variant":[
        "\u65b0\u77f6"
    ],
    "name:zho_x_preferred":[
        "\u65b0\u77f6"
    ],
    "wof:name":"Xinji",
    "wof:placetype":"locality"
},
  "geometry": {"coordinates":[117.00118000000001,26.04166],"type":"Point"}
}