{
  "type": "Feature",
  "properties": {
    "gn:admin1_code":"29.0",
    "gn:admin2_code":"1281672",
    "gn:admin3_code":"6643310.0",
    "gn:asciiname":"Mangkuanxiang",
    "gn:country_code":"CN",
    "gn:dem":850,
    "gn:feature_class":"P",
    "gn:feature_code":"PPL",
    "gn:name":"Mangkuanxiang",
    "gn:population":0,
    "gn:timezone":"Asia/Shanghai",
    "iso:country":"CN",
    "wof:name":"Mangkuanxiang",
    "wof:placetype":"locality"
},
  "geometry": {"coordinates":[98.86485,25.44521],"type":"Point"}
}