{
  "type": "Feature",
  "properties": {
    "gn:admin1_code":"29.0",
    "gn:asciiname":"Deyi",
    "gn:country_code":"CN",
    "gn:dem":1952,
    "gn:feature_class":"P",
    "gn:feature_code":"PPL",
    "gn:name":"Deyi",
    "gn:population":0,
    "gn:timezone":"Asia/Shanghai",
    "iso:country":"CN",
    "name:und_x_variant":[
        "\u5f97\u5b9c"
    ],
    "wof:name":"Deyi",
    "wof:placetype":"locality"
},
  "geometry": {"coordinates":[104.16800000000001,26.4908],"type":"Point"}
}