{
  "type": "Feature",
  "properties": {
    "gn:admin1_code":"29.0",
    "gn:asciiname":"Maheba",
    "gn:country_code":"CN",
    "gn:dem":1722,
    "gn:feature_class":"P",
    "gn:feature_code":"PPL",
    "gn:name":"Maheba",
    "gn:population":0,
    "gn:timezone":"Asia/Shanghai",
    "iso:country":"CN",
    "name:zho_x_preferred":[
        "\u9ebb\u6cb3\u575d"
    ],
    "wof:name":"Maheba",
    "wof:placetype":"locality"
},
  "geometry": {"coordinates":[98.99290000000001,25.2192],"type":"Point"}
}