{
  "type": "Feature",
  "properties": {
    "gn:admin1_code":"4.0",
    "gn:asciiname":"Nijiaduo",
    "gn:country_code":"CN",
    "gn:dem":4,
    "gn:feature_class":"P",
    "gn:feature_code":"PPL",
    "gn:name":"Nijiaduo",
    "gn:population":0,
    "gn:timezone":"Asia/Shanghai",
    "iso:country":"CN",
    "name:und_x_variant":[
        "\u502a\u5bb6\u579b"
    ],
    "name:zho_x_preferred":[
        "\u502a\u5bb6\u579b"
    ],
    "wof:name":"Nijiaduo",
    "wof:placetype":"locality"
},
  "geometry": {"coordinates":[120.40051,32.67484],"type":"Point"}
}