{
  "type": "Feature",
  "properties": {
    "gn:admin1_code":"18",
    "gn:asciiname":"Leidashi",
    "gn:country_code":"CN",
    "gn:dem":784,
    "gn:feature_class":"P",
    "gn:feature_code":"PPL",
    "gn:name":"Leidashi",
    "gn:population":0,
    "gn:timezone":"Asia/Shanghai",
    "iso:country":"CN",
    "name:zho_x_preferred":[
        "\u96f7\u6253\u77f3"
    ],
    "wof:name":"Leidashi",
    "wof:placetype":"locality"
},
  "geometry": {"coordinates":[106.203,28.5399],"type":"Point"}
}