{
  "type": "Feature",
  "properties": {
    "gn:admin1_code":"11",
    "gn:asciiname":"Guchengjie",
    "gn:country_code":"CN",
    "gn:dem":163,
    "gn:feature_class":"P",
    "gn:feature_code":"PPL",
    "gn:name":"Guchengjie",
    "gn:population":0,
    "gn:timezone":"Asia/Shanghai",
    "iso:country":"CN",
    "name:zho_x_preferred":[
        "\u53e4\u57ce\u8857"
    ],
    "wof:name":"Guchengjie",
    "wof:placetype":"locality"
},
  "geometry": {"coordinates":[113.80297,26.97966],"type":"Point"}
}