{
  "type": "Feature",
  "properties": {
    "gn:admin1_code":"25",
    "gn:asciiname":"Nancheng",
    "gn:country_code":"CN",
    "gn:dem":42,
    "gn:feature_class":"P",
    "gn:feature_code":"PPL",
    "gn:name":"Nancheng",
    "gn:population":0,
    "gn:timezone":"Asia/Shanghai",
    "iso:country":"CN",
    "name:ceb_x_preferred":[
        "Nancheng"
    ],
    "name:deu_x_preferred":[
        "Nancheng"
    ],
    "name:fra_x_preferred":[
        "Nancheng"
    ],
    "name:nld_x_preferred":[
        "Nancheng"
    ],
    "name:zho_x_preferred":[
        "\u5357\u57ce"
    ],
    "wof:name":"Nancheng",
    "wof:placetype":"locality"
},
  "geometry": {"coordinates":[116.253,36.2144],"type":"Point"}
}