{
  "type": "Feature",
  "properties": {
    "gn:admin1_code":"7",
    "gn:asciiname":"Qianyangkeng",
    "gn:country_code":"CN",
    "gn:dem":532,
    "gn:feature_class":"P",
    "gn:feature_code":"PPL",
    "gn:name":"Qianyangkeng",
    "gn:population":0,
    "gn:timezone":"Asia/Shanghai",
    "iso:country":"CN",
    "name:und_x_variant":[
        "\u5343\u6d0b\u5751",
        "Qianyangkeng"
    ],
    "wof:name":"Qianyangkeng",
    "wof:placetype":"locality"
},
  "geometry": {"coordinates":[118.73565000000001,27.78343],"type":"Point"}
}