{
  "type": "Feature",
  "properties": {
    "gn:admin1_code":"24",
    "gn:asciiname":"Nanhu",
    "gn:cc2":"CN",
    "gn:country_code":"CN",
    "gn:dem":1468,
    "gn:feature_class":"P",
    "gn:feature_code":"PPL",
    "gn:name":"Nanhu",
    "gn:population":0,
    "gn:timezone":"Asia/Shanghai",
    "iso:country":"CN",
    "name:und_x_variant":[
        "Ma-hu",
        "Nanhu"
    ],
    "wof:name":"Nanhu",
    "wof:placetype":"locality"
},
  "geometry": {"coordinates":[113.34139,35.93861],"type":"Point"}
}