{
  "type": "Feature",
  "properties": {
    "gn:admin1_code":"29.0",
    "gn:asciiname":"Babaocun",
    "gn:country_code":"CN",
    "gn:dem":1686,
    "gn:feature_class":"P",
    "gn:feature_code":"PPL",
    "gn:name":"Babaocun",
    "gn:population":0,
    "gn:timezone":"Asia/Shanghai",
    "iso:country":"CN",
    "name:zho_x_preferred":[
        "\u516b\u5b9d\u6751"
    ],
    "wof:name":"Babaocun",
    "wof:placetype":"locality"
},
  "geometry": {"coordinates":[103.361,27.0837],"type":"Point"}
}