{
  "type": "Feature",
  "properties": {
    "gn:admin1_code":"26.0",
    "gn:asciiname":"Xiadaiyucun",
    "gn:country_code":"CN",
    "gn:dem":928,
    "gn:feature_class":"P",
    "gn:feature_code":"PPL",
    "gn:name":"Xiadaiyucun",
    "gn:population":0,
    "gn:timezone":"Asia/Shanghai",
    "iso:country":"CN",
    "name:zho_x_preferred":[
        "\u4e0b\u5cb1\u5cea\u6751"
    ],
    "wof:name":"Xiadaiyucun",
    "wof:placetype":"locality"
},
  "geometry": {"coordinates":[109.31610000000001,33.9914],"type":"Point"}
}