{
  "type": "Feature",
  "properties": {
    "gn:admin1_code":"8.0",
    "gn:asciiname":"Xinhua Nongchang Ershierdui",
    "gn:country_code":"CN",
    "gn:dem":108,
    "gn:feature_class":"P",
    "gn:feature_code":"PPLF",
    "gn:name":"Xinhua Nongchang Ershierdui",
    "gn:population":0,
    "gn:timezone":"Asia/Shanghai",
    "iso:country":"CN",
    "name:zho_x_preferred":[
        "\u65b0\u534e\u519c\u573a\u4e8c\u5341\u4e8c\u961f"
    ],
    "wof:name":"Xinhua Nongchang Ershierdui",
    "wof:placetype":"locality"
},
  "geometry": {"coordinates":[130.39744999999999,47.25395],"type":"Point"}
}