{
  "type": "Feature",
  "properties": {
    "gn:admin1_code":"32.0",
    "gn:asciiname":"Tiantai",
    "gn:country_code":"CN",
    "gn:dem":1062,
    "gn:feature_class":"P",
    "gn:feature_code":"PPL",
    "gn:name":"Tiantai",
    "gn:population":0,
    "gn:timezone":"Asia/Shanghai",
    "iso:country":"CN",
    "name:zho_x_preferred":[
        "\u5929\u53f0"
    ],
    "wof:name":"Tiantai",
    "wof:placetype":"locality"
},
  "geometry": {"coordinates":[103.25817000000001,27.70964],"type":"Point"}
}