{
  "type": "Feature",
  "properties": {
    "gn:admin1_code":"14.0",
    "gn:asciiname":"Mu",
    "gn:country_code":"CN",
    "gn:dem":3838,
    "gn:feature_class":"P",
    "gn:feature_code":"PPLA4",
    "gn:name":"Mu",
    "gn:population":0,
    "gn:timezone":"Asia/Urumqi",
    "iso:country":"CN",
    "name:und_x_variant":[
        "Mu Xiang"
    ],
    "name:zho_x_preferred":[
        "\u6bcd"
    ],
    "name:zho_x_variant":[
        "\u6bcd\u4e61"
    ],
    "wof:name":"Mu",
    "wof:placetype":"locality"
},
  "geometry": {"coordinates":[89.76553,29.28709000000001],"type":"Point"}
}