{
  "type": "Feature",
  "properties": {
    "gn:admin1_code":"14.0",
    "gn:asciiname":"Naqu",
    "gn:country_code":"CN",
    "gn:dem":4595,
    "gn:feature_class":"P",
    "gn:feature_code":"PPL",
    "gn:name":"Naqu",
    "gn:population":0,
    "gn:timezone":"Asia/Urumqi",
    "iso:country":"CN",
    "name:zho_x_preferred":[
        "\u90a3\u66f2"
    ],
    "wof:name":"Naqu",
    "wof:placetype":"locality"
},
  "geometry": {"coordinates":[83.96939999999999,31.0476],"type":"Point"}
}