{
  "type": "Feature",
  "properties": {
    "gn:admin1_code":"8.0",
    "gn:asciiname":"Hadayan",
    "gn:country_code":"CN",
    "gn:dem":111,
    "gn:feature_class":"P",
    "gn:feature_code":"PPL",
    "gn:name":"Hadayan",
    "gn:population":0,
    "gn:timezone":"Asia/Shanghai",
    "iso:country":"CN",
    "name:zho_x_preferred":[
        "\u54c8\u8fbe\u6cbf"
    ],
    "wof:name":"Hadayan",
    "wof:placetype":"locality"
},
  "geometry": {"coordinates":[127.91712,49.56394],"type":"Point"}
}