{
  "type": "Feature",
  "properties": {
    "gn:admin1_code":"10.0",
    "gn:asciiname":"Daxinzhuang",
    "gn:country_code":"CN",
    "gn:dem":739,
    "gn:feature_class":"P",
    "gn:feature_code":"PPL",
    "gn:name":"Daxinzhuang",
    "gn:population":0,
    "gn:timezone":"Asia/Shanghai",
    "iso:country":"CN",
    "name:zho_x_preferred":[
        "\u5927\u8f9b\u5e84"
    ],
    "wof:name":"Daxinzhuang",
    "wof:placetype":"locality"
},
  "geometry": {"coordinates":[115.02584,40.71875],"type":"Point"}
}