{
  "type": "Feature",
  "properties": {
    "gn:admin1_code":"31.0",
    "gn:asciiname":"Baoyan",
    "gn:country_code":"CN",
    "gn:dem":195,
    "gn:feature_class":"P",
    "gn:feature_code":"PPL",
    "gn:name":"Baoyan",
    "gn:population":0,
    "gn:timezone":"Asia/Shanghai",
    "iso:country":"CN",
    "name:zho_x_preferred":[
        "\u4fdd\u4e25"
    ],
    "wof:name":"Baoyan",
    "wof:placetype":"locality"
},
  "geometry": {"coordinates":[109.30732999999999,18.4644],"type":"Point"}
}