{
  "type": "Feature",
  "properties": {
    "gn:admin1_code":"30.0",
    "gn:asciiname":"Sandanzhong",
    "gn:country_code":"CN",
    "gn:dem":57,
    "gn:feature_class":"P",
    "gn:feature_code":"PPL",
    "gn:name":"Sandanzhong",
    "gn:population":0,
    "gn:timezone":"Asia/Shanghai",
    "iso:country":"CN",
    "name:zho_x_preferred":[
        "\u4e09\u62c5\u79cd"
    ],
    "wof:name":"Sandanzhong",
    "wof:placetype":"locality"
},
  "geometry": {"coordinates":[112.66667,22.01053],"type":"Point"}
}