{
  "type": "Feature",
  "properties": {
    "gn:admin1_code":"32.0",
    "gn:asciiname":"Dajizong",
    "gn:country_code":"CN",
    "gn:dem":3656,
    "gn:feature_class":"P",
    "gn:feature_code":"PPL",
    "gn:name":"Dajizong",
    "gn:population":0,
    "gn:timezone":"Asia/Shanghai",
    "iso:country":"CN",
    "name:zho_x_preferred":[
        "\u5927\u5409\u5b97"
    ],
    "wof:name":"Dajizong",
    "wof:placetype":"locality"
},
  "geometry": {"coordinates":[101.355,29.8978],"type":"Point"}
}