{
  "type": "Feature",
  "properties": {
    "gn:admin1_code":"24.0",
    "gn:asciiname":"Yinzigou",
    "gn:country_code":"CN",
    "gn:dem":1210,
    "gn:feature_class":"P",
    "gn:feature_code":"PPL",
    "gn:name":"Yinzigou",
    "gn:population":0,
    "gn:timezone":"Asia/Shanghai",
    "iso:country":"CN",
    "name:zho_x_preferred":[
        "\u7aa8\u5b50\u6c9f"
    ],
    "wof:name":"Yinzigou",
    "wof:placetype":"locality"
},
  "geometry": {"coordinates":[113.28649,40.26866],"type":"Point"}
}