{
  "type": "Feature",
  "properties": {
    "gn:admin1_code":"18",
    "gn:asciiname":"Gaopulong",
    "gn:country_code":"CN",
    "gn:dem":1304,
    "gn:feature_class":"P",
    "gn:feature_code":"PPL",
    "gn:name":"Gaopulong",
    "gn:population":0,
    "gn:timezone":"Asia/Shanghai",
    "iso:country":"CN",
    "name:zho_x_preferred":[
        "\u9ad8\u666e\u9647"
    ],
    "wof:name":"Gaopulong",
    "wof:placetype":"locality"
},
  "geometry": {"coordinates":[105.253,25.1558],"type":"Point"}
}