{
  "type": "Feature",
  "properties": {
    "gn:admin1_code":"11",
    "gn:asciiname":"Qingcaohu",
    "gn:country_code":"CN",
    "gn:dem":353,
    "gn:feature_class":"P",
    "gn:feature_code":"PPL",
    "gn:name":"Qingcaohu",
    "gn:population":0,
    "gn:timezone":"Asia/Shanghai",
    "iso:country":"CN",
    "name:zho_x_preferred":[
        "\u9752\u8349\u6e56"
    ],
    "wof:name":"Qingcaohu",
    "wof:placetype":"locality"
},
  "geometry": {"coordinates":[111.50707,25.08711],"type":"Point"}
}