{
  "type": "Feature",
  "properties": {
    "gn:admin1_code":"10",
    "gn:asciiname":"Liushuquan",
    "gn:cc2":"CN",
    "gn:country_code":"CN",
    "gn:dem":2,
    "gn:feature_class":"P",
    "gn:feature_code":"PPL",
    "gn:name":"Liushuquan",
    "gn:population":0,
    "gn:timezone":"Asia/Shanghai",
    "iso:country":"CN",
    "name:und_x_variant":[
        "Liushuqu",
        "Liu-shu-ch\u2019\u00fceh",
        "Liushuquan"
    ],
    "wof:name":"Liushuquan",
    "wof:placetype":"locality"
},
  "geometry": {"coordinates":[118.09999999999999,39.38333],"type":"Point"}
}