{
  "type": "Feature",
  "properties": {
    "gn:admin1_code":"22.0",
    "gn:asciiname":"Xixiaoying",
    "gn:country_code":"CN",
    "gn:dem":45,
    "gn:feature_class":"P",
    "gn:feature_code":"PPL",
    "gn:name":"Xixiaoying",
    "gn:population":0,
    "gn:timezone":"Asia/Shanghai",
    "iso:country":"CN",
    "name:zho_x_preferred":[
        "\u897f\u5c0f\u8425"
    ],
    "wof:name":"Xixiaoying",
    "wof:placetype":"locality"
},
  "geometry": {"coordinates":[116.54957,40.1877],"type":"Point"}
}