{
  "type": "Feature",
  "properties": {
    "gn:admin1_code":"18",
    "gn:asciiname":"Shiniuzhai",
    "gn:country_code":"CN",
    "gn:dem":935,
    "gn:feature_class":"P",
    "gn:feature_code":"PPL",
    "gn:name":"Shiniuzhai",
    "gn:population":0,
    "gn:timezone":"Asia/Shanghai",
    "iso:country":"CN",
    "name:zho_x_preferred":[
        "\u77f3\u725b\u5be8"
    ],
    "wof:name":"Shiniuzhai",
    "wof:placetype":"locality"
},
  "geometry": {"coordinates":[108.078,27.4585],"type":"Point"}
}