{
  "type": "Feature",
  "properties": {
    "gn:admin1_code":"13.0",
    "gn:asciiname":"Andir",
    "gn:country_code":"CN",
    "gn:dem":2209,
    "gn:feature_class":"P",
    "gn:feature_code":"PPL",
    "gn:name":"Andir",
    "gn:population":0,
    "gn:timezone":"Asia/Shanghai",
    "iso:country":"CN",
    "name:uig_x_preferred":[
        "Andir"
    ],
    "name:und_x_variant":[
        "Andi\u2019er"
    ],
    "name:zho_x_preferred":[
        "\u5b89\u8fea\u5c14"
    ],
    "wof:name":"Andir",
    "wof:placetype":"locality"
},
  "geometry": {"coordinates":[80.65813,36.46111],"type":"Point"}
}