{
  "type": "Feature",
  "properties": {
    "gn:admin1_code":"15.0",
    "gn:asciiname":"Luopo",
    "gn:country_code":"CN",
    "gn:dem":1515,
    "gn:feature_class":"P",
    "gn:feature_code":"PPL",
    "gn:name":"Luopo",
    "gn:population":0,
    "gn:timezone":"Asia/Shanghai",
    "iso:country":"CN",
    "name:zho_x_preferred":[
        "\u7f57\u5761"
    ],
    "wof:name":"Luopo",
    "wof:placetype":"locality"
},
  "geometry": {"coordinates":[105.616,34.1444],"type":"Point"}
}