{
  "type": "Feature",
  "properties": {
    "gn:admin1_code":"19.0",
    "gn:asciiname":"Xiagaojiagou",
    "gn:country_code":"CN",
    "gn:dem":160,
    "gn:feature_class":"P",
    "gn:feature_code":"PPL",
    "gn:name":"Xiagaojiagou",
    "gn:population":0,
    "gn:timezone":"Asia/Shanghai",
    "iso:country":"CN",
    "name:und_x_variant":[
        "\u4e0b\u9ad8\u5bb6\u6c9f"
    ],
    "name:zho_x_preferred":[
        "\u4e0b\u9ad8\u5bb6\u6c9f"
    ],
    "wof:name":"Xiagaojiagou",
    "wof:placetype":"locality"
},
  "geometry": {"coordinates":[121.04545,41.42677],"type":"Point"}
}