{
  "type": "Feature",
  "properties": {
    "gn:admin1_code":"24",
    "gn:asciiname":"Nanyanzhuang",
    "gn:country_code":"CN",
    "gn:dem":1003,
    "gn:feature_class":"P",
    "gn:feature_code":"PPL",
    "gn:name":"Nanyanzhuang",
    "gn:population":0,
    "gn:timezone":"Asia/Shanghai",
    "iso:country":"CN",
    "name:und_x_variant":[
        "\u5357\u664f\u5e84"
    ],
    "wof:name":"Nanyanzhuang",
    "wof:placetype":"locality"
},
  "geometry": {"coordinates":[113.09965,39.77879],"type":"Point"}
}