{
  "type": "Feature",
  "properties": {
    "gn:admin1_code":"26.0",
    "gn:asciiname":"Panjiayuan",
    "gn:country_code":"CN",
    "gn:dem":754,
    "gn:feature_class":"P",
    "gn:feature_code":"PPL",
    "gn:name":"Panjiayuan",
    "gn:population":0,
    "gn:timezone":"Asia/Shanghai",
    "iso:country":"CN",
    "name:und_x_variant":[
        "\u6f58\u5bb6\u9662"
    ],
    "wof:name":"Panjiayuan",
    "wof:placetype":"locality"
},
  "geometry": {"coordinates":[106.51268,33.03403],"type":"Point"}
}