{
  "type": "Feature",
  "properties": {
    "gn:admin1_code":"19.0",
    "gn:asciiname":"Xiatukouzicun",
    "gn:country_code":"CN",
    "gn:dem":130,
    "gn:feature_class":"P",
    "gn:feature_code":"PPL",
    "gn:name":"Xiatukouzicun",
    "gn:population":0,
    "gn:timezone":"Asia/Shanghai",
    "iso:country":"CN",
    "name:zho_x_preferred":[
        "\u4e0b\u571f\u53e3\u5b50\u6751"
    ],
    "wof:name":"Xiatukouzicun",
    "wof:placetype":"locality"
},
  "geometry": {"coordinates":[124.102,42.4443],"type":"Point"}
}