{
  "type": "Feature",
  "properties": {
    "gn:admin1_code":"29",
    "gn:asciiname":"Longbeng",
    "gn:country_code":"CN",
    "gn:dem":1118,
    "gn:feature_class":"P",
    "gn:feature_code":"PPL",
    "gn:name":"Longbeng",
    "gn:population":0,
    "gn:timezone":"Asia/Shanghai",
    "iso:country":"CN",
    "name:zho_x_preferred":[
        "\u9f99\u868c"
    ],
    "wof:name":"Longbeng",
    "wof:placetype":"locality"
},
  "geometry": {"coordinates":[105.027,24.1862],"type":"Point"}
}