{
  "type": "Feature",
  "properties": {
    "gn:admin1_code":"11",
    "gn:asciiname":"Qidi",
    "gn:country_code":"CN",
    "gn:dem":175,
    "gn:feature_class":"P",
    "gn:feature_code":"PPLA4",
    "gn:name":"Qidi",
    "gn:population":0,
    "gn:timezone":"Asia/Shanghai",
    "iso:country":"CN",
    "name:und_x_variant":[
        "Chongtou",
        "Qidi Xiang"
    ],
    "name:zho_x_preferred":[
        "\u4e03\u5730"
    ],
    "name:zho_x_variant":[
        "\u51b2\u5934",
        "\u4e03\u5730\u4e61"
    ],
    "wof:name":"Qidi",
    "wof:placetype":"locality"
},
  "geometry": {"coordinates":[113.66137000000001,26.95592000000001],"type":"Point"}
}