{
  "type": "Feature",
  "properties": {
    "gn:admin1_code":"3.0",
    "gn:asciiname":"Pinghu",
    "gn:country_code":"CN",
    "gn:dem":460,
    "gn:feature_class":"P",
    "gn:feature_code":"PPL",
    "gn:name":"Pinghu",
    "gn:population":0,
    "gn:timezone":"Asia/Shanghai",
    "iso:country":"CN",
    "name:und_x_variant":[
        "\u576a\u6e56"
    ],
    "wof:name":"Pinghu",
    "wof:placetype":"locality"
},
  "geometry": {"coordinates":[115.62708000000001,26.44735],"type":"Point"}
}