{
  "type": "Feature",
  "properties": {
    "gn:admin1_code":"2.0",
    "gn:asciiname":"Huangpoqiao",
    "gn:country_code":"CN",
    "gn:dem":43,
    "gn:feature_class":"P",
    "gn:feature_code":"PPL",
    "gn:name":"Huangpoqiao",
    "gn:population":0,
    "gn:timezone":"Asia/Shanghai",
    "iso:country":"CN",
    "name:zho_x_preferred":[
        "\u9ec4\u5a46\u6865"
    ],
    "wof:name":"Huangpoqiao",
    "wof:placetype":"locality"
},
  "geometry": {"coordinates":[120.32331000000001,29.70012],"type":"Point"}
}