{
  "type": "Feature",
  "properties": {
    "gn:admin1_code":"04",
    "gn:asciiname":"Xiejiazhuang",
    "gn:cc2":"CN",
    "gn:country_code":"CN",
    "gn:dem":6,
    "gn:feature_class":"P",
    "gn:feature_code":"PPL",
    "gn:name":"Xiejiazhuang",
    "gn:population":0,
    "gn:timezone":"Asia/Shanghai",
    "iso:country":"CN",
    "name:und_x_variant":[
        "Hsieh-chia-chuang",
        "Xiejiazhuang"
    ],
    "wof:name":"Xiejiazhuang",
    "wof:placetype":"locality"
},
  "geometry": {"coordinates":[120.59417000000001,32.20194],"type":"Point"}
}