{
  "type": "Feature",
  "properties": {
    "gn:admin1_code":"12.0",
    "gn:asciiname":"Toudaoshui",
    "gn:country_code":"CN",
    "gn:dem":420,
    "gn:feature_class":"P",
    "gn:feature_code":"PPL",
    "gn:name":"Toudaoshui",
    "gn:population":0,
    "gn:timezone":"Asia/Shanghai",
    "iso:country":"CN",
    "name:zho_x_preferred":[
        "\u5934\u9053\u6c34"
    ],
    "wof:name":"Toudaoshui",
    "wof:placetype":"locality"
},
  "geometry": {"coordinates":[109.45631000000002,30.23632000000001],"type":"Point"}
}