{
  "type": "Feature",
  "properties": {
    "gn:admin1_code":"1.0",
    "gn:asciiname":"Liuhulicun",
    "gn:country_code":"CN",
    "gn:dem":67,
    "gn:feature_class":"P",
    "gn:feature_code":"PPL",
    "gn:name":"Liuhulicun",
    "gn:population":0,
    "gn:timezone":"Asia/Shanghai",
    "iso:country":"CN",
    "name:und_x_variant":[
        "Liuhuli"
    ],
    "name:zho_x_preferred":[
        "\u516d\u6237\u674e\u6751"
    ],
    "wof:name":"Liuhulicun",
    "wof:placetype":"locality"
},
  "geometry": {"coordinates":[117.61382999999999,32.41412],"type":"Point"}
}