{
  "type": "Feature",
  "properties": {
    "gn:admin1_code":"29.0",
    "gn:asciiname":"Hexi",
    "gn:country_code":"CN",
    "gn:dem":1820,
    "gn:feature_class":"P",
    "gn:feature_code":"PPLA4",
    "gn:name":"Hexi",
    "gn:population":0,
    "gn:timezone":"Asia/Shanghai",
    "iso:country":"CN",
    "name:und_x_variant":[
        "Xicheng",
        "Hosi",
        "Ho-hsi",
        "Hsi-ch\u2019eng",
        "Ho-hsi-hsien",
        "Hosihsien",
        "\u6cb3\u897f",
        "Hexi Zhen",
        "\u6cb3\u897f\u9547",
        "Hexi"
    ],
    "wof:name":"Hexi",
    "wof:placetype":"locality"
},
  "geometry": {"coordinates":[102.64861000000001,24.14361],"type":"Point"}
}