{
  "type": "Feature",
  "properties": {
    "gn:admin1_code":"01",
    "gn:asciiname":"Maoshandian",
    "gn:cc2":"CN",
    "gn:country_code":"CN",
    "gn:dem":55,
    "gn:feature_class":"P",
    "gn:feature_code":"PPL",
    "gn:name":"Maoshandian",
    "gn:population":0,
    "gn:timezone":"Asia/Shanghai",
    "iso:country":"CN",
    "name:und_x_variant":[
        "Mao-shan-tien",
        "Maoshandian"
    ],
    "wof:name":"Maoshandian",
    "wof:placetype":"locality"
},
  "geometry": {"coordinates":[116.86667,34.13333],"type":"Point"}
}