{
  "type": "Feature",
  "properties": {
    "gn:admin1_code":"14.0",
    "gn:asciiname":"Goinsargoin",
    "gn:cc2":"CN",
    "gn:country_code":"CN",
    "gn:dem":3976,
    "gn:feature_class":"P",
    "gn:feature_code":"PPL",
    "gn:name":"Goinsargoin",
    "gn:population":0,
    "gn:timezone":"Asia/Urumqi",
    "iso:country":"CN",
    "name:ara_x_preferred":[
        "\u063a\u0648\u0627\u0646\u0633\u0631\u063a\u0648\u0627\u0646"
    ],
    "name:bod_x_preferred":[
        "Goinsargoin"
    ],
    "name:fas_x_preferred":[
        "\u06af\u0648\u06cc\u0646\u0633\u0627\u0631\u06af\u0648\u06cc\u0646"
    ],
    "name:msa_x_preferred":[
        "Goinsargoin"
    ],
    "name:und_x_variant":[
        "Ken-sha-kun"
    ],
    "name:zho_x_preferred":[
        "Genshagong"
    ],
    "name:zho_x_variant":[
        "\u6839\u6c99\u8d21",
        "Renzhenduo Gongshe",
        "\u4ec1\u771f\u591a\u516c\u793e"
    ],
    "wof:name":"Goinsargoin",
    "wof:placetype":"locality"
},
  "geometry": {"coordinates":[98.06667,31.93333],"type":"Point"}
}