{
  "type": "Feature",
  "properties": {
    "gn:admin1_code":"24.0",
    "gn:asciiname":"Xiashennan",
    "gn:country_code":"CN",
    "gn:dem":1370,
    "gn:feature_class":"P",
    "gn:feature_code":"PPL",
    "gn:name":"Xiashennan",
    "gn:population":0,
    "gn:timezone":"Asia/Shanghai",
    "iso:country":"CN",
    "name:zho_x_preferred":[
        "\u4e0b\u795e\u5357"
    ],
    "wof:name":"Xiashennan",
    "wof:placetype":"locality"
},
  "geometry": {"coordinates":[112.20780999999999,37.03401],"type":"Point"}
}