{
  "type": "Feature",
  "properties": {
    "gn:admin1_code":"07",
    "gn:asciiname":"Shanqian",
    "gn:country_code":"CN",
    "gn:dem":74,
    "gn:feature_class":"P",
    "gn:feature_code":"PPL",
    "gn:name":"Shanqian",
    "gn:population":0,
    "gn:timezone":"Asia/Shanghai",
    "iso:country":"CN",
    "name:zho_x_preferred":[
        "\u5c71\u524d"
    ],
    "wof:name":"Shanqian",
    "wof:placetype":"locality"
},
  "geometry": {"coordinates":[118.32025,25.21851],"type":"Point"}
}