{
  "type": "Feature",
  "properties": {
    "gn:admin1_code":"30.0",
    "gn:asciiname":"Tongpancun",
    "gn:country_code":"CN",
    "gn:dem":19,
    "gn:feature_class":"P",
    "gn:feature_code":"PPL",
    "gn:name":"Tongpancun",
    "gn:population":0,
    "gn:timezone":"Asia/Shanghai",
    "iso:country":"CN",
    "name:zho_x_preferred":[
        "\u94dc\u76d8\u6751"
    ],
    "wof:name":"Tongpancun",
    "wof:placetype":"locality"
},
  "geometry": {"coordinates":[116.19905,23.74528],"type":"Point"}
}