{
  "type": "Feature",
  "properties": {
    "gn:admin1_code":"12.0",
    "gn:asciiname":"Chenjiadu",
    "gn:country_code":"CN",
    "gn:dem":43,
    "gn:feature_class":"P",
    "gn:feature_code":"PPL",
    "gn:name":"Chenjiadu",
    "gn:population":0,
    "gn:timezone":"Asia/Shanghai",
    "iso:country":"CN",
    "name:zho_x_preferred":[
        "Chenjiadu"
    ],
    "name:zho_x_variant":[
        "\u9648\u5bb6\u6e21"
    ],
    "wof:name":"Chenjiadu",
    "wof:placetype":"locality"
},
  "geometry": {"coordinates":[111.72369999999999,30.39947],"type":"Point"}
}