{
  "type": "Feature",
  "properties": {
    "gn:admin1_code":"15.0",
    "gn:asciiname":"Gengdupo",
    "gn:country_code":"CN",
    "gn:dem":2474,
    "gn:feature_class":"P",
    "gn:feature_code":"PPL",
    "gn:name":"Gengdupo",
    "gn:population":0,
    "gn:timezone":"Asia/Shanghai",
    "iso:country":"CN",
    "name:zho_x_preferred":[
        "\u8015\u8bfb\u5761"
    ],
    "wof:name":"Gengdupo",
    "wof:placetype":"locality"
},
  "geometry": {"coordinates":[103.015,37.3631],"type":"Point"}
}