{
  "type": "Feature",
  "properties": {
    "gn:admin1_code":"19.0",
    "gn:asciiname":"Hougujingzi",
    "gn:country_code":"CN",
    "gn:dem":86,
    "gn:feature_class":"P",
    "gn:feature_code":"PPL",
    "gn:name":"Hougujingzi",
    "gn:population":0,
    "gn:timezone":"Asia/Shanghai",
    "iso:country":"CN",
    "name:und_x_variant":[
        "\u540e\u53e4\u4e95\u5b50"
    ],
    "name:zho_x_preferred":[
        "\u540e\u53e4\u4e95\u5b50"
    ],
    "wof:name":"Hougujingzi",
    "wof:placetype":"locality"
},
  "geometry": {"coordinates":[122.61057,42.42209],"type":"Point"}
}