{
  "type": "Feature",
  "properties": {
    "gn:admin1_code":"32.0",
    "gn:asciiname":"Suiwa",
    "gn:country_code":"CN",
    "gn:dem":2172,
    "gn:feature_class":"P",
    "gn:feature_code":"PPL",
    "gn:name":"Suiwa",
    "gn:population":0,
    "gn:timezone":"Asia/Shanghai",
    "iso:country":"CN",
    "name:zho_x_preferred":[
        "\u788e\u74e6"
    ],
    "wof:name":"Suiwa",
    "wof:placetype":"locality"
},
  "geometry": {"coordinates":[102.62873999999999,28.31878],"type":"Point"}
}