{
  "type": "Feature",
  "properties": {
    "gn:admin1_code":"30.0",
    "gn:asciiname":"Kongwu",
    "gn:country_code":"CN",
    "gn:dem":276,
    "gn:feature_class":"P",
    "gn:feature_code":"PPL",
    "gn:name":"Kongwu",
    "gn:population":0,
    "gn:timezone":"Asia/Shanghai",
    "iso:country":"CN",
    "name:zho_x_preferred":[
        "\u5b54\u5c4b"
    ],
    "wof:name":"Kongwu",
    "wof:placetype":"locality"
},
  "geometry": {"coordinates":[112.01899,23.80535],"type":"Point"}
}