{
  "type": "Feature",
  "properties": {
    "gn:admin1_code":"30",
    "gn:asciiname":"Pinghengcun",
    "gn:country_code":"CN",
    "gn:dem":12,
    "gn:feature_class":"P",
    "gn:feature_code":"PPL",
    "gn:name":"Pinghengcun",
    "gn:population":0,
    "gn:timezone":"Asia/Urumqi",
    "iso:country":"CN",
    "name:zho_x_preferred":[
        "\u5e73\u8861\u6751"
    ],
    "wof:name":"Pinghengcun",
    "wof:placetype":"locality"
},
  "geometry": {"coordinates":[110.12108000000001,21.05125],"type":"Point"}
}