{
  "type": "Feature",
  "properties": {
    "gn:admin1_code":"16.0",
    "gn:asciiname":"Tianwei",
    "gn:country_code":"CN",
    "gn:dem":278,
    "gn:feature_class":"P",
    "gn:feature_code":"PPL",
    "gn:name":"Tianwei",
    "gn:population":0,
    "gn:timezone":"Asia/Shanghai",
    "iso:country":"CN",
    "name:hak_x_preferred":[
        "Thi\u00e8n-m\u00ee-hi\u00f4ng"
    ],
    "name:ita_x_preferred":[
        "Tianwei"
    ],
    "name:jpn_x_preferred":[
        "\u7530\u5c3e\u90f7"
    ],
    "name:kor_x_preferred":[
        "\ud188\uc6e8\uc774\ud5a5"
    ],
    "name:pol_x_preferred":[
        "Tianwei"
    ],
    "name:vie_x_preferred":[
        "\u0110i\u1ec1n V\u0129"
    ],
    "name:zho_x_preferred":[
        "\u7530\u5c3e"
    ],
    "name:zho_x_variant":[
        "\u7530\u5c3e\u9109"
    ],
    "wof:name":"Tianwei",
    "wof:placetype":"locality"
},
  "geometry": {"coordinates":[110.429,24.3442],"type":"Point"}
}