{
  "type": "Feature",
  "properties": {
    "gn:admin1_code":"20",
    "gn:asciiname":"Burd Liang",
    "gn:cc2":"CN",
    "gn:country_code":"CN",
    "gn:dem":1374,
    "gn:feature_class":"P",
    "gn:feature_code":"PPL",
    "gn:name":"Burd Liang",
    "gn:population":0,
    "gn:timezone":"Asia/Shanghai",
    "iso:country":"CN",
    "name:und_x_variant":[
        "Bu\u2019erduliang",
        "Burd Liang"
    ],
    "wof:name":"Burd Liang",
    "wof:placetype":"locality"
},
  "geometry": {"coordinates":[109.93361000000002,39.73611],"type":"Point"}
}