{
  "type": "Feature",
  "properties": {
    "gn:admin1_code":"12",
    "gn:asciiname":"Tucheng",
    "gn:country_code":"CN",
    "gn:dem":136,
    "gn:feature_class":"P",
    "gn:feature_code":"PPLA4",
    "gn:name":"Tucheng",
    "gn:population":0,
    "gn:timezone":"Asia/Shanghai",
    "iso:country":"CN",
    "name:und_x_variant":[
        "\u571f\u57ce",
        "Tucheng Xiang",
        "\u571f\u57ce\u4e61"
    ],
    "wof:name":"Tucheng",
    "wof:placetype":"locality"
},
  "geometry": {"coordinates":[111.10648999999999,30.65606],"type":"Point"}
}