{
  "type": "Feature",
  "properties": {
    "gn:admin1_code":"19.0",
    "gn:asciiname":"Chaganchaolaocun",
    "gn:country_code":"CN",
    "gn:dem":337,
    "gn:feature_class":"P",
    "gn:feature_code":"PPL",
    "gn:name":"Chaganchaolaocun",
    "gn:population":0,
    "gn:timezone":"Asia/Shanghai",
    "iso:country":"CN",
    "name:zho_x_preferred":[
        "\u67e5\u5e72\u671d\u8001\u6751"
    ],
    "wof:name":"Chaganchaolaocun",
    "wof:placetype":"locality"
},
  "geometry": {"coordinates":[121.367,42.381],"type":"Point"}
}