{
  "type": "Feature",
  "properties": {
    "gn:admin1_code":"15.0",
    "gn:asciiname":"Niuzuigou",
    "gn:country_code":"CN",
    "gn:dem":1387,
    "gn:feature_class":"P",
    "gn:feature_code":"PPL",
    "gn:name":"Niuzuigou",
    "gn:population":0,
    "gn:timezone":"Asia/Shanghai",
    "iso:country":"CN",
    "name:zho_x_preferred":[
        "\u725b\u5480\u6c9f"
    ],
    "wof:name":"Niuzuigou",
    "wof:placetype":"locality"
},
  "geometry": {"coordinates":[108.262,36.359],"type":"Point"}
}