{
  "type": "Feature",
  "properties": {
    "gn:admin1_code":"29.0",
    "gn:asciiname":"Kazishang",
    "gn:country_code":"CN",
    "gn:dem":2659,
    "gn:feature_class":"P",
    "gn:feature_code":"PPL",
    "gn:name":"Kazishang",
    "gn:population":0,
    "gn:timezone":"Asia/Shanghai",
    "iso:country":"CN",
    "name:zho_x_preferred":[
        "\u5361\u5b50\u4e0a"
    ],
    "wof:name":"Kazishang",
    "wof:placetype":"locality"
},
  "geometry": {"coordinates":[103.334,26.7904],"type":"Point"}
}