{
  "type": "Feature",
  "properties": {
    "gn:admin1_code":"29.0",
    "gn:asciiname":"Kenpeigu",
    "gn:country_code":"CN",
    "gn:dem":2694,
    "gn:feature_class":"P",
    "gn:feature_code":"PPL",
    "gn:name":"Kenpeigu",
    "gn:population":0,
    "gn:timezone":"Asia/Shanghai",
    "iso:country":"CN",
    "name:zho_x_preferred":[
        "\u80af\u914d\u53e4"
    ],
    "wof:name":"Kenpeigu",
    "wof:placetype":"locality"
},
  "geometry": {"coordinates":[100.31100000000001,27.3187],"type":"Point"}
}