{
  "type": "Feature",
  "properties": {
    "gn:admin1_code":"24.0",
    "gn:asciiname":"Gaojiashan",
    "gn:country_code":"CN",
    "gn:dem":1019,
    "gn:feature_class":"P",
    "gn:feature_code":"PPL",
    "gn:name":"Gaojiashan",
    "gn:population":0,
    "gn:timezone":"Asia/Shanghai",
    "iso:country":"CN",
    "name:zho_x_preferred":[
        "\u9ad8\u5bb6\u5c71"
    ],
    "wof:name":"Gaojiashan",
    "wof:placetype":"locality"
},
  "geometry": {"coordinates":[110.60214000000001,38.18393],"type":"Point"}
}