{
  "type": "Feature",
  "properties": {
    "gn:admin1_code":"18",
    "gn:asciiname":"Laoyingtou",
    "gn:country_code":"CN",
    "gn:dem":863,
    "gn:feature_class":"P",
    "gn:feature_code":"PPL",
    "gn:name":"Laoyingtou",
    "gn:population":0,
    "gn:timezone":"Asia/Shanghai",
    "iso:country":"CN",
    "name:zho_x_preferred":[
        "\u8001\u8425\u5934"
    ],
    "wof:name":"Laoyingtou",
    "wof:placetype":"locality"
},
  "geometry": {"coordinates":[105.078,26.1067],"type":"Point"}
}