{
  "type": "Feature",
  "properties": {
    "gn:admin1_code":"11.0",
    "gn:asciiname":"Qingshiling",
    "gn:country_code":"CN",
    "gn:dem":889,
    "gn:feature_class":"P",
    "gn:feature_code":"PPL",
    "gn:name":"Qingshiling",
    "gn:population":0,
    "gn:timezone":"Asia/Shanghai",
    "iso:country":"CN",
    "name:zho_x_preferred":[
        "\u9752\u77f3\u5cad"
    ],
    "wof:name":"Qingshiling",
    "wof:placetype":"locality"
},
  "geometry": {"coordinates":[113.55019,25.79224],"type":"Point"}
}