{
  "type": "Feature",
  "properties": {
    "gn:admin1_code":"15.0",
    "gn:asciiname":"Hewan",
    "gn:country_code":"CN",
    "gn:dem":1315,
    "gn:feature_class":"P",
    "gn:feature_code":"PPL",
    "gn:name":"Hewan",
    "gn:population":0,
    "gn:timezone":"Asia/Shanghai",
    "iso:country":"CN",
    "name:zho_x_preferred":[
        "\u4f55\u6e7e"
    ],
    "wof:name":"Hewan",
    "wof:placetype":"locality"
},
  "geometry": {"coordinates":[107.473,35.6505],"type":"Point"}
}