{
  "type": "Feature",
  "properties": {
    "gn:admin1_code":"29.0",
    "gn:asciiname":"Mushu",
    "gn:country_code":"CN",
    "gn:dem":3156,
    "gn:feature_class":"P",
    "gn:feature_code":"PPL",
    "gn:name":"Mushu",
    "gn:population":0,
    "gn:timezone":"Asia/Shanghai",
    "iso:country":"CN",
    "name:zho_x_preferred":[
        "\u6728\u4e66"
    ],
    "wof:name":"Mushu",
    "wof:placetype":"locality"
},
  "geometry": {"coordinates":[100.121,26.7072],"type":"Point"}
}