{
  "type": "Feature",
  "properties": {
    "gn:admin1_code":"29",
    "gn:asciiname":"Bacai",
    "gn:country_code":"CN",
    "gn:dem":1443,
    "gn:feature_class":"P",
    "gn:feature_code":"PPL",
    "gn:name":"Bacai",
    "gn:population":0,
    "gn:timezone":"Asia/Shanghai",
    "iso:country":"CN",
    "name:zho_x_preferred":[
        "\u575d\u5f69"
    ],
    "wof:name":"Bacai",
    "wof:placetype":"locality"
},
  "geometry": {"coordinates":[104.762,24.0813],"type":"Point"}
}