{
  "type": "Feature",
  "properties": {
    "gn:admin1_code":"30",
    "gn:asciiname":"Xiaozhu",
    "gn:country_code":"CN",
    "gn:dem":123,
    "gn:feature_class":"P",
    "gn:feature_code":"PPL",
    "gn:name":"Xiaozhu",
    "gn:population":0,
    "gn:timezone":"Asia/Shanghai",
    "iso:country":"CN",
    "name:und_x_variant":[
        "\u5c0f\u7af9"
    ],
    "name:zho_x_preferred":[
        "\u5c0f\u7af9"
    ],
    "wof:name":"Xiaozhu",
    "wof:placetype":"locality"
},
  "geometry": {"coordinates":[112.3725,23.93306],"type":"Point"}
}