{
  "type": "Feature",
  "properties": {
    "gn:admin1_code":"26.0",
    "gn:asciiname":"Bei'ercun",
    "gn:country_code":"CN",
    "gn:dem":429,
    "gn:feature_class":"P",
    "gn:feature_code":"PPL",
    "gn:name":"Bei\u2019ercun",
    "gn:population":0,
    "gn:timezone":"Asia/Shanghai",
    "iso:country":"CN",
    "name:zho_x_preferred":[
        "\u5317\u4e8c\u6751"
    ],
    "name:zho_x_variant":[
        "Bei\u2019ercun"
    ],
    "wof:name":"Bei'ercun",
    "wof:placetype":"locality"
},
  "geometry": {"coordinates":[109.40849,34.87298],"type":"Point"}
}