{
  "type": "Feature",
  "properties": {
    "gn:admin1_code":"24",
    "gn:asciiname":"Baijiazhuang",
    "gn:cc2":"CN",
    "gn:country_code":"CN",
    "gn:dem":1184,
    "gn:feature_class":"P",
    "gn:feature_code":"PPL",
    "gn:name":"Baijiazhuang",
    "gn:population":0,
    "gn:timezone":"Asia/Shanghai",
    "iso:country":"CN",
    "name:und_x_variant":[
        "Pai-chia-chuang",
        "Baijiazhuang"
    ],
    "wof:name":"Baijiazhuang",
    "wof:placetype":"locality"
},
  "geometry": {"coordinates":[113.30167,38.59278],"type":"Point"}
}