{
  "type": "Feature",
  "properties": {
    "gn:admin1_code":"9.0",
    "gn:asciiname":"Longtangou",
    "gn:country_code":"CN",
    "gn:dem":199,
    "gn:feature_class":"P",
    "gn:feature_code":"PPL",
    "gn:name":"Longtangou",
    "gn:population":0,
    "gn:timezone":"Asia/Shanghai",
    "iso:country":"CN",
    "name:und_x_variant":[
        "\u9f99\u6f6d\u6c9f",
        "Longtangou"
    ],
    "wof:name":"Longtangou",
    "wof:placetype":"locality"
},
  "geometry": {"coordinates":[112.68876000000002,33.75366],"type":"Point"}
}