{
  "type": "Feature",
  "properties": {
    "gn:admin1_code":"2.0",
    "gn:asciiname":"Pingwo",
    "gn:country_code":"CN",
    "gn:dem":707,
    "gn:feature_class":"P",
    "gn:feature_code":"PPL",
    "gn:name":"Pingwo",
    "gn:population":0,
    "gn:timezone":"Asia/Shanghai",
    "iso:country":"CN",
    "name:zho_x_preferred":[
        "\u5e73\u7a9d"
    ],
    "wof:name":"Pingwo",
    "wof:placetype":"locality"
},
  "geometry": {"coordinates":[120.23866,29.44972000000001],"type":"Point"}
}