{
  "type": "Feature",
  "properties": {
    "gn:admin1_code":"14.0",
    "gn:asciiname":"Lalaga",
    "gn:country_code":"CN",
    "gn:dem":4542,
    "gn:feature_class":"P",
    "gn:feature_code":"PPL",
    "gn:name":"Lalaga",
    "gn:population":0,
    "gn:timezone":"Asia/Urumqi",
    "iso:country":"CN",
    "name:zho_x_preferred":[
        "\u62c9\u62c9\u560e"
    ],
    "wof:name":"Lalaga",
    "wof:placetype":"locality"
},
  "geometry": {"coordinates":[85.53830000000001,28.3974],"type":"Point"}
}