{
  "type": "Feature",
  "properties": {
    "gn:admin1_code":"16",
    "gn:asciiname":"Dazhou",
    "gn:country_code":"CN",
    "gn:dem":156,
    "gn:feature_class":"P",
    "gn:feature_code":"PPL",
    "gn:name":"Dazhou",
    "gn:population":0,
    "gn:timezone":"Asia/Shanghai",
    "iso:country":"CN",
    "name:ara_x_preferred":[
        "\u062f\u0627\u062a\u0634\u0648"
    ],
    "name:cdo_x_preferred":[
        "D\u0103k-ci\u016d"
    ],
    "name:ceb_x_preferred":[
        "Dazhou"
    ],
    "name:ces_x_preferred":[
        "Ta-\u010dou"
    ],
    "name:dan_x_preferred":[
        "Dazhou"
    ],
    "name:deu_x_preferred":[
        "Dazhou"
    ],
    "name:eus_x_preferred":[
        "Dazhou"
    ],
    "name:fas_x_preferred":[
        "\u062f\u0627\u0698\u0648"
    ],
    "name:fin_x_preferred":[
        "Dazhou"
    ],
    "name:fra_x_preferred":[
        "Dazhou"
    ],
    "name:hak_x_preferred":[
        "Tha\u030dt-ch\u00fb-s\u1e73"
    ],
    "name:ita_x_preferred":[
        "Dazhou"
    ],
    "name:jpn_x_preferred":[
        "\u9054\u5dde\u5e02"
    ],
    "name:kaz_x_preferred":[
        "\u0414\u0430\u0447\u0436\u043e\u0443"
    ],
    "name:kik_x_preferred":[
        "Dazhou"
    ],
    "name:kor_x_preferred":[
        "\ub2e4\uc800\uc6b0\uc2dc"
    ],
    "name:mlg_x_preferred":[
        "Dazhou"
    ],
    "name:nld_x_preferred":[
        "Dazhou"
    ],
    "name:nno_x_preferred":[
        "Dazhou"
    ],
    "name:nor_x_preferred":[
        "Dazhou"
    ],
    "name:pol_x_preferred":[
        "Dazhou"
    ],
    "name:rus_x_preferred":[
        "\u0414\u0430\u0447\u0436\u043e\u0443"
    ],
    "name:spa_x_preferred":[
        "Dazhou"
    ],
    "name:swe_x_preferred":[
        "Dazhou"
    ],
    "name:tur_x_preferred":[
        "Dazhou"
    ],
    "name:urd_x_preferred":[
        "\u062f\u0627\u0698\u0648\u0648"
    ],
    "name:vie_x_preferred":[
        "\u0110\u1ea1t Ch\u00e2u"
    ],
    "name:war_x_preferred":[
        "Dazhou"
    ],
    "name:wuu_x_preferred":[
        "\u8fbe\u5dde\u5e02"
    ],
    "name:zho_x_preferred":[
        "\u5927\u6d32"
    ],
    "name:zho_x_variant":[
        "\u8fbe\u5dde\u5e02"
    ],
    "wof:name":"Dazhou",
    "wof:placetype":"locality"
},
  "geometry": {"coordinates":[110.03400000000001,25.1678],"type":"Point"}
}