{
  "type": "Feature",
  "properties": {
    "gn:admin1_code":"25.0",
    "gn:asciiname":"Xizhuangdongcun",
    "gn:country_code":"CN",
    "gn:dem":16,
    "gn:feature_class":"P",
    "gn:feature_code":"PPL",
    "gn:name":"Xizhuangdongcun",
    "gn:population":0,
    "gn:timezone":"Asia/Shanghai",
    "iso:country":"CN",
    "name:zho_x_preferred":[
        "\u897f\u5e84\u4e1c\u6751"
    ],
    "wof:name":"Xizhuangdongcun",
    "wof:placetype":"locality"
},
  "geometry": {"coordinates":[120.07137,36.29579],"type":"Point"}
}