{
  "type": "Feature",
  "properties": {
    "gn:admin1_code":"16.0",
    "gn:asciiname":"Weiwu",
    "gn:country_code":"CN",
    "gn:dem":522,
    "gn:feature_class":"P",
    "gn:feature_code":"PPL",
    "gn:name":"Weiwu",
    "gn:population":0,
    "gn:timezone":"Asia/Shanghai",
    "iso:country":"CN",
    "name:zho_x_preferred":[
        "\u5a01\u6b66"
    ],
    "wof:name":"Weiwu",
    "wof:placetype":"locality"
},
  "geometry": {"coordinates":[110.31999999999999,22.9069],"type":"Point"}
}