{
  "type": "Feature",
  "properties": {
    "gn:admin1_code":"24.0",
    "gn:asciiname":"Xisiyuan",
    "gn:country_code":"CN",
    "gn:dem":1035,
    "gn:feature_class":"P",
    "gn:feature_code":"PPL",
    "gn:name":"Xisiyuan",
    "gn:population":0,
    "gn:timezone":"Asia/Shanghai",
    "iso:country":"CN",
    "name:zho_x_preferred":[
        "\u897f\u5bfa\u9662"
    ],
    "wof:name":"Xisiyuan",
    "wof:placetype":"locality"
},
  "geometry": {"coordinates":[112.73443,39.39599000000001],"type":"Point"}
}