{
  "type": "Feature",
  "properties": {
    "gn:admin1_code":"10",
    "gn:asciiname":"Qincun",
    "gn:country_code":"CN",
    "gn:dem":16,
    "gn:feature_class":"P",
    "gn:feature_code":"PPL",
    "gn:name":"Qincun",
    "gn:population":0,
    "gn:timezone":"Asia/Shanghai",
    "iso:country":"CN",
    "name:und_x_variant":[
        "Ch\u2019in-ts\u2019un-chen",
        "Ch\u2019in-ts\u2019un",
        "Qincun"
    ],
    "name:zho_x_preferred":[
        "\u79e6\u6751"
    ],
    "wof:name":"Qincun",
    "wof:placetype":"locality"
},
  "geometry": {"coordinates":[116.67036,37.83599],"type":"Point"}
}