{
  "type": "Feature",
  "properties": {
    "gn:admin1_code":"15.0",
    "gn:asciiname":"Huangtianzi",
    "gn:country_code":"CN",
    "gn:dem":1396,
    "gn:feature_class":"P",
    "gn:feature_code":"PPL",
    "gn:name":"Huangtianzi",
    "gn:population":0,
    "gn:timezone":"Asia/Shanghai",
    "iso:country":"CN",
    "name:zho_x_preferred":[
        "\u9ec4\u5929\u5b50"
    ],
    "wof:name":"Huangtianzi",
    "wof:placetype":"locality"
},
  "geometry": {"coordinates":[107.26300000000001,37.0518],"type":"Point"}
}