{
  "type": "Feature",
  "properties": {
    "gn:admin1_code":"33.0",
    "gn:asciiname":"Longtanba",
    "gn:country_code":"CN",
    "gn:dem":1096,
    "gn:feature_class":"P",
    "gn:feature_code":"PPL",
    "gn:name":"Longtanba",
    "gn:population":0,
    "gn:timezone":"Asia/Shanghai",
    "iso:country":"CN",
    "name:zho_x_preferred":[
        "\u9f99\u5766\u575d"
    ],
    "wof:name":"Longtanba",
    "wof:placetype":"locality"
},
  "geometry": {"coordinates":[108.04928999999998,29.75299],"type":"Point"}
}