{
  "type": "Feature",
  "properties": {
    "gn:admin1_code":"8.0",
    "gn:asciiname":"Danjiatun",
    "gn:country_code":"CN",
    "gn:dem":126,
    "gn:feature_class":"P",
    "gn:feature_code":"PPL",
    "gn:name":"Danjiatun",
    "gn:population":0,
    "gn:timezone":"Asia/Shanghai",
    "iso:country":"CN",
    "name:zho_x_preferred":[
        "\u5355\u5bb6\u5c6f"
    ],
    "wof:name":"Danjiatun",
    "wof:placetype":"locality"
},
  "geometry": {"coordinates":[125.99630999999999,45.53333],"type":"Point"}
}