{
  "type": "Feature",
  "properties": {
    "gn:admin1_code":"2.0",
    "gn:asciiname":"Sanjia",
    "gn:country_code":"CN",
    "gn:dem":8,
    "gn:feature_class":"P",
    "gn:feature_code":"PPL",
    "gn:name":"Sanjia",
    "gn:population":0,
    "gn:timezone":"Asia/Shanghai",
    "iso:country":"CN",
    "name:und_x_variant":[
        "\u4e09\u5bb6"
    ],
    "wof:name":"Sanjia",
    "wof:placetype":"locality"
},
  "geometry": {"coordinates":[120.86368,30.7377],"type":"Point"}
}