{
  "type": "Feature",
  "properties": {
    "gn:admin1_code":"32.0",
    "gn:asciiname":"Xueduo",
    "gn:country_code":"CN",
    "gn:dem":3587,
    "gn:feature_class":"P",
    "gn:feature_code":"PPL",
    "gn:name":"Xueduo",
    "gn:population":0,
    "gn:timezone":"Asia/Shanghai",
    "iso:country":"CN",
    "name:zho_x_preferred":[
        "\u5b66\u591a"
    ],
    "wof:name":"Xueduo",
    "wof:placetype":"locality"
},
  "geometry": {"coordinates":[99.21726,31.44403],"type":"Point"}
}