{
  "type": "Feature",
  "properties": {
    "gn:admin1_code":"15.0",
    "gn:asciiname":"Weijiachuan",
    "gn:country_code":"CN",
    "gn:dem":950,
    "gn:feature_class":"P",
    "gn:feature_code":"PPL",
    "gn:name":"Weijiachuan",
    "gn:population":0,
    "gn:timezone":"Asia/Shanghai",
    "iso:country":"CN",
    "name:zho_x_preferred":[
        "\u9b4f\u5bb6\u5ddd"
    ],
    "wof:name":"Weijiachuan",
    "wof:placetype":"locality"
},
  "geometry": {"coordinates":[107.88200000000001,35.3969],"type":"Point"}
}