{
  "type": "Feature",
  "properties": {
    "gn:admin1_code":"29.0",
    "gn:asciiname":"Luohushan",
    "gn:country_code":"CN",
    "gn:dem":1264,
    "gn:feature_class":"P",
    "gn:feature_code":"PPL",
    "gn:name":"Luohushan",
    "gn:population":0,
    "gn:timezone":"Asia/Shanghai",
    "iso:country":"CN",
    "name:zho_x_preferred":[
        "\u7f57\u80e1\u5c71"
    ],
    "wof:name":"Luohushan",
    "wof:placetype":"locality"
},
  "geometry": {"coordinates":[98.57250000000001,24.1257],"type":"Point"}
}