{
  "type": "Feature",
  "properties": {
    "gn:admin1_code":"8.0",
    "gn:asciiname":"Yucuncun",
    "gn:country_code":"CN",
    "gn:dem":215,
    "gn:feature_class":"P",
    "gn:feature_code":"PPL",
    "gn:name":"Yucuncun",
    "gn:population":0,
    "gn:timezone":"Asia/Shanghai",
    "iso:country":"CN",
    "name:zho_x_preferred":[
        "\u80b2\u6751\u6751"
    ],
    "wof:name":"Yucuncun",
    "wof:placetype":"locality"
},
  "geometry": {"coordinates":[127.02504,47.34329],"type":"Point"}
}