{
  "type": "Feature",
  "properties": {
    "gn:admin1_code":"2",
    "gn:asciiname":"Jiazishan",
    "gn:country_code":"CN",
    "gn:dem":574,
    "gn:feature_class":"P",
    "gn:feature_code":"PPL",
    "gn:name":"Jiazishan",
    "gn:population":0,
    "gn:timezone":"Asia/Shanghai",
    "iso:country":"CN",
    "name:und_x_variant":[
        "\u7532\u5b50\u5c71"
    ],
    "wof:name":"Jiazishan",
    "wof:placetype":"locality"
},
  "geometry": {"coordinates":[119.131,30.21043],"type":"Point"}
}