{
  "type": "Feature",
  "properties": {
    "gn:admin1_code":"2.0",
    "gn:asciiname":"Fangjiatou",
    "gn:country_code":"CN",
    "gn:dem":100,
    "gn:feature_class":"P",
    "gn:feature_code":"PPL",
    "gn:name":"Fangjiatou",
    "gn:population":0,
    "gn:timezone":"Asia/Shanghai",
    "iso:country":"CN",
    "name:und_x_variant":[
        "\u65b9\u5bb6\u5934"
    ],
    "wof:name":"Fangjiatou",
    "wof:placetype":"locality"
},
  "geometry": {"coordinates":[119.84735000000001,30.21613],"type":"Point"}
}