{
  "type": "Feature",
  "properties": {
    "gn:admin1_code":"4.0",
    "gn:asciiname":"Dashuxia",
    "gn:country_code":"CN",
    "gn:dem":26,
    "gn:feature_class":"P",
    "gn:feature_code":"PPL",
    "gn:name":"Dashuxia",
    "gn:population":0,
    "gn:timezone":"Asia/Shanghai",
    "iso:country":"CN",
    "name:zho_x_preferred":[
        "\u5927\u6811\u4e0b"
    ],
    "wof:name":"Dashuxia",
    "wof:placetype":"locality"
},
  "geometry": {"coordinates":[119.43877000000001,31.97848],"type":"Point"}
}