{
  "type": "Feature",
  "properties": {
    "gn:admin1_code":"20.0",
    "gn:asciiname":"Zuoshugang",
    "gn:country_code":"CN",
    "gn:dem":350,
    "gn:feature_class":"P",
    "gn:feature_code":"PPL",
    "gn:name":"Zuoshugang",
    "gn:population":0,
    "gn:timezone":"Asia/Shanghai",
    "iso:country":"CN",
    "name:zho_x_preferred":[
        "\u67de\u6811\u5c97"
    ],
    "wof:name":"Zuoshugang",
    "wof:placetype":"locality"
},
  "geometry": {"coordinates":[124.65015,49.26646],"type":"Point"}
}