{
  "type": "Feature",
  "properties": {
    "gn:admin1_code":"18.0",
    "gn:asciiname":"Puzizhai",
    "gn:country_code":"CN",
    "gn:dem":526,
    "gn:feature_class":"P",
    "gn:feature_code":"PPL",
    "gn:name":"Puzizhai",
    "gn:population":0,
    "gn:timezone":"Asia/Shanghai",
    "iso:country":"CN",
    "name:zho_x_preferred":[
        "\u94fa\u5b50\u5be8"
    ],
    "wof:name":"Puzizhai",
    "wof:placetype":"locality"
},
  "geometry": {"coordinates":[109.015,26.9379],"type":"Point"}
}