{
  "type": "Feature",
  "properties": {
    "gn:admin1_code":"20.0",
    "gn:asciiname":"Honghua",
    "gn:country_code":"CN",
    "gn:dem":1628,
    "gn:feature_class":"P",
    "gn:feature_code":"PPL",
    "gn:name":"Honghua",
    "gn:population":0,
    "gn:timezone":"Asia/Shanghai",
    "iso:country":"CN",
    "name:und_x_variant":[
        "\u7ea2\u82b1"
    ],
    "wof:name":"Honghua",
    "wof:placetype":"locality"
},
  "geometry": {"coordinates":[109.73016,41.43207],"type":"Point"}
}