{
  "type": "Feature",
  "properties": {
    "gn:admin1_code":"15.0",
    "gn:asciiname":"Majiagou",
    "gn:country_code":"CN",
    "gn:dem":2192,
    "gn:feature_class":"P",
    "gn:feature_code":"PPL",
    "gn:name":"Majiagou",
    "gn:population":0,
    "gn:timezone":"Asia/Shanghai",
    "iso:country":"CN",
    "name:und_x_variant":[
        "\u9a6c\u5bb6\u6c9f"
    ],
    "wof:name":"Majiagou",
    "wof:placetype":"locality"
},
  "geometry": {"coordinates":[104.93449,34.31468],"type":"Point"}
}