{
  "type": "Feature",
  "properties": {
    "gn:admin1_code":"32.0",
    "gn:asciiname":"Bendegu",
    "gn:country_code":"CN",
    "gn:dem":3621,
    "gn:feature_class":"P",
    "gn:feature_code":"PPL",
    "gn:name":"Bendegu",
    "gn:population":0,
    "gn:timezone":"Asia/Shanghai",
    "iso:country":"CN",
    "name:zho_x_preferred":[
        "\u7b28\u5f97\u53e4"
    ],
    "wof:name":"Bendegu",
    "wof:placetype":"locality"
},
  "geometry": {"coordinates":[99.9783,31.5853],"type":"Point"}
}