{
  "type": "Feature",
  "properties": {
    "gn:admin1_code":"1.0",
    "gn:asciiname":"Shangxingcun",
    "gn:country_code":"CN",
    "gn:dem":52,
    "gn:feature_class":"P",
    "gn:feature_code":"PPL",
    "gn:name":"Shangxingcun",
    "gn:population":0,
    "gn:timezone":"Asia/Shanghai",
    "iso:country":"CN",
    "name:zho_x_preferred":[
        "\u4e0a\u884c\u6751"
    ],
    "wof:name":"Shangxingcun",
    "wof:placetype":"locality"
},
  "geometry": {"coordinates":[116.72123000000001,31.6372],"type":"Point"}
}