{
  "type": "Feature",
  "properties": {
    "gn:admin1_code":"29.0",
    "gn:asciiname":"Wujiazhuang",
    "gn:country_code":"CN",
    "gn:dem":2051,
    "gn:feature_class":"P",
    "gn:feature_code":"PPL",
    "gn:name":"Wujiazhuang",
    "gn:population":0,
    "gn:timezone":"Asia/Shanghai",
    "iso:country":"CN",
    "name:zho_x_preferred":[
        "\u4e94\u5bb6\u5e84"
    ],
    "wof:name":"Wujiazhuang",
    "wof:placetype":"locality"
},
  "geometry": {"coordinates":[101.075,25.0448],"type":"Point"}
}