{
  "type": "Feature",
  "properties": {
    "gn:admin1_code":"12.0",
    "gn:asciiname":"Baoshihe",
    "gn:country_code":"CN",
    "gn:dem":96,
    "gn:feature_class":"P",
    "gn:feature_code":"PPL",
    "gn:name":"Baoshihe",
    "gn:population":0,
    "gn:timezone":"Asia/Shanghai",
    "iso:country":"CN",
    "name:zho_x_preferred":[
        "Baoshihe"
    ],
    "name:zho_x_variant":[
        "\u5b9d\u77f3\u6cb3"
    ],
    "wof:name":"Baoshihe",
    "wof:placetype":"locality"
},
  "geometry": {"coordinates":[114.62014000000001,29.49622],"type":"Point"}
}