{
  "type": "Feature",
  "properties": {
    "gn:admin1_code":"12.0",
    "gn:asciiname":"Zhangjia Dayuan",
    "gn:country_code":"CN",
    "gn:dem":675,
    "gn:feature_class":"P",
    "gn:feature_code":"PPL",
    "gn:name":"Zhangjia Dayuan",
    "gn:population":0,
    "gn:timezone":"Asia/Shanghai",
    "iso:country":"CN",
    "name:zho_x_preferred":[
        "\u5f20\u5bb6\u5927\u9662"
    ],
    "wof:name":"Zhangjia Dayuan",
    "wof:placetype":"locality"
},
  "geometry": {"coordinates":[110.49657000000001,32.10865],"type":"Point"}
}