{
  "type": "Feature",
  "properties": {
    "gn:admin1_code":"12.0",
    "gn:asciiname":"Masangpo",
    "gn:country_code":"CN",
    "gn:dem":654,
    "gn:feature_class":"P",
    "gn:feature_code":"PPL",
    "gn:name":"Masangpo",
    "gn:population":0,
    "gn:timezone":"Asia/Shanghai",
    "iso:country":"CN",
    "name:zho_x_preferred":[
        "\u9a6c\u6851\u5761"
    ],
    "wof:name":"Masangpo",
    "wof:placetype":"locality"
},
  "geometry": {"coordinates":[108.48163999999998,29.73168],"type":"Point"}
}