{
  "type": "Feature",
  "properties": {
    "gn:admin1_code":"21.0",
    "gn:asciiname":"Zhongzuizi",
    "gn:country_code":"CN",
    "gn:dem":1678,
    "gn:feature_class":"P",
    "gn:feature_code":"PPL",
    "gn:name":"Zhongzuizi",
    "gn:population":0,
    "gn:timezone":"Asia/Shanghai",
    "iso:country":"CN",
    "name:zho_x_preferred":[
        "\u4e2d\u5480\u5b50"
    ],
    "wof:name":"Zhongzuizi",
    "wof:placetype":"locality"
},
  "geometry": {"coordinates":[107.252,37.1149],"type":"Point"}
}