{
  "type": "Feature",
  "properties": {
    "gn:admin1_code":"3.0",
    "gn:asciiname":"Simakeng",
    "gn:country_code":"CN",
    "gn:dem":196,
    "gn:feature_class":"P",
    "gn:feature_code":"PPL",
    "gn:name":"Simakeng",
    "gn:population":0,
    "gn:timezone":"Asia/Shanghai",
    "iso:country":"CN",
    "name:und_x_variant":[
        "\u53f8\u9a6c\u5751"
    ],
    "wof:name":"Simakeng",
    "wof:placetype":"locality"
},
  "geometry": {"coordinates":[114.79867,27.63807000000001],"type":"Point"}
}