{
  "type": "Feature",
  "properties": {
    "gn:admin1_code":"7.0",
    "gn:asciiname":"Luokeng",
    "gn:country_code":"CN",
    "gn:dem":357,
    "gn:feature_class":"P",
    "gn:feature_code":"PPL",
    "gn:name":"Luokeng",
    "gn:population":0,
    "gn:timezone":"Asia/Shanghai",
    "iso:country":"CN",
    "name:zho_x_preferred":[
        "\u7f57\u5751"
    ],
    "wof:name":"Luokeng",
    "wof:placetype":"locality"
},
  "geometry": {"coordinates":[116.46805000000001,25.81951],"type":"Point"}
}