{
  "type": "Feature",
  "properties": {
    "gn:admin1_code":"5.0",
    "gn:asciiname":"Xiaodonggou",
    "gn:country_code":"CN",
    "gn:dem":288,
    "gn:feature_class":"P",
    "gn:feature_code":"PPL",
    "gn:name":"Xiaodonggou",
    "gn:population":0,
    "gn:timezone":"Asia/Shanghai",
    "iso:country":"CN",
    "name:und_x_variant":[
        "\u5c0f\u4e1c\u6c9f"
    ],
    "wof:name":"Xiaodonggou",
    "wof:placetype":"locality"
},
  "geometry": {"coordinates":[126.09662,41.15893],"type":"Point"}
}