{
  "type": "Feature",
  "properties": {
    "gn:admin1_code":"8.0",
    "gn:asciiname":"Houjiatun",
    "gn:country_code":"CN",
    "gn:dem":172,
    "gn:feature_class":"P",
    "gn:feature_code":"PPL",
    "gn:name":"Houjiatun",
    "gn:population":0,
    "gn:timezone":"Asia/Shanghai",
    "iso:country":"CN",
    "name:zho_x_preferred":[
        "\u540e\u8d3e\u5c6f"
    ],
    "wof:name":"Houjiatun",
    "wof:placetype":"locality"
},
  "geometry": {"coordinates":[128.04898,45.7784],"type":"Point"}
}