{
  "type": "Feature",
  "properties": {
    "gn:admin1_code":"8.0",
    "gn:asciiname":"Dashengcun",
    "gn:country_code":"CN",
    "gn:dem":290,
    "gn:feature_class":"P",
    "gn:feature_code":"PPL",
    "gn:name":"Dashengcun",
    "gn:population":0,
    "gn:timezone":"Asia/Shanghai",
    "iso:country":"CN",
    "name:zho_x_preferred":[
        "\u5927\u751f\u6751"
    ],
    "wof:name":"Dashengcun",
    "wof:placetype":"locality"
},
  "geometry": {"coordinates":[129.32321000000002,44.28281],"type":"Point"}
}