{
  "type": "Feature",
  "properties": {
    "gn:admin1_code":"26.0",
    "gn:asciiname":"Beigoucun",
    "gn:country_code":"CN",
    "gn:dem":1245,
    "gn:feature_class":"P",
    "gn:feature_code":"PPL",
    "gn:name":"Beigoucun",
    "gn:population":0,
    "gn:timezone":"Asia/Shanghai",
    "iso:country":"CN",
    "name:zho_x_preferred":[
        "\u5317\u6c9f\u6751"
    ],
    "wof:name":"Beigoucun",
    "wof:placetype":"locality"
},
  "geometry": {"coordinates":[109.40416999999999,36.5253],"type":"Point"}
}