{
  "type": "Feature",
  "properties": {
    "gn:admin1_code":"26",
    "gn:asciiname":"Heishancun",
    "gn:country_code":"CN",
    "gn:dem":1191,
    "gn:feature_class":"P",
    "gn:feature_code":"PPL",
    "gn:name":"Heishancun",
    "gn:population":0,
    "gn:timezone":"Asia/Shanghai",
    "iso:country":"CN",
    "name:und_x_variant":[
        "Heishan"
    ],
    "name:zho_x_preferred":[
        "\u9ed1\u5c71\u6751"
    ],
    "wof:name":"Heishancun",
    "wof:placetype":"locality"
},
  "geometry": {"coordinates":[110.15293,34.31145],"type":"Point"}
}