{
  "type": "Feature",
  "properties": {
    "gn:admin1_code":"5.0",
    "gn:asciiname":"Shadong",
    "gn:country_code":"CN",
    "gn:dem":255,
    "gn:feature_class":"P",
    "gn:feature_code":"PPL",
    "gn:name":"Shadong",
    "gn:population":0,
    "gn:timezone":"Asia/Shanghai",
    "iso:country":"CN",
    "name:und_x_variant":[
        "\u6c99\u4e1c"
    ],
    "wof:name":"Shadong",
    "wof:placetype":"locality"
},
  "geometry": {"coordinates":[129.73484999999999,43.30126],"type":"Point"}
}