{
  "type": "Feature",
  "properties": {
    "gn:admin1_code":"32.0",
    "gn:asciiname":"Shangcun",
    "gn:country_code":"CN",
    "gn:dem":3314,
    "gn:feature_class":"P",
    "gn:feature_code":"PPL",
    "gn:name":"Shangcun",
    "gn:population":0,
    "gn:timezone":"Asia/Shanghai",
    "iso:country":"CN",
    "name:zho_x_preferred":[
        "\u4e0a\u6751"
    ],
    "wof:name":"Shangcun",
    "wof:placetype":"locality"
},
  "geometry": {"coordinates":[101.036,27.6804],"type":"Point"}
}