{
  "type": "Feature",
  "properties": {
    "gn:admin1_code":"32.0",
    "gn:asciiname":"Juemu",
    "gn:country_code":"CN",
    "gn:dem":1981,
    "gn:feature_class":"P",
    "gn:feature_code":"PPL",
    "gn:name":"Juemu",
    "gn:population":0,
    "gn:timezone":"Asia/Shanghai",
    "iso:country":"CN",
    "name:zho_x_preferred":[
        "\u89c9\u7261"
    ],
    "wof:name":"Juemu",
    "wof:placetype":"locality"
},
  "geometry": {"coordinates":[103.342,28.2825],"type":"Point"}
}