{
  "type": "Feature",
  "properties": {
    "gn:admin1_code":"2",
    "gn:asciiname":"Shuanggang",
    "gn:country_code":"CN",
    "gn:dem":427,
    "gn:feature_class":"P",
    "gn:feature_code":"PPL",
    "gn:name":"Shuanggang",
    "gn:population":0,
    "gn:timezone":"Asia/Shanghai",
    "iso:country":"CN",
    "name:und_x_variant":[
        "\u53cc\u6e2f",
        "Shuanggang"
    ],
    "wof:name":"Shuanggang",
    "wof:placetype":"locality"
},
  "geometry": {"coordinates":[119.69833,27.53087],"type":"Point"}
}