{
  "type": "Feature",
  "properties": {
    "gn:admin1_code":"25",
    "gn:asciiname":"Ciyu",
    "gn:country_code":"CN",
    "gn:dem":378,
    "gn:feature_class":"P",
    "gn:feature_code":"PPL",
    "gn:name":"Ciyu",
    "gn:population":0,
    "gn:timezone":"Asia/Shanghai",
    "iso:country":"CN",
    "name:zho_x_preferred":[
        "\u8328\u5cea"
    ],
    "wof:name":"Ciyu",
    "wof:placetype":"locality"
},
  "geometry": {"coordinates":[118.11199999999999,36.2587],"type":"Point"}
}