{
  "type": "Feature",
  "properties": {
    "gn:admin1_code":"18",
    "gn:asciiname":"Ganzishu",
    "gn:country_code":"CN",
    "gn:dem":886,
    "gn:feature_class":"P",
    "gn:feature_code":"PPL",
    "gn:name":"Ganzishu",
    "gn:population":0,
    "gn:timezone":"Asia/Shanghai",
    "iso:country":"CN",
    "name:zho_x_preferred":[
        "\u67d1\u5b50\u6811"
    ],
    "wof:name":"Ganzishu",
    "wof:placetype":"locality"
},
  "geometry": {"coordinates":[106.265,28.4208],"type":"Point"}
}