{
  "type": "Feature",
  "properties": {
    "gn:admin1_code":"26.0",
    "gn:asciiname":"Cigou",
    "gn:country_code":"CN",
    "gn:dem":693,
    "gn:feature_class":"P",
    "gn:feature_code":"PPL",
    "gn:name":"Cigou",
    "gn:population":0,
    "gn:timezone":"Asia/Shanghai",
    "iso:country":"CN",
    "name:und_x_variant":[
        "\u6b21\u6c9f"
    ],
    "wof:name":"Cigou",
    "wof:placetype":"locality"
},
  "geometry": {"coordinates":[107.97511000000002,33.19792],"type":"Point"}
}