{
  "type": "Feature",
  "properties": {
    "gn:admin1_code":"4.0",
    "gn:asciiname":"Yanjicun",
    "gn:country_code":"CN",
    "gn:dem":27,
    "gn:feature_class":"P",
    "gn:feature_code":"PPL",
    "gn:name":"Yanjicun",
    "gn:population":0,
    "gn:timezone":"Asia/Shanghai",
    "iso:country":"CN",
    "name:zho_x_preferred":[
        "\u95eb\u96c6\u6751"
    ],
    "wof:name":"Yanjicun",
    "wof:placetype":"locality"
},
  "geometry": {"coordinates":[117.71622000000001,34.22092],"type":"Point"}
}