{
  "type": "Feature",
  "properties": {
    "gn:admin1_code":"29",
    "gn:asciiname":"Xijiu",
    "gn:country_code":"CN",
    "gn:dem":1743,
    "gn:feature_class":"P",
    "gn:feature_code":"PPL",
    "gn:name":"Xijiu",
    "gn:population":0,
    "gn:timezone":"Asia/Shanghai",
    "iso:country":"CN",
    "name:zho_x_preferred":[
        "\u897f\u5c31"
    ],
    "wof:name":"Xijiu",
    "wof:placetype":"locality"
},
  "geometry": {"coordinates":[102.149,24.3765],"type":"Point"}
}