{
  "type": "Feature",
  "properties": {
    "gn:admin1_code":"10",
    "gn:asciiname":"Xizhuanglingxi",
    "gn:country_code":"CN",
    "gn:dem":178,
    "gn:feature_class":"P",
    "gn:feature_code":"PPL",
    "gn:name":"Xizhuanglingxi",
    "gn:population":0,
    "gn:timezone":"Asia/Shanghai",
    "iso:country":"CN",
    "name:zho_x_preferred":[
        "\u897f\u5e84\u5cad\u897f"
    ],
    "wof:name":"Xizhuanglingxi",
    "wof:placetype":"locality"
},
  "geometry": {"coordinates":[118.24652,40.1001],"type":"Point"}
}