{
  "type": "Feature",
  "properties": {
    "gn:admin1_code":"5.0",
    "gn:asciiname":"Qicuocun",
    "gn:country_code":"CN",
    "gn:dem":142,
    "gn:feature_class":"P",
    "gn:feature_code":"PPL",
    "gn:name":"Qicuocun",
    "gn:population":0,
    "gn:timezone":"Asia/Shanghai",
    "iso:country":"CN",
    "name:zho_x_preferred":[
        "\u4e03\u64ae\u6751"
    ],
    "wof:name":"Qicuocun",
    "wof:placetype":"locality"
},
  "geometry": {"coordinates":[123.42762,44.69005],"type":"Point"}
}