{
  "type": "Feature",
  "properties": {
    "gn:admin1_code":"5.0",
    "gn:asciiname":"Laoguicun",
    "gn:country_code":"CN",
    "gn:dem":174,
    "gn:feature_class":"P",
    "gn:feature_code":"PPL",
    "gn:name":"Laoguicun",
    "gn:population":0,
    "gn:timezone":"Asia/Shanghai",
    "iso:country":"CN",
    "name:zho_x_preferred":[
        "\u8001\u67dc\u6751"
    ],
    "wof:name":"Laoguicun",
    "wof:placetype":"locality"
},
  "geometry": {"coordinates":[124.71569,43.72232],"type":"Point"}
}