{
  "type": "Feature",
  "properties": {
    "gn:admin1_code":"26.0",
    "gn:asciiname":"Sanhuangmiaocun",
    "gn:country_code":"CN",
    "gn:dem":919,
    "gn:feature_class":"P",
    "gn:feature_code":"PPL",
    "gn:name":"Sanhuangmiaocun",
    "gn:population":0,
    "gn:timezone":"Asia/Shanghai",
    "iso:country":"CN",
    "name:zho_x_preferred":[
        "\u4e09\u7687\u5e99\u6751"
    ],
    "wof:name":"Sanhuangmiaocun",
    "wof:placetype":"locality"
},
  "geometry": {"coordinates":[109.91307999999999,37.95502000000001],"type":"Point"}
}