{
  "type": "Feature",
  "properties": {
    "gn:admin1_code":"12.0",
    "gn:asciiname":"Lulintai",
    "gn:country_code":"CN",
    "gn:dem":27,
    "gn:feature_class":"P",
    "gn:feature_code":"PPL",
    "gn:name":"Lulintai",
    "gn:population":0,
    "gn:timezone":"Asia/Shanghai",
    "iso:country":"CN",
    "name:zho_x_preferred":[
        "\u82a6\u6797\u53f0"
    ],
    "wof:name":"Lulintai",
    "wof:placetype":"locality"
},
  "geometry": {"coordinates":[112.93523999999999,30.00616],"type":"Point"}
}