{
  "type": "Feature",
  "properties": {
    "gn:admin1_code":"05",
    "gn:asciiname":"Jiulong",
    "gn:country_code":"CN",
    "gn:dem":229,
    "gn:feature_class":"P",
    "gn:feature_code":"PPLA4",
    "gn:name":"Jiulong",
    "gn:population":0,
    "gn:timezone":"Asia/Shanghai",
    "iso:country":"CN",
    "name:und_x_variant":[
        "I-lan-kou",
        "Yilan Zhen",
        "Jiulong",
        "\u4e5d\u9f99",
        "\u4f9d\u5170\u9547"
    ],
    "wof:name":"Jiulong",
    "wof:placetype":"locality"
},
  "geometry": {"coordinates":[129.51716000000002,43.10683],"type":"Point"}
}