{
  "type": "Feature",
  "properties": {
    "gn:admin1_code":"29.0",
    "gn:asciiname":"Shipenshui",
    "gn:country_code":"CN",
    "gn:dem":1815,
    "gn:feature_class":"P",
    "gn:feature_code":"PPL",
    "gn:name":"Shipenshui",
    "gn:population":0,
    "gn:timezone":"Asia/Shanghai",
    "iso:country":"CN",
    "name:zho_x_preferred":[
        "\u77f3\u76c6\u6c34"
    ],
    "wof:name":"Shipenshui",
    "wof:placetype":"locality"
},
  "geometry": {"coordinates":[104.441,25.0852],"type":"Point"}
}