{
  "type": "Feature",
  "properties": {
    "gn:admin1_code":"13.0",
    "gn:asciiname":"Saghan",
    "gn:country_code":"CN",
    "gn:dem":1433,
    "gn:feature_class":"P",
    "gn:feature_code":"PPL",
    "gn:name":"Saghan",
    "gn:population":0,
    "gn:timezone":"Asia/Shanghai",
    "iso:country":"CN",
    "name:uig_x_preferred":[
        "Sa\u01a3an"
    ],
    "name:uig_x_variant":[
        "Saghan",
        "\u0633\u0627\u063a\u0627\u0646",
        "\u0421\u0430\u0493\u0430\u043d"
    ],
    "name:und_x_variant":[
        "Sa-kan",
        "Sagan",
        "Sagancun"
    ],
    "name:zho_x_preferred":[
        "\u8428\u5e72"
    ],
    "name:zho_x_variant":[
        "\u8428\u5e72\u6751"
    ],
    "wof:name":"Saghan",
    "wof:placetype":"locality"
},
  "geometry": {"coordinates":[78.24345,37.56508],"type":"Point"}
}