{
  "type": "Feature",
  "properties": {
    "gn:admin1_code":"32.0",
    "gn:asciiname":"Yanxiaba",
    "gn:country_code":"CN",
    "gn:dem":710,
    "gn:feature_class":"P",
    "gn:feature_code":"PPL",
    "gn:name":"Yanxiaba",
    "gn:population":0,
    "gn:timezone":"Asia/Shanghai",
    "iso:country":"CN",
    "name:zho_x_preferred":[
        "\u5ca9\u4e0b\u575d"
    ],
    "wof:name":"Yanxiaba",
    "wof:placetype":"locality"
},
  "geometry": {"coordinates":[104.479,28.3566],"type":"Point"}
}