{
  "type": "Feature",
  "properties": {
    "gn:admin1_code":"5.0",
    "gn:asciiname":"Dagujiazicun",
    "gn:country_code":"CN",
    "gn:dem":308,
    "gn:feature_class":"P",
    "gn:feature_code":"PPL",
    "gn:name":"Dagujiazicun",
    "gn:population":0,
    "gn:timezone":"Asia/Shanghai",
    "iso:country":"CN",
    "name:zho_x_preferred":[
        "\u5927\u5b64\u5bb6\u5b50\u6751"
    ],
    "wof:name":"Dagujiazicun",
    "wof:placetype":"locality"
},
  "geometry": {"coordinates":[126.75337,43.80125],"type":"Point"}
}