{
  "type": "Feature",
  "properties": {
    "gn:admin1_code":"14.0",
    "gn:asciiname":"Yuribu",
    "gn:country_code":"CN",
    "gn:dem":4386,
    "gn:feature_class":"P",
    "gn:feature_code":"PPL",
    "gn:name":"Yuribu",
    "gn:population":0,
    "gn:timezone":"Asia/Urumqi",
    "iso:country":"CN",
    "name:zho_x_preferred":[
        "\u7389\u65e5\u5e03"
    ],
    "wof:name":"Yuribu",
    "wof:placetype":"locality"
},
  "geometry": {"coordinates":[83.6854,32.0636],"type":"Point"}
}