{
  "type": "Feature",
  "properties": {
    "gn:admin1_code":"25.0",
    "gn:asciiname":"Xiyugezhuangcun",
    "gn:country_code":"CN",
    "gn:dem":39,
    "gn:feature_class":"P",
    "gn:feature_code":"PPL",
    "gn:name":"Xiyugezhuangcun",
    "gn:population":0,
    "gn:timezone":"Asia/Shanghai",
    "iso:country":"CN",
    "name:zho_x_preferred":[
        "\u897f\u4e8e\u6208\u5e84\u6751"
    ],
    "wof:name":"Xiyugezhuangcun",
    "wof:placetype":"locality"
},
  "geometry": {"coordinates":[119.40273000000001,36.32988],"type":"Point"}
}