{
  "type": "Feature",
  "properties": {
    "gn:admin1_code":"18",
    "gn:asciiname":"Yalaoshan",
    "gn:country_code":"CN",
    "gn:dem":741,
    "gn:feature_class":"P",
    "gn:feature_code":"PPL",
    "gn:name":"Yalaoshan",
    "gn:population":0,
    "gn:timezone":"Asia/Shanghai",
    "iso:country":"CN",
    "name:zho_x_preferred":[
        "\u538b\u8001\u5c71"
    ],
    "wof:name":"Yalaoshan",
    "wof:placetype":"locality"
},
  "geometry": {"coordinates":[107.989,28.2021],"type":"Point"}
}