{
  "type": "Feature",
  "properties": {
    "gn:admin1_code":"24.0",
    "gn:asciiname":"Siyuan",
    "gn:country_code":"CN",
    "gn:dem":1043,
    "gn:feature_class":"P",
    "gn:feature_code":"PPL",
    "gn:name":"Siyuan",
    "gn:population":0,
    "gn:timezone":"Asia/Shanghai",
    "iso:country":"CN",
    "name:zho_x_preferred":[
        "\u56db\u5143"
    ],
    "wof:name":"Siyuan",
    "wof:placetype":"locality"
},
  "geometry": {"coordinates":[112.32221,36.47543],"type":"Point"}
}