{
  "type": "Feature",
  "properties": {
    "gn:admin1_code":"14.0",
    "gn:asciiname":"Gongka",
    "gn:country_code":"CN",
    "gn:dem":4273,
    "gn:feature_class":"P",
    "gn:feature_code":"PPL",
    "gn:name":"Gongka",
    "gn:population":0,
    "gn:timezone":"Asia/Urumqi",
    "iso:country":"CN",
    "name:bod_x_preferred":[
        "Gangka"
    ],
    "name:zho_x_preferred":[
        "\u8d21\u5361"
    ],
    "wof:name":"Gongka",
    "wof:placetype":"locality"
},
  "geometry": {"coordinates":[94.29112000000001,31.50738],"type":"Point"}
}