{
  "type": "Feature",
  "properties": {
    "gn:admin1_code":"10",
    "gn:asciiname":"Fenghuangchi",
    "gn:country_code":"CN",
    "gn:dem":24,
    "gn:feature_class":"P",
    "gn:feature_code":"PPL",
    "gn:name":"Fenghuangchi",
    "gn:population":0,
    "gn:timezone":"Asia/Shanghai",
    "iso:country":"CN",
    "name:zho_x_preferred":[
        "\u51e4\u51f0\u6c60"
    ],
    "wof:name":"Fenghuangchi",
    "wof:placetype":"locality"
},
  "geometry": {"coordinates":[115.602,37.8713],"type":"Point"}
}