{
  "type": "Feature",
  "properties": {
    "gn:admin1_code":"3.0",
    "gn:asciiname":"Dongnankeng",
    "gn:country_code":"CN",
    "gn:dem":192,
    "gn:feature_class":"P",
    "gn:feature_code":"PPL",
    "gn:name":"Dongnankeng",
    "gn:population":0,
    "gn:timezone":"Asia/Shanghai",
    "iso:country":"CN",
    "name:zho_x_preferred":[
        "\u4e1c\u5357\u5751"
    ],
    "wof:name":"Dongnankeng",
    "wof:placetype":"locality"
},
  "geometry": {"coordinates":[118.06638,28.79438],"type":"Point"}
}