{
  "type": "Feature",
  "properties": {
    "gn:admin1_code":"14.0",
    "gn:asciiname":"Songduo",
    "gn:country_code":"CN",
    "gn:dem":5189,
    "gn:feature_class":"P",
    "gn:feature_code":"PPL",
    "gn:name":"Songduo",
    "gn:population":0,
    "gn:timezone":"Asia/Urumqi",
    "iso:country":"CN",
    "name:zho_x_preferred":[
        "\u677e\u591a"
    ],
    "wof:name":"Songduo",
    "wof:placetype":"locality"
},
  "geometry": {"coordinates":[85.8733,30.0352],"type":"Point"}
}