{
  "type": "Feature",
  "properties": {
    "gn:admin1_code":"26",
    "gn:asciiname":"Chenzigoucun",
    "gn:country_code":"CN",
    "gn:dem":1217,
    "gn:feature_class":"P",
    "gn:feature_code":"PPL",
    "gn:name":"Chenzigoucun",
    "gn:population":0,
    "gn:timezone":"Asia/Shanghai",
    "iso:country":"CN",
    "name:und_x_variant":[
        "Ch\u2019en-tzu-kou",
        "Ch\u2019eng-chia-kou",
        "Chenzigou",
        "Chenzigoucun"
    ],
    "name:zho_x_preferred":[
        "\u9648\u5b50\u6c9f\u6751"
    ],
    "wof:name":"Chenzigoucun",
    "wof:placetype":"locality"
},
  "geometry": {"coordinates":[109.60142999999999,36.45527],"type":"Point"}
}