{
  "type": "Feature",
  "properties": {
    "gn:admin1_code":"3",
    "gn:asciiname":"Changfuqiao",
    "gn:country_code":"CN",
    "gn:dem":311,
    "gn:feature_class":"P",
    "gn:feature_code":"PPL",
    "gn:name":"Changfuqiao",
    "gn:population":0,
    "gn:timezone":"Asia/Shanghai",
    "iso:country":"CN",
    "name:zho_x_preferred":[
        "\u957f\u5bcc\u6865"
    ],
    "wof:name":"Changfuqiao",
    "wof:placetype":"locality"
},
  "geometry": {"coordinates":[114.11608,26.69318],"type":"Point"}
}