{
  "type": "Feature",
  "properties": {
    "gn:admin1_code":"18",
    "gn:asciiname":"Tianbazhai",
    "gn:country_code":"CN",
    "gn:dem":1598,
    "gn:feature_class":"P",
    "gn:feature_code":"PPL",
    "gn:name":"Tianbazhai",
    "gn:population":0,
    "gn:timezone":"Asia/Shanghai",
    "iso:country":"CN",
    "name:zho_x_preferred":[
        "\u7530\u575d\u5be8"
    ],
    "wof:name":"Tianbazhai",
    "wof:placetype":"locality"
},
  "geometry": {"coordinates":[105.129,26.3593],"type":"Point"}
}