{
  "type": "Feature",
  "properties": {
    "gn:admin1_code":"22.0",
    "gn:asciiname":"Beitaoyuan",
    "gn:country_code":"CN",
    "gn:dem":28,
    "gn:feature_class":"P",
    "gn:feature_code":"PPL",
    "gn:name":"Beitaoyuan",
    "gn:population":0,
    "gn:timezone":"Asia/Shanghai",
    "iso:country":"CN",
    "name:zho_x_preferred":[
        "\u5317\u6843\u56ed"
    ],
    "wof:name":"Beitaoyuan",
    "wof:placetype":"locality"
},
  "geometry": {"coordinates":[116.72327,40.02881],"type":"Point"}
}