{
  "type": "Feature",
  "properties": {
    "gn:admin1_code":"8.0",
    "gn:asciiname":"Jinmofang",
    "gn:country_code":"CN",
    "gn:dem":269,
    "gn:feature_class":"P",
    "gn:feature_code":"PPL",
    "gn:name":"Jinmofang",
    "gn:population":0,
    "gn:timezone":"Asia/Shanghai",
    "iso:country":"CN",
    "name:zho_x_preferred":[
        "\u91d1\u78e8\u623f"
    ],
    "wof:name":"Jinmofang",
    "wof:placetype":"locality"
},
  "geometry": {"coordinates":[127.93711999999999,45.43796],"type":"Point"}
}