{
  "type": "Feature",
  "properties": {
    "gn:admin1_code":"10.0",
    "gn:asciiname":"Anminzhai",
    "gn:country_code":"CN",
    "gn:dem":36,
    "gn:feature_class":"P",
    "gn:feature_code":"PPL",
    "gn:name":"Anminzhai",
    "gn:population":0,
    "gn:timezone":"Asia/Shanghai",
    "iso:country":"CN",
    "name:zho_x_preferred":[
        "\u5b89\u6c11\u5be8"
    ],
    "wof:name":"Anminzhai",
    "wof:placetype":"locality"
},
  "geometry": {"coordinates":[119.6311,40.00482],"type":"Point"}
}