{
  "type": "Feature",
  "properties": {
    "gn:admin1_code":"32.0",
    "gn:asciiname":"Gengduoshe",
    "gn:country_code":"CN",
    "gn:dem":3706,
    "gn:feature_class":"P",
    "gn:feature_code":"PPL",
    "gn:name":"Gengduoshe",
    "gn:population":0,
    "gn:timezone":"Asia/Shanghai",
    "iso:country":"CN",
    "name:zho_x_preferred":[
        "\u66f4\u591a\u793e"
    ],
    "wof:name":"Gengduoshe",
    "wof:placetype":"locality"
},
  "geometry": {"coordinates":[98.40559,32.09529000000001],"type":"Point"}
}