{
  "type": "Feature",
  "properties": {
    "gn:admin1_code":"3",
    "gn:asciiname":"Xiayangqiu",
    "gn:country_code":"CN",
    "gn:dem":83,
    "gn:feature_class":"P",
    "gn:feature_code":"PPL",
    "gn:name":"Xiayangqiu",
    "gn:population":0,
    "gn:timezone":"Asia/Shanghai",
    "iso:country":"CN",
    "name:und_x_variant":[
        "\u4e0b\u9633\u4e18",
        "Yangqiu"
    ],
    "wof:name":"Xiayangqiu",
    "wof:placetype":"locality"
},
  "geometry": {"coordinates":[115.09954999999999,26.72562000000001],"type":"Point"}
}