{
  "type": "Feature",
  "properties": {
    "gn:admin1_code":"10.0",
    "gn:asciiname":"Xibeizhuang",
    "gn:country_code":"CN",
    "gn:dem":11,
    "gn:feature_class":"P",
    "gn:feature_code":"PPL",
    "gn:name":"Xibeizhuang",
    "gn:population":0,
    "gn:timezone":"Asia/Shanghai",
    "iso:country":"CN",
    "name:zho_x_preferred":[
        "\u897f\u5317\u5e84"
    ],
    "wof:name":"Xibeizhuang",
    "wof:placetype":"locality"
},
  "geometry": {"coordinates":[116.575,38.3986],"type":"Point"}
}