{
  "type": "Feature",
  "properties": {
    "gn:admin1_code":"29",
    "gn:asciiname":"Changming",
    "gn:country_code":"CN",
    "gn:dem":2111,
    "gn:feature_class":"P",
    "gn:feature_code":"PPL",
    "gn:name":"Changming",
    "gn:population":0,
    "gn:timezone":"Asia/Shanghai",
    "iso:country":"CN",
    "name:zho_x_preferred":[
        "\u660c\u660e"
    ],
    "wof:name":"Changming",
    "wof:placetype":"locality"
},
  "geometry": {"coordinates":[102.401,23.9239],"type":"Point"}
}