{
  "type": "Feature",
  "properties": {
    "gn:admin1_code":"3.0",
    "gn:asciiname":"Wutongyuan",
    "gn:country_code":"CN",
    "gn:dem":100,
    "gn:feature_class":"P",
    "gn:feature_code":"PPL",
    "gn:name":"Wutongyuan",
    "gn:population":0,
    "gn:timezone":"Asia/Shanghai",
    "iso:country":"CN",
    "name:und_x_variant":[
        "\u68a7\u6850\u6e90"
    ],
    "wof:name":"Wutongyuan",
    "wof:placetype":"locality"
},
  "geometry": {"coordinates":[116.51411,27.14028],"type":"Point"}
}