{
  "type": "Feature",
  "properties": {
    "gn:admin1_code":"5.0",
    "gn:asciiname":"Fengmicun",
    "gn:country_code":"CN",
    "gn:dem":181,
    "gn:feature_class":"P",
    "gn:feature_code":"PPL",
    "gn:name":"Fengmicun",
    "gn:population":0,
    "gn:timezone":"Asia/Shanghai",
    "iso:country":"CN",
    "name:zho_x_preferred":[
        "\u8702\u871c\u6751"
    ],
    "wof:name":"Fengmicun",
    "wof:placetype":"locality"
},
  "geometry": {"coordinates":[126.35738000000001,44.30419000000001],"type":"Point"}
}