{
  "type": "Feature",
  "properties": {
    "gn:admin1_code":"19.0",
    "gn:asciiname":"Julikecun",
    "gn:country_code":"CN",
    "gn:dem":277,
    "gn:feature_class":"P",
    "gn:feature_code":"PPL",
    "gn:name":"Julikecun",
    "gn:population":0,
    "gn:timezone":"Asia/Shanghai",
    "iso:country":"CN",
    "name:zho_x_preferred":[
        "\u5de8\u529b\u514b\u6751"
    ],
    "wof:name":"Julikecun",
    "wof:placetype":"locality"
},
  "geometry": {"coordinates":[121.681,42.1875],"type":"Point"}
}