{
  "type": "Feature",
  "properties": {
    "gn:admin1_code":"3.0",
    "gn:asciiname":"Beixiacun",
    "gn:country_code":"CN",
    "gn:dem":47,
    "gn:feature_class":"P",
    "gn:feature_code":"PPL",
    "gn:name":"Beixiacun",
    "gn:population":0,
    "gn:timezone":"Asia/Shanghai",
    "iso:country":"CN",
    "name:und_x_variant":[
        "\u9642\u4e0b\u6751"
    ],
    "wof:name":"Beixiacun",
    "wof:placetype":"locality"
},
  "geometry": {"coordinates":[115.42146,28.8316],"type":"Point"}
}