{
  "type": "Feature",
  "properties": {
    "gn:admin1_code":"9",
    "gn:asciiname":"Qianwanglou",
    "gn:country_code":"CN",
    "gn:dem":45,
    "gn:feature_class":"P",
    "gn:feature_code":"PPL",
    "gn:name":"Qianwanglou",
    "gn:population":0,
    "gn:timezone":"Asia/Shanghai",
    "iso:country":"CN",
    "name:zho_x_preferred":[
        "\u524d\u738b\u697c"
    ],
    "wof:name":"Qianwanglou",
    "wof:placetype":"locality"
},
  "geometry": {"coordinates":[115.81204,36.00843],"type":"Point"}
}