{
  "type": "Feature",
  "properties": {
    "gn:admin1_code":"18.0",
    "gn:asciiname":"Shibanhe",
    "gn:country_code":"CN",
    "gn:dem":1102,
    "gn:feature_class":"P",
    "gn:feature_code":"PPL",
    "gn:name":"Shibanhe",
    "gn:population":0,
    "gn:timezone":"Asia/Shanghai",
    "iso:country":"CN",
    "name:zho_x_preferred":[
        "\u77f3\u677f\u6cb3"
    ],
    "wof:name":"Shibanhe",
    "wof:placetype":"locality"
},
  "geometry": {"coordinates":[107.39700000000001,26.5012],"type":"Point"}
}