{
  "type": "Feature",
  "properties": {
    "gn:admin1_code":"24.0",
    "gn:asciiname":"Jinjiazhuang",
    "gn:country_code":"CN",
    "gn:dem":1564,
    "gn:feature_class":"P",
    "gn:feature_code":"PPL",
    "gn:name":"Jinjiazhuang",
    "gn:population":0,
    "gn:timezone":"Asia/Shanghai",
    "iso:country":"CN",
    "name:zho_x_preferred":[
        "\u91d1\u5bb6\u5e84"
    ],
    "wof:name":"Jinjiazhuang",
    "wof:placetype":"locality"
},
  "geometry": {"coordinates":[112.41970000000001,38.62109],"type":"Point"}
}