{
  "type": "Feature",
  "properties": {
    "gn:admin1_code":"7.0",
    "gn:asciiname":"Hutou",
    "gn:country_code":"CN",
    "gn:dem":722,
    "gn:feature_class":"P",
    "gn:feature_code":"PPL",
    "gn:name":"Hutou",
    "gn:population":0,
    "gn:timezone":"Asia/Shanghai",
    "iso:country":"CN",
    "name:und_x_variant":[
        "\u6e56\u5934"
    ],
    "name:zho_x_preferred":[
        "\u6e56\u5934"
    ],
    "wof:name":"Hutou",
    "wof:placetype":"locality"
},
  "geometry": {"coordinates":[116.6121,26.3585],"type":"Point"}
}