{
  "type": "Feature",
  "properties": {
    "gn:admin1_code":"1.0",
    "gn:asciiname":"Hengtanggangcun",
    "gn:country_code":"CN",
    "gn:dem":74,
    "gn:feature_class":"P",
    "gn:feature_code":"PPL",
    "gn:name":"Hengtanggangcun",
    "gn:population":0,
    "gn:timezone":"Asia/Shanghai",
    "iso:country":"CN",
    "name:und_x_variant":[
        "Hengtanggang"
    ],
    "name:zho_x_preferred":[
        "\u6a2a\u5858\u5c97\u6751"
    ],
    "wof:name":"Hengtanggangcun",
    "wof:placetype":"locality"
},
  "geometry": {"coordinates":[116.49039999999999,31.53561],"type":"Point"}
}