{
  "type": "Feature",
  "properties": {
    "gn:admin1_code":"18",
    "gn:asciiname":"Liushuigou",
    "gn:country_code":"CN",
    "gn:dem":1363,
    "gn:feature_class":"P",
    "gn:feature_code":"PPL",
    "gn:name":"Liushuigou",
    "gn:population":0,
    "gn:timezone":"Asia/Shanghai",
    "iso:country":"CN",
    "name:zho_x_preferred":[
        "\u6d41\u6c34\u6c9f"
    ],
    "wof:name":"Liushuigou",
    "wof:placetype":"locality"
},
  "geometry": {"coordinates":[105.19799999999999,25.4322],"type":"Point"}
}