{
  "type": "Feature",
  "properties": {
    "gn:admin1_code":"32.0",
    "gn:asciiname":"Jiajiao",
    "gn:country_code":"CN",
    "gn:dem":423,
    "gn:feature_class":"P",
    "gn:feature_code":"PPL",
    "gn:name":"Jiajiao",
    "gn:population":0,
    "gn:timezone":"Asia/Shanghai",
    "iso:country":"CN",
    "name:zho_x_preferred":[
        "\u5047\u89d2"
    ],
    "wof:name":"Jiajiao",
    "wof:placetype":"locality"
},
  "geometry": {"coordinates":[106.58799999999999,31.1793],"type":"Point"}
}