{
  "type": "Feature",
  "properties": {
    "gn:admin1_code":"11.0",
    "gn:asciiname":"Huangmaolun",
    "gn:country_code":"CN",
    "gn:dem":181,
    "gn:feature_class":"P",
    "gn:feature_code":"PPL",
    "gn:name":"Huangmaolun",
    "gn:population":0,
    "gn:timezone":"Asia/Shanghai",
    "iso:country":"CN",
    "name:zho_x_preferred":[
        "\u9ec4\u6bdb\u4ed1"
    ],
    "wof:name":"Huangmaolun",
    "wof:placetype":"locality"
},
  "geometry": {"coordinates":[111.69444,28.24077],"type":"Point"}
}