{
  "type": "Feature",
  "properties": {
    "gn:admin1_code":"4.0",
    "gn:asciiname":"Touzhuangcun",
    "gn:country_code":"CN",
    "gn:dem":-3,
    "gn:feature_class":"P",
    "gn:feature_code":"PPL",
    "gn:name":"Touzhuangcun",
    "gn:population":0,
    "gn:timezone":"Asia/Shanghai",
    "iso:country":"CN",
    "name:und_x_variant":[
        "Touzhuang",
        "\u5934\u5e84",
        "Touzhuangcun"
    ],
    "name:zho_x_preferred":[
        "\u5934\u5e84\u6751"
    ],
    "wof:name":"Touzhuangcun",
    "wof:placetype":"locality"
},
  "geometry": {"coordinates":[120.2063,34.10107],"type":"Point"}
}