{
  "type": "Feature",
  "properties": {
    "gn:admin1_code":"16.0",
    "gn:asciiname":"Dajiang",
    "gn:country_code":"CN",
    "gn:dem":682,
    "gn:feature_class":"P",
    "gn:feature_code":"PPL",
    "gn:name":"Dajiang",
    "gn:population":0,
    "gn:timezone":"Asia/Shanghai",
    "iso:country":"CN",
    "name:ceb_x_preferred":[
        "Dajiang"
    ],
    "name:swe_x_preferred":[
        "Dajiang"
    ],
    "name:zho_x_preferred":[
        "\u8fbe\u6c5f"
    ],
    "wof:name":"Dajiang",
    "wof:placetype":"locality"
},
  "geometry": {"coordinates":[108.52200000000001,25.3586],"type":"Point"}
}