{
  "type": "Feature",
  "properties": {
    "gn:admin1_code":"15.0",
    "gn:asciiname":"Shaoguowan",
    "gn:country_code":"CN",
    "gn:dem":1342,
    "gn:feature_class":"P",
    "gn:feature_code":"PPL",
    "gn:name":"Shaoguowan",
    "gn:population":0,
    "gn:timezone":"Asia/Shanghai",
    "iso:country":"CN",
    "name:zho_x_preferred":[
        "\u70e7\u9505\u6e7e"
    ],
    "wof:name":"Shaoguowan",
    "wof:placetype":"locality"
},
  "geometry": {"coordinates":[107.43899999999999,35.9376],"type":"Point"}
}