{
  "type": "Feature",
  "properties": {
    "gn:admin1_code":"14.0",
    "gn:asciiname":"Gala",
    "gn:country_code":"CN",
    "gn:dem":4445,
    "gn:feature_class":"P",
    "gn:feature_code":"PPLA4",
    "gn:name":"Gala",
    "gn:population":0,
    "gn:timezone":"Asia/Urumqi",
    "iso:country":"CN",
    "name:ara_x_preferred":[
        "\u063a\u0627\u0644\u0627"
    ],
    "name:bod_x_preferred":[
        "Gala"
    ],
    "name:fas_x_preferred":[
        "\u06af\u0627\u0644\u0627"
    ],
    "name:msa_x_preferred":[
        "Gala"
    ],
    "name:und_x_variant":[
        "Kalbashar",
        "K\u2019a-la",
        "K\u2019ai-la",
        "Kalashar",
        "K\u2019a-la-sha-erh",
        "K\u2019a-la-sha",
        "K\u2019a-la-sa",
        "Gala",
        "Gala Xiang"
    ],
    "name:zho_x_preferred":[
        "\u560e\u62c9"
    ],
    "name:zho_x_variant":[
        "Galaxia",
        "\u560e\u62c9\u590f",
        "\u560e\u62c9\u4e61"
    ],
    "wof:name":"Gala",
    "wof:placetype":"locality"
},
  "geometry": {"coordinates":[89.38186999999998,28.26311],"type":"Point"}
}