{
  "type": "Feature",
  "properties": {
    "gn:admin1_code":"10.0",
    "gn:asciiname":"Longmenpo",
    "gn:country_code":"CN",
    "gn:dem":841,
    "gn:feature_class":"P",
    "gn:feature_code":"PPL",
    "gn:name":"Longmenpo",
    "gn:population":0,
    "gn:timezone":"Asia/Shanghai",
    "iso:country":"CN",
    "name:zho_x_preferred":[
        "\u9f99\u95e8\u5761"
    ],
    "wof:name":"Longmenpo",
    "wof:placetype":"locality"
},
  "geometry": {"coordinates":[114.97165,40.46969],"type":"Point"}
}