{
  "type": "Feature",
  "properties": {
    "gn:admin1_code":"18.0",
    "gn:asciiname":"Shanjiaozhai",
    "gn:country_code":"CN",
    "gn:dem":1007,
    "gn:feature_class":"P",
    "gn:feature_code":"PPL",
    "gn:name":"Shanjiaozhai",
    "gn:population":0,
    "gn:timezone":"Asia/Shanghai",
    "iso:country":"CN",
    "name:zho_x_preferred":[
        "\u5c71\u811a\u5be8"
    ],
    "wof:name":"Shanjiaozhai",
    "wof:placetype":"locality"
},
  "geometry": {"coordinates":[107.518,25.9062],"type":"Point"}
}