{
  "type": "Feature",
  "properties": {
    "gn:admin1_code":"26.0",
    "gn:asciiname":"Yinlaowan",
    "gn:country_code":"CN",
    "gn:dem":1142,
    "gn:feature_class":"P",
    "gn:feature_code":"PPL",
    "gn:name":"Yinlaowan",
    "gn:population":0,
    "gn:timezone":"Asia/Shanghai",
    "iso:country":"CN",
    "name:zho_x_preferred":[
        "\u94f6\u8001\u6e7e"
    ],
    "wof:name":"Yinlaowan",
    "wof:placetype":"locality"
},
  "geometry": {"coordinates":[110.12099000000001,38.51494],"type":"Point"}
}