{
  "type": "Feature",
  "properties": {
    "gn:admin1_code":"26.0",
    "gn:asciiname":"Qianhua'eryuan",
    "gn:country_code":"CN",
    "gn:dem":1219,
    "gn:feature_class":"P",
    "gn:feature_code":"PPL",
    "gn:name":"Qianhua\u2019eryuan",
    "gn:population":0,
    "gn:timezone":"Asia/Shanghai",
    "iso:country":"CN",
    "name:und_x_variant":[
        "Qianhua\u2019eryuan"
    ],
    "name:zho_x_preferred":[
        "\u524d\u82b1\u513f\u586c"
    ],
    "wof:name":"Qianhua'eryuan",
    "wof:placetype":"locality"
},
  "geometry": {"coordinates":[109.10218999999999,35.96898],"type":"Point"}
}