{
  "type": "Feature",
  "properties": {
    "gn:admin1_code":"15.0",
    "gn:asciiname":"Longchigou",
    "gn:country_code":"CN",
    "gn:dem":1075,
    "gn:feature_class":"P",
    "gn:feature_code":"PPL",
    "gn:name":"Longchigou",
    "gn:population":0,
    "gn:timezone":"Asia/Shanghai",
    "iso:country":"CN",
    "name:und_x_variant":[
        "\u9f99\u6c60\u6c9f"
    ],
    "wof:name":"Longchigou",
    "wof:placetype":"locality"
},
  "geometry": {"coordinates":[105.77956,33.76049],"type":"Point"}
}