{
  "type": "Feature",
  "properties": {
    "gn:admin1_code":"30.0",
    "gn:asciiname":"Tianchengwei",
    "gn:country_code":"CN",
    "gn:dem":-3,
    "gn:feature_class":"P",
    "gn:feature_code":"PPL",
    "gn:name":"Tianchengwei",
    "gn:population":0,
    "gn:timezone":"Asia/Shanghai",
    "iso:country":"CN",
    "name:zho_x_preferred":[
        "\u5929\u6210\u56f4"
    ],
    "wof:name":"Tianchengwei",
    "wof:placetype":"locality"
},
  "geometry": {"coordinates":[113.28672,22.68134],"type":"Point"}
}