{
  "type": "Feature",
  "properties": {
    "gn:admin1_code":"29.0",
    "gn:asciiname":"Qilonggou",
    "gn:country_code":"CN",
    "gn:dem":1854,
    "gn:feature_class":"P",
    "gn:feature_code":"PPL",
    "gn:name":"Qilonggou",
    "gn:population":0,
    "gn:timezone":"Asia/Shanghai",
    "iso:country":"CN",
    "name:zho_x_preferred":[
        "\u9a91\u9f99\u6c9f"
    ],
    "wof:name":"Qilonggou",
    "wof:placetype":"locality"
},
  "geometry": {"coordinates":[104.345,27.5759],"type":"Point"}
}