{
  "type": "Feature",
  "properties": {
    "gn:admin1_code":"15.0",
    "gn:asciiname":"Baoshe",
    "gn:country_code":"CN",
    "gn:dem":1361,
    "gn:feature_class":"P",
    "gn:feature_code":"PPL",
    "gn:name":"Baoshe",
    "gn:population":0,
    "gn:timezone":"Asia/Shanghai",
    "iso:country":"CN",
    "name:zho_x_preferred":[
        "\u62a5\u793e"
    ],
    "wof:name":"Baoshe",
    "wof:placetype":"locality"
},
  "geometry": {"coordinates":[108.45999999999999,36.3022],"type":"Point"}
}