{
  "type": "Feature",
  "properties": {
    "gn:admin1_code":"11",
    "gn:asciiname":"Congshuwang",
    "gn:country_code":"CN",
    "gn:dem":200,
    "gn:feature_class":"P",
    "gn:feature_code":"PPL",
    "gn:name":"Congshuwang",
    "gn:population":0,
    "gn:timezone":"Asia/Shanghai",
    "iso:country":"CN",
    "name:und_x_variant":[
        "\u679e\u6811\u6c6a",
        "Congshuwang"
    ],
    "wof:name":"Congshuwang",
    "wof:placetype":"locality"
},
  "geometry": {"coordinates":[111.80889000000001,25.50167],"type":"Point"}
}