{
  "type": "Feature",
  "properties": {
    "gn:admin1_code":"10.0",
    "gn:asciiname":"Yutian",
    "gn:country_code":"CN",
    "gn:dem":19,
    "gn:feature_class":"P",
    "gn:feature_code":"PPLA3",
    "gn:name":"Yutian",
    "gn:population":0,
    "gn:timezone":"Asia/Shanghai",
    "iso:country":"CN",
    "name:und_x_variant":[
        "Y\u00fc-t\u2019ien-hsien",
        "Y\u00fc-t\u2019ien-ch\u2019eng-kuan",
        "Y\u00fc-t\u2019ien",
        "Yutian"
    ],
    "name:zho_x_preferred":[
        "\u7389\u7530"
    ],
    "wof:name":"Yutian",
    "wof:placetype":"locality"
},
  "geometry": {"coordinates":[117.73917,39.87861],"type":"Point"}
}