{
  "type": "Feature",
  "properties": {
    "gn:admin1_code":"10.0",
    "gn:asciiname":"Yutian",
    "gn:country_code":"CN",
    "gn:dem":19,
    "gn:feature_class":"P",
    "gn:feature_code":"PPLA3",
    "gn:name":"Yutian",
    "gn:population":0,
    "gn:timezone":"Asia/Shanghai",
    "iso:country":"CN",
    "name:deu_x_preferred":[
        "Yutian"
    ],
    "name:fas_x_preferred":[
        "\u0634\u0647\u0631\u0633\u062a\u0627\u0646 \u06cc\u0648\u062a\u06cc\u0627\u0646"
    ],
    "name:jpn_x_preferred":[
        "\u7389\u7530\u770c"
    ],
    "name:kor_x_preferred":[
        "\uc704\ud188\ud604"
    ],
    "name:nor_x_preferred":[
        "Yutian"
    ],
    "name:rus_x_preferred":[
        "\u042e\u0439\u0442\u044f\u043d\u044c"
    ],
    "name:swe_x_preferred":[
        "Yutian"
    ],
    "name:und_x_variant":[
        "Y\u00fc-t\u2019ien-hsien",
        "Y\u00fc-t\u2019ien-ch\u2019eng-kuan",
        "Y\u00fc-t\u2019ien",
        "Yutian"
    ],
    "name:urd_x_preferred":[
        "\u06cc\u062a\u06cc\u0646 \u06a9\u0627\u0624\u0646\u0679\u06cc"
    ],
    "name:vie_x_preferred":[
        "Ng\u1ecdc \u0110i\u1ec1n"
    ],
    "name:zho_x_preferred":[
        "\u7389\u7530"
    ],
    "name:zho_x_variant":[
        "\u7389\u7530\u53bf"
    ],
    "wof:name":"Yutian",
    "wof:placetype":"locality"
},
  "geometry": {"coordinates":[117.73917,39.87861],"type":"Point"}
}