{
  "type": "Feature",
  "properties": {
    "gn:admin1_code":"32.0",
    "gn:asciiname":"Shanya",
    "gn:country_code":"CN",
    "gn:dem":777,
    "gn:feature_class":"P",
    "gn:feature_code":"PPL",
    "gn:name":"Shanya",
    "gn:population":0,
    "gn:timezone":"Asia/Shanghai",
    "iso:country":"CN",
    "name:zho_x_preferred":[
        "\u5c71\u57ad"
    ],
    "wof:name":"Shanya",
    "wof:placetype":"locality"
},
  "geometry": {"coordinates":[105.79900000000001,32.5328],"type":"Point"}
}