{
  "type": "Feature",
  "properties": {
    "gn:admin1_code":"5.0",
    "gn:asciiname":"Dailai Gangzi",
    "gn:country_code":"CN",
    "gn:dem":133,
    "gn:feature_class":"P",
    "gn:feature_code":"PPL",
    "gn:name":"Dailai Gangzi",
    "gn:population":0,
    "gn:timezone":"Asia/Shanghai",
    "iso:country":"CN",
    "name:zho_x_preferred":[
        "\u4ee3\u6765\u5c97\u5b50"
    ],
    "wof:name":"Dailai Gangzi",
    "wof:placetype":"locality"
},
  "geometry": {"coordinates":[123.88124999999999,45.78984000000001],"type":"Point"}
}