{
  "type": "Feature",
  "properties": {
    "gn:admin1_code":"25",
    "gn:asciiname":"Nandongzhou",
    "gn:country_code":"CN",
    "gn:dem":105,
    "gn:feature_class":"P",
    "gn:feature_code":"PPL",
    "gn:name":"Nandongzhou",
    "gn:population":0,
    "gn:timezone":"Asia/Shanghai",
    "iso:country":"CN",
    "name:zho_x_preferred":[
        "\u5357\u4e1c\u6d32"
    ],
    "wof:name":"Nandongzhou",
    "wof:placetype":"locality"
},
  "geometry": {"coordinates":[118.02,35.2968],"type":"Point"}
}