{
  "type": "Feature",
  "properties": {
    "gn:admin1_code":"29",
    "gn:asciiname":"Shanweiba",
    "gn:country_code":"CN",
    "gn:dem":1965,
    "gn:feature_class":"P",
    "gn:feature_code":"PPL",
    "gn:name":"Shanweiba",
    "gn:population":0,
    "gn:timezone":"Asia/Shanghai",
    "iso:country":"CN",
    "name:zho_x_preferred":[
        "\u5c71\u5c3e\u5df4"
    ],
    "wof:name":"Shanweiba",
    "wof:placetype":"locality"
},
  "geometry": {"coordinates":[101.22499999999999,24.8021],"type":"Point"}
}