{
  "type": "Feature",
  "properties": {
    "gn:admin1_code":"19",
    "gn:asciiname":"Wutong Shugou",
    "gn:country_code":"CN",
    "gn:dem":122,
    "gn:feature_class":"P",
    "gn:feature_code":"PPL",
    "gn:name":"Wutong Shugou",
    "gn:population":0,
    "gn:timezone":"Asia/Shanghai",
    "iso:country":"CN",
    "name:und_x_variant":[
        "\u68a7\u6850\u6811\u6c9f"
    ],
    "wof:name":"Wutong Shugou",
    "wof:placetype":"locality"
},
  "geometry": {"coordinates":[122.80692000000001,40.67021],"type":"Point"}
}