{
  "type": "Feature",
  "properties": {
    "gn:admin1_code":"25.0",
    "gn:asciiname":"Qiantianzhuang",
    "gn:country_code":"CN",
    "gn:dem":42,
    "gn:feature_class":"P",
    "gn:feature_code":"PPL",
    "gn:name":"Qiantianzhuang",
    "gn:population":0,
    "gn:timezone":"Asia/Shanghai",
    "iso:country":"CN",
    "name:zho_x_preferred":[
        "\u524d\u7530\u5e84"
    ],
    "wof:name":"Qiantianzhuang",
    "wof:placetype":"locality"
},
  "geometry": {"coordinates":[119.50816,36.31597],"type":"Point"}
}