{
  "type": "Feature",
  "properties": {
    "gn:admin1_code":"16.0",
    "gn:asciiname":"Bagu",
    "gn:country_code":"CN",
    "gn:dem":916,
    "gn:feature_class":"P",
    "gn:feature_code":"PPL",
    "gn:name":"Bagu",
    "gn:population":0,
    "gn:timezone":"Asia/Shanghai",
    "iso:country":"CN",
    "name:zho_x_preferred":[
        "\u516b\u53e4"
    ],
    "wof:name":"Bagu",
    "wof:placetype":"locality"
},
  "geometry": {"coordinates":[105.316,24.2339],"type":"Point"}
}