{
  "type": "Feature",
  "properties": {
    "gn:admin1_code":"21.0",
    "gn:asciiname":"Tanchangzi",
    "gn:country_code":"CN",
    "gn:dem":1227,
    "gn:feature_class":"P",
    "gn:feature_code":"PPL",
    "gn:name":"Tanchangzi",
    "gn:population":0,
    "gn:timezone":"Asia/Shanghai",
    "iso:country":"CN",
    "name:zho_x_preferred":[
        "\u70ad\u573a\u5b50"
    ],
    "wof:name":"Tanchangzi",
    "wof:placetype":"locality"
},
  "geometry": {"coordinates":[105.17700000000001,37.493],"type":"Point"}
}