{
  "type": "Feature",
  "properties": {
    "gn:admin1_code":"11",
    "gn:asciiname":"Zhujindu",
    "gn:country_code":"CN",
    "gn:dem":51,
    "gn:feature_class":"P",
    "gn:feature_code":"PPL",
    "gn:name":"Zhujindu",
    "gn:population":0,
    "gn:timezone":"Asia/Shanghai",
    "iso:country":"CN",
    "name:zho_x_preferred":[
        "\u6d19\u6d25\u6e21"
    ],
    "wof:name":"Zhujindu",
    "wof:placetype":"locality"
},
  "geometry": {"coordinates":[112.4773,27.69763],"type":"Point"}
}