{
  "type": "Feature",
  "properties": {
    "gn:admin1_code":"30.0",
    "gn:asciiname":"Heinitang",
    "gn:country_code":"CN",
    "gn:dem":24,
    "gn:feature_class":"P",
    "gn:feature_code":"PPL",
    "gn:name":"Heinitang",
    "gn:population":0,
    "gn:timezone":"Asia/Shanghai",
    "iso:country":"CN",
    "name:zho_x_preferred":[
        "\u9ed1\u6ce5\u5858"
    ],
    "wof:name":"Heinitang",
    "wof:placetype":"locality"
},
  "geometry": {"coordinates":[112.52657000000001,22.19029],"type":"Point"}
}