{
  "type": "Feature",
  "properties": {
    "gn:admin1_code":"32.0",
    "gn:asciiname":"Wulongmiaozu",
    "gn:country_code":"CN",
    "gn:dem":758,
    "gn:feature_class":"P",
    "gn:feature_code":"PPL",
    "gn:name":"Wulongmiaozu",
    "gn:population":0,
    "gn:timezone":"Asia/Shanghai",
    "iso:country":"CN",
    "name:zho_x_preferred":[
        "\u4e4c\u9f99\u82d7\u65cf"
    ],
    "wof:name":"Wulongmiaozu",
    "wof:placetype":"locality"
},
  "geometry": {"coordinates":[105.58796,28.07145],"type":"Point"}
}