{
  "type": "Feature",
  "properties": {
    "gn:admin1_code":"3.0",
    "gn:asciiname":"Bingqiu",
    "gn:country_code":"CN",
    "gn:dem":177,
    "gn:feature_class":"P",
    "gn:feature_code":"PPL",
    "gn:name":"Bingqiu",
    "gn:population":0,
    "gn:timezone":"Asia/Shanghai",
    "iso:country":"CN",
    "name:zho_x_preferred":[
        "\u997c\u4e18"
    ],
    "wof:name":"Bingqiu",
    "wof:placetype":"locality"
},
  "geometry": {"coordinates":[115.788,25.8476],"type":"Point"}
}