{
  "type": "Feature",
  "properties": {
    "gn:admin1_code":"14.0",
    "gn:asciiname":"Kangshacun",
    "gn:country_code":"CN",
    "gn:dem":3460,
    "gn:feature_class":"P",
    "gn:feature_code":"PPL",
    "gn:name":"Kangshacun",
    "gn:population":0,
    "gn:timezone":"Asia/Urumqi",
    "iso:country":"CN",
    "name:zho_x_preferred":[
        "\u5eb7\u6c99\u6751"
    ],
    "wof:name":"Kangshacun",
    "wof:placetype":"locality"
},
  "geometry": {"coordinates":[98.21823999999999,29.12294],"type":"Point"}
}