{
  "type": "Feature",
  "properties": {
    "gn:admin1_code":"18",
    "gn:asciiname":"Dashu",
    "gn:country_code":"CN",
    "gn:dem":1618,
    "gn:feature_class":"P",
    "gn:feature_code":"PPL",
    "gn:name":"Dashu",
    "gn:population":0,
    "gn:timezone":"Asia/Shanghai",
    "iso:country":"CN",
    "name:zho_x_preferred":[
        "\u5927\u6811"
    ],
    "wof:name":"Dashu",
    "wof:placetype":"locality"
},
  "geometry": {"coordinates":[105.67100000000001,27.3775],"type":"Point"}
}