{
  "type": "Feature",
  "properties": {
    "gn:admin1_code":"32.0",
    "gn:asciiname":"Guangfochang",
    "gn:country_code":"CN",
    "gn:dem":363,
    "gn:feature_class":"P",
    "gn:feature_code":"PPL",
    "gn:name":"Guangfochang",
    "gn:population":0,
    "gn:timezone":"Asia/Shanghai",
    "iso:country":"CN",
    "name:zho_x_preferred":[
        "\u5e7f\u4f5b\u573a"
    ],
    "wof:name":"Guangfochang",
    "wof:placetype":"locality"
},
  "geometry": {"coordinates":[104.67932,30.19156],"type":"Point"}
}