{
  "type": "Feature",
  "properties": {
    "gn:admin1_code":"18",
    "gn:asciiname":"Huahuazi",
    "gn:country_code":"CN",
    "gn:dem":882,
    "gn:feature_class":"P",
    "gn:feature_code":"PPL",
    "gn:name":"Huahuazi",
    "gn:population":0,
    "gn:timezone":"Asia/Shanghai",
    "iso:country":"CN",
    "name:zho_x_preferred":[
        "\u82b1\u82b1\u5b50"
    ],
    "wof:name":"Huahuazi",
    "wof:placetype":"locality"
},
  "geometry": {"coordinates":[107.265,28.1871],"type":"Point"}
}