{
  "type": "Feature",
  "properties": {
    "gn:admin1_code":"25",
    "gn:asciiname":"Niushanxitou",
    "gn:country_code":"CN",
    "gn:dem":225,
    "gn:feature_class":"P",
    "gn:feature_code":"PPL",
    "gn:name":"Niushanxitou",
    "gn:population":0,
    "gn:timezone":"Asia/Shanghai",
    "iso:country":"CN",
    "name:zho_x_preferred":[
        "\u725b\u5c71\u897f\u5934"
    ],
    "wof:name":"Niushanxitou",
    "wof:placetype":"locality"
},
  "geometry": {"coordinates":[118.59399999999999,36.4487],"type":"Point"}
}