{
  "type": "Feature",
  "properties": {
    "gn:admin1_code":"05",
    "gn:asciiname":"Ch'ang-hsin-p'ing",
    "gn:country_code":"CN",
    "gn:dem":62,
    "gn:feature_class":"P",
    "gn:feature_code":"PPL",
    "gn:name":"Ch\u2019ang-hsin-p\u2019ing",
    "gn:population":0,
    "gn:timezone":"Asia/Shanghai",
    "iso:country":"CN",
    "wof:name":"Ch'ang-hsin-p'ing",
    "wof:placetype":"locality"
},
  "geometry": {"coordinates":[130.44221999999999,42.92194],"type":"Point"}
}