{
  "type": "Feature",
  "properties": {
    "gn:admin1_code":"4.0",
    "gn:asciiname":"Ouhangcun",
    "gn:country_code":"CN",
    "gn:dem":1,
    "gn:feature_class":"P",
    "gn:feature_code":"PPL",
    "gn:name":"Ouhangcun",
    "gn:population":0,
    "gn:timezone":"Asia/Shanghai",
    "iso:country":"CN",
    "name:zho_x_preferred":[
        "\u85d5\u676d\u6751"
    ],
    "wof:name":"Ouhangcun",
    "wof:placetype":"locality"
},
  "geometry": {"coordinates":[120.14209,32.80908],"type":"Point"}
}