{
  "type": "Feature",
  "properties": {
    "gn:admin1_code":"32.0",
    "gn:asciiname":"Songli",
    "gn:country_code":"CN",
    "gn:dem":3434,
    "gn:feature_class":"P",
    "gn:feature_code":"PPL",
    "gn:name":"Songli",
    "gn:population":0,
    "gn:timezone":"Asia/Shanghai",
    "iso:country":"CN",
    "name:zho_x_preferred":[
        "\u677e\u680e"
    ],
    "wof:name":"Songli",
    "wof:placetype":"locality"
},
  "geometry": {"coordinates":[99.3167,28.53],"type":"Point"}
}