{
  "type": "Feature",
  "properties": {
    "gn:admin1_code":"10.0",
    "gn:asciiname":"Chiwawu",
    "gn:country_code":"CN",
    "gn:dem":440,
    "gn:feature_class":"P",
    "gn:feature_code":"PPL",
    "gn:name":"Chiwawu",
    "gn:population":0,
    "gn:timezone":"Asia/Shanghai",
    "iso:country":"CN",
    "name:und_x_variant":[
        "\u8d64\u74e6\u5c4b"
    ],
    "wof:name":"Chiwawu",
    "wof:placetype":"locality"
},
  "geometry": {"coordinates":[114.03496,38.77325],"type":"Point"}
}