{
  "type": "Feature",
  "properties": {
    "gn:admin1_code":"30",
    "gn:asciiname":"Minzhu",
    "gn:country_code":"CN",
    "gn:dem":-2,
    "gn:feature_class":"P",
    "gn:feature_code":"PPL",
    "gn:name":"Minzhu",
    "gn:population":0,
    "gn:timezone":"Asia/Shanghai",
    "iso:country":"CN",
    "name:und_x_variant":[
        "\u6c11\u4e3b"
    ],
    "name:zho_x_preferred":[
        "\u6c11\u4e3b"
    ],
    "wof:name":"Minzhu",
    "wof:placetype":"locality"
},
  "geometry": {"coordinates":[113.77722,22.72111],"type":"Point"}
}