{
  "type": "Feature",
  "properties": {
    "gn:admin1_code":"32.0",
    "gn:asciiname":"Maiziping",
    "gn:country_code":"CN",
    "gn:dem":1399,
    "gn:feature_class":"P",
    "gn:feature_code":"PPL",
    "gn:name":"Maiziping",
    "gn:population":0,
    "gn:timezone":"Asia/Shanghai",
    "iso:country":"CN",
    "name:zho_x_preferred":[
        "\u9ea6\u5b50\u576a"
    ],
    "wof:name":"Maiziping",
    "wof:placetype":"locality"
},
  "geometry": {"coordinates":[103.37470999999999,28.55829],"type":"Point"}
}