{
  "type": "Feature",
  "properties": {
    "gn:admin1_code":"11.0",
    "gn:asciiname":"Haoli",
    "gn:country_code":"CN",
    "gn:dem":219,
    "gn:feature_class":"P",
    "gn:feature_code":"PPL",
    "gn:name":"Haoli",
    "gn:population":0,
    "gn:timezone":"Asia/Shanghai",
    "iso:country":"CN",
    "name:zho_x_preferred":[
        "\u8c6a\u91cc"
    ],
    "wof:name":"Haoli",
    "wof:placetype":"locality"
},
  "geometry": {"coordinates":[112.94963,25.81735],"type":"Point"}
}