{
  "type": "Feature",
  "properties": {
    "gn:admin1_code":"19.0",
    "gn:asciiname":"Baiyangmugoucun",
    "gn:country_code":"CN",
    "gn:dem":105,
    "gn:feature_class":"P",
    "gn:feature_code":"PPL",
    "gn:name":"Baiyangmugoucun",
    "gn:population":0,
    "gn:timezone":"Asia/Shanghai",
    "iso:country":"CN",
    "name:zho_x_preferred":[
        "\u767d\u6768\u6728\u6c9f\u6751"
    ],
    "wof:name":"Baiyangmugoucun",
    "wof:placetype":"locality"
},
  "geometry": {"coordinates":[120.572,40.8124],"type":"Point"}
}