{
  "type": "Feature",
  "properties": {
    "gn:admin1_code":"6.0",
    "gn:asciiname":"Dong'egong",
    "gn:country_code":"CN",
    "gn:dem":4215,
    "gn:feature_class":"P",
    "gn:feature_code":"PPL",
    "gn:name":"Dong\u2019egong",
    "gn:population":0,
    "gn:timezone":"Asia/Urumqi",
    "iso:country":"CN",
    "name:und_x_variant":[
        "Dong\u2019egong"
    ],
    "name:zho_x_preferred":[
        "\u4e1c\u4fc4\u8d21"
    ],
    "wof:name":"Dong'egong",
    "wof:placetype":"locality"
},
  "geometry": {"coordinates":[96.90985999999999,32.41693],"type":"Point"}
}