{
  "type": "Feature",
  "properties": {
    "gn:admin1_code":"32.0",
    "gn:asciiname":"Zhaizishanxiaba",
    "gn:country_code":"CN",
    "gn:dem":491,
    "gn:feature_class":"P",
    "gn:feature_code":"PPL",
    "gn:name":"Zhaizishanxiaba",
    "gn:population":0,
    "gn:timezone":"Asia/Shanghai",
    "iso:country":"CN",
    "name:zho_x_preferred":[
        "\u5be8\u5b50\u5c71\u4e0b\u575d"
    ],
    "wof:name":"Zhaizishanxiaba",
    "wof:placetype":"locality"
},
  "geometry": {"coordinates":[103.59658,30.2888],"type":"Point"}
}