{
  "type": "Feature",
  "properties": {
    "gn:admin1_code":"4.0",
    "gn:asciiname":"Gaozhuangcun",
    "gn:country_code":"CN",
    "gn:dem":3,
    "gn:feature_class":"P",
    "gn:feature_code":"PPL",
    "gn:name":"Gaozhuangcun",
    "gn:population":0,
    "gn:timezone":"Asia/Shanghai",
    "iso:country":"CN",
    "name:zho_x_preferred":[
        "\u90dc\u5e84\u6751"
    ],
    "wof:name":"Gaozhuangcun",
    "wof:placetype":"locality"
},
  "geometry": {"coordinates":[119.72772000000001,32.69952],"type":"Point"}
}