{
  "type": "Feature",
  "properties": {
    "gn:admin1_code":"32.0",
    "gn:asciiname":"Nibiriwo",
    "gn:country_code":"CN",
    "gn:dem":1248,
    "gn:feature_class":"P",
    "gn:feature_code":"PPL",
    "gn:name":"Nibiriwo",
    "gn:population":0,
    "gn:timezone":"Asia/Shanghai",
    "iso:country":"CN",
    "name:zho_x_preferred":[
        "\u5c3c\u6bd4\u65e5\u6da1"
    ],
    "wof:name":"Nibiriwo",
    "wof:placetype":"locality"
},
  "geometry": {"coordinates":[103.3792,28.52457],"type":"Point"}
}