{
  "type": "Feature",
  "properties": {
    "gn:admin1_code":"23.0",
    "gn:asciiname":"Yanhaicun",
    "gn:cc2":"CN",
    "gn:country_code":"CN",
    "gn:dem":5,
    "gn:feature_class":"P",
    "gn:feature_code":"PPL",
    "gn:name":"Yanhaicun",
    "gn:population":0,
    "gn:timezone":"Asia/Shanghai",
    "iso:country":"CN",
    "name:und_x_variant":[
        "Yen-hai-ts\u2019un",
        "Yanhaicun"
    ],
    "wof:name":"Yanhaicun",
    "wof:placetype":"locality"
},
  "geometry": {"coordinates":[121.67583,30.88778],"type":"Point"}
}