{
  "type": "Feature",
  "properties": {
    "gn:admin1_code":"8.0",
    "gn:asciiname":"Xinlongcun",
    "gn:country_code":"CN",
    "gn:dem":160,
    "gn:feature_class":"P",
    "gn:feature_code":"PPL",
    "gn:name":"Xinlongcun",
    "gn:population":0,
    "gn:timezone":"Asia/Shanghai",
    "iso:country":"CN",
    "name:zho_x_preferred":[
        "\u65b0\u9f99\u6751"
    ],
    "wof:name":"Xinlongcun",
    "wof:placetype":"locality"
},
  "geometry": {"coordinates":[129.51114999999999,49.17345],"type":"Point"}
}