{
  "type": "Feature",
  "properties": {
    "gn:admin1_code":"19.0",
    "gn:asciiname":"Xingjiatun",
    "gn:country_code":"CN",
    "gn:dem":154,
    "gn:feature_class":"P",
    "gn:feature_code":"PPL",
    "gn:name":"Xingjiatun",
    "gn:population":0,
    "gn:timezone":"Asia/Shanghai",
    "iso:country":"CN",
    "name:zho_x_preferred":[
        "\u90a2\u5bb6\u5c6f"
    ],
    "wof:name":"Xingjiatun",
    "wof:placetype":"locality"
},
  "geometry": {"coordinates":[124.202,43.1288],"type":"Point"}
}