{
  "type": "Feature",
  "properties": {
    "gn:admin1_code":"4.0",
    "gn:asciiname":"Baonan Bazu",
    "gn:country_code":"CN",
    "gn:dem":5,
    "gn:feature_class":"P",
    "gn:feature_code":"PPLF",
    "gn:name":"Baonan Bazu",
    "gn:population":0,
    "gn:timezone":"Asia/Shanghai",
    "iso:country":"CN",
    "name:zho_x_preferred":[
        "\u5305\u5357\u516b\u7ec4"
    ],
    "wof:name":"Baonan Bazu",
    "wof:placetype":"locality"
},
  "geometry": {"coordinates":[121.42813,32.03991],"type":"Point"}
}