{
  "type": "Feature",
  "properties": {
    "gn:admin1_code":"19.0",
    "gn:asciiname":"Dagangzicun",
    "gn:country_code":"CN",
    "gn:dem":3,
    "gn:feature_class":"P",
    "gn:feature_code":"PPL",
    "gn:name":"Dagangzicun",
    "gn:population":0,
    "gn:timezone":"Asia/Shanghai",
    "iso:country":"CN",
    "name:zho_x_preferred":[
        "\u5927\u5c97\u5b50\u6751"
    ],
    "wof:name":"Dagangzicun",
    "wof:placetype":"locality"
},
  "geometry": {"coordinates":[122.303,40.9481],"type":"Point"}
}