{
  "type": "Feature",
  "properties": {
    "gn:admin1_code":"19.0",
    "gn:asciiname":"Guanbu Wobucun",
    "gn:country_code":"CN",
    "gn:dem":111,
    "gn:feature_class":"P",
    "gn:feature_code":"PPL",
    "gn:name":"Guanbu Wobucun",
    "gn:population":0,
    "gn:timezone":"Asia/Shanghai",
    "iso:country":"CN",
    "name:und_x_variant":[
        "Guanbuwobucun",
        "Guanbu Wobucun"
    ],
    "name:zho_x_preferred":[
        "\u5b98\u5b9d\u7a9d\u5821\u6751"
    ],
    "wof:name":"Guanbu Wobucun",
    "wof:placetype":"locality"
},
  "geometry": {"coordinates":[122.99288,42.76534],"type":"Point"}
}