{
  "type": "Feature",
  "properties": {
    "gn:admin1_code":"15.0",
    "gn:asciiname":"Pushanggou",
    "gn:country_code":"CN",
    "gn:dem":1423,
    "gn:feature_class":"P",
    "gn:feature_code":"PPL",
    "gn:name":"Pushanggou",
    "gn:population":0,
    "gn:timezone":"Asia/Shanghai",
    "iso:country":"CN",
    "name:zho_x_preferred":[
        "\u84b2\u4e0a\u6c9f"
    ],
    "wof:name":"Pushanggou",
    "wof:placetype":"locality"
},
  "geometry": {"coordinates":[98.5829,39.7769],"type":"Point"}
}