{
  "type": "Feature",
  "properties": {
    "gn:admin1_code":"4.0",
    "gn:asciiname":"Shijiabangcun",
    "gn:country_code":"CN",
    "gn:dem":5,
    "gn:feature_class":"P",
    "gn:feature_code":"PPL",
    "gn:name":"Shijiabangcun",
    "gn:population":0,
    "gn:timezone":"Asia/Shanghai",
    "iso:country":"CN",
    "name:und_x_variant":[
        "\u77f3\u5bb6\u6d5c\u6751"
    ],
    "name:zho_x_preferred":[
        "\u77f3\u5bb6\u6d5c\u6751"
    ],
    "wof:name":"Shijiabangcun",
    "wof:placetype":"locality"
},
  "geometry": {"coordinates":[120.38084000000001,31.66773],"type":"Point"}
}