{
  "type": "Feature",
  "properties": {
    "gn:admin1_code":"2.0",
    "gn:asciiname":"Baiyangwu",
    "gn:country_code":"CN",
    "gn:dem":238,
    "gn:feature_class":"P",
    "gn:feature_code":"PPL",
    "gn:name":"Baiyangwu",
    "gn:population":0,
    "gn:timezone":"Asia/Shanghai",
    "iso:country":"CN",
    "name:zho_x_preferred":[
        "\u767d\u6d0b\u575e"
    ],
    "wof:name":"Baiyangwu",
    "wof:placetype":"locality"
},
  "geometry": {"coordinates":[119.21092,29.6946],"type":"Point"}
}