{
  "type": "Feature",
  "properties": {
    "gn:admin1_code":"18.0",
    "gn:asciiname":"Pingzheng",
    "gn:country_code":"CN",
    "gn:dem":1178,
    "gn:feature_class":"P",
    "gn:feature_code":"PPL",
    "gn:name":"Pingzheng",
    "gn:population":0,
    "gn:timezone":"Asia/Shanghai",
    "iso:country":"CN",
    "wof:name":"Pingzheng",
    "wof:placetype":"locality"
},
  "geometry": {"coordinates":[106.50278,27.68917],"type":"Point"}
}