{
  "type": "Feature",
  "properties": {
    "gn:admin1_code":"30.0",
    "gn:asciiname":"Jiangxi",
    "gn:country_code":"CN",
    "gn:dem":5,
    "gn:feature_class":"P",
    "gn:feature_code":"PPL",
    "gn:name":"Jiangxi",
    "gn:population":0,
    "gn:timezone":"Asia/Shanghai",
    "iso:country":"CN",
    "name:rus_x_preferred":[
        "\u0426\u0437\u044f\u043d\u0441\u0438"
    ],
    "name:zho_x_preferred":[
        "\u6c5f\u6eaa"
    ],
    "wof:name":"Jiangxi",
    "wof:placetype":"locality"
},
  "geometry": {"coordinates":[112.70480000000001,23.21169],"type":"Point"}
}