{
  "type": "Feature",
  "properties": {
    "gn:admin1_code":"04",
    "gn:asciiname":"Sanhe",
    "gn:country_code":"CN",
    "gn:dem":8,
    "gn:feature_class":"P",
    "gn:feature_code":"PPLA4",
    "gn:name":"Sanhe",
    "gn:population":0,
    "gn:timezone":"Asia/Shanghai",
    "iso:country":"CN",
    "name:ceb_x_preferred":[
        "Sanhe"
    ],
    "name:deu_x_preferred":[
        "Sanhe"
    ],
    "name:nor_x_preferred":[
        "Sanhe"
    ],
    "name:und_x_variant":[
        "Sanhe Xiang",
        "San-ho-chen",
        "Sanhe",
        "Shangsanhe",
        "\u4e0a\u4e09\u548c",
        "Sanhe Zhen",
        "Shangsanhe Zhen",
        "\u4e09\u548c",
        "\u4e09\u548c\u9547",
        "\u4e0a\u4e09\u548c\u9547"
    ],
    "wof:name":"Sanhe",
    "wof:placetype":"locality"
},
  "geometry": {"coordinates":[121.11514,31.87874],"type":"Point"}
}