{
  "type": "Feature",
  "properties": {
    "gn:admin1_code":"02",
    "gn:asciiname":"Meilinzhen",
    "gn:country_code":"CN",
    "gn:dem":26,
    "gn:feature_class":"P",
    "gn:feature_code":"PPL",
    "gn:name":"Meilinzhen",
    "gn:population":0,
    "gn:timezone":"Asia/Shanghai",
    "iso:country":"CN",
    "name:und_x_variant":[
        "Mei-lin-shih",
        "Meilinzhen"
    ],
    "name:zho_x_preferred":[
        "\u6885\u6797"
    ],
    "wof:name":"Meilinzhen",
    "wof:placetype":"locality"
},
  "geometry": {"coordinates":[121.44288,29.37271],"type":"Point"}
}