{
  "type": "Feature",
  "properties": {
    "gn:admin1_code":"16.0",
    "gn:asciiname":"Guolong",
    "gn:country_code":"CN",
    "gn:dem":755,
    "gn:feature_class":"P",
    "gn:feature_code":"PPL",
    "gn:name":"Guolong",
    "gn:population":0,
    "gn:timezone":"Asia/Shanghai",
    "iso:country":"CN",
    "name:zho_x_preferred":[
        "\u679c\u9686"
    ],
    "wof:name":"Guolong",
    "wof:placetype":"locality"
},
  "geometry": {"coordinates":[107.215,24.4431],"type":"Point"}
}