{
  "type": "Feature",
  "properties": {
    "gn:admin1_code":"15.0",
    "gn:asciiname":"Liuyao",
    "gn:country_code":"CN",
    "gn:dem":1727,
    "gn:feature_class":"P",
    "gn:feature_code":"PPL",
    "gn:name":"Liuyao",
    "gn:population":0,
    "gn:timezone":"Asia/Shanghai",
    "iso:country":"CN",
    "name:zho_x_preferred":[
        "\u5218\u7a91"
    ],
    "wof:name":"Liuyao",
    "wof:placetype":"locality"
},
  "geometry": {"coordinates":[105.51900000000001,34.8901],"type":"Point"}
}