{
  "type": "Feature",
  "properties": {
    "gn:admin1_code":"15.0",
    "gn:asciiname":"Yantaping",
    "gn:country_code":"CN",
    "gn:dem":2340,
    "gn:feature_class":"P",
    "gn:feature_code":"PPL",
    "gn:name":"Yantaping",
    "gn:population":0,
    "gn:timezone":"Asia/Shanghai",
    "iso:country":"CN",
    "name:zho_x_preferred":[
        "\u773c\u5854\u576a"
    ],
    "wof:name":"Yantaping",
    "wof:placetype":"locality"
},
  "geometry": {"coordinates":[104.102,35.3995],"type":"Point"}
}