{
  "type": "Feature",
  "properties": {
    "gn:admin1_code":"4.0",
    "gn:asciiname":"Gaoloucun",
    "gn:country_code":"CN",
    "gn:dem":23,
    "gn:feature_class":"P",
    "gn:feature_code":"PPL",
    "gn:name":"Gaoloucun",
    "gn:population":0,
    "gn:timezone":"Asia/Shanghai",
    "iso:country":"CN",
    "name:zho_x_preferred":[
        "\u6772\u697c\u6751"
    ],
    "wof:name":"Gaoloucun",
    "wof:placetype":"locality"
},
  "geometry": {"coordinates":[118.01129,34.17828],"type":"Point"}
}