{
  "type": "Feature",
  "properties": {
    "gn:admin1_code":"5.0",
    "gn:asciiname":"Sihechuan",
    "gn:country_code":"CN",
    "gn:dem":195,
    "gn:feature_class":"P",
    "gn:feature_code":"PPL",
    "gn:name":"Sihechuan",
    "gn:population":0,
    "gn:timezone":"Asia/Shanghai",
    "iso:country":"CN",
    "name:zho_x_preferred":[
        "\u6cd7\u6cb3\u5ddd"
    ],
    "wof:name":"Sihechuan",
    "wof:placetype":"locality"
},
  "geometry": {"coordinates":[126.50655999999999,44.96451],"type":"Point"}
}