{
  "type": "Feature",
  "properties": {
    "gn:admin1_code":"25",
    "gn:asciiname":"Shilongtou",
    "gn:country_code":"CN",
    "gn:dem":155,
    "gn:feature_class":"P",
    "gn:feature_code":"PPL",
    "gn:name":"Shilongtou",
    "gn:population":0,
    "gn:timezone":"Asia/Shanghai",
    "iso:country":"CN",
    "name:zho_x_preferred":[
        "\u77f3\u9f99\u5934"
    ],
    "wof:name":"Shilongtou",
    "wof:placetype":"locality"
},
  "geometry": {"coordinates":[117.30200000000001,36.2445],"type":"Point"}
}