{
  "type": "Feature",
  "properties": {
    "gn:admin1_code":"30.0",
    "gn:asciiname":"Dabang",
    "gn:country_code":"CN",
    "gn:dem":48,
    "gn:feature_class":"P",
    "gn:feature_code":"PPL",
    "gn:name":"Dabang",
    "gn:population":0,
    "gn:timezone":"Asia/Shanghai",
    "iso:country":"CN",
    "name:por_x_preferred":[
        "Dabang"
    ],
    "name:zho_x_preferred":[
        "\u5927\u90a6"
    ],
    "wof:name":"Dabang",
    "wof:placetype":"locality"
},
  "geometry": {"coordinates":[111.49217,23.19378],"type":"Point"}
}