{
  "type": "Feature",
  "properties": {
    "gn:admin1_code":"29.0",
    "gn:asciiname":"Luluo",
    "gn:country_code":"CN",
    "gn:dem":1069,
    "gn:feature_class":"P",
    "gn:feature_code":"PPL",
    "gn:name":"Luluo",
    "gn:population":0,
    "gn:timezone":"Asia/Shanghai",
    "iso:country":"CN",
    "name:zho_x_preferred":[
        "\u9c81\u6d1b"
    ],
    "wof:name":"Luluo",
    "wof:placetype":"locality"
},
  "geometry": {"coordinates":[98.1189,24.9409],"type":"Point"}
}