{
  "type": "Feature",
  "properties": {
    "gn:admin1_code":"16",
    "gn:asciiname":"Tianweidi",
    "gn:country_code":"CN",
    "gn:dem":155,
    "gn:feature_class":"P",
    "gn:feature_code":"PPL",
    "gn:name":"Tianweidi",
    "gn:population":0,
    "gn:timezone":"Asia/Shanghai",
    "iso:country":"CN",
    "name:zho_x_preferred":[
        "\u7530\u5c3e\u5e95"
    ],
    "wof:name":"Tianweidi",
    "wof:placetype":"locality"
},
  "geometry": {"coordinates":[111.10899999999999,25.9635],"type":"Point"}
}