{
  "type": "Feature",
  "properties": {
    "gn:admin1_code":"26.0",
    "gn:asciiname":"Bailongjingcun",
    "gn:country_code":"CN",
    "gn:dem":1077,
    "gn:feature_class":"P",
    "gn:feature_code":"PPL",
    "gn:name":"Bailongjingcun",
    "gn:population":0,
    "gn:timezone":"Asia/Shanghai",
    "iso:country":"CN",
    "name:zho_x_preferred":[
        "\u767d\u9f99\u4e95\u6751"
    ],
    "wof:name":"Bailongjingcun",
    "wof:placetype":"locality"
},
  "geometry": {"coordinates":[108.18326,32.9672],"type":"Point"}
}