{
  "type": "Feature",
  "properties": {
    "gn:admin1_code":"30",
    "gn:asciiname":"Nizai",
    "gn:country_code":"CN",
    "gn:dem":22,
    "gn:feature_class":"P",
    "gn:feature_code":"PPL",
    "gn:name":"Nizai",
    "gn:population":0,
    "gn:timezone":"Asia/Urumqi",
    "iso:country":"CN",
    "name:zho_x_preferred":[
        "\u576d\u4ed4"
    ],
    "wof:name":"Nizai",
    "wof:placetype":"locality"
},
  "geometry": {"coordinates":[109.92498000000001,21.34305],"type":"Point"}
}