{
  "type": "Feature",
  "properties": {
    "gn:admin1_code":"5.0",
    "gn:asciiname":"Xideshengyong",
    "gn:country_code":"CN",
    "gn:dem":158,
    "gn:feature_class":"P",
    "gn:feature_code":"PPL",
    "gn:name":"Xideshengyong",
    "gn:population":0,
    "gn:timezone":"Asia/Shanghai",
    "iso:country":"CN",
    "name:zho_x_preferred":[
        "\u897f\u5fb7\u76db\u6c38"
    ],
    "wof:name":"Xideshengyong",
    "wof:placetype":"locality"
},
  "geometry": {"coordinates":[122.72987999999999,44.85851],"type":"Point"}
}