{
  "type": "Feature",
  "properties": {
    "gn:admin1_code":"2.0",
    "gn:asciiname":"Lingxia",
    "gn:country_code":"CN",
    "gn:dem":323,
    "gn:feature_class":"P",
    "gn:feature_code":"PPL",
    "gn:name":"Lingxia",
    "gn:population":0,
    "gn:timezone":"Asia/Shanghai",
    "iso:country":"CN",
    "name:und_x_variant":[
        "\u5cad\u4e0b",
        "Lingxia"
    ],
    "wof:name":"Lingxia",
    "wof:placetype":"locality"
},
  "geometry": {"coordinates":[119.01379,29.205],"type":"Point"}
}