{
  "type": "Feature",
  "properties": {
    "gn:admin1_code":"29.0",
    "gn:asciiname":"Najiu",
    "gn:country_code":"CN",
    "gn:dem":2871,
    "gn:feature_class":"P",
    "gn:feature_code":"PPL",
    "gn:name":"Najiu",
    "gn:population":0,
    "gn:timezone":"Asia/Shanghai",
    "iso:country":"CN",
    "name:zho_x_preferred":[
        "\u62ff\u4e45"
    ],
    "wof:name":"Najiu",
    "wof:placetype":"locality"
},
  "geometry": {"coordinates":[98.652,27.8483],"type":"Point"}
}