{
  "type": "Feature",
  "properties": {
    "gn:admin1_code":"11.0",
    "gn:asciiname":"Zhuye Wangjia",
    "gn:country_code":"CN",
    "gn:dem":87,
    "gn:feature_class":"P",
    "gn:feature_code":"PPL",
    "gn:name":"Zhuye Wangjia",
    "gn:population":0,
    "gn:timezone":"Asia/Shanghai",
    "iso:country":"CN",
    "name:zho_x_preferred":[
        "Zhuye Wangjia"
    ],
    "name:zho_x_variant":[
        "\u7af9\u53f6\u738b\u5bb6"
    ],
    "wof:name":"Zhuye Wangjia",
    "wof:placetype":"locality"
},
  "geometry": {"coordinates":[111.85545999999999,29.30158],"type":"Point"}
}