{
  "type": "Feature",
  "properties": {
    "gn:admin1_code":"29.0",
    "gn:asciiname":"Guochang Xinzhai",
    "gn:country_code":"CN",
    "gn:dem":1572,
    "gn:feature_class":"P",
    "gn:feature_code":"PPL",
    "gn:name":"Guochang Xinzhai",
    "gn:population":0,
    "gn:timezone":"Asia/Shanghai",
    "iso:country":"CN",
    "name:zho_x_preferred":[
        "\u9505\u5382\u65b0\u5be8"
    ],
    "wof:name":"Guochang Xinzhai",
    "wof:placetype":"locality"
},
  "geometry": {"coordinates":[104.36799999999999,22.8685],"type":"Point"}
}