{
  "type": "Feature",
  "properties": {
    "gn:admin1_code":"12.0",
    "gn:asciiname":"Xijiachi",
    "gn:country_code":"CN",
    "gn:dem":105,
    "gn:feature_class":"P",
    "gn:feature_code":"PPL",
    "gn:name":"Xijiachi",
    "gn:population":0,
    "gn:timezone":"Asia/Shanghai",
    "iso:country":"CN",
    "name:zho_x_preferred":[
        "\u4e60\u5bb6\u6c60"
    ],
    "wof:name":"Xijiachi",
    "wof:placetype":"locality"
},
  "geometry": {"coordinates":[112.15591999999999,31.98237],"type":"Point"}
}