{
  "type": "Feature",
  "properties": {
    "gn:admin1_code":"8.0",
    "gn:asciiname":"Jiguang Erdui",
    "gn:country_code":"CN",
    "gn:dem":260,
    "gn:feature_class":"P",
    "gn:feature_code":"PPLF",
    "gn:name":"Jiguang Erdui",
    "gn:population":0,
    "gn:timezone":"Asia/Shanghai",
    "iso:country":"CN",
    "name:zho_x_preferred":[
        "\u7ee7\u5149\u4e8c\u961f"
    ],
    "wof:name":"Jiguang Erdui",
    "wof:placetype":"locality"
},
  "geometry": {"coordinates":[124.9807,48.70058],"type":"Point"}
}