{
  "type": "Feature",
  "properties": {
    "gn:admin1_code":"25.0",
    "gn:asciiname":"Sanshuitoucun",
    "gn:country_code":"CN",
    "gn:dem":50,
    "gn:feature_class":"P",
    "gn:feature_code":"PPL",
    "gn:name":"Sanshuitoucun",
    "gn:population":0,
    "gn:timezone":"Asia/Shanghai",
    "iso:country":"CN",
    "name:zho_x_preferred":[
        "\u6563\u6c34\u5934\u6751"
    ],
    "wof:name":"Sanshuitoucun",
    "wof:placetype":"locality"
},
  "geometry": {"coordinates":[120.38536999999999,36.8227],"type":"Point"}
}