{
  "type": "Feature",
  "properties": {
    "gn:admin1_code":"10",
    "gn:asciiname":"Gangyao Huiziying",
    "gn:country_code":"CN",
    "gn:dem":719,
    "gn:feature_class":"P",
    "gn:feature_code":"PPL",
    "gn:name":"Gangyao Huiziying",
    "gn:population":0,
    "gn:timezone":"Asia/Shanghai",
    "iso:country":"CN",
    "name:zho_x_preferred":[
        "\u7f38\u7a91\u56de\u5b50\u8425"
    ],
    "wof:name":"Gangyao Huiziying",
    "wof:placetype":"locality"
},
  "geometry": {"coordinates":[116.85894999999999,41.23721],"type":"Point"}
}