{
  "type": "Feature",
  "properties": {
    "gn:admin1_code":"3.0",
    "gn:asciiname":"Gongjia",
    "gn:country_code":"CN",
    "gn:dem":18,
    "gn:feature_class":"P",
    "gn:feature_code":"PPL",
    "gn:name":"Gongjia",
    "gn:population":0,
    "gn:timezone":"Asia/Shanghai",
    "iso:country":"CN",
    "name:und_x_variant":[
        "\u9f9a\u5bb6"
    ],
    "wof:name":"Gongjia",
    "wof:placetype":"locality"
},
  "geometry": {"coordinates":[115.85612999999999,29.09565],"type":"Point"}
}