{
  "type": "Feature",
  "properties": {
    "gn:admin1_code":"33.0",
    "gn:asciiname":"Heping",
    "gn:country_code":"CN",
    "gn:dem":375,
    "gn:feature_class":"P",
    "gn:feature_code":"PPL",
    "gn:name":"Heping",
    "gn:population":0,
    "gn:timezone":"Asia/Shanghai",
    "iso:country":"CN",
    "name:zho_x_preferred":[
        "\u548c\u5e73"
    ],
    "wof:name":"Heping",
    "wof:placetype":"locality"
},
  "geometry": {"coordinates":[105.72971,29.71607],"type":"Point"}
}