{
  "type": "Feature",
  "properties": {
    "gn:admin1_code":"26.0",
    "gn:asciiname":"Miao'erzui",
    "gn:country_code":"CN",
    "gn:dem":1264,
    "gn:feature_class":"P",
    "gn:feature_code":"PPL",
    "gn:name":"Miao\u2019erzui",
    "gn:population":0,
    "gn:timezone":"Asia/Shanghai",
    "iso:country":"CN",
    "name:und_x_variant":[
        "Miao\u2019erzui"
    ],
    "name:zho_x_preferred":[
        "\u5e99\u513f\u5480"
    ],
    "wof:name":"Miao'erzui",
    "wof:placetype":"locality"
},
  "geometry": {"coordinates":[106.88021999999999,35.06953],"type":"Point"}
}