{
  "type": "Feature",
  "properties": {
    "gn:admin1_code":"30.0",
    "gn:asciiname":"Potouxia",
    "gn:country_code":"CN",
    "gn:dem":146,
    "gn:feature_class":"P",
    "gn:feature_code":"PPL",
    "gn:name":"Potouxia",
    "gn:population":0,
    "gn:timezone":"Asia/Shanghai",
    "iso:country":"CN",
    "name:zho_x_preferred":[
        "Potouxia"
    ],
    "name:zho_x_variant":[
        "\u5761\u5934\u4e0b"
    ],
    "wof:name":"Potouxia",
    "wof:placetype":"locality"
},
  "geometry": {"coordinates":[115.10444,24.25944],"type":"Point"}
}