{
  "type": "Feature",
  "properties": {
    "gn:admin1_code":"19",
    "gn:asciiname":"Congjia Buzi",
    "gn:country_code":"CN",
    "gn:dem":238,
    "gn:feature_class":"P",
    "gn:feature_code":"PPL",
    "gn:name":"Congjia Buzi",
    "gn:population":0,
    "gn:timezone":"Asia/Shanghai",
    "iso:country":"CN",
    "name:und_x_variant":[
        "Congjia Puzi",
        "\u4ece\u5bb6\u5821\u5b50",
        "Congjia Buzi"
    ],
    "wof:name":"Congjia Buzi",
    "wof:placetype":"locality"
},
  "geometry": {"coordinates":[122.41426,40.11799],"type":"Point"}
}