{
  "type": "Feature",
  "properties": {
    "gn:admin1_code":"33",
    "gn:asciiname":"Bailin",
    "gn:cc2":"CN",
    "gn:country_code":"CN",
    "gn:dem":254,
    "gn:feature_class":"P",
    "gn:feature_code":"PPL",
    "gn:name":"Bailin",
    "gn:population":0,
    "gn:timezone":"Asia/Shanghai",
    "iso:country":"CN",
    "name:und_x_variant":[
        "Pai-lin",
        "Bailin"
    ],
    "wof:name":"Bailin",
    "wof:placetype":"locality"
},
  "geometry": {"coordinates":[105.9425,29.16167],"type":"Point"}
}