{
  "type": "Feature",
  "properties": {
    "gn:admin1_code":"8.0",
    "gn:asciiname":"Beiningcun",
    "gn:country_code":"CN",
    "gn:dem":231,
    "gn:feature_class":"P",
    "gn:feature_code":"PPL",
    "gn:name":"Beiningcun",
    "gn:population":0,
    "gn:timezone":"Asia/Shanghai",
    "iso:country":"CN",
    "name:zho_x_preferred":[
        "\u5317\u5b81\u6751"
    ],
    "wof:name":"Beiningcun",
    "wof:placetype":"locality"
},
  "geometry": {"coordinates":[129.66630000000001,45.17075],"type":"Point"}
}