{
  "type": "Feature",
  "properties": {
    "gn:admin1_code":"14.0",
    "gn:asciiname":"Pa'ermacun",
    "gn:country_code":"CN",
    "gn:dem":4363,
    "gn:feature_class":"P",
    "gn:feature_code":"PPL",
    "gn:name":"Pa\u2019ermacun",
    "gn:population":0,
    "gn:timezone":"Asia/Urumqi",
    "iso:country":"CN",
    "name:und_x_variant":[
        "Pa\u2019ermacun"
    ],
    "name:zho_x_preferred":[
        "\u5e15\u5c14\u739b\u6751"
    ],
    "wof:name":"Pa'ermacun",
    "wof:placetype":"locality"
},
  "geometry": {"coordinates":[92.92697,31.45613],"type":"Point"}
}