{
  "type": "Feature",
  "properties": {
    "gn:admin1_code":"15.0",
    "gn:asciiname":"Lijia Xinan Shangcun",
    "gn:country_code":"CN",
    "gn:dem":1766,
    "gn:feature_class":"P",
    "gn:feature_code":"PPL",
    "gn:name":"Lijia Xinan Shangcun",
    "gn:population":0,
    "gn:timezone":"Asia/Shanghai",
    "iso:country":"CN",
    "name:zho_x_preferred":[
        "\u674e\u5bb6\u897f\u5357\u4e0a\u6751"
    ],
    "wof:name":"Lijia Xinan Shangcun",
    "wof:placetype":"locality"
},
  "geometry": {"coordinates":[98.8497,39.414],"type":"Point"}
}