{
  "type": "Feature",
  "properties": {
    "gn:admin1_code":"25.0",
    "gn:asciiname":"Mojia Longtou",
    "gn:country_code":"CN",
    "gn:dem":51,
    "gn:feature_class":"P",
    "gn:feature_code":"PPL",
    "gn:name":"Mojia Longtou",
    "gn:population":0,
    "gn:timezone":"Asia/Shanghai",
    "iso:country":"CN",
    "name:zho_x_preferred":[
        "\u83ab\u5bb6\u9f99\u5934"
    ],
    "wof:name":"Mojia Longtou",
    "wof:placetype":"locality"
},
  "geometry": {"coordinates":[119.00972,35.15824],"type":"Point"}
}