{
  "type": "Feature",
  "properties": {
    "gn:admin1_code":"32.0",
    "gn:asciiname":"Zhuanfangzi",
    "gn:country_code":"CN",
    "gn:dem":501,
    "gn:feature_class":"P",
    "gn:feature_code":"PPL",
    "gn:name":"Zhuanfangzi",
    "gn:population":0,
    "gn:timezone":"Asia/Shanghai",
    "iso:country":"CN",
    "name:zho_x_preferred":[
        "\u7816\u623f\u5b50"
    ],
    "wof:name":"Zhuanfangzi",
    "wof:placetype":"locality"
},
  "geometry": {"coordinates":[104.91385,30.34014],"type":"Point"}
}