{
  "type": "Feature",
  "properties": {
    "gn:admin1_code":"18",
    "gn:asciiname":"Shatangshui",
    "gn:country_code":"CN",
    "gn:dem":809,
    "gn:feature_class":"P",
    "gn:feature_code":"PPL",
    "gn:name":"Shatangshui",
    "gn:population":0,
    "gn:timezone":"Asia/Shanghai",
    "iso:country":"CN",
    "name:zho_x_preferred":[
        "\u6c99\u5858\u6c34"
    ],
    "wof:name":"Shatangshui",
    "wof:placetype":"locality"
},
  "geometry": {"coordinates":[107.483,27.5922],"type":"Point"}
}