{
  "type": "Feature",
  "properties": {
    "gn:admin1_code":"30",
    "gn:asciiname":"Shuangshezai",
    "gn:country_code":"CN",
    "gn:dem":203,
    "gn:feature_class":"P",
    "gn:feature_code":"PPL",
    "gn:name":"Shuangshezai",
    "gn:population":0,
    "gn:timezone":"Asia/Shanghai",
    "iso:country":"CN",
    "name:zho_x_preferred":[
        "\u53cc\u793e\u4ed4"
    ],
    "wof:name":"Shuangshezai",
    "wof:placetype":"locality"
},
  "geometry": {"coordinates":[115.62739999999999,24.14335],"type":"Point"}
}