{
  "type": "Feature",
  "properties": {
    "gn:admin1_code":"15.0",
    "gn:asciiname":"Haojiashan",
    "gn:country_code":"CN",
    "gn:dem":1699,
    "gn:feature_class":"P",
    "gn:feature_code":"PPL",
    "gn:name":"Haojiashan",
    "gn:population":0,
    "gn:timezone":"Asia/Shanghai",
    "iso:country":"CN",
    "name:und_x_variant":[
        "\u90dd\u5bb6\u5c71"
    ],
    "wof:name":"Haojiashan",
    "wof:placetype":"locality"
},
  "geometry": {"coordinates":[105.11303999999998,33.05924],"type":"Point"}
}