{
  "type": "Feature",
  "properties": {
    "gn:admin1_code":"19.0",
    "gn:asciiname":"Qianmajiagou",
    "gn:country_code":"CN",
    "gn:dem":138,
    "gn:feature_class":"P",
    "gn:feature_code":"PPL",
    "gn:name":"Qianmajiagou",
    "gn:population":0,
    "gn:timezone":"Asia/Shanghai",
    "iso:country":"CN",
    "name:und_x_variant":[
        "\u524d\u9a6c\u5bb6\u6c9f"
    ],
    "name:zho_x_preferred":[
        "\u524d\u9a6c\u5bb6\u6c9f"
    ],
    "wof:name":"Qianmajiagou",
    "wof:placetype":"locality"
},
  "geometry": {"coordinates":[124.14700999999999,42.49578],"type":"Point"}
}