{
  "type": "Feature",
  "properties": {
    "gn:admin1_code":"32.0",
    "gn:asciiname":"Shuiguanyin",
    "gn:country_code":"CN",
    "gn:dem":646,
    "gn:feature_class":"P",
    "gn:feature_code":"PPL",
    "gn:name":"Shuiguanyin",
    "gn:population":0,
    "gn:timezone":"Asia/Shanghai",
    "iso:country":"CN",
    "name:zho_x_preferred":[
        "\u6c34\u89c2\u97f3"
    ],
    "wof:name":"Shuiguanyin",
    "wof:placetype":"locality"
},
  "geometry": {"coordinates":[104.57365,31.12876],"type":"Point"}
}