{
  "type": "Feature",
  "properties": {
    "gn:admin1_code":"16.0",
    "gn:asciiname":"Qingjing",
    "gn:country_code":"CN",
    "gn:dem":194,
    "gn:feature_class":"P",
    "gn:feature_code":"PPL",
    "gn:name":"Qingjing",
    "gn:population":0,
    "gn:timezone":"Asia/Shanghai",
    "iso:country":"CN",
    "name:zho_x_preferred":[
        "\u6e05\u51c0"
    ],
    "wof:name":"Qingjing",
    "wof:placetype":"locality"
},
  "geometry": {"coordinates":[108.18300000000001,22.2874],"type":"Point"}
}