{
  "type": "Feature",
  "properties": {
    "gn:admin1_code":"32",
    "gn:asciiname":"Jinxian",
    "gn:country_code":"CN",
    "gn:dem":716,
    "gn:feature_class":"P",
    "gn:feature_code":"PPL",
    "gn:name":"Jinxian",
    "gn:population":0,
    "gn:timezone":"Asia/Shanghai",
    "iso:country":"CN",
    "name:und_x_variant":[
        "Jinxianchang",
        "Jinxian"
    ],
    "name:zho_x_preferred":[
        "\u91d1\u4ed9"
    ],
    "wof:name":"Jinxian",
    "wof:placetype":"locality"
},
  "geometry": {"coordinates":[105.58969999999999,31.63765],"type":"Point"}
}