{
  "type": "Feature",
  "properties": {
    "gn:admin1_code":"29",
    "gn:asciiname":"Xiaobanqiao",
    "gn:country_code":"CN",
    "gn:dem":1901,
    "gn:feature_class":"P",
    "gn:feature_code":"PPLA4",
    "gn:name":"Xiaobanqiao",
    "gn:population":0,
    "gn:timezone":"Asia/Shanghai",
    "iso:country":"CN",
    "name:und_x_variant":[
        "Xiaobanqiao Zhen",
        "\u5c0f\u677f\u6865\u9547",
        "Xiaobanqiao"
    ],
    "name:zho_x_preferred":[
        "\u5c0f\u677f\u6865"
    ],
    "wof:name":"Xiaobanqiao",
    "wof:placetype":"locality"
},
  "geometry": {"coordinates":[102.77379999999999,24.97944],"type":"Point"}
}