{
  "type": "Feature",
  "properties": {
    "gn:admin1_code":"15.0",
    "gn:asciiname":"Yitiaoshan",
    "gn:country_code":"CN",
    "gn:dem":1616,
    "gn:feature_class":"P",
    "gn:feature_code":"PPLA3",
    "gn:name":"Yitiaoshan",
    "gn:population":0,
    "gn:timezone":"Asia/Shanghai",
    "iso:country":"CN",
    "name:und_x_variant":[
        "Hung-shui",
        "Tsintay",
        "Khunshuy",
        "Lu-yang",
        "Ching-t\u2019ai",
        "Ta-lu-t\u2019ang",
        "Ityaoshan\u2019",
        "I-t\u2019iao-shan",
        "Jingtai",
        "Yitiaoshan",
        "Jingtai Xian"
    ],
    "name:zho_x_preferred":[
        "\u4e00\u6761\u5c71"
    ],
    "name:zho_x_variant":[
        "\u666f\u6cf0\u53bf"
    ],
    "wof:name":"Yitiaoshan",
    "wof:placetype":"locality"
},
  "geometry": {"coordinates":[104.062,37.1533],"type":"Point"}
}