{
  "type": "Feature",
  "properties": {
    "gn:admin1_code":"30.0",
    "gn:asciiname":"Shijiucun",
    "gn:country_code":"CN",
    "gn:dem":31,
    "gn:feature_class":"P",
    "gn:feature_code":"PPL",
    "gn:name":"Shijiucun",
    "gn:population":0,
    "gn:timezone":"Asia/Shanghai",
    "iso:country":"CN",
    "name:zho_x_preferred":[
        "\u77f3\u4e5d\u6751"
    ],
    "wof:name":"Shijiucun",
    "wof:placetype":"locality"
},
  "geometry": {"coordinates":[116.49659,24.00561],"type":"Point"}
}