{
  "type": "Feature",
  "properties": {
    "gn:admin1_code":"9.0",
    "gn:asciiname":"Chedaogoukou",
    "gn:country_code":"CN",
    "gn:dem":670,
    "gn:feature_class":"P",
    "gn:feature_code":"PPL",
    "gn:name":"Chedaogoukou",
    "gn:population":0,
    "gn:timezone":"Asia/Shanghai",
    "iso:country":"CN",
    "name:zho_x_preferred":[
        "\u8f66\u9053\u6c9f\u53e3"
    ],
    "wof:name":"Chedaogoukou",
    "wof:placetype":"locality"
},
  "geometry": {"coordinates":[111.22703,34.09820999999999],"type":"Point"}
}