{
  "type": "Feature",
  "properties": {
    "gn:admin1_code":"9.0",
    "gn:asciiname":"Hemiao",
    "gn:country_code":"CN",
    "gn:dem":120,
    "gn:feature_class":"P",
    "gn:feature_code":"PPL",
    "gn:name":"Hemiao",
    "gn:population":0,
    "gn:timezone":"Asia/Shanghai",
    "iso:country":"CN",
    "name:und_x_variant":[
        "\u4f55\u5e99",
        "Hemiao"
    ],
    "wof:name":"Hemiao",
    "wof:placetype":"locality"
},
  "geometry": {"coordinates":[112.90467,33.00035],"type":"Point"}
}