{
  "type": "Feature",
  "properties": {
    "gn:admin1_code":"15.0",
    "gn:asciiname":"Sanqingmiao",
    "gn:country_code":"CN",
    "gn:dem":2122,
    "gn:feature_class":"P",
    "gn:feature_code":"PPL",
    "gn:name":"Sanqingmiao",
    "gn:population":0,
    "gn:timezone":"Asia/Shanghai",
    "iso:country":"CN",
    "name:zho_x_preferred":[
        "\u4e09\u6e05\u5e99"
    ],
    "wof:name":"Sanqingmiao",
    "wof:placetype":"locality"
},
  "geometry": {"coordinates":[101.14700000000001,38.5471],"type":"Point"}
}