{
  "type": "Feature",
  "properties": {
    "gn:admin1_code":"26.0",
    "gn:asciiname":"Mingshuihucun",
    "gn:country_code":"CN",
    "gn:dem":1332,
    "gn:feature_class":"P",
    "gn:feature_code":"PPL",
    "gn:name":"Mingshuihucun",
    "gn:population":0,
    "gn:timezone":"Asia/Shanghai",
    "iso:country":"CN",
    "name:zho_x_preferred":[
        "\u660e\u6c34\u6e56\u6751"
    ],
    "wof:name":"Mingshuihucun",
    "wof:placetype":"locality"
},
  "geometry": {"coordinates":[107.81959999999999,37.79512],"type":"Point"}
}