{
  "type": "Feature",
  "properties": {
    "gn:admin1_code":"20.0",
    "gn:asciiname":"Qijianfang",
    "gn:country_code":"CN",
    "gn:dem":290,
    "gn:feature_class":"P",
    "gn:feature_code":"PPL",
    "gn:name":"Qijianfang",
    "gn:population":0,
    "gn:timezone":"Asia/Shanghai",
    "iso:country":"CN",
    "name:zho_x_preferred":[
        "\u4e03\u95f4\u623f"
    ],
    "wof:name":"Qijianfang",
    "wof:placetype":"locality"
},
  "geometry": {"coordinates":[124.34043,48.76534],"type":"Point"}
}