{
  "type": "Feature",
  "properties": {
    "gn:admin1_code":"18.0",
    "gn:asciiname":"Zhanbi",
    "gn:country_code":"CN",
    "gn:dem":897,
    "gn:feature_class":"P",
    "gn:feature_code":"PPL",
    "gn:name":"Zhanbi",
    "gn:population":0,
    "gn:timezone":"Asia/Shanghai",
    "iso:country":"CN",
    "name:zho_x_preferred":[
        "\u5c55\u58c1"
    ],
    "wof:name":"Zhanbi",
    "wof:placetype":"locality"
},
  "geometry": {"coordinates":[108.313,26.7822],"type":"Point"}
}