{
  "type": "Feature",
  "properties": {
    "gn:admin1_code":"9.0",
    "gn:asciiname":"Chahuamiao",
    "gn:country_code":"CN",
    "gn:dem":43,
    "gn:feature_class":"P",
    "gn:feature_code":"PPL",
    "gn:name":"Chahuamiao",
    "gn:population":0,
    "gn:timezone":"Asia/Shanghai",
    "iso:country":"CN",
    "name:zho_x_preferred":[
        "\u63d2\u82b1\u5e99"
    ],
    "wof:name":"Chahuamiao",
    "wof:placetype":"locality"
},
  "geometry": {"coordinates":[115.06938999999998,32.81495],"type":"Point"}
}