{
  "type": "Feature",
  "properties": {
    "gn:admin1_code":"5.0",
    "gn:asciiname":"Huapicun",
    "gn:country_code":"CN",
    "gn:dem":423,
    "gn:feature_class":"P",
    "gn:feature_code":"PPL",
    "gn:name":"Huapicun",
    "gn:population":0,
    "gn:timezone":"Asia/Shanghai",
    "iso:country":"CN",
    "name:zho_x_preferred":[
        "\u6866\u76ae\u6751"
    ],
    "wof:name":"Huapicun",
    "wof:placetype":"locality"
},
  "geometry": {"coordinates":[125.54686,42.12185],"type":"Point"}
}