{
  "type": "Feature",
  "properties": {
    "gn:admin1_code":"18.0",
    "gn:asciiname":"Hongmenxi",
    "gn:country_code":"CN",
    "gn:dem":384,
    "gn:feature_class":"P",
    "gn:feature_code":"PPL",
    "gn:name":"Hongmenxi",
    "gn:population":0,
    "gn:timezone":"Asia/Shanghai",
    "iso:country":"CN",
    "name:zho_x_preferred":[
        "\u7ea2\u95e8\u6eaa"
    ],
    "wof:name":"Hongmenxi",
    "wof:placetype":"locality"
},
  "geometry": {"coordinates":[108.919,27.2605],"type":"Point"}
}