{
  "type": "Feature",
  "properties": {
    "gn:admin1_code":"3",
    "gn:asciiname":"Reshuizhou",
    "gn:country_code":"CN",
    "gn:dem":471,
    "gn:feature_class":"P",
    "gn:feature_code":"PPL",
    "gn:name":"Reshuizhou",
    "gn:population":0,
    "gn:timezone":"Asia/Shanghai",
    "iso:country":"CN",
    "name:zho_x_preferred":[
        "\u70ed\u6c34\u6d32"
    ],
    "wof:name":"Reshuizhou",
    "wof:placetype":"locality"
},
  "geometry": {"coordinates":[114.152,26.3888],"type":"Point"}
}