{
  "type": "Feature",
  "properties": {
    "gn:admin1_code":"3.0",
    "gn:asciiname":"Shixiali",
    "gn:country_code":"CN",
    "gn:dem":109,
    "gn:feature_class":"P",
    "gn:feature_code":"PPL",
    "gn:name":"Shixiali",
    "gn:population":0,
    "gn:timezone":"Asia/Shanghai",
    "iso:country":"CN",
    "name:und_x_variant":[
        "\u77f3\u4e0b\u91cc"
    ],
    "wof:name":"Shixiali",
    "wof:placetype":"locality"
},
  "geometry": {"coordinates":[114.47286,27.77358],"type":"Point"}
}