{
  "type": "Feature",
  "properties": {
    "gn:admin1_code":"02",
    "gn:asciiname":"Shangzhoucun",
    "gn:country_code":"CN",
    "gn:dem":416,
    "gn:feature_class":"P",
    "gn:feature_code":"PPL",
    "gn:name":"Shangzhoucun",
    "gn:population":0,
    "gn:timezone":"Asia/Shanghai",
    "iso:country":"CN",
    "name:und_x_variant":[
        "Shang-chou",
        "Shangzhou",
        "Shangzhoucun"
    ],
    "name:zho_x_preferred":[
        "\u4e0a\u5468"
    ],
    "name:zho_x_variant":[
        "\u4e0a\u5468\u6751"
    ],
    "wof:name":"Shangzhoucun",
    "wof:placetype":"locality"
},
  "geometry": {"coordinates":[120.27502,28.65615],"type":"Point"}
}