{
  "type": "Feature",
  "properties": {
    "gn:admin1_code":"19.0",
    "gn:asciiname":"Dafangzicun",
    "gn:country_code":"CN",
    "gn:dem":395,
    "gn:feature_class":"P",
    "gn:feature_code":"PPL",
    "gn:name":"Dafangzicun",
    "gn:population":0,
    "gn:timezone":"Asia/Shanghai",
    "iso:country":"CN",
    "name:zho_x_preferred":[
        "\u5927\u623f\u5b50\u6751"
    ],
    "wof:name":"Dafangzicun",
    "wof:placetype":"locality"
},
  "geometry": {"coordinates":[124.511,41.6818],"type":"Point"}
}