{
  "type": "Feature",
  "properties": {
    "gn:admin1_code":"4.0",
    "gn:asciiname":"Hetao",
    "gn:country_code":"CN",
    "gn:dem":33,
    "gn:feature_class":"P",
    "gn:feature_code":"PPL",
    "gn:name":"Hetao",
    "gn:population":0,
    "gn:timezone":"Asia/Shanghai",
    "iso:country":"CN",
    "name:deu_x_preferred":[
        "Hetao-Ebene"
    ],
    "name:fra_x_preferred":[
        "Hetao"
    ],
    "name:kor_x_preferred":[
        "\ud5c8\ud0c0\uc624"
    ],
    "name:pol_x_preferred":[
        "Hetao"
    ],
    "name:rus_x_preferred":[
        "\u0425\u044d\u0442\u0430\u043e"
    ],
    "name:zho_x_preferred":[
        "\u6cb3\u5957"
    ],
    "wof:name":"Hetao",
    "wof:placetype":"locality"
},
  "geometry": {"coordinates":[117.375,34.256],"type":"Point"}
}