{
  "type": "Feature",
  "properties": {
    "gn:admin1_code":"29.0",
    "gn:asciiname":"Shenkeding",
    "gn:country_code":"CN",
    "gn:dem":3197,
    "gn:feature_class":"P",
    "gn:feature_code":"PPL",
    "gn:name":"Shenkeding",
    "gn:population":0,
    "gn:timezone":"Asia/Shanghai",
    "iso:country":"CN",
    "name:zho_x_preferred":[
        "\u7533\u79d1\u4e01"
    ],
    "wof:name":"Shenkeding",
    "wof:placetype":"locality"
},
  "geometry": {"coordinates":[99.79519999999999,27.5325],"type":"Point"}
}