{
  "type": "Feature",
  "properties": {
    "gn:admin1_code":"18.0",
    "gn:asciiname":"Yan'ao",
    "gn:country_code":"CN",
    "gn:dem":342,
    "gn:feature_class":"P",
    "gn:feature_code":"PPL",
    "gn:name":"Yan\u2019ao",
    "gn:population":0,
    "gn:timezone":"Asia/Shanghai",
    "iso:country":"CN",
    "name:und_x_variant":[
        "Yan\u2019ao"
    ],
    "name:zho_x_preferred":[
        "\u5ca9\u5773"
    ],
    "wof:name":"Yan'ao",
    "wof:placetype":"locality"
},
  "geometry": {"coordinates":[109.476,26.9222],"type":"Point"}
}