{
  "type": "Feature",
  "properties": {
    "gn:admin1_code":"1.0",
    "gn:asciiname":"Hankou",
    "gn:country_code":"CN",
    "gn:dem":9,
    "gn:feature_class":"P",
    "gn:feature_code":"PPL",
    "gn:name":"Hankou",
    "gn:population":0,
    "gn:timezone":"Asia/Shanghai",
    "iso:country":"CN",
    "name:ell_x_preferred":[
        "\u03a7\u03b1\u03bd\u03ba\u03cc\u03bf\u03c5"
    ],
    "name:fas_x_preferred":[
        "\u0647\u0627\u0646\u06a9\u0648"
    ],
    "name:fin_x_preferred":[
        "Hankou"
    ],
    "name:fra_x_preferred":[
        "Hankou"
    ],
    "name:ind_x_preferred":[
        "Hankou"
    ],
    "name:ita_x_preferred":[
        "Hankou"
    ],
    "name:kor_x_preferred":[
        "\ud55c\ucee4\uc6b0"
    ],
    "name:mlg_x_preferred":[
        "Hankou"
    ],
    "name:nor_x_preferred":[
        "Hankou"
    ],
    "name:pol_x_preferred":[
        "Hankou"
    ],
    "name:spa_x_preferred":[
        "Hankou"
    ],
    "name:swe_x_preferred":[
        "Hankou"
    ],
    "name:ukr_x_preferred":[
        "\u0425\u0430\u043d\u044c\u043a\u043e\u0443"
    ],
    "name:vie_x_preferred":[
        "H\u00e1n Kh\u1ea9u"
    ],
    "name:zho_x_preferred":[
        "\u6db5\u53e3"
    ],
    "wof:name":"Hankou",
    "wof:placetype":"locality"
},
  "geometry": {"coordinates":[118.67048,31.31554],"type":"Point"}
}