{
  "type": "Feature",
  "properties": {
    "gn:admin1_code":"24.0",
    "gn:asciiname":"Hucuncun",
    "gn:country_code":"CN",
    "gn:dem":1116,
    "gn:feature_class":"P",
    "gn:feature_code":"PPL",
    "gn:name":"Hucuncun",
    "gn:population":0,
    "gn:timezone":"Asia/Shanghai",
    "iso:country":"CN",
    "name:zho_x_preferred":[
        "\u80e1\u6751\u6751"
    ],
    "wof:name":"Hucuncun",
    "wof:placetype":"locality"
},
  "geometry": {"coordinates":[110.91750999999999,36.02397],"type":"Point"}
}