{
  "type": "Feature",
  "properties": {
    "gn:admin1_code":"16.0",
    "gn:asciiname":"Liugu",
    "gn:country_code":"CN",
    "gn:dem":280,
    "gn:feature_class":"P",
    "gn:feature_code":"PPL",
    "gn:name":"Liugu",
    "gn:population":0,
    "gn:timezone":"Asia/Shanghai",
    "iso:country":"CN",
    "name:zho_x_preferred":[
        "\u516d\u8c37"
    ],
    "wof:name":"Liugu",
    "wof:placetype":"locality"
},
  "geometry": {"coordinates":[107.867,24.4197],"type":"Point"}
}