{
  "type": "Feature",
  "properties": {
    "gn:admin1_code":"11.0",
    "gn:asciiname":"Tongxinggong",
    "gn:country_code":"CN",
    "gn:dem":25,
    "gn:feature_class":"P",
    "gn:feature_code":"PPL",
    "gn:name":"Tongxinggong",
    "gn:population":0,
    "gn:timezone":"Asia/Shanghai",
    "iso:country":"CN",
    "name:und_x_variant":[
        "Tongxing"
    ],
    "name:zho_x_preferred":[
        "\u540c\u5174\u516c"
    ],
    "wof:name":"Tongxinggong",
    "wof:placetype":"locality"
},
  "geometry": {"coordinates":[113.49406999999999,29.77761],"type":"Point"}
}