{
  "type": "Feature",
  "properties": {
    "gn:admin1_code":"3.0",
    "gn:asciiname":"Pingdishan",
    "gn:country_code":"CN",
    "gn:dem":264,
    "gn:feature_class":"P",
    "gn:feature_code":"PPL",
    "gn:name":"Pingdishan",
    "gn:population":0,
    "gn:timezone":"Asia/Shanghai",
    "iso:country":"CN",
    "name:und_x_variant":[
        "\u576a\u5730\u5c71"
    ],
    "wof:name":"Pingdishan",
    "wof:placetype":"locality"
},
  "geometry": {"coordinates":[115.25696000000001,25.32801],"type":"Point"}
}