{
  "type": "Feature",
  "properties": {
    "gn:admin1_code":"29.0",
    "gn:asciiname":"Akumi",
    "gn:country_code":"CN",
    "gn:dem":2355,
    "gn:feature_class":"P",
    "gn:feature_code":"PPL",
    "gn:name":"Akumi",
    "gn:population":0,
    "gn:timezone":"Asia/Shanghai",
    "iso:country":"CN",
    "name:zho_x_preferred":[
        "\u963f\u5e93\u7c73"
    ],
    "wof:name":"Akumi",
    "wof:placetype":"locality"
},
  "geometry": {"coordinates":[99.011,27.5579],"type":"Point"}
}