{
  "type": "Feature",
  "properties": {
    "gn:admin1_code":"18",
    "gn:asciiname":"Ciga",
    "gn:country_code":"CN",
    "gn:dem":1679,
    "gn:feature_class":"P",
    "gn:feature_code":"PPL",
    "gn:name":"Ciga",
    "gn:population":0,
    "gn:timezone":"Asia/Shanghai",
    "iso:country":"CN",
    "name:zho_x_preferred":[
        "\u8328\u560e"
    ],
    "wof:name":"Ciga",
    "wof:placetype":"locality"
},
  "geometry": {"coordinates":[104.74299999999999,25.9791],"type":"Point"}
}