{
  "type": "Feature",
  "properties": {
    "gn:admin1_code":"4.0",
    "gn:asciiname":"Lidazhuang",
    "gn:country_code":"CN",
    "gn:dem":36,
    "gn:feature_class":"P",
    "gn:feature_code":"PPL",
    "gn:name":"Lidazhuang",
    "gn:population":0,
    "gn:timezone":"Asia/Shanghai",
    "iso:country":"CN",
    "name:zho_x_preferred":[
        "\u674e\u5927\u5e84"
    ],
    "wof:name":"Lidazhuang",
    "wof:placetype":"locality"
},
  "geometry": {"coordinates":[116.93000000000001,34.7987],"type":"Point"}
}