{
  "type": "Feature",
  "properties": {
    "gn:admin1_code":"5.0",
    "gn:asciiname":"Quanbaocun",
    "gn:country_code":"CN",
    "gn:dem":149,
    "gn:feature_class":"P",
    "gn:feature_code":"PPL",
    "gn:name":"Quanbaocun",
    "gn:population":0,
    "gn:timezone":"Asia/Shanghai",
    "iso:country":"CN",
    "name:zho_x_preferred":[
        "\u5168\u4fdd\u6751"
    ],
    "wof:name":"Quanbaocun",
    "wof:placetype":"locality"
},
  "geometry": {"coordinates":[122.76638,45.40903],"type":"Point"}
}