{
  "type": "Feature",
  "properties": {
    "gn:admin1_code":"10",
    "gn:asciiname":"Duanjialing",
    "gn:cc2":"CN",
    "gn:country_code":"CN",
    "gn:dem":30,
    "gn:feature_class":"P",
    "gn:feature_code":"PPL",
    "gn:name":"Duanjialing",
    "gn:population":0,
    "gn:timezone":"Asia/Shanghai",
    "iso:country":"CN",
    "name:und_x_variant":[
        "Tuan-chia-ling",
        "Duanjialing"
    ],
    "wof:name":"Duanjialing",
    "wof:placetype":"locality"
},
  "geometry": {"coordinates":[117.16249999999999,39.99444],"type":"Point"}
}