{
  "type": "Feature",
  "properties": {
    "gn:admin1_code":"19.0",
    "gn:asciiname":"Dahuigou",
    "gn:country_code":"CN",
    "gn:dem":189,
    "gn:feature_class":"P",
    "gn:feature_code":"PPL",
    "gn:name":"Dahuigou",
    "gn:population":0,
    "gn:timezone":"Asia/Shanghai",
    "iso:country":"CN",
    "name:zho_x_preferred":[
        "\u5927\u7070\u6c9f"
    ],
    "wof:name":"Dahuigou",
    "wof:placetype":"locality"
},
  "geometry": {"coordinates":[124.164,42.3468],"type":"Point"}
}