{
  "type": "Feature",
  "properties": {
    "gn:admin1_code":"16.0",
    "gn:asciiname":"Xiajiudong",
    "gn:country_code":"CN",
    "gn:dem":874,
    "gn:feature_class":"P",
    "gn:feature_code":"PPL",
    "gn:name":"Xiajiudong",
    "gn:population":0,
    "gn:timezone":"Asia/Shanghai",
    "iso:country":"CN",
    "name:zho_x_preferred":[
        "\u4e0b\u4e5d\u6d1e"
    ],
    "wof:name":"Xiajiudong",
    "wof:placetype":"locality"
},
  "geometry": {"coordinates":[105.223,24.8299],"type":"Point"}
}