{
  "type": "Feature",
  "properties": {
    "gn:admin1_code":"11.0",
    "gn:asciiname":"Beifeng'ao",
    "gn:country_code":"CN",
    "gn:dem":108,
    "gn:feature_class":"P",
    "gn:feature_code":"PPL",
    "gn:name":"Beifeng\u2019ao",
    "gn:population":0,
    "gn:timezone":"Asia/Shanghai",
    "iso:country":"CN",
    "name:und_x_variant":[
        "Beifeng\u2019ao"
    ],
    "name:zho_x_preferred":[
        "\u5317\u98ce\u5773"
    ],
    "wof:name":"Beifeng'ao",
    "wof:placetype":"locality"
},
  "geometry": {"coordinates":[112.76518,27.73924],"type":"Point"}
}