{
  "type": "Feature",
  "properties": {
    "gn:admin1_code":"26.0",
    "gn:asciiname":"Shiguanya",
    "gn:country_code":"CN",
    "gn:dem":1180,
    "gn:feature_class":"P",
    "gn:feature_code":"PPL",
    "gn:name":"Shiguanya",
    "gn:population":0,
    "gn:timezone":"Asia/Shanghai",
    "iso:country":"CN",
    "name:und_x_variant":[
        "\u77f3\u5173\u57ad"
    ],
    "wof:name":"Shiguanya",
    "wof:placetype":"locality"
},
  "geometry": {"coordinates":[107.30231999999999,33.45397],"type":"Point"}
}