{
  "type": "Feature",
  "properties": {
    "gn:admin1_code":"4.0",
    "gn:asciiname":"Xinyixu",
    "gn:country_code":"CN",
    "gn:dem":6,
    "gn:feature_class":"P",
    "gn:feature_code":"PPLF",
    "gn:name":"Xinyixu",
    "gn:population":0,
    "gn:timezone":"Asia/Shanghai",
    "iso:country":"CN",
    "name:zho_x_preferred":[
        "\u65b0\u4e00\u5729"
    ],
    "wof:name":"Xinyixu",
    "wof:placetype":"locality"
},
  "geometry": {"coordinates":[120.13852,32.00482],"type":"Point"}
}