{
  "type": "Feature",
  "properties": {
    "gn:admin1_code":"8.0",
    "gn:asciiname":"Qinnongcun",
    "gn:country_code":"CN",
    "gn:dem":98,
    "gn:feature_class":"P",
    "gn:feature_code":"PPL",
    "gn:name":"Qinnongcun",
    "gn:population":0,
    "gn:timezone":"Asia/Shanghai",
    "iso:country":"CN",
    "name:zho_x_preferred":[
        "\u52e4\u519c\u6751"
    ],
    "wof:name":"Qinnongcun",
    "wof:placetype":"locality"
},
  "geometry": {"coordinates":[132.18466999999998,45.39798],"type":"Point"}
}