{
  "type": "Feature",
  "properties": {
    "gn:admin1_code":"29.0",
    "gn:asciiname":"Xiaodianwei",
    "gn:country_code":"CN",
    "gn:dem":1814,
    "gn:feature_class":"P",
    "gn:feature_code":"PPL",
    "gn:name":"Xiaodianwei",
    "gn:population":0,
    "gn:timezone":"Asia/Shanghai",
    "iso:country":"CN",
    "name:zho_x_preferred":[
        "\u5c0f\u7538\u5c3e"
    ],
    "wof:name":"Xiaodianwei",
    "wof:placetype":"locality"
},
  "geometry": {"coordinates":[101.73099999999999,25.1938],"type":"Point"}
}