{
  "type": "Feature",
  "properties": {
    "gn:admin1_code":"29.0",
    "gn:asciiname":"Madishan",
    "gn:country_code":"CN",
    "gn:dem":2398,
    "gn:feature_class":"P",
    "gn:feature_code":"PPL",
    "gn:name":"Madishan",
    "gn:population":0,
    "gn:timezone":"Asia/Shanghai",
    "iso:country":"CN",
    "name:zho_x_preferred":[
        "\u9ebb\u5730\u5c71"
    ],
    "wof:name":"Madishan",
    "wof:placetype":"locality"
},
  "geometry": {"coordinates":[100.946,24.7456],"type":"Point"}
}