{
  "type": "Feature",
  "properties": {
    "gn:admin1_code":"1.0",
    "gn:asciiname":"Dawangcun",
    "gn:country_code":"CN",
    "gn:dem":13,
    "gn:feature_class":"P",
    "gn:feature_code":"PPL",
    "gn:name":"Dawangcun",
    "gn:population":0,
    "gn:timezone":"Asia/Shanghai",
    "iso:country":"CN",
    "name:zho_x_preferred":[
        "\u5927\u6c6a\u6751"
    ],
    "wof:name":"Dawangcun",
    "wof:placetype":"locality"
},
  "geometry": {"coordinates":[117.82214999999999,31.24431],"type":"Point"}
}