{
  "type": "Feature",
  "properties": {
    "gn:admin1_code":"12.0",
    "gn:asciiname":"Zhafangping",
    "gn:country_code":"CN",
    "gn:dem":1461,
    "gn:feature_class":"P",
    "gn:feature_code":"PPL",
    "gn:name":"Zhafangping",
    "gn:population":0,
    "gn:timezone":"Asia/Shanghai",
    "iso:country":"CN",
    "name:zho_x_preferred":[
        "Zhafangping"
    ],
    "name:zho_x_variant":[
        "\u69a8\u65b9\u576a"
    ],
    "wof:name":"Zhafangping",
    "wof:placetype":"locality"
},
  "geometry": {"coordinates":[110.23653,29.99828],"type":"Point"}
}