{
  "type": "Feature",
  "properties": {
    "gn:admin1_code":"22.0",
    "gn:asciiname":"Dongwuya",
    "gn:country_code":"CN",
    "gn:dem":41,
    "gn:feature_class":"P",
    "gn:feature_code":"PPL",
    "gn:name":"Dongwuya",
    "gn:population":0,
    "gn:timezone":"Asia/Shanghai",
    "iso:country":"CN",
    "name:zho_x_preferred":[
        "\u4e1c\u4e4c\u9e26"
    ],
    "wof:name":"Dongwuya",
    "wof:placetype":"locality"
},
  "geometry": {"coordinates":[116.72978999999999,40.2242],"type":"Point"}
}