{
  "type": "Feature",
  "properties": {
    "gn:admin1_code":"29.0",
    "gn:asciiname":"Nayutang",
    "gn:country_code":"CN",
    "gn:dem":2137,
    "gn:feature_class":"P",
    "gn:feature_code":"PPL",
    "gn:name":"Nayutang",
    "gn:population":0,
    "gn:timezone":"Asia/Shanghai",
    "iso:country":"CN",
    "name:zho_x_preferred":[
        "\u62ff\u9c7c\u5858"
    ],
    "wof:name":"Nayutang",
    "wof:placetype":"locality"
},
  "geometry": {"coordinates":[102.63800000000001,25.2873],"type":"Point"}
}