{
  "type": "Feature",
  "properties": {
    "gn:admin1_code":"15.0",
    "gn:asciiname":"Wafangchuan",
    "gn:country_code":"CN",
    "gn:dem":2195,
    "gn:feature_class":"P",
    "gn:feature_code":"PPL",
    "gn:name":"Wafangchuan",
    "gn:population":0,
    "gn:timezone":"Asia/Shanghai",
    "iso:country":"CN",
    "name:zho_x_preferred":[
        "\u74e6\u623f\u5ddd"
    ],
    "wof:name":"Wafangchuan",
    "wof:placetype":"locality"
},
  "geometry": {"coordinates":[103.371,35.585],"type":"Point"}
}