{
  "type": "Feature",
  "properties": {
    "gn:admin1_code":"4.0",
    "gn:asciiname":"Luantancun",
    "gn:country_code":"CN",
    "gn:dem":2,
    "gn:feature_class":"P",
    "gn:feature_code":"PPL",
    "gn:name":"Luantancun",
    "gn:population":0,
    "gn:timezone":"Asia/Shanghai",
    "iso:country":"CN",
    "name:zho_x_preferred":[
        "\u683e\u6ee9\u6751"
    ],
    "wof:name":"Luantancun",
    "wof:placetype":"locality"
},
  "geometry": {"coordinates":[119.90949000000001,33.87408],"type":"Point"}
}