{
  "type": "Feature",
  "properties": {
    "gn:admin1_code":"3.0",
    "gn:asciiname":"Longxiawan",
    "gn:country_code":"CN",
    "gn:dem":231,
    "gn:feature_class":"P",
    "gn:feature_code":"PPL",
    "gn:name":"Longxiawan",
    "gn:population":0,
    "gn:timezone":"Asia/Shanghai",
    "iso:country":"CN",
    "name:und_x_variant":[
        "\u9f99\u4e0b\u6e7e"
    ],
    "wof:name":"Longxiawan",
    "wof:placetype":"locality"
},
  "geometry": {"coordinates":[115.58503,25.76292],"type":"Point"}
}