{
  "type": "Feature",
  "properties": {
    "gn:admin1_code":"16.0",
    "gn:asciiname":"Pengkuishan",
    "gn:country_code":"CN",
    "gn:dem":342,
    "gn:feature_class":"P",
    "gn:feature_code":"PPL",
    "gn:name":"Pengkuishan",
    "gn:population":0,
    "gn:timezone":"Asia/Shanghai",
    "iso:country":"CN",
    "name:zho_x_preferred":[
        "\u84ec\u594e\u5c71"
    ],
    "wof:name":"Pengkuishan",
    "wof:placetype":"locality"
},
  "geometry": {"coordinates":[109.483,22.5073],"type":"Point"}
}