{
  "type": "Feature",
  "properties": {
    "gn:admin1_code":"29",
    "gn:asciiname":"Podai",
    "gn:country_code":"CN",
    "gn:dem":1324,
    "gn:feature_class":"P",
    "gn:feature_code":"PPL",
    "gn:name":"Podai",
    "gn:population":0,
    "gn:timezone":"Asia/Shanghai",
    "iso:country":"CN",
    "name:zho_x_preferred":[
        "\u5761\u4ee3"
    ],
    "wof:name":"Podai",
    "wof:placetype":"locality"
},
  "geometry": {"coordinates":[101.982,24.3048],"type":"Point"}
}