{
  "type": "Feature",
  "properties": {
    "gn:admin1_code":"11.0",
    "gn:asciiname":"Guanghutang",
    "gn:country_code":"CN",
    "gn:dem":55,
    "gn:feature_class":"P",
    "gn:feature_code":"PPL",
    "gn:name":"Guanghutang",
    "gn:population":0,
    "gn:timezone":"Asia/Shanghai",
    "iso:country":"CN",
    "name:zho_x_preferred":[
        "\u5149\u6e56\u5858"
    ],
    "wof:name":"Guanghutang",
    "wof:placetype":"locality"
},
  "geometry": {"coordinates":[112.64655999999999,27.99704],"type":"Point"}
}