{
  "type": "Feature",
  "properties": {
    "gn:admin1_code":"30.0",
    "gn:asciiname":"Yaliaodong",
    "gn:country_code":"CN",
    "gn:dem":45,
    "gn:feature_class":"P",
    "gn:feature_code":"PPL",
    "gn:name":"Yaliaodong",
    "gn:population":0,
    "gn:timezone":"Asia/Shanghai",
    "iso:country":"CN",
    "name:zho_x_preferred":[
        "\u9e26\u9e69\u6d1e"
    ],
    "wof:name":"Yaliaodong",
    "wof:placetype":"locality"
},
  "geometry": {"coordinates":[112.56228,23.40087],"type":"Point"}
}