{
  "type": "Feature",
  "properties": {
    "gn:admin1_code":"1.0",
    "gn:asciiname":"Fandatangcun",
    "gn:country_code":"CN",
    "gn:dem":48,
    "gn:feature_class":"P",
    "gn:feature_code":"PPL",
    "gn:name":"Fandatangcun",
    "gn:population":0,
    "gn:timezone":"Asia/Shanghai",
    "iso:country":"CN",
    "name:zho_x_preferred":[
        "\u8303\u5927\u5858\u6751"
    ],
    "wof:name":"Fandatangcun",
    "wof:placetype":"locality"
},
  "geometry": {"coordinates":[116.41467,31.6463],"type":"Point"}
}