{
  "type": "Feature",
  "properties": {
    "gn:admin1_code":"26.0",
    "gn:asciiname":"Zhuanyaogou",
    "gn:country_code":"CN",
    "gn:dem":1237,
    "gn:feature_class":"P",
    "gn:feature_code":"PPL",
    "gn:name":"Zhuanyaogou",
    "gn:population":0,
    "gn:timezone":"Asia/Shanghai",
    "iso:country":"CN",
    "name:zho_x_preferred":[
        "\u7816\u7a91\u6c9f"
    ],
    "wof:name":"Zhuanyaogou",
    "wof:placetype":"locality"
},
  "geometry": {"coordinates":[109.66482000000001,35.86445],"type":"Point"}
}