{
  "type": "Feature",
  "properties": {
    "gn:admin1_code":"19.0",
    "gn:asciiname":"Bei'ertaizi",
    "gn:country_code":"CN",
    "gn:dem":82,
    "gn:feature_class":"P",
    "gn:feature_code":"PPL",
    "gn:name":"Bei\u2019ertaizi",
    "gn:population":0,
    "gn:timezone":"Asia/Shanghai",
    "iso:country":"CN",
    "name:zho_x_preferred":[
        "Bei\u2019ertaizi"
    ],
    "name:zho_x_variant":[
        "\u5317\u4e8c\u53f0\u5b50"
    ],
    "wof:name":"Bei'ertaizi",
    "wof:placetype":"locality"
},
  "geometry": {"coordinates":[121.35374,41.4469],"type":"Point"}
}