{
  "type": "Feature",
  "properties": {
    "gn:admin1_code":"11.0",
    "gn:asciiname":"Huaxiangping",
    "gn:country_code":"CN",
    "gn:dem":132,
    "gn:feature_class":"P",
    "gn:feature_code":"PPL",
    "gn:name":"Huaxiangping",
    "gn:population":0,
    "gn:timezone":"Asia/Shanghai",
    "iso:country":"CN",
    "name:zho_x_preferred":[
        "Huaxiangping"
    ],
    "name:zho_x_variant":[
        "\u82b1\u9999\u576a"
    ],
    "wof:name":"Huaxiangping",
    "wof:placetype":"locality"
},
  "geometry": {"coordinates":[111.13308000000001,28.99082000000001],"type":"Point"}
}