{
  "type": "Feature",
  "properties": {
    "gn:admin1_code":"7",
    "gn:asciiname":"Shanling",
    "gn:country_code":"CN",
    "gn:dem":556,
    "gn:feature_class":"P",
    "gn:feature_code":"PPL",
    "gn:name":"Shanling",
    "gn:population":0,
    "gn:timezone":"Asia/Shanghai",
    "iso:country":"CN",
    "name:und_x_variant":[
        "\u5c71\u5cad",
        "Shanling"
    ],
    "wof:name":"Shanling",
    "wof:placetype":"locality"
},
  "geometry": {"coordinates":[119.42749999999999,27.34438],"type":"Point"}
}