{
  "type": "Feature",
  "properties": {
    "gn:admin1_code":"29.0",
    "gn:asciiname":"Xiadabi",
    "gn:country_code":"CN",
    "gn:dem":1694,
    "gn:feature_class":"P",
    "gn:feature_code":"PPL",
    "gn:name":"Xiadabi",
    "gn:population":0,
    "gn:timezone":"Asia/Shanghai",
    "iso:country":"CN",
    "name:zho_x_preferred":[
        "\u4e0b\u6253\u6bd4"
    ],
    "wof:name":"Xiadabi",
    "wof:placetype":"locality"
},
  "geometry": {"coordinates":[100.018,25.0788],"type":"Point"}
}