{
  "type": "Feature",
  "properties": {
    "gn:admin1_code":"26.0",
    "gn:asciiname":"Ximengcun",
    "gn:country_code":"CN",
    "gn:dem":619,
    "gn:feature_class":"P",
    "gn:feature_code":"PPL",
    "gn:name":"Ximengcun",
    "gn:population":0,
    "gn:timezone":"Asia/Shanghai",
    "iso:country":"CN",
    "name:zho_x_preferred":[
        "\u897f\u8499\u6751"
    ],
    "wof:name":"Ximengcun",
    "wof:placetype":"locality"
},
  "geometry": {"coordinates":[110.27779,35.23727],"type":"Point"}
}