{
  "type": "Feature",
  "properties": {
    "gn:admin1_code":"12.0",
    "gn:asciiname":"Xiayaotaihe",
    "gn:country_code":"CN",
    "gn:dem":27,
    "gn:feature_class":"P",
    "gn:feature_code":"PPL",
    "gn:name":"Xiayaotaihe",
    "gn:population":0,
    "gn:timezone":"Asia/Shanghai",
    "iso:country":"CN",
    "name:zho_x_preferred":[
        "\u4e0b\u7a91\u53f0\u6cb3"
    ],
    "wof:name":"Xiayaotaihe",
    "wof:placetype":"locality"
},
  "geometry": {"coordinates":[113.72458,30.3616],"type":"Point"}
}