{
  "type": "Feature",
  "properties": {
    "gn:admin1_code":"12.0",
    "gn:asciiname":"Hei'ao",
    "gn:country_code":"CN",
    "gn:dem":834,
    "gn:feature_class":"P",
    "gn:feature_code":"PPL",
    "gn:name":"Hei\u2019ao",
    "gn:population":0,
    "gn:timezone":"Asia/Shanghai",
    "iso:country":"CN",
    "name:und_x_variant":[
        "Hei\u2019ao"
    ],
    "name:zho_x_preferred":[
        "\u9ed1\u51f9"
    ],
    "wof:name":"Hei'ao",
    "wof:placetype":"locality"
},
  "geometry": {"coordinates":[110.00912,32.48975],"type":"Point"}
}