{
  "type": "Feature",
  "properties": {
    "gn:admin1_code":"29.0",
    "gn:asciiname":"Cheyiping",
    "gn:country_code":"CN",
    "gn:dem":1812,
    "gn:feature_class":"P",
    "gn:feature_code":"PPL",
    "gn:name":"Cheyiping",
    "gn:population":0,
    "gn:timezone":"Asia/Shanghai",
    "iso:country":"CN",
    "name:zho_x_preferred":[
        "\u8f66\u9091\u576a"
    ],
    "wof:name":"Cheyiping",
    "wof:placetype":"locality"
},
  "geometry": {"coordinates":[99.1704,26.7935],"type":"Point"}
}