{
  "type": "Feature",
  "properties": {
    "gn:admin1_code":"11.0",
    "gn:asciiname":"Shibixia",
    "gn:country_code":"CN",
    "gn:dem":345,
    "gn:feature_class":"P",
    "gn:feature_code":"PPL",
    "gn:name":"Shibixia",
    "gn:population":0,
    "gn:timezone":"Asia/Shanghai",
    "iso:country":"CN",
    "name:zho_x_preferred":[
        "\u77f3\u58c1\u4e0b"
    ],
    "wof:name":"Shibixia",
    "wof:placetype":"locality"
},
  "geometry": {"coordinates":[113.69712,25.63855],"type":"Point"}
}