{
  "type": "Feature",
  "properties": {
    "gn:admin1_code":"14",
    "gn:asciiname":"Shalu",
    "gn:country_code":"CN",
    "gn:dem":4356,
    "gn:feature_class":"P",
    "gn:feature_code":"PPL",
    "gn:name":"Shalu",
    "gn:population":0,
    "gn:timezone":"Asia/Urumqi",
    "iso:country":"CN",
    "name:zho_x_preferred":[
        "\u838e\u9c81"
    ],
    "wof:name":"Shalu",
    "wof:placetype":"locality"
},
  "geometry": {"coordinates":[89.60080000000001,28.452],"type":"Point"}
}