{
  "type": "Feature",
  "properties": {
    "gn:admin1_code":"32.0",
    "gn:asciiname":"Niupingzi",
    "gn:country_code":"CN",
    "gn:dem":1398,
    "gn:feature_class":"P",
    "gn:feature_code":"PPL",
    "gn:name":"Niupingzi",
    "gn:population":0,
    "gn:timezone":"Asia/Shanghai",
    "iso:country":"CN",
    "name:zho_x_preferred":[
        "\u725b\u576a\u5b50"
    ],
    "wof:name":"Niupingzi",
    "wof:placetype":"locality"
},
  "geometry": {"coordinates":[101.95125,26.71927],"type":"Point"}
}