{
  "type": "Feature",
  "properties": {
    "gn:admin1_code":"3.0",
    "gn:asciiname":"Yingjiang",
    "gn:country_code":"CN",
    "gn:dem":183,
    "gn:feature_class":"P",
    "gn:feature_code":"PPL",
    "gn:name":"Yingjiang",
    "gn:population":0,
    "gn:timezone":"Asia/Shanghai",
    "iso:country":"CN",
    "name:und_x_variant":[
        "\u9896\u6c5f"
    ],
    "wof:name":"Yingjiang",
    "wof:placetype":"locality"
},
  "geometry": {"coordinates":[114.94947000000001,29.54086],"type":"Point"}
}