{
  "type": "Feature",
  "properties": {
    "gn:admin1_code":"8.0",
    "gn:asciiname":"Diaoyugou",
    "gn:country_code":"CN",
    "gn:dem":352,
    "gn:feature_class":"P",
    "gn:feature_code":"PPLF",
    "gn:name":"Diaoyugou",
    "gn:population":0,
    "gn:timezone":"Asia/Shanghai",
    "iso:country":"CN",
    "name:und_x_variant":[
        "\u9493\u9c7c\u6c9f"
    ],
    "wof:name":"Diaoyugou",
    "wof:placetype":"locality"
},
  "geometry": {"coordinates":[127.16453,49.7201],"type":"Point"}
}