{
  "type": "Feature",
  "properties": {
    "gn:admin1_code":"12.0",
    "gn:asciiname":"Zhengjiajuan",
    "gn:country_code":"CN",
    "gn:dem":27,
    "gn:feature_class":"P",
    "gn:feature_code":"PPL",
    "gn:name":"Zhengjiajuan",
    "gn:population":0,
    "gn:timezone":"Asia/Shanghai",
    "iso:country":"CN",
    "name:und_x_variant":[
        "\u90d1\u5bb6\u5377"
    ],
    "wof:name":"Zhengjiajuan",
    "wof:placetype":"locality"
},
  "geometry": {"coordinates":[114.52007999999999,30.85882],"type":"Point"}
}