{
  "type": "Feature",
  "properties": {
    "gn:admin1_code":"5.0",
    "gn:asciiname":"Xiaobinglianggou",
    "gn:country_code":"CN",
    "gn:dem":790,
    "gn:feature_class":"P",
    "gn:feature_code":"PPL",
    "gn:name":"Xiaobinglianggou",
    "gn:population":0,
    "gn:timezone":"Asia/Shanghai",
    "iso:country":"CN",
    "name:und_x_variant":[
        "\u5c0f\u51b0\u51c9\u6c9f"
    ],
    "wof:name":"Xiaobinglianggou",
    "wof:placetype":"locality"
},
  "geometry": {"coordinates":[127.27743999999998,42.26207],"type":"Point"}
}