{
  "type": "Feature",
  "properties": {
    "gn:admin1_code":"26.0",
    "gn:asciiname":"Wujia Shancun",
    "gn:country_code":"CN",
    "gn:dem":1068,
    "gn:feature_class":"P",
    "gn:feature_code":"PPL",
    "gn:name":"Wujia Shancun",
    "gn:population":0,
    "gn:timezone":"Asia/Shanghai",
    "iso:country":"CN",
    "name:zho_x_preferred":[
        "\u5434\u5bb6\u5c71\u6751"
    ],
    "wof:name":"Wujia Shancun",
    "wof:placetype":"locality"
},
  "geometry": {"coordinates":[109.86499999999999,37.758],"type":"Point"}
}