{
  "type": "Feature",
  "properties": {
    "gn:admin1_code":"15.0",
    "gn:asciiname":"Da'ebotu",
    "gn:country_code":"CN",
    "gn:dem":2848,
    "gn:feature_class":"P",
    "gn:feature_code":"PPL",
    "gn:name":"Da\u2019ebotu",
    "gn:population":0,
    "gn:timezone":"Asia/Urumqi",
    "iso:country":"CN",
    "name:und_x_variant":[
        "Da\u2019ebotu"
    ],
    "name:zho_x_preferred":[
        "\u5927\u9102\u535a\u56fe"
    ],
    "wof:name":"Da'ebotu",
    "wof:placetype":"locality"
},
  "geometry": {"coordinates":[94.10980000000001,39.3768],"type":"Point"}
}