{
  "type": "Feature",
  "properties": {
    "gn:admin1_code":"33.0",
    "gn:asciiname":"Baishucao",
    "gn:country_code":"CN",
    "gn:dem":943,
    "gn:feature_class":"P",
    "gn:feature_code":"PPL",
    "gn:name":"Baishucao",
    "gn:population":0,
    "gn:timezone":"Asia/Shanghai",
    "iso:country":"CN",
    "name:zho_x_preferred":[
        "\u67cf\u6811\u69fd"
    ],
    "wof:name":"Baishucao",
    "wof:placetype":"locality"
},
  "geometry": {"coordinates":[109.54653,30.86782],"type":"Point"}
}