{
  "type": "Feature",
  "properties": {
    "gn:admin1_code":"8.0",
    "gn:asciiname":"Tumutaicun",
    "gn:country_code":"CN",
    "gn:dem":142,
    "gn:feature_class":"P",
    "gn:feature_code":"PPL",
    "gn:name":"Tumutaicun",
    "gn:population":0,
    "gn:timezone":"Asia/Shanghai",
    "iso:country":"CN",
    "name:zho_x_preferred":[
        "\u5410\u6728\u53f0\u6751"
    ],
    "wof:name":"Tumutaicun",
    "wof:placetype":"locality"
},
  "geometry": {"coordinates":[123.93965,46.93679],"type":"Point"}
}