{
  "type": "Feature",
  "properties": {
    "gn:admin1_code":"26.0",
    "gn:asciiname":"Tanggoukou",
    "gn:country_code":"CN",
    "gn:dem":1431,
    "gn:feature_class":"P",
    "gn:feature_code":"PPL",
    "gn:name":"Tanggoukou",
    "gn:population":0,
    "gn:timezone":"Asia/Shanghai",
    "iso:country":"CN",
    "name:und_x_variant":[
        "\u5510\u6c9f\u53e3"
    ],
    "wof:name":"Tanggoukou",
    "wof:placetype":"locality"
},
  "geometry": {"coordinates":[106.96356000000002,33.97659],"type":"Point"}
}