{
  "type": "Feature",
  "properties": {
    "gn:admin1_code":"16",
    "gn:asciiname":"Liqianling",
    "gn:country_code":"CN",
    "gn:dem":567,
    "gn:feature_class":"P",
    "gn:feature_code":"PPL",
    "gn:name":"Liqianling",
    "gn:population":0,
    "gn:timezone":"Asia/Shanghai",
    "iso:country":"CN",
    "name:zho_x_preferred":[
        "\u91cc\u4e7e\u5cad"
    ],
    "wof:name":"Liqianling",
    "wof:placetype":"locality"
},
  "geometry": {"coordinates":[110.145,25.5907],"type":"Point"}
}