{
  "type": "Feature",
  "properties": {
    "gn:admin1_code":"32.0",
    "gn:asciiname":"Damushu",
    "gn:country_code":"CN",
    "gn:dem":721,
    "gn:feature_class":"P",
    "gn:feature_code":"PPL",
    "gn:name":"Damushu",
    "gn:population":0,
    "gn:timezone":"Asia/Shanghai",
    "iso:country":"CN",
    "name:zho_x_preferred":[
        "\u5927\u6728\u6811"
    ],
    "wof:name":"Damushu",
    "wof:placetype":"locality"
},
  "geometry": {"coordinates":[107.18600000000001,31.9521],"type":"Point"}
}