{
  "type": "Feature",
  "properties": {
    "gn:admin1_code":"4.0",
    "gn:asciiname":"Dajianzi",
    "gn:country_code":"CN",
    "gn:dem":23,
    "gn:feature_class":"P",
    "gn:feature_code":"PPL",
    "gn:name":"Dajianzi",
    "gn:population":0,
    "gn:timezone":"Asia/Shanghai",
    "iso:country":"CN",
    "name:zho_x_preferred":[
        "\u5927\u6da7\u5b50"
    ],
    "wof:name":"Dajianzi",
    "wof:placetype":"locality"
},
  "geometry": {"coordinates":[119.16918,31.91722],"type":"Point"}
}