{
  "type": "Feature",
  "properties": {
    "gn:admin1_code":"19.0",
    "gn:asciiname":"Taigouli",
    "gn:country_code":"CN",
    "gn:dem":375,
    "gn:feature_class":"P",
    "gn:feature_code":"PPL",
    "gn:name":"Taigouli",
    "gn:population":0,
    "gn:timezone":"Asia/Shanghai",
    "iso:country":"CN",
    "name:und_x_variant":[
        "\u53f0\u6c9f\u91cc"
    ],
    "name:zho_x_preferred":[
        "\u53f0\u6c9f\u91cc"
    ],
    "wof:name":"Taigouli",
    "wof:placetype":"locality"
},
  "geometry": {"coordinates":[124.66289,41.8189],"type":"Point"}
}