{
  "type": "Feature",
  "properties": {
    "gn:admin1_code":"12.0",
    "gn:asciiname":"Hehuaqiao",
    "gn:country_code":"CN",
    "gn:dem":26,
    "gn:feature_class":"P",
    "gn:feature_code":"PPL",
    "gn:name":"Hehuaqiao",
    "gn:population":0,
    "gn:timezone":"Asia/Shanghai",
    "iso:country":"CN",
    "name:zho_x_preferred":[
        "\u8377\u82b1\u6865"
    ],
    "wof:name":"Hehuaqiao",
    "wof:placetype":"locality"
},
  "geometry": {"coordinates":[113.75348,30.44344],"type":"Point"}
}