{
  "type": "Feature",
  "properties": {
    "gn:admin1_code":"29",
    "gn:asciiname":"Diaocao'ao",
    "gn:country_code":"CN",
    "gn:dem":1817,
    "gn:feature_class":"P",
    "gn:feature_code":"PPL",
    "gn:name":"Diaocao\u2019ao",
    "gn:population":0,
    "gn:timezone":"Asia/Shanghai",
    "iso:country":"CN",
    "name:und_x_variant":[
        "Diaocao\u2019ao"
    ],
    "name:zho_x_preferred":[
        "\u540a\u69fd\u51f9"
    ],
    "wof:name":"Diaocao'ao",
    "wof:placetype":"locality"
},
  "geometry": {"coordinates":[101.55200000000001,25.0616],"type":"Point"}
}