{
  "type": "Feature",
  "properties": {
    "gn:admin1_code":"9",
    "gn:asciiname":"Baofeng",
    "gn:country_code":"CN",
    "gn:dem":812,
    "gn:feature_class":"P",
    "gn:feature_code":"PPL",
    "gn:name":"Baofeng",
    "gn:population":0,
    "gn:timezone":"Asia/Shanghai",
    "iso:country":"CN",
    "name:und_x_variant":[
        "\u5b9d\u4e30",
        "Baofenggou",
        "Baofeng"
    ],
    "wof:name":"Baofeng",
    "wof:placetype":"locality"
},
  "geometry": {"coordinates":[112.42863,33.94213],"type":"Point"}
}