{
  "type": "Feature",
  "properties": {
    "gn:admin1_code":"14",
    "gn:asciiname":"Nyainba",
    "gn:country_code":"CN",
    "gn:dem":4453,
    "gn:feature_class":"P",
    "gn:feature_code":"PPL",
    "gn:name":"Nyainba",
    "gn:population":0,
    "gn:timezone":"Asia/Urumqi",
    "iso:country":"CN",
    "name:bod_x_preferred":[
        "\u0f66\u0f99\u0f53\u0f0b\u0f54"
    ],
    "wof:name":"Nyainba",
    "wof:placetype":"locality"
},
  "geometry": {"coordinates":[90.73703,29.01925],"type":"Point"}
}