{
  "type": "Feature",
  "properties": {
    "gn:admin1_code":"29",
    "gn:asciiname":"Shanggucheng",
    "gn:country_code":"CN",
    "gn:dem":1482,
    "gn:feature_class":"P",
    "gn:feature_code":"PPL",
    "gn:name":"Shanggucheng",
    "gn:population":0,
    "gn:timezone":"Asia/Shanghai",
    "iso:country":"CN",
    "name:zho_x_preferred":[
        "\u4e0a\u53e4\u57ce"
    ],
    "wof:name":"Shanggucheng",
    "wof:placetype":"locality"
},
  "geometry": {"coordinates":[101.976,24.0564],"type":"Point"}
}