{
  "type": "Feature",
  "properties": {
    "gn:admin1_code":"5.0",
    "gn:asciiname":"Menfangzhang",
    "gn:country_code":"CN",
    "gn:dem":136,
    "gn:feature_class":"P",
    "gn:feature_code":"PPL",
    "gn:name":"Menfangzhang",
    "gn:population":0,
    "gn:timezone":"Asia/Shanghai",
    "iso:country":"CN",
    "name:zho_x_preferred":[
        "\u95e8\u623f\u5f20"
    ],
    "wof:name":"Menfangzhang",
    "wof:placetype":"locality"
},
  "geometry": {"coordinates":[124.13393000000001,43.66224],"type":"Point"}
}