{
  "type": "Feature",
  "properties": {
    "gn:admin1_code":"32.0",
    "gn:asciiname":"Hezhangshi",
    "gn:country_code":"CN",
    "gn:dem":255,
    "gn:feature_class":"P",
    "gn:feature_code":"PPL",
    "gn:name":"Hezhangshi",
    "gn:population":0,
    "gn:timezone":"Asia/Shanghai",
    "iso:country":"CN",
    "name:zho_x_preferred":[
        "\u5408\u638c\u77f3"
    ],
    "wof:name":"Hezhangshi",
    "wof:placetype":"locality"
},
  "geometry": {"coordinates":[106.271,30.2922],"type":"Point"}
}