{
  "type": "Feature",
  "properties": {
    "gn:admin1_code":"16.0",
    "gn:asciiname":"Xiaonitang",
    "gn:country_code":"CN",
    "gn:dem":493,
    "gn:feature_class":"P",
    "gn:feature_code":"PPL",
    "gn:name":"Xiaonitang",
    "gn:population":0,
    "gn:timezone":"Asia/Shanghai",
    "iso:country":"CN",
    "name:zho_x_preferred":[
        "\u5c0f\u6ce5\u5858"
    ],
    "wof:name":"Xiaonitang",
    "wof:placetype":"locality"
},
  "geometry": {"coordinates":[107.82899999999999,24.8999],"type":"Point"}
}