{
  "type": "Feature",
  "properties": {
    "gn:admin1_code":"12.0",
    "gn:asciiname":"Dongbianshan",
    "gn:country_code":"CN",
    "gn:dem":130,
    "gn:feature_class":"P",
    "gn:feature_code":"PPL",
    "gn:name":"Dongbianshan",
    "gn:population":0,
    "gn:timezone":"Asia/Shanghai",
    "iso:country":"CN",
    "name:zho_x_preferred":[
        "\u4e1c\u8fb9\u5c71"
    ],
    "wof:name":"Dongbianshan",
    "wof:placetype":"locality"
},
  "geometry": {"coordinates":[114.79564999999999,31.27126],"type":"Point"}
}