{
  "type": "Feature",
  "properties": {
    "gn:admin1_code":"6.0",
    "gn:asciiname":"Kenci'er",
    "gn:country_code":"CN",
    "gn:dem":4539,
    "gn:feature_class":"P",
    "gn:feature_code":"PPL",
    "gn:name":"Kenci\u2019er",
    "gn:population":0,
    "gn:timezone":"Asia/Urumqi",
    "iso:country":"CN",
    "name:und_x_variant":[
        "Kenci\u2019er"
    ],
    "name:zho_x_preferred":[
        "\u80af\u523a\u513f"
    ],
    "wof:name":"Kenci'er",
    "wof:placetype":"locality"
},
  "geometry": {"coordinates":[95.96281,32.17593],"type":"Point"}
}