{
  "type": "Feature",
  "properties": {
    "gn:admin1_code":"33.0",
    "gn:asciiname":"Puxichang",
    "gn:country_code":"CN",
    "gn:dem":216,
    "gn:feature_class":"P",
    "gn:feature_code":"PPL",
    "gn:name":"Puxichang",
    "gn:population":0,
    "gn:timezone":"Asia/Shanghai",
    "iso:country":"CN",
    "name:zho_x_preferred":[
        "\u84b2\u6eaa\u573a"
    ],
    "wof:name":"Puxichang",
    "wof:placetype":"locality"
},
  "geometry": {"coordinates":[106.38368,30.08204000000001],"type":"Point"}
}