{
  "type": "Feature",
  "properties": {
    "gn:admin1_code":"5.0",
    "gn:asciiname":"Jiefang Nancun",
    "gn:country_code":"CN",
    "gn:dem":301,
    "gn:feature_class":"P",
    "gn:feature_code":"PPL",
    "gn:name":"Jiefang Nancun",
    "gn:population":0,
    "gn:timezone":"Asia/Shanghai",
    "iso:country":"CN",
    "name:zho_x_preferred":[
        "\u89e3\u653e\u5357\u6751"
    ],
    "wof:name":"Jiefang Nancun",
    "wof:placetype":"locality"
},
  "geometry": {"coordinates":[125.90036000000001,43.27146],"type":"Point"}
}