{
  "type": "Feature",
  "properties": {
    "gn:admin1_code":"24.0",
    "gn:asciiname":"Putong",
    "gn:country_code":"CN",
    "gn:dem":1177,
    "gn:feature_class":"P",
    "gn:feature_code":"PPL",
    "gn:name":"Putong",
    "gn:population":0,
    "gn:timezone":"Asia/Shanghai",
    "iso:country":"CN",
    "name:zho_x_preferred":[
        "\u666e\u901a"
    ],
    "wof:name":"Putong",
    "wof:placetype":"locality"
},
  "geometry": {"coordinates":[111.70763999999998,38.25892],"type":"Point"}
}