{
  "type": "Feature",
  "properties": {
    "gn:admin1_code":"12.0",
    "gn:asciiname":"Shangshaojiapeng",
    "gn:country_code":"CN",
    "gn:dem":98,
    "gn:feature_class":"P",
    "gn:feature_code":"PPL",
    "gn:name":"Shangshaojiapeng",
    "gn:population":0,
    "gn:timezone":"Asia/Shanghai",
    "iso:country":"CN",
    "name:zho_x_preferred":[
        "Shangshaojiapeng"
    ],
    "name:zho_x_variant":[
        "\u4e0a\u90b5\u5bb6\u68da"
    ],
    "wof:name":"Shangshaojiapeng",
    "wof:placetype":"locality"
},
  "geometry": {"coordinates":[112.95480000000001,30.9001],"type":"Point"}
}