{
  "type": "Feature",
  "properties": {
    "gn:admin1_code":"1.0",
    "gn:asciiname":"Huguangcun",
    "gn:country_code":"CN",
    "gn:dem":23,
    "gn:feature_class":"P",
    "gn:feature_code":"PPL",
    "gn:name":"Huguangcun",
    "gn:population":0,
    "gn:timezone":"Asia/Shanghai",
    "iso:country":"CN",
    "name:und_x_variant":[
        "Huguang"
    ],
    "name:zho_x_preferred":[
        "\u6e56\u5149\u6751"
    ],
    "wof:name":"Huguangcun",
    "wof:placetype":"locality"
},
  "geometry": {"coordinates":[117.46802,31.61316],"type":"Point"}
}