{
  "type": "Feature",
  "properties": {
    "gn:admin1_code":"12.0",
    "gn:asciiname":"Aojiazhai",
    "gn:country_code":"CN",
    "gn:dem":73,
    "gn:feature_class":"P",
    "gn:feature_code":"PPL",
    "gn:name":"Aojiazhai",
    "gn:population":0,
    "gn:timezone":"Asia/Shanghai",
    "iso:country":"CN",
    "name:zho_x_preferred":[
        "\u6556\u5bb6\u5be8"
    ],
    "wof:name":"Aojiazhai",
    "wof:placetype":"locality"
},
  "geometry": {"coordinates":[113.41454,31.15635],"type":"Point"}
}