{
  "type": "Feature",
  "properties": {
    "gn:admin1_code":"24",
    "gn:asciiname":"Jiangan",
    "gn:cc2":"CN",
    "gn:country_code":"CN",
    "gn:dem":1346,
    "gn:feature_class":"P",
    "gn:feature_code":"PPL",
    "gn:name":"Jiangan",
    "gn:population":0,
    "gn:timezone":"Asia/Shanghai",
    "iso:country":"CN",
    "name:und_x_variant":[
        "Chien-kan-ts\u2019un",
        "Jiangan"
    ],
    "wof:name":"Jiangan",
    "wof:placetype":"locality"
},
  "geometry": {"coordinates":[112.31028000000001,38.24806],"type":"Point"}
}