{
  "type": "Feature",
  "properties": {
    "gn:admin1_code":"20.0",
    "gn:asciiname":"Yifaquan",
    "gn:country_code":"CN",
    "gn:dem":1472,
    "gn:feature_class":"P",
    "gn:feature_code":"PPLA4",
    "gn:name":"Yifaquan",
    "gn:population":0,
    "gn:timezone":"Asia/Shanghai",
    "iso:country":"CN",
    "name:und_x_variant":[
        "\u4e49\u53d1\u6cc9"
    ],
    "wof:name":"Yifaquan",
    "wof:placetype":"locality"
},
  "geometry": {"coordinates":[112.52687,41.62315],"type":"Point"}
}