{
  "type": "Feature",
  "properties": {
    "gn:admin1_code":"6.0",
    "gn:asciiname":"Suozhai",
    "gn:country_code":"CN",
    "gn:dem":3941,
    "gn:feature_class":"P",
    "gn:feature_code":"PPL",
    "gn:name":"Suozhai",
    "gn:population":0,
    "gn:timezone":"Asia/Urumqi",
    "iso:country":"CN",
    "name:zho_x_preferred":[
        "\u7d22\u5be8"
    ],
    "wof:name":"Suozhai",
    "wof:placetype":"locality"
},
  "geometry": {"coordinates":[95.98872,32.07744],"type":"Point"}
}