{
  "type": "Feature",
  "properties": {
    "gn:admin1_code":"26.0",
    "gn:asciiname":"Huanggangxiang",
    "gn:country_code":"CN",
    "gn:dem":567,
    "gn:feature_class":"P",
    "gn:feature_code":"PPL",
    "gn:name":"Huanggangxiang",
    "gn:population":0,
    "gn:timezone":"Asia/Shanghai",
    "iso:country":"CN",
    "name:und_x_variant":[
        "\u9ec4\u5c97\u4e61"
    ],
    "wof:name":"Huanggangxiang",
    "wof:placetype":"locality"
},
  "geometry": {"coordinates":[107.18897,32.98017],"type":"Point"}
}