{
  "type": "Feature",
  "properties": {
    "gn:admin1_code":"2.0",
    "gn:asciiname":"Zhujia Hetou",
    "gn:country_code":"CN",
    "gn:dem":4,
    "gn:feature_class":"P",
    "gn:feature_code":"PPL",
    "gn:name":"Zhujia Hetou",
    "gn:population":0,
    "gn:timezone":"Asia/Shanghai",
    "iso:country":"CN",
    "name:und_x_variant":[
        "Chu-chia-ho-t\u2019ou",
        "Zhujia Hetou"
    ],
    "wof:name":"Zhujia Hetou",
    "wof:placetype":"locality"
},
  "geometry": {"coordinates":[121.68333,29.93778],"type":"Point"}
}