{
  "type": "Feature",
  "properties": {
    "gn:admin1_code":"15.0",
    "gn:asciiname":"Qianjiaba",
    "gn:country_code":"CN",
    "gn:dem":1648,
    "gn:feature_class":"P",
    "gn:feature_code":"PPL",
    "gn:name":"Qianjiaba",
    "gn:population":0,
    "gn:timezone":"Asia/Shanghai",
    "iso:country":"CN",
    "name:zho_x_preferred":[
        "\u524d\u5bb6\u575d"
    ],
    "wof:name":"Qianjiaba",
    "wof:placetype":"locality"
},
  "geometry": {"coordinates":[105.81,34.2666],"type":"Point"}
}