{
  "type": "Feature",
  "properties": {
    "gn:admin1_code":"12.0",
    "gn:asciiname":"Tuozigang",
    "gn:country_code":"CN",
    "gn:dem":87,
    "gn:feature_class":"P",
    "gn:feature_code":"PPL",
    "gn:name":"Tuozigang",
    "gn:population":0,
    "gn:timezone":"Asia/Shanghai",
    "iso:country":"CN",
    "name:zho_x_preferred":[
        "\u9a7c\u5b50\u5c97"
    ],
    "wof:name":"Tuozigang",
    "wof:placetype":"locality"
},
  "geometry": {"coordinates":[114.01904,31.57982],"type":"Point"}
}