{
  "type": "Feature",
  "properties": {
    "gn:admin1_code":"1.0",
    "gn:asciiname":"Shanyang",
    "gn:country_code":"CN",
    "gn:dem":9,
    "gn:feature_class":"P",
    "gn:feature_code":"PPL",
    "gn:name":"Shanyang",
    "gn:population":0,
    "gn:timezone":"Asia/Shanghai",
    "iso:country":"CN",
    "name:ceb_x_preferred":[
        "Shanyang"
    ],
    "name:deu_x_preferred":[
        "Shanyang"
    ],
    "name:fra_x_preferred":[
        "Shanyang"
    ],
    "name:mlg_x_preferred":[
        "Shanyang"
    ],
    "name:nor_x_preferred":[
        "Shanyang"
    ],
    "name:rus_x_preferred":[
        "\u0428\u0430\u043d\u044c\u044f\u043d"
    ],
    "name:swe_x_preferred":[
        "Shanyang"
    ],
    "name:zho_x_preferred":[
        "\u5c71\u9633"
    ],
    "wof:name":"Shanyang",
    "wof:placetype":"locality"
},
  "geometry": {"coordinates":[118.41256,31.2989],"type":"Point"}
}