{
  "type": "Feature",
  "properties": {
    "gn:admin1_code":"29.0",
    "gn:asciiname":"Muzhutang",
    "gn:country_code":"CN",
    "gn:dem":2263,
    "gn:feature_class":"P",
    "gn:feature_code":"PPL",
    "gn:name":"Muzhutang",
    "gn:population":0,
    "gn:timezone":"Asia/Shanghai",
    "iso:country":"CN",
    "name:zho_x_preferred":[
        "\u6bcd\u732a\u5858"
    ],
    "wof:name":"Muzhutang",
    "wof:placetype":"locality"
},
  "geometry": {"coordinates":[102.595,25.5878],"type":"Point"}
}