{
  "type": "Feature",
  "properties": {
    "gn:admin1_code":"11.0",
    "gn:asciiname":"Jingtangshan",
    "gn:country_code":"CN",
    "gn:dem":578,
    "gn:feature_class":"P",
    "gn:feature_code":"PPL",
    "gn:name":"Jingtangshan",
    "gn:population":0,
    "gn:timezone":"Asia/Shanghai",
    "iso:country":"CN",
    "name:zho_x_preferred":[
        "\u4e95\u5858\u5c71"
    ],
    "wof:name":"Jingtangshan",
    "wof:placetype":"locality"
},
  "geometry": {"coordinates":[110.81574000000001,26.79203],"type":"Point"}
}