{
  "type": "Feature",
  "properties": {
    "gn:admin1_code":"24",
    "gn:asciiname":"Guai'er",
    "gn:country_code":"CN",
    "gn:dem":1004,
    "gn:feature_class":"P",
    "gn:feature_code":"PPL",
    "gn:name":"Guai\u2019er",
    "gn:population":0,
    "gn:timezone":"Asia/Shanghai",
    "iso:country":"CN",
    "name:und_x_variant":[
        "Kuai-erh",
        "Guai\u2019erzhen",
        "Kuai-erh-chen",
        "Guai\u2019er"
    ],
    "wof:name":"Guai'er",
    "wof:placetype":"locality"
},
  "geometry": {"coordinates":[113.62528,37.07694],"type":"Point"}
}