{
  "type": "Feature",
  "properties": {
    "gn:admin1_code":"18",
    "gn:asciiname":"Kachao",
    "gn:country_code":"CN",
    "gn:dem":1246,
    "gn:feature_class":"P",
    "gn:feature_code":"PPL",
    "gn:name":"Kachao",
    "gn:population":0,
    "gn:timezone":"Asia/Shanghai",
    "iso:country":"CN",
    "name:zho_x_preferred":[
        "\u5361\u671d"
    ],
    "wof:name":"Kachao",
    "wof:placetype":"locality"
},
  "geometry": {"coordinates":[106.02800000000001,25.3097],"type":"Point"}
}