{
  "type": "Feature",
  "properties": {
    "gn:admin1_code":"11.0",
    "gn:asciiname":"Dongtingbin",
    "gn:country_code":"CN",
    "gn:dem":33,
    "gn:feature_class":"P",
    "gn:feature_code":"PPL",
    "gn:name":"Dongtingbin",
    "gn:population":0,
    "gn:timezone":"Asia/Shanghai",
    "iso:country":"CN",
    "name:zho_x_preferred":[
        "\u6d1e\u5ead\u6ee8"
    ],
    "wof:name":"Dongtingbin",
    "wof:placetype":"locality"
},
  "geometry": {"coordinates":[112.56358,29.00852],"type":"Point"}
}