{
  "type": "Feature",
  "properties": {
    "gn:admin1_code":"8.0",
    "gn:asciiname":"Zhangyingtun",
    "gn:country_code":"CN",
    "gn:dem":132,
    "gn:feature_class":"P",
    "gn:feature_code":"PPL",
    "gn:name":"Zhangyingtun",
    "gn:population":0,
    "gn:timezone":"Asia/Shanghai",
    "iso:country":"CN",
    "name:zho_x_preferred":[
        "\u5f20\u82f1\u5c6f"
    ],
    "wof:name":"Zhangyingtun",
    "wof:placetype":"locality"
},
  "geometry": {"coordinates":[127.39614,46.03143],"type":"Point"}
}