{
  "type": "Feature",
  "properties": {
    "gn:admin1_code":"3.0",
    "gn:asciiname":"Shanbei",
    "gn:country_code":"CN",
    "gn:dem":89,
    "gn:feature_class":"P",
    "gn:feature_code":"PPL",
    "gn:name":"Shanbei",
    "gn:population":0,
    "gn:timezone":"Asia/Shanghai",
    "iso:country":"CN",
    "name:und_x_variant":[
        "\u5c71\u80cc"
    ],
    "wof:name":"Shanbei",
    "wof:placetype":"locality"
},
  "geometry": {"coordinates":[116.59687,27.25887],"type":"Point"}
}