{
  "type": "Feature",
  "properties": {
    "gn:admin1_code":"8.0",
    "gn:asciiname":"Yixingquan",
    "gn:country_code":"CN",
    "gn:dem":124,
    "gn:feature_class":"P",
    "gn:feature_code":"PPL",
    "gn:name":"Yixingquan",
    "gn:population":0,
    "gn:timezone":"Asia/Shanghai",
    "iso:country":"CN",
    "name:zho_x_preferred":[
        "\u4e49\u5174\u6cc9"
    ],
    "wof:name":"Yixingquan",
    "wof:placetype":"locality"
},
  "geometry": {"coordinates":[126.84096,45.74097],"type":"Point"}
}