{
  "type": "Feature",
  "properties": {
    "gn:admin1_code":"1.0",
    "gn:asciiname":"Changzhuangcun",
    "gn:country_code":"CN",
    "gn:dem":33,
    "gn:feature_class":"P",
    "gn:feature_code":"PPL",
    "gn:name":"Changzhuangcun",
    "gn:population":0,
    "gn:timezone":"Asia/Shanghai",
    "iso:country":"CN",
    "name:zho_x_preferred":[
        "\u5e38\u5e84\u6751"
    ],
    "wof:name":"Changzhuangcun",
    "wof:placetype":"locality"
},
  "geometry": {"coordinates":[116.30408,33.7373],"type":"Point"}
}