{
  "type": "Feature",
  "properties": {
    "gn:admin1_code":"3.0",
    "gn:asciiname":"Tongluoqiu",
    "gn:country_code":"CN",
    "gn:dem":196,
    "gn:feature_class":"P",
    "gn:feature_code":"PPL",
    "gn:name":"Tongluoqiu",
    "gn:population":0,
    "gn:timezone":"Asia/Shanghai",
    "iso:country":"CN",
    "name:und_x_variant":[
        "\u94dc\u9523\u4e18"
    ],
    "wof:name":"Tongluoqiu",
    "wof:placetype":"locality"
},
  "geometry": {"coordinates":[115.40803,26.39043],"type":"Point"}
}