{
  "type": "Feature",
  "properties": {
    "gn:admin1_code":"7",
    "gn:asciiname":"Denglu",
    "gn:country_code":"CN",
    "gn:dem":379,
    "gn:feature_class":"P",
    "gn:feature_code":"PPL",
    "gn:name":"Denglu",
    "gn:population":0,
    "gn:timezone":"Asia/Shanghai",
    "iso:country":"CN",
    "name:zho_x_preferred":[
        "\u706f\u7089"
    ],
    "wof:name":"Denglu",
    "wof:placetype":"locality"
},
  "geometry": {"coordinates":[119.09088,25.73773],"type":"Point"}
}