{
  "type": "Feature",
  "properties": {
    "gn:admin1_code":"32.0",
    "gn:asciiname":"Zhuocangcun",
    "gn:country_code":"CN",
    "gn:dem":3216,
    "gn:feature_class":"P",
    "gn:feature_code":"PPL",
    "gn:name":"Zhuocangcun",
    "gn:population":0,
    "gn:timezone":"Asia/Shanghai",
    "iso:country":"CN",
    "name:zho_x_preferred":[
        "\u5353\u85cf\u6751"
    ],
    "wof:name":"Zhuocangcun",
    "wof:placetype":"locality"
},
  "geometry": {"coordinates":[103.236,33.7101],"type":"Point"}
}