{
  "type": "Feature",
  "properties": {
    "gn:admin1_code":"26.0",
    "gn:asciiname":"Shidizhan",
    "gn:country_code":"CN",
    "gn:dem":1408,
    "gn:feature_class":"P",
    "gn:feature_code":"PPL",
    "gn:name":"Shidizhan",
    "gn:population":0,
    "gn:timezone":"Asia/Shanghai",
    "iso:country":"CN",
    "name:zho_x_preferred":[
        "\u77f3\u5e95\u7ad9"
    ],
    "wof:name":"Shidizhan",
    "wof:placetype":"locality"
},
  "geometry": {"coordinates":[108.66764000000001,35.41265999999999],"type":"Point"}
}