{
  "type": "Feature",
  "properties": {
    "gn:admin1_code":"29",
    "gn:asciiname":"Maozu",
    "gn:cc2":"CN",
    "gn:country_code":"CN",
    "gn:dem":2403,
    "gn:feature_class":"P",
    "gn:feature_code":"PPL",
    "gn:name":"Maozu",
    "gn:population":0,
    "gn:timezone":"Asia/Shanghai",
    "iso:country":"CN",
    "name:und_x_variant":[
        "Mao-tsu",
        "Maozu"
    ],
    "wof:name":"Maozu",
    "wof:placetype":"locality"
},
  "geometry": {"coordinates":[103.85693999999999,27.33861],"type":"Point"}
}