{
  "type": "Feature",
  "properties": {
    "gn:admin1_code":"9.0",
    "gn:asciiname":"Wangchenzhuang",
    "gn:country_code":"CN",
    "gn:dem":72,
    "gn:feature_class":"P",
    "gn:feature_code":"PPL",
    "gn:name":"Wangchenzhuang",
    "gn:population":0,
    "gn:timezone":"Asia/Shanghai",
    "iso:country":"CN",
    "name:zho_x_preferred":[
        "\u738b\u9648\u5e84"
    ],
    "wof:name":"Wangchenzhuang",
    "wof:placetype":"locality"
},
  "geometry": {"coordinates":[114.45459,35.18833],"type":"Point"}
}