{
  "type": "Feature",
  "properties": {
    "gn:admin1_code":"11.0",
    "gn:asciiname":"Laohutang",
    "gn:country_code":"CN",
    "gn:dem":84,
    "gn:feature_class":"P",
    "gn:feature_code":"PPL",
    "gn:name":"Laohutang",
    "gn:population":0,
    "gn:timezone":"Asia/Shanghai",
    "iso:country":"CN",
    "name:zho_x_preferred":[
        "\u8001\u864e\u5858"
    ],
    "wof:name":"Laohutang",
    "wof:placetype":"locality"
},
  "geometry": {"coordinates":[112.74703999999998,26.91547000000001],"type":"Point"}
}