{
  "type": "Feature",
  "properties": {
    "gn:admin1_code":"05",
    "gn:asciiname":"Xiaohuanggou",
    "gn:cc2":"CN",
    "gn:country_code":"CN",
    "gn:dem":541,
    "gn:feature_class":"P",
    "gn:feature_code":"PPL",
    "gn:name":"Xiaohuanggou",
    "gn:population":0,
    "gn:timezone":"Asia/Shanghai",
    "iso:country":"CN",
    "name:und_x_variant":[
        "Hsiao-huang-kou",
        "Xiaohuanggou"
    ],
    "wof:name":"Xiaohuanggou",
    "wof:placetype":"locality"
},
  "geometry": {"coordinates":[126.05444,41.98694],"type":"Point"}
}