{
  "type": "Feature",
  "properties": {
    "gn:admin1_code":"5.0",
    "gn:asciiname":"Xilihua",
    "gn:country_code":"CN",
    "gn:dem":116,
    "gn:feature_class":"P",
    "gn:feature_code":"PPL",
    "gn:name":"Xilihua",
    "gn:population":0,
    "gn:timezone":"Asia/Shanghai",
    "iso:country":"CN",
    "name:zho_x_preferred":[
        "\u897f\u7406\u5316"
    ],
    "wof:name":"Xilihua",
    "wof:placetype":"locality"
},
  "geometry": {"coordinates":[130.30351999999999,42.95809000000001],"type":"Point"}
}