{
  "type": "Feature",
  "properties": {
    "gn:admin1_code":"3.0",
    "gn:asciiname":"Bailukeng",
    "gn:country_code":"CN",
    "gn:dem":94,
    "gn:feature_class":"P",
    "gn:feature_code":"PPL",
    "gn:name":"Bailukeng",
    "gn:population":0,
    "gn:timezone":"Asia/Shanghai",
    "iso:country":"CN",
    "name:und_x_variant":[
        "\u767d\u8def\u5751"
    ],
    "wof:name":"Bailukeng",
    "wof:placetype":"locality"
},
  "geometry": {"coordinates":[116.01649999999999,27.90138],"type":"Point"}
}