{
  "type": "Feature",
  "properties": {
    "gn:admin1_code":"15.0",
    "gn:asciiname":"Xiushuicha",
    "gn:country_code":"CN",
    "gn:dem":1979,
    "gn:feature_class":"P",
    "gn:feature_code":"PPL",
    "gn:name":"Xiushuicha",
    "gn:population":0,
    "gn:timezone":"Asia/Shanghai",
    "iso:country":"CN",
    "name:und_x_variant":[
        "\u79c0\u6c34\u5c94"
    ],
    "wof:name":"Xiushuicha",
    "wof:placetype":"locality"
},
  "geometry": {"coordinates":[105.37651,35.5901],"type":"Point"}
}