{
  "type": "Feature",
  "properties": {
    "gn:admin1_code":"29.0",
    "gn:asciiname":"Banzhulin",
    "gn:country_code":"CN",
    "gn:dem":1508,
    "gn:feature_class":"P",
    "gn:feature_code":"PPL",
    "gn:name":"Banzhulin",
    "gn:population":0,
    "gn:timezone":"Asia/Shanghai",
    "iso:country":"CN",
    "name:zho_x_preferred":[
        "\u73ed\u7af9\u6797"
    ],
    "wof:name":"Banzhulin",
    "wof:placetype":"locality"
},
  "geometry": {"coordinates":[101.19499999999999,22.3443],"type":"Point"}
}