{
  "type": "Feature",
  "properties": {
    "gn:admin1_code":"12.0",
    "gn:asciiname":"Xiaoyinpo",
    "gn:country_code":"CN",
    "gn:dem":1735,
    "gn:feature_class":"P",
    "gn:feature_code":"PPL",
    "gn:name":"Xiaoyinpo",
    "gn:population":0,
    "gn:timezone":"Asia/Shanghai",
    "iso:country":"CN",
    "name:zho_x_preferred":[
        "\u5c0f\u9634\u5761"
    ],
    "wof:name":"Xiaoyinpo",
    "wof:placetype":"locality"
},
  "geometry": {"coordinates":[109.05265,30.5127],"type":"Point"}
}