{
  "type": "Feature",
  "properties": {
    "gn:admin1_code":"14.0",
    "gn:asciiname":"Yueluo",
    "gn:country_code":"CN",
    "gn:dem":3561,
    "gn:feature_class":"P",
    "gn:feature_code":"PPL",
    "gn:name":"Yueluo",
    "gn:population":0,
    "gn:timezone":"Asia/Urumqi",
    "iso:country":"CN",
    "name:zho_x_preferred":[
        "\u7ea6\u843d"
    ],
    "wof:name":"Yueluo",
    "wof:placetype":"locality"
},
  "geometry": {"coordinates":[98.67776000000001,29.31637000000001],"type":"Point"}
}