{
  "type": "Feature",
  "properties": {
    "gn:admin1_code":"15.0",
    "gn:asciiname":"Saizha",
    "gn:country_code":"CN",
    "gn:dem":3048,
    "gn:feature_class":"P",
    "gn:feature_code":"PPL",
    "gn:name":"Saizha",
    "gn:population":0,
    "gn:timezone":"Asia/Shanghai",
    "iso:country":"CN",
    "name:zho_x_preferred":[
        "\u8d5b\u672d"
    ],
    "wof:name":"Saizha",
    "wof:placetype":"locality"
},
  "geometry": {"coordinates":[103.28100000000001,33.8888],"type":"Point"}
}