{
  "type": "Feature",
  "properties": {
    "gn:admin1_code":"26.0",
    "gn:asciiname":"Tayucun",
    "gn:country_code":"CN",
    "gn:dem":766,
    "gn:feature_class":"P",
    "gn:feature_code":"PPL",
    "gn:name":"Tayucun",
    "gn:population":0,
    "gn:timezone":"Asia/Shanghai",
    "iso:country":"CN",
    "name:und_x_variant":[
        "\u5854\u5cea\u6751"
    ],
    "wof:name":"Tayucun",
    "wof:placetype":"locality"
},
  "geometry": {"coordinates":[107.57982,33.35714],"type":"Point"}
}