{
  "type": "Feature",
  "properties": {
    "gn:admin1_code":"30.0",
    "gn:asciiname":"Dacuoliao",
    "gn:country_code":"CN",
    "gn:dem":3,
    "gn:feature_class":"P",
    "gn:feature_code":"PPL",
    "gn:name":"Dacuoliao",
    "gn:population":0,
    "gn:timezone":"Asia/Shanghai",
    "iso:country":"CN",
    "name:zho_x_preferred":[
        "\u5927\u539d\u5bee"
    ],
    "wof:name":"Dacuoliao",
    "wof:placetype":"locality"
},
  "geometry": {"coordinates":[116.0204,22.85212000000001],"type":"Point"}
}