{
  "type": "Feature",
  "properties": {
    "gn:admin1_code":"26.0",
    "gn:asciiname":"Xuetianchi",
    "gn:country_code":"CN",
    "gn:dem":1527,
    "gn:feature_class":"P",
    "gn:feature_code":"PPL",
    "gn:name":"Xuetianchi",
    "gn:population":0,
    "gn:timezone":"Asia/Shanghai",
    "iso:country":"CN",
    "name:zho_x_preferred":[
        "\u859b\u5929\u6c60"
    ],
    "wof:name":"Xuetianchi",
    "wof:placetype":"locality"
},
  "geometry": {"coordinates":[108.06207000000001,37.15581],"type":"Point"}
}