{
  "type": "Feature",
  "properties": {
    "gn:admin1_code":"26.0",
    "gn:asciiname":"Lamasi",
    "gn:country_code":"CN",
    "gn:dem":1145,
    "gn:feature_class":"P",
    "gn:feature_code":"PPL",
    "gn:name":"Lamasi",
    "gn:population":0,
    "gn:timezone":"Asia/Shanghai",
    "iso:country":"CN",
    "name:zho_x_preferred":[
        "\u5587\u561b\u5bfa"
    ],
    "wof:name":"Lamasi",
    "wof:placetype":"locality"
},
  "geometry": {"coordinates":[110.30265,39.05164],"type":"Point"}
}