{
  "type": "Feature",
  "properties": {
    "gn:admin1_code":"16.0",
    "gn:asciiname":"La'an",
    "gn:country_code":"CN",
    "gn:dem":180,
    "gn:feature_class":"P",
    "gn:feature_code":"PPL",
    "gn:name":"La\u2019an",
    "gn:population":0,
    "gn:timezone":"Asia/Shanghai",
    "iso:country":"CN",
    "name:und_x_variant":[
        "La\u2019an"
    ],
    "name:zho_x_preferred":[
        "\u62c9\u5cb8"
    ],
    "wof:name":"La'an",
    "wof:placetype":"locality"
},
  "geometry": {"coordinates":[108.446,24.8206],"type":"Point"}
}