{
  "type": "Feature",
  "properties": {
    "gn:admin1_code":"02",
    "gn:asciiname":"Lingxuecun",
    "gn:country_code":"CN",
    "gn:dem":483,
    "gn:feature_class":"P",
    "gn:feature_code":"PPL",
    "gn:name":"Lingxuecun",
    "gn:population":0,
    "gn:timezone":"Asia/Shanghai",
    "iso:country":"CN",
    "name:und_x_variant":[
        "Leng-shui",
        "Lingxue",
        "Lingxuecun"
    ],
    "name:zho_x_preferred":[
        "\u5cad\u96ea"
    ],
    "name:zho_x_variant":[
        "\u5cad\u96ea\u6751"
    ],
    "wof:name":"Lingxuecun",
    "wof:placetype":"locality"
},
  "geometry": {"coordinates":[120.41070999999999,28.07092],"type":"Point"}
}