{
  "type": "Feature",
  "properties": {
    "gn:admin1_code":"8.0",
    "gn:asciiname":"Laolinjiatun",
    "gn:country_code":"CN",
    "gn:dem":150,
    "gn:feature_class":"P",
    "gn:feature_code":"PPL",
    "gn:name":"Laolinjiatun",
    "gn:population":0,
    "gn:timezone":"Asia/Shanghai",
    "iso:country":"CN",
    "name:zho_x_preferred":[
        "\u8001\u6797\u5bb6\u5c6f"
    ],
    "wof:name":"Laolinjiatun",
    "wof:placetype":"locality"
},
  "geometry": {"coordinates":[125.23502000000001,46.17567],"type":"Point"}
}