{
  "type": "Feature",
  "properties": {
    "gn:admin1_code":"1.0",
    "gn:asciiname":"Chengyingcun",
    "gn:country_code":"CN",
    "gn:dem":29,
    "gn:feature_class":"P",
    "gn:feature_code":"PPL",
    "gn:name":"Chengyingcun",
    "gn:population":0,
    "gn:timezone":"Asia/Shanghai",
    "iso:country":"CN",
    "name:zho_x_preferred":[
        "\u6f84\u82f1\u6751"
    ],
    "wof:name":"Chengyingcun",
    "wof:placetype":"locality"
},
  "geometry": {"coordinates":[117.53798999999999,30.88363],"type":"Point"}
}