{
  "type": "Feature",
  "properties": {
    "gn:admin1_code":"29.0",
    "gn:asciiname":"Shanwei",
    "gn:country_code":"CN",
    "gn:dem":1573,
    "gn:feature_class":"P",
    "gn:feature_code":"PPL",
    "gn:name":"Shanwei",
    "gn:population":0,
    "gn:timezone":"Asia/Shanghai",
    "iso:country":"CN",
    "name:ara_x_preferred":[
        "\u0634\u0627\u0646\u0648\u064a"
    ],
    "name:cdo_x_preferred":[
        "S\u00e1ng-mu\u014di"
    ],
    "name:ces_x_preferred":[
        "\u0160an-wej"
    ],
    "name:cym_x_preferred":[
        "Shanwei"
    ],
    "name:dan_x_preferred":[
        "Shanwei"
    ],
    "name:deu_x_preferred":[
        "Shanwei"
    ],
    "name:eus_x_preferred":[
        "Shanwei"
    ],
    "name:fas_x_preferred":[
        "\u0634\u0627\u0646\u0648\u06cc"
    ],
    "name:fin_x_preferred":[
        "Shanwei"
    ],
    "name:fra_x_preferred":[
        "Shanwei"
    ],
    "name:hak_x_preferred":[
        "S\u00e2n-m\u00ee-s\u1e73"
    ],
    "name:ind_x_preferred":[
        "Shanwei"
    ],
    "name:ita_x_preferred":[
        "Shanwei"
    ],
    "name:jpn_x_preferred":[
        "\u6c55\u5c3e\u5e02"
    ],
    "name:kik_x_preferred":[
        "Shanwei"
    ],
    "name:kor_x_preferred":[
        "\uc0b0\uc6e8\uc774\uc2dc"
    ],
    "name:mlg_x_preferred":[
        "Shanwei"
    ],
    "name:nld_x_preferred":[
        "Shanwei"
    ],
    "name:nno_x_preferred":[
        "Shanwei"
    ],
    "name:nor_x_preferred":[
        "Shanwei"
    ],
    "name:pam_x_preferred":[
        "Shanwei"
    ],
    "name:pnb_x_preferred":[
        "\u0634\u0627\u0646\u0648\u06cc\u0626\u06cc"
    ],
    "name:pol_x_preferred":[
        "Shanwei"
    ],
    "name:por_x_preferred":[
        "Shanwei"
    ],
    "name:rus_x_preferred":[
        "\u0428\u0430\u043d\u044c\u0432\u044d\u0439"
    ],
    "name:spa_x_preferred":[
        "Shanw\u00e9i"
    ],
    "name:swa_x_preferred":[
        "Shanwei"
    ],
    "name:swe_x_preferred":[
        "Shanwei"
    ],
    "name:tur_x_preferred":[
        "Shanwei"
    ],
    "name:urd_x_preferred":[
        "\u0634\u0627\u0646\u0648\u0626\u06cc"
    ],
    "name:vie_x_preferred":[
        "S\u00e1n V\u0129"
    ],
    "name:war_x_preferred":[
        "Shanwei"
    ],
    "name:zho_x_preferred":[
        "\u5c71\u5c3e"
    ],
    "name:zho_x_variant":[
        "\u6c55\u5c3e\u5e02"
    ],
    "wof:name":"Shanwei",
    "wof:placetype":"locality"
},
  "geometry": {"coordinates":[100.80200000000001,25.0669],"type":"Point"}
}