{
  "type": "Feature",
  "properties": {
    "gn:admin1_code":"15.0",
    "gn:asciiname":"Chaoyang Jiudui",
    "gn:country_code":"CN",
    "gn:dem":1402,
    "gn:feature_class":"P",
    "gn:feature_code":"PPLF",
    "gn:name":"Chaoyang Jiudui",
    "gn:population":0,
    "gn:timezone":"Asia/Urumqi",
    "iso:country":"CN",
    "name:zho_x_preferred":[
        "\u671d\u9633\u4e5d\u961f"
    ],
    "wof:name":"Chaoyang Jiudui",
    "wof:placetype":"locality"
},
  "geometry": {"coordinates":[96.883,40.4985],"type":"Point"}
}