{
  "type": "Feature",
  "properties": {
    "gn:admin1_code":"9.0",
    "gn:asciiname":"Hongxingzhuang",
    "gn:country_code":"CN",
    "gn:dem":99,
    "gn:feature_class":"P",
    "gn:feature_code":"PPL",
    "gn:name":"Hongxingzhuang",
    "gn:population":0,
    "gn:timezone":"Asia/Shanghai",
    "iso:country":"CN",
    "name:zho_x_preferred":[
        "\u7ea2\u661f\u5e84"
    ],
    "wof:name":"Hongxingzhuang",
    "wof:placetype":"locality"
},
  "geometry": {"coordinates":[112.74272000000001,32.59776],"type":"Point"}
}