{
  "type": "Feature",
  "properties": {
    "gn:admin1_code":"15.0",
    "gn:asciiname":"Manwan",
    "gn:country_code":"CN",
    "gn:dem":1815,
    "gn:feature_class":"P",
    "gn:feature_code":"PPL",
    "gn:name":"Manwan",
    "gn:population":0,
    "gn:timezone":"Asia/Shanghai",
    "iso:country":"CN",
    "name:deu_x_preferred":[
        "Manwan"
    ],
    "name:zho_x_preferred":[
        "\u6f2b\u6e7e"
    ],
    "wof:name":"Manwan",
    "wof:placetype":"locality"
},
  "geometry": {"coordinates":[104.96899999999999,35.6778],"type":"Point"}
}