{
  "type": "Feature",
  "properties": {
    "gn:admin1_code":"32.0",
    "gn:asciiname":"Wawaying",
    "gn:country_code":"CN",
    "gn:dem":779,
    "gn:feature_class":"P",
    "gn:feature_code":"PPL",
    "gn:name":"Wawaying",
    "gn:population":0,
    "gn:timezone":"Asia/Shanghai",
    "iso:country":"CN",
    "name:zho_x_preferred":[
        "\u5a03\u5a03\u8425"
    ],
    "wof:name":"Wawaying",
    "wof:placetype":"locality"
},
  "geometry": {"coordinates":[102.667,29.3263],"type":"Point"}
}