{
  "type": "Feature",
  "properties": {
    "gn:admin1_code":"11.0",
    "gn:asciiname":"Puzhutian",
    "gn:country_code":"CN",
    "gn:dem":443,
    "gn:feature_class":"P",
    "gn:feature_code":"PPL",
    "gn:name":"Puzhutian",
    "gn:population":0,
    "gn:timezone":"Asia/Shanghai",
    "iso:country":"CN",
    "name:zho_x_preferred":[
        "\u84b2\u7af9\u7530"
    ],
    "wof:name":"Puzhutian",
    "wof:placetype":"locality"
},
  "geometry": {"coordinates":[110.57615,27.67863],"type":"Point"}
}