{
  "type": "Feature",
  "properties": {
    "gn:admin1_code":"4.0",
    "gn:asciiname":"Baozhuang",
    "gn:country_code":"CN",
    "gn:dem":12,
    "gn:feature_class":"P",
    "gn:feature_code":"PPL",
    "gn:name":"Baozhuang",
    "gn:population":0,
    "gn:timezone":"Asia/Shanghai",
    "iso:country":"CN",
    "name:zho_x_preferred":[
        "\u5305\u5e84"
    ],
    "wof:name":"Baozhuang",
    "wof:placetype":"locality"
},
  "geometry": {"coordinates":[118.875,33.7364],"type":"Point"}
}