{
  "type": "Feature",
  "properties": {
    "gn:admin1_code":"1.0",
    "gn:asciiname":"Yangmaohucun",
    "gn:country_code":"CN",
    "gn:dem":28,
    "gn:feature_class":"P",
    "gn:feature_code":"PPL",
    "gn:name":"Yangmaohucun",
    "gn:population":0,
    "gn:timezone":"Asia/Shanghai",
    "iso:country":"CN",
    "name:zho_x_preferred":[
        "\u6768\u8306\u6e56\u6751"
    ],
    "wof:name":"Yangmaohucun",
    "wof:placetype":"locality"
},
  "geometry": {"coordinates":[117.11776,33.70106],"type":"Point"}
}