{
  "type": "Feature",
  "properties": {
    "gn:admin1_code":"24.0",
    "gn:asciiname":"Shixianggou",
    "gn:country_code":"CN",
    "gn:dem":1379,
    "gn:feature_class":"P",
    "gn:feature_code":"PPL",
    "gn:name":"Shixianggou",
    "gn:population":0,
    "gn:timezone":"Asia/Shanghai",
    "iso:country":"CN",
    "name:zho_x_preferred":[
        "\u77f3\u76f8\u6c9f"
    ],
    "wof:name":"Shixianggou",
    "wof:placetype":"locality"
},
  "geometry": {"coordinates":[111.86839000000001,37.86343],"type":"Point"}
}