{
  "type": "Feature",
  "properties": {
    "gn:admin1_code":"5.0",
    "gn:asciiname":"Xidaqihaocun",
    "gn:country_code":"CN",
    "gn:dem":219,
    "gn:feature_class":"P",
    "gn:feature_code":"PPL",
    "gn:name":"Xidaqihaocun",
    "gn:population":0,
    "gn:timezone":"Asia/Shanghai",
    "iso:country":"CN",
    "name:zho_x_preferred":[
        "\u897f\u5927\u4e03\u53f7\u6751"
    ],
    "wof:name":"Xidaqihaocun",
    "wof:placetype":"locality"
},
  "geometry": {"coordinates":[125.92773,45.00888],"type":"Point"}
}