{
  "type": "Feature",
  "properties": {
    "gn:admin1_code":"5.0",
    "gn:asciiname":"Nanshancun",
    "gn:country_code":"CN",
    "gn:dem":65,
    "gn:feature_class":"P",
    "gn:feature_code":"PPL",
    "gn:name":"Nanshancun",
    "gn:population":0,
    "gn:timezone":"Asia/Shanghai",
    "iso:country":"CN",
    "name:zho_x_preferred":[
        "\u5357\u5c71\u6751"
    ],
    "wof:name":"Nanshancun",
    "wof:placetype":"locality"
},
  "geometry": {"coordinates":[130.44969,42.84686],"type":"Point"}
}