{
  "type": "Feature",
  "properties": {
    "gn:admin1_code":"5.0",
    "gn:asciiname":"Daliu Jiazi",
    "gn:country_code":"CN",
    "gn:dem":130,
    "gn:feature_class":"P",
    "gn:feature_code":"PPL",
    "gn:name":"Daliu Jiazi",
    "gn:population":0,
    "gn:timezone":"Asia/Shanghai",
    "iso:country":"CN",
    "name:zho_x_preferred":[
        "\u5927\u516d\u5bb6\u5b50"
    ],
    "wof:name":"Daliu Jiazi",
    "wof:placetype":"locality"
},
  "geometry": {"coordinates":[123.96462,45.4603],"type":"Point"}
}