{
  "type": "Feature",
  "properties": {
    "gn:admin1_code":"18",
    "gn:asciiname":"Gaopodong",
    "gn:country_code":"CN",
    "gn:dem":1336,
    "gn:feature_class":"P",
    "gn:feature_code":"PPL",
    "gn:name":"Gaopodong",
    "gn:population":0,
    "gn:timezone":"Asia/Shanghai",
    "iso:country":"CN",
    "name:zho_x_preferred":[
        "\u9ad8\u5761\u6d1e"
    ],
    "wof:name":"Gaopodong",
    "wof:placetype":"locality"
},
  "geometry": {"coordinates":[106.599,26.8919],"type":"Point"}
}