{
  "type": "Feature",
  "properties": {
    "gn:admin1_code":"31",
    "gn:asciiname":"Meiting",
    "gn:country_code":"CN",
    "gn:dem":59,
    "gn:feature_class":"P",
    "gn:feature_code":"PPL",
    "gn:name":"Meiting",
    "gn:population":0,
    "gn:timezone":"Asia/Shanghai",
    "iso:country":"CN",
    "name:und_x_variant":[
        "Mei-t\u2019ing-shih",
        "Meiting",
        "\u7f8e\u4ead"
    ],
    "wof:name":"Meiting",
    "wof:placetype":"locality"
},
  "geometry": {"coordinates":[110.07899999999999,19.8312],"type":"Point"}
}