{
  "type": "Feature",
  "properties": {
    "gn:admin1_code":"4.0",
    "gn:asciiname":"Wangjianglou Xincun",
    "gn:country_code":"CN",
    "gn:dem":7,
    "gn:feature_class":"P",
    "gn:feature_code":"PPL",
    "gn:name":"Wangjianglou Xincun",
    "gn:population":0,
    "gn:timezone":"Asia/Shanghai",
    "iso:country":"CN",
    "name:zho_x_preferred":[
        "\u671b\u6c5f\u697c\u65b0\u6751"
    ],
    "wof:name":"Wangjianglou Xincun",
    "wof:placetype":"locality"
},
  "geometry": {"coordinates":[120.87166999999999,32.02022],"type":"Point"}
}