{
  "type": "Feature",
  "properties": {
    "gn:admin1_code":"30.0",
    "gn:asciiname":"Jiangbeiwei",
    "gn:country_code":"CN",
    "gn:dem":17,
    "gn:feature_class":"P",
    "gn:feature_code":"PPL",
    "gn:name":"Jiangbeiwei",
    "gn:population":0,
    "gn:timezone":"Asia/Shanghai",
    "iso:country":"CN",
    "name:zho_x_preferred":[
        "\u6c5f\u8d1d\u5c3e"
    ],
    "wof:name":"Jiangbeiwei",
    "wof:placetype":"locality"
},
  "geometry": {"coordinates":[112.5287,23.42592],"type":"Point"}
}