{
  "type": "Feature",
  "properties": {
    "gn:admin1_code":"5.0",
    "gn:asciiname":"Ximengnangou",
    "gn:country_code":"CN",
    "gn:dem":255,
    "gn:feature_class":"P",
    "gn:feature_code":"PPL",
    "gn:name":"Ximengnangou",
    "gn:population":0,
    "gn:timezone":"Asia/Shanghai",
    "iso:country":"CN",
    "name:zho_x_preferred":[
        "\u897f\u5b5f\u5357\u6c9f"
    ],
    "wof:name":"Ximengnangou",
    "wof:placetype":"locality"
},
  "geometry": {"coordinates":[125.06249,42.92933],"type":"Point"}
}