{
  "type": "Feature",
  "properties": {
    "gn:admin1_code":"7.0",
    "gn:asciiname":"Guxiancun",
    "gn:country_code":"CN",
    "gn:dem":110,
    "gn:feature_class":"P",
    "gn:feature_code":"PPL",
    "gn:name":"Guxiancun",
    "gn:population":0,
    "gn:timezone":"Asia/Shanghai",
    "iso:country":"CN",
    "name:und_x_variant":[
        "\u53e4\u53bf\u6751"
    ],
    "name:zho_x_preferred":[
        "\u53e4\u53bf\u6751"
    ],
    "wof:name":"Guxiancun",
    "wof:placetype":"locality"
},
  "geometry": {"coordinates":[117.82669,26.3884],"type":"Point"}
}