{
  "type": "Feature",
  "properties": {
    "gn:admin1_code":"2.0",
    "gn:asciiname":"Chunjing",
    "gn:country_code":"CN",
    "gn:dem":12,
    "gn:feature_class":"P",
    "gn:feature_code":"PPLA4",
    "gn:name":"Chunjing",
    "gn:population":0,
    "gn:timezone":"Asia/Shanghai",
    "iso:country":"CN",
    "name:und_x_variant":[
        "\u6625\u6c5f"
    ],
    "name:zho_x_preferred":[
        "Chunjiang Jiedao"
    ],
    "name:zho_x_variant":[
        "\u6625\u6c5f\u8857\u9053"
    ],
    "wof:name":"Chunjing",
    "wof:placetype":"locality"
},
  "geometry": {"coordinates":[119.96405,30.03328],"type":"Point"}
}