{
  "type": "Feature",
  "properties": {
    "gn:admin1_code":"14.0",
    "gn:asciiname":"Dacainiba",
    "gn:country_code":"CN",
    "gn:dem":4215,
    "gn:feature_class":"P",
    "gn:feature_code":"PPL",
    "gn:name":"Dacainiba",
    "gn:population":0,
    "gn:timezone":"Asia/Urumqi",
    "iso:country":"CN",
    "name:zho_x_preferred":[
        "\u6253\u624d\u5c3c\u575d"
    ],
    "wof:name":"Dacainiba",
    "wof:placetype":"locality"
},
  "geometry": {"coordinates":[94.55444,29.85959],"type":"Point"}
}