{
  "type": "Feature",
  "properties": {
    "gn:admin1_code":"18",
    "gn:asciiname":"Dachuba",
    "gn:country_code":"CN",
    "gn:dem":1081,
    "gn:feature_class":"P",
    "gn:feature_code":"PPL",
    "gn:name":"Dachuba",
    "gn:population":0,
    "gn:timezone":"Asia/Shanghai",
    "iso:country":"CN",
    "name:zho_x_preferred":[
        "\u6253\u9504\u575d"
    ],
    "wof:name":"Dachuba",
    "wof:placetype":"locality"
},
  "geometry": {"coordinates":[106.375,25.7853],"type":"Point"}
}