{
  "type": "Feature",
  "properties": {
    "gn:admin1_code":"29.0",
    "gn:asciiname":"Diziluo",
    "gn:country_code":"CN",
    "gn:dem":1752,
    "gn:feature_class":"P",
    "gn:feature_code":"PPL",
    "gn:name":"Diziluo",
    "gn:population":0,
    "gn:timezone":"Asia/Shanghai",
    "iso:country":"CN",
    "name:zho_x_preferred":[
        "\u8fea\u5b50\u6d1b"
    ],
    "wof:name":"Diziluo",
    "wof:placetype":"locality"
},
  "geometry": {"coordinates":[99.0347,27.5487],"type":"Point"}
}