{
  "type": "Feature",
  "properties": {
    "gn:admin1_code":"24.0",
    "gn:asciiname":"Zhangzuan",
    "gn:country_code":"CN",
    "gn:dem":572,
    "gn:feature_class":"P",
    "gn:feature_code":"PPL",
    "gn:name":"Zhangzuan",
    "gn:population":0,
    "gn:timezone":"Asia/Shanghai",
    "iso:country":"CN",
    "name:und_x_variant":[
        "\u5f20\u7e82"
    ],
    "name:zho_x_preferred":[
        "\u5f20\u7e82"
    ],
    "wof:name":"Zhangzuan",
    "wof:placetype":"locality"
},
  "geometry": {"coordinates":[111.54237999999999,35.89698],"type":"Point"}
}