{
  "type": "Feature",
  "properties": {
    "gn:admin1_code":"32.0",
    "gn:asciiname":"Tongziling",
    "gn:country_code":"CN",
    "gn:dem":490,
    "gn:feature_class":"P",
    "gn:feature_code":"PPL",
    "gn:name":"Tongziling",
    "gn:population":0,
    "gn:timezone":"Asia/Shanghai",
    "iso:country":"CN",
    "name:zho_x_preferred":[
        "\u6850\u5b50\u5cad"
    ],
    "wof:name":"Tongziling",
    "wof:placetype":"locality"
},
  "geometry": {"coordinates":[104.40131,28.89987],"type":"Point"}
}