{
  "type": "Feature",
  "properties": {
    "gn:admin1_code":"26.0",
    "gn:asciiname":"Hongyawan",
    "gn:country_code":"CN",
    "gn:dem":1125,
    "gn:feature_class":"P",
    "gn:feature_code":"PPL",
    "gn:name":"Hongyawan",
    "gn:population":0,
    "gn:timezone":"Asia/Shanghai",
    "iso:country":"CN",
    "name:zho_x_preferred":[
        "\u7ea2\u5d16\u6e7e"
    ],
    "wof:name":"Hongyawan",
    "wof:placetype":"locality"
},
  "geometry": {"coordinates":[109.91161,37.3141],"type":"Point"}
}