{
  "type": "Feature",
  "properties": {
    "gn:admin1_code":"11",
    "gn:asciiname":"Xiliwei",
    "gn:country_code":"CN",
    "gn:dem":397,
    "gn:feature_class":"P",
    "gn:feature_code":"PPL",
    "gn:name":"Xiliwei",
    "gn:population":0,
    "gn:timezone":"Asia/Shanghai",
    "iso:country":"CN",
    "name:zho_x_preferred":[
        "\u897f\u680e\u5c3e"
    ],
    "wof:name":"Xiliwei",
    "wof:placetype":"locality"
},
  "geometry": {"coordinates":[111.43409,25.06911],"type":"Point"}
}