{
  "type": "Feature",
  "properties": {
    "gn:admin1_code":"4.0",
    "gn:asciiname":"Lianzhuangcun",
    "gn:country_code":"CN",
    "gn:dem":7,
    "gn:feature_class":"P",
    "gn:feature_code":"PPL",
    "gn:name":"Lianzhuangcun",
    "gn:population":0,
    "gn:timezone":"Asia/Shanghai",
    "iso:country":"CN",
    "name:zho_x_preferred":[
        "\u7ec3\u5e84\u6751"
    ],
    "wof:name":"Lianzhuangcun",
    "wof:placetype":"locality"
},
  "geometry": {"coordinates":[119.26428,31.4895],"type":"Point"}
}