{
  "type": "Feature",
  "properties": {
    "gn:admin1_code":"16.0",
    "gn:asciiname":"Xinlong",
    "gn:country_code":"CN",
    "gn:dem":354,
    "gn:feature_class":"P",
    "gn:feature_code":"PPL",
    "gn:name":"Xinlong",
    "gn:population":0,
    "gn:timezone":"Asia/Shanghai",
    "iso:country":"CN",
    "name:zho_x_preferred":[
        "\u65b0\u9686"
    ],
    "wof:name":"Xinlong",
    "wof:placetype":"locality"
},
  "geometry": {"coordinates":[108.73099999999999,23.9825],"type":"Point"}
}