{
  "type": "Feature",
  "properties": {
    "gn:admin1_code":"3.0",
    "gn:asciiname":"Xintianfang",
    "gn:country_code":"CN",
    "gn:dem":139,
    "gn:feature_class":"P",
    "gn:feature_code":"PPL",
    "gn:name":"Xintianfang",
    "gn:population":0,
    "gn:timezone":"Asia/Shanghai",
    "iso:country":"CN",
    "name:und_x_variant":[
        "\u65b0\u7530\u574a"
    ],
    "wof:name":"Xintianfang",
    "wof:placetype":"locality"
},
  "geometry": {"coordinates":[115.65613999999999,26.06149],"type":"Point"}
}