{
  "type": "Feature",
  "properties": {
    "gn:admin1_code":"15.0",
    "gn:asciiname":"Sanpianzui",
    "gn:country_code":"CN",
    "gn:dem":1994,
    "gn:feature_class":"P",
    "gn:feature_code":"PPL",
    "gn:name":"Sanpianzui",
    "gn:population":0,
    "gn:timezone":"Asia/Shanghai",
    "iso:country":"CN",
    "name:zho_x_preferred":[
        "\u4e09\u7247\u5634"
    ],
    "wof:name":"Sanpianzui",
    "wof:placetype":"locality"
},
  "geometry": {"coordinates":[104.446,35.6433],"type":"Point"}
}