{
  "type": "Feature",
  "properties": {
    "gn:admin1_code":"19.0",
    "gn:asciiname":"Shanzui",
    "gn:country_code":"CN",
    "gn:dem":156,
    "gn:feature_class":"P",
    "gn:feature_code":"PPL",
    "gn:name":"Shanzui",
    "gn:population":0,
    "gn:timezone":"Asia/Shanghai",
    "iso:country":"CN",
    "name:und_x_variant":[
        "\u5c71\u5480"
    ],
    "name:zho_x_preferred":[
        "\u5c71\u5480"
    ],
    "wof:name":"Shanzui",
    "wof:placetype":"locality"
},
  "geometry": {"coordinates":[122.28452,39.8811],"type":"Point"}
}