{
  "type": "Feature",
  "properties": {
    "gn:admin1_code":"29",
    "gn:asciiname":"Shangbaiyiguan",
    "gn:country_code":"CN",
    "gn:dem":1900,
    "gn:feature_class":"P",
    "gn:feature_code":"PPL",
    "gn:name":"Shangbaiyiguan",
    "gn:population":0,
    "gn:timezone":"Asia/Shanghai",
    "iso:country":"CN",
    "name:zho_x_preferred":[
        "\u4e0a\u767d\u9091\u5173"
    ],
    "wof:name":"Shangbaiyiguan",
    "wof:placetype":"locality"
},
  "geometry": {"coordinates":[102.12,24.7867],"type":"Point"}
}