{
  "type": "Feature",
  "properties": {
    "gn:admin1_code":"3",
    "gn:asciiname":"Qianwuzai",
    "gn:country_code":"CN",
    "gn:dem":164,
    "gn:feature_class":"P",
    "gn:feature_code":"PPL",
    "gn:name":"Qianwuzai",
    "gn:population":0,
    "gn:timezone":"Asia/Shanghai",
    "iso:country":"CN",
    "name:zho_x_preferred":[
        "\u94b1\u5c4b\u4ed4"
    ],
    "wof:name":"Qianwuzai",
    "wof:placetype":"locality"
},
  "geometry": {"coordinates":[114.84699999999999,25.4349],"type":"Point"}
}