{
  "type": "Feature",
  "properties": {
    "gn:admin1_code":"11",
    "gn:asciiname":"Bantang",
    "gn:cc2":"CN",
    "gn:country_code":"CN",
    "gn:dem":65,
    "gn:feature_class":"P",
    "gn:feature_code":"PPL",
    "gn:name":"Bantang",
    "gn:population":0,
    "gn:timezone":"Asia/Shanghai",
    "iso:country":"CN",
    "name:und_x_variant":[
        "Pan-t\u2019ang-p\u2019u",
        "Bantangpu",
        "Bantang"
    ],
    "wof:name":"Bantang",
    "wof:placetype":"locality"
},
  "geometry": {"coordinates":[112.96666999999999,27.86667000000001],"type":"Point"}
}