{
  "type": "Feature",
  "properties": {
    "gn:admin1_code":"25.0",
    "gn:asciiname":"Dasunjiacun",
    "gn:country_code":"CN",
    "gn:dem":11,
    "gn:feature_class":"P",
    "gn:feature_code":"PPL",
    "gn:name":"Dasunjiacun",
    "gn:population":0,
    "gn:timezone":"Asia/Shanghai",
    "iso:country":"CN",
    "name:zho_x_preferred":[
        "\u5927\u5b59\u5bb6\u6751"
    ],
    "wof:name":"Dasunjiacun",
    "wof:placetype":"locality"
},
  "geometry": {"coordinates":[119.71532999999999,36.58381],"type":"Point"}
}