{
  "type": "Feature",
  "properties": {
    "gn:admin1_code":"16.0",
    "gn:asciiname":"Niancun",
    "gn:country_code":"CN",
    "gn:dem":243,
    "gn:feature_class":"P",
    "gn:feature_code":"PPL",
    "gn:name":"Niancun",
    "gn:population":0,
    "gn:timezone":"Asia/Shanghai",
    "iso:country":"CN",
    "name:zho_x_preferred":[
        "\u5ff5\u6751"
    ],
    "wof:name":"Niancun",
    "wof:placetype":"locality"
},
  "geometry": {"coordinates":[110.218,24.3872],"type":"Point"}
}