{
  "type": "Feature",
  "properties": {
    "gn:admin1_code":"16",
    "gn:asciiname":"Guangyuan",
    "gn:country_code":"CN",
    "gn:dem":194,
    "gn:feature_class":"P",
    "gn:feature_code":"PPL",
    "gn:name":"Guangyuan",
    "gn:population":0,
    "gn:timezone":"Asia/Shanghai",
    "iso:country":"CN",
    "name:ara_x_preferred":[
        "\u063a\u0648\u0627\u0646\u063a\u064a\u0648\u0627\u0646"
    ],
    "name:cdo_x_preferred":[
        "Gu\u014dng-ngu\u00f2ng"
    ],
    "name:ceb_x_preferred":[
        "Guangyuan"
    ],
    "name:ces_x_preferred":[
        "Kuang-j\u00fcan"
    ],
    "name:dan_x_preferred":[
        "Guangyuan"
    ],
    "name:deu_x_preferred":[
        "Guangyuan"
    ],
    "name:eus_x_preferred":[
        "Guangyuan"
    ],
    "name:fas_x_preferred":[
        "\u06af\u0648\u0627\u0646\u06af\u06cc\u0648\u0627\u0646"
    ],
    "name:fin_x_preferred":[
        "Guangyuan"
    ],
    "name:fra_x_preferred":[
        "Guangyuan"
    ],
    "name:ita_x_preferred":[
        "Guangyuan"
    ],
    "name:jpn_x_preferred":[
        "\u5e83\u5143\u5e02"
    ],
    "name:kaz_x_preferred":[
        "\u0413\u0443\u0430\u043d\u044a\u044e\u0430\u043d\u044c"
    ],
    "name:kik_x_preferred":[
        "Guangyuan"
    ],
    "name:kor_x_preferred":[
        "\uad11\uc704\uc548\uc2dc"
    ],
    "name:mlg_x_preferred":[
        "Guangyuan"
    ],
    "name:nld_x_preferred":[
        "Guangyuan"
    ],
    "name:nno_x_preferred":[
        "Guangyuan"
    ],
    "name:nor_x_preferred":[
        "Guangyuan"
    ],
    "name:pol_x_preferred":[
        "Guangyuan"
    ],
    "name:rus_x_preferred":[
        "\u0413\u0443\u0430\u043d\u044a\u044e\u0430\u043d\u044c"
    ],
    "name:spa_x_preferred":[
        "Guangyuan"
    ],
    "name:sqi_x_preferred":[
        "Guangjuan"
    ],
    "name:srp_x_preferred":[
        "\u0413\u0443\u0430\u043d\u0433\u0458\u0443\u0435\u043d"
    ],
    "name:swe_x_preferred":[
        "Guangyuan"
    ],
    "name:tur_x_preferred":[
        "Guangyuan"
    ],
    "name:urd_x_preferred":[
        "\u06af\u0648\u0627\u0646\u06af\u06cc\u0648\u0627\u0646"
    ],
    "name:vie_x_preferred":[
        "Qu\u1ea3ng Nguy\u00ean"
    ],
    "name:war_x_preferred":[
        "Guangyuan"
    ],
    "name:wuu_x_preferred":[
        "\u5e7f\u5143\u5e02"
    ],
    "name:zho_x_preferred":[
        "\u5e7f\u5143"
    ],
    "name:zho_x_variant":[
        "\u5e7f\u5143\u5e02"
    ],
    "wof:name":"Guangyuan",
    "wof:placetype":"locality"
},
  "geometry": {"coordinates":[108.008,22.1753],"type":"Point"}
}