{
  "type": "Feature",
  "properties": {
    "gn:admin1_code":"32.0",
    "gn:asciiname":"Jipagou",
    "gn:country_code":"CN",
    "gn:dem":2953,
    "gn:feature_class":"P",
    "gn:feature_code":"PPL",
    "gn:name":"Jipagou",
    "gn:population":0,
    "gn:timezone":"Asia/Shanghai",
    "iso:country":"CN",
    "name:zho_x_preferred":[
        "\u9e21\u722c\u6c9f"
    ],
    "wof:name":"Jipagou",
    "wof:placetype":"locality"
},
  "geometry": {"coordinates":[101.298,27.4883],"type":"Point"}
}