{
  "type": "Feature",
  "properties": {
    "gn:admin1_code":"14.0",
    "gn:asciiname":"Duorongka",
    "gn:country_code":"CN",
    "gn:dem":4242,
    "gn:feature_class":"P",
    "gn:feature_code":"PPL",
    "gn:name":"Duorongka",
    "gn:population":0,
    "gn:timezone":"Asia/Urumqi",
    "iso:country":"CN",
    "name:zho_x_preferred":[
        "\u591a\u7ed2\u5361"
    ],
    "wof:name":"Duorongka",
    "wof:placetype":"locality"
},
  "geometry": {"coordinates":[94.55761,31.57343],"type":"Point"}
}