{
  "type": "Feature",
  "properties": {
    "gn:admin1_code":"12.0",
    "gn:asciiname":"Haohu Dadui",
    "gn:country_code":"CN",
    "gn:dem":21,
    "gn:feature_class":"P",
    "gn:feature_code":"PPLF",
    "gn:name":"Haohu Dadui",
    "gn:population":0,
    "gn:timezone":"Asia/Shanghai",
    "iso:country":"CN",
    "name:und_x_variant":[
        "\u84bf\u6e56\u5927\u961f"
    ],
    "wof:name":"Haohu Dadui",
    "wof:placetype":"locality"
},
  "geometry": {"coordinates":[114.02573999999998,30.69799],"type":"Point"}
}