{
  "type": "Feature",
  "properties": {
    "gn:admin1_code":"03",
    "gn:asciiname":"Fengyang",
    "gn:country_code":"CN",
    "gn:dem":96,
    "gn:feature_class":"P",
    "gn:feature_code":"PPLA4",
    "gn:name":"Fengyang",
    "gn:population":0,
    "gn:timezone":"Asia/Shanghai",
    "iso:country":"CN",
    "name:und_x_variant":[
        "\u51e4\u9633",
        "Fengyang Xiang",
        "\u51e4\u9633\u4e61"
    ],
    "wof:name":"Fengyang",
    "wof:placetype":"locality"
},
  "geometry": {"coordinates":[114.64158,27.86058],"type":"Point"}
}