{
  "type": "Feature",
  "properties": {
    "gn:admin1_code":"15.0",
    "gn:asciiname":"Huangcaochuan",
    "gn:country_code":"CN",
    "gn:dem":2802,
    "gn:feature_class":"P",
    "gn:feature_code":"PPL",
    "gn:name":"Huangcaochuan",
    "gn:population":0,
    "gn:timezone":"Asia/Shanghai",
    "iso:country":"CN",
    "name:zho_x_preferred":[
        "\u9ec4\u8349\u5ddd"
    ],
    "wof:name":"Huangcaochuan",
    "wof:placetype":"locality"
},
  "geometry": {"coordinates":[103.09099999999999,37.1083],"type":"Point"}
}