{
  "type": "Feature",
  "properties": {
    "gn:admin1_code":"25",
    "gn:asciiname":"Beixiaoshui",
    "gn:country_code":"CN",
    "gn:dem":266,
    "gn:feature_class":"P",
    "gn:feature_code":"PPL",
    "gn:name":"Beixiaoshui",
    "gn:population":0,
    "gn:timezone":"Asia/Shanghai",
    "iso:country":"CN",
    "name:zho_x_preferred":[
        "\u5317\u5c0f\u6c34"
    ],
    "wof:name":"Beixiaoshui",
    "wof:placetype":"locality"
},
  "geometry": {"coordinates":[118.267,36.1578],"type":"Point"}
}