{
  "type": "Feature",
  "properties": {
    "gn:admin1_code":"4.0",
    "gn:asciiname":"Jumindian",
    "gn:country_code":"CN",
    "gn:dem":6,
    "gn:feature_class":"P",
    "gn:feature_code":"PPL",
    "gn:name":"Jumindian",
    "gn:population":0,
    "gn:timezone":"Asia/Shanghai",
    "iso:country":"CN",
    "name:und_x_variant":[
        "\u5c45\u6c11\u70b9"
    ],
    "wof:name":"Jumindian",
    "wof:placetype":"locality"
},
  "geometry": {"coordinates":[121.23242,31.87756],"type":"Point"}
}