{
  "type": "Feature",
  "properties": {
    "gn:admin1_code":"26",
    "gn:asciiname":"Chatian",
    "gn:country_code":"CN",
    "gn:dem":400,
    "gn:feature_class":"P",
    "gn:feature_code":"PPL",
    "gn:name":"Chatian",
    "gn:population":0,
    "gn:timezone":"Asia/Shanghai",
    "iso:country":"CN",
    "name:und_x_variant":[
        "Chatiancun"
    ],
    "name:zho_x_preferred":[
        "\u67e5\u7530"
    ],
    "wof:name":"Chatian",
    "wof:placetype":"locality"
},
  "geometry": {"coordinates":[108.62721999999999,34.33],"type":"Point"}
}