{
  "type": "Feature",
  "properties": {
    "gn:admin1_code":"5.0",
    "gn:asciiname":"Yaoliuhao",
    "gn:country_code":"CN",
    "gn:dem":174,
    "gn:feature_class":"P",
    "gn:feature_code":"PPL",
    "gn:name":"Yaoliuhao",
    "gn:population":0,
    "gn:timezone":"Asia/Shanghai",
    "iso:country":"CN",
    "name:zho_x_preferred":[
        "\u8170\u516d\u53f7"
    ],
    "wof:name":"Yaoliuhao",
    "wof:placetype":"locality"
},
  "geometry": {"coordinates":[126.56286,45.17185],"type":"Point"}
}