{
  "type": "Feature",
  "properties": {
    "gn:admin1_code":"6.0",
    "gn:asciiname":"Shigai",
    "gn:country_code":"CN",
    "gn:dem":2860,
    "gn:feature_class":"P",
    "gn:feature_code":"PPL",
    "gn:name":"Shigai",
    "gn:population":0,
    "gn:timezone":"Asia/Shanghai",
    "iso:country":"CN",
    "name:und_x_variant":[
        "\u77f3\u76d6"
    ],
    "wof:name":"Shigai",
    "wof:placetype":"locality"
},
  "geometry": {"coordinates":[102.16656999999999,35.98956],"type":"Point"}
}