{
  "type": "Feature",
  "properties": {
    "gn:admin1_code":"19.0",
    "gn:asciiname":"Xiahuangjin",
    "gn:country_code":"CN",
    "gn:dem":111,
    "gn:feature_class":"P",
    "gn:feature_code":"PPL",
    "gn:name":"Xiahuangjin",
    "gn:population":0,
    "gn:timezone":"Asia/Shanghai",
    "iso:country":"CN",
    "name:und_x_variant":[
        "\u4e0b\u9ec4\u91d1"
    ],
    "name:zho_x_preferred":[
        "\u4e0b\u9ec4\u91d1"
    ],
    "wof:name":"Xiahuangjin",
    "wof:placetype":"locality"
},
  "geometry": {"coordinates":[123.80257,41.95633],"type":"Point"}
}