{
  "type": "Feature",
  "properties": {
    "gn:admin1_code":"5.0",
    "gn:asciiname":"Beitaipingcun",
    "gn:country_code":"CN",
    "gn:dem":388,
    "gn:feature_class":"P",
    "gn:feature_code":"PPL",
    "gn:name":"Beitaipingcun",
    "gn:population":0,
    "gn:timezone":"Asia/Shanghai",
    "iso:country":"CN",
    "name:zho_x_preferred":[
        "\u5317\u592a\u5e73\u6751"
    ],
    "wof:name":"Beitaipingcun",
    "wof:placetype":"locality"
},
  "geometry": {"coordinates":[121.68689999999999,45.73869000000001],"type":"Point"}
}