{
  "type": "Feature",
  "properties": {
    "gn:admin1_code":"32",
    "gn:asciiname":"Tongtan",
    "gn:country_code":"CN",
    "gn:dem":272,
    "gn:feature_class":"P",
    "gn:feature_code":"PPL",
    "gn:name":"Tongtan",
    "gn:population":0,
    "gn:timezone":"Asia/Shanghai",
    "iso:country":"CN",
    "name:und_x_variant":[
        "T\u2019ung-t\u2019an",
        "Tongtan"
    ],
    "name:zho_x_preferred":[
        "\u901a\u6ee9"
    ],
    "wof:name":"Tongtan",
    "wof:placetype":"locality"
},
  "geometry": {"coordinates":[105.28642000000001,28.92002],"type":"Point"}
}