{
  "type": "Feature",
  "properties": {
    "gn:admin1_code":"14.0",
    "gn:asciiname":"Jinzhucun",
    "gn:country_code":"CN",
    "gn:dem":3834,
    "gn:feature_class":"P",
    "gn:feature_code":"PPL",
    "gn:name":"Jinzhucun",
    "gn:population":0,
    "gn:timezone":"Asia/Urumqi",
    "iso:country":"CN",
    "name:zho_x_preferred":[
        "\u91d1\u73e0\u6751"
    ],
    "wof:name":"Jinzhucun",
    "wof:placetype":"locality"
},
  "geometry": {"coordinates":[98.21655,31.06801],"type":"Point"}
}