{
  "type": "Feature",
  "properties": {
    "gn:admin1_code":"11",
    "gn:asciiname":"Renshiqiao",
    "gn:country_code":"CN",
    "gn:dem":66,
    "gn:feature_class":"P",
    "gn:feature_code":"PPL",
    "gn:name":"Renshiqiao",
    "gn:population":0,
    "gn:timezone":"Asia/Shanghai",
    "iso:country":"CN",
    "wof:name":"Renshiqiao",
    "wof:placetype":"locality"
},
  "geometry": {"coordinates":[112.91500000000001,28.05333],"type":"Point"}
}