{
  "type": "Feature",
  "properties": {
    "gn:admin1_code":"10.0",
    "gn:asciiname":"Lujiagou",
    "gn:country_code":"CN",
    "gn:dem":31,
    "gn:feature_class":"P",
    "gn:feature_code":"PPL",
    "gn:name":"L\u00fcjiagou",
    "gn:population":0,
    "gn:timezone":"Asia/Shanghai",
    "iso:country":"CN",
    "name:und_x_variant":[
        "L\u00fcjiagou"
    ],
    "name:zho_x_preferred":[
        "\u5415\u5bb6\u6c9f"
    ],
    "wof:name":"Lujiagou",
    "wof:placetype":"locality"
},
  "geometry": {"coordinates":[119.77321000000001,40.0166],"type":"Point"}
}