{
  "type": "Feature",
  "properties": {
    "gn:admin1_code":"3",
    "gn:asciiname":"Yangqiaodian",
    "gn:country_code":"CN",
    "gn:dem":46,
    "gn:feature_class":"P",
    "gn:feature_code":"PPLA4",
    "gn:name":"Yangqiaodian",
    "gn:population":0,
    "gn:timezone":"Asia/Shanghai",
    "iso:country":"CN",
    "name:und_x_variant":[
        "\u6768\u6865\u6bbf",
        "Yangqiaodian Zhen",
        "\u6768\u6865\u6bbf\u9547"
    ],
    "wof:name":"Yangqiaodian",
    "wof:placetype":"locality"
},
  "geometry": {"coordinates":[116.54183999999999,28.37161],"type":"Point"}
}