{
  "type": "Feature",
  "properties": {
    "gn:admin1_code":"2.0",
    "gn:asciiname":"Xiangdong Linchang",
    "gn:country_code":"CN",
    "gn:dem":910,
    "gn:feature_class":"P",
    "gn:feature_code":"PPLF",
    "gn:name":"Xiangdong Linchang",
    "gn:population":0,
    "gn:timezone":"Asia/Shanghai",
    "iso:country":"CN",
    "name:zho_x_preferred":[
        "\u5411\u4e1c\u6797\u573a"
    ],
    "wof:name":"Xiangdong Linchang",
    "wof:placetype":"locality"
},
  "geometry": {"coordinates":[119.85138999999999,28.21655],"type":"Point"}
}