{
  "type": "Feature",
  "properties": {
    "gn:admin1_code":"4.0",
    "gn:asciiname":"Tiaofeng",
    "gn:country_code":"CN",
    "gn:dem":3,
    "gn:feature_class":"P",
    "gn:feature_code":"PPL",
    "gn:name":"Tiaofeng",
    "gn:population":0,
    "gn:timezone":"Asia/Shanghai",
    "iso:country":"CN",
    "name:zho_x_preferred":[
        "Tiaofeng"
    ],
    "name:zho_x_variant":[
        "\u6761\u4e30"
    ],
    "wof:name":"Tiaofeng",
    "wof:placetype":"locality"
},
  "geometry": {"coordinates":[119.43089999999999,34.32113],"type":"Point"}
}