{
  "type": "Feature",
  "properties": {
    "gn:admin1_code":"26.0",
    "gn:asciiname":"Hualianggoucun",
    "gn:country_code":"CN",
    "gn:dem":1048,
    "gn:feature_class":"P",
    "gn:feature_code":"PPL",
    "gn:name":"Hualianggoucun",
    "gn:population":0,
    "gn:timezone":"Asia/Shanghai",
    "iso:country":"CN",
    "name:zho_x_preferred":[
        "\u534e\u826f\u6c9f\u6751"
    ],
    "wof:name":"Hualianggoucun",
    "wof:placetype":"locality"
},
  "geometry": {"coordinates":[109.86347000000001,33.69583],"type":"Point"}
}