{
  "type": "Feature",
  "properties": {
    "gn:admin1_code":"18",
    "gn:asciiname":"Xiaobaiya",
    "gn:country_code":"CN",
    "gn:dem":1720,
    "gn:feature_class":"P",
    "gn:feature_code":"PPL",
    "gn:name":"Xiaobaiya",
    "gn:population":0,
    "gn:timezone":"Asia/Shanghai",
    "iso:country":"CN",
    "name:zho_x_preferred":[
        "\u5c0f\u767d\u5d16"
    ],
    "wof:name":"Xiaobaiya",
    "wof:placetype":"locality"
},
  "geometry": {"coordinates":[104.92100000000001,27.0613],"type":"Point"}
}