{
  "type": "Feature",
  "properties": {
    "gn:admin1_code":"19.0",
    "gn:asciiname":"Wutangcun",
    "gn:country_code":"CN",
    "gn:dem":228,
    "gn:feature_class":"P",
    "gn:feature_code":"PPL",
    "gn:name":"Wutangcun",
    "gn:population":0,
    "gn:timezone":"Asia/Shanghai",
    "iso:country":"CN",
    "name:zho_x_preferred":[
        "\u4e94\u5858\u6751"
    ],
    "name:zho_x_variant":[
        "\u4e94\u5510\u6751"
    ],
    "wof:name":"Wutangcun",
    "wof:placetype":"locality"
},
  "geometry": {"coordinates":[124.7161,42.70378],"type":"Point"}
}