{
  "type": "Feature",
  "properties": {
    "gn:admin1_code":"14.0",
    "gn:asciiname":"Zhangge",
    "gn:country_code":"CN",
    "gn:dem":4037,
    "gn:feature_class":"P",
    "gn:feature_code":"PPL",
    "gn:name":"Zhangge",
    "gn:population":0,
    "gn:timezone":"Asia/Urumqi",
    "iso:country":"CN",
    "name:zho_x_preferred":[
        "\u7ae0\u6b4c"
    ],
    "wof:name":"Zhangge",
    "wof:placetype":"locality"
},
  "geometry": {"coordinates":[91.47007000000001,29.19195],"type":"Point"}
}