{
  "type": "Feature",
  "properties": {
    "gn:admin1_code":"14.0",
    "gn:asciiname":"Jianze",
    "gn:country_code":"CN",
    "gn:dem":3281,
    "gn:feature_class":"P",
    "gn:feature_code":"PPL",
    "gn:name":"Jianze",
    "gn:population":0,
    "gn:timezone":"Asia/Urumqi",
    "iso:country":"CN",
    "name:zho_x_preferred":[
        "\u7b80\u5219"
    ],
    "wof:name":"Jianze",
    "wof:placetype":"locality"
},
  "geometry": {"coordinates":[93.54231,29.88776],"type":"Point"}
}