{
  "type": "Feature",
  "properties": {
    "gn:admin1_code":"2.0",
    "gn:asciiname":"Shiguhou",
    "gn:country_code":"CN",
    "gn:dem":346,
    "gn:feature_class":"P",
    "gn:feature_code":"PPL",
    "gn:name":"Shiguhou",
    "gn:population":0,
    "gn:timezone":"Asia/Shanghai",
    "iso:country":"CN",
    "name:und_x_variant":[
        "\u77f3\u9f13\u540e",
        "Shiguhou"
    ],
    "wof:name":"Shiguhou",
    "wof:placetype":"locality"
},
  "geometry": {"coordinates":[119.90470999999999,29.36081],"type":"Point"}
}