{
  "type": "Feature",
  "properties": {
    "gn:admin1_code":"30",
    "gn:asciiname":"Pengjian",
    "gn:country_code":"CN",
    "gn:dem":58,
    "gn:feature_class":"P",
    "gn:feature_code":"PPL",
    "gn:name":"Pengjian",
    "gn:population":0,
    "gn:timezone":"Asia/Urumqi",
    "iso:country":"CN",
    "name:zho_x_preferred":[
        "\u5f6d\u7b80"
    ],
    "wof:name":"Pengjian",
    "wof:placetype":"locality"
},
  "geometry": {"coordinates":[110.18692,21.89117],"type":"Point"}
}