{
  "type": "Feature",
  "properties": {
    "gn:admin1_code":"26",
    "gn:asciiname":"Wanjia",
    "gn:country_code":"CN",
    "gn:dem":1027,
    "gn:feature_class":"P",
    "gn:feature_code":"PPL",
    "gn:name":"Wanjia",
    "gn:population":0,
    "gn:timezone":"Asia/Shanghai",
    "iso:country":"CN",
    "name:und_x_variant":[
        "\u6e7e\u5bb6"
    ],
    "name:zho_x_preferred":[
        "\u6e7e\u5bb6"
    ],
    "wof:name":"Wanjia",
    "wof:placetype":"locality"
},
  "geometry": {"coordinates":[108.58693999999998,34.74583],"type":"Point"}
}