{
  "type": "Feature",
  "properties": {
    "gn:admin1_code":"4.0",
    "gn:asciiname":"Tansuncun",
    "gn:country_code":"CN",
    "gn:dem":5,
    "gn:feature_class":"P",
    "gn:feature_code":"PPL",
    "gn:name":"Tansuncun",
    "gn:population":0,
    "gn:timezone":"Asia/Shanghai",
    "iso:country":"CN",
    "name:zho_x_preferred":[
        "\u6a80\u5b59\u6751"
    ],
    "wof:name":"Tansuncun",
    "wof:placetype":"locality"
},
  "geometry": {"coordinates":[119.90991,33.04468],"type":"Point"}
}