{
  "type": "Feature",
  "properties": {
    "gn:admin1_code":"5.0",
    "gn:asciiname":"Zouqiu Jiadian",
    "gn:country_code":"CN",
    "gn:dem":220,
    "gn:feature_class":"P",
    "gn:feature_code":"PPL",
    "gn:name":"Zouqiu Jiadian",
    "gn:population":0,
    "gn:timezone":"Asia/Shanghai",
    "iso:country":"CN",
    "name:zho_x_preferred":[
        "\u90b9\u4e18\u5bb6\u5e97"
    ],
    "wof:name":"Zouqiu Jiadian",
    "wof:placetype":"locality"
},
  "geometry": {"coordinates":[124.8965,44.58971],"type":"Point"}
}