{
  "type": "Feature",
  "properties": {
    "gn:admin1_code":"33.0",
    "gn:asciiname":"Gaoshiba",
    "gn:country_code":"CN",
    "gn:dem":320,
    "gn:feature_class":"P",
    "gn:feature_code":"PPL",
    "gn:name":"Gaoshiba",
    "gn:population":0,
    "gn:timezone":"Asia/Shanghai",
    "iso:country":"CN",
    "name:zho_x_preferred":[
        "\u9ad8\u77f3\u575d"
    ],
    "wof:name":"Gaoshiba",
    "wof:placetype":"locality"
},
  "geometry": {"coordinates":[106.51964,30.19063],"type":"Point"}
}