{
  "type": "Feature",
  "properties": {
    "gn:admin1_code":"03",
    "gn:asciiname":"Shenxi",
    "gn:country_code":"CN",
    "gn:dem":248,
    "gn:feature_class":"P",
    "gn:feature_code":"PPL",
    "gn:name":"Shenxi",
    "gn:population":0,
    "gn:timezone":"Asia/Shanghai",
    "iso:country":"CN",
    "name:und_x_variant":[
        "\u6df1\u6eaa"
    ],
    "wof:name":"Shenxi",
    "wof:placetype":"locality"
},
  "geometry": {"coordinates":[115.55773000000001,25.44996],"type":"Point"}
}