{
  "type": "Feature",
  "properties": {
    "gn:admin1_code":"32.0",
    "gn:asciiname":"Mojiang",
    "gn:country_code":"CN",
    "gn:dem":427,
    "gn:feature_class":"P",
    "gn:feature_code":"PPL",
    "gn:name":"Mojiang",
    "gn:population":0,
    "gn:timezone":"Asia/Shanghai",
    "iso:country":"CN",
    "name:zho_x_preferred":[
        "\u6cab\u6c5f"
    ],
    "wof:name":"Mojiang",
    "wof:placetype":"locality"
},
  "geometry": {"coordinates":[103.556,29.3503],"type":"Point"}
}