{
  "type": "Feature",
  "properties": {
    "gn:admin1_code":"3.0",
    "gn:asciiname":"Datangxing",
    "gn:country_code":"CN",
    "gn:dem":105,
    "gn:feature_class":"P",
    "gn:feature_code":"PPL",
    "gn:name":"Datangxing",
    "gn:population":0,
    "gn:timezone":"Asia/Shanghai",
    "iso:country":"CN",
    "name:zho_x_preferred":[
        "\u5927\u5858\u5f62"
    ],
    "wof:name":"Datangxing",
    "wof:placetype":"locality"
},
  "geometry": {"coordinates":[117.0629,28.58227],"type":"Point"}
}