{
  "type": "Feature",
  "properties": {
    "gn:admin1_code":"07",
    "gn:asciiname":"Shenkengjing",
    "gn:country_code":"CN",
    "gn:dem":343,
    "gn:feature_class":"P",
    "gn:feature_code":"PPL",
    "gn:name":"Shenkengjing",
    "gn:population":0,
    "gn:timezone":"Asia/Shanghai",
    "iso:country":"CN",
    "name:zho_x_preferred":[
        "\u6df1\u5751\u4e95"
    ],
    "wof:name":"Shenkengjing",
    "wof:placetype":"locality"
},
  "geometry": {"coordinates":[117.69399,25.50844],"type":"Point"}
}