{
  "type": "Feature",
  "properties": {
    "gn:admin1_code":"2.0",
    "gn:asciiname":"Qiaodong",
    "gn:country_code":"CN",
    "gn:dem":66,
    "gn:feature_class":"P",
    "gn:feature_code":"PPL",
    "gn:name":"Qiaodong",
    "gn:population":0,
    "gn:timezone":"Asia/Shanghai",
    "iso:country":"CN",
    "name:zho_x_preferred":[
        "\u6865\u4e1c"
    ],
    "wof:name":"Qiaodong",
    "wof:placetype":"locality"
},
  "geometry": {"coordinates":[120.08468000000001,29.30544],"type":"Point"}
}