{
  "type": "Feature",
  "properties": {
    "gn:admin1_code":"11.0",
    "gn:asciiname":"Songshuitang",
    "gn:country_code":"CN",
    "gn:dem":93,
    "gn:feature_class":"P",
    "gn:feature_code":"PPL",
    "gn:name":"Songshuitang",
    "gn:population":0,
    "gn:timezone":"Asia/Shanghai",
    "iso:country":"CN",
    "name:zho_x_preferred":[
        "\u677e\u6c34\u5858"
    ],
    "wof:name":"Songshuitang",
    "wof:placetype":"locality"
},
  "geometry": {"coordinates":[112.78225,26.61808],"type":"Point"}
}