{
  "type": "Feature",
  "properties": {
    "gn:admin1_code":"19.0",
    "gn:asciiname":"Shijiacun",
    "gn:country_code":"CN",
    "gn:dem":96,
    "gn:feature_class":"P",
    "gn:feature_code":"PPL",
    "gn:name":"Shijiacun",
    "gn:population":0,
    "gn:timezone":"Asia/Shanghai",
    "iso:country":"CN",
    "name:zho_x_preferred":[
        "\u65bd\u5bb6\u6751"
    ],
    "wof:name":"Shijiacun",
    "wof:placetype":"locality"
},
  "geometry": {"coordinates":[123.937,41.8957],"type":"Point"}
}