{
  "type": "Feature",
  "properties": {
    "gn:admin1_code":"26.0",
    "gn:asciiname":"Dawuchang",
    "gn:country_code":"CN",
    "gn:dem":1201,
    "gn:feature_class":"P",
    "gn:feature_code":"PPL",
    "gn:name":"Dawuchang",
    "gn:population":0,
    "gn:timezone":"Asia/Shanghai",
    "iso:country":"CN",
    "name:zho_x_preferred":[
        "\u5927\u5c4b\u573a"
    ],
    "wof:name":"Dawuchang",
    "wof:placetype":"locality"
},
  "geometry": {"coordinates":[109.01895,33.71716],"type":"Point"}
}