{
  "type": "Feature",
  "properties": {
    "gn:admin1_code":"16.0",
    "gn:asciiname":"Zaoqing",
    "gn:country_code":"CN",
    "gn:dem":143,
    "gn:feature_class":"P",
    "gn:feature_code":"PPL",
    "gn:name":"Zaoqing",
    "gn:population":0,
    "gn:timezone":"Asia/Shanghai",
    "iso:country":"CN",
    "name:zho_x_preferred":[
        "\u9020\u5e86"
    ],
    "wof:name":"Zaoqing",
    "wof:placetype":"locality"
},
  "geometry": {"coordinates":[108.325,23.0154],"type":"Point"}
}