{
  "type": "Feature",
  "properties": {
    "gn:admin1_code":"16",
    "gn:asciiname":"Zongsikou",
    "gn:country_code":"CN",
    "gn:dem":860,
    "gn:feature_class":"P",
    "gn:feature_code":"PPL",
    "gn:name":"Zongsikou",
    "gn:population":0,
    "gn:timezone":"Asia/Shanghai",
    "iso:country":"CN",
    "name:zho_x_preferred":[
        "\u68d5\u4e1d\u53e3"
    ],
    "wof:name":"Zongsikou",
    "wof:placetype":"locality"
},
  "geometry": {"coordinates":[110.628,26.3127],"type":"Point"}
}