{
  "type": "Feature",
  "properties": {
    "gn:admin1_code":"9.0",
    "gn:asciiname":"Taolinpu",
    "gn:country_code":"CN",
    "gn:dem":52,
    "gn:feature_class":"P",
    "gn:feature_code":"PPL",
    "gn:name":"Taolinpu",
    "gn:population":0,
    "gn:timezone":"Asia/Shanghai",
    "iso:country":"CN",
    "name:zho_x_preferred":[
        "\u6843\u6797\u94fa"
    ],
    "wof:name":"Taolinpu",
    "wof:placetype":"locality"
},
  "geometry": {"coordinates":[115.30267000000001,32.17821],"type":"Point"}
}