{
  "type": "Feature",
  "properties": {
    "gn:admin1_code":"30.0",
    "gn:asciiname":"Letang",
    "gn:country_code":"CN",
    "gn:dem":12,
    "gn:feature_class":"P",
    "gn:feature_code":"PPL",
    "gn:name":"Letang",
    "gn:population":0,
    "gn:timezone":"Asia/Shanghai",
    "iso:country":"CN",
    "name:bih_x_preferred":[
        "\u0932\u0947\u091f\u093e\u0919\u094d\u0917"
    ],
    "name:ceb_x_preferred":[
        "Letang"
    ],
    "name:deu_x_preferred":[
        "Letang-Bhogateni"
    ],
    "name:mai_x_preferred":[
        "\u0932\u0947\u091f\u093e\u0919\u094d\u0917"
    ],
    "name:msa_x_preferred":[
        "Letang"
    ],
    "name:nep_x_preferred":[
        "\u0932\u0947\u091f\u093e\u0919-\u092d\u094b\u0917\u091f\u0947\u0928\u0940 \u0928\u0917\u0930\u092a\u093e\u0932\u093f\u0915\u093e"
    ],
    "name:new_x_preferred":[
        "\u0932\u0947\u091f\u093e\u0919"
    ],
    "name:pol_x_preferred":[
        "Letang"
    ],
    "name:zho_x_preferred":[
        "\u6a02\u5858"
    ],
    "wof:name":"Letang",
    "wof:placetype":"locality"
},
  "geometry": {"coordinates":[112.56319000000001,22.98942000000001],"type":"Point"}
}