{
  "type": "Feature",
  "properties": {
    "gn:admin1_code":"32.0",
    "gn:asciiname":"Nailong",
    "gn:country_code":"CN",
    "gn:dem":4109,
    "gn:feature_class":"P",
    "gn:feature_code":"PPL",
    "gn:name":"Nailong",
    "gn:population":0,
    "gn:timezone":"Asia/Shanghai",
    "iso:country":"CN",
    "name:zho_x_preferred":[
        "\u5976\u9f99"
    ],
    "name:zho_x_variant":[
        "\u4e43\u9686"
    ],
    "wof:name":"Nailong",
    "wof:placetype":"locality"
},
  "geometry": {"coordinates":[98.74420000000001,32.2286],"type":"Point"}
}