{
  "type": "Feature",
  "properties": {
    "gn:admin1_code":"10.0",
    "gn:asciiname":"Dabaidian",
    "gn:country_code":"CN",
    "gn:dem":40,
    "gn:feature_class":"P",
    "gn:feature_code":"PPL",
    "gn:name":"Dabaidian",
    "gn:population":0,
    "gn:timezone":"Asia/Shanghai",
    "iso:country":"CN",
    "name:zho_x_preferred":[
        "\u5927\u767d\u5e97"
    ],
    "wof:name":"Dabaidian",
    "wof:placetype":"locality"
},
  "geometry": {"coordinates":[115.21899999999999,38.0389],"type":"Point"}
}