{
  "type": "Feature",
  "properties": {
    "gn:admin1_code":"1.0",
    "gn:asciiname":"Yehucun",
    "gn:country_code":"CN",
    "gn:dem":23,
    "gn:feature_class":"P",
    "gn:feature_code":"PPL",
    "gn:name":"Yehucun",
    "gn:population":0,
    "gn:timezone":"Asia/Shanghai",
    "iso:country":"CN",
    "name:und_x_variant":[
        "Yehu"
    ],
    "name:zho_x_preferred":[
        "\u53f6\u6e56\u6751"
    ],
    "wof:name":"Yehucun",
    "wof:placetype":"locality"
},
  "geometry": {"coordinates":[117.31036,33.23089],"type":"Point"}
}