{
  "type": "Feature",
  "properties": {
    "gn:admin1_code":"32.0",
    "gn:asciiname":"Jianjiaping",
    "gn:country_code":"CN",
    "gn:dem":597,
    "gn:feature_class":"P",
    "gn:feature_code":"PPL",
    "gn:name":"Jianjiaping",
    "gn:population":0,
    "gn:timezone":"Asia/Shanghai",
    "iso:country":"CN",
    "name:zho_x_preferred":[
        "\u8e47\u5bb6\u576a"
    ],
    "wof:name":"Jianjiaping",
    "wof:placetype":"locality"
},
  "geometry": {"coordinates":[106.56699999999999,31.8852],"type":"Point"}
}