{
  "type": "Feature",
  "properties": {
    "gn:admin1_code":"11",
    "gn:asciiname":"Qingshan Longjia",
    "gn:country_code":"CN",
    "gn:dem":584,
    "gn:feature_class":"P",
    "gn:feature_code":"PPL",
    "gn:name":"Qingshan Longjia",
    "gn:population":0,
    "gn:timezone":"Asia/Shanghai",
    "iso:country":"CN",
    "name:und_x_variant":[
        "Qingshanpengjia",
        "Qingshan Longjia"
    ],
    "name:zho_x_preferred":[
        "\u9752\u5c71\u9f99\u5bb6"
    ],
    "wof:name":"Qingshan Longjia",
    "wof:placetype":"locality"
},
  "geometry": {"coordinates":[111.42336,27.02223],"type":"Point"}
}