{
  "type": "Feature",
  "properties": {
    "gn:admin1_code":"8.0",
    "gn:asciiname":"Baoquanling Ershi'erdui",
    "gn:country_code":"CN",
    "gn:dem":115,
    "gn:feature_class":"P",
    "gn:feature_code":"PPLF",
    "gn:name":"Baoquanling Ershi\u2019erdui",
    "gn:population":0,
    "gn:timezone":"Asia/Shanghai",
    "iso:country":"CN",
    "name:und_x_variant":[
        "Baoquanling Ershi\u2019erdui"
    ],
    "name:zho_x_preferred":[
        "\u5b9d\u6cc9\u5cad\u4e8c\u5341\u4e8c\u961f"
    ],
    "wof:name":"Baoquanling Ershi'erdui",
    "wof:placetype":"locality"
},
  "geometry": {"coordinates":[130.43769,47.45413],"type":"Point"}
}