{
  "type": "Feature",
  "properties": {
    "gn:admin1_code":"6.0",
    "gn:asciiname":"Gaguangji",
    "gn:country_code":"CN",
    "gn:dem":4161,
    "gn:feature_class":"P",
    "gn:feature_code":"PPL",
    "gn:name":"Gaguangji",
    "gn:population":0,
    "gn:timezone":"Asia/Urumqi",
    "iso:country":"CN",
    "name:zho_x_preferred":[
        "\u5c15\u5149\u7ed9"
    ],
    "wof:name":"Gaguangji",
    "wof:placetype":"locality"
},
  "geometry": {"coordinates":[96.39597000000001,32.6827],"type":"Point"}
}