{
  "type": "Feature",
  "properties": {
    "gn:admin1_code":"3.0",
    "gn:asciiname":"Litangxia",
    "gn:country_code":"CN",
    "gn:dem":115,
    "gn:feature_class":"P",
    "gn:feature_code":"PPL",
    "gn:name":"Litangxia",
    "gn:population":0,
    "gn:timezone":"Asia/Shanghai",
    "iso:country":"CN",
    "name:und_x_variant":[
        "\u6817\u5858\u4e0b"
    ],
    "wof:name":"Litangxia",
    "wof:placetype":"locality"
},
  "geometry": {"coordinates":[114.36418999999999,27.8845],"type":"Point"}
}