{
  "type": "Feature",
  "properties": {
    "gn:admin1_code":"2.0",
    "gn:asciiname":"Beizhuangdou",
    "gn:country_code":"CN",
    "gn:dem":5,
    "gn:feature_class":"P",
    "gn:feature_code":"PPL",
    "gn:name":"Beizhuangdou",
    "gn:population":0,
    "gn:timezone":"Asia/Shanghai",
    "iso:country":"CN",
    "name:und_x_variant":[
        "\u5317\u5e84\u515c"
    ],
    "wof:name":"Beizhuangdou",
    "wof:placetype":"locality"
},
  "geometry": {"coordinates":[120.58356000000001,30.57671],"type":"Point"}
}