{
  "type": "Feature",
  "properties": {
    "gn:admin1_code":"9",
    "gn:asciiname":"Xijigan",
    "gn:country_code":"CN",
    "gn:dem":50,
    "gn:feature_class":"P",
    "gn:feature_code":"PPL",
    "gn:name":"Xijigan",
    "gn:population":0,
    "gn:timezone":"Asia/Shanghai",
    "iso:country":"CN",
    "name:zho_x_preferred":[
        "\u897f\u5409\u5e72"
    ],
    "wof:name":"Xijigan",
    "wof:placetype":"locality"
},
  "geometry": {"coordinates":[115.28758999999999,36.03372],"type":"Point"}
}