{
  "type": "Feature",
  "properties": {
    "gn:admin1_code":"24.0",
    "gn:asciiname":"Kangjiazhuang Linchang",
    "gn:country_code":"CN",
    "gn:dem":1623,
    "gn:feature_class":"P",
    "gn:feature_code":"PPLF",
    "gn:name":"Kangjiazhuang Linchang",
    "gn:population":0,
    "gn:timezone":"Asia/Shanghai",
    "iso:country":"CN",
    "name:zho_x_preferred":[
        "\u5eb7\u5bb6\u5e84\u6797\u573a"
    ],
    "wof:name":"Kangjiazhuang Linchang",
    "wof:placetype":"locality"
},
  "geometry": {"coordinates":[111.91148,37.4643],"type":"Point"}
}