{
  "type": "Feature",
  "properties": {
    "gn:admin1_code":"10",
    "gn:asciiname":"Laolingwan",
    "gn:country_code":"CN",
    "gn:dem":261,
    "gn:feature_class":"P",
    "gn:feature_code":"PPL",
    "gn:name":"Laolingwan",
    "gn:population":0,
    "gn:timezone":"Asia/Shanghai",
    "iso:country":"CN",
    "name:zho_x_preferred":[
        "\u8001\u5cad\u6e7e"
    ],
    "wof:name":"Laolingwan",
    "wof:placetype":"locality"
},
  "geometry": {"coordinates":[119.12067,40.59069],"type":"Point"}
}