{
  "type": "Feature",
  "properties": {
    "gn:admin1_code":"30.0",
    "gn:asciiname":"Xiekeng",
    "gn:country_code":"CN",
    "gn:dem":317,
    "gn:feature_class":"P",
    "gn:feature_code":"PPL",
    "gn:name":"Xiekeng",
    "gn:population":0,
    "gn:timezone":"Asia/Shanghai",
    "iso:country":"CN",
    "name:zho_x_preferred":[
        "\u978b\u5751"
    ],
    "wof:name":"Xiekeng",
    "wof:placetype":"locality"
},
  "geometry": {"coordinates":[113.29125999999999,25.20921],"type":"Point"}
}