{
  "type": "Feature",
  "properties": {
    "gn:admin1_code":"25",
    "gn:asciiname":"Nanzhongjia",
    "gn:country_code":"CN",
    "gn:dem":241,
    "gn:feature_class":"P",
    "gn:feature_code":"PPL",
    "gn:name":"Nanzhongjia",
    "gn:population":0,
    "gn:timezone":"Asia/Shanghai",
    "iso:country":"CN",
    "name:zho_x_preferred":[
        "\u5357\u4ef2\u5bb6"
    ],
    "wof:name":"Nanzhongjia",
    "wof:placetype":"locality"
},
  "geometry": {"coordinates":[119.09,35.6155],"type":"Point"}
}