{
  "type": "Feature",
  "properties": {
    "gn:admin1_code":"7.0",
    "gn:asciiname":"Fuwo",
    "gn:country_code":"CN",
    "gn:dem":140,
    "gn:feature_class":"P",
    "gn:feature_code":"PPL",
    "gn:name":"Fuwo",
    "gn:population":0,
    "gn:timezone":"Asia/Taipei",
    "iso:country":"CN",
    "name:zho_x_preferred":[
        "\u798f\u6c83"
    ],
    "wof:name":"Fuwo",
    "wof:placetype":"locality"
},
  "geometry": {"coordinates":[119.94204999999999,26.15716],"type":"Point"}
}