{
  "type": "Feature",
  "properties": {
    "gn:admin1_code":"26.0",
    "gn:asciiname":"Taoyuanzi",
    "gn:country_code":"CN",
    "gn:dem":989,
    "gn:feature_class":"P",
    "gn:feature_code":"PPL",
    "gn:name":"Taoyuanzi",
    "gn:population":0,
    "gn:timezone":"Asia/Shanghai",
    "iso:country":"CN",
    "name:und_x_variant":[
        "\u6843\u56ed\u5b50"
    ],
    "wof:name":"Taoyuanzi",
    "wof:placetype":"locality"
},
  "geometry": {"coordinates":[106.15152,33.15413],"type":"Point"}
}