{
  "type": "Feature",
  "properties": {
    "gn:admin1_code":"12.0",
    "gn:asciiname":"Jiuligang",
    "gn:country_code":"CN",
    "gn:dem":78,
    "gn:feature_class":"P",
    "gn:feature_code":"PPL",
    "gn:name":"Jiuligang",
    "gn:population":0,
    "gn:timezone":"Asia/Shanghai",
    "iso:country":"CN",
    "name:zho_x_preferred":[
        "Jiuligang"
    ],
    "name:zho_x_variant":[
        "\u4e5d\u91cc\u5c97"
    ],
    "wof:name":"Jiuligang",
    "wof:placetype":"locality"
},
  "geometry": {"coordinates":[111.87758999999998,30.8753],"type":"Point"}
}