{
  "type": "Feature",
  "properties": {
    "gn:admin1_code":"9.0",
    "gn:asciiname":"Geda Shangcun",
    "gn:country_code":"CN",
    "gn:dem":509,
    "gn:feature_class":"P",
    "gn:feature_code":"PPL",
    "gn:name":"Geda Shangcun",
    "gn:population":0,
    "gn:timezone":"Asia/Shanghai",
    "iso:country":"CN",
    "name:zho_x_preferred":[
        "\u7599\u57af\u4e0a\u6751"
    ],
    "wof:name":"Geda Shangcun",
    "wof:placetype":"locality"
},
  "geometry": {"coordinates":[111.98793000000001,34.0245],"type":"Point"}
}