{
  "type": "Feature",
  "properties": {
    "gn:admin1_code":"26.0",
    "gn:asciiname":"Changmaoyancun",
    "gn:country_code":"CN",
    "gn:dem":1234,
    "gn:feature_class":"P",
    "gn:feature_code":"PPL",
    "gn:name":"Changmaoyancun",
    "gn:population":0,
    "gn:timezone":"Asia/Shanghai",
    "iso:country":"CN",
    "name:zho_x_preferred":[
        "\u5e38\u5cc1\u5895\u6751"
    ],
    "wof:name":"Changmaoyancun",
    "wof:placetype":"locality"
},
  "geometry": {"coordinates":[109.66698,37.76392],"type":"Point"}
}