{
  "type": "Feature",
  "properties": {
    "gn:admin1_code":"29",
    "gn:asciiname":"Fazhai",
    "gn:country_code":"CN",
    "gn:dem":2240,
    "gn:feature_class":"P",
    "gn:feature_code":"PPL",
    "gn:name":"Fazhai",
    "gn:population":0,
    "gn:timezone":"Asia/Shanghai",
    "iso:country":"CN",
    "name:zho_x_preferred":[
        "\u6cd5\u5be8"
    ],
    "wof:name":"Fazhai",
    "wof:placetype":"locality"
},
  "geometry": {"coordinates":[102.371,24.4433],"type":"Point"}
}