{
  "type": "Feature",
  "properties": {
    "gn:admin1_code":"29",
    "gn:asciiname":"Yepinde",
    "gn:country_code":"CN",
    "gn:dem":1509,
    "gn:feature_class":"P",
    "gn:feature_code":"PPL",
    "gn:name":"Yepinde",
    "gn:population":0,
    "gn:timezone":"Asia/Shanghai",
    "iso:country":"CN",
    "name:zho_x_preferred":[
        "\u91ce\u54c1\u5f97"
    ],
    "wof:name":"Yepinde",
    "wof:placetype":"locality"
},
  "geometry": {"coordinates":[104.74299999999999,23.8813],"type":"Point"}
}