{
  "type": "Feature",
  "properties": {
    "gn:admin1_code":"3",
    "gn:asciiname":"Jingkou",
    "gn:country_code":"CN",
    "gn:dem":295,
    "gn:feature_class":"P",
    "gn:feature_code":"PPL",
    "gn:name":"Jingkou",
    "gn:population":0,
    "gn:timezone":"Asia/Shanghai",
    "iso:country":"CN",
    "name:und_x_variant":[
        "\u5f84\u53e3"
    ],
    "wof:name":"Jingkou",
    "wof:placetype":"locality"
},
  "geometry": {"coordinates":[116.29307,26.02958],"type":"Point"}
}