{
  "type": "Feature",
  "properties": {
    "gn:admin1_code":"1.0",
    "gn:asciiname":"Dingloucun",
    "gn:country_code":"CN",
    "gn:dem":36,
    "gn:feature_class":"P",
    "gn:feature_code":"PPL",
    "gn:name":"Dingloucun",
    "gn:population":0,
    "gn:timezone":"Asia/Shanghai",
    "iso:country":"CN",
    "name:zho_x_preferred":[
        "\u4e01\u697c\u6751"
    ],
    "wof:name":"Dingloucun",
    "wof:placetype":"locality"
},
  "geometry": {"coordinates":[115.93831000000002,33.68118],"type":"Point"}
}