{
  "type": "Feature",
  "properties": {
    "gn:admin1_code":"11.0",
    "gn:asciiname":"Qianlong",
    "gn:country_code":"CN",
    "gn:dem":249,
    "gn:feature_class":"P",
    "gn:feature_code":"PPL",
    "gn:name":"Qianlong",
    "gn:population":0,
    "gn:timezone":"Asia/Shanghai",
    "iso:country":"CN",
    "name:zho_x_preferred":[
        "\u6f5c\u9f99"
    ],
    "wof:name":"Qianlong",
    "wof:placetype":"locality"
},
  "geometry": {"coordinates":[111.94577,26.93803],"type":"Point"}
}