{
  "type": "Feature",
  "properties": {
    "gn:admin1_code":"32.0",
    "gn:asciiname":"Xinyoufang",
    "gn:country_code":"CN",
    "gn:dem":466,
    "gn:feature_class":"P",
    "gn:feature_code":"PPL",
    "gn:name":"Xinyoufang",
    "gn:population":0,
    "gn:timezone":"Asia/Shanghai",
    "iso:country":"CN",
    "name:zho_x_preferred":[
        "\u65b0\u6cb9\u623f"
    ],
    "wof:name":"Xinyoufang",
    "wof:placetype":"locality"
},
  "geometry": {"coordinates":[107.31,31.0106],"type":"Point"}
}