{
  "type": "Feature",
  "properties": {
    "gn:admin1_code":"12.0",
    "gn:asciiname":"Zoujia Huayuan",
    "gn:country_code":"CN",
    "gn:dem":35,
    "gn:feature_class":"P",
    "gn:feature_code":"PPL",
    "gn:name":"Zoujia Huayuan",
    "gn:population":0,
    "gn:timezone":"Asia/Shanghai",
    "iso:country":"CN",
    "name:zho_x_preferred":[
        "\u90b9\u5bb6\u82b1\u56ed"
    ],
    "wof:name":"Zoujia Huayuan",
    "wof:placetype":"locality"
},
  "geometry": {"coordinates":[112.72291,30.59183],"type":"Point"}
}