{
  "type": "Feature",
  "properties": {
    "gn:admin1_code":"19.0",
    "gn:asciiname":"Dongfagnshen",
    "gn:country_code":"CN",
    "gn:dem":16,
    "gn:feature_class":"P",
    "gn:feature_code":"PPL",
    "gn:name":"Dongfagnshen",
    "gn:population":0,
    "gn:timezone":"Asia/Shanghai",
    "iso:country":"CN",
    "name:zho_x_preferred":[
        "\u4e1c\u623f\u8eab"
    ],
    "wof:name":"Dongfagnshen",
    "wof:placetype":"locality"
},
  "geometry": {"coordinates":[122.58863999999998,41.60482],"type":"Point"}
}