{
  "type": "Feature",
  "properties": {
    "gn:admin1_code":"7",
    "gn:asciiname":"Yunlong",
    "gn:country_code":"CN",
    "gn:dem":54,
    "gn:feature_class":"P",
    "gn:feature_code":"PPLA4",
    "gn:name":"Yunlong",
    "gn:population":0,
    "gn:timezone":"Asia/Shanghai",
    "iso:country":"CN",
    "name:und_x_variant":[
        "Yunlong Xiang"
    ],
    "name:zho_x_preferred":[
        "\u4e91\u9f99"
    ],
    "name:zho_x_variant":[
        "\u4e91\u9f99\u4e61"
    ],
    "wof:name":"Yunlong",
    "wof:placetype":"locality"
},
  "geometry": {"coordinates":[118.82995,26.17088],"type":"Point"}
}