{
  "type": "Feature",
  "properties": {
    "gn:admin1_code":"3.0",
    "gn:asciiname":"Ji'an Shi Wugongshan Linchang",
    "gn:country_code":"CN",
    "gn:dem":198,
    "gn:feature_class":"P",
    "gn:feature_code":"PPLF",
    "gn:name":"Ji\u2019an Shi Wugongshan Linchang",
    "gn:population":0,
    "gn:timezone":"Asia/Shanghai",
    "iso:country":"CN",
    "name:und_x_variant":[
        "Ji\u2019an Shi Wugongshan Linchang",
        "\u5409\u5b89\u5e02\u6b66\u529f\u5c71\u6797\u573a"
    ],
    "wof:name":"Ji'an Shi Wugongshan Linchang",
    "wof:placetype":"locality"
},
  "geometry": {"coordinates":[114.24039,27.30243],"type":"Point"}
}