{
  "type": "Feature",
  "properties": {
    "gn:admin1_code":"32.0",
    "gn:asciiname":"Deyi",
    "gn:country_code":"CN",
    "gn:dem":3620,
    "gn:feature_class":"P",
    "gn:feature_code":"PPL",
    "gn:name":"Deyi",
    "gn:population":0,
    "gn:timezone":"Asia/Shanghai",
    "iso:country":"CN",
    "name:zho_x_preferred":[
        "\u5fb7\u8863"
    ],
    "wof:name":"Deyi",
    "wof:placetype":"locality"
},
  "geometry": {"coordinates":[100.221,31.6742],"type":"Point"}
}