{
  "type": "Feature",
  "properties": {
    "gn:admin1_code":"5.0",
    "gn:asciiname":"Ping'ancun",
    "gn:country_code":"CN",
    "gn:dem":205,
    "gn:feature_class":"P",
    "gn:feature_code":"PPL",
    "gn:name":"Ping\u2019ancun",
    "gn:population":0,
    "gn:timezone":"Asia/Shanghai",
    "iso:country":"CN",
    "name:und_x_variant":[
        "Ping\u2019ancun"
    ],
    "name:zho_x_preferred":[
        "\u5e73\u5b89\u6751"
    ],
    "wof:name":"Ping'ancun",
    "wof:placetype":"locality"
},
  "geometry": {"coordinates":[126.16839,43.90969000000001],"type":"Point"}
}