{
  "type": "Feature",
  "properties": {
    "gn:admin1_code":"29",
    "gn:asciiname":"Yijiachong",
    "gn:country_code":"CN",
    "gn:dem":1593,
    "gn:feature_class":"P",
    "gn:feature_code":"PPL",
    "gn:name":"Yijiachong",
    "gn:population":0,
    "gn:timezone":"Asia/Shanghai",
    "iso:country":"CN",
    "name:zho_x_preferred":[
        "\u9091\u7532\u51b2"
    ],
    "wof:name":"Yijiachong",
    "wof:placetype":"locality"
},
  "geometry": {"coordinates":[102.224,23.6478],"type":"Point"}
}