{
  "type": "Feature",
  "properties": {
    "gn:admin1_code":"4.0",
    "gn:asciiname":"Jiuli",
    "gn:country_code":"CN",
    "gn:dem":3,
    "gn:feature_class":"P",
    "gn:feature_code":"PPL",
    "gn:name":"Jiuli",
    "gn:population":0,
    "gn:timezone":"Asia/Shanghai",
    "iso:country":"CN",
    "name:ceb_x_preferred":[
        "Jiuli"
    ],
    "name:deu_x_preferred":[
        "Jiuli"
    ],
    "name:swe_x_preferred":[
        "Jiuli"
    ],
    "name:zho_x_preferred":[
        "Jiuli"
    ],
    "name:zho_x_variant":[
        "\u4e5d\u91cc"
    ],
    "wof:name":"Jiuli",
    "wof:placetype":"locality"
},
  "geometry": {"coordinates":[119.66743999999998,33.31381],"type":"Point"}
}