{
  "type": "Feature",
  "properties": {
    "gn:admin1_code":"10",
    "gn:asciiname":"Zicheng",
    "gn:country_code":"CN",
    "gn:dem":41,
    "gn:feature_class":"P",
    "gn:feature_code":"PPL",
    "gn:name":"Zicheng",
    "gn:population":0,
    "gn:timezone":"Asia/Shanghai",
    "iso:country":"CN",
    "name:ben_x_preferred":[
        "\u099d\u09bf\u099b\u09c7\u0982"
    ],
    "name:deu_x_preferred":[
        "Zicheng"
    ],
    "name:ell_x_preferred":[
        "\u0396\u03b9\u03c4\u03c3\u03ad\u03bd\u03b3\u03ba"
    ],
    "name:fas_x_preferred":[
        "\u0632\u06cc\u0686\u0646\u06af"
    ],
    "name:fra_x_preferred":[
        "Zicheng"
    ],
    "name:heb_x_preferred":[
        "\u05d6'\u05d9\u05e6'\u05e0\u05d2"
    ],
    "name:hin_x_preferred":[
        "\u091c\u093c\u093e\u0907\u0915\u0947\u0902\u0917"
    ],
    "name:hun_x_preferred":[
        "Zicheng"
    ],
    "name:ind_x_preferred":[
        "Zicheng"
    ],
    "name:ita_x_preferred":[
        "Zicheng"
    ],
    "name:kor_x_preferred":[
        "\uc790\uc774\uccad"
    ],
    "name:nld_x_preferred":[
        "Zicheng"
    ],
    "name:pol_x_preferred":[
        "Zicheng"
    ],
    "name:rus_x_preferred":[
        "\u0426\u0437\u044b\u0447\u044d\u043d"
    ],
    "name:spa_x_preferred":[
        "Zicheng"
    ],
    "name:tur_x_preferred":[
        "Zicheng"
    ],
    "name:ukr_x_preferred":[
        "\u0426\u0437\u0438\u0447\u0435\u043d"
    ],
    "name:urd_x_preferred":[
        "\u0632\u06cc\u0686\u06cc\u0646\u06af"
    ],
    "name:vie_x_preferred":[
        "T\u1eed Th\u00e0nh"
    ],
    "name:zho_x_preferred":[
        "\u5b50\u57ce"
    ],
    "wof:name":"Zicheng",
    "wof:placetype":"locality"
},
  "geometry": {"coordinates":[115.21899999999999,38.8036],"type":"Point"}
}