{
  "type": "Feature",
  "properties": {
    "gn:admin1_code":"2",
    "gn:asciiname":"Jinchu",
    "gn:country_code":"CN",
    "gn:dem":681,
    "gn:feature_class":"P",
    "gn:feature_code":"PPL",
    "gn:name":"Jinchu",
    "gn:population":0,
    "gn:timezone":"Asia/Shanghai",
    "iso:country":"CN",
    "name:zho_x_preferred":[
        "\u91d1\u5904"
    ],
    "wof:name":"Jinchu",
    "wof:placetype":"locality"
},
  "geometry": {"coordinates":[119.48472,27.89194],"type":"Point"}
}