{
  "type": "Feature",
  "properties": {
    "gn:admin1_code":"19.0",
    "gn:asciiname":"Yanwubishi",
    "gn:country_code":"CN",
    "gn:dem":71,
    "gn:feature_class":"P",
    "gn:feature_code":"PPL",
    "gn:name":"Yanwubishi",
    "gn:population":0,
    "gn:timezone":"Asia/Shanghai",
    "iso:country":"CN",
    "name:zho_x_preferred":[
        "\u6f14\u6b66\u6bd4\u5f0f"
    ],
    "wof:name":"Yanwubishi",
    "wof:placetype":"locality"
},
  "geometry": {"coordinates":[123.667,42.097],"type":"Point"}
}