{
  "type": "Feature",
  "properties": {
    "gn:admin1_code":"11.0",
    "gn:asciiname":"Honghualing",
    "gn:country_code":"CN",
    "gn:dem":606,
    "gn:feature_class":"P",
    "gn:feature_code":"PPL",
    "gn:name":"Honghualing",
    "gn:population":0,
    "gn:timezone":"Asia/Shanghai",
    "iso:country":"CN",
    "name:zho_x_preferred":[
        "\u7ea2\u82b1\u5cad"
    ],
    "wof:name":"Honghualing",
    "wof:placetype":"locality"
},
  "geometry": {"coordinates":[110.44963,29.65828],"type":"Point"}
}