{
  "type": "Feature",
  "properties": {
    "gn:admin1_code":"19.0",
    "gn:asciiname":"Lijiafang",
    "gn:country_code":"CN",
    "gn:dem":10,
    "gn:feature_class":"P",
    "gn:feature_code":"PPL",
    "gn:name":"Lijiafang",
    "gn:population":0,
    "gn:timezone":"Asia/Shanghai",
    "iso:country":"CN",
    "name:und_x_variant":[
        "\u674e\u5bb6\u623f"
    ],
    "name:zho_x_preferred":[
        "\u674e\u5bb6\u623f"
    ],
    "wof:name":"Lijiafang",
    "wof:placetype":"locality"
},
  "geometry": {"coordinates":[122.46308000000001,41.4487],"type":"Point"}
}