{
  "type": "Feature",
  "properties": {
    "gn:admin1_code":"05",
    "gn:asciiname":"Kuaidamao",
    "gn:country_code":"CN",
    "gn:dem":517,
    "gn:feature_class":"P",
    "gn:feature_code":"PPLA3",
    "gn:name":"Kuaidamao",
    "gn:population":0,
    "gn:timezone":"Asia/Shanghai",
    "iso:country":"CN",
    "name:deu_x_preferred":[
        "Tonghua"
    ],
    "name:fas_x_preferred":[
        "\u0634\u0647\u0631\u0633\u062a\u0627\u0646 \u062a\u0648\u0646\u06af\u0647\u0648\u0627"
    ],
    "name:jpn_x_preferred":[
        "\u901a\u5316\u770c"
    ],
    "name:kor_x_preferred":[
        "\ud241\ud654\ud604"
    ],
    "name:nor_x_preferred":[
        "Tonghua"
    ],
    "name:pol_x_preferred":[
        "Tonghua"
    ],
    "name:rus_x_preferred":[
        "\u0422\u0443\u043d\u0445\u0443\u0430"
    ],
    "name:swe_x_preferred":[
        "Tonghua"
    ],
    "name:und_x_variant":[
        "Kuaidamao"
    ],
    "name:urd_x_preferred":[
        "\u062a\u0648\u0646\u06af\u06c1\u0648\u0627 \u06a9\u0627\u0624\u0646\u0679\u06cc"
    ],
    "name:vie_x_preferred":[
        "Th\u00f4ng H\u00f3a"
    ],
    "name:zho_x_preferred":[
        "T\u2019ung-hua-hsien"
    ],
    "name:zho_x_variant":[
        "K\u2019uai-tang-mao-tzu",
        "K\u2019uai-ta-mao-tzu",
        "K\u2019uai-ta-mao",
        "\u5feb\u5927\u8302",
        "\u901a\u5316\u53bf"
    ],
    "wof:name":"Kuaidamao",
    "wof:placetype":"locality"
},
  "geometry": {"coordinates":[125.74225,41.65532],"type":"Point"}
}