{
  "type": "Feature",
  "properties": {
    "gn:admin1_code":"05",
    "gn:asciiname":"Kuaidamao",
    "gn:country_code":"CN",
    "gn:dem":517,
    "gn:feature_class":"P",
    "gn:feature_code":"PPLA3",
    "gn:name":"Kuaidamao",
    "gn:population":0,
    "gn:timezone":"Asia/Shanghai",
    "iso:country":"CN",
    "name:und_x_variant":[
        "Tonghua",
        "Kuaidamao"
    ],
    "name:zho_x_preferred":[
        "T\u2019ung-hua-hsien"
    ],
    "name:zho_x_variant":[
        "K\u2019uai-tang-mao-tzu",
        "K\u2019uai-ta-mao-tzu",
        "K\u2019uai-ta-mao",
        "\u5feb\u5927\u8302"
    ],
    "wof:name":"Kuaidamao",
    "wof:placetype":"locality"
},
  "geometry": {"coordinates":[125.74225,41.65532],"type":"Point"}
}