{
  "type": "Feature",
  "properties": {
    "gn:admin1_code":"19.0",
    "gn:asciiname":"Qijianfang",
    "gn:country_code":"CN",
    "gn:dem":74,
    "gn:feature_class":"P",
    "gn:feature_code":"PPL",
    "gn:name":"Qijianfang",
    "gn:population":0,
    "gn:timezone":"Asia/Shanghai",
    "iso:country":"CN",
    "name:und_x_variant":[
        "\u4e03\u95f4\u623f"
    ],
    "wof:name":"Qijianfang",
    "wof:placetype":"locality"
},
  "geometry": {"coordinates":[122.5257,40.48475],"type":"Point"}
}