{
  "type": "Feature",
  "properties": {
    "gn:admin1_code":"29",
    "gn:asciiname":"Muzhanglang",
    "gn:country_code":"CN",
    "gn:dem":1784,
    "gn:feature_class":"P",
    "gn:feature_code":"PPL",
    "gn:name":"Muzhanglang",
    "gn:population":0,
    "gn:timezone":"Asia/Shanghai",
    "iso:country":"CN",
    "name:zho_x_preferred":[
        "\u6728\u7ae0\u90ce"
    ],
    "wof:name":"Muzhanglang",
    "wof:placetype":"locality"
},
  "geometry": {"coordinates":[101.792,24.6529],"type":"Point"}
}