{
  "type": "Feature",
  "properties": {
    "gn:admin1_code":"12.0",
    "gn:asciiname":"Shejia Doupo",
    "gn:country_code":"CN",
    "gn:dem":52,
    "gn:feature_class":"P",
    "gn:feature_code":"PPL",
    "gn:name":"Shejia Doupo",
    "gn:population":0,
    "gn:timezone":"Asia/Shanghai",
    "iso:country":"CN",
    "name:zho_x_preferred":[
        "Shejia Doupo"
    ],
    "name:zho_x_variant":[
        "\u4f58\u5bb6\u9661\u5761"
    ],
    "wof:name":"Shejia Doupo",
    "wof:placetype":"locality"
},
  "geometry": {"coordinates":[111.84773,29.94999],"type":"Point"}
}