{
  "type": "Feature",
  "properties": {
    "gn:admin1_code":"1.0",
    "gn:asciiname":"Nanyangmiaocun",
    "gn:country_code":"CN",
    "gn:dem":29,
    "gn:feature_class":"P",
    "gn:feature_code":"PPL",
    "gn:name":"Nanyangmiaocun",
    "gn:population":0,
    "gn:timezone":"Asia/Shanghai",
    "iso:country":"CN",
    "name:zho_x_preferred":[
        "\u5357\u9633\u5e99\u6751"
    ],
    "wof:name":"Nanyangmiaocun",
    "wof:placetype":"locality"
},
  "geometry": {"coordinates":[116.21373,31.9661],"type":"Point"}
}