{
  "type": "Feature",
  "properties": {
    "gn:admin1_code":"19.0",
    "gn:asciiname":"Dadonggou",
    "gn:country_code":"CN",
    "gn:dem":433,
    "gn:feature_class":"P",
    "gn:feature_code":"PPL",
    "gn:name":"Dadonggou",
    "gn:population":0,
    "gn:timezone":"Asia/Shanghai",
    "iso:country":"CN",
    "name:zho_x_preferred":[
        "\u5927\u4e1c\u6c9f"
    ],
    "wof:name":"Dadonggou",
    "wof:placetype":"locality"
},
  "geometry": {"coordinates":[119.883,41.3861],"type":"Point"}
}