{
  "type": "Feature",
  "properties": {
    "gn:admin1_code":"06",
    "gn:asciiname":"Gyimkar",
    "gn:country_code":"CN",
    "gn:dem":3865,
    "gn:feature_class":"P",
    "gn:feature_code":"PPLA4",
    "gn:name":"Gyimkar",
    "gn:population":0,
    "gn:timezone":"Asia/Shanghai",
    "iso:country":"CN",
    "name:mon_x_preferred":[
        "Gyimkar"
    ],
    "name:und_x_variant":[
        "Jika",
        "Jika Xiang",
        "Jiyao Dangwuda"
    ],
    "name:zho_x_preferred":[
        "\u5409\u5361"
    ],
    "name:zho_x_variant":[
        "\u5409\u5361\u4e61",
        "\u5409\u8981\u5f53\u543e\u8fbe"
    ],
    "wof:name":"Gyimkar",
    "wof:placetype":"locality"
},
  "geometry": {"coordinates":[100.28037999999999,32.81809000000001],"type":"Point"}
}