{
  "type": "Feature",
  "properties": {
    "gn:admin1_code":"20.0",
    "gn:asciiname":"Xinximiao",
    "gn:country_code":"CN",
    "gn:dem":1047,
    "gn:feature_class":"P",
    "gn:feature_code":"PPL",
    "gn:name":"Xinximiao",
    "gn:population":0,
    "gn:timezone":"Asia/Shanghai",
    "iso:country":"CN",
    "name:zho_x_preferred":[
        "\u65b0\u897f\u5e99"
    ],
    "wof:name":"Xinximiao",
    "wof:placetype":"locality"
},
  "geometry": {"coordinates":[100.39022,41.16267],"type":"Point"}
}