{
  "type": "Feature",
  "properties": {
    "gn:admin1_code":"9",
    "gn:asciiname":"Caibai",
    "gn:country_code":"CN",
    "gn:dem":52,
    "gn:feature_class":"P",
    "gn:feature_code":"PPL",
    "gn:name":"Caibai",
    "gn:population":0,
    "gn:timezone":"Asia/Shanghai",
    "iso:country":"CN",
    "name:zho_x_preferred":[
        "\u8521\u767d"
    ],
    "wof:name":"Caibai",
    "wof:placetype":"locality"
},
  "geometry": {"coordinates":[114.88500000000001,33.9423],"type":"Point"}
}