{
  "type": "Feature",
  "properties": {
    "gn:admin1_code":"15.0",
    "gn:asciiname":"Changxianzi",
    "gn:country_code":"CN",
    "gn:dem":2132,
    "gn:feature_class":"P",
    "gn:feature_code":"PPL",
    "gn:name":"Changxianzi",
    "gn:population":0,
    "gn:timezone":"Asia/Shanghai",
    "iso:country":"CN",
    "name:zho_x_preferred":[
        "\u5e38\u5c98\u5b50"
    ],
    "wof:name":"Changxianzi",
    "wof:placetype":"locality"
},
  "geometry": {"coordinates":[105.05500000000001,36.8242],"type":"Point"}
}