{
  "type": "Feature",
  "properties": {
    "gn:admin1_code":"14.0",
    "gn:asciiname":"Xianzikacun",
    "gn:country_code":"CN",
    "gn:dem":4045,
    "gn:feature_class":"P",
    "gn:feature_code":"PPL",
    "gn:name":"Xianzikacun",
    "gn:population":0,
    "gn:timezone":"Asia/Urumqi",
    "iso:country":"CN",
    "name:zho_x_preferred":[
        "\u9c9c\u5b5c\u5494\u6751"
    ],
    "wof:name":"Xianzikacun",
    "wof:placetype":"locality"
},
  "geometry": {"coordinates":[93.84193,31.68724000000001],"type":"Point"}
}