{
  "type": "Feature",
  "properties": {
    "gn:admin1_code":"24.0",
    "gn:asciiname":"Maozeshang",
    "gn:country_code":"CN",
    "gn:dem":1046,
    "gn:feature_class":"P",
    "gn:feature_code":"PPL",
    "gn:name":"Maozeshang",
    "gn:population":0,
    "gn:timezone":"Asia/Shanghai",
    "iso:country":"CN",
    "name:zho_x_preferred":[
        "\u5cc1\u5219\u4e0a"
    ],
    "wof:name":"Maozeshang",
    "wof:placetype":"locality"
},
  "geometry": {"coordinates":[110.75368,37.96046],"type":"Point"}
}