{
  "type": "Feature",
  "properties": {
    "gn:admin1_code":"5.0",
    "gn:asciiname":"Qianyong'antun",
    "gn:country_code":"CN",
    "gn:dem":225,
    "gn:feature_class":"P",
    "gn:feature_code":"PPL",
    "gn:name":"Qianyong\u2019antun",
    "gn:population":0,
    "gn:timezone":"Asia/Shanghai",
    "iso:country":"CN",
    "name:und_x_variant":[
        "Qianyong\u2019antun"
    ],
    "name:zho_x_preferred":[
        "\u524d\u6c38\u5b89\u5c6f"
    ],
    "wof:name":"Qianyong'antun",
    "wof:placetype":"locality"
},
  "geometry": {"coordinates":[126.94835,44.73582],"type":"Point"}
}