{
  "type": "Feature",
  "properties": {
    "gn:admin1_code":"26.0",
    "gn:asciiname":"Mata",
    "gn:country_code":"CN",
    "gn:dem":1197,
    "gn:feature_class":"P",
    "gn:feature_code":"PPL",
    "gn:name":"Mata",
    "gn:population":0,
    "gn:timezone":"Asia/Shanghai",
    "iso:country":"CN",
    "name:bel_x_preferred":[
        "\u041c\u0430\u0442\u0430"
    ],
    "name:bpy_x_preferred":[
        "\u09ae\u09be\u099f\u09be"
    ],
    "name:cat_x_preferred":[
        "Mata"
    ],
    "name:ceb_x_preferred":[
        "Mata"
    ],
    "name:deu_x_preferred":[
        "Mata"
    ],
    "name:fin_x_preferred":[
        "Mata"
    ],
    "name:fra_x_preferred":[
        "Mata"
    ],
    "name:heb_x_preferred":[
        "\u05de\u05d0\u05d8\u05d4"
    ],
    "name:hye_x_preferred":[
        "\u0544\u0561\u057f\u0561"
    ],
    "name:ind_x_preferred":[
        "Mata"
    ],
    "name:ita_x_preferred":[
        "Mata"
    ],
    "name:jav_x_preferred":[
        "Mata"
    ],
    "name:jpn_x_preferred":[
        "\u30de\u30fc\u30bf"
    ],
    "name:lav_x_preferred":[
        "Mata"
    ],
    "name:msa_x_preferred":[
        "Mata"
    ],
    "name:nld_x_preferred":[
        "Mata"
    ],
    "name:pol_x_preferred":[
        "Mata"
    ],
    "name:por_x_preferred":[
        "Mata"
    ],
    "name:rus_x_preferred":[
        "\u041c\u0430\u0442\u0430"
    ],
    "name:spa_x_preferred":[
        "Mata"
    ],
    "name:swe_x_preferred":[
        "Mata"
    ],
    "name:ukr_x_preferred":[
        "\u041c\u0430\u0442\u0430"
    ],
    "name:vie_x_preferred":[
        "Mata"
    ],
    "name:zho_x_preferred":[
        "\u9ebb\u5854"
    ],
    "wof:name":"Mata",
    "wof:placetype":"locality"
},
  "geometry": {"coordinates":[109.5279,36.47191],"type":"Point"}
}