{
  "type": "Feature",
  "properties": {
    "gn:admin1_code":"30.0",
    "gn:asciiname":"Bianjiao",
    "gn:country_code":"CN",
    "gn:dem":-1,
    "gn:feature_class":"P",
    "gn:feature_code":"PPL",
    "gn:name":"Bianjiao",
    "gn:population":0,
    "gn:timezone":"Asia/Shanghai",
    "iso:country":"CN",
    "name:zho_x_preferred":[
        "\u6241\u7a96"
    ],
    "wof:name":"Bianjiao",
    "wof:placetype":"locality"
},
  "geometry": {"coordinates":[113.31283000000001,22.74876],"type":"Point"}
}