{
  "type": "Feature",
  "properties": {
    "gn:admin1_code":"24.0",
    "gn:asciiname":"Yaodi",
    "gn:cc2":"CN",
    "gn:country_code":"CN",
    "gn:dem":1159,
    "gn:feature_class":"P",
    "gn:feature_code":"PPL",
    "gn:name":"Yaodi",
    "gn:population":0,
    "gn:timezone":"Asia/Shanghai",
    "iso:country":"CN",
    "name:und_x_variant":[
        "Yao-ti",
        "Yaodi"
    ],
    "wof:name":"Yaodi",
    "wof:placetype":"locality"
},
  "geometry": {"coordinates":[112.15000000000001,37.65],"type":"Point"}
}