{
  "type": "Feature",
  "properties": {
    "gn:admin1_code":"29.0",
    "gn:asciiname":"Huaguo",
    "gn:country_code":"CN",
    "gn:dem":1953,
    "gn:feature_class":"P",
    "gn:feature_code":"PPL",
    "gn:name":"Huaguo",
    "gn:population":0,
    "gn:timezone":"Asia/Shanghai",
    "iso:country":"CN",
    "name:zho_x_preferred":[
        "\u534e\u56fd"
    ],
    "wof:name":"Huaguo",
    "wof:placetype":"locality"
},
  "geometry": {"coordinates":[103.971,24.5713],"type":"Point"}
}