{
  "type": "Feature",
  "properties": {
    "gn:admin1_code":"29.0",
    "gn:asciiname":"Xiaquzu",
    "gn:country_code":"CN",
    "gn:dem":1568,
    "gn:feature_class":"P",
    "gn:feature_code":"PPL",
    "gn:name":"Xiaquzu",
    "gn:population":0,
    "gn:timezone":"Asia/Shanghai",
    "iso:country":"CN",
    "name:zho_x_preferred":[
        "\u4e0b\u66f2\u7956"
    ],
    "wof:name":"Xiaquzu",
    "wof:placetype":"locality"
},
  "geometry": {"coordinates":[104.215,24.7653],"type":"Point"}
}