{
  "type": "Feature",
  "properties": {
    "gn:admin1_code":"10.0",
    "gn:asciiname":"Lu'anzhuang",
    "gn:country_code":"CN",
    "gn:dem":12,
    "gn:feature_class":"P",
    "gn:feature_code":"PPL",
    "gn:name":"Lu\u2019anzhuang",
    "gn:population":0,
    "gn:timezone":"Asia/Shanghai",
    "iso:country":"CN",
    "name:und_x_variant":[
        "Lu\u2019anzhuang"
    ],
    "name:zho_x_preferred":[
        "\u9c81\u5b89\u5e84"
    ],
    "wof:name":"Lu'anzhuang",
    "wof:placetype":"locality"
},
  "geometry": {"coordinates":[116.613,38.2992],"type":"Point"}
}