{
  "type": "Feature",
  "properties": {
    "gn:admin1_code":"9.0",
    "gn:asciiname":"Housunzhuang",
    "gn:country_code":"CN",
    "gn:dem":57,
    "gn:feature_class":"P",
    "gn:feature_code":"PPL",
    "gn:name":"Housunzhuang",
    "gn:population":0,
    "gn:timezone":"Asia/Shanghai",
    "iso:country":"CN",
    "name:zho_x_preferred":[
        "\u540e\u5b59\u5e84"
    ],
    "wof:name":"Housunzhuang",
    "wof:placetype":"locality"
},
  "geometry": {"coordinates":[114.66123,32.63516],"type":"Point"}
}