{
  "type": "Feature",
  "properties": {
    "gn:admin1_code":"15.0",
    "gn:asciiname":"Huangchuangou",
    "gn:country_code":"CN",
    "gn:dem":1836,
    "gn:feature_class":"P",
    "gn:feature_code":"PPL",
    "gn:name":"Huangchuangou",
    "gn:population":0,
    "gn:timezone":"Asia/Shanghai",
    "iso:country":"CN",
    "name:zho_x_preferred":[
        "\u9ec4\u5ddd\u6c9f"
    ],
    "wof:name":"Huangchuangou",
    "wof:placetype":"locality"
},
  "geometry": {"coordinates":[105.28,36.0322],"type":"Point"}
}