{
  "type": "Feature",
  "properties": {
    "gn:admin1_code":"23.0",
    "gn:asciiname":"Xinshi",
    "gn:cc2":"CN",
    "gn:country_code":"CN",
    "gn:dem":4,
    "gn:feature_class":"P",
    "gn:feature_code":"PPL",
    "gn:name":"Xinshi",
    "gn:population":0,
    "gn:timezone":"Asia/Shanghai",
    "iso:country":"CN",
    "name:ceb_x_preferred":[
        "Xinshi"
    ],
    "name:deu_x_preferred":[
        "Xinshi"
    ],
    "name:eus_x_preferred":[
        "Xinshi"
    ],
    "name:fra_x_preferred":[
        "Xinshi"
    ],
    "name:mlg_x_preferred":[
        "Xinshi"
    ],
    "name:nor_x_preferred":[
        "Xinshi"
    ],
    "name:rus_x_preferred":[
        "\u0421\u0438\u043d\u044c\u0448\u0438"
    ],
    "name:swe_x_preferred":[
        "Xinshi"
    ],
    "name:und_x_variant":[
        "Tung-hsin-shih",
        "Hsin-shih",
        "Tung-hsin-shih-chen",
        "\u65b0\u5e02"
    ],
    "name:vie_x_preferred":[
        "T\u00e2n Th\u1ecb"
    ],
    "wof:name":"Xinshi",
    "wof:placetype":"locality"
},
  "geometry": {"coordinates":[121.66472,30.97278],"type":"Point"}
}