{
  "type": "Feature",
  "properties": {
    "gn:admin1_code":"10",
    "gn:asciiname":"Chande",
    "gn:country_code":"CN",
    "gn:dem":130,
    "gn:feature_class":"P",
    "gn:feature_code":"PPLA4",
    "gn:name":"Chande",
    "gn:population":0,
    "gn:timezone":"Asia/Shanghai",
    "iso:country":"CN",
    "name:und_x_variant":[
        "\u4ea7\u5fb7",
        "Chande Xiang",
        "\u4ea7\u5fb7\u4e61"
    ],
    "wof:name":"Chande",
    "wof:placetype":"locality"
},
  "geometry": {"coordinates":[114.58503,38.64587],"type":"Point"}
}