{
  "type": "Feature",
  "properties": {
    "gn:admin1_code":"1.0",
    "gn:asciiname":"Lusicun",
    "gn:country_code":"CN",
    "gn:dem":22,
    "gn:feature_class":"P",
    "gn:feature_code":"PPL",
    "gn:name":"L\u00fcsicun",
    "gn:population":0,
    "gn:timezone":"Asia/Shanghai",
    "iso:country":"CN",
    "name:und_x_variant":[
        "L\u00fcsicun",
        "L\u00fcsiyuan"
    ],
    "name:zho_x_preferred":[
        "\u5415\u5bfa\u6751"
    ],
    "wof:name":"Lusicun",
    "wof:placetype":"locality"
},
  "geometry": {"coordinates":[116.99167,33.49167],"type":"Point"}
}