{
  "type": "Feature",
  "properties": {
    "gn:admin1_code":"14.0",
    "gn:asciiname":"Baoguoka",
    "gn:country_code":"CN",
    "gn:dem":4375,
    "gn:feature_class":"P",
    "gn:feature_code":"PPL",
    "gn:name":"Baoguoka",
    "gn:population":0,
    "gn:timezone":"Asia/Urumqi",
    "iso:country":"CN",
    "name:zho_x_preferred":[
        "\u5305\u679c\u5361"
    ],
    "wof:name":"Baoguoka",
    "wof:placetype":"locality"
},
  "geometry": {"coordinates":[97.07312,31.05896],"type":"Point"}
}