{
  "type": "Feature",
  "properties": {
    "gn:admin1_code":"1.0",
    "gn:asciiname":"Qiuqiaocun",
    "gn:country_code":"CN",
    "gn:dem":22,
    "gn:feature_class":"P",
    "gn:feature_code":"PPL",
    "gn:name":"Qiuqiaocun",
    "gn:population":0,
    "gn:timezone":"Asia/Shanghai",
    "iso:country":"CN",
    "name:zho_x_preferred":[
        "\u90b1\u6865\u6751"
    ],
    "wof:name":"Qiuqiaocun",
    "wof:placetype":"locality"
},
  "geometry": {"coordinates":[117.38625999999999,32.90375],"type":"Point"}
}