{
  "type": "Feature",
  "properties": {
    "gn:admin1_code":"29.0",
    "gn:asciiname":"Ajiju",
    "gn:country_code":"CN",
    "gn:dem":2150,
    "gn:feature_class":"P",
    "gn:feature_code":"PPL",
    "gn:name":"Ajiju",
    "gn:population":0,
    "gn:timezone":"Asia/Shanghai",
    "iso:country":"CN",
    "name:zho_x_preferred":[
        "\u963f\u57fa\u82f4"
    ],
    "wof:name":"Ajiju",
    "wof:placetype":"locality"
},
  "geometry": {"coordinates":[101.039,25.7148],"type":"Point"}
}