{
  "type": "Feature",
  "properties": {
    "gn:admin1_code":"29.0",
    "gn:asciiname":"Baijixun",
    "gn:cc2":"CN",
    "gn:country_code":"CN",
    "gn:dem":1814,
    "gn:feature_class":"P",
    "gn:feature_code":"PPL",
    "gn:name":"Baijixun",
    "gn:population":0,
    "gn:timezone":"Asia/Shanghai",
    "iso:country":"CN",
    "name:und_x_variant":[
        "Pai-chi",
        "Baijixun"
    ],
    "wof:name":"Baijixun",
    "wof:placetype":"locality"
},
  "geometry": {"coordinates":[99.09999999999999,27.33333],"type":"Point"}
}