{
  "type": "Feature",
  "properties": {
    "gn:admin1_code":"30",
    "gn:asciiname":"Huangfengliu",
    "gn:country_code":"CN",
    "gn:dem":792,
    "gn:feature_class":"P",
    "gn:feature_code":"PPL",
    "gn:name":"Huangfengliu",
    "gn:population":0,
    "gn:timezone":"Asia/Shanghai",
    "iso:country":"CN",
    "name:zho_x_preferred":[
        "\u9ec4\u5cf0\u6e9c"
    ],
    "wof:name":"Huangfengliu",
    "wof:placetype":"locality"
},
  "geometry": {"coordinates":[116.03243999999999,23.84655],"type":"Point"}
}