{
  "type": "Feature",
  "properties": {
    "gn:admin1_code":"4.0",
    "gn:asciiname":"Santangcun",
    "gn:country_code":"CN",
    "gn:dem":37,
    "gn:feature_class":"P",
    "gn:feature_code":"PPL",
    "gn:name":"Santangcun",
    "gn:population":0,
    "gn:timezone":"Asia/Shanghai",
    "iso:country":"CN",
    "name:und_x_variant":[
        "Santang",
        "Santangcun"
    ],
    "name:zho_x_preferred":[
        "\u4e09\u5858"
    ],
    "name:zho_x_variant":[
        "\u4e09\u5858\u6751"
    ],
    "wof:name":"Santangcun",
    "wof:placetype":"locality"
},
  "geometry": {"coordinates":[118.53570999999999,32.96149],"type":"Point"}
}