{
  "type": "Feature",
  "properties": {
    "gn:admin1_code":"4.0",
    "gn:asciiname":"Yangjia Menkou",
    "gn:country_code":"CN",
    "gn:dem":3,
    "gn:feature_class":"P",
    "gn:feature_code":"PPL",
    "gn:name":"Yangjia Menkou",
    "gn:population":0,
    "gn:timezone":"Asia/Shanghai",
    "iso:country":"CN",
    "name:zho_x_preferred":[
        "\u6768\u5bb6\u95e8\u53e3"
    ],
    "wof:name":"Yangjia Menkou",
    "wof:placetype":"locality"
},
  "geometry": {"coordinates":[120.94302999999999,31.86174],"type":"Point"}
}