{
  "type": "Feature",
  "properties": {
    "gn:admin1_code":"15.0",
    "gn:asciiname":"Qianjiawan",
    "gn:country_code":"CN",
    "gn:dem":1999,
    "gn:feature_class":"P",
    "gn:feature_code":"PPL",
    "gn:name":"Qianjiawan",
    "gn:population":0,
    "gn:timezone":"Asia/Shanghai",
    "iso:country":"CN",
    "name:zho_x_preferred":[
        "\u5343\u5bb6\u6e7e"
    ],
    "wof:name":"Qianjiawan",
    "wof:placetype":"locality"
},
  "geometry": {"coordinates":[104.751,35.3095],"type":"Point"}
}