{
  "type": "Feature",
  "properties": {
    "gn:admin1_code":"14.0",
    "gn:asciiname":"Nyilung",
    "gn:country_code":"CN",
    "gn:dem":3959,
    "gn:feature_class":"P",
    "gn:feature_code":"PPLF",
    "gn:name":"Nyilung",
    "gn:population":0,
    "gn:timezone":"Asia/Urumqi",
    "iso:country":"CN",
    "name:bod_x_preferred":[
        "Nyilung"
    ],
    "name:zho_x_preferred":[
        "Nilong"
    ],
    "name:zho_x_variant":[
        "\u5c3c\u9f99",
        "Wangnai",
        "\u65fa\u4e43"
    ],
    "wof:name":"Nyilung",
    "wof:placetype":"locality"
},
  "geometry": {"coordinates":[93.80200000000001,31.502],"type":"Point"}
}