{
  "type": "Feature",
  "properties": {
    "gn:admin1_code":"30.0",
    "gn:asciiname":"Fengwu",
    "gn:country_code":"CN",
    "gn:dem":457,
    "gn:feature_class":"P",
    "gn:feature_code":"PPL",
    "gn:name":"Fengwu",
    "gn:population":0,
    "gn:timezone":"Asia/Shanghai",
    "iso:country":"CN",
    "name:zho_x_preferred":[
        "\u51af\u5c4b"
    ],
    "wof:name":"Fengwu",
    "wof:placetype":"locality"
},
  "geometry": {"coordinates":[113.75879999999999,24.54329],"type":"Point"}
}