{
  "type": "Feature",
  "properties": {
    "gn:admin1_code":"14.0",
    "gn:asciiname":"Rinacun",
    "gn:country_code":"CN",
    "gn:dem":3862,
    "gn:feature_class":"P",
    "gn:feature_code":"PPL",
    "gn:name":"Rinacun",
    "gn:population":0,
    "gn:timezone":"Asia/Urumqi",
    "iso:country":"CN",
    "name:zho_x_preferred":[
        "\u65e5\u90a3\u6751"
    ],
    "wof:name":"Rinacun",
    "wof:placetype":"locality"
},
  "geometry": {"coordinates":[92.55838,28.94811],"type":"Point"}
}