{
  "type": "Feature",
  "properties": {
    "gn:admin1_code":"25",
    "gn:asciiname":"Zhailiji",
    "gn:country_code":"CN",
    "gn:dem":40,
    "gn:feature_class":"P",
    "gn:feature_code":"PPL",
    "gn:name":"Zhailiji",
    "gn:population":0,
    "gn:timezone":"Asia/Shanghai",
    "iso:country":"CN",
    "name:zho_x_preferred":[
        "\u5be8\u91cc\u96c6"
    ],
    "wof:name":"Zhailiji",
    "wof:placetype":"locality"
},
  "geometry": {"coordinates":[116.26900000000001,34.9911],"type":"Point"}
}