{
  "type": "Feature",
  "properties": {
    "gn:admin1_code":"14",
    "gn:asciiname":"Zhiruocegaqie Kangba",
    "gn:country_code":"CN",
    "gn:dem":4723,
    "gn:feature_class":"P",
    "gn:feature_code":"PPL",
    "gn:name":"Zhiruocegaqie Kangba",
    "gn:population":0,
    "gn:timezone":"Asia/Urumqi",
    "iso:country":"CN",
    "name:zho_x_preferred":[
        "\u76f4\u82e5\u4fa7\u5c15\u5207\u5eb7\u5df4"
    ],
    "wof:name":"Zhiruocegaqie Kangba",
    "wof:placetype":"locality"
},
  "geometry": {"coordinates":[89.116,32.3161],"type":"Point"}
}