{
  "type": "Feature",
  "properties": {
    "gn:admin1_code":"19.0",
    "gn:asciiname":"Lianhetun",
    "gn:country_code":"CN",
    "gn:dem":90,
    "gn:feature_class":"P",
    "gn:feature_code":"PPL",
    "gn:name":"Lianhetun",
    "gn:population":0,
    "gn:timezone":"Asia/Shanghai",
    "iso:country":"CN",
    "name:zho_x_preferred":[
        "\u8054\u5408\u5c6f"
    ],
    "wof:name":"Lianhetun",
    "wof:placetype":"locality"
},
  "geometry": {"coordinates":[123.744,42.9744],"type":"Point"}
}