{
  "type": "Feature",
  "properties": {
    "gn:admin1_code":"32.0",
    "gn:asciiname":"Hexincun",
    "gn:country_code":"CN",
    "gn:dem":922,
    "gn:feature_class":"P",
    "gn:feature_code":"PPL",
    "gn:name":"Hexincun",
    "gn:population":0,
    "gn:timezone":"Asia/Shanghai",
    "iso:country":"CN",
    "name:zho_x_preferred":[
        "\u76d2\u65b0\u6751"
    ],
    "wof:name":"Hexincun",
    "wof:placetype":"locality"
},
  "geometry": {"coordinates":[105.29300000000001,32.6213],"type":"Point"}
}