{
  "type": "Feature",
  "properties": {
    "gn:admin1_code":"12.0",
    "gn:asciiname":"Wangjiadian",
    "gn:country_code":"CN",
    "gn:dem":29,
    "gn:feature_class":"P",
    "gn:feature_code":"PPL",
    "gn:name":"Wangjiadian",
    "gn:population":0,
    "gn:timezone":"Asia/Shanghai",
    "iso:country":"CN",
    "name:zho_x_preferred":[
        "Wangjiadian"
    ],
    "name:zho_x_variant":[
        "\u738b\u5bb6\u5e97"
    ],
    "wof:name":"Wangjiadian",
    "wof:placetype":"locality"
},
  "geometry": {"coordinates":[115.03165,30.58272],"type":"Point"}
}