{
  "type": "Feature",
  "properties": {
    "gn:admin1_code":"3.0",
    "gn:asciiname":"Shangjie",
    "gn:country_code":"CN",
    "gn:dem":201,
    "gn:feature_class":"P",
    "gn:feature_code":"PPL",
    "gn:name":"Shangjie",
    "gn:population":0,
    "gn:timezone":"Asia/Shanghai",
    "iso:country":"CN",
    "name:und_x_variant":[
        "\u4e0a\u8857"
    ],
    "wof:name":"Shangjie",
    "wof:placetype":"locality"
},
  "geometry": {"coordinates":[115.22443,25.99778],"type":"Point"}
}