{
  "type": "Feature",
  "properties": {
    "gn:admin1_code":"3.0",
    "gn:asciiname":"Honggang Linchang",
    "gn:country_code":"CN",
    "gn:dem":66,
    "gn:feature_class":"P",
    "gn:feature_code":"PPLF",
    "gn:name":"Honggang Linchang",
    "gn:population":0,
    "gn:timezone":"Asia/Shanghai",
    "iso:country":"CN",
    "name:und_x_variant":[
        "\u7ea2\u5c97\u6797\u573a"
    ],
    "wof:name":"Honggang Linchang",
    "wof:placetype":"locality"
},
  "geometry": {"coordinates":[115.40022,28.79591],"type":"Point"}
}