{
  "type": "Feature",
  "properties": {
    "gn:admin1_code":"8.0",
    "gn:asciiname":"Huangsong Jingyingsuo Lindui",
    "gn:country_code":"CN",
    "gn:dem":554,
    "gn:feature_class":"P",
    "gn:feature_code":"PPLF",
    "gn:name":"Huangsong Jingyingsuo Lindui",
    "gn:population":0,
    "gn:timezone":"Asia/Shanghai",
    "iso:country":"CN",
    "name:und_x_variant":[
        "\u9ec4\u677e\u7ecf\u8425\u6240\u6797\u961f"
    ],
    "wof:name":"Huangsong Jingyingsuo Lindui",
    "wof:placetype":"locality"
},
  "geometry": {"coordinates":[130.55186,44.04821],"type":"Point"}
}