{
  "type": "Feature",
  "properties": {
    "gn:admin1_code":"12.0",
    "gn:asciiname":"Zhujia Wuji",
    "gn:country_code":"CN",
    "gn:dem":63,
    "gn:feature_class":"P",
    "gn:feature_code":"PPL",
    "gn:name":"Zhujia Wuji",
    "gn:population":0,
    "gn:timezone":"Asia/Shanghai",
    "iso:country":"CN",
    "name:zho_x_preferred":[
        "Zhujia Wuji"
    ],
    "name:zho_x_variant":[
        "\u6731\u5bb6\u5c4b\u57fa"
    ],
    "wof:name":"Zhujia Wuji",
    "wof:placetype":"locality"
},
  "geometry": {"coordinates":[115.02187000000001,30.67221],"type":"Point"}
}