{
  "type": "Feature",
  "properties": {
    "gn:admin1_code":"32.0",
    "gn:asciiname":"Yinjiaping",
    "gn:country_code":"CN",
    "gn:dem":576,
    "gn:feature_class":"P",
    "gn:feature_code":"PPL",
    "gn:name":"Yinjiaping",
    "gn:population":0,
    "gn:timezone":"Asia/Shanghai",
    "iso:country":"CN",
    "name:zho_x_preferred":[
        "\u6bb7\u5bb6\u576a"
    ],
    "wof:name":"Yinjiaping",
    "wof:placetype":"locality"
},
  "geometry": {"coordinates":[106.006,28.8413],"type":"Point"}
}