{
  "type": "Feature",
  "properties": {
    "gn:admin1_code":"14.0",
    "gn:asciiname":"Xianga",
    "gn:country_code":"CN",
    "gn:dem":4739,
    "gn:feature_class":"P",
    "gn:feature_code":"PPL",
    "gn:name":"Xianga",
    "gn:population":0,
    "gn:timezone":"Asia/Urumqi",
    "iso:country":"CN",
    "name:zho_x_preferred":[
        "\u8d24\u560e"
    ],
    "wof:name":"Xianga",
    "wof:placetype":"locality"
},
  "geometry": {"coordinates":[91.06653,30.8024],"type":"Point"}
}