{
  "type": "Feature",
  "properties": {
    "gn:admin1_code":"33.0",
    "gn:asciiname":"Zongde",
    "gn:country_code":"CN",
    "gn:dem":232,
    "gn:feature_class":"P",
    "gn:feature_code":"PPL",
    "gn:name":"Zongde",
    "gn:population":0,
    "gn:timezone":"Asia/Shanghai",
    "iso:country":"CN",
    "name:zho_x_preferred":[
        "\u5b97\u5fb7"
    ],
    "wof:name":"Zongde",
    "wof:placetype":"locality"
},
  "geometry": {"coordinates":[106.59,29.0068],"type":"Point"}
}