{
  "type": "Feature",
  "properties": {
    "gn:admin1_code":"02",
    "gn:asciiname":"Dulangping",
    "gn:country_code":"CN",
    "gn:dem":6,
    "gn:feature_class":"P",
    "gn:feature_code":"PPL",
    "gn:name":"Dulangping",
    "gn:population":0,
    "gn:timezone":"Asia/Shanghai",
    "iso:country":"CN",
    "name:und_x_variant":[
        "\u675c\u90ce\u576a"
    ],
    "name:zho_x_preferred":[
        "\u675c\u90ce\u576a"
    ],
    "wof:name":"Dulangping",
    "wof:placetype":"locality"
},
  "geometry": {"coordinates":[121.35138999999999,29.71556],"type":"Point"}
}