{
  "type": "Feature",
  "properties": {
    "gn:admin1_code":"16.0",
    "gn:asciiname":"Shifu",
    "gn:country_code":"CN",
    "gn:dem":224,
    "gn:feature_class":"P",
    "gn:feature_code":"PPL",
    "gn:name":"Shifu",
    "gn:population":0,
    "gn:timezone":"Asia/Shanghai",
    "iso:country":"CN",
    "name:ast_x_preferred":[
        "Sifu"
    ],
    "name:deu_x_preferred":[
        "Shifu"
    ],
    "name:fas_x_preferred":[
        "\u0633\u06cc\u200c\u0641\u0648"
    ],
    "name:fra_x_preferred":[
        "Sifu"
    ],
    "name:ind_x_preferred":[
        "Suhu"
    ],
    "name:ita_x_preferred":[
        "Shifu"
    ],
    "name:nld_x_preferred":[
        "Sifu"
    ],
    "name:pol_x_preferred":[
        "Sifu"
    ],
    "name:por_x_preferred":[
        "Sifu"
    ],
    "name:spa_x_preferred":[
        "Shifu"
    ],
    "name:vie_x_preferred":[
        "S\u01b0 ph\u1ee5"
    ],
    "name:zho_x_preferred":[
        "\u77f3\u4ed8"
    ],
    "wof:name":"Shifu",
    "wof:placetype":"locality"
},
  "geometry": {"coordinates":[108.233,24.8716],"type":"Point"}
}