{
  "type": "Feature",
  "properties": {
    "gn:admin1_code":"14",
    "gn:asciiname":"Jiubu",
    "gn:country_code":"CN",
    "gn:dem":3921,
    "gn:feature_class":"P",
    "gn:feature_code":"PPL",
    "gn:name":"Jiubu",
    "gn:population":0,
    "gn:timezone":"Asia/Urumqi",
    "iso:country":"CN",
    "name:zho_x_preferred":[
        "\u4e45\u5e03"
    ],
    "wof:name":"Jiubu",
    "wof:placetype":"locality"
},
  "geometry": {"coordinates":[89.2615,29.0476],"type":"Point"}
}