{
  "type": "Feature",
  "properties": {
    "gn:admin1_code":"8.0",
    "gn:asciiname":"Liangzhanwu",
    "gn:country_code":"CN",
    "gn:dem":209,
    "gn:feature_class":"P",
    "gn:feature_code":"PPL",
    "gn:name":"Liangzhanwu",
    "gn:population":0,
    "gn:timezone":"Asia/Shanghai",
    "iso:country":"CN",
    "name:zho_x_preferred":[
        "\u6881\u5360\u6b66"
    ],
    "wof:name":"Liangzhanwu",
    "wof:placetype":"locality"
},
  "geometry": {"coordinates":[127.56685,47.01426],"type":"Point"}
}