{
  "type": "Feature",
  "properties": {
    "gn:admin1_code":"1.0",
    "gn:asciiname":"Yuwancun",
    "gn:country_code":"CN",
    "gn:dem":29,
    "gn:feature_class":"P",
    "gn:feature_code":"PPL",
    "gn:name":"Yuwancun",
    "gn:population":0,
    "gn:timezone":"Asia/Shanghai",
    "iso:country":"CN",
    "name:zho_x_preferred":[
        "\u4e8e\u6e7e\u6751"
    ],
    "wof:name":"Yuwancun",
    "wof:placetype":"locality"
},
  "geometry": {"coordinates":[117.40430000000001,31.9281],"type":"Point"}
}