{
  "type": "Feature",
  "properties": {
    "gn:admin1_code":"12.0",
    "gn:asciiname":"Nongkezhan",
    "gn:country_code":"CN",
    "gn:dem":561,
    "gn:feature_class":"P",
    "gn:feature_code":"PPL",
    "gn:name":"Nongkezhan",
    "gn:population":0,
    "gn:timezone":"Asia/Shanghai",
    "iso:country":"CN",
    "name:zho_x_preferred":[
        "\u519c\u79d1\u7ad9"
    ],
    "wof:name":"Nongkezhan",
    "wof:placetype":"locality"
},
  "geometry": {"coordinates":[108.51588999999998,29.76131],"type":"Point"}
}