{
  "type": "Feature",
  "properties": {
    "gn:admin1_code":"26.0",
    "gn:asciiname":"Wangyaocun",
    "gn:country_code":"CN",
    "gn:dem":1062,
    "gn:feature_class":"P",
    "gn:feature_code":"PPL",
    "gn:name":"Wangyaocun",
    "gn:population":0,
    "gn:timezone":"Asia/Shanghai",
    "iso:country":"CN",
    "name:zho_x_preferred":[
        "\u738b\u7a91\u6751"
    ],
    "wof:name":"Wangyaocun",
    "wof:placetype":"locality"
},
  "geometry": {"coordinates":[110.38500000000001,34.22025],"type":"Point"}
}