{
  "type": "Feature",
  "properties": {
    "gn:admin1_code":"18.0",
    "gn:asciiname":"Lingwa",
    "gn:country_code":"CN",
    "gn:dem":602,
    "gn:feature_class":"P",
    "gn:feature_code":"PPL",
    "gn:name":"Lingwa",
    "gn:population":0,
    "gn:timezone":"Asia/Shanghai",
    "iso:country":"CN",
    "name:zho_x_preferred":[
        "\u4ee4\u5a03"
    ],
    "wof:name":"Lingwa",
    "wof:placetype":"locality"
},
  "geometry": {"coordinates":[108.672,25.8444],"type":"Point"}
}