{
  "type": "Feature",
  "properties": {
    "gn:admin1_code":"32.0",
    "gn:asciiname":"Wangdedi",
    "gn:country_code":"CN",
    "gn:dem":4566,
    "gn:feature_class":"P",
    "gn:feature_code":"PPL",
    "gn:name":"Wangdedi",
    "gn:population":0,
    "gn:timezone":"Asia/Shanghai",
    "iso:country":"CN",
    "name:zho_x_preferred":[
        "\u738b\u5f97\u4f4e"
    ],
    "wof:name":"Wangdedi",
    "wof:placetype":"locality"
},
  "geometry": {"coordinates":[101.2004,29.23395],"type":"Point"}
}