{
  "type": "Feature",
  "properties": {
    "gn:admin1_code":"4.0",
    "gn:asciiname":"Liuxudai",
    "gn:country_code":"CN",
    "gn:dem":17,
    "gn:feature_class":"P",
    "gn:feature_code":"PPL",
    "gn:name":"Liuxudai",
    "gn:population":0,
    "gn:timezone":"Asia/Shanghai",
    "iso:country":"CN",
    "name:zho_x_preferred":[
        "\u516d\u5729\u57ed"
    ],
    "wof:name":"Liuxudai",
    "wof:placetype":"locality"
},
  "geometry": {"coordinates":[119.33962,31.59851],"type":"Point"}
}