{
  "type": "Feature",
  "properties": {
    "gn:admin1_code":"8.0",
    "gn:asciiname":"Dongxiaoshan",
    "gn:country_code":"CN",
    "gn:dem":195,
    "gn:feature_class":"P",
    "gn:feature_code":"PPL",
    "gn:name":"Dongxiaoshan",
    "gn:population":0,
    "gn:timezone":"Asia/Shanghai",
    "iso:country":"CN",
    "name:zho_x_preferred":[
        "\u4e1c\u5c0f\u5c71"
    ],
    "wof:name":"Dongxiaoshan",
    "wof:placetype":"locality"
},
  "geometry": {"coordinates":[127.62326000000002,44.96972],"type":"Point"}
}