{
  "type": "Feature",
  "properties": {
    "gn:admin1_code":"25.0",
    "gn:asciiname":"Songqian",
    "gn:country_code":"CN",
    "gn:dem":13,
    "gn:feature_class":"P",
    "gn:feature_code":"PPL",
    "gn:name":"Songqian",
    "gn:population":0,
    "gn:timezone":"Asia/Shanghai",
    "iso:country":"CN",
    "name:zho_x_preferred":[
        "\u5d69\u524d"
    ],
    "wof:name":"Songqian",
    "wof:placetype":"locality"
},
  "geometry": {"coordinates":[120.71422,37.97996],"type":"Point"}
}