{
  "type": "Feature",
  "properties": {
    "gn:admin1_code":"29.0",
    "gn:asciiname":"Kesi",
    "gn:country_code":"CN",
    "gn:dem":2119,
    "gn:feature_class":"P",
    "gn:feature_code":"PPL",
    "gn:name":"Kesi",
    "gn:population":0,
    "gn:timezone":"Asia/Shanghai",
    "iso:country":"CN",
    "name:zho_x_preferred":[
        "\u67ef\u65af"
    ],
    "wof:name":"Kesi",
    "wof:placetype":"locality"
},
  "geometry": {"coordinates":[99.3335,27.5685],"type":"Point"}
}