{
  "type": "Feature",
  "properties": {
    "gn:admin1_code":"4.0",
    "gn:asciiname":"Xiache",
    "gn:country_code":"CN",
    "gn:dem":1,
    "gn:feature_class":"P",
    "gn:feature_code":"PPLA4",
    "gn:name":"Xiache",
    "gn:population":0,
    "gn:timezone":"Asia/Shanghai",
    "iso:country":"CN",
    "name:und_x_variant":[
        "\u4e0b\u8f66",
        "Xiachejie",
        "Xiache Xiang",
        "\u4e0b\u8f66\u4e61"
    ],
    "wof:name":"Xiache",
    "wof:placetype":"locality"
},
  "geometry": {"coordinates":[119.31667,34.35],"type":"Point"}
}