{
  "type": "Feature",
  "properties": {
    "gn:admin1_code":"25.0",
    "gn:asciiname":"Yaokoucun",
    "gn:country_code":"CN",
    "gn:dem":86,
    "gn:feature_class":"P",
    "gn:feature_code":"PPL",
    "gn:name":"Yaokoucun",
    "gn:population":0,
    "gn:timezone":"Asia/Shanghai",
    "iso:country":"CN",
    "name:zho_x_preferred":[
        "\u7a91\u53e3\u6751"
    ],
    "wof:name":"Yaokoucun",
    "wof:placetype":"locality"
},
  "geometry": {"coordinates":[121.66585000000001,37.35151],"type":"Point"}
}