{
  "type": "Feature",
  "properties": {
    "gn:admin1_code":"9",
    "gn:asciiname":"Liuzhai",
    "gn:country_code":"CN",
    "gn:dem":45,
    "gn:feature_class":"P",
    "gn:feature_code":"PPL",
    "gn:name":"Liuzhai",
    "gn:population":0,
    "gn:timezone":"Asia/Shanghai",
    "iso:country":"CN",
    "name:zho_x_preferred":[
        "\u5218\u5be8"
    ],
    "wof:name":"Liuzhai",
    "wof:placetype":"locality"
},
  "geometry": {"coordinates":[115.44598999999999,36.07624000000001],"type":"Point"}
}