{
  "type": "Feature",
  "properties": {
    "gn:admin1_code":"7.0",
    "gn:asciiname":"Puli",
    "gn:country_code":"CN",
    "gn:dem":167,
    "gn:feature_class":"P",
    "gn:feature_code":"PPL",
    "gn:name":"Puli",
    "gn:population":0,
    "gn:timezone":"Asia/Shanghai",
    "iso:country":"CN",
    "name:ceb_x_preferred":[
        "Puli"
    ],
    "name:deu_x_preferred":[
        "Puli"
    ],
    "name:epo_x_preferred":[
        "Puli"
    ],
    "name:hun_x_preferred":[
        "Puli"
    ],
    "name:nld_x_preferred":[
        "Puli"
    ],
    "name:spa_x_preferred":[
        "Puli"
    ],
    "name:swe_x_preferred":[
        "Puli"
    ],
    "name:zho_x_preferred":[
        "\u666e\u793c"
    ],
    "wof:name":"Puli",
    "wof:placetype":"locality"
},
  "geometry": {"coordinates":[119.20578999999999,25.76364],"type":"Point"}
}