{
  "type": "Feature",
  "properties": {
    "gn:admin1_code":"25",
    "gn:asciiname":"Haogangtun",
    "gn:country_code":"CN",
    "gn:dem":48,
    "gn:feature_class":"P",
    "gn:feature_code":"PPL",
    "gn:name":"Haogangtun",
    "gn:population":0,
    "gn:timezone":"Asia/Shanghai",
    "iso:country":"CN",
    "name:zho_x_preferred":[
        "\u90dd\u5c97\u5c6f"
    ],
    "wof:name":"Haogangtun",
    "wof:placetype":"locality"
},
  "geometry": {"coordinates":[115.70775,35.14374],"type":"Point"}
}