{
  "type": "Feature",
  "properties": {
    "gn:admin1_code":"19.0",
    "gn:asciiname":"Dong'ertaizi",
    "gn:country_code":"CN",
    "gn:dem":94,
    "gn:feature_class":"P",
    "gn:feature_code":"PPL",
    "gn:name":"Dong\u2019ertaizi",
    "gn:population":0,
    "gn:timezone":"Asia/Shanghai",
    "iso:country":"CN",
    "name:und_x_variant":[
        "\u4e1c\u4e8c\u53f0\u5b50"
    ],
    "name:zho_x_preferred":[
        "Dong\u2019ertaizi"
    ],
    "name:zho_x_variant":[
        "\u4e1c\u4e8c\u53f0\u5b50"
    ],
    "wof:name":"Dong'ertaizi",
    "wof:placetype":"locality"
},
  "geometry": {"coordinates":[123.52552,42.53457],"type":"Point"}
}