{
  "type": "Feature",
  "properties": {
    "gn:admin1_code":"14.0",
    "gn:asciiname":"Liangguo",
    "gn:country_code":"CN",
    "gn:dem":3863,
    "gn:feature_class":"P",
    "gn:feature_code":"PPL",
    "gn:name":"Liangguo",
    "gn:population":0,
    "gn:timezone":"Asia/Urumqi",
    "iso:country":"CN",
    "name:zho_x_preferred":[
        "\u6881\u8fc7"
    ],
    "wof:name":"Liangguo",
    "wof:placetype":"locality"
},
  "geometry": {"coordinates":[90.47611000000001,29.27892],"type":"Point"}
}