{
  "type": "Feature",
  "properties": {
    "gn:admin1_code":"29.0",
    "gn:asciiname":"Shangpucang",
    "gn:country_code":"CN",
    "gn:dem":2011,
    "gn:feature_class":"P",
    "gn:feature_code":"PPL",
    "gn:name":"Shangpucang",
    "gn:population":0,
    "gn:timezone":"Asia/Shanghai",
    "iso:country":"CN",
    "name:zho_x_preferred":[
        "\u4e0a\u666e\u4ed3"
    ],
    "wof:name":"Shangpucang",
    "wof:placetype":"locality"
},
  "geometry": {"coordinates":[104.194,26.3546],"type":"Point"}
}