{
  "type": "Feature",
  "properties": {
    "gn:admin1_code":"29",
    "gn:asciiname":"Nan-ting-ma-chieh",
    "gn:country_code":"CN",
    "gn:dem":230,
    "gn:feature_class":"P",
    "gn:feature_code":"PPL",
    "gn:name":"Nan-ting-ma-chieh",
    "gn:population":0,
    "gn:timezone":"Asia/Shanghai",
    "iso:country":"CN",
    "wof:name":"Nan-ting-ma-chieh",
    "wof:placetype":"locality"
},
  "geometry": {"coordinates":[103.90944,22.65556],"type":"Point"}
}