{
  "type": "Feature",
  "properties": {
    "gn:admin1_code":"30",
    "gn:asciiname":"Luyue",
    "gn:country_code":"CN",
    "gn:dem":24,
    "gn:feature_class":"P",
    "gn:feature_code":"PPL",
    "gn:name":"Luyue",
    "gn:population":0,
    "gn:timezone":"Asia/Urumqi",
    "iso:country":"CN",
    "name:zho_x_preferred":[
        "\u7984\u5cb3"
    ],
    "wof:name":"Luyue",
    "wof:placetype":"locality"
},
  "geometry": {"coordinates":[111.34238999999999,21.59436],"type":"Point"}
}