{
  "type": "Feature",
  "properties": {
    "gn:admin1_code":"15.0",
    "gn:asciiname":"Jingjiadian",
    "gn:country_code":"CN",
    "gn:dem":1414,
    "gn:feature_class":"P",
    "gn:feature_code":"PPL",
    "gn:name":"Jingjiadian",
    "gn:population":0,
    "gn:timezone":"Asia/Shanghai",
    "iso:country":"CN",
    "name:zho_x_preferred":[
        "\u666f\u5bb6\u5e97"
    ],
    "wof:name":"Jingjiadian",
    "wof:placetype":"locality"
},
  "geometry": {"coordinates":[107.03100000000001,35.2269],"type":"Point"}
}