{
  "type": "Feature",
  "properties": {
    "gn:admin1_code":"32.0",
    "gn:asciiname":"Niu'erwan",
    "gn:country_code":"CN",
    "gn:dem":351,
    "gn:feature_class":"P",
    "gn:feature_code":"PPL",
    "gn:name":"Niu\u2019erwan",
    "gn:population":0,
    "gn:timezone":"Asia/Shanghai",
    "iso:country":"CN",
    "name:und_x_variant":[
        "Niu\u2019erwan"
    ],
    "name:zho_x_preferred":[
        "\u725b\u513f\u6e7e"
    ],
    "wof:name":"Niu'erwan",
    "wof:placetype":"locality"
},
  "geometry": {"coordinates":[104.79900000000001,29.8262],"type":"Point"}
}