{
  "type": "Feature",
  "properties": {
    "gn:admin1_code":"15.0",
    "gn:asciiname":"Tongchangkou",
    "gn:country_code":"CN",
    "gn:dem":2102,
    "gn:feature_class":"P",
    "gn:feature_code":"PPL",
    "gn:name":"Tongchangkou",
    "gn:population":0,
    "gn:timezone":"Asia/Urumqi",
    "iso:country":"CN",
    "wof:name":"Tongchangkou",
    "wof:placetype":"locality"
},
  "geometry": {"coordinates":[96.96666999999999,41.53333],"type":"Point"}
}