{
  "type": "Feature",
  "properties": {
    "gn:admin1_code":"7.0",
    "gn:asciiname":"Beilingxia",
    "gn:country_code":"CN",
    "gn:dem":29,
    "gn:feature_class":"P",
    "gn:feature_code":"PPL",
    "gn:name":"Beilingxia",
    "gn:population":0,
    "gn:timezone":"Asia/Shanghai",
    "iso:country":"CN",
    "name:und_x_variant":[
        "\u5317\u5cad\u4e0b"
    ],
    "name:zho_x_preferred":[
        "Beilingxia"
    ],
    "wof:name":"Beilingxia",
    "wof:placetype":"locality"
},
  "geometry": {"coordinates":[119.32884,26.15007],"type":"Point"}
}