{
  "type": "Feature",
  "properties": {
    "gn:admin1_code":"16.0",
    "gn:asciiname":"Gebanshan",
    "gn:country_code":"CN",
    "gn:dem":46,
    "gn:feature_class":"P",
    "gn:feature_code":"PPL",
    "gn:name":"Gebanshan",
    "gn:population":0,
    "gn:timezone":"Asia/Shanghai",
    "iso:country":"CN",
    "name:zho_x_preferred":[
        "\u5272\u677f\u5c71"
    ],
    "wof:name":"Gebanshan",
    "wof:placetype":"locality"
},
  "geometry": {"coordinates":[108.601,22.0244],"type":"Point"}
}