{
  "type": "Feature",
  "properties": {
    "gn:admin1_code":"30.0",
    "gn:asciiname":"Wupingzhaicun",
    "gn:country_code":"CN",
    "gn:dem":6,
    "gn:feature_class":"P",
    "gn:feature_code":"PPL",
    "gn:name":"Wupingzhaicun",
    "gn:population":0,
    "gn:timezone":"Asia/Shanghai",
    "iso:country":"CN",
    "name:zho_x_preferred":[
        "\u5434\u5e73\u5be8\u6751"
    ],
    "wof:name":"Wupingzhaicun",
    "wof:placetype":"locality"
},
  "geometry": {"coordinates":[117.10646,23.47598],"type":"Point"}
}