{
  "type": "Feature",
  "properties": {
    "gn:admin1_code":"19.0",
    "gn:asciiname":"Niebu Wopeng",
    "gn:country_code":"CN",
    "gn:dem":98,
    "gn:feature_class":"P",
    "gn:feature_code":"PPL",
    "gn:name":"Niebu Wopeng",
    "gn:population":0,
    "gn:timezone":"Asia/Shanghai",
    "iso:country":"CN",
    "name:und_x_variant":[
        "Niebaowopeng",
        "Niebu Wopeng"
    ],
    "name:zho_x_preferred":[
        "\u8042\u5821\u7a9d\u68da"
    ],
    "wof:name":"Niebu Wopeng",
    "wof:placetype":"locality"
},
  "geometry": {"coordinates":[123.10963999999998,42.64946],"type":"Point"}
}