{
  "type": "Feature",
  "properties": {
    "gn:admin1_code":"5.0",
    "gn:asciiname":"Luotuolaicun",
    "gn:country_code":"CN",
    "gn:dem":173,
    "gn:feature_class":"P",
    "gn:feature_code":"PPL",
    "gn:name":"Luotuolaicun",
    "gn:population":0,
    "gn:timezone":"Asia/Shanghai",
    "iso:country":"CN",
    "name:zho_x_preferred":[
        "\u9a86\u9a7c\u6765\u6751"
    ],
    "wof:name":"Luotuolaicun",
    "wof:placetype":"locality"
},
  "geometry": {"coordinates":[123.88339999999999,44.32891],"type":"Point"}
}