{
  "type": "Feature",
  "properties": {
    "gn:admin1_code":"29.0",
    "gn:asciiname":"Hongshuitang",
    "gn:country_code":"CN",
    "gn:dem":2656,
    "gn:feature_class":"P",
    "gn:feature_code":"PPL",
    "gn:name":"Hongshuitang",
    "gn:population":0,
    "gn:timezone":"Asia/Shanghai",
    "iso:country":"CN",
    "name:zho_x_preferred":[
        "\u7ea2\u6c34\u5858"
    ],
    "wof:name":"Hongshuitang",
    "wof:placetype":"locality"
},
  "geometry": {"coordinates":[100.35899999999999,27.0117],"type":"Point"}
}