{
  "type": "Feature",
  "properties": {
    "gn:admin1_code":"15.0",
    "gn:asciiname":"Shangzhangjiagou",
    "gn:country_code":"CN",
    "gn:dem":2668,
    "gn:feature_class":"P",
    "gn:feature_code":"PPL",
    "gn:name":"Shangzhangjiagou",
    "gn:population":0,
    "gn:timezone":"Asia/Shanghai",
    "iso:country":"CN",
    "name:zho_x_preferred":[
        "\u4e0a\u5f20\u5bb6\u6c9f"
    ],
    "wof:name":"Shangzhangjiagou",
    "wof:placetype":"locality"
},
  "geometry": {"coordinates":[103.12,37.402],"type":"Point"}
}