{
  "type": "Feature",
  "properties": {
    "gn:admin1_code":"18",
    "gn:asciiname":"Laozhai",
    "gn:country_code":"CN",
    "gn:dem":1546,
    "gn:feature_class":"P",
    "gn:feature_code":"PPL",
    "gn:name":"Laozhai",
    "gn:population":0,
    "gn:timezone":"Asia/Shanghai",
    "iso:country":"CN",
    "name:zho_x_preferred":[
        "\u8001\u5be8"
    ],
    "wof:name":"Laozhai",
    "wof:placetype":"locality"
},
  "geometry": {"coordinates":[105.247,25.2755],"type":"Point"}
}