{
  "type": "Feature",
  "properties": {
    "gn:admin1_code":"26",
    "gn:asciiname":"Huanghuaping",
    "gn:country_code":"CN",
    "gn:dem":879,
    "gn:feature_class":"P",
    "gn:feature_code":"PPL",
    "gn:name":"Huanghuaping",
    "gn:population":0,
    "gn:timezone":"Asia/Shanghai",
    "iso:country":"CN",
    "name:und_x_variant":[
        "\u9ec4\u82b1\u576a"
    ],
    "name:zho_x_preferred":[
        "\u9ec4\u82b1\u576a"
    ],
    "wof:name":"Huanghuaping",
    "wof:placetype":"locality"
},
  "geometry": {"coordinates":[108.77528,34.76611],"type":"Point"}
}