{
  "type": "Feature",
  "properties": {
    "gn:admin1_code":"1.0",
    "gn:asciiname":"Nandingloucun",
    "gn:country_code":"CN",
    "gn:dem":28,
    "gn:feature_class":"P",
    "gn:feature_code":"PPL",
    "gn:name":"Nandingloucun",
    "gn:population":0,
    "gn:timezone":"Asia/Shanghai",
    "iso:country":"CN",
    "name:zho_x_preferred":[
        "\u5357\u4e01\u697c\u6751"
    ],
    "wof:name":"Nandingloucun",
    "wof:placetype":"locality"
},
  "geometry": {"coordinates":[117.30383,33.79238],"type":"Point"}
}