{
  "type": "Feature",
  "properties": {
    "gn:admin1_code":"05",
    "gn:asciiname":"Chia-hsin-tzu",
    "gn:country_code":"CN",
    "gn:dem":36,
    "gn:feature_class":"P",
    "gn:feature_code":"PPL",
    "gn:name":"Chia-hsin-tzu",
    "gn:population":0,
    "gn:timezone":"Asia/Shanghai",
    "iso:country":"CN",
    "wof:name":"Chia-hsin-tzu",
    "wof:placetype":"locality"
},
  "geometry": {"coordinates":[130.34472,42.84889],"type":"Point"}
}