{
  "type": "Feature",
  "properties": {
    "gn:admin1_code":"22.0",
    "gn:asciiname":"Danlicun",
    "gn:country_code":"CN",
    "gn:dem":158,
    "gn:feature_class":"P",
    "gn:feature_code":"PPL",
    "gn:name":"Danlicun",
    "gn:population":0,
    "gn:timezone":"Asia/Shanghai",
    "iso:country":"CN",
    "name:zho_x_preferred":[
        "\u62c5\u793c\u6751"
    ],
    "wof:name":"Danlicun",
    "wof:placetype":"locality"
},
  "geometry": {"coordinates":[116.04327000000001,39.98651],"type":"Point"}
}