{
  "type": "Feature",
  "properties": {
    "gn:admin1_code":"25.0",
    "gn:asciiname":"Zhazi",
    "gn:cc2":"CN",
    "gn:country_code":"CN",
    "gn:dem":6,
    "gn:feature_class":"P",
    "gn:feature_code":"PPL",
    "gn:name":"Zhazi",
    "gn:population":0,
    "gn:timezone":"Asia/Shanghai",
    "iso:country":"CN",
    "name:und_x_variant":[
        "Cha-tzu",
        "Zhazi"
    ],
    "wof:name":"Zhazi",
    "wof:placetype":"locality"
},
  "geometry": {"coordinates":[120.08944,36.43778],"type":"Point"}
}