{
  "type": "Feature",
  "properties": {
    "gn:admin1_code":"1.0",
    "gn:asciiname":"Yangwukeng",
    "gn:country_code":"CN",
    "gn:dem":466,
    "gn:feature_class":"P",
    "gn:feature_code":"PPL",
    "gn:name":"Yangwukeng",
    "gn:population":0,
    "gn:timezone":"Asia/Shanghai",
    "iso:country":"CN",
    "name:und_x_variant":[
        "\u9633\u575e\u5751"
    ],
    "name:zho_x_preferred":[
        "Yangwukeng"
    ],
    "wof:name":"Yangwukeng",
    "wof:placetype":"locality"
},
  "geometry": {"coordinates":[119.09265000000001,30.34155],"type":"Point"}
}