{
  "type": "Feature",
  "properties": {
    "gn:admin1_code":"2",
    "gn:asciiname":"Guihu",
    "gn:country_code":"CN",
    "gn:dem":608,
    "gn:feature_class":"P",
    "gn:feature_code":"PPLA4",
    "gn:name":"Guihu",
    "gn:population":0,
    "gn:timezone":"Asia/Shanghai",
    "iso:country":"CN",
    "name:und_x_variant":[
        "\u9f9f\u6e56",
        "Guihu Zhen"
    ],
    "name:zho_x_preferred":[
        "\u9f9f\u6e56\u9547"
    ],
    "wof:name":"Guihu",
    "wof:placetype":"locality"
},
  "geometry": {"coordinates":[119.80444,27.32333],"type":"Point"}
}