{
  "type": "Feature",
  "properties": {
    "gn:admin1_code":"2.0",
    "gn:asciiname":"Shangyou Dadui",
    "gn:country_code":"CN",
    "gn:dem":9,
    "gn:feature_class":"P",
    "gn:feature_code":"PPLF",
    "gn:name":"Shangyou Dadui",
    "gn:population":0,
    "gn:timezone":"Asia/Shanghai",
    "iso:country":"CN",
    "name:und_x_variant":[
        "\u4e0a\u6e38\u5927\u961f"
    ],
    "wof:name":"Shangyou Dadui",
    "wof:placetype":"locality"
},
  "geometry": {"coordinates":[120.35056000000002,30.28095],"type":"Point"}
}