{
  "type": "Feature",
  "properties": {
    "gn:admin1_code":"23.0",
    "gn:asciiname":"Chennan",
    "gn:country_code":"CN",
    "gn:dem":5,
    "gn:feature_class":"P",
    "gn:feature_code":"PPL",
    "gn:name":"Chennan",
    "gn:population":0,
    "gn:timezone":"Asia/Shanghai",
    "iso:country":"CN",
    "name:zho_x_preferred":[
        "Chennan"
    ],
    "name:zho_x_variant":[
        "\u9648\u5357"
    ],
    "wof:name":"Chennan",
    "wof:placetype":"locality"
},
  "geometry": {"coordinates":[121.78518,31.49067],"type":"Point"}
}