{
  "type": "Feature",
  "properties": {
    "gn:admin1_code":"29.0",
    "gn:asciiname":"Bieluogu",
    "gn:country_code":"CN",
    "gn:dem":1966,
    "gn:feature_class":"P",
    "gn:feature_code":"PPL",
    "gn:name":"Bieluogu",
    "gn:population":0,
    "gn:timezone":"Asia/Shanghai",
    "iso:country":"CN",
    "name:zho_x_preferred":[
        "\u522b\u843d\u53e4"
    ],
    "wof:name":"Bieluogu",
    "wof:placetype":"locality"
},
  "geometry": {"coordinates":[100.143,25.1386],"type":"Point"}
}