{
  "type": "Feature",
  "properties": {
    "gn:admin1_code":"16.0",
    "gn:asciiname":"Dasha",
    "gn:country_code":"CN",
    "gn:dem":60,
    "gn:feature_class":"P",
    "gn:feature_code":"PPL",
    "gn:name":"Dasha",
    "gn:population":0,
    "gn:timezone":"Asia/Shanghai",
    "iso:country":"CN",
    "name:ceb_x_preferred":[
        "Dasha"
    ],
    "name:deu_x_preferred":[
        "Dasha"
    ],
    "name:ita_x_preferred":[
        "Dasha"
    ],
    "name:swe_x_preferred":[
        "Dasha"
    ],
    "name:zho_x_preferred":[
        "\u5927\u6c99"
    ],
    "wof:name":"Dasha",
    "wof:placetype":"locality"
},
  "geometry": {"coordinates":[109.242,22.2192],"type":"Point"}
}