{
  "type": "Feature",
  "properties": {
    "gn:admin1_code":"5.0",
    "gn:asciiname":"Yaobatai",
    "gn:country_code":"CN",
    "gn:dem":216,
    "gn:feature_class":"P",
    "gn:feature_code":"PPL",
    "gn:name":"Yaobatai",
    "gn:population":0,
    "gn:timezone":"Asia/Shanghai",
    "iso:country":"CN",
    "name:zho_x_preferred":[
        "\u8170\u516b\u53f0"
    ],
    "wof:name":"Yaobatai",
    "wof:placetype":"locality"
},
  "geometry": {"coordinates":[125.96568000000001,44.25946],"type":"Point"}
}