{
  "type": "Feature",
  "properties": {
    "gn:admin1_code":"8.0",
    "gn:asciiname":"Yongshengdi Yingzi",
    "gn:country_code":"CN",
    "gn:dem":313,
    "gn:feature_class":"P",
    "gn:feature_code":"PPL",
    "gn:name":"Yongshengdi Yingzi",
    "gn:population":0,
    "gn:timezone":"Asia/Shanghai",
    "iso:country":"CN",
    "name:zho_x_preferred":[
        "\u6c38\u80dc\u5730\u8425\u5b50"
    ],
    "wof:name":"Yongshengdi Yingzi",
    "wof:placetype":"locality"
},
  "geometry": {"coordinates":[126.53824,50.34505],"type":"Point"}
}