{
  "type": "Feature",
  "properties": {
    "gn:admin1_code":"30.0",
    "gn:asciiname":"Liushuijing",
    "gn:country_code":"CN",
    "gn:dem":58,
    "gn:feature_class":"P",
    "gn:feature_code":"PPL",
    "gn:name":"Liushuijing",
    "gn:population":0,
    "gn:timezone":"Asia/Shanghai",
    "iso:country":"CN",
    "name:und_x_variant":[
        "\u6d41\u6c34\u4e95"
    ],
    "name:zho_x_preferred":[
        "\u6d41\u6c34\u4e95"
    ],
    "wof:name":"Liushuijing",
    "wof:placetype":"locality"
},
  "geometry": {"coordinates":[113.55797,22.77774],"type":"Point"}
}