{
  "type": "Feature",
  "properties": {
    "gn:admin1_code":"7.0",
    "gn:asciiname":"Huangyuan",
    "gn:country_code":"CN",
    "gn:dem":338,
    "gn:feature_class":"P",
    "gn:feature_code":"PPL",
    "gn:name":"Huangyuan",
    "gn:population":0,
    "gn:timezone":"Asia/Shanghai",
    "iso:country":"CN",
    "name:zho_x_preferred":[
        "\u9ec4\u6e90"
    ],
    "wof:name":"Huangyuan",
    "wof:placetype":"locality"
},
  "geometry": {"coordinates":[117.15434999999999,27.42336],"type":"Point"}
}