{
  "type": "Feature",
  "properties": {
    "gn:admin1_code":"12.0",
    "gn:asciiname":"Tangjia",
    "gn:country_code":"CN",
    "gn:dem":160,
    "gn:feature_class":"P",
    "gn:feature_code":"PPL",
    "gn:name":"Tangjia",
    "gn:population":0,
    "gn:timezone":"Asia/Shanghai",
    "iso:country":"CN",
    "name:zho_x_preferred":[
        "Tangjia"
    ],
    "name:zho_x_variant":[
        "\u6c64\u5bb6"
    ],
    "wof:name":"Tangjia",
    "wof:placetype":"locality"
},
  "geometry": {"coordinates":[114.25462,29.55605],"type":"Point"}
}