{
  "type": "Feature",
  "properties": {
    "gn:admin1_code":"16.0",
    "gn:asciiname":"Bafu",
    "gn:country_code":"CN",
    "gn:dem":196,
    "gn:feature_class":"P",
    "gn:feature_code":"PPL",
    "gn:name":"Bafu",
    "gn:population":0,
    "gn:timezone":"Asia/Shanghai",
    "iso:country":"CN",
    "name:zho_x_preferred":[
        "\u5c9c\u832f"
    ],
    "wof:name":"Bafu",
    "wof:placetype":"locality"
},
  "geometry": {"coordinates":[107.173,22.2369],"type":"Point"}
}