{
  "type": "Feature",
  "properties": {
    "gn:admin1_code":"19.0",
    "gn:asciiname":"Miaolingcun",
    "gn:country_code":"CN",
    "gn:dem":136,
    "gn:feature_class":"P",
    "gn:feature_code":"PPL",
    "gn:name":"Miaolingcun",
    "gn:population":0,
    "gn:timezone":"Asia/Shanghai",
    "iso:country":"CN",
    "name:zho_x_preferred":[
        "\u5e99\u5cad\u6751"
    ],
    "wof:name":"Miaolingcun",
    "wof:placetype":"locality"
},
  "geometry": {"coordinates":[122.29067000000001,39.72678],"type":"Point"}
}