{
  "type": "Feature",
  "properties": {
    "gn:admin1_code":"25",
    "gn:asciiname":"Dachijia",
    "gn:country_code":"CN",
    "gn:dem":49,
    "gn:feature_class":"P",
    "gn:feature_code":"PPL",
    "gn:name":"Dachijia",
    "gn:population":0,
    "gn:timezone":"Asia/Shanghai",
    "iso:country":"CN",
    "name:zho_x_preferred":[
        "\u5927\u8fdf\u5bb6"
    ],
    "wof:name":"Dachijia",
    "wof:placetype":"locality"
},
  "geometry": {"coordinates":[120.699,37.6276],"type":"Point"}
}