{
  "type": "Feature",
  "properties": {
    "gn:admin1_code":"11.0",
    "gn:asciiname":"Fengxianmiao",
    "gn:country_code":"CN",
    "gn:dem":186,
    "gn:feature_class":"P",
    "gn:feature_code":"PPL",
    "gn:name":"Fengxianmiao",
    "gn:population":0,
    "gn:timezone":"Asia/Shanghai",
    "iso:country":"CN",
    "name:zho_x_preferred":[
        "\u67ab\u4ed9\u5e99"
    ],
    "wof:name":"Fengxianmiao",
    "wof:placetype":"locality"
},
  "geometry": {"coordinates":[113.49957000000001,26.56547],"type":"Point"}
}