{
  "type": "Feature",
  "properties": {
    "gn:admin1_code":"29.0",
    "gn:asciiname":"Zuokoushan",
    "gn:country_code":"CN",
    "gn:dem":2191,
    "gn:feature_class":"P",
    "gn:feature_code":"PPL",
    "gn:name":"Zuokoushan",
    "gn:population":0,
    "gn:timezone":"Asia/Shanghai",
    "iso:country":"CN",
    "name:zho_x_preferred":[
        "\u5de6\u53e3\u5c71"
    ],
    "wof:name":"Zuokoushan",
    "wof:placetype":"locality"
},
  "geometry": {"coordinates":[103.504,25.7879],"type":"Point"}
}