{
  "type": "Feature",
  "properties": {
    "gn:admin1_code":"24.0",
    "gn:asciiname":"Yangyecun",
    "gn:country_code":"CN",
    "gn:dem":1181,
    "gn:feature_class":"P",
    "gn:feature_code":"PPL",
    "gn:name":"Yangyecun",
    "gn:population":0,
    "gn:timezone":"Asia/Shanghai",
    "iso:country":"CN",
    "name:zho_x_preferred":[
        "\u6768\u91ce\u6751"
    ],
    "wof:name":"Yangyecun",
    "wof:placetype":"locality"
},
  "geometry": {"coordinates":[111.4051,37.03435],"type":"Point"}
}