{
  "type": "Feature",
  "properties": {
    "gn:admin1_code":"29",
    "gn:asciiname":"Baishuiqing",
    "gn:country_code":"CN",
    "gn:dem":2088,
    "gn:feature_class":"P",
    "gn:feature_code":"PPL",
    "gn:name":"Baishuiqing",
    "gn:population":0,
    "gn:timezone":"Asia/Shanghai",
    "iso:country":"CN",
    "name:zho_x_preferred":[
        "\u767d\u6c34\u7b90"
    ],
    "wof:name":"Baishuiqing",
    "wof:placetype":"locality"
},
  "geometry": {"coordinates":[102.63500000000001,24.5026],"type":"Point"}
}