{
  "type": "Feature",
  "properties": {
    "gn:admin1_code":"30",
    "gn:asciiname":"Shenxia",
    "gn:country_code":"CN",
    "gn:dem":250,
    "gn:feature_class":"P",
    "gn:feature_code":"PPL",
    "gn:name":"Shenxia",
    "gn:population":0,
    "gn:timezone":"Asia/Shanghai",
    "iso:country":"CN",
    "name:zho_x_preferred":[
        "\u795e\u4e0b"
    ],
    "wof:name":"Shenxia",
    "wof:placetype":"locality"
},
  "geometry": {"coordinates":[115.94103,24.83029],"type":"Point"}
}