{
  "type": "Feature",
  "properties": {
    "gn:admin1_code":"4.0",
    "gn:asciiname":"Zhanchengcun",
    "gn:country_code":"CN",
    "gn:dem":27,
    "gn:feature_class":"P",
    "gn:feature_code":"PPL",
    "gn:name":"Zhanchengcun",
    "gn:population":0,
    "gn:timezone":"Asia/Shanghai",
    "iso:country":"CN",
    "name:zho_x_preferred":[
        "\u5360\u57ce\u6751"
    ],
    "wof:name":"Zhanchengcun",
    "wof:placetype":"locality"
},
  "geometry": {"coordinates":[117.76181,34.17812],"type":"Point"}
}