{
  "type": "Feature",
  "properties": {
    "gn:admin1_code":"30",
    "gn:asciiname":"He'andong",
    "gn:country_code":"CN",
    "gn:dem":579,
    "gn:feature_class":"P",
    "gn:feature_code":"PPL",
    "gn:name":"He\u2019andong",
    "gn:population":0,
    "gn:timezone":"Asia/Shanghai",
    "iso:country":"CN",
    "name:zho_x_preferred":[
        "He\u2019andong"
    ],
    "wof:name":"He'andong",
    "wof:placetype":"locality"
},
  "geometry": {"coordinates":[115.75167,23.16222],"type":"Point"}
}