{
  "type": "Feature",
  "properties": {
    "gn:admin1_code":"14.0",
    "gn:asciiname":"Shensheng",
    "gn:country_code":"CN",
    "gn:dem":4716,
    "gn:feature_class":"P",
    "gn:feature_code":"PPL",
    "gn:name":"Shensheng",
    "gn:population":0,
    "gn:timezone":"Asia/Urumqi",
    "iso:country":"CN",
    "name:zho_x_preferred":[
        "\u7533\u7701"
    ],
    "wof:name":"Shensheng",
    "wof:placetype":"locality"
},
  "geometry": {"coordinates":[91.92757,31.23028],"type":"Point"}
}