{
  "type": "Feature",
  "properties": {
    "gn:admin1_code":"4.0",
    "gn:asciiname":"Chenxu Linchang",
    "gn:country_code":"CN",
    "gn:dem":13,
    "gn:feature_class":"P",
    "gn:feature_code":"PPLF",
    "gn:name":"Chenxu Linchang",
    "gn:population":0,
    "gn:timezone":"Asia/Shanghai",
    "iso:country":"CN",
    "wof:name":"Chenxu Linchang",
    "wof:placetype":"locality"
},
  "geometry": {"coordinates":[118.3625,33.28333],"type":"Point"}
}