{
  "type": "Feature",
  "properties": {
    "gn:admin1_code":"2.0",
    "gn:asciiname":"Maxing",
    "gn:country_code":"CN",
    "gn:dem":11,
    "gn:feature_class":"P",
    "gn:feature_code":"PPL",
    "gn:name":"Maxing",
    "gn:population":0,
    "gn:timezone":"Asia/Shanghai",
    "iso:country":"CN",
    "name:jpn_x_preferred":[
        "\u30de\u30ad\u30b7\u30f3\u30b0"
    ],
    "name:zho_x_preferred":[
        "\u9ebb\u5f62"
    ],
    "name:zho_x_variant":[
        "Maxing"
    ],
    "wof:name":"Maxing",
    "wof:placetype":"locality"
},
  "geometry": {"coordinates":[121.69311,29.68616],"type":"Point"}
}