{
  "type": "Feature",
  "properties": {
    "gn:admin1_code":"30",
    "gn:asciiname":"Shibipu",
    "gn:country_code":"CN",
    "gn:dem":61,
    "gn:feature_class":"P",
    "gn:feature_code":"PPL",
    "gn:name":"Shibipu",
    "gn:population":0,
    "gn:timezone":"Asia/Shanghai",
    "iso:country":"CN",
    "name:zho_x_preferred":[
        "\u77f3\u58c1\u94fa"
    ],
    "wof:name":"Shibipu",
    "wof:placetype":"locality"
},
  "geometry": {"coordinates":[116.61067,23.81565],"type":"Point"}
}