{
  "type": "Feature",
  "properties": {
    "gn:admin1_code":"32.0",
    "gn:asciiname":"Jiashangou",
    "gn:country_code":"CN",
    "gn:dem":926,
    "gn:feature_class":"P",
    "gn:feature_code":"PPL",
    "gn:name":"Jiashangou",
    "gn:population":0,
    "gn:timezone":"Asia/Shanghai",
    "iso:country":"CN",
    "name:zho_x_preferred":[
        "\u7532\u5c71\u6c9f"
    ],
    "wof:name":"Jiashangou",
    "wof:placetype":"locality"
},
  "geometry": {"coordinates":[107.82599999999999,31.233],"type":"Point"}
}