{
  "type": "Feature",
  "properties": {
    "gn:admin1_code":"25.0",
    "gn:asciiname":"Suijiatun",
    "gn:country_code":"CN",
    "gn:dem":73,
    "gn:feature_class":"P",
    "gn:feature_code":"PPL",
    "gn:name":"Suijiatun",
    "gn:population":0,
    "gn:timezone":"Asia/Shanghai",
    "iso:country":"CN",
    "name:zho_x_preferred":[
        "\u968b\u5bb6\u5c6f"
    ],
    "wof:name":"Suijiatun",
    "wof:placetype":"locality"
},
  "geometry": {"coordinates":[120.50649,36.88995],"type":"Point"}
}