{
  "type": "Feature",
  "properties": {
    "gn:admin1_code":"10.0",
    "gn:asciiname":"Hounianzu",
    "gn:country_code":"CN",
    "gn:dem":12,
    "gn:feature_class":"P",
    "gn:feature_code":"PPL",
    "gn:name":"Hounianzu",
    "gn:population":0,
    "gn:timezone":"Asia/Shanghai",
    "iso:country":"CN",
    "name:zho_x_preferred":[
        "\u540e\u5ff5\u7956"
    ],
    "wof:name":"Hounianzu",
    "wof:placetype":"locality"
},
  "geometry": {"coordinates":[116.38200000000001,38.4721],"type":"Point"}
}