{
  "type": "Feature",
  "properties": {
    "gn:admin1_code":"26.0",
    "gn:asciiname":"Baiyangshupingcun",
    "gn:country_code":"CN",
    "gn:dem":1201,
    "gn:feature_class":"P",
    "gn:feature_code":"PPL",
    "gn:name":"Baiyangshupingcun",
    "gn:population":0,
    "gn:timezone":"Asia/Shanghai",
    "iso:country":"CN",
    "name:zho_x_preferred":[
        "\u767d\u6768\u6811\u576a\u6751"
    ],
    "wof:name":"Baiyangshupingcun",
    "wof:placetype":"locality"
},
  "geometry": {"coordinates":[109.37958999999999,37.19705],"type":"Point"}
}