{
  "type": "Feature",
  "properties": {
    "gn:admin1_code":"24.0",
    "gn:asciiname":"Miaojiao",
    "gn:country_code":"CN",
    "gn:dem":1369,
    "gn:feature_class":"P",
    "gn:feature_code":"PPL",
    "gn:name":"Miaojiao",
    "gn:population":0,
    "gn:timezone":"Asia/Shanghai",
    "iso:country":"CN",
    "name:zho_x_preferred":[
        "\u5e99\u90ca"
    ],
    "wof:name":"Miaojiao",
    "wof:placetype":"locality"
},
  "geometry": {"coordinates":[113.48256000000001,35.98702],"type":"Point"}
}