{
  "type": "Feature",
  "properties": {
    "gn:admin1_code":"16",
    "gn:asciiname":"Anmin",
    "gn:country_code":"CN",
    "gn:dem":223,
    "gn:feature_class":"P",
    "gn:feature_code":"PPL",
    "gn:name":"Anmin",
    "gn:population":0,
    "gn:timezone":"Asia/Shanghai",
    "iso:country":"CN",
    "name:und_x_variant":[
        "An-min-ts\u2019un",
        "Anmin"
    ],
    "name:zho_x_preferred":[
        "\u5b89\u6c11"
    ],
    "wof:name":"Anmin",
    "wof:placetype":"locality"
},
  "geometry": {"coordinates":[107.002,22.715],"type":"Point"}
}