{
  "type": "Feature",
  "properties": {
    "gn:admin1_code":"20.0",
    "gn:asciiname":"Sanhecun",
    "gn:country_code":"CN",
    "gn:dem":1774,
    "gn:feature_class":"P",
    "gn:feature_code":"PPL",
    "gn:name":"Sanhecun",
    "gn:population":0,
    "gn:timezone":"Asia/Shanghai",
    "iso:country":"CN",
    "name:und_x_variant":[
        "\u4e09\u548c\u6751"
    ],
    "wof:name":"Sanhecun",
    "wof:placetype":"locality"
},
  "geometry": {"coordinates":[112.5521,41.36738],"type":"Point"}
}