{
  "type": "Feature",
  "properties": {
    "gn:admin1_code":"24.0",
    "gn:asciiname":"Beiyanbei",
    "gn:country_code":"CN",
    "gn:dem":1642,
    "gn:feature_class":"P",
    "gn:feature_code":"PPL",
    "gn:name":"Beiyanbei",
    "gn:population":0,
    "gn:timezone":"Asia/Shanghai",
    "iso:country":"CN",
    "name:zho_x_preferred":[
        "\u5317\u5ca9\u80cc"
    ],
    "wof:name":"Beiyanbei",
    "wof:placetype":"locality"
},
  "geometry": {"coordinates":[113.47983000000001,37.11963],"type":"Point"}
}