{
  "type": "Feature",
  "properties": {
    "gn:admin1_code":"5.0",
    "gn:asciiname":"Jianyetun",
    "gn:country_code":"CN",
    "gn:dem":163,
    "gn:feature_class":"P",
    "gn:feature_code":"PPL",
    "gn:name":"Jianyetun",
    "gn:population":0,
    "gn:timezone":"Asia/Shanghai",
    "iso:country":"CN",
    "name:zho_x_preferred":[
        "\u5efa\u4e1a\u5c6f"
    ],
    "wof:name":"Jianyetun",
    "wof:placetype":"locality"
},
  "geometry": {"coordinates":[122.40288,45.23653],"type":"Point"}
}