{
  "type": "Feature",
  "properties": {
    "gn:admin1_code":"26.0",
    "gn:asciiname":"Sujiashancun",
    "gn:country_code":"CN",
    "gn:dem":998,
    "gn:feature_class":"P",
    "gn:feature_code":"PPL",
    "gn:name":"Sujiashancun",
    "gn:population":0,
    "gn:timezone":"Asia/Shanghai",
    "iso:country":"CN",
    "name:zho_x_preferred":[
        "\u82cf\u5bb6\u5c71\u6751"
    ],
    "wof:name":"Sujiashancun",
    "wof:placetype":"locality"
},
  "geometry": {"coordinates":[109.11254,35.48551],"type":"Point"}
}