{
  "type": "Feature",
  "properties": {
    "gn:admin1_code":"29.0",
    "gn:asciiname":"Xiyaozi",
    "gn:country_code":"CN",
    "gn:dem":1258,
    "gn:feature_class":"P",
    "gn:feature_code":"PPL",
    "gn:name":"Xiyaozi",
    "gn:population":0,
    "gn:timezone":"Asia/Shanghai",
    "iso:country":"CN",
    "name:zho_x_preferred":[
        "\u7ec6\u8170\u5b50"
    ],
    "wof:name":"Xiyaozi",
    "wof:placetype":"locality"
},
  "geometry": {"coordinates":[100.508,22.6455],"type":"Point"}
}