{
  "type": "Feature",
  "properties": {
    "gn:admin1_code":"26.0",
    "gn:asciiname":"Gulucun",
    "gn:country_code":"CN",
    "gn:dem":1182,
    "gn:feature_class":"P",
    "gn:feature_code":"PPL",
    "gn:name":"Gulucun",
    "gn:population":0,
    "gn:timezone":"Asia/Shanghai",
    "iso:country":"CN",
    "name:zho_x_preferred":[
        "\u53e4\u8def\u6751"
    ],
    "wof:name":"Gulucun",
    "wof:placetype":"locality"
},
  "geometry": {"coordinates":[109.16958,35.71808],"type":"Point"}
}