{
  "type": "Feature",
  "properties": {
    "gn:admin1_code":"32.0",
    "gn:asciiname":"Zhazha",
    "gn:country_code":"CN",
    "gn:dem":3932,
    "gn:feature_class":"P",
    "gn:feature_code":"PPL",
    "gn:name":"Zhazha",
    "gn:population":0,
    "gn:timezone":"Asia/Shanghai",
    "iso:country":"CN",
    "name:zho_x_preferred":[
        "\u67e5\u624e"
    ],
    "wof:name":"Zhazha",
    "wof:placetype":"locality"
},
  "geometry": {"coordinates":[99.79465999999999,31.96591],"type":"Point"}
}