{
  "type": "Feature",
  "properties": {
    "gn:admin1_code":"26.0",
    "gn:asciiname":"Luoquanyan",
    "gn:country_code":"CN",
    "gn:dem":1469,
    "gn:feature_class":"P",
    "gn:feature_code":"PPL",
    "gn:name":"Luoquanyan",
    "gn:population":0,
    "gn:timezone":"Asia/Shanghai",
    "iso:country":"CN",
    "name:und_x_variant":[
        "\u7f57\u5168\u5ca9"
    ],
    "wof:name":"Luoquanyan",
    "wof:placetype":"locality"
},
  "geometry": {"coordinates":[106.26354000000001,32.72668],"type":"Point"}
}