{
  "type": "Feature",
  "properties": {
    "gn:admin1_code":"9.0",
    "gn:asciiname":"Leshangou",
    "gn:country_code":"CN",
    "gn:dem":162,
    "gn:feature_class":"P",
    "gn:feature_code":"PPL",
    "gn:name":"Leshangou",
    "gn:population":0,
    "gn:timezone":"Asia/Shanghai",
    "iso:country":"CN",
    "name:zho_x_preferred":[
        "\u4e50\u5c71\u6c9f"
    ],
    "wof:name":"Leshangou",
    "wof:placetype":"locality"
},
  "geometry": {"coordinates":[113.87954000000001,32.86789],"type":"Point"}
}