{
  "type": "Feature",
  "properties": {
    "gn:admin1_code":"20.0",
    "gn:asciiname":"Dahongshan",
    "gn:country_code":"CN",
    "gn:dem":445,
    "gn:feature_class":"P",
    "gn:feature_code":"PPL",
    "gn:name":"Dahongshan",
    "gn:population":0,
    "gn:timezone":"Asia/Shanghai",
    "iso:country":"CN",
    "name:zho_x_preferred":[
        "\u5927\u7ea2\u5c71"
    ],
    "wof:name":"Dahongshan",
    "wof:placetype":"locality"
},
  "geometry": {"coordinates":[122.50821999999999,47.96303],"type":"Point"}
}