{
  "type": "Feature",
  "properties": {
    "gn:admin1_code":"14.0",
    "gn:asciiname":"Yuhecun",
    "gn:country_code":"CN",
    "gn:dem":3485,
    "gn:feature_class":"P",
    "gn:feature_code":"PPL",
    "gn:name":"Yuhecun",
    "gn:population":0,
    "gn:timezone":"Asia/Urumqi",
    "iso:country":"CN",
    "name:zho_x_preferred":[
        "\u7389\u548c\u6751"
    ],
    "wof:name":"Yuhecun",
    "wof:placetype":"locality"
},
  "geometry": {"coordinates":[97.15813,29.18988],"type":"Point"}
}