{
  "type": "Feature",
  "properties": {
    "gn:admin1_code":"31.0",
    "gn:asciiname":"Lincun",
    "gn:country_code":"CN",
    "gn:dem":16,
    "gn:feature_class":"P",
    "gn:feature_code":"PPL",
    "gn:name":"Lincun",
    "gn:population":0,
    "gn:timezone":"Asia/Shanghai",
    "iso:country":"CN",
    "name:zho_x_preferred":[
        "Lincun"
    ],
    "name:zho_x_variant":[
        "\u6797\u6751"
    ],
    "wof:name":"Lincun",
    "wof:placetype":"locality"
},
  "geometry": {"coordinates":[110.83476,19.68653],"type":"Point"}
}