{
  "type": "Feature",
  "properties": {
    "gn:admin1_code":"12",
    "gn:asciiname":"Sijiachang",
    "gn:country_code":"CN",
    "gn:dem":105,
    "gn:feature_class":"P",
    "gn:feature_code":"PPLA4",
    "gn:name":"Sijiachang",
    "gn:population":0,
    "gn:timezone":"Asia/Shanghai",
    "iso:country":"CN",
    "name:und_x_variant":[
        "\u65af\u5bb6\u573a",
        "Sijiachang Zhen",
        "\u65af\u5bb6\u573a\u9547"
    ],
    "wof:name":"Sijiachang",
    "wof:placetype":"locality"
},
  "geometry": {"coordinates":[111.62126000000001,30.08597],"type":"Point"}
}