{
  "type": "Feature",
  "properties": {
    "gn:admin1_code":"10",
    "gn:asciiname":"Wazi",
    "gn:country_code":"CN",
    "gn:dem":1219,
    "gn:feature_class":"P",
    "gn:feature_code":"PPL",
    "gn:name":"Wazi",
    "gn:population":0,
    "gn:timezone":"Asia/Shanghai",
    "iso:country":"CN",
    "name:zho_x_preferred":[
        "\u6d3c\u5b50"
    ],
    "wof:name":"Wazi",
    "wof:placetype":"locality"
},
  "geometry": {"coordinates":[117.97223,42.27723],"type":"Point"}
}