{
  "type": "Feature",
  "properties": {
    "gn:admin1_code":"32.0",
    "gn:asciiname":"Mazishi",
    "gn:country_code":"CN",
    "gn:dem":3174,
    "gn:feature_class":"P",
    "gn:feature_code":"PPL",
    "gn:name":"Mazishi",
    "gn:population":0,
    "gn:timezone":"Asia/Shanghai",
    "iso:country":"CN",
    "name:zho_x_preferred":[
        "\u9ebb\u5b50\u77f3"
    ],
    "wof:name":"Mazishi",
    "wof:placetype":"locality"
},
  "geometry": {"coordinates":[101.06833,29.94247],"type":"Point"}
}