{
  "type": "Feature",
  "properties": {
    "gn:admin1_code":"16.0",
    "gn:asciiname":"Xiaxia",
    "gn:country_code":"CN",
    "gn:dem":402,
    "gn:feature_class":"P",
    "gn:feature_code":"PPL",
    "gn:name":"Xiaxia",
    "gn:population":0,
    "gn:timezone":"Asia/Shanghai",
    "iso:country":"CN",
    "name:zho_x_preferred":[
        "\u4e0b\u5ce1"
    ],
    "wof:name":"Xiaxia",
    "wof:placetype":"locality"
},
  "geometry": {"coordinates":[107.996,25.0332],"type":"Point"}
}