{
  "type": "Feature",
  "properties": {
    "gn:admin1_code":"30.0",
    "gn:asciiname":"Shahaogang",
    "gn:country_code":"CN",
    "gn:dem":60,
    "gn:feature_class":"P",
    "gn:feature_code":"PPL",
    "gn:name":"Shahaogang",
    "gn:population":0,
    "gn:timezone":"Asia/Shanghai",
    "iso:country":"CN",
    "name:zho_x_preferred":[
        "\u6c99\u8c6a\u5c97"
    ],
    "wof:name":"Shahaogang",
    "wof:placetype":"locality"
},
  "geometry": {"coordinates":[111.60856,22.70581],"type":"Point"}
}