{
  "type": "Feature",
  "properties": {
    "gn:admin1_code":"32.0",
    "gn:asciiname":"Momu Shangcun",
    "gn:country_code":"CN",
    "gn:dem":3045,
    "gn:feature_class":"P",
    "gn:feature_code":"PPL",
    "gn:name":"Momu Shangcun",
    "gn:population":0,
    "gn:timezone":"Asia/Shanghai",
    "iso:country":"CN",
    "name:zho_x_preferred":[
        "\u83ab\u6728\u4e0a\u6751"
    ],
    "wof:name":"Momu Shangcun",
    "wof:placetype":"locality"
},
  "geometry": {"coordinates":[99.3536,28.6033],"type":"Point"}
}