{
  "type": "Feature",
  "properties": {
    "gn:admin1_code":"10.0",
    "gn:asciiname":"Wuzhuang",
    "gn:country_code":"CN",
    "gn:dem":179,
    "gn:feature_class":"P",
    "gn:feature_code":"PPL",
    "gn:name":"Wuzhuang",
    "gn:population":0,
    "gn:timezone":"Asia/Shanghai",
    "iso:country":"CN",
    "name:und_x_variant":[
        "\u5434\u5e84"
    ],
    "wof:name":"Wuzhuang",
    "wof:placetype":"locality"
},
  "geometry": {"coordinates":[114.41558000000001,38.61668],"type":"Point"}
}