{
  "type": "Feature",
  "properties": {
    "gn:admin1_code":"11.0",
    "gn:asciiname":"Putang",
    "gn:country_code":"CN",
    "gn:dem":282,
    "gn:feature_class":"P",
    "gn:feature_code":"PPL",
    "gn:name":"Putang",
    "gn:population":0,
    "gn:timezone":"Asia/Shanghai",
    "iso:country":"CN",
    "name:und_x_variant":[
        "Putong"
    ],
    "name:zho_x_preferred":[
        "\u6734\u5858"
    ],
    "wof:name":"Putang",
    "wof:placetype":"locality"
},
  "geometry": {"coordinates":[111.14373000000001,27.38396],"type":"Point"}
}