{
  "type": "Feature",
  "properties": {
    "gn:admin1_code":"2.0",
    "gn:asciiname":"Fengjiawan",
    "gn:country_code":"CN",
    "gn:dem":6,
    "gn:feature_class":"P",
    "gn:feature_code":"PPL",
    "gn:name":"Fengjiawan",
    "gn:population":0,
    "gn:timezone":"Asia/Shanghai",
    "iso:country":"CN",
    "name:und_x_variant":[
        "\u51af\u5bb6\u6e7e"
    ],
    "wof:name":"Fengjiawan",
    "wof:placetype":"locality"
},
  "geometry": {"coordinates":[119.93537000000001,30.9859],"type":"Point"}
}