{
  "type": "Feature",
  "properties": {
    "gn:admin1_code":"3.0",
    "gn:asciiname":"Gangshangcun",
    "gn:country_code":"CN",
    "gn:dem":70,
    "gn:feature_class":"P",
    "gn:feature_code":"PPL",
    "gn:name":"Gangshangcun",
    "gn:population":0,
    "gn:timezone":"Asia/Shanghai",
    "iso:country":"CN",
    "name:zho_x_preferred":[
        "\u5c97\u4e0a\u6751"
    ],
    "wof:name":"Gangshangcun",
    "wof:placetype":"locality"
},
  "geometry": {"coordinates":[115.33199999999999,28.554],"type":"Point"}
}