{
  "type": "Feature",
  "properties": {
    "gn:admin1_code":"31.0",
    "gn:asciiname":"Dutou",
    "gn:country_code":"CN",
    "gn:dem":6,
    "gn:feature_class":"P",
    "gn:feature_code":"PPL",
    "gn:name":"Dutou",
    "gn:population":0,
    "gn:timezone":"Asia/Shanghai",
    "iso:country":"CN",
    "name:zho_x_preferred":[
        "Dutou"
    ],
    "name:zho_x_variant":[
        "\u6e21\u5934"
    ],
    "wof:name":"Dutou",
    "wof:placetype":"locality"
},
  "geometry": {"coordinates":[110.6142,20.01927],"type":"Point"}
}