{
  "type": "Feature",
  "properties": {
    "gn:admin1_code":"19.0",
    "gn:asciiname":"Dama Kouzicun",
    "gn:country_code":"CN",
    "gn:dem":37,
    "gn:feature_class":"P",
    "gn:feature_code":"PPL",
    "gn:name":"Dama Kouzicun",
    "gn:population":0,
    "gn:timezone":"Asia/Shanghai",
    "iso:country":"CN",
    "name:und_x_variant":[
        "Damakouzicun",
        "Dama Kouzicun"
    ],
    "name:zho_x_preferred":[
        "\u5927\u9a6c\u53e3\u5b50\u6751"
    ],
    "wof:name":"Dama Kouzicun",
    "wof:placetype":"locality"
},
  "geometry": {"coordinates":[120.98672000000001,41.14583],"type":"Point"}
}