{
  "type": "Feature",
  "properties": {
    "gn:admin1_code":"1.0",
    "gn:asciiname":"Qinqiaocun",
    "gn:country_code":"CN",
    "gn:dem":44,
    "gn:feature_class":"P",
    "gn:feature_code":"PPL",
    "gn:name":"Qinqiaocun",
    "gn:population":0,
    "gn:timezone":"Asia/Shanghai",
    "iso:country":"CN",
    "name:zho_x_preferred":[
        "\u79e6\u6865\u6751"
    ],
    "wof:name":"Qinqiaocun",
    "wof:placetype":"locality"
},
  "geometry": {"coordinates":[117.57632,31.72689],"type":"Point"}
}