{
  "type": "Feature",
  "properties": {
    "gn:admin1_code":"13.0",
    "gn:asciiname":"Beitun",
    "gn:country_code":"CN",
    "gn:dem":507,
    "gn:feature_class":"P",
    "gn:feature_code":"PPLA4",
    "gn:name":"Beitun",
    "gn:population":0,
    "gn:timezone":"Asia/Urumqi",
    "iso:country":"CN",
    "name:cdo_x_preferred":[
        "B\u00e1e\u0324k-d\u016dng"
    ],
    "name:deu_x_preferred":[
        "Beitun"
    ],
    "name:ell_x_preferred":[
        "\u039c\u03c0\u03b5\u03ca\u03c4\u03bf\u03cd\u03bd"
    ],
    "name:fra_x_preferred":[
        "Beitun"
    ],
    "name:ita_x_preferred":[
        "Beitun"
    ],
    "name:jpn_x_preferred":[
        "\u5317\u5c6f\u5e02"
    ],
    "name:kaz_x_preferred":[
        "\u0628\u06d5\u064a\u062a\u06c7\u0646 \u0642\u0627\u0644\u0627\u0634\u0649\u0639\u0649"
    ],
    "name:kik_x_preferred":[
        "Beitun"
    ],
    "name:kor_x_preferred":[
        "\ubca0\uc774\ud230\uc2dc"
    ],
    "name:pol_x_preferred":[
        "Beitun"
    ],
    "name:rus_x_preferred":[
        "\u0411\u044d\u0439\u0442\u0443\u043d\u044c"
    ],
    "name:swe_x_preferred":[
        "Beitun"
    ],
    "name:tur_x_preferred":[
        "Beitun"
    ],
    "name:uig_x_preferred":[
        "\u0628\u06d0\u064a\u062a\u06c7\u0646 \u0628\u0627\u0632\u0649\u0631\u0649"
    ],
    "name:uig_x_variant":[
        "\u0628\u06d5\u064a\u062a\u06c8\u0646 \u0634\u06d5\u06be\u0649\u0631\u0649"
    ],
    "name:und_x_variant":[
        "Pei-t\u2019un",
        "Beitun",
        "Beitun Zhen"
    ],
    "name:urd_x_preferred":[
        "\u0628\u06cc\u0626\u062a\u0648\u0646"
    ],
    "name:vie_x_preferred":[
        "B\u1eafc \u0110\u1ed3n"
    ],
    "name:zho_x_preferred":[
        "\u5317\u5c6f"
    ],
    "name:zho_x_variant":[
        "\u5317\u5c6f\u9547",
        "\u5317\u5c6f\u5e02"
    ],
    "wof:name":"Beitun",
    "wof:placetype":"locality"
},
  "geometry": {"coordinates":[87.82053000000001,47.35249],"type":"Point"}
}