{
  "type": "Feature",
  "properties": {
    "gn:admin1_code":"13.0",
    "gn:asciiname":"Beitun",
    "gn:country_code":"CN",
    "gn:dem":507,
    "gn:feature_class":"P",
    "gn:feature_code":"PPLA4",
    "gn:name":"Beitun",
    "gn:population":0,
    "gn:timezone":"Asia/Urumqi",
    "iso:country":"CN",
    "name:kaz_x_preferred":[
        "\u0628\u06d5\u064a\u062a\u06c7\u0646 \u0642\u0627\u0644\u0627\u0634\u0649\u0639\u0649"
    ],
    "name:uig_x_preferred":[
        "\u0628\u06d0\u064a\u062a\u06c7\u0646 \u0628\u0627\u0632\u0649\u0631\u0649"
    ],
    "name:und_x_variant":[
        "Pei-t\u2019un",
        "Beitun",
        "Beitun Zhen"
    ],
    "name:zho_x_preferred":[
        "\u5317\u5c6f"
    ],
    "name:zho_x_variant":[
        "\u5317\u5c6f\u9547"
    ],
    "wof:name":"Beitun",
    "wof:placetype":"locality"
},
  "geometry": {"coordinates":[87.82053000000001,47.35249],"type":"Point"}
}