{
  "type": "Feature",
  "properties": {
    "gn:admin1_code":"26.0",
    "gn:asciiname":"Lijia Tacun",
    "gn:country_code":"CN",
    "gn:dem":979,
    "gn:feature_class":"P",
    "gn:feature_code":"PPL",
    "gn:name":"Lijia Tacun",
    "gn:population":0,
    "gn:timezone":"Asia/Shanghai",
    "iso:country":"CN",
    "name:zho_x_preferred":[
        "\u674e\u5bb6\u584c\u6751"
    ],
    "wof:name":"Lijia Tacun",
    "wof:placetype":"locality"
},
  "geometry": {"coordinates":[110.70999999999999,37.5118],"type":"Point"}
}