{
  "type": "Feature",
  "properties": {
    "gn:admin1_code":"19.0",
    "gn:asciiname":"Wujiazhuang",
    "gn:country_code":"CN",
    "gn:dem":565,
    "gn:feature_class":"P",
    "gn:feature_code":"PPL",
    "gn:name":"Wujiazhuang",
    "gn:population":0,
    "gn:timezone":"Asia/Shanghai",
    "iso:country":"CN",
    "name:zho_x_preferred":[
        "\u5434\u5bb6\u5e84"
    ],
    "wof:name":"Wujiazhuang",
    "wof:placetype":"locality"
},
  "geometry": {"coordinates":[119.455,40.7115],"type":"Point"}
}