{
  "type": "Feature",
  "properties": {
    "gn:admin1_code":"22.0",
    "gn:asciiname":"Wangping",
    "gn:country_code":"CN",
    "gn:dem":203,
    "gn:feature_class":"P",
    "gn:feature_code":"PPLA4",
    "gn:name":"Wangping",
    "gn:population":0,
    "gn:timezone":"Asia/Shanghai",
    "iso:country":"CN",
    "name:und_x_variant":[
        "Wangping Zhen"
    ],
    "name:zho_x_preferred":[
        "\u738b\u5e73"
    ],
    "name:zho_x_variant":[
        "\u738b\u5e73\u9547"
    ],
    "wof:name":"Wangping",
    "wof:placetype":"locality"
},
  "geometry": {"coordinates":[115.98125,39.96723],"type":"Point"}
}