{
  "type": "Feature",
  "properties": {
    "gn:admin1_code":"8.0",
    "gn:asciiname":"Longmiao",
    "gn:country_code":"CN",
    "gn:dem":165,
    "gn:feature_class":"P",
    "gn:feature_code":"PPLA4",
    "gn:name":"Longmiao",
    "gn:population":0,
    "gn:timezone":"Asia/Shanghai",
    "iso:country":"CN",
    "name:und_x_variant":[
        "Longmiao Zhen"
    ],
    "name:zho_x_preferred":[
        "\u9f99\u5e99"
    ],
    "name:zho_x_variant":[
        "\u9f99\u5e99\u9547"
    ],
    "wof:name":"Longmiao",
    "wof:placetype":"locality"
},
  "geometry": {"coordinates":[127.22739,46.35113],"type":"Point"}
}