{
  "type": "Feature",
  "properties": {
    "gn:admin1_code":"26.0",
    "gn:asciiname":"Ma'anqiao",
    "gn:country_code":"CN",
    "gn:dem":995,
    "gn:feature_class":"P",
    "gn:feature_code":"PPL",
    "gn:name":"Ma\u2019anqiao",
    "gn:population":0,
    "gn:timezone":"Asia/Shanghai",
    "iso:country":"CN",
    "name:und_x_variant":[
        "Ma\u2019anqiao",
        "\u9a6c\u978d\u6865"
    ],
    "wof:name":"Ma'anqiao",
    "wof:placetype":"locality"
},
  "geometry": {"coordinates":[106.57827,33.06835],"type":"Point"}
}