{
  "type": "Feature",
  "properties": {
    "gn:admin1_code":"8.0",
    "gn:asciiname":"Qianshiyicun",
    "gn:country_code":"CN",
    "gn:dem":169,
    "gn:feature_class":"P",
    "gn:feature_code":"PPL",
    "gn:name":"Qianshiyicun",
    "gn:population":0,
    "gn:timezone":"Asia/Shanghai",
    "iso:country":"CN",
    "name:zho_x_preferred":[
        "\u524d\u5341\u4e00\u6751"
    ],
    "wof:name":"Qianshiyicun",
    "wof:placetype":"locality"
},
  "geometry": {"coordinates":[123.55101999999999,47.79648],"type":"Point"}
}