{
  "type": "Feature",
  "properties": {
    "gn:admin1_code":"18",
    "gn:asciiname":"Liling",
    "gn:country_code":"CN",
    "gn:dem":514,
    "gn:feature_class":"P",
    "gn:feature_code":"PPL",
    "gn:name":"Liling",
    "gn:population":0,
    "gn:timezone":"Asia/Shanghai",
    "iso:country":"CN",
    "name:deu_x_preferred":[
        "Liling"
    ],
    "name:fra_x_preferred":[
        "Liling"
    ],
    "name:hak_x_preferred":[
        "Th\u00ed-l\u00een-s\u1e73"
    ],
    "name:ita_x_preferred":[
        "Liling"
    ],
    "name:jpn_x_preferred":[
        "\u91b4\u9675\u5e02"
    ],
    "name:kik_x_preferred":[
        "Liling"
    ],
    "name:kor_x_preferred":[
        "\ub9ac\ub9c1\uc2dc"
    ],
    "name:mlg_x_preferred":[
        "Liling"
    ],
    "name:nor_x_preferred":[
        "Liling"
    ],
    "name:pam_x_preferred":[
        "Liling"
    ],
    "name:pol_x_preferred":[
        "Liling"
    ],
    "name:swe_x_preferred":[
        "Liling"
    ],
    "name:vie_x_preferred":[
        "L\u1ec5 L\u0103ng"
    ],
    "name:war_x_preferred":[
        "Liling"
    ],
    "name:wuu_x_preferred":[
        "\u91b4\u9675\u5e02"
    ],
    "name:zho_x_preferred":[
        "\u91cc\u5cad"
    ],
    "name:zho_x_variant":[
        "\u91b4\u9675\u5e02"
    ],
    "wof:name":"Liling",
    "wof:placetype":"locality"
},
  "geometry": {"coordinates":[106.828,25.4361],"type":"Point"}
}