{
  "type": "Feature",
  "properties": {
    "gn:admin1_code":"32.0",
    "gn:asciiname":"Erjuekeku",
    "gn:country_code":"CN",
    "gn:dem":1809,
    "gn:feature_class":"P",
    "gn:feature_code":"PPL",
    "gn:name":"Erjuekeku",
    "gn:population":0,
    "gn:timezone":"Asia/Shanghai",
    "iso:country":"CN",
    "name:zho_x_preferred":[
        "\u5c14\u89c9\u514b\u82e6"
    ],
    "wof:name":"Erjuekeku",
    "wof:placetype":"locality"
},
  "geometry": {"coordinates":[103.212,28.0787],"type":"Point"}
}