{
  "type": "Feature",
  "properties": {
    "gn:admin1_code":"19.0",
    "gn:asciiname":"Lihugang",
    "gn:country_code":"CN",
    "gn:dem":14,
    "gn:feature_class":"P",
    "gn:feature_code":"PPL",
    "gn:name":"Lihugang",
    "gn:population":0,
    "gn:timezone":"Asia/Shanghai",
    "iso:country":"CN",
    "name:zho_x_preferred":[
        "\u674e\u80e1\u5c97"
    ],
    "wof:name":"Lihugang",
    "wof:placetype":"locality"
},
  "geometry": {"coordinates":[122.52325,41.59874],"type":"Point"}
}