{
  "type": "Feature",
  "properties": {
    "gn:admin1_code":"11.0",
    "gn:asciiname":"Qiaoxia",
    "gn:country_code":"CN",
    "gn:dem":86,
    "gn:feature_class":"P",
    "gn:feature_code":"PPL",
    "gn:name":"Qiaoxia",
    "gn:population":0,
    "gn:timezone":"Asia/Shanghai",
    "iso:country":"CN",
    "name:zho_x_preferred":[
        "\u4e54\u4e0b"
    ],
    "name:zho_x_variant":[
        "\u6865\u4e0b"
    ],
    "wof:name":"Qiaoxia",
    "wof:placetype":"locality"
},
  "geometry": {"coordinates":[113.41616999999999,26.94594],"type":"Point"}
}