{
  "type": "Feature",
  "properties": {
    "gn:admin1_code":"2.0",
    "gn:asciiname":"Liyuqiu",
    "gn:country_code":"CN",
    "gn:dem":304,
    "gn:feature_class":"P",
    "gn:feature_code":"PPL",
    "gn:name":"Liyuqiu",
    "gn:population":0,
    "gn:timezone":"Asia/Shanghai",
    "iso:country":"CN",
    "name:zho_x_preferred":[
        "\u91cc\u9c7c\u4e18"
    ],
    "wof:name":"Liyuqiu",
    "wof:placetype":"locality"
},
  "geometry": {"coordinates":[119.32293,28.20567],"type":"Point"}
}