{
  "type": "Feature",
  "properties": {
    "gn:admin1_code":"30",
    "gn:asciiname":"Ningxin",
    "gn:country_code":"CN",
    "gn:dem":117,
    "gn:feature_class":"P",
    "gn:feature_code":"PPLA4",
    "gn:name":"Ningxin",
    "gn:population":0,
    "gn:timezone":"Asia/Shanghai",
    "iso:country":"CN",
    "name:und_x_variant":[
        "Ningxin Jiedao",
        "Ningxin",
        "Ningxin Zhen"
    ],
    "name:zho_x_preferred":[
        "\u5b81\u65b0"
    ],
    "name:zho_x_variant":[
        "\u5b81\u65b0\u9547",
        "\u5b81\u65b0\u8857\u9053"
    ],
    "wof:name":"Ningxin",
    "wof:placetype":"locality"
},
  "geometry": {"coordinates":[115.75479,24.13797000000001],"type":"Point"}
}