{
  "type": "Feature",
  "properties": {
    "gn:admin1_code":"32",
    "gn:asciiname":"Sanjiang",
    "gn:country_code":"CN",
    "gn:dem":1074,
    "gn:feature_class":"P",
    "gn:feature_code":"PPL",
    "gn:name":"Sanjiang",
    "gn:population":0,
    "gn:timezone":"Asia/Shanghai",
    "iso:country":"CN",
    "name:und_x_variant":[
        "San-chiang-k\u2019ou",
        "Sanjiangkou",
        "Sanjiang"
    ],
    "name:zho_x_preferred":[
        "\u4e09\u6c5f"
    ],
    "wof:name":"Sanjiang",
    "wof:placetype":"locality"
},
  "geometry": {"coordinates":[103.33889000000001,30.91794],"type":"Point"}
}