{
  "type": "Feature",
  "properties": {
    "gn:admin1_code":"9.0",
    "gn:asciiname":"Qiaojia",
    "gn:country_code":"CN",
    "gn:dem":657,
    "gn:feature_class":"P",
    "gn:feature_code":"PPL",
    "gn:name":"Qiaojia",
    "gn:population":0,
    "gn:timezone":"Asia/Shanghai",
    "iso:country":"CN",
    "name:zho_x_preferred":[
        "\u4e54\u5bb6"
    ],
    "wof:name":"Qiaojia",
    "wof:placetype":"locality"
},
  "geometry": {"coordinates":[111.00014,34.0607],"type":"Point"}
}