{
  "type": "Feature",
  "properties": {
    "gn:admin1_code":"26.0",
    "gn:asciiname":"Baishuliang",
    "gn:country_code":"CN",
    "gn:dem":1265,
    "gn:feature_class":"P",
    "gn:feature_code":"PPL",
    "gn:name":"Baishuliang",
    "gn:population":0,
    "gn:timezone":"Asia/Shanghai",
    "iso:country":"CN",
    "name:zho_x_preferred":[
        "\u67cf\u6811\u6881"
    ],
    "wof:name":"Baishuliang",
    "wof:placetype":"locality"
},
  "geometry": {"coordinates":[110.05704,38.44338],"type":"Point"}
}