{
  "type": "Feature",
  "properties": {
    "gn:admin1_code":"02",
    "gn:asciiname":"Canglingkengcun",
    "gn:country_code":"CN",
    "gn:dem":193,
    "gn:feature_class":"P",
    "gn:feature_code":"PPL",
    "gn:name":"Canglingkengcun",
    "gn:population":0,
    "gn:timezone":"Asia/Shanghai",
    "iso:country":"CN",
    "name:und_x_variant":[
        "Ts\u2019ang-ling-k\u2019eng",
        "Canglingkeng",
        "Canglingkengcun"
    ],
    "name:zho_x_preferred":[
        "\u82cd\u5cad\u5751"
    ],
    "name:zho_x_variant":[
        "\u82cd\u5cad\u5751\u6751"
    ],
    "wof:name":"Canglingkengcun",
    "wof:placetype":"locality"
},
  "geometry": {"coordinates":[120.41396,28.74886],"type":"Point"}
}