{
  "type": "Feature",
  "properties": {
    "gn:admin1_code":"32.0",
    "gn:asciiname":"Leiguping",
    "gn:country_code":"CN",
    "gn:dem":574,
    "gn:feature_class":"P",
    "gn:feature_code":"PPL",
    "gn:name":"Leiguping",
    "gn:population":0,
    "gn:timezone":"Asia/Shanghai",
    "iso:country":"CN",
    "name:zho_x_preferred":[
        "\u64c2\u9f13\u576a"
    ],
    "wof:name":"Leiguping",
    "wof:placetype":"locality"
},
  "geometry": {"coordinates":[106.98399999999999,30.4281],"type":"Point"}
}