{
  "type": "Feature",
  "properties": {
    "gn:admin1_code":"29.0",
    "gn:asciiname":"Fuwodema",
    "gn:country_code":"CN",
    "gn:dem":1596,
    "gn:feature_class":"P",
    "gn:feature_code":"PPL",
    "gn:name":"Fuwodema",
    "gn:population":0,
    "gn:timezone":"Asia/Shanghai",
    "iso:country":"CN",
    "name:zho_x_preferred":[
        "\u4ed8\u7a9d\u5f97\u9a6c"
    ],
    "wof:name":"Fuwodema",
    "wof:placetype":"locality"
},
  "geometry": {"coordinates":[100.535,21.8361],"type":"Point"}
}