{
  "type": "Feature",
  "properties": {
    "gn:admin1_code":"18.0",
    "gn:asciiname":"Shangdai",
    "gn:country_code":"CN",
    "gn:dem":653,
    "gn:feature_class":"P",
    "gn:feature_code":"PPL",
    "gn:name":"Shangdai",
    "gn:population":0,
    "gn:timezone":"Asia/Shanghai",
    "iso:country":"CN",
    "name:zho_x_preferred":[
        "\u4e0a\u6b79"
    ],
    "wof:name":"Shangdai",
    "wof:placetype":"locality"
},
  "geometry": {"coordinates":[108.78400000000001,25.8051],"type":"Point"}
}