{
  "type": "Feature",
  "properties": {
    "gn:admin1_code":"32.0",
    "gn:asciiname":"Lianhe",
    "gn:country_code":"CN",
    "gn:dem":447,
    "gn:feature_class":"P",
    "gn:feature_code":"PPL",
    "gn:name":"Lianhe",
    "gn:population":0,
    "gn:timezone":"Asia/Shanghai",
    "iso:country":"CN",
    "name:zho_x_preferred":[
        "\u8054\u548c"
    ],
    "wof:name":"Lianhe",
    "wof:placetype":"locality"
},
  "geometry": {"coordinates":[103.40000000000001,29.8438],"type":"Point"}
}