{
  "type": "Feature",
  "properties": {
    "gn:admin1_code":"9.0",
    "gn:asciiname":"Dachenzhuang",
    "gn:country_code":"CN",
    "gn:dem":46,
    "gn:feature_class":"P",
    "gn:feature_code":"PPL",
    "gn:name":"Dachenzhuang",
    "gn:population":0,
    "gn:timezone":"Asia/Shanghai",
    "iso:country":"CN",
    "name:zho_x_preferred":[
        "\u5927\u9648\u5e84"
    ],
    "wof:name":"Dachenzhuang",
    "wof:placetype":"locality"
},
  "geometry": {"coordinates":[115.00166000000002,33.6472],"type":"Point"}
}