{
  "type": "Feature",
  "properties": {
    "gn:admin1_code":"19.0",
    "gn:asciiname":"Taotun",
    "gn:country_code":"CN",
    "gn:dem":11,
    "gn:feature_class":"P",
    "gn:feature_code":"PPL",
    "gn:name":"Taotun",
    "gn:population":0,
    "gn:timezone":"Asia/Shanghai",
    "iso:country":"CN",
    "name:und_x_variant":[
        "\u9676\u5c6f"
    ],
    "name:zho_x_preferred":[
        "\u9676\u5c6f"
    ],
    "wof:name":"Taotun",
    "wof:placetype":"locality"
},
  "geometry": {"coordinates":[122.68528999999999,39.61993],"type":"Point"}
}