{
  "type": "Feature",
  "properties": {
    "gn:admin1_code":"16.0",
    "gn:asciiname":"Feishuiyan",
    "gn:country_code":"CN",
    "gn:dem":872,
    "gn:feature_class":"P",
    "gn:feature_code":"PPL",
    "gn:name":"Feishuiyan",
    "gn:population":0,
    "gn:timezone":"Asia/Shanghai",
    "iso:country":"CN",
    "name:zho_x_preferred":[
        "\u98de\u6c34\u5ca9"
    ],
    "wof:name":"Feishuiyan",
    "wof:placetype":"locality"
},
  "geometry": {"coordinates":[111.012,24.7875],"type":"Point"}
}