{
  "type": "Feature",
  "properties": {
    "gn:admin1_code":"14.0",
    "gn:asciiname":"Tongre",
    "gn:country_code":"CN",
    "gn:dem":3610,
    "gn:feature_class":"P",
    "gn:feature_code":"PPL",
    "gn:name":"Tongre",
    "gn:population":0,
    "gn:timezone":"Asia/Urumqi",
    "iso:country":"CN",
    "name:zho_x_preferred":[
        "\u901a\u70ed"
    ],
    "wof:name":"Tongre",
    "wof:placetype":"locality"
},
  "geometry": {"coordinates":[94.72939,29.63644],"type":"Point"}
}