{
  "type": "Feature",
  "properties": {
    "gn:admin1_code":"11.0",
    "gn:asciiname":"Pipaxing",
    "gn:country_code":"CN",
    "gn:dem":366,
    "gn:feature_class":"P",
    "gn:feature_code":"PPL",
    "gn:name":"Pipaxing",
    "gn:population":0,
    "gn:timezone":"Asia/Shanghai",
    "iso:country":"CN",
    "name:zho_x_preferred":[
        "\u7435\u7436\u5f62"
    ],
    "wof:name":"Pipaxing",
    "wof:placetype":"locality"
},
  "geometry": {"coordinates":[113.68248,26.53724],"type":"Point"}
}