{
  "type": "Feature",
  "properties": {
    "gn:admin1_code":"32.0",
    "gn:asciiname":"Luolasi",
    "gn:country_code":"CN",
    "gn:dem":3941,
    "gn:feature_class":"P",
    "gn:feature_code":"PPL",
    "gn:name":"Luolasi",
    "gn:population":0,
    "gn:timezone":"Asia/Shanghai",
    "iso:country":"CN",
    "name:zho_x_preferred":[
        "\u6d1b\u62c9\u5bfa"
    ],
    "wof:name":"Luolasi",
    "wof:placetype":"locality"
},
  "geometry": {"coordinates":[101.095,30.5532],"type":"Point"}
}