{
  "type": "Feature",
  "properties": {
    "gn:admin1_code":"16.0",
    "gn:asciiname":"Yanglanqiao",
    "gn:country_code":"CN",
    "gn:dem":134,
    "gn:feature_class":"P",
    "gn:feature_code":"PPL",
    "gn:name":"Yanglanqiao",
    "gn:population":0,
    "gn:timezone":"Asia/Shanghai",
    "iso:country":"CN",
    "name:zho_x_preferred":[
        "\u7f8a\u680f\u6865"
    ],
    "wof:name":"Yanglanqiao",
    "wof:placetype":"locality"
},
  "geometry": {"coordinates":[110.783,24.6693],"type":"Point"}
}