{
  "type": "Feature",
  "properties": {
    "gn:admin1_code":"4.0",
    "gn:asciiname":"Zhaodingcun",
    "gn:country_code":"CN",
    "gn:dem":17,
    "gn:feature_class":"P",
    "gn:feature_code":"PPL",
    "gn:name":"Zhaodingcun",
    "gn:population":0,
    "gn:timezone":"Asia/Shanghai",
    "iso:country":"CN",
    "name:zho_x_preferred":[
        "\u8d75\u9876\u6751"
    ],
    "wof:name":"Zhaodingcun",
    "wof:placetype":"locality"
},
  "geometry": {"coordinates":[118.92128,34.85982],"type":"Point"}
}