{
  "type": "Feature",
  "properties": {
    "gn:admin1_code":"16.0",
    "gn:asciiname":"Nanian",
    "gn:country_code":"CN",
    "gn:dem":788,
    "gn:feature_class":"P",
    "gn:feature_code":"PPL",
    "gn:name":"Nanian",
    "gn:population":0,
    "gn:timezone":"Asia/Shanghai",
    "iso:country":"CN",
    "name:zho_x_preferred":[
        "\u90a3\u5ff5"
    ],
    "wof:name":"Nanian",
    "wof:placetype":"locality"
},
  "geometry": {"coordinates":[105.726,24.232],"type":"Point"}
}