{
  "type": "Feature",
  "properties": {
    "gn:admin1_code":"19.0",
    "gn:asciiname":"Sanwangou",
    "gn:country_code":"CN",
    "gn:dem":431,
    "gn:feature_class":"P",
    "gn:feature_code":"PPL",
    "gn:name":"Sanwangou",
    "gn:population":0,
    "gn:timezone":"Asia/Shanghai",
    "iso:country":"CN",
    "name:und_x_variant":[
        "\u4e09\u6e7e\u6c9f"
    ],
    "wof:name":"Sanwangou",
    "wof:placetype":"locality"
},
  "geometry": {"coordinates":[123.08159000000001,40.76499],"type":"Point"}
}