{
  "type": "Feature",
  "properties": {
    "gn:admin1_code":"25",
    "gn:asciiname":"Chengwucun",
    "gn:country_code":"CN",
    "gn:dem":29,
    "gn:feature_class":"P",
    "gn:feature_code":"PPL",
    "gn:name":"Chengwucun",
    "gn:population":0,
    "gn:timezone":"Asia/Shanghai",
    "iso:country":"CN",
    "name:zho_x_preferred":[
        "\u6210\u4e94\u6751"
    ],
    "wof:name":"Chengwucun",
    "wof:placetype":"locality"
},
  "geometry": {"coordinates":[117.69799999999999,36.8869],"type":"Point"}
}