{
  "type": "Feature",
  "properties": {
    "gn:admin1_code":"9.0",
    "gn:asciiname":"Nihe",
    "gn:country_code":"CN",
    "gn:dem":128,
    "gn:feature_class":"P",
    "gn:feature_code":"PPL",
    "gn:name":"Nihe",
    "gn:population":0,
    "gn:timezone":"Asia/Shanghai",
    "iso:country":"CN",
    "name:zho_x_preferred":[
        "\u502a\u6cb3"
    ],
    "wof:name":"Nihe",
    "wof:placetype":"locality"
},
  "geometry": {"coordinates":[112.98309,32.66189],"type":"Point"}
}