{
  "type": "Feature",
  "properties": {
    "gn:admin1_code":"19.0",
    "gn:asciiname":"Longwangshanzi",
    "gn:country_code":"CN",
    "gn:dem":242,
    "gn:feature_class":"P",
    "gn:feature_code":"PPL",
    "gn:name":"Longwangshanzi",
    "gn:population":0,
    "gn:timezone":"Asia/Shanghai",
    "iso:country":"CN",
    "name:zho_x_preferred":[
        "\u9f99\u738b\u5c71\u5b50"
    ],
    "wof:name":"Longwangshanzi",
    "wof:placetype":"locality"
},
  "geometry": {"coordinates":[120.46290999999999,40.97736],"type":"Point"}
}