{
  "type": "Feature",
  "properties": {
    "gn:admin1_code":"7",
    "gn:asciiname":"Caoxiedian",
    "gn:country_code":"CN",
    "gn:dem":32,
    "gn:feature_class":"P",
    "gn:feature_code":"PPL",
    "gn:name":"Caoxiedian",
    "gn:population":0,
    "gn:timezone":"Asia/Shanghai",
    "iso:country":"CN",
    "name:zho_x_preferred":[
        "\u8349\u978b\u5e97"
    ],
    "wof:name":"Caoxiedian",
    "wof:placetype":"locality"
},
  "geometry": {"coordinates":[117.56233,24.48009],"type":"Point"}
}