{
  "type": "Feature",
  "properties": {
    "gn:admin1_code":"16.0",
    "gn:asciiname":"Siming",
    "gn:country_code":"CN",
    "gn:dem":144,
    "gn:feature_class":"P",
    "gn:feature_code":"PPL",
    "gn:name":"Siming",
    "gn:population":0,
    "gn:timezone":"Asia/Shanghai",
    "iso:country":"CN",
    "name:fra_x_preferred":[
        "Siming"
    ],
    "name:zho_x_preferred":[
        "\u56db\u660e"
    ],
    "wof:name":"Siming",
    "wof:placetype":"locality"
},
  "geometry": {"coordinates":[108.187,23.4045],"type":"Point"}
}