{
  "type": "Feature",
  "properties": {
    "gn:admin1_code":"1.0",
    "gn:asciiname":"Shanmacun",
    "gn:country_code":"CN",
    "gn:dem":58,
    "gn:feature_class":"P",
    "gn:feature_code":"PPL",
    "gn:name":"Shanmacun",
    "gn:population":0,
    "gn:timezone":"Asia/Shanghai",
    "iso:country":"CN",
    "name:zho_x_preferred":[
        "\u5c71\u9a6c\u6751"
    ],
    "wof:name":"Shanmacun",
    "wof:placetype":"locality"
},
  "geometry": {"coordinates":[117.30835,32.67187],"type":"Point"}
}