{
  "type": "Feature",
  "properties": {
    "gn:admin1_code":"29.0",
    "gn:asciiname":"Taoshuzhai",
    "gn:country_code":"CN",
    "gn:dem":1654,
    "gn:feature_class":"P",
    "gn:feature_code":"PPL",
    "gn:name":"Taoshuzhai",
    "gn:population":0,
    "gn:timezone":"Asia/Shanghai",
    "iso:country":"CN",
    "name:zho_x_preferred":[
        "\u6843\u6811\u5be8"
    ],
    "wof:name":"Taoshuzhai",
    "wof:placetype":"locality"
},
  "geometry": {"coordinates":[103.40000000000001,23.6264],"type":"Point"}
}