{
  "type": "Feature",
  "properties": {
    "gn:admin1_code":"24.0",
    "gn:asciiname":"Wangzhuang",
    "gn:country_code":"CN",
    "gn:dem":999,
    "gn:feature_class":"P",
    "gn:feature_code":"PPL",
    "gn:name":"Wangzhuang",
    "gn:population":0,
    "gn:timezone":"Asia/Shanghai",
    "iso:country":"CN",
    "name:und_x_variant":[
        "Wang-chuang",
        "Wangzhuang",
        "\u738b\u5e84"
    ],
    "wof:name":"Wangzhuang",
    "wof:placetype":"locality"
},
  "geometry": {"coordinates":[113.31735,39.75148],"type":"Point"}
}