{
  "type": "Feature",
  "properties": {
    "gn:admin1_code":"1.0",
    "gn:asciiname":"Wangloucun",
    "gn:country_code":"CN",
    "gn:dem":38,
    "gn:feature_class":"P",
    "gn:feature_code":"PPL",
    "gn:name":"Wangloucun",
    "gn:population":0,
    "gn:timezone":"Asia/Shanghai",
    "iso:country":"CN",
    "name:zho_x_preferred":[
        "\u738b\u697c\u6751"
    ],
    "wof:name":"Wangloucun",
    "wof:placetype":"locality"
},
  "geometry": {"coordinates":[116.06541,33.77275],"type":"Point"}
}