{
  "type": "Feature",
  "properties": {
    "gn:admin1_code":"16.0",
    "gn:asciiname":"Shilong",
    "gn:country_code":"CN",
    "gn:dem":172,
    "gn:feature_class":"P",
    "gn:feature_code":"PPL",
    "gn:name":"Shilong",
    "gn:population":0,
    "gn:timezone":"Asia/Shanghai",
    "iso:country":"CN",
    "name:ceb_x_preferred":[
        "Shilong"
    ],
    "name:deu_x_preferred":[
        "Shilong"
    ],
    "name:fra_x_preferred":[
        "Shilong"
    ],
    "name:mlg_x_preferred":[
        "Shilong"
    ],
    "name:sco_x_preferred":[
        "Shilong"
    ],
    "name:zho_x_preferred":[
        "\u77f3\u9f99"
    ],
    "name:zho_x_variant":[
        "\u77f3\u9f99\u9547"
    ],
    "wof:name":"Shilong",
    "wof:placetype":"locality"
},
  "geometry": {"coordinates":[108.474,22.4513],"type":"Point"}
}