{
  "type": "Feature",
  "properties": {
    "gn:admin1_code":"9",
    "gn:asciiname":"Xitaohe",
    "gn:country_code":"CN",
    "gn:dem":55,
    "gn:feature_class":"P",
    "gn:feature_code":"PPL",
    "gn:name":"Xitaohe",
    "gn:population":0,
    "gn:timezone":"Asia/Shanghai",
    "iso:country":"CN",
    "name:zho_x_preferred":[
        "\u897f\u7ee6\u6cb3"
    ],
    "wof:name":"Xitaohe",
    "wof:placetype":"locality"
},
  "geometry": {"coordinates":[115.39675,35.6622],"type":"Point"}
}