{
  "type": "Feature",
  "properties": {
    "gn:admin1_code":"30",
    "gn:asciiname":"Shuanghe",
    "gn:country_code":"CN",
    "gn:dem":38,
    "gn:feature_class":"P",
    "gn:feature_code":"PPL",
    "gn:name":"Shuanghe",
    "gn:population":0,
    "gn:timezone":"Asia/Shanghai",
    "iso:country":"CN",
    "name:und_x_variant":[
        "Shuangzhen",
        "Shuanghe"
    ],
    "name:zho_x_preferred":[
        "\u53cc\u6cb3"
    ],
    "wof:name":"Shuanghe",
    "wof:placetype":"locality"
},
  "geometry": {"coordinates":[115.35512,23.12927],"type":"Point"}
}