{
  "type": "Feature",
  "properties": {
    "gn:admin1_code":"29.0",
    "gn:asciiname":"Dalongtan",
    "gn:country_code":"CN",
    "gn:dem":1744,
    "gn:feature_class":"P",
    "gn:feature_code":"PPL",
    "gn:name":"Dalongtan",
    "gn:population":0,
    "gn:timezone":"Asia/Shanghai",
    "iso:country":"CN",
    "name:zho_x_preferred":[
        "\u5927\u9f99\u6f6d"
    ],
    "wof:name":"Dalongtan",
    "wof:placetype":"locality"
},
  "geometry": {"coordinates":[100.977,24.8056],"type":"Point"}
}