{
  "type": "Feature",
  "properties": {
    "gn:admin1_code":"24.0",
    "gn:asciiname":"Chenhe",
    "gn:country_code":"CN",
    "gn:dem":608,
    "gn:feature_class":"P",
    "gn:feature_code":"PPL",
    "gn:name":"Chenhe",
    "gn:population":0,
    "gn:timezone":"Asia/Shanghai",
    "iso:country":"CN",
    "name:zho_x_preferred":[
        "\u9648\u6cb3"
    ],
    "wof:name":"Chenhe",
    "wof:placetype":"locality"
},
  "geometry": {"coordinates":[112.66622,35.34353],"type":"Point"}
}