{
  "type": "Feature",
  "properties": {
    "gn:admin1_code":"6.0",
    "gn:asciiname":"Youdunzi",
    "gn:cc2":"CN",
    "gn:country_code":"CN",
    "gn:dem":2721,
    "gn:feature_class":"P",
    "gn:feature_code":"PPL",
    "gn:name":"Youdunzi",
    "gn:population":0,
    "gn:timezone":"Asia/Urumqi",
    "iso:country":"CN",
    "name:und_x_variant":[
        "Yu-chuan-tzu",
        "Yu-tun-tzu",
        "Youdunzi"
    ],
    "wof:name":"Youdunzi",
    "wof:placetype":"locality"
},
  "geometry": {"coordinates":[91.91667,38.05],"type":"Point"}
}