{
  "type": "Feature",
  "properties": {
    "gn:admin1_code":"25",
    "gn:asciiname":"Nanpulu",
    "gn:country_code":"CN",
    "gn:dem":199,
    "gn:feature_class":"P",
    "gn:feature_code":"PPL",
    "gn:name":"Nanpulu",
    "gn:population":0,
    "gn:timezone":"Asia/Shanghai",
    "iso:country":"CN",
    "name:zho_x_preferred":[
        "\u5357\u84b2\u82a6"
    ],
    "wof:name":"Nanpulu",
    "wof:placetype":"locality"
},
  "geometry": {"coordinates":[117.60599999999999,35.3991],"type":"Point"}
}