{
  "type": "Feature",
  "properties": {
    "gn:admin1_code":"16",
    "gn:asciiname":"Zhenglong",
    "gn:country_code":"CN",
    "gn:dem":339,
    "gn:feature_class":"P",
    "gn:feature_code":"PPL",
    "gn:name":"Zhenglong",
    "gn:population":0,
    "gn:timezone":"Asia/Shanghai",
    "iso:country":"CN",
    "name:und_x_variant":[
        "Cheng-lung-ts\u2019un",
        "Zhenglong"
    ],
    "name:zho_x_preferred":[
        "\u6b63\u9686"
    ],
    "wof:name":"Zhenglong",
    "wof:placetype":"locality"
},
  "geometry": {"coordinates":[107.23099999999999,22.6859],"type":"Point"}
}