{
  "type": "Feature",
  "properties": {
    "gn:admin1_code":"30.0",
    "gn:asciiname":"Xikengcun",
    "gn:country_code":"CN",
    "gn:dem":238,
    "gn:feature_class":"P",
    "gn:feature_code":"PPL",
    "gn:name":"Xikengcun",
    "gn:population":0,
    "gn:timezone":"Asia/Shanghai",
    "iso:country":"CN",
    "name:zho_x_preferred":[
        "\u897f\u5751\u6751"
    ],
    "wof:name":"Xikengcun",
    "wof:placetype":"locality"
},
  "geometry": {"coordinates":[116.89993,24.31684],"type":"Point"}
}