{
  "type": "Feature",
  "properties": {
    "gn:admin1_code":"12.0",
    "gn:asciiname":"Xingou",
    "gn:country_code":"CN",
    "gn:dem":28,
    "gn:feature_class":"P",
    "gn:feature_code":"PPL",
    "gn:name":"Xingou",
    "gn:population":0,
    "gn:timezone":"Asia/Shanghai",
    "iso:country":"CN",
    "name:eng_x_historical":[
        "Hsin-kou",
        "Sinkow"
    ],
    "name:eng_x_preferred":[
        "Hsin-kou"
    ],
    "name:eng_x_variant":[
        "Sinkow"
    ],
    "name:und_x_variant":[
        "Xingou Zhen"
    ],
    "name:zho_x_preferred":[
        "\u65b0\u6c9f"
    ],
    "name:zho_x_variant":[
        "\u65b0\u6c9f\u9547"
    ],
    "wof:name":"Xingou",
    "wof:placetype":"locality"
},
  "geometry": {"coordinates":[113.94868999999998,30.69505],"type":"Point"}
}