{
  "type": "Feature",
  "properties": {
    "gn:admin1_code":"4.0",
    "gn:asciiname":"Jiulongkoucun",
    "gn:country_code":"CN",
    "gn:dem":-2,
    "gn:feature_class":"P",
    "gn:feature_code":"PPL",
    "gn:name":"Jiulongkoucun",
    "gn:population":0,
    "gn:timezone":"Asia/Shanghai",
    "iso:country":"CN",
    "name:zho_x_preferred":[
        "\u4e5d\u9f99\u53e3\u6751"
    ],
    "wof:name":"Jiulongkoucun",
    "wof:placetype":"locality"
},
  "geometry": {"coordinates":[119.60773,33.39752],"type":"Point"}
}