{
  "type": "Feature",
  "properties": {
    "gn:admin1_code":"11.0",
    "gn:asciiname":"Xinglong",
    "gn:country_code":"CN",
    "gn:dem":294,
    "gn:feature_class":"P",
    "gn:feature_code":"PPL",
    "gn:name":"Xinglong",
    "gn:population":0,
    "gn:timezone":"Asia/Shanghai",
    "iso:country":"CN",
    "name:ceb_x_preferred":[
        "Xinglong"
    ],
    "name:deu_x_preferred":[
        "Xinglong"
    ],
    "name:zho_x_preferred":[
        "\u674f\u9f99"
    ],
    "wof:name":"Xinglong",
    "wof:placetype":"locality"
},
  "geometry": {"coordinates":[113.76094000000001,28.42752],"type":"Point"}
}