{
  "type": "Feature",
  "properties": {
    "gn:admin1_code":"12.0",
    "gn:asciiname":"Hebaohu",
    "gn:country_code":"CN",
    "gn:dem":26,
    "gn:feature_class":"P",
    "gn:feature_code":"PPLA4",
    "gn:name":"Hebaohu",
    "gn:population":0,
    "gn:timezone":"Asia/Shanghai",
    "iso:country":"CN",
    "name:und_x_variant":[
        "Hebaohu Jiedao"
    ],
    "name:zho_x_preferred":[
        "\u8377\u82de\u6e56"
    ],
    "name:zho_x_variant":[
        "\u8377\u82de\u6e56\u8857\u9053"
    ],
    "wof:name":"Hebaohu",
    "wof:placetype":"locality"
},
  "geometry": {"coordinates":[113.97228,30.70128],"type":"Point"}
}