{
  "type": "Feature",
  "properties": {
    "gn:admin1_code":"32.0",
    "gn:asciiname":"Gusheping",
    "gn:country_code":"CN",
    "gn:dem":958,
    "gn:feature_class":"P",
    "gn:feature_code":"PPL",
    "gn:name":"Gusheping",
    "gn:population":0,
    "gn:timezone":"Asia/Shanghai",
    "iso:country":"CN",
    "name:zho_x_preferred":[
        "\u53e4\u793e\u576a"
    ],
    "wof:name":"Gusheping",
    "wof:placetype":"locality"
},
  "geometry": {"coordinates":[107.64635,31.90217],"type":"Point"}
}