{
  "type": "Feature",
  "properties": {
    "gn:admin1_code":"1.0",
    "gn:asciiname":"Hongxincun",
    "gn:country_code":"CN",
    "gn:dem":157,
    "gn:feature_class":"P",
    "gn:feature_code":"PPL",
    "gn:name":"Hongxincun",
    "gn:population":0,
    "gn:timezone":"Asia/Shanghai",
    "iso:country":"CN",
    "name:zho_x_preferred":[
        "\u7ea2\u5fc3\u6751"
    ],
    "wof:name":"Hongxincun",
    "wof:placetype":"locality"
},
  "geometry": {"coordinates":[118.21991,29.81293],"type":"Point"}
}