{
  "type": "Feature",
  "properties": {
    "gn:admin1_code":"9.0",
    "gn:asciiname":"Xiangshan",
    "gn:country_code":"CN",
    "gn:dem":93,
    "gn:feature_class":"P",
    "gn:feature_code":"PPL",
    "gn:name":"Xiangshan",
    "gn:population":0,
    "gn:timezone":"Asia/Shanghai",
    "iso:country":"CN",
    "name:zho_x_preferred":[
        "\u54cd\u5c71"
    ],
    "wof:name":"Xiangshan",
    "wof:placetype":"locality"
},
  "geometry": {"coordinates":[114.10969,32.05035],"type":"Point"}
}