{
  "type": "Feature",
  "properties": {
    "gn:admin1_code":"11",
    "gn:asciiname":"Shangbaixiang",
    "gn:country_code":"CN",
    "gn:dem":242,
    "gn:feature_class":"P",
    "gn:feature_code":"PPL",
    "gn:name":"Shangbaixiang",
    "gn:population":0,
    "gn:timezone":"Asia/Shanghai",
    "iso:country":"CN",
    "name:zho_x_preferred":[
        "\u4e0a\u767d\u8c61"
    ],
    "wof:name":"Shangbaixiang",
    "wof:placetype":"locality"
},
  "geometry": {"coordinates":[111.08754999999999,25.05782],"type":"Point"}
}