{
  "type": "Feature",
  "properties": {
    "gn:admin1_code":"16.0",
    "gn:asciiname":"Nongkang",
    "gn:country_code":"CN",
    "gn:dem":673,
    "gn:feature_class":"P",
    "gn:feature_code":"PPL",
    "gn:name":"Nongkang",
    "gn:population":0,
    "gn:timezone":"Asia/Shanghai",
    "iso:country":"CN",
    "name:zho_x_preferred":[
        "\u5f04\u6297"
    ],
    "wof:name":"Nongkang",
    "wof:placetype":"locality"
},
  "geometry": {"coordinates":[107.458,24.4097],"type":"Point"}
}