{
  "type": "Feature",
  "properties": {
    "gn:admin1_code":"26.0",
    "gn:asciiname":"Shunxiaocun",
    "gn:country_code":"CN",
    "gn:dem":875,
    "gn:feature_class":"P",
    "gn:feature_code":"PPL",
    "gn:name":"Shunxiaocun",
    "gn:population":0,
    "gn:timezone":"Asia/Shanghai",
    "iso:country":"CN",
    "name:zho_x_preferred":[
        "\u987a\u5b5d\u6751"
    ],
    "wof:name":"Shunxiaocun",
    "wof:placetype":"locality"
},
  "geometry": {"coordinates":[109.54313999999999,35.37832],"type":"Point"}
}