{
  "type": "Feature",
  "properties": {
    "gn:admin1_code":"15.0",
    "gn:asciiname":"Jingou",
    "gn:country_code":"CN",
    "gn:dem":2893,
    "gn:feature_class":"P",
    "gn:feature_code":"PPL",
    "gn:name":"Jingou",
    "gn:population":0,
    "gn:timezone":"Asia/Urumqi",
    "iso:country":"CN",
    "name:zho_x_preferred":[
        "\u91d1\u6c9f"
    ],
    "wof:name":"Jingou",
    "wof:placetype":"locality"
},
  "geometry": {"coordinates":[97.0949,39.6988],"type":"Point"}
}