{
  "type": "Feature",
  "properties": {
    "gn:admin1_code":"30.0",
    "gn:asciiname":"Liutang",
    "gn:country_code":"CN",
    "gn:dem":314,
    "gn:feature_class":"P",
    "gn:feature_code":"PPL",
    "gn:name":"Liutang",
    "gn:population":0,
    "gn:timezone":"Asia/Shanghai",
    "iso:country":"CN",
    "name:zho_x_preferred":[
        "Liutang"
    ],
    "name:zho_x_variant":[
        "\u67f3\u5858"
    ],
    "wof:name":"Liutang",
    "wof:placetype":"locality"
},
  "geometry": {"coordinates":[112.72139,24.51],"type":"Point"}
}