{
  "type": "Feature",
  "properties": {
    "gn:admin1_code":"15.0",
    "gn:asciiname":"Fangzigou",
    "gn:country_code":"CN",
    "gn:dem":2370,
    "gn:feature_class":"P",
    "gn:feature_code":"PPL",
    "gn:name":"Fangzigou",
    "gn:population":0,
    "gn:timezone":"Asia/Shanghai",
    "iso:country":"CN",
    "name:zho_x_preferred":[
        "\u623f\u5b50\u6c9f"
    ],
    "wof:name":"Fangzigou",
    "wof:placetype":"locality"
},
  "geometry": {"coordinates":[103.485,35.92800000000001],"type":"Point"}
}