{
  "type": "Feature",
  "properties": {
    "gn:admin1_code":"1.0",
    "gn:asciiname":"Wubiancun",
    "gn:country_code":"CN",
    "gn:dem":75,
    "gn:feature_class":"P",
    "gn:feature_code":"PPL",
    "gn:name":"Wubiancun",
    "gn:population":0,
    "gn:timezone":"Asia/Shanghai",
    "iso:country":"CN",
    "name:zho_x_preferred":[
        "\u4e4c\u8fb9\u6751"
    ],
    "wof:name":"Wubiancun",
    "wof:placetype":"locality"
},
  "geometry": {"coordinates":[118.81988,30.82727],"type":"Point"}
}