{
  "type": "Feature",
  "properties": {
    "gn:admin1_code":"30.0",
    "gn:asciiname":"Wutoukeng",
    "gn:country_code":"CN",
    "gn:dem":140,
    "gn:feature_class":"P",
    "gn:feature_code":"PPL",
    "gn:name":"Wutoukeng",
    "gn:population":0,
    "gn:timezone":"Asia/Shanghai",
    "iso:country":"CN",
    "name:zho_x_preferred":[
        "Wutoukeng"
    ],
    "name:zho_x_variant":[
        "\u5c4b\u5934\u5751"
    ],
    "wof:name":"Wutoukeng",
    "wof:placetype":"locality"
},
  "geometry": {"coordinates":[114.89864,24.20455],"type":"Point"}
}