{
  "type": "Feature",
  "properties": {
    "gn:admin1_code":"32.0",
    "gn:asciiname":"Changliangshan",
    "gn:country_code":"CN",
    "gn:dem":749,
    "gn:feature_class":"P",
    "gn:feature_code":"PPL",
    "gn:name":"Changliangshan",
    "gn:population":0,
    "gn:timezone":"Asia/Shanghai",
    "iso:country":"CN",
    "name:zho_x_preferred":[
        "\u957f\u6881\u5c71"
    ],
    "wof:name":"Changliangshan",
    "wof:placetype":"locality"
},
  "geometry": {"coordinates":[105.54537999999999,32.5834],"type":"Point"}
}