{
  "type": "Feature",
  "properties": {
    "gn:admin1_code":"02",
    "gn:asciiname":"Wujia Shanxia",
    "gn:country_code":"CN",
    "gn:dem":12,
    "gn:feature_class":"P",
    "gn:feature_code":"PPL",
    "gn:name":"Wujia Shanxia",
    "gn:population":0,
    "gn:timezone":"Asia/Shanghai",
    "iso:country":"CN",
    "name:und_x_variant":[
        "Wu-chia-shan-hsia",
        "Wujia Shanxia"
    ],
    "wof:name":"Wujia Shanxia",
    "wof:placetype":"locality"
},
  "geometry": {"coordinates":[122.19167,30.01056],"type":"Point"}
}