{
  "type": "Feature",
  "properties": {
    "gn:admin1_code":"4.0",
    "gn:asciiname":"Zhongjingcun",
    "gn:country_code":"CN",
    "gn:dem":5,
    "gn:feature_class":"P",
    "gn:feature_code":"PPL",
    "gn:name":"Zhongjingcun",
    "gn:population":0,
    "gn:timezone":"Asia/Shanghai",
    "iso:country":"CN",
    "name:und_x_variant":[
        "\u4e2d\u6cfe\u6751"
    ],
    "name:zho_x_preferred":[
        "\u4e2d\u6cfe\u6751"
    ],
    "wof:name":"Zhongjingcun",
    "wof:placetype":"locality"
},
  "geometry": {"coordinates":[120.70269999999999,31.73969],"type":"Point"}
}