{
  "type": "Feature",
  "properties": {
    "gn:admin1_code":"32.0",
    "gn:asciiname":"Hanlin",
    "gn:country_code":"CN",
    "gn:dem":326,
    "gn:feature_class":"P",
    "gn:feature_code":"PPL",
    "gn:name":"Hanlin",
    "gn:population":0,
    "gn:timezone":"Asia/Shanghai",
    "iso:country":"CN",
    "name:zho_x_preferred":[
        "\u7ff0\u6797"
    ],
    "wof:name":"Hanlin",
    "wof:placetype":"locality"
},
  "geometry": {"coordinates":[105.702,30.4983],"type":"Point"}
}