{
  "type": "Feature",
  "properties": {
    "gn:admin1_code":"32.0",
    "gn:asciiname":"Fengkou",
    "gn:country_code":"CN",
    "gn:dem":503,
    "gn:feature_class":"P",
    "gn:feature_code":"PPL",
    "gn:name":"Fengkou",
    "gn:population":0,
    "gn:timezone":"Asia/Shanghai",
    "iso:country":"CN",
    "name:zho_x_preferred":[
        "\u5c01\u53e3"
    ],
    "wof:name":"Fengkou",
    "wof:placetype":"locality"
},
  "geometry": {"coordinates":[107.438,31.3512],"type":"Point"}
}