{
  "type": "Feature",
  "properties": {
    "gn:admin1_code":"26.0",
    "gn:asciiname":"Xiyaokecun",
    "gn:country_code":"CN",
    "gn:dem":1208,
    "gn:feature_class":"P",
    "gn:feature_code":"PPL",
    "gn:name":"Xiyaokecun",
    "gn:population":0,
    "gn:timezone":"Asia/Shanghai",
    "iso:country":"CN",
    "name:zho_x_preferred":[
        "\u897f\u7a91\u79d1\u6751"
    ],
    "wof:name":"Xiyaokecun",
    "wof:placetype":"locality"
},
  "geometry": {"coordinates":[109.14492,35.72755],"type":"Point"}
}