{
  "type": "Feature",
  "properties": {
    "gn:admin1_code":"25.0",
    "gn:asciiname":"Xiaguan Legou",
    "gn:country_code":"CN",
    "gn:dem":41,
    "gn:feature_class":"P",
    "gn:feature_code":"PPL",
    "gn:name":"Xiaguan Legou",
    "gn:population":0,
    "gn:timezone":"Asia/Shanghai",
    "iso:country":"CN",
    "name:zho_x_preferred":[
        "\u4e0b\u5b98\u4e50\u6c9f"
    ],
    "wof:name":"Xiaguan Legou",
    "wof:placetype":"locality"
},
  "geometry": {"coordinates":[121.17247999999999,37.40472000000001],"type":"Point"}
}