{
  "type": "Feature",
  "properties": {
    "gn:admin1_code":"30.0",
    "gn:asciiname":"Dadongkeng",
    "gn:country_code":"CN",
    "gn:dem":785,
    "gn:feature_class":"P",
    "gn:feature_code":"PPL",
    "gn:name":"Dadongkeng",
    "gn:population":0,
    "gn:timezone":"Asia/Shanghai",
    "iso:country":"CN",
    "name:zho_x_preferred":[
        "Dadongkeng"
    ],
    "name:zho_x_variant":[
        "\u5927\u4e1c\u5751"
    ],
    "wof:name":"Dadongkeng",
    "wof:placetype":"locality"
},
  "geometry": {"coordinates":[112.28028,24.58833],"type":"Point"}
}