{
  "type": "Feature",
  "properties": {
    "gn:admin1_code":"32.0",
    "gn:asciiname":"Jiaomoxiasha",
    "gn:country_code":"CN",
    "gn:dem":1606,
    "gn:feature_class":"P",
    "gn:feature_code":"PPL",
    "gn:name":"Jiaomoxiasha",
    "gn:population":0,
    "gn:timezone":"Asia/Shanghai",
    "iso:country":"CN",
    "name:zho_x_preferred":[
        "\u811a\u83ab\u5477\u6c99"
    ],
    "wof:name":"Jiaomoxiasha",
    "wof:placetype":"locality"
},
  "geometry": {"coordinates":[102.706,29.2883],"type":"Point"}
}