{
  "type": "Feature",
  "properties": {
    "gn:admin1_code":"16.0",
    "gn:asciiname":"Zhenglan",
    "gn:country_code":"CN",
    "gn:dem":146,
    "gn:feature_class":"P",
    "gn:feature_code":"PPL",
    "gn:name":"Zhenglan",
    "gn:population":0,
    "gn:timezone":"Asia/Shanghai",
    "iso:country":"CN",
    "name:zho_x_preferred":[
        "\u6b63\u5170"
    ],
    "wof:name":"Zhenglan",
    "wof:placetype":"locality"
},
  "geometry": {"coordinates":[109.09999999999999,24.413],"type":"Point"}
}