{
  "type": "Feature",
  "properties": {
    "gn:admin1_code":"19.0",
    "gn:asciiname":"Heidaocun",
    "gn:country_code":"CN",
    "gn:dem":64,
    "gn:feature_class":"P",
    "gn:feature_code":"PPL",
    "gn:name":"Heidaocun",
    "gn:population":0,
    "gn:timezone":"Asia/Shanghai",
    "iso:country":"CN",
    "name:zho_x_preferred":[
        "\u9ed1\u5c9b\u6751"
    ],
    "wof:name":"Heidaocun",
    "wof:placetype":"locality"
},
  "geometry": {"coordinates":[123.24249,39.70908],"type":"Point"}
}