{
  "type": "Feature",
  "properties": {
    "gn:admin1_code":"3.0",
    "gn:asciiname":"Qikengcun",
    "gn:country_code":"CN",
    "gn:dem":299,
    "gn:feature_class":"P",
    "gn:feature_code":"PPL",
    "gn:name":"Qikengcun",
    "gn:population":0,
    "gn:timezone":"Asia/Shanghai",
    "iso:country":"CN",
    "name:und_x_variant":[
        "\u5176\u5751\u6751"
    ],
    "wof:name":"Qikengcun",
    "wof:placetype":"locality"
},
  "geometry": {"coordinates":[115.67274,26.84742],"type":"Point"}
}