{
  "type": "Feature",
  "properties": {
    "gn:admin1_code":"4.0",
    "gn:asciiname":"Wangxuewucun",
    "gn:country_code":"CN",
    "gn:dem":45,
    "gn:feature_class":"P",
    "gn:feature_code":"PPL",
    "gn:name":"Wangxuewucun",
    "gn:population":0,
    "gn:timezone":"Asia/Shanghai",
    "iso:country":"CN",
    "name:zho_x_preferred":[
        "\u738b\u5b66\u5c4b\u6751"
    ],
    "wof:name":"Wangxuewucun",
    "wof:placetype":"locality"
},
  "geometry": {"coordinates":[116.4375,34.72449],"type":"Point"}
}