{
  "type": "Feature",
  "properties": {
    "gn:admin1_code":"4.0",
    "gn:asciiname":"Maxiangtou",
    "gn:country_code":"CN",
    "gn:dem":2,
    "gn:feature_class":"P",
    "gn:feature_code":"PPL",
    "gn:name":"Maxiangtou",
    "gn:population":0,
    "gn:timezone":"Asia/Shanghai",
    "iso:country":"CN",
    "name:zho_x_preferred":[
        "Maxiangtou"
    ],
    "name:zho_x_variant":[
        "\u9a6c\u5df7\u5934"
    ],
    "wof:name":"Maxiangtou",
    "wof:placetype":"locality"
},
  "geometry": {"coordinates":[119.42236,33.50382],"type":"Point"}
}