{
  "type": "Feature",
  "properties": {
    "gn:admin1_code":"16.0",
    "gn:asciiname":"Dadongjiang",
    "gn:country_code":"CN",
    "gn:dem":482,
    "gn:feature_class":"P",
    "gn:feature_code":"PPL",
    "gn:name":"Dadongjiang",
    "gn:population":0,
    "gn:timezone":"Asia/Shanghai",
    "iso:country":"CN",
    "name:zho_x_preferred":[
        "\u5927\u4e1c\u6c5f"
    ],
    "wof:name":"Dadongjiang",
    "wof:placetype":"locality"
},
  "geometry": {"coordinates":[109.071,25.3649],"type":"Point"}
}