{
  "type": "Feature",
  "properties": {
    "gn:admin1_code":"26.0",
    "gn:asciiname":"Jiangjiashangou",
    "gn:country_code":"CN",
    "gn:dem":1113,
    "gn:feature_class":"P",
    "gn:feature_code":"PPL",
    "gn:name":"Jiangjiashangou",
    "gn:population":0,
    "gn:timezone":"Asia/Shanghai",
    "iso:country":"CN",
    "name:zho_x_preferred":[
        "\u59dc\u5bb6\u5c71\u6c9f"
    ],
    "wof:name":"Jiangjiashangou",
    "wof:placetype":"locality"
},
  "geometry": {"coordinates":[109.58031,34.21144],"type":"Point"}
}