{
  "type": "Feature",
  "properties": {
    "gn:admin1_code":"32.0",
    "gn:asciiname":"Waniao",
    "gn:country_code":"CN",
    "gn:dem":2512,
    "gn:feature_class":"P",
    "gn:feature_code":"PPL",
    "gn:name":"Waniao",
    "gn:population":0,
    "gn:timezone":"Asia/Shanghai",
    "iso:country":"CN",
    "name:zho_x_preferred":[
        "\u6316\u9e1f"
    ],
    "wof:name":"Waniao",
    "wof:placetype":"locality"
},
  "geometry": {"coordinates":[103.04000000000001,28.4701],"type":"Point"}
}