{
  "type": "Feature",
  "properties": {
    "gn:admin1_code":"11.0",
    "gn:asciiname":"Shiya",
    "gn:country_code":"CN",
    "gn:dem":81,
    "gn:feature_class":"P",
    "gn:feature_code":"PPL",
    "gn:name":"Shiya",
    "gn:population":0,
    "gn:timezone":"Asia/Shanghai",
    "iso:country":"CN",
    "name:zho_x_preferred":[
        "Shiya"
    ],
    "name:zho_x_variant":[
        "\u77f3\u57ad"
    ],
    "wof:name":"Shiya",
    "wof:placetype":"locality"
},
  "geometry": {"coordinates":[111.55606,29.2851],"type":"Point"}
}