{
  "type": "Feature",
  "properties": {
    "gn:admin1_code":"26",
    "gn:asciiname":"Baiwang",
    "gn:country_code":"CN",
    "gn:dem":570,
    "gn:feature_class":"P",
    "gn:feature_code":"PPLA4",
    "gn:name":"Baiwang",
    "gn:population":0,
    "gn:timezone":"Asia/Shanghai",
    "iso:country":"CN",
    "name:und_x_variant":[
        "Baiwang Zhen",
        "Baiwang"
    ],
    "name:zho_x_preferred":[
        "\u767d\u738b"
    ],
    "name:zho_x_variant":[
        "\u767d\u738b\u9547"
    ],
    "wof:name":"Baiwang",
    "wof:placetype":"locality"
},
  "geometry": {"coordinates":[108.64910999999999,34.67333],"type":"Point"}
}