{
  "type": "Feature",
  "properties": {
    "gn:admin1_code":"18",
    "gn:asciiname":"Zheliucun",
    "gn:country_code":"CN",
    "gn:dem":894,
    "gn:feature_class":"P",
    "gn:feature_code":"PPL",
    "gn:name":"Zheliucun",
    "gn:population":0,
    "gn:timezone":"Asia/Shanghai",
    "iso:country":"CN",
    "name:zho_x_preferred":[
        "\u8005\u516d\u6751"
    ],
    "wof:name":"Zheliucun",
    "wof:placetype":"locality"
},
  "geometry": {"coordinates":[105.67100000000001,24.939],"type":"Point"}
}