{
  "type": "Feature",
  "properties": {
    "gn:admin1_code":"11.0",
    "gn:asciiname":"Choulichong",
    "gn:country_code":"CN",
    "gn:dem":81,
    "gn:feature_class":"P",
    "gn:feature_code":"PPL",
    "gn:name":"Choulichong",
    "gn:population":0,
    "gn:timezone":"Asia/Shanghai",
    "iso:country":"CN",
    "name:zho_x_preferred":[
        "\u4ec7\u7406\u51b2"
    ],
    "wof:name":"Choulichong",
    "wof:placetype":"locality"
},
  "geometry": {"coordinates":[113.10624,28.75879],"type":"Point"}
}