{
  "type": "Feature",
  "properties": {
    "gn:admin1_code":"32.0",
    "gn:asciiname":"Ergu",
    "gn:country_code":"CN",
    "gn:dem":1108,
    "gn:feature_class":"P",
    "gn:feature_code":"PPL",
    "gn:name":"Ergu",
    "gn:population":0,
    "gn:timezone":"Asia/Shanghai",
    "iso:country":"CN",
    "name:zho_x_preferred":[
        "\u5c14\u59d1"
    ],
    "wof:name":"Ergu",
    "wof:placetype":"locality"
},
  "geometry": {"coordinates":[102.746,29.0127],"type":"Point"}
}