{
  "type": "Feature",
  "properties": {
    "gn:admin1_code":"30.0",
    "gn:asciiname":"Lunlang",
    "gn:country_code":"CN",
    "gn:dem":214,
    "gn:feature_class":"P",
    "gn:feature_code":"PPL",
    "gn:name":"Lunlang",
    "gn:population":0,
    "gn:timezone":"Asia/Shanghai",
    "iso:country":"CN",
    "name:zho_x_preferred":[
        "\u6ca6\u6d6a"
    ],
    "wof:name":"Lunlang",
    "wof:placetype":"locality"
},
  "geometry": {"coordinates":[114.62393,25.30709],"type":"Point"}
}