{
  "type": "Feature",
  "properties": {
    "gn:admin1_code":"8.0",
    "gn:asciiname":"Hanjia Fenfang",
    "gn:country_code":"CN",
    "gn:dem":141,
    "gn:feature_class":"P",
    "gn:feature_code":"PPL",
    "gn:name":"Hanjia Fenfang",
    "gn:population":0,
    "gn:timezone":"Asia/Shanghai",
    "iso:country":"CN",
    "name:zho_x_preferred":[
        "\u97e9\u5bb6\u7c89\u623f"
    ],
    "wof:name":"Hanjia Fenfang",
    "wof:placetype":"locality"
},
  "geometry": {"coordinates":[125.17089,45.73254],"type":"Point"}
}