{
  "type": "Feature",
  "properties": {
    "gn:admin1_code":"4.0",
    "gn:asciiname":"Shibaxudai",
    "gn:country_code":"CN",
    "gn:dem":5,
    "gn:feature_class":"P",
    "gn:feature_code":"PPL",
    "gn:name":"Shibaxudai",
    "gn:population":0,
    "gn:timezone":"Asia/Shanghai",
    "iso:country":"CN",
    "name:zho_x_preferred":[
        "\u5341\u516b\u5729\u57ed"
    ],
    "wof:name":"Shibaxudai",
    "wof:placetype":"locality"
},
  "geometry": {"coordinates":[119.84887999999999,32.24195],"type":"Point"}
}