{
  "type": "Feature",
  "properties": {
    "gn:admin1_code":"14.0",
    "gn:asciiname":"Luokang",
    "gn:country_code":"CN",
    "gn:dem":4582,
    "gn:feature_class":"P",
    "gn:feature_code":"PPL",
    "gn:name":"Luokang",
    "gn:population":0,
    "gn:timezone":"Asia/Urumqi",
    "iso:country":"CN",
    "name:zho_x_preferred":[
        "\u7f57\u5eb7"
    ],
    "wof:name":"Luokang",
    "wof:placetype":"locality"
},
  "geometry": {"coordinates":[83.49590000000001,30.0198],"type":"Point"}
}