{
  "type": "Feature",
  "properties": {
    "gn:admin1_code":"16.0",
    "gn:asciiname":"Miaobei",
    "gn:country_code":"CN",
    "gn:dem":112,
    "gn:feature_class":"P",
    "gn:feature_code":"PPL",
    "gn:name":"Miaobei",
    "gn:population":0,
    "gn:timezone":"Asia/Shanghai",
    "iso:country":"CN",
    "name:zho_x_preferred":[
        "\u5999\u8d1d"
    ],
    "wof:name":"Miaobei",
    "wof:placetype":"locality"
},
  "geometry": {"coordinates":[109.146,24.6572],"type":"Point"}
}