{
  "type": "Feature",
  "properties": {
    "gn:admin1_code":"21.0",
    "gn:asciiname":"Yangshanwa",
    "gn:country_code":"CN",
    "gn:dem":1778,
    "gn:feature_class":"P",
    "gn:feature_code":"PPL",
    "gn:name":"Yangshanwa",
    "gn:population":0,
    "gn:timezone":"Asia/Shanghai",
    "iso:country":"CN",
    "name:zho_x_preferred":[
        "\u9633\u5c71\u6d3c"
    ],
    "wof:name":"Yangshanwa",
    "wof:placetype":"locality"
},
  "geometry": {"coordinates":[106.61641000000002,36.26936],"type":"Point"}
}