{
  "type": "Feature",
  "properties": {
    "gn:admin1_code":"10.0",
    "gn:asciiname":"Shanghulugou",
    "gn:country_code":"CN",
    "gn:dem":296,
    "gn:feature_class":"P",
    "gn:feature_code":"PPL",
    "gn:name":"Shanghulugou",
    "gn:population":0,
    "gn:timezone":"Asia/Shanghai",
    "iso:country":"CN",
    "name:und_x_variant":[
        "\u4e0a\u846b\u82a6\u6c9f"
    ],
    "wof:name":"Shanghulugou",
    "wof:placetype":"locality"
},
  "geometry": {"coordinates":[114.23945000000001,38.7594],"type":"Point"}
}