{
  "type": "Feature",
  "properties": {
    "gn:admin1_code":"11.0",
    "gn:asciiname":"Baiwu",
    "gn:country_code":"CN",
    "gn:dem":60,
    "gn:feature_class":"P",
    "gn:feature_code":"PPL",
    "gn:name":"Baiwu",
    "gn:population":0,
    "gn:timezone":"Asia/Shanghai",
    "iso:country":"CN",
    "name:zho_x_preferred":[
        "\u767d\u5c4b"
    ],
    "wof:name":"Baiwu",
    "wof:placetype":"locality"
},
  "geometry": {"coordinates":[112.70052,27.51615],"type":"Point"}
}