{
  "type": "Feature",
  "properties": {
    "gn:admin1_code":"19.0",
    "gn:asciiname":"Beifangzi",
    "gn:country_code":"CN",
    "gn:dem":98,
    "gn:feature_class":"P",
    "gn:feature_code":"PPL",
    "gn:name":"Beifangzi",
    "gn:population":0,
    "gn:timezone":"Asia/Shanghai",
    "iso:country":"CN",
    "name:zho_x_preferred":[
        "\u5317\u623f\u5b50"
    ],
    "wof:name":"Beifangzi",
    "wof:placetype":"locality"
},
  "geometry": {"coordinates":[122.9736,40.70671],"type":"Point"}
}