{
  "type": "Feature",
  "properties": {
    "gn:admin1_code":"9.0",
    "gn:asciiname":"Xiaoyangzhai",
    "gn:country_code":"CN",
    "gn:dem":168,
    "gn:feature_class":"P",
    "gn:feature_code":"PPL",
    "gn:name":"Xiaoyangzhai",
    "gn:population":0,
    "gn:timezone":"Asia/Shanghai",
    "iso:country":"CN",
    "name:zho_x_preferred":[
        "\u5c0f\u6768\u5be8"
    ],
    "wof:name":"Xiaoyangzhai",
    "wof:placetype":"locality"
},
  "geometry": {"coordinates":[112.00626,32.87863],"type":"Point"}
}