{
  "type": "Feature",
  "properties": {
    "gn:admin1_code":"3.0",
    "gn:asciiname":"Jiashan",
    "gn:country_code":"CN",
    "gn:dem":210,
    "gn:feature_class":"P",
    "gn:feature_code":"PPL",
    "gn:name":"Jiashan",
    "gn:population":0,
    "gn:timezone":"Asia/Shanghai",
    "iso:country":"CN",
    "name:zho_x_preferred":[
        "\u52a0\u5c71"
    ],
    "wof:name":"Jiashan",
    "wof:placetype":"locality"
},
  "geometry": {"coordinates":[114.18600000000001,27.2978],"type":"Point"}
}