{
  "type": "Feature",
  "properties": {
    "gn:admin1_code":"29.0",
    "gn:asciiname":"Dayanzi",
    "gn:country_code":"CN",
    "gn:dem":2375,
    "gn:feature_class":"P",
    "gn:feature_code":"PPL",
    "gn:name":"Dayanzi",
    "gn:population":0,
    "gn:timezone":"Asia/Shanghai",
    "iso:country":"CN",
    "name:zho_x_preferred":[
        "\u5927\u5ca9\u5b50"
    ],
    "wof:name":"Dayanzi",
    "wof:placetype":"locality"
},
  "geometry": {"coordinates":[99.27119999999999,23.8493],"type":"Point"}
}