{
  "type": "Feature",
  "properties": {
    "gn:admin1_code":"10.0",
    "gn:asciiname":"Gangtou",
    "gn:country_code":"CN",
    "gn:dem":129,
    "gn:feature_class":"P",
    "gn:feature_code":"PPL",
    "gn:name":"Gangtou",
    "gn:population":0,
    "gn:timezone":"Asia/Shanghai",
    "iso:country":"CN",
    "name:und_x_variant":[
        "\u5c97\u5934"
    ],
    "wof:name":"Gangtou",
    "wof:placetype":"locality"
},
  "geometry": {"coordinates":[114.42252999999999,38.41359],"type":"Point"}
}