{
  "type": "Feature",
  "properties": {
    "gn:admin1_code":"4.0",
    "gn:asciiname":"Shuang'an",
    "gn:country_code":"CN",
    "gn:dem":14,
    "gn:feature_class":"P",
    "gn:feature_code":"PPL",
    "gn:name":"Shuang\u2019an",
    "gn:population":0,
    "gn:timezone":"Asia/Shanghai",
    "iso:country":"CN",
    "name:und_x_variant":[
        "Shuang\u2019an"
    ],
    "name:zho_x_preferred":[
        "\u53cc\u5b89"
    ],
    "wof:name":"Shuang'an",
    "wof:placetype":"locality"
},
  "geometry": {"coordinates":[118.73492,33.70148],"type":"Point"}
}