{
  "type": "Feature",
  "properties": {
    "gn:admin1_code":"15.0",
    "gn:asciiname":"Damalianshui",
    "gn:country_code":"CN",
    "gn:dem":2108,
    "gn:feature_class":"P",
    "gn:feature_code":"PPL",
    "gn:name":"Damalianshui",
    "gn:population":0,
    "gn:timezone":"Asia/Shanghai",
    "iso:country":"CN",
    "name:zho_x_preferred":[
        "\u5927\u9a6c\u83b2\u6c34"
    ],
    "wof:name":"Damalianshui",
    "wof:placetype":"locality"
},
  "geometry": {"coordinates":[103.90900000000001,36.9866],"type":"Point"}
}