{
  "type": "Feature",
  "properties": {
    "gn:admin1_code":"15.0",
    "gn:asciiname":"Ma'anqiao",
    "gn:country_code":"CN",
    "gn:dem":1458,
    "gn:feature_class":"P",
    "gn:feature_code":"PPL",
    "gn:name":"Ma\u2019anqiao",
    "gn:population":0,
    "gn:timezone":"Asia/Shanghai",
    "iso:country":"CN",
    "name:und_x_variant":[
        "Ma\u2019anqiao"
    ],
    "name:zho_x_preferred":[
        "\u9a6c\u978d\u6865"
    ],
    "wof:name":"Ma'anqiao",
    "wof:placetype":"locality"
},
  "geometry": {"coordinates":[108.001,36.0822],"type":"Point"}
}