{
  "type": "Feature",
  "properties": {
    "gn:admin1_code":"25.0",
    "gn:asciiname":"Liangjiaguanzhuangcun",
    "gn:country_code":"CN",
    "gn:dem":70,
    "gn:feature_class":"P",
    "gn:feature_code":"PPL",
    "gn:name":"Liangjiaguanzhuangcun",
    "gn:population":0,
    "gn:timezone":"Asia/Shanghai",
    "iso:country":"CN",
    "name:zho_x_preferred":[
        "\u6881\u5bb6\u5b98\u5e84\u6751"
    ],
    "wof:name":"Liangjiaguanzhuangcun",
    "wof:placetype":"locality"
},
  "geometry": {"coordinates":[119.25825,36.30217],"type":"Point"}
}