{
  "type": "Feature",
  "properties": {
    "gn:admin1_code":"32.0",
    "gn:asciiname":"Shanglaogou",
    "gn:country_code":"CN",
    "gn:dem":612,
    "gn:feature_class":"P",
    "gn:feature_code":"PPL",
    "gn:name":"Shanglaogou",
    "gn:population":0,
    "gn:timezone":"Asia/Shanghai",
    "iso:country":"CN",
    "name:zho_x_preferred":[
        "\u4e0a\u8001\u6c9f"
    ],
    "wof:name":"Shanglaogou",
    "wof:placetype":"locality"
},
  "geometry": {"coordinates":[103.95112,28.82985],"type":"Point"}
}