{
  "type": "Feature",
  "properties": {
    "gn:admin1_code":"32.0",
    "gn:asciiname":"Chenlongping",
    "gn:country_code":"CN",
    "gn:dem":421,
    "gn:feature_class":"P",
    "gn:feature_code":"PPL",
    "gn:name":"Chenlongping",
    "gn:population":0,
    "gn:timezone":"Asia/Shanghai",
    "iso:country":"CN",
    "name:zho_x_preferred":[
        "\u9648\u9f99\u576a"
    ],
    "wof:name":"Chenlongping",
    "wof:placetype":"locality"
},
  "geometry": {"coordinates":[106.753,31.3544],"type":"Point"}
}