{
  "type": "Feature",
  "properties": {
    "gn:admin1_code":"4.0",
    "gn:asciiname":"Tangzhuang",
    "gn:country_code":"CN",
    "gn:dem":30,
    "gn:feature_class":"P",
    "gn:feature_code":"PPL",
    "gn:name":"Tangzhuang",
    "gn:population":0,
    "gn:timezone":"Asia/Shanghai",
    "iso:country":"CN",
    "name:ita_x_preferred":[
        "Tangzhuang"
    ],
    "name:zha_x_preferred":[
        "Buhdangzcangh"
    ],
    "name:zho_x_preferred":[
        "\u6c64\u5e84"
    ],
    "wof:name":"Tangzhuang",
    "wof:placetype":"locality"
},
  "geometry": {"coordinates":[118.26603,34.16342],"type":"Point"}
}