{
  "type": "Feature",
  "properties": {
    "gn:admin1_code":"15.0",
    "gn:asciiname":"Huamawan",
    "gn:country_code":"CN",
    "gn:dem":2319,
    "gn:feature_class":"P",
    "gn:feature_code":"PPL",
    "gn:name":"Huamawan",
    "gn:population":0,
    "gn:timezone":"Asia/Shanghai",
    "iso:country":"CN",
    "name:zho_x_preferred":[
        "\u82b1\u9ebb\u6e7e"
    ],
    "wof:name":"Huamawan",
    "wof:placetype":"locality"
},
  "geometry": {"coordinates":[104.06699999999999,35.3911],"type":"Point"}
}