{
  "type": "Feature",
  "properties": {
    "gn:admin1_code":"08",
    "gn:asciiname":"Mengjiagang",
    "gn:country_code":"CN",
    "gn:dem":186,
    "gn:feature_class":"P",
    "gn:feature_code":"PPLA4",
    "gn:name":"Mengjiagang",
    "gn:population":0,
    "gn:timezone":"Asia/Shanghai",
    "iso:country":"CN",
    "name:und_x_variant":[
        "Meng-chia-kang",
        "Mengjiagang",
        "Mengjiagang Zhen"
    ],
    "name:zho_x_preferred":[
        "\u5b5f\u5bb6\u5c97"
    ],
    "name:zho_x_variant":[
        "\u5b5f\u5bb6\u5c97\u9547"
    ],
    "wof:name":"Mengjiagang",
    "wof:placetype":"locality"
},
  "geometry": {"coordinates":[130.66,46.4224],"type":"Point"}
}