{
  "type": "Feature",
  "properties": {
    "gn:admin1_code":"11.0",
    "gn:asciiname":"Yanjiatang",
    "gn:country_code":"CN",
    "gn:dem":86,
    "gn:feature_class":"P",
    "gn:feature_code":"PPL",
    "gn:name":"Yanjiatang",
    "gn:population":0,
    "gn:timezone":"Asia/Shanghai",
    "iso:country":"CN",
    "name:zho_x_preferred":[
        "\u989c\u5bb6\u5858"
    ],
    "wof:name":"Yanjiatang",
    "wof:placetype":"locality"
},
  "geometry": {"coordinates":[113.08329999999999,27.99607],"type":"Point"}
}