{
  "type": "Feature",
  "properties": {
    "gn:admin1_code":"26.0",
    "gn:asciiname":"Jishancun",
    "gn:country_code":"CN",
    "gn:dem":1322,
    "gn:feature_class":"P",
    "gn:feature_code":"PPL",
    "gn:name":"Jishancun",
    "gn:population":0,
    "gn:timezone":"Asia/Shanghai",
    "iso:country":"CN",
    "name:zho_x_preferred":[
        "\u9e21\u5c71\u6751"
    ],
    "wof:name":"Jishancun",
    "wof:placetype":"locality"
},
  "geometry": {"coordinates":[108.91661000000001,35.1867],"type":"Point"}
}