{
  "type": "Feature",
  "properties": {
    "gn:admin1_code":"12.0",
    "gn:asciiname":"Xifanyuan",
    "gn:country_code":"CN",
    "gn:dem":35,
    "gn:feature_class":"P",
    "gn:feature_code":"PPL",
    "gn:name":"Xifanyuan",
    "gn:population":0,
    "gn:timezone":"Asia/Shanghai",
    "iso:country":"CN",
    "name:zho_x_preferred":[
        "Xifanyuan"
    ],
    "name:zho_x_variant":[
        "\u897f\u7548\u57b8"
    ],
    "wof:name":"Xifanyuan",
    "wof:placetype":"locality"
},
  "geometry": {"coordinates":[115.44575,29.94098],"type":"Point"}
}