{
  "type": "Feature",
  "properties": {
    "gn:admin1_code":"29.0",
    "gn:asciiname":"Yueyadi",
    "gn:country_code":"CN",
    "gn:dem":1075,
    "gn:feature_class":"P",
    "gn:feature_code":"PPL",
    "gn:name":"Yueyadi",
    "gn:population":0,
    "gn:timezone":"Asia/Shanghai",
    "iso:country":"CN",
    "name:zho_x_preferred":[
        "\u6708\u7259\u5730"
    ],
    "wof:name":"Yueyadi",
    "wof:placetype":"locality"
},
  "geometry": {"coordinates":[100.22,24.4763],"type":"Point"}
}