{
  "type": "Feature",
  "properties": {
    "gn:admin1_code":"31",
    "gn:asciiname":"Futian",
    "gn:country_code":"CN",
    "gn:dem":33,
    "gn:feature_class":"P",
    "gn:feature_code":"PPL",
    "gn:name":"Futian",
    "gn:population":0,
    "gn:timezone":"Asia/Shanghai",
    "iso:country":"CN",
    "name:und_x_variant":[
        "\u798f\u7530"
    ],
    "wof:name":"Futian",
    "wof:placetype":"locality"
},
  "geometry": {"coordinates":[110.30800000000001,18.8194],"type":"Point"}
}