{
  "type": "Feature",
  "properties": {
    "gn:admin1_code":"3.0",
    "gn:asciiname":"Shanjiacun",
    "gn:country_code":"CN",
    "gn:dem":172,
    "gn:feature_class":"P",
    "gn:feature_code":"PPL",
    "gn:name":"Shanjiacun",
    "gn:population":0,
    "gn:timezone":"Asia/Shanghai",
    "iso:country":"CN",
    "name:und_x_variant":[
        "\u5c71\u5bb6\u6751"
    ],
    "wof:name":"Shanjiacun",
    "wof:placetype":"locality"
},
  "geometry": {"coordinates":[115.66428999999999,26.22987],"type":"Point"}
}