{
  "type": "Feature",
  "properties": {
    "gn:admin1_code":"19.0",
    "gn:asciiname":"Lishugou",
    "gn:country_code":"CN",
    "gn:dem":320,
    "gn:feature_class":"P",
    "gn:feature_code":"PPL",
    "gn:name":"Lishugou",
    "gn:population":0,
    "gn:timezone":"Asia/Shanghai",
    "iso:country":"CN",
    "name:und_x_variant":[
        "\u68a8\u6811\u6c9f"
    ],
    "wof:name":"Lishugou",
    "wof:placetype":"locality"
},
  "geometry": {"coordinates":[123.11147,40.4695],"type":"Point"}
}