{
  "type": "Feature",
  "properties": {
    "gn:admin1_code":"7.0",
    "gn:asciiname":"Taojinkeng",
    "gn:country_code":"CN",
    "gn:dem":510,
    "gn:feature_class":"P",
    "gn:feature_code":"PPL",
    "gn:name":"Taojinkeng",
    "gn:population":0,
    "gn:timezone":"Asia/Shanghai",
    "iso:country":"CN",
    "name:und_x_variant":[
        "\u6843\u91d1\u5751"
    ],
    "name:zho_x_preferred":[
        "\u6843\u91d1\u5751"
    ],
    "wof:name":"Taojinkeng",
    "wof:placetype":"locality"
},
  "geometry": {"coordinates":[117.22521,26.71667],"type":"Point"}
}