{
  "type": "Feature",
  "properties": {
    "gn:admin1_code":"9",
    "gn:asciiname":"Daqing",
    "gn:country_code":"CN",
    "gn:dem":46,
    "gn:feature_class":"P",
    "gn:feature_code":"PPL",
    "gn:name":"Daqing",
    "gn:population":0,
    "gn:timezone":"Asia/Shanghai",
    "iso:country":"CN",
    "name:und_x_variant":[
        "Daqingji"
    ],
    "name:zho_x_preferred":[
        "\u5927\u6e05"
    ],
    "name:zho_x_variant":[
        "\u5927\u6e05\u96c6"
    ],
    "wof:name":"Daqing",
    "wof:placetype":"locality"
},
  "geometry": {"coordinates":[115.43653999999999,36.06643],"type":"Point"}
}