{
  "type": "Feature",
  "properties": {
    "gn:admin1_code":"8.0",
    "gn:asciiname":"Yonghucun",
    "gn:country_code":"CN",
    "gn:dem":155,
    "gn:feature_class":"P",
    "gn:feature_code":"PPL",
    "gn:name":"Yonghucun",
    "gn:population":0,
    "gn:timezone":"Asia/Shanghai",
    "iso:country":"CN",
    "name:zho_x_preferred":[
        "\u62e5\u62a4\u6751"
    ],
    "wof:name":"Yonghucun",
    "wof:placetype":"locality"
},
  "geometry": {"coordinates":[125.24338,46.21074],"type":"Point"}
}