{
  "type": "Feature",
  "properties": {
    "gn:admin1_code":"07",
    "gn:asciiname":"Dahouxi",
    "gn:country_code":"CN",
    "gn:dem":442,
    "gn:feature_class":"P",
    "gn:feature_code":"PPL",
    "gn:name":"Dahouxi",
    "gn:population":0,
    "gn:timezone":"Asia/Shanghai",
    "iso:country":"CN",
    "name:zho_x_preferred":[
        "\u5927\u540e\u6eaa"
    ],
    "wof:name":"Dahouxi",
    "wof:placetype":"locality"
},
  "geometry": {"coordinates":[117.18427,25.71458],"type":"Point"}
}