{
  "type": "Feature",
  "properties": {
    "gn:admin1_code":"2.0",
    "gn:asciiname":"Huangposhan",
    "gn:country_code":"CN",
    "gn:dem":284,
    "gn:feature_class":"P",
    "gn:feature_code":"PPL",
    "gn:name":"Huangposhan",
    "gn:population":0,
    "gn:timezone":"Asia/Shanghai",
    "iso:country":"CN",
    "name:zho_x_preferred":[
        "\u9ec4\u5a46\u5c71"
    ],
    "wof:name":"Huangposhan",
    "wof:placetype":"locality"
},
  "geometry": {"coordinates":[121.12512,29.41409],"type":"Point"}
}