{
  "type": "Feature",
  "properties": {
    "gn:admin1_code":"32.0",
    "gn:asciiname":"Daojiaotou",
    "gn:country_code":"CN",
    "gn:dem":585,
    "gn:feature_class":"P",
    "gn:feature_code":"PPL",
    "gn:name":"Daojiaotou",
    "gn:population":0,
    "gn:timezone":"Asia/Shanghai",
    "iso:country":"CN",
    "name:zho_x_preferred":[
        "\u5012\u89d2\u5934"
    ],
    "wof:name":"Daojiaotou",
    "wof:placetype":"locality"
},
  "geometry": {"coordinates":[105.16844,31.84399],"type":"Point"}
}