{
  "type": "Feature",
  "properties": {
    "gn:admin1_code":"4.0",
    "gn:asciiname":"Sujiajian",
    "gn:country_code":"CN",
    "gn:dem":2,
    "gn:feature_class":"P",
    "gn:feature_code":"PPL",
    "gn:name":"Sujiajian",
    "gn:population":0,
    "gn:timezone":"Asia/Shanghai",
    "iso:country":"CN",
    "name:zho_x_preferred":[
        "Sujiajian"
    ],
    "name:zho_x_variant":[
        "\u82cf\u5bb6\u5c16"
    ],
    "wof:name":"Sujiajian",
    "wof:placetype":"locality"
},
  "geometry": {"coordinates":[121.71144,31.90627000000001],"type":"Point"}
}