{
  "type": "Feature",
  "properties": {
    "gn:admin1_code":"26.0",
    "gn:asciiname":"Yue'er",
    "gn:country_code":"CN",
    "gn:dem":410,
    "gn:feature_class":"P",
    "gn:feature_code":"PPL",
    "gn:name":"Yue\u2019er",
    "gn:population":0,
    "gn:timezone":"Asia/Shanghai",
    "iso:country":"CN",
    "name:und_x_variant":[
        "Y\u00fceh-erh-t\u2019an",
        "Yue\u2019ertan",
        "Yue\u2019er"
    ],
    "wof:name":"Yue'er",
    "wof:placetype":"locality"
},
  "geometry": {"coordinates":[109.93832999999999,32.87611],"type":"Point"}
}