{
  "type": "Feature",
  "properties": {
    "gn:admin1_code":"32.0",
    "gn:asciiname":"Shaohuaping",
    "gn:country_code":"CN",
    "gn:dem":2133,
    "gn:feature_class":"P",
    "gn:feature_code":"PPL",
    "gn:name":"Shaohuaping",
    "gn:population":0,
    "gn:timezone":"Asia/Shanghai",
    "iso:country":"CN",
    "name:zho_x_preferred":[
        "\u7ecd\u82b1\u576a"
    ],
    "wof:name":"Shaohuaping",
    "wof:placetype":"locality"
},
  "geometry": {"coordinates":[102.024,27.0354],"type":"Point"}
}