{
  "type": "Feature",
  "properties": {
    "gn:admin1_code":"24.0",
    "gn:asciiname":"Zhangliuzhuangcun",
    "gn:country_code":"CN",
    "gn:dem":359,
    "gn:feature_class":"P",
    "gn:feature_code":"PPL",
    "gn:name":"Zhangliuzhuangcun",
    "gn:population":0,
    "gn:timezone":"Asia/Shanghai",
    "iso:country":"CN",
    "name:zho_x_preferred":[
        "\u5f20\u7559\u5e84\u6751"
    ],
    "wof:name":"Zhangliuzhuangcun",
    "wof:placetype":"locality"
},
  "geometry": {"coordinates":[110.34413000000001,34.8323],"type":"Point"}
}