{
  "type": "Feature",
  "properties": {
    "gn:admin1_code":"18",
    "gn:asciiname":"Bashan",
    "gn:country_code":"CN",
    "gn:dem":685,
    "gn:feature_class":"P",
    "gn:feature_code":"PPL",
    "gn:name":"Bashan",
    "gn:population":0,
    "gn:timezone":"Asia/Shanghai",
    "iso:country":"CN",
    "name:ara_x_preferred":[
        "\u0628\u0627\u0634\u0627\u0646"
    ],
    "name:cat_x_preferred":[
        "Basan"
    ],
    "name:deu_x_preferred":[
        "Baschan"
    ],
    "name:ell_x_preferred":[
        "\u0392\u03b1\u03c3\u03ac\u03bd"
    ],
    "name:fra_x_preferred":[
        "Bach\u00e2n"
    ],
    "name:heb_x_preferred":[
        "\u05d4\u05d1\u05e9\u05df"
    ],
    "name:ind_x_preferred":[
        "Basan"
    ],
    "name:ita_x_preferred":[
        "Ba\u0161an"
    ],
    "name:jpn_x_preferred":[
        "\u30d0\u30b7\u30e3\u30f3"
    ],
    "name:lit_x_preferred":[
        "Ba\u0161anas"
    ],
    "name:nld_x_preferred":[
        "Basan"
    ],
    "name:nor_x_preferred":[
        "Basan"
    ],
    "name:pol_x_preferred":[
        "Baszan"
    ],
    "name:por_x_preferred":[
        "Bas\u00e3"
    ],
    "name:rus_x_preferred":[
        "\u0412\u0430\u0441\u0430\u043d"
    ],
    "name:yid_x_preferred":[
        "\u05d1\u05e9\u05df"
    ],
    "name:zho_x_preferred":[
        "\u575d\u5c71"
    ],
    "wof:name":"Bashan",
    "wof:placetype":"locality"
},
  "geometry": {"coordinates":[105.67100000000001,25.6763],"type":"Point"}
}