{
  "type": "Feature",
  "properties": {
    "gn:admin1_code":"12.0",
    "gn:asciiname":"Qingshanyuan",
    "gn:country_code":"CN",
    "gn:dem":28,
    "gn:feature_class":"P",
    "gn:feature_code":"PPL",
    "gn:name":"Qingshanyuan",
    "gn:population":0,
    "gn:timezone":"Asia/Shanghai",
    "iso:country":"CN",
    "name:zho_x_preferred":[
        "\u9752\u5c71\u57b8"
    ],
    "wof:name":"Qingshanyuan",
    "wof:placetype":"locality"
},
  "geometry": {"coordinates":[113.60975999999999,29.91951],"type":"Point"}
}