{
  "type": "Feature",
  "properties": {
    "gn:admin1_code":"3.0",
    "gn:asciiname":"Huangtuping Linchang",
    "gn:country_code":"CN",
    "gn:dem":311,
    "gn:feature_class":"P",
    "gn:feature_code":"PPLF",
    "gn:name":"Huangtuping Linchang",
    "gn:population":0,
    "gn:timezone":"Asia/Shanghai",
    "iso:country":"CN",
    "name:und_x_variant":[
        "\u9ec4\u571f\u576a\u6797\u573a"
    ],
    "wof:name":"Huangtuping Linchang",
    "wof:placetype":"locality"
},
  "geometry": {"coordinates":[114.80158,27.99187],"type":"Point"}
}