{
  "type": "Feature",
  "properties": {
    "gn:admin1_code":"20.0",
    "gn:asciiname":"Xuejiawan",
    "gn:country_code":"CN",
    "gn:dem":1138,
    "gn:feature_class":"P",
    "gn:feature_code":"PPLA3",
    "gn:name":"Xuejiawan",
    "gn:population":0,
    "gn:timezone":"Asia/Shanghai",
    "iso:country":"CN",
    "name:deu_x_preferred":[
        "Jung-Gar-Banner"
    ],
    "name:jpn_x_preferred":[
        "\u30b8\u30e5\u30f3\u30ac\u30eb\u65d7"
    ],
    "name:kor_x_preferred":[
        "\uc900\uac70\uc5bc \uae30"
    ],
    "name:mon_x_preferred":[
        "\u0417\u04af\u04af\u043d\u0433\u0430\u0440 \u0445\u043e\u0448\u0443\u0443"
    ],
    "name:nor_x_preferred":[
        "Jungar"
    ],
    "name:pol_x_preferred":[
        "Jungar Qi"
    ],
    "name:rus_x_preferred":[
        "\u0414\u0436\u0443\u043d\u0433\u0430\u0440-\u0426\u0438"
    ],
    "name:swe_x_preferred":[
        "Jungar"
    ],
    "name:und_x_variant":[
        "\u859b\u5bb6\u6e7e",
        "Xuejiawan Zhen",
        "Zhunge\u2019er Qi",
        "\u859b\u5bb6\u6e7e\u9547"
    ],
    "name:urd_x_preferred":[
        "\u062c\u0646\u06af\u0627\u0631 \u067e\u0631\u0686\u0645"
    ],
    "name:vie_x_preferred":[
        "Jung Gar"
    ],
    "name:zho_x_preferred":[
        "Xuejiawan"
    ],
    "name:zho_x_variant":[
        "\u51c6\u683c\u5c14\u65d7"
    ],
    "wof:name":"Xuejiawan",
    "wof:placetype":"locality"
},
  "geometry": {"coordinates":[111.2208,39.86678],"type":"Point"}
}