{
  "type": "Feature",
  "properties": {
    "gn:admin1_code":"20.0",
    "gn:asciiname":"Xuejiawan",
    "gn:country_code":"CN",
    "gn:dem":1138,
    "gn:feature_class":"P",
    "gn:feature_code":"PPLA3",
    "gn:name":"Xuejiawan",
    "gn:population":0,
    "gn:timezone":"Asia/Shanghai",
    "iso:country":"CN",
    "name:und_x_variant":[
        "\u859b\u5bb6\u6e7e",
        "Xuejiawan Zhen",
        "Jungar Qi",
        "Zhunge\u2019er Qi",
        "\u859b\u5bb6\u6e7e\u9547",
        "\u51c6\u683c\u5c14\u65d7"
    ],
    "name:zho_x_preferred":[
        "Xuejiawan"
    ],
    "wof:name":"Xuejiawan",
    "wof:placetype":"locality"
},
  "geometry": {"coordinates":[111.2208,39.86678],"type":"Point"}
}