{
  "type": "Feature",
  "properties": {
    "gn:admin1_code":"19",
    "gn:asciiname":"Huanrenxian Balidianzi Guoyou Linchang",
    "gn:country_code":"CN",
    "gn:dem":741,
    "gn:feature_class":"P",
    "gn:feature_code":"PPLF",
    "gn:name":"Huanrenxian Balidianzi Guoyou Linchang",
    "gn:population":0,
    "gn:timezone":"Asia/Shanghai",
    "iso:country":"CN",
    "name:und_x_variant":[
        "Guoying Linchang",
        "Huanrenxian Balidianzi Guoyou Linchang",
        "\u6853\u4ec1\u53bf\u516b\u91cc\u7538\u5b50\u56fd\u6709\u6797\u573a",
        "Huanren Manzu Zhizixian Balidianzi Guoyou Linchang",
        "\u56fd\u8425\u6797\u573a",
        "\u6853\u4ec1\u6ee1\u65cf\u81ea\u6cbb\u53bf\u516b\u91cc\u7538\u5b50\u56fd\u6709\u6797\u573a"
    ],
    "wof:name":"Huanrenxian Balidianzi Guoyou Linchang",
    "wof:placetype":"locality"
},
  "geometry": {"coordinates":[124.78255,41.24033],"type":"Point"}
}