{
  "type": "Feature",
  "properties": {
    "gn:admin1_code":"26.0",
    "gn:asciiname":"Zhuyu",
    "gn:country_code":"CN",
    "gn:dem":767,
    "gn:feature_class":"P",
    "gn:feature_code":"PPL",
    "gn:name":"Zhuyu",
    "gn:population":0,
    "gn:timezone":"Asia/Shanghai",
    "iso:country":"CN",
    "name:und_x_variant":[
        "\u73e0\u5cea"
    ],
    "wof:name":"Zhuyu",
    "wof:placetype":"locality"
},
  "geometry": {"coordinates":[107.20677999999999,34.3121],"type":"Point"}
}