{
  "type": "Feature",
  "properties": {
    "gn:admin1_code":"19.0",
    "gn:asciiname":"Wuchengdian",
    "gn:country_code":"CN",
    "gn:dem":241,
    "gn:feature_class":"P",
    "gn:feature_code":"PPL",
    "gn:name":"Wuchengdian",
    "gn:population":0,
    "gn:timezone":"Asia/Shanghai",
    "iso:country":"CN",
    "name:zho_x_preferred":[
        "\u5434\u6210\u5e97"
    ],
    "wof:name":"Wuchengdian",
    "wof:placetype":"locality"
},
  "geometry": {"coordinates":[122.54900000000001,42.7594],"type":"Point"}
}