{
  "type": "Feature",
  "properties": {
    "gn:admin1_code":"16.0",
    "gn:asciiname":"Kongchongwei",
    "gn:country_code":"CN",
    "gn:dem":99,
    "gn:feature_class":"P",
    "gn:feature_code":"PPL",
    "gn:name":"Kongchongwei",
    "gn:population":0,
    "gn:timezone":"Asia/Shanghai",
    "iso:country":"CN",
    "name:zho_x_preferred":[
        "\u5b54\u51b2\u5c3e"
    ],
    "wof:name":"Kongchongwei",
    "wof:placetype":"locality"
},
  "geometry": {"coordinates":[110.95,23.026],"type":"Point"}
}