{
  "type": "Feature",
  "properties": {
    "gn:admin1_code":"4.0",
    "gn:asciiname":"Tangqiao",
    "gn:country_code":"CN",
    "gn:dem":6,
    "gn:feature_class":"P",
    "gn:feature_code":"PPL",
    "gn:name":"Tangqiao",
    "gn:population":0,
    "gn:timezone":"Asia/Shanghai",
    "iso:country":"CN",
    "name:und_x_variant":[
        "\u5510\u6865"
    ],
    "name:zho_x_preferred":[
        "\u5510\u6865"
    ],
    "wof:name":"Tangqiao",
    "wof:placetype":"locality"
},
  "geometry": {"coordinates":[120.40627000000001,32.47965],"type":"Point"}
}