{
  "type": "Feature",
  "properties": {
    "gn:admin1_code":"25.0",
    "gn:asciiname":"Dashangzhuang",
    "gn:cc2":"CN",
    "gn:country_code":"CN",
    "gn:dem":183,
    "gn:feature_class":"P",
    "gn:feature_code":"PPL",
    "gn:name":"Dashangzhuang",
    "gn:population":0,
    "gn:timezone":"Asia/Shanghai",
    "iso:country":"CN",
    "name:zho_x_preferred":[
        "\u5927\u5c1a\u5e84"
    ],
    "wof:name":"Dashangzhuang",
    "wof:placetype":"locality"
},
  "geometry": {"coordinates":[119.27918,35.74903],"type":"Point"}
}