{
  "type": "Feature",
  "properties": {
    "gn:admin1_code":"15.0",
    "gn:asciiname":"Caosheping",
    "gn:country_code":"CN",
    "gn:dem":1604,
    "gn:feature_class":"P",
    "gn:feature_code":"PPL",
    "gn:name":"Caosheping",
    "gn:population":0,
    "gn:timezone":"Asia/Shanghai",
    "iso:country":"CN",
    "name:zho_x_preferred":[
        "\u8349\u820c\u576a"
    ],
    "wof:name":"Caosheping",
    "wof:placetype":"locality"
},
  "geometry": {"coordinates":[105.0318,33.39765],"type":"Point"}
}