{
  "type": "Feature",
  "properties": {
    "gn:admin1_code":"31.0",
    "gn:asciiname":"Sandukou",
    "gn:country_code":"CN",
    "gn:dem":82,
    "gn:feature_class":"P",
    "gn:feature_code":"PPL",
    "gn:name":"Sandukou",
    "gn:population":0,
    "gn:timezone":"Asia/Shanghai",
    "iso:country":"CN",
    "name:zho_x_preferred":[
        "\u4e09\u6e21\u53e3"
    ],
    "wof:name":"Sandukou",
    "wof:placetype":"locality"
},
  "geometry": {"coordinates":[109.94422,19.58358],"type":"Point"}
}