{
  "type": "Feature",
  "properties": {
    "gn:admin1_code":"26.0",
    "gn:asciiname":"Hua'erqu",
    "gn:country_code":"CN",
    "gn:dem":1417,
    "gn:feature_class":"P",
    "gn:feature_code":"PPL",
    "gn:name":"Hua\u2019erqu",
    "gn:population":0,
    "gn:timezone":"Asia/Shanghai",
    "iso:country":"CN",
    "name:und_x_variant":[
        "Hua\u2019erqu",
        "\u82b1\u513f\u6e20"
    ],
    "wof:name":"Hua'erqu",
    "wof:placetype":"locality"
},
  "geometry": {"coordinates":[107.90183,36.87825],"type":"Point"}
}