{
  "type": "Feature",
  "properties": {
    "gn:admin1_code":"10",
    "gn:asciiname":"Fentuo",
    "gn:country_code":"CN",
    "gn:dem":31,
    "gn:feature_class":"P",
    "gn:feature_code":"PPL",
    "gn:name":"Fentuo",
    "gn:population":0,
    "gn:timezone":"Asia/Shanghai",
    "iso:country":"CN",
    "name:und_x_variant":[
        "Fentou",
        "Fen-t\u2019o",
        "Fen-t\u2019ou-chuang",
        "Fentuo"
    ],
    "name:zho_x_preferred":[
        "\u575f\u5768"
    ],
    "wof:name":"Fentuo",
    "wof:placetype":"locality"
},
  "geometry": {"coordinates":[119.19958,39.84361],"type":"Point"}
}