{
  "type": "Feature",
  "properties": {
    "gn:admin1_code":"5.0",
    "gn:asciiname":"Minfengcun",
    "gn:country_code":"CN",
    "gn:dem":216,
    "gn:feature_class":"P",
    "gn:feature_code":"PPL",
    "gn:name":"Minfengcun",
    "gn:population":0,
    "gn:timezone":"Asia/Shanghai",
    "iso:country":"CN",
    "name:zho_x_preferred":[
        "\u6c11\u4e30\u6751"
    ],
    "wof:name":"Minfengcun",
    "wof:placetype":"locality"
},
  "geometry": {"coordinates":[125.17773,43.8905],"type":"Point"}
}