{
  "type": "Feature",
  "properties": {
    "gn:admin1_code":"32.0",
    "gn:asciiname":"Jueta",
    "gn:country_code":"CN",
    "gn:dem":4378,
    "gn:feature_class":"P",
    "gn:feature_code":"PPL",
    "gn:name":"Jueta",
    "gn:population":0,
    "gn:timezone":"Asia/Shanghai",
    "iso:country":"CN",
    "name:zho_x_preferred":[
        "\u89c9\u5854"
    ],
    "wof:name":"Jueta",
    "wof:placetype":"locality"
},
  "geometry": {"coordinates":[100.22499999999999,30.1794],"type":"Point"}
}