{
  "type": "Feature",
  "properties": {
    "gn:admin1_code":"33.0",
    "gn:asciiname":"Longfeng",
    "gn:country_code":"CN",
    "gn:dem":212,
    "gn:feature_class":"P",
    "gn:feature_code":"PPLA4",
    "gn:name":"Longfeng",
    "gn:population":0,
    "gn:timezone":"Asia/Shanghai",
    "iso:country":"CN",
    "name:und_x_variant":[
        "Longfeng Jiedao"
    ],
    "name:zho_x_preferred":[
        "\u9f99\u51e4"
    ],
    "name:zho_x_variant":[
        "\u9f99\u51e4\u8857\u9053"
    ],
    "wof:name":"Longfeng",
    "wof:placetype":"locality"
},
  "geometry": {"coordinates":[106.42906000000001,29.81527],"type":"Point"}
}