{
  "type": "Feature",
  "properties": {
    "gn:admin1_code":"02",
    "gn:asciiname":"Chishi",
    "gn:country_code":"CN",
    "gn:dem":245,
    "gn:feature_class":"P",
    "gn:feature_code":"PPL",
    "gn:name":"Chishi",
    "gn:population":0,
    "gn:timezone":"Asia/Shanghai",
    "iso:country":"CN",
    "name:und_x_variant":[
        "Ch\u2019ih-shih",
        "Chishi"
    ],
    "name:zho_x_preferred":[
        "\u8d64\u77f3"
    ],
    "wof:name":"Chishi",
    "wof:placetype":"locality"
},
  "geometry": {"coordinates":[119.44302,28.1333],"type":"Point"}
}