{
  "type": "Feature",
  "properties": {
    "gn:admin1_code":"26",
    "gn:asciiname":"Zhangbagou",
    "gn:country_code":"CN",
    "gn:dem":410,
    "gn:feature_class":"P",
    "gn:feature_code":"PPLA4",
    "gn:name":"Zhangbagou",
    "gn:population":0,
    "gn:timezone":"Asia/Shanghai",
    "iso:country":"CN",
    "name:und_x_variant":[
        "Zhangbagou Jieban",
        "Zhangbagou"
    ],
    "name:zho_x_preferred":[
        "\u4e08\u516b\u6c9f"
    ],
    "name:zho_x_variant":[
        "\u4e08\u516b\u6c9f\u8857\u529e"
    ],
    "wof:name":"Zhangbagou",
    "wof:placetype":"locality"
},
  "geometry": {"coordinates":[108.88028,34.21291],"type":"Point"}
}