{
  "type": "Feature",
  "properties": {
    "gn:admin1_code":"14.0",
    "gn:asciiname":"Yachongcun",
    "gn:country_code":"CN",
    "gn:dem":4065,
    "gn:feature_class":"P",
    "gn:feature_code":"PPL",
    "gn:name":"Yachongcun",
    "gn:population":0,
    "gn:timezone":"Asia/Urumqi",
    "iso:country":"CN",
    "name:zho_x_preferred":[
        "\u4e9a\u51b2\u6751"
    ],
    "wof:name":"Yachongcun",
    "wof:placetype":"locality"
},
  "geometry": {"coordinates":[94.58831000000001,31.44507],"type":"Point"}
}