{
  "type": "Feature",
  "properties": {
    "gn:admin1_code":"30",
    "gn:asciiname":"Shiwan",
    "gn:country_code":"CN",
    "gn:dem":0,
    "gn:feature_class":"P",
    "gn:feature_code":"PPLA4",
    "gn:name":"Shiwan",
    "gn:population":0,
    "gn:timezone":"Asia/Shanghai",
    "iso:country":"CN",
    "name:deu_x_preferred":[
        "Shiwan"
    ],
    "name:und_x_variant":[
        "Shiwan Zhen",
        "\u77f3\u6e7e\u9547"
    ],
    "name:zho_x_preferred":[
        "\u77f3\u6e7e"
    ],
    "wof:name":"Shiwan",
    "wof:placetype":"locality"
},
  "geometry": {"coordinates":[113.85303,23.13987],"type":"Point"}
}