{
  "type": "Feature",
  "properties": {
    "gn:admin1_code":"4.0",
    "gn:asciiname":"Huaiyuancun",
    "gn:country_code":"CN",
    "gn:dem":12,
    "gn:feature_class":"P",
    "gn:feature_code":"PPL",
    "gn:name":"Huaiyuancun",
    "gn:population":0,
    "gn:timezone":"Asia/Shanghai",
    "iso:country":"CN",
    "name:zho_x_preferred":[
        "\u6dee\u6e90\u6751"
    ],
    "wof:name":"Huaiyuancun",
    "wof:placetype":"locality"
},
  "geometry": {"coordinates":[119.19391,31.81189],"type":"Point"}
}