{
  "type": "Feature",
  "properties": {
    "gn:admin1_code":"7.0",
    "gn:asciiname":"Dingqi",
    "gn:country_code":"CN",
    "gn:dem":11,
    "gn:feature_class":"P",
    "gn:feature_code":"PPL",
    "gn:name":"Dingqi",
    "gn:population":0,
    "gn:timezone":"Asia/Shanghai",
    "iso:country":"CN",
    "name:zho_x_preferred":[
        "\u5b9a\u5c90"
    ],
    "wof:name":"Dingqi",
    "wof:placetype":"locality"
},
  "geometry": {"coordinates":[119.62081000000001,26.15225],"type":"Point"}
}