{
  "type": "Feature",
  "properties": {
    "gn:admin1_code":"11.0",
    "gn:asciiname":"Shedong",
    "gn:country_code":"CN",
    "gn:dem":323,
    "gn:feature_class":"P",
    "gn:feature_code":"PPL",
    "gn:name":"Shedong",
    "gn:population":0,
    "gn:timezone":"Asia/Shanghai",
    "iso:country":"CN",
    "name:zho_x_preferred":[
        "\u86c7\u6d1e"
    ],
    "wof:name":"Shedong",
    "wof:placetype":"locality"
},
  "geometry": {"coordinates":[109.87936999999999,27.04402],"type":"Point"}
}