{
  "type": "Feature",
  "properties": {
    "gn:admin1_code":"16.0",
    "gn:asciiname":"Dashui",
    "gn:country_code":"CN",
    "gn:dem":87,
    "gn:feature_class":"P",
    "gn:feature_code":"PPL",
    "gn:name":"Dashui",
    "gn:population":0,
    "gn:timezone":"Asia/Shanghai",
    "iso:country":"CN",
    "name:zho_x_preferred":[
        "\u5927\u8c01"
    ],
    "wof:name":"Dashui",
    "wof:placetype":"locality"
},
  "geometry": {"coordinates":[111.066,23.6841],"type":"Point"}
}