{
  "type": "Feature",
  "properties": {
    "gn:admin1_code":"29.0",
    "gn:asciiname":"Sailin",
    "gn:country_code":"CN",
    "gn:dem":1692,
    "gn:feature_class":"P",
    "gn:feature_code":"PPL",
    "gn:name":"Sailin",
    "gn:population":0,
    "gn:timezone":"Asia/Shanghai",
    "iso:country":"CN",
    "name:zho_x_preferred":[
        "\u8d5b\u6797"
    ],
    "wof:name":"Sailin",
    "wof:placetype":"locality"
},
  "geometry": {"coordinates":[98.79859999999999,25.1699],"type":"Point"}
}