{
  "type": "Feature",
  "properties": {
    "gn:admin1_code":"29.0",
    "gn:asciiname":"Zhuanyunzhan",
    "gn:country_code":"CN",
    "gn:dem":2035,
    "gn:feature_class":"P",
    "gn:feature_code":"PPL",
    "gn:name":"Zhuanyunzhan",
    "gn:population":0,
    "gn:timezone":"Asia/Shanghai",
    "iso:country":"CN",
    "name:zho_x_preferred":[
        "\u8f6c\u8fd0\u7ad9"
    ],
    "wof:name":"Zhuanyunzhan",
    "wof:placetype":"locality"
},
  "geometry": {"coordinates":[102.875,25.0928],"type":"Point"}
}