{
  "type": "Feature",
  "properties": {
    "gn:admin1_code":"26.0",
    "gn:asciiname":"Weiganping",
    "gn:country_code":"CN",
    "gn:dem":1256,
    "gn:feature_class":"P",
    "gn:feature_code":"PPL",
    "gn:name":"Weiganping",
    "gn:population":0,
    "gn:timezone":"Asia/Shanghai",
    "iso:country":"CN",
    "name:und_x_variant":[
        "\u6845\u6746\u576a"
    ],
    "wof:name":"Weiganping",
    "wof:placetype":"locality"
},
  "geometry": {"coordinates":[106.57804,32.79662],"type":"Point"}
}