{
  "type": "Feature",
  "properties": {
    "gn:admin1_code":"24.0",
    "gn:asciiname":"Shipoyu",
    "gn:country_code":"CN",
    "gn:dem":1119,
    "gn:feature_class":"P",
    "gn:feature_code":"PPL",
    "gn:name":"Shipoyu",
    "gn:population":0,
    "gn:timezone":"Asia/Shanghai",
    "iso:country":"CN",
    "name:zho_x_preferred":[
        "\u77f3\u5761\u5cea"
    ],
    "wof:name":"Shipoyu",
    "wof:placetype":"locality"
},
  "geometry": {"coordinates":[113.39928999999999,38.00752],"type":"Point"}
}