{
  "type": "Feature",
  "properties": {
    "gn:admin1_code":"18",
    "gn:asciiname":"Tuole",
    "gn:country_code":"CN",
    "gn:dem":1681,
    "gn:feature_class":"P",
    "gn:feature_code":"PPL",
    "gn:name":"Tuole",
    "gn:population":0,
    "gn:timezone":"Asia/Shanghai",
    "iso:country":"CN",
    "name:zho_x_preferred":[
        "\u59a5\u4e50"
    ],
    "wof:name":"Tuole",
    "wof:placetype":"locality"
},
  "geometry": {"coordinates":[104.547,25.6144],"type":"Point"}
}