{
  "type": "Feature",
  "properties": {
    "gn:admin1_code":"18.0",
    "gn:asciiname":"Huaxiangchong",
    "gn:country_code":"CN",
    "gn:dem":676,
    "gn:feature_class":"P",
    "gn:feature_code":"PPL",
    "gn:name":"Huaxiangchong",
    "gn:population":0,
    "gn:timezone":"Asia/Shanghai",
    "iso:country":"CN",
    "name:zho_x_preferred":[
        "\u5316\u9999\u51b2"
    ],
    "wof:name":"Huaxiangchong",
    "wof:placetype":"locality"
},
  "geometry": {"coordinates":[107.79000000000001,26.9941],"type":"Point"}
}