{
  "type": "Feature",
  "properties": {
    "gn:admin1_code":"10",
    "gn:asciiname":"Shaojialiang",
    "gn:country_code":"CN",
    "gn:dem":814,
    "gn:feature_class":"P",
    "gn:feature_code":"PPL",
    "gn:name":"Shaojialiang",
    "gn:population":0,
    "gn:timezone":"Asia/Shanghai",
    "iso:country":"CN",
    "name:zho_x_preferred":[
        "\u90b5\u5bb6\u6881"
    ],
    "wof:name":"Shaojialiang",
    "wof:placetype":"locality"
},
  "geometry": {"coordinates":[118.84244,40.82194000000001],"type":"Point"}
}