{
  "type": "Feature",
  "properties": {
    "gn:admin1_code":"12.0",
    "gn:asciiname":"Liangzhou",
    "gn:country_code":"CN",
    "gn:dem":26,
    "gn:feature_class":"P",
    "gn:feature_code":"PPL",
    "gn:name":"Liangzhou",
    "gn:population":0,
    "gn:timezone":"Asia/Shanghai",
    "iso:country":"CN",
    "name:zho_x_preferred":[
        "\u7cae\u6d32"
    ],
    "wof:name":"Liangzhou",
    "wof:placetype":"locality"
},
  "geometry": {"coordinates":[113.71847,29.96992],"type":"Point"}
}