{
  "type": "Feature",
  "properties": {
    "gn:admin1_code":"29.0",
    "gn:asciiname":"Luzhimi",
    "gn:country_code":"CN",
    "gn:dem":2333,
    "gn:feature_class":"P",
    "gn:feature_code":"PPL",
    "gn:name":"Luzhimi",
    "gn:population":0,
    "gn:timezone":"Asia/Shanghai",
    "iso:country":"CN",
    "name:zho_x_preferred":[
        "\u9e7f\u652f\u5bc6"
    ],
    "wof:name":"Luzhimi",
    "wof:placetype":"locality"
},
  "geometry": {"coordinates":[99.5955,25.6736],"type":"Point"}
}