{
  "type": "Feature",
  "properties": {
    "gn:admin1_code":"2.0",
    "gn:asciiname":"Huangjia'ao",
    "gn:country_code":"CN",
    "gn:dem":35,
    "gn:feature_class":"P",
    "gn:feature_code":"PPL",
    "gn:name":"Huangjia\u2019ao",
    "gn:population":0,
    "gn:timezone":"Asia/Shanghai",
    "iso:country":"CN",
    "name:und_x_variant":[
        "Huangjia\u2019ao"
    ],
    "name:zho_x_preferred":[
        "\u9ec4\u5bb6\u5c99"
    ],
    "wof:name":"Huangjia'ao",
    "wof:placetype":"locality"
},
  "geometry": {"coordinates":[122.26385999999999,30.24769],"type":"Point"}
}