{
  "type": "Feature",
  "properties": {
    "gn:admin1_code":"25",
    "gn:asciiname":"Beisancun",
    "gn:country_code":"CN",
    "gn:dem":47,
    "gn:feature_class":"P",
    "gn:feature_code":"PPL",
    "gn:name":"Beisancun",
    "gn:population":0,
    "gn:timezone":"Asia/Shanghai",
    "iso:country":"CN",
    "name:zho_x_preferred":[
        "\u5317\u4e09\u6751"
    ],
    "wof:name":"Beisancun",
    "wof:placetype":"locality"
},
  "geometry": {"coordinates":[115.83199999999999,34.8386],"type":"Point"}
}