{
  "type": "Feature",
  "properties": {
    "gn:admin1_code":"7.0",
    "gn:asciiname":"Kanlongping",
    "gn:country_code":"CN",
    "gn:dem":357,
    "gn:feature_class":"P",
    "gn:feature_code":"PPL",
    "gn:name":"Kanlongping",
    "gn:population":0,
    "gn:timezone":"Asia/Shanghai",
    "iso:country":"CN",
    "name:zho_x_preferred":[
        "\u770b\u9f99\u576a"
    ],
    "wof:name":"Kanlongping",
    "wof:placetype":"locality"
},
  "geometry": {"coordinates":[116.5813,24.93374],"type":"Point"}
}