{
  "type": "Feature",
  "properties": {
    "gn:admin1_code":"29.0",
    "gn:asciiname":"Songshuhe",
    "gn:country_code":"CN",
    "gn:dem":2588,
    "gn:feature_class":"P",
    "gn:feature_code":"PPL",
    "gn:name":"Songshuhe",
    "gn:population":0,
    "gn:timezone":"Asia/Shanghai",
    "iso:country":"CN",
    "name:zho_x_preferred":[
        "\u677e\u6811\u6cb3"
    ],
    "wof:name":"Songshuhe",
    "wof:placetype":"locality"
},
  "geometry": {"coordinates":[100.876,26.8835],"type":"Point"}
}