{
  "type": "Feature",
  "properties": {
    "gn:admin1_code":"4.0",
    "gn:asciiname":"Shanhecun",
    "gn:country_code":"CN",
    "gn:dem":20,
    "gn:feature_class":"P",
    "gn:feature_code":"PPL",
    "gn:name":"Shanhecun",
    "gn:population":0,
    "gn:timezone":"Asia/Shanghai",
    "iso:country":"CN",
    "name:zho_x_preferred":[
        "\u5c71\u6cb3\u6751"
    ],
    "wof:name":"Shanhecun",
    "wof:placetype":"locality"
},
  "geometry": {"coordinates":[118.17712,33.71527],"type":"Point"}
}