{
  "type": "Feature",
  "properties": {
    "gn:admin1_code":"22",
    "gn:asciiname":"Pigezhuang",
    "gn:country_code":"CN",
    "gn:dem":40,
    "gn:feature_class":"P",
    "gn:feature_code":"PPL",
    "gn:name":"Pigezhuang",
    "gn:population":0,
    "gn:timezone":"Asia/Shanghai",
    "iso:country":"CN",
    "name:und_x_variant":[
        "P\u2019i-ko-chuang",
        "Pigezhuang"
    ],
    "name:zho_x_preferred":[
        "\u76ae\u5404\u5e84"
    ],
    "wof:name":"Pigezhuang",
    "wof:placetype":"locality"
},
  "geometry": {"coordinates":[116.27109,39.65204],"type":"Point"}
}