{
  "type": "Feature",
  "properties": {
    "gn:admin1_code":"3.0",
    "gn:asciiname":"Niu'elong",
    "gn:country_code":"CN",
    "gn:dem":144,
    "gn:feature_class":"P",
    "gn:feature_code":"PPL",
    "gn:name":"Niu\u2019elong",
    "gn:population":0,
    "gn:timezone":"Asia/Shanghai",
    "iso:country":"CN",
    "name:und_x_variant":[
        "Niu\u2019elong",
        "\u725b\u8f6d\u5784"
    ],
    "wof:name":"Niu'elong",
    "wof:placetype":"locality"
},
  "geometry": {"coordinates":[114.08992000000001,27.80043],"type":"Point"}
}