{
  "type": "Feature",
  "properties": {
    "gn:admin1_code":"1.0",
    "gn:asciiname":"Houzouzhuangcun",
    "gn:country_code":"CN",
    "gn:dem":37,
    "gn:feature_class":"P",
    "gn:feature_code":"PPL",
    "gn:name":"Houzouzhuangcun",
    "gn:population":0,
    "gn:timezone":"Asia/Shanghai",
    "iso:country":"CN",
    "name:zho_x_preferred":[
        "\u540e\u90b9\u5e84\u6751"
    ],
    "wof:name":"Houzouzhuangcun",
    "wof:placetype":"locality"
},
  "geometry": {"coordinates":[115.82747000000001,33.63568],"type":"Point"}
}