{
  "type": "Feature",
  "properties": {
    "gn:admin1_code":"3.0",
    "gn:asciiname":"Dongkou",
    "gn:country_code":"CN",
    "gn:dem":100,
    "gn:feature_class":"P",
    "gn:feature_code":"PPL",
    "gn:name":"Dongkou",
    "gn:population":0,
    "gn:timezone":"Asia/Shanghai",
    "iso:country":"CN",
    "name:und_x_variant":[
        "\u6d1e\u53e3"
    ],
    "wof:name":"Dongkou",
    "wof:placetype":"locality"
},
  "geometry": {"coordinates":[115.28006000000001,27.76879000000001],"type":"Point"}
}