{
  "type": "Feature",
  "properties": {
    "gn:admin1_code":"18",
    "gn:asciiname":"Xiaomeizichong",
    "gn:country_code":"CN",
    "gn:dem":1761,
    "gn:feature_class":"P",
    "gn:feature_code":"PPL",
    "gn:name":"Xiaomeizichong",
    "gn:population":0,
    "gn:timezone":"Asia/Shanghai",
    "iso:country":"CN",
    "name:zho_x_preferred":[
        "\u5c0f\u6885\u5b50\u51b2"
    ],
    "wof:name":"Xiaomeizichong",
    "wof:placetype":"locality"
},
  "geometry": {"coordinates":[104.64400000000001,25.6417],"type":"Point"}
}