{
  "type": "Feature",
  "properties": {
    "gn:admin1_code":"11.0",
    "gn:asciiname":"Zhaiya",
    "gn:cc2":"CN",
    "gn:country_code":"CN",
    "gn:dem":389,
    "gn:feature_class":"P",
    "gn:feature_code":"PPL",
    "gn:name":"Zhaiya",
    "gn:population":0,
    "gn:timezone":"Asia/Shanghai",
    "iso:country":"CN",
    "name:und_x_variant":[
        "Chzhayya",
        "Chai-ya",
        "Zhaiya"
    ],
    "wof:name":"Zhaiya",
    "wof:placetype":"locality"
},
  "geometry": {"coordinates":[109.82917,26.52806],"type":"Point"}
}