{
  "type": "Feature",
  "properties": {
    "gn:admin1_code":"25",
    "gn:asciiname":"Beiniujia",
    "gn:country_code":"CN",
    "gn:dem":34,
    "gn:feature_class":"P",
    "gn:feature_code":"PPL",
    "gn:name":"Beiniujia",
    "gn:population":0,
    "gn:timezone":"Asia/Shanghai",
    "iso:country":"CN",
    "name:zho_x_preferred":[
        "\u5317\u725b\u5bb6"
    ],
    "wof:name":"Beiniujia",
    "wof:placetype":"locality"
},
  "geometry": {"coordinates":[118.589,36.8378],"type":"Point"}
}