{
  "type": "Feature",
  "properties": {
    "gn:admin1_code":"26",
    "gn:asciiname":"Wangbiaodian",
    "gn:cc2":"CN",
    "gn:country_code":"CN",
    "gn:dem":275,
    "gn:feature_class":"P",
    "gn:feature_code":"PPL",
    "gn:name":"Wangbiaodian",
    "gn:population":0,
    "gn:timezone":"Asia/Shanghai",
    "iso:country":"CN",
    "name:und_x_variant":[
        "Wang-piao-tien",
        "Wang-p\u2019o-tien",
        "Wangbiaodian"
    ],
    "wof:name":"Wangbiaodian",
    "wof:placetype":"locality"
},
  "geometry": {"coordinates":[108.80638999999999,32.72583],"type":"Point"}
}