{
  "type": "Feature",
  "properties": {
    "gn:admin1_code":"3.0",
    "gn:asciiname":"Getangchong",
    "gn:country_code":"CN",
    "gn:dem":205,
    "gn:feature_class":"P",
    "gn:feature_code":"PPL",
    "gn:name":"Getangchong",
    "gn:population":0,
    "gn:timezone":"Asia/Shanghai",
    "iso:country":"CN",
    "name:zho_x_preferred":[
        "\u9601\u5858\u51b2"
    ],
    "wof:name":"Getangchong",
    "wof:placetype":"locality"
},
  "geometry": {"coordinates":[113.958,27.052],"type":"Point"}
}