{
  "type": "Feature",
  "properties": {
    "gn:admin1_code":"10",
    "gn:asciiname":"Xia'erdao Hezi",
    "gn:country_code":"CN",
    "gn:dem":450,
    "gn:feature_class":"P",
    "gn:feature_code":"PPL",
    "gn:name":"Xia\u2019erdao Hezi",
    "gn:population":0,
    "gn:timezone":"Asia/Shanghai",
    "iso:country":"CN",
    "name:und_x_variant":[
        "Xia\u2019erdao Hezi"
    ],
    "name:zho_x_preferred":[
        "\u4e0b\u4e8c\u9053\u6cb3\u5b50"
    ],
    "wof:name":"Xia'erdao Hezi",
    "wof:placetype":"locality"
},
  "geometry": {"coordinates":[118.27551,41.04558],"type":"Point"}
}