{
  "type": "Feature",
  "properties": {
    "gn:admin1_code":"12.0",
    "gn:asciiname":"Xianhepu",
    "gn:country_code":"CN",
    "gn:dem":411,
    "gn:feature_class":"P",
    "gn:feature_code":"PPL",
    "gn:name":"Xianhepu",
    "gn:population":0,
    "gn:timezone":"Asia/Shanghai",
    "iso:country":"CN",
    "name:und_x_variant":[
        "Hsien-ho-p\u2019u",
        "Xianhepu"
    ],
    "name:zho_x_preferred":[
        "\u53bf\u6cb3\u94fa"
    ],
    "wof:name":"Xianhepu",
    "wof:placetype":"locality"
},
  "geometry": {"coordinates":[109.89641,32.31206],"type":"Point"}
}