{
  "type": "Feature",
  "properties": {
    "gn:admin1_code":"9",
    "gn:asciiname":"Beilizhuang",
    "gn:country_code":"CN",
    "gn:dem":35,
    "gn:feature_class":"P",
    "gn:feature_code":"PPL",
    "gn:name":"Beilizhuang",
    "gn:population":0,
    "gn:timezone":"Asia/Shanghai",
    "iso:country":"CN",
    "name:zho_x_preferred":[
        "\u5317\u674e\u5e84"
    ],
    "wof:name":"Beilizhuang",
    "wof:placetype":"locality"
},
  "geometry": {"coordinates":[116.331,34.0082],"type":"Point"}
}