{
  "type": "Feature",
  "properties": {
    "gn:admin1_code":"4.0",
    "gn:asciiname":"Tonghai",
    "gn:country_code":"CN",
    "gn:dem":20,
    "gn:feature_class":"P",
    "gn:feature_code":"PPL",
    "gn:name":"Tonghai",
    "gn:population":0,
    "gn:timezone":"Asia/Shanghai",
    "iso:country":"CN",
    "name:zho_x_preferred":[
        "\u4edd\u6d77"
    ],
    "wof:name":"Tonghai",
    "wof:placetype":"locality"
},
  "geometry": {"coordinates":[118.066,33.8329],"type":"Point"}
}