{
  "type": "Feature",
  "properties": {
    "gn:admin1_code":"32",
    "gn:asciiname":"Qingxi",
    "gn:country_code":"CN",
    "gn:dem":348,
    "gn:feature_class":"P",
    "gn:feature_code":"PPL",
    "gn:name":"Qingxi",
    "gn:population":0,
    "gn:timezone":"Asia/Shanghai",
    "iso:country":"CN",
    "name:ceb_x_preferred":[
        "Qingxi"
    ],
    "name:deu_x_preferred":[
        "Qingxi"
    ],
    "name:swe_x_preferred":[
        "Qingxi"
    ],
    "name:und_x_variant":[
        "Ch\u2019ing-ch\u2019i-ch\u2019ang",
        "Qingxichang",
        "Qingxi"
    ],
    "name:zho_x_preferred":[
        "\u6e05\u6eaa"
    ],
    "wof:name":"Qingxi",
    "wof:placetype":"locality"
},
  "geometry": {"coordinates":[107.79598,31.41966],"type":"Point"}
}