{
  "type": "Feature",
  "properties": {
    "gn:admin1_code":"14.0",
    "gn:asciiname":"Zhigunong",
    "gn:country_code":"CN",
    "gn:dem":4917,
    "gn:feature_class":"P",
    "gn:feature_code":"PPL",
    "gn:name":"Zhigunong",
    "gn:population":0,
    "gn:timezone":"Asia/Urumqi",
    "iso:country":"CN",
    "name:zho_x_preferred":[
        "\u81f4\u53e4\u5f04"
    ],
    "wof:name":"Zhigunong",
    "wof:placetype":"locality"
},
  "geometry": {"coordinates":[87.41459999999999,29.637],"type":"Point"}
}