{
  "type": "Feature",
  "properties": {
    "gn:admin1_code":"12.0",
    "gn:asciiname":"Shenjiangzhan",
    "gn:country_code":"CN",
    "gn:dem":30,
    "gn:feature_class":"P",
    "gn:feature_code":"PPL",
    "gn:name":"Shenjiangzhan",
    "gn:population":0,
    "gn:timezone":"Asia/Shanghai",
    "iso:country":"CN",
    "name:zho_x_preferred":[
        "\u6df1\u6c5f\u7ad9"
    ],
    "wof:name":"Shenjiangzhan",
    "wof:placetype":"locality"
},
  "geometry": {"coordinates":[112.98271,30.42583],"type":"Point"}
}