{
  "type": "Feature",
  "properties": {
    "gn:admin1_code":"20.0",
    "gn:asciiname":"Sanquan Jiudui",
    "gn:country_code":"CN",
    "gn:dem":410,
    "gn:feature_class":"P",
    "gn:feature_code":"PPLF",
    "gn:name":"Sanquan Jiudui",
    "gn:population":0,
    "gn:timezone":"Asia/Shanghai",
    "iso:country":"CN",
    "name:zho_x_preferred":[
        "\u4e09\u6cc9\u4e5d\u961f"
    ],
    "wof:name":"Sanquan Jiudui",
    "wof:placetype":"locality"
},
  "geometry": {"coordinates":[124.28382000000001,50.21948],"type":"Point"}
}