{
  "type": "Feature",
  "properties": {
    "gn:admin1_code":"20.0",
    "gn:asciiname":"Hexiliuzu",
    "gn:country_code":"CN",
    "gn:dem":396,
    "gn:feature_class":"P",
    "gn:feature_code":"PPL",
    "gn:name":"Hexiliuzu",
    "gn:population":0,
    "gn:timezone":"Asia/Shanghai",
    "iso:country":"CN",
    "name:zho_x_preferred":[
        "\u6cb3\u897f\u516d\u7ec4"
    ],
    "wof:name":"Hexiliuzu",
    "wof:placetype":"locality"
},
  "geometry": {"coordinates":[123.02034999999999,48.49364],"type":"Point"}
}