{
  "type": "Feature",
  "properties": {
    "gn:admin1_code":"29.0",
    "gn:asciiname":"Zhumasai",
    "gn:country_code":"CN",
    "gn:dem":3056,
    "gn:feature_class":"P",
    "gn:feature_code":"PPL",
    "gn:name":"Zhumasai",
    "gn:population":0,
    "gn:timezone":"Asia/Shanghai",
    "iso:country":"CN",
    "name:zho_x_preferred":[
        "\u7af9\u9a6c\u8d5b"
    ],
    "wof:name":"Zhumasai",
    "wof:placetype":"locality"
},
  "geometry": {"coordinates":[99.5462,27.1606],"type":"Point"}
}