{
  "type": "Feature",
  "properties": {
    "gn:admin1_code":"32.0",
    "gn:asciiname":"Gangezhuang",
    "gn:country_code":"CN",
    "gn:dem":2314,
    "gn:feature_class":"P",
    "gn:feature_code":"PPL",
    "gn:name":"Gangezhuang",
    "gn:population":0,
    "gn:timezone":"Asia/Shanghai",
    "iso:country":"CN",
    "name:zho_x_preferred":[
        "\u5e72\u7599\u6869"
    ],
    "wof:name":"Gangezhuang",
    "wof:placetype":"locality"
},
  "geometry": {"coordinates":[102.246,26.899],"type":"Point"}
}