{
  "type": "Feature",
  "properties": {
    "gn:admin1_code":"4.0",
    "gn:asciiname":"Dawangzhuangcun",
    "gn:country_code":"CN",
    "gn:dem":43,
    "gn:feature_class":"P",
    "gn:feature_code":"PPL",
    "gn:name":"Dawangzhuangcun",
    "gn:population":0,
    "gn:timezone":"Asia/Shanghai",
    "iso:country":"CN",
    "name:zho_x_preferred":[
        "\u5927\u738b\u5e84\u6751"
    ],
    "wof:name":"Dawangzhuangcun",
    "wof:placetype":"locality"
},
  "geometry": {"coordinates":[116.6795,34.6311],"type":"Point"}
}