{
  "type": "Feature",
  "properties": {
    "gn:admin1_code":"32",
    "gn:asciiname":"Gongxing",
    "gn:country_code":"CN",
    "gn:dem":496,
    "gn:feature_class":"P",
    "gn:feature_code":"PPL",
    "gn:name":"Gongxing",
    "gn:population":0,
    "gn:timezone":"Asia/Shanghai",
    "iso:country":"CN",
    "name:zho_x_preferred":[
        "\u516c\u5174"
    ],
    "wof:name":"Gongxing",
    "wof:placetype":"locality"
},
  "geometry": {"coordinates":[105.60312999999999,31.70661],"type":"Point"}
}