{
  "type": "Feature",
  "properties": {
    "gn:admin1_code":"4.0",
    "gn:asciiname":"Huangzi Xiaoxu",
    "gn:country_code":"CN",
    "gn:dem":4,
    "gn:feature_class":"P",
    "gn:feature_code":"PPL",
    "gn:name":"Huangzi Xiaoxu",
    "gn:population":0,
    "gn:timezone":"Asia/Shanghai",
    "iso:country":"CN",
    "name:zho_x_preferred":[
        "\u9ec4\u5b57\u5c0f\u5729"
    ],
    "wof:name":"Huangzi Xiaoxu",
    "wof:placetype":"locality"
},
  "geometry": {"coordinates":[120.78239000000001,32.06869],"type":"Point"}
}