{
  "type": "Feature",
  "properties": {
    "gn:admin1_code":"5.0",
    "gn:asciiname":"Xiaotonggou",
    "gn:country_code":"CN",
    "gn:dem":619,
    "gn:feature_class":"P",
    "gn:feature_code":"PPL",
    "gn:name":"Xiaotonggou",
    "gn:population":0,
    "gn:timezone":"Asia/Shanghai",
    "iso:country":"CN",
    "name:zho_x_preferred":[
        "\u5c0f\u901a\u6c9f"
    ],
    "wof:name":"Xiaotonggou",
    "wof:placetype":"locality"
},
  "geometry": {"coordinates":[126.47001000000002,41.90416],"type":"Point"}
}