{
  "type": "Feature",
  "properties": {
    "gn:admin1_code":"16.0",
    "gn:asciiname":"Jiling",
    "gn:country_code":"CN",
    "gn:dem":49,
    "gn:feature_class":"P",
    "gn:feature_code":"PPL",
    "gn:name":"Jiling",
    "gn:population":0,
    "gn:timezone":"Asia/Shanghai",
    "iso:country":"CN",
    "name:zho_x_preferred":[
        "\u5409\u5cad"
    ],
    "wof:name":"Jiling",
    "wof:placetype":"locality"
},
  "geometry": {"coordinates":[110.07299999999999,23.5647],"type":"Point"}
}