{
  "type": "Feature",
  "properties": {
    "gn:admin1_code":"30",
    "gn:asciiname":"Wanyaoxia",
    "gn:country_code":"CN",
    "gn:dem":515,
    "gn:feature_class":"P",
    "gn:feature_code":"PPL",
    "gn:name":"Wanyaoxia",
    "gn:population":0,
    "gn:timezone":"Asia/Shanghai",
    "iso:country":"CN",
    "name:zho_x_preferred":[
        "\u7897\u7a91\u4e0b"
    ],
    "wof:name":"Wanyaoxia",
    "wof:placetype":"locality"
},
  "geometry": {"coordinates":[116.86185999999999,24.19576],"type":"Point"}
}