{
  "type": "Feature",
  "properties": {
    "gn:admin1_code":"3.0",
    "gn:asciiname":"Qixing",
    "gn:country_code":"CN",
    "gn:dem":290,
    "gn:feature_class":"P",
    "gn:feature_code":"PPL",
    "gn:name":"Qixing",
    "gn:population":0,
    "gn:timezone":"Asia/Shanghai",
    "iso:country":"CN",
    "name:ceb_x_preferred":[
        "Qixing"
    ],
    "name:deu_x_preferred":[
        "Qixing"
    ],
    "name:fra_x_preferred":[
        "Qixing"
    ],
    "name:und_x_variant":[
        "\u65d7\u5f62"
    ],
    "wof:name":"Qixing",
    "wof:placetype":"locality"
},
  "geometry": {"coordinates":[116.32725000000001,26.58887],"type":"Point"}
}