{
  "type": "Feature",
  "properties": {
    "gn:admin1_code":"26.0",
    "gn:asciiname":"Tuoyan Goucun",
    "gn:country_code":"CN",
    "gn:dem":1020,
    "gn:feature_class":"P",
    "gn:feature_code":"PPL",
    "gn:name":"Tuoyan Goucun",
    "gn:population":0,
    "gn:timezone":"Asia/Shanghai",
    "iso:country":"CN",
    "name:zho_x_preferred":[
        "\u9a7c\u71d5\u6c9f\u6751"
    ],
    "wof:name":"Tuoyan Goucun",
    "wof:placetype":"locality"
},
  "geometry": {"coordinates":[109.563,38.0428],"type":"Point"}
}