{
  "type": "Feature",
  "properties": {
    "gn:admin1_code":"18",
    "gn:asciiname":"Wenjia Yanjiao",
    "gn:country_code":"CN",
    "gn:dem":1282,
    "gn:feature_class":"P",
    "gn:feature_code":"PPL",
    "gn:name":"Wenjia Yanjiao",
    "gn:population":0,
    "gn:timezone":"Asia/Shanghai",
    "iso:country":"CN",
    "name:zho_x_preferred":[
        "\u6587\u5bb6\u5ca9\u811a"
    ],
    "wof:name":"Wenjia Yanjiao",
    "wof:placetype":"locality"
},
  "geometry": {"coordinates":[106.95699999999999,25.8798],"type":"Point"}
}