{
  "type": "Feature",
  "properties": {
    "gn:admin1_code":"28",
    "gn:asciiname":"Daliutan",
    "gn:country_code":"CN",
    "gn:dem":7,
    "gn:feature_class":"P",
    "gn:feature_code":"PPL",
    "gn:name":"Daliutan",
    "gn:population":0,
    "gn:timezone":"Asia/Shanghai",
    "iso:country":"CN",
    "name:zho_x_preferred":[
        "\u5927\u67f3\u6ee9"
    ],
    "wof:name":"Daliutan",
    "wof:placetype":"locality"
},
  "geometry": {"coordinates":[116.96276,39.15904000000001],"type":"Point"}
}