{
  "type": "Feature",
  "properties": {
    "gn:admin1_code":"9.0",
    "gn:asciiname":"Baizhangtun",
    "gn:country_code":"CN",
    "gn:dem":75,
    "gn:feature_class":"P",
    "gn:feature_code":"PPL",
    "gn:name":"Baizhangtun",
    "gn:population":0,
    "gn:timezone":"Asia/Shanghai",
    "iso:country":"CN",
    "name:zho_x_preferred":[
        "\u67cf\u4e08\u5c6f"
    ],
    "wof:name":"Baizhangtun",
    "wof:placetype":"locality"
},
  "geometry": {"coordinates":[114.21819000000001,32.72918],"type":"Point"}
}