{
  "type": "Feature",
  "properties": {
    "gn:admin1_code":"2",
    "gn:asciiname":"Baiyang",
    "gn:country_code":"CN",
    "gn:dem":149,
    "gn:feature_class":"P",
    "gn:feature_code":"PPL",
    "gn:name":"Baiyang",
    "gn:population":0,
    "gn:timezone":"Asia/Shanghai",
    "iso:country":"CN",
    "name:ceb_x_preferred":[
        "Baiyang"
    ],
    "name:deu_x_preferred":[
        "Baiyang"
    ],
    "name:swe_x_preferred":[
        "Baiyang"
    ],
    "wof:name":"Baiyang",
    "wof:placetype":"locality"
},
  "geometry": {"coordinates":[119.495,30.68083],"type":"Point"}
}