{
  "type": "Feature",
  "properties": {
    "gn:admin1_code":"3.0",
    "gn:asciiname":"Heshuwo",
    "gn:country_code":"CN",
    "gn:dem":708,
    "gn:feature_class":"P",
    "gn:feature_code":"PPL",
    "gn:name":"Heshuwo",
    "gn:population":0,
    "gn:timezone":"Asia/Shanghai",
    "iso:country":"CN",
    "name:zho_x_preferred":[
        "\u8377\u6811\u7a9d"
    ],
    "wof:name":"Heshuwo",
    "wof:placetype":"locality"
},
  "geometry": {"coordinates":[115.45399999999999,26.1703],"type":"Point"}
}