{
  "type": "Feature",
  "properties": {
    "gn:admin1_code":"2.0",
    "gn:asciiname":"Changqiaotou",
    "gn:country_code":"CN",
    "gn:dem":7,
    "gn:feature_class":"P",
    "gn:feature_code":"PPL",
    "gn:name":"Changqiaotou",
    "gn:population":0,
    "gn:timezone":"Asia/Shanghai",
    "iso:country":"CN",
    "name:und_x_variant":[
        "\u957f\u6865\u5934"
    ],
    "wof:name":"Changqiaotou",
    "wof:placetype":"locality"
},
  "geometry": {"coordinates":[120.63414,30.78823],"type":"Point"}
}