{
  "type": "Feature",
  "properties": {
    "gn:admin1_code":"7.0",
    "gn:asciiname":"Yunlu",
    "gn:country_code":"CN",
    "gn:dem":791,
    "gn:feature_class":"P",
    "gn:feature_code":"PPL",
    "gn:name":"Yunlu",
    "gn:population":0,
    "gn:timezone":"Asia/Shanghai",
    "iso:country":"CN",
    "name:vie_x_preferred":[
        "D\u1eadn L\u1ed9c"
    ],
    "name:zho_x_preferred":[
        "\u4e91\u8def"
    ],
    "wof:name":"Yunlu",
    "wof:placetype":"locality"
},
  "geometry": {"coordinates":[118.15038,25.71864],"type":"Point"}
}