{
  "type": "Feature",
  "properties": {
    "gn:admin1_code":"3.0",
    "gn:asciiname":"Beitou Gaojia",
    "gn:country_code":"CN",
    "gn:dem":23,
    "gn:feature_class":"P",
    "gn:feature_code":"PPL",
    "gn:name":"Beitou Gaojia",
    "gn:population":0,
    "gn:timezone":"Asia/Shanghai",
    "iso:country":"CN",
    "name:und_x_variant":[
        "\u5317\u5934\u9ad8\u5bb6"
    ],
    "wof:name":"Beitou Gaojia",
    "wof:placetype":"locality"
},
  "geometry": {"coordinates":[116.16463,28.53248],"type":"Point"}
}