{
  "type": "Feature",
  "properties": {
    "gn:admin1_code":"11.0",
    "gn:asciiname":"Ganshanchong",
    "gn:country_code":"CN",
    "gn:dem":205,
    "gn:feature_class":"P",
    "gn:feature_code":"PPL",
    "gn:name":"Ganshanchong",
    "gn:population":0,
    "gn:timezone":"Asia/Shanghai",
    "iso:country":"CN",
    "name:zho_x_preferred":[
        "\u5e72\u5c71\u51b2"
    ],
    "wof:name":"Ganshanchong",
    "wof:placetype":"locality"
},
  "geometry": {"coordinates":[112.05373,28.11156],"type":"Point"}
}