{
  "type": "Feature",
  "properties": {
    "gn:admin1_code":"19.0",
    "gn:asciiname":"Liuhatuncun",
    "gn:country_code":"CN",
    "gn:dem":124,
    "gn:feature_class":"P",
    "gn:feature_code":"PPL",
    "gn:name":"Liuhatuncun",
    "gn:population":0,
    "gn:timezone":"Asia/Shanghai",
    "iso:country":"CN",
    "name:zho_x_preferred":[
        "\u5218\u54c8\u5c6f\u6751"
    ],
    "wof:name":"Liuhatuncun",
    "wof:placetype":"locality"
},
  "geometry": {"coordinates":[120.87262,41.14167],"type":"Point"}
}