{
  "type": "Feature",
  "properties": {
    "gn:admin1_code":"26",
    "gn:asciiname":"Daijiaba",
    "gn:country_code":"CN",
    "gn:dem":822,
    "gn:feature_class":"P",
    "gn:feature_code":"PPLA4",
    "gn:name":"Daijiaba",
    "gn:population":0,
    "gn:timezone":"Asia/Shanghai",
    "iso:country":"CN",
    "name:und_x_variant":[
        "Tai-chia-pa",
        "Daijiaba",
        "\u4ee3\u5bb6\u575d",
        "Daijiaba Zhen",
        "\u4ee3\u5bb6\u575d\u9547"
    ],
    "wof:name":"Daijiaba",
    "wof:placetype":"locality"
},
  "geometry": {"coordinates":[106.18352,33.0097],"type":"Point"}
}