{
  "type": "Feature",
  "properties": {
    "gn:admin1_code":"18.0",
    "gn:asciiname":"Shenjiangyan",
    "gn:country_code":"CN",
    "gn:dem":431,
    "gn:feature_class":"P",
    "gn:feature_code":"PPL",
    "gn:name":"Shenjiangyan",
    "gn:population":0,
    "gn:timezone":"Asia/Shanghai",
    "iso:country":"CN",
    "name:zho_x_preferred":[
        "\u6df1\u6c5f\u5ca9"
    ],
    "wof:name":"Shenjiangyan",
    "wof:placetype":"locality"
},
  "geometry": {"coordinates":[108.709,27.1101],"type":"Point"}
}