{
  "type": "Feature",
  "properties": {
    "gn:admin1_code":"14.0",
    "gn:asciiname":"Gongbutong",
    "gn:country_code":"CN",
    "gn:dem":3747,
    "gn:feature_class":"P",
    "gn:feature_code":"PPL",
    "gn:name":"Gongbutong",
    "gn:population":0,
    "gn:timezone":"Asia/Urumqi",
    "iso:country":"CN",
    "name:zho_x_preferred":[
        "\u516c\u5e03\u540c"
    ],
    "wof:name":"Gongbutong",
    "wof:placetype":"locality"
},
  "geometry": {"coordinates":[98.60588,29.50092],"type":"Point"}
}