{
  "type": "Feature",
  "properties": {
    "gn:admin1_code":"29.0",
    "gn:asciiname":"Luhua",
    "gn:country_code":"CN",
    "gn:dem":2106,
    "gn:feature_class":"P",
    "gn:feature_code":"PPL",
    "gn:name":"Luhua",
    "gn:population":0,
    "gn:timezone":"Asia/Shanghai",
    "iso:country":"CN",
    "name:zho_x_preferred":[
        "\u8def\u82b1"
    ],
    "wof:name":"Luhua",
    "wof:placetype":"locality"
},
  "geometry": {"coordinates":[103.617,24.8757],"type":"Point"}
}