{
  "type": "Feature",
  "properties": {
    "gn:admin1_code":"31.0",
    "gn:asciiname":"Wanzhong",
    "gn:country_code":"CN",
    "gn:dem":356,
    "gn:elevation":"445.0",
    "gn:feature_class":"P",
    "gn:feature_code":"PPL",
    "gn:name":"Wanzhong",
    "gn:population":0,
    "gn:timezone":"Asia/Shanghai",
    "iso:country":"CN",
    "name:und_x_variant":[
        "\u4e07\u4f17"
    ],
    "wof:name":"Wanzhong",
    "wof:placetype":"locality"
},
  "geometry": {"coordinates":[109.83915,18.95624],"type":"Point"}
}