{
  "type": "Feature",
  "properties": {
    "gn:admin1_code":"7",
    "gn:asciiname":"Heyu",
    "gn:country_code":"CN",
    "gn:dem":4,
    "gn:feature_class":"P",
    "gn:feature_code":"PPL",
    "gn:name":"Heyu",
    "gn:population":0,
    "gn:timezone":"Asia/Shanghai",
    "iso:country":"CN",
    "name:zho_x_preferred":[
        "\u8377\u5c7f"
    ],
    "wof:name":"Heyu",
    "wof:placetype":"locality"
},
  "geometry": {"coordinates":[119.62526,26.77262],"type":"Point"}
}