{
  "type": "Feature",
  "properties": {
    "gn:admin1_code":"4.0",
    "gn:asciiname":"Wanying",
    "gn:country_code":"CN",
    "gn:dem":44,
    "gn:feature_class":"P",
    "gn:feature_code":"PPL",
    "gn:name":"Wanying",
    "gn:population":0,
    "gn:timezone":"Asia/Shanghai",
    "iso:country":"CN",
    "name:zho_x_preferred":[
        "\u4e07\u90e2"
    ],
    "wof:name":"Wanying",
    "wof:placetype":"locality"
},
  "geometry": {"coordinates":[118.57268999999999,32.79371],"type":"Point"}
}