{
  "type": "Feature",
  "properties": {
    "gn:admin1_code":"5.0",
    "gn:asciiname":"Jianshe",
    "gn:country_code":"CN",
    "gn:dem":363,
    "gn:feature_class":"P",
    "gn:feature_code":"PPL",
    "gn:name":"Jianshe",
    "gn:population":0,
    "gn:timezone":"Asia/Shanghai",
    "iso:country":"CN",
    "name:ceb_x_preferred":[
        "Jianshe"
    ],
    "name:deu_x_preferred":[
        "Jianshe"
    ],
    "name:swe_x_preferred":[
        "Jianshe"
    ],
    "name:und_x_variant":[
        "\u5efa\u8bbe"
    ],
    "wof:name":"Jianshe",
    "wof:placetype":"locality"
},
  "geometry": {"coordinates":[125.53046999999999,41.50193],"type":"Point"}
}