{
  "type": "Feature",
  "properties": {
    "gn:admin1_code":"8.0",
    "gn:asciiname":"Wanbaoshancun",
    "gn:country_code":"CN",
    "gn:dem":368,
    "gn:feature_class":"P",
    "gn:feature_code":"PPL",
    "gn:name":"Wanbaoshancun",
    "gn:population":0,
    "gn:timezone":"Asia/Shanghai",
    "iso:country":"CN",
    "name:zho_x_preferred":[
        "\u4e07\u5b9d\u5c71\u6751"
    ],
    "wof:name":"Wanbaoshancun",
    "wof:placetype":"locality"
},
  "geometry": {"coordinates":[131.53538,46.12628],"type":"Point"}
}