{
  "type": "Feature",
  "properties": {
    "gn:admin1_code":"3",
    "gn:asciiname":"Zoumaling",
    "gn:country_code":"CN",
    "gn:dem":298,
    "gn:feature_class":"P",
    "gn:feature_code":"PPL",
    "gn:name":"Zoumaling",
    "gn:population":0,
    "gn:timezone":"Asia/Shanghai",
    "iso:country":"CN",
    "name:zho_x_preferred":[
        "\u8d70\u9a6c\u5cad"
    ],
    "wof:name":"Zoumaling",
    "wof:placetype":"locality"
},
  "geometry": {"coordinates":[114.063,25.6505],"type":"Point"}
}