{
  "type": "Feature",
  "properties": {
    "gn:admin1_code":"25.0",
    "gn:asciiname":"Xiaosunjia",
    "gn:country_code":"CN",
    "gn:dem":9,
    "gn:feature_class":"P",
    "gn:feature_code":"PPL",
    "gn:name":"Xiaosunjia",
    "gn:population":0,
    "gn:timezone":"Asia/Shanghai",
    "iso:country":"CN",
    "name:zho_x_preferred":[
        "\u5c0f\u5b59\u5bb6"
    ],
    "wof:name":"Xiaosunjia",
    "wof:placetype":"locality"
},
  "geometry": {"coordinates":[122.47087999999999,37.15994],"type":"Point"}
}