{
  "type": "Feature",
  "properties": {
    "gn:admin1_code":"3.0",
    "gn:asciiname":"Qixia",
    "gn:country_code":"CN",
    "gn:dem":348,
    "gn:feature_class":"P",
    "gn:feature_code":"PPL",
    "gn:name":"Qixia",
    "gn:population":0,
    "gn:timezone":"Asia/Shanghai",
    "iso:country":"CN",
    "name:zho_x_preferred":[
        "\u78dc\u4e0b"
    ],
    "wof:name":"Qixia",
    "wof:placetype":"locality"
},
  "geometry": {"coordinates":[117.06344,27.36281],"type":"Point"}
}