{
  "type": "Feature",
  "properties": {
    "gn:admin1_code":"04",
    "gn:asciiname":"Changsha",
    "gn:country_code":"CN",
    "gn:dem":9,
    "gn:feature_class":"P",
    "gn:feature_code":"PPLA4",
    "gn:name":"Changsha",
    "gn:population":0,
    "gn:timezone":"Asia/Shanghai",
    "iso:country":"CN",
    "name:und_x_variant":[
        "Ch\u2019ang-sha-chen",
        "Ch\u2019ang-sha",
        "Changsha",
        "\u957f\u6c99",
        "Changshazhen",
        "Changsha Zhen",
        "\u957f\u6c99\u9547"
    ],
    "wof:name":"Changsha",
    "wof:placetype":"locality"
},
  "geometry": {"coordinates":[121.28798999999999,32.4096],"type":"Point"}
}