{
  "type": "Feature",
  "properties": {
    "gn:admin1_code":"19.0",
    "gn:asciiname":"Haitinggou",
    "gn:country_code":"CN",
    "gn:dem":143,
    "gn:feature_class":"P",
    "gn:feature_code":"PPL",
    "gn:name":"Haitinggou",
    "gn:population":0,
    "gn:timezone":"Asia/Shanghai",
    "iso:country":"CN",
    "name:zho_x_preferred":[
        "\u6d77\u4ead\u6c9f"
    ],
    "wof:name":"Haitinggou",
    "wof:placetype":"locality"
},
  "geometry": {"coordinates":[120.099,40.7257],"type":"Point"}
}