{
  "type": "Feature",
  "properties": {
    "gn:admin1_code":"32.0",
    "gn:asciiname":"Banzhuwan",
    "gn:country_code":"CN",
    "gn:dem":440,
    "gn:feature_class":"P",
    "gn:feature_code":"PPL",
    "gn:name":"Banzhuwan",
    "gn:population":0,
    "gn:timezone":"Asia/Shanghai",
    "iso:country":"CN",
    "name:zho_x_preferred":[
        "\u6591\u7af9\u6e7e"
    ],
    "wof:name":"Banzhuwan",
    "wof:placetype":"locality"
},
  "geometry": {"coordinates":[103.98648,29.06552000000001],"type":"Point"}
}