{
  "type": "Feature",
  "properties": {
    "gn:admin1_code":"29",
    "gn:asciiname":"Ajiao Dazhai",
    "gn:country_code":"CN",
    "gn:dem":1579,
    "gn:feature_class":"P",
    "gn:feature_code":"PPL",
    "gn:name":"Ajiao Dazhai",
    "gn:population":0,
    "gn:timezone":"Asia/Shanghai",
    "iso:country":"CN",
    "name:zho_x_preferred":[
        "\u963f\u7ede\u5927\u5be8"
    ],
    "wof:name":"Ajiao Dazhai",
    "wof:placetype":"locality"
},
  "geometry": {"coordinates":[104.505,23.9512],"type":"Point"}
}