{
  "type": "Feature",
  "properties": {
    "gn:admin1_code":"26.0",
    "gn:asciiname":"Jigou",
    "gn:country_code":"CN",
    "gn:dem":762,
    "gn:feature_class":"P",
    "gn:feature_code":"PPL",
    "gn:name":"Jigou",
    "gn:population":0,
    "gn:timezone":"Asia/Shanghai",
    "iso:country":"CN",
    "name:zho_x_preferred":[
        "\u59ec\u6c9f"
    ],
    "wof:name":"Jigou",
    "wof:placetype":"locality"
},
  "geometry": {"coordinates":[110.07628,33.82371],"type":"Point"}
}