{
  "type": "Feature",
  "properties": {
    "gn:admin1_code":"19.0",
    "gn:asciiname":"Makuagou",
    "gn:country_code":"CN",
    "gn:dem":91,
    "gn:feature_class":"P",
    "gn:feature_code":"PPL",
    "gn:name":"Makuagou",
    "gn:population":0,
    "gn:timezone":"Asia/Shanghai",
    "iso:country":"CN",
    "name:zho_x_preferred":[
        "\u9a6c\u4f89\u6c9f"
    ],
    "wof:name":"Makuagou",
    "wof:placetype":"locality"
},
  "geometry": {"coordinates":[120.113,40.5157],"type":"Point"}
}