{
  "type": "Feature",
  "properties": {
    "gn:admin1_code":"15.0",
    "gn:asciiname":"Yangjiashangwan",
    "gn:country_code":"CN",
    "gn:dem":1712,
    "gn:feature_class":"P",
    "gn:feature_code":"PPL",
    "gn:name":"Yangjiashangwan",
    "gn:population":0,
    "gn:timezone":"Asia/Shanghai",
    "iso:country":"CN",
    "name:und_x_variant":[
        "\u6768\u5bb6\u4e0a\u6e7e"
    ],
    "wof:name":"Yangjiashangwan",
    "wof:placetype":"locality"
},
  "geometry": {"coordinates":[105.89727999999999,35.04238],"type":"Point"}
}