{
  "type": "Feature",
  "properties": {
    "gn:admin1_code":"10.0",
    "gn:asciiname":"Xifudian",
    "gn:country_code":"CN",
    "gn:dem":29,
    "gn:feature_class":"P",
    "gn:feature_code":"PPL",
    "gn:name":"Xifudian",
    "gn:population":0,
    "gn:timezone":"Asia/Shanghai",
    "iso:country":"CN",
    "name:zho_x_preferred":[
        "\u897f\u5085\u5e97"
    ],
    "wof:name":"Xifudian",
    "wof:placetype":"locality"
},
  "geometry": {"coordinates":[119.64757,39.98953],"type":"Point"}
}