{
  "type": "Feature",
  "properties": {
    "gn:admin1_code":"4.0",
    "gn:asciiname":"Anxiancun",
    "gn:country_code":"CN",
    "gn:dem":30,
    "gn:feature_class":"P",
    "gn:feature_code":"PPL",
    "gn:name":"Anxiancun",
    "gn:population":0,
    "gn:timezone":"Asia/Shanghai",
    "iso:country":"CN",
    "name:zho_x_preferred":[
        "\u5b89\u8d24\u6751"
    ],
    "wof:name":"Anxiancun",
    "wof:placetype":"locality"
},
  "geometry": {"coordinates":[117.9455,34.43689000000001],"type":"Point"}
}