{
  "type": "Feature",
  "properties": {
    "gn:admin1_code":"12.0",
    "gn:asciiname":"Liuwutai",
    "gn:country_code":"CN",
    "gn:dem":31,
    "gn:feature_class":"P",
    "gn:feature_code":"PPL",
    "gn:name":"Liuwutai",
    "gn:population":0,
    "gn:timezone":"Asia/Shanghai",
    "iso:country":"CN",
    "name:zho_x_preferred":[
        "\u516d\u5c4b\u53f0"
    ],
    "wof:name":"Liuwutai",
    "wof:placetype":"locality"
},
  "geometry": {"coordinates":[113.33578,30.3727],"type":"Point"}
}