{
  "type": "Feature",
  "properties": {
    "gn:admin1_code":"19",
    "gn:asciiname":"Laofangshen",
    "gn:country_code":"CN",
    "gn:dem":536,
    "gn:feature_class":"P",
    "gn:feature_code":"PPL",
    "gn:name":"Laofangshen",
    "gn:population":0,
    "gn:timezone":"Asia/Shanghai",
    "iso:country":"CN",
    "name:und_x_variant":[
        "Fang-shen",
        "Laofangshen"
    ],
    "name:zho_x_preferred":[
        "\u8001\u623f\u8eab"
    ],
    "wof:name":"Laofangshen",
    "wof:placetype":"locality"
},
  "geometry": {"coordinates":[119.48217,42.05257],"type":"Point"}
}