{
  "type": "Feature",
  "properties": {
    "gn:admin1_code":"2.0",
    "gn:asciiname":"Shiba",
    "gn:country_code":"CN",
    "gn:dem":605,
    "gn:feature_class":"P",
    "gn:feature_code":"PPL",
    "gn:name":"Shiba",
    "gn:population":0,
    "gn:timezone":"Asia/Shanghai",
    "iso:country":"CN",
    "name:ceb_x_preferred":[
        "Shiba"
    ],
    "name:deu_x_preferred":[
        "Shiba"
    ],
    "name:fas_x_preferred":[
        "\u0634\u06cc\u0628\u0627"
    ],
    "name:fra_x_preferred":[
        "Shiba"
    ],
    "name:ita_x_preferred":[
        "Shiba"
    ],
    "name:pol_x_preferred":[
        "Shiba"
    ],
    "name:rus_x_preferred":[
        "\u0421\u0438\u0431\u0430"
    ],
    "name:zho_x_preferred":[
        "\u77f3\u575d"
    ],
    "wof:name":"Shiba",
    "wof:placetype":"locality"
},
  "geometry": {"coordinates":[119.85256,27.78191],"type":"Point"}
}