{
  "type": "Feature",
  "properties": {
    "gn:admin1_code":"18",
    "gn:asciiname":"Tongtie",
    "gn:country_code":"CN",
    "gn:dem":1023,
    "gn:feature_class":"P",
    "gn:feature_code":"PPL",
    "gn:name":"Tongtie",
    "gn:population":0,
    "gn:timezone":"Asia/Shanghai",
    "iso:country":"CN",
    "wof:name":"Tongtie",
    "wof:placetype":"locality"
},
  "geometry": {"coordinates":[107.60138999999999,26.84167],"type":"Point"}
}