{
  "type": "Feature",
  "properties": {
    "gn:admin1_code":"2.0",
    "gn:asciiname":"Lijiaokeng",
    "gn:country_code":"CN",
    "gn:dem":10,
    "gn:feature_class":"P",
    "gn:feature_code":"PPL",
    "gn:name":"Lijiaokeng",
    "gn:population":0,
    "gn:timezone":"Asia/Shanghai",
    "iso:country":"CN",
    "name:zho_x_preferred":[
        "\u91cc\u89d2\u5751"
    ],
    "wof:name":"Lijiaokeng",
    "wof:placetype":"locality"
},
  "geometry": {"coordinates":[121.59272,28.27181],"type":"Point"}
}