{
  "type": "Feature",
  "properties": {
    "gn:admin1_code":"15.0",
    "gn:asciiname":"Zhangjialeng",
    "gn:country_code":"CN",
    "gn:dem":1218,
    "gn:feature_class":"P",
    "gn:feature_code":"PPL",
    "gn:name":"Zhangjialeng",
    "gn:population":0,
    "gn:timezone":"Asia/Shanghai",
    "iso:country":"CN",
    "name:und_x_variant":[
        "\u5f20\u5bb6\u5844"
    ],
    "wof:name":"Zhangjialeng",
    "wof:placetype":"locality"
},
  "geometry": {"coordinates":[106.14582,34.06293],"type":"Point"}
}