{
  "type": "Feature",
  "properties": {
    "gn:admin1_code":"16.0",
    "gn:asciiname":"Tanleng",
    "gn:country_code":"CN",
    "gn:dem":132,
    "gn:feature_class":"P",
    "gn:feature_code":"PPL",
    "gn:name":"Tanleng",
    "gn:population":0,
    "gn:timezone":"Asia/Shanghai",
    "iso:country":"CN",
    "name:zho_x_preferred":[
        "\u6ee9\u51b7"
    ],
    "wof:name":"Tanleng",
    "wof:placetype":"locality"
},
  "geometry": {"coordinates":[107.937,21.5863],"type":"Point"}
}