{
  "type": "Feature",
  "properties": {
    "gn:admin1_code":"12.0",
    "gn:asciiname":"Xiaojiawan",
    "gn:country_code":"CN",
    "gn:dem":24,
    "gn:feature_class":"P",
    "gn:feature_code":"PPL",
    "gn:name":"Xiaojiawan",
    "gn:population":0,
    "gn:timezone":"Asia/Shanghai",
    "iso:country":"CN",
    "name:und_x_variant":[
        "\u8096\u5bb6\u5846"
    ],
    "wof:name":"Xiaojiawan",
    "wof:placetype":"locality"
},
  "geometry": {"coordinates":[114.14865,30.43484],"type":"Point"}
}