{
  "type": "Feature",
  "properties": {
    "gn:admin1_code":"25",
    "gn:asciiname":"Yangjiashangliu",
    "gn:country_code":"CN",
    "gn:dem":73,
    "gn:feature_class":"P",
    "gn:feature_code":"PPL",
    "gn:name":"Yangjiashangliu",
    "gn:population":0,
    "gn:timezone":"Asia/Shanghai",
    "iso:country":"CN",
    "name:zho_x_preferred":[
        "\u626c\u5bb6\u4e0a\u6d41"
    ],
    "wof:name":"Yangjiashangliu",
    "wof:placetype":"locality"
},
  "geometry": {"coordinates":[120.48944,36.19086],"type":"Point"}
}