{
  "type": "Feature",
  "properties": {
    "gn:admin1_code":"18",
    "gn:asciiname":"Mengnong",
    "gn:country_code":"CN",
    "gn:dem":1231,
    "gn:feature_class":"P",
    "gn:feature_code":"PPL",
    "gn:name":"Mengnong",
    "gn:population":0,
    "gn:timezone":"Asia/Shanghai",
    "iso:country":"CN",
    "name:zho_x_preferred":[
        "\u8499\u5f04"
    ],
    "wof:name":"Mengnong",
    "wof:placetype":"locality"
},
  "geometry": {"coordinates":[106.179,26.11],"type":"Point"}
}