{
  "type": "Feature",
  "properties": {
    "gn:admin1_code":"3.0",
    "gn:asciiname":"Litou",
    "gn:country_code":"CN",
    "gn:dem":81,
    "gn:feature_class":"P",
    "gn:feature_code":"PPL",
    "gn:name":"Litou",
    "gn:population":0,
    "gn:timezone":"Asia/Shanghai",
    "iso:country":"CN",
    "name:und_x_variant":[
        "\u6ca5\u5934"
    ],
    "wof:name":"Litou",
    "wof:placetype":"locality"
},
  "geometry": {"coordinates":[114.7504,29.19427],"type":"Point"}
}