{
  "type": "Feature",
  "properties": {
    "gn:admin1_code":"29.0",
    "gn:asciiname":"Baizhaizi",
    "gn:country_code":"CN",
    "gn:dem":2777,
    "gn:feature_class":"P",
    "gn:feature_code":"PPL",
    "gn:name":"Baizhaizi",
    "gn:population":0,
    "gn:timezone":"Asia/Shanghai",
    "iso:country":"CN",
    "name:zho_x_preferred":[
        "\u767d\u5be8\u5b50"
    ],
    "wof:name":"Baizhaizi",
    "wof:placetype":"locality"
},
  "geometry": {"coordinates":[103.371,27.5792],"type":"Point"}
}