{
  "type": "Feature",
  "properties": {
    "gn:admin1_code":"7.0",
    "gn:asciiname":"Luowupai",
    "gn:country_code":"CN",
    "gn:dem":310,
    "gn:feature_class":"P",
    "gn:feature_code":"PPL",
    "gn:name":"Luowupai",
    "gn:population":0,
    "gn:timezone":"Asia/Shanghai",
    "iso:country":"CN",
    "name:zho_x_preferred":[
        "\u7f57\u5c4b\u6392"
    ],
    "wof:name":"Luowupai",
    "wof:placetype":"locality"
},
  "geometry": {"coordinates":[116.43358000000001,25.68763],"type":"Point"}
}