{
  "type": "Feature",
  "properties": {
    "gn:admin1_code":"7.0",
    "gn:asciiname":"Yaobeijiang",
    "gn:country_code":"CN",
    "gn:dem":353,
    "gn:feature_class":"P",
    "gn:feature_code":"PPL",
    "gn:name":"Yaobeijiang",
    "gn:population":0,
    "gn:timezone":"Asia/Shanghai",
    "iso:country":"CN",
    "name:zho_x_preferred":[
        "\u7476\u80cc\u6c5f"
    ],
    "wof:name":"Yaobeijiang",
    "wof:placetype":"locality"
},
  "geometry": {"coordinates":[116.48105,26.23439],"type":"Point"}
}