{
  "type": "Feature",
  "properties": {
    "gn:admin1_code":"15.0",
    "gn:asciiname":"Baojiacha",
    "gn:country_code":"CN",
    "gn:dem":2067,
    "gn:feature_class":"P",
    "gn:feature_code":"PPL",
    "gn:name":"Baojiacha",
    "gn:population":0,
    "gn:timezone":"Asia/Shanghai",
    "iso:country":"CN",
    "name:zho_x_preferred":[
        "\u5305\u5bb6\u5c94"
    ],
    "wof:name":"Baojiacha",
    "wof:placetype":"locality"
},
  "geometry": {"coordinates":[104.798,35.0531],"type":"Point"}
}