{
  "type": "Feature",
  "properties": {
    "gn:admin1_code":"21.0",
    "gn:asciiname":"Qujianao",
    "gn:country_code":"CN",
    "gn:dem":2008,
    "gn:feature_class":"P",
    "gn:feature_code":"PPL",
    "gn:name":"Qujianao",
    "gn:population":0,
    "gn:timezone":"Asia/Shanghai",
    "iso:country":"CN",
    "name:zho_x_preferred":[
        "\u5c48\u5bb6\u57b4"
    ],
    "wof:name":"Qujianao",
    "wof:placetype":"locality"
},
  "geometry": {"coordinates":[105.45967,35.92095],"type":"Point"}
}