{
  "type": "Feature",
  "properties": {
    "gn:admin1_code":"5.0",
    "gn:asciiname":"Shenglicun",
    "gn:country_code":"CN",
    "gn:dem":593,
    "gn:feature_class":"P",
    "gn:feature_code":"PPL",
    "gn:name":"Shenglicun",
    "gn:population":0,
    "gn:timezone":"Asia/Shanghai",
    "iso:country":"CN",
    "name:und_x_variant":[
        "\u80dc\u5229\u6751"
    ],
    "wof:name":"Shenglicun",
    "wof:placetype":"locality"
},
  "geometry": {"coordinates":[126.83947000000001,41.84728],"type":"Point"}
}