{
  "type": "Feature",
  "properties": {
    "gn:admin1_code":"29.0",
    "gn:asciiname":"Houcaocun",
    "gn:country_code":"CN",
    "gn:dem":1234,
    "gn:feature_class":"P",
    "gn:feature_code":"PPL",
    "gn:name":"Houcaocun",
    "gn:population":0,
    "gn:timezone":"Asia/Shanghai",
    "iso:country":"CN",
    "name:zho_x_preferred":[
        "\u540e\u69fd\u6751"
    ],
    "wof:name":"Houcaocun",
    "wof:placetype":"locality"
},
  "geometry": {"coordinates":[105.166,27.5634],"type":"Point"}
}