{
  "type": "Feature",
  "properties": {
    "gn:admin1_code":"4.0",
    "gn:asciiname":"Dazhong Nongchang",
    "gn:country_code":"CN",
    "gn:dem":3,
    "gn:feature_class":"P",
    "gn:feature_code":"PPLF",
    "gn:name":"Dazhong Nongchang",
    "gn:population":0,
    "gn:timezone":"Asia/Shanghai",
    "iso:country":"CN",
    "name:und_x_variant":[
        "\u5927\u4e2d\u519c\u573a"
    ],
    "wof:name":"Dazhong Nongchang",
    "wof:placetype":"locality"
},
  "geometry": {"coordinates":[120.65492,33.13661],"type":"Point"}
}