{
  "type": "Feature",
  "properties": {
    "gn:admin1_code":"16.0",
    "gn:asciiname":"Nibei",
    "gn:country_code":"CN",
    "gn:dem":77,
    "gn:feature_class":"P",
    "gn:feature_code":"PPL",
    "gn:name":"Nibei",
    "gn:population":0,
    "gn:timezone":"Asia/Shanghai",
    "iso:country":"CN",
    "name:fas_x_preferred":[
        "\u0646\u06cc\u0628\u0626\u06cc"
    ],
    "name:zho_x_preferred":[
        "\u576d\u7891"
    ],
    "name:zho_x_variant":[
        "\u576d\u9642\u9547"
    ],
    "wof:name":"Nibei",
    "wof:placetype":"locality"
},
  "geometry": {"coordinates":[109.497,23.6762],"type":"Point"}
}