{
  "type": "Feature",
  "properties": {
    "gn:admin1_code":"12.0",
    "gn:asciiname":"Jiangjiadian",
    "gn:country_code":"CN",
    "gn:dem":41,
    "gn:feature_class":"P",
    "gn:feature_code":"PPL",
    "gn:name":"Jiangjiadian",
    "gn:population":0,
    "gn:timezone":"Asia/Shanghai",
    "iso:country":"CN",
    "name:und_x_variant":[
        "\u59dc\u5bb6\u5e97"
    ],
    "wof:name":"Jiangjiadian",
    "wof:placetype":"locality"
},
  "geometry": {"coordinates":[114.24696000000002,30.91201],"type":"Point"}
}