{
  "type": "Feature",
  "properties": {
    "gn:admin1_code":"30.0",
    "gn:asciiname":"Xiaraocun",
    "gn:country_code":"CN",
    "gn:dem":17,
    "gn:feature_class":"P",
    "gn:feature_code":"PPL",
    "gn:name":"Xiaraocun",
    "gn:population":0,
    "gn:timezone":"Asia/Shanghai",
    "iso:country":"CN",
    "name:zho_x_preferred":[
        "\u4e0b\u9976\u6751"
    ],
    "wof:name":"Xiaraocun",
    "wof:placetype":"locality"
},
  "geometry": {"coordinates":[116.97696999999999,23.73649],"type":"Point"}
}