{
  "type": "Feature",
  "properties": {
    "gn:admin1_code":"33.0",
    "gn:asciiname":"Mazhu",
    "gn:country_code":"CN",
    "gn:dem":408,
    "gn:feature_class":"P",
    "gn:feature_code":"PPL",
    "gn:name":"Mazhu",
    "gn:population":0,
    "gn:timezone":"Asia/Shanghai",
    "iso:country":"CN",
    "name:zho_x_preferred":[
        "\u9a6c\u7afa"
    ],
    "wof:name":"Mazhu",
    "wof:placetype":"locality"
},
  "geometry": {"coordinates":[107.44276000000001,30.39695],"type":"Point"}
}