{
  "type": "Feature",
  "properties": {
    "gn:admin1_code":"8.0",
    "gn:asciiname":"Liming",
    "gn:country_code":"CN",
    "gn:dem":155,
    "gn:feature_class":"P",
    "gn:feature_code":"PPLA4",
    "gn:name":"Liming",
    "gn:population":0,
    "gn:timezone":"Asia/Shanghai",
    "iso:country":"CN",
    "name:und_x_variant":[
        "Liming Xiang"
    ],
    "name:zho_x_preferred":[
        "\u9ece\u660e"
    ],
    "name:zho_x_variant":[
        "\u9ece\u660e\u4e61"
    ],
    "wof:name":"Liming",
    "wof:placetype":"locality"
},
  "geometry": {"coordinates":[125.0067,47.1337],"type":"Point"}
}