{
  "type": "Feature",
  "properties": {
    "gn:admin1_code":"29.0",
    "gn:asciiname":"Xiaoling",
    "gn:country_code":"CN",
    "gn:dem":2044,
    "gn:feature_class":"P",
    "gn:feature_code":"PPL",
    "gn:name":"Xiaoling",
    "gn:population":0,
    "gn:timezone":"Asia/Shanghai",
    "iso:country":"CN",
    "name:swe_x_preferred":[
        "Xiaoling"
    ],
    "name:zho_x_preferred":[
        "\u5c0f\u5cad"
    ],
    "wof:name":"Xiaoling",
    "wof:placetype":"locality"
},
  "geometry": {"coordinates":[99.3009,26.0804],"type":"Point"}
}