{
  "type": "Feature",
  "properties": {
    "gn:admin1_code":"19.0",
    "gn:asciiname":"Jinhaitun",
    "gn:country_code":"CN",
    "gn:dem":23,
    "gn:feature_class":"P",
    "gn:feature_code":"PPL",
    "gn:name":"Jinhaitun",
    "gn:population":0,
    "gn:timezone":"Asia/Shanghai",
    "iso:country":"CN",
    "name:zho_x_preferred":[
        "\u91d1\u6d77\u5c6f"
    ],
    "wof:name":"Jinhaitun",
    "wof:placetype":"locality"
},
  "geometry": {"coordinates":[121.889,39.0306],"type":"Point"}
}