{
  "type": "Feature",
  "properties": {
    "gn:admin1_code":"5.0",
    "gn:asciiname":"Jingquancun",
    "gn:country_code":"CN",
    "gn:dem":189,
    "gn:feature_class":"P",
    "gn:feature_code":"PPL",
    "gn:name":"Jingquancun",
    "gn:population":0,
    "gn:timezone":"Asia/Shanghai",
    "iso:country":"CN",
    "name:zho_x_preferred":[
        "\u4e95\u6cc9\u6751"
    ],
    "wof:name":"Jingquancun",
    "wof:placetype":"locality"
},
  "geometry": {"coordinates":[125.74177,45.1173],"type":"Point"}
}