{
  "type": "Feature",
  "properties": {
    "gn:admin1_code":"31",
    "gn:asciiname":"Fubao",
    "gn:country_code":"CN",
    "gn:dem":177,
    "gn:feature_class":"P",
    "gn:feature_code":"PPL",
    "gn:name":"Fubao",
    "gn:population":0,
    "gn:timezone":"Asia/Shanghai",
    "iso:country":"CN",
    "name:hun_x_preferred":[
        "Fu Pao"
    ],
    "name:und_x_variant":[
        "\u798f\u62a5"
    ],
    "wof:name":"Fubao",
    "wof:placetype":"locality"
},
  "geometry": {"coordinates":[109.10691,18.52354],"type":"Point"}
}