{
  "type": "Feature",
  "properties": {
    "gn:admin1_code":"8.0",
    "gn:asciiname":"Chengjiucun",
    "gn:country_code":"CN",
    "gn:dem":209,
    "gn:feature_class":"P",
    "gn:feature_code":"PPL",
    "gn:name":"Chengjiucun",
    "gn:population":0,
    "gn:timezone":"Asia/Shanghai",
    "iso:country":"CN",
    "name:zho_x_preferred":[
        "\u57ce\u4e45\u6751"
    ],
    "wof:name":"Chengjiucun",
    "wof:placetype":"locality"
},
  "geometry": {"coordinates":[126.88384000000001,47.76076],"type":"Point"}
}