{
  "type": "Feature",
  "properties": {
    "gn:admin1_code":"3.0",
    "gn:asciiname":"Gangbei",
    "gn:country_code":"CN",
    "gn:dem":510,
    "gn:feature_class":"P",
    "gn:feature_code":"PPL",
    "gn:name":"Gangbei",
    "gn:population":0,
    "gn:timezone":"Asia/Shanghai",
    "iso:country":"CN",
    "name:und_x_variant":[
        "\u6e2f\u80cc"
    ],
    "wof:name":"Gangbei",
    "wof:placetype":"locality"
},
  "geometry": {"coordinates":[114.55107,29.29111],"type":"Point"}
}