{
  "type": "Feature",
  "properties": {
    "gn:admin1_code":"25",
    "gn:asciiname":"Xiaolichangtun",
    "gn:country_code":"CN",
    "gn:dem":29,
    "gn:feature_class":"P",
    "gn:feature_code":"PPL",
    "gn:name":"Xiaolichangtun",
    "gn:population":0,
    "gn:timezone":"Asia/Shanghai",
    "iso:country":"CN",
    "name:zho_x_preferred":[
        "\u8096\u91cc\u957f\u5c6f"
    ],
    "wof:name":"Xiaolichangtun",
    "wof:placetype":"locality"
},
  "geometry": {"coordinates":[116.036,37.105],"type":"Point"}
}