{
  "type": "Feature",
  "properties": {
    "gn:admin1_code":"18",
    "gn:asciiname":"Jiaoni",
    "gn:country_code":"CN",
    "gn:dem":1666,
    "gn:feature_class":"P",
    "gn:feature_code":"PPL",
    "gn:name":"Jiaoni",
    "gn:population":0,
    "gn:timezone":"Asia/Shanghai",
    "iso:country":"CN",
    "name:zho_x_preferred":[
        "\u811a\u6ce5"
    ],
    "wof:name":"Jiaoni",
    "wof:placetype":"locality"
},
  "geometry": {"coordinates":[104.68600000000001,26.1226],"type":"Point"}
}