{
  "type": "Feature",
  "properties": {
    "gn:admin1_code":"25.0",
    "gn:asciiname":"Dingjiashawu",
    "gn:country_code":"CN",
    "gn:dem":43,
    "gn:feature_class":"P",
    "gn:feature_code":"PPL",
    "gn:name":"Dingjiashawu",
    "gn:population":0,
    "gn:timezone":"Asia/Shanghai",
    "iso:country":"CN",
    "name:zho_x_preferred":[
        "\u4e01\u5bb6\u6c99\u6d6f"
    ],
    "wof:name":"Dingjiashawu",
    "wof:placetype":"locality"
},
  "geometry": {"coordinates":[119.44537,36.24325],"type":"Point"}
}