{
  "type": "Feature",
  "properties": {
    "gn:admin1_code":"6.0",
    "gn:asciiname":"Weila",
    "gn:country_code":"CN",
    "gn:dem":3566,
    "gn:feature_class":"P",
    "gn:feature_code":"PPL",
    "gn:name":"Weila",
    "gn:population":0,
    "gn:timezone":"Asia/Shanghai",
    "iso:country":"CN",
    "name:zho_x_preferred":[
        "\u536b\u62c9"
    ],
    "wof:name":"Weila",
    "wof:placetype":"locality"
},
  "geometry": {"coordinates":[101.26456,34.61744],"type":"Point"}
}