{
  "type": "Feature",
  "properties": {
    "gn:admin1_code":"4.0",
    "gn:asciiname":"Yaozhencun",
    "gn:country_code":"CN",
    "gn:dem":6,
    "gn:feature_class":"P",
    "gn:feature_code":"PPL",
    "gn:name":"Yaozhencun",
    "gn:population":0,
    "gn:timezone":"Asia/Shanghai",
    "iso:country":"CN",
    "name:und_x_variant":[
        "Yaozhen",
        "\u7a91\u9547",
        "Yaozhencun"
    ],
    "name:zho_x_preferred":[
        "\u7a91\u9547\u6751"
    ],
    "wof:name":"Yaozhencun",
    "wof:placetype":"locality"
},
  "geometry": {"coordinates":[120.98968000000001,31.57507],"type":"Point"}
}