{
  "type": "Feature",
  "properties": {
    "gn:admin1_code":"7.0",
    "gn:asciiname":"Xiaojiawan",
    "gn:country_code":"CN",
    "gn:dem":417,
    "gn:feature_class":"P",
    "gn:feature_code":"PPL",
    "gn:name":"Xiaojiawan",
    "gn:population":0,
    "gn:timezone":"Asia/Shanghai",
    "iso:country":"CN",
    "name:und_x_variant":[
        "\u8096\u5bb6\u6e7e"
    ],
    "wof:name":"Xiaojiawan",
    "wof:placetype":"locality"
},
  "geometry": {"coordinates":[116.69437000000001,26.95098],"type":"Point"}
}