{
  "type": "Feature",
  "properties": {
    "gn:admin1_code":"07",
    "gn:asciiname":"Likeng",
    "gn:country_code":"CN",
    "gn:dem":541,
    "gn:feature_class":"P",
    "gn:feature_code":"PPL",
    "gn:name":"Likeng",
    "gn:population":0,
    "gn:timezone":"Asia/Shanghai",
    "iso:country":"CN",
    "name:zho_x_preferred":[
        "\u9ece\u5751"
    ],
    "wof:name":"Likeng",
    "wof:placetype":"locality"
},
  "geometry": {"coordinates":[117.94233,25.86648],"type":"Point"}
}