{
  "type": "Feature",
  "properties": {
    "gn:admin1_code":"3.0",
    "gn:asciiname":"Yingxianshi",
    "gn:country_code":"CN",
    "gn:dem":269,
    "gn:feature_class":"P",
    "gn:feature_code":"PPL",
    "gn:name":"Yingxianshi",
    "gn:population":0,
    "gn:timezone":"Asia/Shanghai",
    "iso:country":"CN",
    "name:und_x_variant":[
        "\u8fce\u4ed9\u5e02"
    ],
    "wof:name":"Yingxianshi",
    "wof:placetype":"locality"
},
  "geometry": {"coordinates":[114.66164000000001,28.74396],"type":"Point"}
}