{
  "type": "Feature",
  "properties": {
    "gn:admin1_code":"32.0",
    "gn:asciiname":"Baifangzi",
    "gn:country_code":"CN",
    "gn:dem":478,
    "gn:feature_class":"P",
    "gn:feature_code":"PPL",
    "gn:name":"Baifangzi",
    "gn:population":0,
    "gn:timezone":"Asia/Shanghai",
    "iso:country":"CN",
    "name:zho_x_preferred":[
        "\u767d\u623f\u5b50"
    ],
    "wof:name":"Baifangzi",
    "wof:placetype":"locality"
},
  "geometry": {"coordinates":[104.20372999999999,28.8996],"type":"Point"}
}