{
  "type": "Feature",
  "properties": {
    "gn:admin1_code":"10",
    "gn:asciiname":"Litaizi",
    "gn:country_code":"CN",
    "gn:dem":697,
    "gn:feature_class":"P",
    "gn:feature_code":"PPL",
    "gn:name":"Litaizi",
    "gn:population":0,
    "gn:timezone":"Asia/Shanghai",
    "iso:country":"CN",
    "name:zho_x_preferred":[
        "\u674e\u53f0\u5b50"
    ],
    "wof:name":"Litaizi",
    "wof:placetype":"locality"
},
  "geometry": {"coordinates":[118.63418,41.1103],"type":"Point"}
}