{
  "type": "Feature",
  "properties": {
    "gn:admin1_code":"20.0",
    "gn:asciiname":"Fugui",
    "gn:country_code":"CN",
    "gn:dem":1485,
    "gn:feature_class":"P",
    "gn:feature_code":"PPL",
    "gn:name":"Fugui",
    "gn:population":0,
    "gn:timezone":"Asia/Shanghai",
    "iso:country":"CN",
    "name:und_x_variant":[
        "\u5bcc\u8d35"
    ],
    "wof:name":"Fugui",
    "wof:placetype":"locality"
},
  "geometry": {"coordinates":[113.18465,41.88729],"type":"Point"}
}