{
  "type": "Feature",
  "properties": {
    "gn:admin1_code":"14.0",
    "gn:asciiname":"Ri'e",
    "gn:country_code":"CN",
    "gn:dem":4412,
    "gn:feature_class":"P",
    "gn:feature_code":"PPL",
    "gn:name":"Ri\u2019e",
    "gn:population":0,
    "gn:timezone":"Asia/Urumqi",
    "iso:country":"CN",
    "name:und_x_variant":[
        "Ri\u2019e"
    ],
    "name:zho_x_preferred":[
        "\u65e5\u9e45"
    ],
    "wof:name":"Ri'e",
    "wof:placetype":"locality"
},
  "geometry": {"coordinates":[97.32782,30.21305],"type":"Point"}
}