{
  "type": "Feature",
  "properties": {
    "gn:admin1_code":"32.0",
    "gn:asciiname":"Tuochuanchang",
    "gn:country_code":"CN",
    "gn:dem":384,
    "gn:feature_class":"P",
    "gn:feature_code":"PPL",
    "gn:name":"Tuochuanchang",
    "gn:population":0,
    "gn:timezone":"Asia/Shanghai",
    "iso:country":"CN",
    "name:zho_x_preferred":[
        "\u62d6\u8239\u573a"
    ],
    "wof:name":"Tuochuanchang",
    "wof:placetype":"locality"
},
  "geometry": {"coordinates":[105.14,28.3679],"type":"Point"}
}