{
  "type": "Feature",
  "properties": {
    "gn:admin1_code":"33.0",
    "gn:asciiname":"Heya",
    "gn:country_code":"CN",
    "gn:dem":878,
    "gn:feature_class":"P",
    "gn:feature_code":"PPL",
    "gn:name":"Heya",
    "gn:population":0,
    "gn:timezone":"Asia/Shanghai",
    "iso:country":"CN",
    "name:zho_x_preferred":[
        "\u4f55\u57ad"
    ],
    "wof:name":"Heya",
    "wof:placetype":"locality"
},
  "geometry": {"coordinates":[109.14708,30.83903],"type":"Point"}
}