{
  "type": "Feature",
  "properties": {
    "gn:admin1_code":"29.0",
    "gn:asciiname":"Jiuchangchong",
    "gn:country_code":"CN",
    "gn:dem":2200,
    "gn:feature_class":"P",
    "gn:feature_code":"PPL",
    "gn:name":"Jiuchangchong",
    "gn:population":0,
    "gn:timezone":"Asia/Shanghai",
    "iso:country":"CN",
    "name:zho_x_preferred":[
        "\u65e7\u957f\u51b2"
    ],
    "wof:name":"Jiuchangchong",
    "wof:placetype":"locality"
},
  "geometry": {"coordinates":[102.128,25.395],"type":"Point"}
}