{
  "type": "Feature",
  "properties": {
    "gn:admin1_code":"21.0",
    "gn:asciiname":"Daijia Naozi",
    "gn:country_code":"CN",
    "gn:dem":1706,
    "gn:feature_class":"P",
    "gn:feature_code":"PPL",
    "gn:name":"Daijia Naozi",
    "gn:population":0,
    "gn:timezone":"Asia/Shanghai",
    "iso:country":"CN",
    "name:zho_x_preferred":[
        "\u6234\u5bb6\u8111\u5b50"
    ],
    "wof:name":"Daijia Naozi",
    "wof:placetype":"locality"
},
  "geometry": {"coordinates":[105.563,36.876],"type":"Point"}
}