{
  "type": "Feature",
  "properties": {
    "gn:admin1_code":"19.0",
    "gn:asciiname":"Sanmen Lijia",
    "gn:country_code":"CN",
    "gn:dem":268,
    "gn:feature_class":"P",
    "gn:feature_code":"PPL",
    "gn:name":"Sanmen Lijia",
    "gn:population":0,
    "gn:timezone":"Asia/Shanghai",
    "iso:country":"CN",
    "name:zho_x_preferred":[
        "\u4e09\u95e8\u674e\u5bb6"
    ],
    "wof:name":"Sanmen Lijia",
    "wof:placetype":"locality"
},
  "geometry": {"coordinates":[124.35599999999999,42.8811],"type":"Point"}
}