{
  "type": "Feature",
  "properties": {
    "gn:admin1_code":"8.0",
    "gn:asciiname":"Jifacun",
    "gn:country_code":"CN",
    "gn:dem":212,
    "gn:feature_class":"P",
    "gn:feature_code":"PPL",
    "gn:name":"Jifacun",
    "gn:population":0,
    "gn:timezone":"Asia/Shanghai",
    "iso:country":"CN",
    "name:zho_x_preferred":[
        "\u96c6\u53d1\u6751"
    ],
    "wof:name":"Jifacun",
    "wof:placetype":"locality"
},
  "geometry": {"coordinates":[125.66595,47.26186],"type":"Point"}
}