{
  "type": "Feature",
  "properties": {
    "gn:admin1_code":"3",
    "gn:asciiname":"Bazili",
    "gn:country_code":"CN",
    "gn:dem":145,
    "gn:feature_class":"P",
    "gn:feature_code":"PPL",
    "gn:name":"Bazili",
    "gn:population":0,
    "gn:timezone":"Asia/Shanghai",
    "iso:country":"CN",
    "name:zho_x_preferred":[
        "\u575d\u5b5c\u91cc"
    ],
    "wof:name":"Bazili",
    "wof:placetype":"locality"
},
  "geometry": {"coordinates":[114.636,25.8068],"type":"Point"}
}