{
  "type": "Feature",
  "properties": {
    "gn:admin1_code":"22.0",
    "gn:asciiname":"Beisun Gezhuangcun",
    "gn:country_code":"CN",
    "gn:dem":40,
    "gn:feature_class":"P",
    "gn:feature_code":"PPL",
    "gn:name":"Beisun Gezhuangcun",
    "gn:population":0,
    "gn:timezone":"Asia/Shanghai",
    "iso:country":"CN",
    "name:zho_x_preferred":[
        "\u5317\u5b59\u5404\u5e84\u6751"
    ],
    "wof:name":"Beisun Gezhuangcun",
    "wof:placetype":"locality"
},
  "geometry": {"coordinates":[116.65223,40.24867],"type":"Point"}
}