{
  "type": "Feature",
  "properties": {
    "gn:admin1_code":"19.0",
    "gn:asciiname":"Guihualing",
    "gn:country_code":"CN",
    "gn:dem":124,
    "gn:feature_class":"P",
    "gn:feature_code":"PPL",
    "gn:name":"Guihualing",
    "gn:population":0,
    "gn:timezone":"Asia/Shanghai",
    "iso:country":"CN",
    "name:und_x_variant":[
        "\u6842\u82b1\u5cad"
    ],
    "wof:name":"Guihualing",
    "wof:placetype":"locality"
},
  "geometry": {"coordinates":[123.34368000000001,40.17914],"type":"Point"}
}