{
  "type": "Feature",
  "properties": {
    "gn:admin1_code":"29.0",
    "gn:asciiname":"Chela Bacun",
    "gn:country_code":"CN",
    "gn:dem":2392,
    "gn:feature_class":"P",
    "gn:feature_code":"PPL",
    "gn:name":"Chela Bacun",
    "gn:population":0,
    "gn:timezone":"Asia/Shanghai",
    "iso:country":"CN",
    "name:zho_x_preferred":[
        "\u8f66\u62c9\u516b\u6751"
    ],
    "wof:name":"Chela Bacun",
    "wof:placetype":"locality"
},
  "geometry": {"coordinates":[100.101,27.5826],"type":"Point"}
}