{
  "type": "Feature",
  "properties": {
    "gn:admin1_code":"29.0",
    "gn:asciiname":"Yanfangtou",
    "gn:country_code":"CN",
    "gn:dem":2034,
    "gn:feature_class":"P",
    "gn:feature_code":"PPL",
    "gn:name":"Yanfangtou",
    "gn:population":0,
    "gn:timezone":"Asia/Shanghai",
    "iso:country":"CN",
    "name:zho_x_preferred":[
        "\u5ca9\u623f\u5934"
    ],
    "wof:name":"Yanfangtou",
    "wof:placetype":"locality"
},
  "geometry": {"coordinates":[99.16679999999999,24.51],"type":"Point"}
}