{
  "type": "Feature",
  "properties": {
    "gn:admin1_code":"19.0",
    "gn:asciiname":"Bayuefu",
    "gn:country_code":"CN",
    "gn:dem":158,
    "gn:feature_class":"P",
    "gn:feature_code":"PPL",
    "gn:name":"Bayuefu",
    "gn:population":0,
    "gn:timezone":"Asia/Shanghai",
    "iso:country":"CN",
    "name:und_x_variant":[
        "\u516b\u6708\u5e9c"
    ],
    "name:zho_x_preferred":[
        "\u516b\u6708\u5e9c"
    ],
    "wof:name":"Bayuefu",
    "wof:placetype":"locality"
},
  "geometry": {"coordinates":[122.07619,42.30641],"type":"Point"}
}