{
  "type": "Feature",
  "properties": {
    "gn:admin1_code":"25",
    "gn:asciiname":"Yingjiatuan",
    "gn:country_code":"CN",
    "gn:dem":99,
    "gn:feature_class":"P",
    "gn:feature_code":"PPL",
    "gn:name":"Yingjiatuan",
    "gn:population":0,
    "gn:timezone":"Asia/Shanghai",
    "iso:country":"CN",
    "name:zho_x_preferred":[
        "\u82f1\u5bb6\u7583"
    ],
    "wof:name":"Yingjiatuan",
    "wof:placetype":"locality"
},
  "geometry": {"coordinates":[118.08799999999999,35.1828],"type":"Point"}
}