{
  "type": "Feature",
  "properties": {
    "gn:admin1_code":"3.0",
    "gn:asciiname":"Liuzhou",
    "gn:country_code":"CN",
    "gn:dem":15,
    "gn:feature_class":"P",
    "gn:feature_code":"PPL",
    "gn:name":"Liuzhou",
    "gn:population":0,
    "gn:timezone":"Asia/Shanghai",
    "iso:country":"CN",
    "name:afr_x_preferred":[
        "Liuzhou"
    ],
    "name:ara_x_preferred":[
        "\u0644\u064a\u0648\u0634\u0648"
    ],
    "name:ast_x_preferred":[
        "Liuzhou"
    ],
    "name:bel_x_preferred":[
        "\u041b\u044e\u0447\u0436\u043e\u0443"
    ],
    "name:bre_x_preferred":[
        "Liuzhou"
    ],
    "name:bul_x_preferred":[
        "\u041b\u0438\u0443\u0434\u0436\u043e\u0443"
    ],
    "name:cdo_x_preferred":[
        "Li\u016b-ci\u016d"
    ],
    "name:ceb_x_preferred":[
        "Liuzhou Shi"
    ],
    "name:ces_x_preferred":[
        "Liou-\u010dou"
    ],
    "name:dan_x_preferred":[
        "Liuzhou"
    ],
    "name:deu_x_preferred":[
        "Liuzhou"
    ],
    "name:epo_x_preferred":[
        "Lju\u011dou"
    ],
    "name:eus_x_preferred":[
        "Liuzhou"
    ],
    "name:fas_x_preferred":[
        "\u0644\u06cc\u0648\u0698\u0648"
    ],
    "name:fin_x_preferred":[
        "Liuzhou"
    ],
    "name:fra_x_preferred":[
        "Liuzhou"
    ],
    "name:hak_x_preferred":[
        "Li\u00fa-ch\u00fb-s\u1e73"
    ],
    "name:ind_x_preferred":[
        "Liuzhou"
    ],
    "name:ita_x_preferred":[
        "Liuzhou"
    ],
    "name:jpn_x_preferred":[
        "\u67f3\u5dde\u5e02"
    ],
    "name:kaz_x_preferred":[
        "\u041b\u044e\u0447\u0436\u043e\u0443"
    ],
    "name:kik_x_preferred":[
        "Liuzhou"
    ],
    "name:kor_x_preferred":[
        "\ub958\uc800\uc6b0\uc2dc"
    ],
    "name:nld_x_preferred":[
        "Liuzhou"
    ],
    "name:nno_x_preferred":[
        "Liuzhou"
    ],
    "name:nor_x_preferred":[
        "Liuzhou"
    ],
    "name:oci_x_preferred":[
        "Liuzhou"
    ],
    "name:pnb_x_preferred":[
        "\u0644\u06cc\u0648\u0698\u0648\u0624"
    ],
    "name:pol_x_preferred":[
        "Liuzhou"
    ],
    "name:por_x_preferred":[
        "Liuzhou"
    ],
    "name:rus_x_preferred":[
        "\u041b\u044e\u0447\u0436\u043e\u0443"
    ],
    "name:spa_x_preferred":[
        "Liuzhou"
    ],
    "name:srp_x_preferred":[
        "\u0409\u0443\u045f\u043e\u0443"
    ],
    "name:swe_x_preferred":[
        "Liuzhou"
    ],
    "name:tur_x_preferred":[
        "Liuzhou"
    ],
    "name:uig_x_preferred":[
        "Lyuju shehiri"
    ],
    "name:ukr_x_preferred":[
        "\u041b\u044e\u0447\u0436\u043e\u0443"
    ],
    "name:und_x_variant":[
        "\u67f3\u6d32"
    ],
    "name:urd_x_preferred":[
        "\u0644\u06cc\u0648\u0698\u0648"
    ],
    "name:vie_x_preferred":[
        "Li\u1ec5u Ch\u00e2u"
    ],
    "name:war_x_preferred":[
        "Liuzhou"
    ],
    "name:zha_x_preferred":[
        "Liujcouh"
    ],
    "name:zho_x_preferred":[
        "\u67f3\u5dde\u5e02"
    ],
    "wof:name":"Liuzhou",
    "wof:placetype":"locality"
},
  "geometry": {"coordinates":[116.19280999999999,29.79419],"type":"Point"}
}