{
  "type": "Feature",
  "properties": {
    "gn:admin1_code":"3.0",
    "gn:asciiname":"Liuzhou",
    "gn:country_code":"CN",
    "gn:dem":15,
    "gn:feature_class":"P",
    "gn:feature_code":"PPL",
    "gn:name":"Liuzhou",
    "gn:population":0,
    "gn:timezone":"Asia/Shanghai",
    "iso:country":"CN",
    "name:und_x_variant":[
        "\u67f3\u6d32"
    ],
    "wof:name":"Liuzhou",
    "wof:placetype":"locality"
},
  "geometry": {"coordinates":[116.19280999999999,29.79419],"type":"Point"}
}