{
  "type": "Feature",
  "properties": {
    "gn:admin1_code":"4.0",
    "gn:asciiname":"Chong'ansi",
    "gn:country_code":"CN",
    "gn:dem":6,
    "gn:feature_class":"P",
    "gn:feature_code":"PPLA3",
    "gn:name":"Chong\u2019ansi",
    "gn:population":0,
    "gn:timezone":"Asia/Shanghai",
    "iso:country":"CN",
    "name:und_x_variant":[
        "Chong\u2019ansi",
        "Chong\u2019ansi Jiedao",
        "Chong\u2019an Qu"
    ],
    "name:zho_x_preferred":[
        "\u5d07\u5b89\u5bfa"
    ],
    "name:zho_x_variant":[
        "\u5d07\u5b89\u5bfa\u8857\u9053",
        "\u5d07\u5b89\u533a"
    ],
    "wof:name":"Chong'ansi",
    "wof:placetype":"locality"
},
  "geometry": {"coordinates":[120.29518,31.57987],"type":"Point"}
}