{
  "type": "Feature",
  "properties": {
    "gn:admin1_code":"9.0",
    "gn:asciiname":"Sanzhang",
    "gn:country_code":"CN",
    "gn:dem":144,
    "gn:feature_class":"P",
    "gn:feature_code":"PPL",
    "gn:name":"Sanzhang",
    "gn:population":0,
    "gn:timezone":"Asia/Shanghai",
    "iso:country":"CN",
    "name:und_x_variant":[
        "\u4e09\u5f20",
        "Sanzhang"
    ],
    "wof:name":"Sanzhang",
    "wof:placetype":"locality"
},
  "geometry": {"coordinates":[112.8006,33.14431],"type":"Point"}
}