{
  "type": "Feature",
  "properties": {
    "gn:admin1_code":"3.0",
    "gn:asciiname":"Houshan Leijia",
    "gn:country_code":"CN",
    "gn:dem":20,
    "gn:feature_class":"P",
    "gn:feature_code":"PPL",
    "gn:name":"Houshan Leijia",
    "gn:population":0,
    "gn:timezone":"Asia/Shanghai",
    "iso:country":"CN",
    "name:und_x_variant":[
        "\u540e\u5c71\u96f7\u5bb6"
    ],
    "wof:name":"Houshan Leijia",
    "wof:placetype":"locality"
},
  "geometry": {"coordinates":[116.8686,29.04944],"type":"Point"}
}