{
  "type": "Feature",
  "properties": {
    "gn:admin1_code":"9.0",
    "gn:asciiname":"Nanzhangzhuang",
    "gn:country_code":"CN",
    "gn:dem":215,
    "gn:feature_class":"P",
    "gn:feature_code":"PPL",
    "gn:name":"Nanzhangzhuang",
    "gn:population":0,
    "gn:timezone":"Asia/Shanghai",
    "iso:country":"CN",
    "name:zho_x_preferred":[
        "\u5357\u5f20\u5e84"
    ],
    "wof:name":"Nanzhangzhuang",
    "wof:placetype":"locality"
},
  "geometry": {"coordinates":[112.90457000000001,34.02719],"type":"Point"}
}