{
  "type": "Feature",
  "properties": {
    "gn:admin1_code":"19.0",
    "gn:asciiname":"Dabangniu",
    "gn:country_code":"CN",
    "gn:dem":16,
    "gn:feature_class":"P",
    "gn:feature_code":"PPL",
    "gn:name":"Dabangniu",
    "gn:population":0,
    "gn:timezone":"Asia/Shanghai",
    "iso:country":"CN",
    "name:und_x_variant":[
        "\u5927\u90a6\u725b"
    ],
    "name:zho_x_preferred":[
        "\u5927\u90a6\u725b"
    ],
    "wof:name":"Dabangniu",
    "wof:placetype":"locality"
},
  "geometry": {"coordinates":[122.72960999999999,41.55575],"type":"Point"}
}