{
  "type": "Feature",
  "properties": {
    "gn:admin1_code":"12.0",
    "gn:asciiname":"Tangjiacitang",
    "gn:country_code":"CN",
    "gn:dem":32,
    "gn:feature_class":"P",
    "gn:feature_code":"PPL",
    "gn:name":"Tangjiacitang",
    "gn:population":0,
    "gn:timezone":"Asia/Shanghai",
    "iso:country":"CN",
    "name:zho_x_preferred":[
        "\u6c64\u5bb6\u7960\u5802"
    ],
    "wof:name":"Tangjiacitang",
    "wof:placetype":"locality"
},
  "geometry": {"coordinates":[112.33958,30.14215],"type":"Point"}
}