{
  "type": "Feature",
  "properties": {
    "gn:admin1_code":"29.0",
    "gn:asciiname":"Samachong",
    "gn:country_code":"CN",
    "gn:dem":2581,
    "gn:feature_class":"P",
    "gn:feature_code":"PPL",
    "gn:name":"Samachong",
    "gn:population":0,
    "gn:timezone":"Asia/Shanghai",
    "iso:country":"CN",
    "name:zho_x_preferred":[
        "\u6492\u9a6c\u51b2"
    ],
    "wof:name":"Samachong",
    "wof:placetype":"locality"
},
  "geometry": {"coordinates":[102.33199999999999,26.061],"type":"Point"}
}