{
  "type": "Feature",
  "properties": {
    "gn:admin1_code":"9.0",
    "gn:asciiname":"Zhoukou",
    "gn:country_code":"CN",
    "gn:dem":125,
    "gn:feature_class":"P",
    "gn:feature_code":"PPL",
    "gn:name":"Zhoukou",
    "gn:population":0,
    "gn:timezone":"Asia/Shanghai",
    "iso:country":"CN",
    "name:afr_x_preferred":[
        "Zhoukou"
    ],
    "name:ara_x_preferred":[
        "\u0632\u0647\u0648\u0643\u0648"
    ],
    "name:cdo_x_preferred":[
        "Ci\u016d-k\u0101u"
    ],
    "name:ceb_x_preferred":[
        "Zhoukou"
    ],
    "name:ces_x_preferred":[
        "\u010cou-kchou"
    ],
    "name:dan_x_preferred":[
        "Zhoukou"
    ],
    "name:deu_x_preferred":[
        "Zhoukou"
    ],
    "name:eus_x_preferred":[
        "Zhoukou"
    ],
    "name:fas_x_preferred":[
        "\u0698\u0648\u06a9\u0648"
    ],
    "name:fin_x_preferred":[
        "Zhoukou"
    ],
    "name:fra_x_preferred":[
        "Zhoukou"
    ],
    "name:ita_x_preferred":[
        "Zhoukou"
    ],
    "name:jpn_x_preferred":[
        "\u5468\u53e3\u5e02"
    ],
    "name:kik_x_preferred":[
        "Zhoukou"
    ],
    "name:kor_x_preferred":[
        "\uc800\uc6b0\ucee4\uc6b0\uc2dc"
    ],
    "name:mlg_x_preferred":[
        "Zhoukou"
    ],
    "name:nld_x_preferred":[
        "Zhoukou"
    ],
    "name:nno_x_preferred":[
        "Zhoukou"
    ],
    "name:nor_x_preferred":[
        "Zhoukou"
    ],
    "name:pam_x_preferred":[
        "Zhoukou"
    ],
    "name:pol_x_preferred":[
        "Zhoukou"
    ],
    "name:rus_x_preferred":[
        "\u0427\u0436\u043e\u0443\u043a\u043e\u0443"
    ],
    "name:spa_x_preferred":[
        "Zhoukou"
    ],
    "name:srp_x_preferred":[
        "\u040f\u043e\u0443\u043a\u043e\u0443"
    ],
    "name:swe_x_preferred":[
        "Zhoukou"
    ],
    "name:tur_x_preferred":[
        "Zhoukou"
    ],
    "name:uig_x_preferred":[
        "Juko shehiri"
    ],
    "name:urd_x_preferred":[
        "\u0698\u0648\u0648\u06a9\u0648\u0648"
    ],
    "name:vie_x_preferred":[
        "Chu Kh\u1ea9u"
    ],
    "name:war_x_preferred":[
        "Zhoukou"
    ],
    "name:zho_x_preferred":[
        "\u5468\u53e3"
    ],
    "name:zho_x_variant":[
        "\u5468\u53e3\u5e02"
    ],
    "wof:name":"Zhoukou",
    "wof:placetype":"locality"
},
  "geometry": {"coordinates":[112.57934,34.84555],"type":"Point"}
}