{
  "type": "Feature",
  "properties": {
    "gn:admin1_code":"22.0",
    "gn:asciiname":"Junzhuangcun",
    "gn:country_code":"CN",
    "gn:dem":18,
    "gn:feature_class":"P",
    "gn:feature_code":"PPL",
    "gn:name":"Junzhuangcun",
    "gn:population":0,
    "gn:timezone":"Asia/Shanghai",
    "iso:country":"CN",
    "name:zho_x_preferred":[
        "\u519b\u5e84\u6751"
    ],
    "wof:name":"Junzhuangcun",
    "wof:placetype":"locality"
},
  "geometry": {"coordinates":[116.85303999999999,39.69482],"type":"Point"}
}