{
  "type": "Feature",
  "properties": {
    "gn:admin1_code":"11.0",
    "gn:asciiname":"Xiananmu",
    "gn:country_code":"CN",
    "gn:dem":272,
    "gn:feature_class":"P",
    "gn:feature_code":"PPL",
    "gn:name":"Xiananmu",
    "gn:population":0,
    "gn:timezone":"Asia/Shanghai",
    "iso:country":"CN",
    "name:zho_x_preferred":[
        "\u4e0b\u6960\u6728"
    ],
    "wof:name":"Xiananmu",
    "wof:placetype":"locality"
},
  "geometry": {"coordinates":[109.91267000000001,26.82745],"type":"Point"}
}