{
  "type": "Feature",
  "properties": {
    "gn:admin1_code":"24",
    "gn:asciiname":"Longyu",
    "gn:cc2":"CN",
    "gn:country_code":"CN",
    "gn:dem":1428,
    "gn:feature_class":"P",
    "gn:feature_code":"PPL",
    "gn:name":"Longyu",
    "gn:population":0,
    "gn:timezone":"Asia/Shanghai",
    "iso:country":"CN",
    "name:und_x_variant":[
        "Lung-y\u00fc",
        "Longyu"
    ],
    "wof:name":"Longyu",
    "wof:placetype":"locality"
},
  "geometry": {"coordinates":[113.55,37.45],"type":"Point"}
}