{
  "type": "Feature",
  "properties": {
    "gn:admin1_code":"9.0",
    "gn:asciiname":"Miaojiaxing",
    "gn:country_code":"CN",
    "gn:dem":70,
    "gn:feature_class":"P",
    "gn:feature_code":"PPL",
    "gn:name":"Miaojiaxing",
    "gn:population":0,
    "gn:timezone":"Asia/Shanghai",
    "iso:country":"CN",
    "name:zho_x_preferred":[
        "\u82d7\u5bb6\u884c"
    ],
    "wof:name":"Miaojiaxing",
    "wof:placetype":"locality"
},
  "geometry": {"coordinates":[114.44025999999999,36.1049],"type":"Point"}
}