{
  "type": "Feature",
  "properties": {
    "gn:admin1_code":"3.0",
    "gn:asciiname":"Songqiuyuan",
    "gn:country_code":"CN",
    "gn:dem":531,
    "gn:feature_class":"P",
    "gn:feature_code":"PPL",
    "gn:name":"Songqiuyuan",
    "gn:population":0,
    "gn:timezone":"Asia/Shanghai",
    "iso:country":"CN",
    "name:und_x_variant":[
        "\u677e\u4e18\u6e90"
    ],
    "wof:name":"Songqiuyuan",
    "wof:placetype":"locality"
},
  "geometry": {"coordinates":[115.80885000000001,26.95647],"type":"Point"}
}