{
  "type": "Feature",
  "properties": {
    "gn:admin1_code":"14.0",
    "gn:asciiname":"Song'ebu",
    "gn:country_code":"CN",
    "gn:dem":4645,
    "gn:feature_class":"P",
    "gn:feature_code":"PPL",
    "gn:name":"Song\u2019ebu",
    "gn:population":0,
    "gn:timezone":"Asia/Urumqi",
    "iso:country":"CN",
    "name:und_x_variant":[
        "Song\u2019ebu"
    ],
    "name:zho_x_preferred":[
        "\u677e\u4fc4\u5e03"
    ],
    "wof:name":"Song'ebu",
    "wof:placetype":"locality"
},
  "geometry": {"coordinates":[85.7427,32.4547],"type":"Point"}
}