{
  "type": "Feature",
  "properties": {
    "gn:admin1_code":"7.0",
    "gn:asciiname":"Lishe",
    "gn:country_code":"CN",
    "gn:dem":404,
    "gn:feature_class":"P",
    "gn:feature_code":"PPL",
    "gn:name":"Lishe",
    "gn:population":0,
    "gn:timezone":"Asia/Shanghai",
    "iso:country":"CN",
    "name:und_x_variant":[
        "\u674e\u7572"
    ],
    "name:zho_x_preferred":[
        "\u674e\u7572"
    ],
    "wof:name":"Lishe",
    "wof:placetype":"locality"
},
  "geometry": {"coordinates":[116.75054,26.29745],"type":"Point"}
}