{
  "type": "Feature",
  "properties": {
    "gn:admin1_code":"11.0",
    "gn:asciiname":"Banmenjing",
    "gn:country_code":"CN",
    "gn:dem":798,
    "gn:feature_class":"P",
    "gn:feature_code":"PPL",
    "gn:name":"Banmenjing",
    "gn:population":0,
    "gn:timezone":"Asia/Shanghai",
    "iso:country":"CN",
    "name:zho_x_preferred":[
        "\u677f\u95f7\u656c"
    ],
    "wof:name":"Banmenjing",
    "wof:placetype":"locality"
},
  "geometry": {"coordinates":[109.49566000000002,28.26122],"type":"Point"}
}