{
  "type": "Feature",
  "properties": {
    "gn:admin1_code":"24",
    "gn:asciiname":"Aojiawan",
    "gn:cc2":"CN",
    "gn:country_code":"CN",
    "gn:dem":1078,
    "gn:feature_class":"P",
    "gn:feature_code":"PPL",
    "gn:name":"Aojiawan",
    "gn:population":0,
    "gn:timezone":"Asia/Shanghai",
    "iso:country":"CN",
    "name:und_x_variant":[
        "Ao-chia-wan",
        "Aojiawan"
    ],
    "wof:name":"Aojiawan",
    "wof:placetype":"locality"
},
  "geometry": {"coordinates":[111.18333,38.46667],"type":"Point"}
}