{
  "type": "Feature",
  "properties": {
    "gn:admin1_code":"32.0",
    "gn:asciiname":"Taojiaba",
    "gn:country_code":"CN",
    "gn:dem":330,
    "gn:feature_class":"P",
    "gn:feature_code":"PPL",
    "gn:name":"Taojiaba",
    "gn:population":0,
    "gn:timezone":"Asia/Shanghai",
    "iso:country":"CN",
    "name:zho_x_preferred":[
        "\u9676\u5bb6\u575d"
    ],
    "wof:name":"Taojiaba",
    "wof:placetype":"locality"
},
  "geometry": {"coordinates":[107.40000000000001,30.8955],"type":"Point"}
}