{
  "type": "Feature",
  "properties": {
    "gn:admin1_code":"21.0",
    "gn:asciiname":"Wufangcha",
    "gn:country_code":"CN",
    "gn:dem":1943,
    "gn:feature_class":"P",
    "gn:feature_code":"PPL",
    "gn:name":"Wufangcha",
    "gn:population":0,
    "gn:timezone":"Asia/Shanghai",
    "iso:country":"CN",
    "name:zho_x_preferred":[
        "\u4e94\u65b9\u5c94"
    ],
    "wof:name":"Wufangcha",
    "wof:placetype":"locality"
},
  "geometry": {"coordinates":[105.35856,35.93768],"type":"Point"}
}