{
  "type": "Feature",
  "properties": {
    "gn:admin1_code":"15.0",
    "gn:asciiname":"Zhumo",
    "gn:country_code":"CN",
    "gn:dem":1759,
    "gn:feature_class":"P",
    "gn:feature_code":"PPL",
    "gn:name":"Zhumo",
    "gn:population":0,
    "gn:timezone":"Asia/Shanghai",
    "iso:country":"CN",
    "name:zho_x_preferred":[
        "\u6731\u78e8"
    ],
    "wof:name":"Zhumo",
    "wof:placetype":"locality"
},
  "geometry": {"coordinates":[105.23999999999999,34.4112],"type":"Point"}
}