{
  "type": "Feature",
  "properties": {
    "gn:admin1_code":"3",
    "gn:asciiname":"Yinzichong",
    "gn:country_code":"CN",
    "gn:dem":581,
    "gn:feature_class":"P",
    "gn:feature_code":"PPL",
    "gn:name":"Yinzichong",
    "gn:population":0,
    "gn:timezone":"Asia/Shanghai",
    "iso:country":"CN",
    "name:zho_x_preferred":[
        "\u94f6\u5b50\u51b2"
    ],
    "wof:name":"Yinzichong",
    "wof:placetype":"locality"
},
  "geometry": {"coordinates":[113.995,26.6226],"type":"Point"}
}