{
  "type": "Feature",
  "properties": {
    "gn:admin1_code":"14.0",
    "gn:asciiname":"Sheji",
    "gn:country_code":"CN",
    "gn:dem":3847,
    "gn:feature_class":"P",
    "gn:feature_code":"PPL",
    "gn:name":"Sheji",
    "gn:population":0,
    "gn:timezone":"Asia/Urumqi",
    "iso:country":"CN",
    "name:zho_x_preferred":[
        "\u820d\u7ed9"
    ],
    "wof:name":"Sheji",
    "wof:placetype":"locality"
},
  "geometry": {"coordinates":[98.75944,29.32157],"type":"Point"}
}