{
  "type": "Feature",
  "properties": {
    "gn:admin1_code":"24.0",
    "gn:asciiname":"Houyuling",
    "gn:country_code":"CN",
    "gn:dem":1385,
    "gn:feature_class":"P",
    "gn:feature_code":"PPL",
    "gn:name":"Houyuling",
    "gn:population":0,
    "gn:timezone":"Asia/Shanghai",
    "iso:country":"CN",
    "name:zho_x_preferred":[
        "\u540e\u6986\u5cad"
    ],
    "wof:name":"Houyuling",
    "wof:placetype":"locality"
},
  "geometry": {"coordinates":[112.4757,39.70419],"type":"Point"}
}