{
  "type": "Feature",
  "properties": {
    "gn:admin1_code":"5.0",
    "gn:asciiname":"Changqingcun",
    "gn:country_code":"CN",
    "gn:dem":203,
    "gn:feature_class":"P",
    "gn:feature_code":"PPL",
    "gn:name":"Changqingcun",
    "gn:population":0,
    "gn:timezone":"Asia/Shanghai",
    "iso:country":"CN",
    "name:zho_x_preferred":[
        "\u957f\u9752\u6751"
    ],
    "wof:name":"Changqingcun",
    "wof:placetype":"locality"
},
  "geometry": {"coordinates":[126.54756999999999,44.66962],"type":"Point"}
}