{
  "type": "Feature",
  "properties": {
    "gn:admin1_code":"1.0",
    "gn:asciiname":"Fanjiachong",
    "gn:country_code":"CN",
    "gn:dem":44,
    "gn:feature_class":"P",
    "gn:feature_code":"PPL",
    "gn:name":"Fanjiachong",
    "gn:population":0,
    "gn:timezone":"Asia/Shanghai",
    "iso:country":"CN",
    "name:zho_x_preferred":[
        "\u8303\u5bb6\u51b2"
    ],
    "wof:name":"Fanjiachong",
    "wof:placetype":"locality"
},
  "geometry": {"coordinates":[118.26815999999999,31.06107],"type":"Point"}
}