{
  "type": "Feature",
  "properties": {
    "gn:admin1_code":"9.0",
    "gn:asciiname":"Beichuan",
    "gn:country_code":"CN",
    "gn:dem":752,
    "gn:feature_class":"P",
    "gn:feature_code":"PPL",
    "gn:name":"Beichuan",
    "gn:population":0,
    "gn:timezone":"Asia/Shanghai",
    "iso:country":"CN",
    "name:zho_x_preferred":[
        "\u5317\u5ddd"
    ],
    "wof:name":"Beichuan",
    "wof:placetype":"locality"
},
  "geometry": {"coordinates":[111.51784000000001,34.02502],"type":"Point"}
}