{
  "type": "Feature",
  "properties": {
    "gn:admin1_code":"2.0",
    "gn:asciiname":"Liheyuan",
    "gn:country_code":"CN",
    "gn:dem":218,
    "gn:feature_class":"P",
    "gn:feature_code":"PPL",
    "gn:name":"Liheyuan",
    "gn:population":0,
    "gn:timezone":"Asia/Shanghai",
    "iso:country":"CN",
    "name:und_x_variant":[
        "\u91cc\u4f55\u6e90",
        "Liheyuan"
    ],
    "wof:name":"Liheyuan",
    "wof:placetype":"locality"
},
  "geometry": {"coordinates":[119.4752,29.62752],"type":"Point"}
}