{
  "type": "Feature",
  "properties": {
    "gn:admin1_code":"26",
    "gn:asciiname":"Yanhe",
    "gn:country_code":"CN",
    "gn:dem":578,
    "gn:feature_class":"P",
    "gn:feature_code":"PPL",
    "gn:name":"Yanhe",
    "gn:population":0,
    "gn:timezone":"Asia/Shanghai",
    "iso:country":"CN",
    "name:ceb_x_preferred":[
        "Yanhe"
    ],
    "name:deu_x_preferred":[
        "Yanhe"
    ],
    "name:fra_x_preferred":[
        "Yanhe"
    ],
    "name:zho_x_preferred":[
        "\u5ef6\u6cb3"
    ],
    "wof:name":"Yanhe",
    "wof:placetype":"locality"
},
  "geometry": {"coordinates":[108.38388999999999,34.51778],"type":"Point"}
}