{
  "type": "Feature",
  "properties": {
    "gn:admin1_code":"15.0",
    "gn:asciiname":"Mang'erwan",
    "gn:country_code":"CN",
    "gn:dem":1975,
    "gn:feature_class":"P",
    "gn:feature_code":"PPL",
    "gn:name":"Mang\u2019erwan",
    "gn:population":0,
    "gn:timezone":"Asia/Shanghai",
    "iso:country":"CN",
    "name:und_x_variant":[
        "Mang\u2019erwan"
    ],
    "name:zho_x_preferred":[
        "\u87d2\u513f\u6e7e"
    ],
    "wof:name":"Mang'erwan",
    "wof:placetype":"locality"
},
  "geometry": {"coordinates":[104.956,35.2209],"type":"Point"}
}