{
  "type": "Feature",
  "properties": {
    "gn:admin1_code":"2.0",
    "gn:asciiname":"Xiachen",
    "gn:country_code":"CN",
    "gn:dem":141,
    "gn:feature_class":"P",
    "gn:feature_code":"PPL",
    "gn:name":"Xiachen",
    "gn:population":0,
    "gn:timezone":"Asia/Shanghai",
    "iso:country":"CN",
    "name:zho_x_preferred":[
        "\u4e0b\u9648"
    ],
    "wof:name":"Xiachen",
    "wof:placetype":"locality"
},
  "geometry": {"coordinates":[120.85167,29.19762],"type":"Point"}
}