{
  "type": "Feature",
  "properties": {
    "gn:admin1_code":"2.0",
    "gn:asciiname":"Maozhuping",
    "gn:country_code":"CN",
    "gn:dem":625,
    "gn:feature_class":"P",
    "gn:feature_code":"PPL",
    "gn:name":"Maozhuping",
    "gn:population":0,
    "gn:timezone":"Asia/Shanghai",
    "iso:country":"CN",
    "name:und_x_variant":[
        "\u6bdb\u7af9\u576a"
    ],
    "wof:name":"Maozhuping",
    "wof:placetype":"locality"
},
  "geometry": {"coordinates":[119.29624,30.09665],"type":"Point"}
}