{
  "type": "Feature",
  "properties": {
    "gn:admin1_code":"4.0",
    "gn:asciiname":"Langanqiao",
    "gn:country_code":"CN",
    "gn:dem":4,
    "gn:feature_class":"P",
    "gn:feature_code":"PPL",
    "gn:name":"Langanqiao",
    "gn:population":0,
    "gn:timezone":"Asia/Shanghai",
    "iso:country":"CN",
    "name:zho_x_preferred":[
        "\u680f\u6746\u6865"
    ],
    "wof:name":"Langanqiao",
    "wof:placetype":"locality"
},
  "geometry": {"coordinates":[119.74794,32.23324],"type":"Point"}
}