{
  "type": "Feature",
  "properties": {
    "gn:admin1_code":"4.0",
    "gn:asciiname":"Kongjiaxu",
    "gn:country_code":"CN",
    "gn:dem":3,
    "gn:feature_class":"P",
    "gn:feature_code":"PPL",
    "gn:name":"Kongjiaxu",
    "gn:population":0,
    "gn:timezone":"Asia/Shanghai",
    "iso:country":"CN",
    "name:zho_x_preferred":[
        "\u5b54\u5bb6\u5729"
    ],
    "wof:name":"Kongjiaxu",
    "wof:placetype":"locality"
},
  "geometry": {"coordinates":[119.74666000000001,32.28814000000001],"type":"Point"}
}