{
  "type": "Feature",
  "properties": {
    "gn:admin1_code":"16.0",
    "gn:asciiname":"Wulong",
    "gn:country_code":"CN",
    "gn:dem":190,
    "gn:feature_class":"P",
    "gn:feature_code":"PPL",
    "gn:name":"Wulong",
    "gn:population":0,
    "gn:timezone":"Asia/Shanghai",
    "iso:country":"CN",
    "name:zho_x_preferred":[
        "\u821e\u9f99"
    ],
    "wof:name":"Wulong",
    "wof:placetype":"locality"
},
  "geometry": {"coordinates":[111.348,24.389],"type":"Point"}
}