{
  "type": "Feature",
  "properties": {
    "gn:admin1_code":"1.0",
    "gn:asciiname":"Saihucun",
    "gn:country_code":"CN",
    "gn:dem":15,
    "gn:feature_class":"P",
    "gn:feature_code":"PPL",
    "gn:name":"Saihucun",
    "gn:population":0,
    "gn:timezone":"Asia/Shanghai",
    "iso:country":"CN",
    "name:zho_x_preferred":[
        "\u8d5b\u6e56\u6751"
    ],
    "wof:name":"Saihucun",
    "wof:placetype":"locality"
},
  "geometry": {"coordinates":[117.05137000000001,30.73406],"type":"Point"}
}