{
  "type": "Feature",
  "properties": {
    "gn:admin1_code":"26.0",
    "gn:asciiname":"Mengjia Laozhuang",
    "gn:country_code":"CN",
    "gn:dem":1020,
    "gn:feature_class":"P",
    "gn:feature_code":"PPL",
    "gn:name":"Mengjia Laozhuang",
    "gn:population":0,
    "gn:timezone":"Asia/Shanghai",
    "iso:country":"CN",
    "name:zho_x_preferred":[
        "\u5b5f\u5bb6\u8001\u5e84"
    ],
    "wof:name":"Mengjia Laozhuang",
    "wof:placetype":"locality"
},
  "geometry": {"coordinates":[110.71966999999999,33.76137],"type":"Point"}
}