{
  "type": "Feature",
  "properties": {
    "gn:admin1_code":"29.0",
    "gn:asciiname":"Likuai",
    "gn:country_code":"CN",
    "gn:dem":2454,
    "gn:feature_class":"P",
    "gn:feature_code":"PPL",
    "gn:name":"Likuai",
    "gn:population":0,
    "gn:timezone":"Asia/Shanghai",
    "iso:country":"CN",
    "name:und_x_variant":[
        "\u91cc\u5757"
    ],
    "wof:name":"Likuai",
    "wof:placetype":"locality"
},
  "geometry": {"coordinates":[102.79095,25.86942],"type":"Point"}
}