{
  "type": "Feature",
  "properties": {
    "gn:admin1_code":"11.0",
    "gn:asciiname":"Wang'erqiao",
    "gn:country_code":"CN",
    "gn:dem":292,
    "gn:feature_class":"P",
    "gn:feature_code":"PPL",
    "gn:name":"Wang\u2019erqiao",
    "gn:population":0,
    "gn:timezone":"Asia/Shanghai",
    "iso:country":"CN",
    "name:und_x_variant":[
        "Wang\u2019erqiao"
    ],
    "name:zho_x_preferred":[
        "\u738b\u513f\u6865"
    ],
    "wof:name":"Wang'erqiao",
    "wof:placetype":"locality"
},
  "geometry": {"coordinates":[109.48826,28.57389],"type":"Point"}
}