{
  "type": "Feature",
  "properties": {
    "gn:admin1_code":"02",
    "gn:asciiname":"Dongxicun",
    "gn:country_code":"CN",
    "gn:dem":15,
    "gn:feature_class":"P",
    "gn:feature_code":"PPL",
    "gn:name":"Dongxicun",
    "gn:population":0,
    "gn:timezone":"Asia/Shanghai",
    "iso:country":"CN",
    "name:und_x_variant":[
        "Tung-hsi-shih",
        "Dongxi",
        "Dongxicun"
    ],
    "name:zho_x_preferred":[
        "\u4e1c\u6eaa"
    ],
    "name:zho_x_variant":[
        "\u4e1c\u6eaa\u6751"
    ],
    "wof:name":"Dongxicun",
    "wof:placetype":"locality"
},
  "geometry": {"coordinates":[121.85119,29.3435],"type":"Point"}
}