{
  "type": "Feature",
  "properties": {
    "gn:admin1_code":"15.0",
    "gn:asciiname":"Chaijiazhuang",
    "gn:country_code":"CN",
    "gn:dem":1922,
    "gn:feature_class":"P",
    "gn:feature_code":"PPL",
    "gn:name":"Chaijiazhuang",
    "gn:population":0,
    "gn:timezone":"Asia/Shanghai",
    "iso:country":"CN",
    "name:zho_x_preferred":[
        "\u67f4\u5bb6\u5e84"
    ],
    "wof:name":"Chaijiazhuang",
    "wof:placetype":"locality"
},
  "geometry": {"coordinates":[102.91,37.5613],"type":"Point"}
}