{
  "type": "Feature",
  "properties": {
    "gn:admin1_code":"2.0",
    "gn:asciiname":"Huangmaoling",
    "gn:country_code":"CN",
    "gn:dem":444,
    "gn:feature_class":"P",
    "gn:feature_code":"PPL",
    "gn:name":"Huangmaoling",
    "gn:population":0,
    "gn:timezone":"Asia/Shanghai",
    "iso:country":"CN",
    "name:zho_x_preferred":[
        "\u9ec4\u6bdb\u5cad"
    ],
    "wof:name":"Huangmaoling",
    "wof:placetype":"locality"
},
  "geometry": {"coordinates":[118.35816,29.48475],"type":"Point"}
}