{
  "type": "Feature",
  "properties": {
    "gn:admin1_code":"26.0",
    "gn:asciiname":"Niangoudazhuang",
    "gn:country_code":"CN",
    "gn:dem":1298,
    "gn:feature_class":"P",
    "gn:feature_code":"PPL",
    "gn:name":"Niangoudazhuang",
    "gn:population":0,
    "gn:timezone":"Asia/Shanghai",
    "iso:country":"CN",
    "name:und_x_variant":[
        "\u78be\u6c9f\u5927\u5e84"
    ],
    "wof:name":"Niangoudazhuang",
    "wof:placetype":"locality"
},
  "geometry": {"coordinates":[105.9023,33.45453],"type":"Point"}
}