{
  "type": "Feature",
  "properties": {
    "gn:admin1_code":"29.0",
    "gn:asciiname":"Tuogu",
    "gn:country_code":"CN",
    "gn:dem":2462,
    "gn:feature_class":"P",
    "gn:feature_code":"PPL",
    "gn:name":"Tuogu",
    "gn:population":0,
    "gn:timezone":"Asia/Shanghai",
    "iso:country":"CN",
    "name:und_x_variant":[
        "\u62d6\u59d1"
    ],
    "wof:name":"Tuogu",
    "wof:placetype":"locality"
},
  "geometry": {"coordinates":[103.294,26.5083],"type":"Point"}
}