{
  "type": "Feature",
  "properties": {
    "gn:admin1_code":"32.0",
    "gn:asciiname":"Poji",
    "gn:country_code":"CN",
    "gn:dem":2927,
    "gn:feature_class":"P",
    "gn:feature_code":"PPL",
    "gn:name":"Poji",
    "gn:population":0,
    "gn:timezone":"Asia/Shanghai",
    "iso:country":"CN",
    "name:zho_x_preferred":[
        "\u5761\u5409"
    ],
    "wof:name":"Poji",
    "wof:placetype":"locality"
},
  "geometry": {"coordinates":[102.878,27.7168],"type":"Point"}
}