{
  "type": "Feature",
  "properties": {
    "gn:admin1_code":"5.0",
    "gn:asciiname":"Toudaogou",
    "gn:country_code":"CN",
    "gn:dem":315,
    "gn:feature_class":"P",
    "gn:feature_code":"PPL",
    "gn:name":"Toudaogou",
    "gn:population":0,
    "gn:timezone":"Asia/Shanghai",
    "iso:country":"CN",
    "name:zho_x_preferred":[
        "\u5934\u9053\u6c9f"
    ],
    "wof:name":"Toudaogou",
    "wof:placetype":"locality"
},
  "geometry": {"coordinates":[126.39511,43.50709000000001],"type":"Point"}
}