{
  "type": "Feature",
  "properties": {
    "gn:admin1_code":"30",
    "gn:asciiname":"Baitang",
    "gn:country_code":"CN",
    "gn:dem":33,
    "gn:feature_class":"P",
    "gn:feature_code":"PPLA4",
    "gn:name":"Baitang",
    "gn:population":0,
    "gn:timezone":"Asia/Shanghai",
    "iso:country":"CN",
    "name:fas_x_preferred":[
        "\u0628\u0627\u06cc\u062a\u0627\u0646\u06af"
    ],
    "name:hak_x_preferred":[
        "Pak-th\u00f2ng-ch\u1e73\u0301n"
    ],
    "name:und_x_variant":[
        "Pai-t\u2019ang-hs\u00fc",
        "Pai-t\u2019ang",
        "Baitang Zhen",
        "Baitang",
        "Botang Zhen",
        "\u67cf\u5858\u9547"
    ],
    "name:zho_x_preferred":[
        "\u67cf\u5858"
    ],
    "name:zho_x_variant":[
        "\u67cf\u5858\u9547"
    ],
    "wof:name":"Baitang",
    "wof:placetype":"locality"
},
  "geometry": {"coordinates":[114.36042999999999,23.39471],"type":"Point"}
}