{
  "type": "Feature",
  "properties": {
    "gn:admin1_code":"20.0",
    "gn:asciiname":"Xibaoshan",
    "gn:country_code":"CN",
    "gn:dem":250,
    "gn:feature_class":"P",
    "gn:feature_code":"PPL",
    "gn:name":"Xibaoshan",
    "gn:population":0,
    "gn:timezone":"Asia/Shanghai",
    "iso:country":"CN",
    "name:zho_x_preferred":[
        "\u897f\u5b9d\u5c71"
    ],
    "wof:name":"Xibaoshan",
    "wof:placetype":"locality"
},
  "geometry": {"coordinates":[124.06878,48.59315],"type":"Point"}
}