{
  "type": "Feature",
  "properties": {
    "gn:admin1_code":"12.0",
    "gn:asciiname":"Gangxiaxu",
    "gn:country_code":"CN",
    "gn:dem":28,
    "gn:feature_class":"P",
    "gn:feature_code":"PPL",
    "gn:name":"Gangxiaxu",
    "gn:population":0,
    "gn:timezone":"Asia/Shanghai",
    "iso:country":"CN",
    "name:zho_x_preferred":[
        "Gangxiaxu"
    ],
    "name:zho_x_variant":[
        "\u6e2f\u4e0b\u5f90"
    ],
    "wof:name":"Gangxiaxu",
    "wof:placetype":"locality"
},
  "geometry": {"coordinates":[114.55378,29.97585],"type":"Point"}
}