{
  "type": "Feature",
  "properties": {
    "gn:admin1_code":"15.0",
    "gn:asciiname":"Xinghutai",
    "gn:country_code":"CN",
    "gn:dem":1854,
    "gn:feature_class":"P",
    "gn:feature_code":"PPL",
    "gn:name":"Xinghutai",
    "gn:population":0,
    "gn:timezone":"Asia/Shanghai",
    "iso:country":"CN",
    "name:zho_x_preferred":[
        "\u674f\u80e1\u53f0"
    ],
    "wof:name":"Xinghutai",
    "wof:placetype":"locality"
},
  "geometry": {"coordinates":[103.605,36.073],"type":"Point"}
}