{
  "type": "Feature",
  "properties": {
    "gn:admin1_code":"26.0",
    "gn:asciiname":"Zhangjiayuancun",
    "gn:country_code":"CN",
    "gn:dem":1299,
    "gn:feature_class":"P",
    "gn:feature_code":"PPL",
    "gn:name":"Zhangjiayuancun",
    "gn:population":0,
    "gn:timezone":"Asia/Shanghai",
    "iso:country":"CN",
    "name:zho_x_preferred":[
        "\u5f20\u5bb6\u586c\u6751"
    ],
    "wof:name":"Zhangjiayuancun",
    "wof:placetype":"locality"
},
  "geometry": {"coordinates":[109.47692000000001,36.13514],"type":"Point"}
}