{
  "type": "Feature",
  "properties": {
    "gn:admin1_code":"5.0",
    "gn:asciiname":"Miaoling Qingniandian",
    "gn:country_code":"CN",
    "gn:dem":432,
    "gn:feature_class":"P",
    "gn:feature_code":"PPLF",
    "gn:name":"Miaoling Qingniandian",
    "gn:population":0,
    "gn:timezone":"Asia/Shanghai",
    "iso:country":"CN",
    "name:und_x_variant":[
        "\u5e99\u5cad\u9752\u5e74\u70b9"
    ],
    "wof:name":"Miaoling Qingniandian",
    "wof:placetype":"locality"
},
  "geometry": {"coordinates":[129.67676,43.55263],"type":"Point"}
}