{
  "type": "Feature",
  "properties": {
    "gn:admin1_code":"32.0",
    "gn:asciiname":"Simiao",
    "gn:country_code":"CN",
    "gn:dem":3263,
    "gn:feature_class":"P",
    "gn:feature_code":"PPL",
    "gn:name":"Simiao",
    "gn:population":0,
    "gn:timezone":"Asia/Shanghai",
    "iso:country":"CN",
    "name:zho_x_preferred":[
        "\u5bfa\u5e99"
    ],
    "wof:name":"Simiao",
    "wof:placetype":"locality"
},
  "geometry": {"coordinates":[100.31699999999999,31.0401],"type":"Point"}
}