{
  "type": "Feature",
  "properties": {
    "gn:admin1_code":"8.0",
    "gn:asciiname":"Xianzucun",
    "gn:country_code":"CN",
    "gn:dem":143,
    "gn:feature_class":"P",
    "gn:feature_code":"PPL",
    "gn:name":"Xianzucun",
    "gn:population":0,
    "gn:timezone":"Asia/Shanghai",
    "iso:country":"CN",
    "name:zho_x_preferred":[
        "\u9c9c\u65cf\u6751"
    ],
    "wof:name":"Xianzucun",
    "wof:placetype":"locality"
},
  "geometry": {"coordinates":[127.52449,46.36264],"type":"Point"}
}