{
  "type": "Feature",
  "properties": {
    "gn:admin1_code":"11.0",
    "gn:asciiname":"Banshi",
    "gn:country_code":"CN",
    "gn:dem":50,
    "gn:feature_class":"P",
    "gn:feature_code":"PPL",
    "gn:name":"Banshi",
    "gn:population":0,
    "gn:timezone":"Asia/Shanghai",
    "iso:country":"CN",
    "name:ben_x_preferred":[
        "\u09ac\u09be\u0981\u09b6\u09bf"
    ],
    "name:zho_x_preferred":[
        "\u677f\u77f3"
    ],
    "wof:name":"Banshi",
    "wof:placetype":"locality"
},
  "geometry": {"coordinates":[113.169,28.29612],"type":"Point"}
}