{
  "type": "Feature",
  "properties": {
    "gn:admin1_code":"25",
    "gn:asciiname":"Zhongjinma",
    "gn:country_code":"CN",
    "gn:dem":61,
    "gn:feature_class":"P",
    "gn:feature_code":"PPL",
    "gn:name":"Zhongjinma",
    "gn:population":0,
    "gn:timezone":"Asia/Shanghai",
    "iso:country":"CN",
    "name:zho_x_preferred":[
        "\u4e2d\u91d1\u9a6c"
    ],
    "wof:name":"Zhongjinma",
    "wof:placetype":"locality"
},
  "geometry": {"coordinates":[116.816,35.7141],"type":"Point"}
}