{
  "type": "Feature",
  "properties": {
    "gn:admin1_code":"9.0",
    "gn:asciiname":"Shundian",
    "gn:country_code":"CN",
    "gn:dem":183,
    "gn:feature_class":"P",
    "gn:feature_code":"PPL",
    "gn:name":"Shundian",
    "gn:population":0,
    "gn:timezone":"Asia/Shanghai",
    "iso:country":"CN",
    "name:und_x_variant":[
        "\u987a\u5e97",
        "Shundian"
    ],
    "wof:name":"Shundian",
    "wof:placetype":"locality"
},
  "geometry": {"coordinates":[112.9969,33.50904],"type":"Point"}
}