{
  "type": "Feature",
  "properties": {
    "gn:admin1_code":"29.0",
    "gn:asciiname":"Tuguoqing",
    "gn:country_code":"CN",
    "gn:dem":1891,
    "gn:feature_class":"P",
    "gn:feature_code":"PPL",
    "gn:name":"Tuguoqing",
    "gn:population":0,
    "gn:timezone":"Asia/Shanghai",
    "iso:country":"CN",
    "name:zho_x_preferred":[
        "\u571f\u9505\u7b90"
    ],
    "wof:name":"Tuguoqing",
    "wof:placetype":"locality"
},
  "geometry": {"coordinates":[99.70489999999999,24.3491],"type":"Point"}
}