{
  "type": "Feature",
  "properties": {
    "gn:admin1_code":"19",
    "gn:asciiname":"Qianshuangjing",
    "gn:country_code":"CN",
    "gn:dem":109,
    "gn:feature_class":"P",
    "gn:feature_code":"PPL",
    "gn:name":"Qianshuangjing",
    "gn:population":0,
    "gn:timezone":"Asia/Shanghai",
    "iso:country":"CN",
    "name:und_x_variant":[
        "Shuangjingzi",
        "Qianshuangjing"
    ],
    "name:zho_x_preferred":[
        "\u524d\u53cc\u4e95"
    ],
    "wof:name":"Qianshuangjing",
    "wof:placetype":"locality"
},
  "geometry": {"coordinates":[123.81811,43.0757],"type":"Point"}
}