{
  "type": "Feature",
  "properties": {
    "gn:admin1_code":"7.0",
    "gn:asciiname":"Hutoutan",
    "gn:country_code":"CN",
    "gn:dem":400,
    "gn:feature_class":"P",
    "gn:feature_code":"PPL",
    "gn:name":"Hutoutan",
    "gn:population":0,
    "gn:timezone":"Asia/Shanghai",
    "iso:country":"CN",
    "name:und_x_variant":[
        "\u6e56\u5934\u6f6d"
    ],
    "wof:name":"Hutoutan",
    "wof:placetype":"locality"
},
  "geometry": {"coordinates":[116.89941,26.88327],"type":"Point"}
}