{
  "type": "Feature",
  "properties": {
    "gn:admin1_code":"01",
    "gn:asciiname":"Shangcaocun",
    "gn:country_code":"CN",
    "gn:dem":227,
    "gn:feature_class":"P",
    "gn:feature_code":"PPL",
    "gn:name":"Shangcaocun",
    "gn:population":0,
    "gn:timezone":"Asia/Shanghai",
    "iso:country":"CN",
    "name:und_x_variant":[
        "Shang-ts\u2019ao-ts\u2019un",
        "Shangcaocun",
        "Shangcao"
    ],
    "name:zho_x_preferred":[
        "\u4e0a\u6f15\u6751"
    ],
    "wof:name":"Shangcaocun",
    "wof:placetype":"locality"
},
  "geometry": {"coordinates":[118.54382,30.53952],"type":"Point"}
}