{
  "type": "Feature",
  "properties": {
    "gn:admin1_code":"10",
    "gn:asciiname":"Bujitun",
    "gn:country_code":"CN",
    "gn:dem":30,
    "gn:feature_class":"P",
    "gn:feature_code":"PPL",
    "gn:name":"Bujitun",
    "gn:population":0,
    "gn:timezone":"Asia/Shanghai",
    "iso:country":"CN",
    "name:zho_x_preferred":[
        "\u535c\u5409\u5c6f"
    ],
    "wof:name":"Bujitun",
    "wof:placetype":"locality"
},
  "geometry": {"coordinates":[115.617,37.2882],"type":"Point"}
}