{
  "type": "Feature",
  "properties": {
    "gn:admin1_code":"32.0",
    "gn:asciiname":"Yuejinping",
    "gn:country_code":"CN",
    "gn:dem":2203,
    "gn:feature_class":"P",
    "gn:feature_code":"PPL",
    "gn:name":"Yuejinping",
    "gn:population":0,
    "gn:timezone":"Asia/Shanghai",
    "iso:country":"CN",
    "name:zho_x_preferred":[
        "\u8dc3\u8fdb\u576a"
    ],
    "wof:name":"Yuejinping",
    "wof:placetype":"locality"
},
  "geometry": {"coordinates":[102.06399999999999,29.7345],"type":"Point"}
}