{
  "type": "Feature",
  "properties": {
    "gn:admin1_code":"12.0",
    "gn:asciiname":"Xiaoxiniugou",
    "gn:country_code":"CN",
    "gn:dem":685,
    "gn:feature_class":"P",
    "gn:feature_code":"PPL",
    "gn:name":"Xiaoxiniugou",
    "gn:population":0,
    "gn:timezone":"Asia/Shanghai",
    "iso:country":"CN",
    "name:zho_x_preferred":[
        "\u5c0f\u7280\u725b\u6c9f"
    ],
    "wof:name":"Xiaoxiniugou",
    "wof:placetype":"locality"
},
  "geometry": {"coordinates":[110.77809000000001,32.17513],"type":"Point"}
}