{
  "type": "Feature",
  "properties": {
    "gn:admin1_code":"3.0",
    "gn:asciiname":"Shahecun",
    "gn:country_code":"CN",
    "gn:dem":28,
    "gn:feature_class":"P",
    "gn:feature_code":"PPL",
    "gn:name":"Shahecun",
    "gn:population":0,
    "gn:timezone":"Asia/Shanghai",
    "iso:country":"CN",
    "name:und_x_variant":[
        "\u6c99\u6cb3\u6751"
    ],
    "wof:name":"Shahecun",
    "wof:placetype":"locality"
},
  "geometry": {"coordinates":[116.10012999999999,28.30744],"type":"Point"}
}