{
  "type": "Feature",
  "properties": {
    "gn:admin1_code":"16",
    "gn:asciiname":"Bailaping",
    "gn:country_code":"CN",
    "gn:dem":691,
    "gn:feature_class":"P",
    "gn:feature_code":"PPL",
    "gn:name":"Bailaping",
    "gn:population":0,
    "gn:timezone":"Asia/Shanghai",
    "iso:country":"CN",
    "name:zho_x_preferred":[
        "\u767d\u814a\u576a"
    ],
    "wof:name":"Bailaping",
    "wof:placetype":"locality"
},
  "geometry": {"coordinates":[110.236,25.8311],"type":"Point"}
}