{
  "type": "Feature",
  "properties": {
    "gn:admin1_code":"8.0",
    "gn:asciiname":"Wudianzhentun",
    "gn:country_code":"CN",
    "gn:dem":161,
    "gn:feature_class":"P",
    "gn:feature_code":"PPL",
    "gn:name":"Wudianzhentun",
    "gn:population":0,
    "gn:timezone":"Asia/Shanghai",
    "iso:country":"CN",
    "name:zho_x_preferred":[
        "\u5434\u6bbf\u771f\u5c6f"
    ],
    "wof:name":"Wudianzhentun",
    "wof:placetype":"locality"
},
  "geometry": {"coordinates":[127.18908999999999,45.82224],"type":"Point"}
}