{
  "type": "Feature",
  "properties": {
    "gn:admin1_code":"6.0",
    "gn:asciiname":"Naren Qiuji",
    "gn:country_code":"CN",
    "gn:dem":4339,
    "gn:feature_class":"P",
    "gn:feature_code":"PPL",
    "gn:name":"Naren Qiuji",
    "gn:population":0,
    "gn:timezone":"Asia/Urumqi",
    "iso:country":"CN",
    "name:zho_x_preferred":[
        "\u90a3\u4ec1\u4e18\u5409"
    ],
    "wof:name":"Naren Qiuji",
    "wof:placetype":"locality"
},
  "geometry": {"coordinates":[96.27629,33.02632],"type":"Point"}
}