{
  "type": "Feature",
  "properties": {
    "gn:admin1_code":"26.0",
    "gn:asciiname":"Shaziliang",
    "gn:country_code":"CN",
    "gn:dem":735,
    "gn:feature_class":"P",
    "gn:feature_code":"PPL",
    "gn:name":"Shaziliang",
    "gn:population":0,
    "gn:timezone":"Asia/Shanghai",
    "iso:country":"CN",
    "name:und_x_variant":[
        "\u6c99\u5b50\u6881"
    ],
    "wof:name":"Shaziliang",
    "wof:placetype":"locality"
},
  "geometry": {"coordinates":[107.17961,32.93993],"type":"Point"}
}