{
  "type": "Feature",
  "properties": {
    "gn:admin1_code":"32.0",
    "gn:asciiname":"Xingwu",
    "gn:country_code":"CN",
    "gn:dem":414,
    "gn:feature_class":"P",
    "gn:feature_code":"PPL",
    "gn:name":"Xingwu",
    "gn:population":0,
    "gn:timezone":"Asia/Shanghai",
    "iso:country":"CN",
    "name:zho_x_preferred":[
        "\u5174\u65e0"
    ],
    "wof:name":"Xingwu",
    "wof:placetype":"locality"
},
  "geometry": {"coordinates":[104.092,29.8596],"type":"Point"}
}