{
  "type": "Feature",
  "properties": {
    "gn:admin1_code":"30.0",
    "gn:asciiname":"Dongqiaoyuancun",
    "gn:country_code":"CN",
    "gn:dem":8,
    "gn:feature_class":"P",
    "gn:feature_code":"PPL",
    "gn:name":"Dongqiaoyuancun",
    "gn:population":0,
    "gn:timezone":"Asia/Shanghai",
    "iso:country":"CN",
    "name:zho_x_preferred":[
        "\u4e1c\u6865\u56ed\u6751"
    ],
    "wof:name":"Dongqiaoyuancun",
    "wof:placetype":"locality"
},
  "geometry": {"coordinates":[116.12434,23.48813],"type":"Point"}
}