{
  "type": "Feature",
  "properties": {
    "gn:admin1_code":"25",
    "gn:asciiname":"Zhangqinzhuang",
    "gn:country_code":"CN",
    "gn:dem":61,
    "gn:feature_class":"P",
    "gn:feature_code":"PPL",
    "gn:name":"Zhangqinzhuang",
    "gn:population":0,
    "gn:timezone":"Asia/Shanghai",
    "iso:country":"CN",
    "name:zho_x_preferred":[
        "\u5f20\u79e6\u5e84"
    ],
    "wof:name":"Zhangqinzhuang",
    "wof:placetype":"locality"
},
  "geometry": {"coordinates":[117.26900000000001,34.9796],"type":"Point"}
}