{
  "type": "Feature",
  "properties": {
    "gn:admin1_code":"3.0",
    "gn:asciiname":"Lingxia",
    "gn:country_code":"CN",
    "gn:dem":50,
    "gn:feature_class":"P",
    "gn:feature_code":"PPL",
    "gn:name":"Lingxia",
    "gn:population":0,
    "gn:timezone":"Asia/Shanghai",
    "iso:country":"CN",
    "name:und_x_variant":[
        "\u5cad\u4e0b"
    ],
    "wof:name":"Lingxia",
    "wof:placetype":"locality"
},
  "geometry": {"coordinates":[116.25558999999998,27.83766],"type":"Point"}
}