{
  "type": "Feature",
  "properties": {
    "gn:admin1_code":"26.0",
    "gn:asciiname":"Wangjiadun",
    "gn:cc2":"CN",
    "gn:country_code":"CN",
    "gn:dem":1125,
    "gn:feature_class":"P",
    "gn:feature_code":"PPL",
    "gn:name":"Wangjiadun",
    "gn:population":0,
    "gn:timezone":"Asia/Shanghai",
    "iso:country":"CN",
    "name:und_x_variant":[
        "Wang-chia-tun",
        "Wangjiadun"
    ],
    "wof:name":"Wangjiadun",
    "wof:placetype":"locality"
},
  "geometry": {"coordinates":[110.88333,38.78333],"type":"Point"}
}