{
  "type": "Feature",
  "properties": {
    "gn:admin1_code":"31",
    "gn:asciiname":"Yuxiong",
    "gn:country_code":"CN",
    "gn:dem":18,
    "gn:feature_class":"P",
    "gn:feature_code":"PPL",
    "gn:name":"Yuxiong",
    "gn:population":0,
    "gn:timezone":"Asia/Shanghai",
    "iso:country":"CN",
    "name:ind_x_preferred":[
        "Yuxiong"
    ],
    "name:und_x_variant":[
        "\u7389\u96c4"
    ],
    "wof:name":"Yuxiong",
    "wof:placetype":"locality"
},
  "geometry": {"coordinates":[108.776,19.2411],"type":"Point"}
}