{
  "type": "Feature",
  "properties": {
    "gn:admin1_code":"20",
    "gn:asciiname":"Ming-hsin-ssu",
    "gn:country_code":"CN",
    "gn:dem":764,
    "gn:feature_class":"P",
    "gn:feature_code":"PPL",
    "gn:name":"Ming-hsin-ssu",
    "gn:population":0,
    "gn:timezone":"Asia/Shanghai",
    "iso:country":"CN",
    "wof:name":"Ming-hsin-ssu",
    "wof:placetype":"locality"
},
  "geometry": {"coordinates":[118.95193999999999,42.86694],"type":"Point"}
}