{
  "type": "Feature",
  "properties": {
    "gn:admin1_code":"15.0",
    "gn:asciiname":"Kangjia Wopu",
    "gn:country_code":"CN",
    "gn:dem":1879,
    "gn:feature_class":"P",
    "gn:feature_code":"PPL",
    "gn:name":"Kangjia Wopu",
    "gn:population":0,
    "gn:timezone":"Asia/Shanghai",
    "iso:country":"CN",
    "name:zho_x_preferred":[
        "\u5eb7\u5bb6\u7a9d\u94fa"
    ],
    "wof:name":"Kangjia Wopu",
    "wof:placetype":"locality"
},
  "geometry": {"coordinates":[103.18600000000001,37.562],"type":"Point"}
}