{
  "type": "Feature",
  "properties": {
    "gn:admin1_code":"4.0",
    "gn:asciiname":"Yijuji",
    "gn:country_code":"CN",
    "gn:dem":-1,
    "gn:feature_class":"P",
    "gn:feature_code":"PPL",
    "gn:name":"Yijuji",
    "gn:population":0,
    "gn:timezone":"Asia/Shanghai",
    "iso:country":"CN",
    "name:zho_x_preferred":[
        "Yijuji"
    ],
    "name:zho_x_variant":[
        "\u79fb\u5c45\u96c6"
    ],
    "wof:name":"Yijuji",
    "wof:placetype":"locality"
},
  "geometry": {"coordinates":[120.011,34.05798],"type":"Point"}
}