{
  "type": "Feature",
  "properties": {
    "gn:admin1_code":"19.0",
    "gn:asciiname":"Douyawopu",
    "gn:country_code":"CN",
    "gn:dem":62,
    "gn:feature_class":"P",
    "gn:feature_code":"PPL",
    "gn:name":"Douyawopu",
    "gn:population":0,
    "gn:timezone":"Asia/Shanghai",
    "iso:country":"CN",
    "name:und_x_variant":[
        "\u8c46\u82bd\u7a9d\u94fa"
    ],
    "name:zho_x_preferred":[
        "\u8c46\u82bd\u7a9d\u94fa"
    ],
    "wof:name":"Douyawopu",
    "wof:placetype":"locality"
},
  "geometry": {"coordinates":[122.23,42.1117],"type":"Point"}
}