{
  "type": "Feature",
  "properties": {
    "gn:admin1_code":"15.0",
    "gn:asciiname":"Wujiayuan",
    "gn:country_code":"CN",
    "gn:dem":2001,
    "gn:feature_class":"P",
    "gn:feature_code":"PPL",
    "gn:name":"Wujiayuan",
    "gn:population":0,
    "gn:timezone":"Asia/Shanghai",
    "iso:country":"CN",
    "name:zho_x_preferred":[
        "\u4e94\u5bb6\u9662"
    ],
    "wof:name":"Wujiayuan",
    "wof:placetype":"locality"
},
  "geometry": {"coordinates":[104.876,35.4325],"type":"Point"}
}