{
  "type": "Feature",
  "properties": {
    "gn:admin1_code":"15.0",
    "gn:asciiname":"Yuejiawan",
    "gn:country_code":"CN",
    "gn:dem":2245,
    "gn:feature_class":"P",
    "gn:feature_code":"PPL",
    "gn:name":"Yuejiawan",
    "gn:population":0,
    "gn:timezone":"Asia/Shanghai",
    "iso:country":"CN",
    "name:zho_x_preferred":[
        "\u5cb3\u5bb6\u6e7e"
    ],
    "wof:name":"Yuejiawan",
    "wof:placetype":"locality"
},
  "geometry": {"coordinates":[103.90900000000001,35.3085],"type":"Point"}
}