{
  "type": "Feature",
  "properties": {
    "gn:admin1_code":"11.0",
    "gn:asciiname":"Fangjia Laowu",
    "gn:country_code":"CN",
    "gn:dem":451,
    "gn:feature_class":"P",
    "gn:feature_code":"PPL",
    "gn:name":"Fangjia Laowu",
    "gn:population":0,
    "gn:timezone":"Asia/Shanghai",
    "iso:country":"CN",
    "name:zho_x_preferred":[
        "\u65b9\u5bb6\u8001\u5c4b"
    ],
    "wof:name":"Fangjia Laowu",
    "wof:placetype":"locality"
},
  "geometry": {"coordinates":[113.83046000000002,29.038],"type":"Point"}
}