{
  "type": "Feature",
  "properties": {
    "gn:admin1_code":"19.0",
    "gn:asciiname":"Shanghu Xiangou",
    "gn:country_code":"CN",
    "gn:dem":64,
    "gn:feature_class":"P",
    "gn:feature_code":"PPL",
    "gn:name":"Shanghu Xiangou",
    "gn:population":0,
    "gn:timezone":"Asia/Shanghai",
    "iso:country":"CN",
    "name:zho_x_preferred":[
        "\u4e0a\u80e1\u4ed9\u6c9f"
    ],
    "wof:name":"Shanghu Xiangou",
    "wof:placetype":"locality"
},
  "geometry": {"coordinates":[120.086,40.2395],"type":"Point"}
}