{
  "type": "Feature",
  "properties": {
    "gn:admin1_code":"12.0",
    "gn:asciiname":"Lijingou",
    "gn:country_code":"CN",
    "gn:dem":603,
    "gn:feature_class":"P",
    "gn:feature_code":"PPL",
    "gn:name":"Lijingou",
    "gn:population":0,
    "gn:timezone":"Asia/Shanghai",
    "iso:country":"CN",
    "name:zho_x_preferred":[
        "\u674e\u91d1\u6c9f"
    ],
    "wof:name":"Lijingou",
    "wof:placetype":"locality"
},
  "geometry": {"coordinates":[109.87026000000002,32.93458],"type":"Point"}
}