{
  "type": "Feature",
  "properties": {
    "gn:admin1_code":"8.0",
    "gn:asciiname":"Sigongliban",
    "gn:country_code":"CN",
    "gn:dem":288,
    "gn:feature_class":"P",
    "gn:feature_code":"PPL",
    "gn:name":"Sigongliban",
    "gn:population":0,
    "gn:timezone":"Asia/Shanghai",
    "iso:country":"CN",
    "name:zho_x_preferred":[
        "\u56db\u516c\u91cc\u534a"
    ],
    "wof:name":"Sigongliban",
    "wof:placetype":"locality"
},
  "geometry": {"coordinates":[128.88766000000001,46.92396],"type":"Point"}
}