{
  "type": "Feature",
  "properties": {
    "gn:admin1_code":"19.0",
    "gn:asciiname":"Yuzuicun",
    "gn:country_code":"CN",
    "gn:dem":24,
    "gn:feature_class":"P",
    "gn:feature_code":"PPL",
    "gn:name":"Yuzuicun",
    "gn:population":0,
    "gn:timezone":"Asia/Shanghai",
    "iso:country":"CN",
    "name:zho_x_preferred":[
        "\u4e8e\u5480\u6751"
    ],
    "wof:name":"Yuzuicun",
    "wof:placetype":"locality"
},
  "geometry": {"coordinates":[121.79300000000001,39.3941],"type":"Point"}
}