{
  "type": "Feature",
  "properties": {
    "gn:country":"CN",
    "gn:fcode":"PPLA4",
    "gn:pop":0,
    "iso:country":"CN",
    "name:unk_x_variant":[
        "Sung-kang"
    ],
    "name:zho_x_preferred":[
        "\u677e\u5c97"
    ],
    "qs:name":"Songgang",
    "qs:photos_9r":0,
    "qs:photos_sr":0,
    "qs:pop_sr":"6",
    "wof:name":"Songgang",
    "wof:placetype":"locality",
    "wof:population":0
},
  "geometry": {"coordinates":[113.8454,22.77866],"type":"Point"}
}