{
  "type": "Feature",
  "properties": {
    "gn:admin1_code":"15.0",
    "gn:asciiname":"Shangzhuang",
    "gn:country_code":"CN",
    "gn:dem":1939,
    "gn:feature_class":"P",
    "gn:feature_code":"PPL",
    "gn:name":"Shangzhuang",
    "gn:population":0,
    "gn:timezone":"Asia/Shanghai",
    "iso:country":"CN",
    "name:ceb_x_preferred":[
        "Shangzhuang"
    ],
    "name:swe_x_preferred":[
        "Shangzhuang"
    ],
    "name:zho_x_preferred":[
        "\u4e0a\u5e84"
    ],
    "wof:name":"Shangzhuang",
    "wof:placetype":"locality"
},
  "geometry": {"coordinates":[103.44799999999999,37.4332],"type":"Point"}
}