{
  "type": "Feature",
  "properties": {
    "gn:admin1_code":"5.0",
    "gn:asciiname":"Xibei Liudui",
    "gn:country_code":"CN",
    "gn:dem":472,
    "gn:feature_class":"P",
    "gn:feature_code":"PPLF",
    "gn:name":"Xibei Liudui",
    "gn:population":0,
    "gn:timezone":"Asia/Shanghai",
    "iso:country":"CN",
    "name:und_x_variant":[
        "\u897f\u5317\u516d\u961f"
    ],
    "wof:name":"Xibei Liudui",
    "wof:placetype":"locality"
},
  "geometry": {"coordinates":[128.96489,43.28064000000001],"type":"Point"}
}