{
  "type": "Feature",
  "properties": {
    "gn:admin1_code":"15.0",
    "gn:asciiname":"Kuizishan",
    "gn:country_code":"CN",
    "gn:dem":2227,
    "gn:feature_class":"P",
    "gn:feature_code":"PPL",
    "gn:name":"Kuizishan",
    "gn:population":0,
    "gn:timezone":"Asia/Shanghai",
    "iso:country":"CN",
    "name:und_x_variant":[
        "\u76d4\u5b50\u5c71"
    ],
    "wof:name":"Kuizishan",
    "wof:placetype":"locality"
},
  "geometry": {"coordinates":[104.93487,34.60479],"type":"Point"}
}