{
  "type": "Feature",
  "properties": {
    "gn:admin1_code":"14.0",
    "gn:asciiname":"Kyungto",
    "gn:country_code":"CN",
    "gn:dem":4789,
    "gn:feature_class":"P",
    "gn:feature_code":"PPL",
    "gn:name":"Kyungto",
    "gn:population":0,
    "gn:timezone":"Asia/Urumqi",
    "iso:country":"CN",
    "name:bod_x_preferred":[
        "Kyungto"
    ],
    "name:zho_x_preferred":[
        "Qiongtuo"
    ],
    "name:zho_x_variant":[
        "\u7a77\u6258"
    ],
    "wof:name":"Kyungto",
    "wof:placetype":"locality"
},
  "geometry": {"coordinates":[96.502,30.602],"type":"Point"}
}