{
  "type": "Feature",
  "properties": {
    "gn:country":"CN",
    "gn:fcode":"ADM3",
    "gn:pop":0,
    "iso:country":"CN",
    "name:unk_x_variant":[
        "Tun-hua Hsien"
    ],
    "name:zho_x_preferred":[
        "\u6566\u5316\u5e02"
    ],
    "name:zho_x_variant":[
        "\u6566\u5316"
    ],
    "qs:name":"Dunhua Shi",
    "qs:photos_9r":0,
    "qs:photos_sr":0,
    "qs:pop_sr":"0",
    "wof:name":"Dunhua Shi",
    "wof:placetype":"localadmin",
    "wof:population":0
},
  "geometry": {"coordinates":[128.21666999999999,43.35],"type":"Point"}
}