{
  "type": "Feature",
  "properties": {
    "gn:admin1_code":"15.0",
    "gn:asciiname":"Genggou",
    "gn:country_code":"CN",
    "gn:dem":1367,
    "gn:feature_class":"P",
    "gn:feature_code":"PPL",
    "gn:name":"Genggou",
    "gn:population":0,
    "gn:timezone":"Asia/Shanghai",
    "iso:country":"CN",
    "name:zho_x_preferred":[
        "\u803f\u6c9f"
    ],
    "wof:name":"Genggou",
    "wof:placetype":"locality"
},
  "geometry": {"coordinates":[106.965,35.6789],"type":"Point"}
}