{
  "type": "Feature",
  "properties": {
    "gn:admin1_code":"18",
    "gn:asciiname":"Yinchanggou",
    "gn:country_code":"CN",
    "gn:dem":1859,
    "gn:feature_class":"P",
    "gn:feature_code":"PPL",
    "gn:name":"Yinchanggou",
    "gn:population":0,
    "gn:timezone":"Asia/Shanghai",
    "iso:country":"CN",
    "name:zho_x_preferred":[
        "\u94f6\u5382\u6c9f"
    ],
    "wof:name":"Yinchanggou",
    "wof:placetype":"locality"
},
  "geometry": {"coordinates":[105.425,27.1034],"type":"Point"}
}