{
  "type": "Feature",
  "properties": {
    "gn:admin1_code":"26.0",
    "gn:asciiname":"Gengdongwan",
    "gn:country_code":"CN",
    "gn:dem":1341,
    "gn:feature_class":"P",
    "gn:feature_code":"PPL",
    "gn:name":"Gengdongwan",
    "gn:population":0,
    "gn:timezone":"Asia/Shanghai",
    "iso:country":"CN",
    "name:zho_x_preferred":[
        "\u803f\u6d1e\u6e7e"
    ],
    "wof:name":"Gengdongwan",
    "wof:placetype":"locality"
},
  "geometry": {"coordinates":[107.79394000000001,37.75228],"type":"Point"}
}