{
  "type": "Feature",
  "properties": {
    "gn:admin1_code":"9.0",
    "gn:asciiname":"Nanzhangfang",
    "gn:country_code":"CN",
    "gn:dem":68,
    "gn:feature_class":"P",
    "gn:feature_code":"PPL",
    "gn:name":"Nanzhangfang",
    "gn:population":0,
    "gn:timezone":"Asia/Shanghai",
    "iso:country":"CN",
    "name:zho_x_preferred":[
        "\u5357\u5f20\u574a"
    ],
    "wof:name":"Nanzhangfang",
    "wof:placetype":"locality"
},
  "geometry": {"coordinates":[114.11827,34.12675],"type":"Point"}
}