{
  "type": "Feature",
  "properties": {
    "gn:admin1_code":"4.0",
    "gn:asciiname":"Chuannan Jiuzu",
    "gn:country_code":"CN",
    "gn:dem":6,
    "gn:feature_class":"P",
    "gn:feature_code":"PPLF",
    "gn:name":"Chuannan Jiuzu",
    "gn:population":0,
    "gn:timezone":"Asia/Shanghai",
    "iso:country":"CN",
    "name:zho_x_preferred":[
        "\u5ddd\u5357\u4e5d\u7ec4"
    ],
    "wof:name":"Chuannan Jiuzu",
    "wof:placetype":"locality"
},
  "geometry": {"coordinates":[120.679,33.0061],"type":"Point"}
}