{
  "type": "Feature",
  "properties": {
    "gn:admin1_code":"32.0",
    "gn:asciiname":"Daixiu",
    "gn:country_code":"CN",
    "gn:dem":3196,
    "gn:feature_class":"P",
    "gn:feature_code":"PPL",
    "gn:name":"Daixiu",
    "gn:population":0,
    "gn:timezone":"Asia/Shanghai",
    "iso:country":"CN",
    "name:zho_x_preferred":[
        "\u4ee3\u4fee"
    ],
    "wof:name":"Daixiu",
    "wof:placetype":"locality"
},
  "geometry": {"coordinates":[102.503,31.8905],"type":"Point"}
}