{
  "type": "Feature",
  "properties": {
    "gn:admin1_code":"3.0",
    "gn:asciiname":"Shangwujiacun",
    "gn:country_code":"CN",
    "gn:dem":26,
    "gn:feature_class":"P",
    "gn:feature_code":"PPL",
    "gn:name":"Shangwujiacun",
    "gn:population":0,
    "gn:timezone":"Asia/Shanghai",
    "iso:country":"CN",
    "name:und_x_variant":[
        "\u4e0a\u90ac\u5bb6\u6751"
    ],
    "wof:name":"Shangwujiacun",
    "wof:placetype":"locality"
},
  "geometry": {"coordinates":[115.90249,28.45579],"type":"Point"}
}