{
  "type": "Feature",
  "properties": {
    "gn:admin1_code":"29.0",
    "gn:asciiname":"Huaqiuping",
    "gn:country_code":"CN",
    "gn:dem":1408,
    "gn:feature_class":"P",
    "gn:feature_code":"PPL",
    "gn:name":"Huaqiuping",
    "gn:population":0,
    "gn:timezone":"Asia/Shanghai",
    "iso:country":"CN",
    "name:zho_x_preferred":[
        "\u82b1\u79cb\u576a"
    ],
    "wof:name":"Huaqiuping",
    "wof:placetype":"locality"
},
  "geometry": {"coordinates":[104.634,27.8529],"type":"Point"}
}