{
  "type": "Feature",
  "properties": {
    "gn:admin1_code":"14.0",
    "gn:asciiname":"Rulong",
    "gn:country_code":"CN",
    "gn:dem":4159,
    "gn:feature_class":"P",
    "gn:feature_code":"PPL",
    "gn:name":"Rulong",
    "gn:population":0,
    "gn:timezone":"Asia/Urumqi",
    "iso:country":"CN",
    "name:zho_x_preferred":[
        "\u5982\u9f99"
    ],
    "name:zho_x_variant":[
        "\u8339\u9f99\u9547"
    ],
    "wof:name":"Rulong",
    "wof:placetype":"locality"
},
  "geometry": {"coordinates":[95.07590999999999,31.36505],"type":"Point"}
}