{
  "type": "Feature",
  "properties": {
    "gn:admin1_code":"8.0",
    "gn:asciiname":"Gaoyuncun",
    "gn:country_code":"CN",
    "gn:dem":305,
    "gn:feature_class":"P",
    "gn:feature_code":"PPL",
    "gn:name":"Gaoyuncun",
    "gn:population":0,
    "gn:timezone":"Asia/Shanghai",
    "iso:country":"CN",
    "name:zho_x_preferred":[
        "\u9ad8\u4e91\u6751"
    ],
    "wof:name":"Gaoyuncun",
    "wof:placetype":"locality"
},
  "geometry": {"coordinates":[130.11611000000002,45.31838],"type":"Point"}
}