{
  "type": "Feature",
  "properties": {
    "gn:admin1_code":"7",
    "gn:asciiname":"Pengzhou",
    "gn:country_code":"CN",
    "gn:dem":20,
    "gn:feature_class":"P",
    "gn:feature_code":"PPL",
    "gn:name":"Pengzhou",
    "gn:population":0,
    "gn:timezone":"Asia/Shanghai",
    "iso:country":"CN",
    "name:deu_x_preferred":[
        "Pengzhou"
    ],
    "name:eus_x_preferred":[
        "Pengzhou"
    ],
    "name:fas_x_preferred":[
        "\u067e\u0646\u06af\u0698\u0648"
    ],
    "name:fra_x_preferred":[
        "Pengzhou"
    ],
    "name:hak_x_preferred":[
        "Ph\u00e0ng-ch\u00fb-s\u1e73"
    ],
    "name:ita_x_preferred":[
        "Pengzhou"
    ],
    "name:jpn_x_preferred":[
        "\u5f6d\u5dde\u5e02"
    ],
    "name:kik_x_preferred":[
        "Pengzhou"
    ],
    "name:kor_x_preferred":[
        "\ud391\uc800\uc6b0\uc2dc"
    ],
    "name:nor_x_preferred":[
        "Pengzhou"
    ],
    "name:rus_x_preferred":[
        "\u041f\u044d\u043d\u0447\u0436\u043e\u0443"
    ],
    "name:spa_x_preferred":[
        "Pengzhou"
    ],
    "name:swe_x_preferred":[
        "Pengzhou"
    ],
    "name:urd_x_preferred":[
        "\u067e\u06cc\u0646\u06af\u0698\u0648\u0648"
    ],
    "name:vie_x_preferred":[
        "B\u00e0nh Ch\u00e2u"
    ],
    "name:zho_x_preferred":[
        "\u84ec\u5dde"
    ],
    "name:zho_x_variant":[
        "\u5f6d\u5dde\u5e02"
    ],
    "wof:name":"Pengzhou",
    "wof:placetype":"locality"
},
  "geometry": {"coordinates":[117.70471999999999,24.57111],"type":"Point"}
}