{
  "type": "Feature",
  "properties": {
    "gn:admin1_code":"7",
    "gn:asciiname":"Pengzhou",
    "gn:country_code":"CN",
    "gn:dem":20,
    "gn:feature_class":"P",
    "gn:feature_code":"PPL",
    "gn:name":"Pengzhou",
    "gn:population":0,
    "gn:timezone":"Asia/Shanghai",
    "iso:country":"CN",
    "name:zho_x_preferred":[
        "\u84ec\u5dde"
    ],
    "wof:name":"Pengzhou",
    "wof:placetype":"locality"
},
  "geometry": {"coordinates":[117.70471999999999,24.57111],"type":"Point"}
}