{
  "type": "Feature",
  "properties": {
    "gn:admin1_code":"16.0",
    "gn:asciiname":"Yuyaowan",
    "gn:country_code":"CN",
    "gn:dem":782,
    "gn:feature_class":"P",
    "gn:feature_code":"PPL",
    "gn:name":"Yuyaowan",
    "gn:population":0,
    "gn:timezone":"Asia/Shanghai",
    "iso:country":"CN",
    "name:zho_x_preferred":[
        "\u96e8\u5c27\u6e7e"
    ],
    "wof:name":"Yuyaowan",
    "wof:placetype":"locality"
},
  "geometry": {"coordinates":[108.73699999999999,24.9981],"type":"Point"}
}