{
  "type": "Feature",
  "properties": {
    "gn:admin1_code":"2.0",
    "gn:asciiname":"Wuyankeng",
    "gn:country_code":"CN",
    "gn:dem":139,
    "gn:feature_class":"P",
    "gn:feature_code":"PPL",
    "gn:name":"Wuyankeng",
    "gn:population":0,
    "gn:timezone":"Asia/Shanghai",
    "iso:country":"CN",
    "name:und_x_variant":[
        "\u4e4c\u5ca9\u5751"
    ],
    "wof:name":"Wuyankeng",
    "wof:placetype":"locality"
},
  "geometry": {"coordinates":[119.81765,30.57824],"type":"Point"}
}