{
  "type": "Feature",
  "properties": {
    "gn:admin1_code":"5.0",
    "gn:asciiname":"Chunxing",
    "gn:country_code":"CN",
    "gn:dem":330,
    "gn:feature_class":"P",
    "gn:feature_code":"PPL",
    "gn:name":"Chunxing",
    "gn:population":0,
    "gn:timezone":"Asia/Shanghai",
    "iso:country":"CN",
    "name:und_x_variant":[
        "\u6625\u5174",
        "Chunxingcun",
        "\u6625\u5174\u6751"
    ],
    "wof:name":"Chunxing",
    "wof:placetype":"locality"
},
  "geometry": {"coordinates":[129.11751000000001,42.69101],"type":"Point"}
}