{
  "type": "Feature",
  "properties": {
    "gn:admin1_code":"25.0",
    "gn:asciiname":"Jiadeng",
    "gn:country_code":"CN",
    "gn:dem":27,
    "gn:feature_class":"P",
    "gn:feature_code":"PPL",
    "gn:name":"Jiadeng",
    "gn:population":0,
    "gn:timezone":"Asia/Shanghai",
    "iso:country":"CN",
    "name:zho_x_preferred":[
        "\u8d3e\u9093"
    ],
    "wof:name":"Jiadeng",
    "wof:placetype":"locality"
},
  "geometry": {"coordinates":[120.03185000000001,37.30605],"type":"Point"}
}