{
  "type": "Feature",
  "properties": {
    "gn:admin1_code":"18",
    "gn:asciiname":"Pudong",
    "gn:country_code":"CN",
    "gn:dem":821,
    "gn:feature_class":"P",
    "gn:feature_code":"PPL",
    "gn:name":"Pudong",
    "gn:population":0,
    "gn:timezone":"Asia/Shanghai",
    "iso:country":"CN",
    "name:ara_x_preferred":[
        "\u0628\u0648\u062f\u0648\u0646\u063a"
    ],
    "name:ast_x_preferred":[
        "Pudong"
    ],
    "name:aze_x_preferred":[
        "Pudun"
    ],
    "name:ceb_x_preferred":[
        "Pudong Xinqu"
    ],
    "name:ces_x_preferred":[
        "Pchu-tung"
    ],
    "name:dan_x_preferred":[
        "Pudong"
    ],
    "name:deu_x_preferred":[
        "Pudong"
    ],
    "name:eus_x_preferred":[
        "Pudong barrutia"
    ],
    "name:fas_x_preferred":[
        "\u067e\u0648\u062f\u0627\u0646\u06af"
    ],
    "name:fin_x_preferred":[
        "Pudong"
    ],
    "name:glg_x_preferred":[
        "Pudong"
    ],
    "name:heb_x_preferred":[
        "\u05e4\u05d5\u05d3\u05d5\u05e0\u05d2"
    ],
    "name:hun_x_preferred":[
        "Putung"
    ],
    "name:ind_x_preferred":[
        "Pudong"
    ],
    "name:ita_x_preferred":[
        "Pudong"
    ],
    "name:jpn_x_preferred":[
        "\u6d66\u6771\u65b0\u533a"
    ],
    "name:kor_x_preferred":[
        "\ud478\ub465 \uc2e0\uad6c"
    ],
    "name:lit_x_preferred":[
        "Pudongas"
    ],
    "name:nld_x_preferred":[
        "Pudong"
    ],
    "name:nno_x_preferred":[
        "Pudong"
    ],
    "name:nor_x_preferred":[
        "Pudong"
    ],
    "name:pol_x_preferred":[
        "Pudong"
    ],
    "name:por_x_preferred":[
        "Pudong"
    ],
    "name:ron_x_preferred":[
        "Pudong"
    ],
    "name:rus_x_preferred":[
        "\u041f\u0443\u0434\u0443\u043d"
    ],
    "name:slk_x_preferred":[
        "Pchu-tung"
    ],
    "name:spa_x_preferred":[
        "Pudong"
    ],
    "name:swe_x_preferred":[
        "Pudong"
    ],
    "name:tgl_x_preferred":[
        "Pudong"
    ],
    "name:tur_x_preferred":[
        "Pudong"
    ],
    "name:ukr_x_preferred":[
        "\u041f\u0443\u0434\u0443\u043d"
    ],
    "name:urd_x_preferred":[
        "\u067e\u0648\u062f\u0627\u0646\u06af"
    ],
    "name:vie_x_preferred":[
        "Ph\u1ed1 \u0110\u00f4ng"
    ],
    "name:wuu_x_preferred":[
        "\u6d66\u4e1c\u65b0\u533a"
    ],
    "name:zho_x_preferred":[
        "\u84b2\u6d1e"
    ],
    "name:zho_x_variant":[
        "\u6d66\u4e1c\u65b0\u533a"
    ],
    "wof:name":"Pudong",
    "wof:placetype":"locality"
},
  "geometry": {"coordinates":[108.988,26.1719],"type":"Point"}
}