{
  "type": "Feature",
  "properties": {
    "gn:admin1_code":"18",
    "gn:asciiname":"Pudong",
    "gn:country_code":"CN",
    "gn:dem":821,
    "gn:feature_class":"P",
    "gn:feature_code":"PPL",
    "gn:name":"Pudong",
    "gn:population":0,
    "gn:timezone":"Asia/Shanghai",
    "iso:country":"CN",
    "name:zho_x_preferred":[
        "\u84b2\u6d1e"
    ],
    "wof:name":"Pudong",
    "wof:placetype":"locality"
},
  "geometry": {"coordinates":[108.988,26.1719],"type":"Point"}
}