{
  "type": "Feature",
  "properties": {
    "gn:admin1_code":"3.0",
    "gn:asciiname":"Yangfang",
    "gn:country_code":"CN",
    "gn:dem":99,
    "gn:feature_class":"P",
    "gn:feature_code":"PPL",
    "gn:name":"Yangfang",
    "gn:population":0,
    "gn:timezone":"Asia/Shanghai",
    "iso:country":"CN",
    "name:und_x_variant":[
        "\u6d0b\u574a"
    ],
    "wof:name":"Yangfang",
    "wof:placetype":"locality"
},
  "geometry": {"coordinates":[116.81220999999999,27.32708],"type":"Point"}
}