{
  "type": "Feature",
  "properties": {
    "gn:admin1_code":"5.0",
    "gn:asciiname":"Qihaotaizi",
    "gn:country_code":"CN",
    "gn:dem":635,
    "gn:feature_class":"P",
    "gn:feature_code":"PPL",
    "gn:name":"Qihaotaizi",
    "gn:population":0,
    "gn:timezone":"Asia/Shanghai",
    "iso:country":"CN",
    "name:und_x_variant":[
        "\u4e03\u53f7\u53f0\u5b50"
    ],
    "wof:name":"Qihaotaizi",
    "wof:placetype":"locality"
},
  "geometry": {"coordinates":[130.09606000000002,43.35875],"type":"Point"}
}