{
  "type": "Feature",
  "properties": {
    "gn:admin1_code":"15.0",
    "gn:asciiname":"Zhengzhang",
    "gn:country_code":"CN",
    "gn:dem":1521,
    "gn:feature_class":"P",
    "gn:feature_code":"PPL",
    "gn:name":"Zhengzhang",
    "gn:population":0,
    "gn:timezone":"Asia/Shanghai",
    "iso:country":"CN",
    "name:und_x_variant":[
        "\u90d1\u638c"
    ],
    "wof:name":"Zhengzhang",
    "wof:placetype":"locality"
},
  "geometry": {"coordinates":[107.70805,36.78122000000001],"type":"Point"}
}