{
  "type": "Feature",
  "properties": {
    "gn:admin1_code":"15.0",
    "gn:asciiname":"Dagaka",
    "gn:country_code":"CN",
    "gn:dem":3024,
    "gn:feature_class":"P",
    "gn:feature_code":"PPL",
    "gn:name":"Dagaka",
    "gn:population":0,
    "gn:timezone":"Asia/Shanghai",
    "iso:country":"CN",
    "name:und_x_variant":[
        "\u5927\u5c15\u5361"
    ],
    "wof:name":"Dagaka",
    "wof:placetype":"locality"
},
  "geometry": {"coordinates":[103.48081999999999,34.12964],"type":"Point"}
}