{
  "type": "Feature",
  "properties": {
    "gn:admin1_code":"16",
    "gn:asciiname":"Hongdeng",
    "gn:country_code":"CN",
    "gn:dem":309,
    "gn:feature_class":"P",
    "gn:feature_code":"PPL",
    "gn:name":"Hongdeng",
    "gn:population":0,
    "gn:timezone":"Asia/Shanghai",
    "iso:country":"CN",
    "name:zho_x_preferred":[
        "\u7ea2\u7b49"
    ],
    "wof:name":"Hongdeng",
    "wof:placetype":"locality"
},
  "geometry": {"coordinates":[109.664,25.5987],"type":"Point"}
}