{
  "type": "Feature",
  "properties": {
    "gn:admin1_code":"30.0",
    "gn:asciiname":"Caidongkeng",
    "gn:country_code":"CN",
    "gn:dem":338,
    "gn:feature_class":"P",
    "gn:feature_code":"PPL",
    "gn:name":"Caidongkeng",
    "gn:population":0,
    "gn:timezone":"Asia/Shanghai",
    "iso:country":"CN",
    "name:zho_x_preferred":[
        "\u8521\u6d1e\u5751"
    ],
    "wof:name":"Caidongkeng",
    "wof:placetype":"locality"
},
  "geometry": {"coordinates":[112.35728,24.16879],"type":"Point"}
}