{
  "type": "Feature",
  "properties": {
    "gn:admin1_code":"16.0",
    "gn:asciiname":"Sheqicun",
    "gn:country_code":"CN",
    "gn:dem":169,
    "gn:feature_class":"P",
    "gn:feature_code":"PPL",
    "gn:name":"Sheqicun",
    "gn:population":0,
    "gn:timezone":"Asia/Shanghai",
    "iso:country":"CN",
    "name:zho_x_preferred":[
        "\u793e\u4e03\u6751"
    ],
    "wof:name":"Sheqicun",
    "wof:placetype":"locality"
},
  "geometry": {"coordinates":[107.979,23.6702],"type":"Point"}
}