{
  "type": "Feature",
  "properties": {
    "gn:admin1_code":"4.0",
    "gn:asciiname":"Dachecun",
    "gn:country_code":"CN",
    "gn:dem":2,
    "gn:feature_class":"P",
    "gn:feature_code":"PPL",
    "gn:name":"Dachecun",
    "gn:population":0,
    "gn:timezone":"Asia/Shanghai",
    "iso:country":"CN",
    "name:zho_x_preferred":[
        "\u5927\u8f66\u6751"
    ],
    "wof:name":"Dachecun",
    "wof:placetype":"locality"
},
  "geometry": {"coordinates":[119.32769999999999,33.46429000000001],"type":"Point"}
}