{
  "type": "Feature",
  "properties": {
    "gn:admin1_code":"7",
    "gn:asciiname":"Houxing",
    "gn:country_code":"CN",
    "gn:dem":12,
    "gn:feature_class":"P",
    "gn:feature_code":"PPL",
    "gn:name":"Houxing",
    "gn:population":0,
    "gn:timezone":"Asia/Shanghai",
    "iso:country":"CN",
    "name:und_x_variant":[
        "Hou-hsing",
        "Houxing"
    ],
    "name:zho_x_preferred":[
        "\u540e\u884c"
    ],
    "wof:name":"Houxing",
    "wof:placetype":"locality"
},
  "geometry": {"coordinates":[118.97481999999999,24.99239],"type":"Point"}
}