{
  "type": "Feature",
  "properties": {
    "gn:admin1_code":"19.0",
    "gn:asciiname":"Bianqiangzicun",
    "gn:country_code":"CN",
    "gn:dem":73,
    "gn:feature_class":"P",
    "gn:feature_code":"PPL",
    "gn:name":"Bianqiangzicun",
    "gn:population":0,
    "gn:timezone":"Asia/Shanghai",
    "iso:country":"CN",
    "name:zho_x_preferred":[
        "\u8fb9\u5899\u5b50\u6751"
    ],
    "wof:name":"Bianqiangzicun",
    "wof:placetype":"locality"
},
  "geometry": {"coordinates":[121.07111999999999,41.20378],"type":"Point"}
}