{
  "type": "Feature",
  "properties": {
    "gn:admin1_code":"26.0",
    "gn:asciiname":"Shuiniushi",
    "gn:country_code":"CN",
    "gn:dem":543,
    "gn:feature_class":"P",
    "gn:feature_code":"PPL",
    "gn:name":"Shuiniushi",
    "gn:population":0,
    "gn:timezone":"Asia/Shanghai",
    "iso:country":"CN",
    "name:zho_x_preferred":[
        "\u6c34\u725b\u77f3"
    ],
    "wof:name":"Shuiniushi",
    "wof:placetype":"locality"
},
  "geometry": {"coordinates":[108.37669,32.77937],"type":"Point"}
}