{
  "type": "Feature",
  "properties": {
    "gn:admin1_code":"30.0",
    "gn:asciiname":"Shimentang",
    "gn:country_code":"CN",
    "gn:dem":560,
    "gn:feature_class":"P",
    "gn:feature_code":"PPL",
    "gn:name":"Shimentang",
    "gn:population":0,
    "gn:timezone":"Asia/Shanghai",
    "iso:country":"CN",
    "name:zho_x_preferred":[
        "\u77f3\u95e8\u5858"
    ],
    "wof:name":"Shimentang",
    "wof:placetype":"locality"
},
  "geometry": {"coordinates":[111.88625,23.44637],"type":"Point"}
}