{
  "type": "Feature",
  "properties": {
    "gn:admin1_code":"15.0",
    "gn:asciiname":"Lianggoukou",
    "gn:country_code":"CN",
    "gn:dem":1379,
    "gn:feature_class":"P",
    "gn:feature_code":"PPL",
    "gn:name":"Lianggoukou",
    "gn:population":0,
    "gn:timezone":"Asia/Shanghai",
    "iso:country":"CN",
    "name:und_x_variant":[
        "\u6881\u6c9f\u53e3"
    ],
    "wof:name":"Lianggoukou",
    "wof:placetype":"locality"
},
  "geometry": {"coordinates":[107.28167000000001,36.86841],"type":"Point"}
}