{
  "type": "Feature",
  "properties": {
    "gn:admin1_code":"15.0",
    "gn:asciiname":"Dazhuangzi",
    "gn:country_code":"CN",
    "gn:dem":1221,
    "gn:feature_class":"P",
    "gn:feature_code":"PPL",
    "gn:name":"Dazhuangzi",
    "gn:population":0,
    "gn:timezone":"Asia/Shanghai",
    "iso:country":"CN",
    "name:und_x_variant":[
        "Dazhuangzi Xiang"
    ],
    "name:zho_x_preferred":[
        "\u5927\u5e84\u5b50"
    ],
    "name:zho_x_variant":[
        "\u5927\u5e84\u5b50\u4e61"
    ],
    "wof:name":"Dazhuangzi",
    "wof:placetype":"locality"
},
  "geometry": {"coordinates":[99.02809999999999,40.2245],"type":"Point"}
}