{
  "type": "Feature",
  "properties": {
    "gn:admin1_code":"23.0",
    "gn:asciiname":"Yuandong",
    "gn:country_code":"CN",
    "gn:dem":3,
    "gn:feature_class":"P",
    "gn:feature_code":"PPL",
    "gn:name":"Yuandong",
    "gn:population":0,
    "gn:timezone":"Asia/Shanghai",
    "iso:country":"CN",
    "name:zho_x_preferred":[
        "Yuandong"
    ],
    "name:zho_x_variant":[
        "\u5706\u4e1c"
    ],
    "wof:name":"Yuandong",
    "wof:placetype":"locality"
},
  "geometry": {"coordinates":[121.77373,31.34647],"type":"Point"}
}