{
  "type": "Feature",
  "properties": {
    "gn:admin1_code":"10.0",
    "gn:asciiname":"Maoshanwei",
    "gn:country_code":"CN",
    "gn:dem":34,
    "gn:feature_class":"P",
    "gn:feature_code":"PPL",
    "gn:name":"Maoshanwei",
    "gn:population":0,
    "gn:timezone":"Asia/Shanghai",
    "iso:country":"CN",
    "name:zho_x_preferred":[
        "\u8302\u5c71\u536b"
    ],
    "wof:name":"Maoshanwei",
    "wof:placetype":"locality"
},
  "geometry": {"coordinates":[115.33499999999999,38.2551],"type":"Point"}
}