{
  "type": "Feature",
  "properties": {
    "gn:admin1_code":"20.0",
    "gn:asciiname":"Wugongli",
    "gn:country_code":"CN",
    "gn:dem":892,
    "gn:feature_class":"P",
    "gn:feature_code":"PPL",
    "gn:name":"Wugongli",
    "gn:population":0,
    "gn:timezone":"Asia/Shanghai",
    "iso:country":"CN",
    "name:zho_x_preferred":[
        "\u4e94\u516c\u91cc"
    ],
    "wof:name":"Wugongli",
    "wof:placetype":"locality"
},
  "geometry": {"coordinates":[121.39577,48.3845],"type":"Point"}
}