{
  "type": "Feature",
  "properties": {
    "gn:admin1_code":"4.0",
    "gn:asciiname":"Dongyaowan",
    "gn:country_code":"CN",
    "gn:dem":-1,
    "gn:feature_class":"P",
    "gn:feature_code":"PPL",
    "gn:name":"Dongyaowan",
    "gn:population":0,
    "gn:timezone":"Asia/Shanghai",
    "iso:country":"CN",
    "name:zho_x_preferred":[
        "Dongyaowan"
    ],
    "name:zho_x_variant":[
        "\u4e1c\u7a91\u6e7e"
    ],
    "wof:name":"Dongyaowan",
    "wof:placetype":"locality"
},
  "geometry": {"coordinates":[119.82986,33.77143],"type":"Point"}
}