{
  "type": "Feature",
  "properties": {
    "gn:admin1_code":"32.0",
    "gn:asciiname":"Sansheng",
    "gn:country_code":"CN",
    "gn:dem":618,
    "gn:feature_class":"P",
    "gn:feature_code":"PPL",
    "gn:name":"Sansheng",
    "gn:population":0,
    "gn:timezone":"Asia/Shanghai",
    "iso:country":"CN",
    "name:zho_x_preferred":[
        "\u4e09\u5723"
    ],
    "wof:name":"Sansheng",
    "wof:placetype":"locality"
},
  "geometry": {"coordinates":[103.614,30.8144],"type":"Point"}
}