{
  "type": "Feature",
  "properties": {
    "gn:admin1_code":"26.0",
    "gn:asciiname":"Qiujia Goucun",
    "gn:country_code":"CN",
    "gn:dem":1159,
    "gn:feature_class":"P",
    "gn:feature_code":"PPL",
    "gn:name":"Qiujia Goucun",
    "gn:population":0,
    "gn:timezone":"Asia/Shanghai",
    "iso:country":"CN",
    "name:zho_x_preferred":[
        "\u90b1\u5bb6\u6c9f\u6751"
    ],
    "wof:name":"Qiujia Goucun",
    "wof:placetype":"locality"
},
  "geometry": {"coordinates":[110.753,38.7846],"type":"Point"}
}