{
  "type": "Feature",
  "properties": {
    "gn:admin1_code":"2.0",
    "gn:asciiname":"Zhangwan",
    "gn:country_code":"CN",
    "gn:dem":18,
    "gn:feature_class":"P",
    "gn:feature_code":"PPL",
    "gn:name":"Zhangwan",
    "gn:population":0,
    "gn:timezone":"Asia/Shanghai",
    "iso:country":"CN",
    "name:und_x_variant":[
        "\u7ae0\u6e7e"
    ],
    "wof:name":"Zhangwan",
    "wof:placetype":"locality"
},
  "geometry": {"coordinates":[119.75165,30.84314],"type":"Point"}
}