{
  "type": "Feature",
  "properties": {
    "gn:admin1_code":"11.0",
    "gn:asciiname":"Dengzhan'ao",
    "gn:country_code":"CN",
    "gn:dem":1261,
    "gn:feature_class":"P",
    "gn:feature_code":"PPL",
    "gn:name":"Dengzhan\u2019ao",
    "gn:population":0,
    "gn:timezone":"Asia/Shanghai",
    "iso:country":"CN",
    "name:und_x_variant":[
        "Dengzhan\u2019ao"
    ],
    "name:zho_x_preferred":[
        "\u706f\u76cf\u5773"
    ],
    "wof:name":"Dengzhan'ao",
    "wof:placetype":"locality"
},
  "geometry": {"coordinates":[111.94919,26.03079],"type":"Point"}
}