{
  "type": "Feature",
  "properties": {
    "gn:admin1_code":"14",
    "gn:asciiname":"Bajin",
    "gn:country_code":"CN",
    "gn:dem":4198,
    "gn:feature_class":"P",
    "gn:feature_code":"PPL",
    "gn:name":"Bajin",
    "gn:population":0,
    "gn:timezone":"Asia/Urumqi",
    "iso:country":"CN",
    "name:zho_x_preferred":[
        "\u5df4\u91d1"
    ],
    "wof:name":"Bajin",
    "wof:placetype":"locality"
},
  "geometry": {"coordinates":[89.1527,28.8249],"type":"Point"}
}