{
  "type": "Feature",
  "properties": {
    "gn:admin1_code":"12.0",
    "gn:asciiname":"Huangjinzhuang",
    "gn:country_code":"CN",
    "gn:dem":360,
    "gn:feature_class":"P",
    "gn:feature_code":"PPL",
    "gn:name":"Huangjinzhuang",
    "gn:population":0,
    "gn:timezone":"Asia/Shanghai",
    "iso:country":"CN",
    "name:zho_x_preferred":[
        "\u9ec4\u91d1\u5e84"
    ],
    "wof:name":"Huangjinzhuang",
    "wof:placetype":"locality"
},
  "geometry": {"coordinates":[110.4451,30.96971],"type":"Point"}
}