{
  "type": "Feature",
  "properties": {
    "gn:admin1_code":"19.0",
    "gn:asciiname":"Huangjinlouzi",
    "gn:country_code":"CN",
    "gn:dem":59,
    "gn:feature_class":"P",
    "gn:feature_code":"PPL",
    "gn:name":"Huangjinlouzi",
    "gn:population":0,
    "gn:timezone":"Asia/Shanghai",
    "iso:country":"CN",
    "name:und_x_variant":[
        "\u9ec4\u91d1\u697c\u5b50"
    ],
    "name:zho_x_preferred":[
        "\u9ec4\u91d1\u697c\u5b50"
    ],
    "wof:name":"Huangjinlouzi",
    "wof:placetype":"locality"
},
  "geometry": {"coordinates":[123.15639,42.1839],"type":"Point"}
}