{
  "type": "Feature",
  "properties": {
    "gn:admin1_code":"3.0",
    "gn:asciiname":"Chonglintou",
    "gn:country_code":"CN",
    "gn:dem":45,
    "gn:feature_class":"P",
    "gn:feature_code":"PPL",
    "gn:name":"Chonglintou",
    "gn:population":0,
    "gn:timezone":"Asia/Shanghai",
    "iso:country":"CN",
    "name:und_x_variant":[
        "\u5d07\u6797\u5934"
    ],
    "wof:name":"Chonglintou",
    "wof:placetype":"locality"
},
  "geometry": {"coordinates":[116.6129,28.25988],"type":"Point"}
}