{
  "type": "Feature",
  "properties": {
    "gn:admin1_code":"31",
    "gn:asciiname":"Nanlin Qiqu",
    "gn:country_code":"CN",
    "gn:dem":137,
    "gn:feature_class":"P",
    "gn:feature_code":"PPLF",
    "gn:name":"Nanlin Qiqu",
    "gn:population":0,
    "gn:timezone":"Asia/Shanghai",
    "iso:country":"CN",
    "name:und_x_variant":[
        "\u5357\u6797\u4e03\u533a",
        "Nanlinsishiyilian"
    ],
    "wof:name":"Nanlin Qiqu",
    "wof:placetype":"locality"
},
  "geometry": {"coordinates":[110.07857,18.7401],"type":"Point"}
}