{
  "type": "Feature",
  "properties": {
    "gn:admin1_code":"8.0",
    "gn:asciiname":"Wujiazi",
    "gn:country_code":"CN",
    "gn:dem":169,
    "gn:feature_class":"P",
    "gn:feature_code":"PPL",
    "gn:name":"Wujiazi",
    "gn:population":0,
    "gn:timezone":"Asia/Shanghai",
    "iso:country":"CN",
    "name:zho_x_preferred":[
        "\u4e94\u5bb6\u5b50"
    ],
    "wof:name":"Wujiazi",
    "wof:placetype":"locality"
},
  "geometry": {"coordinates":[125.2991,46.03474],"type":"Point"}
}