{
  "type": "Feature",
  "properties": {
    "gn:admin1_code":"1.0",
    "gn:asciiname":"Xiajiangjia",
    "gn:country_code":"CN",
    "gn:dem":771,
    "gn:feature_class":"P",
    "gn:feature_code":"PPL",
    "gn:name":"Xiajiangjia",
    "gn:population":0,
    "gn:timezone":"Asia/Shanghai",
    "iso:country":"CN",
    "wof:name":"Xiajiangjia",
    "wof:placetype":"locality"
},
  "geometry": {"coordinates":[117.59999999999999,30.27917],"type":"Point"}
}