{
  "type": "Feature",
  "properties": {
    "gn:admin1_code":"32",
    "gn:asciiname":"Xinning",
    "gn:country_code":"CN",
    "gn:dem":462,
    "gn:feature_class":"P",
    "gn:feature_code":"PPLA3",
    "gn:name":"Xinning",
    "gn:population":0,
    "gn:timezone":"Asia/Shanghai",
    "iso:country":"CN",
    "name:deu_x_preferred":[
        "Xinning"
    ],
    "name:und_x_variant":[
        "Sin\u2019nin",
        "Hsin-ning",
        "Sinning",
        "K\u2019ai-chiang-hsien",
        "Sinninghsien",
        "Kaikiang",
        "K\u2019ai-chiang",
        "Kaikianghsien",
        "Kaytszan",
        "Kaijiang",
        "Xinning"
    ],
    "name:zho_x_preferred":[
        "\u65b0\u5b81"
    ],
    "wof:name":"Xinning",
    "wof:placetype":"locality"
},
  "geometry": {"coordinates":[107.86508000000001,31.08515],"type":"Point"}
}