{
  "type": "Feature",
  "properties": {
    "gn:admin1_code":"14.0",
    "gn:asciiname":"Renizhong",
    "gn:country_code":"CN",
    "gn:dem":3443,
    "gn:feature_class":"P",
    "gn:feature_code":"PPL",
    "gn:name":"Renizhong",
    "gn:population":0,
    "gn:timezone":"Asia/Urumqi",
    "iso:country":"CN",
    "name:zho_x_preferred":[
        "\u70ed\u5c3c\u4e2d"
    ],
    "wof:name":"Renizhong",
    "wof:placetype":"locality"
},
  "geometry": {"coordinates":[98.71459,29.93774],"type":"Point"}
}