{
  "type": "Feature",
  "properties": {
    "gn:admin1_code":"14.0",
    "gn:asciiname":"Rigongdong",
    "gn:country_code":"CN",
    "gn:dem":4241,
    "gn:feature_class":"P",
    "gn:feature_code":"PPL",
    "gn:name":"Rigongdong",
    "gn:population":0,
    "gn:timezone":"Asia/Urumqi",
    "iso:country":"CN",
    "name:zho_x_preferred":[
        "\u65e5\u8d21\u6d1e"
    ],
    "wof:name":"Rigongdong",
    "wof:placetype":"locality"
},
  "geometry": {"coordinates":[95.42816999999999,31.21397],"type":"Point"}
}