{
  "type": "Feature",
  "properties": {
    "gn:admin1_code":"16.0",
    "gn:asciiname":"Youjilang",
    "gn:country_code":"CN",
    "gn:dem":93,
    "gn:feature_class":"P",
    "gn:feature_code":"PPL",
    "gn:name":"Youjilang",
    "gn:population":0,
    "gn:timezone":"Asia/Shanghai",
    "iso:country":"CN",
    "name:zho_x_preferred":[
        "\u53c8\u5409\u57cc"
    ],
    "wof:name":"Youjilang",
    "wof:placetype":"locality"
},
  "geometry": {"coordinates":[110.374,22.7175],"type":"Point"}
}