{
  "type": "Feature",
  "properties": {
    "gn:admin1_code":"26.0",
    "gn:asciiname":"Michayan",
    "gn:country_code":"CN",
    "gn:dem":1219,
    "gn:feature_class":"P",
    "gn:feature_code":"PPL",
    "gn:name":"Michayan",
    "gn:population":0,
    "gn:timezone":"Asia/Shanghai",
    "iso:country":"CN",
    "name:zho_x_preferred":[
        "\u7cdc\u832c\u7109"
    ],
    "wof:name":"Michayan",
    "wof:placetype":"locality"
},
  "geometry": {"coordinates":[110.87602,39.32442],"type":"Point"}
}