{
  "type": "Feature",
  "properties": {
    "gn:admin1_code":"31.0",
    "gn:asciiname":"Nanlai",
    "gn:country_code":"CN",
    "gn:dem":17,
    "gn:feature_class":"P",
    "gn:feature_code":"PPL",
    "gn:name":"Nanlai",
    "gn:population":0,
    "gn:timezone":"Asia/Shanghai",
    "iso:country":"CN",
    "name:zho_x_preferred":[
        "Nanlai"
    ],
    "name:zho_x_variant":[
        "\u5357\u6765"
    ],
    "wof:name":"Nanlai",
    "wof:placetype":"locality"
},
  "geometry": {"coordinates":[110.72537,19.97548],"type":"Point"}
}