{
  "type": "Feature",
  "properties": {
    "gn:admin1_code":"6.0",
    "gn:asciiname":"Dongni Shaka",
    "gn:country_code":"CN",
    "gn:dem":3559,
    "gn:feature_class":"P",
    "gn:feature_code":"PPL",
    "gn:name":"Dongni Shaka",
    "gn:population":0,
    "gn:timezone":"Asia/Shanghai",
    "iso:country":"CN",
    "name:zho_x_preferred":[
        "\u4e1c\u5c3c\u6c99\u5580"
    ],
    "wof:name":"Dongni Shaka",
    "wof:placetype":"locality"
},
  "geometry": {"coordinates":[101.69331,34.80647],"type":"Point"}
}