{
  "type": "Feature",
  "properties": {
    "gn:admin1_code":"16.0",
    "gn:asciiname":"Danshuiwan",
    "gn:country_code":"CN",
    "gn:dem":12,
    "gn:feature_class":"P",
    "gn:feature_code":"PPL",
    "gn:name":"Danshuiwan",
    "gn:population":0,
    "gn:timezone":"Asia/Shanghai",
    "iso:country":"CN",
    "name:zho_x_preferred":[
        "\u6de1\u6c34\u6e7e"
    ],
    "wof:name":"Danshuiwan",
    "wof:placetype":"locality"
},
  "geometry": {"coordinates":[108.649,21.7268],"type":"Point"}
}