{
  "type": "Feature",
  "properties": {
    "gn:admin1_code":"22.0",
    "gn:asciiname":"Shangmengyingcun",
    "gn:country_code":"CN",
    "gn:dem":438,
    "gn:feature_class":"P",
    "gn:feature_code":"PPL",
    "gn:name":"Shangmengyingcun",
    "gn:population":0,
    "gn:timezone":"Asia/Shanghai",
    "iso:country":"CN",
    "name:zho_x_preferred":[
        "\u4e0a\u5b5f\u8425\u6751"
    ],
    "wof:name":"Shangmengyingcun",
    "wof:placetype":"locality"
},
  "geometry": {"coordinates":[116.67908,40.80152],"type":"Point"}
}