{
  "type": "Feature",
  "properties": {
    "gn:admin1_code":"25",
    "gn:asciiname":"Dayuli",
    "gn:country_code":"CN",
    "gn:dem":20,
    "gn:feature_class":"P",
    "gn:feature_code":"PPL",
    "gn:name":"Dayuli",
    "gn:population":0,
    "gn:timezone":"Asia/Shanghai",
    "iso:country":"CN",
    "name:zho_x_preferred":[
        "\u5927\u9c7c\u674e"
    ],
    "wof:name":"Dayuli",
    "wof:placetype":"locality"
},
  "geometry": {"coordinates":[116.755,37.7878],"type":"Point"}
}