{
  "type": "Feature",
  "properties": {
    "gn:admin1_code":"9.0",
    "gn:asciiname":"Huanglaozhuang",
    "gn:country_code":"CN",
    "gn:dem":172,
    "gn:feature_class":"P",
    "gn:feature_code":"PPL",
    "gn:name":"Huanglaozhuang",
    "gn:population":0,
    "gn:timezone":"Asia/Shanghai",
    "iso:country":"CN",
    "name:zho_x_preferred":[
        "\u7687\u8001\u5e84"
    ],
    "wof:name":"Huanglaozhuang",
    "wof:placetype":"locality"
},
  "geometry": {"coordinates":[112.58454,33.23449],"type":"Point"}
}