{
  "type": "Feature",
  "properties": {
    "gn:admin1_code":"26.0",
    "gn:asciiname":"Hongyatou",
    "gn:country_code":"CN",
    "gn:dem":516,
    "gn:feature_class":"P",
    "gn:feature_code":"PPL",
    "gn:name":"Hongyatou",
    "gn:population":0,
    "gn:timezone":"Asia/Shanghai",
    "iso:country":"CN",
    "name:und_x_variant":[
        "\u7ea2\u5d16\u5934"
    ],
    "wof:name":"Hongyatou",
    "wof:placetype":"locality"
},
  "geometry": {"coordinates":[107.89609,34.18986],"type":"Point"}
}