{
  "type": "Feature",
  "properties": {
    "gn:admin1_code":"12.0",
    "gn:asciiname":"Songjiaguai",
    "gn:country_code":"CN",
    "gn:dem":28,
    "gn:feature_class":"P",
    "gn:feature_code":"PPL",
    "gn:name":"Songjiaguai",
    "gn:population":0,
    "gn:timezone":"Asia/Shanghai",
    "iso:country":"CN",
    "name:zho_x_preferred":[
        "\u5b8b\u5bb6\u62d0"
    ],
    "wof:name":"Songjiaguai",
    "wof:placetype":"locality"
},
  "geometry": {"coordinates":[112.81931000000002,30.21305],"type":"Point"}
}