{
  "type": "Feature",
  "properties": {
    "gn:admin1_code":"24.0",
    "gn:asciiname":"Haolinshan",
    "gn:country_code":"CN",
    "gn:dem":1757,
    "gn:feature_class":"P",
    "gn:feature_code":"PPL",
    "gn:name":"Haolinshan",
    "gn:population":0,
    "gn:timezone":"Asia/Shanghai",
    "iso:country":"CN",
    "name:und_x_variant":[
        "\u84bf\u6797\u5c71"
    ],
    "wof:name":"Haolinshan",
    "wof:placetype":"locality"
},
  "geometry": {"coordinates":[112.02070999999999,39.45698],"type":"Point"}
}