{
  "type": "Feature",
  "properties": {
    "gn:admin1_code":"29.0",
    "gn:asciiname":"Bangqiancun",
    "gn:country_code":"CN",
    "gn:dem":1661,
    "gn:feature_class":"P",
    "gn:feature_code":"PPL",
    "gn:name":"Bangqiancun",
    "gn:population":0,
    "gn:timezone":"Asia/Shanghai",
    "iso:country":"CN",
    "name:zho_x_preferred":[
        "\u90a6\u5343\u6751"
    ],
    "wof:name":"Bangqiancun",
    "wof:placetype":"locality"
},
  "geometry": {"coordinates":[97.6802,24.3366],"type":"Point"}
}