{
  "type": "Feature",
  "properties": {
    "gn:admin1_code":"30",
    "gn:asciiname":"Dajiangli",
    "gn:country_code":"CN",
    "gn:dem":177,
    "gn:feature_class":"P",
    "gn:feature_code":"PPL",
    "gn:name":"Dajiangli",
    "gn:population":0,
    "gn:timezone":"Asia/Shanghai",
    "iso:country":"CN",
    "name:zho_x_preferred":[
        "\u5927\u6c5f\u91cc"
    ],
    "wof:name":"Dajiangli",
    "wof:placetype":"locality"
},
  "geometry": {"coordinates":[116.60845,24.12701],"type":"Point"}
}