{
  "type": "Feature",
  "properties": {
    "gn:admin1_code":"30.0",
    "gn:asciiname":"Xiaojiwei",
    "gn:country_code":"CN",
    "gn:dem":167,
    "gn:feature_class":"P",
    "gn:feature_code":"PPL",
    "gn:name":"Xiaojiwei",
    "gn:population":0,
    "gn:timezone":"Asia/Shanghai",
    "iso:country":"CN",
    "name:zho_x_preferred":[
        "\u5c0f\u9e21\u5c3e"
    ],
    "wof:name":"Xiaojiwei",
    "wof:placetype":"locality"
},
  "geometry": {"coordinates":[111.54486,23.61424],"type":"Point"}
}