{
  "type": "Feature",
  "properties": {
    "gn:admin1_code":"12.0",
    "gn:asciiname":"Cangjiawan",
    "gn:country_code":"CN",
    "gn:dem":85,
    "gn:feature_class":"P",
    "gn:feature_code":"PPL",
    "gn:name":"Cangjiawan",
    "gn:population":0,
    "gn:timezone":"Asia/Shanghai",
    "iso:country":"CN",
    "name:und_x_variant":[
        "\u4ed3\u5bb6\u5846"
    ],
    "wof:name":"Cangjiawan",
    "wof:placetype":"locality"
},
  "geometry": {"coordinates":[115.39431999999999,30.37447],"type":"Point"}
}