{
  "type": "Feature",
  "properties": {
    "gn:admin1_code":"15.0",
    "gn:asciiname":"Zhangfuzui",
    "gn:country_code":"CN",
    "gn:dem":1498,
    "gn:feature_class":"P",
    "gn:feature_code":"PPL",
    "gn:name":"Zhangfuzui",
    "gn:population":0,
    "gn:timezone":"Asia/Shanghai",
    "iso:country":"CN",
    "name:zho_x_preferred":[
        "\u5f20\u5bcc\u5480"
    ],
    "wof:name":"Zhangfuzui",
    "wof:placetype":"locality"
},
  "geometry": {"coordinates":[107.14700000000001,37.0112],"type":"Point"}
}