{
  "type": "Feature",
  "properties": {
    "gn:admin1_code":"26.0",
    "gn:asciiname":"Zhengquancun",
    "gn:country_code":"CN",
    "gn:dem":1392,
    "gn:feature_class":"P",
    "gn:feature_code":"PPL",
    "gn:name":"Zhengquancun",
    "gn:population":0,
    "gn:timezone":"Asia/Shanghai",
    "iso:country":"CN",
    "name:zho_x_preferred":[
        "\u90d1\u5708\u6751"
    ],
    "wof:name":"Zhengquancun",
    "wof:placetype":"locality"
},
  "geometry": {"coordinates":[107.59551999999999,37.55373],"type":"Point"}
}