{
  "type": "Feature",
  "properties": {
    "gn:admin1_code":"7.0",
    "gn:asciiname":"Laiwu",
    "gn:country_code":"CN",
    "gn:dem":307,
    "gn:feature_class":"P",
    "gn:feature_code":"PPL",
    "gn:name":"Laiwu",
    "gn:population":0,
    "gn:timezone":"Asia/Shanghai",
    "iso:country":"CN",
    "name:und_x_variant":[
        "\u8d56\u5c4b"
    ],
    "name:zho_x_preferred":[
        "\u8d56\u5c4b"
    ],
    "wof:name":"Laiwu",
    "wof:placetype":"locality"
},
  "geometry": {"coordinates":[116.39708,25.39151],"type":"Point"}
}