{
  "type": "Feature",
  "properties": {
    "gn:admin1_code":"19.0",
    "gn:asciiname":"Chujia Xigou",
    "gn:country_code":"CN",
    "gn:dem":499,
    "gn:feature_class":"P",
    "gn:feature_code":"PPL",
    "gn:name":"Chujia Xigou",
    "gn:population":0,
    "gn:timezone":"Asia/Shanghai",
    "iso:country":"CN",
    "name:zho_x_preferred":[
        "\u521d\u5bb6\u897f\u6c9f"
    ],
    "wof:name":"Chujia Xigou",
    "wof:placetype":"locality"
},
  "geometry": {"coordinates":[123.492,40.856],"type":"Point"}
}