{
  "type": "Feature",
  "properties": {
    "gn:admin1_code":"16.0",
    "gn:asciiname":"Longwanchong",
    "gn:country_code":"CN",
    "gn:dem":93,
    "gn:feature_class":"P",
    "gn:feature_code":"PPL",
    "gn:name":"Longwanchong",
    "gn:population":0,
    "gn:timezone":"Asia/Shanghai",
    "iso:country":"CN",
    "name:zho_x_preferred":[
        "\u9f99\u6e7e\u51b2"
    ],
    "wof:name":"Longwanchong",
    "wof:placetype":"locality"
},
  "geometry": {"coordinates":[110.56100000000001,22.9632],"type":"Point"}
}