{
  "type": "Feature",
  "properties": {
    "gn:admin1_code":"19.0",
    "gn:asciiname":"Caojiatai",
    "gn:country_code":"CN",
    "gn:dem":37,
    "gn:feature_class":"P",
    "gn:feature_code":"PPL",
    "gn:name":"Caojiatai",
    "gn:population":0,
    "gn:timezone":"Asia/Shanghai",
    "iso:country":"CN",
    "name:und_x_variant":[
        "\u66f9\u5bb6\u53f0"
    ],
    "name:zho_x_preferred":[
        "\u66f9\u5bb6\u53f0"
    ],
    "wof:name":"Caojiatai",
    "wof:placetype":"locality"
},
  "geometry": {"coordinates":[123.19568,41.8789],"type":"Point"}
}