{
  "type": "Feature",
  "properties": {
    "gn:admin1_code":"19.0",
    "gn:asciiname":"Beidengcun",
    "gn:country_code":"CN",
    "gn:dem":371,
    "gn:feature_class":"P",
    "gn:feature_code":"PPL",
    "gn:name":"Beidengcun",
    "gn:population":0,
    "gn:timezone":"Asia/Shanghai",
    "iso:country":"CN",
    "name:zho_x_preferred":[
        "\u7891\u767b\u6751"
    ],
    "wof:name":"Beidengcun",
    "wof:placetype":"locality"
},
  "geometry": {"coordinates":[125.10413,41.41452],"type":"Point"}
}