{
  "type": "Feature",
  "properties": {
    "gn:admin1_code":"3.0",
    "gn:asciiname":"Shaipowu",
    "gn:country_code":"CN",
    "gn:dem":168,
    "gn:feature_class":"P",
    "gn:feature_code":"PPL",
    "gn:name":"Shaipowu",
    "gn:population":0,
    "gn:timezone":"Asia/Shanghai",
    "iso:country":"CN",
    "name:zho_x_preferred":[
        "\u6652\u5761\u575e"
    ],
    "wof:name":"Shaipowu",
    "wof:placetype":"locality"
},
  "geometry": {"coordinates":[117.26079,28.57208],"type":"Point"}
}