{
  "type": "Feature",
  "properties": {
    "gn:admin1_code":"3.0",
    "gn:asciiname":"Miao'an",
    "gn:country_code":"CN",
    "gn:dem":195,
    "gn:feature_class":"P",
    "gn:feature_code":"PPL",
    "gn:name":"Miao\u2019an",
    "gn:population":0,
    "gn:timezone":"Asia/Shanghai",
    "iso:country":"CN",
    "name:und_x_variant":[
        "Miao\u2019an",
        "\u82d7\u5b89"
    ],
    "wof:name":"Miao'an",
    "wof:placetype":"locality"
},
  "geometry": {"coordinates":[115.83573,25.81761],"type":"Point"}
}