{
  "type": "Feature",
  "properties": {
    "gn:admin1_code":"26.0",
    "gn:asciiname":"Yaoyuan",
    "gn:country_code":"CN",
    "gn:dem":633,
    "gn:feature_class":"P",
    "gn:feature_code":"PPL",
    "gn:name":"Yaoyuan",
    "gn:population":0,
    "gn:timezone":"Asia/Shanghai",
    "iso:country":"CN",
    "name:zho_x_preferred":[
        "\u7a91\u56ed"
    ],
    "wof:name":"Yaoyuan",
    "wof:placetype":"locality"
},
  "geometry": {"coordinates":[108.08086000000002,34.10187],"type":"Point"}
}