{
  "type": "Feature",
  "properties": {
    "gn:admin1_code":"1.0",
    "gn:asciiname":"Hejiafangcun",
    "gn:country_code":"CN",
    "gn:dem":428,
    "gn:feature_class":"P",
    "gn:feature_code":"PPL",
    "gn:name":"Hejiafangcun",
    "gn:population":0,
    "gn:timezone":"Asia/Shanghai",
    "iso:country":"CN",
    "name:zho_x_preferred":[
        "\u4f55\u5bb6\u574a\u6751"
    ],
    "wof:name":"Hejiafangcun",
    "wof:placetype":"locality"
},
  "geometry": {"coordinates":[115.95868,31.06311],"type":"Point"}
}