{
  "type": "Feature",
  "properties": {
    "gn:admin1_code":"25",
    "gn:asciiname":"Donggaicun",
    "gn:country_code":"CN",
    "gn:dem":39,
    "gn:feature_class":"P",
    "gn:feature_code":"PPL",
    "gn:name":"Donggaicun",
    "gn:population":0,
    "gn:timezone":"Asia/Shanghai",
    "iso:country":"CN",
    "name:zho_x_preferred":[
        "\u4e1c\u76d6\u6751"
    ],
    "wof:name":"Donggaicun",
    "wof:placetype":"locality"
},
  "geometry": {"coordinates":[116.90600000000001,35.0844],"type":"Point"}
}