{
  "type": "Feature",
  "properties": {
    "gn:admin1_code":"26.0",
    "gn:asciiname":"Mao'ergou",
    "gn:country_code":"CN",
    "gn:dem":706,
    "gn:feature_class":"P",
    "gn:feature_code":"PPL",
    "gn:name":"Mao\u2019ergou",
    "gn:population":0,
    "gn:timezone":"Asia/Shanghai",
    "iso:country":"CN",
    "name:und_x_variant":[
        "Mao\u2019ergou",
        "\u732b\u513f\u6c9f"
    ],
    "wof:name":"Mao'ergou",
    "wof:placetype":"locality"
},
  "geometry": {"coordinates":[106.02478000000001,33.43183],"type":"Point"}
}