{
  "type": "Feature",
  "properties": {
    "gn:admin1_code":"19.0",
    "gn:asciiname":"Lengjiadiancun",
    "gn:country_code":"CN",
    "gn:dem":151,
    "gn:feature_class":"P",
    "gn:feature_code":"PPL",
    "gn:name":"Lengjiadiancun",
    "gn:population":0,
    "gn:timezone":"Asia/Shanghai",
    "iso:country":"CN",
    "name:zho_x_preferred":[
        "\u51b7\u5bb6\u5e97\u6751"
    ],
    "wof:name":"Lengjiadiancun",
    "wof:placetype":"locality"
},
  "geometry": {"coordinates":[120.16844,40.83886],"type":"Point"}
}