{
  "type": "Feature",
  "properties": {
    "gn:admin1_code":"4.0",
    "gn:asciiname":"Huangsan Qiaodai",
    "gn:country_code":"CN",
    "gn:dem":2,
    "gn:feature_class":"P",
    "gn:feature_code":"PPL",
    "gn:name":"Huangsan Qiaodai",
    "gn:population":0,
    "gn:timezone":"Asia/Shanghai",
    "iso:country":"CN",
    "name:zho_x_preferred":[
        "\u9ec4\u4e09\u6865\u5788"
    ],
    "wof:name":"Huangsan Qiaodai",
    "wof:placetype":"locality"
},
  "geometry": {"coordinates":[120.32505,32.04703],"type":"Point"}
}