{
  "type": "Feature",
  "properties": {
    "gn:admin1_code":"12.0",
    "gn:asciiname":"Wawuzhuang",
    "gn:country_code":"CN",
    "gn:dem":442,
    "gn:feature_class":"P",
    "gn:feature_code":"PPL",
    "gn:name":"Wawuzhuang",
    "gn:population":0,
    "gn:timezone":"Asia/Shanghai",
    "iso:country":"CN",
    "name:zho_x_preferred":[
        "\u74e6\u5c4b\u5e84"
    ],
    "wof:name":"Wawuzhuang",
    "wof:placetype":"locality"
},
  "geometry": {"coordinates":[113.4336,32.21835],"type":"Point"}
}