{
  "type": "Feature",
  "properties": {
    "gn:admin1_code":"2.0",
    "gn:asciiname":"Xiage",
    "gn:country_code":"CN",
    "gn:dem":36,
    "gn:feature_class":"P",
    "gn:feature_code":"PPLA4",
    "gn:name":"Xiage",
    "gn:population":0,
    "gn:timezone":"Asia/Shanghai",
    "iso:country":"CN",
    "name:und_x_variant":[
        "Hsia-ko-chen",
        "Hsia-ko",
        "Xiage",
        "Xiage Zhen"
    ],
    "name:zho_x_preferred":[
        "\u4e0b\u5404"
    ],
    "name:zho_x_variant":[
        "\u4e0b\u5404\u9547"
    ],
    "wof:name":"Xiage",
    "wof:placetype":"locality"
},
  "geometry": {"coordinates":[120.84556000000001,28.86001],"type":"Point"}
}