{
  "type": "Feature",
  "properties": {
    "gn:admin1_code":"25",
    "gn:asciiname":"Yujiadao",
    "gn:country_code":"CN",
    "gn:dem":221,
    "gn:feature_class":"P",
    "gn:feature_code":"PPL",
    "gn:name":"Yujiadao",
    "gn:population":0,
    "gn:timezone":"Asia/Shanghai",
    "iso:country":"CN",
    "name:zho_x_preferred":[
        "\u5fa1\u9a7e\u9053"
    ],
    "wof:name":"Yujiadao",
    "wof:placetype":"locality"
},
  "geometry": {"coordinates":[117.532,35.55300000000001],"type":"Point"}
}