{
  "type": "Feature",
  "properties": {
    "gn:admin1_code":"6.0",
    "gn:asciiname":"Longqugou",
    "gn:country_code":"CN",
    "gn:dem":3304,
    "gn:feature_class":"P",
    "gn:feature_code":"PPL",
    "gn:name":"Longqugou",
    "gn:population":0,
    "gn:timezone":"Asia/Shanghai",
    "iso:country":"CN",
    "name:und_x_variant":[
        "\u9f99\u66f2\u6c9f"
    ],
    "wof:name":"Longqugou",
    "wof:placetype":"locality"
},
  "geometry": {"coordinates":[99.99959,35.62825],"type":"Point"}
}