{
  "type": "Feature",
  "properties": {
    "gn:admin1_code":"11.0",
    "gn:asciiname":"Nanling",
    "gn:country_code":"CN",
    "gn:dem":325,
    "gn:feature_class":"P",
    "gn:feature_code":"PPL",
    "gn:name":"Nanling",
    "gn:population":0,
    "gn:timezone":"Asia/Shanghai",
    "iso:country":"CN",
    "name:ceb_x_preferred":[
        "Nanling"
    ],
    "name:deu_x_preferred":[
        "Nanling"
    ],
    "name:nor_x_preferred":[
        "Nanling"
    ],
    "name:swe_x_preferred":[
        "Nanling"
    ],
    "name:zho_x_preferred":[
        "\u5357\u5cad"
    ],
    "wof:name":"Nanling",
    "wof:placetype":"locality"
},
  "geometry": {"coordinates":[113.95348,28.95941],"type":"Point"}
}