{
  "type": "Feature",
  "properties": {
    "gn:admin1_code":"7",
    "gn:asciiname":"Dutan",
    "gn:country_code":"CN",
    "gn:dem":134,
    "gn:feature_class":"P",
    "gn:feature_code":"PPL",
    "gn:name":"Dutan",
    "gn:population":0,
    "gn:timezone":"Asia/Shanghai",
    "iso:country":"CN",
    "name:und_x_variant":[
        "\u6e21\u6f6d"
    ],
    "wof:name":"Dutan",
    "wof:placetype":"locality"
},
  "geometry": {"coordinates":[118.68306,27.20806],"type":"Point"}
}