{
  "type": "Feature",
  "properties": {
    "gn:admin1_code":"1.0",
    "gn:asciiname":"Liangmiaocun",
    "gn:country_code":"CN",
    "gn:dem":26,
    "gn:feature_class":"P",
    "gn:feature_code":"PPL",
    "gn:name":"Liangmiaocun",
    "gn:population":0,
    "gn:timezone":"Asia/Shanghai",
    "iso:country":"CN",
    "name:zho_x_preferred":[
        "\u6881\u5e99\u6751"
    ],
    "wof:name":"Liangmiaocun",
    "wof:placetype":"locality"
},
  "geometry": {"coordinates":[117.68210999999999,33.83847],"type":"Point"}
}