{
  "type": "Feature",
  "properties": {
    "gn:admin1_code":"8.0",
    "gn:asciiname":"Xiaohongqi Yingzicun",
    "gn:country_code":"CN",
    "gn:dem":135,
    "gn:feature_class":"P",
    "gn:feature_code":"PPL",
    "gn:name":"Xiaohongqi Yingzicun",
    "gn:population":0,
    "gn:timezone":"Asia/Shanghai",
    "iso:country":"CN",
    "name:zho_x_preferred":[
        "\u5c0f\u7ea2\u65d7\u8425\u5b50\u6751"
    ],
    "wof:name":"Xiaohongqi Yingzicun",
    "wof:placetype":"locality"
},
  "geometry": {"coordinates":[127.36579,49.88195],"type":"Point"}
}