{
  "type": "Feature",
  "properties": {
    "gn:admin1_code":"11.0",
    "gn:asciiname":"Shouyun",
    "gn:country_code":"CN",
    "gn:dem":362,
    "gn:feature_class":"P",
    "gn:feature_code":"PPL",
    "gn:name":"Shouyun",
    "gn:population":0,
    "gn:timezone":"Asia/Shanghai",
    "iso:country":"CN",
    "name:zho_x_preferred":[
        "\u9996\u4e91"
    ],
    "wof:name":"Shouyun",
    "wof:placetype":"locality"
},
  "geometry": {"coordinates":[109.57859000000001,28.12275],"type":"Point"}
}