{
  "type": "Feature",
  "properties": {
    "gn:admin1_code":"5.0",
    "gn:asciiname":"Si'erhao",
    "gn:country_code":"CN",
    "gn:dem":171,
    "gn:feature_class":"P",
    "gn:feature_code":"PPL",
    "gn:name":"Si\u2019erhao",
    "gn:population":0,
    "gn:timezone":"Asia/Shanghai",
    "iso:country":"CN",
    "name:und_x_variant":[
        "Si\u2019erhao"
    ],
    "name:zho_x_preferred":[
        "\u56db\u4e8c\u53f7"
    ],
    "wof:name":"Si'erhao",
    "wof:placetype":"locality"
},
  "geometry": {"coordinates":[126.45396,45.11258],"type":"Point"}
}