{
  "type": "Feature",
  "properties": {
    "gn:admin1_code":"11",
    "gn:asciiname":"Huaqiao",
    "gn:cc2":"CN",
    "gn:country_code":"CN",
    "gn:dem":209,
    "gn:feature_class":"P",
    "gn:feature_code":"PPL",
    "gn:name":"Huaqiao",
    "gn:population":0,
    "gn:timezone":"Asia/Shanghai",
    "iso:country":"CN",
    "name:und_x_variant":[
        "Hua-ch\u2019iao",
        "Huaqiao"
    ],
    "wof:name":"Huaqiao",
    "wof:placetype":"locality"
},
  "geometry": {"coordinates":[110.68333,28.03333],"type":"Point"}
}