{
  "type": "Feature",
  "properties": {
    "gn:admin1_code":"32.0",
    "gn:asciiname":"Areqietuo",
    "gn:country_code":"CN",
    "gn:dem":2428,
    "gn:feature_class":"P",
    "gn:feature_code":"PPL",
    "gn:name":"Areqietuo",
    "gn:population":0,
    "gn:timezone":"Asia/Shanghai",
    "iso:country":"CN",
    "name:zho_x_preferred":[
        "\u963f\u60f9\u5207\u6258"
    ],
    "wof:name":"Areqietuo",
    "wof:placetype":"locality"
},
  "geometry": {"coordinates":[103.065,28.3942],"type":"Point"}
}