{
  "type": "Feature",
  "properties": {
    "gn:admin1_code":"9.0",
    "gn:asciiname":"Wangmaozhuang",
    "gn:country_code":"CN",
    "gn:dem":142,
    "gn:feature_class":"P",
    "gn:feature_code":"PPL",
    "gn:name":"Wangmaozhuang",
    "gn:population":0,
    "gn:timezone":"Asia/Shanghai",
    "iso:country":"CN",
    "name:zho_x_preferred":[
        "\u738b\u8302\u5e84"
    ],
    "wof:name":"Wangmaozhuang",
    "wof:placetype":"locality"
},
  "geometry": {"coordinates":[113.17424,32.88679],"type":"Point"}
}