{
  "type": "Feature",
  "properties": {
    "gn:admin1_code":"29.0",
    "gn:asciiname":"Yintan",
    "gn:country_code":"CN",
    "gn:dem":1120,
    "gn:feature_class":"P",
    "gn:feature_code":"PPL",
    "gn:name":"Yintan",
    "gn:population":0,
    "gn:timezone":"Asia/Shanghai",
    "iso:country":"CN",
    "name:zho_x_preferred":[
        "\u9634\u6ee9"
    ],
    "wof:name":"Yintan",
    "wof:placetype":"locality"
},
  "geometry": {"coordinates":[101.392,26.3982],"type":"Point"}
}