{
  "type": "Feature",
  "properties": {
    "gn:admin1_code":"19.0",
    "gn:asciiname":"Zhuanshan",
    "gn:country_code":"CN",
    "gn:dem":13,
    "gn:feature_class":"P",
    "gn:feature_code":"PPL",
    "gn:name":"Zhuanshan",
    "gn:population":0,
    "gn:timezone":"Asia/Shanghai",
    "iso:country":"CN",
    "name:und_x_variant":[
        "\u8f6c\u5c71"
    ],
    "wof:name":"Zhuanshan",
    "wof:placetype":"locality"
},
  "geometry": {"coordinates":[122.25282,40.36321],"type":"Point"}
}