{
  "type": "Feature",
  "properties": {
    "gn:admin1_code":"2.0",
    "gn:asciiname":"Zhoukeng",
    "gn:country_code":"CN",
    "gn:dem":673,
    "gn:feature_class":"P",
    "gn:feature_code":"PPL",
    "gn:name":"Zhoukeng",
    "gn:population":0,
    "gn:timezone":"Asia/Shanghai",
    "iso:country":"CN",
    "name:zho_x_preferred":[
        "\u5468\u5751"
    ],
    "wof:name":"Zhoukeng",
    "wof:placetype":"locality"
},
  "geometry": {"coordinates":[119.74471,28.21288],"type":"Point"}
}