{
  "type": "Feature",
  "properties": {
    "gn:admin1_code":"11.0",
    "gn:asciiname":"Gudiao",
    "gn:country_code":"CN",
    "gn:dem":224,
    "gn:feature_class":"P",
    "gn:feature_code":"PPL",
    "gn:name":"Gudiao",
    "gn:population":0,
    "gn:timezone":"Asia/Shanghai",
    "iso:country":"CN",
    "name:zho_x_preferred":[
        "\u53e4\u8c03"
    ],
    "wof:name":"Gudiao",
    "wof:placetype":"locality"
},
  "geometry": {"coordinates":[110.96814999999999,25.06221],"type":"Point"}
}