{
  "type": "Feature",
  "properties": {
    "gn:admin1_code":"12.0",
    "gn:asciiname":"Fujiagang",
    "gn:country_code":"CN",
    "gn:dem":57,
    "gn:feature_class":"P",
    "gn:feature_code":"PPL",
    "gn:name":"Fujiagang",
    "gn:population":0,
    "gn:timezone":"Asia/Shanghai",
    "iso:country":"CN",
    "name:zho_x_preferred":[
        "\u5085\u5bb6\u5c97"
    ],
    "wof:name":"Fujiagang",
    "wof:placetype":"locality"
},
  "geometry": {"coordinates":[114.06395000000001,31.07475],"type":"Point"}
}