{
  "type": "Feature",
  "properties": {
    "gn:admin1_code":"26.0",
    "gn:asciiname":"Dangshancun",
    "gn:country_code":"CN",
    "gn:dem":1181,
    "gn:feature_class":"P",
    "gn:feature_code":"PPL",
    "gn:name":"Dangshancun",
    "gn:population":0,
    "gn:timezone":"Asia/Shanghai",
    "iso:country":"CN",
    "name:zho_x_preferred":[
        "\u515a\u5c71\u6751"
    ],
    "wof:name":"Dangshancun",
    "wof:placetype":"locality"
},
  "geometry": {"coordinates":[110.03077999999999,36.01450999999999],"type":"Point"}
}