{
  "type": "Feature",
  "properties": {
    "gn:admin1_code":"12",
    "gn:asciiname":"Aijia",
    "gn:country_code":"CN",
    "gn:dem":67,
    "gn:feature_class":"P",
    "gn:feature_code":"PPLA4",
    "gn:name":"Aijia",
    "gn:population":0,
    "gn:timezone":"Asia/Shanghai",
    "iso:country":"CN",
    "name:und_x_variant":[
        "\u827e\u5bb6",
        "Aijia Zhen",
        "\u827e\u5bb6\u9547"
    ],
    "wof:name":"Aijia",
    "wof:placetype":"locality"
},
  "geometry": {"coordinates":[111.34614000000001,30.62359],"type":"Point"}
}