{
  "type": "Feature",
  "properties": {
    "gn:admin1_code":"15.0",
    "gn:asciiname":"Fanying",
    "gn:country_code":"CN",
    "gn:dem":2089,
    "gn:feature_class":"P",
    "gn:feature_code":"PPL",
    "gn:name":"Fanying",
    "gn:population":0,
    "gn:timezone":"Asia/Shanghai",
    "iso:country":"CN",
    "name:zho_x_preferred":[
        "\u8303\u8425"
    ],
    "wof:name":"Fanying",
    "wof:placetype":"locality"
},
  "geometry": {"coordinates":[101.18899999999999,38.5477],"type":"Point"}
}