{
  "type": "Feature",
  "properties": {
    "gn:admin1_code":"5.0",
    "gn:asciiname":"Cantoucheng",
    "gn:country_code":"CN",
    "gn:dem":337,
    "gn:feature_class":"P",
    "gn:feature_code":"PPL",
    "gn:name":"Cantoucheng",
    "gn:population":0,
    "gn:timezone":"Asia/Shanghai",
    "iso:country":"CN",
    "name:und_x_variant":[
        "\u8695\u5934\u57ce"
    ],
    "wof:name":"Cantoucheng",
    "wof:placetype":"locality"
},
  "geometry": {"coordinates":[129.21549999999999,42.68397],"type":"Point"}
}