{
  "type": "Feature",
  "properties": {
    "gn:admin1_code":"8.0",
    "gn:asciiname":"Hongqigan",
    "gn:country_code":"CN",
    "gn:dem":284,
    "gn:feature_class":"P",
    "gn:feature_code":"PPL",
    "gn:name":"Hongqigan",
    "gn:population":0,
    "gn:timezone":"Asia/Shanghai",
    "iso:country":"CN",
    "name:zho_x_preferred":[
        "\u7ea2\u65d7\u6746"
    ],
    "wof:name":"Hongqigan",
    "wof:placetype":"locality"
},
  "geometry": {"coordinates":[127.51938,45.1649],"type":"Point"}
}