{
  "type": "Feature",
  "properties": {
    "gn:admin1_code":"9.0",
    "gn:asciiname":"Jieguanting",
    "gn:country_code":"CN",
    "gn:dem":538,
    "gn:feature_class":"P",
    "gn:feature_code":"PPL",
    "gn:name":"Jieguanting",
    "gn:population":0,
    "gn:timezone":"Asia/Shanghai",
    "iso:country":"CN",
    "name:und_x_variant":[
        "\u63a5\u5b98\u5385",
        "Jieguanting"
    ],
    "wof:name":"Jieguanting",
    "wof:placetype":"locality"
},
  "geometry": {"coordinates":[112.10344000000001,33.51461],"type":"Point"}
}