{
  "type": "Feature",
  "properties": {
    "gn:admin1_code":"16.0",
    "gn:asciiname":"Sanxicun",
    "gn:country_code":"CN",
    "gn:dem":884,
    "gn:feature_class":"P",
    "gn:feature_code":"PPL",
    "gn:name":"Sanxicun",
    "gn:population":0,
    "gn:timezone":"Asia/Shanghai",
    "iso:country":"CN",
    "name:zho_x_preferred":[
        "\u4e09\u897f\u6751"
    ],
    "wof:name":"Sanxicun",
    "wof:placetype":"locality"
},
  "geometry": {"coordinates":[106.072,23.2363],"type":"Point"}
}