{
  "type": "Feature",
  "properties": {
    "gn:admin1_code":"16.0",
    "gn:asciiname":"Niandun",
    "gn:country_code":"CN",
    "gn:dem":894,
    "gn:feature_class":"P",
    "gn:feature_code":"PPL",
    "gn:name":"Niandun",
    "gn:population":0,
    "gn:timezone":"Asia/Shanghai",
    "iso:country":"CN",
    "name:zho_x_preferred":[
        "\u5ff5\u6c8c"
    ],
    "wof:name":"Niandun",
    "wof:placetype":"locality"
},
  "geometry": {"coordinates":[106.19799999999999,23.209],"type":"Point"}
}