{
  "type": "Feature",
  "properties": {
    "gn:admin1_code":"2.0",
    "gn:asciiname":"Zhuyuantou",
    "gn:country_code":"CN",
    "gn:dem":7,
    "gn:feature_class":"P",
    "gn:feature_code":"PPL",
    "gn:name":"Zhuyuantou",
    "gn:population":0,
    "gn:timezone":"Asia/Shanghai",
    "iso:country":"CN",
    "name:zho_x_preferred":[
        "\u7af9\u56ed\u5934"
    ],
    "wof:name":"Zhuyuantou",
    "wof:placetype":"locality"
},
  "geometry": {"coordinates":[121.30864,28.59565],"type":"Point"}
}