{
  "type": "Feature",
  "properties": {
    "gn:admin1_code":"5.0",
    "gn:asciiname":"Yaobutun",
    "gn:country_code":"CN",
    "gn:dem":337,
    "gn:feature_class":"P",
    "gn:feature_code":"PPL",
    "gn:name":"Yaobutun",
    "gn:population":0,
    "gn:timezone":"Asia/Shanghai",
    "iso:country":"CN",
    "name:zho_x_preferred":[
        "\u8170\u5821\u5c6f"
    ],
    "wof:name":"Yaobutun",
    "wof:placetype":"locality"
},
  "geometry": {"coordinates":[125.37071,42.92217],"type":"Point"}
}