{
  "type": "Feature",
  "properties": {
    "gn:admin1_code":"24",
    "gn:asciiname":"Jingangku",
    "gn:cc2":"CN",
    "gn:country_code":"CN",
    "gn:dem":1352,
    "gn:feature_class":"P",
    "gn:feature_code":"PPL",
    "gn:name":"Jingangku",
    "gn:population":0,
    "gn:timezone":"Asia/Shanghai",
    "iso:country":"CN",
    "name:und_x_variant":[
        "Chin-kang-k\u2019u",
        "Jingangku"
    ],
    "wof:name":"Jingangku",
    "wof:placetype":"locality"
},
  "geometry": {"coordinates":[113.66083,38.88028],"type":"Point"}
}