{
  "type": "Feature",
  "properties": {
    "gn:admin1_code":"01",
    "gn:asciiname":"Donghong",
    "gn:country_code":"CN",
    "gn:dem":34,
    "gn:feature_class":"P",
    "gn:feature_code":"PPL",
    "gn:name":"Donghong",
    "gn:population":0,
    "gn:timezone":"Asia/Shanghai",
    "iso:country":"CN",
    "name:und_x_variant":[
        "Tung-hung",
        "Hung-chia-ling",
        "Donghong"
    ],
    "name:zho_x_preferred":[
        "\u4e1c\u6d2a"
    ],
    "wof:name":"Donghong",
    "wof:placetype":"locality"
},
  "geometry": {"coordinates":[116.37888,30.09403],"type":"Point"}
}