{
  "type": "Feature",
  "properties": {
    "gn:admin1_code":"14.0",
    "gn:asciiname":"Ligu",
    "gn:country_code":"CN",
    "gn:dem":4135,
    "gn:feature_class":"P",
    "gn:feature_code":"PPL",
    "gn:name":"Ligu",
    "gn:population":0,
    "gn:timezone":"Asia/Urumqi",
    "iso:country":"CN",
    "name:zho_x_preferred":[
        "\u91cc\u53e4"
    ],
    "wof:name":"Ligu",
    "wof:placetype":"locality"
},
  "geometry": {"coordinates":[93.52115000000001,30.12841],"type":"Point"}
}