{
  "type": "Feature",
  "properties": {
    "gn:admin1_code":"11.0",
    "gn:asciiname":"Shangyanzhai",
    "gn:country_code":"CN",
    "gn:dem":321,
    "gn:feature_class":"P",
    "gn:feature_code":"PPL",
    "gn:name":"Shangyanzhai",
    "gn:population":0,
    "gn:timezone":"Asia/Shanghai",
    "iso:country":"CN",
    "name:zho_x_preferred":[
        "\u4e0a\u5ca9\u5be8"
    ],
    "wof:name":"Shangyanzhai",
    "wof:placetype":"locality"
},
  "geometry": {"coordinates":[110.03951000000001,28.36014],"type":"Point"}
}