{
  "type": "Feature",
  "properties": {
    "gn:admin1_code":"11",
    "gn:asciiname":"Wanzili",
    "gn:country_code":"CN",
    "gn:dem":201,
    "gn:feature_class":"P",
    "gn:feature_code":"PPL",
    "gn:name":"Wanzili",
    "gn:population":0,
    "gn:timezone":"Asia/Shanghai",
    "iso:country":"CN",
    "name:und_x_variant":[
        "\u6e7e\u5b50\u91cc",
        "Wanzili"
    ],
    "wof:name":"Wanzili",
    "wof:placetype":"locality"
},
  "geometry": {"coordinates":[111.84444000000001,25.6225],"type":"Point"}
}