{
  "type": "Feature",
  "properties": {
    "gn:admin1_code":"3.0",
    "gn:asciiname":"Santang Chenjia",
    "gn:country_code":"CN",
    "gn:dem":18,
    "gn:feature_class":"P",
    "gn:feature_code":"PPL",
    "gn:name":"Santang Chenjia",
    "gn:population":0,
    "gn:timezone":"Asia/Shanghai",
    "iso:country":"CN",
    "name:und_x_variant":[
        "\u4e09\u5858\u9648\u5bb6"
    ],
    "wof:name":"Santang Chenjia",
    "wof:placetype":"locality"
},
  "geometry": {"coordinates":[116.83248,29.04766],"type":"Point"}
}