{
  "type": "Feature",
  "properties": {
    "gn:admin1_code":"18",
    "gn:asciiname":"Zhelai",
    "gn:country_code":"CN",
    "gn:dem":1278,
    "gn:feature_class":"P",
    "gn:feature_code":"PPL",
    "gn:name":"Zhelai",
    "gn:population":0,
    "gn:timezone":"Asia/Shanghai",
    "iso:country":"CN",
    "name:zho_x_preferred":[
        "\u8005\u8d56"
    ],
    "wof:name":"Zhelai",
    "wof:placetype":"locality"
},
  "geometry": {"coordinates":[105.542,24.9516],"type":"Point"}
}