{
  "type": "Feature",
  "properties": {
    "gn:admin1_code":"29",
    "gn:asciiname":"Abao Shangzhai",
    "gn:country_code":"CN",
    "gn:dem":823,
    "gn:feature_class":"P",
    "gn:feature_code":"PPL",
    "gn:name":"Abao Shangzhai",
    "gn:population":0,
    "gn:timezone":"Asia/Shanghai",
    "iso:country":"CN",
    "name:zho_x_preferred":[
        "\u963f\u5b9d\u4e0a\u5be8"
    ],
    "wof:name":"Abao Shangzhai",
    "wof:placetype":"locality"
},
  "geometry": {"coordinates":[101.824,24.2463],"type":"Point"}
}