{
  "type": "Feature",
  "properties": {
    "gn:admin1_code":"8.0",
    "gn:asciiname":"Sijianfang Xigou",
    "gn:country_code":"CN",
    "gn:dem":333,
    "gn:feature_class":"P",
    "gn:feature_code":"PPL",
    "gn:name":"Sijianfang Xigou",
    "gn:population":0,
    "gn:timezone":"Asia/Shanghai",
    "iso:country":"CN",
    "name:zho_x_preferred":[
        "\u56db\u95f4\u623f\u897f\u6c9f"
    ],
    "wof:name":"Sijianfang Xigou",
    "wof:placetype":"locality"
},
  "geometry": {"coordinates":[128.58543,45.02316],"type":"Point"}
}