{
  "type": "Feature",
  "properties": {
    "gn:admin1_code":"4.0",
    "gn:asciiname":"Shuangmu",
    "gn:country_code":"CN",
    "gn:dem":4,
    "gn:feature_class":"P",
    "gn:feature_code":"PPL",
    "gn:name":"Shuangmu",
    "gn:population":0,
    "gn:timezone":"Asia/Shanghai",
    "iso:country":"CN",
    "name:zho_x_preferred":[
        "\u53cc\u6c90"
    ],
    "wof:name":"Shuangmu",
    "wof:placetype":"locality"
},
  "geometry": {"coordinates":[120.12043,32.74631],"type":"Point"}
}