{
  "type": "Feature",
  "properties": {
    "gn:admin1_code":"16.0",
    "gn:asciiname":"Bichi",
    "gn:country_code":"CN",
    "gn:dem":108,
    "gn:feature_class":"P",
    "gn:feature_code":"PPL",
    "gn:name":"Bichi",
    "gn:population":0,
    "gn:timezone":"Asia/Shanghai",
    "iso:country":"CN",
    "name:zho_x_preferred":[
        "\u5fc5\u6c60"
    ],
    "wof:name":"Bichi",
    "wof:placetype":"locality"
},
  "geometry": {"coordinates":[107.881,22.8566],"type":"Point"}
}