{
  "type": "Feature",
  "properties": {
    "gn:admin1_code":"30.0",
    "gn:asciiname":"Laohongchong",
    "gn:country_code":"CN",
    "gn:dem":758,
    "gn:feature_class":"P",
    "gn:feature_code":"PPL",
    "gn:name":"Laohongchong",
    "gn:population":0,
    "gn:timezone":"Asia/Shanghai",
    "iso:country":"CN",
    "name:zho_x_preferred":[
        "Laohongchong"
    ],
    "name:zho_x_variant":[
        "\u8001\u7ea2\u51b2"
    ],
    "wof:name":"Laohongchong",
    "wof:placetype":"locality"
},
  "geometry": {"coordinates":[113.27164999999999,25.05933],"type":"Point"}
}