{
  "type": "Feature",
  "properties": {
    "gn:admin1_code":"15.0",
    "gn:asciiname":"Xiacuijia",
    "gn:country_code":"CN",
    "gn:dem":1685,
    "gn:feature_class":"P",
    "gn:feature_code":"PPL",
    "gn:name":"Xiacuijia",
    "gn:population":0,
    "gn:timezone":"Asia/Shanghai",
    "iso:country":"CN",
    "name:und_x_variant":[
        "\u4e0b\u5d14\u5bb6"
    ],
    "wof:name":"Xiacuijia",
    "wof:placetype":"locality"
},
  "geometry": {"coordinates":[105.13961999999999,33.32121],"type":"Point"}
}