{
  "type": "Feature",
  "properties": {
    "gn:admin1_code":"19.0",
    "gn:asciiname":"Sangshugou",
    "gn:country_code":"CN",
    "gn:dem":284,
    "gn:feature_class":"P",
    "gn:feature_code":"PPL",
    "gn:name":"Sangshugou",
    "gn:population":0,
    "gn:timezone":"Asia/Shanghai",
    "iso:country":"CN",
    "name:und_x_variant":[
        "\u6851\u6811\u6c9f"
    ],
    "wof:name":"Sangshugou",
    "wof:placetype":"locality"
},
  "geometry": {"coordinates":[124.72545,41.96289],"type":"Point"}
}