{
  "type": "Feature",
  "properties": {
    "gn:admin1_code":"26.0",
    "gn:asciiname":"Beicaocun",
    "gn:country_code":"CN",
    "gn:dem":916,
    "gn:feature_class":"P",
    "gn:feature_code":"PPL",
    "gn:name":"Beicaocun",
    "gn:population":0,
    "gn:timezone":"Asia/Shanghai",
    "iso:country":"CN",
    "name:zho_x_preferred":[
        "\u5317\u8349\u6751"
    ],
    "wof:name":"Beicaocun",
    "wof:placetype":"locality"
},
  "geometry": {"coordinates":[109.52009,35.24886],"type":"Point"}
}