{
  "type": "Feature",
  "properties": {
    "gn:admin1_code":"8.0",
    "gn:asciiname":"Xinxinghe Beicun",
    "gn:country_code":"CN",
    "gn:dem":368,
    "gn:feature_class":"P",
    "gn:feature_code":"PPL",
    "gn:name":"Xinxinghe Beicun",
    "gn:population":0,
    "gn:timezone":"Asia/Shanghai",
    "iso:country":"CN",
    "name:zho_x_preferred":[
        "\u65b0\u5174\u6cb3\u5317\u6751"
    ],
    "wof:name":"Xinxinghe Beicun",
    "wof:placetype":"locality"
},
  "geometry": {"coordinates":[130.40588,44.88769],"type":"Point"}
}