{
  "type": "Feature",
  "properties": {
    "gn:admin1_code":"18.0",
    "gn:asciiname":"Banqiao",
    "gn:country_code":"CN",
    "gn:dem":833,
    "gn:feature_class":"P",
    "gn:feature_code":"PPL",
    "gn:name":"Banqiao",
    "gn:population":0,
    "gn:timezone":"Asia/Shanghai",
    "iso:country":"CN",
    "name:ceb_x_preferred":[
        "Banqiao"
    ],
    "name:deu_x_preferred":[
        "Banqiao"
    ],
    "name:kor_x_preferred":[
        "\ud310\uad50\uad6c"
    ],
    "name:swe_x_preferred":[
        "Banqiao"
    ],
    "name:zho_x_preferred":[
        "\u677f\u6865"
    ],
    "name:zho_x_variant":[
        "\u677f\u6a4b\u5340"
    ],
    "wof:name":"Banqiao",
    "wof:placetype":"locality"
},
  "geometry": {"coordinates":[107.676,26.947],"type":"Point"}
}