{
  "type": "Feature",
  "properties": {
    "gn:admin1_code":"2",
    "gn:asciiname":"Xiantan",
    "gn:country_code":"CN",
    "gn:dem":109,
    "gn:feature_class":"P",
    "gn:feature_code":"PPL",
    "gn:name":"Xiantan",
    "gn:population":0,
    "gn:timezone":"Asia/Shanghai",
    "iso:country":"CN",
    "name:zho_x_preferred":[
        "\u663e\u6f6d"
    ],
    "wof:name":"Xiantan",
    "wof:placetype":"locality"
},
  "geometry": {"coordinates":[120.63999,29.72864],"type":"Point"}
}