{
  "type": "Feature",
  "properties": {
    "gn:admin1_code":"25.0",
    "gn:asciiname":"Zhuguocun",
    "gn:cc2":"CN",
    "gn:country_code":"CN",
    "gn:dem":59,
    "gn:feature_class":"P",
    "gn:feature_code":"PPL",
    "gn:name":"Zhuguocun",
    "gn:population":0,
    "gn:timezone":"Asia/Shanghai",
    "iso:country":"CN",
    "name:zho_x_preferred":[
        "\u6731\u90ed\u6751"
    ],
    "wof:name":"Zhuguocun",
    "wof:placetype":"locality"
},
  "geometry": {"coordinates":[119.77638,36.14684000000001],"type":"Point"}
}