{
  "type": "Feature",
  "properties": {
    "gn:admin1_code":"10",
    "gn:asciiname":"Shaoguodian",
    "gn:country_code":"CN",
    "gn:dem":400,
    "gn:feature_class":"P",
    "gn:feature_code":"PPL",
    "gn:name":"Shaoguodian",
    "gn:population":0,
    "gn:timezone":"Asia/Shanghai",
    "iso:country":"CN",
    "name:zho_x_preferred":[
        "\u70e7\u9505\u5e97"
    ],
    "wof:name":"Shaoguodian",
    "wof:placetype":"locality"
},
  "geometry": {"coordinates":[119.51375,40.52772],"type":"Point"}
}