{
  "type": "Feature",
  "properties": {
    "gn:admin1_code":"5.0",
    "gn:asciiname":"Jingxingcun",
    "gn:country_code":"CN",
    "gn:dem":371,
    "gn:feature_class":"P",
    "gn:feature_code":"PPL",
    "gn:name":"Jingxingcun",
    "gn:population":0,
    "gn:timezone":"Asia/Shanghai",
    "iso:country":"CN",
    "name:zho_x_preferred":[
        "\u666f\u5174\u6751"
    ],
    "wof:name":"Jingxingcun",
    "wof:placetype":"locality"
},
  "geometry": {"coordinates":[125.42242,42.29406],"type":"Point"}
}