{
  "type": "Feature",
  "properties": {
    "gn:admin1_code":"10",
    "gn:asciiname":"Hualinbei",
    "gn:country_code":"CN",
    "gn:dem":1395,
    "gn:feature_class":"P",
    "gn:feature_code":"PPL",
    "gn:name":"Hualinbei",
    "gn:population":0,
    "gn:timezone":"Asia/Shanghai",
    "iso:country":"CN",
    "name:zho_x_preferred":[
        "\u6866\u6797\u80cc"
    ],
    "wof:name":"Hualinbei",
    "wof:placetype":"locality"
},
  "geometry": {"coordinates":[114.82177,40.97897],"type":"Point"}
}