{
  "type": "Feature",
  "properties": {
    "gn:admin1_code":"7.0",
    "gn:asciiname":"Meihua",
    "gn:country_code":"CN",
    "gn:dem":205,
    "gn:feature_class":"P",
    "gn:feature_code":"PPL",
    "gn:name":"Meihua",
    "gn:population":0,
    "gn:timezone":"Asia/Shanghai",
    "iso:country":"CN",
    "name:zho_x_preferred":[
        "\u6885\u82b1"
    ],
    "wof:name":"Meihua",
    "wof:placetype":"locality"
},
  "geometry": {"coordinates":[120.22654,26.98394],"type":"Point"}
}