{
  "type": "Feature",
  "properties": {
    "gn:admin1_code":"16.0",
    "gn:asciiname":"Fuli",
    "gn:country_code":"CN",
    "gn:dem":509,
    "gn:feature_class":"P",
    "gn:feature_code":"PPL",
    "gn:name":"Fuli",
    "gn:population":0,
    "gn:timezone":"Asia/Shanghai",
    "iso:country":"CN",
    "name:ceb_x_preferred":[
        "Fuli"
    ],
    "name:deu_x_preferred":[
        "Fuli"
    ],
    "name:swe_x_preferred":[
        "Fuli"
    ],
    "name:zho_x_preferred":[
        "\u798f\u5229"
    ],
    "wof:name":"Fuli",
    "wof:placetype":"locality"
},
  "geometry": {"coordinates":[106.89400000000001,23.182],"type":"Point"}
}