{
  "type": "Feature",
  "properties": {
    "gn:admin1_code":"02",
    "gn:asciiname":"Daidaon",
    "gn:country_code":"CN",
    "gn:dem":3,
    "gn:feature_class":"P",
    "gn:feature_code":"PPLA4",
    "gn:name":"Daidaon",
    "gn:population":0,
    "gn:timezone":"Asia/Shanghai",
    "iso:country":"CN",
    "name:und_x_variant":[
        "Ts\u2019ao-chia",
        "Caojia",
        "\u66f9\u5bb6",
        "Daidongzhen",
        "Daidong Zhen",
        "\u5cb1\u4e1c\u9547",
        "Daidaon"
    ],
    "name:zho_x_preferred":[
        "\u5cb1\u4e1c"
    ],
    "wof:name":"Daidaon",
    "wof:placetype":"locality"
},
  "geometry": {"coordinates":[122.19794,30.29526],"type":"Point"}
}