{
  "type": "Feature",
  "properties": {
    "gn:admin1_code":"29.0",
    "gn:asciiname":"Layihua",
    "gn:country_code":"CN",
    "gn:dem":2702,
    "gn:feature_class":"P",
    "gn:feature_code":"PPL",
    "gn:name":"Layihua",
    "gn:population":0,
    "gn:timezone":"Asia/Shanghai",
    "iso:country":"CN",
    "name:zho_x_preferred":[
        "\u62c9\u79fb\u534e"
    ],
    "wof:name":"Layihua",
    "wof:placetype":"locality"
},
  "geometry": {"coordinates":[100.39100000000001,27.5892],"type":"Point"}
}