{
  "type": "Feature",
  "properties": {
    "gn:admin1_code":"30",
    "gn:asciiname":"Hemushan",
    "gn:country_code":"CN",
    "gn:dem":26,
    "gn:feature_class":"P",
    "gn:feature_code":"PPL",
    "gn:name":"Hemushan",
    "gn:population":0,
    "gn:timezone":"Asia/Urumqi",
    "iso:country":"CN",
    "name:zho_x_preferred":[
        "\u8377\u6728\u5c71"
    ],
    "wof:name":"Hemushan",
    "wof:placetype":"locality"
},
  "geometry": {"coordinates":[110.58669999999999,21.48689],"type":"Point"}
}