{
  "type": "Feature",
  "properties": {
    "gn:admin1_code":"26.0",
    "gn:asciiname":"Ruanjia Guacun",
    "gn:country_code":"CN",
    "gn:dem":1040,
    "gn:feature_class":"P",
    "gn:feature_code":"PPL",
    "gn:name":"Ruanjia Guacun",
    "gn:population":0,
    "gn:timezone":"Asia/Shanghai",
    "iso:country":"CN",
    "name:zho_x_preferred":[
        "\u962e\u5bb6\u576c\u6751"
    ],
    "wof:name":"Ruanjia Guacun",
    "wof:placetype":"locality"
},
  "geometry": {"coordinates":[110.848,38.6481],"type":"Point"}
}