{
  "type": "Feature",
  "properties": {
    "gn:admin1_code":"16.0",
    "gn:asciiname":"Luna",
    "gn:country_code":"CN",
    "gn:dem":682,
    "gn:feature_class":"P",
    "gn:feature_code":"PPL",
    "gn:name":"L\u00fcna",
    "gn:population":0,
    "gn:timezone":"Asia/Shanghai",
    "iso:country":"CN",
    "name:und_x_variant":[
        "L\u00fcna"
    ],
    "name:zho_x_preferred":[
        "\u5415\u90a3"
    ],
    "wof:name":"Luna",
    "wof:placetype":"locality"
},
  "geometry": {"coordinates":[106.367,22.9304],"type":"Point"}
}