{
  "type": "Feature",
  "properties": {
    "gn:admin1_code":"16.0",
    "gn:asciiname":"Lannitian",
    "gn:country_code":"CN",
    "gn:dem":305,
    "gn:feature_class":"P",
    "gn:feature_code":"PPL",
    "gn:name":"Lannitian",
    "gn:population":0,
    "gn:timezone":"Asia/Shanghai",
    "iso:country":"CN",
    "name:zho_x_preferred":[
        "\u70c2\u6ce5\u7530"
    ],
    "wof:name":"Lannitian",
    "wof:placetype":"locality"
},
  "geometry": {"coordinates":[110.01300000000001,24.7663],"type":"Point"}
}