{
  "type": "Feature",
  "properties": {
    "gn:admin1_code":"18",
    "gn:asciiname":"Xibo",
    "gn:country_code":"CN",
    "gn:dem":1635,
    "gn:feature_class":"P",
    "gn:feature_code":"PPL",
    "gn:name":"Xibo",
    "gn:population":0,
    "gn:timezone":"Asia/Shanghai",
    "iso:country":"CN",
    "name:zho_x_preferred":[
        "\u897f\u6ce2"
    ],
    "wof:name":"Xibo",
    "wof:placetype":"locality"
},
  "geometry": {"coordinates":[105.845,27.1903],"type":"Point"}
}