{
  "type": "Feature",
  "properties": {
    "gn:admin1_code":"4.0",
    "gn:asciiname":"Shuangcheng",
    "gn:country_code":"CN",
    "gn:dem":11,
    "gn:feature_class":"P",
    "gn:feature_code":"PPL",
    "gn:name":"Shuangcheng",
    "gn:population":0,
    "gn:timezone":"Asia/Shanghai",
    "iso:country":"CN",
    "name:ara_x_preferred":[
        "\u0634\u0648\u0627\u0646\u063a"
    ],
    "name:ben_x_preferred":[
        "\u09b6\u09c1\u09df\u09be\u0982\u099a\u09c7\u0982"
    ],
    "name:ell_x_preferred":[
        "\u03a3\u03bf\u03c5\u03b1\u03bd\u03b3\u03ba\u03c4\u03c3\u03ad\u03bd\u03b3\u03ba"
    ],
    "name:fas_x_preferred":[
        "\u0634\u0648\u0627\u0646\u06af \u0686\u0646\u06af"
    ],
    "name:heb_x_preferred":[
        "\u05e9\u05d5\u05d0\u05e0\u05d2\u05e6'\u05e0\u05d2"
    ],
    "name:hin_x_preferred":[
        "\u0936\u0941\u0906\u0902\u0917\u091a\u0947\u0902\u0917"
    ],
    "name:hun_x_preferred":[
        "Shuangcheng"
    ],
    "name:ind_x_preferred":[
        "Shuangcheng"
    ],
    "name:pol_x_preferred":[
        "Shuangcheng"
    ],
    "name:por_x_preferred":[
        "Shuangcheng"
    ],
    "name:tur_x_preferred":[
        "Shuangcheng"
    ],
    "name:ukr_x_preferred":[
        "\u0428\u0443\u0430\u043d\u0447\u0435\u043d"
    ],
    "name:zho_x_preferred":[
        "\u53cc\u57ce"
    ],
    "wof:name":"Shuangcheng",
    "wof:placetype":"locality"
},
  "geometry": {"coordinates":[118.82384999999999,31.32452],"type":"Point"}
}