{
  "type": "Feature",
  "properties": {
    "gn:admin1_code":"29.0",
    "gn:asciiname":"Manghai",
    "gn:country_code":"CN",
    "gn:dem":951,
    "gn:feature_class":"P",
    "gn:feature_code":"PPL",
    "gn:name":"Manghai",
    "gn:population":0,
    "gn:timezone":"Asia/Shanghai",
    "iso:country":"CN",
    "name:zho_x_preferred":[
        "\u5fd9\u6d77"
    ],
    "wof:name":"Manghai",
    "wof:placetype":"locality"
},
  "geometry": {"coordinates":[99.37730000000001,24.0545],"type":"Point"}
}