{
  "type": "Feature",
  "properties": {
    "gn:admin1_code":"4.0",
    "gn:asciiname":"Wuxu",
    "gn:country_code":"CN",
    "gn:dem":3,
    "gn:feature_class":"P",
    "gn:feature_code":"PPL",
    "gn:name":"Wuxu",
    "gn:population":0,
    "gn:timezone":"Asia/Shanghai",
    "iso:country":"CN",
    "name:und_x_variant":[
        "\u4e94\u5729"
    ],
    "name:zho_x_preferred":[
        "\u4e94\u5729"
    ],
    "wof:name":"Wuxu",
    "wof:placetype":"locality"
},
  "geometry": {"coordinates":[120.99290999999999,31.8867],"type":"Point"}
}