{
  "type": "Feature",
  "properties": {
    "gn:admin1_code":"16.0",
    "gn:asciiname":"Xinzhouping",
    "gn:country_code":"CN",
    "gn:dem":88,
    "gn:feature_class":"P",
    "gn:feature_code":"PPL",
    "gn:name":"Xinzhouping",
    "gn:population":0,
    "gn:timezone":"Asia/Shanghai",
    "iso:country":"CN",
    "name:zho_x_preferred":[
        "\u65b0\u5468\u5e73"
    ],
    "wof:name":"Xinzhouping",
    "wof:placetype":"locality"
},
  "geometry": {"coordinates":[109.10599999999999,23.7052],"type":"Point"}
}