{
  "type": "Feature",
  "properties": {
    "gn:admin1_code":"11.0",
    "gn:asciiname":"Oujiashan",
    "gn:country_code":"CN",
    "gn:dem":480,
    "gn:feature_class":"P",
    "gn:feature_code":"PPL",
    "gn:name":"Oujiashan",
    "gn:population":0,
    "gn:timezone":"Asia/Shanghai",
    "iso:country":"CN",
    "name:zho_x_preferred":[
        "\u6b27\u5bb6\u5c71"
    ],
    "wof:name":"Oujiashan",
    "wof:placetype":"locality"
},
  "geometry": {"coordinates":[113.27898999999999,25.63318],"type":"Point"}
}