{
  "type": "Feature",
  "properties": {
    "gn:admin1_code":"8.0",
    "gn:asciiname":"Sanshiliu Gongli",
    "gn:country_code":"CN",
    "gn:dem":289,
    "gn:feature_class":"P",
    "gn:feature_code":"PPL",
    "gn:name":"Sanshiliu Gongli",
    "gn:population":0,
    "gn:timezone":"Asia/Shanghai",
    "iso:country":"CN",
    "name:zho_x_preferred":[
        "\u4e09\u5341\u516d\u516c\u91cc"
    ],
    "wof:name":"Sanshiliu Gongli",
    "wof:placetype":"locality"
},
  "geometry": {"coordinates":[127.94385,44.44312],"type":"Point"}
}