{
  "type": "Feature",
  "properties": {
    "gn:admin1_code":"18",
    "gn:asciiname":"Zheshanzhai",
    "gn:country_code":"CN",
    "gn:dem":801,
    "gn:feature_class":"P",
    "gn:feature_code":"PPL",
    "gn:name":"Zheshanzhai",
    "gn:population":0,
    "gn:timezone":"Asia/Shanghai",
    "iso:country":"CN",
    "name:zho_x_preferred":[
        "\u8005\u5c71\u5be8"
    ],
    "wof:name":"Zheshanzhai",
    "wof:placetype":"locality"
},
  "geometry": {"coordinates":[105.806,24.9973],"type":"Point"}
}