{
  "type": "Feature",
  "properties": {
    "gn:admin1_code":"32.0",
    "gn:asciiname":"Yonghe",
    "gn:country_code":"CN",
    "gn:dem":968,
    "gn:feature_class":"P",
    "gn:feature_code":"PPL",
    "gn:name":"Yonghe",
    "gn:population":0,
    "gn:timezone":"Asia/Shanghai",
    "iso:country":"CN",
    "name:ceb_x_preferred":[
        "Yonghe"
    ],
    "name:deu_x_preferred":[
        "Yonghe"
    ],
    "name:rus_x_preferred":[
        "\u042e\u043d\u0445\u044d"
    ],
    "name:zho_x_preferred":[
        "\u6c38\u548c"
    ],
    "wof:name":"Yonghe",
    "wof:placetype":"locality"
},
  "geometry": {"coordinates":[105.557,27.9893],"type":"Point"}
}