{
  "type": "Feature",
  "properties": {
    "gn:admin1_code":"13.0",
    "gn:asciiname":"Youlegun Bulake",
    "gn:country_code":"CN",
    "gn:dem":2397,
    "gn:feature_class":"P",
    "gn:feature_code":"PPL",
    "gn:name":"Youlegun Bulake",
    "gn:population":0,
    "gn:timezone":"Asia/Urumqi",
    "iso:country":"CN",
    "name:zho_x_preferred":[
        "\u5c24\u52d2\u6eda\u5e03\u62c9\u514b"
    ],
    "wof:name":"Youlegun Bulake",
    "wof:placetype":"locality"
},
  "geometry": {"coordinates":[83.34039,36.72717],"type":"Point"}
}