{
  "type": "Feature",
  "properties": {
    "gn:admin1_code":"9.0",
    "gn:asciiname":"Beiying",
    "gn:country_code":"CN",
    "gn:dem":685,
    "gn:feature_class":"P",
    "gn:feature_code":"PPL",
    "gn:name":"Beiying",
    "gn:population":0,
    "gn:timezone":"Asia/Shanghai",
    "iso:country":"CN",
    "name:zho_x_preferred":[
        "\u5317\u8425"
    ],
    "wof:name":"Beiying",
    "wof:placetype":"locality"
},
  "geometry": {"coordinates":[111.13334,34.69244],"type":"Point"}
}