{
  "type": "Feature",
  "properties": {
    "gn:admin1_code":"29",
    "gn:asciiname":"Yuziwu",
    "gn:country_code":"CN",
    "gn:dem":2147,
    "gn:feature_class":"P",
    "gn:feature_code":"PPL",
    "gn:name":"Yuziwu",
    "gn:population":0,
    "gn:timezone":"Asia/Shanghai",
    "iso:country":"CN",
    "name:zho_x_preferred":[
        "\u96e8\u5b5c\u96fe"
    ],
    "wof:name":"Yuziwu",
    "wof:placetype":"locality"
},
  "geometry": {"coordinates":[102.807,24.699],"type":"Point"}
}