{
  "type": "Feature",
  "properties": {
    "gn:admin1_code":"24",
    "gn:asciiname":"Jiuliwan",
    "gn:country_code":"CN",
    "gn:dem":1436,
    "gn:feature_class":"P",
    "gn:feature_code":"PPL",
    "gn:name":"Jiuliwan",
    "gn:population":0,
    "gn:timezone":"Asia/Shanghai",
    "iso:country":"CN",
    "name:und_x_variant":[
        "Chiu-li-wan",
        "Jiuliwan"
    ],
    "name:zho_x_preferred":[
        "\u4e5d\u91cc\u6e7e"
    ],
    "wof:name":"Jiuliwan",
    "wof:placetype":"locality"
},
  "geometry": {"coordinates":[111.50552999999999,37.41904],"type":"Point"}
}