{
  "type": "Feature",
  "properties": {
    "gn:admin1_code":"16.0",
    "gn:asciiname":"Xiadizhu",
    "gn:country_code":"CN",
    "gn:dem":191,
    "gn:feature_class":"P",
    "gn:feature_code":"PPL",
    "gn:name":"Xiadizhu",
    "gn:population":0,
    "gn:timezone":"Asia/Shanghai",
    "iso:country":"CN",
    "name:zho_x_preferred":[
        "\u4e0b\u5730\u7af9"
    ],
    "wof:name":"Xiadizhu",
    "wof:placetype":"locality"
},
  "geometry": {"coordinates":[108.199,24.3226],"type":"Point"}
}