{
  "type": "Feature",
  "properties": {
    "gn:admin1_code":"8.0",
    "gn:asciiname":"Leyuancun",
    "gn:country_code":"CN",
    "gn:dem":144,
    "gn:feature_class":"P",
    "gn:feature_code":"PPL",
    "gn:name":"Leyuancun",
    "gn:population":0,
    "gn:timezone":"Asia/Shanghai",
    "iso:country":"CN",
    "name:zho_x_preferred":[
        "\u4e50\u56ed\u6751"
    ],
    "wof:name":"Leyuancun",
    "wof:placetype":"locality"
},
  "geometry": {"coordinates":[125.12564999999999,45.86336],"type":"Point"}
}