{
  "type": "Feature",
  "properties": {
    "gn:admin1_code":"11.0",
    "gn:asciiname":"Xilahu",
    "gn:country_code":"CN",
    "gn:dem":555,
    "gn:feature_class":"P",
    "gn:feature_code":"PPL",
    "gn:name":"Xilahu",
    "gn:population":0,
    "gn:timezone":"Asia/Shanghai",
    "iso:country":"CN",
    "name:zho_x_preferred":[
        "\u7ec6\u62c9\u6e56"
    ],
    "wof:name":"Xilahu",
    "wof:placetype":"locality"
},
  "geometry": {"coordinates":[109.30117,29.01759],"type":"Point"}
}