{
  "type": "Feature",
  "properties": {
    "gn:admin1_code":"25.0",
    "gn:asciiname":"Qianpanjia",
    "gn:country_code":"CN",
    "gn:dem":115,
    "gn:feature_class":"P",
    "gn:feature_code":"PPL",
    "gn:name":"Qianpanjia",
    "gn:population":0,
    "gn:timezone":"Asia/Shanghai",
    "iso:country":"CN",
    "name:zho_x_preferred":[
        "\u524d\u6f58\u5bb6"
    ],
    "wof:name":"Qianpanjia",
    "wof:placetype":"locality"
},
  "geometry": {"coordinates":[120.15419,36.95357],"type":"Point"}
}