{
  "type": "Feature",
  "properties": {
    "gn:admin1_code":"26.0",
    "gn:asciiname":"Dongcaocun",
    "gn:country_code":"CN",
    "gn:dem":679,
    "gn:feature_class":"P",
    "gn:feature_code":"PPL",
    "gn:name":"Dongcaocun",
    "gn:population":0,
    "gn:timezone":"Asia/Shanghai",
    "iso:country":"CN",
    "name:zho_x_preferred":[
        "\u4e1c\u66f9\u6751"
    ],
    "wof:name":"Dongcaocun",
    "wof:placetype":"locality"
},
  "geometry": {"coordinates":[109.45631000000002,34.16552],"type":"Point"}
}