{
  "type": "Feature",
  "properties": {
    "gn:admin1_code":"26.0",
    "gn:asciiname":"Songjiashan",
    "gn:country_code":"CN",
    "gn:dem":1317,
    "gn:feature_class":"P",
    "gn:feature_code":"PPL",
    "gn:name":"Songjiashan",
    "gn:population":0,
    "gn:timezone":"Asia/Shanghai",
    "iso:country":"CN",
    "name:und_x_variant":[
        "\u5b8b\u5bb6\u5c71"
    ],
    "wof:name":"Songjiashan",
    "wof:placetype":"locality"
},
  "geometry": {"coordinates":[106.65792,33.85736],"type":"Point"}
}