{
  "type": "Feature",
  "properties": {
    "gn:admin1_code":"14.0",
    "gn:asciiname":"Kabu",
    "gn:country_code":"CN",
    "gn:dem":3090,
    "gn:feature_class":"P",
    "gn:feature_code":"PPL",
    "gn:name":"Kabu",
    "gn:population":0,
    "gn:timezone":"Asia/Urumqi",
    "iso:country":"CN",
    "name:zho_x_preferred":[
        "\u5361\u5e03"
    ],
    "wof:name":"Kabu",
    "wof:placetype":"locality"
},
  "geometry": {"coordinates":[94.19523,29.75609],"type":"Point"}
}