{
  "type": "Feature",
  "properties": {
    "gn:admin1_code":"25.0",
    "gn:asciiname":"Xisonggezhuang",
    "gn:cc2":"CN",
    "gn:country_code":"CN",
    "gn:dem":39,
    "gn:feature_class":"P",
    "gn:feature_code":"PPL",
    "gn:name":"Xisonggezhuang",
    "gn:population":0,
    "gn:timezone":"Asia/Shanghai",
    "iso:country":"CN",
    "name:zho_x_preferred":[
        "\u897f\u5b8b\u6208\u5e84"
    ],
    "wof:name":"Xisonggezhuang",
    "wof:placetype":"locality"
},
  "geometry": {"coordinates":[119.81,36.23345],"type":"Point"}
}