{
  "type": "Feature",
  "properties": {
    "gn:admin1_code":"5.0",
    "gn:asciiname":"Xifengku",
    "gn:country_code":"CN",
    "gn:dem":150,
    "gn:feature_class":"P",
    "gn:feature_code":"PPL",
    "gn:name":"Xifengku",
    "gn:population":0,
    "gn:timezone":"Asia/Shanghai",
    "iso:country":"CN",
    "name:zho_x_preferred":[
        "\u897f\u4e30\u5e93"
    ],
    "wof:name":"Xifengku",
    "wof:placetype":"locality"
},
  "geometry": {"coordinates":[123.25396000000001,44.28888],"type":"Point"}
}