{
  "type": "Feature",
  "properties": {
    "gn:admin1_code":"20.0",
    "gn:asciiname":"Shangfengyibu",
    "gn:country_code":"CN",
    "gn:dem":311,
    "gn:feature_class":"P",
    "gn:feature_code":"PPL",
    "gn:name":"Shangfengyibu",
    "gn:population":0,
    "gn:timezone":"Asia/Shanghai",
    "iso:country":"CN",
    "name:zho_x_preferred":[
        "\u4e0a\u51af\u4e49\u5821"
    ],
    "wof:name":"Shangfengyibu",
    "wof:placetype":"locality"
},
  "geometry": {"coordinates":[123.80276000000001,48.41411],"type":"Point"}
}