{
  "type": "Feature",
  "properties": {
    "gn:admin1_code":"26.0",
    "gn:asciiname":"Shenxianyan",
    "gn:country_code":"CN",
    "gn:dem":655,
    "gn:feature_class":"P",
    "gn:feature_code":"PPL",
    "gn:name":"Shenxianyan",
    "gn:population":0,
    "gn:timezone":"Asia/Shanghai",
    "iso:country":"CN",
    "name:zho_x_preferred":[
        "\u795e\u4ed9\u5ca9"
    ],
    "wof:name":"Shenxianyan",
    "wof:placetype":"locality"
},
  "geometry": {"coordinates":[107.48236,32.80775999999999],"type":"Point"}
}