{
  "type": "Feature",
  "properties": {
    "gn:admin1_code":"16.0",
    "gn:asciiname":"Naya",
    "gn:country_code":"CN",
    "gn:dem":255,
    "gn:feature_class":"P",
    "gn:feature_code":"PPL",
    "gn:name":"Naya",
    "gn:population":0,
    "gn:timezone":"Asia/Shanghai",
    "iso:country":"CN",
    "name:ceb_x_preferred":[
        "Naya"
    ],
    "name:deu_x_preferred":[
        "Naya"
    ],
    "name:fra_x_preferred":[
        "Naya"
    ],
    "name:ita_x_preferred":[
        "Naya"
    ],
    "name:rus_x_preferred":[
        "\u041d\u0430\u0439\u044f"
    ],
    "name:spa_x_preferred":[
        "Naya"
    ],
    "name:swe_x_preferred":[
        "Naya"
    ],
    "name:zho_x_preferred":[
        "\u90a3\u96c5"
    ],
    "wof:name":"Naya",
    "wof:placetype":"locality"
},
  "geometry": {"coordinates":[106.929,22.6632],"type":"Point"}
}