{
  "type": "Feature",
  "properties": {
    "gn:admin1_code":"3",
    "gn:asciiname":"Guizibei",
    "gn:country_code":"CN",
    "gn:dem":185,
    "gn:feature_class":"P",
    "gn:feature_code":"PPL",
    "gn:name":"Guizibei",
    "gn:population":0,
    "gn:timezone":"Asia/Shanghai",
    "iso:country":"CN",
    "name:zho_x_preferred":[
        "\u9f9f\u5b50\u80cc"
    ],
    "wof:name":"Guizibei",
    "wof:placetype":"locality"
},
  "geometry": {"coordinates":[114.355,26.2116],"type":"Point"}
}