{
  "type": "Feature",
  "properties": {
    "gn:admin1_code":"3.0",
    "gn:asciiname":"Luanshi",
    "gn:country_code":"CN",
    "gn:dem":189,
    "gn:feature_class":"P",
    "gn:feature_code":"PPL",
    "gn:name":"Luanshi",
    "gn:population":0,
    "gn:timezone":"Asia/Shanghai",
    "iso:country":"CN",
    "name:und_x_variant":[
        "\u4e71\u77f3"
    ],
    "wof:name":"Luanshi",
    "wof:placetype":"locality"
},
  "geometry": {"coordinates":[115.75806,25.4954],"type":"Point"}
}