{
  "type": "Feature",
  "properties": {
    "gn:admin1_code":"32.0",
    "gn:asciiname":"Sanjiadian",
    "gn:country_code":"CN",
    "gn:dem":2351,
    "gn:feature_class":"P",
    "gn:feature_code":"PPL",
    "gn:name":"Sanjiadian",
    "gn:population":0,
    "gn:timezone":"Asia/Shanghai",
    "iso:country":"CN",
    "name:zho_x_preferred":[
        "\u4e09\u5bb6\u5e97"
    ],
    "wof:name":"Sanjiadian",
    "wof:placetype":"locality"
},
  "geometry": {"coordinates":[102.303,28.9471],"type":"Point"}
}