{
  "type": "Feature",
  "properties": {
    "gn:admin1_code":"10",
    "gn:asciiname":"Beiweiquan",
    "gn:country_code":"CN",
    "gn:dem":603,
    "gn:feature_class":"P",
    "gn:feature_code":"PPL",
    "gn:name":"Beiweiquan",
    "gn:population":0,
    "gn:timezone":"Asia/Shanghai",
    "iso:country":"CN",
    "name:zho_x_preferred":[
        "\u5317\u82c7\u6cc9"
    ],
    "wof:name":"Beiweiquan",
    "wof:placetype":"locality"
},
  "geometry": {"coordinates":[114.005,36.8561],"type":"Point"}
}