{
  "type": "Feature",
  "properties": {
    "gn:admin1_code":"24",
    "gn:asciiname":"Donghui",
    "gn:country_code":"CN",
    "gn:dem":1027,
    "gn:feature_class":"P",
    "gn:feature_code":"PPL",
    "gn:name":"Donghui",
    "gn:population":0,
    "gn:timezone":"Asia/Shanghai",
    "iso:country":"CN",
    "name:zho_x_preferred":[
        "\u4e1c\u6c47"
    ],
    "wof:name":"Donghui",
    "wof:placetype":"locality"
},
  "geometry": {"coordinates":[112.99267999999999,37.07742],"type":"Point"}
}