{
  "type": "Feature",
  "properties": {
    "gn:admin1_code":"11",
    "gn:asciiname":"Sifen",
    "gn:cc2":"CN",
    "gn:country_code":"CN",
    "gn:dem":61,
    "gn:feature_class":"P",
    "gn:feature_code":"PPL",
    "gn:name":"Sifen",
    "gn:population":0,
    "gn:timezone":"Asia/Shanghai",
    "iso:country":"CN",
    "name:und_x_variant":[
        "Szefenpu",
        "Ssu-fen",
        "Sifen"
    ],
    "wof:name":"Sifen",
    "wof:placetype":"locality"
},
  "geometry": {"coordinates":[113.48778,27.52889],"type":"Point"}
}