{
  "type": "Feature",
  "properties": {
    "gn:admin1_code":"26.0",
    "gn:asciiname":"Qinghekou",
    "gn:country_code":"CN",
    "gn:dem":600,
    "gn:feature_class":"P",
    "gn:feature_code":"PPL",
    "gn:name":"Qinghekou",
    "gn:population":0,
    "gn:timezone":"Asia/Shanghai",
    "iso:country":"CN",
    "name:und_x_variant":[
        "\u9752\u6cb3\u53e3"
    ],
    "wof:name":"Qinghekou",
    "wof:placetype":"locality"
},
  "geometry": {"coordinates":[106.01286,32.96550999999999],"type":"Point"}
}