{
  "type": "Feature",
  "properties": {
    "gn:admin1_code":"32.0",
    "gn:asciiname":"Qiaomu",
    "gn:country_code":"CN",
    "gn:dem":360,
    "gn:feature_class":"P",
    "gn:feature_code":"PPL",
    "gn:name":"Qiaomu",
    "gn:population":0,
    "gn:timezone":"Asia/Shanghai",
    "iso:country":"CN",
    "name:zho_x_preferred":[
        "\u6865\u6728"
    ],
    "wof:name":"Qiaomu",
    "wof:placetype":"locality"
},
  "geometry": {"coordinates":[105.54600000000001,30.7224],"type":"Point"}
}