{
  "type": "Feature",
  "properties": {
    "gn:admin1_code":"10",
    "gn:asciiname":"Guanzhuang",
    "gn:cc2":"CN",
    "gn:country_code":"CN",
    "gn:dem":65,
    "gn:feature_class":"P",
    "gn:feature_code":"PPL",
    "gn:name":"Guanzhuang",
    "gn:population":0,
    "gn:timezone":"Asia/Shanghai",
    "iso:country":"CN",
    "name:ceb_x_preferred":[
        "Guanzhuang"
    ],
    "name:swe_x_preferred":[
        "Guanzhuang"
    ],
    "name:und_x_variant":[
        "Kuan-chuang",
        "Kuan-chuang-chen"
    ],
    "name:zho_x_preferred":[
        "\u5b98\u5e84\u9547"
    ],
    "wof:name":"Guanzhuang",
    "wof:placetype":"locality"
},
  "geometry": {"coordinates":[114.545,37.19139000000001],"type":"Point"}
}