{
  "type": "Feature",
  "properties": {
    "gn:admin1_code":"30.0",
    "gn:asciiname":"Rongshukeng",
    "gn:country_code":"CN",
    "gn:dem":338,
    "gn:feature_class":"P",
    "gn:feature_code":"PPL",
    "gn:name":"Rongshukeng",
    "gn:population":0,
    "gn:timezone":"Asia/Shanghai",
    "iso:country":"CN",
    "name:zho_x_preferred":[
        "Rongshukeng"
    ],
    "name:zho_x_variant":[
        "\u6995\u6811\u5751"
    ],
    "wof:name":"Rongshukeng",
    "wof:placetype":"locality"
},
  "geometry": {"coordinates":[114.11354,24.59155],"type":"Point"}
}