{
  "type": "Feature",
  "properties": {
    "gn:admin1_code":"31.0",
    "gn:asciiname":"Liuqiu",
    "gn:country_code":"CN",
    "gn:dem":63,
    "gn:feature_class":"P",
    "gn:feature_code":"PPL",
    "gn:name":"Liuqiu",
    "gn:population":0,
    "gn:timezone":"Asia/Shanghai",
    "iso:country":"CN",
    "name:zho_x_preferred":[
        "\u7409\u7403"
    ],
    "wof:name":"Liuqiu",
    "wof:placetype":"locality"
},
  "geometry": {"coordinates":[110.46223999999999,19.68924],"type":"Point"}
}