{
  "type": "Feature",
  "properties": {
    "gn:admin1_code":"32.0",
    "gn:asciiname":"Xifang Puzi",
    "gn:country_code":"CN",
    "gn:dem":1903,
    "gn:feature_class":"P",
    "gn:feature_code":"PPL",
    "gn:name":"Xifang Puzi",
    "gn:population":0,
    "gn:timezone":"Asia/Shanghai",
    "iso:country":"CN",
    "name:zho_x_preferred":[
        "\u897f\u653e\u666e\u5b50"
    ],
    "wof:name":"Xifang Puzi",
    "wof:placetype":"locality"
},
  "geometry": {"coordinates":[102.45807000000001,28.55422],"type":"Point"}
}