{
  "type": "Feature",
  "properties": {
    "gn:admin1_code":"32.0",
    "gn:asciiname":"Xiaowuma",
    "gn:country_code":"CN",
    "gn:dem":1737,
    "gn:feature_class":"P",
    "gn:feature_code":"PPL",
    "gn:name":"Xiaowuma",
    "gn:population":0,
    "gn:timezone":"Asia/Shanghai",
    "iso:country":"CN",
    "name:zho_x_preferred":[
        "\u5c0f\u4e4c\u9a6c"
    ],
    "wof:name":"Xiaowuma",
    "wof:placetype":"locality"
},
  "geometry": {"coordinates":[102.483,29.4984],"type":"Point"}
}