{
  "type": "Feature",
  "properties": {
    "gn:admin1_code":"2.0",
    "gn:asciiname":"Daicun",
    "gn:country_code":"CN",
    "gn:dem":13,
    "gn:feature_class":"P",
    "gn:feature_code":"PPLA4",
    "gn:name":"Daicun",
    "gn:population":0,
    "gn:timezone":"Asia/Shanghai",
    "iso:country":"CN",
    "name:und_x_variant":[
        "\u6234\u6751",
        "Daicun Zhen",
        "\u6234\u6751\u9547"
    ],
    "wof:name":"Daicun",
    "wof:placetype":"locality"
},
  "geometry": {"coordinates":[120.19593999999999,30.01759],"type":"Point"}
}