{
  "type": "Feature",
  "properties": {
    "gn:admin1_code":"29",
    "gn:asciiname":"Dagaozhai",
    "gn:country_code":"CN",
    "gn:dem":1187,
    "gn:feature_class":"P",
    "gn:feature_code":"PPL",
    "gn:name":"Dagaozhai",
    "gn:population":0,
    "gn:timezone":"Asia/Shanghai",
    "iso:country":"CN",
    "name:zho_x_preferred":[
        "\u5927\u9ad8\u5be8"
    ],
    "wof:name":"Dagaozhai",
    "wof:placetype":"locality"
},
  "geometry": {"coordinates":[103.41200000000001,24.0713],"type":"Point"}
}