{
  "type": "Feature",
  "properties": {
    "gn:admin1_code":"10",
    "gn:asciiname":"Boluoshu",
    "gn:country_code":"CN",
    "gn:dem":333,
    "gn:feature_class":"P",
    "gn:feature_code":"PPL",
    "gn:name":"Boluoshu",
    "gn:population":0,
    "gn:timezone":"Asia/Shanghai",
    "iso:country":"CN",
    "name:zho_x_preferred":[
        "\u6872\u6924\u6811"
    ],
    "wof:name":"Boluoshu",
    "wof:placetype":"locality"
},
  "geometry": {"coordinates":[117.9327,40.70448],"type":"Point"}
}