{
  "type": "Feature",
  "properties": {
    "gn:admin1_code":"25",
    "gn:asciiname":"Xizhongyu",
    "gn:country_code":"CN",
    "gn:dem":187,
    "gn:feature_class":"P",
    "gn:feature_code":"PPL",
    "gn:name":"Xizhongyu",
    "gn:population":0,
    "gn:timezone":"Asia/Shanghai",
    "iso:country":"CN",
    "name:zho_x_preferred":[
        "\u897f\u4e2d\u5cea"
    ],
    "wof:name":"Xizhongyu",
    "wof:placetype":"locality"
},
  "geometry": {"coordinates":[118.511,35.8717],"type":"Point"}
}