{
  "type": "Feature",
  "properties": {
    "gn:admin1_code":"30",
    "gn:asciiname":"Wudiling",
    "gn:country_code":"CN",
    "gn:dem":451,
    "gn:feature_class":"P",
    "gn:feature_code":"PPL",
    "gn:name":"Wudiling",
    "gn:population":0,
    "gn:timezone":"Asia/Shanghai",
    "iso:country":"CN",
    "name:zho_x_preferred":[
        "\u5c4b\u5730\u5cad"
    ],
    "wof:name":"Wudiling",
    "wof:placetype":"locality"
},
  "geometry": {"coordinates":[111.42694,22.18515],"type":"Point"}
}