{
  "type": "Feature",
  "properties": {
    "gn:admin1_code":"32.0",
    "gn:asciiname":"Zhongjiashan",
    "gn:country_code":"CN",
    "gn:dem":387,
    "gn:feature_class":"P",
    "gn:feature_code":"PPL",
    "gn:name":"Zhongjiashan",
    "gn:population":0,
    "gn:timezone":"Asia/Shanghai",
    "iso:country":"CN",
    "name:zho_x_preferred":[
        "\u949f\u5bb6\u5c71"
    ],
    "wof:name":"Zhongjiashan",
    "wof:placetype":"locality"
},
  "geometry": {"coordinates":[104.736,28.9603],"type":"Point"}
}