{
  "type": "Feature",
  "properties": {
    "gn:admin1_code":"9",
    "gn:asciiname":"Qianxiaotun",
    "gn:country_code":"CN",
    "gn:dem":49,
    "gn:feature_class":"P",
    "gn:feature_code":"PPL",
    "gn:name":"Qianxiaotun",
    "gn:population":0,
    "gn:timezone":"Asia/Shanghai",
    "iso:country":"CN",
    "name:zho_x_preferred":[
        "\u524d\u5c0f\u5c6f"
    ],
    "wof:name":"Qianxiaotun",
    "wof:placetype":"locality"
},
  "geometry": {"coordinates":[115.44107,35.76988],"type":"Point"}
}