{
  "type": "Feature",
  "properties": {
    "gn:admin1_code":"9.0",
    "gn:asciiname":"Liujia Chengou",
    "gn:country_code":"CN",
    "gn:dem":169,
    "gn:feature_class":"P",
    "gn:feature_code":"PPL",
    "gn:name":"Liujia Chengou",
    "gn:population":0,
    "gn:timezone":"Asia/Shanghai",
    "iso:country":"CN",
    "name:zho_x_preferred":[
        "\u5218\u5bb6\u9648\u6c9f"
    ],
    "wof:name":"Liujia Chengou",
    "wof:placetype":"locality"
},
  "geometry": {"coordinates":[113.18736,32.50499],"type":"Point"}
}