{
  "type": "Feature",
  "properties": {
    "gn:admin1_code":"24.0",
    "gn:asciiname":"Peishe",
    "gn:country_code":"CN",
    "gn:dem":521,
    "gn:feature_class":"P",
    "gn:feature_code":"PPL",
    "gn:name":"Peishe",
    "gn:population":0,
    "gn:timezone":"Asia/Shanghai",
    "iso:country":"CN",
    "name:und_x_variant":[
        "\u88f4\u793e"
    ],
    "wof:name":"Peishe",
    "wof:placetype":"locality"
},
  "geometry": {"coordinates":[111.12536,35.50147],"type":"Point"}
}