{
  "type": "Feature",
  "properties": {
    "gn:admin1_code":"16.0",
    "gn:asciiname":"Gong'ai",
    "gn:country_code":"CN",
    "gn:dem":652,
    "gn:feature_class":"P",
    "gn:feature_code":"PPL",
    "gn:name":"Gong\u2019ai",
    "gn:population":0,
    "gn:timezone":"Asia/Shanghai",
    "iso:country":"CN",
    "name:und_x_variant":[
        "Gong\u2019ai"
    ],
    "name:zho_x_preferred":[
        "\u516c\u7231"
    ],
    "wof:name":"Gong'ai",
    "wof:placetype":"locality"
},
  "geometry": {"coordinates":[107.011,24.2558],"type":"Point"}
}