{
  "type": "Feature",
  "properties": {
    "gn:admin1_code":"5.0",
    "gn:asciiname":"Hailantun",
    "gn:country_code":"CN",
    "gn:dem":224,
    "gn:feature_class":"P",
    "gn:feature_code":"PPL",
    "gn:name":"Hailantun",
    "gn:population":0,
    "gn:timezone":"Asia/Shanghai",
    "iso:country":"CN",
    "name:und_x_variant":[
        "\u6d77\u5170\u5c6f"
    ],
    "wof:name":"Hailantun",
    "wof:placetype":"locality"
},
  "geometry": {"coordinates":[129.45410000000001,42.81044],"type":"Point"}
}