{
  "type": "Feature",
  "properties": {
    "gn:admin1_code":"10",
    "gn:asciiname":"Shenjing",
    "gn:cc2":"CN",
    "gn:country_code":"CN",
    "gn:dem":1120,
    "gn:feature_class":"P",
    "gn:feature_code":"PPL",
    "gn:name":"Shenjing",
    "gn:population":0,
    "gn:timezone":"Asia/Shanghai",
    "iso:country":"CN",
    "name:und_x_variant":[
        "Shen-ching-p\u2019u",
        "Shen-ching-pao",
        "Shenjingbu",
        "Shen-ching",
        "Shenjing"
    ],
    "wof:name":"Shenjing",
    "wof:placetype":"locality"
},
  "geometry": {"coordinates":[114.8275,40.39889],"type":"Point"}
}