{
  "type": "Feature",
  "properties": {
    "gn:admin1_code":"5.0",
    "gn:asciiname":"Changxindong",
    "gn:country_code":"CN",
    "gn:dem":146,
    "gn:feature_class":"P",
    "gn:feature_code":"PPL",
    "gn:name":"Changxindong",
    "gn:population":0,
    "gn:timezone":"Asia/Shanghai",
    "iso:country":"CN",
    "name:zho_x_preferred":[
        "\u660c\u65b0\u6d1e"
    ],
    "wof:name":"Changxindong",
    "wof:placetype":"locality"
},
  "geometry": {"coordinates":[129.80535,42.86727],"type":"Point"}
}