{
  "type": "Feature",
  "properties": {
    "gn:admin1_code":"30.0",
    "gn:asciiname":"Lashuyuan",
    "gn:country_code":"CN",
    "gn:dem":171,
    "gn:feature_class":"P",
    "gn:feature_code":"PPL",
    "gn:name":"Lashuyuan",
    "gn:population":0,
    "gn:timezone":"Asia/Shanghai",
    "iso:country":"CN",
    "name:zho_x_preferred":[
        "\u814a\u6811\u56ed"
    ],
    "wof:name":"Lashuyuan",
    "wof:placetype":"locality"
},
  "geometry": {"coordinates":[114.59705,25.23317],"type":"Point"}
}