{
  "type": "Feature",
  "properties": {
    "gn:admin1_code":"32.0",
    "gn:asciiname":"Ese",
    "gn:country_code":"CN",
    "gn:dem":3261,
    "gn:feature_class":"P",
    "gn:feature_code":"PPL",
    "gn:name":"Ese",
    "gn:population":0,
    "gn:timezone":"Asia/Shanghai",
    "iso:country":"CN",
    "name:zho_x_preferred":[
        "\u4fc4\u8272"
    ],
    "wof:name":"Ese",
    "wof:placetype":"locality"
},
  "geometry": {"coordinates":[100.318,31.0463],"type":"Point"}
}