{
  "type": "Feature",
  "properties": {
    "gn:admin1_code":"30.0",
    "gn:asciiname":"Bianxin",
    "gn:country_code":"CN",
    "gn:dem":2,
    "gn:feature_class":"P",
    "gn:feature_code":"PPL",
    "gn:name":"Bianxin",
    "gn:population":0,
    "gn:timezone":"Asia/Shanghai",
    "iso:country":"CN",
    "name:zho_x_preferred":[
        "\u908a\u65b0"
    ],
    "wof:name":"Bianxin",
    "wof:placetype":"locality"
},
  "geometry": {"coordinates":[112.58548999999999,22.34424],"type":"Point"}
}