{
  "type": "Feature",
  "properties": {
    "gn:admin1_code":"14",
    "gn:asciiname":"Gacai",
    "gn:country_code":"CN",
    "gn:dem":3699,
    "gn:feature_class":"P",
    "gn:feature_code":"PPL",
    "gn:name":"Gacai",
    "gn:population":0,
    "gn:timezone":"Asia/Urumqi",
    "iso:country":"CN",
    "name:bod_x_preferred":[
        "\u0f51\u0f42\u0f60\u0f0b\u0f5a\u0f63"
    ],
    "wof:name":"Gacai",
    "wof:placetype":"locality"
},
  "geometry": {"coordinates":[91.10326999999999,29.18379],"type":"Point"}
}