{
  "type": "Feature",
  "properties": {
    "gn:admin1_code":"11.0",
    "gn:asciiname":"Houzikou",
    "gn:country_code":"CN",
    "gn:dem":29,
    "gn:feature_class":"P",
    "gn:feature_code":"PPL",
    "gn:name":"Houzikou",
    "gn:population":0,
    "gn:timezone":"Asia/Shanghai",
    "iso:country":"CN",
    "name:zho_x_preferred":[
        "\u7334\u5b50\u53e3"
    ],
    "wof:name":"Houzikou",
    "wof:placetype":"locality"
},
  "geometry": {"coordinates":[112.52946,29.12065],"type":"Point"}
}