{
  "type": "Feature",
  "properties": {
    "gn:admin1_code":"29",
    "gn:asciiname":"Xiaochong",
    "gn:country_code":"CN",
    "gn:dem":1784,
    "gn:feature_class":"P",
    "gn:feature_code":"PPL",
    "gn:name":"Xiaochong",
    "gn:population":0,
    "gn:timezone":"Asia/Shanghai",
    "iso:country":"CN",
    "name:zho_x_preferred":[
        "\u5c0f\u51b2"
    ],
    "wof:name":"Xiaochong",
    "wof:placetype":"locality"
},
  "geometry": {"coordinates":[102.702,24.3466],"type":"Point"}
}