{
  "type": "Feature",
  "properties": {
    "gn:admin1_code":"32.0",
    "gn:asciiname":"Changtianpu",
    "gn:country_code":"CN",
    "gn:dem":402,
    "gn:feature_class":"P",
    "gn:feature_code":"PPL",
    "gn:name":"Changtianpu",
    "gn:population":0,
    "gn:timezone":"Asia/Shanghai",
    "iso:country":"CN",
    "name:zho_x_preferred":[
        "\u5382\u7530\u94fa"
    ],
    "wof:name":"Changtianpu",
    "wof:placetype":"locality"
},
  "geometry": {"coordinates":[105.24168,29.40687],"type":"Point"}
}