{
  "type": "Feature",
  "properties": {
    "gn:admin1_code":"4.0",
    "gn:asciiname":"Jingxing",
    "gn:country_code":"CN",
    "gn:dem":3,
    "gn:feature_class":"P",
    "gn:feature_code":"PPL",
    "gn:name":"Jingxing",
    "gn:population":0,
    "gn:timezone":"Asia/Shanghai",
    "iso:country":"CN",
    "name:ceb_x_preferred":[
        "Jingxing"
    ],
    "name:deu_x_preferred":[
        "Jingxing"
    ],
    "name:rus_x_preferred":[
        "\u0426\u0437\u0438\u043d\u0441\u0438\u043d"
    ],
    "name:zho_x_preferred":[
        "\u9756\u5174"
    ],
    "wof:name":"Jingxing",
    "wof:placetype":"locality"
},
  "geometry": {"coordinates":[120.50467999999999,32.09359],"type":"Point"}
}