{
  "type": "Feature",
  "properties": {
    "gn:admin1_code":"15.0",
    "gn:asciiname":"Baicao",
    "gn:country_code":"CN",
    "gn:dem":1948,
    "gn:feature_class":"P",
    "gn:feature_code":"PPL",
    "gn:name":"Baicao",
    "gn:population":0,
    "gn:timezone":"Asia/Shanghai",
    "iso:country":"CN",
    "name:zho_x_preferred":[
        "\u767d\u8349"
    ],
    "wof:name":"Baicao",
    "wof:placetype":"locality"
},
  "geometry": {"coordinates":[104.99348999999999,33.86348],"type":"Point"}
}