{
  "type": "Feature",
  "properties": {
    "gn:admin1_code":"15.0",
    "gn:asciiname":"Tianqiao Daban",
    "gn:country_code":"CN",
    "gn:dem":3049,
    "gn:feature_class":"P",
    "gn:feature_code":"PPL",
    "gn:name":"Tianqiao Daban",
    "gn:population":0,
    "gn:timezone":"Asia/Shanghai",
    "iso:country":"CN",
    "name:zho_x_preferred":[
        "\u5929\u6865\u5927\u5742"
    ],
    "wof:name":"Tianqiao Daban",
    "wof:placetype":"locality"
},
  "geometry": {"coordinates":[101.94,37.9297],"type":"Point"}
}