{
  "type": "Feature",
  "properties": {
    "gn:admin1_code":"4.0",
    "gn:asciiname":"Laobadai",
    "gn:country_code":"CN",
    "gn:dem":4,
    "gn:feature_class":"P",
    "gn:feature_code":"PPL",
    "gn:name":"Laobadai",
    "gn:population":0,
    "gn:timezone":"Asia/Shanghai",
    "iso:country":"CN",
    "name:zho_x_preferred":[
        "\u8001\u575d\u57ed"
    ],
    "wof:name":"Laobadai",
    "wof:placetype":"locality"
},
  "geometry": {"coordinates":[119.85809999999999,32.17385],"type":"Point"}
}