{
  "type": "Feature",
  "properties": {
    "gn:admin1_code":"19.0",
    "gn:asciiname":"Zhoutuncun",
    "gn:country_code":"CN",
    "gn:dem":141,
    "gn:feature_class":"P",
    "gn:feature_code":"PPL",
    "gn:name":"Zhoutuncun",
    "gn:population":0,
    "gn:timezone":"Asia/Shanghai",
    "iso:country":"CN",
    "name:zho_x_preferred":[
        "\u5468\u5c6f\u6751"
    ],
    "wof:name":"Zhoutuncun",
    "wof:placetype":"locality"
},
  "geometry": {"coordinates":[122.15300000000001,39.7437],"type":"Point"}
}