{
  "type": "Feature",
  "properties": {
    "gn:admin1_code":"3.0",
    "gn:asciiname":"Yanyuan",
    "gn:country_code":"CN",
    "gn:dem":222,
    "gn:feature_class":"P",
    "gn:feature_code":"PPL",
    "gn:name":"Yanyuan",
    "gn:population":0,
    "gn:timezone":"Asia/Shanghai",
    "iso:country":"CN",
    "name:und_x_variant":[
        "\u70df\u56ed"
    ],
    "wof:name":"Yanyuan",
    "wof:placetype":"locality"
},
  "geometry": {"coordinates":[114.81265,24.92692000000001],"type":"Point"}
}