{
  "type": "Feature",
  "properties": {
    "gn:admin1_code":"4.0",
    "gn:asciiname":"Fenglezhuang",
    "gn:country_code":"CN",
    "gn:dem":5,
    "gn:feature_class":"P",
    "gn:feature_code":"PPL",
    "gn:name":"Fenglezhuang",
    "gn:population":0,
    "gn:timezone":"Asia/Shanghai",
    "iso:country":"CN",
    "name:und_x_variant":[
        "\u4e30\u4e50\u5e84"
    ],
    "name:zho_x_preferred":[
        "\u4e30\u4e50\u5e84"
    ],
    "wof:name":"Fenglezhuang",
    "wof:placetype":"locality"
},
  "geometry": {"coordinates":[120.68420999999999,32.97725],"type":"Point"}
}