{
  "type": "Feature",
  "properties": {
    "gn:admin1_code":"11.0",
    "gn:asciiname":"Pipatang",
    "gn:country_code":"CN",
    "gn:dem":128,
    "gn:feature_class":"P",
    "gn:feature_code":"PPL",
    "gn:name":"Pipatang",
    "gn:population":0,
    "gn:timezone":"Asia/Shanghai",
    "iso:country":"CN",
    "name:zho_x_preferred":[
        "\u6787\u6777\u5858"
    ],
    "wof:name":"Pipatang",
    "wof:placetype":"locality"
},
  "geometry": {"coordinates":[112.20878,28.05241],"type":"Point"}
}