{
  "type": "Feature",
  "properties": {
    "gn:admin1_code":"15.0",
    "gn:asciiname":"Muxihe",
    "gn:country_code":"CN",
    "gn:dem":3597,
    "gn:feature_class":"P",
    "gn:feature_code":"PPLA4",
    "gn:name":"Muxihe",
    "gn:population":0,
    "gn:timezone":"Asia/Shanghai",
    "iso:country":"CN",
    "name:und_x_variant":[
        "Muxihe Xiang"
    ],
    "name:zho_x_preferred":[
        "\u6728\u897f\u5408"
    ],
    "name:zho_x_variant":[
        "\u6728\u897f\u5408\u4e61"
    ],
    "wof:name":"Muxihe",
    "wof:placetype":"locality"
},
  "geometry": {"coordinates":[101.24533,33.7572],"type":"Point"}
}