{
  "type": "Feature",
  "properties": {
    "gn:admin1_code":"25",
    "gn:asciiname":"Hezhuang",
    "gn:country_code":"CN",
    "gn:dem":23,
    "gn:feature_class":"P",
    "gn:feature_code":"PPL",
    "gn:name":"Hezhuang",
    "gn:population":0,
    "gn:timezone":"Asia/Shanghai",
    "iso:country":"CN",
    "name:ceb_x_preferred":[
        "Hezhuang"
    ],
    "name:swe_x_preferred":[
        "Hezhuang"
    ],
    "name:zho_x_preferred":[
        "\u4f55\u5e84"
    ],
    "wof:name":"Hezhuang",
    "wof:placetype":"locality"
},
  "geometry": {"coordinates":[116.583,37.1554],"type":"Point"}
}