{
  "type": "Feature",
  "properties": {
    "gn:admin1_code":"14.0",
    "gn:asciiname":"Xiaya Dongcun",
    "gn:country_code":"CN",
    "gn:dem":1094,
    "gn:feature_class":"P",
    "gn:feature_code":"PPL",
    "gn:name":"Xiaya Dongcun",
    "gn:population":0,
    "gn:timezone":"Asia/Urumqi",
    "iso:country":"CN",
    "name:zho_x_preferred":[
        "\u4e0b\u4e9a\u4e1c\u6751"
    ],
    "wof:name":"Xiaya Dongcun",
    "wof:placetype":"locality"
},
  "geometry": {"coordinates":[95.33417,29.32586],"type":"Point"}
}