{
  "type": "Feature",
  "properties": {
    "gn:admin1_code":"19.0",
    "gn:asciiname":"Shuangmiaozi",
    "gn:country_code":"CN",
    "gn:dem":412,
    "gn:feature_class":"P",
    "gn:feature_code":"PPL",
    "gn:name":"Shuangmiaozi",
    "gn:population":0,
    "gn:timezone":"Asia/Shanghai",
    "iso:country":"CN",
    "name:und_x_variant":[
        "\u53cc\u5e99\u5b50"
    ],
    "name:zho_x_preferred":[
        "\u53cc\u5e99\u5b50"
    ],
    "wof:name":"Shuangmiaozi",
    "wof:placetype":"locality"
},
  "geometry": {"coordinates":[121.22356000000001,41.91527],"type":"Point"}
}