{
  "type": "Feature",
  "properties": {
    "gn:admin1_code":"32.0",
    "gn:asciiname":"Xikou",
    "gn:country_code":"CN",
    "gn:dem":960,
    "gn:feature_class":"P",
    "gn:feature_code":"PPL",
    "gn:name":"Xikou",
    "gn:population":0,
    "gn:timezone":"Asia/Shanghai",
    "iso:country":"CN",
    "name:zho_x_preferred":[
        "\u6eaa\u53e3"
    ],
    "wof:name":"Xikou",
    "wof:placetype":"locality"
},
  "geometry": {"coordinates":[102.983,29.7837],"type":"Point"}
}