{
  "type": "Feature",
  "properties": {
    "gn:admin1_code":"18",
    "gn:asciiname":"Liujiashan",
    "gn:country_code":"CN",
    "gn:dem":1082,
    "gn:feature_class":"P",
    "gn:feature_code":"PPL",
    "gn:name":"Liujiashan",
    "gn:population":0,
    "gn:timezone":"Asia/Shanghai",
    "iso:country":"CN",
    "name:zho_x_preferred":[
        "\u67f3\u5bb6\u5c71"
    ],
    "wof:name":"Liujiashan",
    "wof:placetype":"locality"
},
  "geometry": {"coordinates":[106.902,27.1657],"type":"Point"}
}