{
  "type": "Feature",
  "properties": {
    "gn:admin1_code":"16.0",
    "gn:asciiname":"Mianmu",
    "gn:country_code":"CN",
    "gn:dem":340,
    "gn:feature_class":"P",
    "gn:feature_code":"PPL",
    "gn:name":"Mianmu",
    "gn:population":0,
    "gn:timezone":"Asia/Shanghai",
    "iso:country":"CN",
    "name:zho_x_preferred":[
        "\u68c9\u6728"
    ],
    "wof:name":"Mianmu",
    "wof:placetype":"locality"
},
  "geometry": {"coordinates":[108.825,24.2488],"type":"Point"}
}