{
  "type": "Feature",
  "properties": {
    "gn:admin1_code":"5.0",
    "gn:asciiname":"Jianyao",
    "gn:country_code":"CN",
    "gn:dem":160,
    "gn:feature_class":"P",
    "gn:feature_code":"PPL",
    "gn:name":"Jianyao",
    "gn:population":0,
    "gn:timezone":"Asia/Shanghai",
    "iso:country":"CN",
    "name:und_x_variant":[
        "\u78b1\u7a96"
    ],
    "wof:name":"Jianyao",
    "wof:placetype":"locality"
},
  "geometry": {"coordinates":[125.98215999999999,40.92592],"type":"Point"}
}