{
  "type": "Feature",
  "properties": {
    "gn:admin1_code":"1.0",
    "gn:asciiname":"Wangxincun",
    "gn:country_code":"CN",
    "gn:dem":21,
    "gn:feature_class":"P",
    "gn:feature_code":"PPL",
    "gn:name":"Wangxincun",
    "gn:population":0,
    "gn:timezone":"Asia/Shanghai",
    "iso:country":"CN",
    "name:zho_x_preferred":[
        "\u738b\u65b0\u6751"
    ],
    "wof:name":"Wangxincun",
    "wof:placetype":"locality"
},
  "geometry": {"coordinates":[117.37222,33.27156],"type":"Point"}
}