{
  "type": "Feature",
  "properties": {
    "gn:admin1_code":"29.0",
    "gn:asciiname":"Xiaoqianglang",
    "gn:country_code":"CN",
    "gn:dem":1828,
    "gn:feature_class":"P",
    "gn:feature_code":"PPL",
    "gn:name":"Xiaoqianglang",
    "gn:population":0,
    "gn:timezone":"Asia/Shanghai",
    "iso:country":"CN",
    "name:zho_x_preferred":[
        "\u5c0f\u7f8c\u6717"
    ],
    "wof:name":"Xiaoqianglang",
    "wof:placetype":"locality"
},
  "geometry": {"coordinates":[100.767,26.0514],"type":"Point"}
}