{
  "type": "Feature",
  "properties": {
    "gn:admin1_code":"11.0",
    "gn:asciiname":"Nanzhan",
    "gn:country_code":"CN",
    "gn:dem":43,
    "gn:feature_class":"P",
    "gn:feature_code":"PPL",
    "gn:name":"Nanzhan",
    "gn:population":0,
    "gn:timezone":"Asia/Shanghai",
    "iso:country":"CN",
    "name:und_x_variant":[
        "\u5357\u7ad9"
    ],
    "wof:name":"Nanzhan",
    "wof:placetype":"locality"
},
  "geometry": {"coordinates":[111.49854000000001,28.90018],"type":"Point"}
}