{
  "type": "Feature",
  "properties": {
    "gn:admin1_code":"9.0",
    "gn:asciiname":"Zhazigou",
    "gn:country_code":"CN",
    "gn:dem":250,
    "gn:feature_class":"P",
    "gn:feature_code":"PPL",
    "gn:name":"Zhazigou",
    "gn:population":0,
    "gn:timezone":"Asia/Shanghai",
    "iso:country":"CN",
    "name:zho_x_preferred":[
        "\u624e\u5b50\u6c9f"
    ],
    "wof:name":"Zhazigou",
    "wof:placetype":"locality"
},
  "geometry": {"coordinates":[113.30222000000001,34.50072],"type":"Point"}
}