{
  "type": "Feature",
  "properties": {
    "gn:admin1_code":"24.0",
    "gn:asciiname":"Ya'erya",
    "gn:country_code":"CN",
    "gn:dem":1411,
    "gn:feature_class":"P",
    "gn:feature_code":"PPLA4",
    "gn:name":"Ya\u2019erya",
    "gn:population":0,
    "gn:timezone":"Asia/Shanghai",
    "iso:country":"CN",
    "name:und_x_variant":[
        "Yen-yai",
        "Ya-chi-yai",
        "Yen-erh-ya",
        "Ya-erh-ya",
        "Yen-ya",
        "Yan\u2019erya",
        "Ya\u2019erya",
        "\u9e26\u513f\u5d16",
        "Ya\u2019erya Xiang",
        "\u9e26\u513f\u5d16\u4e61"
    ],
    "wof:name":"Ya'erya",
    "wof:placetype":"locality"
},
  "geometry": {"coordinates":[112.99309,39.96876],"type":"Point"}
}