{
  "type": "Feature",
  "properties": {
    "gn:admin1_code":"25",
    "gn:asciiname":"Huangqiaozhangxi",
    "gn:country_code":"CN",
    "gn:dem":8,
    "gn:feature_class":"P",
    "gn:feature_code":"PPL",
    "gn:name":"Huangqiaozhangxi",
    "gn:population":0,
    "gn:timezone":"Asia/Shanghai",
    "iso:country":"CN",
    "name:zho_x_preferred":[
        "\u9ec4\u6865\u5f20\u897f"
    ],
    "wof:name":"Huangqiaozhangxi",
    "wof:placetype":"locality"
},
  "geometry": {"coordinates":[118.947,37.0211],"type":"Point"}
}