{
  "type": "Feature",
  "properties": {
    "gn:admin1_code":"15.0",
    "gn:asciiname":"Heilongdian",
    "gn:country_code":"CN",
    "gn:dem":1995,
    "gn:feature_class":"P",
    "gn:feature_code":"PPL",
    "gn:name":"Heilongdian",
    "gn:population":0,
    "gn:timezone":"Asia/Shanghai",
    "iso:country":"CN",
    "name:zho_x_preferred":[
        "\u9ed1\u9f99\u5e97"
    ],
    "wof:name":"Heilongdian",
    "wof:placetype":"locality"
},
  "geometry": {"coordinates":[104.718,35.7055],"type":"Point"}
}