{
  "type": "Feature",
  "properties": {
    "gn:admin1_code":"4.0",
    "gn:asciiname":"Qiangwuli",
    "gn:country_code":"CN",
    "gn:dem":27,
    "gn:feature_class":"P",
    "gn:feature_code":"PPL",
    "gn:name":"Qiangwuli",
    "gn:population":0,
    "gn:timezone":"Asia/Shanghai",
    "iso:country":"CN",
    "name:zho_x_preferred":[
        "\u5899\u5c4b\u91cc"
    ],
    "wof:name":"Qiangwuli",
    "wof:placetype":"locality"
},
  "geometry": {"coordinates":[119.06202,31.26271],"type":"Point"}
}