{
  "type": "Feature",
  "properties": {
    "gn:admin1_code":"11.0",
    "gn:asciiname":"Bailiwan",
    "gn:country_code":"CN",
    "gn:dem":427,
    "gn:feature_class":"P",
    "gn:feature_code":"PPL",
    "gn:name":"Bailiwan",
    "gn:population":0,
    "gn:timezone":"Asia/Shanghai",
    "iso:country":"CN",
    "name:zho_x_preferred":[
        "\u767d\u5229\u6e7e"
    ],
    "wof:name":"Bailiwan",
    "wof:placetype":"locality"
},
  "geometry": {"coordinates":[110.29344,27.81507],"type":"Point"}
}