{
  "type": "Feature",
  "properties": {
    "gn:admin1_code":"11",
    "gn:asciiname":"Dingzi",
    "gn:cc2":"CN",
    "gn:country_code":"CN",
    "gn:dem":21,
    "gn:feature_class":"P",
    "gn:feature_code":"PPL",
    "gn:name":"Dingzi",
    "gn:population":0,
    "gn:timezone":"Asia/Shanghai",
    "iso:country":"CN",
    "name:und_x_variant":[
        "Dingziwan",
        "Dingzi"
    ],
    "wof:name":"Dingzi",
    "wof:placetype":"locality"
},
  "geometry": {"coordinates":[112.86,28.36278],"type":"Point"}
}