{
  "type": "Feature",
  "properties": {
    "gn:admin1_code":"30",
    "gn:asciiname":"Changhuan",
    "gn:country_code":"CN",
    "gn:dem":17,
    "gn:feature_class":"P",
    "gn:feature_code":"PPL",
    "gn:name":"Changhuan",
    "gn:population":0,
    "gn:timezone":"Asia/Shanghai",
    "iso:country":"CN",
    "name:und_x_variant":[
        "\u957f\u73af",
        "Changzhou"
    ],
    "name:zho_x_preferred":[
        "\u957f\u73af"
    ],
    "wof:name":"Changhuan",
    "wof:placetype":"locality"
},
  "geometry": {"coordinates":[113.33723000000001,22.45846],"type":"Point"}
}