{
  "type": "Feature",
  "properties": {
    "gn:admin1_code":"4.0",
    "gn:asciiname":"Nidang",
    "gn:country_code":"CN",
    "gn:dem":28,
    "gn:feature_class":"P",
    "gn:feature_code":"PPL",
    "gn:name":"Nidang",
    "gn:population":0,
    "gn:timezone":"Asia/Shanghai",
    "iso:country":"CN",
    "name:zho_x_preferred":[
        "\u502a\u6863"
    ],
    "wof:name":"Nidang",
    "wof:placetype":"locality"
},
  "geometry": {"coordinates":[117.851,34.1523],"type":"Point"}
}