{
  "type": "Feature",
  "properties": {
    "gn:admin1_code":"16.0",
    "gn:asciiname":"Huanggang",
    "gn:country_code":"CN",
    "gn:dem":379,
    "gn:feature_class":"P",
    "gn:feature_code":"PPL",
    "gn:name":"Huanggang",
    "gn:population":0,
    "gn:timezone":"Asia/Shanghai",
    "iso:country":"CN",
    "name:afr_x_preferred":[
        "Huanggang"
    ],
    "name:ara_x_preferred":[
        "\u0647\u0648\u0627\u0646\u063a\u0642\u0627\u0646\u063a"
    ],
    "name:bul_x_preferred":[
        "\u0425\u0443\u0430\u043d\u0433\u0430\u043d"
    ],
    "name:cdo_x_preferred":[
        "U\u00f2ng-g\u014fng"
    ],
    "name:ces_x_preferred":[
        "Chuang-kang"
    ],
    "name:dan_x_preferred":[
        "Huanggang"
    ],
    "name:deu_x_preferred":[
        "Huanggang"
    ],
    "name:eus_x_preferred":[
        "Huanggang"
    ],
    "name:fas_x_preferred":[
        "\u0647\u0648\u0627\u0646\u06af\u0627\u0646\u06af"
    ],
    "name:fin_x_preferred":[
        "Huanggang"
    ],
    "name:fra_x_preferred":[
        "Huanggang"
    ],
    "name:ita_x_preferred":[
        "Huanggang"
    ],
    "name:jpn_x_preferred":[
        "\u9ec4\u5ca1\u5e02"
    ],
    "name:kik_x_preferred":[
        "Huanggang"
    ],
    "name:kor_x_preferred":[
        "\ud669\uac15\uc2dc"
    ],
    "name:mlg_x_preferred":[
        "Huanggang"
    ],
    "name:mya_x_preferred":[
        "\u101f\u1014\u103a\u1000\u1031\u102c\u1004\u103a\u1019\u103c\u102d\u102f\u1037"
    ],
    "name:nld_x_preferred":[
        "Huanggang"
    ],
    "name:nno_x_preferred":[
        "Huanggang"
    ],
    "name:nor_x_preferred":[
        "Huanggang"
    ],
    "name:pam_x_preferred":[
        "Huanggang"
    ],
    "name:pol_x_preferred":[
        "Huanggang"
    ],
    "name:rus_x_preferred":[
        "\u0425\u0443\u0430\u043d\u0433\u0430\u043d"
    ],
    "name:spa_x_preferred":[
        "Huanggang"
    ],
    "name:srp_x_preferred":[
        "\u0425\u0443\u0430\u043d\u0433\u0430\u043d\u0433"
    ],
    "name:swa_x_preferred":[
        "Huanggang"
    ],
    "name:swe_x_preferred":[
        "Huanggang"
    ],
    "name:tgl_x_preferred":[
        "Huanggang"
    ],
    "name:tur_x_preferred":[
        "Huanggang"
    ],
    "name:ukr_x_preferred":[
        "\u0425\u0443\u0430\u043d\u0433\u0430\u043d"
    ],
    "name:urd_x_preferred":[
        "\u06c1\u0648\u0627\u0646\u06af\u06af\u0627\u0646\u06af"
    ],
    "name:vie_x_preferred":[
        "Ho\u00e0ng C\u01b0\u01a1ng"
    ],
    "name:zho_x_preferred":[
        "\u9ec4\u6e2f"
    ],
    "name:zho_x_variant":[
        "\u9ec4\u5188\u5e02"
    ],
    "wof:name":"Huanggang",
    "wof:placetype":"locality"
},
  "geometry": {"coordinates":[107.143,25.4284],"type":"Point"}
}