{
  "type": "Feature",
  "properties": {
    "gn:admin1_code":"16.0",
    "gn:asciiname":"Shangqin",
    "gn:country_code":"CN",
    "gn:dem":743,
    "gn:feature_class":"P",
    "gn:feature_code":"PPL",
    "gn:name":"Shangqin",
    "gn:population":0,
    "gn:timezone":"Asia/Shanghai",
    "iso:country":"CN",
    "name:zho_x_preferred":[
        "\u5c1a\u52e4"
    ],
    "wof:name":"Shangqin",
    "wof:placetype":"locality"
},
  "geometry": {"coordinates":[107.05800000000001,24.1331],"type":"Point"}
}