{
  "type": "Feature",
  "properties": {
    "gn:admin1_code":"3.0",
    "gn:asciiname":"Dongkengzi",
    "gn:country_code":"CN",
    "gn:dem":145,
    "gn:feature_class":"P",
    "gn:feature_code":"PPL",
    "gn:name":"Dongkengzi",
    "gn:population":0,
    "gn:timezone":"Asia/Shanghai",
    "iso:country":"CN",
    "name:und_x_variant":[
        "\u4e1c\u5751\u5b50"
    ],
    "wof:name":"Dongkengzi",
    "wof:placetype":"locality"
},
  "geometry": {"coordinates":[115.62318,25.80701],"type":"Point"}
}