{
  "type": "Feature",
  "properties": {
    "gn:admin1_code":"3.0",
    "gn:asciiname":"Kaifeng",
    "gn:country_code":"CN",
    "gn:dem":335,
    "gn:feature_class":"P",
    "gn:feature_code":"PPL",
    "gn:name":"Kaifeng",
    "gn:population":0,
    "gn:timezone":"Asia/Shanghai",
    "iso:country":"CN",
    "name:und_x_variant":[
        "\u51ef\u4e30"
    ],
    "wof:name":"Kaifeng",
    "wof:placetype":"locality"
},
  "geometry": {"coordinates":[115.95995000000001,25.96145],"type":"Point"}
}