{
  "type": "Feature",
  "properties": {
    "gn:admin1_code":"8.0",
    "gn:asciiname":"Zhaoguang Nongchang Sanshijiudui",
    "gn:country_code":"CN",
    "gn:dem":307,
    "gn:feature_class":"P",
    "gn:feature_code":"PPLF",
    "gn:name":"Zhaoguang Nongchang Sanshijiudui",
    "gn:population":0,
    "gn:timezone":"Asia/Shanghai",
    "iso:country":"CN",
    "name:zho_x_preferred":[
        "\u8d75\u5149\u519c\u573a\u4e09\u5341\u4e5d\u961f"
    ],
    "wof:name":"Zhaoguang Nongchang Sanshijiudui",
    "wof:placetype":"locality"
},
  "geometry": {"coordinates":[127.03683999999998,47.94298],"type":"Point"}
}