{
  "type": "Feature",
  "properties": {
    "gn:admin1_code":"26.0",
    "gn:asciiname":"Houfengjiahui",
    "gn:country_code":"CN",
    "gn:dem":871,
    "gn:feature_class":"P",
    "gn:feature_code":"PPL",
    "gn:name":"Houfengjiahui",
    "gn:population":0,
    "gn:timezone":"Asia/Shanghai",
    "iso:country":"CN",
    "name:zho_x_preferred":[
        "\u540e\u51af\u5bb6\u4f1a"
    ],
    "wof:name":"Houfengjiahui",
    "wof:placetype":"locality"
},
  "geometry": {"coordinates":[111.17699,39.30588],"type":"Point"}
}