{
  "type": "Feature",
  "properties": {
    "gn:admin1_code":"14.0",
    "gn:asciiname":"Buba",
    "gn:country_code":"CN",
    "gn:dem":4776,
    "gn:feature_class":"P",
    "gn:feature_code":"PPL",
    "gn:name":"Buba",
    "gn:population":0,
    "gn:timezone":"Asia/Urumqi",
    "iso:country":"CN",
    "name:cat_x_preferred":[
        "Buba"
    ],
    "name:ceb_x_preferred":[
        "Buba"
    ],
    "name:deu_x_preferred":[
        "Buba"
    ],
    "name:epo_x_preferred":[
        "Buba"
    ],
    "name:fin_x_preferred":[
        "Buba"
    ],
    "name:frr_x_preferred":[
        "Buba"
    ],
    "name:ita_x_preferred":[
        "Buba"
    ],
    "name:kor_x_preferred":[
        "\ubd80\ubc14"
    ],
    "name:lit_x_preferred":[
        "Buba"
    ],
    "name:nld_x_preferred":[
        "Buba"
    ],
    "name:pol_x_preferred":[
        "Buba"
    ],
    "name:por_x_preferred":[
        "Buba"
    ],
    "name:ron_x_preferred":[
        "Buba"
    ],
    "name:swe_x_preferred":[
        "Buba"
    ],
    "name:zho_x_preferred":[
        "\u5e03\u628a"
    ],
    "wof:name":"Buba",
    "wof:placetype":"locality"
},
  "geometry": {"coordinates":[85.5368,30.544],"type":"Point"}
}