{
  "type": "Feature",
  "properties": {
    "gn:admin1_code":"14.0",
    "gn:asciiname":"Buba",
    "gn:country_code":"CN",
    "gn:dem":4776,
    "gn:feature_class":"P",
    "gn:feature_code":"PPL",
    "gn:name":"Buba",
    "gn:population":0,
    "gn:timezone":"Asia/Urumqi",
    "iso:country":"CN",
    "name:zho_x_preferred":[
        "\u5e03\u628a"
    ],
    "wof:name":"Buba",
    "wof:placetype":"locality"
},
  "geometry": {"coordinates":[85.5368,30.544],"type":"Point"}
}