{
  "type": "Feature",
  "properties": {
    "gn:admin1_code":"9.0",
    "gn:asciiname":"Duxiaotun",
    "gn:country_code":"CN",
    "gn:dem":83,
    "gn:feature_class":"P",
    "gn:feature_code":"PPL",
    "gn:name":"Duxiaotun",
    "gn:population":0,
    "gn:timezone":"Asia/Shanghai",
    "iso:country":"CN",
    "name:zho_x_preferred":[
        "\u675c\u5c0f\u5c6f"
    ],
    "wof:name":"Duxiaotun",
    "wof:placetype":"locality"
},
  "geometry": {"coordinates":[114.28478,36.16773],"type":"Point"}
}