{
  "type": "Feature",
  "properties": {
    "gn:admin1_code":"30",
    "gn:asciiname":"Gudou",
    "gn:country_code":"CN",
    "gn:dem":5,
    "gn:feature_class":"P",
    "gn:feature_code":"PPL",
    "gn:name":"Gudou",
    "gn:population":0,
    "gn:timezone":"Asia/Shanghai",
    "iso:country":"CN",
    "name:und_x_variant":[
        "Ku-pu",
        "Gubu",
        "Gudou"
    ],
    "name:zho_x_preferred":[
        "\u53e4\u6597"
    ],
    "wof:name":"Gudou",
    "wof:placetype":"locality"
},
  "geometry": {"coordinates":[113.04962999999999,22.7226],"type":"Point"}
}