{
  "type": "Feature",
  "properties": {
    "gn:admin1_code":"30.0",
    "gn:asciiname":"Chenhuang",
    "gn:country_code":"CN",
    "gn:dem":12,
    "gn:feature_class":"P",
    "gn:feature_code":"PPL",
    "gn:name":"Chenhuang",
    "gn:population":0,
    "gn:timezone":"Asia/Shanghai",
    "iso:country":"CN",
    "name:zho_x_preferred":[
        "\u9648\u9ec4"
    ],
    "wof:name":"Chenhuang",
    "wof:placetype":"locality"
},
  "geometry": {"coordinates":[113.71456000000001,22.84803],"type":"Point"}
}