{
  "type": "Feature",
  "properties": {
    "gn:admin1_code":"11.0",
    "gn:asciiname":"Dongwan",
    "gn:country_code":"CN",
    "gn:dem":171,
    "gn:feature_class":"P",
    "gn:feature_code":"PPL",
    "gn:name":"Dongwan",
    "gn:population":0,
    "gn:timezone":"Asia/Shanghai",
    "iso:country":"CN",
    "name:deu_x_preferred":[
        "Dongwan"
    ],
    "name:zho_x_preferred":[
        "\u4e1c\u6e7e"
    ],
    "wof:name":"Dongwan",
    "wof:placetype":"locality"
},
  "geometry": {"coordinates":[113.01326,25.773],"type":"Point"}
}