{
  "type": "Feature",
  "properties": {
    "gn:admin1_code":"4.0",
    "gn:asciiname":"Jinggongdai",
    "gn:country_code":"CN",
    "gn:dem":5,
    "gn:feature_class":"P",
    "gn:feature_code":"PPL",
    "gn:name":"Jinggongdai",
    "gn:population":0,
    "gn:timezone":"Asia/Shanghai",
    "iso:country":"CN",
    "name:zho_x_preferred":[
        "\u9756\u516c\u5788"
    ],
    "wof:name":"Jinggongdai",
    "wof:placetype":"locality"
},
  "geometry": {"coordinates":[120.22584999999999,32.07011],"type":"Point"}
}