{
  "type": "Feature",
  "properties": {
    "gn:admin1_code":"30.0",
    "gn:asciiname":"Shangyangwu",
    "gn:country_code":"CN",
    "gn:dem":259,
    "gn:feature_class":"P",
    "gn:feature_code":"PPL",
    "gn:name":"Shangyangwu",
    "gn:population":0,
    "gn:timezone":"Asia/Shanghai",
    "iso:country":"CN",
    "name:zho_x_preferred":[
        "\u4e0a\u6768\u5c4b"
    ],
    "wof:name":"Shangyangwu",
    "wof:placetype":"locality"
},
  "geometry": {"coordinates":[116.00993,23.94727],"type":"Point"}
}