{
  "type": "Feature",
  "properties": {
    "gn:admin1_code":"12.0",
    "gn:asciiname":"Liuzhanggang",
    "gn:country_code":"CN",
    "gn:dem":36,
    "gn:feature_class":"P",
    "gn:feature_code":"PPL",
    "gn:name":"Liuzhanggang",
    "gn:population":0,
    "gn:timezone":"Asia/Shanghai",
    "iso:country":"CN",
    "name:zho_x_preferred":[
        "\u516d\u5f20\u5c97"
    ],
    "wof:name":"Liuzhanggang",
    "wof:placetype":"locality"
},
  "geometry": {"coordinates":[113.92825999999999,31.05529000000001],"type":"Point"}
}