{
  "type": "Feature",
  "properties": {
    "gn:admin1_code":"9.0",
    "gn:asciiname":"Jixingou",
    "gn:country_code":"CN",
    "gn:dem":310,
    "gn:feature_class":"P",
    "gn:feature_code":"PPL",
    "gn:name":"Jixingou",
    "gn:population":0,
    "gn:timezone":"Asia/Shanghai",
    "iso:country":"CN",
    "name:zho_x_preferred":[
        "\u9e21\u5fc3\u6c9f"
    ],
    "wof:name":"Jixingou",
    "wof:placetype":"locality"
},
  "geometry": {"coordinates":[111.53422,33.33905],"type":"Point"}
}