{
  "type": "Feature",
  "properties": {
    "gn:admin1_code":"11.0",
    "gn:asciiname":"Zhangshangchong",
    "gn:country_code":"CN",
    "gn:dem":287,
    "gn:feature_class":"P",
    "gn:feature_code":"PPL",
    "gn:name":"Zhangshangchong",
    "gn:population":0,
    "gn:timezone":"Asia/Shanghai",
    "iso:country":"CN",
    "name:zho_x_preferred":[
        "\u5e10\u4e0a\u51b2"
    ],
    "wof:name":"Zhangshangchong",
    "wof:placetype":"locality"
},
  "geometry": {"coordinates":[111.99368,27.22411],"type":"Point"}
}