{
  "type": "Feature",
  "properties": {
    "gn:admin1_code":"30",
    "gn:asciiname":"Sikouwo",
    "gn:country_code":"CN",
    "gn:dem":597,
    "gn:feature_class":"P",
    "gn:feature_code":"PPL",
    "gn:name":"Sikouwo",
    "gn:population":0,
    "gn:timezone":"Asia/Shanghai",
    "iso:country":"CN",
    "name:zho_x_preferred":[
        "\u56db\u53e3\u7a9d"
    ],
    "wof:name":"Sikouwo",
    "wof:placetype":"locality"
},
  "geometry": {"coordinates":[116.27968,24.24118],"type":"Point"}
}