{
  "type": "Feature",
  "properties": {
    "gn:admin1_code":"7.0",
    "gn:asciiname":"Longjiang",
    "gn:country_code":"CN",
    "gn:dem":16,
    "gn:feature_class":"P",
    "gn:feature_code":"PPL",
    "gn:name":"Longjiang",
    "gn:population":0,
    "gn:timezone":"Asia/Shanghai",
    "iso:country":"CN",
    "name:ceb_x_preferred":[
        "Longjiang"
    ],
    "name:deu_x_preferred":[
        "Longjiang"
    ],
    "name:mlg_x_preferred":[
        "Longjiang"
    ],
    "name:zho_x_preferred":[
        "\u9f99\u6c5f"
    ],
    "wof:name":"Longjiang",
    "wof:placetype":"locality"
},
  "geometry": {"coordinates":[117.89421000000002,24.55451],"type":"Point"}
}