{
  "type": "Feature",
  "properties": {
    "gn:admin1_code":"15.0",
    "gn:asciiname":"Shangdianzi",
    "gn:country_code":"CN",
    "gn:dem":1690,
    "gn:feature_class":"P",
    "gn:feature_code":"PPL",
    "gn:name":"Shangdianzi",
    "gn:population":0,
    "gn:timezone":"Asia/Shanghai",
    "iso:country":"CN",
    "name:zho_x_preferred":[
        "\u4e0a\u5e97\u5b50"
    ],
    "wof:name":"Shangdianzi",
    "wof:placetype":"locality"
},
  "geometry": {"coordinates":[104.98197,33.98022],"type":"Point"}
}