{
  "type": "Feature",
  "properties": {
    "gn:admin1_code":"4.0",
    "gn:asciiname":"Zhouchongcun",
    "gn:country_code":"CN",
    "gn:dem":22,
    "gn:feature_class":"P",
    "gn:feature_code":"PPL",
    "gn:name":"Zhouchongcun",
    "gn:population":0,
    "gn:timezone":"Asia/Shanghai",
    "iso:country":"CN",
    "name:zho_x_preferred":[
        "\u5468\u51b2\u6751"
    ],
    "wof:name":"Zhouchongcun",
    "wof:placetype":"locality"
},
  "geometry": {"coordinates":[118.20868,33.2193],"type":"Point"}
}