{
  "type": "Feature",
  "properties": {
    "gn:admin1_code":"22.0",
    "gn:asciiname":"Houquhe",
    "gn:country_code":"CN",
    "gn:dem":39,
    "gn:feature_class":"P",
    "gn:feature_code":"PPL",
    "gn:name":"Houquhe",
    "gn:population":0,
    "gn:timezone":"Asia/Shanghai",
    "iso:country":"CN",
    "name:zho_x_preferred":[
        "\u540e\u6e20\u6cb3"
    ],
    "wof:name":"Houquhe",
    "wof:placetype":"locality"
},
  "geometry": {"coordinates":[116.52992,40.15601],"type":"Point"}
}