{
  "type": "Feature",
  "properties": {
    "gn:admin1_code":"12.0",
    "gn:asciiname":"Yachaqing",
    "gn:country_code":"CN",
    "gn:dem":445,
    "gn:feature_class":"P",
    "gn:feature_code":"PPL",
    "gn:name":"Yachaqing",
    "gn:population":0,
    "gn:timezone":"Asia/Shanghai",
    "iso:country":"CN",
    "name:zho_x_preferred":[
        "\u57ad\u5c94\u6e05"
    ],
    "wof:name":"Yachaqing",
    "wof:placetype":"locality"
},
  "geometry": {"coordinates":[109.32979,29.30019],"type":"Point"}
}