{
  "type": "Feature",
  "properties": {
    "gn:admin1_code":"19",
    "gn:asciiname":"Dongxinzhuang",
    "gn:cc2":"CN",
    "gn:country_code":"CN",
    "gn:dem":15,
    "gn:feature_class":"P",
    "gn:feature_code":"PPL",
    "gn:name":"Dongxinzhuang",
    "gn:population":0,
    "gn:timezone":"Asia/Shanghai",
    "iso:country":"CN",
    "name:und_x_variant":[
        "Tung-hsin-chuang",
        "Dongxinzhuang"
    ],
    "wof:name":"Dongxinzhuang",
    "wof:placetype":"locality"
},
  "geometry": {"coordinates":[120.45,40.36667],"type":"Point"}
}