{
  "type": "Feature",
  "properties": {
    "gn:admin1_code":"29.0",
    "gn:asciiname":"Xiaobaxin",
    "gn:country_code":"CN",
    "gn:dem":2027,
    "gn:feature_class":"P",
    "gn:feature_code":"PPL",
    "gn:name":"Xiaobaxin",
    "gn:population":0,
    "gn:timezone":"Asia/Shanghai",
    "iso:country":"CN",
    "name:zho_x_preferred":[
        "\u5c0f\u575d\u5fc3"
    ],
    "wof:name":"Xiaobaxin",
    "wof:placetype":"locality"
},
  "geometry": {"coordinates":[103.80200000000001,24.0149],"type":"Point"}
}