{
  "type": "Feature",
  "properties": {
    "gn:admin1_code":"2.0",
    "gn:asciiname":"Xiucai",
    "gn:country_code":"CN",
    "gn:dem":5,
    "gn:feature_class":"P",
    "gn:feature_code":"PPL",
    "gn:name":"Xiucai",
    "gn:population":0,
    "gn:timezone":"Asia/Shanghai",
    "iso:country":"CN",
    "name:und_x_variant":[
        "\u79c0\u624d"
    ],
    "wof:name":"Xiucai",
    "wof:placetype":"locality"
},
  "geometry": {"coordinates":[120.40989,30.57912],"type":"Point"}
}