{
  "type": "Feature",
  "properties": {
    "gn:admin1_code":"29.0",
    "gn:asciiname":"Shangkazuo",
    "gn:country_code":"CN",
    "gn:dem":1505,
    "gn:feature_class":"P",
    "gn:feature_code":"PPL",
    "gn:name":"Shangkazuo",
    "gn:population":0,
    "gn:timezone":"Asia/Shanghai",
    "iso:country":"CN",
    "name:zho_x_preferred":[
        "\u4e0a\u5361\u4f5c"
    ],
    "wof:name":"Shangkazuo",
    "wof:placetype":"locality"
},
  "geometry": {"coordinates":[104.126,23.5398],"type":"Point"}
}