{
  "type": "Feature",
  "properties": {
    "gn:admin1_code":"9",
    "gn:asciiname":"Yaozhuang",
    "gn:country_code":"CN",
    "gn:dem":51,
    "gn:feature_class":"P",
    "gn:feature_code":"PPL",
    "gn:name":"Yaozhuang",
    "gn:population":0,
    "gn:timezone":"Asia/Shanghai",
    "iso:country":"CN",
    "name:zho_x_preferred":[
        "\u59da\u5e84"
    ],
    "wof:name":"Yaozhuang",
    "wof:placetype":"locality"
},
  "geometry": {"coordinates":[115.12455,35.91054000000001],"type":"Point"}
}