{
  "type": "Feature",
  "properties": {
    "gn:admin1_code":"26.0",
    "gn:asciiname":"Laozhuanggoucun",
    "gn:country_code":"CN",
    "gn:dem":1314,
    "gn:feature_class":"P",
    "gn:feature_code":"PPL",
    "gn:name":"Laozhuanggoucun",
    "gn:population":0,
    "gn:timezone":"Asia/Shanghai",
    "iso:country":"CN",
    "name:zho_x_preferred":[
        "\u8001\u5e84\u6c9f\u6751"
    ],
    "wof:name":"Laozhuanggoucun",
    "wof:placetype":"locality"
},
  "geometry": {"coordinates":[109.61638000000001,33.90834],"type":"Point"}
}