{
  "type": "Feature",
  "properties": {
    "gn:admin1_code":"7.0",
    "gn:asciiname":"Laohukeng",
    "gn:country_code":"CN",
    "gn:dem":500,
    "gn:feature_class":"P",
    "gn:feature_code":"PPL",
    "gn:name":"Laohukeng",
    "gn:population":0,
    "gn:timezone":"Asia/Shanghai",
    "iso:country":"CN",
    "name:zho_x_preferred":[
        "\u8001\u864e\u5751"
    ],
    "wof:name":"Laohukeng",
    "wof:placetype":"locality"
},
  "geometry": {"coordinates":[115.92301999999999,25.09542],"type":"Point"}
}