{
  "type": "Feature",
  "properties": {
    "gn:admin1_code":"4.0",
    "gn:asciiname":"Yangdai",
    "gn:country_code":"CN",
    "gn:dem":7,
    "gn:feature_class":"P",
    "gn:feature_code":"PPL",
    "gn:name":"Yangdai",
    "gn:population":0,
    "gn:timezone":"Asia/Shanghai",
    "iso:country":"CN",
    "name:und_x_variant":[
        "\u6768\u5cb1"
    ],
    "name:zho_x_preferred":[
        "\u6768\u5cb1"
    ],
    "wof:name":"Yangdai",
    "wof:placetype":"locality"
},
  "geometry": {"coordinates":[120.28026,32.3885],"type":"Point"}
}