{
  "type": "Feature",
  "properties": {
    "gn:admin1_code":"5.0",
    "gn:asciiname":"Libanhaocun",
    "gn:country_code":"CN",
    "gn:dem":201,
    "gn:feature_class":"P",
    "gn:feature_code":"PPL",
    "gn:name":"Libanhaocun",
    "gn:population":0,
    "gn:timezone":"Asia/Shanghai",
    "iso:country":"CN",
    "name:zho_x_preferred":[
        "\u91cc\u534a\u53f7\u6751"
    ],
    "wof:name":"Libanhaocun",
    "wof:placetype":"locality"
},
  "geometry": {"coordinates":[126.08553000000001,45.05189],"type":"Point"}
}