{
  "type": "Feature",
  "properties": {
    "gn:admin1_code":"11.0",
    "gn:asciiname":"Zeng Laowu",
    "gn:country_code":"CN",
    "gn:dem":79,
    "gn:feature_class":"P",
    "gn:feature_code":"PPL",
    "gn:name":"Zeng Laowu",
    "gn:population":0,
    "gn:timezone":"Asia/Shanghai",
    "iso:country":"CN",
    "name:zho_x_preferred":[
        "\u66fe\u8001\u5c4b"
    ],
    "wof:name":"Zeng Laowu",
    "wof:placetype":"locality"
},
  "geometry": {"coordinates":[112.6773,26.97861],"type":"Point"}
}