{
  "type": "Feature",
  "properties": {
    "gn:admin1_code":"3.0",
    "gn:asciiname":"Baijiacun",
    "gn:country_code":"CN",
    "gn:dem":517,
    "gn:feature_class":"P",
    "gn:feature_code":"PPL",
    "gn:name":"Baijiacun",
    "gn:population":0,
    "gn:timezone":"Asia/Shanghai",
    "iso:country":"CN",
    "name:und_x_variant":[
        "\u767d\u5bb6\u6751"
    ],
    "wof:name":"Baijiacun",
    "wof:placetype":"locality"
},
  "geometry": {"coordinates":[116.25391999999999,26.40705],"type":"Point"}
}