{
  "type": "Feature",
  "properties": {
    "gn:admin1_code":"29",
    "gn:asciiname":"Aziying",
    "gn:country_code":"CN",
    "gn:dem":2064,
    "gn:feature_class":"P",
    "gn:feature_code":"PPL",
    "gn:name":"Aziying",
    "gn:population":0,
    "gn:timezone":"Asia/Shanghai",
    "iso:country":"CN",
    "wof:name":"Aziying",
    "wof:placetype":"locality"
},
  "geometry": {"coordinates":[102.77861,25.34167],"type":"Point"}
}