{
  "type": "Feature",
  "properties": {
    "gn:admin1_code":"13.0",
    "gn:asciiname":"Utubulak",
    "gn:cc2":"CN",
    "gn:country_code":"CN",
    "gn:dem":1227,
    "gn:feature_class":"P",
    "gn:feature_code":"PPL",
    "gn:name":"Utubulak",
    "gn:population":0,
    "gn:timezone":"Asia/Urumqi",
    "iso:country":"CN",
    "name:und_x_variant":[
        "Ussu-Bulaktai",
        "Ushu-Bulak",
        "Wu-shu-pu-la-k\u2019o-t\u2019ai",
        "Utu-bulak Post",
        "Uru Bulak",
        "Urta Bulak",
        "Wu-t\u2019u-pu-la-k\u2019o",
        "Utu-bulak Karaul",
        "Wu-lu-pu-la-k\u2019o-t\u2019ai",
        "Wu-lu-ch\u2019\u00fcan",
        "Utubulak"
    ],
    "wof:name":"Utubulak",
    "wof:placetype":"locality"
},
  "geometry": {"coordinates":[86.38333,46.88333],"type":"Point"}
}