{
  "type": "Feature",
  "properties": {
    "gn:admin1_code":"15.0",
    "gn:asciiname":"Sangou Jingzi",
    "gn:country_code":"CN",
    "gn:dem":2401,
    "gn:feature_class":"P",
    "gn:feature_code":"PPL",
    "gn:name":"Sangou Jingzi",
    "gn:population":0,
    "gn:timezone":"Asia/Shanghai",
    "iso:country":"CN",
    "name:zho_x_preferred":[
        "\u4e09\u6c9f\u4e95\u5b50"
    ],
    "wof:name":"Sangou Jingzi",
    "wof:placetype":"locality"
},
  "geometry": {"coordinates":[102.294,37.8931],"type":"Point"}
}