{
  "type": "Feature",
  "properties": {
    "gn:admin1_code":"29",
    "gn:asciiname":"Tuzhangfang",
    "gn:country_code":"CN",
    "gn:dem":1805,
    "gn:feature_class":"P",
    "gn:feature_code":"PPL",
    "gn:name":"Tuzhangfang",
    "gn:population":0,
    "gn:timezone":"Asia/Shanghai",
    "iso:country":"CN",
    "name:zho_x_preferred":[
        "\u571f\u638c\u623f"
    ],
    "wof:name":"Tuzhangfang",
    "wof:placetype":"locality"
},
  "geometry": {"coordinates":[101.348,24.9297],"type":"Point"}
}