{
  "type": "Feature",
  "properties": {
    "gn:admin1_code":"19.0",
    "gn:asciiname":"Xiaolutun",
    "gn:country_code":"CN",
    "gn:dem":15,
    "gn:feature_class":"P",
    "gn:feature_code":"PPL",
    "gn:name":"Xiaol\u00fctun",
    "gn:population":0,
    "gn:timezone":"Asia/Shanghai",
    "iso:country":"CN",
    "name:zho_x_preferred":[
        "Xiaol\u00fctun"
    ],
    "name:zho_x_variant":[
        "\u5c0f\u5415\u5c6f"
    ],
    "wof:name":"Xiaolutun",
    "wof:placetype":"locality"
},
  "geometry": {"coordinates":[121.72732000000001,39.40873],"type":"Point"}
}