{
  "type": "Feature",
  "properties": {
    "gn:admin1_code":"13",
    "gn:asciiname":"Xinjian",
    "gn:country_code":"CN",
    "gn:dem":467,
    "gn:feature_class":"P",
    "gn:feature_code":"PPL",
    "gn:name":"Xinjian",
    "gn:population":0,
    "gn:timezone":"Asia/Urumqi",
    "iso:country":"CN",
    "name:zho_x_preferred":[
        "\u65b0\u5efa"
    ],
    "wof:name":"Xinjian",
    "wof:placetype":"locality"
},
  "geometry": {"coordinates":[87.59059000000001,44.1883],"type":"Point"}
}