{
  "type": "Feature",
  "properties": {
    "gn:admin1_code":"30",
    "gn:asciiname":"Haitian",
    "gn:country_code":"CN",
    "gn:dem":7,
    "gn:feature_class":"P",
    "gn:feature_code":"PPL",
    "gn:name":"Haitian",
    "gn:population":0,
    "gn:timezone":"Asia/Shanghai",
    "iso:country":"CN",
    "name:hat_x_preferred":[
        "Ayisyen"
    ],
    "wof:name":"Haitian",
    "wof:placetype":"locality"
},
  "geometry": {"coordinates":[116.50381000000002,23.36105],"type":"Point"}
}