{
  "type": "Feature",
  "properties": {
    "gn:admin1_code":"9.0",
    "gn:asciiname":"Yanggou",
    "gn:country_code":"CN",
    "gn:dem":340,
    "gn:feature_class":"P",
    "gn:feature_code":"PPL",
    "gn:name":"Yanggou",
    "gn:population":0,
    "gn:timezone":"Asia/Shanghai",
    "iso:country":"CN",
    "name:und_x_variant":[
        "\u7f8a\u6c9f",
        "Yanggou"
    ],
    "wof:name":"Yanggou",
    "wof:placetype":"locality"
},
  "geometry": {"coordinates":[112.74966999999999,33.54283],"type":"Point"}
}