{
  "type": "Feature",
  "properties": {
    "gn:admin1_code":"30.0",
    "gn:asciiname":"Huashuishan Yaozucun",
    "gn:country_code":"CN",
    "gn:dem":422,
    "gn:feature_class":"P",
    "gn:feature_code":"PPL",
    "gn:name":"Huashuishan Yaozucun",
    "gn:population":0,
    "gn:timezone":"Asia/Shanghai",
    "iso:country":"CN",
    "name:zho_x_preferred":[
        "\u6ed1\u6c34\u5c71\u7476\u65cf\u6751"
    ],
    "wof:name":"Huashuishan Yaozucun",
    "wof:placetype":"locality"
},
  "geometry": {"coordinates":[113.66833,24.44694],"type":"Point"}
}