{
  "type": "Feature",
  "properties": {
    "gn:admin1_code":"8.0",
    "gn:asciiname":"Nanjicun",
    "gn:country_code":"CN",
    "gn:dem":303,
    "gn:feature_class":"P",
    "gn:feature_code":"PPL",
    "gn:name":"Nanjicun",
    "gn:population":0,
    "gn:timezone":"Asia/Shanghai",
    "iso:country":"CN",
    "name:zho_x_preferred":[
        "\u5357\u6d4e\u6751"
    ],
    "wof:name":"Nanjicun",
    "wof:placetype":"locality"
},
  "geometry": {"coordinates":[122.59123999999998,47.30782],"type":"Point"}
}