{
  "type": "Feature",
  "properties": {
    "gn:admin1_code":"2.0",
    "gn:asciiname":"Xiahounong",
    "gn:country_code":"CN",
    "gn:dem":537,
    "gn:feature_class":"P",
    "gn:feature_code":"PPL",
    "gn:name":"Xiahounong",
    "gn:population":0,
    "gn:timezone":"Asia/Shanghai",
    "iso:country":"CN",
    "name:zho_x_preferred":[
        "\u4e0b\u540e\u5f04"
    ],
    "wof:name":"Xiahounong",
    "wof:placetype":"locality"
},
  "geometry": {"coordinates":[119.98914000000001,28.5135],"type":"Point"}
}