{
  "type": "Feature",
  "properties": {
    "gn:admin1_code":"3.0",
    "gn:asciiname":"Gaiziling",
    "gn:country_code":"CN",
    "gn:dem":409,
    "gn:feature_class":"P",
    "gn:feature_code":"PPL",
    "gn:name":"Gaiziling",
    "gn:population":0,
    "gn:timezone":"Asia/Shanghai",
    "iso:country":"CN",
    "name:und_x_variant":[
        "\u6539\u5b50\u5cad"
    ],
    "wof:name":"Gaiziling",
    "wof:placetype":"locality"
},
  "geometry": {"coordinates":[116.24099,26.47782],"type":"Point"}
}