{
  "type": "Feature",
  "properties": {
    "gn:admin1_code":"7.0",
    "gn:asciiname":"Laiyangtou",
    "gn:country_code":"CN",
    "gn:dem":793,
    "gn:feature_class":"P",
    "gn:feature_code":"PPL",
    "gn:name":"Laiyangtou",
    "gn:population":0,
    "gn:timezone":"Asia/Shanghai",
    "iso:country":"CN",
    "name:zho_x_preferred":[
        "\u6765\u6d0b\u5934"
    ],
    "wof:name":"Laiyangtou",
    "wof:placetype":"locality"
},
  "geometry": {"coordinates":[118.64709999999999,26.21516],"type":"Point"}
}