{
  "type": "Feature",
  "properties": {
    "gn:admin1_code":"7",
    "gn:asciiname":"Matou",
    "gn:country_code":"CN",
    "gn:dem":525,
    "gn:feature_class":"P",
    "gn:feature_code":"PPL",
    "gn:name":"Matou",
    "gn:population":0,
    "gn:timezone":"Asia/Shanghai",
    "iso:country":"CN",
    "name:und_x_variant":[
        "\u9a6c\u5934",
        "Matou"
    ],
    "wof:name":"Matou",
    "wof:placetype":"locality"
},
  "geometry": {"coordinates":[119.73629,27.30956],"type":"Point"}
}