{
  "type": "Feature",
  "properties": {
    "gn:admin1_code":"1.0",
    "gn:asciiname":"Duyingcun",
    "gn:country_code":"CN",
    "gn:dem":35,
    "gn:feature_class":"P",
    "gn:feature_code":"PPL",
    "gn:name":"Duyingcun",
    "gn:population":0,
    "gn:timezone":"Asia/Shanghai",
    "iso:country":"CN",
    "name:zho_x_preferred":[
        "\u675c\u90e2\u6751"
    ],
    "wof:name":"Duyingcun",
    "wof:placetype":"locality"
},
  "geometry": {"coordinates":[115.34631,32.59967],"type":"Point"}
}