{
  "type": "Feature",
  "properties": {
    "gn:admin1_code":"8.0",
    "gn:asciiname":"Furongcun",
    "gn:country_code":"CN",
    "gn:dem":494,
    "gn:feature_class":"P",
    "gn:feature_code":"PPL",
    "gn:name":"Furongcun",
    "gn:population":0,
    "gn:timezone":"Asia/Shanghai",
    "iso:country":"CN",
    "name:zho_x_preferred":[
        "\u5bcc\u8363\u6751"
    ],
    "wof:name":"Furongcun",
    "wof:placetype":"locality"
},
  "geometry": {"coordinates":[130.94668999999999,44.31055],"type":"Point"}
}