{
  "type": "Feature",
  "properties": {
    "gn:admin1_code":"9.0",
    "gn:asciiname":"Goukou",
    "gn:country_code":"CN",
    "gn:dem":225,
    "gn:feature_class":"P",
    "gn:feature_code":"PPL",
    "gn:name":"Goukou",
    "gn:population":0,
    "gn:timezone":"Asia/Shanghai",
    "iso:country":"CN",
    "name:und_x_variant":[
        "\u6c9f\u53e3",
        "Goukou"
    ],
    "wof:name":"Goukou",
    "wof:placetype":"locality"
},
  "geometry": {"coordinates":[112.34153999999999,33.21124],"type":"Point"}
}