{
  "type": "Feature",
  "properties": {
    "gn:admin1_code":"8.0",
    "gn:asciiname":"Lingyuncun",
    "gn:country_code":"CN",
    "gn:dem":104,
    "gn:feature_class":"P",
    "gn:feature_code":"PPL",
    "gn:name":"Lingyuncun",
    "gn:population":0,
    "gn:timezone":"Asia/Shanghai",
    "iso:country":"CN",
    "name:zho_x_preferred":[
        "\u51cc\u4e91\u6751"
    ],
    "wof:name":"Lingyuncun",
    "wof:placetype":"locality"
},
  "geometry": {"coordinates":[132.31466,45.62521],"type":"Point"}
}