{
  "type": "Feature",
  "properties": {
    "gn:admin1_code":"19.0",
    "gn:asciiname":"Daxigoucun",
    "gn:country_code":"CN",
    "gn:dem":125,
    "gn:feature_class":"P",
    "gn:feature_code":"PPL",
    "gn:name":"Daxigoucun",
    "gn:population":0,
    "gn:timezone":"Asia/Shanghai",
    "iso:country":"CN",
    "name:zho_x_preferred":[
        "\u5927\u897f\u6c9f\u6751"
    ],
    "wof:name":"Daxigoucun",
    "wof:placetype":"locality"
},
  "geometry": {"coordinates":[123.28337000000001,41.01714000000001],"type":"Point"}
}