{
  "type": "Feature",
  "properties": {
    "gn:admin1_code":"29.0",
    "gn:asciiname":"Dapojiao",
    "gn:country_code":"CN",
    "gn:dem":1873,
    "gn:feature_class":"P",
    "gn:feature_code":"PPL",
    "gn:name":"Dapojiao",
    "gn:population":0,
    "gn:timezone":"Asia/Shanghai",
    "iso:country":"CN",
    "name:zho_x_preferred":[
        "\u5927\u5761\u811a"
    ],
    "wof:name":"Dapojiao",
    "wof:placetype":"locality"
},
  "geometry": {"coordinates":[104.23099999999999,26.1019],"type":"Point"}
}