{
  "type": "Feature",
  "properties": {
    "gn:admin1_code":"29.0",
    "gn:asciiname":"Dayongsheng",
    "gn:country_code":"CN",
    "gn:dem":1928,
    "gn:feature_class":"P",
    "gn:feature_code":"PPL",
    "gn:name":"Dayongsheng",
    "gn:population":0,
    "gn:timezone":"Asia/Shanghai",
    "iso:country":"CN",
    "name:zho_x_preferred":[
        "\u5927\u6c38\u80dc"
    ],
    "wof:name":"Dayongsheng",
    "wof:placetype":"locality"
},
  "geometry": {"coordinates":[103.551,23.466],"type":"Point"}
}