{
  "type": "Feature",
  "properties": {
    "gn:admin1_code":"11",
    "gn:asciiname":"Dawuzhangjia",
    "gn:country_code":"CN",
    "gn:dem":152,
    "gn:feature_class":"P",
    "gn:feature_code":"PPL",
    "gn:name":"Dawuzhangjia",
    "gn:population":0,
    "gn:timezone":"Asia/Shanghai",
    "iso:country":"CN",
    "name:zho_x_preferred":[
        "\u5927\u5c4b\u5f20\u5bb6"
    ],
    "wof:name":"Dawuzhangjia",
    "wof:placetype":"locality"
},
  "geometry": {"coordinates":[111.72441999999999,26.79208],"type":"Point"}
}