{
  "type": "Feature",
  "properties": {
    "gn:admin1_code":"32.0",
    "gn:asciiname":"Zhanghua",
    "gn:country_code":"CN",
    "gn:dem":465,
    "gn:feature_class":"P",
    "gn:feature_code":"PPLA4",
    "gn:name":"Zhanghua",
    "gn:population":0,
    "gn:timezone":"Asia/Shanghai",
    "iso:country":"CN",
    "name:und_x_variant":[
        "Zhanghua Zhen",
        "\u5f20\u534e\u9547"
    ],
    "name:zho_x_preferred":[
        "\u5f20\u534e"
    ],
    "wof:name":"Zhanghua",
    "wof:placetype":"locality"
},
  "geometry": {"coordinates":[106.18505999999999,32.14784],"type":"Point"}
}