{
  "type": "Feature",
  "properties": {
    "gn:admin1_code":"3",
    "gn:asciiname":"Ludong",
    "gn:country_code":"CN",
    "gn:dem":75,
    "gn:feature_class":"P",
    "gn:feature_code":"PPL",
    "gn:name":"Ludong",
    "gn:population":0,
    "gn:timezone":"Asia/Shanghai",
    "iso:country":"CN",
    "name:und_x_variant":[
        "\u8def\u4e1c"
    ],
    "wof:name":"Ludong",
    "wof:placetype":"locality"
},
  "geometry": {"coordinates":[116.57989999999999,27.43689],"type":"Point"}
}