{
  "type": "Feature",
  "properties": {
    "gn:admin1_code":"5.0",
    "gn:asciiname":"Sanhaocun",
    "gn:country_code":"CN",
    "gn:dem":150,
    "gn:feature_class":"P",
    "gn:feature_code":"PPL",
    "gn:name":"Sanhaocun",
    "gn:population":0,
    "gn:timezone":"Asia/Shanghai",
    "iso:country":"CN",
    "name:zho_x_preferred":[
        "\u4e09\u597d\u6751"
    ],
    "wof:name":"Sanhaocun",
    "wof:placetype":"locality"
},
  "geometry": {"coordinates":[123.67657,44.01146],"type":"Point"}
}