{
  "type": "Feature",
  "properties": {
    "gn:admin1_code":"10.0",
    "gn:asciiname":"Xiapiluo",
    "gn:country_code":"CN",
    "gn:dem":584,
    "gn:feature_class":"P",
    "gn:feature_code":"PPL",
    "gn:name":"Xiapiluo",
    "gn:population":0,
    "gn:timezone":"Asia/Shanghai",
    "iso:country":"CN",
    "name:zho_x_preferred":[
        "\u4e0b\u76ae\u7f57"
    ],
    "wof:name":"Xiapiluo",
    "wof:placetype":"locality"
},
  "geometry": {"coordinates":[115.2787,39.77852],"type":"Point"}
}