{
  "type": "Feature",
  "properties": {
    "gn:admin1_code":"11.0",
    "gn:asciiname":"Hetan",
    "gn:country_code":"CN",
    "gn:dem":215,
    "gn:feature_class":"P",
    "gn:feature_code":"PPL",
    "gn:name":"Hetan",
    "gn:population":0,
    "gn:timezone":"Asia/Shanghai",
    "iso:country":"CN",
    "name:zho_x_preferred":[
        "\u8910\u6ee9"
    ],
    "wof:name":"Hetan",
    "wof:placetype":"locality"
},
  "geometry": {"coordinates":[110.64792,28.65887],"type":"Point"}
}