{
  "type": "Feature",
  "properties": {
    "gn:admin1_code":"07",
    "gn:asciiname":"Dashan",
    "gn:country_code":"CN",
    "gn:dem":416,
    "gn:feature_class":"P",
    "gn:feature_code":"PPL",
    "gn:name":"Dashan",
    "gn:population":0,
    "gn:timezone":"Asia/Shanghai",
    "iso:country":"CN",
    "name:zho_x_preferred":[
        "\u5927\u5c71"
    ],
    "wof:name":"Dashan",
    "wof:placetype":"locality"
},
  "geometry": {"coordinates":[120.22519,27.22257],"type":"Point"}
}