{
  "type": "Feature",
  "properties": {
    "gn:admin1_code":"29.0",
    "gn:asciiname":"Xiaogexi",
    "gn:country_code":"CN",
    "gn:dem":1923,
    "gn:feature_class":"P",
    "gn:feature_code":"PPL",
    "gn:name":"Xiaogexi",
    "gn:population":0,
    "gn:timezone":"Asia/Shanghai",
    "iso:country":"CN",
    "name:zho_x_preferred":[
        "\u5c0f\u6208\u606f"
    ],
    "wof:name":"Xiaogexi",
    "wof:placetype":"locality"
},
  "geometry": {"coordinates":[104.05500000000001,25.1894],"type":"Point"}
}