{
  "type": "Feature",
  "properties": {
    "gn:admin1_code":"26.0",
    "gn:asciiname":"Majiawa",
    "gn:country_code":"CN",
    "gn:dem":1251,
    "gn:feature_class":"P",
    "gn:feature_code":"PPL",
    "gn:name":"Majiawa",
    "gn:population":0,
    "gn:timezone":"Asia/Shanghai",
    "iso:country":"CN",
    "name:zho_x_preferred":[
        "\u9a6c\u5bb6\u6d3c"
    ],
    "wof:name":"Majiawa",
    "wof:placetype":"locality"
},
  "geometry": {"coordinates":[109.8322,38.51922],"type":"Point"}
}