{
  "type": "Feature",
  "properties": {
    "gn:admin1_code":"3",
    "gn:asciiname":"Mahong",
    "gn:country_code":"CN",
    "gn:dem":60,
    "gn:feature_class":"P",
    "gn:feature_code":"PPLA4",
    "gn:name":"Mahong",
    "gn:population":0,
    "gn:timezone":"Asia/Shanghai",
    "iso:country":"CN",
    "name:und_x_variant":[
        "\u9a6c\u6d2a",
        "Mahong Xiang",
        "\u9a6c\u6d2a\u4e61"
    ],
    "wof:name":"Mahong",
    "wof:placetype":"locality"
},
  "geometry": {"coordinates":[115.01752999999999,27.91907],"type":"Point"}
}