{
  "type": "Feature",
  "properties": {
    "gn:admin1_code":"30.0",
    "gn:asciiname":"Maolongcun",
    "gn:country_code":"CN",
    "gn:dem":10,
    "gn:feature_class":"P",
    "gn:feature_code":"PPL",
    "gn:name":"Maolongcun",
    "gn:population":0,
    "gn:timezone":"Asia/Shanghai",
    "iso:country":"CN",
    "name:zho_x_preferred":[
        "\u8302\u9f99\u6751"
    ],
    "wof:name":"Maolongcun",
    "wof:placetype":"locality"
},
  "geometry": {"coordinates":[116.68001,23.44831],"type":"Point"}
}