{
  "type": "Feature",
  "properties": {
    "gn:admin1_code":"19.0",
    "gn:asciiname":"Xiaonantai",
    "gn:country_code":"CN",
    "gn:dem":400,
    "gn:feature_class":"P",
    "gn:feature_code":"PPL",
    "gn:name":"Xiaonantai",
    "gn:population":0,
    "gn:timezone":"Asia/Shanghai",
    "iso:country":"CN",
    "name:zho_x_preferred":[
        "\u5c0f\u5357\u53f0"
    ],
    "wof:name":"Xiaonantai",
    "wof:placetype":"locality"
},
  "geometry": {"coordinates":[119.93335,40.96276],"type":"Point"}
}