{
  "type": "Feature",
  "properties": {
    "gn:admin1_code":"8.0",
    "gn:asciiname":"Sifenchang Qidui Wopeng",
    "gn:country_code":"CN",
    "gn:dem":142,
    "gn:feature_class":"P",
    "gn:feature_code":"PPLF",
    "gn:name":"Sifenchang Qidui Wopeng",
    "gn:population":0,
    "gn:timezone":"Asia/Shanghai",
    "iso:country":"CN",
    "name:zho_x_preferred":[
        "\u56db\u5206\u573a\u4e03\u961f\u7a9d\u68da"
    ],
    "wof:name":"Sifenchang Qidui Wopeng",
    "wof:placetype":"locality"
},
  "geometry": {"coordinates":[124.72114999999999,46.86396],"type":"Point"}
}