{
  "type": "Feature",
  "properties": {
    "gn:admin1_code":"1.0",
    "gn:asciiname":"Liu'ancun",
    "gn:country_code":"CN",
    "gn:dem":28,
    "gn:feature_class":"P",
    "gn:feature_code":"PPL",
    "gn:name":"Liu\u2019ancun",
    "gn:population":0,
    "gn:timezone":"Asia/Shanghai",
    "iso:country":"CN",
    "name:und_x_variant":[
        "Liu\u2019ancun"
    ],
    "name:zho_x_preferred":[
        "\u5218\u5eb5\u6751"
    ],
    "wof:name":"Liu'ancun",
    "wof:placetype":"locality"
},
  "geometry": {"coordinates":[117.5177,33.97351],"type":"Point"}
}