{
  "type": "Feature",
  "properties": {
    "gn:admin1_code":"18.0",
    "gn:asciiname":"Jiaogaopo",
    "gn:country_code":"CN",
    "gn:dem":935,
    "gn:feature_class":"P",
    "gn:feature_code":"PPL",
    "gn:name":"Jiaogaopo",
    "gn:population":0,
    "gn:timezone":"Asia/Shanghai",
    "iso:country":"CN",
    "name:zho_x_preferred":[
        "\u811a\u9ad8\u5761"
    ],
    "wof:name":"Jiaogaopo",
    "wof:placetype":"locality"
},
  "geometry": {"coordinates":[107.925,26.3901],"type":"Point"}
}