{
  "type": "Feature",
  "properties": {
    "gn:admin1_code":"1.0",
    "gn:asciiname":"Yangzhushan",
    "gn:country_code":"CN",
    "gn:dem":18,
    "gn:feature_class":"P",
    "gn:feature_code":"PPL",
    "gn:name":"Yangzhushan",
    "gn:population":0,
    "gn:timezone":"Asia/Shanghai",
    "iso:country":"CN",
    "name:zho_x_preferred":[
        "Yangzhushan"
    ],
    "name:zho_x_variant":[
        "\u6768\u7af9\u5c71"
    ],
    "wof:name":"Yangzhushan",
    "wof:placetype":"locality"
},
  "geometry": {"coordinates":[119.01821,31.03384],"type":"Point"}
}