{
  "type": "Feature",
  "properties": {
    "gn:admin1_code":"19.0",
    "gn:asciiname":"Beituozi",
    "gn:country_code":"CN",
    "gn:dem":18,
    "gn:feature_class":"P",
    "gn:feature_code":"PPL",
    "gn:name":"Beituozi",
    "gn:population":0,
    "gn:timezone":"Asia/Shanghai",
    "iso:country":"CN",
    "name:zho_x_preferred":[
        "\u5317\u5768\u5b50"
    ],
    "wof:name":"Beituozi",
    "wof:placetype":"locality"
},
  "geometry": {"coordinates":[122.98971,41.46029],"type":"Point"}
}