{
  "type": "Feature",
  "properties": {
    "gn:admin1_code":"2.0",
    "gn:asciiname":"Gao'er",
    "gn:country_code":"CN",
    "gn:dem":610,
    "gn:feature_class":"P",
    "gn:feature_code":"PPLA4",
    "gn:name":"Gao\u2019er",
    "gn:population":0,
    "gn:timezone":"Asia/Shanghai",
    "iso:country":"CN",
    "name:und_x_variant":[
        "Gao\u2019er",
        "Gao\u2019er Xiang",
        "Dazhekeng"
    ],
    "name:zho_x_preferred":[
        "\u9ad8\u4e8c"
    ],
    "name:zho_x_variant":[
        "\u9ad8\u4e8c\u4e61",
        "\u5927\u67d8\u5751"
    ],
    "wof:name":"Gao'er",
    "wof:placetype":"locality"
},
  "geometry": {"coordinates":[120.58051,28.92355],"type":"Point"}
}