{
  "type": "Feature",
  "properties": {
    "gn:admin1_code":"32.0",
    "gn:asciiname":"Tuqiang",
    "gn:country_code":"CN",
    "gn:dem":620,
    "gn:feature_class":"P",
    "gn:feature_code":"PPL",
    "gn:name":"Tuqiang",
    "gn:population":0,
    "gn:timezone":"Asia/Shanghai",
    "iso:country":"CN",
    "name:zho_x_preferred":[
        "\u56fe\u5f3a"
    ],
    "wof:name":"Tuqiang",
    "wof:placetype":"locality"
},
  "geometry": {"coordinates":[104.173,31.3572],"type":"Point"}
}