{
  "type": "Feature",
  "properties": {
    "gn:admin1_code":"02",
    "gn:asciiname":"Yuantou",
    "gn:country_code":"CN",
    "gn:dem":540,
    "gn:feature_class":"P",
    "gn:feature_code":"PPL",
    "gn:name":"Yuantou",
    "gn:population":0,
    "gn:timezone":"Asia/Shanghai",
    "iso:country":"CN",
    "name:zho_x_preferred":[
        "\u6e90\u5934"
    ],
    "wof:name":"Yuantou",
    "wof:placetype":"locality"
},
  "geometry": {"coordinates":[120.94722,28.44858],"type":"Point"}
}