{
  "type": "Feature",
  "properties": {
    "gn:admin1_code":"19.0",
    "gn:asciiname":"Hedonggouli",
    "gn:country_code":"CN",
    "gn:dem":184,
    "gn:feature_class":"P",
    "gn:feature_code":"PPL",
    "gn:name":"Hedonggouli",
    "gn:population":0,
    "gn:timezone":"Asia/Shanghai",
    "iso:country":"CN",
    "name:und_x_variant":[
        "\u6cb3\u4e1c\u6c9f\u91cc"
    ],
    "name:zho_x_preferred":[
        "\u6cb3\u4e1c\u6c9f\u91cc"
    ],
    "wof:name":"Hedonggouli",
    "wof:placetype":"locality"
},
  "geometry": {"coordinates":[120.09807000000001,40.69134],"type":"Point"}
}