{
  "type": "Feature",
  "properties": {
    "gn:admin1_code":"05",
    "gn:asciiname":"Huashulinzi",
    "gn:cc2":"CN",
    "gn:country_code":"CN",
    "gn:dem":243,
    "gn:feature_class":"P",
    "gn:feature_code":"PPL",
    "gn:name":"Huashulinzi",
    "gn:population":0,
    "gn:timezone":"Asia/Shanghai",
    "iso:country":"CN",
    "name:und_x_variant":[
        "Hua-shu-lin-tzu",
        "Huashulinzi"
    ],
    "wof:name":"Huashulinzi",
    "wof:placetype":"locality"
},
  "geometry": {"coordinates":[126.98833,43.21028],"type":"Point"}
}