{
  "type": "Feature",
  "properties": {
    "gn:admin1_code":"11.0",
    "gn:asciiname":"Laowuchang",
    "gn:country_code":"CN",
    "gn:dem":694,
    "gn:feature_class":"P",
    "gn:feature_code":"PPL",
    "gn:name":"Laowuchang",
    "gn:population":0,
    "gn:timezone":"Asia/Shanghai",
    "iso:country":"CN",
    "name:zho_x_preferred":[
        "\u8001\u5c4b\u573a"
    ],
    "wof:name":"Laowuchang",
    "wof:placetype":"locality"
},
  "geometry": {"coordinates":[112.32208,26.13993],"type":"Point"}
}