{
  "type": "Feature",
  "properties": {
    "gn:admin1_code":"19.0",
    "gn:asciiname":"Xiyaozi",
    "gn:country_code":"CN",
    "gn:dem":9,
    "gn:feature_class":"P",
    "gn:feature_code":"PPL",
    "gn:name":"Xiyaozi",
    "gn:population":0,
    "gn:timezone":"Asia/Shanghai",
    "iso:country":"CN",
    "name:und_x_variant":[
        "\u897f\u8170\u5b50"
    ],
    "name:zho_x_preferred":[
        "\u897f\u8170\u5b50"
    ],
    "wof:name":"Xiyaozi",
    "wof:placetype":"locality"
},
  "geometry": {"coordinates":[122.77679000000001,41.26431],"type":"Point"}
}