{
  "type": "Feature",
  "properties": {
    "gn:admin1_code":"32.0",
    "gn:asciiname":"Shunshan",
    "gn:country_code":"CN",
    "gn:dem":330,
    "gn:feature_class":"P",
    "gn:feature_code":"PPL",
    "gn:name":"Shunshan",
    "gn:population":0,
    "gn:timezone":"Asia/Shanghai",
    "iso:country":"CN",
    "name:zho_x_preferred":[
        "\u987a\u5c71"
    ],
    "wof:name":"Shunshan",
    "wof:placetype":"locality"
},
  "geometry": {"coordinates":[105.101,29.002],"type":"Point"}
}