{
  "type": "Feature",
  "properties": {
    "gn:admin1_code":"26.0",
    "gn:asciiname":"Chengzhengcun",
    "gn:country_code":"CN",
    "gn:dem":422,
    "gn:feature_class":"P",
    "gn:feature_code":"PPL",
    "gn:name":"Chengzhengcun",
    "gn:population":0,
    "gn:timezone":"Asia/Shanghai",
    "iso:country":"CN",
    "name:und_x_variant":[
        "\u7a0b\u90d1\u6751"
    ],
    "wof:name":"Chengzhengcun",
    "wof:placetype":"locality"
},
  "geometry": {"coordinates":[109.30125,34.74811],"type":"Point"}
}