{
  "type": "Feature",
  "properties": {
    "gn:admin1_code":"32.0",
    "gn:asciiname":"Liziwan",
    "gn:country_code":"CN",
    "gn:dem":359,
    "gn:feature_class":"P",
    "gn:feature_code":"PPL",
    "gn:name":"Liziwan",
    "gn:population":0,
    "gn:timezone":"Asia/Shanghai",
    "iso:country":"CN",
    "name:zho_x_preferred":[
        "\u674e\u5b50\u6e7e"
    ],
    "wof:name":"Liziwan",
    "wof:placetype":"locality"
},
  "geometry": {"coordinates":[105.67655000000001,29.09800000000001],"type":"Point"}
}