{
  "type": "Feature",
  "properties": {
    "gn:admin1_code":"11",
    "gn:asciiname":"Huazifen",
    "gn:country_code":"CN",
    "gn:dem":31,
    "gn:feature_class":"P",
    "gn:feature_code":"PPL",
    "gn:name":"Huazifen",
    "gn:population":0,
    "gn:timezone":"Asia/Shanghai",
    "iso:country":"CN",
    "name:zho_x_preferred":[
        "\u82b1\u5b50\u575f"
    ],
    "wof:name":"Huazifen",
    "wof:placetype":"locality"
},
  "geometry": {"coordinates":[112.575,29.47635],"type":"Point"}
}