{
  "type": "Feature",
  "properties": {
    "gn:admin1_code":"19.0",
    "gn:asciiname":"Xiajiagou",
    "gn:country_code":"CN",
    "gn:dem":57,
    "gn:feature_class":"P",
    "gn:feature_code":"PPL",
    "gn:name":"Xiajiagou",
    "gn:population":0,
    "gn:timezone":"Asia/Shanghai",
    "iso:country":"CN",
    "name:zho_x_preferred":[
        "\u590f\u5bb6\u6c9f"
    ],
    "wof:name":"Xiajiagou",
    "wof:placetype":"locality"
},
  "geometry": {"coordinates":[122.889,39.856],"type":"Point"}
}