{
  "type": "Feature",
  "properties": {
    "gn:admin1_code":"09",
    "gn:asciiname":"Dongyao",
    "gn:cc2":"CN",
    "gn:country_code":"CN",
    "gn:dem":417,
    "gn:feature_class":"P",
    "gn:feature_code":"PPL",
    "gn:name":"Dongyao",
    "gn:population":0,
    "gn:timezone":"Asia/Shanghai",
    "iso:country":"CN",
    "name:und_x_variant":[
        "Tung-yao",
        "Tung-yao-chi",
        "Dongyao"
    ],
    "wof:name":"Dongyao",
    "wof:placetype":"locality"
},
  "geometry": {"coordinates":[113.9525,35.89083],"type":"Point"}
}