{
  "type": "Feature",
  "properties": {
    "gn:admin1_code":"29.0",
    "gn:asciiname":"Miankulin",
    "gn:country_code":"CN",
    "gn:dem":1984,
    "gn:feature_class":"P",
    "gn:feature_code":"PPL",
    "gn:name":"Miankulin",
    "gn:population":0,
    "gn:timezone":"Asia/Shanghai",
    "iso:country":"CN",
    "name:zho_x_preferred":[
        "\u9762\u82e6\u6797"
    ],
    "wof:name":"Miankulin",
    "wof:placetype":"locality"
},
  "geometry": {"coordinates":[99.7672,24.5152],"type":"Point"}
}