{
  "type": "Feature",
  "properties": {
    "gn:admin1_code":"16.0",
    "gn:asciiname":"Diaoban",
    "gn:country_code":"CN",
    "gn:dem":230,
    "gn:feature_class":"P",
    "gn:feature_code":"PPL",
    "gn:name":"Diaoban",
    "gn:population":0,
    "gn:timezone":"Asia/Shanghai",
    "iso:country":"CN",
    "name:zho_x_preferred":[
        "\u5201\u534a"
    ],
    "wof:name":"Diaoban",
    "wof:placetype":"locality"
},
  "geometry": {"coordinates":[107.828,23.8004],"type":"Point"}
}