{
  "type": "Feature",
  "properties": {
    "gn:admin1_code":"6.0",
    "gn:asciiname":"Kesheng",
    "gn:country_code":"CN",
    "gn:dem":3420,
    "gn:feature_class":"P",
    "gn:feature_code":"PPLA4",
    "gn:name":"Kesheng",
    "gn:population":0,
    "gn:timezone":"Asia/Shanghai",
    "iso:country":"CN",
    "name:und_x_variant":[
        "Kesheng Xiang",
        "Xiangzasi"
    ],
    "name:zho_x_preferred":[
        "\u67ef\u751f"
    ],
    "name:zho_x_variant":[
        "\u67ef\u751f\u4e61",
        "\u9999\u624e\u5bfa"
    ],
    "wof:name":"Kesheng",
    "wof:placetype":"locality"
},
  "geometry": {"coordinates":[101.55288,34.20885999999999],"type":"Point"}
}