{
  "type": "Feature",
  "properties": {
    "gn:admin1_code":"21",
    "gn:asciiname":"Toudaodun",
    "gn:country_code":"CN",
    "gn:dem":1107,
    "gn:feature_class":"P",
    "gn:feature_code":"PPL",
    "gn:name":"Toudaodun",
    "gn:population":0,
    "gn:timezone":"Asia/Shanghai",
    "iso:country":"CN",
    "name:zho_x_preferred":[
        "\u5934\u9053\u58a9"
    ],
    "wof:name":"Toudaodun",
    "wof:placetype":"locality"
},
  "geometry": {"coordinates":[106.565,38.6265],"type":"Point"}
}