{
  "type": "Feature",
  "properties": {
    "gn:admin1_code":"4.0",
    "gn:asciiname":"Chunjiang",
    "gn:country_code":"CN",
    "gn:dem":9,
    "gn:feature_class":"P",
    "gn:feature_code":"PPLA4",
    "gn:name":"Chunjiang",
    "gn:population":0,
    "gn:timezone":"Asia/Shanghai",
    "iso:country":"CN",
    "name:und_x_variant":[
        "Chunjiang Zhen"
    ],
    "name:zho_x_preferred":[
        "\u6625\u6c5f"
    ],
    "name:zho_x_variant":[
        "\u6625\u6c5f\u9547"
    ],
    "wof:name":"Chunjiang",
    "wof:placetype":"locality"
},
  "geometry": {"coordinates":[119.98635,31.9471],"type":"Point"}
}