{
  "type": "Feature",
  "properties": {
    "gn:admin1_code":"5.0",
    "gn:asciiname":"Daliu Jiazicun",
    "gn:country_code":"CN",
    "gn:dem":142,
    "gn:feature_class":"P",
    "gn:feature_code":"PPL",
    "gn:name":"Daliu Jiazicun",
    "gn:population":0,
    "gn:timezone":"Asia/Shanghai",
    "iso:country":"CN",
    "name:zho_x_preferred":[
        "\u5927\u516d\u5bb6\u5b50\u6751"
    ],
    "wof:name":"Daliu Jiazicun",
    "wof:placetype":"locality"
},
  "geometry": {"coordinates":[123.05482000000001,45.51438],"type":"Point"}
}