{
  "type": "Feature",
  "properties": {
    "gn:admin1_code":"9.0",
    "gn:asciiname":"Dingzhai",
    "gn:country_code":"CN",
    "gn:dem":45,
    "gn:feature_class":"P",
    "gn:feature_code":"PPL",
    "gn:name":"Dingzhai",
    "gn:population":0,
    "gn:timezone":"Asia/Shanghai",
    "iso:country":"CN",
    "name:zho_x_preferred":[
        "\u4e01\u5be8"
    ],
    "name:zho_x_variant":[
        "\u4e01\u5be8\u6751"
    ],
    "wof:name":"Dingzhai",
    "wof:placetype":"locality"
},
  "geometry": {"coordinates":[115.04989,32.59916],"type":"Point"}
}