{
  "type": "Feature",
  "properties": {
    "gn:admin1_code":"2.0",
    "gn:asciiname":"Hudingshan",
    "gn:country_code":"CN",
    "gn:dem":433,
    "gn:feature_class":"P",
    "gn:feature_code":"PPL",
    "gn:name":"Hudingshan",
    "gn:population":0,
    "gn:timezone":"Asia/Shanghai",
    "iso:country":"CN",
    "name:zho_x_preferred":[
        "\u6e56\u9876\u5c71"
    ],
    "wof:name":"Hudingshan",
    "wof:placetype":"locality"
},
  "geometry": {"coordinates":[121.01958999999999,29.36488],"type":"Point"}
}