{
  "type": "Feature",
  "properties": {
    "gn:admin1_code":"32.0",
    "gn:asciiname":"Goujun",
    "gn:country_code":"CN",
    "gn:dem":2840,
    "gn:feature_class":"P",
    "gn:feature_code":"PPL",
    "gn:name":"Goujun",
    "gn:population":0,
    "gn:timezone":"Asia/Shanghai",
    "iso:country":"CN",
    "name:zho_x_preferred":[
        "\u82df\u5747"
    ],
    "wof:name":"Goujun",
    "wof:placetype":"locality"
},
  "geometry": {"coordinates":[103.355,33.689],"type":"Point"}
}