{
  "type": "Feature",
  "properties": {
    "gn:admin1_code":"02",
    "gn:asciiname":"Longshantou",
    "gn:cc2":"CN",
    "gn:country_code":"CN",
    "gn:dem":3,
    "gn:feature_class":"P",
    "gn:feature_code":"PPL",
    "gn:name":"Longshantou",
    "gn:population":0,
    "gn:timezone":"Asia/Shanghai",
    "iso:country":"CN",
    "name:zho_x_preferred":[
        "Lung-shan-t\u2019ou"
    ],
    "wof:name":"Longshantou",
    "wof:placetype":"locality"
},
  "geometry": {"coordinates":[120.52028,27.60778],"type":"Point"}
}