{
  "type": "Feature",
  "properties": {
    "gn:admin1_code":"30",
    "gn:asciiname":"Maweikeng",
    "gn:country_code":"CN",
    "gn:dem":115,
    "gn:feature_class":"P",
    "gn:feature_code":"PPL",
    "gn:name":"Maweikeng",
    "gn:population":0,
    "gn:timezone":"Asia/Shanghai",
    "iso:country":"CN",
    "name:zho_x_preferred":[
        "\u9a6c\u5c3e\u5751"
    ],
    "wof:name":"Maweikeng",
    "wof:placetype":"locality"
},
  "geometry": {"coordinates":[111.8468,22.52803],"type":"Point"}
}