{
  "type": "Feature",
  "properties": {
    "gn:admin1_code":"32.0",
    "gn:asciiname":"Xianjiagou",
    "gn:country_code":"CN",
    "gn:dem":475,
    "gn:feature_class":"P",
    "gn:feature_code":"PPL",
    "gn:name":"Xianjiagou",
    "gn:population":0,
    "gn:timezone":"Asia/Shanghai",
    "iso:country":"CN",
    "name:zho_x_preferred":[
        "\u9c9c\u5bb6\u6c9f"
    ],
    "wof:name":"Xianjiagou",
    "wof:placetype":"locality"
},
  "geometry": {"coordinates":[106.035,31.8198],"type":"Point"}
}