{
  "type": "Feature",
  "properties": {
    "gn:admin1_code":"25",
    "gn:asciiname":"Bolihezhuang",
    "gn:country_code":"CN",
    "gn:dem":50,
    "gn:feature_class":"P",
    "gn:feature_code":"PPL",
    "gn:name":"Bolihezhuang",
    "gn:population":0,
    "gn:timezone":"Asia/Shanghai",
    "iso:country":"CN",
    "name:zho_x_preferred":[
        "\u6ce2\u91cc\u4f55\u5e84"
    ],
    "wof:name":"Bolihezhuang",
    "wof:placetype":"locality"
},
  "geometry": {"coordinates":[115.782,35.5839],"type":"Point"}
}