{
  "type": "Feature",
  "properties": {
    "gn:admin1_code":"11",
    "gn:asciiname":"Niwanli",
    "gn:country_code":"CN",
    "gn:dem":182,
    "gn:feature_class":"P",
    "gn:feature_code":"PPL",
    "gn:name":"Niwanli",
    "gn:population":0,
    "gn:timezone":"Asia/Shanghai",
    "iso:country":"CN",
    "name:zho_x_preferred":[
        "\u6ce5\u6e7e\u91cc"
    ],
    "wof:name":"Niwanli",
    "wof:placetype":"locality"
},
  "geometry": {"coordinates":[111.355,27.7116],"type":"Point"}
}