{
  "type": "Feature",
  "properties": {
    "gn:admin1_code":"12.0",
    "gn:asciiname":"Sidaba",
    "gn:country_code":"CN",
    "gn:dem":621,
    "gn:feature_class":"P",
    "gn:feature_code":"PPL",
    "gn:name":"Sidaba",
    "gn:population":0,
    "gn:timezone":"Asia/Shanghai",
    "iso:country":"CN",
    "name:zho_x_preferred":[
        "Sidaba"
    ],
    "name:zho_x_variant":[
        "\u56db\u5927\u575d"
    ],
    "wof:name":"Sidaba",
    "wof:placetype":"locality"
},
  "geometry": {"coordinates":[109.00285,29.85278],"type":"Point"}
}