{
  "type": "Feature",
  "properties": {
    "gn:admin1_code":"7.0",
    "gn:asciiname":"Wangcuoping",
    "gn:country_code":"CN",
    "gn:dem":742,
    "gn:feature_class":"P",
    "gn:feature_code":"PPL",
    "gn:name":"Wangcuoping",
    "gn:population":0,
    "gn:timezone":"Asia/Shanghai",
    "iso:country":"CN",
    "name:zho_x_preferred":[
        "\u65fa\u539d\u576a"
    ],
    "wof:name":"Wangcuoping",
    "wof:placetype":"locality"
},
  "geometry": {"coordinates":[118.68087,26.7084],"type":"Point"}
}