{
  "type": "Feature",
  "properties": {
    "gn:admin1_code":"1.0",
    "gn:asciiname":"Shouloucun",
    "gn:country_code":"CN",
    "gn:dem":40,
    "gn:feature_class":"P",
    "gn:feature_code":"PPL",
    "gn:name":"Shouloucun",
    "gn:population":0,
    "gn:timezone":"Asia/Shanghai",
    "iso:country":"CN",
    "name:zho_x_preferred":[
        "\u5bff\u697c\u6751"
    ],
    "wof:name":"Shouloucun",
    "wof:placetype":"locality"
},
  "geometry": {"coordinates":[116.67968999999999,34.13647],"type":"Point"}
}