{
  "type": "Feature",
  "properties": {
    "gn:admin1_code":"9",
    "gn:asciiname":"Taoliwang",
    "gn:country_code":"CN",
    "gn:dem":50,
    "gn:feature_class":"P",
    "gn:feature_code":"PPL",
    "gn:name":"Taoliwang",
    "gn:population":0,
    "gn:timezone":"Asia/Shanghai",
    "iso:country":"CN",
    "name:zho_x_preferred":[
        "\u5957\u674e\u738b"
    ],
    "wof:name":"Taoliwang",
    "wof:placetype":"locality"
},
  "geometry": {"coordinates":[115.146,33.9387],"type":"Point"}
}