{
  "type": "Feature",
  "properties": {
    "gn:admin1_code":"14",
    "gn:asciiname":"Niangqie",
    "gn:country_code":"CN",
    "gn:dem":4671,
    "gn:feature_class":"P",
    "gn:feature_code":"PPL",
    "gn:name":"Niangqie",
    "gn:population":0,
    "gn:timezone":"Asia/Urumqi",
    "iso:country":"CN",
    "name:zho_x_preferred":[
        "\u5a18\u5207"
    ],
    "wof:name":"Niangqie",
    "wof:placetype":"locality"
},
  "geometry": {"coordinates":[88.22190000000001,31.0655],"type":"Point"}
}