{
  "type": "Feature",
  "properties": {
    "gn:admin1_code":"1.0",
    "gn:asciiname":"Zhongjiagang",
    "gn:cc2":"CN",
    "gn:country_code":"CN",
    "gn:dem":39,
    "gn:feature_class":"P",
    "gn:feature_code":"PPL",
    "gn:name":"Zhongjiagang",
    "gn:population":0,
    "gn:timezone":"Asia/Shanghai",
    "iso:country":"CN",
    "name:und_x_variant":[
        "Chung-chia-kang",
        "Zhongjiagang"
    ],
    "wof:name":"Zhongjiagang",
    "wof:placetype":"locality"
},
  "geometry": {"coordinates":[117.13333,31.18333],"type":"Point"}
}