{
  "type": "Feature",
  "properties": {
    "gn:admin1_code":"12",
    "gn:asciiname":"Huajiaoping",
    "gn:cc2":"CN",
    "gn:country_code":"CN",
    "gn:dem":1267,
    "gn:feature_class":"P",
    "gn:feature_code":"PPL",
    "gn:name":"Huajiaoping",
    "gn:population":0,
    "gn:timezone":"Asia/Shanghai",
    "iso:country":"CN",
    "name:und_x_variant":[
        "Hua-chiao-p\u2019ing",
        "Huajiaoping"
    ],
    "wof:name":"Huajiaoping",
    "wof:placetype":"locality"
},
  "geometry": {"coordinates":[109.05,30.21667],"type":"Point"}
}