{
  "type": "Feature",
  "properties": {
    "gn:admin1_code":"16",
    "gn:asciiname":"Chonglin",
    "gn:country_code":"CN",
    "gn:dem":794,
    "gn:feature_class":"P",
    "gn:feature_code":"PPL",
    "gn:name":"Chonglin",
    "gn:population":0,
    "gn:timezone":"Asia/Shanghai",
    "iso:country":"CN",
    "name:zho_x_preferred":[
        "\u5d07\u6797"
    ],
    "wof:name":"Chonglin",
    "wof:placetype":"locality"
},
  "geometry": {"coordinates":[110.023,25.9314],"type":"Point"}
}