{
  "type": "Feature",
  "properties": {
    "gn:admin1_code":"15.0",
    "gn:asciiname":"Zao'erping",
    "gn:country_code":"CN",
    "gn:dem":1576,
    "gn:feature_class":"P",
    "gn:feature_code":"PPL",
    "gn:name":"Zao\u2019erping",
    "gn:population":0,
    "gn:timezone":"Asia/Shanghai",
    "iso:country":"CN",
    "name:und_x_variant":[
        "Zao\u2019erping"
    ],
    "name:zho_x_preferred":[
        "\u67a3\u513f\u576a"
    ],
    "wof:name":"Zao'erping",
    "wof:placetype":"locality"
},
  "geometry": {"coordinates":[106.364,34.3127],"type":"Point"}
}