{
  "type": "Feature",
  "properties": {
    "gn:admin1_code":"9.0",
    "gn:asciiname":"Yushulin",
    "gn:country_code":"CN",
    "gn:dem":1008,
    "gn:feature_class":"P",
    "gn:feature_code":"PPL",
    "gn:name":"Yushulin",
    "gn:population":0,
    "gn:timezone":"Asia/Shanghai",
    "iso:country":"CN",
    "name:zho_x_preferred":[
        "\u6986\u6811\u6797"
    ],
    "wof:name":"Yushulin",
    "wof:placetype":"locality"
},
  "geometry": {"coordinates":[111.04033,33.88752],"type":"Point"}
}