{
  "type": "Feature",
  "properties": {
    "gn:admin1_code":"29.0",
    "gn:asciiname":"Yiminshe",
    "gn:country_code":"CN",
    "gn:dem":685,
    "gn:feature_class":"P",
    "gn:feature_code":"PPL",
    "gn:name":"Yiminshe",
    "gn:population":0,
    "gn:timezone":"Asia/Shanghai",
    "iso:country":"CN",
    "name:zho_x_preferred":[
        "\u79fb\u6c11\u793e"
    ],
    "wof:name":"Yiminshe",
    "wof:placetype":"locality"
},
  "geometry": {"coordinates":[99.5801,23.899],"type":"Point"}
}