{
  "type": "Feature",
  "properties": {
    "gn:admin1_code":"12.0",
    "gn:asciiname":"Weijiatian",
    "gn:country_code":"CN",
    "gn:dem":34,
    "gn:feature_class":"P",
    "gn:feature_code":"PPL",
    "gn:name":"Weijiatian",
    "gn:population":0,
    "gn:timezone":"Asia/Shanghai",
    "iso:country":"CN",
    "name:und_x_variant":[
        "\u9b4f\u5bb6\u7530"
    ],
    "wof:name":"Weijiatian",
    "wof:placetype":"locality"
},
  "geometry": {"coordinates":[114.88114,30.52992],"type":"Point"}
}