{
  "type": "Feature",
  "properties": {
    "gn:admin1_code":"12",
    "gn:asciiname":"Miaohe",
    "gn:country_code":"CN",
    "gn:dem":354,
    "gn:feature_class":"P",
    "gn:feature_code":"PPL",
    "gn:name":"Miaohe",
    "gn:population":0,
    "gn:timezone":"Asia/Shanghai",
    "iso:country":"CN",
    "name:und_x_variant":[
        "\u5e99\u6cb3"
    ],
    "wof:name":"Miaohe",
    "wof:placetype":"locality"
},
  "geometry": {"coordinates":[111.43322000000001,30.14954],"type":"Point"}
}