{
  "type": "Feature",
  "properties": {
    "gn:admin1_code":"3.0",
    "gn:asciiname":"Tiaoshang",
    "gn:country_code":"CN",
    "gn:dem":75,
    "gn:feature_class":"P",
    "gn:feature_code":"PPL",
    "gn:name":"Tiaoshang",
    "gn:population":0,
    "gn:timezone":"Asia/Shanghai",
    "iso:country":"CN",
    "name:zho_x_preferred":[
        "\u8df3\u4e0a"
    ],
    "wof:name":"Tiaoshang",
    "wof:placetype":"locality"
},
  "geometry": {"coordinates":[117.19061000000001,28.72002],"type":"Point"}
}