{
  "type": "Feature",
  "properties": {
    "gn:admin1_code":"2.0",
    "gn:asciiname":"Baohoucun",
    "gn:country_code":"CN",
    "gn:dem":187,
    "gn:feature_class":"P",
    "gn:feature_code":"PPL",
    "gn:name":"Baohoucun",
    "gn:population":0,
    "gn:timezone":"Asia/Shanghai",
    "iso:country":"CN",
    "name:zho_x_preferred":[
        "\u5305\u540e\u6751"
    ],
    "wof:name":"Baohoucun",
    "wof:placetype":"locality"
},
  "geometry": {"coordinates":[119.79286,28.81561],"type":"Point"}
}