{
  "type": "Feature",
  "properties": {
    "gn:admin1_code":"8.0",
    "gn:asciiname":"Fenyongcun",
    "gn:country_code":"CN",
    "gn:dem":149,
    "gn:feature_class":"P",
    "gn:feature_code":"PPL",
    "gn:name":"Fenyongcun",
    "gn:population":0,
    "gn:timezone":"Asia/Shanghai",
    "iso:country":"CN",
    "name:zho_x_preferred":[
        "\u594b\u52c7\u6751"
    ],
    "wof:name":"Fenyongcun",
    "wof:placetype":"locality"
},
  "geometry": {"coordinates":[124.92091000000001,46.65983],"type":"Point"}
}