{
  "type": "Feature",
  "properties": {
    "gn:admin1_code":"26.0",
    "gn:asciiname":"Sujiazhuangcun",
    "gn:country_code":"CN",
    "gn:dem":1049,
    "gn:feature_class":"P",
    "gn:feature_code":"PPL",
    "gn:name":"Sujiazhuangcun",
    "gn:population":0,
    "gn:timezone":"Asia/Shanghai",
    "iso:country":"CN",
    "name:zho_x_preferred":[
        "\u82cf\u5bb6\u5e84\u6751"
    ],
    "wof:name":"Sujiazhuangcun",
    "wof:placetype":"locality"
},
  "geometry": {"coordinates":[108.08508999999999,32.74692],"type":"Point"}
}