{
  "type": "Feature",
  "properties": {
    "gn:admin1_code":"19.0",
    "gn:asciiname":"Zuojiawopeng",
    "gn:country_code":"CN",
    "gn:dem":71,
    "gn:feature_class":"P",
    "gn:feature_code":"PPL",
    "gn:name":"Zuojiawopeng",
    "gn:population":0,
    "gn:timezone":"Asia/Shanghai",
    "iso:country":"CN",
    "name:zho_x_preferred":[
        "\u5de6\u5bb6\u7a9d\u68da"
    ],
    "wof:name":"Zuojiawopeng",
    "wof:placetype":"locality"
},
  "geometry": {"coordinates":[123.795,42.532],"type":"Point"}
}