{
  "type": "Feature",
  "properties": {
    "gn:admin1_code":"8.0",
    "gn:asciiname":"Xifentun",
    "gn:country_code":"CN",
    "gn:dem":327,
    "gn:feature_class":"P",
    "gn:feature_code":"PPL",
    "gn:name":"Xifentun",
    "gn:population":0,
    "gn:timezone":"Asia/Shanghai",
    "iso:country":"CN",
    "name:zho_x_preferred":[
        "\u897f\u5206\u5c6f"
    ],
    "wof:name":"Xifentun",
    "wof:placetype":"locality"
},
  "geometry": {"coordinates":[128.61401000000001,45.03125],"type":"Point"}
}