{
  "type": "Feature",
  "properties": {
    "gn:admin1_code":"19.0",
    "gn:asciiname":"Dongtaitou Gouli",
    "gn:country_code":"CN",
    "gn:dem":265,
    "gn:feature_class":"P",
    "gn:feature_code":"PPL",
    "gn:name":"Dongtaitou Gouli",
    "gn:population":0,
    "gn:timezone":"Asia/Shanghai",
    "iso:country":"CN",
    "name:zho_x_preferred":[
        "\u4e1c\u53f0\u5934\u6c9f\u91cc"
    ],
    "wof:name":"Dongtaitou Gouli",
    "wof:placetype":"locality"
},
  "geometry": {"coordinates":[120.813,41.8134],"type":"Point"}
}