{
  "type": "Feature",
  "properties": {
    "gn:admin1_code":"3.0",
    "gn:asciiname":"Hutou",
    "gn:country_code":"CN",
    "gn:dem":79,
    "gn:feature_class":"P",
    "gn:feature_code":"PPL",
    "gn:name":"Hutou",
    "gn:population":0,
    "gn:timezone":"Asia/Shanghai",
    "iso:country":"CN",
    "name:und_x_variant":[
        "\u6d52\u5934"
    ],
    "wof:name":"Hutou",
    "wof:placetype":"locality"
},
  "geometry": {"coordinates":[114.74302,27.72834000000001],"type":"Point"}
}