{
  "type": "Feature",
  "properties": {
    "gn:admin1_code":"4.0",
    "gn:asciiname":"Shuichanchang Shenghuoqu",
    "gn:country_code":"CN",
    "gn:dem":1,
    "gn:feature_class":"P",
    "gn:feature_code":"PPLF",
    "gn:name":"Shuichanchang Shenghuoqu",
    "gn:population":0,
    "gn:timezone":"Asia/Shanghai",
    "iso:country":"CN",
    "name:zho_x_preferred":[
        "\u6c34\u4ea7\u573a\u751f\u6d3b\u533a"
    ],
    "wof:name":"Shuichanchang Shenghuoqu",
    "wof:placetype":"locality"
},
  "geometry": {"coordinates":[120.15649000000001,32.6687],"type":"Point"}
}