{
  "type": "Feature",
  "properties": {
    "gn:admin1_code":"8.0",
    "gn:asciiname":"Yindifang",
    "gn:country_code":"CN",
    "gn:dem":150,
    "gn:feature_class":"P",
    "gn:feature_code":"PPL",
    "gn:name":"Yindifang",
    "gn:population":0,
    "gn:timezone":"Asia/Shanghai",
    "iso:country":"CN",
    "name:zho_x_preferred":[
        "\u5c39\u5730\u65b9"
    ],
    "wof:name":"Yindifang",
    "wof:placetype":"locality"
},
  "geometry": {"coordinates":[125.92151,45.34967],"type":"Point"}
}