{
  "type": "Feature",
  "properties": {
    "gn:admin1_code":"12.0",
    "gn:asciiname":"Baishayuan",
    "gn:country_code":"CN",
    "gn:dem":1724,
    "gn:feature_class":"P",
    "gn:feature_code":"PPL",
    "gn:name":"Baishayuan",
    "gn:population":0,
    "gn:timezone":"Asia/Shanghai",
    "iso:country":"CN",
    "name:zho_x_preferred":[
        "\u767d\u6749\u56ed"
    ],
    "wof:name":"Baishayuan",
    "wof:placetype":"locality"
},
  "geometry": {"coordinates":[110.36415,31.63742],"type":"Point"}
}