{
  "type": "Feature",
  "properties": {
    "gn:admin1_code":"7.0",
    "gn:asciiname":"Dajilong",
    "gn:country_code":"CN",
    "gn:dem":402,
    "gn:feature_class":"P",
    "gn:feature_code":"PPL",
    "gn:name":"Dajilong",
    "gn:population":0,
    "gn:timezone":"Asia/Shanghai",
    "iso:country":"CN",
    "name:zho_x_preferred":[
        "\u5927\u9645\u9f99"
    ],
    "wof:name":"Dajilong",
    "wof:placetype":"locality"
},
  "geometry": {"coordinates":[117.65174,27.20159],"type":"Point"}
}