{
  "type": "Feature",
  "properties": {
    "gn:admin1_code":"18",
    "gn:asciiname":"Chundianshu",
    "gn:country_code":"CN",
    "gn:dem":1287,
    "gn:feature_class":"P",
    "gn:feature_code":"PPL",
    "gn:name":"Chundianshu",
    "gn:population":0,
    "gn:timezone":"Asia/Shanghai",
    "iso:country":"CN",
    "name:zho_x_preferred":[
        "\u693f\u98a0\u6811"
    ],
    "wof:name":"Chundianshu",
    "wof:placetype":"locality"
},
  "geometry": {"coordinates":[106.887,28.3576],"type":"Point"}
}