{
  "type": "Feature",
  "properties": {
    "gn:admin1_code":"4.0",
    "gn:asciiname":"Xidoucang",
    "gn:country_code":"CN",
    "gn:dem":2,
    "gn:feature_class":"P",
    "gn:feature_code":"PPL",
    "gn:name":"Xidoucang",
    "gn:population":0,
    "gn:timezone":"Asia/Shanghai",
    "iso:country":"CN",
    "name:zho_x_preferred":[
        "\u897f\u6597\u4ed3"
    ],
    "wof:name":"Xidoucang",
    "wof:placetype":"locality"
},
  "geometry": {"coordinates":[120.84274000000001,32.49596],"type":"Point"}
}