{
  "type": "Feature",
  "properties": {
    "gn:admin1_code":"26.0",
    "gn:asciiname":"Jicun",
    "gn:country_code":"CN",
    "gn:dem":427,
    "gn:feature_class":"P",
    "gn:feature_code":"PPL",
    "gn:name":"Jicun",
    "gn:population":0,
    "gn:timezone":"Asia/Shanghai",
    "iso:country":"CN",
    "name:und_x_variant":[
        "\u7eaa\u6751"
    ],
    "wof:name":"Jicun",
    "wof:placetype":"locality"
},
  "geometry": {"coordinates":[109.45095999999999,34.88927],"type":"Point"}
}