{
  "type": "Feature",
  "properties": {
    "gn:admin1_code":"14.0",
    "gn:asciiname":"Zanle",
    "gn:country_code":"CN",
    "gn:dem":4180,
    "gn:feature_class":"P",
    "gn:feature_code":"PPL",
    "gn:name":"Zanle",
    "gn:population":0,
    "gn:timezone":"Asia/Urumqi",
    "iso:country":"CN",
    "name:zho_x_preferred":[
        "\u54b1\u52d2"
    ],
    "wof:name":"Zanle",
    "wof:placetype":"locality"
},
  "geometry": {"coordinates":[95.38197,30.8602],"type":"Point"}
}