{
  "type": "Feature",
  "properties": {
    "gn:admin1_code":"30.0",
    "gn:asciiname":"Wangniuling",
    "gn:country_code":"CN",
    "gn:dem":23,
    "gn:feature_class":"P",
    "gn:feature_code":"PPL",
    "gn:name":"Wangniuling",
    "gn:population":0,
    "gn:timezone":"Asia/Shanghai",
    "iso:country":"CN",
    "name:zho_x_preferred":[
        "\u671b\u725b\u5cad"
    ],
    "wof:name":"Wangniuling",
    "wof:placetype":"locality"
},
  "geometry": {"coordinates":[113.01326,22.30059],"type":"Point"}
}