{
  "type": "Feature",
  "properties": {
    "gn:admin1_code":"30.0",
    "gn:asciiname":"Xintangcun",
    "gn:country_code":"CN",
    "gn:dem":23,
    "gn:feature_class":"P",
    "gn:feature_code":"PPL",
    "gn:name":"Xintangcun",
    "gn:population":0,
    "gn:timezone":"Asia/Shanghai",
    "iso:country":"CN",
    "name:zho_x_preferred":[
        "\u65b0\u5858\u6751"
    ],
    "wof:name":"Xintangcun",
    "wof:placetype":"locality"
},
  "geometry": {"coordinates":[113.40622999999999,23.16194],"type":"Point"}
}