{
  "type": "Feature",
  "properties": {
    "gn:admin1_code":"16",
    "gn:asciiname":"Longtang",
    "gn:country_code":"CN",
    "gn:dem":494,
    "gn:feature_class":"P",
    "gn:feature_code":"PPL",
    "gn:name":"Longtang",
    "gn:population":0,
    "gn:timezone":"Asia/Shanghai",
    "iso:country":"CN",
    "name:fra_x_preferred":[
        "Lilong"
    ],
    "name:nor_x_preferred":[
        "Longtang"
    ],
    "name:zho_x_preferred":[
        "\u9f99\u5858"
    ],
    "wof:name":"Longtang",
    "wof:placetype":"locality"
},
  "geometry": {"coordinates":[110.247,25.9957],"type":"Point"}
}