{
  "type": "Feature",
  "properties": {
    "gn:admin1_code":"29.0",
    "gn:asciiname":"Huoshan",
    "gn:country_code":"CN",
    "gn:dem":2359,
    "gn:feature_class":"P",
    "gn:feature_code":"PPL",
    "gn:name":"Huoshan",
    "gn:population":0,
    "gn:timezone":"Asia/Shanghai",
    "iso:country":"CN",
    "name:zho_x_preferred":[
        "\u706b\u5c71"
    ],
    "wof:name":"Huoshan",
    "wof:placetype":"locality"
},
  "geometry": {"coordinates":[100.371,25.1972],"type":"Point"}
}