{
  "type": "Feature",
  "properties": {
    "gn:admin1_code":"10",
    "gn:asciiname":"Xingzhangtun",
    "gn:country_code":"CN",
    "gn:dem":44,
    "gn:feature_class":"P",
    "gn:feature_code":"PPL",
    "gn:name":"Xingzhangtun",
    "gn:population":0,
    "gn:timezone":"Asia/Shanghai",
    "iso:country":"CN",
    "name:zho_x_preferred":[
        "\u90a2\u5f20\u5c6f"
    ],
    "wof:name":"Xingzhangtun",
    "wof:placetype":"locality"
},
  "geometry": {"coordinates":[115.28757,36.62148],"type":"Point"}
}