{
  "type": "Feature",
  "properties": {
    "gn:admin1_code":"24.0",
    "gn:asciiname":"Yangtan",
    "gn:country_code":"CN",
    "gn:dem":565,
    "gn:feature_class":"P",
    "gn:feature_code":"PPLA4",
    "gn:name":"Yangtan",
    "gn:population":0,
    "gn:timezone":"Asia/Shanghai",
    "iso:country":"CN",
    "name:und_x_variant":[
        "Kou-hsi-ts\u2019un",
        "Yangtan",
        "\u6768\u8c08",
        "Yangtan Xiang",
        "\u6768\u8c08\u4e61"
    ],
    "wof:name":"Yangtan",
    "wof:placetype":"locality"
},
  "geometry": {"coordinates":[111.53847,35.77516],"type":"Point"}
}