{
  "type": "Feature",
  "properties": {
    "gn:admin1_code":"3.0",
    "gn:asciiname":"Huangcunwan Linchang",
    "gn:country_code":"CN",
    "gn:dem":167,
    "gn:feature_class":"P",
    "gn:feature_code":"PPLF",
    "gn:name":"Huangcunwan Linchang",
    "gn:population":0,
    "gn:timezone":"Asia/Shanghai",
    "iso:country":"CN",
    "name:und_x_variant":[
        "\u9ec4\u6751\u6e7e\u6797\u573a"
    ],
    "wof:name":"Huangcunwan Linchang",
    "wof:placetype":"locality"
},
  "geometry": {"coordinates":[117.82541000000001,29.01449],"type":"Point"}
}