{
  "type": "Feature",
  "properties": {
    "gn:admin1_code":"2",
    "gn:asciiname":"Saoshe",
    "gn:country_code":"CN",
    "gn:dem":102,
    "gn:feature_class":"P",
    "gn:feature_code":"PPL",
    "gn:name":"Saoshe",
    "gn:population":0,
    "gn:timezone":"Asia/Shanghai",
    "iso:country":"CN",
    "name:und_x_variant":[
        "\u7f2b\u820d"
    ],
    "wof:name":"Saoshe",
    "wof:placetype":"locality"
},
  "geometry": {"coordinates":[119.41379000000001,30.61811],"type":"Point"}
}