{
  "type": "Feature",
  "properties": {
    "gn:admin1_code":"3.0",
    "gn:asciiname":"Shanqian",
    "gn:country_code":"CN",
    "gn:dem":78,
    "gn:feature_class":"P",
    "gn:feature_code":"PPL",
    "gn:name":"Shanqian",
    "gn:population":0,
    "gn:timezone":"Asia/Shanghai",
    "iso:country":"CN",
    "name:und_x_variant":[
        "\u5c71\u524d",
        "Shanqiancun",
        "\u5c71\u524d\u6751"
    ],
    "wof:name":"Shanqian",
    "wof:placetype":"locality"
},
  "geometry": {"coordinates":[115.04409,27.06068],"type":"Point"}
}