{
  "type": "Feature",
  "properties": {
    "gn:admin1_code":"12.0",
    "gn:asciiname":"Baimayan",
    "gn:country_code":"CN",
    "gn:dem":82,
    "gn:feature_class":"P",
    "gn:feature_code":"PPL",
    "gn:name":"Baimayan",
    "gn:population":0,
    "gn:timezone":"Asia/Shanghai",
    "iso:country":"CN",
    "name:zho_x_preferred":[
        "Baimayan"
    ],
    "name:zho_x_variant":[
        "\u767d\u9a6c\u5830"
    ],
    "wof:name":"Baimayan",
    "wof:placetype":"locality"
},
  "geometry": {"coordinates":[111.53539000000001,30.36076],"type":"Point"}
}