{
  "type": "Feature",
  "properties": {
    "gn:admin1_code":"11.0",
    "gn:asciiname":"Banbianshan",
    "gn:country_code":"CN",
    "gn:dem":640,
    "gn:feature_class":"P",
    "gn:feature_code":"PPL",
    "gn:name":"Banbianshan",
    "gn:population":0,
    "gn:timezone":"Asia/Shanghai",
    "iso:country":"CN",
    "name:zho_x_preferred":[
        "\u534a\u8fb9\u5c71"
    ],
    "wof:name":"Banbianshan",
    "wof:placetype":"locality"
},
  "geometry": {"coordinates":[111.34496,28.47716],"type":"Point"}
}