{
  "type": "Feature",
  "properties": {
    "gn:admin1_code":"20.0",
    "gn:asciiname":"Fendou",
    "gn:country_code":"CN",
    "gn:dem":287,
    "gn:feature_class":"P",
    "gn:feature_code":"PPL",
    "gn:name":"Fendou",
    "gn:population":0,
    "gn:timezone":"Asia/Shanghai",
    "iso:country":"CN",
    "name:zho_x_preferred":[
        "\u594b\u6597"
    ],
    "wof:name":"Fendou",
    "wof:placetype":"locality"
},
  "geometry": {"coordinates":[125.00371,49.59976],"type":"Point"}
}