{
  "type": "Feature",
  "properties": {
    "gn:admin1_code":"4.0",
    "gn:asciiname":"Dongliucun",
    "gn:country_code":"CN",
    "gn:dem":4,
    "gn:feature_class":"P",
    "gn:feature_code":"PPL",
    "gn:name":"Dongliucun",
    "gn:population":0,
    "gn:timezone":"Asia/Shanghai",
    "iso:country":"CN",
    "name:zho_x_preferred":[
        "\u4e1c\u5218\u6751"
    ],
    "wof:name":"Dongliucun",
    "wof:placetype":"locality"
},
  "geometry": {"coordinates":[120.01111000000002,32.88611],"type":"Point"}
}