{
  "type": "Feature",
  "properties": {
    "gn:admin1_code":"6.0",
    "gn:asciiname":"Ri'akao",
    "gn:country_code":"CN",
    "gn:dem":4103,
    "gn:feature_class":"P",
    "gn:feature_code":"PPL",
    "gn:name":"Ri\u2019akao",
    "gn:population":0,
    "gn:timezone":"Asia/Urumqi",
    "iso:country":"CN",
    "name:und_x_variant":[
        "Ri\u2019akao"
    ],
    "name:zho_x_preferred":[
        "\u65e5\u963f\u8003"
    ],
    "wof:name":"Ri'akao",
    "wof:placetype":"locality"
},
  "geometry": {"coordinates":[97.02516,32.94144],"type":"Point"}
}