{
  "type": "Feature",
  "properties": {
    "gn:admin1_code":"20.0",
    "gn:asciiname":"Qihao",
    "gn:country_code":"CN",
    "gn:dem":1060,
    "gn:feature_class":"P",
    "gn:feature_code":"PPL",
    "gn:name":"Qihao",
    "gn:population":0,
    "gn:timezone":"Asia/Shanghai",
    "iso:country":"CN",
    "name:zho_x_preferred":[
        "\u4e03\u53f7"
    ],
    "wof:name":"Qihao",
    "wof:placetype":"locality"
},
  "geometry": {"coordinates":[100.27718,41.1044],"type":"Point"}
}