{
  "type": "Feature",
  "properties": {
    "gn:admin1_code":"4.0",
    "gn:asciiname":"Dongbei",
    "gn:country_code":"CN",
    "gn:dem":4,
    "gn:feature_class":"P",
    "gn:feature_code":"PPL",
    "gn:name":"Dongbei",
    "gn:population":0,
    "gn:timezone":"Asia/Shanghai",
    "iso:country":"CN",
    "name:und_x_variant":[
        "\u8463\u5317"
    ],
    "name:zho_x_preferred":[
        "\u8463\u5317"
    ],
    "wof:name":"Dongbei",
    "wof:placetype":"locality"
},
  "geometry": {"coordinates":[120.10992,32.73954000000001],"type":"Point"}
}