{
  "type": "Feature",
  "properties": {
    "gn:admin1_code":"25.0",
    "gn:asciiname":"Yanggezhuang",
    "gn:country_code":"CN",
    "gn:dem":27,
    "gn:feature_class":"P",
    "gn:feature_code":"PPL",
    "gn:name":"Yanggezhuang",
    "gn:population":0,
    "gn:timezone":"Asia/Shanghai",
    "iso:country":"CN",
    "name:zho_x_preferred":[
        "\u6768\u6208\u5e84"
    ],
    "wof:name":"Yanggezhuang",
    "wof:placetype":"locality"
},
  "geometry": {"coordinates":[120.00979,36.3147],"type":"Point"}
}