{
  "type": "Feature",
  "properties": {
    "gn:admin1_code":"30",
    "gn:asciiname":"Bengxi",
    "gn:country_code":"CN",
    "gn:dem":256,
    "gn:feature_class":"P",
    "gn:feature_code":"PPL",
    "gn:name":"Bengxi",
    "gn:population":0,
    "gn:timezone":"Asia/Shanghai",
    "iso:country":"CN",
    "name:zho_x_preferred":[
        "\u868c\u6eaa"
    ],
    "wof:name":"Bengxi",
    "wof:placetype":"locality"
},
  "geometry": {"coordinates":[112.49388999999999,23.59833],"type":"Point"}
}