{
  "type": "Feature",
  "properties": {
    "gn:admin1_code":"32.0",
    "gn:asciiname":"Mole",
    "gn:country_code":"CN",
    "gn:dem":3845,
    "gn:feature_class":"P",
    "gn:feature_code":"PPL",
    "gn:name":"Mole",
    "gn:population":0,
    "gn:timezone":"Asia/Shanghai",
    "iso:country":"CN",
    "name:ceb_x_preferred":[
        "Mole"
    ],
    "name:deu_x_preferred":[
        "Mole"
    ],
    "name:ell_x_preferred":[
        "Mole"
    ],
    "name:fin_x_preferred":[
        "Myyr\u00e4"
    ],
    "name:fra_x_preferred":[
        "Mole"
    ],
    "name:ita_x_preferred":[
        "Mole"
    ],
    "name:jpn_x_preferred":[
        "\u3082\u3050\u3089"
    ],
    "name:nld_x_preferred":[
        "Mole"
    ],
    "name:nor_x_preferred":[
        "Mole"
    ],
    "name:pol_x_preferred":[
        "Mole"
    ],
    "name:por_x_preferred":[
        "Mole"
    ],
    "name:spa_x_preferred":[
        "Mole"
    ],
    "name:swe_x_preferred":[
        "Mole"
    ],
    "name:zho_x_preferred":[
        "\u78e8\u52d2"
    ],
    "wof:name":"Mole",
    "wof:placetype":"locality"
},
  "geometry": {"coordinates":[98.9616,32.528],"type":"Point"}
}