{
  "type": "Feature",
  "properties": {
    "gn:admin1_code":"07",
    "gn:asciiname":"Taiping",
    "gn:country_code":"CN",
    "gn:dem":60,
    "gn:feature_class":"P",
    "gn:feature_code":"PPLA4",
    "gn:name":"Taiping",
    "gn:population":0,
    "gn:timezone":"Asia/Shanghai",
    "iso:country":"CN",
    "name:ceb_x_preferred":[
        "Taiping"
    ],
    "name:deu_x_preferred":[
        "Taiping"
    ],
    "name:fra_x_preferred":[
        "Taiping"
    ],
    "name:hun_x_preferred":[
        "Taiping"
    ],
    "name:ind_x_preferred":[
        "Taiping"
    ],
    "name:msa_x_preferred":[
        "Taiping"
    ],
    "name:nld_x_preferred":[
        "Taiping"
    ],
    "name:rus_x_preferred":[
        "\u0422\u0430\u0439\u043f\u0438\u043d"
    ],
    "name:swe_x_preferred":[
        "Taiping"
    ],
    "name:und_x_variant":[
        "\u592a\u5e73",
        "Taiping Zhen",
        "\u592a\u5e73\u9547"
    ],
    "wof:name":"Taiping",
    "wof:placetype":"locality"
},
  "geometry": {"coordinates":[118.41869,26.44567],"type":"Point"}
}