{
  "type": "Feature",
  "properties": {
    "gn:admin1_code":"18",
    "gn:asciiname":"Lishuwan",
    "gn:country_code":"CN",
    "gn:dem":1220,
    "gn:feature_class":"P",
    "gn:feature_code":"PPL",
    "gn:name":"Lishuwan",
    "gn:population":0,
    "gn:timezone":"Asia/Shanghai",
    "iso:country":"CN",
    "name:zho_x_preferred":[
        "\u6817\u6811\u6e7e"
    ],
    "wof:name":"Lishuwan",
    "wof:placetype":"locality"
},
  "geometry": {"coordinates":[106.11,25.9718],"type":"Point"}
}