{
  "type": "Feature",
  "properties": {
    "gn:admin1_code":"30.0",
    "gn:asciiname":"Xilian",
    "gn:country_code":"CN",
    "gn:dem":20,
    "gn:feature_class":"P",
    "gn:feature_code":"PPLA4",
    "gn:name":"Xilian",
    "gn:population":0,
    "gn:timezone":"Asia/Urumqi",
    "iso:country":"CN",
    "name:und_x_variant":[
        "Hsi-lien",
        "Xilian",
        "Xilian Zhen",
        "\u897f\u8fde\u9547"
    ],
    "name:zho_x_preferred":[
        "\u897f\u8fde"
    ],
    "wof:name":"Xilian",
    "wof:placetype":"locality"
},
  "geometry": {"coordinates":[109.94544999999999,20.38003],"type":"Point"}
}