{
  "type": "Feature",
  "properties": {
    "gn:admin1_code":"4.0",
    "gn:asciiname":"Yunting",
    "gn:country_code":"CN",
    "gn:dem":12,
    "gn:feature_class":"P",
    "gn:feature_code":"PPLA4",
    "gn:name":"Yunting",
    "gn:population":0,
    "gn:timezone":"Asia/Shanghai",
    "iso:country":"CN",
    "name:und_x_variant":[
        "Y\u00fcn-t\u2019ing-chen",
        "Yunting",
        "\u4e91\u4ead",
        "Yunting Zhen"
    ],
    "wof:name":"Yunting",
    "wof:placetype":"locality"
},
  "geometry": {"coordinates":[120.33727,31.86441],"type":"Point"}
}