{
  "type": "Feature",
  "properties": {
    "gn:admin1_code":"9",
    "gn:asciiname":"Liulitang",
    "gn:country_code":"CN",
    "gn:dem":57,
    "gn:feature_class":"P",
    "gn:feature_code":"PPL",
    "gn:name":"Liulitang",
    "gn:population":0,
    "gn:timezone":"Asia/Shanghai",
    "iso:country":"CN",
    "name:zho_x_preferred":[
        "\u5218\u674e\u5802"
    ],
    "wof:name":"Liulitang",
    "wof:placetype":"locality"
},
  "geometry": {"coordinates":[114.968,34.2625],"type":"Point"}
}