{
  "type": "Feature",
  "properties": {
    "gn:admin1_code":"19.0",
    "gn:asciiname":"Xinkai",
    "gn:country_code":"CN",
    "gn:dem":234,
    "gn:feature_class":"P",
    "gn:feature_code":"PPL",
    "gn:name":"Xinkai",
    "gn:population":0,
    "gn:timezone":"Asia/Shanghai",
    "iso:country":"CN",
    "name:pol_x_preferred":[
        "Xinkai"
    ],
    "name:rus_x_preferred":[
        "Xinkai"
    ],
    "name:und_x_variant":[
        "\u65b0\u5f00"
    ],
    "name:zho_x_preferred":[
        "\u65b0\u5f00"
    ],
    "wof:name":"Xinkai",
    "wof:placetype":"locality"
},
  "geometry": {"coordinates":[124.40786,40.89462],"type":"Point"}
}