{
  "type": "Feature",
  "properties": {
    "gn:admin1_code":"1.0",
    "gn:asciiname":"Shenbincun",
    "gn:country_code":"CN",
    "gn:dem":22,
    "gn:feature_class":"P",
    "gn:feature_code":"PPL",
    "gn:name":"Shenbincun",
    "gn:population":0,
    "gn:timezone":"Asia/Shanghai",
    "iso:country":"CN",
    "name:zho_x_preferred":[
        "\u6c88\u658c\u6751"
    ],
    "wof:name":"Shenbincun",
    "wof:placetype":"locality"
},
  "geometry": {"coordinates":[117.71771,31.4353],"type":"Point"}
}