{
  "type": "Feature",
  "properties": {
    "gn:admin1_code":"30.0",
    "gn:asciiname":"Tangbian",
    "gn:country_code":"CN",
    "gn:dem":57,
    "gn:feature_class":"P",
    "gn:feature_code":"PPL",
    "gn:name":"Tangbian",
    "gn:population":0,
    "gn:timezone":"Asia/Shanghai",
    "iso:country":"CN",
    "name:zho_x_preferred":[
        "Tangbian"
    ],
    "name:zho_x_variant":[
        "\u5858\u8fb9"
    ],
    "wof:name":"Tangbian",
    "wof:placetype":"locality"
},
  "geometry": {"coordinates":[112.74417,24.45167],"type":"Point"}
}