{
  "type": "Feature",
  "properties": {
    "gn:admin1_code":"10",
    "gn:asciiname":"Shapoyu",
    "gn:cc2":"CN",
    "gn:country_code":"CN",
    "gn:dem":174,
    "gn:feature_class":"P",
    "gn:feature_code":"PPL",
    "gn:name":"Shapoyu",
    "gn:population":0,
    "gn:timezone":"Asia/Shanghai",
    "iso:country":"CN",
    "name:und_x_variant":[
        "Sha-p\u2019o-y\u00fc-k\u2019ou",
        "Shapoyu"
    ],
    "wof:name":"Shapoyu",
    "wof:placetype":"locality"
},
  "geometry": {"coordinates":[117.87667,40.27639],"type":"Point"}
}