{
  "type": "Feature",
  "properties": {
    "gn:admin1_code":"8.0",
    "gn:asciiname":"Fula'erji",
    "gn:country_code":"CN",
    "gn:dem":124,
    "gn:feature_class":"P",
    "gn:feature_code":"PPL",
    "gn:name":"Fula\u2019erji",
    "gn:population":0,
    "gn:timezone":"Asia/Yakutsk",
    "iso:country":"CN",
    "name:und_x_variant":[
        "Fula\u2019erji",
        "\u5bcc\u62c9\u5c14\u57fa"
    ],
    "wof:name":"Fula'erji",
    "wof:placetype":"locality"
},
  "geometry": {"coordinates":[127.51044,49.85122],"type":"Point"}
}