{
  "type": "Feature",
  "properties": {
    "gn:admin1_code":"7.0",
    "gn:asciiname":"Dachen",
    "gn:country_code":"CN",
    "gn:dem":652,
    "gn:feature_class":"P",
    "gn:feature_code":"PPL",
    "gn:name":"Dachen",
    "gn:population":0,
    "gn:timezone":"Asia/Shanghai",
    "iso:country":"CN",
    "name:zho_x_preferred":[
        "\u5927\u9648"
    ],
    "wof:name":"Dachen",
    "wof:placetype":"locality"
},
  "geometry": {"coordinates":[118.56399999999999,25.49564],"type":"Point"}
}