{
  "type": "Feature",
  "properties": {
    "gn:admin1_code":"9.0",
    "gn:asciiname":"Zhongliuzhuang",
    "gn:country_code":"CN",
    "gn:dem":71,
    "gn:feature_class":"P",
    "gn:feature_code":"PPL",
    "gn:name":"Zhongliuzhuang",
    "gn:population":0,
    "gn:timezone":"Asia/Shanghai",
    "iso:country":"CN",
    "name:zho_x_preferred":[
        "\u4e2d\u5218\u5e84"
    ],
    "wof:name":"Zhongliuzhuang",
    "wof:placetype":"locality"
},
  "geometry": {"coordinates":[114.58789,35.03755],"type":"Point"}
}