{
  "type": "Feature",
  "properties": {
    "gn:admin1_code":"11.0",
    "gn:asciiname":"Zhushu",
    "gn:country_code":"CN",
    "gn:dem":258,
    "gn:feature_class":"P",
    "gn:feature_code":"PPL",
    "gn:name":"Zhushu",
    "gn:population":0,
    "gn:timezone":"Asia/Shanghai",
    "iso:country":"CN",
    "name:zho_x_preferred":[
        "\u682a\u6811"
    ],
    "wof:name":"Zhushu",
    "wof:placetype":"locality"
},
  "geometry": {"coordinates":[112.78355999999999,26.13667],"type":"Point"}
}