{
  "type": "Feature",
  "properties": {
    "gn:admin1_code":"12.0",
    "gn:asciiname":"Nihezhai",
    "gn:country_code":"CN",
    "gn:dem":100,
    "gn:feature_class":"P",
    "gn:feature_code":"PPL",
    "gn:name":"Nihezhai",
    "gn:population":0,
    "gn:timezone":"Asia/Shanghai",
    "iso:country":"CN",
    "name:zho_x_preferred":[
        "\u6ce5\u6cb3\u5be8"
    ],
    "wof:name":"Nihezhai",
    "wof:placetype":"locality"
},
  "geometry": {"coordinates":[113.24151000000001,31.89732],"type":"Point"}
}