{
  "type": "Feature",
  "properties": {
    "gn:admin1_code":"7.0",
    "gn:asciiname":"Qingguansi",
    "gn:country_code":"CN",
    "gn:dem":57,
    "gn:feature_class":"P",
    "gn:feature_code":"PPL",
    "gn:name":"Qingguansi",
    "gn:population":0,
    "gn:timezone":"Asia/Shanghai",
    "iso:country":"CN",
    "name:zho_x_preferred":[
        "\u9752\u5b98\u53f8"
    ],
    "wof:name":"Qingguansi",
    "wof:placetype":"locality"
},
  "geometry": {"coordinates":[120.23641000000001,26.96416],"type":"Point"}
}