{
  "type": "Feature",
  "properties": {
    "gn:admin1_code":"25",
    "gn:asciiname":"Nigouzi",
    "gn:country_code":"CN",
    "gn:dem":153,
    "gn:feature_class":"P",
    "gn:feature_code":"PPL",
    "gn:name":"Nigouzi",
    "gn:population":0,
    "gn:timezone":"Asia/Shanghai",
    "iso:country":"CN",
    "name:zho_x_preferred":[
        "\u6ce5\u6c9f\u5b50"
    ],
    "wof:name":"Nigouzi",
    "wof:placetype":"locality"
},
  "geometry": {"coordinates":[118.961,35.5224],"type":"Point"}
}