{
  "type": "Feature",
  "properties": {
    "gn:admin1_code":"3.0",
    "gn:asciiname":"Liuyuan",
    "gn:country_code":"CN",
    "gn:dem":95,
    "gn:feature_class":"P",
    "gn:feature_code":"PPL",
    "gn:name":"Liuyuan",
    "gn:population":0,
    "gn:timezone":"Asia/Shanghai",
    "iso:country":"CN",
    "name:und_x_variant":[
        "\u5218\u6e90"
    ],
    "wof:name":"Liuyuan",
    "wof:placetype":"locality"
},
  "geometry": {"coordinates":[116.5459,27.69817],"type":"Point"}
}