{
  "type": "Feature",
  "properties": {
    "gn:admin1_code":"19.0",
    "gn:asciiname":"Laoranfang",
    "gn:country_code":"CN",
    "gn:dem":6,
    "gn:feature_class":"P",
    "gn:feature_code":"PPL",
    "gn:name":"Laoranfang",
    "gn:population":0,
    "gn:timezone":"Asia/Shanghai",
    "iso:country":"CN",
    "name:und_x_variant":[
        "\u8001\u67d3\u623f"
    ],
    "name:zho_x_preferred":[
        "\u8001\u67d3\u623f"
    ],
    "wof:name":"Laoranfang",
    "wof:placetype":"locality"
},
  "geometry": {"coordinates":[121.73118999999998,39.47144],"type":"Point"}
}