{
  "type": "Feature",
  "properties": {
    "gn:admin1_code":"26.0",
    "gn:asciiname":"Yangyaoze",
    "gn:country_code":"CN",
    "gn:dem":1138,
    "gn:feature_class":"P",
    "gn:feature_code":"PPL",
    "gn:name":"Yangyaoze",
    "gn:population":0,
    "gn:timezone":"Asia/Shanghai",
    "iso:country":"CN",
    "name:zho_x_preferred":[
        "\u6768\u7a91\u5219"
    ],
    "wof:name":"Yangyaoze",
    "wof:placetype":"locality"
},
  "geometry": {"coordinates":[109.4093,38.16697],"type":"Point"}
}