{
  "type": "Feature",
  "properties": {
    "gn:admin1_code":"3.0",
    "gn:asciiname":"Dadeshan Linchang",
    "gn:country_code":"CN",
    "gn:dem":157,
    "gn:feature_class":"P",
    "gn:feature_code":"PPLF",
    "gn:name":"Dadeshan Linchang",
    "gn:population":0,
    "gn:timezone":"Asia/Shanghai",
    "iso:country":"CN",
    "name:und_x_variant":[
        "\u5927\u5fb7\u5c71\u6797\u573a"
    ],
    "wof:name":"Dadeshan Linchang",
    "wof:placetype":"locality"
},
  "geometry": {"coordinates":[115.38108,29.61082],"type":"Point"}
}