{
  "type": "Feature",
  "properties": {
    "gn:admin1_code":"11.0",
    "gn:asciiname":"Yajiangqiao",
    "gn:cc2":"CN",
    "gn:country_code":"CN",
    "gn:dem":124,
    "gn:feature_class":"P",
    "gn:feature_code":"PPL",
    "gn:name":"Yajiangqiao",
    "gn:population":0,
    "gn:timezone":"Asia/Shanghai",
    "iso:country":"CN",
    "name:und_x_variant":[
        "Ya-chiang-ch\u2019iao",
        "Yajiangqiao"
    ],
    "name:urd_x_preferred":[
        "\u06cc\u0627\u062c\u06cc\u0646\u06af\u0642\u0627\u0624"
    ],
    "name:zho_x_preferred":[
        "\u4e2b\u6c5f\u6865\u9547"
    ],
    "wof:name":"Yajiangqiao",
    "wof:placetype":"locality"
},
  "geometry": {"coordinates":[113.31,27.2825],"type":"Point"}
}