{
  "type": "Feature",
  "properties": {
    "gn:admin1_code":"18.0",
    "gn:asciiname":"Shili",
    "gn:country_code":"CN",
    "gn:dem":1718,
    "gn:feature_class":"P",
    "gn:feature_code":"PPL",
    "gn:name":"Shili",
    "gn:population":0,
    "gn:timezone":"Asia/Shanghai",
    "iso:country":"CN",
    "wof:name":"Shili",
    "wof:placetype":"locality"
},
  "geometry": {"coordinates":[104.77083,25.625],"type":"Point"}
}