{
  "type": "Feature",
  "properties": {
    "gn:admin1_code":"21",
    "gn:asciiname":"Langbuzhang",
    "gn:country_code":"CN",
    "gn:dem":1536,
    "gn:feature_class":"P",
    "gn:feature_code":"PPL",
    "gn:name":"Langbuzhang",
    "gn:population":0,
    "gn:timezone":"Asia/Shanghai",
    "iso:country":"CN",
    "name:zho_x_preferred":[
        "\u72fc\u5e03\u638c"
    ],
    "wof:name":"Langbuzhang",
    "wof:placetype":"locality"
},
  "geometry": {"coordinates":[106.792,37.2656],"type":"Point"}
}