{
  "type": "Feature",
  "properties": {
    "gn:admin1_code":"9.0",
    "gn:asciiname":"Zhaobaigou",
    "gn:country_code":"CN",
    "gn:dem":946,
    "gn:feature_class":"P",
    "gn:feature_code":"PPL",
    "gn:name":"Zhaobaigou",
    "gn:population":0,
    "gn:timezone":"Asia/Shanghai",
    "iso:country":"CN",
    "name:zho_x_preferred":[
        "\u8d75\u767d\u6c9f"
    ],
    "wof:name":"Zhaobaigou",
    "wof:placetype":"locality"
},
  "geometry": {"coordinates":[110.83644,33.93028],"type":"Point"}
}