{
  "type": "Feature",
  "properties": {
    "gn:admin1_code":"9",
    "gn:asciiname":"Liukuizhaixi",
    "gn:country_code":"CN",
    "gn:dem":47,
    "gn:feature_class":"P",
    "gn:feature_code":"PPL",
    "gn:name":"Liukuizhaixi",
    "gn:population":0,
    "gn:timezone":"Asia/Shanghai",
    "iso:country":"CN",
    "name:zho_x_preferred":[
        "\u5218\u594e\u658b\u897f"
    ],
    "wof:name":"Liukuizhaixi",
    "wof:placetype":"locality"
},
  "geometry": {"coordinates":[115.82899999999999,35.9625],"type":"Point"}
}