{
  "type": "Feature",
  "properties": {
    "gn:admin1_code":"26.0",
    "gn:asciiname":"Baijiazhuang",
    "gn:country_code":"CN",
    "gn:dem":1231,
    "gn:feature_class":"P",
    "gn:feature_code":"PPL",
    "gn:name":"Baijiazhuang",
    "gn:population":0,
    "gn:timezone":"Asia/Shanghai",
    "iso:country":"CN",
    "name:und_x_variant":[
        "\u767d\u5bb6\u5e84"
    ],
    "wof:name":"Baijiazhuang",
    "wof:placetype":"locality"
},
  "geometry": {"coordinates":[106.5822,33.47067],"type":"Point"}
}