{
  "type": "Feature",
  "properties": {
    "gn:admin1_code":"8.0",
    "gn:asciiname":"Xingshengcun",
    "gn:country_code":"CN",
    "gn:dem":241,
    "gn:feature_class":"P",
    "gn:feature_code":"PPL",
    "gn:name":"Xingshengcun",
    "gn:population":0,
    "gn:timezone":"Asia/Shanghai",
    "iso:country":"CN",
    "name:zho_x_preferred":[
        "\u5174\u80dc\u6751"
    ],
    "wof:name":"Xingshengcun",
    "wof:placetype":"locality"
},
  "geometry": {"coordinates":[125.01725999999999,48.29461],"type":"Point"}
}