{
  "type": "Feature",
  "properties": {
    "gn:admin1_code":"32.0",
    "gn:asciiname":"Wushengmiao",
    "gn:country_code":"CN",
    "gn:dem":440,
    "gn:feature_class":"P",
    "gn:feature_code":"PPL",
    "gn:name":"Wushengmiao",
    "gn:population":0,
    "gn:timezone":"Asia/Shanghai",
    "iso:country":"CN",
    "name:zho_x_preferred":[
        "\u4e94\u5723\u5e99"
    ],
    "wof:name":"Wushengmiao",
    "wof:placetype":"locality"
},
  "geometry": {"coordinates":[106.56399999999999,30.7155],"type":"Point"}
}