{
  "type": "Feature",
  "properties": {
    "gn:admin1_code":"13",
    "gn:asciiname":"Kala'asiti",
    "gn:country_code":"CN",
    "gn:dem":1026,
    "gn:feature_class":"P",
    "gn:feature_code":"PPL",
    "gn:name":"Kala\u2019asiti",
    "gn:population":0,
    "gn:timezone":"Asia/Shanghai",
    "iso:country":"CN",
    "name:und_x_variant":[
        "Kala\u2019asiti",
        "\u5580\u62c9\u963f\u65af\u63d0"
    ],
    "wof:name":"Kala'asiti",
    "wof:placetype":"locality"
},
  "geometry": {"coordinates":[80.92103,40.46606],"type":"Point"}
}