{
  "type": "Feature",
  "properties": {
    "gn:admin1_code":"7",
    "gn:asciiname":"Houjia",
    "gn:country_code":"CN",
    "gn:dem":914,
    "gn:feature_class":"P",
    "gn:feature_code":"PPLA4",
    "gn:name":"Houjia",
    "gn:population":0,
    "gn:timezone":"Asia/Shanghai",
    "iso:country":"CN",
    "name:und_x_variant":[
        "Houjia Xiang"
    ],
    "name:zho_x_preferred":[
        "\u540e\u4f73"
    ],
    "name:zho_x_variant":[
        "\u540e\u4f73\u4e61"
    ],
    "wof:name":"Houjia",
    "wof:placetype":"locality"
},
  "geometry": {"coordinates":[118.54872,26.03681],"type":"Point"}
}