{
  "type": "Feature",
  "properties": {
    "gn:admin1_code":"3.0",
    "gn:asciiname":"Yanli",
    "gn:country_code":"CN",
    "gn:dem":27,
    "gn:feature_class":"P",
    "gn:feature_code":"PPL",
    "gn:name":"Yanli",
    "gn:population":0,
    "gn:timezone":"Asia/Shanghai",
    "iso:country":"CN",
    "name:und_x_variant":[
        "\u664f\u91cc"
    ],
    "wof:name":"Yanli",
    "wof:placetype":"locality"
},
  "geometry": {"coordinates":[115.79447999999999,28.96115],"type":"Point"}
}