{
  "type": "Feature",
  "properties": {
    "gn:admin1_code":"25",
    "gn:asciiname":"Beitingshui",
    "gn:country_code":"CN",
    "gn:dem":115,
    "gn:feature_class":"P",
    "gn:feature_code":"PPL",
    "gn:name":"Beitingshui",
    "gn:population":0,
    "gn:timezone":"Asia/Shanghai",
    "iso:country":"CN",
    "name:zho_x_preferred":[
        "\u5317\u6c40\u6c34"
    ],
    "wof:name":"Beitingshui",
    "wof:placetype":"locality"
},
  "geometry": {"coordinates":[118.62,35.4202],"type":"Point"}
}