{
  "type": "Feature",
  "properties": {
    "gn:admin1_code":"15",
    "gn:asciiname":"Pinggou",
    "gn:country_code":"CN",
    "gn:dem":2321,
    "gn:feature_class":"P",
    "gn:feature_code":"PPL",
    "gn:name":"Pinggou",
    "gn:population":0,
    "gn:timezone":"Asia/Shanghai",
    "iso:country":"CN",
    "wof:name":"Pinggou",
    "wof:placetype":"locality"
},
  "geometry": {"coordinates":[103.05056,36.16111],"type":"Point"}
}