{
  "type": "Feature",
  "properties": {
    "gn:admin1_code":"19",
    "gn:asciiname":"Sunjiapu",
    "gn:cc2":"CN",
    "gn:country_code":"CN",
    "gn:dem":16,
    "gn:feature_class":"P",
    "gn:feature_code":"PPL",
    "gn:name":"Sunjiapu",
    "gn:population":0,
    "gn:timezone":"Asia/Shanghai",
    "iso:country":"CN",
    "name:und_x_variant":[
        "Sun-chia-p\u2019u",
        "Sunjiapu"
    ],
    "wof:name":"Sunjiapu",
    "wof:placetype":"locality"
},
  "geometry": {"coordinates":[124.21193999999998,39.9975],"type":"Point"}
}