{
  "type": "Feature",
  "properties": {
    "gn:admin1_code":"30.0",
    "gn:asciiname":"Tanbeizhai",
    "gn:country_code":"CN",
    "gn:dem":560,
    "gn:feature_class":"P",
    "gn:feature_code":"PPL",
    "gn:name":"Tanbeizhai",
    "gn:population":0,
    "gn:timezone":"Asia/Shanghai",
    "iso:country":"CN",
    "name:zho_x_preferred":[
        "\u6ee9\u9642\u5be8"
    ],
    "wof:name":"Tanbeizhai",
    "wof:placetype":"locality"
},
  "geometry": {"coordinates":[114.20283999999999,25.20666],"type":"Point"}
}