{
  "type": "Feature",
  "properties": {
    "gn:admin1_code":"16.0",
    "gn:asciiname":"Kanhuai",
    "gn:country_code":"CN",
    "gn:dem":898,
    "gn:feature_class":"P",
    "gn:feature_code":"PPL",
    "gn:name":"Kanhuai",
    "gn:population":0,
    "gn:timezone":"Asia/Shanghai",
    "iso:country":"CN",
    "name:zho_x_preferred":[
        "\u582a\u6000"
    ],
    "wof:name":"Kanhuai",
    "wof:placetype":"locality"
},
  "geometry": {"coordinates":[106.04600000000001,23.2384],"type":"Point"}
}