{
  "type": "Feature",
  "properties": {
    "gn:admin1_code":"3",
    "gn:asciiname":"Zhongtang",
    "gn:country_code":"CN",
    "gn:dem":120,
    "gn:feature_class":"P",
    "gn:feature_code":"PPL",
    "gn:name":"Zhongtang",
    "gn:population":0,
    "gn:timezone":"Asia/Shanghai",
    "iso:country":"CN",
    "name:sco_x_preferred":[
        "Zhongtang"
    ],
    "name:zho_x_preferred":[
        "\u4e2d\u5858"
    ],
    "wof:name":"Zhongtang",
    "wof:placetype":"locality"
},
  "geometry": {"coordinates":[115.01027999999999,26.1251],"type":"Point"}
}