{
  "type": "Feature",
  "properties": {
    "gn:admin1_code":"23",
    "gn:asciiname":"Sijing",
    "gn:country_code":"CN",
    "gn:dem":8,
    "gn:feature_class":"P",
    "gn:feature_code":"PPLA4",
    "gn:name":"Sijing",
    "gn:population":0,
    "gn:timezone":"Asia/Shanghai",
    "iso:country":"CN",
    "name:und_x_variant":[
        "Szeking",
        "Ssu-ching-chen",
        "Ssu-ching",
        "Sijing",
        "\u6cd7\u6cfe",
        "Sijing Zhen"
    ],
    "wof:name":"Sijing",
    "wof:placetype":"locality"
},
  "geometry": {"coordinates":[121.26833000000001,31.11444],"type":"Point"}
}