{
  "type": "Feature",
  "properties": {
    "gn:admin1_code":"19",
    "gn:asciiname":"Sandaoguan Linchang",
    "gn:country_code":"CN",
    "gn:dem":469,
    "gn:feature_class":"P",
    "gn:feature_code":"PPLF",
    "gn:name":"Sandaoguan Linchang",
    "gn:population":0,
    "gn:timezone":"Asia/Shanghai",
    "iso:country":"CN",
    "name:und_x_variant":[
        "\u4e09\u9053\u5173\u6797\u573a"
    ],
    "wof:name":"Sandaoguan Linchang",
    "wof:placetype":"locality"
},
  "geometry": {"coordinates":[124.58064,41.55606],"type":"Point"}
}