{
  "type": "Feature",
  "properties": {
    "iso:country":"CN",
    "qs:name":"\u51e4\u9633\u53bf",
    "qs:name_adm0":"\u4e2d\u570b",
    "qs:name_adm1":"\u5b89\u5fbd\u7701",
    "qs:photos":2,
    "qs:photos_1k":1,
    "qs:photos_9k":1,
    "qs:photos_9r":1,
    "qs:photos_all":21,
    "qs:photos_sr":1,
    "qs:placetype":"LocalAdmin",
    "qs:pop_sr":"0",
    "wd:wordcount":510,
    "wof:name":"\u51e4\u9633\u53bf",
    "wof:placetype":"localadmin"
},
  "geometry": {"coordinates":[117.561092,32.856229],"type":"Point"}
}