{
  "type": "Feature",
  "properties": {
    "gn:admin1_code":"29",
    "gn:asciiname":"Longxi",
    "gn:country_code":"CN",
    "gn:dem":1340,
    "gn:feature_class":"P",
    "gn:feature_code":"PPL",
    "gn:name":"Longxi",
    "gn:population":0,
    "gn:timezone":"Asia/Shanghai",
    "iso:country":"CN",
    "name:zho_x_preferred":[
        "\u9647\u897f"
    ],
    "wof:name":"Longxi",
    "wof:placetype":"locality"
},
  "geometry": {"coordinates":[104.581,24.3621],"type":"Point"}
}