{
  "type": "Feature",
  "properties": {
    "gn:admin1_code":"25",
    "gn:asciiname":"Lanwo",
    "gn:country_code":"CN",
    "gn:dem":359,
    "gn:feature_class":"P",
    "gn:feature_code":"PPL",
    "gn:name":"Lanwo",
    "gn:population":0,
    "gn:timezone":"Asia/Shanghai",
    "iso:country":"CN",
    "name:zho_x_preferred":[
        "\u5754\u7a9d"
    ],
    "wof:name":"Lanwo",
    "wof:placetype":"locality"
},
  "geometry": {"coordinates":[117.267,36.5128],"type":"Point"}
}