{
  "type": "Feature",
  "properties": {
    "gn:admin1_code":"08",
    "gn:asciiname":"Qianshao",
    "gn:country_code":"CN",
    "gn:dem":259,
    "gn:feature_class":"P",
    "gn:feature_code":"PPL",
    "gn:name":"Qianshao",
    "gn:population":0,
    "gn:timezone":"Asia/Shanghai",
    "iso:country":"CN",
    "wof:name":"Qianshao",
    "wof:placetype":"locality"
},
  "geometry": {"coordinates":[126.46666999999999,51.81667],"type":"Point"}
}