{
  "type": "Feature",
  "properties": {
    "gn:admin1_code":"10.0",
    "gn:asciiname":"Baitu'an",
    "gn:country_code":"CN",
    "gn:dem":272,
    "gn:feature_class":"P",
    "gn:feature_code":"PPL",
    "gn:name":"Baitu\u2019an",
    "gn:population":0,
    "gn:timezone":"Asia/Shanghai",
    "iso:country":"CN",
    "name:und_x_variant":[
        "Baitu\u2019an"
    ],
    "name:zho_x_preferred":[
        "\u767d\u571f\u5b89"
    ],
    "wof:name":"Baitu'an",
    "wof:placetype":"locality"
},
  "geometry": {"coordinates":[115.16321000000001,39.33823],"type":"Point"}
}