{
  "type": "Feature",
  "properties": {
    "gn:admin1_code":"24.0",
    "gn:asciiname":"Gemaling",
    "gn:country_code":"CN",
    "gn:dem":1038,
    "gn:feature_class":"P",
    "gn:feature_code":"PPL",
    "gn:name":"Gemaling",
    "gn:population":0,
    "gn:timezone":"Asia/Shanghai",
    "iso:country":"CN",
    "name:zho_x_preferred":[
        "\u572a\u9ebb\u5cad"
    ],
    "wof:name":"Gemaling",
    "wof:placetype":"locality"
},
  "geometry": {"coordinates":[111.04474999999999,37.89364000000001],"type":"Point"}
}