{
  "type": "Feature",
  "properties": {
    "gn:admin1_code":"4.0",
    "gn:asciiname":"Linshang",
    "gn:country_code":"CN",
    "gn:dem":4,
    "gn:feature_class":"P",
    "gn:feature_code":"PPL",
    "gn:name":"Linshang",
    "gn:population":0,
    "gn:timezone":"Asia/Shanghai",
    "iso:country":"CN",
    "name:zho_x_preferred":[
        "Linshang"
    ],
    "name:zho_x_variant":[
        "\u6797\u4e0a"
    ],
    "wof:name":"Linshang",
    "wof:placetype":"locality"
},
  "geometry": {"coordinates":[119.58458,33.35848],"type":"Point"}
}