{
  "type": "Feature",
  "properties": {
    "gn:admin1_code":"12.0",
    "gn:asciiname":"Miao'ergang",
    "gn:country_code":"CN",
    "gn:dem":191,
    "gn:feature_class":"P",
    "gn:feature_code":"PPL",
    "gn:name":"Miao\u2019ergang",
    "gn:population":0,
    "gn:timezone":"Asia/Shanghai",
    "iso:country":"CN",
    "name:und_x_variant":[
        "Miao\u2019ergang"
    ],
    "name:zho_x_preferred":[
        "\u5e99\u513f\u5c97"
    ],
    "wof:name":"Miao'ergang",
    "wof:placetype":"locality"
},
  "geometry": {"coordinates":[111.80603000000001,31.81216],"type":"Point"}
}