{
  "type": "Feature",
  "properties": {
    "gn:admin1_code":"3",
    "gn:asciiname":"Sanshan",
    "gn:country_code":"CN",
    "gn:dem":83,
    "gn:feature_class":"P",
    "gn:feature_code":"PPLA4",
    "gn:name":"Sanshan",
    "gn:population":0,
    "gn:timezone":"Asia/Shanghai",
    "iso:country":"CN",
    "name:und_x_variant":[
        "\u4e09\u5c71",
        "Sanshanmiao",
        "Sanshan Xiang",
        "\u4e09\u5c71\u4e61"
    ],
    "wof:name":"Sanshan",
    "wof:placetype":"locality"
},
  "geometry": {"coordinates":[115.98771000000001,27.84198],"type":"Point"}
}