{
  "type": "Feature",
  "properties": {
    "gn:admin1_code":"4.0",
    "gn:asciiname":"Houjiao",
    "gn:country_code":"CN",
    "gn:dem":28,
    "gn:feature_class":"P",
    "gn:feature_code":"PPL",
    "gn:name":"Houjiao",
    "gn:population":0,
    "gn:timezone":"Asia/Shanghai",
    "iso:country":"CN",
    "name:zho_x_preferred":[
        "\u539a\u89d2"
    ],
    "wof:name":"Houjiao",
    "wof:placetype":"locality"
},
  "geometry": {"coordinates":[119.71021,32.15619],"type":"Point"}
}