{
  "type": "Feature",
  "properties": {
    "gn:admin1_code":"29.0",
    "gn:asciiname":"Maiziba",
    "gn:country_code":"CN",
    "gn:dem":1399,
    "gn:feature_class":"P",
    "gn:feature_code":"PPL",
    "gn:name":"Maiziba",
    "gn:population":0,
    "gn:timezone":"Asia/Shanghai",
    "iso:country":"CN",
    "name:zho_x_preferred":[
        "\u9ea6\u5b50\u575d"
    ],
    "wof:name":"Maiziba",
    "wof:placetype":"locality"
},
  "geometry": {"coordinates":[104.15300000000001,27.8283],"type":"Point"}
}