{
  "type": "Feature",
  "properties": {
    "gn:admin1_code":"19.0",
    "gn:asciiname":"Dongtazishan",
    "gn:country_code":"CN",
    "gn:dem":232,
    "gn:feature_class":"P",
    "gn:feature_code":"PPL",
    "gn:name":"Dongtazishan",
    "gn:population":0,
    "gn:timezone":"Asia/Shanghai",
    "iso:country":"CN",
    "name:und_x_variant":[
        "\u4e1c\u5854\u5b50\u5c71"
    ],
    "name:zho_x_preferred":[
        "\u4e1c\u5854\u5b50\u5c71"
    ],
    "wof:name":"Dongtazishan",
    "wof:placetype":"locality"
},
  "geometry": {"coordinates":[121.45050000000001,42.14971],"type":"Point"}
}