{
  "type": "Feature",
  "properties": {
    "gn:admin1_code":"26.0",
    "gn:asciiname":"Dayu Linchang",
    "gn:country_code":"CN",
    "gn:dem":922,
    "gn:feature_class":"P",
    "gn:feature_code":"PPLF",
    "gn:name":"Dayu Linchang",
    "gn:population":0,
    "gn:timezone":"Asia/Shanghai",
    "iso:country":"CN",
    "name:und_x_variant":[
        "\u5927\u5cea\u6797\u573a"
    ],
    "wof:name":"Dayu Linchang",
    "wof:placetype":"locality"
},
  "geometry": {"coordinates":[109.09945999999999,34.01539],"type":"Point"}
}