{
  "type": "Feature",
  "properties": {
    "gn:admin1_code":"15.0",
    "gn:asciiname":"Dujiayuan",
    "gn:country_code":"CN",
    "gn:dem":1232,
    "gn:feature_class":"P",
    "gn:feature_code":"PPL",
    "gn:name":"Dujiayuan",
    "gn:population":0,
    "gn:timezone":"Asia/Shanghai",
    "iso:country":"CN",
    "name:zho_x_preferred":[
        "\u675c\u5bb6\u586c"
    ],
    "wof:name":"Dujiayuan",
    "wof:placetype":"locality"
},
  "geometry": {"coordinates":[106.896,35.2895],"type":"Point"}
}