{
  "type": "Feature",
  "properties": {
    "gn:admin1_code":"4.0",
    "gn:asciiname":"Baozhuangcun",
    "gn:country_code":"CN",
    "gn:dem":6,
    "gn:feature_class":"P",
    "gn:feature_code":"PPL",
    "gn:name":"Baozhuangcun",
    "gn:population":0,
    "gn:timezone":"Asia/Shanghai",
    "iso:country":"CN",
    "name:und_x_variant":[
        "Baozhuang",
        "Baoxu",
        "Baozhuangcun"
    ],
    "name:zho_x_preferred":[
        "\u9c8d\u5e84"
    ],
    "name:zho_x_variant":[
        "\u9c8d\u5f90",
        "\u9c8d\u5e84\u6751"
    ],
    "wof:name":"Baozhuangcun",
    "wof:placetype":"locality"
},
  "geometry": {"coordinates":[119.88312000000001,32.45209000000001],"type":"Point"}
}