{
  "type": "Feature",
  "properties": {
    "gn:admin1_code":"15.0",
    "gn:asciiname":"Songshanshui",
    "gn:country_code":"CN",
    "gn:dem":2023,
    "gn:feature_class":"P",
    "gn:feature_code":"PPL",
    "gn:name":"Songshanshui",
    "gn:population":0,
    "gn:timezone":"Asia/Shanghai",
    "iso:country":"CN",
    "name:zho_x_preferred":[
        "\u677e\u5c71\u6c34"
    ],
    "wof:name":"Songshanshui",
    "wof:placetype":"locality"
},
  "geometry": {"coordinates":[103.934,37.0522],"type":"Point"}
}