{
  "type": "Feature",
  "properties": {
    "gn:admin1_code":"3.0",
    "gn:asciiname":"Datangkeng",
    "gn:country_code":"CN",
    "gn:dem":230,
    "gn:feature_class":"P",
    "gn:feature_code":"PPL",
    "gn:name":"Datangkeng",
    "gn:population":0,
    "gn:timezone":"Asia/Shanghai",
    "iso:country":"CN",
    "name:und_x_variant":[
        "\u5927\u5858\u5751"
    ],
    "wof:name":"Datangkeng",
    "wof:placetype":"locality"
},
  "geometry": {"coordinates":[115.18725000000001,25.32877],"type":"Point"}
}