{
  "type": "Feature",
  "properties": {
    "gn:admin1_code":"29.0",
    "gn:asciiname":"Dabaqing",
    "gn:country_code":"CN",
    "gn:dem":1598,
    "gn:feature_class":"P",
    "gn:feature_code":"PPL",
    "gn:name":"Dabaqing",
    "gn:population":0,
    "gn:timezone":"Asia/Shanghai",
    "iso:country":"CN",
    "name:zho_x_preferred":[
        "\u5927\u575d\u7b90"
    ],
    "wof:name":"Dabaqing",
    "wof:placetype":"locality"
},
  "geometry": {"coordinates":[102.01600000000001,25.0102],"type":"Point"}
}