{
  "type": "Feature",
  "properties": {
    "gn:admin1_code":"14",
    "gn:asciiname":"Qaloin",
    "gn:country_code":"CN",
    "gn:dem":3454,
    "gn:feature_class":"P",
    "gn:feature_code":"PPL",
    "gn:name":"Qaloin",
    "gn:population":0,
    "gn:timezone":"Asia/Urumqi",
    "iso:country":"CN",
    "name:bod_x_preferred":[
        "\u0f56\u0fb1\u0f0b\u0f62\u0fb3\u0f7c\u0f53"
    ],
    "wof:name":"Qaloin",
    "wof:placetype":"locality"
},
  "geometry": {"coordinates":[92.68581,28.29478],"type":"Point"}
}