{
  "type": "Feature",
  "properties": {
    "gn:admin1_code":"4.0",
    "gn:asciiname":"Huzaoyuan",
    "gn:country_code":"CN",
    "gn:dem":25,
    "gn:feature_class":"P",
    "gn:feature_code":"PPL",
    "gn:name":"Huzaoyuan",
    "gn:population":0,
    "gn:timezone":"Asia/Shanghai",
    "iso:country":"CN",
    "name:zho_x_preferred":[
        "\u80e1\u67a3\u56ed"
    ],
    "wof:name":"Huzaoyuan",
    "wof:placetype":"locality"
},
  "geometry": {"coordinates":[118.569,33.1545],"type":"Point"}
}