{
  "type": "Feature",
  "properties": {
    "gn:admin1_code":"29",
    "gn:asciiname":"Shangmaidi",
    "gn:country_code":"CN",
    "gn:dem":2117,
    "gn:feature_class":"P",
    "gn:feature_code":"PPL",
    "gn:name":"Shangmaidi",
    "gn:population":0,
    "gn:timezone":"Asia/Shanghai",
    "iso:country":"CN",
    "name:zho_x_preferred":[
        "\u4e0a\u9ea6\u5730"
    ],
    "wof:name":"Shangmaidi",
    "wof:placetype":"locality"
},
  "geometry": {"coordinates":[102.86199999999999,24.1143],"type":"Point"}
}