{
  "type": "Feature",
  "properties": {
    "gn:admin1_code":"04",
    "gn:asciiname":"Jianghua",
    "gn:country_code":"CN",
    "gn:dem":5,
    "gn:feature_class":"P",
    "gn:feature_code":"PPLA4",
    "gn:name":"Jianghua",
    "gn:population":0,
    "gn:timezone":"Asia/Shanghai",
    "iso:country":"CN",
    "name:und_x_variant":[
        "Chiang-hua-ch\u2019iao",
        "Jianghuaqiao",
        "Jianghua",
        "\u848b\u534e",
        "Jianghua Zhen",
        "\u848b\u534e\u9547"
    ],
    "wof:name":"Jianghua",
    "wof:placetype":"locality"
},
  "geometry": {"coordinates":[120.00895,32.07341],"type":"Point"}
}