{
  "type": "Feature",
  "properties": {
    "gn:admin1_code":"18",
    "gn:asciiname":"Daihua",
    "gn:cc2":"CN",
    "gn:country_code":"CN",
    "gn:dem":1058,
    "gn:feature_class":"P",
    "gn:feature_code":"PPL",
    "gn:name":"Daihua",
    "gn:population":0,
    "gn:timezone":"Asia/Shanghai",
    "iso:country":"CN",
    "name:und_x_variant":[
        "Tai-hua",
        "Daihua"
    ],
    "wof:name":"Daihua",
    "wof:placetype":"locality"
},
  "geometry": {"coordinates":[106.36667,25.73333],"type":"Point"}
}