{
  "type": "Feature",
  "properties": {
    "gn:admin1_code":"19.0",
    "gn:asciiname":"Dongwengcheng",
    "gn:country_code":"CN",
    "gn:dem":96,
    "gn:feature_class":"P",
    "gn:feature_code":"PPL",
    "gn:name":"Dongwengcheng",
    "gn:population":0,
    "gn:timezone":"Asia/Shanghai",
    "iso:country":"CN",
    "name:zho_x_preferred":[
        "\u4e1c\u7fc1\u57ce"
    ],
    "wof:name":"Dongwengcheng",
    "wof:placetype":"locality"
},
  "geometry": {"coordinates":[122.16386,39.68431],"type":"Point"}
}