{
  "type": "Feature",
  "properties": {
    "gn:admin1_code":"4.0",
    "gn:asciiname":"Huangxu",
    "gn:country_code":"CN",
    "gn:dem":6,
    "gn:feature_class":"P",
    "gn:feature_code":"PPL",
    "gn:name":"Huangxu",
    "gn:population":0,
    "gn:timezone":"Asia/Shanghai",
    "iso:country":"CN",
    "name:und_x_variant":[
        "\u9ec4\u5729"
    ],
    "wof:name":"Huangxu",
    "wof:placetype":"locality"
},
  "geometry": {"coordinates":[119.17167999999999,34.29989],"type":"Point"}
}