{
  "type": "Feature",
  "properties": {
    "gn:admin1_code":"4.0",
    "gn:asciiname":"Daohuai",
    "gn:country_code":"CN",
    "gn:dem":18,
    "gn:feature_class":"P",
    "gn:feature_code":"PPL",
    "gn:name":"Daohuai",
    "gn:population":0,
    "gn:timezone":"Asia/Shanghai",
    "iso:country":"CN",
    "name:zho_x_preferred":[
        "\u5bfc\u6dee"
    ],
    "wof:name":"Daohuai",
    "wof:placetype":"locality"
},
  "geometry": {"coordinates":[118.444,33.8163],"type":"Point"}
}