{
  "type": "Feature",
  "properties": {
    "gn:admin1_code":"09",
    "gn:asciiname":"Chuwang",
    "gn:cc2":"CN",
    "gn:country_code":"CN",
    "gn:dem":55,
    "gn:feature_class":"P",
    "gn:feature_code":"PPL",
    "gn:name":"Chuwang",
    "gn:population":0,
    "gn:timezone":"Asia/Shanghai",
    "iso:country":"CN",
    "name:und_x_variant":[
        "Ch\u2019u-wang-chen",
        "Chuwang"
    ],
    "wof:name":"Chuwang",
    "wof:placetype":"locality"
},
  "geometry": {"coordinates":[114.85778000000001,36.06972],"type":"Point"}
}