{
  "type": "Feature",
  "properties": {
    "gn:admin1_code":"9.0",
    "gn:asciiname":"Houjie",
    "gn:country_code":"CN",
    "gn:dem":76,
    "gn:feature_class":"P",
    "gn:feature_code":"PPL",
    "gn:name":"Houjie",
    "gn:population":0,
    "gn:timezone":"Asia/Shanghai",
    "iso:country":"CN",
    "name:fas_x_preferred":[
        "\u0647\u0648\u062c\u06cc"
    ],
    "name:swe_x_preferred":[
        "Houjie"
    ],
    "name:zho_x_preferred":[
        "\u540e\u8857"
    ],
    "name:zho_x_variant":[
        "\u539a\u8857\u9547"
    ],
    "wof:name":"Houjie",
    "wof:placetype":"locality"
},
  "geometry": {"coordinates":[113.86296000000002,34.08761],"type":"Point"}
}