{
  "type": "Feature",
  "properties": {
    "gn:admin1_code":"26.0",
    "gn:asciiname":"Xieyangcun",
    "gn:country_code":"CN",
    "gn:dem":466,
    "gn:feature_class":"P",
    "gn:feature_code":"PPL",
    "gn:name":"Xieyangcun",
    "gn:population":0,
    "gn:timezone":"Asia/Shanghai",
    "iso:country":"CN",
    "name:zho_x_preferred":[
        "\u659c\u6768\u6751"
    ],
    "wof:name":"Xieyangcun",
    "wof:placetype":"locality"
},
  "geometry": {"coordinates":[109.29704,34.41298],"type":"Point"}
}