{
  "type": "Feature",
  "properties": {
    "gn:admin1_code":"14.0",
    "gn:asciiname":"Daxiang",
    "gn:country_code":"CN",
    "gn:dem":3871,
    "gn:feature_class":"P",
    "gn:feature_code":"PPL",
    "gn:name":"Daxiang",
    "gn:population":0,
    "gn:timezone":"Asia/Urumqi",
    "iso:country":"CN",
    "name:zho_x_preferred":[
        "\u6253\u9999"
    ],
    "wof:name":"Daxiang",
    "wof:placetype":"locality"
},
  "geometry": {"coordinates":[94.0067,30.20815],"type":"Point"}
}