{
  "type": "Feature",
  "properties": {
    "gn:admin1_code":"11",
    "gn:asciiname":"Zhengguyuan",
    "gn:country_code":"CN",
    "gn:dem":235,
    "gn:feature_class":"P",
    "gn:feature_code":"PPL",
    "gn:name":"Zhengguyuan",
    "gn:population":0,
    "gn:timezone":"Asia/Shanghai",
    "iso:country":"CN",
    "name:und_x_variant":[
        "\u90d1\u53e4\u5143",
        "Zhengguyuan"
    ],
    "wof:name":"Zhengguyuan",
    "wof:placetype":"locality"
},
  "geometry": {"coordinates":[112.00943999999998,25.77444],"type":"Point"}
}