{
  "type": "Feature",
  "properties": {
    "gn:admin1_code":"3",
    "gn:asciiname":"Liuli",
    "gn:country_code":"CN",
    "gn:dem":68,
    "gn:feature_class":"P",
    "gn:feature_code":"PPL",
    "gn:name":"Liuli",
    "gn:population":0,
    "gn:timezone":"Asia/Shanghai",
    "iso:country":"CN",
    "name:und_x_variant":[
        "\u7409\u7483",
        "Liulixiang",
        "\u7409\u7483\u4e61"
    ],
    "wof:name":"Liuli",
    "wof:placetype":"locality"
},
  "geometry": {"coordinates":[116.5868,27.99555],"type":"Point"}
}