{
  "type": "Feature",
  "properties": {
    "gn:admin1_code":"25.0",
    "gn:asciiname":"Hujiayacun",
    "gn:country_code":"CN",
    "gn:dem":78,
    "gn:feature_class":"P",
    "gn:feature_code":"PPL",
    "gn:name":"Hujiayacun",
    "gn:population":0,
    "gn:timezone":"Asia/Shanghai",
    "iso:country":"CN",
    "name:zho_x_preferred":[
        "\u62a4\u9a7e\u5d16\u6751"
    ],
    "wof:name":"Hujiayacun",
    "wof:placetype":"locality"
},
  "geometry": {"coordinates":[120.90731,36.91756],"type":"Point"}
}