{
  "type": "Feature",
  "properties": {
    "gn:admin1_code":"12.0",
    "gn:asciiname":"Liujiagang",
    "gn:country_code":"CN",
    "gn:dem":82,
    "gn:feature_class":"P",
    "gn:feature_code":"PPL",
    "gn:name":"Liujiagang",
    "gn:population":0,
    "gn:timezone":"Asia/Shanghai",
    "iso:country":"CN",
    "name:zho_x_preferred":[
        "Liujiagang"
    ],
    "name:zho_x_variant":[
        "\u5218\u5bb6\u5c97"
    ],
    "wof:name":"Liujiagang",
    "wof:placetype":"locality"
},
  "geometry": {"coordinates":[111.84716,30.90053],"type":"Point"}
}