{
  "type": "Feature",
  "properties": {
    "gn:admin1_code":"19.0",
    "gn:asciiname":"Dadaogou",
    "gn:country_code":"CN",
    "gn:dem":194,
    "gn:feature_class":"P",
    "gn:feature_code":"PPL",
    "gn:name":"Dadaogou",
    "gn:population":0,
    "gn:timezone":"Asia/Shanghai",
    "iso:country":"CN",
    "name:und_x_variant":[
        "\u5927\u9053\u6c9f"
    ],
    "wof:name":"Dadaogou",
    "wof:placetype":"locality"
},
  "geometry": {"coordinates":[123.60048999999999,40.57528],"type":"Point"}
}