{
  "type": "Feature",
  "properties": {
    "gn:admin1_code":"16.0",
    "gn:asciiname":"Xinshechong",
    "gn:country_code":"CN",
    "gn:dem":103,
    "gn:feature_class":"P",
    "gn:feature_code":"PPL",
    "gn:name":"Xinshechong",
    "gn:population":0,
    "gn:timezone":"Asia/Shanghai",
    "iso:country":"CN",
    "name:zho_x_preferred":[
        "\u65b0\u793e\u51b2"
    ],
    "wof:name":"Xinshechong",
    "wof:placetype":"locality"
},
  "geometry": {"coordinates":[109.227,24.4659],"type":"Point"}
}