{
  "type": "Feature",
  "properties": {
    "gn:admin1_code":"11.0",
    "gn:asciiname":"Jiuhuoping",
    "gn:country_code":"CN",
    "gn:dem":555,
    "gn:feature_class":"P",
    "gn:feature_code":"PPL",
    "gn:name":"Jiuhuoping",
    "gn:population":0,
    "gn:timezone":"Asia/Shanghai",
    "iso:country":"CN",
    "name:zho_x_preferred":[
        "\u4e5d\u4f19\u576a"
    ],
    "wof:name":"Jiuhuoping",
    "wof:placetype":"locality"
},
  "geometry": {"coordinates":[110.92433,29.71934000000001],"type":"Point"}
}