{
  "type": "Feature",
  "properties": {
    "gn:admin1_code":"18",
    "gn:asciiname":"Laoyayan",
    "gn:country_code":"CN",
    "gn:dem":919,
    "gn:feature_class":"P",
    "gn:feature_code":"PPL",
    "gn:name":"Laoyayan",
    "gn:population":0,
    "gn:timezone":"Asia/Shanghai",
    "iso:country":"CN",
    "name:zho_x_preferred":[
        "\u8001\u9e26\u5ca9"
    ],
    "wof:name":"Laoyayan",
    "wof:placetype":"locality"
},
  "geometry": {"coordinates":[108.304,27.2827],"type":"Point"}
}