{
  "type": "Feature",
  "properties": {
    "gn:admin1_code":"30.0",
    "gn:asciiname":"Niulanxu",
    "gn:country_code":"CN",
    "gn:dem":671,
    "gn:feature_class":"P",
    "gn:feature_code":"PPL",
    "gn:name":"Niulanxu",
    "gn:population":0,
    "gn:timezone":"Asia/Shanghai",
    "iso:country":"CN",
    "name:zho_x_preferred":[
        "Niulanxu"
    ],
    "name:zho_x_variant":[
        "\u725b\u680f\u5729"
    ],
    "wof:name":"Niulanxu",
    "wof:placetype":"locality"
},
  "geometry": {"coordinates":[112.19861000000002,24.86111],"type":"Point"}
}