{
  "type": "Feature",
  "properties": {
    "gn:admin1_code":"12.0",
    "gn:asciiname":"Dajianshan",
    "gn:country_code":"CN",
    "gn:dem":673,
    "gn:feature_class":"P",
    "gn:feature_code":"PPL",
    "gn:name":"Dajianshan",
    "gn:population":0,
    "gn:timezone":"Asia/Shanghai",
    "iso:country":"CN",
    "name:zho_x_preferred":[
        "\u5927\u5c16\u5c71"
    ],
    "wof:name":"Dajianshan",
    "wof:placetype":"locality"
},
  "geometry": {"coordinates":[111.35799,31.11404000000001],"type":"Point"}
}