{
  "type": "Feature",
  "properties": {
    "gn:admin1_code":"5.0",
    "gn:asciiname":"Jiameisuo",
    "gn:country_code":"CN",
    "gn:dem":394,
    "gn:feature_class":"P",
    "gn:feature_code":"PPL",
    "gn:name":"Jiameisuo",
    "gn:population":0,
    "gn:timezone":"Asia/Shanghai",
    "iso:country":"CN",
    "name:und_x_variant":[
        "Chia-mei-so"
    ],
    "wof:name":"Jiameisuo",
    "wof:placetype":"locality"
},
  "geometry": {"coordinates":[129.67362,42.44583],"type":"Point"}
}