{
  "type": "Feature",
  "properties": {
    "gn:admin1_code":"14.0",
    "gn:asciiname":"E'adong",
    "gn:country_code":"CN",
    "gn:dem":2953,
    "gn:feature_class":"P",
    "gn:feature_code":"PPL",
    "gn:name":"E\u2019adong",
    "gn:population":0,
    "gn:timezone":"Asia/Urumqi",
    "iso:country":"CN",
    "name:und_x_variant":[
        "E\u2019adong"
    ],
    "name:zho_x_preferred":[
        "\u989d\u963f\u4e1c"
    ],
    "wof:name":"E'adong",
    "wof:placetype":"locality"
},
  "geometry": {"coordinates":[94.81422000000001,29.45569],"type":"Point"}
}