{
  "type": "Feature",
  "properties": {
    "gn:admin1_code":"3",
    "gn:asciiname":"Canzhou",
    "gn:country_code":"CN",
    "gn:dem":129,
    "gn:feature_class":"P",
    "gn:feature_code":"PPL",
    "gn:name":"Canzhou",
    "gn:population":0,
    "gn:timezone":"Asia/Shanghai",
    "iso:country":"CN",
    "name:zho_x_preferred":[
        "\u8695\u6d32"
    ],
    "wof:name":"Canzhou",
    "wof:placetype":"locality"
},
  "geometry": {"coordinates":[114.48399999999999,26.3357],"type":"Point"}
}