{
  "type": "Feature",
  "properties": {
    "gn:admin1_code":"29.0",
    "gn:asciiname":"Ciliba",
    "gn:country_code":"CN",
    "gn:dem":1911,
    "gn:feature_class":"P",
    "gn:feature_code":"PPL",
    "gn:name":"Ciliba",
    "gn:population":0,
    "gn:timezone":"Asia/Shanghai",
    "iso:country":"CN",
    "name:zho_x_preferred":[
        "\u8328\u85dc\u5df4"
    ],
    "wof:name":"Ciliba",
    "wof:placetype":"locality"
},
  "geometry": {"coordinates":[103.58799999999999,27.3632],"type":"Point"}
}