{
  "type": "Feature",
  "properties": {
    "gn:admin1_code":"3.0",
    "gn:asciiname":"Meiling",
    "gn:country_code":"CN",
    "gn:dem":603,
    "gn:feature_class":"P",
    "gn:feature_code":"PPL",
    "gn:name":"Meiling",
    "gn:population":0,
    "gn:timezone":"Asia/Shanghai",
    "iso:country":"CN",
    "name:ceb_x_preferred":[
        "Meiling"
    ],
    "name:deu_x_preferred":[
        "Meiling"
    ],
    "name:jpn_x_preferred":[
        "\u30e1\u30a4\u30ea\u30f3"
    ],
    "name:swe_x_preferred":[
        "Meiling"
    ],
    "name:und_x_variant":[
        "\u6885\u5cad"
    ],
    "wof:name":"Meiling",
    "wof:placetype":"locality"
},
  "geometry": {"coordinates":[114.2959,28.43414000000001],"type":"Point"}
}