{
  "type": "Feature",
  "properties": {
    "gn:admin1_code":"1.0",
    "gn:asciiname":"Fuhu Liangzhongchang",
    "gn:country_code":"CN",
    "gn:dem":23,
    "gn:feature_class":"P",
    "gn:feature_code":"PPL",
    "gn:name":"Fuhu Liangzhongchang",
    "gn:population":0,
    "gn:timezone":"Asia/Shanghai",
    "iso:country":"CN",
    "name:zho_x_preferred":[
        "\u4ed8\u6e56\u826f\u79cd\u573a"
    ],
    "wof:name":"Fuhu Liangzhongchang",
    "wof:placetype":"locality"
},
  "geometry": {"coordinates":[117.83611999999999,33.32629],"type":"Point"}
}