{
  "type": "Feature",
  "properties": {
    "gn:admin1_code":"11.0",
    "gn:asciiname":"Tanjia Wuchang",
    "gn:country_code":"CN",
    "gn:dem":50,
    "gn:feature_class":"P",
    "gn:feature_code":"PPL",
    "gn:name":"Tanjia Wuchang",
    "gn:population":0,
    "gn:timezone":"Asia/Shanghai",
    "iso:country":"CN",
    "name:zho_x_preferred":[
        "\u8c2d\u5bb6\u5c4b\u573a"
    ],
    "wof:name":"Tanjia Wuchang",
    "wof:placetype":"locality"
},
  "geometry": {"coordinates":[112.51224000000001,28.38928],"type":"Point"}
}