{
  "type": "Feature",
  "properties": {
    "gn:admin1_code":"33.0",
    "gn:asciiname":"Wuping",
    "gn:country_code":"CN",
    "gn:dem":1159,
    "gn:feature_class":"P",
    "gn:feature_code":"PPL",
    "gn:name":"Wuping",
    "gn:population":0,
    "gn:timezone":"Asia/Shanghai",
    "iso:country":"CN",
    "name:deu_x_preferred":[
        "Wuping"
    ],
    "name:zho_x_preferred":[
        "\u4e94\u576a"
    ],
    "wof:name":"Wuping",
    "wof:placetype":"locality"
},
  "geometry": {"coordinates":[108.24352,29.9541],"type":"Point"}
}