{
  "type": "Feature",
  "properties": {
    "gn:admin1_code":"1.0",
    "gn:asciiname":"Chenzhacun",
    "gn:country_code":"CN",
    "gn:dem":7,
    "gn:feature_class":"P",
    "gn:feature_code":"PPL",
    "gn:name":"Chenzhacun",
    "gn:population":0,
    "gn:timezone":"Asia/Shanghai",
    "iso:country":"CN",
    "name:zho_x_preferred":[
        "\u9648\u95f8\u6751"
    ],
    "wof:name":"Chenzhacun",
    "wof:placetype":"locality"
},
  "geometry": {"coordinates":[117.92738,31.39661],"type":"Point"}
}