{
  "type": "Feature",
  "properties": {
    "gn:admin1_code":"7",
    "gn:asciiname":"Tangbeixie",
    "gn:country_code":"CN",
    "gn:dem":408,
    "gn:feature_class":"P",
    "gn:feature_code":"PPL",
    "gn:name":"Tangbeixie",
    "gn:population":0,
    "gn:timezone":"Asia/Shanghai",
    "iso:country":"CN",
    "name:und_x_variant":[
        "Futang",
        "Tangbeixie"
    ],
    "name:zho_x_preferred":[
        "\u5858\u80cc\u659c"
    ],
    "wof:name":"Tangbeixie",
    "wof:placetype":"locality"
},
  "geometry": {"coordinates":[116.98976999999999,24.31106],"type":"Point"}
}