{
  "type": "Feature",
  "properties": {
    "gn:admin1_code":"3.0",
    "gn:asciiname":"Shangguanlong",
    "gn:country_code":"CN",
    "gn:dem":33,
    "gn:feature_class":"P",
    "gn:feature_code":"PPL",
    "gn:name":"Shangguanlong",
    "gn:population":0,
    "gn:timezone":"Asia/Shanghai",
    "iso:country":"CN",
    "name:und_x_variant":[
        "\u4e0a\u7f50\u5784"
    ],
    "wof:name":"Shangguanlong",
    "wof:placetype":"locality"
},
  "geometry": {"coordinates":[115.83866,29.15427],"type":"Point"}
}