{
  "type": "Feature",
  "properties": {
    "gn:admin1_code":"15.0",
    "gn:asciiname":"Maidigou",
    "gn:country_code":"CN",
    "gn:dem":1605,
    "gn:feature_class":"P",
    "gn:feature_code":"PPL",
    "gn:name":"Maidigou",
    "gn:population":0,
    "gn:timezone":"Asia/Shanghai",
    "iso:country":"CN",
    "name:zho_x_preferred":[
        "\u9ea6\u5730\u6c9f"
    ],
    "wof:name":"Maidigou",
    "wof:placetype":"locality"
},
  "geometry": {"coordinates":[104.19199999999999,36.4233],"type":"Point"}
}