{
  "type": "Feature",
  "properties": {
    "gn:admin1_code":"30.0",
    "gn:asciiname":"Changlingpi",
    "gn:country_code":"CN",
    "gn:dem":37,
    "gn:feature_class":"P",
    "gn:feature_code":"PPL",
    "gn:name":"Changlingpi",
    "gn:population":0,
    "gn:timezone":"Asia/Shanghai",
    "iso:country":"CN",
    "name:zho_x_preferred":[
        "\u957f\u5cad\u76ae"
    ],
    "wof:name":"Changlingpi",
    "wof:placetype":"locality"
},
  "geometry": {"coordinates":[114.00705000000001,22.60068],"type":"Point"}
}