{
  "type": "Feature",
  "properties": {
    "gn:admin1_code":"30.0",
    "gn:asciiname":"Niupishui",
    "gn:country_code":"CN",
    "gn:dem":31,
    "gn:feature_class":"P",
    "gn:feature_code":"PPL",
    "gn:name":"Niupishui",
    "gn:population":0,
    "gn:timezone":"Asia/Shanghai",
    "iso:country":"CN",
    "name:zho_x_preferred":[
        "\u725b\u76ae\u6c34"
    ],
    "wof:name":"Niupishui",
    "wof:placetype":"locality"
},
  "geometry": {"coordinates":[114.06764,23.22664],"type":"Point"}
}