{
  "type": "Feature",
  "properties": {
    "gn:admin1_code":"33.0",
    "gn:asciiname":"Shuangxi",
    "gn:country_code":"CN",
    "gn:dem":388,
    "gn:feature_class":"P",
    "gn:feature_code":"PPL",
    "gn:name":"Shuangxi",
    "gn:population":0,
    "gn:timezone":"Asia/Shanghai",
    "iso:country":"CN",
    "name:ceb_x_preferred":[
        "Shuangxi"
    ],
    "name:deu_x_preferred":[
        "Shuangxi"
    ],
    "name:swe_x_preferred":[
        "Shuangxi"
    ],
    "name:zho_x_preferred":[
        "\u53cc\u6eaa"
    ],
    "wof:name":"Shuangxi",
    "wof:placetype":"locality"
},
  "geometry": {"coordinates":[105.62721999999999,29.77816],"type":"Point"}
}