{
  "type": "Feature",
  "properties": {
    "gn:admin1_code":"12.0",
    "gn:asciiname":"Gaoqiaohe",
    "gn:country_code":"CN",
    "gn:dem":1419,
    "gn:feature_class":"P",
    "gn:feature_code":"PPL",
    "gn:name":"Gaoqiaohe",
    "gn:population":0,
    "gn:timezone":"Asia/Shanghai",
    "iso:country":"CN",
    "name:zho_x_preferred":[
        "\u9ad8\u6865\u6cb3"
    ],
    "wof:name":"Gaoqiaohe",
    "wof:placetype":"locality"
},
  "geometry": {"coordinates":[110.07631000000001,31.49743],"type":"Point"}
}