{
  "type": "Feature",
  "properties": {
    "gn:admin1_code":"29.0",
    "gn:asciiname":"Longkan",
    "gn:country_code":"CN",
    "gn:dem":1081,
    "gn:feature_class":"P",
    "gn:feature_code":"PPL",
    "gn:name":"Longkan",
    "gn:population":0,
    "gn:timezone":"Asia/Shanghai",
    "iso:country":"CN",
    "name:zho_x_preferred":[
        "\u9f99\u574e"
    ],
    "wof:name":"Longkan",
    "wof:placetype":"locality"
},
  "geometry": {"coordinates":[99.3359,22.3789],"type":"Point"}
}