{
  "type": "Feature",
  "properties": {
    "gn:admin1_code":"18",
    "gn:asciiname":"Huangzhongyan",
    "gn:country_code":"CN",
    "gn:dem":1348,
    "gn:feature_class":"P",
    "gn:feature_code":"PPL",
    "gn:name":"Huangzhongyan",
    "gn:population":0,
    "gn:timezone":"Asia/Shanghai",
    "iso:country":"CN",
    "name:zho_x_preferred":[
        "\u9ec4\u91cd\u5ca9"
    ],
    "wof:name":"Huangzhongyan",
    "wof:placetype":"locality"
},
  "geometry": {"coordinates":[107.02500000000001,28.0471],"type":"Point"}
}