{
  "type": "Feature",
  "properties": {
    "gn:admin1_code":"25.0",
    "gn:asciiname":"Qiaonantoucun",
    "gn:country_code":"CN",
    "gn:dem":93,
    "gn:feature_class":"P",
    "gn:feature_code":"PPL",
    "gn:name":"Qiaonantoucun",
    "gn:population":0,
    "gn:timezone":"Asia/Shanghai",
    "iso:country":"CN",
    "name:zho_x_preferred":[
        "\u6865\u5357\u5934\u6751"
    ],
    "wof:name":"Qiaonantoucun",
    "wof:placetype":"locality"
},
  "geometry": {"coordinates":[122.33072,37.23072],"type":"Point"}
}