{
  "type": "Feature",
  "properties": {
    "gn:admin1_code":"24",
    "gn:asciiname":"Buziyu",
    "gn:cc2":"CN",
    "gn:country_code":"CN",
    "gn:dem":803,
    "gn:feature_class":"P",
    "gn:feature_code":"PPL",
    "gn:name":"Buziyu",
    "gn:population":0,
    "gn:timezone":"Asia/Shanghai",
    "iso:country":"CN",
    "name:und_x_variant":[
        "Pao-tzu-y\u00fc",
        "Buziyu"
    ],
    "wof:name":"Buziyu",
    "wof:placetype":"locality"
},
  "geometry": {"coordinates":[110.73333,37.75],"type":"Point"}
}