{
  "type": "Feature",
  "properties": {
    "gn:admin1_code":"9.0",
    "gn:asciiname":"Wulidian",
    "gn:cc2":"CN",
    "gn:country_code":"CN",
    "gn:dem":61,
    "gn:feature_class":"P",
    "gn:feature_code":"PPL",
    "gn:name":"Wulidian",
    "gn:population":0,
    "gn:timezone":"Asia/Shanghai",
    "iso:country":"CN",
    "name:und_x_variant":[
        "Wu-li-tien",
        "Wulidian"
    ],
    "wof:name":"Wulidian",
    "wof:placetype":"locality"
},
  "geometry": {"coordinates":[114.28722,32.13194],"type":"Point"}
}