{
  "type": "Feature",
  "properties": {
    "gn:admin1_code":"25",
    "gn:asciiname":"Matoucun",
    "gn:country_code":"CN",
    "gn:dem":0,
    "gn:feature_class":"P",
    "gn:feature_code":"PPL",
    "gn:name":"Matoucun",
    "gn:population":0,
    "gn:timezone":"Asia/Shanghai",
    "iso:country":"CN",
    "name:und_x_variant":[
        "Matou",
        "Matoucun"
    ],
    "name:zho_x_preferred":[
        "\u7801\u5934"
    ],
    "name:zho_x_variant":[
        "\u7801\u5934\u6751"
    ],
    "wof:name":"Matoucun",
    "wof:placetype":"locality"
},
  "geometry": {"coordinates":[120.092,36.23594],"type":"Point"}
}