{
  "type": "Feature",
  "properties": {
    "gn:admin1_code":"19.0",
    "gn:asciiname":"Yingshugou",
    "gn:country_code":"CN",
    "gn:dem":350,
    "gn:feature_class":"P",
    "gn:feature_code":"PPL",
    "gn:name":"Yingshugou",
    "gn:population":0,
    "gn:timezone":"Asia/Shanghai",
    "iso:country":"CN",
    "name:und_x_variant":[
        "\u82f1\u6811\u6c9f"
    ],
    "wof:name":"Yingshugou",
    "wof:placetype":"locality"
},
  "geometry": {"coordinates":[124.08481,41.60726],"type":"Point"}
}