{
  "type": "Feature",
  "properties": {
    "gn:admin1_code":"29.0",
    "gn:asciiname":"Xindiji",
    "gn:country_code":"CN",
    "gn:dem":1830,
    "gn:feature_class":"P",
    "gn:feature_code":"PPL",
    "gn:name":"Xindiji",
    "gn:population":0,
    "gn:timezone":"Asia/Shanghai",
    "iso:country":"CN",
    "name:zho_x_preferred":[
        "\u65b0\u5730\u57fa"
    ],
    "wof:name":"Xindiji",
    "wof:placetype":"locality"
},
  "geometry": {"coordinates":[100.393,24.6056],"type":"Point"}
}