{
  "type": "Feature",
  "properties": {
    "gn:admin1_code":"19.0",
    "gn:asciiname":"Panjiabu",
    "gn:country_code":"CN",
    "gn:dem":273,
    "gn:feature_class":"P",
    "gn:feature_code":"PPL",
    "gn:name":"Panjiabu",
    "gn:population":0,
    "gn:timezone":"Asia/Shanghai",
    "iso:country":"CN",
    "name:und_x_variant":[
        "Panjiabaozi",
        "Panjia Buzi"
    ],
    "name:zho_x_preferred":[
        "\u6f58\u5bb6\u5821"
    ],
    "name:zho_x_variant":[
        "\u6f58\u5bb6\u5821\u5b50"
    ],
    "wof:name":"Panjiabu",
    "wof:placetype":"locality"
},
  "geometry": {"coordinates":[125.10299999999999,40.8373],"type":"Point"}
}