{
  "type": "Feature",
  "properties": {
    "gn:admin1_code":"03",
    "gn:asciiname":"Nantang",
    "gn:country_code":"CN",
    "gn:dem":135,
    "gn:feature_class":"P",
    "gn:feature_code":"PPL",
    "gn:name":"Nantang",
    "gn:population":0,
    "gn:timezone":"Asia/Shanghai",
    "iso:country":"CN",
    "name:deu_x_preferred":[
        "Nantang"
    ],
    "name:und_x_variant":[
        "Nan-t\u2019ang-hs\u00fc"
    ],
    "wof:name":"Nantang",
    "wof:placetype":"locality"
},
  "geometry": {"coordinates":[115.24918999999998,26.08579],"type":"Point"}
}