{
  "type": "Feature",
  "properties": {
    "gn:admin1_code":"32.0",
    "gn:asciiname":"Fanping",
    "gn:country_code":"CN",
    "gn:dem":1140,
    "gn:feature_class":"P",
    "gn:feature_code":"PPL",
    "gn:name":"Fanping",
    "gn:population":0,
    "gn:timezone":"Asia/Shanghai",
    "iso:country":"CN",
    "name:zho_x_preferred":[
        "\u7ffb\u576a"
    ],
    "wof:name":"Fanping",
    "wof:placetype":"locality"
},
  "geometry": {"coordinates":[105.93192000000001,28.14084],"type":"Point"}
}