{
  "type": "Feature",
  "properties": {
    "gn:admin1_code":"11.0",
    "gn:asciiname":"Chazishan",
    "gn:country_code":"CN",
    "gn:dem":118,
    "gn:feature_class":"P",
    "gn:feature_code":"PPL",
    "gn:name":"Chazishan",
    "gn:population":0,
    "gn:timezone":"Asia/Shanghai",
    "iso:country":"CN",
    "name:zho_x_preferred":[
        "\u8336\u5b50\u5c71"
    ],
    "wof:name":"Chazishan",
    "wof:placetype":"locality"
},
  "geometry": {"coordinates":[112.54115,28.13295],"type":"Point"}
}