{
  "type": "Feature",
  "properties": {
    "gn:admin1_code":"21.0",
    "gn:asciiname":"Xishawo",
    "gn:country_code":"CN",
    "gn:dem":1097,
    "gn:feature_class":"P",
    "gn:feature_code":"PPL",
    "gn:name":"Xishawo",
    "gn:population":0,
    "gn:timezone":"Asia/Shanghai",
    "iso:country":"CN",
    "name:zho_x_preferred":[
        "\u897f\u6c99\u7a9d"
    ],
    "wof:name":"Xishawo",
    "wof:placetype":"locality"
},
  "geometry": {"coordinates":[106.373,38.9355],"type":"Point"}
}