{
  "type": "Feature",
  "properties": {
    "gn:admin1_code":"12.0",
    "gn:asciiname":"Yinjiabaishu",
    "gn:country_code":"CN",
    "gn:dem":33,
    "gn:feature_class":"P",
    "gn:feature_code":"PPL",
    "gn:name":"Yinjiabaishu",
    "gn:population":0,
    "gn:timezone":"Asia/Shanghai",
    "iso:country":"CN",
    "name:zho_x_preferred":[
        "\u6bb7\u5bb6\u67cf\u6811"
    ],
    "wof:name":"Yinjiabaishu",
    "wof:placetype":"locality"
},
  "geometry": {"coordinates":[112.12927999999999,30.35268],"type":"Point"}
}