{
  "type": "Feature",
  "properties": {
    "gn:admin1_code":"30.0",
    "gn:asciiname":"Xinyangxi",
    "gn:country_code":"CN",
    "gn:dem":99,
    "gn:feature_class":"P",
    "gn:feature_code":"PPL",
    "gn:name":"Xinyangxi",
    "gn:population":0,
    "gn:timezone":"Asia/Shanghai",
    "iso:country":"CN",
    "name:zho_x_preferred":[
        "Xinyangxi"
    ],
    "name:zho_x_variant":[
        "\u65b0\u6768\u6eaa"
    ],
    "wof:name":"Xinyangxi",
    "wof:placetype":"locality"
},
  "geometry": {"coordinates":[113.38137999999999,25.01746],"type":"Point"}
}