{
  "type": "Feature",
  "properties": {
    "gn:admin1_code":"18.0",
    "gn:asciiname":"Xiaowengguang",
    "gn:country_code":"CN",
    "gn:dem":1170,
    "gn:feature_class":"P",
    "gn:feature_code":"PPL",
    "gn:name":"Xiaowengguang",
    "gn:population":0,
    "gn:timezone":"Asia/Shanghai",
    "iso:country":"CN",
    "name:zho_x_preferred":[
        "\u5c0f\u7fc1\u5149"
    ],
    "wof:name":"Xiaowengguang",
    "wof:placetype":"locality"
},
  "geometry": {"coordinates":[107.39,26.9201],"type":"Point"}
}