{
  "type": "Feature",
  "properties": {
    "gn:admin1_code":"8.0",
    "gn:asciiname":"Hongshengtun",
    "gn:country_code":"CN",
    "gn:dem":299,
    "gn:feature_class":"P",
    "gn:feature_code":"PPL",
    "gn:name":"Hongshengtun",
    "gn:population":0,
    "gn:timezone":"Asia/Shanghai",
    "iso:country":"CN",
    "name:zho_x_preferred":[
        "\u6d2a\u5347\u5c6f"
    ],
    "wof:name":"Hongshengtun",
    "wof:placetype":"locality"
},
  "geometry": {"coordinates":[127.83844999999999,45.42247],"type":"Point"}
}