{
  "type": "Feature",
  "properties": {
    "gn:admin1_code":"26.0",
    "gn:asciiname":"Shicaogou",
    "gn:country_code":"CN",
    "gn:dem":496,
    "gn:feature_class":"P",
    "gn:feature_code":"PPL",
    "gn:name":"Shicaogou",
    "gn:population":0,
    "gn:timezone":"Asia/Shanghai",
    "iso:country":"CN",
    "name:zho_x_preferred":[
        "\u77f3\u69fd\u6c9f"
    ],
    "wof:name":"Shicaogou",
    "wof:placetype":"locality"
},
  "geometry": {"coordinates":[109.81059999999999,35.15620999999999],"type":"Point"}
}