{
  "type": "Feature",
  "properties": {
    "gn:admin1_code":"8.0",
    "gn:asciiname":"Dongtaipingchuan",
    "gn:country_code":"CN",
    "gn:dem":241,
    "gn:feature_class":"P",
    "gn:feature_code":"PPL",
    "gn:name":"Dongtaipingchuan",
    "gn:population":0,
    "gn:timezone":"Asia/Shanghai",
    "iso:country":"CN",
    "name:zho_x_preferred":[
        "\u4e1c\u592a\u5e73\u5ddd"
    ],
    "wof:name":"Dongtaipingchuan",
    "wof:placetype":"locality"
},
  "geometry": {"coordinates":[123.16055,47.44549],"type":"Point"}
}