{
  "type": "Feature",
  "properties": {
    "gn:admin1_code":"11.0",
    "gn:asciiname":"Yaoli Renjia",
    "gn:country_code":"CN",
    "gn:dem":172,
    "gn:feature_class":"P",
    "gn:feature_code":"PPL",
    "gn:name":"Yaoli Renjia",
    "gn:population":0,
    "gn:timezone":"Asia/Shanghai",
    "iso:country":"CN",
    "name:zho_x_preferred":[
        "\u7a91\u91cc\u4eba\u5bb6"
    ],
    "wof:name":"Yaoli Renjia",
    "wof:placetype":"locality"
},
  "geometry": {"coordinates":[111.84544,26.91197],"type":"Point"}
}