{
  "type": "Feature",
  "properties": {
    "gn:admin1_code":"24.0",
    "gn:asciiname":"Shizhuang",
    "gn:country_code":"CN",
    "gn:dem":1022,
    "gn:feature_class":"P",
    "gn:feature_code":"PPL",
    "gn:name":"Shizhuang",
    "gn:population":0,
    "gn:timezone":"Asia/Shanghai",
    "iso:country":"CN",
    "name:und_x_variant":[
        "\u77f3\u5e84"
    ],
    "name:zho_x_preferred":[
        "\u77f3\u5e84"
    ],
    "wof:name":"Shizhuang",
    "wof:placetype":"locality"
},
  "geometry": {"coordinates":[113.04665,39.7209],"type":"Point"}
}