{
  "type": "Feature",
  "properties": {
    "gn:admin1_code":"11.0",
    "gn:asciiname":"Manjia",
    "gn:country_code":"CN",
    "gn:dem":249,
    "gn:feature_class":"P",
    "gn:feature_code":"PPL",
    "gn:name":"Manjia",
    "gn:population":0,
    "gn:timezone":"Asia/Shanghai",
    "iso:country":"CN",
    "name:zho_x_preferred":[
        "\u6ee1\u5bb6"
    ],
    "wof:name":"Manjia",
    "wof:placetype":"locality"
},
  "geometry": {"coordinates":[112.49397999999999,26.15154],"type":"Point"}
}