{
  "type": "Feature",
  "properties": {
    "gn:admin1_code":"16.0",
    "gn:asciiname":"Longjiang",
    "gn:country_code":"CN",
    "gn:dem":847,
    "gn:feature_class":"P",
    "gn:feature_code":"PPL",
    "gn:name":"Longjiang",
    "gn:population":0,
    "gn:timezone":"Asia/Shanghai",
    "iso:country":"CN",
    "name:zho_x_preferred":[
        "\u804b\u6c5f"
    ],
    "wof:name":"Longjiang",
    "wof:placetype":"locality"
},
  "geometry": {"coordinates":[107.592,25.119],"type":"Point"}
}