{
  "type": "Feature",
  "properties": {
    "gn:admin1_code":"14",
    "gn:asciiname":"Delaigang",
    "gn:country_code":"CN",
    "gn:dem":3798,
    "gn:feature_class":"P",
    "gn:feature_code":"PPL",
    "gn:name":"Delaigang",
    "gn:population":0,
    "gn:timezone":"Asia/Urumqi",
    "iso:country":"CN",
    "name:zho_x_preferred":[
        "\u5fb7\u6765\u5c97"
    ],
    "wof:name":"Delaigang",
    "wof:placetype":"locality"
},
  "geometry": {"coordinates":[89.63720000000001,29.3705],"type":"Point"}
}