{
  "type": "Feature",
  "properties": {
    "gn:admin1_code":"12.0",
    "gn:asciiname":"Bafangwan",
    "gn:country_code":"CN",
    "gn:dem":38,
    "gn:feature_class":"P",
    "gn:feature_code":"PPL",
    "gn:name":"Bafangwan",
    "gn:population":0,
    "gn:timezone":"Asia/Shanghai",
    "iso:country":"CN",
    "name:und_x_variant":[
        "\u516b\u65b9\u5846"
    ],
    "name:zho_x_preferred":[
        "Bafangwan"
    ],
    "wof:name":"Bafangwan",
    "wof:placetype":"locality"
},
  "geometry": {"coordinates":[114.14489,30.47601],"type":"Point"}
}