{
  "type": "Feature",
  "properties": {
    "gn:admin1_code":"26.0",
    "gn:asciiname":"Sangloucun",
    "gn:country_code":"CN",
    "gn:dem":458,
    "gn:feature_class":"P",
    "gn:feature_code":"PPL",
    "gn:name":"Sangloucun",
    "gn:population":0,
    "gn:timezone":"Asia/Shanghai",
    "iso:country":"CN",
    "name:und_x_variant":[
        "\u6851\u697c\u6751"
    ],
    "wof:name":"Sangloucun",
    "wof:placetype":"locality"
},
  "geometry": {"coordinates":[109.41271,34.91341],"type":"Point"}
}