{
  "type": "Feature",
  "properties": {
    "gn:admin1_code":"24.0",
    "gn:asciiname":"Dongjiazhuangcun",
    "gn:country_code":"CN",
    "gn:dem":475,
    "gn:feature_class":"P",
    "gn:feature_code":"PPL",
    "gn:name":"Dongjiazhuangcun",
    "gn:population":0,
    "gn:timezone":"Asia/Shanghai",
    "iso:country":"CN",
    "name:zho_x_preferred":[
        "\u8463\u5bb6\u5e84\u6751"
    ],
    "wof:name":"Dongjiazhuangcun",
    "wof:placetype":"locality"
},
  "geometry": {"coordinates":[110.97114999999999,35.53694],"type":"Point"}
}