{
  "type": "Feature",
  "properties": {
    "gn:admin1_code":"15.0",
    "gn:asciiname":"Dashahe",
    "gn:country_code":"CN",
    "gn:dem":1663,
    "gn:feature_class":"P",
    "gn:feature_code":"PPL",
    "gn:name":"Dashahe",
    "gn:population":0,
    "gn:timezone":"Asia/Shanghai",
    "iso:country":"CN",
    "name:zho_x_preferred":[
        "\u5927\u6c99\u6cb3"
    ],
    "wof:name":"Dashahe",
    "wof:placetype":"locality"
},
  "geometry": {"coordinates":[104.78400000000001,37.1916],"type":"Point"}
}