{
  "type": "Feature",
  "properties": {
    "gn:admin1_code":"29.0",
    "gn:asciiname":"Yangjuzhai",
    "gn:country_code":"CN",
    "gn:dem":1132,
    "gn:feature_class":"P",
    "gn:feature_code":"PPL",
    "gn:name":"Yangjuzhai",
    "gn:population":0,
    "gn:timezone":"Asia/Shanghai",
    "iso:country":"CN",
    "name:zho_x_preferred":[
        "\u6768\u5c45\u5be8"
    ],
    "wof:name":"Yangjuzhai",
    "wof:placetype":"locality"
},
  "geometry": {"coordinates":[103.637,23.0234],"type":"Point"}
}