{
  "type": "Feature",
  "properties": {
    "gn:admin1_code":"2.0",
    "gn:asciiname":"Yuzhang",
    "gn:country_code":"CN",
    "gn:dem":54,
    "gn:feature_class":"P",
    "gn:feature_code":"PPL",
    "gn:name":"Yuzhang",
    "gn:population":0,
    "gn:timezone":"Asia/Shanghai",
    "iso:country":"CN",
    "name:zho_x_preferred":[
        "\u8c6b\u6a1f"
    ],
    "wof:name":"Yuzhang",
    "wof:placetype":"locality"
},
  "geometry": {"coordinates":[120.702,28.2642],"type":"Point"}
}