{
  "type": "Feature",
  "properties": {
    "gn:admin1_code":"02",
    "gn:asciiname":"Aoxia",
    "gn:country_code":"CN",
    "gn:dem":460,
    "gn:feature_class":"P",
    "gn:feature_code":"PPL",
    "gn:name":"Aoxia",
    "gn:population":0,
    "gn:timezone":"Asia/Shanghai",
    "iso:country":"CN",
    "name:und_x_variant":[
        "Ao-hsia",
        "Aoxia"
    ],
    "name:zho_x_preferred":[
        "\u5773\u4e0b"
    ],
    "wof:name":"Aoxia",
    "wof:placetype":"locality"
},
  "geometry": {"coordinates":[120.13413,27.53115],"type":"Point"}
}