{
  "type": "Feature",
  "properties": {
    "gn:admin1_code":"11.0",
    "gn:asciiname":"Zhengjia Yuanzi",
    "gn:country_code":"CN",
    "gn:dem":260,
    "gn:feature_class":"P",
    "gn:feature_code":"PPL",
    "gn:name":"Zhengjia Yuanzi",
    "gn:population":0,
    "gn:timezone":"Asia/Shanghai",
    "iso:country":"CN",
    "name:zho_x_preferred":[
        "\u90d1\u5bb6\u9662\u5b50"
    ],
    "wof:name":"Zhengjia Yuanzi",
    "wof:placetype":"locality"
},
  "geometry": {"coordinates":[109.70462999999999,27.41972],"type":"Point"}
}