{
  "type": "Feature",
  "properties": {
    "gn:admin1_code":"11.0",
    "gn:asciiname":"Qixingzhuang",
    "gn:country_code":"CN",
    "gn:dem":73,
    "gn:feature_class":"P",
    "gn:feature_code":"PPL",
    "gn:name":"Qixingzhuang",
    "gn:population":0,
    "gn:timezone":"Asia/Shanghai",
    "iso:country":"CN",
    "name:zho_x_preferred":[
        "\u4e03\u661f\u5e84"
    ],
    "wof:name":"Qixingzhuang",
    "wof:placetype":"locality"
},
  "geometry": {"coordinates":[112.40304,28.16982],"type":"Point"}
}