{
  "type": "Feature",
  "properties": {
    "gn:admin1_code":"11.0",
    "gn:asciiname":"Zengjiatai",
    "gn:country_code":"CN",
    "gn:dem":36,
    "gn:feature_class":"P",
    "gn:feature_code":"PPL",
    "gn:name":"Zengjiatai",
    "gn:population":0,
    "gn:timezone":"Asia/Shanghai",
    "iso:country":"CN",
    "name:zho_x_preferred":[
        "Zengjiatai"
    ],
    "name:zho_x_variant":[
        "\u66fe\u5bb6\u53f0"
    ],
    "wof:name":"Zengjiatai",
    "wof:placetype":"locality"
},
  "geometry": {"coordinates":[111.93843,29.61659],"type":"Point"}
}