{
  "type": "Feature",
  "properties": {
    "gn:admin1_code":"32.0",
    "gn:asciiname":"Semu",
    "gn:country_code":"CN",
    "gn:dem":3123,
    "gn:feature_class":"P",
    "gn:feature_code":"PPL",
    "gn:name":"Semu",
    "gn:population":0,
    "gn:timezone":"Asia/Shanghai",
    "iso:country":"CN",
    "name:zho_x_preferred":[
        "\u8272\u6728"
    ],
    "wof:name":"Semu",
    "wof:placetype":"locality"
},
  "geometry": {"coordinates":[102.41200000000001,30.962],"type":"Point"}
}