{
  "type": "Feature",
  "properties": {
    "gn:admin1_code":"29.0",
    "gn:asciiname":"Dawotang",
    "gn:country_code":"CN",
    "gn:dem":2065,
    "gn:feature_class":"P",
    "gn:feature_code":"PPL",
    "gn:name":"Dawotang",
    "gn:population":0,
    "gn:timezone":"Asia/Shanghai",
    "iso:country":"CN",
    "name:zho_x_preferred":[
        "\u5927\u7a9d\u5858"
    ],
    "wof:name":"Dawotang",
    "wof:placetype":"locality"
},
  "geometry": {"coordinates":[102.194,25.6718],"type":"Point"}
}