{
  "type": "Feature",
  "properties": {
    "gn:admin1_code":"19.0",
    "gn:asciiname":"Kantan Nongchang",
    "gn:country_code":"CN",
    "gn:dem":3,
    "gn:feature_class":"P",
    "gn:feature_code":"PPLF",
    "gn:name":"Kantan Nongchang",
    "gn:population":0,
    "gn:timezone":"Asia/Shanghai",
    "iso:country":"CN",
    "name:und_x_variant":[
        "\u52d8\u63a2\u519c\u573a"
    ],
    "name:zho_x_preferred":[
        "\u52d8\u63a2\u519c\u573a"
    ],
    "wof:name":"Kantan Nongchang",
    "wof:placetype":"locality"
},
  "geometry": {"coordinates":[121.85937,41.17384000000001],"type":"Point"}
}