{
  "type": "Feature",
  "properties": {
    "gn:admin1_code":"11.0",
    "gn:asciiname":"Yanggongqiao",
    "gn:country_code":"CN",
    "gn:dem":266,
    "gn:feature_class":"P",
    "gn:feature_code":"PPL",
    "gn:name":"Yanggongqiao",
    "gn:population":0,
    "gn:timezone":"Asia/Shanghai",
    "iso:country":"CN",
    "name:zho_x_preferred":[
        "\u6768\u516c\u6865"
    ],
    "wof:name":"Yanggongqiao",
    "wof:placetype":"locality"
},
  "geometry": {"coordinates":[109.82903,29.00479],"type":"Point"}
}