{
  "type": "Feature",
  "properties": {
    "gn:admin1_code":"11",
    "gn:asciiname":"Songshanwan",
    "gn:country_code":"CN",
    "gn:dem":132,
    "gn:feature_class":"P",
    "gn:feature_code":"PPL",
    "gn:name":"Songshanwan",
    "gn:population":0,
    "gn:timezone":"Asia/Shanghai",
    "iso:country":"CN",
    "name:zho_x_preferred":[
        "\u677e\u5c71\u6e7e"
    ],
    "wof:name":"Songshanwan",
    "wof:placetype":"locality"
},
  "geometry": {"coordinates":[111.79528000000001,26.76171],"type":"Point"}
}