{
  "type": "Feature",
  "properties": {
    "gn:admin1_code":"15.0",
    "gn:asciiname":"Xiaheqing",
    "gn:country_code":"CN",
    "gn:dem":1453,
    "gn:feature_class":"P",
    "gn:feature_code":"PPLA4",
    "gn:name":"Xiaheqing",
    "gn:population":0,
    "gn:timezone":"Asia/Shanghai",
    "iso:country":"CN",
    "name:und_x_variant":[
        "Xiaheqing Xiang"
    ],
    "name:zho_x_preferred":[
        "\u4e0b\u6cb3\u6e05"
    ],
    "name:zho_x_variant":[
        "\u4e0b\u6cb3\u6e05\u4e61"
    ],
    "wof:name":"Xiaheqing",
    "wof:placetype":"locality"
},
  "geometry": {"coordinates":[98.96666999999999,39.56667],"type":"Point"}
}