{
  "type": "Feature",
  "properties": {
    "gn:admin1_code":"6.0",
    "gn:asciiname":"Gaqian",
    "gn:country_code":"CN",
    "gn:dem":3409,
    "gn:feature_class":"P",
    "gn:feature_code":"PPL",
    "gn:name":"Gaqian",
    "gn:population":0,
    "gn:timezone":"Asia/Shanghai",
    "iso:country":"CN",
    "name:zho_x_preferred":[
        "\u5c15\u6b20"
    ],
    "wof:name":"Gaqian",
    "wof:placetype":"locality"
},
  "geometry": {"coordinates":[101.97960999999999,34.51628],"type":"Point"}
}