{
  "type": "Feature",
  "properties": {
    "gn:admin1_code":"29.0",
    "gn:asciiname":"Xingangba",
    "gn:country_code":"CN",
    "gn:dem":1792,
    "gn:feature_class":"P",
    "gn:feature_code":"PPL",
    "gn:name":"Xingangba",
    "gn:population":0,
    "gn:timezone":"Asia/Shanghai",
    "iso:country":"CN",
    "name:zho_x_preferred":[
        "\u65b0\u5c97\u5df4"
    ],
    "wof:name":"Xingangba",
    "wof:placetype":"locality"
},
  "geometry": {"coordinates":[98.0902,24.446],"type":"Point"}
}