{
  "type": "Feature",
  "properties": {
    "gn:admin1_code":"12.0",
    "gn:asciiname":"Yuliangting",
    "gn:country_code":"CN",
    "gn:dem":63,
    "gn:feature_class":"P",
    "gn:feature_code":"PPL",
    "gn:name":"Yuliangting",
    "gn:population":0,
    "gn:timezone":"Asia/Shanghai",
    "iso:country":"CN",
    "name:zho_x_preferred":[
        "Yuliangting"
    ],
    "name:zho_x_variant":[
        "\u4f59\u51c9\u4ead"
    ],
    "wof:name":"Yuliangting",
    "wof:placetype":"locality"
},
  "geometry": {"coordinates":[115.32908,30.25702],"type":"Point"}
}