{
  "type": "Feature",
  "properties": {
    "gn:admin1_code":"12.0",
    "gn:asciiname":"Maozichong",
    "gn:country_code":"CN",
    "gn:dem":86,
    "gn:feature_class":"P",
    "gn:feature_code":"PPL",
    "gn:name":"Maozichong",
    "gn:population":0,
    "gn:timezone":"Asia/Shanghai",
    "iso:country":"CN",
    "name:zho_x_preferred":[
        "\u732b\u5b50\u51b2"
    ],
    "wof:name":"Maozichong",
    "wof:placetype":"locality"
},
  "geometry": {"coordinates":[112.39864,31.99696],"type":"Point"}
}