{
  "type": "Feature",
  "properties": {
    "gn:admin1_code":"9.0",
    "gn:asciiname":"Geshan",
    "gn:country_code":"CN",
    "gn:dem":88,
    "gn:feature_class":"P",
    "gn:feature_code":"PPL",
    "gn:name":"Geshan",
    "gn:population":0,
    "gn:timezone":"Asia/Shanghai",
    "iso:country":"CN",
    "name:zho_x_preferred":[
        "\u9694\u5c71"
    ],
    "wof:name":"Geshan",
    "wof:placetype":"locality"
},
  "geometry": {"coordinates":[115.43347,31.8891],"type":"Point"}
}