{
  "type": "Feature",
  "properties": {
    "gn:admin1_code":"10.0",
    "gn:asciiname":"Xianhuayu",
    "gn:country_code":"CN",
    "gn:dem":143,
    "gn:feature_class":"P",
    "gn:feature_code":"PPL",
    "gn:name":"Xianhuayu",
    "gn:population":0,
    "gn:timezone":"Asia/Shanghai",
    "iso:country":"CN",
    "name:zho_x_preferred":[
        "\u9c9c\u82b1\u5cea"
    ],
    "wof:name":"Xianhuayu",
    "wof:placetype":"locality"
},
  "geometry": {"coordinates":[119.01326,40.03542],"type":"Point"}
}