{
  "type": "Feature",
  "properties": {
    "gn:admin1_code":"16.0",
    "gn:asciiname":"Caila",
    "gn:country_code":"CN",
    "gn:dem":258,
    "gn:feature_class":"P",
    "gn:feature_code":"PPL",
    "gn:name":"Caila",
    "gn:population":0,
    "gn:timezone":"Asia/Shanghai",
    "iso:country":"CN",
    "name:zho_x_preferred":[
        "\u624d\u814a"
    ],
    "wof:name":"Caila",
    "wof:placetype":"locality"
},
  "geometry": {"coordinates":[108.23699999999999,25.1174],"type":"Point"}
}