{
  "type": "Feature",
  "properties": {
    "gn:admin1_code":"19.0",
    "gn:asciiname":"Qingyishancun",
    "gn:country_code":"CN",
    "gn:dem":248,
    "gn:feature_class":"P",
    "gn:feature_code":"PPL",
    "gn:name":"Qingyishancun",
    "gn:population":0,
    "gn:timezone":"Asia/Shanghai",
    "iso:country":"CN",
    "name:zho_x_preferred":[
        "\u9752\u6905\u5c71\u6751"
    ],
    "wof:name":"Qingyishancun",
    "wof:placetype":"locality"
},
  "geometry": {"coordinates":[124.61939,40.68836],"type":"Point"}
}