{
  "type": "Feature",
  "properties": {
    "gn:admin1_code":"32.0",
    "gn:asciiname":"Fuyanxi",
    "gn:country_code":"CN",
    "gn:dem":1183,
    "gn:feature_class":"P",
    "gn:feature_code":"PPL",
    "gn:name":"Fuyanxi",
    "gn:population":0,
    "gn:timezone":"Asia/Shanghai",
    "iso:country":"CN",
    "name:zho_x_preferred":[
        "\u590d\u70df\u6eaa"
    ],
    "wof:name":"Fuyanxi",
    "wof:placetype":"locality"
},
  "geometry": {"coordinates":[102.80242,29.91635],"type":"Point"}
}