{
  "type": "Feature",
  "properties": {
    "gn:admin1_code":"2.0",
    "gn:asciiname":"Tangqi",
    "gn:country_code":"CN",
    "gn:dem":282,
    "gn:feature_class":"P",
    "gn:feature_code":"PPL",
    "gn:name":"Tangqi",
    "gn:population":0,
    "gn:timezone":"Asia/Shanghai",
    "iso:country":"CN",
    "name:zho_x_preferred":[
        "\u5858\u9f50"
    ],
    "wof:name":"Tangqi",
    "wof:placetype":"locality"
},
  "geometry": {"coordinates":[119.66803,28.70767],"type":"Point"}
}