{
  "type": "Feature",
  "properties": {
    "gn:admin1_code":"21.0",
    "gn:asciiname":"Litao",
    "gn:country_code":"CN",
    "gn:dem":2098,
    "gn:feature_class":"P",
    "gn:feature_code":"PPL",
    "gn:name":"Litao",
    "gn:population":0,
    "gn:timezone":"Asia/Shanghai",
    "iso:country":"CN",
    "name:zho_x_preferred":[
        "\u9ece\u5957"
    ],
    "wof:name":"Litao",
    "wof:placetype":"locality"
},
  "geometry": {"coordinates":[106.059,35.9291],"type":"Point"}
}