{
  "type": "Feature",
  "properties": {
    "gn:admin1_code":"1.0",
    "gn:asciiname":"Gushancun",
    "gn:country_code":"CN",
    "gn:dem":61,
    "gn:feature_class":"P",
    "gn:feature_code":"PPL",
    "gn:name":"Gushancun",
    "gn:population":0,
    "gn:timezone":"Asia/Shanghai",
    "iso:country":"CN",
    "name:zho_x_preferred":[
        "\u59d1\u5c71\u6751"
    ],
    "wof:name":"Gushancun",
    "wof:placetype":"locality"
},
  "geometry": {"coordinates":[116.92977999999999,31.69614],"type":"Point"}
}