{
  "type": "Feature",
  "properties": {
    "gn:admin1_code":"29",
    "gn:asciiname":"Zhelian",
    "gn:country_code":"CN",
    "gn:dem":807,
    "gn:feature_class":"P",
    "gn:feature_code":"PPL",
    "gn:name":"Zhelian",
    "gn:population":0,
    "gn:timezone":"Asia/Shanghai",
    "iso:country":"CN",
    "name:zho_x_preferred":[
        "\u8005\u8fde"
    ],
    "wof:name":"Zhelian",
    "wof:placetype":"locality"
},
  "geometry": {"coordinates":[104.867,24.4068],"type":"Point"}
}