{
  "type": "Feature",
  "properties": {
    "gn:admin1_code":"11.0",
    "gn:asciiname":"Longtouyan",
    "gn:country_code":"CN",
    "gn:dem":211,
    "gn:feature_class":"P",
    "gn:feature_code":"PPL",
    "gn:name":"Longtouyan",
    "gn:population":0,
    "gn:timezone":"Asia/Shanghai",
    "iso:country":"CN",
    "name:zho_x_preferred":[
        "\u5785\u5934\u5ca9"
    ],
    "wof:name":"Longtouyan",
    "wof:placetype":"locality"
},
  "geometry": {"coordinates":[113.57033,26.58756],"type":"Point"}
}