{
  "type": "Feature",
  "properties": {
    "gn:admin1_code":"4.0",
    "gn:asciiname":"Liuhong",
    "gn:country_code":"CN",
    "gn:dem":11,
    "gn:feature_class":"P",
    "gn:feature_code":"PPL",
    "gn:name":"Liuhong",
    "gn:population":0,
    "gn:timezone":"Asia/Shanghai",
    "iso:country":"CN",
    "name:zho_x_preferred":[
        "\u5218\u6d2a"
    ],
    "wof:name":"Liuhong",
    "wof:placetype":"locality"
},
  "geometry": {"coordinates":[118.74933,34.06769],"type":"Point"}
}