{
  "type": "Feature",
  "properties": {
    "gn:admin1_code":"4.0",
    "gn:asciiname":"Ruyi",
    "gn:country_code":"CN",
    "gn:dem":6,
    "gn:feature_class":"P",
    "gn:feature_code":"PPL",
    "gn:name":"Ruyi",
    "gn:population":0,
    "gn:timezone":"Asia/Shanghai",
    "iso:country":"CN",
    "name:deu_x_preferred":[
        "Ruyi"
    ],
    "name:zho_x_preferred":[
        "\u5982\u610f"
    ],
    "wof:name":"Ruyi",
    "wof:placetype":"locality"
},
  "geometry": {"coordinates":[119.86212999999999,32.11651],"type":"Point"}
}