{
  "type": "Feature",
  "properties": {
    "gn:admin1_code":"1.0",
    "gn:asciiname":"Dajiangcun",
    "gn:country_code":"CN",
    "gn:dem":57,
    "gn:feature_class":"P",
    "gn:feature_code":"PPL",
    "gn:name":"Dajiangcun",
    "gn:population":0,
    "gn:timezone":"Asia/Shanghai",
    "iso:country":"CN",
    "name:zho_x_preferred":[
        "\u5927\u848b\u6751"
    ],
    "wof:name":"Dajiangcun",
    "wof:placetype":"locality"
},
  "geometry": {"coordinates":[117.83844000000001,32.27612],"type":"Point"}
}