{
  "type": "Feature",
  "properties": {
    "gn:admin1_code":"32.0",
    "gn:asciiname":"Mogangling",
    "gn:country_code":"CN",
    "gn:dem":1843,
    "gn:feature_class":"P",
    "gn:feature_code":"PPL",
    "gn:name":"Mogangling",
    "gn:population":0,
    "gn:timezone":"Asia/Shanghai",
    "iso:country":"CN",
    "name:zho_x_preferred":[
        "\u6469\u5c97\u5cad"
    ],
    "wof:name":"Mogangling",
    "wof:placetype":"locality"
},
  "geometry": {"coordinates":[102.154,29.6138],"type":"Point"}
}