{
  "type": "Feature",
  "properties": {
    "gn:admin1_code":"4.0",
    "gn:asciiname":"Guanzhuang",
    "gn:country_code":"CN",
    "gn:dem":50,
    "gn:feature_class":"P",
    "gn:feature_code":"PPL",
    "gn:name":"Guanzhuang",
    "gn:population":0,
    "gn:timezone":"Asia/Shanghai",
    "iso:country":"CN",
    "name:ceb_x_preferred":[
        "Guanzhuang"
    ],
    "name:swe_x_preferred":[
        "Guanzhuang"
    ],
    "name:zho_x_preferred":[
        "\u5b98\u5e84"
    ],
    "name:zho_x_variant":[
        "\u5b98\u5e84\u9547"
    ],
    "wof:name":"Guanzhuang",
    "wof:placetype":"locality"
},
  "geometry": {"coordinates":[117.527,34.1775],"type":"Point"}
}