{
  "type": "Feature",
  "properties": {
    "gn:admin1_code":"11.0",
    "gn:asciiname":"Caishetang",
    "gn:country_code":"CN",
    "gn:dem":107,
    "gn:feature_class":"P",
    "gn:feature_code":"PPL",
    "gn:name":"Caishetang",
    "gn:population":0,
    "gn:timezone":"Asia/Shanghai",
    "iso:country":"CN",
    "name:zho_x_preferred":[
        "\u83dc\u820d\u5858"
    ],
    "wof:name":"Caishetang",
    "wof:placetype":"locality"
},
  "geometry": {"coordinates":[111.91065,26.43114000000001],"type":"Point"}
}