{
  "type": "Feature",
  "properties": {
    "gn:admin1_code":"29.0",
    "gn:asciiname":"Liushima Xiaozhai",
    "gn:country_code":"CN",
    "gn:dem":1482,
    "gn:feature_class":"P",
    "gn:feature_code":"PPL",
    "gn:name":"Liushima Xiaozhai",
    "gn:population":0,
    "gn:timezone":"Asia/Shanghai",
    "iso:country":"CN",
    "name:zho_x_preferred":[
        "\u516d\u5341\u9a82\u5c0f\u5be8"
    ],
    "wof:name":"Liushima Xiaozhai",
    "wof:placetype":"locality"
},
  "geometry": {"coordinates":[104.18600000000001,24.1158],"type":"Point"}
}