{
  "type": "Feature",
  "properties": {
    "gn:admin1_code":"18",
    "gn:asciiname":"Bazhangping",
    "gn:country_code":"CN",
    "gn:dem":923,
    "gn:feature_class":"P",
    "gn:feature_code":"PPL",
    "gn:name":"Bazhangping",
    "gn:population":0,
    "gn:timezone":"Asia/Shanghai",
    "iso:country":"CN",
    "name:zho_x_preferred":[
        "\u5df4\u638c\u576a"
    ],
    "wof:name":"Bazhangping",
    "wof:placetype":"locality"
},
  "geometry": {"coordinates":[107.33499999999999,28.7772],"type":"Point"}
}