{
  "type": "Feature",
  "properties": {
    "gn:admin1_code":"4.0",
    "gn:asciiname":"Zouhuangcun",
    "gn:country_code":"CN",
    "gn:dem":31,
    "gn:feature_class":"P",
    "gn:feature_code":"PPL",
    "gn:name":"Zouhuangcun",
    "gn:population":0,
    "gn:timezone":"Asia/Shanghai",
    "iso:country":"CN",
    "name:zho_x_preferred":[
        "\u90b9\u9ec4\u6751"
    ],
    "wof:name":"Zouhuangcun",
    "wof:placetype":"locality"
},
  "geometry": {"coordinates":[118.29546999999999,33.08069],"type":"Point"}
}