{
  "type": "Feature",
  "properties": {
    "gn:admin1_code":"25",
    "gn:asciiname":"Sannanyin",
    "gn:country_code":"CN",
    "gn:dem":94,
    "gn:feature_class":"P",
    "gn:feature_code":"PPL",
    "gn:name":"Sannanyin",
    "gn:population":0,
    "gn:timezone":"Asia/Shanghai",
    "iso:country":"CN",
    "name:zho_x_preferred":[
        "\u4e09\u5357\u5c39"
    ],
    "wof:name":"Sannanyin",
    "wof:placetype":"locality"
},
  "geometry": {"coordinates":[118.095,35.2335],"type":"Point"}
}