{
  "type": "Feature",
  "properties": {
    "gn:admin1_code":"11",
    "gn:asciiname":"Huilongan",
    "gn:country_code":"CN",
    "gn:dem":359,
    "gn:feature_class":"P",
    "gn:feature_code":"PPLA4",
    "gn:name":"Huilongan",
    "gn:population":0,
    "gn:timezone":"Asia/Shanghai",
    "iso:country":"CN",
    "name:und_x_variant":[
        "\u56de\u9f99\u5eb5",
        "Huilong",
        "Huilong Xiang",
        "\u56de\u9f99",
        "\u56de\u9f99\u4e61"
    ],
    "wof:name":"Huilongan",
    "wof:placetype":"locality"
},
  "geometry": {"coordinates":[110.18219000000001,28.8893],"type":"Point"}
}