{
  "type": "Feature",
  "properties": {
    "gn:admin1_code":"7.0",
    "gn:asciiname":"Liankeng",
    "gn:country_code":"CN",
    "gn:dem":477,
    "gn:feature_class":"P",
    "gn:feature_code":"PPL",
    "gn:name":"Liankeng",
    "gn:population":0,
    "gn:timezone":"Asia/Shanghai",
    "iso:country":"CN",
    "name:und_x_variant":[
        "\u8fde\u5751"
    ],
    "name:zho_x_preferred":[
        "\u8fde\u5751"
    ],
    "wof:name":"Liankeng",
    "wof:placetype":"locality"
},
  "geometry": {"coordinates":[118.48108999999999,26.63481],"type":"Point"}
}