{
  "type": "Feature",
  "properties": {
    "gn:admin1_code":"32.0",
    "gn:asciiname":"Zhuori",
    "gn:country_code":"CN",
    "gn:dem":4257,
    "gn:feature_class":"P",
    "gn:feature_code":"PPL",
    "gn:name":"Zhuori",
    "gn:population":0,
    "gn:timezone":"Asia/Shanghai",
    "iso:country":"CN",
    "name:zho_x_preferred":[
        "\u6349\u65e5"
    ],
    "wof:name":"Zhuori",
    "wof:placetype":"locality"
},
  "geometry": {"coordinates":[98.3348,33.1388],"type":"Point"}
}