{
  "type": "Feature",
  "properties": {
    "gn:admin1_code":"30.0",
    "gn:asciiname":"Shenshuilong",
    "gn:country_code":"CN",
    "gn:dem":27,
    "gn:feature_class":"P",
    "gn:feature_code":"PPL",
    "gn:name":"Shenshuilong",
    "gn:population":0,
    "gn:timezone":"Asia/Shanghai",
    "iso:country":"CN",
    "name:zho_x_preferred":[
        "\u6df1\u6c34\u9f99"
    ],
    "wof:name":"Shenshuilong",
    "wof:placetype":"locality"
},
  "geometry": {"coordinates":[113.21722,24.09472],"type":"Point"}
}