{
  "type": "Feature",
  "properties": {
    "gn:admin1_code":"32.0",
    "gn:asciiname":"Beiyahe",
    "gn:country_code":"CN",
    "gn:dem":349,
    "gn:feature_class":"P",
    "gn:feature_code":"PPL",
    "gn:name":"Beiyahe",
    "gn:population":0,
    "gn:timezone":"Asia/Shanghai",
    "iso:country":"CN",
    "name:zho_x_preferred":[
        "\u7891\u57ad\u5408"
    ],
    "wof:name":"Beiyahe",
    "wof:placetype":"locality"
},
  "geometry": {"coordinates":[106.139,31.1747],"type":"Point"}
}