{
  "type": "Feature",
  "properties": {
    "gn:admin1_code":"25.0",
    "gn:asciiname":"Wangjiakouzi",
    "gn:cc2":"CN",
    "gn:country_code":"CN",
    "gn:dem":188,
    "gn:feature_class":"P",
    "gn:feature_code":"PPL",
    "gn:name":"Wangjiakouzi",
    "gn:population":0,
    "gn:timezone":"Asia/Shanghai",
    "iso:country":"CN",
    "name:zho_x_preferred":[
        "\u738b\u5bb6\u53e3\u5b50"
    ],
    "wof:name":"Wangjiakouzi",
    "wof:placetype":"locality"
},
  "geometry": {"coordinates":[119.29978,35.70957],"type":"Point"}
}