{
  "type": "Feature",
  "properties": {
    "gn:admin1_code":"25.0",
    "gn:asciiname":"Guanshuaicun",
    "gn:country_code":"CN",
    "gn:dem":110,
    "gn:feature_class":"P",
    "gn:feature_code":"PPL",
    "gn:name":"Guanshuaicun",
    "gn:population":0,
    "gn:timezone":"Asia/Shanghai",
    "iso:country":"CN",
    "name:zho_x_preferred":[
        "\u7ba1\u5e05\u6751"
    ],
    "wof:name":"Guanshuaicun",
    "wof:placetype":"locality"
},
  "geometry": {"coordinates":[119.03767999999999,35.87611],"type":"Point"}
}