{
  "type": "Feature",
  "properties": {
    "gn:admin1_code":"9",
    "gn:asciiname":"Yanghe",
    "gn:country_code":"CN",
    "gn:dem":120,
    "gn:feature_class":"P",
    "gn:feature_code":"PPL",
    "gn:name":"Yanghe",
    "gn:population":0,
    "gn:timezone":"Asia/Shanghai",
    "iso:country":"CN",
    "name:ceb_x_preferred":[
        "Yanghe"
    ],
    "name:deu_x_preferred":[
        "Yanghe"
    ],
    "name:swe_x_preferred":[
        "Yanghe"
    ],
    "name:zho_x_preferred":[
        "\u6768\u6cb3"
    ],
    "wof:name":"Yanghe",
    "wof:placetype":"locality"
},
  "geometry": {"coordinates":[113.77043,32.25429],"type":"Point"}
}