{
  "type": "Feature",
  "properties": {
    "gn:admin1_code":"30.0",
    "gn:asciiname":"Nantouchong",
    "gn:country_code":"CN",
    "gn:dem":814,
    "gn:feature_class":"P",
    "gn:feature_code":"PPL",
    "gn:name":"Nantouchong",
    "gn:population":0,
    "gn:timezone":"Asia/Shanghai",
    "iso:country":"CN",
    "name:zho_x_preferred":[
        "Nantouchong"
    ],
    "name:zho_x_variant":[
        "\u5357\u5934\u51b2"
    ],
    "wof:name":"Nantouchong",
    "wof:placetype":"locality"
},
  "geometry": {"coordinates":[113.14387000000001,25.07932000000001],"type":"Point"}
}