{
  "type": "Feature",
  "properties": {
    "gn:admin1_code":"9",
    "gn:asciiname":"Beifouzipu",
    "gn:country_code":"CN",
    "gn:dem":48,
    "gn:feature_class":"P",
    "gn:feature_code":"PPL",
    "gn:name":"Beifouzipu",
    "gn:population":0,
    "gn:timezone":"Asia/Shanghai",
    "iso:country":"CN",
    "name:zho_x_preferred":[
        "\u5317\u5426\u5b50\u94fa"
    ],
    "wof:name":"Beifouzipu",
    "wof:placetype":"locality"
},
  "geometry": {"coordinates":[115.48383,35.81933],"type":"Point"}
}