{
  "type": "Feature",
  "properties": {
    "gn:admin1_code":"8.0",
    "gn:asciiname":"Ejia Wobu",
    "gn:country_code":"CN",
    "gn:dem":167,
    "gn:feature_class":"P",
    "gn:feature_code":"PPL",
    "gn:name":"Ejia Wobu",
    "gn:population":0,
    "gn:timezone":"Asia/Shanghai",
    "iso:country":"CN",
    "name:zho_x_preferred":[
        "\u9102\u5bb6\u7a9d\u5821"
    ],
    "wof:name":"Ejia Wobu",
    "wof:placetype":"locality"
},
  "geometry": {"coordinates":[126.16522999999999,46.22307],"type":"Point"}
}