{
  "type": "Feature",
  "properties": {
    "gn:admin1_code":"29.0",
    "gn:asciiname":"Wenshu",
    "gn:country_code":"CN",
    "gn:dem":2671,
    "gn:feature_class":"P",
    "gn:feature_code":"PPL",
    "gn:name":"Wenshu",
    "gn:population":0,
    "gn:timezone":"Asia/Shanghai",
    "iso:country":"CN",
    "name:zho_x_preferred":[
        "\u6e29\u6811"
    ],
    "wof:name":"Wenshu",
    "wof:placetype":"locality"
},
  "geometry": {"coordinates":[99.504,26.1384],"type":"Point"}
}