{
  "type": "Feature",
  "properties": {
    "gn:admin1_code":"10.0",
    "gn:asciiname":"Wanglongwa",
    "gn:country_code":"CN",
    "gn:dem":7,
    "gn:feature_class":"P",
    "gn:feature_code":"PPL",
    "gn:name":"Wanglongwa",
    "gn:population":0,
    "gn:timezone":"Asia/Shanghai",
    "iso:country":"CN",
    "name:zho_x_preferred":[
        "\u738b\u9f99\u6d3c"
    ],
    "wof:name":"Wanglongwa",
    "wof:placetype":"locality"
},
  "geometry": {"coordinates":[117.423,38.1062],"type":"Point"}
}