{
  "type": "Feature",
  "properties": {
    "gn:admin1_code":"32.0",
    "gn:asciiname":"Qiongxia",
    "gn:country_code":"CN",
    "gn:dem":3577,
    "gn:feature_class":"P",
    "gn:feature_code":"PPL",
    "gn:name":"Qiongxia",
    "gn:population":0,
    "gn:timezone":"Asia/Shanghai",
    "iso:country":"CN",
    "name:zho_x_preferred":[
        "\u7a77\u5477"
    ],
    "wof:name":"Qiongxia",
    "wof:placetype":"locality"
},
  "geometry": {"coordinates":[100.623,29.6244],"type":"Point"}
}