{
  "type": "Feature",
  "properties": {
    "gn:admin1_code":"12.0",
    "gn:asciiname":"Xintiangou",
    "gn:country_code":"CN",
    "gn:dem":787,
    "gn:feature_class":"P",
    "gn:feature_code":"PPL",
    "gn:name":"Xintiangou",
    "gn:population":0,
    "gn:timezone":"Asia/Shanghai",
    "iso:country":"CN",
    "name:zho_x_preferred":[
        "Xintiangou"
    ],
    "name:zho_x_variant":[
        "\u65b0\u7530\u6c9f"
    ],
    "wof:name":"Xintiangou",
    "wof:placetype":"locality"
},
  "geometry": {"coordinates":[109.17035,29.69917],"type":"Point"}
}