{
  "type": "Feature",
  "properties": {
    "gn:admin1_code":"07",
    "gn:asciiname":"Jinfengkeng",
    "gn:country_code":"CN",
    "gn:dem":435,
    "gn:feature_class":"P",
    "gn:feature_code":"PPL",
    "gn:name":"Jinfengkeng",
    "gn:population":0,
    "gn:timezone":"Asia/Shanghai",
    "iso:country":"CN",
    "name:zho_x_preferred":[
        "\u8fdb\u5cf0\u5751"
    ],
    "wof:name":"Jinfengkeng",
    "wof:placetype":"locality"
},
  "geometry": {"coordinates":[117.23762000000001,25.87914],"type":"Point"}
}