{
  "type": "Feature",
  "properties": {
    "gn:admin1_code":"15.0",
    "gn:asciiname":"Choujiashan",
    "gn:country_code":"CN",
    "gn:dem":1793,
    "gn:feature_class":"P",
    "gn:feature_code":"PPL",
    "gn:name":"Choujiashan",
    "gn:population":0,
    "gn:timezone":"Asia/Shanghai",
    "iso:country":"CN",
    "name:zho_x_preferred":[
        "\u4ec7\u5bb6\u5c71"
    ],
    "wof:name":"Choujiashan",
    "wof:placetype":"locality"
},
  "geometry": {"coordinates":[104.53308,33.77486],"type":"Point"}
}