{
  "type": "Feature",
  "properties": {
    "gn:admin1_code":"10.0",
    "gn:asciiname":"Dongguancheng",
    "gn:country_code":"CN",
    "gn:dem":45,
    "gn:feature_class":"P",
    "gn:feature_code":"PPL",
    "gn:name":"Dongguancheng",
    "gn:population":0,
    "gn:timezone":"Asia/Shanghai",
    "iso:country":"CN",
    "name:zho_x_preferred":[
        "\u4e1c\u8d2f\u57ce"
    ],
    "wof:name":"Dongguancheng",
    "wof:placetype":"locality"
},
  "geometry": {"coordinates":[115.55410999999999,39.2678],"type":"Point"}
}