{
  "type": "Feature",
  "properties": {
    "gn:admin1_code":"26.0",
    "gn:asciiname":"Laowa Xiaotanzi",
    "gn:country_code":"CN",
    "gn:dem":1258,
    "gn:feature_class":"P",
    "gn:feature_code":"PPL",
    "gn:name":"Laowa Xiaotanzi",
    "gn:population":0,
    "gn:timezone":"Asia/Shanghai",
    "iso:country":"CN",
    "name:zho_x_preferred":[
        "\u8001\u6d3c\u5c0f\u6ee9\u5b50"
    ],
    "wof:name":"Laowa Xiaotanzi",
    "wof:placetype":"locality"
},
  "geometry": {"coordinates":[109.79600000000001,38.5941],"type":"Point"}
}