{
  "type": "Feature",
  "properties": {
    "gn:admin1_code":"02",
    "gn:asciiname":"Luzhongcun",
    "gn:country_code":"CN",
    "gn:dem":10,
    "gn:feature_class":"P",
    "gn:feature_code":"PPL",
    "gn:name":"Luzhongcun",
    "gn:population":0,
    "gn:timezone":"Asia/Shanghai",
    "iso:country":"CN",
    "name:und_x_variant":[
        "Luzhong",
        "\u8def\u4ef2",
        "Luzhongcun"
    ],
    "name:zho_x_preferred":[
        "\u8def\u4ef2\u6751"
    ],
    "wof:name":"Luzhongcun",
    "wof:placetype":"locality"
},
  "geometry": {"coordinates":[120.60804,30.52861],"type":"Point"}
}