{
  "type": "Feature",
  "properties": {
    "gn:admin1_code":"2.0",
    "gn:asciiname":"Pantiaokou",
    "gn:country_code":"CN",
    "gn:dem":907,
    "gn:feature_class":"P",
    "gn:feature_code":"PPL",
    "gn:name":"Pantiaokou",
    "gn:population":0,
    "gn:timezone":"Asia/Shanghai",
    "iso:country":"CN",
    "name:und_x_variant":[
        "\u76d8\u6761\u53e3",
        "Pantiaokou"
    ],
    "wof:name":"Pantiaokou",
    "wof:placetype":"locality"
},
  "geometry": {"coordinates":[119.39095,27.97792],"type":"Point"}
}