{
  "type": "Feature",
  "properties": {
    "gn:admin1_code":"19.0",
    "gn:asciiname":"Tianbaotuncun",
    "gn:country_code":"CN",
    "gn:dem":171,
    "gn:feature_class":"P",
    "gn:feature_code":"PPL",
    "gn:name":"Tianbaotuncun",
    "gn:population":0,
    "gn:timezone":"Asia/Shanghai",
    "iso:country":"CN",
    "name:zho_x_preferred":[
        "\u5929\u4fdd\u5c6f\u6751"
    ],
    "wof:name":"Tianbaotuncun",
    "wof:placetype":"locality"
},
  "geometry": {"coordinates":[122.693,40.3703],"type":"Point"}
}