{
  "type": "Feature",
  "properties": {
    "gn:admin1_code":"29.0",
    "gn:asciiname":"Diaotongqing",
    "gn:country_code":"CN",
    "gn:dem":1906,
    "gn:feature_class":"P",
    "gn:feature_code":"PPL",
    "gn:name":"Diaotongqing",
    "gn:population":0,
    "gn:timezone":"Asia/Shanghai",
    "iso:country":"CN",
    "name:zho_x_preferred":[
        "\u540a\u6876\u7b90"
    ],
    "wof:name":"Diaotongqing",
    "wof:placetype":"locality"
},
  "geometry": {"coordinates":[101.565,25.574],"type":"Point"}
}