{
  "type": "Feature",
  "properties": {
    "gn:admin1_code":"0.0",
    "gn:asciiname":"Jianong",
    "gn:country_code":"CN",
    "gn:dem":391,
    "gn:feature_class":"P",
    "gn:feature_code":"PPL",
    "gn:name":"Jianong",
    "gn:population":0,
    "gn:timezone":"Asia/Shanghai",
    "iso:country":"CN",
    "name:zho_x_preferred":[
        "\u5609\u519c"
    ],
    "wof:name":"Jianong",
    "wof:placetype":"locality"
},
  "geometry": {"coordinates":[103.60829,29.49525],"type":"Point"}
}