{
  "type": "Feature",
  "properties": {
    "gn:admin1_code":"14.0",
    "gn:asciiname":"Moinkar",
    "gn:country_code":"CN",
    "gn:dem":4133,
    "gn:feature_class":"P",
    "gn:feature_code":"PPL",
    "gn:name":"Moinkar",
    "gn:population":0,
    "gn:timezone":"Asia/Urumqi",
    "iso:country":"CN",
    "name:bod_x_preferred":[
        "Moinkar"
    ],
    "name:zho_x_preferred":[
        "Menka"
    ],
    "name:zho_x_variant":[
        "\u95e8\u5361",
        "Duoga Gongshe",
        "\u591a\u560e\u516c\u793e"
    ],
    "wof:name":"Moinkar",
    "wof:placetype":"locality"
},
  "geometry": {"coordinates":[92.503,29.003],"type":"Point"}
}