{
  "type": "Feature",
  "properties": {
    "gn:admin1_code":"3.0",
    "gn:asciiname":"Xiahuai",
    "gn:country_code":"CN",
    "gn:dem":25,
    "gn:feature_class":"P",
    "gn:feature_code":"PPL",
    "gn:name":"Xiahuai",
    "gn:population":0,
    "gn:timezone":"Asia/Shanghai",
    "iso:country":"CN",
    "name:und_x_variant":[
        "\u590f\u69d0"
    ],
    "name:zho_x_preferred":[
        "\u4e0b\u69d0\u9547"
    ],
    "wof:name":"Xiahuai",
    "wof:placetype":"locality"
},
  "geometry": {"coordinates":[116.27556,29.67936],"type":"Point"}
}