{
  "type": "Feature",
  "properties": {
    "gn:admin1_code":"19.0",
    "gn:asciiname":"Kuntouyingzi",
    "gn:country_code":"CN",
    "gn:dem":236,
    "gn:feature_class":"P",
    "gn:feature_code":"PPL",
    "gn:name":"Kuntouyingzi",
    "gn:population":0,
    "gn:timezone":"Asia/Shanghai",
    "iso:country":"CN",
    "name:zho_x_preferred":[
        "\u5764\u5934\u8425\u5b50"
    ],
    "wof:name":"Kuntouyingzi",
    "wof:placetype":"locality"
},
  "geometry": {"coordinates":[120.07899999999999,41.3681],"type":"Point"}
}