{
  "type": "Feature",
  "properties": {
    "gn:admin1_code":"11.0",
    "gn:asciiname":"Bainitian",
    "gn:country_code":"CN",
    "gn:dem":189,
    "gn:feature_class":"P",
    "gn:feature_code":"PPL",
    "gn:name":"Bainitian",
    "gn:population":0,
    "gn:timezone":"Asia/Shanghai",
    "iso:country":"CN",
    "name:zho_x_preferred":[
        "\u767d\u6ce5\u7530"
    ],
    "wof:name":"Bainitian",
    "wof:placetype":"locality"
},
  "geometry": {"coordinates":[109.7088,27.84041],"type":"Point"}
}