{
  "type": "Feature",
  "properties": {
    "gn:admin1_code":"3.0",
    "gn:asciiname":"Huanggang Zhengjia",
    "gn:country_code":"CN",
    "gn:dem":65,
    "gn:feature_class":"P",
    "gn:feature_code":"PPL",
    "gn:name":"Huanggang Zhengjia",
    "gn:population":0,
    "gn:timezone":"Asia/Shanghai",
    "iso:country":"CN",
    "name:und_x_variant":[
        "\u9ec4\u5c97\u90d1\u5bb6"
    ],
    "wof:name":"Huanggang Zhengjia",
    "wof:placetype":"locality"
},
  "geometry": {"coordinates":[116.89946999999999,28.18264000000001],"type":"Point"}
}