{
  "type": "Feature",
  "properties": {
    "gn:admin1_code":"5",
    "gn:asciiname":"Xibeicha",
    "gn:country_code":"CN",
    "gn:dem":344,
    "gn:feature_class":"P",
    "gn:feature_code":"PPL",
    "gn:name":"Xibeicha",
    "gn:population":0,
    "gn:timezone":"Asia/Shanghai",
    "iso:country":"CN",
    "name:zho_x_preferred":[
        "\u897f\u5317\u5c94"
    ],
    "wof:name":"Xibeicha",
    "wof:placetype":"locality"
},
  "geometry": {"coordinates":[127.227,43.1866],"type":"Point"}
}