{
  "type": "Feature",
  "properties": {
    "gn:admin1_code":"10.0",
    "gn:asciiname":"Houzhuangzi",
    "gn:country_code":"CN",
    "gn:dem":856,
    "gn:feature_class":"P",
    "gn:feature_code":"PPL",
    "gn:name":"Houzhuangzi",
    "gn:population":0,
    "gn:timezone":"Asia/Shanghai",
    "iso:country":"CN",
    "name:zho_x_preferred":[
        "\u540e\u5e84\u5b50"
    ],
    "wof:name":"Houzhuangzi",
    "wof:placetype":"locality"
},
  "geometry": {"coordinates":[114.93189,39.50232000000001],"type":"Point"}
}