{
  "type": "Feature",
  "properties": {
    "gn:admin1_code":"3.0",
    "gn:asciiname":"Shangkengkou",
    "gn:country_code":"CN",
    "gn:dem":29,
    "gn:feature_class":"P",
    "gn:feature_code":"PPL",
    "gn:name":"Shangkengkou",
    "gn:population":0,
    "gn:timezone":"Asia/Shanghai",
    "iso:country":"CN",
    "name:zho_x_preferred":[
        "\u4e0a\u5751\u53e3"
    ],
    "wof:name":"Shangkengkou",
    "wof:placetype":"locality"
},
  "geometry": {"coordinates":[117.208,28.9593],"type":"Point"}
}