{
  "type": "Feature",
  "properties": {
    "gn:admin1_code":"12.0",
    "gn:asciiname":"Wachabu",
    "gn:country_code":"CN",
    "gn:dem":25,
    "gn:feature_class":"P",
    "gn:feature_code":"PPL",
    "gn:name":"Wachabu",
    "gn:population":0,
    "gn:timezone":"Asia/Shanghai",
    "iso:country":"CN",
    "name:zho_x_preferred":[
        "\u74e6\u78b4\u5821"
    ],
    "wof:name":"Wachabu",
    "wof:placetype":"locality"
},
  "geometry": {"coordinates":[113.93203,30.39572],"type":"Point"}
}