{
  "type": "Feature",
  "properties": {
    "gn:admin1_code":"16.0",
    "gn:asciiname":"Shuanglu",
    "gn:country_code":"CN",
    "gn:dem":101,
    "gn:feature_class":"P",
    "gn:feature_code":"PPL",
    "gn:name":"Shuanglu",
    "gn:population":0,
    "gn:timezone":"Asia/Shanghai",
    "iso:country":"CN",
    "name:zho_x_preferred":[
        "\u53cc\u5362"
    ],
    "wof:name":"Shuanglu",
    "wof:placetype":"locality"
},
  "geometry": {"coordinates":[108.128,23.137],"type":"Point"}
}