{
  "type": "Feature",
  "properties": {
    "gn:admin1_code":"1.0",
    "gn:asciiname":"Yonghongcun",
    "gn:country_code":"CN",
    "gn:dem":22,
    "gn:feature_class":"P",
    "gn:feature_code":"PPL",
    "gn:name":"Yonghongcun",
    "gn:population":0,
    "gn:timezone":"Asia/Shanghai",
    "iso:country":"CN",
    "name:zho_x_preferred":[
        "\u6c38\u7ea2\u6751"
    ],
    "wof:name":"Yonghongcun",
    "wof:placetype":"locality"
},
  "geometry": {"coordinates":[118.43183000000001,32.27711],"type":"Point"}
}