{
  "type": "Feature",
  "properties": {
    "gn:admin1_code":"6.0",
    "gn:asciiname":"Domkog",
    "gn:country_code":"CN",
    "gn:dem":3974,
    "gn:feature_class":"P",
    "gn:feature_code":"PPL",
    "gn:name":"Domkog",
    "gn:population":0,
    "gn:timezone":"Asia/Shanghai",
    "iso:country":"CN",
    "wof:name":"Domkog",
    "wof:placetype":"locality"
},
  "geometry": {"coordinates":[99.98333,34.51667],"type":"Point"}
}