{
  "type": "Feature",
  "properties": {
    "gn:admin1_code":"30",
    "gn:asciiname":"Hetangbei",
    "gn:country_code":"CN",
    "gn:dem":192,
    "gn:feature_class":"P",
    "gn:feature_code":"PPL",
    "gn:name":"Hetangbei",
    "gn:population":0,
    "gn:timezone":"Asia/Shanghai",
    "iso:country":"CN",
    "name:zho_x_preferred":[
        "\u79be\u5858\u80cc"
    ],
    "wof:name":"Hetangbei",
    "wof:placetype":"locality"
},
  "geometry": {"coordinates":[115.73761,24.28368],"type":"Point"}
}