{
  "type": "Feature",
  "properties": {
    "gn:admin1_code":"3.0",
    "gn:asciiname":"Xitang",
    "gn:country_code":"CN",
    "gn:dem":580,
    "gn:feature_class":"P",
    "gn:feature_code":"PPL",
    "gn:name":"Xitang",
    "gn:population":0,
    "gn:timezone":"Asia/Shanghai",
    "iso:country":"CN",
    "name:ara_x_preferred":[
        "\u0634\u064a\u062a\u0627\u0646\u063a"
    ],
    "name:deu_x_preferred":[
        "Xitang"
    ],
    "name:fra_x_preferred":[
        "Xitang"
    ],
    "name:jpn_x_preferred":[
        "\u897f\u5858\u93ae"
    ],
    "name:und_x_variant":[
        "\u897f\u5858"
    ],
    "name:vie_x_preferred":[
        "T\u00e2y \u0110\u01b0\u1eddng"
    ],
    "name:wuu_x_preferred":[
        "\u897f\u5858\u9547"
    ],
    "name:zho_x_preferred":[
        "\u897f\u5858\u9547"
    ],
    "wof:name":"Xitang",
    "wof:placetype":"locality"
},
  "geometry": {"coordinates":[114.10996000000002,27.57578],"type":"Point"}
}