{
  "type": "Feature",
  "properties": {
    "gn:admin1_code":"10.0",
    "gn:asciiname":"Xiaxinglongzhuang",
    "gn:country_code":"CN",
    "gn:dem":132,
    "gn:feature_class":"P",
    "gn:feature_code":"PPL",
    "gn:name":"Xiaxinglongzhuang",
    "gn:population":0,
    "gn:timezone":"Asia/Shanghai",
    "iso:country":"CN",
    "name:zho_x_preferred":[
        "\u4e0b\u5174\u9686\u5e84"
    ],
    "wof:name":"Xiaxinglongzhuang",
    "wof:placetype":"locality"
},
  "geometry": {"coordinates":[119.08853999999999,40.06718],"type":"Point"}
}