{
  "type": "Feature",
  "properties": {
    "gn:admin1_code":"29.0",
    "gn:asciiname":"Daka Xinzhai",
    "gn:country_code":"CN",
    "gn:dem":660,
    "gn:feature_class":"P",
    "gn:feature_code":"PPL",
    "gn:name":"Daka Xinzhai",
    "gn:population":0,
    "gn:timezone":"Asia/Shanghai",
    "iso:country":"CN",
    "name:zho_x_preferred":[
        "\u5927\u5361\u65b0\u5be8"
    ],
    "wof:name":"Daka Xinzhai",
    "wof:placetype":"locality"
},
  "geometry": {"coordinates":[101.247,21.9008],"type":"Point"}
}