{
  "type": "Feature",
  "properties": {
    "gn:admin1_code":"8.0",
    "gn:asciiname":"Heishantun",
    "gn:country_code":"CN",
    "gn:dem":168,
    "gn:feature_class":"P",
    "gn:feature_code":"PPL",
    "gn:name":"Heishantun",
    "gn:population":0,
    "gn:timezone":"Asia/Shanghai",
    "iso:country":"CN",
    "name:zho_x_preferred":[
        "\u9ed1\u5c71\u5c6f"
    ],
    "wof:name":"Heishantun",
    "wof:placetype":"locality"
},
  "geometry": {"coordinates":[124.40112000000001,47.96353],"type":"Point"}
}