{
  "type": "Feature",
  "properties": {
    "gn:admin1_code":"26",
    "gn:asciiname":"Fenghou",
    "gn:country_code":"CN",
    "gn:dem":981,
    "gn:feature_class":"P",
    "gn:feature_code":"PPL",
    "gn:name":"Fenghou",
    "gn:population":0,
    "gn:timezone":"Asia/Shanghai",
    "iso:country":"CN",
    "name:zho_x_preferred":[
        "\u5c01\u4faf"
    ],
    "wof:name":"Fenghou",
    "wof:placetype":"locality"
},
  "geometry": {"coordinates":[108.15443999999999,34.70611],"type":"Point"}
}