{
  "type": "Feature",
  "properties": {
    "gn:admin1_code":"4.0",
    "gn:asciiname":"Chenwucun",
    "gn:country_code":"CN",
    "gn:dem":46,
    "gn:feature_class":"P",
    "gn:feature_code":"PPL",
    "gn:name":"Chenwucun",
    "gn:population":0,
    "gn:timezone":"Asia/Shanghai",
    "iso:country":"CN",
    "name:zho_x_preferred":[
        "\u9648\u6b66\u6751"
    ],
    "wof:name":"Chenwucun",
    "wof:placetype":"locality"
},
  "geometry": {"coordinates":[119.26251000000001,32.03229],"type":"Point"}
}