{
  "type": "Feature",
  "properties": {
    "gn:admin1_code":"14.0",
    "gn:asciiname":"Quruo",
    "gn:country_code":"CN",
    "gn:dem":4414,
    "gn:feature_class":"P",
    "gn:feature_code":"PPL",
    "gn:name":"Quruo",
    "gn:population":0,
    "gn:timezone":"Asia/Shanghai",
    "iso:country":"CN",
    "name:und_x_variant":[
        "Qiaolu",
        "Quruo"
    ],
    "name:zho_x_preferred":[
        "\u4e54\u8def"
    ],
    "name:zho_x_variant":[
        "\u66f2\u82e5"
    ],
    "wof:name":"Quruo",
    "wof:placetype":"locality"
},
  "geometry": {"coordinates":[80.24120000000001,33.7409],"type":"Point"}
}