{
  "type": "Feature",
  "properties": {
    "gn:admin1_code":"29.0",
    "gn:asciiname":"Manlaojie",
    "gn:country_code":"CN",
    "gn:dem":1085,
    "gn:feature_class":"P",
    "gn:feature_code":"PPL",
    "gn:name":"Manlaojie",
    "gn:population":0,
    "gn:timezone":"Asia/Shanghai",
    "iso:country":"CN",
    "name:zho_x_preferred":[
        "\u66fc\u8001\u8857"
    ],
    "wof:name":"Manlaojie",
    "wof:placetype":"locality"
},
  "geometry": {"coordinates":[101.32299999999999,22.7634],"type":"Point"}
}