{
  "type": "Feature",
  "properties": {
    "gn:admin1_code":"24",
    "gn:asciiname":"Nangou",
    "gn:country_code":"CN",
    "gn:dem":648,
    "gn:feature_class":"P",
    "gn:feature_code":"PPL",
    "gn:name":"Nangou",
    "gn:population":0,
    "gn:timezone":"Asia/Shanghai",
    "iso:country":"CN",
    "name:und_x_variant":[
        "Nan-kou",
        "Nangou"
    ],
    "name:zho_x_preferred":[
        "\u5357\u6c9f"
    ],
    "wof:name":"Nangou",
    "wof:placetype":"locality"
},
  "geometry": {"coordinates":[111.69907000000001,36.43444],"type":"Point"}
}