{
  "type": "Feature",
  "properties": {
    "gn:admin1_code":"12.0",
    "gn:asciiname":"Pianyanzi",
    "gn:country_code":"CN",
    "gn:dem":1048,
    "gn:feature_class":"P",
    "gn:feature_code":"PPL",
    "gn:name":"Pianyanzi",
    "gn:population":0,
    "gn:timezone":"Asia/Shanghai",
    "iso:country":"CN",
    "name:zho_x_preferred":[
        "\u504f\u5ca9\u5b50"
    ],
    "wof:name":"Pianyanzi",
    "wof:placetype":"locality"
},
  "geometry": {"coordinates":[109.68902,32.01231],"type":"Point"}
}