{
  "type": "Feature",
  "properties": {
    "gn:admin1_code":"5.0",
    "gn:asciiname":"Yangmaocun",
    "gn:country_code":"CN",
    "gn:dem":164,
    "gn:feature_class":"P",
    "gn:feature_code":"PPL",
    "gn:name":"Yangmaocun",
    "gn:population":0,
    "gn:timezone":"Asia/Shanghai",
    "iso:country":"CN",
    "name:zho_x_preferred":[
        "\u6768\u8302\u6751"
    ],
    "wof:name":"Yangmaocun",
    "wof:placetype":"locality"
},
  "geometry": {"coordinates":[125.72693999999998,44.97141],"type":"Point"}
}