{
  "type": "Feature",
  "properties": {
    "gn:admin1_code":"32.0",
    "gn:asciiname":"Shaguo Pingzi",
    "gn:country_code":"CN",
    "gn:dem":1545,
    "gn:feature_class":"P",
    "gn:feature_code":"PPL",
    "gn:name":"Shaguo Pingzi",
    "gn:population":0,
    "gn:timezone":"Asia/Shanghai",
    "iso:country":"CN",
    "name:zho_x_preferred":[
        "\u6c99\u9505\u576a\u5b50"
    ],
    "wof:name":"Shaguo Pingzi",
    "wof:placetype":"locality"
},
  "geometry": {"coordinates":[102.88467,27.38516],"type":"Point"}
}