{
  "type": "Feature",
  "properties": {
    "gn:admin1_code":"33",
    "gn:asciiname":"Shizitan",
    "gn:cc2":"CN",
    "gn:country_code":"CN",
    "gn:dem":338,
    "gn:feature_class":"P",
    "gn:feature_code":"PPL",
    "gn:name":"Shizitan",
    "gn:population":0,
    "gn:timezone":"Asia/Shanghai",
    "iso:country":"CN",
    "name:und_x_variant":[
        "Shih-tzu-t\u2019an",
        "Shizitan"
    ],
    "wof:name":"Shizitan",
    "wof:placetype":"locality"
},
  "geometry": {"coordinates":[107.16667,29.93333],"type":"Point"}
}