{
  "type": "Feature",
  "properties": {
    "gn:admin1_code":"32.0",
    "gn:asciiname":"Lannigou",
    "gn:country_code":"CN",
    "gn:dem":317,
    "gn:feature_class":"P",
    "gn:feature_code":"PPL",
    "gn:name":"Lannigou",
    "gn:population":0,
    "gn:timezone":"Asia/Shanghai",
    "iso:country":"CN",
    "name:zho_x_preferred":[
        "\u70c2\u6ce5\u6c9f"
    ],
    "wof:name":"Lannigou",
    "wof:placetype":"locality"
},
  "geometry": {"coordinates":[106.10899999999999,30.8963],"type":"Point"}
}