{
  "type": "Feature",
  "properties": {
    "gn:admin1_code":"11.0",
    "gn:asciiname":"Kedengwei",
    "gn:country_code":"CN",
    "gn:dem":640,
    "gn:feature_class":"P",
    "gn:feature_code":"PPL",
    "gn:name":"Kedengwei",
    "gn:population":0,
    "gn:timezone":"Asia/Shanghai",
    "iso:country":"CN",
    "name:zho_x_preferred":[
        "\u514b\u7b49\u4f4d"
    ],
    "wof:name":"Kedengwei",
    "wof:placetype":"locality"
},
  "geometry": {"coordinates":[109.38891,29.24397],"type":"Point"}
}