{
  "type": "Feature",
  "properties": {
    "gn:admin1_code":"04",
    "gn:asciiname":"Sung-chia-t'ou-chen",
    "gn:country_code":"CN",
    "gn:dem":7,
    "gn:feature_class":"P",
    "gn:feature_code":"PPL",
    "gn:name":"Sung-chia-t\u2019ou-chen",
    "gn:population":0,
    "gn:timezone":"Asia/Shanghai",
    "iso:country":"CN",
    "wof:name":"Sung-chia-t'ou-chen",
    "wof:placetype":"locality"
},
  "geometry": {"coordinates":[120.09721999999999,31.66028],"type":"Point"}
}