{
  "type": "Feature",
  "properties": {
    "gn:admin1_code":"19.0",
    "gn:asciiname":"Weizigou",
    "gn:country_code":"CN",
    "gn:dem":46,
    "gn:feature_class":"P",
    "gn:feature_code":"PPL",
    "gn:name":"Weizigou",
    "gn:population":0,
    "gn:timezone":"Asia/Shanghai",
    "iso:country":"CN",
    "name:und_x_variant":[
        "\u82c7\u5b50\u6c9f"
    ],
    "wof:name":"Weizigou",
    "wof:placetype":"locality"
},
  "geometry": {"coordinates":[122.57773,40.59107],"type":"Point"}
}