{
  "type": "Feature",
  "properties": {
    "gn:admin1_code":"32.0",
    "gn:asciiname":"Guanlong",
    "gn:country_code":"CN",
    "gn:dem":353,
    "gn:feature_class":"P",
    "gn:feature_code":"PPL",
    "gn:name":"Guanlong",
    "gn:population":0,
    "gn:timezone":"Asia/Shanghai",
    "iso:country":"CN",
    "name:cat_x_preferred":[
        "Guanlong wucaii"
    ],
    "name:ces_x_preferred":[
        "Guanlong"
    ],
    "name:deu_x_preferred":[
        "Guanlong"
    ],
    "name:fas_x_preferred":[
        "\u06af\u0648\u0627\u0646\u0644\u0627\u0646\u06af"
    ],
    "name:fin_x_preferred":[
        "Guanlong"
    ],
    "name:fra_x_preferred":[
        "Guanlong"
    ],
    "name:heb_x_preferred":[
        "\u05d2\u05d5\u05d0\u05dc\u05d5\u05e0\u05d2"
    ],
    "name:hun_x_preferred":[
        "Guanlong"
    ],
    "name:ita_x_preferred":[
        "Guanlong wucaii"
    ],
    "name:jpn_x_preferred":[
        "\u30b0\u30a2\u30f3\u30ed\u30f3"
    ],
    "name:kor_x_preferred":[
        "\uad6c\uc548\ub871"
    ],
    "name:mal_x_preferred":[
        "\u0d17\u0d4d\u0d35\u0d3e\u0d7b\u0d32\u0d4b\u0d19\u0d4d"
    ],
    "name:nld_x_preferred":[
        "Guanlong"
    ],
    "name:ori_x_preferred":[
        "Guanlong"
    ],
    "name:pol_x_preferred":[
        "Guanlong"
    ],
    "name:por_x_preferred":[
        "Guanlong"
    ],
    "name:rus_x_preferred":[
        "\u0413\u0443\u0430\u043d\u044c\u043b\u0443\u043d"
    ],
    "name:slk_x_preferred":[
        "Guanlong"
    ],
    "name:spa_x_preferred":[
        "Guanlong wucaii"
    ],
    "name:swe_x_preferred":[
        "Guanlong"
    ],
    "name:ukr_x_preferred":[
        "\u0413\u0443\u0430\u043d\u044c\u043b\u0443\u043d"
    ],
    "name:vie_x_preferred":[
        "Guanlong"
    ],
    "name:zho_x_preferred":[
        "\u89c2\u9f99"
    ],
    "name:zho_x_variant":[
        "\u4e94\u5f69\u51a0\u9f8d"
    ],
    "wof:name":"Guanlong",
    "wof:placetype":"locality"
},
  "geometry": {"coordinates":[106.74760999999999,30.82598],"type":"Point"}
}