{
  "type": "Feature",
  "properties": {
    "gn:admin1_code":"10.0",
    "gn:asciiname":"Dashengzhuang",
    "gn:country_code":"CN",
    "gn:dem":13,
    "gn:feature_class":"P",
    "gn:feature_code":"PPL",
    "gn:name":"Dashengzhuang",
    "gn:population":0,
    "gn:timezone":"Asia/Shanghai",
    "iso:country":"CN",
    "name:zho_x_preferred":[
        "\u5927\u751f\u5e84"
    ],
    "wof:name":"Dashengzhuang",
    "wof:placetype":"locality"
},
  "geometry": {"coordinates":[116.69352000000001,37.91964],"type":"Point"}
}