{
  "type": "Feature",
  "properties": {
    "gn:admin1_code":"29.0",
    "gn:asciiname":"Yixichong",
    "gn:country_code":"CN",
    "gn:dem":1832,
    "gn:feature_class":"P",
    "gn:feature_code":"PPL",
    "gn:name":"Yixichong",
    "gn:population":0,
    "gn:timezone":"Asia/Shanghai",
    "iso:country":"CN",
    "name:zho_x_preferred":[
        "\u8fe4\u897f\u51b2"
    ],
    "wof:name":"Yixichong",
    "wof:placetype":"locality"
},
  "geometry": {"coordinates":[101.611,25.329],"type":"Point"}
}