{
  "type": "Feature",
  "properties": {
    "gn:admin1_code":"30.0",
    "gn:asciiname":"Wangqiancun",
    "gn:country_code":"CN",
    "gn:dem":13,
    "gn:feature_class":"P",
    "gn:feature_code":"PPL",
    "gn:name":"Wangqiancun",
    "gn:population":0,
    "gn:timezone":"Asia/Shanghai",
    "iso:country":"CN",
    "name:zho_x_preferred":[
        "\u671b\u524d\u6751"
    ],
    "wof:name":"Wangqiancun",
    "wof:placetype":"locality"
},
  "geometry": {"coordinates":[116.53874,23.09901],"type":"Point"}
}