{
  "type": "Feature",
  "properties": {
    "gn:admin1_code":"29.0",
    "gn:asciiname":"Fuyan Shangzhai",
    "gn:country_code":"CN",
    "gn:dem":1596,
    "gn:feature_class":"P",
    "gn:feature_code":"PPL",
    "gn:name":"Fuyan Shangzhai",
    "gn:population":0,
    "gn:timezone":"Asia/Shanghai",
    "iso:country":"CN",
    "name:zho_x_preferred":[
        "\u5bcc\u5ca9\u4e0a\u5be8"
    ],
    "wof:name":"Fuyan Shangzhai",
    "wof:placetype":"locality"
},
  "geometry": {"coordinates":[99.52160000000001,22.4639],"type":"Point"}
}