{
  "type": "Feature",
  "properties": {
    "gn:admin1_code":"02",
    "gn:asciiname":"Wangdianqiaocun",
    "gn:country_code":"CN",
    "gn:dem":7,
    "gn:feature_class":"P",
    "gn:feature_code":"PPL",
    "gn:name":"Wangdianqiaocun",
    "gn:population":0,
    "gn:timezone":"Asia/Shanghai",
    "iso:country":"CN",
    "name:und_x_variant":[
        "Wang-tien-ch\u2019iao",
        "Washan",
        "Wangdianqiao",
        "\u738b\u5e97\u6865",
        "Wangdianqiaocun"
    ],
    "name:zho_x_preferred":[
        "\u738b\u5e97\u6865\u6751"
    ],
    "wof:name":"Wangdianqiaocun",
    "wof:placetype":"locality"
},
  "geometry": {"coordinates":[121.06180000000001,30.61967000000001],"type":"Point"}
}