{
  "type": "Feature",
  "properties": {
    "gn:admin1_code":"4.0",
    "gn:asciiname":"Honghu Sizu",
    "gn:country_code":"CN",
    "gn:dem":14,
    "gn:feature_class":"P",
    "gn:feature_code":"PPLF",
    "gn:name":"Honghu Sizu",
    "gn:population":0,
    "gn:timezone":"Asia/Shanghai",
    "iso:country":"CN",
    "name:zho_x_preferred":[
        "\u6d2a\u6e56\u56db\u7ec4"
    ],
    "wof:name":"Honghu Sizu",
    "wof:placetype":"locality"
},
  "geometry": {"coordinates":[118.629,33.0896],"type":"Point"}
}