{
  "type": "Feature",
  "properties": {
    "gn:admin1_code":"1.0",
    "gn:asciiname":"Zhangkailoucun",
    "gn:country_code":"CN",
    "gn:dem":37,
    "gn:feature_class":"P",
    "gn:feature_code":"PPL",
    "gn:name":"Zhangkailoucun",
    "gn:population":0,
    "gn:timezone":"Asia/Shanghai",
    "iso:country":"CN",
    "name:zho_x_preferred":[
        "\u5f20\u5f00\u697c\u6751"
    ],
    "wof:name":"Zhangkailoucun",
    "wof:placetype":"locality"
},
  "geometry": {"coordinates":[115.38612000000001,32.62407],"type":"Point"}
}