{
  "type": "Feature",
  "properties": {
    "gn:admin1_code":"26.0",
    "gn:asciiname":"Houzhitoucun",
    "gn:country_code":"CN",
    "gn:dem":1006,
    "gn:feature_class":"P",
    "gn:feature_code":"PPL",
    "gn:name":"Houzhitoucun",
    "gn:population":0,
    "gn:timezone":"Asia/Shanghai",
    "iso:country":"CN",
    "name:zho_x_preferred":[
        "\u540e\u65e8\u5934\u6751"
    ],
    "wof:name":"Houzhitoucun",
    "wof:placetype":"locality"
},
  "geometry": {"coordinates":[108.56699,34.85666],"type":"Point"}
}