{
  "type": "Feature",
  "properties": {
    "gn:admin1_code":"4.0",
    "gn:asciiname":"Qiaokou",
    "gn:country_code":"CN",
    "gn:dem":13,
    "gn:feature_class":"P",
    "gn:feature_code":"PPL",
    "gn:name":"Qiaokou",
    "gn:population":0,
    "gn:timezone":"Asia/Shanghai",
    "iso:country":"CN",
    "name:zho_x_preferred":[
        "Qiaokou"
    ],
    "name:zho_x_variant":[
        "\u6865\u53e3"
    ],
    "wof:name":"Qiaokou",
    "wof:placetype":"locality"
},
  "geometry": {"coordinates":[119.12175000000001,33.68028],"type":"Point"}
}