{
  "type": "Feature",
  "properties": {
    "gn:admin1_code":"4.0",
    "gn:asciiname":"Yapucun",
    "gn:country_code":"CN",
    "gn:dem":8,
    "gn:feature_class":"P",
    "gn:feature_code":"PPL",
    "gn:name":"Yapucun",
    "gn:population":0,
    "gn:timezone":"Asia/Shanghai",
    "iso:country":"CN",
    "name:und_x_variant":[
        "\u96c5\u6d66\u6751"
    ],
    "name:zho_x_preferred":[
        "\u96c5\u6d66\u6751"
    ],
    "wof:name":"Yapucun",
    "wof:placetype":"locality"
},
  "geometry": {"coordinates":[120.08392000000001,31.47528],"type":"Point"}
}