{
  "type": "Feature",
  "properties": {
    "gn:admin1_code":"12.0",
    "gn:asciiname":"Houshan",
    "gn:country_code":"CN",
    "gn:dem":541,
    "gn:feature_class":"P",
    "gn:feature_code":"PPL",
    "gn:name":"Houshan",
    "gn:population":0,
    "gn:timezone":"Asia/Shanghai",
    "iso:country":"CN",
    "name:zho_x_preferred":[
        "Houshan"
    ],
    "name:zho_x_variant":[
        "\u540e\u5c71"
    ],
    "wof:name":"Houshan",
    "wof:placetype":"locality"
},
  "geometry": {"coordinates":[111.06031000000002,30.71394],"type":"Point"}
}