{
  "type": "Feature",
  "properties": {
    "gn:admin1_code":"18.0",
    "gn:asciiname":"Dachangtian",
    "gn:country_code":"CN",
    "gn:dem":1315,
    "gn:feature_class":"P",
    "gn:feature_code":"PPL",
    "gn:name":"Dachangtian",
    "gn:population":0,
    "gn:timezone":"Asia/Shanghai",
    "iso:country":"CN",
    "wof:name":"Dachangtian",
    "wof:placetype":"locality"
},
  "geometry": {"coordinates":[105.56667,25.575],"type":"Point"}
}