{
  "type": "Feature",
  "properties": {
    "gn:admin1_code":"29.0",
    "gn:asciiname":"Lisida",
    "gn:country_code":"CN",
    "gn:dem":1881,
    "gn:feature_class":"P",
    "gn:feature_code":"PPL",
    "gn:name":"Lisida",
    "gn:population":0,
    "gn:timezone":"Asia/Shanghai",
    "iso:country":"CN",
    "name:zho_x_preferred":[
        "\u7acb\u65af\u8fbe"
    ],
    "wof:name":"Lisida",
    "wof:placetype":"locality"
},
  "geometry": {"coordinates":[99.5146,24.8886],"type":"Point"}
}