{
  "type": "Feature",
  "properties": {
    "gn:admin1_code":"18",
    "gn:asciiname":"Guanglaba",
    "gn:country_code":"CN",
    "gn:dem":917,
    "gn:feature_class":"P",
    "gn:feature_code":"PPL",
    "gn:name":"Guanglaba",
    "gn:population":0,
    "gn:timezone":"Asia/Shanghai",
    "iso:country":"CN",
    "name:zho_x_preferred":[
        "\u5149\u814a\u575d"
    ],
    "wof:name":"Guanglaba",
    "wof:placetype":"locality"
},
  "geometry": {"coordinates":[106.845,27.2686],"type":"Point"}
}