{
  "type": "Feature",
  "properties": {
    "gn:admin1_code":"4.0",
    "gn:asciiname":"Yaoduo",
    "gn:country_code":"CN",
    "gn:dem":6,
    "gn:feature_class":"P",
    "gn:feature_code":"PPL",
    "gn:name":"Yaoduo",
    "gn:population":0,
    "gn:timezone":"Asia/Shanghai",
    "iso:country":"CN",
    "name:und_x_variant":[
        "\u7a91\u579b"
    ],
    "name:zho_x_preferred":[
        "\u7a91\u579b"
    ],
    "wof:name":"Yaoduo",
    "wof:placetype":"locality"
},
  "geometry": {"coordinates":[120.38630000000001,32.46028],"type":"Point"}
}