{
  "type": "Feature",
  "properties": {
    "gn:admin1_code":"9",
    "gn:asciiname":"Xizhaolou",
    "gn:country_code":"CN",
    "gn:dem":52,
    "gn:feature_class":"P",
    "gn:feature_code":"PPL",
    "gn:name":"Xizhaolou",
    "gn:population":0,
    "gn:timezone":"Asia/Shanghai",
    "iso:country":"CN",
    "name:zho_x_preferred":[
        "\u897f\u8d75\u697c"
    ],
    "wof:name":"Xizhaolou",
    "wof:placetype":"locality"
},
  "geometry": {"coordinates":[115.133,34.0384],"type":"Point"}
}