{
  "type": "Feature",
  "properties": {
    "gn:admin1_code":"1.0",
    "gn:asciiname":"Damuqiaocun",
    "gn:country_code":"CN",
    "gn:dem":39,
    "gn:feature_class":"P",
    "gn:feature_code":"PPL",
    "gn:name":"Damuqiaocun",
    "gn:population":0,
    "gn:timezone":"Asia/Shanghai",
    "iso:country":"CN",
    "name:und_x_variant":[
        "Damuqiao"
    ],
    "name:zho_x_preferred":[
        "\u5927\u6728\u6865\u6751"
    ],
    "wof:name":"Damuqiaocun",
    "wof:placetype":"locality"
},
  "geometry": {"coordinates":[117.38172,32.44073],"type":"Point"}
}