{
  "type": "Feature",
  "properties": {
    "gn:admin1_code":"32.0",
    "gn:asciiname":"Shanwangmiao",
    "gn:country_code":"CN",
    "gn:dem":423,
    "gn:feature_class":"P",
    "gn:feature_code":"PPL",
    "gn:name":"Shanwangmiao",
    "gn:population":0,
    "gn:timezone":"Asia/Shanghai",
    "iso:country":"CN",
    "name:zho_x_preferred":[
        "\u5c71\u738b\u5e99"
    ],
    "wof:name":"Shanwangmiao",
    "wof:placetype":"locality"
},
  "geometry": {"coordinates":[104.86199999999999,30.3429],"type":"Point"}
}