{
  "type": "Feature",
  "properties": {
    "gn:admin1_code":"3.0",
    "gn:asciiname":"Baiguo",
    "gn:country_code":"CN",
    "gn:dem":47,
    "gn:feature_class":"P",
    "gn:feature_code":"PPL",
    "gn:name":"Baiguo",
    "gn:population":0,
    "gn:timezone":"Asia/Shanghai",
    "iso:country":"CN",
    "name:und_x_variant":[
        "\u767d\u679c"
    ],
    "wof:name":"Baiguo",
    "wof:placetype":"locality"
},
  "geometry": {"coordinates":[116.79425000000001,29.53114],"type":"Point"}
}