{
  "type": "Feature",
  "properties": {
    "gn:admin1_code":"3.0",
    "gn:asciiname":"Xitou",
    "gn:country_code":"CN",
    "gn:dem":175,
    "gn:feature_class":"P",
    "gn:feature_code":"PPL",
    "gn:name":"Xitou",
    "gn:population":0,
    "gn:timezone":"Asia/Shanghai",
    "iso:country":"CN",
    "name:deu_x_preferred":[
        "Xitou"
    ],
    "name:und_x_variant":[
        "Hsi-t\u2019ou"
    ],
    "name:zho_x_preferred":[
        "\u897f\u5934"
    ],
    "wof:name":"Xitou",
    "wof:placetype":"locality"
},
  "geometry": {"coordinates":[115.143,28.9124],"type":"Point"}
}