{
  "type": "Feature",
  "properties": {
    "gn:admin1_code":"22.0",
    "gn:asciiname":"Baipenyaocun",
    "gn:country_code":"CN",
    "gn:dem":51,
    "gn:feature_class":"P",
    "gn:feature_code":"PPL",
    "gn:name":"Baipenyaocun",
    "gn:population":0,
    "gn:timezone":"Asia/Shanghai",
    "iso:country":"CN",
    "name:zho_x_preferred":[
        "\u767d\u76c6\u7a91\u6751"
    ],
    "wof:name":"Baipenyaocun",
    "wof:placetype":"locality"
},
  "geometry": {"coordinates":[116.31698,39.81505],"type":"Point"}
}