{
  "type": "Feature",
  "properties": {
    "gn:admin1_code":"19.0",
    "gn:asciiname":"Sujia Wopeng",
    "gn:country_code":"CN",
    "gn:dem":11,
    "gn:feature_class":"P",
    "gn:feature_code":"PPL",
    "gn:name":"Sujia Wopeng",
    "gn:population":0,
    "gn:timezone":"Asia/Shanghai",
    "iso:country":"CN",
    "name:zho_x_preferred":[
        "\u82cf\u5bb6\u7a9d\u68da"
    ],
    "wof:name":"Sujia Wopeng",
    "wof:placetype":"locality"
},
  "geometry": {"coordinates":[122.69466,41.28446],"type":"Point"}
}