{
  "type": "Feature",
  "properties": {
    "gn:admin1_code":"30.0",
    "gn:asciiname":"Hetangwei",
    "gn:country_code":"CN",
    "gn:dem":12,
    "gn:feature_class":"P",
    "gn:feature_code":"PPL",
    "gn:name":"Hetangwei",
    "gn:population":0,
    "gn:timezone":"Asia/Shanghai",
    "iso:country":"CN",
    "name:zho_x_preferred":[
        "\u8377\u5858\u56f4"
    ],
    "wof:name":"Hetangwei",
    "wof:placetype":"locality"
},
  "geometry": {"coordinates":[114.30398999999998,23.15602],"type":"Point"}
}