{
  "type": "Feature",
  "properties": {
    "gn:admin1_code":"14.0",
    "gn:asciiname":"Mujiezhong",
    "gn:country_code":"CN",
    "gn:dem":3858,
    "gn:feature_class":"P",
    "gn:feature_code":"PPL",
    "gn:name":"Mujiezhong",
    "gn:population":0,
    "gn:timezone":"Asia/Urumqi",
    "iso:country":"CN",
    "name:zho_x_preferred":[
        "\u6728\u6770\u79cd"
    ],
    "wof:name":"Mujiezhong",
    "wof:placetype":"locality"
},
  "geometry": {"coordinates":[98.68465,30.13305],"type":"Point"}
}