{
  "type": "Feature",
  "properties": {
    "gn:admin1_code":"26.0",
    "gn:asciiname":"Zhucaogou",
    "gn:country_code":"CN",
    "gn:dem":1019,
    "gn:feature_class":"P",
    "gn:feature_code":"PPL",
    "gn:name":"Zhucaogou",
    "gn:population":0,
    "gn:timezone":"Asia/Shanghai",
    "iso:country":"CN",
    "name:zho_x_preferred":[
        "\u732a\u69fd\u6c9f"
    ],
    "wof:name":"Zhucaogou",
    "wof:placetype":"locality"
},
  "geometry": {"coordinates":[110.32225,33.58555],"type":"Point"}
}