{
  "type": "Feature",
  "properties": {
    "gn:admin1_code":"14.0",
    "gn:asciiname":"Quwa",
    "gn:country_code":"CN",
    "gn:dem":4316,
    "gn:feature_class":"P",
    "gn:feature_code":"PPL",
    "gn:name":"Quwa",
    "gn:population":0,
    "gn:timezone":"Asia/Urumqi",
    "iso:country":"CN",
    "name:zho_x_preferred":[
        "\u66f2\u74e6"
    ],
    "wof:name":"Quwa",
    "wof:placetype":"locality"
},
  "geometry": {"coordinates":[87.9486,28.617],"type":"Point"}
}