{
  "type": "Feature",
  "properties": {
    "gn:admin1_code":"1.0",
    "gn:asciiname":"Lianggoucun",
    "gn:country_code":"CN",
    "gn:dem":31,
    "gn:feature_class":"P",
    "gn:feature_code":"PPL",
    "gn:name":"Lianggoucun",
    "gn:population":0,
    "gn:timezone":"Asia/Shanghai",
    "iso:country":"CN",
    "name:zho_x_preferred":[
        "\u6881\u6c9f\u6751"
    ],
    "wof:name":"Lianggoucun",
    "wof:placetype":"locality"
},
  "geometry": {"coordinates":[116.33193,33.20504],"type":"Point"}
}