{
  "type": "Feature",
  "properties": {
    "gn:admin1_code":"29.0",
    "gn:asciiname":"Longdonghe",
    "gn:country_code":"CN",
    "gn:dem":2459,
    "gn:feature_class":"P",
    "gn:feature_code":"PPL",
    "gn:name":"Longdonghe",
    "gn:population":0,
    "gn:timezone":"Asia/Shanghai",
    "iso:country":"CN",
    "name:zho_x_preferred":[
        "\u9f99\u6d1e\u6cb3"
    ],
    "wof:name":"Longdonghe",
    "wof:placetype":"locality"
},
  "geometry": {"coordinates":[100.518,27.6591],"type":"Point"}
}