{
  "type": "Feature",
  "properties": {
    "gn:admin1_code":"30.0",
    "gn:asciiname":"Qianhucun",
    "gn:country_code":"CN",
    "gn:dem":60,
    "gn:feature_class":"P",
    "gn:feature_code":"PPL",
    "gn:name":"Qianhucun",
    "gn:population":0,
    "gn:timezone":"Asia/Shanghai",
    "iso:country":"CN",
    "name:zho_x_preferred":[
        "\u524d\u6e56\u6751"
    ],
    "wof:name":"Qianhucun",
    "wof:placetype":"locality"
},
  "geometry": {"coordinates":[116.37045000000001,23.00894],"type":"Point"}
}