{
  "type": "Feature",
  "properties": {
    "gn:admin1_code":"8.0",
    "gn:asciiname":"Zhenbei",
    "gn:country_code":"CN",
    "gn:dem":116,
    "gn:feature_class":"P",
    "gn:feature_code":"PPL",
    "gn:name":"Zhenbei",
    "gn:population":0,
    "gn:timezone":"Asia/Shanghai",
    "iso:country":"CN",
    "name:zho_x_preferred":[
        "\u9547\u5317"
    ],
    "wof:name":"Zhenbei",
    "wof:placetype":"locality"
},
  "geometry": {"coordinates":[128.04266000000001,45.96911],"type":"Point"}
}