{
  "type": "Feature",
  "properties": {
    "gn:admin1_code":"18",
    "gn:asciiname":"Huazuo",
    "gn:country_code":"CN",
    "gn:dem":1347,
    "gn:feature_class":"P",
    "gn:feature_code":"PPL",
    "gn:name":"Huazuo",
    "gn:population":0,
    "gn:timezone":"Asia/Shanghai",
    "iso:country":"CN",
    "name:zho_x_preferred":[
        "\u5316\u4f5c"
    ],
    "wof:name":"Huazuo",
    "wof:placetype":"locality"
},
  "geometry": {"coordinates":[105.65900000000001,26.4621],"type":"Point"}
}