{
  "type": "Feature",
  "properties": {
    "gn:admin1_code":"26.0",
    "gn:asciiname":"Geqiuhecun",
    "gn:country_code":"CN",
    "gn:dem":1197,
    "gn:feature_class":"P",
    "gn:feature_code":"PPL",
    "gn:name":"Geqiuhecun",
    "gn:population":0,
    "gn:timezone":"Asia/Shanghai",
    "iso:country":"CN",
    "name:zho_x_preferred":[
        "\u572a\u6c42\u6cb3\u6751"
    ],
    "wof:name":"Geqiuhecun",
    "wof:placetype":"locality"
},
  "geometry": {"coordinates":[109.55687,38.61538],"type":"Point"}
}