{
  "type": "Feature",
  "properties": {
    "gn:admin1_code":"26.0",
    "gn:asciiname":"Bajiabucun",
    "gn:country_code":"CN",
    "gn:dem":370,
    "gn:feature_class":"P",
    "gn:feature_code":"PPL",
    "gn:name":"Bajiabucun",
    "gn:population":0,
    "gn:timezone":"Asia/Shanghai",
    "iso:country":"CN",
    "name:zho_x_preferred":[
        "\u516b\u5bb6\u5821\u6751"
    ],
    "wof:name":"Bajiabucun",
    "wof:placetype":"locality"
},
  "geometry": {"coordinates":[108.99211,34.39836],"type":"Point"}
}