{
  "type": "Feature",
  "properties": {
    "gn:admin1_code":"14.0",
    "gn:asciiname":"Jieguidang",
    "gn:country_code":"CN",
    "gn:dem":4080,
    "gn:feature_class":"P",
    "gn:feature_code":"PPL",
    "gn:name":"Jieguidang",
    "gn:population":0,
    "gn:timezone":"Asia/Urumqi",
    "iso:country":"CN",
    "name:zho_x_preferred":[
        "\u754c\u5f52\u515a"
    ],
    "wof:name":"Jieguidang",
    "wof:placetype":"locality"
},
  "geometry": {"coordinates":[92.59343,28.44846],"type":"Point"}
}