{
  "type": "Feature",
  "properties": {
    "gn:admin1_code":"19.0",
    "gn:asciiname":"Tiebei",
    "gn:country_code":"CN",
    "gn:dem":51,
    "gn:feature_class":"P",
    "gn:feature_code":"PPL",
    "gn:name":"Tiebei",
    "gn:population":0,
    "gn:timezone":"Asia/Shanghai",
    "iso:country":"CN",
    "name:und_x_variant":[
        "\u94c1\u5317"
    ],
    "name:zho_x_preferred":[
        "\u94c1\u5317"
    ],
    "wof:name":"Tiebei",
    "wof:placetype":"locality"
},
  "geometry": {"coordinates":[122.35899999999999,42.0618],"type":"Point"}
}