{
  "type": "Feature",
  "properties": {
    "gn:admin1_code":"02",
    "gn:asciiname":"Shadi",
    "gn:cc2":"CN",
    "gn:country_code":"CN",
    "gn:dem":60,
    "gn:feature_class":"P",
    "gn:feature_code":"PPL",
    "gn:name":"Shadi",
    "gn:population":0,
    "gn:timezone":"Asia/Shanghai",
    "iso:country":"CN",
    "name:und_x_variant":[
        "Sha-ti",
        "Shadi"
    ],
    "wof:name":"Shadi",
    "wof:placetype":"locality"
},
  "geometry": {"coordinates":[121.36083000000001,29.40889],"type":"Point"}
}