{
  "type": "Feature",
  "properties": {
    "gn:admin1_code":"2.0",
    "gn:asciiname":"Zhutang",
    "gn:country_code":"CN",
    "gn:dem":44,
    "gn:feature_class":"P",
    "gn:feature_code":"PPL",
    "gn:name":"Zhutang",
    "gn:population":0,
    "gn:timezone":"Asia/Shanghai",
    "iso:country":"CN",
    "name:und_x_variant":[
        "\u7af9\u5858",
        "Zhutang"
    ],
    "wof:name":"Zhutang",
    "wof:placetype":"locality"
},
  "geometry": {"coordinates":[119.44109,29.27362],"type":"Point"}
}