{
  "type": "Feature",
  "properties": {
    "gn:admin1_code":"23.0",
    "gn:asciiname":"Shijianong",
    "gn:country_code":"CN",
    "gn:dem":5,
    "gn:feature_class":"P",
    "gn:feature_code":"PPL",
    "gn:name":"Shijianong",
    "gn:population":0,
    "gn:timezone":"Asia/Shanghai",
    "iso:country":"CN",
    "name:zho_x_preferred":[
        "Shijianong"
    ],
    "name:zho_x_variant":[
        "\u77f3\u5bb6\u5f04"
    ],
    "wof:name":"Shijianong",
    "wof:placetype":"locality"
},
  "geometry": {"coordinates":[121.41807,31.11874000000001],"type":"Point"}
}