{
  "type": "Feature",
  "properties": {
    "gn:admin1_code":"3.0",
    "gn:asciiname":"Yangping",
    "gn:country_code":"CN",
    "gn:dem":493,
    "gn:feature_class":"P",
    "gn:feature_code":"PPL",
    "gn:name":"Yangping",
    "gn:population":0,
    "gn:timezone":"Asia/Shanghai",
    "iso:country":"CN",
    "name:ceb_x_preferred":[
        "Yangping"
    ],
    "name:swe_x_preferred":[
        "Yangping"
    ],
    "name:und_x_variant":[
        "\u79e7\u576a"
    ],
    "wof:name":"Yangping",
    "wof:placetype":"locality"
},
  "geometry": {"coordinates":[116.05046000000002,27.4368],"type":"Point"}
}