{
  "type": "Feature",
  "properties": {
    "gn:admin1_code":"11",
    "gn:asciiname":"Jiaoqi",
    "gn:country_code":"CN",
    "gn:dem":38,
    "gn:feature_class":"P",
    "gn:feature_code":"PPLA4",
    "gn:name":"Jiaoqi",
    "gn:population":0,
    "gn:timezone":"Asia/Shanghai",
    "iso:country":"CN",
    "name:und_x_variant":[
        "\u7126\u573b",
        "Jiaoqi Zhen",
        "\u7126\u573b\u9547"
    ],
    "wof:name":"Jiaoqi",
    "wof:placetype":"locality"
},
  "geometry": {"coordinates":[112.08196,29.64833],"type":"Point"}
}