{
  "type": "Feature",
  "properties": {
    "gn:admin1_code":"24.0",
    "gn:asciiname":"Gelaozhang",
    "gn:country_code":"CN",
    "gn:dem":1576,
    "gn:feature_class":"P",
    "gn:feature_code":"PPL",
    "gn:name":"Gelaozhang",
    "gn:population":0,
    "gn:timezone":"Asia/Shanghai",
    "iso:country":"CN",
    "name:zho_x_preferred":[
        "\u9601\u8001\u638c"
    ],
    "wof:name":"Gelaozhang",
    "wof:placetype":"locality"
},
  "geometry": {"coordinates":[111.21577000000001,36.53777],"type":"Point"}
}