{
  "type": "Feature",
  "properties": {
    "gn:admin1_code":"30.0",
    "gn:asciiname":"Qingshi",
    "gn:country_code":"CN",
    "gn:dem":580,
    "gn:feature_class":"P",
    "gn:feature_code":"PPL",
    "gn:name":"Qingshi",
    "gn:population":0,
    "gn:timezone":"Asia/Shanghai",
    "iso:country":"CN",
    "name:zho_x_preferred":[
        "Qingshi"
    ],
    "name:zho_x_variant":[
        "\u9752\u77f3"
    ],
    "wof:name":"Qingshi",
    "wof:placetype":"locality"
},
  "geometry": {"coordinates":[113.25207,25.01902],"type":"Point"}
}