{
  "type": "Feature",
  "properties": {
    "gn:admin1_code":"10",
    "gn:asciiname":"Houshageta",
    "gn:country_code":"CN",
    "gn:dem":47,
    "gn:feature_class":"P",
    "gn:feature_code":"PPL",
    "gn:name":"Houshageta",
    "gn:population":0,
    "gn:timezone":"Asia/Shanghai",
    "iso:country":"CN",
    "name:und_x_variant":[
        "Housha"
    ],
    "name:zho_x_preferred":[
        "\u540e\u6c99\u572a\u5854"
    ],
    "name:zho_x_variant":[
        "\u540e\u6c99"
    ],
    "wof:name":"Houshageta",
    "wof:placetype":"locality"
},
  "geometry": {"coordinates":[115.12143,36.47902],"type":"Point"}
}