{
  "type": "Feature",
  "properties": {
    "gn:admin1_code":"1.0",
    "gn:asciiname":"Nanzhaocun",
    "gn:country_code":"CN",
    "gn:dem":67,
    "gn:feature_class":"P",
    "gn:feature_code":"PPL",
    "gn:name":"Nanzhaocun",
    "gn:population":0,
    "gn:timezone":"Asia/Shanghai",
    "iso:country":"CN",
    "name:zho_x_preferred":[
        "\u5357\u8d75\u6751"
    ],
    "wof:name":"Nanzhaocun",
    "wof:placetype":"locality"
},
  "geometry": {"coordinates":[117.65644,32.17745],"type":"Point"}
}