{
  "type": "Feature",
  "properties": {
    "gn:admin1_code":"7.0",
    "gn:asciiname":"Xinxicun",
    "gn:country_code":"CN",
    "gn:dem":313,
    "gn:feature_class":"P",
    "gn:feature_code":"PPL",
    "gn:name":"Xinxicun",
    "gn:population":0,
    "gn:timezone":"Asia/Shanghai",
    "iso:country":"CN",
    "name:zho_x_preferred":[
        "\u65b0\u897f\u6751"
    ],
    "wof:name":"Xinxicun",
    "wof:placetype":"locality"
},
  "geometry": {"coordinates":[117.12093,25.70719],"type":"Point"}
}