{
  "type": "Feature",
  "properties": {
    "gn:admin1_code":"7",
    "gn:asciiname":"Menqianyang",
    "gn:country_code":"CN",
    "gn:dem":388,
    "gn:feature_class":"P",
    "gn:feature_code":"PPL",
    "gn:name":"Menqianyang",
    "gn:population":0,
    "gn:timezone":"Asia/Shanghai",
    "iso:country":"CN",
    "name:zho_x_preferred":[
        "\u95e8\u524d\u6d0b"
    ],
    "wof:name":"Menqianyang",
    "wof:placetype":"locality"
},
  "geometry": {"coordinates":[118.5975,25.97694],"type":"Point"}
}