{
  "type": "Feature",
  "properties": {
    "gn:admin1_code":"14.0",
    "gn:asciiname":"Buling",
    "gn:country_code":"CN",
    "gn:dem":4638,
    "gn:feature_class":"P",
    "gn:feature_code":"PPL",
    "gn:name":"Buling",
    "gn:population":0,
    "gn:timezone":"Asia/Shanghai",
    "iso:country":"CN",
    "name:bod_x_preferred":[
        "Buling"
    ],
    "name:zho_x_preferred":[
        "Bolin"
    ],
    "name:zho_x_variant":[
        "\u6ce2\u6797"
    ],
    "wof:name":"Buling",
    "wof:placetype":"locality"
},
  "geometry": {"coordinates":[79.501,31.3279],"type":"Point"}
}