{
  "type": "Feature",
  "properties": {
    "gn:admin1_code":"25",
    "gn:asciiname":"Baishizhuang",
    "gn:country_code":"CN",
    "gn:dem":228,
    "gn:feature_class":"P",
    "gn:feature_code":"PPL",
    "gn:name":"Baishizhuang",
    "gn:population":0,
    "gn:timezone":"Asia/Shanghai",
    "iso:country":"CN",
    "name:zho_x_preferred":[
        "\u767d\u77f3\u5e84"
    ],
    "wof:name":"Baishizhuang",
    "wof:placetype":"locality"
},
  "geometry": {"coordinates":[117.45099999999999,35.4668],"type":"Point"}
}