{
  "type": "Feature",
  "properties": {
    "gn:admin1_code":"2.0",
    "gn:asciiname":"Nizhai",
    "gn:country_code":"CN",
    "gn:dem":93,
    "gn:feature_class":"P",
    "gn:feature_code":"PPL",
    "gn:name":"Nizhai",
    "gn:population":0,
    "gn:timezone":"Asia/Shanghai",
    "iso:country":"CN",
    "name:und_x_variant":[
        "\u502a\u5b85",
        "Nizhai"
    ],
    "wof:name":"Nizhai",
    "wof:placetype":"locality"
},
  "geometry": {"coordinates":[119.67708,29.37548],"type":"Point"}
}