{
  "type": "Feature",
  "properties": {
    "gn:admin1_code":"10",
    "gn:asciiname":"Houhuo Shiling",
    "gn:country_code":"CN",
    "gn:dem":535,
    "gn:feature_class":"P",
    "gn:feature_code":"PPL",
    "gn:name":"Houhuo Shiling",
    "gn:population":0,
    "gn:timezone":"Asia/Shanghai",
    "iso:country":"CN",
    "name:zho_x_preferred":[
        "\u540e\u706b\u77f3\u5cad"
    ],
    "wof:name":"Houhuo Shiling",
    "wof:placetype":"locality"
},
  "geometry": {"coordinates":[116.89952,40.78606],"type":"Point"}
}