{
  "type": "Feature",
  "properties": {
    "gn:admin1_code":"12.0",
    "gn:asciiname":"Lanqiangba",
    "gn:country_code":"CN",
    "gn:dem":1192,
    "gn:feature_class":"P",
    "gn:feature_code":"PPL",
    "gn:name":"Lanqiangba",
    "gn:population":0,
    "gn:timezone":"Asia/Shanghai",
    "iso:country":"CN",
    "name:zho_x_preferred":[
        "\u61d2\u5899\u575d"
    ],
    "wof:name":"Lanqiangba",
    "wof:placetype":"locality"
},
  "geometry": {"coordinates":[108.931,30.49579],"type":"Point"}
}