{
  "type": "Feature",
  "properties": {
    "gn:country":"CN",
    "gn:fcode":"ADM3",
    "gn:population":0,
    "iso:country":"CN",
    "name:und_x_variant":[
        "Shou-kuang Hsien"
    ],
    "name:zho_x_preferred":[
        "\u5bff\u5149\u5e02"
    ],
    "name:zho_x_variant":[
        "\u5bff\u5149"
    ],
    "qs:name":"Shouguang Shi",
    "qs:photos_9r":0,
    "qs:photos_sr":0,
    "qs:pop_sr":"0",
    "wof:name":"Shouguang Shi",
    "wof:placetype":"localadmin",
    "wof:population":0
},
  "geometry": {"coordinates":[118.85833,36.98389],"type":"Point"}
}