{
  "type": "Feature",
  "properties": {
    "gn:admin1_code":"3.0",
    "gn:asciiname":"Jiangxiamian",
    "gn:country_code":"CN",
    "gn:dem":165,
    "gn:feature_class":"P",
    "gn:feature_code":"PPL",
    "gn:name":"Jiangxiamian",
    "gn:population":0,
    "gn:timezone":"Asia/Shanghai",
    "iso:country":"CN",
    "name:und_x_variant":[
        "\u6c5f\u4e0b\u9762"
    ],
    "wof:name":"Jiangxiamian",
    "wof:placetype":"locality"
},
  "geometry": {"coordinates":[115.36225,26.37996],"type":"Point"}
}