{
  "type": "Feature",
  "properties": {
    "gn:admin1_code":"16",
    "gn:asciiname":"Shitang",
    "gn:country_code":"CN",
    "gn:dem":168,
    "gn:feature_class":"P",
    "gn:feature_code":"PPL",
    "gn:name":"Shitang",
    "gn:population":0,
    "gn:timezone":"Asia/Shanghai",
    "iso:country":"CN",
    "name:und_x_variant":[
        "Shih-t\u2019ang",
        "Shih-t\u2019ang-hs\u00fc",
        "Shitang"
    ],
    "name:zho_x_preferred":[
        "\u77f3\u5858"
    ],
    "wof:name":"Shitang",
    "wof:placetype":"locality"
},
  "geometry": {"coordinates":[108.03100000000001,23.6452],"type":"Point"}
}