{
  "type": "Feature",
  "properties": {
    "gn:admin1_code":"1.0",
    "gn:asciiname":"Chenguangcun",
    "gn:country_code":"CN",
    "gn:dem":25,
    "gn:feature_class":"P",
    "gn:feature_code":"PPL",
    "gn:name":"Chenguangcun",
    "gn:population":0,
    "gn:timezone":"Asia/Shanghai",
    "iso:country":"CN",
    "name:und_x_variant":[
        "Chenguang"
    ],
    "name:zho_x_preferred":[
        "\u6668\u5149\u6751"
    ],
    "wof:name":"Chenguangcun",
    "wof:placetype":"locality"
},
  "geometry": {"coordinates":[117.30804999999999,31.25199],"type":"Point"}
}