{
  "type": "Feature",
  "properties": {
    "gn:admin1_code":"25.0",
    "gn:asciiname":"Gaogezhuang",
    "gn:country_code":"CN",
    "gn:dem":100,
    "gn:feature_class":"P",
    "gn:feature_code":"PPL",
    "gn:name":"Gaogezhuang",
    "gn:population":0,
    "gn:timezone":"Asia/Shanghai",
    "iso:country":"CN",
    "name:zho_x_preferred":[
        "\u9ad8\u9601\u5e84"
    ],
    "name:zho_x_variant":[
        "\u9ad8\u683c\u5e84\u9547"
    ],
    "wof:name":"Gaogezhuang",
    "wof:placetype":"locality"
},
  "geometry": {"coordinates":[119.42726999999999,35.76009000000001],"type":"Point"}
}