{
  "type": "Feature",
  "properties": {
    "gn:admin1_code":"5",
    "gn:asciiname":"Beijituan",
    "gn:country_code":"CN",
    "gn:dem":565,
    "gn:feature_class":"P",
    "gn:feature_code":"PPL",
    "gn:name":"Beijituan",
    "gn:population":0,
    "gn:timezone":"Asia/Shanghai",
    "iso:country":"CN",
    "name:zho_x_preferred":[
        "\u5317\u96c6\u56e2"
    ],
    "wof:name":"Beijituan",
    "wof:placetype":"locality"
},
  "geometry": {"coordinates":[127.825,43.5812],"type":"Point"}
}