{
  "type": "Feature",
  "properties": {
    "gn:admin1_code":"29.0",
    "gn:asciiname":"Zhongyang",
    "gn:country_code":"CN",
    "gn:dem":2258,
    "gn:feature_class":"P",
    "gn:feature_code":"PPL",
    "gn:name":"Zhongyang",
    "gn:population":0,
    "gn:timezone":"Asia/Shanghai",
    "iso:country":"CN",
    "name:zho_x_preferred":[
        "\u4e2d\u7f8a"
    ],
    "wof:name":"Zhongyang",
    "wof:placetype":"locality"
},
  "geometry": {"coordinates":[99.83839999999999,26.4669],"type":"Point"}
}