{
  "type": "Feature",
  "properties": {
    "gn:admin1_code":"24.0",
    "gn:asciiname":"Beiyang",
    "gn:country_code":"CN",
    "gn:dem":653,
    "gn:feature_class":"P",
    "gn:feature_code":"PPL",
    "gn:name":"Beiyang",
    "gn:population":0,
    "gn:timezone":"Asia/Shanghai",
    "iso:country":"CN",
    "name:deu_x_preferred":[
        "Beiyang"
    ],
    "name:ita_x_preferred":[
        "Beiyang"
    ],
    "name:nor_x_preferred":[
        "Beiyang"
    ],
    "name:rus_x_preferred":[
        "\u0411\u044d\u0439\u044f\u043d"
    ],
    "name:ukr_x_preferred":[
        "\u0411\u0435\u0439\u044f\u043d"
    ],
    "name:und_x_variant":[
        "\u5317\u9633"
    ],
    "wof:name":"Beiyang",
    "wof:placetype":"locality"
},
  "geometry": {"coordinates":[111.40264999999999,35.36832000000001],"type":"Point"}
}