{
  "type": "Feature",
  "properties": {
    "gn:admin1_code":"15.0",
    "gn:asciiname":"Guanlu Yaoxian",
    "gn:country_code":"CN",
    "gn:dem":1552,
    "gn:feature_class":"P",
    "gn:feature_code":"PPL",
    "gn:name":"Guanlu Yaoxian",
    "gn:population":0,
    "gn:timezone":"Asia/Shanghai",
    "iso:country":"CN",
    "name:zho_x_preferred":[
        "\u5173\u8def\u5d3e\u5c98"
    ],
    "wof:name":"Guanlu Yaoxian",
    "wof:placetype":"locality"
},
  "geometry": {"coordinates":[107.053,35.9608],"type":"Point"}
}