{
  "type": "Feature",
  "properties": {
    "gn:admin1_code":"3.0",
    "gn:asciiname":"Shangtingshan",
    "gn:country_code":"CN",
    "gn:dem":246,
    "gn:feature_class":"P",
    "gn:feature_code":"PPL",
    "gn:name":"Shangtingshan",
    "gn:population":0,
    "gn:timezone":"Asia/Shanghai",
    "iso:country":"CN",
    "name:und_x_variant":[
        "\u4e0a\u4ead\u5c71"
    ],
    "wof:name":"Shangtingshan",
    "wof:placetype":"locality"
},
  "geometry": {"coordinates":[114.30475,28.93299],"type":"Point"}
}