{
  "type": "Feature",
  "properties": {
    "gn:admin1_code":"32.0",
    "gn:asciiname":"Guandimiao",
    "gn:country_code":"CN",
    "gn:dem":450,
    "gn:feature_class":"P",
    "gn:feature_code":"PPL",
    "gn:name":"Guandimiao",
    "gn:population":0,
    "gn:timezone":"Asia/Shanghai",
    "iso:country":"CN",
    "name:zho_x_preferred":[
        "\u5173\u5e1d\u5e99"
    ],
    "wof:name":"Guandimiao",
    "wof:placetype":"locality"
},
  "geometry": {"coordinates":[104.44799999999999,30.867],"type":"Point"}
}