{
  "type": "Feature",
  "properties": {
    "gn:admin1_code":"09",
    "gn:asciiname":"Chaozhuang",
    "gn:cc2":"CN",
    "gn:country_code":"CN",
    "gn:dem":39,
    "gn:feature_class":"P",
    "gn:feature_code":"PPL",
    "gn:name":"Chaozhuang",
    "gn:population":0,
    "gn:timezone":"Asia/Shanghai",
    "iso:country":"CN",
    "name:und_x_variant":[
        "Ch\u2019ao-chuang",
        "Chaozhuang"
    ],
    "wof:name":"Chaozhuang",
    "wof:placetype":"locality"
},
  "geometry": {"coordinates":[114.93333,32.26667],"type":"Point"}
}