{
  "type": "Feature",
  "properties": {
    "gn:admin1_code":"15.0",
    "gn:asciiname":"Yaoziwan",
    "gn:country_code":"CN",
    "gn:dem":2129,
    "gn:feature_class":"P",
    "gn:feature_code":"PPL",
    "gn:name":"Yaoziwan",
    "gn:population":0,
    "gn:timezone":"Asia/Shanghai",
    "iso:country":"CN",
    "name:zho_x_preferred":[
        "\u9e5e\u5b50\u6e7e"
    ],
    "wof:name":"Yaoziwan",
    "wof:placetype":"locality"
},
  "geometry": {"coordinates":[105.214,34.3929],"type":"Point"}
}