{
  "type": "Feature",
  "properties": {
    "gn:admin1_code":"21.0",
    "gn:asciiname":"Zhangwunao",
    "gn:country_code":"CN",
    "gn:dem":1965,
    "gn:feature_class":"P",
    "gn:feature_code":"PPL",
    "gn:name":"Zhangwunao",
    "gn:population":0,
    "gn:timezone":"Asia/Shanghai",
    "iso:country":"CN",
    "name:und_x_variant":[
        "\u5f20\u6b66\u57b4"
    ],
    "name:zho_x_preferred":[
        "\u5f20\u6b66\u57b4"
    ],
    "wof:name":"Zhangwunao",
    "wof:placetype":"locality"
},
  "geometry": {"coordinates":[105.60047,35.73583],"type":"Point"}
}