{
  "type": "Feature",
  "properties": {
    "gn:admin1_code":"20.0",
    "gn:asciiname":"Yilelite Shengchandui",
    "gn:country_code":"CN",
    "gn:dem":667,
    "gn:feature_class":"P",
    "gn:feature_code":"PPLF",
    "gn:name":"Yilelite Shengchandui",
    "gn:population":0,
    "gn:timezone":"Asia/Shanghai",
    "iso:country":"CN",
    "name:zho_x_preferred":[
        "\u4f0a\u52d2\u5229\u7279\u751f\u4ea7\u961f"
    ],
    "wof:name":"Yilelite Shengchandui",
    "wof:placetype":"locality"
},
  "geometry": {"coordinates":[119.02110999999999,48.50725],"type":"Point"}
}