{
  "type": "Feature",
  "properties": {
    "gn:admin1_code":"14.0",
    "gn:asciiname":"Qinong",
    "gn:country_code":"CN",
    "gn:dem":5161,
    "gn:feature_class":"P",
    "gn:feature_code":"PPLF",
    "gn:name":"Qinong",
    "gn:population":0,
    "gn:timezone":"Asia/Urumqi",
    "iso:country":"CN",
    "name:bod_x_preferred":[
        "Q\u00ealung"
    ],
    "name:zho_x_preferred":[
        "\u9f50\u519c"
    ],
    "wof:name":"Qinong",
    "wof:placetype":"locality"
},
  "geometry": {"coordinates":[90.50921,29.51863],"type":"Point"}
}