{
  "type": "Feature",
  "properties": {
    "gn:admin1_code":"33.0",
    "gn:asciiname":"Qiankoupo",
    "gn:country_code":"CN",
    "gn:dem":1489,
    "gn:feature_class":"P",
    "gn:feature_code":"PPL",
    "gn:name":"Qiankoupo",
    "gn:population":0,
    "gn:timezone":"Asia/Shanghai",
    "iso:country":"CN",
    "name:zho_x_preferred":[
        "\u5343\u53e3\u5761"
    ],
    "wof:name":"Qiankoupo",
    "wof:placetype":"locality"
},
  "geometry": {"coordinates":[107.61633,29.20533],"type":"Point"}
}