{
  "type": "Feature",
  "properties": {
    "gn:admin1_code":"31",
    "gn:asciiname":"Xiangou",
    "gn:cc2":"CN",
    "gn:country_code":"CN",
    "gn:dem":52,
    "gn:feature_class":"P",
    "gn:feature_code":"PPL",
    "gn:name":"Xiangou",
    "gn:population":0,
    "gn:timezone":"Asia/Shanghai",
    "iso:country":"CN",
    "name:und_x_variant":[
        "Hsien-kou-shih",
        "Xiangou"
    ],
    "wof:name":"Xiangou",
    "wof:placetype":"locality"
},
  "geometry": {"coordinates":[110.37278000000001,19.67528],"type":"Point"}
}