{
  "type": "Feature",
  "properties": {
    "gn:admin1_code":"18",
    "gn:asciiname":"Hekouzhai",
    "gn:country_code":"CN",
    "gn:dem":1932,
    "gn:feature_class":"P",
    "gn:feature_code":"PPL",
    "gn:name":"Hekouzhai",
    "gn:population":0,
    "gn:timezone":"Asia/Shanghai",
    "iso:country":"CN",
    "name:zho_x_preferred":[
        "\u559d\u53e3\u5be8"
    ],
    "wof:name":"Hekouzhai",
    "wof:placetype":"locality"
},
  "geometry": {"coordinates":[105.005,26.6862],"type":"Point"}
}