{
  "type": "Feature",
  "properties": {
    "gn:admin1_code":"21.0",
    "gn:asciiname":"Laochigou",
    "gn:country_code":"CN",
    "gn:dem":1779,
    "gn:feature_class":"P",
    "gn:feature_code":"PPL",
    "gn:name":"Laochigou",
    "gn:population":0,
    "gn:timezone":"Asia/Shanghai",
    "iso:country":"CN",
    "name:zho_x_preferred":[
        "\u6d9d\u6c60\u6c9f"
    ],
    "wof:name":"Laochigou",
    "wof:placetype":"locality"
},
  "geometry": {"coordinates":[106.41,35.38800000000001],"type":"Point"}
}