{
  "type": "Feature",
  "properties": {
    "gn:admin1_code":"25",
    "gn:asciiname":"Dahuangzhuang",
    "gn:country_code":"CN",
    "gn:dem":72,
    "gn:feature_class":"P",
    "gn:feature_code":"PPL",
    "gn:name":"Dahuangzhuang",
    "gn:population":0,
    "gn:timezone":"Asia/Shanghai",
    "iso:country":"CN",
    "name:zho_x_preferred":[
        "\u5927\u9ec4\u5e84"
    ],
    "wof:name":"Dahuangzhuang",
    "wof:placetype":"locality"
},
  "geometry": {"coordinates":[114.893,35.0237],"type":"Point"}
}