{
  "type": "Feature",
  "properties": {
    "gn:admin1_code":"32.0",
    "gn:asciiname":"Zhenwu",
    "gn:country_code":"CN",
    "gn:dem":274,
    "gn:feature_class":"P",
    "gn:feature_code":"PPL",
    "gn:name":"Zhenwu",
    "gn:population":0,
    "gn:timezone":"Asia/Shanghai",
    "iso:country":"CN",
    "name:zho_x_preferred":[
        "\u771f\u6b66"
    ],
    "wof:name":"Zhenwu",
    "wof:placetype":"locality"
},
  "geometry": {"coordinates":[105.61199999999999,30.0527],"type":"Point"}
}