{
  "type": "Feature",
  "properties": {
    "gn:admin1_code":"25.0",
    "gn:asciiname":"Buxi",
    "gn:country_code":"CN",
    "gn:dem":7,
    "gn:feature_class":"P",
    "gn:feature_code":"PPL",
    "gn:name":"Buxi",
    "gn:population":0,
    "gn:timezone":"Asia/Shanghai",
    "iso:country":"CN",
    "name:zho_x_preferred":[
        "\u57e0\u897f"
    ],
    "wof:name":"Buxi",
    "wof:placetype":"locality"
},
  "geometry": {"coordinates":[120.07201000000001,37.4222],"type":"Point"}
}