{
  "type": "Feature",
  "properties": {
    "gn:admin1_code":"10.0",
    "gn:asciiname":"Chegulutuo",
    "gn:country_code":"CN",
    "gn:dem":701,
    "gn:feature_class":"P",
    "gn:feature_code":"PPL",
    "gn:name":"Chegulutuo",
    "gn:population":0,
    "gn:timezone":"Asia/Shanghai",
    "iso:country":"CN",
    "name:zho_x_preferred":[
        "\u8f66\u8f71\u8f98\u5768"
    ],
    "wof:name":"Chegulutuo",
    "wof:placetype":"locality"
},
  "geometry": {"coordinates":[113.91788,38.60278],"type":"Point"}
}