{
  "type": "Feature",
  "properties": {
    "gn:admin1_code":"7.0",
    "gn:asciiname":"Zhuoran",
    "gn:country_code":"CN",
    "gn:dem":468,
    "gn:feature_class":"P",
    "gn:feature_code":"PPL",
    "gn:name":"Zhuoran",
    "gn:population":0,
    "gn:timezone":"Asia/Shanghai",
    "iso:country":"CN",
    "name:zho_x_preferred":[
        "\u5353\u7136"
    ],
    "wof:name":"Zhuoran",
    "wof:placetype":"locality"
},
  "geometry": {"coordinates":[116.87729,25.13873],"type":"Point"}
}