{
  "type": "Feature",
  "properties": {
    "gn:admin1_code":"29.0",
    "gn:asciiname":"Duanleng",
    "gn:country_code":"CN",
    "gn:dem":854,
    "gn:feature_class":"P",
    "gn:feature_code":"PPL",
    "gn:name":"Duanleng",
    "gn:population":0,
    "gn:timezone":"Asia/Shanghai",
    "iso:country":"CN",
    "name:zho_x_preferred":[
        "\u7aef\u695e"
    ],
    "wof:name":"Duanleng",
    "wof:placetype":"locality"
},
  "geometry": {"coordinates":[99.3794,24.0744],"type":"Point"}
}