{
  "type": "Feature",
  "properties": {
    "gn:admin1_code":"11",
    "gn:asciiname":"Tianjiadong",
    "gn:country_code":"CN",
    "gn:dem":534,
    "gn:feature_class":"P",
    "gn:feature_code":"PPL",
    "gn:name":"Tianjiadong",
    "gn:population":0,
    "gn:timezone":"Asia/Shanghai",
    "iso:country":"CN",
    "wof:name":"Tianjiadong",
    "wof:placetype":"locality"
},
  "geometry": {"coordinates":[109.80638999999999,28.67556],"type":"Point"}
}