{
  "type": "Feature",
  "properties": {
    "gn:admin1_code":"29.0",
    "gn:asciiname":"Shilongshan",
    "gn:country_code":"CN",
    "gn:dem":2008,
    "gn:feature_class":"P",
    "gn:feature_code":"PPL",
    "gn:name":"Shilongshan",
    "gn:population":0,
    "gn:timezone":"Asia/Shanghai",
    "iso:country":"CN",
    "name:zho_x_preferred":[
        "\u77f3\u9f99\u5c71"
    ],
    "wof:name":"Shilongshan",
    "wof:placetype":"locality"
},
  "geometry": {"coordinates":[103.617,25.9883],"type":"Point"}
}