{
  "type": "Feature",
  "properties": {
    "gn:admin1_code":"3.0",
    "gn:asciiname":"Hetuan",
    "gn:country_code":"CN",
    "gn:dem":40,
    "gn:feature_class":"P",
    "gn:feature_code":"PPL",
    "gn:name":"Hetuan",
    "gn:population":0,
    "gn:timezone":"Asia/Shanghai",
    "iso:country":"CN",
    "name:und_x_variant":[
        "\u548c\u56e2",
        "Hetuanxiang",
        "\u548c\u56e2\u4e61"
    ],
    "wof:name":"Hetuan",
    "wof:placetype":"locality"
},
  "geometry": {"coordinates":[116.7527,29.98351],"type":"Point"}
}