{
  "type": "Feature",
  "properties": {
    "gn:admin1_code":"3.0",
    "gn:asciiname":"Wentiannao",
    "gn:country_code":"CN",
    "gn:dem":242,
    "gn:feature_class":"P",
    "gn:feature_code":"PPL",
    "gn:name":"Wentiannao",
    "gn:population":0,
    "gn:timezone":"Asia/Shanghai",
    "iso:country":"CN",
    "name:und_x_variant":[
        "\u6587\u7530\u8111"
    ],
    "wof:name":"Wentiannao",
    "wof:placetype":"locality"
},
  "geometry": {"coordinates":[115.88849999999999,25.97609],"type":"Point"}
}