{
  "type": "Feature",
  "properties": {
    "gn:admin1_code":"14.0",
    "gn:asciiname":"Wazhu",
    "gn:country_code":"CN",
    "gn:dem":3996,
    "gn:feature_class":"P",
    "gn:feature_code":"PPL",
    "gn:name":"Wazhu",
    "gn:population":0,
    "gn:timezone":"Asia/Urumqi",
    "iso:country":"CN",
    "name:zho_x_preferred":[
        "\u74e6\u7af9"
    ],
    "wof:name":"Wazhu",
    "wof:placetype":"locality"
},
  "geometry": {"coordinates":[94.33521,30.73431],"type":"Point"}
}