{
  "type": "Feature",
  "properties": {
    "gn:admin1_code":"29",
    "gn:asciiname":"Yunping",
    "gn:country_code":"CN",
    "gn:dem":1755,
    "gn:feature_class":"P",
    "gn:feature_code":"PPL",
    "gn:name":"Yunping",
    "gn:population":0,
    "gn:timezone":"Asia/Shanghai",
    "iso:country":"CN",
    "name:zho_x_preferred":[
        "\u4e91\u5e73"
    ],
    "wof:name":"Yunping",
    "wof:placetype":"locality"
},
  "geometry": {"coordinates":[102.706,24.3254],"type":"Point"}
}