{
  "type": "Feature",
  "properties": {
    "gn:admin1_code":"24.0",
    "gn:asciiname":"Diaowangping",
    "gn:country_code":"CN",
    "gn:dem":1543,
    "gn:feature_class":"P",
    "gn:feature_code":"PPL",
    "gn:name":"Diaowangping",
    "gn:population":0,
    "gn:timezone":"Asia/Shanghai",
    "iso:country":"CN",
    "name:zho_x_preferred":[
        "\u5201\u738b\u576a"
    ],
    "wof:name":"Diaowangping",
    "wof:placetype":"locality"
},
  "geometry": {"coordinates":[112.0937,36.67908],"type":"Point"}
}