{
  "type": "Feature",
  "properties": {
    "gn:admin1_code":"4.0",
    "gn:asciiname":"Yingxicun",
    "gn:country_code":"CN",
    "gn:dem":4,
    "gn:feature_class":"P",
    "gn:feature_code":"PPL",
    "gn:name":"Yingxicun",
    "gn:population":0,
    "gn:timezone":"Asia/Shanghai",
    "iso:country":"CN",
    "name:zho_x_preferred":[
        "\u8425\u897f\u6751"
    ],
    "wof:name":"Yingxicun",
    "wof:placetype":"locality"
},
  "geometry": {"coordinates":[119.50049,33.00708],"type":"Point"}
}