{
  "type": "Feature",
  "properties": {
    "gn:admin1_code":"5.0",
    "gn:asciiname":"Yuandong",
    "gn:country_code":"CN",
    "gn:dem":533,
    "gn:feature_class":"P",
    "gn:feature_code":"PPL",
    "gn:name":"Yuandong",
    "gn:population":0,
    "gn:timezone":"Asia/Shanghai",
    "iso:country":"CN",
    "name:und_x_variant":[
        "\u5143\u4e1c"
    ],
    "wof:name":"Yuandong",
    "wof:placetype":"locality"
},
  "geometry": {"coordinates":[129.47096999999999,42.60858],"type":"Point"}
}