{
  "type": "Feature",
  "properties": {
    "iso:country":"CN",
    "qs:name":"\u7259\u514b\u77f3",
    "qs:name_adm0":"\u4e2d\u570b",
    "qs:name_adm1":"\u5185\u8499\u53e4\u81ea\u6cbb\u533a",
    "qs:photos":4,
    "qs:photos_1k":1,
    "qs:photos_9k":1,
    "qs:photos_9r":1,
    "qs:photos_all":4,
    "qs:photos_sr":1,
    "qs:placetype":"Town",
    "qs:pop_sr":"0",
    "wof:name":"\u7259\u514b\u77f3",
    "wof:placetype":"locality"
},
  "geometry": {"coordinates":[120.699119,49.291709],"type":"Point"}
}