{
  "type": "Feature",
  "properties": {
    "gn:admin1_code":"25",
    "gn:asciiname":"Bama",
    "gn:country_code":"CN",
    "gn:dem":200,
    "gn:feature_class":"P",
    "gn:feature_code":"PPL",
    "gn:name":"Bama",
    "gn:population":0,
    "gn:timezone":"Asia/Shanghai",
    "iso:country":"CN",
    "name:cat_x_preferred":[
        "Bama"
    ],
    "name:ceb_x_preferred":[
        "Bama"
    ],
    "name:deu_x_preferred":[
        "Bama"
    ],
    "name:fra_x_preferred":[
        "Bama"
    ],
    "name:glg_x_preferred":[
        "Bama"
    ],
    "name:ita_x_preferred":[
        "Bama"
    ],
    "name:nld_x_preferred":[
        "Bama"
    ],
    "name:nor_x_preferred":[
        "Bama"
    ],
    "name:swe_x_preferred":[
        "Bama"
    ],
    "name:zho_x_preferred":[
        "\u62d4\u9ebb"
    ],
    "wof:name":"Bama",
    "wof:placetype":"locality"
},
  "geometry": {"coordinates":[118.30500000000001,35.6948],"type":"Point"}
}