{
  "type": "Feature",
  "properties": {
    "gn:admin1_code":"4.0",
    "gn:asciiname":"Wanliucun",
    "gn:country_code":"CN",
    "gn:dem":1,
    "gn:feature_class":"P",
    "gn:feature_code":"PPL",
    "gn:name":"Wanliucun",
    "gn:population":0,
    "gn:timezone":"Asia/Shanghai",
    "iso:country":"CN",
    "name:zho_x_preferred":[
        "\u4e07\u5218\u6751"
    ],
    "wof:name":"Wanliucun",
    "wof:placetype":"locality"
},
  "geometry": {"coordinates":[120.09528,33.04169],"type":"Point"}
}