{
  "type": "Feature",
  "properties": {
    "gn:admin1_code":"13.0",
    "gn:asciiname":"Argan",
    "gn:cc2":"CN",
    "gn:country_code":"CN",
    "gn:dem":830,
    "gn:feature_class":"P",
    "gn:feature_code":"PPL",
    "gn:name":"Argan",
    "gn:population":0,
    "gn:timezone":"Asia/Urumqi",
    "iso:country":"CN",
    "name:uig_x_preferred":[
        "Ar\u01a3an"
    ],
    "name:uig_x_variant":[
        "Arghan",
        "\u0626\u0627\u0631\u063a\u0627\u0646",
        "\u0410\u0440\u0493\u0430\u043d"
    ],
    "name:und_x_variant":[
        "A-la-kan",
        "Argan"
    ],
    "wof:name":"Argan",
    "wof:placetype":"locality"
},
  "geometry": {"coordinates":[88.35361,40.14389],"type":"Point"}
}