{
  "type": "Feature",
  "properties": {
    "gn:admin1_code":"12.0",
    "gn:asciiname":"Caijiatao",
    "gn:country_code":"CN",
    "gn:dem":24,
    "gn:feature_class":"P",
    "gn:feature_code":"PPL",
    "gn:name":"Caijiatao",
    "gn:population":0,
    "gn:timezone":"Asia/Shanghai",
    "iso:country":"CN",
    "name:zho_x_preferred":[
        "\u8521\u5bb6\u5957"
    ],
    "wof:name":"Caijiatao",
    "wof:placetype":"locality"
},
  "geometry": {"coordinates":[113.93413,30.10324],"type":"Point"}
}