{
  "type": "Feature",
  "properties": {
    "gn:admin1_code":"11.0",
    "gn:asciiname":"Fengye",
    "gn:country_code":"CN",
    "gn:dem":155,
    "gn:feature_class":"P",
    "gn:feature_code":"PPL",
    "gn:name":"Fengye",
    "gn:population":0,
    "gn:timezone":"Asia/Shanghai",
    "iso:country":"CN",
    "name:zho_x_preferred":[
        "\u9022\u7237"
    ],
    "wof:name":"Fengye",
    "wof:placetype":"locality"
},
  "geometry": {"coordinates":[109.80701999999999,27.85332],"type":"Point"}
}