{
  "type": "Feature",
  "properties": {
    "gn:admin1_code":"25.0",
    "gn:asciiname":"Gaogezhuangcun",
    "gn:country_code":"CN",
    "gn:dem":72,
    "gn:feature_class":"P",
    "gn:feature_code":"PPL",
    "gn:name":"Gaogezhuangcun",
    "gn:population":0,
    "gn:timezone":"Asia/Shanghai",
    "iso:country":"CN",
    "name:zho_x_preferred":[
        "\u9ad8\u6208\u5e84\u6751"
    ],
    "wof:name":"Gaogezhuangcun",
    "wof:placetype":"locality"
},
  "geometry": {"coordinates":[119.34301000000001,36.17751],"type":"Point"}
}