{
  "type": "Feature",
  "properties": {
    "gn:admin1_code":"8.0",
    "gn:asciiname":"Lijiting Wopeng",
    "gn:country_code":"CN",
    "gn:dem":128,
    "gn:feature_class":"P",
    "gn:feature_code":"PPL",
    "gn:name":"Lijiting Wopeng",
    "gn:population":0,
    "gn:timezone":"Asia/Shanghai",
    "iso:country":"CN",
    "name:zho_x_preferred":[
        "\u674e\u7ee7\u4ead\u7a9d\u68da"
    ],
    "wof:name":"Lijiting Wopeng",
    "wof:placetype":"locality"
},
  "geometry": {"coordinates":[124.67813,45.5883],"type":"Point"}
}