{
  "type": "Feature",
  "properties": {
    "gn:admin1_code":"11",
    "gn:asciiname":"Muxi",
    "gn:country_code":"CN",
    "gn:dem":270,
    "gn:feature_class":"P",
    "gn:feature_code":"PPLA4",
    "gn:name":"Muxi",
    "gn:population":0,
    "gn:timezone":"Asia/Shanghai",
    "iso:country":"CN",
    "name:und_x_variant":[
        "Muxi Xiang"
    ],
    "name:zho_x_preferred":[
        "\u6728\u6eaa"
    ],
    "name:zho_x_variant":[
        "\u6728\u6eaa\u4e61"
    ],
    "wof:name":"Muxi",
    "wof:placetype":"locality"
},
  "geometry": {"coordinates":[110.58861,28.09222],"type":"Point"}
}