{
  "type": "Feature",
  "properties": {
    "gn:admin1_code":"29.0",
    "gn:asciiname":"Dawu",
    "gn:country_code":"CN",
    "gn:dem":2080,
    "gn:feature_class":"P",
    "gn:feature_code":"PPL",
    "gn:name":"Dawu",
    "gn:population":0,
    "gn:timezone":"Asia/Shanghai",
    "iso:country":"CN",
    "name:ceb_x_preferred":[
        "Dawu"
    ],
    "name:deu_x_preferred":[
        "Dawu"
    ],
    "name:eus_x_preferred":[
        "Dawu"
    ],
    "name:fra_x_preferred":[
        "Dawu"
    ],
    "name:nor_x_preferred":[
        "Dawu"
    ],
    "name:swe_x_preferred":[
        "Dawu"
    ],
    "name:zho_x_preferred":[
        "\u6253\u4e4c"
    ],
    "wof:name":"Dawu",
    "wof:placetype":"locality"
},
  "geometry": {"coordinates":[101.066,26.8128],"type":"Point"}
}