{
  "type": "Feature",
  "properties": {
    "gn:admin1_code":"14.0",
    "gn:asciiname":"Womima",
    "gn:country_code":"CN",
    "gn:dem":4252,
    "gn:feature_class":"P",
    "gn:feature_code":"PPL",
    "gn:name":"Womima",
    "gn:population":0,
    "gn:timezone":"Asia/Urumqi",
    "iso:country":"CN",
    "name:zho_x_preferred":[
        "\u7a9d\u7c73\u739b"
    ],
    "wof:name":"Womima",
    "wof:placetype":"locality"
},
  "geometry": {"coordinates":[95.11403,31.57296],"type":"Point"}
}