{
  "type": "Feature",
  "properties": {
    "gn:admin1_code":"5.0",
    "gn:asciiname":"Chengzihou",
    "gn:country_code":"CN",
    "gn:dem":377,
    "gn:feature_class":"P",
    "gn:feature_code":"PPL",
    "gn:name":"Chengzihou",
    "gn:population":0,
    "gn:timezone":"Asia/Shanghai",
    "iso:country":"CN",
    "name:und_x_variant":[
        "\u57ce\u5b50\u540e",
        "Chengzihoucun",
        "\u57ce\u5b50\u540e\u6751"
    ],
    "wof:name":"Chengzihou",
    "wof:placetype":"locality"
},
  "geometry": {"coordinates":[130.34776000000002,43.73799],"type":"Point"}
}