{
  "type": "Feature",
  "properties": {
    "gn:admin1_code":"29",
    "gn:asciiname":"Shaojia",
    "gn:country_code":"CN",
    "gn:dem":1861,
    "gn:feature_class":"P",
    "gn:feature_code":"PPL",
    "gn:name":"Shaojia",
    "gn:population":0,
    "gn:timezone":"Asia/Shanghai",
    "iso:country":"CN",
    "name:zho_x_preferred":[
        "\u90b5\u5bb6"
    ],
    "wof:name":"Shaojia",
    "wof:placetype":"locality"
},
  "geometry": {"coordinates":[101.47199999999999,25.0329],"type":"Point"}
}