{
  "type": "Feature",
  "properties": {
    "gn:admin1_code":"25",
    "gn:asciiname":"Jiazhuang",
    "gn:country_code":"CN",
    "gn:dem":37,
    "gn:feature_class":"P",
    "gn:feature_code":"PPL",
    "gn:name":"Jiazhuang",
    "gn:population":0,
    "gn:timezone":"Asia/Shanghai",
    "iso:country":"CN",
    "name:zho_x_preferred":[
        "\u8d3e\u5e84"
    ],
    "wof:name":"Jiazhuang",
    "wof:placetype":"locality"
},
  "geometry": {"coordinates":[118.358,34.5783],"type":"Point"}
}