{
  "type": "Feature",
  "properties": {
    "gn:admin1_code":"1.0",
    "gn:asciiname":"Hujiaducun",
    "gn:country_code":"CN",
    "gn:dem":42,
    "gn:feature_class":"P",
    "gn:feature_code":"PPL",
    "gn:name":"Hujiaducun",
    "gn:population":0,
    "gn:timezone":"Asia/Shanghai",
    "iso:country":"CN",
    "name:zho_x_preferred":[
        "\u80e1\u5bb6\u6e21\u6751"
    ],
    "wof:name":"Hujiaducun",
    "wof:placetype":"locality"
},
  "geometry": {"coordinates":[116.44416,31.75773],"type":"Point"}
}