{
  "type": "Feature",
  "properties": {
    "gn:admin1_code":"19.0",
    "gn:asciiname":"Hedongyan",
    "gn:country_code":"CN",
    "gn:dem":179,
    "gn:feature_class":"P",
    "gn:feature_code":"PPL",
    "gn:name":"Hedongyan",
    "gn:population":0,
    "gn:timezone":"Asia/Shanghai",
    "iso:country":"CN",
    "name:und_x_variant":[
        "\u6cb3\u4e1c\u6cbf"
    ],
    "name:zho_x_preferred":[
        "\u6cb3\u4e1c\u6cbf"
    ],
    "wof:name":"Hedongyan",
    "wof:placetype":"locality"
},
  "geometry": {"coordinates":[123.64015999999999,40.59193],"type":"Point"}
}