{
  "type": "Feature",
  "properties": {
    "gn:admin1_code":"29.0",
    "gn:asciiname":"Shandian",
    "gn:country_code":"CN",
    "gn:dem":1975,
    "gn:feature_class":"P",
    "gn:feature_code":"PPL",
    "gn:name":"Shandian",
    "gn:population":0,
    "gn:timezone":"Asia/Shanghai",
    "iso:country":"CN",
    "name:ara_x_preferred":[
        "\u0634\u0627\u0646\u062f\u0627\u064a\u0646"
    ],
    "name:ben_x_preferred":[
        "\u09b6\u09cd\u09af\u09be\u09a8\u09cd\u09a1\u09bf\u09af\u09bc\u09be\u09a8"
    ],
    "name:deu_x_preferred":[
        "Shandian"
    ],
    "name:ell_x_preferred":[
        "\u03a3\u03b1\u03bd\u03c4\u03b9\u03ac\u03bd"
    ],
    "name:fas_x_preferred":[
        "\u0634\u0627\u0646\u062f\u06cc\u0627\u0646"
    ],
    "name:fra_x_preferred":[
        "Shandian"
    ],
    "name:heb_x_preferred":[
        "\u05e9\u05d0\u05e0\u05d3\u05d9\u05d0\u05df"
    ],
    "name:hin_x_preferred":[
        "\u0936\u093e\u0902\u0921\u093f\u092f\u0928"
    ],
    "name:hun_x_preferred":[
        "Shandian"
    ],
    "name:ind_x_preferred":[
        "Shandian"
    ],
    "name:ita_x_preferred":[
        "Shandian"
    ],
    "name:jpn_x_preferred":[
        "\u9583\u96fb\u6cb3"
    ],
    "name:kor_x_preferred":[
        "\uc0b0\ub3ac"
    ],
    "name:nld_x_preferred":[
        "Shandian"
    ],
    "name:pol_x_preferred":[
        "Shandian"
    ],
    "name:por_x_preferred":[
        "Shandia"
    ],
    "name:rus_x_preferred":[
        "\u0428\u0430\u043d\u044c\u0434\u044d\u043d\u044c\u0445\u044d"
    ],
    "name:spa_x_preferred":[
        "Shangani"
    ],
    "name:swe_x_preferred":[
        "Shandian"
    ],
    "name:tur_x_preferred":[
        "Shandian"
    ],
    "name:ukr_x_preferred":[
        "\u0428\u0435\u043d\u0434\u0456\u0430\u043d"
    ],
    "name:und_x_variant":[
        "\u5c71\u5e97"
    ],
    "name:urd_x_preferred":[
        "\u0634\u0627\u0646\u062f\u06cc\u0627\u0646"
    ],
    "name:vie_x_preferred":[
        "S\u00f4ng Thi\u1ec3m \u0110i\u1ec7n"
    ],
    "name:zho_cn_x_preferred":[
        "\u95ea\u7535\u6cb3"
    ],
    "name:zho_tw_x_preferred":[
        "\u9583\u96fb\u6cb3"
    ],
    "wof:name":"Shandian",
    "wof:placetype":"locality"
},
  "geometry": {"coordinates":[103.00425,27.25489],"type":"Point"}
}