{
  "type": "Feature",
  "properties": {
    "gn:admin1_code":"32.0",
    "gn:asciiname":"Shuigu",
    "gn:country_code":"CN",
    "gn:dem":731,
    "gn:feature_class":"P",
    "gn:feature_code":"PPL",
    "gn:name":"Shuigu",
    "gn:population":0,
    "gn:timezone":"Asia/Shanghai",
    "iso:country":"CN",
    "name:zho_x_preferred":[
        "\u6c34\u53e4"
    ],
    "wof:name":"Shuigu",
    "wof:placetype":"locality"
},
  "geometry": {"coordinates":[108.44173000000001,31.68925],"type":"Point"}
}