{
  "type": "Feature",
  "properties": {
    "gn:admin1_code":"02",
    "gn:asciiname":"Qiaodun",
    "gn:country_code":"CN",
    "gn:dem":62,
    "gn:feature_class":"P",
    "gn:feature_code":"PPL",
    "gn:name":"Qiaodun",
    "gn:population":0,
    "gn:timezone":"Asia/Shanghai",
    "iso:country":"CN",
    "name:und_x_variant":[
        "Qiaodunzhen",
        "Qiaodun"
    ],
    "name:zho_x_preferred":[
        "Ch\u2019iao-tun-men"
    ],
    "name:zho_x_variant":[
        "Ch\u2019iao-tun"
    ],
    "wof:name":"Qiaodun",
    "wof:placetype":"locality"
},
  "geometry": {"coordinates":[120.29389,27.46132],"type":"Point"}
}