{
  "type": "Feature",
  "properties": {
    "gn:admin1_code":"1.0",
    "gn:asciiname":"Xinxingcun",
    "gn:country_code":"CN",
    "gn:dem":132,
    "gn:feature_class":"P",
    "gn:feature_code":"PPL",
    "gn:name":"Xinxingcun",
    "gn:population":0,
    "gn:timezone":"Asia/Shanghai",
    "iso:country":"CN",
    "name:zho_x_preferred":[
        "\u4fe1\u884c\u6751"
    ],
    "wof:name":"Xinxingcun",
    "wof:placetype":"locality"
},
  "geometry": {"coordinates":[118.3111,29.83392000000001],"type":"Point"}
}