{
  "type": "Feature",
  "properties": {
    "gn:admin1_code":"12.0",
    "gn:asciiname":"Yazigang",
    "gn:country_code":"CN",
    "gn:dem":379,
    "gn:feature_class":"P",
    "gn:feature_code":"PPL",
    "gn:name":"Yazigang",
    "gn:population":0,
    "gn:timezone":"Asia/Shanghai",
    "iso:country":"CN",
    "name:zho_x_preferred":[
        "\u9e2d\u5b50\u6e2f"
    ],
    "wof:name":"Yazigang",
    "wof:placetype":"locality"
},
  "geometry": {"coordinates":[115.1588,31.40332],"type":"Point"}
}