{
  "type": "Feature",
  "properties": {
    "gn:admin1_code":"21.0",
    "gn:asciiname":"Shiqiaozi",
    "gn:country_code":"CN",
    "gn:dem":1599,
    "gn:feature_class":"P",
    "gn:feature_code":"PPL",
    "gn:name":"Shiqiaozi",
    "gn:population":0,
    "gn:timezone":"Asia/Shanghai",
    "iso:country":"CN",
    "name:zho_x_preferred":[
        "\u77f3\u6865\u5b50"
    ],
    "wof:name":"Shiqiaozi",
    "wof:placetype":"locality"
},
  "geometry": {"coordinates":[106.23757999999999,36.14109000000001],"type":"Point"}
}