{
  "type": "Feature",
  "properties": {
    "gn:admin1_code":"19.0",
    "gn:asciiname":"Zhengbeigou",
    "gn:country_code":"CN",
    "gn:dem":457,
    "gn:feature_class":"P",
    "gn:feature_code":"PPL",
    "gn:name":"Zhengbeigou",
    "gn:population":0,
    "gn:timezone":"Asia/Shanghai",
    "iso:country":"CN",
    "name:und_x_variant":[
        "\u6b63\u5317\u6c9f"
    ],
    "wof:name":"Zhengbeigou",
    "wof:placetype":"locality"
},
  "geometry": {"coordinates":[122.73296999999999,40.29162],"type":"Point"}
}