{
  "type": "Feature",
  "properties": {
    "gn:admin1_code":"32.0",
    "gn:asciiname":"Gaya",
    "gn:country_code":"CN",
    "gn:dem":3533,
    "gn:feature_class":"P",
    "gn:feature_code":"PPL",
    "gn:name":"Gaya",
    "gn:population":0,
    "gn:timezone":"Asia/Shanghai",
    "iso:country":"CN",
    "name:zho_x_preferred":[
        "\u560e\u4e9a"
    ],
    "wof:name":"Gaya",
    "wof:placetype":"locality"
},
  "geometry": {"coordinates":[101.096,31.0573],"type":"Point"}
}