{
  "type": "Feature",
  "properties": {
    "gn:admin1_code":"29.0",
    "gn:asciiname":"Fashiyan",
    "gn:country_code":"CN",
    "gn:dem":1564,
    "gn:feature_class":"P",
    "gn:feature_code":"PPL",
    "gn:name":"Fashiyan",
    "gn:population":0,
    "gn:timezone":"Asia/Shanghai",
    "iso:country":"CN",
    "name:zho_x_preferred":[
        "\u53d1\u77f3\u5ca9"
    ],
    "wof:name":"Fashiyan",
    "wof:placetype":"locality"
},
  "geometry": {"coordinates":[104.584,24.9867],"type":"Point"}
}