{
  "type": "Feature",
  "properties": {
    "gn:admin1_code":"32.0",
    "gn:asciiname":"Tiangongmiao",
    "gn:country_code":"CN",
    "gn:dem":405,
    "gn:feature_class":"P",
    "gn:feature_code":"PPL",
    "gn:name":"Tiangongmiao",
    "gn:population":0,
    "gn:timezone":"Asia/Shanghai",
    "iso:country":"CN",
    "name:zho_x_preferred":[
        "\u5929\u5bab\u5e99"
    ],
    "wof:name":"Tiangongmiao",
    "wof:placetype":"locality"
},
  "geometry": {"coordinates":[104.742,30.2363],"type":"Point"}
}