{
  "type": "Feature",
  "properties": {
    "gn:admin1_code":"11.0",
    "gn:asciiname":"Dayingang",
    "gn:country_code":"CN",
    "gn:dem":79,
    "gn:feature_class":"P",
    "gn:feature_code":"PPL",
    "gn:name":"Dayingang",
    "gn:population":0,
    "gn:timezone":"Asia/Shanghai",
    "iso:country":"CN",
    "name:zho_x_preferred":[
        "Dayingang"
    ],
    "name:zho_x_variant":[
        "\u5927\u94f6\u5c97"
    ],
    "wof:name":"Dayingang",
    "wof:placetype":"locality"
},
  "geometry": {"coordinates":[111.58485,29.24029],"type":"Point"}
}