{
  "type": "Feature",
  "properties": {
    "gn:admin1_code":"3.0",
    "gn:asciiname":"Shangguan",
    "gn:country_code":"CN",
    "gn:dem":146,
    "gn:feature_class":"P",
    "gn:feature_code":"PPL",
    "gn:name":"Shangguan",
    "gn:population":0,
    "gn:timezone":"Asia/Shanghai",
    "iso:country":"CN",
    "name:deu_x_preferred":[
        "Shangguan"
    ],
    "name:und_x_variant":[
        "\u4e0a\u5173"
    ],
    "wof:name":"Shangguan",
    "wof:placetype":"locality"
},
  "geometry": {"coordinates":[115.64355,25.91749],"type":"Point"}
}