{
  "type": "Feature",
  "properties": {
    "gn:admin1_code":"15.0",
    "gn:asciiname":"Yanji",
    "gn:country_code":"CN",
    "gn:dem":1596,
    "gn:feature_class":"P",
    "gn:feature_code":"PPL",
    "gn:name":"Yanji",
    "gn:population":0,
    "gn:timezone":"Asia/Shanghai",
    "iso:country":"CN",
    "name:ara_x_preferred":[
        "\u064a\u0627\u0646\u062c\u064a"
    ],
    "name:cat_x_preferred":[
        "Yanji"
    ],
    "name:ceb_x_preferred":[
        "Yanji"
    ],
    "name:ces_x_preferred":[
        "Jongil"
    ],
    "name:deu_x_preferred":[
        "Yanji"
    ],
    "name:fas_x_preferred":[
        "\u06cc\u0627\u0646\u06af\u0698\u06cc"
    ],
    "name:fra_x_preferred":[
        "Yanji"
    ],
    "name:ind_x_preferred":[
        "Yanji"
    ],
    "name:ita_x_preferred":[
        "Yanji"
    ],
    "name:jpn_x_preferred":[
        "\u5ef6\u5409\u5e02"
    ],
    "name:kik_x_preferred":[
        "Yanji"
    ],
    "name:kor_x_preferred":[
        "\uc60c\uc9c0\uc2dc"
    ],
    "name:mlg_x_preferred":[
        "Yanji"
    ],
    "name:nld_x_preferred":[
        "Yanji"
    ],
    "name:nor_x_preferred":[
        "Yanji"
    ],
    "name:pol_x_preferred":[
        "Yanji"
    ],
    "name:por_x_preferred":[
        "Yanji"
    ],
    "name:rus_x_preferred":[
        "\u042f\u043d\u044c\u0446\u0437\u0438"
    ],
    "name:spa_x_preferred":[
        "Yanji"
    ],
    "name:srp_x_preferred":[
        "\u0408\u0430\u043d\u0452\u0438"
    ],
    "name:swe_x_preferred":[
        "Yanji"
    ],
    "name:tur_x_preferred":[
        "Yanji"
    ],
    "name:urd_x_preferred":[
        "\u06cc\u0627\u0646\u062c\u06cc"
    ],
    "name:vie_x_preferred":[
        "Di\u00ean C\u00e1t"
    ],
    "name:war_x_preferred":[
        "Yanji"
    ],
    "name:wuu_x_preferred":[
        "\u5ef6\u5409\u5e02"
    ],
    "name:zho_x_preferred":[
        "\u960e\u96c6"
    ],
    "name:zho_x_variant":[
        "\u5ef6\u5409\u5e02"
    ],
    "wof:name":"Yanji",
    "wof:placetype":"locality"
},
  "geometry": {"coordinates":[105.602,34.2202],"type":"Point"}
}