{
  "type": "Feature",
  "properties": {
    "gn:admin1_code":"19.0",
    "gn:asciiname":"Zhouhuzigou",
    "gn:country_code":"CN",
    "gn:dem":767,
    "gn:feature_class":"P",
    "gn:feature_code":"PPL",
    "gn:name":"Zhouhuzigou",
    "gn:population":0,
    "gn:timezone":"Asia/Shanghai",
    "iso:country":"CN",
    "name:zho_x_preferred":[
        "\u5468\u80e1\u5b50\u6c9f"
    ],
    "wof:name":"Zhouhuzigou",
    "wof:placetype":"locality"
},
  "geometry": {"coordinates":[119.89,41.8313],"type":"Point"}
}