{
  "type": "Feature",
  "properties": {
    "gn:admin1_code":"10.0",
    "gn:asciiname":"Hanhugou",
    "gn:country_code":"CN",
    "gn:dem":722,
    "gn:feature_class":"P",
    "gn:feature_code":"PPL",
    "gn:name":"Hanhugou",
    "gn:population":0,
    "gn:timezone":"Asia/Shanghai",
    "iso:country":"CN",
    "name:zho_x_preferred":[
        "\u97e9\u864e\u6c9f"
    ],
    "wof:name":"Hanhugou",
    "wof:placetype":"locality"
},
  "geometry": {"coordinates":[114.48130999999999,39.19093],"type":"Point"}
}