{
  "type": "Feature",
  "properties": {
    "gn:admin1_code":"29.0",
    "gn:asciiname":"Gesa",
    "gn:country_code":"CN",
    "gn:dem":3033,
    "gn:feature_class":"P",
    "gn:feature_code":"PPL",
    "gn:name":"Gesa",
    "gn:population":0,
    "gn:timezone":"Asia/Shanghai",
    "iso:country":"CN",
    "name:zho_x_preferred":[
        "\u683c\u6492"
    ],
    "wof:name":"Gesa",
    "wof:placetype":"locality"
},
  "geometry": {"coordinates":[99.97190000000001,27.3841],"type":"Point"}
}