{
  "type": "Feature",
  "properties": {
    "gn:admin1_code":"2",
    "gn:asciiname":"Dongxi",
    "gn:country_code":"CN",
    "gn:dem":358,
    "gn:feature_class":"P",
    "gn:feature_code":"PPLA4",
    "gn:name":"Dongxi",
    "gn:population":0,
    "gn:timezone":"Asia/Shanghai",
    "iso:country":"CN",
    "name:und_x_variant":[
        "\u4e1c\u6eaa",
        "Dongxi",
        "Dongxi Xiang"
    ],
    "name:zho_x_preferred":[
        "\u4e1c\u6eaa\u4e61"
    ],
    "wof:name":"Dongxi",
    "wof:placetype":"locality"
},
  "geometry": {"coordinates":[119.95977000000001,27.42371],"type":"Point"}
}