{
  "type": "Feature",
  "properties": {
    "gn:admin1_code":"10",
    "gn:asciiname":"Liangzhitai",
    "gn:country_code":"CN",
    "gn:dem":26,
    "gn:feature_class":"P",
    "gn:feature_code":"PPL",
    "gn:name":"Liangzhitai",
    "gn:population":0,
    "gn:timezone":"Asia/Shanghai",
    "iso:country":"CN",
    "name:zho_x_preferred":[
        "\u826f\u77e5\u53f0"
    ],
    "wof:name":"Liangzhitai",
    "wof:placetype":"locality"
},
  "geometry": {"coordinates":[115.63,37.9952],"type":"Point"}
}