{
  "type": "Feature",
  "properties": {
    "gn:admin1_code":"11.0",
    "gn:asciiname":"Yangtan",
    "gn:country_code":"CN",
    "gn:dem":808,
    "gn:feature_class":"P",
    "gn:feature_code":"PPL",
    "gn:name":"Yangtan",
    "gn:population":0,
    "gn:timezone":"Asia/Shanghai",
    "iso:country":"CN",
    "name:zho_x_preferred":[
        "\u7f8a\u5766"
    ],
    "wof:name":"Yangtan",
    "wof:placetype":"locality"
},
  "geometry": {"coordinates":[113.23908,25.63901],"type":"Point"}
}