{
  "type": "Feature",
  "properties": {
    "gn:admin1_code":"25.0",
    "gn:asciiname":"Miaodao",
    "gn:country_code":"CN",
    "gn:dem":4,
    "gn:feature_class":"P",
    "gn:feature_code":"PPL",
    "gn:name":"Miaodao",
    "gn:population":0,
    "gn:timezone":"Asia/Shanghai",
    "iso:country":"CN",
    "name:ita_x_preferred":[
        "Miao dao"
    ],
    "name:lit_x_preferred":[
        "Miao dao"
    ],
    "name:zho_x_preferred":[
        "\u5e99\u5c9b"
    ],
    "wof:name":"Miaodao",
    "wof:placetype":"locality"
},
  "geometry": {"coordinates":[120.68479000000001,37.946],"type":"Point"}
}