{
  "type": "Feature",
  "properties": {
    "gn:admin1_code":"15.0",
    "gn:asciiname":"Xuwa",
    "gn:country_code":"CN",
    "gn:dem":1537,
    "gn:feature_class":"P",
    "gn:feature_code":"PPL",
    "gn:name":"Xuwa",
    "gn:population":0,
    "gn:timezone":"Asia/Shanghai",
    "iso:country":"CN",
    "name:und_x_variant":[
        "\u5f90\u5c72"
    ],
    "wof:name":"Xuwa",
    "wof:placetype":"locality"
},
  "geometry": {"coordinates":[105.87821,35.03773],"type":"Point"}
}