{
  "type": "Feature",
  "properties": {
    "gn:admin1_code":"20.0",
    "gn:asciiname":"Gezhenwan",
    "gn:country_code":"CN",
    "gn:dem":1584,
    "gn:feature_class":"P",
    "gn:feature_code":"PPL",
    "gn:name":"Gezhenwan",
    "gn:population":0,
    "gn:timezone":"Asia/Shanghai",
    "iso:country":"CN",
    "name:und_x_variant":[
        "\u572a\u9488\u6e7e"
    ],
    "wof:name":"Gezhenwan",
    "wof:placetype":"locality"
},
  "geometry": {"coordinates":[111.82769,39.66884],"type":"Point"}
}