{
  "type": "Feature",
  "properties": {
    "gn:admin1_code":"5.0",
    "gn:asciiname":"Qiaojia Weizicun",
    "gn:country_code":"CN",
    "gn:dem":142,
    "gn:feature_class":"P",
    "gn:feature_code":"PPL",
    "gn:name":"Qiaojia Weizicun",
    "gn:population":0,
    "gn:timezone":"Asia/Shanghai",
    "iso:country":"CN",
    "name:zho_x_preferred":[
        "\u4e54\u5bb6\u56f4\u5b50\u6751"
    ],
    "wof:name":"Qiaojia Weizicun",
    "wof:placetype":"locality"
},
  "geometry": {"coordinates":[123.33225,44.74398],"type":"Point"}
}