{
  "type": "Feature",
  "properties": {
    "gn:admin1_code":"11.0",
    "gn:asciiname":"Suijiapo",
    "gn:country_code":"CN",
    "gn:dem":821,
    "gn:feature_class":"P",
    "gn:feature_code":"PPL",
    "gn:name":"Suijiapo",
    "gn:population":0,
    "gn:timezone":"Asia/Shanghai",
    "iso:country":"CN",
    "name:zho_x_preferred":[
        "\u968f\u5bb6\u5761"
    ],
    "name:zho_x_variant":[
        "\u968b\u5bb6\u5761"
    ],
    "wof:name":"Suijiapo",
    "wof:placetype":"locality"
},
  "geometry": {"coordinates":[109.90361,29.52345],"type":"Point"}
}