{
  "type": "Feature",
  "properties": {
    "gn:admin1_code":"19.0",
    "gn:asciiname":"Xinglongtuncun",
    "gn:country_code":"CN",
    "gn:dem":76,
    "gn:feature_class":"P",
    "gn:feature_code":"PPL",
    "gn:name":"Xinglongtuncun",
    "gn:population":0,
    "gn:timezone":"Asia/Shanghai",
    "iso:country":"CN",
    "name:zho_x_preferred":[
        "\u5174\u9686\u5c6f\u6751"
    ],
    "wof:name":"Xinglongtuncun",
    "wof:placetype":"locality"
},
  "geometry": {"coordinates":[123.583,42.4263],"type":"Point"}
}