{
  "type": "Feature",
  "properties": {
    "gn:admin1_code":"25.0",
    "gn:asciiname":"Wanghaocun",
    "gn:country_code":"CN",
    "gn:dem":9,
    "gn:feature_class":"P",
    "gn:feature_code":"PPL",
    "gn:name":"Wanghaocun",
    "gn:population":0,
    "gn:timezone":"Asia/Shanghai",
    "iso:country":"CN",
    "name:zho_x_preferred":[
        "\u738b\u6d69\u6751"
    ],
    "wof:name":"Wanghaocun",
    "wof:placetype":"locality"
},
  "geometry": {"coordinates":[118.34562,37.21471],"type":"Point"}
}