{
  "type": "Feature",
  "properties": {
    "gn:admin1_code":"11.0",
    "gn:asciiname":"Fujianpo",
    "gn:country_code":"CN",
    "gn:dem":376,
    "gn:feature_class":"P",
    "gn:feature_code":"PPL",
    "gn:name":"Fujianpo",
    "gn:population":0,
    "gn:timezone":"Asia/Shanghai",
    "iso:country":"CN",
    "name:zho_x_preferred":[
        "\u798f\u5efa\u5761"
    ],
    "wof:name":"Fujianpo",
    "wof:placetype":"locality"
},
  "geometry": {"coordinates":[110.25913,29.5309],"type":"Point"}
}