{
  "type": "Feature",
  "properties": {
    "gn:admin1_code":"3.0",
    "gn:asciiname":"Youjiukeng",
    "gn:country_code":"CN",
    "gn:dem":168,
    "gn:feature_class":"P",
    "gn:feature_code":"PPL",
    "gn:name":"Youjiukeng",
    "gn:population":0,
    "gn:timezone":"Asia/Shanghai",
    "iso:country":"CN",
    "name:und_x_variant":[
        "\u60a0\u4e45\u5751"
    ],
    "wof:name":"Youjiukeng",
    "wof:placetype":"locality"
},
  "geometry": {"coordinates":[115.29991,26.35027],"type":"Point"}
}