{
  "type": "Feature",
  "properties": {
    "gn:admin1_code":"12.0",
    "gn:asciiname":"Fengtan",
    "gn:country_code":"CN",
    "gn:dem":34,
    "gn:feature_class":"P",
    "gn:feature_code":"PPL",
    "gn:name":"Fengtan",
    "gn:population":0,
    "gn:timezone":"Asia/Shanghai",
    "iso:country":"CN",
    "name:zho_x_preferred":[
        "\u67ab\u6f6d"
    ],
    "wof:name":"Fengtan",
    "wof:placetype":"locality"
},
  "geometry": {"coordinates":[113.83817000000001,29.76252],"type":"Point"}
}