{
  "type": "Feature",
  "properties": {
    "gn:admin1_code":"5.0",
    "gn:asciiname":"Chaoyangchuancun",
    "gn:country_code":"CN",
    "gn:dem":578,
    "gn:feature_class":"P",
    "gn:feature_code":"PPL",
    "gn:name":"Chaoyangchuancun",
    "gn:population":0,
    "gn:timezone":"Asia/Shanghai",
    "iso:country":"CN",
    "name:zho_x_preferred":[
        "\u671d\u9633\u5ddd\u6751"
    ],
    "wof:name":"Chaoyangchuancun",
    "wof:placetype":"locality"
},
  "geometry": {"coordinates":[128.07194999999999,43.38034],"type":"Point"}
}