{
  "type": "Feature",
  "properties": {
    "gn:admin1_code":"7",
    "gn:asciiname":"Daji",
    "gn:country_code":"CN",
    "gn:dem":69,
    "gn:feature_class":"P",
    "gn:feature_code":"PPLA4",
    "gn:name":"Daji",
    "gn:population":0,
    "gn:timezone":"Asia/Shanghai",
    "iso:country":"CN",
    "name:und_x_variant":[
        "Daji Zhen"
    ],
    "name:zho_x_preferred":[
        "\u5927\u6d4e"
    ],
    "name:zho_x_variant":[
        "\u5927\u6d4e\u9547"
    ],
    "wof:name":"Daji",
    "wof:placetype":"locality"
},
  "geometry": {"coordinates":[118.63453,25.37261],"type":"Point"}
}