{
  "type": "Feature",
  "properties": {
    "gn:admin1_code":"1.0",
    "gn:asciiname":"Anmei",
    "gn:country_code":"CN",
    "gn:dem":121,
    "gn:feature_class":"P",
    "gn:feature_code":"PPL",
    "gn:name":"Anmei",
    "gn:population":0,
    "gn:timezone":"Asia/Shanghai",
    "iso:country":"CN",
    "name:und_x_variant":[
        "\u5b89\u6885",
        "Anmei"
    ],
    "wof:name":"Anmei",
    "wof:placetype":"locality"
},
  "geometry": {"coordinates":[118.59348,29.87277000000001],"type":"Point"}
}