{
  "type": "Feature",
  "properties": {
    "gn:admin1_code":"31.0",
    "gn:asciiname":"Longmi",
    "gn:country_code":"CN",
    "gn:dem":168,
    "gn:feature_class":"P",
    "gn:feature_code":"PPL",
    "gn:name":"Longmi",
    "gn:population":0,
    "gn:timezone":"Asia/Shanghai",
    "iso:country":"CN",
    "name:und_x_variant":[
        "\u9f99\u5bc6"
    ],
    "wof:name":"Longmi",
    "wof:placetype":"locality"
},
  "geometry": {"coordinates":[109.2912,18.43846],"type":"Point"}
}