{
  "type": "Feature",
  "properties": {
    "gn:admin1_code":"32.0",
    "gn:asciiname":"Duoxia",
    "gn:country_code":"CN",
    "gn:dem":4084,
    "gn:feature_class":"P",
    "gn:feature_code":"PPL",
    "gn:name":"Duoxia",
    "gn:population":0,
    "gn:timezone":"Asia/Shanghai",
    "iso:country":"CN",
    "name:zho_x_preferred":[
        "\u593a\u5477"
    ],
    "wof:name":"Duoxia",
    "wof:placetype":"locality"
},
  "geometry": {"coordinates":[98.2975,32.8905],"type":"Point"}
}