{
  "type": "Feature",
  "properties": {
    "gn:admin1_code":"15.0",
    "gn:asciiname":"Qijiafen",
    "gn:country_code":"CN",
    "gn:dem":2570,
    "gn:feature_class":"P",
    "gn:feature_code":"PPL",
    "gn:name":"Qijiafen",
    "gn:population":0,
    "gn:timezone":"Asia/Shanghai",
    "iso:country":"CN",
    "name:und_x_variant":[
        "\u621a\u5bb6\u575f"
    ],
    "wof:name":"Qijiafen",
    "wof:placetype":"locality"
},
  "geometry": {"coordinates":[103.705,35.0455],"type":"Point"}
}