{
  "type": "Feature",
  "properties": {
    "gn:admin1_code":"15.0",
    "gn:asciiname":"Shishuba",
    "gn:country_code":"CN",
    "gn:dem":1139,
    "gn:feature_class":"P",
    "gn:feature_code":"PPL",
    "gn:name":"Shishuba",
    "gn:population":0,
    "gn:timezone":"Asia/Shanghai",
    "iso:country":"CN",
    "name:und_x_variant":[
        "\u67ff\u6811\u575d"
    ],
    "wof:name":"Shishuba",
    "wof:placetype":"locality"
},
  "geometry": {"coordinates":[106.34448,33.77866],"type":"Point"}
}