{
  "type": "Feature",
  "properties": {
    "gn:admin1_code":"29.0",
    "gn:asciiname":"Linkoushang",
    "gn:country_code":"CN",
    "gn:dem":1342,
    "gn:feature_class":"P",
    "gn:feature_code":"PPL",
    "gn:name":"Linkoushang",
    "gn:population":0,
    "gn:timezone":"Asia/Shanghai",
    "iso:country":"CN",
    "name:zho_x_preferred":[
        "\u6797\u53e3\u4e0a"
    ],
    "wof:name":"Linkoushang",
    "wof:placetype":"locality"
},
  "geometry": {"coordinates":[105.152,27.7609],"type":"Point"}
}