{
  "type": "Feature",
  "properties": {
    "gn:admin1_code":"4.0",
    "gn:asciiname":"Langzhuang",
    "gn:country_code":"CN",
    "gn:dem":8,
    "gn:feature_class":"P",
    "gn:feature_code":"PPL",
    "gn:name":"Langzhuang",
    "gn:population":0,
    "gn:timezone":"Asia/Shanghai",
    "iso:country":"CN",
    "name:zho_x_preferred":[
        "\u90ce\u5e84"
    ],
    "wof:name":"Langzhuang",
    "wof:placetype":"locality"
},
  "geometry": {"coordinates":[119.93634,32.27073],"type":"Point"}
}