{
  "type": "Feature",
  "properties": {
    "gn:admin1_code":"32.0",
    "gn:asciiname":"Zhongqin",
    "gn:country_code":"CN",
    "gn:dem":2990,
    "gn:feature_class":"P",
    "gn:feature_code":"PPL",
    "gn:name":"Zhongqin",
    "gn:population":0,
    "gn:timezone":"Asia/Shanghai",
    "iso:country":"CN",
    "name:zho_x_preferred":[
        "\u4e2d\u52e4"
    ],
    "wof:name":"Zhongqin",
    "wof:placetype":"locality"
},
  "geometry": {"coordinates":[100.15282000000001,30.8025],"type":"Point"}
}