{
  "type": "Feature",
  "properties": {
    "gn:admin1_code":"19.0",
    "gn:asciiname":"Huihegou",
    "gn:country_code":"CN",
    "gn:dem":546,
    "gn:feature_class":"P",
    "gn:feature_code":"PPL",
    "gn:name":"Huihegou",
    "gn:population":0,
    "gn:timezone":"Asia/Shanghai",
    "iso:country":"CN",
    "name:und_x_variant":[
        "\u4f1a\u5408\u6c9f"
    ],
    "name:zho_x_preferred":[
        "\u4f1a\u5408\u6c9f"
    ],
    "wof:name":"Huihegou",
    "wof:placetype":"locality"
},
  "geometry": {"coordinates":[119.45455,40.60026],"type":"Point"}
}