{
  "type": "Feature",
  "properties": {
    "gn:admin1_code":"3.0",
    "gn:asciiname":"Gebuchong",
    "gn:country_code":"CN",
    "gn:dem":466,
    "gn:feature_class":"P",
    "gn:feature_code":"PPL",
    "gn:name":"Gebuchong",
    "gn:population":0,
    "gn:timezone":"Asia/Shanghai",
    "iso:country":"CN",
    "name:und_x_variant":[
        "\u5272\u5e03\u51b2"
    ],
    "wof:name":"Gebuchong",
    "wof:placetype":"locality"
},
  "geometry": {"coordinates":[114.49318999999998,27.49591],"type":"Point"}
}