{
  "type": "Feature",
  "properties": {
    "gn:admin1_code":"16",
    "gn:asciiname":"Manqingshan",
    "gn:country_code":"CN",
    "gn:dem":169,
    "gn:feature_class":"P",
    "gn:feature_code":"PPL",
    "gn:name":"Manqingshan",
    "gn:population":0,
    "gn:timezone":"Asia/Shanghai",
    "iso:country":"CN",
    "name:zho_x_preferred":[
        "\u6ee1\u9752\u5c71"
    ],
    "wof:name":"Manqingshan",
    "wof:placetype":"locality"
},
  "geometry": {"coordinates":[109.995,25.1569],"type":"Point"}
}