{
  "type": "Feature",
  "properties": {
    "gn:admin1_code":"29.0",
    "gn:asciiname":"Dongping",
    "gn:country_code":"CN",
    "gn:dem":1815,
    "gn:feature_class":"P",
    "gn:feature_code":"PPL",
    "gn:name":"Dongping",
    "gn:population":0,
    "gn:timezone":"Asia/Shanghai",
    "iso:country":"CN",
    "name:und_x_variant":[
        "\u4e1c\u5c4f"
    ],
    "wof:name":"Dongping",
    "wof:placetype":"locality"
},
  "geometry": {"coordinates":[102.51398,25.64333],"type":"Point"}
}