{
  "type": "Feature",
  "properties": {
    "gn:admin1_code":"12.0",
    "gn:asciiname":"Tianjiadun",
    "gn:country_code":"CN",
    "gn:dem":48,
    "gn:feature_class":"P",
    "gn:feature_code":"PPL",
    "gn:name":"Tianjiadun",
    "gn:population":0,
    "gn:timezone":"Asia/Shanghai",
    "iso:country":"CN",
    "name:zho_x_preferred":[
        "Tianjiadun"
    ],
    "name:zho_x_variant":[
        "\u7530\u5bb6\u58a9"
    ],
    "wof:name":"Tianjiadun",
    "wof:placetype":"locality"
},
  "geometry": {"coordinates":[115.14489,30.19917],"type":"Point"}
}