{
  "type": "Feature",
  "properties": {
    "gn:admin1_code":"4.0",
    "gn:asciiname":"Beichacun",
    "gn:country_code":"CN",
    "gn:dem":21,
    "gn:feature_class":"P",
    "gn:feature_code":"PPL",
    "gn:name":"Beichacun",
    "gn:population":0,
    "gn:timezone":"Asia/Shanghai",
    "iso:country":"CN",
    "name:zho_x_preferred":[
        "\u5317\u8336\u6751"
    ],
    "wof:name":"Beichacun",
    "wof:placetype":"locality"
},
  "geometry": {"coordinates":[119.23766999999999,32.64313],"type":"Point"}
}