{
  "type": "Feature",
  "properties": {
    "gn:admin1_code":"11.0",
    "gn:asciiname":"Dengpingluo",
    "gn:country_code":"CN",
    "gn:dem":991,
    "gn:feature_class":"P",
    "gn:feature_code":"PPL",
    "gn:name":"Dengpingluo",
    "gn:population":0,
    "gn:timezone":"Asia/Shanghai",
    "iso:country":"CN",
    "name:zho_x_preferred":[
        "\u9093\u576a\u6f2f"
    ],
    "wof:name":"Dengpingluo",
    "wof:placetype":"locality"
},
  "geometry": {"coordinates":[111.95055000000001,26.05125],"type":"Point"}
}