{
  "type": "Feature",
  "properties": {
    "gn:admin1_code":"14.0",
    "gn:asciiname":"Momda",
    "gn:country_code":"CN",
    "gn:dem":4645,
    "gn:feature_class":"P",
    "gn:feature_code":"PPL",
    "gn:name":"Momda",
    "gn:population":0,
    "gn:timezone":"Asia/Urumqi",
    "iso:country":"CN",
    "name:bod_x_preferred":[
        "Momda"
    ],
    "name:zho_x_preferred":[
        "Mengda"
    ],
    "name:zho_x_variant":[
        "\u68a6\u8fbe"
    ],
    "wof:name":"Momda",
    "wof:placetype":"locality"
},
  "geometry": {"coordinates":[96.401,31.401],"type":"Point"}
}