{
  "type": "Feature",
  "properties": {
    "gn:admin1_code":"18.0",
    "gn:asciiname":"Yingshang",
    "gn:country_code":"CN",
    "gn:dem":1400,
    "gn:feature_class":"P",
    "gn:feature_code":"PPL",
    "gn:name":"Yingshang",
    "gn:population":0,
    "gn:timezone":"Asia/Shanghai",
    "iso:country":"CN",
    "wof:name":"Yingshang",
    "wof:placetype":"locality"
},
  "geometry": {"coordinates":[105.48333,25.63333],"type":"Point"}
}