{
  "type": "Feature",
  "properties": {
    "gn:admin1_code":"07",
    "gn:asciiname":"Xinancheng",
    "gn:country_code":"CN",
    "gn:dem":560,
    "gn:feature_class":"P",
    "gn:feature_code":"PPL",
    "gn:name":"Xinancheng",
    "gn:population":0,
    "gn:timezone":"Asia/Shanghai",
    "iso:country":"CN",
    "name:zho_x_preferred":[
        "\u6eaa\u5357\u57d5"
    ],
    "wof:name":"Xinancheng",
    "wof:placetype":"locality"
},
  "geometry": {"coordinates":[118.29243999999998,25.64464],"type":"Point"}
}