{
  "type": "Feature",
  "properties": {
    "gn:admin1_code":"19.0",
    "gn:asciiname":"Tieyingzi",
    "gn:country_code":"CN",
    "gn:dem":89,
    "gn:feature_class":"P",
    "gn:feature_code":"PPL",
    "gn:name":"Tieyingzi",
    "gn:population":0,
    "gn:timezone":"Asia/Shanghai",
    "iso:country":"CN",
    "name:und_x_variant":[
        "\u94c1\u8425\u5b50"
    ],
    "name:zho_x_preferred":[
        "\u94c1\u8425\u5b50"
    ],
    "wof:name":"Tieyingzi",
    "wof:placetype":"locality"
},
  "geometry": {"coordinates":[123.673,41.99396],"type":"Point"}
}