{
  "type": "Feature",
  "properties": {
    "gn:admin1_code":"15.0",
    "gn:asciiname":"Gantansi",
    "gn:country_code":"CN",
    "gn:dem":2769,
    "gn:feature_class":"P",
    "gn:feature_code":"PPL",
    "gn:name":"Gantansi",
    "gn:population":0,
    "gn:timezone":"Asia/Shanghai",
    "iso:country":"CN",
    "name:und_x_variant":[
        "\u7518\u6ee9\u5bfa"
    ],
    "wof:name":"Gantansi",
    "wof:placetype":"locality"
},
  "geometry": {"coordinates":[104.11244000000001,34.76832],"type":"Point"}
}