{
  "type": "Feature",
  "properties": {
    "gn:admin1_code":"9.0",
    "gn:asciiname":"Shandi",
    "gn:country_code":"CN",
    "gn:dem":180,
    "gn:feature_class":"P",
    "gn:feature_code":"PPL",
    "gn:name":"Shandi",
    "gn:population":0,
    "gn:timezone":"Asia/Shanghai",
    "iso:country":"CN",
    "name:ceb_x_preferred":[
        "Shandi"
    ],
    "name:por_x_preferred":[
        "Shandi"
    ],
    "name:zho_x_preferred":[
        "\u5c71\u5e95"
    ],
    "wof:name":"Shandi",
    "wof:placetype":"locality"
},
  "geometry": {"coordinates":[112.88443999999998,33.27529000000001],"type":"Point"}
}