{
  "type": "Feature",
  "properties": {
    "gn:admin1_code":"12.0",
    "gn:asciiname":"Fengjialaoyuan",
    "gn:country_code":"CN",
    "gn:dem":41,
    "gn:feature_class":"P",
    "gn:feature_code":"PPL",
    "gn:name":"Fengjialaoyuan",
    "gn:population":0,
    "gn:timezone":"Asia/Shanghai",
    "iso:country":"CN",
    "name:zho_x_preferred":[
        "Fengjialaoyuan"
    ],
    "name:zho_x_variant":[
        "\u51af\u5bb6\u8001\u9662"
    ],
    "wof:name":"Fengjialaoyuan",
    "wof:placetype":"locality"
},
  "geometry": {"coordinates":[112.17515,30.48729],"type":"Point"}
}