{
  "type": "Feature",
  "properties": {
    "gn:admin1_code":"19.0",
    "gn:asciiname":"Yujiagou Beiliang",
    "gn:country_code":"CN",
    "gn:dem":521,
    "gn:feature_class":"P",
    "gn:feature_code":"PPL",
    "gn:name":"Yujiagou Beiliang",
    "gn:population":0,
    "gn:timezone":"Asia/Shanghai",
    "iso:country":"CN",
    "name:zho_x_preferred":[
        "\u4e8e\u5bb6\u6c9f\u5317\u6881"
    ],
    "wof:name":"Yujiagou Beiliang",
    "wof:placetype":"locality"
},
  "geometry": {"coordinates":[120.15900000000001,41.087],"type":"Point"}
}