{
  "type": "Feature",
  "properties": {
    "gn:admin1_code":"29.0",
    "gn:asciiname":"Muta",
    "gn:country_code":"CN",
    "gn:dem":2060,
    "gn:feature_class":"P",
    "gn:feature_code":"PPL",
    "gn:name":"Muta",
    "gn:population":0,
    "gn:timezone":"Asia/Shanghai",
    "iso:country":"CN",
    "name:ceb_x_preferred":[
        "Muta"
    ],
    "name:deu_x_preferred":[
        "Muta"
    ],
    "name:fra_x_preferred":[
        "Muta"
    ],
    "name:heb_x_preferred":[
        "\u05de\u05d5\u05d9\u05e0\u05d2\u05d4"
    ],
    "name:hun_x_preferred":[
        "Muta"
    ],
    "name:hye_x_preferred":[
        "\u0544\u0578\u0582\u057f\u0561"
    ],
    "name:ita_x_preferred":[
        "Muta"
    ],
    "name:rus_x_preferred":[
        "\u041c\u0443\u0442\u0430"
    ],
    "name:swe_x_preferred":[
        "Muta"
    ],
    "name:zho_x_preferred":[
        "\u6728\u69bb"
    ],
    "wof:name":"Muta",
    "wof:placetype":"locality"
},
  "geometry": {"coordinates":[103.93300000000001,24.5195],"type":"Point"}
}