{
  "type": "Feature",
  "properties": {
    "gn:admin1_code":"16.0",
    "gn:asciiname":"Yinlukou",
    "gn:country_code":"CN",
    "gn:dem":479,
    "gn:feature_class":"P",
    "gn:feature_code":"PPL",
    "gn:name":"Yinlukou",
    "gn:population":0,
    "gn:timezone":"Asia/Shanghai",
    "iso:country":"CN",
    "name:zho_x_preferred":[
        "\u94f6\u7089\u53e3"
    ],
    "wof:name":"Yinlukou",
    "wof:placetype":"locality"
},
  "geometry": {"coordinates":[111.57899999999999,24.2511],"type":"Point"}
}