{
  "type": "Feature",
  "properties": {
    "gn:admin1_code":"25",
    "gn:asciiname":"Shangbaojiazhuang",
    "gn:country_code":"CN",
    "gn:dem":141,
    "gn:feature_class":"P",
    "gn:feature_code":"PPL",
    "gn:name":"Shangbaojiazhuang",
    "gn:population":0,
    "gn:timezone":"Asia/Shanghai",
    "iso:country":"CN",
    "name:zho_x_preferred":[
        "\u4e0a\u9c8d\u5bb6\u5e84"
    ],
    "wof:name":"Shangbaojiazhuang",
    "wof:placetype":"locality"
},
  "geometry": {"coordinates":[117.26000000000001,35.4708],"type":"Point"}
}