{
  "type": "Feature",
  "properties": {
    "gn:admin1_code":"19.0",
    "gn:asciiname":"Renjiajie",
    "gn:country_code":"CN",
    "gn:dem":403,
    "gn:feature_class":"P",
    "gn:feature_code":"PPL",
    "gn:name":"Renjiajie",
    "gn:population":0,
    "gn:timezone":"Asia/Shanghai",
    "iso:country":"CN",
    "name:und_x_variant":[
        "\u4efb\u5bb6\u8857"
    ],
    "wof:name":"Renjiajie",
    "wof:placetype":"locality"
},
  "geometry": {"coordinates":[124.37922,41.55214],"type":"Point"}
}