{
  "type": "Feature",
  "properties": {
    "gn:admin1_code":"3",
    "gn:asciiname":"Huangzhou",
    "gn:country_code":"CN",
    "gn:dem":33,
    "gn:feature_class":"P",
    "gn:feature_code":"PPL",
    "gn:name":"Huangzhou",
    "gn:population":0,
    "gn:timezone":"Asia/Shanghai",
    "iso:country":"CN",
    "name:und_x_variant":[
        "\u9ec4\u6d32",
        "Huangzhou Zhen",
        "\u9ec4\u6d32\u9547"
    ],
    "wof:name":"Huangzhou",
    "wof:placetype":"locality"
},
  "geometry": {"coordinates":[115.49308000000001,28.73887],"type":"Point"}
}