{
  "type": "Feature",
  "properties": {
    "gn:admin1_code":"30.0",
    "gn:asciiname":"Maopingcun",
    "gn:country_code":"CN",
    "gn:dem":58,
    "gn:feature_class":"P",
    "gn:feature_code":"PPL",
    "gn:name":"Maopingcun",
    "gn:population":0,
    "gn:timezone":"Asia/Shanghai",
    "iso:country":"CN",
    "name:zho_x_preferred":[
        "\u8305\u576a\u6751"
    ],
    "wof:name":"Maopingcun",
    "wof:placetype":"locality"
},
  "geometry": {"coordinates":[112.14767000000001,22.0819],"type":"Point"}
}