{
  "type": "Feature",
  "properties": {
    "gn:admin1_code":"19.0",
    "gn:asciiname":"Xiaogujiazi",
    "gn:country_code":"CN",
    "gn:dem":29,
    "gn:feature_class":"P",
    "gn:feature_code":"PPL",
    "gn:name":"Xiaogujiazi",
    "gn:population":0,
    "gn:timezone":"Asia/Shanghai",
    "iso:country":"CN",
    "name:zho_x_preferred":[
        "\u5c0f\u53e4\u5bb6\u5b50"
    ],
    "wof:name":"Xiaogujiazi",
    "wof:placetype":"locality"
},
  "geometry": {"coordinates":[123.06999999999999,41.7629],"type":"Point"}
}