{
  "type": "Feature",
  "properties": {
    "gn:admin1_code":"24.0",
    "gn:asciiname":"Dongruoyuan",
    "gn:country_code":"CN",
    "gn:dem":910,
    "gn:feature_class":"P",
    "gn:feature_code":"PPL",
    "gn:name":"Dongruoyuan",
    "gn:population":0,
    "gn:timezone":"Asia/Shanghai",
    "iso:country":"CN",
    "name:zho_x_preferred":[
        "\u4e1c\u82e5\u9662"
    ],
    "wof:name":"Dongruoyuan",
    "wof:placetype":"locality"
},
  "geometry": {"coordinates":[113.03252000000001,39.12571],"type":"Point"}
}