{
  "type": "Feature",
  "properties": {
    "gn:admin1_code":"3.0",
    "gn:asciiname":"Kunyuan",
    "gn:country_code":"CN",
    "gn:dem":26,
    "gn:feature_class":"P",
    "gn:feature_code":"PPL",
    "gn:name":"Kunyuan",
    "gn:population":0,
    "gn:timezone":"Asia/Shanghai",
    "iso:country":"CN",
    "name:und_x_variant":[
        "\u5764\u5143"
    ],
    "wof:name":"Kunyuan",
    "wof:placetype":"locality"
},
  "geometry": {"coordinates":[115.92959999999999,28.17643],"type":"Point"}
}