{
  "type": "Feature",
  "properties": {
    "gn:admin1_code":"14.0",
    "gn:asciiname":"Sa'en",
    "gn:country_code":"CN",
    "gn:dem":3547,
    "gn:feature_class":"P",
    "gn:feature_code":"PPL",
    "gn:name":"Sa\u2019en",
    "gn:population":0,
    "gn:timezone":"Asia/Urumqi",
    "iso:country":"CN",
    "name:und_x_variant":[
        "Sa\u2019en"
    ],
    "name:zho_x_preferred":[
        "\u8428\u6069"
    ],
    "wof:name":"Sa'en",
    "wof:placetype":"locality"
},
  "geometry": {"coordinates":[98.15429,32.19015],"type":"Point"}
}