{
  "type": "Feature",
  "properties": {
    "gn:admin1_code":"10.0",
    "gn:asciiname":"Dongchengguan",
    "gn:country_code":"CN",
    "gn:dem":26,
    "gn:feature_class":"P",
    "gn:feature_code":"PPL",
    "gn:name":"Dongchengguan",
    "gn:population":0,
    "gn:timezone":"Asia/Shanghai",
    "iso:country":"CN",
    "name:zho_x_preferred":[
        "\u4e1c\u57ce\u8d2f"
    ],
    "wof:name":"Dongchengguan",
    "wof:placetype":"locality"
},
  "geometry": {"coordinates":[119.25484,39.89653],"type":"Point"}
}