{
  "type": "Feature",
  "properties": {
    "gn:admin1_code":"26.0",
    "gn:asciiname":"Xialiujiazhai",
    "gn:country_code":"CN",
    "gn:dem":728,
    "gn:feature_class":"P",
    "gn:feature_code":"PPL",
    "gn:name":"Xialiujiazhai",
    "gn:population":0,
    "gn:timezone":"Asia/Shanghai",
    "iso:country":"CN",
    "name:zho_x_preferred":[
        "\u4e0b\u5218\u5bb6\u5be8"
    ],
    "wof:name":"Xialiujiazhai",
    "wof:placetype":"locality"
},
  "geometry": {"coordinates":[109.50431,34.21298],"type":"Point"}
}