{
  "type": "Feature",
  "properties": {
    "gn:admin1_code":"8.0",
    "gn:asciiname":"Bafangtun",
    "gn:country_code":"CN",
    "gn:dem":190,
    "gn:feature_class":"P",
    "gn:feature_code":"PPL",
    "gn:name":"Bafangtun",
    "gn:population":0,
    "gn:timezone":"Asia/Shanghai",
    "iso:country":"CN",
    "name:zho_x_preferred":[
        "\u516b\u65b9\u5c6f"
    ],
    "wof:name":"Bafangtun",
    "wof:placetype":"locality"
},
  "geometry": {"coordinates":[124.76683,48.40633],"type":"Point"}
}