{
  "type": "Feature",
  "properties": {
    "gn:admin1_code":"32.0",
    "gn:asciiname":"Zhoushiqiao",
    "gn:country_code":"CN",
    "gn:dem":487,
    "gn:feature_class":"P",
    "gn:feature_code":"PPL",
    "gn:name":"Zhoushiqiao",
    "gn:population":0,
    "gn:timezone":"Asia/Shanghai",
    "iso:country":"CN",
    "name:zho_x_preferred":[
        "\u5468\u77f3\u6865"
    ],
    "wof:name":"Zhoushiqiao",
    "wof:placetype":"locality"
},
  "geometry": {"coordinates":[103.339,30.0129],"type":"Point"}
}