{
  "type": "Feature",
  "properties": {
    "gn:admin1_code":"4.0",
    "gn:asciiname":"Xinfeng",
    "gn:country_code":"CN",
    "gn:dem":3,
    "gn:feature_class":"P",
    "gn:feature_code":"PPL",
    "gn:name":"Xinfeng",
    "gn:population":0,
    "gn:timezone":"Asia/Shanghai",
    "iso:country":"CN",
    "name:ceb_x_preferred":[
        "Xinfeng"
    ],
    "name:deu_x_preferred":[
        "Xinfeng"
    ],
    "name:fra_x_preferred":[
        "Xinfeng"
    ],
    "name:kor_x_preferred":[
        "\uc2e0\ud391\ud604"
    ],
    "name:nor_x_preferred":[
        "Xinfeng"
    ],
    "name:swe_x_preferred":[
        "Xinfeng"
    ],
    "name:zho_x_preferred":[
        "\u65b0\u4e30"
    ],
    "wof:name":"Xinfeng",
    "wof:placetype":"locality"
},
  "geometry": {"coordinates":[120.09254,32.93583],"type":"Point"}
}