{
  "type": "Feature",
  "properties": {
    "gn:admin1_code":"12.0",
    "gn:asciiname":"Loujiaodi",
    "gn:country_code":"CN",
    "gn:dem":40,
    "gn:feature_class":"P",
    "gn:feature_code":"PPL",
    "gn:name":"Loujiaodi",
    "gn:population":0,
    "gn:timezone":"Asia/Shanghai",
    "iso:country":"CN",
    "name:zho_x_preferred":[
        "\u697c\u811a\u5e95"
    ],
    "wof:name":"Loujiaodi",
    "wof:placetype":"locality"
},
  "geometry": {"coordinates":[113.93715,29.84434000000001],"type":"Point"}
}