{
  "type": "Feature",
  "properties": {
    "gn:admin1_code":"30.0",
    "gn:asciiname":"Shanghuangsha",
    "gn:country_code":"CN",
    "gn:dem":659,
    "gn:feature_class":"P",
    "gn:feature_code":"PPL",
    "gn:name":"Shanghuangsha",
    "gn:population":0,
    "gn:timezone":"Asia/Shanghai",
    "iso:country":"CN",
    "name:zho_x_preferred":[
        "Shanghuangsha"
    ],
    "name:zho_x_variant":[
        "\u4e0a\u9ec4\u6c99"
    ],
    "wof:name":"Shanghuangsha",
    "wof:placetype":"locality"
},
  "geometry": {"coordinates":[113.25139,25.43056],"type":"Point"}
}