{
  "type": "Feature",
  "properties": {
    "gn:admin1_code":"12.0",
    "gn:asciiname":"Yanglinzui",
    "gn:country_code":"CN",
    "gn:dem":35,
    "gn:feature_class":"P",
    "gn:feature_code":"PPL",
    "gn:name":"Yanglinzui",
    "gn:population":0,
    "gn:timezone":"Asia/Shanghai",
    "iso:country":"CN",
    "name:zho_x_preferred":[
        "\u6768\u6797\u5480"
    ],
    "wof:name":"Yanglinzui",
    "wof:placetype":"locality"
},
  "geometry": {"coordinates":[113.73371000000002,29.64837],"type":"Point"}
}