{
  "type": "Feature",
  "properties": {
    "gn:admin1_code":"19.0",
    "gn:asciiname":"Yangmugou",
    "gn:country_code":"CN",
    "gn:dem":236,
    "gn:feature_class":"P",
    "gn:feature_code":"PPL",
    "gn:name":"Yangmugou",
    "gn:population":0,
    "gn:timezone":"Asia/Shanghai",
    "iso:country":"CN",
    "name:und_x_variant":[
        "\u6768\u6728\u6c9f"
    ],
    "name:zho_x_preferred":[
        "\u6768\u6728\u6c9f"
    ],
    "wof:name":"Yangmugou",
    "wof:placetype":"locality"
},
  "geometry": {"coordinates":[123.8381,41.178],"type":"Point"}
}