{
  "type": "Feature",
  "properties": {
    "gn:admin1_code":"4.0",
    "gn:asciiname":"Jiangranqiao",
    "gn:country_code":"CN",
    "gn:dem":5,
    "gn:feature_class":"P",
    "gn:feature_code":"PPL",
    "gn:name":"Jiangranqiao",
    "gn:population":0,
    "gn:timezone":"Asia/Shanghai",
    "iso:country":"CN",
    "name:zho_x_preferred":[
        "\u848b\u67d3\u6865"
    ],
    "wof:name":"Jiangranqiao",
    "wof:placetype":"locality"
},
  "geometry": {"coordinates":[119.84307,31.45644],"type":"Point"}
}