{
  "type": "Feature",
  "properties": {
    "gn:admin1_code":"16.0",
    "gn:asciiname":"Nahu",
    "gn:country_code":"CN",
    "gn:dem":423,
    "gn:feature_class":"P",
    "gn:feature_code":"PPL",
    "gn:name":"Nahu",
    "gn:population":0,
    "gn:timezone":"Asia/Shanghai",
    "iso:country":"CN",
    "name:zho_x_preferred":[
        "\u90a3\u6237"
    ],
    "wof:name":"Nahu",
    "wof:placetype":"locality"
},
  "geometry": {"coordinates":[107.599,24.0321],"type":"Point"}
}