{
  "type": "Feature",
  "properties": {
    "gn:admin1_code":"16",
    "gn:asciiname":"Niutangling",
    "gn:country_code":"CN",
    "gn:dem":836,
    "gn:feature_class":"P",
    "gn:feature_code":"PPL",
    "gn:name":"Niutangling",
    "gn:population":0,
    "gn:timezone":"Asia/Shanghai",
    "iso:country":"CN",
    "name:zho_x_preferred":[
        "\u725b\u5858\u5cad"
    ],
    "wof:name":"Niutangling",
    "wof:placetype":"locality"
},
  "geometry": {"coordinates":[110.741,26.1038],"type":"Point"}
}