{
  "type": "Feature",
  "properties": {
    "gn:admin1_code":"11.0",
    "gn:asciiname":"Tangjieshang",
    "gn:country_code":"CN",
    "gn:dem":97,
    "gn:feature_class":"P",
    "gn:feature_code":"PPL",
    "gn:name":"Tangjieshang",
    "gn:population":0,
    "gn:timezone":"Asia/Shanghai",
    "iso:country":"CN",
    "name:und_x_variant":[
        "Liaotangpu"
    ],
    "name:zho_x_preferred":[
        "\u5858\u754c\u4e0a"
    ],
    "name:zho_x_variant":[
        "\u5ed6\u5858\u94fa"
    ],
    "wof:name":"Tangjieshang",
    "wof:placetype":"locality"
},
  "geometry": {"coordinates":[113.39248000000001,26.85785],"type":"Point"}
}