{
  "type": "Feature",
  "properties": {
    "gn:country":"CN",
    "gn:fcode":"PPL",
    "gn:pop":0,
    "iso:country":"CN",
    "name:unk_x_variant":[
        "Sungkiang"
    ],
    "qs:name":"\u8f9b\u5e84",
    "qs:name_adm0":"\u4e2d\u570b",
    "qs:name_adm1":"\u4e0a\u6d77\u76f4\u8f96\u5e02",
    "qs:photos":266,
    "qs:photos_1k":54,
    "qs:photos_9k":1,
    "qs:photos_9r":4,
    "qs:photos_all":266,
    "qs:photos_sr":5,
    "qs:placetype":"Suburb",
    "qs:pop_sr":"0",
    "wof:name":"\u8f9b\u5e84",
    "wof:placetype":"neighbourhood",
    "wof:population":0
},
  "geometry": {"coordinates":[121.36563,31.12872],"type":"Point"}
}