{
  "type": "Feature",
  "properties": {
    "gn:admin1_code":"7.0",
    "gn:asciiname":"Linshan",
    "gn:country_code":"CN",
    "gn:dem":847,
    "gn:feature_class":"P",
    "gn:feature_code":"PPL",
    "gn:name":"Linshan",
    "gn:population":0,
    "gn:timezone":"Asia/Shanghai",
    "iso:country":"CN",
    "name:zho_x_preferred":[
        "\u6797\u5c71"
    ],
    "wof:name":"Linshan",
    "wof:placetype":"locality"
},
  "geometry": {"coordinates":[117.19756,25.91409],"type":"Point"}
}