{
  "type": "Feature",
  "properties": {
    "gn:admin1_code":"29.0",
    "gn:asciiname":"Xiala Muping",
    "gn:country_code":"CN",
    "gn:dem":1583,
    "gn:feature_class":"P",
    "gn:feature_code":"PPL",
    "gn:name":"Xiala Muping",
    "gn:population":0,
    "gn:timezone":"Asia/Shanghai",
    "iso:country":"CN",
    "name:zho_x_preferred":[
        "\u4e0b\u814a\u6728\u576a"
    ],
    "wof:name":"Xiala Muping",
    "wof:placetype":"locality"
},
  "geometry": {"coordinates":[101.15600000000001,26.5324],"type":"Point"}
}