{
  "type": "Feature",
  "properties": {
    "gn:admin1_code":"18.0",
    "gn:asciiname":"Jiashi",
    "gn:country_code":"CN",
    "gn:dem":467,
    "gn:feature_class":"P",
    "gn:feature_code":"PPL",
    "gn:name":"Jiashi",
    "gn:population":0,
    "gn:timezone":"Asia/Shanghai",
    "iso:country":"CN",
    "name:zho_x_preferred":[
        "\u67b6\u89c6"
    ],
    "wof:name":"Jiashi",
    "wof:placetype":"locality"
},
  "geometry": {"coordinates":[109.283,26.6562],"type":"Point"}
}