{
  "type": "Feature",
  "properties": {
    "gn:admin1_code":"14.0",
    "gn:asciiname":"Jiangxiongcun",
    "gn:country_code":"CN",
    "gn:dem":3969,
    "gn:feature_class":"P",
    "gn:feature_code":"PPL",
    "gn:name":"Jiangxiongcun",
    "gn:population":0,
    "gn:timezone":"Asia/Urumqi",
    "iso:country":"CN",
    "name:zho_x_preferred":[
        "\u6c5f\u96c4\u6751"
    ],
    "wof:name":"Jiangxiongcun",
    "wof:placetype":"locality"
},
  "geometry": {"coordinates":[91.10697999999999,29.09335],"type":"Point"}
}