{
  "type": "Feature",
  "properties": {
    "gn:admin1_code":"30.0",
    "gn:asciiname":"Zhangcuozhaicun",
    "gn:country_code":"CN",
    "gn:dem":11,
    "gn:feature_class":"P",
    "gn:feature_code":"PPL",
    "gn:name":"Zhangcuozhaicun",
    "gn:population":0,
    "gn:timezone":"Asia/Shanghai",
    "iso:country":"CN",
    "name:zho_x_preferred":[
        "\u5f20\u539d\u5be8\u6751"
    ],
    "wof:name":"Zhangcuozhaicun",
    "wof:placetype":"locality"
},
  "geometry": {"coordinates":[116.15801999999999,23.44257],"type":"Point"}
}