{
  "type": "Feature",
  "properties": {
    "gn:admin1_code":"2.0",
    "gn:asciiname":"Dongmuwu",
    "gn:country_code":"CN",
    "gn:dem":37,
    "gn:feature_class":"P",
    "gn:feature_code":"PPL",
    "gn:name":"Dongmuwu",
    "gn:population":0,
    "gn:timezone":"Asia/Shanghai",
    "iso:country":"CN",
    "name:und_x_variant":[
        "\u4e1c\u7a46\u575e"
    ],
    "wof:name":"Dongmuwu",
    "wof:placetype":"locality"
},
  "geometry": {"coordinates":[120.05392999999999,30.22617],"type":"Point"}
}