{
  "type": "Feature",
  "properties": {
    "gn:admin1_code":"19.0",
    "gn:asciiname":"Dadiaoyutai",
    "gn:country_code":"CN",
    "gn:dem":455,
    "gn:feature_class":"P",
    "gn:feature_code":"PPL",
    "gn:name":"Dadiaoyutai",
    "gn:population":0,
    "gn:timezone":"Asia/Shanghai",
    "iso:country":"CN",
    "name:und_x_variant":[
        "\u5927\u9493\u9c7c\u53f0"
    ],
    "wof:name":"Dadiaoyutai",
    "wof:placetype":"locality"
},
  "geometry": {"coordinates":[124.86648,41.94349],"type":"Point"}
}