{
  "type": "Feature",
  "properties": {
    "gn:admin1_code":"3",
    "gn:asciiname":"Aoshangling",
    "gn:country_code":"CN",
    "gn:dem":800,
    "gn:feature_class":"P",
    "gn:feature_code":"PPL",
    "gn:name":"Aoshangling",
    "gn:population":0,
    "gn:timezone":"Asia/Shanghai",
    "iso:country":"CN",
    "wof:name":"Aoshangling",
    "wof:placetype":"locality"
},
  "geometry": {"coordinates":[116.60222,26.39833],"type":"Point"}
}