{
  "type": "Feature",
  "properties": {
    "gn:country":"CN",
    "gn:fcode":"ADM3",
    "gn:pop":0,
    "iso:country":"CN",
    "name:unk_x_variant":[
        "Puning Xian"
    ],
    "name:zho_x_preferred":[
        "\u666e\u5b81\u5e02"
    ],
    "name:zho_x_variant":[
        "\u666e\u5b81"
    ],
    "qs:name":"Puning Shi",
    "qs:photos_9r":0,
    "qs:photos_sr":0,
    "qs:pop_sr":"0",
    "wof:name":"Puning Shi",
    "wof:placetype":"localadmin",
    "wof:population":0
},
  "geometry": {"coordinates":[116.16902,23.42853],"type":"Point"}
}