{
  "type": "Feature",
  "properties": {
    "gn:admin1_code":"29.0",
    "gn:asciiname":"Liu'aozi",
    "gn:country_code":"CN",
    "gn:dem":1964,
    "gn:feature_class":"P",
    "gn:feature_code":"PPL",
    "gn:name":"Liu\u2019aozi",
    "gn:population":0,
    "gn:timezone":"Asia/Shanghai",
    "iso:country":"CN",
    "name:und_x_variant":[
        "Liu\u2019aozi"
    ],
    "name:zho_x_preferred":[
        "\u5218\u51f9\u5b50"
    ],
    "wof:name":"Liu'aozi",
    "wof:placetype":"locality"
},
  "geometry": {"coordinates":[101.461,25.4419],"type":"Point"}
}