{
  "type": "Feature",
  "properties": {
    "gn:admin1_code":"29.0",
    "gn:asciiname":"Qingtoushang",
    "gn:country_code":"CN",
    "gn:dem":2101,
    "gn:feature_class":"P",
    "gn:feature_code":"PPL",
    "gn:name":"Qingtoushang",
    "gn:population":0,
    "gn:timezone":"Asia/Shanghai",
    "iso:country":"CN",
    "name:zho_x_preferred":[
        "\u7b90\u5934\u4e0a"
    ],
    "wof:name":"Qingtoushang",
    "wof:placetype":"locality"
},
  "geometry": {"coordinates":[103.178,26.0316],"type":"Point"}
}