{
  "type": "Feature",
  "properties": {
    "gn:admin1_code":"18",
    "gn:asciiname":"Damatian",
    "gn:country_code":"CN",
    "gn:dem":1754,
    "gn:feature_class":"P",
    "gn:feature_code":"PPL",
    "gn:name":"Damatian",
    "gn:population":0,
    "gn:timezone":"Asia/Shanghai",
    "iso:country":"CN",
    "name:zho_x_preferred":[
        "\u6253\u9a6c\u7530"
    ],
    "wof:name":"Damatian",
    "wof:placetype":"locality"
},
  "geometry": {"coordinates":[104.658,25.9629],"type":"Point"}
}