{
  "type": "Feature",
  "properties": {
    "gn:admin1_code":"30",
    "gn:asciiname":"Jiangbuxu",
    "gn:country_code":"CN",
    "gn:dem":18,
    "gn:feature_class":"P",
    "gn:feature_code":"PPL",
    "gn:name":"Jiangbuxu",
    "gn:population":0,
    "gn:timezone":"Asia/Shanghai",
    "iso:country":"CN",
    "name:und_x_variant":[
        "\u6c5f\u57d7\u5729"
    ],
    "name:zho_x_preferred":[
        "\u6c5f\u57d7\u5729"
    ],
    "wof:name":"Jiangbuxu",
    "wof:placetype":"locality"
},
  "geometry": {"coordinates":[113.14778,23.75],"type":"Point"}
}