{
  "type": "Feature",
  "properties": {
    "gn:admin1_code":"13.0",
    "gn:asciiname":"Yingmaili",
    "gn:country_code":"CN",
    "gn:dem":1204,
    "gn:feature_class":"P",
    "gn:feature_code":"PPLA4",
    "gn:name":"Yingmaili",
    "gn:population":0,
    "gn:timezone":"Asia/Shanghai",
    "iso:country":"CN",
    "name:und_x_variant":[
        "Yingmaili Xiang"
    ],
    "name:zho_x_preferred":[
        "\u82f1\u4e70\u91cc"
    ],
    "name:zho_x_variant":[
        "\u82f1\u4e70\u91cc\u4e61"
    ],
    "wof:name":"Yingmaili",
    "wof:placetype":"locality"
},
  "geometry": {"coordinates":[76.80144,39.51068],"type":"Point"}
}