{
  "type": "Feature",
  "properties": {
    "gn:admin1_code":"8.0",
    "gn:asciiname":"Majia Fangzi",
    "gn:country_code":"CN",
    "gn:dem":289,
    "gn:feature_class":"P",
    "gn:feature_code":"PPL",
    "gn:name":"Majia Fangzi",
    "gn:population":0,
    "gn:timezone":"Asia/Shanghai",
    "iso:country":"CN",
    "name:zho_x_preferred":[
        "\u9a6c\u5bb6\u623f\u5b50"
    ],
    "wof:name":"Majia Fangzi",
    "wof:placetype":"locality"
},
  "geometry": {"coordinates":[126.50286,48.00131],"type":"Point"}
}