{
  "type": "Feature",
  "properties": {
    "gn:admin1_code":"32.0",
    "gn:asciiname":"Saizizhou",
    "gn:country_code":"CN",
    "gn:dem":2848,
    "gn:feature_class":"P",
    "gn:feature_code":"PPL",
    "gn:name":"Saizizhou",
    "gn:population":0,
    "gn:timezone":"Asia/Shanghai",
    "iso:country":"CN",
    "name:zho_x_preferred":[
        "\u585e\u5b50\u5dde"
    ],
    "wof:name":"Saizizhou",
    "wof:placetype":"locality"
},
  "geometry": {"coordinates":[102.574,27.7565],"type":"Point"}
}