{
  "type": "Feature",
  "properties": {
    "gn:admin1_code":"3.0",
    "gn:asciiname":"Hongyantan",
    "gn:country_code":"CN",
    "gn:dem":80,
    "gn:feature_class":"P",
    "gn:feature_code":"PPL",
    "gn:name":"Hongyantan",
    "gn:population":0,
    "gn:timezone":"Asia/Shanghai",
    "iso:country":"CN",
    "name:und_x_variant":[
        "\u7ea2\u5ca9\u6f6d"
    ],
    "wof:name":"Hongyantan",
    "wof:placetype":"locality"
},
  "geometry": {"coordinates":[115.22493,29.35227],"type":"Point"}
}