{
  "type": "Feature",
  "properties": {
    "gn:admin1_code":"2.0",
    "gn:asciiname":"Fengqingqiao Majia",
    "gn:country_code":"CN",
    "gn:dem":5,
    "gn:feature_class":"P",
    "gn:feature_code":"PPL",
    "gn:name":"Fengqingqiao Majia",
    "gn:population":0,
    "gn:timezone":"Asia/Shanghai",
    "iso:country":"CN",
    "name:und_x_variant":[
        "\u98ce\u9752\u6865\u9a6c\u5bb6"
    ],
    "wof:name":"Fengqingqiao Majia",
    "wof:placetype":"locality"
},
  "geometry": {"coordinates":[120.80864,30.50886],"type":"Point"}
}