{
  "type": "Feature",
  "properties": {
    "gn:admin1_code":"30.0",
    "gn:asciiname":"Jingtiankeng",
    "gn:country_code":"CN",
    "gn:dem":5,
    "gn:feature_class":"P",
    "gn:feature_code":"PPL",
    "gn:name":"Jingtiankeng",
    "gn:population":0,
    "gn:timezone":"Asia/Shanghai",
    "iso:country":"CN",
    "name:zho_x_preferred":[
        "\u4e95\u7530\u5751"
    ],
    "wof:name":"Jingtiankeng",
    "wof:placetype":"locality"
},
  "geometry": {"coordinates":[114.75438,22.6793],"type":"Point"}
}