{
  "type": "Feature",
  "properties": {
    "gn:admin1_code":"31",
    "gn:asciiname":"Huixincun",
    "gn:country_code":"CN",
    "gn:dem":9,
    "gn:feature_class":"P",
    "gn:feature_code":"PPL",
    "gn:name":"Huixincun",
    "gn:population":0,
    "gn:timezone":"Asia/Shanghai",
    "iso:country":"CN",
    "name:zho_x_preferred":[
        "\u56de\u65b0\u6751"
    ],
    "wof:name":"Huixincun",
    "wof:placetype":"locality"
},
  "geometry": {"coordinates":[109.45595,18.2867],"type":"Point"}
}