{
  "type": "Feature",
  "properties": {
    "gn:admin1_code":"15.0",
    "gn:asciiname":"Gaguo",
    "gn:country_code":"CN",
    "gn:dem":3126,
    "gn:feature_class":"P",
    "gn:feature_code":"PPL",
    "gn:name":"Gaguo",
    "gn:population":0,
    "gn:timezone":"Asia/Shanghai",
    "iso:country":"CN",
    "name:zho_x_preferred":[
        "\u5c15\u679c"
    ],
    "wof:name":"Gaguo",
    "wof:placetype":"locality"
},
  "geometry": {"coordinates":[102.673,34.5137],"type":"Point"}
}