{
  "type": "Feature",
  "properties": {
    "gn:admin1_code":"9",
    "gn:asciiname":"Jinkelou",
    "gn:country_code":"CN",
    "gn:dem":86,
    "gn:feature_class":"P",
    "gn:feature_code":"PPL",
    "gn:name":"Jinkelou",
    "gn:population":0,
    "gn:timezone":"Asia/Shanghai",
    "iso:country":"CN",
    "name:zho_x_preferred":[
        "\u8fd1\u79d1\u697c"
    ],
    "wof:name":"Jinkelou",
    "wof:placetype":"locality"
},
  "geometry": {"coordinates":[113.80595,35.04446],"type":"Point"}
}