{
  "type": "Feature",
  "properties": {
    "gn:admin1_code":"2.0",
    "gn:asciiname":"Dongzhou",
    "gn:country_code":"CN",
    "gn:dem":74,
    "gn:feature_class":"P",
    "gn:feature_code":"PPL",
    "gn:name":"Dongzhou",
    "gn:population":0,
    "gn:timezone":"Asia/Shanghai",
    "iso:country":"CN",
    "name:und_x_variant":[
        "\u4e1c\u5468",
        "Dongzhou"
    ],
    "wof:name":"Dongzhou",
    "wof:placetype":"locality"
},
  "geometry": {"coordinates":[119.1024,29.10907000000001],"type":"Point"}
}