{
  "type": "Feature",
  "properties": {
    "gn:admin1_code":"2.0",
    "gn:asciiname":"Dong'ao",
    "gn:country_code":"CN",
    "gn:dem":6,
    "gn:feature_class":"P",
    "gn:feature_code":"PPL",
    "gn:name":"Dong\u2019ao",
    "gn:population":0,
    "gn:timezone":"Asia/Shanghai",
    "iso:country":"CN",
    "name:und_x_variant":[
        "Dong\u2019ao"
    ],
    "name:zho_x_preferred":[
        "\u4e1c\u5c99"
    ],
    "wof:name":"Dong'ao",
    "wof:placetype":"locality"
},
  "geometry": {"coordinates":[120.75297999999999,27.84404],"type":"Point"}
}