{
  "type": "Feature",
  "properties": {
    "gn:admin1_code":"15.0",
    "gn:asciiname":"Miaozui",
    "gn:country_code":"CN",
    "gn:dem":1817,
    "gn:feature_class":"P",
    "gn:feature_code":"PPL",
    "gn:name":"Miaozui",
    "gn:population":0,
    "gn:timezone":"Asia/Shanghai",
    "iso:country":"CN",
    "name:und_x_variant":[
        "\u5e99\u5634"
    ],
    "wof:name":"Miaozui",
    "wof:placetype":"locality"
},
  "geometry": {"coordinates":[105.80387,35.51793],"type":"Point"}
}