{
  "type": "Feature",
  "properties": {
    "gn:admin1_code":"19.0",
    "gn:asciiname":"Zhengyingzi",
    "gn:country_code":"CN",
    "gn:dem":710,
    "gn:feature_class":"P",
    "gn:feature_code":"PPL",
    "gn:name":"Zhengyingzi",
    "gn:population":0,
    "gn:timezone":"Asia/Shanghai",
    "iso:country":"CN",
    "name:zho_x_preferred":[
        "\u90d1\u8425\u5b50"
    ],
    "wof:name":"Zhengyingzi",
    "wof:placetype":"locality"
},
  "geometry": {"coordinates":[119.77661999999999,41.95528],"type":"Point"}
}