{
  "type": "Feature",
  "properties": {
    "gn:admin1_code":"11.0",
    "gn:asciiname":"Luochengmiao",
    "gn:country_code":"CN",
    "gn:dem":123,
    "gn:feature_class":"P",
    "gn:feature_code":"PPL",
    "gn:name":"Luochengmiao",
    "gn:population":0,
    "gn:timezone":"Asia/Shanghai",
    "iso:country":"CN",
    "name:zho_x_preferred":[
        "\u7f57\u57ce\u5e99"
    ],
    "wof:name":"Luochengmiao",
    "wof:placetype":"locality"
},
  "geometry": {"coordinates":[112.19096999999999,27.03812000000001],"type":"Point"}
}