{
  "type": "Feature",
  "properties": {
    "gn:admin1_code":"9",
    "gn:asciiname":"Dalilou",
    "gn:country_code":"CN",
    "gn:dem":49,
    "gn:feature_class":"P",
    "gn:feature_code":"PPL",
    "gn:name":"Dalilou",
    "gn:population":0,
    "gn:timezone":"Asia/Shanghai",
    "iso:country":"CN",
    "name:zho_x_preferred":[
        "\u5927\u674e\u697c"
    ],
    "wof:name":"Dalilou",
    "wof:placetype":"locality"
},
  "geometry": {"coordinates":[115.093,33.8993],"type":"Point"}
}