{
  "type": "Feature",
  "properties": {
    "gn:admin1_code":"4.0",
    "gn:asciiname":"Tanglugang Shi'erzu",
    "gn:country_code":"CN",
    "gn:dem":3,
    "gn:feature_class":"P",
    "gn:feature_code":"PPLF",
    "gn:name":"Tanglugang Shi\u2019erzu",
    "gn:population":0,
    "gn:timezone":"Asia/Shanghai",
    "iso:country":"CN",
    "name:und_x_variant":[
        "Tanglugang Shi\u2019erzu"
    ],
    "name:zho_x_preferred":[
        "\u5858\u82a6\u6e2f\u5341\u4e8c\u7ec4"
    ],
    "wof:name":"Tanglugang Shi'erzu",
    "wof:placetype":"locality"
},
  "geometry": {"coordinates":[119.79953,31.39197],"type":"Point"}
}