{
  "type": "Feature",
  "properties": {
    "gn:admin1_code":"29.0",
    "gn:asciiname":"Longyuancun",
    "gn:country_code":"CN",
    "gn:dem":1917,
    "gn:feature_class":"P",
    "gn:feature_code":"PPL",
    "gn:name":"Longyuancun",
    "gn:population":0,
    "gn:timezone":"Asia/Shanghai",
    "iso:country":"CN",
    "name:zho_x_preferred":[
        "\u9f99\u9662\u6751"
    ],
    "wof:name":"Longyuancun",
    "wof:placetype":"locality"
},
  "geometry": {"coordinates":[103.09699999999999,25.4085],"type":"Point"}
}