{
  "type": "Feature",
  "properties": {
    "gn:admin1_code":"7",
    "gn:asciiname":"Putianxianlinyemiaopu",
    "gn:country_code":"CN",
    "gn:dem":388,
    "gn:feature_class":"P",
    "gn:feature_code":"PPLF",
    "gn:name":"Putianxianlinyemiaopu",
    "gn:population":0,
    "gn:timezone":"Asia/Shanghai",
    "iso:country":"CN",
    "wof:name":"Putianxianlinyemiaopu",
    "wof:placetype":"locality"
},
  "geometry": {"coordinates":[118.97,25.71417000000001],"type":"Point"}
}