{
  "type": "Feature",
  "properties": {
    "gn:admin1_code":"8.0",
    "gn:asciiname":"Dongfangcun",
    "gn:country_code":"CN",
    "gn:dem":150,
    "gn:feature_class":"P",
    "gn:feature_code":"PPL",
    "gn:name":"Dongfangcun",
    "gn:population":0,
    "gn:timezone":"Asia/Shanghai",
    "iso:country":"CN",
    "name:zho_x_preferred":[
        "\u4e1c\u65b9\u6751"
    ],
    "wof:name":"Dongfangcun",
    "wof:placetype":"locality"
},
  "geometry": {"coordinates":[128.26857999999999,45.91994],"type":"Point"}
}