{
  "type": "Feature",
  "properties": {
    "gn:admin1_code":"32.0",
    "gn:asciiname":"Gexi",
    "gn:country_code":"CN",
    "gn:dem":305,
    "gn:feature_class":"P",
    "gn:feature_code":"PPL",
    "gn:name":"Gexi",
    "gn:population":0,
    "gn:timezone":"Asia/Shanghai",
    "iso:country":"CN",
    "name:zho_x_preferred":[
        "\u9601\u6eaa"
    ],
    "wof:name":"Gexi",
    "wof:placetype":"locality"
},
  "geometry": {"coordinates":[107.434,31.1847],"type":"Point"}
}