{
  "type": "Feature",
  "properties": {
    "gn:admin1_code":"11.0",
    "gn:asciiname":"Lijiatian",
    "gn:country_code":"CN",
    "gn:dem":578,
    "gn:feature_class":"P",
    "gn:feature_code":"PPL",
    "gn:name":"Lijiatian",
    "gn:population":0,
    "gn:timezone":"Asia/Shanghai",
    "iso:country":"CN",
    "name:zho_x_preferred":[
        "\u674e\u5bb6\u7530"
    ],
    "wof:name":"Lijiatian",
    "wof:placetype":"locality"
},
  "geometry": {"coordinates":[113.82868000000001,29.05693],"type":"Point"}
}