{
  "type": "Feature",
  "properties": {
    "gn:admin1_code":"5.0",
    "gn:asciiname":"Huanxincun",
    "gn:country_code":"CN",
    "gn:dem":132,
    "gn:feature_class":"P",
    "gn:feature_code":"PPL",
    "gn:name":"Huanxincun",
    "gn:population":0,
    "gn:timezone":"Asia/Shanghai",
    "iso:country":"CN",
    "name:zho_x_preferred":[
        "\u7115\u65b0\u6751"
    ],
    "wof:name":"Huanxincun",
    "wof:placetype":"locality"
},
  "geometry": {"coordinates":[123.93204,45.68767],"type":"Point"}
}