{
  "type": "Feature",
  "properties": {
    "gn:admin1_code":"19.0",
    "gn:asciiname":"Xiyangdi",
    "gn:country_code":"CN",
    "gn:dem":18,
    "gn:feature_class":"P",
    "gn:feature_code":"PPL",
    "gn:name":"Xiyangdi",
    "gn:population":0,
    "gn:timezone":"Asia/Shanghai",
    "iso:country":"CN",
    "name:und_x_variant":[
        "Xiyang"
    ],
    "name:zho_x_preferred":[
        "\u897f\u6768\u5e95"
    ],
    "wof:name":"Xiyangdi",
    "wof:placetype":"locality"
},
  "geometry": {"coordinates":[121.82136,39.88819],"type":"Point"}
}