{
  "type": "Feature",
  "properties": {
    "gn:admin1_code":"23.0",
    "gn:asciiname":"Haichao",
    "gn:country_code":"CN",
    "gn:dem":3,
    "gn:feature_class":"P",
    "gn:feature_code":"PPL",
    "gn:name":"Haichao",
    "gn:population":0,
    "gn:timezone":"Asia/Shanghai",
    "iso:country":"CN",
    "name:und_x_variant":[
        "\u6d77\u6f6e"
    ],
    "wof:name":"Haichao",
    "wof:placetype":"locality"
},
  "geometry": {"coordinates":[121.75903,30.95764],"type":"Point"}
}