{
  "type": "Feature",
  "properties": {
    "gn:admin1_code":"16.0",
    "gn:asciiname":"Laoyefen",
    "gn:country_code":"CN",
    "gn:dem":233,
    "gn:feature_class":"P",
    "gn:feature_code":"PPL",
    "gn:name":"Laoyefen",
    "gn:population":0,
    "gn:timezone":"Asia/Shanghai",
    "iso:country":"CN",
    "name:zho_x_preferred":[
        "\u8001\u7237\u575f"
    ],
    "wof:name":"Laoyefen",
    "wof:placetype":"locality"
},
  "geometry": {"coordinates":[108.29300000000001,24.4565],"type":"Point"}
}