{
  "type": "Feature",
  "properties": {
    "gn:admin1_code":"14.0",
    "gn:asciiname":"Chanaduocun",
    "gn:country_code":"CN",
    "gn:dem":4458,
    "gn:feature_class":"P",
    "gn:feature_code":"PPL",
    "gn:name":"Chanaduocun",
    "gn:population":0,
    "gn:timezone":"Asia/Urumqi",
    "iso:country":"CN",
    "name:zho_x_preferred":[
        "\u67e5\u90a3\u6735\u6751"
    ],
    "wof:name":"Chanaduocun",
    "wof:placetype":"locality"
},
  "geometry": {"coordinates":[92.57513,31.52876],"type":"Point"}
}