{
  "type": "Feature",
  "properties": {
    "gn:admin1_code":"29.0",
    "gn:asciiname":"Baitali",
    "gn:country_code":"CN",
    "gn:dem":2190,
    "gn:feature_class":"P",
    "gn:feature_code":"PPL",
    "gn:name":"Baitali",
    "gn:population":0,
    "gn:timezone":"Asia/Shanghai",
    "iso:country":"CN",
    "name:zho_x_preferred":[
        "\u767d\u5854\u91cc"
    ],
    "wof:name":"Baitali",
    "wof:placetype":"locality"
},
  "geometry": {"coordinates":[100.292,25.5191],"type":"Point"}
}