{
  "type": "Feature",
  "properties": {
    "gn:admin1_code":"19.0",
    "gn:asciiname":"Datai Yanggou",
    "gn:country_code":"CN",
    "gn:dem":77,
    "gn:feature_class":"P",
    "gn:feature_code":"PPL",
    "gn:name":"Datai Yanggou",
    "gn:population":0,
    "gn:timezone":"Asia/Shanghai",
    "iso:country":"CN",
    "name:und_x_variant":[
        "\u5927\u592a\u9633\u6c9f"
    ],
    "wof:name":"Datai Yanggou",
    "wof:placetype":"locality"
},
  "geometry": {"coordinates":[122.1854,40.09992],"type":"Point"}
}