{
  "type": "Feature",
  "properties": {
    "gn:admin1_code":"5.0",
    "gn:asciiname":"Yangyingzicun",
    "gn:country_code":"CN",
    "gn:dem":139,
    "gn:feature_class":"P",
    "gn:feature_code":"PPL",
    "gn:name":"Yangyingzicun",
    "gn:population":0,
    "gn:timezone":"Asia/Shanghai",
    "iso:country":"CN",
    "name:zho_x_preferred":[
        "\u6d0b\u8425\u5b50\u6751"
    ],
    "wof:name":"Yangyingzicun",
    "wof:placetype":"locality"
},
  "geometry": {"coordinates":[123.1469,45.85719],"type":"Point"}
}