{
  "type": "Feature",
  "properties": {
    "gn:admin1_code":"26.0",
    "gn:asciiname":"Yejiapingcun",
    "gn:country_code":"CN",
    "gn:dem":769,
    "gn:feature_class":"P",
    "gn:feature_code":"PPL",
    "gn:name":"Yejiapingcun",
    "gn:population":0,
    "gn:timezone":"Asia/Shanghai",
    "iso:country":"CN",
    "name:zho_x_preferred":[
        "\u53f6\u5bb6\u576a\u6751"
    ],
    "wof:name":"Yejiapingcun",
    "wof:placetype":"locality"
},
  "geometry": {"coordinates":[109.9455,33.82667],"type":"Point"}
}