{
  "type": "Feature",
  "properties": {
    "gn:admin1_code":"32.0",
    "gn:asciiname":"Xiake",
    "gn:country_code":"CN",
    "gn:dem":3514,
    "gn:feature_class":"P",
    "gn:feature_code":"PPL",
    "gn:name":"Xiake",
    "gn:population":0,
    "gn:timezone":"Asia/Shanghai",
    "iso:country":"CN",
    "name:zho_x_preferred":[
        "\u5477\u67ef"
    ],
    "wof:name":"Xiake",
    "wof:placetype":"locality"
},
  "geometry": {"coordinates":[101.15300000000001,31.3894],"type":"Point"}
}