{
  "type": "Feature",
  "properties": {
    "gn:admin1_code":"7",
    "gn:asciiname":"Zhentoushan",
    "gn:country_code":"CN",
    "gn:dem":20,
    "gn:feature_class":"P",
    "gn:feature_code":"PPL",
    "gn:name":"Zhentoushan",
    "gn:population":0,
    "gn:timezone":"Asia/Shanghai",
    "iso:country":"CN",
    "name:zho_x_preferred":[
        "\u6795\u5934\u5c71"
    ],
    "wof:name":"Zhentoushan",
    "wof:placetype":"locality"
},
  "geometry": {"coordinates":[118.86790999999999,25.2805],"type":"Point"}
}