{
  "type": "Feature",
  "properties": {
    "gn:admin1_code":"26.0",
    "gn:asciiname":"Yangjiapingcun",
    "gn:country_code":"CN",
    "gn:dem":806,
    "gn:feature_class":"P",
    "gn:feature_code":"PPL",
    "gn:name":"Yangjiapingcun",
    "gn:population":0,
    "gn:timezone":"Asia/Shanghai",
    "iso:country":"CN",
    "name:zho_x_preferred":[
        "\u6768\u5bb6\u576a\u6751"
    ],
    "wof:name":"Yangjiapingcun",
    "wof:placetype":"locality"
},
  "geometry": {"coordinates":[110.35307,36.93048],"type":"Point"}
}