{
  "type": "Feature",
  "properties": {
    "gn:admin1_code":"13.0",
    "gn:asciiname":"Yapuqiang",
    "gn:country_code":"CN",
    "gn:dem":1596,
    "gn:feature_class":"P",
    "gn:feature_code":"PPL",
    "gn:name":"Yapuqiang",
    "gn:population":0,
    "gn:timezone":"Asia/Shanghai",
    "iso:country":"CN",
    "name:zho_x_preferred":[
        "\u4e9a\u666e\u7f8c"
    ],
    "wof:name":"Yapuqiang",
    "wof:placetype":"locality"
},
  "geometry": {"coordinates":[78.17144999999999,37.46579000000001],"type":"Point"}
}