{
  "type": "Feature",
  "properties": {
    "gn:admin1_code":"9.0",
    "gn:asciiname":"Nanyangji",
    "gn:country_code":"CN",
    "gn:dem":41,
    "gn:feature_class":"P",
    "gn:feature_code":"PPL",
    "gn:name":"Nanyangji",
    "gn:population":0,
    "gn:timezone":"Asia/Shanghai",
    "iso:country":"CN",
    "name:zho_x_preferred":[
        "\u5357\u6768\u96c6"
    ],
    "wof:name":"Nanyangji",
    "wof:placetype":"locality"
},
  "geometry": {"coordinates":[115.27527000000001,33.21098],"type":"Point"}
}