{
  "type": "Feature",
  "properties": {
    "gn:admin1_code":"30.0",
    "gn:asciiname":"Guanglong",
    "gn:country_code":"CN",
    "gn:dem":1,
    "gn:feature_class":"P",
    "gn:feature_code":"PPL",
    "gn:name":"Guanglong",
    "gn:population":0,
    "gn:timezone":"Asia/Shanghai",
    "iso:country":"CN",
    "name:zho_x_preferred":[
        "\u5ee3\u9686"
    ],
    "wof:name":"Guanglong",
    "wof:placetype":"locality"
},
  "geometry": {"coordinates":[113.53662,22.77635],"type":"Point"}
}