{
  "type": "Feature",
  "properties": {
    "gn:admin1_code":"19.0",
    "gn:asciiname":"Huaniu Buzi",
    "gn:country_code":"CN",
    "gn:dem":87,
    "gn:feature_class":"P",
    "gn:feature_code":"PPL",
    "gn:name":"Huaniu Buzi",
    "gn:population":0,
    "gn:timezone":"Asia/Shanghai",
    "iso:country":"CN",
    "name:und_x_variant":[
        "Huaniubaozi",
        "Huaniu Buzi"
    ],
    "name:zho_x_preferred":[
        "\u82b1\u725b\u5821\u5b50"
    ],
    "wof:name":"Huaniu Buzi",
    "wof:placetype":"locality"
},
  "geometry": {"coordinates":[123.521,41.38245],"type":"Point"}
}