{
  "type": "Feature",
  "properties": {
    "gn:admin1_code":"7",
    "gn:asciiname":"Zhujiao",
    "gn:country_code":"CN",
    "gn:dem":33,
    "gn:feature_class":"P",
    "gn:feature_code":"PPL",
    "gn:name":"Zhujiao",
    "gn:population":0,
    "gn:timezone":"Asia/Shanghai",
    "iso:country":"CN",
    "name:und_x_variant":[
        "\u7af9\u811a"
    ],
    "wof:name":"Zhujiao",
    "wof:placetype":"locality"
},
  "geometry": {"coordinates":[118.77831,24.98753],"type":"Point"}
}