{
  "type": "Feature",
  "properties": {
    "gn:admin1_code":"8.0",
    "gn:asciiname":"Qinglecun",
    "gn:country_code":"CN",
    "gn:dem":182,
    "gn:feature_class":"P",
    "gn:feature_code":"PPL",
    "gn:name":"Qinglecun",
    "gn:population":0,
    "gn:timezone":"Asia/Shanghai",
    "iso:country":"CN",
    "name:zho_x_preferred":[
        "\u5e86\u4e50\u6751"
    ],
    "wof:name":"Qinglecun",
    "wof:placetype":"locality"
},
  "geometry": {"coordinates":[126.49012,45.48714],"type":"Point"}
}