{
  "type": "Feature",
  "properties": {
    "gn:admin1_code":"12.0",
    "gn:asciiname":"Xiaozhang'e",
    "gn:country_code":"CN",
    "gn:dem":31,
    "gn:feature_class":"P",
    "gn:feature_code":"PPL",
    "gn:name":"Xiaozhang\u2019e",
    "gn:population":0,
    "gn:timezone":"Asia/Shanghai",
    "iso:country":"CN",
    "name:und_x_variant":[
        "Xiaozhang\u2019e",
        "\u5c0f\u5f20\u9e45"
    ],
    "wof:name":"Xiaozhang'e",
    "wof:placetype":"locality"
},
  "geometry": {"coordinates":[114.60588,30.46587],"type":"Point"}
}