{
  "type": "Feature",
  "properties": {
    "gn:admin1_code":"7.0",
    "gn:asciiname":"Shipaichang",
    "gn:country_code":"CN",
    "gn:dem":624,
    "gn:feature_class":"P",
    "gn:feature_code":"PPL",
    "gn:name":"Shipaichang",
    "gn:population":0,
    "gn:timezone":"Asia/Shanghai",
    "iso:country":"CN",
    "name:zho_x_preferred":[
        "\u77f3\u6392\u573a"
    ],
    "wof:name":"Shipaichang",
    "wof:placetype":"locality"
},
  "geometry": {"coordinates":[117.31977000000001,26.54002],"type":"Point"}
}