{
  "type": "Feature",
  "properties": {
    "gn:admin1_code":"32.0",
    "gn:asciiname":"Qianjiagou",
    "gn:country_code":"CN",
    "gn:dem":415,
    "gn:feature_class":"P",
    "gn:feature_code":"PPL",
    "gn:name":"Qianjiagou",
    "gn:population":0,
    "gn:timezone":"Asia/Shanghai",
    "iso:country":"CN",
    "name:zho_x_preferred":[
        "\u4e7e\u5bb6\u6c9f"
    ],
    "wof:name":"Qianjiagou",
    "wof:placetype":"locality"
},
  "geometry": {"coordinates":[104.901,30.1996],"type":"Point"}
}