{
  "type": "Feature",
  "properties": {
    "gn:admin1_code":"26.0",
    "gn:asciiname":"Liujia Laoyuanzi",
    "gn:country_code":"CN",
    "gn:dem":584,
    "gn:feature_class":"P",
    "gn:feature_code":"PPL",
    "gn:name":"Liujia Laoyuanzi",
    "gn:population":0,
    "gn:timezone":"Asia/Shanghai",
    "iso:country":"CN",
    "name:zho_x_preferred":[
        "\u5218\u5bb6\u8001\u9662\u5b50"
    ],
    "wof:name":"Liujia Laoyuanzi",
    "wof:placetype":"locality"
},
  "geometry": {"coordinates":[108.45066,32.45401],"type":"Point"}
}