{
  "type": "Feature",
  "properties": {
    "gn:admin1_code":"32.0",
    "gn:asciiname":"Bajiazhai",
    "gn:country_code":"CN",
    "gn:dem":3093,
    "gn:feature_class":"P",
    "gn:feature_code":"PPL",
    "gn:name":"Bajiazhai",
    "gn:population":0,
    "gn:timezone":"Asia/Shanghai",
    "iso:country":"CN",
    "name:zho_x_preferred":[
        "\u516b\u5bb6\u5be8"
    ],
    "wof:name":"Bajiazhai",
    "wof:placetype":"locality"
},
  "geometry": {"coordinates":[102.223,31.0688],"type":"Point"}
}