{
  "type": "Feature",
  "properties": {
    "gn:admin1_code":"10",
    "gn:asciiname":"Haisu Gounao",
    "gn:country_code":"CN",
    "gn:dem":881,
    "gn:feature_class":"P",
    "gn:feature_code":"PPL",
    "gn:name":"Haisu Gounao",
    "gn:population":0,
    "gn:timezone":"Asia/Shanghai",
    "iso:country":"CN",
    "name:zho_x_preferred":[
        "\u6d77\u82cf\u6c9f\u8111"
    ],
    "wof:name":"Haisu Gounao",
    "wof:placetype":"locality"
},
  "geometry": {"coordinates":[116.96548,41.37295],"type":"Point"}
}