{
  "type": "Feature",
  "properties": {
    "gn:admin1_code":"19.0",
    "gn:asciiname":"Erdaogouzicun",
    "gn:country_code":"CN",
    "gn:dem":221,
    "gn:feature_class":"P",
    "gn:feature_code":"PPL",
    "gn:name":"Erdaogouzicun",
    "gn:population":0,
    "gn:timezone":"Asia/Shanghai",
    "iso:country":"CN",
    "name:zho_x_preferred":[
        "\u4e8c\u9053\u6c9f\u5b50\u6751"
    ],
    "wof:name":"Erdaogouzicun",
    "wof:placetype":"locality"
},
  "geometry": {"coordinates":[122.07599999999999,42.6586],"type":"Point"}
}