{
  "type": "Feature",
  "properties": {
    "gn:admin1_code":"29.0",
    "gn:asciiname":"Zhujihe",
    "gn:country_code":"CN",
    "gn:dem":2163,
    "gn:feature_class":"P",
    "gn:feature_code":"PPL",
    "gn:name":"Zhujihe",
    "gn:population":0,
    "gn:timezone":"Asia/Shanghai",
    "iso:country":"CN",
    "name:und_x_variant":[
        "\u7af9\u9e21\u6cb3"
    ],
    "wof:name":"Zhujihe",
    "wof:placetype":"locality"
},
  "geometry": {"coordinates":[103.86166,25.8781],"type":"Point"}
}