{
  "type": "Feature",
  "properties": {
    "gn:admin1_code":"9.0",
    "gn:asciiname":"Chenjia",
    "gn:country_code":"CN",
    "gn:dem":294,
    "gn:feature_class":"P",
    "gn:feature_code":"PPL",
    "gn:name":"Chenjia",
    "gn:population":0,
    "gn:timezone":"Asia/Shanghai",
    "iso:country":"CN",
    "name:und_x_variant":[
        "\u9648\u5bb6",
        "Chenjia"
    ],
    "wof:name":"Chenjia",
    "wof:placetype":"locality"
},
  "geometry": {"coordinates":[112.21207,33.09338],"type":"Point"}
}