{
  "type": "Feature",
  "properties": {
    "gn:admin1_code":"26.0",
    "gn:asciiname":"Houyanjiamiao",
    "gn:country_code":"CN",
    "gn:dem":1633,
    "gn:feature_class":"P",
    "gn:feature_code":"PPL",
    "gn:name":"Houyanjiamiao",
    "gn:population":0,
    "gn:timezone":"Asia/Shanghai",
    "iso:country":"CN",
    "name:zho_x_preferred":[
        "\u540e\u960e\u5bb6\u5e99"
    ],
    "wof:name":"Houyanjiamiao",
    "wof:placetype":"locality"
},
  "geometry": {"coordinates":[108.73049,37.12231],"type":"Point"}
}