{
  "type": "Feature",
  "properties": {
    "gn:admin1_code":"14.0",
    "gn:asciiname":"Xinkacun",
    "gn:country_code":"CN",
    "gn:dem":4083,
    "gn:feature_class":"P",
    "gn:feature_code":"PPL",
    "gn:name":"Xinkacun",
    "gn:population":0,
    "gn:timezone":"Asia/Urumqi",
    "iso:country":"CN",
    "name:zho_x_preferred":[
        "\u65b0\u5361\u6751"
    ],
    "wof:name":"Xinkacun",
    "wof:placetype":"locality"
},
  "geometry": {"coordinates":[97.44413,30.9097],"type":"Point"}
}