{
  "type": "Feature",
  "properties": {
    "gn:admin1_code":"32.0",
    "gn:asciiname":"Lanmaqiang",
    "gn:country_code":"CN",
    "gn:dem":1194,
    "gn:feature_class":"P",
    "gn:feature_code":"PPL",
    "gn:name":"Lanmaqiang",
    "gn:population":0,
    "gn:timezone":"Asia/Shanghai",
    "iso:country":"CN",
    "name:zho_x_preferred":[
        "\u62e6\u9a6c\u5899"
    ],
    "wof:name":"Lanmaqiang",
    "wof:placetype":"locality"
},
  "geometry": {"coordinates":[104.297,31.8507],"type":"Point"}
}