{
  "type": "Feature",
  "properties": {
    "gn:admin1_code":"16",
    "gn:asciiname":"Nawang",
    "gn:cc2":"CN",
    "gn:country_code":"CN",
    "gn:dem":714,
    "gn:feature_class":"P",
    "gn:feature_code":"PPL",
    "gn:name":"Nawang",
    "gn:population":0,
    "gn:timezone":"Asia/Shanghai",
    "iso:country":"CN",
    "name:und_x_variant":[
        "Na-mo-t\u2019un",
        "Nawang"
    ],
    "wof:name":"Nawang",
    "wof:placetype":"locality"
},
  "geometry": {"coordinates":[106.26111000000002,23.56028],"type":"Point"}
}