{
  "type": "Feature",
  "properties": {
    "gn:admin1_code":"3.0",
    "gn:asciiname":"Xiao'ao",
    "gn:country_code":"CN",
    "gn:dem":328,
    "gn:feature_class":"P",
    "gn:feature_code":"PPL",
    "gn:name":"Xiao\u2019ao",
    "gn:population":0,
    "gn:timezone":"Asia/Shanghai",
    "iso:country":"CN",
    "name:ind_x_preferred":[
        "Xiao'ao"
    ],
    "name:kor_x_preferred":[
        "\ucd08 \uc18c\uc624"
    ],
    "name:und_x_variant":[
        "Xiao\u2019ao"
    ],
    "name:zho_x_preferred":[
        "\u5c0f\u5773"
    ],
    "wof:name":"Xiao'ao",
    "wof:placetype":"locality"
},
  "geometry": {"coordinates":[114.44199999999999,28.9549],"type":"Point"}
}