{
  "type": "Feature",
  "properties": {
    "gn:admin1_code":"31",
    "gn:asciiname":"Wushi Nongchang Lingtiandui",
    "gn:country_code":"CN",
    "gn:dem":327,
    "gn:feature_class":"P",
    "gn:feature_code":"PPLF",
    "gn:name":"Wushi Nongchang Lingtiandui",
    "gn:population":0,
    "gn:timezone":"Asia/Shanghai",
    "iso:country":"CN",
    "name:und_x_variant":[
        "\u4e4c\u77f3\u519c\u573a\u5cad\u7530\u961f",
        "Yifenqu",
        "\u4e00\u5206\u533a"
    ],
    "wof:name":"Wushi Nongchang Lingtiandui",
    "wof:placetype":"locality"
},
  "geometry": {"coordinates":[109.84739999999999,19.17136],"type":"Point"}
}