{
  "type": "Feature",
  "properties": {
    "gn:admin1_code":"32.0",
    "gn:asciiname":"Maomiaozi",
    "gn:country_code":"CN",
    "gn:dem":473,
    "gn:feature_class":"P",
    "gn:feature_code":"PPL",
    "gn:name":"Maomiaozi",
    "gn:population":0,
    "gn:timezone":"Asia/Shanghai",
    "iso:country":"CN",
    "name:zho_x_preferred":[
        "\u8305\u5e99\u5b50"
    ],
    "wof:name":"Maomiaozi",
    "wof:placetype":"locality"
},
  "geometry": {"coordinates":[106.173,31.7878],"type":"Point"}
}