{
  "type": "Feature",
  "properties": {
    "gn:admin1_code":"15.0",
    "gn:asciiname":"Louyuanzhuang",
    "gn:country_code":"CN",
    "gn:dem":2202,
    "gn:feature_class":"P",
    "gn:feature_code":"PPL",
    "gn:name":"Louyuanzhuang",
    "gn:population":0,
    "gn:timezone":"Asia/Shanghai",
    "iso:country":"CN",
    "name:zho_x_preferred":[
        "\u697c\u9662\u5e84"
    ],
    "wof:name":"Louyuanzhuang",
    "wof:placetype":"locality"
},
  "geometry": {"coordinates":[101.11499999999999,38.4961],"type":"Point"}
}