{
  "type": "Feature",
  "properties": {
    "gn:admin1_code":"12.0",
    "gn:asciiname":"Hongyanziping",
    "gn:country_code":"CN",
    "gn:dem":1462,
    "gn:feature_class":"P",
    "gn:feature_code":"PPL",
    "gn:name":"Hongyanziping",
    "gn:population":0,
    "gn:timezone":"Asia/Shanghai",
    "iso:country":"CN",
    "name:zho_x_preferred":[
        "\u7ea2\u5ca9\u5b50\u576a"
    ],
    "wof:name":"Hongyanziping",
    "wof:placetype":"locality"
},
  "geometry": {"coordinates":[111.33696999999999,31.71393],"type":"Point"}
}