{
  "type": "Feature",
  "properties": {
    "gn:admin1_code":"15.0",
    "gn:asciiname":"Mabu",
    "gn:country_code":"CN",
    "gn:dem":2038,
    "gn:feature_class":"P",
    "gn:feature_code":"PPL",
    "gn:name":"Mabu",
    "gn:population":0,
    "gn:timezone":"Asia/Shanghai",
    "iso:country":"CN",
    "name:ceb_x_preferred":[
        "Mabu"
    ],
    "name:rus_x_preferred":[
        "\u041c\u0430\u0431\u0443"
    ],
    "name:swe_x_preferred":[
        "Mabu"
    ],
    "name:und_x_variant":[
        "\u9a6c\u535c"
    ],
    "wof:name":"Mabu",
    "wof:placetype":"locality"
},
  "geometry": {"coordinates":[104.61859,34.76237],"type":"Point"}
}