{
  "type": "Feature",
  "properties": {
    "gn:admin1_code":"11.0",
    "gn:asciiname":"Liumuqiao",
    "gn:country_code":"CN",
    "gn:dem":43,
    "gn:feature_class":"P",
    "gn:feature_code":"PPL",
    "gn:name":"Liumuqiao",
    "gn:population":0,
    "gn:timezone":"Asia/Shanghai",
    "iso:country":"CN",
    "name:zho_x_preferred":[
        "\u67f3\u6728\u6865"
    ],
    "wof:name":"Liumuqiao",
    "wof:placetype":"locality"
},
  "geometry": {"coordinates":[112.90998999999999,28.6417],"type":"Point"}
}