{
  "type": "Feature",
  "properties": {
    "gn:admin1_code":"16.0",
    "gn:asciiname":"Dongzhai",
    "gn:country_code":"CN",
    "gn:dem":390,
    "gn:feature_class":"P",
    "gn:feature_code":"PPL",
    "gn:name":"Dongzhai",
    "gn:population":0,
    "gn:timezone":"Asia/Shanghai",
    "iso:country":"CN",
    "name:zho_x_preferred":[
        "\u5cd2\u5be8"
    ],
    "wof:name":"Dongzhai",
    "wof:placetype":"locality"
},
  "geometry": {"coordinates":[108.033,25.137],"type":"Point"}
}