{
  "type": "Feature",
  "properties": {
    "gn:admin1_code":"16",
    "gn:asciiname":"Chewan",
    "gn:country_code":"CN",
    "gn:dem":287,
    "gn:feature_class":"P",
    "gn:feature_code":"PPL",
    "gn:name":"Chewan",
    "gn:population":0,
    "gn:timezone":"Asia/Shanghai",
    "iso:country":"CN",
    "name:zho_x_preferred":[
        "\u8f66\u6e7e"
    ],
    "wof:name":"Chewan",
    "wof:placetype":"locality"
},
  "geometry": {"coordinates":[110.121,24.8803],"type":"Point"}
}