{
  "type": "Feature",
  "properties": {
    "gn:admin1_code":"32.0",
    "gn:asciiname":"Fenbatou",
    "gn:country_code":"CN",
    "gn:dem":349,
    "gn:feature_class":"P",
    "gn:feature_code":"PPL",
    "gn:name":"Fenbatou",
    "gn:population":0,
    "gn:timezone":"Asia/Shanghai",
    "iso:country":"CN",
    "name:zho_x_preferred":[
        "\u575f\u575d\u5934"
    ],
    "wof:name":"Fenbatou",
    "wof:placetype":"locality"
},
  "geometry": {"coordinates":[104.52200000000001,28.7177],"type":"Point"}
}