{
  "type": "Feature",
  "properties": {
    "gn:admin1_code":"29.0",
    "gn:asciiname":"Kemeizi",
    "gn:country_code":"CN",
    "gn:dem":2529,
    "gn:feature_class":"P",
    "gn:feature_code":"PPL",
    "gn:name":"Kemeizi",
    "gn:population":0,
    "gn:timezone":"Asia/Shanghai",
    "iso:country":"CN",
    "name:zho_x_preferred":[
        "\u53ef\u7f8e\u5b50"
    ],
    "wof:name":"Kemeizi",
    "wof:placetype":"locality"
},
  "geometry": {"coordinates":[100.44499999999999,27.2276],"type":"Point"}
}