{
  "type": "Feature",
  "properties": {
    "gn:admin1_code":"16.0",
    "gn:asciiname":"Huang'an",
    "gn:country_code":"CN",
    "gn:dem":108,
    "gn:feature_class":"P",
    "gn:feature_code":"PPL",
    "gn:name":"Huang\u2019an",
    "gn:population":0,
    "gn:timezone":"Asia/Shanghai",
    "iso:country":"CN",
    "name:und_x_variant":[
        "Huang\u2019an"
    ],
    "name:zho_x_preferred":[
        "\u9ec4\u5b89"
    ],
    "wof:name":"Huang'an",
    "wof:placetype":"locality"
},
  "geometry": {"coordinates":[108.871,23.2135],"type":"Point"}
}