{
  "type": "Feature",
  "properties": {
    "gn:admin1_code":"32.0",
    "gn:asciiname":"Yidiguo",
    "gn:country_code":"CN",
    "gn:dem":1862,
    "gn:feature_class":"P",
    "gn:feature_code":"PPL",
    "gn:name":"Yidiguo",
    "gn:population":0,
    "gn:timezone":"Asia/Shanghai",
    "iso:country":"CN",
    "name:zho_x_preferred":[
        "\u8863\u5e95\u679c"
    ],
    "wof:name":"Yidiguo",
    "wof:placetype":"locality"
},
  "geometry": {"coordinates":[102.78700000000001,29.1307],"type":"Point"}
}