{
  "type": "Feature",
  "properties": {
    "gn:admin1_code":"32.0",
    "gn:asciiname":"Tianjing",
    "gn:country_code":"CN",
    "gn:dem":518,
    "gn:feature_class":"P",
    "gn:feature_code":"PPL",
    "gn:name":"Tianjing",
    "gn:population":0,
    "gn:timezone":"Asia/Shanghai",
    "iso:country":"CN",
    "name:fra_x_preferred":[
        "Tianjing"
    ],
    "name:vie_x_preferred":[
        "Thi\u00ean Kinh"
    ],
    "name:zho_x_preferred":[
        "\u5929\u4e95"
    ],
    "wof:name":"Tianjing",
    "wof:placetype":"locality"
},
  "geometry": {"coordinates":[105.52500000000001,31.661],"type":"Point"}
}