{
  "type": "Feature",
  "properties": {
    "gn:admin1_code":"12.0",
    "gn:asciiname":"Zhujiacaochang",
    "gn:country_code":"CN",
    "gn:dem":74,
    "gn:feature_class":"P",
    "gn:feature_code":"PPL",
    "gn:name":"Zhujiacaochang",
    "gn:population":0,
    "gn:timezone":"Asia/Shanghai",
    "iso:country":"CN",
    "name:zho_x_preferred":[
        "\u6731\u5bb6\u64cd\u573a"
    ],
    "wof:name":"Zhujiacaochang",
    "wof:placetype":"locality"
},
  "geometry": {"coordinates":[112.33753,31.43013],"type":"Point"}
}