{
  "type": "Feature",
  "properties": {
    "gn:admin1_code":"15.0",
    "gn:asciiname":"Yanglangou",
    "gn:country_code":"CN",
    "gn:dem":1549,
    "gn:feature_class":"P",
    "gn:feature_code":"PPL",
    "gn:name":"Yanglangou",
    "gn:population":0,
    "gn:timezone":"Asia/Shanghai",
    "iso:country":"CN",
    "name:zho_x_preferred":[
        "\u7f8a\u680f\u6c9f"
    ],
    "wof:name":"Yanglangou",
    "wof:placetype":"locality"
},
  "geometry": {"coordinates":[106.69799999999999,35.2124],"type":"Point"}
}