{
  "type": "Feature",
  "properties": {
    "gn:admin1_code":"32.0",
    "gn:asciiname":"Liyupobei",
    "gn:country_code":"CN",
    "gn:dem":1864,
    "gn:feature_class":"P",
    "gn:feature_code":"PPL",
    "gn:name":"Liyupobei",
    "gn:population":0,
    "gn:timezone":"Asia/Shanghai",
    "iso:country":"CN",
    "name:zho_x_preferred":[
        "\u9ca4\u9c7c\u7834\u80cc"
    ],
    "wof:name":"Liyupobei",
    "wof:placetype":"locality"
},
  "geometry": {"coordinates":[101.52891,26.75646],"type":"Point"}
}