{
  "type": "Feature",
  "properties": {
    "gn:admin1_code":"16.0",
    "gn:asciiname":"Wang'ang",
    "gn:country_code":"CN",
    "gn:dem":403,
    "gn:feature_class":"P",
    "gn:feature_code":"PPL",
    "gn:name":"Wang\u2019ang",
    "gn:population":0,
    "gn:timezone":"Asia/Shanghai",
    "iso:country":"CN",
    "name:und_x_variant":[
        "Wang\u2019ang"
    ],
    "name:zho_x_preferred":[
        "\u738b\u76ce"
    ],
    "wof:name":"Wang'ang",
    "wof:placetype":"locality"
},
  "geometry": {"coordinates":[107.46599999999999,22.8226],"type":"Point"}
}