{
  "type": "Feature",
  "properties": {
    "gn:admin1_code":"4.0",
    "gn:asciiname":"Shiqiaotou",
    "gn:country_code":"CN",
    "gn:dem":0,
    "gn:feature_class":"P",
    "gn:feature_code":"PPL",
    "gn:name":"Shiqiaotou",
    "gn:population":0,
    "gn:timezone":"Asia/Shanghai",
    "iso:country":"CN",
    "name:und_x_variant":[
        "\u77f3\u6865\u5934"
    ],
    "wof:name":"Shiqiaotou",
    "wof:placetype":"locality"
},
  "geometry": {"coordinates":[119.95272,33.50745999999999],"type":"Point"}
}