{
  "type": "Feature",
  "properties": {
    "gn:admin1_code":"15",
    "gn:asciiname":"Zhangli",
    "gn:country_code":"CN",
    "gn:dem":1861,
    "gn:feature_class":"P",
    "gn:feature_code":"PPL",
    "gn:name":"Zhangli",
    "gn:population":0,
    "gn:timezone":"Asia/Shanghai",
    "iso:country":"CN",
    "name:zho_x_preferred":[
        "\u638c\u91cc"
    ],
    "wof:name":"Zhangli",
    "wof:placetype":"locality"
},
  "geometry": {"coordinates":[105.295,36.0209],"type":"Point"}
}