{
  "type": "Feature",
  "properties": {
    "gn:admin1_code":"25",
    "gn:asciiname":"Gulou",
    "gn:country_code":"CN",
    "gn:dem":41,
    "gn:feature_class":"P",
    "gn:feature_code":"PPLA3",
    "gn:name":"Gulou",
    "gn:population":0,
    "gn:timezone":"Asia/Shanghai",
    "iso:country":"CN",
    "name:ceb_x_preferred":[
        "Gulou"
    ],
    "name:deu_x_preferred":[
        "Gulou"
    ],
    "name:eus_x_preferred":[
        "Gulou"
    ],
    "name:fra_x_preferred":[
        "Gulou"
    ],
    "name:jpn_x_preferred":[
        "\u9f13\u697c\u533a"
    ],
    "name:kor_x_preferred":[
        "\uad6c\ub7ec\uc6b0\uad6c"
    ],
    "name:nor_x_preferred":[
        "Gulou"
    ],
    "name:rus_x_preferred":[
        "\u0413\u0443\u043b\u043e\u0443"
    ],
    "name:swe_x_preferred":[
        "Gulou"
    ],
    "name:und_x_variant":[
        "Dongchangfu Qu",
        "Dongchangfu"
    ],
    "name:vie_x_preferred":[
        "C\u1ed5 L\u00e2u"
    ],
    "name:zho_x_preferred":[
        "\u53e4\u697c"
    ],
    "name:zho_x_variant":[
        "\u4e1c\u660c\u5e9c\u533a",
        "\u4e1c\u660c\u5e9c",
        "\u9f13\u697c\u533a"
    ],
    "wof:name":"Gulou",
    "wof:placetype":"locality"
},
  "geometry": {"coordinates":[115.96418,36.44414],"type":"Point"}
}