{
  "type": "Feature",
  "properties": {
    "gn:admin1_code":"25",
    "gn:asciiname":"Gulou",
    "gn:country_code":"CN",
    "gn:dem":41,
    "gn:feature_class":"P",
    "gn:feature_code":"PPLA3",
    "gn:name":"Gulou",
    "gn:population":0,
    "gn:timezone":"Asia/Shanghai",
    "iso:country":"CN",
    "name:und_x_variant":[
        "Dongchangfu Qu",
        "Dongchangfu"
    ],
    "name:zho_x_preferred":[
        "\u53e4\u697c"
    ],
    "name:zho_x_variant":[
        "\u4e1c\u660c\u5e9c\u533a",
        "\u4e1c\u660c\u5e9c"
    ],
    "wof:name":"Gulou",
    "wof:placetype":"locality"
},
  "geometry": {"coordinates":[115.96418,36.44414],"type":"Point"}
}