{
  "type": "Feature",
  "properties": {
    "gn:admin1_code":"15.0",
    "gn:asciiname":"Shicao",
    "gn:country_code":"CN",
    "gn:dem":1091,
    "gn:feature_class":"P",
    "gn:feature_code":"PPL",
    "gn:name":"Shicao",
    "gn:population":0,
    "gn:timezone":"Asia/Urumqi",
    "iso:country":"CN",
    "name:zho_x_preferred":[
        "\u77f3\u69fd"
    ],
    "wof:name":"Shicao",
    "wof:placetype":"locality"
},
  "geometry": {"coordinates":[94.7504,40.2777],"type":"Point"}
}