{
  "type": "Feature",
  "properties": {
    "gn:admin1_code":"21.0",
    "gn:asciiname":"Wei'er Zhuangzi",
    "gn:country_code":"CN",
    "gn:dem":1644,
    "gn:feature_class":"P",
    "gn:feature_code":"PPL",
    "gn:name":"Wei\u2019er Zhuangzi",
    "gn:population":0,
    "gn:timezone":"Asia/Shanghai",
    "iso:country":"CN",
    "name:und_x_variant":[
        "Wei\u2019er Zhuangzi"
    ],
    "name:zho_x_preferred":[
        "\u9b4f\u513f\u5e84\u5b50"
    ],
    "wof:name":"Wei'er Zhuangzi",
    "wof:placetype":"locality"
},
  "geometry": {"coordinates":[106.44199999999999,37.0696],"type":"Point"}
}