{
  "type": "Feature",
  "properties": {
    "gn:admin1_code":"5.0",
    "gn:asciiname":"Shenzijing",
    "gn:country_code":"CN",
    "gn:dem":151,
    "gn:feature_class":"P",
    "gn:feature_code":"PPL",
    "gn:name":"Shenzijing",
    "gn:population":0,
    "gn:timezone":"Asia/Shanghai",
    "iso:country":"CN",
    "name:zho_x_preferred":[
        "\u614e\u5b57\u4e95"
    ],
    "wof:name":"Shenzijing",
    "wof:placetype":"locality"
},
  "geometry": {"coordinates":[123.8623,44.82232],"type":"Point"}
}