{
  "type": "Feature",
  "properties": {
    "gn:admin1_code":"18",
    "gn:asciiname":"Qingtongyuan",
    "gn:country_code":"CN",
    "gn:dem":982,
    "gn:feature_class":"P",
    "gn:feature_code":"PPL",
    "gn:name":"Qingtongyuan",
    "gn:population":0,
    "gn:timezone":"Asia/Shanghai",
    "iso:country":"CN",
    "name:zho_x_preferred":[
        "\u9752\u6850\u56ed"
    ],
    "wof:name":"Qingtongyuan",
    "wof:placetype":"locality"
},
  "geometry": {"coordinates":[108.07599999999999,28.7065],"type":"Point"}
}