{
  "type": "Feature",
  "properties": {
    "gn:admin1_code":"7.0",
    "gn:asciiname":"Qianban",
    "gn:country_code":"CN",
    "gn:dem":1156,
    "gn:feature_class":"P",
    "gn:feature_code":"PPL",
    "gn:name":"Qianban",
    "gn:population":0,
    "gn:timezone":"Asia/Shanghai",
    "iso:country":"CN",
    "name:zho_x_preferred":[
        "\u524d\u5742"
    ],
    "wof:name":"Qianban",
    "wof:placetype":"locality"
},
  "geometry": {"coordinates":[118.87842999999999,26.99246],"type":"Point"}
}