{
  "type": "Feature",
  "properties": {
    "gn:admin1_code":"4.0",
    "gn:asciiname":"Shuangxu",
    "gn:country_code":"CN",
    "gn:dem":3,
    "gn:feature_class":"P",
    "gn:feature_code":"PPL",
    "gn:name":"Shuangxu",
    "gn:population":0,
    "gn:timezone":"Asia/Shanghai",
    "iso:country":"CN",
    "name:zho_x_preferred":[
        "Shuangxu"
    ],
    "name:zho_x_variant":[
        "\u53cc\u5f90"
    ],
    "wof:name":"Shuangxu",
    "wof:placetype":"locality"
},
  "geometry": {"coordinates":[119.69537,33.8667],"type":"Point"}
}