{
  "type": "Feature",
  "properties": {
    "gn:admin1_code":"12.0",
    "gn:asciiname":"Chaoyangguan",
    "gn:country_code":"CN",
    "gn:dem":121,
    "gn:feature_class":"P",
    "gn:feature_code":"PPL",
    "gn:name":"Chaoyangguan",
    "gn:population":0,
    "gn:timezone":"Asia/Shanghai",
    "iso:country":"CN",
    "name:zho_x_preferred":[
        "Chaoyangguan"
    ],
    "name:zho_x_variant":[
        "\u671d\u9633\u89c2"
    ],
    "wof:name":"Chaoyangguan",
    "wof:placetype":"locality"
},
  "geometry": {"coordinates":[111.65197999999999,30.18033],"type":"Point"}
}