{
  "type": "Feature",
  "properties": {
    "gn:admin1_code":"15.0",
    "gn:asciiname":"Wangjiaxiahe",
    "gn:country_code":"CN",
    "gn:dem":1556,
    "gn:feature_class":"P",
    "gn:feature_code":"PPL",
    "gn:name":"Wangjiaxiahe",
    "gn:population":0,
    "gn:timezone":"Asia/Shanghai",
    "iso:country":"CN",
    "name:und_x_variant":[
        "\u738b\u5bb6\u4e0b\u6cb3"
    ],
    "name:zho_x_preferred":[
        "\u738b\u5bb6\u4e0b\u6cb3"
    ],
    "wof:name":"Wangjiaxiahe",
    "wof:placetype":"locality"
},
  "geometry": {"coordinates":[104.92563,33.82285],"type":"Point"}
}