{
  "type": "Feature",
  "properties": {
    "gn:admin1_code":"8.0",
    "gn:asciiname":"Shuangshengcun",
    "gn:country_code":"CN",
    "gn:dem":207,
    "gn:feature_class":"P",
    "gn:feature_code":"PPL",
    "gn:name":"Shuangshengcun",
    "gn:population":0,
    "gn:timezone":"Asia/Shanghai",
    "iso:country":"CN",
    "name:zho_x_preferred":[
        "\u53cc\u80dc\u6751"
    ],
    "wof:name":"Shuangshengcun",
    "wof:placetype":"locality"
},
  "geometry": {"coordinates":[126.71193,47.12713],"type":"Point"}
}