{
  "type": "Feature",
  "properties": {
    "gn:admin1_code":"25",
    "gn:asciiname":"Zhengjiamatou",
    "gn:country_code":"CN",
    "gn:dem":24,
    "gn:feature_class":"P",
    "gn:feature_code":"PPL",
    "gn:name":"Zhengjiamatou",
    "gn:population":0,
    "gn:timezone":"Asia/Shanghai",
    "iso:country":"CN",
    "name:zho_x_preferred":[
        "\u90d1\u5bb6\u7801\u5934"
    ],
    "wof:name":"Zhengjiamatou",
    "wof:placetype":"locality"
},
  "geometry": {"coordinates":[117.39400000000001,36.8736],"type":"Point"}
}