{
  "type": "Feature",
  "properties": {
    "gn:admin1_code":"30.0",
    "gn:asciiname":"Zhangge",
    "gn:country_code":"CN",
    "gn:dem":43,
    "gn:feature_class":"P",
    "gn:feature_code":"PPL",
    "gn:name":"Zhangge",
    "gn:population":0,
    "gn:timezone":"Asia/Shanghai",
    "iso:country":"CN",
    "name:zho_x_preferred":[
        "\u7ae0\u9601"
    ],
    "wof:name":"Zhangge",
    "wof:placetype":"locality"
},
  "geometry": {"coordinates":[114.0117,22.75065],"type":"Point"}
}