{
  "type": "Feature",
  "properties": {
    "gn:admin1_code":"32.0",
    "gn:asciiname":"Xuefangcun",
    "gn:country_code":"CN",
    "gn:dem":2036,
    "gn:feature_class":"P",
    "gn:feature_code":"PPL",
    "gn:name":"Xuefangcun",
    "gn:population":0,
    "gn:timezone":"Asia/Shanghai",
    "iso:country":"CN",
    "name:zho_x_preferred":[
        "\u5b66\u623f\u6751"
    ],
    "wof:name":"Xuefangcun",
    "wof:placetype":"locality"
},
  "geometry": {"coordinates":[102.3245,26.76017],"type":"Point"}
}