{
  "type": "Feature",
  "properties": {
    "gn:admin1_code":"30",
    "gn:asciiname":"Lianhexu",
    "gn:country_code":"CN",
    "gn:dem":12,
    "gn:feature_class":"P",
    "gn:feature_code":"PPL",
    "gn:name":"Lianhexu",
    "gn:population":0,
    "gn:timezone":"Asia/Shanghai",
    "iso:country":"CN",
    "name:und_x_variant":[
        "Lien-ho",
        "Lianhexu"
    ],
    "name:zho_x_preferred":[
        "\u8054\u548c\u5729"
    ],
    "wof:name":"Lianhexu",
    "wof:placetype":"locality"
},
  "geometry": {"coordinates":[113.90976000000001,23.23869],"type":"Point"}
}