{
  "type": "Feature",
  "properties": {
    "gn:admin1_code":"26.0",
    "gn:asciiname":"Qunantang",
    "gn:country_code":"CN",
    "gn:dem":1585,
    "gn:feature_class":"P",
    "gn:feature_code":"PPL",
    "gn:name":"Qunantang",
    "gn:population":0,
    "gn:timezone":"Asia/Shanghai",
    "iso:country":"CN",
    "name:zho_x_preferred":[
        "\u5c48\u5357\u5858"
    ],
    "wof:name":"Qunantang",
    "wof:placetype":"locality"
},
  "geometry": {"coordinates":[108.13239,37.40543],"type":"Point"}
}