{
  "type": "Feature",
  "properties": {
    "gn:admin1_code":"02",
    "gn:asciiname":"Pingshui",
    "gn:country_code":"CN",
    "gn:dem":15,
    "gn:feature_class":"P",
    "gn:feature_code":"PPLA4",
    "gn:name":"Pingshui",
    "gn:population":0,
    "gn:timezone":"Asia/Shanghai",
    "iso:country":"CN",
    "name:und_x_variant":[
        "P\u2019ing-shui-chen",
        "Pingshui",
        "Pingshui Zhen"
    ],
    "name:zho_x_preferred":[
        "\u5e73\u6c34\u9547"
    ],
    "name:zho_x_variant":[
        "\u5e73\u6c34"
    ],
    "wof:name":"Pingshui",
    "wof:placetype":"locality"
},
  "geometry": {"coordinates":[120.6194,29.89364],"type":"Point"}
}