{
  "type": "Feature",
  "properties": {
    "gn:admin1_code":"8.0",
    "gn:asciiname":"Lanfengcun",
    "gn:country_code":"CN",
    "gn:dem":184,
    "gn:feature_class":"P",
    "gn:feature_code":"PPL",
    "gn:name":"Lanfengcun",
    "gn:population":0,
    "gn:timezone":"Asia/Shanghai",
    "iso:country":"CN",
    "name:zho_x_preferred":[
        "\u5c9a\u5cf0\u6751"
    ],
    "wof:name":"Lanfengcun",
    "wof:placetype":"locality"
},
  "geometry": {"coordinates":[131.77889999999999,46.05402],"type":"Point"}
}