{
  "type": "Feature",
  "properties": {
    "gn:admin1_code":"26.0",
    "gn:asciiname":"Tianjia Yuanzi",
    "gn:country_code":"CN",
    "gn:dem":1044,
    "gn:feature_class":"P",
    "gn:feature_code":"PPL",
    "gn:name":"Tianjia Yuanzi",
    "gn:population":0,
    "gn:timezone":"Asia/Shanghai",
    "iso:country":"CN",
    "name:und_x_variant":[
        "\u7530\u5bb6\u9662\u5b50"
    ],
    "wof:name":"Tianjia Yuanzi",
    "wof:placetype":"locality"
},
  "geometry": {"coordinates":[106.32501000000001,33.44183],"type":"Point"}
}