{
  "type": "Feature",
  "properties": {
    "gn:admin1_code":"3.0",
    "gn:asciiname":"Jinjishi",
    "gn:country_code":"CN",
    "gn:dem":247,
    "gn:feature_class":"P",
    "gn:feature_code":"PPL",
    "gn:name":"Jinjishi",
    "gn:population":0,
    "gn:timezone":"Asia/Shanghai",
    "iso:country":"CN",
    "name:und_x_variant":[
        "\u91d1\u9e21\u77f3"
    ],
    "wof:name":"Jinjishi",
    "wof:placetype":"locality"
},
  "geometry": {"coordinates":[116.35533,26.29986],"type":"Point"}
}