{
  "type": "Feature",
  "properties": {
    "gn:admin1_code":"25.0",
    "gn:asciiname":"Shuangshi Yinjiacun",
    "gn:country_code":"CN",
    "gn:dem":37,
    "gn:feature_class":"P",
    "gn:feature_code":"PPL",
    "gn:name":"Shuangshi Yinjiacun",
    "gn:population":0,
    "gn:timezone":"Asia/Shanghai",
    "iso:country":"CN",
    "name:zho_x_preferred":[
        "\u53cc\u77f3\u5c39\u5bb6\u6751"
    ],
    "wof:name":"Shuangshi Yinjiacun",
    "wof:placetype":"locality"
},
  "geometry": {"coordinates":[122.26121999999999,37.067],"type":"Point"}
}