{
  "type": "Feature",
  "properties": {
    "gn:admin1_code":"16.0",
    "gn:asciiname":"Lani",
    "gn:country_code":"CN",
    "gn:dem":364,
    "gn:feature_class":"P",
    "gn:feature_code":"PPL",
    "gn:name":"Lani",
    "gn:population":0,
    "gn:timezone":"Asia/Shanghai",
    "iso:country":"CN",
    "name:ceb_x_preferred":[
        "Lani"
    ],
    "name:deu_x_preferred":[
        "Lani"
    ],
    "name:swe_x_preferred":[
        "Lani"
    ],
    "name:zho_x_preferred":[
        "\u62c9\u576d"
    ],
    "wof:name":"Lani",
    "wof:placetype":"locality"
},
  "geometry": {"coordinates":[108.392,23.8997],"type":"Point"}
}