{
  "type": "Feature",
  "properties": {
    "gn:admin1_code":"15.0",
    "gn:asciiname":"Anjiaba",
    "gn:country_code":"CN",
    "gn:dem":1245,
    "gn:feature_class":"P",
    "gn:feature_code":"PPL",
    "gn:name":"Anjiaba",
    "gn:population":0,
    "gn:timezone":"Asia/Shanghai",
    "iso:country":"CN",
    "name:und_x_variant":[
        "\u5b89\u5bb6\u575d"
    ],
    "wof:name":"Anjiaba",
    "wof:placetype":"locality"
},
  "geometry": {"coordinates":[105.53731999999999,33.31074],"type":"Point"}
}