{
  "type": "Feature",
  "properties": {
    "gn:admin1_code":"8.0",
    "gn:asciiname":"Jiuqiancun",
    "gn:country_code":"CN",
    "gn:dem":179,
    "gn:feature_class":"P",
    "gn:feature_code":"PPL",
    "gn:name":"Jiuqiancun",
    "gn:population":0,
    "gn:timezone":"Asia/Shanghai",
    "iso:country":"CN",
    "name:zho_x_preferred":[
        "\u4e45\u524d\u6751"
    ],
    "wof:name":"Jiuqiancun",
    "wof:placetype":"locality"
},
  "geometry": {"coordinates":[126.42147,45.45004],"type":"Point"}
}