{
  "type": "Feature",
  "properties": {
    "gn:admin1_code":"26.0",
    "gn:asciiname":"Changshumiao",
    "gn:country_code":"CN",
    "gn:dem":795,
    "gn:feature_class":"P",
    "gn:feature_code":"PPL",
    "gn:name":"Changshumiao",
    "gn:population":0,
    "gn:timezone":"Asia/Shanghai",
    "iso:country":"CN",
    "name:und_x_variant":[
        "\u5e38\u719f\u5e99"
    ],
    "wof:name":"Changshumiao",
    "wof:placetype":"locality"
},
  "geometry": {"coordinates":[107.17238999999999,33.53217],"type":"Point"}
}