{
  "type": "Feature",
  "properties": {
    "gn:admin1_code":"1.0",
    "gn:asciiname":"Guanshancun",
    "gn:country_code":"CN",
    "gn:dem":40,
    "gn:feature_class":"P",
    "gn:feature_code":"PPL",
    "gn:name":"Guanshancun",
    "gn:population":0,
    "gn:timezone":"Asia/Shanghai",
    "iso:country":"CN",
    "name:zho_x_preferred":[
        "\u7ba1\u5c71\u6751"
    ],
    "wof:name":"Guanshancun",
    "wof:placetype":"locality"
},
  "geometry": {"coordinates":[116.98623000000001,30.19753],"type":"Point"}
}