{
  "type": "Feature",
  "properties": {
    "gn:admin1_code":"8.0",
    "gn:asciiname":"Yujiada Wopeng",
    "gn:country_code":"CN",
    "gn:dem":218,
    "gn:feature_class":"P",
    "gn:feature_code":"PPL",
    "gn:name":"Yujiada Wopeng",
    "gn:population":0,
    "gn:timezone":"Asia/Shanghai",
    "iso:country":"CN",
    "name:zho_x_preferred":[
        "\u4f59\u5bb6\u5927\u7a9d\u68da"
    ],
    "wof:name":"Yujiada Wopeng",
    "wof:placetype":"locality"
},
  "geometry": {"coordinates":[126.9923,44.78431],"type":"Point"}
}