{
  "type": "Feature",
  "properties": {
    "gn:admin1_code":"21.0",
    "gn:asciiname":"Xiazhangcunbu",
    "gn:country_code":"CN",
    "gn:dem":1930,
    "gn:feature_class":"P",
    "gn:feature_code":"PPL",
    "gn:name":"Xiazhangcunbu",
    "gn:population":0,
    "gn:timezone":"Asia/Shanghai",
    "iso:country":"CN",
    "name:und_x_variant":[
        "\u4e0b\u5f20\u6751\u5821"
    ],
    "name:zho_x_preferred":[
        "\u4e0b\u5f20\u6751\u5821"
    ],
    "wof:name":"Xiazhangcunbu",
    "wof:placetype":"locality"
},
  "geometry": {"coordinates":[105.72421,35.91029],"type":"Point"}
}