{
  "type": "Feature",
  "properties": {
    "gn:admin1_code":"30",
    "gn:asciiname":"Sanhezhen",
    "gn:country_code":"CN",
    "gn:dem":141,
    "gn:feature_class":"P",
    "gn:feature_code":"PPL",
    "gn:name":"Sanhezhen",
    "gn:population":0,
    "gn:timezone":"Asia/Shanghai",
    "iso:country":"CN",
    "name:und_x_variant":[
        "\u4e09\u6cb3\u9547"
    ],
    "wof:name":"Sanhezhen",
    "wof:placetype":"locality"
},
  "geometry": {"coordinates":[114.92315000000001,24.18952],"type":"Point"}
}