{
  "type": "Feature",
  "properties": {
    "gn:admin1_code":"18",
    "gn:asciiname":"Songlintou",
    "gn:country_code":"CN",
    "gn:dem":1953,
    "gn:feature_class":"P",
    "gn:feature_code":"PPL",
    "gn:name":"Songlintou",
    "gn:population":0,
    "gn:timezone":"Asia/Shanghai",
    "iso:country":"CN",
    "name:zho_x_preferred":[
        "\u677e\u6797\u5934"
    ],
    "wof:name":"Songlintou",
    "wof:placetype":"locality"
},
  "geometry": {"coordinates":[104.432,27.2428],"type":"Point"}
}