{
  "type": "Feature",
  "properties": {
    "gn:admin1_code":"26.0",
    "gn:asciiname":"Yuanlongsi",
    "gn:cc2":"CN",
    "gn:country_code":"CN",
    "gn:dem":961,
    "gn:feature_class":"P",
    "gn:feature_code":"PPL",
    "gn:name":"Yuanlongsi",
    "gn:population":0,
    "gn:timezone":"Asia/Shanghai",
    "iso:country":"CN",
    "name:und_x_variant":[
        "Y\u00fcan-lung-ssu",
        "Yuanlongsi"
    ],
    "wof:name":"Yuanlongsi",
    "wof:placetype":"locality"
},
  "geometry": {"coordinates":[109.71666999999999,36.75],"type":"Point"}
}