{
  "type": "Feature",
  "properties": {
    "gn:admin1_code":"3.0",
    "gn:asciiname":"Luokeng Linchang",
    "gn:country_code":"CN",
    "gn:dem":100,
    "gn:feature_class":"P",
    "gn:feature_code":"PPLF",
    "gn:name":"Luokeng Linchang",
    "gn:population":0,
    "gn:timezone":"Asia/Shanghai",
    "iso:country":"CN",
    "name:und_x_variant":[
        "\u843d\u5751\u6797\u573a"
    ],
    "wof:name":"Luokeng Linchang",
    "wof:placetype":"locality"
},
  "geometry": {"coordinates":[114.81135,27.95666],"type":"Point"}
}