{
  "type": "Feature",
  "properties": {
    "gn:admin1_code":"10",
    "gn:asciiname":"Fumashan",
    "gn:country_code":"CN",
    "gn:dem":1018,
    "gn:feature_class":"P",
    "gn:feature_code":"PPL",
    "gn:name":"Fumashan",
    "gn:population":0,
    "gn:timezone":"Asia/Shanghai",
    "iso:country":"CN",
    "name:zho_x_preferred":[
        "\u9a78\u9a6c\u5c71"
    ],
    "wof:name":"Fumashan",
    "wof:placetype":"locality"
},
  "geometry": {"coordinates":[116.47224,41.24438],"type":"Point"}
}