{
  "type": "Feature",
  "properties": {
    "gn:admin1_code":"11.0",
    "gn:asciiname":"Wachangjie",
    "gn:country_code":"CN",
    "gn:dem":443,
    "gn:feature_class":"P",
    "gn:feature_code":"PPL",
    "gn:name":"Wachangjie",
    "gn:population":0,
    "gn:timezone":"Asia/Shanghai",
    "iso:country":"CN",
    "name:zho_x_preferred":[
        "\u74e6\u5382\u754c"
    ],
    "wof:name":"Wachangjie",
    "wof:placetype":"locality"
},
  "geometry": {"coordinates":[110.03896,26.67438],"type":"Point"}
}