{
  "type": "Feature",
  "properties": {
    "gn:admin1_code":"15.0",
    "gn:asciiname":"Renwujia",
    "gn:country_code":"CN",
    "gn:dem":1622,
    "gn:feature_class":"P",
    "gn:feature_code":"PPL",
    "gn:name":"Renwujia",
    "gn:population":0,
    "gn:timezone":"Asia/Shanghai",
    "iso:country":"CN",
    "name:zho_x_preferred":[
        "\u4efb\u5434\u5bb6"
    ],
    "wof:name":"Renwujia",
    "wof:placetype":"locality"
},
  "geometry": {"coordinates":[105.73099999999999,34.8879],"type":"Point"}
}