{
  "type": "Feature",
  "properties": {
    "gn:admin1_code":"16",
    "gn:asciiname":"Huangshahe",
    "gn:cc2":"CN",
    "gn:country_code":"CN",
    "gn:dem":141,
    "gn:feature_class":"P",
    "gn:feature_code":"PPL",
    "gn:name":"Huangshahe",
    "gn:population":0,
    "gn:timezone":"Asia/Shanghai",
    "iso:country":"CN",
    "name:und_x_variant":[
        "Hwangshaho",
        "Huang-sha-p\u2019u",
        "Huang-sha-ho",
        "Huangshahe"
    ],
    "wof:name":"Huangshahe",
    "wof:placetype":"locality"
},
  "geometry": {"coordinates":[111.21056000000002,26.09167],"type":"Point"}
}