{
  "type": "Feature",
  "properties": {
    "gn:admin1_code":"03",
    "gn:asciiname":"Jianchang",
    "gn:country_code":"CN",
    "gn:dem":78,
    "gn:feature_class":"P",
    "gn:feature_code":"PPLA3",
    "gn:name":"Jianchang",
    "gn:population":0,
    "gn:timezone":"Asia/Shanghai",
    "iso:country":"CN",
    "name:deu_x_preferred":[
        "Nancheng"
    ],
    "name:fas_x_preferred":[
        "\u0634\u0647\u0631\u0633\u062a\u0627\u0646 \u0646\u0627\u0646\u0686\u0646\u06af"
    ],
    "name:jpn_x_preferred":[
        "\u5357\u57ce\u770c"
    ],
    "name:kor_x_preferred":[
        "\ub09c\uccad\ud604"
    ],
    "name:nor_x_preferred":[
        "Nancheng"
    ],
    "name:swe_x_preferred":[
        "Nancheng"
    ],
    "name:und_x_variant":[
        "Chien-ch\u2019ang",
        "Nan-ch\u2019eng-hsien",
        "Kienchangfu",
        "Nancheng",
        "Kienchang",
        "Jianchang",
        "\u5efa\u660c",
        "Nancheng Xian",
        "Jianchang Zhen",
        "\u5357\u57ce\u53bf",
        "\u5efa\u660c\u9547"
    ],
    "name:vie_x_preferred":[
        "Nam Th\u00e0nh"
    ],
    "name:zho_x_preferred":[
        "\u5357\u57ce\u53bf"
    ],
    "wof:name":"Jianchang",
    "wof:placetype":"locality"
},
  "geometry": {"coordinates":[116.63978,27.55831],"type":"Point"}
}