{
  "type": "Feature",
  "properties": {
    "gn:admin1_code":"03",
    "gn:asciiname":"Jianchang",
    "gn:country_code":"CN",
    "gn:dem":78,
    "gn:feature_class":"P",
    "gn:feature_code":"PPLA3",
    "gn:name":"Jianchang",
    "gn:population":0,
    "gn:timezone":"Asia/Shanghai",
    "iso:country":"CN",
    "name:und_x_variant":[
        "Chien-ch\u2019ang",
        "Nan-ch\u2019eng-hsien",
        "Kienchangfu",
        "Nancheng",
        "Kienchang",
        "Jianchang",
        "\u5efa\u660c",
        "Nancheng Xian",
        "Jianchang Zhen",
        "\u5357\u57ce\u53bf",
        "\u5efa\u660c\u9547"
    ],
    "wof:name":"Jianchang",
    "wof:placetype":"locality"
},
  "geometry": {"coordinates":[116.63978,27.55831],"type":"Point"}
}