{
  "type": "Feature",
  "properties": {
    "gn:admin1_code":"29.0",
    "gn:asciiname":"Wangshaopo",
    "gn:country_code":"CN",
    "gn:dem":1928,
    "gn:feature_class":"P",
    "gn:feature_code":"PPL",
    "gn:name":"Wangshaopo",
    "gn:population":0,
    "gn:timezone":"Asia/Shanghai",
    "iso:country":"CN",
    "name:zho_x_preferred":[
        "\u671b\u54e8\u5761"
    ],
    "wof:name":"Wangshaopo",
    "wof:placetype":"locality"
},
  "geometry": {"coordinates":[103.401,23.2367],"type":"Point"}
}