{
  "type": "Feature",
  "properties": {
    "gn:admin1_code":"25.0",
    "gn:asciiname":"Nanshi Menkou",
    "gn:country_code":"CN",
    "gn:dem":135,
    "gn:feature_class":"P",
    "gn:feature_code":"PPL",
    "gn:name":"Nanshi Menkou",
    "gn:population":0,
    "gn:timezone":"Asia/Shanghai",
    "iso:country":"CN",
    "name:zho_x_preferred":[
        "\u5357\u77f3\u95e8\u53e3"
    ],
    "wof:name":"Nanshi Menkou",
    "wof:placetype":"locality"
},
  "geometry": {"coordinates":[121.42868,37.20573],"type":"Point"}
}