{
  "type": "Feature",
  "properties": {
    "gn:admin1_code":"30.0",
    "gn:asciiname":"Dongzhou",
    "gn:country_code":"CN",
    "gn:dem":11,
    "gn:feature_class":"P",
    "gn:feature_code":"PPLA4",
    "gn:name":"Dongzhou",
    "gn:population":0,
    "gn:timezone":"Asia/Shanghai",
    "iso:country":"CN",
    "name:fra_x_preferred":[
        "Dongzhou"
    ],
    "name:und_x_variant":[
        "Dongzhou Jiedao",
        "Dongzhou"
    ],
    "name:zho_x_preferred":[
        "\u4e1c\u6d32"
    ],
    "name:zho_x_variant":[
        "\u4e1c\u6d32\u8857\u9053"
    ],
    "wof:name":"Dongzhou",
    "wof:placetype":"locality"
},
  "geometry": {"coordinates":[115.52706000000001,22.71304],"type":"Point"}
}