{
  "type": "Feature",
  "properties": {
    "gn:admin1_code":"8.0",
    "gn:asciiname":"Liuheiniu",
    "gn:country_code":"CN",
    "gn:dem":260,
    "gn:feature_class":"P",
    "gn:feature_code":"PPL",
    "gn:name":"Liuheiniu",
    "gn:population":0,
    "gn:timezone":"Asia/Shanghai",
    "iso:country":"CN",
    "name:zho_x_preferred":[
        "\u5218\u9ed1\u725b"
    ],
    "wof:name":"Liuheiniu",
    "wof:placetype":"locality"
},
  "geometry": {"coordinates":[126.32491,48.50535],"type":"Point"}
}