{
  "type": "Feature",
  "properties": {
    "gn:admin1_code":"3.0",
    "gn:asciiname":"Tanmuwan",
    "gn:country_code":"CN",
    "gn:dem":240,
    "gn:feature_class":"P",
    "gn:feature_code":"PPL",
    "gn:name":"Tanmuwan",
    "gn:population":0,
    "gn:timezone":"Asia/Shanghai",
    "iso:country":"CN",
    "name:zho_x_preferred":[
        "\u6a80\u6728\u6e7e"
    ],
    "wof:name":"Tanmuwan",
    "wof:placetype":"locality"
},
  "geometry": {"coordinates":[117.91643999999999,28.14258],"type":"Point"}
}