{
  "type": "Feature",
  "properties": {
    "gn:admin1_code":"12.0",
    "gn:asciiname":"Cuijiazhou",
    "gn:country_code":"CN",
    "gn:dem":29,
    "gn:feature_class":"P",
    "gn:feature_code":"PPL",
    "gn:name":"Cuijiazhou",
    "gn:population":0,
    "gn:timezone":"Asia/Shanghai",
    "iso:country":"CN",
    "name:zho_x_preferred":[
        "\u5d14\u5bb6\u6d32"
    ],
    "wof:name":"Cuijiazhou",
    "wof:placetype":"locality"
},
  "geometry": {"coordinates":[113.02238,30.20633],"type":"Point"}
}