{
  "type": "Feature",
  "properties": {
    "gn:admin1_code":"1.0",
    "gn:asciiname":"Hubin",
    "gn:country_code":"CN",
    "gn:dem":20,
    "gn:feature_class":"P",
    "gn:feature_code":"PPL",
    "gn:name":"Hubin",
    "gn:population":0,
    "gn:timezone":"Asia/Shanghai",
    "iso:country":"CN",
    "name:ceb_x_preferred":[
        "Hubin"
    ],
    "name:deu_x_preferred":[
        "Hubin"
    ],
    "name:fra_x_preferred":[
        "Hubin"
    ],
    "name:pol_x_preferred":[
        "Hubin"
    ],
    "name:ukr_x_preferred":[
        "\u0413\u0443\u0431\u0438\u043d"
    ],
    "name:zho_x_preferred":[
        "Hubin"
    ],
    "name:zho_x_variant":[
        "\u6e56\u6ee8"
    ],
    "wof:name":"Hubin",
    "wof:placetype":"locality"
},
  "geometry": {"coordinates":[119.01884,31.08769],"type":"Point"}
}