{
  "type": "Feature",
  "properties": {
    "gn:admin1_code":"19.0",
    "gn:asciiname":"Xiaofanhecun",
    "gn:country_code":"CN",
    "gn:dem":57,
    "gn:feature_class":"P",
    "gn:feature_code":"PPL",
    "gn:name":"Xiaofanhecun",
    "gn:population":0,
    "gn:timezone":"Asia/Shanghai",
    "iso:country":"CN",
    "name:zho_x_preferred":[
        "\u5c0f\u51e1\u6cb3\u6751"
    ],
    "wof:name":"Xiaofanhecun",
    "wof:placetype":"locality"
},
  "geometry": {"coordinates":[123.693,42.2391],"type":"Point"}
}