{
  "type": "Feature",
  "properties": {
    "gn:admin1_code":"15.0",
    "gn:asciiname":"Gaozhuang Sidui",
    "gn:country_code":"CN",
    "gn:dem":1583,
    "gn:feature_class":"P",
    "gn:feature_code":"PPLF",
    "gn:name":"Gaozhuang Sidui",
    "gn:population":0,
    "gn:timezone":"Asia/Shanghai",
    "iso:country":"CN",
    "name:zho_x_preferred":[
        "\u9ad8\u5e84\u56db\u961f"
    ],
    "wof:name":"Gaozhuang Sidui",
    "wof:placetype":"locality"
},
  "geometry": {"coordinates":[100.172,39.0066],"type":"Point"}
}