{
  "type": "Feature",
  "properties": {
    "gn:admin1_code":"7.0",
    "gn:asciiname":"Xizhou",
    "gn:country_code":"CN",
    "gn:dem":418,
    "gn:feature_class":"P",
    "gn:feature_code":"PPL",
    "gn:name":"Xizhou",
    "gn:population":0,
    "gn:timezone":"Asia/Shanghai",
    "iso:country":"CN",
    "name:deu_x_preferred":[
        "Xizhou"
    ],
    "name:zho_x_preferred":[
        "\u6eaa\u6d32"
    ],
    "wof:name":"Xizhou",
    "wof:placetype":"locality"
},
  "geometry": {"coordinates":[118.3001,27.93691],"type":"Point"}
}