{
  "type": "Feature",
  "properties": {
    "gn:admin1_code":"7.0",
    "gn:asciiname":"Sanlangxi",
    "gn:country_code":"CN",
    "gn:dem":382,
    "gn:feature_class":"P",
    "gn:feature_code":"PPL",
    "gn:name":"Sanlangxi",
    "gn:population":0,
    "gn:timezone":"Asia/Shanghai",
    "iso:country":"CN",
    "name:zho_x_preferred":[
        "\u4e09\u6d6a\u6eaa"
    ],
    "wof:name":"Sanlangxi",
    "wof:placetype":"locality"
},
  "geometry": {"coordinates":[117.20887,27.03147],"type":"Point"}
}