{
  "type": "Feature",
  "properties": {
    "gn:admin1_code":"4.0",
    "gn:asciiname":"Caizhangcun",
    "gn:country_code":"CN",
    "gn:dem":3,
    "gn:feature_class":"P",
    "gn:feature_code":"PPL",
    "gn:name":"Caizhangcun",
    "gn:population":0,
    "gn:timezone":"Asia/Shanghai",
    "iso:country":"CN",
    "name:zho_x_preferred":[
        "\u8521\u5f20\u6751"
    ],
    "wof:name":"Caizhangcun",
    "wof:placetype":"locality"
},
  "geometry": {"coordinates":[119.60169,33.69611],"type":"Point"}
}