{
  "type": "Feature",
  "properties": {
    "gn:admin1_code":"15.0",
    "gn:asciiname":"Wanjiachuan",
    "gn:country_code":"CN",
    "gn:dem":1190,
    "gn:feature_class":"P",
    "gn:feature_code":"PPL",
    "gn:name":"Wanjiachuan",
    "gn:population":0,
    "gn:timezone":"Asia/Shanghai",
    "iso:country":"CN",
    "name:und_x_variant":[
        "\u4e07\u5bb6\u5ddd"
    ],
    "wof:name":"Wanjiachuan",
    "wof:placetype":"locality"
},
  "geometry": {"coordinates":[107.21299999999999,34.9443],"type":"Point"}
}