{
  "type": "Feature",
  "properties": {
    "gn:admin1_code":"30.0",
    "gn:asciiname":"Tanglang",
    "gn:country_code":"CN",
    "gn:dem":33,
    "gn:feature_class":"P",
    "gn:feature_code":"PPL",
    "gn:name":"Tanglang",
    "gn:population":0,
    "gn:timezone":"Asia/Shanghai",
    "iso:country":"CN",
    "name:ceb_x_preferred":[
        "Tanglang"
    ],
    "name:swe_x_preferred":[
        "Tanglang"
    ],
    "name:zho_x_preferred":[
        "\u5858\u6717"
    ],
    "wof:name":"Tanglang",
    "wof:placetype":"locality"
},
  "geometry": {"coordinates":[113.98399999999999,22.59147],"type":"Point"}
}