{
  "type": "Feature",
  "properties": {
    "gn:admin1_code":"1.0",
    "gn:asciiname":"Houchongcun",
    "gn:country_code":"CN",
    "gn:dem":207,
    "gn:feature_class":"P",
    "gn:feature_code":"PPL",
    "gn:name":"Houchongcun",
    "gn:population":0,
    "gn:timezone":"Asia/Shanghai",
    "iso:country":"CN",
    "name:zho_x_preferred":[
        "\u540e\u51b2\u6751"
    ],
    "wof:name":"Houchongcun",
    "wof:placetype":"locality"
},
  "geometry": {"coordinates":[115.67083999999998,31.45324],"type":"Point"}
}