{
  "type": "Feature",
  "properties": {
    "gn:admin1_code":"02",
    "gn:asciiname":"Hongling Xiacun",
    "gn:country_code":"CN",
    "gn:dem":5,
    "gn:feature_class":"P",
    "gn:feature_code":"PPL",
    "gn:name":"Hongling Xiacun",
    "gn:population":0,
    "gn:timezone":"Asia/Shanghai",
    "iso:country":"CN",
    "name:und_x_variant":[
        "Hung-ling-chiao",
        "Honglingxia",
        "Hongling Xiacun"
    ],
    "name:zho_x_preferred":[
        "\u6d2a\u5cad\u4e0b"
    ],
    "name:zho_x_variant":[
        "\u6d2a\u5cad\u4e0b\u6751"
    ],
    "wof:name":"Hongling Xiacun",
    "wof:placetype":"locality"
},
  "geometry": {"coordinates":[120.64206,27.4687],"type":"Point"}
}