{
  "type": "Feature",
  "properties": {
    "gn:admin1_code":"26.0",
    "gn:asciiname":"Caojiawan",
    "gn:country_code":"CN",
    "gn:dem":1239,
    "gn:feature_class":"P",
    "gn:feature_code":"PPL",
    "gn:name":"Caojiawan",
    "gn:population":0,
    "gn:timezone":"Asia/Shanghai",
    "iso:country":"CN",
    "name:zho_x_preferred":[
        "\u66f9\u5bb6\u6e7e"
    ],
    "wof:name":"Caojiawan",
    "wof:placetype":"locality"
},
  "geometry": {"coordinates":[109.91445,38.89082],"type":"Point"}
}