{
  "type": "Feature",
  "properties": {
    "gn:admin1_code":"6.0",
    "gn:asciiname":"Sanhe",
    "gn:country_code":"CN",
    "gn:dem":2558,
    "gn:feature_class":"P",
    "gn:feature_code":"PPLA4",
    "gn:name":"Sanhe",
    "gn:population":0,
    "gn:timezone":"Asia/Shanghai",
    "iso:country":"CN",
    "name:ceb_x_preferred":[
        "Sanhe"
    ],
    "name:deu_x_preferred":[
        "Sanhe"
    ],
    "name:nor_x_preferred":[
        "Sanhe"
    ],
    "name:und_x_variant":[
        "Sanhe Zhen"
    ],
    "name:zho_x_preferred":[
        "\u4e09\u5408"
    ],
    "name:zho_x_variant":[
        "\u4e09\u5408\u9547"
    ],
    "wof:name":"Sanhe",
    "wof:placetype":"locality"
},
  "geometry": {"coordinates":[101.92955000000001,36.42242],"type":"Point"}
}