{
  "type": "Feature",
  "properties": {
    "gn:admin1_code":"15.0",
    "gn:asciiname":"Zhangzhuang",
    "gn:country_code":"CN",
    "gn:dem":1620,
    "gn:feature_class":"P",
    "gn:feature_code":"PPL",
    "gn:name":"Zhangzhuang",
    "gn:population":0,
    "gn:timezone":"Asia/Shanghai",
    "iso:country":"CN",
    "name:zho_x_preferred":[
        "\u5f20\u5e84"
    ],
    "wof:name":"Zhangzhuang",
    "wof:placetype":"locality"
},
  "geometry": {"coordinates":[102.97499999999999,37.7653],"type":"Point"}
}