{
  "type": "Feature",
  "properties": {
    "gn:admin1_code":"19.0",
    "gn:asciiname":"Goumen",
    "gn:country_code":"CN",
    "gn:dem":330,
    "gn:feature_class":"P",
    "gn:feature_code":"PPL",
    "gn:name":"Goumen",
    "gn:population":0,
    "gn:timezone":"Asia/Shanghai",
    "iso:country":"CN",
    "name:zho_x_preferred":[
        "\u6c9f\u95e8"
    ],
    "wof:name":"Goumen",
    "wof:placetype":"locality"
},
  "geometry": {"coordinates":[120.43153999999998,40.99844],"type":"Point"}
}