{
  "type": "Feature",
  "properties": {
    "gn:admin1_code":"11.0",
    "gn:asciiname":"Fengmuling",
    "gn:country_code":"CN",
    "gn:dem":218,
    "gn:feature_class":"P",
    "gn:feature_code":"PPL",
    "gn:name":"Fengmuling",
    "gn:population":0,
    "gn:timezone":"Asia/Shanghai",
    "iso:country":"CN",
    "name:zho_x_preferred":[
        "\u4e30\u6728\u5cad"
    ],
    "wof:name":"Fengmuling",
    "wof:placetype":"locality"
},
  "geometry": {"coordinates":[112.59638,26.22812],"type":"Point"}
}