{
  "type": "Feature",
  "properties": {
    "gn:admin1_code":"12.0",
    "gn:asciiname":"Xihong",
    "gn:country_code":"CN",
    "gn:dem":387,
    "gn:feature_class":"P",
    "gn:feature_code":"PPL",
    "gn:name":"Xihong",
    "gn:population":0,
    "gn:timezone":"Asia/Shanghai",
    "iso:country":"CN",
    "name:zho_x_preferred":[
        "\u897f\u6d2a"
    ],
    "wof:name":"Xihong",
    "wof:placetype":"locality"
},
  "geometry": {"coordinates":[115.92694,31.04993],"type":"Point"}
}