{
  "type": "Feature",
  "properties": {
    "gn:admin1_code":"14.0",
    "gn:asciiname":"Nalinlaka",
    "gn:country_code":"CN",
    "gn:dem":4077,
    "gn:feature_class":"P",
    "gn:feature_code":"PPL",
    "gn:name":"Nalinlaka",
    "gn:population":0,
    "gn:timezone":"Asia/Urumqi",
    "iso:country":"CN",
    "name:zho_x_preferred":[
        "\u90a3\u6797\u62c9\u5361"
    ],
    "wof:name":"Nalinlaka",
    "wof:placetype":"locality"
},
  "geometry": {"coordinates":[91.34629,29.5853],"type":"Point"}
}