{
  "type": "Feature",
  "properties": {
    "gn:admin1_code":"15.0",
    "gn:asciiname":"Shaojia",
    "gn:country_code":"CN",
    "gn:dem":1003,
    "gn:feature_class":"P",
    "gn:feature_code":"PPL",
    "gn:name":"Shaojia",
    "gn:population":0,
    "gn:timezone":"Asia/Shanghai",
    "iso:country":"CN",
    "name:zho_x_preferred":[
        "\u90b5\u5bb6"
    ],
    "wof:name":"Shaojia",
    "wof:placetype":"locality"
},
  "geometry": {"coordinates":[107.874,35.3563],"type":"Point"}
}