{
  "type": "Feature",
  "properties": {
    "gn:admin1_code":"03",
    "gn:asciiname":"Caojunqiao",
    "gn:country_code":"CN",
    "gn:dem":20,
    "gn:feature_class":"P",
    "gn:feature_code":"PPL",
    "gn:name":"Caojunqiao",
    "gn:population":0,
    "gn:timezone":"Asia/Shanghai",
    "iso:country":"CN",
    "name:und_x_variant":[
        "\u66f9\u94a7\u6865"
    ],
    "wof:name":"Caojunqiao",
    "wof:placetype":"locality"
},
  "geometry": {"coordinates":[116.29646,29.66828],"type":"Point"}
}