{
  "type": "Feature",
  "properties": {
    "gn:admin1_code":"24.0",
    "gn:asciiname":"Zhangjiawan",
    "gn:country_code":"CN",
    "gn:dem":669,
    "gn:feature_class":"P",
    "gn:feature_code":"PPL",
    "gn:name":"Zhangjiawan",
    "gn:population":0,
    "gn:timezone":"Asia/Shanghai",
    "iso:country":"CN",
    "name:und_x_variant":[
        "\u5f20\u5bb6\u6e7e"
    ],
    "wof:name":"Zhangjiawan",
    "wof:placetype":"locality"
},
  "geometry": {"coordinates":[111.4837,35.80599],"type":"Point"}
}