{
  "type": "Feature",
  "properties": {
    "gn:admin1_code":"26.0",
    "gn:asciiname":"Haogudui",
    "gn:country_code":"CN",
    "gn:dem":1807,
    "gn:feature_class":"P",
    "gn:feature_code":"PPL",
    "gn:name":"Haogudui",
    "gn:population":0,
    "gn:timezone":"Asia/Shanghai",
    "iso:country":"CN",
    "name:und_x_variant":[
        "\u84bf\u8c37\u5806"
    ],
    "wof:name":"Haogudui",
    "wof:placetype":"locality"
},
  "geometry": {"coordinates":[107.42661,34.08447],"type":"Point"}
}