{
  "type": "Feature",
  "properties": {
    "gn:admin1_code":"30.0",
    "gn:asciiname":"Qipancun",
    "gn:country_code":"CN",
    "gn:dem":33,
    "gn:feature_class":"P",
    "gn:feature_code":"PPL",
    "gn:name":"Qipancun",
    "gn:population":0,
    "gn:timezone":"Asia/Shanghai",
    "iso:country":"CN",
    "name:zho_x_preferred":[
        "\u68cb\u76d8\u6751"
    ],
    "wof:name":"Qipancun",
    "wof:placetype":"locality"
},
  "geometry": {"coordinates":[116.42908,23.63914],"type":"Point"}
}