{
  "type": "Feature",
  "properties": {
    "gn:admin1_code":"30",
    "gn:asciiname":"Shuikou",
    "gn:country_code":"CN",
    "gn:dem":9,
    "gn:feature_class":"P",
    "gn:feature_code":"PPLA4",
    "gn:name":"Shuikou",
    "gn:population":0,
    "gn:timezone":"Asia/Shanghai",
    "iso:country":"CN",
    "name:und_x_variant":[
        "Shuikou Zhen",
        "\u6c34\u53e3\u9547"
    ],
    "name:zho_x_preferred":[
        "\u6c34\u53e3"
    ],
    "wof:name":"Shuikou",
    "wof:placetype":"locality"
},
  "geometry": {"coordinates":[112.76396,22.45474],"type":"Point"}
}