{
  "type": "Feature",
  "properties": {
    "gn:admin1_code":"4.0",
    "gn:asciiname":"Nianshang",
    "gn:country_code":"CN",
    "gn:dem":6,
    "gn:feature_class":"P",
    "gn:feature_code":"PPL",
    "gn:name":"Nianshang",
    "gn:population":0,
    "gn:timezone":"Asia/Shanghai",
    "iso:country":"CN",
    "name:zho_x_preferred":[
        "\u57dd\u4e0a"
    ],
    "wof:name":"Nianshang",
    "wof:placetype":"locality"
},
  "geometry": {"coordinates":[119.73572,31.63172],"type":"Point"}
}