{
  "type": "Feature",
  "properties": {
    "gn:admin1_code":"7.0",
    "gn:asciiname":"Yujiaqiao",
    "gn:country_code":"CN",
    "gn:dem":672,
    "gn:feature_class":"P",
    "gn:feature_code":"PPL",
    "gn:name":"Yujiaqiao",
    "gn:population":0,
    "gn:timezone":"Asia/Shanghai",
    "iso:country":"CN",
    "name:zho_x_preferred":[
        "\u4fde\u5bb6\u6865"
    ],
    "wof:name":"Yujiaqiao",
    "wof:placetype":"locality"
},
  "geometry": {"coordinates":[116.63373,25.09184],"type":"Point"}
}