{
  "type": "Feature",
  "properties": {
    "gn:admin1_code":"7.0",
    "gn:asciiname":"Xilin",
    "gn:country_code":"CN",
    "gn:dem":23,
    "gn:feature_class":"P",
    "gn:feature_code":"PPL",
    "gn:name":"Xilin",
    "gn:population":0,
    "gn:timezone":"Asia/Shanghai",
    "iso:country":"CN",
    "name:ceb_x_preferred":[
        "Xilin"
    ],
    "name:deu_x_preferred":[
        "Xilin"
    ],
    "name:fra_x_preferred":[
        "Xilin"
    ],
    "name:nno_x_preferred":[
        "Xilin"
    ],
    "name:nor_x_preferred":[
        "Xilin"
    ],
    "name:rus_x_preferred":[
        "\u0421\u0438\u043b\u0438\u043d\u044c"
    ],
    "name:swe_x_preferred":[
        "Xilin"
    ],
    "name:zho_x_preferred":[
        "\u897f\u6797"
    ],
    "wof:name":"Xilin",
    "wof:placetype":"locality"
},
  "geometry": {"coordinates":[118.50771,25.06886],"type":"Point"}
}