{
  "type": "Feature",
  "properties": {
    "gn:admin1_code":"04",
    "gn:asciiname":"Donghutang",
    "gn:country_code":"CN",
    "gn:dem":17,
    "gn:feature_class":"P",
    "gn:feature_code":"PPL",
    "gn:name":"Donghutang",
    "gn:population":0,
    "gn:timezone":"Asia/Shanghai",
    "iso:country":"CN",
    "wof:name":"Donghutang",
    "wof:placetype":"locality"
},
  "geometry": {"coordinates":[120.41667,31.68333],"type":"Point"}
}