{
  "type": "Feature",
  "properties": {
    "gn:admin1_code":"3.0",
    "gn:asciiname":"Lengbanqiao",
    "gn:country_code":"CN",
    "gn:dem":296,
    "gn:feature_class":"P",
    "gn:feature_code":"PPL",
    "gn:name":"Lengbanqiao",
    "gn:population":0,
    "gn:timezone":"Asia/Shanghai",
    "iso:country":"CN",
    "name:zho_x_preferred":[
        "\u51b7\u677f\u6865"
    ],
    "wof:name":"Lengbanqiao",
    "wof:placetype":"locality"
},
  "geometry": {"coordinates":[114.14100000000001,28.2226],"type":"Point"}
}