{
  "type": "Feature",
  "properties": {
    "gn:admin1_code":"7",
    "gn:asciiname":"Songxia",
    "gn:country_code":"CN",
    "gn:dem":16,
    "gn:feature_class":"P",
    "gn:feature_code":"PPLA4",
    "gn:name":"Songxia",
    "gn:population":0,
    "gn:timezone":"Asia/Shanghai",
    "iso:country":"CN",
    "name:und_x_variant":[
        "Shouzhi",
        "Shou-chih",
        "Songxia",
        "Songxia Zhen"
    ],
    "name:zho_x_preferred":[
        "\u677e\u4e0b"
    ],
    "name:zho_x_variant":[
        "\u677e\u4e0b\u9547"
    ],
    "wof:name":"Songxia",
    "wof:placetype":"locality"
},
  "geometry": {"coordinates":[119.59381999999999,25.76415],"type":"Point"}
}