{
  "type": "Feature",
  "properties": {
    "gn:admin1_code":"5.0",
    "gn:asciiname":"Chedaoling",
    "gn:country_code":"CN",
    "gn:dem":392,
    "gn:feature_class":"P",
    "gn:feature_code":"PPL",
    "gn:name":"Chedaoling",
    "gn:population":0,
    "gn:timezone":"Asia/Shanghai",
    "iso:country":"CN",
    "name:zho_x_preferred":[
        "\u8f66\u9053\u5cad"
    ],
    "wof:name":"Chedaoling",
    "wof:placetype":"locality"
},
  "geometry": {"coordinates":[125.15546999999999,42.65572],"type":"Point"}
}