{
  "type": "Feature",
  "properties": {
    "gn:admin1_code":"4.0",
    "gn:asciiname":"Hekou",
    "gn:country_code":"CN",
    "gn:dem":1,
    "gn:feature_class":"P",
    "gn:feature_code":"PPL",
    "gn:name":"Hekou",
    "gn:population":0,
    "gn:timezone":"Asia/Shanghai",
    "iso:country":"CN",
    "name:ceb_x_preferred":[
        "Hekou"
    ],
    "name:deu_x_preferred":[
        "Hekou"
    ],
    "name:fra_x_preferred":[
        "Hekou"
    ],
    "name:nor_x_preferred":[
        "Hekou"
    ],
    "name:rus_x_preferred":[
        "\u0425\u044d\u043a\u043e\u0443"
    ],
    "name:swe_x_preferred":[
        "Hekou"
    ],
    "name:zho_x_preferred":[
        "Hekou"
    ],
    "name:zho_x_variant":[
        "\u6cb3\u53e3"
    ],
    "wof:name":"Hekou",
    "wof:placetype":"locality"
},
  "geometry": {"coordinates":[119.55991000000002,33.4117],"type":"Point"}
}