{
  "type": "Feature",
  "properties": {
    "gn:admin1_code":"18.0",
    "gn:asciiname":"Laohu'ao",
    "gn:country_code":"CN",
    "gn:dem":965,
    "gn:feature_class":"P",
    "gn:feature_code":"PPL",
    "gn:name":"Laohu\u2019ao",
    "gn:population":0,
    "gn:timezone":"Asia/Shanghai",
    "iso:country":"CN",
    "name:und_x_variant":[
        "Laohu\u2019ao"
    ],
    "name:zho_x_preferred":[
        "\u8001\u864e\u5773"
    ],
    "wof:name":"Laohu'ao",
    "wof:placetype":"locality"
},
  "geometry": {"coordinates":[107.946,26.9034],"type":"Point"}
}