{
  "type": "Feature",
  "properties": {
    "gn:admin1_code":"24.0",
    "gn:asciiname":"Lanjiayao",
    "gn:country_code":"CN",
    "gn:dem":1707,
    "gn:feature_class":"P",
    "gn:feature_code":"PPL",
    "gn:name":"Lanjiayao",
    "gn:population":0,
    "gn:timezone":"Asia/Shanghai",
    "iso:country":"CN",
    "name:und_x_variant":[
        "\u5170\u5bb6\u7a91"
    ],
    "wof:name":"Lanjiayao",
    "wof:placetype":"locality"
},
  "geometry": {"coordinates":[112.02282,39.34521],"type":"Point"}
}