{
  "type": "Feature",
  "properties": {
    "gn:admin1_code":"9",
    "gn:asciiname":"Jiezhuang",
    "gn:country_code":"CN",
    "gn:dem":34,
    "gn:feature_class":"P",
    "gn:feature_code":"PPL",
    "gn:name":"Jiezhuang",
    "gn:population":0,
    "gn:timezone":"Asia/Shanghai",
    "iso:country":"CN",
    "name:zho_x_preferred":[
        "\u89e3\u5e84"
    ],
    "wof:name":"Jiezhuang",
    "wof:placetype":"locality"
},
  "geometry": {"coordinates":[116.386,33.9136],"type":"Point"}
}