{
  "type": "Feature",
  "properties": {
    "gn:admin1_code":"8.0",
    "gn:asciiname":"Jiangjiatun",
    "gn:country_code":"CN",
    "gn:dem":201,
    "gn:feature_class":"P",
    "gn:feature_code":"PPL",
    "gn:name":"Jiangjiatun",
    "gn:population":0,
    "gn:timezone":"Asia/Shanghai",
    "iso:country":"CN",
    "name:zho_x_preferred":[
        "\u6c5f\u5bb6\u5c6f"
    ],
    "wof:name":"Jiangjiatun",
    "wof:placetype":"locality"
},
  "geometry": {"coordinates":[127.2043,44.85291],"type":"Point"}
}