{
  "type": "Feature",
  "properties": {
    "gn:admin1_code":"32.0",
    "gn:asciiname":"Ezezhong",
    "gn:country_code":"CN",
    "gn:dem":3627,
    "gn:feature_class":"P",
    "gn:feature_code":"PPL",
    "gn:name":"Ezezhong",
    "gn:population":0,
    "gn:timezone":"Asia/Shanghai",
    "iso:country":"CN",
    "name:zho_x_preferred":[
        "\u989d\u6cfd\u4ef2"
    ],
    "wof:name":"Ezezhong",
    "wof:placetype":"locality"
},
  "geometry": {"coordinates":[101.64,30.0832],"type":"Point"}
}