{
  "type": "Feature",
  "properties": {
    "gn:admin1_code":"12.0",
    "gn:asciiname":"Dazhang",
    "gn:country_code":"CN",
    "gn:dem":39,
    "gn:feature_class":"P",
    "gn:feature_code":"PPL",
    "gn:name":"Dazhang",
    "gn:population":0,
    "gn:timezone":"Asia/Shanghai",
    "iso:country":"CN",
    "name:zho_x_preferred":[
        "\u5927\u7ae0"
    ],
    "wof:name":"Dazhang",
    "wof:placetype":"locality"
},
  "geometry": {"coordinates":[114.39597000000001,30.31378],"type":"Point"}
}