{
  "type": "Feature",
  "properties": {
    "gn:admin1_code":"1.0",
    "gn:asciiname":"Changzhuyuancun",
    "gn:country_code":"CN",
    "gn:dem":79,
    "gn:feature_class":"P",
    "gn:feature_code":"PPL",
    "gn:name":"Changzhuyuancun",
    "gn:population":0,
    "gn:timezone":"Asia/Shanghai",
    "iso:country":"CN",
    "name:zho_x_preferred":[
        "\u957f\u7af9\u56ed\u6751"
    ],
    "wof:name":"Changzhuyuancun",
    "wof:placetype":"locality"
},
  "geometry": {"coordinates":[116.17513,31.5646],"type":"Point"}
}