{
  "type": "Feature",
  "properties": {
    "gn:admin1_code":"32.0",
    "gn:asciiname":"Lizigong",
    "gn:country_code":"CN",
    "gn:dem":2473,
    "gn:feature_class":"P",
    "gn:feature_code":"PPL",
    "gn:name":"Lizigong",
    "gn:population":0,
    "gn:timezone":"Asia/Shanghai",
    "iso:country":"CN",
    "name:zho_x_preferred":[
        "\u674e\u5b50\u8d21"
    ],
    "wof:name":"Lizigong",
    "wof:placetype":"locality"
},
  "geometry": {"coordinates":[100.54423,28.61777],"type":"Point"}
}