{
  "type": "Feature",
  "properties": {
    "gn:admin1_code":"3.0",
    "gn:asciiname":"Yapokeng",
    "gn:country_code":"CN",
    "gn:dem":405,
    "gn:feature_class":"P",
    "gn:feature_code":"PPL",
    "gn:name":"Yapokeng",
    "gn:population":0,
    "gn:timezone":"Asia/Shanghai",
    "iso:country":"CN",
    "name:und_x_variant":[
        "\u9e2d\u5a46\u5751"
    ],
    "wof:name":"Yapokeng",
    "wof:placetype":"locality"
},
  "geometry": {"coordinates":[114.89769,28.0419],"type":"Point"}
}