{
  "type": "Feature",
  "properties": {
    "gn:admin1_code":"10.0",
    "gn:asciiname":"Zhifangtou",
    "gn:country_code":"CN",
    "gn:dem":58,
    "gn:feature_class":"P",
    "gn:feature_code":"PPL",
    "gn:name":"Zhifangtou",
    "gn:population":0,
    "gn:timezone":"Asia/Shanghai",
    "iso:country":"CN",
    "name:und_x_variant":[
        "\u7eb8\u65b9\u5934"
    ],
    "wof:name":"Zhifangtou",
    "wof:placetype":"locality"
},
  "geometry": {"coordinates":[114.95671000000002,38.47859],"type":"Point"}
}