{
  "type": "Feature",
  "properties": {
    "gn:admin1_code":"16",
    "gn:asciiname":"Tongmujiang",
    "gn:country_code":"CN",
    "gn:dem":1189,
    "gn:feature_class":"P",
    "gn:feature_code":"PPL",
    "gn:name":"Tongmujiang",
    "gn:population":0,
    "gn:timezone":"Asia/Shanghai",
    "iso:country":"CN",
    "name:zho_x_preferred":[
        "\u6850\u6728\u6c5f"
    ],
    "wof:name":"Tongmujiang",
    "wof:placetype":"locality"
},
  "geometry": {"coordinates":[110.941,25.5229],"type":"Point"}
}