{
  "type": "Feature",
  "properties": {
    "gn:admin1_code":"29.0",
    "gn:asciiname":"Wanyoujie",
    "gn:country_code":"CN",
    "gn:dem":1832,
    "gn:feature_class":"P",
    "gn:feature_code":"PPL",
    "gn:name":"Wanyoujie",
    "gn:population":0,
    "gn:timezone":"Asia/Shanghai",
    "iso:country":"CN",
    "name:zho_x_preferred":[
        "\u4e07\u4f51\u8857"
    ],
    "wof:name":"Wanyoujie",
    "wof:placetype":"locality"
},
  "geometry": {"coordinates":[100.283,24.4511],"type":"Point"}
}