{
  "type": "Feature",
  "properties": {
    "gn:admin1_code":"10.0",
    "gn:asciiname":"Fangya'e",
    "gn:country_code":"CN",
    "gn:dem":14,
    "gn:feature_class":"P",
    "gn:feature_code":"PPL",
    "gn:name":"Fangya\u2019e",
    "gn:population":0,
    "gn:timezone":"Asia/Shanghai",
    "iso:country":"CN",
    "name:und_x_variant":[
        "Fangya\u2019e"
    ],
    "name:zho_x_preferred":[
        "\u65b9\u96c5\u83aa"
    ],
    "wof:name":"Fangya'e",
    "wof:placetype":"locality"
},
  "geometry": {"coordinates":[116.422,38.3936],"type":"Point"}
}