{
  "type": "Feature",
  "properties": {
    "gn:admin1_code":"11.0",
    "gn:asciiname":"Qianguling",
    "gn:country_code":"CN",
    "gn:dem":383,
    "gn:feature_class":"P",
    "gn:feature_code":"PPL",
    "gn:name":"Qianguling",
    "gn:population":0,
    "gn:timezone":"Asia/Shanghai",
    "iso:country":"CN",
    "name:zho_x_preferred":[
        "\u5343\u53e4\u5cad"
    ],
    "wof:name":"Qianguling",
    "wof:placetype":"locality"
},
  "geometry": {"coordinates":[113.43697,28.88107],"type":"Point"}
}