{
  "type": "Feature",
  "properties": {
    "gn:admin1_code":"26.0",
    "gn:asciiname":"Erlizhen",
    "gn:country_code":"CN",
    "gn:dem":562,
    "gn:feature_class":"P",
    "gn:feature_code":"PPL",
    "gn:name":"Erlizhen",
    "gn:population":0,
    "gn:timezone":"Asia/Shanghai",
    "iso:country":"CN",
    "name:und_x_variant":[
        "\u4e8c\u91cc\u9547"
    ],
    "wof:name":"Erlizhen",
    "wof:placetype":"locality"
},
  "geometry": {"coordinates":[107.21129999999999,32.9281],"type":"Point"}
}