{
  "type": "Feature",
  "properties": {
    "gn:admin1_code":"25.0",
    "gn:asciiname":"Mougezhuangcun",
    "gn:country_code":"CN",
    "gn:dem":70,
    "gn:feature_class":"P",
    "gn:feature_code":"PPL",
    "gn:name":"Mougezhuangcun",
    "gn:population":0,
    "gn:timezone":"Asia/Shanghai",
    "iso:country":"CN",
    "name:zho_x_preferred":[
        "\u725f\u683c\u5e84\u6751"
    ],
    "wof:name":"Mougezhuangcun",
    "wof:placetype":"locality"
},
  "geometry": {"coordinates":[120.84448,36.77662],"type":"Point"}
}