{
  "type": "Feature",
  "properties": {
    "gn:admin1_code":"12.0",
    "gn:asciiname":"Duanjiazhuang",
    "gn:country_code":"CN",
    "gn:dem":516,
    "gn:feature_class":"P",
    "gn:feature_code":"PPL",
    "gn:name":"Duanjiazhuang",
    "gn:population":0,
    "gn:timezone":"Asia/Shanghai",
    "iso:country":"CN",
    "name:zho_x_preferred":[
        "\u6bb5\u5bb6\u5e84"
    ],
    "wof:name":"Duanjiazhuang",
    "wof:placetype":"locality"
},
  "geometry": {"coordinates":[109.93106,32.28821],"type":"Point"}
}