{
  "type": "Feature",
  "properties": {
    "gn:admin1_code":"32.0",
    "gn:asciiname":"Chutouya",
    "gn:country_code":"CN",
    "gn:dem":516,
    "gn:feature_class":"P",
    "gn:feature_code":"PPL",
    "gn:name":"Chutouya",
    "gn:population":0,
    "gn:timezone":"Asia/Shanghai",
    "iso:country":"CN",
    "name:zho_x_preferred":[
        "\u9504\u5934\u57ad"
    ],
    "wof:name":"Chutouya",
    "wof:placetype":"locality"
},
  "geometry": {"coordinates":[106.07987,31.86052],"type":"Point"}
}