{
  "type": "Feature",
  "properties": {
    "gn:admin1_code":"29",
    "gn:asciiname":"Wayilang",
    "gn:country_code":"CN",
    "gn:dem":1269,
    "gn:feature_class":"P",
    "gn:feature_code":"PPL",
    "gn:name":"Wayilang",
    "gn:population":0,
    "gn:timezone":"Asia/Shanghai",
    "iso:country":"CN",
    "name:zho_x_preferred":[
        "\u74e6\u8863\u6717"
    ],
    "wof:name":"Wayilang",
    "wof:placetype":"locality"
},
  "geometry": {"coordinates":[101.41500000000001,24.2793],"type":"Point"}
}