{
  "type": "Feature",
  "properties": {
    "gn:admin1_code":"10",
    "gn:asciiname":"Shibahao",
    "gn:cc2":"CN",
    "gn:country_code":"CN",
    "gn:dem":1428,
    "gn:feature_class":"P",
    "gn:feature_code":"PPL",
    "gn:name":"Shibahao",
    "gn:population":0,
    "gn:timezone":"Asia/Shanghai",
    "iso:country":"CN",
    "name:und_x_variant":[
        "Shih-pa-hao",
        "Shibahao"
    ],
    "wof:name":"Shibahao",
    "wof:placetype":"locality"
},
  "geometry": {"coordinates":[116.0925,41.78694],"type":"Point"}
}