{
  "type": "Feature",
  "properties": {
    "gn:admin1_code":"4.0",
    "gn:asciiname":"Shaojialou",
    "gn:country_code":"CN",
    "gn:dem":2,
    "gn:feature_class":"P",
    "gn:feature_code":"PPL",
    "gn:name":"Shaojialou",
    "gn:population":0,
    "gn:timezone":"Asia/Shanghai",
    "iso:country":"CN",
    "name:zho_x_preferred":[
        "\u90b5\u5bb6\u697c"
    ],
    "wof:name":"Shaojialou",
    "wof:placetype":"locality"
},
  "geometry": {"coordinates":[119.492,32.7481],"type":"Point"}
}