{
  "type": "Feature",
  "properties": {
    "gn:admin1_code":"7.0",
    "gn:asciiname":"Xianyuan",
    "gn:country_code":"CN",
    "gn:dem":178,
    "gn:feature_class":"P",
    "gn:feature_code":"PPL",
    "gn:name":"Xianyuan",
    "gn:population":0,
    "gn:timezone":"Asia/Shanghai",
    "iso:country":"CN",
    "name:und_x_variant":[
        "\u4ed9\u6e90"
    ],
    "name:zho_x_preferred":[
        "\u4ed9\u6e90"
    ],
    "wof:name":"Xianyuan",
    "wof:placetype":"locality"
},
  "geometry": {"coordinates":[118.38795,26.96742],"type":"Point"}
}