{
  "type": "Feature",
  "properties": {
    "gn:admin1_code":"26.0",
    "gn:asciiname":"Da'eryan",
    "gn:country_code":"CN",
    "gn:dem":827,
    "gn:feature_class":"P",
    "gn:feature_code":"PPL",
    "gn:name":"Da\u2019eryan",
    "gn:population":0,
    "gn:timezone":"Asia/Shanghai",
    "iso:country":"CN",
    "name:und_x_variant":[
        "Da\u2019eryan",
        "\u6253\u513f\u5ca9"
    ],
    "wof:name":"Da'eryan",
    "wof:placetype":"locality"
},
  "geometry": {"coordinates":[106.23233,33.37108],"type":"Point"}
}