{
  "type": "Feature",
  "properties": {
    "gn:admin1_code":"32.0",
    "gn:asciiname":"Gelongge",
    "gn:country_code":"CN",
    "gn:dem":4193,
    "gn:feature_class":"P",
    "gn:feature_code":"PPL",
    "gn:name":"Gelongge",
    "gn:population":0,
    "gn:timezone":"Asia/Shanghai",
    "iso:country":"CN",
    "name:zho_x_preferred":[
        "\u5404\u9f99\u54e5"
    ],
    "wof:name":"Gelongge",
    "wof:placetype":"locality"
},
  "geometry": {"coordinates":[102.10195,32.06459],"type":"Point"}
}