{
  "type": "Feature",
  "properties": {
    "gn:admin1_code":"30.0",
    "gn:asciiname":"Dadigang",
    "gn:country_code":"CN",
    "gn:dem":24,
    "gn:feature_class":"P",
    "gn:feature_code":"PPL",
    "gn:name":"Dadigang",
    "gn:population":0,
    "gn:timezone":"Asia/Shanghai",
    "iso:country":"CN",
    "name:zho_x_preferred":[
        "\u5927\u5730\u5c97"
    ],
    "wof:name":"Dadigang",
    "wof:placetype":"locality"
},
  "geometry": {"coordinates":[112.32922000000001,22.33529],"type":"Point"}
}