{
  "type": "Feature",
  "properties": {
    "gn:admin1_code":"3.0",
    "gn:asciiname":"Getengzui",
    "gn:country_code":"CN",
    "gn:dem":332,
    "gn:feature_class":"P",
    "gn:feature_code":"PPL",
    "gn:name":"Getengzui",
    "gn:population":0,
    "gn:timezone":"Asia/Shanghai",
    "iso:country":"CN",
    "name:und_x_variant":[
        "\u845b\u85e4\u5480"
    ],
    "wof:name":"Getengzui",
    "wof:placetype":"locality"
},
  "geometry": {"coordinates":[116.04864000000001,26.18963],"type":"Point"}
}