{
  "type": "Feature",
  "properties": {
    "gn:admin1_code":"7.0",
    "gn:asciiname":"Fengmenling",
    "gn:country_code":"CN",
    "gn:dem":492,
    "gn:feature_class":"P",
    "gn:feature_code":"PPL",
    "gn:name":"Fengmenling",
    "gn:population":0,
    "gn:timezone":"Asia/Shanghai",
    "iso:country":"CN",
    "name:zho_x_preferred":[
        "\u67ab\u95e8\u5cad"
    ],
    "wof:name":"Fengmenling",
    "wof:placetype":"locality"
},
  "geometry": {"coordinates":[116.73421,26.83679],"type":"Point"}
}