{
  "type": "Feature",
  "properties": {
    "gn:admin1_code":"12",
    "gn:asciiname":"Songmuping",
    "gn:country_code":"CN",
    "gn:dem":248,
    "gn:feature_class":"P",
    "gn:feature_code":"PPLA4",
    "gn:name":"Songmuping",
    "gn:population":0,
    "gn:timezone":"Asia/Shanghai",
    "iso:country":"CN",
    "name:und_x_variant":[
        "Sung-mu-p\u2019ing",
        "Songmuping",
        "\u677e\u6728\u576a",
        "Songmuping Zhen",
        "\u677e\u6728\u576a\u9547"
    ],
    "wof:name":"Songmuping",
    "wof:placetype":"locality"
},
  "geometry": {"coordinates":[111.47902000000001,30.13323],"type":"Point"}
}