{
  "type": "Feature",
  "properties": {
    "gn:admin1_code":"9",
    "gn:asciiname":"Niuwangtao",
    "gn:country_code":"CN",
    "gn:dem":59,
    "gn:feature_class":"P",
    "gn:feature_code":"PPL",
    "gn:name":"Niuwangtao",
    "gn:population":0,
    "gn:timezone":"Asia/Shanghai",
    "iso:country":"CN",
    "name:zho_x_preferred":[
        "\u725b\u738b\u5957"
    ],
    "wof:name":"Niuwangtao",
    "wof:placetype":"locality"
},
  "geometry": {"coordinates":[115.01900000000001,34.4121],"type":"Point"}
}