{
  "type": "Feature",
  "properties": {
    "gn:admin1_code":"14.0",
    "gn:asciiname":"Gayicun",
    "gn:country_code":"CN",
    "gn:dem":3196,
    "gn:feature_class":"P",
    "gn:feature_code":"PPL",
    "gn:name":"Gayicun",
    "gn:population":0,
    "gn:timezone":"Asia/Urumqi",
    "iso:country":"CN",
    "name:zho_x_preferred":[
        "\u560e\u76ca\u6751"
    ],
    "wof:name":"Gayicun",
    "wof:placetype":"locality"
},
  "geometry": {"coordinates":[97.96930999999999,30.09403],"type":"Point"}
}