{
  "type": "Feature",
  "properties": {
    "gn:admin1_code":"29",
    "gn:asciiname":"Xiaojuedi",
    "gn:country_code":"CN",
    "gn:dem":2302,
    "gn:feature_class":"P",
    "gn:feature_code":"PPL",
    "gn:name":"Xiaojuedi",
    "gn:population":0,
    "gn:timezone":"Asia/Shanghai",
    "iso:country":"CN",
    "name:zho_x_preferred":[
        "\u5c0f\u53a5\u5730"
    ],
    "wof:name":"Xiaojuedi",
    "wof:placetype":"locality"
},
  "geometry": {"coordinates":[101.14700000000001,24.51],"type":"Point"}
}