{
  "type": "Feature",
  "properties": {
    "gn:admin1_code":"3.0",
    "gn:asciiname":"Bohucun",
    "gn:country_code":"CN",
    "gn:dem":37,
    "gn:feature_class":"P",
    "gn:feature_code":"PPL",
    "gn:name":"Bohucun",
    "gn:population":0,
    "gn:timezone":"Asia/Shanghai",
    "iso:country":"CN",
    "name:und_x_variant":[
        "\u6cca\u6e56\u6751"
    ],
    "wof:name":"Bohucun",
    "wof:placetype":"locality"
},
  "geometry": {"coordinates":[115.74081,28.57194],"type":"Point"}
}