{
  "type": "Feature",
  "properties": {
    "gn:admin1_code":"29.0",
    "gn:asciiname":"Lasike",
    "gn:country_code":"CN",
    "gn:dem":2564,
    "gn:feature_class":"P",
    "gn:feature_code":"PPL",
    "gn:name":"Lasike",
    "gn:population":0,
    "gn:timezone":"Asia/Shanghai",
    "iso:country":"CN",
    "name:zho_x_preferred":[
        "\u62c9\u65af\u79d1"
    ],
    "wof:name":"Lasike",
    "wof:placetype":"locality"
},
  "geometry": {"coordinates":[100.485,27.6712],"type":"Point"}
}