{
  "type": "Feature",
  "properties": {
    "gn:admin1_code":"22.0",
    "gn:asciiname":"Wujianfangcun",
    "gn:country_code":"CN",
    "gn:dem":1109,
    "gn:feature_class":"P",
    "gn:feature_code":"PPL",
    "gn:name":"Wujianfangcun",
    "gn:population":0,
    "gn:timezone":"Asia/Shanghai",
    "iso:country":"CN",
    "name:zho_x_preferred":[
        "\u4e94\u95f4\u623f\u6751"
    ],
    "wof:name":"Wujianfangcun",
    "wof:placetype":"locality"
},
  "geometry": {"coordinates":[115.92726,40.60632],"type":"Point"}
}