{
  "type": "Feature",
  "properties": {
    "gn:admin1_code":"11",
    "gn:asciiname":"Tinglu",
    "gn:country_code":"CN",
    "gn:dem":230,
    "gn:feature_class":"P",
    "gn:feature_code":"PPL",
    "gn:name":"Tinglu",
    "gn:population":0,
    "gn:timezone":"Asia/Shanghai",
    "iso:country":"CN",
    "name:zho_x_preferred":[
        "\u4ead\u8def"
    ],
    "wof:name":"Tinglu",
    "wof:placetype":"locality"
},
  "geometry": {"coordinates":[111.50399,25.27767],"type":"Point"}
}