{
  "type": "Feature",
  "properties": {
    "gn:admin1_code":"9.0",
    "gn:asciiname":"Siliqiao",
    "gn:country_code":"CN",
    "gn:dem":112,
    "gn:feature_class":"P",
    "gn:feature_code":"PPL",
    "gn:name":"Siliqiao",
    "gn:population":0,
    "gn:timezone":"Asia/Shanghai",
    "iso:country":"CN",
    "name:zho_x_preferred":[
        "\u56db\u91cc\u6865"
    ],
    "wof:name":"Siliqiao",
    "wof:placetype":"locality"
},
  "geometry": {"coordinates":[112.86326,32.70081],"type":"Point"}
}