{
  "type": "Feature",
  "properties": {
    "gn:admin1_code":"15.0",
    "gn:asciiname":"Luzhou",
    "gn:country_code":"CN",
    "gn:dem":1548,
    "gn:feature_class":"P",
    "gn:feature_code":"PPL",
    "gn:name":"Luzhou",
    "gn:population":0,
    "gn:timezone":"Asia/Shanghai",
    "iso:country":"CN",
    "name:zho_x_preferred":[
        "\u788c\u78a1"
    ],
    "wof:name":"Luzhou",
    "wof:placetype":"locality"
},
  "geometry": {"coordinates":[102.67400000000001,37.9014],"type":"Point"}
}