{
  "type": "Feature",
  "properties": {
    "gn:admin1_code":"32.0",
    "gn:asciiname":"Wangmu",
    "gn:country_code":"CN",
    "gn:dem":3071,
    "gn:feature_class":"P",
    "gn:feature_code":"PPL",
    "gn:name":"Wangmu",
    "gn:population":0,
    "gn:timezone":"Asia/Shanghai",
    "iso:country":"CN",
    "name:zho_x_preferred":[
        "\u738b\u6728"
    ],
    "wof:name":"Wangmu",
    "wof:placetype":"locality"
},
  "geometry": {"coordinates":[102.039,31.3319],"type":"Point"}
}