{
  "type": "Feature",
  "properties": {
    "gn:admin1_code":"18.0",
    "gn:asciiname":"Linzi",
    "gn:country_code":"CN",
    "gn:dem":948,
    "gn:feature_class":"P",
    "gn:feature_code":"PPL",
    "gn:name":"Linzi",
    "gn:population":0,
    "gn:timezone":"Asia/Shanghai",
    "iso:country":"CN",
    "name:ceb_x_preferred":[
        "Linzi"
    ],
    "name:swe_x_preferred":[
        "Linzi"
    ],
    "wof:name":"Linzi",
    "wof:placetype":"locality"
},
  "geometry": {"coordinates":[106.93361000000002,28.77861],"type":"Point"}
}