{
  "type": "Feature",
  "properties": {
    "gn:admin1_code":"16.0",
    "gn:asciiname":"Funing",
    "gn:country_code":"CN",
    "gn:dem":159,
    "gn:feature_class":"P",
    "gn:feature_code":"PPL",
    "gn:name":"Funing",
    "gn:population":0,
    "gn:timezone":"Asia/Shanghai",
    "iso:country":"CN",
    "name:ceb_x_preferred":[
        "Funing"
    ],
    "name:deu_x_preferred":[
        "Funing"
    ],
    "name:fra_x_preferred":[
        "Funing"
    ],
    "name:kor_x_preferred":[
        "\ud478\ub2dd\ud604"
    ],
    "name:nor_x_preferred":[
        "Funing"
    ],
    "name:rus_x_preferred":[
        "\u0424\u0443\u043d\u0438\u043d"
    ],
    "name:swe_x_preferred":[
        "Funing"
    ],
    "name:zho_x_preferred":[
        "\u5bcc\u5b81"
    ],
    "wof:name":"Funing",
    "wof:placetype":"locality"
},
  "geometry": {"coordinates":[111.072,23.1252],"type":"Point"}
}