{
  "type": "Feature",
  "properties": {
    "gn:admin1_code":"30",
    "gn:asciiname":"Dongyong",
    "gn:country_code":"CN",
    "gn:dem":3,
    "gn:feature_class":"P",
    "gn:feature_code":"PPLA4",
    "gn:name":"Dongyong",
    "gn:population":0,
    "gn:timezone":"Asia/Shanghai",
    "iso:country":"CN",
    "name:und_x_variant":[
        "\u4e1c\u6d8c",
        "Dongchong"
    ],
    "name:zho_x_preferred":[
        "\u4e1c\u6d8c"
    ],
    "wof:name":"Dongyong",
    "wof:placetype":"locality"
},
  "geometry": {"coordinates":[113.45577,22.88656],"type":"Point"}
}