{
  "type": "Feature",
  "properties": {
    "gn:admin1_code":"8.0",
    "gn:asciiname":"Zhaoguang Nongchang Sanfenchang",
    "gn:country_code":"CN",
    "gn:dem":309,
    "gn:feature_class":"P",
    "gn:feature_code":"PPLF",
    "gn:name":"Zhaoguang Nongchang Sanfenchang",
    "gn:population":0,
    "gn:timezone":"Asia/Shanghai",
    "iso:country":"CN",
    "name:zho_x_preferred":[
        "\u8d75\u5149\u519c\u573a\u4e09\u5206\u573a"
    ],
    "wof:name":"Zhaoguang Nongchang Sanfenchang",
    "wof:placetype":"locality"
},
  "geometry": {"coordinates":[126.88737999999999,48.02692],"type":"Point"}
}