{
  "type": "Feature",
  "properties": {
    "gn:admin1_code":"20.0",
    "gn:asciiname":"Gushanzi Erdui",
    "gn:country_code":"CN",
    "gn:dem":473,
    "gn:feature_class":"P",
    "gn:feature_code":"PPLF",
    "gn:name":"Gushanzi Erdui",
    "gn:population":0,
    "gn:timezone":"Asia/Shanghai",
    "iso:country":"CN",
    "name:zho_x_preferred":[
        "\u5b64\u5c71\u5b50\u4e8c\u961f"
    ],
    "wof:name":"Gushanzi Erdui",
    "wof:placetype":"locality"
},
  "geometry": {"coordinates":[122.14397,47.32982],"type":"Point"}
}