{
  "type": "Feature",
  "properties": {
    "gn:admin1_code":"29.0",
    "gn:asciiname":"Baipushan",
    "gn:country_code":"CN",
    "gn:dem":2150,
    "gn:feature_class":"P",
    "gn:feature_code":"PPL",
    "gn:name":"Baipushan",
    "gn:population":0,
    "gn:timezone":"Asia/Shanghai",
    "iso:country":"CN",
    "name:zho_x_preferred":[
        "\u767d\u666e\u5c71"
    ],
    "wof:name":"Baipushan",
    "wof:placetype":"locality"
},
  "geometry": {"coordinates":[101.38,25.0656],"type":"Point"}
}