{
  "type": "Feature",
  "properties": {
    "gn:admin1_code":"29.0",
    "gn:asciiname":"Qingxi",
    "gn:country_code":"CN",
    "gn:dem":1678,
    "gn:feature_class":"P",
    "gn:feature_code":"PPL",
    "gn:name":"Qingxi",
    "gn:population":0,
    "gn:timezone":"Asia/Shanghai",
    "iso:country":"CN",
    "name:zho_x_preferred":[
        "\u6e05\u6eaa"
    ],
    "wof:name":"Qingxi",
    "wof:placetype":"locality"
},
  "geometry": {"coordinates":[102.999,23.927],"type":"Point"}
}