{
  "type": "Feature",
  "properties": {
    "gn:admin1_code":"30.0",
    "gn:asciiname":"Zikengwei",
    "gn:country_code":"CN",
    "gn:dem":189,
    "gn:feature_class":"P",
    "gn:feature_code":"PPL",
    "gn:name":"Zikengwei",
    "gn:population":0,
    "gn:timezone":"Asia/Shanghai",
    "iso:country":"CN",
    "name:zho_x_preferred":[
        "\u81ea\u5751\u5c3e"
    ],
    "wof:name":"Zikengwei",
    "wof:placetype":"locality"
},
  "geometry": {"coordinates":[113.00221999999999,24.04306],"type":"Point"}
}