{
  "type": "Feature",
  "properties": {
    "gn:admin1_code":"29.0",
    "gn:asciiname":"Wasuoluoga",
    "gn:country_code":"CN",
    "gn:dem":2395,
    "gn:feature_class":"P",
    "gn:feature_code":"PPL",
    "gn:name":"Wasuoluoga",
    "gn:population":0,
    "gn:timezone":"Asia/Shanghai",
    "iso:country":"CN",
    "name:zho_x_preferred":[
        "\u5a03\u6240\u502e\u560e"
    ],
    "wof:name":"Wasuoluoga",
    "wof:placetype":"locality"
},
  "geometry": {"coordinates":[98.9706,27.5064],"type":"Point"}
}