{
  "type": "Feature",
  "properties": {
    "gn:admin1_code":"12.0",
    "gn:asciiname":"Changyugou",
    "gn:country_code":"CN",
    "gn:dem":138,
    "gn:feature_class":"P",
    "gn:feature_code":"PPL",
    "gn:name":"Changyugou",
    "gn:population":0,
    "gn:timezone":"Asia/Shanghai",
    "iso:country":"CN",
    "name:zho_x_preferred":[
        "\u957f\u5cea\u6c9f"
    ],
    "wof:name":"Changyugou",
    "wof:placetype":"locality"
},
  "geometry": {"coordinates":[111.5025,32.23036],"type":"Point"}
}