{
  "type": "Feature",
  "properties": {
    "gn:admin1_code":"20.0",
    "gn:asciiname":"Beigou Yidui",
    "gn:country_code":"CN",
    "gn:dem":393,
    "gn:feature_class":"P",
    "gn:feature_code":"PPLF",
    "gn:name":"Beigou Yidui",
    "gn:population":0,
    "gn:timezone":"Asia/Shanghai",
    "iso:country":"CN",
    "name:zho_x_preferred":[
        "\u5317\u6c9f\u4e00\u961f"
    ],
    "wof:name":"Beigou Yidui",
    "wof:placetype":"locality"
},
  "geometry": {"coordinates":[122.40557,48.16136],"type":"Point"}
}