{
  "type": "Feature",
  "properties": {
    "gn:admin1_code":"3.0",
    "gn:asciiname":"Yefang",
    "gn:country_code":"CN",
    "gn:dem":77,
    "gn:feature_class":"P",
    "gn:feature_code":"PPL",
    "gn:name":"Yefang",
    "gn:population":0,
    "gn:timezone":"Asia/Shanghai",
    "iso:country":"CN",
    "name:und_x_variant":[
        "\u53f6\u574a"
    ],
    "wof:name":"Yefang",
    "wof:placetype":"locality"
},
  "geometry": {"coordinates":[116.10236,27.6418],"type":"Point"}
}