{
  "type": "Feature",
  "properties": {
    "gn:admin1_code":"30",
    "gn:asciiname":"Wenci",
    "gn:country_code":"CN",
    "gn:dem":60,
    "gn:feature_class":"P",
    "gn:feature_code":"PPLA4",
    "gn:name":"Wenci",
    "gn:population":0,
    "gn:timezone":"Asia/Shanghai",
    "iso:country":"CN",
    "name:und_x_variant":[
        "\u6587\u7960",
        "Wenci",
        "Wenci Zhen",
        "\u6587\u7960\u9547"
    ],
    "wof:name":"Wenci",
    "wof:placetype":"locality"
},
  "geometry": {"coordinates":[116.67166,23.76993],"type":"Point"}
}