{
  "type": "Feature",
  "properties": {
    "gn:admin1_code":"10.0",
    "gn:asciiname":"Zhongtaishan",
    "gn:country_code":"CN",
    "gn:dem":1403,
    "gn:feature_class":"P",
    "gn:feature_code":"PPL",
    "gn:name":"Zhongtaishan",
    "gn:population":0,
    "gn:timezone":"Asia/Shanghai",
    "iso:country":"CN",
    "name:zho_x_preferred":[
        "\u4e2d\u53f0\u5c71"
    ],
    "wof:name":"Zhongtaishan",
    "wof:placetype":"locality"
},
  "geometry": {"coordinates":[113.81031000000002,38.712],"type":"Point"}
}