{
  "type": "Feature",
  "properties": {
    "gn:admin1_code":"19.0",
    "gn:asciiname":"Fenggoucun",
    "gn:country_code":"CN",
    "gn:dem":125,
    "gn:feature_class":"P",
    "gn:feature_code":"PPL",
    "gn:name":"Fenggoucun",
    "gn:population":0,
    "gn:timezone":"Asia/Shanghai",
    "iso:country":"CN",
    "name:zho_x_preferred":[
        "\u51af\u6c9f\u6751"
    ],
    "wof:name":"Fenggoucun",
    "wof:placetype":"locality"
},
  "geometry": {"coordinates":[122.634,40.6722],"type":"Point"}
}