{
  "type": "Feature",
  "properties": {
    "gn:admin1_code":"10",
    "gn:asciiname":"Xixizhai",
    "gn:country_code":"CN",
    "gn:dem":30,
    "gn:feature_class":"P",
    "gn:feature_code":"PPL",
    "gn:name":"Xixizhai",
    "gn:population":0,
    "gn:timezone":"Asia/Shanghai",
    "iso:country":"CN",
    "name:zho_x_preferred":[
        "\u897f\u90d7\u5be8"
    ],
    "wof:name":"Xixizhai",
    "wof:placetype":"locality"
},
  "geometry": {"coordinates":[114.929,37.1969],"type":"Point"}
}