{
  "type": "Feature",
  "properties": {
    "gn:admin1_code":"26.0",
    "gn:asciiname":"Yanyucun",
    "gn:country_code":"CN",
    "gn:dem":695,
    "gn:feature_class":"P",
    "gn:feature_code":"PPL",
    "gn:name":"Yanyucun",
    "gn:population":0,
    "gn:timezone":"Asia/Shanghai",
    "iso:country":"CN",
    "name:zho_x_preferred":[
        "\u5ca9\u5cea\u6751"
    ],
    "wof:name":"Yanyucun",
    "wof:placetype":"locality"
},
  "geometry": {"coordinates":[110.12456,33.74755],"type":"Point"}
}