{
  "type": "Feature",
  "properties": {
    "gn:admin1_code":"10",
    "gn:asciiname":"Daliying",
    "gn:country_code":"CN",
    "gn:dem":1355,
    "gn:feature_class":"P",
    "gn:feature_code":"PPL",
    "gn:name":"Daliying",
    "gn:population":0,
    "gn:timezone":"Asia/Shanghai",
    "iso:country":"CN",
    "name:zho_x_preferred":[
        "\u5927\u5229\u8425"
    ],
    "wof:name":"Daliying",
    "wof:placetype":"locality"
},
  "geometry": {"coordinates":[114.60975000000001,41.42728],"type":"Point"}
}