{
  "type": "Feature",
  "properties": {
    "gn:admin1_code":"4.0",
    "gn:asciiname":"Xiazhuang",
    "gn:country_code":"CN",
    "gn:dem":4,
    "gn:feature_class":"P",
    "gn:feature_code":"PPL",
    "gn:name":"Xiazhuang",
    "gn:population":0,
    "gn:timezone":"Asia/Shanghai",
    "iso:country":"CN",
    "name:deu_x_preferred":[
        "Xiazhuang"
    ],
    "name:zho_x_preferred":[
        "Xiazhuang"
    ],
    "name:zho_x_variant":[
        "\u590f\u5e84"
    ],
    "wof:name":"Xiazhuang",
    "wof:placetype":"locality"
},
  "geometry": {"coordinates":[121.26867,32.37167],"type":"Point"}
}