{
  "type": "Feature",
  "properties": {
    "gn:admin1_code":"2.0",
    "gn:asciiname":"Taoyuandi",
    "gn:country_code":"CN",
    "gn:dem":457,
    "gn:feature_class":"P",
    "gn:feature_code":"PPL",
    "gn:name":"Taoyuandi",
    "gn:population":0,
    "gn:timezone":"Asia/Shanghai",
    "iso:country":"CN",
    "name:zho_x_preferred":[
        "\u6843\u6e90\u5e95"
    ],
    "wof:name":"Taoyuandi",
    "wof:placetype":"locality"
},
  "geometry": {"coordinates":[120.72945,27.90351],"type":"Point"}
}