{
  "type": "Feature",
  "properties": {
    "gn:admin1_code":"12.0",
    "gn:asciiname":"Shigutai",
    "gn:country_code":"CN",
    "gn:dem":242,
    "gn:feature_class":"P",
    "gn:feature_code":"PPL",
    "gn:name":"Shigutai",
    "gn:population":0,
    "gn:timezone":"Asia/Shanghai",
    "iso:country":"CN",
    "name:zho_x_preferred":[
        "Shigutai"
    ],
    "name:zho_x_variant":[
        "\u5e08\u59d1\u53f0"
    ],
    "wof:name":"Shigutai",
    "wof:placetype":"locality"
},
  "geometry": {"coordinates":[114.688,29.55782],"type":"Point"}
}