{
  "type": "Feature",
  "properties": {
    "gn:admin1_code":"3.0",
    "gn:asciiname":"Caoshanwu",
    "gn:country_code":"CN",
    "gn:dem":83,
    "gn:feature_class":"P",
    "gn:feature_code":"PPL",
    "gn:name":"Caoshanwu",
    "gn:population":0,
    "gn:timezone":"Asia/Shanghai",
    "iso:country":"CN",
    "name:und_x_variant":[
        "\u66f9\u5c71\u575e"
    ],
    "wof:name":"Caoshanwu",
    "wof:placetype":"locality"
},
  "geometry": {"coordinates":[116.94924,29.52316],"type":"Point"}
}