{
  "type": "Feature",
  "properties": {
    "gn:admin1_code":"30",
    "gn:asciiname":"Zhusheke",
    "gn:country_code":"CN",
    "gn:dem":238,
    "gn:feature_class":"P",
    "gn:feature_code":"PPL",
    "gn:name":"Zhusheke",
    "gn:population":0,
    "gn:timezone":"Asia/Shanghai",
    "iso:country":"CN",
    "name:zho_x_preferred":[
        "\u6731\u8f0b\u7aa0"
    ],
    "wof:name":"Zhusheke",
    "wof:placetype":"locality"
},
  "geometry": {"coordinates":[116.71565,24.29618],"type":"Point"}
}