{
  "type": "Feature",
  "properties": {
    "gn:admin1_code":"31",
    "gn:asciiname":"Hongquan Nongchang",
    "gn:country_code":"CN",
    "gn:dem":96,
    "gn:feature_class":"P",
    "gn:feature_code":"PPLF",
    "gn:name":"Hongquan Nongchang",
    "gn:population":0,
    "gn:timezone":"Asia/Shanghai",
    "iso:country":"CN",
    "name:und_x_variant":[
        "\u7ea2\u6cc9\u519c\u573a"
    ],
    "wof:name":"Hongquan Nongchang",
    "wof:placetype":"locality"
},
  "geometry": {"coordinates":[108.9152,19.16096],"type":"Point"}
}