{
  "type": "Feature",
  "properties": {
    "gn:admin1_code":"11",
    "gn:asciiname":"Majia Dayuan",
    "gn:country_code":"CN",
    "gn:dem":237,
    "gn:feature_class":"P",
    "gn:feature_code":"PPL",
    "gn:name":"Majia Dayuan",
    "gn:population":0,
    "gn:timezone":"Asia/Shanghai",
    "iso:country":"CN",
    "name:zho_x_preferred":[
        "\u9a6c\u5bb6\u5927\u9662"
    ],
    "wof:name":"Majia Dayuan",
    "wof:placetype":"locality"
},
  "geometry": {"coordinates":[111.31896,27.16128],"type":"Point"}
}