{
  "type": "Feature",
  "properties": {
    "gn:admin1_code":"11.0",
    "gn:asciiname":"Wenguchong",
    "gn:country_code":"CN",
    "gn:dem":312,
    "gn:feature_class":"P",
    "gn:feature_code":"PPL",
    "gn:name":"Wenguchong",
    "gn:population":0,
    "gn:timezone":"Asia/Shanghai",
    "iso:country":"CN",
    "name:zho_x_preferred":[
        "\u6587\u53e4\u51b2"
    ],
    "wof:name":"Wenguchong",
    "wof:placetype":"locality"
},
  "geometry": {"coordinates":[109.98535,26.94216],"type":"Point"}
}