{
  "type": "Feature",
  "properties": {
    "gn:admin1_code":"2.0",
    "gn:asciiname":"Lilongxi",
    "gn:country_code":"CN",
    "gn:dem":179,
    "gn:feature_class":"P",
    "gn:feature_code":"PPL",
    "gn:name":"Lilongxi",
    "gn:population":0,
    "gn:timezone":"Asia/Shanghai",
    "iso:country":"CN",
    "name:zho_x_preferred":[
        "\u91cc\u9f99\u6eaa"
    ],
    "wof:name":"Lilongxi",
    "wof:placetype":"locality"
},
  "geometry": {"coordinates":[119.99611000000002,28.82189],"type":"Point"}
}