{
  "type": "Feature",
  "properties": {
    "gn:admin1_code":"32.0",
    "gn:asciiname":"Miaozitang",
    "gn:country_code":"CN",
    "gn:dem":1016,
    "gn:feature_class":"P",
    "gn:feature_code":"PPL",
    "gn:name":"Miaozitang",
    "gn:population":0,
    "gn:timezone":"Asia/Shanghai",
    "iso:country":"CN",
    "name:zho_x_preferred":[
        "\u5e99\u5b50\u5802"
    ],
    "wof:name":"Miaozitang",
    "wof:placetype":"locality"
},
  "geometry": {"coordinates":[103.334,29.6553],"type":"Point"}
}