{
  "type": "Feature",
  "properties": {
    "gn:admin1_code":"25",
    "gn:asciiname":"Xijia",
    "gn:country_code":"CN",
    "gn:dem":36,
    "gn:feature_class":"P",
    "gn:feature_code":"PPL",
    "gn:name":"Xijia",
    "gn:population":0,
    "gn:timezone":"Asia/Shanghai",
    "iso:country":"CN",
    "name:zho_x_preferred":[
        "\u897f\u8d3e"
    ],
    "wof:name":"Xijia",
    "wof:placetype":"locality"
},
  "geometry": {"coordinates":[116.095,36.6033],"type":"Point"}
}