{
  "type": "Feature",
  "properties": {
    "gn:admin1_code":"5.0",
    "gn:asciiname":"Rixincun",
    "gn:country_code":"CN",
    "gn:dem":136,
    "gn:feature_class":"P",
    "gn:feature_code":"PPL",
    "gn:name":"Rixincun",
    "gn:population":0,
    "gn:timezone":"Asia/Shanghai",
    "iso:country":"CN",
    "name:zho_x_preferred":[
        "\u65e5\u65b0\u6751"
    ],
    "wof:name":"Rixincun",
    "wof:placetype":"locality"
},
  "geometry": {"coordinates":[123.45663,43.92213],"type":"Point"}
}