{
  "type": "Feature",
  "properties": {
    "gn:admin1_code":"26.0",
    "gn:asciiname":"Zhahong",
    "gn:country_code":"CN",
    "gn:dem":1292,
    "gn:feature_class":"P",
    "gn:feature_code":"PPL",
    "gn:name":"Zhahong",
    "gn:population":0,
    "gn:timezone":"Asia/Shanghai",
    "iso:country":"CN",
    "name:und_x_variant":[
        "\u5953\u7ea2"
    ],
    "wof:name":"Zhahong",
    "wof:placetype":"locality"
},
  "geometry": {"coordinates":[107.98061,34.94663],"type":"Point"}
}