{
  "type": "Feature",
  "properties": {
    "gn:admin1_code":"07",
    "gn:asciiname":"Beiluoshe",
    "gn:country_code":"CN",
    "gn:dem":734,
    "gn:feature_class":"P",
    "gn:feature_code":"PPL",
    "gn:name":"Beiluoshe",
    "gn:population":0,
    "gn:timezone":"Asia/Shanghai",
    "iso:country":"CN",
    "name:zho_x_preferred":[
        "\u5317\u7f57\u7572"
    ],
    "wof:name":"Beiluoshe",
    "wof:placetype":"locality"
},
  "geometry": {"coordinates":[117.26876,25.66953],"type":"Point"}
}