{
  "type": "Feature",
  "properties": {
    "gn:admin1_code":"29.0",
    "gn:asciiname":"Sitoushan",
    "gn:country_code":"CN",
    "gn:dem":1561,
    "gn:feature_class":"P",
    "gn:feature_code":"PPL",
    "gn:name":"Sitoushan",
    "gn:population":0,
    "gn:timezone":"Asia/Shanghai",
    "iso:country":"CN",
    "name:zho_x_preferred":[
        "\u56db\u5934\u5c71"
    ],
    "wof:name":"Sitoushan",
    "wof:placetype":"locality"
},
  "geometry": {"coordinates":[101.461,23.2072],"type":"Point"}
}