{
  "type": "Feature",
  "properties": {
    "gn:admin1_code":"2.0",
    "gn:asciiname":"Wuchu",
    "gn:country_code":"CN",
    "gn:dem":852,
    "gn:feature_class":"P",
    "gn:feature_code":"PPL",
    "gn:name":"Wuchu",
    "gn:population":0,
    "gn:timezone":"Asia/Shanghai",
    "iso:country":"CN",
    "name:zho_x_preferred":[
        "\u5434\u5904"
    ],
    "wof:name":"Wuchu",
    "wof:placetype":"locality"
},
  "geometry": {"coordinates":[119.03155,28.40186],"type":"Point"}
}