{
  "type": "Feature",
  "properties": {
    "gn:admin1_code":"12.0",
    "gn:asciiname":"Wangjiafan",
    "gn:country_code":"CN",
    "gn:dem":82,
    "gn:feature_class":"P",
    "gn:feature_code":"PPL",
    "gn:name":"Wangjiafan",
    "gn:population":0,
    "gn:timezone":"Asia/Shanghai",
    "iso:country":"CN",
    "name:zho_x_preferred":[
        "Wangjiafan"
    ],
    "name:zho_x_variant":[
        "\u6c6a\u5bb6\u7548"
    ],
    "wof:name":"Wangjiafan",
    "wof:placetype":"locality"
},
  "geometry": {"coordinates":[114.63694,29.52099],"type":"Point"}
}