{
  "type": "Feature",
  "properties": {
    "gn:admin1_code":"8.0",
    "gn:asciiname":"Xinsheng Sandui",
    "gn:country_code":"CN",
    "gn:dem":93,
    "gn:feature_class":"P",
    "gn:feature_code":"PPLF",
    "gn:name":"Xinsheng Sandui",
    "gn:population":0,
    "gn:timezone":"Asia/Shanghai",
    "iso:country":"CN",
    "name:zho_x_preferred":[
        "\u65b0\u751f\u4e09\u961f"
    ],
    "wof:name":"Xinsheng Sandui",
    "wof:placetype":"locality"
},
  "geometry": {"coordinates":[132.26122000000001,45.44127],"type":"Point"}
}