{
  "type": "Feature",
  "properties": {
    "gn:admin1_code":"16.0",
    "gn:asciiname":"Danri",
    "gn:country_code":"CN",
    "gn:dem":320,
    "gn:feature_class":"P",
    "gn:feature_code":"PPL",
    "gn:name":"Danri",
    "gn:population":0,
    "gn:timezone":"Asia/Shanghai",
    "iso:country":"CN",
    "name:zho_x_preferred":[
        "\u4e39\u65e5"
    ],
    "wof:name":"Danri",
    "wof:placetype":"locality"
},
  "geometry": {"coordinates":[107.93000000000001,23.8603],"type":"Point"}
}