{
  "type": "Feature",
  "properties": {
    "gn:admin1_code":"29.0",
    "gn:asciiname":"Yangjiagou",
    "gn:country_code":"CN",
    "gn:dem":1698,
    "gn:feature_class":"P",
    "gn:feature_code":"PPL",
    "gn:name":"Yangjiagou",
    "gn:population":0,
    "gn:timezone":"Asia/Shanghai",
    "iso:country":"CN",
    "name:zho_x_preferred":[
        "\u6768\u5bb6\u6c9f"
    ],
    "wof:name":"Yangjiagou",
    "wof:placetype":"locality"
},
  "geometry": {"coordinates":[104.655,27.5078],"type":"Point"}
}