{
  "type": "Feature",
  "properties": {
    "gn:admin1_code":"13",
    "gn:asciiname":"Bokesaimu",
    "gn:country_code":"CN",
    "gn:dem":1098,
    "gn:feature_class":"P",
    "gn:feature_code":"PPL",
    "gn:name":"Bokesaimu",
    "gn:population":0,
    "gn:timezone":"Asia/Shanghai",
    "iso:country":"CN",
    "name:und_x_variant":[
        "\u535a\u514b\u8d5b\u6728"
    ],
    "wof:name":"Bokesaimu",
    "wof:placetype":"locality"
},
  "geometry": {"coordinates":[80.86839999999999,39.47432],"type":"Point"}
}