{
  "type": "Feature",
  "properties": {
    "gn:admin1_code":"25.0",
    "gn:asciiname":"Maiqiu",
    "gn:country_code":"CN",
    "gn:dem":13,
    "gn:feature_class":"P",
    "gn:feature_code":"PPL",
    "gn:name":"Maiqiu",
    "gn:population":0,
    "gn:timezone":"Asia/Shanghai",
    "iso:country":"CN",
    "name:zho_x_preferred":[
        "\u9ea6\u4e18"
    ],
    "wof:name":"Maiqiu",
    "wof:placetype":"locality"
},
  "geometry": {"coordinates":[120.06722000000001,36.47622],"type":"Point"}
}