{
  "type": "Feature",
  "properties": {
    "gn:admin1_code":"26.0",
    "gn:asciiname":"Wanggouta",
    "gn:country_code":"CN",
    "gn:dem":1234,
    "gn:feature_class":"P",
    "gn:feature_code":"PPL",
    "gn:name":"Wanggouta",
    "gn:population":0,
    "gn:timezone":"Asia/Shanghai",
    "iso:country":"CN",
    "name:zho_x_preferred":[
        "\u738b\u6c9f\u584c"
    ],
    "wof:name":"Wanggouta",
    "wof:placetype":"locality"
},
  "geometry": {"coordinates":[109.20520999999999,36.57675],"type":"Point"}
}