{
  "type": "Feature",
  "properties": {
    "gn:admin1_code":"5.0",
    "gn:asciiname":"Chahe Zuizi",
    "gn:country_code":"CN",
    "gn:dem":217,
    "gn:feature_class":"P",
    "gn:feature_code":"PPL",
    "gn:name":"Chahe Zuizi",
    "gn:population":0,
    "gn:timezone":"Asia/Shanghai",
    "iso:country":"CN",
    "name:zho_x_preferred":[
        "\u5c94\u6cb3\u5480\u5b50"
    ],
    "wof:name":"Chahe Zuizi",
    "wof:placetype":"locality"
},
  "geometry": {"coordinates":[126.77733000000001,44.47856],"type":"Point"}
}