{
  "type": "Feature",
  "properties": {
    "gn:admin1_code":"12.0",
    "gn:asciiname":"Xigouya",
    "gn:country_code":"CN",
    "gn:dem":497,
    "gn:feature_class":"P",
    "gn:feature_code":"PPL",
    "gn:name":"Xigouya",
    "gn:population":0,
    "gn:timezone":"Asia/Shanghai",
    "iso:country":"CN",
    "name:zho_x_preferred":[
        "\u897f\u6c9f\u57ad"
    ],
    "wof:name":"Xigouya",
    "wof:placetype":"locality"
},
  "geometry": {"coordinates":[111.34023999999999,32.07959],"type":"Point"}
}