{
  "type": "Feature",
  "properties": {
    "gn:admin1_code":"19.0",
    "gn:asciiname":"Shajiagou",
    "gn:country_code":"CN",
    "gn:dem":210,
    "gn:feature_class":"P",
    "gn:feature_code":"PPL",
    "gn:name":"Shajiagou",
    "gn:population":0,
    "gn:timezone":"Asia/Shanghai",
    "iso:country":"CN",
    "name:und_x_variant":[
        "\u6c99\u5bb6\u6c9f"
    ],
    "wof:name":"Shajiagou",
    "wof:placetype":"locality"
},
  "geometry": {"coordinates":[122.76994000000001,40.57686],"type":"Point"}
}