{
  "type": "Feature",
  "properties": {
    "gn:admin1_code":"5.0",
    "gn:asciiname":"Dongnan Tuizijing",
    "gn:country_code":"CN",
    "gn:dem":152,
    "gn:feature_class":"P",
    "gn:feature_code":"PPL",
    "gn:name":"Dongnan Tuizijing",
    "gn:population":0,
    "gn:timezone":"Asia/Shanghai",
    "iso:country":"CN",
    "name:zho_x_preferred":[
        "\u4e1c\u5357\u9000\u5b57\u4e95"
    ],
    "wof:name":"Dongnan Tuizijing",
    "wof:placetype":"locality"
},
  "geometry": {"coordinates":[124.01985999999999,44.75639],"type":"Point"}
}