{
  "type": "Feature",
  "properties": {
    "gn:admin1_code":"15.0",
    "gn:asciiname":"Baimashi",
    "gn:country_code":"CN",
    "gn:dem":2030,
    "gn:feature_class":"P",
    "gn:feature_code":"PPL",
    "gn:name":"Baimashi",
    "gn:population":0,
    "gn:timezone":"Asia/Shanghai",
    "iso:country":"CN",
    "name:und_x_variant":[
        "Baimajie"
    ],
    "name:zho_x_preferred":[
        "\u767d\u9a6c\u77f3"
    ],
    "name:zho_x_variant":[
        "\u767d\u9a6c\u8857"
    ],
    "wof:name":"Baimashi",
    "wof:placetype":"locality"
},
  "geometry": {"coordinates":[104.989,33.61199999999999],"type":"Point"}
}