{
  "type": "Feature",
  "properties": {
    "gn:admin1_code":"19.0",
    "gn:asciiname":"Dongfangjiatun",
    "gn:country_code":"CN",
    "gn:dem":115,
    "gn:feature_class":"P",
    "gn:feature_code":"PPL",
    "gn:name":"Dongfangjiatun",
    "gn:population":0,
    "gn:timezone":"Asia/Shanghai",
    "iso:country":"CN",
    "name:zho_x_preferred":[
        "\u4e1c\u65b9\u5bb6\u5c6f"
    ],
    "wof:name":"Dongfangjiatun",
    "wof:placetype":"locality"
},
  "geometry": {"coordinates":[123.71299999999999,42.7494],"type":"Point"}
}