{
  "type": "Feature",
  "properties": {
    "gn:admin1_code":"18.0",
    "gn:asciiname":"Gudong",
    "gn:country_code":"CN",
    "gn:dem":489,
    "gn:feature_class":"P",
    "gn:feature_code":"PPL",
    "gn:name":"Gudong",
    "gn:population":0,
    "gn:timezone":"Asia/Shanghai",
    "iso:country":"CN",
    "name:zho_x_preferred":[
        "\u59d1\u4e1c"
    ],
    "wof:name":"Gudong",
    "wof:placetype":"locality"
},
  "geometry": {"coordinates":[108.577,25.7596],"type":"Point"}
}