{
  "type": "Feature",
  "properties": {
    "gn:admin1_code":"12.0",
    "gn:asciiname":"Tizipo",
    "gn:country_code":"CN",
    "gn:dem":122,
    "gn:feature_class":"P",
    "gn:feature_code":"PPL",
    "gn:name":"Tizipo",
    "gn:population":0,
    "gn:timezone":"Asia/Shanghai",
    "iso:country":"CN",
    "name:zho_x_preferred":[
        "\u68af\u5b50\u5761"
    ],
    "wof:name":"Tizipo",
    "wof:placetype":"locality"
},
  "geometry": {"coordinates":[113.51502000000001,31.85871],"type":"Point"}
}