{
  "type": "Feature",
  "properties": {
    "gn:admin1_code":"31.0",
    "gn:asciiname":"Lequn",
    "gn:country_code":"CN",
    "gn:dem":37,
    "gn:feature_class":"P",
    "gn:feature_code":"PPL",
    "gn:name":"Lequn",
    "gn:population":0,
    "gn:timezone":"Asia/Shanghai",
    "iso:country":"CN",
    "name:zho_x_preferred":[
        "Lequn"
    ],
    "name:zho_x_variant":[
        "\u4e50\u7fa4"
    ],
    "wof:name":"Lequn",
    "wof:placetype":"locality"
},
  "geometry": {"coordinates":[110.62356,19.81181],"type":"Point"}
}