{
  "type": "Feature",
  "properties": {
    "gn:admin1_code":"7.0",
    "gn:asciiname":"Xiedun",
    "gn:country_code":"CN",
    "gn:dem":534,
    "gn:feature_class":"P",
    "gn:feature_code":"PPL",
    "gn:name":"Xiedun",
    "gn:population":0,
    "gn:timezone":"Asia/Shanghai",
    "iso:country":"CN",
    "name:zho_x_preferred":[
        "\u8c22\u58a9"
    ],
    "wof:name":"Xiedun",
    "wof:placetype":"locality"
},
  "geometry": {"coordinates":[119.84284,27.03838],"type":"Point"}
}