{
  "type": "Feature",
  "properties": {
    "gn:admin1_code":"15.0",
    "gn:asciiname":"Pingdao",
    "gn:country_code":"CN",
    "gn:dem":1804,
    "gn:feature_class":"P",
    "gn:feature_code":"PPL",
    "gn:name":"Pingdao",
    "gn:population":0,
    "gn:timezone":"Asia/Shanghai",
    "iso:country":"CN",
    "name:zho_x_preferred":[
        "\u5e73\u9053"
    ],
    "wof:name":"Pingdao",
    "wof:placetype":"locality"
},
  "geometry": {"coordinates":[105.286,34.6591],"type":"Point"}
}