{
  "type": "Feature",
  "properties": {
    "gn:admin1_code":"7.0",
    "gn:asciiname":"Xiayaofan",
    "gn:country_code":"CN",
    "gn:dem":272,
    "gn:feature_class":"P",
    "gn:feature_code":"PPL",
    "gn:name":"Xiayaofan",
    "gn:population":0,
    "gn:timezone":"Asia/Shanghai",
    "iso:country":"CN",
    "name:und_x_variant":[
        "\u4e0b\u836f\u8303"
    ],
    "name:zho_x_preferred":[
        "\u4e0b\u836f\u8303"
    ],
    "wof:name":"Xiayaofan",
    "wof:placetype":"locality"
},
  "geometry": {"coordinates":[116.8845,26.0843],"type":"Point"}
}