{
  "type": "Feature",
  "properties": {
    "gn:admin1_code":"12.0",
    "gn:asciiname":"Ba'erwan",
    "gn:country_code":"CN",
    "gn:dem":241,
    "gn:feature_class":"P",
    "gn:feature_code":"PPL",
    "gn:name":"Ba\u2019erwan",
    "gn:population":0,
    "gn:timezone":"Asia/Shanghai",
    "iso:country":"CN",
    "name:und_x_variant":[
        "Ba\u2019erwan"
    ],
    "name:zho_x_preferred":[
        "\u516b\u513f\u6e7e"
    ],
    "wof:name":"Ba'erwan",
    "wof:placetype":"locality"
},
  "geometry": {"coordinates":[111.88291,31.37909],"type":"Point"}
}