{
  "type": "Feature",
  "properties": {
    "gn:admin1_code":"26",
    "gn:asciiname":"Donghekou",
    "gn:country_code":"CN",
    "gn:dem":925,
    "gn:feature_class":"P",
    "gn:feature_code":"PPL",
    "gn:name":"Donghekou",
    "gn:population":0,
    "gn:timezone":"Asia/Shanghai",
    "iso:country":"CN",
    "wof:name":"Donghekou",
    "wof:placetype":"locality"
},
  "geometry": {"coordinates":[108.53389,33.24389],"type":"Point"}
}