{
  "type": "Feature",
  "properties": {
    "gn:admin1_code":"31.0",
    "gn:asciiname":"Xin'an",
    "gn:country_code":"CN",
    "gn:dem":316,
    "gn:feature_class":"P",
    "gn:feature_code":"PPL",
    "gn:name":"Xin\u2019an",
    "gn:population":0,
    "gn:timezone":"Asia/Shanghai",
    "iso:country":"CN",
    "name:zho_x_preferred":[
        "Xin\u2019an"
    ],
    "name:zho_x_variant":[
        "\u65b0\u5b89"
    ],
    "wof:name":"Xin'an",
    "wof:placetype":"locality"
},
  "geometry": {"coordinates":[108.94389,18.62632],"type":"Point"}
}