{
  "type": "Feature",
  "properties": {
    "gn:admin1_code":"18.0",
    "gn:asciiname":"Yunfeng",
    "gn:country_code":"CN",
    "gn:dem":983,
    "gn:feature_class":"P",
    "gn:feature_code":"PPL",
    "gn:name":"Yunfeng",
    "gn:population":0,
    "gn:timezone":"Asia/Shanghai",
    "iso:country":"CN",
    "name:zho_x_preferred":[
        "\u4e91\u4e30"
    ],
    "wof:name":"Yunfeng",
    "wof:placetype":"locality"
},
  "geometry": {"coordinates":[107.51027999999999,28.73833],"type":"Point"}
}