{
  "type": "Feature",
  "properties": {
    "gn:admin1_code":"4.0",
    "gn:asciiname":"Xiaowenzhuang",
    "gn:country_code":"CN",
    "gn:dem":26,
    "gn:feature_class":"P",
    "gn:feature_code":"PPL",
    "gn:name":"Xiaowenzhuang",
    "gn:population":0,
    "gn:timezone":"Asia/Shanghai",
    "iso:country":"CN",
    "name:zho_x_preferred":[
        "\u5c0f\u6e29\u5e84"
    ],
    "wof:name":"Xiaowenzhuang",
    "wof:placetype":"locality"
},
  "geometry": {"coordinates":[118.80247,32.95505],"type":"Point"}
}