{
  "type": "Feature",
  "properties": {
    "gn:admin1_code":"1.0",
    "gn:asciiname":"Qixingcun",
    "gn:country_code":"CN",
    "gn:dem":56,
    "gn:feature_class":"P",
    "gn:feature_code":"PPL",
    "gn:name":"Qixingcun",
    "gn:population":0,
    "gn:timezone":"Asia/Shanghai",
    "iso:country":"CN",
    "name:zho_x_preferred":[
        "\u4e03\u661f\u6751"
    ],
    "wof:name":"Qixingcun",
    "wof:placetype":"locality"
},
  "geometry": {"coordinates":[116.60247,31.67924],"type":"Point"}
}