{
  "type": "Feature",
  "properties": {
    "gn:admin1_code":"10",
    "gn:asciiname":"Guluying",
    "gn:country_code":"CN",
    "gn:dem":61,
    "gn:feature_class":"P",
    "gn:feature_code":"PPL",
    "gn:name":"Guluying",
    "gn:population":0,
    "gn:timezone":"Asia/Shanghai",
    "iso:country":"CN",
    "name:zho_x_preferred":[
        "\u53e4\u9c81\u8425"
    ],
    "wof:name":"Guluying",
    "wof:placetype":"locality"
},
  "geometry": {"coordinates":[114.589,37.4275],"type":"Point"}
}