{
  "type": "Feature",
  "properties": {
    "gn:admin1_code":"26.0",
    "gn:asciiname":"Dangchuan",
    "gn:country_code":"CN",
    "gn:dem":369,
    "gn:feature_class":"P",
    "gn:feature_code":"PPL",
    "gn:name":"Dangchuan",
    "gn:population":0,
    "gn:timezone":"Asia/Shanghai",
    "iso:country":"CN",
    "name:zho_x_preferred":[
        "\u515a\u5ddd"
    ],
    "wof:name":"Dangchuan",
    "wof:placetype":"locality"
},
  "geometry": {"coordinates":[109.78843999999999,34.83472],"type":"Point"}
}