{
  "type": "Feature",
  "properties": {
    "gn:admin1_code":"28",
    "gn:asciiname":"Beitang",
    "gn:cc2":"CN",
    "gn:country_code":"CN",
    "gn:dem":4,
    "gn:feature_class":"P",
    "gn:feature_code":"PPL",
    "gn:name":"Beitang",
    "gn:population":0,
    "gn:timezone":"Asia/Shanghai",
    "iso:country":"CN",
    "name:ind_x_preferred":[
        "Subdistrik Beitang"
    ],
    "name:rus_x_preferred":[
        "\u0411\u044d\u0439\u0442\u0430\u043d"
    ],
    "name:und_x_variant":[
        "Pei-t\u2019ang",
        "Pehtang",
        "Pe-tang",
        "Beitang"
    ],
    "name:zho_x_preferred":[
        "\u5317\u5858\u8857\u9053"
    ],
    "wof:name":"Beitang",
    "wof:placetype":"locality"
},
  "geometry": {"coordinates":[117.70722000000001,39.10333],"type":"Point"}
}