{
  "type": "Feature",
  "properties": {
    "gn:admin1_code":"1.0",
    "gn:asciiname":"Suifengcun",
    "gn:country_code":"CN",
    "gn:dem":7,
    "gn:feature_class":"P",
    "gn:feature_code":"PPL",
    "gn:name":"Suifengcun",
    "gn:population":0,
    "gn:timezone":"Asia/Shanghai",
    "iso:country":"CN",
    "name:zho_x_preferred":[
        "\u5c81\u4e30\u6751"
    ],
    "wof:name":"Suifengcun",
    "wof:placetype":"locality"
},
  "geometry": {"coordinates":[117.79338,31.17685],"type":"Point"}
}