{
  "type": "Feature",
  "properties": {
    "gn:admin1_code":"30",
    "gn:asciiname":"Hetianpo",
    "gn:country_code":"CN",
    "gn:dem":48,
    "gn:feature_class":"P",
    "gn:feature_code":"PPL",
    "gn:name":"Hetianpo",
    "gn:population":0,
    "gn:timezone":"Asia/Urumqi",
    "iso:country":"CN",
    "name:zho_x_preferred":[
        "\u9e64\u7530\u5761"
    ],
    "wof:name":"Hetianpo",
    "wof:placetype":"locality"
},
  "geometry": {"coordinates":[110.43615,21.8942],"type":"Point"}
}