{
  "type": "Feature",
  "properties": {
    "gn:admin1_code":"26.0",
    "gn:asciiname":"Zhangyinzicun",
    "gn:country_code":"CN",
    "gn:dem":1412,
    "gn:feature_class":"P",
    "gn:feature_code":"PPL",
    "gn:name":"Zhangyinzicun",
    "gn:population":0,
    "gn:timezone":"Asia/Shanghai",
    "iso:country":"CN",
    "name:zho_x_preferred":[
        "\u5f20\u7aa8\u5b50\u6751"
    ],
    "wof:name":"Zhangyinzicun",
    "wof:placetype":"locality"
},
  "geometry": {"coordinates":[107.83786000000001,37.52211],"type":"Point"}
}