{
  "type": "Feature",
  "properties": {
    "gn:admin1_code":"8.0",
    "gn:asciiname":"Changrongcun",
    "gn:country_code":"CN",
    "gn:dem":136,
    "gn:feature_class":"P",
    "gn:feature_code":"PPL",
    "gn:name":"Changrongcun",
    "gn:population":0,
    "gn:timezone":"Asia/Shanghai",
    "iso:country":"CN",
    "name:zho_x_preferred":[
        "\u957f\u8363\u6751"
    ],
    "wof:name":"Changrongcun",
    "wof:placetype":"locality"
},
  "geometry": {"coordinates":[126.47787,46.35838],"type":"Point"}
}