{
  "type": "Feature",
  "properties": {
    "gn:admin1_code":"31",
    "gn:asciiname":"Niugentian",
    "gn:country_code":"CN",
    "gn:dem":148,
    "gn:feature_class":"P",
    "gn:feature_code":"PPL",
    "gn:name":"Niugentian",
    "gn:population":0,
    "gn:timezone":"Asia/Shanghai",
    "iso:country":"CN",
    "name:und_x_variant":[
        "\u725b\u6839\u7530"
    ],
    "wof:name":"Niugentian",
    "wof:placetype":"locality"
},
  "geometry": {"coordinates":[110.11682,18.91752],"type":"Point"}
}