{
  "type": "Feature",
  "properties": {
    "gn:admin1_code":"24.0",
    "gn:asciiname":"Jinzhuang",
    "gn:country_code":"CN",
    "gn:dem":1026,
    "gn:feature_class":"P",
    "gn:feature_code":"PPL",
    "gn:name":"Jinzhuang",
    "gn:population":0,
    "gn:timezone":"Asia/Shanghai",
    "iso:country":"CN",
    "name:und_x_variant":[
        "\u664b\u5e84"
    ],
    "wof:name":"Jinzhuang",
    "wof:placetype":"locality"
},
  "geometry": {"coordinates":[113.15633,39.44239],"type":"Point"}
}