{
  "type": "Feature",
  "properties": {
    "gn:admin1_code":"12",
    "gn:asciiname":"Taiping",
    "gn:country_code":"CN",
    "gn:dem":143,
    "gn:feature_class":"P",
    "gn:feature_code":"PPLA4",
    "gn:name":"Taiping",
    "gn:population":0,
    "gn:timezone":"Asia/Shanghai",
    "iso:country":"CN",
    "name:und_x_variant":[
        "T\u2019ai-p\u2019ing-chen",
        "Taiping",
        "Taiping Zhen"
    ],
    "name:zho_x_preferred":[
        "\u592a\u5e73"
    ],
    "name:zho_x_variant":[
        "\u592a\u5e73\u9547"
    ],
    "wof:name":"Taiping",
    "wof:placetype":"locality"
},
  "geometry": {"coordinates":[112.75684,32.28665],"type":"Point"}
}