{
  "type": "Feature",
  "properties": {
    "gn:admin1_code":"24.0",
    "gn:asciiname":"Fujiayan",
    "gn:country_code":"CN",
    "gn:dem":1560,
    "gn:feature_class":"P",
    "gn:feature_code":"PPL",
    "gn:name":"Fujiayan",
    "gn:population":0,
    "gn:timezone":"Asia/Shanghai",
    "iso:country":"CN",
    "name:zho_x_preferred":[
        "\u5bcc\u5bb6\u5895"
    ],
    "wof:name":"Fujiayan",
    "wof:placetype":"locality"
},
  "geometry": {"coordinates":[111.71733999999999,38.92108],"type":"Point"}
}