{
  "type": "Feature",
  "properties": {
    "gn:admin1_code":"3.0",
    "gn:asciiname":"Ruanjiafang",
    "gn:country_code":"CN",
    "gn:dem":212,
    "gn:feature_class":"P",
    "gn:feature_code":"PPL",
    "gn:name":"Ruanjiafang",
    "gn:population":0,
    "gn:timezone":"Asia/Shanghai",
    "iso:country":"CN",
    "name:und_x_variant":[
        "\u962e\u5bb6\u574a"
    ],
    "wof:name":"Ruanjiafang",
    "wof:placetype":"locality"
},
  "geometry": {"coordinates":[116.09357,25.98333],"type":"Point"}
}