{
  "type": "Feature",
  "properties": {
    "gn:admin1_code":"11.0",
    "gn:asciiname":"Hefeng",
    "gn:country_code":"CN",
    "gn:dem":428,
    "gn:feature_class":"P",
    "gn:feature_code":"PPL",
    "gn:name":"Hefeng",
    "gn:population":0,
    "gn:timezone":"Asia/Shanghai",
    "iso:country":"CN",
    "name:zho_x_preferred":[
        "Hefeng"
    ],
    "name:zho_x_variant":[
        "\u548c\u4e30"
    ],
    "wof:name":"Hefeng",
    "wof:placetype":"locality"
},
  "geometry": {"coordinates":[114.09604,28.70283],"type":"Point"}
}