{
  "type": "Feature",
  "properties": {
    "gn:admin1_code":"11.0",
    "gn:asciiname":"Malie",
    "gn:country_code":"CN",
    "gn:dem":671,
    "gn:feature_class":"P",
    "gn:feature_code":"PPL",
    "gn:name":"Malie",
    "gn:population":0,
    "gn:timezone":"Asia/Shanghai",
    "iso:country":"CN",
    "name:ceb_x_preferred":[
        "Malie"
    ],
    "name:pol_x_preferred":[
        "Malie"
    ],
    "name:zho_x_preferred":[
        "\u9ebb\u52a3"
    ],
    "wof:name":"Malie",
    "wof:placetype":"locality"
},
  "geometry": {"coordinates":[109.30924,28.32244],"type":"Point"}
}