{
  "type": "Feature",
  "properties": {
    "gn:admin1_code":"32.0",
    "gn:asciiname":"Tang'erkan",
    "gn:country_code":"CN",
    "gn:dem":466,
    "gn:feature_class":"P",
    "gn:feature_code":"PPL",
    "gn:name":"Tang\u2019erkan",
    "gn:population":0,
    "gn:timezone":"Asia/Shanghai",
    "iso:country":"CN",
    "name:zho_x_preferred":[
        "\u5858\u54a1\u574e"
    ],
    "name:zho_x_variant":[
        "Tang\u2019erkan"
    ],
    "wof:name":"Tang'erkan",
    "wof:placetype":"locality"
},
  "geometry": {"coordinates":[103.56295,29.48671],"type":"Point"}
}