{
  "type": "Feature",
  "properties": {
    "gn:admin1_code":"11",
    "gn:asciiname":"Pushang",
    "gn:country_code":"CN",
    "gn:dem":276,
    "gn:feature_class":"P",
    "gn:feature_code":"PPL",
    "gn:name":"Pushang",
    "gn:population":0,
    "gn:timezone":"Asia/Shanghai",
    "iso:country":"CN",
    "name:und_x_variant":[
        "\u94fa\u4e0a",
        "Pushang"
    ],
    "wof:name":"Pushang",
    "wof:placetype":"locality"
},
  "geometry": {"coordinates":[111.9675,25.47472],"type":"Point"}
}