{
  "type": "Feature",
  "properties": {
    "gn:admin1_code":"02",
    "gn:asciiname":"Zhengyuancun",
    "gn:country_code":"CN",
    "gn:dem":397,
    "gn:feature_class":"P",
    "gn:feature_code":"PPL",
    "gn:name":"Zhengyuancun",
    "gn:population":0,
    "gn:timezone":"Asia/Shanghai",
    "iso:country":"CN",
    "name:und_x_variant":[
        "Ch\u2019en-y\u00fcan-ts\u2019un",
        "Zhengyuan",
        "Zhengyuancun"
    ],
    "name:zho_x_preferred":[
        "\u90d1\u6e90"
    ],
    "name:zho_x_variant":[
        "\u90d1\u6e90\u6751"
    ],
    "wof:name":"Zhengyuancun",
    "wof:placetype":"locality"
},
  "geometry": {"coordinates":[120.96276,28.38936],"type":"Point"}
}