{
  "type": "Feature",
  "properties": {
    "gn:admin1_code":"29.0",
    "gn:asciiname":"Anbo",
    "gn:country_code":"CN",
    "gn:dem":1442,
    "gn:feature_class":"P",
    "gn:feature_code":"PPL",
    "gn:name":"Anbo",
    "gn:population":0,
    "gn:timezone":"Asia/Shanghai",
    "iso:country":"CN",
    "name:zho_x_preferred":[
        "\u5b89\u535a"
    ],
    "wof:name":"Anbo",
    "wof:placetype":"locality"
},
  "geometry": {"coordinates":[99.58710000000001,24.4413],"type":"Point"}
}