{
  "type": "Feature",
  "properties": {
    "gn:admin1_code":"9.0",
    "gn:asciiname":"Luodatang",
    "gn:country_code":"CN",
    "gn:dem":63,
    "gn:feature_class":"P",
    "gn:feature_code":"PPL",
    "gn:name":"Luodatang",
    "gn:population":0,
    "gn:timezone":"Asia/Shanghai",
    "iso:country":"CN",
    "name:zho_x_preferred":[
        "\u7f57\u5927\u5858"
    ],
    "wof:name":"Luodatang",
    "wof:placetype":"locality"
},
  "geometry": {"coordinates":[115.09676,32.06865999999999],"type":"Point"}
}