{
  "type": "Feature",
  "properties": {
    "gn:admin1_code":"29.0",
    "gn:asciiname":"Manmai Xiazhai",
    "gn:country_code":"CN",
    "gn:dem":894,
    "gn:feature_class":"P",
    "gn:feature_code":"PPL",
    "gn:name":"Manmai Xiazhai",
    "gn:population":0,
    "gn:timezone":"Asia/Shanghai",
    "iso:country":"CN",
    "name:zho_x_preferred":[
        "\u66fc\u8fc8\u4e0b\u5be8"
    ],
    "wof:name":"Manmai Xiazhai",
    "wof:placetype":"locality"
},
  "geometry": {"coordinates":[100.21899999999999,21.7363],"type":"Point"}
}