{
  "type": "Feature",
  "properties": {
    "gn:admin1_code":"11.0",
    "gn:asciiname":"Gutian",
    "gn:country_code":"CN",
    "gn:dem":327,
    "gn:feature_class":"P",
    "gn:feature_code":"PPL",
    "gn:name":"Gutian",
    "gn:population":0,
    "gn:timezone":"Asia/Shanghai",
    "iso:country":"CN",
    "name:zho_x_preferred":[
        "\u53e4\u7530"
    ],
    "wof:name":"Gutian",
    "wof:placetype":"locality"
},
  "geometry": {"coordinates":[109.61928,27.35331],"type":"Point"}
}