{
  "type": "Feature",
  "properties": {
    "gn:admin1_code":"25",
    "gn:asciiname":"Xiangzhai",
    "gn:country_code":"CN",
    "gn:dem":58,
    "gn:feature_class":"P",
    "gn:feature_code":"PPL",
    "gn:name":"Xiangzhai",
    "gn:population":0,
    "gn:timezone":"Asia/Shanghai",
    "iso:country":"CN",
    "name:zho_x_preferred":[
        "\u7965\u5be8"
    ],
    "wof:name":"Xiangzhai",
    "wof:placetype":"locality"
},
  "geometry": {"coordinates":[115.10299999999999,35.3823],"type":"Point"}
}