{
  "type": "Feature",
  "properties": {
    "gn:admin1_code":"19.0",
    "gn:asciiname":"Ganwazi",
    "gn:country_code":"CN",
    "gn:dem":390,
    "gn:feature_class":"P",
    "gn:feature_code":"PPL",
    "gn:name":"Ganwazi",
    "gn:population":0,
    "gn:timezone":"Asia/Shanghai",
    "iso:country":"CN",
    "name:und_x_variant":[
        "\u5e72\u6d3c\u5b50"
    ],
    "name:zho_x_preferred":[
        "\u5e72\u6d3c\u5b50"
    ],
    "wof:name":"Ganwazi",
    "wof:placetype":"locality"
},
  "geometry": {"coordinates":[119.66349,40.81899],"type":"Point"}
}