{
  "type": "Feature",
  "properties": {
    "gn:admin1_code":"7",
    "gn:asciiname":"Xiadongxi",
    "gn:country_code":"CN",
    "gn:dem":416,
    "gn:feature_class":"P",
    "gn:feature_code":"PPL",
    "gn:name":"Xiadongxi",
    "gn:population":0,
    "gn:timezone":"Asia/Shanghai",
    "iso:country":"CN",
    "name:und_x_variant":[
        "\u4e0b\u4e1c\u6eaa",
        "Xiadongxi"
    ],
    "wof:name":"Xiadongxi",
    "wof:placetype":"locality"
},
  "geometry": {"coordinates":[119.42012,27.32076],"type":"Point"}
}