{
  "type": "Feature",
  "properties": {
    "gn:admin1_code":"18",
    "gn:asciiname":"Gedadi",
    "gn:country_code":"CN",
    "gn:dem":1727,
    "gn:feature_class":"P",
    "gn:feature_code":"PPL",
    "gn:name":"Gedadi",
    "gn:population":0,
    "gn:timezone":"Asia/Shanghai",
    "iso:country":"CN",
    "name:zho_x_preferred":[
        "\u572a\u8fbe\u5730"
    ],
    "wof:name":"Gedadi",
    "wof:placetype":"locality"
},
  "geometry": {"coordinates":[104.64,25.4279],"type":"Point"}
}