{
  "type": "Feature",
  "properties": {
    "gn:admin1_code":"16.0",
    "gn:asciiname":"Liuju",
    "gn:country_code":"CN",
    "gn:dem":189,
    "gn:feature_class":"P",
    "gn:feature_code":"PPL",
    "gn:name":"Liuju",
    "gn:population":0,
    "gn:timezone":"Asia/Shanghai",
    "iso:country":"CN",
    "name:zho_x_preferred":[
        "\u516d\u5c45"
    ],
    "wof:name":"Liuju",
    "wof:placetype":"locality"
},
  "geometry": {"coordinates":[106.568,23.8054],"type":"Point"}
}