{
  "type": "Feature",
  "properties": {
    "gn:admin1_code":"19.0",
    "gn:asciiname":"Qiujiadian",
    "gn:country_code":"CN",
    "gn:dem":21,
    "gn:feature_class":"P",
    "gn:feature_code":"PPL",
    "gn:name":"Qiujiadian",
    "gn:population":0,
    "gn:timezone":"Asia/Shanghai",
    "iso:country":"CN",
    "name:zho_x_preferred":[
        "\u4e18\u5bb6\u5e97"
    ],
    "wof:name":"Qiujiadian",
    "wof:placetype":"locality"
},
  "geometry": {"coordinates":[122.21026999999999,39.43654],"type":"Point"}
}