{
  "type": "Feature",
  "properties": {
    "gn:admin1_code":"19.0",
    "gn:asciiname":"Caojiatun",
    "gn:country_code":"CN",
    "gn:dem":61,
    "gn:feature_class":"P",
    "gn:feature_code":"PPL",
    "gn:name":"Caojiatun",
    "gn:population":0,
    "gn:timezone":"Asia/Shanghai",
    "iso:country":"CN",
    "name:und_x_variant":[
        "\u66f9\u5bb6\u5c6f"
    ],
    "name:zho_x_preferred":[
        "\u66f9\u5bb6\u5c6f"
    ],
    "wof:name":"Caojiatun",
    "wof:placetype":"locality"
},
  "geometry": {"coordinates":[123.12752999999999,39.86662000000001],"type":"Point"}
}