{
  "type": "Feature",
  "properties": {
    "gn:admin1_code":"29.0",
    "gn:asciiname":"Wanglong",
    "gn:country_code":"CN",
    "gn:dem":2250,
    "gn:feature_class":"P",
    "gn:feature_code":"PPL",
    "gn:name":"Wanglong",
    "gn:population":0,
    "gn:timezone":"Asia/Shanghai",
    "iso:country":"CN",
    "name:zho_x_preferred":[
        "\u671b\u9f99"
    ],
    "wof:name":"Wanglong",
    "wof:placetype":"locality"
},
  "geometry": {"coordinates":[100.083,27.1025],"type":"Point"}
}