{
  "type": "Feature",
  "properties": {
    "gn:admin1_code":"18.0",
    "gn:asciiname":"Guisa",
    "gn:country_code":"CN",
    "gn:dem":817,
    "gn:feature_class":"P",
    "gn:feature_code":"PPL",
    "gn:name":"Guisa",
    "gn:population":0,
    "gn:timezone":"Asia/Shanghai",
    "iso:country":"CN",
    "name:ceb_x_preferred":[
        "Guisa"
    ],
    "name:fra_x_preferred":[
        "Guisa"
    ],
    "name:ita_x_preferred":[
        "Guisa"
    ],
    "name:kat_x_preferred":[
        "\u10d2\u10e3\u10d8\u10e1\u10d0"
    ],
    "name:nld_x_preferred":[
        "Guisa"
    ],
    "name:pol_x_preferred":[
        "Guisa"
    ],
    "name:spa_x_preferred":[
        "Guisa"
    ],
    "name:swe_x_preferred":[
        "Guisa"
    ],
    "name:vie_x_preferred":[
        "Guisa"
    ],
    "name:zho_x_preferred":[
        "\u8d35\u6d12"
    ],
    "name:zho_x_variant":[
        "\u5409\u85a9"
    ],
    "wof:name":"Guisa",
    "wof:placetype":"locality"
},
  "geometry": {"coordinates":[108.489,26.8078],"type":"Point"}
}