{
  "type": "Feature",
  "properties": {
    "gn:admin1_code":"12.0",
    "gn:asciiname":"Longjiagai",
    "gn:country_code":"CN",
    "gn:dem":1143,
    "gn:feature_class":"P",
    "gn:feature_code":"PPL",
    "gn:name":"Longjiagai",
    "gn:population":0,
    "gn:timezone":"Asia/Shanghai",
    "iso:country":"CN",
    "name:zho_x_preferred":[
        "\u9f99\u5bb6\u76d6"
    ],
    "wof:name":"Longjiagai",
    "wof:placetype":"locality"
},
  "geometry": {"coordinates":[109.11752,29.72231],"type":"Point"}
}