{
  "type": "Feature",
  "properties": {
    "gn:admin1_code":"26.0",
    "gn:asciiname":"Daleigongcun",
    "gn:country_code":"CN",
    "gn:dem":754,
    "gn:feature_class":"P",
    "gn:feature_code":"PPL",
    "gn:name":"Daleigongcun",
    "gn:population":0,
    "gn:timezone":"Asia/Shanghai",
    "iso:country":"CN",
    "name:zho_x_preferred":[
        "\u5927\u96f7\u516c\u6751"
    ],
    "wof:name":"Daleigongcun",
    "wof:placetype":"locality"
},
  "geometry": {"coordinates":[109.65877,35.20939],"type":"Point"}
}