{
  "type": "Feature",
  "properties": {
    "gn:admin1_code":"19.0",
    "gn:asciiname":"Wujiazidonggou",
    "gn:country_code":"CN",
    "gn:dem":252,
    "gn:feature_class":"P",
    "gn:feature_code":"PPL",
    "gn:name":"Wujiazidonggou",
    "gn:population":0,
    "gn:timezone":"Asia/Shanghai",
    "iso:country":"CN",
    "name:und_x_variant":[
        "\u4e94\u5bb6\u5b50\u4e1c\u6c9f"
    ],
    "name:zho_x_preferred":[
        "\u4e94\u5bb6\u5b50\u4e1c\u6c9f"
    ],
    "wof:name":"Wujiazidonggou",
    "wof:placetype":"locality"
},
  "geometry": {"coordinates":[121.73884,41.96142],"type":"Point"}
}