{
  "type": "Feature",
  "properties": {
    "gn:admin1_code":"16",
    "gn:asciiname":"Banwu",
    "gn:country_code":"CN",
    "gn:dem":144,
    "gn:feature_class":"P",
    "gn:feature_code":"PPL",
    "gn:name":"Banwu",
    "gn:population":0,
    "gn:timezone":"Asia/Shanghai",
    "iso:country":"CN",
    "name:zho_x_preferred":[
        "\u677f\u5c4b"
    ],
    "wof:name":"Banwu",
    "wof:placetype":"locality"
},
  "geometry": {"coordinates":[111.239,26.2641],"type":"Point"}
}