{
  "type": "Feature",
  "properties": {
    "gn:admin1_code":"9",
    "gn:asciiname":"Nanchanggu",
    "gn:country_code":"CN",
    "gn:dem":56,
    "gn:feature_class":"P",
    "gn:feature_code":"PPL",
    "gn:name":"Nanchanggu",
    "gn:population":0,
    "gn:timezone":"Asia/Shanghai",
    "iso:country":"CN",
    "name:zho_x_preferred":[
        "\u5357\u957f\u56fa"
    ],
    "wof:name":"Nanchanggu",
    "wof:placetype":"locality"
},
  "geometry": {"coordinates":[114.92100000000001,35.9098],"type":"Point"}
}