{
  "type": "Feature",
  "properties": {
    "gn:admin1_code":"7",
    "gn:asciiname":"Xiazhang",
    "gn:country_code":"CN",
    "gn:dem":260,
    "gn:feature_class":"P",
    "gn:feature_code":"PPL",
    "gn:name":"Xiazhang",
    "gn:population":0,
    "gn:timezone":"Asia/Shanghai",
    "iso:country":"CN",
    "name:und_x_variant":[
        "\u4e0b\u6a1f"
    ],
    "name:zho_x_preferred":[
        "\u4e0b\u6a1f"
    ],
    "wof:name":"Xiazhang",
    "wof:placetype":"locality"
},
  "geometry": {"coordinates":[118.56180999999999,27.98144000000001],"type":"Point"}
}