{
  "type": "Feature",
  "properties": {
    "gn:admin1_code":"02",
    "gn:asciiname":"Hexicun",
    "gn:country_code":"CN",
    "gn:dem":11,
    "gn:feature_class":"P",
    "gn:feature_code":"PPL",
    "gn:name":"Hexicun",
    "gn:population":0,
    "gn:timezone":"Asia/Shanghai",
    "iso:country":"CN",
    "name:und_x_variant":[
        "Ho-hsi",
        "Hexi",
        "\u5408\u6eaa",
        "Hexicun"
    ],
    "name:zho_x_preferred":[
        "\u5408\u6eaa\u6751"
    ],
    "wof:name":"Hexicun",
    "wof:placetype":"locality"
},
  "geometry": {"coordinates":[119.82071000000001,31.04533],"type":"Point"}
}