{
  "type": "Feature",
  "properties": {
    "gn:admin1_code":"11.0",
    "gn:asciiname":"Houshi",
    "gn:country_code":"CN",
    "gn:dem":89,
    "gn:feature_class":"P",
    "gn:feature_code":"PPL",
    "gn:name":"Houshi",
    "gn:population":0,
    "gn:timezone":"Asia/Shanghai",
    "iso:country":"CN",
    "name:zho_x_preferred":[
        "\u5019\u5e02"
    ],
    "wof:name":"Houshi",
    "wof:placetype":"locality"
},
  "geometry": {"coordinates":[113.4003,27.09168],"type":"Point"}
}