{
  "type": "Feature",
  "properties": {
    "gn:admin1_code":"2.0",
    "gn:asciiname":"Dongcun",
    "gn:country_code":"CN",
    "gn:dem":9,
    "gn:feature_class":"P",
    "gn:feature_code":"PPL",
    "gn:name":"Dongcun",
    "gn:population":0,
    "gn:timezone":"Asia/Shanghai",
    "iso:country":"CN",
    "name:und_x_variant":[
        "\u4e1c\u6751"
    ],
    "name:zho_x_preferred":[
        "Dongcun"
    ],
    "wof:name":"Dongcun",
    "wof:placetype":"locality"
},
  "geometry": {"coordinates":[120.06818,30.91441],"type":"Point"}
}