{
  "type": "Feature",
  "properties": {
    "gn:admin1_code":"9",
    "gn:asciiname":"Daiwang",
    "gn:country_code":"CN",
    "gn:dem":46,
    "gn:feature_class":"P",
    "gn:feature_code":"PPL",
    "gn:name":"Daiwang",
    "gn:population":0,
    "gn:timezone":"Asia/Shanghai",
    "iso:country":"CN",
    "name:zho_x_preferred":[
        "\u4ee3\u738b"
    ],
    "wof:name":"Daiwang",
    "wof:placetype":"locality"
},
  "geometry": {"coordinates":[115.45037000000001,36.09872],"type":"Point"}
}