{
  "type": "Feature",
  "properties": {
    "gn:admin1_code":"29.0",
    "gn:asciiname":"Xiabiaoyuan",
    "gn:country_code":"CN",
    "gn:dem":1597,
    "gn:feature_class":"P",
    "gn:feature_code":"PPL",
    "gn:name":"Xiabiaoyuan",
    "gn:population":0,
    "gn:timezone":"Asia/Shanghai",
    "iso:country":"CN",
    "name:zho_x_preferred":[
        "\u4e0b\u8868\u9662"
    ],
    "wof:name":"Xiabiaoyuan",
    "wof:placetype":"locality"
},
  "geometry": {"coordinates":[98.5667,25.2192],"type":"Point"}
}