{
  "type": "Feature",
  "properties": {
    "gn:admin1_code":"11.0",
    "gn:asciiname":"Suobadong",
    "gn:country_code":"CN",
    "gn:dem":984,
    "gn:feature_class":"P",
    "gn:feature_code":"PPL",
    "gn:name":"Suobadong",
    "gn:population":0,
    "gn:timezone":"Asia/Shanghai",
    "iso:country":"CN",
    "name:zho_x_preferred":[
        "Suobadong"
    ],
    "name:zho_x_variant":[
        "\u68ad\u628a\u6d1e"
    ],
    "wof:name":"Suobadong",
    "wof:placetype":"locality"
},
  "geometry": {"coordinates":[110.13039000000001,28.96836],"type":"Point"}
}