{
  "type": "Feature",
  "properties": {
    "gn:admin1_code":"09",
    "gn:asciiname":"Jiaxian",
    "gn:country_code":"CN",
    "gn:dem":119,
    "gn:feature_class":"P",
    "gn:feature_code":"PPLA3",
    "gn:name":"Jiaxian",
    "gn:population":0,
    "gn:timezone":"Asia/Shanghai",
    "iso:country":"CN",
    "name:und_x_variant":[
        "Tszyasyan",
        "Chia-hsien",
        "Fu-ch\u2019eng",
        "Chia",
        "Kiahsien",
        "Jia Xian",
        "\u90cf\u53bf",
        "Chengguan Zhen",
        "Jia Xian Chengguanzhen"
    ],
    "name:zho_x_preferred":[
        "\u90cf\u53bf\u57ce\u5173\u9547"
    ],
    "wof:name":"Jiaxian",
    "wof:placetype":"locality"
},
  "geometry": {"coordinates":[113.20806,33.96833],"type":"Point"}
}