{
  "type": "Feature",
  "properties": {
    "gn:admin1_code":"15.0",
    "gn:asciiname":"Guojiabu",
    "gn:country_code":"CN",
    "gn:dem":1646,
    "gn:feature_class":"P",
    "gn:feature_code":"PPL",
    "gn:name":"Guojiabu",
    "gn:population":0,
    "gn:timezone":"Asia/Shanghai",
    "iso:country":"CN",
    "name:zho_x_preferred":[
        "\u90ed\u5bb6\u5821"
    ],
    "wof:name":"Guojiabu",
    "wof:placetype":"locality"
},
  "geometry": {"coordinates":[104.98999999999999,35.9139],"type":"Point"}
}