{
  "type": "Feature",
  "properties": {
    "gn:admin1_code":"16.0",
    "gn:asciiname":"Chaoma",
    "gn:country_code":"CN",
    "gn:dem":501,
    "gn:feature_class":"P",
    "gn:feature_code":"PPL",
    "gn:name":"Chaoma",
    "gn:population":0,
    "gn:timezone":"Asia/Shanghai",
    "iso:country":"CN",
    "name:zho_x_preferred":[
        "\u671d\u9a6c"
    ],
    "wof:name":"Chaoma",
    "wof:placetype":"locality"
},
  "geometry": {"coordinates":[106.81699999999999,23.6389],"type":"Point"}
}