{
  "type": "Feature",
  "properties": {
    "gn:admin1_code":"29.0",
    "gn:asciiname":"Damingyi",
    "gn:country_code":"CN",
    "gn:dem":1861,
    "gn:feature_class":"P",
    "gn:feature_code":"PPL",
    "gn:name":"Damingyi",
    "gn:population":0,
    "gn:timezone":"Asia/Shanghai",
    "iso:country":"CN",
    "name:zho_x_preferred":[
        "\u5927\u660e\u9091"
    ],
    "wof:name":"Damingyi",
    "wof:placetype":"locality"
},
  "geometry": {"coordinates":[99.2236,24.7852],"type":"Point"}
}