{
  "type": "Feature",
  "properties": {
    "gn:admin1_code":"16",
    "gn:asciiname":"Shizishan",
    "gn:country_code":"CN",
    "gn:dem":408,
    "gn:feature_class":"P",
    "gn:feature_code":"PPL",
    "gn:name":"Shizishan",
    "gn:population":0,
    "gn:timezone":"Asia/Shanghai",
    "iso:country":"CN",
    "name:ceb_x_preferred":[
        "Shizishan"
    ],
    "name:deu_x_preferred":[
        "Shizishan"
    ],
    "name:zho_x_preferred":[
        "\u72ee\u5b50\u5c71"
    ],
    "wof:name":"Shizishan",
    "wof:placetype":"locality"
},
  "geometry": {"coordinates":[110.658,25.3775],"type":"Point"}
}