{
  "type": "Feature",
  "properties": {
    "gn:admin1_code":"3.0",
    "gn:asciiname":"Zhengjia",
    "gn:country_code":"CN",
    "gn:dem":61,
    "gn:feature_class":"P",
    "gn:feature_code":"PPL",
    "gn:name":"Zhengjia",
    "gn:population":0,
    "gn:timezone":"Asia/Shanghai",
    "iso:country":"CN",
    "name:und_x_variant":[
        "\u90d1\u5bb6"
    ],
    "wof:name":"Zhengjia",
    "wof:placetype":"locality"
},
  "geometry": {"coordinates":[116.37752999999999,27.79872],"type":"Point"}
}