{
  "type": "Feature",
  "properties": {
    "gn:admin1_code":"26.0",
    "gn:asciiname":"Jingwuta",
    "gn:country_code":"CN",
    "gn:dem":1253,
    "gn:feature_class":"P",
    "gn:feature_code":"PPL",
    "gn:name":"Jingwuta",
    "gn:population":0,
    "gn:timezone":"Asia/Shanghai",
    "iso:country":"CN",
    "name:zho_x_preferred":[
        "\u4e95\u52a1\u584c"
    ],
    "wof:name":"Jingwuta",
    "wof:placetype":"locality"
},
  "geometry": {"coordinates":[109.42453,37.36783],"type":"Point"}
}