{
  "type": "Feature",
  "properties": {
    "gn:admin1_code":"9.0",
    "gn:asciiname":"Laojindong",
    "gn:country_code":"CN",
    "gn:dem":327,
    "gn:feature_class":"P",
    "gn:feature_code":"PPL",
    "gn:name":"Laojindong",
    "gn:population":0,
    "gn:timezone":"Asia/Shanghai",
    "iso:country":"CN",
    "name:zho_x_preferred":[
        "\u8001\u91d1\u6d1e"
    ],
    "wof:name":"Laojindong",
    "wof:placetype":"locality"
},
  "geometry": {"coordinates":[112.01401,34.43679],"type":"Point"}
}