{
  "type": "Feature",
  "properties": {
    "gn:admin1_code":"24.0",
    "gn:asciiname":"Tatizhang",
    "gn:country_code":"CN",
    "gn:dem":1368,
    "gn:feature_class":"P",
    "gn:feature_code":"PPL",
    "gn:name":"Tatizhang",
    "gn:population":0,
    "gn:timezone":"Asia/Shanghai",
    "iso:country":"CN",
    "name:zho_x_preferred":[
        "\u5854\u9898\u638c"
    ],
    "wof:name":"Tatizhang",
    "wof:placetype":"locality"
},
  "geometry": {"coordinates":[113.37785,35.7069],"type":"Point"}
}