{
  "type": "Feature",
  "properties": {
    "gn:admin1_code":"1.0",
    "gn:asciiname":"Sanyuanqiao",
    "gn:country_code":"CN",
    "gn:dem":8,
    "gn:feature_class":"P",
    "gn:feature_code":"PPL",
    "gn:name":"Sanyuanqiao",
    "gn:population":0,
    "gn:timezone":"Asia/Shanghai",
    "iso:country":"CN",
    "name:zho_x_preferred":[
        "\u4e09\u5143\u6865"
    ],
    "wof:name":"Sanyuanqiao",
    "wof:placetype":"locality"
},
  "geometry": {"coordinates":[118.60796000000001,31.37296],"type":"Point"}
}