{
  "type": "Feature",
  "properties": {
    "gn:admin1_code":"32.0",
    "gn:asciiname":"Qiemu",
    "gn:country_code":"CN",
    "gn:dem":2795,
    "gn:feature_class":"P",
    "gn:feature_code":"PPL",
    "gn:name":"Qiemu",
    "gn:population":0,
    "gn:timezone":"Asia/Shanghai",
    "iso:country":"CN",
    "name:zho_x_preferred":[
        "\u4e14\u6728"
    ],
    "wof:name":"Qiemu",
    "wof:placetype":"locality"
},
  "geometry": {"coordinates":[102.658,28.2005],"type":"Point"}
}