{
  "type": "Feature",
  "properties": {
    "gn:admin1_code":"4.0",
    "gn:asciiname":"Yaodai",
    "gn:country_code":"CN",
    "gn:dem":8,
    "gn:feature_class":"P",
    "gn:feature_code":"PPL",
    "gn:name":"Yaodai",
    "gn:population":0,
    "gn:timezone":"Asia/Shanghai",
    "iso:country":"CN",
    "name:und_x_variant":[
        "\u59da\u5788"
    ],
    "name:zho_x_preferred":[
        "\u59da\u5788"
    ],
    "wof:name":"Yaodai",
    "wof:placetype":"locality"
},
  "geometry": {"coordinates":[120.10937,32.17966],"type":"Point"}
}