{
  "type": "Feature",
  "properties": {
    "gn:admin1_code":"29.0",
    "gn:asciiname":"Menggang",
    "gn:country_code":"CN",
    "gn:dem":578,
    "gn:feature_class":"P",
    "gn:feature_code":"PPL",
    "gn:name":"Menggang",
    "gn:population":0,
    "gn:timezone":"Asia/Shanghai",
    "iso:country":"CN",
    "name:zho_x_preferred":[
        "\u52d0\u5188"
    ],
    "wof:name":"Menggang",
    "wof:placetype":"locality"
},
  "geometry": {"coordinates":[101.292,21.6171],"type":"Point"}
}