{
  "type": "Feature",
  "properties": {
    "gn:admin1_code":"18.0",
    "gn:asciiname":"Guaibi",
    "gn:country_code":"CN",
    "gn:dem":1318,
    "gn:feature_class":"P",
    "gn:feature_code":"PPL",
    "gn:name":"Guaibi",
    "gn:population":0,
    "gn:timezone":"Asia/Shanghai",
    "iso:country":"CN",
    "name:zho_x_preferred":[
        "\u62d0\u6bd4"
    ],
    "wof:name":"Guaibi",
    "wof:placetype":"locality"
},
  "geometry": {"coordinates":[106.991,26.8279],"type":"Point"}
}