{
  "type": "Feature",
  "properties": {
    "gn:admin1_code":"25.0",
    "gn:asciiname":"Qilihecun",
    "gn:country_code":"CN",
    "gn:dem":55,
    "gn:feature_class":"P",
    "gn:feature_code":"PPL",
    "gn:name":"Qilihecun",
    "gn:population":0,
    "gn:timezone":"Asia/Shanghai",
    "iso:country":"CN",
    "name:zho_x_preferred":[
        "\u4e03\u91cc\u6cb3\u6751"
    ],
    "wof:name":"Qilihecun",
    "wof:placetype":"locality"
},
  "geometry": {"coordinates":[122.09311,37.19585],"type":"Point"}
}