{
  "type": "Feature",
  "properties": {
    "gn:admin1_code":"32.0",
    "gn:asciiname":"Cuobu",
    "gn:country_code":"CN",
    "gn:dem":4148,
    "gn:feature_class":"P",
    "gn:feature_code":"PPL",
    "gn:name":"Cuobu",
    "gn:population":0,
    "gn:timezone":"Asia/Shanghai",
    "iso:country":"CN",
    "name:zho_x_preferred":[
        "\u9519\u5e03"
    ],
    "wof:name":"Cuobu",
    "wof:placetype":"locality"
},
  "geometry": {"coordinates":[98.4808,33.0336],"type":"Point"}
}