{
  "type": "Feature",
  "properties": {
    "gn:admin1_code":"25",
    "gn:asciiname":"Shizimenkou",
    "gn:country_code":"CN",
    "gn:dem":215,
    "gn:feature_class":"P",
    "gn:feature_code":"PPL",
    "gn:name":"Shizimenkou",
    "gn:population":0,
    "gn:timezone":"Asia/Shanghai",
    "iso:country":"CN",
    "name:zho_x_preferred":[
        "\u72ee\u5b50\u95e8\u53e3"
    ],
    "wof:name":"Shizimenkou",
    "wof:placetype":"locality"
},
  "geometry": {"coordinates":[118.881,35.9193],"type":"Point"}
}