{
  "type": "Feature",
  "properties": {
    "gn:admin1_code":"12.0",
    "gn:asciiname":"Yinyangguang",
    "gn:country_code":"CN",
    "gn:dem":38,
    "gn:feature_class":"P",
    "gn:feature_code":"PPL",
    "gn:name":"Yinyangguang",
    "gn:population":0,
    "gn:timezone":"Asia/Shanghai",
    "iso:country":"CN",
    "name:zho_x_preferred":[
        "Yinyangguang"
    ],
    "name:zho_x_variant":[
        "\u9634\u9633\u5149"
    ],
    "wof:name":"Yinyangguang",
    "wof:placetype":"locality"
},
  "geometry": {"coordinates":[114.29143000000001,29.97677],"type":"Point"}
}