{
  "type": "Feature",
  "properties": {
    "gn:admin1_code":"14.0",
    "gn:asciiname":"Kyimxi",
    "gn:country_code":"CN",
    "gn:dem":3629,
    "gn:feature_class":"P",
    "gn:feature_code":"PPLF",
    "gn:name":"Kyimxi",
    "gn:population":0,
    "gn:timezone":"Asia/Urumqi",
    "iso:country":"CN",
    "name:bod_x_preferred":[
        "Kyimxi"
    ],
    "name:und_x_variant":[
        "Kexi"
    ],
    "name:zho_x_preferred":[
        "\u514b\u897f"
    ],
    "wof:name":"Kyimxi",
    "wof:placetype":"locality"
},
  "geometry": {"coordinates":[91.11507,29.24216],"type":"Point"}
}