{
  "type": "Feature",
  "properties": {
    "gn:admin1_code":"30.0",
    "gn:asciiname":"Shangjicun",
    "gn:country_code":"CN",
    "gn:dem":244,
    "gn:feature_class":"P",
    "gn:feature_code":"PPL",
    "gn:name":"Shangjicun",
    "gn:population":0,
    "gn:timezone":"Asia/Shanghai",
    "iso:country":"CN",
    "name:zho_x_preferred":[
        "\u4e0a\u5409\u6751"
    ],
    "wof:name":"Shangjicun",
    "wof:placetype":"locality"
},
  "geometry": {"coordinates":[116.35439,23.86972],"type":"Point"}
}