{
  "type": "Feature",
  "properties": {
    "gn:admin1_code":"19.0",
    "gn:asciiname":"Tengfangshen",
    "gn:country_code":"CN",
    "gn:dem":11,
    "gn:feature_class":"P",
    "gn:feature_code":"PPL",
    "gn:name":"Tengfangshen",
    "gn:population":0,
    "gn:timezone":"Asia/Shanghai",
    "iso:country":"CN",
    "name:zho_x_preferred":[
        "\u6ed5\u623f\u8eab"
    ],
    "wof:name":"Tengfangshen",
    "wof:placetype":"locality"
},
  "geometry": {"coordinates":[122.2092,40.389],"type":"Point"}
}