{
  "type": "Feature",
  "properties": {
    "gn:admin1_code":"19.0",
    "gn:asciiname":"Shanggachagou",
    "gn:country_code":"CN",
    "gn:dem":181,
    "gn:feature_class":"P",
    "gn:feature_code":"PPL",
    "gn:name":"Shanggachagou",
    "gn:population":0,
    "gn:timezone":"Asia/Shanghai",
    "iso:country":"CN",
    "name:zho_x_preferred":[
        "\u4e0a\u560e\u5c94\u6c9f"
    ],
    "wof:name":"Shanggachagou",
    "wof:placetype":"locality"
},
  "geometry": {"coordinates":[120.724,41.6297],"type":"Point"}
}