{
  "type": "Feature",
  "properties": {
    "gn:admin1_code":"26.0",
    "gn:asciiname":"Huangjiajie",
    "gn:country_code":"CN",
    "gn:dem":891,
    "gn:feature_class":"P",
    "gn:feature_code":"PPL",
    "gn:name":"Huangjiajie",
    "gn:population":0,
    "gn:timezone":"Asia/Shanghai",
    "iso:country":"CN",
    "name:und_x_variant":[
        "\u9ec4\u5bb6\u8857"
    ],
    "wof:name":"Huangjiajie",
    "wof:placetype":"locality"
},
  "geometry": {"coordinates":[106.25568,32.88068],"type":"Point"}
}