{
  "type": "Feature",
  "properties": {
    "gn:admin1_code":"15.0",
    "gn:asciiname":"Gangchaxian",
    "gn:country_code":"CN",
    "gn:dem":1762,
    "gn:feature_class":"P",
    "gn:feature_code":"PPL",
    "gn:name":"Gangchaxian",
    "gn:population":0,
    "gn:timezone":"Asia/Shanghai",
    "iso:country":"CN",
    "name:zho_x_preferred":[
        "\u5c97\u5c94\u5c98"
    ],
    "wof:name":"Gangchaxian",
    "wof:placetype":"locality"
},
  "geometry": {"coordinates":[104.137,36.0965],"type":"Point"}
}