{
  "type": "Feature",
  "properties": {
    "gn:admin1_code":"1.0",
    "gn:asciiname":"Huangtaicun",
    "gn:country_code":"CN",
    "gn:dem":26,
    "gn:feature_class":"P",
    "gn:feature_code":"PPL",
    "gn:name":"Huangtaicun",
    "gn:population":0,
    "gn:timezone":"Asia/Shanghai",
    "iso:country":"CN",
    "name:zho_x_preferred":[
        "\u9ec4\u53f0\u6751"
    ],
    "wof:name":"Huangtaicun",
    "wof:placetype":"locality"
},
  "geometry": {"coordinates":[116.47393,32.49193],"type":"Point"}
}