{
  "type": "Feature",
  "properties": {
    "gn:admin1_code":"4.0",
    "gn:asciiname":"Zhouying",
    "gn:country_code":"CN",
    "gn:dem":43,
    "gn:feature_class":"P",
    "gn:feature_code":"PPL",
    "gn:name":"Zhouying",
    "gn:population":0,
    "gn:timezone":"Asia/Shanghai",
    "iso:country":"CN",
    "name:zho_x_preferred":[
        "\u5468\u90e2"
    ],
    "wof:name":"Zhouying",
    "wof:placetype":"locality"
},
  "geometry": {"coordinates":[118.55562999999999,32.74769000000001],"type":"Point"}
}