{
  "type": "Feature",
  "properties": {
    "gn:admin1_code":"5.0",
    "gn:asciiname":"Beichangzi",
    "gn:country_code":"CN",
    "gn:dem":170,
    "gn:feature_class":"P",
    "gn:feature_code":"PPL",
    "gn:name":"Beichangzi",
    "gn:population":0,
    "gn:timezone":"Asia/Shanghai",
    "iso:country":"CN",
    "name:zho_x_preferred":[
        "\u5317\u573a\u5b50"
    ],
    "wof:name":"Beichangzi",
    "wof:placetype":"locality"
},
  "geometry": {"coordinates":[123.81492,43.96581],"type":"Point"}
}