{
  "type": "Feature",
  "properties": {
    "gn:admin1_code":"4.0",
    "gn:asciiname":"Miaodang",
    "gn:country_code":"CN",
    "gn:dem":5,
    "gn:feature_class":"P",
    "gn:feature_code":"PPL",
    "gn:name":"Miaodang",
    "gn:population":0,
    "gn:timezone":"Asia/Shanghai",
    "iso:country":"CN",
    "name:zho_x_preferred":[
        "Miaodang"
    ],
    "name:zho_x_variant":[
        "\u82d7\u8361"
    ],
    "wof:name":"Miaodang",
    "wof:placetype":"locality"
},
  "geometry": {"coordinates":[119.13443999999998,34.00917],"type":"Point"}
}