{
  "type": "Feature",
  "properties": {
    "gn:admin1_code":"8.0",
    "gn:asciiname":"Wudaogoucun",
    "gn:country_code":"CN",
    "gn:dem":214,
    "gn:feature_class":"P",
    "gn:feature_code":"PPL",
    "gn:name":"Wudaogoucun",
    "gn:population":0,
    "gn:timezone":"Asia/Shanghai",
    "iso:country":"CN",
    "name:zho_x_preferred":[
        "\u4e94\u9053\u6c9f\u6751"
    ],
    "wof:name":"Wudaogoucun",
    "wof:placetype":"locality"
},
  "geometry": {"coordinates":[130.68236999999999,46.13978],"type":"Point"}
}