{
  "type": "Feature",
  "properties": {
    "gn:admin1_code":"24.0",
    "gn:asciiname":"Shijie",
    "gn:country_code":"CN",
    "gn:dem":966,
    "gn:feature_class":"P",
    "gn:feature_code":"PPL",
    "gn:name":"Shijie",
    "gn:population":0,
    "gn:timezone":"Asia/Shanghai",
    "iso:country":"CN",
    "name:zho_x_preferred":[
        "\u65f6\u8857"
    ],
    "wof:name":"Shijie",
    "wof:placetype":"locality"
},
  "geometry": {"coordinates":[112.70753000000001,35.28562],"type":"Point"}
}