{
  "type": "Feature",
  "properties": {
    "gn:admin1_code":"4.0",
    "gn:asciiname":"Aiguo",
    "gn:country_code":"CN",
    "gn:dem":7,
    "gn:feature_class":"P",
    "gn:feature_code":"PPL",
    "gn:name":"Aiguo",
    "gn:population":0,
    "gn:timezone":"Asia/Shanghai",
    "iso:country":"CN",
    "name:zho_x_preferred":[
        "\u7231\u56fd"
    ],
    "wof:name":"Aiguo",
    "wof:placetype":"locality"
},
  "geometry": {"coordinates":[119.61648999999998,31.76501],"type":"Point"}
}