{
  "type": "Feature",
  "properties": {
    "gn:admin1_code":"7.0",
    "gn:asciiname":"Dongyanxia",
    "gn:country_code":"CN",
    "gn:dem":728,
    "gn:feature_class":"P",
    "gn:feature_code":"PPL",
    "gn:name":"Dongyanxia",
    "gn:population":0,
    "gn:timezone":"Asia/Shanghai",
    "iso:country":"CN",
    "name:und_x_variant":[
        "\u4e1c\u5ca9\u4e0b"
    ],
    "name:zho_x_preferred":[
        "\u4e1c\u5ca9\u4e0b"
    ],
    "wof:name":"Dongyanxia",
    "wof:placetype":"locality"
},
  "geometry": {"coordinates":[118.42753,26.68522],"type":"Point"}
}