{
  "type": "Feature",
  "properties": {
    "gn:country":"CN",
    "gn:fcode":"PPL",
    "gn:population":1430,
    "iso:country":"CN",
    "name:und_x_variant":[
        "Pi-yung"
    ],
    "qs:name":"Biyong",
    "qs:photos_9r":0,
    "qs:photos_sr":0,
    "qs:pop_sr":"3",
    "wof:name":"Biyong",
    "wof:placetype":"locality",
    "wof:population":1430
},
  "geometry": {"coordinates":[109.51000000000001,27.18722],"type":"Point"}
}