{
  "type": "Feature",
  "properties": {
    "gn:admin1_code":"16.0",
    "gn:asciiname":"Tuntian",
    "gn:country_code":"CN",
    "gn:dem":246,
    "gn:feature_class":"P",
    "gn:feature_code":"PPL",
    "gn:name":"Tuntian",
    "gn:population":0,
    "gn:timezone":"Asia/Shanghai",
    "iso:country":"CN",
    "name:cat_x_preferred":[
        "Tunti\u00e0"
    ],
    "name:fra_x_preferred":[
        "Tuntian"
    ],
    "name:zho_x_preferred":[
        "\u5c6f\u7530"
    ],
    "name:zho_x_variant":[
        "\u5c6f\u7530\u5236"
    ],
    "wof:name":"Tuntian",
    "wof:placetype":"locality"
},
  "geometry": {"coordinates":[109.146,24.1513],"type":"Point"}
}