{
  "type": "Feature",
  "properties": {
    "gn:admin1_code":"19.0",
    "gn:asciiname":"Qianchenjia Gangzi",
    "gn:country_code":"CN",
    "gn:dem":14,
    "gn:feature_class":"P",
    "gn:feature_code":"PPL",
    "gn:name":"Qianchenjia Gangzi",
    "gn:population":0,
    "gn:timezone":"Asia/Shanghai",
    "iso:country":"CN",
    "name:zho_x_preferred":[
        "\u524d\u9648\u5bb6\u5c97\u5b50"
    ],
    "wof:name":"Qianchenjia Gangzi",
    "wof:placetype":"locality"
},
  "geometry": {"coordinates":[122.551,41.5766],"type":"Point"}
}