{
  "type": "Feature",
  "properties": {
    "gn:admin1_code":"32.0",
    "gn:asciiname":"Yaowangmiao",
    "gn:country_code":"CN",
    "gn:dem":2438,
    "gn:feature_class":"P",
    "gn:feature_code":"PPL",
    "gn:name":"Yaowangmiao",
    "gn:population":0,
    "gn:timezone":"Asia/Shanghai",
    "iso:country":"CN",
    "name:zho_x_preferred":[
        "\u836f\u738b\u5e99"
    ],
    "wof:name":"Yaowangmiao",
    "wof:placetype":"locality"
},
  "geometry": {"coordinates":[102.021,29.7047],"type":"Point"}
}