{
  "type": "Feature",
  "properties": {
    "gn:admin1_code":"9.0",
    "gn:asciiname":"Wanxuzhuang",
    "gn:country_code":"CN",
    "gn:dem":50,
    "gn:feature_class":"P",
    "gn:feature_code":"PPL",
    "gn:name":"Wanxuzhuang",
    "gn:population":0,
    "gn:timezone":"Asia/Shanghai",
    "iso:country":"CN",
    "name:zho_x_preferred":[
        "\u4e07\u8bb8\u5e84"
    ],
    "wof:name":"Wanxuzhuang",
    "wof:placetype":"locality"
},
  "geometry": {"coordinates":[114.82682,33.60762],"type":"Point"}
}