{
  "type": "Feature",
  "properties": {
    "gn:admin1_code":"4.0",
    "gn:asciiname":"Dawu Jiaxiang",
    "gn:country_code":"CN",
    "gn:dem":4,
    "gn:feature_class":"P",
    "gn:feature_code":"PPL",
    "gn:name":"Dawu Jiaxiang",
    "gn:population":0,
    "gn:timezone":"Asia/Shanghai",
    "iso:country":"CN",
    "name:und_x_variant":[
        "\u5927\u5434\u5bb6\u5df7"
    ],
    "wof:name":"Dawu Jiaxiang",
    "wof:placetype":"locality"
},
  "geometry": {"coordinates":[121.009,31.65476],"type":"Point"}
}