{
  "type": "Feature",
  "properties": {
    "gn:admin1_code":"07",
    "gn:asciiname":"Tian'an",
    "gn:country_code":"CN",
    "gn:dem":640,
    "gn:feature_class":"P",
    "gn:feature_code":"PPL",
    "gn:name":"Tian\u2019an",
    "gn:population":0,
    "gn:timezone":"Asia/Shanghai",
    "iso:country":"CN",
    "name:und_x_variant":[
        "Tian\u2019an"
    ],
    "name:zho_x_preferred":[
        "\u7530\u5b89"
    ],
    "wof:name":"Tian'an",
    "wof:placetype":"locality"
},
  "geometry": {"coordinates":[117.79722,25.60611],"type":"Point"}
}