{
  "type": "Feature",
  "properties": {
    "gn:admin1_code":"7.0",
    "gn:asciiname":"Shangchayang",
    "gn:country_code":"CN",
    "gn:dem":618,
    "gn:feature_class":"P",
    "gn:feature_code":"PPL",
    "gn:name":"Shangchayang",
    "gn:population":0,
    "gn:timezone":"Asia/Shanghai",
    "iso:country":"CN",
    "name:zho_x_preferred":[
        "\u4e0a\u8336\u6d0b"
    ],
    "wof:name":"Shangchayang",
    "wof:placetype":"locality"
},
  "geometry": {"coordinates":[119.46003,26.65948],"type":"Point"}
}