{
  "type": "Feature",
  "properties": {
    "gn:admin1_code":"9.0",
    "gn:asciiname":"Jingdian",
    "gn:country_code":"CN",
    "gn:dem":427,
    "gn:feature_class":"P",
    "gn:feature_code":"PPL",
    "gn:name":"Jingdian",
    "gn:population":0,
    "gn:timezone":"Asia/Shanghai",
    "iso:country":"CN",
    "name:zho_x_preferred":[
        "\u666f\u5e97"
    ],
    "wof:name":"Jingdian",
    "wof:placetype":"locality"
},
  "geometry": {"coordinates":[113.20971000000002,34.48936],"type":"Point"}
}