{
  "type": "Feature",
  "properties": {
    "gn:admin1_code":"20.0",
    "gn:asciiname":"Xiadi",
    "gn:country_code":"CN",
    "gn:dem":1663,
    "gn:feature_class":"P",
    "gn:feature_code":"PPL",
    "gn:name":"Xiadi",
    "gn:population":0,
    "gn:timezone":"Asia/Shanghai",
    "iso:country":"CN",
    "name:und_x_variant":[
        "\u4e0b\u5730"
    ],
    "wof:name":"Xiadi",
    "wof:placetype":"locality"
},
  "geometry": {"coordinates":[112.18770000000001,41.59361],"type":"Point"}
}