{
  "type": "Feature",
  "properties": {
    "gn:admin1_code":"12.0",
    "gn:asciiname":"Lihengzhi",
    "gn:country_code":"CN",
    "gn:dem":37,
    "gn:feature_class":"P",
    "gn:feature_code":"PPL",
    "gn:name":"Lihengzhi",
    "gn:population":0,
    "gn:timezone":"Asia/Shanghai",
    "iso:country":"CN",
    "name:zho_x_preferred":[
        "\u674e\u4ea8\u829d"
    ],
    "wof:name":"Lihengzhi",
    "wof:placetype":"locality"
},
  "geometry": {"coordinates":[114.2499,30.10933],"type":"Point"}
}