{
  "type": "Feature",
  "properties": {
    "gn:admin1_code":"32.0",
    "gn:asciiname":"Huilongsi",
    "gn:country_code":"CN",
    "gn:dem":551,
    "gn:feature_class":"P",
    "gn:feature_code":"PPL",
    "gn:name":"Huilongsi",
    "gn:population":0,
    "gn:timezone":"Asia/Shanghai",
    "iso:country":"CN",
    "name:zho_x_preferred":[
        "\u56de\u9f99\u5bfa"
    ],
    "wof:name":"Huilongsi",
    "wof:placetype":"locality"
},
  "geometry": {"coordinates":[104.75981,31.12372],"type":"Point"}
}