{
  "type": "Feature",
  "properties": {
    "gn:admin1_code":"8.0",
    "gn:asciiname":"Changqinghe",
    "gn:country_code":"CN",
    "gn:dem":381,
    "gn:feature_class":"P",
    "gn:feature_code":"PPL",
    "gn:name":"Changqinghe",
    "gn:population":0,
    "gn:timezone":"Asia/Shanghai",
    "iso:country":"CN",
    "name:zho_x_preferred":[
        "\u5e38\u9752\u6cb3"
    ],
    "wof:name":"Changqinghe",
    "wof:placetype":"locality"
},
  "geometry": {"coordinates":[127.33931,48.99915],"type":"Point"}
}