{
  "type": "Feature",
  "properties": {
    "gn:admin1_code":"8.0",
    "gn:asciiname":"Toudaogangcun",
    "gn:country_code":"CN",
    "gn:dem":159,
    "gn:feature_class":"P",
    "gn:feature_code":"PPL",
    "gn:name":"Toudaogangcun",
    "gn:population":0,
    "gn:timezone":"Asia/Shanghai",
    "iso:country":"CN",
    "name:zho_x_preferred":[
        "\u5934\u9053\u5c97\u6751"
    ],
    "wof:name":"Toudaogangcun",
    "wof:placetype":"locality"
},
  "geometry": {"coordinates":[130.42847,46.4153],"type":"Point"}
}