{
  "type": "Feature",
  "properties": {
    "gn:admin1_code":"12.0",
    "gn:asciiname":"Liushuzhuang",
    "gn:country_code":"CN",
    "gn:dem":229,
    "gn:feature_class":"P",
    "gn:feature_code":"PPL",
    "gn:name":"Liushuzhuang",
    "gn:population":0,
    "gn:timezone":"Asia/Shanghai",
    "iso:country":"CN",
    "name:zho_x_preferred":[
        "\u67f3\u6811\u5e84"
    ],
    "wof:name":"Liushuzhuang",
    "wof:placetype":"locality"
},
  "geometry": {"coordinates":[110.90152,32.56807],"type":"Point"}
}