{
  "type": "Feature",
  "properties": {
    "gn:admin1_code":"7.0",
    "gn:asciiname":"Daijiashan",
    "gn:country_code":"CN",
    "gn:dem":584,
    "gn:feature_class":"P",
    "gn:feature_code":"PPL",
    "gn:name":"Daijiashan",
    "gn:population":0,
    "gn:timezone":"Asia/Shanghai",
    "iso:country":"CN",
    "name:zho_x_preferred":[
        "\u6234\u5bb6\u5c71"
    ],
    "wof:name":"Daijiashan",
    "wof:placetype":"locality"
},
  "geometry": {"coordinates":[119.88124999999999,27.08537],"type":"Point"}
}