{
  "type": "Feature",
  "properties": {
    "gn:country":"CN",
    "gn:fcode":"PPL",
    "gn:population":120514,
    "iso:country":"CN",
    "name:ara_x_preferred":[
        "\u0641\u0646\u063a\u062a\u0634\u0646\u063a"
    ],
    "name:ben_x_preferred":[
        "\u09ab\u09c7\u0982\u0997\u099a\u09c7\u09a8"
    ],
    "name:ceb_x_preferred":[
        "Fengcheng"
    ],
    "name:deu_x_preferred":[
        "Fengcheng"
    ],
    "name:ell_x_preferred":[
        "\u03a6\u03ad\u03bd\u03b3\u03ba\u03c4\u03c3\u03b5\u03bd\u03b3\u03ba"
    ],
    "name:fas_x_preferred":[
        "\u0641\u0646\u06af\u0686\u0646\u06af"
    ],
    "name:fra_x_preferred":[
        "Fengcheng"
    ],
    "name:heb_x_preferred":[
        "\u05e4\u05e0\u05d2\u05e6'\u05e0\u05d2"
    ],
    "name:hin_x_preferred":[
        "\u092b\u093c\u0947\u0902\u0917\u091a\u0947\u0902\u0917"
    ],
    "name:hun_x_preferred":[
        "Fengcheng"
    ],
    "name:ind_x_preferred":[
        "Fengcheng"
    ],
    "name:kor_x_preferred":[
        "\ud391\uccad\uc2dc"
    ],
    "name:mlg_x_preferred":[
        "Fengcheng"
    ],
    "name:nor_x_preferred":[
        "Fengcheng"
    ],
    "name:pol_x_preferred":[
        "Fengcheng"
    ],
    "name:por_x_preferred":[
        "Fengcheng"
    ],
    "name:spa_x_preferred":[
        "Fengcheng"
    ],
    "name:swe_x_preferred":[
        "Fengcheng"
    ],
    "name:tur_x_preferred":[
        "Fengcheng"
    ],
    "name:ukr_x_preferred":[
        "\u0424\u0435\u043d\u0447\u0435\u043d"
    ],
    "name:und_x_variant":[
        "Fenghwangcheng"
    ],
    "qs:name":"Fengcheng",
    "qs:photos_9r":0,
    "qs:photos_sr":0,
    "qs:pop_sr":"9",
    "wd:wordcount":47,
    "wof:name":"Fengcheng",
    "wof:placetype":"locality",
    "wof:population":120514
},
  "geometry": {"coordinates":[124.07167,40.45361],"type":"Point"}
}