{
  "type": "Feature",
  "properties": {
    "gn:country":"CN",
    "gn:fcode":"PPL",
    "gn:population":120514,
    "iso:country":"CN",
    "name:ceb_x_preferred":[
        "Fengcheng"
    ],
    "name:deu_x_preferred":[
        "Fengcheng"
    ],
    "name:fra_x_preferred":[
        "Fengcheng"
    ],
    "name:kor_x_preferred":[
        "\ud391\uccad\uc2dc"
    ],
    "name:mlg_x_preferred":[
        "Fengcheng"
    ],
    "name:nor_x_preferred":[
        "Fengcheng"
    ],
    "name:pol_x_preferred":[
        "Fengcheng"
    ],
    "name:swe_x_preferred":[
        "Fengcheng"
    ],
    "name:und_x_variant":[
        "Fenghwangcheng"
    ],
    "qs:name":"Fengcheng",
    "qs:photos_9r":0,
    "qs:photos_sr":0,
    "qs:pop_sr":"9",
    "wd:wordcount":47,
    "wof:name":"Fengcheng",
    "wof:placetype":"locality",
    "wof:population":120514
},
  "geometry": {"coordinates":[124.07167,40.45361],"type":"Point"}
}