{
  "type": "Feature",
  "properties": {
    "gn:admin1_code":"22.0",
    "gn:asciiname":"Lixinzhuangcun",
    "gn:country_code":"CN",
    "gn:dem":18,
    "gn:feature_class":"P",
    "gn:feature_code":"PPL",
    "gn:name":"Lixinzhuangcun",
    "gn:population":0,
    "gn:timezone":"Asia/Shanghai",
    "iso:country":"CN",
    "name:zho_x_preferred":[
        "\u674e\u8f9b\u5e84\u6751"
    ],
    "wof:name":"Lixinzhuangcun",
    "wof:placetype":"locality"
},
  "geometry": {"coordinates":[116.85177,39.72142],"type":"Point"}
}