{
  "type": "Feature",
  "properties": {
    "gn:admin1_code":"11",
    "gn:asciiname":"Luohong",
    "gn:country_code":"CN",
    "gn:dem":500,
    "gn:feature_class":"P",
    "gn:feature_code":"PPLA4",
    "gn:name":"Luohong",
    "gn:population":0,
    "gn:timezone":"Asia/Shanghai",
    "iso:country":"CN",
    "name:und_x_variant":[
        "Lo-hung",
        "Luohong",
        "Zhongluohong",
        "Luohongxiang"
    ],
    "name:zho_x_preferred":[
        "\u7f57\u6d2a"
    ],
    "name:zho_x_variant":[
        "\u7f57\u6d2a\u4e61",
        "\u4e2d\u7f57\u6d2a"
    ],
    "wof:name":"Luohong",
    "wof:placetype":"locality"
},
  "geometry": {"coordinates":[111.07528000000001,27.55556],"type":"Point"}
}