{
  "type": "Feature",
  "properties": {
    "gn:admin1_code":"15.0",
    "gn:asciiname":"Fanggeshan",
    "gn:country_code":"CN",
    "gn:dem":1535,
    "gn:feature_class":"P",
    "gn:feature_code":"PPL",
    "gn:name":"Fanggeshan",
    "gn:population":0,
    "gn:timezone":"Asia/Shanghai",
    "iso:country":"CN",
    "name:zho_x_preferred":[
        "\u623f\u9601\u5c71"
    ],
    "wof:name":"Fanggeshan",
    "wof:placetype":"locality"
},
  "geometry": {"coordinates":[105.06,32.8675],"type":"Point"}
}