{
  "type": "Feature",
  "properties": {
    "gn:admin1_code":"8.0",
    "gn:asciiname":"Hongxin Sandui",
    "gn:country_code":"CN",
    "gn:dem":253,
    "gn:feature_class":"P",
    "gn:feature_code":"PPLF",
    "gn:name":"Hongxin Sandui",
    "gn:population":0,
    "gn:timezone":"Asia/Shanghai",
    "iso:country":"CN",
    "name:zho_x_preferred":[
        "\u7ea2\u5fc3\u4e09\u961f"
    ],
    "wof:name":"Hongxin Sandui",
    "wof:placetype":"locality"
},
  "geometry": {"coordinates":[126.74249,48.16825],"type":"Point"}
}