{
  "type": "Feature",
  "properties": {
    "gn:admin1_code":"16.0",
    "gn:asciiname":"Naliucun",
    "gn:country_code":"CN",
    "gn:dem":210,
    "gn:feature_class":"P",
    "gn:feature_code":"PPL",
    "gn:name":"Naliucun",
    "gn:population":0,
    "gn:timezone":"Asia/Shanghai",
    "iso:country":"CN",
    "name:zho_x_preferred":[
        "\u90a3\u516d\u6751"
    ],
    "wof:name":"Naliucun",
    "wof:placetype":"locality"
},
  "geometry": {"coordinates":[107.03100000000001,21.9901],"type":"Point"}
}