{
  "type": "Feature",
  "properties": {
    "gn:admin1_code":"16.0",
    "gn:asciiname":"Banai",
    "gn:country_code":"CN",
    "gn:dem":329,
    "gn:feature_class":"P",
    "gn:feature_code":"PPL",
    "gn:name":"Banai",
    "gn:population":0,
    "gn:timezone":"Asia/Shanghai",
    "iso:country":"CN",
    "name:fra_x_preferred":[
        "Banai"
    ],
    "name:zho_x_preferred":[
        "\u516b\u5948"
    ],
    "wof:name":"Banai",
    "wof:placetype":"locality"
},
  "geometry": {"coordinates":[107.02800000000001,25.0372],"type":"Point"}
}