{
  "type": "Feature",
  "properties": {
    "gn:admin1_code":"32.0",
    "gn:asciiname":"Zhonglingshang",
    "gn:country_code":"CN",
    "gn:dem":945,
    "gn:feature_class":"P",
    "gn:feature_code":"PPL",
    "gn:name":"Zhonglingshang",
    "gn:population":0,
    "gn:timezone":"Asia/Shanghai",
    "iso:country":"CN",
    "name:zho_x_preferred":[
        "\u4e2d\u5cad\u4e0a"
    ],
    "wof:name":"Zhonglingshang",
    "wof:placetype":"locality"
},
  "geometry": {"coordinates":[107.59765,31.70107],"type":"Point"}
}