{
  "type": "Feature",
  "properties": {
    "gn:admin1_code":"8.0",
    "gn:asciiname":"Dongzuocun",
    "gn:country_code":"CN",
    "gn:dem":131,
    "gn:feature_class":"P",
    "gn:feature_code":"PPL",
    "gn:name":"Dongzuocun",
    "gn:population":0,
    "gn:timezone":"Asia/Shanghai",
    "iso:country":"CN",
    "name:zho_x_preferred":[
        "\u4e1c\u67de\u6751"
    ],
    "wof:name":"Dongzuocun",
    "wof:placetype":"locality"
},
  "geometry": {"coordinates":[130.29498999999998,46.21737],"type":"Point"}
}