{
  "type": "Feature",
  "properties": {
    "gn:admin1_code":"3.0",
    "gn:asciiname":"Xikengdong",
    "gn:country_code":"CN",
    "gn:dem":644,
    "gn:feature_class":"P",
    "gn:feature_code":"PPL",
    "gn:name":"Xikengdong",
    "gn:population":0,
    "gn:timezone":"Asia/Shanghai",
    "iso:country":"CN",
    "name:und_x_variant":[
        "\u897f\u5751\u6d1e"
    ],
    "wof:name":"Xikengdong",
    "wof:placetype":"locality"
},
  "geometry": {"coordinates":[114.8608,29.02868],"type":"Point"}
}