{
  "type": "Feature",
  "properties": {
    "gn:admin1_code":"1.0",
    "gn:asciiname":"Yangjiaduncun",
    "gn:country_code":"CN",
    "gn:dem":229,
    "gn:feature_class":"P",
    "gn:feature_code":"PPL",
    "gn:name":"Yangjiaduncun",
    "gn:population":0,
    "gn:timezone":"Asia/Shanghai",
    "iso:country":"CN",
    "name:und_x_variant":[
        "Yangjiadun"
    ],
    "name:zho_x_preferred":[
        "\u6768\u5bb6\u58a9\u6751"
    ],
    "wof:name":"Yangjiaduncun",
    "wof:placetype":"locality"
},
  "geometry": {"coordinates":[117.78304,30.04823],"type":"Point"}
}