{
  "type": "Feature",
  "properties": {
    "gn:admin1_code":"11.0",
    "gn:asciiname":"Changlinggang",
    "gn:country_code":"CN",
    "gn:dem":70,
    "gn:feature_class":"P",
    "gn:feature_code":"PPL",
    "gn:name":"Changlinggang",
    "gn:population":0,
    "gn:timezone":"Asia/Shanghai",
    "iso:country":"CN",
    "name:zho_x_preferred":[
        "Changlinggang"
    ],
    "name:zho_x_variant":[
        "\u957f\u5cad\u5c97"
    ],
    "wof:name":"Changlinggang",
    "wof:placetype":"locality"
},
  "geometry": {"coordinates":[111.55985,29.11702],"type":"Point"}
}