{
  "type": "Feature",
  "properties": {
    "gn:admin1_code":"11.0",
    "gn:asciiname":"Dawu Luojia",
    "gn:country_code":"CN",
    "gn:dem":107,
    "gn:feature_class":"P",
    "gn:feature_code":"PPL",
    "gn:name":"Dawu Luojia",
    "gn:population":0,
    "gn:timezone":"Asia/Shanghai",
    "iso:country":"CN",
    "name:zho_x_preferred":[
        "\u5927\u5c4b\u7f57\u5bb6"
    ],
    "wof:name":"Dawu Luojia",
    "wof:placetype":"locality"
},
  "geometry": {"coordinates":[113.08436,26.64153],"type":"Point"}
}