{
  "type": "Feature",
  "properties": {
    "gn:admin1_code":"25.0",
    "gn:asciiname":"Dushanzhuangcun",
    "gn:country_code":"CN",
    "gn:dem":89,
    "gn:feature_class":"P",
    "gn:feature_code":"PPL",
    "gn:name":"Dushanzhuangcun",
    "gn:population":0,
    "gn:timezone":"Asia/Shanghai",
    "iso:country":"CN",
    "name:zho_x_preferred":[
        "\u72ec\u5c71\u5e84\u6751"
    ],
    "wof:name":"Dushanzhuangcun",
    "wof:placetype":"locality"
},
  "geometry": {"coordinates":[116.84577,35.19909000000001],"type":"Point"}
}