{
  "type": "Feature",
  "properties": {
    "gn:admin1_code":"6.0",
    "gn:asciiname":"Dongguo",
    "gn:country_code":"CN",
    "gn:dem":3035,
    "gn:feature_class":"P",
    "gn:feature_code":"PPL",
    "gn:name":"Dongguo",
    "gn:population":0,
    "gn:timezone":"Asia/Shanghai",
    "iso:country":"CN",
    "name:und_x_variant":[
        "\u51ac\u679c"
    ],
    "wof:name":"Dongguo",
    "wof:placetype":"locality"
},
  "geometry": {"coordinates":[102.03623,35.83551],"type":"Point"}
}