{
  "type": "Feature",
  "properties": {
    "gn:admin1_code":"29.0",
    "gn:asciiname":"Feitu",
    "gn:country_code":"CN",
    "gn:dem":2078,
    "gn:feature_class":"P",
    "gn:feature_code":"PPL",
    "gn:name":"Feitu",
    "gn:population":0,
    "gn:timezone":"Asia/Shanghai",
    "iso:country":"CN",
    "name:zho_x_preferred":[
        "\u83f2\u9014"
    ],
    "wof:name":"Feitu",
    "wof:placetype":"locality"
},
  "geometry": {"coordinates":[103.548,23.6703],"type":"Point"}
}