{
  "type": "Feature",
  "properties": {
    "gn:admin1_code":"3",
    "gn:asciiname":"Guanghua",
    "gn:country_code":"CN",
    "gn:dem":118,
    "gn:feature_class":"P",
    "gn:feature_code":"PPL",
    "gn:name":"Guanghua",
    "gn:population":0,
    "gn:timezone":"Asia/Shanghai",
    "iso:country":"CN",
    "name:ceb_x_preferred":[
        "Guanghua"
    ],
    "name:deu_x_preferred":[
        "Guanghua"
    ],
    "name:pol_x_preferred":[
        "Guanghua"
    ],
    "name:swe_x_preferred":[
        "Guanghua"
    ],
    "name:zho_x_preferred":[
        "\u5e7f\u5316"
    ],
    "wof:name":"Guanghua",
    "wof:placetype":"locality"
},
  "geometry": {"coordinates":[114.62752999999999,27.0415],"type":"Point"}
}