{
  "type": "Feature",
  "properties": {
    "gn:admin1_code":"10",
    "gn:asciiname":"Songjiaqiao",
    "gn:country_code":"CN",
    "gn:dem":14,
    "gn:feature_class":"P",
    "gn:feature_code":"PPL",
    "gn:name":"Songjiaqiao",
    "gn:population":0,
    "gn:timezone":"Asia/Shanghai",
    "iso:country":"CN",
    "name:zho_x_preferred":[
        "\u5b8b\u5bb6\u6865"
    ],
    "name:zho_x_variant":[
        "\u5b8b\u5bb6\u6865\u8857\u9053"
    ],
    "wof:name":"Songjiaqiao",
    "wof:placetype":"locality"
},
  "geometry": {"coordinates":[115.63,38.7076],"type":"Point"}
}