{
  "type": "Feature",
  "properties": {
    "gn:admin1_code":"11.0",
    "gn:asciiname":"Zishengqiao",
    "gn:country_code":"CN",
    "gn:dem":319,
    "gn:feature_class":"P",
    "gn:feature_code":"PPL",
    "gn:name":"Zishengqiao",
    "gn:population":0,
    "gn:timezone":"Asia/Shanghai",
    "iso:country":"CN",
    "name:zho_x_preferred":[
        "\u81ea\u751f\u6865"
    ],
    "wof:name":"Zishengqiao",
    "wof:placetype":"locality"
},
  "geometry": {"coordinates":[109.9708,29.03764],"type":"Point"}
}