{
  "type": "Feature",
  "properties": {
    "gn:admin1_code":"11.0",
    "gn:asciiname":"Wenshuitang",
    "gn:country_code":"CN",
    "gn:dem":288,
    "gn:feature_class":"P",
    "gn:feature_code":"PPL",
    "gn:name":"Wenshuitang",
    "gn:population":0,
    "gn:timezone":"Asia/Shanghai",
    "iso:country":"CN",
    "name:zho_x_preferred":[
        "\u6e29\u6c34\u5858"
    ],
    "wof:name":"Wenshuitang",
    "wof:placetype":"locality"
},
  "geometry": {"coordinates":[111.48963000000001,26.71747],"type":"Point"}
}