{
  "type": "Feature",
  "properties": {
    "gn:admin1_code":"33.0",
    "gn:asciiname":"Sunjia",
    "gn:country_code":"CN",
    "gn:dem":739,
    "gn:feature_class":"P",
    "gn:feature_code":"PPLA4",
    "gn:name":"Sunjia",
    "gn:population":0,
    "gn:timezone":"Asia/Shanghai",
    "iso:country":"CN",
    "name:und_x_variant":[
        "Sunjia Zhen"
    ],
    "name:zho_x_preferred":[
        "\u5b59\u5bb6"
    ],
    "name:zho_x_variant":[
        "\u5b59\u5bb6\u9547"
    ],
    "wof:name":"Sunjia",
    "wof:placetype":"locality"
},
  "geometry": {"coordinates":[108.01373999999998,30.72977],"type":"Point"}
}