{
  "type": "Feature",
  "properties": {
    "gn:admin1_code":"19.0",
    "gn:asciiname":"Yangshugoucun",
    "gn:country_code":"CN",
    "gn:dem":133,
    "gn:feature_class":"P",
    "gn:feature_code":"PPL",
    "gn:name":"Yangshugoucun",
    "gn:population":0,
    "gn:timezone":"Asia/Shanghai",
    "iso:country":"CN",
    "name:zho_x_preferred":[
        "\u6768\u6811\u6c9f\u6751"
    ],
    "wof:name":"Yangshugoucun",
    "wof:placetype":"locality"
},
  "geometry": {"coordinates":[120.91494,41.37572],"type":"Point"}
}