{
  "type": "Feature",
  "properties": {
    "gn:admin1_code":"04",
    "gn:asciiname":"Hudai",
    "gn:country_code":"CN",
    "gn:dem":6,
    "gn:feature_class":"P",
    "gn:feature_code":"PPLA4",
    "gn:name":"Hudai",
    "gn:population":0,
    "gn:timezone":"Asia/Shanghai",
    "iso:country":"CN",
    "name:und_x_variant":[
        "Hu-tai",
        "Hu-tai-chen",
        "Hudai",
        "Hudai Zhen"
    ],
    "name:zho_x_preferred":[
        "\u80e1\u57ed"
    ],
    "name:zho_x_variant":[
        "\u80e1\u57ed\u9547"
    ],
    "wof:name":"Hudai",
    "wof:placetype":"locality"
},
  "geometry": {"coordinates":[120.11895,31.54878],"type":"Point"}
}