{
  "type": "Feature",
  "properties": {
    "gn:admin1_code":"30.0",
    "gn:asciiname":"Xiaoxitang",
    "gn:country_code":"CN",
    "gn:dem":95,
    "gn:feature_class":"P",
    "gn:feature_code":"PPL",
    "gn:name":"Xiaoxitang",
    "gn:population":0,
    "gn:timezone":"Asia/Shanghai",
    "iso:country":"CN",
    "name:zho_x_preferred":[
        "Xiaoxitang"
    ],
    "name:zho_x_variant":[
        "\u5c0f\u6eaa\u5858"
    ],
    "wof:name":"Xiaoxitang",
    "wof:placetype":"locality"
},
  "geometry": {"coordinates":[113.38806,24.84941],"type":"Point"}
}