{
  "type": "Feature",
  "properties": {
    "gn:admin1_code":"2.0",
    "gn:asciiname":"Fangmenjie",
    "gn:country_code":"CN",
    "gn:dem":53,
    "gn:feature_class":"P",
    "gn:feature_code":"PPL",
    "gn:name":"Fangmenjie",
    "gn:population":0,
    "gn:timezone":"Asia/Shanghai",
    "iso:country":"CN",
    "name:zho_x_preferred":[
        "\u65b9\u95e8\u8857"
    ],
    "wof:name":"Fangmenjie",
    "wof:placetype":"locality"
},
  "geometry": {"coordinates":[119.15057,29.02189000000001],"type":"Point"}
}