{
  "type": "Feature",
  "properties": {
    "gn:admin1_code":"29.0",
    "gn:asciiname":"Duimen",
    "gn:country_code":"CN",
    "gn:dem":2048,
    "gn:feature_class":"P",
    "gn:feature_code":"PPL",
    "gn:name":"Duimen",
    "gn:population":0,
    "gn:timezone":"Asia/Shanghai",
    "iso:country":"CN",
    "name:zho_x_preferred":[
        "\u5bf9\u95e8"
    ],
    "wof:name":"Duimen",
    "wof:placetype":"locality"
},
  "geometry": {"coordinates":[103.68600000000001,25.7092],"type":"Point"}
}