{
  "type": "Feature",
  "properties": {
    "gn:admin1_code":"32.0",
    "gn:asciiname":"Juhe",
    "gn:country_code":"CN",
    "gn:dem":386,
    "gn:feature_class":"P",
    "gn:feature_code":"PPL",
    "gn:name":"Juhe",
    "gn:population":0,
    "gn:timezone":"Asia/Shanghai",
    "iso:country":"CN",
    "name:zho_x_preferred":[
        "\u83ca\u6cb3"
    ],
    "wof:name":"Juhe",
    "wof:placetype":"locality"
},
  "geometry": {"coordinates":[105.01107,30.81002],"type":"Point"}
}