{
  "type": "Feature",
  "properties": {
    "gn:admin1_code":"8.0",
    "gn:asciiname":"Chunshancun",
    "gn:country_code":"CN",
    "gn:dem":151,
    "gn:feature_class":"P",
    "gn:feature_code":"PPL",
    "gn:name":"Chunshancun",
    "gn:population":0,
    "gn:timezone":"Asia/Shanghai",
    "iso:country":"CN",
    "name:zho_x_preferred":[
        "\u6625\u5c71\u6751"
    ],
    "wof:name":"Chunshancun",
    "wof:placetype":"locality"
},
  "geometry": {"coordinates":[131.69958,46.0042],"type":"Point"}
}