{
  "type": "Feature",
  "properties": {
    "gn:admin1_code":"8.0",
    "gn:asciiname":"Changhongcun",
    "gn:country_code":"CN",
    "gn:dem":198,
    "gn:feature_class":"P",
    "gn:feature_code":"PPL",
    "gn:name":"Changhongcun",
    "gn:population":0,
    "gn:timezone":"Asia/Shanghai",
    "iso:country":"CN",
    "name:zho_x_preferred":[
        "\u957f\u7ea2\u6751"
    ],
    "wof:name":"Changhongcun",
    "wof:placetype":"locality"
},
  "geometry": {"coordinates":[126.73662,45.51782],"type":"Point"}
}