{
  "type": "Feature",
  "properties": {
    "gn:admin1_code":"10",
    "gn:asciiname":"Yangjiafangbei",
    "gn:country_code":"CN",
    "gn:dem":39,
    "gn:feature_class":"P",
    "gn:feature_code":"PPL",
    "gn:name":"Yangjiafangbei",
    "gn:population":0,
    "gn:timezone":"Asia/Shanghai",
    "iso:country":"CN",
    "name:zho_x_preferred":[
        "\u6768\u5bb6\u65b9\u7891"
    ],
    "wof:name":"Yangjiafangbei",
    "wof:placetype":"locality"
},
  "geometry": {"coordinates":[115.223,37.9318],"type":"Point"}
}