{
  "type": "Feature",
  "properties": {
    "gn:admin1_code":"12.0",
    "gn:asciiname":"Kejiayuan",
    "gn:country_code":"CN",
    "gn:dem":535,
    "gn:feature_class":"P",
    "gn:feature_code":"PPL",
    "gn:name":"Kejiayuan",
    "gn:population":0,
    "gn:timezone":"Asia/Shanghai",
    "iso:country":"CN",
    "name:zho_x_preferred":[
        "\u67ef\u5bb6\u9662"
    ],
    "wof:name":"Kejiayuan",
    "wof:placetype":"locality"
},
  "geometry": {"coordinates":[110.26383,32.09412],"type":"Point"}
}