{
  "type": "Feature",
  "properties": {
    "gn:admin1_code":"26.0",
    "gn:asciiname":"Chenyucun",
    "gn:country_code":"CN",
    "gn:dem":908,
    "gn:feature_class":"P",
    "gn:feature_code":"PPL",
    "gn:name":"Chenyucun",
    "gn:population":0,
    "gn:timezone":"Asia/Shanghai",
    "iso:country":"CN",
    "name:zho_x_preferred":[
        "\u9648\u5cea\u6751"
    ],
    "wof:name":"Chenyucun",
    "wof:placetype":"locality"
},
  "geometry": {"coordinates":[110.05202,35.36014],"type":"Point"}
}