{
  "type": "Feature",
  "properties": {
    "gn:admin1_code":"26.0",
    "gn:asciiname":"Xiafengqu",
    "gn:country_code":"CN",
    "gn:dem":1205,
    "gn:feature_class":"P",
    "gn:feature_code":"PPL",
    "gn:name":"Xiafengqu",
    "gn:population":0,
    "gn:timezone":"Asia/Shanghai",
    "iso:country":"CN",
    "name:zho_x_preferred":[
        "\u4e0b\u98ce\u6e20"
    ],
    "wof:name":"Xiafengqu",
    "wof:placetype":"locality"
},
  "geometry": {"coordinates":[110.50675,39.06663],"type":"Point"}
}