{
  "type": "Feature",
  "properties": {
    "gn:admin1_code":"11.0",
    "gn:asciiname":"Caowanchong",
    "gn:country_code":"CN",
    "gn:dem":296,
    "gn:feature_class":"P",
    "gn:feature_code":"PPL",
    "gn:name":"Caowanchong",
    "gn:population":0,
    "gn:timezone":"Asia/Shanghai",
    "iso:country":"CN",
    "name:zho_x_preferred":[
        "\u66f9\u6e7e\u51b2"
    ],
    "wof:name":"Caowanchong",
    "wof:placetype":"locality"
},
  "geometry": {"coordinates":[111.5501,27.0702],"type":"Point"}
}