{
  "type": "Feature",
  "properties": {
    "gn:admin1_code":"24",
    "gn:asciiname":"Fushanzhuang",
    "gn:country_code":"CN",
    "gn:dem":1053,
    "gn:feature_class":"P",
    "gn:feature_code":"PPLA4",
    "gn:name":"Fushanzhuang",
    "gn:population":0,
    "gn:timezone":"Asia/Shanghai",
    "iso:country":"CN",
    "name:und_x_variant":[
        "Fu-shan-chuang",
        "Fushanzhuang",
        "\u798f\u5584\u5e84",
        "Fushanzhuang Xiang",
        "\u798f\u5584\u5e84\u4e61"
    ],
    "wof:name":"Fushanzhuang",
    "wof:placetype":"locality"
},
  "geometry": {"coordinates":[112.62555999999999,39.24694],"type":"Point"}
}