{
  "type": "Feature",
  "properties": {
    "gn:admin1_code":"32.0",
    "gn:asciiname":"Wenmingtang",
    "gn:country_code":"CN",
    "gn:dem":434,
    "gn:feature_class":"P",
    "gn:feature_code":"PPL",
    "gn:name":"Wenmingtang",
    "gn:population":0,
    "gn:timezone":"Asia/Shanghai",
    "iso:country":"CN",
    "name:zho_x_preferred":[
        "\u6587\u660e\u5802"
    ],
    "wof:name":"Wenmingtang",
    "wof:placetype":"locality"
},
  "geometry": {"coordinates":[106.44799999999999,30.7685],"type":"Point"}
}