{
  "type": "Feature",
  "properties": {
    "gn:admin1_code":"15.0",
    "gn:asciiname":"Songxia",
    "gn:country_code":"CN",
    "gn:dem":1235,
    "gn:feature_class":"P",
    "gn:feature_code":"PPL",
    "gn:name":"Songxia",
    "gn:population":0,
    "gn:timezone":"Asia/Shanghai",
    "iso:country":"CN",
    "name:zho_x_preferred":[
        "\u5b8b\u5ce1"
    ],
    "wof:name":"Songxia",
    "wof:placetype":"locality"
},
  "geometry": {"coordinates":[105.65600000000001,34.8904],"type":"Point"}
}