{
  "type": "Feature",
  "properties": {
    "gn:admin1_code":"3.0",
    "gn:asciiname":"Zhumushi",
    "gn:country_code":"CN",
    "gn:dem":135,
    "gn:feature_class":"P",
    "gn:feature_code":"PPL",
    "gn:name":"Zhumushi",
    "gn:population":0,
    "gn:timezone":"Asia/Shanghai",
    "iso:country":"CN",
    "name:und_x_variant":[
        "\u732a\u59c6\u77f3"
    ],
    "wof:name":"Zhumushi",
    "wof:placetype":"locality"
},
  "geometry": {"coordinates":[116.38682,27.05479],"type":"Point"}
}