{
  "type": "Feature",
  "properties": {
    "gn:country":"CN",
    "gn:fcode":"PPLA3",
    "gn:pop":89119,
    "iso:country":"CN",
    "name:unk_x_variant":[
        "Lu-chiang-hsien"
    ],
    "name:zho_x_preferred":[
        "\u5e90\u6c5f\u53bf"
    ],
    "qs:name":"Lucheng",
    "qs:photos_9r":0,
    "qs:photos_sr":0,
    "qs:pop_sr":"8",
    "wd:wordcount":124,
    "wof:name":"Lucheng",
    "wof:placetype":"locality",
    "wof:population":89119
},
  "geometry": {"coordinates":[117.28057,31.23357],"type":"Point"}
}