{
  "type": "Feature",
  "properties": {
    "gn:admin1_code":"24.0",
    "gn:asciiname":"Shanglizhai",
    "gn:country_code":"CN",
    "gn:dem":1058,
    "gn:feature_class":"P",
    "gn:feature_code":"PPL",
    "gn:name":"Shanglizhai",
    "gn:population":0,
    "gn:timezone":"Asia/Shanghai",
    "iso:country":"CN",
    "name:zho_x_preferred":[
        "\u4e0a\u7acb\u5be8"
    ],
    "wof:name":"Shanglizhai",
    "wof:placetype":"locality"
},
  "geometry": {"coordinates":[112.61505,36.36946],"type":"Point"}
}