{
  "type": "Feature",
  "properties": {
    "gn:admin1_code":"26.0",
    "gn:asciiname":"Xiasanqingcun",
    "gn:country_code":"CN",
    "gn:dem":449,
    "gn:feature_class":"P",
    "gn:feature_code":"PPL",
    "gn:name":"Xiasanqingcun",
    "gn:population":0,
    "gn:timezone":"Asia/Shanghai",
    "iso:country":"CN",
    "name:zho_x_preferred":[
        "\u4e0b\u4e09\u6e05\u6751"
    ],
    "wof:name":"Xiasanqingcun",
    "wof:placetype":"locality"
},
  "geometry": {"coordinates":[108.25829,34.10053],"type":"Point"}
}