{
  "type": "Feature",
  "properties": {
    "gn:admin1_code":"32.0",
    "gn:asciiname":"Aokoushang",
    "gn:country_code":"CN",
    "gn:dem":474,
    "gn:feature_class":"P",
    "gn:feature_code":"PPL",
    "gn:name":"Aokoushang",
    "gn:population":0,
    "gn:timezone":"Asia/Shanghai",
    "iso:country":"CN",
    "name:zho_x_preferred":[
        "\u5787\u53e3\u4e0a"
    ],
    "wof:name":"Aokoushang",
    "wof:placetype":"locality"
},
  "geometry": {"coordinates":[104.91228,29.06358],"type":"Point"}
}