{
  "type": "Feature",
  "properties": {
    "gn:admin1_code":"16.0",
    "gn:asciiname":"Dongmei",
    "gn:country_code":"CN",
    "gn:dem":565,
    "gn:feature_class":"P",
    "gn:feature_code":"PPL",
    "gn:name":"Dongmei",
    "gn:population":0,
    "gn:timezone":"Asia/Shanghai",
    "iso:country":"CN",
    "name:zho_x_preferred":[
        "\u4e1c\u7709"
    ],
    "wof:name":"Dongmei",
    "wof:placetype":"locality"
},
  "geometry": {"coordinates":[107.89700000000001,24.9282],"type":"Point"}
}