{
  "type": "Feature",
  "properties": {
    "gn:admin1_code":"9.0",
    "gn:asciiname":"Longpaigou",
    "gn:country_code":"CN",
    "gn:dem":189,
    "gn:feature_class":"P",
    "gn:feature_code":"PPL",
    "gn:name":"Longpaigou",
    "gn:population":0,
    "gn:timezone":"Asia/Shanghai",
    "iso:country":"CN",
    "name:zho_x_preferred":[
        "\u9f99\u6392\u6c9f"
    ],
    "wof:name":"Longpaigou",
    "wof:placetype":"locality"
},
  "geometry": {"coordinates":[112.4554,33.45949],"type":"Point"}
}