{
  "type": "Feature",
  "properties": {
    "gn:admin1_code":"23",
    "gn:asciiname":"Huqiao",
    "gn:country_code":"CN",
    "gn:dem":6,
    "gn:feature_class":"P",
    "gn:feature_code":"PPL",
    "gn:name":"Huqiao",
    "gn:population":0,
    "gn:timezone":"Asia/Shanghai",
    "iso:country":"CN",
    "name:und_x_variant":[
        "Hu-chia-ch\u2019iao",
        "Huqiao",
        "\u80e1\u6865"
    ],
    "wof:name":"Huqiao",
    "wof:placetype":"locality"
},
  "geometry": {"coordinates":[121.42753999999999,30.83166],"type":"Point"}
}