{
  "type": "Feature",
  "properties": {
    "gn:admin1_code":"32.0",
    "gn:asciiname":"Luojia Yuanzi",
    "gn:country_code":"CN",
    "gn:dem":553,
    "gn:feature_class":"P",
    "gn:feature_code":"PPL",
    "gn:name":"Luojia Yuanzi",
    "gn:population":0,
    "gn:timezone":"Asia/Shanghai",
    "iso:country":"CN",
    "name:zho_x_preferred":[
        "\u7f57\u5bb6\u9662\u5b50"
    ],
    "wof:name":"Luojia Yuanzi",
    "wof:placetype":"locality"
},
  "geometry": {"coordinates":[104.28442,31.29561],"type":"Point"}
}