{
  "type": "Feature",
  "properties": {
    "gn:admin1_code":"11",
    "gn:asciiname":"Ximixi",
    "gn:country_code":"CN",
    "gn:dem":298,
    "gn:feature_class":"P",
    "gn:feature_code":"PPL",
    "gn:name":"Ximixi",
    "gn:population":0,
    "gn:timezone":"Asia/Shanghai",
    "iso:country":"CN",
    "name:zho_x_preferred":[
        "\u7ec6\u7c73\u6eaa"
    ],
    "wof:name":"Ximixi",
    "wof:placetype":"locality"
},
  "geometry": {"coordinates":[109.4796,27.45224],"type":"Point"}
}