{
  "type": "Feature",
  "properties": {
    "gn:admin1_code":"29",
    "gn:asciiname":"Sansuzhai",
    "gn:country_code":"CN",
    "gn:dem":1611,
    "gn:feature_class":"P",
    "gn:feature_code":"PPL",
    "gn:name":"Sansuzhai",
    "gn:population":0,
    "gn:timezone":"Asia/Shanghai",
    "iso:country":"CN",
    "name:zho_x_preferred":[
        "\u4e09\u82cf\u5be8"
    ],
    "wof:name":"Sansuzhai",
    "wof:placetype":"locality"
},
  "geometry": {"coordinates":[101.68899999999999,24.1581],"type":"Point"}
}