{
  "type": "Feature",
  "properties": {
    "gn:admin1_code":"15.0",
    "gn:asciiname":"Dalaozi",
    "gn:country_code":"CN",
    "gn:dem":2210,
    "gn:feature_class":"P",
    "gn:feature_code":"PPL",
    "gn:name":"Dalaozi",
    "gn:population":0,
    "gn:timezone":"Asia/Shanghai",
    "iso:country":"CN",
    "name:zho_x_preferred":[
        "\u5927\u6d9d\u5b50"
    ],
    "wof:name":"Dalaozi",
    "wof:placetype":"locality"
},
  "geometry": {"coordinates":[104.40300000000001,35.3276],"type":"Point"}
}