{
  "type": "Feature",
  "properties": {
    "gn:admin1_code":"14",
    "gn:asciiname":"Babunima",
    "gn:country_code":"CN",
    "gn:dem":4758,
    "gn:feature_class":"P",
    "gn:feature_code":"PPL",
    "gn:name":"Babunima",
    "gn:population":0,
    "gn:timezone":"Asia/Urumqi",
    "iso:country":"CN",
    "name:zho_x_preferred":[
        "\u5df4\u5e03\u576d\u5417"
    ],
    "wof:name":"Babunima",
    "wof:placetype":"locality"
},
  "geometry": {"coordinates":[88.64060000000001,29.9884],"type":"Point"}
}