{
  "type": "Feature",
  "properties": {
    "gn:admin1_code":"19.0",
    "gn:asciiname":"Xiaosanjiazi",
    "gn:country_code":"CN",
    "gn:dem":6,
    "gn:feature_class":"P",
    "gn:feature_code":"PPL",
    "gn:name":"Xiaosanjiazi",
    "gn:population":0,
    "gn:timezone":"Asia/Shanghai",
    "iso:country":"CN",
    "name:und_x_variant":[
        "\u5c0f\u4e09\u5bb6\u5b50"
    ],
    "wof:name":"Xiaosanjiazi",
    "wof:placetype":"locality"
},
  "geometry": {"coordinates":[122.452,40.9307],"type":"Point"}
}