{
  "type": "Feature",
  "properties": {
    "gn:admin1_code":"10.0",
    "gn:asciiname":"Zhangshenzhuang",
    "gn:country_code":"CN",
    "gn:dem":13,
    "gn:feature_class":"P",
    "gn:feature_code":"PPL",
    "gn:name":"Zhangshenzhuang",
    "gn:population":0,
    "gn:timezone":"Asia/Shanghai",
    "iso:country":"CN",
    "name:zho_x_preferred":[
        "\u5f20\u7533\u5e84"
    ],
    "wof:name":"Zhangshenzhuang",
    "wof:placetype":"locality"
},
  "geometry": {"coordinates":[116.60557,37.934],"type":"Point"}
}