{
  "type": "Feature",
  "properties": {
    "gn:admin1_code":"26.0",
    "gn:asciiname":"Sunjia Guacun",
    "gn:country_code":"CN",
    "gn:dem":957,
    "gn:feature_class":"P",
    "gn:feature_code":"PPL",
    "gn:name":"Sunjia Guacun",
    "gn:population":0,
    "gn:timezone":"Asia/Shanghai",
    "iso:country":"CN",
    "name:zho_x_preferred":[
        "\u5b59\u5bb6\u576c\u6751"
    ],
    "wof:name":"Sunjia Guacun",
    "wof:placetype":"locality"
},
  "geometry": {"coordinates":[110.01300000000001,37.9098],"type":"Point"}
}