{
  "type": "Feature",
  "properties": {
    "gn:admin1_code":"03",
    "gn:asciiname":"Nanjing",
    "gn:country_code":"CN",
    "gn:dem":302,
    "gn:feature_class":"P",
    "gn:feature_code":"PPLA4",
    "gn:name":"Nanjing",
    "gn:population":0,
    "gn:timezone":"Asia/Shanghai",
    "iso:country":"CN",
    "name:rus_x_preferred":[
        "\u041d\u0430\u043d\u043a\u0438\u043d"
    ],
    "name:und_x_variant":[
        "Nan-ching-hs\u00fc",
        "Nan-ching",
        "Nanjing",
        "\u5357\u8ff3",
        "Nanjing Zhen",
        "\u5357\u8ff3\u9547"
    ],
    "wof:name":"Nanjing",
    "wof:placetype":"locality"
},
  "geometry": {"coordinates":[114.40129,24.68629],"type":"Point"}
}