{
  "type": "Feature",
  "properties": {
    "gn:admin1_code":"2.0",
    "gn:asciiname":"Xiaoliao",
    "gn:country_code":"CN",
    "gn:dem":670,
    "gn:feature_class":"P",
    "gn:feature_code":"PPL",
    "gn:name":"Xiaoliao",
    "gn:population":0,
    "gn:timezone":"Asia/Shanghai",
    "iso:country":"CN",
    "name:zho_x_preferred":[
        "\u5c0f\u6f66"
    ],
    "wof:name":"Xiaoliao",
    "wof:placetype":"locality"
},
  "geometry": {"coordinates":[120.40915,29.43093],"type":"Point"}
}