{
  "type": "Feature",
  "properties": {
    "gn:admin1_code":"12.0",
    "gn:asciiname":"Caojiayuan",
    "gn:country_code":"CN",
    "gn:dem":224,
    "gn:feature_class":"P",
    "gn:feature_code":"PPL",
    "gn:name":"Caojiayuan",
    "gn:population":0,
    "gn:timezone":"Asia/Shanghai",
    "iso:country":"CN",
    "name:zho_x_preferred":[
        "Caojiayuan"
    ],
    "name:zho_x_variant":[
        "\u66f9\u5bb6\u6e90"
    ],
    "wof:name":"Caojiayuan",
    "wof:placetype":"locality"
},
  "geometry": {"coordinates":[114.40269000000001,29.45345],"type":"Point"}
}