{
  "type": "Feature",
  "properties": {
    "gn:admin1_code":"9.0",
    "gn:asciiname":"Baihe",
    "gn:country_code":"CN",
    "gn:dem":122,
    "gn:feature_class":"P",
    "gn:feature_code":"PPL",
    "gn:name":"Baihe",
    "gn:population":0,
    "gn:timezone":"Asia/Shanghai",
    "iso:country":"CN",
    "name:deu_x_preferred":[
        "Baihe"
    ],
    "name:nor_x_preferred":[
        "Baihe"
    ],
    "name:zho_x_preferred":[
        "\u767d\u6cb3"
    ],
    "wof:name":"Baihe",
    "wof:placetype":"locality"
},
  "geometry": {"coordinates":[112.52325,32.96338],"type":"Point"}
}