{
  "type": "Feature",
  "properties": {
    "gn:admin1_code":"8.0",
    "gn:asciiname":"Balizhuang",
    "gn:country_code":"CN",
    "gn:dem":62,
    "gn:feature_class":"P",
    "gn:feature_code":"PPL",
    "gn:name":"Balizhuang",
    "gn:population":0,
    "gn:timezone":"Asia/Shanghai",
    "iso:country":"CN",
    "name:zho_x_preferred":[
        "\u516b\u91cc\u6869"
    ],
    "wof:name":"Balizhuang",
    "wof:placetype":"locality"
},
  "geometry": {"coordinates":[133.49714,47.33264000000001],"type":"Point"}
}