{
  "type": "Feature",
  "properties": {
    "gn:admin1_code":"26.0",
    "gn:asciiname":"Baiyazhai",
    "gn:country_code":"CN",
    "gn:dem":997,
    "gn:feature_class":"P",
    "gn:feature_code":"PPL",
    "gn:name":"Baiyazhai",
    "gn:population":0,
    "gn:timezone":"Asia/Shanghai",
    "iso:country":"CN",
    "name:zho_x_preferred":[
        "\u767d\u5d16\u5be8"
    ],
    "wof:name":"Baiyazhai",
    "wof:placetype":"locality"
},
  "geometry": {"coordinates":[108.66991000000002,32.90824],"type":"Point"}
}