{
  "type": "Feature",
  "properties": {
    "gn:admin1_code":"4.0",
    "gn:asciiname":"Baolou",
    "gn:country_code":"CN",
    "gn:dem":20,
    "gn:feature_class":"P",
    "gn:feature_code":"PPL",
    "gn:name":"Baolou",
    "gn:population":0,
    "gn:timezone":"Asia/Shanghai",
    "iso:country":"CN",
    "name:zho_x_preferred":[
        "\u9c8d\u697c"
    ],
    "wof:name":"Baolou",
    "wof:placetype":"locality"
},
  "geometry": {"coordinates":[118.04000000000001,33.7741],"type":"Point"}
}