{
  "type": "Feature",
  "properties": {
    "gn:admin1_code":"11.0",
    "gn:asciiname":"Ganzhouzhai",
    "gn:country_code":"CN",
    "gn:dem":32,
    "gn:feature_class":"P",
    "gn:feature_code":"PPL",
    "gn:name":"Ganzhouzhai",
    "gn:population":0,
    "gn:timezone":"Asia/Shanghai",
    "iso:country":"CN",
    "name:zho_x_preferred":[
        "\u8d76\u6d32\u5be8"
    ],
    "wof:name":"Ganzhouzhai",
    "wof:placetype":"locality"
},
  "geometry": {"coordinates":[112.98063,28.95343],"type":"Point"}
}