{
  "type": "Feature",
  "properties": {
    "gn:admin1_code":"32",
    "gn:asciiname":"Liujiachang",
    "gn:cc2":"CN",
    "gn:country_code":"CN",
    "gn:dem":396,
    "gn:feature_class":"P",
    "gn:feature_code":"PPL",
    "gn:name":"Liujiachang",
    "gn:population":0,
    "gn:timezone":"Asia/Shanghai",
    "iso:country":"CN",
    "name:und_x_variant":[
        "Liu-chia-ch\u2019ang",
        "Liujiachang"
    ],
    "wof:name":"Liujiachang",
    "wof:placetype":"locality"
},
  "geometry": {"coordinates":[104.58333,30.03333],"type":"Point"}
}