{
  "type": "Feature",
  "properties": {
    "gn:admin1_code":"15.0",
    "gn:asciiname":"Luojiashan",
    "gn:country_code":"CN",
    "gn:dem":2009,
    "gn:feature_class":"P",
    "gn:feature_code":"PPL",
    "gn:name":"Luojiashan",
    "gn:population":0,
    "gn:timezone":"Asia/Shanghai",
    "iso:country":"CN",
    "name:und_x_variant":[
        "\u7f57\u5bb6\u5c71"
    ],
    "wof:name":"Luojiashan",
    "wof:placetype":"locality"
},
  "geometry": {"coordinates":[104.88281000000001,34.66917],"type":"Point"}
}