{
  "type": "Feature",
  "properties": {
    "gn:admin1_code":"29.0",
    "gn:asciiname":"Huangnipo",
    "gn:country_code":"CN",
    "gn:dem":1645,
    "gn:feature_class":"P",
    "gn:feature_code":"PPL",
    "gn:name":"Huangnipo",
    "gn:population":0,
    "gn:timezone":"Asia/Shanghai",
    "iso:country":"CN",
    "name:zho_x_preferred":[
        "\u9ec4\u6ce5\u5761"
    ],
    "wof:name":"Huangnipo",
    "wof:placetype":"locality"
},
  "geometry": {"coordinates":[103.148,23.221],"type":"Point"}
}