{
  "type": "Feature",
  "properties": {
    "gn:admin1_code":"15.0",
    "gn:asciiname":"Xujia Dazhuang",
    "gn:country_code":"CN",
    "gn:dem":1541,
    "gn:feature_class":"P",
    "gn:feature_code":"PPL",
    "gn:name":"Xujia Dazhuang",
    "gn:population":0,
    "gn:timezone":"Asia/Shanghai",
    "iso:country":"CN",
    "name:zho_x_preferred":[
        "\u8bb8\u5bb6\u5927\u5e84"
    ],
    "wof:name":"Xujia Dazhuang",
    "wof:placetype":"locality"
},
  "geometry": {"coordinates":[102.58,37.9362],"type":"Point"}
}