{
  "type": "Feature",
  "properties": {
    "gn:admin1_code":"7",
    "gn:asciiname":"Xiacun",
    "gn:country_code":"CN",
    "gn:dem":613,
    "gn:feature_class":"P",
    "gn:feature_code":"PPL",
    "gn:name":"Xiacun",
    "gn:population":0,
    "gn:timezone":"Asia/Shanghai",
    "iso:country":"CN",
    "name:und_x_variant":[
        "\u4e0b\u6751"
    ],
    "wof:name":"Xiacun",
    "wof:placetype":"locality"
},
  "geometry": {"coordinates":[118.73583000000001,27.77306],"type":"Point"}
}