{
  "type": "Feature",
  "properties": {
    "gn:admin1_code":"6.0",
    "gn:asciiname":"Xialuowa",
    "gn:country_code":"CN",
    "gn:dem":2983,
    "gn:feature_class":"P",
    "gn:feature_code":"PPL",
    "gn:name":"Xialuowa",
    "gn:population":0,
    "gn:timezone":"Asia/Shanghai",
    "iso:country":"CN",
    "name:zho_x_preferred":[
        "\u4e0b\u6d1b\u54c7"
    ],
    "wof:name":"Xialuowa",
    "wof:placetype":"locality"
},
  "geometry": {"coordinates":[100.62658999999999,35.65425],"type":"Point"}
}