{
  "type": "Feature",
  "properties": {
    "gn:admin1_code":"16",
    "gn:asciiname":"Dujie",
    "gn:cc2":"CN",
    "gn:country_code":"CN",
    "gn:dem":528,
    "gn:feature_class":"P",
    "gn:feature_code":"PPL",
    "gn:name":"Dujie",
    "gn:population":0,
    "gn:timezone":"Asia/Shanghai",
    "iso:country":"CN",
    "name:und_x_variant":[
        "Tu-chieh",
        "Dujie"
    ],
    "wof:name":"Dujie",
    "wof:placetype":"locality"
},
  "geometry": {"coordinates":[107.34999999999999,23.15],"type":"Point"}
}