{
  "type": "Feature",
  "properties": {
    "gn:admin1_code":"26",
    "gn:asciiname":"Siyuanping",
    "gn:country_code":"CN",
    "gn:dem":1185,
    "gn:feature_class":"P",
    "gn:feature_code":"PPL",
    "gn:name":"Siyuanping",
    "gn:population":0,
    "gn:timezone":"Asia/Shanghai",
    "iso:country":"CN",
    "name:und_x_variant":[
        "Ssu-y\u00fcan-p\u2019ing",
        "Ssu-y\u00fcan",
        "Siyuan",
        "Siyuanping"
    ],
    "name:zho_x_preferred":[
        "\u5bfa\u586c\u576a"
    ],
    "wof:name":"Siyuanping",
    "wof:placetype":"locality"
},
  "geometry": {"coordinates":[110.09887999999999,36.66541],"type":"Point"}
}