{
  "type": "Feature",
  "properties": {
    "gn:admin1_code":"15.0",
    "gn:asciiname":"Sangba",
    "gn:country_code":"CN",
    "gn:dem":2150,
    "gn:feature_class":"P",
    "gn:feature_code":"PPLA4",
    "gn:name":"Sangba",
    "gn:population":0,
    "gn:timezone":"Asia/Shanghai",
    "iso:country":"CN",
    "name:msa_x_preferred":[
        "Sangba"
    ],
    "name:und_x_variant":[
        "\u6851\u575d"
    ],
    "wof:name":"Sangba",
    "wof:placetype":"locality"
},
  "geometry": {"coordinates":[103.79044,34.03907],"type":"Point"}
}