{
  "type": "Feature",
  "properties": {
    "gn:admin1_code":"10.0",
    "gn:asciiname":"Beitaizhuang",
    "gn:country_code":"CN",
    "gn:dem":66,
    "gn:feature_class":"P",
    "gn:feature_code":"PPL",
    "gn:name":"Beitaizhuang",
    "gn:population":0,
    "gn:timezone":"Asia/Shanghai",
    "iso:country":"CN",
    "name:zho_x_preferred":[
        "\u5317\u53f0\u5e84"
    ],
    "wof:name":"Beitaizhuang",
    "wof:placetype":"locality"
},
  "geometry": {"coordinates":[119.24182999999999,40.01618],"type":"Point"}
}