{
  "type": "Feature",
  "properties": {
    "gn:admin1_code":"32.0",
    "gn:asciiname":"Huatouzui",
    "gn:country_code":"CN",
    "gn:dem":3453,
    "gn:feature_class":"P",
    "gn:feature_code":"PPL",
    "gn:name":"Huatouzui",
    "gn:population":0,
    "gn:timezone":"Asia/Shanghai",
    "iso:country":"CN",
    "name:zho_x_preferred":[
        "\u94e7\u5934\u5480"
    ],
    "wof:name":"Huatouzui",
    "wof:placetype":"locality"
},
  "geometry": {"coordinates":[102.31399999999999,31.1216],"type":"Point"}
}