{
  "type": "Feature",
  "properties": {
    "gn:admin1_code":"1.0",
    "gn:asciiname":"Bancangcun",
    "gn:country_code":"CN",
    "gn:dem":510,
    "gn:feature_class":"P",
    "gn:feature_code":"PPL",
    "gn:name":"Bancangcun",
    "gn:population":0,
    "gn:timezone":"Asia/Shanghai",
    "iso:country":"CN",
    "name:zho_x_preferred":[
        "\u677f\u4ed3\u6751"
    ],
    "wof:name":"Bancangcun",
    "wof:placetype":"locality"
},
  "geometry": {"coordinates":[116.54351,30.99784],"type":"Point"}
}