{
  "type": "Feature",
  "properties": {
    "gn:admin1_code":"11",
    "gn:asciiname":"Baya",
    "gn:country_code":"CN",
    "gn:dem":469,
    "gn:feature_class":"P",
    "gn:feature_code":"PPL",
    "gn:name":"Baya",
    "gn:population":0,
    "gn:timezone":"Asia/Shanghai",
    "iso:country":"CN",
    "name:ara_x_preferred":[
        "\u0628\u0627\u064a\u0629"
    ],
    "name:ceb_x_preferred":[
        "Baya"
    ],
    "name:deu_x_preferred":[
        "Baya"
    ],
    "name:fra_x_preferred":[
        "Baya"
    ],
    "name:spa_x_preferred":[
        "Baya"
    ],
    "name:swe_x_preferred":[
        "Baya"
    ],
    "wof:name":"Baya",
    "wof:placetype":"locality"
},
  "geometry": {"coordinates":[109.53639,26.32417],"type":"Point"}
}