{
  "type": "Feature",
  "properties": {
    "gn:admin1_code":"20.0",
    "gn:asciiname":"Jialatu",
    "gn:country_code":"CN",
    "gn:dem":1453,
    "gn:feature_class":"P",
    "gn:feature_code":"PPL",
    "gn:name":"Jialatu",
    "gn:population":0,
    "gn:timezone":"Asia/Shanghai",
    "iso:country":"CN",
    "name:und_x_variant":[
        "\u7532\u62c9\u56fe"
    ],
    "wof:name":"Jialatu",
    "wof:placetype":"locality"
},
  "geometry": {"coordinates":[112.30249999999999,41.15068],"type":"Point"}
}