{
  "type": "Feature",
  "properties": {
    "gn:admin1_code":"30.0",
    "gn:asciiname":"Xiniutang",
    "gn:country_code":"CN",
    "gn:dem":130,
    "gn:feature_class":"P",
    "gn:feature_code":"PPL",
    "gn:name":"Xiniutang",
    "gn:population":0,
    "gn:timezone":"Asia/Shanghai",
    "iso:country":"CN",
    "name:zho_x_preferred":[
        "Xiniutang"
    ],
    "name:zho_x_variant":[
        "\u897f\u725b\u5858"
    ],
    "wof:name":"Xiniutang",
    "wof:placetype":"locality"
},
  "geometry": {"coordinates":[114.40163,24.14705],"type":"Point"}
}