{
  "type": "Feature",
  "properties": {
    "gn:admin1_code":"16.0",
    "gn:asciiname":"Zuqian",
    "gn:country_code":"CN",
    "gn:dem":757,
    "gn:feature_class":"P",
    "gn:feature_code":"PPL",
    "gn:name":"Zuqian",
    "gn:population":0,
    "gn:timezone":"Asia/Shanghai",
    "iso:country":"CN",
    "name:zho_x_preferred":[
        "\u8db3\u4e7e"
    ],
    "wof:name":"Zuqian",
    "wof:placetype":"locality"
},
  "geometry": {"coordinates":[105.611,24.433],"type":"Point"}
}