{
  "type": "Feature",
  "properties": {
    "gn:admin1_code":"03",
    "gn:asciiname":"Shabutan",
    "gn:cc2":"CN",
    "gn:country_code":"CN",
    "gn:dem":21,
    "gn:feature_class":"P",
    "gn:feature_code":"PPL",
    "gn:name":"Shabutan",
    "gn:population":0,
    "gn:timezone":"Asia/Shanghai",
    "iso:country":"CN",
    "name:und_x_variant":[
        "Sha-pu-t\u2019an",
        "Shafowtan",
        "Sha-fou-t\u2019an",
        "Shabutan"
    ],
    "wof:name":"Shabutan",
    "wof:placetype":"locality"
},
  "geometry": {"coordinates":[115.98333,28.45],"type":"Point"}
}