{
  "type": "Feature",
  "properties": {
    "gn:admin1_code":"26.0",
    "gn:asciiname":"Dadaodi",
    "gn:country_code":"CN",
    "gn:dem":648,
    "gn:feature_class":"P",
    "gn:feature_code":"PPL",
    "gn:name":"Dadaodi",
    "gn:population":0,
    "gn:timezone":"Asia/Shanghai",
    "iso:country":"CN",
    "name:zho_x_preferred":[
        "\u5927\u7a3b\u5730"
    ],
    "wof:name":"Dadaodi",
    "wof:placetype":"locality"
},
  "geometry": {"coordinates":[109.61863999999998,33.44721],"type":"Point"}
}