{
  "type": "Feature",
  "properties": {
    "gn:admin1_code":"4.0",
    "gn:asciiname":"Weixingcun",
    "gn:country_code":"CN",
    "gn:dem":-1,
    "gn:feature_class":"P",
    "gn:feature_code":"PPL",
    "gn:name":"Weixingcun",
    "gn:population":0,
    "gn:timezone":"Asia/Shanghai",
    "iso:country":"CN",
    "name:zho_x_preferred":[
        "\u7ef4\u5174\u6751"
    ],
    "wof:name":"Weixingcun",
    "wof:placetype":"locality"
},
  "geometry": {"coordinates":[119.46648999999999,33.02148],"type":"Point"}
}