{
  "type": "Feature",
  "properties": {
    "gn:admin1_code":"24.0",
    "gn:asciiname":"Qianloudi",
    "gn:country_code":"CN",
    "gn:dem":798,
    "gn:feature_class":"P",
    "gn:feature_code":"PPL",
    "gn:name":"Qianloudi",
    "gn:population":0,
    "gn:timezone":"Asia/Shanghai",
    "iso:country":"CN",
    "name:zho_x_preferred":[
        "\u524d\u697c\u5e95"
    ],
    "wof:name":"Qianloudi",
    "wof:placetype":"locality"
},
  "geometry": {"coordinates":[110.79022999999999,36.41237],"type":"Point"}
}