{
  "type": "Feature",
  "properties": {
    "gn:admin1_code":"29.0",
    "gn:asciiname":"Benggeding",
    "gn:country_code":"CN",
    "gn:dem":2751,
    "gn:feature_class":"P",
    "gn:feature_code":"PPL",
    "gn:name":"Benggeding",
    "gn:population":0,
    "gn:timezone":"Asia/Shanghai",
    "iso:country":"CN",
    "name:zho_x_preferred":[
        "\u5d29\u5404\u4e01"
    ],
    "wof:name":"Benggeding",
    "wof:placetype":"locality"
},
  "geometry": {"coordinates":[100.074,27.9469],"type":"Point"}
}