{
  "type": "Feature",
  "properties": {
    "gn:admin1_code":"30.0",
    "gn:asciiname":"Pushangcun",
    "gn:country_code":"CN",
    "gn:dem":11,
    "gn:feature_class":"P",
    "gn:feature_code":"PPL",
    "gn:name":"Pushangcun",
    "gn:population":0,
    "gn:timezone":"Asia/Shanghai",
    "iso:country":"CN",
    "name:zho_x_preferred":[
        "\u57d4\u4e0a\u6751"
    ],
    "wof:name":"Pushangcun",
    "wof:placetype":"locality"
},
  "geometry": {"coordinates":[116.3639,23.55985],"type":"Point"}
}