{
  "type": "Feature",
  "properties": {
    "gn:admin1_code":"23.0",
    "gn:asciiname":"Zhangzixu",
    "gn:country_code":"CN",
    "gn:dem":4,
    "gn:feature_class":"P",
    "gn:feature_code":"PPL",
    "gn:name":"Zhangzixu",
    "gn:population":0,
    "gn:timezone":"Asia/Shanghai",
    "iso:country":"CN",
    "name:zho_x_preferred":[
        "Zhangzixu"
    ],
    "name:zho_x_variant":[
        "\u5f20\u5b57\u5729"
    ],
    "wof:name":"Zhangzixu",
    "wof:placetype":"locality"
},
  "geometry": {"coordinates":[121.08723000000001,31.03397],"type":"Point"}
}