{
  "type": "Feature",
  "properties": {
    "gn:admin1_code":"25",
    "gn:asciiname":"Qianzhuangke",
    "gn:country_code":"CN",
    "gn:dem":90,
    "gn:feature_class":"P",
    "gn:feature_code":"PPL",
    "gn:name":"Qianzhuangke",
    "gn:population":0,
    "gn:timezone":"Asia/Shanghai",
    "iso:country":"CN",
    "name:zho_x_preferred":[
        "\u524d\u5e84\u79d1"
    ],
    "wof:name":"Qianzhuangke",
    "wof:placetype":"locality"
},
  "geometry": {"coordinates":[116.42700000000001,36.0846],"type":"Point"}
}