{
  "type": "Feature",
  "properties": {
    "gn:admin1_code":"11",
    "gn:asciiname":"Shatangxiang",
    "gn:cc2":"CN",
    "gn:country_code":"CN",
    "gn:dem":148,
    "gn:feature_class":"P",
    "gn:feature_code":"PPL",
    "gn:name":"Shatangxiang",
    "gn:population":0,
    "gn:timezone":"Asia/Shanghai",
    "iso:country":"CN",
    "name:und_x_variant":[
        "Wenchangmiao",
        "Shatangxiang"
    ],
    "wof:name":"Shatangxiang",
    "wof:placetype":"locality"
},
  "geometry": {"coordinates":[112.31999999999999,27.47639],"type":"Point"}
}