{
  "type": "Feature",
  "properties": {
    "gn:admin1_code":"18",
    "gn:asciiname":"Xialadan",
    "gn:country_code":"CN",
    "gn:dem":1249,
    "gn:feature_class":"P",
    "gn:feature_code":"PPL",
    "gn:name":"Xialadan",
    "gn:population":0,
    "gn:timezone":"Asia/Shanghai",
    "iso:country":"CN",
    "name:zho_x_preferred":[
        "\u4e0b\u814a\u65e6"
    ],
    "wof:name":"Xialadan",
    "wof:placetype":"locality"
},
  "geometry": {"coordinates":[106.256,26.0375],"type":"Point"}
}