{
  "type": "Feature",
  "properties": {
    "gn:admin1_code":"24.0",
    "gn:asciiname":"Jiajianao",
    "gn:country_code":"CN",
    "gn:dem":965,
    "gn:feature_class":"P",
    "gn:feature_code":"PPL",
    "gn:name":"Jiajianao",
    "gn:population":0,
    "gn:timezone":"Asia/Shanghai",
    "iso:country":"CN",
    "name:zho_x_preferred":[
        "\u8d3e\u5bb6\u57b4"
    ],
    "wof:name":"Jiajianao",
    "wof:placetype":"locality"
},
  "geometry": {"coordinates":[113.50479,38.0547],"type":"Point"}
}