{
  "type": "Feature",
  "properties": {
    "gn:admin1_code":"12.0",
    "gn:asciiname":"Baiguoshubao",
    "gn:country_code":"CN",
    "gn:dem":720,
    "gn:feature_class":"P",
    "gn:feature_code":"PPL",
    "gn:name":"Baiguoshubao",
    "gn:population":0,
    "gn:timezone":"Asia/Shanghai",
    "iso:country":"CN",
    "name:zho_x_preferred":[
        "\u767d\u679c\u6811\u5305"
    ],
    "wof:name":"Baiguoshubao",
    "wof:placetype":"locality"
},
  "geometry": {"coordinates":[111.17019999999999,31.87933],"type":"Point"}
}