{
  "type": "Feature",
  "properties": {
    "gn:admin1_code":"12.0",
    "gn:asciiname":"Shangdongping",
    "gn:country_code":"CN",
    "gn:dem":867,
    "gn:feature_class":"P",
    "gn:feature_code":"PPL",
    "gn:name":"Shangdongping",
    "gn:population":0,
    "gn:timezone":"Asia/Shanghai",
    "iso:country":"CN",
    "name:zho_x_preferred":[
        "Shangdongping"
    ],
    "name:zho_x_variant":[
        "\u4e0a\u6d1e\u576a"
    ],
    "wof:name":"Shangdongping",
    "wof:placetype":"locality"
},
  "geometry": {"coordinates":[109.35639999999999,29.7264],"type":"Point"}
}