{
  "type": "Feature",
  "properties": {
    "gn:admin1_code":"29.0",
    "gn:asciiname":"Hemocun",
    "gn:country_code":"CN",
    "gn:dem":1894,
    "gn:feature_class":"P",
    "gn:feature_code":"PPL",
    "gn:name":"Hemocun",
    "gn:population":0,
    "gn:timezone":"Asia/Shanghai",
    "iso:country":"CN",
    "name:zho_x_preferred":[
        "\u548c\u6469\u6751"
    ],
    "wof:name":"Hemocun",
    "wof:placetype":"locality"
},
  "geometry": {"coordinates":[103.36499999999999,24.9235],"type":"Point"}
}