{
  "type": "Feature",
  "properties": {
    "gn:admin1_code":"32.0",
    "gn:asciiname":"Qingshanping",
    "gn:country_code":"CN",
    "gn:dem":2187,
    "gn:feature_class":"P",
    "gn:feature_code":"PPL",
    "gn:name":"Qingshanping",
    "gn:population":0,
    "gn:timezone":"Asia/Shanghai",
    "iso:country":"CN",
    "name:zho_x_preferred":[
        "\u9752\u5c71\u576a"
    ],
    "wof:name":"Qingshanping",
    "wof:placetype":"locality"
},
  "geometry": {"coordinates":[101.93745,27.46329],"type":"Point"}
}