{
  "type": "Feature",
  "properties": {
    "gn:admin1_code":"8.0",
    "gn:asciiname":"Sunxiutun",
    "gn:country_code":"CN",
    "gn:dem":128,
    "gn:feature_class":"P",
    "gn:feature_code":"PPL",
    "gn:name":"Sunxiutun",
    "gn:population":0,
    "gn:timezone":"Asia/Shanghai",
    "iso:country":"CN",
    "name:zho_x_preferred":[
        "\u5b59\u79c0\u5c6f"
    ],
    "wof:name":"Sunxiutun",
    "wof:placetype":"locality"
},
  "geometry": {"coordinates":[125.20389,45.52636],"type":"Point"}
}