{
  "type": "Feature",
  "properties": {
    "gn:admin1_code":"6.0",
    "gn:asciiname":"Dugusi",
    "gn:country_code":"CN",
    "gn:dem":2685,
    "gn:feature_class":"P",
    "gn:feature_code":"PPL",
    "gn:name":"Dugusi",
    "gn:population":0,
    "gn:timezone":"Asia/Shanghai",
    "iso:country":"CN",
    "name:und_x_variant":[
        "\u90fd\u53e4\u5bfa"
    ],
    "wof:name":"Dugusi",
    "wof:placetype":"locality"
},
  "geometry": {"coordinates":[102.35709,35.71575],"type":"Point"}
}