{
  "type": "Feature",
  "properties": {
    "gn:admin1_code":"10.0",
    "gn:asciiname":"Liuguantun",
    "gn:country_code":"CN",
    "gn:dem":18,
    "gn:feature_class":"P",
    "gn:feature_code":"PPL",
    "gn:name":"Liuguantun",
    "gn:population":0,
    "gn:timezone":"Asia/Shanghai",
    "iso:country":"CN",
    "name:zho_x_preferred":[
        "\u5218\u5b98\u5c6f"
    ],
    "wof:name":"Liuguantun",
    "wof:placetype":"locality"
},
  "geometry": {"coordinates":[116.255,38.0464],"type":"Point"}
}