{
  "type": "Feature",
  "properties": {
    "gn:admin1_code":"1.0",
    "gn:asciiname":"Yongjiazhen",
    "gn:cc2":"CN",
    "gn:country_code":"CN",
    "gn:dem":7,
    "gn:feature_class":"P",
    "gn:feature_code":"PPL",
    "gn:name":"Yongjiazhen",
    "gn:population":0,
    "gn:timezone":"Asia/Shanghai",
    "iso:country":"CN",
    "name:und_x_variant":[
        "Yung-chia-chen",
        "Yongjiazhen"
    ],
    "wof:name":"Yongjiazhen",
    "wof:placetype":"locality"
},
  "geometry": {"coordinates":[118.25,31.38333],"type":"Point"}
}