{
  "type": "Feature",
  "properties": {
    "gn:admin1_code":"32.0",
    "gn:asciiname":"Qizhi",
    "gn:country_code":"CN",
    "gn:dem":2186,
    "gn:feature_class":"P",
    "gn:feature_code":"PPL",
    "gn:name":"Qizhi",
    "gn:population":0,
    "gn:timezone":"Asia/Shanghai",
    "iso:country":"CN",
    "name:zho_x_preferred":[
        "\u9f50\u652f"
    ],
    "wof:name":"Qizhi",
    "wof:placetype":"locality"
},
  "geometry": {"coordinates":[101.861,31.0126],"type":"Point"}
}