{
  "type": "Feature",
  "properties": {
    "gn:admin1_code":"19.0",
    "gn:asciiname":"Xiaochang Wangzhaicun",
    "gn:country_code":"CN",
    "gn:dem":88,
    "gn:feature_class":"P",
    "gn:feature_code":"PPL",
    "gn:name":"Xiaochang Wangzhaicun",
    "gn:population":0,
    "gn:timezone":"Asia/Shanghai",
    "iso:country":"CN",
    "name:zho_x_preferred":[
        "\u5c0f\u5e38\u738b\u5be8\u6751"
    ],
    "wof:name":"Xiaochang Wangzhaicun",
    "wof:placetype":"locality"
},
  "geometry": {"coordinates":[123.654,41.6978],"type":"Point"}
}