{
  "type": "Feature",
  "properties": {
    "gn:admin1_code":"14.0",
    "gn:asciiname":"Along",
    "gn:country_code":"CN",
    "gn:dem":4577,
    "gn:feature_class":"P",
    "gn:feature_code":"PPL",
    "gn:name":"Along",
    "gn:population":0,
    "gn:timezone":"Asia/Urumqi",
    "iso:country":"CN",
    "name:zho_x_preferred":[
        "\u963f\u62e2"
    ],
    "wof:name":"Along",
    "wof:placetype":"locality"
},
  "geometry": {"coordinates":[95.40219999999999,30.64814],"type":"Point"}
}