{
  "type": "Feature",
  "properties": {
    "gn:admin1_code":"19.0",
    "gn:asciiname":"Wukuaishicun",
    "gn:country_code":"CN",
    "gn:dem":39,
    "gn:feature_class":"P",
    "gn:feature_code":"PPL",
    "gn:name":"Wukuaishicun",
    "gn:population":0,
    "gn:timezone":"Asia/Shanghai",
    "iso:country":"CN",
    "name:zho_x_preferred":[
        "\u4e94\u5757\u77f3\u6751"
    ],
    "wof:name":"Wukuaishicun",
    "wof:placetype":"locality"
},
  "geometry": {"coordinates":[123.31634,39.80854],"type":"Point"}
}