{
  "type": "Feature",
  "properties": {
    "gn:admin1_code":"29.0",
    "gn:asciiname":"Luzi",
    "gn:country_code":"CN",
    "gn:dem":3170,
    "gn:feature_class":"P",
    "gn:feature_code":"PPL",
    "gn:name":"Luzi",
    "gn:population":0,
    "gn:timezone":"Asia/Shanghai",
    "iso:country":"CN",
    "name:zho_x_preferred":[
        "\u9e7f\u5b50"
    ],
    "wof:name":"Luzi",
    "wof:placetype":"locality"
},
  "geometry": {"coordinates":[100.14,26.7401],"type":"Point"}
}