{
  "type": "Feature",
  "properties": {
    "gn:admin1_code":"24.0",
    "gn:asciiname":"Shanshuiguduo",
    "gn:country_code":"CN",
    "gn:dem":1091,
    "gn:feature_class":"P",
    "gn:feature_code":"PPL",
    "gn:name":"Shanshuiguduo",
    "gn:population":0,
    "gn:timezone":"Asia/Shanghai",
    "iso:country":"CN",
    "name:und_x_variant":[
        "\u5c71\u6c34\u53e4\u6735"
    ],
    "wof:name":"Shanshuiguduo",
    "wof:placetype":"locality"
},
  "geometry": {"coordinates":[111.40955,35.26983],"type":"Point"}
}