{
  "type": "Feature",
  "properties": {
    "gn:admin1_code":"26.0",
    "gn:asciiname":"Shangfanjiagoucun",
    "gn:country_code":"CN",
    "gn:dem":1129,
    "gn:feature_class":"P",
    "gn:feature_code":"PPL",
    "gn:name":"Shangfanjiagoucun",
    "gn:population":0,
    "gn:timezone":"Asia/Shanghai",
    "iso:country":"CN",
    "name:zho_x_preferred":[
        "\u4e0a\u6a0a\u5bb6\u6c9f\u6751"
    ],
    "wof:name":"Shangfanjiagoucun",
    "wof:placetype":"locality"
},
  "geometry": {"coordinates":[109.66105,36.97686],"type":"Point"}
}