{
  "type": "Feature",
  "properties": {
    "gn:admin1_code":"25.0",
    "gn:asciiname":"Huangchengyang",
    "gn:country_code":"CN",
    "gn:dem":195,
    "gn:feature_class":"P",
    "gn:feature_code":"PPL",
    "gn:name":"Huangchengyang",
    "gn:population":0,
    "gn:timezone":"Asia/Shanghai",
    "iso:country":"CN",
    "name:zho_x_preferred":[
        "\u9ec4\u57ce\u9633"
    ],
    "wof:name":"Huangchengyang",
    "wof:placetype":"locality"
},
  "geometry": {"coordinates":[120.70519,37.47305],"type":"Point"}
}