{
  "type": "Feature",
  "properties": {
    "gn:admin1_code":"16.0",
    "gn:asciiname":"Congguang",
    "gn:country_code":"CN",
    "gn:dem":119,
    "gn:feature_class":"P",
    "gn:feature_code":"PPL",
    "gn:name":"Congguang",
    "gn:population":0,
    "gn:timezone":"Asia/Shanghai",
    "iso:country":"CN",
    "name:zho_x_preferred":[
        "\u4ece\u5e7f"
    ],
    "wof:name":"Congguang",
    "wof:placetype":"locality"
},
  "geometry": {"coordinates":[108.34999999999999,23.1963],"type":"Point"}
}