{
  "type": "Feature",
  "properties": {
    "gn:admin1_code":"26.0",
    "gn:asciiname":"Nianziping",
    "gn:country_code":"CN",
    "gn:dem":1717,
    "gn:feature_class":"P",
    "gn:feature_code":"PPL",
    "gn:name":"Nianziping",
    "gn:population":0,
    "gn:timezone":"Asia/Shanghai",
    "iso:country":"CN",
    "name:zho_x_preferred":[
        "\u78be\u5b50\u576a"
    ],
    "wof:name":"Nianziping",
    "wof:placetype":"locality"
},
  "geometry": {"coordinates":[109.16464000000001,33.82994],"type":"Point"}
}