{
  "type": "Feature",
  "properties": {
    "gn:admin1_code":"2.0",
    "gn:asciiname":"Yushanling",
    "gn:country_code":"CN",
    "gn:dem":304,
    "gn:feature_class":"P",
    "gn:feature_code":"PPL",
    "gn:name":"Yushanling",
    "gn:population":0,
    "gn:timezone":"Asia/Shanghai",
    "iso:country":"CN",
    "name:zho_x_preferred":[
        "\u9c7c\u5c71\u5cad"
    ],
    "wof:name":"Yushanling",
    "wof:placetype":"locality"
},
  "geometry": {"coordinates":[120.19606,28.02618],"type":"Point"}
}