{
  "type": "Feature",
  "properties": {
    "gn:admin1_code":"25",
    "gn:asciiname":"Xiangshanqian",
    "gn:country_code":"CN",
    "gn:dem":25,
    "gn:feature_class":"P",
    "gn:feature_code":"PPL",
    "gn:name":"Xiangshanqian",
    "gn:population":0,
    "gn:timezone":"Asia/Shanghai",
    "iso:country":"CN",
    "name:zho_x_preferred":[
        "\u9999\u5c71\u524d"
    ],
    "wof:name":"Xiangshanqian",
    "wof:placetype":"locality"
},
  "geometry": {"coordinates":[122.51278000000001,37.30111],"type":"Point"}
}