{
  "type": "Feature",
  "properties": {
    "gn:admin1_code":"14.0",
    "gn:asciiname":"Yueduo",
    "gn:country_code":"CN",
    "gn:dem":4033,
    "gn:feature_class":"P",
    "gn:feature_code":"PPL",
    "gn:name":"Yueduo",
    "gn:population":0,
    "gn:timezone":"Asia/Urumqi",
    "iso:country":"CN",
    "name:zho_x_preferred":[
        "\u7ea6\u591a"
    ],
    "wof:name":"Yueduo",
    "wof:placetype":"locality"
},
  "geometry": {"coordinates":[97.27195,30.69486],"type":"Point"}
}