{
  "type": "Feature",
  "properties": {
    "gn:admin1_code":"16.0",
    "gn:asciiname":"Dawenwu",
    "gn:country_code":"CN",
    "gn:dem":24,
    "gn:feature_class":"P",
    "gn:feature_code":"PPL",
    "gn:name":"Dawenwu",
    "gn:population":0,
    "gn:timezone":"Asia/Shanghai",
    "iso:country":"CN",
    "name:zho_x_preferred":[
        "\u5927\u6587\u5c4b"
    ],
    "wof:name":"Dawenwu",
    "wof:placetype":"locality"
},
  "geometry": {"coordinates":[108.92400000000001,21.7241],"type":"Point"}
}