{
  "type": "Feature",
  "properties": {
    "gn:admin1_code":"26.0",
    "gn:asciiname":"Zaobutan",
    "gn:country_code":"CN",
    "gn:dem":887,
    "gn:feature_class":"P",
    "gn:feature_code":"PPL",
    "gn:name":"Zaobutan",
    "gn:population":0,
    "gn:timezone":"Asia/Shanghai",
    "iso:country":"CN",
    "name:zho_x_preferred":[
        "\u67a3\u535c\u6ee9"
    ],
    "wof:name":"Zaobutan",
    "wof:placetype":"locality"
},
  "geometry": {"coordinates":[110.23344,36.73813],"type":"Point"}
}