{
  "type": "Feature",
  "properties": {
    "gn:admin1_code":"32.0",
    "gn:asciiname":"Zhaoping",
    "gn:country_code":"CN",
    "gn:dem":886,
    "gn:feature_class":"P",
    "gn:feature_code":"PPL",
    "gn:name":"Zhaoping",
    "gn:population":0,
    "gn:timezone":"Asia/Shanghai",
    "iso:country":"CN",
    "name:zho_x_preferred":[
        "\u8d75\u576a"
    ],
    "wof:name":"Zhaoping",
    "wof:placetype":"locality"
},
  "geometry": {"coordinates":[103.176,29.7163],"type":"Point"}
}