{
  "type": "Feature",
  "properties": {
    "gn:admin1_code":"11.0",
    "gn:asciiname":"Qiaotou",
    "gn:country_code":"CN",
    "gn:dem":313,
    "gn:feature_class":"P",
    "gn:feature_code":"PPL",
    "gn:name":"Qiaotou",
    "gn:population":0,
    "gn:timezone":"Asia/Shanghai",
    "iso:country":"CN",
    "name:zho_x_preferred":[
        "\u6865\u5934"
    ],
    "wof:name":"Qiaotou",
    "wof:placetype":"locality"
},
  "geometry": {"coordinates":[110.21177,26.58732],"type":"Point"}
}