{
  "type": "Feature",
  "properties": {
    "gn:admin1_code":"13",
    "gn:asciiname":"Chahanbile",
    "gn:country_code":"CN",
    "gn:dem":2480,
    "gn:feature_class":"P",
    "gn:feature_code":"PPL",
    "gn:name":"Chahanbile",
    "gn:population":0,
    "gn:timezone":"Asia/Urumqi",
    "iso:country":"CN",
    "name:und_x_variant":[
        "\u67e5\u6c57\u6bd4\u52d2"
    ],
    "wof:name":"Chahanbile",
    "wof:placetype":"locality"
},
  "geometry": {"coordinates":[84.72589000000001,42.64381],"type":"Point"}
}