{
  "type": "Feature",
  "properties": {
    "gn:admin1_code":"12.0",
    "gn:asciiname":"Longtanzui",
    "gn:country_code":"CN",
    "gn:dem":22,
    "gn:feature_class":"P",
    "gn:feature_code":"PPL",
    "gn:name":"Longtanzui",
    "gn:population":0,
    "gn:timezone":"Asia/Shanghai",
    "iso:country":"CN",
    "name:zho_x_preferred":[
        "\u9f99\u6f6d\u5480"
    ],
    "wof:name":"Longtanzui",
    "wof:placetype":"locality"
},
  "geometry": {"coordinates":[113.51214,30.84739],"type":"Point"}
}