{
  "type": "Feature",
  "properties": {
    "gn:admin1_code":"19.0",
    "gn:asciiname":"Hongyazui",
    "gn:country_code":"CN",
    "gn:dem":59,
    "gn:feature_class":"P",
    "gn:feature_code":"PPL",
    "gn:name":"Hongyazui",
    "gn:population":0,
    "gn:timezone":"Asia/Shanghai",
    "iso:country":"CN",
    "name:zho_x_preferred":[
        "\u7ea2\u5d16\u5480"
    ],
    "wof:name":"Hongyazui",
    "wof:placetype":"locality"
},
  "geometry": {"coordinates":[123.73114,42.31956],"type":"Point"}
}