{
  "type": "Feature",
  "properties": {
    "gn:admin1_code":"4.0",
    "gn:asciiname":"Yujiazhuang",
    "gn:country_code":"CN",
    "gn:dem":7,
    "gn:feature_class":"P",
    "gn:feature_code":"PPL",
    "gn:name":"Yujiazhuang",
    "gn:population":0,
    "gn:timezone":"Asia/Shanghai",
    "iso:country":"CN",
    "name:zho_x_preferred":[
        "Yujiazhuang"
    ],
    "name:zho_x_variant":[
        "\u4e8e\u5bb6\u5e84"
    ],
    "wof:name":"Yujiazhuang",
    "wof:placetype":"locality"
},
  "geometry": {"coordinates":[119.19389,33.05224],"type":"Point"}
}