{
  "type": "Feature",
  "properties": {
    "gn:admin1_code":"30",
    "gn:asciiname":"Nanjing",
    "gn:country_code":"CN",
    "gn:dem":10,
    "gn:feature_class":"P",
    "gn:feature_code":"PPLA4",
    "gn:name":"Nanjing",
    "gn:population":0,
    "gn:timezone":"Asia/Shanghai",
    "iso:country":"CN",
    "name:rus_x_preferred":[
        "\u041d\u0430\u043d\u043a\u0438\u043d"
    ],
    "name:und_x_variant":[
        "Nanjing Zhen",
        "\u5357\u5f84\u9547"
    ],
    "name:zho_x_preferred":[
        "\u5357\u5f84"
    ],
    "wof:name":"Nanjing",
    "wof:placetype":"locality"
},
  "geometry": {"coordinates":[116.29713,23.33989],"type":"Point"}
}