{
  "type": "Feature",
  "properties": {
    "gn:admin1_code":"29.0",
    "gn:asciiname":"Nacha",
    "gn:country_code":"CN",
    "gn:dem":1953,
    "gn:feature_class":"P",
    "gn:feature_code":"PPL",
    "gn:name":"Nacha",
    "gn:population":0,
    "gn:timezone":"Asia/Shanghai",
    "iso:country":"CN",
    "name:und_x_variant":[
        "\u7eb3\u5c94"
    ],
    "wof:name":"Nacha",
    "wof:placetype":"locality"
},
  "geometry": {"coordinates":[102.61194999999999,25.72941],"type":"Point"}
}