{
  "type": "Feature",
  "properties": {
    "gn:admin1_code":"8.0",
    "gn:asciiname":"Yingchuncun",
    "gn:country_code":"CN",
    "gn:dem":174,
    "gn:feature_class":"P",
    "gn:feature_code":"PPL",
    "gn:name":"Yingchuncun",
    "gn:population":0,
    "gn:timezone":"Asia/Shanghai",
    "iso:country":"CN",
    "name:zho_x_preferred":[
        "\u8fce\u6625\u6751"
    ],
    "wof:name":"Yingchuncun",
    "wof:placetype":"locality"
},
  "geometry": {"coordinates":[126.96871000000002,46.35473],"type":"Point"}
}