{
  "type": "Feature",
  "properties": {
    "gn:admin1_code":"4.0",
    "gn:asciiname":"Simenzhacun",
    "gn:country_code":"CN",
    "gn:dem":13,
    "gn:feature_class":"P",
    "gn:feature_code":"PPL",
    "gn:name":"Simenzhacun",
    "gn:population":0,
    "gn:timezone":"Asia/Shanghai",
    "iso:country":"CN",
    "name:zho_x_preferred":[
        "\u56db\u95e8\u95f8\u6751"
    ],
    "wof:name":"Simenzhacun",
    "wof:placetype":"locality"
},
  "geometry": {"coordinates":[118.83392000000001,33.67688],"type":"Point"}
}