{
  "type": "Feature",
  "properties": {
    "gn:admin1_code":"29.0",
    "gn:asciiname":"Lingleng",
    "gn:country_code":"CN",
    "gn:dem":1465,
    "gn:feature_class":"P",
    "gn:feature_code":"PPL",
    "gn:name":"Lingleng",
    "gn:population":0,
    "gn:timezone":"Asia/Shanghai",
    "iso:country":"CN",
    "name:zho_x_preferred":[
        "\u53e6\u695e"
    ],
    "wof:name":"Lingleng",
    "wof:placetype":"locality"
},
  "geometry": {"coordinates":[99.2616,23.3963],"type":"Point"}
}