{
  "type": "Feature",
  "properties": {
    "gn:admin1_code":"32.0",
    "gn:asciiname":"Yangchagou",
    "gn:country_code":"CN",
    "gn:dem":2118,
    "gn:feature_class":"P",
    "gn:feature_code":"PPL",
    "gn:name":"Yangchagou",
    "gn:population":0,
    "gn:timezone":"Asia/Shanghai",
    "iso:country":"CN",
    "name:zho_x_preferred":[
        "\u7f8a\u53c9\u6c9f"
    ],
    "wof:name":"Yangchagou",
    "wof:placetype":"locality"
},
  "geometry": {"coordinates":[102.23099999999999,28.4477],"type":"Point"}
}