{
  "type": "Feature",
  "properties": {
    "gn:admin1_code":"9.0",
    "gn:asciiname":"Zhangshanzhai",
    "gn:country_code":"CN",
    "gn:dem":56,
    "gn:feature_class":"P",
    "gn:feature_code":"PPL",
    "gn:name":"Zhangshanzhai",
    "gn:population":0,
    "gn:timezone":"Asia/Shanghai",
    "iso:country":"CN",
    "name:zho_x_preferred":[
        "\u5f20\u5c71\u5be8"
    ],
    "wof:name":"Zhangshanzhai",
    "wof:placetype":"locality"
},
  "geometry": {"coordinates":[114.7974,34.24124],"type":"Point"}
}