{
  "type": "Feature",
  "properties": {
    "gn:admin1_code":"03",
    "gn:asciiname":"Chishui",
    "gn:country_code":"CN",
    "gn:dem":148,
    "gn:feature_class":"P",
    "gn:feature_code":"PPLA4",
    "gn:name":"Chishui",
    "gn:population":0,
    "gn:timezone":"Asia/Shanghai",
    "iso:country":"CN",
    "name:deu_x_preferred":[
        "Chishui"
    ],
    "name:nor_x_preferred":[
        "Chishui"
    ],
    "name:pam_x_preferred":[
        "Chishui"
    ],
    "name:und_x_variant":[
        "Ch\u2019ih-shui",
        "Chishui",
        "\u8d64\u6c34",
        "Chishui Zhen",
        "\u8d64\u6c34\u9547"
    ],
    "wof:name":"Chishui",
    "wof:placetype":"locality"
},
  "geometry": {"coordinates":[116.3629,26.70126],"type":"Point"}
}