{
  "type": "Feature",
  "properties": {
    "gn:admin1_code":"20.0",
    "gn:asciiname":"Dawo Simen",
    "gn:country_code":"CN",
    "gn:dem":357,
    "gn:feature_class":"P",
    "gn:feature_code":"PPL",
    "gn:name":"Dawo Simen",
    "gn:population":0,
    "gn:timezone":"Asia/Shanghai",
    "iso:country":"CN",
    "name:zho_x_preferred":[
        "\u5927\u65a1\u65af\u95e8"
    ],
    "wof:name":"Dawo Simen",
    "wof:placetype":"locality"
},
  "geometry": {"coordinates":[124.41104,49.30661],"type":"Point"}
}