{
  "type": "Feature",
  "properties": {
    "gn:admin1_code":"4.0",
    "gn:asciiname":"Donggaoweicun",
    "gn:country_code":"CN",
    "gn:dem":1,
    "gn:feature_class":"P",
    "gn:feature_code":"PPL",
    "gn:name":"Donggaoweicun",
    "gn:population":0,
    "gn:timezone":"Asia/Shanghai",
    "iso:country":"CN",
    "name:zho_x_preferred":[
        "\u4e1c\u9ad8\u9b4f\u6751"
    ],
    "wof:name":"Donggaoweicun",
    "wof:placetype":"locality"
},
  "geometry": {"coordinates":[119.93671000000001,32.85828],"type":"Point"}
}