{
  "type": "Feature",
  "properties": {
    "gn:admin1_code":"16",
    "gn:asciiname":"Guzuotang",
    "gn:country_code":"CN",
    "gn:dem":118,
    "gn:feature_class":"P",
    "gn:feature_code":"PPL",
    "gn:name":"Guzuotang",
    "gn:population":0,
    "gn:timezone":"Asia/Shanghai",
    "iso:country":"CN",
    "name:zho_x_preferred":[
        "\u53e4\u5ea7\u5858"
    ],
    "wof:name":"Guzuotang",
    "wof:placetype":"locality"
},
  "geometry": {"coordinates":[110.51000000000001,24.8192],"type":"Point"}
}