{
  "type": "Feature",
  "properties": {
    "gn:admin1_code":"18",
    "gn:asciiname":"Xiaoxi",
    "gn:country_code":"CN",
    "gn:dem":725,
    "gn:feature_class":"P",
    "gn:feature_code":"PPL",
    "gn:name":"Xiaoxi",
    "gn:population":0,
    "gn:timezone":"Asia/Shanghai",
    "iso:country":"CN",
    "name:zho_x_preferred":[
        "\u5c0f\u6eaa"
    ],
    "name:zho_x_variant":[
        "\u5c0f\u6eaa\u9547"
    ],
    "wof:name":"Xiaoxi",
    "wof:placetype":"locality"
},
  "geometry": {"coordinates":[108.06399999999999,27.3937],"type":"Point"}
}