{
  "type": "Feature",
  "properties": {
    "gn:admin1_code":"32.0",
    "gn:asciiname":"Louzijie",
    "gn:country_code":"CN",
    "gn:dem":846,
    "gn:feature_class":"P",
    "gn:feature_code":"PPL",
    "gn:name":"Louzijie",
    "gn:population":0,
    "gn:timezone":"Asia/Shanghai",
    "iso:country":"CN",
    "name:zho_x_preferred":[
        "\u697c\u5b50\u8857"
    ],
    "wof:name":"Louzijie",
    "wof:placetype":"locality"
},
  "geometry": {"coordinates":[104.98260000000001,32.51913],"type":"Point"}
}