{
  "type": "Feature",
  "properties": {
    "gn:admin1_code":"14.0",
    "gn:asciiname":"Maishacun",
    "gn:country_code":"CN",
    "gn:dem":3964,
    "gn:feature_class":"P",
    "gn:feature_code":"PPL",
    "gn:name":"Maishacun",
    "gn:population":0,
    "gn:timezone":"Asia/Urumqi",
    "iso:country":"CN",
    "name:zho_x_preferred":[
        "\u9ea6\u838e\u6751"
    ],
    "wof:name":"Maishacun",
    "wof:placetype":"locality"
},
  "geometry": {"coordinates":[92.32619,28.41404],"type":"Point"}
}