{
  "type": "Feature",
  "properties": {
    "gn:admin1_code":"5.0",
    "gn:asciiname":"Fangniu Wobucun",
    "gn:country_code":"CN",
    "gn:dem":196,
    "gn:feature_class":"P",
    "gn:feature_code":"PPL",
    "gn:name":"Fangniu Wobucun",
    "gn:population":0,
    "gn:timezone":"Asia/Shanghai",
    "iso:country":"CN",
    "name:zho_x_preferred":[
        "\u653e\u725b\u7a9d\u5821\u6751"
    ],
    "wof:name":"Fangniu Wobucun",
    "wof:placetype":"locality"
},
  "geometry": {"coordinates":[125.09672999999999,44.04548],"type":"Point"}
}