{
  "type": "Feature",
  "properties": {
    "gn:admin1_code":"9.0",
    "gn:asciiname":"Houniugang",
    "gn:country_code":"CN",
    "gn:dem":88,
    "gn:feature_class":"P",
    "gn:feature_code":"PPL",
    "gn:name":"Houniugang",
    "gn:population":0,
    "gn:timezone":"Asia/Shanghai",
    "iso:country":"CN",
    "name:zho_x_preferred":[
        "\u540e\u725b\u5c97"
    ],
    "wof:name":"Houniugang",
    "wof:placetype":"locality"
},
  "geometry": {"coordinates":[113.8156,34.82292],"type":"Point"}
}