{
  "type": "Feature",
  "properties": {
    "gn:admin1_code":"30.0",
    "gn:asciiname":"Yangshuikeng",
    "gn:country_code":"CN",
    "gn:dem":616,
    "gn:feature_class":"P",
    "gn:feature_code":"PPL",
    "gn:name":"Yangshuikeng",
    "gn:population":0,
    "gn:timezone":"Asia/Shanghai",
    "iso:country":"CN",
    "name:zho_x_preferred":[
        "\u6d0b\u6c34\u5751"
    ],
    "wof:name":"Yangshuikeng",
    "wof:placetype":"locality"
},
  "geometry": {"coordinates":[112.61973,24.11761],"type":"Point"}
}