{
  "type": "Feature",
  "properties": {
    "gn:admin1_code":"1.0",
    "gn:asciiname":"Caomiao Xiaoqu",
    "gn:country_code":"CN",
    "gn:dem":20,
    "gn:feature_class":"P",
    "gn:feature_code":"PPL",
    "gn:name":"Caomiao Xiaoqu",
    "gn:population":0,
    "gn:timezone":"Asia/Shanghai",
    "iso:country":"CN",
    "name:zho_x_preferred":[
        "\u66f9\u82d7\u5c0f\u533a"
    ],
    "wof:name":"Caomiao Xiaoqu",
    "wof:placetype":"locality"
},
  "geometry": {"coordinates":[117.92108,33.4989],"type":"Point"}
}