{
  "type": "Feature",
  "properties": {
    "gn:admin1_code":"2.0",
    "gn:asciiname":"Sanshiliujie",
    "gn:country_code":"CN",
    "gn:dem":18,
    "gn:feature_class":"P",
    "gn:feature_code":"PPL",
    "gn:name":"Sanshiliujie",
    "gn:population":0,
    "gn:timezone":"Asia/Shanghai",
    "iso:country":"CN",
    "name:zho_x_preferred":[
        "\u4e09\u5341\u516d\u8857"
    ],
    "wof:name":"Sanshiliujie",
    "wof:placetype":"locality"
},
  "geometry": {"coordinates":[120.30998,27.46244],"type":"Point"}
}