{
  "type": "Feature",
  "properties": {
    "gn:admin1_code":"1.0",
    "gn:asciiname":"Nanwancun",
    "gn:country_code":"CN",
    "gn:dem":203,
    "gn:feature_class":"P",
    "gn:feature_code":"PPL",
    "gn:name":"Nanwancun",
    "gn:population":0,
    "gn:timezone":"Asia/Shanghai",
    "iso:country":"CN",
    "name:und_x_variant":[
        "Nanwan"
    ],
    "name:zho_x_preferred":[
        "\u5357\u6e7e\u6751"
    ],
    "wof:name":"Nanwancun",
    "wof:placetype":"locality"
},
  "geometry": {"coordinates":[115.66534,31.53128],"type":"Point"}
}