{
  "type": "Feature",
  "properties": {
    "gn:admin1_code":"30.0",
    "gn:asciiname":"Zaohe Shicun",
    "gn:country_code":"CN",
    "gn:dem":4,
    "gn:feature_class":"P",
    "gn:feature_code":"PPL",
    "gn:name":"Zaohe Shicun",
    "gn:population":0,
    "gn:timezone":"Asia/Shanghai",
    "iso:country":"CN",
    "name:zho_x_preferred":[
        "\u65e9\u79be\u77f3\u6751"
    ],
    "wof:name":"Zaohe Shicun",
    "wof:placetype":"locality"
},
  "geometry": {"coordinates":[112.38925999999999,21.86433],"type":"Point"}
}