{
  "type": "Feature",
  "properties": {
    "gn:admin1_code":"19",
    "gn:asciiname":"Hatanggou",
    "gn:country_code":"CN",
    "gn:dem":633,
    "gn:feature_class":"P",
    "gn:feature_code":"PPL",
    "gn:name":"Hatanggou",
    "gn:population":0,
    "gn:timezone":"Asia/Shanghai",
    "iso:country":"CN",
    "name:zho_x_preferred":[
        "\u54c8\u5858\u6c9f"
    ],
    "wof:name":"Hatanggou",
    "wof:placetype":"locality"
},
  "geometry": {"coordinates":[119.46881999999999,41.8785],"type":"Point"}
}