{
  "type": "Feature",
  "properties": {
    "gn:admin1_code":"25",
    "gn:asciiname":"Chouzhuang",
    "gn:country_code":"CN",
    "gn:dem":50,
    "gn:feature_class":"P",
    "gn:feature_code":"PPL",
    "gn:name":"Chouzhuang",
    "gn:population":0,
    "gn:timezone":"Asia/Shanghai",
    "iso:country":"CN",
    "name:zho_x_preferred":[
        "\u4ec7\u5e84"
    ],
    "wof:name":"Chouzhuang",
    "wof:placetype":"locality"
},
  "geometry": {"coordinates":[115.74231,35.32547],"type":"Point"}
}