{
  "type": "Feature",
  "properties": {
    "gn:admin1_code":"2.0",
    "gn:asciiname":"Shanhoulu",
    "gn:country_code":"CN",
    "gn:dem":7,
    "gn:feature_class":"P",
    "gn:feature_code":"PPL",
    "gn:name":"Shanhoulu",
    "gn:population":0,
    "gn:timezone":"Asia/Shanghai",
    "iso:country":"CN",
    "name:und_x_variant":[
        "\u5c71\u540e\u8def"
    ],
    "wof:name":"Shanhoulu",
    "wof:placetype":"locality"
},
  "geometry": {"coordinates":[120.14165,30.41172000000001],"type":"Point"}
}