{
  "type": "Feature",
  "properties": {
    "gn:admin1_code":"5.0",
    "gn:asciiname":"Houshiyang",
    "gn:country_code":"CN",
    "gn:dem":146,
    "gn:feature_class":"P",
    "gn:feature_code":"PPL",
    "gn:name":"Houshiyang",
    "gn:population":0,
    "gn:timezone":"Asia/Shanghai",
    "iso:country":"CN",
    "name:zho_x_preferred":[
        "\u540e\u77f3\u7f8a"
    ],
    "wof:name":"Houshiyang",
    "wof:placetype":"locality"
},
  "geometry": {"coordinates":[126.34546,45.15801],"type":"Point"}
}