{
  "type": "Feature",
  "properties": {
    "gn:admin1_code":"1.0",
    "gn:asciiname":"Oumiaocun",
    "gn:country_code":"CN",
    "gn:dem":38,
    "gn:feature_class":"P",
    "gn:feature_code":"PPL",
    "gn:name":"Oumiaocun",
    "gn:population":0,
    "gn:timezone":"Asia/Shanghai",
    "iso:country":"CN",
    "name:und_x_variant":[
        "Oumiao"
    ],
    "name:zho_x_preferred":[
        "\u6b27\u5e99\u6751"
    ],
    "wof:name":"Oumiaocun",
    "wof:placetype":"locality"
},
  "geometry": {"coordinates":[116.54617,34.10543],"type":"Point"}
}