{
  "type": "Feature",
  "properties": {
    "gn:admin1_code":"1.0",
    "gn:asciiname":"Xulitong",
    "gn:country_code":"CN",
    "gn:dem":7,
    "gn:feature_class":"P",
    "gn:feature_code":"PPL",
    "gn:name":"Xulitong",
    "gn:population":0,
    "gn:timezone":"Asia/Shanghai",
    "iso:country":"CN",
    "name:zho_x_preferred":[
        "\u5729\u91cc\u540c"
    ],
    "wof:name":"Xulitong",
    "wof:placetype":"locality"
},
  "geometry": {"coordinates":[118.0547,31.34788],"type":"Point"}
}