{
  "type": "Feature",
  "properties": {
    "gn:admin1_code":"8.0",
    "gn:asciiname":"Dongfuyou",
    "gn:country_code":"CN",
    "gn:dem":163,
    "gn:feature_class":"P",
    "gn:feature_code":"PPL",
    "gn:name":"Dongfuyou",
    "gn:population":0,
    "gn:timezone":"Asia/Shanghai",
    "iso:country":"CN",
    "name:zho_x_preferred":[
        "\u4e1c\u5bcc\u6709"
    ],
    "wof:name":"Dongfuyou",
    "wof:placetype":"locality"
},
  "geometry": {"coordinates":[123.47578,47.6882],"type":"Point"}
}