{
  "type": "Feature",
  "properties": {
    "gn:admin1_code":"29.0",
    "gn:asciiname":"Mulianhuashu",
    "gn:country_code":"CN",
    "gn:dem":1916,
    "gn:feature_class":"P",
    "gn:feature_code":"PPL",
    "gn:name":"Mulianhuashu",
    "gn:population":0,
    "gn:timezone":"Asia/Shanghai",
    "iso:country":"CN",
    "name:zho_x_preferred":[
        "\u6728\u83b2\u82b1\u6811"
    ],
    "wof:name":"Mulianhuashu",
    "wof:placetype":"locality"
},
  "geometry": {"coordinates":[98.5022,24.9391],"type":"Point"}
}