{
  "type": "Feature",
  "properties": {
    "gn:admin1_code":"4.0",
    "gn:asciiname":"Dibei",
    "gn:country_code":"CN",
    "gn:dem":3,
    "gn:feature_class":"P",
    "gn:feature_code":"PPL",
    "gn:name":"Dibei",
    "gn:population":0,
    "gn:timezone":"Asia/Shanghai",
    "iso:country":"CN",
    "name:zho_x_preferred":[
        "Dibei"
    ],
    "name:zho_x_variant":[
        "\u5824\u5317"
    ],
    "wof:name":"Dibei",
    "wof:placetype":"locality"
},
  "geometry": {"coordinates":[121.09829999999999,32.23079],"type":"Point"}
}