{
  "type": "Feature",
  "properties": {
    "gn:admin1_code":"14.0",
    "gn:asciiname":"Numa",
    "gn:country_code":"CN",
    "gn:dem":4529,
    "gn:feature_class":"P",
    "gn:feature_code":"PPL",
    "gn:name":"Numa",
    "gn:population":0,
    "gn:timezone":"Asia/Urumqi",
    "iso:country":"CN",
    "name:zho_x_preferred":[
        "\u6012\u8682"
    ],
    "wof:name":"Numa",
    "wof:placetype":"locality"
},
  "geometry": {"coordinates":[92.06285,31.42174],"type":"Point"}
}