{
  "type": "Feature",
  "properties": {
    "gn:admin1_code":"19.0",
    "gn:asciiname":"Dashuanggangzicun",
    "gn:country_code":"CN",
    "gn:dem":37,
    "gn:feature_class":"P",
    "gn:feature_code":"PPL",
    "gn:name":"Dashuanggangzicun",
    "gn:population":0,
    "gn:timezone":"Asia/Shanghai",
    "iso:country":"CN",
    "name:zho_x_preferred":[
        "\u5927\u53cc\u5c97\u5b50\u6751"
    ],
    "wof:name":"Dashuanggangzicun",
    "wof:placetype":"locality"
},
  "geometry": {"coordinates":[122.376,41.9161],"type":"Point"}
}