{
  "type": "Feature",
  "properties": {
    "gn:admin1_code":"10.0",
    "gn:asciiname":"Xisizhuang",
    "gn:cc2":"CN",
    "gn:country_code":"CN",
    "gn:dem":349,
    "gn:feature_class":"P",
    "gn:feature_code":"PPL",
    "gn:name":"Xisizhuang",
    "gn:population":0,
    "gn:timezone":"Asia/Shanghai",
    "iso:country":"CN",
    "name:und_x_variant":[
        "Hsi-ssu-chuang",
        "Xisizhuang"
    ],
    "wof:name":"Xisizhuang",
    "wof:placetype":"locality"
},
  "geometry": {"coordinates":[114.07971999999999,36.78028],"type":"Point"}
}