{
  "type": "Feature",
  "properties": {
    "gn:admin1_code":"32.0",
    "gn:asciiname":"Wageji",
    "gn:country_code":"CN",
    "gn:dem":2953,
    "gn:feature_class":"P",
    "gn:feature_code":"PPL",
    "gn:name":"Wageji",
    "gn:population":0,
    "gn:timezone":"Asia/Shanghai",
    "iso:country":"CN",
    "name:zho_x_preferred":[
        "\u74e6\u6208\u5409"
    ],
    "wof:name":"Wageji",
    "wof:placetype":"locality"
},
  "geometry": {"coordinates":[101.136,30.3461],"type":"Point"}
}