{
  "type": "Feature",
  "properties": {
    "gn:admin1_code":"03",
    "gn:asciiname":"Linjianghu",
    "gn:cc2":"CN",
    "gn:country_code":"CN",
    "gn:dem":207,
    "gn:feature_class":"P",
    "gn:feature_code":"PPL",
    "gn:name":"Linjianghu",
    "gn:population":0,
    "gn:timezone":"Asia/Shanghai",
    "iso:country":"CN",
    "name:und_x_variant":[
        "Lin-chiang-hu",
        "Linjianghu"
    ],
    "wof:name":"Linjianghu",
    "wof:placetype":"locality"
},
  "geometry": {"coordinates":[117.90000000000001,28.68333],"type":"Point"}
}