{
  "type": "Feature",
  "properties": {
    "gn:admin1_code":"9",
    "gn:asciiname":"Dalijia",
    "gn:country_code":"CN",
    "gn:dem":34,
    "gn:feature_class":"P",
    "gn:feature_code":"PPL",
    "gn:name":"Dalijia",
    "gn:population":0,
    "gn:timezone":"Asia/Shanghai",
    "iso:country":"CN",
    "name:zho_x_preferred":[
        "\u5927\u674e\u5bb6"
    ],
    "wof:name":"Dalijia",
    "wof:placetype":"locality"
},
  "geometry": {"coordinates":[116.20399999999999,33.7307],"type":"Point"}
}