{
  "type": "Feature",
  "properties": {
    "gn:admin1_code":"29.0",
    "gn:asciiname":"Xiabaihechang",
    "gn:country_code":"CN",
    "gn:dem":1548,
    "gn:feature_class":"P",
    "gn:feature_code":"PPL",
    "gn:name":"Xiabaihechang",
    "gn:population":0,
    "gn:timezone":"Asia/Shanghai",
    "iso:country":"CN",
    "name:zho_x_preferred":[
        "\u4e0b\u767d\u9e64\u5382"
    ],
    "wof:name":"Xiabaihechang",
    "wof:placetype":"locality"
},
  "geometry": {"coordinates":[102.833,26.2914],"type":"Point"}
}