{
  "type": "Feature",
  "properties": {
    "gn:admin1_code":"16.0",
    "gn:asciiname":"Gaoqiao",
    "gn:country_code":"CN",
    "gn:dem":112,
    "gn:feature_class":"P",
    "gn:feature_code":"PPL",
    "gn:name":"Gaoqiao",
    "gn:population":0,
    "gn:timezone":"Asia/Shanghai",
    "iso:country":"CN",
    "name:ceb_x_preferred":[
        "Gaoqiao"
    ],
    "name:deu_x_preferred":[
        "Gaoqiao"
    ],
    "name:swe_x_preferred":[
        "Gaoqiao"
    ],
    "name:zho_x_preferred":[
        "\u9ad8\u6865"
    ],
    "wof:name":"Gaoqiao",
    "wof:placetype":"locality"
},
  "geometry": {"coordinates":[108.90300000000001,23.1534],"type":"Point"}
}