{
  "type": "Feature",
  "properties": {
    "gn:admin1_code":"01",
    "gn:asciiname":"Nansanshigang",
    "gn:cc2":"CN",
    "gn:country_code":"CN",
    "gn:dem":31,
    "gn:feature_class":"P",
    "gn:feature_code":"PPL",
    "gn:name":"Nansanshigang",
    "gn:population":0,
    "gn:timezone":"Asia/Shanghai",
    "iso:country":"CN",
    "name:und_x_variant":[
        "San-shih-kang",
        "Nan-shan-shih-kang",
        "Nansanshigang"
    ],
    "wof:name":"Nansanshigang",
    "wof:placetype":"locality"
},
  "geometry": {"coordinates":[117.21666999999999,31.85],"type":"Point"}
}