{
  "type": "Feature",
  "properties": {
    "gn:admin1_code":"32.0",
    "gn:asciiname":"Chensheng",
    "gn:country_code":"CN",
    "gn:dem":583,
    "gn:feature_class":"P",
    "gn:feature_code":"PPL",
    "gn:name":"Chensheng",
    "gn:population":0,
    "gn:timezone":"Asia/Shanghai",
    "iso:country":"CN",
    "name:zho_x_preferred":[
        "\u9648\u80dc"
    ],
    "wof:name":"Chensheng",
    "wof:placetype":"locality"
},
  "geometry": {"coordinates":[104.83642,28.2595],"type":"Point"}
}