{
  "type": "Feature",
  "properties": {
    "gn:admin1_code":"29.0",
    "gn:asciiname":"Geping",
    "gn:country_code":"CN",
    "gn:dem":1852,
    "gn:feature_class":"P",
    "gn:feature_code":"PPL",
    "gn:name":"Geping",
    "gn:population":0,
    "gn:timezone":"Asia/Shanghai",
    "iso:country":"CN",
    "name:zho_x_preferred":[
        "\u6208\u5e73"
    ],
    "wof:name":"Geping",
    "wof:placetype":"locality"
},
  "geometry": {"coordinates":[103.831,26.2504],"type":"Point"}
}