{
  "type": "Feature",
  "properties": {
    "gn:admin1_code":"18.0",
    "gn:asciiname":"Dadu",
    "gn:country_code":"CN",
    "gn:dem":847,
    "gn:feature_class":"P",
    "gn:feature_code":"PPL",
    "gn:name":"Dadu",
    "gn:population":0,
    "gn:timezone":"Asia/Shanghai",
    "iso:country":"CN",
    "name:ara_x_preferred":[
        "\u062f\u0627\u062f\u0648"
    ],
    "name:ben_x_preferred":[
        "\u09a1\u09be\u09a6\u09c1"
    ],
    "name:ceb_x_preferred":[
        "Dadu"
    ],
    "name:ces_x_preferred":[
        "Ta-tu"
    ],
    "name:deu_x_preferred":[
        "Dadu"
    ],
    "name:ell_x_preferred":[
        "\u039c\u03c0\u03b1\u03c4\u03bf\u03cd"
    ],
    "name:fra_x_preferred":[
        "Dadu"
    ],
    "name:heb_x_preferred":[
        "\u05d3\u05d0\u05d3\u05d5"
    ],
    "name:hin_x_preferred":[
        "\u0926\u093e\u0926\u0942"
    ],
    "name:hun_x_preferred":[
        "Dadu"
    ],
    "name:ind_x_preferred":[
        "Dadu"
    ],
    "name:nld_x_preferred":[
        "Dadu"
    ],
    "name:nor_x_preferred":[
        "Dadu"
    ],
    "name:por_x_preferred":[
        "Dadu"
    ],
    "name:scn_x_preferred":[
        "Dadu"
    ],
    "name:swe_x_preferred":[
        "Dadu"
    ],
    "name:urd_x_preferred":[
        "\u062f\u0627\u062f\u0648"
    ],
    "wof:name":"Dadu",
    "wof:placetype":"locality"
},
  "geometry": {"coordinates":[107.73999999999999,27.66472],"type":"Point"}
}