{
  "type": "Feature",
  "properties": {
    "gn:admin1_code":"23.0",
    "gn:asciiname":"Yexie",
    "gn:country_code":"CN",
    "gn:dem":6,
    "gn:feature_class":"P",
    "gn:feature_code":"PPLA4",
    "gn:name":"Yexie",
    "gn:population":0,
    "gn:timezone":"Asia/Shanghai",
    "iso:country":"CN",
    "name:und_x_variant":[
        "Yeh-hsieh",
        "Yeh-hsieh-chen",
        "Yexie",
        "\u53f6\u69ad",
        "Yexie Zhen",
        "\u53f6\u69ad\u9547"
    ],
    "wof:name":"Yexie",
    "wof:placetype":"locality"
},
  "geometry": {"coordinates":[121.31643,30.94543],"type":"Point"}
}