{
  "type": "Feature",
  "properties": {
    "gn:admin1_code":"5.0",
    "gn:asciiname":"Yongshengxing",
    "gn:country_code":"CN",
    "gn:dem":234,
    "gn:feature_class":"P",
    "gn:feature_code":"PPL",
    "gn:name":"Yongshengxing",
    "gn:population":0,
    "gn:timezone":"Asia/Shanghai",
    "iso:country":"CN",
    "name:zho_x_preferred":[
        "\u6c38\u76db\u5174"
    ],
    "wof:name":"Yongshengxing",
    "wof:placetype":"locality"
},
  "geometry": {"coordinates":[125.89342000000001,43.48372],"type":"Point"}
}