{
  "type": "Feature",
  "properties": {
    "gn:admin1_code":"14.0",
    "gn:asciiname":"Wujinbozhang",
    "gn:country_code":"CN",
    "gn:dem":3892,
    "gn:feature_class":"P",
    "gn:feature_code":"PPL",
    "gn:name":"Wujinbozhang",
    "gn:population":0,
    "gn:timezone":"Asia/Urumqi",
    "iso:country":"CN",
    "name:zho_x_preferred":[
        "\u4e94\u91d1\u6ce2\u7ae0"
    ],
    "wof:name":"Wujinbozhang",
    "wof:placetype":"locality"
},
  "geometry": {"coordinates":[92.48635,28.41086],"type":"Point"}
}