{
  "type": "Feature",
  "properties": {
    "gn:admin1_code":"5",
    "gn:asciiname":"Gongye",
    "gn:country_code":"CN",
    "gn:dem":302,
    "gn:feature_class":"P",
    "gn:feature_code":"PPL",
    "gn:name":"Gongye",
    "gn:population":0,
    "gn:timezone":"Asia/Shanghai",
    "iso:country":"CN",
    "name:zho_x_preferred":[
        "\u5de5\u4e1a"
    ],
    "wof:name":"Gongye",
    "wof:placetype":"locality"
},
  "geometry": {"coordinates":[127.422,43.6796],"type":"Point"}
}