{
  "type": "Feature",
  "properties": {
    "gn:admin1_code":"3.0",
    "gn:asciiname":"Chaixikeng",
    "gn:country_code":"CN",
    "gn:dem":200,
    "gn:feature_class":"P",
    "gn:feature_code":"PPL",
    "gn:name":"Chaixikeng",
    "gn:population":0,
    "gn:timezone":"Asia/Shanghai",
    "iso:country":"CN",
    "name:und_x_variant":[
        "\u67f4\u6eaa\u5751"
    ],
    "wof:name":"Chaixikeng",
    "wof:placetype":"locality"
},
  "geometry": {"coordinates":[116.52200000000001,26.98594000000001],"type":"Point"}
}