{
  "type": "Feature",
  "properties": {
    "gn:admin1_code":"4.0",
    "gn:asciiname":"Miaoloucun",
    "gn:country_code":"CN",
    "gn:dem":30,
    "gn:feature_class":"P",
    "gn:feature_code":"PPL",
    "gn:name":"Miaoloucun",
    "gn:population":0,
    "gn:timezone":"Asia/Shanghai",
    "iso:country":"CN",
    "name:zho_x_preferred":[
        "\u82d7\u697c\u6751"
    ],
    "wof:name":"Miaoloucun",
    "wof:placetype":"locality"
},
  "geometry": {"coordinates":[117.69232,34.25409000000001],"type":"Point"}
}