{
  "type": "Feature",
  "properties": {
    "gn:admin1_code":"24.0",
    "gn:asciiname":"Diaohugou",
    "gn:country_code":"CN",
    "gn:dem":1776,
    "gn:feature_class":"P",
    "gn:feature_code":"PPL",
    "gn:name":"Diaohugou",
    "gn:population":0,
    "gn:timezone":"Asia/Shanghai",
    "iso:country":"CN",
    "name:zho_x_preferred":[
        "\u5201\u864e\u6c9f"
    ],
    "wof:name":"Diaohugou",
    "wof:placetype":"locality"
},
  "geometry": {"coordinates":[112.21505999999999,38.50411],"type":"Point"}
}