{
  "type": "Feature",
  "properties": {
    "gn:admin1_code":"8.0",
    "gn:asciiname":"Jiafeng",
    "gn:country_code":"CN",
    "gn:dem":49,
    "gn:feature_class":"P",
    "gn:feature_code":"PPL",
    "gn:name":"Jiafeng",
    "gn:population":0,
    "gn:timezone":"Asia/Shanghai",
    "iso:country":"CN",
    "name:zho_x_preferred":[
        "\u4f73\u4e30"
    ],
    "wof:name":"Jiafeng",
    "wof:placetype":"locality"
},
  "geometry": {"coordinates":[133.83371,47.21453],"type":"Point"}
}