{
  "type": "Feature",
  "properties": {
    "gn:admin1_code":"2.0",
    "gn:asciiname":"Shilin",
    "gn:country_code":"CN",
    "gn:dem":8,
    "gn:feature_class":"P",
    "gn:feature_code":"PPL",
    "gn:name":"Shilin",
    "gn:population":0,
    "gn:timezone":"Asia/Shanghai",
    "iso:country":"CN",
    "name:und_x_variant":[
        "\u58eb\u6797",
        "Shilinzhen",
        "\u58eb\u6797\u9547"
    ],
    "wof:name":"Shilin",
    "wof:placetype":"locality"
},
  "geometry": {"coordinates":[120.19853000000001,30.59386],"type":"Point"}
}