{
  "type": "Feature",
  "properties": {
    "gn:admin1_code":"3.0",
    "gn:asciiname":"Jiuzhang",
    "gn:country_code":"CN",
    "gn:dem":28,
    "gn:feature_class":"P",
    "gn:feature_code":"PPL",
    "gn:name":"Jiuzhang",
    "gn:population":0,
    "gn:timezone":"Asia/Shanghai",
    "iso:country":"CN",
    "name:und_x_variant":[
        "\u4e5d\u6a1f"
    ],
    "wof:name":"Jiuzhang",
    "wof:placetype":"locality"
},
  "geometry": {"coordinates":[117.01015,28.90358],"type":"Point"}
}