{
  "type": "Feature",
  "properties": {
    "gn:admin1_code":"30",
    "gn:asciiname":"Chuanxingpai",
    "gn:country_code":"CN",
    "gn:dem":213,
    "gn:feature_class":"P",
    "gn:feature_code":"PPL",
    "gn:name":"Chuanxingpai",
    "gn:population":0,
    "gn:timezone":"Asia/Shanghai",
    "iso:country":"CN",
    "name:zho_x_preferred":[
        "\u8239\u5f62\u6392"
    ],
    "wof:name":"Chuanxingpai",
    "wof:placetype":"locality"
},
  "geometry": {"coordinates":[116.03318,23.94837],"type":"Point"}
}