{
  "type": "Feature",
  "properties": {
    "gn:admin1_code":"10.0",
    "gn:asciiname":"Qianmadi",
    "gn:country_code":"CN",
    "gn:dem":13,
    "gn:feature_class":"P",
    "gn:feature_code":"PPL",
    "gn:name":"Qianmadi",
    "gn:population":0,
    "gn:timezone":"Asia/Shanghai",
    "iso:country":"CN",
    "name:zho_x_preferred":[
        "\u524d\u9ebb\u5730"
    ],
    "wof:name":"Qianmadi",
    "wof:placetype":"locality"
},
  "geometry": {"coordinates":[118.74638,39.5406],"type":"Point"}
}