{
  "type": "Feature",
  "properties": {
    "gn:admin1_code":"4.0",
    "gn:asciiname":"Chengmencun",
    "gn:country_code":"CN",
    "gn:dem":4,
    "gn:feature_class":"P",
    "gn:feature_code":"PPL",
    "gn:name":"Chengmencun",
    "gn:population":0,
    "gn:timezone":"Asia/Shanghai",
    "iso:country":"CN",
    "name:zho_x_preferred":[
        "\u57ce\u95e8\u6751"
    ],
    "wof:name":"Chengmencun",
    "wof:placetype":"locality"
},
  "geometry": {"coordinates":[119.98669,34.20947],"type":"Point"}
}