{
  "type": "Feature",
  "properties": {
    "gn:admin1_code":"32.0",
    "gn:asciiname":"Hongmiaozi",
    "gn:country_code":"CN",
    "gn:dem":439,
    "gn:feature_class":"P",
    "gn:feature_code":"PPL",
    "gn:name":"Hongmiaozi",
    "gn:population":0,
    "gn:timezone":"Asia/Shanghai",
    "iso:country":"CN",
    "name:zho_x_preferred":[
        "\u7ea2\u5e99\u5b50"
    ],
    "wof:name":"Hongmiaozi",
    "wof:placetype":"locality"
},
  "geometry": {"coordinates":[104.56,30.6788],"type":"Point"}
}