{
  "type": "Feature",
  "properties": {
    "gn:admin1_code":"32.0",
    "gn:asciiname":"Baojia Yaodianzi",
    "gn:country_code":"CN",
    "gn:dem":502,
    "gn:feature_class":"P",
    "gn:feature_code":"PPL",
    "gn:name":"Baojia Yaodianzi",
    "gn:population":0,
    "gn:timezone":"Asia/Shanghai",
    "iso:country":"CN",
    "name:zho_x_preferred":[
        "\u5305\u5bb6\u4e48\u5e97\u5b50"
    ],
    "wof:name":"Baojia Yaodianzi",
    "wof:placetype":"locality"
},
  "geometry": {"coordinates":[104.17966,30.68651],"type":"Point"}
}