{
  "type": "Feature",
  "properties": {
    "gn:admin1_code":"25",
    "gn:asciiname":"Gongzhuang",
    "gn:country_code":"CN",
    "gn:dem":70,
    "gn:feature_class":"P",
    "gn:feature_code":"PPL",
    "gn:name":"Gongzhuang",
    "gn:population":0,
    "gn:timezone":"Asia/Shanghai",
    "iso:country":"CN",
    "name:zho_x_preferred":[
        "\u516c\u5e84"
    ],
    "wof:name":"Gongzhuang",
    "wof:placetype":"locality"
},
  "geometry": {"coordinates":[117.11499999999999,35.1656],"type":"Point"}
}