{
  "type": "Feature",
  "properties": {
    "gn:admin1_code":"32.0",
    "gn:asciiname":"Cuoka",
    "gn:country_code":"CN",
    "gn:dem":4520,
    "gn:feature_class":"P",
    "gn:feature_code":"PPL",
    "gn:name":"Cuoka",
    "gn:population":0,
    "gn:timezone":"Asia/Shanghai",
    "iso:country":"CN",
    "name:zho_x_preferred":[
        "\u9519\u5361"
    ],
    "wof:name":"Cuoka",
    "wof:placetype":"locality"
},
  "geometry": {"coordinates":[98.7043,32.9437],"type":"Point"}
}