{
  "type": "Feature",
  "properties": {
    "gn:admin1_code":"25.0",
    "gn:asciiname":"Jingzibu",
    "gn:country_code":"CN",
    "gn:dem":81,
    "gn:feature_class":"P",
    "gn:feature_code":"PPL",
    "gn:name":"Jingzibu",
    "gn:population":0,
    "gn:timezone":"Asia/Shanghai",
    "iso:country":"CN",
    "name:zho_x_preferred":[
        "\u8346\u5b50\u57e0"
    ],
    "wof:name":"Jingzibu",
    "wof:placetype":"locality"
},
  "geometry": {"coordinates":[120.65156,37.48904],"type":"Point"}
}