{
  "type": "Feature",
  "properties": {
    "gn:admin1_code":"26.0",
    "gn:asciiname":"Shajiahecun",
    "gn:country_code":"CN",
    "gn:dem":1146,
    "gn:feature_class":"P",
    "gn:feature_code":"PPL",
    "gn:name":"Shajiahecun",
    "gn:population":0,
    "gn:timezone":"Asia/Shanghai",
    "iso:country":"CN",
    "name:zho_x_preferred":[
        "\u6c99\u5bb6\u6cb3\u6751"
    ],
    "wof:name":"Shajiahecun",
    "wof:placetype":"locality"
},
  "geometry": {"coordinates":[109.8647,37.23937],"type":"Point"}
}