{
  "type": "Feature",
  "properties": {
    "gn:admin1_code":"19.0",
    "gn:asciiname":"Shanghejia Buzi",
    "gn:country_code":"CN",
    "gn:dem":87,
    "gn:feature_class":"P",
    "gn:feature_code":"PPL",
    "gn:name":"Shanghejia Buzi",
    "gn:population":0,
    "gn:timezone":"Asia/Shanghai",
    "iso:country":"CN",
    "name:und_x_variant":[
        "Shanghejiabaozi",
        "Shanghejia Puzi",
        "Shanghejia Buzi"
    ],
    "name:zho_x_preferred":[
        "\u4e0a\u4f55\u5bb6\u5821\u5b50"
    ],
    "wof:name":"Shanghejia Buzi",
    "wof:placetype":"locality"
},
  "geometry": {"coordinates":[123.38357999999999,40.0939],"type":"Point"}
}