{
  "type": "Feature",
  "properties": {
    "gn:admin1_code":"5.0",
    "gn:asciiname":"Shengchantun",
    "gn:country_code":"CN",
    "gn:dem":415,
    "gn:feature_class":"P",
    "gn:feature_code":"PPL",
    "gn:name":"Shengchantun",
    "gn:population":0,
    "gn:timezone":"Asia/Shanghai",
    "iso:country":"CN",
    "name:zho_x_preferred":[
        "\u751f\u4ea7\u5c6f"
    ],
    "wof:name":"Shengchantun",
    "wof:placetype":"locality"
},
  "geometry": {"coordinates":[127.37531,44.04678],"type":"Point"}
}