{
  "type": "Feature",
  "properties": {
    "gn:admin1_code":"20.0",
    "gn:asciiname":"Longtouli",
    "gn:country_code":"CN",
    "gn:dem":537,
    "gn:feature_class":"P",
    "gn:feature_code":"PPL",
    "gn:name":"Longtouli",
    "gn:population":0,
    "gn:timezone":"Asia/Shanghai",
    "iso:country":"CN",
    "name:zho_x_preferred":[
        "\u9f99\u5934\u91cc"
    ],
    "wof:name":"Longtouli",
    "wof:placetype":"locality"
},
  "geometry": {"coordinates":[122.20471000000001,47.70477],"type":"Point"}
}