{
  "type": "Feature",
  "properties": {
    "gn:admin1_code":"14.0",
    "gn:asciiname":"Rongbo",
    "gn:country_code":"CN",
    "gn:dem":4698,
    "gn:feature_class":"P",
    "gn:feature_code":"PPL",
    "gn:name":"Rongbo",
    "gn:population":0,
    "gn:timezone":"Asia/Urumqi",
    "iso:country":"CN",
    "name:msa_x_preferred":[
        "Rongbo"
    ],
    "name:zho_x_preferred":[
        "\u8363\u6ce2"
    ],
    "wof:name":"Rongbo",
    "wof:placetype":"locality"
},
  "geometry": {"coordinates":[90.42072,31.2753],"type":"Point"}
}