{
  "type": "Feature",
  "properties": {
    "gn:admin1_code":"02",
    "gn:admin2_code":"1805525",
    "gn:asciiname":"Wuyi",
    "gn:country_code":"CN",
    "gn:dem":77,
    "gn:feature_class":"P",
    "gn:feature_code":"PPL",
    "gn:name":"Wuyi",
    "gn:population":0,
    "gn:timezone":"Asia/Shanghai",
    "iso:country":"CN",
    "name:ceb_x_preferred":[
        "Wuyi"
    ],
    "name:deu_x_preferred":[
        "Wuyi"
    ],
    "name:fas_x_preferred":[
        "\u0648\u0648 \u06cc\u06cc"
    ],
    "name:fra_x_preferred":[
        "Wuyi"
    ],
    "name:kor_x_preferred":[
        "\uc6b0\uc774\ud604"
    ],
    "name:nor_x_preferred":[
        "Wuyi"
    ],
    "name:swe_x_preferred":[
        "Wuyi"
    ],
    "name:und_x_variant":[
        "Hu-shan-chen",
        "Wuyihsien",
        "Hushan",
        "Wu-i-hsien",
        "Wu-i",
        "Wuyi Che",
        "\u6b66\u4e49",
        "Wuyang"
    ],
    "wof:name":"Wuyi",
    "wof:placetype":"locality"
},
  "geometry": {"coordinates":[119.81636,28.89271],"type":"Point"}
}