{
  "type": "Feature",
  "properties": {
    "gn:admin1_code":"16.0",
    "gn:asciiname":"Donglai",
    "gn:country_code":"CN",
    "gn:dem":544,
    "gn:feature_class":"P",
    "gn:feature_code":"PPL",
    "gn:name":"Donglai",
    "gn:population":0,
    "gn:timezone":"Asia/Shanghai",
    "iso:country":"CN",
    "name:zho_x_preferred":[
        "\u5cd2\u8d56"
    ],
    "wof:name":"Donglai",
    "wof:placetype":"locality"
},
  "geometry": {"coordinates":[107.994,25.1168],"type":"Point"}
}