{
  "type": "Feature",
  "properties": {
    "gn:admin1_code":"16",
    "gn:asciiname":"Shilongjiang",
    "gn:country_code":"CN",
    "gn:dem":220,
    "gn:feature_class":"P",
    "gn:feature_code":"PPL",
    "gn:name":"Shilongjiang",
    "gn:population":0,
    "gn:timezone":"Asia/Shanghai",
    "iso:country":"CN",
    "name:zho_x_preferred":[
        "\u77f3\u9f99\u6c5f"
    ],
    "wof:name":"Shilongjiang",
    "wof:placetype":"locality"
},
  "geometry": {"coordinates":[110.646,25.5874],"type":"Point"}
}