{
  "type": "Feature",
  "properties": {
    "gn:admin1_code":"26",
    "gn:asciiname":"Beijuzhai",
    "gn:country_code":"CN",
    "gn:dem":897,
    "gn:feature_class":"P",
    "gn:feature_code":"PPL",
    "gn:name":"Beijuzhai",
    "gn:population":0,
    "gn:timezone":"Asia/Shanghai",
    "iso:country":"CN",
    "name:und_x_variant":[
        "\u5317\u5c45\u5be8"
    ],
    "name:zho_x_preferred":[
        "\u5317\u5c45\u5be8"
    ],
    "wof:name":"Beijuzhai",
    "wof:placetype":"locality"
},
  "geometry": {"coordinates":[108.73193999999999,34.80444],"type":"Point"}
}