{
  "type": "Feature",
  "properties": {
    "gn:admin1_code":"20.0",
    "gn:asciiname":"Zha'enchagan Gacha",
    "gn:country_code":"CN",
    "gn:dem":968,
    "gn:feature_class":"P",
    "gn:feature_code":"PPL",
    "gn:name":"Zha\u2019enchagan Gacha",
    "gn:population":0,
    "gn:timezone":"Asia/Shanghai",
    "iso:country":"CN",
    "name:und_x_variant":[
        "Zha\u2019enchagan Gacha"
    ],
    "name:zho_x_preferred":[
        "\u624e\u6069\u67e5\u5e72\u560e\u67e5"
    ],
    "wof:name":"Zha'enchagan Gacha",
    "wof:placetype":"locality"
},
  "geometry": {"coordinates":[100.56310999999999,41.84619],"type":"Point"}
}