{
  "type": "Feature",
  "properties": {
    "gn:admin1_code":"4.0",
    "gn:asciiname":"Zhuyougou",
    "gn:country_code":"CN",
    "gn:dem":3,
    "gn:feature_class":"P",
    "gn:feature_code":"PPL",
    "gn:name":"Zhuyougou",
    "gn:population":0,
    "gn:timezone":"Asia/Shanghai",
    "iso:country":"CN",
    "name:zho_x_preferred":[
        "\u6731\u5c24\u6c9f"
    ],
    "wof:name":"Zhuyougou",
    "wof:placetype":"locality"
},
  "geometry": {"coordinates":[119.88488,32.68847],"type":"Point"}
}