{
  "type": "Feature",
  "properties": {
    "gn:admin1_code":"29.0",
    "gn:asciiname":"Shengshengluo",
    "gn:country_code":"CN",
    "gn:dem":1872,
    "gn:feature_class":"P",
    "gn:feature_code":"PPL",
    "gn:name":"Shengshengluo",
    "gn:population":0,
    "gn:timezone":"Asia/Shanghai",
    "iso:country":"CN",
    "name:zho_x_preferred":[
        "\u751f\u751f\u843d"
    ],
    "wof:name":"Shengshengluo",
    "wof:placetype":"locality"
},
  "geometry": {"coordinates":[100.417,27.8116],"type":"Point"}
}