{
  "type": "Feature",
  "properties": {
    "gn:admin1_code":"6.0",
    "gn:asciiname":"Chaxiu Azhang",
    "gn:country_code":"CN",
    "gn:dem":3930,
    "gn:feature_class":"P",
    "gn:feature_code":"PPL",
    "gn:name":"Chaxiu Azhang",
    "gn:population":0,
    "gn:timezone":"Asia/Urumqi",
    "iso:country":"CN",
    "name:zho_x_preferred":[
        "\u67e5\u79c0\u963f\u4ed7"
    ],
    "wof:name":"Chaxiu Azhang",
    "wof:placetype":"locality"
},
  "geometry": {"coordinates":[96.69465,31.88541],"type":"Point"}
}