{
  "type": "Feature",
  "properties": {
    "gn:admin1_code":"1.0",
    "gn:asciiname":"Xugangzicun",
    "gn:country_code":"CN",
    "gn:dem":38,
    "gn:feature_class":"P",
    "gn:feature_code":"PPL",
    "gn:name":"Xugangzicun",
    "gn:population":0,
    "gn:timezone":"Asia/Shanghai",
    "iso:country":"CN",
    "name:und_x_variant":[
        "Xugangzi"
    ],
    "name:zho_x_preferred":[
        "\u8bb8\u5c97\u5b50\u6751"
    ],
    "wof:name":"Xugangzicun",
    "wof:placetype":"locality"
},
  "geometry": {"coordinates":[116.98333,34.08333],"type":"Point"}
}