{
  "type": "Feature",
  "properties": {
    "gn:admin1_code":"25",
    "gn:asciiname":"Houcheng",
    "gn:country_code":"CN",
    "gn:dem":38,
    "gn:feature_class":"P",
    "gn:feature_code":"PPL",
    "gn:name":"Houcheng",
    "gn:population":0,
    "gn:timezone":"Asia/Shanghai",
    "iso:country":"CN",
    "name:zho_x_preferred":[
        "\u540e\u7a0b"
    ],
    "wof:name":"Houcheng",
    "wof:placetype":"locality"
},
  "geometry": {"coordinates":[117.64700000000001,34.6896],"type":"Point"}
}