{
  "type": "Feature",
  "properties": {
    "gn:admin1_code":"29.0",
    "gn:asciiname":"Langnitang",
    "gn:country_code":"CN",
    "gn:dem":2402,
    "gn:feature_class":"P",
    "gn:feature_code":"PPL",
    "gn:name":"Langnitang",
    "gn:population":0,
    "gn:timezone":"Asia/Shanghai",
    "iso:country":"CN",
    "name:zho_x_preferred":[
        "\u6d6a\u6ce5\u5858"
    ],
    "wof:name":"Langnitang",
    "wof:placetype":"locality"
},
  "geometry": {"coordinates":[102.828,25.9923],"type":"Point"}
}