{
  "type": "Feature",
  "properties": {
    "gn:admin1_code":"15.0",
    "gn:asciiname":"Yangyong",
    "gn:country_code":"CN",
    "gn:dem":2680,
    "gn:feature_class":"P",
    "gn:feature_code":"PPLA4",
    "gn:name":"Yangyong",
    "gn:population":0,
    "gn:timezone":"Asia/Shanghai",
    "iso:country":"CN",
    "name:und_x_variant":[
        "\u7f8a\u6c38"
    ],
    "wof:name":"Yangyong",
    "wof:placetype":"locality"
},
  "geometry": {"coordinates":[103.47198,34.6459],"type":"Point"}
}