{
  "type": "Feature",
  "properties": {
    "gn:admin1_code":"14.0",
    "gn:asciiname":"Gongna",
    "gn:country_code":"CN",
    "gn:dem":4609,
    "gn:feature_class":"P",
    "gn:feature_code":"PPL",
    "gn:name":"Gongna",
    "gn:population":0,
    "gn:timezone":"Asia/Urumqi",
    "iso:country":"CN",
    "name:zho_x_preferred":[
        "\u62f1\u54ea"
    ],
    "wof:name":"Gongna",
    "wof:placetype":"locality"
},
  "geometry": {"coordinates":[91.74935000000001,31.68245],"type":"Point"}
}