{
  "type": "Feature",
  "properties": {
    "gn:admin1_code":"09",
    "gn:asciiname":"Dongjie",
    "gn:country_code":"CN",
    "gn:dem":417,
    "gn:feature_class":"P",
    "gn:feature_code":"PPL",
    "gn:name":"Dongjie",
    "gn:population":0,
    "gn:timezone":"Asia/Shanghai",
    "iso:country":"CN",
    "name:und_x_variant":[
        "Tung-chieh",
        "\u6d1e\u8857",
        "Dongjie"
    ],
    "wof:name":"Dongjie",
    "wof:placetype":"locality"
},
  "geometry": {"coordinates":[112.04624,33.50269],"type":"Point"}
}