{
  "type": "Feature",
  "properties": {
    "gn:admin1_code":"32",
    "gn:asciiname":"Guxian",
    "gn:country_code":"CN",
    "gn:dem":408,
    "gn:feature_class":"P",
    "gn:feature_code":"PPL",
    "gn:name":"Guxian",
    "gn:population":0,
    "gn:timezone":"Asia/Shanghai",
    "iso:country":"CN",
    "name:und_x_variant":[
        "Ku-hsien-ch\u2019ang",
        "Guxianchang",
        "Guxian"
    ],
    "name:zho_x_preferred":[
        "\u987e\u53bf"
    ],
    "wof:name":"Guxian",
    "wof:placetype":"locality"
},
  "geometry": {"coordinates":[106.46026000000001,30.66139],"type":"Point"}
}