{
  "type": "Feature",
  "properties": {
    "gn:admin1_code":"9.0",
    "gn:asciiname":"Lianshukou",
    "gn:country_code":"CN",
    "gn:dem":400,
    "gn:feature_class":"P",
    "gn:feature_code":"PPL",
    "gn:name":"Lianshukou",
    "gn:population":0,
    "gn:timezone":"Asia/Shanghai",
    "iso:country":"CN",
    "name:zho_x_preferred":[
        "\u695d\u6811\u53e3"
    ],
    "wof:name":"Lianshukou",
    "wof:placetype":"locality"
},
  "geometry": {"coordinates":[113.21117,34.66914000000001],"type":"Point"}
}