{
  "type": "Feature",
  "properties": {
    "gn:admin1_code":"21.0",
    "gn:asciiname":"Dunjiachuan",
    "gn:country_code":"CN",
    "gn:dem":2040,
    "gn:feature_class":"P",
    "gn:feature_code":"PPL",
    "gn:name":"Dunjiachuan",
    "gn:population":0,
    "gn:timezone":"Asia/Shanghai",
    "iso:country":"CN",
    "name:zho_x_preferred":[
        "\u987f\u5bb6\u5ddd"
    ],
    "wof:name":"Dunjiachuan",
    "wof:placetype":"locality"
},
  "geometry": {"coordinates":[106.274,35.5785],"type":"Point"}
}