{
  "type": "Feature",
  "properties": {
    "gn:admin1_code":"16.0",
    "gn:asciiname":"Bangna",
    "gn:country_code":"CN",
    "gn:dem":385,
    "gn:feature_class":"P",
    "gn:feature_code":"PPL",
    "gn:name":"Bangna",
    "gn:population":0,
    "gn:timezone":"Asia/Shanghai",
    "iso:country":"CN",
    "name:zho_x_preferred":[
        "\u508d\u7eb3"
    ],
    "wof:name":"Bangna",
    "wof:placetype":"locality"
},
  "geometry": {"coordinates":[107.18300000000001,24.0079],"type":"Point"}
}