{
  "type": "Feature",
  "properties": {
    "gn:admin1_code":"19.0",
    "gn:asciiname":"Jinhong",
    "gn:country_code":"CN",
    "gn:dem":4,
    "gn:feature_class":"P",
    "gn:feature_code":"PPL",
    "gn:name":"Jinhong",
    "gn:population":0,
    "gn:timezone":"Asia/Shanghai",
    "iso:country":"CN",
    "name:und_x_variant":[
        "\u9526\u7ea2"
    ],
    "name:zho_x_preferred":[
        "\u9526\u7ea2"
    ],
    "wof:name":"Jinhong",
    "wof:placetype":"locality"
},
  "geometry": {"coordinates":[122.01161999999999,41.00865],"type":"Point"}
}