{
  "type": "Feature",
  "properties": {
    "gn:admin1_code":"29",
    "gn:asciiname":"Watong",
    "gn:country_code":"CN",
    "gn:dem":2000,
    "gn:feature_class":"P",
    "gn:feature_code":"PPL",
    "gn:name":"Watong",
    "gn:population":0,
    "gn:timezone":"Asia/Shanghai",
    "iso:country":"CN",
    "name:zho_x_preferred":[
        "\u6316\u94dc"
    ],
    "wof:name":"Watong",
    "wof:placetype":"locality"
},
  "geometry": {"coordinates":[101.631,24.8595],"type":"Point"}
}