{
  "type": "Feature",
  "properties": {
    "gn:admin1_code":"10.0",
    "gn:asciiname":"Madi'ao",
    "gn:country_code":"CN",
    "gn:dem":633,
    "gn:feature_class":"P",
    "gn:feature_code":"PPL",
    "gn:name":"Madi\u2019ao",
    "gn:population":0,
    "gn:timezone":"Asia/Shanghai",
    "iso:country":"CN",
    "name:und_x_variant":[
        "Madi\u2019ao"
    ],
    "name:zho_x_preferred":[
        "\u9ebb\u5730\u51f9"
    ],
    "wof:name":"Madi'ao",
    "wof:placetype":"locality"
},
  "geometry": {"coordinates":[113.68946,38.4463],"type":"Point"}
}