{
  "type": "Feature",
  "properties": {
    "gn:admin1_code":"5.0",
    "gn:asciiname":"Yongjicun",
    "gn:country_code":"CN",
    "gn:dem":193,
    "gn:feature_class":"P",
    "gn:feature_code":"PPL",
    "gn:name":"Yongjicun",
    "gn:population":0,
    "gn:timezone":"Asia/Shanghai",
    "iso:country":"CN",
    "name:zho_x_preferred":[
        "\u6c38\u5409\u6751"
    ],
    "wof:name":"Yongjicun",
    "wof:placetype":"locality"
},
  "geometry": {"coordinates":[126.11991999999999,44.84476],"type":"Point"}
}