{
  "type": "Feature",
  "properties": {
    "gn:country":"CN",
    "gn:fcode":"PPL",
    "gn:pop":56370,
    "iso:country":"CN",
    "name:zho_x_preferred":[
        "\u6e56\u5858"
    ],
    "qs:name":"Hutang",
    "qs:photos_9r":0,
    "qs:photos_sr":0,
    "qs:pop_sr":"8",
    "wd:wordcount":78,
    "wof:name":"Hutang",
    "wof:placetype":"locality",
    "wof:population":56370
},
  "geometry": {"coordinates":[119.48999999999999,31.53429],"type":"Point"}
}