{
  "type": "Feature",
  "properties": {
    "gn:admin1_code":"4.0",
    "gn:asciiname":"Lubacun",
    "gn:country_code":"CN",
    "gn:dem":28,
    "gn:feature_class":"P",
    "gn:feature_code":"PPL",
    "gn:name":"Lubacun",
    "gn:population":0,
    "gn:timezone":"Asia/Shanghai",
    "iso:country":"CN",
    "name:zho_x_preferred":[
        "\u9c81\u575d\u6751"
    ],
    "wof:name":"Lubacun",
    "wof:placetype":"locality"
},
  "geometry": {"coordinates":[118.71189,32.9686],"type":"Point"}
}