{
  "type": "Feature",
  "properties": {
    "gn:admin1_code":"16.0",
    "gn:asciiname":"Nacao",
    "gn:country_code":"CN",
    "gn:dem":127,
    "gn:feature_class":"P",
    "gn:feature_code":"PPL",
    "gn:name":"Nacao",
    "gn:population":0,
    "gn:timezone":"Asia/Shanghai",
    "iso:country":"CN",
    "name:zho_x_preferred":[
        "\u90a3\u66f9"
    ],
    "wof:name":"Nacao",
    "wof:placetype":"locality"
},
  "geometry": {"coordinates":[107.55800000000001,23.276],"type":"Point"}
}