{
  "type": "Feature",
  "properties": {
    "gn:admin1_code":"19.0",
    "gn:asciiname":"Jinkuangcun",
    "gn:country_code":"CN",
    "gn:dem":140,
    "gn:feature_class":"P",
    "gn:feature_code":"PPL",
    "gn:name":"Jinkuangcun",
    "gn:population":0,
    "gn:timezone":"Asia/Shanghai",
    "iso:country":"CN",
    "name:zho_x_preferred":[
        "\u91d1\u77ff\u6751"
    ],
    "wof:name":"Jinkuangcun",
    "wof:placetype":"locality"
},
  "geometry": {"coordinates":[123.17686999999999,40.0836],"type":"Point"}
}