{
  "type": "Feature",
  "properties": {
    "gn:admin1_code":"10",
    "gn:asciiname":"Zhaoshunying",
    "gn:country_code":"CN",
    "gn:dem":1377,
    "gn:feature_class":"P",
    "gn:feature_code":"PPL",
    "gn:name":"Zhaoshunying",
    "gn:population":0,
    "gn:timezone":"Asia/Shanghai",
    "iso:country":"CN",
    "name:zho_x_preferred":[
        "\u8d75\u987a\u8425"
    ],
    "wof:name":"Zhaoshunying",
    "wof:placetype":"locality"
},
  "geometry": {"coordinates":[114.517,41.67399],"type":"Point"}
}