{
  "type": "Feature",
  "properties": {
    "gn:admin1_code":"24.0",
    "gn:asciiname":"Ji'ergou",
    "gn:country_code":"CN",
    "gn:dem":1559,
    "gn:feature_class":"P",
    "gn:feature_code":"PPL",
    "gn:name":"Ji\u2019ergou",
    "gn:population":0,
    "gn:timezone":"Asia/Shanghai",
    "iso:country":"CN",
    "name:und_x_variant":[
        "Ji\u2019ergou",
        "\u9e21\u513f\u6c9f"
    ],
    "wof:name":"Ji'ergou",
    "wof:placetype":"locality"
},
  "geometry": {"coordinates":[113.3438,39.38732],"type":"Point"}
}