{
  "type": "Feature",
  "properties": {
    "gn:admin1_code":"21.0",
    "gn:asciiname":"Wangjiabu",
    "gn:country_code":"CN",
    "gn:dem":1887,
    "gn:feature_class":"P",
    "gn:feature_code":"PPL",
    "gn:name":"Wangjiabu",
    "gn:population":0,
    "gn:timezone":"Asia/Shanghai",
    "iso:country":"CN",
    "name:und_x_variant":[
        "\u738b\u5bb6\u5821"
    ],
    "name:zho_x_preferred":[
        "\u738b\u5bb6\u5821"
    ],
    "wof:name":"Wangjiabu",
    "wof:placetype":"locality"
},
  "geometry": {"coordinates":[105.62470999999999,35.81178],"type":"Point"}
}