{
  "type": "Feature",
  "properties": {
    "gn:admin1_code":"07",
    "gn:asciiname":"Chuanshi",
    "gn:country_code":"CN",
    "gn:dem":54,
    "gn:feature_class":"P",
    "gn:feature_code":"PPL",
    "gn:name":"Chuanshi",
    "gn:population":0,
    "gn:timezone":"Asia/Shanghai",
    "iso:country":"CN",
    "name:und_x_variant":[
        "Ch\u2019uan-shih",
        "Chuanshi"
    ],
    "name:zho_x_preferred":[
        "\u5ddd\u77f3"
    ],
    "wof:name":"Chuanshi",
    "wof:placetype":"locality"
},
  "geometry": {"coordinates":[119.66555,26.1357],"type":"Point"}
}