{
  "type": "Feature",
  "properties": {
    "gn:admin1_code":"7",
    "gn:asciiname":"Sanxi",
    "gn:country_code":"CN",
    "gn:dem":11,
    "gn:feature_class":"P",
    "gn:feature_code":"PPL",
    "gn:name":"Sanxi",
    "gn:population":0,
    "gn:timezone":"Asia/Shanghai",
    "iso:country":"CN",
    "name:und_x_variant":[
        "San-ch\u2019i",
        "Sanxi"
    ],
    "name:zho_x_preferred":[
        "\u4e09\u6eaa"
    ],
    "wof:name":"Sanxi",
    "wof:placetype":"locality"
},
  "geometry": {"coordinates":[119.53861999999999,25.84212],"type":"Point"}
}