{
  "type": "Feature",
  "properties": {
    "gn:admin1_code":"14.0",
    "gn:asciiname":"Laduocun",
    "gn:country_code":"CN",
    "gn:dem":4503,
    "gn:feature_class":"P",
    "gn:feature_code":"PPL",
    "gn:name":"Laduocun",
    "gn:population":0,
    "gn:timezone":"Asia/Urumqi",
    "iso:country":"CN",
    "name:zho_x_preferred":[
        "\u62c9\u591a\u6751"
    ],
    "wof:name":"Laduocun",
    "wof:placetype":"locality"
},
  "geometry": {"coordinates":[90.59538000000001,30.18577],"type":"Point"}
}