{
  "type": "Feature",
  "properties": {
    "gn:admin1_code":"26.0",
    "gn:asciiname":"Jiajia Goucun",
    "gn:country_code":"CN",
    "gn:dem":1096,
    "gn:feature_class":"P",
    "gn:feature_code":"PPL",
    "gn:name":"Jiajia Goucun",
    "gn:population":0,
    "gn:timezone":"Asia/Shanghai",
    "iso:country":"CN",
    "name:zho_x_preferred":[
        "\u8d3e\u5bb6\u6c9f\u6751"
    ],
    "wof:name":"Jiajia Goucun",
    "wof:placetype":"locality"
},
  "geometry": {"coordinates":[110.806,38.9113],"type":"Point"}
}