{
  "type": "Feature",
  "properties": {
    "gn:admin1_code":"29.0",
    "gn:asciiname":"Tumuka",
    "gn:country_code":"CN",
    "gn:dem":1839,
    "gn:feature_class":"P",
    "gn:feature_code":"PPL",
    "gn:name":"Tumuka",
    "gn:population":0,
    "gn:timezone":"Asia/Shanghai",
    "iso:country":"CN",
    "name:zho_x_preferred":[
        "\u571f\u6728\u5361"
    ],
    "wof:name":"Tumuka",
    "wof:placetype":"locality"
},
  "geometry": {"coordinates":[104.453,26.1589],"type":"Point"}
}