{
  "type": "Feature",
  "properties": {
    "gn:admin1_code":"26.0",
    "gn:asciiname":"Dingjia Pancun",
    "gn:country_code":"CN",
    "gn:dem":807,
    "gn:feature_class":"P",
    "gn:feature_code":"PPL",
    "gn:name":"Dingjia Pancun",
    "gn:population":0,
    "gn:timezone":"Asia/Shanghai",
    "iso:country":"CN",
    "name:zho_x_preferred":[
        "\u4e01\u5bb6\u7554\u6751"
    ],
    "wof:name":"Dingjia Pancun",
    "wof:placetype":"locality"
},
  "geometry": {"coordinates":[110.76900000000001,37.6559],"type":"Point"}
}