{
  "type": "Feature",
  "properties": {
    "gn:admin1_code":"02",
    "gn:asciiname":"Xinwu",
    "gn:country_code":"CN",
    "gn:dem":11,
    "gn:feature_class":"P",
    "gn:feature_code":"PPL",
    "gn:name":"Xinwu",
    "gn:population":0,
    "gn:timezone":"Asia/Shanghai",
    "iso:country":"CN",
    "name:und_x_variant":[
        "\u65b0\u5c4b",
        "Hsin-wu",
        "Xinwu"
    ],
    "wof:name":"Xinwu",
    "wof:placetype":"locality"
},
  "geometry": {"coordinates":[121.3575,28.73147],"type":"Point"}
}