{
  "type": "Feature",
  "properties": {
    "gn:admin1_code":"19",
    "gn:asciiname":"Luanniqiaocun",
    "gn:country_code":"CN",
    "gn:dem":121,
    "gn:feature_class":"P",
    "gn:feature_code":"PPL",
    "gn:name":"Luanniqiaocun",
    "gn:population":0,
    "gn:timezone":"Asia/Shanghai",
    "iso:country":"CN",
    "name:zho_x_preferred":[
        "\u4e71\u6ce5\u6865\u6751"
    ],
    "wof:name":"Luanniqiaocun",
    "wof:placetype":"locality"
},
  "geometry": {"coordinates":[121.428,38.9114],"type":"Point"}
}