{
  "type": "Feature",
  "properties": {
    "gn:admin1_code":"16.0",
    "gn:asciiname":"Weilai",
    "gn:country_code":"CN",
    "gn:dem":729,
    "gn:feature_class":"P",
    "gn:feature_code":"PPL",
    "gn:name":"Weilai",
    "gn:population":0,
    "gn:timezone":"Asia/Shanghai",
    "iso:country":"CN",
    "name:zho_x_preferred":[
        "\u6e2d\u6765"
    ],
    "wof:name":"Weilai",
    "wof:placetype":"locality"
},
  "geometry": {"coordinates":[105.874,24.5119],"type":"Point"}
}