{
  "type": "Feature",
  "properties": {
    "gn:admin1_code":"32.0",
    "gn:asciiname":"Chawanba",
    "gn:country_code":"CN",
    "gn:dem":313,
    "gn:feature_class":"P",
    "gn:feature_code":"PPL",
    "gn:name":"Chawanba",
    "gn:population":0,
    "gn:timezone":"Asia/Shanghai",
    "iso:country":"CN",
    "name:zho_x_preferred":[
        "\u63d2\u5846\u575d"
    ],
    "wof:name":"Chawanba",
    "wof:placetype":"locality"
},
  "geometry": {"coordinates":[107.164,30.2435],"type":"Point"}
}