{
  "type": "Feature",
  "properties": {
    "gn:admin1_code":"19.0",
    "gn:asciiname":"Yujia Wobu",
    "gn:country_code":"CN",
    "gn:dem":11,
    "gn:feature_class":"P",
    "gn:feature_code":"PPL",
    "gn:name":"Yujia Wobu",
    "gn:population":0,
    "gn:timezone":"Asia/Shanghai",
    "iso:country":"CN",
    "name:zho_x_preferred":[
        "\u4e8e\u5bb6\u7a9d\u5821"
    ],
    "wof:name":"Yujia Wobu",
    "wof:placetype":"locality"
},
  "geometry": {"coordinates":[122.554,41.4073],"type":"Point"}
}