{
  "type": "Feature",
  "properties": {
    "gn:admin1_code":"8.0",
    "gn:asciiname":"Qunli Jingyingsuo",
    "gn:country_code":"CN",
    "gn:dem":308,
    "gn:feature_class":"P",
    "gn:feature_code":"PPLF",
    "gn:name":"Qunli Jingyingsuo",
    "gn:population":0,
    "gn:timezone":"Asia/Shanghai",
    "iso:country":"CN",
    "name:zho_x_preferred":[
        "\u7fa4\u529b\u7ecf\u8425\u6240"
    ],
    "wof:name":"Qunli Jingyingsuo",
    "wof:placetype":"locality"
},
  "geometry": {"coordinates":[127.37109,47.85284],"type":"Point"}
}