{
  "type": "Feature",
  "properties": {
    "gn:admin1_code":"29",
    "gn:asciiname":"Sankeshu",
    "gn:country_code":"CN",
    "gn:dem":2257,
    "gn:feature_class":"P",
    "gn:feature_code":"PPL",
    "gn:name":"Sankeshu",
    "gn:population":0,
    "gn:timezone":"Asia/Shanghai",
    "iso:country":"CN",
    "name:zho_x_preferred":[
        "\u4e09\u68f5\u6811"
    ],
    "wof:name":"Sankeshu",
    "wof:placetype":"locality"
},
  "geometry": {"coordinates":[102.11042,24.59904],"type":"Point"}
}