{
  "type": "Feature",
  "properties": {
    "gn:admin1_code":"07",
    "gn:asciiname":"Neichunli",
    "gn:country_code":"CN",
    "gn:dem":932,
    "gn:feature_class":"P",
    "gn:feature_code":"PPL",
    "gn:name":"Neichunli",
    "gn:population":0,
    "gn:timezone":"Asia/Shanghai",
    "iso:country":"CN",
    "name:zho_x_preferred":[
        "\u5185\u6625\u91cc"
    ],
    "wof:name":"Neichunli",
    "wof:placetype":"locality"
},
  "geometry": {"coordinates":[118.07778,25.65306],"type":"Point"}
}