{
  "type": "Feature",
  "properties": {
    "gn:admin1_code":"3.0",
    "gn:asciiname":"Laoxia Fangjia",
    "gn:country_code":"CN",
    "gn:dem":103,
    "gn:feature_class":"P",
    "gn:feature_code":"PPL",
    "gn:name":"Laoxia Fangjia",
    "gn:population":0,
    "gn:timezone":"Asia/Shanghai",
    "iso:country":"CN",
    "name:und_x_variant":[
        "\u8001\u4e0b\u65b9\u5bb6"
    ],
    "wof:name":"Laoxia Fangjia",
    "wof:placetype":"locality"
},
  "geometry": {"coordinates":[114.48751,27.17802],"type":"Point"}
}