{
  "type": "Feature",
  "properties": {
    "gn:admin1_code":"9",
    "gn:asciiname":"Nangaozhuang",
    "gn:country_code":"CN",
    "gn:dem":49,
    "gn:feature_class":"P",
    "gn:feature_code":"PPL",
    "gn:name":"Nangaozhuang",
    "gn:population":0,
    "gn:timezone":"Asia/Shanghai",
    "iso:country":"CN",
    "name:zho_x_preferred":[
        "\u5357\u9ad8\u5e84"
    ],
    "wof:name":"Nangaozhuang",
    "wof:placetype":"locality"
},
  "geometry": {"coordinates":[115.34,36.0494],"type":"Point"}
}