{
  "type": "Feature",
  "properties": {
    "gn:admin1_code":"26.0",
    "gn:asciiname":"Zhuyuancha",
    "gn:country_code":"CN",
    "gn:dem":906,
    "gn:feature_class":"P",
    "gn:feature_code":"PPL",
    "gn:name":"Zhuyuancha",
    "gn:population":0,
    "gn:timezone":"Asia/Shanghai",
    "iso:country":"CN",
    "name:zho_x_preferred":[
        "\u7af9\u56ed\u5c94"
    ],
    "wof:name":"Zhuyuancha",
    "wof:placetype":"locality"
},
  "geometry": {"coordinates":[109.84072,34.46394],"type":"Point"}
}