{
  "type": "Feature",
  "properties": {
    "gn:admin1_code":"19.0",
    "gn:asciiname":"Gaokanzi",
    "gn:country_code":"CN",
    "gn:dem":163,
    "gn:feature_class":"P",
    "gn:feature_code":"PPL",
    "gn:name":"Gaokanzi",
    "gn:population":0,
    "gn:timezone":"Asia/Shanghai",
    "iso:country":"CN",
    "name:zho_x_preferred":[
        "\u9ad8\u574e\u5b50"
    ],
    "wof:name":"Gaokanzi",
    "wof:placetype":"locality"
},
  "geometry": {"coordinates":[125.37942,40.96506],"type":"Point"}
}