{
  "type": "Feature",
  "properties": {
    "gn:admin1_code":"4.0",
    "gn:asciiname":"Li'an",
    "gn:country_code":"CN",
    "gn:dem":47,
    "gn:feature_class":"P",
    "gn:feature_code":"PPL",
    "gn:name":"Li\u2019an",
    "gn:population":0,
    "gn:timezone":"Asia/Shanghai",
    "iso:country":"CN",
    "name:und_x_variant":[
        "Li\u2019an"
    ],
    "name:zho_x_preferred":[
        "\u674e\u5b89"
    ],
    "wof:name":"Li'an",
    "wof:placetype":"locality"
},
  "geometry": {"coordinates":[118.50409000000001,32.91457],"type":"Point"}
}