{
  "type": "Feature",
  "properties": {
    "gn:admin1_code":"14.0",
    "gn:asciiname":"Sabuding",
    "gn:country_code":"CN",
    "gn:dem":4447,
    "gn:feature_class":"P",
    "gn:feature_code":"PPL",
    "gn:name":"Sabuding",
    "gn:population":0,
    "gn:timezone":"Asia/Urumqi",
    "iso:country":"CN",
    "name:zho_x_preferred":[
        "\u8428\u4e0d\u4e01"
    ],
    "wof:name":"Sabuding",
    "wof:placetype":"locality"
},
  "geometry": {"coordinates":[88.0277,28.8784],"type":"Point"}
}