{
  "type": "Feature",
  "properties": {
    "gn:admin1_code":"20.0",
    "gn:asciiname":"Dayoucheng",
    "gn:country_code":"CN",
    "gn:dem":1896,
    "gn:feature_class":"P",
    "gn:feature_code":"PPL",
    "gn:name":"Dayoucheng",
    "gn:population":0,
    "gn:timezone":"Asia/Shanghai",
    "iso:country":"CN",
    "name:und_x_variant":[
        "\u5927\u6709\u57ce"
    ],
    "wof:name":"Dayoucheng",
    "wof:placetype":"locality"
},
  "geometry": {"coordinates":[111.02333,41.00431],"type":"Point"}
}