{
  "type": "Feature",
  "properties": {
    "gn:admin1_code":"11.0",
    "gn:asciiname":"Meijia Haokou",
    "gn:country_code":"CN",
    "gn:dem":32,
    "gn:feature_class":"P",
    "gn:feature_code":"PPL",
    "gn:name":"Meijia Haokou",
    "gn:population":0,
    "gn:timezone":"Asia/Shanghai",
    "iso:country":"CN",
    "name:zho_x_preferred":[
        "Meijia Haokou"
    ],
    "name:zho_x_variant":[
        "\u6885\u5bb6\u8c6a\u53e3"
    ],
    "wof:name":"Meijia Haokou",
    "wof:placetype":"locality"
},
  "geometry": {"coordinates":[111.77173999999999,28.99113],"type":"Point"}
}