{
  "type": "Feature",
  "properties": {
    "gn:admin1_code":"29.0",
    "gn:asciiname":"Yangguang",
    "gn:country_code":"CN",
    "gn:dem":1815,
    "gn:feature_class":"P",
    "gn:feature_code":"PPLA4",
    "gn:name":"Yangguang",
    "gn:population":0,
    "gn:timezone":"Asia/Shanghai",
    "iso:country":"CN",
    "name:und_x_variant":[
        "\u6768\u5e7f",
        "Yangguang Zhen",
        "Yanguang Zhen",
        "\u6768\u5e7f\u9547",
        "Yangguang"
    ],
    "wof:name":"Yangguang",
    "wof:placetype":"locality"
},
  "geometry": {"coordinates":[102.79389,24.13722000000001],"type":"Point"}
}