{
  "type": "Feature",
  "properties": {
    "gn:admin1_code":"1.0",
    "gn:asciiname":"Xujingcun",
    "gn:country_code":"CN",
    "gn:dem":47,
    "gn:feature_class":"P",
    "gn:feature_code":"PPL",
    "gn:name":"Xujingcun",
    "gn:population":0,
    "gn:timezone":"Asia/Shanghai",
    "iso:country":"CN",
    "name:und_x_variant":[
        "Xujing"
    ],
    "name:zho_x_preferred":[
        "\u5f90\u4e95\u6751"
    ],
    "wof:name":"Xujingcun",
    "wof:placetype":"locality"
},
  "geometry": {"coordinates":[116.40000000000001,34.45],"type":"Point"}
}