{
  "type": "Feature",
  "properties": {
    "gn:admin1_code":"32.0",
    "gn:asciiname":"Daquanshan",
    "gn:country_code":"CN",
    "gn:dem":934,
    "gn:feature_class":"P",
    "gn:feature_code":"PPL",
    "gn:name":"Daquanshan",
    "gn:population":0,
    "gn:timezone":"Asia/Shanghai",
    "iso:country":"CN",
    "name:zho_x_preferred":[
        "\u5927\u6cc9\u5c71"
    ],
    "wof:name":"Daquanshan",
    "wof:placetype":"locality"
},
  "geometry": {"coordinates":[103.21719,29.16198],"type":"Point"}
}