{
  "type": "Feature",
  "properties": {
    "gn:admin1_code":"26.0",
    "gn:asciiname":"Qianzuizi",
    "gn:country_code":"CN",
    "gn:dem":972,
    "gn:feature_class":"P",
    "gn:feature_code":"PPL",
    "gn:name":"Qianzuizi",
    "gn:population":0,
    "gn:timezone":"Asia/Shanghai",
    "iso:country":"CN",
    "name:zho_x_preferred":[
        "\u524d\u5634\u5b50"
    ],
    "wof:name":"Qianzuizi",
    "wof:placetype":"locality"
},
  "geometry": {"coordinates":[108.73499,34.90676],"type":"Point"}
}