{
  "type": "Feature",
  "properties": {
    "gn:admin1_code":"21.0",
    "gn:asciiname":"Gaoyaozhang",
    "gn:country_code":"CN",
    "gn:dem":1844,
    "gn:feature_class":"P",
    "gn:feature_code":"PPL",
    "gn:name":"Gaoyaozhang",
    "gn:population":0,
    "gn:timezone":"Asia/Shanghai",
    "iso:country":"CN",
    "name:und_x_variant":[
        "\u9ad8\u5d3e\u638c"
    ],
    "name:zho_x_preferred":[
        "\u9ad8\u5d3e\u638c"
    ],
    "wof:name":"Gaoyaozhang",
    "wof:placetype":"locality"
},
  "geometry": {"coordinates":[106.02475,36.46427],"type":"Point"}
}