{
  "type": "Feature",
  "properties": {
    "gn:admin1_code":"1.0",
    "gn:asciiname":"Guxinfancun",
    "gn:country_code":"CN",
    "gn:dem":63,
    "gn:feature_class":"P",
    "gn:feature_code":"PPL",
    "gn:name":"Guxinfancun",
    "gn:population":0,
    "gn:timezone":"Asia/Shanghai",
    "iso:country":"CN",
    "name:zho_x_preferred":[
        "\u53e4\u5fc3\u7548\u6751"
    ],
    "wof:name":"Guxinfancun",
    "wof:placetype":"locality"
},
  "geometry": {"coordinates":[115.89727999999999,31.84167],"type":"Point"}
}