{
  "type": "Feature",
  "properties": {
    "gn:admin1_code":"1.0",
    "gn:asciiname":"Yancun",
    "gn:country_code":"CN",
    "gn:dem":57,
    "gn:feature_class":"P",
    "gn:feature_code":"PPL",
    "gn:name":"Yancun",
    "gn:population":0,
    "gn:timezone":"Asia/Shanghai",
    "iso:country":"CN",
    "name:zho_x_preferred":[
        "Yancun"
    ],
    "name:zho_x_variant":[
        "\u664f\u6751"
    ],
    "wof:name":"Yancun",
    "wof:placetype":"locality"
},
  "geometry": {"coordinates":[119.48808,30.84597],"type":"Point"}
}