{
  "type": "Feature",
  "properties": {
    "gn:admin1_code":"32.0",
    "gn:asciiname":"Zijiashan",
    "gn:country_code":"CN",
    "gn:dem":1916,
    "gn:feature_class":"P",
    "gn:feature_code":"PPL",
    "gn:name":"Zijiashan",
    "gn:population":0,
    "gn:timezone":"Asia/Shanghai",
    "iso:country":"CN",
    "name:zho_x_preferred":[
        "\u5b5c\u5bb6\u5c71"
    ],
    "wof:name":"Zijiashan",
    "wof:placetype":"locality"
},
  "geometry": {"coordinates":[102.14400000000001,28.3581],"type":"Point"}
}