{
  "type": "Feature",
  "properties": {
    "gn:admin1_code":"15.0",
    "gn:asciiname":"Caiwangjia",
    "gn:country_code":"CN",
    "gn:dem":1933,
    "gn:feature_class":"P",
    "gn:feature_code":"PPL",
    "gn:name":"Caiwangjia",
    "gn:population":0,
    "gn:timezone":"Asia/Shanghai",
    "iso:country":"CN",
    "name:zho_x_preferred":[
        "\u8521\u738b\u5bb6"
    ],
    "wof:name":"Caiwangjia",
    "wof:placetype":"locality"
},
  "geometry": {"coordinates":[103.623,35.5038],"type":"Point"}
}