{
  "type": "Feature",
  "properties": {
    "gn:admin1_code":"2.0",
    "gn:asciiname":"Shenjiaqiao",
    "gn:country_code":"CN",
    "gn:dem":5,
    "gn:feature_class":"P",
    "gn:feature_code":"PPL",
    "gn:name":"Shenjiaqiao",
    "gn:population":0,
    "gn:timezone":"Asia/Shanghai",
    "iso:country":"CN",
    "name:und_x_variant":[
        "\u6c88\u5bb6\u6865"
    ],
    "wof:name":"Shenjiaqiao",
    "wof:placetype":"locality"
},
  "geometry": {"coordinates":[120.83291,30.46446],"type":"Point"}
}