{
  "type": "Feature",
  "properties": {
    "gn:admin1_code":"3.0",
    "gn:asciiname":"Shangba",
    "gn:country_code":"CN",
    "gn:dem":443,
    "gn:feature_class":"P",
    "gn:feature_code":"PPL",
    "gn:name":"Shangba",
    "gn:population":0,
    "gn:timezone":"Asia/Shanghai",
    "iso:country":"CN",
    "name:und_x_variant":[
        "\u4e0a\u575d"
    ],
    "wof:name":"Shangba",
    "wof:placetype":"locality"
},
  "geometry": {"coordinates":[115.28085,25.63713],"type":"Point"}
}