{
  "type": "Feature",
  "properties": {
    "gn:admin1_code":"18",
    "gn:asciiname":"Zhutiyan",
    "gn:country_code":"CN",
    "gn:dem":1028,
    "gn:feature_class":"P",
    "gn:feature_code":"PPL",
    "gn:name":"Zhutiyan",
    "gn:population":0,
    "gn:timezone":"Asia/Shanghai",
    "iso:country":"CN",
    "name:zho_x_preferred":[
        "\u732a\u8e44\u5ca9"
    ],
    "wof:name":"Zhutiyan",
    "wof:placetype":"locality"
},
  "geometry": {"coordinates":[105.374,27.7342],"type":"Point"}
}