{
  "type": "Feature",
  "properties": {
    "gn:admin1_code":"30",
    "gn:asciiname":"Chi'ao",
    "gn:country_code":"CN",
    "gn:dem":34,
    "gn:feature_class":"P",
    "gn:feature_code":"PPL",
    "gn:name":"Chi\u2019ao",
    "gn:population":0,
    "gn:timezone":"Asia/Shanghai",
    "iso:country":"CN",
    "name:zho_x_preferred":[
        "\u8d64\u5773"
    ],
    "name:zho_x_variant":[
        "Chi\u2019ao"
    ],
    "wof:name":"Chi'ao",
    "wof:placetype":"locality"
},
  "geometry": {"coordinates":[112.54883,22.91375],"type":"Point"}
}