{
  "type": "Feature",
  "properties": {
    "gn:admin1_code":"4.0",
    "gn:asciiname":"Houjian Erzu",
    "gn:country_code":"CN",
    "gn:dem":0,
    "gn:feature_class":"P",
    "gn:feature_code":"PPLF",
    "gn:name":"Houjian Erzu",
    "gn:population":0,
    "gn:timezone":"Asia/Shanghai",
    "iso:country":"CN",
    "name:zho_x_preferred":[
        "Houjian Erzu"
    ],
    "name:zho_x_variant":[
        "\u540e\u6da7\u4e8c\u7ec4"
    ],
    "wof:name":"Houjian Erzu",
    "wof:placetype":"locality"
},
  "geometry": {"coordinates":[120.197,34.01819],"type":"Point"}
}