{
  "type": "Feature",
  "properties": {
    "gn:admin1_code":"1.0",
    "gn:asciiname":"Machengduncun",
    "gn:country_code":"CN",
    "gn:dem":34,
    "gn:feature_class":"P",
    "gn:feature_code":"PPL",
    "gn:name":"Machengduncun",
    "gn:population":0,
    "gn:timezone":"Asia/Shanghai",
    "iso:country":"CN",
    "name:zho_x_preferred":[
        "\u9a6c\u57ce\u58a9\u6751"
    ],
    "wof:name":"Machengduncun",
    "wof:placetype":"locality"
},
  "geometry": {"coordinates":[116.10796999999999,32.04822],"type":"Point"}
}