{
  "type": "Feature",
  "properties": {
    "gn:admin1_code":"14.0",
    "gn:asciiname":"Bangxue",
    "gn:country_code":"CN",
    "gn:dem":4064,
    "gn:feature_class":"P",
    "gn:feature_code":"PPL",
    "gn:name":"Bangxue",
    "gn:population":0,
    "gn:timezone":"Asia/Urumqi",
    "iso:country":"CN",
    "name:zho_x_preferred":[
        "\u90a6\u5b66"
    ],
    "wof:name":"Bangxue",
    "wof:placetype":"locality"
},
  "geometry": {"coordinates":[95.84058,30.86532],"type":"Point"}
}