{
  "type": "Feature",
  "properties": {
    "gn:admin1_code":"30.0",
    "gn:asciiname":"Doucun",
    "gn:country_code":"CN",
    "gn:dem":95,
    "gn:feature_class":"P",
    "gn:feature_code":"PPL",
    "gn:name":"Doucun",
    "gn:population":0,
    "gn:timezone":"Asia/Shanghai",
    "iso:country":"CN",
    "name:zho_x_preferred":[
        "Doucun"
    ],
    "name:zho_x_variant":[
        "\u6597\u6751"
    ],
    "wof:name":"Doucun",
    "wof:placetype":"locality"
},
  "geometry": {"coordinates":[113.43161000000001,24.99223],"type":"Point"}
}