{
  "type": "Feature",
  "properties": {
    "gn:admin1_code":"19.0",
    "gn:asciiname":"Zhuguantai",
    "gn:country_code":"CN",
    "gn:dem":23,
    "gn:feature_class":"P",
    "gn:feature_code":"PPL",
    "gn:name":"Zhuguantai",
    "gn:population":0,
    "gn:timezone":"Asia/Shanghai",
    "iso:country":"CN",
    "name:und_x_variant":[
        "\u6731\u5b98\u53f0"
    ],
    "name:zho_x_preferred":[
        "\u6731\u5b98\u53f0"
    ],
    "wof:name":"Zhuguantai",
    "wof:placetype":"locality"
},
  "geometry": {"coordinates":[123.18181,41.49168],"type":"Point"}
}