{
  "type": "Feature",
  "properties": {
    "gn:admin1_code":"02",
    "gn:asciiname":"Lukoucun",
    "gn:country_code":"CN",
    "gn:dem":23,
    "gn:feature_class":"P",
    "gn:feature_code":"PPL",
    "gn:name":"Lukoucun",
    "gn:population":0,
    "gn:timezone":"Asia/Shanghai",
    "iso:country":"CN",
    "name:und_x_variant":[
        "Lu-k\u2019ou-ts\u2019un",
        "Lukou",
        "Lukoucun"
    ],
    "name:zho_x_preferred":[
        "\u8def\u53e3\u6751"
    ],
    "wof:name":"Lukoucun",
    "wof:placetype":"locality"
},
  "geometry": {"coordinates":[120.67528,28.18201],"type":"Point"}
}