{
  "type": "Feature",
  "properties": {
    "gn:admin1_code":"15.0",
    "gn:asciiname":"Wangzhai",
    "gn:country_code":"CN",
    "gn:dem":1624,
    "gn:feature_class":"P",
    "gn:feature_code":"PPL",
    "gn:name":"Wangzhai",
    "gn:population":0,
    "gn:timezone":"Asia/Shanghai",
    "iso:country":"CN",
    "name:zho_x_preferred":[
        "\u738b\u5be8"
    ],
    "wof:name":"Wangzhai",
    "wof:placetype":"locality"
},
  "geometry": {"coordinates":[106.541,35.1987],"type":"Point"}
}