{
  "type": "Feature",
  "properties": {
    "gn:admin1_code":"4.0",
    "gn:asciiname":"Jinnancun",
    "gn:country_code":"CN",
    "gn:dem":0,
    "gn:feature_class":"P",
    "gn:feature_code":"PPL",
    "gn:name":"Jinnancun",
    "gn:population":0,
    "gn:timezone":"Asia/Shanghai",
    "iso:country":"CN",
    "name:zho_x_preferred":[
        "\u6d25\u5357\u6751"
    ],
    "wof:name":"Jinnancun",
    "wof:placetype":"locality"
},
  "geometry": {"coordinates":[120.17,33.631],"type":"Point"}
}