{
  "type": "Feature",
  "properties": {
    "gn:admin1_code":"8.0",
    "gn:asciiname":"Yangjieguan",
    "gn:country_code":"CN",
    "gn:dem":129,
    "gn:feature_class":"P",
    "gn:feature_code":"PPL",
    "gn:name":"Yangjieguan",
    "gn:population":0,
    "gn:timezone":"Asia/Shanghai",
    "iso:country":"CN",
    "name:zho_x_preferred":[
        "\u6768\u754c\u5b98"
    ],
    "wof:name":"Yangjieguan",
    "wof:placetype":"locality"
},
  "geometry": {"coordinates":[126.29328999999998,45.95164000000001],"type":"Point"}
}