{
  "type": "Feature",
  "properties": {
    "gn:admin1_code":"19.0",
    "gn:asciiname":"Hongqigan",
    "gn:country_code":"CN",
    "gn:dem":272,
    "gn:feature_class":"P",
    "gn:feature_code":"PPL",
    "gn:name":"Hongqigan",
    "gn:population":0,
    "gn:timezone":"Asia/Shanghai",
    "iso:country":"CN",
    "name:und_x_variant":[
        "\u7ea2\u65d7\u6746"
    ],
    "name:zho_x_preferred":[
        "\u7ea2\u65d7\u6746"
    ],
    "wof:name":"Hongqigan",
    "wof:placetype":"locality"
},
  "geometry": {"coordinates":[119.756,40.4282],"type":"Point"}
}