{
  "type": "Feature",
  "properties": {
    "gn:admin1_code":"3",
    "gn:asciiname":"Siqian",
    "gn:country_code":"CN",
    "gn:dem":117,
    "gn:feature_class":"P",
    "gn:feature_code":"PPL",
    "gn:name":"Siqian",
    "gn:population":0,
    "gn:timezone":"Asia/Shanghai",
    "iso:country":"CN",
    "name:und_x_variant":[
        "\u53f8\u524d"
    ],
    "wof:name":"Siqian",
    "wof:placetype":"locality"
},
  "geometry": {"coordinates":[116.59359000000001,27.08597],"type":"Point"}
}