{
  "type": "Feature",
  "properties": {
    "gn:admin1_code":"26.0",
    "gn:asciiname":"Huangmaocun",
    "gn:country_code":"CN",
    "gn:dem":413,
    "gn:feature_class":"P",
    "gn:feature_code":"PPL",
    "gn:name":"Huangmaocun",
    "gn:population":0,
    "gn:timezone":"Asia/Shanghai",
    "iso:country":"CN",
    "name:zho_x_preferred":[
        "\u9ec4\u6bdb\u6751"
    ],
    "wof:name":"Huangmaocun",
    "wof:placetype":"locality"
},
  "geometry": {"coordinates":[108.98016,34.61021],"type":"Point"}
}