{
  "type": "Feature",
  "properties": {
    "gn:admin1_code":"26.0",
    "gn:asciiname":"Baipingcun",
    "gn:country_code":"CN",
    "gn:dem":1022,
    "gn:feature_class":"P",
    "gn:feature_code":"PPL",
    "gn:name":"Baipingcun",
    "gn:population":0,
    "gn:timezone":"Asia/Shanghai",
    "iso:country":"CN",
    "name:zho_x_preferred":[
        "\u767d\u576a\u6751"
    ],
    "wof:name":"Baipingcun",
    "wof:placetype":"locality"
},
  "geometry": {"coordinates":[109.64134,36.75304000000001],"type":"Point"}
}