{
  "type": "Feature",
  "properties": {
    "gn:admin1_code":"11.0",
    "gn:asciiname":"Xiaoshuiwan",
    "gn:country_code":"CN",
    "gn:dem":303,
    "gn:feature_class":"P",
    "gn:feature_code":"PPL",
    "gn:name":"Xiaoshuiwan",
    "gn:population":0,
    "gn:timezone":"Asia/Shanghai",
    "iso:country":"CN",
    "name:zho_x_preferred":[
        "\u6d88\u6c34\u6e7e"
    ],
    "wof:name":"Xiaoshuiwan",
    "wof:placetype":"locality"
},
  "geometry": {"coordinates":[110.12690000000001,27.53224],"type":"Point"}
}