{
  "type": "Feature",
  "properties": {
    "gn:admin1_code":"5.0",
    "gn:asciiname":"Xiajia Buzii",
    "gn:country_code":"CN",
    "gn:dem":181,
    "gn:feature_class":"P",
    "gn:feature_code":"PPL",
    "gn:name":"Xiajia Buzii",
    "gn:population":0,
    "gn:timezone":"Asia/Shanghai",
    "iso:country":"CN",
    "name:zho_x_preferred":[
        "\u590f\u5bb6\u5821\u5b50"
    ],
    "wof:name":"Xiajia Buzii",
    "wof:placetype":"locality"
},
  "geometry": {"coordinates":[124.37859,43.30094],"type":"Point"}
}