{
  "type": "Feature",
  "properties": {
    "gn:admin1_code":"30.0",
    "gn:asciiname":"Xiazhaicun",
    "gn:country_code":"CN",
    "gn:dem":8,
    "gn:feature_class":"P",
    "gn:feature_code":"PPL",
    "gn:name":"Xiazhaicun",
    "gn:population":0,
    "gn:timezone":"Asia/Shanghai",
    "iso:country":"CN",
    "name:zho_x_preferred":[
        "\u4e0b\u5be8\u6751"
    ],
    "wof:name":"Xiazhaicun",
    "wof:placetype":"locality"
},
  "geometry": {"coordinates":[116.25279999999999,23.30138],"type":"Point"}
}