{
  "type": "Feature",
  "properties": {
    "gn:admin1_code":"4.0",
    "gn:asciiname":"Huazhuang",
    "gn:country_code":"CN",
    "gn:dem":8,
    "gn:feature_class":"P",
    "gn:feature_code":"PPL",
    "gn:name":"Huazhuang",
    "gn:population":0,
    "gn:timezone":"Asia/Shanghai",
    "iso:country":"CN",
    "name:und_x_variant":[
        "\u82b1\u5e84"
    ],
    "name:zho_x_preferred":[
        "\u82b1\u5e84"
    ],
    "wof:name":"Huazhuang",
    "wof:placetype":"locality"
},
  "geometry": {"coordinates":[120.30826,31.27184],"type":"Point"}
}