{
  "type": "Feature",
  "properties": {
    "gn:admin1_code":"4.0",
    "gn:asciiname":"Jiuxiancun",
    "gn:country_code":"CN",
    "gn:dem":12,
    "gn:feature_class":"P",
    "gn:feature_code":"PPL",
    "gn:name":"Jiuxiancun",
    "gn:population":0,
    "gn:timezone":"Asia/Shanghai",
    "iso:country":"CN",
    "name:und_x_variant":[
        "Jiuxian",
        "Jiuxiancun"
    ],
    "name:zho_x_preferred":[
        "\u65e7\u53bf"
    ],
    "name:zho_x_variant":[
        "\u65e7\u53bf\u6751"
    ],
    "wof:name":"Jiuxiancun",
    "wof:placetype":"locality"
},
  "geometry": {"coordinates":[119.31106,31.48128],"type":"Point"}
}