{
  "type": "Feature",
  "properties": {
    "gn:admin1_code":"19.0",
    "gn:asciiname":"Zhouweizi",
    "gn:country_code":"CN",
    "gn:dem":27,
    "gn:feature_class":"P",
    "gn:feature_code":"PPL",
    "gn:name":"Zhouweizi",
    "gn:population":0,
    "gn:timezone":"Asia/Shanghai",
    "iso:country":"CN",
    "name:und_x_variant":[
        "\u5468\u5d34\u5b50"
    ],
    "wof:name":"Zhouweizi",
    "wof:placetype":"locality"
},
  "geometry": {"coordinates":[122.21647,40.27183],"type":"Point"}
}