{
  "type": "Feature",
  "properties": {
    "gn:admin1_code":"33.0",
    "gn:asciiname":"Yongle",
    "gn:country_code":"CN",
    "gn:dem":594,
    "gn:feature_class":"P",
    "gn:feature_code":"PPLA4",
    "gn:name":"Yongle",
    "gn:population":0,
    "gn:timezone":"Asia/Shanghai",
    "iso:country":"CN",
    "name:und_x_variant":[
        "Yongle Zhen"
    ],
    "name:zho_x_preferred":[
        "\u6c38\u4e50"
    ],
    "name:zho_x_variant":[
        "\u6c38\u4e50\u9547"
    ],
    "wof:name":"Yongle",
    "wof:placetype":"locality"
},
  "geometry": {"coordinates":[109.50479,31.01048],"type":"Point"}
}