{
  "type": "Feature",
  "properties": {
    "gn:admin1_code":"4.0",
    "gn:asciiname":"Yexinzhuang",
    "gn:country_code":"CN",
    "gn:dem":18,
    "gn:feature_class":"P",
    "gn:feature_code":"PPL",
    "gn:name":"Yexinzhuang",
    "gn:population":0,
    "gn:timezone":"Asia/Shanghai",
    "iso:country":"CN",
    "name:zho_x_preferred":[
        "\u53f6\u65b0\u5e84"
    ],
    "wof:name":"Yexinzhuang",
    "wof:placetype":"locality"
},
  "geometry": {"coordinates":[118.60155,34.13462],"type":"Point"}
}