{
  "type": "Feature",
  "properties": {
    "gn:admin1_code":"1.0",
    "gn:asciiname":"Yingjia Citang",
    "gn:country_code":"CN",
    "gn:dem":32,
    "gn:feature_class":"P",
    "gn:feature_code":"PPL",
    "gn:name":"Yingjia Citang",
    "gn:population":0,
    "gn:timezone":"Asia/Shanghai",
    "iso:country":"CN",
    "name:zho_x_preferred":[
        "\u82f1\u5bb6\u7960\u5802"
    ],
    "wof:name":"Yingjia Citang",
    "wof:placetype":"locality"
},
  "geometry": {"coordinates":[116.74509999999999,29.63006],"type":"Point"}
}