{
  "type": "Feature",
  "properties": {
    "gn:admin1_code":"9.0",
    "gn:asciiname":"Sandaoling",
    "gn:country_code":"CN",
    "gn:dem":413,
    "gn:feature_class":"P",
    "gn:feature_code":"PPL",
    "gn:name":"Sandaoling",
    "gn:population":0,
    "gn:timezone":"Asia/Shanghai",
    "iso:country":"CN",
    "name:und_x_variant":[
        "\u4e09\u9053\u5cad",
        "Sandaoling"
    ],
    "wof:name":"Sandaoling",
    "wof:placetype":"locality"
},
  "geometry": {"coordinates":[112.10963,33.55172],"type":"Point"}
}