{
  "type": "Feature",
  "properties": {
    "gn:admin1_code":"8.0",
    "gn:asciiname":"Chaoyang Linchang",
    "gn:country_code":"CN",
    "gn:dem":406,
    "gn:feature_class":"P",
    "gn:feature_code":"PPLF",
    "gn:name":"Chaoyang Linchang",
    "gn:population":0,
    "gn:timezone":"Asia/Shanghai",
    "iso:country":"CN",
    "name:zho_x_preferred":[
        "\u671d\u9633\u6797\u573a"
    ],
    "wof:name":"Chaoyang Linchang",
    "wof:placetype":"locality"
},
  "geometry": {"coordinates":[127.62103,47.97695],"type":"Point"}
}