{
  "type": "Feature",
  "properties": {
    "gn:admin1_code":"18.0",
    "gn:asciiname":"Baiba",
    "gn:country_code":"CN",
    "gn:dem":665,
    "gn:feature_class":"P",
    "gn:feature_code":"PPL",
    "gn:name":"Baiba",
    "gn:population":0,
    "gn:timezone":"Asia/Shanghai",
    "iso:country":"CN",
    "name:deu_x_preferred":[
        "Baiba"
    ],
    "name:zho_x_preferred":[
        "\u6446\u628a"
    ],
    "wof:name":"Baiba",
    "wof:placetype":"locality"
},
  "geometry": {"coordinates":[108.57299999999999,25.69],"type":"Point"}
}