{
  "type": "Feature",
  "properties": {
    "gn:admin1_code":"14.0",
    "gn:asciiname":"Penggang",
    "gn:country_code":"CN",
    "gn:dem":3999,
    "gn:feature_class":"P",
    "gn:feature_code":"PPL",
    "gn:name":"Penggang",
    "gn:population":0,
    "gn:timezone":"Asia/Urumqi",
    "iso:country":"CN",
    "name:zho_x_preferred":[
        "\u670b\u5c97"
    ],
    "wof:name":"Penggang",
    "wof:placetype":"locality"
},
  "geometry": {"coordinates":[91.53400000000001,30.09481],"type":"Point"}
}