{
  "type": "Feature",
  "properties": {
    "gn:admin1_code":"9",
    "gn:asciiname":"Xuyanggou",
    "gn:country_code":"CN",
    "gn:dem":59,
    "gn:feature_class":"P",
    "gn:feature_code":"PPL",
    "gn:name":"Xuyanggou",
    "gn:population":0,
    "gn:timezone":"Asia/Shanghai",
    "iso:country":"CN",
    "name:zho_x_preferred":[
        "\u5f90\u9633\u6c9f"
    ],
    "wof:name":"Xuyanggou",
    "wof:placetype":"locality"
},
  "geometry": {"coordinates":[115.101,34.3309],"type":"Point"}
}