{
  "type": "Feature",
  "properties": {
    "gn:admin1_code":"7.0",
    "gn:asciiname":"Jiuxian",
    "gn:country_code":"CN",
    "gn:dem":261,
    "gn:feature_class":"P",
    "gn:feature_code":"PPL",
    "gn:name":"Jiuxian",
    "gn:population":0,
    "gn:timezone":"Asia/Shanghai",
    "iso:country":"CN",
    "name:ceb_x_preferred":[
        "Jiuxian"
    ],
    "name:deu_x_preferred":[
        "Jiuxian"
    ],
    "name:swe_x_preferred":[
        "Jiuxian"
    ],
    "name:zho_x_preferred":[
        "\u4e5d\u4ed9"
    ],
    "wof:name":"Jiuxian",
    "wof:placetype":"locality"
},
  "geometry": {"coordinates":[119.44826,26.82602],"type":"Point"}
}