{
  "type": "Feature",
  "properties": {
    "gn:admin1_code":"24.0",
    "gn:asciiname":"Jiugaoshan",
    "gn:country_code":"CN",
    "gn:dem":1249,
    "gn:feature_class":"P",
    "gn:feature_code":"PPL",
    "gn:name":"Jiugaoshan",
    "gn:population":0,
    "gn:timezone":"Asia/Shanghai",
    "iso:country":"CN",
    "name:zho_x_preferred":[
        "\u65e7\u9ad8\u5c71"
    ],
    "wof:name":"Jiugaoshan",
    "wof:placetype":"locality"
},
  "geometry": {"coordinates":[112.88948000000001,40.08674],"type":"Point"}
}