{
  "type": "Feature",
  "properties": {
    "gn:admin1_code":"9.0",
    "gn:asciiname":"Jiangxicun",
    "gn:country_code":"CN",
    "gn:dem":70,
    "gn:feature_class":"P",
    "gn:feature_code":"PPL",
    "gn:name":"Jiangxicun",
    "gn:population":0,
    "gn:timezone":"Asia/Shanghai",
    "iso:country":"CN",
    "name:zho_x_preferred":[
        "\u848b\u897f\u6751"
    ],
    "wof:name":"Jiangxicun",
    "wof:placetype":"locality"
},
  "geometry": {"coordinates":[114.40904999999999,35.22063],"type":"Point"}
}