{
  "type": "Feature",
  "properties": {
    "gn:admin1_code":"19.0",
    "gn:asciiname":"Houliangzi",
    "gn:country_code":"CN",
    "gn:dem":26,
    "gn:feature_class":"P",
    "gn:feature_code":"PPL",
    "gn:name":"Houliangzi",
    "gn:population":0,
    "gn:timezone":"Asia/Shanghai",
    "iso:country":"CN",
    "name:zho_x_preferred":[
        "\u540e\u4eae\u5b50"
    ],
    "wof:name":"Houliangzi",
    "wof:placetype":"locality"
},
  "geometry": {"coordinates":[121.306,39.4487],"type":"Point"}
}