{
  "type": "Feature",
  "properties": {
    "gn:admin1_code":"32.0",
    "gn:asciiname":"Zhanjianian",
    "gn:country_code":"CN",
    "gn:dem":499,
    "gn:feature_class":"P",
    "gn:feature_code":"PPL",
    "gn:name":"Zhanjianian",
    "gn:population":0,
    "gn:timezone":"Asia/Shanghai",
    "iso:country":"CN",
    "name:zho_x_preferred":[
        "\u8a79\u5bb6\u78be"
    ],
    "wof:name":"Zhanjianian",
    "wof:placetype":"locality"
},
  "geometry": {"coordinates":[103.92,30.6077],"type":"Point"}
}