{
  "type": "Feature",
  "properties": {
    "gn:admin1_code":"4.0",
    "gn:asciiname":"Feiquancun",
    "gn:country_code":"CN",
    "gn:dem":4,
    "gn:feature_class":"P",
    "gn:feature_code":"PPL",
    "gn:name":"Feiquancun",
    "gn:population":0,
    "gn:timezone":"Asia/Shanghai",
    "iso:country":"CN",
    "name:zho_x_preferred":[
        "\u98de\u6cc9\u6751"
    ],
    "wof:name":"Feiquancun",
    "wof:placetype":"locality"
},
  "geometry": {"coordinates":[119.23714,34.64138],"type":"Point"}
}