{
  "type": "Feature",
  "properties": {
    "gn:admin1_code":"9.0",
    "gn:asciiname":"Silizhuang",
    "gn:country_code":"CN",
    "gn:dem":220,
    "gn:feature_class":"P",
    "gn:feature_code":"PPL",
    "gn:name":"Silizhuang",
    "gn:population":0,
    "gn:timezone":"Asia/Shanghai",
    "iso:country":"CN",
    "name:und_x_variant":[
        "\u56db\u91cc\u5e84",
        "Silizhuang"
    ],
    "wof:name":"Silizhuang",
    "wof:placetype":"locality"
},
  "geometry": {"coordinates":[112.23878999999999,33.07111],"type":"Point"}
}