{
  "type": "Feature",
  "properties": {
    "gn:admin1_code":"3.0",
    "gn:asciiname":"Dianqian Shangpai",
    "gn:country_code":"CN",
    "gn:dem":89,
    "gn:feature_class":"P",
    "gn:feature_code":"PPL",
    "gn:name":"Dianqian Shangpai",
    "gn:population":0,
    "gn:timezone":"Asia/Shanghai",
    "iso:country":"CN",
    "name:zho_x_preferred":[
        "\u5e97\u524d\u4e0a\u6392"
    ],
    "wof:name":"Dianqian Shangpai",
    "wof:placetype":"locality"
},
  "geometry": {"coordinates":[117.23219,28.05838],"type":"Point"}
}