{
  "type": "Feature",
  "properties": {
    "gn:admin1_code":"26.0",
    "gn:asciiname":"Qianmeijiapingcun",
    "gn:country_code":"CN",
    "gn:dem":948,
    "gn:feature_class":"P",
    "gn:feature_code":"PPL",
    "gn:name":"Qianmeijiapingcun",
    "gn:population":0,
    "gn:timezone":"Asia/Shanghai",
    "iso:country":"CN",
    "name:zho_x_preferred":[
        "\u524d\u6885\u5bb6\u576a\u6751"
    ],
    "wof:name":"Qianmeijiapingcun",
    "wof:placetype":"locality"
},
  "geometry": {"coordinates":[110.25570999999999,37.11954],"type":"Point"}
}