{
  "type": "Feature",
  "properties": {
    "gn:admin1_code":"24.0",
    "gn:asciiname":"Qianyingwoshan",
    "gn:country_code":"CN",
    "gn:dem":1391,
    "gn:feature_class":"P",
    "gn:feature_code":"PPL",
    "gn:name":"Qianyingwoshan",
    "gn:population":0,
    "gn:timezone":"Asia/Shanghai",
    "iso:country":"CN",
    "name:zho_x_preferred":[
        "\u524d\u9e70\u5367\u5c71"
    ],
    "wof:name":"Qianyingwoshan",
    "wof:placetype":"locality"
},
  "geometry": {"coordinates":[112.26822,40.03607],"type":"Point"}
}