{
  "type": "Feature",
  "properties": {
    "gn:admin1_code":"18",
    "gn:asciiname":"Hehe",
    "gn:country_code":"CN",
    "gn:dem":2113,
    "gn:feature_class":"P",
    "gn:feature_code":"PPL",
    "gn:name":"Hehe",
    "gn:population":0,
    "gn:timezone":"Asia/Shanghai",
    "iso:country":"CN",
    "name:zho_x_preferred":[
        "\u6cb3\u5475"
    ],
    "wof:name":"Hehe",
    "wof:placetype":"locality"
},
  "geometry": {"coordinates":[104.58,27.2839],"type":"Point"}
}