{
  "type": "Feature",
  "properties": {
    "gn:admin1_code":"9.0",
    "gn:asciiname":"Baozigou",
    "gn:country_code":"CN",
    "gn:dem":1031,
    "gn:feature_class":"P",
    "gn:feature_code":"PPL",
    "gn:name":"Baozigou",
    "gn:population":0,
    "gn:timezone":"Asia/Shanghai",
    "iso:country":"CN",
    "name:und_x_variant":[
        "\u8c79\u5b50\u6c9f",
        "Baozigou"
    ],
    "wof:name":"Baozigou",
    "wof:placetype":"locality"
},
  "geometry": {"coordinates":[112.31903,33.87090999999999],"type":"Point"}
}