{
  "type": "Feature",
  "properties": {
    "gn:admin1_code":"11.0",
    "gn:asciiname":"Wujia Yuanzi",
    "gn:country_code":"CN",
    "gn:dem":1182,
    "gn:feature_class":"P",
    "gn:feature_code":"PPL",
    "gn:name":"Wujia Yuanzi",
    "gn:population":0,
    "gn:timezone":"Asia/Shanghai",
    "iso:country":"CN",
    "name:zho_x_preferred":[
        "\u6b66\u5bb6\u9662\u5b50"
    ],
    "wof:name":"Wujia Yuanzi",
    "wof:placetype":"locality"
},
  "geometry": {"coordinates":[110.65066000000002,27.49661],"type":"Point"}
}