{
  "type": "Feature",
  "properties": {
    "gn:admin1_code":"18.0",
    "gn:asciiname":"Jianxinhe",
    "gn:country_code":"CN",
    "gn:dem":1618,
    "gn:feature_class":"P",
    "gn:feature_code":"PPL",
    "gn:name":"Jianxinhe",
    "gn:population":0,
    "gn:timezone":"Asia/Shanghai",
    "iso:country":"CN",
    "name:zho_x_preferred":[
        "\u5efa\u65b0\u6cb3"
    ],
    "wof:name":"Jianxinhe",
    "wof:placetype":"locality"
},
  "geometry": {"coordinates":[105.09166999999999,26.86667000000001],"type":"Point"}
}