{
  "type": "Feature",
  "properties": {
    "gn:admin1_code":"23.0",
    "gn:asciiname":"Yonglong",
    "gn:country_code":"CN",
    "gn:dem":2,
    "gn:feature_class":"P",
    "gn:feature_code":"PPL",
    "gn:name":"Yonglong",
    "gn:population":0,
    "gn:timezone":"Asia/Shanghai",
    "iso:country":"CN",
    "name:swe_x_preferred":[
        "Yonglong"
    ],
    "name:zho_x_preferred":[
        "Yonglong"
    ],
    "name:zho_x_variant":[
        "\u6c38\u9686"
    ],
    "wof:name":"Yonglong",
    "wof:placetype":"locality"
},
  "geometry": {"coordinates":[121.80634000000001,31.55658],"type":"Point"}
}