{
  "type": "Feature",
  "properties": {
    "gn:admin1_code":"26.0",
    "gn:asciiname":"Fangjiagou",
    "gn:country_code":"CN",
    "gn:dem":1222,
    "gn:feature_class":"P",
    "gn:feature_code":"PPL",
    "gn:name":"Fangjiagou",
    "gn:population":0,
    "gn:timezone":"Asia/Shanghai",
    "iso:country":"CN",
    "name:und_x_variant":[
        "\u623f\u5bb6\u6c9f"
    ],
    "wof:name":"Fangjiagou",
    "wof:placetype":"locality"
},
  "geometry": {"coordinates":[107.33414999999999,34.93002],"type":"Point"}
}