{
  "type": "Feature",
  "properties": {
    "gn:admin1_code":"8.0",
    "gn:asciiname":"Bashiyi",
    "gn:country_code":"CN",
    "gn:dem":264,
    "gn:feature_class":"P",
    "gn:feature_code":"PPL",
    "gn:name":"Bashiyi",
    "gn:population":0,
    "gn:timezone":"Asia/Shanghai",
    "iso:country":"CN",
    "name:zho_x_preferred":[
        "\u516b\u5341\u4e00"
    ],
    "wof:name":"Bashiyi",
    "wof:placetype":"locality"
},
  "geometry": {"coordinates":[128.99509,45.4196],"type":"Point"}
}