{
  "type": "Feature",
  "properties": {
    "gn:admin1_code":"8.0",
    "gn:asciiname":"Lanfengcun",
    "gn:country_code":"CN",
    "gn:dem":98,
    "gn:feature_class":"P",
    "gn:feature_code":"PPL",
    "gn:name":"Lanfengcun",
    "gn:population":0,
    "gn:timezone":"Asia/Shanghai",
    "iso:country":"CN",
    "name:zho_x_preferred":[
        "\u5170\u51e4\u6751"
    ],
    "wof:name":"Lanfengcun",
    "wof:placetype":"locality"
},
  "geometry": {"coordinates":[131.84163000000001,46.55383],"type":"Point"}
}