{
  "type": "Feature",
  "properties": {
    "gn:admin1_code":"9.0",
    "gn:asciiname":"Ouchiren",
    "gn:country_code":"CN",
    "gn:dem":86,
    "gn:feature_class":"P",
    "gn:feature_code":"PPL",
    "gn:name":"Ouchiren",
    "gn:population":0,
    "gn:timezone":"Asia/Shanghai",
    "iso:country":"CN",
    "name:zho_x_preferred":[
        "\u85d5\u6c60\u4efb"
    ],
    "wof:name":"Ouchiren",
    "wof:placetype":"locality"
},
  "geometry": {"coordinates":[114.07687,34.52404],"type":"Point"}
}