{
  "type": "Feature",
  "properties": {
    "gn:admin1_code":"8.0",
    "gn:asciiname":"Zhanjiatun",
    "gn:country_code":"CN",
    "gn:dem":150,
    "gn:feature_class":"P",
    "gn:feature_code":"PPL",
    "gn:name":"Zhanjiatun",
    "gn:population":0,
    "gn:timezone":"Asia/Shanghai",
    "iso:country":"CN",
    "name:zho_x_preferred":[
        "\u8a79\u5bb6\u5c6f"
    ],
    "wof:name":"Zhanjiatun",
    "wof:placetype":"locality"
},
  "geometry": {"coordinates":[127.84784000000001,46.3477],"type":"Point"}
}