{
  "type": "Feature",
  "properties": {
    "gn:admin1_code":"11.0",
    "gn:asciiname":"Menjiatang",
    "gn:country_code":"CN",
    "gn:dem":49,
    "gn:feature_class":"P",
    "gn:feature_code":"PPL",
    "gn:name":"Menjiatang",
    "gn:population":0,
    "gn:timezone":"Asia/Shanghai",
    "iso:country":"CN",
    "name:zho_x_preferred":[
        "\u95e8\u5bb6\u5858"
    ],
    "wof:name":"Menjiatang",
    "wof:placetype":"locality"
},
  "geometry": {"coordinates":[113.18015,28.75729],"type":"Point"}
}