{
  "type": "Feature",
  "properties": {
    "gn:admin1_code":"6.0",
    "gn:asciiname":"Duowa",
    "gn:country_code":"CN",
    "gn:dem":2799,
    "gn:feature_class":"P",
    "gn:feature_code":"PPL",
    "gn:name":"Duowa",
    "gn:population":0,
    "gn:timezone":"Asia/Shanghai",
    "iso:country":"CN",
    "name:zho_x_preferred":[
        "\u591a\u54c7"
    ],
    "wof:name":"Duowa",
    "wof:placetype":"locality"
},
  "geometry": {"coordinates":[101.32885,35.85825],"type":"Point"}
}