{
  "type": "Feature",
  "properties": {
    "gn:admin1_code":"3.0",
    "gn:asciiname":"Lanwuba",
    "gn:country_code":"CN",
    "gn:dem":129,
    "gn:feature_class":"P",
    "gn:feature_code":"PPL",
    "gn:name":"Lanwuba",
    "gn:population":0,
    "gn:timezone":"Asia/Shanghai",
    "iso:country":"CN",
    "name:und_x_variant":[
        "\u5170\u5c4b\u575d"
    ],
    "wof:name":"Lanwuba",
    "wof:placetype":"locality"
},
  "geometry": {"coordinates":[115.34678,25.94319],"type":"Point"}
}