{
  "type": "Feature",
  "properties": {
    "gn:admin1_code":"11",
    "gn:asciiname":"Shigonglao",
    "gn:country_code":"CN",
    "gn:dem":751,
    "gn:feature_class":"P",
    "gn:feature_code":"PPL",
    "gn:name":"Shigonglao",
    "gn:population":0,
    "gn:timezone":"Asia/Shanghai",
    "iso:country":"CN",
    "name:zho_x_preferred":[
        "\u5e08\u516c\u8001"
    ],
    "wof:name":"Shigonglao",
    "wof:placetype":"locality"
},
  "geometry": {"coordinates":[111.46567,25.95129],"type":"Point"}
}