{
  "type": "Feature",
  "properties": {
    "gn:admin1_code":"26.0",
    "gn:asciiname":"Xiqiaojiancun",
    "gn:country_code":"CN",
    "gn:dem":1563,
    "gn:feature_class":"P",
    "gn:feature_code":"PPL",
    "gn:name":"Xiqiaojiancun",
    "gn:population":0,
    "gn:timezone":"Asia/Shanghai",
    "iso:country":"CN",
    "name:zho_x_preferred":[
        "\u897f\u6865\u6da7\u6751"
    ],
    "wof:name":"Xiqiaojiancun",
    "wof:placetype":"locality"
},
  "geometry": {"coordinates":[108.53652,37.36259],"type":"Point"}
}