{
  "type": "Feature",
  "properties": {
    "gn:admin1_code":"8.0",
    "gn:asciiname":"Zhouzhuotun",
    "gn:country_code":"CN",
    "gn:dem":123,
    "gn:feature_class":"P",
    "gn:feature_code":"PPL",
    "gn:name":"Zhouzhuotun",
    "gn:population":0,
    "gn:timezone":"Asia/Shanghai",
    "iso:country":"CN",
    "name:zho_x_preferred":[
        "\u5468\u7422\u5c6f"
    ],
    "wof:name":"Zhouzhuotun",
    "wof:placetype":"locality"
},
  "geometry": {"coordinates":[127.29819000000001,46.17887],"type":"Point"}
}