{
  "type": "Feature",
  "properties": {
    "gn:admin1_code":"2.0",
    "gn:asciiname":"Tianyangli",
    "gn:country_code":"CN",
    "gn:dem":7,
    "gn:feature_class":"P",
    "gn:feature_code":"PPL",
    "gn:name":"Tianyangli",
    "gn:population":0,
    "gn:timezone":"Asia/Shanghai",
    "iso:country":"CN",
    "name:zho_x_preferred":[
        "\u7530\u6d0b\u91cc"
    ],
    "wof:name":"Tianyangli",
    "wof:placetype":"locality"
},
  "geometry": {"coordinates":[121.90527,29.47348],"type":"Point"}
}