{
  "type": "Feature",
  "properties": {
    "gn:admin1_code":"14.0",
    "gn:asciiname":"Niuchang",
    "gn:country_code":"CN",
    "gn:dem":4191,
    "gn:feature_class":"P",
    "gn:feature_code":"PPLF",
    "gn:name":"Niuchang",
    "gn:population":0,
    "gn:timezone":"Asia/Urumqi",
    "iso:country":"CN",
    "name:zho_x_preferred":[
        "\u725b\u573a"
    ],
    "wof:name":"Niuchang",
    "wof:placetype":"locality"
},
  "geometry": {"coordinates":[98.30371,30.33114],"type":"Point"}
}