{
  "type": "Feature",
  "properties": {
    "gn:admin1_code":"16.0",
    "gn:asciiname":"Longyao",
    "gn:country_code":"CN",
    "gn:dem":960,
    "gn:feature_class":"P",
    "gn:feature_code":"PPL",
    "gn:name":"Longyao",
    "gn:population":0,
    "gn:timezone":"Asia/Shanghai",
    "iso:country":"CN",
    "name:zho_x_preferred":[
        "\u9647\u5c27"
    ],
    "wof:name":"Longyao",
    "wof:placetype":"locality"
},
  "geometry": {"coordinates":[106.81,24.5873],"type":"Point"}
}