{
  "type": "Feature",
  "properties": {
    "gn:admin1_code":"22",
    "gn:asciiname":"Changgouyu",
    "gn:country_code":"CN",
    "gn:dem":318,
    "gn:feature_class":"P",
    "gn:feature_code":"PPL",
    "gn:name":"Changgouyu",
    "gn:population":0,
    "gn:timezone":"Asia/Shanghai",
    "iso:country":"CN",
    "name:und_x_variant":[
        "Ch\u2019ang-kou-y\u00fc",
        "Changgouyu"
    ],
    "name:zho_x_preferred":[
        "\u957f\u6c9f\u5cea"
    ],
    "wof:name":"Changgouyu",
    "wof:placetype":"locality"
},
  "geometry": {"coordinates":[115.88251,39.72402],"type":"Point"}
}