{
  "type": "Feature",
  "properties": {
    "gn:admin1_code":"30.0",
    "gn:asciiname":"Guishan",
    "gn:country_code":"CN",
    "gn:dem":262,
    "gn:feature_class":"P",
    "gn:feature_code":"PPL",
    "gn:name":"Guishan",
    "gn:population":0,
    "gn:timezone":"Asia/Shanghai",
    "iso:country":"CN",
    "name:deu_x_preferred":[
        "Guishan"
    ],
    "name:kor_x_preferred":[
        "\uad6c\uc774\uc0b0"
    ],
    "name:und_x_variant":[
        "\u6842\u5c71"
    ],
    "name:zho_x_preferred":[
        "\u6842\u5c71"
    ],
    "wof:name":"Guishan",
    "wof:placetype":"locality"
},
  "geometry": {"coordinates":[115.26067999999999,23.44704],"type":"Point"}
}