{
  "type": "Feature",
  "properties": {
    "gn:admin1_code":"4.0",
    "gn:asciiname":"Xiaobuzicun",
    "gn:country_code":"CN",
    "gn:dem":34,
    "gn:feature_class":"P",
    "gn:feature_code":"PPL",
    "gn:name":"Xiaobuzicun",
    "gn:population":0,
    "gn:timezone":"Asia/Shanghai",
    "iso:country":"CN",
    "name:zho_x_preferred":[
        "\u5c0f\u57e0\u5b50\u6751"
    ],
    "wof:name":"Xiaobuzicun",
    "wof:placetype":"locality"
},
  "geometry": {"coordinates":[118.75848000000001,34.78332],"type":"Point"}
}