{
  "type": "Feature",
  "properties": {
    "gn:admin1_code":"10",
    "gn:asciiname":"Xicha",
    "gn:country_code":"CN",
    "gn:dem":533,
    "gn:feature_class":"P",
    "gn:feature_code":"PPL",
    "gn:name":"Xicha",
    "gn:population":0,
    "gn:timezone":"Asia/Shanghai",
    "iso:country":"CN",
    "name:zho_x_preferred":[
        "\u897f\u5c94"
    ],
    "wof:name":"Xicha",
    "wof:placetype":"locality"
},
  "geometry": {"coordinates":[118.38885999999999,40.95039000000001],"type":"Point"}
}