{
  "type": "Feature",
  "properties": {
    "gn:admin1_code":"32.0",
    "gn:asciiname":"Wukan",
    "gn:country_code":"CN",
    "gn:dem":616,
    "gn:feature_class":"P",
    "gn:feature_code":"PPL",
    "gn:name":"Wukan",
    "gn:population":0,
    "gn:timezone":"Asia/Shanghai",
    "iso:country":"CN",
    "name:deu_x_preferred":[
        "Wukan"
    ],
    "name:epo_x_preferred":[
        "Wukan"
    ],
    "name:fas_x_preferred":[
        "\u0648\u0648\u06a9\u0627\u0646"
    ],
    "name:zho_x_preferred":[
        "\u4f0d\u574e"
    ],
    "name:zho_x_variant":[
        "\u70cf\u574e\u6751"
    ],
    "wof:name":"Wukan",
    "wof:placetype":"locality"
},
  "geometry": {"coordinates":[103.467,29.5027],"type":"Point"}
}