{
  "type": "Feature",
  "properties": {
    "gn:admin1_code":"16.0",
    "gn:asciiname":"Xiahuai",
    "gn:country_code":"CN",
    "gn:dem":435,
    "gn:feature_class":"P",
    "gn:feature_code":"PPL",
    "gn:name":"Xiahuai",
    "gn:population":0,
    "gn:timezone":"Asia/Shanghai",
    "iso:country":"CN",
    "name:zho_x_preferred":[
        "\u4e0b\u6000"
    ],
    "name:zho_x_variant":[
        "\u4e0b\u69d0\u9547"
    ],
    "wof:name":"Xiahuai",
    "wof:placetype":"locality"
},
  "geometry": {"coordinates":[108.501,23.8495],"type":"Point"}
}