{
  "type": "Feature",
  "properties": {
    "gn:admin1_code":"25",
    "gn:asciiname":"Chongjiaobu",
    "gn:country_code":"CN",
    "gn:dem":9,
    "gn:feature_class":"P",
    "gn:feature_code":"PPL",
    "gn:name":"Chongjiaobu",
    "gn:population":0,
    "gn:timezone":"Asia/Shanghai",
    "iso:country":"CN",
    "name:zho_x_preferred":[
        "\u51b2\u89d2\u57e0"
    ],
    "wof:name":"Chongjiaobu",
    "wof:placetype":"locality"
},
  "geometry": {"coordinates":[120.08,36.4254],"type":"Point"}
}