{
  "type": "Feature",
  "properties": {
    "gn:admin1_code":"8.0",
    "gn:asciiname":"Yongqiangcun",
    "gn:country_code":"CN",
    "gn:dem":97,
    "gn:feature_class":"P",
    "gn:feature_code":"PPL",
    "gn:name":"Yongqiangcun",
    "gn:population":0,
    "gn:timezone":"Asia/Shanghai",
    "iso:country":"CN",
    "name:zho_x_preferred":[
        "\u6c38\u5f3a\u6751"
    ],
    "wof:name":"Yongqiangcun",
    "wof:placetype":"locality"
},
  "geometry": {"coordinates":[130.86043000000001,46.82648],"type":"Point"}
}