{
  "type": "Feature",
  "properties": {
    "gn:admin1_code":"1.0",
    "gn:asciiname":"Shangpakeng",
    "gn:country_code":"CN",
    "gn:dem":153,
    "gn:feature_class":"P",
    "gn:feature_code":"PPL",
    "gn:name":"Shangpakeng",
    "gn:population":0,
    "gn:timezone":"Asia/Shanghai",
    "iso:country":"CN",
    "name:zho_x_preferred":[
        "\u4e0a\u7436\u5751"
    ],
    "wof:name":"Shangpakeng",
    "wof:placetype":"locality"
},
  "geometry": {"coordinates":[118.61790999999999,29.90568],"type":"Point"}
}