{
  "type": "Feature",
  "properties": {
    "gn:admin1_code":"30",
    "gn:asciiname":"Da'an",
    "gn:country_code":"CN",
    "gn:dem":16,
    "gn:feature_class":"P",
    "gn:feature_code":"PPL",
    "gn:name":"Da\u2019an",
    "gn:population":0,
    "gn:timezone":"Asia/Shanghai",
    "iso:country":"CN",
    "name:zho_x_preferred":[
        "\u5927\u5b89"
    ],
    "name:zho_x_variant":[
        "Da\u2019an"
    ],
    "wof:name":"Da'an",
    "wof:placetype":"locality"
},
  "geometry": {"coordinates":[111.68935,21.88375],"type":"Point"}
}