{
  "type": "Feature",
  "properties": {
    "gn:admin1_code":"30.0",
    "gn:asciiname":"Jiaoxicun",
    "gn:country_code":"CN",
    "gn:dem":3,
    "gn:feature_class":"P",
    "gn:feature_code":"PPL",
    "gn:name":"Jiaoxicun",
    "gn:population":0,
    "gn:timezone":"Asia/Shanghai",
    "iso:country":"CN",
    "name:zho_x_preferred":[
        "\u89d2\u6eaa\u6751"
    ],
    "wof:name":"Jiaoxicun",
    "wof:placetype":"locality"
},
  "geometry": {"coordinates":[115.80754,22.78705],"type":"Point"}
}