{
  "type": "Feature",
  "properties": {
    "gn:admin1_code":"12.0",
    "gn:asciiname":"Fozuling",
    "gn:country_code":"CN",
    "gn:dem":238,
    "gn:feature_class":"P",
    "gn:feature_code":"PPL",
    "gn:name":"Fozuling",
    "gn:population":0,
    "gn:timezone":"Asia/Shanghai",
    "iso:country":"CN",
    "name:zho_x_preferred":[
        "\u4f5b\u7956\u5cad"
    ],
    "wof:name":"Fozuling",
    "wof:placetype":"locality"
},
  "geometry": {"coordinates":[115.29459,31.25119],"type":"Point"}
}