{
  "type": "Feature",
  "properties": {
    "gn:admin1_code":"19.0",
    "gn:asciiname":"Jinkeng Houpo",
    "gn:country_code":"CN",
    "gn:dem":204,
    "gn:feature_class":"P",
    "gn:feature_code":"PPL",
    "gn:name":"Jinkeng Houpo",
    "gn:population":0,
    "gn:timezone":"Asia/Shanghai",
    "iso:country":"CN",
    "name:zho_x_preferred":[
        "\u91d1\u5751\u540e\u5761"
    ],
    "wof:name":"Jinkeng Houpo",
    "wof:placetype":"locality"
},
  "geometry": {"coordinates":[123.72,41.1402],"type":"Point"}
}