{
  "type": "Feature",
  "properties": {
    "gn:admin1_code":"25",
    "gn:asciiname":"Yuezi",
    "gn:country_code":"CN",
    "gn:dem":559,
    "gn:feature_class":"P",
    "gn:feature_code":"PPL",
    "gn:name":"Yuezi",
    "gn:population":0,
    "gn:timezone":"Asia/Shanghai",
    "iso:country":"CN",
    "name:zho_x_preferred":[
        "\u5cb3\u6ecb"
    ],
    "wof:name":"Yuezi",
    "wof:placetype":"locality"
},
  "geometry": {"coordinates":[117.31699999999999,36.4806],"type":"Point"}
}