{
  "type": "Feature",
  "properties": {
    "gn:admin1_code":"10.0",
    "gn:asciiname":"Damiaozhuang",
    "gn:country_code":"CN",
    "gn:dem":2,
    "gn:feature_class":"P",
    "gn:feature_code":"PPL",
    "gn:name":"Damiaozhuang",
    "gn:population":0,
    "gn:timezone":"Asia/Shanghai",
    "iso:country":"CN",
    "name:zho_x_preferred":[
        "\u5927\u82d7\u5e84"
    ],
    "wof:name":"Damiaozhuang",
    "wof:placetype":"locality"
},
  "geometry": {"coordinates":[118.95707,39.23223],"type":"Point"}
}