{
  "type": "Feature",
  "properties": {
    "gn:admin1_code":"30",
    "gn:asciiname":"Weikan",
    "gn:country_code":"CN",
    "gn:dem":15,
    "gn:feature_class":"P",
    "gn:feature_code":"PPL",
    "gn:name":"Weikan",
    "gn:population":0,
    "gn:timezone":"Asia/Urumqi",
    "iso:country":"CN",
    "name:zho_x_preferred":[
        "\u5c3e\u574e"
    ],
    "wof:name":"Weikan",
    "wof:placetype":"locality"
},
  "geometry": {"coordinates":[109.78449999999999,20.82897],"type":"Point"}
}