{
  "type": "Feature",
  "properties": {
    "gn:admin1_code":"24.0",
    "gn:asciiname":"Beizeli",
    "gn:country_code":"CN",
    "gn:dem":953,
    "gn:feature_class":"P",
    "gn:feature_code":"PPL",
    "gn:name":"Beizeli",
    "gn:population":0,
    "gn:timezone":"Asia/Shanghai",
    "iso:country":"CN",
    "name:zho_x_preferred":[
        "\u5317\u5219\u91cc"
    ],
    "wof:name":"Beizeli",
    "wof:placetype":"locality"
},
  "geometry": {"coordinates":[110.58393,36.66973],"type":"Point"}
}