{
  "type": "Feature",
  "properties": {
    "gn:admin1_code":"26.0",
    "gn:asciiname":"Luzhouping",
    "gn:country_code":"CN",
    "gn:dem":800,
    "gn:feature_class":"P",
    "gn:feature_code":"PPL",
    "gn:name":"Luzhouping",
    "gn:population":0,
    "gn:timezone":"Asia/Shanghai",
    "iso:country":"CN",
    "name:zho_x_preferred":[
        "\u788c\u78a1\u576a"
    ],
    "wof:name":"Luzhouping",
    "wof:placetype":"locality"
},
  "geometry": {"coordinates":[108.27701999999999,34.00225],"type":"Point"}
}