{
  "type": "Feature",
  "properties": {
    "gn:admin1_code":"2.0",
    "gn:asciiname":"Jielian",
    "gn:country_code":"CN",
    "gn:dem":102,
    "gn:feature_class":"P",
    "gn:feature_code":"PPL",
    "gn:name":"Jielian",
    "gn:population":0,
    "gn:timezone":"Asia/Shanghai",
    "iso:country":"CN",
    "name:und_x_variant":[
        "\u754c\u8054"
    ],
    "wof:name":"Jielian",
    "wof:placetype":"locality"
},
  "geometry": {"coordinates":[119.77649,30.11743],"type":"Point"}
}