{
  "type": "Feature",
  "properties": {
    "gn:admin1_code":"25",
    "gn:asciiname":"Gulonggang",
    "gn:country_code":"CN",
    "gn:dem":34,
    "gn:feature_class":"P",
    "gn:feature_code":"PPL",
    "gn:name":"Gulonggang",
    "gn:population":0,
    "gn:timezone":"Asia/Shanghai",
    "iso:country":"CN",
    "name:zho_x_preferred":[
        "\u53e4\u9f99\u5c97"
    ],
    "wof:name":"Gulonggang",
    "wof:placetype":"locality"
},
  "geometry": {"coordinates":[118.71899999999999,34.7356],"type":"Point"}
}