{
  "type": "Feature",
  "properties": {
    "gn:admin1_code":"24",
    "gn:asciiname":"Shimen",
    "gn:country_code":"CN",
    "gn:dem":1161,
    "gn:feature_class":"P",
    "gn:feature_code":"PPL",
    "gn:name":"Shimen",
    "gn:population":0,
    "gn:timezone":"Asia/Shanghai",
    "iso:country":"CN",
    "name:und_x_variant":[
        "Shih-men-ts\u2019un",
        "Shih-men",
        "Shimen"
    ],
    "name:zho_x_preferred":[
        "\u77f3\u95e8"
    ],
    "wof:name":"Shimen",
    "wof:placetype":"locality"
},
  "geometry": {"coordinates":[113.20865000000001,36.78021],"type":"Point"}
}