{
  "type": "Feature",
  "properties": {
    "gn:admin1_code":"11.0",
    "gn:asciiname":"Chaxiangling",
    "gn:country_code":"CN",
    "gn:dem":267,
    "gn:feature_class":"P",
    "gn:feature_code":"PPL",
    "gn:name":"Chaxiangling",
    "gn:population":0,
    "gn:timezone":"Asia/Shanghai",
    "iso:country":"CN",
    "name:zho_x_preferred":[
        "\u8336\u76f8\u5cad"
    ],
    "wof:name":"Chaxiangling",
    "wof:placetype":"locality"
},
  "geometry": {"coordinates":[111.73493999999999,27.02286],"type":"Point"}
}