{
  "type": "Feature",
  "properties": {
    "gn:admin1_code":"1.0",
    "gn:asciiname":"Baopingcun",
    "gn:country_code":"CN",
    "gn:dem":337,
    "gn:feature_class":"P",
    "gn:feature_code":"PPL",
    "gn:name":"Baopingcun",
    "gn:population":0,
    "gn:timezone":"Asia/Shanghai",
    "iso:country":"CN",
    "name:zho_x_preferred":[
        "\u5b9d\u576a\u6751"
    ],
    "wof:name":"Baopingcun",
    "wof:placetype":"locality"
},
  "geometry": {"coordinates":[115.79572,30.73852],"type":"Point"}
}