{
  "type": "Feature",
  "properties": {
    "gn:admin1_code":"9.0",
    "gn:asciiname":"Daguogou",
    "gn:country_code":"CN",
    "gn:dem":668,
    "gn:feature_class":"P",
    "gn:feature_code":"PPL",
    "gn:name":"Daguogou",
    "gn:population":0,
    "gn:timezone":"Asia/Shanghai",
    "iso:country":"CN",
    "name:zho_x_preferred":[
        "\u5927\u90ed\u6c9f"
    ],
    "wof:name":"Daguogou",
    "wof:placetype":"locality"
},
  "geometry": {"coordinates":[112.20023999999999,34.00943],"type":"Point"}
}