{
  "type": "Feature",
  "properties": {
    "gn:admin1_code":"12.0",
    "gn:asciiname":"Dongping",
    "gn:country_code":"CN",
    "gn:dem":1062,
    "gn:feature_class":"P",
    "gn:feature_code":"PPL",
    "gn:name":"Dongping",
    "gn:population":0,
    "gn:timezone":"Asia/Shanghai",
    "iso:country":"CN",
    "name:zho_x_preferred":[
        "\u4e1c\u576a"
    ],
    "wof:name":"Dongping",
    "wof:placetype":"locality"
},
  "geometry": {"coordinates":[111.12694,31.5788],"type":"Point"}
}