{
  "type": "Feature",
  "properties": {
    "gn:admin1_code":"32.0",
    "gn:asciiname":"Chili",
    "gn:country_code":"CN",
    "gn:dem":501,
    "gn:feature_class":"P",
    "gn:feature_code":"PPL",
    "gn:name":"Chili",
    "gn:population":0,
    "gn:timezone":"Asia/Shanghai",
    "iso:country":"CN",
    "name:ceb_x_preferred":[
        "Chili"
    ],
    "name:dan_x_preferred":[
        "Chili"
    ],
    "name:deu_x_preferred":[
        "Chili"
    ],
    "name:fra_x_preferred":[
        "Chili"
    ],
    "name:heb_x_preferred":[
        "\u05e6'\u05d9\u05dc\u05d9"
    ],
    "name:ita_x_preferred":[
        "Chili"
    ],
    "name:pol_x_preferred":[
        "Chili"
    ],
    "name:spa_x_preferred":[
        "Chili"
    ],
    "name:srp_x_preferred":[
        "\u0427\u0438\u043b\u0438"
    ],
    "name:swe_x_preferred":[
        "Chili"
    ],
    "name:ukr_x_preferred":[
        "\u0427\u0430\u0439\u043b\u0430\u0439"
    ],
    "name:zho_x_preferred":[
        "\u6c60\u9ca4"
    ],
    "wof:name":"Chili",
    "wof:placetype":"locality"
},
  "geometry": {"coordinates":[105.898,31.8309],"type":"Point"}
}