{
  "type": "Feature",
  "properties": {
    "gn:admin1_code":"07",
    "gn:asciiname":"Eyang",
    "gn:country_code":"CN",
    "gn:dem":130,
    "gn:feature_class":"P",
    "gn:feature_code":"PPL",
    "gn:name":"Eyang",
    "gn:population":0,
    "gn:timezone":"Asia/Shanghai",
    "iso:country":"CN",
    "name:und_x_variant":[
        "O-yang",
        "Eyang"
    ],
    "name:zho_x_preferred":[
        "\u83aa\u6d0b"
    ],
    "wof:name":"Eyang",
    "wof:placetype":"locality"
},
  "geometry": {"coordinates":[118.67310999999999,26.42583],"type":"Point"}
}