{
  "type": "Feature",
  "properties": {
    "gn:admin1_code":"32.0",
    "gn:asciiname":"Baichunping",
    "gn:country_code":"CN",
    "gn:dem":1189,
    "gn:feature_class":"P",
    "gn:feature_code":"PPL",
    "gn:name":"Baichunping",
    "gn:population":0,
    "gn:timezone":"Asia/Shanghai",
    "iso:country":"CN",
    "name:zho_x_preferred":[
        "\u67cf\u6625\u576a"
    ],
    "wof:name":"Baichunping",
    "wof:placetype":"locality"
},
  "geometry": {"coordinates":[102.93600000000001,30.2753],"type":"Point"}
}