{
  "type": "Feature",
  "properties": {
    "gn:admin1_code":"10",
    "gn:asciiname":"Dashizhuang",
    "gn:country_code":"CN",
    "gn:dem":37,
    "gn:feature_class":"P",
    "gn:feature_code":"PPL",
    "gn:name":"Dashizhuang",
    "gn:population":0,
    "gn:timezone":"Asia/Shanghai",
    "iso:country":"CN",
    "name:und_x_variant":[
        "Ta-shih-chuang",
        "Dashizhuang"
    ],
    "name:zho_x_preferred":[
        "\u5927\u58eb\u5e84"
    ],
    "wof:name":"Dashizhuang",
    "wof:placetype":"locality"
},
  "geometry": {"coordinates":[115.283,37.9207],"type":"Point"}
}