{
  "type": "Feature",
  "properties": {
    "gn:admin1_code":"18",
    "gn:asciiname":"Liujia Wuji",
    "gn:country_code":"CN",
    "gn:dem":1841,
    "gn:feature_class":"P",
    "gn:feature_code":"PPL",
    "gn:name":"Liujia Wuji",
    "gn:population":0,
    "gn:timezone":"Asia/Shanghai",
    "iso:country":"CN",
    "name:zho_x_preferred":[
        "\u5218\u5bb6\u5c4b\u57fa"
    ],
    "wof:name":"Liujia Wuji",
    "wof:placetype":"locality"
},
  "geometry": {"coordinates":[104.733,25.4947],"type":"Point"}
}