{
  "type": "Feature",
  "properties": {
    "gn:admin1_code":"4.0",
    "gn:asciiname":"Chaiwo",
    "gn:country_code":"CN",
    "gn:dem":6,
    "gn:feature_class":"P",
    "gn:feature_code":"PPL",
    "gn:name":"Chaiwo",
    "gn:population":0,
    "gn:timezone":"Asia/Shanghai",
    "iso:country":"CN",
    "name:zho_x_preferred":[
        "Chaiwo"
    ],
    "name:zho_x_variant":[
        "\u67f4\u7a9d"
    ],
    "wof:name":"Chaiwo",
    "wof:placetype":"locality"
},
  "geometry": {"coordinates":[119.16401,34.11116],"type":"Point"}
}