{
  "type": "Feature",
  "properties": {
    "gn:admin1_code":"4.0",
    "gn:asciiname":"Chuantang",
    "gn:country_code":"CN",
    "gn:dem":11,
    "gn:feature_class":"P",
    "gn:feature_code":"PPL",
    "gn:name":"Chuantang",
    "gn:population":0,
    "gn:timezone":"Asia/Shanghai",
    "iso:country":"CN",
    "name:zho_x_preferred":[
        "\u8239\u5858"
    ],
    "wof:name":"Chuantang",
    "wof:placetype":"locality"
},
  "geometry": {"coordinates":[119.01869000000001,32.99708],"type":"Point"}
}