{
  "type": "Feature",
  "properties": {
    "gn:admin1_code":"26.0",
    "gn:asciiname":"Heigouhecun",
    "gn:country_code":"CN",
    "gn:dem":1376,
    "gn:feature_class":"P",
    "gn:feature_code":"PPL",
    "gn:name":"Heigouhecun",
    "gn:population":0,
    "gn:timezone":"Asia/Shanghai",
    "iso:country":"CN",
    "name:zho_x_preferred":[
        "\u9ed1\u6c9f\u6cb3\u6751"
    ],
    "wof:name":"Heigouhecun",
    "wof:placetype":"locality"
},
  "geometry": {"coordinates":[108.3026,36.96182],"type":"Point"}
}