{
  "type": "Feature",
  "properties": {
    "gn:admin1_code":"11.0",
    "gn:asciiname":"Qiangtou'ao",
    "gn:country_code":"CN",
    "gn:dem":871,
    "gn:feature_class":"P",
    "gn:feature_code":"PPL",
    "gn:name":"Qiangtou\u2019ao",
    "gn:population":0,
    "gn:timezone":"Asia/Shanghai",
    "iso:country":"CN",
    "name:und_x_variant":[
        "Qiangtou\u2019ao"
    ],
    "name:zho_x_preferred":[
        "\u5899\u5934\u5773"
    ],
    "wof:name":"Qiangtou'ao",
    "wof:placetype":"locality"
},
  "geometry": {"coordinates":[113.37298,25.43429],"type":"Point"}
}