{
  "type": "Feature",
  "properties": {
    "gn:admin1_code":"26.0",
    "gn:asciiname":"Huichicun",
    "gn:country_code":"CN",
    "gn:dem":1076,
    "gn:feature_class":"P",
    "gn:feature_code":"PPL",
    "gn:name":"Huichicun",
    "gn:population":0,
    "gn:timezone":"Asia/Shanghai",
    "iso:country":"CN",
    "name:zho_x_preferred":[
        "\u7070\u6c60\u6751"
    ],
    "wof:name":"Huichicun",
    "wof:placetype":"locality"
},
  "geometry": {"coordinates":[109.80285000000001,34.4208],"type":"Point"}
}