{
  "type": "Feature",
  "properties": {
    "gn:admin1_code":"29.0",
    "gn:asciiname":"Xiaohenzhao",
    "gn:country_code":"CN",
    "gn:dem":1879,
    "gn:feature_class":"P",
    "gn:feature_code":"PPL",
    "gn:name":"Xiaohenzhao",
    "gn:population":0,
    "gn:timezone":"Asia/Shanghai",
    "iso:country":"CN",
    "name:zho_x_preferred":[
        "\u5c0f\u72e0\u53ec"
    ],
    "wof:name":"Xiaohenzhao",
    "wof:placetype":"locality"
},
  "geometry": {"coordinates":[104.226,25.0428],"type":"Point"}
}