{
  "type": "Feature",
  "properties": {
    "gn:admin1_code":"12.0",
    "gn:asciiname":"Guangshui",
    "gn:cc2":"CN",
    "gn:country_code":"CN",
    "gn:dem":88,
    "gn:feature_class":"P",
    "gn:feature_code":"PPL",
    "gn:name":"Guangshui",
    "gn:population":0,
    "gn:timezone":"Asia/Shanghai",
    "iso:country":"CN",
    "name:ara_x_preferred":[
        "\u063a\u0648\u0627\u0646\u063a\u0634\u0648\u064a"
    ],
    "name:deu_x_preferred":[
        "Guangshui"
    ],
    "name:fra_x_preferred":[
        "Guangshui"
    ],
    "name:ita_x_preferred":[
        "Guangshui"
    ],
    "name:jpn_x_preferred":[
        "\u5e83\u6c34\u5e02"
    ],
    "name:kik_x_preferred":[
        "Guangshui"
    ],
    "name:kor_x_preferred":[
        "\uad11\uc218\uc774\uc2dc"
    ],
    "name:mlg_x_preferred":[
        "Guangshui"
    ],
    "name:nor_x_preferred":[
        "Guangshui"
    ],
    "name:pam_x_preferred":[
        "Guangshui"
    ],
    "name:swe_x_preferred":[
        "Guangshui"
    ],
    "name:und_x_variant":[
        "Ying-shan-hsien",
        "Yingshan"
    ],
    "name:vie_x_preferred":[
        "Qu\u1ea3ng Th\u1ee7y"
    ],
    "name:war_x_preferred":[
        "Guangshui"
    ],
    "name:zho_x_preferred":[
        "\u5e7f\u6c34\u5e02"
    ],
    "wof:name":"Guangshui",
    "wof:placetype":"locality"
},
  "geometry": {"coordinates":[113.81556,31.61611],"type":"Point"}
}