{
  "type": "Feature",
  "properties": {
    "gn:admin1_code":"12.0",
    "gn:asciiname":"Guangshui",
    "gn:cc2":"CN",
    "gn:country_code":"CN",
    "gn:dem":88,
    "gn:feature_class":"P",
    "gn:feature_code":"PPL",
    "gn:name":"Guangshui",
    "gn:population":0,
    "gn:timezone":"Asia/Shanghai",
    "iso:country":"CN",
    "name:und_x_variant":[
        "Ying-shan-hsien",
        "Yingshan",
        "Guangshui"
    ],
    "wof:name":"Guangshui",
    "wof:placetype":"locality"
},
  "geometry": {"coordinates":[113.81556,31.61611],"type":"Point"}
}