{
  "type": "Feature",
  "properties": {
    "gn:admin1_code":"21.0",
    "gn:asciiname":"Sanfangzhuang",
    "gn:country_code":"CN",
    "gn:dem":1893,
    "gn:feature_class":"P",
    "gn:feature_code":"PPL",
    "gn:name":"Sanfangzhuang",
    "gn:population":0,
    "gn:timezone":"Asia/Shanghai",
    "iso:country":"CN",
    "name:zho_x_preferred":[
        "\u4e09\u623f\u5e84"
    ],
    "wof:name":"Sanfangzhuang",
    "wof:placetype":"locality"
},
  "geometry": {"coordinates":[105.43300000000001,36.0854],"type":"Point"}
}