{
  "type": "Feature",
  "properties": {
    "gn:admin1_code":"01",
    "gn:asciiname":"Putang",
    "gn:country_code":"CN",
    "gn:dem":36,
    "gn:feature_class":"P",
    "gn:feature_code":"PPLA4",
    "gn:name":"Putang",
    "gn:population":0,
    "gn:timezone":"Asia/Shanghai",
    "iso:country":"CN",
    "name:und_x_variant":[
        "P\u2019u-t\u2019ang-chen",
        "Putang",
        "Putang Zhen"
    ],
    "name:zho_x_preferred":[
        "\u6fee\u5858"
    ],
    "name:zho_x_variant":[
        "\u6fee\u5858\u9547"
    ],
    "wof:name":"Putang",
    "wof:placetype":"locality"
},
  "geometry": {"coordinates":[118.64924000000001,31.7124],"type":"Point"}
}