{
  "type": "Feature",
  "properties": {
    "gn:admin1_code":"9.0",
    "gn:asciiname":"Gaopo",
    "gn:country_code":"CN",
    "gn:dem":695,
    "gn:feature_class":"P",
    "gn:feature_code":"PPL",
    "gn:name":"Gaopo",
    "gn:population":0,
    "gn:timezone":"Asia/Shanghai",
    "iso:country":"CN",
    "name:und_x_variant":[
        "\u9ad8\u5761",
        "Gaopo"
    ],
    "wof:name":"Gaopo",
    "wof:placetype":"locality"
},
  "geometry": {"coordinates":[112.50272,33.96189],"type":"Point"}
}