{
  "type": "Feature",
  "properties": {
    "gn:admin1_code":"16.0",
    "gn:asciiname":"Niqiao",
    "gn:country_code":"CN",
    "gn:dem":60,
    "gn:feature_class":"P",
    "gn:feature_code":"PPL",
    "gn:name":"Niqiao",
    "gn:population":0,
    "gn:timezone":"Asia/Shanghai",
    "iso:country":"CN",
    "name:zho_x_preferred":[
        "\u576d\u6865"
    ],
    "wof:name":"Niqiao",
    "wof:placetype":"locality"
},
  "geometry": {"coordinates":[109.06,22.2163],"type":"Point"}
}