{
  "type": "Feature",
  "properties": {
    "gn:admin1_code":"12.0",
    "gn:asciiname":"Gebidawu",
    "gn:country_code":"CN",
    "gn:dem":197,
    "gn:feature_class":"P",
    "gn:feature_code":"PPL",
    "gn:name":"Gebidawu",
    "gn:population":0,
    "gn:timezone":"Asia/Shanghai",
    "iso:country":"CN",
    "name:zho_x_preferred":[
        "\u9601\u58c1\u5927\u5c4b"
    ],
    "wof:name":"Gebidawu",
    "wof:placetype":"locality"
},
  "geometry": {"coordinates":[113.97833,29.25324],"type":"Point"}
}