{
  "type": "Feature",
  "properties": {
    "gn:admin1_code":"11.0",
    "gn:asciiname":"Jiaobi",
    "gn:country_code":"CN",
    "gn:dem":696,
    "gn:feature_class":"P",
    "gn:feature_code":"PPL",
    "gn:name":"Jiaobi",
    "gn:population":0,
    "gn:timezone":"Asia/Shanghai",
    "iso:country":"CN",
    "name:zho_x_preferred":[
        "\u7ede\u58c1"
    ],
    "wof:name":"Jiaobi",
    "wof:placetype":"locality"
},
  "geometry": {"coordinates":[108.96178999999999,27.16698],"type":"Point"}
}