{
  "type": "Feature",
  "properties": {
    "gn:admin1_code":"29.0",
    "gn:asciiname":"Bainike",
    "gn:country_code":"CN",
    "gn:dem":2140,
    "gn:feature_class":"P",
    "gn:feature_code":"PPL",
    "gn:name":"Bainike",
    "gn:population":0,
    "gn:timezone":"Asia/Shanghai",
    "iso:country":"CN",
    "name:zho_x_preferred":[
        "\u767d\u6ce5\u514b"
    ],
    "wof:name":"Bainike",
    "wof:placetype":"locality"
},
  "geometry": {"coordinates":[104.133,26.445],"type":"Point"}
}