{
  "type": "Feature",
  "properties": {
    "gn:admin1_code":"6.0",
    "gn:asciiname":"Maiyanong",
    "gn:country_code":"CN",
    "gn:dem":4321,
    "gn:feature_class":"P",
    "gn:feature_code":"PPL",
    "gn:name":"Maiyanong",
    "gn:population":0,
    "gn:timezone":"Asia/Urumqi",
    "iso:country":"CN",
    "name:zho_x_preferred":[
        "\u9ea6\u538b\u5f04"
    ],
    "wof:name":"Maiyanong",
    "wof:placetype":"locality"
},
  "geometry": {"coordinates":[96.34698,31.93079],"type":"Point"}
}