{
  "type": "Feature",
  "properties": {
    "gn:admin1_code":"19.0",
    "gn:asciiname":"Dafangshen",
    "gn:country_code":"CN",
    "gn:dem":92,
    "gn:feature_class":"P",
    "gn:feature_code":"PPL",
    "gn:name":"Dafangshen",
    "gn:population":0,
    "gn:timezone":"Asia/Shanghai",
    "iso:country":"CN",
    "name:und_x_variant":[
        "\u5927\u623f\u7533"
    ],
    "name:zho_x_preferred":[
        "\u5927\u623f\u7533"
    ],
    "wof:name":"Dafangshen",
    "wof:placetype":"locality"
},
  "geometry": {"coordinates":[123.46903,42.54977],"type":"Point"}
}