{
  "type": "Feature",
  "properties": {
    "gn:admin1_code":"15.0",
    "gn:asciiname":"Zudipo",
    "gn:country_code":"CN",
    "gn:dem":2365,
    "gn:feature_class":"P",
    "gn:feature_code":"PPL",
    "gn:name":"Zudipo",
    "gn:population":0,
    "gn:timezone":"Asia/Shanghai",
    "iso:country":"CN",
    "name:zho_x_preferred":[
        "\u79df\u5730\u5761"
    ],
    "wof:name":"Zudipo",
    "wof:placetype":"locality"
},
  "geometry": {"coordinates":[103.303,35.3694],"type":"Point"}
}