{
  "type": "Feature",
  "properties": {
    "gn:admin1_code":"29.0",
    "gn:asciiname":"Xiaoyaoqing",
    "gn:country_code":"CN",
    "gn:dem":1928,
    "gn:feature_class":"P",
    "gn:feature_code":"PPL",
    "gn:name":"Xiaoyaoqing",
    "gn:population":0,
    "gn:timezone":"Asia/Shanghai",
    "iso:country":"CN",
    "name:zho_x_preferred":[
        "\u5c0f\u8170\u7b90"
    ],
    "wof:name":"Xiaoyaoqing",
    "wof:placetype":"locality"
},
  "geometry": {"coordinates":[98.33150000000001,25.1175],"type":"Point"}
}