{
  "type": "Feature",
  "properties": {
    "gn:admin1_code":"3.0",
    "gn:asciiname":"Wenshui",
    "gn:country_code":"CN",
    "gn:dem":113,
    "gn:feature_class":"P",
    "gn:feature_code":"PPL",
    "gn:name":"Wenshui",
    "gn:population":0,
    "gn:timezone":"Asia/Shanghai",
    "iso:country":"CN",
    "name:und_x_variant":[
        "\u6c76\u6c34"
    ],
    "wof:name":"Wenshui",
    "wof:placetype":"locality"
},
  "geometry": {"coordinates":[114.291,27.0322],"type":"Point"}
}