{
  "type": "Feature",
  "properties": {
    "gn:admin1_code":"16",
    "gn:asciiname":"Litang",
    "gn:country_code":"CN",
    "gn:dem":367,
    "gn:feature_class":"P",
    "gn:feature_code":"PPL",
    "gn:name":"Litang",
    "gn:population":0,
    "gn:timezone":"Asia/Shanghai",
    "iso:country":"CN",
    "name:ceb_x_preferred":[
        "Litang"
    ],
    "name:nld_x_preferred":[
        "Litang"
    ],
    "name:zho_x_preferred":[
        "\u6817\u5858"
    ],
    "wof:name":"Litang",
    "wof:placetype":"locality"
},
  "geometry": {"coordinates":[110.181,25.0025],"type":"Point"}
}