{
  "type": "Feature",
  "properties": {
    "gn:admin1_code":"11",
    "gn:asciiname":"Huxingqiao",
    "gn:country_code":"CN",
    "gn:dem":173,
    "gn:feature_class":"P",
    "gn:feature_code":"PPL",
    "gn:name":"Huxingqiao",
    "gn:population":0,
    "gn:timezone":"Asia/Shanghai",
    "iso:country":"CN",
    "wof:name":"Huxingqiao",
    "wof:placetype":"locality"
},
  "geometry": {"coordinates":[111.94861000000002,27.35833],"type":"Point"}
}