{
  "type": "Feature",
  "properties": {
    "gn:admin1_code":"32.0",
    "gn:asciiname":"Yuanbao",
    "gn:country_code":"CN",
    "gn:dem":3031,
    "gn:feature_class":"P",
    "gn:feature_code":"PPL",
    "gn:name":"Yuanbao",
    "gn:population":0,
    "gn:timezone":"Asia/Shanghai",
    "iso:country":"CN",
    "name:zho_x_preferred":[
        "\u5143\u5b9d"
    ],
    "wof:name":"Yuanbao",
    "wof:placetype":"locality"
},
  "geometry": {"coordinates":[101.43600000000001,27.2711],"type":"Point"}
}