{
  "type": "Feature",
  "properties": {
    "gn:admin1_code":"4.0",
    "gn:asciiname":"Tiaogoucun",
    "gn:country_code":"CN",
    "gn:dem":22,
    "gn:feature_class":"P",
    "gn:feature_code":"PPL",
    "gn:name":"Tiaogoucun",
    "gn:population":0,
    "gn:timezone":"Asia/Shanghai",
    "iso:country":"CN",
    "name:zho_x_preferred":[
        "\u6311\u6c9f\u6751"
    ],
    "wof:name":"Tiaogoucun",
    "wof:placetype":"locality"
},
  "geometry": {"coordinates":[118.19989,33.80188],"type":"Point"}
}