{
  "type": "Feature",
  "properties": {
    "gn:admin1_code":"12.0",
    "gn:asciiname":"Wangjiatai",
    "gn:country_code":"CN",
    "gn:dem":32,
    "gn:feature_class":"P",
    "gn:feature_code":"PPL",
    "gn:name":"Wangjiatai",
    "gn:population":0,
    "gn:timezone":"Asia/Shanghai",
    "iso:country":"CN",
    "name:zho_x_preferred":[
        "\u738b\u5bb6\u53f0"
    ],
    "wof:name":"Wangjiatai",
    "wof:placetype":"locality"
},
  "geometry": {"coordinates":[112.25375,30.34007],"type":"Point"}
}