{
  "type": "Feature",
  "properties": {
    "gn:admin1_code":"31.0",
    "gn:asciiname":"Daweng",
    "gn:country_code":"CN",
    "gn:dem":72,
    "gn:feature_class":"P",
    "gn:feature_code":"PPL",
    "gn:name":"Daweng",
    "gn:population":0,
    "gn:timezone":"Asia/Shanghai",
    "iso:country":"CN",
    "name:zho_x_preferred":[
        "\u5927\u7fc1"
    ],
    "wof:name":"Daweng",
    "wof:placetype":"locality"
},
  "geometry": {"coordinates":[110.13997999999999,18.75633],"type":"Point"}
}