{
  "type": "Feature",
  "properties": {
    "gn:admin1_code":"24.0",
    "gn:asciiname":"Xiaochuancun",
    "gn:country_code":"CN",
    "gn:dem":1448,
    "gn:feature_class":"P",
    "gn:feature_code":"PPL",
    "gn:name":"Xiaochuancun",
    "gn:population":0,
    "gn:timezone":"Asia/Shanghai",
    "iso:country":"CN",
    "name:zho_x_preferred":[
        "\u5c0f\u5ddd\u6751"
    ],
    "wof:name":"Xiaochuancun",
    "wof:placetype":"locality"
},
  "geometry": {"coordinates":[112.39228,39.69431],"type":"Point"}
}