{
  "type": "Feature",
  "properties": {
    "gn:admin1_code":"1.0",
    "gn:asciiname":"Meizhaicun",
    "gn:country_code":"CN",
    "gn:dem":35,
    "gn:feature_class":"P",
    "gn:feature_code":"PPL",
    "gn:name":"Meizhaicun",
    "gn:population":0,
    "gn:timezone":"Asia/Shanghai",
    "iso:country":"CN",
    "name:zho_x_preferred":[
        "\u6885\u5be8\u6751"
    ],
    "wof:name":"Meizhaicun",
    "wof:placetype":"locality"
},
  "geometry": {"coordinates":[115.62268,32.98669],"type":"Point"}
}