{
  "type": "Feature",
  "properties": {
    "gn:admin1_code":"5.0",
    "gn:asciiname":"Donghuanxitun",
    "gn:country_code":"CN",
    "gn:dem":184,
    "gn:feature_class":"P",
    "gn:feature_code":"PPL",
    "gn:name":"Donghuanxitun",
    "gn:population":0,
    "gn:timezone":"Asia/Shanghai",
    "iso:country":"CN",
    "name:zho_x_preferred":[
        "\u4e1c\u6b22\u559c\u5c6f"
    ],
    "wof:name":"Donghuanxitun",
    "wof:placetype":"locality"
},
  "geometry": {"coordinates":[125.74284,45.13423],"type":"Point"}
}