{
  "type": "Feature",
  "properties": {
    "gn:admin1_code":"14.0",
    "gn:asciiname":"Jiere",
    "gn:country_code":"CN",
    "gn:dem":4643,
    "gn:feature_class":"P",
    "gn:feature_code":"PPL",
    "gn:name":"Jiere",
    "gn:population":0,
    "gn:timezone":"Asia/Urumqi",
    "iso:country":"CN",
    "name:zho_x_preferred":[
        "\u7ed3\u70ed"
    ],
    "wof:name":"Jiere",
    "wof:placetype":"locality"
},
  "geometry": {"coordinates":[86.57340000000001,30.6641],"type":"Point"}
}