{
  "type": "Feature",
  "properties": {
    "gn:admin1_code":"8.0",
    "gn:asciiname":"Liumajia",
    "gn:country_code":"CN",
    "gn:dem":201,
    "gn:feature_class":"P",
    "gn:feature_code":"PPL",
    "gn:name":"Liumajia",
    "gn:population":0,
    "gn:timezone":"Asia/Shanghai",
    "iso:country":"CN",
    "name:zho_x_preferred":[
        "\u516d\u9a6c\u67b6"
    ],
    "wof:name":"Liumajia",
    "wof:placetype":"locality"
},
  "geometry": {"coordinates":[127.62573999999999,46.22819000000001],"type":"Point"}
}