{
  "type": "Feature",
  "properties": {
    "gn:admin1_code":"29.0",
    "gn:asciiname":"Maying Huaping",
    "gn:country_code":"CN",
    "gn:dem":2481,
    "gn:feature_class":"P",
    "gn:feature_code":"PPL",
    "gn:name":"Maying Huaping",
    "gn:population":0,
    "gn:timezone":"Asia/Shanghai",
    "iso:country":"CN",
    "name:zho_x_preferred":[
        "\u9a6c\u82f1\u82b1\u576a"
    ],
    "wof:name":"Maying Huaping",
    "wof:placetype":"locality"
},
  "geometry": {"coordinates":[100.759,25.9117],"type":"Point"}
}