{
  "type": "Feature",
  "properties": {
    "gn:admin1_code":"1.0",
    "gn:asciiname":"Xincang",
    "gn:cc2":"CN",
    "gn:country_code":"CN",
    "gn:dem":58,
    "gn:feature_class":"P",
    "gn:feature_code":"PPL",
    "gn:name":"Xincang",
    "gn:population":0,
    "gn:timezone":"Asia/Shanghai",
    "iso:country":"CN",
    "name:und_x_variant":[
        "Hsin-ts\u2019ang",
        "Xincang"
    ],
    "wof:name":"Xincang",
    "wof:placetype":"locality"
},
  "geometry": {"coordinates":[116.43333,30.41667],"type":"Point"}
}