{
  "type": "Feature",
  "properties": {
    "gn:admin1_code":"7.0",
    "gn:asciiname":"Linxiacun",
    "gn:country_code":"CN",
    "gn:dem":281,
    "gn:feature_class":"P",
    "gn:feature_code":"PPL",
    "gn:name":"Linxiacun",
    "gn:population":0,
    "gn:timezone":"Asia/Shanghai",
    "iso:country":"CN",
    "name:zho_x_preferred":[
        "\u6797\u4e0b\u6751"
    ],
    "wof:name":"Linxiacun",
    "wof:placetype":"locality"
},
  "geometry": {"coordinates":[118.81999,27.49209],"type":"Point"}
}