{
  "type": "Feature",
  "properties": {
    "gn:admin1_code":"14",
    "gn:asciiname":"Kebatazha",
    "gn:country_code":"CN",
    "gn:dem":4539,
    "gn:feature_class":"P",
    "gn:feature_code":"PPL",
    "gn:name":"Kebatazha",
    "gn:population":0,
    "gn:timezone":"Asia/Urumqi",
    "iso:country":"CN",
    "name:zho_x_preferred":[
        "\u514b\u5df4\u5854\u6e23"
    ],
    "wof:name":"Kebatazha",
    "wof:placetype":"locality"
},
  "geometry": {"coordinates":[88.1812,32.052],"type":"Point"}
}