{
  "type": "Feature",
  "properties": {
    "gn:admin1_code":"30.0",
    "gn:asciiname":"Wanggao",
    "gn:country_code":"CN",
    "gn:dem":61,
    "gn:feature_class":"P",
    "gn:feature_code":"PPL",
    "gn:name":"Wanggao",
    "gn:population":0,
    "gn:timezone":"Asia/Shanghai",
    "iso:country":"CN",
    "name:zho_x_preferred":[
        "\u671b\u9ad8"
    ],
    "wof:name":"Wanggao",
    "wof:placetype":"locality"
},
  "geometry": {"coordinates":[111.88334999999999,23.86058],"type":"Point"}
}