{
  "type": "Feature",
  "properties": {
    "gn:admin1_code":"8.0",
    "gn:asciiname":"Yaolingcun",
    "gn:country_code":"CN",
    "gn:dem":297,
    "gn:feature_class":"P",
    "gn:feature_code":"PPL",
    "gn:name":"Yaolingcun",
    "gn:population":0,
    "gn:timezone":"Asia/Shanghai",
    "iso:country":"CN",
    "name:zho_x_preferred":[
        "\u8170\u5cad\u6751"
    ],
    "wof:name":"Yaolingcun",
    "wof:placetype":"locality"
},
  "geometry": {"coordinates":[127.09683,49.2293],"type":"Point"}
}