{
  "type": "Feature",
  "properties": {
    "gn:admin1_code":"30.0",
    "gn:asciiname":"Xixicun",
    "gn:country_code":"CN",
    "gn:dem":123,
    "gn:feature_class":"P",
    "gn:feature_code":"PPL",
    "gn:name":"Xixicun",
    "gn:population":0,
    "gn:timezone":"Asia/Shanghai",
    "iso:country":"CN",
    "name:und_x_variant":[
        "\u897f\u6eaa\u6751"
    ],
    "name:zho_x_preferred":[
        "\u897f\u6eaa\u6751"
    ],
    "wof:name":"Xixicun",
    "wof:placetype":"locality"
},
  "geometry": {"coordinates":[114.60809999999999,24.01704],"type":"Point"}
}