{
  "type": "Feature",
  "properties": {
    "gn:admin1_code":"12.0",
    "gn:asciiname":"Huamiaozi",
    "gn:country_code":"CN",
    "gn:dem":779,
    "gn:feature_class":"P",
    "gn:feature_code":"PPL",
    "gn:name":"Huamiaozi",
    "gn:population":0,
    "gn:timezone":"Asia/Shanghai",
    "iso:country":"CN",
    "name:zho_x_preferred":[
        "\u82b1\u5e99\u5b50"
    ],
    "wof:name":"Huamiaozi",
    "wof:placetype":"locality"
},
  "geometry": {"coordinates":[111.47866999999999,32.00842],"type":"Point"}
}