{
  "type": "Feature",
  "properties": {
    "gn:admin1_code":"8.0",
    "gn:asciiname":"Diaojia Wopeng",
    "gn:country_code":"CN",
    "gn:dem":293,
    "gn:feature_class":"P",
    "gn:feature_code":"PPL",
    "gn:name":"Diaojia Wopeng",
    "gn:population":0,
    "gn:timezone":"Asia/Shanghai",
    "iso:country":"CN",
    "name:zho_x_preferred":[
        "\u5201\u5bb6\u7a9d\u68da"
    ],
    "wof:name":"Diaojia Wopeng",
    "wof:placetype":"locality"
},
  "geometry": {"coordinates":[125.42692,48.41375],"type":"Point"}
}