{
  "type": "Feature",
  "properties": {
    "gn:admin1_code":"24.0",
    "gn:asciiname":"Chengjiacun",
    "gn:country_code":"CN",
    "gn:dem":1403,
    "gn:feature_class":"P",
    "gn:feature_code":"PPL",
    "gn:name":"Chengjiacun",
    "gn:population":0,
    "gn:timezone":"Asia/Shanghai",
    "iso:country":"CN",
    "name:und_x_variant":[
        "\u7a0b\u5bb6\u6751"
    ],
    "name:zho_x_preferred":[
        "\u7a0b\u5bb6\u6751"
    ],
    "wof:name":"Chengjiacun",
    "wof:placetype":"locality"
},
  "geometry": {"coordinates":[112.3369,39.86143],"type":"Point"}
}