{
  "type": "Feature",
  "properties": {
    "gn:admin1_code":"22.0",
    "gn:asciiname":"Yangtuocun",
    "gn:country_code":"CN",
    "gn:dem":145,
    "gn:feature_class":"P",
    "gn:feature_code":"PPL",
    "gn:name":"Yangtuocun",
    "gn:population":0,
    "gn:timezone":"Asia/Shanghai",
    "iso:country":"CN",
    "name:zho_x_preferred":[
        "\u6768\u5768\u6751"
    ],
    "wof:name":"Yangtuocun",
    "wof:placetype":"locality"
},
  "geometry": {"coordinates":[116.10402000000001,40.00671],"type":"Point"}
}