{
  "type": "Feature",
  "properties": {
    "gn:admin1_code":"25.0",
    "gn:asciiname":"Huangcao'an",
    "gn:country_code":"CN",
    "gn:dem":149,
    "gn:feature_class":"P",
    "gn:feature_code":"PPL",
    "gn:name":"Huangcao\u2019an",
    "gn:population":0,
    "gn:timezone":"Asia/Shanghai",
    "iso:country":"CN",
    "name:und_x_variant":[
        "Huangcao\u2019an"
    ],
    "name:zho_x_preferred":[
        "\u9ec4\u8349\u5eb5"
    ],
    "wof:name":"Huangcao'an",
    "wof:placetype":"locality"
},
  "geometry": {"coordinates":[121.20411,36.85961],"type":"Point"}
}