{
  "type": "Feature",
  "properties": {
    "gn:admin1_code":"11.0",
    "gn:asciiname":"Guangyu",
    "gn:country_code":"CN",
    "gn:dem":446,
    "gn:feature_class":"P",
    "gn:feature_code":"PPL",
    "gn:name":"Guangyu",
    "gn:population":0,
    "gn:timezone":"Asia/Shanghai",
    "iso:country":"CN",
    "name:zho_x_preferred":[
        "\u5e7f\u80b2"
    ],
    "wof:name":"Guangyu",
    "wof:placetype":"locality"
},
  "geometry": {"coordinates":[110.48990000000001,27.00747],"type":"Point"}
}