{
  "type": "Feature",
  "properties": {
    "gn:admin1_code":"25.0",
    "gn:asciiname":"Shanjiaodi",
    "gn:cc2":"CN",
    "gn:country_code":"CN",
    "gn:dem":11,
    "gn:feature_class":"P",
    "gn:feature_code":"PPL",
    "gn:name":"Shanjiaodi",
    "gn:population":0,
    "gn:timezone":"Asia/Shanghai",
    "iso:country":"CN",
    "name:zho_x_preferred":[
        "\u5c71\u89d2\u5e95"
    ],
    "wof:name":"Shanjiaodi",
    "wof:placetype":"locality"
},
  "geometry": {"coordinates":[120.12724,36.23934000000001],"type":"Point"}
}