{
  "type": "Feature",
  "properties": {
    "gn:admin1_code":"12.0",
    "gn:asciiname":"Taoyuanzi",
    "gn:country_code":"CN",
    "gn:dem":1079,
    "gn:feature_class":"P",
    "gn:feature_code":"PPL",
    "gn:name":"Taoyuanzi",
    "gn:population":0,
    "gn:timezone":"Asia/Shanghai",
    "iso:country":"CN",
    "name:zho_x_preferred":[
        "\u6843\u56ed\u5b50"
    ],
    "wof:name":"Taoyuanzi",
    "wof:placetype":"locality"
},
  "geometry": {"coordinates":[109.6307,32.05569000000001],"type":"Point"}
}