{
  "type": "Feature",
  "properties": {
    "gn:admin1_code":"1.0",
    "gn:asciiname":"Caikeng",
    "gn:country_code":"CN",
    "gn:dem":308,
    "gn:feature_class":"P",
    "gn:feature_code":"PPL",
    "gn:name":"Caikeng",
    "gn:population":0,
    "gn:timezone":"Asia/Shanghai",
    "iso:country":"CN",
    "name:und_x_variant":[
        "Ts\u2019ai-chia-wan",
        "Caikeng",
        "\u83dc\u5751"
    ],
    "wof:name":"Caikeng",
    "wof:placetype":"locality"
},
  "geometry": {"coordinates":[117.07163,29.89158],"type":"Point"}
}