{
  "type": "Feature",
  "properties": {
    "gn:admin1_code":"16.0",
    "gn:asciiname":"Zhongyi",
    "gn:country_code":"CN",
    "gn:dem":1116,
    "gn:feature_class":"P",
    "gn:feature_code":"PPL",
    "gn:name":"Zhongyi",
    "gn:population":0,
    "gn:timezone":"Asia/Shanghai",
    "iso:country":"CN",
    "name:zho_x_preferred":[
        "\u5fe0\u4e49"
    ],
    "wof:name":"Zhongyi",
    "wof:placetype":"locality"
},
  "geometry": {"coordinates":[105.19799999999999,24.9603],"type":"Point"}
}