{
  "type": "Feature",
  "properties": {
    "gn:admin1_code":"26.0",
    "gn:asciiname":"Shi'ercun",
    "gn:country_code":"CN",
    "gn:dem":752,
    "gn:feature_class":"P",
    "gn:feature_code":"PPL",
    "gn:name":"Shi\u2019ercun",
    "gn:population":0,
    "gn:timezone":"Asia/Shanghai",
    "iso:country":"CN",
    "name:und_x_variant":[
        "Shi\u2019ercun"
    ],
    "name:zho_x_preferred":[
        "\u4ec0\u4e8c\u6751"
    ],
    "wof:name":"Shi'ercun",
    "wof:placetype":"locality"
},
  "geometry": {"coordinates":[109.71352,35.28919000000001],"type":"Point"}
}