{
  "type": "Feature",
  "properties": {
    "gn:admin1_code":"1.0",
    "gn:asciiname":"Zuogangcun",
    "gn:country_code":"CN",
    "gn:dem":23,
    "gn:feature_class":"P",
    "gn:feature_code":"PPL",
    "gn:name":"Zuogangcun",
    "gn:population":0,
    "gn:timezone":"Asia/Shanghai",
    "iso:country":"CN",
    "name:und_x_variant":[
        "Zuogang"
    ],
    "name:zho_x_preferred":[
        "\u5de6\u5c97\u6751"
    ],
    "wof:name":"Zuogangcun",
    "wof:placetype":"locality"
},
  "geometry": {"coordinates":[117.50708,30.87268],"type":"Point"}
}