{
  "type": "Feature",
  "properties": {
    "gn:admin1_code":"30.0",
    "gn:asciiname":"Huzhua",
    "gn:country_code":"CN",
    "gn:dem":34,
    "gn:feature_class":"P",
    "gn:feature_code":"PPL",
    "gn:name":"Huzhua",
    "gn:population":0,
    "gn:timezone":"Asia/Shanghai",
    "iso:country":"CN",
    "name:zho_x_preferred":[
        "\u864e\u722a"
    ],
    "wof:name":"Huzhua",
    "wof:placetype":"locality"
},
  "geometry": {"coordinates":[112.97053,22.55088],"type":"Point"}
}