{
  "type": "Feature",
  "properties": {
    "gn:admin1_code":"29.0",
    "gn:asciiname":"Hudiequan",
    "gn:country_code":"CN",
    "gn:dem":2076,
    "gn:feature_class":"P",
    "gn:feature_code":"PPL",
    "gn:name":"Hudiequan",
    "gn:population":0,
    "gn:timezone":"Asia/Shanghai",
    "iso:country":"CN",
    "name:zho_x_preferred":[
        "\u8774\u8776\u6cc9"
    ],
    "wof:name":"Hudiequan",
    "wof:placetype":"locality"
},
  "geometry": {"coordinates":[100.09399999999999,25.909],"type":"Point"}
}