{
  "type": "Feature",
  "properties": {
    "gn:admin1_code":"12.0",
    "gn:asciiname":"Wangtang",
    "gn:country_code":"CN",
    "gn:dem":30,
    "gn:feature_class":"P",
    "gn:feature_code":"PPL",
    "gn:name":"Wangtang",
    "gn:population":0,
    "gn:timezone":"Asia/Shanghai",
    "iso:country":"CN",
    "name:zho_x_preferred":[
        "Wangtang"
    ],
    "name:zho_x_variant":[
        "\u6c6a\u5858"
    ],
    "wof:name":"Wangtang",
    "wof:placetype":"locality"
},
  "geometry": {"coordinates":[114.11877,29.82202],"type":"Point"}
}