{
  "type": "Feature",
  "properties": {
    "gn:admin1_code":"10.0",
    "gn:asciiname":"Liduoli",
    "gn:country_code":"CN",
    "gn:dem":15,
    "gn:feature_class":"P",
    "gn:feature_code":"PPL",
    "gn:name":"Liduoli",
    "gn:population":0,
    "gn:timezone":"Asia/Shanghai",
    "iso:country":"CN",
    "name:zho_x_preferred":[
        "\u674e\u591a\u91cc"
    ],
    "wof:name":"Liduoli",
    "wof:placetype":"locality"
},
  "geometry": {"coordinates":[116.56100000000001,38.1318],"type":"Point"}
}