{
  "type": "Feature",
  "properties": {
    "gn:admin1_code":"7",
    "gn:asciiname":"Dingcuo",
    "gn:country_code":"CN",
    "gn:dem":403,
    "gn:feature_class":"P",
    "gn:feature_code":"PPL",
    "gn:name":"Dingcuo",
    "gn:population":0,
    "gn:timezone":"Asia/Shanghai",
    "iso:country":"CN",
    "name:zho_x_preferred":[
        "\u9876\u539d"
    ],
    "wof:name":"Dingcuo",
    "wof:placetype":"locality"
},
  "geometry": {"coordinates":[118.68258,25.39909],"type":"Point"}
}