{
  "type": "Feature",
  "properties": {
    "gn:admin1_code":"29",
    "gn:asciiname":"Weile",
    "gn:country_code":"CN",
    "gn:dem":1307,
    "gn:feature_class":"P",
    "gn:feature_code":"PPL",
    "gn:name":"Weile",
    "gn:population":0,
    "gn:timezone":"Asia/Shanghai",
    "iso:country":"CN",
    "name:zho_x_preferred":[
        "\u6e2d\u52d2"
    ],
    "wof:name":"Weile",
    "wof:placetype":"locality"
},
  "geometry": {"coordinates":[105.64100000000001,23.8138],"type":"Point"}
}