{
  "type": "Feature",
  "properties": {
    "gn:admin1_code":"26",
    "gn:asciiname":"Wangcun",
    "gn:country_code":"CN",
    "gn:dem":481,
    "gn:feature_class":"P",
    "gn:feature_code":"PPL",
    "gn:name":"Wangcun",
    "gn:population":0,
    "gn:timezone":"Asia/Shanghai",
    "iso:country":"CN",
    "name:und_x_variant":[
        "\u738b\u6751"
    ],
    "name:zho_x_preferred":[
        "\u738b\u6751"
    ],
    "wof:name":"Wangcun",
    "wof:placetype":"locality"
},
  "geometry": {"coordinates":[108.78610999999999,34.47278],"type":"Point"}
}