{
  "type": "Feature",
  "properties": {
    "gn:admin1_code":"15.0",
    "gn:asciiname":"Heishan",
    "gn:country_code":"CN",
    "gn:dem":2330,
    "gn:feature_class":"P",
    "gn:feature_code":"PPL",
    "gn:name":"Heishan",
    "gn:population":0,
    "gn:timezone":"Asia/Shanghai",
    "iso:country":"CN",
    "name:ceb_x_preferred":[
        "Heishan"
    ],
    "name:deu_x_preferred":[
        "Heishan"
    ],
    "name:sco_x_preferred":[
        "Heishan"
    ],
    "name:zho_x_preferred":[
        "\u9ed1\u5c71"
    ],
    "wof:name":"Heishan",
    "wof:placetype":"locality"
},
  "geometry": {"coordinates":[104.267,35.4731],"type":"Point"}
}