{
  "type": "Feature",
  "properties": {
    "gn:admin1_code":"2.0",
    "gn:asciiname":"Yaojialing",
    "gn:country_code":"CN",
    "gn:dem":53,
    "gn:feature_class":"P",
    "gn:feature_code":"PPL",
    "gn:name":"Yaojialing",
    "gn:population":0,
    "gn:timezone":"Asia/Shanghai",
    "iso:country":"CN",
    "name:und_x_variant":[
        "\u59da\u5bb6\u5cad"
    ],
    "wof:name":"Yaojialing",
    "wof:placetype":"locality"
},
  "geometry": {"coordinates":[119.58763999999999,30.63082],"type":"Point"}
}