{
  "type": "Feature",
  "properties": {
    "gn:admin1_code":"7.0",
    "gn:asciiname":"Tingjiayang",
    "gn:country_code":"CN",
    "gn:dem":673,
    "gn:feature_class":"P",
    "gn:feature_code":"PPL",
    "gn:name":"Tingjiayang",
    "gn:population":0,
    "gn:timezone":"Asia/Shanghai",
    "iso:country":"CN",
    "name:zho_x_preferred":[
        "\u5ef7\u52a0\u6d0b"
    ],
    "wof:name":"Tingjiayang",
    "wof:placetype":"locality"
},
  "geometry": {"coordinates":[119.49062000000001,27.25412],"type":"Point"}
}