{
  "type": "Feature",
  "properties": {
    "gn:admin1_code":"15.0",
    "gn:asciiname":"Dongjiazhuang",
    "gn:country_code":"CN",
    "gn:dem":1424,
    "gn:feature_class":"P",
    "gn:feature_code":"PPL",
    "gn:name":"Dongjiazhuang",
    "gn:population":0,
    "gn:timezone":"Asia/Shanghai",
    "iso:country":"CN",
    "name:zho_x_preferred":[
        "\u8463\u5bb6\u5e84"
    ],
    "wof:name":"Dongjiazhuang",
    "wof:placetype":"locality"
},
  "geometry": {"coordinates":[108.319,35.5047],"type":"Point"}
}