{
  "type": "Feature",
  "properties": {
    "gn:admin1_code":"1.0",
    "gn:asciiname":"Huangjiawan",
    "gn:country_code":"CN",
    "gn:dem":50,
    "gn:feature_class":"P",
    "gn:feature_code":"PPL",
    "gn:name":"Huangjiawan",
    "gn:population":0,
    "gn:timezone":"Asia/Shanghai",
    "iso:country":"CN",
    "name:und_x_variant":[
        "\u9ec4\u5bb6\u6e7e"
    ],
    "wof:name":"Huangjiawan",
    "wof:placetype":"locality"
},
  "geometry": {"coordinates":[119.44134,30.8541],"type":"Point"}
}