{
  "type": "Feature",
  "properties": {
    "gn:admin1_code":"32.0",
    "gn:asciiname":"Sanguozhuang",
    "gn:country_code":"CN",
    "gn:dem":2407,
    "gn:feature_class":"P",
    "gn:feature_code":"PPL",
    "gn:name":"Sanguozhuang",
    "gn:population":0,
    "gn:timezone":"Asia/Shanghai",
    "iso:country":"CN",
    "name:zho_x_preferred":[
        "\u4e09\u56fd\u5e84"
    ],
    "wof:name":"Sanguozhuang",
    "wof:placetype":"locality"
},
  "geometry": {"coordinates":[102.00700000000001,27.2999],"type":"Point"}
}