{
  "type": "Feature",
  "properties": {
    "gn:admin1_code":"04",
    "gn:asciiname":"Caopie",
    "gn:country_code":"CN",
    "gn:dem":7,
    "gn:feature_class":"P",
    "gn:feature_code":"PPLA4",
    "gn:name":"Caopie",
    "gn:population":0,
    "gn:timezone":"Asia/Shanghai",
    "iso:country":"CN",
    "name:und_x_variant":[
        "Ts\u2019ao-ch\u2019ang-p\u2019ieh",
        "Ts\u2019ao-p\u2019ieh",
        "Caopie",
        "Caopie Zhen"
    ],
    "name:zho_x_preferred":[
        "\u66f9\u4e3f"
    ],
    "name:zho_x_variant":[
        "\u66f9\u4e3f\u9547"
    ],
    "wof:name":"Caopie",
    "wof:placetype":"locality"
},
  "geometry": {"coordinates":[120.66965999999999,32.86012],"type":"Point"}
}