{
  "type": "Feature",
  "properties": {
    "gn:admin1_code":"18",
    "gn:asciiname":"Yanghuayuan",
    "gn:country_code":"CN",
    "gn:dem":916,
    "gn:feature_class":"P",
    "gn:feature_code":"PPL",
    "gn:name":"Yanghuayuan",
    "gn:population":0,
    "gn:timezone":"Asia/Shanghai",
    "iso:country":"CN",
    "name:zho_x_preferred":[
        "\u6768\u5316\u56ed"
    ],
    "wof:name":"Yanghuayuan",
    "wof:placetype":"locality"
},
  "geometry": {"coordinates":[106.32599999999999,28.3926],"type":"Point"}
}