{
  "type": "Feature",
  "properties": {
    "gn:admin1_code":"3.0",
    "gn:asciiname":"Fangbei",
    "gn:country_code":"CN",
    "gn:dem":320,
    "gn:feature_class":"P",
    "gn:feature_code":"PPL",
    "gn:name":"Fangbei",
    "gn:population":0,
    "gn:timezone":"Asia/Shanghai",
    "iso:country":"CN",
    "name:und_x_variant":[
        "\u574a\u80cc"
    ],
    "wof:name":"Fangbei",
    "wof:placetype":"locality"
},
  "geometry": {"coordinates":[115.21044999999999,25.2593],"type":"Point"}
}