{
  "type": "Feature",
  "properties": {
    "gn:admin1_code":"1.0",
    "gn:asciiname":"Xielingcun",
    "gn:country_code":"CN",
    "gn:dem":56,
    "gn:feature_class":"P",
    "gn:feature_code":"PPL",
    "gn:name":"Xielingcun",
    "gn:population":0,
    "gn:timezone":"Asia/Shanghai",
    "iso:country":"CN",
    "name:zho_x_preferred":[
        "\u8c22\u5cad\u6751"
    ],
    "wof:name":"Xielingcun",
    "wof:placetype":"locality"
},
  "geometry": {"coordinates":[118.13909,32.57715],"type":"Point"}
}