{
  "type": "Feature",
  "properties": {
    "gn:admin1_code":"9",
    "gn:asciiname":"Houzhoulou",
    "gn:country_code":"CN",
    "gn:dem":49,
    "gn:feature_class":"P",
    "gn:feature_code":"PPL",
    "gn:name":"Houzhoulou",
    "gn:population":0,
    "gn:timezone":"Asia/Shanghai",
    "iso:country":"CN",
    "name:zho_x_preferred":[
        "\u540e\u5468\u697c"
    ],
    "wof:name":"Houzhoulou",
    "wof:placetype":"locality"
},
  "geometry": {"coordinates":[116.123,34.4117],"type":"Point"}
}