{
  "type": "Feature",
  "properties": {
    "gn:admin1_code":"5.0",
    "gn:asciiname":"Xiaxiaomiying",
    "gn:country_code":"CN",
    "gn:dem":427,
    "gn:feature_class":"P",
    "gn:feature_code":"PPL",
    "gn:name":"Xiaxiaomiying",
    "gn:population":0,
    "gn:timezone":"Asia/Shanghai",
    "iso:country":"CN",
    "name:zho_x_preferred":[
        "\u4e0b\u5c0f\u7c73\u8425"
    ],
    "wof:name":"Xiaxiaomiying",
    "wof:placetype":"locality"
},
  "geometry": {"coordinates":[125.89382000000001,41.62707],"type":"Point"}
}