{
  "type": "Feature",
  "properties": {
    "gn:admin1_code":"31",
    "gn:asciiname":"Baowen",
    "gn:country_code":"CN",
    "gn:dem":319,
    "gn:feature_class":"P",
    "gn:feature_code":"PPL",
    "gn:name":"Baowen",
    "gn:population":0,
    "gn:timezone":"Asia/Shanghai",
    "iso:country":"CN",
    "name:und_x_variant":[
        "\u4fdd\u6587"
    ],
    "wof:name":"Baowen",
    "wof:placetype":"locality"
},
  "geometry": {"coordinates":[109.379,18.5851],"type":"Point"}
}