{
  "type": "Feature",
  "properties": {
    "gn:admin1_code":"30",
    "gn:asciiname":"Longdong",
    "gn:country_code":"CN",
    "gn:dem":348,
    "gn:feature_class":"P",
    "gn:feature_code":"PPL",
    "gn:name":"Longdong",
    "gn:population":0,
    "gn:timezone":"Asia/Shanghai",
    "iso:country":"CN",
    "name:ceb_x_preferred":[
        "Longdong"
    ],
    "name:swe_x_preferred":[
        "Longdong"
    ],
    "wof:name":"Longdong",
    "wof:placetype":"locality"
},
  "geometry": {"coordinates":[115.50221999999999,23.71667],"type":"Point"}
}