{
  "type": "Feature",
  "properties": {
    "gn:admin1_code":"18.0",
    "gn:asciiname":"Fadi",
    "gn:country_code":"CN",
    "gn:dem":2381,
    "gn:feature_class":"P",
    "gn:feature_code":"PPL",
    "gn:name":"Fadi",
    "gn:population":0,
    "gn:timezone":"Asia/Shanghai",
    "iso:country":"CN",
    "name:zho_x_preferred":[
        "\u6cd5\u5730"
    ],
    "wof:name":"Fadi",
    "wof:placetype":"locality"
},
  "geometry": {"coordinates":[104.18000000000001,27.1053],"type":"Point"}
}