{
  "type": "Feature",
  "properties": {
    "gn:admin1_code":"32.0",
    "gn:asciiname":"Keke",
    "gn:country_code":"CN",
    "gn:dem":1626,
    "gn:feature_class":"P",
    "gn:feature_code":"PPL",
    "gn:name":"Keke",
    "gn:population":0,
    "gn:timezone":"Asia/Shanghai",
    "iso:country":"CN",
    "name:ceb_x_preferred":[
        "Keke"
    ],
    "name:fin_x_preferred":[
        "Keke"
    ],
    "name:fra_x_preferred":[
        "Keke"
    ],
    "name:por_x_preferred":[
        "Keke"
    ],
    "name:swe_x_preferred":[
        "Keke"
    ],
    "name:zho_x_preferred":[
        "\u58f3\u58f3"
    ],
    "wof:name":"Keke",
    "wof:placetype":"locality"
},
  "geometry": {"coordinates":[103.80200000000001,31.6548],"type":"Point"}
}