{
  "type": "Feature",
  "properties": {
    "gn:admin1_code":"33.0",
    "gn:asciiname":"Puya",
    "gn:country_code":"CN",
    "gn:dem":371,
    "gn:feature_class":"P",
    "gn:feature_code":"PPL",
    "gn:name":"Puya",
    "gn:population":0,
    "gn:timezone":"Asia/Shanghai",
    "iso:country":"CN",
    "name:fra_x_preferred":[
        "Puya"
    ],
    "name:ita_x_preferred":[
        "Puya"
    ],
    "name:ron_x_preferred":[
        "Puya"
    ],
    "name:rus_x_preferred":[
        "\u041f\u0443\u0439\u044f"
    ],
    "name:spa_x_preferred":[
        "Puya"
    ],
    "name:vie_x_preferred":[
        "Puya"
    ],
    "name:zho_x_preferred":[
        "\u84b2\u9e2d"
    ],
    "wof:name":"Puya",
    "wof:placetype":"locality"
},
  "geometry": {"coordinates":[106.16397000000001,29.63865],"type":"Point"}
}