{
  "type": "Feature",
  "properties": {
    "gn:admin1_code":"29.0",
    "gn:asciiname":"Mangweng",
    "gn:country_code":"CN",
    "gn:dem":1348,
    "gn:feature_class":"P",
    "gn:feature_code":"PPL",
    "gn:name":"Mangweng",
    "gn:population":0,
    "gn:timezone":"Asia/Shanghai",
    "iso:country":"CN",
    "name:zho_x_preferred":[
        "\u8292\u7fc1"
    ],
    "wof:name":"Mangweng",
    "wof:placetype":"locality"
},
  "geometry": {"coordinates":[99.4706,23.428],"type":"Point"}
}