{
  "type": "Feature",
  "properties": {
    "gn:admin1_code":"15.0",
    "gn:asciiname":"Yaodonggou",
    "gn:country_code":"CN",
    "gn:dem":1827,
    "gn:feature_class":"P",
    "gn:feature_code":"PPL",
    "gn:name":"Yaodonggou",
    "gn:population":0,
    "gn:timezone":"Asia/Urumqi",
    "iso:country":"CN",
    "name:zho_x_preferred":[
        "\u7a91\u6d1e\u6c9f"
    ],
    "wof:name":"Yaodonggou",
    "wof:placetype":"locality"
},
  "geometry": {"coordinates":[96.84529999999999,40.9977],"type":"Point"}
}