{
  "type": "Feature",
  "properties": {
    "gn:admin1_code":"10.0",
    "gn:asciiname":"Yuanzhuangzi",
    "gn:country_code":"CN",
    "gn:dem":7,
    "gn:feature_class":"P",
    "gn:feature_code":"PPL",
    "gn:name":"Yuanzhuangzi",
    "gn:population":0,
    "gn:timezone":"Asia/Shanghai",
    "iso:country":"CN",
    "name:zho_x_preferred":[
        "\u82d1\u5e84\u5b50"
    ],
    "wof:name":"Yuanzhuangzi",
    "wof:placetype":"locality"
},
  "geometry": {"coordinates":[118.81041,39.41244],"type":"Point"}
}