{
  "type": "Feature",
  "properties": {
    "gn:admin1_code":"2.0",
    "gn:asciiname":"Xijiaozhu",
    "gn:country_code":"CN",
    "gn:dem":23,
    "gn:feature_class":"P",
    "gn:feature_code":"PPL",
    "gn:name":"Xijiaozhu",
    "gn:population":0,
    "gn:timezone":"Asia/Shanghai",
    "iso:country":"CN",
    "name:zho_x_preferred":[
        "\u897f\u4ea4\u6731"
    ],
    "wof:name":"Xijiaozhu",
    "wof:placetype":"locality"
},
  "geometry": {"coordinates":[121.61445000000001,29.29996],"type":"Point"}
}