{
  "type": "Feature",
  "properties": {
    "gn:admin1_code":"2",
    "gn:asciiname":"Xidui",
    "gn:country_code":"CN",
    "gn:dem":160,
    "gn:feature_class":"P",
    "gn:feature_code":"PPL",
    "gn:name":"Xidui",
    "gn:population":0,
    "gn:timezone":"Asia/Shanghai",
    "iso:country":"CN",
    "name:und_x_variant":[
        "\u897f\u5806"
    ],
    "name:zho_x_preferred":[
        "\u897f\u5806"
    ],
    "wof:name":"Xidui",
    "wof:placetype":"locality"
},
  "geometry": {"coordinates":[120.42125,29.15241],"type":"Point"}
}