{
  "type": "Feature",
  "properties": {
    "gn:admin1_code":"5.0",
    "gn:asciiname":"Fuguocun",
    "gn:country_code":"CN",
    "gn:dem":192,
    "gn:feature_class":"P",
    "gn:feature_code":"PPL",
    "gn:name":"Fuguocun",
    "gn:population":0,
    "gn:timezone":"Asia/Shanghai",
    "iso:country":"CN",
    "name:zho_x_preferred":[
        "\u5bcc\u56fd\u6751"
    ],
    "wof:name":"Fuguocun",
    "wof:placetype":"locality"
},
  "geometry": {"coordinates":[126.14658,44.86445],"type":"Point"}
}