{
  "type": "Feature",
  "properties": {
    "gn:admin1_code":"24.0",
    "gn:asciiname":"Daheizhuang",
    "gn:country_code":"CN",
    "gn:dem":1361,
    "gn:feature_class":"P",
    "gn:feature_code":"PPL",
    "gn:name":"Daheizhuang",
    "gn:population":0,
    "gn:timezone":"Asia/Shanghai",
    "iso:country":"CN",
    "name:und_x_variant":[
        "\u5927\u9ed1\u5e84"
    ],
    "name:zho_x_preferred":[
        "\u5927\u9ed1\u5e84"
    ],
    "wof:name":"Daheizhuang",
    "wof:placetype":"locality"
},
  "geometry": {"coordinates":[111.9425,39.06736],"type":"Point"}
}