{
  "type": "Feature",
  "properties": {
    "gn:admin1_code":"12.0",
    "gn:asciiname":"Xiahuanglongguan",
    "gn:country_code":"CN",
    "gn:dem":71,
    "gn:feature_class":"P",
    "gn:feature_code":"PPL",
    "gn:name":"Xiahuanglongguan",
    "gn:population":0,
    "gn:timezone":"Asia/Shanghai",
    "iso:country":"CN",
    "name:zho_x_preferred":[
        "\u4e0b\u9ec4\u9f99\u89c2"
    ],
    "wof:name":"Xiahuanglongguan",
    "wof:placetype":"locality"
},
  "geometry": {"coordinates":[112.13442999999999,31.88962],"type":"Point"}
}