{
  "type": "Feature",
  "properties": {
    "gn:admin1_code":"07",
    "gn:asciiname":"Jianxiaqian",
    "gn:country_code":"CN",
    "gn:dem":190,
    "gn:feature_class":"P",
    "gn:feature_code":"PPL",
    "gn:name":"Jianxiaqian",
    "gn:population":0,
    "gn:timezone":"Asia/Shanghai",
    "iso:country":"CN",
    "name:zho_x_preferred":[
        "\u67a7\u4e0b\u524d"
    ],
    "wof:name":"Jianxiaqian",
    "wof:placetype":"locality"
},
  "geometry": {"coordinates":[116.68481,24.70639],"type":"Point"}
}