{
  "type": "Feature",
  "properties": {
    "gn:admin1_code":"4.0",
    "gn:asciiname":"Zongpingloucun",
    "gn:country_code":"CN",
    "gn:dem":38,
    "gn:feature_class":"P",
    "gn:feature_code":"PPL",
    "gn:name":"Zongpingloucun",
    "gn:population":0,
    "gn:timezone":"Asia/Shanghai",
    "iso:country":"CN",
    "name:zho_x_preferred":[
        "\u8e2a\u5e73\u697c\u6751"
    ],
    "wof:name":"Zongpingloucun",
    "wof:placetype":"locality"
},
  "geometry": {"coordinates":[116.70726999999999,34.78967],"type":"Point"}
}