{
  "type": "Feature",
  "properties": {
    "gn:admin1_code":"10.0",
    "gn:asciiname":"Balinggou",
    "gn:country_code":"CN",
    "gn:dem":71,
    "gn:feature_class":"P",
    "gn:feature_code":"PPL",
    "gn:name":"Balinggou",
    "gn:population":0,
    "gn:timezone":"Asia/Shanghai",
    "iso:country":"CN",
    "name:zho_x_preferred":[
        "\u516b\u5cad\u6c9f"
    ],
    "wof:name":"Balinggou",
    "wof:placetype":"locality"
},
  "geometry": {"coordinates":[119.52136000000002,40.04015],"type":"Point"}
}