{
  "type": "Feature",
  "properties": {
    "gn:admin1_code":"11.0",
    "gn:asciiname":"Xiaqinmiao",
    "gn:country_code":"CN",
    "gn:dem":438,
    "gn:feature_class":"P",
    "gn:feature_code":"PPL",
    "gn:name":"Xiaqinmiao",
    "gn:population":0,
    "gn:timezone":"Asia/Shanghai",
    "iso:country":"CN",
    "name:zho_x_preferred":[
        "\u4e0b\u7434\u5e99"
    ],
    "wof:name":"Xiaqinmiao",
    "wof:placetype":"locality"
},
  "geometry": {"coordinates":[109.85295000000001,26.73964],"type":"Point"}
}