{
  "type": "Feature",
  "properties": {
    "gn:admin1_code":"2.0",
    "gn:asciiname":"Luotangtou",
    "gn:country_code":"CN",
    "gn:dem":6,
    "gn:feature_class":"P",
    "gn:feature_code":"PPL",
    "gn:name":"Luotangtou",
    "gn:population":0,
    "gn:timezone":"Asia/Shanghai",
    "iso:country":"CN",
    "name:und_x_variant":[
        "\u843d\u5858\u5934"
    ],
    "wof:name":"Luotangtou",
    "wof:placetype":"locality"
},
  "geometry": {"coordinates":[120.92967,30.47407],"type":"Point"}
}