{
  "type": "Feature",
  "properties": {
    "gn:admin1_code":"1.0",
    "gn:asciiname":"Liyingcun",
    "gn:country_code":"CN",
    "gn:dem":57,
    "gn:feature_class":"P",
    "gn:feature_code":"PPL",
    "gn:name":"Liyingcun",
    "gn:population":0,
    "gn:timezone":"Asia/Shanghai",
    "iso:country":"CN",
    "name:zho_x_preferred":[
        "\u674e\u90e2\u6751"
    ],
    "wof:name":"Liyingcun",
    "wof:placetype":"locality"
},
  "geometry": {"coordinates":[116.42698,31.89287],"type":"Point"}
}