{
  "type": "Feature",
  "properties": {
    "gn:admin1_code":"25.0",
    "gn:asciiname":"Xiaokuang",
    "gn:country_code":"CN",
    "gn:dem":46,
    "gn:feature_class":"P",
    "gn:feature_code":"PPL",
    "gn:name":"Xiaokuang",
    "gn:population":0,
    "gn:timezone":"Asia/Shanghai",
    "iso:country":"CN",
    "name:zho_x_preferred":[
        "\u5c0f\u593c"
    ],
    "wof:name":"Xiaokuang",
    "wof:placetype":"locality"
},
  "geometry": {"coordinates":[121.09335,37.45477],"type":"Point"}
}