{
  "type": "Feature",
  "properties": {
    "gn:admin1_code":"7.0",
    "gn:asciiname":"Pushan",
    "gn:country_code":"CN",
    "gn:dem":84,
    "gn:feature_class":"P",
    "gn:feature_code":"PPL",
    "gn:name":"Pushan",
    "gn:population":0,
    "gn:timezone":"Asia/Shanghai",
    "iso:country":"CN",
    "name:zho_x_preferred":[
        "\u84b2\u5c71"
    ],
    "wof:name":"Pushan",
    "wof:placetype":"locality"
},
  "geometry": {"coordinates":[118.64276,25.38479],"type":"Point"}
}