{
  "type": "Feature",
  "properties": {
    "gn:admin1_code":"29.0",
    "gn:asciiname":"Dafandoudi",
    "gn:country_code":"CN",
    "gn:dem":640,
    "gn:feature_class":"P",
    "gn:feature_code":"PPL",
    "gn:name":"Dafandoudi",
    "gn:population":0,
    "gn:timezone":"Asia/Shanghai",
    "iso:country":"CN",
    "name:zho_x_preferred":[
        "\u5927\u996d\u8c46\u5730"
    ],
    "wof:name":"Dafandoudi",
    "wof:placetype":"locality"
},
  "geometry": {"coordinates":[99.2907,23.6739],"type":"Point"}
}