{
  "type": "Feature",
  "properties": {
    "gn:admin1_code":"15.0",
    "gn:asciiname":"Zhahasi",
    "gn:country_code":"CN",
    "gn:dem":2535,
    "gn:feature_class":"P",
    "gn:feature_code":"PPL",
    "gn:name":"Zhahasi",
    "gn:population":0,
    "gn:timezone":"Asia/Shanghai",
    "iso:country":"CN",
    "name:und_x_variant":[
        "\u624e\u54c8\u5bfa"
    ],
    "wof:name":"Zhahasi",
    "wof:placetype":"locality"
},
  "geometry": {"coordinates":[104.52958,34.49055],"type":"Point"}
}