{
  "type": "Feature",
  "properties": {
    "gn:admin1_code":"10.0",
    "gn:asciiname":"Nanxinxing",
    "gn:country_code":"CN",
    "gn:dem":56,
    "gn:feature_class":"P",
    "gn:feature_code":"PPL",
    "gn:name":"Nanxinxing",
    "gn:population":0,
    "gn:timezone":"Asia/Shanghai",
    "iso:country":"CN",
    "name:und_x_variant":[
        "\u5357\u8f9b\u5174"
    ],
    "wof:name":"Nanxinxing",
    "wof:placetype":"locality"
},
  "geometry": {"coordinates":[114.93411,38.39328],"type":"Point"}
}