{
  "type": "Feature",
  "properties": {
    "gn:admin1_code":"31.0",
    "gn:asciiname":"Wenfeng",
    "gn:country_code":"CN",
    "gn:dem":19,
    "gn:feature_class":"P",
    "gn:feature_code":"PPL",
    "gn:name":"Wenfeng",
    "gn:population":0,
    "gn:timezone":"Asia/Shanghai",
    "iso:country":"CN",
    "name:zho_x_preferred":[
        "\u6587\u4e30"
    ],
    "wof:name":"Wenfeng",
    "wof:placetype":"locality"
},
  "geometry": {"coordinates":[110.3506,19.72375],"type":"Point"}
}