{
  "type": "Feature",
  "properties": {
    "gn:admin1_code":"5.0",
    "gn:asciiname":"Xiawazicun",
    "gn:country_code":"CN",
    "gn:dem":203,
    "gn:feature_class":"P",
    "gn:feature_code":"PPL",
    "gn:name":"Xiawazicun",
    "gn:population":0,
    "gn:timezone":"Asia/Shanghai",
    "iso:country":"CN",
    "name:zho_x_preferred":[
        "\u4e0b\u6d3c\u5b50\u6751"
    ],
    "wof:name":"Xiawazicun",
    "wof:placetype":"locality"
},
  "geometry": {"coordinates":[126.20599,43.87448],"type":"Point"}
}