{
  "type": "Feature",
  "properties": {
    "gn:admin1_code":"2.0",
    "gn:asciiname":"Majiawu",
    "gn:country_code":"CN",
    "gn:dem":359,
    "gn:feature_class":"P",
    "gn:feature_code":"PPL",
    "gn:name":"Majiawu",
    "gn:population":0,
    "gn:timezone":"Asia/Shanghai",
    "iso:country":"CN",
    "name:und_x_variant":[
        "\u9a6c\u5bb6\u575e",
        "Majiawu"
    ],
    "wof:name":"Majiawu",
    "wof:placetype":"locality"
},
  "geometry": {"coordinates":[119.92979,29.85776],"type":"Point"}
}