{
  "type": "Feature",
  "properties": {
    "gn:admin1_code":"16",
    "gn:asciiname":"Chengqiangjie",
    "gn:country_code":"CN",
    "gn:dem":897,
    "gn:feature_class":"P",
    "gn:feature_code":"PPL",
    "gn:name":"Chengqiangjie",
    "gn:population":0,
    "gn:timezone":"Asia/Shanghai",
    "iso:country":"CN",
    "name:zho_x_preferred":[
        "\u57ce\u5899\u754c"
    ],
    "wof:name":"Chengqiangjie",
    "wof:placetype":"locality"
},
  "geometry": {"coordinates":[110.98099999999999,25.4195],"type":"Point"}
}