{
  "type": "Feature",
  "properties": {
    "gn:admin1_code":"16.0",
    "gn:asciiname":"Luezhitang",
    "gn:country_code":"CN",
    "gn:dem":49,
    "gn:feature_class":"P",
    "gn:feature_code":"PPL",
    "gn:name":"Luezhitang",
    "gn:population":0,
    "gn:timezone":"Asia/Shanghai",
    "iso:country":"CN",
    "name:zho_x_preferred":[
        "\u7565\u679d\u5858"
    ],
    "wof:name":"Luezhitang",
    "wof:placetype":"locality"
},
  "geometry": {"coordinates":[109.803,22.1382],"type":"Point"}
}