{
  "type": "Feature",
  "properties": {
    "gn:admin1_code":"29.0",
    "gn:asciiname":"Muzheye",
    "gn:country_code":"CN",
    "gn:dem":3114,
    "gn:feature_class":"P",
    "gn:feature_code":"PPL",
    "gn:name":"Muzheye",
    "gn:population":0,
    "gn:timezone":"Asia/Shanghai",
    "iso:country":"CN",
    "name:zho_x_preferred":[
        "\u6728\u8005\u8036"
    ],
    "wof:name":"Muzheye",
    "wof:placetype":"locality"
},
  "geometry": {"coordinates":[99.6925,26.8954],"type":"Point"}
}