{
  "type": "Feature",
  "properties": {
    "gn:admin1_code":"25.0",
    "gn:asciiname":"Shanghetoucun",
    "gn:country_code":"CN",
    "gn:dem":34,
    "gn:feature_class":"P",
    "gn:feature_code":"PPL",
    "gn:name":"Shanghetoucun",
    "gn:population":0,
    "gn:timezone":"Asia/Shanghai",
    "iso:country":"CN",
    "name:zho_x_preferred":[
        "\u5c1a\u6cb3\u5934\u6751"
    ],
    "wof:name":"Shanghetoucun",
    "wof:placetype":"locality"
},
  "geometry": {"coordinates":[120.13066000000001,36.69822],"type":"Point"}
}