{
  "type": "Feature",
  "properties": {
    "gn:admin1_code":"25.0",
    "gn:asciiname":"Zekoujicun",
    "gn:country_code":"CN",
    "gn:dem":40,
    "gn:feature_class":"P",
    "gn:feature_code":"PPL",
    "gn:name":"Zekoujicun",
    "gn:population":0,
    "gn:timezone":"Asia/Shanghai",
    "iso:country":"CN",
    "name:zho_x_preferred":[
        "\u6cfd\u53e3\u96c6\u6751"
    ],
    "wof:name":"Zekoujicun",
    "wof:placetype":"locality"
},
  "geometry": {"coordinates":[120.57535,36.71749000000001],"type":"Point"}
}