{
  "type": "Feature",
  "properties": {
    "gn:admin1_code":"16.0",
    "gn:asciiname":"Wangnichong",
    "gn:country_code":"CN",
    "gn:dem":97,
    "gn:feature_class":"P",
    "gn:feature_code":"PPL",
    "gn:name":"Wangnichong",
    "gn:population":0,
    "gn:timezone":"Asia/Shanghai",
    "iso:country":"CN",
    "name:zho_x_preferred":[
        "\u65fa\u576d\u51b2"
    ],
    "wof:name":"Wangnichong",
    "wof:placetype":"locality"
},
  "geometry": {"coordinates":[110.31399999999999,22.0741],"type":"Point"}
}