{
  "type": "Feature",
  "properties": {
    "gn:admin1_code":"9.0",
    "gn:asciiname":"Nanjie",
    "gn:country_code":"CN",
    "gn:dem":321,
    "gn:feature_class":"P",
    "gn:feature_code":"PPL",
    "gn:name":"Nanjie",
    "gn:population":0,
    "gn:timezone":"Asia/Shanghai",
    "iso:country":"CN",
    "name:deu_x_preferred":[
        "Nanjie"
    ],
    "name:fas_x_preferred":[
        "\u0646\u0627\u0646\u062c\u06cc"
    ],
    "name:fra_x_preferred":[
        "Nanjiecun"
    ],
    "name:jpn_x_preferred":[
        "\u5357\u8857\u6751"
    ],
    "name:nld_x_preferred":[
        "Nanjie"
    ],
    "name:swe_x_preferred":[
        "Nanjie"
    ],
    "name:zho_x_preferred":[
        "\u5357\u8857"
    ],
    "name:zho_x_variant":[
        "\u5357\u8857\u6751"
    ],
    "wof:name":"Nanjie",
    "wof:placetype":"locality"
},
  "geometry": {"coordinates":[112.45863,34.15018],"type":"Point"}
}