{
  "type": "Feature",
  "properties": {
    "gn:admin1_code":"22.0",
    "gn:asciiname":"Qianquhe",
    "gn:country_code":"CN",
    "gn:dem":39,
    "gn:feature_class":"P",
    "gn:feature_code":"PPL",
    "gn:name":"Qianquhe",
    "gn:population":0,
    "gn:timezone":"Asia/Shanghai",
    "iso:country":"CN",
    "name:zho_x_preferred":[
        "\u524d\u6e20\u6cb3"
    ],
    "wof:name":"Qianquhe",
    "wof:placetype":"locality"
},
  "geometry": {"coordinates":[116.52549999999999,40.14863],"type":"Point"}
}