{
  "type": "Feature",
  "properties": {
    "gn:admin1_code":"4.0",
    "gn:asciiname":"Xucheng",
    "gn:cc2":"CN",
    "gn:country_code":"CN",
    "gn:dem":45,
    "gn:feature_class":"P",
    "gn:feature_code":"PPL",
    "gn:name":"Xucheng",
    "gn:population":0,
    "gn:timezone":"Asia/Shanghai",
    "iso:country":"CN",
    "name:und_x_variant":[
        "Chuyi",
        "Xuyi",
        "Hs\u00fc-ch\u2019eng-chen",
        "Chuyihsien",
        "Hs\u00fc-i-ch\u2019eng",
        "Hs\u00fc-i-hsien",
        "Hs\u00fc-i",
        "Xucheng"
    ],
    "wof:name":"Xucheng",
    "wof:placetype":"locality"
},
  "geometry": {"coordinates":[118.48860999999999,33.01111],"type":"Point"}
}