{
  "type": "Feature",
  "properties": {
    "gn:admin1_code":"1.0",
    "gn:asciiname":"Sangxiaomiaocun",
    "gn:country_code":"CN",
    "gn:dem":39,
    "gn:feature_class":"P",
    "gn:feature_code":"PPL",
    "gn:name":"Sangxiaomiaocun",
    "gn:population":0,
    "gn:timezone":"Asia/Shanghai",
    "iso:country":"CN",
    "name:zho_x_preferred":[
        "\u6851\u5c0f\u5e99\u6751"
    ],
    "wof:name":"Sangxiaomiaocun",
    "wof:placetype":"locality"
},
  "geometry": {"coordinates":[115.65783,33.54494],"type":"Point"}
}