{
  "type": "Feature",
  "properties": {
    "gn:admin1_code":"16",
    "gn:asciiname":"Sanli",
    "gn:cc2":"CN",
    "gn:country_code":"CN",
    "gn:dem":55,
    "gn:feature_class":"P",
    "gn:feature_code":"PPL",
    "gn:name":"Sanli",
    "gn:population":0,
    "gn:timezone":"Asia/Shanghai",
    "iso:country":"CN",
    "name:deu_x_preferred":[
        "Sanli"
    ],
    "name:und_x_variant":[
        "San-li-hs\u00fc"
    ],
    "wof:name":"Sanli",
    "wof:placetype":"locality"
},
  "geometry": {"coordinates":[109.38333,23.05],"type":"Point"}
}