{
  "type": "Feature",
  "properties": {
    "gn:admin1_code":"7.0",
    "gn:asciiname":"Tiandi",
    "gn:country_code":"CN",
    "gn:dem":347,
    "gn:feature_class":"P",
    "gn:feature_code":"PPL",
    "gn:name":"Tiandi",
    "gn:population":0,
    "gn:timezone":"Asia/Shanghai",
    "iso:country":"CN",
    "name:und_x_variant":[
        "\u7530\u5730"
    ],
    "name:zho_x_preferred":[
        "\u7530\u5730"
    ],
    "wof:name":"Tiandi",
    "wof:placetype":"locality"
},
  "geometry": {"coordinates":[118.20113000000001,26.51367],"type":"Point"}
}