{
  "type": "Feature",
  "properties": {
    "gn:admin1_code":"24.0",
    "gn:asciiname":"Cilincun",
    "gn:country_code":"CN",
    "gn:dem":827,
    "gn:feature_class":"P",
    "gn:feature_code":"PPL",
    "gn:name":"Cilincun",
    "gn:population":0,
    "gn:timezone":"Asia/Shanghai",
    "iso:country":"CN",
    "name:zho_x_preferred":[
        "\u8328\u6797\u6751"
    ],
    "wof:name":"Cilincun",
    "wof:placetype":"locality"
},
  "geometry": {"coordinates":[110.81914999999999,36.36771],"type":"Point"}
}