{
  "type": "Feature",
  "properties": {
    "gn:admin1_code":"10",
    "gn:asciiname":"Dongshi Haipo",
    "gn:country_code":"CN",
    "gn:dem":21,
    "gn:feature_class":"P",
    "gn:feature_code":"PPL",
    "gn:name":"Dongshi Haipo",
    "gn:population":0,
    "gn:timezone":"Asia/Shanghai",
    "iso:country":"CN",
    "name:zho_x_preferred":[
        "\u4e1c\u77f3\u6d77\u5761"
    ],
    "wof:name":"Dongshi Haipo",
    "wof:placetype":"locality"
},
  "geometry": {"coordinates":[116.05285000000001,37.88858],"type":"Point"}
}