{
  "type": "Feature",
  "properties": {
    "gn:admin1_code":"18",
    "gn:asciiname":"Maipang",
    "gn:country_code":"CN",
    "gn:dem":1018,
    "gn:feature_class":"P",
    "gn:feature_code":"PPL",
    "gn:name":"Maipang",
    "gn:population":0,
    "gn:timezone":"Asia/Shanghai",
    "iso:country":"CN",
    "name:zho_x_preferred":[
        "\u9ea6\u65c1"
    ],
    "wof:name":"Maipang",
    "wof:placetype":"locality"
},
  "geometry": {"coordinates":[106.456,25.9385],"type":"Point"}
}