{
  "type": "Feature",
  "properties": {
    "gn:admin1_code":"12.0",
    "gn:asciiname":"Zhengjiaqiao",
    "gn:country_code":"CN",
    "gn:dem":44,
    "gn:feature_class":"P",
    "gn:feature_code":"PPL",
    "gn:name":"Zhengjiaqiao",
    "gn:population":0,
    "gn:timezone":"Asia/Shanghai",
    "iso:country":"CN",
    "name:zho_x_preferred":[
        "Zhengjiaqiao"
    ],
    "name:zho_x_variant":[
        "\u90d1\u5bb6\u6865"
    ],
    "wof:name":"Zhengjiaqiao",
    "wof:placetype":"locality"
},
  "geometry": {"coordinates":[111.77885000000001,30.35014],"type":"Point"}
}