{
  "type": "Feature",
  "properties": {
    "gn:admin1_code":"11.0",
    "gn:asciiname":"Ganyumiao",
    "gn:country_code":"CN",
    "gn:dem":379,
    "gn:feature_class":"P",
    "gn:feature_code":"PPL",
    "gn:name":"Ganyumiao",
    "gn:population":0,
    "gn:timezone":"Asia/Shanghai",
    "iso:country":"CN",
    "name:zho_x_preferred":[
        "\u5e72\u9c7c\u5e99"
    ],
    "wof:name":"Ganyumiao",
    "wof:placetype":"locality"
},
  "geometry": {"coordinates":[110.96992,28.95352],"type":"Point"}
}