{
  "type": "Feature",
  "properties": {
    "gn:admin1_code":"20.0",
    "gn:asciiname":"Bafangdi",
    "gn:country_code":"CN",
    "gn:dem":434,
    "gn:feature_class":"P",
    "gn:feature_code":"PPL",
    "gn:name":"Bafangdi",
    "gn:population":0,
    "gn:timezone":"Asia/Shanghai",
    "iso:country":"CN",
    "name:zho_x_preferred":[
        "\u516b\u65b9\u5730"
    ],
    "wof:name":"Bafangdi",
    "wof:placetype":"locality"
},
  "geometry": {"coordinates":[122.29429,47.64598],"type":"Point"}
}