{
  "type": "Feature",
  "properties": {
    "gn:admin1_code":"07",
    "gn:asciiname":"Panlong",
    "gn:country_code":"CN",
    "gn:dem":802,
    "gn:feature_class":"P",
    "gn:feature_code":"PPL",
    "gn:name":"Panlong",
    "gn:population":0,
    "gn:timezone":"Asia/Shanghai",
    "iso:country":"CN",
    "name:zho_x_preferred":[
        "\u87e0\u9f99"
    ],
    "wof:name":"Panlong",
    "wof:placetype":"locality"
},
  "geometry": {"coordinates":[118.33613,25.70657000000001],"type":"Point"}
}