{
  "type": "Feature",
  "properties": {
    "gn:admin1_code":"29.0",
    "gn:asciiname":"Lemahua",
    "gn:country_code":"CN",
    "gn:dem":2527,
    "gn:feature_class":"P",
    "gn:feature_code":"PPL",
    "gn:name":"Lemahua",
    "gn:population":0,
    "gn:timezone":"Asia/Shanghai",
    "iso:country":"CN",
    "name:zho_x_preferred":[
        "\u52d2\u9a6c\u82b1"
    ],
    "wof:name":"Lemahua",
    "wof:placetype":"locality"
},
  "geometry": {"coordinates":[99.66930000000001,27.4126],"type":"Point"}
}