{
  "type": "Feature",
  "properties": {
    "gn:admin1_code":"13",
    "gn:asciiname":"Talati",
    "gn:country_code":"CN",
    "gn:dem":1601,
    "gn:feature_class":"P",
    "gn:feature_code":"PPL",
    "gn:name":"Talati",
    "gn:population":0,
    "gn:timezone":"Asia/Urumqi",
    "iso:country":"CN",
    "name:zho_x_preferred":[
        "\u5854\u62c9\u63d0"
    ],
    "wof:name":"Talati",
    "wof:placetype":"locality"
},
  "geometry": {"coordinates":[93.42207000000001,43.22563],"type":"Point"}
}