{
  "type": "Feature",
  "properties": {
    "gn:admin1_code":"29.0",
    "gn:asciiname":"Xiyangtang",
    "gn:country_code":"CN",
    "gn:dem":2074,
    "gn:feature_class":"P",
    "gn:feature_code":"PPL",
    "gn:name":"Xiyangtang",
    "gn:population":0,
    "gn:timezone":"Asia/Shanghai",
    "iso:country":"CN",
    "name:zho_x_preferred":[
        "\u6d17\u7f8a\u5858"
    ],
    "wof:name":"Xiyangtang",
    "wof:placetype":"locality"
},
  "geometry": {"coordinates":[104.12,25.3716],"type":"Point"}
}