{
  "type": "Feature",
  "properties": {
    "gn:admin1_code":"16.0",
    "gn:asciiname":"Yaogan",
    "gn:country_code":"CN",
    "gn:dem":852,
    "gn:feature_class":"P",
    "gn:feature_code":"PPL",
    "gn:name":"Yaogan",
    "gn:population":0,
    "gn:timezone":"Asia/Shanghai",
    "iso:country":"CN",
    "name:deu_x_preferred":[
        "Yaogan Weixing"
    ],
    "name:fin_x_preferred":[
        "Yaogan"
    ],
    "name:fra_x_preferred":[
        "Yaogan"
    ],
    "name:ita_x_preferred":[
        "YaoGan"
    ],
    "name:jpn_x_preferred":[
        "\u9065\u611f\u885b\u661f"
    ],
    "name:kor_x_preferred":[
        "\uc57c\uc624\uac04 \uc704\uc131"
    ],
    "name:rus_x_preferred":[
        "\u042f\u043e\u0433\u0430\u043d\u044c"
    ],
    "name:und_x_variant":[
        "Megan"
    ],
    "name:zho_x_preferred":[
        "\u4e48\u5e72"
    ],
    "name:zho_x_variant":[
        "\u5c16\u5175\u7cfb\u5217\u536b\u661f"
    ],
    "wof:name":"Yaogan",
    "wof:placetype":"locality"
},
  "geometry": {"coordinates":[107.748,25.0906],"type":"Point"}
}