{
  "type": "Feature",
  "properties": {
    "gn:admin1_code":"16.0",
    "gn:asciiname":"Ruitun",
    "gn:country_code":"CN",
    "gn:dem":384,
    "gn:feature_class":"P",
    "gn:feature_code":"PPL",
    "gn:name":"Ruitun",
    "gn:population":0,
    "gn:timezone":"Asia/Shanghai",
    "iso:country":"CN",
    "name:zho_x_preferred":[
        "\u745e\u5c6f"
    ],
    "wof:name":"Ruitun",
    "wof:placetype":"locality"
},
  "geometry": {"coordinates":[107.062,22.9283],"type":"Point"}
}