{
  "type": "Feature",
  "properties": {
    "gn:admin1_code":"14.0",
    "gn:asciiname":"Mainda",
    "gn:country_code":"CN",
    "gn:dem":4385,
    "gn:feature_class":"P",
    "gn:feature_code":"PPLF",
    "gn:name":"Mainda",
    "gn:population":0,
    "gn:timezone":"Asia/Urumqi",
    "iso:country":"CN",
    "name:bod_x_preferred":[
        "Mainda"
    ],
    "name:msa_x_preferred":[
        "Mainda"
    ],
    "name:zho_x_preferred":[
        "Mianda"
    ],
    "name:zho_x_variant":[
        "\u9762\u8fbe"
    ],
    "wof:name":"Mainda",
    "wof:placetype":"locality"
},
  "geometry": {"coordinates":[97.28333000000001,32.03333],"type":"Point"}
}