{
  "type": "Feature",
  "properties": {
    "gn:admin1_code":"7",
    "gn:asciiname":"Zhuzilu",
    "gn:country_code":"CN",
    "gn:dem":915,
    "gn:feature_class":"P",
    "gn:feature_code":"PPL",
    "gn:name":"Zhuzil\u00fc",
    "gn:population":0,
    "gn:timezone":"Asia/Shanghai",
    "iso:country":"CN",
    "name:zho_x_preferred":[
        "\u7af9\u5b50\u9a74"
    ],
    "name:zho_x_variant":[
        "Zhuzil\u00fc"
    ],
    "wof:name":"Zhuzilu",
    "wof:placetype":"locality"
},
  "geometry": {"coordinates":[117.04340999999999,24.91833],"type":"Point"}
}