{
  "type": "Feature",
  "properties": {
    "gn:admin1_code":"9",
    "gn:asciiname":"Houronghua",
    "gn:country_code":"CN",
    "gn:dem":55,
    "gn:feature_class":"P",
    "gn:feature_code":"PPL",
    "gn:name":"Houronghua",
    "gn:population":0,
    "gn:timezone":"Asia/Shanghai",
    "iso:country":"CN",
    "name:zho_x_preferred":[
        "\u540e\u8363\u82b1"
    ],
    "wof:name":"Houronghua",
    "wof:placetype":"locality"
},
  "geometry": {"coordinates":[115.14296000000002,35.85452],"type":"Point"}
}