{
  "type": "Feature",
  "properties": {
    "gn:admin1_code":"11.0",
    "gn:asciiname":"Huangnichong",
    "gn:country_code":"CN",
    "gn:dem":610,
    "gn:feature_class":"P",
    "gn:feature_code":"PPL",
    "gn:name":"Huangnichong",
    "gn:population":0,
    "gn:timezone":"Asia/Shanghai",
    "iso:country":"CN",
    "name:zho_x_preferred":[
        "\u9ec4\u6ce5\u51b2"
    ],
    "wof:name":"Huangnichong",
    "wof:placetype":"locality"
},
  "geometry": {"coordinates":[110.39073999999999,27.43395],"type":"Point"}
}