{
  "type": "Feature",
  "properties": {
    "gn:admin1_code":"33.0",
    "gn:asciiname":"Maohe",
    "gn:country_code":"CN",
    "gn:dem":307,
    "gn:feature_class":"P",
    "gn:feature_code":"PPL",
    "gn:name":"Maohe",
    "gn:population":0,
    "gn:timezone":"Asia/Shanghai",
    "iso:country":"CN",
    "name:zho_x_preferred":[
        "\u5e3d\u5408"
    ],
    "wof:name":"Maohe",
    "wof:placetype":"locality"
},
  "geometry": {"coordinates":[106.32299999999999,29.3269],"type":"Point"}
}