{
  "type": "Feature",
  "properties": {
    "gn:admin1_code":"30.0",
    "gn:asciiname":"Laozhong",
    "gn:country_code":"CN",
    "gn:dem":1,
    "gn:feature_class":"P",
    "gn:feature_code":"PPL",
    "gn:name":"Laozhong",
    "gn:population":0,
    "gn:timezone":"Asia/Shanghai",
    "iso:country":"CN",
    "name:zho_x_preferred":[
        "\u8001\u9418"
    ],
    "wof:name":"Laozhong",
    "wof:placetype":"locality"
},
  "geometry": {"coordinates":[112.44737000000001,21.88974],"type":"Point"}
}