{
  "type": "Feature",
  "properties": {
    "gn:admin1_code":"04",
    "gn:asciiname":"Shanghainongchangchuandongfenchang",
    "gn:country_code":"CN",
    "gn:dem":4,
    "gn:feature_class":"P",
    "gn:feature_code":"PPL",
    "gn:name":"Shanghainongchangchuandongfenchang",
    "gn:population":0,
    "gn:timezone":"Asia/Shanghai",
    "iso:country":"CN",
    "wof:name":"Shanghainongchangchuandongfenchang",
    "wof:placetype":"locality"
},
  "geometry": {"coordinates":[120.71250000000001,33.00417],"type":"Point"}
}