{
  "type": "Feature",
  "properties": {
    "gn:admin1_code":"32",
    "gn:asciiname":"Baima",
    "gn:country_code":"CN",
    "gn:dem":456,
    "gn:feature_class":"P",
    "gn:feature_code":"PPL",
    "gn:name":"Baima",
    "gn:population":0,
    "gn:timezone":"Asia/Shanghai",
    "iso:country":"CN",
    "name:und_x_variant":[
        "Pai-ma-ch\u2019ang",
        "Baimachang",
        "Baima"
    ],
    "wof:name":"Baima",
    "wof:placetype":"locality"
},
  "geometry": {"coordinates":[103.95638,29.67852],"type":"Point"}
}