{
  "type": "Feature",
  "properties": {
    "gn:admin1_code":"1.0",
    "gn:asciiname":"Huajiacun",
    "gn:country_code":"CN",
    "gn:dem":25,
    "gn:feature_class":"P",
    "gn:feature_code":"PPL",
    "gn:name":"Huajiacun",
    "gn:population":0,
    "gn:timezone":"Asia/Shanghai",
    "iso:country":"CN",
    "name:zho_x_preferred":[
        "\u534e\u5bb6\u6751"
    ],
    "wof:name":"Huajiacun",
    "wof:placetype":"locality"
},
  "geometry": {"coordinates":[117.47991,33.71576],"type":"Point"}
}