{
  "type": "Feature",
  "properties": {
    "gn:admin1_code":"9",
    "gn:asciiname":"Xichenlou",
    "gn:country_code":"CN",
    "gn:dem":52,
    "gn:feature_class":"P",
    "gn:feature_code":"PPL",
    "gn:name":"Xichenlou",
    "gn:population":0,
    "gn:timezone":"Asia/Shanghai",
    "iso:country":"CN",
    "name:zho_x_preferred":[
        "\u897f\u9648\u697c"
    ],
    "wof:name":"Xichenlou",
    "wof:placetype":"locality"
},
  "geometry": {"coordinates":[115.4791,35.82453],"type":"Point"}
}