{
  "type": "Feature",
  "properties": {
    "gn:admin1_code":"14.0",
    "gn:asciiname":"Papudacun",
    "gn:country_code":"CN",
    "gn:dem":4313,
    "gn:feature_class":"P",
    "gn:feature_code":"PPL",
    "gn:name":"Papudacun",
    "gn:population":0,
    "gn:timezone":"Asia/Urumqi",
    "iso:country":"CN",
    "name:zho_x_preferred":[
        "\u5e15\u666e\u8fbe\u6751"
    ],
    "wof:name":"Papudacun",
    "wof:placetype":"locality"
},
  "geometry": {"coordinates":[93.96415,32.00366],"type":"Point"}
}