{
  "type": "Feature",
  "properties": {
    "gn:admin1_code":"25",
    "gn:asciiname":"Menzhuangcun",
    "gn:country_code":"CN",
    "gn:dem":239,
    "gn:feature_class":"P",
    "gn:feature_code":"PPL",
    "gn:name":"Menzhuangcun",
    "gn:population":0,
    "gn:timezone":"Asia/Shanghai",
    "iso:country":"CN",
    "name:zho_x_preferred":[
        "\u95e8\u5e84\u6751"
    ],
    "wof:name":"Menzhuangcun",
    "wof:placetype":"locality"
},
  "geometry": {"coordinates":[117.21899999999999,36.3109],"type":"Point"}
}