{
  "type": "Feature",
  "properties": {
    "gn:admin1_code":"19.0",
    "gn:asciiname":"Sijiazi",
    "gn:country_code":"CN",
    "gn:dem":5,
    "gn:feature_class":"P",
    "gn:feature_code":"PPL",
    "gn:name":"Sijiazi",
    "gn:population":0,
    "gn:timezone":"Asia/Shanghai",
    "iso:country":"CN",
    "name:und_x_variant":[
        "\u56db\u5bb6\u5b50"
    ],
    "wof:name":"Sijiazi",
    "wof:placetype":"locality"
},
  "geometry": {"coordinates":[122.33605,40.7668],"type":"Point"}
}