{
  "type": "Feature",
  "properties": {
    "gn:admin1_code":"30",
    "gn:asciiname":"Shangen Linchang",
    "gn:country_code":"CN",
    "gn:dem":211,
    "gn:feature_class":"P",
    "gn:feature_code":"PPLF",
    "gn:name":"Shangen Linchang",
    "gn:population":0,
    "gn:timezone":"Asia/Shanghai",
    "iso:country":"CN",
    "name:zho_x_preferred":[
        "\u5c71\u6839\u6797\u573a"
    ],
    "wof:name":"Shangen Linchang",
    "wof:placetype":"locality"
},
  "geometry": {"coordinates":[112.46111000000001,23.44306],"type":"Point"}
}