{
  "type": "Feature",
  "properties": {
    "gn:admin1_code":"16.0",
    "gn:asciiname":"Tanlong",
    "gn:country_code":"CN",
    "gn:dem":104,
    "gn:feature_class":"P",
    "gn:feature_code":"PPL",
    "gn:name":"Tanlong",
    "gn:population":0,
    "gn:timezone":"Asia/Shanghai",
    "iso:country":"CN",
    "name:zho_x_preferred":[
        "\u6f6d\u9f99"
    ],
    "wof:name":"Tanlong",
    "wof:placetype":"locality"
},
  "geometry": {"coordinates":[108.578,22.6779],"type":"Point"}
}