{
  "type": "Feature",
  "properties": {
    "gn:admin1_code":"26.0",
    "gn:asciiname":"Beiyahuo",
    "gn:country_code":"CN",
    "gn:dem":1322,
    "gn:feature_class":"P",
    "gn:feature_code":"PPL",
    "gn:name":"Beiyahuo",
    "gn:population":0,
    "gn:timezone":"Asia/Shanghai",
    "iso:country":"CN",
    "name:zho_x_preferred":[
        "\u7891\u57ad\u8c41"
    ],
    "wof:name":"Beiyahuo",
    "wof:placetype":"locality"
},
  "geometry": {"coordinates":[107.88958,32.40781],"type":"Point"}
}