{
  "type": "Feature",
  "properties": {
    "gn:admin1_code":"1.0",
    "gn:asciiname":"Kongxucun",
    "gn:country_code":"CN",
    "gn:dem":9,
    "gn:feature_class":"P",
    "gn:feature_code":"PPL",
    "gn:name":"Kongxucun",
    "gn:population":0,
    "gn:timezone":"Asia/Shanghai",
    "iso:country":"CN",
    "name:zho_x_preferred":[
        "\u5b54\u5729\u6751"
    ],
    "wof:name":"Kongxucun",
    "wof:placetype":"locality"
},
  "geometry": {"coordinates":[117.03369000000001,31.54108],"type":"Point"}
}