{
  "type": "Feature",
  "properties": {
    "gn:admin1_code":"16.0",
    "gn:asciiname":"Bai'an",
    "gn:country_code":"CN",
    "gn:dem":403,
    "gn:feature_class":"P",
    "gn:feature_code":"PPL",
    "gn:name":"Bai\u2019an",
    "gn:population":0,
    "gn:timezone":"Asia/Shanghai",
    "iso:country":"CN",
    "name:und_x_variant":[
        "Bai\u2019an"
    ],
    "name:zho_x_preferred":[
        "\u767d\u5cb8"
    ],
    "wof:name":"Bai'an",
    "wof:placetype":"locality"
},
  "geometry": {"coordinates":[108.84,24.7696],"type":"Point"}
}