{
  "type": "Feature",
  "properties": {
    "gn:admin1_code":"18",
    "gn:asciiname":"Tangchong",
    "gn:country_code":"CN",
    "gn:dem":1211,
    "gn:feature_class":"P",
    "gn:feature_code":"PPL",
    "gn:name":"Tangchong",
    "gn:population":0,
    "gn:timezone":"Asia/Shanghai",
    "iso:country":"CN",
    "name:zho_x_preferred":[
        "\u5858\u51b2"
    ],
    "wof:name":"Tangchong",
    "wof:placetype":"locality"
},
  "geometry": {"coordinates":[106.48399999999999,26.6244],"type":"Point"}
}