{
  "type": "Feature",
  "properties": {
    "gn:admin1_code":"16",
    "gn:asciiname":"Tunzhou",
    "gn:country_code":"CN",
    "gn:dem":301,
    "gn:feature_class":"P",
    "gn:feature_code":"PPL",
    "gn:name":"Tunzhou",
    "gn:population":0,
    "gn:timezone":"Asia/Shanghai",
    "iso:country":"CN",
    "name:und_x_variant":[
        "Tun-chou-ts\u2019un",
        "Tunzhou"
    ],
    "name:zho_x_preferred":[
        "\u5c6f\u5468"
    ],
    "wof:name":"Tunzhou",
    "wof:placetype":"locality"
},
  "geometry": {"coordinates":[107.126,22.9174],"type":"Point"}
}