{
  "type": "Feature",
  "properties": {
    "gn:admin1_code":"16.0",
    "gn:asciiname":"Jiaban",
    "gn:country_code":"CN",
    "gn:dem":803,
    "gn:feature_class":"P",
    "gn:feature_code":"PPL",
    "gn:name":"Jiaban",
    "gn:population":0,
    "gn:timezone":"Asia/Shanghai",
    "iso:country":"CN",
    "name:zho_x_preferred":[
        "\u7532\u677f"
    ],
    "wof:name":"Jiaban",
    "wof:placetype":"locality"
},
  "geometry": {"coordinates":[107.029,25.3344],"type":"Point"}
}