{
  "type": "Feature",
  "properties": {
    "gn:admin1_code":"16.0",
    "gn:asciiname":"Nasha",
    "gn:country_code":"CN",
    "gn:dem":83,
    "gn:feature_class":"P",
    "gn:feature_code":"PPL",
    "gn:name":"Nasha",
    "gn:population":0,
    "gn:timezone":"Asia/Shanghai",
    "iso:country":"CN",
    "name:ceb_x_preferred":[
        "Nasha"
    ],
    "name:swe_x_preferred":[
        "Nasha"
    ],
    "name:zho_x_preferred":[
        "\u90a3\u6c99"
    ],
    "wof:name":"Nasha",
    "wof:placetype":"locality"
},
  "geometry": {"coordinates":[108.459,22.8873],"type":"Point"}
}