{
  "type": "Feature",
  "properties": {
    "gn:admin1_code":"4.0",
    "gn:asciiname":"Dapengcun",
    "gn:country_code":"CN",
    "gn:dem":67,
    "gn:feature_class":"P",
    "gn:feature_code":"PPL",
    "gn:name":"Dapengcun",
    "gn:population":0,
    "gn:timezone":"Asia/Shanghai",
    "iso:country":"CN",
    "name:zho_x_preferred":[
        "\u5927\u670b\u6751"
    ],
    "wof:name":"Dapengcun",
    "wof:placetype":"locality"
},
  "geometry": {"coordinates":[118.65081000000001,32.84455999999999],"type":"Point"}
}