{
  "type": "Feature",
  "properties": {
    "gn:admin1_code":"11.0",
    "gn:asciiname":"Youqiling",
    "gn:country_code":"CN",
    "gn:dem":1032,
    "gn:feature_class":"P",
    "gn:feature_code":"PPL",
    "gn:name":"Youqiling",
    "gn:population":0,
    "gn:timezone":"Asia/Shanghai",
    "iso:country":"CN",
    "name:zho_x_preferred":[
        "\u6cb9\u9f50\u5cad"
    ],
    "wof:name":"Youqiling",
    "wof:placetype":"locality"
},
  "geometry": {"coordinates":[113.88585999999999,26.02937],"type":"Point"}
}