{
  "type": "Feature",
  "properties": {
    "gn:admin1_code":"8.0",
    "gn:asciiname":"Damajiacun",
    "gn:country_code":"CN",
    "gn:dem":148,
    "gn:feature_class":"P",
    "gn:feature_code":"PPL",
    "gn:name":"Damajiacun",
    "gn:population":0,
    "gn:timezone":"Asia/Shanghai",
    "iso:country":"CN",
    "name:zho_x_preferred":[
        "\u5927\u9a6c\u5bb6\u6751"
    ],
    "wof:name":"Damajiacun",
    "wof:placetype":"locality"
},
  "geometry": {"coordinates":[125.92944,45.27927],"type":"Point"}
}