{
  "type": "Feature",
  "properties": {
    "gn:admin1_code":"18",
    "gn:asciiname":"Matadeng",
    "gn:country_code":"CN",
    "gn:dem":873,
    "gn:feature_class":"P",
    "gn:feature_code":"PPL",
    "gn:name":"Matadeng",
    "gn:population":0,
    "gn:timezone":"Asia/Shanghai",
    "iso:country":"CN",
    "name:zho_x_preferred":[
        "\u9a6c\u8e0f\u8e6c"
    ],
    "wof:name":"Matadeng",
    "wof:placetype":"locality"
},
  "geometry": {"coordinates":[107.92,28.7681],"type":"Point"}
}