{
  "type": "Feature",
  "properties": {
    "gn:admin1_code":"08",
    "gn:asciiname":"Xilin",
    "gn:country_code":"CN",
    "gn:dem":192,
    "gn:feature_class":"P",
    "gn:feature_code":"PPLA3",
    "gn:name":"Xilin",
    "gn:population":0,
    "gn:timezone":"Asia/Shanghai",
    "iso:country":"CN",
    "name:und_x_variant":[
        "Hsi-lin",
        "Xilin",
        "Xilin Jiedao",
        "Xilin Qu"
    ],
    "name:zho_x_preferred":[
        "\u897f\u6797"
    ],
    "name:zho_x_variant":[
        "\u897f\u6797\u8857\u9053",
        "\u897f\u6797\u533a"
    ],
    "wof:name":"Xilin",
    "wof:placetype":"locality"
},
  "geometry": {"coordinates":[129.30368999999999,47.47606],"type":"Point"}
}