{
  "type": "Feature",
  "properties": {
    "gn:admin1_code":"06",
    "gn:asciiname":"Ganchansi",
    "gn:country_code":"CN",
    "gn:dem":2712,
    "gn:feature_class":"P",
    "gn:feature_code":"PPL",
    "gn:name":"Ganchansi",
    "gn:population":0,
    "gn:timezone":"Asia/Shanghai",
    "iso:country":"CN",
    "wof:name":"Ganchansi",
    "wof:placetype":"locality"
},
  "geometry": {"coordinates":[102.33333,37.06667],"type":"Point"}
}