{
  "type": "Feature",
  "properties": {
    "gn:admin1_code":"9",
    "gn:asciiname":"Yushuanglou",
    "gn:country_code":"CN",
    "gn:dem":54,
    "gn:feature_class":"P",
    "gn:feature_code":"PPL",
    "gn:name":"Yushuanglou",
    "gn:population":0,
    "gn:timezone":"Asia/Shanghai",
    "iso:country":"CN",
    "name:zho_x_preferred":[
        "\u4f59\u53cc\u697c"
    ],
    "wof:name":"Yushuanglou",
    "wof:placetype":"locality"
},
  "geometry": {"coordinates":[115.294,34.2262],"type":"Point"}
}