{
  "type": "Feature",
  "properties": {
    "gn:admin1_code":"19.0",
    "gn:asciiname":"Bapangoucun",
    "gn:country_code":"CN",
    "gn:dem":426,
    "gn:feature_class":"P",
    "gn:feature_code":"PPL",
    "gn:name":"Bapangoucun",
    "gn:population":0,
    "gn:timezone":"Asia/Shanghai",
    "iso:country":"CN",
    "name:zho_x_preferred":[
        "\u516b\u76d8\u6c9f\u6751"
    ],
    "wof:name":"Bapangoucun",
    "wof:placetype":"locality"
},
  "geometry": {"coordinates":[120.258,41.315],"type":"Point"}
}