{
  "type": "Feature",
  "properties": {
    "gn:admin1_code":"25",
    "gn:asciiname":"Beibaidingbei",
    "gn:country_code":"CN",
    "gn:dem":130,
    "gn:feature_class":"P",
    "gn:feature_code":"PPL",
    "gn:name":"Beibaidingbei",
    "gn:population":0,
    "gn:timezone":"Asia/Shanghai",
    "iso:country":"CN",
    "name:zho_x_preferred":[
        "\u5317\u767e\u9876\u5317"
    ],
    "wof:name":"Beibaidingbei",
    "wof:placetype":"locality"
},
  "geometry": {"coordinates":[117.36499999999999,35.7209],"type":"Point"}
}