{
  "type": "Feature",
  "properties": {
    "gn:admin1_code":"10",
    "gn:asciiname":"Dongshijingtuan",
    "gn:country_code":"CN",
    "gn:dem":37,
    "gn:feature_class":"P",
    "gn:feature_code":"PPL",
    "gn:name":"Dongshijingtuan",
    "gn:population":0,
    "gn:timezone":"Asia/Shanghai",
    "iso:country":"CN",
    "name:zho_x_preferred":[
        "\u4e1c\u77f3\u4e95\u7583"
    ],
    "wof:name":"Dongshijingtuan",
    "wof:placetype":"locality"
},
  "geometry": {"coordinates":[115.21585,36.88254000000001],"type":"Point"}
}