{
  "type": "Feature",
  "properties": {
    "gn:admin1_code":"11",
    "gn:asciiname":"Lianhe",
    "gn:country_code":"CN",
    "gn:dem":172,
    "gn:feature_class":"P",
    "gn:feature_code":"PPL",
    "gn:name":"Lianhe",
    "gn:population":0,
    "gn:timezone":"Asia/Shanghai",
    "iso:country":"CN",
    "name:ceb_x_preferred":[
        "Lianhe"
    ],
    "name:deu_x_preferred":[
        "Lianhe"
    ],
    "name:swe_x_preferred":[
        "Lianhe"
    ],
    "wof:name":"Lianhe",
    "wof:placetype":"locality"
},
  "geometry": {"coordinates":[110.64972,27.89333],"type":"Point"}
}