{
  "type": "Feature",
  "properties": {
    "gn:admin1_code":"1.0",
    "gn:asciiname":"Bailayuancun",
    "gn:country_code":"CN",
    "gn:dem":48,
    "gn:feature_class":"P",
    "gn:feature_code":"PPL",
    "gn:name":"Bailayuancun",
    "gn:population":0,
    "gn:timezone":"Asia/Shanghai",
    "iso:country":"CN",
    "name:zho_x_preferred":[
        "\u767d\u8721\u56ed\u6751"
    ],
    "wof:name":"Bailayuancun",
    "wof:placetype":"locality"
},
  "geometry": {"coordinates":[116.50848000000001,34.52728],"type":"Point"}
}