{
  "type": "Feature",
  "properties": {
    "gn:admin1_code":"8.0",
    "gn:asciiname":"Wanbaotun",
    "gn:country_code":"CN",
    "gn:dem":138,
    "gn:feature_class":"P",
    "gn:feature_code":"PPL",
    "gn:name":"Wanbaotun",
    "gn:population":0,
    "gn:timezone":"Asia/Shanghai",
    "iso:country":"CN",
    "name:zho_x_preferred":[
        "\u4e07\u5b9d\u5c6f"
    ],
    "wof:name":"Wanbaotun",
    "wof:placetype":"locality"
},
  "geometry": {"coordinates":[127.78754000000001,46.05886],"type":"Point"}
}