{
  "type": "Feature",
  "properties": {
    "gn:admin1_code":"32.0",
    "gn:asciiname":"Sha'er",
    "gn:country_code":"CN",
    "gn:dem":1700,
    "gn:feature_class":"P",
    "gn:feature_code":"PPL",
    "gn:name":"Sha\u2019er",
    "gn:population":0,
    "gn:timezone":"Asia/Shanghai",
    "iso:country":"CN",
    "name:und_x_variant":[
        "Sha\u2019er"
    ],
    "name:zho_x_preferred":[
        "\u6c99\u8033"
    ],
    "wof:name":"Sha'er",
    "wof:placetype":"locality"
},
  "geometry": {"coordinates":[102.184,28.2609],"type":"Point"}
}