{
  "type": "Feature",
  "properties": {
    "gn:admin1_code":"15.0",
    "gn:asciiname":"Luoxinzhuang",
    "gn:country_code":"CN",
    "gn:dem":1576,
    "gn:feature_class":"P",
    "gn:feature_code":"PPL",
    "gn:name":"Luoxinzhuang",
    "gn:population":0,
    "gn:timezone":"Asia/Shanghai",
    "iso:country":"CN",
    "name:zho_x_preferred":[
        "\u7f57\u65b0\u5e84"
    ],
    "wof:name":"Luoxinzhuang",
    "wof:placetype":"locality"
},
  "geometry": {"coordinates":[106.976,35.9353],"type":"Point"}
}