{
  "type": "Feature",
  "properties": {
    "gn:admin1_code":"30",
    "gn:asciiname":"Huilong",
    "gn:country_code":"CN",
    "gn:dem":211,
    "gn:feature_class":"P",
    "gn:feature_code":"PPLA4",
    "gn:name":"Huilong",
    "gn:population":0,
    "gn:timezone":"Asia/Shanghai",
    "iso:country":"CN",
    "name:und_x_variant":[
        "Huilong Zhen"
    ],
    "name:zho_x_preferred":[
        "\u8ff4\u9f99"
    ],
    "name:zho_x_variant":[
        "\u8ff4\u9f99\u9547"
    ],
    "wof:name":"Huilong",
    "wof:placetype":"locality"
},
  "geometry": {"coordinates":[115.52558000000001,24.37013],"type":"Point"}
}