{
  "type": "Feature",
  "properties": {
    "gn:admin1_code":"18.0",
    "gn:asciiname":"Puxitang",
    "gn:country_code":"CN",
    "gn:dem":1028,
    "gn:feature_class":"P",
    "gn:feature_code":"PPL",
    "gn:name":"Puxitang",
    "gn:population":0,
    "gn:timezone":"Asia/Shanghai",
    "iso:country":"CN",
    "name:zho_x_preferred":[
        "\u8386\u5e2d\u5802"
    ],
    "wof:name":"Puxitang",
    "wof:placetype":"locality"
},
  "geometry": {"coordinates":[107.56699999999999,26.0581],"type":"Point"}
}