{
  "type": "Feature",
  "properties": {
    "gn:country":"CN",
    "gn:fcode":"PPL",
    "gn:pop":1800,
    "iso:country":"CN",
    "qs:name":"Xiangyun",
    "qs:photos_9r":0,
    "qs:photos_sr":0,
    "qs:pop_sr":"3",
    "wd:wordcount":36,
    "wof:name":"Xiangyun",
    "wof:placetype":"locality",
    "wof:population":1800
},
  "geometry": {"coordinates":[118.16028,24.97111],"type":"Point"}
}