{
  "type": "Feature",
  "properties": {
    "gn:admin1_code":"32.0",
    "gn:asciiname":"Washitan",
    "gn:country_code":"CN",
    "gn:dem":511,
    "gn:feature_class":"P",
    "gn:feature_code":"PPL",
    "gn:name":"Washitan",
    "gn:population":0,
    "gn:timezone":"Asia/Shanghai",
    "iso:country":"CN",
    "name:zho_x_preferred":[
        "\u74e6\u77f3\u6ee9"
    ],
    "wof:name":"Washitan",
    "wof:placetype":"locality"
},
  "geometry": {"coordinates":[107.15900000000001,32.3073],"type":"Point"}
}