{
  "type": "Feature",
  "properties": {
    "gn:admin1_code":"32.0",
    "gn:asciiname":"Jiancaomiaozu",
    "gn:country_code":"CN",
    "gn:dem":1103,
    "gn:feature_class":"P",
    "gn:feature_code":"PPL",
    "gn:name":"Jiancaomiaozu",
    "gn:population":0,
    "gn:timezone":"Asia/Shanghai",
    "iso:country":"CN",
    "name:zho_x_preferred":[
        "\u67a7\u69fd\u82d7\u65cf"
    ],
    "wof:name":"Jiancaomiaozu",
    "wof:placetype":"locality"
},
  "geometry": {"coordinates":[105.43227,27.88996],"type":"Point"}
}