{
  "type": "Feature",
  "properties": {
    "gn:admin1_code":"11.0",
    "gn:asciiname":"Wanchanglong",
    "gn:country_code":"CN",
    "gn:dem":165,
    "gn:feature_class":"P",
    "gn:feature_code":"PPL",
    "gn:name":"Wanchanglong",
    "gn:population":0,
    "gn:timezone":"Asia/Shanghai",
    "iso:country":"CN",
    "name:zho_x_preferred":[
        "\u7897\u5382\u5785"
    ],
    "wof:name":"Wanchanglong",
    "wof:placetype":"locality"
},
  "geometry": {"coordinates":[113.26503,26.18322],"type":"Point"}
}