{
  "type": "Feature",
  "properties": {
    "gn:admin1_code":"11.0",
    "gn:asciiname":"Xiahetang",
    "gn:country_code":"CN",
    "gn:dem":54,
    "gn:feature_class":"P",
    "gn:feature_code":"PPL",
    "gn:name":"Xiahetang",
    "gn:population":0,
    "gn:timezone":"Asia/Shanghai",
    "iso:country":"CN",
    "name:zho_x_preferred":[
        "\u4e0b\u8377\u5858"
    ],
    "wof:name":"Xiahetang",
    "wof:placetype":"locality"
},
  "geometry": {"coordinates":[112.91821000000002,27.73862],"type":"Point"}
}