{
  "type": "Feature",
  "properties": {
    "gn:admin1_code":"25",
    "gn:asciiname":"Maguguan",
    "gn:country_code":"CN",
    "gn:dem":142,
    "gn:feature_class":"P",
    "gn:feature_code":"PPL",
    "gn:name":"Maguguan",
    "gn:population":0,
    "gn:timezone":"Asia/Shanghai",
    "iso:country":"CN",
    "name:zho_x_preferred":[
        "\u9ebb\u59d1\u9986"
    ],
    "wof:name":"Maguguan",
    "wof:placetype":"locality"
},
  "geometry": {"coordinates":[119.60599999999999,35.9075],"type":"Point"}
}