{
  "type": "Feature",
  "properties": {
    "gn:admin1_code":"19.0",
    "gn:asciiname":"Lijiahecun",
    "gn:country_code":"CN",
    "gn:dem":83,
    "gn:feature_class":"P",
    "gn:feature_code":"PPL",
    "gn:name":"Lijiahecun",
    "gn:population":0,
    "gn:timezone":"Asia/Shanghai",
    "iso:country":"CN",
    "name:zho_x_preferred":[
        "\u674e\u5bb6\u6cb3\u6751"
    ],
    "wof:name":"Lijiahecun",
    "wof:placetype":"locality"
},
  "geometry": {"coordinates":[123.40900000000001,42.6392],"type":"Point"}
}