{
  "type": "Feature",
  "properties": {
    "gn:admin1_code":"7.0",
    "gn:asciiname":"Youxikou",
    "gn:country_code":"CN",
    "gn:dem":80,
    "gn:feature_class":"P",
    "gn:feature_code":"PPLA4",
    "gn:name":"Youxikou",
    "gn:population":0,
    "gn:timezone":"Asia/Shanghai",
    "iso:country":"CN",
    "name:und_x_variant":[
        "Yu-hsi-k\u2019ou",
        "Youxikou",
        "\u5c24\u6eaa\u53e3",
        "Youxikou Zhen",
        "\u5c24\u6eaa\u53e3\u9547"
    ],
    "wof:name":"Youxikou",
    "wof:placetype":"locality"
},
  "geometry": {"coordinates":[118.44389,26.39812],"type":"Point"}
}