{
  "type": "Feature",
  "properties": {
    "gn:admin1_code":"24.0",
    "gn:asciiname":"Shilougetai",
    "gn:country_code":"CN",
    "gn:dem":1397,
    "gn:feature_class":"P",
    "gn:feature_code":"PPL",
    "gn:name":"Shilougetai",
    "gn:population":0,
    "gn:timezone":"Asia/Shanghai",
    "iso:country":"CN",
    "name:zho_x_preferred":[
        "\u77f3\u697c\u572a\u53f0"
    ],
    "wof:name":"Shilougetai",
    "wof:placetype":"locality"
},
  "geometry": {"coordinates":[111.31682000000001,38.55639],"type":"Point"}
}