{
  "type": "Feature",
  "properties": {
    "gn:admin1_code":"18",
    "gn:asciiname":"Luo'e Chongzi",
    "gn:country_code":"CN",
    "gn:dem":2261,
    "gn:feature_class":"P",
    "gn:feature_code":"PPL",
    "gn:name":"Luo\u2019e Chongzi",
    "gn:population":0,
    "gn:timezone":"Asia/Shanghai",
    "iso:country":"CN",
    "name:und_x_variant":[
        "Luo\u2019e Chongzi"
    ],
    "name:zho_x_preferred":[
        "\u7f57\u4fc4\u51b2\u5b50"
    ],
    "wof:name":"Luo'e Chongzi",
    "wof:placetype":"locality"
},
  "geometry": {"coordinates":[103.873,27.1808],"type":"Point"}
}