{
  "type": "Feature",
  "properties": {
    "gn:admin1_code":"32.0",
    "gn:asciiname":"Jiazong",
    "gn:country_code":"CN",
    "gn:dem":3657,
    "gn:feature_class":"P",
    "gn:feature_code":"PPL",
    "gn:name":"Jiazong",
    "gn:population":0,
    "gn:timezone":"Asia/Shanghai",
    "iso:country":"CN",
    "name:zho_x_preferred":[
        "\u7532\u5b97"
    ],
    "wof:name":"Jiazong",
    "wof:placetype":"locality"
},
  "geometry": {"coordinates":[100.914,31.7054],"type":"Point"}
}