{
  "type": "Feature",
  "properties": {
    "gn:admin1_code":"2.0",
    "gn:asciiname":"Longyuan",
    "gn:country_code":"CN",
    "gn:dem":75,
    "gn:feature_class":"P",
    "gn:feature_code":"PPL",
    "gn:name":"Longyuan",
    "gn:population":0,
    "gn:timezone":"Asia/Shanghai",
    "iso:country":"CN",
    "name:ceb_x_preferred":[
        "Longyuan"
    ],
    "name:deu_x_preferred":[
        "Longyuan"
    ],
    "name:swe_x_preferred":[
        "Longyuan"
    ],
    "name:zho_x_preferred":[
        "\u9f99\u6e90"
    ],
    "wof:name":"Longyuan",
    "wof:placetype":"locality"
},
  "geometry": {"coordinates":[119.81322,28.95984],"type":"Point"}
}