{
  "type": "Feature",
  "properties": {
    "gn:admin1_code":"8.0",
    "gn:asciiname":"Sicuofang",
    "gn:country_code":"CN",
    "gn:dem":131,
    "gn:feature_class":"P",
    "gn:feature_code":"PPL",
    "gn:name":"Sicuofang",
    "gn:population":0,
    "gn:timezone":"Asia/Shanghai",
    "iso:country":"CN",
    "name:zho_x_preferred":[
        "\u56db\u64ae\u623f"
    ],
    "wof:name":"Sicuofang",
    "wof:placetype":"locality"
},
  "geometry": {"coordinates":[124.74721,45.99817],"type":"Point"}
}