{
  "type": "Feature",
  "properties": {
    "gn:admin1_code":"24.0",
    "gn:asciiname":"Lijiagoucun",
    "gn:country_code":"CN",
    "gn:dem":1117,
    "gn:feature_class":"P",
    "gn:feature_code":"PPL",
    "gn:name":"Lijiagoucun",
    "gn:population":0,
    "gn:timezone":"Asia/Shanghai",
    "iso:country":"CN",
    "name:zho_x_preferred":[
        "\u674e\u5bb6\u6c9f\u6751"
    ],
    "wof:name":"Lijiagoucun",
    "wof:placetype":"locality"
},
  "geometry": {"coordinates":[110.92279000000001,37.0529],"type":"Point"}
}