{
  "type": "Feature",
  "properties": {
    "gn:admin1_code":"30.0",
    "gn:asciiname":"Huangwu",
    "gn:country_code":"CN",
    "gn:dem":312,
    "gn:feature_class":"P",
    "gn:feature_code":"PPL",
    "gn:name":"Huangwu",
    "gn:population":0,
    "gn:timezone":"Asia/Shanghai",
    "iso:country":"CN",
    "name:zho_x_preferred":[
        "Huangwu"
    ],
    "name:zho_x_variant":[
        "\u9ec4\u5c4b"
    ],
    "wof:name":"Huangwu",
    "wof:placetype":"locality"
},
  "geometry": {"coordinates":[114.00411,24.87098],"type":"Point"}
}