{
  "type": "Feature",
  "properties": {
    "gn:admin1_code":"29.0",
    "gn:asciiname":"Shangmuzuo",
    "gn:country_code":"CN",
    "gn:dem":1902,
    "gn:feature_class":"P",
    "gn:feature_code":"PPL",
    "gn:name":"Shangmuzuo",
    "gn:population":0,
    "gn:timezone":"Asia/Shanghai",
    "iso:country":"CN",
    "name:zho_x_preferred":[
        "\u4e0a\u6728\u4f5c"
    ],
    "wof:name":"Shangmuzuo",
    "wof:placetype":"locality"
},
  "geometry": {"coordinates":[103.054,25.3257],"type":"Point"}
}