{
  "type": "Feature",
  "properties": {
    "gn:admin1_code":"7.0",
    "gn:asciiname":"Dahun",
    "gn:country_code":"CN",
    "gn:dem":310,
    "gn:feature_class":"P",
    "gn:feature_code":"PPL",
    "gn:name":"Dahun",
    "gn:population":0,
    "gn:timezone":"Asia/Shanghai",
    "iso:country":"CN",
    "name:zho_x_preferred":[
        "\u5927\u6d51"
    ],
    "wof:name":"Dahun",
    "wof:placetype":"locality"
},
  "geometry": {"coordinates":[118.11347000000001,27.88083],"type":"Point"}
}