{
  "type": "Feature",
  "properties": {
    "gn:admin1_code":"30",
    "gn:asciiname":"Gaobeidu",
    "gn:country_code":"CN",
    "gn:dem":239,
    "gn:feature_class":"P",
    "gn:feature_code":"PPL",
    "gn:name":"Gaobeidu",
    "gn:population":0,
    "gn:timezone":"Asia/Shanghai",
    "iso:country":"CN",
    "name:zho_x_preferred":[
        "\u9ad8\u9642\u809a"
    ],
    "wof:name":"Gaobeidu",
    "wof:placetype":"locality"
},
  "geometry": {"coordinates":[115.67098,24.46717],"type":"Point"}
}