{
  "type": "Feature",
  "properties": {
    "gn:admin1_code":"5.0",
    "gn:asciiname":"Shuanglongcun",
    "gn:country_code":"CN",
    "gn:dem":307,
    "gn:feature_class":"P",
    "gn:feature_code":"PPL",
    "gn:name":"Shuanglongcun",
    "gn:population":0,
    "gn:timezone":"Asia/Shanghai",
    "iso:country":"CN",
    "name:und_x_variant":[
        "\u53cc\u9f99\u6751"
    ],
    "wof:name":"Shuanglongcun",
    "wof:placetype":"locality"
},
  "geometry": {"coordinates":[129.16708,42.81145],"type":"Point"}
}