{
  "type": "Feature",
  "properties": {
    "gn:admin1_code":"9",
    "gn:asciiname":"Huangzhuang",
    "gn:country_code":"CN",
    "gn:dem":39,
    "gn:feature_class":"P",
    "gn:feature_code":"PPL",
    "gn:name":"Huangzhuang",
    "gn:population":0,
    "gn:timezone":"Asia/Shanghai",
    "iso:country":"CN",
    "name:zho_x_preferred":[
        "\u9ec4\u5e84"
    ],
    "wof:name":"Huangzhuang",
    "wof:placetype":"locality"
},
  "geometry": {"coordinates":[116.00700000000001,33.9031],"type":"Point"}
}