{
  "type": "Feature",
  "properties": {
    "gn:admin1_code":"21.0",
    "gn:asciiname":"Jijitan",
    "gn:country_code":"CN",
    "gn:dem":1402,
    "gn:feature_class":"P",
    "gn:feature_code":"PPL",
    "gn:name":"Jijitan",
    "gn:population":0,
    "gn:timezone":"Asia/Shanghai",
    "iso:country":"CN",
    "name:zho_x_preferred":[
        "\u82a8\u82a8\u6ee9"
    ],
    "wof:name":"Jijitan",
    "wof:placetype":"locality"
},
  "geometry": {"coordinates":[106.291,39.0762],"type":"Point"}
}