{
  "type": "Feature",
  "properties": {
    "gn:admin1_code":"14.0",
    "gn:asciiname":"Changgoka",
    "gn:country_code":"CN",
    "gn:dem":3358,
    "gn:feature_class":"P",
    "gn:feature_code":"PPL",
    "gn:name":"Changgoka",
    "gn:population":0,
    "gn:timezone":"Asia/Urumqi",
    "iso:country":"CN",
    "name:bod_x_preferred":[
        "Changgoka"
    ],
    "name:zho_x_preferred":[
        "Zhangguoka"
    ],
    "name:zho_x_variant":[
        "\u7ae0\u8fc7\u5361"
    ],
    "wof:name":"Changgoka",
    "wof:placetype":"locality"
},
  "geometry": {"coordinates":[97.20399999999999,31.504],"type":"Point"}
}