{
  "type": "Feature",
  "properties": {
    "gn:admin1_code":"32.0",
    "gn:asciiname":"Houba",
    "gn:country_code":"CN",
    "gn:dem":1066,
    "gn:feature_class":"P",
    "gn:feature_code":"PPL",
    "gn:name":"Houba",
    "gn:population":0,
    "gn:timezone":"Asia/Shanghai",
    "iso:country":"CN",
    "name:und_x_variant":[
        "\u540e\u575d"
    ],
    "wof:name":"Houba",
    "wof:placetype":"locality"
},
  "geometry": {"coordinates":[106.80158,32.56232],"type":"Point"}
}