{
  "type": "Feature",
  "properties": {
    "gn:admin1_code":"26",
    "gn:asciiname":"Hujia",
    "gn:cc2":"CN",
    "gn:country_code":"CN",
    "gn:dem":618,
    "gn:feature_class":"P",
    "gn:feature_code":"PPL",
    "gn:name":"Hujia",
    "gn:population":0,
    "gn:timezone":"Asia/Shanghai",
    "iso:country":"CN",
    "name:deu_x_preferred":[
        "Hujia"
    ],
    "name:spa_x_preferred":[
        "Hujia"
    ],
    "name:und_x_variant":[
        "Hu-chia"
    ],
    "wof:name":"Hujia",
    "wof:placetype":"locality"
},
  "geometry": {"coordinates":[110.38333,36.23333],"type":"Point"}
}