{
  "type": "Feature",
  "properties": {
    "gn:admin1_code":"7.0",
    "gn:asciiname":"Eyi",
    "gn:country_code":"CN",
    "gn:dem":302,
    "gn:feature_class":"P",
    "gn:feature_code":"PPL",
    "gn:name":"Eyi",
    "gn:population":0,
    "gn:timezone":"Asia/Shanghai",
    "iso:country":"CN",
    "name:zho_x_preferred":[
        "\u5ce8\u76ca"
    ],
    "wof:name":"Eyi",
    "wof:placetype":"locality"
},
  "geometry": {"coordinates":[116.68416000000001,25.0408],"type":"Point"}
}