{
  "type": "Feature",
  "properties": {
    "gn:admin1_code":"29.0",
    "gn:asciiname":"Malaka",
    "gn:country_code":"CN",
    "gn:dem":2153,
    "gn:feature_class":"P",
    "gn:feature_code":"PPL",
    "gn:name":"Malaka",
    "gn:population":0,
    "gn:timezone":"Asia/Shanghai",
    "iso:country":"CN",
    "name:ceb_x_preferred":[
        "Malaka"
    ],
    "name:ces_x_preferred":[
        "Malaka"
    ],
    "name:deu_x_preferred":[
        "Malaka"
    ],
    "name:fra_x_preferred":[
        "Malaka"
    ],
    "name:nld_x_preferred":[
        "Malaka"
    ],
    "name:slk_x_preferred":[
        "Malaka"
    ],
    "name:swe_x_preferred":[
        "Malaka"
    ],
    "name:zho_x_preferred":[
        "\u9a82\u62c9\u5361"
    ],
    "wof:name":"Malaka",
    "wof:placetype":"locality"
},
  "geometry": {"coordinates":[102.31,25.6998],"type":"Point"}
}