{
  "type": "Feature",
  "properties": {
    "gn:admin1_code":"29.0",
    "gn:asciiname":"Bianfudong",
    "gn:country_code":"CN",
    "gn:dem":1696,
    "gn:feature_class":"P",
    "gn:feature_code":"PPL",
    "gn:name":"Bianfudong",
    "gn:population":0,
    "gn:timezone":"Asia/Shanghai",
    "iso:country":"CN",
    "name:zho_x_preferred":[
        "\u8759\u8760\u6d1e"
    ],
    "wof:name":"Bianfudong",
    "wof:placetype":"locality"
},
  "geometry": {"coordinates":[100.88800000000001,24.6134],"type":"Point"}
}