{
  "type": "Feature",
  "properties": {
    "gn:admin1_code":"05",
    "gn:asciiname":"Lan-ni-t'ang-tzu-kou-men",
    "gn:country_code":"CN",
    "gn:dem":431,
    "gn:feature_class":"P",
    "gn:feature_code":"PPL",
    "gn:name":"Lan-ni-t\u2019ang-tzu-kou-men",
    "gn:population":0,
    "gn:timezone":"Asia/Shanghai",
    "iso:country":"CN",
    "wof:name":"Lan-ni-t'ang-tzu-kou-men",
    "wof:placetype":"locality"
},
  "geometry": {"coordinates":[126.15083,41.73278],"type":"Point"}
}