{
  "type": "Feature",
  "properties": {
    "gn:admin1_code":"33",
    "gn:asciiname":"Shijia",
    "gn:country_code":"CN",
    "gn:dem":668,
    "gn:feature_class":"P",
    "gn:feature_code":"PPLA4",
    "gn:name":"Shijia",
    "gn:population":0,
    "gn:timezone":"Asia/Shanghai",
    "iso:country":"CN",
    "name:ceb_x_preferred":[
        "Shijia"
    ],
    "name:swe_x_preferred":[
        "Shijia"
    ],
    "name:und_x_variant":[
        "Shijiahe",
        "Shijia Zhen"
    ],
    "name:zho_x_preferred":[
        "\u77f3\u5bb6"
    ],
    "name:zho_x_variant":[
        "\u77f3\u5bb6\u9547"
    ],
    "wof:name":"Shijia",
    "wof:placetype":"locality"
},
  "geometry": {"coordinates":[108.61165,29.23677],"type":"Point"}
}