{
  "type": "Feature",
  "properties": {
    "gn:admin1_code":"11.0",
    "gn:asciiname":"Zhutingchong",
    "gn:country_code":"CN",
    "gn:dem":127,
    "gn:feature_class":"P",
    "gn:feature_code":"PPL",
    "gn:name":"Zhutingchong",
    "gn:population":0,
    "gn:timezone":"Asia/Shanghai",
    "iso:country":"CN",
    "name:zho_x_preferred":[
        "\u6731\u4ead\u51b2"
    ],
    "wof:name":"Zhutingchong",
    "wof:placetype":"locality"
},
  "geometry": {"coordinates":[113.06216000000001,27.23856],"type":"Point"}
}