{
  "type": "Feature",
  "properties": {
    "gn:admin1_code":"2.0",
    "gn:asciiname":"Xiajiexi",
    "gn:country_code":"CN",
    "gn:dem":72,
    "gn:feature_class":"P",
    "gn:feature_code":"PPL",
    "gn:name":"Xiajiexi",
    "gn:population":0,
    "gn:timezone":"Asia/Shanghai",
    "iso:country":"CN",
    "name:zho_x_preferred":[
        "\u4e0b\u754c\u6eaa"
    ],
    "wof:name":"Xiajiexi",
    "wof:placetype":"locality"
},
  "geometry": {"coordinates":[121.21666,29.04721],"type":"Point"}
}