{
  "type": "Feature",
  "properties": {
    "gn:admin1_code":"16.0",
    "gn:asciiname":"Jiuniuzhai",
    "gn:country_code":"CN",
    "gn:dem":110,
    "gn:feature_class":"P",
    "gn:feature_code":"PPL",
    "gn:name":"Jiuniuzhai",
    "gn:population":0,
    "gn:timezone":"Asia/Shanghai",
    "iso:country":"CN",
    "name:zho_x_preferred":[
        "\u4e5d\u725b\u5be8"
    ],
    "wof:name":"Jiuniuzhai",
    "wof:placetype":"locality"
},
  "geometry": {"coordinates":[111.604,24.435],"type":"Point"}
}