{
  "type": "Feature",
  "properties": {
    "gn:admin1_code":"19.0",
    "gn:asciiname":"Qianzhaojiagou",
    "gn:country_code":"CN",
    "gn:dem":278,
    "gn:feature_class":"P",
    "gn:feature_code":"PPL",
    "gn:name":"Qianzhaojiagou",
    "gn:population":0,
    "gn:timezone":"Asia/Shanghai",
    "iso:country":"CN",
    "name:zho_x_preferred":[
        "\u524d\u8d75\u5bb6\u6c9f"
    ],
    "wof:name":"Qianzhaojiagou",
    "wof:placetype":"locality"
},
  "geometry": {"coordinates":[120.282,41.4793],"type":"Point"}
}