{
  "type": "Feature",
  "properties": {
    "gn:admin1_code":"14.0",
    "gn:asciiname":"Anongdong",
    "gn:country_code":"CN",
    "gn:dem":4583,
    "gn:feature_class":"P",
    "gn:feature_code":"PPL",
    "gn:name":"Anongdong",
    "gn:population":0,
    "gn:timezone":"Asia/Urumqi",
    "iso:country":"CN",
    "name:zho_x_preferred":[
        "\u554a\u5f04\u6d1e"
    ],
    "wof:name":"Anongdong",
    "wof:placetype":"locality"
},
  "geometry": {"coordinates":[92.05047,30.32044],"type":"Point"}
}