{
  "type": "Feature",
  "properties": {
    "gn:admin1_code":"32.0",
    "gn:asciiname":"Xinlongtang",
    "gn:country_code":"CN",
    "gn:dem":279,
    "gn:feature_class":"P",
    "gn:feature_code":"PPL",
    "gn:name":"Xinlongtang",
    "gn:population":0,
    "gn:timezone":"Asia/Shanghai",
    "iso:country":"CN",
    "name:zho_x_preferred":[
        "\u65b0\u9f99\u5802"
    ],
    "wof:name":"Xinlongtang",
    "wof:placetype":"locality"
},
  "geometry": {"coordinates":[104.68501999999999,28.69092],"type":"Point"}
}