{
  "type": "Feature",
  "properties": {
    "gn:admin1_code":"12.0",
    "gn:asciiname":"Chencitai",
    "gn:country_code":"CN",
    "gn:dem":289,
    "gn:feature_class":"P",
    "gn:feature_code":"PPL",
    "gn:name":"Chencitai",
    "gn:population":0,
    "gn:timezone":"Asia/Shanghai",
    "iso:country":"CN",
    "name:zho_x_preferred":[
        "\u9648\u523a\u53f0"
    ],
    "wof:name":"Chencitai",
    "wof:placetype":"locality"
},
  "geometry": {"coordinates":[113.12696,32.2691],"type":"Point"}
}