{
  "type": "Feature",
  "properties": {
    "gn:admin1_code":"33.0",
    "gn:asciiname":"Shilan",
    "gn:country_code":"CN",
    "gn:dem":198,
    "gn:feature_class":"P",
    "gn:feature_code":"PPL",
    "gn:name":"Shilan",
    "gn:population":0,
    "gn:timezone":"Asia/Shanghai",
    "iso:country":"CN",
    "name:fas_x_preferred":[
        "\u0634\u06cc\u0644\u0627\u0646"
    ],
    "name:zho_x_preferred":[
        "\u77f3\u680f"
    ],
    "wof:name":"Shilan",
    "wof:placetype":"locality"
},
  "geometry": {"coordinates":[107.59329,29.82708],"type":"Point"}
}