{
  "type": "Feature",
  "properties": {
    "gn:admin1_code":"5.0",
    "gn:asciiname":"Qianjiajiagou",
    "gn:country_code":"CN",
    "gn:dem":175,
    "gn:feature_class":"P",
    "gn:feature_code":"PPL",
    "gn:name":"Qianjiajiagou",
    "gn:population":0,
    "gn:timezone":"Asia/Shanghai",
    "iso:country":"CN",
    "name:zho_x_preferred":[
        "\u524d\u8d3e\u5bb6\u6c9f"
    ],
    "wof:name":"Qianjiajiagou",
    "wof:placetype":"locality"
},
  "geometry": {"coordinates":[123.79537000000001,44.0478],"type":"Point"}
}