{
  "type": "Feature",
  "properties": {
    "gn:admin1_code":"31",
    "gn:asciiname":"Qicha",
    "gn:country_code":"CN",
    "gn:dem":122,
    "gn:feature_class":"P",
    "gn:feature_code":"PPLA4",
    "gn:name":"Qicha",
    "gn:population":0,
    "gn:timezone":"Asia/Shanghai",
    "iso:country":"CN",
    "name:und_x_variant":[
        "\u4e03\u5dee",
        "Qicha Xiang",
        "\u4e03\u5dee\u4e61"
    ],
    "wof:name":"Qicha",
    "wof:placetype":"locality"
},
  "geometry": {"coordinates":[109.06655000000001,19.11494],"type":"Point"}
}