{
  "type": "Feature",
  "properties": {
    "gn:admin1_code":"15.0",
    "gn:asciiname":"Ya'erdiwan",
    "gn:country_code":"CN",
    "gn:dem":2255,
    "gn:feature_class":"P",
    "gn:feature_code":"PPL",
    "gn:name":"Ya\u2019erdiwan",
    "gn:population":0,
    "gn:timezone":"Asia/Shanghai",
    "iso:country":"CN",
    "name:und_x_variant":[
        "Ya\u2019erdiwan"
    ],
    "name:zho_x_preferred":[
        "\u9e26\u513f\u5730\u6e7e"
    ],
    "wof:name":"Ya'erdiwan",
    "wof:placetype":"locality"
},
  "geometry": {"coordinates":[103.075,36.5712],"type":"Point"}
}