{
  "type": "Feature",
  "properties": {
    "gn:admin1_code":"32.0",
    "gn:asciiname":"Yanmijia",
    "gn:country_code":"CN",
    "gn:dem":1829,
    "gn:feature_class":"P",
    "gn:feature_code":"PPL",
    "gn:name":"Yanmijia",
    "gn:population":0,
    "gn:timezone":"Asia/Shanghai",
    "iso:country":"CN",
    "name:zho_x_preferred":[
        "\u5ca9\u7c73\u5bb6"
    ],
    "wof:name":"Yanmijia",
    "wof:placetype":"locality"
},
  "geometry": {"coordinates":[104.15600000000001,33.3406],"type":"Point"}
}