{
  "type": "Feature",
  "properties": {
    "gn:admin1_code":"29.0",
    "gn:asciiname":"Shangbangwa",
    "gn:country_code":"CN",
    "gn:dem":1197,
    "gn:feature_class":"P",
    "gn:feature_code":"PPL",
    "gn:name":"Shangbangwa",
    "gn:population":0,
    "gn:timezone":"Asia/Shanghai",
    "iso:country":"CN",
    "name:zho_x_preferred":[
        "\u4e0a\u90a6\u74e6"
    ],
    "wof:name":"Shangbangwa",
    "wof:placetype":"locality"
},
  "geometry": {"coordinates":[98.4079,24.4638],"type":"Point"}
}