{
  "type": "Feature",
  "properties": {
    "gn:admin1_code":"9",
    "gn:asciiname":"Xinwanglou",
    "gn:country_code":"CN",
    "gn:dem":47,
    "gn:feature_class":"P",
    "gn:feature_code":"PPL",
    "gn:name":"Xinwanglou",
    "gn:population":0,
    "gn:timezone":"Asia/Shanghai",
    "iso:country":"CN",
    "name:zho_x_preferred":[
        "\u65b0\u738b\u697c"
    ],
    "wof:name":"Xinwanglou",
    "wof:placetype":"locality"
},
  "geometry": {"coordinates":[115.80022,35.96959000000001],"type":"Point"}
}