{
  "type": "Feature",
  "properties": {
    "gn:admin1_code":"25",
    "gn:asciiname":"Yangquan",
    "gn:country_code":"CN",
    "gn:dem":27,
    "gn:feature_class":"P",
    "gn:feature_code":"PPL",
    "gn:name":"Yangquan",
    "gn:population":0,
    "gn:timezone":"Asia/Shanghai",
    "iso:country":"CN",
    "name:ara_x_preferred":[
        "\u064a\u0627\u0646\u063a\u062a\u0634\u0648\u0627\u0646"
    ],
    "name:cdo_x_preferred":[
        "I\u00f2ng-ci\u00f2ng"
    ],
    "name:ceb_x_preferred":[
        "Yangquan"
    ],
    "name:ces_x_preferred":[
        "Jang-\u010dch\u00fcan"
    ],
    "name:dan_x_preferred":[
        "Yangquan"
    ],
    "name:deu_x_preferred":[
        "Yangquan"
    ],
    "name:epo_x_preferred":[
        "Jancjuan"
    ],
    "name:eus_x_preferred":[
        "Yangquan"
    ],
    "name:fas_x_preferred":[
        "\u06cc\u0627\u0646\u06af\u06a9\u0648\u0627\u0646"
    ],
    "name:fin_x_preferred":[
        "Yangquan"
    ],
    "name:fra_x_preferred":[
        "Yangquan"
    ],
    "name:ita_x_preferred":[
        "Yangquan"
    ],
    "name:jpn_x_preferred":[
        "\u967d\u6cc9\u5e02"
    ],
    "name:kik_x_preferred":[
        "Yangquan"
    ],
    "name:kor_x_preferred":[
        "\uc591\ucde8\uc548\uc2dc"
    ],
    "name:mlg_x_preferred":[
        "Yangquan"
    ],
    "name:nld_x_preferred":[
        "Yangquan"
    ],
    "name:nno_x_preferred":[
        "Yangquan"
    ],
    "name:nor_x_preferred":[
        "Yangquan"
    ],
    "name:pol_x_preferred":[
        "Yangquan"
    ],
    "name:por_x_preferred":[
        "Yangquan"
    ],
    "name:rus_x_preferred":[
        "\u042f\u043d\u0446\u044e\u0430\u043d\u044c"
    ],
    "name:spa_x_preferred":[
        "Yangquan"
    ],
    "name:srp_x_preferred":[
        "\u0408\u0430\u043d\u0433\u045b\u0443\u0435\u043d"
    ],
    "name:swe_x_preferred":[
        "Yangquan"
    ],
    "name:tur_x_preferred":[
        "Yangquan"
    ],
    "name:urd_x_preferred":[
        "\u06cc\u0627\u0646\u06af\u0686\u0648\u0627\u0646"
    ],
    "name:vie_x_preferred":[
        "D\u01b0\u01a1ng Tuy\u1ec1n"
    ],
    "name:war_x_preferred":[
        "Yangquan"
    ],
    "name:wuu_x_preferred":[
        "\u9633\u6cc9\u5e02"
    ],
    "name:zho_x_preferred":[
        "\u6768\u5708"
    ],
    "name:zho_x_variant":[
        "\u9633\u6cc9\u5e02"
    ],
    "wof:name":"Yangquan",
    "wof:placetype":"locality"
},
  "geometry": {"coordinates":[116.47,36.7774],"type":"Point"}
}