{
  "type": "Feature",
  "properties": {
    "gn:admin1_code":"1.0",
    "gn:asciiname":"Hewangcun",
    "gn:country_code":"CN",
    "gn:dem":24,
    "gn:feature_class":"P",
    "gn:feature_code":"PPL",
    "gn:name":"Hewangcun",
    "gn:population":0,
    "gn:timezone":"Asia/Shanghai",
    "iso:country":"CN",
    "name:zho_x_preferred":[
        "\u6cb3\u738b\u6751"
    ],
    "wof:name":"Hewangcun",
    "wof:placetype":"locality"
},
  "geometry": {"coordinates":[117.58584999999999,33.42431],"type":"Point"}
}