{
  "type": "Feature",
  "properties": {
    "gn:admin1_code":"15.0",
    "gn:asciiname":"Heyanzi Xiazhuang",
    "gn:country_code":"CN",
    "gn:dem":2316,
    "gn:feature_class":"P",
    "gn:feature_code":"PPL",
    "gn:name":"Heyanzi Xiazhuang",
    "gn:population":0,
    "gn:timezone":"Asia/Shanghai",
    "iso:country":"CN",
    "name:zho_x_preferred":[
        "\u6cb3\u6cbf\u5b50\u4e0b\u5e84"
    ],
    "wof:name":"Heyanzi Xiazhuang",
    "wof:placetype":"locality"
},
  "geometry": {"coordinates":[101.61199999999999,38.2529],"type":"Point"}
}