{
  "type": "Feature",
  "properties": {
    "gn:admin1_code":"32.0",
    "gn:asciiname":"Liangya",
    "gn:country_code":"CN",
    "gn:dem":697,
    "gn:feature_class":"P",
    "gn:feature_code":"PPL",
    "gn:name":"Liangya",
    "gn:population":0,
    "gn:timezone":"Asia/Shanghai",
    "iso:country":"CN",
    "name:zho_x_preferred":[
        "\u51c9\u57ad"
    ],
    "wof:name":"Liangya",
    "wof:placetype":"locality"
},
  "geometry": {"coordinates":[106.82267,31.47675],"type":"Point"}
}