{
  "type": "Feature",
  "properties": {
    "gn:admin1_code":"25.0",
    "gn:asciiname":"Yingzituncun",
    "gn:country_code":"CN",
    "gn:dem":11,
    "gn:feature_class":"P",
    "gn:feature_code":"PPL",
    "gn:name":"Yingzituncun",
    "gn:population":0,
    "gn:timezone":"Asia/Shanghai",
    "iso:country":"CN",
    "name:zho_x_preferred":[
        "\u8425\u5b50\u5c6f\u6751"
    ],
    "wof:name":"Yingzituncun",
    "wof:placetype":"locality"
},
  "geometry": {"coordinates":[119.76616,36.63566],"type":"Point"}
}