{
  "type": "Feature",
  "properties": {
    "gn:admin1_code":"25",
    "gn:asciiname":"Linji",
    "gn:country_code":"CN",
    "gn:dem":23,
    "gn:feature_class":"P",
    "gn:feature_code":"PPL",
    "gn:name":"Linji",
    "gn:population":0,
    "gn:timezone":"Asia/Shanghai",
    "iso:country":"CN",
    "name:zho_x_preferred":[
        "\u4e34\u6d4e"
    ],
    "wof:name":"Linji",
    "wof:placetype":"locality"
},
  "geometry": {"coordinates":[117.276,36.9627],"type":"Point"}
}