{
  "type": "Feature",
  "properties": {
    "gn:admin1_code":"26.0",
    "gn:asciiname":"Weijiashan",
    "gn:country_code":"CN",
    "gn:dem":934,
    "gn:feature_class":"P",
    "gn:feature_code":"PPL",
    "gn:name":"Weijiashan",
    "gn:population":0,
    "gn:timezone":"Asia/Shanghai",
    "iso:country":"CN",
    "name:zho_x_preferred":[
        "\u9b4f\u5bb6\u5c71"
    ],
    "wof:name":"Weijiashan",
    "wof:placetype":"locality"
},
  "geometry": {"coordinates":[106.96793999999998,34.4272],"type":"Point"}
}