{
  "type": "Feature",
  "properties": {
    "gn:admin1_code":"19.0",
    "gn:asciiname":"Xiaolishugou",
    "gn:country_code":"CN",
    "gn:dem":104,
    "gn:feature_class":"P",
    "gn:feature_code":"PPL",
    "gn:name":"Xiaolishugou",
    "gn:population":0,
    "gn:timezone":"Asia/Shanghai",
    "iso:country":"CN",
    "name:zho_x_preferred":[
        "\u5c0f\u68a8\u6811\u6c9f"
    ],
    "wof:name":"Xiaolishugou",
    "wof:placetype":"locality"
},
  "geometry": {"coordinates":[124.086,40.3367],"type":"Point"}
}