{
  "type": "Feature",
  "properties": {
    "gn:admin1_code":"29.0",
    "gn:asciiname":"Baihuacen",
    "gn:country_code":"CN",
    "gn:dem":921,
    "gn:feature_class":"P",
    "gn:feature_code":"PPL",
    "gn:name":"Baihuacen",
    "gn:population":0,
    "gn:timezone":"Asia/Shanghai",
    "iso:country":"CN",
    "name:zho_x_preferred":[
        "\u767d\u82b1\u5c91"
    ],
    "wof:name":"Baihuacen",
    "wof:placetype":"locality"
},
  "geometry": {"coordinates":[98.8689,25.7156],"type":"Point"}
}