{
  "type": "Feature",
  "properties": {
    "gn:admin1_code":"24.0",
    "gn:asciiname":"Hantun",
    "gn:country_code":"CN",
    "gn:dem":732,
    "gn:feature_class":"P",
    "gn:feature_code":"PPL",
    "gn:name":"Hantun",
    "gn:population":0,
    "gn:timezone":"Asia/Shanghai",
    "iso:country":"CN",
    "name:zho_x_preferred":[
        "\u97e9\u5c6f"
    ],
    "name:zho_x_variant":[
        "\u97e9\u5c6f\u9547"
    ],
    "wof:name":"Hantun",
    "wof:placetype":"locality"
},
  "geometry": {"coordinates":[111.88893,37.05289000000001],"type":"Point"}
}