{
  "type": "Feature",
  "properties": {
    "gn:admin1_code":"16.0",
    "gn:asciiname":"Wailouti",
    "gn:country_code":"CN",
    "gn:dem":482,
    "gn:feature_class":"P",
    "gn:feature_code":"PPL",
    "gn:name":"Wailouti",
    "gn:population":0,
    "gn:timezone":"Asia/Shanghai",
    "iso:country":"CN",
    "name:zho_x_preferred":[
        "\u5916\u697c\u68af"
    ],
    "wof:name":"Wailouti",
    "wof:placetype":"locality"
},
  "geometry": {"coordinates":[108.491,24.7048],"type":"Point"}
}