{
  "type": "Feature",
  "properties": {
    "gn:admin1_code":"18",
    "gn:asciiname":"Aijiagou",
    "gn:country_code":"CN",
    "gn:dem":493,
    "gn:feature_class":"P",
    "gn:feature_code":"PPL",
    "gn:name":"Aijiagou",
    "gn:population":0,
    "gn:timezone":"Asia/Shanghai",
    "iso:country":"CN",
    "name:zho_x_preferred":[
        "\u827e\u5bb6\u6c9f"
    ],
    "wof:name":"Aijiagou",
    "wof:placetype":"locality"
},
  "geometry": {"coordinates":[107.965,27.6491],"type":"Point"}
}