{
  "type": "Feature",
  "properties": {
    "gn:admin1_code":"3.0",
    "gn:asciiname":"Duimencun",
    "gn:country_code":"CN",
    "gn:dem":65,
    "gn:feature_class":"P",
    "gn:feature_code":"PPL",
    "gn:name":"Duimencun",
    "gn:population":0,
    "gn:timezone":"Asia/Shanghai",
    "iso:country":"CN",
    "name:und_x_variant":[
        "\u5bf9\u95e8\u6751"
    ],
    "wof:name":"Duimencun",
    "wof:placetype":"locality"
},
  "geometry": {"coordinates":[115.41665,28.57787],"type":"Point"}
}