{
  "type": "Feature",
  "properties": {
    "gn:admin1_code":"6.0",
    "gn:asciiname":"Qingshui",
    "gn:country_code":"CN",
    "gn:dem":3970,
    "gn:feature_class":"P",
    "gn:feature_code":"PPL",
    "gn:name":"Qingshui",
    "gn:population":0,
    "gn:timezone":"Asia/Shanghai",
    "iso:country":"CN",
    "name:zho_x_preferred":[
        "\u6e05\u6c34"
    ],
    "wof:name":"Qingshui",
    "wof:placetype":"locality"
},
  "geometry": {"coordinates":[99.27512,34.99590999999999],"type":"Point"}
}