{
  "type": "Feature",
  "properties": {
    "gn:admin1_code":"29.0",
    "gn:asciiname":"Xiaozhuang",
    "gn:country_code":"CN",
    "gn:dem":1307,
    "gn:feature_class":"P",
    "gn:feature_code":"PPL",
    "gn:name":"Xiaozhuang",
    "gn:population":0,
    "gn:timezone":"Asia/Shanghai",
    "iso:country":"CN",
    "name:ceb_x_preferred":[
        "Xiaozhuang"
    ],
    "name:zho_x_preferred":[
        "\u5c0f\u5e84"
    ],
    "wof:name":"Xiaozhuang",
    "wof:placetype":"locality"
},
  "geometry": {"coordinates":[98.8974,25.6707],"type":"Point"}
}