{
  "type": "Feature",
  "properties": {
    "gn:admin1_code":"4.0",
    "gn:asciiname":"Yunxingxu",
    "gn:country_code":"CN",
    "gn:dem":4,
    "gn:feature_class":"P",
    "gn:feature_code":"PPL",
    "gn:name":"Yunxingxu",
    "gn:population":0,
    "gn:timezone":"Asia/Shanghai",
    "iso:country":"CN",
    "name:zho_x_preferred":[
        "\u607d\u5174\u5729"
    ],
    "wof:name":"Yunxingxu",
    "wof:placetype":"locality"
},
  "geometry": {"coordinates":[119.91347,32.01121],"type":"Point"}
}