{
  "type": "Feature",
  "properties": {
    "gn:admin1_code":"14.0",
    "gn:asciiname":"Guocangduo",
    "gn:country_code":"CN",
    "gn:dem":4670,
    "gn:feature_class":"P",
    "gn:feature_code":"PPL",
    "gn:name":"Guocangduo",
    "gn:population":0,
    "gn:timezone":"Asia/Shanghai",
    "iso:country":"CN",
    "name:zho_x_preferred":[
        "\u679c\u4ed3\u591a"
    ],
    "wof:name":"Guocangduo",
    "wof:placetype":"locality"
},
  "geometry": {"coordinates":[80.78660000000001,32.0667],"type":"Point"}
}