{
  "type": "Feature",
  "properties": {
    "gn:admin1_code":"3",
    "gn:asciiname":"Zoumadong",
    "gn:country_code":"CN",
    "gn:dem":979,
    "gn:feature_class":"P",
    "gn:feature_code":"PPL",
    "gn:name":"Zoumadong",
    "gn:population":0,
    "gn:timezone":"Asia/Shanghai",
    "iso:country":"CN",
    "name:zho_x_preferred":[
        "\u8d70\u9a6c\u6d1e"
    ],
    "wof:name":"Zoumadong",
    "wof:placetype":"locality"
},
  "geometry": {"coordinates":[113.928,25.7346],"type":"Point"}
}