{
  "type": "Feature",
  "properties": {
    "gn:admin1_code":"11.0",
    "gn:asciiname":"Yulingpu",
    "gn:country_code":"CN",
    "gn:dem":363,
    "gn:feature_class":"P",
    "gn:feature_code":"PPL",
    "gn:name":"Yulingpu",
    "gn:population":0,
    "gn:timezone":"Asia/Shanghai",
    "iso:country":"CN",
    "name:zho_x_preferred":[
        "\u9c7c\u5cad\u94fa"
    ],
    "wof:name":"Yulingpu",
    "wof:placetype":"locality"
},
  "geometry": {"coordinates":[113.32051,25.93303],"type":"Point"}
}