{
  "type": "Feature",
  "properties": {
    "gn:admin1_code":"11.0",
    "gn:asciiname":"Sanfenchang Qidui",
    "gn:country_code":"CN",
    "gn:dem":32,
    "gn:feature_class":"P",
    "gn:feature_code":"PPLF",
    "gn:name":"Sanfenchang Qidui",
    "gn:population":0,
    "gn:timezone":"Asia/Shanghai",
    "iso:country":"CN",
    "name:zho_x_preferred":[
        "Sanfenchang Qidui"
    ],
    "name:zho_x_variant":[
        "\u4e09\u5206\u573a\u4e03\u961f"
    ],
    "wof:name":"Sanfenchang Qidui",
    "wof:placetype":"locality"
},
  "geometry": {"coordinates":[112.04425999999999,29.05198],"type":"Point"}
}