{
  "type": "Feature",
  "properties": {
    "gn:admin1_code":"7.0",
    "gn:asciiname":"Kengtoulong",
    "gn:country_code":"CN",
    "gn:dem":654,
    "gn:feature_class":"P",
    "gn:feature_code":"PPL",
    "gn:name":"Kengtoulong",
    "gn:population":0,
    "gn:timezone":"Asia/Shanghai",
    "iso:country":"CN",
    "name:zho_x_preferred":[
        "\u5751\u5934\u5784"
    ],
    "wof:name":"Kengtoulong",
    "wof:placetype":"locality"
},
  "geometry": {"coordinates":[118.17941999999999,25.89329],"type":"Point"}
}