{
  "type": "Feature",
  "properties": {
    "gn:admin1_code":"12.0",
    "gn:asciiname":"Daozuomiao",
    "gn:country_code":"CN",
    "gn:dem":133,
    "gn:feature_class":"P",
    "gn:feature_code":"PPL",
    "gn:name":"Daozuomiao",
    "gn:population":0,
    "gn:timezone":"Asia/Shanghai",
    "iso:country":"CN",
    "name:zho_x_preferred":[
        "\u5012\u5ea7\u5e99"
    ],
    "wof:name":"Daozuomiao",
    "wof:placetype":"locality"
},
  "geometry": {"coordinates":[111.49745,32.32039],"type":"Point"}
}