{
  "type": "Feature",
  "properties": {
    "gn:admin1_code":"12.0",
    "gn:asciiname":"Yiyangwan",
    "gn:country_code":"CN",
    "gn:dem":27,
    "gn:feature_class":"P",
    "gn:feature_code":"PPL",
    "gn:name":"Yiyangwan",
    "gn:population":0,
    "gn:timezone":"Asia/Shanghai",
    "iso:country":"CN",
    "name:zho_x_preferred":[
        "\u6613\u6768\u6e7e"
    ],
    "wof:name":"Yiyangwan",
    "wof:placetype":"locality"
},
  "geometry": {"coordinates":[112.82262,30.04355],"type":"Point"}
}