{
  "type": "Feature",
  "properties": {
    "gn:admin1_code":"1.0",
    "gn:asciiname":"Zhoutou",
    "gn:country_code":"CN",
    "gn:dem":23,
    "gn:feature_class":"P",
    "gn:feature_code":"PPLA4",
    "gn:name":"Zhoutou",
    "gn:population":0,
    "gn:timezone":"Asia/Shanghai",
    "iso:country":"CN",
    "name:und_x_variant":[
        "Lao-chou-t\u2019ou",
        "Laozhoutou",
        "Zhoutou",
        "\u6d32\u5934",
        "Zhoutou Xiang",
        "\u6d32\u5934\u4e61"
    ],
    "wof:name":"Zhoutou",
    "wof:placetype":"locality"
},
  "geometry": {"coordinates":[116.31816000000001,29.86409],"type":"Point"}
}