{
  "type": "Feature",
  "properties": {
    "gn:admin1_code":"11.0",
    "gn:asciiname":"Qimulin",
    "gn:country_code":"CN",
    "gn:dem":216,
    "gn:feature_class":"P",
    "gn:feature_code":"PPL",
    "gn:name":"Qimulin",
    "gn:population":0,
    "gn:timezone":"Asia/Shanghai",
    "iso:country":"CN",
    "name:zho_x_preferred":[
        "\u675e\u6728\u6797"
    ],
    "wof:name":"Qimulin",
    "wof:placetype":"locality"
},
  "geometry": {"coordinates":[112.47078,25.95766],"type":"Point"}
}