{
  "type": "Feature",
  "properties": {
    "gn:admin1_code":"29.0",
    "gn:asciiname":"Baomaidi",
    "gn:country_code":"CN",
    "gn:dem":1891,
    "gn:feature_class":"P",
    "gn:feature_code":"PPL",
    "gn:name":"Baomaidi",
    "gn:population":0,
    "gn:timezone":"Asia/Shanghai",
    "iso:country":"CN",
    "name:zho_x_preferred":[
        "\u5305\u9ea6\u5730"
    ],
    "wof:name":"Baomaidi",
    "wof:placetype":"locality"
},
  "geometry": {"coordinates":[100.08199999999999,22.5363],"type":"Point"}
}