{
  "type": "Feature",
  "properties": {
    "gn:admin1_code":"10",
    "gn:asciiname":"Dongshuangta",
    "gn:country_code":"CN",
    "gn:dem":41,
    "gn:feature_class":"P",
    "gn:feature_code":"PPL",
    "gn:name":"Dongshuangta",
    "gn:population":0,
    "gn:timezone":"Asia/Shanghai",
    "iso:country":"CN",
    "name:zho_x_preferred":[
        "\u8463\u53cc\u5854"
    ],
    "wof:name":"Dongshuangta",
    "wof:placetype":"locality"
},
  "geometry": {"coordinates":[114.843,36.8977],"type":"Point"}
}