{
  "type": "Feature",
  "properties": {
    "gn:admin1_code":"29.0",
    "gn:asciiname":"Heigutian",
    "gn:country_code":"CN",
    "gn:dem":1574,
    "gn:feature_class":"P",
    "gn:feature_code":"PPL",
    "gn:name":"Heigutian",
    "gn:population":0,
    "gn:timezone":"Asia/Shanghai",
    "iso:country":"CN",
    "name:zho_x_preferred":[
        "\u9ed1\u8c37\u7530"
    ],
    "wof:name":"Heigutian",
    "wof:placetype":"locality"
},
  "geometry": {"coordinates":[99.3618,25.6494],"type":"Point"}
}