{
  "type": "Feature",
  "properties": {
    "gn:admin1_code":"15.0",
    "gn:asciiname":"Xiaojiashan",
    "gn:country_code":"CN",
    "gn:dem":1667,
    "gn:feature_class":"P",
    "gn:feature_code":"PPL",
    "gn:name":"Xiaojiashan",
    "gn:population":0,
    "gn:timezone":"Asia/Shanghai",
    "iso:country":"CN",
    "name:und_x_variant":[
        "\u8096\u5bb6\u5c71"
    ],
    "wof:name":"Xiaojiashan",
    "wof:placetype":"locality"
},
  "geometry": {"coordinates":[105.49023,33.35082],"type":"Point"}
}