{
  "type": "Feature",
  "properties": {
    "gn:admin1_code":"11.0",
    "gn:asciiname":"Chengjia Hebian",
    "gn:country_code":"CN",
    "gn:dem":62,
    "gn:feature_class":"P",
    "gn:feature_code":"PPL",
    "gn:name":"Chengjia Hebian",
    "gn:population":0,
    "gn:timezone":"Asia/Shanghai",
    "iso:country":"CN",
    "name:zho_x_preferred":[
        "\u7a0b\u5bb6\u6cb3\u8fb9"
    ],
    "wof:name":"Chengjia Hebian",
    "wof:placetype":"locality"
},
  "geometry": {"coordinates":[112.71995,26.79783],"type":"Point"}
}