{
  "type": "Feature",
  "properties": {
    "gn:admin1_code":"25.0",
    "gn:asciiname":"Xiaotaibaocun",
    "gn:country_code":"CN",
    "gn:dem":36,
    "gn:feature_class":"P",
    "gn:feature_code":"PPL",
    "gn:name":"Xiaotaibaocun",
    "gn:population":0,
    "gn:timezone":"Asia/Shanghai",
    "iso:country":"CN",
    "name:zho_x_preferred":[
        "\u5c0f\u592a\u4fdd\u6751"
    ],
    "wof:name":"Xiaotaibaocun",
    "wof:placetype":"locality"
},
  "geometry": {"coordinates":[119.44549000000001,36.5189],"type":"Point"}
}