{
  "type": "Feature",
  "properties": {
    "gn:admin1_code":"12.0",
    "gn:asciiname":"Zhonglingzi",
    "gn:country_code":"CN",
    "gn:dem":31,
    "gn:feature_class":"P",
    "gn:feature_code":"PPL",
    "gn:name":"Zhonglingzi",
    "gn:population":0,
    "gn:timezone":"Asia/Shanghai",
    "iso:country":"CN",
    "name:zho_x_preferred":[
        "\u4e2d\u5cad\u5b50"
    ],
    "wof:name":"Zhonglingzi",
    "wof:placetype":"locality"
},
  "geometry": {"coordinates":[112.6615,29.78326],"type":"Point"}
}