{
  "type": "Feature",
  "properties": {
    "gn:admin1_code":"24.0",
    "gn:asciiname":"Tulingkou",
    "gn:country_code":"CN",
    "gn:dem":997,
    "gn:feature_class":"P",
    "gn:feature_code":"PPL",
    "gn:name":"Tulingkou",
    "gn:population":0,
    "gn:timezone":"Asia/Shanghai",
    "iso:country":"CN",
    "name:zho_x_preferred":[
        "\u571f\u5cad\u53e3"
    ],
    "wof:name":"Tulingkou",
    "wof:placetype":"locality"
},
  "geometry": {"coordinates":[113.08278,38.49095],"type":"Point"}
}