{
  "type": "Feature",
  "properties": {
    "gn:admin1_code":"11.0",
    "gn:asciiname":"Nantianshan",
    "gn:country_code":"CN",
    "gn:dem":1486,
    "gn:feature_class":"P",
    "gn:feature_code":"PPL",
    "gn:name":"Nantianshan",
    "gn:population":0,
    "gn:timezone":"Asia/Shanghai",
    "iso:country":"CN",
    "name:zho_x_preferred":[
        "\u5357\u7530\u5c71"
    ],
    "wof:name":"Nantianshan",
    "wof:placetype":"locality"
},
  "geometry": {"coordinates":[110.11429,26.20974],"type":"Point"}
}