{
  "type": "Feature",
  "properties": {
    "gn:admin1_code":"14.0",
    "gn:asciiname":"Daburen",
    "gn:country_code":"CN",
    "gn:dem":4147,
    "gn:feature_class":"P",
    "gn:feature_code":"PPL",
    "gn:name":"Daburen",
    "gn:population":0,
    "gn:timezone":"Asia/Urumqi",
    "iso:country":"CN",
    "name:zho_x_preferred":[
        "\u8fbe\u5e03\u4ec1"
    ],
    "wof:name":"Daburen",
    "wof:placetype":"locality"
},
  "geometry": {"coordinates":[87.90989999999999,28.9828],"type":"Point"}
}