{
  "type": "Feature",
  "properties": {
    "gn:admin1_code":"26.0",
    "gn:asciiname":"Jiling",
    "gn:country_code":"CN",
    "gn:dem":873,
    "gn:feature_class":"P",
    "gn:feature_code":"PPL",
    "gn:name":"Jiling",
    "gn:population":0,
    "gn:timezone":"Asia/Shanghai",
    "iso:country":"CN",
    "name:ceb_x_preferred":[
        "Jiling"
    ],
    "name:fra_x_preferred":[
        "Jiling"
    ],
    "name:mai_x_preferred":[
        "\u091c\u093f\u0932\u093f\u0919"
    ],
    "name:msa_x_preferred":[
        "Jiling"
    ],
    "name:nep_x_preferred":[
        "\u091c\u093f\u0932\u093f\u0919"
    ],
    "name:new_x_preferred":[
        "\u091c\u093f\u0932\u093f\u0921"
    ],
    "name:pol_x_preferred":[
        "Jiling"
    ],
    "name:zho_x_preferred":[
        "\u5409\u5cad"
    ],
    "wof:name":"Jiling",
    "wof:placetype":"locality"
},
  "geometry": {"coordinates":[109.24748,34.27385],"type":"Point"}
}