{
  "type": "Feature",
  "properties": {
    "gn:admin1_code":"15.0",
    "gn:asciiname":"Xiaowangyaoxian",
    "gn:country_code":"CN",
    "gn:dem":1553,
    "gn:feature_class":"P",
    "gn:feature_code":"PPL",
    "gn:name":"Xiaowangyaoxian",
    "gn:population":0,
    "gn:timezone":"Asia/Shanghai",
    "iso:country":"CN",
    "name:und_x_variant":[
        "\u5c0f\u738b\u5d3e\u5c98"
    ],
    "wof:name":"Xiaowangyaoxian",
    "wof:placetype":"locality"
},
  "geometry": {"coordinates":[107.43342,36.73649],"type":"Point"}
}