{
  "type": "Feature",
  "properties": {
    "gn:admin1_code":"19.0",
    "gn:asciiname":"Quanhe",
    "gn:country_code":"CN",
    "gn:dem":5,
    "gn:feature_class":"P",
    "gn:feature_code":"PPL",
    "gn:name":"Quanhe",
    "gn:population":0,
    "gn:timezone":"Asia/Shanghai",
    "iso:country":"CN",
    "name:zho_x_preferred":[
        "\u5708\u6cb3"
    ],
    "wof:name":"Quanhe",
    "wof:placetype":"locality"
},
  "geometry": {"coordinates":[122.04291000000001,41.06836],"type":"Point"}
}