{
  "type": "Feature",
  "properties": {
    "gn:admin1_code":"02",
    "gn:asciiname":"Zhongshi",
    "gn:country_code":"CN",
    "gn:dem":7,
    "gn:feature_class":"P",
    "gn:feature_code":"PPL",
    "gn:name":"Zhongshi",
    "gn:population":0,
    "gn:timezone":"Asia/Shanghai",
    "iso:country":"CN",
    "name:und_x_variant":[
        "Chung-shih"
    ],
    "name:zho_x_preferred":[
        "\u91cd\u77f3"
    ],
    "wof:name":"Zhongshi",
    "wof:placetype":"locality"
},
  "geometry": {"coordinates":[120.82091,28.00897],"type":"Point"}
}