{
  "type": "Feature",
  "properties": {
    "gn:admin1_code":"10.0",
    "gn:asciiname":"Langwokou",
    "gn:country_code":"CN",
    "gn:dem":3,
    "gn:feature_class":"P",
    "gn:feature_code":"PPL",
    "gn:name":"Langwokou",
    "gn:population":0,
    "gn:timezone":"Asia/Shanghai",
    "iso:country":"CN",
    "name:zho_x_preferred":[
        "\u6d6a\u7a9d\u53e3"
    ],
    "wof:name":"Langwokou",
    "wof:placetype":"locality"
},
  "geometry": {"coordinates":[119.14167,39.3634],"type":"Point"}
}