{
  "type": "Feature",
  "properties": {
    "gn:admin1_code":"12.0",
    "gn:asciiname":"Xiapengjiahe",
    "gn:country_code":"CN",
    "gn:dem":71,
    "gn:feature_class":"P",
    "gn:feature_code":"PPL",
    "gn:name":"Xiapengjiahe",
    "gn:population":0,
    "gn:timezone":"Asia/Shanghai",
    "iso:country":"CN",
    "name:zho_x_preferred":[
        "\u4e0b\u5f6d\u5bb6\u6cb3"
    ],
    "wof:name":"Xiapengjiahe",
    "wof:placetype":"locality"
},
  "geometry": {"coordinates":[113.47739,31.47575],"type":"Point"}
}