{
  "type": "Feature",
  "properties": {
    "gn:admin1_code":"20.0",
    "gn:asciiname":"Dajinzi",
    "gn:country_code":"CN",
    "gn:dem":1368,
    "gn:feature_class":"P",
    "gn:feature_code":"PPL",
    "gn:name":"Dajinzi",
    "gn:population":0,
    "gn:timezone":"Asia/Shanghai",
    "iso:country":"CN",
    "name:und_x_variant":[
        "\u5927\u4e95\u5b50"
    ],
    "wof:name":"Dajinzi",
    "wof:placetype":"locality"
},
  "geometry": {"coordinates":[113.41003000000001,41.51957],"type":"Point"}
}