{
  "type": "Feature",
  "properties": {
    "gn:admin1_code":"7",
    "gn:asciiname":"Niudikeng",
    "gn:country_code":"CN",
    "gn:dem":377,
    "gn:feature_class":"P",
    "gn:feature_code":"PPL",
    "gn:name":"Niudikeng",
    "gn:population":0,
    "gn:timezone":"Asia/Shanghai",
    "iso:country":"CN",
    "name:und_x_variant":[
        "\u725b\u5730\u5751",
        "Niudikeng"
    ],
    "wof:name":"Niudikeng",
    "wof:placetype":"locality"
},
  "geometry": {"coordinates":[119.52844,27.02252],"type":"Point"}
}