{
  "type": "Feature",
  "properties": {
    "gn:admin1_code":"32.0",
    "gn:asciiname":"Youzhaping",
    "gn:country_code":"CN",
    "gn:dem":684,
    "gn:feature_class":"P",
    "gn:feature_code":"PPL",
    "gn:name":"Youzhaping",
    "gn:population":0,
    "gn:timezone":"Asia/Shanghai",
    "iso:country":"CN",
    "name:zho_x_preferred":[
        "\u6cb9\u69a8\u576a"
    ],
    "wof:name":"Youzhaping",
    "wof:placetype":"locality"
},
  "geometry": {"coordinates":[106.361,31.7813],"type":"Point"}
}