{
  "type": "Feature",
  "properties": {
    "gn:admin1_code":"33.0",
    "gn:asciiname":"Woyun",
    "gn:country_code":"CN",
    "gn:dem":877,
    "gn:feature_class":"P",
    "gn:feature_code":"PPL",
    "gn:name":"Woyun",
    "gn:population":0,
    "gn:timezone":"Asia/Shanghai",
    "iso:country":"CN",
    "name:zho_x_preferred":[
        "\u5367\u4e91"
    ],
    "wof:name":"Woyun",
    "wof:placetype":"locality"
},
  "geometry": {"coordinates":[108.15525,31.24916],"type":"Point"}
}