{
  "type": "Feature",
  "properties": {
    "gn:admin1_code":"26",
    "gn:asciiname":"Diwucun",
    "gn:country_code":"CN",
    "gn:dem":459,
    "gn:feature_class":"P",
    "gn:feature_code":"PPL",
    "gn:name":"Diwucun",
    "gn:population":0,
    "gn:timezone":"Asia/Shanghai",
    "iso:country":"CN",
    "name:zho_x_preferred":[
        "\u7b2c\u4e94\u6751"
    ],
    "wof:name":"Diwucun",
    "wof:placetype":"locality"
},
  "geometry": {"coordinates":[108.91194,34.70139],"type":"Point"}
}