{
  "type": "Feature",
  "properties": {
    "gn:admin1_code":"26.0",
    "gn:asciiname":"Qiaojiashan",
    "gn:country_code":"CN",
    "gn:dem":1393,
    "gn:feature_class":"P",
    "gn:feature_code":"PPL",
    "gn:name":"Qiaojiashan",
    "gn:population":0,
    "gn:timezone":"Asia/Shanghai",
    "iso:country":"CN",
    "name:und_x_variant":[
        "\u4e54\u5bb6\u5c71"
    ],
    "wof:name":"Qiaojiashan",
    "wof:placetype":"locality"
},
  "geometry": {"coordinates":[106.27742000000001,33.41843],"type":"Point"}
}