{
  "type": "Feature",
  "properties": {
    "gn:admin1_code":"1.0",
    "gn:asciiname":"Jiaozhaicun",
    "gn:country_code":"CN",
    "gn:dem":33,
    "gn:feature_class":"P",
    "gn:feature_code":"PPL",
    "gn:name":"Jiaozhaicun",
    "gn:population":0,
    "gn:timezone":"Asia/Shanghai",
    "iso:country":"CN",
    "name:und_x_variant":[
        "Jiaozhai"
    ],
    "name:zho_x_preferred":[
        "\u7126\u5be8\u6751"
    ],
    "wof:name":"Jiaozhaicun",
    "wof:placetype":"locality"
},
  "geometry": {"coordinates":[115.77509000000001,32.67273],"type":"Point"}
}