{
  "type": "Feature",
  "properties": {
    "gn:admin1_code":"4.0",
    "gn:asciiname":"Shouhecun",
    "gn:country_code":"CN",
    "gn:dem":4,
    "gn:feature_class":"P",
    "gn:feature_code":"PPL",
    "gn:name":"Shouhecun",
    "gn:population":0,
    "gn:timezone":"Asia/Shanghai",
    "iso:country":"CN",
    "name:zho_x_preferred":[
        "\u53d7\u6cb3\u6751"
    ],
    "wof:name":"Shouhecun",
    "wof:placetype":"locality"
},
  "geometry": {"coordinates":[119.34949,33.47247],"type":"Point"}
}