{
  "type": "Feature",
  "properties": {
    "gn:admin1_code":"32.0",
    "gn:asciiname":"Lanya",
    "gn:country_code":"CN",
    "gn:dem":887,
    "gn:feature_class":"P",
    "gn:feature_code":"PPL",
    "gn:name":"Lanya",
    "gn:population":0,
    "gn:timezone":"Asia/Shanghai",
    "iso:country":"CN",
    "name:und_x_variant":[
        "\u5c9a\u57ad"
    ],
    "wof:name":"Lanya",
    "wof:placetype":"locality"
},
  "geometry": {"coordinates":[106.02086,32.72955],"type":"Point"}
}