{
  "type": "Feature",
  "properties": {
    "gn:admin1_code":"12.0",
    "gn:asciiname":"Huangcaifan",
    "gn:country_code":"CN",
    "gn:dem":57,
    "gn:feature_class":"P",
    "gn:feature_code":"PPL",
    "gn:name":"Huangcaifan",
    "gn:population":0,
    "gn:timezone":"Asia/Shanghai",
    "iso:country":"CN",
    "name:zho_x_preferred":[
        "\u9ec4\u624d\u7548"
    ],
    "wof:name":"Huangcaifan",
    "wof:placetype":"locality"
},
  "geometry": {"coordinates":[114.43452000000001,31.37533],"type":"Point"}
}