{
  "type": "Feature",
  "properties": {
    "gn:admin1_code":"8.0",
    "gn:asciiname":"Dawangliuzi",
    "gn:country_code":"CN",
    "gn:dem":215,
    "gn:feature_class":"P",
    "gn:feature_code":"PPL",
    "gn:name":"Dawangliuzi",
    "gn:population":0,
    "gn:timezone":"Asia/Shanghai",
    "iso:country":"CN",
    "name:zho_x_preferred":[
        "\u5927\u738b\u516d\u5b50"
    ],
    "wof:name":"Dawangliuzi",
    "wof:placetype":"locality"
},
  "geometry": {"coordinates":[124.89127000000001,48.09689],"type":"Point"}
}