{
  "type": "Feature",
  "properties": {
    "gn:admin1_code":"11",
    "gn:asciiname":"Meihua",
    "gn:country_code":"CN",
    "gn:dem":333,
    "gn:feature_class":"P",
    "gn:feature_code":"PPLA4",
    "gn:name":"Meihua",
    "gn:population":0,
    "gn:timezone":"Asia/Shanghai",
    "iso:country":"CN",
    "name:und_x_variant":[
        "Meihua Xiang"
    ],
    "name:zho_x_preferred":[
        "\u6885\u82b1"
    ],
    "name:zho_x_variant":[
        "\u6885\u82b1\u4e61"
    ],
    "wof:name":"Meihua",
    "wof:placetype":"locality"
},
  "geometry": {"coordinates":[109.65837999999999,28.70044],"type":"Point"}
}