{
  "type": "Feature",
  "properties": {
    "gn:admin1_code":"15.0",
    "gn:asciiname":"Liupaiziping",
    "gn:country_code":"CN",
    "gn:dem":2013,
    "gn:feature_class":"P",
    "gn:feature_code":"PPL",
    "gn:name":"Liupaiziping",
    "gn:population":0,
    "gn:timezone":"Asia/Shanghai",
    "iso:country":"CN",
    "name:zho_x_preferred":[
        "\u5218\u6392\u5b50\u576a"
    ],
    "wof:name":"Liupaiziping",
    "wof:placetype":"locality"
},
  "geometry": {"coordinates":[103.807,35.1883],"type":"Point"}
}