{
  "type": "Feature",
  "properties": {
    "gn:admin1_code":"16.0",
    "gn:asciiname":"Laofuling",
    "gn:country_code":"CN",
    "gn:dem":54,
    "gn:feature_class":"P",
    "gn:feature_code":"PPL",
    "gn:name":"Laofuling",
    "gn:population":0,
    "gn:timezone":"Asia/Shanghai",
    "iso:country":"CN",
    "name:zho_x_preferred":[
        "\u8001\u5bcc\u5cad"
    ],
    "wof:name":"Laofuling",
    "wof:placetype":"locality"
},
  "geometry": {"coordinates":[109.78100000000001,23.0872],"type":"Point"}
}