{
  "type": "Feature",
  "properties": {
    "gn:admin1_code":"25",
    "gn:asciiname":"Zhangxuelou",
    "gn:country_code":"CN",
    "gn:dem":47,
    "gn:feature_class":"P",
    "gn:feature_code":"PPL",
    "gn:name":"Zhangxuelou",
    "gn:population":0,
    "gn:timezone":"Asia/Shanghai",
    "iso:country":"CN",
    "name:zho_x_preferred":[
        "\u5f20\u96ea\u697c"
    ],
    "wof:name":"Zhangxuelou",
    "wof:placetype":"locality"
},
  "geometry": {"coordinates":[115.944,34.7819],"type":"Point"}
}