{
  "type": "Feature",
  "properties": {
    "gn:admin1_code":"12.0",
    "gn:asciiname":"Tudizui",
    "gn:country_code":"CN",
    "gn:dem":30,
    "gn:feature_class":"P",
    "gn:feature_code":"PPL",
    "gn:name":"Tudizui",
    "gn:population":0,
    "gn:timezone":"Asia/Shanghai",
    "iso:country":"CN",
    "name:und_x_variant":[
        "\u571f\u5824\u5480"
    ],
    "name:zho_x_preferred":[
        "\u571f\u5730\u5480"
    ],
    "wof:name":"Tudizui",
    "wof:placetype":"locality"
},
  "geometry": {"coordinates":[114.52497,30.19015],"type":"Point"}
}