{
  "type": "Feature",
  "properties": {
    "gn:admin1_code":"7.0",
    "gn:asciiname":"Tangmenli",
    "gn:country_code":"CN",
    "gn:dem":1031,
    "gn:feature_class":"P",
    "gn:feature_code":"PPL",
    "gn:name":"Tangmenli",
    "gn:population":0,
    "gn:timezone":"Asia/Shanghai",
    "iso:country":"CN",
    "name:zho_x_preferred":[
        "\u5802\u95e8\u91cc"
    ],
    "wof:name":"Tangmenli",
    "wof:placetype":"locality"
},
  "geometry": {"coordinates":[119.20317,26.93818],"type":"Point"}
}