{
  "type": "Feature",
  "properties": {
    "gn:admin1_code":"11.0",
    "gn:asciiname":"Xinganxilong",
    "gn:country_code":"CN",
    "gn:dem":749,
    "gn:feature_class":"P",
    "gn:feature_code":"PPL",
    "gn:name":"Xinganxilong",
    "gn:population":0,
    "gn:timezone":"Asia/Shanghai",
    "iso:country":"CN",
    "name:zho_x_preferred":[
        "\u65b0\u5e72\u6eaa\u5784"
    ],
    "wof:name":"Xinganxilong",
    "wof:placetype":"locality"
},
  "geometry": {"coordinates":[113.58578,26.12799],"type":"Point"}
}