{
  "type": "Feature",
  "properties": {
    "gn:admin1_code":"18",
    "gn:asciiname":"Chuandichang",
    "gn:country_code":"CN",
    "gn:dem":1749,
    "gn:feature_class":"P",
    "gn:feature_code":"PPL",
    "gn:name":"Chuandichang",
    "gn:population":0,
    "gn:timezone":"Asia/Shanghai",
    "iso:country":"CN",
    "name:zho_x_preferred":[
        "\u5ddd\u5e95\u573a"
    ],
    "wof:name":"Chuandichang",
    "wof:placetype":"locality"
},
  "geometry": {"coordinates":[105.756,27.2838],"type":"Point"}
}