{
  "type": "Feature",
  "properties": {
    "gn:admin1_code":"11.0",
    "gn:asciiname":"Xiaxinyuan",
    "gn:country_code":"CN",
    "gn:dem":32,
    "gn:feature_class":"P",
    "gn:feature_code":"PPL",
    "gn:name":"Xiaxinyuan",
    "gn:population":0,
    "gn:timezone":"Asia/Shanghai",
    "iso:country":"CN",
    "name:zho_x_preferred":[
        "Xiaxinyuan"
    ],
    "name:zho_x_variant":[
        "\u4e0b\u65b0\u57b8"
    ],
    "wof:name":"Xiaxinyuan",
    "wof:placetype":"locality"
},
  "geometry": {"coordinates":[111.97889000000001,29.55023],"type":"Point"}
}