{
  "type": "Feature",
  "properties": {
    "gn:admin1_code":"25.0",
    "gn:asciiname":"Andongwei",
    "gn:country_code":"CN",
    "gn:dem":6,
    "gn:feature_class":"P",
    "gn:feature_code":"PPL",
    "gn:name":"Andongwei",
    "gn:population":0,
    "gn:timezone":"Asia/Shanghai",
    "iso:country":"CN",
    "name:zho_x_preferred":[
        "\u5b89\u4e1c\u536b"
    ],
    "wof:name":"Andongwei",
    "wof:placetype":"locality"
},
  "geometry": {"coordinates":[119.31140000000001,35.11266],"type":"Point"}
}