{
  "type": "Feature",
  "properties": {
    "gn:admin1_code":"5",
    "gn:asciiname":"Langdonggou Xiatun",
    "gn:country_code":"CN",
    "gn:dem":268,
    "gn:feature_class":"P",
    "gn:feature_code":"PPL",
    "gn:name":"Langdonggou Xiatun",
    "gn:population":0,
    "gn:timezone":"Asia/Shanghai",
    "iso:country":"CN",
    "name:zho_x_preferred":[
        "\u72fc\u6d1e\u6c9f\u4e0b\u5c6f"
    ],
    "wof:name":"Langdonggou Xiatun",
    "wof:placetype":"locality"
},
  "geometry": {"coordinates":[127.178,43.5252],"type":"Point"}
}