{
  "type": "Feature",
  "properties": {
    "gn:admin1_code":"16",
    "gn:asciiname":"Shangtongpanling",
    "gn:country_code":"CN",
    "gn:dem":748,
    "gn:feature_class":"P",
    "gn:feature_code":"PPL",
    "gn:name":"Shangtongpanling",
    "gn:population":0,
    "gn:timezone":"Asia/Shanghai",
    "iso:country":"CN",
    "name:zho_x_preferred":[
        "\u4e0a\u94dc\u76d8\u5cad"
    ],
    "wof:name":"Shangtongpanling",
    "wof:placetype":"locality"
},
  "geometry": {"coordinates":[110.857,25.5226],"type":"Point"}
}