{
  "type": "Feature",
  "properties": {
    "gn:admin1_code":"14.0",
    "gn:asciiname":"Jikaomacun",
    "gn:country_code":"CN",
    "gn:dem":4821,
    "gn:feature_class":"P",
    "gn:feature_code":"PPL",
    "gn:name":"Jikaomacun",
    "gn:population":0,
    "gn:timezone":"Asia/Urumqi",
    "iso:country":"CN",
    "name:zho_x_preferred":[
        "\u5409\u8003\u739b\u6751"
    ],
    "wof:name":"Jikaomacun",
    "wof:placetype":"locality"
},
  "geometry": {"coordinates":[91.94002999999999,32.33237],"type":"Point"}
}