{
  "type": "Feature",
  "properties": {
    "gn:admin1_code":"30",
    "gn:asciiname":"Zaoxi",
    "gn:country_code":"CN",
    "gn:dem":482,
    "gn:feature_class":"P",
    "gn:feature_code":"PPL",
    "gn:name":"Zaoxi",
    "gn:population":0,
    "gn:timezone":"Asia/Shanghai",
    "iso:country":"CN",
    "name:zho_x_preferred":[
        "\u71e5\u6eaa"
    ],
    "wof:name":"Zaoxi",
    "wof:placetype":"locality"
},
  "geometry": {"coordinates":[116.32250999999999,23.74291],"type":"Point"}
}