{
  "type": "Feature",
  "properties": {
    "gn:admin1_code":"5.0",
    "gn:asciiname":"Yandajidi",
    "gn:country_code":"CN",
    "gn:dem":418,
    "gn:feature_class":"P",
    "gn:feature_code":"PPL",
    "gn:name":"Yandajidi",
    "gn:population":0,
    "gn:timezone":"Asia/Shanghai",
    "iso:country":"CN",
    "name:und_x_variant":[
        "\u5ef6\u5927\u57fa\u5730"
    ],
    "wof:name":"Yandajidi",
    "wof:placetype":"locality"
},
  "geometry": {"coordinates":[129.46406000000002,43.07841],"type":"Point"}
}