{
  "type": "Feature",
  "properties": {
    "gn:admin1_code":"16.0",
    "gn:asciiname":"Huangtongshu",
    "gn:country_code":"CN",
    "gn:dem":20,
    "gn:feature_class":"P",
    "gn:feature_code":"PPL",
    "gn:name":"Huangtongshu",
    "gn:population":0,
    "gn:timezone":"Asia/Shanghai",
    "iso:country":"CN",
    "name:zho_x_preferred":[
        "\u9ec4\u6850\u6811"
    ],
    "wof:name":"Huangtongshu",
    "wof:placetype":"locality"
},
  "geometry": {"coordinates":[109.643,21.6737],"type":"Point"}
}