{
  "type": "Feature",
  "properties": {
    "gn:admin1_code":"26.0",
    "gn:asciiname":"Shigezhuang",
    "gn:country_code":"CN",
    "gn:dem":1289,
    "gn:feature_class":"P",
    "gn:feature_code":"PPL",
    "gn:name":"Shigezhuang",
    "gn:population":0,
    "gn:timezone":"Asia/Shanghai",
    "iso:country":"CN",
    "name:zho_x_preferred":[
        "\u77f3\u572a\u5e84"
    ],
    "wof:name":"Shigezhuang",
    "wof:placetype":"locality"
},
  "geometry": {"coordinates":[108.6765,36.5348],"type":"Point"}
}