{
  "type": "Feature",
  "properties": {
    "gn:admin1_code":"18.0",
    "gn:asciiname":"Yueliang",
    "gn:country_code":"CN",
    "gn:dem":860,
    "gn:feature_class":"P",
    "gn:feature_code":"PPL",
    "gn:name":"Yueliang",
    "gn:population":0,
    "gn:timezone":"Asia/Shanghai",
    "iso:country":"CN",
    "name:zho_x_preferred":[
        "\u6708\u4eae"
    ],
    "wof:name":"Yueliang",
    "wof:placetype":"locality"
},
  "geometry": {"coordinates":[107.64400000000001,25.5149],"type":"Point"}
}