{
  "type": "Feature",
  "properties": {
    "gn:admin1_code":"4.0",
    "gn:asciiname":"Huayuanli",
    "gn:country_code":"CN",
    "gn:dem":8,
    "gn:feature_class":"P",
    "gn:feature_code":"PPL",
    "gn:name":"Huayuanli",
    "gn:population":0,
    "gn:timezone":"Asia/Shanghai",
    "iso:country":"CN",
    "name:und_x_variant":[
        "\u82b1\u56ed\u91cc"
    ],
    "name:zho_x_preferred":[
        "\u82b1\u56ed\u91cc"
    ],
    "wof:name":"Huayuanli",
    "wof:placetype":"locality"
},
  "geometry": {"coordinates":[120.06635,31.57249],"type":"Point"}
}