{
  "type": "Feature",
  "properties": {
    "gn:admin1_code":"12.0",
    "gn:asciiname":"Lulintang",
    "gn:country_code":"CN",
    "gn:dem":294,
    "gn:feature_class":"P",
    "gn:feature_code":"PPL",
    "gn:name":"Lulintang",
    "gn:population":0,
    "gn:timezone":"Asia/Shanghai",
    "iso:country":"CN",
    "name:zho_x_preferred":[
        "Lulintang"
    ],
    "name:zho_x_variant":[
        "\u82a6\u6797\u5858"
    ],
    "wof:name":"Lulintang",
    "wof:placetype":"locality"
},
  "geometry": {"coordinates":[114.98029,29.67569],"type":"Point"}
}