{
  "type": "Feature",
  "properties": {
    "gn:admin1_code":"8.0",
    "gn:asciiname":"Liujiatun",
    "gn:country_code":"CN",
    "gn:dem":178,
    "gn:feature_class":"P",
    "gn:feature_code":"PPL",
    "gn:name":"Liujiatun",
    "gn:population":0,
    "gn:timezone":"Asia/Shanghai",
    "iso:country":"CN",
    "name:zho_x_preferred":[
        "\u67f3\u5bb6\u5c6f"
    ],
    "wof:name":"Liujiatun",
    "wof:placetype":"locality"
},
  "geometry": {"coordinates":[127.01118999999998,47.08955],"type":"Point"}
}