{
  "type": "Feature",
  "properties": {
    "gn:admin1_code":"11.0",
    "gn:asciiname":"Youzhapo",
    "gn:country_code":"CN",
    "gn:dem":35,
    "gn:feature_class":"P",
    "gn:feature_code":"PPL",
    "gn:name":"Youzhapo",
    "gn:population":0,
    "gn:timezone":"Asia/Shanghai",
    "iso:country":"CN",
    "name:zho_x_preferred":[
        "Youzhapo"
    ],
    "name:zho_x_variant":[
        "\u6cb9\u69a8\u5761"
    ],
    "wof:name":"Youzhapo",
    "wof:placetype":"locality"
},
  "geometry": {"coordinates":[111.93076000000001,29.5293],"type":"Point"}
}