{
  "type": "Feature",
  "properties": {
    "gn:admin1_code":"8.0",
    "gn:asciiname":"Wangshengtun",
    "gn:country_code":"CN",
    "gn:dem":126,
    "gn:feature_class":"P",
    "gn:feature_code":"PPL",
    "gn:name":"Wangshengtun",
    "gn:population":0,
    "gn:timezone":"Asia/Shanghai",
    "iso:country":"CN",
    "name:zho_x_preferred":[
        "\u738b\u751f\u5c6f"
    ],
    "wof:name":"Wangshengtun",
    "wof:placetype":"locality"
},
  "geometry": {"coordinates":[127.01416,45.92059],"type":"Point"}
}