{
  "type": "Feature",
  "properties": {
    "gn:admin1_code":"24.0",
    "gn:asciiname":"Tulougou",
    "gn:country_code":"CN",
    "gn:dem":1270,
    "gn:feature_class":"P",
    "gn:feature_code":"PPL",
    "gn:name":"Tulougou",
    "gn:population":0,
    "gn:timezone":"Asia/Shanghai",
    "iso:country":"CN",
    "name:zho_x_preferred":[
        "\u571f\u697c\u6c9f"
    ],
    "wof:name":"Tulougou",
    "wof:placetype":"locality"
},
  "geometry": {"coordinates":[110.92966,36.23087],"type":"Point"}
}