{
  "type": "Feature",
  "properties": {
    "gn:admin1_code":"8.0",
    "gn:asciiname":"Liweizitun",
    "gn:country_code":"CN",
    "gn:dem":164,
    "gn:feature_class":"P",
    "gn:feature_code":"PPL",
    "gn:name":"Liweizitun",
    "gn:population":0,
    "gn:timezone":"Asia/Shanghai",
    "iso:country":"CN",
    "name:zho_x_preferred":[
        "\u674e\u56f4\u5b50\u5c6f"
    ],
    "wof:name":"Liweizitun",
    "wof:placetype":"locality"
},
  "geometry": {"coordinates":[126.42865999999999,47.23381],"type":"Point"}
}