{
  "type": "Feature",
  "properties": {
    "gn:admin1_code":"2",
    "gn:asciiname":"Yanghou",
    "gn:country_code":"CN",
    "gn:dem":217,
    "gn:feature_class":"P",
    "gn:feature_code":"PPL",
    "gn:name":"Yanghou",
    "gn:population":0,
    "gn:timezone":"Asia/Shanghai",
    "iso:country":"CN",
    "name:und_x_variant":[
        "Juxi",
        "Yanghou"
    ],
    "name:zho_x_preferred":[
        "\u6837\u540e"
    ],
    "wof:name":"Yanghou",
    "wof:placetype":"locality"
},
  "geometry": {"coordinates":[119.79966,28.56947000000001],"type":"Point"}
}