{
  "type": "Feature",
  "properties": {
    "gn:admin1_code":"11.0",
    "gn:asciiname":"Zhumaping",
    "gn:country_code":"CN",
    "gn:dem":493,
    "gn:feature_class":"P",
    "gn:feature_code":"PPL",
    "gn:name":"Zhumaping",
    "gn:population":0,
    "gn:timezone":"Asia/Shanghai",
    "iso:country":"CN",
    "name:zho_x_preferred":[
        "\u7af9\u9ebb\u576a"
    ],
    "wof:name":"Zhumaping",
    "wof:placetype":"locality"
},
  "geometry": {"coordinates":[110.00261999999999,26.53499],"type":"Point"}
}