{
  "type": "Feature",
  "properties": {
    "gn:admin1_code":"30.0",
    "gn:asciiname":"Tianwei",
    "gn:country_code":"CN",
    "gn:dem":729,
    "gn:feature_class":"P",
    "gn:feature_code":"PPL",
    "gn:name":"Tianwei",
    "gn:population":0,
    "gn:timezone":"Asia/Shanghai",
    "iso:country":"CN",
    "name:zho_x_preferred":[
        "\u7530\u5c3e"
    ],
    "wof:name":"Tianwei",
    "wof:placetype":"locality"
},
  "geometry": {"coordinates":[113.89928,24.40118],"type":"Point"}
}