{
  "type": "Feature",
  "properties": {
    "gn:admin1_code":"03",
    "gn:asciiname":"Guxian",
    "gn:country_code":"CN",
    "gn:dem":98,
    "gn:feature_class":"P",
    "gn:feature_code":"PPLA4",
    "gn:name":"Guxian",
    "gn:population":0,
    "gn:timezone":"Asia/Shanghai",
    "iso:country":"CN",
    "name:und_x_variant":[
        "Ku-hsien",
        "Guxian",
        "\u53e4\u53bf",
        "Guxian Zhen",
        "\u53e4\u53bf\u9547"
    ],
    "wof:name":"Guxian",
    "wof:placetype":"locality"
},
  "geometry": {"coordinates":[115.51543999999998,27.15357],"type":"Point"}
}