{
  "type": "Feature",
  "properties": {
    "gn:admin1_code":"30.0",
    "gn:asciiname":"Lizhiyuan",
    "gn:country_code":"CN",
    "gn:dem":82,
    "gn:feature_class":"P",
    "gn:feature_code":"PPL",
    "gn:name":"Lizhiyuan",
    "gn:population":0,
    "gn:timezone":"Asia/Shanghai",
    "iso:country":"CN",
    "name:zho_x_preferred":[
        "\u8354\u679d\u56ed"
    ],
    "wof:name":"Lizhiyuan",
    "wof:placetype":"locality"
},
  "geometry": {"coordinates":[111.68651,22.60845],"type":"Point"}
}