{
  "type": "Feature",
  "properties": {
    "gn:admin1_code":"26.0",
    "gn:asciiname":"Shenyan",
    "gn:country_code":"CN",
    "gn:dem":1020,
    "gn:feature_class":"P",
    "gn:feature_code":"PPL",
    "gn:name":"Shenyan",
    "gn:population":0,
    "gn:timezone":"Asia/Shanghai",
    "iso:country":"CN",
    "name:zho_x_preferred":[
        "\u6df1\u5895"
    ],
    "wof:name":"Shenyan",
    "wof:placetype":"locality"
},
  "geometry": {"coordinates":[110.95399999999999,39.04188],"type":"Point"}
}