{
  "type": "Feature",
  "properties": {
    "gn:admin1_code":"19.0",
    "gn:asciiname":"Houdalingdi",
    "gn:country_code":"CN",
    "gn:dem":61,
    "gn:feature_class":"P",
    "gn:feature_code":"PPL",
    "gn:name":"Houdalingdi",
    "gn:population":0,
    "gn:timezone":"Asia/Shanghai",
    "iso:country":"CN",
    "name:zho_x_preferred":[
        "\u540e\u5927\u5cad\u5e95"
    ],
    "wof:name":"Houdalingdi",
    "wof:placetype":"locality"
},
  "geometry": {"coordinates":[121.845,39.2624],"type":"Point"}
}