{
  "type": "Feature",
  "properties": {
    "gn:admin1_code":"13.0",
    "gn:asciiname":"Xiamaleleke",
    "gn:country_code":"CN",
    "gn:dem":2827,
    "gn:feature_class":"P",
    "gn:feature_code":"PPL",
    "gn:name":"Xiamaleleke",
    "gn:population":0,
    "gn:timezone":"Asia/Urumqi",
    "iso:country":"CN",
    "name:zho_x_preferred":[
        "\u590f\u739b\u52d2\u52d2\u514b"
    ],
    "wof:name":"Xiamaleleke",
    "wof:placetype":"locality"
},
  "geometry": {"coordinates":[82.83963,36.53164],"type":"Point"}
}