{
  "type": "Feature",
  "properties": {
    "gn:admin1_code":"25",
    "gn:asciiname":"Houyuwo",
    "gn:country_code":"CN",
    "gn:dem":61,
    "gn:feature_class":"P",
    "gn:feature_code":"PPL",
    "gn:name":"Houyuwo",
    "gn:population":0,
    "gn:timezone":"Asia/Shanghai",
    "iso:country":"CN",
    "name:zho_x_preferred":[
        "\u540e\u6e14\u6c83"
    ],
    "wof:name":"Houyuwo",
    "wof:placetype":"locality"
},
  "geometry": {"coordinates":[115.102,35.2642],"type":"Point"}
}