{
  "type": "Feature",
  "properties": {
    "gn:admin1_code":"18.0",
    "gn:asciiname":"Anghao",
    "gn:country_code":"CN",
    "gn:dem":723,
    "gn:feature_class":"P",
    "gn:feature_code":"PPL",
    "gn:name":"Anghao",
    "gn:population":0,
    "gn:timezone":"Asia/Shanghai",
    "iso:country":"CN",
    "name:zho_x_preferred":[
        "\u6602\u8c6a"
    ],
    "wof:name":"Anghao",
    "wof:placetype":"locality"
},
  "geometry": {"coordinates":[108.04000000000001,25.6541],"type":"Point"}
}