{
  "type": "Feature",
  "properties": {
    "gn:admin1_code":"9.0",
    "gn:asciiname":"Xiedian",
    "gn:country_code":"CN",
    "gn:dem":117,
    "gn:feature_class":"P",
    "gn:feature_code":"PPL",
    "gn:name":"Xiedian",
    "gn:population":0,
    "gn:timezone":"Asia/Shanghai",
    "iso:country":"CN",
    "name:zho_x_preferred":[
        "\u90aa\u5e97"
    ],
    "wof:name":"Xiedian",
    "wof:placetype":"locality"
},
  "geometry": {"coordinates":[113.25776,33.54499000000001],"type":"Point"}
}