{
  "type": "Feature",
  "properties": {
    "gn:admin1_code":"26.0",
    "gn:asciiname":"Longwangpingcun",
    "gn:country_code":"CN",
    "gn:dem":814,
    "gn:feature_class":"P",
    "gn:feature_code":"PPL",
    "gn:name":"Longwangpingcun",
    "gn:population":0,
    "gn:timezone":"Asia/Shanghai",
    "iso:country":"CN",
    "name:zho_x_preferred":[
        "\u9f99\u738b\u576a\u6751"
    ],
    "wof:name":"Longwangpingcun",
    "wof:placetype":"locality"
},
  "geometry": {"coordinates":[108.25013,33.4655],"type":"Point"}
}