{
  "type": "Feature",
  "properties": {
    "gn:admin1_code":"29.0",
    "gn:asciiname":"Dumeng",
    "gn:country_code":"CN",
    "gn:dem":1726,
    "gn:feature_class":"P",
    "gn:feature_code":"PPL",
    "gn:name":"Dumeng",
    "gn:population":0,
    "gn:timezone":"Asia/Shanghai",
    "iso:country":"CN",
    "name:zho_x_preferred":[
        "\u675c\u5b5f"
    ],
    "wof:name":"Dumeng",
    "wof:placetype":"locality"
},
  "geometry": {"coordinates":[104.146,23.2482],"type":"Point"}
}