{
  "type": "Feature",
  "properties": {
    "gn:admin1_code":"12.0",
    "gn:asciiname":"Lujialing",
    "gn:country_code":"CN",
    "gn:dem":595,
    "gn:feature_class":"P",
    "gn:feature_code":"PPL",
    "gn:name":"L\u00fcjialing",
    "gn:population":0,
    "gn:timezone":"Asia/Shanghai",
    "iso:country":"CN",
    "name:und_x_variant":[
        "L\u00fcjialing"
    ],
    "name:zho_x_preferred":[
        "\u5415\u5bb6\u5cad"
    ],
    "wof:name":"Lujialing",
    "wof:placetype":"locality"
},
  "geometry": {"coordinates":[110.06426,32.93785],"type":"Point"}
}