{
  "type": "Feature",
  "properties": {
    "gn:admin1_code":"25.0",
    "gn:asciiname":"Beishengjiacun",
    "gn:country_code":"CN",
    "gn:dem":90,
    "gn:feature_class":"P",
    "gn:feature_code":"PPL",
    "gn:name":"Beishengjiacun",
    "gn:population":0,
    "gn:timezone":"Asia/Shanghai",
    "iso:country":"CN",
    "name:zho_x_preferred":[
        "\u5317\u76db\u5bb6\u6751"
    ],
    "wof:name":"Beishengjiacun",
    "wof:placetype":"locality"
},
  "geometry": {"coordinates":[119.90648,36.9099],"type":"Point"}
}