{
  "type": "Feature",
  "properties": {
    "gn:admin1_code":"9.0",
    "gn:asciiname":"Xiaodianwang",
    "gn:country_code":"CN",
    "gn:dem":73,
    "gn:feature_class":"P",
    "gn:feature_code":"PPL",
    "gn:name":"Xiaodianwang",
    "gn:population":0,
    "gn:timezone":"Asia/Shanghai",
    "iso:country":"CN",
    "name:zho_x_preferred":[
        "\u5c0f\u5e97\u738b"
    ],
    "wof:name":"Xiaodianwang",
    "wof:placetype":"locality"
},
  "geometry": {"coordinates":[114.27471,34.63325],"type":"Point"}
}