{
  "type": "Feature",
  "properties": {
    "gn:admin1_code":"7",
    "gn:asciiname":"Baiyangshan",
    "gn:country_code":"CN",
    "gn:dem":534,
    "gn:feature_class":"P",
    "gn:feature_code":"PPL",
    "gn:name":"Baiyangshan",
    "gn:population":0,
    "gn:timezone":"Asia/Shanghai",
    "iso:country":"CN",
    "name:zho_x_preferred":[
        "\u767d\u6d0b\u5c71"
    ],
    "wof:name":"Baiyangshan",
    "wof:placetype":"locality"
},
  "geometry": {"coordinates":[118.32417,25.86861],"type":"Point"}
}