{
  "type": "Feature",
  "properties": {
    "gn:admin1_code":"32.0",
    "gn:asciiname":"Xiangyaoguan",
    "gn:country_code":"CN",
    "gn:dem":1292,
    "gn:feature_class":"P",
    "gn:feature_code":"PPL",
    "gn:name":"Xiangyaoguan",
    "gn:population":0,
    "gn:timezone":"Asia/Shanghai",
    "iso:country":"CN",
    "name:zho_x_preferred":[
        "\u5411\u836f\u8d2f"
    ],
    "wof:name":"Xiangyaoguan",
    "wof:placetype":"locality"
},
  "geometry": {"coordinates":[107.55094,32.27974],"type":"Point"}
}