{
  "type": "Feature",
  "properties": {
    "gn:admin1_code":"32.0",
    "gn:asciiname":"Xinmatou",
    "gn:country_code":"CN",
    "gn:dem":267,
    "gn:feature_class":"P",
    "gn:feature_code":"PPL",
    "gn:name":"Xinmatou",
    "gn:population":0,
    "gn:timezone":"Asia/Shanghai",
    "iso:country":"CN",
    "name:zho_x_preferred":[
        "\u65b0\u9a6c\u5934"
    ],
    "name:zho_x_variant":[
        "\u65b0\u7801\u5934"
    ],
    "wof:name":"Xinmatou",
    "wof:placetype":"locality"
},
  "geometry": {"coordinates":[104.91200000000001,28.7752],"type":"Point"}
}