{
  "type": "Feature",
  "properties": {
    "gn:admin1_code":"26.0",
    "gn:asciiname":"Zaowanzi",
    "gn:country_code":"CN",
    "gn:dem":1248,
    "gn:feature_class":"P",
    "gn:feature_code":"PPL",
    "gn:name":"Zaowanzi",
    "gn:population":0,
    "gn:timezone":"Asia/Shanghai",
    "iso:country":"CN",
    "name:zho_x_preferred":[
        "\u67a3\u6e7e\u5b50"
    ],
    "wof:name":"Zaowanzi",
    "wof:placetype":"locality"
},
  "geometry": {"coordinates":[108.46630999999999,36.66314000000001],"type":"Point"}
}