{
  "type": "Feature",
  "properties": {
    "gn:admin1_code":"14.0",
    "gn:asciiname":"Jipu",
    "gn:country_code":"CN",
    "gn:dem":4241,
    "gn:feature_class":"P",
    "gn:feature_code":"PPL",
    "gn:name":"Jipu",
    "gn:population":0,
    "gn:timezone":"Asia/Urumqi",
    "iso:country":"CN",
    "name:zho_x_preferred":[
        "\u57fa\u6d66"
    ],
    "wof:name":"Jipu",
    "wof:placetype":"locality"
},
  "geometry": {"coordinates":[92.82098999999999,28.59291],"type":"Point"}
}