{
  "type": "Feature",
  "properties": {
    "gn:admin1_code":"32.0",
    "gn:asciiname":"Baitukan",
    "gn:country_code":"CN",
    "gn:dem":1502,
    "gn:feature_class":"P",
    "gn:feature_code":"PPL",
    "gn:name":"Baitukan",
    "gn:population":0,
    "gn:timezone":"Asia/Shanghai",
    "iso:country":"CN",
    "name:zho_x_preferred":[
        "\u767d\u571f\u574e"
    ],
    "wof:name":"Baitukan",
    "wof:placetype":"locality"
},
  "geometry": {"coordinates":[102.1891,27.83311],"type":"Point"}
}