{
  "type": "Feature",
  "properties": {
    "gn:admin1_code":"05",
    "gn:asciiname":"Daxicha",
    "gn:cc2":"CN",
    "gn:country_code":"CN",
    "gn:dem":527,
    "gn:feature_class":"P",
    "gn:feature_code":"PPL",
    "gn:name":"Daxicha",
    "gn:population":0,
    "gn:timezone":"Asia/Shanghai",
    "iso:country":"CN",
    "name:und_x_variant":[
        "Ta-hsi-ch\u2019a-t\u2019un",
        "Daxicha",
        "\u5927\u897f\u5c94"
    ],
    "wof:name":"Daxicha",
    "wof:placetype":"locality"
},
  "geometry": {"coordinates":[126.15611,41.61194],"type":"Point"}
}