{
  "type": "Feature",
  "properties": {
    "gn:admin1_code":"32.0",
    "gn:asciiname":"Xiaqiuguo",
    "gn:country_code":"CN",
    "gn:dem":3980,
    "gn:feature_class":"P",
    "gn:feature_code":"PPL",
    "gn:name":"Xiaqiuguo",
    "gn:population":0,
    "gn:timezone":"Asia/Shanghai",
    "iso:country":"CN",
    "name:zho_x_preferred":[
        "\u4e0b\u90b1\u679c"
    ],
    "wof:name":"Xiaqiuguo",
    "wof:placetype":"locality"
},
  "geometry": {"coordinates":[100.292,32.2592],"type":"Point"}
}