{
  "type": "Feature",
  "properties": {
    "gn:admin1_code":"10",
    "gn:asciiname":"Houcheng",
    "gn:country_code":"CN",
    "gn:dem":45,
    "gn:feature_class":"P",
    "gn:feature_code":"PPL",
    "gn:name":"Houcheng",
    "gn:population":0,
    "gn:timezone":"Asia/Shanghai",
    "iso:country":"CN",
    "name:zho_x_preferred":[
        "\u5019\u57ce"
    ],
    "wof:name":"Houcheng",
    "wof:placetype":"locality"
},
  "geometry": {"coordinates":[115.102,38.101],"type":"Point"}
}