{
  "type": "Feature",
  "properties": {
    "gn:admin1_code":"29",
    "gn:asciiname":"Asiyi",
    "gn:country_code":"CN",
    "gn:dem":1889,
    "gn:feature_class":"P",
    "gn:feature_code":"PPL",
    "gn:name":"Asiyi",
    "gn:population":0,
    "gn:timezone":"Asia/Shanghai",
    "iso:country":"CN",
    "name:zho_x_preferred":[
        "\u963f\u601d\u9091"
    ],
    "wof:name":"Asiyi",
    "wof:placetype":"locality"
},
  "geometry": {"coordinates":[102.492,24.8698],"type":"Point"}
}