{
  "type": "Feature",
  "properties": {
    "gn:admin1_code":"4",
    "gn:asciiname":"Tangjiabang",
    "gn:country_code":"CN",
    "gn:dem":4,
    "gn:feature_class":"P",
    "gn:feature_code":"PPL",
    "gn:name":"Tangjiabang",
    "gn:population":0,
    "gn:timezone":"Asia/Shanghai",
    "iso:country":"CN",
    "name:und_x_variant":[
        "\u6c64\u5bb6\u6d5c",
        "Di Tang"
    ],
    "wof:name":"Tangjiabang",
    "wof:placetype":"locality"
},
  "geometry": {"coordinates":[120.65579,30.98231],"type":"Point"}
}