{
  "type": "Feature",
  "properties": {
    "gn:admin1_code":"29.0",
    "gn:asciiname":"Naruan",
    "gn:country_code":"CN",
    "gn:dem":1439,
    "gn:feature_class":"P",
    "gn:feature_code":"PPL",
    "gn:name":"Naruan",
    "gn:population":0,
    "gn:timezone":"Asia/Shanghai",
    "iso:country":"CN",
    "name:zho_x_preferred":[
        "\u90a3\u8f6f"
    ],
    "wof:name":"Naruan",
    "wof:placetype":"locality"
},
  "geometry": {"coordinates":[101.51300000000001,26.3653],"type":"Point"}
}