{
  "type": "Feature",
  "properties": {
    "gn:admin1_code":"25.0",
    "gn:asciiname":"Guojiaquan",
    "gn:country_code":"CN",
    "gn:dem":72,
    "gn:feature_class":"P",
    "gn:feature_code":"PPL",
    "gn:name":"Guojiaquan",
    "gn:population":0,
    "gn:timezone":"Asia/Shanghai",
    "iso:country":"CN",
    "name:zho_x_preferred":[
        "\u679c\u4f73\u5708"
    ],
    "wof:name":"Guojiaquan",
    "wof:placetype":"locality"
},
  "geometry": {"coordinates":[120.55302,36.93664],"type":"Point"}
}