{
  "type": "Feature",
  "properties": {
    "gn:admin1_code":"26.0",
    "gn:asciiname":"Yaojiagou",
    "gn:country_code":"CN",
    "gn:dem":857,
    "gn:feature_class":"P",
    "gn:feature_code":"PPL",
    "gn:name":"Yaojiagou",
    "gn:population":0,
    "gn:timezone":"Asia/Shanghai",
    "iso:country":"CN",
    "name:und_x_variant":[
        "\u59da\u5bb6\u6c9f"
    ],
    "wof:name":"Yaojiagou",
    "wof:placetype":"locality"
},
  "geometry": {"coordinates":[107.00801,33.51019],"type":"Point"}
}