{
  "type": "Feature",
  "properties": {
    "gn:admin1_code":"29",
    "gn:asciiname":"Daxi",
    "gn:country_code":"CN",
    "gn:dem":2250,
    "gn:feature_class":"P",
    "gn:feature_code":"PPL",
    "gn:name":"Daxi",
    "gn:population":0,
    "gn:timezone":"Asia/Shanghai",
    "iso:country":"CN",
    "name:ceb_x_preferred":[
        "Daxi"
    ],
    "name:deu_x_preferred":[
        "Daxi"
    ],
    "name:swe_x_preferred":[
        "Daxi"
    ],
    "name:zho_x_preferred":[
        "\u5927\u897f"
    ],
    "wof:name":"Daxi",
    "wof:placetype":"locality"
},
  "geometry": {"coordinates":[101.974,24.1816],"type":"Point"}
}