{
  "type": "Feature",
  "properties": {
    "gn:admin1_code":"9.0",
    "gn:asciiname":"Baizhi",
    "gn:country_code":"CN",
    "gn:dem":71,
    "gn:feature_class":"P",
    "gn:feature_code":"PPL",
    "gn:name":"Baizhi",
    "gn:population":0,
    "gn:timezone":"Asia/Shanghai",
    "iso:country":"CN",
    "name:zho_x_preferred":[
        "\u767d\u96c9"
    ],
    "wof:name":"Baizhi",
    "wof:placetype":"locality"
},
  "geometry": {"coordinates":[113.98547000000001,34.0818],"type":"Point"}
}