{
  "type": "Feature",
  "properties": {
    "gn:admin1_code":"32.0",
    "gn:asciiname":"Xiebo",
    "gn:country_code":"CN",
    "gn:dem":3784,
    "gn:feature_class":"P",
    "gn:feature_code":"PPL",
    "gn:name":"Xiebo",
    "gn:population":0,
    "gn:timezone":"Asia/Shanghai",
    "iso:country":"CN",
    "name:zho_x_preferred":[
        "\u534f\u6ce2"
    ],
    "wof:name":"Xiebo",
    "wof:placetype":"locality"
},
  "geometry": {"coordinates":[100.526,29.0839],"type":"Point"}
}