{
  "type": "Feature",
  "properties": {
    "gn:admin1_code":"29.0",
    "gn:asciiname":"Fangmashao",
    "gn:country_code":"CN",
    "gn:dem":2230,
    "gn:feature_class":"P",
    "gn:feature_code":"PPL",
    "gn:name":"Fangmashao",
    "gn:population":0,
    "gn:timezone":"Asia/Shanghai",
    "iso:country":"CN",
    "name:zho_x_preferred":[
        "\u653e\u9a6c\u54e8"
    ],
    "wof:name":"Fangmashao",
    "wof:placetype":"locality"
},
  "geometry": {"coordinates":[102.846,25.769],"type":"Point"}
}