{
  "type": "Feature",
  "properties": {
    "gn:admin1_code":"4.0",
    "gn:asciiname":"Jizhuang",
    "gn:country_code":"CN",
    "gn:dem":9,
    "gn:feature_class":"P",
    "gn:feature_code":"PPL",
    "gn:name":"Jizhuang",
    "gn:population":0,
    "gn:timezone":"Asia/Shanghai",
    "iso:country":"CN",
    "name:zho_x_preferred":[
        "Jizhuang"
    ],
    "name:zho_x_variant":[
        "\u5d47\u5e84"
    ],
    "wof:name":"Jizhuang",
    "wof:placetype":"locality"
},
  "geometry": {"coordinates":[119.06099,33.84622],"type":"Point"}
}