{
  "type": "Feature",
  "properties": {
    "gn:admin1_code":"14.0",
    "gn:asciiname":"Galinggang",
    "gn:country_code":"CN",
    "gn:dem":3668,
    "gn:feature_class":"P",
    "gn:feature_code":"PPLF",
    "gn:name":"Galinggang",
    "gn:population":0,
    "gn:timezone":"Asia/Urumqi",
    "iso:country":"CN",
    "name:bod_x_preferred":[
        "Galinggang"
    ],
    "name:zho_x_preferred":[
        "Galingang"
    ],
    "name:zho_x_variant":[
        "\u560e\u6797\u5c97"
    ],
    "wof:name":"Galinggang",
    "wof:placetype":"locality"
},
  "geometry": {"coordinates":[88.905,27.405],"type":"Point"}
}