{
  "type": "Feature",
  "properties": {
    "gn:admin1_code":"15.0",
    "gn:asciiname":"Ganxiang",
    "gn:country_code":"CN",
    "gn:dem":2607,
    "gn:feature_class":"P",
    "gn:feature_code":"PPL",
    "gn:name":"Ganxiang",
    "gn:population":0,
    "gn:timezone":"Asia/Shanghai",
    "iso:country":"CN",
    "name:und_x_variant":[
        "\u7518\u5411"
    ],
    "wof:name":"Ganxiang",
    "wof:placetype":"locality"
},
  "geometry": {"coordinates":[103.81107,34.03347],"type":"Point"}
}