{
  "type": "Feature",
  "properties": {
    "gn:admin1_code":"22",
    "gn:asciiname":"Shahe",
    "gn:country_code":"CN",
    "gn:dem":44,
    "gn:feature_class":"P",
    "gn:feature_code":"PPLA4",
    "gn:name":"Shahe",
    "gn:population":0,
    "gn:timezone":"Asia/Shanghai",
    "iso:country":"CN",
    "name:ceb_x_preferred":[
        "Shahe"
    ],
    "name:deu_x_preferred":[
        "Shahe"
    ],
    "name:rus_x_preferred":[
        "\u0428\u0430\u0445\u044d"
    ],
    "name:swe_x_preferred":[
        "Shahe"
    ],
    "name:und_x_variant":[
        "Sha-ho",
        "Shahe Zhen"
    ],
    "name:zho_x_preferred":[
        "\u6c99\u6cb3"
    ],
    "name:zho_x_variant":[
        "\u6c99\u6cb3\u9547"
    ],
    "wof:name":"Shahe",
    "wof:placetype":"locality"
},
  "geometry": {"coordinates":[116.26076,40.12324],"type":"Point"}
}