{
  "type": "Feature",
  "properties": {
    "gn:admin1_code":"32.0",
    "gn:asciiname":"Tianyuan",
    "gn:country_code":"CN",
    "gn:dem":320,
    "gn:feature_class":"P",
    "gn:feature_code":"PPL",
    "gn:name":"Tianyuan",
    "gn:population":0,
    "gn:timezone":"Asia/Shanghai",
    "iso:country":"CN",
    "name:deu_x_preferred":[
        "Tianyuan"
    ],
    "name:fra_x_preferred":[
        "Tianyuan"
    ],
    "name:zho_x_preferred":[
        "\u7530\u56ed"
    ],
    "wof:name":"Tianyuan",
    "wof:placetype":"locality"
},
  "geometry": {"coordinates":[105.55,30.3534],"type":"Point"}
}