{
  "type": "Feature",
  "properties": {
    "gn:admin1_code":"9.0",
    "gn:asciiname":"Wawuzhao",
    "gn:country_code":"CN",
    "gn:dem":92,
    "gn:feature_class":"P",
    "gn:feature_code":"PPL",
    "gn:name":"Wawuzhao",
    "gn:population":0,
    "gn:timezone":"Asia/Shanghai",
    "iso:country":"CN",
    "name:und_x_variant":[
        "\u74e6\u5c4b\u8d75"
    ],
    "name:zho_x_preferred":[
        "\u74e6\u5c4b\u8d75"
    ],
    "wof:name":"Wawuzhao",
    "wof:placetype":"locality"
},
  "geometry": {"coordinates":[113.9251,33.26237],"type":"Point"}
}