{
  "type": "Feature",
  "properties": {
    "gn:admin1_code":"3.0",
    "gn:asciiname":"Nan'an",
    "gn:country_code":"CN",
    "gn:dem":44,
    "gn:feature_class":"P",
    "gn:feature_code":"PPL",
    "gn:name":"Nan\u2019an",
    "gn:population":0,
    "gn:timezone":"Asia/Shanghai",
    "iso:country":"CN",
    "name:und_x_variant":[
        "Nan\u2019an",
        "\u5357\u5cb8"
    ],
    "wof:name":"Nan'an",
    "wof:placetype":"locality"
},
  "geometry": {"coordinates":[115.73217,27.99736],"type":"Point"}
}