{
  "type": "Feature",
  "properties": {
    "gn:admin1_code":"20.0",
    "gn:asciiname":"Bayanburide Gacha",
    "gn:country_code":"CN",
    "gn:dem":598,
    "gn:feature_class":"P",
    "gn:feature_code":"PPL",
    "gn:name":"Bayanburide Gacha",
    "gn:population":0,
    "gn:timezone":"Asia/Shanghai",
    "iso:country":"CN",
    "name:zho_x_preferred":[
        "\u5df4\u5f66\u5e03\u65e5\u5fb7\u560e\u67e5"
    ],
    "wof:name":"Bayanburide Gacha",
    "wof:placetype":"locality"
},
  "geometry": {"coordinates":[119.31892000000001,49.19895],"type":"Point"}
}