{
  "type": "Feature",
  "properties": {
    "gn:admin1_code":"2.0",
    "gn:asciiname":"Shenshan'ao",
    "gn:country_code":"CN",
    "gn:dem":40,
    "gn:feature_class":"P",
    "gn:feature_code":"PPL",
    "gn:name":"Shenshan\u2019ao",
    "gn:population":0,
    "gn:timezone":"Asia/Shanghai",
    "iso:country":"CN",
    "name:und_x_variant":[
        "Shenshan\u2019ao"
    ],
    "name:zho_x_preferred":[
        "\u6c88\u5c71\u5c99"
    ],
    "wof:name":"Shenshan'ao",
    "wof:placetype":"locality"
},
  "geometry": {"coordinates":[121.79593,29.47452],"type":"Point"}
}