{
  "type": "Feature",
  "properties": {
    "gn:admin1_code":"4.0",
    "gn:asciiname":"Weixingzhuang",
    "gn:country_code":"CN",
    "gn:dem":4,
    "gn:feature_class":"P",
    "gn:feature_code":"PPL",
    "gn:name":"Weixingzhuang",
    "gn:population":0,
    "gn:timezone":"Asia/Shanghai",
    "iso:country":"CN",
    "name:zho_x_preferred":[
        "\u536b\u661f\u5e84"
    ],
    "wof:name":"Weixingzhuang",
    "wof:placetype":"locality"
},
  "geometry": {"coordinates":[118.928,34.286],"type":"Point"}
}