{
  "type": "Feature",
  "properties": {
    "gn:admin1_code":"10.0",
    "gn:asciiname":"Dabaizhong",
    "gn:country_code":"CN",
    "gn:dem":6,
    "gn:feature_class":"P",
    "gn:feature_code":"PPL",
    "gn:name":"Dabaizhong",
    "gn:population":0,
    "gn:timezone":"Asia/Shanghai",
    "iso:country":"CN",
    "name:zho_x_preferred":[
        "\u5927\u767d\u51a2"
    ],
    "wof:name":"Dabaizhong",
    "wof:placetype":"locality"
},
  "geometry": {"coordinates":[117.114,38.3093],"type":"Point"}
}