{
  "type": "Feature",
  "properties": {
    "gn:admin1_code":"25",
    "gn:asciiname":"Huihe",
    "gn:cc2":"CN",
    "gn:country_code":"CN",
    "gn:dem":22,
    "gn:feature_class":"P",
    "gn:feature_code":"PPL",
    "gn:name":"Huihe",
    "gn:population":0,
    "gn:timezone":"Asia/Shanghai",
    "iso:country":"CN",
    "name:ceb_x_preferred":[
        "Huihe"
    ],
    "name:swe_x_preferred":[
        "Huihe"
    ],
    "name:und_x_variant":[
        "Hui-ho-chieh",
        "Hui-ho-chen",
        "Huiho",
        "Huihe"
    ],
    "wof:name":"Huihe",
    "wof:placetype":"locality"
},
  "geometry": {"coordinates":[117.09999999999999,36.93333],"type":"Point"}
}