{
  "type": "Feature",
  "properties": {
    "gn:admin1_code":"32.0",
    "gn:asciiname":"Yanjia Yuanzi",
    "gn:country_code":"CN",
    "gn:dem":1230,
    "gn:feature_class":"P",
    "gn:feature_code":"PPL",
    "gn:name":"Yanjia Yuanzi",
    "gn:population":0,
    "gn:timezone":"Asia/Shanghai",
    "iso:country":"CN",
    "name:zho_x_preferred":[
        "\u4e25\u5bb6\u9662\u5b50"
    ],
    "wof:name":"Yanjia Yuanzi",
    "wof:placetype":"locality"
},
  "geometry": {"coordinates":[104.58219,32.08072],"type":"Point"}
}