{
  "type": "Feature",
  "properties": {
    "gn:country":"CN",
    "gn:fcode":"ADM3",
    "gn:pop":0,
    "iso:country":"CN",
    "name:unk_x_variant":[
        "Lung-ch\u2019ang Hsien"
    ],
    "name:zho_x_preferred":[
        "\u9686\u660c\u53bf"
    ],
    "name:zho_x_variant":[
        "\u9686\u660c"
    ],
    "qs:name":"Longchang Xian",
    "qs:photos_9r":0,
    "qs:photos_sr":0,
    "qs:pop_sr":"0",
    "wd:wordcount":211,
    "wof:name":"Longchang Xian",
    "wof:placetype":"localadmin",
    "wof:population":0
},
  "geometry": {"coordinates":[105.24607,29.37615],"type":"Point"}
}