{
  "type": "Feature",
  "properties": {
    "gn:country":"CN",
    "gn:fcode":"ADM3",
    "gn:population":0,
    "iso:country":"CN",
    "name:ceb_x_preferred":[
        "Longchang Xian"
    ],
    "name:deu_x_preferred":[
        "Longchang"
    ],
    "name:eng_x_preferred":[
        "Longchang County"
    ],
    "name:gan_x_preferred":[
        "\u9686\u660c\u5e02"
    ],
    "name:ita_x_preferred":[
        "Longchang"
    ],
    "name:jpn_x_preferred":[
        "\u9686\u660c\u5e02"
    ],
    "name:kor_x_preferred":[
        "\ub8fd\ucc3d\uc2dc"
    ],
    "name:nan_x_preferred":[
        "Li\u00f4ng-chhiong-chh\u012b"
    ],
    "name:nld_x_preferred":[
        "Longchang"
    ],
    "name:nob_x_preferred":[
        "Longchang"
    ],
    "name:rus_x_preferred":[
        "\u041b\u0443\u043d\u0447\u0430\u043d"
    ],
    "name:swe_x_preferred":[
        "Longchang"
    ],
    "name:und_x_variant":[
        "Lung-ch\u2019ang Hsien"
    ],
    "name:vie_x_preferred":[
        "Long X\u01b0\u01a1ng"
    ],
    "name:wuu_x_preferred":[
        "\u9686\u660c\u5e02"
    ],
    "name:yue_x_preferred":[
        "\u9686\u660c"
    ],
    "name:zho_x_preferred":[
        "\u9686\u660c\u53bf"
    ],
    "name:zho_x_variant":[
        "\u9686\u660c",
        "\u9686\u660c\u5e02"
    ],
    "qs:name":"Longchang Xian",
    "qs:photos_9r":0,
    "qs:photos_sr":0,
    "qs:pop_sr":"0",
    "wd:wordcount":211,
    "wof:name":"Longchang Xian",
    "wof:placetype":"localadmin",
    "wof:population":0
},
  "geometry": {"coordinates":[105.24607,29.37615],"type":"Point"}
}