{
  "type": "Feature",
  "properties": {
    "gn:admin1_code":"9.0",
    "gn:asciiname":"Nanxun",
    "gn:country_code":"CN",
    "gn:dem":130,
    "gn:feature_class":"P",
    "gn:feature_code":"PPL",
    "gn:name":"Nanxun",
    "gn:population":0,
    "gn:timezone":"Asia/Shanghai",
    "iso:country":"CN",
    "name:zho_x_preferred":[
        "\u5357\u5bfb"
    ],
    "wof:name":"Nanxun",
    "wof:placetype":"locality"
},
  "geometry": {"coordinates":[112.79732,35.10111],"type":"Point"}
}