{
  "type": "Feature",
  "properties": {
    "gn:admin1_code":"16.0",
    "gn:asciiname":"Qing'an",
    "gn:country_code":"CN",
    "gn:dem":489,
    "gn:feature_class":"P",
    "gn:feature_code":"PPL",
    "gn:name":"Qing\u2019an",
    "gn:population":0,
    "gn:timezone":"Asia/Shanghai",
    "iso:country":"CN",
    "name:und_x_variant":[
        "Qing\u2019an"
    ],
    "name:zho_x_preferred":[
        "\u5e86\u5b89"
    ],
    "wof:name":"Qing'an",
    "wof:placetype":"locality"
},
  "geometry": {"coordinates":[108.527,24.9298],"type":"Point"}
}