{
  "type": "Feature",
  "properties": {
    "gn:admin1_code":"30.0",
    "gn:asciiname":"Changlingtou",
    "gn:country_code":"CN",
    "gn:dem":600,
    "gn:feature_class":"P",
    "gn:feature_code":"PPL",
    "gn:name":"Changlingtou",
    "gn:population":0,
    "gn:timezone":"Asia/Shanghai",
    "iso:country":"CN",
    "name:zho_x_preferred":[
        "Changlingtou"
    ],
    "name:zho_x_variant":[
        "\u957f\u5cad\u5934"
    ],
    "wof:name":"Changlingtou",
    "wof:placetype":"locality"
},
  "geometry": {"coordinates":[113.21547,24.993],"type":"Point"}
}