{
  "type": "Feature",
  "properties": {
    "gn:admin1_code":"14.0",
    "gn:asciiname":"Baiba",
    "gn:country_code":"CN",
    "gn:dem":4309,
    "gn:feature_class":"P",
    "gn:feature_code":"PPL",
    "gn:name":"Baiba",
    "gn:population":0,
    "gn:timezone":"Asia/Urumqi",
    "iso:country":"CN",
    "name:zho_x_preferred":[
        "\u767d\u575d"
    ],
    "wof:name":"Baiba",
    "wof:placetype":"locality"
},
  "geometry": {"coordinates":[87.1734,28.6297],"type":"Point"}
}