{
  "type": "Feature",
  "properties": {
    "gn:admin1_code":"10.0",
    "gn:asciiname":"Huiyaozi",
    "gn:country_code":"CN",
    "gn:dem":679,
    "gn:feature_class":"P",
    "gn:feature_code":"PPL",
    "gn:name":"Huiyaozi",
    "gn:population":0,
    "gn:timezone":"Asia/Shanghai",
    "iso:country":"CN",
    "name:zho_x_preferred":[
        "\u7070\u7a91\u5b50"
    ],
    "wof:name":"Huiyaozi",
    "wof:placetype":"locality"
},
  "geometry": {"coordinates":[117.32514,40.48954000000001],"type":"Point"}
}