{
  "type": "Feature",
  "properties": {
    "gn:admin1_code":"8.0",
    "gn:asciiname":"Wangxiantun",
    "gn:country_code":"CN",
    "gn:dem":147,
    "gn:feature_class":"P",
    "gn:feature_code":"PPL",
    "gn:name":"Wangxiantun",
    "gn:population":0,
    "gn:timezone":"Asia/Shanghai",
    "iso:country":"CN",
    "name:zho_x_preferred":[
        "\u738b\u5148\u5c6f"
    ],
    "wof:name":"Wangxiantun",
    "wof:placetype":"locality"
},
  "geometry": {"coordinates":[125.95139,46.03623],"type":"Point"}
}