{
  "type": "Feature",
  "properties": {
    "gn:admin1_code":"08",
    "gn:asciiname":"Changqing",
    "gn:cc2":"CN",
    "gn:country_code":"CN",
    "gn:dem":279,
    "gn:feature_class":"P",
    "gn:feature_code":"PPL",
    "gn:name":"Changqing",
    "gn:population":0,
    "gn:timezone":"Asia/Shanghai",
    "iso:country":"CN",
    "name:deu_x_preferred":[
        "Changqing"
    ],
    "name:und_x_variant":[
        "Ch\u2019ang-ch\u2019ing",
        "Yongqing",
        "Yung-ch\u2019ing",
        "Changqing"
    ],
    "wof:name":"Changqing",
    "wof:placetype":"locality"
},
  "geometry": {"coordinates":[129.44999999999999,48.91667],"type":"Point"}
}