{
  "type": "Feature",
  "properties": {
    "gn:admin1_code":"14.0",
    "gn:asciiname":"Dejilincun",
    "gn:country_code":"CN",
    "gn:dem":3821,
    "gn:feature_class":"P",
    "gn:feature_code":"PPL",
    "gn:name":"Dejilincun",
    "gn:population":0,
    "gn:timezone":"Asia/Urumqi",
    "iso:country":"CN",
    "name:zho_x_preferred":[
        "\u5fb7\u5409\u6797\u6751"
    ],
    "wof:name":"Dejilincun",
    "wof:placetype":"locality"
},
  "geometry": {"coordinates":[91.27531,29.10897000000001],"type":"Point"}
}