{
  "type": "Feature",
  "properties": {
    "gn:admin1_code":"18",
    "gn:asciiname":"Munizhai",
    "gn:country_code":"CN",
    "gn:dem":1263,
    "gn:feature_class":"P",
    "gn:feature_code":"PPL",
    "gn:name":"Munizhai",
    "gn:population":0,
    "gn:timezone":"Asia/Shanghai",
    "iso:country":"CN",
    "name:zho_x_preferred":[
        "\u6728\u6ce5\u5be8"
    ],
    "wof:name":"Munizhai",
    "wof:placetype":"locality"
},
  "geometry": {"coordinates":[106.56100000000001,27.9396],"type":"Point"}
}