{
  "type": "Feature",
  "properties": {
    "gn:admin1_code":"3",
    "gn:asciiname":"Zhongbei",
    "gn:country_code":"CN",
    "gn:dem":125,
    "gn:feature_class":"P",
    "gn:feature_code":"PPL",
    "gn:name":"Zhongbei",
    "gn:population":0,
    "gn:timezone":"Asia/Shanghai",
    "iso:country":"CN",
    "name:zho_x_preferred":[
        "\u4e2d\u9642"
    ],
    "name:zho_x_variant":[
        "\u4e2d\u5317\u9547"
    ],
    "wof:name":"Zhongbei",
    "wof:placetype":"locality"
},
  "geometry": {"coordinates":[114.934,26.531],"type":"Point"}
}