{
  "type": "Feature",
  "properties": {
    "gn:admin1_code":"15.0",
    "gn:asciiname":"Luojiacheng",
    "gn:country_code":"CN",
    "gn:dem":1361,
    "gn:feature_class":"P",
    "gn:feature_code":"PPL",
    "gn:name":"Luojiacheng",
    "gn:population":0,
    "gn:timezone":"Asia/Shanghai",
    "iso:country":"CN",
    "name:zho_x_preferred":[
        "\u7f57\u5bb6\u57ce"
    ],
    "wof:name":"Luojiacheng",
    "wof:placetype":"locality"
},
  "geometry": {"coordinates":[107.619,35.6411],"type":"Point"}
}