{
  "type": "Feature",
  "properties": {
    "gn:admin1_code":"14.0",
    "gn:asciiname":"Caqiu Duimacun",
    "gn:country_code":"CN",
    "gn:dem":4485,
    "gn:feature_class":"P",
    "gn:feature_code":"PPL",
    "gn:name":"Caqiu Duimacun",
    "gn:population":0,
    "gn:timezone":"Asia/Urumqi",
    "iso:country":"CN",
    "name:zho_x_preferred":[
        "\u64e6\u79cb\u5806\u739b\u6751"
    ],
    "wof:name":"Caqiu Duimacun",
    "wof:placetype":"locality"
},
  "geometry": {"coordinates":[92.29406,31.25227000000001],"type":"Point"}
}