{
  "type": "Feature",
  "properties": {
    "gn:admin1_code":"2.0",
    "gn:asciiname":"Gaobutou",
    "gn:country_code":"CN",
    "gn:dem":24,
    "gn:feature_class":"P",
    "gn:feature_code":"PPL",
    "gn:name":"Gaobutou",
    "gn:population":0,
    "gn:timezone":"Asia/Shanghai",
    "iso:country":"CN",
    "name:und_x_variant":[
        "\u9ad8\u57e0\u5934"
    ],
    "wof:name":"Gaobutou",
    "wof:placetype":"locality"
},
  "geometry": {"coordinates":[120.01988,30.21791],"type":"Point"}
}