{
  "type": "Feature",
  "properties": {
    "gn:admin1_code":"24.0",
    "gn:asciiname":"Tuhuanggou",
    "gn:country_code":"CN",
    "gn:dem":992,
    "gn:feature_class":"P",
    "gn:feature_code":"PPL",
    "gn:name":"Tuhuanggou",
    "gn:population":0,
    "gn:timezone":"Asia/Shanghai",
    "iso:country":"CN",
    "name:zho_x_preferred":[
        "\u571f\u9ec4\u6c9f"
    ],
    "wof:name":"Tuhuanggou",
    "wof:placetype":"locality"
},
  "geometry": {"coordinates":[112.65000000000001,38.87414],"type":"Point"}
}