{
  "type": "Feature",
  "properties": {
    "gn:admin1_code":"32.0",
    "gn:asciiname":"Zepu",
    "gn:country_code":"CN",
    "gn:dem":2590,
    "gn:feature_class":"P",
    "gn:feature_code":"PPL",
    "gn:name":"Zepu",
    "gn:population":0,
    "gn:timezone":"Asia/Shanghai",
    "iso:country":"CN",
    "name:zho_x_preferred":[
        "\u5219\u666e"
    ],
    "wof:name":"Zepu",
    "wof:placetype":"locality"
},
  "geometry": {"coordinates":[102.83674000000001,28.296],"type":"Point"}
}