{
  "type": "Feature",
  "properties": {
    "gn:admin1_code":"11.0",
    "gn:asciiname":"Lijiamen",
    "gn:country_code":"CN",
    "gn:dem":35,
    "gn:feature_class":"P",
    "gn:feature_code":"PPL",
    "gn:name":"Lijiamen",
    "gn:population":0,
    "gn:timezone":"Asia/Shanghai",
    "iso:country":"CN",
    "name:zho_x_preferred":[
        "\u9ece\u5bb6\u95e8"
    ],
    "wof:name":"Lijiamen",
    "wof:placetype":"locality"
},
  "geometry": {"coordinates":[112.79949000000001,29.65444],"type":"Point"}
}