{
  "type": "Feature",
  "properties": {
    "gn:admin1_code":"29.0",
    "gn:asciiname":"Yuanjiawan",
    "gn:country_code":"CN",
    "gn:dem":1454,
    "gn:feature_class":"P",
    "gn:feature_code":"PPL",
    "gn:name":"Yuanjiawan",
    "gn:population":0,
    "gn:timezone":"Asia/Shanghai",
    "iso:country":"CN",
    "name:zho_x_preferred":[
        "\u8881\u5bb6\u6e7e"
    ],
    "wof:name":"Yuanjiawan",
    "wof:placetype":"locality"
},
  "geometry": {"coordinates":[103.351,27.0117],"type":"Point"}
}