{
  "type": "Feature",
  "properties": {
    "gn:admin1_code":"5.0",
    "gn:asciiname":"Youyicun",
    "gn:country_code":"CN",
    "gn:dem":536,
    "gn:feature_class":"P",
    "gn:feature_code":"PPL",
    "gn:name":"Youyicun",
    "gn:population":0,
    "gn:timezone":"Asia/Shanghai",
    "iso:country":"CN",
    "name:zho_x_preferred":[
        "\u53cb\u8c0a\u6751"
    ],
    "wof:name":"Youyicun",
    "wof:placetype":"locality"
},
  "geometry": {"coordinates":[128.52787000000001,43.28194000000001],"type":"Point"}
}