{
  "type": "Feature",
  "properties": {
    "gn:admin1_code":"19.0",
    "gn:asciiname":"Jinwopu",
    "gn:country_code":"CN",
    "gn:dem":558,
    "gn:feature_class":"P",
    "gn:feature_code":"PPL",
    "gn:name":"Jinwopu",
    "gn:population":0,
    "gn:timezone":"Asia/Shanghai",
    "iso:country":"CN",
    "name:zho_x_preferred":[
        "\u91d1\u7a9d\u94fa"
    ],
    "wof:name":"Jinwopu",
    "wof:placetype":"locality"
},
  "geometry": {"coordinates":[120.139,41.1774],"type":"Point"}
}