{
  "type": "Feature",
  "properties": {
    "gn:admin1_code":"11.0",
    "gn:asciiname":"Quedaping",
    "gn:country_code":"CN",
    "gn:dem":452,
    "gn:feature_class":"P",
    "gn:feature_code":"PPL",
    "gn:name":"Quedaping",
    "gn:population":0,
    "gn:timezone":"Asia/Shanghai",
    "iso:country":"CN",
    "name:zho_x_preferred":[
        "\u7f3a\u5927\u576a"
    ],
    "wof:name":"Quedaping",
    "wof:placetype":"locality"
},
  "geometry": {"coordinates":[110.18285,29.04779000000001],"type":"Point"}
}