{
  "type": "Feature",
  "properties": {
    "gn:admin1_code":"16",
    "gn:asciiname":"Laojiang",
    "gn:country_code":"CN",
    "gn:dem":375,
    "gn:feature_class":"P",
    "gn:feature_code":"PPL",
    "gn:name":"Laojiang",
    "gn:population":0,
    "gn:timezone":"Asia/Shanghai",
    "iso:country":"CN",
    "name:zho_x_preferred":[
        "\u6d9d\u6c5f"
    ],
    "wof:name":"Laojiang",
    "wof:placetype":"locality"
},
  "geometry": {"coordinates":[110.584,25.1501],"type":"Point"}
}