{
  "type": "Feature",
  "properties": {
    "gn:admin1_code":"2.0",
    "gn:asciiname":"Duancun",
    "gn:country_code":"CN",
    "gn:dem":68,
    "gn:feature_class":"P",
    "gn:feature_code":"PPL",
    "gn:name":"Duancun",
    "gn:population":0,
    "gn:timezone":"Asia/Shanghai",
    "iso:country":"CN",
    "name:zho_x_preferred":[
        "\u7aef\u6751"
    ],
    "wof:name":"Duancun",
    "wof:placetype":"locality"
},
  "geometry": {"coordinates":[119.84166,28.87578],"type":"Point"}
}