{
  "type": "Feature",
  "properties": {
    "gn:admin1_code":"29.0",
    "gn:asciiname":"Nanpo",
    "gn:country_code":"CN",
    "gn:dem":1825,
    "gn:feature_class":"P",
    "gn:feature_code":"PPL",
    "gn:name":"Nanpo",
    "gn:population":0,
    "gn:timezone":"Asia/Shanghai",
    "iso:country":"CN",
    "name:zho_x_preferred":[
        "\u5357\u8feb"
    ],
    "wof:name":"Nanpo",
    "wof:placetype":"locality"
},
  "geometry": {"coordinates":[99.8925,23.794],"type":"Point"}
}