{
  "type": "Feature",
  "properties": {
    "gn:admin1_code":"7.0",
    "gn:asciiname":"Chi'ankou",
    "gn:country_code":"CN",
    "gn:dem":172,
    "gn:feature_class":"P",
    "gn:feature_code":"PPL",
    "gn:name":"Chi\u2019ankou",
    "gn:population":0,
    "gn:timezone":"Asia/Shanghai",
    "iso:country":"CN",
    "name:zho_x_preferred":[
        "\u8d64\u5cb8\u53e3"
    ],
    "name:zho_x_variant":[
        "Chi\u2019ankou"
    ],
    "wof:name":"Chi'ankou",
    "wof:placetype":"locality"
},
  "geometry": {"coordinates":[117.58024,27.20159],"type":"Point"}
}