{
  "type": "Feature",
  "properties": {
    "gn:admin1_code":"1.0",
    "gn:asciiname":"Dingchongcun",
    "gn:country_code":"CN",
    "gn:dem":68,
    "gn:feature_class":"P",
    "gn:feature_code":"PPL",
    "gn:name":"Dingchongcun",
    "gn:population":0,
    "gn:timezone":"Asia/Shanghai",
    "iso:country":"CN",
    "name:zho_x_preferred":[
        "\u4e01\u51b2\u6751"
    ],
    "wof:name":"Dingchongcun",
    "wof:placetype":"locality"
},
  "geometry": {"coordinates":[116.62432,31.48835],"type":"Point"}
}