{
  "type": "Feature",
  "properties": {
    "gn:admin1_code":"4.0",
    "gn:asciiname":"Jiling",
    "gn:country_code":"CN",
    "gn:dem":9,
    "gn:feature_class":"P",
    "gn:feature_code":"PPL",
    "gn:name":"Jiling",
    "gn:population":0,
    "gn:timezone":"Asia/Shanghai",
    "iso:country":"CN",
    "name:zho_x_preferred":[
        "Jiling"
    ],
    "name:zho_x_variant":[
        "\u5d47\u5cad"
    ],
    "wof:name":"Jiling",
    "wof:placetype":"locality"
},
  "geometry": {"coordinates":[119.13487000000001,34.33282],"type":"Point"}
}