{
  "type": "Feature",
  "properties": {
    "gn:admin1_code":"9.0",
    "gn:asciiname":"Qiandingzhuang",
    "gn:country_code":"CN",
    "gn:dem":112,
    "gn:feature_class":"P",
    "gn:feature_code":"PPL",
    "gn:name":"Qiandingzhuang",
    "gn:population":0,
    "gn:timezone":"Asia/Shanghai",
    "iso:country":"CN",
    "name:zho_x_preferred":[
        "\u524d\u4e01\u5e84"
    ],
    "wof:name":"Qiandingzhuang",
    "wof:placetype":"locality"
},
  "geometry": {"coordinates":[112.7944,32.87044],"type":"Point"}
}