{
  "type": "Feature",
  "properties": {
    "gn:admin1_code":"12.0",
    "gn:asciiname":"Shijiatuo",
    "gn:country_code":"CN",
    "gn:dem":1298,
    "gn:feature_class":"P",
    "gn:feature_code":"PPL",
    "gn:name":"Shijiatuo",
    "gn:population":0,
    "gn:timezone":"Asia/Shanghai",
    "iso:country":"CN",
    "name:zho_x_preferred":[
        "Shijiatuo"
    ],
    "name:zho_x_variant":[
        "\u77f3\u5bb6\u5768"
    ],
    "wof:name":"Shijiatuo",
    "wof:placetype":"locality"
},
  "geometry": {"coordinates":[109.0129,29.42606],"type":"Point"}
}