{
  "type": "Feature",
  "properties": {
    "gn:admin1_code":"18.0",
    "gn:asciiname":"Yunpan",
    "gn:country_code":"CN",
    "gn:dem":838,
    "gn:feature_class":"P",
    "gn:feature_code":"PPL",
    "gn:name":"Yunpan",
    "gn:population":0,
    "gn:timezone":"Asia/Shanghai",
    "iso:country":"CN",
    "name:zho_x_preferred":[
        "\u4e91\u76d8"
    ],
    "wof:name":"Yunpan",
    "wof:placetype":"locality"
},
  "geometry": {"coordinates":[109.10899999999999,27.9399],"type":"Point"}
}