{
  "type": "Feature",
  "properties": {
    "gn:admin1_code":"11",
    "gn:asciiname":"Lianglin",
    "gn:country_code":"CN",
    "gn:dem":824,
    "gn:feature_class":"P",
    "gn:feature_code":"PPLA4",
    "gn:name":"Lianglin",
    "gn:population":0,
    "gn:timezone":"Asia/Shanghai",
    "iso:country":"CN",
    "name:und_x_variant":[
        "Lianglin Xiang"
    ],
    "name:zho_x_preferred":[
        "\u4e24\u6797"
    ],
    "name:zho_x_variant":[
        "\u4e24\u6797\u4e61"
    ],
    "wof:name":"Lianglin",
    "wof:placetype":"locality"
},
  "geometry": {"coordinates":[109.38385,28.15779],"type":"Point"}
}