{
  "type": "Feature",
  "properties": {
    "gn:admin1_code":"3.0",
    "gn:asciiname":"Lidayuan",
    "gn:country_code":"CN",
    "gn:dem":428,
    "gn:feature_class":"P",
    "gn:feature_code":"PPL",
    "gn:name":"Lidayuan",
    "gn:population":0,
    "gn:timezone":"Asia/Shanghai",
    "iso:country":"CN",
    "name:zho_x_preferred":[
        "\u91cc\u5927\u6e90"
    ],
    "wof:name":"Lidayuan",
    "wof:placetype":"locality"
},
  "geometry": {"coordinates":[117.08238,27.84027],"type":"Point"}
}