{
  "type": "Feature",
  "properties": {
    "gn:admin1_code":"15.0",
    "gn:asciiname":"Tangjiaquan",
    "gn:country_code":"CN",
    "gn:dem":1457,
    "gn:feature_class":"P",
    "gn:feature_code":"PPL",
    "gn:name":"Tangjiaquan",
    "gn:population":0,
    "gn:timezone":"Asia/Shanghai",
    "iso:country":"CN",
    "name:zho_x_preferred":[
        "\u5510\u5bb6\u5708"
    ],
    "wof:name":"Tangjiaquan",
    "wof:placetype":"locality"
},
  "geometry": {"coordinates":[103.48399999999999,38.2286],"type":"Point"}
}