{
  "type": "Feature",
  "properties": {
    "gn:admin1_code":"33.0",
    "gn:asciiname":"Hongmiao Yakou",
    "gn:country_code":"CN",
    "gn:dem":888,
    "gn:feature_class":"P",
    "gn:feature_code":"PPL",
    "gn:name":"Hongmiao Yakou",
    "gn:population":0,
    "gn:timezone":"Asia/Shanghai",
    "iso:country":"CN",
    "name:zho_x_preferred":[
        "\u7ea2\u5e99\u57ad\u53e3"
    ],
    "wof:name":"Hongmiao Yakou",
    "wof:placetype":"locality"
},
  "geometry": {"coordinates":[107.336,28.9696],"type":"Point"}
}