{
  "type": "Feature",
  "properties": {
    "gn:admin1_code":"12.0",
    "gn:asciiname":"Hailuokou",
    "gn:country_code":"CN",
    "gn:dem":944,
    "gn:feature_class":"P",
    "gn:feature_code":"PPL",
    "gn:name":"Hailuokou",
    "gn:population":0,
    "gn:timezone":"Asia/Shanghai",
    "iso:country":"CN",
    "name:zho_x_preferred":[
        "\u6d77\u87ba\u53e3"
    ],
    "wof:name":"Hailuokou",
    "wof:placetype":"locality"
},
  "geometry": {"coordinates":[108.61203999999999,30.43511],"type":"Point"}
}