{
  "type": "Feature",
  "properties": {
    "gn:admin1_code":"1.0",
    "gn:asciiname":"Weiloucun",
    "gn:country_code":"CN",
    "gn:dem":26,
    "gn:feature_class":"P",
    "gn:feature_code":"PPL",
    "gn:name":"Weiloucun",
    "gn:population":0,
    "gn:timezone":"Asia/Shanghai",
    "iso:country":"CN",
    "name:zho_x_preferred":[
        "\u9b4f\u697c\u6751"
    ],
    "wof:name":"Weiloucun",
    "wof:placetype":"locality"
},
  "geometry": {"coordinates":[116.73626000000002,33.23095],"type":"Point"}
}