{
  "type": "Feature",
  "properties": {
    "gn:admin1_code":"12.0",
    "gn:asciiname":"Shicaoshui",
    "gn:country_code":"CN",
    "gn:dem":1075,
    "gn:feature_class":"P",
    "gn:feature_code":"PPL",
    "gn:name":"Shicaoshui",
    "gn:population":0,
    "gn:timezone":"Asia/Shanghai",
    "iso:country":"CN",
    "name:zho_x_preferred":[
        "\u77f3\u69fd\u6c34"
    ],
    "wof:name":"Shicaoshui",
    "wof:placetype":"locality"
},
  "geometry": {"coordinates":[110.00864,30.32454],"type":"Point"}
}