{
  "type": "Feature",
  "properties": {
    "gn:admin1_code":"32",
    "gn:asciiname":"Maodianzi",
    "gn:cc2":"CN",
    "gn:country_code":"CN",
    "gn:dem":350,
    "gn:feature_class":"P",
    "gn:feature_code":"PPL",
    "gn:name":"Maodianzi",
    "gn:population":0,
    "gn:timezone":"Asia/Shanghai",
    "iso:country":"CN",
    "name:und_x_variant":[
        "Mao-tien-tzu",
        "Maodianzi"
    ],
    "wof:name":"Maodianzi",
    "wof:placetype":"locality"
},
  "geometry": {"coordinates":[104.91667,29.75],"type":"Point"}
}