{
  "type": "Feature",
  "properties": {
    "gn:admin1_code":"12.0",
    "gn:asciiname":"Zhangcitangwan",
    "gn:country_code":"CN",
    "gn:dem":28,
    "gn:feature_class":"P",
    "gn:feature_code":"PPL",
    "gn:name":"Zhangcitangwan",
    "gn:population":0,
    "gn:timezone":"Asia/Shanghai",
    "iso:country":"CN",
    "name:und_x_variant":[
        "\u5f20\u7960\u5802\u5846"
    ],
    "wof:name":"Zhangcitangwan",
    "wof:placetype":"locality"
},
  "geometry": {"coordinates":[114.33316000000001,30.81824000000001],"type":"Point"}
}