{
  "type": "Feature",
  "properties": {
    "gn:admin1_code":"24.0",
    "gn:asciiname":"Jidaoling",
    "gn:country_code":"CN",
    "gn:dem":1477,
    "gn:feature_class":"P",
    "gn:feature_code":"PPL",
    "gn:name":"Jidaoling",
    "gn:population":0,
    "gn:timezone":"Asia/Shanghai",
    "iso:country":"CN",
    "name:zho_x_preferred":[
        "\u6d4e\u9053\u5cad"
    ],
    "wof:name":"Jidaoling",
    "wof:placetype":"locality"
},
  "geometry": {"coordinates":[112.28651000000001,38.31931],"type":"Point"}
}