{
  "type": "Feature",
  "properties": {
    "gn:admin1_code":"18",
    "gn:asciiname":"Pojiao",
    "gn:country_code":"CN",
    "gn:dem":1010,
    "gn:feature_class":"P",
    "gn:feature_code":"PPL",
    "gn:name":"Pojiao",
    "gn:population":0,
    "gn:timezone":"Asia/Shanghai",
    "iso:country":"CN",
    "name:zho_x_preferred":[
        "\u5761\u811a"
    ],
    "wof:name":"Pojiao",
    "wof:placetype":"locality"
},
  "geometry": {"coordinates":[105.13800000000001,26.0753],"type":"Point"}
}