{
  "type": "Feature",
  "properties": {
    "gn:admin1_code":"25",
    "gn:asciiname":"Liuguoxiang",
    "gn:country_code":"CN",
    "gn:dem":11,
    "gn:feature_class":"P",
    "gn:feature_code":"PPL",
    "gn:name":"Liuguoxiang",
    "gn:population":0,
    "gn:timezone":"Asia/Shanghai",
    "iso:country":"CN",
    "name:zho_x_preferred":[
        "\u5218\u56fd\u76f8"
    ],
    "wof:name":"Liuguoxiang",
    "wof:placetype":"locality"
},
  "geometry": {"coordinates":[117.872,37.4414],"type":"Point"}
}