{
  "type": "Feature",
  "properties": {
    "gn:admin1_code":"07",
    "gn:asciiname":"Tushan",
    "gn:country_code":"CN",
    "gn:dem":775,
    "gn:feature_class":"P",
    "gn:feature_code":"PPL",
    "gn:name":"Tushan",
    "gn:population":0,
    "gn:timezone":"Asia/Shanghai",
    "iso:country":"CN",
    "name:zho_x_preferred":[
        "\u6d82\u5c71"
    ],
    "wof:name":"Tushan",
    "wof:placetype":"locality"
},
  "geometry": {"coordinates":[117.95444000000001,25.52806],"type":"Point"}
}