{
  "type": "Feature",
  "properties": {
    "gn:admin1_code":"12.0",
    "gn:asciiname":"Qiaoping",
    "gn:country_code":"CN",
    "gn:dem":1266,
    "gn:feature_class":"P",
    "gn:feature_code":"PPL",
    "gn:name":"Qiaoping",
    "gn:population":0,
    "gn:timezone":"Asia/Shanghai",
    "iso:country":"CN",
    "name:zho_x_preferred":[
        "\u6865\u576a"
    ],
    "wof:name":"Qiaoping",
    "wof:placetype":"locality"
},
  "geometry": {"coordinates":[110.75613,30.23718],"type":"Point"}
}