{
  "type": "Feature",
  "properties": {
    "gn:admin1_code":"26.0",
    "gn:asciiname":"Huashan Chengzi",
    "gn:country_code":"CN",
    "gn:dem":1489,
    "gn:feature_class":"P",
    "gn:feature_code":"PPL",
    "gn:name":"Huashan Chengzi",
    "gn:population":0,
    "gn:timezone":"Asia/Shanghai",
    "iso:country":"CN",
    "name:zho_x_preferred":[
        "\u82b1\u5c71\u57ce\u5b50"
    ],
    "wof:name":"Huashan Chengzi",
    "wof:placetype":"locality"
},
  "geometry": {"coordinates":[108.161,37.1834],"type":"Point"}
}