{
  "type": "Feature",
  "properties": {
    "gn:admin1_code":"19.0",
    "gn:asciiname":"Wujianfang",
    "gn:country_code":"CN",
    "gn:dem":45,
    "gn:feature_class":"P",
    "gn:feature_code":"PPL",
    "gn:name":"Wujianfang",
    "gn:population":0,
    "gn:timezone":"Asia/Shanghai",
    "iso:country":"CN",
    "name:zho_x_preferred":[
        "\u4e94\u95f4\u623f"
    ],
    "wof:name":"Wujianfang",
    "wof:placetype":"locality"
},
  "geometry": {"coordinates":[121.73475000000001,39.54191],"type":"Point"}
}