{
  "type": "Feature",
  "properties": {
    "gn:admin1_code":"26.0",
    "gn:asciiname":"Wangzhuangcun",
    "gn:country_code":"CN",
    "gn:dem":764,
    "gn:feature_class":"P",
    "gn:feature_code":"PPL",
    "gn:name":"Wangzhuangcun",
    "gn:population":0,
    "gn:timezone":"Asia/Shanghai",
    "iso:country":"CN",
    "name:zho_x_preferred":[
        "\u6c6a\u5e84\u6751"
    ],
    "wof:name":"Wangzhuangcun",
    "wof:placetype":"locality"
},
  "geometry": {"coordinates":[109.13703,34.02106],"type":"Point"}
}