{
  "type": "Feature",
  "properties": {
    "gn:admin1_code":"4.0",
    "gn:asciiname":"Longtangcun",
    "gn:country_code":"CN",
    "gn:dem":38,
    "gn:feature_class":"P",
    "gn:feature_code":"PPL",
    "gn:name":"Longtangcun",
    "gn:population":0,
    "gn:timezone":"Asia/Shanghai",
    "iso:country":"CN",
    "name:zho_x_preferred":[
        "\u9f99\u5858\u6751"
    ],
    "wof:name":"Longtangcun",
    "wof:placetype":"locality"
},
  "geometry": {"coordinates":[117.08368,34.54272],"type":"Point"}
}