{
  "type": "Feature",
  "properties": {
    "gn:admin1_code":"12.0",
    "gn:asciiname":"Zhuwatou",
    "gn:country_code":"CN",
    "gn:dem":1097,
    "gn:feature_class":"P",
    "gn:feature_code":"PPL",
    "gn:name":"Zhuwatou",
    "gn:population":0,
    "gn:timezone":"Asia/Shanghai",
    "iso:country":"CN",
    "name:zho_x_preferred":[
        "\u7af9\u74e6\u5934"
    ],
    "wof:name":"Zhuwatou",
    "wof:placetype":"locality"
},
  "geometry": {"coordinates":[110.79138,31.07237000000001],"type":"Point"}
}