{
  "type": "Feature",
  "properties": {
    "gn:admin1_code":"24",
    "gn:asciiname":"Qiuquan",
    "gn:cc2":"CN",
    "gn:country_code":"CN",
    "gn:dem":1084,
    "gn:feature_class":"P",
    "gn:feature_code":"PPL",
    "gn:name":"Qiuquan",
    "gn:population":0,
    "gn:timezone":"Asia/Shanghai",
    "iso:country":"CN",
    "name:und_x_variant":[
        "Ch\u2019iu-ch\u2019\u00fcan",
        "Qiuquan"
    ],
    "wof:name":"Qiuquan",
    "wof:placetype":"locality"
},
  "geometry": {"coordinates":[111.53333000000001,36.76667],"type":"Point"}
}