{
  "type": "Feature",
  "properties": {
    "gn:admin1_code":"29.0",
    "gn:asciiname":"Yangmeishan",
    "gn:country_code":"CN",
    "gn:dem":1966,
    "gn:feature_class":"P",
    "gn:feature_code":"PPL",
    "gn:name":"Yangmeishan",
    "gn:population":0,
    "gn:timezone":"Asia/Shanghai",
    "iso:country":"CN",
    "name:zho_x_preferred":[
        "\u6768\u6885\u5c71"
    ],
    "wof:name":"Yangmeishan",
    "wof:placetype":"locality"
},
  "geometry": {"coordinates":[100.34099999999999,24.1054],"type":"Point"}
}