{
  "type": "Feature",
  "properties": {
    "gn:admin1_code":"25.0",
    "gn:asciiname":"Shawocun",
    "gn:country_code":"CN",
    "gn:dem":18,
    "gn:feature_class":"P",
    "gn:feature_code":"PPL",
    "gn:name":"Shawocun",
    "gn:population":0,
    "gn:timezone":"Asia/Shanghai",
    "iso:country":"CN",
    "name:zho_x_preferred":[
        "\u6c99\u7a9d\u6751"
    ],
    "wof:name":"Shawocun",
    "wof:placetype":"locality"
},
  "geometry": {"coordinates":[119.82583,36.42384000000001],"type":"Point"}
}