{
  "type": "Feature",
  "properties": {
    "gn:admin1_code":"7",
    "gn:asciiname":"Tingxia",
    "gn:country_code":"CN",
    "gn:dem":935,
    "gn:feature_class":"P",
    "gn:feature_code":"PPL",
    "gn:name":"Tingxia",
    "gn:population":0,
    "gn:timezone":"Asia/Shanghai",
    "iso:country":"CN",
    "wof:name":"Tingxia",
    "wof:placetype":"locality"
},
  "geometry": {"coordinates":[118.16972,27.75083],"type":"Point"}
}