{
  "type": "Feature",
  "properties": {
    "gn:admin1_code":"32.0",
    "gn:asciiname":"Yuechipo",
    "gn:country_code":"CN",
    "gn:dem":672,
    "gn:feature_class":"P",
    "gn:feature_code":"PPL",
    "gn:name":"Yuechipo",
    "gn:population":0,
    "gn:timezone":"Asia/Shanghai",
    "iso:country":"CN",
    "name:zho_x_preferred":[
        "\u94a5\u5319\u5761"
    ],
    "wof:name":"Yuechipo",
    "wof:placetype":"locality"
},
  "geometry": {"coordinates":[107.373,31.9024],"type":"Point"}
}