{
  "type": "Feature",
  "properties": {
    "gn:admin1_code":"30.0",
    "gn:asciiname":"Xialuojia",
    "gn:country_code":"CN",
    "gn:dem":96,
    "gn:feature_class":"P",
    "gn:feature_code":"PPL",
    "gn:name":"Xialuojia",
    "gn:population":0,
    "gn:timezone":"Asia/Shanghai",
    "iso:country":"CN",
    "name:zho_x_preferred":[
        "\u4e0b\u7f57\u67b6"
    ],
    "wof:name":"Xialuojia",
    "wof:placetype":"locality"
},
  "geometry": {"coordinates":[112.07398999999999,23.82726],"type":"Point"}
}