{
  "type": "Feature",
  "properties": {
    "gn:admin1_code":"31",
    "gn:asciiname":"Baomei",
    "gn:country_code":"CN",
    "gn:dem":118,
    "gn:feature_class":"P",
    "gn:feature_code":"PPL",
    "gn:name":"Baomei",
    "gn:population":0,
    "gn:timezone":"Asia/Shanghai",
    "iso:country":"CN",
    "name:und_x_variant":[
        "\u4fdd\u6885"
    ],
    "wof:name":"Baomei",
    "wof:placetype":"locality"
},
  "geometry": {"coordinates":[109.056,19.2869],"type":"Point"}
}