{
  "type": "Feature",
  "properties": {
    "gn:admin1_code":"25.0",
    "gn:asciiname":"Jiuqu",
    "gn:country_code":"CN",
    "gn:dem":217,
    "gn:feature_class":"P",
    "gn:feature_code":"PPL",
    "gn:name":"Jiuqu",
    "gn:population":0,
    "gn:timezone":"Asia/Shanghai",
    "iso:country":"CN",
    "name:zho_x_preferred":[
        "\u4e5d\u66f2"
    ],
    "wof:name":"Jiuqu",
    "wof:placetype":"locality"
},
  "geometry": {"coordinates":[120.53973000000001,37.45974],"type":"Point"}
}