{
  "type": "Feature",
  "properties": {
    "gn:admin1_code":"29",
    "gn:asciiname":"Shanwei",
    "gn:country_code":"CN",
    "gn:dem":1482,
    "gn:feature_class":"P",
    "gn:feature_code":"PPL",
    "gn:name":"Shanwei",
    "gn:population":0,
    "gn:timezone":"Asia/Shanghai",
    "iso:country":"CN",
    "name:zho_x_preferred":[
        "\u6247\u5c3e"
    ],
    "wof:name":"Shanwei",
    "wof:placetype":"locality"
},
  "geometry": {"coordinates":[102.33799999999999,23.7131],"type":"Point"}
}