{
  "type": "Feature",
  "properties": {
    "gn:admin1_code":"18",
    "gn:asciiname":"Limuzhai",
    "gn:country_code":"CN",
    "gn:dem":1129,
    "gn:feature_class":"P",
    "gn:feature_code":"PPL",
    "gn:name":"Limuzhai",
    "gn:population":0,
    "gn:timezone":"Asia/Shanghai",
    "iso:country":"CN",
    "name:zho_x_preferred":[
        "\u6817\u6728\u5be8"
    ],
    "wof:name":"Limuzhai",
    "wof:placetype":"locality"
},
  "geometry": {"coordinates":[106.767,26.3299],"type":"Point"}
}