{
  "type": "Feature",
  "properties": {
    "gn:admin1_code":"14.0",
    "gn:asciiname":"Yalang",
    "gn:country_code":"CN",
    "gn:dem":4872,
    "gn:feature_class":"P",
    "gn:feature_code":"PPL",
    "gn:name":"Yalang",
    "gn:population":0,
    "gn:timezone":"Asia/Urumqi",
    "iso:country":"CN",
    "name:zho_x_preferred":[
        "\u4e9a\u6717"
    ],
    "wof:name":"Yalang",
    "wof:placetype":"locality"
},
  "geometry": {"coordinates":[86.962,30.4168],"type":"Point"}
}