{
  "type": "Feature",
  "properties": {
    "gn:admin1_code":"16",
    "gn:asciiname":"Menqianshan",
    "gn:country_code":"CN",
    "gn:dem":187,
    "gn:feature_class":"P",
    "gn:feature_code":"PPL",
    "gn:name":"Menqianshan",
    "gn:population":0,
    "gn:timezone":"Asia/Shanghai",
    "iso:country":"CN",
    "name:zho_x_preferred":[
        "\u95e8\u524d\u5c71"
    ],
    "wof:name":"Menqianshan",
    "wof:placetype":"locality"
},
  "geometry": {"coordinates":[111.17,25.7325],"type":"Point"}
}