{
  "type": "Feature",
  "properties": {
    "gn:admin1_code":"2.0",
    "gn:asciiname":"Shengjia",
    "gn:country_code":"CN",
    "gn:dem":45,
    "gn:feature_class":"P",
    "gn:feature_code":"PPL",
    "gn:name":"Shengjia",
    "gn:population":0,
    "gn:timezone":"Asia/Shanghai",
    "iso:country":"CN",
    "name:zho_x_preferred":[
        "\u76db\u5bb6"
    ],
    "wof:name":"Shengjia",
    "wof:placetype":"locality"
},
  "geometry": {"coordinates":[121.36606,29.87861],"type":"Point"}
}