{
  "type": "Feature",
  "properties": {
    "gn:admin1_code":"7.0",
    "gn:asciiname":"Liujin",
    "gn:country_code":"CN",
    "gn:dem":44,
    "gn:feature_class":"P",
    "gn:feature_code":"PPL",
    "gn:name":"Liujin",
    "gn:population":0,
    "gn:timezone":"Asia/Shanghai",
    "iso:country":"CN",
    "name:zho_x_preferred":[
        "\u7559\u91d1"
    ],
    "wof:name":"Liujin",
    "wof:placetype":"locality"
},
  "geometry": {"coordinates":[120.00857000000001,26.60947],"type":"Point"}
}