{
  "type": "Feature",
  "properties": {
    "gn:admin1_code":"24.0",
    "gn:asciiname":"Guojiaduocun",
    "gn:country_code":"CN",
    "gn:dem":927,
    "gn:feature_class":"P",
    "gn:feature_code":"PPL",
    "gn:name":"Guojiaduocun",
    "gn:population":0,
    "gn:timezone":"Asia/Shanghai",
    "iso:country":"CN",
    "name:zho_x_preferred":[
        "\u90ed\u5bb6\u579b\u6751"
    ],
    "wof:name":"Guojiaduocun",
    "wof:placetype":"locality"
},
  "geometry": {"coordinates":[110.5317,38.00812],"type":"Point"}
}