{
  "type": "Feature",
  "properties": {
    "gn:admin1_code":"30.0",
    "gn:asciiname":"Xikeng",
    "gn:cc2":"CN",
    "gn:country_code":"CN",
    "gn:dem":121,
    "gn:feature_class":"P",
    "gn:feature_code":"PPL",
    "gn:name":"Xikeng",
    "gn:population":0,
    "gn:timezone":"Asia/Shanghai",
    "iso:country":"CN",
    "name:und_x_variant":[
        "Hsi-k\u2019eng",
        "Hsi-k\u2019eng-hs\u00fc",
        "Xikeng"
    ],
    "wof:name":"Xikeng",
    "wof:placetype":"locality"
},
  "geometry": {"coordinates":[115.72778,23.81722],"type":"Point"}
}