{
  "type": "Feature",
  "properties": {
    "gn:admin1_code":"4.0",
    "gn:asciiname":"Liujiabian",
    "gn:country_code":"CN",
    "gn:dem":30,
    "gn:feature_class":"P",
    "gn:feature_code":"PPL",
    "gn:name":"Liujiabian",
    "gn:population":0,
    "gn:timezone":"Asia/Shanghai",
    "iso:country":"CN",
    "name:zho_x_preferred":[
        "\u5218\u5bb6\u8fb9"
    ],
    "wof:name":"Liujiabian",
    "wof:placetype":"locality"
},
  "geometry": {"coordinates":[119.09688,31.62433],"type":"Point"}
}