{
  "type": "Feature",
  "properties": {
    "gn:admin1_code":"19.0",
    "gn:asciiname":"Weijia Taizi",
    "gn:country_code":"CN",
    "gn:dem":39,
    "gn:feature_class":"P",
    "gn:feature_code":"PPL",
    "gn:name":"Weijia Taizi",
    "gn:population":0,
    "gn:timezone":"Asia/Shanghai",
    "iso:country":"CN",
    "name:zho_x_preferred":[
        "\u9b4f\u5bb6\u53f0\u5b50"
    ],
    "wof:name":"Weijia Taizi",
    "wof:placetype":"locality"
},
  "geometry": {"coordinates":[121.535,38.927],"type":"Point"}
}