{
  "type": "Feature",
  "properties": {
    "gn:admin1_code":"10",
    "gn:asciiname":"Balizhuang",
    "gn:country_code":"CN",
    "gn:dem":7,
    "gn:feature_class":"P",
    "gn:feature_code":"PPL",
    "gn:name":"Balizhuang",
    "gn:population":0,
    "gn:timezone":"Asia/Shanghai",
    "iso:country":"CN",
    "name:und_x_variant":[
        "Pa-li-chuang",
        "Balizhuang"
    ],
    "name:zho_x_preferred":[
        "\u516b\u91cc\u5e84"
    ],
    "wof:name":"Balizhuang",
    "wof:placetype":"locality"
},
  "geometry": {"coordinates":[117.45099999999999,38.3055],"type":"Point"}
}