{
  "type": "Feature",
  "properties": {
    "gn:admin1_code":"25.0",
    "gn:asciiname":"Zhangbiaocun",
    "gn:country_code":"CN",
    "gn:dem":46,
    "gn:feature_class":"P",
    "gn:feature_code":"PPL",
    "gn:name":"Zhangbiaocun",
    "gn:population":0,
    "gn:timezone":"Asia/Shanghai",
    "iso:country":"CN",
    "name:zho_x_preferred":[
        "\u5f20\u8868\u6751"
    ],
    "wof:name":"Zhangbiaocun",
    "wof:placetype":"locality"
},
  "geometry": {"coordinates":[115.82619,35.22157],"type":"Point"}
}