{
  "type": "Feature",
  "properties": {
    "gn:admin1_code":"19.0",
    "gn:asciiname":"Dong'a'er Xiang",
    "gn:country_code":"CN",
    "gn:dem":254,
    "gn:feature_class":"P",
    "gn:feature_code":"PPL",
    "gn:name":"Dong\u2019a\u2019er Xiang",
    "gn:population":0,
    "gn:timezone":"Asia/Shanghai",
    "iso:country":"CN",
    "name:und_x_variant":[
        "Dong\u2019a\u2019er Xiang"
    ],
    "name:zho_x_preferred":[
        "\u4e1c\u963f\u5c14\u4e61"
    ],
    "wof:name":"Dong'a'er Xiang",
    "wof:placetype":"locality"
},
  "geometry": {"coordinates":[122.43600000000001,42.8214],"type":"Point"}
}