{
  "type": "Feature",
  "properties": {
    "gn:admin1_code":"19",
    "gn:asciiname":"Ershijiazi",
    "gn:cc2":"CN",
    "gn:country_code":"CN",
    "gn:dem":112,
    "gn:feature_class":"P",
    "gn:feature_code":"PPL",
    "gn:name":"Ershijiazi",
    "gn:population":0,
    "gn:timezone":"Asia/Shanghai",
    "iso:country":"CN",
    "name:und_x_variant":[
        "Erh-shih-chia-tzu",
        "Ershijiazi"
    ],
    "wof:name":"Ershijiazi",
    "wof:placetype":"locality"
},
  "geometry": {"coordinates":[123.96666999999999,42.93333],"type":"Point"}
}