{
  "type": "Feature",
  "properties": {
    "gn:admin1_code":"19.0",
    "gn:asciiname":"Alahecun",
    "gn:country_code":"CN",
    "gn:dem":6,
    "gn:feature_class":"P",
    "gn:feature_code":"PPL",
    "gn:name":"Alahecun",
    "gn:population":0,
    "gn:timezone":"Asia/Shanghai",
    "iso:country":"CN",
    "name:zho_x_preferred":[
        "\u963f\u62c9\u6cb3\u6751"
    ],
    "wof:name":"Alahecun",
    "wof:placetype":"locality"
},
  "geometry": {"coordinates":[122.48621,41.44442],"type":"Point"}
}