{
  "type": "Feature",
  "properties": {
    "gn:admin1_code":"9.0",
    "gn:asciiname":"Liuchenzhai",
    "gn:country_code":"CN",
    "gn:dem":46,
    "gn:feature_class":"P",
    "gn:feature_code":"PPL",
    "gn:name":"Liuchenzhai",
    "gn:population":0,
    "gn:timezone":"Asia/Shanghai",
    "iso:country":"CN",
    "name:zho_x_preferred":[
        "\u5218\u9648\u5be8"
    ],
    "wof:name":"Liuchenzhai",
    "wof:placetype":"locality"
},
  "geometry": {"coordinates":[115.02196000000001,33.56167],"type":"Point"}
}