{
  "type": "Feature",
  "properties": {
    "gn:admin1_code":"23",
    "gn:asciiname":"Huayangqiao",
    "gn:country_code":"CN",
    "gn:dem":4,
    "gn:feature_class":"P",
    "gn:feature_code":"PPL",
    "gn:name":"Huayangqiao",
    "gn:population":0,
    "gn:timezone":"Asia/Shanghai",
    "iso:country":"CN",
    "name:und_x_variant":[
        "Hua-yang-ch\u2019iao",
        "Hua-yang-ch\u2019iao-chen",
        "Huayangqiao",
        "\u534e\u9633\u6865"
    ],
    "wof:name":"Huayangqiao",
    "wof:placetype":"locality"
},
  "geometry": {"coordinates":[121.26555999999999,31.00694],"type":"Point"}
}