{
  "type": "Feature",
  "properties": {
    "gn:admin1_code":"19.0",
    "gn:asciiname":"Liutiaogou",
    "gn:country_code":"CN",
    "gn:dem":93,
    "gn:feature_class":"P",
    "gn:feature_code":"PPL",
    "gn:name":"Liutiaogou",
    "gn:population":0,
    "gn:timezone":"Asia/Shanghai",
    "iso:country":"CN",
    "name:und_x_variant":[
        "\u67f3\u6761\u6c9f"
    ],
    "name:zho_x_preferred":[
        "\u67f3\u6761\u6c9f"
    ],
    "wof:name":"Liutiaogou",
    "wof:placetype":"locality"
},
  "geometry": {"coordinates":[123.80034000000001,41.76529],"type":"Point"}
}