{
  "type": "Feature",
  "properties": {
    "gn:admin1_code":"29",
    "gn:asciiname":"Mengpeng",
    "gn:cc2":"CN",
    "gn:country_code":"CN",
    "gn:dem":565,
    "gn:feature_class":"P",
    "gn:feature_code":"PPL",
    "gn:name":"Mengpeng",
    "gn:population":0,
    "gn:timezone":"Asia/Shanghai",
    "iso:country":"CN",
    "name:und_x_variant":[
        "Pan-na-meng-ni",
        "Meng-ni",
        "Pan-na-meng-p\u2019eng",
        "Meng Pung",
        "Muong Poung",
        "Mengpeng"
    ],
    "wof:name":"Mengpeng",
    "wof:placetype":"locality"
},
  "geometry": {"coordinates":[101.28333000000001,21.43333],"type":"Point"}
}