{
  "type": "Feature",
  "properties": {
    "gn:admin1_code":"3.0",
    "gn:asciiname":"Hetian",
    "gn:country_code":"CN",
    "gn:dem":317,
    "gn:feature_class":"P",
    "gn:feature_code":"PPL",
    "gn:name":"Hetian",
    "gn:population":0,
    "gn:timezone":"Asia/Shanghai",
    "iso:country":"CN",
    "name:und_x_variant":[
        "\u8377\u7530"
    ],
    "wof:name":"Hetian",
    "wof:placetype":"locality"
},
  "geometry": {"coordinates":[116.47078999999999,27.6392],"type":"Point"}
}