{
  "type": "Feature",
  "properties": {
    "gn:admin1_code":"12.0",
    "gn:asciiname":"Yinpo",
    "gn:country_code":"CN",
    "gn:dem":693,
    "gn:feature_class":"P",
    "gn:feature_code":"PPL",
    "gn:name":"Yinpo",
    "gn:population":0,
    "gn:timezone":"Asia/Shanghai",
    "iso:country":"CN",
    "name:zho_x_preferred":[
        "\u9634\u5761"
    ],
    "wof:name":"Yinpo",
    "wof:placetype":"locality"
},
  "geometry": {"coordinates":[110.90645000000001,32.02144000000001],"type":"Point"}
}