{
  "type": "Feature",
  "properties": {
    "gn:admin1_code":"10",
    "gn:asciiname":"Liuzhangzi",
    "gn:cc2":"CN",
    "gn:country_code":"CN",
    "gn:dem":542,
    "gn:feature_class":"P",
    "gn:feature_code":"PPL",
    "gn:name":"Liuzhangzi",
    "gn:population":0,
    "gn:timezone":"Asia/Shanghai",
    "iso:country":"CN",
    "name:und_x_variant":[
        "Liu-chang-tzu",
        "Liuzhangzi"
    ],
    "wof:name":"Liuzhangzi",
    "wof:placetype":"locality"
},
  "geometry": {"coordinates":[117.73361,40.72167],"type":"Point"}
}