{
  "type": "Feature",
  "properties": {
    "gn:admin1_code":"8.0",
    "gn:asciiname":"Yanfangcun",
    "gn:country_code":"CN",
    "gn:dem":172,
    "gn:feature_class":"P",
    "gn:feature_code":"PPL",
    "gn:name":"Yanfangcun",
    "gn:population":0,
    "gn:timezone":"Asia/Shanghai",
    "iso:country":"CN",
    "name:zho_x_preferred":[
        "\u5ef6\u653e\u6751"
    ],
    "wof:name":"Yanfangcun",
    "wof:placetype":"locality"
},
  "geometry": {"coordinates":[126.61563,45.35535],"type":"Point"}
}