{
  "type": "Feature",
  "properties": {
    "gn:admin1_code":"12.0",
    "gn:asciiname":"Yanping",
    "gn:country_code":"CN",
    "gn:dem":1018,
    "gn:feature_class":"P",
    "gn:feature_code":"PPL",
    "gn:name":"Yanping",
    "gn:population":0,
    "gn:timezone":"Asia/Shanghai",
    "iso:country":"CN",
    "name:ceb_x_preferred":[
        "Yanping"
    ],
    "name:zho_x_preferred":[
        "\u5830\u576a"
    ],
    "wof:name":"Yanping",
    "wof:placetype":"locality"
},
  "geometry": {"coordinates":[110.81672,30.67397],"type":"Point"}
}