{
  "type": "Feature",
  "properties": {
    "gn:admin1_code":"16.0",
    "gn:asciiname":"Shuijinping",
    "gn:country_code":"CN",
    "gn:dem":135,
    "gn:feature_class":"P",
    "gn:feature_code":"PPL",
    "gn:name":"Shuijinping",
    "gn:population":0,
    "gn:timezone":"Asia/Shanghai",
    "iso:country":"CN",
    "name:zho_x_preferred":[
        "\u6c34\u6d78\u576a"
    ],
    "wof:name":"Shuijinping",
    "wof:placetype":"locality"
},
  "geometry": {"coordinates":[110.839,24.634],"type":"Point"}
}