{
  "type": "Feature",
  "properties": {
    "gn:admin1_code":"15.0",
    "gn:asciiname":"Sidaowan",
    "gn:country_code":"CN",
    "gn:dem":2419,
    "gn:feature_class":"P",
    "gn:feature_code":"PPLF",
    "gn:name":"Sidaowan",
    "gn:population":0,
    "gn:timezone":"Asia/Urumqi",
    "iso:country":"CN",
    "name:zho_x_preferred":[
        "\u56db\u9053\u6e7e"
    ],
    "wof:name":"Sidaowan",
    "wof:placetype":"locality"
},
  "geometry": {"coordinates":[96.9665,39.5341],"type":"Point"}
}