{
  "type": "Feature",
  "properties": {
    "gn:admin1_code":"3",
    "gn:asciiname":"Yuezai",
    "gn:country_code":"CN",
    "gn:dem":159,
    "gn:feature_class":"P",
    "gn:feature_code":"PPL",
    "gn:name":"Yuezai",
    "gn:population":0,
    "gn:timezone":"Asia/Shanghai",
    "iso:country":"CN",
    "name:zho_x_preferred":[
        "\u6708\u4ed4"
    ],
    "wof:name":"Yuezai",
    "wof:placetype":"locality"
},
  "geometry": {"coordinates":[114.43831000000002,25.81025],"type":"Point"}
}