{
  "type": "Feature",
  "properties": {
    "gn:admin1_code":"3.0",
    "gn:asciiname":"Zhuanwuli",
    "gn:country_code":"CN",
    "gn:dem":260,
    "gn:feature_class":"P",
    "gn:feature_code":"PPL",
    "gn:name":"Zhuanwuli",
    "gn:population":0,
    "gn:timezone":"Asia/Shanghai",
    "iso:country":"CN",
    "name:und_x_variant":[
        "\u7816\u5c4b\u91cc"
    ],
    "wof:name":"Zhuanwuli",
    "wof:placetype":"locality"
},
  "geometry": {"coordinates":[114.38676,28.89228],"type":"Point"}
}