{
  "type": "Feature",
  "properties": {
    "gn:admin1_code":"16.0",
    "gn:asciiname":"Nageng",
    "gn:country_code":"CN",
    "gn:dem":523,
    "gn:feature_class":"P",
    "gn:feature_code":"PPL",
    "gn:name":"Nageng",
    "gn:population":0,
    "gn:timezone":"Asia/Shanghai",
    "iso:country":"CN",
    "name:zho_x_preferred":[
        "\u90a3\u66f4"
    ],
    "wof:name":"Nageng",
    "wof:placetype":"locality"
},
  "geometry": {"coordinates":[107.25700000000001,24.7546],"type":"Point"}
}