{
  "type": "Feature",
  "properties": {
    "gn:admin1_code":"08",
    "gn:asciiname":"Shitouhe",
    "gn:country_code":"CN",
    "gn:dem":208,
    "gn:feature_class":"P",
    "gn:feature_code":"PPLA4",
    "gn:name":"Shitouhe",
    "gn:population":0,
    "gn:timezone":"Asia/Shanghai",
    "iso:country":"CN",
    "name:und_x_variant":[
        "Shitouhezi",
        "Shitouhe Zhen"
    ],
    "name:zho_x_preferred":[
        "\u77f3\u5934\u6cb3"
    ],
    "name:zho_x_variant":[
        "\u77f3\u5934\u6cb3\u9547"
    ],
    "wof:name":"Shitouhe",
    "wof:placetype":"locality"
},
  "geometry": {"coordinates":[130.88813999999999,46.11694],"type":"Point"}
}