{
  "type": "Feature",
  "properties": {
    "gn:admin1_code":"14.0",
    "gn:asciiname":"Jiangde",
    "gn:country_code":"CN",
    "gn:dem":4547,
    "gn:feature_class":"P",
    "gn:feature_code":"PPL",
    "gn:name":"Jiangde",
    "gn:population":0,
    "gn:timezone":"Asia/Urumqi",
    "iso:country":"CN",
    "name:zho_x_preferred":[
        "\u8bb2\u7684"
    ],
    "wof:name":"Jiangde",
    "wof:placetype":"locality"
},
  "geometry": {"coordinates":[91.80815,31.56998],"type":"Point"}
}