{
  "type": "Feature",
  "properties": {
    "gn:admin1_code":"15.0",
    "gn:asciiname":"Xiaomayuan",
    "gn:country_code":"CN",
    "gn:dem":1544,
    "gn:feature_class":"P",
    "gn:feature_code":"PPL",
    "gn:name":"Xiaomayuan",
    "gn:population":0,
    "gn:timezone":"Asia/Shanghai",
    "iso:country":"CN",
    "name:und_x_variant":[
        "\u8096\u9a6c\u586c"
    ],
    "wof:name":"Xiaomayuan",
    "wof:placetype":"locality"
},
  "geometry": {"coordinates":[107.14284000000001,36.21771],"type":"Point"}
}