{
  "type": "Feature",
  "properties": {
    "gn:admin1_code":"25",
    "gn:asciiname":"Xiaoshanzi",
    "gn:country_code":"CN",
    "gn:dem":40,
    "gn:feature_class":"P",
    "gn:feature_code":"PPL",
    "gn:name":"Xiaoshanzi",
    "gn:population":0,
    "gn:timezone":"Asia/Shanghai",
    "iso:country":"CN",
    "name:zho_x_preferred":[
        "\u5c0f\u5c71\u5b50"
    ],
    "wof:name":"Xiaoshanzi",
    "wof:placetype":"locality"
},
  "geometry": {"coordinates":[117.59699999999999,34.529],"type":"Point"}
}