{
  "type": "Feature",
  "properties": {
    "gn:admin1_code":"30.0",
    "gn:asciiname":"Huabicun",
    "gn:country_code":"CN",
    "gn:dem":14,
    "gn:feature_class":"P",
    "gn:feature_code":"PPL",
    "gn:name":"Huabicun",
    "gn:population":0,
    "gn:timezone":"Asia/Shanghai",
    "iso:country":"CN",
    "name:zho_x_preferred":[
        "\u534e\u8f9f\u6751"
    ],
    "wof:name":"Huabicun",
    "wof:placetype":"locality"
},
  "geometry": {"coordinates":[116.29581,23.03049],"type":"Point"}
}