{
  "type": "Feature",
  "properties": {
    "gn:admin1_code":"15.0",
    "gn:asciiname":"Zengjiajing",
    "gn:country_code":"CN",
    "gn:dem":1654,
    "gn:feature_class":"P",
    "gn:feature_code":"PPL",
    "gn:name":"Zengjiajing",
    "gn:population":0,
    "gn:timezone":"Asia/Shanghai",
    "iso:country":"CN",
    "name:zho_x_preferred":[
        "\u66fe\u5bb6\u4e95"
    ],
    "wof:name":"Zengjiajing",
    "wof:placetype":"locality"
},
  "geometry": {"coordinates":[103.926,37.56],"type":"Point"}
}