{
  "type": "Feature",
  "properties": {
    "gn:admin1_code":"32.0",
    "gn:asciiname":"Pingzitou",
    "gn:country_code":"CN",
    "gn:dem":1149,
    "gn:feature_class":"P",
    "gn:feature_code":"PPL",
    "gn:name":"Pingzitou",
    "gn:population":0,
    "gn:timezone":"Asia/Shanghai",
    "iso:country":"CN",
    "name:zho_x_preferred":[
        "\u576a\u5b50\u5934"
    ],
    "wof:name":"Pingzitou",
    "wof:placetype":"locality"
},
  "geometry": {"coordinates":[105.688,28.2199],"type":"Point"}
}