{
  "type": "Feature",
  "properties": {
    "gn:admin1_code":"8.0",
    "gn:asciiname":"Jinshan Wudui",
    "gn:country_code":"CN",
    "gn:dem":306,
    "gn:feature_class":"P",
    "gn:feature_code":"PPLF",
    "gn:name":"Jinshan Wudui",
    "gn:population":0,
    "gn:timezone":"Asia/Shanghai",
    "iso:country":"CN",
    "name:zho_x_preferred":[
        "\u91d1\u5c71\u4e94\u961f"
    ],
    "wof:name":"Jinshan Wudui",
    "wof:placetype":"locality"
},
  "geometry": {"coordinates":[125.68707999999999,49.67381],"type":"Point"}
}