{
  "type": "Feature",
  "properties": {
    "gn:admin1_code":"32.0",
    "gn:asciiname":"Yinshanqiao",
    "gn:country_code":"CN",
    "gn:dem":462,
    "gn:feature_class":"P",
    "gn:feature_code":"PPL",
    "gn:name":"Yinshanqiao",
    "gn:population":0,
    "gn:timezone":"Asia/Shanghai",
    "iso:country":"CN",
    "name:zho_x_preferred":[
        "\u9634\u5c71\u6865"
    ],
    "wof:name":"Yinshanqiao",
    "wof:placetype":"locality"
},
  "geometry": {"coordinates":[104.407,29.8603],"type":"Point"}
}