{
  "type": "Feature",
  "properties": {
    "gn:admin1_code":"12.0",
    "gn:asciiname":"Xigouli",
    "gn:country_code":"CN",
    "gn:dem":245,
    "gn:feature_class":"P",
    "gn:feature_code":"PPL",
    "gn:name":"Xigouli",
    "gn:population":0,
    "gn:timezone":"Asia/Shanghai",
    "iso:country":"CN",
    "name:zho_x_preferred":[
        "Xigouli"
    ],
    "name:zho_x_variant":[
        "\u897f\u6c9f\u674e"
    ],
    "wof:name":"Xigouli",
    "wof:placetype":"locality"
},
  "geometry": {"coordinates":[114.66177999999999,29.93442000000001],"type":"Point"}
}