{
  "type": "Feature",
  "properties": {
    "gn:admin1_code":"2.0",
    "gn:asciiname":"Tongtian",
    "gn:country_code":"CN",
    "gn:dem":550,
    "gn:feature_class":"P",
    "gn:feature_code":"PPL",
    "gn:name":"Tongtian",
    "gn:population":0,
    "gn:timezone":"Asia/Shanghai",
    "iso:country":"CN",
    "name:deu_x_preferred":[
        "Tongtian"
    ],
    "name:zho_x_preferred":[
        "\u540c\u7530"
    ],
    "wof:name":"Tongtian",
    "wof:placetype":"locality"
},
  "geometry": {"coordinates":[120.59793000000001,29.11387],"type":"Point"}
}