{
  "type": "Feature",
  "properties": {
    "gn:admin1_code":"2.0",
    "gn:asciiname":"Tongtian",
    "gn:country_code":"CN",
    "gn:dem":550,
    "gn:feature_class":"P",
    "gn:feature_code":"PPL",
    "gn:name":"Tongtian",
    "gn:population":0,
    "gn:timezone":"Asia/Shanghai",
    "iso:country":"CN",
    "name:ara_x_preferred":[
        "\u062a\u0648\u0646\u063a\u062a\u064a\u0627\u0646"
    ],
    "name:ben_x_preferred":[
        "\u099f\u0982\u099f\u09bf\u09af\u09bc\u09be\u09a8"
    ],
    "name:deu_x_preferred":[
        "Zhi Qu"
    ],
    "name:deu_x_variant":[
        "Tongtian"
    ],
    "name:ell_x_preferred":[
        "\u03a4\u03cc\u03b3\u03ba\u03c4\u03b9\u03b1\u03bd"
    ],
    "name:fas_x_preferred":[
        "\u062a\u0648\u0646\u06af\u062a\u06cc\u0627\u0646"
    ],
    "name:heb_x_preferred":[
        "\u05d8\u05d5\u05e0\u05d2\u05d8\u05d9\u05d0\u05df"
    ],
    "name:hin_x_preferred":[
        "\u091f\u094b\u0902\u0917\u091f\u093f\u092f\u0928"
    ],
    "name:hun_x_preferred":[
        "Tongtian"
    ],
    "name:ind_x_preferred":[
        "Tongtian"
    ],
    "name:ita_x_preferred":[
        "Tongtian"
    ],
    "name:jpn_x_preferred":[
        " \u901a\u5929\u6cb3"
    ],
    "name:kor_x_preferred":[
        "\ud1b5\ucc9c"
    ],
    "name:nld_x_preferred":[
        "Tongtian"
    ],
    "name:pol_x_preferred":[
        "Tongtian"
    ],
    "name:por_x_preferred":[
        "Tongtian"
    ],
    "name:rus_x_preferred":[
        "\u0440\u0435\u043a\u0430 \u0422\u0443\u043d\u0442\u044f\u043d\u044c"
    ],
    "name:spa_x_preferred":[
        "Tongtian"
    ],
    "name:swe_x_preferred":[
        "Tongtian"
    ],
    "name:tur_x_preferred":[
        "Tongtian"
    ],
    "name:ukr_x_preferred":[
        "\u0422\u043e\u043d\u0433\u0442\u0456\u0430\u043d"
    ],
    "name:urd_x_preferred":[
        "\u0679\u0648\u0646\u06af\u0679\u06cc\u0627\u0646"
    ],
    "name:vie_x_preferred":[
        "S\u00f4ng Th\u00f4ng Thi\u00ean"
    ],
    "name:zho_x_preferred":[
        "\u540c\u7530"
    ],
    "wof:name":"Tongtian",
    "wof:placetype":"locality"
},
  "geometry": {"coordinates":[120.59793000000001,29.11387],"type":"Point"}
}