{
  "type": "Feature",
  "properties": {
    "gn:admin1_code":"15.0",
    "gn:asciiname":"Yanjiagou",
    "gn:country_code":"CN",
    "gn:dem":1826,
    "gn:feature_class":"P",
    "gn:feature_code":"PPL",
    "gn:name":"Yanjiagou",
    "gn:population":0,
    "gn:timezone":"Asia/Shanghai",
    "iso:country":"CN",
    "name:und_x_variant":[
        "\u960e\u5bb6\u6c9f"
    ],
    "wof:name":"Yanjiagou",
    "wof:placetype":"locality"
},
  "geometry": {"coordinates":[105.56755,35.65944000000001],"type":"Point"}
}