{
  "type": "Feature",
  "properties": {
    "gn:admin1_code":"9.0",
    "gn:asciiname":"Yangwafang",
    "gn:country_code":"CN",
    "gn:dem":68,
    "gn:feature_class":"P",
    "gn:feature_code":"PPL",
    "gn:name":"Yangwafang",
    "gn:population":0,
    "gn:timezone":"Asia/Shanghai",
    "iso:country":"CN",
    "name:zho_x_preferred":[
        "\u6768\u74e6\u574a"
    ],
    "wof:name":"Yangwafang",
    "wof:placetype":"locality"
},
  "geometry": {"coordinates":[115.13493,32.0031],"type":"Point"}
}