{
  "type": "Feature",
  "properties": {
    "gn:admin1_code":"18.0",
    "gn:asciiname":"Yinjiangping",
    "gn:country_code":"CN",
    "gn:dem":735,
    "gn:feature_class":"P",
    "gn:feature_code":"PPL",
    "gn:name":"Yinjiangping",
    "gn:population":0,
    "gn:timezone":"Asia/Shanghai",
    "iso:country":"CN",
    "name:zho_x_preferred":[
        "\u5370\u6c5f\u576a"
    ],
    "wof:name":"Yinjiangping",
    "wof:placetype":"locality"
},
  "geometry": {"coordinates":[108.711,27.5889],"type":"Point"}
}