{
  "type": "Feature",
  "properties": {
    "gn:admin1_code":"13.0",
    "gn:asciiname":"Yigezuoyi",
    "gn:country_code":"CN",
    "gn:dem":909,
    "gn:feature_class":"P",
    "gn:feature_code":"PPL",
    "gn:name":"Yigezuoyi",
    "gn:population":0,
    "gn:timezone":"Asia/Urumqi",
    "iso:country":"CN",
    "name:zho_x_preferred":[
        "\u4f9d\u683c\u4f50\u4f9d"
    ],
    "wof:name":"Yigezuoyi",
    "wof:placetype":"locality"
},
  "geometry": {"coordinates":[85.35864000000002,40.72138],"type":"Point"}
}