{
  "type": "Feature",
  "properties": {
    "gn:admin1_code":"12",
    "gn:asciiname":"Wudian",
    "gn:cc2":"CN",
    "gn:country_code":"CN",
    "gn:dem":54,
    "gn:feature_class":"P",
    "gn:feature_code":"PPL",
    "gn:name":"Wudian",
    "gn:population":0,
    "gn:timezone":"Asia/Shanghai",
    "iso:country":"CN",
    "name:und_x_variant":[
        "Wu-chia-tien",
        "Wudian",
        "\u5434\u5bb6\u5e97"
    ],
    "wof:name":"Wudian",
    "wof:placetype":"locality"
},
  "geometry": {"coordinates":[113.83750000000001,31.17722],"type":"Point"}
}