{
  "type": "Feature",
  "properties": {
    "gn:admin1_code":"5.0",
    "gn:asciiname":"Shangdonggou",
    "gn:country_code":"CN",
    "gn:dem":311,
    "gn:feature_class":"P",
    "gn:feature_code":"PPL",
    "gn:name":"Shangdonggou",
    "gn:population":0,
    "gn:timezone":"Asia/Shanghai",
    "iso:country":"CN",
    "name:und_x_variant":[
        "\u4e0a\u4e1c\u6c9f"
    ],
    "wof:name":"Shangdonggou",
    "wof:placetype":"locality"
},
  "geometry": {"coordinates":[129.39295000000001,42.93741],"type":"Point"}
}