{
  "type": "Feature",
  "properties": {
    "gn:admin1_code":"03",
    "gn:asciiname":"Ganfang",
    "gn:country_code":"CN",
    "gn:dem":156,
    "gn:feature_class":"P",
    "gn:feature_code":"PPLA4",
    "gn:name":"Ganfang",
    "gn:population":0,
    "gn:timezone":"Asia/Shanghai",
    "iso:country":"CN",
    "name:und_x_variant":[
        "Kan-fang",
        "Ganfang",
        "\u7518\u574a",
        "Ganfang Xiang",
        "\u7518\u574a\u4e61"
    ],
    "wof:name":"Ganfang",
    "wof:placetype":"locality"
},
  "geometry": {"coordinates":[114.86605,28.64295],"type":"Point"}
}