{
  "type": "Feature",
  "properties": {
    "gn:admin1_code":"22.0",
    "gn:asciiname":"Chengjiayingcun",
    "gn:country_code":"CN",
    "gn:dem":507,
    "gn:feature_class":"P",
    "gn:feature_code":"PPL",
    "gn:name":"Chengjiayingcun",
    "gn:population":0,
    "gn:timezone":"Asia/Shanghai",
    "iso:country":"CN",
    "name:zho_x_preferred":[
        "\u7a0b\u5bb6\u8425\u6751"
    ],
    "wof:name":"Chengjiayingcun",
    "wof:placetype":"locality"
},
  "geometry": {"coordinates":[115.95117999999999,40.40461],"type":"Point"}
}