{
  "type": "Feature",
  "properties": {
    "gn:admin1_code":"16.0",
    "gn:asciiname":"Langdan",
    "gn:country_code":"CN",
    "gn:dem":927,
    "gn:feature_class":"P",
    "gn:feature_code":"PPL",
    "gn:name":"Langdan",
    "gn:population":0,
    "gn:timezone":"Asia/Shanghai",
    "iso:country":"CN",
    "name:zho_x_preferred":[
        "\u6d6a\u65e6"
    ],
    "wof:name":"Langdan",
    "wof:placetype":"locality"
},
  "geometry": {"coordinates":[107.136,25.3123],"type":"Point"}
}