{
  "type": "Feature",
  "properties": {
    "gn:admin1_code":"32.0",
    "gn:asciiname":"Ruifeng",
    "gn:country_code":"CN",
    "gn:dem":409,
    "gn:feature_class":"P",
    "gn:feature_code":"PPL",
    "gn:name":"Ruifeng",
    "gn:population":0,
    "gn:timezone":"Asia/Shanghai",
    "iso:country":"CN",
    "name:zho_x_preferred":[
        "\u745e\u5cf0"
    ],
    "wof:name":"Ruifeng",
    "wof:placetype":"locality"
},
  "geometry": {"coordinates":[106.074,28.858],"type":"Point"}
}