{
  "type": "Feature",
  "properties": {
    "gn:admin1_code":"29.0",
    "gn:asciiname":"Yantoushang",
    "gn:country_code":"CN",
    "gn:dem":2046,
    "gn:feature_class":"P",
    "gn:feature_code":"PPL",
    "gn:name":"Yantoushang",
    "gn:population":0,
    "gn:timezone":"Asia/Shanghai",
    "iso:country":"CN",
    "name:und_x_variant":[
        "\u5ca9\u5934\u4e0a"
    ],
    "wof:name":"Yantoushang",
    "wof:placetype":"locality"
},
  "geometry": {"coordinates":[103.54685000000001,25.85662],"type":"Point"}
}