{
  "type": "Feature",
  "properties": {
    "gn:admin1_code":"26.0",
    "gn:asciiname":"Gongjiawan",
    "gn:country_code":"CN",
    "gn:dem":605,
    "gn:feature_class":"P",
    "gn:feature_code":"PPL",
    "gn:name":"Gongjiawan",
    "gn:population":0,
    "gn:timezone":"Asia/Shanghai",
    "iso:country":"CN",
    "name:und_x_variant":[
        "\u9f9a\u5bb6\u6e7e"
    ],
    "wof:name":"Gongjiawan",
    "wof:placetype":"locality"
},
  "geometry": {"coordinates":[107.59375,33.14017],"type":"Point"}
}