{
  "type": "Feature",
  "properties": {
    "gn:admin1_code":"3",
    "gn:asciiname":"Wuxing Zonghe Kenzhichang",
    "gn:country_code":"CN",
    "gn:dem":14,
    "gn:feature_class":"P",
    "gn:feature_code":"PPLF",
    "gn:name":"Wuxing Zonghe Kenzhichang",
    "gn:population":0,
    "gn:timezone":"Asia/Shanghai",
    "iso:country":"CN",
    "name:und_x_variant":[
        "\u4e94\u661f\u7efc\u5408\u57a6\u6b96\u573a",
        "Wuxingzonghekenzhichang"
    ],
    "wof:name":"Wuxing Zonghe Kenzhichang",
    "wof:placetype":"locality"
},
  "geometry": {"coordinates":[116.27616999999999,28.78025],"type":"Point"}
}