{
  "type": "Feature",
  "properties": {
    "gn:admin1_code":"15.0",
    "gn:asciiname":"Dadayao",
    "gn:country_code":"CN",
    "gn:dem":2168,
    "gn:feature_class":"P",
    "gn:feature_code":"PPL",
    "gn:name":"Dadayao",
    "gn:population":0,
    "gn:timezone":"Asia/Shanghai",
    "iso:country":"CN",
    "name:zho_x_preferred":[
        "\u9791\u977c\u7a91"
    ],
    "wof:name":"Dadayao",
    "wof:placetype":"locality"
},
  "geometry": {"coordinates":[104.483,36.0576],"type":"Point"}
}