{
  "type": "Feature",
  "properties": {
    "gn:admin1_code":"15.0",
    "gn:asciiname":"Fangmatan",
    "gn:country_code":"CN",
    "gn:dem":1731,
    "gn:feature_class":"P",
    "gn:feature_code":"PPL",
    "gn:name":"Fangmatan",
    "gn:population":0,
    "gn:timezone":"Asia/Shanghai",
    "iso:country":"CN",
    "name:zho_x_preferred":[
        "\u653e\u9a6c\u6ee9"
    ],
    "wof:name":"Fangmatan",
    "wof:placetype":"locality"
},
  "geometry": {"coordinates":[106.09999999999999,34.4094],"type":"Point"}
}