{
  "type": "Feature",
  "properties": {
    "gn:admin1_code":"24",
    "gn:asciiname":"Shentangdi",
    "gn:cc2":"CN",
    "gn:country_code":"CN",
    "gn:dem":912,
    "gn:feature_class":"P",
    "gn:feature_code":"PPL",
    "gn:name":"Shentangdi",
    "gn:population":0,
    "gn:timezone":"Asia/Shanghai",
    "iso:country":"CN",
    "name:und_x_variant":[
        "Shen-t\u2019ang-ti",
        "Shentangdi"
    ],
    "wof:name":"Shentangdi",
    "wof:placetype":"locality"
},
  "geometry": {"coordinates":[111.9225,37.40417],"type":"Point"}
}