{
  "type": "Feature",
  "properties": {
    "gn:admin1_code":"3.0",
    "gn:asciiname":"Yecunwu",
    "gn:country_code":"CN",
    "gn:dem":133,
    "gn:feature_class":"P",
    "gn:feature_code":"PPL",
    "gn:name":"Yecunwu",
    "gn:population":0,
    "gn:timezone":"Asia/Shanghai",
    "iso:country":"CN",
    "name:zho_x_preferred":[
        "\u53f6\u6751\u575e"
    ],
    "wof:name":"Yecunwu",
    "wof:placetype":"locality"
},
  "geometry": {"coordinates":[118.22007000000001,28.72123],"type":"Point"}
}