{
  "type": "Feature",
  "properties": {
    "gn:admin1_code":"29.0",
    "gn:asciiname":"Niebiezhai",
    "gn:country_code":"CN",
    "gn:dem":1850,
    "gn:feature_class":"P",
    "gn:feature_code":"PPL",
    "gn:name":"Niebiezhai",
    "gn:population":0,
    "gn:timezone":"Asia/Shanghai",
    "iso:country":"CN",
    "name:zho_x_preferred":[
        "\u4e5c\u522b\u5be8"
    ],
    "wof:name":"Niebiezhai",
    "wof:placetype":"locality"
},
  "geometry": {"coordinates":[99.983,23.3701],"type":"Point"}
}