{
  "type": "Feature",
  "properties": {
    "gn:admin1_code":"13.0",
    "gn:asciiname":"Egiztobe",
    "gn:country_code":"CN",
    "gn:dem":523,
    "gn:feature_class":"P",
    "gn:feature_code":"PPLA4",
    "gn:name":"Egiztobe",
    "gn:population":0,
    "gn:timezone":"Asia/Urumqi",
    "iso:country":"CN",
    "name:kaz_x_preferred":[
        "\u06d5\u06af\u0649\u0632\u062a\u0648\u0628\u06d5 \u0627\u06cb\u0649\u0644\u0649"
    ],
    "name:uig_x_preferred":[
        "Egizt\u0275b\u0259"
    ],
    "name:uig_x_variant":[
        "\u00c9gizt\u00f6be",
        "\u0626\u06d0\u06af\u0649\u0632\u062a\u06c6\u0628\u06d5",
        "\u042d\u0433\u0438\u0437\u0442\u04e9\u0431\u04d9",
        "\u0626\u06d0\u06af\u0649\u0632\u062a\u06c6\u0628\u06d5 \u064a\u06d0\u0632\u0649\u0633\u0649"
    ],
    "name:und_x_variant":[
        "Egiztobe Xiang",
        "Egiztobe",
        "Yegezituobie",
        "Yegezituobie Xiang"
    ],
    "name:zho_x_preferred":[
        "\u4e5f\u683c\u5b5c\u6258\u522b"
    ],
    "name:zho_x_variant":[
        "\u4e5f\u683c\u5b5c\u6258\u522b\u4e61"
    ],
    "wof:name":"Egiztobe",
    "wof:placetype":"locality"
},
  "geometry": {"coordinates":[87.00466,47.85938],"type":"Point"}
}