{
  "type": "Feature",
  "properties": {
    "gn:admin1_code":"3",
    "gn:asciiname":"Jieshang",
    "gn:country_code":"CN",
    "gn:dem":356,
    "gn:feature_class":"P",
    "gn:feature_code":"PPL",
    "gn:name":"Jieshang",
    "gn:population":0,
    "gn:timezone":"Asia/Shanghai",
    "iso:country":"CN",
    "name:und_x_variant":[
        "\u754c\u4e0a"
    ],
    "wof:name":"Jieshang",
    "wof:placetype":"locality"
},
  "geometry": {"coordinates":[116.10986,27.13004],"type":"Point"}
}