{
  "type": "Feature",
  "properties": {
    "gn:admin1_code":"25.0",
    "gn:asciiname":"Dujiayacun",
    "gn:country_code":"CN",
    "gn:dem":92,
    "gn:feature_class":"P",
    "gn:feature_code":"PPL",
    "gn:name":"Dujiayacun",
    "gn:population":0,
    "gn:timezone":"Asia/Shanghai",
    "iso:country":"CN",
    "name:zho_x_preferred":[
        "\u675c\u5bb6\u5d16\u6751"
    ],
    "wof:name":"Dujiayacun",
    "wof:placetype":"locality"
},
  "geometry": {"coordinates":[121.13151000000001,37.37579],"type":"Point"}
}