{
  "type": "Feature",
  "properties": {
    "gn:admin1_code":"15.0",
    "gn:asciiname":"Leiyeka",
    "gn:country_code":"CN",
    "gn:dem":2765,
    "gn:feature_class":"P",
    "gn:feature_code":"PPL",
    "gn:name":"Leiyeka",
    "gn:population":0,
    "gn:timezone":"Asia/Shanghai",
    "iso:country":"CN",
    "name:und_x_variant":[
        "\u96f7\u4e5f\u5361"
    ],
    "wof:name":"Leiyeka",
    "wof:placetype":"locality"
},
  "geometry": {"coordinates":[103.59997,34.04263],"type":"Point"}
}