{
  "type": "Feature",
  "properties": {
    "gn:admin1_code":"7.0",
    "gn:asciiname":"Qianping",
    "gn:country_code":"CN",
    "gn:dem":577,
    "gn:feature_class":"P",
    "gn:feature_code":"PPL",
    "gn:name":"Qianping",
    "gn:population":0,
    "gn:timezone":"Asia/Shanghai",
    "iso:country":"CN",
    "name:zho_x_preferred":[
        "\u524d\u576a"
    ],
    "wof:name":"Qianping",
    "wof:placetype":"locality"
},
  "geometry": {"coordinates":[118.84235,26.07758],"type":"Point"}
}