{
  "type": "Feature",
  "properties": {
    "gn:admin1_code":"33",
    "gn:asciiname":"Dachang",
    "gn:country_code":"CN",
    "gn:dem":151,
    "gn:feature_class":"P",
    "gn:feature_code":"PPLA4",
    "gn:name":"Dachang",
    "gn:population":0,
    "gn:timezone":"Asia/Shanghai",
    "iso:country":"CN",
    "name:und_x_variant":[
        "Ta-ch\u2019ang",
        "Dachang Zhen",
        "Ta-ch\u2019ang-chen",
        "Dachang"
    ],
    "name:zho_x_preferred":[
        "\u5927\u660c"
    ],
    "name:zho_x_variant":[
        "\u5927\u660c\u9547"
    ],
    "wof:name":"Dachang",
    "wof:placetype":"locality"
},
  "geometry": {"coordinates":[109.8021,31.26861],"type":"Point"}
}