{
  "type": "Feature",
  "properties": {
    "gn:admin1_code":"3.0",
    "gn:asciiname":"Huoshaodou",
    "gn:country_code":"CN",
    "gn:dem":217,
    "gn:feature_class":"P",
    "gn:feature_code":"PPL",
    "gn:name":"Huoshaodou",
    "gn:population":0,
    "gn:timezone":"Asia/Shanghai",
    "iso:country":"CN",
    "name:und_x_variant":[
        "\u706b\u70e7\u515c"
    ],
    "wof:name":"Huoshaodou",
    "wof:placetype":"locality"
},
  "geometry": {"coordinates":[115.73936,25.99614],"type":"Point"}
}