{
  "type": "Feature",
  "properties": {
    "gn:admin1_code":"10",
    "gn:asciiname":"Pipotun",
    "gn:country_code":"CN",
    "gn:dem":25,
    "gn:feature_class":"P",
    "gn:feature_code":"PPL",
    "gn:name":"Pipotun",
    "gn:population":0,
    "gn:timezone":"Asia/Shanghai",
    "iso:country":"CN",
    "name:zho_x_preferred":[
        "\u76ae\u5a46\u5c6f"
    ],
    "wof:name":"Pipotun",
    "wof:placetype":"locality"
},
  "geometry": {"coordinates":[116.15558,37.52036],"type":"Point"}
}