{
  "type": "Feature",
  "properties": {
    "gn:admin1_code":"16.0",
    "gn:asciiname":"Runtun",
    "gn:country_code":"CN",
    "gn:dem":746,
    "gn:feature_class":"P",
    "gn:feature_code":"PPL",
    "gn:name":"Runtun",
    "gn:population":0,
    "gn:timezone":"Asia/Shanghai",
    "iso:country":"CN",
    "name:zho_x_preferred":[
        "\u6da6\u5c6f"
    ],
    "wof:name":"Runtun",
    "wof:placetype":"locality"
},
  "geometry": {"coordinates":[106.316,23.077],"type":"Point"}
}