{
  "type": "Feature",
  "properties": {
    "gn:admin1_code":"14.0",
    "gn:asciiname":"Galung",
    "gn:country_code":"CN",
    "gn:dem":4392,
    "gn:feature_class":"P",
    "gn:feature_code":"PPL",
    "gn:name":"Galung",
    "gn:population":0,
    "gn:timezone":"Asia/Urumqi",
    "iso:country":"CN",
    "name:bod_x_preferred":[
        "Galung"
    ],
    "name:zho_x_preferred":[
        "Galong"
    ],
    "name:zho_x_variant":[
        "\u5676\u9686"
    ],
    "wof:name":"Galung",
    "wof:placetype":"locality"
},
  "geometry": {"coordinates":[93.70399999999999,32.104],"type":"Point"}
}