{
  "type": "Feature",
  "properties": {
    "gn:admin1_code":"11.0",
    "gn:asciiname":"Fanmu'ao",
    "gn:country_code":"CN",
    "gn:dem":407,
    "gn:feature_class":"P",
    "gn:feature_code":"PPL",
    "gn:name":"Fanmu\u2019ao",
    "gn:population":0,
    "gn:timezone":"Asia/Shanghai",
    "iso:country":"CN",
    "name:und_x_variant":[
        "Fanmu\u2019ao"
    ],
    "name:zho_x_preferred":[
        "\u996d\u6728\u5773"
    ],
    "wof:name":"Fanmu'ao",
    "wof:placetype":"locality"
},
  "geometry": {"coordinates":[109.61615,27.06726],"type":"Point"}
}