{
  "type": "Feature",
  "properties": {
    "gn:admin1_code":"32.0",
    "gn:asciiname":"Sekema",
    "gn:country_code":"CN",
    "gn:dem":3821,
    "gn:feature_class":"P",
    "gn:feature_code":"PPL",
    "gn:name":"Sekema",
    "gn:population":0,
    "gn:timezone":"Asia/Shanghai",
    "iso:country":"CN",
    "name:zho_x_preferred":[
        "\u8272\u67ef\u9a6c"
    ],
    "wof:name":"Sekema",
    "wof:placetype":"locality"
},
  "geometry": {"coordinates":[100.791,31.7855],"type":"Point"}
}