{
  "type": "Feature",
  "properties": {
    "gn:admin1_code":"29.0",
    "gn:asciiname":"Dongpodian",
    "gn:country_code":"CN",
    "gn:dem":2630,
    "gn:feature_class":"P",
    "gn:feature_code":"PPL",
    "gn:name":"Dongpodian",
    "gn:population":0,
    "gn:timezone":"Asia/Shanghai",
    "iso:country":"CN",
    "name:zho_x_preferred":[
        "\u4e1c\u5761\u7538"
    ],
    "wof:name":"Dongpodian",
    "wof:placetype":"locality"
},
  "geometry": {"coordinates":[100.518,27.548],"type":"Point"}
}