{
  "type": "Feature",
  "properties": {
    "gn:admin1_code":"16.0",
    "gn:asciiname":"Dingge",
    "gn:country_code":"CN",
    "gn:dem":1146,
    "gn:feature_class":"P",
    "gn:feature_code":"PPL",
    "gn:name":"Dingge",
    "gn:population":0,
    "gn:timezone":"Asia/Shanghai",
    "iso:country":"CN",
    "name:zho_x_preferred":[
        "\u5b9a\u683c"
    ],
    "wof:name":"Dingge",
    "wof:placetype":"locality"
},
  "geometry": {"coordinates":[105.867,23.3405],"type":"Point"}
}