{
  "type": "Feature",
  "properties": {
    "gn:admin1_code":"4.0",
    "gn:asciiname":"Yuzhuang",
    "gn:country_code":"CN",
    "gn:dem":13,
    "gn:feature_class":"P",
    "gn:feature_code":"PPL",
    "gn:name":"Yuzhuang",
    "gn:population":0,
    "gn:timezone":"Asia/Shanghai",
    "iso:country":"CN",
    "name:zho_x_preferred":[
        "\u90c1\u5e84"
    ],
    "wof:name":"Yuzhuang",
    "wof:placetype":"locality"
},
  "geometry": {"coordinates":[118.82899999999999,33.6171],"type":"Point"}
}