{
  "type": "Feature",
  "properties": {
    "gn:admin1_code":"29.0",
    "gn:asciiname":"Salidu",
    "gn:country_code":"CN",
    "gn:dem":2381,
    "gn:feature_class":"P",
    "gn:feature_code":"PPL",
    "gn:name":"Salidu",
    "gn:population":0,
    "gn:timezone":"Asia/Shanghai",
    "iso:country":"CN",
    "name:zho_x_preferred":[
        "\u6d12\u5229\u5835"
    ],
    "wof:name":"Salidu",
    "wof:placetype":"locality"
},
  "geometry": {"coordinates":[102.087,25.4782],"type":"Point"}
}