{
  "type": "Feature",
  "properties": {
    "gn:admin1_code":"8.0",
    "gn:asciiname":"Xiangjiatun",
    "gn:country_code":"CN",
    "gn:dem":184,
    "gn:feature_class":"P",
    "gn:feature_code":"PPL",
    "gn:name":"Xiangjiatun",
    "gn:population":0,
    "gn:timezone":"Asia/Shanghai",
    "iso:country":"CN",
    "name:zho_x_preferred":[
        "\u9879\u5bb6\u5c6f"
    ],
    "wof:name":"Xiangjiatun",
    "wof:placetype":"locality"
},
  "geometry": {"coordinates":[127.09788,46.97918],"type":"Point"}
}