{
  "type": "Feature",
  "properties": {
    "gn:admin1_code":"3.0",
    "gn:asciiname":"Fuyukeng",
    "gn:country_code":"CN",
    "gn:dem":758,
    "gn:feature_class":"P",
    "gn:feature_code":"PPL",
    "gn:name":"Fuyukeng",
    "gn:population":0,
    "gn:timezone":"Asia/Shanghai",
    "iso:country":"CN",
    "name:und_x_variant":[
        "\u5bcc\u88d5\u5751"
    ],
    "wof:name":"Fuyukeng",
    "wof:placetype":"locality"
},
  "geometry": {"coordinates":[114.38813,28.40628],"type":"Point"}
}