{
  "type": "Feature",
  "properties": {
    "gn:admin1_code":"32.0",
    "gn:asciiname":"Se'erduo",
    "gn:country_code":"CN",
    "gn:dem":2554,
    "gn:feature_class":"P",
    "gn:feature_code":"PPL",
    "gn:name":"Se\u2019erduo",
    "gn:population":0,
    "gn:timezone":"Asia/Shanghai",
    "iso:country":"CN",
    "name:und_x_variant":[
        "Se\u2019erduo"
    ],
    "name:zho_x_preferred":[
        "\u8272\u5c14\u591a"
    ],
    "wof:name":"Se'erduo",
    "wof:placetype":"locality"
},
  "geometry": {"coordinates":[103.789,31.8567],"type":"Point"}
}