{
  "type": "Feature",
  "properties": {
    "gn:admin1_code":"3.0",
    "gn:asciiname":"Panxicun",
    "gn:country_code":"CN",
    "gn:dem":53,
    "gn:feature_class":"P",
    "gn:feature_code":"PPL",
    "gn:name":"Panxicun",
    "gn:population":0,
    "gn:timezone":"Asia/Shanghai",
    "iso:country":"CN",
    "name:und_x_variant":[
        "\u6cee\u6eaa\u6751"
    ],
    "wof:name":"Panxicun",
    "wof:placetype":"locality"
},
  "geometry": {"coordinates":[116.89183,28.54671],"type":"Point"}
}