{
  "type": "Feature",
  "properties": {
    "gn:admin1_code":"11.0",
    "gn:asciiname":"Tangjiaping",
    "gn:country_code":"CN",
    "gn:dem":838,
    "gn:feature_class":"P",
    "gn:feature_code":"PPL",
    "gn:name":"Tangjiaping",
    "gn:population":0,
    "gn:timezone":"Asia/Shanghai",
    "iso:country":"CN",
    "name:zho_x_preferred":[
        "Tangjiaping"
    ],
    "name:zho_x_variant":[
        "\u5510\u5bb6\u576a"
    ],
    "wof:name":"Tangjiaping",
    "wof:placetype":"locality"
},
  "geometry": {"coordinates":[110.65683,30.01634],"type":"Point"}
}