{
  "type": "Feature",
  "properties": {
    "gn:admin1_code":"18.0",
    "gn:asciiname":"Gaojila",
    "gn:country_code":"CN",
    "gn:dem":679,
    "gn:feature_class":"P",
    "gn:feature_code":"PPL",
    "gn:name":"Gaojila",
    "gn:population":0,
    "gn:timezone":"Asia/Shanghai",
    "iso:country":"CN",
    "name:zho_x_preferred":[
        "\u9ad8\u673a\u62c9"
    ],
    "wof:name":"Gaojila",
    "wof:placetype":"locality"
},
  "geometry": {"coordinates":[108.88500000000001,26.9204],"type":"Point"}
}