{
  "type": "Feature",
  "properties": {
    "gn:admin1_code":"8.0",
    "gn:asciiname":"Nanchangsun",
    "gn:country_code":"CN",
    "gn:dem":213,
    "gn:feature_class":"P",
    "gn:feature_code":"PPL",
    "gn:name":"Nanchangsun",
    "gn:population":0,
    "gn:timezone":"Asia/Shanghai",
    "iso:country":"CN",
    "name:zho_x_preferred":[
        "\u5357\u957f\u5b59"
    ],
    "wof:name":"Nanchangsun",
    "wof:placetype":"locality"
},
  "geometry": {"coordinates":[126.84353,46.99853],"type":"Point"}
}