{
  "type": "Feature",
  "properties": {
    "gn:admin1_code":"15.0",
    "gn:asciiname":"Zhazihe",
    "gn:country_code":"CN",
    "gn:dem":2512,
    "gn:feature_class":"P",
    "gn:feature_code":"PPL",
    "gn:name":"Zhazihe",
    "gn:population":0,
    "gn:timezone":"Asia/Shanghai",
    "iso:country":"CN",
    "name:zho_x_preferred":[
        "\u624e\u5b50\u6cb3"
    ],
    "wof:name":"Zhazihe",
    "wof:placetype":"locality"
},
  "geometry": {"coordinates":[103.48399999999999,35.2402],"type":"Point"}
}