{
  "type": "Feature",
  "properties": {
    "gn:admin1_code":"26.0",
    "gn:asciiname":"Dadaohe",
    "gn:country_code":"CN",
    "gn:dem":1004,
    "gn:feature_class":"P",
    "gn:feature_code":"PPL",
    "gn:name":"Dadaohe",
    "gn:population":0,
    "gn:timezone":"Asia/Shanghai",
    "iso:country":"CN",
    "name:zho_x_preferred":[
        "\u5927\u9053\u6cb3"
    ],
    "wof:name":"Dadaohe",
    "wof:placetype":"locality"
},
  "geometry": {"coordinates":[110.12945000000001,36.66346],"type":"Point"}
}