{
  "type": "Feature",
  "properties": {
    "gn:admin1_code":"8.0",
    "gn:asciiname":"Wanbaocun",
    "gn:country_code":"CN",
    "gn:dem":131,
    "gn:feature_class":"P",
    "gn:feature_code":"PPL",
    "gn:name":"Wanbaocun",
    "gn:population":0,
    "gn:timezone":"Asia/Shanghai",
    "iso:country":"CN",
    "name:zho_x_preferred":[
        "\u4e07\u5b9d\u6751"
    ],
    "wof:name":"Wanbaocun",
    "wof:placetype":"locality"
},
  "geometry": {"coordinates":[126.58011999999999,46.24084000000001],"type":"Point"}
}