{
  "type": "Feature",
  "properties": {
    "gn:admin1_code":"18.0",
    "gn:asciiname":"Yanhui",
    "gn:country_code":"CN",
    "gn:dem":1110,
    "gn:feature_class":"P",
    "gn:feature_code":"PPL",
    "gn:name":"Yanhui",
    "gn:population":0,
    "gn:timezone":"Asia/Shanghai",
    "iso:country":"CN",
    "name:zho_x_preferred":[
        "\u5ca9\u7070"
    ],
    "wof:name":"Yanhui",
    "wof:placetype":"locality"
},
  "geometry": {"coordinates":[107.274,26.8135],"type":"Point"}
}