{
  "type": "Feature",
  "properties": {
    "gn:admin1_code":"4.0",
    "gn:asciiname":"Minfucun",
    "gn:country_code":"CN",
    "gn:dem":1,
    "gn:feature_class":"P",
    "gn:feature_code":"PPL",
    "gn:name":"Minfucun",
    "gn:population":0,
    "gn:timezone":"Asia/Shanghai",
    "iso:country":"CN",
    "name:zho_x_preferred":[
        "\u6c11\u5bcc\u6751"
    ],
    "wof:name":"Minfucun",
    "wof:placetype":"locality"
},
  "geometry": {"coordinates":[120.17046999999999,33.31732],"type":"Point"}
}