{
  "type": "Feature",
  "properties": {
    "gn:admin1_code":"26.0",
    "gn:asciiname":"Huangchangou",
    "gn:country_code":"CN",
    "gn:dem":938,
    "gn:feature_class":"P",
    "gn:feature_code":"PPL",
    "gn:name":"Huangchangou",
    "gn:population":0,
    "gn:timezone":"Asia/Shanghai",
    "iso:country":"CN",
    "name:zho_x_preferred":[
        "\u9ec4\u8749\u6c9f"
    ],
    "wof:name":"Huangchangou",
    "wof:placetype":"locality"
},
  "geometry": {"coordinates":[110.53782,33.71095],"type":"Point"}
}