{
  "type": "Feature",
  "properties": {
    "gn:admin1_code":"14.0",
    "gn:asciiname":"Fada",
    "gn:country_code":"CN",
    "gn:dem":4381,
    "gn:feature_class":"P",
    "gn:feature_code":"PPL",
    "gn:name":"Fada",
    "gn:population":0,
    "gn:timezone":"Asia/Urumqi",
    "iso:country":"CN",
    "name:ben_x_preferred":[
        "\u09ab\u09be\u09a6\u09be"
    ],
    "name:ceb_x_preferred":[
        "Fada"
    ],
    "name:deu_x_preferred":[
        "Fada"
    ],
    "name:fas_x_preferred":[
        "\u0641\u0627\u062f\u0627"
    ],
    "name:fra_x_preferred":[
        "Fada"
    ],
    "name:hun_x_preferred":[
        "Fada"
    ],
    "name:jpn_x_preferred":[
        "\u30d5\u30a1\u30c0"
    ],
    "name:por_x_preferred":[
        "Fada"
    ],
    "name:spa_x_preferred":[
        "Fada"
    ],
    "name:vie_x_preferred":[
        "Fada"
    ],
    "name:zho_x_preferred":[
        "\u53d1\u6253"
    ],
    "wof:name":"Fada",
    "wof:placetype":"locality"
},
  "geometry": {"coordinates":[93.73643,31.86206],"type":"Point"}
}