{
  "type": "Feature",
  "properties": {
    "gn:admin1_code":"14.0",
    "gn:asciiname":"Zatang",
    "gn:country_code":"CN",
    "gn:dem":4425,
    "gn:feature_class":"P",
    "gn:feature_code":"PPL",
    "gn:name":"Zatang",
    "gn:population":0,
    "gn:timezone":"Asia/Urumqi",
    "iso:country":"CN",
    "name:bod_x_preferred":[
        "Zatang"
    ],
    "name:zho_x_preferred":[
        "Zadang"
    ],
    "name:zho_x_variant":[
        "\u6742\u5858"
    ],
    "wof:name":"Zatang",
    "wof:placetype":"locality"
},
  "geometry": {"coordinates":[90.25017,29.12012],"type":"Point"}
}