{
  "type": "Feature",
  "properties": {
    "gn:admin1_code":"30",
    "gn:asciiname":"Xiashuangcun",
    "gn:country_code":"CN",
    "gn:dem":67,
    "gn:feature_class":"P",
    "gn:feature_code":"PPL",
    "gn:name":"Xiashuangcun",
    "gn:population":0,
    "gn:timezone":"Asia/Urumqi",
    "iso:country":"CN",
    "name:zho_x_preferred":[
        "\u4e0b\u53cc\u6751"
    ],
    "wof:name":"Xiashuangcun",
    "wof:placetype":"locality"
},
  "geometry": {"coordinates":[110.45134,22.08357],"type":"Point"}
}