{
  "type": "Feature",
  "properties": {
    "gn:admin1_code":"29.0",
    "gn:asciiname":"Nalalu",
    "gn:country_code":"CN",
    "gn:dem":1371,
    "gn:feature_class":"P",
    "gn:feature_code":"PPL",
    "gn:name":"Nalalu",
    "gn:population":0,
    "gn:timezone":"Asia/Shanghai",
    "iso:country":"CN",
    "name:zho_x_preferred":[
        "\u62ff\u62c9\u9c81"
    ],
    "wof:name":"Nalalu",
    "wof:placetype":"locality"
},
  "geometry": {"coordinates":[101.315,23.487],"type":"Point"}
}