{
  "type": "Feature",
  "properties": {
    "gn:admin1_code":"4.0",
    "gn:asciiname":"Qing'ercun",
    "gn:country_code":"CN",
    "gn:dem":0,
    "gn:feature_class":"P",
    "gn:feature_code":"PPL",
    "gn:name":"Qing\u2019ercun",
    "gn:population":0,
    "gn:timezone":"Asia/Shanghai",
    "iso:country":"CN",
    "name:und_x_variant":[
        "Qing\u2019ercun"
    ],
    "name:zho_x_preferred":[
        "\u9752\u4e8c\u6751"
    ],
    "wof:name":"Qing'ercun",
    "wof:placetype":"locality"
},
  "geometry": {"coordinates":[119.54789,33.48225],"type":"Point"}
}