{
  "type": "Feature",
  "properties": {
    "gn:admin1_code":"26.0",
    "gn:asciiname":"Gaotutan",
    "gn:country_code":"CN",
    "gn:dem":1248,
    "gn:feature_class":"P",
    "gn:feature_code":"PPL",
    "gn:name":"Gaotutan",
    "gn:population":0,
    "gn:timezone":"Asia/Shanghai",
    "iso:country":"CN",
    "name:zho_x_preferred":[
        "\u768b\u5154\u6ee9"
    ],
    "wof:name":"Gaotutan",
    "wof:placetype":"locality"
},
  "geometry": {"coordinates":[109.80819,38.55467],"type":"Point"}
}