{
  "type": "Feature",
  "properties": {
    "gn:admin1_code":"2",
    "gn:asciiname":"Xiawu",
    "gn:country_code":"CN",
    "gn:dem":399,
    "gn:feature_class":"P",
    "gn:feature_code":"PPL",
    "gn:name":"Xiawu",
    "gn:population":0,
    "gn:timezone":"Asia/Shanghai",
    "iso:country":"CN",
    "name:und_x_variant":[
        "Sanzhou"
    ],
    "name:zho_x_preferred":[
        "\u4e0b\u5c4b"
    ],
    "wof:name":"Xiawu",
    "wof:placetype":"locality"
},
  "geometry": {"coordinates":[120.80056,29.22],"type":"Point"}
}