{
  "type": "Feature",
  "properties": {
    "gn:admin1_code":"9.0",
    "gn:asciiname":"Tiaoshanweiba",
    "gn:country_code":"CN",
    "gn:dem":231,
    "gn:feature_class":"P",
    "gn:feature_code":"PPL",
    "gn:name":"Tiaoshanweiba",
    "gn:population":0,
    "gn:timezone":"Asia/Shanghai",
    "iso:country":"CN",
    "name:zho_x_preferred":[
        "\u6761\u5c71\u5c3e\u5df4"
    ],
    "wof:name":"Tiaoshanweiba",
    "wof:placetype":"locality"
},
  "geometry": {"coordinates":[113.51243999999998,32.63391],"type":"Point"}
}