{
  "type": "Feature",
  "properties": {
    "gn:admin1_code":"26.0",
    "gn:asciiname":"Qiandujia Goucun",
    "gn:country_code":"CN",
    "gn:dem":1050,
    "gn:feature_class":"P",
    "gn:feature_code":"PPL",
    "gn:name":"Qiandujia Goucun",
    "gn:population":0,
    "gn:timezone":"Asia/Shanghai",
    "iso:country":"CN",
    "name:zho_x_preferred":[
        "\u524d\u675c\u5bb6\u6c9f\u6751"
    ],
    "wof:name":"Qiandujia Goucun",
    "wof:placetype":"locality"
},
  "geometry": {"coordinates":[110.227,38.4011],"type":"Point"}
}