{
  "type": "Feature",
  "properties": {
    "gn:admin1_code":"4.0",
    "gn:asciiname":"Wanxu",
    "gn:country_code":"CN",
    "gn:dem":3,
    "gn:feature_class":"P",
    "gn:feature_code":"PPL",
    "gn:name":"Wanxu",
    "gn:population":0,
    "gn:timezone":"Asia/Shanghai",
    "iso:country":"CN",
    "name:zho_x_preferred":[
        "Wanxu"
    ],
    "name:zho_x_variant":[
        "\u4e07\u5729"
    ],
    "wof:name":"Wanxu",
    "wof:placetype":"locality"
},
  "geometry": {"coordinates":[119.30486999999999,34.01788],"type":"Point"}
}