{
  "type": "Feature",
  "properties": {
    "gn:admin1_code":"12.0",
    "gn:asciiname":"Beisong",
    "gn:country_code":"CN",
    "gn:dem":71,
    "gn:feature_class":"P",
    "gn:feature_code":"PPL",
    "gn:name":"Beisong",
    "gn:population":0,
    "gn:timezone":"Asia/Shanghai",
    "iso:country":"CN",
    "name:ceb_x_preferred":[
        "Beisong"
    ],
    "name:swe_x_preferred":[
        "Beisong"
    ],
    "name:zho_x_preferred":[
        "Beisong"
    ],
    "name:zho_x_variant":[
        "\u5317\u5b8b",
        "\u5317\u5b8b\u9547"
    ],
    "wof:name":"Beisong",
    "wof:placetype":"locality"
},
  "geometry": {"coordinates":[114.75597,29.86632],"type":"Point"}
}