{
  "type": "Feature",
  "properties": {
    "gn:admin1_code":"15.0",
    "gn:asciiname":"Shangxiwan",
    "gn:country_code":"CN",
    "gn:dem":1802,
    "gn:feature_class":"P",
    "gn:feature_code":"PPL",
    "gn:name":"Shangxiwan",
    "gn:population":0,
    "gn:timezone":"Asia/Shanghai",
    "iso:country":"CN",
    "name:zho_x_preferred":[
        "\u4e0a\u897f\u6e7e"
    ],
    "wof:name":"Shangxiwan",
    "wof:placetype":"locality"
},
  "geometry": {"coordinates":[98.6392,39.4435],"type":"Point"}
}