{
  "type": "Feature",
  "properties": {
    "gn:admin1_code":"3.0",
    "gn:asciiname":"Caiguo",
    "gn:country_code":"CN",
    "gn:dem":218,
    "gn:feature_class":"P",
    "gn:feature_code":"PPL",
    "gn:name":"Caiguo",
    "gn:population":0,
    "gn:timezone":"Asia/Shanghai",
    "iso:country":"CN",
    "name:und_x_variant":[
        "\u83dc\u57da"
    ],
    "wof:name":"Caiguo",
    "wof:placetype":"locality"
},
  "geometry": {"coordinates":[114.13234,29.01307000000001],"type":"Point"}
}