{
  "type": "Feature",
  "properties": {
    "gn:admin1_code":"3.0",
    "gn:asciiname":"Wuyang",
    "gn:country_code":"CN",
    "gn:dem":207,
    "gn:feature_class":"P",
    "gn:feature_code":"PPLA4",
    "gn:name":"Wuyang",
    "gn:population":0,
    "gn:timezone":"Asia/Shanghai",
    "iso:country":"CN",
    "name:ceb_x_preferred":[
        "Wuyang"
    ],
    "name:deu_x_preferred":[
        "Wuyang"
    ],
    "name:nor_x_preferred":[
        "Wuyang"
    ],
    "name:und_x_variant":[
        "Wu-yang-hs\u00fc",
        "Wuyang",
        "\u6b66\u9633",
        "Wuyang Zhen",
        "\u6b66\u9633\u9547"
    ],
    "wof:name":"Wuyang",
    "wof:placetype":"locality"
},
  "geometry": {"coordinates":[115.91803,25.76857],"type":"Point"}
}