{
  "type": "Feature",
  "properties": {
    "gn:admin1_code":"24.0",
    "gn:asciiname":"Xinkulue",
    "gn:country_code":"CN",
    "gn:dem":1261,
    "gn:feature_class":"P",
    "gn:feature_code":"PPL",
    "gn:name":"Xinkulue",
    "gn:population":0,
    "gn:timezone":"Asia/Shanghai",
    "iso:country":"CN",
    "name:und_x_variant":[
        "\u65b0\u5710\u5719"
    ],
    "name:zho_x_preferred":[
        "\u65b0\u5710\u5719"
    ],
    "wof:name":"Xinkulue",
    "wof:placetype":"locality"
},
  "geometry": {"coordinates":[113.77961999999999,39.34529000000001],"type":"Point"}
}