{
  "type": "Feature",
  "properties": {
    "gn:admin1_code":"30",
    "gn:asciiname":"Houjiang",
    "gn:country_code":"CN",
    "gn:dem":9,
    "gn:feature_class":"P",
    "gn:feature_code":"PPL",
    "gn:name":"Houjiang",
    "gn:population":0,
    "gn:timezone":"Asia/Urumqi",
    "iso:country":"CN",
    "name:zho_x_preferred":[
        "\u540e\u6c5f"
    ],
    "wof:name":"Houjiang",
    "wof:placetype":"locality"
},
  "geometry": {"coordinates":[110.38908000000001,20.65543],"type":"Point"}
}