{
  "type": "Feature",
  "properties": {
    "gn:admin1_code":"11.0",
    "gn:asciiname":"Shangliaojia",
    "gn:country_code":"CN",
    "gn:dem":148,
    "gn:feature_class":"P",
    "gn:feature_code":"PPL",
    "gn:name":"Shangliaojia",
    "gn:population":0,
    "gn:timezone":"Asia/Shanghai",
    "iso:country":"CN",
    "name:zho_x_preferred":[
        "\u4e0a\u5ed6\u5bb6"
    ],
    "wof:name":"Shangliaojia",
    "wof:placetype":"locality"
},
  "geometry": {"coordinates":[113.02941,25.99447],"type":"Point"}
}