{
  "type": "Feature",
  "properties": {
    "gn:admin1_code":"2.0",
    "gn:asciiname":"Hushan",
    "gn:country_code":"CN",
    "gn:dem":118,
    "gn:feature_class":"P",
    "gn:feature_code":"PPL",
    "gn:name":"Hushan",
    "gn:population":0,
    "gn:timezone":"Asia/Shanghai",
    "iso:country":"CN",
    "name:zho_x_preferred":[
        "\u6e56\u5c71"
    ],
    "wof:name":"Hushan",
    "wof:placetype":"locality"
},
  "geometry": {"coordinates":[118.82119,29.75452],"type":"Point"}
}