{
  "type": "Feature",
  "properties": {
    "gn:admin1_code":"12.0",
    "gn:asciiname":"Tanshuwan",
    "gn:country_code":"CN",
    "gn:dem":174,
    "gn:feature_class":"P",
    "gn:feature_code":"PPL",
    "gn:name":"Tanshuwan",
    "gn:population":0,
    "gn:timezone":"Asia/Shanghai",
    "iso:country":"CN",
    "name:zho_x_preferred":[
        "\u6a80\u6811\u5846"
    ],
    "wof:name":"Tanshuwan",
    "wof:placetype":"locality"
},
  "geometry": {"coordinates":[113.33190999999999,32.04071],"type":"Point"}
}