{
  "type": "Feature",
  "properties": {
    "gn:admin1_code":"26.0",
    "gn:asciiname":"Guaimao",
    "gn:country_code":"CN",
    "gn:dem":1212,
    "gn:feature_class":"P",
    "gn:feature_code":"PPL",
    "gn:name":"Guaimao",
    "gn:population":0,
    "gn:timezone":"Asia/Shanghai",
    "iso:country":"CN",
    "name:zho_x_preferred":[
        "\u62d0\u5cc1"
    ],
    "wof:name":"Guaimao",
    "wof:placetype":"locality"
},
  "geometry": {"coordinates":[109.30783999999998,36.89551],"type":"Point"}
}