{
  "type": "Feature",
  "properties": {
    "gn:admin1_code":"18",
    "gn:asciiname":"Shuangshan",
    "gn:country_code":"CN",
    "gn:dem":1418,
    "gn:feature_class":"P",
    "gn:feature_code":"PPL",
    "gn:name":"Shuangshan",
    "gn:population":0,
    "gn:timezone":"Asia/Shanghai",
    "iso:country":"CN",
    "wof:name":"Shuangshan",
    "wof:placetype":"locality"
},
  "geometry": {"coordinates":[105.51917,27.20778],"type":"Point"}
}