{
  "type": "Feature",
  "properties": {
    "gn:admin1_code":"32.0",
    "gn:asciiname":"Yuanzhongba",
    "gn:country_code":"CN",
    "gn:dem":406,
    "gn:feature_class":"P",
    "gn:feature_code":"PPL",
    "gn:name":"Yuanzhongba",
    "gn:population":0,
    "gn:timezone":"Asia/Shanghai",
    "iso:country":"CN",
    "name:zho_x_preferred":[
        "\u8881\u4e2d\u575d"
    ],
    "wof:name":"Yuanzhongba",
    "wof:placetype":"locality"
},
  "geometry": {"coordinates":[103.562,29.707],"type":"Point"}
}