{
  "type": "Feature",
  "properties": {
    "gn:admin1_code":"8.0",
    "gn:asciiname":"Ganhekou",
    "gn:country_code":"CN",
    "gn:dem":354,
    "gn:feature_class":"P",
    "gn:feature_code":"PPL",
    "gn:name":"Ganhekou",
    "gn:population":0,
    "gn:timezone":"Asia/Shanghai",
    "iso:country":"CN",
    "name:und_x_variant":[
        "\u5e72\u6cb3\u53e3"
    ],
    "wof:name":"Ganhekou",
    "wof:placetype":"locality"
},
  "geometry": {"coordinates":[131.19918000000001,43.80187],"type":"Point"}
}