{
  "type": "Feature",
  "properties": {
    "gn:admin1_code":"3",
    "gn:asciiname":"Nanher Ercun",
    "gn:country_code":"CN",
    "gn:dem":141,
    "gn:feature_class":"P",
    "gn:feature_code":"PPL",
    "gn:name":"Nanher Ercun",
    "gn:population":0,
    "gn:timezone":"Asia/Shanghai",
    "iso:country":"CN",
    "name:zho_x_preferred":[
        "\u5357\u6cb3\u4e8c\u6751"
    ],
    "wof:name":"Nanher Ercun",
    "wof:placetype":"locality"
},
  "geometry": {"coordinates":[114.51300000000001,25.7989],"type":"Point"}
}