{
  "type": "Feature",
  "properties": {
    "gn:admin1_code":"8.0",
    "gn:asciiname":"Xuejiagang",
    "gn:country_code":"CN",
    "gn:dem":231,
    "gn:feature_class":"P",
    "gn:feature_code":"PPL",
    "gn:name":"Xuejiagang",
    "gn:population":0,
    "gn:timezone":"Asia/Shanghai",
    "iso:country":"CN",
    "name:zho_x_preferred":[
        "\u859b\u5bb6\u5c97"
    ],
    "wof:name":"Xuejiagang",
    "wof:placetype":"locality"
},
  "geometry": {"coordinates":[126.77709,47.7987],"type":"Point"}
}