{
  "type": "Feature",
  "properties": {
    "gn:admin1_code":"19.0",
    "gn:asciiname":"Zhangdian",
    "gn:country_code":"CN",
    "gn:dem":107,
    "gn:feature_class":"P",
    "gn:feature_code":"PPLA4",
    "gn:name":"Zhangdian",
    "gn:population":0,
    "gn:timezone":"Asia/Shanghai",
    "iso:country":"CN",
    "name:und_x_variant":[
        "\u5f20\u7538",
        "Zhangdian Jiedao",
        "\u5f20\u7538\u8857\u9053"
    ],
    "wof:name":"Zhangdian",
    "wof:placetype":"locality"
},
  "geometry": {"coordinates":[124.04134999999999,41.8172],"type":"Point"}
}