{
  "type": "Feature",
  "properties": {
    "gn:admin1_code":"30.0",
    "gn:asciiname":"Lianhuazhai",
    "gn:country_code":"CN",
    "gn:dem":124,
    "gn:feature_class":"P",
    "gn:feature_code":"PPL",
    "gn:name":"Lianhuazhai",
    "gn:population":0,
    "gn:timezone":"Asia/Shanghai",
    "iso:country":"CN",
    "name:zho_x_preferred":[
        "\u83b2\u82b1\u5be8"
    ],
    "wof:name":"Lianhuazhai",
    "wof:placetype":"locality"
},
  "geometry": {"coordinates":[111.37923000000001,22.52638],"type":"Point"}
}