{
  "type": "Feature",
  "properties": {
    "gn:admin1_code":"15.0",
    "gn:asciiname":"Liangdajie",
    "gn:country_code":"CN",
    "gn:dem":1388,
    "gn:feature_class":"P",
    "gn:feature_code":"PPL",
    "gn:name":"Liangdajie",
    "gn:population":0,
    "gn:timezone":"Asia/Shanghai",
    "iso:country":"CN",
    "name:zho_x_preferred":[
        "\u4e24\u5927\u754c"
    ],
    "wof:name":"Liangdajie",
    "wof:placetype":"locality"
},
  "geometry": {"coordinates":[102.968,38.5342],"type":"Point"}
}