{
  "type": "Feature",
  "properties": {
    "gn:admin1_code":"29.0",
    "gn:asciiname":"Gumo",
    "gn:country_code":"CN",
    "gn:dem":1545,
    "gn:feature_class":"P",
    "gn:feature_code":"PPL",
    "gn:name":"Gumo",
    "gn:population":0,
    "gn:timezone":"Asia/Shanghai",
    "iso:country":"CN",
    "name:zho_x_preferred":[
        "\u9f13\u78e8"
    ],
    "wof:name":"Gumo",
    "wof:placetype":"locality"
},
  "geometry": {"coordinates":[99.01900000000001,25.8695],"type":"Point"}
}