{
  "type": "Feature",
  "properties": {
    "gn:admin1_code":"4.0",
    "gn:asciiname":"Lujian",
    "gn:country_code":"CN",
    "gn:dem":-1,
    "gn:feature_class":"P",
    "gn:feature_code":"PPL",
    "gn:name":"Lujian",
    "gn:population":0,
    "gn:timezone":"Asia/Shanghai",
    "iso:country":"CN",
    "name:zho_x_preferred":[
        "\u8def\u5efa"
    ],
    "wof:name":"Lujian",
    "wof:placetype":"locality"
},
  "geometry": {"coordinates":[120.09699999999999,33.9419],"type":"Point"}
}