{
  "type": "Feature",
  "properties": {
    "gn:admin1_code":"3.0",
    "gn:asciiname":"Shuikou",
    "gn:country_code":"CN",
    "gn:dem":182,
    "gn:feature_class":"P",
    "gn:feature_code":"PPL",
    "gn:name":"Shuikou",
    "gn:population":0,
    "gn:timezone":"Asia/Shanghai",
    "iso:country":"CN",
    "name:und_x_variant":[
        "\u6c34\u53e3"
    ],
    "wof:name":"Shuikou",
    "wof:placetype":"locality"
},
  "geometry": {"coordinates":[115.32982,26.49692000000001],"type":"Point"}
}