{
  "type": "Feature",
  "properties": {
    "gn:admin1_code":"14.0",
    "gn:asciiname":"Nongba Wengbu",
    "gn:country_code":"CN",
    "gn:dem":4787,
    "gn:feature_class":"P",
    "gn:feature_code":"PPL",
    "gn:name":"Nongba Wengbu",
    "gn:population":0,
    "gn:timezone":"Asia/Urumqi",
    "iso:country":"CN",
    "name:zho_x_preferred":[
        "\u5f04\u9776\u7fc1\u8865"
    ],
    "wof:name":"Nongba Wengbu",
    "wof:placetype":"locality"
},
  "geometry": {"coordinates":[91.86321,31.1183],"type":"Point"}
}