{
  "type": "Feature",
  "properties": {
    "gn:admin1_code":"26.0",
    "gn:asciiname":"Yantangcun",
    "gn:country_code":"CN",
    "gn:dem":1560,
    "gn:feature_class":"P",
    "gn:feature_code":"PPL",
    "gn:name":"Yantangcun",
    "gn:population":0,
    "gn:timezone":"Asia/Shanghai",
    "iso:country":"CN",
    "name:zho_x_preferred":[
        "\u95eb\u5858\u6751"
    ],
    "wof:name":"Yantangcun",
    "wof:placetype":"locality"
},
  "geometry": {"coordinates":[107.70359999999999,37.45833],"type":"Point"}
}