{
  "type": "Feature",
  "properties": {
    "gn:admin1_code":"30.0",
    "gn:asciiname":"Fengsheng",
    "gn:country_code":"CN",
    "gn:dem":1,
    "gn:feature_class":"P",
    "gn:feature_code":"PPL",
    "gn:name":"Fengsheng",
    "gn:population":0,
    "gn:timezone":"Asia/Shanghai",
    "iso:country":"CN",
    "name:zho_x_preferred":[
        "\u4e30\u76db"
    ],
    "wof:name":"Fengsheng",
    "wof:placetype":"locality"
},
  "geometry": {"coordinates":[113.14565,22.52887],"type":"Point"}
}