{
  "type": "Feature",
  "properties": {
    "gn:admin1_code":"26.0",
    "gn:asciiname":"Xiaoguojia Pancun",
    "gn:country_code":"CN",
    "gn:dem":877,
    "gn:feature_class":"P",
    "gn:feature_code":"PPL",
    "gn:name":"Xiaoguojia Pancun",
    "gn:population":0,
    "gn:timezone":"Asia/Shanghai",
    "iso:country":"CN",
    "name:zho_x_preferred":[
        "\u5c0f\u90ed\u5bb6\u7554\u6751"
    ],
    "wof:name":"Xiaoguojia Pancun",
    "wof:placetype":"locality"
},
  "geometry": {"coordinates":[110.49299999999999,37.9344],"type":"Point"}
}