{
  "type": "Feature",
  "properties": {
    "gn:admin1_code":"8.0",
    "gn:asciiname":"Laoliangtou Wopeng",
    "gn:country_code":"CN",
    "gn:dem":193,
    "gn:feature_class":"P",
    "gn:feature_code":"PPL",
    "gn:name":"Laoliangtou Wopeng",
    "gn:population":0,
    "gn:timezone":"Asia/Shanghai",
    "iso:country":"CN",
    "name:zho_x_preferred":[
        "\u8001\u6881\u5934\u7a9d\u68da"
    ],
    "wof:name":"Laoliangtou Wopeng",
    "wof:placetype":"locality"
},
  "geometry": {"coordinates":[124.88296,48.45278],"type":"Point"}
}