{
  "type": "Feature",
  "properties": {
    "gn:admin1_code":"10.0",
    "gn:asciiname":"Longhusi",
    "gn:country_code":"CN",
    "gn:dem":975,
    "gn:feature_class":"P",
    "gn:feature_code":"PPL",
    "gn:name":"Longhusi",
    "gn:population":0,
    "gn:timezone":"Asia/Shanghai",
    "iso:country":"CN",
    "name:zho_x_preferred":[
        "\u9f99\u864e\u5bfa"
    ],
    "wof:name":"Longhusi",
    "wof:placetype":"locality"
},
  "geometry": {"coordinates":[114.59523,39.39075],"type":"Point"}
}