{
  "type": "Feature",
  "properties": {
    "gn:admin1_code":"19.0",
    "gn:asciiname":"Yubaotai",
    "gn:country_code":"CN",
    "gn:dem":30,
    "gn:feature_class":"P",
    "gn:feature_code":"PPL",
    "gn:name":"Yubaotai",
    "gn:population":0,
    "gn:timezone":"Asia/Shanghai",
    "iso:country":"CN",
    "name:zho_x_preferred":[
        "\u6bd3\u5b9d\u53f0"
    ],
    "wof:name":"Yubaotai",
    "wof:placetype":"locality"
},
  "geometry": {"coordinates":[122.89612,41.89792],"type":"Point"}
}