{
  "type": "Feature",
  "properties": {
    "gn:admin1_code":"19.0",
    "gn:asciiname":"Nijia Buzi",
    "gn:country_code":"CN",
    "gn:dem":190,
    "gn:feature_class":"P",
    "gn:feature_code":"PPL",
    "gn:name":"Nijia Buzi",
    "gn:population":0,
    "gn:timezone":"Asia/Shanghai",
    "iso:country":"CN",
    "name:und_x_variant":[
        "Nijiabaozi",
        "\u502a\u5bb6\u5821\u5b50",
        "Nijia Buzi"
    ],
    "name:zho_x_preferred":[
        "\u502a\u5bb6\u5821\u5b50"
    ],
    "wof:name":"Nijia Buzi",
    "wof:placetype":"locality"
},
  "geometry": {"coordinates":[124.60576,40.87667],"type":"Point"}
}