{
  "type": "Feature",
  "properties": {
    "gn:admin1_code":"8.0",
    "gn:asciiname":"Junchuan Jiudui",
    "gn:country_code":"CN",
    "gn:dem":68,
    "gn:feature_class":"P",
    "gn:feature_code":"PPLF",
    "gn:name":"Junchuan Jiudui",
    "gn:population":0,
    "gn:timezone":"Asia/Shanghai",
    "iso:country":"CN",
    "name:zho_x_preferred":[
        "\u519b\u5ddd\u4e5d\u961f"
    ],
    "wof:name":"Junchuan Jiudui",
    "wof:placetype":"locality"
},
  "geometry": {"coordinates":[131.28437,47.49358],"type":"Point"}
}