{
  "type": "Feature",
  "properties": {
    "gn:admin1_code":"30",
    "gn:asciiname":"Dafuji",
    "gn:country_code":"CN",
    "gn:dem":322,
    "gn:feature_class":"P",
    "gn:feature_code":"PPL",
    "gn:name":"Dafuji",
    "gn:population":0,
    "gn:timezone":"Asia/Shanghai",
    "iso:country":"CN",
    "name:zho_x_preferred":[
        "\u5927\u592b\u5c8c"
    ],
    "wof:name":"Dafuji",
    "wof:placetype":"locality"
},
  "geometry": {"coordinates":[115.81122000000001,24.82163],"type":"Point"}
}