{
  "type": "Feature",
  "properties": {
    "gn:admin1_code":"19.0",
    "gn:asciiname":"Nanxiaoshan",
    "gn:country_code":"CN",
    "gn:dem":2,
    "gn:feature_class":"P",
    "gn:feature_code":"PPL",
    "gn:name":"Nanxiaoshan",
    "gn:population":0,
    "gn:timezone":"Asia/Shanghai",
    "iso:country":"CN",
    "name:zho_x_preferred":[
        "\u5357\u5c0f\u5c71"
    ],
    "wof:name":"Nanxiaoshan",
    "wof:placetype":"locality"
},
  "geometry": {"coordinates":[123.48699999999999,39.8838],"type":"Point"}
}