{
  "type": "Feature",
  "properties": {
    "gn:admin1_code":"32.0",
    "gn:asciiname":"Duliaokou",
    "gn:country_code":"CN",
    "gn:dem":1197,
    "gn:feature_class":"P",
    "gn:feature_code":"PPL",
    "gn:name":"Duliaokou",
    "gn:population":0,
    "gn:timezone":"Asia/Shanghai",
    "iso:country":"CN",
    "name:zho_x_preferred":[
        "\u90fd\u6599\u53e3"
    ],
    "wof:name":"Duliaokou",
    "wof:placetype":"locality"
},
  "geometry": {"coordinates":[104.033,31.7599],"type":"Point"}
}