{
  "type": "Feature",
  "properties": {
    "gn:admin1_code":"3.0",
    "gn:asciiname":"Dingjiazhou",
    "gn:country_code":"CN",
    "gn:dem":74,
    "gn:feature_class":"P",
    "gn:feature_code":"PPL",
    "gn:name":"Dingjiazhou",
    "gn:population":0,
    "gn:timezone":"Asia/Shanghai",
    "iso:country":"CN",
    "name:zho_x_preferred":[
        "\u4e01\u5bb6\u6d32"
    ],
    "wof:name":"Dingjiazhou",
    "wof:placetype":"locality"
},
  "geometry": {"coordinates":[118.00593000000001,28.4734],"type":"Point"}
}