{
  "type": "Feature",
  "properties": {
    "gn:admin1_code":"25.0",
    "gn:asciiname":"Dazhuangtou",
    "gn:country_code":"CN",
    "gn:dem":121,
    "gn:feature_class":"P",
    "gn:feature_code":"PPL",
    "gn:name":"Dazhuangtou",
    "gn:population":0,
    "gn:timezone":"Asia/Shanghai",
    "iso:country":"CN",
    "name:zho_x_preferred":[
        "\u5927\u5e84\u5934"
    ],
    "wof:name":"Dazhuangtou",
    "wof:placetype":"locality"
},
  "geometry": {"coordinates":[121.14033999999999,37.29695],"type":"Point"}
}