{
  "type": "Feature",
  "properties": {
    "gn:admin1_code":"29.0",
    "gn:asciiname":"Gaobu",
    "gn:country_code":"CN",
    "gn:dem":1916,
    "gn:feature_class":"P",
    "gn:feature_code":"PPL",
    "gn:name":"Gaobu",
    "gn:population":0,
    "gn:timezone":"Asia/Shanghai",
    "iso:country":"CN",
    "name:sco_x_preferred":[
        "Gaobu"
    ],
    "name:zho_x_preferred":[
        "\u9ad8\u5821"
    ],
    "wof:name":"Gaobu",
    "wof:placetype":"locality"
},
  "geometry": {"coordinates":[103.354,25.3775],"type":"Point"}
}