{
  "type": "Feature",
  "properties": {
    "gn:admin1_code":"24.0",
    "gn:asciiname":"Xixiazhuang",
    "gn:country_code":"CN",
    "gn:dem":947,
    "gn:feature_class":"P",
    "gn:feature_code":"PPL",
    "gn:name":"Xixiazhuang",
    "gn:population":0,
    "gn:timezone":"Asia/Shanghai",
    "iso:country":"CN",
    "name:zho_x_preferred":[
        "\u897f\u4e0b\u5e84"
    ],
    "wof:name":"Xixiazhuang",
    "wof:placetype":"locality"
},
  "geometry": {"coordinates":[112.62675,38.00384],"type":"Point"}
}