{
  "type": "Feature",
  "properties": {
    "gn:admin1_code":"1.0",
    "gn:asciiname":"Liangganchongcun",
    "gn:country_code":"CN",
    "gn:dem":397,
    "gn:feature_class":"P",
    "gn:feature_code":"PPL",
    "gn:name":"Liangganchongcun",
    "gn:population":0,
    "gn:timezone":"Asia/Shanghai",
    "iso:country":"CN",
    "name:zho_x_preferred":[
        "\u826f\u611f\u51b2\u6751"
    ],
    "wof:name":"Liangganchongcun",
    "wof:placetype":"locality"
},
  "geometry": {"coordinates":[116.01194,31.16021],"type":"Point"}
}