{
  "type": "Feature",
  "properties": {
    "gn:admin1_code":"29.0",
    "gn:asciiname":"Linggang",
    "gn:country_code":"CN",
    "gn:dem":1798,
    "gn:feature_class":"P",
    "gn:feature_code":"PPL",
    "gn:name":"Linggang",
    "gn:population":0,
    "gn:timezone":"Asia/Shanghai",
    "iso:country":"CN",
    "name:zho_x_preferred":[
        "\u5cad\u5c97"
    ],
    "wof:name":"Linggang",
    "wof:placetype":"locality"
},
  "geometry": {"coordinates":[99.6148,25.2466],"type":"Point"}
}