{
  "type": "Feature",
  "properties": {
    "gn:admin1_code":"8.0",
    "gn:asciiname":"Zhifu Erdui",
    "gn:country_code":"CN",
    "gn:dem":444,
    "gn:feature_class":"P",
    "gn:feature_code":"PPLF",
    "gn:name":"Zhifu Erdui",
    "gn:population":0,
    "gn:timezone":"Asia/Shanghai",
    "iso:country":"CN",
    "name:zho_x_preferred":[
        "\u81f4\u5bcc\u4e8c\u961f"
    ],
    "wof:name":"Zhifu Erdui",
    "wof:placetype":"locality"
},
  "geometry": {"coordinates":[129.10456000000002,44.75044000000001],"type":"Point"}
}