{
  "type": "Feature",
  "properties": {
    "gn:admin1_code":"9.0",
    "gn:asciiname":"Xiaoshangzhuang",
    "gn:country_code":"CN",
    "gn:dem":73,
    "gn:feature_class":"P",
    "gn:feature_code":"PPL",
    "gn:name":"Xiaoshangzhuang",
    "gn:population":0,
    "gn:timezone":"Asia/Shanghai",
    "iso:country":"CN",
    "name:zho_x_preferred":[
        "\u5c0f\u5c1a\u5e84"
    ],
    "wof:name":"Xiaoshangzhuang",
    "wof:placetype":"locality"
},
  "geometry": {"coordinates":[113.75663,33.83009000000001],"type":"Point"}
}