{
  "type": "Feature",
  "properties": {
    "gn:admin1_code":"26.0",
    "gn:asciiname":"Fujiazhuangcun",
    "gn:country_code":"CN",
    "gn:dem":488,
    "gn:feature_class":"P",
    "gn:feature_code":"PPL",
    "gn:name":"Fujiazhuangcun",
    "gn:population":0,
    "gn:timezone":"Asia/Shanghai",
    "iso:country":"CN",
    "name:zho_x_preferred":[
        "\u7b26\u5bb6\u5e84\u6751"
    ],
    "wof:name":"Fujiazhuangcun",
    "wof:placetype":"locality"
},
  "geometry": {"coordinates":[108.73163,34.62724],"type":"Point"}
}