{
  "type": "Feature",
  "properties": {
    "gn:admin1_code":"9.0",
    "gn:asciiname":"Xiayu",
    "gn:country_code":"CN",
    "gn:dem":358,
    "gn:feature_class":"P",
    "gn:feature_code":"PPL",
    "gn:name":"Xiayu",
    "gn:population":0,
    "gn:timezone":"Asia/Shanghai",
    "iso:country":"CN",
    "name:zho_x_preferred":[
        "\u5ce1\u5cea"
    ],
    "wof:name":"Xiayu",
    "wof:placetype":"locality"
},
  "geometry": {"coordinates":[113.17468,34.64651],"type":"Point"}
}