{
  "type": "Feature",
  "properties": {
    "gn:admin1_code":"29.0",
    "gn:asciiname":"Bidatang",
    "gn:country_code":"CN",
    "gn:dem":1969,
    "gn:feature_class":"P",
    "gn:feature_code":"PPL",
    "gn:name":"Bidatang",
    "gn:population":0,
    "gn:timezone":"Asia/Shanghai",
    "iso:country":"CN",
    "name:zho_x_preferred":[
        "\u6bd4\u6253\u5802"
    ],
    "wof:name":"Bidatang",
    "wof:placetype":"locality"
},
  "geometry": {"coordinates":[100.88200000000001,24.7089],"type":"Point"}
}