{
  "type": "Feature",
  "properties": {
    "gn:admin1_code":"8.0",
    "gn:asciiname":"Panjiadiancun",
    "gn:country_code":"CN",
    "gn:dem":155,
    "gn:feature_class":"P",
    "gn:feature_code":"PPL",
    "gn:name":"Panjiadiancun",
    "gn:population":0,
    "gn:timezone":"Asia/Shanghai",
    "iso:country":"CN",
    "name:zho_x_preferred":[
        "\u6f58\u5bb6\u5e97\u6751"
    ],
    "wof:name":"Panjiadiancun",
    "wof:placetype":"locality"
},
  "geometry": {"coordinates":[132.10568999999998,45.48595],"type":"Point"}
}