{
  "type": "Feature",
  "properties": {
    "gn:admin1_code":"14.0",
    "gn:asciiname":"Gyablung",
    "gn:country_code":"CN",
    "gn:dem":4572,
    "gn:feature_class":"P",
    "gn:feature_code":"PPLF",
    "gn:name":"Gyablung",
    "gn:population":0,
    "gn:timezone":"Asia/Urumqi",
    "iso:country":"CN",
    "name:bod_x_preferred":[
        "Gyablung"
    ],
    "name:msa_x_preferred":[
        "Gyablung"
    ],
    "name:zho_x_preferred":[
        "Jiabulong"
    ],
    "name:zho_x_variant":[
        "\u52a0\u5e03\u9686",
        "Cakagu",
        "\u64e6\u5580\u53e4"
    ],
    "wof:name":"Gyablung",
    "wof:placetype":"locality"
},
  "geometry": {"coordinates":[93.203,32.403],"type":"Point"}
}