{
  "type": "Feature",
  "properties": {
    "gn:admin1_code":"16.0",
    "gn:asciiname":"Zhuli",
    "gn:country_code":"CN",
    "gn:dem":399,
    "gn:feature_class":"P",
    "gn:feature_code":"PPL",
    "gn:name":"Zhuli",
    "gn:population":0,
    "gn:timezone":"Asia/Shanghai",
    "iso:country":"CN",
    "name:zho_x_preferred":[
        "\u7af9\u9ece"
    ],
    "wof:name":"Zhuli",
    "wof:placetype":"locality"
},
  "geometry": {"coordinates":[107.34699999999999,24.0842],"type":"Point"}
}