{
  "type": "Feature",
  "properties": {
    "gn:admin1_code":"04",
    "gn:asciiname":"Chenggai",
    "gn:cc2":"CN",
    "gn:country_code":"CN",
    "gn:dem":22,
    "gn:feature_class":"P",
    "gn:feature_code":"PPL",
    "gn:name":"Chenggai",
    "gn:population":0,
    "gn:timezone":"Asia/Shanghai",
    "iso:country":"CN",
    "name:und_x_variant":[
        "Ch\u2019eng-kai",
        "Chenggai"
    ],
    "wof:name":"Chenggai",
    "wof:placetype":"locality"
},
  "geometry": {"coordinates":[119.01667,31.91667],"type":"Point"}
}