{
  "type": "Feature",
  "properties": {
    "gn:admin1_code":"3.0",
    "gn:asciiname":"Fangtian",
    "gn:country_code":"CN",
    "gn:dem":58,
    "gn:feature_class":"P",
    "gn:feature_code":"PPL",
    "gn:name":"Fangtian",
    "gn:population":0,
    "gn:timezone":"Asia/Shanghai",
    "iso:country":"CN",
    "name:und_x_variant":[
        "\u82b3\u7530"
    ],
    "wof:name":"Fangtian",
    "wof:placetype":"locality"
},
  "geometry": {"coordinates":[117.36928,29.04016],"type":"Point"}
}