{
  "type": "Feature",
  "properties": {
    "gn:admin1_code":"11.0",
    "gn:asciiname":"Niu'erjie",
    "gn:country_code":"CN",
    "gn:dem":495,
    "gn:feature_class":"P",
    "gn:feature_code":"PPL",
    "gn:name":"Niu\u2019erjie",
    "gn:population":0,
    "gn:timezone":"Asia/Shanghai",
    "iso:country":"CN",
    "name:zho_x_preferred":[
        "Niu\u2019erjie"
    ],
    "name:zho_x_variant":[
        "\u725b\u513f\u754c"
    ],
    "wof:name":"Niu'erjie",
    "wof:placetype":"locality"
},
  "geometry": {"coordinates":[111.06473,28.97656],"type":"Point"}
}