{
  "type": "Feature",
  "properties": {
    "gn:admin1_code":"7.0",
    "gn:asciiname":"Puhou",
    "gn:country_code":"CN",
    "gn:dem":118,
    "gn:feature_class":"P",
    "gn:feature_code":"PPL",
    "gn:name":"Puhou",
    "gn:population":0,
    "gn:timezone":"Asia/Shanghai",
    "iso:country":"CN",
    "name:zho_x_preferred":[
        "\u57d4\u540e"
    ],
    "wof:name":"Puhou",
    "wof:placetype":"locality"
},
  "geometry": {"coordinates":[118.78698,26.31771],"type":"Point"}
}