{
  "type": "Feature",
  "properties": {
    "gn:admin1_code":"11.0",
    "gn:asciiname":"Jiepaipu",
    "gn:country_code":"CN",
    "gn:dem":84,
    "gn:feature_class":"P",
    "gn:feature_code":"PPL",
    "gn:name":"Jiepaipu",
    "gn:population":0,
    "gn:timezone":"Asia/Shanghai",
    "iso:country":"CN",
    "name:zho_x_preferred":[
        "\u754c\u724c\u94fa"
    ],
    "wof:name":"Jiepaipu",
    "wof:placetype":"locality"
},
  "geometry": {"coordinates":[112.73522,26.69694],"type":"Point"}
}