{
  "type": "Feature",
  "properties": {
    "gn:admin1_code":"32.0",
    "gn:asciiname":"Kuangping",
    "gn:country_code":"CN",
    "gn:dem":699,
    "gn:feature_class":"P",
    "gn:feature_code":"PPL",
    "gn:name":"Kuangping",
    "gn:population":0,
    "gn:timezone":"Asia/Shanghai",
    "iso:country":"CN",
    "name:zho_x_preferred":[
        "\u5321\u576a"
    ],
    "wof:name":"Kuangping",
    "wof:placetype":"locality"
},
  "geometry": {"coordinates":[107.34999999999999,31.3188],"type":"Point"}
}