{
  "type": "Feature",
  "properties": {
    "gn:admin1_code":"11.0",
    "gn:asciiname":"Furong",
    "gn:country_code":"CN",
    "gn:dem":494,
    "gn:feature_class":"P",
    "gn:feature_code":"PPL",
    "gn:name":"Furong",
    "gn:population":0,
    "gn:timezone":"Asia/Shanghai",
    "iso:country":"CN",
    "name:zho_x_preferred":[
        "\u8299\u84c9"
    ],
    "wof:name":"Furong",
    "wof:placetype":"locality"
},
  "geometry": {"coordinates":[111.96003,24.81388],"type":"Point"}
}