{
  "type": "Feature",
  "properties": {
    "gn:admin1_code":"4.0",
    "gn:asciiname":"Doufucheng",
    "gn:country_code":"CN",
    "gn:dem":29,
    "gn:feature_class":"P",
    "gn:feature_code":"PPL",
    "gn:name":"Doufucheng",
    "gn:population":0,
    "gn:timezone":"Asia/Shanghai",
    "iso:country":"CN",
    "name:zho_x_preferred":[
        "\u9661\u5bcc\u57ce"
    ],
    "wof:name":"Doufucheng",
    "wof:placetype":"locality"
},
  "geometry": {"coordinates":[118.67071,32.54994],"type":"Point"}
}