{
  "type": "Feature",
  "properties": {
    "gn:admin1_code":"32.0",
    "gn:asciiname":"Laojunmiao",
    "gn:country_code":"CN",
    "gn:dem":422,
    "gn:feature_class":"P",
    "gn:feature_code":"PPL",
    "gn:name":"Laojunmiao",
    "gn:population":0,
    "gn:timezone":"Asia/Shanghai",
    "iso:country":"CN",
    "name:zho_x_preferred":[
        "\u8001\u541b\u5e99"
    ],
    "wof:name":"Laojunmiao",
    "wof:placetype":"locality"
},
  "geometry": {"coordinates":[104.32602,29.84542],"type":"Point"}
}