{
  "type": "Feature",
  "properties": {
    "gn:admin1_code":"26.0",
    "gn:asciiname":"Longdongba",
    "gn:country_code":"CN",
    "gn:dem":1307,
    "gn:feature_class":"P",
    "gn:feature_code":"PPL",
    "gn:name":"Longdongba",
    "gn:population":0,
    "gn:timezone":"Asia/Shanghai",
    "iso:country":"CN",
    "name:und_x_variant":[
        "\u9f99\u6d1e\u575d"
    ],
    "wof:name":"Longdongba",
    "wof:placetype":"locality"
},
  "geometry": {"coordinates":[105.98976999999999,33.15798],"type":"Point"}
}