{
  "type": "Feature",
  "properties": {
    "gn:admin1_code":"9",
    "gn:asciiname":"Xiamu",
    "gn:country_code":"CN",
    "gn:dem":58,
    "gn:feature_class":"P",
    "gn:feature_code":"PPL",
    "gn:name":"Xiamu",
    "gn:population":0,
    "gn:timezone":"Asia/Shanghai",
    "iso:country":"CN",
    "name:zho_x_preferred":[
        "\u590f\u6728"
    ],
    "wof:name":"Xiamu",
    "wof:placetype":"locality"
},
  "geometry": {"coordinates":[115.05893,35.5538],"type":"Point"}
}