{
  "type": "Feature",
  "properties": {
    "gn:admin1_code":"19.0",
    "gn:asciiname":"Shijiacun",
    "gn:country_code":"CN",
    "gn:dem":136,
    "gn:feature_class":"P",
    "gn:feature_code":"PPL",
    "gn:name":"Shijiacun",
    "gn:population":0,
    "gn:timezone":"Asia/Shanghai",
    "iso:country":"CN",
    "name:und_x_variant":[
        "Shijiabao",
        "Shijiabu"
    ],
    "name:zho_x_preferred":[
        "\u4ec0\u5bb6\u6751"
    ],
    "name:zho_x_variant":[
        "\u4ec0\u5bb6\u5821"
    ],
    "wof:name":"Shijiacun",
    "wof:placetype":"locality"
},
  "geometry": {"coordinates":[124.00435,42.90252],"type":"Point"}
}