{
  "type": "Feature",
  "properties": {
    "gn:admin1_code":"1.0",
    "gn:asciiname":"Dengzhuangcun",
    "gn:country_code":"CN",
    "gn:dem":26,
    "gn:feature_class":"P",
    "gn:feature_code":"PPL",
    "gn:name":"Dengzhuangcun",
    "gn:population":0,
    "gn:timezone":"Asia/Shanghai",
    "iso:country":"CN",
    "name:und_x_variant":[
        "Dengzhuang"
    ],
    "name:zho_x_preferred":[
        "\u9093\u5e84\u6751"
    ],
    "wof:name":"Dengzhuangcun",
    "wof:placetype":"locality"
},
  "geometry": {"coordinates":[117.43676000000001,33.90504],"type":"Point"}
}