{
  "type": "Feature",
  "properties": {
    "gn:admin1_code":"05",
    "gn:asciiname":"Chi-kuan-li-tzu",
    "gn:country_code":"CN",
    "gn:dem":589,
    "gn:feature_class":"P",
    "gn:feature_code":"PPL",
    "gn:name":"Chi-kuan-li-tzu",
    "gn:population":0,
    "gn:timezone":"Asia/Shanghai",
    "iso:country":"CN",
    "wof:name":"Chi-kuan-li-tzu",
    "wof:placetype":"locality"
},
  "geometry": {"coordinates":[127.89722,41.43667],"type":"Point"}
}