{
  "type": "Feature",
  "properties": {
    "gn:admin1_code":"30.0",
    "gn:asciiname":"Qilecun",
    "gn:country_code":"CN",
    "gn:dem":548,
    "gn:feature_class":"P",
    "gn:feature_code":"PPL",
    "gn:name":"Qilecun",
    "gn:population":0,
    "gn:timezone":"Asia/Shanghai",
    "iso:country":"CN",
    "name:zho_x_preferred":[
        "\u5c90\u4e50\u6751"
    ],
    "wof:name":"Qilecun",
    "wof:placetype":"locality"
},
  "geometry": {"coordinates":[113.29531,25.3131],"type":"Point"}
}