{
  "type": "Feature",
  "properties": {
    "gn:admin1_code":"20",
    "gn:asciiname":"Shahai",
    "gn:cc2":"CN",
    "gn:country_code":"CN",
    "gn:dem":1035,
    "gn:feature_class":"P",
    "gn:feature_code":"PPL",
    "gn:name":"Shahai",
    "gn:population":0,
    "gn:timezone":"Asia/Shanghai",
    "iso:country":"CN",
    "name:und_x_variant":[
        "Hu-la-tai",
        "Shahai"
    ],
    "wof:name":"Shahai",
    "wof:placetype":"locality"
},
  "geometry": {"coordinates":[106.98667,40.95444000000001],"type":"Point"}
}