{
  "type": "Feature",
  "properties": {
    "gn:admin1_code":"32.0",
    "gn:asciiname":"Peilong",
    "gn:country_code":"CN",
    "gn:dem":350,
    "gn:feature_class":"P",
    "gn:feature_code":"PPL",
    "gn:name":"Peilong",
    "gn:population":0,
    "gn:timezone":"Asia/Shanghai",
    "iso:country":"CN",
    "name:zho_x_preferred":[
        "\u914d\u9f99"
    ],
    "wof:name":"Peilong",
    "wof:placetype":"locality"
},
  "geometry": {"coordinates":[104.55522999999999,29.95751],"type":"Point"}
}