{
  "type": "Feature",
  "properties": {
    "gn:admin1_code":"31.0",
    "gn:asciiname":"Houlu",
    "gn:country_code":"CN",
    "gn:dem":13,
    "gn:feature_class":"P",
    "gn:feature_code":"PPL",
    "gn:name":"Houlu",
    "gn:population":0,
    "gn:timezone":"Asia/Shanghai",
    "iso:country":"CN",
    "name:zho_x_preferred":[
        "Houlu"
    ],
    "name:zho_x_variant":[
        "\u540e\u7984"
    ],
    "wof:name":"Houlu",
    "wof:placetype":"locality"
},
  "geometry": {"coordinates":[110.69574,19.97023],"type":"Point"}
}