{
  "type": "Feature",
  "properties": {
    "gn:admin1_code":"13.0",
    "gn:asciiname":"Arun",
    "gn:country_code":"CN",
    "gn:dem":1226,
    "gn:feature_class":"P",
    "gn:feature_code":"PPL",
    "gn:name":"Arun",
    "gn:population":0,
    "gn:timezone":"Asia/Shanghai",
    "iso:country":"CN",
    "name:bar_x_preferred":[
        "Arun"
    ],
    "name:ceb_x_preferred":[
        "Arun"
    ],
    "name:deu_x_preferred":[
        "Arun"
    ],
    "name:fra_x_preferred":[
        "Arun"
    ],
    "name:ita_x_preferred":[
        "Arun"
    ],
    "name:mal_x_preferred":[
        "\u0d05\u0d30\u0d41\u0d7a"
    ],
    "name:nld_x_preferred":[
        "Arun"
    ],
    "name:nor_x_preferred":[
        "Arun"
    ],
    "name:pol_x_preferred":[
        "Arun"
    ],
    "name:rus_x_preferred":[
        "\u0410\u0440\u0443\u043d"
    ],
    "name:swe_x_preferred":[
        "Arun"
    ],
    "name:zho_x_preferred":[
        "\u963f\u6da6"
    ],
    "wof:name":"Arun",
    "wof:placetype":"locality"
},
  "geometry": {"coordinates":[76.56808000000002,39.40465],"type":"Point"}
}