{
  "type": "Feature",
  "properties": {
    "gn:admin1_code":"13.0",
    "gn:asciiname":"Arun",
    "gn:country_code":"CN",
    "gn:dem":1226,
    "gn:feature_class":"P",
    "gn:feature_code":"PPL",
    "gn:name":"Arun",
    "gn:population":0,
    "gn:timezone":"Asia/Shanghai",
    "iso:country":"CN",
    "name:zho_x_preferred":[
        "\u963f\u6da6"
    ],
    "wof:name":"Arun",
    "wof:placetype":"locality"
},
  "geometry": {"coordinates":[76.56808000000002,39.40465],"type":"Point"}
}