{
  "type": "Feature",
  "properties": {
    "gn:admin1_code":"10",
    "gn:asciiname":"Tuodao Goumen",
    "gn:country_code":"CN",
    "gn:dem":603,
    "gn:feature_class":"P",
    "gn:feature_code":"PPL",
    "gn:name":"Tuodao Goumen",
    "gn:population":0,
    "gn:timezone":"Asia/Shanghai",
    "iso:country":"CN",
    "name:zho_x_preferred":[
        "\u9a7c\u9053\u6c9f\u95e8"
    ],
    "wof:name":"Tuodao Goumen",
    "wof:placetype":"locality"
},
  "geometry": {"coordinates":[117.26406,41.08453],"type":"Point"}
}