{
  "type": "Feature",
  "properties": {
    "gn:admin1_code":"11",
    "gn:asciiname":"Dabanlei",
    "gn:country_code":"CN",
    "gn:dem":244,
    "gn:feature_class":"P",
    "gn:feature_code":"PPL",
    "gn:name":"Dabanlei",
    "gn:population":0,
    "gn:timezone":"Asia/Shanghai",
    "iso:country":"CN",
    "name:und_x_variant":[
        "\u5927\u534a\u6f2f",
        "Dabanlei"
    ],
    "wof:name":"Dabanlei",
    "wof:placetype":"locality"
},
  "geometry": {"coordinates":[111.88388999999999,25.61639],"type":"Point"}
}