{
  "type": "Feature",
  "properties": {
    "gn:admin1_code":"32.0",
    "gn:asciiname":"Tongjiagou",
    "gn:country_code":"CN",
    "gn:dem":378,
    "gn:feature_class":"P",
    "gn:feature_code":"PPL",
    "gn:name":"Tongjiagou",
    "gn:population":0,
    "gn:timezone":"Asia/Shanghai",
    "iso:country":"CN",
    "name:zho_x_preferred":[
        "\u540c\u5bb6\u6c9f"
    ],
    "wof:name":"Tongjiagou",
    "wof:placetype":"locality"
},
  "geometry": {"coordinates":[105.5844,30.36373],"type":"Point"}
}