{
  "type": "Feature",
  "properties": {
    "gn:admin1_code":"25",
    "gn:asciiname":"Hebeizhangzhuang",
    "gn:country_code":"CN",
    "gn:dem":32,
    "gn:feature_class":"P",
    "gn:feature_code":"PPL",
    "gn:name":"Hebeizhangzhuang",
    "gn:population":0,
    "gn:timezone":"Asia/Shanghai",
    "iso:country":"CN",
    "name:zho_x_preferred":[
        "\u6cb3\u5317\u5f20\u5e84"
    ],
    "wof:name":"Hebeizhangzhuang",
    "wof:placetype":"locality"
},
  "geometry": {"coordinates":[119.166,36.6995],"type":"Point"}
}