{
  "type": "Feature",
  "properties": {
    "gn:admin1_code":"29.0",
    "gn:asciiname":"Manxing",
    "gn:country_code":"CN",
    "gn:dem":1270,
    "gn:feature_class":"P",
    "gn:feature_code":"PPL",
    "gn:name":"Manxing",
    "gn:population":0,
    "gn:timezone":"Asia/Shanghai",
    "iso:country":"CN",
    "name:zho_x_preferred":[
        "\u66fc\u5174"
    ],
    "wof:name":"Manxing",
    "wof:placetype":"locality"
},
  "geometry": {"coordinates":[101.622,22.978],"type":"Point"}
}