{
  "type": "Feature",
  "properties": {
    "gn:admin1_code":"4.0",
    "gn:asciiname":"Maodou Jiaodai",
    "gn:country_code":"CN",
    "gn:dem":5,
    "gn:feature_class":"P",
    "gn:feature_code":"PPL",
    "gn:name":"Maodou Jiaodai",
    "gn:population":0,
    "gn:timezone":"Asia/Shanghai",
    "iso:country":"CN",
    "name:zho_x_preferred":[
        "\u6bdb\u8c46\u89d2\u5788"
    ],
    "wof:name":"Maodou Jiaodai",
    "wof:placetype":"locality"
},
  "geometry": {"coordinates":[120.23284,32.06092],"type":"Point"}
}