{
  "type": "Feature",
  "properties": {
    "gn:admin1_code":"32.0",
    "gn:asciiname":"Tiantangba",
    "gn:country_code":"CN",
    "gn:dem":591,
    "gn:feature_class":"P",
    "gn:feature_code":"PPL",
    "gn:name":"Tiantangba",
    "gn:population":0,
    "gn:timezone":"Asia/Shanghai",
    "iso:country":"CN",
    "name:zho_x_preferred":[
        "\u5929\u5802\u575d"
    ],
    "wof:name":"Tiantangba",
    "wof:placetype":"locality"
},
  "geometry": {"coordinates":[105.39957,28.45251],"type":"Point"}
}