{
  "type": "Feature",
  "properties": {
    "gn:admin1_code":"14.0",
    "gn:asciiname":"Xiaopengcun",
    "gn:country_code":"CN",
    "gn:dem":4902,
    "gn:feature_class":"P",
    "gn:feature_code":"PPL",
    "gn:name":"Xiaopengcun",
    "gn:population":0,
    "gn:timezone":"Asia/Urumqi",
    "iso:country":"CN",
    "name:zho_x_preferred":[
        "\u5b5d\u5f6d\u6751"
    ],
    "wof:name":"Xiaopengcun",
    "wof:placetype":"locality"
},
  "geometry": {"coordinates":[87.4905,33.0834],"type":"Point"}
}