{
  "type": "Feature",
  "properties": {
    "gn:admin1_code":"30",
    "gn:asciiname":"Jinshan",
    "gn:country_code":"CN",
    "gn:dem":82,
    "gn:feature_class":"P",
    "gn:feature_code":"PPL",
    "gn:name":"Jinshan",
    "gn:population":0,
    "gn:timezone":"Asia/Shanghai",
    "iso:country":"CN",
    "name:ceb_x_preferred":[
        "Jinshan"
    ],
    "name:deu_x_preferred":[
        "Jinshan"
    ],
    "name:sco_x_preferred":[
        "Jinshan"
    ],
    "name:swe_x_preferred":[
        "Jinshan"
    ],
    "wof:name":"Jinshan",
    "wof:placetype":"locality"
},
  "geometry": {"coordinates":[116.01667,23.19806],"type":"Point"}
}