{
  "type": "Feature",
  "properties": {
    "gn:admin1_code":"10",
    "gn:asciiname":"Gaojiayao",
    "gn:country_code":"CN",
    "gn:dem":1496,
    "gn:feature_class":"P",
    "gn:feature_code":"PPL",
    "gn:name":"Gaojiayao",
    "gn:population":0,
    "gn:timezone":"Asia/Shanghai",
    "iso:country":"CN",
    "name:zho_x_preferred":[
        "\u9ad8\u5bb6\u7a91"
    ],
    "wof:name":"Gaojiayao",
    "wof:placetype":"locality"
},
  "geometry": {"coordinates":[115.61054,41.31554000000001],"type":"Point"}
}