{
  "type": "Feature",
  "properties": {
    "gn:admin1_code":"29.0",
    "gn:asciiname":"Xinminzhai",
    "gn:country_code":"CN",
    "gn:dem":1745,
    "gn:feature_class":"P",
    "gn:feature_code":"PPL",
    "gn:name":"Xinminzhai",
    "gn:population":0,
    "gn:timezone":"Asia/Shanghai",
    "iso:country":"CN",
    "name:zho_x_preferred":[
        "\u65b0\u6c11\u5be8"
    ],
    "wof:name":"Xinminzhai",
    "wof:placetype":"locality"
},
  "geometry": {"coordinates":[102.687,22.7062],"type":"Point"}
}