{
  "type": "Feature",
  "properties": {
    "gn:admin1_code":"26.0",
    "gn:asciiname":"Zhaiwangoukou",
    "gn:country_code":"CN",
    "gn:dem":1597,
    "gn:feature_class":"P",
    "gn:feature_code":"PPL",
    "gn:name":"Zhaiwangoukou",
    "gn:population":0,
    "gn:timezone":"Asia/Shanghai",
    "iso:country":"CN",
    "name:zho_x_preferred":[
        "\u5be8\u6e7e\u6c9f\u53e3"
    ],
    "wof:name":"Zhaiwangoukou",
    "wof:placetype":"locality"
},
  "geometry": {"coordinates":[108.53161,33.58229],"type":"Point"}
}