{
  "type": "Feature",
  "properties": {
    "gn:admin1_code":"7.0",
    "gn:asciiname":"Jihuicun",
    "gn:country_code":"CN",
    "gn:dem":155,
    "gn:feature_class":"P",
    "gn:feature_code":"PPL",
    "gn:name":"Jihuicun",
    "gn:population":0,
    "gn:timezone":"Asia/Shanghai",
    "iso:country":"CN",
    "name:zho_x_preferred":[
        "\u9645\u4f1a\u6751"
    ],
    "wof:name":"Jihuicun",
    "wof:placetype":"locality"
},
  "geometry": {"coordinates":[117.89740999999999,26.85127],"type":"Point"}
}