{
  "type": "Feature",
  "properties": {
    "gn:admin1_code":"5.0",
    "gn:asciiname":"Dianyuancun",
    "gn:country_code":"CN",
    "gn:dem":136,
    "gn:feature_class":"P",
    "gn:feature_code":"PPL",
    "gn:name":"Dianyuancun",
    "gn:population":0,
    "gn:timezone":"Asia/Shanghai",
    "iso:country":"CN",
    "name:zho_x_preferred":[
        "\u6bbf\u5143\u6751"
    ],
    "wof:name":"Dianyuancun",
    "wof:placetype":"locality"
},
  "geometry": {"coordinates":[124.01296000000001,45.64529],"type":"Point"}
}