{
  "type": "Feature",
  "properties": {
    "gn:admin1_code":"20.0",
    "gn:asciiname":"Qidaoquan",
    "gn:country_code":"CN",
    "gn:dem":276,
    "gn:feature_class":"P",
    "gn:feature_code":"PPL",
    "gn:name":"Qidaoquan",
    "gn:population":0,
    "gn:timezone":"Asia/Shanghai",
    "iso:country":"CN",
    "name:zho_x_preferred":[
        "\u4e03\u9053\u6cc9"
    ],
    "wof:name":"Qidaoquan",
    "wof:placetype":"locality"
},
  "geometry": {"coordinates":[124.05432,48.4735],"type":"Point"}
}