{
  "type": "Feature",
  "properties": {
    "gn:admin1_code":"1.0",
    "gn:asciiname":"Sijicun",
    "gn:country_code":"CN",
    "gn:dem":200,
    "gn:feature_class":"P",
    "gn:feature_code":"PPL",
    "gn:name":"Sijicun",
    "gn:population":0,
    "gn:timezone":"Asia/Shanghai",
    "iso:country":"CN",
    "name:zho_x_preferred":[
        "\u56db\u5409\u6751"
    ],
    "wof:name":"Sijicun",
    "wof:placetype":"locality"
},
  "geometry": {"coordinates":[115.92151,30.37957],"type":"Point"}
}