{
  "type": "Feature",
  "properties": {
    "gn:admin1_code":"11",
    "gn:asciiname":"Jietouling",
    "gn:country_code":"CN",
    "gn:dem":475,
    "gn:feature_class":"P",
    "gn:feature_code":"PPL",
    "gn:name":"Jietouling",
    "gn:population":0,
    "gn:timezone":"Asia/Shanghai",
    "iso:country":"CN",
    "name:zho_x_preferred":[
        "\u754c\u5934\u5cad"
    ],
    "wof:name":"Jietouling",
    "wof:placetype":"locality"
},
  "geometry": {"coordinates":[111.33123000000001,27.9255],"type":"Point"}
}