{
  "type": "Feature",
  "properties": {
    "gn:admin1_code":"1.0",
    "gn:asciiname":"Xiawanzhoucun",
    "gn:country_code":"CN",
    "gn:dem":8,
    "gn:feature_class":"P",
    "gn:feature_code":"PPL",
    "gn:name":"Xiawanzhoucun",
    "gn:population":0,
    "gn:timezone":"Asia/Shanghai",
    "iso:country":"CN",
    "name:zho_x_preferred":[
        "\u4e0b\u6e7e\u5468\u6751"
    ],
    "wof:name":"Xiawanzhoucun",
    "wof:placetype":"locality"
},
  "geometry": {"coordinates":[117.30571999999999,31.56033],"type":"Point"}
}