{
  "type": "Feature",
  "properties": {
    "gn:admin1_code":"3",
    "gn:asciiname":"Longgangzi",
    "gn:country_code":"CN",
    "gn:dem":403,
    "gn:feature_class":"P",
    "gn:feature_code":"PPL",
    "gn:name":"Longgangzi",
    "gn:population":0,
    "gn:timezone":"Asia/Shanghai",
    "iso:country":"CN",
    "name:zho_x_preferred":[
        "\u9f99\u5c97\u5b50"
    ],
    "wof:name":"Longgangzi",
    "wof:placetype":"locality"
},
  "geometry": {"coordinates":[114.107,25.7556],"type":"Point"}
}