{
  "type": "Feature",
  "properties": {
    "gn:admin1_code":"28.0",
    "gn:asciiname":"Babu",
    "gn:country_code":"CN",
    "gn:dem":4,
    "gn:feature_class":"P",
    "gn:feature_code":"PPL",
    "gn:name":"Babu",
    "gn:population":0,
    "gn:timezone":"Asia/Shanghai",
    "iso:country":"CN",
    "name:ceb_x_preferred":[
        "Babu"
    ],
    "name:deu_x_preferred":[
        "Babu"
    ],
    "name:fra_x_preferred":[
        "Babu"
    ],
    "name:mlg_x_preferred":[
        "Babu"
    ],
    "name:pol_x_preferred":[
        "Babu"
    ],
    "name:por_x_preferred":[
        "Babu"
    ],
    "name:rus_x_preferred":[
        "\u0411\u0430\u0431\u0443"
    ],
    "name:swe_x_preferred":[
        "Babu"
    ],
    "name:tel_x_preferred":[
        "\u0c2c\u0c3e\u0c2c\u0c41"
    ],
    "name:zho_x_preferred":[
        "\u516b\u5821"
    ],
    "wof:name":"Babu",
    "wof:placetype":"locality"
},
  "geometry": {"coordinates":[117.54952,39.03746],"type":"Point"}
}