{
  "type": "Feature",
  "properties": {
    "gn:admin1_code":"02",
    "gn:asciiname":"Dachang",
    "gn:cc2":"CN",
    "gn:country_code":"CN",
    "gn:dem":7,
    "gn:feature_class":"P",
    "gn:feature_code":"PPL",
    "gn:name":"Dachang",
    "gn:population":0,
    "gn:timezone":"Asia/Shanghai",
    "iso:country":"CN",
    "name:und_x_variant":[
        "Ta-ti-tien",
        "Dachang"
    ],
    "name:zho_x_preferred":[
        "\u5927\u5382"
    ],
    "wof:name":"Dachang",
    "wof:placetype":"locality"
},
  "geometry": {"coordinates":[121.54139000000001,28.72722000000001],"type":"Point"}
}