{
  "type": "Feature",
  "properties": {
    "gn:admin1_code":"29.0",
    "gn:asciiname":"Diaojingpo",
    "gn:country_code":"CN",
    "gn:dem":1354,
    "gn:feature_class":"P",
    "gn:feature_code":"PPL",
    "gn:name":"Diaojingpo",
    "gn:population":0,
    "gn:timezone":"Asia/Shanghai",
    "iso:country":"CN",
    "name:zho_x_preferred":[
        "\u540a\u4e95\u5761"
    ],
    "wof:name":"Diaojingpo",
    "wof:placetype":"locality"
},
  "geometry": {"coordinates":[104.428,24.7368],"type":"Point"}
}