{
  "type": "Feature",
  "properties": {
    "gn:admin1_code":"4.0",
    "gn:asciiname":"Xingjiazhuang",
    "gn:country_code":"CN",
    "gn:dem":5,
    "gn:feature_class":"P",
    "gn:feature_code":"PPL",
    "gn:name":"Xingjiazhuang",
    "gn:population":0,
    "gn:timezone":"Asia/Shanghai",
    "iso:country":"CN",
    "name:und_x_variant":[
        "\u90a2\u5bb6\u5e84"
    ],
    "wof:name":"Xingjiazhuang",
    "wof:placetype":"locality"
},
  "geometry": {"coordinates":[121.07946,31.65131],"type":"Point"}
}