{
  "type": "Feature",
  "properties": {
    "gn:admin1_code":"29.0",
    "gn:asciiname":"Nabotian Xinzhai",
    "gn:country_code":"CN",
    "gn:dem":1261,
    "gn:feature_class":"P",
    "gn:feature_code":"PPL",
    "gn:name":"Nabotian Xinzhai",
    "gn:population":0,
    "gn:timezone":"Asia/Shanghai",
    "iso:country":"CN",
    "name:zho_x_preferred":[
        "\u54ea\u6ce2\u7530\u65b0\u5be8"
    ],
    "wof:name":"Nabotian Xinzhai",
    "wof:placetype":"locality"
},
  "geometry": {"coordinates":[100.22799999999999,22.9097],"type":"Point"}
}