{
  "type": "Feature",
  "properties": {
    "gn:admin1_code":"19.0",
    "gn:asciiname":"Mengjiatuncun",
    "gn:country_code":"CN",
    "gn:dem":105,
    "gn:feature_class":"P",
    "gn:feature_code":"PPL",
    "gn:name":"Mengjiatuncun",
    "gn:population":0,
    "gn:timezone":"Asia/Shanghai",
    "iso:country":"CN",
    "name:zho_x_preferred":[
        "\u5b5f\u5bb6\u5c6f\u6751"
    ],
    "wof:name":"Mengjiatuncun",
    "wof:placetype":"locality"
},
  "geometry": {"coordinates":[120.64233,40.98291],"type":"Point"}
}