{
  "type": "Feature",
  "properties": {
    "gn:admin1_code":"8.0",
    "gn:asciiname":"Xinfacun",
    "gn:country_code":"CN",
    "gn:dem":163,
    "gn:feature_class":"P",
    "gn:feature_code":"PPL",
    "gn:name":"Xinfacun",
    "gn:population":0,
    "gn:timezone":"Asia/Shanghai",
    "iso:country":"CN",
    "name:zho_x_preferred":[
        "\u65b0\u53d1\u6751"
    ],
    "wof:name":"Xinfacun",
    "wof:placetype":"locality"
},
  "geometry": {"coordinates":[130.29053000000002,45.96427],"type":"Point"}
}