{
  "type": "Feature",
  "properties": {
    "gn:admin1_code":"24",
    "gn:asciiname":"Xiguankou",
    "gn:country_code":"CN",
    "gn:dem":950,
    "gn:feature_class":"P",
    "gn:feature_code":"PPL",
    "gn:name":"Xiguankou",
    "gn:population":0,
    "gn:timezone":"Asia/Shanghai",
    "iso:country":"CN",
    "name:und_x_variant":[
        "Hsi-kuan-k\u2019ou",
        "Xiguankou"
    ],
    "name:zho_x_preferred":[
        "\u897f\u5173\u53e3"
    ],
    "wof:name":"Xiguankou",
    "wof:placetype":"locality"
},
  "geometry": {"coordinates":[112.45355000000001,38.05695],"type":"Point"}
}