{
  "type": "Feature",
  "properties": {
    "gn:admin1_code":"19.0",
    "gn:asciiname":"Peijia Wopeng",
    "gn:country_code":"CN",
    "gn:dem":42,
    "gn:feature_class":"P",
    "gn:feature_code":"PPL",
    "gn:name":"Peijia Wopeng",
    "gn:population":0,
    "gn:timezone":"Asia/Shanghai",
    "iso:country":"CN",
    "name:zho_x_preferred":[
        "\u88f4\u5bb6\u7a9d\u68da"
    ],
    "wof:name":"Peijia Wopeng",
    "wof:placetype":"locality"
},
  "geometry": {"coordinates":[123.241,42.0657],"type":"Point"}
}