{
  "type": "Feature",
  "properties": {
    "gn:admin1_code":"26.0",
    "gn:asciiname":"Shaofanggou",
    "gn:country_code":"CN",
    "gn:dem":1085,
    "gn:feature_class":"P",
    "gn:feature_code":"PPL",
    "gn:name":"Shaofanggou",
    "gn:population":0,
    "gn:timezone":"Asia/Shanghai",
    "iso:country":"CN",
    "name:und_x_variant":[
        "\u70e7\u574a\u6c9f"
    ],
    "wof:name":"Shaofanggou",
    "wof:placetype":"locality"
},
  "geometry": {"coordinates":[107.97622,33.31477],"type":"Point"}
}