{
  "type": "Feature",
  "properties": {
    "gn:admin1_code":"10.0",
    "gn:asciiname":"Huopao",
    "gn:country_code":"CN",
    "gn:dem":17,
    "gn:feature_class":"P",
    "gn:feature_code":"PPL",
    "gn:name":"Huopao",
    "gn:population":0,
    "gn:timezone":"Asia/Shanghai",
    "iso:country":"CN",
    "name:zho_x_preferred":[
        "\u970d\u6ce1"
    ],
    "wof:name":"Huopao",
    "wof:placetype":"locality"
},
  "geometry": {"coordinates":[118.71963999999998,39.55158],"type":"Point"}
}