{
  "type": "Feature",
  "properties": {
    "gn:admin1_code":"32.0",
    "gn:asciiname":"Rerong",
    "gn:country_code":"CN",
    "gn:dem":3384,
    "gn:feature_class":"P",
    "gn:feature_code":"PPL",
    "gn:name":"Rerong",
    "gn:population":0,
    "gn:timezone":"Asia/Shanghai",
    "iso:country":"CN",
    "name:zho_x_preferred":[
        "\u70ed\u7ed2"
    ],
    "wof:name":"Rerong",
    "wof:placetype":"locality"
},
  "geometry": {"coordinates":[100.83,29.892],"type":"Point"}
}