{
  "type": "Feature",
  "properties": {
    "gn:admin1_code":"32.0",
    "gn:asciiname":"Jiajigou",
    "gn:country_code":"CN",
    "gn:dem":1759,
    "gn:feature_class":"P",
    "gn:feature_code":"PPL",
    "gn:name":"Jiajigou",
    "gn:population":0,
    "gn:timezone":"Asia/Shanghai",
    "iso:country":"CN",
    "name:zho_x_preferred":[
        "\u5bb6\u9e21\u6c9f"
    ],
    "wof:name":"Jiajigou",
    "wof:placetype":"locality"
},
  "geometry": {"coordinates":[101.50507,27.18451],"type":"Point"}
}