{
  "type": "Feature",
  "properties": {
    "gn:admin1_code":"11.0",
    "gn:asciiname":"Heyetang",
    "gn:country_code":"CN",
    "gn:dem":144,
    "gn:feature_class":"P",
    "gn:feature_code":"PPL",
    "gn:name":"Heyetang",
    "gn:population":0,
    "gn:timezone":"Asia/Shanghai",
    "iso:country":"CN",
    "name:zho_x_preferred":[
        "\u8377\u53f6\u5858"
    ],
    "wof:name":"Heyetang",
    "wof:placetype":"locality"
},
  "geometry": {"coordinates":[113.54022999999999,27.97759000000001],"type":"Point"}
}