{
  "type": "Feature",
  "properties": {
    "gn:admin1_code":"1.0",
    "gn:asciiname":"Dawu",
    "gn:country_code":"CN",
    "gn:dem":718,
    "gn:feature_class":"P",
    "gn:feature_code":"PPL",
    "gn:name":"Dawu",
    "gn:population":0,
    "gn:timezone":"Asia/Shanghai",
    "iso:country":"CN",
    "name:ceb_x_preferred":[
        "Dawu"
    ],
    "name:deu_x_preferred":[
        "Dawu"
    ],
    "name:eus_x_preferred":[
        "Dawu"
    ],
    "name:fra_x_preferred":[
        "Dawu"
    ],
    "name:nor_x_preferred":[
        "Dawu"
    ],
    "name:swe_x_preferred":[
        "Dawu"
    ],
    "wof:name":"Dawu",
    "wof:placetype":"locality"
},
  "geometry": {"coordinates":[116.08333,30.84167],"type":"Point"}
}