{
  "type": "Feature",
  "properties": {
    "gn:admin1_code":"15.0",
    "gn:asciiname":"Sanwei",
    "gn:country_code":"CN",
    "gn:dem":1138,
    "gn:feature_class":"P",
    "gn:feature_code":"PPLA4",
    "gn:name":"Sanwei",
    "gn:population":0,
    "gn:timezone":"Asia/Urumqi",
    "iso:country":"CN",
    "name:und_x_variant":[
        "Sanwei Xiang"
    ],
    "name:zho_x_preferred":[
        "\u4e09\u5371"
    ],
    "name:zho_x_variant":[
        "\u4e09\u5371\u4e61"
    ],
    "wof:name":"Sanwei",
    "wof:placetype":"locality"
},
  "geometry": {"coordinates":[94.7011,40.15111],"type":"Point"}
}