{
  "type": "Feature",
  "properties": {
    "gn:admin1_code":"15.0",
    "gn:asciiname":"Tangwang",
    "gn:country_code":"CN",
    "gn:dem":2254,
    "gn:feature_class":"P",
    "gn:feature_code":"PPL",
    "gn:name":"Tangwang",
    "gn:population":0,
    "gn:timezone":"Asia/Shanghai",
    "iso:country":"CN",
    "name:und_x_variant":[
        "\u5510\u738b"
    ],
    "wof:name":"Tangwang",
    "wof:placetype":"locality"
},
  "geometry": {"coordinates":[104.73654999999999,34.15682],"type":"Point"}
}