{
  "type": "Feature",
  "properties": {
    "gn:admin1_code":"25.0",
    "gn:asciiname":"Lujiadacun",
    "gn:cc2":"CN",
    "gn:country_code":"CN",
    "gn:dem":63,
    "gn:feature_class":"P",
    "gn:feature_code":"PPL",
    "gn:name":"L\u00fcjiadacun",
    "gn:population":0,
    "gn:timezone":"Asia/Shanghai",
    "iso:country":"CN",
    "name:und_x_variant":[
        "L\u00fcjiadacun"
    ],
    "name:zho_x_preferred":[
        "\u5415\u5bb6\u5927\u6751"
    ],
    "wof:name":"Lujiadacun",
    "wof:placetype":"locality"
},
  "geometry": {"coordinates":[119.84983,36.17409],"type":"Point"}
}