{
  "type": "Feature",
  "properties": {
    "gn:admin1_code":"4.0",
    "gn:asciiname":"Puzhuangli",
    "gn:country_code":"CN",
    "gn:dem":5,
    "gn:feature_class":"P",
    "gn:feature_code":"PPL",
    "gn:name":"Puzhuangli",
    "gn:population":0,
    "gn:timezone":"Asia/Shanghai",
    "iso:country":"CN",
    "name:und_x_variant":[
        "\u6fee\u5e84\u91cc"
    ],
    "name:zho_x_preferred":[
        "\u6fee\u5e84\u91cc"
    ],
    "wof:name":"Puzhuangli",
    "wof:placetype":"locality"
},
  "geometry": {"coordinates":[120.30397000000001,31.68839],"type":"Point"}
}