{
  "type": "Feature",
  "properties": {
    "gn:admin1_code":"10.0",
    "gn:asciiname":"Yema",
    "gn:country_code":"CN",
    "gn:dem":16,
    "gn:feature_class":"P",
    "gn:feature_code":"PPL",
    "gn:name":"Yema",
    "gn:population":0,
    "gn:timezone":"Asia/Shanghai",
    "iso:country":"CN",
    "name:ceb_x_preferred":[
        "Yema"
    ],
    "name:swe_x_preferred":[
        "Yema"
    ],
    "name:zho_x_preferred":[
        "\u91ce\u9a6c"
    ],
    "wof:name":"Yema",
    "wof:placetype":"locality"
},
  "geometry": {"coordinates":[116.245,38.23],"type":"Point"}
}