{
  "type": "Feature",
  "properties": {
    "gn:admin1_code":"11.0",
    "gn:asciiname":"Da'aoxia",
    "gn:country_code":"CN",
    "gn:dem":678,
    "gn:feature_class":"P",
    "gn:feature_code":"PPL",
    "gn:name":"Da\u2019aoxia",
    "gn:population":0,
    "gn:timezone":"Asia/Shanghai",
    "iso:country":"CN",
    "name:und_x_variant":[
        "Da\u2019aoxia"
    ],
    "name:zho_x_preferred":[
        "\u5927\u5773\u4e0b"
    ],
    "wof:name":"Da'aoxia",
    "wof:placetype":"locality"
},
  "geometry": {"coordinates":[112.80768999999999,24.98571],"type":"Point"}
}