{
  "type": "Feature",
  "properties": {
    "gn:admin1_code":"19.0",
    "gn:asciiname":"Zengdingzi",
    "gn:country_code":"CN",
    "gn:dem":404,
    "gn:feature_class":"P",
    "gn:feature_code":"PPL",
    "gn:name":"Zengdingzi",
    "gn:population":0,
    "gn:timezone":"Asia/Shanghai",
    "iso:country":"CN",
    "name:zho_x_preferred":[
        "\u66fe\u9876\u5b50"
    ],
    "wof:name":"Zengdingzi",
    "wof:placetype":"locality"
},
  "geometry": {"coordinates":[124.75700000000001,42.1837],"type":"Point"}
}