{
  "type": "Feature",
  "properties": {
    "gn:admin1_code":"30.0",
    "gn:asciiname":"Xijitang",
    "gn:country_code":"CN",
    "gn:dem":15,
    "gn:feature_class":"P",
    "gn:feature_code":"PPL",
    "gn:name":"Xijitang",
    "gn:population":0,
    "gn:timezone":"Asia/Shanghai",
    "iso:country":"CN",
    "name:zho_x_preferred":[
        "\u897f\u57fa\u5858"
    ],
    "wof:name":"Xijitang",
    "wof:placetype":"locality"
},
  "geometry": {"coordinates":[111.61472000000001,23.2323],"type":"Point"}
}