{
  "type": "Feature",
  "properties": {
    "gn:admin1_code":"3.0",
    "gn:asciiname":"Lengshuikeng",
    "gn:country_code":"CN",
    "gn:dem":276,
    "gn:feature_class":"P",
    "gn:feature_code":"PPL",
    "gn:name":"Lengshuikeng",
    "gn:population":0,
    "gn:timezone":"Asia/Shanghai",
    "iso:country":"CN",
    "name:und_x_variant":[
        "\u51b7\u6c34\u5751"
    ],
    "wof:name":"Lengshuikeng",
    "wof:placetype":"locality"
},
  "geometry": {"coordinates":[116.00668,26.89033],"type":"Point"}
}