{
  "type": "Feature",
  "properties": {
    "gn:admin1_code":"18",
    "gn:asciiname":"Luojiang",
    "gn:country_code":"CN",
    "gn:dem":972,
    "gn:feature_class":"P",
    "gn:feature_code":"PPL",
    "gn:name":"Luojiang",
    "gn:population":0,
    "gn:timezone":"Asia/Shanghai",
    "iso:country":"CN",
    "name:ceb_x_preferred":[
        "Luojiang"
    ],
    "name:deu_x_preferred":[
        "Luojiang"
    ],
    "name:fra_x_preferred":[
        "Luojiang"
    ],
    "name:nor_x_preferred":[
        "Luojiang"
    ],
    "name:swe_x_preferred":[
        "Luojiang"
    ],
    "name:zho_x_preferred":[
        "\u6d1b\u6c5f"
    ],
    "wof:name":"Luojiang",
    "wof:placetype":"locality"
},
  "geometry": {"coordinates":[105.925,24.8642],"type":"Point"}
}