{
  "type": "Feature",
  "properties": {
    "gn:admin1_code":"26.0",
    "gn:asciiname":"Gaohongsi Goucun",
    "gn:country_code":"CN",
    "gn:dem":1070,
    "gn:feature_class":"P",
    "gn:feature_code":"PPL",
    "gn:name":"Gaohongsi Goucun",
    "gn:population":0,
    "gn:timezone":"Asia/Shanghai",
    "iso:country":"CN",
    "name:zho_x_preferred":[
        "\u9ad8\u5b8f\u5bfa\u6c9f\u6751"
    ],
    "wof:name":"Gaohongsi Goucun",
    "wof:placetype":"locality"
},
  "geometry": {"coordinates":[110.32899999999999,37.8574],"type":"Point"}
}