{
  "type": "Feature",
  "properties": {
    "gn:admin1_code":"30",
    "gn:asciiname":"Shangjing Shangzhai",
    "gn:country_code":"CN",
    "gn:dem":661,
    "gn:feature_class":"P",
    "gn:feature_code":"PPL",
    "gn:name":"Shangjing Shangzhai",
    "gn:population":0,
    "gn:timezone":"Asia/Shanghai",
    "iso:country":"CN",
    "name:und_x_variant":[
        "\u4e0a\u5f84\u4e0a\u5be8",
        "Shanglian"
    ],
    "wof:name":"Shangjing Shangzhai",
    "wof:placetype":"locality"
},
  "geometry": {"coordinates":[112.04819999999999,24.67897],"type":"Point"}
}