{
  "type": "Feature",
  "properties": {
    "gn:admin1_code":"22.0",
    "gn:asciiname":"Dongnangoucun",
    "gn:country_code":"CN",
    "gn:dem":347,
    "gn:feature_class":"P",
    "gn:feature_code":"PPL",
    "gn:name":"Dongnangoucun",
    "gn:population":0,
    "gn:timezone":"Asia/Shanghai",
    "iso:country":"CN",
    "name:zho_x_preferred":[
        "\u4e1c\u5357\u6c9f\u6751"
    ],
    "wof:name":"Dongnangoucun",
    "wof:placetype":"locality"
},
  "geometry": {"coordinates":[116.71317999999999,40.77228],"type":"Point"}
}