{
  "type": "Feature",
  "properties": {
    "gn:admin1_code":"29",
    "gn:asciiname":"Xiaopingba",
    "gn:country_code":"CN",
    "gn:dem":2262,
    "gn:feature_class":"P",
    "gn:feature_code":"PPL",
    "gn:name":"Xiaopingba",
    "gn:population":0,
    "gn:timezone":"Asia/Shanghai",
    "iso:country":"CN",
    "name:zho_x_preferred":[
        "\u5c0f\u5e73\u575d"
    ],
    "wof:name":"Xiaopingba",
    "wof:placetype":"locality"
},
  "geometry": {"coordinates":[102.72817000000001,24.59034],"type":"Point"}
}