{
  "type": "Feature",
  "properties": {
    "gn:admin1_code":"25",
    "gn:asciiname":"Dongxiaolongtang",
    "gn:country_code":"CN",
    "gn:dem":135,
    "gn:feature_class":"P",
    "gn:feature_code":"PPL",
    "gn:name":"Dongxiaolongtang",
    "gn:population":0,
    "gn:timezone":"Asia/Shanghai",
    "iso:country":"CN",
    "name:zho_x_preferred":[
        "\u4e1c\u5c0f\u9f99\u5802"
    ],
    "wof:name":"Dongxiaolongtang",
    "wof:placetype":"locality"
},
  "geometry": {"coordinates":[117.283,36.6583],"type":"Point"}
}