{
  "type": "Feature",
  "properties": {
    "gn:admin1_code":"15.0",
    "gn:asciiname":"Tianjiazhuang",
    "gn:country_code":"CN",
    "gn:dem":2876,
    "gn:feature_class":"P",
    "gn:feature_code":"PPL",
    "gn:name":"Tianjiazhuang",
    "gn:population":0,
    "gn:timezone":"Asia/Shanghai",
    "iso:country":"CN",
    "name:und_x_variant":[
        "\u7530\u5bb6\u5e84"
    ],
    "wof:name":"Tianjiazhuang",
    "wof:placetype":"locality"
},
  "geometry": {"coordinates":[103.9109,34.89326],"type":"Point"}
}