{
  "type": "Feature",
  "properties": {
    "gn:admin1_code":"25.0",
    "gn:asciiname":"Xiliuzhuangcun",
    "gn:country_code":"CN",
    "gn:dem":54,
    "gn:feature_class":"P",
    "gn:feature_code":"PPL",
    "gn:name":"Xiliuzhuangcun",
    "gn:population":0,
    "gn:timezone":"Asia/Shanghai",
    "iso:country":"CN",
    "name:zho_x_preferred":[
        "\u897f\u67f3\u5e84\u6751"
    ],
    "wof:name":"Xiliuzhuangcun",
    "wof:placetype":"locality"
},
  "geometry": {"coordinates":[121.67977,37.30094],"type":"Point"}
}