{
  "type": "Feature",
  "properties": {
    "gn:admin1_code":"14.0",
    "gn:asciiname":"Yugongguo",
    "gn:country_code":"CN",
    "gn:dem":4152,
    "gn:feature_class":"P",
    "gn:feature_code":"PPL",
    "gn:name":"Yugongguo",
    "gn:population":0,
    "gn:timezone":"Asia/Urumqi",
    "iso:country":"CN",
    "name:bod_x_preferred":[
        "Y\u00fcgunggo"
    ],
    "name:und_x_variant":[
        "Enzhuge Qu"
    ],
    "name:zho_x_preferred":[
        "\u4e8e\u516c\u679c"
    ],
    "name:zho_x_variant":[
        "\u6069\u6731\u683c\u533a"
    ],
    "wof:name":"Yugongguo",
    "wof:placetype":"locality"
},
  "geometry": {"coordinates":[94.303,30.70300000000001],"type":"Point"}
}