{
  "type": "Feature",
  "properties": {
    "gn:admin1_code":"32.0",
    "gn:asciiname":"Huofengshan",
    "gn:country_code":"CN",
    "gn:dem":677,
    "gn:feature_class":"P",
    "gn:feature_code":"PPL",
    "gn:name":"Huofengshan",
    "gn:population":0,
    "gn:timezone":"Asia/Shanghai",
    "iso:country":"CN",
    "name:zho_x_preferred":[
        "\u706b\u5cf0\u5c71"
    ],
    "wof:name":"Huofengshan",
    "wof:placetype":"locality"
},
  "geometry": {"coordinates":[106.876,31.7008],"type":"Point"}
}