{
  "type": "Feature",
  "properties": {
    "gn:admin1_code":"06",
    "gn:asciiname":"Serbolungba",
    "gn:country_code":"CN",
    "gn:dem":4199,
    "gn:feature_class":"P",
    "gn:feature_code":"PPL",
    "gn:name":"S\u00earbolungba",
    "gn:population":0,
    "gn:timezone":"Asia/Urumqi",
    "iso:country":"CN",
    "name:bod_x_preferred":[
        "\u0f66\u0f7a\u0f62\u0f0b\u0f54\u0f7c\u0f0b\u0f63\u0f74\u0f44\u0f0b\u0f54"
    ],
    "name:und_x_variant":[
        "Yuegai"
    ],
    "name:zho_x_preferred":[
        "\u7ea6\u6539"
    ],
    "wof:name":"Serbolungba",
    "wof:placetype":"locality"
},
  "geometry": {"coordinates":[95.79734999999999,34.12857],"type":"Point"}
}