{
  "type": "Feature",
  "properties": {
    "gn:admin1_code":"30.0",
    "gn:asciiname":"Aicun",
    "gn:country_code":"CN",
    "gn:dem":23,
    "gn:feature_class":"P",
    "gn:feature_code":"PPL",
    "gn:name":"Aicun",
    "gn:population":0,
    "gn:timezone":"Asia/Shanghai",
    "iso:country":"CN",
    "name:zho_x_preferred":[
        "\u7231\u6751"
    ],
    "wof:name":"Aicun",
    "wof:placetype":"locality"
},
  "geometry": {"coordinates":[112.38567999999999,23.16173],"type":"Point"}
}