{
  "type": "Feature",
  "properties": {
    "gn:admin1_code":"03",
    "gn:asciiname":"Matou",
    "gn:country_code":"CN",
    "gn:dem":26,
    "gn:feature_class":"P",
    "gn:feature_code":"PPLA4",
    "gn:name":"Matou",
    "gn:population":0,
    "gn:timezone":"Asia/Shanghai",
    "iso:country":"CN",
    "name:eng_x_historical":[
        "Makau"
    ],
    "name:eng_x_preferred":[
        "Makau"
    ],
    "name:und_x_variant":[
        "Ma-t\u2019ou-ch\u2019en",
        "Matou",
        "\u7801\u5934",
        "Matou Zhen",
        "\u7801\u5934\u9547"
    ],
    "wof:name":"Matou",
    "wof:placetype":"locality"
},
  "geometry": {"coordinates":[115.57738999999999,29.83146],"type":"Point"}
}