{
  "type": "Feature",
  "properties": {
    "gn:admin1_code":"3",
    "gn:asciiname":"Ejingbei",
    "gn:country_code":"CN",
    "gn:dem":231,
    "gn:feature_class":"P",
    "gn:feature_code":"PPL",
    "gn:name":"Ejingbei",
    "gn:population":0,
    "gn:timezone":"Asia/Shanghai",
    "iso:country":"CN",
    "name:zho_x_preferred":[
        "\u9e45\u9888\u80cc"
    ],
    "wof:name":"Ejingbei",
    "wof:placetype":"locality"
},
  "geometry": {"coordinates":[114.833,25.6154],"type":"Point"}
}