{
  "type": "Feature",
  "properties": {
    "gn:admin1_code":"29.0",
    "gn:asciiname":"Mazonglin",
    "gn:country_code":"CN",
    "gn:dem":1894,
    "gn:feature_class":"P",
    "gn:feature_code":"PPL",
    "gn:name":"Mazonglin",
    "gn:population":0,
    "gn:timezone":"Asia/Shanghai",
    "iso:country":"CN",
    "name:zho_x_preferred":[
        "\u9a6c\u9b03\u6797"
    ],
    "wof:name":"Mazonglin",
    "wof:placetype":"locality"
},
  "geometry": {"coordinates":[99.89019999999999,24.3715],"type":"Point"}
}