{
  "type": "Feature",
  "properties": {
    "gn:admin1_code":"16.0",
    "gn:asciiname":"Zhixue",
    "gn:country_code":"CN",
    "gn:dem":336,
    "gn:feature_class":"P",
    "gn:feature_code":"PPL",
    "gn:name":"Zhixue",
    "gn:population":0,
    "gn:timezone":"Asia/Shanghai",
    "iso:country":"CN",
    "name:zho_x_preferred":[
        "\u77e5\u5b66"
    ],
    "wof:name":"Zhixue",
    "wof:placetype":"locality"
},
  "geometry": {"coordinates":[107.62,24.7194],"type":"Point"}
}