{
  "type": "Feature",
  "properties": {
    "gn:admin1_code":"11.0",
    "gn:asciiname":"Manwangcheng",
    "gn:country_code":"CN",
    "gn:dem":315,
    "gn:feature_class":"P",
    "gn:feature_code":"PPL",
    "gn:name":"Manwangcheng",
    "gn:population":0,
    "gn:timezone":"Asia/Shanghai",
    "iso:country":"CN",
    "name:zho_x_preferred":[
        "Manwangcheng"
    ],
    "name:zho_x_variant":[
        "\u86ee\u738b\u57ce"
    ],
    "wof:name":"Manwangcheng",
    "wof:placetype":"locality"
},
  "geometry": {"coordinates":[111.19454,29.54305],"type":"Point"}
}