{
  "type": "Feature",
  "properties": {
    "gn:admin1_code":"18",
    "gn:asciiname":"Yongjiaba",
    "gn:country_code":"CN",
    "gn:dem":786,
    "gn:feature_class":"P",
    "gn:feature_code":"PPL",
    "gn:name":"Yongjiaba",
    "gn:population":0,
    "gn:timezone":"Asia/Shanghai",
    "iso:country":"CN",
    "name:zho_x_preferred":[
        "\u6c38\u5bb6\u575d"
    ],
    "wof:name":"Yongjiaba",
    "wof:placetype":"locality"
},
  "geometry": {"coordinates":[107.515,27.5745],"type":"Point"}
}