{
  "type": "Feature",
  "properties": {
    "gn:admin1_code":"3.0",
    "gn:asciiname":"Zhongluocun",
    "gn:country_code":"CN",
    "gn:dem":229,
    "gn:feature_class":"P",
    "gn:feature_code":"PPL",
    "gn:name":"Zhongluocun",
    "gn:population":0,
    "gn:timezone":"Asia/Shanghai",
    "iso:country":"CN",
    "name:und_x_variant":[
        "\u4e2d\u7f57\u6751"
    ],
    "wof:name":"Zhongluocun",
    "wof:placetype":"locality"
},
  "geometry": {"coordinates":[115.65275,26.89378],"type":"Point"}
}