{
  "type": "Feature",
  "properties": {
    "gn:admin1_code":"14.0",
    "gn:asciiname":"Ludui",
    "gn:country_code":"CN",
    "gn:dem":4148,
    "gn:feature_class":"P",
    "gn:feature_code":"PPL",
    "gn:name":"Ludui",
    "gn:population":0,
    "gn:timezone":"Asia/Urumqi",
    "iso:country":"CN",
    "name:zho_x_preferred":[
        "\u82a6\u5806"
    ],
    "wof:name":"Ludui",
    "wof:placetype":"locality"
},
  "geometry": {"coordinates":[93.75944,29.9353],"type":"Point"}
}