{
  "type": "Feature",
  "properties": {
    "gn:admin1_code":"15.0",
    "gn:asciiname":"Hongliuwan",
    "gn:country_code":"CN",
    "gn:dem":1763,
    "gn:feature_class":"P",
    "gn:feature_code":"PPL",
    "gn:name":"Hongliuwan",
    "gn:population":0,
    "gn:timezone":"Asia/Shanghai",
    "iso:country":"CN",
    "name:zho_x_preferred":[
        "\u7ea2\u67f3\u6e7e"
    ],
    "wof:name":"Hongliuwan",
    "wof:placetype":"locality"
},
  "geometry": {"coordinates":[103.496,37.5796],"type":"Point"}
}