{
  "type": "Feature",
  "properties": {
    "gn:admin1_code":"8.0",
    "gn:asciiname":"Hongtacun",
    "gn:country_code":"CN",
    "gn:dem":274,
    "gn:feature_class":"P",
    "gn:feature_code":"PPL",
    "gn:name":"Hongtacun",
    "gn:population":0,
    "gn:timezone":"Asia/Shanghai",
    "iso:country":"CN",
    "name:zho_x_preferred":[
        "\u7ea2\u5854\u6751"
    ],
    "wof:name":"Hongtacun",
    "wof:placetype":"locality"
},
  "geometry": {"coordinates":[126.11921,47.95336],"type":"Point"}
}