{
  "type": "Feature",
  "properties": {
    "gn:admin1_code":"19.0",
    "gn:asciiname":"Heqingcun",
    "gn:country_code":"CN",
    "gn:dem":496,
    "gn:feature_class":"P",
    "gn:feature_code":"PPL",
    "gn:name":"Heqingcun",
    "gn:population":0,
    "gn:timezone":"Asia/Shanghai",
    "iso:country":"CN",
    "name:zho_x_preferred":[
        "\u548c\u5e86\u6751"
    ],
    "wof:name":"Heqingcun",
    "wof:placetype":"locality"
},
  "geometry": {"coordinates":[124.98399999999999,41.8908],"type":"Point"}
}