{
  "type": "Feature",
  "properties": {
    "gn:admin1_code":"12.0",
    "gn:asciiname":"Tongjiawan",
    "gn:country_code":"CN",
    "gn:dem":23,
    "gn:feature_class":"P",
    "gn:feature_code":"PPL",
    "gn:name":"Tongjiawan",
    "gn:population":0,
    "gn:timezone":"Asia/Shanghai",
    "iso:country":"CN",
    "name:zho_x_preferred":[
        "Tongjiawan"
    ],
    "name:zho_x_variant":[
        "\u7ae5\u5bb6\u6e7e"
    ],
    "wof:name":"Tongjiawan",
    "wof:placetype":"locality"
},
  "geometry": {"coordinates":[114.12009999999999,29.91749],"type":"Point"}
}