{
  "type": "Feature",
  "properties": {
    "gn:admin1_code":"2.0",
    "gn:asciiname":"Wunongkeng",
    "gn:country_code":"CN",
    "gn:dem":271,
    "gn:feature_class":"P",
    "gn:feature_code":"PPL",
    "gn:name":"Wunongkeng",
    "gn:population":0,
    "gn:timezone":"Asia/Shanghai",
    "iso:country":"CN",
    "name:zho_x_preferred":[
        "\u4e4c\u5f04\u5751"
    ],
    "wof:name":"Wunongkeng",
    "wof:placetype":"locality"
},
  "geometry": {"coordinates":[119.58387999999999,28.20441],"type":"Point"}
}