{
  "type": "Feature",
  "properties": {
    "gn:admin1_code":"12.0",
    "gn:asciiname":"Luosidong",
    "gn:country_code":"CN",
    "gn:dem":720,
    "gn:feature_class":"P",
    "gn:feature_code":"PPL",
    "gn:name":"Luosidong",
    "gn:population":0,
    "gn:timezone":"Asia/Shanghai",
    "iso:country":"CN",
    "name:zho_x_preferred":[
        "\u87ba\u4e1d\u6d1e"
    ],
    "wof:name":"Luosidong",
    "wof:placetype":"locality"
},
  "geometry": {"coordinates":[111.4941,32.03077],"type":"Point"}
}