{
  "type": "Feature",
  "properties": {
    "gn:admin1_code":"8.0",
    "gn:asciiname":"Sandaoliucun",
    "gn:country_code":"CN",
    "gn:dem":284,
    "gn:feature_class":"P",
    "gn:feature_code":"PPL",
    "gn:name":"Sandaoliucun",
    "gn:population":0,
    "gn:timezone":"Asia/Shanghai",
    "iso:country":"CN",
    "name:zho_x_preferred":[
        "\u4e09\u9053\u516d\u6751"
    ],
    "wof:name":"Sandaoliucun",
    "wof:placetype":"locality"
},
  "geometry": {"coordinates":[129.56093999999999,44.77684],"type":"Point"}
}