{
  "type": "Feature",
  "properties": {
    "gn:admin1_code":"26",
    "gn:asciiname":"Baiyangtan",
    "gn:country_code":"CN",
    "gn:dem":1423,
    "gn:feature_class":"P",
    "gn:feature_code":"PPL",
    "gn:name":"Baiyangtan",
    "gn:population":0,
    "gn:timezone":"Asia/Shanghai",
    "iso:country":"CN",
    "name:zho_x_preferred":[
        "\u767d\u7f8a\u6ee9"
    ],
    "wof:name":"Baiyangtan",
    "wof:placetype":"locality"
},
  "geometry": {"coordinates":[107.84517,33.80005],"type":"Point"}
}