{
  "type": "Feature",
  "properties": {
    "gn:admin1_code":"30",
    "gn:asciiname":"Wuqiuping",
    "gn:country_code":"CN",
    "gn:dem":186,
    "gn:feature_class":"P",
    "gn:feature_code":"PPL",
    "gn:name":"Wuqiuping",
    "gn:population":0,
    "gn:timezone":"Asia/Shanghai",
    "iso:country":"CN",
    "name:zho_x_preferred":[
        "\u4e4c\u79cb\u576a"
    ],
    "wof:name":"Wuqiuping",
    "wof:placetype":"locality"
},
  "geometry": {"coordinates":[116.80485,23.77576],"type":"Point"}
}