{
  "type": "Feature",
  "properties": {
    "gn:admin1_code":"8.0",
    "gn:asciiname":"Shanhou Wangjiatun",
    "gn:country_code":"CN",
    "gn:dem":114,
    "gn:feature_class":"P",
    "gn:feature_code":"PPL",
    "gn:name":"Shanhou Wangjiatun",
    "gn:population":0,
    "gn:timezone":"Asia/Shanghai",
    "iso:country":"CN",
    "name:zho_x_preferred":[
        "\u5c71\u540e\u738b\u5bb6\u5c6f"
    ],
    "wof:name":"Shanhou Wangjiatun",
    "wof:placetype":"locality"
},
  "geometry": {"coordinates":[128.01837,45.89316],"type":"Point"}
}