{
  "type": "Feature",
  "properties": {
    "gn:admin1_code":"29.0",
    "gn:asciiname":"Li'e",
    "gn:country_code":"CN",
    "gn:dem":2027,
    "gn:feature_class":"P",
    "gn:feature_code":"PPL",
    "gn:name":"Li\u2019e",
    "gn:population":0,
    "gn:timezone":"Asia/Shanghai",
    "iso:country":"CN",
    "name:und_x_variant":[
        "Li\u2019e"
    ],
    "name:zho_x_preferred":[
        "\u91cc\u4fc4"
    ],
    "wof:name":"Li'e",
    "wof:placetype":"locality"
},
  "geometry": {"coordinates":[99.0943,27.2842],"type":"Point"}
}