{
  "type": "Feature",
  "properties": {
    "gn:admin1_code":"26.0",
    "gn:asciiname":"Baijia Goucun",
    "gn:country_code":"CN",
    "gn:dem":951,
    "gn:feature_class":"P",
    "gn:feature_code":"PPL",
    "gn:name":"Baijia Goucun",
    "gn:population":0,
    "gn:timezone":"Asia/Shanghai",
    "iso:country":"CN",
    "name:zho_x_preferred":[
        "\u767d\u5bb6\u6c9f\u6751"
    ],
    "wof:name":"Baijia Goucun",
    "wof:placetype":"locality"
},
  "geometry": {"coordinates":[110.658,38.4119],"type":"Point"}
}