{
  "type": "Feature",
  "properties": {
    "gn:admin1_code":"3",
    "gn:asciiname":"Zhushanxia",
    "gn:country_code":"CN",
    "gn:dem":647,
    "gn:feature_class":"P",
    "gn:feature_code":"PPL",
    "gn:name":"Zhushanxia",
    "gn:population":0,
    "gn:timezone":"Asia/Shanghai",
    "iso:country":"CN",
    "name:zho_x_preferred":[
        "\u7af9\u5c71\u4e0b"
    ],
    "wof:name":"Zhushanxia",
    "wof:placetype":"locality"
},
  "geometry": {"coordinates":[114.23399999999999,26.0447],"type":"Point"}
}