{
  "type": "Feature",
  "properties": {
    "gn:admin1_code":"10",
    "gn:asciiname":"Lihuai",
    "gn:country_code":"CN",
    "gn:dem":35,
    "gn:feature_class":"P",
    "gn:feature_code":"PPL",
    "gn:name":"Lihuai",
    "gn:population":0,
    "gn:timezone":"Asia/Shanghai",
    "iso:country":"CN",
    "name:und_x_variant":[
        "Li-huai-ts\u2019un",
        "Lihuai"
    ],
    "name:zho_x_preferred":[
        "\u674e\u6000"
    ],
    "wof:name":"Lihuai",
    "wof:placetype":"locality"
},
  "geometry": {"coordinates":[115.21899999999999,37.133],"type":"Point"}
}