{
  "type": "Feature",
  "properties": {
    "gn:admin1_code":"28.0",
    "gn:asciiname":"Guangkai",
    "gn:country_code":"CN",
    "gn:dem":8,
    "gn:feature_class":"P",
    "gn:feature_code":"PPLA4",
    "gn:name":"Guangkai",
    "gn:population":0,
    "gn:timezone":"Asia/Shanghai",
    "iso:country":"CN",
    "name:und_x_variant":[
        "Guangkai Jiedao"
    ],
    "name:zho_x_preferred":[
        "\u5e7f\u5f00"
    ],
    "name:zho_x_variant":[
        "\u5e7f\u5f00\u8857\u9053"
    ],
    "wof:name":"Guangkai",
    "wof:placetype":"locality"
},
  "geometry": {"coordinates":[117.16209000000001,39.13474],"type":"Point"}
}