{
  "type": "Feature",
  "properties": {
    "gn:admin1_code":"32.0",
    "gn:asciiname":"Jieguozha'ou",
    "gn:country_code":"CN",
    "gn:dem":3244,
    "gn:feature_class":"P",
    "gn:feature_code":"PPL",
    "gn:name":"Jieguozha\u2019ou",
    "gn:population":0,
    "gn:timezone":"Asia/Shanghai",
    "iso:country":"CN",
    "name:und_x_variant":[
        "Jieguozha\u2019ou"
    ],
    "name:zho_x_preferred":[
        "\u63a5\u679c\u624e\u6b27"
    ],
    "wof:name":"Jieguozha'ou",
    "wof:placetype":"locality"
},
  "geometry": {"coordinates":[100.904,29.8492],"type":"Point"}
}