{
  "type": "Feature",
  "properties": {
    "gn:admin1_code":"2.0",
    "gn:asciiname":"Wujing",
    "gn:country_code":"CN",
    "gn:dem":9,
    "gn:feature_class":"P",
    "gn:feature_code":"PPL",
    "gn:name":"Wujing",
    "gn:population":0,
    "gn:timezone":"Asia/Shanghai",
    "iso:country":"CN",
    "name:deu_x_preferred":[
        "Wujing"
    ],
    "name:swe_x_preferred":[
        "Wujing"
    ],
    "name:und_x_variant":[
        "\u4e94\u6cfe"
    ],
    "wof:name":"Wujing",
    "wof:placetype":"locality"
},
  "geometry": {"coordinates":[120.38539,30.64038],"type":"Point"}
}