{
  "type": "Feature",
  "properties": {
    "gn:admin1_code":"1.0",
    "gn:asciiname":"Heihushancun",
    "gn:country_code":"CN",
    "gn:dem":80,
    "gn:feature_class":"P",
    "gn:feature_code":"PPL",
    "gn:name":"Heihushancun",
    "gn:population":0,
    "gn:timezone":"Asia/Shanghai",
    "iso:country":"CN",
    "name:zho_x_preferred":[
        "\u9ed1\u864e\u5c71\u6751"
    ],
    "wof:name":"Heihushancun",
    "wof:placetype":"locality"
},
  "geometry": {"coordinates":[116.43149,31.47199],"type":"Point"}
}