{
  "type": "Feature",
  "properties": {
    "gn:admin1_code":"31.0",
    "gn:asciiname":"Ehaoling",
    "gn:country_code":"CN",
    "gn:dem":49,
    "gn:feature_class":"P",
    "gn:feature_code":"PPL",
    "gn:name":"Ehaoling",
    "gn:population":0,
    "gn:timezone":"Asia/Shanghai",
    "iso:country":"CN",
    "name:und_x_variant":[
        "Ehaodui",
        "Longshan Nongchang Liladui",
        "Longshan Nongchang Ehaodui"
    ],
    "name:zho_x_preferred":[
        "\u5ce8\u6beb\u5cad"
    ],
    "name:zho_x_variant":[
        "\u5ce8\u6beb\u961f",
        "\u9f99\u5c71\u519c\u573a\u5229\u62c9\u961f",
        "\u9f99\u5c71\u519c\u573a\u5ce8\u6beb\u961f"
    ],
    "wof:name":"Ehaoling",
    "wof:placetype":"locality"
},
  "geometry": {"coordinates":[109.182,19.5615],"type":"Point"}
}