{
  "type": "Feature",
  "properties": {
    "gn:admin1_code":"29.0",
    "gn:asciiname":"Daguanying",
    "gn:country_code":"CN",
    "gn:dem":2072,
    "gn:feature_class":"P",
    "gn:feature_code":"PPL",
    "gn:name":"Daguanying",
    "gn:population":0,
    "gn:timezone":"Asia/Shanghai",
    "iso:country":"CN",
    "name:zho_x_preferred":[
        "\u5927\u5b98\u8425"
    ],
    "wof:name":"Daguanying",
    "wof:placetype":"locality"
},
  "geometry": {"coordinates":[99.9824,26.1567],"type":"Point"}
}