{
  "type": "Feature",
  "properties": {
    "gn:admin1_code":"14.0",
    "gn:asciiname":"Sangzhu",
    "gn:country_code":"CN",
    "gn:dem":4107,
    "gn:feature_class":"P",
    "gn:feature_code":"PPL",
    "gn:name":"Sangzhu",
    "gn:population":0,
    "gn:timezone":"Asia/Urumqi",
    "iso:country":"CN",
    "name:zho_x_preferred":[
        "\u6851\u73e0"
    ],
    "wof:name":"Sangzhu",
    "wof:placetype":"locality"
},
  "geometry": {"coordinates":[87.6525,29.0251],"type":"Point"}
}