{
  "type": "Feature",
  "properties": {
    "gn:admin1_code":"26.0",
    "gn:asciiname":"Jingjia",
    "gn:country_code":"CN",
    "gn:dem":926,
    "gn:feature_class":"P",
    "gn:feature_code":"PPL",
    "gn:name":"Jingjia",
    "gn:population":0,
    "gn:timezone":"Asia/Shanghai",
    "iso:country":"CN",
    "name:und_x_variant":[
        "\u666f\u5bb6"
    ],
    "wof:name":"Jingjia",
    "wof:placetype":"locality"
},
  "geometry": {"coordinates":[107.55952000000001,34.52954],"type":"Point"}
}