{
  "type": "Feature",
  "properties": {
    "gn:admin1_code":"15.0",
    "gn:asciiname":"Tuqian'ao",
    "gn:country_code":"CN",
    "gn:dem":1007,
    "gn:feature_class":"P",
    "gn:feature_code":"PPL",
    "gn:name":"Tuqian\u2019ao",
    "gn:population":0,
    "gn:timezone":"Asia/Shanghai",
    "iso:country":"CN",
    "name:und_x_variant":[
        "Tuqian\u2019ao"
    ],
    "name:zho_x_preferred":[
        "\u571f\u5811\u5773"
    ],
    "wof:name":"Tuqian'ao",
    "wof:placetype":"locality"
},
  "geometry": {"coordinates":[107.517,35.361],"type":"Point"}
}