{
  "type": "Feature",
  "properties": {
    "gn:admin1_code":"19.0",
    "gn:asciiname":"Caochengxigou",
    "gn:country_code":"CN",
    "gn:dem":224,
    "gn:feature_class":"P",
    "gn:feature_code":"PPL",
    "gn:name":"Caochengxigou",
    "gn:population":0,
    "gn:timezone":"Asia/Shanghai",
    "iso:country":"CN",
    "name:und_x_variant":[
        "\u8349\u57ce\u897f\u6c9f"
    ],
    "name:zho_x_preferred":[
        "\u8349\u57ce\u897f\u6c9f"
    ],
    "wof:name":"Caochengxigou",
    "wof:placetype":"locality"
},
  "geometry": {"coordinates":[124.01325,40.87485],"type":"Point"}
}