{
  "type": "Feature",
  "properties": {
    "gn:admin1_code":"11",
    "gn:asciiname":"Liangshi",
    "gn:cc2":"CN",
    "gn:country_code":"CN",
    "gn:dem":95,
    "gn:feature_class":"P",
    "gn:feature_code":"PPL",
    "gn:name":"Liangshi",
    "gn:population":0,
    "gn:timezone":"Asia/Shanghai",
    "iso:country":"CN",
    "name:und_x_variant":[
        "Liangchuanbu",
        "Liangshi"
    ],
    "wof:name":"Liangshi",
    "wof:placetype":"locality"
},
  "geometry": {"coordinates":[112.295,26.55778],"type":"Point"}
}