{
  "type": "Feature",
  "properties": {
    "gn:admin1_code":"25",
    "gn:asciiname":"Zhongxing",
    "gn:country_code":"CN",
    "gn:dem":338,
    "gn:feature_class":"P",
    "gn:feature_code":"PPL",
    "gn:name":"Zhongxing",
    "gn:population":0,
    "gn:timezone":"Asia/Shanghai",
    "iso:country":"CN",
    "name:ceb_x_preferred":[
        "Zhongxing"
    ],
    "name:deu_x_preferred":[
        "Zhongxing"
    ],
    "name:pol_x_preferred":[
        "Zhongxing"
    ],
    "name:swe_x_preferred":[
        "Zhongxing"
    ],
    "name:zho_x_preferred":[
        "\u4e2d\u90a2"
    ],
    "wof:name":"Zhongxing",
    "wof:placetype":"locality"
},
  "geometry": {"coordinates":[117.92400000000001,36.3289],"type":"Point"}
}