{
  "type": "Feature",
  "properties": {
    "gn:admin1_code":"15.0",
    "gn:asciiname":"Hezishang",
    "gn:country_code":"CN",
    "gn:dem":1198,
    "gn:feature_class":"P",
    "gn:feature_code":"PPL",
    "gn:name":"Hezishang",
    "gn:population":0,
    "gn:timezone":"Asia/Shanghai",
    "iso:country":"CN",
    "name:und_x_variant":[
        "\u5408\u5b50\u4e0a"
    ],
    "wof:name":"Hezishang",
    "wof:placetype":"locality"
},
  "geometry": {"coordinates":[105.88003,33.1586],"type":"Point"}
}