{
  "type": "Feature",
  "properties": {
    "gn:admin1_code":"4.0",
    "gn:asciiname":"Shuichancun",
    "gn:country_code":"CN",
    "gn:dem":6,
    "gn:feature_class":"P",
    "gn:feature_code":"PPL",
    "gn:name":"Shuichancun",
    "gn:population":0,
    "gn:timezone":"Asia/Shanghai",
    "iso:country":"CN",
    "name:zho_x_preferred":[
        "\u6c34\u4ea7\u6751"
    ],
    "wof:name":"Shuichancun",
    "wof:placetype":"locality"
},
  "geometry": {"coordinates":[119.67010999999999,32.95789],"type":"Point"}
}