{
  "type": "Feature",
  "properties": {
    "gn:admin1_code":"29.0",
    "gn:asciiname":"Renzhanshi",
    "gn:country_code":"CN",
    "gn:dem":1022,
    "gn:feature_class":"P",
    "gn:feature_code":"PPL",
    "gn:name":"Renzhanshi",
    "gn:population":0,
    "gn:timezone":"Asia/Shanghai",
    "iso:country":"CN",
    "name:zho_x_preferred":[
        "\u4eba\u7ad9\u77f3"
    ],
    "wof:name":"Renzhanshi",
    "wof:placetype":"locality"
},
  "geometry": {"coordinates":[102.95,26.3403],"type":"Point"}
}