{
  "type": "Feature",
  "properties": {
    "gn:admin1_code":"4.0",
    "gn:asciiname":"Quyangcun",
    "gn:country_code":"CN",
    "gn:dem":15,
    "gn:feature_class":"P",
    "gn:feature_code":"PPL",
    "gn:name":"Quyangcun",
    "gn:population":0,
    "gn:timezone":"Asia/Shanghai",
    "iso:country":"CN",
    "name:und_x_variant":[
        "Quyang",
        "Quyangcun"
    ],
    "name:zho_x_preferred":[
        "\u66f2\u9633"
    ],
    "name:zho_x_variant":[
        "\u66f2\u9633\u6751"
    ],
    "wof:name":"Quyangcun",
    "wof:placetype":"locality"
},
  "geometry": {"coordinates":[119.36351999999999,31.8819],"type":"Point"}
}