{
  "type": "Feature",
  "properties": {
    "gn:admin1_code":"13",
    "gn:asciiname":"Tuokemansu",
    "gn:country_code":"CN",
    "gn:dem":4071,
    "gn:feature_class":"P",
    "gn:feature_code":"PPL",
    "gn:name":"Tuokemansu",
    "gn:population":0,
    "gn:timezone":"Asia/Shanghai",
    "iso:country":"CN",
    "name:zho_x_preferred":[
        "\u6258\u514b\u6ee1\u82cf"
    ],
    "wof:name":"Tuokemansu",
    "wof:placetype":"locality"
},
  "geometry": {"coordinates":[74.81998,37.16087],"type":"Point"}
}