{
  "type": "Feature",
  "properties": {
    "gn:admin1_code":"11.0",
    "gn:asciiname":"Yantangchong",
    "gn:country_code":"CN",
    "gn:dem":211,
    "gn:feature_class":"P",
    "gn:feature_code":"PPL",
    "gn:name":"Yantangchong",
    "gn:population":0,
    "gn:timezone":"Asia/Shanghai",
    "iso:country":"CN",
    "name:zho_x_preferred":[
        "\u4e25\u5858\u51b2"
    ],
    "wof:name":"Yantangchong",
    "wof:placetype":"locality"
},
  "geometry": {"coordinates":[111.96784,27.10232],"type":"Point"}
}