{
  "type": "Feature",
  "properties": {
    "gn:admin1_code":"26.0",
    "gn:asciiname":"Hongyanmiaocun",
    "gn:country_code":"CN",
    "gn:dem":921,
    "gn:feature_class":"P",
    "gn:feature_code":"PPL",
    "gn:name":"Hongyanmiaocun",
    "gn:population":0,
    "gn:timezone":"Asia/Shanghai",
    "iso:country":"CN",
    "name:zho_x_preferred":[
        "\u7ea2\u5ca9\u5e99\u6751"
    ],
    "wof:name":"Hongyanmiaocun",
    "wof:placetype":"locality"
},
  "geometry": {"coordinates":[108.09966,32.30859],"type":"Point"}
}