{
  "type": "Feature",
  "properties": {
    "gn:admin1_code":"3.0",
    "gn:asciiname":"Xiachijiao",
    "gn:country_code":"CN",
    "gn:dem":620,
    "gn:feature_class":"P",
    "gn:feature_code":"PPL",
    "gn:name":"Xiachijiao",
    "gn:population":0,
    "gn:timezone":"Asia/Shanghai",
    "iso:country":"CN",
    "name:und_x_variant":[
        "\u4e0b\u8d64\u6559"
    ],
    "wof:name":"Xiachijiao",
    "wof:placetype":"locality"
},
  "geometry": {"coordinates":[115.99225,25.50839],"type":"Point"}
}