{
  "type": "Feature",
  "properties": {
    "gn:admin1_code":"12.0",
    "gn:asciiname":"Yangjia Liangzi",
    "gn:country_code":"CN",
    "gn:dem":300,
    "gn:feature_class":"P",
    "gn:feature_code":"PPL",
    "gn:name":"Yangjia Liangzi",
    "gn:population":0,
    "gn:timezone":"Asia/Shanghai",
    "iso:country":"CN",
    "name:zho_x_preferred":[
        "\u6768\u5bb6\u6881\u5b50"
    ],
    "wof:name":"Yangjia Liangzi",
    "wof:placetype":"locality"
},
  "geometry": {"coordinates":[111.1084,32.75602],"type":"Point"}
}