{
  "type": "Feature",
  "properties": {
    "gn:admin1_code":"12.0",
    "gn:asciiname":"Dawu Xiongjia",
    "gn:country_code":"CN",
    "gn:dem":35,
    "gn:feature_class":"P",
    "gn:feature_code":"PPL",
    "gn:name":"Dawu Xiongjia",
    "gn:population":0,
    "gn:timezone":"Asia/Shanghai",
    "iso:country":"CN",
    "name:zho_x_preferred":[
        "\u5927\u5c4b\u718a\u5bb6"
    ],
    "wof:name":"Dawu Xiongjia",
    "wof:placetype":"locality"
},
  "geometry": {"coordinates":[113.78157,29.86924],"type":"Point"}
}