{
  "type": "Feature",
  "properties": {
    "gn:admin1_code":"31.0",
    "gn:asciiname":"Bajiao",
    "gn:country_code":"CN",
    "gn:dem":170,
    "gn:feature_class":"P",
    "gn:feature_code":"PPL",
    "gn:name":"Bajiao",
    "gn:population":0,
    "gn:timezone":"Asia/Shanghai",
    "iso:country":"CN",
    "name:zho_x_preferred":[
        "\u82ad\u8549"
    ],
    "wof:name":"Bajiao",
    "wof:placetype":"locality"
},
  "geometry": {"coordinates":[108.9015,19.00978],"type":"Point"}
}