{
  "type": "Feature",
  "properties": {
    "gn:admin1_code":"14.0",
    "gn:asciiname":"Kajia",
    "gn:country_code":"CN",
    "gn:dem":2920,
    "gn:feature_class":"P",
    "gn:feature_code":"PPL",
    "gn:name":"Kajia",
    "gn:population":0,
    "gn:timezone":"Asia/Urumqi",
    "iso:country":"CN",
    "name:zho_x_preferred":[
        "\u5361\u5047"
    ],
    "wof:name":"Kajia",
    "wof:placetype":"locality"
},
  "geometry": {"coordinates":[95.85921,29.78968],"type":"Point"}
}