{
  "type": "Feature",
  "properties": {
    "gn:admin1_code":"16.0",
    "gn:asciiname":"Zhu'ershan",
    "gn:country_code":"CN",
    "gn:dem":369,
    "gn:feature_class":"P",
    "gn:feature_code":"PPL",
    "gn:name":"Zhu\u2019ershan",
    "gn:population":0,
    "gn:timezone":"Asia/Shanghai",
    "iso:country":"CN",
    "name:und_x_variant":[
        "Zhu\u2019ershan"
    ],
    "name:zho_x_preferred":[
        "\u7af9\u513f\u5c71"
    ],
    "wof:name":"Zhu'ershan",
    "wof:placetype":"locality"
},
  "geometry": {"coordinates":[109.59099999999999,22.4158],"type":"Point"}
}