{
  "type": "Feature",
  "properties": {
    "gn:admin1_code":"3.0",
    "gn:asciiname":"Yongchang",
    "gn:cc2":"CN",
    "gn:country_code":"CN",
    "gn:dem":59,
    "gn:feature_class":"P",
    "gn:feature_code":"PPL",
    "gn:name":"Yongchang",
    "gn:population":0,
    "gn:timezone":"Asia/Shanghai",
    "iso:country":"CN",
    "name:ceb_x_preferred":[
        "Yongchang"
    ],
    "name:deu_x_preferred":[
        "Yongchang"
    ],
    "name:und_x_variant":[
        "Yung-ch\u2019ang"
    ],
    "wof:name":"Yongchang",
    "wof:placetype":"locality"
},
  "geometry": {"coordinates":[114.95,26.78333],"type":"Point"}
}