{
  "type": "Feature",
  "properties": {
    "gn:admin1_code":"13",
    "gn:asciiname":"Huqing'e'ertan",
    "gn:country_code":"CN",
    "gn:dem":1940,
    "gn:feature_class":"P",
    "gn:feature_code":"PPL",
    "gn:name":"Huqing\u2019e\u2019ertan",
    "gn:population":0,
    "gn:timezone":"Asia/Urumqi",
    "iso:country":"CN",
    "name:und_x_variant":[
        "Huqing\u2019e\u2019ertan",
        "\u547c\u6e05\u989d\u5c14\u5766"
    ],
    "wof:name":"Huqing'e'ertan",
    "wof:placetype":"locality"
},
  "geometry": {"coordinates":[86.37479999999999,42.76819],"type":"Point"}
}