{
  "type": "Feature",
  "properties": {
    "gn:admin1_code":"25",
    "gn:asciiname":"Nanluoling",
    "gn:country_code":"CN",
    "gn:dem":45,
    "gn:feature_class":"P",
    "gn:feature_code":"PPL",
    "gn:name":"Nanluoling",
    "gn:population":0,
    "gn:timezone":"Asia/Shanghai",
    "iso:country":"CN",
    "name:zho_x_preferred":[
        "\u5357\u843d\u9675"
    ],
    "wof:name":"Nanluoling",
    "wof:placetype":"locality"
},
  "geometry": {"coordinates":[116.878,35.3342],"type":"Point"}
}