{
  "type": "Feature",
  "properties": {
    "gn:admin1_code":"21.0",
    "gn:asciiname":"Houyangwa",
    "gn:country_code":"CN",
    "gn:dem":1717,
    "gn:feature_class":"P",
    "gn:feature_code":"PPL",
    "gn:name":"Houyangwa",
    "gn:population":0,
    "gn:timezone":"Asia/Shanghai",
    "iso:country":"CN",
    "name:zho_x_preferred":[
        "\u540e\u9633\u6d3c"
    ],
    "wof:name":"Houyangwa",
    "wof:placetype":"locality"
},
  "geometry": {"coordinates":[106.72757,36.10274],"type":"Point"}
}