{
  "type": "Feature",
  "properties": {
    "gn:admin1_code":"8.0",
    "gn:asciiname":"Zhenzhushan",
    "gn:country_code":"CN",
    "gn:dem":266,
    "gn:feature_class":"P",
    "gn:feature_code":"PPLA4",
    "gn:name":"Zhenzhushan",
    "gn:population":0,
    "gn:timezone":"Asia/Shanghai",
    "iso:country":"CN",
    "name:und_x_variant":[
        "Zhenzhushan Xiang"
    ],
    "name:zho_x_preferred":[
        "\u73cd\u73e0\u5c71"
    ],
    "name:zho_x_variant":[
        "\u73cd\u73e0\u5c71\u4e61"
    ],
    "wof:name":"Zhenzhushan",
    "wof:placetype":"locality"
},
  "geometry": {"coordinates":[128.33096,44.89247],"type":"Point"}
}