{
  "type": "Feature",
  "properties": {
    "gn:admin1_code":"8.0",
    "gn:asciiname":"Shanhe Bafenchang",
    "gn:country_code":"CN",
    "gn:dem":312,
    "gn:feature_class":"P",
    "gn:feature_code":"PPLF",
    "gn:name":"Shanhe Bafenchang",
    "gn:population":0,
    "gn:timezone":"Asia/Shanghai",
    "iso:country":"CN",
    "name:zho_x_preferred":[
        "\u5c71\u6cb3\u516b\u5206\u573a"
    ],
    "wof:name":"Shanhe Bafenchang",
    "wof:placetype":"locality"
},
  "geometry": {"coordinates":[125.89697,49.28644],"type":"Point"}
}