{
  "type": "Feature",
  "properties": {
    "gn:admin1_code":"26.0",
    "gn:asciiname":"Yuanleicun",
    "gn:country_code":"CN",
    "gn:dem":468,
    "gn:feature_class":"P",
    "gn:feature_code":"PPL",
    "gn:name":"Yuanleicun",
    "gn:population":0,
    "gn:timezone":"Asia/Shanghai",
    "iso:country":"CN",
    "name:zho_x_preferred":[
        "\u57a3\u96f7\u6751"
    ],
    "wof:name":"Yuanleicun",
    "wof:placetype":"locality"
},
  "geometry": {"coordinates":[109.75641,34.85832],"type":"Point"}
}