{
  "type": "Feature",
  "properties": {
    "gn:admin1_code":"11",
    "gn:asciiname":"Siping",
    "gn:country_code":"CN",
    "gn:dem":74,
    "gn:feature_class":"P",
    "gn:feature_code":"PPLA4",
    "gn:name":"Siping",
    "gn:population":0,
    "gn:timezone":"Asia/Shanghai",
    "iso:country":"CN",
    "name:ceb_x_preferred":[
        "Siping"
    ],
    "name:und_x_variant":[
        "Siping Xiang"
    ],
    "name:zho_x_preferred":[
        "\u5bfa\u576a"
    ],
    "name:zho_x_variant":[
        "\u5bfa\u576a\u4e61"
    ],
    "wof:name":"Siping",
    "wof:placetype":"locality"
},
  "geometry": {"coordinates":[111.29833000000001,28.69028],"type":"Point"}
}