{
  "type": "Feature",
  "properties": {
    "gn:admin1_code":"29.0",
    "gn:asciiname":"Dongdongshui",
    "gn:country_code":"CN",
    "gn:dem":1852,
    "gn:feature_class":"P",
    "gn:feature_code":"PPL",
    "gn:name":"Dongdongshui",
    "gn:population":0,
    "gn:timezone":"Asia/Shanghai",
    "iso:country":"CN",
    "name:zho_x_preferred":[
        "\u6d1e\u6d1e\u6c34"
    ],
    "wof:name":"Dongdongshui",
    "wof:placetype":"locality"
},
  "geometry": {"coordinates":[104.062,24.6328],"type":"Point"}
}