{
  "type": "Feature",
  "properties": {
    "gn:admin1_code":"15.0",
    "gn:asciiname":"Ganbaling",
    "gn:country_code":"CN",
    "gn:dem":2038,
    "gn:feature_class":"P",
    "gn:feature_code":"PPL",
    "gn:name":"Ganbaling",
    "gn:population":0,
    "gn:timezone":"Asia/Shanghai",
    "iso:country":"CN",
    "name:zho_x_preferred":[
        "\u5e72\u5df4\u5cad"
    ],
    "wof:name":"Ganbaling",
    "wof:placetype":"locality"
},
  "geometry": {"coordinates":[103.952,35.95],"type":"Point"}
}