{
  "type": "Feature",
  "properties": {
    "gn:admin1_code":"3",
    "gn:asciiname":"Chashanxia",
    "gn:country_code":"CN",
    "gn:dem":298,
    "gn:feature_class":"P",
    "gn:feature_code":"PPL",
    "gn:name":"Chashanxia",
    "gn:population":0,
    "gn:timezone":"Asia/Shanghai",
    "iso:country":"CN",
    "name:und_x_variant":[
        "\u8336\u5c71\u4e0b"
    ],
    "wof:name":"Chashanxia",
    "wof:placetype":"locality"
},
  "geometry": {"coordinates":[114.94465,24.72306],"type":"Point"}
}