{
  "type": "Feature",
  "properties": {
    "gn:admin1_code":"10.0",
    "gn:asciiname":"Liuzongfen",
    "gn:country_code":"CN",
    "gn:dem":664,
    "gn:feature_class":"P",
    "gn:feature_code":"PPL",
    "gn:name":"Liuzongfen",
    "gn:population":0,
    "gn:timezone":"Asia/Shanghai",
    "iso:country":"CN",
    "name:zho_x_preferred":[
        "\u5218\u603b\u575f"
    ],
    "wof:name":"Liuzongfen",
    "wof:placetype":"locality"
},
  "geometry": {"coordinates":[115.66762,40.38461],"type":"Point"}
}