{
  "type": "Feature",
  "properties": {
    "gn:admin1_code":"5.0",
    "gn:asciiname":"Chuanchangcun",
    "gn:country_code":"CN",
    "gn:dem":194,
    "gn:feature_class":"P",
    "gn:feature_code":"PPL",
    "gn:name":"Chuanchangcun",
    "gn:population":0,
    "gn:timezone":"Asia/Shanghai",
    "iso:country":"CN",
    "name:zho_x_preferred":[
        "\u8239\u5382\u6751"
    ],
    "wof:name":"Chuanchangcun",
    "wof:placetype":"locality"
},
  "geometry": {"coordinates":[125.58993,44.56788],"type":"Point"}
}