{
  "type": "Feature",
  "properties": {
    "gn:admin1_code":"8.0",
    "gn:asciiname":"Dongyabuhai",
    "gn:country_code":"CN",
    "gn:dem":151,
    "gn:feature_class":"P",
    "gn:feature_code":"PPL",
    "gn:name":"Dongyabuhai",
    "gn:population":0,
    "gn:timezone":"Asia/Shanghai",
    "iso:country":"CN",
    "name:zho_x_preferred":[
        "\u4e1c\u4e9a\u5e03\u6d77"
    ],
    "wof:name":"Dongyabuhai",
    "wof:placetype":"locality"
},
  "geometry": {"coordinates":[124.47365000000001,47.34763],"type":"Point"}
}