{
  "type": "Feature",
  "properties": {
    "gn:admin1_code":"18",
    "gn:asciiname":"Wangjia Wanzi",
    "gn:country_code":"CN",
    "gn:dem":1973,
    "gn:feature_class":"P",
    "gn:feature_code":"PPL",
    "gn:name":"Wangjia Wanzi",
    "gn:population":0,
    "gn:timezone":"Asia/Shanghai",
    "iso:country":"CN",
    "name:zho_x_preferred":[
        "\u738b\u5bb6\u6e7e\u5b50"
    ],
    "wof:name":"Wangjia Wanzi",
    "wof:placetype":"locality"
},
  "geometry": {"coordinates":[104.18600000000001,27.2352],"type":"Point"}
}