{
  "type": "Feature",
  "properties": {
    "gn:admin1_code":"14",
    "gn:asciiname":"Xialu",
    "gn:country_code":"CN",
    "gn:dem":3888,
    "gn:feature_class":"P",
    "gn:feature_code":"PPL",
    "gn:name":"Xialu",
    "gn:population":0,
    "gn:timezone":"Asia/Urumqi",
    "iso:country":"CN",
    "name:zho_x_preferred":[
        "\u590f\u9c81"
    ],
    "wof:name":"Xialu",
    "wof:placetype":"locality"
},
  "geometry": {"coordinates":[88.991,29.1285],"type":"Point"}
}