{
  "type": "Feature",
  "properties": {
    "gn:admin1_code":"18.0",
    "gn:asciiname":"Anxi",
    "gn:country_code":"CN",
    "gn:dem":416,
    "gn:feature_class":"P",
    "gn:feature_code":"PPL",
    "gn:name":"Anxi",
    "gn:population":0,
    "gn:timezone":"Asia/Shanghai",
    "iso:country":"CN",
    "name:ara_x_preferred":[
        "\u0623\u0646\u0643\u0633\u064a"
    ],
    "name:ben_x_preferred":[
        "\u0986\u09a8\u0995\u09cd\u09b8\u09bf"
    ],
    "name:ceb_x_preferred":[
        "Anxi"
    ],
    "name:deu_x_preferred":[
        "Anxi"
    ],
    "name:ell_x_preferred":[
        "\u0386\u03bd\u03be\u03b9"
    ],
    "name:fas_x_preferred":[
        "\u0622\u0646\u0634\u06cc"
    ],
    "name:fra_x_preferred":[
        "Anxi"
    ],
    "name:heb_x_preferred":[
        "\u05d0\u05e0\u05e7\u05e1\u05d9"
    ],
    "name:hin_x_preferred":[
        "\u090f\u0902\u0915\u094d\u0938\u0940"
    ],
    "name:hun_x_preferred":[
        "Anxi"
    ],
    "name:ind_x_preferred":[
        "Anxi"
    ],
    "name:ita_x_preferred":[
        "Anxi"
    ],
    "name:jpn_x_preferred":[
        "\u5b89\u6e13"
    ],
    "name:kor_x_preferred":[
        "\uc548\uc2dc"
    ],
    "name:nld_x_preferred":[
        "Anxi"
    ],
    "name:pol_x_preferred":[
        "Anxi"
    ],
    "name:por_x_preferred":[
        "Anxi"
    ],
    "name:rus_x_preferred":[
        "\u0410\u043d\u044c\u0441\u0438"
    ],
    "name:spa_x_preferred":[
        "Anxi"
    ],
    "name:swe_x_preferred":[
        "Anxi"
    ],
    "name:tur_x_preferred":[
        "Anxi"
    ],
    "name:ukr_x_preferred":[
        "\u0410\u043d\u0441\u0456"
    ],
    "name:urd_x_preferred":[
        "\u0627\u0646\u0632\u06cc"
    ],
    "name:vie_x_preferred":[
        "An Kh\u00ea"
    ],
    "name:zho_cn_x_preferred":[
        "\u5b89\u6eaa"
    ],
    "name:zho_tw_x_preferred":[
        "\u5b89\u6eaa"
    ],
    "name:zho_x_preferred":[
        "\u5b89\u6eaa"
    ],
    "wof:name":"Anxi",
    "wof:placetype":"locality"
},
  "geometry": {"coordinates":[109.334,27.6466],"type":"Point"}
}