{
  "type": "Feature",
  "properties": {
    "gn:admin1_code":"3.0",
    "gn:asciiname":"Pailouxia",
    "gn:country_code":"CN",
    "gn:dem":258,
    "gn:feature_class":"P",
    "gn:feature_code":"PPL",
    "gn:name":"Pailouxia",
    "gn:population":0,
    "gn:timezone":"Asia/Shanghai",
    "iso:country":"CN",
    "name:und_x_variant":[
        "\u724c\u697c\u4e0b"
    ],
    "wof:name":"Pailouxia",
    "wof:placetype":"locality"
},
  "geometry": {"coordinates":[114.35477,28.72064],"type":"Point"}
}