{
  "type": "Feature",
  "properties": {
    "gn:admin1_code":"07",
    "gn:asciiname":"Yijiabang",
    "gn:country_code":"CN",
    "gn:dem":192,
    "gn:feature_class":"P",
    "gn:feature_code":"PPL",
    "gn:name":"Yijiabang",
    "gn:population":0,
    "gn:timezone":"Asia/Shanghai",
    "iso:country":"CN",
    "name:zho_x_preferred":[
        "\u6613\u5bb6\u90a6"
    ],
    "wof:name":"Yijiabang",
    "wof:placetype":"locality"
},
  "geometry": {"coordinates":[117.2878,25.32077],"type":"Point"}
}