{
  "type": "Feature",
  "properties": {
    "gn:admin1_code":"05",
    "gn:asciiname":"Qingyanggou",
    "gn:country_code":"CN",
    "gn:dem":485,
    "gn:feature_class":"P",
    "gn:feature_code":"PPL",
    "gn:name":"Qingyanggou",
    "gn:population":0,
    "gn:timezone":"Asia/Shanghai",
    "iso:country":"CN",
    "name:zho_x_preferred":[
        "\u9752\u6768\u6c9f"
    ],
    "wof:name":"Qingyanggou",
    "wof:placetype":"locality"
},
  "geometry": {"coordinates":[126.6046,43.42547],"type":"Point"}
}