{
  "type": "Feature",
  "properties": {
    "gn:admin1_code":"18.0",
    "gn:asciiname":"Qikuaitian",
    "gn:country_code":"CN",
    "gn:dem":1151,
    "gn:feature_class":"P",
    "gn:feature_code":"PPL",
    "gn:name":"Qikuaitian",
    "gn:population":0,
    "gn:timezone":"Asia/Shanghai",
    "iso:country":"CN",
    "name:zho_x_preferred":[
        "\u4e03\u5757\u7530"
    ],
    "wof:name":"Qikuaitian",
    "wof:placetype":"locality"
},
  "geometry": {"coordinates":[107.151,26.7405],"type":"Point"}
}