{
  "type": "Feature",
  "properties": {
    "gn:admin1_code":"4.0",
    "gn:asciiname":"Geji",
    "gn:country_code":"CN",
    "gn:dem":6,
    "gn:feature_class":"P",
    "gn:feature_code":"PPL",
    "gn:name":"Geji",
    "gn:population":0,
    "gn:timezone":"Asia/Shanghai",
    "iso:country":"CN",
    "name:zho_x_preferred":[
        "\u845b\u96c6"
    ],
    "wof:name":"Geji",
    "wof:placetype":"locality"
},
  "geometry": {"coordinates":[119.164,34.1112],"type":"Point"}
}