{
  "type": "Feature",
  "properties": {
    "gn:admin1_code":"07",
    "gn:asciiname":"Luocheng",
    "gn:country_code":"CN",
    "gn:dem":34,
    "gn:feature_class":"P",
    "gn:feature_code":"PPLA3",
    "gn:name":"Luocheng",
    "gn:population":0,
    "gn:timezone":"Asia/Shanghai",
    "iso:country":"CN",
    "name:und_x_variant":[
        "Huei-an",
        "Hweian",
        "Hweianhsien",
        "Hui-an-hsien",
        "Luocheng"
    ],
    "name:zho_x_preferred":[
        "Hui\u2019an"
    ],
    "name:zho_x_variant":[
        "\u87ba\u57ce"
    ],
    "wof:name":"Luocheng",
    "wof:placetype":"locality"
},
  "geometry": {"coordinates":[118.79495,25.03231],"type":"Point"}
}