{
  "type": "Feature",
  "properties": {
    "gn:admin1_code":"16.0",
    "gn:asciiname":"Zhushan",
    "gn:country_code":"CN",
    "gn:dem":9,
    "gn:feature_class":"P",
    "gn:feature_code":"PPL",
    "gn:name":"Zhushan",
    "gn:population":0,
    "gn:timezone":"Asia/Shanghai",
    "iso:country":"CN",
    "name:ceb_x_preferred":[
        "Zhushan"
    ],
    "name:deu_x_preferred":[
        "Zhushan"
    ],
    "name:fra_x_preferred":[
        "Zhushan"
    ],
    "name:nor_x_preferred":[
        "Zhushan"
    ],
    "name:swe_x_preferred":[
        "Zhushan"
    ],
    "name:zho_x_preferred":[
        "\u7af9\u5c71"
    ],
    "wof:name":"Zhushan",
    "wof:placetype":"locality"
},
  "geometry": {"coordinates":[108.05200000000001,21.5448],"type":"Point"}
}