{
  "type": "Feature",
  "properties": {
    "gn:admin1_code":"3.0",
    "gn:asciiname":"Sanzhaolun",
    "gn:country_code":"CN",
    "gn:dem":415,
    "gn:feature_class":"P",
    "gn:feature_code":"PPLA4",
    "gn:name":"Sanzhaolun",
    "gn:population":0,
    "gn:timezone":"Asia/Shanghai",
    "iso:country":"CN",
    "name:und_x_variant":[
        "\u4e09\u722a\u4ed1",
        "Sanzhaolun Xiang",
        "\u4e09\u722a\u4ed1\u4e61"
    ],
    "wof:name":"Sanzhaolun",
    "wof:placetype":"locality"
},
  "geometry": {"coordinates":[115.22123999999999,29.06239],"type":"Point"}
}