{
  "type": "Feature",
  "properties": {
    "gn:admin1_code":"26.0",
    "gn:asciiname":"Mengjiaya",
    "gn:country_code":"CN",
    "gn:dem":794,
    "gn:feature_class":"P",
    "gn:feature_code":"PPL",
    "gn:name":"Mengjiaya",
    "gn:population":0,
    "gn:timezone":"Asia/Shanghai",
    "iso:country":"CN",
    "name:und_x_variant":[
        "\u5b5f\u5bb6\u57ad"
    ],
    "wof:name":"Mengjiaya",
    "wof:placetype":"locality"
},
  "geometry": {"coordinates":[107.81990999999999,33.26383],"type":"Point"}
}