{
  "type": "Feature",
  "properties": {
    "gn:admin1_code":"15.0",
    "gn:asciiname":"Chaoyang",
    "gn:country_code":"CN",
    "gn:dem":2410,
    "gn:feature_class":"P",
    "gn:feature_code":"PPL",
    "gn:name":"Chaoyang",
    "gn:population":0,
    "gn:timezone":"Asia/Shanghai",
    "iso:country":"CN",
    "name:und_x_variant":[
        "\u671d\u9633"
    ],
    "wof:name":"Chaoyang",
    "wof:placetype":"locality"
},
  "geometry": {"coordinates":[104.19884999999999,34.85897],"type":"Point"}
}