{
  "type": "Feature",
  "properties": {
    "gn:admin1_code":"7.0",
    "gn:asciiname":"Beilingtou",
    "gn:country_code":"CN",
    "gn:dem":494,
    "gn:feature_class":"P",
    "gn:feature_code":"PPL",
    "gn:name":"Beilingtou",
    "gn:population":0,
    "gn:timezone":"Asia/Shanghai",
    "iso:country":"CN",
    "name:und_x_variant":[
        "\u5317\u5cad\u5934"
    ],
    "name:zho_x_preferred":[
        "Beilingtou"
    ],
    "wof:name":"Beilingtou",
    "wof:placetype":"locality"
},
  "geometry": {"coordinates":[119.34502000000001,26.16707],"type":"Point"}
}