{
  "type": "Feature",
  "properties": {
    "gn:admin1_code":"19.0",
    "gn:asciiname":"Qingtian",
    "gn:country_code":"CN",
    "gn:dem":5,
    "gn:feature_class":"P",
    "gn:feature_code":"PPL",
    "gn:name":"Qingtian",
    "gn:population":0,
    "gn:timezone":"Asia/Shanghai",
    "iso:country":"CN",
    "name:und_x_variant":[
        "\u9752\u5929"
    ],
    "wof:name":"Qingtian",
    "wof:placetype":"locality"
},
  "geometry": {"coordinates":[122.27023,40.85083],"type":"Point"}
}