{
  "type": "Feature",
  "properties": {
    "gn:admin1_code":"30.0",
    "gn:asciiname":"Baishimen",
    "gn:country_code":"CN",
    "gn:dem":291,
    "gn:feature_class":"P",
    "gn:feature_code":"PPL",
    "gn:name":"Baishimen",
    "gn:population":0,
    "gn:timezone":"Asia/Shanghai",
    "iso:country":"CN",
    "name:zho_x_preferred":[
        "Baishimen"
    ],
    "name:zho_x_variant":[
        "\u767d\u77f3\u95e8"
    ],
    "wof:name":"Baishimen",
    "wof:placetype":"locality"
},
  "geometry": {"coordinates":[112.40389,24.63417],"type":"Point"}
}