{
  "type": "Feature",
  "properties": {
    "gn:admin1_code":"19.0",
    "gn:asciiname":"Beihekou",
    "gn:country_code":"CN",
    "gn:dem":19,
    "gn:feature_class":"P",
    "gn:feature_code":"PPL",
    "gn:name":"Beihekou",
    "gn:population":0,
    "gn:timezone":"Asia/Shanghai",
    "iso:country":"CN",
    "name:zho_x_preferred":[
        "\u5317\u6cb3\u53e3"
    ],
    "wof:name":"Beihekou",
    "wof:placetype":"locality"
},
  "geometry": {"coordinates":[121.501,38.8464],"type":"Point"}
}