{
  "type": "Feature",
  "properties": {
    "gn:admin1_code":"11.0",
    "gn:asciiname":"Yueyang",
    "gn:country_code":"CN",
    "gn:dem":32,
    "gn:feature_class":"P",
    "gn:feature_code":"PPL",
    "gn:name":"Yueyang",
    "gn:population":0,
    "gn:timezone":"Asia/Shanghai",
    "iso:country":"CN",
    "name:afr_x_preferred":[
        "Yueyang"
    ],
    "name:ara_x_preferred":[
        "\u064a\u0648\u064a\u064a\u0627\u0646\u063a"
    ],
    "name:bul_x_preferred":[
        "\u042e\u044a\u044f\u043d"
    ],
    "name:cat_x_preferred":[
        "Yueyang"
    ],
    "name:cdo_x_preferred":[
        "Ng\u014fk-i\u00f2ng"
    ],
    "name:ces_x_preferred":[
        "J\u00fce-jang"
    ],
    "name:dan_x_preferred":[
        "Yueyang"
    ],
    "name:deu_x_preferred":[
        "Yueyang"
    ],
    "name:epo_x_preferred":[
        "Juejang"
    ],
    "name:eus_x_preferred":[
        "Yueyang"
    ],
    "name:fas_x_preferred":[
        "\u06cc\u0648\u06cc\u0648\u0646\u06af"
    ],
    "name:fin_x_preferred":[
        "Yueyang"
    ],
    "name:fra_x_preferred":[
        "Yueyang"
    ],
    "name:hak_x_preferred":[
        "Ngo\u030dk-y\u00f2ng-s\u1e73"
    ],
    "name:ind_x_preferred":[
        "Yueyang"
    ],
    "name:ita_x_preferred":[
        "Yueyang"
    ],
    "name:jpn_x_preferred":[
        "\u5cb3\u967d\u5e02"
    ],
    "name:kik_x_preferred":[
        "Yueyang"
    ],
    "name:kor_x_preferred":[
        "\uc6e8\uc591\uc2dc"
    ],
    "name:mlg_x_preferred":[
        "Yueyang"
    ],
    "name:nld_x_preferred":[
        "Yueyang"
    ],
    "name:nno_x_preferred":[
        "Yueyang"
    ],
    "name:nor_x_preferred":[
        "Yueyang"
    ],
    "name:pam_x_preferred":[
        "Yueyang"
    ],
    "name:pol_x_preferred":[
        "Yueyang"
    ],
    "name:por_x_preferred":[
        "Yueyang"
    ],
    "name:rus_x_preferred":[
        "\u042e\u044d\u044f\u043d"
    ],
    "name:sco_x_preferred":[
        "Yueyang"
    ],
    "name:spa_x_preferred":[
        "Yueyang"
    ],
    "name:srp_x_preferred":[
        "\u0408\u0443\u0435\u0458\u0430\u043d\u0433"
    ],
    "name:swe_x_preferred":[
        "Yueyang"
    ],
    "name:szl_x_preferred":[
        "Yueyang"
    ],
    "name:tur_x_preferred":[
        "Yueyang"
    ],
    "name:urd_x_preferred":[
        "\u06cc\u0648\u0626\u06cc\u0627\u0646\u06af"
    ],
    "name:vie_x_preferred":[
        "Nh\u1ea1c D\u01b0\u01a1ng"
    ],
    "name:war_x_preferred":[
        "Yueyang"
    ],
    "name:zho_x_preferred":[
        "\u6708\u9633"
    ],
    "name:zho_x_variant":[
        "\u5cb3\u9633\u5e02"
    ],
    "wof:name":"Yueyang",
    "wof:placetype":"locality"
},
  "geometry": {"coordinates":[112.72548999999999,29.25069],"type":"Point"}
}