{
  "type": "Feature",
  "properties": {
    "gn:admin1_code":"14.0",
    "gn:asciiname":"Dobjoi",
    "gn:country_code":"CN",
    "gn:dem":3941,
    "gn:feature_class":"P",
    "gn:feature_code":"PPLA4",
    "gn:name":"Dobjoi",
    "gn:population":0,
    "gn:timezone":"Asia/Urumqi",
    "iso:country":"CN",
    "name:bod_x_preferred":[
        "Dobjoi"
    ],
    "name:msa_x_preferred":[
        "Dobjoi"
    ],
    "name:und_x_variant":[
        "Duojiao Xiang"
    ],
    "name:zho_x_preferred":[
        "Duojiao"
    ],
    "name:zho_x_variant":[
        "\u591a\u89d2",
        "\u591a\u89d2\u4e61"
    ],
    "wof:name":"Dobjoi",
    "wof:placetype":"locality"
},
  "geometry": {"coordinates":[89.06054,29.53331],"type":"Point"}
}