{
  "type": "Feature",
  "properties": {
    "gn:admin1_code":"19.0",
    "gn:asciiname":"Niudonggou",
    "gn:country_code":"CN",
    "gn:dem":226,
    "gn:feature_class":"P",
    "gn:feature_code":"PPL",
    "gn:name":"Niudonggou",
    "gn:population":0,
    "gn:timezone":"Asia/Shanghai",
    "iso:country":"CN",
    "name:und_x_variant":[
        "\u725b\u4e1c\u6c9f"
    ],
    "wof:name":"Niudonggou",
    "wof:placetype":"locality"
},
  "geometry": {"coordinates":[123.18173,40.87969],"type":"Point"}
}