{
  "type": "Feature",
  "properties": {
    "gn:admin1_code":"16.0",
    "gn:asciiname":"Xiachuanshan",
    "gn:country_code":"CN",
    "gn:dem":235,
    "gn:feature_class":"P",
    "gn:feature_code":"PPL",
    "gn:name":"Xiachuanshan",
    "gn:population":0,
    "gn:timezone":"Asia/Shanghai",
    "iso:country":"CN",
    "name:zho_x_preferred":[
        "\u4e0b\u7a7f\u5c71"
    ],
    "wof:name":"Xiachuanshan",
    "wof:placetype":"locality"
},
  "geometry": {"coordinates":[108.71599999999999,24.6739],"type":"Point"}
}