{
  "type": "Feature",
  "properties": {
    "gn:admin1_code":"3",
    "gn:asciiname":"Lianqian",
    "gn:country_code":"CN",
    "gn:dem":97,
    "gn:feature_class":"P",
    "gn:feature_code":"PPL",
    "gn:name":"Lianqian",
    "gn:population":0,
    "gn:timezone":"Asia/Shanghai",
    "iso:country":"CN",
    "name:und_x_variant":[
        "\u5e18\u524d"
    ],
    "wof:name":"Lianqian",
    "wof:placetype":"locality"
},
  "geometry": {"coordinates":[116.18548,27.48632000000001],"type":"Point"}
}