{
  "type": "Feature",
  "properties": {
    "gn:admin1_code":"3.0",
    "gn:asciiname":"Aotouping",
    "gn:country_code":"CN",
    "gn:dem":66,
    "gn:feature_class":"P",
    "gn:feature_code":"PPL",
    "gn:name":"Aotouping",
    "gn:population":0,
    "gn:timezone":"Asia/Shanghai",
    "iso:country":"CN",
    "name:und_x_variant":[
        "\u5773\u5934\u576a"
    ],
    "wof:name":"Aotouping",
    "wof:placetype":"locality"
},
  "geometry": {"coordinates":[115.13691,29.24069],"type":"Point"}
}