{
  "type": "Feature",
  "properties": {
    "gn:admin1_code":"32.0",
    "gn:asciiname":"Shuangchaomen",
    "gn:country_code":"CN",
    "gn:dem":320,
    "gn:feature_class":"P",
    "gn:feature_code":"PPL",
    "gn:name":"Shuangchaomen",
    "gn:population":0,
    "gn:timezone":"Asia/Shanghai",
    "iso:country":"CN",
    "name:zho_x_preferred":[
        "\u53cc\u671d\u95e8"
    ],
    "wof:name":"Shuangchaomen",
    "wof:placetype":"locality"
},
  "geometry": {"coordinates":[104.76064,28.82483],"type":"Point"}
}