{
  "type": "Feature",
  "properties": {
    "gn:admin1_code":"24.0",
    "gn:asciiname":"Doulin",
    "gn:country_code":"CN",
    "gn:dem":1717,
    "gn:feature_class":"P",
    "gn:feature_code":"PPL",
    "gn:name":"Doulin",
    "gn:population":0,
    "gn:timezone":"Asia/Shanghai",
    "iso:country":"CN",
    "name:zho_x_preferred":[
        "\u6597\u6797"
    ],
    "wof:name":"Doulin",
    "wof:placetype":"locality"
},
  "geometry": {"coordinates":[113.5823,40.27566],"type":"Point"}
}