{
  "type": "Feature",
  "properties": {
    "gn:admin1_code":"10",
    "gn:asciiname":"Huangtuling",
    "gn:country_code":"CN",
    "gn:dem":939,
    "gn:feature_class":"P",
    "gn:feature_code":"PPL",
    "gn:name":"Huangtuling",
    "gn:population":0,
    "gn:timezone":"Asia/Shanghai",
    "iso:country":"CN",
    "name:zho_x_preferred":[
        "\u9ec4\u571f\u5cad"
    ],
    "wof:name":"Huangtuling",
    "wof:placetype":"locality"
},
  "geometry": {"coordinates":[115.7851,40.96653],"type":"Point"}
}