{
  "type": "Feature",
  "properties": {
    "gn:admin1_code":"31.0",
    "gn:asciiname":"Jianbanyuan",
    "gn:country_code":"CN",
    "gn:dem":5,
    "gn:feature_class":"P",
    "gn:feature_code":"PPL",
    "gn:name":"Jianbanyuan",
    "gn:population":0,
    "gn:timezone":"Asia/Shanghai",
    "iso:country":"CN",
    "name:zho_x_preferred":[
        "\u526a\u534a\u56ed"
    ],
    "wof:name":"Jianbanyuan",
    "wof:placetype":"locality"
},
  "geometry": {"coordinates":[108.67908,19.14439],"type":"Point"}
}