{
  "type": "Feature",
  "properties": {
    "gn:admin1_code":"29.0",
    "gn:asciiname":"Jiade",
    "gn:country_code":"CN",
    "gn:dem":1678,
    "gn:feature_class":"P",
    "gn:feature_code":"PPL",
    "gn:name":"Jiade",
    "gn:population":0,
    "gn:timezone":"Asia/Shanghai",
    "iso:country":"CN",
    "name:zho_x_preferred":[
        "\u52a0\u7684"
    ],
    "wof:name":"Jiade",
    "wof:placetype":"locality"
},
  "geometry": {"coordinates":[101.971,23.3083],"type":"Point"}
}