{
  "type": "Feature",
  "properties": {
    "gn:admin1_code":"10",
    "gn:asciiname":"Xuzhangzi",
    "gn:country_code":"CN",
    "gn:dem":355,
    "gn:feature_class":"P",
    "gn:feature_code":"PPL",
    "gn:name":"Xuzhangzi",
    "gn:population":0,
    "gn:timezone":"Asia/Shanghai",
    "iso:country":"CN",
    "name:zho_x_preferred":[
        "\u8bb8\u6756\u5b50"
    ],
    "wof:name":"Xuzhangzi",
    "wof:placetype":"locality"
},
  "geometry": {"coordinates":[119.4813,40.44794],"type":"Point"}
}