{
  "type": "Feature",
  "properties": {
    "gn:admin1_code":"16.0",
    "gn:asciiname":"Fendiwo",
    "gn:country_code":"CN",
    "gn:dem":164,
    "gn:feature_class":"P",
    "gn:feature_code":"PPL",
    "gn:name":"Fendiwo",
    "gn:population":0,
    "gn:timezone":"Asia/Shanghai",
    "iso:country":"CN",
    "name:zho_x_preferred":[
        "\u575f\u5730\u7a9d"
    ],
    "wof:name":"Fendiwo",
    "wof:placetype":"locality"
},
  "geometry": {"coordinates":[110.417,22.5382],"type":"Point"}
}