{
  "type": "Feature",
  "properties": {
    "gn:admin1_code":"1.0",
    "gn:asciiname":"Caogangcun",
    "gn:country_code":"CN",
    "gn:dem":22,
    "gn:feature_class":"P",
    "gn:feature_code":"PPL",
    "gn:name":"Caogangcun",
    "gn:population":0,
    "gn:timezone":"Asia/Shanghai",
    "iso:country":"CN",
    "name:zho_x_preferred":[
        "\u8349\u5c97\u6751"
    ],
    "wof:name":"Caogangcun",
    "wof:placetype":"locality"
},
  "geometry": {"coordinates":[117.16330000000001,31.77757],"type":"Point"}
}