{
  "type": "Feature",
  "properties": {
    "gn:admin1_code":"33.0",
    "gn:asciiname":"Senjiping",
    "gn:country_code":"CN",
    "gn:dem":1265,
    "gn:feature_class":"P",
    "gn:feature_code":"PPL",
    "gn:name":"Senjiping",
    "gn:population":0,
    "gn:timezone":"Asia/Shanghai",
    "iso:country":"CN",
    "name:zho_x_preferred":[
        "\u68ee\u57fa\u576a"
    ],
    "wof:name":"Senjiping",
    "wof:placetype":"locality"
},
  "geometry": {"coordinates":[109.25624000000001,31.52025],"type":"Point"}
}