{
  "type": "Feature",
  "properties": {
    "gn:admin1_code":"12",
    "gn:asciiname":"Huanghualao",
    "gn:country_code":"CN",
    "gn:dem":30,
    "gn:feature_class":"P",
    "gn:feature_code":"PPL",
    "gn:name":"Huanghualao",
    "gn:population":0,
    "gn:timezone":"Asia/Shanghai",
    "iso:country":"CN",
    "name:und_x_variant":[
        "\u9ec4\u82b1\u6d9d"
    ],
    "wof:name":"Huanghualao",
    "wof:placetype":"locality"
},
  "geometry": {"coordinates":[114.1905,30.72424],"type":"Point"}
}