{
  "type": "Feature",
  "properties": {
    "gn:admin1_code":"14.0",
    "gn:asciiname":"Norma",
    "gn:country_code":"CN",
    "gn:dem":4124,
    "gn:feature_class":"P",
    "gn:feature_code":"PPLF",
    "gn:name":"Norma",
    "gn:population":0,
    "gn:timezone":"Asia/Urumqi",
    "iso:country":"CN",
    "name:bod_x_preferred":[
        "Norma"
    ],
    "name:zho_x_preferred":[
        "Luoma"
    ],
    "name:zho_x_variant":[
        "\u6d1b\u739b",
        "Bushinang",
        "\u5821\u4e16\u56ca"
    ],
    "wof:name":"Norma",
    "wof:placetype":"locality"
},
  "geometry": {"coordinates":[97.59801,31.97627],"type":"Point"}
}