{
  "type": "Feature",
  "properties": {
    "gn:admin1_code":"9.0",
    "gn:asciiname":"Shanguai",
    "gn:country_code":"CN",
    "gn:dem":125,
    "gn:feature_class":"P",
    "gn:feature_code":"PPL",
    "gn:name":"Shanguai",
    "gn:population":0,
    "gn:timezone":"Asia/Shanghai",
    "iso:country":"CN",
    "name:zho_x_preferred":[
        "\u95ea\u62d0"
    ],
    "wof:name":"Shanguai",
    "wof:placetype":"locality"
},
  "geometry": {"coordinates":[112.9641,35.13336],"type":"Point"}
}