{
  "type": "Feature",
  "properties": {
    "gn:admin1_code":"3",
    "gn:asciiname":"Dengdun",
    "gn:country_code":"CN",
    "gn:dem":31,
    "gn:feature_class":"P",
    "gn:feature_code":"PPLA4",
    "gn:name":"Dengdun",
    "gn:population":0,
    "gn:timezone":"Asia/Shanghai",
    "iso:country":"CN",
    "name:und_x_variant":[
        "\u9093\u58a9",
        "Dengdun Xiang",
        "\u9093\u58a9\u4e61"
    ],
    "wof:name":"Dengdun",
    "wof:placetype":"locality"
},
  "geometry": {"coordinates":[116.57632,28.3996],"type":"Point"}
}