{
  "type": "Feature",
  "properties": {
    "gn:admin1_code":"15.0",
    "gn:asciiname":"Shaogouwan",
    "gn:country_code":"CN",
    "gn:dem":1908,
    "gn:feature_class":"P",
    "gn:feature_code":"PPL",
    "gn:name":"Shaogouwan",
    "gn:population":0,
    "gn:timezone":"Asia/Shanghai",
    "iso:country":"CN",
    "name:und_x_variant":[
        "\u7a0d\u6c9f\u6e7e"
    ],
    "wof:name":"Shaogouwan",
    "wof:placetype":"locality"
},
  "geometry": {"coordinates":[106.45614,36.55513],"type":"Point"}
}