{
  "type": "Feature",
  "properties": {
    "gn:admin1_code":"29.0",
    "gn:asciiname":"Daqingshu",
    "gn:country_code":"CN",
    "gn:dem":1137,
    "gn:feature_class":"P",
    "gn:feature_code":"PPL",
    "gn:name":"Daqingshu",
    "gn:population":0,
    "gn:timezone":"Asia/Shanghai",
    "iso:country":"CN",
    "name:zho_x_preferred":[
        "\u5927\u9752\u6811"
    ],
    "wof:name":"Daqingshu",
    "wof:placetype":"locality"
},
  "geometry": {"coordinates":[100.803,22.7236],"type":"Point"}
}