{
  "type": "Feature",
  "properties": {
    "gn:admin1_code":"10",
    "gn:asciiname":"Shiquanhe",
    "gn:country_code":"CN",
    "gn:dem":1004,
    "gn:feature_class":"P",
    "gn:feature_code":"PPL",
    "gn:name":"Shiquanhe",
    "gn:population":0,
    "gn:timezone":"Asia/Shanghai",
    "iso:country":"CN",
    "name:ara_x_preferred":[
        "\u0634\u064a\u0643\u0648\u0627\u0646\u0647\u064a"
    ],
    "name:deu_x_preferred":[
        "S\u00eangg\u00ea Zangbo"
    ],
    "name:fas_x_preferred":[
        "\u0634\u06cc\u06a9\u0648\u0627\u0646\u0647"
    ],
    "name:fra_x_preferred":[
        "Shiquanhe"
    ],
    "name:hin_x_preferred":[
        "\u0906\u0932\u0940"
    ],
    "name:msa_x_preferred":[
        "Shiquanhe"
    ],
    "name:zho_x_preferred":[
        "\u77f3\u6cc9\u6cb3"
    ],
    "name:zho_x_variant":[
        "\u72ee\u6cc9\u6cb3\u9547"
    ],
    "wof:name":"Shiquanhe",
    "wof:placetype":"locality"
},
  "geometry": {"coordinates":[118.26246999999999,42.03468],"type":"Point"}
}