{
  "type": "Feature",
  "properties": {
    "gn:admin1_code":"10",
    "gn:asciiname":"Shiquanhe",
    "gn:country_code":"CN",
    "gn:dem":1004,
    "gn:feature_class":"P",
    "gn:feature_code":"PPL",
    "gn:name":"Shiquanhe",
    "gn:population":0,
    "gn:timezone":"Asia/Shanghai",
    "iso:country":"CN",
    "name:zho_x_preferred":[
        "\u77f3\u6cc9\u6cb3"
    ],
    "wof:name":"Shiquanhe",
    "wof:placetype":"locality"
},
  "geometry": {"coordinates":[118.26246999999999,42.03468],"type":"Point"}
}