{
  "type": "Feature",
  "properties": {
    "gn:admin1_code":"9.0",
    "gn:asciiname":"Mawan",
    "gn:country_code":"CN",
    "gn:dem":78,
    "gn:feature_class":"P",
    "gn:feature_code":"PPL",
    "gn:name":"Mawan",
    "gn:population":0,
    "gn:timezone":"Asia/Shanghai",
    "iso:country":"CN",
    "name:ceb_x_preferred":[
        "Mawan"
    ],
    "name:swe_x_preferred":[
        "Mawan"
    ],
    "name:zho_x_preferred":[
        "\u9a6c\u6e7e"
    ],
    "wof:name":"Mawan",
    "wof:placetype":"locality"
},
  "geometry": {"coordinates":[113.56019000000001,33.68810999999999],"type":"Point"}
}