{
  "type": "Feature",
  "properties": {
    "gn:admin1_code":"25",
    "gn:asciiname":"Dongmijiahe",
    "gn:country_code":"CN",
    "gn:dem":17,
    "gn:feature_class":"P",
    "gn:feature_code":"PPL",
    "gn:name":"Dongmijiahe",
    "gn:population":0,
    "gn:timezone":"Asia/Shanghai",
    "iso:country":"CN",
    "name:zho_x_preferred":[
        "\u4e1c\u5f2d\u5bb6\u6cb3"
    ],
    "wof:name":"Dongmijiahe",
    "wof:placetype":"locality"
},
  "geometry": {"coordinates":[116.804,37.5888],"type":"Point"}
}