{
  "type": "Feature",
  "properties": {
    "gn:admin1_code":"32.0",
    "gn:asciiname":"Feihongqiao",
    "gn:country_code":"CN",
    "gn:dem":1779,
    "gn:feature_class":"P",
    "gn:feature_code":"PPL",
    "gn:name":"Feihongqiao",
    "gn:population":0,
    "gn:timezone":"Asia/Shanghai",
    "iso:country":"CN",
    "name:zho_x_preferred":[
        "\u98de\u8679\u6865"
    ],
    "wof:name":"Feihongqiao",
    "wof:placetype":"locality"
},
  "geometry": {"coordinates":[103.72319,31.82664],"type":"Point"}
}