{
  "type": "Feature",
  "properties": {
    "gn:admin1_code":"3.0",
    "gn:asciiname":"Peimo",
    "gn:country_code":"CN",
    "gn:dem":86,
    "gn:feature_class":"P",
    "gn:feature_code":"PPL",
    "gn:name":"Peimo",
    "gn:population":0,
    "gn:timezone":"Asia/Shanghai",
    "iso:country":"CN",
    "name:und_x_variant":[
        "\u57f9\u6a21"
    ],
    "wof:name":"Peimo",
    "wof:placetype":"locality"
},
  "geometry": {"coordinates":[114.93532,27.17503],"type":"Point"}
}