{
  "type": "Feature",
  "properties": {
    "gn:admin1_code":"32.0",
    "gn:asciiname":"Yige",
    "gn:country_code":"CN",
    "gn:dem":3375,
    "gn:feature_class":"P",
    "gn:feature_code":"PPL",
    "gn:name":"Yige",
    "gn:population":0,
    "gn:timezone":"Asia/Shanghai",
    "iso:country":"CN",
    "name:zho_x_preferred":[
        "\u610f\u683c"
    ],
    "wof:name":"Yige",
    "wof:placetype":"locality"
},
  "geometry": {"coordinates":[101.116,31.0632],"type":"Point"}
}