{
  "type": "Feature",
  "properties": {
    "gn:admin1_code":"18",
    "gn:asciiname":"Fanbei",
    "gn:country_code":"CN",
    "gn:dem":1212,
    "gn:feature_class":"P",
    "gn:feature_code":"PPL",
    "gn:name":"Fanbei",
    "gn:population":0,
    "gn:timezone":"Asia/Shanghai",
    "iso:country":"CN",
    "name:zho_x_preferred":[
        "\u53cd\u80cc"
    ],
    "wof:name":"Fanbei",
    "wof:placetype":"locality"
},
  "geometry": {"coordinates":[106.56100000000001,28.6566],"type":"Point"}
}