{
  "type": "Feature",
  "properties": {
    "gn:admin1_code":"24",
    "gn:asciiname":"Zhengbianbu",
    "gn:country_code":"CN",
    "gn:dem":1405,
    "gn:feature_class":"P",
    "gn:feature_code":"PPL",
    "gn:name":"Zhengbianbu",
    "gn:population":0,
    "gn:timezone":"Asia/Shanghai",
    "iso:country":"CN",
    "name:und_x_variant":[
        "Chen-pien-pao",
        "Zhenbianbu",
        "Chen-pien-p\u2019u",
        "Zhengbianbu"
    ],
    "name:zho_x_preferred":[
        "\u6b63\u8fb9\u5821"
    ],
    "wof:name":"Zhengbianbu",
    "wof:placetype":"locality"
},
  "geometry": {"coordinates":[113.51262,40.32395],"type":"Point"}
}