{
  "type": "Feature",
  "properties": {
    "gn:admin1_code":"16",
    "gn:asciiname":"Wenjiazhuang",
    "gn:country_code":"CN",
    "gn:dem":381,
    "gn:feature_class":"P",
    "gn:feature_code":"PPL",
    "gn:name":"Wenjiazhuang",
    "gn:population":0,
    "gn:timezone":"Asia/Shanghai",
    "iso:country":"CN",
    "name:zho_x_preferred":[
        "\u6587\u7532\u5e84"
    ],
    "wof:name":"Wenjiazhuang",
    "wof:placetype":"locality"
},
  "geometry": {"coordinates":[111.169,25.8218],"type":"Point"}
}