{
  "type": "Feature",
  "properties": {
    "gn:admin1_code":"26.0",
    "gn:asciiname":"Qinjiagoukou",
    "gn:country_code":"CN",
    "gn:dem":1286,
    "gn:feature_class":"P",
    "gn:feature_code":"PPL",
    "gn:name":"Qinjiagoukou",
    "gn:population":0,
    "gn:timezone":"Asia/Shanghai",
    "iso:country":"CN",
    "name:zho_x_preferred":[
        "\u79e6\u5bb6\u6c9f\u53e3"
    ],
    "wof:name":"Qinjiagoukou",
    "wof:placetype":"locality"
},
  "geometry": {"coordinates":[109.60278,33.85456],"type":"Point"}
}