{
  "type": "Feature",
  "properties": {
    "gn:admin1_code":"14",
    "gn:asciiname":"Xiajiao",
    "gn:country_code":"CN",
    "gn:dem":4386,
    "gn:feature_class":"P",
    "gn:feature_code":"PPL",
    "gn:name":"Xiajiao",
    "gn:population":0,
    "gn:timezone":"Asia/Urumqi",
    "iso:country":"CN",
    "name:zho_x_preferred":[
        "\u971e\u811a"
    ],
    "wof:name":"Xiajiao",
    "wof:placetype":"locality"
},
  "geometry": {"coordinates":[89.7246,29.0881],"type":"Point"}
}