{
  "type": "Feature",
  "properties": {
    "gn:admin1_code":"12.0",
    "gn:asciiname":"Yanglaoyan",
    "gn:country_code":"CN",
    "gn:dem":43,
    "gn:feature_class":"P",
    "gn:feature_code":"PPL",
    "gn:name":"Yanglaoyan",
    "gn:population":0,
    "gn:timezone":"Asia/Shanghai",
    "iso:country":"CN",
    "name:zho_x_preferred":[
        "Yanglaoyan"
    ],
    "name:zho_x_variant":[
        "\u517b\u8001\u5830"
    ],
    "wof:name":"Yanglaoyan",
    "wof:placetype":"locality"
},
  "geometry": {"coordinates":[111.77753,29.99364000000001],"type":"Point"}
}