{
  "type": "Feature",
  "properties": {
    "gn:admin1_code":"19.0",
    "gn:asciiname":"Lengtangcun",
    "gn:country_code":"CN",
    "gn:dem":285,
    "gn:feature_class":"P",
    "gn:feature_code":"PPL",
    "gn:name":"Lengtangcun",
    "gn:population":0,
    "gn:timezone":"Asia/Shanghai",
    "iso:country":"CN",
    "name:zho_x_preferred":[
        "\u51b7\u6c64\u6751"
    ],
    "wof:name":"Lengtangcun",
    "wof:placetype":"locality"
},
  "geometry": {"coordinates":[121.773,42.3395],"type":"Point"}
}