{
  "type": "Feature",
  "properties": {
    "gn:admin1_code":"30",
    "gn:asciiname":"Fubin",
    "gn:country_code":"CN",
    "gn:dem":36,
    "gn:feature_class":"P",
    "gn:feature_code":"PPLA4",
    "gn:name":"Fubin",
    "gn:population":0,
    "gn:timezone":"Asia/Shanghai",
    "iso:country":"CN",
    "name:und_x_variant":[
        "Fubin Zhen",
        "\u6d6e\u6ee8\u9547"
    ],
    "name:zho_x_preferred":[
        "\u6d6e\u6ee8"
    ],
    "wof:name":"Fubin",
    "wof:placetype":"locality"
},
  "geometry": {"coordinates":[116.85706999999999,23.84472],"type":"Point"}
}