{
  "type": "Feature",
  "properties": {
    "gn:admin1_code":"18",
    "gn:asciiname":"Xibu",
    "gn:country_code":"CN",
    "gn:dem":725,
    "gn:feature_class":"P",
    "gn:feature_code":"PPL",
    "gn:name":"Xibu",
    "gn:population":0,
    "gn:timezone":"Asia/Shanghai",
    "iso:country":"CN",
    "name:zho_x_preferred":[
        "\u559c\u5e03"
    ],
    "name:zho_x_variant":[
        "\u897f\u57d4\u9547"
    ],
    "wof:name":"Xibu",
    "wof:placetype":"locality"
},
  "geometry": {"coordinates":[106.015,25.5104],"type":"Point"}
}