{
  "type": "Feature",
  "properties": {
    "gn:admin1_code":"15.0",
    "gn:asciiname":"Cegaogama",
    "gn:country_code":"CN",
    "gn:dem":3356,
    "gn:feature_class":"P",
    "gn:feature_code":"PPL",
    "gn:name":"Cegaogama",
    "gn:population":0,
    "gn:timezone":"Asia/Shanghai",
    "iso:country":"CN",
    "name:und_x_variant":[
        "\u7b56\u9ad8\u5c15\u9a6c"
    ],
    "wof:name":"Cegaogama",
    "wof:placetype":"locality"
},
  "geometry": {"coordinates":[103.09175999999999,35.03122],"type":"Point"}
}