{
  "type": "Feature",
  "properties": {
    "gn:admin1_code":"4.0",
    "gn:asciiname":"Dadingying",
    "gn:country_code":"CN",
    "gn:dem":28,
    "gn:feature_class":"P",
    "gn:feature_code":"PPL",
    "gn:name":"Dadingying",
    "gn:population":0,
    "gn:timezone":"Asia/Shanghai",
    "iso:country":"CN",
    "name:zho_x_preferred":[
        "\u5927\u4e01\u8425"
    ],
    "wof:name":"Dadingying",
    "wof:placetype":"locality"
},
  "geometry": {"coordinates":[118.76832,32.41742],"type":"Point"}
}