{
  "type": "Feature",
  "properties": {
    "gn:admin1_code":"4.0",
    "gn:asciiname":"Zhonglinzicun",
    "gn:country_code":"CN",
    "gn:dem":1,
    "gn:feature_class":"P",
    "gn:feature_code":"PPL",
    "gn:name":"Zhonglinzicun",
    "gn:population":0,
    "gn:timezone":"Asia/Shanghai",
    "iso:country":"CN",
    "name:zho_x_preferred":[
        "\u4e2d\u6797\u5b50\u6751"
    ],
    "wof:name":"Zhonglinzicun",
    "wof:placetype":"locality"
},
  "geometry": {"coordinates":[119.24988,35.07928],"type":"Point"}
}