{
  "type": "Feature",
  "properties": {
    "gn:admin1_code":"32.0",
    "gn:asciiname":"Wangjia Dangdang",
    "gn:country_code":"CN",
    "gn:dem":1721,
    "gn:feature_class":"P",
    "gn:feature_code":"PPL",
    "gn:name":"Wangjia Dangdang",
    "gn:population":0,
    "gn:timezone":"Asia/Shanghai",
    "iso:country":"CN",
    "name:zho_x_preferred":[
        "\u738b\u5bb6\u51fc\u51fc"
    ],
    "wof:name":"Wangjia Dangdang",
    "wof:placetype":"locality"
},
  "geometry": {"coordinates":[102.881,29.3212],"type":"Point"}
}