{
  "type": "Feature",
  "properties": {
    "gn:admin1_code":"32.0",
    "gn:asciiname":"Heli",
    "gn:country_code":"CN",
    "gn:dem":1788,
    "gn:feature_class":"P",
    "gn:feature_code":"PPL",
    "gn:name":"Heli",
    "gn:population":0,
    "gn:timezone":"Asia/Shanghai",
    "iso:country":"CN",
    "name:cat_x_preferred":[
        "Heli"
    ],
    "name:deu_x_preferred":[
        "Heli"
    ],
    "name:fin_x_preferred":[
        "Heli"
    ],
    "name:nld_x_preferred":[
        "Heli"
    ],
    "name:zho_x_preferred":[
        "\u6cb3\u91cc"
    ],
    "wof:name":"Heli",
    "wof:placetype":"locality"
},
  "geometry": {"coordinates":[102.0776,28.34552],"type":"Point"}
}