{
  "type": "Feature",
  "properties": {
    "gn:admin1_code":"8.0",
    "gn:asciiname":"Chang'ancun",
    "gn:country_code":"CN",
    "gn:dem":208,
    "gn:feature_class":"P",
    "gn:feature_code":"PPL",
    "gn:name":"Chang\u2019ancun",
    "gn:population":0,
    "gn:timezone":"Asia/Shanghai",
    "iso:country":"CN",
    "name:und_x_variant":[
        "Chang\u2019ancun"
    ],
    "name:zho_x_preferred":[
        "\u957f\u5b89\u6751"
    ],
    "wof:name":"Chang'ancun",
    "wof:placetype":"locality"
},
  "geometry": {"coordinates":[130.74818999999999,46.44306],"type":"Point"}
}