{
  "type": "Feature",
  "properties": {
    "gn:admin1_code":"15.0",
    "gn:asciiname":"Canmudaokehe",
    "gn:country_code":"CN",
    "gn:dem":3057,
    "gn:feature_class":"P",
    "gn:feature_code":"PPL",
    "gn:name":"Canmudaokehe",
    "gn:population":0,
    "gn:timezone":"Asia/Shanghai",
    "iso:country":"CN",
    "name:und_x_variant":[
        "\u53c2\u6728\u9053\u53ef\u5408"
    ],
    "wof:name":"Canmudaokehe",
    "wof:placetype":"locality"
},
  "geometry": {"coordinates":[103.07585,34.78305],"type":"Point"}
}