{
  "type": "Feature",
  "properties": {
    "gn:admin1_code":"10.0",
    "gn:asciiname":"Yanxiaoli",
    "gn:country_code":"CN",
    "gn:dem":21,
    "gn:feature_class":"P",
    "gn:feature_code":"PPL",
    "gn:name":"Yanxiaoli",
    "gn:population":0,
    "gn:timezone":"Asia/Shanghai",
    "iso:country":"CN",
    "name:zho_x_preferred":[
        "\u71d5\u79c0\u91cc"
    ],
    "wof:name":"Yanxiaoli",
    "wof:placetype":"locality"
},
  "geometry": {"coordinates":[119.60435,39.9569],"type":"Point"}
}