{
  "type": "Feature",
  "properties": {
    "gn:admin1_code":"18",
    "gn:asciiname":"Yanjiawan",
    "gn:country_code":"CN",
    "gn:dem":835,
    "gn:feature_class":"P",
    "gn:feature_code":"PPL",
    "gn:name":"Yanjiawan",
    "gn:population":0,
    "gn:timezone":"Asia/Shanghai",
    "iso:country":"CN",
    "name:zho_x_preferred":[
        "\u4e25\u5bb6\u6e7e"
    ],
    "wof:name":"Yanjiawan",
    "wof:placetype":"locality"
},
  "geometry": {"coordinates":[107.048,27.5858],"type":"Point"}
}