{
  "type": "Feature",
  "properties": {
    "gn:admin1_code":"33.0",
    "gn:asciiname":"Zhaojiawan",
    "gn:country_code":"CN",
    "gn:dem":841,
    "gn:feature_class":"P",
    "gn:feature_code":"PPL",
    "gn:name":"Zhaojiawan",
    "gn:population":0,
    "gn:timezone":"Asia/Shanghai",
    "iso:country":"CN",
    "name:zho_x_preferred":[
        "\u8d75\u5bb6\u5f2f"
    ],
    "wof:name":"Zhaojiawan",
    "wof:placetype":"locality"
},
  "geometry": {"coordinates":[108.59896999999999,28.99556],"type":"Point"}
}