{
  "type": "Feature",
  "properties": {
    "gn:admin1_code":"11.0",
    "gn:asciiname":"Shujiatang",
    "gn:country_code":"CN",
    "gn:dem":247,
    "gn:feature_class":"P",
    "gn:feature_code":"PPL",
    "gn:name":"Shujiatang",
    "gn:population":0,
    "gn:timezone":"Asia/Shanghai",
    "iso:country":"CN",
    "name:zho_x_preferred":[
        "\u8212\u5bb6\u5858"
    ],
    "wof:name":"Shujiatang",
    "wof:placetype":"locality"
},
  "geometry": {"coordinates":[110.54758,27.933],"type":"Point"}
}