{
  "type": "Feature",
  "properties": {
    "gn:admin1_code":"7",
    "gn:asciiname":"Cunwei",
    "gn:country_code":"CN",
    "gn:dem":614,
    "gn:feature_class":"P",
    "gn:feature_code":"PPL",
    "gn:name":"Cunwei",
    "gn:population":0,
    "gn:timezone":"Asia/Shanghai",
    "iso:country":"CN",
    "name:und_x_variant":[
        "\u6751\u5c3e",
        "Cunwei"
    ],
    "wof:name":"Cunwei",
    "wof:placetype":"locality"
},
  "geometry": {"coordinates":[119.56265999999999,27.39621],"type":"Point"}
}