{
  "type": "Feature",
  "properties": {
    "gn:country":"CN",
    "gn:fcode":"PPLA3",
    "gn:population":145440,
    "iso:country":"CN",
    "name:ara_x_preferred":[
        "\u062a\u0627\u064a\u0634\u0627\u0646"
    ],
    "name:eng_x_preferred":[
        "Taishan"
    ],
    "name:fas_x_preferred":[
        "\u062a\u0627\u06cc\u0634\u0627\u0646"
    ],
    "name:hak_x_preferred":[
        "Th\u00f2i-s\u00e2n-s\u1e73"
    ],
    "name:heb_x_preferred":[
        "\u05d8\u05d0\u05d9\u05e9\u05d0\u05df"
    ],
    "name:jpn_x_preferred":[
        "\u53f0\u5c71\u5e02"
    ],
    "name:kor_x_preferred":[
        "\ud0c0\uc774\uc0b0 \uc2dc"
    ],
    "name:pnb_x_preferred":[
        "\u062a\u0627\u0626\u06cc\u0634\u0627\u0646"
    ],
    "name:rus_x_preferred":[
        "\u0422\u0430\u0439\u0448\u0430\u043d\u044c"
    ],
    "name:und_x_variant":[
        "Hsin-ning"
    ],
    "name:urd_x_preferred":[
        "\u062a\u0627\u0626\u0634\u0627\u0646"
    ],
    "name:vie_x_preferred":[
        "\u0110\u00e0i S\u01a1n"
    ],
    "name:yue_x_preferred":[
        "\u53f0\u5c71"
    ],
    "name:zho_x_preferred":[
        "\u53f0\u57ce"
    ],
    "name:zho_x_variant":[
        "\u53f0\u57ce\u8857\u9053",
        "\u53f0\u5c71",
        "\u53f0\u5c71\u5e02"
    ],
    "qs_pg:aaroncc":"CN",
    "qs_pg:gn_country":"CN",
    "qs_pg:gn_fcode":"PPLA3",
    "qs_pg:gn_pop":145440,
    "qs_pg:name":"\u53f0\u5c71\u5e02",
    "qs_pg:name_adm0":"\u4e2d\u570b",
    "qs_pg:name_adm1":"\u5e7f\u4e1c\u7701",
    "qs_pg:photos":77,
    "qs_pg:photos_1k":16,
    "qs_pg:photos_9k":2,
    "qs_pg:photos_9r":5,
    "qs_pg:photos_all":442,
    "qs_pg:photos_sr":3,
    "qs_pg:pop_sr":9,
    "qs_pg:qs_pg_placetype":"localadmin",
    "qs_pg:qs_pg_placetype_gp":"LocalAdmin",
    "qs_pg:woe_adm0":23424781,
    "woe:adm0_id":23424781,
    "woe:name_adm0":"\u4e2d\u570b",
    "woe:name_adm1":"\u5e7f\u4e1c\u7701",
    "woe:placetype":"LocalAdmin",
    "wof:name":"\u53f0\u5c71\u5e02",
    "wof:placetype":"localadmin",
    "wof:population":145440
},
  "geometry": {"coordinates":[112.7799,22.25135],"type":"Point"}
}