{
  "type": "Feature",
  "properties": {
    "gn:admin1_code":"12.0",
    "gn:asciiname":"Zhangjia Chapeng",
    "gn:country_code":"CN",
    "gn:dem":78,
    "gn:feature_class":"P",
    "gn:feature_code":"PPL",
    "gn:name":"Zhangjia Chapeng",
    "gn:population":0,
    "gn:timezone":"Asia/Shanghai",
    "iso:country":"CN",
    "name:zho_x_preferred":[
        "\u5f20\u5bb6\u8336\u68da"
    ],
    "wof:name":"Zhangjia Chapeng",
    "wof:placetype":"locality"
},
  "geometry": {"coordinates":[113.45887,31.09554],"type":"Point"}
}