{
  "type": "Feature",
  "properties": {
    "gn:admin1_code":"7.0",
    "gn:asciiname":"Yang'an",
    "gn:country_code":"CN",
    "gn:dem":211,
    "gn:feature_class":"P",
    "gn:feature_code":"PPL",
    "gn:name":"Yang\u2019an",
    "gn:population":0,
    "gn:timezone":"Asia/Shanghai",
    "iso:country":"CN",
    "name:zho_x_preferred":[
        "Yang\u2019an"
    ],
    "name:zho_x_variant":[
        "\u6d0b\u5b89"
    ],
    "wof:name":"Yang'an",
    "wof:placetype":"locality"
},
  "geometry": {"coordinates":[118.04142,26.74749000000001],"type":"Point"}
}