{
  "type": "Feature",
  "properties": {
    "gn:admin1_code":"19.0",
    "gn:asciiname":"Xujia Buzicun",
    "gn:country_code":"CN",
    "gn:dem":15,
    "gn:feature_class":"P",
    "gn:feature_code":"PPL",
    "gn:name":"Xujia Buzicun",
    "gn:population":0,
    "gn:timezone":"Asia/Shanghai",
    "iso:country":"CN",
    "name:zho_x_preferred":[
        "\u5f90\u5bb6\u5821\u5b50\u6751"
    ],
    "wof:name":"Xujia Buzicun",
    "wof:placetype":"locality"
},
  "geometry": {"coordinates":[123.607,40.0021],"type":"Point"}
}