{
  "type": "Feature",
  "properties": {
    "gn:admin1_code":"11.0",
    "gn:asciiname":"Dachihu",
    "gn:country_code":"CN",
    "gn:dem":678,
    "gn:feature_class":"P",
    "gn:feature_code":"PPL",
    "gn:name":"Dachihu",
    "gn:population":0,
    "gn:timezone":"Asia/Shanghai",
    "iso:country":"CN",
    "name:zho_x_preferred":[
        "\u5927\u6c60\u6e56"
    ],
    "wof:name":"Dachihu",
    "wof:placetype":"locality"
},
  "geometry": {"coordinates":[111.08592,28.25393],"type":"Point"}
}