{
  "type": "Feature",
  "properties": {
    "gn:admin1_code":"26.0",
    "gn:asciiname":"Tianjingyuan",
    "gn:country_code":"CN",
    "gn:dem":1347,
    "gn:feature_class":"P",
    "gn:feature_code":"PPL",
    "gn:name":"Tianjingyuan",
    "gn:population":0,
    "gn:timezone":"Asia/Shanghai",
    "iso:country":"CN",
    "name:zho_x_preferred":[
        "\u5929\u4e95\u9662"
    ],
    "wof:name":"Tianjingyuan",
    "wof:placetype":"locality"
},
  "geometry": {"coordinates":[109.63301,33.78803],"type":"Point"}
}