{
  "type": "Feature",
  "properties": {
    "gn:admin1_code":"1.0",
    "gn:asciiname":"Lanxi",
    "gn:country_code":"CN",
    "gn:dem":127,
    "gn:feature_class":"P",
    "gn:feature_code":"PPL",
    "gn:name":"Lanxi",
    "gn:population":0,
    "gn:timezone":"Asia/Shanghai",
    "iso:country":"CN",
    "name:zho_x_preferred":[
        "Lanxi"
    ],
    "name:zho_x_variant":[
        "\u5170\u6eaa"
    ],
    "wof:name":"Lanxi",
    "wof:placetype":"locality"
},
  "geometry": {"coordinates":[119.19438999999998,30.56938],"type":"Point"}
}