{
  "type": "Feature",
  "properties": {
    "gn:admin1_code":"29.0",
    "gn:asciiname":"Saiqili",
    "gn:country_code":"CN",
    "gn:dem":2632,
    "gn:feature_class":"P",
    "gn:feature_code":"PPL",
    "gn:name":"Saiqili",
    "gn:population":0,
    "gn:timezone":"Asia/Shanghai",
    "iso:country":"CN",
    "name:zho_x_preferred":[
        "\u8d5b\u4e03\u91cc"
    ],
    "wof:name":"Saiqili",
    "wof:placetype":"locality"
},
  "geometry": {"coordinates":[99.6026,27.0666],"type":"Point"}
}