{
  "type": "Feature",
  "properties": {
    "gn:admin1_code":"29.0",
    "gn:asciiname":"Mangjing Shangzhai",
    "gn:country_code":"CN",
    "gn:dem":1396,
    "gn:feature_class":"P",
    "gn:feature_code":"PPL",
    "gn:name":"Mangjing Shangzhai",
    "gn:population":0,
    "gn:timezone":"Asia/Shanghai",
    "iso:country":"CN",
    "name:zho_x_preferred":[
        "\u8292\u666f\u4e0a\u5be8"
    ],
    "wof:name":"Mangjing Shangzhai",
    "wof:placetype":"locality"
},
  "geometry": {"coordinates":[100.015,22.1608],"type":"Point"}
}