{
  "type": "Feature",
  "properties": {
    "gn:admin1_code":"32.0",
    "gn:asciiname":"Zhatuo",
    "gn:country_code":"CN",
    "gn:dem":3253,
    "gn:feature_class":"P",
    "gn:feature_code":"PPL",
    "gn:name":"Zhatuo",
    "gn:population":0,
    "gn:timezone":"Asia/Shanghai",
    "iso:country":"CN",
    "name:zho_x_preferred":[
        "\u624e\u62d6"
    ],
    "wof:name":"Zhatuo",
    "wof:placetype":"locality"
},
  "geometry": {"coordinates":[101.50995,29.12341],"type":"Point"}
}