{
  "type": "Feature",
  "properties": {
    "gn:admin1_code":"12.0",
    "gn:asciiname":"Xiangyaping",
    "gn:country_code":"CN",
    "gn:dem":534,
    "gn:feature_class":"P",
    "gn:feature_code":"PPL",
    "gn:name":"Xiangyaping",
    "gn:population":0,
    "gn:timezone":"Asia/Shanghai",
    "iso:country":"CN",
    "name:zho_x_preferred":[
        "\u8c61\u7259\u576a"
    ],
    "wof:name":"Xiangyaping",
    "wof:placetype":"locality"
},
  "geometry": {"coordinates":[110.50275999999999,32.44698],"type":"Point"}
}