{
  "type": "Feature",
  "properties": {
    "gn:admin1_code":"15.0",
    "gn:asciiname":"Gaofeng",
    "gn:country_code":"CN",
    "gn:dem":2074,
    "gn:feature_class":"P",
    "gn:feature_code":"PPL",
    "gn:name":"Gaofeng",
    "gn:population":0,
    "gn:timezone":"Asia/Shanghai",
    "iso:country":"CN",
    "name:zho_x_preferred":[
        "\u9ad8\u98ce"
    ],
    "wof:name":"Gaofeng",
    "wof:placetype":"locality"
},
  "geometry": {"coordinates":[103.492,36.076],"type":"Point"}
}