{
  "type": "Feature",
  "properties": {
    "gn:admin1_code":"08",
    "gn:asciiname":"Xingnong",
    "gn:country_code":"CN",
    "gn:dem":261,
    "gn:feature_class":"P",
    "gn:feature_code":"PPLA4",
    "gn:name":"Xingnong",
    "gn:population":0,
    "gn:timezone":"Asia/Shanghai",
    "iso:country":"CN",
    "name:und_x_variant":[
        "Xingnong Zhen"
    ],
    "name:zho_x_preferred":[
        "\u5174\u519c"
    ],
    "name:zho_x_variant":[
        "\u5174\u519c\u9547"
    ],
    "wof:name":"Xingnong",
    "wof:placetype":"locality"
},
  "geometry": {"coordinates":[130.94633000000002,45.50136],"type":"Point"}
}