{
  "type": "Feature",
  "properties": {
    "gn:admin1_code":"13.0",
    "gn:asciiname":"A'leike Aiqike",
    "gn:country_code":"CN",
    "gn:dem":2092,
    "gn:feature_class":"P",
    "gn:feature_code":"PPL",
    "gn:name":"A\u2019leike Aiqike",
    "gn:population":0,
    "gn:timezone":"Asia/Shanghai",
    "iso:country":"CN",
    "name:und_x_variant":[
        "A\u2019leike Aiqike",
        "\u963f\u52d2\u514b\u827e\u5176\u514b"
    ],
    "wof:name":"A'leike Aiqike",
    "wof:placetype":"locality"
},
  "geometry": {"coordinates":[76.27594000000001,38.49775],"type":"Point"}
}