{
  "type": "Feature",
  "properties": {
    "gn:admin1_code":"30.0",
    "gn:asciiname":"Fubiao",
    "gn:country_code":"CN",
    "gn:dem":197,
    "gn:feature_class":"P",
    "gn:feature_code":"PPL",
    "gn:name":"Fubiao",
    "gn:population":0,
    "gn:timezone":"Asia/Shanghai",
    "iso:country":"CN",
    "name:zho_x_preferred":[
        "\u798f\u6753"
    ],
    "wof:name":"Fubiao",
    "wof:placetype":"locality"
},
  "geometry": {"coordinates":[114.39239000000001,23.69445],"type":"Point"}
}