{
  "type": "Feature",
  "properties": {
    "gn:admin1_code":"26.0",
    "gn:asciiname":"Tongjiaba",
    "gn:country_code":"CN",
    "gn:dem":597,
    "gn:feature_class":"P",
    "gn:feature_code":"PPL",
    "gn:name":"Tongjiaba",
    "gn:population":0,
    "gn:timezone":"Asia/Shanghai",
    "iso:country":"CN",
    "name:und_x_variant":[
        "\u6850\u5bb6\u575d"
    ],
    "wof:name":"Tongjiaba",
    "wof:placetype":"locality"
},
  "geometry": {"coordinates":[107.22225,32.94422],"type":"Point"}
}