{
  "type": "Feature",
  "properties": {
    "gn:admin1_code":"1.0",
    "gn:asciiname":"Xujincun",
    "gn:country_code":"CN",
    "gn:dem":40,
    "gn:feature_class":"P",
    "gn:feature_code":"PPL",
    "gn:name":"Xujincun",
    "gn:population":0,
    "gn:timezone":"Asia/Shanghai",
    "iso:country":"CN",
    "name:zho_x_preferred":[
        "\u5f90\u91d1\u6751"
    ],
    "wof:name":"Xujincun",
    "wof:placetype":"locality"
},
  "geometry": {"coordinates":[115.33216000000002,32.83145],"type":"Point"}
}