{
  "type": "Feature",
  "properties": {
    "gn:admin1_code":"18.0",
    "gn:asciiname":"Hongyan",
    "gn:country_code":"CN",
    "gn:dem":1204,
    "gn:feature_class":"P",
    "gn:feature_code":"PPL",
    "gn:name":"Hongyan",
    "gn:population":0,
    "gn:timezone":"Asia/Shanghai",
    "iso:country":"CN",
    "name:ceb_x_preferred":[
        "Hongyan"
    ],
    "name:deu_x_preferred":[
        "Hongyan"
    ],
    "name:ita_x_preferred":[
        "Hongyan"
    ],
    "name:swe_x_preferred":[
        "Hongyan"
    ],
    "wof:name":"Hongyan",
    "wof:placetype":"locality"
},
  "geometry": {"coordinates":[107.21222,28.65139000000001],"type":"Point"}
}