{
  "type": "Feature",
  "properties": {
    "gn:admin1_code":"25",
    "gn:asciiname":"Houhesi",
    "gn:country_code":"CN",
    "gn:dem":22,
    "gn:feature_class":"P",
    "gn:feature_code":"PPL",
    "gn:name":"Houhesi",
    "gn:population":0,
    "gn:timezone":"Asia/Shanghai",
    "iso:country":"CN",
    "name:zho_x_preferred":[
        "\u540e\u4f55\u5bfa"
    ],
    "wof:name":"Houhesi",
    "wof:placetype":"locality"
},
  "geometry": {"coordinates":[116.592,37.1774],"type":"Point"}
}