{
  "type": "Feature",
  "properties": {
    "gn:admin1_code":"11.0",
    "gn:asciiname":"Tianxing'an",
    "gn:country_code":"CN",
    "gn:dem":52,
    "gn:feature_class":"P",
    "gn:feature_code":"PPL",
    "gn:name":"Tianxing\u2019an",
    "gn:population":0,
    "gn:timezone":"Asia/Shanghai",
    "iso:country":"CN",
    "name:und_x_variant":[
        "Tianxing\u2019an"
    ],
    "name:zho_x_preferred":[
        "\u5929\u661f\u5eb5"
    ],
    "wof:name":"Tianxing'an",
    "wof:placetype":"locality"
},
  "geometry": {"coordinates":[111.94898000000001,28.78457],"type":"Point"}
}