{
  "type": "Feature",
  "properties": {
    "gn:admin1_code":"2.0",
    "gn:asciiname":"Wu'ao",
    "gn:country_code":"CN",
    "gn:dem":65,
    "gn:feature_class":"P",
    "gn:feature_code":"PPL",
    "gn:name":"Wu\u2019ao",
    "gn:population":0,
    "gn:timezone":"Asia/Shanghai",
    "iso:country":"CN",
    "name:zho_x_preferred":[
        "\u5434\u5c99"
    ],
    "name:zho_x_variant":[
        "Wu\u2019ao"
    ],
    "wof:name":"Wu'ao",
    "wof:placetype":"locality"
},
  "geometry": {"coordinates":[121.23347,29.05102],"type":"Point"}
}