{
  "type": "Feature",
  "properties": {
    "gn:admin1_code":"32.0",
    "gn:asciiname":"Aozipo",
    "gn:country_code":"CN",
    "gn:dem":1132,
    "gn:feature_class":"P",
    "gn:feature_code":"PPL",
    "gn:name":"Aozipo",
    "gn:population":0,
    "gn:timezone":"Asia/Shanghai",
    "iso:country":"CN",
    "name:zho_x_preferred":[
        "\u51f9\u5b50\u5761"
    ],
    "wof:name":"Aozipo",
    "wof:placetype":"locality"
},
  "geometry": {"coordinates":[101.758,26.4632],"type":"Point"}
}