{
  "type": "Feature",
  "properties": {
    "gn:admin1_code":"24.0",
    "gn:asciiname":"Podi",
    "gn:country_code":"CN",
    "gn:dem":596,
    "gn:feature_class":"P",
    "gn:feature_code":"PPL",
    "gn:name":"Podi",
    "gn:population":0,
    "gn:timezone":"Asia/Shanghai",
    "iso:country":"CN",
    "name:und_x_variant":[
        "\u5761\u5e95"
    ],
    "wof:name":"Podi",
    "wof:placetype":"locality"
},
  "geometry": {"coordinates":[111.13330000000001,35.39458],"type":"Point"}
}