{
  "type": "Feature",
  "properties": {
    "gn:admin1_code":"19.0",
    "gn:asciiname":"Tubuzicun",
    "gn:country_code":"CN",
    "gn:dem":24,
    "gn:feature_class":"P",
    "gn:feature_code":"PPL",
    "gn:name":"Tubuzicun",
    "gn:population":0,
    "gn:timezone":"Asia/Shanghai",
    "iso:country":"CN",
    "name:zho_x_preferred":[
        "\u571f\u5821\u5b50\u6751"
    ],
    "wof:name":"Tubuzicun",
    "wof:placetype":"locality"
},
  "geometry": {"coordinates":[122.99894,41.63495],"type":"Point"}
}