{
  "type": "Feature",
  "properties": {
    "gn:admin1_code":"15.0",
    "gn:asciiname":"Wangjia Luanzhuangzi",
    "gn:country_code":"CN",
    "gn:dem":1423,
    "gn:feature_class":"P",
    "gn:feature_code":"PPL",
    "gn:name":"Wangjia Luanzhuangzi",
    "gn:population":0,
    "gn:timezone":"Asia/Shanghai",
    "iso:country":"CN",
    "name:zho_x_preferred":[
        "\u738b\u5bb6\u4e71\u5e84\u5b50"
    ],
    "wof:name":"Wangjia Luanzhuangzi",
    "wof:placetype":"locality"
},
  "geometry": {"coordinates":[98.7022,39.6747],"type":"Point"}
}