{
  "type": "Feature",
  "properties": {
    "gn:admin1_code":"32",
    "gn:asciiname":"Luojiang",
    "gn:country_code":"CN",
    "gn:dem":289,
    "gn:feature_class":"P",
    "gn:feature_code":"PPL",
    "gn:name":"Luojiang",
    "gn:population":0,
    "gn:timezone":"Asia/Shanghai",
    "iso:country":"CN",
    "name:ceb_x_preferred":[
        "Luojiang"
    ],
    "name:deu_x_preferred":[
        "Luojiang"
    ],
    "name:fra_x_preferred":[
        "Luojiang"
    ],
    "name:nor_x_preferred":[
        "Luojiang"
    ],
    "name:swe_x_preferred":[
        "Luojiang"
    ],
    "name:und_x_variant":[
        "Lotszyankou",
        "Lo-chiang-k\u2019ou",
        "Luojiangkou"
    ],
    "name:zho_x_preferred":[
        "\u7f57\u6c5f"
    ],
    "wof:name":"Luojiang",
    "wof:placetype":"locality"
},
  "geometry": {"coordinates":[107.53388,31.30673],"type":"Point"}
}