{
  "type": "Feature",
  "properties": {
    "gn:admin1_code":"3.0",
    "gn:asciiname":"Tuhuangcun",
    "gn:country_code":"CN",
    "gn:dem":14,
    "gn:feature_class":"P",
    "gn:feature_code":"PPL",
    "gn:name":"Tuhuangcun",
    "gn:population":0,
    "gn:timezone":"Asia/Shanghai",
    "iso:country":"CN",
    "name:und_x_variant":[
        "\u6d82\u9ec4\u6751"
    ],
    "wof:name":"Tuhuangcun",
    "wof:placetype":"locality"
},
  "geometry": {"coordinates":[116.15208,28.78822000000001],"type":"Point"}
}