{
  "type": "Feature",
  "properties": {
    "gn:admin1_code":"26.0",
    "gn:asciiname":"Qingrencun",
    "gn:country_code":"CN",
    "gn:dem":636,
    "gn:feature_class":"P",
    "gn:feature_code":"PPL",
    "gn:name":"Qingrencun",
    "gn:population":0,
    "gn:timezone":"Asia/Shanghai",
    "iso:country":"CN",
    "name:und_x_variant":[
        "Daqingrencun",
        "Daqingren"
    ],
    "name:zho_x_preferred":[
        "\u9752\u4ec1\u6751"
    ],
    "name:zho_x_variant":[
        "\u5927\u9752\u4ec1"
    ],
    "wof:name":"Qingrencun",
    "wof:placetype":"locality"
},
  "geometry": {"coordinates":[108.25743,34.53457],"type":"Point"}
}