{
  "type": "Feature",
  "properties": {
    "gn:admin1_code":"9.0",
    "gn:asciiname":"Xiezhuang",
    "gn:cc2":"CN",
    "gn:country_code":"CN",
    "gn:dem":119,
    "gn:feature_class":"P",
    "gn:feature_code":"PPL",
    "gn:name":"Xiezhuang",
    "gn:population":0,
    "gn:timezone":"Asia/Shanghai",
    "iso:country":"CN",
    "name:und_x_variant":[
        "Hsieh-chuang",
        "Hsieh-chuang-chi",
        "Xiezhuang"
    ],
    "wof:name":"Xiezhuang",
    "wof:placetype":"locality"
},
  "geometry": {"coordinates":[113.80722,34.63083],"type":"Point"}
}