{
  "type": "Feature",
  "properties": {
    "gn:admin1_code":"14.0",
    "gn:asciiname":"Langmo Cuoruowa",
    "gn:country_code":"CN",
    "gn:dem":4594,
    "gn:feature_class":"P",
    "gn:feature_code":"PPL",
    "gn:name":"Langmo Cuoruowa",
    "gn:population":0,
    "gn:timezone":"Asia/Urumqi",
    "iso:country":"CN",
    "name:zho_x_preferred":[
        "\u6717\u6a21\u9519\u82e5\u5a03"
    ],
    "wof:name":"Langmo Cuoruowa",
    "wof:placetype":"locality"
},
  "geometry": {"coordinates":[90.30686,30.03407],"type":"Point"}
}