{
  "type": "Feature",
  "properties": {
    "gn:admin1_code":"11.0",
    "gn:asciiname":"Longhuang",
    "gn:country_code":"CN",
    "gn:dem":484,
    "gn:feature_class":"P",
    "gn:feature_code":"PPL",
    "gn:name":"Longhuang",
    "gn:population":0,
    "gn:timezone":"Asia/Shanghai",
    "iso:country":"CN",
    "name:zho_x_preferred":[
        "\u9f99\u9ec4"
    ],
    "wof:name":"Longhuang",
    "wof:placetype":"locality"
},
  "geometry": {"coordinates":[113.90895999999999,28.99276],"type":"Point"}
}