{
  "type": "Feature",
  "properties": {
    "gn:admin1_code":"1.0",
    "gn:asciiname":"Zhudaloucun",
    "gn:country_code":"CN",
    "gn:dem":40,
    "gn:feature_class":"P",
    "gn:feature_code":"PPL",
    "gn:name":"Zhudaloucun",
    "gn:population":0,
    "gn:timezone":"Asia/Shanghai",
    "iso:country":"CN",
    "name:zho_x_preferred":[
        "\u6731\u5927\u697c\u6751"
    ],
    "wof:name":"Zhudaloucun",
    "wof:placetype":"locality"
},
  "geometry": {"coordinates":[116.56653,34.08991],"type":"Point"}
}