{
  "type": "Feature",
  "properties": {
    "gn:admin1_code":"6.0",
    "gn:asciiname":"Xiureqieba",
    "gn:country_code":"CN",
    "gn:dem":2887,
    "gn:feature_class":"P",
    "gn:feature_code":"PPL",
    "gn:name":"Xiureqieba",
    "gn:population":0,
    "gn:timezone":"Asia/Shanghai",
    "iso:country":"CN",
    "name:und_x_variant":[
        "\u79c0\u70ed\u5207\u575d"
    ],
    "wof:name":"Xiureqieba",
    "wof:placetype":"locality"
},
  "geometry": {"coordinates":[102.1953,35.81333],"type":"Point"}
}