{
  "type": "Feature",
  "properties": {
    "gn:admin1_code":"30",
    "gn:asciiname":"Dayangcun",
    "gn:country_code":"CN",
    "gn:dem":4,
    "gn:feature_class":"P",
    "gn:feature_code":"PPL",
    "gn:name":"Dayangcun",
    "gn:population":0,
    "gn:timezone":"Asia/Shanghai",
    "iso:country":"CN",
    "name:und_x_variant":[
        "\u5927\u6d0b\u6751",
        "Dayangcun"
    ],
    "wof:name":"Dayangcun",
    "wof:placetype":"locality"
},
  "geometry": {"coordinates":[111.85008999999999,21.65357],"type":"Point"}
}