{
  "type": "Feature",
  "properties": {
    "gn:admin1_code":"29.0",
    "gn:asciiname":"Maoshajing",
    "gn:country_code":"CN",
    "gn:dem":2326,
    "gn:feature_class":"P",
    "gn:feature_code":"PPL",
    "gn:name":"Maoshajing",
    "gn:population":0,
    "gn:timezone":"Asia/Shanghai",
    "iso:country":"CN",
    "name:und_x_variant":[
        "\u5192\u6c99\u4e95"
    ],
    "wof:name":"Maoshajing",
    "wof:placetype":"locality"
},
  "geometry": {"coordinates":[103.628,26.7695],"type":"Point"}
}