{
  "type": "Feature",
  "properties": {
    "gn:admin1_code":"14.0",
    "gn:asciiname":"Yangdacun",
    "gn:country_code":"CN",
    "gn:dem":4439,
    "gn:feature_class":"P",
    "gn:feature_code":"PPL",
    "gn:name":"Yangdacun",
    "gn:population":0,
    "gn:timezone":"Asia/Urumqi",
    "iso:country":"CN",
    "name:zho_x_preferred":[
        "\u7f8a\u8fbe\u6751"
    ],
    "wof:name":"Yangdacun",
    "wof:placetype":"locality"
},
  "geometry": {"coordinates":[97.03269,30.69943],"type":"Point"}
}