{
  "type": "Feature",
  "properties": {
    "gn:admin1_code":"1.0",
    "gn:asciiname":"Jiaowancun",
    "gn:country_code":"CN",
    "gn:dem":11,
    "gn:feature_class":"P",
    "gn:feature_code":"PPL",
    "gn:name":"Jiaowancun",
    "gn:population":0,
    "gn:timezone":"Asia/Shanghai",
    "iso:country":"CN",
    "name:zho_x_preferred":[
        "\u7126\u6e7e\u6751"
    ],
    "wof:name":"Jiaowancun",
    "wof:placetype":"locality"
},
  "geometry": {"coordinates":[118.16370000000001,31.22491],"type":"Point"}
}