{
  "type": "Feature",
  "properties": {
    "gn:admin1_code":"15.0",
    "gn:asciiname":"Sanjiaoxiang",
    "gn:country_code":"CN",
    "gn:dem":2216,
    "gn:feature_class":"P",
    "gn:feature_code":"PPL",
    "gn:name":"Sanjiaoxiang",
    "gn:population":0,
    "gn:timezone":"Asia/Shanghai",
    "iso:country":"CN",
    "name:zho_x_preferred":[
        "\u4e09\u89d2\u4e61"
    ],
    "wof:name":"Sanjiaoxiang",
    "wof:placetype":"locality"
},
  "geometry": {"coordinates":[103.14,35.6384],"type":"Point"}
}