{
  "type": "Feature",
  "properties": {
    "gn:admin1_code":"16.0",
    "gn:asciiname":"Liuxie",
    "gn:country_code":"CN",
    "gn:dem":224,
    "gn:feature_class":"P",
    "gn:feature_code":"PPL",
    "gn:name":"Liuxie",
    "gn:population":0,
    "gn:timezone":"Asia/Shanghai",
    "iso:country":"CN",
    "name:zho_x_preferred":[
        "\u516d\u8c22"
    ],
    "wof:name":"Liuxie",
    "wof:placetype":"locality"
},
  "geometry": {"coordinates":[109.32599999999999,23.0763],"type":"Point"}
}