{
  "type": "Feature",
  "properties": {
    "gn:admin1_code":"11.0",
    "gn:asciiname":"Huanggangqiao",
    "gn:country_code":"CN",
    "gn:dem":102,
    "gn:feature_class":"P",
    "gn:feature_code":"PPL",
    "gn:name":"Huanggangqiao",
    "gn:population":0,
    "gn:timezone":"Asia/Shanghai",
    "iso:country":"CN",
    "name:zho_x_preferred":[
        "\u9ec4\u5c97\u6865"
    ],
    "wof:name":"Huanggangqiao",
    "wof:placetype":"locality"
},
  "geometry": {"coordinates":[113.80117,28.32099],"type":"Point"}
}