{
  "type": "Feature",
  "properties": {
    "gn:admin1_code":"08",
    "gn:asciiname":"Jiaxin",
    "gn:country_code":"CN",
    "gn:dem":129,
    "gn:feature_class":"P",
    "gn:feature_code":"PPLA4",
    "gn:name":"Jiaxin",
    "gn:population":0,
    "gn:timezone":"Asia/Shanghai",
    "iso:country":"CN",
    "name:und_x_variant":[
        "Chia-hsin-tzu",
        "Jiaxinzi",
        "Jiaxin",
        "Jiaxin Zhen"
    ],
    "name:zho_x_preferred":[
        "\u52a0\u4fe1"
    ],
    "name:zho_x_variant":[
        "\u52a0\u4fe1\u9547"
    ],
    "wof:name":"Jiaxin",
    "wof:placetype":"locality"
},
  "geometry": {"coordinates":[128.71016,45.66726],"type":"Point"}
}