{
  "type": "Feature",
  "properties": {
    "gn:admin1_code":"11.0",
    "gn:asciiname":"Huxi",
    "gn:country_code":"CN",
    "gn:dem":315,
    "gn:feature_class":"P",
    "gn:feature_code":"PPL",
    "gn:name":"Huxi",
    "gn:population":0,
    "gn:timezone":"Asia/Shanghai",
    "iso:country":"CN",
    "name:ceb_x_preferred":[
        "Huxi"
    ],
    "name:swe_x_preferred":[
        "Huxi"
    ],
    "name:zho_x_preferred":[
        "\u6d52\u6eaa"
    ],
    "wof:name":"Huxi",
    "wof:placetype":"locality"
},
  "geometry": {"coordinates":[111.16489,27.41411],"type":"Point"}
}