{
  "type": "Feature",
  "properties": {
    "gn:admin1_code":"24",
    "gn:asciiname":"Qidun",
    "gn:country_code":"CN",
    "gn:dem":1620,
    "gn:feature_class":"P",
    "gn:feature_code":"PPL",
    "gn:name":"Qidun",
    "gn:population":0,
    "gn:timezone":"Asia/Shanghai",
    "iso:country":"CN",
    "name:und_x_variant":[
        "Ch\u2019i-tun-chen",
        "Ch\u2019i-tun",
        "Qidun",
        "\u4e03\u58a9"
    ],
    "wof:name":"Qidun",
    "wof:placetype":"locality"
},
  "geometry": {"coordinates":[112.09466,39.95913],"type":"Point"}
}