{
  "type": "Feature",
  "properties": {
    "gn:admin1_code":"11.0",
    "gn:asciiname":"Douling",
    "gn:country_code":"CN",
    "gn:dem":184,
    "gn:feature_class":"P",
    "gn:feature_code":"PPL",
    "gn:name":"Douling",
    "gn:population":0,
    "gn:timezone":"Asia/Shanghai",
    "iso:country":"CN",
    "name:zho_x_preferred":[
        "\u9661\u5cad"
    ],
    "wof:name":"Douling",
    "wof:placetype":"locality"
},
  "geometry": {"coordinates":[113.63536999999999,29.47598],"type":"Point"}
}