{
  "type": "Feature",
  "properties": {
    "gn:admin1_code":"3.0",
    "gn:asciiname":"Yukeng",
    "gn:country_code":"CN",
    "gn:dem":158,
    "gn:feature_class":"P",
    "gn:feature_code":"PPL",
    "gn:name":"Yukeng",
    "gn:population":0,
    "gn:timezone":"Asia/Shanghai",
    "iso:country":"CN",
    "name:und_x_variant":[
        "\u828b\u5751"
    ],
    "wof:name":"Yukeng",
    "wof:placetype":"locality"
},
  "geometry": {"coordinates":[116.32105,26.74385],"type":"Point"}
}