{
  "type": "Feature",
  "properties": {
    "gn:admin1_code":"3.0",
    "gn:asciiname":"Qiaokeng",
    "gn:country_code":"CN",
    "gn:dem":126,
    "gn:feature_class":"P",
    "gn:feature_code":"PPL",
    "gn:name":"Qiaokeng",
    "gn:population":0,
    "gn:timezone":"Asia/Shanghai",
    "iso:country":"CN",
    "name:und_x_variant":[
        "\u6865\u5751"
    ],
    "wof:name":"Qiaokeng",
    "wof:placetype":"locality"
},
  "geometry": {"coordinates":[115.50046,27.21136],"type":"Point"}
}