{
  "type": "Feature",
  "properties": {
    "gn:admin1_code":"30",
    "gn:asciiname":"Yezhuwo",
    "gn:country_code":"CN",
    "gn:dem":340,
    "gn:feature_class":"P",
    "gn:feature_code":"PPL",
    "gn:name":"Yezhuwo",
    "gn:population":0,
    "gn:timezone":"Asia/Shanghai",
    "iso:country":"CN",
    "name:zho_x_preferred":[
        "\u91ce\u732a\u7a9d"
    ],
    "wof:name":"Yezhuwo",
    "wof:placetype":"locality"
},
  "geometry": {"coordinates":[116.10899999999999,24.79537],"type":"Point"}
}