{
  "type": "Feature",
  "properties": {
    "gn:admin1_code":"10.0",
    "gn:asciiname":"Wangyushi",
    "gn:country_code":"CN",
    "gn:dem":1,
    "gn:feature_class":"P",
    "gn:feature_code":"PPL",
    "gn:name":"Wangyushi",
    "gn:population":0,
    "gn:timezone":"Asia/Shanghai",
    "iso:country":"CN",
    "name:zho_x_preferred":[
        "\u738b\u7389\u77f3"
    ],
    "wof:name":"Wangyushi",
    "wof:placetype":"locality"
},
  "geometry": {"coordinates":[117.90767,39.52335],"type":"Point"}
}