{
  "type": "Feature",
  "properties": {
    "gn:admin1_code":"10",
    "gn:asciiname":"Anzijiang Beigou",
    "gn:country_code":"CN",
    "gn:dem":893,
    "gn:feature_class":"P",
    "gn:feature_code":"PPL",
    "gn:name":"Anzijiang Beigou",
    "gn:population":0,
    "gn:timezone":"Asia/Shanghai",
    "iso:country":"CN",
    "name:zho_x_preferred":[
        "\u978d\u5b50\u5320\u5317\u6c9f"
    ],
    "wof:name":"Anzijiang Beigou",
    "wof:placetype":"locality"
},
  "geometry": {"coordinates":[118.50586,41.11348],"type":"Point"}
}