{
  "type": "Feature",
  "properties": {
    "gn:admin1_code":"24",
    "gn:asciiname":"Mazishan",
    "gn:country_code":"CN",
    "gn:dem":1300,
    "gn:feature_class":"P",
    "gn:feature_code":"PPL",
    "gn:name":"Mazishan",
    "gn:population":0,
    "gn:timezone":"Asia/Shanghai",
    "iso:country":"CN",
    "name:und_x_variant":[
        "Ma-tzu-shan",
        "Mazishan",
        "\u9ebb\u5b50\u5c71"
    ],
    "wof:name":"Mazishan",
    "wof:placetype":"locality"
},
  "geometry": {"coordinates":[113.73215999999999,39.08934],"type":"Point"}
}