{
  "type": "Feature",
  "properties": {
    "gn:admin1_code":"16.0",
    "gn:asciiname":"Wangmianling",
    "gn:country_code":"CN",
    "gn:dem":107,
    "gn:feature_class":"P",
    "gn:feature_code":"PPL",
    "gn:name":"Wangmianling",
    "gn:population":0,
    "gn:timezone":"Asia/Shanghai",
    "iso:country":"CN",
    "name:zho_x_preferred":[
        "\u65fa\u9762\u5cad"
    ],
    "wof:name":"Wangmianling",
    "wof:placetype":"locality"
},
  "geometry": {"coordinates":[110.313,22.7267],"type":"Point"}
}