{
  "type": "Feature",
  "properties": {
    "gn:admin1_code":"18",
    "gn:asciiname":"Dongcao",
    "gn:country_code":"CN",
    "gn:dem":898,
    "gn:feature_class":"P",
    "gn:feature_code":"PPL",
    "gn:name":"Dongcao",
    "gn:population":0,
    "gn:timezone":"Asia/Shanghai",
    "iso:country":"CN",
    "name:zho_x_preferred":[
        "\u8463\u8349"
    ],
    "wof:name":"Dongcao",
    "wof:placetype":"locality"
},
  "geometry": {"coordinates":[107.67700000000001,27.7256],"type":"Point"}
}