{
  "type": "Feature",
  "properties": {
    "gn:admin1_code":"8.0",
    "gn:asciiname":"Baonan Nongchang",
    "gn:country_code":"CN",
    "gn:dem":84,
    "gn:feature_class":"P",
    "gn:feature_code":"PPLF",
    "gn:name":"Baonan Nongchang",
    "gn:population":0,
    "gn:timezone":"Asia/Shanghai",
    "iso:country":"CN",
    "name:zho_x_preferred":[
        "\u5b9d\u5357\u519c\u573a"
    ],
    "wof:name":"Baonan Nongchang",
    "wof:placetype":"locality"
},
  "geometry": {"coordinates":[130.48566,47.33958],"type":"Point"}
}