{
  "type": "Feature",
  "properties": {
    "gn:admin1_code":"16.0",
    "gn:asciiname":"Jiaxiang",
    "gn:country_code":"CN",
    "gn:dem":196,
    "gn:feature_class":"P",
    "gn:feature_code":"PPL",
    "gn:name":"Jiaxiang",
    "gn:population":0,
    "gn:timezone":"Asia/Shanghai",
    "iso:country":"CN",
    "name:hrv_x_preferred":[
        "Jiaxiang"
    ],
    "name:nor_x_preferred":[
        "Jiaxiang"
    ],
    "name:zho_x_preferred":[
        "\u52a0\u76f8"
    ],
    "wof:name":"Jiaxiang",
    "wof:placetype":"locality"
},
  "geometry": {"coordinates":[108.16800000000001,24.7046],"type":"Point"}
}