{
  "type": "Feature",
  "properties": {
    "gn:admin1_code":"4.0",
    "gn:asciiname":"Dongsunjiadai",
    "gn:country_code":"CN",
    "gn:dem":1,
    "gn:feature_class":"P",
    "gn:feature_code":"PPL",
    "gn:name":"Dongsunjiadai",
    "gn:population":0,
    "gn:timezone":"Asia/Shanghai",
    "iso:country":"CN",
    "name:zho_x_preferred":[
        "\u4e1c\u5b59\u5bb6\u5788"
    ],
    "wof:name":"Dongsunjiadai",
    "wof:placetype":"locality"
},
  "geometry": {"coordinates":[120.14284000000001,32.04948],"type":"Point"}
}