{
  "type": "Feature",
  "properties": {
    "gn:admin1_code":"16.0",
    "gn:asciiname":"Jiutuan'e",
    "gn:country_code":"CN",
    "gn:dem":265,
    "gn:feature_class":"P",
    "gn:feature_code":"PPL",
    "gn:name":"Jiutuan\u2019e",
    "gn:population":0,
    "gn:timezone":"Asia/Shanghai",
    "iso:country":"CN",
    "name:und_x_variant":[
        "Jiutuan\u2019e"
    ],
    "name:zho_x_preferred":[
        "\u65e7\u56e2\u989d"
    ],
    "wof:name":"Jiutuan'e",
    "wof:placetype":"locality"
},
  "geometry": {"coordinates":[108.16500000000001,24.9276],"type":"Point"}
}