{
  "type": "Feature",
  "properties": {
    "gn:admin1_code":"14.0",
    "gn:asciiname":"Biangaguo",
    "gn:country_code":"CN",
    "gn:dem":4598,
    "gn:feature_class":"P",
    "gn:feature_code":"PPL",
    "gn:name":"Biangaguo",
    "gn:population":0,
    "gn:timezone":"Asia/Urumqi",
    "iso:country":"CN",
    "name:zho_x_preferred":[
        "\u8fb9\u560e\u679c"
    ],
    "wof:name":"Biangaguo",
    "wof:placetype":"locality"
},
  "geometry": {"coordinates":[90.70232,30.21963],"type":"Point"}
}