{
  "type": "Feature",
  "properties": {
    "gn:admin1_code":"11.0",
    "gn:asciiname":"Dalaowu",
    "gn:country_code":"CN",
    "gn:dem":57,
    "gn:feature_class":"P",
    "gn:feature_code":"PPL",
    "gn:name":"Dalaowu",
    "gn:population":0,
    "gn:timezone":"Asia/Shanghai",
    "iso:country":"CN",
    "name:zho_x_preferred":[
        "\u5927\u8001\u5c4b"
    ],
    "wof:name":"Dalaowu",
    "wof:placetype":"locality"
},
  "geometry": {"coordinates":[112.91974,28.56679],"type":"Point"}
}