{
  "type": "Feature",
  "properties": {
    "gn:admin1_code":"29",
    "gn:asciiname":"Pingzhangzi",
    "gn:country_code":"CN",
    "gn:dem":1763,
    "gn:feature_class":"P",
    "gn:feature_code":"PPL",
    "gn:name":"Pingzhangzi",
    "gn:population":0,
    "gn:timezone":"Asia/Shanghai",
    "iso:country":"CN",
    "name:zho_x_preferred":[
        "\u5e73\u638c\u5b50"
    ],
    "wof:name":"Pingzhangzi",
    "wof:placetype":"locality"
},
  "geometry": {"coordinates":[101.488,24.759],"type":"Point"}
}