{
  "type": "Feature",
  "properties": {
    "gn:admin1_code":"15.0",
    "gn:asciiname":"Meidongtai",
    "gn:country_code":"CN",
    "gn:dem":2743,
    "gn:feature_class":"P",
    "gn:feature_code":"PPL",
    "gn:name":"Meidongtai",
    "gn:population":0,
    "gn:timezone":"Asia/Shanghai",
    "iso:country":"CN",
    "name:zho_x_preferred":[
        "\u7164\u6d1e\u53f0"
    ],
    "wof:name":"Meidongtai",
    "wof:placetype":"locality"
},
  "geometry": {"coordinates":[102.648,37.3578],"type":"Point"}
}