{
  "type": "Feature",
  "properties": {
    "gn:admin1_code":"2.0",
    "gn:asciiname":"Yangzhai",
    "gn:country_code":"CN",
    "gn:dem":129,
    "gn:feature_class":"P",
    "gn:feature_code":"PPL",
    "gn:name":"Yangzhai",
    "gn:population":0,
    "gn:timezone":"Asia/Shanghai",
    "iso:country":"CN",
    "name:zho_x_preferred":[
        "\u6768\u5b85"
    ],
    "wof:name":"Yangzhai",
    "wof:placetype":"locality"
},
  "geometry": {"coordinates":[120.37139999999999,29.54025],"type":"Point"}
}