{
  "type": "Feature",
  "properties": {
    "gn:admin1_code":"16.0",
    "gn:asciiname":"Liubang",
    "gn:country_code":"CN",
    "gn:dem":804,
    "gn:feature_class":"P",
    "gn:feature_code":"PPL",
    "gn:name":"Liubang",
    "gn:population":0,
    "gn:timezone":"Asia/Shanghai",
    "iso:country":"CN",
    "name:zho_x_preferred":[
        "\u516d\u5e2e"
    ],
    "wof:name":"Liubang",
    "wof:placetype":"locality"
},
  "geometry": {"coordinates":[105.86199999999999,24.0809],"type":"Point"}
}