{
  "type": "Feature",
  "properties": {
    "gn:admin1_code":"8.0",
    "gn:asciiname":"Keyinpu",
    "gn:country_code":"CN",
    "gn:dem":211,
    "gn:feature_class":"P",
    "gn:feature_code":"PPL",
    "gn:name":"Keyinpu",
    "gn:population":0,
    "gn:timezone":"Asia/Shanghai",
    "iso:country":"CN",
    "name:zho_x_preferred":[
        "\u67ef\u94f6\u94fa"
    ],
    "wof:name":"Keyinpu",
    "wof:placetype":"locality"
},
  "geometry": {"coordinates":[127.72183,46.87013],"type":"Point"}
}