{
  "type": "Feature",
  "properties": {
    "gn:admin1_code":"19.0",
    "gn:asciiname":"Zhaojia Wazi",
    "gn:country_code":"CN",
    "gn:dem":277,
    "gn:feature_class":"P",
    "gn:feature_code":"PPL",
    "gn:name":"Zhaojia Wazi",
    "gn:population":0,
    "gn:timezone":"Asia/Shanghai",
    "iso:country":"CN",
    "name:und_x_variant":[
        "\u8d75\u5bb6\u6d3c\u5b50"
    ],
    "wof:name":"Zhaojia Wazi",
    "wof:placetype":"locality"
},
  "geometry": {"coordinates":[124.43962000000001,41.25647],"type":"Point"}
}