{
  "type": "Feature",
  "properties": {
    "gn:admin1_code":"9.0",
    "gn:asciiname":"Daweizhuang",
    "gn:country_code":"CN",
    "gn:dem":86,
    "gn:feature_class":"P",
    "gn:feature_code":"PPL",
    "gn:name":"Daweizhuang",
    "gn:population":0,
    "gn:timezone":"Asia/Shanghai",
    "iso:country":"CN",
    "name:zho_x_preferred":[
        "\u5927\u9b4f\u5e84"
    ],
    "wof:name":"Daweizhuang",
    "wof:placetype":"locality"
},
  "geometry": {"coordinates":[113.69208999999999,33.91463],"type":"Point"}
}