{
  "type": "Feature",
  "properties": {
    "gn:admin1_code":"1.0",
    "gn:asciiname":"Huangshanlu",
    "gn:country_code":"CN",
    "gn:dem":48,
    "gn:feature_class":"P",
    "gn:feature_code":"PPL",
    "gn:name":"Huangshanlu",
    "gn:population":0,
    "gn:timezone":"Asia/Shanghai",
    "iso:country":"CN",
    "name:zho_x_preferred":[
        "\u9ec4\u5c71\u8def"
    ],
    "wof:name":"Huangshanlu",
    "wof:placetype":"locality"
},
  "geometry": {"coordinates":[117.20442,31.84201],"type":"Point"}
}