{
  "type": "Feature",
  "properties": {
    "gn:admin1_code":"01",
    "gn:asciiname":"Liutian",
    "gn:country_code":"CN",
    "gn:dem":97,
    "gn:feature_class":"P",
    "gn:feature_code":"PPL",
    "gn:name":"Liutian",
    "gn:population":0,
    "gn:timezone":"Asia/Shanghai",
    "iso:country":"CN",
    "name:und_x_variant":[
        "Shang-liu-t\u2019ien",
        "Liu-t\u2019ien",
        "Liutian"
    ],
    "name:zho_x_preferred":[
        "\u7559\u7530"
    ],
    "wof:name":"Liutian",
    "wof:placetype":"locality"
},
  "geometry": {"coordinates":[117.61377,30.33742],"type":"Point"}
}