{
  "type": "Feature",
  "properties": {
    "gn:admin1_code":"19.0",
    "gn:asciiname":"Sanhe",
    "gn:country_code":"CN",
    "gn:dem":43,
    "gn:feature_class":"P",
    "gn:feature_code":"PPL",
    "gn:name":"Sanhe",
    "gn:population":0,
    "gn:timezone":"Asia/Shanghai",
    "iso:country":"CN",
    "name:und_x_variant":[
        "\u4e09\u5408"
    ],
    "name:zho_x_preferred":[
        "\u4e09\u5408"
    ],
    "wof:name":"Sanhe",
    "wof:placetype":"locality"
},
  "geometry": {"coordinates":[122.72736,39.67788],"type":"Point"}
}