{
  "type": "Feature",
  "properties": {
    "gn:admin1_code":"20.0",
    "gn:asciiname":"Yebiqi Yidui",
    "gn:country_code":"CN",
    "gn:dem":262,
    "gn:feature_class":"P",
    "gn:feature_code":"PPLF",
    "gn:name":"Yebiqi Yidui",
    "gn:population":0,
    "gn:timezone":"Asia/Shanghai",
    "iso:country":"CN",
    "name:zho_x_preferred":[
        "\u4e5f\u5fc5\u5947\u4e00\u961f"
    ],
    "wof:name":"Yebiqi Yidui",
    "wof:placetype":"locality"
},
  "geometry": {"coordinates":[124.52545000000001,48.9082],"type":"Point"}
}