{
  "type": "Feature",
  "properties": {
    "gn:admin1_code":"29.0",
    "gn:asciiname":"Wanjia Pingzi",
    "gn:country_code":"CN",
    "gn:dem":2301,
    "gn:feature_class":"P",
    "gn:feature_code":"PPL",
    "gn:name":"Wanjia Pingzi",
    "gn:population":0,
    "gn:timezone":"Asia/Shanghai",
    "iso:country":"CN",
    "name:zho_x_preferred":[
        "\u4e07\u5bb6\u576a\u5b50"
    ],
    "wof:name":"Wanjia Pingzi",
    "wof:placetype":"locality"
},
  "geometry": {"coordinates":[101.184,26.2254],"type":"Point"}
}