{
  "type": "Feature",
  "properties": {
    "gn:admin1_code":"18.0",
    "gn:asciiname":"Dajie",
    "gn:country_code":"CN",
    "gn:dem":2476,
    "gn:feature_class":"P",
    "gn:feature_code":"PPL",
    "gn:name":"Dajie",
    "gn:population":0,
    "gn:timezone":"Asia/Shanghai",
    "iso:country":"CN",
    "name:ceb_x_preferred":[
        "Dajie"
    ],
    "name:deu_x_preferred":[
        "Dajie"
    ],
    "name:swe_x_preferred":[
        "Dajie"
    ],
    "name:zho_x_preferred":[
        "\u5927\u8857"
    ],
    "wof:name":"Dajie",
    "wof:placetype":"locality"
},
  "geometry": {"coordinates":[104.122,27.0836],"type":"Point"}
}