{
  "type": "Feature",
  "properties": {
    "gn:admin1_code":"8.0",
    "gn:asciiname":"Wanjiecun",
    "gn:country_code":"CN",
    "gn:dem":174,
    "gn:feature_class":"P",
    "gn:feature_code":"PPL",
    "gn:name":"Wanjiecun",
    "gn:population":0,
    "gn:timezone":"Asia/Shanghai",
    "iso:country":"CN",
    "name:zho_x_preferred":[
        "\u4e07\u7ed3\u6751"
    ],
    "wof:name":"Wanjiecun",
    "wof:placetype":"locality"
},
  "geometry": {"coordinates":[126.58529,45.37398],"type":"Point"}
}