{
  "type": "Feature",
  "properties": {
    "gn:admin1_code":"12.0",
    "gn:asciiname":"Mayangzhai",
    "gn:country_code":"CN",
    "gn:dem":776,
    "gn:feature_class":"P",
    "gn:feature_code":"PPL",
    "gn:name":"Mayangzhai",
    "gn:population":0,
    "gn:timezone":"Asia/Shanghai",
    "iso:country":"CN",
    "name:zho_x_preferred":[
        "Mayangzhai"
    ],
    "name:zho_x_variant":[
        "\u9ebb\u9633\u5be8"
    ],
    "wof:name":"Mayangzhai",
    "wof:placetype":"locality"
},
  "geometry": {"coordinates":[109.44444,29.72541],"type":"Point"}
}