{
  "type": "Feature",
  "properties": {
    "gn:admin1_code":"30",
    "gn:asciiname":"Landicun",
    "gn:country_code":"CN",
    "gn:dem":17,
    "gn:feature_class":"P",
    "gn:feature_code":"PPL",
    "gn:name":"Landicun",
    "gn:population":0,
    "gn:timezone":"Asia/Shanghai",
    "iso:country":"CN",
    "name:zho_x_preferred":[
        "\u5170\u5730\u6751"
    ],
    "wof:name":"Landicun",
    "wof:placetype":"locality"
},
  "geometry": {"coordinates":[111.60881999999999,21.64383],"type":"Point"}
}