{
  "type": "Feature",
  "properties": {
    "gn:admin1_code":"26.0",
    "gn:asciiname":"Hujiaozeyancun",
    "gn:country_code":"CN",
    "gn:dem":1083,
    "gn:feature_class":"P",
    "gn:feature_code":"PPL",
    "gn:name":"Hujiaozeyancun",
    "gn:population":0,
    "gn:timezone":"Asia/Shanghai",
    "iso:country":"CN",
    "name:zho_x_preferred":[
        "\u80e1\u7a96\u5219\u5895\u6751"
    ],
    "wof:name":"Hujiaozeyancun",
    "wof:placetype":"locality"
},
  "geometry": {"coordinates":[110.58771000000002,38.60955],"type":"Point"}
}