{
  "type": "Feature",
  "properties": {
    "gn:admin1_code":"24",
    "gn:asciiname":"Guyang",
    "gn:cc2":"CN",
    "gn:country_code":"CN",
    "gn:dem":948,
    "gn:feature_class":"P",
    "gn:feature_code":"PPL",
    "gn:name":"Guyang",
    "gn:population":0,
    "gn:timezone":"Asia/Shanghai",
    "iso:country":"CN",
    "name:und_x_variant":[
        "Ku-yang",
        "Ku-yang-ts\u2019un",
        "Guyang"
    ],
    "wof:name":"Guyang",
    "wof:placetype":"locality"
},
  "geometry": {"coordinates":[112.01667,36.41667],"type":"Point"}
}