{
  "type": "Feature",
  "properties": {
    "gn:admin1_code":"32.0",
    "gn:asciiname":"Shanziwan",
    "gn:country_code":"CN",
    "gn:dem":326,
    "gn:feature_class":"P",
    "gn:feature_code":"PPL",
    "gn:name":"Shanziwan",
    "gn:population":0,
    "gn:timezone":"Asia/Shanghai",
    "iso:country":"CN",
    "name:zho_x_preferred":[
        "\u6247\u5b50\u6e7e"
    ],
    "wof:name":"Shanziwan",
    "wof:placetype":"locality"
},
  "geometry": {"coordinates":[104.98099999999999,29.5715],"type":"Point"}
}