{
  "type": "Feature",
  "properties": {
    "gn:admin1_code":"20.0",
    "gn:asciiname":"Xiyi Biqi",
    "gn:country_code":"CN",
    "gn:dem":249,
    "gn:feature_class":"P",
    "gn:feature_code":"PPL",
    "gn:name":"Xiyi Biqi",
    "gn:population":0,
    "gn:timezone":"Asia/Shanghai",
    "iso:country":"CN",
    "name:zho_x_preferred":[
        "\u897f\u4f0a\u5fc5\u5947"
    ],
    "wof:name":"Xiyi Biqi",
    "wof:placetype":"locality"
},
  "geometry": {"coordinates":[124.39604,48.94177],"type":"Point"}
}