{
  "type": "Feature",
  "properties": {
    "gn:admin1_code":"30.0",
    "gn:asciiname":"Gaojian",
    "gn:country_code":"CN",
    "gn:dem":52,
    "gn:feature_class":"P",
    "gn:feature_code":"PPL",
    "gn:name":"Gaojian",
    "gn:population":0,
    "gn:timezone":"Asia/Shanghai",
    "iso:country":"CN",
    "name:und_x_variant":[
        "\u9ad8\u7b80"
    ],
    "name:zho_x_preferred":[
        "\u9ad8\u7b80"
    ],
    "wof:name":"Gaojian",
    "wof:placetype":"locality"
},
  "geometry": {"coordinates":[114.90119,23.86547],"type":"Point"}
}