{
  "type": "Feature",
  "properties": {
    "gn:admin1_code":"26",
    "gn:asciiname":"Nanshe",
    "gn:country_code":"CN",
    "gn:dem":704,
    "gn:feature_class":"P",
    "gn:feature_code":"PPL",
    "gn:name":"Nanshe",
    "gn:population":0,
    "gn:timezone":"Asia/Shanghai",
    "iso:country":"CN",
    "name:und_x_variant":[
        "\u5357\u793e"
    ],
    "name:zho_x_preferred":[
        "\u5357\u793e"
    ],
    "wof:name":"Nanshe",
    "wof:placetype":"locality"
},
  "geometry": {"coordinates":[108.86888999999999,34.78556],"type":"Point"}
}