{
  "type": "Feature",
  "properties": {
    "gn:admin1_code":"8.0",
    "gn:asciiname":"Nanguanzuizi",
    "gn:country_code":"CN",
    "gn:dem":232,
    "gn:feature_class":"P",
    "gn:feature_code":"PPL",
    "gn:name":"Nanguanzuizi",
    "gn:population":0,
    "gn:timezone":"Asia/Shanghai",
    "iso:country":"CN",
    "name:zho_x_preferred":[
        "\u5357\u5173\u5480\u5b50"
    ],
    "wof:name":"Nanguanzuizi",
    "wof:placetype":"locality"
},
  "geometry": {"coordinates":[128.1619,46.86639],"type":"Point"}
}