{
  "type": "Feature",
  "properties": {
    "gn:admin1_code":"30",
    "gn:asciiname":"Xiacangzi",
    "gn:country_code":"CN",
    "gn:dem":473,
    "gn:feature_class":"P",
    "gn:feature_code":"PPL",
    "gn:name":"Xiacangzi",
    "gn:population":0,
    "gn:timezone":"Asia/Shanghai",
    "iso:country":"CN",
    "name:zho_x_preferred":[
        "\u4e0b\u4ed3\u5b50"
    ],
    "wof:name":"Xiacangzi",
    "wof:placetype":"locality"
},
  "geometry": {"coordinates":[115.94907000000001,24.7932],"type":"Point"}
}