{
  "type": "Feature",
  "properties": {
    "gn:admin1_code":"26.0",
    "gn:asciiname":"Jingkouxiang Linchang",
    "gn:country_code":"CN",
    "gn:dem":1748,
    "gn:feature_class":"P",
    "gn:feature_code":"PPLF",
    "gn:name":"Jingkouxiang Linchang",
    "gn:population":0,
    "gn:timezone":"Asia/Shanghai",
    "iso:country":"CN",
    "name:und_x_variant":[
        "\u9756\u53e3\u4e61\u6797\u573a"
    ],
    "wof:name":"Jingkouxiang Linchang",
    "wof:placetype":"locality"
},
  "geometry": {"coordinates":[107.17632999999999,34.12146],"type":"Point"}
}