{
  "type": "Feature",
  "properties": {
    "gn:admin1_code":"14.0",
    "gn:asciiname":"Ri'aqin",
    "gn:country_code":"CN",
    "gn:dem":4843,
    "gn:feature_class":"P",
    "gn:feature_code":"PPL",
    "gn:name":"Ri\u2019aqin",
    "gn:population":0,
    "gn:timezone":"Asia/Urumqi",
    "iso:country":"CN",
    "name:und_x_variant":[
        "Ri\u2019aqin"
    ],
    "name:zho_x_preferred":[
        "\u65e5\u963f\u4eb2"
    ],
    "wof:name":"Ri'aqin",
    "wof:placetype":"locality"
},
  "geometry": {"coordinates":[94.21168,31.06314],"type":"Point"}
}