{
  "type": "Feature",
  "properties": {
    "gn:admin1_code":"20.0",
    "gn:asciiname":"Shao'er Baoge",
    "gn:country_code":"CN",
    "gn:dem":545,
    "gn:feature_class":"P",
    "gn:feature_code":"PPL",
    "gn:name":"Shao\u2019er Baoge",
    "gn:population":0,
    "gn:timezone":"Asia/Shanghai",
    "iso:country":"CN",
    "name:und_x_variant":[
        "Shao\u2019er Baoge"
    ],
    "name:zho_x_preferred":[
        "\u7ecd\u5c14\u5305\u683c"
    ],
    "wof:name":"Shao'er Baoge",
    "wof:placetype":"locality"
},
  "geometry": {"coordinates":[118.06453,48.90542],"type":"Point"}
}