{
  "type": "Feature",
  "properties": {
    "gn:admin1_code":"24.0",
    "gn:asciiname":"Dongtang",
    "gn:country_code":"CN",
    "gn:dem":902,
    "gn:feature_class":"P",
    "gn:feature_code":"PPL",
    "gn:name":"Dongtang",
    "gn:population":0,
    "gn:timezone":"Asia/Shanghai",
    "iso:country":"CN",
    "name:zho_x_preferred":[
        "\u4e1c\u5510"
    ],
    "wof:name":"Dongtang",
    "wof:placetype":"locality"
},
  "geometry": {"coordinates":[112.36466,36.03458],"type":"Point"}
}