{
  "type": "Feature",
  "properties": {
    "gn:admin1_code":"12.0",
    "gn:asciiname":"Shibanhe",
    "gn:country_code":"CN",
    "gn:dem":519,
    "gn:feature_class":"P",
    "gn:feature_code":"PPL",
    "gn:name":"Shibanhe",
    "gn:population":0,
    "gn:timezone":"Asia/Shanghai",
    "iso:country":"CN",
    "name:zho_x_preferred":[
        "\u77f3\u677f\u6cb3"
    ],
    "wof:name":"Shibanhe",
    "wof:placetype":"locality"
},
  "geometry": {"coordinates":[111.20729,31.60891],"type":"Point"}
}