{
  "type": "Feature",
  "properties": {
    "gn:admin1_code":"32.0",
    "gn:asciiname":"Shihua",
    "gn:country_code":"CN",
    "gn:dem":525,
    "gn:feature_class":"P",
    "gn:feature_code":"PPL",
    "gn:name":"Shihua",
    "gn:population":0,
    "gn:timezone":"Asia/Shanghai",
    "iso:country":"CN",
    "name:zho_x_preferred":[
        "\u77f3\u82b1"
    ],
    "wof:name":"Shihua",
    "wof:placetype":"locality"
},
  "geometry": {"coordinates":[106.89400000000001,31.2881],"type":"Point"}
}