{
  "type": "Feature",
  "properties": {
    "gn:admin1_code":"7",
    "gn:asciiname":"Zhongkengyang",
    "gn:country_code":"CN",
    "gn:dem":180,
    "gn:feature_class":"P",
    "gn:feature_code":"PPL",
    "gn:name":"Zhongkengyang",
    "gn:population":0,
    "gn:timezone":"Asia/Shanghai",
    "iso:country":"CN",
    "name:und_x_variant":[
        "\u4f17\u5751\u6d0b"
    ],
    "wof:name":"Zhongkengyang",
    "wof:placetype":"locality"
},
  "geometry": {"coordinates":[119.65389,27.245],"type":"Point"}
}