{
  "type": "Feature",
  "properties": {
    "gn:admin1_code":"5.0",
    "gn:asciiname":"Hewanzi",
    "gn:country_code":"CN",
    "gn:dem":190,
    "gn:feature_class":"P",
    "gn:feature_code":"PPL",
    "gn:name":"Hewanzi",
    "gn:population":0,
    "gn:timezone":"Asia/Shanghai",
    "iso:country":"CN",
    "name:zho_x_preferred":[
        "\u6cb3\u6e7e\u5b50"
    ],
    "wof:name":"Hewanzi",
    "wof:placetype":"locality"
},
  "geometry": {"coordinates":[126.56894,44.04369000000001],"type":"Point"}
}