{
  "type": "Feature",
  "properties": {
    "gn:admin1_code":"3.0",
    "gn:asciiname":"Waihuang",
    "gn:country_code":"CN",
    "gn:dem":110,
    "gn:feature_class":"P",
    "gn:feature_code":"PPL",
    "gn:name":"Waihuang",
    "gn:population":0,
    "gn:timezone":"Asia/Shanghai",
    "iso:country":"CN",
    "name:und_x_variant":[
        "\u5916\u9ec4"
    ],
    "wof:name":"Waihuang",
    "wof:placetype":"locality"
},
  "geometry": {"coordinates":[117.61320000000001,29.26436],"type":"Point"}
}