{
  "type": "Feature",
  "properties": {
    "gn:admin1_code":"9.0",
    "gn:asciiname":"Yingheji",
    "gn:country_code":"CN",
    "gn:dem":46,
    "gn:feature_class":"P",
    "gn:feature_code":"PPL",
    "gn:name":"Yingheji",
    "gn:population":0,
    "gn:timezone":"Asia/Shanghai",
    "iso:country":"CN",
    "name:zho_x_preferred":[
        "\u8fce\u6cb3\u96c6"
    ],
    "wof:name":"Yingheji",
    "wof:placetype":"locality"
},
  "geometry": {"coordinates":[115.51161999999999,32.14567],"type":"Point"}
}