{
  "type": "Feature",
  "properties": {
    "gn:admin1_code":"7.0",
    "gn:asciiname":"Jiuwange",
    "gn:country_code":"CN",
    "gn:dem":413,
    "gn:feature_class":"P",
    "gn:feature_code":"PPL",
    "gn:name":"Jiuwange",
    "gn:population":0,
    "gn:timezone":"Asia/Shanghai",
    "iso:country":"CN",
    "name:zho_x_preferred":[
        "\u4e5d\u6e7e\u9694"
    ],
    "wof:name":"Jiuwange",
    "wof:placetype":"locality"
},
  "geometry": {"coordinates":[118.64377,26.10774],"type":"Point"}
}