{
  "type": "Feature",
  "properties": {
    "gn:admin1_code":"32.0",
    "gn:asciiname":"Miaoziling",
    "gn:country_code":"CN",
    "gn:dem":472,
    "gn:feature_class":"P",
    "gn:feature_code":"PPL",
    "gn:name":"Miaoziling",
    "gn:population":0,
    "gn:timezone":"Asia/Shanghai",
    "iso:country":"CN",
    "name:zho_x_preferred":[
        "\u5e99\u5b50\u5cad"
    ],
    "wof:name":"Miaoziling",
    "wof:placetype":"locality"
},
  "geometry": {"coordinates":[107.73399999999999,31.1323],"type":"Point"}
}