{
  "type": "Feature",
  "properties": {
    "gn:admin1_code":"12.0",
    "gn:asciiname":"Nibachong",
    "gn:country_code":"CN",
    "gn:dem":173,
    "gn:feature_class":"P",
    "gn:feature_code":"PPL",
    "gn:name":"Nibachong",
    "gn:population":0,
    "gn:timezone":"Asia/Shanghai",
    "iso:country":"CN",
    "name:zho_x_preferred":[
        "\u6ce5\u5df4\u51b2"
    ],
    "wof:name":"Nibachong",
    "wof:placetype":"locality"
},
  "geometry": {"coordinates":[113.2449,31.11559],"type":"Point"}
}