{
  "type": "Feature",
  "properties": {
    "gn:admin1_code":"26.0",
    "gn:asciiname":"Muwanghecun",
    "gn:country_code":"CN",
    "gn:dem":607,
    "gn:feature_class":"P",
    "gn:feature_code":"PPL",
    "gn:name":"Muwanghecun",
    "gn:population":0,
    "gn:timezone":"Asia/Shanghai",
    "iso:country":"CN",
    "name:zho_x_preferred":[
        "\u7766\u738b\u6cb3\u6751"
    ],
    "wof:name":"Muwanghecun",
    "wof:placetype":"locality"
},
  "geometry": {"coordinates":[109.68277,35.13705],"type":"Point"}
}