{
  "type": "Feature",
  "properties": {
    "gn:admin1_code":"4.0",
    "gn:asciiname":"Sanlipo",
    "gn:country_code":"CN",
    "gn:dem":4,
    "gn:feature_class":"P",
    "gn:feature_code":"PPL",
    "gn:name":"Sanlipo",
    "gn:population":0,
    "gn:timezone":"Asia/Shanghai",
    "iso:country":"CN",
    "name:zho_x_preferred":[
        "Sanlipo"
    ],
    "name:zho_x_variant":[
        "\u4e09\u91cc\u5761"
    ],
    "wof:name":"Sanlipo",
    "wof:placetype":"locality"
},
  "geometry": {"coordinates":[119.12275,34.67734],"type":"Point"}
}