{
  "type": "Feature",
  "properties": {
    "gn:admin1_code":"24.0",
    "gn:asciiname":"Tianjialingcun",
    "gn:country_code":"CN",
    "gn:dem":1099,
    "gn:feature_class":"P",
    "gn:feature_code":"PPL",
    "gn:name":"Tianjialingcun",
    "gn:population":0,
    "gn:timezone":"Asia/Shanghai",
    "iso:country":"CN",
    "name:zho_x_preferred":[
        "\u7530\u5bb6\u5cad\u6751"
    ],
    "wof:name":"Tianjialingcun",
    "wof:placetype":"locality"
},
  "geometry": {"coordinates":[110.65993,38.1155],"type":"Point"}
}