{
  "type": "Feature",
  "properties": {
    "gn:admin1_code":"11.0",
    "gn:asciiname":"Yangtangchong",
    "gn:country_code":"CN",
    "gn:dem":132,
    "gn:feature_class":"P",
    "gn:feature_code":"PPL",
    "gn:name":"Yangtangchong",
    "gn:population":0,
    "gn:timezone":"Asia/Shanghai",
    "iso:country":"CN",
    "name:zho_x_preferred":[
        "\u79e7\u5858\u51b2"
    ],
    "wof:name":"Yangtangchong",
    "wof:placetype":"locality"
},
  "geometry": {"coordinates":[112.10912999999999,26.71555],"type":"Point"}
}