{
  "type": "Feature",
  "properties": {
    "gn:admin1_code":"11.0",
    "gn:asciiname":"Yemaoping",
    "gn:country_code":"CN",
    "gn:dem":153,
    "gn:feature_class":"P",
    "gn:feature_code":"PPL",
    "gn:name":"Yemaoping",
    "gn:population":0,
    "gn:timezone":"Asia/Shanghai",
    "iso:country":"CN",
    "name:zho_x_preferred":[
        "\u91ce\u6bdb\u576a"
    ],
    "wof:name":"Yemaoping",
    "wof:placetype":"locality"
},
  "geometry": {"coordinates":[111.02318,28.60468],"type":"Point"}
}