{
  "type": "Feature",
  "properties": {
    "gn:admin1_code":"1.0",
    "gn:asciiname":"Lianggangcun",
    "gn:country_code":"CN",
    "gn:dem":38,
    "gn:feature_class":"P",
    "gn:feature_code":"PPL",
    "gn:name":"Lianggangcun",
    "gn:population":0,
    "gn:timezone":"Asia/Shanghai",
    "iso:country":"CN",
    "name:zho_x_preferred":[
        "\u6881\u5c97\u6751"
    ],
    "wof:name":"Lianggangcun",
    "wof:placetype":"locality"
},
  "geometry": {"coordinates":[117.38970999999999,31.35632],"type":"Point"}
}