{
  "type": "Feature",
  "properties": {
    "gn:admin1_code":"8.0",
    "gn:asciiname":"Xinchuncun",
    "gn:country_code":"CN",
    "gn:dem":166,
    "gn:feature_class":"P",
    "gn:feature_code":"PPL",
    "gn:name":"Xinchuncun",
    "gn:population":0,
    "gn:timezone":"Asia/Shanghai",
    "iso:country":"CN",
    "name:zho_x_preferred":[
        "\u65b0\u6625\u6751"
    ],
    "wof:name":"Xinchuncun",
    "wof:placetype":"locality"
},
  "geometry": {"coordinates":[127.71171,46.32424],"type":"Point"}
}