{
  "type": "Feature",
  "properties": {
    "gn:admin1_code":"31.0",
    "gn:asciiname":"Longma",
    "gn:country_code":"CN",
    "gn:dem":70,
    "gn:feature_class":"P",
    "gn:feature_code":"PPL",
    "gn:name":"Longma",
    "gn:population":0,
    "gn:timezone":"Asia/Shanghai",
    "iso:country":"CN",
    "name:zho_x_preferred":[
        "Longma"
    ],
    "name:zho_x_variant":[
        "\u9f99\u9a6c"
    ],
    "wof:name":"Longma",
    "wof:placetype":"locality"
},
  "geometry": {"coordinates":[110.57615,19.74172],"type":"Point"}
}