{
  "type": "Feature",
  "properties": {
    "gn:admin1_code":"18",
    "gn:asciiname":"Qiaogang",
    "gn:country_code":"CN",
    "gn:dem":818,
    "gn:feature_class":"P",
    "gn:feature_code":"PPL",
    "gn:name":"Qiaogang",
    "gn:population":0,
    "gn:timezone":"Asia/Shanghai",
    "iso:country":"CN",
    "name:zho_x_preferred":[
        "\u6865\u6e2f"
    ],
    "wof:name":"Qiaogang",
    "wof:placetype":"locality"
},
  "geometry": {"coordinates":[108.04000000000001,26.2734],"type":"Point"}
}