{
  "type": "Feature",
  "properties": {
    "gn:admin1_code":"1.0",
    "gn:asciiname":"Xiasicun",
    "gn:country_code":"CN",
    "gn:dem":51,
    "gn:feature_class":"P",
    "gn:feature_code":"PPL",
    "gn:name":"Xiasicun",
    "gn:population":0,
    "gn:timezone":"Asia/Shanghai",
    "iso:country":"CN",
    "name:zho_x_preferred":[
        "\u4e0b\u5bfa\u6751"
    ],
    "wof:name":"Xiasicun",
    "wof:placetype":"locality"
},
  "geometry": {"coordinates":[119.36407,31.09869],"type":"Point"}
}