{
  "type": "Feature",
  "properties": {
    "gn:admin1_code":"32.0",
    "gn:asciiname":"Guanluqu",
    "gn:country_code":"CN",
    "gn:dem":1273,
    "gn:feature_class":"P",
    "gn:feature_code":"PPL",
    "gn:name":"Guanluqu",
    "gn:population":0,
    "gn:timezone":"Asia/Shanghai",
    "iso:country":"CN",
    "name:zho_x_preferred":[
        "\u89c2\u8def\u6e20"
    ],
    "wof:name":"Guanluqu",
    "wof:placetype":"locality"
},
  "geometry": {"coordinates":[105.422,32.4146],"type":"Point"}
}