{
  "type": "Feature",
  "properties": {
    "gn:admin1_code":"26.0",
    "gn:asciiname":"Lucaogou",
    "gn:country_code":"CN",
    "gn:dem":1612,
    "gn:feature_class":"P",
    "gn:feature_code":"PPL",
    "gn:name":"Lucaogou",
    "gn:population":0,
    "gn:timezone":"Asia/Shanghai",
    "iso:country":"CN",
    "name:zho_x_preferred":[
        "\u82a6\u8349\u6c9f"
    ],
    "wof:name":"Lucaogou",
    "wof:placetype":"locality"
},
  "geometry": {"coordinates":[107.64315000000001,37.09638],"type":"Point"}
}