{
  "type": "Feature",
  "properties": {
    "gn:admin1_code":"11.0",
    "gn:asciiname":"Tuqiangling",
    "gn:country_code":"CN",
    "gn:dem":792,
    "gn:feature_class":"P",
    "gn:feature_code":"PPL",
    "gn:name":"Tuqiangling",
    "gn:population":0,
    "gn:timezone":"Asia/Shanghai",
    "iso:country":"CN",
    "name:zho_x_preferred":[
        "\u571f\u5899\u5cad"
    ],
    "wof:name":"Tuqiangling",
    "wof:placetype":"locality"
},
  "geometry": {"coordinates":[110.55306000000002,28.14904000000001],"type":"Point"}
}