{
  "type": "Feature",
  "properties": {
    "gn:admin1_code":"24.0",
    "gn:asciiname":"Chijiazhuang",
    "gn:country_code":"CN",
    "gn:dem":1404,
    "gn:feature_class":"P",
    "gn:feature_code":"PPL",
    "gn:name":"Chijiazhuang",
    "gn:population":0,
    "gn:timezone":"Asia/Shanghai",
    "iso:country":"CN",
    "name:zho_x_preferred":[
        "\u6c60\u5bb6\u5e84"
    ],
    "wof:name":"Chijiazhuang",
    "wof:placetype":"locality"
},
  "geometry": {"coordinates":[112.42041,37.04621],"type":"Point"}
}