{
  "type": "Feature",
  "properties": {
    "gn:admin1_code":"14.0",
    "gn:asciiname":"Naidong Muchang",
    "gn:country_code":"CN",
    "gn:dem":4035,
    "gn:feature_class":"P",
    "gn:feature_code":"PPLF",
    "gn:name":"Naidong Muchang",
    "gn:population":0,
    "gn:timezone":"Asia/Urumqi",
    "iso:country":"CN",
    "name:zho_x_preferred":[
        "\u4e43\u4e1c\u7267\u573a"
    ],
    "wof:name":"Naidong Muchang",
    "wof:placetype":"locality"
},
  "geometry": {"coordinates":[91.9055,29.44818],"type":"Point"}
}