{
  "type": "Feature",
  "properties": {
    "gn:admin1_code":"14.0",
    "gn:asciiname":"Cangge",
    "gn:country_code":"CN",
    "gn:dem":4762,
    "gn:feature_class":"P",
    "gn:feature_code":"PPL",
    "gn:name":"Cangge",
    "gn:population":0,
    "gn:timezone":"Asia/Urumqi",
    "iso:country":"CN",
    "name:zho_x_preferred":[
        "\u4ed3\u6208"
    ],
    "wof:name":"Cangge",
    "wof:placetype":"locality"
},
  "geometry": {"coordinates":[93.4285,30.00719],"type":"Point"}
}