{
  "type": "Feature",
  "properties": {
    "gn:admin1_code":"11",
    "gn:asciiname":"Yupingshan",
    "gn:country_code":"CN",
    "gn:dem":499,
    "gn:feature_class":"P",
    "gn:feature_code":"PPL",
    "gn:name":"Yupingshan",
    "gn:population":0,
    "gn:timezone":"Asia/Shanghai",
    "iso:country":"CN",
    "name:und_x_variant":[
        "\u7389\u5c4f\u5c71",
        "Yupingshan"
    ],
    "wof:name":"Yupingshan",
    "wof:placetype":"locality"
},
  "geometry": {"coordinates":[112.08806,25.85222000000001],"type":"Point"}
}