{
  "type": "Feature",
  "properties": {
    "gn:admin1_code":"16",
    "gn:asciiname":"Baishandi",
    "gn:country_code":"CN",
    "gn:dem":143,
    "gn:feature_class":"P",
    "gn:feature_code":"PPL",
    "gn:name":"Baishandi",
    "gn:population":0,
    "gn:timezone":"Asia/Shanghai",
    "iso:country":"CN",
    "name:zho_x_preferred":[
        "\u767d\u5c71\u5e95"
    ],
    "wof:name":"Baishandi",
    "wof:placetype":"locality"
},
  "geometry": {"coordinates":[110.56399999999999,24.9365],"type":"Point"}
}