{
  "type": "Feature",
  "properties": {
    "gn:admin1_code":"4.0",
    "gn:asciiname":"Gengguang",
    "gn:country_code":"CN",
    "gn:dem":5,
    "gn:feature_class":"P",
    "gn:feature_code":"PPL",
    "gn:name":"Gengguang",
    "gn:population":0,
    "gn:timezone":"Asia/Shanghai",
    "iso:country":"CN",
    "name:zho_x_preferred":[
        "\u803f\u7ba1"
    ],
    "wof:name":"Gengguang",
    "wof:placetype":"locality"
},
  "geometry": {"coordinates":[119.4539,32.34182],"type":"Point"}
}