{
  "type": "Feature",
  "properties": {
    "gn:admin1_code":"11.0",
    "gn:asciiname":"Sujiatang",
    "gn:country_code":"CN",
    "gn:dem":126,
    "gn:feature_class":"P",
    "gn:feature_code":"PPL",
    "gn:name":"Sujiatang",
    "gn:population":0,
    "gn:timezone":"Asia/Shanghai",
    "iso:country":"CN",
    "name:zho_x_preferred":[
        "\u7c9f\u5bb6\u5858"
    ],
    "wof:name":"Sujiatang",
    "wof:placetype":"locality"
},
  "geometry": {"coordinates":[112.14988,27.57448],"type":"Point"}
}