{
  "type": "Feature",
  "properties": {
    "gn:admin1_code":"19.0",
    "gn:asciiname":"Wajia Buzi",
    "gn:country_code":"CN",
    "gn:dem":262,
    "gn:feature_class":"P",
    "gn:feature_code":"PPL",
    "gn:name":"Wajia Buzi",
    "gn:population":0,
    "gn:timezone":"Asia/Shanghai",
    "iso:country":"CN",
    "name:zho_x_preferred":[
        "\u74e6\u5bb6\u5821\u5b50"
    ],
    "wof:name":"Wajia Buzi",
    "wof:placetype":"locality"
},
  "geometry": {"coordinates":[124.09,40.942],"type":"Point"}
}