{
  "type": "Feature",
  "properties": {
    "gn:admin1_code":"32.0",
    "gn:asciiname":"Atiri",
    "gn:country_code":"CN",
    "gn:dem":4081,
    "gn:feature_class":"P",
    "gn:feature_code":"PPL",
    "gn:name":"Atiri",
    "gn:population":0,
    "gn:timezone":"Asia/Shanghai",
    "iso:country":"CN",
    "name:zho_x_preferred":[
        "\u963f\u68af\u65e5"
    ],
    "wof:name":"Atiri",
    "wof:placetype":"locality"
},
  "geometry": {"coordinates":[101.29953,28.31513],"type":"Point"}
}