{
  "type": "Feature",
  "properties": {
    "gn:admin1_code":"30.0",
    "gn:asciiname":"Xialiaoxu",
    "gn:country_code":"CN",
    "gn:dem":22,
    "gn:feature_class":"P",
    "gn:feature_code":"PPL",
    "gn:name":"Xialiaoxu",
    "gn:population":0,
    "gn:timezone":"Asia/Shanghai",
    "iso:country":"CN",
    "name:zho_x_preferred":[
        "\u4e0b\u5bee\u5729"
    ],
    "wof:name":"Xialiaoxu",
    "wof:placetype":"locality"
},
  "geometry": {"coordinates":[112.74629,23.509],"type":"Point"}
}