{
  "type": "Feature",
  "properties": {
    "gn:admin1_code":"12.0",
    "gn:asciiname":"Junwangjiawan",
    "gn:country_code":"CN",
    "gn:dem":47,
    "gn:feature_class":"P",
    "gn:feature_code":"PPL",
    "gn:name":"Junwangjiawan",
    "gn:population":0,
    "gn:timezone":"Asia/Shanghai",
    "iso:country":"CN",
    "name:zho_x_preferred":[
        "Junwangjiawan"
    ],
    "name:zho_x_variant":[
        "\u541b\u738b\u5bb6\u6e7e"
    ],
    "wof:name":"Junwangjiawan",
    "wof:placetype":"locality"
},
  "geometry": {"coordinates":[111.93769,30.73571],"type":"Point"}
}