{
  "type": "Feature",
  "properties": {
    "gn:admin1_code":"5.0",
    "gn:asciiname":"Liangjiazicun",
    "gn:country_code":"CN",
    "gn:dem":142,
    "gn:feature_class":"P",
    "gn:feature_code":"PPL",
    "gn:name":"Liangjiazicun",
    "gn:population":0,
    "gn:timezone":"Asia/Shanghai",
    "iso:country":"CN",
    "name:zho_x_preferred":[
        "\u4e24\u5bb6\u5b50\u6751"
    ],
    "wof:name":"Liangjiazicun",
    "wof:placetype":"locality"
},
  "geometry": {"coordinates":[123.03625,45.43121],"type":"Point"}
}