{
  "type": "Feature",
  "properties": {
    "gn:admin1_code":"2.0",
    "gn:asciiname":"Xinyi",
    "gn:country_code":"CN",
    "gn:dem":134,
    "gn:feature_class":"P",
    "gn:feature_code":"PPL",
    "gn:name":"Xinyi",
    "gn:population":0,
    "gn:timezone":"Asia/Shanghai",
    "iso:country":"CN",
    "name:zho_x_preferred":[
        "\u65b0\u79fb"
    ],
    "wof:name":"Xinyi",
    "wof:placetype":"locality"
},
  "geometry": {"coordinates":[118.42440999999999,28.80332000000001],"type":"Point"}
}