{
  "type": "Feature",
  "properties": {
    "gn:admin1_code":"5.0",
    "gn:asciiname":"Yangjia Fenfang",
    "gn:country_code":"CN",
    "gn:dem":216,
    "gn:feature_class":"P",
    "gn:feature_code":"PPL",
    "gn:name":"Yangjia Fenfang",
    "gn:population":0,
    "gn:timezone":"Asia/Shanghai",
    "iso:country":"CN",
    "name:zho_x_preferred":[
        "\u6768\u5bb6\u7c89\u623f"
    ],
    "wof:name":"Yangjia Fenfang",
    "wof:placetype":"locality"
},
  "geometry": {"coordinates":[125.2696,43.91965],"type":"Point"}
}