{
  "type": "Feature",
  "properties": {
    "gn:admin1_code":"13.0",
    "gn:asciiname":"Qiong'aitike",
    "gn:country_code":"CN",
    "gn:dem":1151,
    "gn:feature_class":"P",
    "gn:feature_code":"PPL",
    "gn:name":"Qiong\u2019aitike",
    "gn:population":0,
    "gn:timezone":"Asia/Shanghai",
    "iso:country":"CN",
    "name:und_x_variant":[
        "Qiong\u2019aitike"
    ],
    "name:zho_x_preferred":[
        "\u743c\u827e\u63d0\u514b"
    ],
    "wof:name":"Qiong'aitike",
    "wof:placetype":"locality"
},
  "geometry": {"coordinates":[77.6797,39.70064],"type":"Point"}
}