{
  "type": "Feature",
  "properties": {
    "gn:admin1_code":"30.0",
    "gn:asciiname":"Nanshetang",
    "gn:country_code":"CN",
    "gn:dem":126,
    "gn:feature_class":"P",
    "gn:feature_code":"PPL",
    "gn:name":"Nanshetang",
    "gn:population":0,
    "gn:timezone":"Asia/Shanghai",
    "iso:country":"CN",
    "name:zho_x_preferred":[
        "Nanshetang"
    ],
    "name:zho_x_variant":[
        "\u5357\u86c7\u5858"
    ],
    "wof:name":"Nanshetang",
    "wof:placetype":"locality"
},
  "geometry": {"coordinates":[114.37796000000002,24.13419],"type":"Point"}
}