{
  "type": "Feature",
  "properties": {
    "gn:admin1_code":"29.0",
    "gn:asciiname":"Xilong",
    "gn:country_code":"CN",
    "gn:dem":2474,
    "gn:feature_class":"P",
    "gn:feature_code":"PPL",
    "gn:name":"Xilong",
    "gn:population":0,
    "gn:timezone":"Asia/Shanghai",
    "iso:country":"CN",
    "name:zho_x_preferred":[
        "\u897f\u9f99"
    ],
    "wof:name":"Xilong",
    "wof:placetype":"locality"
},
  "geometry": {"coordinates":[100.102,27.0536],"type":"Point"}
}