{
  "type": "Feature",
  "properties": {
    "gn:admin1_code":"19.0",
    "gn:asciiname":"Songshugou Xiagou",
    "gn:country_code":"CN",
    "gn:dem":230,
    "gn:feature_class":"P",
    "gn:feature_code":"PPL",
    "gn:name":"Songshugou Xiagou",
    "gn:population":0,
    "gn:timezone":"Asia/Shanghai",
    "iso:country":"CN",
    "name:zho_x_preferred":[
        "\u677e\u6811\u6c9f\u4e0b\u6c9f"
    ],
    "wof:name":"Songshugou Xiagou",
    "wof:placetype":"locality"
},
  "geometry": {"coordinates":[120.40300000000001,41.2487],"type":"Point"}
}