{
  "type": "Feature",
  "properties": {
    "gn:admin1_code":"16.0",
    "gn:asciiname":"Daqin",
    "gn:country_code":"CN",
    "gn:dem":118,
    "gn:feature_class":"P",
    "gn:feature_code":"PPL",
    "gn:name":"Daqin",
    "gn:population":0,
    "gn:timezone":"Asia/Shanghai",
    "iso:country":"CN",
    "name:deu_x_preferred":[
        "Daqin"
    ],
    "name:epo_x_preferred":[
        "Da Qin"
    ],
    "name:fin_x_preferred":[
        "Daqin"
    ],
    "name:fra_x_preferred":[
        "Da Qin"
    ],
    "name:ind_x_preferred":[
        "Daqin"
    ],
    "name:ita_x_preferred":[
        "Da Qin"
    ],
    "name:kor_x_preferred":[
        "\ub300\uc9c4"
    ],
    "name:nld_x_preferred":[
        "Da Qin"
    ],
    "name:nor_x_preferred":[
        "Daqin"
    ],
    "name:pol_x_preferred":[
        "Daqin"
    ],
    "name:spa_x_preferred":[
        "Da Qin"
    ],
    "name:zho_x_preferred":[
        "\u5927\u7434"
    ],
    "wof:name":"Daqin",
    "wof:placetype":"locality"
},
  "geometry": {"coordinates":[108.19,22.5945],"type":"Point"}
}