{
  "type": "Feature",
  "properties": {
    "gn:admin1_code":"25.0",
    "gn:asciiname":"Beiliushui",
    "gn:country_code":"CN",
    "gn:dem":54,
    "gn:feature_class":"P",
    "gn:feature_code":"PPL",
    "gn:name":"Beiliushui",
    "gn:population":0,
    "gn:timezone":"Asia/Shanghai",
    "iso:country":"CN",
    "name:zho_x_preferred":[
        "\u5317\u6d41\u6c34"
    ],
    "wof:name":"Beiliushui",
    "wof:placetype":"locality"
},
  "geometry": {"coordinates":[122.33280999999999,37.2004],"type":"Point"}
}