{
  "type": "Feature",
  "properties": {
    "gn:admin1_code":"15.0",
    "gn:asciiname":"Shigucha",
    "gn:country_code":"CN",
    "gn:dem":2497,
    "gn:feature_class":"P",
    "gn:feature_code":"PPL",
    "gn:name":"Shigucha",
    "gn:population":0,
    "gn:timezone":"Asia/Shanghai",
    "iso:country":"CN",
    "name:zho_x_preferred":[
        "\u77f3\u9aa8\u5c94"
    ],
    "wof:name":"Shigucha",
    "wof:placetype":"locality"
},
  "geometry": {"coordinates":[104.03100000000001,35.7812],"type":"Point"}
}