{
  "type": "Feature",
  "properties": {
    "gn:admin1_code":"29.0",
    "gn:asciiname":"Kuangchang",
    "gn:country_code":"CN",
    "gn:dem":1933,
    "gn:feature_class":"P",
    "gn:feature_code":"PPL",
    "gn:name":"Kuangchang",
    "gn:population":0,
    "gn:timezone":"Asia/Shanghai",
    "iso:country":"CN",
    "name:zho_x_preferred":[
        "\u77ff\u5382"
    ],
    "wof:name":"Kuangchang",
    "wof:placetype":"locality"
},
  "geometry": {"coordinates":[103.67100000000001,24.7036],"type":"Point"}
}