{
  "type": "Feature",
  "properties": {
    "gn:admin1_code":"29",
    "gn:asciiname":"Longtan",
    "gn:country_code":"CN",
    "gn:dem":1887,
    "gn:feature_class":"P",
    "gn:feature_code":"PPL",
    "gn:name":"Longtan",
    "gn:population":0,
    "gn:timezone":"Asia/Shanghai",
    "iso:country":"CN",
    "name:und_x_variant":[
        "\u9f99\u6f6d"
    ],
    "wof:name":"Longtan",
    "wof:placetype":"locality"
},
  "geometry": {"coordinates":[103.76291000000001,25.53614],"type":"Point"}
}