{
  "type": "Feature",
  "properties": {
    "gn:admin1_code":"15.0",
    "gn:asciiname":"Zhujiaxianzi",
    "gn:country_code":"CN",
    "gn:dem":1463,
    "gn:feature_class":"P",
    "gn:feature_code":"PPL",
    "gn:name":"Zhujiaxianzi",
    "gn:population":0,
    "gn:timezone":"Asia/Shanghai",
    "iso:country":"CN",
    "name:zho_x_preferred":[
        "\u6731\u5bb6\u5c98\u5b50"
    ],
    "wof:name":"Zhujiaxianzi",
    "wof:placetype":"locality"
},
  "geometry": {"coordinates":[108.298,35.9429],"type":"Point"}
}