{
  "type": "Feature",
  "properties": {
    "gn:admin1_code":"24",
    "gn:asciiname":"Xubu",
    "gn:country_code":"CN",
    "gn:dem":1041,
    "gn:feature_class":"P",
    "gn:feature_code":"PPLA4",
    "gn:name":"Xubu",
    "gn:population":0,
    "gn:timezone":"Asia/Shanghai",
    "iso:country":"CN",
    "name:jpn_x_preferred":[
        "\u9808\u535c\u6c0f"
    ],
    "name:kor_x_preferred":[
        "\uc218\ubcf5\uc528"
    ],
    "name:und_x_variant":[
        "Hs\u00fc-chia-pao",
        "Hs\u00fc-pao",
        "Hs\u00fc-chia-p\u2019u",
        "Xubu",
        "\u8bb8\u5821",
        "Xubu Zhen",
        "\u8bb8\u5821\u9547"
    ],
    "name:zho_x_preferred":[
        "\u9808\u535c\u6c0f"
    ],
    "wof:name":"Xubu",
    "wof:placetype":"locality"
},
  "geometry": {"coordinates":[113.74473,40.02792],"type":"Point"}
}