{
  "type": "Feature",
  "properties": {
    "gn:admin1_code":"10.0",
    "gn:asciiname":"Zhouliangzhi",
    "gn:country_code":"CN",
    "gn:dem":7,
    "gn:feature_class":"P",
    "gn:feature_code":"PPL",
    "gn:name":"Zhouliangzhi",
    "gn:population":0,
    "gn:timezone":"Asia/Shanghai",
    "iso:country":"CN",
    "name:zho_x_preferred":[
        "\u5468\u826f\u5fd7"
    ],
    "wof:name":"Zhouliangzhi",
    "wof:placetype":"locality"
},
  "geometry": {"coordinates":[117.54900000000001,38.1565],"type":"Point"}
}