{
  "type": "Feature",
  "properties": {
    "gn:admin1_code":"26.0",
    "gn:asciiname":"Lannihu",
    "gn:country_code":"CN",
    "gn:dem":757,
    "gn:feature_class":"P",
    "gn:feature_code":"PPL",
    "gn:name":"Lannihu",
    "gn:population":0,
    "gn:timezone":"Asia/Shanghai",
    "iso:country":"CN",
    "name:zho_x_preferred":[
        "\u6ee5\u6ce5\u6e56"
    ],
    "wof:name":"Lannihu",
    "wof:placetype":"locality"
},
  "geometry": {"coordinates":[109.84197,32.79638],"type":"Point"}
}