{
  "type": "Feature",
  "properties": {
    "gn:admin1_code":"11.0",
    "gn:asciiname":"Shiniuba",
    "gn:country_code":"CN",
    "gn:dem":72,
    "gn:feature_class":"P",
    "gn:feature_code":"PPL",
    "gn:name":"Shiniuba",
    "gn:population":0,
    "gn:timezone":"Asia/Shanghai",
    "iso:country":"CN",
    "name:zho_x_preferred":[
        "\u77f3\u725b\u575d"
    ],
    "wof:name":"Shiniuba",
    "wof:placetype":"locality"
},
  "geometry": {"coordinates":[112.70889,27.87572],"type":"Point"}
}