{
  "type": "Feature",
  "properties": {
    "gn:admin1_code":"6.0",
    "gn:asciiname":"Guolayang",
    "gn:country_code":"CN",
    "gn:dem":3413,
    "gn:feature_class":"P",
    "gn:feature_code":"PPL",
    "gn:name":"Guolayang",
    "gn:population":0,
    "gn:timezone":"Asia/Shanghai",
    "iso:country":"CN",
    "name:zho_x_preferred":[
        "\u90ed\u62c9\u7f8a"
    ],
    "wof:name":"Guolayang",
    "wof:placetype":"locality"
},
  "geometry": {"coordinates":[101.52272000000001,35.73477000000001],"type":"Point"}
}