{
  "type": "Feature",
  "properties": {
    "gn:admin1_code":"18",
    "gn:asciiname":"Baiyanggang",
    "gn:country_code":"CN",
    "gn:dem":1134,
    "gn:feature_class":"P",
    "gn:feature_code":"PPL",
    "gn:name":"Baiyanggang",
    "gn:population":0,
    "gn:timezone":"Asia/Shanghai",
    "iso:country":"CN",
    "name:zho_x_preferred":[
        "\u67cf\u6768\u5c97"
    ],
    "wof:name":"Baiyanggang",
    "wof:placetype":"locality"
},
  "geometry": {"coordinates":[106.387,28.2824],"type":"Point"}
}