{
  "type": "Feature",
  "properties": {
    "gn:admin1_code":"18.0",
    "gn:asciiname":"Dongda",
    "gn:country_code":"CN",
    "gn:dem":869,
    "gn:feature_class":"P",
    "gn:feature_code":"PPL",
    "gn:name":"Dongda",
    "gn:population":0,
    "gn:timezone":"Asia/Shanghai",
    "iso:country":"CN",
    "name:zho_x_preferred":[
        "\u8463\u5927"
    ],
    "wof:name":"Dongda",
    "wof:placetype":"locality"
},
  "geometry": {"coordinates":[107.61499999999999,25.5166],"type":"Point"}
}