{
  "type": "Feature",
  "properties": {
    "gn:admin1_code":"9.0",
    "gn:asciiname":"Zhifanggou",
    "gn:country_code":"CN",
    "gn:dem":436,
    "gn:feature_class":"P",
    "gn:feature_code":"PPL",
    "gn:name":"Zhifanggou",
    "gn:population":0,
    "gn:timezone":"Asia/Shanghai",
    "iso:country":"CN",
    "name:zho_x_preferred":[
        "\u7eb8\u623f\u6c9f"
    ],
    "wof:name":"Zhifanggou",
    "wof:placetype":"locality"
},
  "geometry": {"coordinates":[111.38449,33.17472],"type":"Point"}
}