{
  "type": "Feature",
  "properties": {
    "gn:admin1_code":"30.0",
    "gn:asciiname":"Zhouwu",
    "gn:country_code":"CN",
    "gn:dem":72,
    "gn:feature_class":"P",
    "gn:feature_code":"PPL",
    "gn:name":"Zhouwu",
    "gn:population":0,
    "gn:timezone":"Asia/Shanghai",
    "iso:country":"CN",
    "name:zho_x_preferred":[
        "\u5468\u5c4b"
    ],
    "wof:name":"Zhouwu",
    "wof:placetype":"locality"
},
  "geometry": {"coordinates":[112.00714000000001,23.92232000000001],"type":"Point"}
}