{
  "type": "Feature",
  "properties": {
    "gn:admin1_code":"29",
    "gn:asciiname":"Yixiang",
    "gn:country_code":"CN",
    "gn:dem":1622,
    "gn:feature_class":"P",
    "gn:feature_code":"PPL",
    "gn:name":"Yixiang",
    "gn:population":0,
    "gn:timezone":"Asia/Shanghai",
    "iso:country":"CN",
    "name:zho_x_preferred":[
        "\u8fe4\u9999"
    ],
    "wof:name":"Yixiang",
    "wof:placetype":"locality"
},
  "geometry": {"coordinates":[101.732,24.9775],"type":"Point"}
}