{
  "type": "Feature",
  "properties": {
    "gn:admin1_code":"12.0",
    "gn:asciiname":"Yaoling",
    "gn:country_code":"CN",
    "gn:dem":853,
    "gn:feature_class":"P",
    "gn:feature_code":"PPL",
    "gn:name":"Yaoling",
    "gn:population":0,
    "gn:timezone":"Asia/Shanghai",
    "iso:country":"CN",
    "name:zho_x_preferred":[
        "\u7a91\u5cad"
    ],
    "wof:name":"Yaoling",
    "wof:placetype":"locality"
},
  "geometry": {"coordinates":[110.11288999999999,33.12149],"type":"Point"}
}