{
  "type": "Feature",
  "properties": {
    "gn:admin1_code":"24.0",
    "gn:asciiname":"Xiaohangou",
    "gn:country_code":"CN",
    "gn:dem":1644,
    "gn:feature_class":"P",
    "gn:feature_code":"PPL",
    "gn:name":"Xiaohangou",
    "gn:population":0,
    "gn:timezone":"Asia/Shanghai",
    "iso:country":"CN",
    "name:zho_x_preferred":[
        "\u5c0f\u6c49\u6c9f"
    ],
    "wof:name":"Xiaohangou",
    "wof:placetype":"locality"
},
  "geometry": {"coordinates":[112.19323,38.66321],"type":"Point"}
}