{
  "type": "Feature",
  "properties": {
    "gn:admin1_code":"16.0",
    "gn:asciiname":"Daluping",
    "gn:country_code":"CN",
    "gn:dem":91,
    "gn:feature_class":"P",
    "gn:feature_code":"PPL",
    "gn:name":"Daluping",
    "gn:population":0,
    "gn:timezone":"Asia/Shanghai",
    "iso:country":"CN",
    "name:zho_x_preferred":[
        "\u5927\u9e93\u576a"
    ],
    "wof:name":"Daluping",
    "wof:placetype":"locality"
},
  "geometry": {"coordinates":[109.14400000000001,22.2279],"type":"Point"}
}