{
  "type": "Feature",
  "properties": {
    "gn:admin1_code":"32.0",
    "gn:asciiname":"Qilongmiao",
    "gn:country_code":"CN",
    "gn:dem":437,
    "gn:feature_class":"P",
    "gn:feature_code":"PPL",
    "gn:name":"Qilongmiao",
    "gn:population":0,
    "gn:timezone":"Asia/Shanghai",
    "iso:country":"CN",
    "name:zho_x_preferred":[
        "\u9a91\u9f99\u5e99"
    ],
    "wof:name":"Qilongmiao",
    "wof:placetype":"locality"
},
  "geometry": {"coordinates":[105.22799999999999,30.0961],"type":"Point"}
}