{
  "type": "Feature",
  "properties": {
    "gn:admin1_code":"16.0",
    "gn:asciiname":"Banpang",
    "gn:country_code":"CN",
    "gn:dem":198,
    "gn:feature_class":"P",
    "gn:feature_code":"PPL",
    "gn:name":"Banpang",
    "gn:population":0,
    "gn:timezone":"Asia/Shanghai",
    "iso:country":"CN",
    "name:zho_x_preferred":[
        "\u677f\u5e9e"
    ],
    "wof:name":"Banpang",
    "wof:placetype":"locality"
},
  "geometry": {"coordinates":[108.52200000000001,23.2727],"type":"Point"}
}