{
  "type": "Feature",
  "properties": {
    "gn:admin1_code":"18",
    "gn:asciiname":"Fayingou",
    "gn:country_code":"CN",
    "gn:dem":1570,
    "gn:feature_class":"P",
    "gn:feature_code":"PPL",
    "gn:name":"Fayingou",
    "gn:population":0,
    "gn:timezone":"Asia/Shanghai",
    "iso:country":"CN",
    "name:zho_x_preferred":[
        "\u53d1\u97f3\u6c9f"
    ],
    "wof:name":"Fayingou",
    "wof:placetype":"locality"
},
  "geometry": {"coordinates":[105.35899999999999,27.1155],"type":"Point"}
}