{
  "type": "Feature",
  "properties": {
    "gn:admin1_code":"7.0",
    "gn:asciiname":"Youshantou",
    "gn:country_code":"CN",
    "gn:dem":552,
    "gn:feature_class":"P",
    "gn:feature_code":"PPL",
    "gn:name":"Youshantou",
    "gn:population":0,
    "gn:timezone":"Asia/Shanghai",
    "iso:country":"CN",
    "name:zho_x_preferred":[
        "\u6e38\u5c71\u5934"
    ],
    "wof:name":"Youshantou",
    "wof:placetype":"locality"
},
  "geometry": {"coordinates":[117.59763,25.61298],"type":"Point"}
}