{
  "type": "Feature",
  "properties": {
    "gn:admin1_code":"29.0",
    "gn:asciiname":"Xiaoyuejiu",
    "gn:country_code":"CN",
    "gn:dem":1151,
    "gn:feature_class":"P",
    "gn:feature_code":"PPL",
    "gn:name":"Xiaoyuejiu",
    "gn:population":0,
    "gn:timezone":"Asia/Shanghai",
    "iso:country":"CN",
    "name:zho_x_preferred":[
        "\u5c0f\u6708\u65e7"
    ],
    "wof:name":"Xiaoyuejiu",
    "wof:placetype":"locality"
},
  "geometry": {"coordinates":[101.83199999999999,25.5959],"type":"Point"}
}