{
  "type": "Feature",
  "properties": {
    "gn:admin1_code":"32.0",
    "gn:asciiname":"Rediping",
    "gn:country_code":"CN",
    "gn:dem":2814,
    "gn:feature_class":"P",
    "gn:feature_code":"PPL",
    "gn:name":"Rediping",
    "gn:population":0,
    "gn:timezone":"Asia/Shanghai",
    "iso:country":"CN",
    "name:zho_x_preferred":[
        "\u70ed\u5730\u576a"
    ],
    "wof:name":"Rediping",
    "wof:placetype":"locality"
},
  "geometry": {"coordinates":[102.17743,31.48964],"type":"Point"}
}