{
  "type": "Feature",
  "properties": {
    "gn:admin1_code":"30",
    "gn:asciiname":"Buxu",
    "gn:country_code":"CN",
    "gn:dem":-2,
    "gn:feature_class":"P",
    "gn:feature_code":"PPL",
    "gn:name":"Buxu",
    "gn:population":0,
    "gn:timezone":"Asia/Shanghai",
    "iso:country":"CN",
    "name:und_x_variant":[
        "Pu-hs\u00fc",
        "Buxu"
    ],
    "wof:name":"Buxu",
    "wof:placetype":"locality"
},
  "geometry": {"coordinates":[113.33333,22.63333],"type":"Point"}
}