{
  "type": "Feature",
  "properties": {
    "gn:admin1_code":"29.0",
    "gn:asciiname":"Laba",
    "gn:country_code":"CN",
    "gn:dem":2432,
    "gn:feature_class":"P",
    "gn:feature_code":"PPL",
    "gn:name":"Laba",
    "gn:population":0,
    "gn:timezone":"Asia/Shanghai",
    "iso:country":"CN",
    "name:zho_x_preferred":[
        "\u62c9\u5df4"
    ],
    "wof:name":"Laba",
    "wof:placetype":"locality"
},
  "geometry": {"coordinates":[100.108,27.7799],"type":"Point"}
}