{
  "type": "Feature",
  "properties": {
    "gn:admin1_code":"1.0",
    "gn:asciiname":"Sanxiangcun",
    "gn:country_code":"CN",
    "gn:dem":20,
    "gn:feature_class":"P",
    "gn:feature_code":"PPL",
    "gn:name":"Sanxiangcun",
    "gn:population":0,
    "gn:timezone":"Asia/Shanghai",
    "iso:country":"CN",
    "name:zho_x_preferred":[
        "\u4e09\u5df7\u6751"
    ],
    "wof:name":"Sanxiangcun",
    "wof:placetype":"locality"
},
  "geometry": {"coordinates":[117.13538,33.02282],"type":"Point"}
}