{
  "type": "Feature",
  "properties": {
    "gn:admin1_code":"04",
    "gn:asciiname":"Sidadui",
    "gn:country_code":"CN",
    "gn:dem":-9999,
    "gn:feature_class":"P",
    "gn:feature_code":"PPLF",
    "gn:name":"Sidadui",
    "gn:population":0,
    "gn:timezone":"Asia/Shanghai",
    "iso:country":"CN",
    "wof:name":"Sidadui",
    "wof:placetype":"locality"
},
  "geometry": {"coordinates":[121.33444,32.42556],"type":"Point"}
}