{
  "type": "Feature",
  "properties": {
    "gn:admin1_code":"18.0",
    "gn:asciiname":"Shazikan",
    "gn:country_code":"CN",
    "gn:dem":1159,
    "gn:feature_class":"P",
    "gn:feature_code":"PPL",
    "gn:name":"Shazikan",
    "gn:population":0,
    "gn:timezone":"Asia/Shanghai",
    "iso:country":"CN",
    "name:zho_x_preferred":[
        "\u6c99\u5b50\u574e"
    ],
    "wof:name":"Shazikan",
    "wof:placetype":"locality"
},
  "geometry": {"coordinates":[107.435,26.9352],"type":"Point"}
}