{
  "type": "Feature",
  "properties": {
    "gn:admin1_code":"3.0",
    "gn:asciiname":"Shaofangcun",
    "gn:country_code":"CN",
    "gn:dem":22,
    "gn:feature_class":"P",
    "gn:feature_code":"PPL",
    "gn:name":"Shaofangcun",
    "gn:population":0,
    "gn:timezone":"Asia/Shanghai",
    "iso:country":"CN",
    "name:und_x_variant":[
        "\u90b5\u574a\u6751"
    ],
    "wof:name":"Shaofangcun",
    "wof:placetype":"locality"
},
  "geometry": {"coordinates":[115.92740999999999,28.37665],"type":"Point"}
}