{
  "type": "Feature",
  "properties": {
    "gn:admin1_code":"15",
    "gn:asciiname":"Qiangwan",
    "gn:cc2":"CN",
    "gn:country_code":"CN",
    "gn:dem":1606,
    "gn:feature_class":"P",
    "gn:feature_code":"PPL",
    "gn:name":"Qiangwan",
    "gn:population":0,
    "gn:timezone":"Asia/Shanghai",
    "iso:country":"CN",
    "wof:name":"Qiangwan",
    "wof:placetype":"locality"
},
  "geometry": {"coordinates":[104.205,36.42139],"type":"Point"}
}