{
  "type": "Feature",
  "properties": {
    "gn:admin1_code":"11.0",
    "gn:asciiname":"Qujiaxi",
    "gn:country_code":"CN",
    "gn:dem":210,
    "gn:feature_class":"P",
    "gn:feature_code":"PPL",
    "gn:name":"Qujiaxi",
    "gn:population":0,
    "gn:timezone":"Asia/Shanghai",
    "iso:country":"CN",
    "name:zho_x_preferred":[
        "\u77bf\u5bb6\u6eaa"
    ],
    "wof:name":"Qujiaxi",
    "wof:placetype":"locality"
},
  "geometry": {"coordinates":[110.37841,28.62711],"type":"Point"}
}