{
  "type": "Feature",
  "properties": {
    "gn:admin1_code":"9.0",
    "gn:asciiname":"Shangling",
    "gn:country_code":"CN",
    "gn:dem":740,
    "gn:feature_class":"P",
    "gn:feature_code":"PPL",
    "gn:name":"Shangling",
    "gn:population":0,
    "gn:timezone":"Asia/Shanghai",
    "iso:country":"CN",
    "name:zho_x_preferred":[
        "\u4e0a\u5cad"
    ],
    "wof:name":"Shangling",
    "wof:placetype":"locality"
},
  "geometry": {"coordinates":[111.51557,34.59961],"type":"Point"}
}