{
  "type": "Feature",
  "properties": {
    "gn:admin1_code":"4.0",
    "gn:asciiname":"Yunlong",
    "gn:country_code":"CN",
    "gn:dem":2,
    "gn:feature_class":"P",
    "gn:feature_code":"PPL",
    "gn:name":"Yunlong",
    "gn:population":0,
    "gn:timezone":"Asia/Shanghai",
    "iso:country":"CN",
    "name:ceb_x_preferred":[
        "Yunlong"
    ],
    "name:deu_x_preferred":[
        "Yunlong"
    ],
    "name:fra_x_preferred":[
        "Yunlong"
    ],
    "name:rus_x_preferred":[
        "\u042e\u043d\u044c\u043b\u0443\u043d"
    ],
    "name:swe_x_preferred":[
        "Yunlong"
    ],
    "name:und_x_variant":[
        "\u4e91\u9f99"
    ],
    "wof:name":"Yunlong",
    "wof:placetype":"locality"
},
  "geometry": {"coordinates":[121.30808,31.97277],"type":"Point"}
}