{
  "type": "Feature",
  "properties": {
    "gn:admin1_code":"29.0",
    "gn:asciiname":"Tiansheng",
    "gn:country_code":"CN",
    "gn:dem":2084,
    "gn:feature_class":"P",
    "gn:feature_code":"PPL",
    "gn:name":"Tiansheng",
    "gn:population":0,
    "gn:timezone":"Asia/Shanghai",
    "iso:country":"CN",
    "name:und_x_variant":[
        "\u5929\u751f"
    ],
    "wof:name":"Tiansheng",
    "wof:placetype":"locality"
},
  "geometry": {"coordinates":[103.04207,26.99817],"type":"Point"}
}