{
  "type": "Feature",
  "properties": {
    "gn:admin1_code":"19.0",
    "gn:asciiname":"Motianling",
    "gn:country_code":"CN",
    "gn:dem":292,
    "gn:feature_class":"P",
    "gn:feature_code":"PPL",
    "gn:name":"Motianling",
    "gn:population":0,
    "gn:timezone":"Asia/Shanghai",
    "iso:country":"CN",
    "name:und_x_variant":[
        "\u6469\u5929\u5cad"
    ],
    "wof:name":"Motianling",
    "wof:placetype":"locality"
},
  "geometry": {"coordinates":[123.71813,40.9575],"type":"Point"}
}