{
  "type": "Feature",
  "properties": {
    "gn:admin1_code":"24",
    "gn:asciiname":"Dongcaozhai",
    "gn:country_code":"CN",
    "gn:dem":768,
    "gn:feature_class":"P",
    "gn:feature_code":"PPL",
    "gn:name":"Dongcaozhai",
    "gn:population":0,
    "gn:timezone":"Asia/Shanghai",
    "iso:country":"CN",
    "wof:name":"Dongcaozhai",
    "wof:placetype":"locality"
},
  "geometry": {"coordinates":[112.46278,37.67139],"type":"Point"}
}