{
  "type": "Feature",
  "properties": {
    "gn:admin1_code":"7",
    "gn:asciiname":"Laidi",
    "gn:country_code":"CN",
    "gn:dem":99,
    "gn:feature_class":"P",
    "gn:feature_code":"PPL",
    "gn:name":"Laidi",
    "gn:population":0,
    "gn:timezone":"Asia/Shanghai",
    "iso:country":"CN",
    "name:zho_x_preferred":[
        "\u6fd1\u5e95"
    ],
    "wof:name":"Laidi",
    "wof:placetype":"locality"
},
  "geometry": {"coordinates":[119.21857,25.71331],"type":"Point"}
}