{
  "type": "Feature",
  "properties": {
    "gn:admin1_code":"25.0",
    "gn:asciiname":"Baimashecun",
    "gn:country_code":"CN",
    "gn:dem":28,
    "gn:feature_class":"P",
    "gn:feature_code":"PPL",
    "gn:name":"Baimashecun",
    "gn:population":0,
    "gn:timezone":"Asia/Shanghai",
    "iso:country":"CN",
    "name:zho_x_preferred":[
        "\u767d\u9a6c\u793e\u6751"
    ],
    "wof:name":"Baimashecun",
    "wof:placetype":"locality"
},
  "geometry": {"coordinates":[119.6431,35.76197],"type":"Point"}
}