{
  "type": "Feature",
  "properties": {
    "gn:admin1_code":"4.0",
    "gn:asciiname":"Fengwa",
    "gn:country_code":"CN",
    "gn:dem":21,
    "gn:feature_class":"P",
    "gn:feature_code":"PPL",
    "gn:name":"Fengwa",
    "gn:population":0,
    "gn:timezone":"Asia/Shanghai",
    "iso:country":"CN",
    "name:zho_x_preferred":[
        "\u4e30\u6d3c"
    ],
    "wof:name":"Fengwa",
    "wof:placetype":"locality"
},
  "geometry": {"coordinates":[118.33799999999999,33.9692],"type":"Point"}
}