{
  "type": "Feature",
  "properties": {
    "gn:admin1_code":"29.0",
    "gn:asciiname":"Yiqiutian",
    "gn:country_code":"CN",
    "gn:dem":1456,
    "gn:feature_class":"P",
    "gn:feature_code":"PPL",
    "gn:name":"Yiqiutian",
    "gn:population":0,
    "gn:timezone":"Asia/Shanghai",
    "iso:country":"CN",
    "name:zho_x_preferred":[
        "\u4e00\u4e18\u7530"
    ],
    "wof:name":"Yiqiutian",
    "wof:placetype":"locality"
},
  "geometry": {"coordinates":[98.675,24.5523],"type":"Point"}
}