{
  "type": "Feature",
  "properties": {
    "gn:admin1_code":"16.0",
    "gn:asciiname":"Baluo",
    "gn:country_code":"CN",
    "gn:dem":748,
    "gn:feature_class":"P",
    "gn:feature_code":"PPL",
    "gn:name":"Baluo",
    "gn:population":0,
    "gn:timezone":"Asia/Shanghai",
    "iso:country":"CN",
    "name:zho_x_preferred":[
        "\u628a\u7f57"
    ],
    "wof:name":"Baluo",
    "wof:placetype":"locality"
},
  "geometry": {"coordinates":[106.586,23.1686],"type":"Point"}
}