{
  "type": "Feature",
  "properties": {
    "gn:admin1_code":"18",
    "gn:asciiname":"Shuigoukan",
    "gn:country_code":"CN",
    "gn:dem":878,
    "gn:feature_class":"P",
    "gn:feature_code":"PPL",
    "gn:name":"Shuigoukan",
    "gn:population":0,
    "gn:timezone":"Asia/Shanghai",
    "iso:country":"CN",
    "name:zho_x_preferred":[
        "\u6c34\u6c9f\u574e"
    ],
    "wof:name":"Shuigoukan",
    "wof:placetype":"locality"
},
  "geometry": {"coordinates":[107.742,28.1315],"type":"Point"}
}