{
  "type": "Feature",
  "properties": {
    "gn:admin1_code":"30",
    "gn:asciiname":"Zhegulong",
    "gn:country_code":"CN",
    "gn:dem":227,
    "gn:feature_class":"P",
    "gn:feature_code":"PPL",
    "gn:name":"Zhegulong",
    "gn:population":0,
    "gn:timezone":"Asia/Shanghai",
    "iso:country":"CN",
    "name:zho_x_preferred":[
        "\u9e67\u9e2a\u9686"
    ],
    "wof:name":"Zhegulong",
    "wof:placetype":"locality"
},
  "geometry": {"coordinates":[115.9203,24.89565],"type":"Point"}
}