{
  "type": "Feature",
  "properties": {
    "gn:admin1_code":"10",
    "gn:asciiname":"Nantongye",
    "gn:country_code":"CN",
    "gn:dem":91,
    "gn:feature_class":"P",
    "gn:feature_code":"PPL",
    "gn:name":"Nantongye",
    "gn:population":0,
    "gn:timezone":"Asia/Shanghai",
    "iso:country":"CN",
    "name:und_x_variant":[
        "Nan-t\u2019ung-yeh-chen",
        "Nan-t\u2019ung-yeh",
        "Nantongye"
    ],
    "name:zho_x_preferred":[
        "\u5357\u94dc\u51b6"
    ],
    "wof:name":"Nantongye",
    "wof:placetype":"locality"
},
  "geometry": {"coordinates":[114.376,37.961],"type":"Point"}
}