{
  "type": "Feature",
  "properties": {
    "gn:admin1_code":"11",
    "gn:asciiname":"Tieluling",
    "gn:country_code":"CN",
    "gn:dem":777,
    "gn:feature_class":"P",
    "gn:feature_code":"PPL",
    "gn:name":"Tieluling",
    "gn:population":0,
    "gn:timezone":"Asia/Shanghai",
    "iso:country":"CN",
    "wof:name":"Tieluling",
    "wof:placetype":"locality"
},
  "geometry": {"coordinates":[110.21722,29.25917],"type":"Point"}
}