{
  "type": "Feature",
  "properties": {
    "gn:admin1_code":"32.0",
    "gn:asciiname":"Kalu",
    "gn:country_code":"CN",
    "gn:dem":3694,
    "gn:feature_class":"P",
    "gn:feature_code":"PPL",
    "gn:name":"Kalu",
    "gn:population":0,
    "gn:timezone":"Asia/Shanghai",
    "iso:country":"CN",
    "name:zho_x_preferred":[
        "\u5361\u9c81"
    ],
    "wof:name":"Kalu",
    "wof:placetype":"locality"
},
  "geometry": {"coordinates":[100.248,30.9137],"type":"Point"}
}