{
  "type": "Feature",
  "properties": {
    "gn:admin1_code":"22",
    "gn:asciiname":"Dongxinfang",
    "gn:country_code":"CN",
    "gn:dem":146,
    "gn:feature_class":"P",
    "gn:feature_code":"PPL",
    "gn:name":"Dongxinfang",
    "gn:population":0,
    "gn:timezone":"Asia/Shanghai",
    "iso:country":"CN",
    "name:zho_x_preferred":[
        "\u4e1c\u8f9b\u623f"
    ],
    "wof:name":"Dongxinfang",
    "wof:placetype":"locality"
},
  "geometry": {"coordinates":[116.06569,39.93155],"type":"Point"}
}