{
  "type": "Feature",
  "properties": {
    "gn:admin1_code":"1.0",
    "gn:asciiname":"Tongdajingcun",
    "gn:country_code":"CN",
    "gn:dem":67,
    "gn:feature_class":"P",
    "gn:feature_code":"PPL",
    "gn:name":"Tongdajingcun",
    "gn:population":0,
    "gn:timezone":"Asia/Shanghai",
    "iso:country":"CN",
    "name:zho_x_preferred":[
        "\u7ae5\u5927\u4e95\u6751"
    ],
    "wof:name":"Tongdajingcun",
    "wof:placetype":"locality"
},
  "geometry": {"coordinates":[116.87442,31.77678],"type":"Point"}
}