{
  "type": "Feature",
  "properties": {
    "gn:admin1_code":"15.0",
    "gn:asciiname":"Xiamawan",
    "gn:country_code":"CN",
    "gn:dem":1982,
    "gn:feature_class":"P",
    "gn:feature_code":"PPL",
    "gn:name":"Xiamawan",
    "gn:population":0,
    "gn:timezone":"Asia/Shanghai",
    "iso:country":"CN",
    "name:zho_x_preferred":[
        "\u4e0b\u9ebb\u6e7e"
    ],
    "wof:name":"Xiamawan",
    "wof:placetype":"locality"
},
  "geometry": {"coordinates":[104.80262,33.55195],"type":"Point"}
}