{
  "type": "Feature",
  "properties": {
    "gn:admin1_code":"14.0",
    "gn:asciiname":"Makelacun",
    "gn:country_code":"CN",
    "gn:dem":4593,
    "gn:feature_class":"P",
    "gn:feature_code":"PPL",
    "gn:name":"Makelacun",
    "gn:population":0,
    "gn:timezone":"Asia/Urumqi",
    "iso:country":"CN",
    "name:zho_x_preferred":[
        "\u739b\u514b\u62c9\u6751"
    ],
    "wof:name":"Makelacun",
    "wof:placetype":"locality"
},
  "geometry": {"coordinates":[91.96485,31.5494],"type":"Point"}
}