{
  "type": "Feature",
  "properties": {
    "gn:admin1_code":"11.0",
    "gn:asciiname":"Xidigang",
    "gn:country_code":"CN",
    "gn:dem":29,
    "gn:feature_class":"P",
    "gn:feature_code":"PPL",
    "gn:name":"Xidigang",
    "gn:population":0,
    "gn:timezone":"Asia/Shanghai",
    "iso:country":"CN",
    "name:zho_x_preferred":[
        "\u897f\u5824\u6e2f"
    ],
    "wof:name":"Xidigang",
    "wof:placetype":"locality"
},
  "geometry": {"coordinates":[112.78755,28.69818],"type":"Point"}
}