{
  "type": "Feature",
  "properties": {
    "gn:admin1_code":"18.0",
    "gn:asciiname":"Houhui",
    "gn:country_code":"CN",
    "gn:dem":697,
    "gn:feature_class":"P",
    "gn:feature_code":"PPL",
    "gn:name":"Houhui",
    "gn:population":0,
    "gn:timezone":"Asia/Shanghai",
    "iso:country":"CN",
    "name:zho_x_preferred":[
        "\u540e\u8f89"
    ],
    "wof:name":"Houhui",
    "wof:placetype":"locality"
},
  "geometry": {"coordinates":[108.04300000000001,25.8794],"type":"Point"}
}