{
  "type": "Feature",
  "properties": {
    "gn:admin1_code":"15.0",
    "gn:asciiname":"Zhangbeizhuang",
    "gn:country_code":"CN",
    "gn:dem":2158,
    "gn:feature_class":"P",
    "gn:feature_code":"PPL",
    "gn:name":"Zhangbeizhuang",
    "gn:population":0,
    "gn:timezone":"Asia/Shanghai",
    "iso:country":"CN",
    "name:zho_x_preferred":[
        "\u5f20\u5317\u5e84"
    ],
    "wof:name":"Zhangbeizhuang",
    "wof:placetype":"locality"
},
  "geometry": {"coordinates":[101.73699999999999,38.3264],"type":"Point"}
}