{
  "type": "Feature",
  "properties": {
    "gn:admin1_code":"32.0",
    "gn:asciiname":"Zhenguosi",
    "gn:country_code":"CN",
    "gn:dem":674,
    "gn:feature_class":"P",
    "gn:feature_code":"PPL",
    "gn:name":"Zhenguosi",
    "gn:population":0,
    "gn:timezone":"Asia/Shanghai",
    "iso:country":"CN",
    "name:zho_x_preferred":[
        "\u9547\u56fd\u5bfa"
    ],
    "wof:name":"Zhenguosi",
    "wof:placetype":"locality"
},
  "geometry": {"coordinates":[105.40000000000001,28.0849],"type":"Point"}
}