{
  "type": "Feature",
  "properties": {
    "gn:admin1_code":"29",
    "gn:asciiname":"Anju",
    "gn:country_code":"CN",
    "gn:dem":1661,
    "gn:feature_class":"P",
    "gn:feature_code":"PPL",
    "gn:name":"Anju",
    "gn:population":0,
    "gn:timezone":"Asia/Shanghai",
    "iso:country":"CN",
    "name:ceb_x_preferred":[
        "Anju"
    ],
    "name:deu_x_preferred":[
        "Anju"
    ],
    "name:fra_x_preferred":[
        "Anju"
    ],
    "name:ind_x_preferred":[
        "Anju"
    ],
    "name:ita_x_preferred":[
        "Anju"
    ],
    "name:jpn_x_preferred":[
        "\u30a2\u30f3\u30b8\u30e5"
    ],
    "name:nld_x_preferred":[
        "Anju"
    ],
    "name:ron_x_preferred":[
        "Anju"
    ],
    "name:sco_x_preferred":[
        "Anju"
    ],
    "name:spa_x_preferred":[
        "Anju"
    ],
    "name:swe_x_preferred":[
        "Anju"
    ],
    "name:vie_x_preferred":[
        "Anju"
    ],
    "name:zho_x_preferred":[
        "\u5b89\u5c45"
    ],
    "wof:name":"Anju",
    "wof:placetype":"locality"
},
  "geometry": {"coordinates":[102.188,24.322],"type":"Point"}
}