{
  "type": "Feature",
  "properties": {
    "gn:admin1_code":"11.0",
    "gn:asciiname":"Shegongtan",
    "gn:country_code":"CN",
    "gn:dem":606,
    "gn:feature_class":"P",
    "gn:feature_code":"PPL",
    "gn:name":"Shegongtan",
    "gn:population":0,
    "gn:timezone":"Asia/Shanghai",
    "iso:country":"CN",
    "name:zho_x_preferred":[
        "\u793e\u516c\u6f6d"
    ],
    "wof:name":"Shegongtan",
    "wof:placetype":"locality"
},
  "geometry": {"coordinates":[110.59275,27.23526],"type":"Point"}
}