{
  "type": "Feature",
  "properties": {
    "gn:admin1_code":"26.0",
    "gn:asciiname":"Shuidigou",
    "gn:country_code":"CN",
    "gn:dem":1089,
    "gn:feature_class":"P",
    "gn:feature_code":"PPL",
    "gn:name":"Shuidigou",
    "gn:population":0,
    "gn:timezone":"Asia/Shanghai",
    "iso:country":"CN",
    "name:zho_x_preferred":[
        "\u6c34\u5730\u6c9f"
    ],
    "wof:name":"Shuidigou",
    "wof:placetype":"locality"
},
  "geometry": {"coordinates":[110.4941,33.39357],"type":"Point"}
}