{
  "type": "Feature",
  "properties": {
    "gn:admin1_code":"8.0",
    "gn:asciiname":"Toudao Weizi",
    "gn:country_code":"CN",
    "gn:dem":367,
    "gn:feature_class":"P",
    "gn:feature_code":"PPL",
    "gn:name":"Toudao Weizi",
    "gn:population":0,
    "gn:timezone":"Asia/Shanghai",
    "iso:country":"CN",
    "name:zho_x_preferred":[
        "\u5934\u9053\u5d34\u5b50"
    ],
    "wof:name":"Toudao Weizi",
    "wof:placetype":"locality"
},
  "geometry": {"coordinates":[130.39534,44.8798],"type":"Point"}
}