{
  "type": "Feature",
  "properties": {
    "gn:admin1_code":"26.0",
    "gn:asciiname":"Shangmacun",
    "gn:country_code":"CN",
    "gn:dem":1161,
    "gn:feature_class":"P",
    "gn:feature_code":"PPL",
    "gn:name":"Shangmacun",
    "gn:population":0,
    "gn:timezone":"Asia/Shanghai",
    "iso:country":"CN",
    "name:zho_x_preferred":[
        "\u4e0a\u9a6c\u6751"
    ],
    "wof:name":"Shangmacun",
    "wof:placetype":"locality"
},
  "geometry": {"coordinates":[109.619,35.5911],"type":"Point"}
}