{
  "type": "Feature",
  "properties": {
    "gn:admin1_code":"26.0",
    "gn:asciiname":"Yishecun",
    "gn:country_code":"CN",
    "gn:dem":837,
    "gn:feature_class":"P",
    "gn:feature_code":"PPL",
    "gn:name":"Yishecun",
    "gn:population":0,
    "gn:timezone":"Asia/Shanghai",
    "iso:country":"CN",
    "name:zho_x_preferred":[
        "\u4e59\u793e\u6751"
    ],
    "wof:name":"Yishecun",
    "wof:placetype":"locality"
},
  "geometry": {"coordinates":[108.81654,34.84544],"type":"Point"}
}