{
  "type": "Feature",
  "properties": {
    "gn:admin1_code":"3",
    "gn:asciiname":"Banzhou",
    "gn:country_code":"CN",
    "gn:dem":63,
    "gn:feature_class":"P",
    "gn:feature_code":"PPL",
    "gn:name":"Banzhou",
    "gn:population":0,
    "gn:timezone":"Asia/Shanghai",
    "iso:country":"CN",
    "name:zho_x_preferred":[
        "\u529e\u6d32"
    ],
    "wof:name":"Banzhou",
    "wof:placetype":"locality"
},
  "geometry": {"coordinates":[114.77166,26.75468],"type":"Point"}
}