{
  "type": "Feature",
  "properties": {
    "gn:admin1_code":"3.0",
    "gn:asciiname":"Shangtan",
    "gn:country_code":"CN",
    "gn:dem":221,
    "gn:feature_class":"P",
    "gn:feature_code":"PPL",
    "gn:name":"Shangtan",
    "gn:population":0,
    "gn:timezone":"Asia/Shanghai",
    "iso:country":"CN",
    "name:und_x_variant":[
        "\u4e0a\u575b"
    ],
    "wof:name":"Shangtan",
    "wof:placetype":"locality"
},
  "geometry": {"coordinates":[116.07980000000001,26.49007000000001],"type":"Point"}
}