{
  "type": "Feature",
  "properties": {
    "gn:admin1_code":"25",
    "gn:asciiname":"Xiaoxinzhuang",
    "gn:country_code":"CN",
    "gn:dem":187,
    "gn:feature_class":"P",
    "gn:feature_code":"PPL",
    "gn:name":"Xiaoxinzhuang",
    "gn:population":0,
    "gn:timezone":"Asia/Shanghai",
    "iso:country":"CN",
    "name:zho_x_preferred":[
        "\u5c0f\u8f9b\u5e84"
    ],
    "wof:name":"Xiaoxinzhuang",
    "wof:placetype":"locality"
},
  "geometry": {"coordinates":[116.99299999999999,36.2321],"type":"Point"}
}