{
  "type": "Feature",
  "properties": {
    "gn:admin1_code":"10.0",
    "gn:asciiname":"Shenwangzhuang",
    "gn:country_code":"CN",
    "gn:dem":12,
    "gn:feature_class":"P",
    "gn:feature_code":"PPL",
    "gn:name":"Shenwangzhuang",
    "gn:population":0,
    "gn:timezone":"Asia/Shanghai",
    "iso:country":"CN",
    "name:zho_x_preferred":[
        "\u6c88\u738b\u5e84"
    ],
    "wof:name":"Shenwangzhuang",
    "wof:placetype":"locality"
},
  "geometry": {"coordinates":[117.66136000000002,39.87408],"type":"Point"}
}