{
  "type": "Feature",
  "properties": {
    "gn:admin1_code":"32.0",
    "gn:asciiname":"Zeyi",
    "gn:country_code":"CN",
    "gn:dem":3515,
    "gn:feature_class":"P",
    "gn:feature_code":"PPL",
    "gn:name":"Zeyi",
    "gn:population":0,
    "gn:timezone":"Asia/Shanghai",
    "iso:country":"CN",
    "name:zho_x_preferred":[
        "\u5219\u8863"
    ],
    "wof:name":"Zeyi",
    "wof:placetype":"locality"
},
  "geometry": {"coordinates":[100.20399999999999,31.7341],"type":"Point"}
}