{
  "type": "Feature",
  "properties": {
    "gn:admin1_code":"14.0",
    "gn:asciiname":"Xiongyao",
    "gn:country_code":"CN",
    "gn:dem":2232,
    "gn:feature_class":"P",
    "gn:feature_code":"PPL",
    "gn:name":"Xiongyao",
    "gn:population":0,
    "gn:timezone":"Asia/Urumqi",
    "iso:country":"CN",
    "name:zho_x_preferred":[
        "\u718a\u8981"
    ],
    "wof:name":"Xiongyao",
    "wof:placetype":"locality"
},
  "geometry": {"coordinates":[98.44517999999999,28.40969],"type":"Point"}
}