{
  "type": "Feature",
  "properties": {
    "iso:country":"CN",
    "name:ara_x_preferred":[
        "\u062c\u064a\u0643\u0648\u0646\u062f\u0648"
    ],
    "name:ben_x_preferred":[
        "\u099c\u09df\u09c7\u0995\u0989\u09a8\u09cd\u09a6\u09c1"
    ],
    "name:ell_x_preferred":[
        "\u03a4\u03b6\u03b9\u03b5\u03ba\u03bf\u03cd\u03bd\u03c4\u03bf"
    ],
    "name:hin_x_preferred":[
        "\u091c\u094d\u092f\u0947\u0915\u0941\u0902\u0926\u094b"
    ],
    "name:hun_x_preferred":[
        "Jyekundo"
    ],
    "name:ind_x_preferred":[
        "Jyekundo"
    ],
    "name:kor_x_preferred":[
        "\uc81c\uad70\ub3c4"
    ],
    "name:pol_x_preferred":[
        "Jyekundo"
    ],
    "name:por_x_preferred":[
        "Gy\u00eagumdo"
    ],
    "name:spa_x_preferred":[
        "Jyekundo"
    ],
    "name:tur_x_preferred":[
        "Jyekundo"
    ],
    "name:ukr_x_preferred":[
        "\u0426\u0437\u0438\u0454\u043a\u0443\u043d\u0434\u043e"
    ],
    "name:urd_x_preferred":[
        "\u062c\u0627\u0626\u06cc\u06a9\u0648\u0646\u0688\u0648"
    ],
    "name:vie_x_preferred":[
        "K\u1ebft C\u1ed5 Tr\u1ea5n"
    ],
    "ne:ADM0CAP":0.0,
    "ne:ADM0NAME":"China",
    "ne:ADM0_A3":"CHN",
    "ne:ADM1NAME":"Gansu",
    "ne:ADMIN1_COD":0,
    "ne:CAPALT":0,
    "ne:CHANGED":1,
    "ne:CHECKME":0,
    "ne:COMPARE":0,
    "ne:DIFFASCII":0,
    "ne:DIFFNOTE":"Changed scale rank.",
    "ne:ELEVATION":0.0,
    "ne:FEATURECLA":"Populated place",
    "ne:GEONAMEID":-1,
    "ne:GEONAMESNO":"No GeoNames match due to small population, not in GeoNames, or poor NEV placement.",
    "ne:GN_POP":0,
    "ne:GTOPO30":0.0,
    "ne:ISO_A2":"CN",
    "ne:LABELRANK":1,
    "ne:LATITUDE":33.016627,
    "ne:LONGITUDE":96.73331,
    "ne:LS_MATCH":0,
    "ne:LS_NAME":"Gyegu",
    "ne:MAX_AREAKM":0.0,
    "ne:MAX_AREAMI":0.0,
    "ne:MAX_BBXMAX":0.0,
    "ne:MAX_BBXMIN":0.0,
    "ne:MAX_BBYMAX":0.0,
    "ne:MAX_BBYMIN":0.0,
    "ne:MAX_NATSCA":0.0,
    "ne:MAX_PERKM":0.0,
    "ne:MAX_PERMI":0.0,
    "ne:MAX_POP10":0,
    "ne:MAX_POP20":0,
    "ne:MAX_POP300":0,
    "ne:MAX_POP310":0,
    "ne:MAX_POP50":0,
    "ne:MEAN_BBXC":0.0,
    "ne:MEAN_BBYC":0.0,
    "ne:MEGACITY":0,
    "ne:MIN_AREAKM":0.0,
    "ne:MIN_AREAMI":0.0,
    "ne:MIN_BBXMAX":0.0,
    "ne:MIN_BBXMIN":0.0,
    "ne:MIN_BBYMAX":0.0,
    "ne:MIN_BBYMIN":0.0,
    "ne:MIN_PERKM":0.0,
    "ne:MIN_PERMI":0.0,
    "ne:NAME":"Jyekundo",
    "ne:NAMEASCII":"Jyekundo",
    "ne:NAMEDIFF":0,
    "ne:NAMEPAR":"Gyegu",
    "ne:NATSCALE":30,
    "ne:POP1950":0,
    "ne:POP1955":0,
    "ne:POP1960":0,
    "ne:POP1965":0,
    "ne:POP1970":0,
    "ne:POP1975":0,
    "ne:POP1980":0,
    "ne:POP1985":0,
    "ne:POP1990":0,
    "ne:POP1995":0,
    "ne:POP2000":0,
    "ne:POP2005":0,
    "ne:POP2010":0,
    "ne:POP2015":0,
    "ne:POP2020":0,
    "ne:POP2025":0,
    "ne:POP2050":0,
    "ne:POP_MAX":23000,
    "ne:POP_MIN":10000,
    "ne:POP_OTHER":0,
    "ne:RANK_MAX":7,
    "ne:RANK_MIN":5,
    "ne:SCALERANK":6,
    "ne:SOV0NAME":"China",
    "ne:SOV_A3":"CHN",
    "ne:UN_FID":0,
    "ne:UN_LAT":0.0,
    "ne:UN_LONG":0.0,
    "ne:WORLDCITY":0,
    "ne:min_zoom":6.0,
    "wof:name":"Jyekundo",
    "wof:placetype":"locality"
},
  "geometry": {"coordinates":[96.73331,33.016627],"type":"Point"}
}