{
  "type": "Feature",
  "properties": {
    "gn:admin1_code":"18",
    "gn:asciiname":"Bailong",
    "gn:country_code":"CN",
    "gn:dem":1845,
    "gn:feature_class":"P",
    "gn:feature_code":"PPL",
    "gn:name":"Bailong",
    "gn:population":0,
    "gn:timezone":"Asia/Shanghai",
    "iso:country":"CN",
    "name:zho_x_preferred":[
        "\u767d\u9f99"
    ],
    "wof:name":"Bailong",
    "wof:placetype":"locality"
},
  "geometry": {"coordinates":[105.148,27.2961],"type":"Point"}
}