{
  "type": "Feature",
  "properties": {
    "gn:admin1_code":"4.0",
    "gn:asciiname":"Taoqiaocun",
    "gn:country_code":"CN",
    "gn:dem":2,
    "gn:feature_class":"P",
    "gn:feature_code":"PPL",
    "gn:name":"Taoqiaocun",
    "gn:population":0,
    "gn:timezone":"Asia/Shanghai",
    "iso:country":"CN",
    "name:und_x_variant":[
        "Taoqiao",
        "\u9676\u6865",
        "Taoqiaocun"
    ],
    "name:zho_x_preferred":[
        "\u9676\u6865\u6751"
    ],
    "wof:name":"Taoqiaocun",
    "wof:placetype":"locality"
},
  "geometry": {"coordinates":[119.39532,33.51349],"type":"Point"}
}