{
  "type": "Feature",
  "properties": {
    "gn:admin1_code":"07",
    "gn:asciiname":"Pantangzhai",
    "gn:country_code":"CN",
    "gn:dem":449,
    "gn:feature_class":"P",
    "gn:feature_code":"PPL",
    "gn:name":"Pantangzhai",
    "gn:population":0,
    "gn:timezone":"Asia/Shanghai",
    "iso:country":"CN",
    "name:zho_x_preferred":[
        "\u6cee\u5858\u5be8"
    ],
    "wof:name":"Pantangzhai",
    "wof:placetype":"locality"
},
  "geometry": {"coordinates":[116.3173,24.87633],"type":"Point"}
}