{
  "type": "Feature",
  "properties": {
    "gn:admin1_code":"02",
    "gn:asciiname":"Dong'ao",
    "gn:country_code":"CN",
    "gn:dem":26,
    "gn:feature_class":"P",
    "gn:feature_code":"PPL",
    "gn:name":"Dong\u2019ao",
    "gn:population":0,
    "gn:timezone":"Asia/Shanghai",
    "iso:country":"CN",
    "name:zho_x_preferred":[
        "Dong\u2019ao"
    ],
    "wof:name":"Dong'ao",
    "wof:placetype":"locality"
},
  "geometry": {"coordinates":[121.49666999999999,28.92028],"type":"Point"}
}