{
  "type": "Feature",
  "properties": {
    "gn:admin1_code":"12.0",
    "gn:asciiname":"Hengyanwan",
    "gn:country_code":"CN",
    "gn:dem":935,
    "gn:feature_class":"P",
    "gn:feature_code":"PPL",
    "gn:name":"Hengyanwan",
    "gn:population":0,
    "gn:timezone":"Asia/Shanghai",
    "iso:country":"CN",
    "name:zho_x_preferred":[
        "\u6a2a\u5ca9\u5846"
    ],
    "wof:name":"Hengyanwan",
    "wof:placetype":"locality"
},
  "geometry": {"coordinates":[109.29226,30.08564],"type":"Point"}
}