{
  "type": "Feature",
  "properties": {
    "gn:admin1_code":"30.0",
    "gn:asciiname":"Dajiangcun",
    "gn:country_code":"CN",
    "gn:dem":17,
    "gn:feature_class":"P",
    "gn:feature_code":"PPL",
    "gn:name":"Dajiangcun",
    "gn:population":0,
    "gn:timezone":"Asia/Shanghai",
    "iso:country":"CN",
    "name:zho_x_preferred":[
        "\u5927\u6c5f\u6751"
    ],
    "wof:name":"Dajiangcun",
    "wof:placetype":"locality"
},
  "geometry": {"coordinates":[113.23435000000001,23.68575],"type":"Point"}
}