{
  "type": "Feature",
  "properties": {
    "gn:admin1_code":"32.0",
    "gn:asciiname":"Shangfangwan",
    "gn:country_code":"CN",
    "gn:dem":318,
    "gn:feature_class":"P",
    "gn:feature_code":"PPL",
    "gn:name":"Shangfangwan",
    "gn:population":0,
    "gn:timezone":"Asia/Shanghai",
    "iso:country":"CN",
    "name:zho_x_preferred":[
        "\u4e0a\u623f\u6e7e"
    ],
    "wof:name":"Shangfangwan",
    "wof:placetype":"locality"
},
  "geometry": {"coordinates":[104.985,28.9879],"type":"Point"}
}