{
  "type": "Feature",
  "properties": {
    "gn:admin1_code":"21.0",
    "gn:asciiname":"Yangpozi",
    "gn:country_code":"CN",
    "gn:dem":1961,
    "gn:feature_class":"P",
    "gn:feature_code":"PPL",
    "gn:name":"Yangpozi",
    "gn:population":0,
    "gn:timezone":"Asia/Shanghai",
    "iso:country":"CN",
    "name:und_x_variant":[
        "\u9633\u5761\u5b50"
    ],
    "name:zho_x_preferred":[
        "\u9633\u5761\u5b50"
    ],
    "wof:name":"Yangpozi",
    "wof:placetype":"locality"
},
  "geometry": {"coordinates":[105.98553,35.64257],"type":"Point"}
}