{
  "type": "Feature",
  "properties": {
    "gn:admin1_code":"4.0",
    "gn:asciiname":"Yuwangcun",
    "gn:country_code":"CN",
    "gn:dem":25,
    "gn:feature_class":"P",
    "gn:feature_code":"PPL",
    "gn:name":"Yuwangcun",
    "gn:population":0,
    "gn:timezone":"Asia/Shanghai",
    "iso:country":"CN",
    "name:und_x_variant":[
        "Yuwang",
        "Yuwangcun"
    ],
    "name:zho_x_preferred":[
        "\u7389\u738b"
    ],
    "name:zho_x_variant":[
        "\u7389\u738b\u6751"
    ],
    "wof:name":"Yuwangcun",
    "wof:placetype":"locality"
},
  "geometry": {"coordinates":[118.76788000000001,32.5307],"type":"Point"}
}