{
  "type": "Feature",
  "properties": {
    "gn:admin1_code":"15.0",
    "gn:asciiname":"Dashanpo",
    "gn:country_code":"CN",
    "gn:dem":1872,
    "gn:feature_class":"P",
    "gn:feature_code":"PPL",
    "gn:name":"Dashanpo",
    "gn:population":0,
    "gn:timezone":"Asia/Shanghai",
    "iso:country":"CN",
    "name:zho_x_preferred":[
        "\u5927\u5c71\u5761"
    ],
    "wof:name":"Dashanpo",
    "wof:placetype":"locality"
},
  "geometry": {"coordinates":[105.367,34.3769],"type":"Point"}
}