{
  "type": "Feature",
  "properties": {
    "gn:admin1_code":"14.0",
    "gn:asciiname":"Ladingxue",
    "gn:country_code":"CN",
    "gn:dem":3273,
    "gn:feature_class":"P",
    "gn:feature_code":"PPL",
    "gn:name":"Ladingxue",
    "gn:population":0,
    "gn:timezone":"Asia/Urumqi",
    "iso:country":"CN",
    "name:bod_x_preferred":[
        "Lad\u00eangxoi"
    ],
    "name:und_x_variant":[
        "Ladingxuecun"
    ],
    "name:zho_x_preferred":[
        "\u62c9\u4e01\u96ea"
    ],
    "name:zho_x_variant":[
        "\u62c9\u4e01\u96ea\u6751"
    ],
    "wof:name":"Ladingxue",
    "wof:placetype":"locality"
},
  "geometry": {"coordinates":[92.84842,28.99216],"type":"Point"}
}