{
  "type": "Feature",
  "properties": {
    "gn:admin1_code":"30",
    "gn:asciiname":"Sijiuwei",
    "gn:country_code":"CN",
    "gn:dem":32,
    "gn:feature_class":"P",
    "gn:feature_code":"PPL",
    "gn:name":"Sijiuwei",
    "gn:population":0,
    "gn:timezone":"Asia/Urumqi",
    "iso:country":"CN",
    "name:und_x_variant":[
        "\u56db\u4e5d\u5729",
        "Sijiuwei"
    ],
    "wof:name":"Sijiuwei",
    "wof:placetype":"locality"
},
  "geometry": {"coordinates":[110.31604,21.43795],"type":"Point"}
}