{
  "type": "Feature",
  "properties": {
    "gn:admin1_code":"32.0",
    "gn:asciiname":"Rimei",
    "gn:country_code":"CN",
    "gn:dem":3943,
    "gn:feature_class":"P",
    "gn:feature_code":"PPL",
    "gn:name":"Rimei",
    "gn:population":0,
    "gn:timezone":"Asia/Shanghai",
    "iso:country":"CN",
    "name:zho_x_preferred":[
        "\u65e5\u7f8e"
    ],
    "wof:name":"Rimei",
    "wof:placetype":"locality"
},
  "geometry": {"coordinates":[98.91679999999999,32.8043],"type":"Point"}
}