{
  "type": "Feature",
  "properties": {
    "gn:admin1_code":"02",
    "gn:asciiname":"Yaoshu'ao",
    "gn:country_code":"CN",
    "gn:dem":59,
    "gn:feature_class":"P",
    "gn:feature_code":"PPL",
    "gn:name":"Yaoshu\u2019ao",
    "gn:population":0,
    "gn:timezone":"Asia/Shanghai",
    "iso:country":"CN",
    "name:und_x_variant":[
        "\u59da\u5885\u5c99"
    ],
    "name:zho_x_preferred":[
        "Yaoshu\u2019ao"
    ],
    "name:zho_x_variant":[
        "\u59da\u5885\u5c99"
    ],
    "wof:name":"Yaoshu'ao",
    "wof:placetype":"locality"
},
  "geometry": {"coordinates":[121.71444,29.87694],"type":"Point"}
}