{
  "type": "Feature",
  "properties": {
    "gn:admin1_code":"21.0",
    "gn:asciiname":"Luyuan",
    "gn:country_code":"CN",
    "gn:dem":2151,
    "gn:feature_class":"P",
    "gn:feature_code":"PPL",
    "gn:name":"L\u00fcyuan",
    "gn:population":0,
    "gn:timezone":"Asia/Shanghai",
    "iso:country":"CN",
    "name:und_x_variant":[
        "L\u00fcyuan"
    ],
    "name:zho_x_preferred":[
        "\u7eff\u586c"
    ],
    "wof:name":"Luyuan",
    "wof:placetype":"locality"
},
  "geometry": {"coordinates":[106.224,35.7325],"type":"Point"}
}