{
  "type": "Feature",
  "properties": {
    "gn:admin1_code":"30.0",
    "gn:asciiname":"Shenshui",
    "gn:country_code":"CN",
    "gn:dem":62,
    "gn:feature_class":"P",
    "gn:feature_code":"PPL",
    "gn:name":"Shenshui",
    "gn:population":0,
    "gn:timezone":"Asia/Urumqi",
    "iso:country":"CN",
    "name:zho_x_preferred":[
        "\u6df1\u6c34"
    ],
    "wof:name":"Shenshui",
    "wof:placetype":"locality"
},
  "geometry": {"coordinates":[110.41848,20.44746],"type":"Point"}
}