{
  "type": "Feature",
  "properties": {
    "gn:admin1_code":"21.0",
    "gn:asciiname":"Weizhen Qibadui",
    "gn:country_code":"CN",
    "gn:dem":1098,
    "gn:feature_class":"P",
    "gn:feature_code":"PPLF",
    "gn:name":"Weizhen Qibadui",
    "gn:population":0,
    "gn:timezone":"Asia/Shanghai",
    "iso:country":"CN",
    "name:zho_x_preferred":[
        "\u5a01\u9547\u4e03\u516b\u961f"
    ],
    "wof:name":"Weizhen Qibadui",
    "wof:placetype":"locality"
},
  "geometry": {"coordinates":[106.51000000000001,38.9611],"type":"Point"}
}