{
  "type": "Feature",
  "properties": {
    "gn:admin1_code":"24.0",
    "gn:asciiname":"Gushangou",
    "gn:country_code":"CN",
    "gn:dem":1399,
    "gn:feature_class":"P",
    "gn:feature_code":"PPL",
    "gn:name":"Gushangou",
    "gn:population":0,
    "gn:timezone":"Asia/Shanghai",
    "iso:country":"CN",
    "name:zho_x_preferred":[
        "\u5b64\u5c71\u6c9f"
    ],
    "wof:name":"Gushangou",
    "wof:placetype":"locality"
},
  "geometry": {"coordinates":[113.50511000000002,35.95312],"type":"Point"}
}