{
  "type": "Feature",
  "properties": {
    "gn:admin1_code":"12.0",
    "gn:asciiname":"Baojiatudi",
    "gn:country_code":"CN",
    "gn:dem":32,
    "gn:feature_class":"P",
    "gn:feature_code":"PPL",
    "gn:name":"Baojiatudi",
    "gn:population":0,
    "gn:timezone":"Asia/Shanghai",
    "iso:country":"CN",
    "name:zho_x_preferred":[
        "\u9c8d\u5bb6\u571f\u5730"
    ],
    "wof:name":"Baojiatudi",
    "wof:placetype":"locality"
},
  "geometry": {"coordinates":[112.9551,30.31523],"type":"Point"}
}