{
  "type": "Feature",
  "properties": {
    "gn:admin1_code":"3.0",
    "gn:asciiname":"Wanglou",
    "gn:country_code":"CN",
    "gn:dem":38,
    "gn:feature_class":"P",
    "gn:feature_code":"PPL",
    "gn:name":"Wanglou",
    "gn:population":0,
    "gn:timezone":"Asia/Shanghai",
    "iso:country":"CN",
    "name:zho_x_preferred":[
        "\u671b\u697c"
    ],
    "wof:name":"Wanglou",
    "wof:placetype":"locality"
},
  "geometry": {"coordinates":[117.26535,28.94397],"type":"Point"}
}