{
  "type": "Feature",
  "properties": {
    "gn:admin1_code":"29.0",
    "gn:asciiname":"Lubu",
    "gn:country_code":"CN",
    "gn:dem":2681,
    "gn:feature_class":"P",
    "gn:feature_code":"PPL",
    "gn:name":"Lubu",
    "gn:population":0,
    "gn:timezone":"Asia/Shanghai",
    "iso:country":"CN",
    "name:ceb_x_preferred":[
        "Lubu"
    ],
    "name:fra_x_preferred":[
        "Lubu"
    ],
    "name:swe_x_preferred":[
        "Lubu"
    ],
    "name:und_x_variant":[
        "\u565c\u5e03"
    ],
    "wof:name":"Lubu",
    "wof:placetype":"locality"
},
  "geometry": {"coordinates":[103.13558,26.7295],"type":"Point"}
}