{
  "type": "Feature",
  "properties": {
    "gn:admin1_code":"26.0",
    "gn:asciiname":"Lintai",
    "gn:country_code":"CN",
    "gn:dem":1331,
    "gn:feature_class":"P",
    "gn:feature_code":"PPL",
    "gn:name":"Lintai",
    "gn:population":0,
    "gn:timezone":"Asia/Shanghai",
    "iso:country":"CN",
    "name:zho_x_preferred":[
        "\u853a\u53f0"
    ],
    "wof:name":"Lintai",
    "wof:placetype":"locality"
},
  "geometry": {"coordinates":[108.10625,36.89927],"type":"Point"}
}