{
  "type": "Feature",
  "properties": {
    "gn:admin1_code":"12.0",
    "gn:asciiname":"Caoziba",
    "gn:country_code":"CN",
    "gn:dem":549,
    "gn:feature_class":"P",
    "gn:feature_code":"PPL",
    "gn:name":"Caoziba",
    "gn:population":0,
    "gn:timezone":"Asia/Shanghai",
    "iso:country":"CN",
    "name:zho_x_preferred":[
        "\u8349\u5b50\u575d"
    ],
    "wof:name":"Caoziba",
    "wof:placetype":"locality"
},
  "geometry": {"coordinates":[109.40488000000001,30.12614],"type":"Point"}
}