{
  "type": "Feature",
  "properties": {
    "gn:admin1_code":"32.0",
    "gn:asciiname":"Muli",
    "gn:country_code":"CN",
    "gn:dem":4298,
    "gn:feature_class":"P",
    "gn:feature_code":"PPL",
    "gn:name":"Muli",
    "gn:population":0,
    "gn:timezone":"Asia/Shanghai",
    "iso:country":"CN",
    "name:ceb_x_preferred":[
        "Muli"
    ],
    "name:deu_x_preferred":[
        "Muli"
    ],
    "name:div_x_preferred":[
        "\u0789\u07aa\u078d\u07a8"
    ],
    "name:fas_x_preferred":[
        "\u0645\u0648\u0644\u06cc"
    ],
    "name:nld_x_preferred":[
        "Muli"
    ],
    "name:swe_x_preferred":[
        "Muli"
    ],
    "wof:name":"Muli",
    "wof:placetype":"locality"
},
  "geometry": {"coordinates":[101.37085,28.6219],"type":"Point"}
}