{
  "type": "Feature",
  "properties": {
    "gn:admin1_code":"32.0",
    "gn:asciiname":"Muli",
    "gn:country_code":"CN",
    "gn:dem":4298,
    "gn:feature_class":"P",
    "gn:feature_code":"PPL",
    "gn:name":"Muli",
    "gn:population":0,
    "gn:timezone":"Asia/Shanghai",
    "iso:country":"CN",
    "wof:name":"Muli",
    "wof:placetype":"locality"
},
  "geometry": {"coordinates":[101.37085,28.6219],"type":"Point"}
}