{
  "type": "Feature",
  "properties": {
    "gn:admin1_code":"2.0",
    "gn:asciiname":"Louxiazhai",
    "gn:country_code":"CN",
    "gn:dem":516,
    "gn:feature_class":"P",
    "gn:feature_code":"PPL",
    "gn:name":"Louxiazhai",
    "gn:population":0,
    "gn:timezone":"Asia/Shanghai",
    "iso:country":"CN",
    "name:zho_x_preferred":[
        "\u697c\u4e0b\u5b85"
    ],
    "wof:name":"Louxiazhai",
    "wof:placetype":"locality"
},
  "geometry": {"coordinates":[120.72881,29.21576],"type":"Point"}
}