{
  "type": "Feature",
  "properties": {
    "gn:admin1_code":"1.0",
    "gn:asciiname":"Sanmenchengcun",
    "gn:country_code":"CN",
    "gn:dem":135,
    "gn:feature_class":"P",
    "gn:feature_code":"PPL",
    "gn:name":"Sanmenchengcun",
    "gn:population":0,
    "gn:timezone":"Asia/Shanghai",
    "iso:country":"CN",
    "name:zho_x_preferred":[
        "\u4e09\u95e8\u5448\u6751"
    ],
    "wof:name":"Sanmenchengcun",
    "wof:placetype":"locality"
},
  "geometry": {"coordinates":[118.27271,29.7005],"type":"Point"}
}