{
  "type": "Feature",
  "properties": {
    "gn:admin1_code":"2.0",
    "gn:asciiname":"Jiaokeng",
    "gn:country_code":"CN",
    "gn:dem":368,
    "gn:feature_class":"P",
    "gn:feature_code":"PPL",
    "gn:name":"Jiaokeng",
    "gn:population":0,
    "gn:timezone":"Asia/Shanghai",
    "iso:country":"CN",
    "name:zho_x_preferred":[
        "\u86df\u5751"
    ],
    "wof:name":"Jiaokeng",
    "wof:placetype":"locality"
},
  "geometry": {"coordinates":[120.21859000000001,28.56934],"type":"Point"}
}