{
  "type": "Feature",
  "properties": {
    "gn:admin1_code":"07",
    "gn:asciiname":"Songlinkeng",
    "gn:country_code":"CN",
    "gn:dem":629,
    "gn:feature_class":"P",
    "gn:feature_code":"PPL",
    "gn:name":"Songlinkeng",
    "gn:population":0,
    "gn:timezone":"Asia/Shanghai",
    "iso:country":"CN",
    "name:zho_x_preferred":[
        "\u677e\u6797\u5751"
    ],
    "wof:name":"Songlinkeng",
    "wof:placetype":"locality"
},
  "geometry": {"coordinates":[117.47771000000002,25.8913],"type":"Point"}
}