{
  "type": "Feature",
  "properties": {
    "gn:admin1_code":"8.0",
    "gn:asciiname":"Baoguocun",
    "gn:country_code":"CN",
    "gn:dem":141,
    "gn:feature_class":"P",
    "gn:feature_code":"PPL",
    "gn:name":"Baoguocun",
    "gn:population":0,
    "gn:timezone":"Asia/Shanghai",
    "iso:country":"CN",
    "name:zho_x_preferred":[
        "\u4fdd\u56fd\u6751"
    ],
    "wof:name":"Baoguocun",
    "wof:placetype":"locality"
},
  "geometry": {"coordinates":[125.75530000000001,45.4359],"type":"Point"}
}