{
  "type": "Feature",
  "properties": {
    "gn:admin1_code":"3.0",
    "gn:asciiname":"Huangkeng",
    "gn:country_code":"CN",
    "gn:dem":453,
    "gn:feature_class":"P",
    "gn:feature_code":"PPL",
    "gn:name":"Huangkeng",
    "gn:population":0,
    "gn:timezone":"Asia/Shanghai",
    "iso:country":"CN",
    "name:und_x_variant":[
        "\u9ec4\u5751"
    ],
    "wof:name":"Huangkeng",
    "wof:placetype":"locality"
},
  "geometry": {"coordinates":[115.31622,28.97531],"type":"Point"}
}