{
  "type": "Feature",
  "properties": {
    "gn:admin1_code":"10",
    "gn:asciiname":"Yingtufang",
    "gn:country_code":"CN",
    "gn:dem":1527,
    "gn:feature_class":"P",
    "gn:feature_code":"PPL",
    "gn:name":"Yingtufang",
    "gn:population":0,
    "gn:timezone":"Asia/Shanghai",
    "iso:country":"CN",
    "name:zho_x_preferred":[
        "\u82f1\u56fe\u623f"
    ],
    "wof:name":"Yingtufang",
    "wof:placetype":"locality"
},
  "geometry": {"coordinates":[114.32680000000001,41.90474],"type":"Point"}
}