{
  "type": "Feature",
  "properties": {
    "gn:admin1_code":"15.0",
    "gn:asciiname":"Xiaochen",
    "gn:country_code":"CN",
    "gn:dem":1586,
    "gn:feature_class":"P",
    "gn:feature_code":"PPL",
    "gn:name":"Xiaochen",
    "gn:population":0,
    "gn:timezone":"Asia/Shanghai",
    "iso:country":"CN",
    "name:zho_x_preferred":[
        "\u5c0f\u9648"
    ],
    "wof:name":"Xiaochen",
    "wof:placetype":"locality"
},
  "geometry": {"coordinates":[106.73,35.5655],"type":"Point"}
}