{
  "type": "Feature",
  "properties": {
    "gn:admin1_code":"11.0",
    "gn:asciiname":"Yaoshengtian",
    "gn:country_code":"CN",
    "gn:dem":207,
    "gn:feature_class":"P",
    "gn:feature_code":"PPL",
    "gn:name":"Yaoshengtian",
    "gn:population":0,
    "gn:timezone":"Asia/Shanghai",
    "iso:country":"CN",
    "name:zho_x_preferred":[
        "\u8170\u80dc\u7530"
    ],
    "wof:name":"Yaoshengtian",
    "wof:placetype":"locality"
},
  "geometry": {"coordinates":[109.82398999999999,27.29059],"type":"Point"}
}