{
  "type": "Feature",
  "properties": {
    "gn:admin1_code":"26",
    "gn:asciiname":"Guanyuan",
    "gn:cc2":"CN",
    "gn:country_code":"CN",
    "gn:dem":733,
    "gn:feature_class":"P",
    "gn:feature_code":"PPL",
    "gn:name":"Guanyuan",
    "gn:population":0,
    "gn:timezone":"Asia/Shanghai",
    "iso:country":"CN",
    "name:und_x_variant":[
        "Kuan-y\u00fcan",
        "Guanyuan"
    ],
    "wof:name":"Guanyuan",
    "wof:placetype":"locality"
},
  "geometry": {"coordinates":[108.71444,32.25056],"type":"Point"}
}