{
  "type": "Feature",
  "properties": {
    "gn:admin1_code":"32.0",
    "gn:asciiname":"Qingtianbu",
    "gn:country_code":"CN",
    "gn:dem":1287,
    "gn:feature_class":"P",
    "gn:feature_code":"PPL",
    "gn:name":"Qingtianbu",
    "gn:population":0,
    "gn:timezone":"Asia/Shanghai",
    "iso:country":"CN",
    "name:zho_x_preferred":[
        "\u9752\u5929\u5821"
    ],
    "wof:name":"Qingtianbu",
    "wof:placetype":"locality"
},
  "geometry": {"coordinates":[105.54071999999999,27.94506],"type":"Point"}
}