{
  "type": "Feature",
  "properties": {
    "gn:admin1_code":"24.0",
    "gn:asciiname":"Zhangjiazhuocun",
    "gn:country_code":"CN",
    "gn:dem":385,
    "gn:feature_class":"P",
    "gn:feature_code":"PPL",
    "gn:name":"Zhangjiazhuocun",
    "gn:population":0,
    "gn:timezone":"Asia/Shanghai",
    "iso:country":"CN",
    "name:zho_x_preferred":[
        "\u5f20\u5bb6\u5353\u6751"
    ],
    "wof:name":"Zhangjiazhuocun",
    "wof:placetype":"locality"
},
  "geometry": {"coordinates":[110.49375000000001,35.00354],"type":"Point"}
}