{
  "type": "Feature",
  "properties": {
    "gn:admin1_code":"18",
    "gn:asciiname":"Changtutou",
    "gn:country_code":"CN",
    "gn:dem":599,
    "gn:feature_class":"P",
    "gn:feature_code":"PPL",
    "gn:name":"Changtutou",
    "gn:population":0,
    "gn:timezone":"Asia/Shanghai",
    "iso:country":"CN",
    "name:zho_x_preferred":[
        "\u957f\u571f\u5934"
    ],
    "wof:name":"Changtutou",
    "wof:placetype":"locality"
},
  "geometry": {"coordinates":[106.087,28.305],"type":"Point"}
}