{
  "type": "Feature",
  "properties": {
    "gn:admin1_code":"25",
    "gn:asciiname":"Dashigou",
    "gn:country_code":"CN",
    "gn:dem":263,
    "gn:feature_class":"P",
    "gn:feature_code":"PPL",
    "gn:name":"Dashigou",
    "gn:population":0,
    "gn:timezone":"Asia/Shanghai",
    "iso:country":"CN",
    "name:zho_x_preferred":[
        "\u5927\u77f3\u6c9f"
    ],
    "wof:name":"Dashigou",
    "wof:placetype":"locality"
},
  "geometry": {"coordinates":[118.444,36.0761],"type":"Point"}
}