{
  "type": "Feature",
  "properties": {
    "gn:admin1_code":"6.0",
    "gn:asciiname":"Jieqingda",
    "gn:country_code":"CN",
    "gn:dem":4311,
    "gn:feature_class":"P",
    "gn:feature_code":"PPL",
    "gn:name":"Jieqingda",
    "gn:population":0,
    "gn:timezone":"Asia/Urumqi",
    "iso:country":"CN",
    "name:zho_x_preferred":[
        "\u89e3\u9752\u8fbe"
    ],
    "wof:name":"Jieqingda",
    "wof:placetype":"locality"
},
  "geometry": {"coordinates":[95.47705000000001,32.46059],"type":"Point"}
}