{
  "type": "Feature",
  "properties": {
    "gn:admin1_code":"9",
    "gn:asciiname":"Beidaizhuang",
    "gn:country_code":"CN",
    "gn:dem":72,
    "gn:feature_class":"P",
    "gn:feature_code":"PPL",
    "gn:name":"Beidaizhuang",
    "gn:population":0,
    "gn:timezone":"Asia/Shanghai",
    "iso:country":"CN",
    "name:zho_x_preferred":[
        "\u5317\u4ee3\u5e84"
    ],
    "wof:name":"Beidaizhuang",
    "wof:placetype":"locality"
},
  "geometry": {"coordinates":[114.961,34.8815],"type":"Point"}
}