{
  "type": "Feature",
  "properties": {
    "gn:admin1_code":"32.0",
    "gn:asciiname":"Pengnamusa",
    "gn:country_code":"CN",
    "gn:dem":2764,
    "gn:feature_class":"P",
    "gn:feature_code":"PPL",
    "gn:name":"Pengnamusa",
    "gn:population":0,
    "gn:timezone":"Asia/Shanghai",
    "iso:country":"CN",
    "name:zho_x_preferred":[
        "\u84ec\u7eb3\u6728\u8428"
    ],
    "wof:name":"Pengnamusa",
    "wof:placetype":"locality"
},
  "geometry": {"coordinates":[102.72175,28.06958],"type":"Point"}
}