{
  "type": "Feature",
  "properties": {
    "gn:admin1_code":"11.0",
    "gn:asciiname":"Fuqiaoping",
    "gn:country_code":"CN",
    "gn:dem":358,
    "gn:feature_class":"P",
    "gn:feature_code":"PPL",
    "gn:name":"Fuqiaoping",
    "gn:population":0,
    "gn:timezone":"Asia/Shanghai",
    "iso:country":"CN",
    "name:zho_x_preferred":[
        "\u6d6e\u6865\u576a"
    ],
    "wof:name":"Fuqiaoping",
    "wof:placetype":"locality"
},
  "geometry": {"coordinates":[109.35008000000001,28.54518],"type":"Point"}
}