{
  "type": "Feature",
  "properties": {
    "gn:admin1_code":"15.0",
    "gn:asciiname":"Goulebaliang",
    "gn:country_code":"CN",
    "gn:dem":1837,
    "gn:feature_class":"P",
    "gn:feature_code":"PPL",
    "gn:name":"Goulebaliang",
    "gn:population":0,
    "gn:timezone":"Asia/Shanghai",
    "iso:country":"CN",
    "name:zho_x_preferred":[
        "\u72d7\u808b\u5df4\u6881"
    ],
    "wof:name":"Goulebaliang",
    "wof:placetype":"locality"
},
  "geometry": {"coordinates":[104.96899999999999,35.9933],"type":"Point"}
}