{
  "type": "Feature",
  "properties": {
    "gn:admin1_code":"29.0",
    "gn:asciiname":"Junliang",
    "gn:country_code":"CN",
    "gn:dem":2456,
    "gn:feature_class":"P",
    "gn:feature_code":"PPL",
    "gn:name":"Junliang",
    "gn:population":0,
    "gn:timezone":"Asia/Shanghai",
    "iso:country":"CN",
    "name:zho_x_preferred":[
        "\u5747\u826f"
    ],
    "wof:name":"Junliang",
    "wof:placetype":"locality"
},
  "geometry": {"coordinates":[100.131,26.9039],"type":"Point"}
}