{
  "type": "Feature",
  "properties": {
    "gn:admin1_code":"19.0",
    "gn:asciiname":"Renjia Zhangzi",
    "gn:country_code":"CN",
    "gn:dem":378,
    "gn:feature_class":"P",
    "gn:feature_code":"PPL",
    "gn:name":"Renjia Zhangzi",
    "gn:population":0,
    "gn:timezone":"Asia/Shanghai",
    "iso:country":"CN",
    "name:zho_x_preferred":[
        "\u4efb\u5bb6\u6756\u5b50"
    ],
    "wof:name":"Renjia Zhangzi",
    "wof:placetype":"locality"
},
  "geometry": {"coordinates":[119.75516,41.4021],"type":"Point"}
}