{
  "type": "Feature",
  "properties": {
    "gn:admin1_code":"2",
    "gn:asciiname":"Zhangcun",
    "gn:country_code":"CN",
    "gn:dem":209,
    "gn:feature_class":"P",
    "gn:feature_code":"PPL",
    "gn:name":"Zhangcun",
    "gn:population":0,
    "gn:timezone":"Asia/Shanghai",
    "iso:country":"CN",
    "name:und_x_variant":[
        "Chang-ts\u2019un",
        "Zhangcun"
    ],
    "name:zho_x_preferred":[
        "\u6a1f\u6751"
    ],
    "wof:name":"Zhangcun",
    "wof:placetype":"locality"
},
  "geometry": {"coordinates":[118.41388000000001,29.47028],"type":"Point"}
}