{
  "type": "Feature",
  "properties": {
    "gn:admin1_code":"3.0",
    "gn:asciiname":"Yangmeitan",
    "gn:country_code":"CN",
    "gn:dem":134,
    "gn:feature_class":"P",
    "gn:feature_code":"PPL",
    "gn:name":"Yangmeitan",
    "gn:population":0,
    "gn:timezone":"Asia/Shanghai",
    "iso:country":"CN",
    "name:und_x_variant":[
        "\u6768\u6885\u5766"
    ],
    "wof:name":"Yangmeitan",
    "wof:placetype":"locality"
},
  "geometry": {"coordinates":[117.41858999999999,29.12565],"type":"Point"}
}