{
  "type": "Feature",
  "properties": {
    "gn:admin1_code":"14.0",
    "gn:asciiname":"Pudeze Niuchang",
    "gn:country_code":"CN",
    "gn:dem":4031,
    "gn:feature_class":"P",
    "gn:feature_code":"PPLF",
    "gn:name":"Pudeze Niuchang",
    "gn:population":0,
    "gn:timezone":"Asia/Urumqi",
    "iso:country":"CN",
    "name:zho_x_preferred":[
        "\u666e\u5fb7\u62e9\u725b\u573a"
    ],
    "wof:name":"Pudeze Niuchang",
    "wof:placetype":"locality"
},
  "geometry": {"coordinates":[98.62881,30.83666],"type":"Point"}
}