{
  "type": "Feature",
  "properties": {
    "gn:admin1_code":"18",
    "gn:asciiname":"Dashangjiao",
    "gn:country_code":"CN",
    "gn:dem":2058,
    "gn:feature_class":"P",
    "gn:feature_code":"PPL",
    "gn:name":"Dashangjiao",
    "gn:population":0,
    "gn:timezone":"Asia/Shanghai",
    "iso:country":"CN",
    "name:zho_x_preferred":[
        "\u5927\u4e0a\u811a"
    ],
    "wof:name":"Dashangjiao",
    "wof:placetype":"locality"
},
  "geometry": {"coordinates":[104.80500000000001,26.5432],"type":"Point"}
}