{
  "type": "Feature",
  "properties": {
    "gn:admin1_code":"5.0",
    "gn:asciiname":"Liucai",
    "gn:country_code":"CN",
    "gn:dem":280,
    "gn:feature_class":"P",
    "gn:feature_code":"PPL",
    "gn:name":"Liucai",
    "gn:population":0,
    "gn:timezone":"Asia/Shanghai",
    "iso:country":"CN",
    "name:und_x_variant":[
        "\u67f3\u83dc"
    ],
    "wof:name":"Liucai",
    "wof:placetype":"locality"
},
  "geometry": {"coordinates":[129.53521999999998,43.13639000000001],"type":"Point"}
}