{
  "type": "Feature",
  "properties": {
    "gn:admin1_code":"29.0",
    "gn:asciiname":"Landizhai",
    "gn:country_code":"CN",
    "gn:dem":1750,
    "gn:feature_class":"P",
    "gn:feature_code":"PPL",
    "gn:name":"Landizhai",
    "gn:population":0,
    "gn:timezone":"Asia/Shanghai",
    "iso:country":"CN",
    "name:zho_x_preferred":[
        "\u70c2\u5730\u5be8"
    ],
    "wof:name":"Landizhai",
    "wof:placetype":"locality"
},
  "geometry": {"coordinates":[99.3009,24.1681],"type":"Point"}
}