{
  "type": "Feature",
  "properties": {
    "gn:admin1_code":"9.0",
    "gn:asciiname":"Wanghuamin",
    "gn:country_code":"CN",
    "gn:dem":94,
    "gn:feature_class":"P",
    "gn:feature_code":"PPL",
    "gn:name":"Wanghuamin",
    "gn:population":0,
    "gn:timezone":"Asia/Shanghai",
    "iso:country":"CN",
    "name:und_x_variant":[
        "\u738b\u5316\u6c11"
    ],
    "name:zho_x_preferred":[
        "\u738b\u5316\u6c11"
    ],
    "wof:name":"Wanghuamin",
    "wof:placetype":"locality"
},
  "geometry": {"coordinates":[113.91285000000001,33.01786],"type":"Point"}
}