{
  "type": "Feature",
  "properties": {
    "gn:admin1_code":"3.0",
    "gn:asciiname":"Lungang",
    "gn:country_code":"CN",
    "gn:dem":244,
    "gn:feature_class":"P",
    "gn:feature_code":"PPL",
    "gn:name":"Lungang",
    "gn:population":0,
    "gn:timezone":"Asia/Shanghai",
    "iso:country":"CN",
    "name:und_x_variant":[
        "\u4ed1\u5c97"
    ],
    "wof:name":"Lungang",
    "wof:placetype":"locality"
},
  "geometry": {"coordinates":[115.32937,29.54076],"type":"Point"}
}