{
  "type": "Feature",
  "properties": {
    "gn:admin1_code":"29",
    "gn:asciiname":"Daqing",
    "gn:country_code":"CN",
    "gn:dem":1823,
    "gn:feature_class":"P",
    "gn:feature_code":"PPL",
    "gn:name":"Daqing",
    "gn:population":0,
    "gn:timezone":"Asia/Shanghai",
    "iso:country":"CN",
    "name:zho_x_preferred":[
        "\u5927\u7b90"
    ],
    "wof:name":"Daqing",
    "wof:placetype":"locality"
},
  "geometry": {"coordinates":[102.872,24.1719],"type":"Point"}
}