{
  "type": "Feature",
  "properties": {
    "gn:admin1_code":"18",
    "gn:asciiname":"Bainiu",
    "gn:country_code":"CN",
    "gn:dem":1203,
    "gn:feature_class":"P",
    "gn:feature_code":"PPL",
    "gn:name":"Bainiu",
    "gn:population":0,
    "gn:timezone":"Asia/Shanghai",
    "iso:country":"CN",
    "name:zho_x_preferred":[
        "\u6446\u725b"
    ],
    "wof:name":"Bainiu",
    "wof:placetype":"locality"
},
  "geometry": {"coordinates":[106.602,26.3715],"type":"Point"}
}