{
  "type": "Feature",
  "properties": {
    "gn:admin1_code":"31",
    "gn:asciiname":"Gongtangshang",
    "gn:country_code":"CN",
    "gn:dem":41,
    "gn:feature_class":"P",
    "gn:feature_code":"PPL",
    "gn:name":"Gongtangshang",
    "gn:population":0,
    "gn:timezone":"Asia/Shanghai",
    "iso:country":"CN",
    "name:und_x_variant":[
        "\u516c\u5802\u4e0a"
    ],
    "wof:name":"Gongtangshang",
    "wof:placetype":"locality"
},
  "geometry": {"coordinates":[109.16852,19.78935],"type":"Point"}
}