{
  "type": "Feature",
  "properties": {
    "gn:admin1_code":"5.0",
    "gn:asciiname":"Qianjintun",
    "gn:country_code":"CN",
    "gn:dem":444,
    "gn:feature_class":"P",
    "gn:feature_code":"PPL",
    "gn:name":"Qianjintun",
    "gn:population":0,
    "gn:timezone":"Asia/Shanghai",
    "iso:country":"CN",
    "name:zho_x_preferred":[
        "\u524d\u8fdb\u5c6f"
    ],
    "wof:name":"Qianjintun",
    "wof:placetype":"locality"
},
  "geometry": {"coordinates":[126.26939,43.31206],"type":"Point"}
}