{
  "type": "Feature",
  "properties": {
    "gn:admin1_code":"29.0",
    "gn:asciiname":"Tiankou",
    "gn:country_code":"CN",
    "gn:dem":1314,
    "gn:feature_class":"P",
    "gn:feature_code":"PPL",
    "gn:name":"Tiankou",
    "gn:population":0,
    "gn:timezone":"Asia/Shanghai",
    "iso:country":"CN",
    "name:zho_x_preferred":[
        "\u7530\u53e3"
    ],
    "wof:name":"Tiankou",
    "wof:placetype":"locality"
},
  "geometry": {"coordinates":[100.188,24.9849],"type":"Point"}
}