{
  "type": "Feature",
  "properties": {
    "gn:admin1_code":"3.0",
    "gn:asciiname":"Sansuncun",
    "gn:country_code":"CN",
    "gn:dem":52,
    "gn:feature_class":"P",
    "gn:feature_code":"PPL",
    "gn:name":"Sansuncun",
    "gn:population":0,
    "gn:timezone":"Asia/Shanghai",
    "iso:country":"CN",
    "name:und_x_variant":[
        "\u4e09\u5b59\u6751"
    ],
    "wof:name":"Sansuncun",
    "wof:placetype":"locality"
},
  "geometry": {"coordinates":[116.84529000000001,28.51462],"type":"Point"}
}