{
  "type": "Feature",
  "properties": {
    "gn:admin1_code":"29.0",
    "gn:asciiname":"Mangpan",
    "gn:country_code":"CN",
    "gn:dem":1087,
    "gn:feature_class":"P",
    "gn:feature_code":"PPL",
    "gn:name":"Mangpan",
    "gn:population":0,
    "gn:timezone":"Asia/Shanghai",
    "iso:country":"CN",
    "name:zho_x_preferred":[
        "\u8292\u5224"
    ],
    "wof:name":"Mangpan",
    "wof:placetype":"locality"
},
  "geometry": {"coordinates":[100.39100000000001,23.3453],"type":"Point"}
}