{
  "type": "Feature",
  "properties": {
    "gn:admin1_code":"24.0",
    "gn:asciiname":"Wangcunpucun",
    "gn:country_code":"CN",
    "gn:dem":1002,
    "gn:feature_class":"P",
    "gn:feature_code":"PPL",
    "gn:name":"Wangcunpucun",
    "gn:population":0,
    "gn:timezone":"Asia/Shanghai",
    "iso:country":"CN",
    "name:zho_x_preferred":[
        "\u738b\u6751\u94fa\u6751"
    ],
    "wof:name":"Wangcunpucun",
    "wof:placetype":"locality"
},
  "geometry": {"coordinates":[114.04541999999999,39.242],"type":"Point"}
}