{
  "type": "Feature",
  "properties": {
    "gn:admin1_code":"12",
    "gn:asciiname":"Wanggang",
    "gn:country_code":"CN",
    "gn:dem":58,
    "gn:feature_class":"P",
    "gn:feature_code":"PPLA4",
    "gn:name":"Wanggang",
    "gn:population":0,
    "gn:timezone":"Asia/Shanghai",
    "iso:country":"CN",
    "name:und_x_variant":[
        "Wang-kang",
        "Wang-chia-kang",
        "Wanggang",
        "\u6c6a\u5c97",
        "Wanggang Zhen",
        "\u6c6a\u5c97\u9547"
    ],
    "wof:name":"Wanggang",
    "wof:placetype":"locality"
},
  "geometry": {"coordinates":[115.17294,30.62278],"type":"Point"}
}