{
  "type": "Feature",
  "properties": {
    "gn:admin1_code":"7",
    "gn:asciiname":"Wenzhuang",
    "gn:country_code":"CN",
    "gn:dem":524,
    "gn:feature_class":"P",
    "gn:feature_code":"PPL",
    "gn:name":"Wenzhuang",
    "gn:population":0,
    "gn:timezone":"Asia/Shanghai",
    "iso:country":"CN",
    "name:zho_x_preferred":[
        "\u6e29\u5e84"
    ],
    "wof:name":"Wenzhuang",
    "wof:placetype":"locality"
},
  "geometry": {"coordinates":[117.11618,24.79037000000001],"type":"Point"}
}