{
  "type": "Feature",
  "properties": {
    "gn:admin1_code":"30.0",
    "gn:asciiname":"Toujinshi",
    "gn:country_code":"CN",
    "gn:dem":398,
    "gn:feature_class":"P",
    "gn:feature_code":"PPL",
    "gn:name":"Toujinshi",
    "gn:population":0,
    "gn:timezone":"Asia/Shanghai",
    "iso:country":"CN",
    "name:zho_x_preferred":[
        "Toujinshi"
    ],
    "name:zho_x_variant":[
        "\u5934\u91d1\u77f3"
    ],
    "wof:name":"Toujinshi",
    "wof:placetype":"locality"
},
  "geometry": {"coordinates":[113.26167,25.32833],"type":"Point"}
}