{
  "type": "Feature",
  "properties": {
    "gn:admin1_code":"11",
    "gn:asciiname":"Furong",
    "gn:country_code":"CN",
    "gn:dem":389,
    "gn:feature_class":"P",
    "gn:feature_code":"PPL",
    "gn:name":"Furong",
    "gn:population":0,
    "gn:timezone":"Asia/Shanghai",
    "iso:country":"CN",
    "name:ceb_x_preferred":[
        "Furong"
    ],
    "name:deu_x_preferred":[
        "Furong"
    ],
    "name:swe_x_preferred":[
        "Furong"
    ],
    "wof:name":"Furong",
    "wof:placetype":"locality"
},
  "geometry": {"coordinates":[109.71722,26.24],"type":"Point"}
}