{
  "type": "Feature",
  "properties": {
    "gn:admin1_code":"15.0",
    "gn:asciiname":"Washigou",
    "gn:country_code":"CN",
    "gn:dem":1095,
    "gn:feature_class":"P",
    "gn:feature_code":"PPL",
    "gn:name":"Washigou",
    "gn:population":0,
    "gn:timezone":"Asia/Shanghai",
    "iso:country":"CN",
    "name:und_x_variant":[
        "\u74e6\u77f3\u6c9f"
    ],
    "wof:name":"Washigou",
    "wof:placetype":"locality"
},
  "geometry": {"coordinates":[105.81016,33.52362],"type":"Point"}
}