{
  "type": "Feature",
  "properties": {
    "gn:admin1_code":"24.0",
    "gn:asciiname":"Shibaping",
    "gn:country_code":"CN",
    "gn:dem":826,
    "gn:feature_class":"P",
    "gn:feature_code":"PPL",
    "gn:name":"Shibaping",
    "gn:population":0,
    "gn:timezone":"Asia/Shanghai",
    "iso:country":"CN",
    "name:und_x_variant":[
        "\u5341\u516b\u576a"
    ],
    "name:zho_x_preferred":[
        "\u5341\u516b\u576a"
    ],
    "wof:name":"Shibaping",
    "wof:placetype":"locality"
},
  "geometry": {"coordinates":[111.40073,35.26257000000001],"type":"Point"}
}