{
  "type": "Feature",
  "properties": {
    "gn:admin1_code":"16.0",
    "gn:asciiname":"Posang",
    "gn:country_code":"CN",
    "gn:dem":1101,
    "gn:feature_class":"P",
    "gn:feature_code":"PPL",
    "gn:name":"Posang",
    "gn:population":0,
    "gn:timezone":"Asia/Shanghai",
    "iso:country":"CN",
    "name:zho_x_preferred":[
        "\u5761\u6851"
    ],
    "wof:name":"Posang",
    "wof:placetype":"locality"
},
  "geometry": {"coordinates":[105.649,23.3213],"type":"Point"}
}