{
  "type": "Feature",
  "properties": {
    "gn:admin1_code":"29.0",
    "gn:asciiname":"Caodi",
    "gn:country_code":"CN",
    "gn:dem":1748,
    "gn:feature_class":"P",
    "gn:feature_code":"PPL",
    "gn:name":"Caodi",
    "gn:population":0,
    "gn:timezone":"Asia/Shanghai",
    "iso:country":"CN",
    "name:zho_x_preferred":[
        "\u66f9\u5730"
    ],
    "wof:name":"Caodi",
    "wof:placetype":"locality"
},
  "geometry": {"coordinates":[103.23999999999999,27.2499],"type":"Point"}
}