{
  "type": "Feature",
  "properties": {
    "gn:admin1_code":"3.0",
    "gn:asciiname":"Xinwan",
    "gn:country_code":"CN",
    "gn:dem":170,
    "gn:feature_class":"P",
    "gn:feature_code":"PPLA4",
    "gn:name":"Xinwan",
    "gn:population":0,
    "gn:timezone":"Asia/Shanghai",
    "iso:country":"CN",
    "name:und_x_variant":[
        "\u65b0\u6e7e",
        "Xinwan Xiang",
        "\u65b0\u6e7e\u4e61"
    ],
    "wof:name":"Xinwan",
    "wof:placetype":"locality"
},
  "geometry": {"coordinates":[114.45353,29.19331],"type":"Point"}
}