{
  "type": "Feature",
  "properties": {
    "gn:admin1_code":"12.0",
    "gn:asciiname":"Shangbaotashan",
    "gn:country_code":"CN",
    "gn:dem":773,
    "gn:feature_class":"P",
    "gn:feature_code":"PPL",
    "gn:name":"Shangbaotashan",
    "gn:population":0,
    "gn:timezone":"Asia/Shanghai",
    "iso:country":"CN",
    "name:zho_x_preferred":[
        "\u4e0a\u5b9d\u5854\u5c71"
    ],
    "wof:name":"Shangbaotashan",
    "wof:placetype":"locality"
},
  "geometry": {"coordinates":[110.91781,30.34634],"type":"Point"}
}