{
  "type": "Feature",
  "properties": {
    "gn:admin1_code":"1.0",
    "gn:asciiname":"Nanqincun",
    "gn:country_code":"CN",
    "gn:dem":27,
    "gn:feature_class":"P",
    "gn:feature_code":"PPL",
    "gn:name":"Nanqincun",
    "gn:population":0,
    "gn:timezone":"Asia/Shanghai",
    "iso:country":"CN",
    "name:zho_x_preferred":[
        "\u5357\u82b9\u6751"
    ],
    "wof:name":"Nanqincun",
    "wof:placetype":"locality"
},
  "geometry": {"coordinates":[116.54823,32.87834],"type":"Point"}
}