{
  "type": "Feature",
  "properties": {
    "gn:admin1_code":"8.0",
    "gn:asciiname":"Wangzhaojin",
    "gn:country_code":"CN",
    "gn:dem":188,
    "gn:feature_class":"P",
    "gn:feature_code":"PPL",
    "gn:name":"Wangzhaojin",
    "gn:population":0,
    "gn:timezone":"Asia/Shanghai",
    "iso:country":"CN",
    "name:zho_x_preferred":[
        "\u738b\u5146\u91d1"
    ],
    "wof:name":"Wangzhaojin",
    "wof:placetype":"locality"
},
  "geometry": {"coordinates":[125.48560000000001,45.86397],"type":"Point"}
}