{
  "type": "Feature",
  "properties": {
    "gn:admin1_code":"30.0",
    "gn:asciiname":"Yutiankeng",
    "gn:country_code":"CN",
    "gn:dem":187,
    "gn:feature_class":"P",
    "gn:feature_code":"PPL",
    "gn:name":"Yutiankeng",
    "gn:population":0,
    "gn:timezone":"Asia/Shanghai",
    "iso:country":"CN",
    "name:zho_x_preferred":[
        "\u9c7c\u7530\u5751"
    ],
    "wof:name":"Yutiankeng",
    "wof:placetype":"locality"
},
  "geometry": {"coordinates":[115.19597,23.30857],"type":"Point"}
}