{
  "type": "Feature",
  "properties": {
    "gn:admin1_code":"14.0",
    "gn:asciiname":"Masi Songduocun",
    "gn:country_code":"CN",
    "gn:dem":4386,
    "gn:feature_class":"P",
    "gn:feature_code":"PPL",
    "gn:name":"Masi Songduocun",
    "gn:population":0,
    "gn:timezone":"Asia/Urumqi",
    "iso:country":"CN",
    "name:zho_x_preferred":[
        "\u739b\u65af\u677e\u591a\u6751"
    ],
    "wof:name":"Masi Songduocun",
    "wof:placetype":"locality"
},
  "geometry": {"coordinates":[93.70457,32.11193],"type":"Point"}
}