{
  "type": "Feature",
  "properties": {
    "gn:admin1_code":"20.0",
    "gn:asciiname":"Shangwu Ergen",
    "gn:country_code":"CN",
    "gn:dem":650,
    "gn:feature_class":"P",
    "gn:feature_code":"PPL",
    "gn:name":"Shangwu Ergen",
    "gn:population":0,
    "gn:timezone":"Asia/Shanghai",
    "iso:country":"CN",
    "name:zho_x_preferred":[
        "\u4e0a\u4e4c\u5c14\u6839"
    ],
    "wof:name":"Shangwu Ergen",
    "wof:placetype":"locality"
},
  "geometry": {"coordinates":[120.54778,50.48852],"type":"Point"}
}