{
  "type": "Feature",
  "properties": {
    "gn:admin1_code":"3.0",
    "gn:asciiname":"Donggang",
    "gn:country_code":"CN",
    "gn:dem":71,
    "gn:feature_class":"P",
    "gn:feature_code":"PPL",
    "gn:name":"Donggang",
    "gn:population":0,
    "gn:timezone":"Asia/Shanghai",
    "iso:country":"CN",
    "name:ceb_x_preferred":[
        "Donggang"
    ],
    "name:deu_x_preferred":[
        "Donggang"
    ],
    "name:fra_x_preferred":[
        "Donggang"
    ],
    "name:nor_x_preferred":[
        "Donggang"
    ],
    "name:swe_x_preferred":[
        "Donggang"
    ],
    "name:und_x_variant":[
        "\u4e1c\u6e2f"
    ],
    "wof:name":"Donggang",
    "wof:placetype":"locality"
},
  "geometry": {"coordinates":[115.50581,29.3357],"type":"Point"}
}