{
  "type": "Feature",
  "properties": {
    "gn:admin1_code":"11.0",
    "gn:asciiname":"Wujiawan",
    "gn:country_code":"CN",
    "gn:dem":186,
    "gn:feature_class":"P",
    "gn:feature_code":"PPL",
    "gn:name":"Wujiawan",
    "gn:population":0,
    "gn:timezone":"Asia/Shanghai",
    "iso:country":"CN",
    "name:zho_x_preferred":[
        "\u5434\u5bb6\u6e7e"
    ],
    "wof:name":"Wujiawan",
    "wof:placetype":"locality"
},
  "geometry": {"coordinates":[112.06103,28.11886],"type":"Point"}
}