{
  "type": "Feature",
  "properties": {
    "gn:admin1_code":"29.0",
    "gn:asciiname":"Maxi",
    "gn:country_code":"CN",
    "gn:dem":1474,
    "gn:feature_class":"P",
    "gn:feature_code":"PPL",
    "gn:name":"Maxi",
    "gn:population":0,
    "gn:timezone":"Asia/Shanghai",
    "iso:country":"CN",
    "name:deu_x_preferred":[
        "Maxi"
    ],
    "name:fra_x_preferred":[
        "Maxi"
    ],
    "name:ita_x_preferred":[
        "Maxi"
    ],
    "name:spa_x_preferred":[
        "Maxi"
    ],
    "name:swe_x_preferred":[
        "Maxi"
    ],
    "name:zho_x_preferred":[
        "\u9a6c\u897f"
    ],
    "wof:name":"Maxi",
    "wof:placetype":"locality"
},
  "geometry": {"coordinates":[104.18000000000001,22.9726],"type":"Point"}
}