{
  "type": "Feature",
  "properties": {
    "gn:admin1_code":"11",
    "gn:asciiname":"Chixiping",
    "gn:country_code":"CN",
    "gn:dem":341,
    "gn:feature_class":"P",
    "gn:feature_code":"PPL",
    "gn:name":"Chixiping",
    "gn:population":0,
    "gn:timezone":"Asia/Shanghai",
    "iso:country":"CN",
    "name:und_x_variant":[
        "\u8d64\u6eaa\u576a",
        "Chixi",
        "\u8d64\u6eaa"
    ],
    "name:zho_x_preferred":[
        "\u8d64\u6eaa\u576a"
    ],
    "wof:name":"Chixiping",
    "wof:placetype":"locality"
},
  "geometry": {"coordinates":[110.12546,29.38861],"type":"Point"}
}