{
  "type": "Feature",
  "properties": {
    "gn:admin1_code":"33.0",
    "gn:asciiname":"Nanqiaosi",
    "gn:country_code":"CN",
    "gn:dem":291,
    "gn:feature_class":"P",
    "gn:feature_code":"PPL",
    "gn:name":"Nanqiaosi",
    "gn:population":0,
    "gn:timezone":"Asia/Shanghai",
    "iso:country":"CN",
    "name:zho_x_preferred":[
        "\u5357\u6865\u5bfa"
    ],
    "wof:name":"Nanqiaosi",
    "wof:placetype":"locality"
},
  "geometry": {"coordinates":[106.471,29.5868],"type":"Point"}
}