{
  "type": "Feature",
  "properties": {
    "gn:admin1_code":"26.0",
    "gn:asciiname":"Jiezicun",
    "gn:country_code":"CN",
    "gn:dem":430,
    "gn:feature_class":"P",
    "gn:feature_code":"PPL",
    "gn:name":"Jiezicun",
    "gn:population":0,
    "gn:timezone":"Asia/Shanghai",
    "iso:country":"CN",
    "name:zho_x_preferred":[
        "\u8857\u5b50\u6751"
    ],
    "wof:name":"Jiezicun",
    "wof:placetype":"locality"
},
  "geometry": {"coordinates":[108.87304,34.62994],"type":"Point"}
}