{
  "type": "Feature",
  "properties": {
    "gn:admin1_code":"12.0",
    "gn:asciiname":"Zhangwan",
    "gn:country_code":"CN",
    "gn:dem":35,
    "gn:feature_class":"P",
    "gn:feature_code":"PPL",
    "gn:name":"Zhangwan",
    "gn:population":0,
    "gn:timezone":"Asia/Shanghai",
    "iso:country":"CN",
    "name:ceb_x_preferred":[
        "Zhangwan"
    ],
    "name:deu_x_preferred":[
        "Zhangwan"
    ],
    "name:zho_x_preferred":[
        "\u7ae0\u6e7e"
    ],
    "wof:name":"Zhangwan",
    "wof:placetype":"locality"
},
  "geometry": {"coordinates":[113.85008999999999,30.46401],"type":"Point"}
}