{
  "type": "Feature",
  "properties": {
    "gn:admin1_code":"26",
    "gn:asciiname":"Wangjiayao",
    "gn:country_code":"CN",
    "gn:dem":705,
    "gn:feature_class":"P",
    "gn:feature_code":"PPL",
    "gn:name":"Wangjiayao",
    "gn:population":0,
    "gn:timezone":"Asia/Shanghai",
    "iso:country":"CN",
    "name:zho_x_preferred":[
        "\u738b\u5bb6\u7a91"
    ],
    "wof:name":"Wangjiayao",
    "wof:placetype":"locality"
},
  "geometry": {"coordinates":[109.32550000000001,35.0035],"type":"Point"}
}