{
  "type": "Feature",
  "properties": {
    "gn:admin1_code":"26.0",
    "gn:asciiname":"Laohuya",
    "gn:country_code":"CN",
    "gn:dem":1241,
    "gn:feature_class":"P",
    "gn:feature_code":"PPL",
    "gn:name":"Laohuya",
    "gn:population":0,
    "gn:timezone":"Asia/Shanghai",
    "iso:country":"CN",
    "name:und_x_variant":[
        "\u8001\u864e\u57ad"
    ],
    "wof:name":"Laohuya",
    "wof:placetype":"locality"
},
  "geometry": {"coordinates":[106.02027,33.1694],"type":"Point"}
}