{
  "type": "Feature",
  "properties": {
    "gn:admin1_code":"2.0",
    "gn:asciiname":"Guangyao",
    "gn:country_code":"CN",
    "gn:dem":40,
    "gn:feature_class":"P",
    "gn:feature_code":"PPL",
    "gn:name":"Guangyao",
    "gn:population":0,
    "gn:timezone":"Asia/Shanghai",
    "iso:country":"CN",
    "name:und_x_variant":[
        "\u5149\u8000"
    ],
    "wof:name":"Guangyao",
    "wof:placetype":"locality"
},
  "geometry": {"coordinates":[119.78496,31.06149000000001],"type":"Point"}
}