{
  "type": "Feature",
  "properties": {
    "gn:admin1_code":"12.0",
    "gn:asciiname":"Nianzitai",
    "gn:country_code":"CN",
    "gn:dem":29,
    "gn:feature_class":"P",
    "gn:feature_code":"PPL",
    "gn:name":"Nianzitai",
    "gn:population":0,
    "gn:timezone":"Asia/Shanghai",
    "iso:country":"CN",
    "name:zho_x_preferred":[
        "\u78be\u5b50\u53f0"
    ],
    "wof:name":"Nianzitai",
    "wof:placetype":"locality"
},
  "geometry": {"coordinates":[112.90266,29.86979],"type":"Point"}
}