{
  "type": "Feature",
  "properties": {
    "gn:admin1_code":"25",
    "gn:asciiname":"Jiangjiazhuang",
    "gn:country_code":"CN",
    "gn:dem":137,
    "gn:feature_class":"P",
    "gn:feature_code":"PPL",
    "gn:name":"Jiangjiazhuang",
    "gn:population":0,
    "gn:timezone":"Asia/Shanghai",
    "iso:country":"CN",
    "name:zho_x_preferred":[
        "\u848b\u5bb6\u5e84"
    ],
    "wof:name":"Jiangjiazhuang",
    "wof:placetype":"locality"
},
  "geometry": {"coordinates":[117.52500000000001,35.6405],"type":"Point"}
}