{
  "type": "Feature",
  "properties": {
    "gn:admin1_code":"19.0",
    "gn:asciiname":"Huangdi",
    "gn:country_code":"CN",
    "gn:dem":269,
    "gn:feature_class":"P",
    "gn:feature_code":"PPL",
    "gn:name":"Huangdi",
    "gn:population":0,
    "gn:timezone":"Asia/Shanghai",
    "iso:country":"CN",
    "name:cat_x_preferred":[
        "Huangdi"
    ],
    "name:fra_x_preferred":[
        "Huangdi"
    ],
    "name:und_x_variant":[
        "\u8352\u5730"
    ],
    "wof:name":"Huangdi",
    "wof:placetype":"locality"
},
  "geometry": {"coordinates":[124.05056,41.60307],"type":"Point"}
}