{
  "type": "Feature",
  "properties": {
    "gn:admin1_code":"10.0",
    "gn:asciiname":"Beiliuzhuang",
    "gn:country_code":"CN",
    "gn:dem":930,
    "gn:feature_class":"P",
    "gn:feature_code":"PPL",
    "gn:name":"Beiliuzhuang",
    "gn:population":0,
    "gn:timezone":"Asia/Shanghai",
    "iso:country":"CN",
    "name:zho_x_preferred":[
        "\u5317\u5218\u5e84"
    ],
    "wof:name":"Beiliuzhuang",
    "wof:placetype":"locality"
},
  "geometry": {"coordinates":[113.85383,38.93006],"type":"Point"}
}