{
  "type": "Feature",
  "properties": {
    "gn:admin1_code":"2.0",
    "gn:asciiname":"Lianlingjiao",
    "gn:country_code":"CN",
    "gn:dem":293,
    "gn:feature_class":"P",
    "gn:feature_code":"PPL",
    "gn:name":"Lianlingjiao",
    "gn:population":0,
    "gn:timezone":"Asia/Shanghai",
    "iso:country":"CN",
    "name:zho_x_preferred":[
        "\u8fde\u5cad\u811a"
    ],
    "wof:name":"Lianlingjiao",
    "wof:placetype":"locality"
},
  "geometry": {"coordinates":[118.51906,29.54331],"type":"Point"}
}