{
  "type": "Feature",
  "properties": {
    "gn:admin1_code":"32.0",
    "gn:asciiname":"Rong'a",
    "gn:country_code":"CN",
    "gn:dem":3514,
    "gn:feature_class":"P",
    "gn:feature_code":"PPL",
    "gn:name":"Rong\u2019a",
    "gn:population":0,
    "gn:timezone":"Asia/Shanghai",
    "iso:country":"CN",
    "name:und_x_variant":[
        "Rong\u2019a"
    ],
    "name:zho_x_preferred":[
        "\u7ed2\u963f"
    ],
    "wof:name":"Rong'a",
    "wof:placetype":"locality"
},
  "geometry": {"coordinates":[101.503,30.5333],"type":"Point"}
}