{
  "type": "Feature",
  "properties": {
    "gn:admin1_code":"9.0",
    "gn:asciiname":"Wenzhuang",
    "gn:country_code":"CN",
    "gn:dem":94,
    "gn:feature_class":"P",
    "gn:feature_code":"PPL",
    "gn:name":"Wenzhuang",
    "gn:population":0,
    "gn:timezone":"Asia/Shanghai",
    "iso:country":"CN",
    "name:zho_x_preferred":[
        "\u6e29\u5e84"
    ],
    "wof:name":"Wenzhuang",
    "wof:placetype":"locality"
},
  "geometry": {"coordinates":[113.72611000000001,32.98035],"type":"Point"}
}