{
  "type": "Feature",
  "properties": {
    "gn:admin1_code":"7",
    "gn:asciiname":"Mianliang",
    "gn:country_code":"CN",
    "gn:dem":214,
    "gn:feature_class":"P",
    "gn:feature_code":"PPL",
    "gn:name":"Mianliang",
    "gn:population":0,
    "gn:timezone":"Asia/Shanghai",
    "iso:country":"CN",
    "name:zho_x_preferred":[
        "\u7ef5\u826f"
    ],
    "wof:name":"Mianliang",
    "wof:placetype":"locality"
},
  "geometry": {"coordinates":[117.54076000000001,25.05269],"type":"Point"}
}