{
  "type": "Feature",
  "properties": {
    "gn:admin1_code":"29.0",
    "gn:asciiname":"Dongdao Xinzhai",
    "gn:country_code":"CN",
    "gn:dem":1055,
    "gn:feature_class":"P",
    "gn:feature_code":"PPL",
    "gn:name":"Dongdao Xinzhai",
    "gn:population":0,
    "gn:timezone":"Asia/Shanghai",
    "iso:country":"CN",
    "name:zho_x_preferred":[
        "\u4e1c\u5c9b\u65b0\u5be8"
    ],
    "wof:name":"Dongdao Xinzhai",
    "wof:placetype":"locality"
},
  "geometry": {"coordinates":[99.65000000000001,22.4308],"type":"Point"}
}