{
  "type": "Feature",
  "properties": {
    "gn:admin1_code":"29.0",
    "gn:asciiname":"Shelang",
    "gn:country_code":"CN",
    "gn:dem":1666,
    "gn:feature_class":"P",
    "gn:feature_code":"PPL",
    "gn:name":"Shelang",
    "gn:population":0,
    "gn:timezone":"Asia/Shanghai",
    "iso:country":"CN",
    "name:zho_x_preferred":[
        "\u820d\u90ce"
    ],
    "wof:name":"Shelang",
    "wof:placetype":"locality"
},
  "geometry": {"coordinates":[102.327,23.3079],"type":"Point"}
}