{
  "type": "Feature",
  "properties": {
    "gn:admin1_code":"09",
    "gn:asciiname":"Mengzhai",
    "gn:country_code":"CN",
    "gn:dem":78,
    "gn:feature_class":"P",
    "gn:feature_code":"PPLA4",
    "gn:name":"Mengzhai",
    "gn:population":0,
    "gn:timezone":"Asia/Shanghai",
    "iso:country":"CN",
    "name:und_x_variant":[
        "Meng-chai",
        "Mengzhai Zhen",
        "Mengzhai"
    ],
    "name:zho_x_preferred":[
        "\u5b5f\u5be8"
    ],
    "wof:name":"Mengzhai",
    "wof:placetype":"locality"
},
  "geometry": {"coordinates":[113.60889,33.54252],"type":"Point"}
}