{
  "type": "Feature",
  "properties": {
    "gn:admin1_code":"14.0",
    "gn:asciiname":"Langqingmacun",
    "gn:country_code":"CN",
    "gn:dem":4763,
    "gn:feature_class":"P",
    "gn:feature_code":"PPL",
    "gn:name":"Langqingmacun",
    "gn:population":0,
    "gn:timezone":"Asia/Urumqi",
    "iso:country":"CN",
    "name:zho_x_preferred":[
        "\u6717\u9752\u739b\u6751"
    ],
    "wof:name":"Langqingmacun",
    "wof:placetype":"locality"
},
  "geometry": {"coordinates":[91.93344999999999,32.21724],"type":"Point"}
}