{
  "type": "Feature",
  "properties": {
    "gn:admin1_code":"9.0",
    "gn:asciiname":"Xiawangwan",
    "gn:country_code":"CN",
    "gn:dem":44,
    "gn:feature_class":"P",
    "gn:feature_code":"PPL",
    "gn:name":"Xiawangwan",
    "gn:population":0,
    "gn:timezone":"Asia/Shanghai",
    "iso:country":"CN",
    "name:zho_x_preferred":[
        "\u4e0b\u738b\u6e7e"
    ],
    "wof:name":"Xiawangwan",
    "wof:placetype":"locality"
},
  "geometry": {"coordinates":[114.64831,33.07921],"type":"Point"}
}