{
  "type": "Feature",
  "properties": {
    "gn:admin1_code":"7.0",
    "gn:asciiname":"Cunli",
    "gn:country_code":"CN",
    "gn:dem":30,
    "gn:feature_class":"P",
    "gn:feature_code":"PPL",
    "gn:name":"Cunli",
    "gn:population":0,
    "gn:timezone":"Asia/Shanghai",
    "iso:country":"CN",
    "name:zho_x_preferred":[
        "\u6751\u91cc"
    ],
    "wof:name":"Cunli",
    "wof:placetype":"locality"
},
  "geometry": {"coordinates":[119.87358,26.86275],"type":"Point"}
}