{
  "type": "Feature",
  "properties": {
    "gn:admin1_code":"32.0",
    "gn:asciiname":"Erluo",
    "gn:country_code":"CN",
    "gn:dem":2085,
    "gn:feature_class":"P",
    "gn:feature_code":"PPL",
    "gn:name":"Erluo",
    "gn:population":0,
    "gn:timezone":"Asia/Shanghai",
    "iso:country":"CN",
    "name:zho_x_preferred":[
        "\u4e8c\u7f57"
    ],
    "wof:name":"Erluo",
    "wof:placetype":"locality"
},
  "geometry": {"coordinates":[101.569,28.073],"type":"Point"}
}