{
  "type": "Feature",
  "properties": {
    "gn:admin1_code":"32.0",
    "gn:asciiname":"Youjia Wazi",
    "gn:country_code":"CN",
    "gn:dem":1745,
    "gn:feature_class":"P",
    "gn:feature_code":"PPL",
    "gn:name":"Youjia Wazi",
    "gn:population":0,
    "gn:timezone":"Asia/Shanghai",
    "iso:country":"CN",
    "name:zho_x_preferred":[
        "\u5c24\u5bb6\u6d3c\u5b50"
    ],
    "wof:name":"Youjia Wazi",
    "wof:placetype":"locality"
},
  "geometry": {"coordinates":[102.453,26.5482],"type":"Point"}
}