{
  "type": "Feature",
  "properties": {
    "gn:admin1_code":"3.0",
    "gn:asciiname":"Lidongshan",
    "gn:country_code":"CN",
    "gn:dem":446,
    "gn:feature_class":"P",
    "gn:feature_code":"PPL",
    "gn:name":"Lidongshan",
    "gn:population":0,
    "gn:timezone":"Asia/Shanghai",
    "iso:country":"CN",
    "name:zho_x_preferred":[
        "\u91cc\u4e1c\u5c71"
    ],
    "wof:name":"Lidongshan",
    "wof:placetype":"locality"
},
  "geometry": {"coordinates":[118.03636000000002,28.74222],"type":"Point"}
}