{
  "type": "Feature",
  "properties": {
    "gn:admin1_code":"8.0",
    "gn:asciiname":"Xingjiecun",
    "gn:country_code":"CN",
    "gn:dem":167,
    "gn:feature_class":"P",
    "gn:feature_code":"PPL",
    "gn:name":"Xingjiecun",
    "gn:population":0,
    "gn:timezone":"Asia/Shanghai",
    "iso:country":"CN",
    "name:zho_x_preferred":[
        "\u5174\u7ed3\u6751"
    ],
    "wof:name":"Xingjiecun",
    "wof:placetype":"locality"
},
  "geometry": {"coordinates":[126.49617000000001,45.33717],"type":"Point"}
}