{
  "type": "Feature",
  "properties": {
    "gn:admin1_code":"11",
    "gn:asciiname":"Yangliutang",
    "gn:country_code":"CN",
    "gn:dem":574,
    "gn:feature_class":"P",
    "gn:feature_code":"PPL",
    "gn:name":"Yangliutang",
    "gn:population":0,
    "gn:timezone":"Asia/Shanghai",
    "iso:country":"CN",
    "name:zho_x_preferred":[
        "\u6768\u67f3\u5858"
    ],
    "wof:name":"Yangliutang",
    "wof:placetype":"locality"
},
  "geometry": {"coordinates":[111.51254,27.76742],"type":"Point"}
}