{
  "type": "Feature",
  "properties": {
    "gn:admin1_code":"15.0",
    "gn:asciiname":"Liujia Buzi",
    "gn:country_code":"CN",
    "gn:dem":1632,
    "gn:feature_class":"P",
    "gn:feature_code":"PPL",
    "gn:name":"Liujia Buzi",
    "gn:population":0,
    "gn:timezone":"Asia/Shanghai",
    "iso:country":"CN",
    "name:zho_x_preferred":[
        "\u5218\u5bb6\u5821\u5b50"
    ],
    "wof:name":"Liujia Buzi",
    "wof:placetype":"locality"
},
  "geometry": {"coordinates":[106.85899999999999,35.9003],"type":"Point"}
}