{
  "type": "Feature",
  "properties": {
    "gn:admin1_code":"32.0",
    "gn:asciiname":"Rongsi",
    "gn:country_code":"CN",
    "gn:dem":2737,
    "gn:feature_class":"P",
    "gn:feature_code":"PPL",
    "gn:name":"Rongsi",
    "gn:population":0,
    "gn:timezone":"Asia/Shanghai",
    "iso:country":"CN",
    "name:zho_x_preferred":[
        "\u7ed2\u65af"
    ],
    "wof:name":"Rongsi",
    "wof:placetype":"locality"
},
  "geometry": {"coordinates":[99.28919999999999,28.5908],"type":"Point"}
}