{
  "type": "Feature",
  "properties": {
    "gn:admin1_code":"32.0",
    "gn:asciiname":"Hulugou",
    "gn:country_code":"CN",
    "gn:dem":430,
    "gn:feature_class":"P",
    "gn:feature_code":"PPL",
    "gn:name":"Hulugou",
    "gn:population":0,
    "gn:timezone":"Asia/Shanghai",
    "iso:country":"CN",
    "name:zho_x_preferred":[
        "\u846b\u82a6\u6c9f"
    ],
    "wof:name":"Hulugou",
    "wof:placetype":"locality"
},
  "geometry": {"coordinates":[104.80531999999999,30.45161],"type":"Point"}
}