{
  "type": "Feature",
  "properties": {
    "gn:admin1_code":"12.0",
    "gn:asciiname":"Maodian",
    "gn:country_code":"CN",
    "gn:dem":48,
    "gn:feature_class":"P",
    "gn:feature_code":"PPL",
    "gn:name":"Maodian",
    "gn:population":0,
    "gn:timezone":"Asia/Shanghai",
    "iso:country":"CN",
    "name:zho_x_preferred":[
        "\u8305\u5e97"
    ],
    "wof:name":"Maodian",
    "wof:placetype":"locality"
},
  "geometry": {"coordinates":[114.39109999999999,30.46601],"type":"Point"}
}