{
  "type": "Feature",
  "properties": {
    "gn:admin1_code":"4.0",
    "gn:asciiname":"Zhougou",
    "gn:country_code":"CN",
    "gn:dem":3,
    "gn:feature_class":"P",
    "gn:feature_code":"PPL",
    "gn:name":"Zhougou",
    "gn:population":0,
    "gn:timezone":"Asia/Shanghai",
    "iso:country":"CN",
    "name:zho_x_preferred":[
        "Zhougou"
    ],
    "name:zho_x_variant":[
        "\u5468\u6c9f"
    ],
    "wof:name":"Zhougou",
    "wof:placetype":"locality"
},
  "geometry": {"coordinates":[119.50608,34.13821],"type":"Point"}
}