{
  "type": "Feature",
  "properties": {
    "gn:admin1_code":"29.0",
    "gn:asciiname":"Yanzijiao",
    "gn:country_code":"CN",
    "gn:dem":1413,
    "gn:feature_class":"P",
    "gn:feature_code":"PPL",
    "gn:name":"Yanzijiao",
    "gn:population":0,
    "gn:timezone":"Asia/Shanghai",
    "iso:country":"CN",
    "name:zho_x_preferred":[
        "\u5ca9\u5b50\u811a"
    ],
    "wof:name":"Yanzijiao",
    "wof:placetype":"locality"
},
  "geometry": {"coordinates":[101.40000000000001,23.3993],"type":"Point"}
}