{
  "type": "Feature",
  "properties": {
    "gn:admin1_code":"26.0",
    "gn:asciiname":"Gaopan",
    "gn:country_code":"CN",
    "gn:dem":1148,
    "gn:feature_class":"P",
    "gn:feature_code":"PPL",
    "gn:name":"Gaopan",
    "gn:population":0,
    "gn:timezone":"Asia/Shanghai",
    "iso:country":"CN",
    "name:und_x_variant":[
        "\u9ad8\u76d8"
    ],
    "wof:name":"Gaopan",
    "wof:placetype":"locality"
},
  "geometry": {"coordinates":[107.09050999999999,34.77954],"type":"Point"}
}