{
  "type": "Feature",
  "properties": {
    "gn:admin1_code":"30.0",
    "gn:asciiname":"Libeiling",
    "gn:country_code":"CN",
    "gn:dem":25,
    "gn:feature_class":"P",
    "gn:feature_code":"PPL",
    "gn:name":"Libeiling",
    "gn:population":0,
    "gn:timezone":"Asia/Shanghai",
    "iso:country":"CN",
    "name:zho_x_preferred":[
        "\u9ece\u8d1d\u5cad"
    ],
    "wof:name":"Libeiling",
    "wof:placetype":"locality"
},
  "geometry": {"coordinates":[113.90168,22.95409],"type":"Point"}
}