{
  "type": "Feature",
  "properties": {
    "gn:admin1_code":"29.0",
    "gn:asciiname":"Hejia Yingzhai",
    "gn:country_code":"CN",
    "gn:dem":1871,
    "gn:feature_class":"P",
    "gn:feature_code":"PPL",
    "gn:name":"Hejia Yingzhai",
    "gn:population":0,
    "gn:timezone":"Asia/Shanghai",
    "iso:country":"CN",
    "name:zho_x_preferred":[
        "\u4f55\u5bb6\u8425\u5be8"
    ],
    "wof:name":"Hejia Yingzhai",
    "wof:placetype":"locality"
},
  "geometry": {"coordinates":[98.70010000000001,25.4666],"type":"Point"}
}