{
  "type": "Feature",
  "properties": {
    "gn:admin1_code":"19.0",
    "gn:asciiname":"Limingcun",
    "gn:country_code":"CN",
    "gn:dem":35,
    "gn:feature_class":"P",
    "gn:feature_code":"PPL",
    "gn:name":"Limingcun",
    "gn:population":0,
    "gn:timezone":"Asia/Shanghai",
    "iso:country":"CN",
    "name:zho_x_preferred":[
        "\u9ece\u660e\u6751"
    ],
    "wof:name":"Limingcun",
    "wof:placetype":"locality"
},
  "geometry": {"coordinates":[123.053,42.0852],"type":"Point"}
}