{
  "type": "Feature",
  "properties": {
    "gn:admin1_code":"26.0",
    "gn:asciiname":"Shixiakoucun",
    "gn:country_code":"CN",
    "gn:dem":406,
    "gn:feature_class":"P",
    "gn:feature_code":"PPL",
    "gn:name":"Shixiakoucun",
    "gn:population":0,
    "gn:timezone":"Asia/Shanghai",
    "iso:country":"CN",
    "name:zho_x_preferred":[
        "\u77f3\u5323\u53e3\u6751"
    ],
    "wof:name":"Shixiakoucun",
    "wof:placetype":"locality"
},
  "geometry": {"coordinates":[108.77271,34.18604000000001],"type":"Point"}
}