{
  "type": "Feature",
  "properties": {
    "gn:admin1_code":"19.0",
    "gn:asciiname":"Gongtuncun",
    "gn:country_code":"CN",
    "gn:dem":36,
    "gn:feature_class":"P",
    "gn:feature_code":"PPL",
    "gn:name":"Gongtuncun",
    "gn:population":0,
    "gn:timezone":"Asia/Shanghai",
    "iso:country":"CN",
    "name:zho_x_preferred":[
        "\u5bab\u5c6f\u6751"
    ],
    "wof:name":"Gongtuncun",
    "wof:placetype":"locality"
},
  "geometry": {"coordinates":[122.03700000000001,39.5471],"type":"Point"}
}