{
  "type": "Feature",
  "properties": {
    "gn:admin1_code":"14.0",
    "gn:asciiname":"Lexue",
    "gn:country_code":"CN",
    "gn:dem":3736,
    "gn:feature_class":"P",
    "gn:feature_code":"PPL",
    "gn:name":"Lexue",
    "gn:population":0,
    "gn:timezone":"Asia/Urumqi",
    "iso:country":"CN",
    "name:zho_x_preferred":[
        "\u52d2\u5b66"
    ],
    "wof:name":"Lexue",
    "wof:placetype":"locality"
},
  "geometry": {"coordinates":[98.81471000000001,29.30637],"type":"Point"}
}