{
  "type": "Feature",
  "properties": {
    "gn:admin1_code":"5.0",
    "gn:asciiname":"Qianweicun",
    "gn:country_code":"CN",
    "gn:dem":197,
    "gn:feature_class":"P",
    "gn:feature_code":"PPL",
    "gn:name":"Qianweicun",
    "gn:population":0,
    "gn:timezone":"Asia/Shanghai",
    "iso:country":"CN",
    "name:zho_x_preferred":[
        "\u524d\u82c7\u6751"
    ],
    "wof:name":"Qianweicun",
    "wof:placetype":"locality"
},
  "geometry": {"coordinates":[126.7199,44.64457],"type":"Point"}
}