{
  "type": "Feature",
  "properties": {
    "gn:admin1_code":"15.0",
    "gn:asciiname":"Honggounao",
    "gn:country_code":"CN",
    "gn:dem":2443,
    "gn:feature_class":"P",
    "gn:feature_code":"PPL",
    "gn:name":"Honggounao",
    "gn:population":0,
    "gn:timezone":"Asia/Shanghai",
    "iso:country":"CN",
    "name:zho_x_preferred":[
        "\u7ea2\u6c9f\u8111"
    ],
    "wof:name":"Honggounao",
    "wof:placetype":"locality"
},
  "geometry": {"coordinates":[104.352,35.4021],"type":"Point"}
}