{
  "type": "Feature",
  "properties": {
    "gn:admin1_code":"10",
    "gn:asciiname":"Guchengying",
    "gn:country_code":"CN",
    "gn:dem":37,
    "gn:feature_class":"P",
    "gn:feature_code":"PPL",
    "gn:name":"Guchengying",
    "gn:population":0,
    "gn:timezone":"Asia/Shanghai",
    "iso:country":"CN",
    "name:und_x_variant":[
        "Kucheng",
        "Ku-ch\u2019eng-ying",
        "Guchengying"
    ],
    "name:zho_x_preferred":[
        "\u53e4\u57ce\u8425"
    ],
    "wof:name":"Guchengying",
    "wof:placetype":"locality"
},
  "geometry": {"coordinates":[115.137,36.8911],"type":"Point"}
}