{
  "type": "Feature",
  "properties": {
    "gn:admin1_code":"30",
    "gn:asciiname":"Guizhubei",
    "gn:country_code":"CN",
    "gn:dem":645,
    "gn:feature_class":"P",
    "gn:feature_code":"PPL",
    "gn:name":"Guizhubei",
    "gn:population":0,
    "gn:timezone":"Asia/Shanghai",
    "iso:country":"CN",
    "name:zho_x_preferred":[
        "\u7b40\u7af9\u80cc"
    ],
    "wof:name":"Guizhubei",
    "wof:placetype":"locality"
},
  "geometry": {"coordinates":[116.26860000000001,24.72626],"type":"Point"}
}