{
  "type": "Feature",
  "properties": {
    "gn:admin1_code":"13.0",
    "gn:asciiname":"Qilian",
    "gn:country_code":"CN",
    "gn:dem":870,
    "gn:feature_class":"P",
    "gn:feature_code":"PPLF",
    "gn:name":"Qilian",
    "gn:population":0,
    "gn:timezone":"Asia/Urumqi",
    "iso:country":"CN",
    "name:zho_x_preferred":[
        "\u4e03\u8fde"
    ],
    "wof:name":"Qilian",
    "wof:placetype":"locality"
},
  "geometry": {"coordinates":[86.89918,40.91986],"type":"Point"}
}