{
  "type": "Feature",
  "properties": {
    "gn:admin1_code":"26",
    "gn:asciiname":"Shandi",
    "gn:country_code":"CN",
    "gn:dem":593,
    "gn:feature_class":"P",
    "gn:feature_code":"PPL",
    "gn:name":"Shandi",
    "gn:population":0,
    "gn:timezone":"Asia/Shanghai",
    "iso:country":"CN",
    "name:und_x_variant":[
        "\u5c71\u5e95"
    ],
    "name:zho_x_preferred":[
        "\u5c71\u5e95"
    ],
    "wof:name":"Shandi",
    "wof:placetype":"locality"
},
  "geometry": {"coordinates":[108.51639,34.60417],"type":"Point"}
}