{
  "type": "Feature",
  "properties": {
    "gn:admin1_code":"31",
    "gn:asciiname":"Changwen",
    "gn:country_code":"CN",
    "gn:dem":99,
    "gn:feature_class":"P",
    "gn:feature_code":"PPL",
    "gn:name":"Changwen",
    "gn:population":0,
    "gn:timezone":"Asia/Shanghai",
    "iso:country":"CN",
    "name:und_x_variant":[
        "\u660c\u6587"
    ],
    "wof:name":"Changwen",
    "wof:placetype":"locality"
},
  "geometry": {"coordinates":[110.093,19.6265],"type":"Point"}
}