{
  "type": "Feature",
  "properties": {
    "gn:admin1_code":"19.0",
    "gn:asciiname":"Yingtaoyuancun",
    "gn:country_code":"CN",
    "gn:dem":54,
    "gn:feature_class":"P",
    "gn:feature_code":"PPL",
    "gn:name":"Yingtaoyuancun",
    "gn:population":0,
    "gn:timezone":"Asia/Shanghai",
    "iso:country":"CN",
    "name:zho_x_preferred":[
        "\u6a31\u6843\u56ed\u6751"
    ],
    "wof:name":"Yingtaoyuancun",
    "wof:placetype":"locality"
},
  "geometry": {"coordinates":[123.09173,41.16918],"type":"Point"}
}