{
  "type": "Feature",
  "properties": {
    "gn:admin1_code":"32.0",
    "gn:asciiname":"Yangcao",
    "gn:country_code":"CN",
    "gn:dem":2310,
    "gn:feature_class":"P",
    "gn:feature_code":"PPL",
    "gn:name":"Yangcao",
    "gn:population":0,
    "gn:timezone":"Asia/Shanghai",
    "iso:country":"CN",
    "name:zho_x_preferred":[
        "\u7f8a\u69fd"
    ],
    "wof:name":"Yangcao",
    "wof:placetype":"locality"
},
  "geometry": {"coordinates":[102.67100000000001,26.7189],"type":"Point"}
}