{
  "type": "Feature",
  "properties": {
    "gn:admin1_code":"5.0",
    "gn:asciiname":"Qibaogou",
    "gn:country_code":"CN",
    "gn:dem":175,
    "gn:feature_class":"P",
    "gn:feature_code":"PPL",
    "gn:name":"Qibaogou",
    "gn:population":0,
    "gn:timezone":"Asia/Shanghai",
    "iso:country":"CN",
    "name:und_x_variant":[
        "\u4e03\u5b9d\u6c9f"
    ],
    "wof:name":"Qibaogou",
    "wof:placetype":"locality"
},
  "geometry": {"coordinates":[125.92324000000001,40.90945],"type":"Point"}
}