{
  "type": "Feature",
  "properties": {
    "gn:admin1_code":"33.0",
    "gn:asciiname":"Hongzhuan",
    "gn:country_code":"CN",
    "gn:dem":227,
    "gn:feature_class":"P",
    "gn:feature_code":"PPL",
    "gn:name":"Hongzhuan",
    "gn:population":0,
    "gn:timezone":"Asia/Shanghai",
    "iso:country":"CN",
    "name:zho_x_preferred":[
        "\u7ea2\u4e13"
    ],
    "wof:name":"Hongzhuan",
    "wof:placetype":"locality"
},
  "geometry": {"coordinates":[106.43385000000001,29.09302000000001],"type":"Point"}
}