{
  "type": "Feature",
  "properties": {
    "gn:admin1_code":"15.0",
    "gn:asciiname":"Bianqiangwan",
    "gn:country_code":"CN",
    "gn:dem":1372,
    "gn:feature_class":"P",
    "gn:feature_code":"PPL",
    "gn:name":"Bianqiangwan",
    "gn:population":0,
    "gn:timezone":"Asia/Shanghai",
    "iso:country":"CN",
    "name:zho_x_preferred":[
        "\u8fb9\u5899\u6e7e"
    ],
    "wof:name":"Bianqiangwan",
    "wof:placetype":"locality"
},
  "geometry": {"coordinates":[104.491,37.1953],"type":"Point"}
}