{
  "type": "Feature",
  "properties": {
    "gn:admin1_code":"26.0",
    "gn:asciiname":"Hesancun",
    "gn:country_code":"CN",
    "gn:dem":927,
    "gn:feature_class":"P",
    "gn:feature_code":"PPL",
    "gn:name":"Hesancun",
    "gn:population":0,
    "gn:timezone":"Asia/Shanghai",
    "iso:country":"CN",
    "name:zho_x_preferred":[
        "\u8d3a\u4e09\u6751"
    ],
    "wof:name":"Hesancun",
    "wof:placetype":"locality"
},
  "geometry": {"coordinates":[110.38612000000001,37.46015],"type":"Point"}
}