{
  "type": "Feature",
  "properties": {
    "gn:admin1_code":"07",
    "gn:asciiname":"Wuqiling",
    "gn:country_code":"CN",
    "gn:dem":277,
    "gn:feature_class":"P",
    "gn:feature_code":"PPL",
    "gn:name":"Wuqiling",
    "gn:population":0,
    "gn:timezone":"Asia/Shanghai",
    "iso:country":"CN",
    "name:zho_x_preferred":[
        "\u543e\u65d7\u5cad"
    ],
    "wof:name":"Wuqiling",
    "wof:placetype":"locality"
},
  "geometry": {"coordinates":[118.37917,25.35944],"type":"Point"}
}