{
  "type": "Feature",
  "properties": {
    "gn:admin1_code":"9.0",
    "gn:asciiname":"Wangou",
    "gn:country_code":"CN",
    "gn:dem":47,
    "gn:feature_class":"P",
    "gn:feature_code":"PPL",
    "gn:name":"Wangou",
    "gn:population":0,
    "gn:timezone":"Asia/Shanghai",
    "iso:country":"CN",
    "name:fra_x_preferred":[
        "Wangou"
    ],
    "name:zho_x_preferred":[
        "\u4e07\u6c9f"
    ],
    "wof:name":"Wangou",
    "wof:placetype":"locality"
},
  "geometry": {"coordinates":[115.48743,32.26203],"type":"Point"}
}