{
  "type": "Feature",
  "properties": {
    "gn:admin1_code":"30",
    "gn:asciiname":"Banqiao",
    "gn:country_code":"CN",
    "gn:dem":9,
    "gn:feature_class":"P",
    "gn:feature_code":"PPL",
    "gn:name":"Banqiao",
    "gn:population":0,
    "gn:timezone":"Asia/Urumqi",
    "iso:country":"CN",
    "name:zho_x_preferred":[
        "\u677f\u6865"
    ],
    "wof:name":"Banqiao",
    "wof:placetype":"locality"
},
  "geometry": {"coordinates":[110.62748999999999,21.46255],"type":"Point"}
}