{
  "type": "Feature",
  "properties": {
    "gn:admin1_code":"3.0",
    "gn:asciiname":"Guijiazhuang",
    "gn:country_code":"CN",
    "gn:dem":25,
    "gn:feature_class":"P",
    "gn:feature_code":"PPL",
    "gn:name":"Guijiazhuang",
    "gn:population":0,
    "gn:timezone":"Asia/Shanghai",
    "iso:country":"CN",
    "name:und_x_variant":[
        "\u6842\u5bb6\u5e84"
    ],
    "wof:name":"Guijiazhuang",
    "wof:placetype":"locality"
},
  "geometry": {"coordinates":[115.82335,29.18875],"type":"Point"}
}