{
  "type": "Feature",
  "properties": {
    "gn:admin1_code":"2.0",
    "gn:asciiname":"Hulu'ao",
    "gn:country_code":"CN",
    "gn:dem":144,
    "gn:feature_class":"P",
    "gn:feature_code":"PPL",
    "gn:name":"Hulu\u2019ao",
    "gn:population":0,
    "gn:timezone":"Asia/Shanghai",
    "iso:country":"CN",
    "name:und_x_variant":[
        "Hulu\u2019ao"
    ],
    "name:zho_x_preferred":[
        "\u846b\u82a6\u5c99"
    ],
    "wof:name":"Hulu'ao",
    "wof:placetype":"locality"
},
  "geometry": {"coordinates":[120.79022999999999,29.06626],"type":"Point"}
}