{
  "type": "Feature",
  "properties": {
    "gn:admin1_code":"23",
    "gn:asciiname":"Shengzimiao",
    "gn:cc2":"CN",
    "gn:country_code":"CN",
    "gn:dem":4,
    "gn:feature_class":"P",
    "gn:feature_code":"PPL",
    "gn:name":"Shengzimiao",
    "gn:population":0,
    "gn:timezone":"Asia/Shanghai",
    "iso:country":"CN",
    "name:und_x_variant":[
        "Sheng-tzu-miao",
        "Shengzimiao",
        "\u76db\u6893\u5e99"
    ],
    "wof:name":"Shengzimiao",
    "wof:placetype":"locality"
},
  "geometry": {"coordinates":[121.3475,30.91056],"type":"Point"}
}