{
  "type": "Feature",
  "properties": {
    "gn:admin1_code":"7",
    "gn:asciiname":"Libidou",
    "gn:country_code":"CN",
    "gn:dem":329,
    "gn:feature_class":"P",
    "gn:feature_code":"PPL",
    "gn:name":"Libidou",
    "gn:population":0,
    "gn:timezone":"Asia/Shanghai",
    "iso:country":"CN",
    "name:zho_x_preferred":[
        "\u7281\u58c1\u6597"
    ],
    "wof:name":"Libidou",
    "wof:placetype":"locality"
},
  "geometry": {"coordinates":[117.26517,24.24707],"type":"Point"}
}