{
  "type": "Feature",
  "properties": {
    "gn:admin1_code":"19.0",
    "gn:asciiname":"Erjibai",
    "gn:country_code":"CN",
    "gn:dem":131,
    "gn:feature_class":"P",
    "gn:feature_code":"PPL",
    "gn:name":"Erjibai",
    "gn:population":0,
    "gn:timezone":"Asia/Shanghai",
    "iso:country":"CN",
    "name:zho_x_preferred":[
        "\u4e8c\u5409\u767e"
    ],
    "wof:name":"Erjibai",
    "wof:placetype":"locality"
},
  "geometry": {"coordinates":[122.85299999999999,42.5299],"type":"Point"}
}