{
  "type": "Feature",
  "properties": {
    "gn:admin1_code":"26.0",
    "gn:asciiname":"Xinhuacun",
    "gn:country_code":"CN",
    "gn:dem":490,
    "gn:feature_class":"P",
    "gn:feature_code":"PPL",
    "gn:name":"Xinhuacun",
    "gn:population":0,
    "gn:timezone":"Asia/Shanghai",
    "iso:country":"CN",
    "name:und_x_variant":[
        "\u65b0\u534e\u6751"
    ],
    "wof:name":"Xinhuacun",
    "wof:placetype":"locality"
},
  "geometry": {"coordinates":[107.26888999999998,33.16427],"type":"Point"}
}