{
  "type": "Feature",
  "properties": {
    "gn:admin1_code":"3.0",
    "gn:asciiname":"Sanfanglong",
    "gn:country_code":"CN",
    "gn:dem":25,
    "gn:feature_class":"P",
    "gn:feature_code":"PPL",
    "gn:name":"Sanfanglong",
    "gn:population":0,
    "gn:timezone":"Asia/Shanghai",
    "iso:country":"CN",
    "name:und_x_variant":[
        "\u4e09\u623f\u5784"
    ],
    "wof:name":"Sanfanglong",
    "wof:placetype":"locality"
},
  "geometry": {"coordinates":[115.91003000000001,28.18784],"type":"Point"}
}