{
  "type": "Feature",
  "properties": {
    "gn:admin1_code":"20",
    "gn:asciiname":"Chaogutai",
    "gn:country_code":"CN",
    "gn:dem":403,
    "gn:feature_class":"P",
    "gn:feature_code":"PPL",
    "gn:name":"Chaogutai",
    "gn:population":0,
    "gn:timezone":"Asia/Shanghai",
    "iso:country":"CN",
    "wof:name":"Chaogutai",
    "wof:placetype":"locality"
},
  "geometry": {"coordinates":[121.08138999999998,42.7275],"type":"Point"}
}