{
  "type": "Feature",
  "properties": {
    "gn:admin1_code":"21",
    "gn:asciiname":"Changxin",
    "gn:cc2":"CN",
    "gn:country_code":"CN",
    "gn:dem":1106,
    "gn:feature_class":"P",
    "gn:feature_code":"PPL",
    "gn:name":"Changxin",
    "gn:population":0,
    "gn:timezone":"Asia/Shanghai",
    "iso:country":"CN",
    "name:und_x_variant":[
        "Ch\u2019ang-hsin-p\u2019u",
        "Changxingpu",
        "Changxin"
    ],
    "wof:name":"Changxin",
    "wof:placetype":"locality"
},
  "geometry": {"coordinates":[106.32971999999999,38.67472],"type":"Point"}
}