{
  "type": "Feature",
  "properties": {
    "gn:admin1_code":"12.0",
    "gn:asciiname":"Laoguanwo",
    "gn:country_code":"CN",
    "gn:dem":284,
    "gn:feature_class":"P",
    "gn:feature_code":"PPL",
    "gn:name":"Laoguanwo",
    "gn:population":0,
    "gn:timezone":"Asia/Shanghai",
    "iso:country":"CN",
    "name:zho_x_preferred":[
        "\u8001\u89c2\u7a9d"
    ],
    "wof:name":"Laoguanwo",
    "wof:placetype":"locality"
},
  "geometry": {"coordinates":[111.79254,31.10308],"type":"Point"}
}