{
  "type": "Feature",
  "properties": {
    "gn:admin1_code":"32.0",
    "gn:asciiname":"Luoba",
    "gn:country_code":"CN",
    "gn:dem":417,
    "gn:feature_class":"P",
    "gn:feature_code":"PPL",
    "gn:name":"Luoba",
    "gn:population":0,
    "gn:timezone":"Asia/Shanghai",
    "iso:country":"CN",
    "name:ces_x_preferred":[
        "Luoba"
    ],
    "name:zho_x_preferred":[
        "\u7f57\u575d"
    ],
    "wof:name":"Luoba",
    "wof:placetype":"locality"
},
  "geometry": {"coordinates":[108.06399999999999,31.4747],"type":"Point"}
}