{
  "type": "Feature",
  "properties": {
    "gn:admin1_code":"30.0",
    "gn:asciiname":"Zhen'an",
    "gn:country_code":"CN",
    "gn:dem":111,
    "gn:feature_class":"P",
    "gn:feature_code":"PPL",
    "gn:name":"Zhen\u2019an",
    "gn:population":0,
    "gn:timezone":"Asia/Shanghai",
    "iso:country":"CN",
    "name:zho_x_preferred":[
        "\u9547\u5b89"
    ],
    "name:zho_x_variant":[
        "Zhen\u2019an"
    ],
    "wof:name":"Zhen'an",
    "wof:placetype":"locality"
},
  "geometry": {"coordinates":[111.84793000000001,22.77559],"type":"Point"}
}