{
  "type": "Feature",
  "properties": {
    "gn:admin1_code":"10.0",
    "gn:asciiname":"Lugezhuang",
    "gn:country_code":"CN",
    "gn:dem":18,
    "gn:feature_class":"P",
    "gn:feature_code":"PPL",
    "gn:name":"Lugezhuang",
    "gn:population":0,
    "gn:timezone":"Asia/Shanghai",
    "iso:country":"CN",
    "name:zho_x_preferred":[
        "\u9c81\u5404\u5e84"
    ],
    "wof:name":"Lugezhuang",
    "wof:placetype":"locality"
},
  "geometry": {"coordinates":[117.96969,39.65547],"type":"Point"}
}