{
  "type": "Feature",
  "properties": {
    "gn:admin1_code":"0.0",
    "gn:asciiname":"Jinma",
    "gn:country_code":"CN",
    "gn:dem":515,
    "gn:feature_class":"P",
    "gn:feature_code":"PPL",
    "gn:name":"Jinma",
    "gn:population":0,
    "gn:timezone":"Asia/Shanghai",
    "iso:country":"CN",
    "name:zho_x_preferred":[
        "\u91d1\u9a6c"
    ],
    "wof:name":"Jinma",
    "wof:placetype":"locality"
},
  "geometry": {"coordinates":[103.80994,30.62601],"type":"Point"}
}