{
  "type": "Feature",
  "properties": {
    "gn:admin1_code":"5.0",
    "gn:asciiname":"Qubin Weizi",
    "gn:country_code":"CN",
    "gn:dem":135,
    "gn:feature_class":"P",
    "gn:feature_code":"PPL",
    "gn:name":"Qubin Weizi",
    "gn:population":0,
    "gn:timezone":"Asia/Shanghai",
    "iso:country":"CN",
    "name:zho_x_preferred":[
        "\u66f2\u5f6c\u56f4\u5b50"
    ],
    "wof:name":"Qubin Weizi",
    "wof:placetype":"locality"
},
  "geometry": {"coordinates":[124.71602,45.04975],"type":"Point"}
}