{
  "type": "Feature",
  "properties": {
    "gn:admin1_code":"16.0",
    "gn:asciiname":"Neimeng",
    "gn:country_code":"CN",
    "gn:dem":244,
    "gn:feature_class":"P",
    "gn:feature_code":"PPL",
    "gn:name":"Neimeng",
    "gn:population":0,
    "gn:timezone":"Asia/Shanghai",
    "iso:country":"CN",
    "name:zho_x_preferred":[
        "\u5185\u8499"
    ],
    "wof:name":"Neimeng",
    "wof:placetype":"locality"
},
  "geometry": {"coordinates":[108.44499999999999,24.072],"type":"Point"}
}