{
  "type": "Feature",
  "properties": {
    "gn:admin1_code":"3",
    "gn:asciiname":"Chuzhou",
    "gn:country_code":"CN",
    "gn:dem":363,
    "gn:feature_class":"P",
    "gn:feature_code":"PPL",
    "gn:name":"Chuzhou",
    "gn:population":0,
    "gn:timezone":"Asia/Shanghai",
    "iso:country":"CN",
    "name:zho_x_preferred":[
        "\u6ec1\u6d32"
    ],
    "wof:name":"Chuzhou",
    "wof:placetype":"locality"
},
  "geometry": {"coordinates":[114.13299000000001,26.33388],"type":"Point"}
}