{
  "type": "Feature",
  "properties": {
    "gn:admin1_code":"3",
    "gn:asciiname":"Chuzhou",
    "gn:country_code":"CN",
    "gn:dem":363,
    "gn:feature_class":"P",
    "gn:feature_code":"PPL",
    "gn:name":"Chuzhou",
    "gn:population":0,
    "gn:timezone":"Asia/Shanghai",
    "iso:country":"CN",
    "name:afr_x_preferred":[
        "Chuzhou"
    ],
    "name:ara_x_preferred":[
        "\u0634\u0648\u0632\u0648"
    ],
    "name:bre_x_preferred":[
        "Chuzhou"
    ],
    "name:bul_x_preferred":[
        "\u0427\u0443\u0434\u0436\u043e\u0443"
    ],
    "name:cdo_x_preferred":[
        "D\u1e73\u0300-ci\u016d"
    ],
    "name:ceb_x_preferred":[
        "Chuzhou Shi"
    ],
    "name:ces_x_preferred":[
        "\u010cchu-\u010dou"
    ],
    "name:cym_x_preferred":[
        "Chuzhou"
    ],
    "name:dan_x_preferred":[
        "Chuzhou"
    ],
    "name:deu_x_preferred":[
        "Chuzhou"
    ],
    "name:eus_x_preferred":[
        "Chuzhou"
    ],
    "name:fas_x_preferred":[
        "\u0686\u0627\u062c\u0648\u0627"
    ],
    "name:fin_x_preferred":[
        "Chuzhou"
    ],
    "name:fra_x_preferred":[
        "Chuzhou"
    ],
    "name:hye_x_preferred":[
        "\u0549\u0578\u0582\u0579\u056a\u0578\u0578\u0582"
    ],
    "name:ita_x_preferred":[
        "Chuzhou"
    ],
    "name:jpn_x_preferred":[
        "\u30b8\u30e7\u5dde\u5e02"
    ],
    "name:kik_x_preferred":[
        "Chuzhou"
    ],
    "name:kor_x_preferred":[
        "\ucd94\uc800\uc6b0\uc2dc"
    ],
    "name:mlg_x_preferred":[
        "Chuzhou"
    ],
    "name:nld_x_preferred":[
        "Chuzhou"
    ],
    "name:nno_x_preferred":[
        "Chuzhou"
    ],
    "name:nor_x_preferred":[
        "Chuzhou"
    ],
    "name:pam_x_preferred":[
        "Chuzhou"
    ],
    "name:pnb_x_preferred":[
        "\u0686\u0648\u0698\u0648\u0624"
    ],
    "name:pol_x_preferred":[
        "Chuzhou"
    ],
    "name:por_x_preferred":[
        "Chuzhou"
    ],
    "name:rus_x_preferred":[
        "\u0427\u0443\u0447\u0436\u043e\u0443"
    ],
    "name:spa_x_preferred":[
        "Chuzhou"
    ],
    "name:srp_x_preferred":[
        "\u0427\u0443\u045f\u043e\u0443"
    ],
    "name:swe_x_preferred":[
        "Chuzhou"
    ],
    "name:tgl_x_preferred":[
        "Chuzhou"
    ],
    "name:tur_x_preferred":[
        "Chuzhou"
    ],
    "name:uig_x_preferred":[
        "Chuju shehiri"
    ],
    "name:urd_x_preferred":[
        "\u0686\u0648\u0698\u0648\u0648"
    ],
    "name:vie_x_preferred":[
        "Tr\u1eeb Ch\u00e2u"
    ],
    "name:war_x_preferred":[
        "Chuzhou"
    ],
    "name:wuu_x_preferred":[
        "\u6ec1\u5dde\u5e02"
    ],
    "name:zho_x_preferred":[
        "\u6ec1\u6d32"
    ],
    "name:zho_x_variant":[
        "\u6ec1\u5dde\u5e02"
    ],
    "wof:name":"Chuzhou",
    "wof:placetype":"locality"
},
  "geometry": {"coordinates":[114.13299000000001,26.33388],"type":"Point"}
}