{
  "type": "Feature",
  "properties": {
    "gn:admin1_code":"8.0",
    "gn:asciiname":"Mintaicun",
    "gn:country_code":"CN",
    "gn:dem":157,
    "gn:feature_class":"P",
    "gn:feature_code":"PPL",
    "gn:name":"Mintaicun",
    "gn:population":0,
    "gn:timezone":"Asia/Shanghai",
    "iso:country":"CN",
    "name:zho_x_preferred":[
        "\u6c11\u592a\u6751"
    ],
    "wof:name":"Mintaicun",
    "wof:placetype":"locality"
},
  "geometry": {"coordinates":[130.35706000000002,45.98125],"type":"Point"}
}