{
  "type": "Feature",
  "properties": {
    "gn:admin1_code":"32.0",
    "gn:asciiname":"Suojiagou",
    "gn:country_code":"CN",
    "gn:dem":339,
    "gn:feature_class":"P",
    "gn:feature_code":"PPL",
    "gn:name":"Suojiagou",
    "gn:population":0,
    "gn:timezone":"Asia/Shanghai",
    "iso:country":"CN",
    "name:zho_x_preferred":[
        "\u7d22\u5bb6\u6c9f"
    ],
    "wof:name":"Suojiagou",
    "wof:placetype":"locality"
},
  "geometry": {"coordinates":[106.018,30.6133],"type":"Point"}
}