{
  "type": "Feature",
  "properties": {
    "gn:admin1_code":"14.0",
    "gn:asciiname":"Manqinzhongcuo",
    "gn:country_code":"CN",
    "gn:dem":4167,
    "gn:feature_class":"P",
    "gn:feature_code":"PPL",
    "gn:name":"Manqinzhongcuo",
    "gn:population":0,
    "gn:timezone":"Asia/Urumqi",
    "iso:country":"CN",
    "name:zho_x_preferred":[
        "\u6ee1\u4eb2\u91cd\u9519"
    ],
    "wof:name":"Manqinzhongcuo",
    "wof:placetype":"locality"
},
  "geometry": {"coordinates":[98.06855,31.59313],"type":"Point"}
}