{
  "type": "Feature",
  "properties": {
    "gn:admin1_code":"26.0",
    "gn:asciiname":"Bianfangjie",
    "gn:country_code":"CN",
    "gn:dem":1181,
    "gn:feature_class":"P",
    "gn:feature_code":"PPL",
    "gn:name":"Bianfangjie",
    "gn:population":0,
    "gn:timezone":"Asia/Shanghai",
    "iso:country":"CN",
    "name:und_x_variant":[
        "\u535e\u623f\u8857"
    ],
    "wof:name":"Bianfangjie",
    "wof:placetype":"locality"
},
  "geometry": {"coordinates":[109.48486,34.02235],"type":"Point"}
}