{
  "type": "Feature",
  "properties": {
    "gn:admin1_code":"14",
    "gn:asciiname":"Codoi",
    "gn:country_code":"CN",
    "gn:dem":3765,
    "gn:feature_class":"P",
    "gn:feature_code":"PPL",
    "gn:name":"Codoi",
    "gn:population":0,
    "gn:timezone":"Asia/Urumqi",
    "iso:country":"CN",
    "name:bod_x_preferred":[
        "\u0f58\u0f5a\u0f7c\u0f0b\u0f62\u0fa1\u0f7c\u0f63"
    ],
    "name:und_x_variant":[
        "Zedui"
    ],
    "name:zho_x_preferred":[
        "\u63aa\u5806"
    ],
    "wof:name":"Codoi",
    "wof:placetype":"locality"
},
  "geometry": {"coordinates":[92.0765,29.12817],"type":"Point"}
}