{
  "type": "Feature",
  "properties": {
    "gn:admin1_code":"04",
    "gn:asciiname":"Fanji",
    "gn:cc2":"CN",
    "gn:country_code":"CN",
    "gn:dem":6,
    "gn:feature_class":"P",
    "gn:feature_code":"PPL",
    "gn:name":"Fanji",
    "gn:population":0,
    "gn:timezone":"Asia/Shanghai",
    "iso:country":"CN",
    "name:und_x_variant":[
        "Fan-chia-chi",
        "Fan-chi",
        "Fanji"
    ],
    "wof:name":"Fanji",
    "wof:placetype":"locality"
},
  "geometry": {"coordinates":[119.06667,33.38333],"type":"Point"}
}