{
  "type": "Feature",
  "properties": {
    "gn:admin1_code":"20.0",
    "gn:asciiname":"Harechu",
    "gn:country_code":"CN",
    "gn:dem":301,
    "gn:feature_class":"P",
    "gn:feature_code":"PPL",
    "gn:name":"Harechu",
    "gn:population":0,
    "gn:timezone":"Asia/Shanghai",
    "iso:country":"CN",
    "name:zho_x_preferred":[
        "\u54c8\u70ed\u695a"
    ],
    "wof:name":"Harechu",
    "wof:placetype":"locality"
},
  "geometry": {"coordinates":[123.83719000000001,48.74919000000001],"type":"Point"}
}