{
  "type": "Feature",
  "properties": {
    "gn:admin1_code":"3",
    "gn:asciiname":"Wenpai",
    "gn:country_code":"CN",
    "gn:dem":389,
    "gn:feature_class":"P",
    "gn:feature_code":"PPL",
    "gn:name":"Wenpai",
    "gn:population":0,
    "gn:timezone":"Asia/Shanghai",
    "iso:country":"CN",
    "name:zho_x_preferred":[
        "\u6e29\u6392"
    ],
    "wof:name":"Wenpai",
    "wof:placetype":"locality"
},
  "geometry": {"coordinates":[114.324,25.5317],"type":"Point"}
}