{
  "type": "Feature",
  "properties": {
    "gn:admin1_code":"30",
    "gn:asciiname":"Kuanglongba",
    "gn:country_code":"CN",
    "gn:dem":532,
    "gn:feature_class":"P",
    "gn:feature_code":"PPL",
    "gn:name":"Kuanglongba",
    "gn:population":0,
    "gn:timezone":"Asia/Shanghai",
    "iso:country":"CN",
    "name:zho_x_preferred":[
        "\u77ff\u9686\u575d"
    ],
    "wof:name":"Kuanglongba",
    "wof:placetype":"locality"
},
  "geometry": {"coordinates":[115.53403,23.39705],"type":"Point"}
}