{
  "type": "Feature",
  "properties": {
    "gn:admin1_code":"6.0",
    "gn:asciiname":"Xiangka Ruwa",
    "gn:country_code":"CN",
    "gn:dem":3878,
    "gn:feature_class":"P",
    "gn:feature_code":"PPL",
    "gn:name":"Xiangka Ruwa",
    "gn:population":0,
    "gn:timezone":"Asia/Urumqi",
    "iso:country":"CN",
    "name:zho_x_preferred":[
        "\u9999\u5580\u5982\u74e6"
    ],
    "wof:name":"Xiangka Ruwa",
    "wof:placetype":"locality"
},
  "geometry": {"coordinates":[96.68241999999999,33.55548],"type":"Point"}
}