{
  "type": "Feature",
  "properties": {
    "gn:admin1_code":"29.0",
    "gn:asciiname":"Taoziba",
    "gn:country_code":"CN",
    "gn:dem":837,
    "gn:feature_class":"P",
    "gn:feature_code":"PPL",
    "gn:name":"Taoziba",
    "gn:population":0,
    "gn:timezone":"Asia/Shanghai",
    "iso:country":"CN",
    "name:zho_x_preferred":[
        "\u6843\u5b50\u575d"
    ],
    "wof:name":"Taoziba",
    "wof:placetype":"locality"
},
  "geometry": {"coordinates":[104.267,28.1576],"type":"Point"}
}