{
  "type": "Feature",
  "properties": {
    "gn:admin1_code":"30",
    "gn:asciiname":"Zhongxintang",
    "gn:country_code":"CN",
    "gn:dem":333,
    "gn:feature_class":"P",
    "gn:feature_code":"PPL",
    "gn:name":"Zhongxintang",
    "gn:population":0,
    "gn:timezone":"Asia/Shanghai",
    "iso:country":"CN",
    "name:zho_x_preferred":[
        "\u4e2d\u5fc3\u5858"
    ],
    "wof:name":"Zhongxintang",
    "wof:placetype":"locality"
},
  "geometry": {"coordinates":[115.79142,24.38477],"type":"Point"}
}