{
  "type": "Feature",
  "properties": {
    "gn:admin1_code":"15.0",
    "gn:asciiname":"Qianzhuang",
    "gn:country_code":"CN",
    "gn:dem":2383,
    "gn:feature_class":"P",
    "gn:feature_code":"PPL",
    "gn:name":"Qianzhuang",
    "gn:population":0,
    "gn:timezone":"Asia/Shanghai",
    "iso:country":"CN",
    "name:zho_x_preferred":[
        "\u524d\u5e84"
    ],
    "wof:name":"Qianzhuang",
    "wof:placetype":"locality"
},
  "geometry": {"coordinates":[103.393,35.8939],"type":"Point"}
}