{
  "type": "Feature",
  "properties": {
    "gn:admin1_code":"16.0",
    "gn:asciiname":"Shishen",
    "gn:country_code":"CN",
    "gn:dem":429,
    "gn:feature_class":"P",
    "gn:feature_code":"PPL",
    "gn:name":"Shishen",
    "gn:population":0,
    "gn:timezone":"Asia/Shanghai",
    "iso:country":"CN",
    "name:zho_x_preferred":[
        "\u65f6\u4f38"
    ],
    "wof:name":"Shishen",
    "wof:placetype":"locality"
},
  "geometry": {"coordinates":[107.349,23.8061],"type":"Point"}
}