{
  "type": "Feature",
  "properties": {
    "gn:admin1_code":"26.0",
    "gn:asciiname":"Wayaogou",
    "gn:country_code":"CN",
    "gn:dem":653,
    "gn:feature_class":"P",
    "gn:feature_code":"PPL",
    "gn:name":"Wayaogou",
    "gn:population":0,
    "gn:timezone":"Asia/Shanghai",
    "iso:country":"CN",
    "name:und_x_variant":[
        "\u74e6\u7a91\u6c9f"
    ],
    "wof:name":"Wayaogou",
    "wof:placetype":"locality"
},
  "geometry": {"coordinates":[106.1378,33.26672],"type":"Point"}
}