{
  "type": "Feature",
  "properties": {
    "gn:admin1_code":"1.0",
    "gn:asciiname":"Ruancun",
    "gn:country_code":"CN",
    "gn:dem":6,
    "gn:feature_class":"P",
    "gn:feature_code":"PPL",
    "gn:name":"Ruancun",
    "gn:population":0,
    "gn:timezone":"Asia/Shanghai",
    "iso:country":"CN",
    "name:zho_x_preferred":[
        "\u962e\u6751"
    ],
    "wof:name":"Ruancun",
    "wof:placetype":"locality"
},
  "geometry": {"coordinates":[118.75118000000001,31.24118],"type":"Point"}
}