{
  "type": "Feature",
  "properties": {
    "gn:admin1_code":"02",
    "gn:asciiname":"Shangcaotian",
    "gn:cc2":"CN",
    "gn:country_code":"CN",
    "gn:dem":6,
    "gn:feature_class":"P",
    "gn:feature_code":"PPL",
    "gn:name":"Shangcaotian",
    "gn:population":0,
    "gn:timezone":"Asia/Shanghai",
    "iso:country":"CN",
    "name:zho_x_preferred":[
        "T\u2019s\u2019ao-t\u2019ien"
    ],
    "wof:name":"Shangcaotian",
    "wof:placetype":"locality"
},
  "geometry": {"coordinates":[121.58917,28.32944],"type":"Point"}
}