{
  "type": "Feature",
  "properties": {
    "gn:admin1_code":"11.0",
    "gn:asciiname":"Tangtouli",
    "gn:country_code":"CN",
    "gn:dem":601,
    "gn:feature_class":"P",
    "gn:feature_code":"PPL",
    "gn:name":"Tangtouli",
    "gn:population":0,
    "gn:timezone":"Asia/Shanghai",
    "iso:country":"CN",
    "name:zho_x_preferred":[
        "\u5858\u5934\u91cc"
    ],
    "wof:name":"Tangtouli",
    "wof:placetype":"locality"
},
  "geometry": {"coordinates":[114.16019,26.17772],"type":"Point"}
}