{
  "type": "Feature",
  "properties": {
    "gn:admin1_code":"10.0",
    "gn:asciiname":"Beishi",
    "gn:country_code":"CN",
    "gn:dem":26,
    "gn:feature_class":"P",
    "gn:feature_code":"PPL",
    "gn:name":"Beishi",
    "gn:population":0,
    "gn:timezone":"Asia/Shanghai",
    "iso:country":"CN",
    "name:ceb_x_preferred":[
        "Beishi"
    ],
    "name:deu_x_preferred":[
        "Beishi"
    ],
    "name:swe_x_preferred":[
        "Beishi"
    ],
    "name:zho_x_preferred":[
        "\u5317\u53f2"
    ],
    "wof:name":"Beishi",
    "wof:placetype":"locality"
},
  "geometry": {"coordinates":[115.63800000000001,38.0839],"type":"Point"}
}