{
  "type": "Feature",
  "properties": {
    "gn:admin1_code":"32.0",
    "gn:asciiname":"Shuangchi",
    "gn:country_code":"CN",
    "gn:dem":322,
    "gn:feature_class":"P",
    "gn:feature_code":"PPL",
    "gn:name":"Shuangchi",
    "gn:population":0,
    "gn:timezone":"Asia/Shanghai",
    "iso:country":"CN",
    "name:zho_x_preferred":[
        "\u53cc\u6c60"
    ],
    "wof:name":"Shuangchi",
    "wof:placetype":"locality"
},
  "geometry": {"coordinates":[105.22799999999999,30.5757],"type":"Point"}
}