{
  "type": "Feature",
  "properties": {
    "gn:admin1_code":"16.0",
    "gn:asciiname":"Zhongdeshi",
    "gn:country_code":"CN",
    "gn:dem":176,
    "gn:feature_class":"P",
    "gn:feature_code":"PPL",
    "gn:name":"Zhongdeshi",
    "gn:population":0,
    "gn:timezone":"Asia/Shanghai",
    "iso:country":"CN",
    "name:zho_x_preferred":[
        "\u4e2d\u5fb7\u65f6"
    ],
    "wof:name":"Zhongdeshi",
    "wof:placetype":"locality"
},
  "geometry": {"coordinates":[108.691,23.66800000000001],"type":"Point"}
}