{
  "type": "Feature",
  "properties": {
    "gn:admin1_code":"12.0",
    "gn:asciiname":"Majia",
    "gn:country_code":"CN",
    "gn:dem":52,
    "gn:feature_class":"P",
    "gn:feature_code":"PPL",
    "gn:name":"Majia",
    "gn:population":0,
    "gn:timezone":"Asia/Shanghai",
    "iso:country":"CN",
    "name:zho_x_preferred":[
        "Majia"
    ],
    "name:zho_x_variant":[
        "\u9a6c\u5bb6"
    ],
    "wof:name":"Majia",
    "wof:placetype":"locality"
},
  "geometry": {"coordinates":[114.46066999999999,29.99855],"type":"Point"}
}