{
  "type": "Feature",
  "properties": {
    "gn:admin1_code":"20.0",
    "gn:asciiname":"Dawuhao",
    "gn:country_code":"CN",
    "gn:dem":1350,
    "gn:feature_class":"P",
    "gn:feature_code":"PPL",
    "gn:name":"Dawuhao",
    "gn:population":0,
    "gn:timezone":"Asia/Shanghai",
    "iso:country":"CN",
    "name:und_x_variant":[
        "\u5927\u4e94\u53f7"
    ],
    "wof:name":"Dawuhao",
    "wof:placetype":"locality"
},
  "geometry": {"coordinates":[113.61028,40.84458],"type":"Point"}
}