{
  "type": "Feature",
  "properties": {
    "gn:admin1_code":"4.0",
    "gn:asciiname":"Beixinzhuang",
    "gn:country_code":"CN",
    "gn:dem":2,
    "gn:feature_class":"P",
    "gn:feature_code":"PPL",
    "gn:name":"Beixinzhuang",
    "gn:population":0,
    "gn:timezone":"Asia/Shanghai",
    "iso:country":"CN",
    "name:und_x_variant":[
        "\u5317\u65b0\u5e84"
    ],
    "name:zho_x_preferred":[
        "\u5317\u65b0\u5e84"
    ],
    "wof:name":"Beixinzhuang",
    "wof:placetype":"locality"
},
  "geometry": {"coordinates":[120.07209,33.11993],"type":"Point"}
}