{
  "type": "Feature",
  "properties": {
    "gn:admin1_code":"5.0",
    "gn:asciiname":"Ji'anxian Renao Linchang",
    "gn:country_code":"CN",
    "gn:dem":733,
    "gn:feature_class":"P",
    "gn:feature_code":"PPLF",
    "gn:name":"Ji\u2019anxian Renao Linchang",
    "gn:population":0,
    "gn:timezone":"Asia/Shanghai",
    "iso:country":"CN",
    "name:und_x_variant":[
        "Ji\u2019anxian Renao Linchang",
        "\u96c6\u5b89\u53bf\u70ed\u95f9\u6797\u573a"
    ],
    "wof:name":"Ji'anxian Renao Linchang",
    "wof:placetype":"locality"
},
  "geometry": {"coordinates":[126.11123000000001,41.38535],"type":"Point"}
}