{
  "type": "Feature",
  "properties": {
    "gn:admin1_code":"33.0",
    "gn:asciiname":"Lijia Yuanzi",
    "gn:country_code":"CN",
    "gn:dem":453,
    "gn:feature_class":"P",
    "gn:feature_code":"PPL",
    "gn:name":"Lijia Yuanzi",
    "gn:population":0,
    "gn:timezone":"Asia/Shanghai",
    "iso:country":"CN",
    "name:zho_x_preferred":[
        "\u674e\u5bb6\u9662\u5b50"
    ],
    "wof:name":"Lijia Yuanzi",
    "wof:placetype":"locality"
},
  "geometry": {"coordinates":[107.75393,30.65754],"type":"Point"}
}