{
  "type": "Feature",
  "properties": {
    "gn:admin1_code":"24",
    "gn:asciiname":"Beiwangzhan",
    "gn:country_code":"CN",
    "gn:dem":830,
    "gn:feature_class":"P",
    "gn:feature_code":"PPL",
    "gn:name":"Beiwangzhan",
    "gn:population":0,
    "gn:timezone":"Asia/Shanghai",
    "iso:country":"CN",
    "name:und_x_variant":[
        "Pei-wang-chan",
        "Beiwangzhan"
    ],
    "name:zho_x_preferred":[
        "\u5317\u6c6a\u6e5b"
    ],
    "wof:name":"Beiwangzhan",
    "wof:placetype":"locality"
},
  "geometry": {"coordinates":[112.26888999999998,37.20791],"type":"Point"}
}