{
  "type": "Feature",
  "properties": {
    "gn:admin1_code":"3.0",
    "gn:asciiname":"Guifeng",
    "gn:country_code":"CN",
    "gn:dem":348,
    "gn:feature_class":"P",
    "gn:feature_code":"PPL",
    "gn:name":"Guifeng",
    "gn:population":0,
    "gn:timezone":"Asia/Shanghai",
    "iso:country":"CN",
    "name:und_x_variant":[
        "\u6842\u4e30"
    ],
    "wof:name":"Guifeng",
    "wof:placetype":"locality"
},
  "geometry": {"coordinates":[114.47729,28.52047],"type":"Point"}
}