{
  "type": "Feature",
  "properties": {
    "gn:admin1_code":"30",
    "gn:asciiname":"Xinpuzai",
    "gn:country_code":"CN",
    "gn:dem":41,
    "gn:feature_class":"P",
    "gn:feature_code":"PPL",
    "gn:name":"Xinpuzai",
    "gn:population":0,
    "gn:timezone":"Asia/Shanghai",
    "iso:country":"CN",
    "name:zho_x_preferred":[
        "\u65b0\u57d4\u4ed4"
    ],
    "wof:name":"Xinpuzai",
    "wof:placetype":"locality"
},
  "geometry": {"coordinates":[115.60028,23.1025],"type":"Point"}
}