{
  "type": "Feature",
  "properties": {
    "gn:admin1_code":"10.0",
    "gn:asciiname":"Xiaosongzhuang",
    "gn:country_code":"CN",
    "gn:dem":14,
    "gn:feature_class":"P",
    "gn:feature_code":"PPL",
    "gn:name":"Xiaosongzhuang",
    "gn:population":0,
    "gn:timezone":"Asia/Shanghai",
    "iso:country":"CN",
    "name:zho_x_preferred":[
        "\u5c0f\u5b8b\u5e84"
    ],
    "wof:name":"Xiaosongzhuang",
    "wof:placetype":"locality"
},
  "geometry": {"coordinates":[116.51609999999999,37.95812],"type":"Point"}
}