{
  "type": "Feature",
  "properties": {
    "gn:admin1_code":"9",
    "gn:asciiname":"Qiandiwan",
    "gn:country_code":"CN",
    "gn:dem":44,
    "gn:feature_class":"P",
    "gn:feature_code":"PPL",
    "gn:name":"Qiandiwan",
    "gn:population":0,
    "gn:timezone":"Asia/Shanghai",
    "iso:country":"CN",
    "name:zho_x_preferred":[
        "\u524d\u5824\u6e7e"
    ],
    "wof:name":"Qiandiwan",
    "wof:placetype":"locality"
},
  "geometry": {"coordinates":[116.49299999999999,34.2784],"type":"Point"}
}