{
  "type": "Feature",
  "properties": {
    "gn:admin1_code":"11.0",
    "gn:asciiname":"Yangzitang",
    "gn:country_code":"CN",
    "gn:dem":148,
    "gn:feature_class":"P",
    "gn:feature_code":"PPL",
    "gn:name":"Yangzitang",
    "gn:population":0,
    "gn:timezone":"Asia/Shanghai",
    "iso:country":"CN",
    "name:zho_x_preferred":[
        "\u6768\u5b50\u5858"
    ],
    "wof:name":"Yangzitang",
    "wof:placetype":"locality"
},
  "geometry": {"coordinates":[112.21176,28.01364],"type":"Point"}
}