{
  "type": "Feature",
  "properties": {
    "gn:admin1_code":"30.0",
    "gn:asciiname":"Zhangbeishang",
    "gn:country_code":"CN",
    "gn:dem":23,
    "gn:feature_class":"P",
    "gn:feature_code":"PPL",
    "gn:name":"Zhangbeishang",
    "gn:population":0,
    "gn:timezone":"Asia/Shanghai",
    "iso:country":"CN",
    "name:zho_x_preferred":[
        "\u748b\u80cc\u4e0a"
    ],
    "wof:name":"Zhangbeishang",
    "wof:placetype":"locality"
},
  "geometry": {"coordinates":[112.8556,22.29625],"type":"Point"}
}