{
  "type": "Feature",
  "properties": {
    "gn:admin1_code":"9.0",
    "gn:asciiname":"Yingwangcun",
    "gn:country_code":"CN",
    "gn:dem":63,
    "gn:feature_class":"P",
    "gn:feature_code":"PPL",
    "gn:name":"Yingwangcun",
    "gn:population":0,
    "gn:timezone":"Asia/Shanghai",
    "iso:country":"CN",
    "name:zho_x_preferred":[
        "\u82f1\u738b\u6751"
    ],
    "wof:name":"Yingwangcun",
    "wof:placetype":"locality"
},
  "geometry": {"coordinates":[113.99527,33.85126],"type":"Point"}
}