{
  "type": "Feature",
  "properties": {
    "gn:admin1_code":"8.0",
    "gn:asciiname":"Huamucun",
    "gn:country_code":"CN",
    "gn:dem":213,
    "gn:feature_class":"P",
    "gn:feature_code":"PPL",
    "gn:name":"Huamucun",
    "gn:population":0,
    "gn:timezone":"Asia/Shanghai",
    "iso:country":"CN",
    "name:zho_x_preferred":[
        "\u6866\u6728\u6751"
    ],
    "wof:name":"Huamucun",
    "wof:placetype":"locality"
},
  "geometry": {"coordinates":[124.85781,49.14095],"type":"Point"}
}