{
  "type": "Feature",
  "properties": {
    "gn:admin1_code":"11.0",
    "gn:asciiname":"Pingshiling",
    "gn:country_code":"CN",
    "gn:dem":161,
    "gn:feature_class":"P",
    "gn:feature_code":"PPL",
    "gn:name":"Pingshiling",
    "gn:population":0,
    "gn:timezone":"Asia/Shanghai",
    "iso:country":"CN",
    "name:zho_x_preferred":[
        "\u576a\u77f3\u5cad"
    ],
    "wof:name":"Pingshiling",
    "wof:placetype":"locality"
},
  "geometry": {"coordinates":[113.19914,26.62552],"type":"Point"}
}