{
  "type": "Feature",
  "properties": {
    "gn:admin1_code":"11",
    "gn:asciiname":"Shuilidang",
    "gn:country_code":"CN",
    "gn:dem":1332,
    "gn:feature_class":"P",
    "gn:feature_code":"PPL",
    "gn:name":"Shuilidang",
    "gn:population":0,
    "gn:timezone":"Asia/Shanghai",
    "iso:country":"CN",
    "name:zho_x_preferred":[
        "\u6c34\u6817\u51fc"
    ],
    "wof:name":"Shuilidang",
    "wof:placetype":"locality"
},
  "geometry": {"coordinates":[110.64528,27.55111],"type":"Point"}
}