{
  "type": "Feature",
  "properties": {
    "gn:admin1_code":"18",
    "gn:asciiname":"Malaoyan",
    "gn:country_code":"CN",
    "gn:dem":1055,
    "gn:feature_class":"P",
    "gn:feature_code":"PPL",
    "gn:name":"Malaoyan",
    "gn:population":0,
    "gn:timezone":"Asia/Shanghai",
    "iso:country":"CN",
    "name:zho_x_preferred":[
        "\u9a6c\u8001\u5ca9"
    ],
    "wof:name":"Malaoyan",
    "wof:placetype":"locality"
},
  "geometry": {"coordinates":[107.821,28.4769],"type":"Point"}
}