{
  "type": "Feature",
  "properties": {
    "gn:admin1_code":"8.0",
    "gn:asciiname":"Yingchunxiang Canchang",
    "gn:country_code":"CN",
    "gn:dem":244,
    "gn:feature_class":"P",
    "gn:feature_code":"PPLF",
    "gn:name":"Yingchunxiang Canchang",
    "gn:population":0,
    "gn:timezone":"Asia/Shanghai",
    "iso:country":"CN",
    "name:zho_x_preferred":[
        "\u8fce\u6625\u4e61\u53c2\u573a"
    ],
    "wof:name":"Yingchunxiang Canchang",
    "wof:placetype":"locality"
},
  "geometry": {"coordinates":[129.26065,47.32084],"type":"Point"}
}