{
  "type": "Feature",
  "properties": {
    "gn:admin1_code":"16",
    "gn:asciiname":"Banjia",
    "gn:country_code":"CN",
    "gn:dem":260,
    "gn:feature_class":"P",
    "gn:feature_code":"PPL",
    "gn:name":"Banjia",
    "gn:population":0,
    "gn:timezone":"Asia/Shanghai",
    "iso:country":"CN",
    "name:und_x_variant":[
        "Pan-chia",
        "Banjia"
    ],
    "name:zho_x_preferred":[
        "\u677f\u4ef7"
    ],
    "wof:name":"Banjia",
    "wof:placetype":"locality"
},
  "geometry": {"coordinates":[106.884,22.6818],"type":"Point"}
}