{
  "type": "Feature",
  "properties": {
    "gn:admin1_code":"32.0",
    "gn:asciiname":"Nie'erlaiji",
    "gn:country_code":"CN",
    "gn:dem":2617,
    "gn:feature_class":"P",
    "gn:feature_code":"PPL",
    "gn:name":"Nie\u2019erlaiji",
    "gn:population":0,
    "gn:timezone":"Asia/Shanghai",
    "iso:country":"CN",
    "name:und_x_variant":[
        "Nie\u2019erlaiji"
    ],
    "name:zho_x_preferred":[
        "\u6d85\u5c14\u6765\u53ca"
    ],
    "wof:name":"Nie'erlaiji",
    "wof:placetype":"locality"
},
  "geometry": {"coordinates":[102.85599999999999,27.662],"type":"Point"}
}