{
  "type": "Feature",
  "properties": {
    "gn:admin1_code":"2.0",
    "gn:asciiname":"Shiguqian",
    "gn:country_code":"CN",
    "gn:dem":147,
    "gn:feature_class":"P",
    "gn:feature_code":"PPL",
    "gn:name":"Shiguqian",
    "gn:population":0,
    "gn:timezone":"Asia/Shanghai",
    "iso:country":"CN",
    "name:zho_x_preferred":[
        "\u77f3\u8c37\u5811"
    ],
    "wof:name":"Shiguqian",
    "wof:placetype":"locality"
},
  "geometry": {"coordinates":[120.02646,28.28012],"type":"Point"}
}