{
  "type": "Feature",
  "properties": {
    "gn:admin1_code":"15.0",
    "gn:asciiname":"Jiangjuntai",
    "gn:cc2":"CN",
    "gn:country_code":"CN",
    "gn:dem":1964,
    "gn:feature_class":"P",
    "gn:feature_code":"PPL",
    "gn:name":"Jiangjuntai",
    "gn:population":0,
    "gn:timezone":"Asia/Urumqi",
    "iso:country":"CN",
    "name:und_x_variant":[
        "Chiang-ch\u00fcn-t\u2019ai",
        "Jiangjuntai"
    ],
    "wof:name":"Jiangjuntai",
    "wof:placetype":"locality"
},
  "geometry": {"coordinates":[96.93333,41.15],"type":"Point"}
}