{
  "type": "Feature",
  "properties": {
    "gn:admin1_code":"18",
    "gn:asciiname":"Bazhai",
    "gn:country_code":"CN",
    "gn:dem":610,
    "gn:feature_class":"P",
    "gn:feature_code":"PPL",
    "gn:name":"Bazhai",
    "gn:population":0,
    "gn:timezone":"Asia/Shanghai",
    "iso:country":"CN",
    "name:zho_x_preferred":[
        "\u628a\u5be8"
    ],
    "wof:name":"Bazhai",
    "wof:placetype":"locality"
},
  "geometry": {"coordinates":[106.52800000000001,25.3968],"type":"Point"}
}