{
  "type": "Feature",
  "properties": {
    "gn:admin1_code":"31",
    "gn:asciiname":"Shankou",
    "gn:country_code":"CN",
    "gn:dem":44,
    "gn:feature_class":"P",
    "gn:feature_code":"PPL",
    "gn:name":"Shankou",
    "gn:population":0,
    "gn:timezone":"Asia/Shanghai",
    "iso:country":"CN",
    "name:deu_x_preferred":[
        "Shankou"
    ],
    "name:und_x_variant":[
        "\u5c71\u53e3"
    ],
    "wof:name":"Shankou",
    "wof:placetype":"locality"
},
  "geometry": {"coordinates":[109.96597,19.69391],"type":"Point"}
}