{
  "type": "Feature",
  "properties": {
    "gn:admin1_code":"11.0",
    "gn:asciiname":"Zhemujiang",
    "gn:country_code":"CN",
    "gn:dem":120,
    "gn:feature_class":"P",
    "gn:feature_code":"PPL",
    "gn:name":"Zhemujiang",
    "gn:population":0,
    "gn:timezone":"Asia/Shanghai",
    "iso:country":"CN",
    "name:zho_x_preferred":[
        "\u67d8\u6728\u6c5f"
    ],
    "wof:name":"Zhemujiang",
    "wof:placetype":"locality"
},
  "geometry": {"coordinates":[113.2343,26.05402],"type":"Point"}
}