{
  "type": "Feature",
  "properties": {
    "gn:admin1_code":"14.0",
    "gn:asciiname":"Zonggo",
    "gn:country_code":"CN",
    "gn:dem":4917,
    "gn:feature_class":"P",
    "gn:feature_code":"PPL",
    "gn:name":"Zonggo",
    "gn:population":0,
    "gn:timezone":"Asia/Urumqi",
    "iso:country":"CN",
    "name:bod_x_preferred":[
        "Zonggo"
    ],
    "name:zho_x_preferred":[
        "Zongguo"
    ],
    "name:zho_x_variant":[
        "\u5b97\u679c",
        "Jiare Gongshe",
        "\u52a0\u60f9\u516c\u793e"
    ],
    "wof:name":"Zonggo",
    "wof:placetype":"locality"
},
  "geometry": {"coordinates":[94.601,30.801],"type":"Point"}
}