{
  "type": "Feature",
  "properties": {
    "gn:admin1_code":"07",
    "gn:asciiname":"Sanbu",
    "gn:country_code":"CN",
    "gn:dem":313,
    "gn:feature_class":"P",
    "gn:feature_code":"PPL",
    "gn:name":"Sanbu",
    "gn:population":0,
    "gn:timezone":"Asia/Shanghai",
    "iso:country":"CN",
    "name:und_x_variant":[
        "Ma-shan-pao",
        "Sanbu"
    ],
    "name:zho_x_preferred":[
        "\u4e09\u5821"
    ],
    "wof:name":"Sanbu",
    "wof:placetype":"locality"
},
  "geometry": {"coordinates":[116.79994000000001,24.89708],"type":"Point"}
}