{
  "type": "Feature",
  "properties": {
    "gn:admin1_code":"24.0",
    "gn:asciiname":"Ganhuidao",
    "gn:country_code":"CN",
    "gn:dem":1052,
    "gn:feature_class":"P",
    "gn:feature_code":"PPL",
    "gn:name":"Ganhuidao",
    "gn:population":0,
    "gn:timezone":"Asia/Shanghai",
    "iso:country":"CN",
    "name:zho_x_preferred":[
        "\u8d76\u4f1a\u9053"
    ],
    "wof:name":"Ganhuidao",
    "wof:placetype":"locality"
},
  "geometry": {"coordinates":[112.58908999999998,38.39457],"type":"Point"}
}