{
  "type": "Feature",
  "properties": {
    "gn:admin1_code":"30.0",
    "gn:asciiname":"Ruyi Xicun",
    "gn:country_code":"CN",
    "gn:dem":357,
    "gn:feature_class":"P",
    "gn:feature_code":"PPL",
    "gn:name":"Ruyi Xicun",
    "gn:population":0,
    "gn:timezone":"Asia/Shanghai",
    "iso:country":"CN",
    "name:zho_x_preferred":[
        "\u5982\u610f\u6eaa\u6751"
    ],
    "wof:name":"Ruyi Xicun",
    "wof:placetype":"locality"
},
  "geometry": {"coordinates":[116.70179,23.80618],"type":"Point"}
}