{
  "type": "Feature",
  "properties": {
    "gn:admin1_code":"19.0",
    "gn:asciiname":"Yandanpaocun",
    "gn:country_code":"CN",
    "gn:dem":80,
    "gn:feature_class":"P",
    "gn:feature_code":"PPL",
    "gn:name":"Yandanpaocun",
    "gn:population":0,
    "gn:timezone":"Asia/Shanghai",
    "iso:country":"CN",
    "name:zho_x_preferred":[
        "\u96c1\u86cb\u6ce1\u6751"
    ],
    "wof:name":"Yandanpaocun",
    "wof:placetype":"locality"
},
  "geometry": {"coordinates":[123.70099999999999,42.6579],"type":"Point"}
}