{
  "type": "Feature",
  "properties": {
    "gn:admin1_code":"15.0",
    "gn:asciiname":"Yuangudui",
    "gn:country_code":"CN",
    "gn:dem":2322,
    "gn:feature_class":"P",
    "gn:feature_code":"PPL",
    "gn:name":"Yuangudui",
    "gn:population":0,
    "gn:timezone":"Asia/Shanghai",
    "iso:country":"CN",
    "name:und_x_variant":[
        "\u56ed\u56fa\u5806"
    ],
    "wof:name":"Yuangudui",
    "wof:placetype":"locality"
},
  "geometry": {"coordinates":[104.50826000000001,34.63174],"type":"Point"}
}