{
  "type": "Feature",
  "properties": {
    "gn:admin1_code":"26.0",
    "gn:asciiname":"Erjiahe",
    "gn:country_code":"CN",
    "gn:dem":1283,
    "gn:feature_class":"P",
    "gn:feature_code":"PPL",
    "gn:name":"Erjiahe",
    "gn:population":0,
    "gn:timezone":"Asia/Shanghai",
    "iso:country":"CN",
    "name:zho_x_preferred":[
        "\u4e8c\u5bb6\u6cb3"
    ],
    "wof:name":"Erjiahe",
    "wof:placetype":"locality"
},
  "geometry": {"coordinates":[109.09774,36.76248],"type":"Point"}
}