{
  "type": "Feature",
  "properties": {
    "gn:admin1_code":"10.0",
    "gn:asciiname":"Zhangbianzhuang",
    "gn:country_code":"CN",
    "gn:dem":42,
    "gn:feature_class":"P",
    "gn:feature_code":"PPL",
    "gn:name":"Zhangbianzhuang",
    "gn:population":0,
    "gn:timezone":"Asia/Shanghai",
    "iso:country":"CN",
    "name:zho_x_preferred":[
        "\u5f20\u8fb9\u5e84"
    ],
    "wof:name":"Zhangbianzhuang",
    "wof:placetype":"locality"
},
  "geometry": {"coordinates":[118.66188,39.68106],"type":"Point"}
}