{
  "type": "Feature",
  "properties": {
    "gn:admin1_code":"10.0",
    "gn:asciiname":"Qianbaita",
    "gn:country_code":"CN",
    "gn:dem":114,
    "gn:feature_class":"P",
    "gn:feature_code":"PPL",
    "gn:name":"Qianbaita",
    "gn:population":0,
    "gn:timezone":"Asia/Shanghai",
    "iso:country":"CN",
    "name:zho_x_preferred":[
        "\u524d\u767d\u5854"
    ],
    "wof:name":"Qianbaita",
    "wof:placetype":"locality"
},
  "geometry": {"coordinates":[119.09759,39.94828],"type":"Point"}
}