{
  "type": "Feature",
  "properties": {
    "gn:admin1_code":"11.0",
    "gn:asciiname":"Shashi",
    "gn:country_code":"CN",
    "gn:dem":287,
    "gn:feature_class":"P",
    "gn:feature_code":"PPL",
    "gn:name":"Shashi",
    "gn:population":0,
    "gn:timezone":"Asia/Shanghai",
    "iso:country":"CN",
    "name:ceb_x_preferred":[
        "Shashi"
    ],
    "name:fra_x_preferred":[
        "Shashi"
    ],
    "name:swe_x_preferred":[
        "Shashi"
    ],
    "name:zho_x_preferred":[
        "\u6c99\u5e02"
    ],
    "wof:name":"Shashi",
    "wof:placetype":"locality"
},
  "geometry": {"coordinates":[112.54956,25.25631],"type":"Point"}
}