{
  "type": "Feature",
  "properties": {
    "gn:admin1_code":"05",
    "gn:asciiname":"San-tao-ling-tzu",
    "gn:country_code":"CN",
    "gn:dem":53,
    "gn:feature_class":"P",
    "gn:feature_code":"PPL",
    "gn:name":"San-tao-ling-tzu",
    "gn:population":0,
    "gn:timezone":"Asia/Shanghai",
    "iso:country":"CN",
    "wof:name":"San-tao-ling-tzu",
    "wof:placetype":"locality"
},
  "geometry": {"coordinates":[130.30916999999999,42.90222],"type":"Point"}
}