{
  "type": "Feature",
  "properties": {
    "gn:admin1_code":"4.0",
    "gn:asciiname":"Liulaozhuangcun",
    "gn:country_code":"CN",
    "gn:dem":10,
    "gn:feature_class":"P",
    "gn:feature_code":"PPL",
    "gn:name":"Liulaozhuangcun",
    "gn:population":0,
    "gn:timezone":"Asia/Shanghai",
    "iso:country":"CN",
    "name:zho_x_preferred":[
        "\u5218\u8001\u5e84\u6751"
    ],
    "wof:name":"Liulaozhuangcun",
    "wof:placetype":"locality"
},
  "geometry": {"coordinates":[118.97168000000001,33.81128],"type":"Point"}
}