{
  "type": "Feature",
  "properties": {
    "gn:admin1_code":"24.0",
    "gn:asciiname":"Yongqing",
    "gn:country_code":"CN",
    "gn:dem":607,
    "gn:feature_class":"P",
    "gn:feature_code":"PPL",
    "gn:name":"Yongqing",
    "gn:population":0,
    "gn:timezone":"Asia/Shanghai",
    "iso:country":"CN",
    "name:zho_x_preferred":[
        "\u6c38\u9752"
    ],
    "wof:name":"Yongqing",
    "wof:placetype":"locality"
},
  "geometry": {"coordinates":[111.38142000000001,35.50852000000001],"type":"Point"}
}