{
  "type": "Feature",
  "properties": {
    "gn:admin1_code":"24.0",
    "gn:asciiname":"Baicaowan",
    "gn:country_code":"CN",
    "gn:dem":1628,
    "gn:feature_class":"P",
    "gn:feature_code":"PPL",
    "gn:name":"Baicaowan",
    "gn:population":0,
    "gn:timezone":"Asia/Shanghai",
    "iso:country":"CN",
    "name:zho_x_preferred":[
        "\u767d\u8349\u6e7e"
    ],
    "wof:name":"Baicaowan",
    "wof:placetype":"locality"
},
  "geometry": {"coordinates":[113.93422,39.58353],"type":"Point"}
}