{
  "type": "Feature",
  "properties": {
    "gn:admin1_code":"26.0",
    "gn:asciiname":"Tuanluzigou",
    "gn:country_code":"CN",
    "gn:dem":1407,
    "gn:feature_class":"P",
    "gn:feature_code":"PPL",
    "gn:name":"Tuanluzigou",
    "gn:population":0,
    "gn:timezone":"Asia/Shanghai",
    "iso:country":"CN",
    "name:zho_x_preferred":[
        "\u56e2\u9a74\u5b50\u6c9f"
    ],
    "wof:name":"Tuanluzigou",
    "wof:placetype":"locality"
},
  "geometry": {"coordinates":[108.29441,36.93922],"type":"Point"}
}