{
  "type": "Feature",
  "properties": {
    "gn:admin1_code":"11.0",
    "gn:asciiname":"Niuzhitian",
    "gn:country_code":"CN",
    "gn:dem":337,
    "gn:feature_class":"P",
    "gn:feature_code":"PPL",
    "gn:name":"Niuzhitian",
    "gn:population":0,
    "gn:timezone":"Asia/Shanghai",
    "iso:country":"CN",
    "name:zho_x_preferred":[
        "\u725b\u8dbe\u7530"
    ],
    "wof:name":"Niuzhitian",
    "wof:placetype":"locality"
},
  "geometry": {"coordinates":[111.59875,24.94945],"type":"Point"}
}