{
  "type": "Feature",
  "properties": {
    "gn:admin1_code":"5.0",
    "gn:asciiname":"Qianda Fangzi",
    "gn:country_code":"CN",
    "gn:dem":310,
    "gn:feature_class":"P",
    "gn:feature_code":"PPL",
    "gn:name":"Qianda Fangzi",
    "gn:population":0,
    "gn:timezone":"Asia/Shanghai",
    "iso:country":"CN",
    "name:zho_x_preferred":[
        "\u94b1\u5927\u623f\u5b50"
    ],
    "wof:name":"Qianda Fangzi",
    "wof:placetype":"locality"
},
  "geometry": {"coordinates":[125.36736000000001,43.03039],"type":"Point"}
}