{
  "type": "Feature",
  "properties": {
    "gn:admin1_code":"16",
    "gn:asciiname":"Shangmeng",
    "gn:country_code":"CN",
    "gn:dem":727,
    "gn:feature_class":"P",
    "gn:feature_code":"PPL",
    "gn:name":"Shangmeng",
    "gn:population":0,
    "gn:timezone":"Asia/Shanghai",
    "iso:country":"CN",
    "name:zho_x_preferred":[
        "\u4e0a\u5b5f"
    ],
    "wof:name":"Shangmeng",
    "wof:placetype":"locality"
},
  "geometry": {"coordinates":[109.95999999999999,25.7189],"type":"Point"}
}