{
  "type": "Feature",
  "properties": {
    "gn:admin1_code":"33.0",
    "gn:asciiname":"Banpo",
    "gn:country_code":"CN",
    "gn:dem":469,
    "gn:feature_class":"P",
    "gn:feature_code":"PPL",
    "gn:name":"Banpo",
    "gn:population":0,
    "gn:timezone":"Asia/Shanghai",
    "iso:country":"CN",
    "name:zho_x_preferred":[
        "\u534a\u5761"
    ],
    "wof:name":"Banpo",
    "wof:placetype":"locality"
},
  "geometry": {"coordinates":[109.09178,29.1452],"type":"Point"}
}