{
  "type": "Feature",
  "properties": {
    "gn:admin1_code":"33.0",
    "gn:asciiname":"Banpo",
    "gn:country_code":"CN",
    "gn:dem":469,
    "gn:feature_class":"P",
    "gn:feature_code":"PPL",
    "gn:name":"Banpo",
    "gn:population":0,
    "gn:timezone":"Asia/Shanghai",
    "iso:country":"CN",
    "name:ceb_x_preferred":[
        "Banbo"
    ],
    "name:deu_x_preferred":[
        "Banpo-Siedlung"
    ],
    "name:epo_x_preferred":[
        "Banpo"
    ],
    "name:fas_x_preferred":[
        "\u0628\u0627\u0646\u067e\u0648"
    ],
    "name:fin_x_preferred":[
        "Banpo"
    ],
    "name:fra_x_preferred":[
        "Banpo"
    ],
    "name:ind_x_preferred":[
        "Banpo"
    ],
    "name:ita_x_preferred":[
        "Banpo"
    ],
    "name:jpn_x_preferred":[
        "\u534a\u5761\u907a\u8de1"
    ],
    "name:nor_x_preferred":[
        "Banpo"
    ],
    "name:pol_x_preferred":[
        "Banpo"
    ],
    "name:rus_x_preferred":[
        "\u0411\u0430\u043d\u044c\u043f\u043e"
    ],
    "name:spa_x_preferred":[
        "Banpo"
    ],
    "name:swe_x_preferred":[
        "Banpo"
    ],
    "name:zho_x_preferred":[
        "\u534a\u5761"
    ],
    "name:zho_x_variant":[
        "\u534a\u5761\u9057\u5740"
    ],
    "wof:name":"Banpo",
    "wof:placetype":"locality"
},
  "geometry": {"coordinates":[109.09178,29.1452],"type":"Point"}
}