{
  "type": "Feature",
  "properties": {
    "gn:admin1_code":"7.0",
    "gn:asciiname":"Aoshan",
    "gn:country_code":"CN",
    "gn:dem":15,
    "gn:feature_class":"P",
    "gn:feature_code":"PPL",
    "gn:name":"Aoshan",
    "gn:population":0,
    "gn:timezone":"Asia/Shanghai",
    "iso:country":"CN",
    "name:zho_x_preferred":[
        "\u9ccc\u5c71"
    ],
    "wof:name":"Aoshan",
    "wof:placetype":"locality"
},
  "geometry": {"coordinates":[119.15062,25.45544],"type":"Point"}
}