{
  "type": "Feature",
  "properties": {
    "gn:admin1_code":"11",
    "gn:asciiname":"Pingdichong",
    "gn:country_code":"CN",
    "gn:dem":271,
    "gn:feature_class":"P",
    "gn:feature_code":"PPL",
    "gn:name":"Pingdichong",
    "gn:population":0,
    "gn:timezone":"Asia/Shanghai",
    "iso:country":"CN",
    "wof:name":"Pingdichong",
    "wof:placetype":"locality"
},
  "geometry": {"coordinates":[110.13028,27.19333],"type":"Point"}
}