{
  "type": "Feature",
  "properties": {
    "gn:admin1_code":"9.0",
    "gn:asciiname":"Xiaoqinzhuang",
    "gn:country_code":"CN",
    "gn:dem":49,
    "gn:feature_class":"P",
    "gn:feature_code":"PPL",
    "gn:name":"Xiaoqinzhuang",
    "gn:population":0,
    "gn:timezone":"Asia/Shanghai",
    "iso:country":"CN",
    "name:zho_x_preferred":[
        "\u5c0f\u79e6\u5e84"
    ],
    "wof:name":"Xiaoqinzhuang",
    "wof:placetype":"locality"
},
  "geometry": {"coordinates":[114.61548999999999,33.15826],"type":"Point"}
}