{
  "type": "Feature",
  "properties": {
    "gn:admin1_code":"30",
    "gn:asciiname":"Qingzhusun",
    "gn:country_code":"CN",
    "gn:dem":58,
    "gn:feature_class":"P",
    "gn:feature_code":"PPL",
    "gn:name":"Qingzhusun",
    "gn:population":0,
    "gn:timezone":"Asia/Shanghai",
    "iso:country":"CN",
    "name:zho_x_preferred":[
        "\u9752\u7af9\u7b0b"
    ],
    "wof:name":"Qingzhusun",
    "wof:placetype":"locality"
},
  "geometry": {"coordinates":[113.76139000000001,22.94167],"type":"Point"}
}