{
  "type": "Feature",
  "properties": {
    "gn:admin1_code":"25",
    "gn:asciiname":"Zhenwumiao",
    "gn:country_code":"CN",
    "gn:dem":39,
    "gn:feature_class":"P",
    "gn:feature_code":"PPL",
    "gn:name":"Zhenwumiao",
    "gn:population":0,
    "gn:timezone":"Asia/Shanghai",
    "iso:country":"CN",
    "name:zho_x_preferred":[
        "\u771f\u6b66\u5e99"
    ],
    "wof:name":"Zhenwumiao",
    "wof:placetype":"locality"
},
  "geometry": {"coordinates":[115.97071,36.17526],"type":"Point"}
}