{
  "type": "Feature",
  "properties": {
    "gn:admin1_code":"26.0",
    "gn:asciiname":"Xiaoxingzhuang",
    "gn:country_code":"CN",
    "gn:dem":1743,
    "gn:feature_class":"P",
    "gn:feature_code":"PPL",
    "gn:name":"Xiaoxingzhuang",
    "gn:population":0,
    "gn:timezone":"Asia/Shanghai",
    "iso:country":"CN",
    "name:zho_x_preferred":[
        "\u5c0f\u5174\u5e84"
    ],
    "wof:name":"Xiaoxingzhuang",
    "wof:placetype":"locality"
},
  "geometry": {"coordinates":[107.48468,37.32196],"type":"Point"}
}