{
  "type": "Feature",
  "properties": {
    "gn:admin1_code":"15.0",
    "gn:asciiname":"Xuanmawan",
    "gn:country_code":"CN",
    "gn:dem":1115,
    "gn:feature_class":"P",
    "gn:feature_code":"PPL",
    "gn:name":"Xuanmawan",
    "gn:population":0,
    "gn:timezone":"Asia/Shanghai",
    "iso:country":"CN",
    "name:und_x_variant":[
        "\u7384\u9a6c\u6e7e"
    ],
    "wof:name":"Xuanmawan",
    "wof:placetype":"locality"
},
  "geometry": {"coordinates":[107.90845,36.16042],"type":"Point"}
}