{
  "type": "Feature",
  "properties": {
    "gn:admin1_code":"12",
    "gn:asciiname":"Rongmei",
    "gn:country_code":"CN",
    "gn:dem":503,
    "gn:feature_class":"P",
    "gn:feature_code":"PPLA3",
    "gn:name":"Rongmei",
    "gn:population":0,
    "gn:timezone":"Asia/Shanghai",
    "iso:country":"CN",
    "name:und_x_variant":[
        "Hofeng-hsien",
        "Hao-feng-hsien",
        "Hao-feng",
        "Hefeng",
        "Ho-feng",
        "Hefeng Xian",
        "Rongmei",
        "Rongmei Zhen"
    ],
    "name:zho_x_preferred":[
        "\u5bb9\u7f8e"
    ],
    "name:zho_x_variant":[
        "\u9e64\u5cf0\u53bf",
        "\u5bb9\u7f8e\u9547",
        "\u9e64\u5cf0"
    ],
    "wof:name":"Rongmei",
    "wof:placetype":"locality"
},
  "geometry": {"coordinates":[110.02611,29.89333],"type":"Point"}
}