{
  "type": "Feature",
  "properties": {
    "gn:admin1_code":"29.0",
    "gn:asciiname":"Laozhichang",
    "gn:country_code":"CN",
    "gn:dem":1556,
    "gn:feature_class":"P",
    "gn:feature_code":"PPL",
    "gn:name":"Laozhichang",
    "gn:population":0,
    "gn:timezone":"Asia/Shanghai",
    "iso:country":"CN",
    "name:zho_x_preferred":[
        "\u8001\u7eb8\u5382"
    ],
    "wof:name":"Laozhichang",
    "wof:placetype":"locality"
},
  "geometry": {"coordinates":[101.089,22.8509],"type":"Point"}
}