{
  "type": "Feature",
  "properties": {
    "gn:admin1_code":"5.0",
    "gn:asciiname":"Xinglonggoucun",
    "gn:country_code":"CN",
    "gn:dem":191,
    "gn:feature_class":"P",
    "gn:feature_code":"PPL",
    "gn:name":"Xinglonggoucun",
    "gn:population":0,
    "gn:timezone":"Asia/Shanghai",
    "iso:country":"CN",
    "name:zho_x_preferred":[
        "\u5174\u9686\u6c9f\u6751"
    ],
    "wof:name":"Xinglonggoucun",
    "wof:placetype":"locality"
},
  "geometry": {"coordinates":[124.72017,43.84873],"type":"Point"}
}