{
  "type": "Feature",
  "properties": {
    "gn:admin1_code":"26.0",
    "gn:asciiname":"Houwacun",
    "gn:country_code":"CN",
    "gn:dem":952,
    "gn:feature_class":"P",
    "gn:feature_code":"PPL",
    "gn:name":"Houwacun",
    "gn:population":0,
    "gn:timezone":"Asia/Shanghai",
    "iso:country":"CN",
    "name:zho_x_preferred":[
        "\u540e\u6d3c\u6751"
    ],
    "wof:name":"Houwacun",
    "wof:placetype":"locality"
},
  "geometry": {"coordinates":[109.47306,35.22395],"type":"Point"}
}