{
  "type": "Feature",
  "properties": {
    "gn:admin1_code":"29.0",
    "gn:asciiname":"Shenda",
    "gn:country_code":"CN",
    "gn:dem":2176,
    "gn:feature_class":"P",
    "gn:feature_code":"PPL",
    "gn:name":"Shenda",
    "gn:population":0,
    "gn:timezone":"Asia/Shanghai",
    "iso:country":"CN",
    "name:zho_x_preferred":[
        "\u7533\u8fbe"
    ],
    "wof:name":"Shenda",
    "wof:placetype":"locality"
},
  "geometry": {"coordinates":[99.17449999999999,28.5291],"type":"Point"}
}