{
  "type": "Feature",
  "properties": {
    "gn:admin1_code":"19.0",
    "gn:asciiname":"Yangquanzi",
    "gn:country_code":"CN",
    "gn:dem":12,
    "gn:feature_class":"P",
    "gn:feature_code":"PPL",
    "gn:name":"Yangquanzi",
    "gn:population":0,
    "gn:timezone":"Asia/Shanghai",
    "iso:country":"CN",
    "name:zho_x_preferred":[
        "\u7f8a\u5708\u5b50"
    ],
    "wof:name":"Yangquanzi",
    "wof:placetype":"locality"
},
  "geometry": {"coordinates":[122.15409,41.55752],"type":"Point"}
}