{
  "type": "Feature",
  "properties": {
    "gn:admin1_code":"05",
    "gn:asciiname":"Sidongfang",
    "gn:country_code":"CN",
    "gn:dem":2022,
    "gn:feature_class":"P",
    "gn:feature_code":"PPL",
    "gn:name":"Sidongfang",
    "gn:population":0,
    "gn:timezone":"Asia/Shanghai",
    "iso:country":"CN",
    "name:und_x_variant":[
        "\u56db\u680b\u623f",
        "Sidengfang"
    ],
    "wof:name":"Sidongfang",
    "wof:placetype":"locality"
},
  "geometry": {"coordinates":[127.83385,41.70177],"type":"Point"}
}