{
  "type": "Feature",
  "properties": {
    "gn:admin1_code":"25.0",
    "gn:asciiname":"Sanshilibucun",
    "gn:country_code":"CN",
    "gn:dem":22,
    "gn:feature_class":"P",
    "gn:feature_code":"PPL",
    "gn:name":"Sanshilibucun",
    "gn:population":0,
    "gn:timezone":"Asia/Shanghai",
    "iso:country":"CN",
    "name:zho_x_preferred":[
        "\u4e09\u5341\u91cc\u5821\u6751"
    ],
    "wof:name":"Sanshilibucun",
    "wof:placetype":"locality"
},
  "geometry": {"coordinates":[121.45775,37.43203],"type":"Point"}
}