{
  "type": "Feature",
  "properties": {
    "gn:admin1_code":"30.0",
    "gn:asciiname":"Helukou",
    "gn:country_code":"CN",
    "gn:dem":271,
    "gn:feature_class":"P",
    "gn:feature_code":"PPL",
    "gn:name":"Helukou",
    "gn:population":0,
    "gn:timezone":"Asia/Shanghai",
    "iso:country":"CN",
    "name:zho_x_preferred":[
        "Helukou"
    ],
    "name:zho_x_variant":[
        "\u5408\u8def\u53e3"
    ],
    "wof:name":"Helukou",
    "wof:placetype":"locality"
},
  "geometry": {"coordinates":[115.34639,24.07194],"type":"Point"}
}