{
  "type": "Feature",
  "properties": {
    "gn:admin1_code":"08",
    "gn:asciiname":"Changgang",
    "gn:country_code":"CN",
    "gn:dem":130,
    "gn:feature_class":"P",
    "gn:feature_code":"PPLA4",
    "gn:name":"Changgang",
    "gn:population":0,
    "gn:timezone":"Asia/Shanghai",
    "iso:country":"CN",
    "name:und_x_variant":[
        "Ch\u2019ang-kang-tzu",
        "Changgang",
        "Changgang Xiang"
    ],
    "name:zho_x_preferred":[
        "\u957f\u5c97"
    ],
    "name:zho_x_variant":[
        "\u957f\u5c97\u4e61"
    ],
    "wof:name":"Changgang",
    "wof:placetype":"locality"
},
  "geometry": {"coordinates":[126.43259,46.34515],"type":"Point"}
}