{
  "type": "Feature",
  "properties": {
    "gn:admin1_code":"04",
    "gn:asciiname":"Dinggou",
    "gn:country_code":"CN",
    "gn:dem":5,
    "gn:feature_class":"P",
    "gn:feature_code":"PPLA4",
    "gn:name":"Dinggou",
    "gn:population":0,
    "gn:timezone":"Asia/Shanghai",
    "iso:country":"CN",
    "name:und_x_variant":[
        "Ting-kou",
        "Ting-kou-chen",
        "Dinggou",
        "Dinggou Zhen"
    ],
    "name:zho_x_preferred":[
        "\u4e01\u6c9f"
    ],
    "name:zho_x_variant":[
        "\u4e01\u6c9f\u9547"
    ],
    "wof:name":"Dinggou",
    "wof:placetype":"locality"
},
  "geometry": {"coordinates":[119.66255,32.56423],"type":"Point"}
}