{
  "type": "Feature",
  "properties": {
    "gn:admin1_code":"12.0",
    "gn:asciiname":"Miaolingshang",
    "gn:country_code":"CN",
    "gn:dem":79,
    "gn:feature_class":"P",
    "gn:feature_code":"PPL",
    "gn:name":"Miaolingshang",
    "gn:population":0,
    "gn:timezone":"Asia/Shanghai",
    "iso:country":"CN",
    "name:zho_x_preferred":[
        "\u5e99\u5cad\u4e0a"
    ],
    "wof:name":"Miaolingshang",
    "wof:placetype":"locality"
},
  "geometry": {"coordinates":[112.67095,31.43114000000001],"type":"Point"}
}