{
  "type": "Feature",
  "properties": {
    "gn:admin1_code":"8.0",
    "gn:asciiname":"Dashahecun",
    "gn:country_code":"CN",
    "gn:dem":474,
    "gn:feature_class":"P",
    "gn:feature_code":"PPL",
    "gn:name":"Dashahecun",
    "gn:population":0,
    "gn:timezone":"Asia/Shanghai",
    "iso:country":"CN",
    "name:zho_x_preferred":[
        "\u5927\u6c99\u6cb3\u6751"
    ],
    "wof:name":"Dashahecun",
    "wof:placetype":"locality"
},
  "geometry": {"coordinates":[126.21294,49.85445],"type":"Point"}
}