{
  "type": "Feature",
  "properties": {
    "gn:admin1_code":"4.0",
    "gn:asciiname":"Wangdazhuang",
    "gn:country_code":"CN",
    "gn:dem":24,
    "gn:feature_class":"P",
    "gn:feature_code":"PPL",
    "gn:name":"Wangdazhuang",
    "gn:population":0,
    "gn:timezone":"Asia/Shanghai",
    "iso:country":"CN",
    "name:zho_x_preferred":[
        "\u738b\u5927\u5e84"
    ],
    "wof:name":"Wangdazhuang",
    "wof:placetype":"locality"
},
  "geometry": {"coordinates":[118.56562,33.71021],"type":"Point"}
}