{
  "type": "Feature",
  "properties": {
    "gn:admin1_code":"11.0",
    "gn:asciiname":"Motangchi",
    "gn:country_code":"CN",
    "gn:dem":600,
    "gn:feature_class":"P",
    "gn:feature_code":"PPL",
    "gn:name":"Motangchi",
    "gn:population":0,
    "gn:timezone":"Asia/Shanghai",
    "iso:country":"CN",
    "name:zho_x_preferred":[
        "\u58a8\u5858\u6c60"
    ],
    "wof:name":"Motangchi",
    "wof:placetype":"locality"
},
  "geometry": {"coordinates":[109.99259000000001,29.09893],"type":"Point"}
}