{
  "type": "Feature",
  "properties": {
    "gn:admin1_code":"4.0",
    "gn:asciiname":"Zutiancun",
    "gn:country_code":"CN",
    "gn:dem":3,
    "gn:feature_class":"P",
    "gn:feature_code":"PPL",
    "gn:name":"Zutiancun",
    "gn:population":0,
    "gn:timezone":"Asia/Shanghai",
    "iso:country":"CN",
    "name:zho_x_preferred":[
        "\u79df\u7530\u6751"
    ],
    "wof:name":"Zutiancun",
    "wof:placetype":"locality"
},
  "geometry": {"coordinates":[119.43311,33.96472],"type":"Point"}
}