{
  "type": "Feature",
  "properties": {
    "gn:admin1_code":"13",
    "gn:asciiname":"Subeixi",
    "gn:country_code":"CN",
    "gn:dem":250,
    "gn:feature_class":"P",
    "gn:feature_code":"PPL",
    "gn:name":"Subeixi",
    "gn:population":0,
    "gn:timezone":"Asia/Urumqi",
    "iso:country":"CN",
    "name:und_x_variant":[
        "\u82cf\u8d1d\u5e0c"
    ],
    "wof:name":"Subeixi",
    "wof:placetype":"locality"
},
  "geometry": {"coordinates":[89.7329,42.92115],"type":"Point"}
}