{
  "type": "Feature",
  "properties": {
    "gn:admin1_code":"32.0",
    "gn:asciiname":"Mopan",
    "gn:country_code":"CN",
    "gn:dem":302,
    "gn:feature_class":"P",
    "gn:feature_code":"PPL",
    "gn:name":"Mopan",
    "gn:population":0,
    "gn:timezone":"Asia/Shanghai",
    "iso:country":"CN",
    "name:deu_x_preferred":[
        "Mopan"
    ],
    "name:nds_x_preferred":[
        "Mopan"
    ],
    "name:nld_x_preferred":[
        "Mopan"
    ],
    "name:tur_x_preferred":[
        "Mopan"
    ],
    "name:zho_x_preferred":[
        "\u78e8\u76d8"
    ],
    "wof:name":"Mopan",
    "wof:placetype":"locality"
},
  "geometry": {"coordinates":[106.928,30.9726],"type":"Point"}
}