{
  "type": "Feature",
  "properties": {
    "gn:admin1_code":"30.0",
    "gn:asciiname":"Tianxinwei",
    "gn:country_code":"CN",
    "gn:dem":121,
    "gn:feature_class":"P",
    "gn:feature_code":"PPL",
    "gn:name":"Tianxinwei",
    "gn:population":0,
    "gn:timezone":"Asia/Shanghai",
    "iso:country":"CN",
    "name:und_x_variant":[
        "\u7530\u5fc3\u56f4"
    ],
    "name:zho_x_preferred":[
        "\u7530\u5fc3\u56f4"
    ],
    "wof:name":"Tianxinwei",
    "wof:placetype":"locality"
},
  "geometry": {"coordinates":[115.15147,23.50887],"type":"Point"}
}