{
  "type": "Feature",
  "properties": {
    "gn:admin1_code":"9",
    "gn:asciiname":"Chenlaolou",
    "gn:country_code":"CN",
    "gn:dem":44,
    "gn:feature_class":"P",
    "gn:feature_code":"PPL",
    "gn:name":"Chenlaolou",
    "gn:population":0,
    "gn:timezone":"Asia/Shanghai",
    "iso:country":"CN",
    "name:zho_x_preferred":[
        "\u9648\u8001\u697c"
    ],
    "wof:name":"Chenlaolou",
    "wof:placetype":"locality"
},
  "geometry": {"coordinates":[115.824,34.1582],"type":"Point"}
}