{
  "type": "Feature",
  "properties": {
    "gn:admin1_code":"3.0",
    "gn:asciiname":"Shizichong",
    "gn:country_code":"CN",
    "gn:dem":146,
    "gn:feature_class":"P",
    "gn:feature_code":"PPL",
    "gn:name":"Shizichong",
    "gn:population":0,
    "gn:timezone":"Asia/Shanghai",
    "iso:country":"CN",
    "name:und_x_variant":[
        "\u77f3\u5b50\u51b2"
    ],
    "wof:name":"Shizichong",
    "wof:placetype":"locality"
},
  "geometry": {"coordinates":[114.56913,27.51949],"type":"Point"}
}