{
  "type": "Feature",
  "properties": {
    "gn:admin1_code":"11",
    "gn:asciiname":"Yejiping",
    "gn:country_code":"CN",
    "gn:dem":390,
    "gn:feature_class":"P",
    "gn:feature_code":"PPL",
    "gn:name":"Yejiping",
    "gn:population":0,
    "gn:timezone":"Asia/Shanghai",
    "iso:country":"CN",
    "wof:name":"Yejiping",
    "wof:placetype":"locality"
},
  "geometry": {"coordinates":[109.53278,27.78278],"type":"Point"}
}