{
  "type": "Feature",
  "properties": {
    "gn:admin1_code":"1.0",
    "gn:asciiname":"Huangzhuyuancun",
    "gn:country_code":"CN",
    "gn:dem":38,
    "gn:feature_class":"P",
    "gn:feature_code":"PPL",
    "gn:name":"Huangzhuyuancun",
    "gn:population":0,
    "gn:timezone":"Asia/Shanghai",
    "iso:country":"CN",
    "name:zho_x_preferred":[
        "\u9ec4\u7af9\u56ed\u6751"
    ],
    "wof:name":"Huangzhuyuancun",
    "wof:placetype":"locality"
},
  "geometry": {"coordinates":[116.24702000000001,32.06665],"type":"Point"}
}