{
  "type": "Feature",
  "properties": {
    "gn:admin1_code":"26",
    "gn:asciiname":"Shaluo",
    "gn:cc2":"CN",
    "gn:country_code":"CN",
    "gn:dem":1271,
    "gn:feature_class":"P",
    "gn:feature_code":"PPL",
    "gn:name":"Shaluo",
    "gn:population":0,
    "gn:timezone":"Asia/Shanghai",
    "iso:country":"CN",
    "name:und_x_variant":[
        "Sha-lo-chang",
        "Sha-lo",
        "Shaluo"
    ],
    "wof:name":"Shaluo",
    "wof:placetype":"locality"
},
  "geometry": {"coordinates":[108.91667,33.71667],"type":"Point"}
}