{
  "type": "Feature",
  "properties": {
    "gn:admin1_code":"14",
    "gn:asciiname":"Kangsha",
    "gn:country_code":"CN",
    "gn:dem":4357,
    "gn:feature_class":"P",
    "gn:feature_code":"PPL",
    "gn:name":"Kangsha",
    "gn:population":0,
    "gn:timezone":"Asia/Urumqi",
    "iso:country":"CN",
    "name:zho_x_preferred":[
        "\u5eb7\u838e"
    ],
    "wof:name":"Kangsha",
    "wof:placetype":"locality"
},
  "geometry": {"coordinates":[88.976,29.5559],"type":"Point"}
}