{
  "type": "Feature",
  "properties": {
    "gn:admin1_code":"9.0",
    "gn:asciiname":"Hutai",
    "gn:country_code":"CN",
    "gn:dem":182,
    "gn:feature_class":"P",
    "gn:feature_code":"PPL",
    "gn:name":"Hutai",
    "gn:population":0,
    "gn:timezone":"Asia/Shanghai",
    "iso:country":"CN",
    "name:und_x_variant":[
        "\u6237\u53f0",
        "Hutai"
    ],
    "wof:name":"Hutai",
    "wof:placetype":"locality"
},
  "geometry": {"coordinates":[112.73246,33.26761],"type":"Point"}
}