{
  "type": "Feature",
  "properties": {
    "gn:admin1_code":"24.0",
    "gn:asciiname":"Zhaobaicun",
    "gn:country_code":"CN",
    "gn:dem":360,
    "gn:feature_class":"P",
    "gn:feature_code":"PPL",
    "gn:name":"Zhaobaicun",
    "gn:population":0,
    "gn:timezone":"Asia/Shanghai",
    "iso:country":"CN",
    "name:zho_x_preferred":[
        "\u8d75\u67cf\u6751"
    ],
    "wof:name":"Zhaobaicun",
    "wof:placetype":"locality"
},
  "geometry": {"coordinates":[110.46441000000002,34.91934000000001],"type":"Point"}
}