{
  "type": "Feature",
  "properties": {
    "gn:admin1_code":"4.0",
    "gn:asciiname":"Wenjiazhuang",
    "gn:country_code":"CN",
    "gn:dem":0,
    "gn:feature_class":"P",
    "gn:feature_code":"PPL",
    "gn:name":"Wenjiazhuang",
    "gn:population":0,
    "gn:timezone":"Asia/Shanghai",
    "iso:country":"CN",
    "name:zho_x_preferred":[
        "Wenjiazhuang"
    ],
    "name:zho_x_variant":[
        "\u6e29\u5bb6\u5e84"
    ],
    "wof:name":"Wenjiazhuang",
    "wof:placetype":"locality"
},
  "geometry": {"coordinates":[119.46852,33.5055],"type":"Point"}
}