{
  "type": "Feature",
  "properties": {
    "gn:admin1_code":"9.0",
    "gn:asciiname":"Zhujiacang",
    "gn:country_code":"CN",
    "gn:dem":218,
    "gn:feature_class":"P",
    "gn:feature_code":"PPL",
    "gn:name":"Zhujiacang",
    "gn:population":0,
    "gn:timezone":"Asia/Shanghai",
    "iso:country":"CN",
    "name:zho_x_preferred":[
        "\u6731\u5bb6\u4ed3"
    ],
    "wof:name":"Zhujiacang",
    "wof:placetype":"locality"
},
  "geometry": {"coordinates":[112.61687999999999,34.77504],"type":"Point"}
}