{
  "type": "Feature",
  "properties": {
    "gn:admin1_code":"29",
    "gn:asciiname":"Pofang",
    "gn:country_code":"CN",
    "gn:dem":981,
    "gn:feature_class":"P",
    "gn:feature_code":"PPL",
    "gn:name":"Pofang",
    "gn:population":0,
    "gn:timezone":"Asia/Shanghai",
    "iso:country":"CN",
    "name:zho_x_preferred":[
        "\u5761\u623f"
    ],
    "wof:name":"Pofang",
    "wof:placetype":"locality"
},
  "geometry": {"coordinates":[105.59999999999999,23.6932],"type":"Point"}
}