{
  "type": "Feature",
  "properties": {
    "gn:admin1_code":"10",
    "gn:asciiname":"Dianchizi",
    "gn:country_code":"CN",
    "gn:dem":140,
    "gn:feature_class":"P",
    "gn:feature_code":"PPL",
    "gn:name":"Dianchizi",
    "gn:population":0,
    "gn:timezone":"Asia/Shanghai",
    "iso:country":"CN",
    "name:zho_x_preferred":[
        "\u975b\u6c60\u5b50"
    ],
    "wof:name":"Dianchizi",
    "wof:placetype":"locality"
},
  "geometry": {"coordinates":[118.84483,40.24426],"type":"Point"}
}