{
  "type": "Feature",
  "properties": {
    "gn:admin1_code":"16.0",
    "gn:asciiname":"Damingwai",
    "gn:country_code":"CN",
    "gn:dem":905,
    "gn:feature_class":"P",
    "gn:feature_code":"PPL",
    "gn:name":"Damingwai",
    "gn:population":0,
    "gn:timezone":"Asia/Shanghai",
    "iso:country":"CN",
    "name:zho_x_preferred":[
        "\u5927\u540d\u5916"
    ],
    "wof:name":"Damingwai",
    "wof:placetype":"locality"
},
  "geometry": {"coordinates":[106.167,23.2704],"type":"Point"}
}