{
  "type": "Feature",
  "properties": {
    "gn:admin1_code":"16.0",
    "gn:asciiname":"Shang'antang",
    "gn:country_code":"CN",
    "gn:dem":62,
    "gn:feature_class":"P",
    "gn:feature_code":"PPL",
    "gn:name":"Shang\u2019antang",
    "gn:population":0,
    "gn:timezone":"Asia/Shanghai",
    "iso:country":"CN",
    "name:und_x_variant":[
        "Shang\u2019antang"
    ],
    "name:zho_x_preferred":[
        "\u4e0a\u5b89\u5858"
    ],
    "wof:name":"Shang'antang",
    "wof:placetype":"locality"
},
  "geometry": {"coordinates":[109.221,21.8894],"type":"Point"}
}