{
  "type": "Feature",
  "properties": {
    "gn:admin1_code":"10",
    "gn:asciiname":"Daduanjiaying",
    "gn:country_code":"CN",
    "gn:dem":1450,
    "gn:feature_class":"P",
    "gn:feature_code":"PPL",
    "gn:name":"Daduanjiaying",
    "gn:population":0,
    "gn:timezone":"Asia/Shanghai",
    "iso:country":"CN",
    "name:zho_x_preferred":[
        "\u5927\u6bb5\u5bb6\u8425"
    ],
    "wof:name":"Daduanjiaying",
    "wof:placetype":"locality"
},
  "geometry": {"coordinates":[115.17007,41.34501],"type":"Point"}
}