{
  "type": "Feature",
  "properties": {
    "gn:admin1_code":"30.0",
    "gn:asciiname":"Shuihuaba",
    "gn:country_code":"CN",
    "gn:dem":190,
    "gn:feature_class":"P",
    "gn:feature_code":"PPL",
    "gn:name":"Shuihuaba",
    "gn:population":0,
    "gn:timezone":"Asia/Shanghai",
    "iso:country":"CN",
    "name:zho_x_preferred":[
        "Shuihuaba"
    ],
    "name:zho_x_variant":[
        "\u6c34\u534e\u575d"
    ],
    "wof:name":"Shuihuaba",
    "wof:placetype":"locality"
},
  "geometry": {"coordinates":[115.35972,24.28444],"type":"Point"}
}