{
  "type": "Feature",
  "properties": {
    "gn:admin1_code":"29.0",
    "gn:asciiname":"Mangling Xinzhai",
    "gn:country_code":"CN",
    "gn:dem":1450,
    "gn:feature_class":"P",
    "gn:feature_code":"PPL",
    "gn:name":"Mangling Xinzhai",
    "gn:population":0,
    "gn:timezone":"Asia/Shanghai",
    "iso:country":"CN",
    "name:zho_x_preferred":[
        "\u8292\u4ee4\u65b0\u5be8"
    ],
    "wof:name":"Mangling Xinzhai",
    "wof:placetype":"locality"
},
  "geometry": {"coordinates":[99.822,22.3676],"type":"Point"}
}