{
  "type": "Feature",
  "properties": {
    "gn:admin1_code":"29",
    "gn:asciiname":"Gengjing",
    "gn:country_code":"CN",
    "gn:dem":774,
    "gn:feature_class":"P",
    "gn:feature_code":"PPL",
    "gn:name":"Gengjing",
    "gn:population":0,
    "gn:timezone":"Asia/Shanghai",
    "iso:country":"CN",
    "name:zho_x_preferred":[
        "\u57c2\u4e95"
    ],
    "wof:name":"Gengjing",
    "wof:placetype":"locality"
},
  "geometry": {"coordinates":[101.80800000000001,24.2677],"type":"Point"}
}