{
  "type": "Feature",
  "properties": {
    "gn:admin1_code":"12.0",
    "gn:asciiname":"Taoshuya",
    "gn:country_code":"CN",
    "gn:dem":1087,
    "gn:feature_class":"P",
    "gn:feature_code":"PPL",
    "gn:name":"Taoshuya",
    "gn:population":0,
    "gn:timezone":"Asia/Shanghai",
    "iso:country":"CN",
    "name:zho_x_preferred":[
        "\u6843\u6811\u57ad"
    ],
    "wof:name":"Taoshuya",
    "wof:placetype":"locality"
},
  "geometry": {"coordinates":[111.22439,31.49254],"type":"Point"}
}