{
  "type": "Feature",
  "properties": {
    "gn:admin1_code":"32.0",
    "gn:asciiname":"Xiaozhuba",
    "gn:country_code":"CN",
    "gn:dem":348,
    "gn:feature_class":"P",
    "gn:feature_code":"PPL",
    "gn:name":"Xiaozhuba",
    "gn:population":0,
    "gn:timezone":"Asia/Shanghai",
    "iso:country":"CN",
    "name:zho_x_preferred":[
        "\u5c0f\u73e0\u575d"
    ],
    "wof:name":"Xiaozhuba",
    "wof:placetype":"locality"
},
  "geometry": {"coordinates":[105.723,30.9364],"type":"Point"}
}