{
  "type": "Feature",
  "properties": {
    "gn:admin1_code":"29.0",
    "gn:asciiname":"Tangguanqing",
    "gn:country_code":"CN",
    "gn:dem":1915,
    "gn:feature_class":"P",
    "gn:feature_code":"PPL",
    "gn:name":"Tangguanqing",
    "gn:population":0,
    "gn:timezone":"Asia/Shanghai",
    "iso:country":"CN",
    "name:zho_x_preferred":[
        "\u6c64\u5b98\u7b90"
    ],
    "wof:name":"Tangguanqing",
    "wof:placetype":"locality"
},
  "geometry": {"coordinates":[103.729,24.9152],"type":"Point"}
}