{
  "type": "Feature",
  "properties": {
    "gn:admin1_code":"16",
    "gn:asciiname":"Qingtai",
    "gn:country_code":"CN",
    "gn:dem":272,
    "gn:feature_class":"P",
    "gn:feature_code":"PPL",
    "gn:name":"Qingtai",
    "gn:population":0,
    "gn:timezone":"Asia/Shanghai",
    "iso:country":"CN",
    "name:zho_x_preferred":[
        "\u6e05\u6cf0"
    ],
    "wof:name":"Qingtai",
    "wof:placetype":"locality"
},
  "geometry": {"coordinates":[110.21599999999999,24.963],"type":"Point"}
}