{
  "type": "Feature",
  "properties": {
    "gn:admin1_code":"18",
    "gn:asciiname":"Dagejia",
    "gn:country_code":"CN",
    "gn:dem":1673,
    "gn:feature_class":"P",
    "gn:feature_code":"PPL",
    "gn:name":"Dagejia",
    "gn:population":0,
    "gn:timezone":"Asia/Shanghai",
    "iso:country":"CN",
    "name:zho_x_preferred":[
        "\u5927\u683c\u621b"
    ],
    "wof:name":"Dagejia",
    "wof:placetype":"locality"
},
  "geometry": {"coordinates":[105.40900000000001,26.472],"type":"Point"}
}