{
  "type": "Feature",
  "properties": {
    "gn:admin1_code":"10.0",
    "gn:asciiname":"Dadigou",
    "gn:country_code":"CN",
    "gn:dem":762,
    "gn:feature_class":"P",
    "gn:feature_code":"PPL",
    "gn:name":"Dadigou",
    "gn:population":0,
    "gn:timezone":"Asia/Shanghai",
    "iso:country":"CN",
    "name:zho_x_preferred":[
        "\u5927\u5730\u6c9f"
    ],
    "wof:name":"Dadigou",
    "wof:placetype":"locality"
},
  "geometry": {"coordinates":[114.08208999999999,39.06716],"type":"Point"}
}