{
  "type": "Feature",
  "properties": {
    "gn:admin1_code":"4.0",
    "gn:asciiname":"Botuogoucun",
    "gn:country_code":"CN",
    "gn:dem":15,
    "gn:feature_class":"P",
    "gn:feature_code":"PPL",
    "gn:name":"Botuogoucun",
    "gn:population":0,
    "gn:timezone":"Asia/Shanghai",
    "iso:country":"CN",
    "name:zho_x_preferred":[
        "\u67cf\u5768\u6c9f\u6751"
    ],
    "wof:name":"Botuogoucun",
    "wof:placetype":"locality"
},
  "geometry": {"coordinates":[118.98108000000001,34.8747],"type":"Point"}
}