{
  "type": "Feature",
  "properties": {
    "gn:admin1_code":"14.0",
    "gn:asciiname":"Jiacha",
    "gn:country_code":"CN",
    "gn:dem":4604,
    "gn:feature_class":"P",
    "gn:feature_code":"PPL",
    "gn:name":"Jiacha",
    "gn:population":0,
    "gn:timezone":"Asia/Urumqi",
    "iso:country":"CN",
    "name:zho_x_preferred":[
        "\u52a0\u67e5"
    ],
    "wof:name":"Jiacha",
    "wof:placetype":"locality"
},
  "geometry": {"coordinates":[85.14060000000001,31.9308],"type":"Point"}
}