{
  "type": "Feature",
  "properties": {
    "gn:admin1_code":"19.0",
    "gn:asciiname":"Majia Wobu",
    "gn:country_code":"CN",
    "gn:dem":89,
    "gn:feature_class":"P",
    "gn:feature_code":"PPL",
    "gn:name":"Majia Wobu",
    "gn:population":0,
    "gn:timezone":"Asia/Shanghai",
    "iso:country":"CN",
    "name:und_x_variant":[
        "Nanmajiawobao",
        "Nanmajia Wobu"
    ],
    "name:zho_x_preferred":[
        "\u9a6c\u5bb6\u7a9d\u5821"
    ],
    "name:zho_x_variant":[
        "\u5357\u9a6c\u5bb6\u7a9d\u5821"
    ],
    "wof:name":"Majia Wobu",
    "wof:placetype":"locality"
},
  "geometry": {"coordinates":[123.334,42.6528],"type":"Point"}
}