{
  "type": "Feature",
  "properties": {
    "gn:admin1_code":"25.0",
    "gn:asciiname":"Haojiajimabu",
    "gn:country_code":"CN",
    "gn:dem":46,
    "gn:feature_class":"P",
    "gn:feature_code":"PPL",
    "gn:name":"Haojiajimabu",
    "gn:population":0,
    "gn:timezone":"Asia/Shanghai",
    "iso:country":"CN",
    "name:zho_x_preferred":[
        "\u90dd\u5bb6\u5bc4\u9a6c\u57e0"
    ],
    "wof:name":"Haojiajimabu",
    "wof:placetype":"locality"
},
  "geometry": {"coordinates":[120.59693,36.62831],"type":"Point"}
}