{
  "type": "Feature",
  "properties": {
    "gn:admin1_code":"7.0",
    "gn:asciiname":"Longyan",
    "gn:country_code":"CN",
    "gn:dem":460,
    "gn:feature_class":"P",
    "gn:feature_code":"PPL",
    "gn:name":"Longyan",
    "gn:population":0,
    "gn:timezone":"Asia/Shanghai",
    "iso:country":"CN",
    "name:ara_x_preferred":[
        "\u0644\u0648\u0646\u063a\u064a\u0627\u0646"
    ],
    "name:cdo_x_preferred":[
        "L\u1e73\u0300ng-ng\u00e0ng"
    ],
    "name:ces_x_preferred":[
        "Lung-jen"
    ],
    "name:dan_x_preferred":[
        "Longyan"
    ],
    "name:deu_x_preferred":[
        "Longyan"
    ],
    "name:eus_x_preferred":[
        "Longyan"
    ],
    "name:fas_x_preferred":[
        "\u0644\u0627\u0646\u06af\u06cc\u0627\u0646"
    ],
    "name:fin_x_preferred":[
        "Longyan"
    ],
    "name:fra_x_preferred":[
        "Longyan"
    ],
    "name:hak_x_preferred":[
        "Li\u00f9ng-ng\u00e0m-s\u1e73"
    ],
    "name:ita_x_preferred":[
        "Longyan"
    ],
    "name:jpn_x_preferred":[
        "\u7adc\u5ca9\u5e02"
    ],
    "name:kaz_x_preferred":[
        "\u041b\u0443\u043d\u044a\u044f\u043d\u044c"
    ],
    "name:kik_x_preferred":[
        "Longyan"
    ],
    "name:kor_x_preferred":[
        "\ub8fd\uc60c\uc2dc"
    ],
    "name:mlg_x_preferred":[
        "Longyan"
    ],
    "name:nld_x_preferred":[
        "Longyan"
    ],
    "name:nno_x_preferred":[
        "Longyan"
    ],
    "name:nor_x_preferred":[
        "Longyan"
    ],
    "name:pam_x_preferred":[
        "Longyan"
    ],
    "name:pol_x_preferred":[
        "Longyan"
    ],
    "name:por_x_preferred":[
        "Longyan"
    ],
    "name:rus_x_preferred":[
        "\u041b\u0443\u043d\u044a\u044f\u043d\u044c"
    ],
    "name:sco_x_preferred":[
        "Longyan"
    ],
    "name:spa_x_preferred":[
        "Longyan"
    ],
    "name:swe_x_preferred":[
        "Longyan"
    ],
    "name:tgl_x_preferred":[
        "Longyan"
    ],
    "name:tur_x_preferred":[
        "Longyan"
    ],
    "name:uig_x_preferred":[
        "Longyen shehiri"
    ],
    "name:urd_x_preferred":[
        "\u0644\u0648\u0646\u06af\u06cc\u0627\u0646"
    ],
    "name:vie_x_preferred":[
        "Long Nham"
    ],
    "name:war_x_preferred":[
        "Longyan"
    ],
    "name:wuu_x_preferred":[
        "\u9f99\u5ca9\u5e02"
    ],
    "name:zho_x_preferred":[
        "\u9f99\u5ca9"
    ],
    "name:zho_x_variant":[
        "\u9f99\u5ca9\u5e02"
    ],
    "wof:name":"Longyan",
    "wof:placetype":"locality"
},
  "geometry": {"coordinates":[117.86490000000001,26.89405],"type":"Point"}
}