{
  "type": "Feature",
  "properties": {
    "gn:admin1_code":"30.0",
    "gn:asciiname":"Dongmingcun",
    "gn:country_code":"CN",
    "gn:dem":61,
    "gn:feature_class":"P",
    "gn:feature_code":"PPL",
    "gn:name":"Dongmingcun",
    "gn:population":0,
    "gn:timezone":"Asia/Shanghai",
    "iso:country":"CN",
    "name:und_x_variant":[
        "Dongming"
    ],
    "name:zho_x_preferred":[
        "\u4e1c\u660e\u6751"
    ],
    "name:zho_x_variant":[
        "\u4e1c\u660e"
    ],
    "wof:name":"Dongmingcun",
    "wof:placetype":"locality"
},
  "geometry": {"coordinates":[116.96431,23.89232],"type":"Point"}
}