{
  "type": "Feature",
  "properties": {
    "gn:admin1_code":"15.0",
    "gn:asciiname":"Qianzui",
    "gn:country_code":"CN",
    "gn:dem":1854,
    "gn:feature_class":"P",
    "gn:feature_code":"PPL",
    "gn:name":"Qianzui",
    "gn:population":0,
    "gn:timezone":"Asia/Shanghai",
    "iso:country":"CN",
    "name:und_x_variant":[
        "\u524d\u5634"
    ],
    "wof:name":"Qianzui",
    "wof:placetype":"locality"
},
  "geometry": {"coordinates":[105.47789,35.71045],"type":"Point"}
}