{
  "type": "Feature",
  "properties": {
    "gn:admin1_code":"8.0",
    "gn:asciiname":"Fengyucun",
    "gn:country_code":"CN",
    "gn:dem":63,
    "gn:feature_class":"P",
    "gn:feature_code":"PPL",
    "gn:name":"Fengyucun",
    "gn:population":0,
    "gn:timezone":"Asia/Shanghai",
    "iso:country":"CN",
    "name:zho_x_preferred":[
        "\u4e30\u88d5\u6751"
    ],
    "wof:name":"Fengyucun",
    "wof:placetype":"locality"
},
  "geometry": {"coordinates":[132.17158999999998,46.91983],"type":"Point"}
}