{
  "type": "Feature",
  "properties": {
    "gn:admin1_code":"26.0",
    "gn:asciiname":"Zaowancun",
    "gn:country_code":"CN",
    "gn:dem":1147,
    "gn:feature_class":"P",
    "gn:feature_code":"PPL",
    "gn:name":"Zaowancun",
    "gn:population":0,
    "gn:timezone":"Asia/Shanghai",
    "iso:country":"CN",
    "name:zho_x_preferred":[
        "\u67a3\u6e7e\u6751"
    ],
    "wof:name":"Zaowancun",
    "wof:placetype":"locality"
},
  "geometry": {"coordinates":[109.65239,37.18308],"type":"Point"}
}