{
  "type": "Feature",
  "properties": {
    "gn:admin1_code":"16.0",
    "gn:asciiname":"Ren'an",
    "gn:country_code":"CN",
    "gn:dem":627,
    "gn:feature_class":"P",
    "gn:feature_code":"PPL",
    "gn:name":"Ren\u2019an",
    "gn:population":0,
    "gn:timezone":"Asia/Shanghai",
    "iso:country":"CN",
    "name:und_x_variant":[
        "Ren\u2019an"
    ],
    "name:zho_x_preferred":[
        "\u4ec1\u5b89"
    ],
    "wof:name":"Ren'an",
    "wof:placetype":"locality"
},
  "geometry": {"coordinates":[107.05200000000001,24.4289],"type":"Point"}
}