{
  "type": "Feature",
  "properties": {
    "gn:admin1_code":"19.0",
    "gn:asciiname":"Xinglonggangzi",
    "gn:country_code":"CN",
    "gn:dem":12,
    "gn:feature_class":"P",
    "gn:feature_code":"PPL",
    "gn:name":"Xinglonggangzi",
    "gn:population":0,
    "gn:timezone":"Asia/Shanghai",
    "iso:country":"CN",
    "name:zho_x_preferred":[
        "\u5174\u9686\u5c97\u5b50"
    ],
    "wof:name":"Xinglonggangzi",
    "wof:placetype":"locality"
},
  "geometry": {"coordinates":[122.345,41.5196],"type":"Point"}
}