{
  "type": "Feature",
  "properties": {
    "gn:admin1_code":"16",
    "gn:asciiname":"Zhulinjiao",
    "gn:country_code":"CN",
    "gn:dem":343,
    "gn:feature_class":"P",
    "gn:feature_code":"PPL",
    "gn:name":"Zhulinjiao",
    "gn:population":0,
    "gn:timezone":"Asia/Shanghai",
    "iso:country":"CN",
    "name:zho_x_preferred":[
        "\u7af9\u6797\u811a"
    ],
    "wof:name":"Zhulinjiao",
    "wof:placetype":"locality"
},
  "geometry": {"coordinates":[110.767,25.5303],"type":"Point"}
}