{
  "type": "Feature",
  "properties": {
    "gn:admin1_code":"30",
    "gn:asciiname":"Dafang",
    "gn:country_code":"CN",
    "gn:dem":253,
    "gn:feature_class":"P",
    "gn:feature_code":"PPLA4",
    "gn:name":"Dafang",
    "gn:population":0,
    "gn:timezone":"Asia/Shanghai",
    "iso:country":"CN",
    "name:und_x_variant":[
        "\u5927\u65b9",
        "Dafang Zhen",
        "\u5927\u65b9\u9547"
    ],
    "wof:name":"Dafang",
    "wof:placetype":"locality"
},
  "geometry": {"coordinates":[111.57988,22.97108],"type":"Point"}
}