{
  "type": "Feature",
  "properties": {
    "gn:admin1_code":"18",
    "gn:asciiname":"Malaotian",
    "gn:country_code":"CN",
    "gn:dem":1281,
    "gn:feature_class":"P",
    "gn:feature_code":"PPL",
    "gn:name":"Malaotian",
    "gn:population":0,
    "gn:timezone":"Asia/Shanghai",
    "iso:country":"CN",
    "name:zho_x_preferred":[
        "\u9a6c\u8001\u7530"
    ],
    "wof:name":"Malaotian",
    "wof:placetype":"locality"
},
  "geometry": {"coordinates":[105.42100000000001,25.7456],"type":"Point"}
}