{
  "type": "Feature",
  "properties": {
    "gn:admin1_code":"32.0",
    "gn:asciiname":"Juewucun",
    "gn:country_code":"CN",
    "gn:dem":4273,
    "gn:feature_class":"P",
    "gn:feature_code":"PPL",
    "gn:name":"Juewucun",
    "gn:population":0,
    "gn:timezone":"Asia/Shanghai",
    "iso:country":"CN",
    "name:und_x_variant":[
        "Ch\u00fceh-wu-ssu",
        "Jumanggoin",
        "Juewucun"
    ],
    "name:zho_x_preferred":[
        "\u89c9\u609f\u6751"
    ],
    "wof:name":"Juewucun",
    "wof:placetype":"locality"
},
  "geometry": {"coordinates":[98.56218,32.39811],"type":"Point"}
}