{
  "type": "Feature",
  "properties": {
    "gn:admin1_code":"9.0",
    "gn:asciiname":"Dadengzhuang",
    "gn:country_code":"CN",
    "gn:dem":78,
    "gn:feature_class":"P",
    "gn:feature_code":"PPL",
    "gn:name":"Dadengzhuang",
    "gn:population":0,
    "gn:timezone":"Asia/Shanghai",
    "iso:country":"CN",
    "name:zho_x_preferred":[
        "\u5927\u9093\u5e84"
    ],
    "wof:name":"Dadengzhuang",
    "wof:placetype":"locality"
},
  "geometry": {"coordinates":[114.18415,32.53955],"type":"Point"}
}