{
  "type": "Feature",
  "properties": {
    "gn:admin1_code":"29.0",
    "gn:asciiname":"Zuohemu",
    "gn:country_code":"CN",
    "gn:dem":2024,
    "gn:feature_class":"P",
    "gn:feature_code":"PPL",
    "gn:name":"Zuohemu",
    "gn:population":0,
    "gn:timezone":"Asia/Shanghai",
    "iso:country":"CN",
    "name:zho_x_preferred":[
        "\u5de6\u5408\u6bcd"
    ],
    "wof:name":"Zuohemu",
    "wof:placetype":"locality"
},
  "geometry": {"coordinates":[103.827,23.3288],"type":"Point"}
}