{
  "type": "Feature",
  "properties": {
    "gn:admin1_code":"32.0",
    "gn:asciiname":"Du'er",
    "gn:country_code":"CN",
    "gn:dem":2294,
    "gn:feature_class":"P",
    "gn:feature_code":"PPL",
    "gn:name":"Du\u2019er",
    "gn:population":0,
    "gn:timezone":"Asia/Shanghai",
    "iso:country":"CN",
    "name:und_x_variant":[
        "Du\u2019er"
    ],
    "name:zho_x_preferred":[
        "\u90fd\u5c14"
    ],
    "wof:name":"Du'er",
    "wof:placetype":"locality"
},
  "geometry": {"coordinates":[102.601,27.6626],"type":"Point"}
}