{
  "type": "Feature",
  "properties": {
    "gn:admin1_code":"16.0",
    "gn:asciiname":"Dadi",
    "gn:country_code":"CN",
    "gn:dem":59,
    "gn:feature_class":"P",
    "gn:feature_code":"PPL",
    "gn:name":"Dadi",
    "gn:population":0,
    "gn:timezone":"Asia/Shanghai",
    "iso:country":"CN",
    "name:ceb_x_preferred":[
        "Dadi"
    ],
    "name:deu_x_preferred":[
        "Dadi"
    ],
    "name:ita_x_preferred":[
        "Dadi"
    ],
    "name:pol_x_preferred":[
        "Dadi"
    ],
    "name:rus_x_preferred":[
        "Dadi"
    ],
    "name:swe_x_preferred":[
        "Dadi"
    ],
    "name:zho_x_preferred":[
        "\u5927\u5730"
    ],
    "wof:name":"Dadi",
    "wof:placetype":"locality"
},
  "geometry": {"coordinates":[111.521,23.6893],"type":"Point"}
}