{
  "type": "Feature",
  "properties": {
    "gn:admin1_code":"12.0",
    "gn:asciiname":"Tuofengling",
    "gn:country_code":"CN",
    "gn:dem":63,
    "gn:feature_class":"P",
    "gn:feature_code":"PPL",
    "gn:name":"Tuofengling",
    "gn:population":0,
    "gn:timezone":"Asia/Shanghai",
    "iso:country":"CN",
    "name:zho_x_preferred":[
        "Tuofengling"
    ],
    "name:zho_x_variant":[
        "\u9a7c\u5cf0\u5cad"
    ],
    "wof:name":"Tuofengling",
    "wof:placetype":"locality"
},
  "geometry": {"coordinates":[114.58351,29.90322],"type":"Point"}
}