{
  "type": "Feature",
  "properties": {
    "gn:admin1_code":"07",
    "gn:asciiname":"Qiaxi",
    "gn:country_code":"CN",
    "gn:dem":285,
    "gn:feature_class":"P",
    "gn:feature_code":"PPL",
    "gn:name":"Qiaxi",
    "gn:population":0,
    "gn:timezone":"Asia/Shanghai",
    "iso:country":"CN",
    "name:zho_x_preferred":[
        "\u6d3d\u6eaa"
    ],
    "wof:name":"Qiaxi",
    "wof:placetype":"locality"
},
  "geometry": {"coordinates":[116.18698000000001,24.9511],"type":"Point"}
}