{
  "type": "Feature",
  "properties": {
    "gn:admin1_code":"4.0",
    "gn:asciiname":"Qiuhucun",
    "gn:country_code":"CN",
    "gn:dem":31,
    "gn:feature_class":"P",
    "gn:feature_code":"PPL",
    "gn:name":"Qiuhucun",
    "gn:population":0,
    "gn:timezone":"Asia/Shanghai",
    "iso:country":"CN",
    "name:zho_x_preferred":[
        "\u79cb\u6e56\u6751"
    ],
    "wof:name":"Qiuhucun",
    "wof:placetype":"locality"
},
  "geometry": {"coordinates":[119.09631,31.57928],"type":"Point"}
}