{
  "type": "Feature",
  "properties": {
    "gn:admin1_code":"4.0",
    "gn:asciiname":"Gaoyao",
    "gn:country_code":"CN",
    "gn:dem":2,
    "gn:feature_class":"P",
    "gn:feature_code":"PPL",
    "gn:name":"Gaoyao",
    "gn:population":0,
    "gn:timezone":"Asia/Shanghai",
    "iso:country":"CN",
    "name:und_x_variant":[
        "\u9ad8\u7a91"
    ],
    "name:zho_x_preferred":[
        "\u9ad8\u7a91"
    ],
    "wof:name":"Gaoyao",
    "wof:placetype":"locality"
},
  "geometry": {"coordinates":[120.32758,32.77366],"type":"Point"}
}