{
  "type": "Feature",
  "properties": {
    "gn:admin1_code":"30.0",
    "gn:asciiname":"Jiuhengshan",
    "gn:country_code":"CN",
    "gn:dem":73,
    "gn:feature_class":"P",
    "gn:feature_code":"PPL",
    "gn:name":"Jiuhengshan",
    "gn:population":0,
    "gn:timezone":"Asia/Shanghai",
    "iso:country":"CN",
    "name:zho_x_preferred":[
        "\u65e7\u6a2a\u5c71"
    ],
    "wof:name":"Jiuhengshan",
    "wof:placetype":"locality"
},
  "geometry": {"coordinates":[112.14981,22.61564],"type":"Point"}
}