{
  "type": "Feature",
  "properties": {
    "gn:admin1_code":"2.0",
    "gn:asciiname":"Qiao'ao",
    "gn:country_code":"CN",
    "gn:dem":120,
    "gn:feature_class":"P",
    "gn:feature_code":"PPL",
    "gn:name":"Qiao\u2019ao",
    "gn:population":0,
    "gn:timezone":"Asia/Shanghai",
    "iso:country":"CN",
    "name:und_x_variant":[
        "Qiao\u2019ao"
    ],
    "name:zho_x_preferred":[
        "\u6865\u5c99"
    ],
    "wof:name":"Qiao'ao",
    "wof:placetype":"locality"
},
  "geometry": {"coordinates":[120.74003999999999,29.79025],"type":"Point"}
}