{
  "type": "Feature",
  "properties": {
    "gn:admin1_code":"32.0",
    "gn:asciiname":"Dushuliang",
    "gn:country_code":"CN",
    "gn:dem":402,
    "gn:feature_class":"P",
    "gn:feature_code":"PPL",
    "gn:name":"Dushuliang",
    "gn:population":0,
    "gn:timezone":"Asia/Shanghai",
    "iso:country":"CN",
    "name:zho_x_preferred":[
        "\u72ec\u6811\u6881"
    ],
    "wof:name":"Dushuliang",
    "wof:placetype":"locality"
},
  "geometry": {"coordinates":[107.968,31.3501],"type":"Point"}
}