{
  "type": "Feature",
  "properties": {
    "gn:admin1_code":"2",
    "gn:asciiname":"Xiatian",
    "gn:country_code":"CN",
    "gn:dem":703,
    "gn:feature_class":"P",
    "gn:feature_code":"PPL",
    "gn:name":"Xiatian",
    "gn:population":0,
    "gn:timezone":"Asia/Shanghai",
    "iso:country":"CN",
    "name:zho_x_preferred":[
        "\u590f\u7530"
    ],
    "wof:name":"Xiatian",
    "wof:placetype":"locality"
},
  "geometry": {"coordinates":[119.74028,27.73361],"type":"Point"}
}