{
  "type": "Feature",
  "properties": {
    "gn:admin1_code":"24.0",
    "gn:asciiname":"Geta",
    "gn:country_code":"CN",
    "gn:dem":1026,
    "gn:feature_class":"P",
    "gn:feature_code":"PPL",
    "gn:name":"Geta",
    "gn:population":0,
    "gn:timezone":"Asia/Shanghai",
    "iso:country":"CN",
    "name:bul_x_preferred":[
        "\u0413\u0435\u0442\u0430"
    ],
    "name:cat_x_preferred":[
        "Geta"
    ],
    "name:ceb_x_preferred":[
        "Geta"
    ],
    "name:deu_x_preferred":[
        "Geta"
    ],
    "name:ell_x_preferred":[
        "\u0393\u03ad\u03c4\u03b1\u03c2"
    ],
    "name:fin_x_preferred":[
        "Geta"
    ],
    "name:fra_x_preferred":[
        "Geta"
    ],
    "name:hrv_x_preferred":[
        "Geta"
    ],
    "name:ind_x_preferred":[
        "Geta"
    ],
    "name:ita_x_preferred":[
        "Geta"
    ],
    "name:nld_x_preferred":[
        "Geta"
    ],
    "name:pol_x_preferred":[
        "Geta"
    ],
    "name:por_x_preferred":[
        "Geta"
    ],
    "name:sco_x_preferred":[
        "Geta"
    ],
    "name:spa_x_preferred":[
        "Geta"
    ],
    "name:srp_x_preferred":[
        "\u0413\u0435\u0442\u0430"
    ],
    "name:swe_x_preferred":[
        "Geta"
    ],
    "name:zho_x_preferred":[
        "\u572a\u5854"
    ],
    "wof:name":"Geta",
    "wof:placetype":"locality"
},
  "geometry": {"coordinates":[110.65638,36.4082],"type":"Point"}
}