{
  "type": "Feature",
  "properties": {
    "gn:admin1_code":"11",
    "gn:asciiname":"Mengcheng",
    "gn:country_code":"CN",
    "gn:dem":124,
    "gn:feature_class":"P",
    "gn:feature_code":"PPL",
    "gn:name":"Mengcheng",
    "gn:population":0,
    "gn:timezone":"Asia/Shanghai",
    "iso:country":"CN",
    "name:zho_x_preferred":[
        "\u5b5f\u57ce"
    ],
    "wof:name":"Mengcheng",
    "wof:placetype":"locality"
},
  "geometry": {"coordinates":[113.55597,29.25764],"type":"Point"}
}