{
  "type": "Feature",
  "properties": {
    "gn:admin1_code":"2.0",
    "gn:asciiname":"Huangtanyuan",
    "gn:country_code":"CN",
    "gn:dem":256,
    "gn:feature_class":"P",
    "gn:feature_code":"PPL",
    "gn:name":"Huangtanyuan",
    "gn:population":0,
    "gn:timezone":"Asia/Shanghai",
    "iso:country":"CN",
    "name:zho_x_preferred":[
        "\u9ec4\u575b\u6c85"
    ],
    "wof:name":"Huangtanyuan",
    "wof:placetype":"locality"
},
  "geometry": {"coordinates":[118.97275,28.78273],"type":"Point"}
}