{
  "type": "Feature",
  "properties": {
    "gn:admin1_code":"26.0",
    "gn:asciiname":"Piaocaotan",
    "gn:country_code":"CN",
    "gn:dem":1110,
    "gn:feature_class":"P",
    "gn:feature_code":"PPL",
    "gn:name":"Piaocaotan",
    "gn:population":0,
    "gn:timezone":"Asia/Shanghai",
    "iso:country":"CN",
    "name:und_x_variant":[
        "\u6f02\u8349\u6ee9",
        "Piaocaotan"
    ],
    "wof:name":"Piaocaotan",
    "wof:placetype":"locality"
},
  "geometry": {"coordinates":[107.83651999999999,33.46291],"type":"Point"}
}