{
  "type": "Feature",
  "properties": {
    "gn:admin1_code":"26.0",
    "gn:asciiname":"Majiageta",
    "gn:country_code":"CN",
    "gn:dem":1034,
    "gn:feature_class":"P",
    "gn:feature_code":"PPL",
    "gn:name":"Majiageta",
    "gn:population":0,
    "gn:timezone":"Asia/Shanghai",
    "iso:country":"CN",
    "name:zho_x_preferred":[
        "\u9a6c\u5bb6\u572a\u5854"
    ],
    "wof:name":"Majiageta",
    "wof:placetype":"locality"
},
  "geometry": {"coordinates":[109.83938999999999,37.0401],"type":"Point"}
}