{
  "type": "Feature",
  "properties": {
    "gn:admin1_code":"15.0",
    "gn:asciiname":"Zhaizili",
    "gn:country_code":"CN",
    "gn:dem":1454,
    "gn:feature_class":"P",
    "gn:feature_code":"PPL",
    "gn:name":"Zhaizili",
    "gn:population":0,
    "gn:timezone":"Asia/Shanghai",
    "iso:country":"CN",
    "name:zho_x_preferred":[
        "\u5be8\u5b50\u91cc"
    ],
    "wof:name":"Zhaizili",
    "wof:placetype":"locality"
},
  "geometry": {"coordinates":[105.03230000000001,33.7496],"type":"Point"}
}