{
  "type": "Feature",
  "properties": {
    "gn:admin1_code":"10.0",
    "gn:asciiname":"Dailiuzhuang",
    "gn:country_code":"CN",
    "gn:dem":16,
    "gn:feature_class":"P",
    "gn:feature_code":"PPL",
    "gn:name":"Dailiuzhuang",
    "gn:population":0,
    "gn:timezone":"Asia/Shanghai",
    "iso:country":"CN",
    "name:zho_x_preferred":[
        "\u6234\u5218\u5e84"
    ],
    "wof:name":"Dailiuzhuang",
    "wof:placetype":"locality"
},
  "geometry": {"coordinates":[115.91,38.3545],"type":"Point"}
}