{
  "type": "Feature",
  "properties": {
    "gn:admin1_code":"8.0",
    "gn:asciiname":"Qianjiashutun",
    "gn:country_code":"CN",
    "gn:dem":170,
    "gn:feature_class":"P",
    "gn:feature_code":"PPL",
    "gn:name":"Qianjiashutun",
    "gn:population":0,
    "gn:timezone":"Asia/Shanghai",
    "iso:country":"CN",
    "name:zho_x_preferred":[
        "\u524d\u5bb6\u5c5e\u5c6f"
    ],
    "wof:name":"Qianjiashutun",
    "wof:placetype":"locality"
},
  "geometry": {"coordinates":[125.45171999999999,47.15824],"type":"Point"}
}