{
  "type": "Feature",
  "properties": {
    "gn:admin1_code":"16.0",
    "gn:asciiname":"Kenba",
    "gn:country_code":"CN",
    "gn:dem":552,
    "gn:feature_class":"P",
    "gn:feature_code":"PPL",
    "gn:name":"Kenba",
    "gn:population":0,
    "gn:timezone":"Asia/Shanghai",
    "iso:country":"CN",
    "name:zho_x_preferred":[
        "\u80af\u575d"
    ],
    "wof:name":"Kenba",
    "wof:placetype":"locality"
},
  "geometry": {"coordinates":[108.46299999999999,24.7507],"type":"Point"}
}