{
  "type": "Feature",
  "properties": {
    "gn:admin1_code":"21.0",
    "gn:asciiname":"Qibaihu",
    "gn:country_code":"CN",
    "gn:dem":1414,
    "gn:feature_class":"P",
    "gn:feature_code":"PPL",
    "gn:name":"Qibaihu",
    "gn:population":0,
    "gn:timezone":"Asia/Shanghai",
    "iso:country":"CN",
    "name:zho_x_preferred":[
        "\u4e03\u767e\u6237"
    ],
    "wof:name":"Qibaihu",
    "wof:placetype":"locality"
},
  "geometry": {"coordinates":[106.0635,36.7255],"type":"Point"}
}