{
  "type": "Feature",
  "properties": {
    "gn:admin1_code":"15.0",
    "gn:asciiname":"Hejiachuan",
    "gn:country_code":"CN",
    "gn:dem":2094,
    "gn:feature_class":"P",
    "gn:feature_code":"PPL",
    "gn:name":"Hejiachuan",
    "gn:population":0,
    "gn:timezone":"Asia/Shanghai",
    "iso:country":"CN",
    "name:zho_x_preferred":[
        "\u4f55\u5bb6\u5ddd"
    ],
    "wof:name":"Hejiachuan",
    "wof:placetype":"locality"
},
  "geometry": {"coordinates":[104.026,35.5288],"type":"Point"}
}