{
  "type": "Feature",
  "properties": {
    "gn:admin1_code":"19.0",
    "gn:asciiname":"Guojia Buzi",
    "gn:country_code":"CN",
    "gn:dem":184,
    "gn:feature_class":"P",
    "gn:feature_code":"PPL",
    "gn:name":"Guojia Buzi",
    "gn:population":0,
    "gn:timezone":"Asia/Shanghai",
    "iso:country":"CN",
    "name:zho_x_preferred":[
        "\u90ed\u5bb6\u5821\u5b50"
    ],
    "wof:name":"Guojia Buzi",
    "wof:placetype":"locality"
},
  "geometry": {"coordinates":[124.419,42.5452],"type":"Point"}
}