{
  "type": "Feature",
  "properties": {
    "gn:admin1_code":"29.0",
    "gn:asciiname":"Moguchang",
    "gn:country_code":"CN",
    "gn:dem":2040,
    "gn:feature_class":"P",
    "gn:feature_code":"PPL",
    "gn:name":"Moguchang",
    "gn:population":0,
    "gn:timezone":"Asia/Shanghai",
    "iso:country":"CN",
    "name:zho_x_preferred":[
        "\u8611\u83c7\u573a"
    ],
    "wof:name":"Moguchang",
    "wof:placetype":"locality"
},
  "geometry": {"coordinates":[98.80329999999999,25.895],"type":"Point"}
}