{
  "type": "Feature",
  "properties": {
    "gn:admin1_code":"2.0",
    "gn:asciiname":"Jianhai",
    "gn:country_code":"CN",
    "gn:dem":14,
    "gn:feature_class":"P",
    "gn:feature_code":"PPL",
    "gn:name":"Jianhai",
    "gn:population":0,
    "gn:timezone":"Asia/Shanghai",
    "iso:country":"CN",
    "name:und_x_variant":[
        "\u5efa\u6d77"
    ],
    "wof:name":"Jianhai",
    "wof:placetype":"locality"
},
  "geometry": {"coordinates":[120.68170000000001,30.11283],"type":"Point"}
}