{
  "type": "Feature",
  "properties": {
    "gn:admin1_code":"24.0",
    "gn:asciiname":"Maidishan",
    "gn:country_code":"CN",
    "gn:dem":1209,
    "gn:feature_class":"P",
    "gn:feature_code":"PPL",
    "gn:name":"Maidishan",
    "gn:population":0,
    "gn:timezone":"Asia/Shanghai",
    "iso:country":"CN",
    "name:zho_x_preferred":[
        "\u9ea6\u5730\u5c71"
    ],
    "wof:name":"Maidishan",
    "wof:placetype":"locality"
},
  "geometry": {"coordinates":[111.1605,38.51787],"type":"Point"}
}