{
  "type": "Feature",
  "properties": {
    "gn:admin1_code":"8.0",
    "gn:asciiname":"Xinhongcun",
    "gn:country_code":"CN",
    "gn:dem":109,
    "gn:feature_class":"P",
    "gn:feature_code":"PPL",
    "gn:name":"Xinhongcun",
    "gn:population":0,
    "gn:timezone":"Asia/Shanghai",
    "iso:country":"CN",
    "name:zho_x_preferred":[
        "\u65b0\u5b8f\u6751"
    ],
    "wof:name":"Xinhongcun",
    "wof:placetype":"locality"
},
  "geometry": {"coordinates":[129.77046000000001,46.39196],"type":"Point"}
}