{
  "type": "Feature",
  "properties": {
    "gn:admin1_code":"30.0",
    "gn:asciiname":"Jingloucun",
    "gn:country_code":"CN",
    "gn:dem":246,
    "gn:feature_class":"P",
    "gn:feature_code":"PPL",
    "gn:name":"Jingloucun",
    "gn:population":0,
    "gn:timezone":"Asia/Shanghai",
    "iso:country":"CN",
    "name:zho_x_preferred":[
        "\u5f84\u697c\u6751"
    ],
    "wof:name":"Jingloucun",
    "wof:placetype":"locality"
},
  "geometry": {"coordinates":[116.78082000000001,23.85744],"type":"Point"}
}