{
  "type": "Feature",
  "properties": {
    "gn:admin1_code":"14",
    "gn:asciiname":"Xoboxar",
    "gn:country_code":"CN",
    "gn:dem":4185,
    "gn:feature_class":"P",
    "gn:feature_code":"PPL",
    "gn:name":"Xoboxar",
    "gn:population":0,
    "gn:timezone":"Asia/Urumqi",
    "iso:country":"CN",
    "name:bod_x_preferred":[
        "\u0f64\u0f7c\u0f0b\u0f54\u0f7c\u0f0b\u0f64\u0f62"
    ],
    "wof:name":"Xoboxar",
    "wof:placetype":"locality"
},
  "geometry": {"coordinates":[92.33717,28.51342],"type":"Point"}
}