{
  "type": "Feature",
  "properties": {
    "gn:admin1_code":"30",
    "gn:asciiname":"Nanjuncun",
    "gn:country_code":"CN",
    "gn:dem":23,
    "gn:feature_class":"P",
    "gn:feature_code":"PPL",
    "gn:name":"Nanjuncun",
    "gn:population":0,
    "gn:timezone":"Asia/Urumqi",
    "iso:country":"CN",
    "name:zho_x_preferred":[
        "\u5357\u90e1\u6751"
    ],
    "wof:name":"Nanjuncun",
    "wof:placetype":"locality"
},
  "geometry": {"coordinates":[110.05794,20.97491],"type":"Point"}
}