{
  "type": "Feature",
  "properties": {
    "gn:admin1_code":"3.0",
    "gn:asciiname":"Chenluo",
    "gn:country_code":"CN",
    "gn:dem":628,
    "gn:feature_class":"P",
    "gn:feature_code":"PPL",
    "gn:name":"Chenluo",
    "gn:population":0,
    "gn:timezone":"Asia/Shanghai",
    "iso:country":"CN",
    "name:und_x_variant":[
        "\u9648\u7f57"
    ],
    "wof:name":"Chenluo",
    "wof:placetype":"locality"
},
  "geometry": {"coordinates":[116.1892,26.5572],"type":"Point"}
}