{
  "type": "Feature",
  "properties": {
    "gn:admin1_code":"9.0",
    "gn:asciiname":"Houtuo",
    "gn:country_code":"CN",
    "gn:dem":940,
    "gn:feature_class":"P",
    "gn:feature_code":"PPL",
    "gn:name":"Houtuo",
    "gn:population":0,
    "gn:timezone":"Asia/Shanghai",
    "iso:country":"CN",
    "name:zho_x_preferred":[
        "\u540e\u9a7c"
    ],
    "wof:name":"Houtuo",
    "wof:placetype":"locality"
},
  "geometry": {"coordinates":[110.91459999999999,34.01851],"type":"Point"}
}