{
  "type": "Feature",
  "properties": {
    "gn:admin1_code":"18",
    "gn:asciiname":"Shipentou",
    "gn:country_code":"CN",
    "gn:dem":616,
    "gn:feature_class":"P",
    "gn:feature_code":"PPL",
    "gn:name":"Shipentou",
    "gn:population":0,
    "gn:timezone":"Asia/Shanghai",
    "iso:country":"CN",
    "name:zho_x_preferred":[
        "\u77f3\u76c6\u5934"
    ],
    "wof:name":"Shipentou",
    "wof:placetype":"locality"
},
  "geometry": {"coordinates":[107.97499999999999,27.9399],"type":"Point"}
}