{
  "type": "Feature",
  "properties": {
    "iso:country":"CN",
    "name:ceb_x_preferred":[
        "Wugong Xian"
    ],
    "name:deu_x_preferred":[
        "Wugong"
    ],
    "name:eng_x_preferred":[
        "Wugong County"
    ],
    "name:fas_x_preferred":[
        "\u0634\u0647\u0631\u0633\u062a\u0627\u0646 \u0648\u0648\u06af\u0648\u0646\u06af"
    ],
    "name:gan_x_preferred":[
        "\u6b66\u529f\u53bf"
    ],
    "name:ind_x_preferred":[
        "Kabupaten Wugong"
    ],
    "name:jpn_x_preferred":[
        "\u6b66\u529f\u770c"
    ],
    "name:kor_x_preferred":[
        "\uc6b0\uad81\ud604"
    ],
    "name:nan_x_preferred":[
        "B\u00fa-kong-ko\u0101n"
    ],
    "name:nld_x_preferred":[
        "Wugong"
    ],
    "name:nob_x_preferred":[
        "Wugong"
    ],
    "name:rus_x_preferred":[
        "\u0423\u0433\u0443\u043d"
    ],
    "name:spa_x_preferred":[
        "Wugong"
    ],
    "name:swe_x_preferred":[
        "Wugong"
    ],
    "name:vie_x_preferred":[
        "V\u0169 C\u00f4ng"
    ],
    "name:wuu_x_preferred":[
        "\u6b66\u529f\u53bf"
    ],
    "name:yue_x_preferred":[
        "\u6b66\u529f\u7e23"
    ],
    "name:zho_x_preferred":[
        "\u6b66\u529f\u53bf"
    ],
    "qs:name":"\u6b66\u529f\u53bf",
    "qs:name_adm0":"\u4e2d\u570b",
    "qs:name_adm1":"\u965d\u897f\u7701",
    "qs:photos":51,
    "qs:photos_1k":10,
    "qs:photos_9k":1,
    "qs:photos_9r":3,
    "qs:photos_all":116,
    "qs:photos_sr":2,
    "qs:placetype":"LocalAdmin",
    "qs:pop_sr":"0",
    "wd:wordcount":85,
    "wof:name":"\u6b66\u529f\u53bf",
    "wof:placetype":"localadmin"
},
  "geometry": {"coordinates":[108.069,34.2775],"type":"Point"}
}