{
  "type": "Feature",
  "properties": {
    "iso:country":"CN",
    "qs:name":"\u6b66\u529f\u53bf",
    "qs:name_adm0":"\u4e2d\u570b",
    "qs:name_adm1":"\u965d\u897f\u7701",
    "qs:photos":51,
    "qs:photos_1k":10,
    "qs:photos_9k":1,
    "qs:photos_9r":3,
    "qs:photos_all":116,
    "qs:photos_sr":2,
    "qs:placetype":"LocalAdmin",
    "qs:pop_sr":"0",
    "wd:wordcount":85,
    "wof:name":"\u6b66\u529f\u53bf",
    "wof:placetype":"localadmin"
},
  "geometry": {"coordinates":[108.069,34.2775],"type":"Point"}
}