{
  "type": "Feature",
  "properties": {
    "gn:admin1_code":"29",
    "gn:asciiname":"Guoshuigou",
    "gn:country_code":"CN",
    "gn:dem":1966,
    "gn:feature_class":"P",
    "gn:feature_code":"PPL",
    "gn:name":"Guoshuigou",
    "gn:population":0,
    "gn:timezone":"Asia/Shanghai",
    "iso:country":"CN",
    "name:zho_x_preferred":[
        "\u8fc7\u6c34\u6c9f"
    ],
    "wof:name":"Guoshuigou",
    "wof:placetype":"locality"
},
  "geometry": {"coordinates":[102.05885000000001,24.77866],"type":"Point"}
}