{
  "type": "Feature",
  "properties": {
    "gn:admin1_code":"19.0",
    "gn:asciiname":"Xingjiacun",
    "gn:country_code":"CN",
    "gn:dem":5,
    "gn:feature_class":"P",
    "gn:feature_code":"PPL",
    "gn:name":"Xingjiacun",
    "gn:population":0,
    "gn:timezone":"Asia/Shanghai",
    "iso:country":"CN",
    "name:und_x_variant":[
        "\u90a2\u5bb6\u6811"
    ],
    "wof:name":"Xingjiacun",
    "wof:placetype":"locality"
},
  "geometry": {"coordinates":[122.15148000000001,40.7944],"type":"Point"}
}