{
  "type": "Feature",
  "properties": {
    "gn:admin1_code":"14.0",
    "gn:asciiname":"Dazi",
    "gn:country_code":"CN",
    "gn:dem":3744,
    "gn:feature_class":"P",
    "gn:feature_code":"PPL",
    "gn:name":"Dazi",
    "gn:population":0,
    "gn:timezone":"Asia/Urumqi",
    "iso:country":"CN",
    "name:zho_x_preferred":[
        "\u8fbe\u5b5c"
    ],
    "wof:name":"Dazi",
    "wof:placetype":"locality"
},
  "geometry": {"coordinates":[91.49599000000001,29.82091],"type":"Point"}
}