{
  "type": "Feature",
  "properties": {
    "gn:admin1_code":"3.0",
    "gn:asciiname":"Disiling",
    "gn:country_code":"CN",
    "gn:dem":60,
    "gn:feature_class":"P",
    "gn:feature_code":"PPL",
    "gn:name":"Disiling",
    "gn:population":0,
    "gn:timezone":"Asia/Shanghai",
    "iso:country":"CN",
    "name:und_x_variant":[
        "\u5730\u56db\u5cad"
    ],
    "wof:name":"Disiling",
    "wof:placetype":"locality"
},
  "geometry": {"coordinates":[115.36839999999999,28.86948],"type":"Point"}
}