{
  "type": "Feature",
  "properties": {
    "gn:admin1_code":"12.0",
    "gn:asciiname":"Songnaizhou",
    "gn:country_code":"CN",
    "gn:dem":29,
    "gn:feature_class":"P",
    "gn:feature_code":"PPL",
    "gn:name":"Songnaizhou",
    "gn:population":0,
    "gn:timezone":"Asia/Shanghai",
    "iso:country":"CN",
    "name:zho_x_preferred":[
        "\u9001\u5976\u6d32"
    ],
    "wof:name":"Songnaizhou",
    "wof:placetype":"locality"
},
  "geometry": {"coordinates":[113.71762,29.94317],"type":"Point"}
}