{
  "type": "Feature",
  "properties": {
    "gn:admin1_code":"30.0",
    "gn:asciiname":"Houkengcun",
    "gn:country_code":"CN",
    "gn:dem":13,
    "gn:feature_class":"P",
    "gn:feature_code":"PPL",
    "gn:name":"Houkengcun",
    "gn:population":0,
    "gn:timezone":"Asia/Shanghai",
    "iso:country":"CN",
    "name:zho_x_preferred":[
        "\u540e\u5751\u6751"
    ],
    "wof:name":"Houkengcun",
    "wof:placetype":"locality"
},
  "geometry": {"coordinates":[116.22836,23.45347000000001],"type":"Point"}
}