{
  "type": "Feature",
  "properties": {
    "gn:admin1_code":"29.0",
    "gn:asciiname":"Lukoushao",
    "gn:country_code":"CN",
    "gn:dem":2014,
    "gn:feature_class":"P",
    "gn:feature_code":"PPL",
    "gn:name":"Lukoushao",
    "gn:population":0,
    "gn:timezone":"Asia/Shanghai",
    "iso:country":"CN",
    "name:zho_x_preferred":[
        "\u9c81\u53e3\u54e8"
    ],
    "wof:name":"Lukoushao",
    "wof:placetype":"locality"
},
  "geometry": {"coordinates":[103.417,25.5074],"type":"Point"}
}