{
  "type": "Feature",
  "properties": {
    "gn:admin1_code":"4.0",
    "gn:asciiname":"Minlian Shi'erzu",
    "gn:country_code":"CN",
    "gn:dem":3,
    "gn:feature_class":"P",
    "gn:feature_code":"PPLF",
    "gn:name":"Minlian Shi\u2019erzu",
    "gn:population":0,
    "gn:timezone":"Asia/Shanghai",
    "iso:country":"CN",
    "name:und_x_variant":[
        "\u6c11\u8054\u5341\u4e8c\u7ec4"
    ],
    "name:zho_x_preferred":[
        "Minlian Shi\u2019erzu"
    ],
    "name:zho_x_variant":[
        "\u6c11\u8054\u5341\u4e8c\u7ec4"
    ],
    "wof:name":"Minlian Shi'erzu",
    "wof:placetype":"locality"
},
  "geometry": {"coordinates":[120.32572999999999,32.04883],"type":"Point"}
}