{
  "type": "Feature",
  "properties": {
    "gn:admin1_code":"4.0",
    "gn:asciiname":"Jingtailu",
    "gn:country_code":"CN",
    "gn:dem":7,
    "gn:feature_class":"P",
    "gn:feature_code":"PPLA4",
    "gn:name":"Jingtailu",
    "gn:population":0,
    "gn:timezone":"Asia/Shanghai",
    "iso:country":"CN",
    "name:und_x_variant":[
        "Jiuliqiao",
        "\u4e5d\u91cc\u6865",
        "Taidong",
        "Taidong Zhen",
        "\u6cf0\u4e1c",
        "\u6cf0\u4e1c\u9547",
        "Jingtailu",
        "Jingtailu Jiedao"
    ],
    "name:zho_x_preferred":[
        "\u4eac\u6cf0\u8def"
    ],
    "name:zho_x_variant":[
        "\u4eac\u6cf0\u8def\u8857\u9053"
    ],
    "wof:name":"Jingtailu",
    "wof:placetype":"locality"
},
  "geometry": {"coordinates":[119.97172999999999,32.50471],"type":"Point"}
}