{
  "type": "Feature",
  "properties": {
    "gn:admin1_code":"26.0",
    "gn:asciiname":"Anjiazhuang",
    "gn:country_code":"CN",
    "gn:dem":1395,
    "gn:feature_class":"P",
    "gn:feature_code":"PPL",
    "gn:name":"Anjiazhuang",
    "gn:population":0,
    "gn:timezone":"Asia/Shanghai",
    "iso:country":"CN",
    "name:und_x_variant":[
        "\u5b89\u5bb6\u5e84"
    ],
    "wof:name":"Anjiazhuang",
    "wof:placetype":"locality"
},
  "geometry": {"coordinates":[107.47676,34.82037],"type":"Point"}
}