{
  "type": "Feature",
  "properties": {
    "gn:admin1_code":"11.0",
    "gn:asciiname":"Tapiao",
    "gn:country_code":"CN",
    "gn:dem":653,
    "gn:feature_class":"P",
    "gn:feature_code":"PPL",
    "gn:name":"Tapiao",
    "gn:population":0,
    "gn:timezone":"Asia/Shanghai",
    "iso:country":"CN",
    "name:zho_x_preferred":[
        "\u8e0f\u6f02"
    ],
    "wof:name":"Tapiao",
    "wof:placetype":"locality"
},
  "geometry": {"coordinates":[109.77994,28.62501],"type":"Point"}
}