{
  "type": "Feature",
  "properties": {
    "gn:admin1_code":"4.0",
    "gn:asciiname":"Lujia Bandai",
    "gn:country_code":"CN",
    "gn:dem":3,
    "gn:feature_class":"P",
    "gn:feature_code":"PPL",
    "gn:name":"Lujia Bandai",
    "gn:population":0,
    "gn:timezone":"Asia/Shanghai",
    "iso:country":"CN",
    "name:zho_x_preferred":[
        "\u9646\u5bb6\u534a\u5788"
    ],
    "wof:name":"Lujia Bandai",
    "wof:placetype":"locality"
},
  "geometry": {"coordinates":[120.3359,32.05475999999999],"type":"Point"}
}