{
  "type": "Feature",
  "properties": {
    "gn:admin1_code":"13",
    "gn:asciiname":"Hongxing Yimuchang",
    "gn:country_code":"CN",
    "gn:dem":1607,
    "gn:feature_class":"P",
    "gn:feature_code":"PPLF",
    "gn:name":"Hongxing Yimuchang",
    "gn:population":0,
    "gn:timezone":"Asia/Urumqi",
    "iso:country":"CN",
    "name:und_x_variant":[
        "\u7ea2\u661f\u4e00\u7267\u573a"
    ],
    "wof:name":"Hongxing Yimuchang",
    "wof:placetype":"locality"
},
  "geometry": {"coordinates":[93.03324000000001,43.63557],"type":"Point"}
}