{
  "type": "Feature",
  "properties": {
    "gn:admin1_code":"29.0",
    "gn:asciiname":"Xiamalu",
    "gn:country_code":"CN",
    "gn:dem":1257,
    "gn:feature_class":"P",
    "gn:feature_code":"PPL",
    "gn:name":"Xiamalu",
    "gn:population":0,
    "gn:timezone":"Asia/Shanghai",
    "iso:country":"CN",
    "name:zho_x_preferred":[
        "\u4e0b\u9a6c\u9e7f"
    ],
    "wof:name":"Xiamalu",
    "wof:placetype":"locality"
},
  "geometry": {"coordinates":[99.6024,24.4319],"type":"Point"}
}