{
  "type": "Feature",
  "properties": {
    "gn:admin1_code":"16.0",
    "gn:asciiname":"Tiandong",
    "gn:country_code":"CN",
    "gn:dem":450,
    "gn:feature_class":"P",
    "gn:feature_code":"PPL",
    "gn:name":"Tiandong",
    "gn:population":0,
    "gn:timezone":"Asia/Shanghai",
    "iso:country":"CN",
    "name:zho_x_preferred":[
        "\u7530\u5cd2"
    ],
    "wof:name":"Tiandong",
    "wof:placetype":"locality"
},
  "geometry": {"coordinates":[107.934,24.5712],"type":"Point"}
}