{
  "type": "Feature",
  "properties": {
    "gn:admin1_code":"19",
    "gn:asciiname":"Chien-shan-tzu",
    "gn:country_code":"CN",
    "gn:dem":451,
    "gn:feature_class":"P",
    "gn:feature_code":"PPL",
    "gn:name":"Chien-shan-tzu",
    "gn:population":0,
    "gn:timezone":"Asia/Shanghai",
    "iso:country":"CN",
    "wof:name":"Chien-shan-tzu",
    "wof:placetype":"locality"
},
  "geometry": {"coordinates":[125.08444,41.96167],"type":"Point"}
}