{
  "type": "Feature",
  "properties": {
    "gn:admin1_code":"11.0",
    "gn:asciiname":"Jiangdouchong",
    "gn:country_code":"CN",
    "gn:dem":728,
    "gn:feature_class":"P",
    "gn:feature_code":"PPL",
    "gn:name":"Jiangdouchong",
    "gn:population":0,
    "gn:timezone":"Asia/Shanghai",
    "iso:country":"CN",
    "name:zho_x_preferred":[
        "\u6c5f\u8c46\u51b2"
    ],
    "wof:name":"Jiangdouchong",
    "wof:placetype":"locality"
},
  "geometry": {"coordinates":[110.36631,26.87766],"type":"Point"}
}