{
  "type": "Feature",
  "properties": {
    "gn:country":"CN",
    "gn:fcode":"ADM3",
    "gn:pop":0,
    "iso:country":"CN",
    "name:unk_x_variant":[
        "Shishi"
    ],
    "name:zho_x_preferred":[
        "\u77f3\u72ee\u5e02"
    ],
    "name:zho_x_variant":[
        "\u77f3\u72ee"
    ],
    "qs:name":"Shishi Shi",
    "qs:photos_9r":0,
    "qs:photos_sr":0,
    "qs:pop_sr":"0",
    "wd:wordcount":338,
    "wof:name":"Shishi Shi",
    "wof:placetype":"localadmin",
    "wof:population":0
},
  "geometry": {"coordinates":[118.70265000000001,24.72338],"type":"Point"}
}