{
  "type": "Feature",
  "properties": {
    "gn:country":"CN",
    "gn:fcode":"ADM3",
    "gn:pop":0,
    "iso:country":"CN",
    "name:ast_x_preferred":[
        "Shi Shi"
    ],
    "name:aze_x_preferred":[
        "\u015ei \u015ei"
    ],
    "name:deu_x_preferred":[
        "Shi Shi"
    ],
    "name:eng_x_preferred":[
        "Shi Shi"
    ],
    "name:jpn_x_preferred":[
        "\u77f3\u4e16"
    ],
    "name:kor_x_preferred":[
        "\uc11d\uc138"
    ],
    "name:nan_x_preferred":[
        "Chio\u030dh S\u00e8"
    ],
    "name:nld_x_preferred":[
        "Shi Shi"
    ],
    "name:rus_x_preferred":[
        "\u0428\u0438 \u0428\u0438"
    ],
    "name:spa_x_preferred":[
        "Shi Shi"
    ],
    "name:ukr_x_preferred":[
        "\u0428\u0438 \u0428\u0438"
    ],
    "name:unk_x_variant":[
        "Shishi"
    ],
    "name:vie_x_preferred":[
        "Th\u1ea1ch Th\u1ebf"
    ],
    "name:zho_x_preferred":[
        "\u77f3\u72ee\u5e02"
    ],
    "name:zho_x_variant":[
        "\u77f3\u72ee",
        "\u77f3\u4e16"
    ],
    "qs:name":"Shishi Shi",
    "qs:photos_9r":0,
    "qs:photos_sr":0,
    "qs:pop_sr":"0",
    "wd:wordcount":338,
    "wof:name":"Shishi Shi",
    "wof:placetype":"localadmin",
    "wof:population":0
},
  "geometry": {"coordinates":[118.70265000000001,24.72338],"type":"Point"}
}