{
  "type": "Feature",
  "properties": {
    "gn:admin1_code":"23",
    "gn:asciiname":"Guangfu",
    "gn:cc2":"CN",
    "gn:country_code":"CN",
    "gn:dem":2,
    "gn:feature_class":"P",
    "gn:feature_code":"PPL",
    "gn:name":"Guangfu",
    "gn:population":0,
    "gn:timezone":"Asia/Shanghai",
    "iso:country":"CN",
    "name:fra_x_preferred":[
        "Guangfu"
    ],
    "name:swe_x_preferred":[
        "Guangfu"
    ],
    "name:und_x_variant":[
        "Kuang-fu",
        "Guangfu",
        "\u5e7f\u798f"
    ],
    "wof:name":"Guangfu",
    "wof:placetype":"locality"
},
  "geometry": {"coordinates":[121.32944000000001,31.35306],"type":"Point"}
}