{
  "type": "Feature",
  "properties": {
    "gn:admin1_code":"4.0",
    "gn:asciiname":"Huangchuan",
    "gn:country_code":"CN",
    "gn:dem":17,
    "gn:feature_class":"P",
    "gn:feature_code":"PPL",
    "gn:name":"Huangchuan",
    "gn:population":0,
    "gn:timezone":"Asia/Shanghai",
    "iso:country":"CN",
    "name:zho_x_preferred":[
        "\u51f0\u5ddd"
    ],
    "wof:name":"Huangchuan",
    "wof:placetype":"locality"
},
  "geometry": {"coordinates":[119.87389,31.19119],"type":"Point"}
}