{
  "type": "Feature",
  "properties": {
    "gn:admin1_code":"26.0",
    "gn:asciiname":"Qinglongcun",
    "gn:country_code":"CN",
    "gn:dem":462,
    "gn:feature_class":"P",
    "gn:feature_code":"PPL",
    "gn:name":"Qinglongcun",
    "gn:population":0,
    "gn:timezone":"Asia/Shanghai",
    "iso:country":"CN",
    "name:und_x_variant":[
        "\u9752\u9f99\u6751"
    ],
    "wof:name":"Qinglongcun",
    "wof:placetype":"locality"
},
  "geometry": {"coordinates":[107.77873,33.02126],"type":"Point"}
}