{
  "type": "Feature",
  "properties": {
    "gn:admin1_code":"25",
    "gn:asciiname":"Liushawo",
    "gn:country_code":"CN",
    "gn:dem":44,
    "gn:feature_class":"P",
    "gn:feature_code":"PPL",
    "gn:name":"Liushawo",
    "gn:population":0,
    "gn:timezone":"Asia/Shanghai",
    "iso:country":"CN",
    "name:zho_x_preferred":[
        "\u5218\u6c99\u7a9d"
    ],
    "wof:name":"Liushawo",
    "wof:placetype":"locality"
},
  "geometry": {"coordinates":[116.113,35.0451],"type":"Point"}
}