{
  "type": "Feature",
  "properties": {
    "gn:admin1_code":"04",
    "gn:asciiname":"Dongyu",
    "gn:country_code":"CN",
    "gn:dem":1,
    "gn:feature_class":"P",
    "gn:feature_code":"PPL",
    "gn:name":"Dongyu",
    "gn:population":0,
    "gn:timezone":"Asia/Shanghai",
    "iso:country":"CN",
    "name:und_x_variant":[
        "Kuan-ch\u2019iu",
        "Dong\u2019anzhen",
        "Tung-an-chen",
        "Dongyuzhen",
        "Dongyu",
        "\u4e1c\u4f59",
        "\u4e1c\u4f59\u9547"
    ],
    "wof:name":"Dongyu",
    "wof:placetype":"locality"
},
  "geometry": {"coordinates":[121.83041,31.8134],"type":"Point"}
}