{
  "type": "Feature",
  "properties": {
    "gn:admin1_code":"2.0",
    "gn:asciiname":"Jinhua",
    "gn:country_code":"CN",
    "gn:dem":8,
    "gn:feature_class":"P",
    "gn:feature_code":"PPLA4",
    "gn:name":"Jinhua",
    "gn:population":0,
    "gn:timezone":"Asia/Shanghai",
    "iso:country":"CN",
    "name:und_x_variant":[
        "\u8fdb\u5316",
        "Jinhua Zhen",
        "\u8fdb\u5316\u9547"
    ],
    "wof:name":"Jinhua",
    "wof:placetype":"locality"
},
  "geometry": {"coordinates":[120.28865999999999,30.01347],"type":"Point"}
}