{
  "type": "Feature",
  "properties": {
    "gn:admin1_code":"11.0",
    "gn:asciiname":"Qianchongli",
    "gn:country_code":"CN",
    "gn:dem":127,
    "gn:feature_class":"P",
    "gn:feature_code":"PPL",
    "gn:name":"Qianchongli",
    "gn:population":0,
    "gn:timezone":"Asia/Shanghai",
    "iso:country":"CN",
    "name:zho_x_preferred":[
        "\u5343\u51b2\u91cc"
    ],
    "wof:name":"Qianchongli",
    "wof:placetype":"locality"
},
  "geometry": {"coordinates":[111.26111000000002,28.65443],"type":"Point"}
}