{
  "type": "Feature",
  "properties": {
    "gn:admin1_code":"29.0",
    "gn:asciiname":"Qikong",
    "gn:country_code":"CN",
    "gn:dem":1362,
    "gn:feature_class":"P",
    "gn:feature_code":"PPL",
    "gn:name":"Qikong",
    "gn:population":0,
    "gn:timezone":"Asia/Shanghai",
    "iso:country":"CN",
    "name:zho_x_preferred":[
        "\u4e03\u7a7a"
    ],
    "wof:name":"Qikong",
    "wof:placetype":"locality"
},
  "geometry": {"coordinates":[104.75700000000001,25.2762],"type":"Point"}
}