{
  "type": "Feature",
  "properties": {
    "gn:admin1_code":"8.0",
    "gn:asciiname":"Zhangmofangtun",
    "gn:country_code":"CN",
    "gn:dem":267,
    "gn:feature_class":"P",
    "gn:feature_code":"PPL",
    "gn:name":"Zhangmofangtun",
    "gn:population":0,
    "gn:timezone":"Asia/Shanghai",
    "iso:country":"CN",
    "name:zho_x_preferred":[
        "\u5f20\u78e8\u623f\u5c6f"
    ],
    "wof:name":"Zhangmofangtun",
    "wof:placetype":"locality"
},
  "geometry": {"coordinates":[127.88194,45.63264],"type":"Point"}
}