{
  "type": "Feature",
  "properties": {
    "gn:admin1_code":"8.0",
    "gn:asciiname":"Beishuntun",
    "gn:country_code":"CN",
    "gn:dem":169,
    "gn:feature_class":"P",
    "gn:feature_code":"PPL",
    "gn:name":"Beishuntun",
    "gn:population":0,
    "gn:timezone":"Asia/Shanghai",
    "iso:country":"CN",
    "name:zho_x_preferred":[
        "\u5317\u987a\u5c6f"
    ],
    "wof:name":"Beishuntun",
    "wof:placetype":"locality"
},
  "geometry": {"coordinates":[125.02290000000001,47.6527],"type":"Point"}
}