{
  "type": "Feature",
  "properties": {
    "gn:admin1_code":"18",
    "gn:asciiname":"Gouyangba",
    "gn:country_code":"CN",
    "gn:dem":1151,
    "gn:feature_class":"P",
    "gn:feature_code":"PPL",
    "gn:name":"Gouyangba",
    "gn:population":0,
    "gn:timezone":"Asia/Shanghai",
    "iso:country":"CN",
    "name:zho_x_preferred":[
        "\u82df\u9633\u575d"
    ],
    "wof:name":"Gouyangba",
    "wof:placetype":"locality"
},
  "geometry": {"coordinates":[107.09399999999999,27.8418],"type":"Point"}
}