{
  "type": "Feature",
  "properties": {
    "gn:admin1_code":"8.0",
    "gn:asciiname":"Sunyingtun",
    "gn:country_code":"CN",
    "gn:dem":193,
    "gn:feature_class":"P",
    "gn:feature_code":"PPL",
    "gn:name":"Sunyingtun",
    "gn:population":0,
    "gn:timezone":"Asia/Shanghai",
    "iso:country":"CN",
    "name:zho_x_preferred":[
        "\u5b59\u82f1\u5c6f"
    ],
    "wof:name":"Sunyingtun",
    "wof:placetype":"locality"
},
  "geometry": {"coordinates":[126.61523,47.44394000000001],"type":"Point"}
}