{
  "type": "Feature",
  "properties": {
    "gn:admin1_code":"11.0",
    "gn:asciiname":"Gantianya",
    "gn:country_code":"CN",
    "gn:dem":179,
    "gn:feature_class":"P",
    "gn:feature_code":"PPL",
    "gn:name":"Gantianya",
    "gn:population":0,
    "gn:timezone":"Asia/Shanghai",
    "iso:country":"CN",
    "name:zho_x_preferred":[
        "\u5e72\u7530\u57ad"
    ],
    "wof:name":"Gantianya",
    "wof:placetype":"locality"
},
  "geometry": {"coordinates":[110.96563999999999,29.56012],"type":"Point"}
}