{
  "type": "Feature",
  "properties": {
    "gn:admin1_code":"16",
    "gn:asciiname":"Shangxingbei",
    "gn:country_code":"CN",
    "gn:dem":172,
    "gn:feature_class":"P",
    "gn:feature_code":"PPL",
    "gn:name":"Shangxingbei",
    "gn:population":0,
    "gn:timezone":"Asia/Shanghai",
    "iso:country":"CN",
    "name:zho_x_preferred":[
        "\u4e0a\u5e78\u9642"
    ],
    "wof:name":"Shangxingbei",
    "wof:placetype":"locality"
},
  "geometry": {"coordinates":[110.465,25.2036],"type":"Point"}
}