{
  "type": "Feature",
  "properties": {
    "gn:admin1_code":"33.0",
    "gn:asciiname":"Tingziya",
    "gn:country_code":"CN",
    "gn:dem":722,
    "gn:feature_class":"P",
    "gn:feature_code":"PPL",
    "gn:name":"Tingziya",
    "gn:population":0,
    "gn:timezone":"Asia/Shanghai",
    "iso:country":"CN",
    "name:zho_x_preferred":[
        "\u4ead\u5b50\u57ad"
    ],
    "wof:name":"Tingziya",
    "wof:placetype":"locality"
},
  "geometry": {"coordinates":[107.64614,29.79078],"type":"Point"}
}