{
  "type": "Feature",
  "properties": {
    "gn:admin1_code":"32.0",
    "gn:asciiname":"Jiufangwo",
    "gn:country_code":"CN",
    "gn:dem":834,
    "gn:feature_class":"P",
    "gn:feature_code":"PPL",
    "gn:name":"Jiufangwo",
    "gn:population":0,
    "gn:timezone":"Asia/Shanghai",
    "iso:country":"CN",
    "name:zho_x_preferred":[
        "\u65e7\u623f\u7a9d"
    ],
    "wof:name":"Jiufangwo",
    "wof:placetype":"locality"
},
  "geometry": {"coordinates":[102.794,30.0942],"type":"Point"}
}