{
  "type": "Feature",
  "properties": {
    "gn:admin1_code":"26.0",
    "gn:asciiname":"Wangjiapuzi",
    "gn:country_code":"CN",
    "gn:dem":449,
    "gn:feature_class":"P",
    "gn:feature_code":"PPL",
    "gn:name":"Wangjiapuzi",
    "gn:population":0,
    "gn:timezone":"Asia/Shanghai",
    "iso:country":"CN",
    "name:zho_x_preferred":[
        "\u738b\u5bb6\u94fa\u5b50"
    ],
    "wof:name":"Wangjiapuzi",
    "wof:placetype":"locality"
},
  "geometry": {"coordinates":[108.72891,32.52602],"type":"Point"}
}