{
  "type": "Feature",
  "properties": {
    "gn:admin1_code":"18",
    "gn:asciiname":"Lamo",
    "gn:country_code":"CN",
    "gn:dem":908,
    "gn:feature_class":"P",
    "gn:feature_code":"PPL",
    "gn:name":"Lamo",
    "gn:population":0,
    "gn:timezone":"Asia/Shanghai",
    "iso:country":"CN",
    "name:ita_x_preferred":[
        "Lamo"
    ],
    "name:zho_x_preferred":[
        "\u62c9\u62b9"
    ],
    "wof:name":"Lamo",
    "wof:placetype":"locality"
},
  "geometry": {"coordinates":[107.23099999999999,25.785],"type":"Point"}
}