{
  "type": "Feature",
  "properties": {
    "gn:admin1_code":"15.0",
    "gn:asciiname":"Zhongdong",
    "gn:country_code":"CN",
    "gn:dem":1248,
    "gn:feature_class":"P",
    "gn:feature_code":"PPLA4",
    "gn:name":"Zhongdong",
    "gn:population":0,
    "gn:timezone":"Asia/Shanghai",
    "iso:country":"CN",
    "name:und_x_variant":[
        "Zhongdong Zhen"
    ],
    "name:zho_x_preferred":[
        "\u4e2d\u4e1c"
    ],
    "name:zho_x_variant":[
        "\u4e2d\u4e1c\u9547"
    ],
    "wof:name":"Zhongdong",
    "wof:placetype":"locality"
},
  "geometry": {"coordinates":[98.81716,40.11899],"type":"Point"}
}