{
  "type": "Feature",
  "properties": {
    "gn:admin1_code":"11.0",
    "gn:asciiname":"Wumuchong",
    "gn:country_code":"CN",
    "gn:dem":150,
    "gn:feature_class":"P",
    "gn:feature_code":"PPL",
    "gn:name":"Wumuchong",
    "gn:population":0,
    "gn:timezone":"Asia/Shanghai",
    "iso:country":"CN",
    "name:zho_x_preferred":[
        "\u4e94\u4ea9\u51b2"
    ],
    "wof:name":"Wumuchong",
    "wof:placetype":"locality"
},
  "geometry": {"coordinates":[112.11645,28.03311],"type":"Point"}
}