{
  "type": "Feature",
  "properties": {
    "gn:admin1_code":"31.0",
    "gn:asciiname":"Changhou",
    "gn:country_code":"CN",
    "gn:dem":79,
    "gn:feature_class":"P",
    "gn:feature_code":"PPL",
    "gn:name":"Changhou",
    "gn:population":0,
    "gn:timezone":"Asia/Shanghai",
    "iso:country":"CN",
    "name:und_x_variant":[
        "\u660c\u540e"
    ],
    "wof:name":"Changhou",
    "wof:placetype":"locality"
},
  "geometry": {"coordinates":[109.84049,18.58989],"type":"Point"}
}