{
  "type": "Feature",
  "properties": {
    "gn:admin1_code":"02",
    "gn:asciiname":"Baita",
    "gn:country_code":"CN",
    "gn:dem":94,
    "gn:feature_class":"P",
    "gn:feature_code":"PPLA4",
    "gn:name":"Baita",
    "gn:population":0,
    "gn:timezone":"Asia/Shanghai",
    "iso:country":"CN",
    "name:ceb_x_preferred":[
        "Baita"
    ],
    "name:deu_x_preferred":[
        "Baita"
    ],
    "name:ita_x_preferred":[
        "Baita"
    ],
    "name:swe_x_preferred":[
        "Baita"
    ],
    "name:und_x_variant":[
        "Pai-t\u2019a",
        "Baita",
        "Baita Zhen"
    ],
    "name:vie_x_preferred":[
        "Baita"
    ],
    "name:zho_x_preferred":[
        "\u767d\u5854"
    ],
    "name:zho_x_variant":[
        "\u767d\u5854\u9547"
    ],
    "wof:name":"Baita",
    "wof:placetype":"locality"
},
  "geometry": {"coordinates":[120.58835999999999,28.75602],"type":"Point"}
}