{
  "type": "Feature",
  "properties": {
    "gn:admin1_code":"32.0",
    "gn:asciiname":"Tiandengpo",
    "gn:country_code":"CN",
    "gn:dem":377,
    "gn:feature_class":"P",
    "gn:feature_code":"PPL",
    "gn:name":"Tiandengpo",
    "gn:population":0,
    "gn:timezone":"Asia/Shanghai",
    "iso:country":"CN",
    "name:zho_x_preferred":[
        "\u5929\u706f\u5761"
    ],
    "wof:name":"Tiandengpo",
    "wof:placetype":"locality"
},
  "geometry": {"coordinates":[104.25596,29.10084],"type":"Point"}
}