{
  "type": "Feature",
  "properties": {
    "gn:admin1_code":"3.0",
    "gn:asciiname":"Shangjuzhou",
    "gn:country_code":"CN",
    "gn:dem":401,
    "gn:feature_class":"P",
    "gn:feature_code":"PPL",
    "gn:name":"Shangjuzhou",
    "gn:population":0,
    "gn:timezone":"Asia/Shanghai",
    "iso:country":"CN",
    "name:und_x_variant":[
        "\u4e0a\u8392\u6d32"
    ],
    "wof:name":"Shangjuzhou",
    "wof:placetype":"locality"
},
  "geometry": {"coordinates":[116.96528000000001,27.71024],"type":"Point"}
}