{
  "type": "Feature",
  "properties": {
    "gn:admin1_code":"21.0",
    "gn:asciiname":"Yujialaozhuang",
    "gn:country_code":"CN",
    "gn:dem":1590,
    "gn:feature_class":"P",
    "gn:feature_code":"PPL",
    "gn:name":"Yujialaozhuang",
    "gn:population":0,
    "gn:timezone":"Asia/Shanghai",
    "iso:country":"CN",
    "name:und_x_variant":[
        "\u4f59\u5bb6\u8001\u5e84"
    ],
    "name:zho_x_preferred":[
        "\u4f59\u5bb6\u8001\u5e84"
    ],
    "wof:name":"Yujialaozhuang",
    "wof:placetype":"locality"
},
  "geometry": {"coordinates":[106.39349,36.89856],"type":"Point"}
}