{
  "type": "Feature",
  "properties": {
    "gn:admin1_code":"9.0",
    "gn:asciiname":"Xiyucao",
    "gn:country_code":"CN",
    "gn:dem":72,
    "gn:feature_class":"P",
    "gn:feature_code":"PPL",
    "gn:name":"Xiyucao",
    "gn:population":0,
    "gn:timezone":"Asia/Shanghai",
    "iso:country":"CN",
    "name:zho_x_preferred":[
        "\u897f\u4e8e\u66f9"
    ],
    "wof:name":"Xiyucao",
    "wof:placetype":"locality"
},
  "geometry": {"coordinates":[114.40687,36.13225],"type":"Point"}
}