{
  "type": "Feature",
  "properties": {
    "gn:admin1_code":"9.0",
    "gn:asciiname":"Houxiaozhuang",
    "gn:country_code":"CN",
    "gn:dem":110,
    "gn:feature_class":"P",
    "gn:feature_code":"PPL",
    "gn:name":"Houxiaozhuang",
    "gn:population":0,
    "gn:timezone":"Asia/Shanghai",
    "iso:country":"CN",
    "name:zho_x_preferred":[
        "\u4faf\u5c0f\u5e84"
    ],
    "wof:name":"Houxiaozhuang",
    "wof:placetype":"locality"
},
  "geometry": {"coordinates":[113.80229,32.44244],"type":"Point"}
}