{
  "type": "Feature",
  "properties": {
    "gn:admin1_code":"1.0",
    "gn:asciiname":"Minbingcun",
    "gn:country_code":"CN",
    "gn:dem":45,
    "gn:feature_class":"P",
    "gn:feature_code":"PPL",
    "gn:name":"Minbingcun",
    "gn:population":0,
    "gn:timezone":"Asia/Shanghai",
    "iso:country":"CN",
    "name:zho_x_preferred":[
        "\u6c11\u5175\u6751"
    ],
    "wof:name":"Minbingcun",
    "wof:placetype":"locality"
},
  "geometry": {"coordinates":[117.67072,32.04594],"type":"Point"}
}