{
  "type": "Feature",
  "properties": {
    "gn:admin1_code":"12.0",
    "gn:asciiname":"Shenjiacheng",
    "gn:country_code":"CN",
    "gn:dem":86,
    "gn:feature_class":"P",
    "gn:feature_code":"PPL",
    "gn:name":"Shenjiacheng",
    "gn:population":0,
    "gn:timezone":"Asia/Shanghai",
    "iso:country":"CN",
    "name:zho_x_preferred":[
        "\u6c88\u5bb6\u57ce"
    ],
    "wof:name":"Shenjiacheng",
    "wof:placetype":"locality"
},
  "geometry": {"coordinates":[114.14431,31.69943],"type":"Point"}
}