{
  "type": "Feature",
  "properties": {
    "gn:admin1_code":"25",
    "gn:asciiname":"Yuhuacun",
    "gn:country_code":"CN",
    "gn:dem":365,
    "gn:feature_class":"P",
    "gn:feature_code":"PPL",
    "gn:name":"Yuhuacun",
    "gn:population":0,
    "gn:timezone":"Asia/Shanghai",
    "iso:country":"CN",
    "name:zho_x_preferred":[
        "\u88d5\u534e\u6751"
    ],
    "wof:name":"Yuhuacun",
    "wof:placetype":"locality"
},
  "geometry": {"coordinates":[118.203,35.9846],"type":"Point"}
}