{
  "type": "Feature",
  "properties": {
    "gn:admin1_code":"5.0",
    "gn:asciiname":"Chunjiangcun",
    "gn:country_code":"CN",
    "gn:dem":285,
    "gn:feature_class":"P",
    "gn:feature_code":"PPL",
    "gn:name":"Chunjiangcun",
    "gn:population":0,
    "gn:timezone":"Asia/Shanghai",
    "iso:country":"CN",
    "name:zho_x_preferred":[
        "\u6625\u6c5f\u6751"
    ],
    "wof:name":"Chunjiangcun",
    "wof:placetype":"locality"
},
  "geometry": {"coordinates":[126.9284,43.86229],"type":"Point"}
}