{
  "type": "Feature",
  "properties": {
    "gn:admin1_code":"32.0",
    "gn:asciiname":"Jinkeluobo",
    "gn:country_code":"CN",
    "gn:dem":2978,
    "gn:feature_class":"P",
    "gn:feature_code":"PPL",
    "gn:name":"Jinkeluobo",
    "gn:population":0,
    "gn:timezone":"Asia/Shanghai",
    "iso:country":"CN",
    "name:zho_x_preferred":[
        "\u91d1\u514b\u6d1b\u535a"
    ],
    "wof:name":"Jinkeluobo",
    "wof:placetype":"locality"
},
  "geometry": {"coordinates":[102.577,27.8012],"type":"Point"}
}