{
  "type": "Feature",
  "properties": {
    "gn:admin1_code":"25.0",
    "gn:asciiname":"Houshimiaocun",
    "gn:country_code":"CN",
    "gn:dem":103,
    "gn:feature_class":"P",
    "gn:feature_code":"PPL",
    "gn:name":"Houshimiaocun",
    "gn:population":0,
    "gn:timezone":"Asia/Shanghai",
    "iso:country":"CN",
    "name:zho_x_preferred":[
        "\u540e\u77f3\u5e99\u6751"
    ],
    "wof:name":"Houshimiaocun",
    "wof:placetype":"locality"
},
  "geometry": {"coordinates":[120.86790999999999,36.84739],"type":"Point"}
}