{
  "type": "Feature",
  "properties": {
    "gn:admin1_code":"3.0",
    "gn:asciiname":"Tongbu",
    "gn:country_code":"CN",
    "gn:dem":119,
    "gn:feature_class":"P",
    "gn:feature_code":"PPL",
    "gn:name":"Tongbu",
    "gn:population":0,
    "gn:timezone":"Asia/Shanghai",
    "iso:country":"CN",
    "name:und_x_variant":[
        "\u6850\u57e0"
    ],
    "wof:name":"Tongbu",
    "wof:placetype":"locality"
},
  "geometry": {"coordinates":[116.89848000000001,27.53378],"type":"Point"}
}