{
  "type": "Feature",
  "properties": {
    "gn:admin1_code":"15.0",
    "gn:asciiname":"Hanchuan",
    "gn:country_code":"CN",
    "gn:dem":1654,
    "gn:feature_class":"P",
    "gn:feature_code":"PPL",
    "gn:name":"Hanchuan",
    "gn:population":0,
    "gn:timezone":"Asia/Shanghai",
    "iso:country":"CN",
    "name:deu_x_preferred":[
        "Hanchuan"
    ],
    "name:fra_x_preferred":[
        "Hanchuan"
    ],
    "name:ita_x_preferred":[
        "Hanchuan"
    ],
    "name:jpn_x_preferred":[
        "\u6f22\u5ddd\u5e02"
    ],
    "name:kik_x_preferred":[
        "Hanchuan"
    ],
    "name:kor_x_preferred":[
        "\ud55c\ucd28\uc2dc"
    ],
    "name:mlg_x_preferred":[
        "Hanchuan"
    ],
    "name:nor_x_preferred":[
        "Hanchuan"
    ],
    "name:pam_x_preferred":[
        "Hanchuan"
    ],
    "name:swe_x_preferred":[
        "Hanchuan"
    ],
    "name:und_x_variant":[
        "\u97e9\u5ddd"
    ],
    "name:vie_x_preferred":[
        "H\u00e1n Xuy\u00ean"
    ],
    "name:zho_x_preferred":[
        "\u6c49\u5ddd\u5e02"
    ],
    "wof:name":"Hanchuan",
    "wof:placetype":"locality"
},
  "geometry": {"coordinates":[105.64713999999999,35.51664],"type":"Point"}
}