{
  "type": "Feature",
  "properties": {
    "gn:admin1_code":"11.0",
    "gn:asciiname":"Fengjia Wuchang",
    "gn:country_code":"CN",
    "gn:dem":46,
    "gn:feature_class":"P",
    "gn:feature_code":"PPL",
    "gn:name":"Fengjia Wuchang",
    "gn:population":0,
    "gn:timezone":"Asia/Shanghai",
    "iso:country":"CN",
    "name:zho_x_preferred":[
        "\u51af\u5bb6\u5c4b\u573a"
    ],
    "wof:name":"Fengjia Wuchang",
    "wof:placetype":"locality"
},
  "geometry": {"coordinates":[112.87,29.63529],"type":"Point"}
}