{
  "type": "Feature",
  "properties": {
    "gn:admin1_code":"26.0",
    "gn:asciiname":"Gengjia Maocun",
    "gn:country_code":"CN",
    "gn:dem":1162,
    "gn:feature_class":"P",
    "gn:feature_code":"PPL",
    "gn:name":"Gengjia Maocun",
    "gn:population":0,
    "gn:timezone":"Asia/Shanghai",
    "iso:country":"CN",
    "name:zho_x_preferred":[
        "\u803f\u5bb6\u5cc1\u6751"
    ],
    "wof:name":"Gengjia Maocun",
    "wof:placetype":"locality"
},
  "geometry": {"coordinates":[110.548,38.8914],"type":"Point"}
}