{
  "type": "Feature",
  "properties": {
    "gn:admin1_code":"7.0",
    "gn:asciiname":"Shilin",
    "gn:country_code":"CN",
    "gn:dem":84,
    "gn:feature_class":"P",
    "gn:feature_code":"PPL",
    "gn:name":"Shilin",
    "gn:population":0,
    "gn:timezone":"Asia/Shanghai",
    "iso:country":"CN",
    "name:ceb_x_preferred":[
        "Shilin"
    ],
    "name:deu_x_preferred":[
        "Shilin"
    ],
    "name:mlg_x_preferred":[
        "Shilin"
    ],
    "name:sco_x_preferred":[
        "Shilin"
    ],
    "name:zho_x_preferred":[
        "\u77f3\u6797"
    ],
    "wof:name":"Shilin",
    "wof:placetype":"locality"
},
  "geometry": {"coordinates":[118.31027,25.14643],"type":"Point"}
}