{
  "type": "Feature",
  "properties": {
    "gn:admin1_code":"5.0",
    "gn:asciiname":"Tuozidao",
    "gn:country_code":"CN",
    "gn:dem":409,
    "gn:feature_class":"P",
    "gn:feature_code":"PPL",
    "gn:name":"Tuozidao",
    "gn:population":0,
    "gn:timezone":"Asia/Shanghai",
    "iso:country":"CN",
    "name:und_x_variant":[
        "\u9a6e\u5b50\u9053"
    ],
    "wof:name":"Tuozidao",
    "wof:placetype":"locality"
},
  "geometry": {"coordinates":[127.02531999999999,42.94915],"type":"Point"}
}