{
  "type": "Feature",
  "properties": {
    "gn:admin1_code":"11.0",
    "gn:asciiname":"Wanniankeng",
    "gn:country_code":"CN",
    "gn:dem":147,
    "gn:feature_class":"P",
    "gn:feature_code":"PPL",
    "gn:name":"Wanniankeng",
    "gn:population":0,
    "gn:timezone":"Asia/Shanghai",
    "iso:country":"CN",
    "name:zho_x_preferred":[
        "\u4e07\u5e74\u5751"
    ],
    "wof:name":"Wanniankeng",
    "wof:placetype":"locality"
},
  "geometry": {"coordinates":[112.18387,28.16358],"type":"Point"}
}