{
  "type": "Feature",
  "properties": {
    "gn:admin1_code":"9",
    "gn:asciiname":"Dinanwangzhuang",
    "gn:country_code":"CN",
    "gn:dem":50,
    "gn:feature_class":"P",
    "gn:feature_code":"PPL",
    "gn:name":"Dinanwangzhuang",
    "gn:population":0,
    "gn:timezone":"Asia/Shanghai",
    "iso:country":"CN",
    "name:zho_x_preferred":[
        "\u5824\u5357\u738b\u5e84"
    ],
    "wof:name":"Dinanwangzhuang",
    "wof:placetype":"locality"
},
  "geometry": {"coordinates":[116.068,34.5498],"type":"Point"}
}