{
  "type": "Feature",
  "properties": {
    "gn:admin1_code":"15.0",
    "gn:asciiname":"Changjiatai",
    "gn:country_code":"CN",
    "gn:dem":1611,
    "gn:feature_class":"P",
    "gn:feature_code":"PPL",
    "gn:name":"Changjiatai",
    "gn:population":0,
    "gn:timezone":"Asia/Shanghai",
    "iso:country":"CN",
    "name:und_x_variant":[
        "\u5e38\u5bb6\u53f0"
    ],
    "wof:name":"Changjiatai",
    "wof:placetype":"locality"
},
  "geometry": {"coordinates":[106.87558,36.55767],"type":"Point"}
}