{
  "type": "Feature",
  "properties": {
    "gn:admin1_code":"25",
    "gn:asciiname":"Zhougudui",
    "gn:country_code":"CN",
    "gn:dem":42,
    "gn:feature_class":"P",
    "gn:feature_code":"PPL",
    "gn:name":"Zhougudui",
    "gn:population":0,
    "gn:timezone":"Asia/Shanghai",
    "iso:country":"CN",
    "name:zho_x_preferred":[
        "\u5468\u580c\u5806"
    ],
    "wof:name":"Zhougudui",
    "wof:placetype":"locality"
},
  "geometry": {"coordinates":[116.28100000000001,34.921],"type":"Point"}
}