{
  "type": "Feature",
  "properties": {
    "gn:admin1_code":"15.0",
    "gn:asciiname":"Changgou",
    "gn:country_code":"CN",
    "gn:dem":2278,
    "gn:feature_class":"P",
    "gn:feature_code":"PPL",
    "gn:name":"Changgou",
    "gn:population":0,
    "gn:timezone":"Asia/Shanghai",
    "iso:country":"CN",
    "name:zho_x_preferred":[
        "\u957f\u6c9f"
    ],
    "wof:name":"Changgou",
    "wof:placetype":"locality"
},
  "geometry": {"coordinates":[103.05800000000001,36.5732],"type":"Point"}
}