{
  "type": "Feature",
  "properties": {
    "gn:admin1_code":"25.0",
    "gn:asciiname":"Jiangge",
    "gn:country_code":"CN",
    "gn:dem":9,
    "gn:feature_class":"P",
    "gn:feature_code":"PPL",
    "gn:name":"Jiangge",
    "gn:population":0,
    "gn:timezone":"Asia/Shanghai",
    "iso:country":"CN",
    "name:zho_x_preferred":[
        "\u59dc\u683c"
    ],
    "wof:name":"Jiangge",
    "wof:placetype":"locality"
},
  "geometry": {"coordinates":[121.55798,36.77997],"type":"Point"}
}