{
  "type": "Feature",
  "properties": {
    "gn:admin1_code":"4.0",
    "gn:asciiname":"Xinhe",
    "gn:country_code":"CN",
    "gn:dem":23,
    "gn:feature_class":"P",
    "gn:feature_code":"PPL",
    "gn:name":"Xinhe",
    "gn:population":0,
    "gn:timezone":"Asia/Shanghai",
    "iso:country":"CN",
    "name:ceb_x_preferred":[
        "Xinhe"
    ],
    "name:deu_x_preferred":[
        "Xinhe"
    ],
    "name:fra_x_preferred":[
        "Xinhe"
    ],
    "name:kor_x_preferred":[
        "\uc2e0\ud5c8\ud604"
    ],
    "name:und_x_variant":[
        "\u65b0\u5408"
    ],
    "wof:name":"Xinhe",
    "wof:placetype":"locality"
},
  "geometry": {"coordinates":[118.91476000000002,32.14389],"type":"Point"}
}