{
  "type": "Feature",
  "properties": {
    "gn:admin1_code":"18",
    "gn:asciiname":"Dashi",
    "gn:country_code":"CN",
    "gn:dem":909,
    "gn:feature_class":"P",
    "gn:feature_code":"PPL",
    "gn:name":"Dashi",
    "gn:population":0,
    "gn:timezone":"Asia/Shanghai",
    "iso:country":"CN",
    "name:ara_x_preferred":[
        "\u062f\u0627\u0634\u064a"
    ],
    "name:cat_x_preferred":[
        "Dashi"
    ],
    "name:ceb_x_preferred":[
        "Dashi"
    ],
    "name:dan_x_preferred":[
        "Dashi"
    ],
    "name:deu_x_preferred":[
        "Dashi"
    ],
    "name:epo_x_preferred":[
        "Da\u015dio"
    ],
    "name:fas_x_preferred":[
        "\u062f\u0627\u0634\u06cc"
    ],
    "name:fin_x_preferred":[
        "Dashi"
    ],
    "name:fra_x_preferred":[
        "Dashi"
    ],
    "name:heb_x_preferred":[
        "\u05d3\u05d0\u05e9\u05d9"
    ],
    "name:hun_x_preferred":[
        "Dasi"
    ],
    "name:hye_x_preferred":[
        "\u0534\u0561\u057d\u056b"
    ],
    "name:ind_x_preferred":[
        "Dashi"
    ],
    "name:ita_x_preferred":[
        "Dashi"
    ],
    "name:jav_x_preferred":[
        "Dashi"
    ],
    "name:msa_x_preferred":[
        "Dashi"
    ],
    "name:nld_x_preferred":[
        "Dashi"
    ],
    "name:nor_x_preferred":[
        "Dashi"
    ],
    "name:pol_x_preferred":[
        "Dashi"
    ],
    "name:por_x_preferred":[
        "Dashi"
    ],
    "name:rus_x_preferred":[
        "\u0414\u0430\u0441\u0438"
    ],
    "name:spa_x_preferred":[
        "Dashi"
    ],
    "name:swe_x_preferred":[
        "Dashi"
    ],
    "name:tha_x_preferred":[
        "\u0e14\u0e32\u0e0a\u0e34"
    ],
    "name:tur_x_preferred":[
        "Dashi"
    ],
    "name:ukr_x_preferred":[
        "\u0414\u0430\u0441\u0456"
    ],
    "name:zho_x_preferred":[
        "\u5927\u77f3"
    ],
    "name:zho_x_variant":[
        "\u65e5\u5f0f\u4e0a\u6e6f"
    ],
    "wof:name":"Dashi",
    "wof:placetype":"locality"
},
  "geometry": {"coordinates":[108.411,28.0691],"type":"Point"}
}