{
  "type": "Feature",
  "properties": {
    "gn:admin1_code":"14.0",
    "gn:asciiname":"Womadang",
    "gn:country_code":"CN",
    "gn:dem":5032,
    "gn:feature_class":"P",
    "gn:feature_code":"PPL",
    "gn:name":"Womadang",
    "gn:population":0,
    "gn:timezone":"Asia/Urumqi",
    "iso:country":"CN",
    "name:bod_x_preferred":[
        "Ogmad\u00eang"
    ],
    "name:zho_x_preferred":[
        "Womadang"
    ],
    "name:zho_x_variant":[
        "\u5367\u739b\u5f53",
        "Zhuopu Gongshe",
        "\u5353\u666e\u516c\u793e"
    ],
    "wof:name":"Womadang",
    "wof:placetype":"locality"
},
  "geometry": {"coordinates":[91.20099999999999,29.101],"type":"Point"}
}