{
  "type": "Feature",
  "properties": {
    "gn:admin1_code":"19.0",
    "gn:asciiname":"Shifenggou",
    "gn:country_code":"CN",
    "gn:dem":296,
    "gn:feature_class":"P",
    "gn:feature_code":"PPL",
    "gn:name":"Shifenggou",
    "gn:population":0,
    "gn:timezone":"Asia/Shanghai",
    "iso:country":"CN",
    "name:zho_x_preferred":[
        "\u77f3\u98ce\u6c9f"
    ],
    "wof:name":"Shifenggou",
    "wof:placetype":"locality"
},
  "geometry": {"coordinates":[124.72803,40.77464000000001],"type":"Point"}
}