{
  "type": "Feature",
  "properties": {
    "gn:admin1_code":"18",
    "gn:asciiname":"Nahe",
    "gn:country_code":"CN",
    "gn:dem":1070,
    "gn:feature_class":"P",
    "gn:feature_code":"PPL",
    "gn:name":"Nahe",
    "gn:population":0,
    "gn:timezone":"Asia/Shanghai",
    "iso:country":"CN",
    "name:ceb_x_preferred":[
        "Nahe"
    ],
    "name:dan_x_preferred":[
        "Nahe"
    ],
    "name:deu_x_preferred":[
        "Nahe"
    ],
    "name:epo_x_preferred":[
        "Nahe"
    ],
    "name:fra_x_preferred":[
        "Nahe"
    ],
    "name:ita_x_preferred":[
        "Nahe"
    ],
    "name:ltz_x_preferred":[
        "Nahe"
    ],
    "name:mkd_x_preferred":[
        "\u041d\u0430\u0435"
    ],
    "name:nld_x_preferred":[
        "Nahe"
    ],
    "name:pol_x_preferred":[
        "Nahe"
    ],
    "name:ron_x_preferred":[
        "Nahe"
    ],
    "name:rus_x_preferred":[
        "\u041d\u0430\u044d"
    ],
    "name:swe_x_preferred":[
        "Nahe"
    ],
    "name:zho_x_preferred":[
        "\u7eb3\u6838"
    ],
    "wof:name":"Nahe",
    "wof:placetype":"locality"
},
  "geometry": {"coordinates":[105.66500000000001,25.4283],"type":"Point"}
}