{
  "type": "Feature",
  "properties": {
    "gn:admin1_code":"32.0",
    "gn:asciiname":"Aoshanzhai",
    "gn:country_code":"CN",
    "gn:dem":318,
    "gn:feature_class":"P",
    "gn:feature_code":"PPL",
    "gn:name":"Aoshanzhai",
    "gn:population":0,
    "gn:timezone":"Asia/Shanghai",
    "iso:country":"CN",
    "name:zho_x_preferred":[
        "\u9ccc\u5c71\u5be8"
    ],
    "wof:name":"Aoshanzhai",
    "wof:placetype":"locality"
},
  "geometry": {"coordinates":[105.11767,29.00938],"type":"Point"}
}