{
  "type": "Feature",
  "properties": {
    "gn:admin1_code":"1.0",
    "gn:asciiname":"Yuezhan",
    "gn:country_code":"CN",
    "gn:dem":613,
    "gn:feature_class":"P",
    "gn:feature_code":"PPL",
    "gn:name":"Yuezhan",
    "gn:population":0,
    "gn:timezone":"Asia/Shanghai",
    "iso:country":"CN",
    "name:und_x_variant":[
        "\u5cb3\u7ad9",
        "Yuezhan"
    ],
    "wof:name":"Yuezhan",
    "wof:placetype":"locality"
},
  "geometry": {"coordinates":[118.828,29.89532],"type":"Point"}
}