{
  "type": "Feature",
  "properties": {
    "gn:admin1_code":"22.0",
    "gn:asciiname":"Xiegezhuangcun",
    "gn:country_code":"CN",
    "gn:dem":21,
    "gn:feature_class":"P",
    "gn:feature_code":"PPL",
    "gn:name":"Xiegezhuangcun",
    "gn:population":0,
    "gn:timezone":"Asia/Shanghai",
    "iso:country":"CN",
    "name:zho_x_preferred":[
        "\u534f\u5404\u5e84\u6751"
    ],
    "wof:name":"Xiegezhuangcun",
    "wof:placetype":"locality"
},
  "geometry": {"coordinates":[116.85782,39.82873],"type":"Point"}
}