{
  "type": "Feature",
  "properties": {
    "gn:admin1_code":"16.0",
    "gn:asciiname":"Laoheshan",
    "gn:country_code":"CN",
    "gn:dem":265,
    "gn:feature_class":"P",
    "gn:feature_code":"PPL",
    "gn:name":"Laoheshan",
    "gn:population":0,
    "gn:timezone":"Asia/Shanghai",
    "iso:country":"CN",
    "name:zho_x_preferred":[
        "\u8001\u5408\u5c71"
    ],
    "wof:name":"Laoheshan",
    "wof:placetype":"locality"
},
  "geometry": {"coordinates":[108.883,23.881],"type":"Point"}
}