{
  "type": "Feature",
  "properties": {
    "gn:admin1_code":"18",
    "gn:asciiname":"Qingtengchong",
    "gn:country_code":"CN",
    "gn:dem":1008,
    "gn:feature_class":"P",
    "gn:feature_code":"PPL",
    "gn:name":"Qingtengchong",
    "gn:population":0,
    "gn:timezone":"Asia/Shanghai",
    "iso:country":"CN",
    "name:zho_x_preferred":[
        "\u9752\u85e4\u51b2"
    ],
    "wof:name":"Qingtengchong",
    "wof:placetype":"locality"
},
  "geometry": {"coordinates":[107.155,26.1342],"type":"Point"}
}