{
  "type": "Feature",
  "properties": {
    "gn:admin1_code":"21.0",
    "gn:asciiname":"Erdaoqiao",
    "gn:country_code":"CN",
    "gn:dem":1122,
    "gn:feature_class":"P",
    "gn:feature_code":"PPL",
    "gn:name":"Erdaoqiao",
    "gn:population":0,
    "gn:timezone":"Asia/Shanghai",
    "iso:country":"CN",
    "name:zho_x_preferred":[
        "\u4e8c\u9053\u6865"
    ],
    "wof:name":"Erdaoqiao",
    "wof:placetype":"locality"
},
  "geometry": {"coordinates":[106.20999999999999,38.0209],"type":"Point"}
}