{
  "type": "Feature",
  "properties": {
    "gn:admin1_code":"16.0",
    "gn:asciiname":"Zhongdong",
    "gn:cc2":"CN",
    "gn:country_code":"CN",
    "gn:dem":125,
    "gn:feature_class":"P",
    "gn:feature_code":"PPL",
    "gn:name":"Zhongdong",
    "gn:population":0,
    "gn:timezone":"Asia/Shanghai",
    "iso:country":"CN",
    "name:und_x_variant":[
        "T\u2019ung-cheng-hsien",
        "Yungkong",
        "Chung-tung",
        "Yung-k\u2019ang",
        "T\u2019ung-cheng",
        "Chiu-t\u2019ung-cheng",
        "Zhongdong"
    ],
    "wof:name":"Zhongdong",
    "wof:placetype":"locality"
},
  "geometry": {"coordinates":[107.80916999999999,22.78056],"type":"Point"}
}