{
  "type": "Feature",
  "properties": {
    "gn:admin1_code":"29.0",
    "gn:asciiname":"Menglong",
    "gn:country_code":"CN",
    "gn:dem":1669,
    "gn:feature_class":"P",
    "gn:feature_code":"PPL",
    "gn:name":"Menglong",
    "gn:population":0,
    "gn:timezone":"Asia/Shanghai",
    "iso:country":"CN",
    "name:zho_x_preferred":[
        "\u8499\u80e7"
    ],
    "wof:name":"Menglong",
    "wof:placetype":"locality"
},
  "geometry": {"coordinates":[103.998,23.8767],"type":"Point"}
}