{
  "type": "Feature",
  "properties": {
    "gn:admin1_code":"30.0",
    "gn:asciiname":"Shangyangdong",
    "gn:country_code":"CN",
    "gn:dem":420,
    "gn:feature_class":"P",
    "gn:feature_code":"PPL",
    "gn:name":"Shangyangdong",
    "gn:population":0,
    "gn:timezone":"Asia/Shanghai",
    "iso:country":"CN",
    "name:zho_x_preferred":[
        "Shangyangdong"
    ],
    "name:zho_x_variant":[
        "\u4e0a\u6d0b\u6d1e"
    ],
    "wof:name":"Shangyangdong",
    "wof:placetype":"locality"
},
  "geometry": {"coordinates":[114.23737,24.89513],"type":"Point"}
}