{
  "type": "Feature",
  "properties": {
    "gn:admin1_code":"4.0",
    "gn:asciiname":"Luducun",
    "gn:country_code":"CN",
    "gn:dem":6,
    "gn:feature_class":"P",
    "gn:feature_code":"PPL",
    "gn:name":"Luducun",
    "gn:population":0,
    "gn:timezone":"Asia/Shanghai",
    "iso:country":"CN",
    "name:zho_x_preferred":[
        "\u9c81\u6e21\u6751"
    ],
    "wof:name":"Luducun",
    "wof:placetype":"locality"
},
  "geometry": {"coordinates":[119.35308999999999,33.8985],"type":"Point"}
}