{
  "type": "Feature",
  "properties": {
    "gn:admin1_code":"8.0",
    "gn:asciiname":"Xingsheng Liudui",
    "gn:country_code":"CN",
    "gn:dem":169,
    "gn:feature_class":"P",
    "gn:feature_code":"PPL",
    "gn:name":"Xingsheng Liudui",
    "gn:population":0,
    "gn:timezone":"Asia/Shanghai",
    "iso:country":"CN",
    "name:zho_x_preferred":[
        "\u5174\u80dc\u516d\u961f"
    ],
    "wof:name":"Xingsheng Liudui",
    "wof:placetype":"locality"
},
  "geometry": {"coordinates":[123.35729000000001,47.68315],"type":"Point"}
}