{
  "type": "Feature",
  "properties": {
    "gn:admin1_code":"12.0",
    "gn:asciiname":"Yaoyingpo",
    "gn:country_code":"CN",
    "gn:dem":1183,
    "gn:feature_class":"P",
    "gn:feature_code":"PPL",
    "gn:name":"Yaoyingpo",
    "gn:population":0,
    "gn:timezone":"Asia/Shanghai",
    "iso:country":"CN",
    "name:zho_x_preferred":[
        "\u9e5e\u9e70\u5761"
    ],
    "wof:name":"Yaoyingpo",
    "wof:placetype":"locality"
},
  "geometry": {"coordinates":[109.98944,30.57885],"type":"Point"}
}