{
  "type": "Feature",
  "properties": {
    "gn:admin1_code":"19.0",
    "gn:asciiname":"Sunjiatuo",
    "gn:country_code":"CN",
    "gn:dem":70,
    "gn:feature_class":"P",
    "gn:feature_code":"PPL",
    "gn:name":"Sunjiatuo",
    "gn:population":0,
    "gn:timezone":"Asia/Shanghai",
    "iso:country":"CN",
    "name:und_x_variant":[
        "\u5b59\u5bb6\u5768"
    ],
    "name:zho_x_preferred":[
        "\u5b59\u5bb6\u5768"
    ],
    "wof:name":"Sunjiatuo",
    "wof:placetype":"locality"
},
  "geometry": {"coordinates":[123.74997999999999,42.51696],"type":"Point"}
}