{
  "type": "Feature",
  "properties": {
    "gn:admin1_code":"9.0",
    "gn:asciiname":"Ciyuan",
    "gn:country_code":"CN",
    "gn:dem":49,
    "gn:feature_class":"P",
    "gn:feature_code":"PPL",
    "gn:name":"Ciyuan",
    "gn:population":0,
    "gn:timezone":"Asia/Shanghai",
    "iso:country":"CN",
    "name:deu_x_preferred":[
        "Ciyuan"
    ],
    "name:spa_x_preferred":[
        "Ciyuan"
    ],
    "name:zho_x_preferred":[
        "\u8328\u56ed"
    ],
    "wof:name":"Ciyuan",
    "wof:placetype":"locality"
},
  "geometry": {"coordinates":[114.67225999999999,32.89826],"type":"Point"}
}