{
  "type": "Feature",
  "properties": {
    "gn:admin1_code":"29.0",
    "gn:asciiname":"Gaozhao",
    "gn:country_code":"CN",
    "gn:dem":2369,
    "gn:feature_class":"P",
    "gn:feature_code":"PPL",
    "gn:name":"Gaozhao",
    "gn:population":0,
    "gn:timezone":"Asia/Shanghai",
    "iso:country":"CN",
    "name:zho_x_preferred":[
        "\u9ad8\u7167"
    ],
    "wof:name":"Gaozhao",
    "wof:placetype":"locality"
},
  "geometry": {"coordinates":[102.69,25.9163],"type":"Point"}
}