{
  "type": "Feature",
  "properties": {
    "gn:admin1_code":"29.0",
    "gn:asciiname":"Jiasawa",
    "gn:country_code":"CN",
    "gn:dem":2718,
    "gn:feature_class":"P",
    "gn:feature_code":"PPL",
    "gn:name":"Jiasawa",
    "gn:population":0,
    "gn:timezone":"Asia/Shanghai",
    "iso:country":"CN",
    "name:zho_x_preferred":[
        "\u621b\u6492\u74e6"
    ],
    "wof:name":"Jiasawa",
    "wof:placetype":"locality"
},
  "geometry": {"coordinates":[100.688,27.7947],"type":"Point"}
}