{
  "type": "Feature",
  "properties": {
    "gn:admin1_code":"1.0",
    "gn:asciiname":"Xidi",
    "gn:country_code":"CN",
    "gn:dem":235,
    "gn:feature_class":"P",
    "gn:feature_code":"PPLA4",
    "gn:name":"Xidi",
    "gn:population":0,
    "gn:timezone":"Asia/Shanghai",
    "iso:country":"CN",
    "name:ara_x_preferred":[
        "\u0634\u064a\u062f\u064a"
    ],
    "name:ast_x_preferred":[
        "Xidi"
    ],
    "name:ces_x_preferred":[
        "Si-ti"
    ],
    "name:eus_x_preferred":[
        "Xidi"
    ],
    "name:fas_x_preferred":[
        "\u0634\u06cc\u062f\u06cc"
    ],
    "name:fin_x_preferred":[
        "Xidi"
    ],
    "name:fra_x_preferred":[
        "Xidi"
    ],
    "name:heb_x_preferred":[
        "\u05e9\u05d9\u05d3\u05d9"
    ],
    "name:hrv_x_preferred":[
        "Xidi"
    ],
    "name:ita_x_preferred":[
        "Xidi"
    ],
    "name:jpn_x_preferred":[
        "\u897f\u9013\u6751"
    ],
    "name:kat_x_preferred":[
        "\u10e1\u10d8\u10d3\u10d8"
    ],
    "name:kor_x_preferred":[
        "\uc2dc\ub514\ucd98"
    ],
    "name:mal_x_preferred":[
        "\u0d37\u0d40\u0d26\u0d3f"
    ],
    "name:nld_x_preferred":[
        "Xidi"
    ],
    "name:nor_x_preferred":[
        "Xidi"
    ],
    "name:por_x_preferred":[
        "Xidi"
    ],
    "name:slk_x_preferred":[
        "Si-ti"
    ],
    "name:spa_x_preferred":[
        "Xidi"
    ],
    "name:swe_x_preferred":[
        "Xidi"
    ],
    "name:tur_x_preferred":[
        "Xidi"
    ],
    "name:und_x_variant":[
        "Hsi-ti",
        "Xidi",
        "\u897f\u9012",
        "Xidi Zhen",
        "\u897f\u9012\u9547"
    ],
    "name:vie_x_preferred":[
        "T\u00e2y \u0110\u1ec7"
    ],
    "name:zho_x_preferred":[
        "\u897f\u9012\u6751"
    ],
    "wof:name":"Xidi",
    "wof:placetype":"locality"
},
  "geometry": {"coordinates":[117.99241000000001,29.90722],"type":"Point"}
}