{
  "type": "Feature",
  "properties": {
    "gn:admin1_code":"1.0",
    "gn:asciiname":"Xidi",
    "gn:country_code":"CN",
    "gn:dem":235,
    "gn:feature_class":"P",
    "gn:feature_code":"PPLA4",
    "gn:name":"Xidi",
    "gn:population":0,
    "gn:timezone":"Asia/Shanghai",
    "iso:country":"CN",
    "name:und_x_variant":[
        "Hsi-ti",
        "Xidi",
        "\u897f\u9012",
        "Xidi Zhen",
        "\u897f\u9012\u9547"
    ],
    "wof:name":"Xidi",
    "wof:placetype":"locality"
},
  "geometry": {"coordinates":[117.99241000000001,29.90722],"type":"Point"}
}