{
  "type": "Feature",
  "properties": {
    "gn:admin1_code":"30.0",
    "gn:asciiname":"Julong",
    "gn:country_code":"CN",
    "gn:dem":1,
    "gn:feature_class":"P",
    "gn:feature_code":"PPL",
    "gn:name":"Julong",
    "gn:population":0,
    "gn:timezone":"Asia/Shanghai",
    "iso:country":"CN",
    "name:zho_x_preferred":[
        "\u805a\u9f99"
    ],
    "wof:name":"Julong",
    "wof:placetype":"locality"
},
  "geometry": {"coordinates":[113.33118,22.61127],"type":"Point"}
}