{
  "type": "Feature",
  "properties": {
    "gn:admin1_code":"20",
    "gn:asciiname":"Tung-pa-kan-t'a-la",
    "gn:country_code":"CN",
    "gn:dem":600,
    "gn:feature_class":"P",
    "gn:feature_code":"PPL",
    "gn:name":"Tung-pa-kan-t\u2019a-la",
    "gn:population":0,
    "gn:timezone":"Asia/Shanghai",
    "iso:country":"CN",
    "wof:name":"Tung-pa-kan-t'a-la",
    "wof:placetype":"locality"
},
  "geometry": {"coordinates":[119.30278,42.925],"type":"Point"}
}