{
  "type": "Feature",
  "properties": {
    "gn:admin1_code":"8.0",
    "gn:asciiname":"Baiyutan",
    "gn:country_code":"CN",
    "gn:dem":76,
    "gn:feature_class":"P",
    "gn:feature_code":"PPL",
    "gn:name":"Baiyutan",
    "gn:population":0,
    "gn:timezone":"Asia/Shanghai",
    "iso:country":"CN",
    "name:zho_x_preferred":[
        "\u767d\u6e14\u6ee9"
    ],
    "wof:name":"Baiyutan",
    "wof:placetype":"locality"
},
  "geometry": {"coordinates":[132.47266000000002,45.33492],"type":"Point"}
}