{
  "type": "Feature",
  "properties": {
    "gn:admin1_code":"13",
    "gn:asciiname":"Baxilike",
    "gn:country_code":"CN",
    "gn:dem":2457,
    "gn:feature_class":"P",
    "gn:feature_code":"PPL",
    "gn:name":"Baxilike",
    "gn:population":0,
    "gn:timezone":"Asia/Urumqi",
    "iso:country":"CN",
    "name:und_x_variant":[
        "\u5df4\u897f\u529b\u514b"
    ],
    "wof:name":"Baxilike",
    "wof:placetype":"locality"
},
  "geometry": {"coordinates":[84.49065,42.77835],"type":"Point"}
}