{
  "type": "Feature",
  "properties": {
    "gn:admin1_code":"25",
    "gn:asciiname":"Zhuanyu Yicun",
    "gn:country_code":"CN",
    "gn:dem":143,
    "gn:feature_class":"P",
    "gn:feature_code":"PPL",
    "gn:name":"Zhuanyu Yicun",
    "gn:population":0,
    "gn:timezone":"Asia/Shanghai",
    "iso:country":"CN",
    "name:zho_x_preferred":[
        "\u989b\u81fe\u4e00\u6751"
    ],
    "wof:name":"Zhuanyu Yicun",
    "wof:placetype":"locality"
},
  "geometry": {"coordinates":[117.68300000000001,35.5079],"type":"Point"}
}