{
  "type": "Feature",
  "properties": {
    "gn:admin1_code":"25",
    "gn:asciiname":"Houlizeng",
    "gn:country_code":"CN",
    "gn:dem":68,
    "gn:feature_class":"P",
    "gn:feature_code":"PPL",
    "gn:name":"Houlizeng",
    "gn:population":0,
    "gn:timezone":"Asia/Shanghai",
    "iso:country":"CN",
    "name:zho_x_preferred":[
        "\u540e\u5229\u589e"
    ],
    "wof:name":"Houlizeng",
    "wof:placetype":"locality"
},
  "geometry": {"coordinates":[117.776,34.8186],"type":"Point"}
}