{
  "type": "Feature",
  "properties": {
    "gn:admin1_code":"14.0",
    "gn:asciiname":"Debu",
    "gn:country_code":"CN",
    "gn:dem":4086,
    "gn:feature_class":"P",
    "gn:feature_code":"PPL",
    "gn:name":"Debu",
    "gn:population":0,
    "gn:timezone":"Asia/Urumqi",
    "iso:country":"CN",
    "name:zho_x_preferred":[
        "\u5fb7\u5e03"
    ],
    "wof:name":"Debu",
    "wof:placetype":"locality"
},
  "geometry": {"coordinates":[88.38679999999999,29.0394],"type":"Point"}
}