{
  "type": "Feature",
  "properties": {
    "gn:admin1_code":"4.0",
    "gn:asciiname":"Tianduli",
    "gn:country_code":"CN",
    "gn:dem":4,
    "gn:feature_class":"P",
    "gn:feature_code":"PPL",
    "gn:name":"Tianduli",
    "gn:population":0,
    "gn:timezone":"Asia/Shanghai",
    "iso:country":"CN",
    "name:und_x_variant":[
        "\u7530\u809a\u91cc"
    ],
    "name:zho_x_preferred":[
        "\u7530\u809a\u91cc"
    ],
    "wof:name":"Tianduli",
    "wof:placetype":"locality"
},
  "geometry": {"coordinates":[120.86539999999999,31.55852],"type":"Point"}
}