{
  "type": "Feature",
  "properties": {
    "gn:admin1_code":"3.0",
    "gn:asciiname":"Huangkengkou",
    "gn:country_code":"CN",
    "gn:dem":152,
    "gn:feature_class":"P",
    "gn:feature_code":"PPL",
    "gn:name":"Huangkengkou",
    "gn:population":0,
    "gn:timezone":"Asia/Shanghai",
    "iso:country":"CN",
    "name:und_x_variant":[
        "\u9ec4\u5751\u53e3"
    ],
    "wof:name":"Huangkengkou",
    "wof:placetype":"locality"
},
  "geometry": {"coordinates":[115.76088,26.15309],"type":"Point"}
}