{
  "type": "Feature",
  "properties": {
    "gn:admin1_code":"1.0",
    "gn:asciiname":"Ma'an",
    "gn:country_code":"CN",
    "gn:dem":27,
    "gn:feature_class":"P",
    "gn:feature_code":"PPL",
    "gn:name":"Ma\u2019an",
    "gn:population":0,
    "gn:timezone":"Asia/Shanghai",
    "iso:country":"CN",
    "name:ara_x_preferred":[
        "\u0645\u0639\u0627\u0646"
    ],
    "name:cat_x_preferred":[
        "Maan"
    ],
    "name:ceb_x_preferred":[
        "Ma'an"
    ],
    "name:ces_x_preferred":[
        "Ma'\u00e1n"
    ],
    "name:cym_x_preferred":[
        "Ma'an"
    ],
    "name:dan_x_preferred":[
        "Ma'an"
    ],
    "name:deu_x_preferred":[
        "Ma\u02bfan"
    ],
    "name:fas_x_preferred":[
        "\u0645\u0639\u0627\u0646"
    ],
    "name:fin_x_preferred":[
        "Ma\u2019an"
    ],
    "name:fra_x_preferred":[
        "Ma'an"
    ],
    "name:heb_x_preferred":[
        "\u05de\u05e2\u05d0\u05df"
    ],
    "name:hun_x_preferred":[
        "Ma\u00e1n"
    ],
    "name:hye_x_preferred":[
        "\u0544\u0561\u0561\u0576"
    ],
    "name:ita_x_preferred":[
        "Ma'an"
    ],
    "name:jpn_x_preferred":[
        "\u30de\u30a2\u30fc\u30f3"
    ],
    "name:kaz_x_preferred":[
        "\u041c\u0430\u0430\u043d \u049b\u0430\u043b\u0430\u0441\u044b"
    ],
    "name:lit_x_preferred":[
        "Maanas"
    ],
    "name:mzn_x_preferred":[
        "\u0645\u0639\u0627\u0646"
    ],
    "name:nld_x_preferred":[
        "Ma'an"
    ],
    "name:nno_x_preferred":[
        "Ma'an"
    ],
    "name:nor_x_preferred":[
        "Ma'an"
    ],
    "name:pnb_x_preferred":[
        "\u0645\u0639\u0627\u0646"
    ],
    "name:pol_x_preferred":[
        "Ma\u2019an"
    ],
    "name:rus_x_preferred":[
        "\u041c\u0430\u0430\u043d"
    ],
    "name:sco_x_preferred":[
        "Ma'an"
    ],
    "name:spa_x_preferred":[
        "Ma'an"
    ],
    "name:sqi_x_preferred":[
        "Ma'an"
    ],
    "name:tur_x_preferred":[
        "Ma'an"
    ],
    "name:urd_x_preferred":[
        "\u0645\u0639\u0627\u0646"
    ],
    "name:zho_x_preferred":[
        "Ma\u2019an"
    ],
    "name:zho_x_variant":[
        "\u9a6c\u978d"
    ],
    "wof:name":"Ma'an",
    "wof:placetype":"locality"
},
  "geometry": {"coordinates":[118.47834,30.74781],"type":"Point"}
}