{
  "type": "Feature",
  "properties": {
    "gn:admin1_code":"11.0",
    "gn:asciiname":"Huangyusi",
    "gn:country_code":"CN",
    "gn:dem":489,
    "gn:feature_class":"P",
    "gn:feature_code":"PPL",
    "gn:name":"Huangyusi",
    "gn:population":0,
    "gn:timezone":"Asia/Shanghai",
    "iso:country":"CN",
    "name:zho_x_preferred":[
        "\u9ec4\u5cea\u5bfa"
    ],
    "wof:name":"Huangyusi",
    "wof:placetype":"locality"
},
  "geometry": {"coordinates":[110.29526,29.60908],"type":"Point"}
}