{
  "type": "Feature",
  "properties": {
    "gn:admin1_code":"16",
    "gn:asciiname":"Shanggui",
    "gn:country_code":"CN",
    "gn:dem":338,
    "gn:feature_class":"P",
    "gn:feature_code":"PPL",
    "gn:name":"Shanggui",
    "gn:population":0,
    "gn:timezone":"Asia/Shanghai",
    "iso:country":"CN",
    "wof:name":"Shanggui",
    "wof:placetype":"locality"
},
  "geometry": {"coordinates":[110.63222,25.38083],"type":"Point"}
}