{
  "type": "Feature",
  "properties": {
    "gn:admin1_code":"2.0",
    "gn:asciiname":"Huanggekeng",
    "gn:country_code":"CN",
    "gn:dem":490,
    "gn:feature_class":"P",
    "gn:feature_code":"PPL",
    "gn:name":"Huanggekeng",
    "gn:population":0,
    "gn:timezone":"Asia/Shanghai",
    "iso:country":"CN",
    "name:zho_x_preferred":[
        "\u9ec4\u5404\u5751"
    ],
    "wof:name":"Huanggekeng",
    "wof:placetype":"locality"
},
  "geometry": {"coordinates":[120.70547000000001,29.2716],"type":"Point"}
}