{
  "type": "Feature",
  "properties": {
    "gn:admin1_code":"15.0",
    "gn:asciiname":"Changzhaotai",
    "gn:country_code":"CN",
    "gn:dem":1505,
    "gn:feature_class":"P",
    "gn:feature_code":"PPL",
    "gn:name":"Changzhaotai",
    "gn:population":0,
    "gn:timezone":"Asia/Shanghai",
    "iso:country":"CN",
    "name:und_x_variant":[
        "\u5e38\u8d75\u53f0"
    ],
    "wof:name":"Changzhaotai",
    "wof:placetype":"locality"
},
  "geometry": {"coordinates":[106.9764,36.46457],"type":"Point"}
}