{
  "type": "Feature",
  "properties": {
    "gn:admin1_code":"15.0",
    "gn:asciiname":"Yuezhuang",
    "gn:country_code":"CN",
    "gn:dem":1351,
    "gn:feature_class":"P",
    "gn:feature_code":"PPL",
    "gn:name":"Yuezhuang",
    "gn:population":0,
    "gn:timezone":"Asia/Shanghai",
    "iso:country":"CN",
    "name:zho_x_preferred":[
        "\u5cb3\u5e84"
    ],
    "wof:name":"Yuezhuang",
    "wof:placetype":"locality"
},
  "geometry": {"coordinates":[107.39700000000001,35.8324],"type":"Point"}
}