{
  "type": "Feature",
  "properties": {
    "gn:admin1_code":"26.0",
    "gn:asciiname":"Shangdiancun",
    "gn:country_code":"CN",
    "gn:dem":1282,
    "gn:feature_class":"P",
    "gn:feature_code":"PPL",
    "gn:name":"Shangdiancun",
    "gn:population":0,
    "gn:timezone":"Asia/Shanghai",
    "iso:country":"CN",
    "name:zho_x_preferred":[
        "\u4e0a\u5e97\u6751"
    ],
    "wof:name":"Shangdiancun",
    "wof:placetype":"locality"
},
  "geometry": {"coordinates":[109.18491000000002,35.01788],"type":"Point"}
}