{
  "type": "Feature",
  "properties": {
    "gn:admin1_code":"19.0",
    "gn:asciiname":"Sandaolinzi",
    "gn:country_code":"CN",
    "gn:dem":125,
    "gn:feature_class":"P",
    "gn:feature_code":"PPL",
    "gn:name":"Sandaolinzi",
    "gn:population":0,
    "gn:timezone":"Asia/Shanghai",
    "iso:country":"CN",
    "name:zho_x_preferred":[
        "\u4e09\u9053\u6797\u5b50"
    ],
    "wof:name":"Sandaolinzi",
    "wof:placetype":"locality"
},
  "geometry": {"coordinates":[124.0531,42.92089],"type":"Point"}
}