{
  "type": "Feature",
  "properties": {
    "gn:admin1_code":"30",
    "gn:asciiname":"Jinxiang",
    "gn:country_code":"CN",
    "gn:dem":5,
    "gn:feature_class":"P",
    "gn:feature_code":"PPLA4",
    "gn:name":"Jinxiang",
    "gn:population":0,
    "gn:timezone":"Asia/Shanghai",
    "iso:country":"CN",
    "name:und_x_variant":[
        "Jinxiang Zhen",
        "\u91d1\u53a2\u9547"
    ],
    "name:zho_x_preferred":[
        "\u91d1\u53a2"
    ],
    "wof:name":"Jinxiang",
    "wof:placetype":"locality"
},
  "geometry": {"coordinates":[115.72826000000001,22.86221],"type":"Point"}
}