{
  "type": "Feature",
  "properties": {
    "gn:admin1_code":"7",
    "gn:asciiname":"Qijiayang",
    "gn:country_code":"CN",
    "gn:dem":968,
    "gn:feature_class":"P",
    "gn:feature_code":"PPL",
    "gn:name":"Qijiayang",
    "gn:population":0,
    "gn:timezone":"Asia/Shanghai",
    "iso:country":"CN",
    "name:und_x_variant":[
        "\u9f50\u5bb6\u6d0b"
    ],
    "wof:name":"Qijiayang",
    "wof:placetype":"locality"
},
  "geometry": {"coordinates":[119.05777999999999,27.19167],"type":"Point"}
}