{
  "type": "Feature",
  "properties": {
    "gn:admin1_code":"19.0",
    "gn:asciiname":"Xiangshuipao",
    "gn:country_code":"CN",
    "gn:dem":10,
    "gn:feature_class":"P",
    "gn:feature_code":"PPL",
    "gn:name":"Xiangshuipao",
    "gn:population":0,
    "gn:timezone":"Asia/Shanghai",
    "iso:country":"CN",
    "name:und_x_variant":[
        "\u7965\u6c34\u6ce1"
    ],
    "wof:name":"Xiangshuipao",
    "wof:placetype":"locality"
},
  "geometry": {"coordinates":[122.55643000000001,40.82053],"type":"Point"}
}