{
  "type": "Feature",
  "properties": {
    "gn:admin1_code":"30.0",
    "gn:asciiname":"Fengguang",
    "gn:country_code":"CN",
    "gn:dem":14,
    "gn:feature_class":"P",
    "gn:feature_code":"PPL",
    "gn:name":"Fengguang",
    "gn:population":0,
    "gn:timezone":"Asia/Shanghai",
    "iso:country":"CN",
    "name:zho_x_preferred":[
        "\u98a8\u5149"
    ],
    "wof:name":"Fengguang",
    "wof:placetype":"locality"
},
  "geometry": {"coordinates":[112.51622999999999,22.24393],"type":"Point"}
}