{
  "type": "Feature",
  "properties": {
    "gn:admin1_code":"15.0",
    "gn:asciiname":"Yinjiacheng",
    "gn:country_code":"CN",
    "gn:dem":1378,
    "gn:feature_class":"P",
    "gn:feature_code":"PPLA4",
    "gn:name":"Yinjiacheng",
    "gn:population":0,
    "gn:timezone":"Asia/Shanghai",
    "iso:country":"CN",
    "name:und_x_variant":[
        "\u6bb7\u5bb6\u57ce",
        "Yinjiacheng Xiang",
        "\u6bb7\u5bb6\u57ce\u4e61"
    ],
    "wof:name":"Yinjiacheng",
    "wof:placetype":"locality"
},
  "geometry": {"coordinates":[106.94127,36.18866],"type":"Point"}
}