{
  "type": "Feature",
  "properties": {
    "gn:admin1_code":"29.0",
    "gn:asciiname":"Yijiaoluo",
    "gn:country_code":"CN",
    "gn:dem":1632,
    "gn:feature_class":"P",
    "gn:feature_code":"PPL",
    "gn:name":"Yijiaoluo",
    "gn:population":0,
    "gn:timezone":"Asia/Shanghai",
    "iso:country":"CN",
    "name:zho_x_preferred":[
        "\u4e00\u89d2\u843d"
    ],
    "wof:name":"Yijiaoluo",
    "wof:placetype":"locality"
},
  "geometry": {"coordinates":[99.36190000000001,24.8158],"type":"Point"}
}