{
  "type": "Feature",
  "properties": {
    "gn:admin1_code":"03",
    "gn:asciiname":"Jiantianjie",
    "gn:country_code":"CN",
    "gn:dem":39,
    "gn:feature_class":"P",
    "gn:feature_code":"PPLA4",
    "gn:name":"Jiantianjie",
    "gn:population":0,
    "gn:timezone":"Asia/Shanghai",
    "iso:country":"CN",
    "name:und_x_variant":[
        "Chien-t\u2019ien",
        "Jiantian",
        "Jiantianjie",
        "\u67a7\u7530\u8857",
        "Jiantianjie Xiang",
        "\u67a7\u7530\u8857\u4e61"
    ],
    "wof:name":"Jiantianjie",
    "wof:placetype":"locality"
},
  "geometry": {"coordinates":[116.98582,29.42304],"type":"Point"}
}