{
  "type": "Feature",
  "properties": {
    "gn:admin1_code":"14.0",
    "gn:asciiname":"Zaza",
    "gn:country_code":"CN",
    "gn:dem":4224,
    "gn:feature_class":"P",
    "gn:feature_code":"PPL",
    "gn:name":"Zaza",
    "gn:population":0,
    "gn:timezone":"Asia/Urumqi",
    "iso:country":"CN",
    "name:bre_x_preferred":[
        "Zaza"
    ],
    "name:cat_x_preferred":[
        "Zaza"
    ],
    "name:ceb_x_preferred":[
        "Zaza"
    ],
    "name:ces_x_preferred":[
        "Zaza"
    ],
    "name:deu_x_preferred":[
        "Zaza"
    ],
    "name:fra_x_preferred":[
        "Zaza"
    ],
    "name:ita_x_preferred":[
        "Zaza"
    ],
    "name:nld_x_preferred":[
        "Zaza"
    ],
    "name:por_x_preferred":[
        "Zaza"
    ],
    "name:rus_x_preferred":[
        "\u0417\u0430\u0437\u0430"
    ],
    "name:swe_x_preferred":[
        "Zaza"
    ],
    "name:ukr_x_preferred":[
        "\u0417\u0430\u0437\u0430"
    ],
    "name:zho_x_preferred":[
        "\u6742\u6742"
    ],
    "wof:name":"Zaza",
    "wof:placetype":"locality"
},
  "geometry": {"coordinates":[87.25320000000001,28.1888],"type":"Point"}
}