{
  "type": "Feature",
  "properties": {
    "gn:admin1_code":"16.0",
    "gn:asciiname":"Shikouding",
    "gn:country_code":"CN",
    "gn:dem":372,
    "gn:feature_class":"P",
    "gn:feature_code":"PPL",
    "gn:name":"Shikouding",
    "gn:population":0,
    "gn:timezone":"Asia/Shanghai",
    "iso:country":"CN",
    "name:zho_x_preferred":[
        "\u77f3\u53e3\u9876"
    ],
    "wof:name":"Shikouding",
    "wof:placetype":"locality"
},
  "geometry": {"coordinates":[110.59999999999999,22.4818],"type":"Point"}
}