{
  "type": "Feature",
  "properties": {
    "gn:admin1_code":"10",
    "gn:asciiname":"Zaohu Chenyicun",
    "gn:country_code":"CN",
    "gn:dem":18,
    "gn:feature_class":"P",
    "gn:feature_code":"PPL",
    "gn:name":"Zaohu Chenyicun",
    "gn:population":0,
    "gn:timezone":"Asia/Shanghai",
    "iso:country":"CN",
    "name:zho_x_preferred":[
        "\u7682\u6237\u9648\u4e00\u6751"
    ],
    "wof:name":"Zaohu Chenyicun",
    "wof:placetype":"locality"
},
  "geometry": {"coordinates":[116.49288,37.80163],"type":"Point"}
}