{
  "type": "Feature",
  "properties": {
    "gn:admin1_code":"24.0",
    "gn:asciiname":"Songluo",
    "gn:country_code":"CN",
    "gn:dem":1538,
    "gn:feature_class":"P",
    "gn:feature_code":"PPL",
    "gn:name":"Songluo",
    "gn:population":0,
    "gn:timezone":"Asia/Shanghai",
    "iso:country":"CN",
    "name:zho_x_preferred":[
        "\u677e\u7f57"
    ],
    "wof:name":"Songluo",
    "wof:placetype":"locality"
},
  "geometry": {"coordinates":[112.21759,36.84854],"type":"Point"}
}