{
  "type": "Feature",
  "properties": {
    "gn:admin1_code":"1.0",
    "gn:asciiname":"Pangzhuangcun",
    "gn:country_code":"CN",
    "gn:dem":47,
    "gn:feature_class":"P",
    "gn:feature_code":"PPL",
    "gn:name":"Pangzhuangcun",
    "gn:population":0,
    "gn:timezone":"Asia/Shanghai",
    "iso:country":"CN",
    "name:zho_x_preferred":[
        "\u5e9e\u5e84\u6751"
    ],
    "wof:name":"Pangzhuangcun",
    "wof:placetype":"locality"
},
  "geometry": {"coordinates":[114.93491000000002,32.99056],"type":"Point"}
}