{
  "type": "Feature",
  "properties": {
    "gn:admin1_code":"31.0",
    "gn:asciiname":"Baizhun",
    "gn:country_code":"CN",
    "gn:dem":352,
    "gn:feature_class":"P",
    "gn:feature_code":"PPL",
    "gn:name":"Baizhun",
    "gn:population":0,
    "gn:timezone":"Asia/Shanghai",
    "iso:country":"CN",
    "name:zho_x_preferred":[
        "\u767d\u51c6"
    ],
    "wof:name":"Baizhun",
    "wof:placetype":"locality"
},
  "geometry": {"coordinates":[109.43653,19.33825],"type":"Point"}
}