{
  "type": "Feature",
  "properties": {
    "gn:admin1_code":"10",
    "gn:asciiname":"Xibeihua",
    "gn:country_code":"CN",
    "gn:dem":26,
    "gn:feature_class":"P",
    "gn:feature_code":"PPL",
    "gn:name":"Xibeihua",
    "gn:population":0,
    "gn:timezone":"Asia/Shanghai",
    "iso:country":"CN",
    "name:zho_x_preferred":[
        "\u897f\u5317\u5316"
    ],
    "wof:name":"Xibeihua",
    "wof:placetype":"locality"
},
  "geometry": {"coordinates":[116.04916,37.48785],"type":"Point"}
}