{
  "type": "Feature",
  "properties": {
    "gn:admin1_code":"9.0",
    "gn:asciiname":"Houshan Longkou",
    "gn:country_code":"CN",
    "gn:dem":69,
    "gn:feature_class":"P",
    "gn:feature_code":"PPL",
    "gn:name":"Houshan Longkou",
    "gn:population":0,
    "gn:timezone":"Asia/Shanghai",
    "iso:country":"CN",
    "name:zho_x_preferred":[
        "\u540e\u5c71\u9f99\u53e3"
    ],
    "wof:name":"Houshan Longkou",
    "wof:placetype":"locality"
},
  "geometry": {"coordinates":[114.47747,34.52311],"type":"Point"}
}