{
  "type": "Feature",
  "properties": {
    "gn:admin1_code":"3.0",
    "gn:asciiname":"Zengfang",
    "gn:country_code":"CN",
    "gn:dem":345,
    "gn:feature_class":"P",
    "gn:feature_code":"PPL",
    "gn:name":"Zengfang",
    "gn:population":0,
    "gn:timezone":"Asia/Shanghai",
    "iso:country":"CN",
    "name:und_x_variant":[
        "\u589e\u574a"
    ],
    "wof:name":"Zengfang",
    "wof:placetype":"locality"
},
  "geometry": {"coordinates":[114.7921,24.65565],"type":"Point"}
}