{
  "type": "Feature",
  "properties": {
    "gn:admin1_code":"5.0",
    "gn:asciiname":"Tangfanggoucun",
    "gn:country_code":"CN",
    "gn:dem":195,
    "gn:feature_class":"P",
    "gn:feature_code":"PPL",
    "gn:name":"Tangfanggoucun",
    "gn:population":0,
    "gn:timezone":"Asia/Shanghai",
    "iso:country":"CN",
    "name:zho_x_preferred":[
        "\u7cd6\u574a\u6c9f\u6751"
    ],
    "wof:name":"Tangfanggoucun",
    "wof:placetype":"locality"
},
  "geometry": {"coordinates":[126.18196,44.01119],"type":"Point"}
}