{
  "type": "Feature",
  "properties": {
    "gn:admin1_code":"32.0",
    "gn:asciiname":"Babang",
    "gn:country_code":"CN",
    "gn:dem":3900,
    "gn:feature_class":"P",
    "gn:feature_code":"PPL",
    "gn:name":"Babang",
    "gn:population":0,
    "gn:timezone":"Asia/Shanghai",
    "iso:country":"CN",
    "name:zho_x_preferred":[
        "\u516b\u90a6"
    ],
    "wof:name":"Babang",
    "wof:placetype":"locality"
},
  "geometry": {"coordinates":[98.79098999999999,31.63589],"type":"Point"}
}