{
  "type": "Feature",
  "properties": {
    "gn:admin1_code":"4.0",
    "gn:asciiname":"Zhukengcun",
    "gn:country_code":"CN",
    "gn:dem":39,
    "gn:feature_class":"P",
    "gn:feature_code":"PPL",
    "gn:name":"Zhukengcun",
    "gn:population":0,
    "gn:timezone":"Asia/Shanghai",
    "iso:country":"CN",
    "name:zho_x_preferred":[
        "\u6731\u5751\u6751"
    ],
    "wof:name":"Zhukengcun",
    "wof:placetype":"locality"
},
  "geometry": {"coordinates":[116.5401,34.86908],"type":"Point"}
}