{
  "type": "Feature",
  "properties": {
    "gn:admin1_code":"7.0",
    "gn:asciiname":"Gantangwan",
    "gn:country_code":"CN",
    "gn:dem":287,
    "gn:feature_class":"P",
    "gn:feature_code":"PPL",
    "gn:name":"Gantangwan",
    "gn:population":0,
    "gn:timezone":"Asia/Shanghai",
    "iso:country":"CN",
    "name:zho_x_preferred":[
        "\u7518\u68e0\u6e7e"
    ],
    "wof:name":"Gantangwan",
    "wof:placetype":"locality"
},
  "geometry": {"coordinates":[116.22928,25.38871],"type":"Point"}
}