{
  "type": "Feature",
  "properties": {
    "gn:admin1_code":"29.0",
    "gn:asciiname":"Longjiezi",
    "gn:country_code":"CN",
    "gn:dem":1261,
    "gn:feature_class":"P",
    "gn:feature_code":"PPL",
    "gn:name":"Longjiezi",
    "gn:population":0,
    "gn:timezone":"Asia/Shanghai",
    "iso:country":"CN",
    "name:zho_x_preferred":[
        "\u9f99\u8857\u5b50"
    ],
    "wof:name":"Longjiezi",
    "wof:placetype":"locality"
},
  "geometry": {"coordinates":[104.473,25.0387],"type":"Point"}
}