{
  "type": "Feature",
  "properties": {
    "gn:admin1_code":"8.0",
    "gn:asciiname":"Junchuan Sishierdui",
    "gn:country_code":"CN",
    "gn:dem":65,
    "gn:feature_class":"P",
    "gn:feature_code":"PPLF",
    "gn:name":"Junchuan Sishierdui",
    "gn:population":0,
    "gn:timezone":"Asia/Shanghai",
    "iso:country":"CN",
    "name:zho_x_preferred":[
        "\u519b\u5ddd\u56db\u5341\u4e8c\u961f"
    ],
    "wof:name":"Junchuan Sishierdui",
    "wof:placetype":"locality"
},
  "geometry": {"coordinates":[131.13767000000001,47.4055],"type":"Point"}
}