{
  "type": "Feature",
  "properties": {
    "gn:admin1_code":"18",
    "gn:asciiname":"Jiabang",
    "gn:country_code":"CN",
    "gn:dem":764,
    "gn:feature_class":"P",
    "gn:feature_code":"PPL",
    "gn:name":"Jiabang",
    "gn:population":0,
    "gn:timezone":"Asia/Shanghai",
    "iso:country":"CN",
    "wof:name":"Jiabang",
    "wof:placetype":"locality"
},
  "geometry": {"coordinates":[108.51972000000001,25.53056],"type":"Point"}
}