{
  "type": "Feature",
  "properties": {
    "gn:admin1_code":"12.0",
    "gn:asciiname":"Liujiadu",
    "gn:country_code":"CN",
    "gn:dem":24,
    "gn:feature_class":"P",
    "gn:feature_code":"PPL",
    "gn:name":"Liujiadu",
    "gn:population":0,
    "gn:timezone":"Asia/Shanghai",
    "iso:country":"CN",
    "name:zho_x_preferred":[
        "Liujiadu"
    ],
    "name:zho_x_variant":[
        "\u5218\u5bb6\u6e21"
    ],
    "wof:name":"Liujiadu",
    "wof:placetype":"locality"
},
  "geometry": {"coordinates":[115.0677,30.28048],"type":"Point"}
}