{
  "type": "Feature",
  "properties": {
    "gn:admin1_code":"11.0",
    "gn:asciiname":"Yuqianwan",
    "gn:country_code":"CN",
    "gn:dem":291,
    "gn:feature_class":"P",
    "gn:feature_code":"PPL",
    "gn:name":"Yuqianwan",
    "gn:population":0,
    "gn:timezone":"Asia/Shanghai",
    "iso:country":"CN",
    "name:zho_x_preferred":[
        "\u4f59\u524d\u6e7e"
    ],
    "wof:name":"Yuqianwan",
    "wof:placetype":"locality"
},
  "geometry": {"coordinates":[111.52159,28.13973],"type":"Point"}
}