{
  "type": "Feature",
  "properties": {
    "gn:admin1_code":"24.0",
    "gn:asciiname":"Shangbaile",
    "gn:country_code":"CN",
    "gn:dem":1029,
    "gn:feature_class":"P",
    "gn:feature_code":"PPL",
    "gn:name":"Shangbaile",
    "gn:population":0,
    "gn:timezone":"Asia/Shanghai",
    "iso:country":"CN",
    "name:zho_x_preferred":[
        "\u4e0a\u67cf\u4e50"
    ],
    "wof:name":"Shangbaile",
    "wof:placetype":"locality"
},
  "geometry": {"coordinates":[111.43868999999999,36.69449],"type":"Point"}
}