{
  "type": "Feature",
  "properties": {
    "gn:admin1_code":"26.0",
    "gn:asciiname":"Wangwancun",
    "gn:country_code":"CN",
    "gn:dem":589,
    "gn:feature_class":"P",
    "gn:feature_code":"PPL",
    "gn:name":"Wangwancun",
    "gn:population":0,
    "gn:timezone":"Asia/Shanghai",
    "iso:country":"CN",
    "name:zho_x_preferred":[
        "\u738b\u6e7e\u6751"
    ],
    "wof:name":"Wangwancun",
    "wof:placetype":"locality"
},
  "geometry": {"coordinates":[108.99212,34.84936],"type":"Point"}
}