{
  "type": "Feature",
  "properties": {
    "gn:admin1_code":"29",
    "gn:asciiname":"Dahei",
    "gn:country_code":"CN",
    "gn:dem":2226,
    "gn:feature_class":"P",
    "gn:feature_code":"PPL",
    "gn:name":"Dahei",
    "gn:population":0,
    "gn:timezone":"Asia/Shanghai",
    "iso:country":"CN",
    "name:zho_x_preferred":[
        "\u6253\u9ed1"
    ],
    "wof:name":"Dahei",
    "wof:placetype":"locality"
},
  "geometry": {"coordinates":[102.328,24.4208],"type":"Point"}
}