{
  "type": "Feature",
  "properties": {
    "gn:admin1_code":"29.0",
    "gn:asciiname":"Yimigu",
    "gn:country_code":"CN",
    "gn:dem":1640,
    "gn:feature_class":"P",
    "gn:feature_code":"PPL",
    "gn:name":"Yimigu",
    "gn:population":0,
    "gn:timezone":"Asia/Shanghai",
    "iso:country":"CN",
    "name:zho_x_preferred":[
        "\u4ee5\u54aa\u53e4"
    ],
    "wof:name":"Yimigu",
    "wof:placetype":"locality"
},
  "geometry": {"coordinates":[102.12,25.916],"type":"Point"}
}