{
  "type": "Feature",
  "properties": {
    "gn:admin1_code":"15.0",
    "gn:asciiname":"Zhongzhuangshan",
    "gn:country_code":"CN",
    "gn:dem":2180,
    "gn:feature_class":"P",
    "gn:feature_code":"PPL",
    "gn:name":"Zhongzhuangshan",
    "gn:population":0,
    "gn:timezone":"Asia/Shanghai",
    "iso:country":"CN",
    "name:und_x_variant":[
        "\u4e2d\u5e84\u5c71"
    ],
    "wof:name":"Zhongzhuangshan",
    "wof:placetype":"locality"
},
  "geometry": {"coordinates":[102.96299999999999,35.8524],"type":"Point"}
}