{
  "type": "Feature",
  "properties": {
    "gn:admin1_code":"14.0",
    "gn:asciiname":"Dibacun",
    "gn:country_code":"CN",
    "gn:dem":3162,
    "gn:feature_class":"P",
    "gn:feature_code":"PPL",
    "gn:name":"Dibacun",
    "gn:population":0,
    "gn:timezone":"Asia/Urumqi",
    "iso:country":"CN",
    "name:zho_x_preferred":[
        "\u5730\u5df4\u6751"
    ],
    "wof:name":"Dibacun",
    "wof:placetype":"locality"
},
  "geometry": {"coordinates":[98.45702,28.92135],"type":"Point"}
}