{
  "type": "Feature",
  "properties": {
    "gn:admin1_code":"5.0",
    "gn:asciiname":"Jingyuxian Diyicanchang",
    "gn:country_code":"CN",
    "gn:dem":574,
    "gn:feature_class":"P",
    "gn:feature_code":"PPLF",
    "gn:name":"Jingyuxian Diyicanchang",
    "gn:population":0,
    "gn:timezone":"Asia/Shanghai",
    "iso:country":"CN",
    "name:und_x_variant":[
        "\u9756\u5b87\u53bf\u7b2c\u4e00\u53c2\u573a"
    ],
    "wof:name":"Jingyuxian Diyicanchang",
    "wof:placetype":"locality"
},
  "geometry": {"coordinates":[126.99396000000002,42.3163],"type":"Point"}
}