{
  "type": "Feature",
  "properties": {
    "gn:admin1_code":"25",
    "gn:asciiname":"Houyu",
    "gn:country_code":"CN",
    "gn:dem":270,
    "gn:feature_class":"P",
    "gn:feature_code":"PPL",
    "gn:name":"Houyu",
    "gn:population":0,
    "gn:timezone":"Asia/Shanghai",
    "iso:country":"CN",
    "name:zho_x_preferred":[
        "\u540e\u5cea"
    ],
    "wof:name":"Houyu",
    "wof:placetype":"locality"
},
  "geometry": {"coordinates":[117.851,36.1951],"type":"Point"}
}