{
  "type": "Feature",
  "properties": {
    "gn:admin1_code":"8.0",
    "gn:asciiname":"Houtou",
    "gn:country_code":"CN",
    "gn:dem":212,
    "gn:feature_class":"P",
    "gn:feature_code":"PPLA4",
    "gn:name":"Houtou",
    "gn:population":0,
    "gn:timezone":"Asia/Shanghai",
    "iso:country":"CN",
    "name:und_x_variant":[
        "Houtou Xiang"
    ],
    "name:zho_x_preferred":[
        "\u540e\u5934"
    ],
    "name:zho_x_variant":[
        "\u540e\u5934\u4e61"
    ],
    "wof:name":"Houtou",
    "wof:placetype":"locality"
},
  "geometry": {"coordinates":[127.13803,47.17503],"type":"Point"}
}