{
  "type": "Feature",
  "properties": {
    "gn:admin1_code":"29.0",
    "gn:asciiname":"Tuguachong",
    "gn:country_code":"CN",
    "gn:dem":2086,
    "gn:feature_class":"P",
    "gn:feature_code":"PPL",
    "gn:name":"Tuguachong",
    "gn:population":0,
    "gn:timezone":"Asia/Shanghai",
    "iso:country":"CN",
    "name:zho_x_preferred":[
        "\u571f\u74dc\u51b2"
    ],
    "wof:name":"Tuguachong",
    "wof:placetype":"locality"
},
  "geometry": {"coordinates":[103.652,25.4496],"type":"Point"}
}