{
  "type": "Feature",
  "properties": {
    "gn:admin1_code":"16",
    "gn:asciiname":"Mashan",
    "gn:cc2":"CN",
    "gn:country_code":"CN",
    "gn:dem":169,
    "gn:feature_class":"P",
    "gn:feature_code":"PPL",
    "gn:name":"Mashan",
    "gn:population":0,
    "gn:timezone":"Asia/Shanghai",
    "iso:country":"CN",
    "name:und_x_variant":[
        "Ma-shan-hs\u00fc",
        "Mashan"
    ],
    "wof:name":"Mashan",
    "wof:placetype":"locality"
},
  "geometry": {"coordinates":[109.08861,24.53583],"type":"Point"}
}