{
  "type": "Feature",
  "properties": {
    "gn:admin1_code":"07",
    "gn:asciiname":"Shekou",
    "gn:country_code":"CN",
    "gn:dem":70,
    "gn:feature_class":"P",
    "gn:feature_code":"PPLA4",
    "gn:name":"Shekou",
    "gn:population":0,
    "gn:timezone":"Asia/Shanghai",
    "iso:country":"CN",
    "name:und_x_variant":[
        "Hsieh-k\u2019ou",
        "Shekow",
        "Shekou",
        "Shekou Zhen"
    ],
    "name:zho_x_preferred":[
        "\u793e\u53e3"
    ],
    "name:zho_x_variant":[
        "\u793e\u53e3\u9547"
    ],
    "wof:name":"Shekou",
    "wof:placetype":"locality"
},
  "geometry": {"coordinates":[119.57138999999999,27.21194],"type":"Point"}
}