{
  "type": "Feature",
  "properties": {
    "gn:admin1_code":"4.0",
    "gn:asciiname":"Muzi Xudai",
    "gn:country_code":"CN",
    "gn:dem":5,
    "gn:feature_class":"P",
    "gn:feature_code":"PPL",
    "gn:name":"Muzi Xudai",
    "gn:population":0,
    "gn:timezone":"Asia/Shanghai",
    "iso:country":"CN",
    "name:zho_x_preferred":[
        "\u6bcd\u5b50\u5729\u57ed"
    ],
    "wof:name":"Muzi Xudai",
    "wof:placetype":"locality"
},
  "geometry": {"coordinates":[119.85763,32.17024],"type":"Point"}
}