{
  "type": "Feature",
  "properties": {
    "gn:admin1_code":"10",
    "gn:asciiname":"Yanmochang",
    "gn:country_code":"CN",
    "gn:dem":1292,
    "gn:feature_class":"P",
    "gn:feature_code":"PPL",
    "gn:name":"Yanmochang",
    "gn:population":0,
    "gn:timezone":"Asia/Shanghai",
    "iso:country":"CN",
    "name:zho_x_preferred":[
        "\u70df\u58a8\u5382"
    ],
    "wof:name":"Yanmochang",
    "wof:placetype":"locality"
},
  "geometry": {"coordinates":[116.16759999999999,41.03184],"type":"Point"}
}