{
  "type": "Feature",
  "properties": {
    "gn:admin1_code":"12.0",
    "gn:asciiname":"Ma'anzi",
    "gn:country_code":"CN",
    "gn:dem":1042,
    "gn:feature_class":"P",
    "gn:feature_code":"PPL",
    "gn:name":"Ma\u2019anzi",
    "gn:population":0,
    "gn:timezone":"Asia/Shanghai",
    "iso:country":"CN",
    "name:zho_x_preferred":[
        "\u9a6c\u978d\u5b50"
    ],
    "name:zho_x_variant":[
        "Ma\u2019anzi"
    ],
    "wof:name":"Ma'anzi",
    "wof:placetype":"locality"
},
  "geometry": {"coordinates":[110.20050999999999,29.83046],"type":"Point"}
}