{
  "type": "Feature",
  "properties": {
    "gn:admin1_code":"33.0",
    "gn:asciiname":"Tiansheng",
    "gn:country_code":"CN",
    "gn:dem":1634,
    "gn:feature_class":"P",
    "gn:feature_code":"PPL",
    "gn:name":"Tiansheng",
    "gn:population":0,
    "gn:timezone":"Asia/Shanghai",
    "iso:country":"CN",
    "name:zho_x_preferred":[
        "\u5929\u5347"
    ],
    "wof:name":"Tiansheng",
    "wof:placetype":"locality"
},
  "geometry": {"coordinates":[109.43786,30.81444],"type":"Point"}
}