{
  "type": "Feature",
  "properties": {
    "gn:admin1_code":"7.0",
    "gn:asciiname":"Fulinggan",
    "gn:country_code":"CN",
    "gn:dem":178,
    "gn:feature_class":"P",
    "gn:feature_code":"PPL",
    "gn:name":"Fulinggan",
    "gn:population":0,
    "gn:timezone":"Asia/Shanghai",
    "iso:country":"CN",
    "name:und_x_variant":[
        "\u4f0f\u5cad\u5e72"
    ],
    "name:zho_x_preferred":[
        "\u4f0f\u5cad\u5e72"
    ],
    "wof:name":"Fulinggan",
    "wof:placetype":"locality"
},
  "geometry": {"coordinates":[117.4297,26.61312],"type":"Point"}
}