{
  "type": "Feature",
  "properties": {
    "gn:admin1_code":"9.0",
    "gn:asciiname":"Guduo",
    "gn:country_code":"CN",
    "gn:dem":262,
    "gn:feature_class":"P",
    "gn:feature_code":"PPL",
    "gn:name":"Guduo",
    "gn:population":0,
    "gn:timezone":"Asia/Shanghai",
    "iso:country":"CN",
    "name:und_x_variant":[
        "\u53e4\u579b",
        "Guduo"
    ],
    "wof:name":"Guduo",
    "wof:placetype":"locality"
},
  "geometry": {"coordinates":[112.85630999999999,33.96761],"type":"Point"}
}