{
  "type": "Feature",
  "properties": {
    "gn:admin1_code":"22.0",
    "gn:asciiname":"Dongxingyuancun",
    "gn:country_code":"CN",
    "gn:dem":503,
    "gn:feature_class":"P",
    "gn:feature_code":"PPL",
    "gn:name":"Dongxingyuancun",
    "gn:population":0,
    "gn:timezone":"Asia/Shanghai",
    "iso:country":"CN",
    "name:zho_x_preferred":[
        "\u4e1c\u674f\u56ed\u6751"
    ],
    "wof:name":"Dongxingyuancun",
    "wof:placetype":"locality"
},
  "geometry": {"coordinates":[115.97579,40.4284],"type":"Point"}
}