{
  "type": "Feature",
  "properties": {
    "gn:admin1_code":"16.0",
    "gn:asciiname":"Ningwu Jiuxu",
    "gn:country_code":"CN",
    "gn:dem":108,
    "gn:feature_class":"P",
    "gn:feature_code":"PPL",
    "gn:name":"Ningwu Jiuxu",
    "gn:population":0,
    "gn:timezone":"Asia/Shanghai",
    "iso:country":"CN",
    "name:zho_x_preferred":[
        "\u5b81\u6b66\u65e7\u5729"
    ],
    "wof:name":"Ningwu Jiuxu",
    "wof:placetype":"locality"
},
  "geometry": {"coordinates":[108.20699999999999,23.1325],"type":"Point"}
}