{
  "type": "Feature",
  "properties": {
    "gn:admin1_code":"1.0",
    "gn:asciiname":"Jiuligoucun",
    "gn:country_code":"CN",
    "gn:dem":41,
    "gn:feature_class":"P",
    "gn:feature_code":"PPL",
    "gn:name":"Jiuligoucun",
    "gn:population":0,
    "gn:timezone":"Asia/Shanghai",
    "iso:country":"CN",
    "name:zho_x_preferred":[
        "\u4e5d\u91cc\u6c9f\u6751"
    ],
    "wof:name":"Jiuligoucun",
    "wof:placetype":"locality"
},
  "geometry": {"coordinates":[116.52289,31.78203],"type":"Point"}
}