{
  "type": "Feature",
  "properties": {
    "gn:admin1_code":"2.0",
    "gn:asciiname":"Dongmenli",
    "gn:country_code":"CN",
    "gn:dem":150,
    "gn:feature_class":"P",
    "gn:feature_code":"PPL",
    "gn:name":"Dongmenli",
    "gn:population":0,
    "gn:timezone":"Asia/Shanghai",
    "iso:country":"CN",
    "name:zho_x_preferred":[
        "\u4e1c\u95e8\u91cc"
    ],
    "wof:name":"Dongmenli",
    "wof:placetype":"locality"
},
  "geometry": {"coordinates":[119.56347,29.25856],"type":"Point"}
}