{
  "type": "Feature",
  "properties": {
    "gn:admin1_code":"29",
    "gn:asciiname":"Pingmeng",
    "gn:country_code":"CN",
    "gn:dem":777,
    "gn:feature_class":"P",
    "gn:feature_code":"PPL",
    "gn:name":"Pingmeng",
    "gn:population":0,
    "gn:timezone":"Asia/Shanghai",
    "iso:country":"CN",
    "name:zho_x_preferred":[
        "\u5e73\u8499"
    ],
    "wof:name":"Pingmeng",
    "wof:placetype":"locality"
},
  "geometry": {"coordinates":[106.06399999999999,23.5763],"type":"Point"}
}