{
  "type": "Feature",
  "properties": {
    "gn:admin1_code":"1.0",
    "gn:asciiname":"Lishulingcun",
    "gn:country_code":"CN",
    "gn:dem":438,
    "gn:feature_class":"P",
    "gn:feature_code":"PPL",
    "gn:name":"Lishulingcun",
    "gn:population":0,
    "gn:timezone":"Asia/Shanghai",
    "iso:country":"CN",
    "name:zho_x_preferred":[
        "\u6817\u6811\u5cad\u6751"
    ],
    "wof:name":"Lishulingcun",
    "wof:placetype":"locality"
},
  "geometry": {"coordinates":[115.9444,31.08447],"type":"Point"}
}