{
  "type": "Feature",
  "properties": {
    "gn:admin1_code":"29.0",
    "gn:asciiname":"Xiashengqing",
    "gn:country_code":"CN",
    "gn:dem":2136,
    "gn:feature_class":"P",
    "gn:feature_code":"PPL",
    "gn:name":"Xiashengqing",
    "gn:population":0,
    "gn:timezone":"Asia/Shanghai",
    "iso:country":"CN",
    "name:zho_x_preferred":[
        "\u4e0b\u5347\u7b90"
    ],
    "wof:name":"Xiashengqing",
    "wof:placetype":"locality"
},
  "geometry": {"coordinates":[102.637,25.9619],"type":"Point"}
}