{
  "type": "Feature",
  "properties": {
    "gn:admin1_code":"32.0",
    "gn:asciiname":"Shihezhongba",
    "gn:country_code":"CN",
    "gn:dem":532,
    "gn:feature_class":"P",
    "gn:feature_code":"PPL",
    "gn:name":"Shihezhongba",
    "gn:population":0,
    "gn:timezone":"Asia/Shanghai",
    "iso:country":"CN",
    "name:zho_x_preferred":[
        "\u77f3\u6cb3\u4e2d\u575d"
    ],
    "wof:name":"Shihezhongba",
    "wof:placetype":"locality"
},
  "geometry": {"coordinates":[107.46606,30.63884],"type":"Point"}
}