{
  "type": "Feature",
  "properties": {
    "gn:admin1_code":"7.0",
    "gn:asciiname":"Yangtouzai",
    "gn:country_code":"CN",
    "gn:dem":877,
    "gn:feature_class":"P",
    "gn:feature_code":"PPL",
    "gn:name":"Yangtouzai",
    "gn:population":0,
    "gn:timezone":"Asia/Shanghai",
    "iso:country":"CN",
    "name:zho_x_preferred":[
        "\u6d0b\u5934\u4ed4"
    ],
    "wof:name":"Yangtouzai",
    "wof:placetype":"locality"
},
  "geometry": {"coordinates":[118.91054,26.84701],"type":"Point"}
}