{
  "type": "Feature",
  "properties": {
    "gn:admin1_code":"4.0",
    "gn:asciiname":"Sanfencun",
    "gn:country_code":"CN",
    "gn:dem":11,
    "gn:feature_class":"P",
    "gn:feature_code":"PPL",
    "gn:name":"Sanfencun",
    "gn:population":0,
    "gn:timezone":"Asia/Shanghai",
    "iso:country":"CN",
    "name:zho_x_preferred":[
        "\u4e09\u6c7e\u6751"
    ],
    "wof:name":"Sanfencun",
    "wof:placetype":"locality"
},
  "geometry": {"coordinates":[119.82971000000001,34.11731],"type":"Point"}
}