{
  "type": "Feature",
  "properties": {
    "gn:admin1_code":"7.0",
    "gn:asciiname":"Wutongli",
    "gn:country_code":"CN",
    "gn:dem":1005,
    "gn:feature_class":"P",
    "gn:feature_code":"PPL",
    "gn:name":"Wutongli",
    "gn:population":0,
    "gn:timezone":"Asia/Shanghai",
    "iso:country":"CN",
    "name:zho_x_preferred":[
        "\u68a7\u6850\u91cc"
    ],
    "wof:name":"Wutongli",
    "wof:placetype":"locality"
},
  "geometry": {"coordinates":[119.11936,26.38484],"type":"Point"}
}