{
  "type": "Feature",
  "properties": {
    "gn:admin1_code":"4.0",
    "gn:asciiname":"Dingjian",
    "gn:country_code":"CN",
    "gn:dem":3,
    "gn:feature_class":"P",
    "gn:feature_code":"PPL",
    "gn:name":"Dingjian",
    "gn:population":0,
    "gn:timezone":"Asia/Shanghai",
    "iso:country":"CN",
    "name:und_x_variant":[
        "\u4e01\u5c16",
        "Dingjiajian"
    ],
    "wof:name":"Dingjian",
    "wof:placetype":"locality"
},
  "geometry": {"coordinates":[120.55148,32.9753],"type":"Point"}
}