{
  "type": "Feature",
  "properties": {
    "gn:admin1_code":"32.0",
    "gn:asciiname":"Munuocao",
    "gn:country_code":"CN",
    "gn:dem":874,
    "gn:feature_class":"P",
    "gn:feature_code":"PPL",
    "gn:name":"Munuocao",
    "gn:population":0,
    "gn:timezone":"Asia/Shanghai",
    "iso:country":"CN",
    "name:zho_x_preferred":[
        "\u6728\u8bfa\u69fd"
    ],
    "wof:name":"Munuocao",
    "wof:placetype":"locality"
},
  "geometry": {"coordinates":[107.434,32.4529],"type":"Point"}
}