{
  "type": "Feature",
  "properties": {
    "gn:admin1_code":"30",
    "gn:asciiname":"Shajing",
    "gn:country_code":"CN",
    "gn:dem":8,
    "gn:feature_class":"P",
    "gn:feature_code":"PPLA4",
    "gn:name":"Shajing",
    "gn:population":0,
    "gn:timezone":"Asia/Shanghai",
    "iso:country":"CN",
    "name:und_x_variant":[
        "Shatsing",
        "Sha-ching",
        "Shajing",
        "Shajing Jiedao",
        "\u6c99\u4e95\u8857\u9053"
    ],
    "name:zho_x_preferred":[
        "\u6c99\u4e95"
    ],
    "wof:name":"Shajing",
    "wof:placetype":"locality"
},
  "geometry": {"coordinates":[113.81903,22.74628],"type":"Point"}
}