{
  "type": "Feature",
  "properties": {
    "gn:admin1_code":"14",
    "gn:asciiname":"Zhaiqen",
    "gn:country_code":"CN",
    "gn:dem":3990,
    "gn:feature_class":"P",
    "gn:feature_code":"PPL",
    "gn:name":"Zhaiq\u00ean",
    "gn:population":0,
    "gn:timezone":"Asia/Urumqi",
    "iso:country":"CN",
    "name:bod_x_preferred":[
        "\u0f51\u0f56\u0fb2\u0f63\u0f0b\u0f46\u0f7a\u0f53"
    ],
    "wof:name":"Zhaiqen",
    "wof:placetype":"locality"
},
  "geometry": {"coordinates":[92.22662,29.29426],"type":"Point"}
}