{
  "type": "Feature",
  "properties": {
    "gn:admin1_code":"19.0",
    "gn:asciiname":"Nigoucun",
    "gn:country_code":"CN",
    "gn:dem":17,
    "gn:feature_class":"P",
    "gn:feature_code":"PPL",
    "gn:name":"Nigoucun",
    "gn:population":0,
    "gn:timezone":"Asia/Shanghai",
    "iso:country":"CN",
    "name:zho_x_preferred":[
        "\u6ce5\u6c9f\u6751"
    ],
    "wof:name":"Nigoucun",
    "wof:placetype":"locality"
},
  "geometry": {"coordinates":[122.7694,41.01626],"type":"Point"}
}