{
  "type": "Feature",
  "properties": {
    "gn:admin1_code":"30",
    "gn:asciiname":"Xincunzai",
    "gn:country_code":"CN",
    "gn:dem":27,
    "gn:feature_class":"P",
    "gn:feature_code":"PPL",
    "gn:name":"Xincunzai",
    "gn:population":0,
    "gn:timezone":"Asia/Shanghai",
    "iso:country":"CN",
    "name:zho_x_preferred":[
        "\u65b0\u6751\u4ed4"
    ],
    "wof:name":"Xincunzai",
    "wof:placetype":"locality"
},
  "geometry": {"coordinates":[111.58517000000001,21.79581],"type":"Point"}
}