{
  "type": "Feature",
  "properties": {
    "gn:admin1_code":"9.0",
    "gn:asciiname":"Jizhuang",
    "gn:country_code":"CN",
    "gn:dem":294,
    "gn:feature_class":"P",
    "gn:feature_code":"PPL",
    "gn:name":"Jizhuang",
    "gn:population":0,
    "gn:timezone":"Asia/Shanghai",
    "iso:country":"CN",
    "name:zho_x_preferred":[
        "\u5180\u5e84"
    ],
    "wof:name":"Jizhuang",
    "wof:placetype":"locality"
},
  "geometry": {"coordinates":[111.7372,34.40199],"type":"Point"}
}