{
  "type": "Feature",
  "properties": {
    "gn:admin1_code":"13.0",
    "gn:asciiname":"Liushuquan Nongchang",
    "gn:country_code":"CN",
    "gn:dem":826,
    "gn:feature_class":"P",
    "gn:feature_code":"PPLF",
    "gn:name":"Liushuquan Nongchang",
    "gn:population":0,
    "gn:timezone":"Asia/Urumqi",
    "iso:country":"CN",
    "name:und_x_variant":[
        "Liu-shu-ch\u2019\u00fcan",
        "Liushuquan Nongchang"
    ],
    "name:zho_x_preferred":[
        "\u5218\u6811\u6cc9\u519c\u573a"
    ],
    "wof:name":"Liushuquan Nongchang",
    "wof:placetype":"locality"
},
  "geometry": {"coordinates":[92.8771,43.0522],"type":"Point"}
}