{
  "type": "Feature",
  "properties": {
    "gn:admin1_code":"33.0",
    "gn:asciiname":"Tonggu",
    "gn:country_code":"CN",
    "gn:dem":927,
    "gn:feature_class":"P",
    "gn:feature_code":"PPLA4",
    "gn:name":"Tonggu",
    "gn:population":0,
    "gn:timezone":"Asia/Shanghai",
    "iso:country":"CN",
    "name:und_x_variant":[
        "Tonggu Zhen"
    ],
    "name:zho_x_preferred":[
        "\u94dc\u9f13"
    ],
    "name:zho_x_variant":[
        "\u94dc\u9f13\u9547"
    ],
    "wof:name":"Tonggu",
    "wof:placetype":"locality"
},
  "geometry": {"coordinates":[109.7311,30.93409],"type":"Point"}
}