{
  "type": "Feature",
  "properties": {
    "gn:admin1_code":"14.0",
    "gn:asciiname":"Gougoutong",
    "gn:country_code":"CN",
    "gn:dem":3914,
    "gn:feature_class":"P",
    "gn:feature_code":"PPL",
    "gn:name":"Gougoutong",
    "gn:population":0,
    "gn:timezone":"Asia/Urumqi",
    "iso:country":"CN",
    "name:zho_x_preferred":[
        "\u6c9f\u6c9f\u540c"
    ],
    "wof:name":"Gougoutong",
    "wof:placetype":"locality"
},
  "geometry": {"coordinates":[98.00712,29.27162],"type":"Point"}
}