{
  "type": "Feature",
  "properties": {
    "gn:admin1_code":"24.0",
    "gn:asciiname":"Shangyeyu",
    "gn:country_code":"CN",
    "gn:dem":992,
    "gn:feature_class":"P",
    "gn:feature_code":"PPL",
    "gn:name":"Shangyeyu",
    "gn:population":0,
    "gn:timezone":"Asia/Shanghai",
    "iso:country":"CN",
    "name:zho_x_preferred":[
        "\u4e0a\u51b6\u5cea"
    ],
    "wof:name":"Shangyeyu",
    "wof:placetype":"locality"
},
  "geometry": {"coordinates":[112.43042,37.79277],"type":"Point"}
}