{
  "type": "Feature",
  "properties": {
    "gn:admin1_code":"19.0",
    "gn:asciiname":"Dabai Miaozicun",
    "gn:country_code":"CN",
    "gn:dem":86,
    "gn:feature_class":"P",
    "gn:feature_code":"PPL",
    "gn:name":"Dabai Miaozicun",
    "gn:population":0,
    "gn:timezone":"Asia/Shanghai",
    "iso:country":"CN",
    "name:und_x_variant":[
        "Dabaimiaozicun",
        "Dabai Miaozicun"
    ],
    "name:zho_x_preferred":[
        "\u5927\u767d\u5e99\u5b50\u6751"
    ],
    "wof:name":"Dabai Miaozicun",
    "wof:placetype":"locality"
},
  "geometry": {"coordinates":[124.06431000000001,42.45584],"type":"Point"}
}