{
  "type": "Feature",
  "properties": {
    "gn:admin1_code":"8.0",
    "gn:asciiname":"Xincun Ershi'erhao",
    "gn:country_code":"CN",
    "gn:dem":167,
    "gn:feature_class":"P",
    "gn:feature_code":"PPLF",
    "gn:name":"Xincun Ershi\u2019erhao",
    "gn:population":0,
    "gn:timezone":"Asia/Shanghai",
    "iso:country":"CN",
    "name:und_x_variant":[
        "Xincun Ershi\u2019erhao"
    ],
    "name:zho_x_preferred":[
        "\u65b0\u6751\u4e8c\u5341\u4e8c\u53f7"
    ],
    "wof:name":"Xincun Ershi'erhao",
    "wof:placetype":"locality"
},
  "geometry": {"coordinates":[125.18172,47.4172],"type":"Point"}
}