{
  "type": "Feature",
  "properties": {
    "gn:admin1_code":"16.0",
    "gn:asciiname":"Baidi",
    "gn:country_code":"CN",
    "gn:dem":163,
    "gn:feature_class":"P",
    "gn:feature_code":"PPL",
    "gn:name":"Baidi",
    "gn:population":0,
    "gn:timezone":"Asia/Shanghai",
    "iso:country":"CN",
    "name:ceb_x_preferred":[
        "Baidi"
    ],
    "name:deu_x_preferred":[
        "Baidi"
    ],
    "name:swe_x_preferred":[
        "Baidi"
    ],
    "name:zho_x_preferred":[
        "\u767e\u5730"
    ],
    "wof:name":"Baidi",
    "wof:placetype":"locality"
},
  "geometry": {"coordinates":[108.084,24.0135],"type":"Point"}
}