{
  "type": "Feature",
  "properties": {
    "gn:admin1_code":"3.0",
    "gn:asciiname":"Kengli",
    "gn:country_code":"CN",
    "gn:dem":86,
    "gn:feature_class":"P",
    "gn:feature_code":"PPL",
    "gn:name":"Kengli",
    "gn:population":0,
    "gn:timezone":"Asia/Shanghai",
    "iso:country":"CN",
    "name:und_x_variant":[
        "\u5751\u91cc"
    ],
    "wof:name":"Kengli",
    "wof:placetype":"locality"
},
  "geometry": {"coordinates":[115.08432000000001,26.96022],"type":"Point"}
}