{
  "type": "Feature",
  "properties": {
    "gn:admin1_code":"29.0",
    "gn:asciiname":"Lajika",
    "gn:country_code":"CN",
    "gn:dem":2061,
    "gn:feature_class":"P",
    "gn:feature_code":"PPL",
    "gn:name":"Lajika",
    "gn:population":0,
    "gn:timezone":"Asia/Shanghai",
    "iso:country":"CN",
    "name:zho_x_preferred":[
        "\u814a\u9e21\u5361"
    ],
    "wof:name":"Lajika",
    "wof:placetype":"locality"
},
  "geometry": {"coordinates":[102.788,25.6688],"type":"Point"}
}