{
  "type": "Feature",
  "properties": {
    "gn:admin1_code":"29.0",
    "gn:asciiname":"Niubudai",
    "gn:country_code":"CN",
    "gn:dem":1424,
    "gn:feature_class":"P",
    "gn:feature_code":"PPL",
    "gn:name":"Niubudai",
    "gn:population":0,
    "gn:timezone":"Asia/Shanghai",
    "iso:country":"CN",
    "name:zho_x_preferred":[
        "\u725b\u8865\u6b79"
    ],
    "wof:name":"Niubudai",
    "wof:placetype":"locality"
},
  "geometry": {"coordinates":[104.489,24.9782],"type":"Point"}
}