{
  "type": "Feature",
  "properties": {
    "gn:admin1_code":"05",
    "gn:asciiname":"Dayanmuzigou",
    "gn:country_code":"CN",
    "gn:dem":231,
    "gn:feature_class":"P",
    "gn:feature_code":"PPL",
    "gn:name":"Dayanmuzigou",
    "gn:population":0,
    "gn:timezone":"Asia/Shanghai",
    "iso:country":"CN",
    "name:und_x_variant":[
        "\u5927\u773c\u76ee\u5b50\u6c9f",
        "Ta-kao-i-mu-tzu"
    ],
    "wof:name":"Dayanmuzigou",
    "wof:placetype":"locality"
},
  "geometry": {"coordinates":[125.91722,40.94833],"type":"Point"}
}