{
  "type": "Feature",
  "properties": {
    "gn:admin1_code":"16.0",
    "gn:asciiname":"Fu'er",
    "gn:country_code":"CN",
    "gn:dem":152,
    "gn:feature_class":"P",
    "gn:feature_code":"PPL",
    "gn:name":"Fu\u2019er",
    "gn:population":0,
    "gn:timezone":"Asia/Shanghai",
    "iso:country":"CN",
    "name:und_x_variant":[
        "Fu\u2019er"
    ],
    "name:zho_x_preferred":[
        "\u798f\u8033"
    ],
    "wof:name":"Fu'er",
    "wof:placetype":"locality"
},
  "geometry": {"coordinates":[109.506,24.6141],"type":"Point"}
}