{
  "type": "Feature",
  "properties": {
    "gn:admin1_code":"29",
    "gn:asciiname":"Xiaojie",
    "gn:country_code":"CN",
    "gn:dem":1882,
    "gn:feature_class":"P",
    "gn:feature_code":"PPLA4",
    "gn:name":"Xiaojie",
    "gn:population":0,
    "gn:timezone":"Asia/Shanghai",
    "iso:country":"CN",
    "name:und_x_variant":[
        "Xiaojie Xiang",
        "\u5c0f\u8857\u4e61",
        "Xiaojie"
    ],
    "name:zho_x_preferred":[
        "\u5c0f\u8857"
    ],
    "wof:name":"Xiaojie",
    "wof:placetype":"locality"
},
  "geometry": {"coordinates":[102.13505000000001,24.86456],"type":"Point"}
}