{
  "type": "Feature",
  "properties": {
    "gn:admin1_code":"5.0",
    "gn:asciiname":"Fujugongcun",
    "gn:country_code":"CN",
    "gn:dem":211,
    "gn:feature_class":"P",
    "gn:feature_code":"PPL",
    "gn:name":"Fujugongcun",
    "gn:population":0,
    "gn:timezone":"Asia/Shanghai",
    "iso:country":"CN",
    "name:zho_x_preferred":[
        "\u798f\u5de8\u516c\u6751"
    ],
    "wof:name":"Fujugongcun",
    "wof:placetype":"locality"
},
  "geometry": {"coordinates":[124.4603,43.99411],"type":"Point"}
}