{
  "type": "Feature",
  "properties": {
    "gn:admin1_code":"15.0",
    "gn:asciiname":"Bajia Wopu",
    "gn:country_code":"CN",
    "gn:dem":2559,
    "gn:feature_class":"P",
    "gn:feature_code":"PPL",
    "gn:name":"Bajia Wopu",
    "gn:population":0,
    "gn:timezone":"Asia/Shanghai",
    "iso:country":"CN",
    "name:zho_x_preferred":[
        "\u5df4\u5bb6\u7a9d\u94fa"
    ],
    "wof:name":"Bajia Wopu",
    "wof:placetype":"locality"
},
  "geometry": {"coordinates":[102.639,37.4498],"type":"Point"}
}