{
  "type": "Feature",
  "properties": {
    "gn:admin1_code":"9",
    "gn:asciiname":"Houzhangzhai",
    "gn:country_code":"CN",
    "gn:dem":59,
    "gn:feature_class":"P",
    "gn:feature_code":"PPL",
    "gn:name":"Houzhangzhai",
    "gn:population":0,
    "gn:timezone":"Asia/Shanghai",
    "iso:country":"CN",
    "name:zho_x_preferred":[
        "\u540e\u5f20\u5be8"
    ],
    "wof:name":"Houzhangzhai",
    "wof:placetype":"locality"
},
  "geometry": {"coordinates":[116.096,34.5832],"type":"Point"}
}