{
  "type": "Feature",
  "properties": {
    "gn:admin1_code":"32.0",
    "gn:asciiname":"Shiyanbian",
    "gn:country_code":"CN",
    "gn:dem":495,
    "gn:feature_class":"P",
    "gn:feature_code":"PPL",
    "gn:name":"Shiyanbian",
    "gn:population":0,
    "gn:timezone":"Asia/Shanghai",
    "iso:country":"CN",
    "name:zho_x_preferred":[
        "\u77f3\u5ca9\u8fb9"
    ],
    "wof:name":"Shiyanbian",
    "wof:placetype":"locality"
},
  "geometry": {"coordinates":[104.80768999999999,31.52007],"type":"Point"}
}