{
  "type": "Feature",
  "properties": {
    "gn:admin1_code":"30.0",
    "gn:asciiname":"Liuliluo",
    "gn:country_code":"CN",
    "gn:dem":7,
    "gn:feature_class":"P",
    "gn:feature_code":"PPL",
    "gn:name":"Liuliluo",
    "gn:population":0,
    "gn:timezone":"Asia/Shanghai",
    "iso:country":"CN",
    "name:zho_x_preferred":[
        "\u5218\u674e\u7f57"
    ],
    "wof:name":"Liuliluo",
    "wof:placetype":"locality"
},
  "geometry": {"coordinates":[112.77179,21.96065],"type":"Point"}
}