{
  "type": "Feature",
  "properties": {
    "gn:admin1_code":"9.0",
    "gn:asciiname":"Sandaogang",
    "gn:country_code":"CN",
    "gn:dem":983,
    "gn:feature_class":"P",
    "gn:feature_code":"PPL",
    "gn:name":"Sandaogang",
    "gn:population":0,
    "gn:timezone":"Asia/Shanghai",
    "iso:country":"CN",
    "name:und_x_variant":[
        "\u4e09\u9053\u5c97",
        "Sandaogang"
    ],
    "wof:name":"Sandaogang",
    "wof:placetype":"locality"
},
  "geometry": {"coordinates":[112.2659,33.82157],"type":"Point"}
}