{
  "type": "Feature",
  "properties": {
    "gn:admin1_code":"19.0",
    "gn:asciiname":"Tai'ancun",
    "gn:country_code":"CN",
    "gn:dem":11,
    "gn:feature_class":"P",
    "gn:feature_code":"PPL",
    "gn:name":"Tai\u2019ancun",
    "gn:population":0,
    "gn:timezone":"Asia/Shanghai",
    "iso:country":"CN",
    "name:und_x_variant":[
        "Tai\u2019ancun"
    ],
    "name:zho_x_preferred":[
        "\u592a\u5b89\u6751"
    ],
    "wof:name":"Tai'ancun",
    "wof:placetype":"locality"
},
  "geometry": {"coordinates":[124.11505,39.93612],"type":"Point"}
}