{
  "type": "Feature",
  "properties": {
    "gn:admin1_code":"26.0",
    "gn:asciiname":"Shangdonggou",
    "gn:country_code":"CN",
    "gn:dem":1411,
    "gn:feature_class":"P",
    "gn:feature_code":"PPL",
    "gn:name":"Shangdonggou",
    "gn:population":0,
    "gn:timezone":"Asia/Shanghai",
    "iso:country":"CN",
    "name:zho_x_preferred":[
        "\u4e0a\u4e1c\u6c9f"
    ],
    "wof:name":"Shangdonggou",
    "wof:placetype":"locality"
},
  "geometry": {"coordinates":[109.71913000000001,35.73096],"type":"Point"}
}