{
  "type": "Feature",
  "properties": {
    "gn:admin1_code":"18.0",
    "gn:asciiname":"Qibai",
    "gn:country_code":"CN",
    "gn:dem":1455,
    "gn:feature_class":"P",
    "gn:feature_code":"PPL",
    "gn:name":"Qibai",
    "gn:population":0,
    "gn:timezone":"Asia/Shanghai",
    "iso:country":"CN",
    "name:zho_x_preferred":[
        "\u542f\u767d"
    ],
    "wof:name":"Qibai",
    "wof:placetype":"locality"
},
  "geometry": {"coordinates":[105.40900000000001,25.5622],"type":"Point"}
}