{
  "type": "Feature",
  "properties": {
    "gn:admin1_code":"29.0",
    "gn:asciiname":"Zuojiazhai",
    "gn:country_code":"CN",
    "gn:dem":1992,
    "gn:feature_class":"P",
    "gn:feature_code":"PPL",
    "gn:name":"Zuojiazhai",
    "gn:population":0,
    "gn:timezone":"Asia/Shanghai",
    "iso:country":"CN",
    "name:zho_x_preferred":[
        "\u4f50\u5bb6\u5be8"
    ],
    "wof:name":"Zuojiazhai",
    "wof:placetype":"locality"
},
  "geometry": {"coordinates":[97.7559,24.8973],"type":"Point"}
}