{
  "type": "Feature",
  "properties": {
    "gn:admin1_code":"15.0",
    "gn:asciiname":"Xiayikeshu",
    "gn:country_code":"CN",
    "gn:dem":1986,
    "gn:feature_class":"P",
    "gn:feature_code":"PPL",
    "gn:name":"Xiayikeshu",
    "gn:population":0,
    "gn:timezone":"Asia/Shanghai",
    "iso:country":"CN",
    "name:zho_x_preferred":[
        "\u4e0b\u4e00\u68f5\u6811"
    ],
    "wof:name":"Xiayikeshu",
    "wof:placetype":"locality"
},
  "geometry": {"coordinates":[100.858,39.1255],"type":"Point"}
}