{
  "type": "Feature",
  "properties": {
    "gn:admin1_code":"11",
    "gn:asciiname":"Zhengdongtian",
    "gn:country_code":"CN",
    "gn:dem":595,
    "gn:feature_class":"P",
    "gn:feature_code":"PPL",
    "gn:name":"Zhengdongtian",
    "gn:population":0,
    "gn:timezone":"Asia/Shanghai",
    "iso:country":"CN",
    "name:zho_x_preferred":[
        "\u6b63\u6d1e\u7530"
    ],
    "wof:name":"Zhengdongtian",
    "wof:placetype":"locality"
},
  "geometry": {"coordinates":[111.83399,25.2632],"type":"Point"}
}