{
  "type": "Feature",
  "properties": {
    "gn:admin1_code":"25",
    "gn:asciiname":"Liujia Huanglongwan",
    "gn:country_code":"CN",
    "gn:dem":8,
    "gn:feature_class":"P",
    "gn:feature_code":"PPL",
    "gn:name":"Liujia Huanglongwan",
    "gn:population":0,
    "gn:timezone":"Asia/Shanghai",
    "iso:country":"CN",
    "name:zho_x_preferred":[
        "\u5218\u5bb6\u9ec4\u9f99\u6e7e"
    ],
    "wof:name":"Liujia Huanglongwan",
    "wof:placetype":"locality"
},
  "geometry": {"coordinates":[117.65000000000001,37.9847],"type":"Point"}
}