{
  "type": "Feature",
  "properties": {
    "gn:admin1_code":"16.0",
    "gn:asciiname":"Shijing'ao",
    "gn:country_code":"CN",
    "gn:dem":121,
    "gn:feature_class":"P",
    "gn:feature_code":"PPL",
    "gn:name":"Shijing\u2019ao",
    "gn:population":0,
    "gn:timezone":"Asia/Shanghai",
    "iso:country":"CN",
    "name:und_x_variant":[
        "Shijing\u2019ao"
    ],
    "name:zho_x_preferred":[
        "\u77f3\u666f\u5773"
    ],
    "wof:name":"Shijing'ao",
    "wof:placetype":"locality"
},
  "geometry": {"coordinates":[110.342,23.2759],"type":"Point"}
}