{
  "type": "Feature",
  "properties": {
    "gn:admin1_code":"12.0",
    "gn:asciiname":"Henglinzi",
    "gn:country_code":"CN",
    "gn:dem":710,
    "gn:feature_class":"P",
    "gn:feature_code":"PPL",
    "gn:name":"Henglinzi",
    "gn:population":0,
    "gn:timezone":"Asia/Shanghai",
    "iso:country":"CN",
    "name:zho_x_preferred":[
        "Henglinzi"
    ],
    "name:zho_x_variant":[
        "\u6a2a\u6797\u5b50"
    ],
    "wof:name":"Henglinzi",
    "wof:placetype":"locality"
},
  "geometry": {"coordinates":[111.12137,30.32092],"type":"Point"}
}