{
  "type": "Feature",
  "properties": {
    "gn:admin1_code":"19.0",
    "gn:asciiname":"Shanzuizi",
    "gn:country_code":"CN",
    "gn:dem":104,
    "gn:feature_class":"P",
    "gn:feature_code":"PPL",
    "gn:name":"Shanzuizi",
    "gn:population":0,
    "gn:timezone":"Asia/Shanghai",
    "iso:country":"CN",
    "name:zho_x_preferred":[
        "\u5c71\u5480\u5b50"
    ],
    "wof:name":"Shanzuizi",
    "wof:placetype":"locality"
},
  "geometry": {"coordinates":[123.663,43.0825],"type":"Point"}
}