{
  "type": "Feature",
  "properties": {
    "gn:admin1_code":"12.0",
    "gn:asciiname":"Chenliuwan",
    "gn:country_code":"CN",
    "gn:dem":24,
    "gn:feature_class":"P",
    "gn:feature_code":"PPL",
    "gn:name":"Chenliuwan",
    "gn:population":0,
    "gn:timezone":"Asia/Shanghai",
    "iso:country":"CN",
    "name:und_x_variant":[
        "\u9648\u5218\u5846"
    ],
    "wof:name":"Chenliuwan",
    "wof:placetype":"locality"
},
  "geometry": {"coordinates":[114.38113,30.83662],"type":"Point"}
}