{
  "type": "Feature",
  "properties": {
    "gn:admin1_code":"19.0",
    "gn:asciiname":"Banjiegou",
    "gn:country_code":"CN",
    "gn:dem":645,
    "gn:feature_class":"P",
    "gn:feature_code":"PPL",
    "gn:name":"Banjiegou",
    "gn:population":0,
    "gn:timezone":"Asia/Shanghai",
    "iso:country":"CN",
    "name:zho_x_preferred":[
        "\u534a\u622a\u6c9f"
    ],
    "wof:name":"Banjiegou",
    "wof:placetype":"locality"
},
  "geometry": {"coordinates":[119.49363999999998,41.97487],"type":"Point"}
}