{
  "type": "Feature",
  "properties": {
    "gn:admin1_code":"32.0",
    "gn:asciiname":"Bazhe",
    "gn:country_code":"CN",
    "gn:dem":2236,
    "gn:feature_class":"P",
    "gn:feature_code":"PPL",
    "gn:name":"Bazhe",
    "gn:population":0,
    "gn:timezone":"Asia/Shanghai",
    "iso:country":"CN",
    "name:zho_x_preferred":[
        "\u5df4\u6298"
    ],
    "wof:name":"Bazhe",
    "wof:placetype":"locality"
},
  "geometry": {"coordinates":[101.81522,27.92385],"type":"Point"}
}