{
  "type": "Feature",
  "properties": {
    "gn:admin1_code":"5.0",
    "gn:asciiname":"Wenjia Weizi",
    "gn:country_code":"CN",
    "gn:dem":173,
    "gn:feature_class":"P",
    "gn:feature_code":"PPL",
    "gn:name":"Wenjia Weizi",
    "gn:population":0,
    "gn:timezone":"Asia/Shanghai",
    "iso:country":"CN",
    "name:zho_x_preferred":[
        "\u6e29\u5bb6\u5d34\u5b50"
    ],
    "wof:name":"Wenjia Weizi",
    "wof:placetype":"locality"
},
  "geometry": {"coordinates":[125.19441999999999,44.33048],"type":"Point"}
}