{
  "type": "Feature",
  "properties": {
    "gn:admin1_code":"19.0",
    "gn:asciiname":"Anjiapu",
    "gn:country_code":"CN",
    "gn:dem":4,
    "gn:feature_class":"P",
    "gn:feature_code":"PPL",
    "gn:name":"Anjiapu",
    "gn:population":0,
    "gn:timezone":"Asia/Shanghai",
    "iso:country":"CN",
    "name:und_x_variant":[
        "\u5b89\u5bb6\u94fa"
    ],
    "name:zho_x_preferred":[
        "\u5b89\u5bb6\u94fa"
    ],
    "wof:name":"Anjiapu",
    "wof:placetype":"locality"
},
  "geometry": {"coordinates":[122.24301,41.00809],"type":"Point"}
}