{
  "type": "Feature",
  "properties": {
    "gn:admin1_code":"11.0",
    "gn:asciiname":"Beiyantang",
    "gn:country_code":"CN",
    "gn:dem":72,
    "gn:feature_class":"P",
    "gn:feature_code":"PPL",
    "gn:name":"Beiyantang",
    "gn:population":0,
    "gn:timezone":"Asia/Shanghai",
    "iso:country":"CN",
    "name:zho_x_preferred":[
        "\u5317\u5ef6\u5858"
    ],
    "wof:name":"Beiyantang",
    "wof:placetype":"locality"
},
  "geometry": {"coordinates":[113.19244999999999,28.12088],"type":"Point"}
}