{
  "type": "Feature",
  "properties": {
    "gn:admin1_code":"32.0",
    "gn:asciiname":"Wafangcun",
    "gn:country_code":"CN",
    "gn:dem":2554,
    "gn:feature_class":"P",
    "gn:feature_code":"PPL",
    "gn:name":"Wafangcun",
    "gn:population":0,
    "gn:timezone":"Asia/Shanghai",
    "iso:country":"CN",
    "name:zho_x_preferred":[
        "\u74e6\u623f\u6751"
    ],
    "wof:name":"Wafangcun",
    "wof:placetype":"locality"
},
  "geometry": {"coordinates":[102.78894,26.53128],"type":"Point"}
}