{
  "type": "Feature",
  "properties": {
    "gn:admin1_code":"8.0",
    "gn:asciiname":"Yinggeji",
    "gn:country_code":"CN",
    "gn:dem":128,
    "gn:feature_class":"P",
    "gn:feature_code":"PPL",
    "gn:name":"Yinggeji",
    "gn:population":0,
    "gn:timezone":"Asia/Shanghai",
    "iso:country":"CN",
    "name:zho_x_preferred":[
        "\u82f1\u683c\u5409"
    ],
    "wof:name":"Yinggeji",
    "wof:placetype":"locality"
},
  "geometry": {"coordinates":[124.53654,45.84003],"type":"Point"}
}