{
  "type": "Feature",
  "properties": {
    "gn:admin1_code":"1.0",
    "gn:asciiname":"Wangtangcun",
    "gn:country_code":"CN",
    "gn:dem":55,
    "gn:feature_class":"P",
    "gn:feature_code":"PPL",
    "gn:name":"Wangtangcun",
    "gn:population":0,
    "gn:timezone":"Asia/Shanghai",
    "iso:country":"CN",
    "name:zho_x_preferred":[
        "\u6c6a\u5858\u6751"
    ],
    "wof:name":"Wangtangcun",
    "wof:placetype":"locality"
},
  "geometry": {"coordinates":[116.06247999999999,32.2718],"type":"Point"}
}