{
  "type": "Feature",
  "properties": {
    "gn:admin1_code":"11.0",
    "gn:asciiname":"Liziping",
    "gn:country_code":"CN",
    "gn:dem":501,
    "gn:feature_class":"P",
    "gn:feature_code":"PPL",
    "gn:name":"Liziping",
    "gn:population":0,
    "gn:timezone":"Asia/Shanghai",
    "iso:country":"CN",
    "name:zho_x_preferred":[
        "\u68a8\u5b50\u576a"
    ],
    "wof:name":"Liziping",
    "wof:placetype":"locality"
},
  "geometry": {"coordinates":[110.71666,26.32772000000001],"type":"Point"}
}