{
  "type": "Feature",
  "properties": {
    "gn:admin1_code":"29.0",
    "gn:asciiname":"Shimen",
    "gn:country_code":"CN",
    "gn:dem":2097,
    "gn:feature_class":"P",
    "gn:feature_code":"PPLA3",
    "gn:name":"Shimen",
    "gn:population":0,
    "gn:timezone":"Asia/Shanghai",
    "iso:country":"CN",
    "name:und_x_variant":[
        "Yunlong",
        "Shimenzhen",
        "Y\u00fcn-lung-hsien",
        "Shih-men-chen",
        "Y\u00fcn-lung",
        "Shih-men-ching",
        "Shimen"
    ],
    "name:zho_x_preferred":[
        "\u77f3\u95e8"
    ],
    "name:zho_x_variant":[
        "Y\u00fcn-lung-hsien",
        "Y\u00fcn-lung"
    ],
    "wof:name":"Shimen",
    "wof:placetype":"locality"
},
  "geometry": {"coordinates":[99.42936,25.89479],"type":"Point"}
}