{
  "type": "Feature",
  "properties": {
    "gn:admin1_code":"12.0",
    "gn:asciiname":"Yanjiagang",
    "gn:country_code":"CN",
    "gn:dem":178,
    "gn:feature_class":"P",
    "gn:feature_code":"PPL",
    "gn:name":"Yanjiagang",
    "gn:population":0,
    "gn:timezone":"Asia/Shanghai",
    "iso:country":"CN",
    "name:zho_x_preferred":[
        "\u9122\u5bb6\u5c97"
    ],
    "wof:name":"Yanjiagang",
    "wof:placetype":"locality"
},
  "geometry": {"coordinates":[111.90907,31.1446],"type":"Point"}
}