{
  "type": "Feature",
  "properties": {
    "gn:admin1_code":"25.0",
    "gn:asciiname":"Jinkoucun",
    "gn:country_code":"CN",
    "gn:dem":5,
    "gn:feature_class":"P",
    "gn:feature_code":"PPL",
    "gn:name":"Jinkoucun",
    "gn:population":0,
    "gn:timezone":"Asia/Shanghai",
    "iso:country":"CN",
    "name:zho_x_preferred":[
        "\u91d1\u53e3\u6751"
    ],
    "wof:name":"Jinkoucun",
    "wof:placetype":"locality"
},
  "geometry": {"coordinates":[120.75588,36.60131],"type":"Point"}
}