{
  "type": "Feature",
  "properties": {
    "gn:admin1_code":"15.0",
    "gn:asciiname":"Huangjiazui",
    "gn:country_code":"CN",
    "gn:dem":1967,
    "gn:feature_class":"P",
    "gn:feature_code":"PPL",
    "gn:name":"Huangjiazui",
    "gn:population":0,
    "gn:timezone":"Asia/Shanghai",
    "iso:country":"CN",
    "name:zho_x_preferred":[
        "\u9ec4\u5bb6\u5634"
    ],
    "wof:name":"Huangjiazui",
    "wof:placetype":"locality"
},
  "geometry": {"coordinates":[104.712,35.6769],"type":"Point"}
}