{
  "type": "Feature",
  "properties": {
    "gn:admin1_code":"32.0",
    "gn:asciiname":"Nianzi",
    "gn:country_code":"CN",
    "gn:dem":2011,
    "gn:feature_class":"P",
    "gn:feature_code":"PPL",
    "gn:name":"Nianzi",
    "gn:population":0,
    "gn:timezone":"Asia/Shanghai",
    "iso:country":"CN",
    "name:zho_x_preferred":[
        "\u78be\u5b50"
    ],
    "wof:name":"Nianzi",
    "wof:placetype":"locality"
},
  "geometry": {"coordinates":[102.1683,28.73842],"type":"Point"}
}