{
  "type": "Feature",
  "properties": {
    "gn:admin1_code":"32.0",
    "gn:asciiname":"Hujiaxiang",
    "gn:country_code":"CN",
    "gn:dem":400,
    "gn:feature_class":"P",
    "gn:feature_code":"PPL",
    "gn:name":"Hujiaxiang",
    "gn:population":0,
    "gn:timezone":"Asia/Shanghai",
    "iso:country":"CN",
    "name:zho_x_preferred":[
        "\u80e1\u5bb6\u5df7"
    ],
    "wof:name":"Hujiaxiang",
    "wof:placetype":"locality"
},
  "geometry": {"coordinates":[104.31480999999999,29.36714000000001],"type":"Point"}
}