{
  "type": "Feature",
  "properties": {
    "gn:admin1_code":"7.0",
    "gn:asciiname":"Liaoyuan",
    "gn:country_code":"CN",
    "gn:dem":102,
    "gn:feature_class":"P",
    "gn:feature_code":"PPL",
    "gn:name":"Liaoyuan",
    "gn:population":0,
    "gn:timezone":"Asia/Shanghai",
    "iso:country":"CN",
    "name:ara_x_preferred":[
        "\u0644\u064a\u0627\u0648\u064a\u0648\u0627\u0646"
    ],
    "name:ast_x_preferred":[
        "Liaoyu\u00e1n"
    ],
    "name:bel_x_preferred":[
        "\u041b\u044f\u0430\u044e\u0430\u043d\u044c"
    ],
    "name:cdo_x_preferred":[
        "Li\u00e8u-ngu\u00f2ng"
    ],
    "name:ces_x_preferred":[
        "Liao-j\u00fcan"
    ],
    "name:dan_x_preferred":[
        "Liaoyuan"
    ],
    "name:deu_x_preferred":[
        "Liaoyuan"
    ],
    "name:eus_x_preferred":[
        "Liaoyuan"
    ],
    "name:fas_x_preferred":[
        "\u0644\u06cc\u0627\u0648\u06cc\u0648\u0627\u0646"
    ],
    "name:fin_x_preferred":[
        "Liaoyuan"
    ],
    "name:fra_x_preferred":[
        "Liaoyuan"
    ],
    "name:ita_x_preferred":[
        "Liaoyuan"
    ],
    "name:jpn_x_preferred":[
        "\u907c\u6e90\u5e02"
    ],
    "name:kik_x_preferred":[
        "Liaoyuan"
    ],
    "name:kor_x_preferred":[
        "\ub7b4\uc624\uc704\uc548\uc2dc"
    ],
    "name:lit_x_preferred":[
        "Liaojuanas"
    ],
    "name:mlg_x_preferred":[
        "Liaoyuan"
    ],
    "name:nld_x_preferred":[
        "Liaoyuan"
    ],
    "name:nno_x_preferred":[
        "Liaoyuan"
    ],
    "name:nor_x_preferred":[
        "Liaoyuan"
    ],
    "name:pol_x_preferred":[
        "Liaoyuan"
    ],
    "name:rus_x_preferred":[
        "\u041b\u044f\u043e\u044e\u0430\u043d\u044c"
    ],
    "name:spa_x_preferred":[
        "Liaoyu\u00e1n"
    ],
    "name:srp_x_preferred":[
        "\u0409\u0430\u043e\u0458\u0443\u0435\u043d"
    ],
    "name:swe_x_preferred":[
        "Liaoyuan"
    ],
    "name:tur_x_preferred":[
        "Liaoyuan"
    ],
    "name:urd_x_preferred":[
        "\u0644\u06cc\u0627\u0648\u06cc\u0648\u0627\u0646"
    ],
    "name:vep_x_preferred":[
        "L\u00e4ojuan'"
    ],
    "name:vie_x_preferred":[
        "Li\u00eau Nguy\u00ean"
    ],
    "name:war_x_preferred":[
        "Liaoyuan"
    ],
    "name:wuu_x_preferred":[
        "\u8fbd\u6e90\u5e02"
    ],
    "name:zho_x_preferred":[
        "\u71ce\u539f"
    ],
    "name:zho_x_variant":[
        "\u8fbd\u6e90\u5e02"
    ],
    "wof:name":"Liaoyuan",
    "wof:placetype":"locality"
},
  "geometry": {"coordinates":[118.07304999999999,25.02278],"type":"Point"}
}