{
  "type": "Feature",
  "properties": {
    "gn:admin1_code":"7.0",
    "gn:asciiname":"Liaoyuan",
    "gn:country_code":"CN",
    "gn:dem":102,
    "gn:feature_class":"P",
    "gn:feature_code":"PPL",
    "gn:name":"Liaoyuan",
    "gn:population":0,
    "gn:timezone":"Asia/Shanghai",
    "iso:country":"CN",
    "name:zho_x_preferred":[
        "\u71ce\u539f"
    ],
    "wof:name":"Liaoyuan",
    "wof:placetype":"locality"
},
  "geometry": {"coordinates":[118.07304999999999,25.02278],"type":"Point"}
}