{
  "type": "Feature",
  "properties": {
    "gn:admin1_code":"32.0",
    "gn:asciiname":"Huangjueyan",
    "gn:country_code":"CN",
    "gn:dem":368,
    "gn:feature_class":"P",
    "gn:feature_code":"PPL",
    "gn:name":"Huangjueyan",
    "gn:population":0,
    "gn:timezone":"Asia/Shanghai",
    "iso:country":"CN",
    "name:zho_x_preferred":[
        "\u9ec4\u6877\u5ca9"
    ],
    "wof:name":"Huangjueyan",
    "wof:placetype":"locality"
},
  "geometry": {"coordinates":[104.35491,28.90958],"type":"Point"}
}