{
  "type": "Feature",
  "properties": {
    "gn:admin1_code":"16",
    "gn:asciiname":"Hongfuling",
    "gn:country_code":"CN",
    "gn:dem":627,
    "gn:feature_class":"P",
    "gn:feature_code":"PPL",
    "gn:name":"Hongfuling",
    "gn:population":0,
    "gn:timezone":"Asia/Shanghai",
    "iso:country":"CN",
    "name:zho_x_preferred":[
        "\u6d2a\u798f\u5cad"
    ],
    "wof:name":"Hongfuling",
    "wof:placetype":"locality"
},
  "geometry": {"coordinates":[110.34699999999999,25.9263],"type":"Point"}
}