{
  "type": "Feature",
  "properties": {
    "gn:admin1_code":"14",
    "gn:asciiname":"Danaqiong",
    "gn:country_code":"CN",
    "gn:dem":3717,
    "gn:feature_class":"P",
    "gn:feature_code":"PPL",
    "gn:name":"Danaqiong",
    "gn:population":0,
    "gn:timezone":"Asia/Urumqi",
    "iso:country":"CN",
    "name:zho_x_preferred":[
        "\u6253\u54ea\u7a77"
    ],
    "wof:name":"Danaqiong",
    "wof:placetype":"locality"
},
  "geometry": {"coordinates":[88.8844,27.3945],"type":"Point"}
}