{
  "type": "Feature",
  "properties": {
    "gn:admin1_code":"2.0",
    "gn:asciiname":"Furong",
    "gn:country_code":"CN",
    "gn:dem":53,
    "gn:feature_class":"P",
    "gn:feature_code":"PPL",
    "gn:name":"Furong",
    "gn:population":0,
    "gn:timezone":"Asia/Shanghai",
    "iso:country":"CN",
    "name:ceb_x_preferred":[
        "Furong"
    ],
    "name:deu_x_preferred":[
        "Furong"
    ],
    "name:swe_x_preferred":[
        "Furong"
    ],
    "name:zho_x_preferred":[
        "\u8299\u84c9"
    ],
    "wof:name":"Furong",
    "wof:placetype":"locality"
},
  "geometry": {"coordinates":[121.23654000000001,28.17281],"type":"Point"}
}