{
  "type": "Feature",
  "properties": {
    "gn:admin1_code":"24",
    "gn:asciiname":"Qingshunbu",
    "gn:country_code":"CN",
    "gn:dem":1056,
    "gn:feature_class":"P",
    "gn:feature_code":"PPL",
    "gn:name":"Qingshunbu",
    "gn:population":0,
    "gn:timezone":"Asia/Shanghai",
    "iso:country":"CN",
    "name:und_x_variant":[
        "Ch\u2019ing-shun-p\u2019u",
        "Ch\u2019ing-shun-pao",
        "Qingshunbu"
    ],
    "name:zho_x_preferred":[
        "\u9752\u987a\u5821"
    ],
    "wof:name":"Qingshunbu",
    "wof:placetype":"locality"
},
  "geometry": {"coordinates":[113.70707,40.33081],"type":"Point"}
}