{
  "type": "Feature",
  "properties": {
    "gn:admin1_code":"16",
    "gn:asciiname":"Huangpijiangtou",
    "gn:country_code":"CN",
    "gn:dem":1000,
    "gn:feature_class":"P",
    "gn:feature_code":"PPL",
    "gn:name":"Huangpijiangtou",
    "gn:population":0,
    "gn:timezone":"Asia/Shanghai",
    "iso:country":"CN",
    "name:zho_x_preferred":[
        "\u9ec4\u76ae\u6c5f\u5934"
    ],
    "wof:name":"Huangpijiangtou",
    "wof:placetype":"locality"
},
  "geometry": {"coordinates":[110.131,25.655],"type":"Point"}
}