{
  "type": "Feature",
  "properties": {
    "gn:admin1_code":"8.0",
    "gn:asciiname":"Donghaodecun",
    "gn:country_code":"CN",
    "gn:dem":130,
    "gn:feature_class":"P",
    "gn:feature_code":"PPL",
    "gn:name":"Donghaodecun",
    "gn:population":0,
    "gn:timezone":"Asia/Shanghai",
    "iso:country":"CN",
    "name:zho_x_preferred":[
        "\u4e1c\u6d69\u5fb7\u6751"
    ],
    "wof:name":"Donghaodecun",
    "wof:placetype":"locality"
},
  "geometry": {"coordinates":[124.53296,45.72637],"type":"Point"}
}