{
  "type": "Feature",
  "properties": {
    "gn:admin1_code":"9.0",
    "gn:asciiname":"Dangzhuang",
    "gn:country_code":"CN",
    "gn:dem":202,
    "gn:feature_class":"P",
    "gn:feature_code":"PPL",
    "gn:name":"Dangzhuang",
    "gn:population":0,
    "gn:timezone":"Asia/Shanghai",
    "iso:country":"CN",
    "name:und_x_variant":[
        "\u515a\u5e84",
        "Dangzhuang"
    ],
    "wof:name":"Dangzhuang",
    "wof:placetype":"locality"
},
  "geometry": {"coordinates":[112.50712,33.31132],"type":"Point"}
}