{
  "type": "Feature",
  "properties": {
    "gn:admin1_code":"19.0",
    "gn:asciiname":"Zhantuncun",
    "gn:country_code":"CN",
    "gn:dem":6,
    "gn:feature_class":"P",
    "gn:feature_code":"PPL",
    "gn:name":"Zhantuncun",
    "gn:population":0,
    "gn:timezone":"Asia/Shanghai",
    "iso:country":"CN",
    "name:zho_x_preferred":[
        "\u8a79\u5c6f\u6751"
    ],
    "wof:name":"Zhantuncun",
    "wof:placetype":"locality"
},
  "geometry": {"coordinates":[121.617,41.24],"type":"Point"}
}