{
  "type": "Feature",
  "properties": {
    "gn:admin1_code":"24",
    "gn:asciiname":"Zhoujiazhuang",
    "gn:country_code":"CN",
    "gn:dem":1174,
    "gn:feature_class":"P",
    "gn:feature_code":"PPL",
    "gn:name":"Zhoujiazhuang",
    "gn:population":0,
    "gn:timezone":"Asia/Shanghai",
    "iso:country":"CN",
    "wof:name":"Zhoujiazhuang",
    "wof:placetype":"locality"
},
  "geometry": {"coordinates":[112.41306000000002,37.74639000000001],"type":"Point"}
}