{
  "type": "Feature",
  "properties": {
    "gn:admin1_code":"31",
    "gn:asciiname":"Xinju",
    "gn:country_code":"CN",
    "gn:dem":37,
    "gn:feature_class":"P",
    "gn:feature_code":"PPL",
    "gn:name":"Xinju",
    "gn:population":0,
    "gn:timezone":"Asia/Shanghai",
    "iso:country":"CN",
    "name:und_x_variant":[
        "\u65b0\u5c45",
        "Zhouju"
    ],
    "wof:name":"Xinju",
    "wof:placetype":"locality"
},
  "geometry": {"coordinates":[110.91916999999999,19.90111],"type":"Point"}
}