{
  "type": "Feature",
  "properties": {
    "gn:admin1_code":"1.0",
    "gn:asciiname":"Huchongcun",
    "gn:country_code":"CN",
    "gn:dem":419,
    "gn:feature_class":"P",
    "gn:feature_code":"PPL",
    "gn:name":"Huchongcun",
    "gn:population":0,
    "gn:timezone":"Asia/Shanghai",
    "iso:country":"CN",
    "name:zho_x_preferred":[
        "\u80e1\u51b2\u6751"
    ],
    "wof:name":"Huchongcun",
    "wof:placetype":"locality"
},
  "geometry": {"coordinates":[116.77227999999999,31.0031],"type":"Point"}
}