{
  "type": "Feature",
  "properties": {
    "gn:admin1_code":"16.0",
    "gn:asciiname":"Shangjuzhou",
    "gn:country_code":"CN",
    "gn:dem":207,
    "gn:feature_class":"P",
    "gn:feature_code":"PPL",
    "gn:name":"Shangjuzhou",
    "gn:population":0,
    "gn:timezone":"Asia/Shanghai",
    "iso:country":"CN",
    "name:zho_x_preferred":[
        "\u4e0a\u5c40\u5dde"
    ],
    "wof:name":"Shangjuzhou",
    "wof:placetype":"locality"
},
  "geometry": {"coordinates":[108.211,23.7045],"type":"Point"}
}