{
  "type": "Feature",
  "properties": {
    "gn:admin1_code":"22.0",
    "gn:asciiname":"Chengjiayaocun",
    "gn:country_code":"CN",
    "gn:dem":576,
    "gn:feature_class":"P",
    "gn:feature_code":"PPL",
    "gn:name":"Chengjiayaocun",
    "gn:population":0,
    "gn:timezone":"Asia/Shanghai",
    "iso:country":"CN",
    "name:zho_x_preferred":[
        "\u7a0b\u5bb6\u7a91\u6751"
    ],
    "wof:name":"Chengjiayaocun",
    "wof:placetype":"locality"
},
  "geometry": {"coordinates":[115.97893999999999,40.3753],"type":"Point"}
}