{
  "type": "Feature",
  "properties": {
    "gn:admin1_code":"9.0",
    "gn:asciiname":"Gushezhai",
    "gn:country_code":"CN",
    "gn:dem":106,
    "gn:feature_class":"P",
    "gn:feature_code":"PPL",
    "gn:name":"Gushezhai",
    "gn:population":0,
    "gn:timezone":"Asia/Shanghai",
    "iso:country":"CN",
    "name:zho_x_preferred":[
        "\u8c37\u793e\u5be8"
    ],
    "wof:name":"Gushezhai",
    "wof:placetype":"locality"
},
  "geometry": {"coordinates":[112.24203,32.72265],"type":"Point"}
}