{
  "type": "Feature",
  "properties": {
    "gn:admin1_code":"32.0",
    "gn:asciiname":"Xinkaitan",
    "gn:country_code":"CN",
    "gn:dem":551,
    "gn:feature_class":"P",
    "gn:feature_code":"PPL",
    "gn:name":"Xinkaitan",
    "gn:population":0,
    "gn:timezone":"Asia/Shanghai",
    "iso:country":"CN",
    "name:zho_x_preferred":[
        "\u65b0\u5f00\u6ee9"
    ],
    "wof:name":"Xinkaitan",
    "wof:placetype":"locality"
},
  "geometry": {"coordinates":[104.02070000000001,28.62937],"type":"Point"}
}