{
  "type": "Feature",
  "properties": {
    "gn:admin1_code":"30",
    "gn:asciiname":"Changzhi",
    "gn:country_code":"CN",
    "gn:dem":175,
    "gn:feature_class":"P",
    "gn:feature_code":"PPL",
    "gn:name":"Changzhi",
    "gn:population":0,
    "gn:timezone":"Asia/Shanghai",
    "iso:country":"CN",
    "name:ara_x_preferred":[
        "\u062a\u0634\u0627\u0646\u063a \u062a\u0634\u0649"
    ],
    "name:bul_x_preferred":[
        "\u0427\u0430\u043d\u0434\u0436\u044a"
    ],
    "name:cdo_x_preferred":[
        "Di\u00f2ng-d\u00ea"
    ],
    "name:ces_x_preferred":[
        "\u010cchang-\u010d'"
    ],
    "name:dan_x_preferred":[
        "Changzhi"
    ],
    "name:deu_x_preferred":[
        "Changzhi"
    ],
    "name:epo_x_preferred":[
        "\u0108an\u011di"
    ],
    "name:eus_x_preferred":[
        "Changzhi"
    ],
    "name:fas_x_preferred":[
        "\u0686\u0627\u0646\u06af\u062c\u06cc"
    ],
    "name:fin_x_preferred":[
        "Changzhi"
    ],
    "name:fra_x_preferred":[
        "Changzhi"
    ],
    "name:ind_x_preferred":[
        "Changzhi"
    ],
    "name:ita_x_preferred":[
        "Changzhi"
    ],
    "name:jpn_x_preferred":[
        "\u9577\u6cbb\u5e02"
    ],
    "name:kik_x_preferred":[
        "Changzhi"
    ],
    "name:kor_x_preferred":[
        "\ucc3d\uc988\uc2dc"
    ],
    "name:lit_x_preferred":[
        "\u010cangd\u017ei"
    ],
    "name:mlg_x_preferred":[
        "Changzhi"
    ],
    "name:nld_x_preferred":[
        "Changzhi"
    ],
    "name:nno_x_preferred":[
        "Changzhi"
    ],
    "name:nor_x_preferred":[
        "Changzhi"
    ],
    "name:pol_x_preferred":[
        "Changzhi"
    ],
    "name:rus_x_preferred":[
        "\u0427\u0430\u043d\u0447\u0436\u0438"
    ],
    "name:spa_x_preferred":[
        "Changzhi"
    ],
    "name:srp_x_preferred":[
        "\u0427\u0430\u043d\u0433\u045f\u0438"
    ],
    "name:swe_x_preferred":[
        "Changzhi"
    ],
    "name:tur_x_preferred":[
        "Changzhi"
    ],
    "name:urd_x_preferred":[
        "\u0686\u0627\u0646\u06af\u0698\u06cc"
    ],
    "name:vie_x_preferred":[
        "Tr\u01b0\u1eddng Tr\u1ecb"
    ],
    "name:war_x_preferred":[
        "Changzhi"
    ],
    "name:wuu_x_preferred":[
        "\u957f\u6cbb\u5e02"
    ],
    "name:zho_x_preferred":[
        "\u957f\u6cbb"
    ],
    "name:zho_x_variant":[
        "\u957f\u6cbb\u5e02"
    ],
    "wof:name":"Changzhi",
    "wof:placetype":"locality"
},
  "geometry": {"coordinates":[116.64471,24.62024],"type":"Point"}
}