{
  "type": "Feature",
  "properties": {
    "gn:admin1_code":"5.0",
    "gn:asciiname":"Zhangjiatuncun",
    "gn:country_code":"CN",
    "gn:dem":191,
    "gn:feature_class":"P",
    "gn:feature_code":"PPL",
    "gn:name":"Zhangjiatuncun",
    "gn:population":0,
    "gn:timezone":"Asia/Shanghai",
    "iso:country":"CN",
    "name:zho_x_preferred":[
        "\u5f20\u5bb6\u5c6f\u6751"
    ],
    "wof:name":"Zhangjiatuncun",
    "wof:placetype":"locality"
},
  "geometry": {"coordinates":[124.42013,43.42952],"type":"Point"}
}