{
  "type": "Feature",
  "properties": {
    "gn:admin1_code":"1.0",
    "gn:asciiname":"Lidamiaocun",
    "gn:country_code":"CN",
    "gn:dem":31,
    "gn:feature_class":"P",
    "gn:feature_code":"PPL",
    "gn:name":"Lidamiaocun",
    "gn:population":0,
    "gn:timezone":"Asia/Shanghai",
    "iso:country":"CN",
    "name:zho_x_preferred":[
        "\u674e\u5927\u5e99\u6751"
    ],
    "wof:name":"Lidamiaocun",
    "wof:placetype":"locality"
},
  "geometry": {"coordinates":[116.04962999999999,33.02572],"type":"Point"}
}