{
  "type": "Feature",
  "properties": {
    "gn:admin1_code":"4.0",
    "gn:asciiname":"Kelianzhuangcun",
    "gn:country_code":"CN",
    "gn:dem":34,
    "gn:feature_class":"P",
    "gn:feature_code":"PPL",
    "gn:name":"Kelianzhuangcun",
    "gn:population":0,
    "gn:timezone":"Asia/Shanghai",
    "iso:country":"CN",
    "name:zho_x_preferred":[
        "\u53ef\u604b\u5e84\u6751"
    ],
    "wof:name":"Kelianzhuangcun",
    "wof:placetype":"locality"
},
  "geometry": {"coordinates":[117.30571999999999,34.30652],"type":"Point"}
}