{
  "type": "Feature",
  "properties": {
    "gn:admin1_code":"10",
    "gn:asciiname":"Yong'an",
    "gn:country_code":"CN",
    "gn:dem":82,
    "gn:feature_class":"P",
    "gn:feature_code":"PPL",
    "gn:name":"Yong\u2019an",
    "gn:population":0,
    "gn:timezone":"Asia/Shanghai",
    "iso:country":"CN",
    "name:und_x_variant":[
        "Yong\u2019an",
        "\u6c38\u5b89"
    ],
    "wof:name":"Yong'an",
    "wof:placetype":"locality"
},
  "geometry": {"coordinates":[114.54671999999999,38.18911],"type":"Point"}
}