{
  "type": "Feature",
  "properties": {
    "gn:admin1_code":"04",
    "gn:asciiname":"Haozhai",
    "gn:country_code":"CN",
    "gn:dem":44,
    "gn:feature_class":"P",
    "gn:feature_code":"PPL",
    "gn:name":"Haozhai",
    "gn:population":0,
    "gn:timezone":"Asia/Shanghai",
    "iso:country":"CN",
    "name:und_x_variant":[
        "Ho-chai-chan",
        "Ho-chai",
        "Hao-chai",
        "Haozhai"
    ],
    "name:zho_x_preferred":[
        "\u90dd\u5be8"
    ],
    "wof:name":"Haozhai",
    "wof:placetype":"locality"
},
  "geometry": {"coordinates":[116.98999999999999,34.2988],"type":"Point"}
}