{
  "type": "Feature",
  "properties": {
    "gn:admin1_code":"11.0",
    "gn:asciiname":"Dadongshan",
    "gn:country_code":"CN",
    "gn:dem":134,
    "gn:feature_class":"P",
    "gn:feature_code":"PPL",
    "gn:name":"Dadongshan",
    "gn:population":0,
    "gn:timezone":"Asia/Shanghai",
    "iso:country":"CN",
    "name:zho_x_preferred":[
        "\u5927\u6d1e\u5c71"
    ],
    "wof:name":"Dadongshan",
    "wof:placetype":"locality"
},
  "geometry": {"coordinates":[113.44515,26.59941],"type":"Point"}
}