{
  "type": "Feature",
  "properties": {
    "gn:admin1_code":"7.0",
    "gn:asciiname":"Longbeixi",
    "gn:country_code":"CN",
    "gn:dem":213,
    "gn:feature_class":"P",
    "gn:feature_code":"PPL",
    "gn:name":"Longbeixi",
    "gn:population":0,
    "gn:timezone":"Asia/Shanghai",
    "iso:country":"CN",
    "name:zho_x_preferred":[
        "\u9f99\u5317\u6eaa"
    ],
    "wof:name":"Longbeixi",
    "wof:placetype":"locality"
},
  "geometry": {"coordinates":[118.42086999999999,26.73895],"type":"Point"}
}