{
  "type": "Feature",
  "properties": {
    "gn:admin1_code":"26",
    "gn:asciiname":"Mazhanguo",
    "gn:country_code":"CN",
    "gn:dem":425,
    "gn:feature_class":"P",
    "gn:feature_code":"PPL",
    "gn:name":"Mazhanguo",
    "gn:population":0,
    "gn:timezone":"Asia/Shanghai",
    "iso:country":"CN",
    "name:und_x_variant":[
        "\u9a6c\u7ad9\u90ed"
    ],
    "name:zho_x_preferred":[
        "\u9a6c\u7ad9\u90ed"
    ],
    "wof:name":"Mazhanguo",
    "wof:placetype":"locality"
},
  "geometry": {"coordinates":[108.76361,34.57056],"type":"Point"}
}