{
  "type": "Feature",
  "properties": {
    "gn:admin1_code":"19.0",
    "gn:asciiname":"Xibinggou",
    "gn:country_code":"CN",
    "gn:dem":303,
    "gn:feature_class":"P",
    "gn:feature_code":"PPL",
    "gn:name":"Xibinggou",
    "gn:population":0,
    "gn:timezone":"Asia/Shanghai",
    "iso:country":"CN",
    "name:zho_x_preferred":[
        "\u897f\u51b0\u6c9f"
    ],
    "wof:name":"Xibinggou",
    "wof:placetype":"locality"
},
  "geometry": {"coordinates":[121.149,41.7521],"type":"Point"}
}