{
  "type": "Feature",
  "properties": {
    "gn:admin1_code":"16.0",
    "gn:asciiname":"Dongjing",
    "gn:country_code":"CN",
    "gn:dem":688,
    "gn:feature_class":"P",
    "gn:feature_code":"PPL",
    "gn:name":"Dongjing",
    "gn:population":0,
    "gn:timezone":"Asia/Shanghai",
    "iso:country":"CN",
    "name:deu_x_preferred":[
        "Dongjing"
    ],
    "name:zho_x_preferred":[
        "\u4e1c\u4e95"
    ],
    "wof:name":"Dongjing",
    "wof:placetype":"locality"
},
  "geometry": {"coordinates":[107.149,25.5506],"type":"Point"}
}