{
  "type": "Feature",
  "properties": {
    "gn:admin1_code":"18",
    "gn:asciiname":"Changwozi",
    "gn:country_code":"CN",
    "gn:dem":915,
    "gn:feature_class":"P",
    "gn:feature_code":"PPL",
    "gn:name":"Changwozi",
    "gn:population":0,
    "gn:timezone":"Asia/Shanghai",
    "iso:country":"CN",
    "name:zho_x_preferred":[
        "\u957f\u7a9d\u5b50"
    ],
    "wof:name":"Changwozi",
    "wof:placetype":"locality"
},
  "geometry": {"coordinates":[106.751,27.5767],"type":"Point"}
}