{
  "type": "Feature",
  "properties": {
    "gn:admin1_code":"3.0",
    "gn:asciiname":"Niujiaoguo",
    "gn:country_code":"CN",
    "gn:dem":326,
    "gn:feature_class":"P",
    "gn:feature_code":"PPL",
    "gn:name":"Niujiaoguo",
    "gn:population":0,
    "gn:timezone":"Asia/Shanghai",
    "iso:country":"CN",
    "name:und_x_variant":[
        "\u725b\u89d2\u57da"
    ],
    "wof:name":"Niujiaoguo",
    "wof:placetype":"locality"
},
  "geometry": {"coordinates":[114.28064000000001,28.87098],"type":"Point"}
}