{
  "type": "Feature",
  "properties": {
    "gn:admin1_code":"11.0",
    "gn:asciiname":"Gaoqiaotou",
    "gn:country_code":"CN",
    "gn:dem":113,
    "gn:feature_class":"P",
    "gn:feature_code":"PPL",
    "gn:name":"Gaoqiaotou",
    "gn:population":0,
    "gn:timezone":"Asia/Shanghai",
    "iso:country":"CN",
    "name:zho_x_preferred":[
        "\u9ad8\u6865\u5934"
    ],
    "wof:name":"Gaoqiaotou",
    "wof:placetype":"locality"
},
  "geometry": {"coordinates":[111.68304999999999,26.35694],"type":"Point"}
}