{
  "type": "Feature",
  "properties": {
    "gn:admin1_code":"1.0",
    "gn:asciiname":"Qianloucun",
    "gn:country_code":"CN",
    "gn:dem":24,
    "gn:feature_class":"P",
    "gn:feature_code":"PPL",
    "gn:name":"Qianloucun",
    "gn:population":0,
    "gn:timezone":"Asia/Shanghai",
    "iso:country":"CN",
    "name:zho_x_preferred":[
        "\u524d\u697c\u6751"
    ],
    "wof:name":"Qianloucun",
    "wof:placetype":"locality"
},
  "geometry": {"coordinates":[116.79785,32.21973],"type":"Point"}
}