{
  "type": "Feature",
  "properties": {
    "gn:admin1_code":"30.0",
    "gn:asciiname":"Youtan",
    "gn:country_code":"CN",
    "gn:dem":11,
    "gn:feature_class":"P",
    "gn:feature_code":"PPL",
    "gn:name":"Youtan",
    "gn:population":0,
    "gn:timezone":"Asia/Shanghai",
    "iso:country":"CN",
    "name:zho_x_preferred":[
        "\u53f3\u6ee9"
    ],
    "wof:name":"Youtan",
    "wof:placetype":"locality"
},
  "geometry": {"coordinates":[113.07411999999999,22.79752],"type":"Point"}
}