{
  "type": "Feature",
  "properties": {
    "gn:admin1_code":"3.0",
    "gn:asciiname":"Laowu",
    "gn:country_code":"CN",
    "gn:dem":90,
    "gn:feature_class":"P",
    "gn:feature_code":"PPL",
    "gn:name":"Laowu",
    "gn:population":0,
    "gn:timezone":"Asia/Shanghai",
    "iso:country":"CN",
    "name:zho_x_preferred":[
        "\u8001\u5c4b"
    ],
    "wof:name":"Laowu",
    "wof:placetype":"locality"
},
  "geometry": {"coordinates":[114.57899999999999,27.2923],"type":"Point"}
}