{
  "type": "Feature",
  "properties": {
    "gn:admin1_code":"1.0",
    "gn:asciiname":"Zhangjicun",
    "gn:country_code":"CN",
    "gn:dem":32,
    "gn:feature_class":"P",
    "gn:feature_code":"PPL",
    "gn:name":"Zhangjicun",
    "gn:population":0,
    "gn:timezone":"Asia/Shanghai",
    "iso:country":"CN",
    "name:und_x_variant":[
        "Chang-chia-chi",
        "Chang-chi",
        "Zhangji",
        "Zhangjicun"
    ],
    "name:zho_x_preferred":[
        "\u5f20\u96c6\u6751"
    ],
    "wof:name":"Zhangjicun",
    "wof:placetype":"locality"
},
  "geometry": {"coordinates":[115.76698,32.66333],"type":"Point"}
}