{
  "type": "Feature",
  "properties": {
    "gn:admin1_code":"15.0",
    "gn:asciiname":"Changjiaya",
    "gn:country_code":"CN",
    "gn:dem":2248,
    "gn:feature_class":"P",
    "gn:feature_code":"PPL",
    "gn:name":"Changjiaya",
    "gn:population":0,
    "gn:timezone":"Asia/Shanghai",
    "iso:country":"CN",
    "name:zho_x_preferred":[
        "\u5e38\u5bb6\u5d16"
    ],
    "wof:name":"Changjiaya",
    "wof:placetype":"locality"
},
  "geometry": {"coordinates":[105.208,36.4636],"type":"Point"}
}