{
  "type": "Feature",
  "properties": {
    "gn:admin1_code":"33.0",
    "gn:asciiname":"Zhonghe",
    "gn:country_code":"CN",
    "gn:dem":357,
    "gn:feature_class":"P",
    "gn:feature_code":"PPLA3",
    "gn:name":"Zhonghe",
    "gn:population":0,
    "gn:timezone":"Asia/Shanghai",
    "iso:country":"CN",
    "name:ceb_x_preferred":[
        "Zhonghe"
    ],
    "name:deu_x_preferred":[
        "Zhonghe"
    ],
    "name:swe_x_preferred":[
        "Zhonghe"
    ],
    "name:und_x_variant":[
        "Xiushan Tujiazu Miaozu Zizhixian",
        "Siushan",
        "Hsiu-shan",
        "Siushan-hsien",
        "Hsiu-shan-hsien",
        "Zhonghe",
        "Zhonghe Zhen"
    ],
    "name:zho_x_preferred":[
        "\u4e2d\u548c"
    ],
    "name:zho_x_variant":[
        "\u4e2d\u548c\u9547",
        "\u79c0\u5c71\u571f\u5bb6\u65cf\u82d7\u65cf\u81ea\u6cbb\u53bf"
    ],
    "wof:name":"Zhonghe",
    "wof:placetype":"locality"
},
  "geometry": {"coordinates":[108.98900999999999,28.45049],"type":"Point"}
}