{
  "type": "Feature",
  "properties": {
    "gn:admin1_code":"19.0",
    "gn:asciiname":"Gengjiajie",
    "gn:country_code":"CN",
    "gn:dem":144,
    "gn:feature_class":"P",
    "gn:feature_code":"PPL",
    "gn:name":"Gengjiajie",
    "gn:population":0,
    "gn:timezone":"Asia/Shanghai",
    "iso:country":"CN",
    "name:und_x_variant":[
        "\u803f\u5bb6\u8857"
    ],
    "wof:name":"Gengjiajie",
    "wof:placetype":"locality"
},
  "geometry": {"coordinates":[124.002,41.8222],"type":"Point"}
}