{
  "type": "Feature",
  "properties": {
    "gn:admin1_code":"10",
    "gn:asciiname":"Xinbu",
    "gn:cc2":"CN",
    "gn:country_code":"CN",
    "gn:dem":883,
    "gn:feature_class":"P",
    "gn:feature_code":"PPL",
    "gn:name":"Xinbu",
    "gn:population":0,
    "gn:timezone":"Asia/Shanghai",
    "iso:country":"CN",
    "name:und_x_variant":[
        "Hsin-pao",
        "Hsin-pao-chia",
        "Hsin-p\u2019u-chia",
        "Xinbu"
    ],
    "wof:name":"Xinbu",
    "wof:placetype":"locality"
},
  "geometry": {"coordinates":[114.54472,40.15944],"type":"Point"}
}