{
  "type": "Feature",
  "properties": {
    "gn:admin1_code":"19.0",
    "gn:asciiname":"Kulongshancun",
    "gn:country_code":"CN",
    "gn:dem":1,
    "gn:feature_class":"P",
    "gn:feature_code":"PPL",
    "gn:name":"Kulongshancun",
    "gn:population":0,
    "gn:timezone":"Asia/Shanghai",
    "iso:country":"CN",
    "name:zho_x_preferred":[
        "\u7a9f\u7abf\u5c71\u6751"
    ],
    "wof:name":"Kulongshancun",
    "wof:placetype":"locality"
},
  "geometry": {"coordinates":[124.01098,39.83854],"type":"Point"}
}