{
  "type": "Feature",
  "properties": {
    "gn:admin1_code":"24",
    "gn:asciiname":"Yixing",
    "gn:country_code":"CN",
    "gn:dem":1379,
    "gn:feature_class":"P",
    "gn:feature_code":"PPLA3",
    "gn:name":"Yixing",
    "gn:population":0,
    "gn:timezone":"Asia/Shanghai",
    "iso:country":"CN",
    "name:und_x_variant":[
        "Kheshun",
        "Ho-shun",
        "Ho-shun-hsien",
        "Heshun",
        "Yixing",
        "Heshun Xian",
        "Yixing Zhen",
        "\u548c\u987a\u53bf",
        "\u4e49\u5174\u9547"
    ],
    "name:zho_x_preferred":[
        "\u4e49\u5174"
    ],
    "wof:name":"Yixing",
    "wof:placetype":"locality"
},
  "geometry": {"coordinates":[113.53926,37.3376],"type":"Point"}
}