{
  "type": "Feature",
  "properties": {
    "gn:admin1_code":"14.0",
    "gn:asciiname":"Mengqiong Muchang",
    "gn:country_code":"CN",
    "gn:dem":4369,
    "gn:feature_class":"P",
    "gn:feature_code":"PPLF",
    "gn:name":"Mengqiong Muchang",
    "gn:population":0,
    "gn:timezone":"Asia/Urumqi",
    "iso:country":"CN",
    "name:zho_x_preferred":[
        "\u5b5f\u7a77\u7267\u573a"
    ],
    "wof:name":"Mengqiong Muchang",
    "wof:placetype":"locality"
},
  "geometry": {"coordinates":[97.88081,29.76564],"type":"Point"}
}