{
  "type": "Feature",
  "properties": {
    "gn:admin1_code":"33",
    "gn:asciiname":"Yanshan",
    "gn:country_code":"CN",
    "gn:dem":321,
    "gn:feature_class":"P",
    "gn:feature_code":"PPLA4",
    "gn:name":"Yanshan",
    "gn:population":0,
    "gn:timezone":"Asia/Shanghai",
    "iso:country":"CN",
    "name:ceb_x_preferred":[
        "Yanshan"
    ],
    "name:deu_x_preferred":[
        "Yanshan"
    ],
    "name:fra_x_preferred":[
        "Yanshan"
    ],
    "name:nor_x_preferred":[
        "Yanshan"
    ],
    "name:rus_x_preferred":[
        "\u042f\u043d\u044c\u0448\u0430\u043d\u044c"
    ],
    "name:swe_x_preferred":[
        "Yanshan"
    ],
    "name:und_x_variant":[
        "Yanshan Xiang",
        "Xiaxingchang"
    ],
    "name:zho_x_preferred":[
        "\u71d5\u5c71"
    ],
    "name:zho_x_variant":[
        "\u71d5\u5c71\u4e61",
        "\u590f\u5174\u573a"
    ],
    "wof:name":"Yanshan",
    "wof:placetype":"locality"
},
  "geometry": {"coordinates":[108.30907999999999,30.55435],"type":"Point"}
}