{
  "type": "Feature",
  "properties": {
    "gn:admin1_code":"3",
    "gn:asciiname":"Xinggong'ao",
    "gn:country_code":"CN",
    "gn:dem":285,
    "gn:feature_class":"P",
    "gn:feature_code":"PPL",
    "gn:name":"Xinggong\u2019ao",
    "gn:population":0,
    "gn:timezone":"Asia/Shanghai",
    "iso:country":"CN",
    "name:und_x_variant":[
        "Xinggong\u2019ao",
        "\u674f\u516c\u5773"
    ],
    "wof:name":"Xinggong'ao",
    "wof:placetype":"locality"
},
  "geometry": {"coordinates":[116.09905000000001,27.07269],"type":"Point"}
}