{
  "type": "Feature",
  "properties": {
    "gn:admin1_code":"11.0",
    "gn:asciiname":"Luojia Wuchang",
    "gn:country_code":"CN",
    "gn:dem":65,
    "gn:feature_class":"P",
    "gn:feature_code":"PPL",
    "gn:name":"Luojia Wuchang",
    "gn:population":0,
    "gn:timezone":"Asia/Shanghai",
    "iso:country":"CN",
    "name:zho_x_preferred":[
        "\u7f57\u5bb6\u5c4b\u573a"
    ],
    "wof:name":"Luojia Wuchang",
    "wof:placetype":"locality"
},
  "geometry": {"coordinates":[113.25838,28.4049],"type":"Point"}
}