{
  "type": "Feature",
  "properties": {
    "gn:admin1_code":"15.0",
    "gn:asciiname":"Dongyueshan",
    "gn:country_code":"CN",
    "gn:dem":1788,
    "gn:feature_class":"P",
    "gn:feature_code":"PPL",
    "gn:name":"Dongyueshan",
    "gn:population":0,
    "gn:timezone":"Asia/Shanghai",
    "iso:country":"CN",
    "name:zho_x_preferred":[
        "\u4e1c\u5cb3\u5c71"
    ],
    "wof:name":"Dongyueshan",
    "wof:placetype":"locality"
},
  "geometry": {"coordinates":[105.07621,33.26354],"type":"Point"}
}