{
  "type": "Feature",
  "properties": {
    "gn:admin1_code":"24",
    "gn:asciiname":"Huotan",
    "gn:country_code":"CN",
    "gn:dem":380,
    "gn:feature_class":"P",
    "gn:feature_code":"PPL",
    "gn:name":"Huotan",
    "gn:population":0,
    "gn:timezone":"Asia/Shanghai",
    "iso:country":"CN",
    "wof:name":"Huotan",
    "wof:placetype":"locality"
},
  "geometry": {"coordinates":[112.62083,35.26278],"type":"Point"}
}