{
  "type": "Feature",
  "properties": {
    "gn:admin1_code":"32.0",
    "gn:asciiname":"Renshuishi",
    "gn:country_code":"CN",
    "gn:dem":532,
    "gn:feature_class":"P",
    "gn:feature_code":"PPL",
    "gn:name":"Renshuishi",
    "gn:population":0,
    "gn:timezone":"Asia/Shanghai",
    "iso:country":"CN",
    "name:zho_x_preferred":[
        "\u4eba\u7761\u77f3"
    ],
    "wof:name":"Renshuishi",
    "wof:placetype":"locality"
},
  "geometry": {"coordinates":[104.88,31.717],"type":"Point"}
}