{
  "type": "Feature",
  "properties": {
    "gn:admin1_code":"18",
    "gn:asciiname":"Gouchangpo",
    "gn:country_code":"CN",
    "gn:dem":1247,
    "gn:feature_class":"P",
    "gn:feature_code":"PPL",
    "gn:name":"Gouchangpo",
    "gn:population":0,
    "gn:timezone":"Asia/Shanghai",
    "iso:country":"CN",
    "name:zho_x_preferred":[
        "\u72d7\u573a\u5761"
    ],
    "wof:name":"Gouchangpo",
    "wof:placetype":"locality"
},
  "geometry": {"coordinates":[105.65900000000001,26.0912],"type":"Point"}
}