{
  "type": "Feature",
  "properties": {
    "gn:admin1_code":"19.0",
    "gn:asciiname":"Beitun",
    "gn:country_code":"CN",
    "gn:dem":4,
    "gn:feature_class":"P",
    "gn:feature_code":"PPL",
    "gn:name":"Beitun",
    "gn:population":0,
    "gn:timezone":"Asia/Shanghai",
    "iso:country":"CN",
    "name:deu_x_preferred":[
        "Beitun"
    ],
    "name:zho_x_preferred":[
        "\u5317\u5c6f"
    ],
    "wof:name":"Beitun",
    "wof:placetype":"locality"
},
  "geometry": {"coordinates":[121.396,39.4314],"type":"Point"}
}