{
  "type": "Feature",
  "properties": {
    "gn:admin1_code":"29",
    "gn:asciiname":"Talong",
    "gn:country_code":"CN",
    "gn:dem":1535,
    "gn:feature_class":"P",
    "gn:feature_code":"PPL",
    "gn:name":"Talong",
    "gn:population":0,
    "gn:timezone":"Asia/Shanghai",
    "iso:country":"CN",
    "name:zho_x_preferred":[
        "\u4ed6\u9f99"
    ],
    "wof:name":"Talong",
    "wof:placetype":"locality"
},
  "geometry": {"coordinates":[102.714,23.8755],"type":"Point"}
}