{
  "type": "Feature",
  "properties": {
    "gn:admin1_code":"16.0",
    "gn:asciiname":"Longyi",
    "gn:country_code":"CN",
    "gn:dem":328,
    "gn:feature_class":"P",
    "gn:feature_code":"PPL",
    "gn:name":"Longyi",
    "gn:population":0,
    "gn:timezone":"Asia/Shanghai",
    "iso:country":"CN",
    "name:aze_x_preferred":[
        "Londji"
    ],
    "name:deu_x_preferred":[
        "Longyi"
    ],
    "name:fin_x_preferred":[
        "Longyi"
    ],
    "name:fra_x_preferred":[
        "Longyi"
    ],
    "name:hye_x_preferred":[
        "\u053c\u0578\u0576\u057b\u056b"
    ],
    "name:ind_x_preferred":[
        "Longyi"
    ],
    "name:ita_x_preferred":[
        "Longyi"
    ],
    "name:jpn_x_preferred":[
        "\u30ed\u30f3\u30b8\u30fc"
    ],
    "name:mya_x_preferred":[
        "\u101c\u102f\u1036\u1001\u103b\u100a\u103a"
    ],
    "name:rus_x_preferred":[
        "\u041b\u043e\u043d\u0434\u0436\u0438"
    ],
    "name:zho_x_preferred":[
        "\u9f99\u76ca"
    ],
    "wof:name":"Longyi",
    "wof:placetype":"locality"
},
  "geometry": {"coordinates":[107.292,22.8898],"type":"Point"}
}