{
  "type": "Feature",
  "properties": {
    "gn:admin1_code":"30.0",
    "gn:asciiname":"Xiaxikeng",
    "gn:country_code":"CN",
    "gn:dem":318,
    "gn:feature_class":"P",
    "gn:feature_code":"PPL",
    "gn:name":"Xiaxikeng",
    "gn:population":0,
    "gn:timezone":"Asia/Shanghai",
    "iso:country":"CN",
    "name:zho_x_preferred":[
        "Xiaxikeng"
    ],
    "name:zho_x_variant":[
        "\u4e0b\u897f\u5751"
    ],
    "wof:name":"Xiaxikeng",
    "wof:placetype":"locality"
},
  "geometry": {"coordinates":[113.38611000000002,25.23917],"type":"Point"}
}