{
  "type": "Feature",
  "properties": {
    "gn:admin1_code":"25",
    "gn:asciiname":"Hougezhuang",
    "gn:country_code":"CN",
    "gn:dem":98,
    "gn:feature_class":"P",
    "gn:feature_code":"PPL",
    "gn:name":"Hougezhuang",
    "gn:population":0,
    "gn:timezone":"Asia/Shanghai",
    "iso:country":"CN",
    "name:zho_x_preferred":[
        "\u540e\u6208\u5e84"
    ],
    "wof:name":"Hougezhuang",
    "wof:placetype":"locality"
},
  "geometry": {"coordinates":[119.18300000000001,35.9655],"type":"Point"}
}