{
  "type": "Feature",
  "properties": {
    "gn:admin1_code":"16",
    "gn:asciiname":"Guishanchong",
    "gn:country_code":"CN",
    "gn:dem":237,
    "gn:feature_class":"P",
    "gn:feature_code":"PPL",
    "gn:name":"Guishanchong",
    "gn:population":0,
    "gn:timezone":"Asia/Shanghai",
    "iso:country":"CN",
    "name:zho_x_preferred":[
        "\u6842\u5c71\u51b2"
    ],
    "wof:name":"Guishanchong",
    "wof:placetype":"locality"
},
  "geometry": {"coordinates":[110.508,24.4937],"type":"Point"}
}