{
  "type": "Feature",
  "properties": {
    "gn:admin1_code":"7.0",
    "gn:asciiname":"Zhanggang",
    "gn:country_code":"CN",
    "gn:dem":4,
    "gn:feature_class":"P",
    "gn:feature_code":"PPLA4",
    "gn:name":"Zhanggang",
    "gn:population":0,
    "gn:timezone":"Asia/Shanghai",
    "iso:country":"CN",
    "name:und_x_variant":[
        "Chang-chiang",
        "Chang-kang",
        "Zhanggang",
        "Zhanggang Zhen"
    ],
    "name:zho_x_preferred":[
        "\u6f33\u6e2f"
    ],
    "name:zho_x_variant":[
        "\u6f33\u6e2f\u9547"
    ],
    "wof:name":"Zhanggang",
    "wof:placetype":"locality"
},
  "geometry": {"coordinates":[119.62724,25.92479],"type":"Point"}
}