{
  "type": "Feature",
  "properties": {
    "gn:admin1_code":"25",
    "gn:asciiname":"Daqizhouwu Dongbei",
    "gn:country_code":"CN",
    "gn:dem":8,
    "gn:feature_class":"P",
    "gn:feature_code":"PPL",
    "gn:name":"Daqizhouwu Dongbei",
    "gn:population":0,
    "gn:timezone":"Asia/Shanghai",
    "iso:country":"CN",
    "name:zho_x_preferred":[
        "\u5927\u9f50\u5468\u52a1\u4e1c\u5317"
    ],
    "wof:name":"Daqizhouwu Dongbei",
    "wof:placetype":"locality"
},
  "geometry": {"coordinates":[117.536,37.9961],"type":"Point"}
}