{
  "type": "Feature",
  "properties": {
    "gn:admin1_code":"01",
    "gn:asciiname":"Mayaqiao",
    "gn:cc2":"CN",
    "gn:country_code":"CN",
    "gn:dem":92,
    "gn:feature_class":"P",
    "gn:feature_code":"PPL",
    "gn:name":"Mayaqiao",
    "gn:population":0,
    "gn:timezone":"Asia/Shanghai",
    "iso:country":"CN",
    "name:und_x_variant":[
        "Ma-an-ch\u2019iao",
        "Ma-ya-ch\u2019iao",
        "Maya",
        "Mayaqiao"
    ],
    "wof:name":"Mayaqiao",
    "wof:placetype":"locality"
},
  "geometry": {"coordinates":[117.61667,30.63333],"type":"Point"}
}