{
  "type": "Feature",
  "properties": {
    "gn:admin1_code":"30.0",
    "gn:asciiname":"Zengwuzhang",
    "gn:country_code":"CN",
    "gn:dem":363,
    "gn:feature_class":"P",
    "gn:feature_code":"PPL",
    "gn:name":"Zengwuzhang",
    "gn:population":0,
    "gn:timezone":"Asia/Shanghai",
    "iso:country":"CN",
    "name:zho_x_preferred":[
        "\u66fe\u5c4b\u5d82"
    ],
    "wof:name":"Zengwuzhang",
    "wof:placetype":"locality"
},
  "geometry": {"coordinates":[114.91648000000001,23.69451],"type":"Point"}
}