{
  "type": "Feature",
  "properties": {
    "gn:admin1_code":"26.0",
    "gn:asciiname":"Yanjiawan",
    "gn:country_code":"CN",
    "gn:dem":973,
    "gn:feature_class":"P",
    "gn:feature_code":"PPL",
    "gn:name":"Yanjiawan",
    "gn:population":0,
    "gn:timezone":"Asia/Shanghai",
    "iso:country":"CN",
    "name:und_x_variant":[
        "\u70df\u5bb6\u6e7e"
    ],
    "wof:name":"Yanjiawan",
    "wof:placetype":"locality"
},
  "geometry": {"coordinates":[106.22429,33.04149],"type":"Point"}
}