{
  "type": "Feature",
  "properties": {
    "gn:admin1_code":"05",
    "gn:asciiname":"Qitamu",
    "gn:cc2":"CN",
    "gn:country_code":"CN",
    "gn:dem":179,
    "gn:feature_class":"P",
    "gn:feature_code":"PPL",
    "gn:name":"Qitamu",
    "gn:population":0,
    "gn:timezone":"Asia/Shanghai",
    "iso:country":"CN",
    "name:und_x_variant":[
        "Ch\u2019i-t\u2019a-mu",
        "Qitamu"
    ],
    "wof:name":"Qitamu",
    "wof:placetype":"locality"
},
  "geometry": {"coordinates":[126.33333,44.36667],"type":"Point"}
}