{
  "type": "Feature",
  "properties": {
    "gn:admin1_code":"2.0",
    "gn:asciiname":"Ganzhushan",
    "gn:country_code":"CN",
    "gn:dem":163,
    "gn:feature_class":"P",
    "gn:feature_code":"PPL",
    "gn:name":"Ganzhushan",
    "gn:population":0,
    "gn:timezone":"Asia/Shanghai",
    "iso:country":"CN",
    "name:und_x_variant":[
        "\u7518\u7af9\u5c71"
    ],
    "wof:name":"Ganzhushan",
    "wof:placetype":"locality"
},
  "geometry": {"coordinates":[119.67373000000001,31.00637],"type":"Point"}
}