{
  "type": "Feature",
  "properties": {
    "gn:admin1_code":"14.0",
    "gn:asciiname":"Rongga",
    "gn:country_code":"CN",
    "gn:dem":3391,
    "gn:feature_class":"P",
    "gn:feature_code":"PPL",
    "gn:name":"Rongga",
    "gn:population":0,
    "gn:timezone":"Asia/Urumqi",
    "iso:country":"CN",
    "name:zho_x_preferred":[
        "\u5bb9\u560e"
    ],
    "wof:name":"Rongga",
    "wof:placetype":"locality"
},
  "geometry": {"coordinates":[93.67046000000001,30.00800000000001],"type":"Point"}
}