{
  "type": "Feature",
  "properties": {
    "gn:admin1_code":"26.0",
    "gn:asciiname":"Gao'eryuancun",
    "gn:country_code":"CN",
    "gn:dem":1197,
    "gn:feature_class":"P",
    "gn:feature_code":"PPL",
    "gn:name":"Gao\u2019eryuancun",
    "gn:population":0,
    "gn:timezone":"Asia/Shanghai",
    "iso:country":"CN",
    "name:und_x_variant":[
        "Gao\u2019eryuancun"
    ],
    "name:zho_x_preferred":[
        "\u9ad8\u5c14\u539f\u6751"
    ],
    "wof:name":"Gao'eryuancun",
    "wof:placetype":"locality"
},
  "geometry": {"coordinates":[108.69759999999999,35.00321],"type":"Point"}
}