{
  "type": "Feature",
  "properties": {
    "gn:admin1_code":"15.0",
    "gn:asciiname":"Hua'erzhang",
    "gn:country_code":"CN",
    "gn:dem":1789,
    "gn:feature_class":"P",
    "gn:feature_code":"PPL",
    "gn:name":"Hua\u2019erzhang",
    "gn:population":0,
    "gn:timezone":"Asia/Shanghai",
    "iso:country":"CN",
    "name:und_x_variant":[
        "Hua\u2019erzhang",
        "\u82b1\u513f\u638c"
    ],
    "wof:name":"Hua'erzhang",
    "wof:placetype":"locality"
},
  "geometry": {"coordinates":[106.59114,36.29179],"type":"Point"}
}