{
  "type": "Feature",
  "properties": {
    "gn:admin1_code":"29.0",
    "gn:asciiname":"Xiaocun",
    "gn:country_code":"CN",
    "gn:dem":1943,
    "gn:feature_class":"P",
    "gn:feature_code":"PPL",
    "gn:name":"Xiaocun",
    "gn:population":0,
    "gn:timezone":"Asia/Shanghai",
    "iso:country":"CN",
    "name:zho_x_preferred":[
        "\u5c0f\u6751"
    ],
    "wof:name":"Xiaocun",
    "wof:placetype":"locality"
},
  "geometry": {"coordinates":[101.47199999999999,25.9614],"type":"Point"}
}