{
  "type": "Feature",
  "properties": {
    "gn:admin1_code":"19.0",
    "gn:asciiname":"Heimencun",
    "gn:country_code":"CN",
    "gn:dem":113,
    "gn:feature_class":"P",
    "gn:feature_code":"PPL",
    "gn:name":"Heimencun",
    "gn:population":0,
    "gn:timezone":"Asia/Shanghai",
    "iso:country":"CN",
    "name:zho_x_preferred":[
        "\u9ed1\u95e8\u6751"
    ],
    "wof:name":"Heimencun",
    "wof:placetype":"locality"
},
  "geometry": {"coordinates":[124.12203,40.69061],"type":"Point"}
}