{
  "type": "Feature",
  "properties": {
    "gn:admin1_code":"11.0",
    "gn:asciiname":"Shenshuixi",
    "gn:country_code":"CN",
    "gn:dem":1134,
    "gn:feature_class":"P",
    "gn:feature_code":"PPL",
    "gn:name":"Shenshuixi",
    "gn:population":0,
    "gn:timezone":"Asia/Shanghai",
    "iso:country":"CN",
    "name:zho_x_preferred":[
        "Shenshuixi"
    ],
    "name:zho_x_variant":[
        "\u795e\u6c34\u6eaa"
    ],
    "wof:name":"Shenshuixi",
    "wof:placetype":"locality"
},
  "geometry": {"coordinates":[110.84563,30.02416],"type":"Point"}
}