{
  "type": "Feature",
  "properties": {
    "gn:admin1_code":"1.0",
    "gn:asciiname":"Lujing",
    "gn:country_code":"CN",
    "gn:dem":38,
    "gn:feature_class":"P",
    "gn:feature_code":"PPL",
    "gn:name":"Lujing",
    "gn:population":0,
    "gn:timezone":"Asia/Shanghai",
    "iso:country":"CN",
    "name:zho_x_preferred":[
        "Lujing"
    ],
    "name:zho_x_variant":[
        "\u9c81\u4eac"
    ],
    "wof:name":"Lujing",
    "wof:placetype":"locality"
},
  "geometry": {"coordinates":[119.45587,31.04174],"type":"Point"}
}