{
  "type": "Feature",
  "properties": {
    "gn:admin1_code":"19.0",
    "gn:asciiname":"Dahamagou",
    "gn:country_code":"CN",
    "gn:dem":36,
    "gn:feature_class":"P",
    "gn:feature_code":"PPL",
    "gn:name":"Dahamagou",
    "gn:population":0,
    "gn:timezone":"Asia/Shanghai",
    "iso:country":"CN",
    "name:zho_x_preferred":[
        "\u5927\u86e4\u87c6\u6c9f"
    ],
    "wof:name":"Dahamagou",
    "wof:placetype":"locality"
},
  "geometry": {"coordinates":[122.98099999999999,39.5013],"type":"Point"}
}