{
  "type": "Feature",
  "properties": {
    "gn:admin1_code":"9.0",
    "gn:asciiname":"Dongchenzhuang",
    "gn:country_code":"CN",
    "gn:dem":131,
    "gn:feature_class":"P",
    "gn:feature_code":"PPL",
    "gn:name":"Dongchenzhuang",
    "gn:population":0,
    "gn:timezone":"Asia/Shanghai",
    "iso:country":"CN",
    "name:zho_x_preferred":[
        "\u4e1c\u9648\u5e84"
    ],
    "wof:name":"Dongchenzhuang",
    "wof:placetype":"locality"
},
  "geometry": {"coordinates":[111.99334,32.56668],"type":"Point"}
}