{
  "type": "Feature",
  "properties": {
    "gn:admin1_code":"8.0",
    "gn:asciiname":"Liyecun",
    "gn:country_code":"CN",
    "gn:dem":214,
    "gn:feature_class":"P",
    "gn:feature_code":"PPL",
    "gn:name":"Liyecun",
    "gn:population":0,
    "gn:timezone":"Asia/Shanghai",
    "iso:country":"CN",
    "name:zho_x_preferred":[
        "\u7acb\u4e1a\u6751"
    ],
    "wof:name":"Liyecun",
    "wof:placetype":"locality"
},
  "geometry": {"coordinates":[126.63576,47.75386],"type":"Point"}
}