{
  "type": "Feature",
  "properties": {
    "gn:admin1_code":"9.0",
    "gn:asciiname":"Xiapanggou",
    "gn:country_code":"CN",
    "gn:dem":353,
    "gn:feature_class":"P",
    "gn:feature_code":"PPL",
    "gn:name":"Xiapanggou",
    "gn:population":0,
    "gn:timezone":"Asia/Shanghai",
    "iso:country":"CN",
    "name:zho_x_preferred":[
        "\u4e0b\u5e9e\u6c9f"
    ],
    "wof:name":"Xiapanggou",
    "wof:placetype":"locality"
},
  "geometry": {"coordinates":[111.81686000000001,34.3996],"type":"Point"}
}