{
  "type": "Feature",
  "properties": {
    "gn:admin1_code":"9",
    "gn:asciiname":"Lukou",
    "gn:country_code":"CN",
    "gn:dem":49,
    "gn:feature_class":"P",
    "gn:feature_code":"PPL",
    "gn:name":"Lukou",
    "gn:population":0,
    "gn:timezone":"Asia/Shanghai",
    "iso:country":"CN",
    "name:deu_x_preferred":[
        "Lukou"
    ],
    "name:zho_x_preferred":[
        "\u8def\u53e3"
    ],
    "wof:name":"Lukou",
    "wof:placetype":"locality"
},
  "geometry": {"coordinates":[115.705,34.3597],"type":"Point"}
}