{
  "type": "Feature",
  "properties": {
    "gn:admin1_code":"1.0",
    "gn:asciiname":"Yanqiaocun",
    "gn:country_code":"CN",
    "gn:dem":30,
    "gn:feature_class":"P",
    "gn:feature_code":"PPL",
    "gn:name":"Yanqiaocun",
    "gn:population":0,
    "gn:timezone":"Asia/Shanghai",
    "iso:country":"CN",
    "name:und_x_variant":[
        "Yanqiao"
    ],
    "name:zho_x_preferred":[
        "\u4e25\u6865\u6751"
    ],
    "wof:name":"Yanqiaocun",
    "wof:placetype":"locality"
},
  "geometry": {"coordinates":[117.34314999999999,32.8208],"type":"Point"}
}