{
  "type": "Feature",
  "properties": {
    "gn:admin1_code":"19.0",
    "gn:asciiname":"Miaowanzi",
    "gn:country_code":"CN",
    "gn:dem":533,
    "gn:feature_class":"P",
    "gn:feature_code":"PPL",
    "gn:name":"Miaowanzi",
    "gn:population":0,
    "gn:timezone":"Asia/Shanghai",
    "iso:country":"CN",
    "name:zho_x_preferred":[
        "\u5e99\u6e7e\u5b50"
    ],
    "wof:name":"Miaowanzi",
    "wof:placetype":"locality"
},
  "geometry": {"coordinates":[119.68544,41.5961],"type":"Point"}
}