{
  "type": "Feature",
  "properties": {
    "gn:admin1_code":"8.0",
    "gn:asciiname":"Fengshengcun",
    "gn:country_code":"CN",
    "gn:dem":196,
    "gn:feature_class":"P",
    "gn:feature_code":"PPL",
    "gn:name":"Fengshengcun",
    "gn:population":0,
    "gn:timezone":"Asia/Shanghai",
    "iso:country":"CN",
    "name:zho_x_preferred":[
        "\u4e30\u80dc\u6751"
    ],
    "wof:name":"Fengshengcun",
    "wof:placetype":"locality"
},
  "geometry": {"coordinates":[127.76461999999999,46.94648],"type":"Point"}
}