{
  "type": "Feature",
  "properties": {
    "gn:admin1_code":"16.0",
    "gn:asciiname":"Nalong",
    "gn:country_code":"CN",
    "gn:dem":660,
    "gn:feature_class":"P",
    "gn:feature_code":"PPL",
    "gn:name":"Nalong",
    "gn:population":0,
    "gn:timezone":"Asia/Shanghai",
    "iso:country":"CN",
    "name:jpn_x_preferred":[
        "\u30c8\u30a5\u30eb\u30c8\u30a5\u30eb\u30c8\u30a5 \u30ca\u30ed\u30f3\u30a4"
    ],
    "name:kor_x_preferred":[
        "\ub69c\ub8e8\ub69c\ub8e8\ub69c \ub098\ub871\uc774"
    ],
    "name:tha_x_preferred":[
        "\u0e19\u0e32\u0e25\u0e2d\u0e07 \u0e01\u0e23\u0e30\u0e23\u0e2d\u0e01\u0e19\u0e49\u0e2d\u0e22\u0e40\u0e2b\u0e34\u0e19\u0e1f\u0e49\u0e32"
    ],
    "name:zho_x_preferred":[
        "\u7eb3\u9f99"
    ],
    "wof:name":"Nalong",
    "wof:placetype":"locality"
},
  "geometry": {"coordinates":[107.074,25.3318],"type":"Point"}
}