{
  "type": "Feature",
  "properties": {
    "gn:admin1_code":"4.0",
    "gn:asciiname":"Liuzhuang",
    "gn:country_code":"CN",
    "gn:dem":5,
    "gn:feature_class":"P",
    "gn:feature_code":"PPL",
    "gn:name":"Liuzhuang",
    "gn:population":0,
    "gn:timezone":"Asia/Shanghai",
    "iso:country":"CN",
    "name:zho_x_preferred":[
        "Liuzhuang"
    ],
    "name:zho_x_variant":[
        "\u5218\u5e84"
    ],
    "wof:name":"Liuzhuang",
    "wof:placetype":"locality"
},
  "geometry": {"coordinates":[119.23943,33.4227],"type":"Point"}
}