{
  "type": "Feature",
  "properties": {
    "gn:admin1_code":"1.0",
    "gn:asciiname":"Lijingcun",
    "gn:country_code":"CN",
    "gn:dem":33,
    "gn:feature_class":"P",
    "gn:feature_code":"PPL",
    "gn:name":"Lijingcun",
    "gn:population":0,
    "gn:timezone":"Asia/Shanghai",
    "iso:country":"CN",
    "name:zho_x_preferred":[
        "\u674e\u4e95\u6751"
    ],
    "wof:name":"Lijingcun",
    "wof:placetype":"locality"
},
  "geometry": {"coordinates":[115.75087000000001,32.61392],"type":"Point"}
}