{
  "type": "Feature",
  "properties": {
    "gn:admin1_code":"22.0",
    "gn:asciiname":"Xituogucun",
    "gn:country_code":"CN",
    "gn:dem":470,
    "gn:feature_class":"P",
    "gn:feature_code":"PPL",
    "gn:name":"Xituogucun",
    "gn:population":0,
    "gn:timezone":"Asia/Shanghai",
    "iso:country":"CN",
    "name:zho_x_preferred":[
        "\u897f\u9a7c\u53e4\u6751"
    ],
    "wof:name":"Xituogucun",
    "wof:placetype":"locality"
},
  "geometry": {"coordinates":[116.95520999999999,40.68517],"type":"Point"}
}