{
  "type": "Feature",
  "properties": {
    "gn:admin1_code":"26.0",
    "gn:asciiname":"Kuixingloucun",
    "gn:country_code":"CN",
    "gn:dem":1218,
    "gn:feature_class":"P",
    "gn:feature_code":"PPL",
    "gn:name":"Kuixingloucun",
    "gn:population":0,
    "gn:timezone":"Asia/Shanghai",
    "iso:country":"CN",
    "name:und_x_variant":[
        "\u9b41\u661f\u697c\u6751"
    ],
    "wof:name":"Kuixingloucun",
    "wof:placetype":"locality"
},
  "geometry": {"coordinates":[107.5253,34.05535],"type":"Point"}
}