{
  "type": "Feature",
  "properties": {
    "gn:admin1_code":"29.0",
    "gn:asciiname":"Baoshan",
    "gn:country_code":"CN",
    "gn:dem":1803,
    "gn:feature_class":"P",
    "gn:feature_code":"PPL",
    "gn:name":"Baoshan",
    "gn:population":0,
    "gn:timezone":"Asia/Shanghai",
    "iso:country":"CN",
    "name:ceb_x_preferred":[
        "Baoshan"
    ],
    "name:ces_x_preferred":[
        "Pao-\u0161an"
    ],
    "name:deu_x_preferred":[
        "Baoshan"
    ],
    "name:eus_x_preferred":[
        "Baoshan"
    ],
    "name:fra_x_preferred":[
        "Baoshan"
    ],
    "name:heb_x_preferred":[
        "\u05d1\u05d0\u05d5\u05e9\u05d0\u05df"
    ],
    "name:hun_x_preferred":[
        "Paosan"
    ],
    "name:mlg_x_preferred":[
        "Baoshan"
    ],
    "name:nld_x_preferred":[
        "Baoshan"
    ],
    "name:nor_x_preferred":[
        "Baoshan"
    ],
    "name:por_x_preferred":[
        "Baoshan"
    ],
    "name:rus_x_preferred":[
        "\u0411\u0430\u043e\u0448\u0430\u043d\u044c"
    ],
    "name:swe_x_preferred":[
        "Baoshan"
    ],
    "name:tur_x_preferred":[
        "Baoshan"
    ],
    "name:vie_x_preferred":[
        "B\u1ea3o S\u01a1n"
    ],
    "name:zho_x_preferred":[
        "\u5b9d\u5c71"
    ],
    "wof:name":"Baoshan",
    "wof:placetype":"locality"
},
  "geometry": {"coordinates":[100.428,27.4733],"type":"Point"}
}