{
  "type": "Feature",
  "properties": {
    "gn:admin1_code":"14.0",
    "gn:asciiname":"Mojiangcun",
    "gn:country_code":"CN",
    "gn:dem":3208,
    "gn:feature_class":"P",
    "gn:feature_code":"PPL",
    "gn:name":"Mojiangcun",
    "gn:population":0,
    "gn:timezone":"Asia/Urumqi",
    "iso:country":"CN",
    "name:zho_x_preferred":[
        "\u83ab\u6c5f\u6751"
    ],
    "wof:name":"Mojiangcun",
    "wof:placetype":"locality"
},
  "geometry": {"coordinates":[96.09775,29.88016],"type":"Point"}
}