{
  "type": "Feature",
  "properties": {
    "gn:admin1_code":"33.0",
    "gn:asciiname":"Tuotian",
    "gn:country_code":"CN",
    "gn:dem":1344,
    "gn:feature_class":"P",
    "gn:feature_code":"PPL",
    "gn:name":"Tuotian",
    "gn:population":0,
    "gn:timezone":"Asia/Shanghai",
    "iso:country":"CN",
    "name:zho_x_preferred":[
        "\u5768\u7530"
    ],
    "wof:name":"Tuotian",
    "wof:placetype":"locality"
},
  "geometry": {"coordinates":[107.73882999999999,29.57685],"type":"Point"}
}