{
  "type": "Feature",
  "properties": {
    "gn:admin1_code":"15.0",
    "gn:asciiname":"Heishui",
    "gn:country_code":"CN",
    "gn:dem":1878,
    "gn:feature_class":"P",
    "gn:feature_code":"PPL",
    "gn:name":"Heishui",
    "gn:population":0,
    "gn:timezone":"Asia/Shanghai",
    "iso:country":"CN",
    "name:ceb_x_preferred":[
        "Heishui"
    ],
    "name:zho_x_preferred":[
        "\u9ed1\u6c34"
    ],
    "wof:name":"Heishui",
    "wof:placetype":"locality"
},
  "geometry": {"coordinates":[105.152,34.2821],"type":"Point"}
}