{
  "type": "Feature",
  "properties": {
    "gn:admin1_code":"12.0",
    "gn:asciiname":"Jindiao Yuewan",
    "gn:country_code":"CN",
    "gn:dem":56,
    "gn:feature_class":"P",
    "gn:feature_code":"PPL",
    "gn:name":"Jindiao Yuewan",
    "gn:population":0,
    "gn:timezone":"Asia/Shanghai",
    "iso:country":"CN",
    "name:und_x_variant":[
        "\u91d1\u540a\u6708\u5846"
    ],
    "wof:name":"Jindiao Yuewan",
    "wof:placetype":"locality"
},
  "geometry": {"coordinates":[115.4772,30.49088],"type":"Point"}
}