{
  "type": "Feature",
  "properties": {
    "gn:admin1_code":"11.0",
    "gn:asciiname":"Xincunjie",
    "gn:country_code":"CN",
    "gn:dem":532,
    "gn:feature_class":"P",
    "gn:feature_code":"PPL",
    "gn:name":"Xincunjie",
    "gn:population":0,
    "gn:timezone":"Asia/Shanghai",
    "iso:country":"CN",
    "name:zho_x_preferred":[
        "\u65b0\u6751\u754c"
    ],
    "wof:name":"Xincunjie",
    "wof:placetype":"locality"
},
  "geometry": {"coordinates":[109.48811000000001,27.31611],"type":"Point"}
}