{
  "type": "Feature",
  "properties": {
    "gn:admin1_code":"5.0",
    "gn:asciiname":"Erdao Hezicun",
    "gn:country_code":"CN",
    "gn:dem":534,
    "gn:feature_class":"P",
    "gn:feature_code":"PPL",
    "gn:name":"Erdao Hezicun",
    "gn:population":0,
    "gn:timezone":"Asia/Shanghai",
    "iso:country":"CN",
    "name:zho_x_preferred":[
        "\u4e8c\u9053\u6cb3\u5b50\u6751"
    ],
    "wof:name":"Erdao Hezicun",
    "wof:placetype":"locality"
},
  "geometry": {"coordinates":[128.52038000000002,43.25495],"type":"Point"}
}