{
  "type": "Feature",
  "properties": {
    "gn:admin1_code":"9.0",
    "gn:asciiname":"Songcuntun",
    "gn:country_code":"CN",
    "gn:dem":69,
    "gn:feature_class":"P",
    "gn:feature_code":"PPL",
    "gn:name":"Songcuntun",
    "gn:population":0,
    "gn:timezone":"Asia/Shanghai",
    "iso:country":"CN",
    "name:zho_x_preferred":[
        "\u5b8b\u6751\u5c6f"
    ],
    "wof:name":"Songcuntun",
    "wof:placetype":"locality"
},
  "geometry": {"coordinates":[114.48032000000001,36.12951],"type":"Point"}
}