{
  "type": "Feature",
  "properties": {
    "gn:admin1_code":"14.0",
    "gn:asciiname":"Bidacun",
    "gn:country_code":"CN",
    "gn:dem":2130,
    "gn:feature_class":"P",
    "gn:feature_code":"PPL",
    "gn:name":"Bidacun",
    "gn:population":0,
    "gn:timezone":"Asia/Urumqi",
    "iso:country":"CN",
    "name:zho_x_preferred":[
        "\u6bd5\u8fbe\u6751"
    ],
    "wof:name":"Bidacun",
    "wof:placetype":"locality"
},
  "geometry": {"coordinates":[96.55267000000001,29.03644],"type":"Point"}
}