{
  "type": "Feature",
  "properties": {
    "gn:admin1_code":"18",
    "gn:asciiname":"Wangjiaba",
    "gn:country_code":"CN",
    "gn:dem":1658,
    "gn:feature_class":"P",
    "gn:feature_code":"PPL",
    "gn:name":"Wangjiaba",
    "gn:population":0,
    "gn:timezone":"Asia/Shanghai",
    "iso:country":"CN",
    "name:zho_x_preferred":[
        "\u738b\u5bb6\u575d"
    ],
    "wof:name":"Wangjiaba",
    "wof:placetype":"locality"
},
  "geometry": {"coordinates":[104.893,26.6848],"type":"Point"}
}