{
  "type": "Feature",
  "properties": {
    "gn:admin1_code":"24",
    "gn:asciiname":"Hebian",
    "gn:cc2":"CN",
    "gn:country_code":"CN",
    "gn:dem":754,
    "gn:feature_class":"P",
    "gn:feature_code":"PPL",
    "gn:name":"Hebian",
    "gn:population":0,
    "gn:timezone":"Asia/Shanghai",
    "iso:country":"CN",
    "name:und_x_variant":[
        "Ho-pien-ts\u2019un",
        "Ho-pien",
        "Ho-pein-ts\u2019un",
        "Hebian"
    ],
    "wof:name":"Hebian",
    "wof:placetype":"locality"
},
  "geometry": {"coordinates":[113.10028,38.58972],"type":"Point"}
}