{
  "type": "Feature",
  "properties": {
    "gn:admin1_code":"29.0",
    "gn:asciiname":"Yunwushan",
    "gn:country_code":"CN",
    "gn:dem":2069,
    "gn:feature_class":"P",
    "gn:feature_code":"PPL",
    "gn:name":"Yunwushan",
    "gn:population":0,
    "gn:timezone":"Asia/Shanghai",
    "iso:country":"CN",
    "name:zho_x_preferred":[
        "\u4e91\u96fe\u5c71"
    ],
    "wof:name":"Yunwushan",
    "wof:placetype":"locality"
},
  "geometry": {"coordinates":[103.54300000000001,27.7811],"type":"Point"}
}