{
  "type": "Feature",
  "properties": {
    "gn:admin1_code":"32.0",
    "gn:asciiname":"Jinjiaqing",
    "gn:country_code":"CN",
    "gn:dem":1868,
    "gn:feature_class":"P",
    "gn:feature_code":"PPL",
    "gn:name":"Jinjiaqing",
    "gn:population":0,
    "gn:timezone":"Asia/Shanghai",
    "iso:country":"CN",
    "name:zho_x_preferred":[
        "\u91d1\u5bb6\u7b90"
    ],
    "wof:name":"Jinjiaqing",
    "wof:placetype":"locality"
},
  "geometry": {"coordinates":[102.18899999999999,26.522],"type":"Point"}
}