{
  "type": "Feature",
  "properties": {
    "gn:admin1_code":"30",
    "gn:asciiname":"Kantangcun",
    "gn:country_code":"CN",
    "gn:dem":13,
    "gn:feature_class":"P",
    "gn:feature_code":"PPL",
    "gn:name":"Kantangcun",
    "gn:population":0,
    "gn:timezone":"Asia/Urumqi",
    "iso:country":"CN",
    "name:zho_x_preferred":[
        "\u574e\u5858\u6751"
    ],
    "wof:name":"Kantangcun",
    "wof:placetype":"locality"
},
  "geometry": {"coordinates":[110.09978999999998,21.17295],"type":"Point"}
}