{
  "type": "Feature",
  "properties": {
    "gn:admin1_code":"5.0",
    "gn:asciiname":"Xiaohengdao",
    "gn:country_code":"CN",
    "gn:dem":604,
    "gn:feature_class":"P",
    "gn:feature_code":"PPL",
    "gn:name":"Xiaohengdao",
    "gn:population":0,
    "gn:timezone":"Asia/Shanghai",
    "iso:country":"CN",
    "name:zho_x_preferred":[
        "\u5c0f\u6a2a\u9053"
    ],
    "wof:name":"Xiaohengdao",
    "wof:placetype":"locality"
},
  "geometry": {"coordinates":[126.31957,41.81915],"type":"Point"}
}