{
  "type": "Feature",
  "properties": {
    "gn:admin1_code":"19.0",
    "gn:asciiname":"Xiaocuoyucun",
    "gn:country_code":"CN",
    "gn:dem":415,
    "gn:feature_class":"P",
    "gn:feature_code":"PPL",
    "gn:name":"Xiaocuoyucun",
    "gn:population":0,
    "gn:timezone":"Asia/Shanghai",
    "iso:country":"CN",
    "name:zho_x_preferred":[
        "\u5c0f\u9519\u5cea\u6751"
    ],
    "wof:name":"Xiaocuoyucun",
    "wof:placetype":"locality"
},
  "geometry": {"coordinates":[122.82599999999999,40.3566],"type":"Point"}
}