{
  "type": "Feature",
  "properties": {
    "gn:admin1_code":"12.0",
    "gn:asciiname":"Zhujiawuchang",
    "gn:country_code":"CN",
    "gn:dem":1038,
    "gn:feature_class":"P",
    "gn:feature_code":"PPL",
    "gn:name":"Zhujiawuchang",
    "gn:population":0,
    "gn:timezone":"Asia/Shanghai",
    "iso:country":"CN",
    "name:zho_x_preferred":[
        "\u6731\u5bb6\u5c4b\u573a"
    ],
    "wof:name":"Zhujiawuchang",
    "wof:placetype":"locality"
},
  "geometry": {"coordinates":[110.58194,30.20009000000001],"type":"Point"}
}