{
  "type": "Feature",
  "properties": {
    "gn:admin1_code":"14.0",
    "gn:asciiname":"Langzhu",
    "gn:country_code":"CN",
    "gn:dem":4562,
    "gn:feature_class":"P",
    "gn:feature_code":"PPL",
    "gn:name":"Langzhu",
    "gn:population":0,
    "gn:timezone":"Asia/Urumqi",
    "iso:country":"CN",
    "name:zho_x_preferred":[
        "\u6717\u73e0"
    ],
    "wof:name":"Langzhu",
    "wof:placetype":"locality"
},
  "geometry": {"coordinates":[88.316,28.3464],"type":"Point"}
}