{
  "type": "Feature",
  "properties": {
    "gn:admin1_code":"15.0",
    "gn:asciiname":"Sigounao",
    "gn:country_code":"CN",
    "gn:dem":2828,
    "gn:feature_class":"P",
    "gn:feature_code":"PPL",
    "gn:name":"Sigounao",
    "gn:population":0,
    "gn:timezone":"Asia/Shanghai",
    "iso:country":"CN",
    "name:zho_x_preferred":[
        "\u5bfa\u6c9f\u8111"
    ],
    "wof:name":"Sigounao",
    "wof:placetype":"locality"
},
  "geometry": {"coordinates":[102.994,36.9973],"type":"Point"}
}