{
  "type": "Feature",
  "properties": {
    "gn:admin1_code":"26.0",
    "gn:asciiname":"Wujia Huochangcun",
    "gn:country_code":"CN",
    "gn:dem":1206,
    "gn:feature_class":"P",
    "gn:feature_code":"PPL",
    "gn:name":"Wujia Huochangcun",
    "gn:population":0,
    "gn:timezone":"Asia/Shanghai",
    "iso:country":"CN",
    "name:zho_x_preferred":[
        "\u6b66\u5bb6\u4f19\u573a\u6751"
    ],
    "wof:name":"Wujia Huochangcun",
    "wof:placetype":"locality"
},
  "geometry": {"coordinates":[109.97799999999999,38.6514],"type":"Point"}
}