{
  "type": "Feature",
  "properties": {
    "gn:admin1_code":"29.0",
    "gn:asciiname":"Yongding",
    "gn:country_code":"CN",
    "gn:dem":1517,
    "gn:feature_class":"P",
    "gn:feature_code":"PPLA3",
    "gn:name":"Yongding",
    "gn:population":0,
    "gn:timezone":"Asia/Shanghai",
    "iso:country":"CN",
    "name:ara_x_preferred":[
        "\u064a\u0648\u0646\u063a\u062f\u064a\u0646\u063a"
    ],
    "name:ben_x_preferred":[
        "\u0987\u09af\u09bc\u0982\u09a1\u09bf\u0982"
    ],
    "name:ceb_x_preferred":[
        "Yongding"
    ],
    "name:deu_x_preferred":[
        "Yongding"
    ],
    "name:ell_x_preferred":[
        "\u0393\u03b9\u03bf\u03bd\u03b3\u03ba\u03bd\u03c4\u03af\u03bd\u03b3\u03ba"
    ],
    "name:fas_x_preferred":[
        "\u06cc\u0648\u0646\u06af\u062f\u06cc\u0646\u06af"
    ],
    "name:fra_x_preferred":[
        "Yongding"
    ],
    "name:heb_x_preferred":[
        "\u05d9\u05d0\u05e0\u05d2\u05d3\u05d9\u05e0\u05d2"
    ],
    "name:hin_x_preferred":[
        "\u092f\u094b\u0902\u0917\u0921\u093f\u0902\u0917"
    ],
    "name:hun_x_preferred":[
        "Yongding"
    ],
    "name:nld_x_preferred":[
        "Yongding"
    ],
    "name:nor_x_preferred":[
        "Yongding"
    ],
    "name:por_x_preferred":[
        "Yongding"
    ],
    "name:spa_x_preferred":[
        "Yongding"
    ],
    "name:swe_x_preferred":[
        "Yongding"
    ],
    "name:tur_x_preferred":[
        "Yongding"
    ],
    "name:und_x_variant":[
        "Chucho",
        "Yongren",
        "Yung-jen",
        "Chuchih",
        "Yung-jen-hsien",
        "Yung-ting-chen"
    ],
    "name:urd_x_preferred":[
        "\u06cc\u0648\u0646\u06af \u0688\u0646\u06af"
    ],
    "name:zho_x_preferred":[
        "\u6c38\u5b9a"
    ],
    "name:zho_x_variant":[
        "Ch\u00fc-ch\u00fceh"
    ],
    "wof:name":"Yongding",
    "wof:placetype":"locality"
},
  "geometry": {"coordinates":[101.68642,26.04122],"type":"Point"}
}