{
  "type": "Feature",
  "properties": {
    "gn:admin1_code":"29.0",
    "gn:asciiname":"Yongding",
    "gn:country_code":"CN",
    "gn:dem":1517,
    "gn:feature_class":"P",
    "gn:feature_code":"PPLA3",
    "gn:name":"Yongding",
    "gn:population":0,
    "gn:timezone":"Asia/Shanghai",
    "iso:country":"CN",
    "name:und_x_variant":[
        "Chucho",
        "Yongren",
        "Ch\u00fc-ch\u00fceh",
        "Yung-jen",
        "Chuchih",
        "Yung-jen-hsien",
        "Yung-ting-chen",
        "Yongding"
    ],
    "name:zho_x_preferred":[
        "\u6c38\u5b9a"
    ],
    "name:zho_x_variant":[
        "Ch\u00fc-ch\u00fceh"
    ],
    "wof:name":"Yongding",
    "wof:placetype":"locality"
},
  "geometry": {"coordinates":[101.68642,26.04122000000001],"type":"Point"}
}