{
  "type": "Feature",
  "properties": {
    "gn:admin1_code":"11.0",
    "gn:asciiname":"Xinhequ",
    "gn:country_code":"CN",
    "gn:dem":31,
    "gn:feature_class":"P",
    "gn:feature_code":"PPL",
    "gn:name":"Xinhequ",
    "gn:population":0,
    "gn:timezone":"Asia/Shanghai",
    "iso:country":"CN",
    "name:zho_x_preferred":[
        "\u65b0\u6cb3\u533a"
    ],
    "wof:name":"Xinhequ",
    "wof:placetype":"locality"
},
  "geometry": {"coordinates":[113.01794,29.48838],"type":"Point"}
}