{
  "type": "Feature",
  "properties": {
    "gn:admin1_code":"29.0",
    "gn:asciiname":"Bajiaoqing",
    "gn:country_code":"CN",
    "gn:dem":2268,
    "gn:feature_class":"P",
    "gn:feature_code":"PPL",
    "gn:name":"Bajiaoqing",
    "gn:population":0,
    "gn:timezone":"Asia/Shanghai",
    "iso:country":"CN",
    "name:zho_x_preferred":[
        "\u82ad\u8549\u7b90"
    ],
    "wof:name":"Bajiaoqing",
    "wof:placetype":"locality"
},
  "geometry": {"coordinates":[101.944,25.3943],"type":"Point"}
}