{
  "type": "Feature",
  "properties": {
    "gn:admin1_code":"25.0",
    "gn:asciiname":"Qiaojiawacun",
    "gn:country_code":"CN",
    "gn:dem":19,
    "gn:feature_class":"P",
    "gn:feature_code":"PPL",
    "gn:name":"Qiaojiawacun",
    "gn:population":0,
    "gn:timezone":"Asia/Shanghai",
    "iso:country":"CN",
    "name:zho_x_preferred":[
        "\u4e54\u5bb6\u6d3c\u6751"
    ],
    "wof:name":"Qiaojiawacun",
    "wof:placetype":"locality"
},
  "geometry": {"coordinates":[120.01898,35.79279000000001],"type":"Point"}
}