{
  "type": "Feature",
  "properties": {
    "gn:admin1_code":"4.0",
    "gn:asciiname":"Mengxuzi",
    "gn:country_code":"CN",
    "gn:dem":38,
    "gn:feature_class":"P",
    "gn:feature_code":"PPL",
    "gn:name":"Mengxuzi",
    "gn:population":0,
    "gn:timezone":"Asia/Shanghai",
    "iso:country":"CN",
    "name:zho_x_preferred":[
        "\u5b5f\u5729\u5b50"
    ],
    "wof:name":"Mengxuzi",
    "wof:placetype":"locality"
},
  "geometry": {"coordinates":[118.28,34.1675],"type":"Point"}
}