{
  "type": "Feature",
  "properties": {
    "gn:admin1_code":"10",
    "gn:asciiname":"Yu'ershan",
    "gn:country_code":"CN",
    "gn:dem":1462,
    "gn:feature_class":"P",
    "gn:feature_code":"PPL",
    "gn:name":"Yu\u2019ershan",
    "gn:population":0,
    "gn:timezone":"Asia/Shanghai",
    "iso:country":"CN",
    "name:und_x_variant":[
        "P\u2019ing-an-pao",
        "Ping\u2019anbu",
        "Yu\u2019ershan"
    ],
    "wof:name":"Yu'ershan",
    "wof:placetype":"locality"
},
  "geometry": {"coordinates":[116.15806000000001,41.75361],"type":"Point"}
}