{
  "type": "Feature",
  "properties": {
    "gn:admin1_code":"4.0",
    "gn:asciiname":"Nongzhuangcun",
    "gn:country_code":"CN",
    "gn:dem":16,
    "gn:feature_class":"P",
    "gn:feature_code":"PPL",
    "gn:name":"Nongzhuangcun",
    "gn:population":0,
    "gn:timezone":"Asia/Shanghai",
    "iso:country":"CN",
    "name:zho_x_preferred":[
        "\u519c\u5e84\u6751"
    ],
    "wof:name":"Nongzhuangcun",
    "wof:placetype":"locality"
},
  "geometry": {"coordinates":[118.64752,33.89471],"type":"Point"}
}