{
  "type": "Feature",
  "properties": {
    "gn:admin1_code":"18",
    "gn:asciiname":"Panjiagou",
    "gn:country_code":"CN",
    "gn:dem":1065,
    "gn:feature_class":"P",
    "gn:feature_code":"PPL",
    "gn:name":"Panjiagou",
    "gn:population":0,
    "gn:timezone":"Asia/Shanghai",
    "iso:country":"CN",
    "name:zho_x_preferred":[
        "\u6f58\u5bb6\u6c9f"
    ],
    "wof:name":"Panjiagou",
    "wof:placetype":"locality"
},
  "geometry": {"coordinates":[107.21599999999999,27.9399],"type":"Point"}
}