{
  "type": "Feature",
  "properties": {
    "gn:admin1_code":"32.0",
    "gn:asciiname":"Sihejing",
    "gn:country_code":"CN",
    "gn:dem":2330,
    "gn:feature_class":"P",
    "gn:feature_code":"PPL",
    "gn:name":"Sihejing",
    "gn:population":0,
    "gn:timezone":"Asia/Shanghai",
    "iso:country":"CN",
    "name:zho_x_preferred":[
        "\u56db\u5408\u4e95"
    ],
    "wof:name":"Sihejing",
    "wof:placetype":"locality"
},
  "geometry": {"coordinates":[102.77500000000001,28.2692],"type":"Point"}
}