{
  "type": "Feature",
  "properties": {
    "gn:admin1_code":"10.0",
    "gn:asciiname":"Dusi",
    "gn:country_code":"CN",
    "gn:dem":61,
    "gn:feature_class":"P",
    "gn:feature_code":"PPL",
    "gn:name":"Dusi",
    "gn:population":0,
    "gn:timezone":"Asia/Shanghai",
    "iso:country":"CN",
    "name:und_x_variant":[
        "\u675c\u5bfa"
    ],
    "wof:name":"Dusi",
    "wof:placetype":"locality"
},
  "geometry": {"coordinates":[114.89288000000001,38.38079000000001],"type":"Point"}
}