{
  "type": "Feature",
  "properties": {
    "gn:admin1_code":"19.0",
    "gn:asciiname":"Dabuqiyan",
    "gn:country_code":"CN",
    "gn:dem":562,
    "gn:feature_class":"P",
    "gn:feature_code":"PPL",
    "gn:name":"Dabuqiyan",
    "gn:population":0,
    "gn:timezone":"Asia/Shanghai",
    "iso:country":"CN",
    "name:und_x_variant":[
        "\u5927\u4e0d\u8d77\u773c"
    ],
    "name:zho_x_preferred":[
        "\u5927\u4e0d\u8d77\u773c"
    ],
    "wof:name":"Dabuqiyan",
    "wof:placetype":"locality"
},
  "geometry": {"coordinates":[124.86807,41.45187],"type":"Point"}
}