{
  "type": "Feature",
  "properties": {
    "gn:admin1_code":"12.0",
    "gn:asciiname":"Xiheling",
    "gn:country_code":"CN",
    "gn:dem":24,
    "gn:feature_class":"P",
    "gn:feature_code":"PPL",
    "gn:name":"Xiheling",
    "gn:population":0,
    "gn:timezone":"Asia/Shanghai",
    "iso:country":"CN",
    "name:zho_x_preferred":[
        "\u897f\u6cb3\u5cad"
    ],
    "wof:name":"Xiheling",
    "wof:placetype":"locality"
},
  "geometry": {"coordinates":[113.35963,30.16338],"type":"Point"}
}