{
  "type": "Feature",
  "properties": {
    "gn:admin1_code":"5.0",
    "gn:asciiname":"Fuxingcun",
    "gn:country_code":"CN",
    "gn:dem":280,
    "gn:feature_class":"P",
    "gn:feature_code":"PPL",
    "gn:name":"Fuxingcun",
    "gn:population":0,
    "gn:timezone":"Asia/Shanghai",
    "iso:country":"CN",
    "name:zho_x_preferred":[
        "\u798f\u5174\u6751"
    ],
    "wof:name":"Fuxingcun",
    "wof:placetype":"locality"
},
  "geometry": {"coordinates":[126.86212999999999,43.13597],"type":"Point"}
}