{
  "type": "Feature",
  "properties": {
    "gn:admin1_code":"4.0",
    "gn:asciiname":"Chengsheng",
    "gn:country_code":"CN",
    "gn:dem":5,
    "gn:feature_class":"P",
    "gn:feature_code":"PPL",
    "gn:name":"Chengsheng",
    "gn:population":0,
    "gn:timezone":"Asia/Shanghai",
    "iso:country":"CN",
    "name:zho_x_preferred":[
        "\u4e58\u80dc"
    ],
    "wof:name":"Chengsheng",
    "wof:placetype":"locality"
},
  "geometry": {"coordinates":[120.50163000000001,32.69022],"type":"Point"}
}