{
  "type": "Feature",
  "properties": {
    "gn:admin1_code":"26.0",
    "gn:asciiname":"Qianyaokou",
    "gn:country_code":"CN",
    "gn:dem":1447,
    "gn:feature_class":"P",
    "gn:feature_code":"PPL",
    "gn:name":"Qianyaokou",
    "gn:population":0,
    "gn:timezone":"Asia/Shanghai",
    "iso:country":"CN",
    "name:zho_x_preferred":[
        "\u524d\u7a91\u53e3"
    ],
    "wof:name":"Qianyaokou",
    "wof:placetype":"locality"
},
  "geometry": {"coordinates":[109.84636,35.5601],"type":"Point"}
}