{
  "type": "Feature",
  "properties": {
    "gn:admin1_code":"26.0",
    "gn:asciiname":"Qiuwacun",
    "gn:country_code":"CN",
    "gn:dem":985,
    "gn:feature_class":"P",
    "gn:feature_code":"PPL",
    "gn:name":"Qiuwacun",
    "gn:population":0,
    "gn:timezone":"Asia/Shanghai",
    "iso:country":"CN",
    "name:zho_x_preferred":[
        "\u6e6b\u6d3c\u6751"
    ],
    "wof:name":"Qiuwacun",
    "wof:placetype":"locality"
},
  "geometry": {"coordinates":[109.32195,35.19583],"type":"Point"}
}