{
  "type": "Feature",
  "properties": {
    "gn:admin1_code":"5.0",
    "gn:asciiname":"Zhoujia Wobucun",
    "gn:country_code":"CN",
    "gn:dem":135,
    "gn:feature_class":"P",
    "gn:feature_code":"PPL",
    "gn:name":"Zhoujia Wobucun",
    "gn:population":0,
    "gn:timezone":"Asia/Shanghai",
    "iso:country":"CN",
    "name:zho_x_preferred":[
        "\u5468\u5bb6\u7a9d\u5821\u6751"
    ],
    "wof:name":"Zhoujia Wobucun",
    "wof:placetype":"locality"
},
  "geometry": {"coordinates":[124.12488,43.71667],"type":"Point"}
}