{
  "type": "Feature",
  "properties": {
    "gn:admin1_code":"18",
    "gn:asciiname":"Luoni",
    "gn:country_code":"CN",
    "gn:dem":1736,
    "gn:feature_class":"P",
    "gn:feature_code":"PPL",
    "gn:name":"Luoni",
    "gn:population":0,
    "gn:timezone":"Asia/Shanghai",
    "iso:country":"CN",
    "name:zho_x_preferred":[
        "\u843d\u6ce5"
    ],
    "wof:name":"Luoni",
    "wof:placetype":"locality"
},
  "geometry": {"coordinates":[104.898,25.6471],"type":"Point"}
}