{
  "type": "Feature",
  "properties": {
    "gn:admin1_code":"24.0",
    "gn:asciiname":"Xuejiagang",
    "gn:country_code":"CN",
    "gn:dem":1363,
    "gn:feature_class":"P",
    "gn:feature_code":"PPL",
    "gn:name":"Xuejiagang",
    "gn:population":0,
    "gn:timezone":"Asia/Shanghai",
    "iso:country":"CN",
    "name:zho_x_preferred":[
        "\u859b\u5bb6\u6e2f"
    ],
    "wof:name":"Xuejiagang",
    "wof:placetype":"locality"
},
  "geometry": {"coordinates":[112.48457000000001,39.56038],"type":"Point"}
}