{
  "type": "Feature",
  "properties": {
    "gn:admin1_code":"18.0",
    "gn:asciiname":"Chahe",
    "gn:country_code":"CN",
    "gn:dem":1493,
    "gn:feature_class":"P",
    "gn:feature_code":"PPL",
    "gn:name":"Chahe",
    "gn:population":0,
    "gn:timezone":"Asia/Shanghai",
    "iso:country":"CN",
    "name:ceb_x_preferred":[
        "Chahe"
    ],
    "name:swe_x_preferred":[
        "Chahe"
    ],
    "wof:name":"Chahe",
    "wof:placetype":"locality"
},
  "geometry": {"coordinates":[105.49833,27.07389],"type":"Point"}
}