{
  "type": "Feature",
  "properties": {
    "gn:admin1_code":"29.0",
    "gn:asciiname":"Jinlonggou",
    "gn:country_code":"CN",
    "gn:dem":1855,
    "gn:feature_class":"P",
    "gn:feature_code":"PPL",
    "gn:name":"Jinlonggou",
    "gn:population":0,
    "gn:timezone":"Asia/Shanghai",
    "iso:country":"CN",
    "name:zho_x_preferred":[
        "\u91d1\u9f99\u6c9f"
    ],
    "wof:name":"Jinlonggou",
    "wof:placetype":"locality"
},
  "geometry": {"coordinates":[103.84699999999999,25.565],"type":"Point"}
}