{
  "type": "Feature",
  "properties": {
    "gn:admin1_code":"14.0",
    "gn:asciiname":"Gangdoi",
    "gn:country_code":"CN",
    "gn:dem":2828,
    "gn:feature_class":"P",
    "gn:feature_code":"PPL",
    "gn:name":"Gangdoi",
    "gn:population":0,
    "gn:timezone":"Asia/Urumqi",
    "iso:country":"CN",
    "name:bod_x_preferred":[
        "Gangdoi"
    ],
    "name:zho_x_preferred":[
        "Gangdui"
    ],
    "name:zho_x_variant":[
        "\u5c97\u5806",
        "Gang Gongshe",
        "\u5c97\u516c\u793e"
    ],
    "wof:name":"Gangdoi",
    "wof:placetype":"locality"
},
  "geometry": {"coordinates":[95.59435999999999,29.87309],"type":"Point"}
}