{
  "type": "Feature",
  "properties": {
    "gn:admin1_code":"16.0",
    "gn:asciiname":"Shangxinwu",
    "gn:country_code":"CN",
    "gn:dem":363,
    "gn:feature_class":"P",
    "gn:feature_code":"PPL",
    "gn:name":"Shangxinwu",
    "gn:population":0,
    "gn:timezone":"Asia/Shanghai",
    "iso:country":"CN",
    "name:zho_x_preferred":[
        "\u4e0a\u65b0\u5c4b"
    ],
    "wof:name":"Shangxinwu",
    "wof:placetype":"locality"
},
  "geometry": {"coordinates":[109.691,22.3353],"type":"Point"}
}