{
  "type": "Feature",
  "properties": {
    "gn:admin1_code":"29.0",
    "gn:asciiname":"Xiaoluojiazhai",
    "gn:country_code":"CN",
    "gn:dem":1350,
    "gn:feature_class":"P",
    "gn:feature_code":"PPL",
    "gn:name":"Xiaoluojiazhai",
    "gn:population":0,
    "gn:timezone":"Asia/Shanghai",
    "iso:country":"CN",
    "name:zho_x_preferred":[
        "\u5c0f\u7f57\u5bb6\u5be8"
    ],
    "wof:name":"Xiaoluojiazhai",
    "wof:placetype":"locality"
},
  "geometry": {"coordinates":[99.6143,24.2767],"type":"Point"}
}