{
  "type": "Feature",
  "properties": {
    "gn:admin1_code":"26",
    "gn:asciiname":"Guanzhuang",
    "gn:country_code":"CN",
    "gn:dem":994,
    "gn:feature_class":"P",
    "gn:feature_code":"PPL",
    "gn:name":"Guanzhuang",
    "gn:population":0,
    "gn:timezone":"Asia/Shanghai",
    "iso:country":"CN",
    "name:und_x_variant":[
        "\u5b98\u5e84"
    ],
    "name:zho_x_preferred":[
        "\u5b98\u5e84"
    ],
    "wof:name":"Guanzhuang",
    "wof:placetype":"locality"
},
  "geometry": {"coordinates":[108.69917,34.8475],"type":"Point"}
}