{
  "type": "Feature",
  "properties": {
    "gn:admin1_code":"29.0",
    "gn:asciiname":"Shuihaizi",
    "gn:country_code":"CN",
    "gn:dem":1915,
    "gn:feature_class":"P",
    "gn:feature_code":"PPL",
    "gn:name":"Shuihaizi",
    "gn:population":0,
    "gn:timezone":"Asia/Shanghai",
    "iso:country":"CN",
    "name:zho_x_preferred":[
        "\u6c34\u6d77\u5b50"
    ],
    "wof:name":"Shuihaizi",
    "wof:placetype":"locality"
},
  "geometry": {"coordinates":[103.218,25.3469],"type":"Point"}
}