{
  "type": "Feature",
  "properties": {
    "gn:admin1_code":"12.0",
    "gn:asciiname":"Nanying Jiahaopo",
    "gn:country_code":"CN",
    "gn:dem":31,
    "gn:feature_class":"P",
    "gn:feature_code":"PPL",
    "gn:name":"Nanying Jiahaopo",
    "gn:population":0,
    "gn:timezone":"Asia/Shanghai",
    "iso:country":"CN",
    "name:zho_x_preferred":[
        "\u5357\u5e94\u5bb6\u58d5\u5761"
    ],
    "wof:name":"Nanying Jiahaopo",
    "wof:placetype":"locality"
},
  "geometry": {"coordinates":[112.39046999999999,30.1834],"type":"Point"}
}