{
  "type": "Feature",
  "properties": {
    "gn:admin1_code":"11.0",
    "gn:asciiname":"Zouchongtang",
    "gn:country_code":"CN",
    "gn:dem":193,
    "gn:feature_class":"P",
    "gn:feature_code":"PPL",
    "gn:name":"Zouchongtang",
    "gn:population":0,
    "gn:timezone":"Asia/Shanghai",
    "iso:country":"CN",
    "name:zho_x_preferred":[
        "\u90b9\u51b2\u5858"
    ],
    "wof:name":"Zouchongtang",
    "wof:placetype":"locality"
},
  "geometry": {"coordinates":[112.0134,28.05904],"type":"Point"}
}