{
  "type": "Feature",
  "properties": {
    "gn:admin1_code":"12.0",
    "gn:asciiname":"Hebeizui",
    "gn:country_code":"CN",
    "gn:dem":130,
    "gn:feature_class":"P",
    "gn:feature_code":"PPL",
    "gn:name":"Hebeizui",
    "gn:population":0,
    "gn:timezone":"Asia/Shanghai",
    "iso:country":"CN",
    "name:zho_x_preferred":[
        "\u6cb3\u80cc\u5480"
    ],
    "wof:name":"Hebeizui",
    "wof:placetype":"locality"
},
  "geometry": {"coordinates":[114.22735,31.31013],"type":"Point"}
}