{
  "type": "Feature",
  "properties": {
    "gn:admin1_code":"12.0",
    "gn:asciiname":"Huojiawan",
    "gn:country_code":"CN",
    "gn:dem":907,
    "gn:feature_class":"P",
    "gn:feature_code":"PPL",
    "gn:name":"Huojiawan",
    "gn:population":0,
    "gn:timezone":"Asia/Shanghai",
    "iso:country":"CN",
    "name:zho_x_preferred":[
        "\u970d\u5bb6\u6e7e"
    ],
    "wof:name":"Huojiawan",
    "wof:placetype":"locality"
},
  "geometry": {"coordinates":[111.54037,31.41036],"type":"Point"}
}