{
  "type": "Feature",
  "properties": {
    "gn:admin1_code":"15.0",
    "gn:asciiname":"Ao'ao",
    "gn:country_code":"CN",
    "gn:dem":2344,
    "gn:feature_class":"P",
    "gn:feature_code":"PPL",
    "gn:name":"Ao\u2019ao",
    "gn:population":0,
    "gn:timezone":"Asia/Shanghai",
    "iso:country":"CN",
    "name:und_x_variant":[
        "Ao\u2019ao",
        "\u50b2\u50b2"
    ],
    "wof:name":"Ao'ao",
    "wof:placetype":"locality"
},
  "geometry": {"coordinates":[103.28867,34.02318],"type":"Point"}
}