{
  "type": "Feature",
  "properties": {
    "gn:admin1_code":"5.0",
    "gn:asciiname":"Madanggou",
    "gn:country_code":"CN",
    "gn:dem":517,
    "gn:feature_class":"P",
    "gn:feature_code":"PPL",
    "gn:name":"Madanggou",
    "gn:population":0,
    "gn:timezone":"Asia/Shanghai",
    "iso:country":"CN",
    "name:und_x_variant":[
        "\u9a6c\u5f53\u6c9f"
    ],
    "wof:name":"Madanggou",
    "wof:placetype":"locality"
},
  "geometry": {"coordinates":[125.88593,41.84692],"type":"Point"}
}