{
  "type": "Feature",
  "properties": {
    "gn:admin1_code":"30",
    "gn:asciiname":"Dalang",
    "gn:country_code":"CN",
    "gn:dem":5,
    "gn:feature_class":"P",
    "gn:feature_code":"PPL",
    "gn:name":"Dalang",
    "gn:population":0,
    "gn:timezone":"Asia/Urumqi",
    "iso:country":"CN",
    "name:ceb_x_preferred":[
        "Dalang"
    ],
    "name:deu_x_preferred":[
        "Dalang"
    ],
    "name:nld_x_preferred":[
        "Dalang"
    ],
    "name:sco_x_preferred":[
        "Dalang"
    ],
    "name:swe_x_preferred":[
        "Dalang"
    ],
    "name:zho_x_preferred":[
        "\u5927\u6d6a"
    ],
    "wof:name":"Dalang",
    "wof:placetype":"locality"
},
  "geometry": {"coordinates":[110.5997,20.94301],"type":"Point"}
}