{
  "type": "Feature",
  "properties": {
    "gn:admin1_code":"32.0",
    "gn:asciiname":"Shuijingyin",
    "gn:country_code":"CN",
    "gn:dem":696,
    "gn:feature_class":"P",
    "gn:feature_code":"PPL",
    "gn:name":"Shuijingyin",
    "gn:population":0,
    "gn:timezone":"Asia/Shanghai",
    "iso:country":"CN",
    "name:zho_x_preferred":[
        "\u6c34\u4e95\u94f6"
    ],
    "wof:name":"Shuijingyin",
    "wof:placetype":"locality"
},
  "geometry": {"coordinates":[107.59827,31.67305],"type":"Point"}
}