{
  "type": "Feature",
  "properties": {
    "gn:admin1_code":"4.0",
    "gn:asciiname":"Linhuaicun",
    "gn:country_code":"CN",
    "gn:dem":2,
    "gn:feature_class":"P",
    "gn:feature_code":"PPL",
    "gn:name":"Linhuaicun",
    "gn:population":0,
    "gn:timezone":"Asia/Shanghai",
    "iso:country":"CN",
    "name:zho_x_preferred":[
        "\u4e34\u6dee\u6751"
    ],
    "wof:name":"Linhuaicun",
    "wof:placetype":"locality"
},
  "geometry": {"coordinates":[119.96411000000001,34.22052],"type":"Point"}
}