{
  "type": "Feature",
  "properties": {
    "gn:admin1_code":"11.0",
    "gn:asciiname":"Xiazhoujing",
    "gn:country_code":"CN",
    "gn:dem":513,
    "gn:feature_class":"P",
    "gn:feature_code":"PPL",
    "gn:name":"Xiazhoujing",
    "gn:population":0,
    "gn:timezone":"Asia/Shanghai",
    "iso:country":"CN",
    "name:zho_x_preferred":[
        "\u4e0b\u821f\u5883"
    ],
    "wof:name":"Xiazhoujing",
    "wof:placetype":"locality"
},
  "geometry": {"coordinates":[112.46988,25.41559],"type":"Point"}
}