{
  "type": "Feature",
  "properties": {
    "gn:admin1_code":"3",
    "gn:asciiname":"Taiping",
    "gn:country_code":"CN",
    "gn:dem":282,
    "gn:feature_class":"P",
    "gn:feature_code":"PPL",
    "gn:name":"Taiping",
    "gn:population":0,
    "gn:timezone":"Asia/Shanghai",
    "iso:country":"CN",
    "wof:name":"Taiping",
    "wof:placetype":"locality"
},
  "geometry": {"coordinates":[115.38806,25.26722],"type":"Point"}
}