{
  "type": "Feature",
  "properties": {
    "gn:admin1_code":"11.0",
    "gn:asciiname":"Lujianhe",
    "gn:country_code":"CN",
    "gn:dem":57,
    "gn:feature_class":"P",
    "gn:feature_code":"PPL",
    "gn:name":"Lujianhe",
    "gn:population":0,
    "gn:timezone":"Asia/Shanghai",
    "iso:country":"CN",
    "name:zho_x_preferred":[
        "\u82a6\u7bad\u6cb3"
    ],
    "wof:name":"Lujianhe",
    "wof:placetype":"locality"
},
  "geometry": {"coordinates":[113.31331000000002,28.84634],"type":"Point"}
}