{
  "type": "Feature",
  "properties": {
    "gn:admin1_code":"19.0",
    "gn:asciiname":"Shabaozi",
    "gn:country_code":"CN",
    "gn:dem":2,
    "gn:feature_class":"P",
    "gn:feature_code":"PPL",
    "gn:name":"Shabaozi",
    "gn:population":0,
    "gn:timezone":"Asia/Shanghai",
    "iso:country":"CN",
    "name:zho_x_preferred":[
        "\u6c99\u5305\u5b50"
    ],
    "wof:name":"Shabaozi",
    "wof:placetype":"locality"
},
  "geometry": {"coordinates":[122.715,39.2401],"type":"Point"}
}