{
  "type": "Feature",
  "properties": {
    "iso:country":"CN",
    "qs:name":"\u9edf\u53bf",
    "qs:name_adm0":"\u4e2d\u570b",
    "qs:name_adm1":"\u5b89\u5fbd\u7701",
    "qs:photos":56,
    "qs:photos_1k":11,
    "qs:photos_9k":2,
    "qs:photos_9r":5,
    "qs:photos_all":357,
    "qs:photos_sr":2,
    "qs:placetype":"LocalAdmin",
    "qs:pop_sr":"0",
    "wd:wordcount":172,
    "wof:name":"\u9edf\u53bf",
    "wof:placetype":"localadmin"
},
  "geometry": {"coordinates":[117.982944,29.912802],"type":"Point"}
}