{
  "type": "Feature",
  "properties": {
    "iso:country":"CN",
    "name:ceb_x_preferred":[
        "Yi Xian"
    ],
    "name:deu_x_preferred":[
        "Yi"
    ],
    "name:eng_x_preferred":[
        "Yi County"
    ],
    "name:fas_x_preferred":[
        "\u0634\u0647\u0631\u0633\u062a\u0627\u0646 \u06cc\u06cc"
    ],
    "name:gan_x_preferred":[
        "\u9edf\u53bf"
    ],
    "name:ind_x_preferred":[
        "County Yi"
    ],
    "name:jpn_x_preferred":[
        "\u30a4\u770c"
    ],
    "name:kor_x_preferred":[
        "\uc774\ud604"
    ],
    "name:mwl_x_preferred":[
        "Yi"
    ],
    "name:nan_x_preferred":[
        "\u00c8-ko\u0101n"
    ],
    "name:nld_x_preferred":[
        "Yi"
    ],
    "name:nob_x_preferred":[
        "Yi"
    ],
    "name:pol_x_preferred":[
        "Yi"
    ],
    "name:rus_x_preferred":[
        "\u0418\u0441\u044f\u043d\u044c"
    ],
    "name:spa_x_preferred":[
        "Y\u012b Xi\u00e0n"
    ],
    "name:swe_x_preferred":[
        "Yi"
    ],
    "name:wuu_x_preferred":[
        "\u9edf\u53bf"
    ],
    "name:yue_x_preferred":[
        "\u9edf\u7e23"
    ],
    "name:zho_x_preferred":[
        "\u9edf\u53bf"
    ],
    "qs:name":"\u9edf\u53bf",
    "qs:name_adm0":"\u4e2d\u570b",
    "qs:name_adm1":"\u5b89\u5fbd\u7701",
    "qs:photos":56,
    "qs:photos_1k":11,
    "qs:photos_9k":2,
    "qs:photos_9r":5,
    "qs:photos_all":357,
    "qs:photos_sr":2,
    "qs:placetype":"LocalAdmin",
    "qs:pop_sr":"0",
    "wd:wordcount":172,
    "wof:name":"\u9edf\u53bf",
    "wof:placetype":"localadmin"
},
  "geometry": {"coordinates":[117.982944,29.912802],"type":"Point"}
}