{
  "type": "Feature",
  "properties": {
    "gn:admin1_code":"29",
    "gn:asciiname":"Kafangjiao",
    "gn:country_code":"CN",
    "gn:dem":1173,
    "gn:feature_class":"P",
    "gn:feature_code":"PPL",
    "gn:name":"Kafangjiao",
    "gn:population":0,
    "gn:timezone":"Asia/Shanghai",
    "iso:country":"CN",
    "name:zho_x_preferred":[
        "\u5361\u623f\u811a"
    ],
    "wof:name":"Kafangjiao",
    "wof:placetype":"locality"
},
  "geometry": {"coordinates":[104.663,22.8415],"type":"Point"}
}