{
  "type": "Feature",
  "properties": {
    "gn:admin1_code":"16",
    "gn:asciiname":"Tiantangling",
    "gn:country_code":"CN",
    "gn:dem":200,
    "gn:feature_class":"P",
    "gn:feature_code":"PPL",
    "gn:name":"Tiantangling",
    "gn:population":0,
    "gn:timezone":"Asia/Shanghai",
    "iso:country":"CN",
    "name:zho_x_preferred":[
        "\u5929\u5802\u5cad"
    ],
    "wof:name":"Tiantangling",
    "wof:placetype":"locality"
},
  "geometry": {"coordinates":[110.584,24.9392],"type":"Point"}
}