{
  "type": "Feature",
  "properties": {
    "gn:admin1_code":"4.0",
    "gn:asciiname":"Fengyuncun",
    "gn:country_code":"CN",
    "gn:dem":28,
    "gn:feature_class":"P",
    "gn:feature_code":"PPL",
    "gn:name":"Fengyuncun",
    "gn:population":0,
    "gn:timezone":"Asia/Shanghai",
    "iso:country":"CN",
    "name:zho_x_preferred":[
        "\u51e4\u4e91\u6751"
    ],
    "wof:name":"Fengyuncun",
    "wof:placetype":"locality"
},
  "geometry": {"coordinates":[118.48389,34.23132],"type":"Point"}
}