{
  "type": "Feature",
  "properties": {
    "gn:admin1_code":"29.0",
    "gn:asciiname":"Xianshenmiao",
    "gn:country_code":"CN",
    "gn:dem":2474,
    "gn:feature_class":"P",
    "gn:feature_code":"PPL",
    "gn:name":"Xianshenmiao",
    "gn:population":0,
    "gn:timezone":"Asia/Shanghai",
    "iso:country":"CN",
    "name:zho_x_preferred":[
        "\u4ed9\u795e\u5e99"
    ],
    "wof:name":"Xianshenmiao",
    "wof:placetype":"locality"
},
  "geometry": {"coordinates":[99.1117,25.7849],"type":"Point"}
}