{
  "type": "Feature",
  "properties": {
    "gn:admin1_code":"16.0",
    "gn:asciiname":"Nagui Xinpo",
    "gn:country_code":"CN",
    "gn:dem":132,
    "gn:feature_class":"P",
    "gn:feature_code":"PPL",
    "gn:name":"Nagui Xinpo",
    "gn:population":0,
    "gn:timezone":"Asia/Shanghai",
    "iso:country":"CN",
    "name:zho_x_preferred":[
        "\u90a3\u8d35\u65b0\u5761"
    ],
    "wof:name":"Nagui Xinpo",
    "wof:placetype":"locality"
},
  "geometry": {"coordinates":[108.59099999999999,22.7601],"type":"Point"}
}