{
  "type": "Feature",
  "properties": {
    "gn:admin1_code":"5.0",
    "gn:asciiname":"Housimen Wangjia",
    "gn:country_code":"CN",
    "gn:dem":200,
    "gn:feature_class":"P",
    "gn:feature_code":"PPL",
    "gn:name":"Housimen Wangjia",
    "gn:population":0,
    "gn:timezone":"Asia/Shanghai",
    "iso:country":"CN",
    "name:zho_x_preferred":[
        "\u540e\u56db\u95e8\u738b\u5bb6"
    ],
    "wof:name":"Housimen Wangjia",
    "wof:placetype":"locality"
},
  "geometry": {"coordinates":[124.25612,44.29304000000001],"type":"Point"}
}