{
  "type": "Feature",
  "properties": {
    "gn:admin1_code":"12.0",
    "gn:asciiname":"Guanmutang",
    "gn:country_code":"CN",
    "gn:dem":77,
    "gn:feature_class":"P",
    "gn:feature_code":"PPL",
    "gn:name":"Guanmutang",
    "gn:population":0,
    "gn:timezone":"Asia/Shanghai",
    "iso:country":"CN",
    "name:zho_x_preferred":[
        "\u5b98\u6728\u5858"
    ],
    "wof:name":"Guanmutang",
    "wof:placetype":"locality"
},
  "geometry": {"coordinates":[114.54850999999999,31.10588],"type":"Point"}
}