{
  "type": "Feature",
  "properties": {
    "gn:admin1_code":"30.0",
    "gn:asciiname":"Andu",
    "gn:country_code":"CN",
    "gn:dem":32,
    "gn:feature_class":"P",
    "gn:feature_code":"PPL",
    "gn:name":"Andu",
    "gn:population":0,
    "gn:timezone":"Asia/Shanghai",
    "iso:country":"CN",
    "name:zho_x_preferred":[
        "\u6697\u5835"
    ],
    "wof:name":"Andu",
    "wof:placetype":"locality"
},
  "geometry": {"coordinates":[112.12430000000001,21.87318],"type":"Point"}
}