{
  "type": "Feature",
  "properties": {
    "gn:admin1_code":"31",
    "gn:asciiname":"Gangdong",
    "gn:country_code":"CN",
    "gn:dem":2,
    "gn:feature_class":"P",
    "gn:feature_code":"PPL",
    "gn:name":"Gangdong",
    "gn:population":0,
    "gn:timezone":"Asia/Shanghai",
    "iso:country":"CN",
    "name:und_x_variant":[
        "\u6e2f\u4e1c",
        "Guanlian"
    ],
    "wof:name":"Gangdong",
    "wof:placetype":"locality"
},
  "geometry": {"coordinates":[110.78400000000001,19.47004],"type":"Point"}
}