{
  "type": "Feature",
  "properties": {
    "gn:admin1_code":"3.0",
    "gn:asciiname":"Tankouwu",
    "gn:country_code":"CN",
    "gn:dem":71,
    "gn:feature_class":"P",
    "gn:feature_code":"PPL",
    "gn:name":"Tankouwu",
    "gn:population":0,
    "gn:timezone":"Asia/Shanghai",
    "iso:country":"CN",
    "name:und_x_variant":[
        "\u6f6d\u53e3\u575e"
    ],
    "wof:name":"Tankouwu",
    "wof:placetype":"locality"
},
  "geometry": {"coordinates":[117.36763999999999,29.70263],"type":"Point"}
}