{
  "type": "Feature",
  "properties": {
    "gn:admin1_code":"12.0",
    "gn:asciiname":"Tsai chia kau (historical)",
    "gn:country_code":"CN",
    "gn:dem":28,
    "gn:feature_class":"P",
    "gn:feature_code":"PPL",
    "gn:name":"Tsai chia kau (historical)",
    "gn:population":0,
    "gn:timezone":"Asia/Shanghai",
    "iso:country":"CN",
    "wof:name":"Tsai chia kau (historical)",
    "wof:placetype":"locality"
},
  "geometry": {"coordinates":[113.99263999999999,30.62499],"type":"Point"}
}