{
  "type": "Feature",
  "properties": {
    "gn:admin1_code":"25.0",
    "gn:asciiname":"Muchangkou",
    "gn:cc2":"CN",
    "gn:country_code":"CN",
    "gn:dem":79,
    "gn:feature_class":"P",
    "gn:feature_code":"PPL",
    "gn:name":"Muchangkou",
    "gn:population":0,
    "gn:timezone":"Asia/Shanghai",
    "iso:country":"CN",
    "name:zho_x_preferred":[
        "\u6728\u5382\u53e3"
    ],
    "wof:name":"Muchangkou",
    "wof:placetype":"locality"
},
  "geometry": {"coordinates":[120.05419000000001,35.9907],"type":"Point"}
}