{
  "type": "Feature",
  "properties": {
    "gn:admin1_code":"32.0",
    "gn:asciiname":"Zaojiaoshu Wuji",
    "gn:country_code":"CN",
    "gn:dem":469,
    "gn:feature_class":"P",
    "gn:feature_code":"PPL",
    "gn:name":"Zaojiaoshu Wuji",
    "gn:population":0,
    "gn:timezone":"Asia/Shanghai",
    "iso:country":"CN",
    "name:zho_x_preferred":[
        "\u7682\u89d2\u6811\u5c4b\u57fa"
    ],
    "wof:name":"Zaojiaoshu Wuji",
    "wof:placetype":"locality"
},
  "geometry": {"coordinates":[107.26797000000001,31.41023],"type":"Point"}
}