{
  "type": "Feature",
  "properties": {
    "gn:admin1_code":"24.0",
    "gn:asciiname":"Beichengcun",
    "gn:country_code":"CN",
    "gn:dem":761,
    "gn:feature_class":"P",
    "gn:feature_code":"PPL",
    "gn:name":"Beichengcun",
    "gn:population":0,
    "gn:timezone":"Asia/Shanghai",
    "iso:country":"CN",
    "name:zho_x_preferred":[
        "\u5317\u7a0b\u6751"
    ],
    "wof:name":"Beichengcun",
    "wof:placetype":"locality"
},
  "geometry": {"coordinates":[112.37045999999999,37.53465],"type":"Point"}
}