{
  "type": "Feature",
  "properties": {
    "gn:admin1_code":"26.0",
    "gn:asciiname":"Songshuba",
    "gn:country_code":"CN",
    "gn:dem":1002,
    "gn:feature_class":"P",
    "gn:feature_code":"PPL",
    "gn:name":"Songshuba",
    "gn:population":0,
    "gn:timezone":"Asia/Shanghai",
    "iso:country":"CN",
    "name:und_x_variant":[
        "\u677e\u6811\u575d"
    ],
    "wof:name":"Songshuba",
    "wof:placetype":"locality"
},
  "geometry": {"coordinates":[106.91098999999998,33.53072],"type":"Point"}
}