{
  "type": "Feature",
  "properties": {
    "gn:admin1_code":"26.0",
    "gn:asciiname":"Xujiabacun",
    "gn:country_code":"CN",
    "gn:dem":417,
    "gn:feature_class":"P",
    "gn:feature_code":"PPL",
    "gn:name":"Xujiabacun",
    "gn:population":0,
    "gn:timezone":"Asia/Shanghai",
    "iso:country":"CN",
    "name:und_x_variant":[
        "Hs\u00fc-chia-pa",
        "Xujiaba",
        "Xujiabacun"
    ],
    "name:zho_x_preferred":[
        "\u5f90\u5bb6\u575d\u6751"
    ],
    "wof:name":"Xujiabacun",
    "wof:placetype":"locality"
},
  "geometry": {"coordinates":[109.2702,32.44422],"type":"Point"}
}