{
  "type": "Feature",
  "properties": {
    "gn:admin1_code":"26.0",
    "gn:asciiname":"Shenglicun",
    "gn:country_code":"CN",
    "gn:dem":897,
    "gn:feature_class":"P",
    "gn:feature_code":"PPL",
    "gn:name":"Shenglicun",
    "gn:population":0,
    "gn:timezone":"Asia/Shanghai",
    "iso:country":"CN",
    "name:zho_x_preferred":[
        "\u80dc\u5229\u6751"
    ],
    "wof:name":"Shenglicun",
    "wof:placetype":"locality"
},
  "geometry": {"coordinates":[108.73835,33.45696],"type":"Point"}
}