{
  "type": "Feature",
  "properties": {
    "gn:admin1_code":"26.0",
    "gn:asciiname":"Dangpuyao",
    "gn:country_code":"CN",
    "gn:dem":1657,
    "gn:feature_class":"P",
    "gn:feature_code":"PPL",
    "gn:name":"Dangpuyao",
    "gn:population":0,
    "gn:timezone":"Asia/Shanghai",
    "iso:country":"CN",
    "name:zho_x_preferred":[
        "\u5f53\u94fa\u7a91"
    ],
    "wof:name":"Dangpuyao",
    "wof:placetype":"locality"
},
  "geometry": {"coordinates":[108.54918000000001,37.47531],"type":"Point"}
}