{
  "type": "Feature",
  "properties": {
    "gn:admin1_code":"30.0",
    "gn:asciiname":"Sancai",
    "gn:country_code":"CN",
    "gn:dem":191,
    "gn:feature_class":"P",
    "gn:feature_code":"PPL",
    "gn:name":"Sancai",
    "gn:population":0,
    "gn:timezone":"Asia/Shanghai",
    "iso:country":"CN",
    "name:zho_x_preferred":[
        "Sancai"
    ],
    "name:zho_x_variant":[
        "\u4e09\u624d"
    ],
    "wof:name":"Sancai",
    "wof:placetype":"locality"
},
  "geometry": {"coordinates":[112.13583,24.24417],"type":"Point"}
}