{
  "type": "Feature",
  "properties": {
    "gn:admin1_code":"30.0",
    "gn:asciiname":"Sancai",
    "gn:country_code":"CN",
    "gn:dem":191,
    "gn:feature_class":"P",
    "gn:feature_code":"PPL",
    "gn:name":"Sancai",
    "gn:population":0,
    "gn:timezone":"Asia/Shanghai",
    "iso:country":"CN",
    "name:cat_x_preferred":[
        "Sancai"
    ],
    "name:fra_x_preferred":[
        "Sancai"
    ],
    "name:heb_x_preferred":[
        "\u05e1\u05e0\u05e7\u05d0\u05d9"
    ],
    "name:ind_x_preferred":[
        "Sancai"
    ],
    "name:ita_x_preferred":[
        "Sancai"
    ],
    "name:jpn_x_preferred":[
        "\u5510\u4e09\u5f69"
    ],
    "name:kor_x_preferred":[
        "\ub2f9\uc0bc\ucc44"
    ],
    "name:nor_x_preferred":[
        "Sancai"
    ],
    "name:pol_x_preferred":[
        "Sancai"
    ],
    "name:rus_x_preferred":[
        "\u0421\u0430\u043d\u044c-\u0446\u0430\u0439"
    ],
    "name:spa_x_preferred":[
        "Sancai"
    ],
    "name:swe_x_preferred":[
        "Sancai"
    ],
    "name:ukr_x_preferred":[
        "\u0421\u0430\u043d\u043a\u0430\u0439"
    ],
    "name:wuu_x_preferred":[
        "\u5510\u4e09\u5f69"
    ],
    "name:zho_x_preferred":[
        "Sancai"
    ],
    "name:zho_x_variant":[
        "\u4e09\u624d",
        "\u5510\u4e09\u5f69"
    ],
    "wof:name":"Sancai",
    "wof:placetype":"locality"
},
  "geometry": {"coordinates":[112.13583,24.24417],"type":"Point"}
}