{
  "type": "Feature",
  "properties": {
    "gn:admin1_code":"16.0",
    "gn:asciiname":"Zhongyuan",
    "gn:country_code":"CN",
    "gn:dem":162,
    "gn:feature_class":"P",
    "gn:feature_code":"PPL",
    "gn:name":"Zhongyuan",
    "gn:population":0,
    "gn:timezone":"Asia/Shanghai",
    "iso:country":"CN",
    "name:bul_x_preferred":[
        "\u0414\u0436\u0443\u043d\u044e\u0435\u043d"
    ],
    "name:deu_x_preferred":[
        "Zentralchinesische Ebene"
    ],
    "name:fas_x_preferred":[
        "\u0698\u0627\u0646\u06af\u06cc\u0648\u0627\u0646"
    ],
    "name:fra_x_preferred":[
        "Plaine centrale"
    ],
    "name:ind_x_preferred":[
        "Zhongyuan"
    ],
    "name:ita_x_preferred":[
        "Zhongyuan"
    ],
    "name:kor_x_preferred":[
        "\uc911\uc6d0"
    ],
    "name:lit_x_preferred":[
        "Vidurio lyguma"
    ],
    "name:nld_x_preferred":[
        "Zhongyuan"
    ],
    "name:spa_x_preferred":[
        "Llanura Central"
    ],
    "name:ukr_x_preferred":[
        "\u0426\u0435\u043d\u0442\u0440\u0430\u043b\u044c\u043d\u0430 \u0440\u0456\u0432\u043d\u0438\u043d\u0430"
    ],
    "name:vie_x_preferred":[
        "Trung Nguy\u00ean"
    ],
    "name:wuu_x_preferred":[
        "\u4e2d\u539f\u5730\u533a"
    ],
    "name:zho_x_preferred":[
        "\u4e2d\u539f"
    ],
    "wof:name":"Zhongyuan",
    "wof:placetype":"locality"
},
  "geometry": {"coordinates":[107.611,22.4719],"type":"Point"}
}