{
  "type": "Feature",
  "properties": {
    "gn:admin1_code":"8.0",
    "gn:asciiname":"Jianshan Nongchang Gangshang",
    "gn:country_code":"CN",
    "gn:dem":380,
    "gn:feature_class":"P",
    "gn:feature_code":"PPLF",
    "gn:name":"Jianshan Nongchang Gangshang",
    "gn:population":0,
    "gn:timezone":"Asia/Shanghai",
    "iso:country":"CN",
    "name:zho_x_preferred":[
        "\u5c16\u5c71\u519c\u573a\u5c97\u4e0a"
    ],
    "wof:name":"Jianshan Nongchang Gangshang",
    "wof:placetype":"locality"
},
  "geometry": {"coordinates":[125.62468,48.89292],"type":"Point"}
}