{
  "type": "Feature",
  "properties": {
    "gn:admin1_code":"20",
    "gn:asciiname":"Qingcaogou",
    "gn:country_code":"CN",
    "gn:dem":1426,
    "gn:feature_class":"P",
    "gn:feature_code":"PPL",
    "gn:name":"Qingcaogou",
    "gn:population":0,
    "gn:timezone":"Asia/Shanghai",
    "iso:country":"CN",
    "wof:name":"Qingcaogou",
    "wof:placetype":"locality"
},
  "geometry": {"coordinates":[115.99333,41.96778],"type":"Point"}
}