{
  "type": "Feature",
  "properties": {
    "gn:admin1_code":"18",
    "gn:asciiname":"Huangjiaogou",
    "gn:country_code":"CN",
    "gn:dem":329,
    "gn:feature_class":"P",
    "gn:feature_code":"PPL",
    "gn:name":"Huangjiaogou",
    "gn:population":0,
    "gn:timezone":"Asia/Shanghai",
    "iso:country":"CN",
    "name:zho_x_preferred":[
        "\u9ec4\u89d2\u6c9f"
    ],
    "wof:name":"Huangjiaogou",
    "wof:placetype":"locality"
},
  "geometry": {"coordinates":[106.051,28.5955],"type":"Point"}
}