{
  "type": "Feature",
  "properties": {
    "gn:admin1_code":"8.0",
    "gn:asciiname":"Dawaziyu",
    "gn:country_code":"CN",
    "gn:dem":175,
    "gn:feature_class":"P",
    "gn:feature_code":"PPL",
    "gn:name":"Dawaziyu",
    "gn:population":0,
    "gn:timezone":"Asia/Shanghai",
    "iso:country":"CN",
    "name:zho_x_preferred":[
        "\u5927\u6d3c\u5b50\u4e8e"
    ],
    "wof:name":"Dawaziyu",
    "wof:placetype":"locality"
},
  "geometry": {"coordinates":[125.76125,46.52663],"type":"Point"}
}