{
  "type": "Feature",
  "properties": {
    "gn:admin1_code":"33.0",
    "gn:asciiname":"Mianbutai",
    "gn:country_code":"CN",
    "gn:dem":771,
    "gn:feature_class":"P",
    "gn:feature_code":"PPL",
    "gn:name":"Mianbutai",
    "gn:population":0,
    "gn:timezone":"Asia/Shanghai",
    "iso:country":"CN",
    "name:zho_x_preferred":[
        "\u68c9\u5e03\u53f0"
    ],
    "wof:name":"Mianbutai",
    "wof:placetype":"locality"
},
  "geometry": {"coordinates":[108.39936000000002,28.6717],"type":"Point"}
}