{
  "type": "Feature",
  "properties": {
    "gn:admin1_code":"3",
    "gn:asciiname":"Jinshadi",
    "gn:country_code":"CN",
    "gn:dem":129,
    "gn:feature_class":"P",
    "gn:feature_code":"PPL",
    "gn:name":"Jinshadi",
    "gn:population":0,
    "gn:timezone":"Asia/Shanghai",
    "iso:country":"CN",
    "name:und_x_variant":[
        "\u91d1\u6c99\u5730"
    ],
    "wof:name":"Jinshadi",
    "wof:placetype":"locality"
},
  "geometry": {"coordinates":[116.81771999999999,27.248],"type":"Point"}
}