{
  "type": "Feature",
  "properties": {
    "gn:admin1_code":"18",
    "gn:asciiname":"Dingpeng",
    "gn:country_code":"CN",
    "gn:dem":1153,
    "gn:feature_class":"P",
    "gn:feature_code":"PPL",
    "gn:name":"Dingpeng",
    "gn:population":0,
    "gn:timezone":"Asia/Shanghai",
    "iso:country":"CN",
    "name:zho_x_preferred":[
        "\u9876\u670b"
    ],
    "wof:name":"Dingpeng",
    "wof:placetype":"locality"
},
  "geometry": {"coordinates":[105.983,25.491],"type":"Point"}
}