{
  "type": "Feature",
  "properties": {
    "gn:admin1_code":"8.0",
    "gn:asciiname":"Pujingcun",
    "gn:country_code":"CN",
    "gn:dem":136,
    "gn:feature_class":"P",
    "gn:feature_code":"PPL",
    "gn:name":"Pujingcun",
    "gn:population":0,
    "gn:timezone":"Asia/Shanghai",
    "iso:country":"CN",
    "name:zho_x_preferred":[
        "\u84b2\u4e95\u6751"
    ],
    "wof:name":"Pujingcun",
    "wof:placetype":"locality"
},
  "geometry": {"coordinates":[126.72328,46.17023],"type":"Point"}
}