{
  "type": "Feature",
  "properties": {
    "gn:admin1_code":"12.0",
    "gn:asciiname":"Qiyueqiao",
    "gn:country_code":"CN",
    "gn:dem":1123,
    "gn:feature_class":"P",
    "gn:feature_code":"PPL",
    "gn:name":"Qiyueqiao",
    "gn:population":0,
    "gn:timezone":"Asia/Shanghai",
    "iso:country":"CN",
    "name:zho_x_preferred":[
        "\u9f50\u5cb3\u6865"
    ],
    "wof:name":"Qiyueqiao",
    "wof:placetype":"locality"
},
  "geometry": {"coordinates":[108.68151,30.3087],"type":"Point"}
}