{
  "type": "Feature",
  "properties": {
    "gn:admin1_code":"25",
    "gn:asciiname":"Zhugouya",
    "gn:country_code":"CN",
    "gn:dem":34,
    "gn:feature_class":"P",
    "gn:feature_code":"PPL",
    "gn:name":"Zhugouya",
    "gn:population":0,
    "gn:timezone":"Asia/Shanghai",
    "iso:country":"CN",
    "name:zho_x_preferred":[
        "\u6731\u6c9f\u5d16"
    ],
    "wof:name":"Zhugouya",
    "wof:placetype":"locality"
},
  "geometry": {"coordinates":[118.288,34.4898],"type":"Point"}
}