{
  "type": "Feature",
  "properties": {
    "gn:admin1_code":"9.0",
    "gn:asciiname":"Xiaozhanggou",
    "gn:country_code":"CN",
    "gn:dem":185,
    "gn:feature_class":"P",
    "gn:feature_code":"PPL",
    "gn:name":"Xiaozhanggou",
    "gn:population":0,
    "gn:timezone":"Asia/Shanghai",
    "iso:country":"CN",
    "name:und_x_variant":[
        "\u5c0f\u5f20\u6c9f",
        "Xiaozhanggou"
    ],
    "wof:name":"Xiaozhanggou",
    "wof:placetype":"locality"
},
  "geometry": {"coordinates":[112.5419,33.26337],"type":"Point"}
}