{
  "type": "Feature",
  "properties": {
    "gn:admin1_code":"33",
    "gn:asciiname":"Gelan",
    "gn:country_code":"CN",
    "gn:dem":334,
    "gn:feature_class":"P",
    "gn:feature_code":"PPLA4",
    "gn:name":"Gelan",
    "gn:population":0,
    "gn:timezone":"Asia/Shanghai",
    "iso:country":"CN",
    "name:und_x_variant":[
        "Gelan Zhen"
    ],
    "name:zho_x_preferred":[
        "\u845b\u5170"
    ],
    "name:zho_x_variant":[
        "\u845b\u5170\u9547"
    ],
    "wof:name":"Gelan",
    "wof:placetype":"locality"
},
  "geometry": {"coordinates":[107.11612,30.03589],"type":"Point"}
}