{
  "type": "Feature",
  "properties": {
    "gn:admin1_code":"16.0",
    "gn:asciiname":"Lufeng",
    "gn:country_code":"CN",
    "gn:dem":141,
    "gn:feature_class":"P",
    "gn:feature_code":"PPL",
    "gn:name":"Lufeng",
    "gn:population":0,
    "gn:timezone":"Asia/Shanghai",
    "iso:country":"CN",
    "name:ceb_x_preferred":[
        "Lufeng"
    ],
    "name:ces_x_preferred":[
        "Lu-feng"
    ],
    "name:deu_x_preferred":[
        "Lufeng"
    ],
    "name:fra_x_preferred":[
        "Lufeng"
    ],
    "name:nor_x_preferred":[
        "Lufeng"
    ],
    "name:rus_x_preferred":[
        "\u041b\u0443\u0444\u044d\u043d"
    ],
    "name:swe_x_preferred":[
        "Lufeng"
    ],
    "name:zho_x_preferred":[
        "\u9732\u51e4"
    ],
    "wof:name":"Lufeng",
    "wof:placetype":"locality"
},
  "geometry": {"coordinates":[110.297,23.1101],"type":"Point"}
}