{
  "type": "Feature",
  "properties": {
    "gn:admin1_code":"18.0",
    "gn:asciiname":"Niujiaodong",
    "gn:country_code":"CN",
    "gn:dem":1024,
    "gn:feature_class":"P",
    "gn:feature_code":"PPL",
    "gn:name":"Niujiaodong",
    "gn:population":0,
    "gn:timezone":"Asia/Shanghai",
    "iso:country":"CN",
    "name:zho_x_preferred":[
        "\u725b\u89d2\u6d1e"
    ],
    "wof:name":"Niujiaodong",
    "wof:placetype":"locality"
},
  "geometry": {"coordinates":[108.774,27.9865],"type":"Point"}
}