{
  "type": "Feature",
  "properties": {
    "gn:admin1_code":"11.0",
    "gn:asciiname":"Daobeiling",
    "gn:country_code":"CN",
    "gn:dem":167,
    "gn:feature_class":"P",
    "gn:feature_code":"PPL",
    "gn:name":"Daobeiling",
    "gn:population":0,
    "gn:timezone":"Asia/Shanghai",
    "iso:country":"CN",
    "name:zho_x_preferred":[
        "\u5230\u80cc\u5cad"
    ],
    "wof:name":"Daobeiling",
    "wof:placetype":"locality"
},
  "geometry": {"coordinates":[113.67755,26.75873],"type":"Point"}
}