{
  "type": "Feature",
  "properties": {
    "gn:admin1_code":"7.0",
    "gn:asciiname":"Hantan",
    "gn:country_code":"CN",
    "gn:dem":833,
    "gn:feature_class":"P",
    "gn:feature_code":"PPL",
    "gn:name":"Hantan",
    "gn:population":0,
    "gn:timezone":"Asia/Shanghai",
    "iso:country":"CN",
    "name:zho_x_preferred":[
        "\u7f55\u575b"
    ],
    "wof:name":"Hantan",
    "wof:placetype":"locality"
},
  "geometry": {"coordinates":[116.56601000000001,26.8628],"type":"Point"}
}