{
  "type": "Feature",
  "properties": {
    "gn:admin1_code":"3.0",
    "gn:asciiname":"Liujiayuan",
    "gn:country_code":"CN",
    "gn:dem":52,
    "gn:feature_class":"P",
    "gn:feature_code":"PPL",
    "gn:name":"Liujiayuan",
    "gn:population":0,
    "gn:timezone":"Asia/Shanghai",
    "iso:country":"CN",
    "name:und_x_variant":[
        "\u6d41\u5bb6\u6e90"
    ],
    "wof:name":"Liujiayuan",
    "wof:placetype":"locality"
},
  "geometry": {"coordinates":[116.97273,28.17323],"type":"Point"}
}