{
  "type": "Feature",
  "properties": {
    "gn:admin1_code":"32.0",
    "gn:asciiname":"Xietaizi",
    "gn:country_code":"CN",
    "gn:dem":774,
    "gn:feature_class":"P",
    "gn:feature_code":"PPL",
    "gn:name":"Xietaizi",
    "gn:population":0,
    "gn:timezone":"Asia/Shanghai",
    "iso:country":"CN",
    "name:zho_x_preferred":[
        "\u659c\u53f0\u5b50"
    ],
    "wof:name":"Xietaizi",
    "wof:placetype":"locality"
},
  "geometry": {"coordinates":[104.61799999999999,31.7891],"type":"Point"}
}