{
  "type": "Feature",
  "properties": {
    "gn:admin1_code":"2.0",
    "gn:asciiname":"Nongnei",
    "gn:country_code":"CN",
    "gn:dem":273,
    "gn:feature_class":"P",
    "gn:feature_code":"PPL",
    "gn:name":"Nongnei",
    "gn:population":0,
    "gn:timezone":"Asia/Shanghai",
    "iso:country":"CN",
    "name:zho_x_preferred":[
        "\u5f04\u5185"
    ],
    "wof:name":"Nongnei",
    "wof:placetype":"locality"
},
  "geometry": {"coordinates":[119.02442000000001,28.616],"type":"Point"}
}