{
  "type": "Feature",
  "properties": {
    "gn:admin1_code":"29.0",
    "gn:asciiname":"Huangqichang",
    "gn:country_code":"CN",
    "gn:dem":1687,
    "gn:feature_class":"P",
    "gn:feature_code":"PPL",
    "gn:name":"Huangqichang",
    "gn:population":0,
    "gn:timezone":"Asia/Shanghai",
    "iso:country":"CN",
    "name:zho_x_preferred":[
        "\u9ec4\u65d7\u5382"
    ],
    "wof:name":"Huangqichang",
    "wof:placetype":"locality"
},
  "geometry": {"coordinates":[100.452,25.3612],"type":"Point"}
}