{
  "type": "Feature",
  "properties": {
    "gn:admin1_code":"29",
    "gn:asciiname":"Tengziqing",
    "gn:country_code":"CN",
    "gn:dem":1662,
    "gn:feature_class":"P",
    "gn:feature_code":"PPL",
    "gn:name":"Tengziqing",
    "gn:population":0,
    "gn:timezone":"Asia/Shanghai",
    "iso:country":"CN",
    "name:zho_x_preferred":[
        "\u85e4\u5b50\u7b90"
    ],
    "wof:name":"Tengziqing",
    "wof:placetype":"locality"
},
  "geometry": {"coordinates":[101.92700000000001,24.9369],"type":"Point"}
}