{
  "type": "Feature",
  "properties": {
    "gn:admin1_code":"3.0",
    "gn:asciiname":"Xizhoujiang",
    "gn:country_code":"CN",
    "gn:dem":41,
    "gn:feature_class":"P",
    "gn:feature_code":"PPL",
    "gn:name":"Xizhoujiang",
    "gn:population":0,
    "gn:timezone":"Asia/Shanghai",
    "iso:country":"CN",
    "name:und_x_variant":[
        "\u897f\u6d32\u6c5f"
    ],
    "wof:name":"Xizhoujiang",
    "wof:placetype":"locality"
},
  "geometry": {"coordinates":[115.30669,27.85986],"type":"Point"}
}