{
  "type": "Feature",
  "properties": {
    "gn:admin1_code":"11.0",
    "gn:asciiname":"Hengluwan",
    "gn:country_code":"CN",
    "gn:dem":429,
    "gn:feature_class":"P",
    "gn:feature_code":"PPL",
    "gn:name":"Hengluwan",
    "gn:population":0,
    "gn:timezone":"Asia/Shanghai",
    "iso:country":"CN",
    "name:zho_x_preferred":[
        "\u6a2a\u8def\u6e7e"
    ],
    "wof:name":"Hengluwan",
    "wof:placetype":"locality"
},
  "geometry": {"coordinates":[110.70179,27.8133],"type":"Point"}
}