{
  "type": "Feature",
  "properties": {
    "gn:admin1_code":"32.0",
    "gn:asciiname":"Hanuolijiao",
    "gn:country_code":"CN",
    "gn:dem":2732,
    "gn:feature_class":"P",
    "gn:feature_code":"PPL",
    "gn:name":"Hanuolijiao",
    "gn:population":0,
    "gn:timezone":"Asia/Shanghai",
    "iso:country":"CN",
    "name:zho_x_preferred":[
        "\u54c8\u8bfa\u674e\u811a"
    ],
    "wof:name":"Hanuolijiao",
    "wof:placetype":"locality"
},
  "geometry": {"coordinates":[102.66691,28.67446],"type":"Point"}
}