{
  "type": "Feature",
  "properties": {
    "gn:admin1_code":"32.0",
    "gn:asciiname":"Wujian",
    "gn:country_code":"CN",
    "gn:dem":428,
    "gn:feature_class":"P",
    "gn:feature_code":"PPL",
    "gn:name":"Wujian",
    "gn:population":0,
    "gn:timezone":"Asia/Shanghai",
    "iso:country":"CN",
    "name:zho_x_preferred":[
        "\u4e94\u5efa"
    ],
    "wof:name":"Wujian",
    "wof:placetype":"locality"
},
  "geometry": {"coordinates":[104.18899999999999,30.1695],"type":"Point"}
}