{
  "type": "Feature",
  "properties": {
    "gn:admin1_code":"3.0",
    "gn:asciiname":"Xianshouguanju Zhumu Linchang",
    "gn:country_code":"CN",
    "gn:dem":221,
    "gn:feature_class":"P",
    "gn:feature_code":"PPLF",
    "gn:name":"Xianshouguanju Zhumu Linchang",
    "gn:population":0,
    "gn:timezone":"Asia/Shanghai",
    "iso:country":"CN",
    "name:und_x_variant":[
        "\u53bf\u624b\u7ba1\u5c40\u7af9\u6728\u6797\u573a"
    ],
    "wof:name":"Xianshouguanju Zhumu Linchang",
    "wof:placetype":"locality"
},
  "geometry": {"coordinates":[115.53501,27.51207],"type":"Point"}
}