{
  "type": "Feature",
  "properties": {
    "gn:admin1_code":"1.0",
    "gn:asciiname":"Fojiaoling",
    "gn:country_code":"CN",
    "gn:dem":280,
    "gn:feature_class":"P",
    "gn:feature_code":"PPL",
    "gn:name":"Fojiaoling",
    "gn:population":0,
    "gn:timezone":"Asia/Shanghai",
    "iso:country":"CN",
    "name:zho_x_preferred":[
        "\u4f5b\u811a\u5cad"
    ],
    "wof:name":"Fojiaoling",
    "wof:placetype":"locality"
},
  "geometry": {"coordinates":[118.5184,29.91366],"type":"Point"}
}