{
  "type": "Feature",
  "properties": {
    "gn:admin1_code":"12.0",
    "gn:asciiname":"Zhangjia Dawan",
    "gn:country_code":"CN",
    "gn:dem":60,
    "gn:feature_class":"P",
    "gn:feature_code":"PPL",
    "gn:name":"Zhangjia Dawan",
    "gn:population":0,
    "gn:timezone":"Asia/Shanghai",
    "iso:country":"CN",
    "name:und_x_variant":[
        "\u5f20\u5bb6\u5927\u5846"
    ],
    "wof:name":"Zhangjia Dawan",
    "wof:placetype":"locality"
},
  "geometry": {"coordinates":[115.22069999999999,30.35098],"type":"Point"}
}