{
  "type": "Feature",
  "properties": {
    "gn:admin1_code":"1.0",
    "gn:asciiname":"Huangqiaocun",
    "gn:country_code":"CN",
    "gn:dem":31,
    "gn:feature_class":"P",
    "gn:feature_code":"PPL",
    "gn:name":"Huangqiaocun",
    "gn:population":0,
    "gn:timezone":"Asia/Shanghai",
    "iso:country":"CN",
    "name:zho_x_preferred":[
        "\u9ec4\u6865\u6751"
    ],
    "wof:name":"Huangqiaocun",
    "wof:placetype":"locality"
},
  "geometry": {"coordinates":[117.78069000000001,31.97498],"type":"Point"}
}