{
  "type": "Feature",
  "properties": {
    "gn:admin1_code":"24",
    "gn:asciiname":"Liubu",
    "gn:cc2":"CN",
    "gn:country_code":"CN",
    "gn:dem":781,
    "gn:feature_class":"P",
    "gn:feature_code":"PPL",
    "gn:name":"Liubu",
    "gn:population":0,
    "gn:timezone":"Asia/Shanghai",
    "iso:country":"CN",
    "name:und_x_variant":[
        "Liu-pao-chen",
        "Liu-pao",
        "Liubu"
    ],
    "wof:name":"Liubu",
    "wof:placetype":"locality"
},
  "geometry": {"coordinates":[112.65000000000001,37.71667],"type":"Point"}
}