{
  "type": "Feature",
  "properties": {
    "gn:admin1_code":"30.0",
    "gn:asciiname":"Guogongkeng",
    "gn:country_code":"CN",
    "gn:dem":185,
    "gn:feature_class":"P",
    "gn:feature_code":"PPL",
    "gn:name":"Guogongkeng",
    "gn:population":0,
    "gn:timezone":"Asia/Shanghai",
    "iso:country":"CN",
    "name:zho_x_preferred":[
        "Guogongkeng"
    ],
    "name:zho_x_variant":[
        "\u90ed\u516c\u5751"
    ],
    "wof:name":"Guogongkeng",
    "wof:placetype":"locality"
},
  "geometry": {"coordinates":[114.94444,24.50444],"type":"Point"}
}