{
  "type": "Feature",
  "properties": {
    "gn:admin1_code":"2.0",
    "gn:asciiname":"Zhujiazhuang",
    "gn:country_code":"CN",
    "gn:dem":120,
    "gn:feature_class":"P",
    "gn:feature_code":"PPL",
    "gn:name":"Zhujiazhuang",
    "gn:population":0,
    "gn:timezone":"Asia/Shanghai",
    "iso:country":"CN",
    "name:und_x_variant":[
        "\u795d\u5bb6\u5e84"
    ],
    "name:zho_x_preferred":[
        "Zhujiazhuang"
    ],
    "wof:name":"Zhujiazhuang",
    "wof:placetype":"locality"
},
  "geometry": {"coordinates":[119.98316,30.13692],"type":"Point"}
}