{
  "type": "Feature",
  "properties": {
    "gn:admin1_code":"5",
    "gn:asciiname":"Dongtuoyaozi",
    "gn:country_code":"CN",
    "gn:dem":554,
    "gn:feature_class":"P",
    "gn:feature_code":"PPL",
    "gn:name":"Dongtuoyaozi",
    "gn:population":0,
    "gn:timezone":"Asia/Shanghai",
    "iso:country":"CN",
    "name:zho_x_preferred":[
        "\u4e1c\u9a7c\u8170\u5b50"
    ],
    "wof:name":"Dongtuoyaozi",
    "wof:placetype":"locality"
},
  "geometry": {"coordinates":[127.935,43.5725],"type":"Point"}
}