{
  "type": "Feature",
  "properties": {
    "gn:admin1_code":"15.0",
    "gn:asciiname":"Jiaochangba",
    "gn:country_code":"CN",
    "gn:dem":2240,
    "gn:feature_class":"P",
    "gn:feature_code":"PPL",
    "gn:name":"Jiaochangba",
    "gn:population":0,
    "gn:timezone":"Asia/Shanghai",
    "iso:country":"CN",
    "name:zho_x_preferred":[
        "\u6559\u573a\u575d"
    ],
    "wof:name":"Jiaochangba",
    "wof:placetype":"locality"
},
  "geometry": {"coordinates":[104.84142,34.05896],"type":"Point"}
}