{
  "type": "Feature",
  "properties": {
    "gn:admin1_code":"5.0",
    "gn:asciiname":"Daipingfang",
    "gn:country_code":"CN",
    "gn:dem":169,
    "gn:feature_class":"P",
    "gn:feature_code":"PPL",
    "gn:name":"Daipingfang",
    "gn:population":0,
    "gn:timezone":"Asia/Shanghai",
    "iso:country":"CN",
    "name:zho_x_preferred":[
        "\u6234\u5e73\u623f"
    ],
    "wof:name":"Daipingfang",
    "wof:placetype":"locality"
},
  "geometry": {"coordinates":[125.25575000000001,44.40489],"type":"Point"}
}