{
  "type": "Feature",
  "properties": {
    "gn:admin1_code":"5.0",
    "gn:asciiname":"Changshanling Linchang",
    "gn:country_code":"CN",
    "gn:dem":776,
    "gn:feature_class":"P",
    "gn:feature_code":"PPLF",
    "gn:name":"Changshanling Linchang",
    "gn:population":0,
    "gn:timezone":"Asia/Shanghai",
    "iso:country":"CN",
    "name:und_x_variant":[
        "\u957f\u5c71\u5cad\u6797\u573a"
    ],
    "wof:name":"Changshanling Linchang",
    "wof:placetype":"locality"
},
  "geometry": {"coordinates":[128.71903999999998,42.1729],"type":"Point"}
}