{
  "type": "Feature",
  "properties": {
    "gn:admin1_code":"30.0",
    "gn:asciiname":"Shangkeng",
    "gn:country_code":"CN",
    "gn:dem":295,
    "gn:feature_class":"P",
    "gn:feature_code":"PPL",
    "gn:name":"Shangkeng",
    "gn:population":0,
    "gn:timezone":"Asia/Shanghai",
    "iso:country":"CN",
    "name:und_x_variant":[
        "\u4e0a\u5751"
    ],
    "name:zho_x_preferred":[
        "\u4e0a\u5751"
    ],
    "wof:name":"Shangkeng",
    "wof:placetype":"locality"
},
  "geometry": {"coordinates":[115.31126,23.34337],"type":"Point"}
}