{
  "type": "Feature",
  "properties": {
    "gn:admin1_code":"2.0",
    "gn:asciiname":"Waihuangdu",
    "gn:country_code":"CN",
    "gn:dem":70,
    "gn:feature_class":"P",
    "gn:feature_code":"PPL",
    "gn:name":"Waihuangdu",
    "gn:population":0,
    "gn:timezone":"Asia/Shanghai",
    "iso:country":"CN",
    "name:und_x_variant":[
        "\u5916\u9ec4\u675c"
    ],
    "wof:name":"Waihuangdu",
    "wof:placetype":"locality"
},
  "geometry": {"coordinates":[119.7565,30.73219000000001],"type":"Point"}
}