{
  "type": "Feature",
  "properties": {
    "gn:admin1_code":"10",
    "gn:asciiname":"Luanxie",
    "gn:country_code":"CN",
    "gn:dem":246,
    "gn:feature_class":"P",
    "gn:feature_code":"PPL",
    "gn:name":"Luanxie",
    "gn:population":0,
    "gn:timezone":"Asia/Shanghai",
    "iso:country":"CN",
    "name:zho_x_preferred":[
        "\u683e\u5378"
    ],
    "wof:name":"Luanxie",
    "wof:placetype":"locality"
},
  "geometry": {"coordinates":[114.20999999999999,36.8588],"type":"Point"}
}