{
  "type": "Feature",
  "properties": {
    "gn:admin1_code":"12.0",
    "gn:asciiname":"Yanwukou",
    "gn:country_code":"CN",
    "gn:dem":809,
    "gn:feature_class":"P",
    "gn:feature_code":"PPL",
    "gn:name":"Yanwukou",
    "gn:population":0,
    "gn:timezone":"Asia/Shanghai",
    "iso:country":"CN",
    "name:zho_x_preferred":[
        "\u5ca9\u5c4b\u53e3"
    ],
    "name:zho_x_variant":[
        "\u5ca9\u5c4b\u53e3\u4e61"
    ],
    "wof:name":"Yanwukou",
    "wof:placetype":"locality"
},
  "geometry": {"coordinates":[111.22342999999999,31.72136],"type":"Point"}
}