{
  "type": "Feature",
  "properties": {
    "gn:admin1_code":"15.0",
    "gn:asciiname":"Shangbali",
    "gn:country_code":"CN",
    "gn:dem":1769,
    "gn:feature_class":"P",
    "gn:feature_code":"PPL",
    "gn:name":"Shangbali",
    "gn:population":0,
    "gn:timezone":"Asia/Shanghai",
    "iso:country":"CN",
    "name:und_x_variant":[
        "\u4e0a\u575d\u91cc"
    ],
    "wof:name":"Shangbali",
    "wof:placetype":"locality"
},
  "geometry": {"coordinates":[105.3424,33.31943],"type":"Point"}
}