{
  "type": "Feature",
  "properties": {
    "gn:admin1_code":"20.0",
    "gn:asciiname":"Ajiri Gatinghundi",
    "gn:country_code":"CN",
    "gn:dem":797,
    "gn:feature_class":"P",
    "gn:feature_code":"PPL",
    "gn:name":"Ajiri Gatinghundi",
    "gn:population":0,
    "gn:timezone":"Asia/Shanghai",
    "iso:country":"CN",
    "name:zho_x_preferred":[
        "\u963f\u5409\u65e5\u560e\u5ef7\u6d51\u8fea"
    ],
    "wof:name":"Ajiri Gatinghundi",
    "wof:placetype":"locality"
},
  "geometry": {"coordinates":[120.21804,49.98377],"type":"Point"}
}