{
  "type": "Feature",
  "properties": {
    "gn:admin1_code":"32.0",
    "gn:asciiname":"Maipala",
    "gn:country_code":"CN",
    "gn:dem":2131,
    "gn:feature_class":"P",
    "gn:feature_code":"PPL",
    "gn:name":"Maipala",
    "gn:population":0,
    "gn:timezone":"Asia/Shanghai",
    "iso:country":"CN",
    "name:zho_x_preferred":[
        "\u9ea6\u5e15\u62c9"
    ],
    "wof:name":"Maipala",
    "wof:placetype":"locality"
},
  "geometry": {"coordinates":[101.944,27.532],"type":"Point"}
}