{
  "type": "Feature",
  "properties": {
    "gn:admin1_code":"14.0",
    "gn:asciiname":"Xialong",
    "gn:country_code":"CN",
    "gn:dem":4392,
    "gn:feature_class":"P",
    "gn:feature_code":"PPL",
    "gn:name":"Xialong",
    "gn:population":0,
    "gn:timezone":"Asia/Urumqi",
    "iso:country":"CN",
    "name:zho_x_preferred":[
        "\u8f96\u9f99"
    ],
    "wof:name":"Xialong",
    "wof:placetype":"locality"
},
  "geometry": {"coordinates":[87.715,28.6338],"type":"Point"}
}