{
  "type": "Feature",
  "properties": {
    "gn:admin1_code":"21.0",
    "gn:asciiname":"Lulujing",
    "gn:country_code":"CN",
    "gn:dem":1332,
    "gn:feature_class":"P",
    "gn:feature_code":"PPL",
    "gn:name":"Lulujing",
    "gn:population":0,
    "gn:timezone":"Asia/Shanghai",
    "iso:country":"CN",
    "name:zho_x_preferred":[
        "\u8f98\u8f73\u4e95"
    ],
    "wof:name":"Lulujing",
    "wof:placetype":"locality"
},
  "geometry": {"coordinates":[106.73,37.6962],"type":"Point"}
}