{
  "type": "Feature",
  "properties": {
    "gn:admin1_code":"5.0",
    "gn:asciiname":"Putaogou Linchang",
    "gn:country_code":"CN",
    "gn:dem":445,
    "gn:feature_class":"P",
    "gn:feature_code":"PPLF",
    "gn:name":"Putaogou Linchang",
    "gn:population":0,
    "gn:timezone":"Asia/Shanghai",
    "iso:country":"CN",
    "name:und_x_variant":[
        "\u8461\u8404\u6c9f\u6797\u573a"
    ],
    "wof:name":"Putaogou Linchang",
    "wof:placetype":"locality"
},
  "geometry": {"coordinates":[129.97489999999999,43.66753],"type":"Point"}
}