{
  "type": "Feature",
  "properties": {
    "gn:admin1_code":"1.0",
    "gn:asciiname":"Bashipucun",
    "gn:country_code":"CN",
    "gn:dem":28,
    "gn:feature_class":"P",
    "gn:feature_code":"PPL",
    "gn:name":"Bashipucun",
    "gn:population":0,
    "gn:timezone":"Asia/Shanghai",
    "iso:country":"CN",
    "name:zho_x_preferred":[
        "\u516b\u5341\u94fa\u6751"
    ],
    "wof:name":"Bashipucun",
    "wof:placetype":"locality"
},
  "geometry": {"coordinates":[116.72384,31.53301],"type":"Point"}
}