{
  "type": "Feature",
  "properties": {
    "gn:admin1_code":"19.0",
    "gn:asciiname":"Beideng",
    "gn:country_code":"CN",
    "gn:dem":373,
    "gn:feature_class":"P",
    "gn:feature_code":"PPL",
    "gn:name":"Beideng",
    "gn:population":0,
    "gn:timezone":"Asia/Shanghai",
    "iso:country":"CN",
    "name:und_x_variant":[
        "\u7891\u767b"
    ],
    "name:zho_x_preferred":[
        "\u7891\u767b"
    ],
    "wof:name":"Beideng",
    "wof:placetype":"locality"
},
  "geometry": {"coordinates":[125.10278999999998,41.41633],"type":"Point"}
}