{
  "type": "Feature",
  "properties": {
    "gn:admin1_code":"2.0",
    "gn:asciiname":"Lujiadai",
    "gn:country_code":"CN",
    "gn:dem":5,
    "gn:feature_class":"P",
    "gn:feature_code":"PPL",
    "gn:name":"Lujiadai",
    "gn:population":0,
    "gn:timezone":"Asia/Shanghai",
    "iso:country":"CN",
    "name:und_x_variant":[
        "\u9646\u5bb6\u57ed"
    ],
    "wof:name":"Lujiadai",
    "wof:placetype":"locality"
},
  "geometry": {"coordinates":[120.49572000000001,30.5568],"type":"Point"}
}