{
  "type": "Feature",
  "properties": {
    "gn:admin1_code":"9.0",
    "gn:asciiname":"Zhuangke",
    "gn:country_code":"CN",
    "gn:dem":1151,
    "gn:feature_class":"P",
    "gn:feature_code":"PPL",
    "gn:name":"Zhuangke",
    "gn:population":0,
    "gn:timezone":"Asia/Shanghai",
    "iso:country":"CN",
    "name:zho_x_preferred":[
        "\u5e84\u79d1"
    ],
    "wof:name":"Zhuangke",
    "wof:placetype":"locality"
},
  "geometry": {"coordinates":[111.25897000000001,34.02583],"type":"Point"}
}