{
  "type": "Feature",
  "properties": {
    "gn:admin1_code":"11.0",
    "gn:asciiname":"Jiuhua'an",
    "gn:country_code":"CN",
    "gn:dem":56,
    "gn:feature_class":"P",
    "gn:feature_code":"PPL",
    "gn:name":"Jiuhua\u2019an",
    "gn:population":0,
    "gn:timezone":"Asia/Shanghai",
    "iso:country":"CN",
    "name:und_x_variant":[
        "Jiuhua\u2019an"
    ],
    "name:zho_x_preferred":[
        "\u4e5d\u534e\u5eb5"
    ],
    "wof:name":"Jiuhua'an",
    "wof:placetype":"locality"
},
  "geometry": {"coordinates":[112.92663,27.94216],"type":"Point"}
}