{
  "type": "Feature",
  "properties": {
    "gn:admin1_code":"20.0",
    "gn:asciiname":"Xuetiandi",
    "gn:country_code":"CN",
    "gn:dem":1508,
    "gn:feature_class":"P",
    "gn:feature_code":"PPL",
    "gn:name":"Xuetiandi",
    "gn:population":0,
    "gn:timezone":"Asia/Shanghai",
    "iso:country":"CN",
    "name:und_x_variant":[
        "\u5b66\u7530\u5730"
    ],
    "wof:name":"Xuetiandi",
    "wof:placetype":"locality"
},
  "geometry": {"coordinates":[112.48599,41.55432],"type":"Point"}
}