{
  "type": "Feature",
  "properties": {
    "gn:admin1_code":"32.0",
    "gn:asciiname":"Shenguo",
    "gn:country_code":"CN",
    "gn:dem":2580,
    "gn:feature_class":"P",
    "gn:feature_code":"PPL",
    "gn:name":"Shenguo",
    "gn:population":0,
    "gn:timezone":"Asia/Shanghai",
    "iso:country":"CN",
    "name:zho_x_preferred":[
        "\u7533\u679c"
    ],
    "wof:name":"Shenguo",
    "wof:placetype":"locality"
},
  "geometry": {"coordinates":[102.82183000000001,28.4429],"type":"Point"}
}