{
  "type": "Feature",
  "properties": {
    "gn:admin1_code":"32.0",
    "gn:asciiname":"Niantoushan",
    "gn:country_code":"CN",
    "gn:dem":1660,
    "gn:feature_class":"P",
    "gn:feature_code":"PPL",
    "gn:name":"Niantoushan",
    "gn:population":0,
    "gn:timezone":"Asia/Shanghai",
    "iso:country":"CN",
    "name:zho_x_preferred":[
        "\u57dd\u5934\u5c71"
    ],
    "wof:name":"Niantoushan",
    "wof:placetype":"locality"
},
  "geometry": {"coordinates":[104.41125,32.48423],"type":"Point"}
}