{
  "type": "Feature",
  "properties": {
    "gn:admin1_code":"11.0",
    "gn:asciiname":"Laowu Liujia",
    "gn:country_code":"CN",
    "gn:dem":282,
    "gn:feature_class":"P",
    "gn:feature_code":"PPL",
    "gn:name":"Laowu Liujia",
    "gn:population":0,
    "gn:timezone":"Asia/Shanghai",
    "iso:country":"CN",
    "name:zho_x_preferred":[
        "\u8001\u5c4b\u5218\u5bb6"
    ],
    "wof:name":"Laowu Liujia",
    "wof:placetype":"locality"
},
  "geometry": {"coordinates":[111.64128999999998,27.39626],"type":"Point"}
}