{
  "type": "Feature",
  "properties": {
    "gn:admin1_code":"5.0",
    "gn:asciiname":"Xianrentun",
    "gn:country_code":"CN",
    "gn:dem":300,
    "gn:feature_class":"P",
    "gn:feature_code":"PPL",
    "gn:name":"Xianrentun",
    "gn:population":0,
    "gn:timezone":"Asia/Shanghai",
    "iso:country":"CN",
    "name:zho_x_preferred":[
        "\u4ed9\u4ec1\u5c6f"
    ],
    "wof:name":"Xianrentun",
    "wof:placetype":"locality"
},
  "geometry": {"coordinates":[125.17768,42.93234],"type":"Point"}
}