{
  "type": "Feature",
  "properties": {
    "gn:admin1_code":"3.0",
    "gn:asciiname":"Yingchao",
    "gn:country_code":"CN",
    "gn:dem":341,
    "gn:feature_class":"P",
    "gn:feature_code":"PPL",
    "gn:name":"Yingchao",
    "gn:population":0,
    "gn:timezone":"Asia/Shanghai",
    "iso:country":"CN",
    "name:und_x_variant":[
        "\u82f1\u671d"
    ],
    "wof:name":"Yingchao",
    "wof:placetype":"locality"
},
  "geometry": {"coordinates":[114.25263,28.72396],"type":"Point"}
}