{
  "type": "Feature",
  "properties": {
    "gn:admin1_code":"31.0",
    "gn:asciiname":"Hongguandui",
    "gn:country_code":"CN",
    "gn:dem":356,
    "gn:feature_class":"P",
    "gn:feature_code":"PPLF",
    "gn:name":"Hongguandui",
    "gn:population":0,
    "gn:timezone":"Asia/Shanghai",
    "iso:country":"CN",
    "name:und_x_variant":[
        "\u7ea2\u5149\u961f"
    ],
    "wof:name":"Hongguandui",
    "wof:placetype":"locality"
},
  "geometry": {"coordinates":[109.61045,18.728],"type":"Point"}
}