{
  "type": "Feature",
  "properties": {
    "gn:admin1_code":"18.0",
    "gn:asciiname":"Jiahui",
    "gn:country_code":"CN",
    "gn:dem":308,
    "gn:feature_class":"P",
    "gn:feature_code":"PPL",
    "gn:name":"Jiahui",
    "gn:population":0,
    "gn:timezone":"Asia/Shanghai",
    "iso:country":"CN",
    "name:zho_x_preferred":[
        "\u5609\u4f1a"
    ],
    "wof:name":"Jiahui",
    "wof:placetype":"locality"
},
  "geometry": {"coordinates":[108.384,25.995],"type":"Point"}
}