{
  "type": "Feature",
  "properties": {
    "gn:admin1_code":"30",
    "gn:asciiname":"Bantang",
    "gn:country_code":"CN",
    "gn:dem":197,
    "gn:feature_class":"P",
    "gn:feature_code":"PPL",
    "gn:name":"Bantang",
    "gn:population":0,
    "gn:timezone":"Asia/Shanghai",
    "iso:country":"CN",
    "name:und_x_variant":[
        "\u6273\u5858",
        "Bantang"
    ],
    "name:zho_x_preferred":[
        "\u6273\u5858"
    ],
    "wof:name":"Bantang",
    "wof:placetype":"locality"
},
  "geometry": {"coordinates":[115.83471000000002,24.18726],"type":"Point"}
}