{
  "type": "Feature",
  "properties": {
    "gn:admin1_code":"32.0",
    "gn:asciiname":"Luoluogou",
    "gn:country_code":"CN",
    "gn:dem":2032,
    "gn:feature_class":"P",
    "gn:feature_code":"PPL",
    "gn:name":"Luoluogou",
    "gn:population":0,
    "gn:timezone":"Asia/Shanghai",
    "iso:country":"CN",
    "name:zho_x_preferred":[
        "\u9aa1\u9aa1\u6c9f"
    ],
    "wof:name":"Luoluogou",
    "wof:placetype":"locality"
},
  "geometry": {"coordinates":[102.396,29.6303],"type":"Point"}
}