{
  "type": "Feature",
  "properties": {
    "gn:admin1_code":"18",
    "gn:asciiname":"Shipanya",
    "gn:country_code":"CN",
    "gn:dem":983,
    "gn:feature_class":"P",
    "gn:feature_code":"PPL",
    "gn:name":"Shipanya",
    "gn:population":0,
    "gn:timezone":"Asia/Shanghai",
    "iso:country":"CN",
    "name:zho_x_preferred":[
        "\u77f3\u76d8\u57ad"
    ],
    "wof:name":"Shipanya",
    "wof:placetype":"locality"
},
  "geometry": {"coordinates":[107.191,27.9345],"type":"Point"}
}