{
  "type": "Feature",
  "properties": {
    "gn:admin1_code":"11.0",
    "gn:asciiname":"Tuqiaoxi",
    "gn:country_code":"CN",
    "gn:dem":198,
    "gn:feature_class":"P",
    "gn:feature_code":"PPL",
    "gn:name":"Tuqiaoxi",
    "gn:population":0,
    "gn:timezone":"Asia/Shanghai",
    "iso:country":"CN",
    "name:zho_x_preferred":[
        "\u571f\u6865\u6eaa"
    ],
    "wof:name":"Tuqiaoxi",
    "wof:placetype":"locality"
},
  "geometry": {"coordinates":[109.77412,27.70069],"type":"Point"}
}