{
  "type": "Feature",
  "properties": {
    "gn:admin1_code":"25",
    "gn:asciiname":"Gengshankou",
    "gn:country_code":"CN",
    "gn:dem":48,
    "gn:feature_class":"P",
    "gn:feature_code":"PPL",
    "gn:name":"Gengshankou",
    "gn:population":0,
    "gn:timezone":"Asia/Shanghai",
    "iso:country":"CN",
    "name:zho_x_preferred":[
        "\u803f\u5c71\u53e3"
    ],
    "wof:name":"Gengshankou",
    "wof:placetype":"locality"
},
  "geometry": {"coordinates":[116.093,36.047],"type":"Point"}
}