{
  "type": "Feature",
  "properties": {
    "gn:admin1_code":"9.0",
    "gn:asciiname":"Qianliuzhuang",
    "gn:country_code":"CN",
    "gn:dem":68,
    "gn:feature_class":"P",
    "gn:feature_code":"PPL",
    "gn:name":"Qianliuzhuang",
    "gn:population":0,
    "gn:timezone":"Asia/Shanghai",
    "iso:country":"CN",
    "name:zho_x_preferred":[
        "\u524d\u5218\u5e84"
    ],
    "wof:name":"Qianliuzhuang",
    "wof:placetype":"locality"
},
  "geometry": {"coordinates":[114.39144,34.45306],"type":"Point"}
}