{
  "type": "Feature",
  "properties": {
    "gn:admin1_code":"33",
    "gn:asciiname":"Tieqiao",
    "gn:country_code":"CN",
    "gn:dem":207,
    "gn:feature_class":"P",
    "gn:feature_code":"PPLA4",
    "gn:name":"Tieqiao",
    "gn:population":0,
    "gn:timezone":"Asia/Shanghai",
    "iso:country":"CN",
    "name:und_x_variant":[
        "T\u2019ieh-so-ch\u2019iao",
        "Tieqiao",
        "Tieqiao Zhen"
    ],
    "name:zho_x_preferred":[
        "\u94c1\u6865"
    ],
    "name:zho_x_variant":[
        "\u94c1\u6865\u9547"
    ],
    "wof:name":"Tieqiao",
    "wof:placetype":"locality"
},
  "geometry": {"coordinates":[108.13361999999999,31.04001],"type":"Point"}
}