{
  "type": "Feature",
  "properties": {
    "gn:admin1_code":"25",
    "gn:asciiname":"Banguanzhuang",
    "gn:country_code":"CN",
    "gn:dem":61,
    "gn:feature_class":"P",
    "gn:feature_code":"PPL",
    "gn:name":"Banguanzhuang",
    "gn:population":0,
    "gn:timezone":"Asia/Shanghai",
    "iso:country":"CN",
    "name:zho_x_preferred":[
        "\u73ed\u5b98\u5e84"
    ],
    "wof:name":"Banguanzhuang",
    "wof:placetype":"locality"
},
  "geometry": {"coordinates":[118.581,34.8898],"type":"Point"}
}