{
  "type": "Feature",
  "properties": {
    "gn:admin1_code":"30.0",
    "gn:asciiname":"Qingling",
    "gn:country_code":"CN",
    "gn:dem":746,
    "gn:feature_class":"P",
    "gn:feature_code":"PPL",
    "gn:name":"Qingling",
    "gn:population":0,
    "gn:timezone":"Asia/Shanghai",
    "iso:country":"CN",
    "name:ceb_x_preferred":[
        "Qingling"
    ],
    "name:deu_x_preferred":[
        "Qingling"
    ],
    "name:fra_x_preferred":[
        "Qingling"
    ],
    "name:swe_x_preferred":[
        "Qingling"
    ],
    "name:zho_x_preferred":[
        "Qingling"
    ],
    "name:zho_x_variant":[
        "\u9752\u5cad"
    ],
    "wof:name":"Qingling",
    "wof:placetype":"locality"
},
  "geometry": {"coordinates":[113.53278,25.35194],"type":"Point"}
}