{
  "type": "Feature",
  "properties": {
    "gn:admin1_code":"19.0",
    "gn:asciiname":"Xinglongwa",
    "gn:country_code":"CN",
    "gn:dem":209,
    "gn:feature_class":"P",
    "gn:feature_code":"PPL",
    "gn:name":"Xinglongwa",
    "gn:population":0,
    "gn:timezone":"Asia/Shanghai",
    "iso:country":"CN",
    "name:und_x_variant":[
        "\u5174\u9686\u6d3c"
    ],
    "name:zho_x_preferred":[
        "\u5174\u9686\u6d3c"
    ],
    "wof:name":"Xinglongwa",
    "wof:placetype":"locality"
},
  "geometry": {"coordinates":[120.65497000000001,41.8482],"type":"Point"}
}