{
  "type": "Feature",
  "properties": {
    "gn:admin1_code":"3.0",
    "gn:asciiname":"Cha'ao",
    "gn:country_code":"CN",
    "gn:dem":246,
    "gn:feature_class":"P",
    "gn:feature_code":"PPL",
    "gn:name":"Cha\u2019ao",
    "gn:population":0,
    "gn:timezone":"Asia/Shanghai",
    "iso:country":"CN",
    "name:und_x_variant":[
        "Cha\u2019ao"
    ],
    "name:zho_x_preferred":[
        "\u8336\u5773"
    ],
    "wof:name":"Cha'ao",
    "wof:placetype":"locality"
},
  "geometry": {"coordinates":[114.30500000000001,28.933],"type":"Point"}
}