{
  "type": "Feature",
  "properties": {
    "gn:admin1_code":"4.0",
    "gn:asciiname":"Chenjicun",
    "gn:country_code":"CN",
    "gn:dem":13,
    "gn:feature_class":"P",
    "gn:feature_code":"PPL",
    "gn:name":"Chenjicun",
    "gn:population":0,
    "gn:timezone":"Asia/Shanghai",
    "iso:country":"CN",
    "name:und_x_variant":[
        "Chenji",
        "Chenjicun"
    ],
    "name:zho_x_preferred":[
        "\u9648\u96c6"
    ],
    "name:zho_x_variant":[
        "\u9648\u96c6\u6751"
    ],
    "wof:name":"Chenjicun",
    "wof:placetype":"locality"
},
  "geometry": {"coordinates":[118.71683,34.37362],"type":"Point"}
}