{
  "type": "Feature",
  "properties": {
    "gn:admin1_code":"4.0",
    "gn:asciiname":"Bakuangdai",
    "gn:country_code":"CN",
    "gn:dem":3,
    "gn:feature_class":"P",
    "gn:feature_code":"PPL",
    "gn:name":"Bakuangdai",
    "gn:population":0,
    "gn:timezone":"Asia/Shanghai",
    "iso:country":"CN",
    "name:und_x_variant":[
        "\u516b\u6846\u57ed"
    ],
    "name:zho_x_preferred":[
        "\u516b\u6846\u57ed"
    ],
    "wof:name":"Bakuangdai",
    "wof:placetype":"locality"
},
  "geometry": {"coordinates":[120.93755,31.92952],"type":"Point"}
}