{
  "type": "Feature",
  "properties": {
    "gn:admin1_code":"2",
    "gn:asciiname":"Lushi",
    "gn:country_code":"CN",
    "gn:dem":76,
    "gn:feature_class":"P",
    "gn:feature_code":"PPL",
    "gn:name":"Lushi",
    "gn:population":0,
    "gn:timezone":"Asia/Shanghai",
    "iso:country":"CN",
    "wof:name":"Lushi",
    "wof:placetype":"locality"
},
  "geometry": {"coordinates":[118.66222,28.93667],"type":"Point"}
}