{
  "type": "Feature",
  "properties": {
    "gn:admin1_code":"19.0",
    "gn:asciiname":"Taitougaocun",
    "gn:country_code":"CN",
    "gn:dem":270,
    "gn:feature_class":"P",
    "gn:feature_code":"PPL",
    "gn:name":"Taitougaocun",
    "gn:population":0,
    "gn:timezone":"Asia/Shanghai",
    "iso:country":"CN",
    "name:zho_x_preferred":[
        "\u53f0\u5934\u768b\u6751"
    ],
    "wof:name":"Taitougaocun",
    "wof:placetype":"locality"
},
  "geometry": {"coordinates":[121.818,42.0257],"type":"Point"}
}