{
  "type": "Feature",
  "properties": {
    "gn:admin1_code":"11.0",
    "gn:asciiname":"Baikewan",
    "gn:country_code":"CN",
    "gn:dem":581,
    "gn:feature_class":"P",
    "gn:feature_code":"PPL",
    "gn:name":"Baikewan",
    "gn:population":0,
    "gn:timezone":"Asia/Shanghai",
    "iso:country":"CN",
    "name:zho_x_preferred":[
        "\u767d\u5777\u6e7e"
    ],
    "wof:name":"Baikewan",
    "wof:placetype":"locality"
},
  "geometry": {"coordinates":[109.86499000000001,26.89075],"type":"Point"}
}