{
  "type": "Feature",
  "properties": {
    "gn:admin1_code":"07",
    "gn:asciiname":"Liangfengjie",
    "gn:country_code":"CN",
    "gn:dem":512,
    "gn:feature_class":"P",
    "gn:feature_code":"PPL",
    "gn:name":"Liangfengjie",
    "gn:population":0,
    "gn:timezone":"Asia/Shanghai",
    "iso:country":"CN",
    "name:zho_x_preferred":[
        "\u826f\u4e30\u8857"
    ],
    "wof:name":"Liangfengjie",
    "wof:placetype":"locality"
},
  "geometry": {"coordinates":[117.35778000000001,25.80722],"type":"Point"}
}