{
  "type": "Feature",
  "properties": {
    "gn:admin1_code":"10.0",
    "gn:asciiname":"Nandi",
    "gn:country_code":"CN",
    "gn:dem":8,
    "gn:feature_class":"P",
    "gn:feature_code":"PPL",
    "gn:name":"Nandi",
    "gn:population":0,
    "gn:timezone":"Asia/Shanghai",
    "iso:country":"CN",
    "name:bar_x_preferred":[
        "Nandi"
    ],
    "name:ceb_x_preferred":[
        "Nandi"
    ],
    "name:deu_x_preferred":[
        "Nandi"
    ],
    "name:fra_x_preferred":[
        "Nandi"
    ],
    "name:hrv_x_preferred":[
        "Nandi"
    ],
    "name:nld_x_preferred":[
        "Nandi"
    ],
    "name:pol_x_preferred":[
        "Nandi"
    ],
    "name:rus_x_preferred":[
        "\u041d\u0430\u043d\u0434\u0438"
    ],
    "name:swe_x_preferred":[
        "Nandi"
    ],
    "name:ukr_x_preferred":[
        "\u041d\u0430\u043d\u0434\u0456"
    ],
    "name:zho_x_preferred":[
        "\u5357\u5824"
    ],
    "wof:name":"Nandi",
    "wof:placetype":"locality"
},
  "geometry": {"coordinates":[117.07899999999999,38.4616],"type":"Point"}
}