{
  "type": "Feature",
  "properties": {
    "gn:admin1_code":"14",
    "gn:asciiname":"Seding",
    "gn:country_code":"CN",
    "gn:dem":3846,
    "gn:feature_class":"P",
    "gn:feature_code":"PPL",
    "gn:name":"Seding",
    "gn:population":0,
    "gn:timezone":"Asia/Urumqi",
    "iso:country":"CN",
    "name:zho_x_preferred":[
        "\u8272\u9876"
    ],
    "wof:name":"Seding",
    "wof:placetype":"locality"
},
  "geometry": {"coordinates":[88.7784,29.3676],"type":"Point"}
}