{
  "type": "Feature",
  "properties": {
    "gn:admin1_code":"14.0",
    "gn:asciiname":"Qiazhaga",
    "gn:country_code":"CN",
    "gn:dem":4609,
    "gn:feature_class":"P",
    "gn:feature_code":"PPL",
    "gn:name":"Qiazhaga",
    "gn:population":0,
    "gn:timezone":"Asia/Urumqi",
    "iso:country":"CN",
    "name:zho_x_preferred":[
        "\u6070\u624e\u560e"
    ],
    "wof:name":"Qiazhaga",
    "wof:placetype":"locality"
},
  "geometry": {"coordinates":[86.8409,29.3383],"type":"Point"}
}