{
  "type": "Feature",
  "properties": {
    "gn:admin1_code":"4.0",
    "gn:asciiname":"Sanshilian",
    "gn:country_code":"CN",
    "gn:dem":-2,
    "gn:feature_class":"P",
    "gn:feature_code":"PPL",
    "gn:name":"Sanshilian",
    "gn:population":0,
    "gn:timezone":"Asia/Shanghai",
    "iso:country":"CN",
    "name:zho_x_preferred":[
        "Sanshilian"
    ],
    "name:zho_x_variant":[
        "\u4e09\u5341\u8fde"
    ],
    "wof:name":"Sanshilian",
    "wof:placetype":"locality"
},
  "geometry": {"coordinates":[120.00596000000002,34.28455],"type":"Point"}
}