{
  "type": "Feature",
  "properties": {
    "gn:admin1_code":"26.0",
    "gn:asciiname":"Leijiashan",
    "gn:country_code":"CN",
    "gn:dem":1216,
    "gn:feature_class":"P",
    "gn:feature_code":"PPL",
    "gn:name":"Leijiashan",
    "gn:population":0,
    "gn:timezone":"Asia/Shanghai",
    "iso:country":"CN",
    "name:und_x_variant":[
        "\u96f7\u5bb6\u5c71"
    ],
    "wof:name":"Leijiashan",
    "wof:placetype":"locality"
},
  "geometry": {"coordinates":[107.09153999999999,33.26716],"type":"Point"}
}