{
  "type": "Feature",
  "properties": {
    "gn:admin1_code":"16.0",
    "gn:asciiname":"Nalai",
    "gn:country_code":"CN",
    "gn:dem":806,
    "gn:feature_class":"P",
    "gn:feature_code":"PPL",
    "gn:name":"Nalai",
    "gn:population":0,
    "gn:timezone":"Asia/Shanghai",
    "iso:country":"CN",
    "name:zho_x_preferred":[
        "\u90a3\u6765"
    ],
    "wof:name":"Nalai",
    "wof:placetype":"locality"
},
  "geometry": {"coordinates":[105.36499999999999,24.1424],"type":"Point"}
}