{
  "type": "Feature",
  "properties": {
    "gn:admin1_code":"13",
    "gn:asciiname":"Santuan Ererlian",
    "gn:country_code":"CN",
    "gn:dem":1052,
    "gn:feature_class":"P",
    "gn:feature_code":"PPL",
    "gn:name":"Santuan Ererlian",
    "gn:population":0,
    "gn:timezone":"Asia/Shanghai",
    "iso:country":"CN",
    "name:und_x_variant":[
        "\u4e09\u56e2\u4e8c\u4e8c\u8fde"
    ],
    "wof:name":"Santuan Ererlian",
    "wof:placetype":"locality"
},
  "geometry": {"coordinates":[79.90380999999999,40.41666],"type":"Point"}
}