{
  "type": "Feature",
  "properties": {
    "gn:admin1_code":"29",
    "gn:asciiname":"Shangmali",
    "gn:country_code":"CN",
    "gn:dem":1632,
    "gn:feature_class":"P",
    "gn:feature_code":"PPL",
    "gn:name":"Shangmali",
    "gn:population":0,
    "gn:timezone":"Asia/Shanghai",
    "iso:country":"CN",
    "name:zho_x_preferred":[
        "\u4e0a\u5417\u54e9"
    ],
    "wof:name":"Shangmali",
    "wof:placetype":"locality"
},
  "geometry": {"coordinates":[104.595,23.7894],"type":"Point"}
}