{
  "type": "Feature",
  "properties": {
    "gn:admin1_code":"26.0",
    "gn:asciiname":"Simaqiao",
    "gn:country_code":"CN",
    "gn:dem":1171,
    "gn:feature_class":"P",
    "gn:feature_code":"PPL",
    "gn:name":"Simaqiao",
    "gn:population":0,
    "gn:timezone":"Asia/Shanghai",
    "iso:country":"CN",
    "name:und_x_variant":[
        "\u53f8\u9a6c\u6865"
    ],
    "wof:name":"Simaqiao",
    "wof:placetype":"locality"
},
  "geometry": {"coordinates":[106.65336000000001,33.77901],"type":"Point"}
}