{
  "type": "Feature",
  "properties": {
    "gn:admin1_code":"15.0",
    "gn:asciiname":"Wugaoyao",
    "gn:country_code":"CN",
    "gn:dem":2646,
    "gn:feature_class":"P",
    "gn:feature_code":"PPL",
    "gn:name":"Wugaoyao",
    "gn:population":0,
    "gn:timezone":"Asia/Shanghai",
    "iso:country":"CN",
    "name:zho_x_preferred":[
        "\u4e94\u9ad8\u7a91"
    ],
    "wof:name":"Wugaoyao",
    "wof:placetype":"locality"
},
  "geometry": {"coordinates":[104.10299999999999,35.6211],"type":"Point"}
}