{
  "type": "Feature",
  "properties": {
    "gn:admin1_code":"24.0",
    "gn:asciiname":"Zhanshang",
    "gn:cc2":"CN",
    "gn:country_code":"CN",
    "gn:dem":1214,
    "gn:feature_class":"P",
    "gn:feature_code":"PPL",
    "gn:name":"Zhanshang",
    "gn:population":0,
    "gn:timezone":"Asia/Shanghai",
    "iso:country":"CN",
    "name:und_x_variant":[
        "Chan-shang",
        "Chan-shang-chen",
        "Zhanshang"
    ],
    "wof:name":"Zhanshang",
    "wof:placetype":"locality"
},
  "geometry": {"coordinates":[113.47667,37.6375],"type":"Point"}
}