{
  "type": "Feature",
  "properties": {
    "gn:admin1_code":"26.0",
    "gn:asciiname":"Baijiapingcun",
    "gn:country_code":"CN",
    "gn:dem":967,
    "gn:feature_class":"P",
    "gn:feature_code":"PPL",
    "gn:name":"Baijiapingcun",
    "gn:population":0,
    "gn:timezone":"Asia/Shanghai",
    "iso:country":"CN",
    "name:zho_x_preferred":[
        "\u767d\u5bb6\u576a\u6751"
    ],
    "wof:name":"Baijiapingcun",
    "wof:placetype":"locality"
},
  "geometry": {"coordinates":[110.00176,37.19303],"type":"Point"}
}