{
  "type": "Feature",
  "properties": {
    "gn:admin1_code":"30",
    "gn:asciiname":"Yexikeng",
    "gn:country_code":"CN",
    "gn:dem":618,
    "gn:feature_class":"P",
    "gn:feature_code":"PPL",
    "gn:name":"Yexikeng",
    "gn:population":0,
    "gn:timezone":"Asia/Shanghai",
    "iso:country":"CN",
    "name:zho_x_preferred":[
        "\u9875\u9521\u5751"
    ],
    "wof:name":"Yexikeng",
    "wof:placetype":"locality"
},
  "geometry": {"coordinates":[115.87482,23.6149],"type":"Point"}
}