{
  "type": "Feature",
  "properties": {
    "gn:admin1_code":"12.0",
    "gn:asciiname":"Niuxinshigou",
    "gn:country_code":"CN",
    "gn:dem":769,
    "gn:feature_class":"P",
    "gn:feature_code":"PPL",
    "gn:name":"Niuxinshigou",
    "gn:population":0,
    "gn:timezone":"Asia/Shanghai",
    "iso:country":"CN",
    "name:zho_x_preferred":[
        "\u725b\u5fc3\u77f3\u6c9f"
    ],
    "wof:name":"Niuxinshigou",
    "wof:placetype":"locality"
},
  "geometry": {"coordinates":[110.35987,32.52318],"type":"Point"}
}