{
  "type": "Feature",
  "properties": {
    "gn:admin1_code":"15.0",
    "gn:asciiname":"Mianhuadi",
    "gn:country_code":"CN",
    "gn:dem":2199,
    "gn:feature_class":"P",
    "gn:feature_code":"PPL",
    "gn:name":"Mianhuadi",
    "gn:population":0,
    "gn:timezone":"Asia/Shanghai",
    "iso:country":"CN",
    "name:und_x_variant":[
        "\u68c9\u82b1\u5730"
    ],
    "wof:name":"Mianhuadi",
    "wof:placetype":"locality"
},
  "geometry": {"coordinates":[104.77006,34.59475],"type":"Point"}
}