{
  "type": "Feature",
  "properties": {
    "gn:admin1_code":"7",
    "gn:asciiname":"Guangci",
    "gn:country_code":"CN",
    "gn:dem":416,
    "gn:feature_class":"P",
    "gn:feature_code":"PPL",
    "gn:name":"Guangci",
    "gn:population":0,
    "gn:timezone":"Asia/Shanghai",
    "iso:country":"CN",
    "name:zho_x_preferred":[
        "\u5149\u7960"
    ],
    "wof:name":"Guangci",
    "wof:placetype":"locality"
},
  "geometry": {"coordinates":[117.19943000000001,24.77276],"type":"Point"}
}