{
  "type": "Feature",
  "properties": {
    "gn:admin1_code":"10",
    "gn:asciiname":"Shijianfang",
    "gn:country_code":"CN",
    "gn:dem":1765,
    "gn:feature_class":"P",
    "gn:feature_code":"PPL",
    "gn:name":"Shijianfang",
    "gn:population":0,
    "gn:timezone":"Asia/Shanghai",
    "iso:country":"CN",
    "name:zho_x_preferred":[
        "\u5341\u95f4\u623f"
    ],
    "wof:name":"Shijianfang",
    "wof:placetype":"locality"
},
  "geometry": {"coordinates":[117.55018,42.58713],"type":"Point"}
}