{
  "type": "Feature",
  "properties": {
    "gn:admin1_code":"29.0",
    "gn:asciiname":"Yangqiaochong",
    "gn:country_code":"CN",
    "gn:dem":1977,
    "gn:feature_class":"P",
    "gn:feature_code":"PPL",
    "gn:name":"Yangqiaochong",
    "gn:population":0,
    "gn:timezone":"Asia/Shanghai",
    "iso:country":"CN",
    "name:zho_x_preferred":[
        "\u6768\u6865\u51b2"
    ],
    "wof:name":"Yangqiaochong",
    "wof:placetype":"locality"
},
  "geometry": {"coordinates":[103.393,25.8492],"type":"Point"}
}