{
  "type": "Feature",
  "properties": {
    "gn:admin1_code":"19.0",
    "gn:asciiname":"Xiaolanqi",
    "gn:country_code":"CN",
    "gn:dem":15,
    "gn:feature_class":"P",
    "gn:feature_code":"PPL",
    "gn:name":"Xiaolanqi",
    "gn:population":0,
    "gn:timezone":"Asia/Shanghai",
    "iso:country":"CN",
    "name:und_x_variant":[
        "\u5c0f\u5170\u65d7"
    ],
    "wof:name":"Xiaolanqi",
    "wof:placetype":"locality"
},
  "geometry": {"coordinates":[122.15939,40.22582],"type":"Point"}
}