{
  "type": "Feature",
  "properties": {
    "gn:admin1_code":"25",
    "gn:asciiname":"Beigao Sancun",
    "gn:country_code":"CN",
    "gn:dem":76,
    "gn:feature_class":"P",
    "gn:feature_code":"PPL",
    "gn:name":"Beigao Sancun",
    "gn:population":0,
    "gn:timezone":"Asia/Shanghai",
    "iso:country":"CN",
    "name:zho_x_preferred":[
        "\u5317\u9ad8\u4e09\u6751"
    ],
    "wof:name":"Beigao Sancun",
    "wof:placetype":"locality"
},
  "geometry": {"coordinates":[118.873,35.156],"type":"Point"}
}