{
  "type": "Feature",
  "properties": {
    "gn:admin1_code":"29",
    "gn:asciiname":"Luohebai",
    "gn:country_code":"CN",
    "gn:dem":2133,
    "gn:feature_class":"P",
    "gn:feature_code":"PPL",
    "gn:name":"Luohebai",
    "gn:population":0,
    "gn:timezone":"Asia/Shanghai",
    "iso:country":"CN",
    "name:zho_x_preferred":[
        "\u7f57\u5408\u767d"
    ],
    "wof:name":"Luohebai",
    "wof:placetype":"locality"
},
  "geometry": {"coordinates":[102.63946,24.23341],"type":"Point"}
}