{
  "type": "Feature",
  "properties": {
    "gn:admin1_code":"15.0",
    "gn:asciiname":"Mengshangchuan",
    "gn:country_code":"CN",
    "gn:dem":1955,
    "gn:feature_class":"P",
    "gn:feature_code":"PPL",
    "gn:name":"Mengshangchuan",
    "gn:population":0,
    "gn:timezone":"Asia/Shanghai",
    "iso:country":"CN",
    "name:zho_x_preferred":[
        "\u5b5f\u4e0a\u5ddd"
    ],
    "wof:name":"Mengshangchuan",
    "wof:placetype":"locality"
},
  "geometry": {"coordinates":[104.941,35.0512],"type":"Point"}
}