{
  "type": "Feature",
  "properties": {
    "gn:admin1_code":"18",
    "gn:asciiname":"Dawengzhi",
    "gn:country_code":"CN",
    "gn:dem":1130,
    "gn:feature_class":"P",
    "gn:feature_code":"PPL",
    "gn:name":"Dawengzhi",
    "gn:population":0,
    "gn:timezone":"Asia/Shanghai",
    "iso:country":"CN",
    "name:zho_x_preferred":[
        "\u5927\u7fc1\u5740"
    ],
    "wof:name":"Dawengzhi",
    "wof:placetype":"locality"
},
  "geometry": {"coordinates":[106.67700000000001,25.7965],"type":"Point"}
}