{
  "type": "Feature",
  "properties": {
    "gn:admin1_code":"16",
    "gn:asciiname":"Zhenjiao",
    "gn:country_code":"CN",
    "gn:dem":119,
    "gn:feature_class":"P",
    "gn:feature_code":"PPL",
    "gn:name":"Zhenjiao",
    "gn:population":0,
    "gn:timezone":"Asia/Shanghai",
    "iso:country":"CN",
    "name:zho_x_preferred":[
        "\u9547\u811a"
    ],
    "wof:name":"Zhenjiao",
    "wof:placetype":"locality"
},
  "geometry": {"coordinates":[109.56999999999999,22.4607],"type":"Point"}
}