{
  "type": "Feature",
  "properties": {
    "gn:admin1_code":"8.0",
    "gn:asciiname":"Beikaoshancun",
    "gn:country_code":"CN",
    "gn:dem":142,
    "gn:feature_class":"P",
    "gn:feature_code":"PPL",
    "gn:name":"Beikaoshancun",
    "gn:population":0,
    "gn:timezone":"Asia/Shanghai",
    "iso:country":"CN",
    "name:zho_x_preferred":[
        "\u5317\u9760\u5c71\u6751"
    ],
    "wof:name":"Beikaoshancun",
    "wof:placetype":"locality"
},
  "geometry": {"coordinates":[129.77923000000001,46.76451],"type":"Point"}
}