{
  "type": "Feature",
  "properties": {
    "gn:admin1_code":"16",
    "gn:asciiname":"Panhuangdian",
    "gn:country_code":"CN",
    "gn:dem":1526,
    "gn:elevation":"1748.0",
    "gn:feature_class":"P",
    "gn:feature_code":"PPL",
    "gn:name":"Panhuangdian",
    "gn:population":0,
    "gn:timezone":"Asia/Shanghai",
    "iso:country":"CN",
    "wof:name":"Panhuangdian",
    "wof:placetype":"locality"
},
  "geometry": {"coordinates":[110.88388999999999,25.36528],"type":"Point"}
}