{
  "type": "Feature",
  "properties": {
    "gn:admin1_code":"3.0",
    "gn:asciiname":"Huxi",
    "gn:country_code":"CN",
    "gn:dem":117,
    "gn:feature_class":"P",
    "gn:feature_code":"PPL",
    "gn:name":"Huxi",
    "gn:population":0,
    "gn:timezone":"Asia/Shanghai",
    "iso:country":"CN",
    "name:ceb_x_preferred":[
        "Huxi"
    ],
    "name:swe_x_preferred":[
        "Huxi"
    ],
    "name:und_x_variant":[
        "\u6e56\u6eaa"
    ],
    "wof:name":"Huxi",
    "wof:placetype":"locality"
},
  "geometry": {"coordinates":[114.96747000000001,28.58918],"type":"Point"}
}