{
  "type": "Feature",
  "properties": {
    "gn:admin1_code":"1.0",
    "gn:asciiname":"Wuliduicun",
    "gn:country_code":"CN",
    "gn:dem":48,
    "gn:feature_class":"P",
    "gn:feature_code":"PPL",
    "gn:name":"Wuliduicun",
    "gn:population":0,
    "gn:timezone":"Asia/Shanghai",
    "iso:country":"CN",
    "name:zho_x_preferred":[
        "\u4e94\u91cc\u5806\u6751"
    ],
    "wof:name":"Wuliduicun",
    "wof:placetype":"locality"
},
  "geometry": {"coordinates":[115.98430999999999,32.16748],"type":"Point"}
}