{
  "type": "Feature",
  "properties": {
    "gn:admin1_code":"31.0",
    "gn:asciiname":"Dongsheng",
    "gn:country_code":"CN",
    "gn:dem":23,
    "gn:feature_class":"P",
    "gn:feature_code":"PPL",
    "gn:name":"Dongsheng",
    "gn:population":0,
    "gn:timezone":"Asia/Shanghai",
    "iso:country":"CN",
    "name:zho_x_preferred":[
        "Dongsheng"
    ],
    "name:zho_x_variant":[
        "\u4e1c\u5347"
    ],
    "wof:name":"Dongsheng",
    "wof:placetype":"locality"
},
  "geometry": {"coordinates":[110.22569,19.74572],"type":"Point"}
}