{
  "type": "Feature",
  "properties": {
    "gn:admin1_code":"9.0",
    "gn:asciiname":"Lihuzhai",
    "gn:country_code":"CN",
    "gn:dem":74,
    "gn:feature_class":"P",
    "gn:feature_code":"PPL",
    "gn:name":"Lihuzhai",
    "gn:population":0,
    "gn:timezone":"Asia/Shanghai",
    "iso:country":"CN",
    "name:zho_x_preferred":[
        "\u674e\u80e1\u5be8"
    ],
    "wof:name":"Lihuzhai",
    "wof:placetype":"locality"
},
  "geometry": {"coordinates":[114.0414,35.30372],"type":"Point"}
}