{
  "type": "Feature",
  "properties": {
    "gn:admin1_code":"1.0",
    "gn:asciiname":"Yugengcun",
    "gn:country_code":"CN",
    "gn:dem":6,
    "gn:feature_class":"P",
    "gn:feature_code":"PPL",
    "gn:name":"Yugengcun",
    "gn:population":0,
    "gn:timezone":"Asia/Shanghai",
    "iso:country":"CN",
    "name:zho_x_preferred":[
        "\u4f59\u57c2\u6751"
    ],
    "wof:name":"Yugengcun",
    "wof:placetype":"locality"
},
  "geometry": {"coordinates":[117.73808,31.13206],"type":"Point"}
}