{
  "type": "Feature",
  "properties": {
    "gn:admin1_code":"6.0",
    "gn:asciiname":"Baicaomao",
    "gn:country_code":"CN",
    "gn:dem":2438,
    "gn:feature_class":"P",
    "gn:feature_code":"PPL",
    "gn:name":"Baicaomao",
    "gn:population":0,
    "gn:timezone":"Asia/Shanghai",
    "iso:country":"CN",
    "name:und_x_variant":[
        "\u767d\u8349\u6bdb"
    ],
    "wof:name":"Baicaomao",
    "wof:placetype":"locality"
},
  "geometry": {"coordinates":[102.37712000000001,35.74018],"type":"Point"}
}