{
  "type": "Feature",
  "properties": {
    "gn:admin1_code":"32.0",
    "gn:asciiname":"Gunziping",
    "gn:country_code":"CN",
    "gn:dem":1004,
    "gn:feature_class":"P",
    "gn:feature_code":"PPL",
    "gn:name":"Gunziping",
    "gn:population":0,
    "gn:timezone":"Asia/Shanghai",
    "iso:country":"CN",
    "name:zho_x_preferred":[
        "\u78d9\u5b50\u576a"
    ],
    "wof:name":"Gunziping",
    "wof:placetype":"locality"
},
  "geometry": {"coordinates":[108.09999999999999,32.1002],"type":"Point"}
}