{
  "type": "Feature",
  "properties": {
    "gn:admin1_code":"16.0",
    "gn:asciiname":"Banhe",
    "gn:country_code":"CN",
    "gn:dem":420,
    "gn:feature_class":"P",
    "gn:feature_code":"PPL",
    "gn:name":"Banhe",
    "gn:population":0,
    "gn:timezone":"Asia/Shanghai",
    "iso:country":"CN",
    "name:zho_x_preferred":[
        "\u677f\u5408"
    ],
    "wof:name":"Banhe",
    "wof:placetype":"locality"
},
  "geometry": {"coordinates":[107.687,24.5609],"type":"Point"}
}