{
  "type": "Feature",
  "properties": {
    "gn:admin1_code":"32.0",
    "gn:asciiname":"Hefeng",
    "gn:country_code":"CN",
    "gn:dem":519,
    "gn:feature_class":"P",
    "gn:feature_code":"PPL",
    "gn:name":"Hefeng",
    "gn:population":0,
    "gn:timezone":"Asia/Shanghai",
    "iso:country":"CN",
    "name:zho_x_preferred":[
        "\u79be\u4e30"
    ],
    "wof:name":"Hefeng",
    "wof:placetype":"locality"
},
  "geometry": {"coordinates":[104.21214000000001,31.15159],"type":"Point"}
}