{
  "type": "Feature",
  "properties": {
    "gn:admin1_code":"30",
    "gn:asciiname":"Yanzaocun",
    "gn:country_code":"CN",
    "gn:dem":4,
    "gn:feature_class":"P",
    "gn:feature_code":"PPL",
    "gn:name":"Yanzaocun",
    "gn:population":0,
    "gn:timezone":"Asia/Shanghai",
    "iso:country":"CN",
    "name:zho_x_preferred":[
        "\u76d0\u7076\u6751"
    ],
    "wof:name":"Yanzaocun",
    "wof:placetype":"locality"
},
  "geometry": {"coordinates":[111.90131,21.60422],"type":"Point"}
}