{
  "type": "Feature",
  "properties": {
    "gn:admin1_code":"33.0",
    "gn:asciiname":"Laochenshan",
    "gn:country_code":"CN",
    "gn:dem":340,
    "gn:feature_class":"P",
    "gn:feature_code":"PPL",
    "gn:name":"Laochenshan",
    "gn:population":0,
    "gn:timezone":"Asia/Shanghai",
    "iso:country":"CN",
    "name:zho_x_preferred":[
        "\u8001\u9648\u5c71"
    ],
    "wof:name":"Laochenshan",
    "wof:placetype":"locality"
},
  "geometry": {"coordinates":[107.95929,30.60083],"type":"Point"}
}