{
  "type": "Feature",
  "properties": {
    "gn:admin1_code":"8.0",
    "gn:asciiname":"Fuxingcun",
    "gn:country_code":"CN",
    "gn:dem":171,
    "gn:feature_class":"P",
    "gn:feature_code":"PPL",
    "gn:name":"Fuxingcun",
    "gn:population":0,
    "gn:timezone":"Asia/Shanghai",
    "iso:country":"CN",
    "name:zho_x_preferred":[
        "\u798f\u5174\u6751"
    ],
    "wof:name":"Fuxingcun",
    "wof:placetype":"locality"
},
  "geometry": {"coordinates":[127.20560999999999,46.58836],"type":"Point"}
}