{
  "type": "Feature",
  "properties": {
    "gn:admin1_code":"11.0",
    "gn:asciiname":"Anchong",
    "gn:country_code":"CN",
    "gn:dem":364,
    "gn:feature_class":"P",
    "gn:feature_code":"PPL",
    "gn:name":"Anchong",
    "gn:population":0,
    "gn:timezone":"Asia/Shanghai",
    "iso:country":"CN",
    "name:zho_x_preferred":[
        "\u6697\u51b2"
    ],
    "wof:name":"Anchong",
    "wof:placetype":"locality"
},
  "geometry": {"coordinates":[111.77217,25.01353],"type":"Point"}
}