{
  "type": "Feature",
  "properties": {
    "gn:admin1_code":"9.0",
    "gn:asciiname":"Zhangpocun",
    "gn:country_code":"CN",
    "gn:dem":69,
    "gn:feature_class":"P",
    "gn:feature_code":"PPL",
    "gn:name":"Zhangpocun",
    "gn:population":0,
    "gn:timezone":"Asia/Shanghai",
    "iso:country":"CN",
    "name:und_x_variant":[
        "\u5f20\u5761\u6751"
    ],
    "name:zho_x_preferred":[
        "\u5f20\u5761\u6751"
    ],
    "wof:name":"Zhangpocun",
    "wof:placetype":"locality"
},
  "geometry": {"coordinates":[113.934,33.35181],"type":"Point"}
}