{
  "type": "Feature",
  "properties": {
    "gn:admin1_code":"32.0",
    "gn:asciiname":"Duoyazong",
    "gn:country_code":"CN",
    "gn:dem":3673,
    "gn:feature_class":"P",
    "gn:feature_code":"PPL",
    "gn:name":"Duoyazong",
    "gn:population":0,
    "gn:timezone":"Asia/Shanghai",
    "iso:country":"CN",
    "name:zho_x_preferred":[
        "\u593a\u7259\u5b97"
    ],
    "wof:name":"Duoyazong",
    "wof:placetype":"locality"
},
  "geometry": {"coordinates":[101.367,29.9136],"type":"Point"}
}