{
  "type": "Feature",
  "properties": {
    "gn:admin1_code":"26.0",
    "gn:asciiname":"Xiaoshiban",
    "gn:country_code":"CN",
    "gn:dem":1229,
    "gn:feature_class":"P",
    "gn:feature_code":"PPL",
    "gn:name":"Xiaoshiban",
    "gn:population":0,
    "gn:timezone":"Asia/Shanghai",
    "iso:country":"CN",
    "name:zho_x_preferred":[
        "\u5c0f\u77f3\u677f"
    ],
    "wof:name":"Xiaoshiban",
    "wof:placetype":"locality"
},
  "geometry": {"coordinates":[109.22787,35.28514000000001],"type":"Point"}
}