{
  "type": "Feature",
  "properties": {
    "gn:admin1_code":"24",
    "gn:asciiname":"Wangjiacha",
    "gn:cc2":"CN",
    "gn:country_code":"CN",
    "gn:dem":1530,
    "gn:feature_class":"P",
    "gn:feature_code":"PPL",
    "gn:name":"Wangjiacha",
    "gn:population":0,
    "gn:timezone":"Asia/Shanghai",
    "iso:country":"CN",
    "name:und_x_variant":[
        "Wang-chia-ch\u2019a",
        "Wangjiacha"
    ],
    "wof:name":"Wangjiacha",
    "wof:placetype":"locality"
},
  "geometry": {"coordinates":[111.70917,38.62278],"type":"Point"}
}