{
  "type": "Feature",
  "properties": {
    "gn:admin1_code":"7.0",
    "gn:asciiname":"Huaxi",
    "gn:country_code":"CN",
    "gn:dem":229,
    "gn:feature_class":"P",
    "gn:feature_code":"PPL",
    "gn:name":"Huaxi",
    "gn:population":0,
    "gn:timezone":"Asia/Shanghai",
    "iso:country":"CN",
    "name:ceb_x_preferred":[
        "Huaxi"
    ],
    "name:deu_x_preferred":[
        "Huaxi"
    ],
    "name:epo_x_preferred":[
        "Huaxi"
    ],
    "name:zho_x_preferred":[
        "\u534e\u6eaa"
    ],
    "wof:name":"Huaxi",
    "wof:placetype":"locality"
},
  "geometry": {"coordinates":[117.86109,27.4562],"type":"Point"}
}