{
  "type": "Feature",
  "properties": {
    "gn:admin1_code":"29.0",
    "gn:asciiname":"Banfapo Jiujia",
    "gn:country_code":"CN",
    "gn:dem":1232,
    "gn:feature_class":"P",
    "gn:feature_code":"PPL",
    "gn:name":"Banfapo Jiujia",
    "gn:population":0,
    "gn:timezone":"Asia/Shanghai",
    "iso:country":"CN",
    "name:zho_x_preferred":[
        "\u73ed\u6cd5\u5761\u65e7\u5bb6"
    ],
    "wof:name":"Banfapo Jiujia",
    "wof:placetype":"locality"
},
  "geometry": {"coordinates":[100.53100000000001,22.4371],"type":"Point"}
}