{
  "type": "Feature",
  "properties": {
    "gn:admin1_code":"30.0",
    "gn:asciiname":"Chaotian",
    "gn:country_code":"CN",
    "gn:dem":10,
    "gn:feature_class":"P",
    "gn:feature_code":"PPL",
    "gn:name":"Chaotian",
    "gn:population":0,
    "gn:timezone":"Asia/Shanghai",
    "iso:country":"CN",
    "name:ceb_x_preferred":[
        "Chaotian"
    ],
    "name:zho_x_preferred":[
        "\u8d85\u7530"
    ],
    "wof:name":"Chaotian",
    "wof:placetype":"locality"
},
  "geometry": {"coordinates":[112.60595000000001,22.14781],"type":"Point"}
}