{
  "type": "Feature",
  "properties": {
    "gn:admin1_code":"29.0",
    "gn:asciiname":"Yaojiafen",
    "gn:country_code":"CN",
    "gn:dem":1803,
    "gn:feature_class":"P",
    "gn:feature_code":"PPL",
    "gn:name":"Yaojiafen",
    "gn:population":0,
    "gn:timezone":"Asia/Shanghai",
    "iso:country":"CN",
    "name:zho_x_preferred":[
        "\u59da\u5bb6\u575f"
    ],
    "wof:name":"Yaojiafen",
    "wof:placetype":"locality"
},
  "geometry": {"coordinates":[101.79600000000001,25.517],"type":"Point"}
}