{
  "type": "Feature",
  "properties": {
    "gn:admin1_code":"16",
    "gn:asciiname":"Changgouwei",
    "gn:country_code":"CN",
    "gn:dem":343,
    "gn:feature_class":"P",
    "gn:feature_code":"PPL",
    "gn:name":"Changgouwei",
    "gn:population":0,
    "gn:timezone":"Asia/Shanghai",
    "iso:country":"CN",
    "name:zho_x_preferred":[
        "\u957f\u6c9f\u5c3e"
    ],
    "wof:name":"Changgouwei",
    "wof:placetype":"locality"
},
  "geometry": {"coordinates":[109.871,25.1026],"type":"Point"}
}