{
  "type": "Feature",
  "properties": {
    "gn:admin1_code":"31",
    "gn:asciiname":"Gaoyuan",
    "gn:country_code":"CN",
    "gn:dem":36,
    "gn:feature_class":"P",
    "gn:feature_code":"PPL",
    "gn:name":"Gaoyuan",
    "gn:population":0,
    "gn:timezone":"Asia/Shanghai",
    "iso:country":"CN",
    "name:und_x_variant":[
        "\u9ad8\u56ed"
    ],
    "wof:name":"Gaoyuan",
    "wof:placetype":"locality"
},
  "geometry": {"coordinates":[108.73399999999999,18.7508],"type":"Point"}
}