{
  "type": "Feature",
  "properties": {
    "gn:admin1_code":"7.0",
    "gn:asciiname":"Mashantou",
    "gn:country_code":"CN",
    "gn:dem":466,
    "gn:feature_class":"P",
    "gn:feature_code":"PPL",
    "gn:name":"Mashantou",
    "gn:population":0,
    "gn:timezone":"Asia/Shanghai",
    "iso:country":"CN",
    "name:zho_x_preferred":[
        "Mashantou"
    ],
    "name:zho_x_variant":[
        "\u9a6c\u5c71\u5934"
    ],
    "wof:name":"Mashantou",
    "wof:placetype":"locality"
},
  "geometry": {"coordinates":[118.67111,26.44417],"type":"Point"}
}