{
  "type": "Feature",
  "properties": {
    "gn:admin1_code":"3.0",
    "gn:asciiname":"Zhongcun",
    "gn:country_code":"CN",
    "gn:dem":254,
    "gn:feature_class":"P",
    "gn:feature_code":"PPL",
    "gn:name":"Zhongcun",
    "gn:population":0,
    "gn:timezone":"Asia/Shanghai",
    "iso:country":"CN",
    "name:und_x_variant":[
        "\u4e2d\u6751"
    ],
    "wof:name":"Zhongcun",
    "wof:placetype":"locality"
},
  "geometry": {"coordinates":[115.90255999999999,26.22139],"type":"Point"}
}