{
  "type": "Feature",
  "properties": {
    "gn:admin1_code":"30.0",
    "gn:asciiname":"Xinpucun",
    "gn:country_code":"CN",
    "gn:dem":45,
    "gn:feature_class":"P",
    "gn:feature_code":"PPL",
    "gn:name":"Xinpucun",
    "gn:population":0,
    "gn:timezone":"Asia/Shanghai",
    "iso:country":"CN",
    "name:zho_x_preferred":[
        "\u65b0\u57d4\u6751"
    ],
    "wof:name":"Xinpucun",
    "wof:placetype":"locality"
},
  "geometry": {"coordinates":[116.83956999999999,23.8396],"type":"Point"}
}