{
  "type": "Feature",
  "properties": {
    "gn:admin1_code":"12",
    "gn:asciiname":"Nanqiao",
    "gn:country_code":"CN",
    "gn:dem":79,
    "gn:feature_class":"P",
    "gn:feature_code":"PPL",
    "gn:name":"Nanqiao",
    "gn:population":0,
    "gn:timezone":"Asia/Shanghai",
    "iso:country":"CN",
    "name:und_x_variant":[
        "Nan-ch\u2019iao",
        "Nanqiao",
        "\u5357\u6865"
    ],
    "wof:name":"Nanqiao",
    "wof:placetype":"locality"
},
  "geometry": {"coordinates":[112.20553,31.17141],"type":"Point"}
}