{
  "type": "Feature",
  "properties": {
    "gn:admin1_code":"14.0",
    "gn:asciiname":"Benduo",
    "gn:country_code":"CN",
    "gn:dem":3309,
    "gn:feature_class":"P",
    "gn:feature_code":"PPL",
    "gn:name":"Benduo",
    "gn:population":0,
    "gn:timezone":"Asia/Urumqi",
    "iso:country":"CN",
    "name:zho_x_preferred":[
        "\u7b28\u591a"
    ],
    "wof:name":"Benduo",
    "wof:placetype":"locality"
},
  "geometry": {"coordinates":[94.05833,30.46488],"type":"Point"}
}