{
  "type": "Feature",
  "properties": {
    "gn:admin1_code":"11.0",
    "gn:asciiname":"Zhongjiawan",
    "gn:country_code":"CN",
    "gn:dem":263,
    "gn:feature_class":"P",
    "gn:feature_code":"PPL",
    "gn:name":"Zhongjiawan",
    "gn:population":0,
    "gn:timezone":"Asia/Shanghai",
    "iso:country":"CN",
    "name:zho_x_preferred":[
        "\u949f\u5bb6\u6e7e"
    ],
    "wof:name":"Zhongjiawan",
    "wof:placetype":"locality"
},
  "geometry": {"coordinates":[113.55848,27.9387],"type":"Point"}
}