{
  "type": "Feature",
  "properties": {
    "gn:admin1_code":"26",
    "gn:asciiname":"Cangyou",
    "gn:country_code":"CN",
    "gn:dem":400,
    "gn:feature_class":"P",
    "gn:feature_code":"PPLA4",
    "gn:name":"Cangyou",
    "gn:population":0,
    "gn:timezone":"Asia/Shanghai",
    "iso:country":"CN",
    "name:und_x_variant":[
        "Cangyou Zhen",
        "Cangyou"
    ],
    "name:zho_x_preferred":[
        "\u82cd\u6e38"
    ],
    "name:zho_x_variant":[
        "\u82cd\u6e38\u9547"
    ],
    "wof:name":"Cangyou",
    "wof:placetype":"locality"
},
  "geometry": {"coordinates":[108.65443999999999,34.16324],"type":"Point"}
}