{
  "type": "Feature",
  "properties": {
    "gn:admin1_code":"32.0",
    "gn:asciiname":"Diaojiaolou",
    "gn:country_code":"CN",
    "gn:dem":409,
    "gn:feature_class":"P",
    "gn:feature_code":"PPL",
    "gn:name":"Diaojiaolou",
    "gn:population":0,
    "gn:timezone":"Asia/Shanghai",
    "iso:country":"CN",
    "name:zho_x_preferred":[
        "\u540a\u811a\u697c"
    ],
    "wof:name":"Diaojiaolou",
    "wof:placetype":"locality"
},
  "geometry": {"coordinates":[104.26300000000001,30.0526],"type":"Point"}
}