{
  "type": "Feature",
  "properties": {
    "gn:admin1_code":"19.0",
    "gn:asciiname":"Toutaizi",
    "gn:country_code":"CN",
    "gn:dem":24,
    "gn:feature_class":"P",
    "gn:feature_code":"PPL",
    "gn:name":"Toutaizi",
    "gn:population":0,
    "gn:timezone":"Asia/Shanghai",
    "iso:country":"CN",
    "name:und_x_variant":[
        "\u5934\u53f0\u5b50"
    ],
    "name:zho_x_preferred":[
        "\u5934\u53f0\u5b50"
    ],
    "wof:name":"Toutaizi",
    "wof:placetype":"locality"
},
  "geometry": {"coordinates":[123.11105000000001,41.60284],"type":"Point"}
}