{
  "type": "Feature",
  "properties": {
    "gn:admin1_code":"5.0",
    "gn:asciiname":"Qianxinfa",
    "gn:country_code":"CN",
    "gn:dem":164,
    "gn:feature_class":"P",
    "gn:feature_code":"PPL",
    "gn:name":"Qianxinfa",
    "gn:population":0,
    "gn:timezone":"Asia/Shanghai",
    "iso:country":"CN",
    "name:zho_x_preferred":[
        "\u524d\u65b0\u53d1"
    ],
    "wof:name":"Qianxinfa",
    "wof:placetype":"locality"
},
  "geometry": {"coordinates":[122.34031,44.74451],"type":"Point"}
}