{
  "type": "Feature",
  "properties": {
    "gn:admin1_code":"15.0",
    "gn:asciiname":"Majia Kouzi",
    "gn:country_code":"CN",
    "gn:dem":1829,
    "gn:feature_class":"P",
    "gn:feature_code":"PPL",
    "gn:name":"Majia Kouzi",
    "gn:population":0,
    "gn:timezone":"Asia/Shanghai",
    "iso:country":"CN",
    "name:zho_x_preferred":[
        "\u9a6c\u5bb6\u53e3\u5b50"
    ],
    "wof:name":"Majia Kouzi",
    "wof:placetype":"locality"
},
  "geometry": {"coordinates":[106.67100000000001,37.0493],"type":"Point"}
}