{
  "type": "Feature",
  "properties": {
    "gn:admin1_code":"14.0",
    "gn:asciiname":"Puggog",
    "gn:country_code":"CN",
    "gn:dem":4839,
    "gn:feature_class":"P",
    "gn:feature_code":"PPL",
    "gn:name":"Puggog",
    "gn:population":0,
    "gn:timezone":"Asia/Urumqi",
    "iso:country":"CN",
    "name:bod_x_preferred":[
        "Puggog"
    ],
    "name:zho_x_preferred":[
        "Poguo"
    ],
    "name:zho_x_variant":[
        "\u5761\u90ed"
    ],
    "wof:name":"Puggog",
    "wof:placetype":"locality"
},
  "geometry": {"coordinates":[94.20099999999999,32.101],"type":"Point"}
}