{
  "type": "Feature",
  "properties": {
    "gn:admin1_code":"14.0",
    "gn:asciiname":"Bilung",
    "gn:country_code":"CN",
    "gn:dem":4467,
    "gn:feature_class":"P",
    "gn:feature_code":"PPL",
    "gn:name":"Bilung",
    "gn:population":0,
    "gn:timezone":"Asia/Urumqi",
    "iso:country":"CN",
    "name:bod_x_preferred":[
        "Bilung"
    ],
    "name:zho_x_preferred":[
        "Bulong"
    ],
    "name:zho_x_variant":[
        "\u5e03\u9686",
        "Kedi",
        "\u514b\u7b2c",
        "\u8865\u9f99"
    ],
    "wof:name":"Bilung",
    "wof:placetype":"locality"
},
  "geometry": {"coordinates":[93.06278,31.90249],"type":"Point"}
}