{
  "type": "Feature",
  "properties": {
    "gn:admin1_code":"4.0",
    "gn:asciiname":"Beiyoujing",
    "gn:country_code":"CN",
    "gn:dem":3,
    "gn:feature_class":"P",
    "gn:feature_code":"PPL",
    "gn:name":"Beiyoujing",
    "gn:population":0,
    "gn:timezone":"Asia/Shanghai",
    "iso:country":"CN",
    "name:und_x_variant":[
        "\u5317\u5c24\u6cfe"
    ],
    "name:zho_x_preferred":[
        "\u5317\u5c24\u6cfe"
    ],
    "wof:name":"Beiyoujing",
    "wof:placetype":"locality"
},
  "geometry": {"coordinates":[120.8737,31.41064],"type":"Point"}
}