{
  "type": "Feature",
  "properties": {
    "gn:admin1_code":"16.0",
    "gn:asciiname":"Heshunling",
    "gn:country_code":"CN",
    "gn:dem":109,
    "gn:feature_class":"P",
    "gn:feature_code":"PPL",
    "gn:name":"Heshunling",
    "gn:population":0,
    "gn:timezone":"Asia/Shanghai",
    "iso:country":"CN",
    "name:zho_x_preferred":[
        "\u548c\u987a\u5cad"
    ],
    "wof:name":"Heshunling",
    "wof:placetype":"locality"
},
  "geometry": {"coordinates":[110.301,22.6887],"type":"Point"}
}