{
  "type": "Feature",
  "properties": {
    "gn:admin1_code":"25",
    "gn:asciiname":"Wuzhutai",
    "gn:country_code":"CN",
    "gn:dem":228,
    "gn:feature_class":"P",
    "gn:feature_code":"PPL",
    "gn:name":"Wuzhutai",
    "gn:population":0,
    "gn:timezone":"Asia/Shanghai",
    "iso:country":"CN",
    "name:zho_x_preferred":[
        "\u4e4c\u73e0\u53f0"
    ],
    "wof:name":"Wuzhutai",
    "wof:placetype":"locality"
},
  "geometry": {"coordinates":[117.693,35.8257],"type":"Point"}
}