{
  "type": "Feature",
  "properties": {
    "gn:admin1_code":"11.0",
    "gn:asciiname":"Shalingbei",
    "gn:country_code":"CN",
    "gn:dem":136,
    "gn:feature_class":"P",
    "gn:feature_code":"PPL",
    "gn:name":"Shalingbei",
    "gn:population":0,
    "gn:timezone":"Asia/Shanghai",
    "iso:country":"CN",
    "name:zho_x_preferred":[
        "\u6c99\u5cad\u80cc"
    ],
    "wof:name":"Shalingbei",
    "wof:placetype":"locality"
},
  "geometry": {"coordinates":[113.66133000000001,26.72234000000001],"type":"Point"}
}