{
  "type": "Feature",
  "properties": {
    "gn:admin1_code":"30.0",
    "gn:asciiname":"Zhuangxilongcun",
    "gn:country_code":"CN",
    "gn:dem":8,
    "gn:feature_class":"P",
    "gn:feature_code":"PPL",
    "gn:name":"Zhuangxilongcun",
    "gn:population":0,
    "gn:timezone":"Asia/Shanghai",
    "iso:country":"CN",
    "name:zho_x_preferred":[
        "\u5e84\u897f\u9647\u6751"
    ],
    "wof:name":"Zhuangxilongcun",
    "wof:placetype":"locality"
},
  "geometry": {"coordinates":[116.64745000000001,23.53998],"type":"Point"}
}