{
  "type": "Feature",
  "properties": {
    "gn:admin1_code":"26.0",
    "gn:asciiname":"Xianyiguancun",
    "gn:country_code":"CN",
    "gn:dem":1153,
    "gn:feature_class":"P",
    "gn:feature_code":"PPL",
    "gn:name":"Xianyiguancun",
    "gn:population":0,
    "gn:timezone":"Asia/Shanghai",
    "iso:country":"CN",
    "name:und_x_variant":[
        "Syan\u2019iguan\u2019",
        "Hsien-i-kuan",
        "Hsien-ning-kuan",
        "Xianyiguan",
        "Xianyiguancun"
    ],
    "name:zho_x_preferred":[
        "\u54b8\u5b9c\u5173\u6751"
    ],
    "wof:name":"Xianyiguancun",
    "wof:placetype":"locality"
},
  "geometry": {"coordinates":[106.67282,34.89184],"type":"Point"}
}