{
  "type": "Feature",
  "properties": {
    "gn:admin1_code":"32.0",
    "gn:asciiname":"Yangcungou",
    "gn:country_code":"CN",
    "gn:dem":1328,
    "gn:feature_class":"P",
    "gn:feature_code":"PPL",
    "gn:name":"Yangcungou",
    "gn:population":0,
    "gn:timezone":"Asia/Shanghai",
    "iso:country":"CN",
    "name:zho_x_preferred":[
        "\u7f8a\u6751\u6c9f"
    ],
    "wof:name":"Yangcungou",
    "wof:placetype":"locality"
},
  "geometry": {"coordinates":[102.77713,30.42142],"type":"Point"}
}