{
  "type": "Feature",
  "properties": {
    "gn:admin1_code":"8.0",
    "gn:asciiname":"Dongjiefangtun",
    "gn:country_code":"CN",
    "gn:dem":190,
    "gn:feature_class":"P",
    "gn:feature_code":"PPL",
    "gn:name":"Dongjiefangtun",
    "gn:population":0,
    "gn:timezone":"Asia/Shanghai",
    "iso:country":"CN",
    "name:zho_x_preferred":[
        "\u4e1c\u89e3\u653e\u5c6f"
    ],
    "wof:name":"Dongjiefangtun",
    "wof:placetype":"locality"
},
  "geometry": {"coordinates":[124.72698,48.2288],"type":"Point"}
}