{
  "type": "Feature",
  "properties": {
    "gn:admin1_code":"20.0",
    "gn:asciiname":"Xiaohuopan",
    "gn:country_code":"CN",
    "gn:dem":1214,
    "gn:feature_class":"P",
    "gn:feature_code":"PPL",
    "gn:name":"Xiaohuopan",
    "gn:population":0,
    "gn:timezone":"Asia/Shanghai",
    "iso:country":"CN",
    "name:und_x_variant":[
        "\u5c0f\u706b\u76d8"
    ],
    "wof:name":"Xiaohuopan",
    "wof:placetype":"locality"
},
  "geometry": {"coordinates":[111.51401,39.96191],"type":"Point"}
}