{
  "type": "Feature",
  "properties": {
    "gn:admin1_code":"21.0",
    "gn:asciiname":"Wangtian",
    "gn:country_code":"CN",
    "gn:dem":1106,
    "gn:feature_class":"P",
    "gn:feature_code":"PPL",
    "gn:name":"Wangtian",
    "gn:population":0,
    "gn:timezone":"Asia/Shanghai",
    "iso:country":"CN",
    "name:zho_x_preferred":[
        "\u738b\u7530"
    ],
    "wof:name":"Wangtian",
    "wof:placetype":"locality"
},
  "geometry": {"coordinates":[106.271,38.7045],"type":"Point"}
}