{
  "type": "Feature",
  "properties": {
    "gn:admin1_code":"8.0",
    "gn:asciiname":"Dongzhengjia",
    "gn:country_code":"CN",
    "gn:dem":155,
    "gn:feature_class":"P",
    "gn:feature_code":"PPL",
    "gn:name":"Dongzhengjia",
    "gn:population":0,
    "gn:timezone":"Asia/Shanghai",
    "iso:country":"CN",
    "name:zho_x_preferred":[
        "\u4e1c\u90d1\u5bb6"
    ],
    "wof:name":"Dongzhengjia",
    "wof:placetype":"locality"
},
  "geometry": {"coordinates":[126.46773,46.8541],"type":"Point"}
}