{
  "type": "Feature",
  "properties": {
    "gn:admin1_code":"3.0",
    "gn:asciiname":"Zhushanbei",
    "gn:country_code":"CN",
    "gn:dem":159,
    "gn:feature_class":"P",
    "gn:feature_code":"PPL",
    "gn:name":"Zhushanbei",
    "gn:population":0,
    "gn:timezone":"Asia/Shanghai",
    "iso:country":"CN",
    "name:und_x_variant":[
        "\u7af9\u5c71\u80cc"
    ],
    "wof:name":"Zhushanbei",
    "wof:placetype":"locality"
},
  "geometry": {"coordinates":[115.60787000000001,26.77446],"type":"Point"}
}