{
  "type": "Feature",
  "properties": {
    "gn:admin1_code":"04",
    "gn:asciiname":"Erkuang",
    "gn:country_code":"CN",
    "gn:dem":6,
    "gn:feature_class":"P",
    "gn:feature_code":"PPL",
    "gn:name":"Erkuang",
    "gn:population":0,
    "gn:timezone":"Asia/Shanghai",
    "iso:country":"CN",
    "name:und_x_variant":[
        "Erh-k\u2019uang-chen",
        "Erkuang",
        "\u4e8c\u5321",
        "Erkuangzhen"
    ],
    "name:zho_x_preferred":[
        "\u4e8c\u5321\u9547"
    ],
    "wof:name":"Erkuang",
    "wof:placetype":"locality"
},
  "geometry": {"coordinates":[121.286,31.9407],"type":"Point"}
}