{
  "type": "Feature",
  "properties": {
    "gn:admin1_code":"5.0",
    "gn:asciiname":"Fenghuang Tuozi",
    "gn:country_code":"CN",
    "gn:dem":141,
    "gn:feature_class":"P",
    "gn:feature_code":"PPL",
    "gn:name":"Fenghuang Tuozi",
    "gn:population":0,
    "gn:timezone":"Asia/Shanghai",
    "iso:country":"CN",
    "name:zho_x_preferred":[
        "\u51e4\u51f0\u5768\u5b50"
    ],
    "wof:name":"Fenghuang Tuozi",
    "wof:placetype":"locality"
},
  "geometry": {"coordinates":[123.22968,46.26073],"type":"Point"}
}