{
  "type": "Feature",
  "properties": {
    "gn:admin1_code":"1.0",
    "gn:asciiname":"Hutiancun",
    "gn:country_code":"CN",
    "gn:dem":219,
    "gn:feature_class":"P",
    "gn:feature_code":"PPL",
    "gn:name":"Hutiancun",
    "gn:population":0,
    "gn:timezone":"Asia/Shanghai",
    "iso:country":"CN",
    "name:zho_x_preferred":[
        "\u6e56\u7530\u6751"
    ],
    "wof:name":"Hutiancun",
    "wof:placetype":"locality"
},
  "geometry": {"coordinates":[117.76402,30.1332],"type":"Point"}
}