{
  "type": "Feature",
  "properties": {
    "gn:admin1_code":"8.0",
    "gn:asciiname":"Kaoshantuncun",
    "gn:country_code":"CN",
    "gn:dem":134,
    "gn:feature_class":"P",
    "gn:feature_code":"PPL",
    "gn:name":"Kaoshantuncun",
    "gn:population":0,
    "gn:timezone":"Asia/Shanghai",
    "iso:country":"CN",
    "name:zho_x_preferred":[
        "\u9760\u5c71\u5c6f\u6751"
    ],
    "wof:name":"Kaoshantuncun",
    "wof:placetype":"locality"
},
  "geometry": {"coordinates":[124.35697,45.622],"type":"Point"}
}