{
  "type": "Feature",
  "properties": {
    "gn:admin1_code":"15.0",
    "gn:asciiname":"Xiasan Zucun",
    "gn:country_code":"CN",
    "gn:dem":2382,
    "gn:feature_class":"P",
    "gn:feature_code":"PPL",
    "gn:name":"Xiasan Zucun",
    "gn:population":0,
    "gn:timezone":"Asia/Shanghai",
    "iso:country":"CN",
    "name:zho_x_preferred":[
        "\u4e0b\u4e09\u65cf\u6751"
    ],
    "wof:name":"Xiasan Zucun",
    "wof:placetype":"locality"
},
  "geometry": {"coordinates":[103.86517000000001,34.48109],"type":"Point"}
}