{
  "type": "Feature",
  "properties": {
    "gn:admin1_code":"29",
    "gn:asciiname":"Lalizhai",
    "gn:country_code":"CN",
    "gn:dem":1170,
    "gn:feature_class":"P",
    "gn:feature_code":"PPL",
    "gn:name":"Lalizhai",
    "gn:population":0,
    "gn:timezone":"Asia/Shanghai",
    "iso:country":"CN",
    "name:zho_x_preferred":[
        "\u62c9\u91cc\u5be8"
    ],
    "wof:name":"Lalizhai",
    "wof:placetype":"locality"
},
  "geometry": {"coordinates":[103.14803999999999,24.01992000000001],"type":"Point"}
}