{
  "type": "Feature",
  "properties": {
    "gn:admin1_code":"14.0",
    "gn:asciiname":"Cheridang",
    "gn:country_code":"CN",
    "gn:dem":3890,
    "gn:feature_class":"P",
    "gn:feature_code":"PPL",
    "gn:name":"Cheridang",
    "gn:population":0,
    "gn:timezone":"Asia/Urumqi",
    "iso:country":"CN",
    "name:zho_x_preferred":[
        "\u626f\u65e5\u5f53"
    ],
    "wof:name":"Cheridang",
    "wof:placetype":"locality"
},
  "geometry": {"coordinates":[98.38215,29.95597],"type":"Point"}
}