{
  "type": "Feature",
  "properties": {
    "gn:admin1_code":"07",
    "gn:asciiname":"Baipu",
    "gn:country_code":"CN",
    "gn:dem":53,
    "gn:feature_class":"P",
    "gn:feature_code":"PPL",
    "gn:name":"Baipu",
    "gn:population":0,
    "gn:timezone":"Asia/Shanghai",
    "iso:country":"CN",
    "name:zho_x_preferred":[
        "\u62dc\u57d4"
    ],
    "wof:name":"Baipu",
    "wof:placetype":"locality"
},
  "geometry": {"coordinates":[118.56917,25.03131],"type":"Point"}
}