{
  "type": "Feature",
  "properties": {
    "gn:admin1_code":"4.0",
    "gn:asciiname":"Qingfu",
    "gn:country_code":"CN",
    "gn:dem":5,
    "gn:feature_class":"P",
    "gn:feature_code":"PPL",
    "gn:name":"Qingfu",
    "gn:population":0,
    "gn:timezone":"Asia/Shanghai",
    "iso:country":"CN",
    "name:und_x_variant":[
        "\u9752\u4f0f"
    ],
    "wof:name":"Qingfu",
    "wof:placetype":"locality"
},
  "geometry": {"coordinates":[118.97365000000001,32.25441],"type":"Point"}
}