{
  "type": "Feature",
  "properties": {
    "gn:admin1_code":"25",
    "gn:asciiname":"Dongbeishan",
    "gn:country_code":"CN",
    "gn:dem":205,
    "gn:feature_class":"P",
    "gn:feature_code":"PPL",
    "gn:name":"Dongbeishan",
    "gn:population":0,
    "gn:timezone":"Asia/Shanghai",
    "iso:country":"CN",
    "name:zho_x_preferred":[
        "\u4e1c\u5317\u5c71"
    ],
    "wof:name":"Dongbeishan",
    "wof:placetype":"locality"
},
  "geometry": {"coordinates":[117.68600000000001,35.1881],"type":"Point"}
}