{
  "type": "Feature",
  "properties": {
    "gn:admin1_code":"16.0",
    "gn:asciiname":"Youli",
    "gn:country_code":"CN",
    "gn:dem":917,
    "gn:feature_class":"P",
    "gn:feature_code":"PPL",
    "gn:name":"Youli",
    "gn:population":0,
    "gn:timezone":"Asia/Shanghai",
    "iso:country":"CN",
    "name:zho_x_preferred":[
        "\u53f3\u91cc"
    ],
    "wof:name":"Youli",
    "wof:placetype":"locality"
},
  "geometry": {"coordinates":[107.098,24.5969],"type":"Point"}
}