{
  "type": "Feature",
  "properties": {
    "gn:admin1_code":"02",
    "gn:asciiname":"Zhongjiabang",
    "gn:country_code":"CN",
    "gn:dem":7,
    "gn:feature_class":"P",
    "gn:feature_code":"PPL",
    "gn:name":"Zhongjiabang",
    "gn:population":0,
    "gn:timezone":"Asia/Shanghai",
    "iso:country":"CN",
    "name:und_x_variant":[
        "Chung-chia-pang",
        "Zhongjiabang",
        "\u949f\u5bb6\u6d5c"
    ],
    "wof:name":"Zhongjiabang",
    "wof:placetype":"locality"
},
  "geometry": {"coordinates":[121.10458,30.63496],"type":"Point"}
}