{
  "type": "Feature",
  "properties": {
    "gn:admin1_code":"16.0",
    "gn:asciiname":"Meihuai",
    "gn:country_code":"CN",
    "gn:dem":120,
    "gn:feature_class":"P",
    "gn:feature_code":"PPL",
    "gn:name":"Meihuai",
    "gn:population":0,
    "gn:timezone":"Asia/Shanghai",
    "iso:country":"CN",
    "name:zho_x_preferred":[
        "\u7f8e\u6000"
    ],
    "wof:name":"Meihuai",
    "wof:placetype":"locality"
},
  "geometry": {"coordinates":[108.294,23.205],"type":"Point"}
}