{
  "type": "Feature",
  "properties": {
    "gn:admin1_code":"18",
    "gn:asciiname":"Sifangtu",
    "gn:country_code":"CN",
    "gn:dem":1345,
    "gn:feature_class":"P",
    "gn:feature_code":"PPL",
    "gn:name":"Sifangtu",
    "gn:population":0,
    "gn:timezone":"Asia/Shanghai",
    "iso:country":"CN",
    "name:zho_x_preferred":[
        "\u56db\u65b9\u571f"
    ],
    "wof:name":"Sifangtu",
    "wof:placetype":"locality"
},
  "geometry": {"coordinates":[106.608,28.3912],"type":"Point"}
}