{
  "type": "Feature",
  "properties": {
    "gn:admin1_code":"16.0",
    "gn:asciiname":"Shiyingchong",
    "gn:country_code":"CN",
    "gn:dem":262,
    "gn:feature_class":"P",
    "gn:feature_code":"PPL",
    "gn:name":"Shiyingchong",
    "gn:population":0,
    "gn:timezone":"Asia/Shanghai",
    "iso:country":"CN",
    "name:zho_x_preferred":[
        "\u77f3\u5e94\u51b2"
    ],
    "wof:name":"Shiyingchong",
    "wof:placetype":"locality"
},
  "geometry": {"coordinates":[110.53100000000001,23.0109],"type":"Point"}
}