{
  "type": "Feature",
  "properties": {
    "gn:admin1_code":"07",
    "gn:asciiname":"Chengsheshan",
    "gn:country_code":"CN",
    "gn:dem":671,
    "gn:feature_class":"P",
    "gn:feature_code":"PPL",
    "gn:name":"Chengsheshan",
    "gn:population":0,
    "gn:timezone":"Asia/Shanghai",
    "iso:country":"CN",
    "name:zho_x_preferred":[
        "\u7a0b\u820d\u5c71"
    ],
    "wof:name":"Chengsheshan",
    "wof:placetype":"locality"
},
  "geometry": {"coordinates":[117.44194,25.76278],"type":"Point"}
}