{
  "type": "Feature",
  "properties": {
    "gn:admin1_code":"25",
    "gn:asciiname":"Nankoubu",
    "gn:country_code":"CN",
    "gn:dem":40,
    "gn:feature_class":"P",
    "gn:feature_code":"PPL",
    "gn:name":"Nankoubu",
    "gn:population":0,
    "gn:timezone":"Asia/Shanghai",
    "iso:country":"CN",
    "name:zho_x_preferred":[
        "\u5357\u53e3\u57e0"
    ],
    "wof:name":"Nankoubu",
    "wof:placetype":"locality"
},
  "geometry": {"coordinates":[118.623,36.7982],"type":"Point"}
}