{
  "type": "Feature",
  "properties": {
    "gn:admin1_code":"04",
    "gn:asciiname":"Sizao Erdui",
    "gn:country_code":"CN",
    "gn:dem":3,
    "gn:feature_class":"P",
    "gn:feature_code":"PPLF",
    "gn:name":"Sizao Erdui",
    "gn:population":0,
    "gn:timezone":"Asia/Shanghai",
    "iso:country":"CN",
    "name:und_x_variant":[
        "Ssu-hu-tsao",
        "Sizao Erdui"
    ],
    "wof:name":"Sizao Erdui",
    "wof:placetype":"locality"
},
  "geometry": {"coordinates":[120.65139000000001,33.07167],"type":"Point"}
}