{
  "type": "Feature",
  "properties": {
    "gn:admin1_code":"25",
    "gn:asciiname":"Dongdacun",
    "gn:country_code":"CN",
    "gn:dem":40,
    "gn:feature_class":"P",
    "gn:feature_code":"PPL",
    "gn:name":"Dongdacun",
    "gn:population":0,
    "gn:timezone":"Asia/Shanghai",
    "iso:country":"CN",
    "name:zho_x_preferred":[
        "\u4e1c\u5927\u6751"
    ],
    "wof:name":"Dongdacun",
    "wof:placetype":"locality"
},
  "geometry": {"coordinates":[120.41500000000001,36.16472],"type":"Point"}
}