{
  "type": "Feature",
  "properties": {
    "gn:admin1_code":"16.0",
    "gn:asciiname":"Fulangchong",
    "gn:country_code":"CN",
    "gn:dem":233,
    "gn:feature_class":"P",
    "gn:feature_code":"PPL",
    "gn:name":"Fulangchong",
    "gn:population":0,
    "gn:timezone":"Asia/Shanghai",
    "iso:country":"CN",
    "name:zho_x_preferred":[
        "\u5bcc\u90ce\u51b2"
    ],
    "wof:name":"Fulangchong",
    "wof:placetype":"locality"
},
  "geometry": {"coordinates":[110.36499999999999,23.1381],"type":"Point"}
}