{
  "type": "Feature",
  "properties": {
    "gn:admin1_code":"29.0",
    "gn:asciiname":"Xudika",
    "gn:country_code":"CN",
    "gn:dem":1979,
    "gn:feature_class":"P",
    "gn:feature_code":"PPL",
    "gn:name":"Xudika",
    "gn:population":0,
    "gn:timezone":"Asia/Shanghai",
    "iso:country":"CN",
    "name:zho_x_preferred":[
        "\u8bb8\u5e95\u5361"
    ],
    "wof:name":"Xudika",
    "wof:placetype":"locality"
},
  "geometry": {"coordinates":[104.483,26.3199],"type":"Point"}
}