{
  "type": "Feature",
  "properties": {
    "gn:admin1_code":"3.0",
    "gn:asciiname":"Dingshan",
    "gn:country_code":"CN",
    "gn:dem":38,
    "gn:feature_class":"P",
    "gn:feature_code":"PPLA4",
    "gn:name":"Dingshan",
    "gn:population":0,
    "gn:timezone":"Asia/Shanghai",
    "iso:country":"CN",
    "name:und_x_variant":[
        "\u5b9a\u5c71",
        "Dingshan Zhen",
        "\u5b9a\u5c71\u9547"
    ],
    "wof:name":"Dingshan",
    "wof:placetype":"locality"
},
  "geometry": {"coordinates":[116.40992,29.82356],"type":"Point"}
}