{
  "type": "Feature",
  "properties": {
    "gn:admin1_code":"4.0",
    "gn:asciiname":"Houdaiyicun",
    "gn:country_code":"CN",
    "gn:dem":32,
    "gn:feature_class":"P",
    "gn:feature_code":"PPL",
    "gn:name":"Houdaiyicun",
    "gn:population":0,
    "gn:timezone":"Asia/Shanghai",
    "iso:country":"CN",
    "name:zho_x_preferred":[
        "\u540e\u4ee3\u9091\u6751"
    ],
    "wof:name":"Houdaiyicun",
    "wof:placetype":"locality"
},
  "geometry": {"coordinates":[118.8017,34.7301],"type":"Point"}
}