{
  "type": "Feature",
  "properties": {
    "gn:admin1_code":"4.0",
    "gn:asciiname":"Houzhuyuanzhuang",
    "gn:country_code":"CN",
    "gn:dem":13,
    "gn:feature_class":"P",
    "gn:feature_code":"PPL",
    "gn:name":"Houzhuyuanzhuang",
    "gn:population":0,
    "gn:timezone":"Asia/Shanghai",
    "iso:country":"CN",
    "name:zho_x_preferred":[
        "Houzhuyuanzhuang"
    ],
    "name:zho_x_variant":[
        "\u540e\u6731\u8881\u5e84"
    ],
    "wof:name":"Houzhuyuanzhuang",
    "wof:placetype":"locality"
},
  "geometry": {"coordinates":[119.11673999999999,33.64765999999999],"type":"Point"}
}