{
  "type": "Feature",
  "properties": {
    "gn:admin1_code":"16.0",
    "gn:asciiname":"Beixiangjie",
    "gn:country_code":"CN",
    "gn:dem":294,
    "gn:feature_class":"P",
    "gn:feature_code":"PPL",
    "gn:name":"Beixiangjie",
    "gn:population":0,
    "gn:timezone":"Asia/Shanghai",
    "iso:country":"CN",
    "name:zho_x_preferred":[
        "\u5317\u9999\u8857"
    ],
    "wof:name":"Beixiangjie",
    "wof:placetype":"locality"
},
  "geometry": {"coordinates":[107.809,24.7692],"type":"Point"}
}