{
  "type": "Feature",
  "properties": {
    "gn:admin1_code":"33.0",
    "gn:asciiname":"Baima",
    "gn:country_code":"CN",
    "gn:dem":530,
    "gn:feature_class":"P",
    "gn:feature_code":"PPL",
    "gn:name":"Baima",
    "gn:population":0,
    "gn:timezone":"Asia/Shanghai",
    "iso:country":"CN",
    "name:ceb_x_preferred":[
        "Baima"
    ],
    "name:deu_x_preferred":[
        "Baima"
    ],
    "name:nor_x_preferred":[
        "Baima"
    ],
    "name:zho_x_preferred":[
        "\u767d\u9a6c"
    ],
    "wof:name":"Baima",
    "wof:placetype":"locality"
},
  "geometry": {"coordinates":[107.67983999999998,30.29464],"type":"Point"}
}