{
  "type": "Feature",
  "properties": {
    "gn:admin1_code":"14.0",
    "gn:asciiname":"Nangecun",
    "gn:country_code":"CN",
    "gn:dem":3155,
    "gn:feature_class":"P",
    "gn:feature_code":"PPL",
    "gn:name":"Nangecun",
    "gn:population":0,
    "gn:timezone":"Asia/Urumqi",
    "iso:country":"CN",
    "name:zho_x_preferred":[
        "\u5357\u683c\u6751"
    ],
    "wof:name":"Nangecun",
    "wof:placetype":"locality"
},
  "geometry": {"coordinates":[98.95925,30.25556],"type":"Point"}
}