{
  "type": "Feature",
  "properties": {
    "gn:admin1_code":"19.0",
    "gn:asciiname":"Shibeicun",
    "gn:country_code":"CN",
    "gn:dem":386,
    "gn:feature_class":"P",
    "gn:feature_code":"PPL",
    "gn:name":"Shibeicun",
    "gn:population":0,
    "gn:timezone":"Asia/Shanghai",
    "iso:country":"CN",
    "name:und_x_variant":[
        "Shih-p\u2019ai-kou"
    ],
    "name:zho_x_preferred":[
        "\u77f3\u7891\u6751"
    ],
    "wof:name":"Shibeicun",
    "wof:placetype":"locality"
},
  "geometry": {"coordinates":[125.121,41.7762],"type":"Point"}
}