{
  "type": "Feature",
  "properties": {
    "gn:admin1_code":"2.0",
    "gn:asciiname":"Menlinhou",
    "gn:country_code":"CN",
    "gn:dem":968,
    "gn:feature_class":"P",
    "gn:feature_code":"PPL",
    "gn:name":"Menlinhou",
    "gn:population":0,
    "gn:timezone":"Asia/Shanghai",
    "iso:country":"CN",
    "name:zho_x_preferred":[
        "\u95e8\u6797\u540e"
    ],
    "wof:name":"Menlinhou",
    "wof:placetype":"locality"
},
  "geometry": {"coordinates":[119.13225,27.51647],"type":"Point"}
}