{
  "type": "Feature",
  "properties": {
    "gn:admin1_code":"32.0",
    "gn:asciiname":"Yindou",
    "gn:country_code":"CN",
    "gn:dem":652,
    "gn:feature_class":"P",
    "gn:feature_code":"PPL",
    "gn:name":"Yindou",
    "gn:population":0,
    "gn:timezone":"Asia/Shanghai",
    "iso:country":"CN",
    "name:und_x_variant":[
        "\u5370\u6597"
    ],
    "wof:name":"Yindou",
    "wof:placetype":"locality"
},
  "geometry": {"coordinates":[106.45202999999999,32.09059],"type":"Point"}
}