{
  "type": "Feature",
  "properties": {
    "gn:admin1_code":"13",
    "gn:asciiname":"Kashidun",
    "gn:country_code":"CN",
    "gn:dem":1293,
    "gn:feature_class":"P",
    "gn:feature_code":"PPL",
    "gn:name":"Kashidun",
    "gn:population":0,
    "gn:timezone":"Asia/Shanghai",
    "iso:country":"CN",
    "name:und_x_variant":[
        "\u5580\u4ec0\u58a9"
    ],
    "wof:name":"Kashidun",
    "wof:placetype":"locality"
},
  "geometry": {"coordinates":[77.26749000000002,38.078],"type":"Point"}
}