{
  "type": "Feature",
  "properties": {
    "gn:admin1_code":"1.0",
    "gn:asciiname":"Sanchacun",
    "gn:country_code":"CN",
    "gn:dem":21,
    "gn:feature_class":"P",
    "gn:feature_code":"PPL",
    "gn:name":"Sanchacun",
    "gn:population":0,
    "gn:timezone":"Asia/Shanghai",
    "iso:country":"CN",
    "name:zho_x_preferred":[
        "\u4e09\u6c4a\u6751"
    ],
    "wof:name":"Sanchacun",
    "wof:placetype":"locality"
},
  "geometry": {"coordinates":[116.52405,32.39599],"type":"Point"}
}