{
  "type": "Feature",
  "properties": {
    "gn:admin1_code":"15.0",
    "gn:asciiname":"Qinjiajie",
    "gn:country_code":"CN",
    "gn:dem":2040,
    "gn:feature_class":"P",
    "gn:feature_code":"PPL",
    "gn:name":"Qinjiajie",
    "gn:population":0,
    "gn:timezone":"Asia/Shanghai",
    "iso:country":"CN",
    "name:zho_x_preferred":[
        "\u79e6\u5bb6\u8857"
    ],
    "wof:name":"Qinjiajie",
    "wof:placetype":"locality"
},
  "geometry": {"coordinates":[103.371,37.4223],"type":"Point"}
}