{
  "type": "Feature",
  "properties": {
    "gn:admin1_code":"18",
    "gn:asciiname":"Chalayuan",
    "gn:country_code":"CN",
    "gn:dem":1118,
    "gn:feature_class":"P",
    "gn:feature_code":"PPL",
    "gn:name":"Chalayuan",
    "gn:population":0,
    "gn:timezone":"Asia/Shanghai",
    "iso:country":"CN",
    "name:zho_x_preferred":[
        "\u63d2\u814a\u56ed"
    ],
    "wof:name":"Chalayuan",
    "wof:placetype":"locality"
},
  "geometry": {"coordinates":[106.783,28.5625],"type":"Point"}
}