{
  "type": "Feature",
  "properties": {
    "gn:admin1_code":"9",
    "gn:asciiname":"Gaodian",
    "gn:country_code":"CN",
    "gn:dem":64,
    "gn:feature_class":"P",
    "gn:feature_code":"PPL",
    "gn:name":"Gaodian",
    "gn:population":0,
    "gn:timezone":"Asia/Shanghai",
    "iso:country":"CN",
    "wof:name":"Gaodian",
    "wof:placetype":"locality"
},
  "geometry": {"coordinates":[114.68944,35.13389],"type":"Point"}
}