{
  "type": "Feature",
  "properties": {
    "gn:admin1_code":"16.0",
    "gn:asciiname":"Zhongcun",
    "gn:country_code":"CN",
    "gn:dem":562,
    "gn:feature_class":"P",
    "gn:feature_code":"PPL",
    "gn:name":"Zhongcun",
    "gn:population":0,
    "gn:timezone":"Asia/Shanghai",
    "iso:country":"CN",
    "name:zho_x_preferred":[
        "\u4e2d\u6751"
    ],
    "wof:name":"Zhongcun",
    "wof:placetype":"locality"
},
  "geometry": {"coordinates":[109.56,24.8317],"type":"Point"}
}