{
  "type": "Feature",
  "properties": {
    "gn:admin1_code":"11.0",
    "gn:asciiname":"Dafangyu",
    "gn:country_code":"CN",
    "gn:dem":533,
    "gn:feature_class":"P",
    "gn:feature_code":"PPL",
    "gn:name":"Dafangyu",
    "gn:population":0,
    "gn:timezone":"Asia/Shanghai",
    "iso:country":"CN",
    "name:zho_x_preferred":[
        "\u5927\u65b9\u5cea"
    ],
    "wof:name":"Dafangyu",
    "wof:placetype":"locality"
},
  "geometry": {"coordinates":[110.72329000000001,29.72257],"type":"Point"}
}