{
  "type": "Feature",
  "properties": {
    "gn:admin1_code":"25.0",
    "gn:asciiname":"Dongliangezhuangcun",
    "gn:country_code":"CN",
    "gn:dem":67,
    "gn:feature_class":"P",
    "gn:feature_code":"PPL",
    "gn:name":"Dongliangezhuangcun",
    "gn:population":0,
    "gn:timezone":"Asia/Shanghai",
    "iso:country":"CN",
    "name:zho_x_preferred":[
        "\u4e1c\u8fde\u6208\u5e84\u6751"
    ],
    "wof:name":"Dongliangezhuangcun",
    "wof:placetype":"locality"
},
  "geometry": {"coordinates":[120.26716,36.91642],"type":"Point"}
}