{
  "type": "Feature",
  "properties": {
    "gn:admin1_code":"15.0",
    "gn:asciiname":"Yangpotai",
    "gn:country_code":"CN",
    "gn:dem":2262,
    "gn:feature_class":"P",
    "gn:feature_code":"PPL",
    "gn:name":"Yangpotai",
    "gn:population":0,
    "gn:timezone":"Asia/Shanghai",
    "iso:country":"CN",
    "name:zho_x_preferred":[
        "\u9633\u5761\u53f0"
    ],
    "wof:name":"Yangpotai",
    "wof:placetype":"locality"
},
  "geometry": {"coordinates":[104.381,35.2864],"type":"Point"}
}