{
  "type": "Feature",
  "properties": {
    "gn:admin1_code":"31.0",
    "gn:asciiname":"Shifen",
    "gn:country_code":"CN",
    "gn:dem":467,
    "gn:feature_class":"P",
    "gn:feature_code":"PPL",
    "gn:name":"Shifen",
    "gn:population":0,
    "gn:timezone":"Asia/Shanghai",
    "iso:country":"CN",
    "name:zho_x_preferred":[
        "\u4ec0\u594b"
    ],
    "wof:name":"Shifen",
    "wof:placetype":"locality"
},
  "geometry": {"coordinates":[109.49408,18.7087],"type":"Point"}
}