{
  "type": "Feature",
  "properties": {
    "gn:admin1_code":"4.0",
    "gn:asciiname":"Jing'ansan",
    "gn:country_code":"CN",
    "gn:dem":41,
    "gn:feature_class":"P",
    "gn:feature_code":"PPL",
    "gn:name":"Jing\u2019ansan",
    "gn:population":0,
    "gn:timezone":"Asia/Shanghai",
    "iso:country":"CN",
    "name:und_x_variant":[
        "Jing\u2019ansan"
    ],
    "name:zho_x_preferred":[
        "\u656c\u5b89\u4e09"
    ],
    "wof:name":"Jing'ansan",
    "wof:placetype":"locality"
},
  "geometry": {"coordinates":[116.91710999999999,34.50232],"type":"Point"}
}