{
  "type": "Feature",
  "properties": {
    "gn:admin1_code":"08",
    "gn:asciiname":"Shibazhan",
    "gn:cc2":"CN",
    "gn:country_code":"CN",
    "gn:dem":334,
    "gn:feature_class":"P",
    "gn:feature_code":"PPL",
    "gn:name":"Shibazhan",
    "gn:population":0,
    "gn:timezone":"Asia/Shanghai",
    "iso:country":"CN",
    "name:und_x_variant":[
        "Shih-pa-chen",
        "Shih-pa-cha",
        "Shibazhan Orogenzu Xiang",
        "Shibazhan"
    ],
    "wof:name":"Shibazhan",
    "wof:placetype":"locality"
},
  "geometry": {"coordinates":[125.42667,52.4275],"type":"Point"}
}