{
  "type": "Feature",
  "properties": {
    "gn:admin1_code":"11.0",
    "gn:asciiname":"Dashuzui",
    "gn:country_code":"CN",
    "gn:dem":68,
    "gn:feature_class":"P",
    "gn:feature_code":"PPL",
    "gn:name":"Dashuzui",
    "gn:population":0,
    "gn:timezone":"Asia/Shanghai",
    "iso:country":"CN",
    "name:zho_x_preferred":[
        "\u5927\u6811\u5480"
    ],
    "wof:name":"Dashuzui",
    "wof:placetype":"locality"
},
  "geometry": {"coordinates":[113.26514,28.18629],"type":"Point"}
}