{
  "type": "Feature",
  "properties": {
    "gn:admin1_code":"4.0",
    "gn:asciiname":"Panlicun",
    "gn:country_code":"CN",
    "gn:dem":3,
    "gn:feature_class":"P",
    "gn:feature_code":"PPL",
    "gn:name":"Panlicun",
    "gn:population":0,
    "gn:timezone":"Asia/Shanghai",
    "iso:country":"CN",
    "name:zho_x_preferred":[
        "\u6f58\u674e\u6751"
    ],
    "wof:name":"Panlicun",
    "wof:placetype":"locality"
},
  "geometry": {"coordinates":[120.65882000000001,32.72212],"type":"Point"}
}