{
  "type": "Feature",
  "properties": {
    "gn:admin1_code":"04",
    "gn:asciiname":"Jiangjia",
    "gn:country_code":"CN",
    "gn:dem":5,
    "gn:feature_class":"P",
    "gn:feature_code":"PPL",
    "gn:name":"Jiangjia",
    "gn:population":0,
    "gn:timezone":"Asia/Shanghai",
    "iso:country":"CN",
    "name:und_x_variant":[
        "Chiang-chia-chen",
        "Chang-chia-chen",
        "Jiangjia",
        "\u6c5f\u5bb6",
        "Jiangjiazhen",
        "Jiangjia Zhen",
        "\u6c5f\u5bb6\u9547"
    ],
    "wof:name":"Jiangjia",
    "wof:placetype":"locality"
},
  "geometry": {"coordinates":[121.46525,31.98376],"type":"Point"}
}