{
  "type": "Feature",
  "properties": {
    "gn:admin1_code":"7.0",
    "gn:asciiname":"Shaquyang",
    "gn:country_code":"CN",
    "gn:dem":720,
    "gn:feature_class":"P",
    "gn:feature_code":"PPL",
    "gn:name":"Shaquyang",
    "gn:population":0,
    "gn:timezone":"Asia/Shanghai",
    "iso:country":"CN",
    "name:zho_x_preferred":[
        "\u6c99\u6e20\u6d0b"
    ],
    "wof:name":"Shaquyang",
    "wof:placetype":"locality"
},
  "geometry": {"coordinates":[117.94983999999999,27.85866],"type":"Point"}
}