{
  "type": "Feature",
  "properties": {
    "gn:admin1_code":"3.0",
    "gn:asciiname":"Qingtangxin",
    "gn:country_code":"CN",
    "gn:dem":42,
    "gn:feature_class":"P",
    "gn:feature_code":"PPL",
    "gn:name":"Qingtangxin",
    "gn:population":0,
    "gn:timezone":"Asia/Shanghai",
    "iso:country":"CN",
    "name:und_x_variant":[
        "\u9752\u5858\u65b0"
    ],
    "wof:name":"Qingtangxin",
    "wof:placetype":"locality"
},
  "geometry": {"coordinates":[117.19949,29.36213],"type":"Point"}
}