{
  "type": "Feature",
  "properties": {
    "gn:admin1_code":"5.0",
    "gn:asciiname":"Jiajia Wobu",
    "gn:country_code":"CN",
    "gn:dem":144,
    "gn:feature_class":"P",
    "gn:feature_code":"PPL",
    "gn:name":"Jiajia Wobu",
    "gn:population":0,
    "gn:timezone":"Asia/Shanghai",
    "iso:country":"CN",
    "name:zho_x_preferred":[
        "\u8d3e\u5bb6\u7a9d\u5821"
    ],
    "wof:name":"Jiajia Wobu",
    "wof:placetype":"locality"
},
  "geometry": {"coordinates":[123.15273000000001,44.89078],"type":"Point"}
}