{
  "type": "Feature",
  "properties": {
    "gn:admin1_code":"14.0",
    "gn:asciiname":"Sandain",
    "gn:country_code":"CN",
    "gn:dem":3590,
    "gn:feature_class":"P",
    "gn:feature_code":"PPLF",
    "gn:name":"Sandain",
    "gn:population":0,
    "gn:timezone":"Asia/Urumqi",
    "iso:country":"CN",
    "name:bod_x_preferred":[
        "Sandain"
    ],
    "name:zho_x_preferred":[
        "Sangdeng"
    ],
    "name:zho_x_variant":[
        "\u6851\u767b",
        "Zhamu Qu",
        "\u624e\u6728\u533a"
    ],
    "wof:name":"Sandain",
    "wof:placetype":"locality"
},
  "geometry": {"coordinates":[95.70099999999999,29.801],"type":"Point"}
}