{
  "type": "Feature",
  "properties": {
    "gn:admin1_code":"4.0",
    "gn:asciiname":"Dawuzhuang",
    "gn:country_code":"CN",
    "gn:dem":28,
    "gn:feature_class":"P",
    "gn:feature_code":"PPL",
    "gn:name":"Dawuzhuang",
    "gn:population":0,
    "gn:timezone":"Asia/Shanghai",
    "iso:country":"CN",
    "wof:name":"Dawuzhuang",
    "wof:placetype":"locality"
},
  "geometry": {"coordinates":[117.7625,33.96667],"type":"Point"}
}