{
  "type": "Feature",
  "properties": {
    "gn:admin1_code":"9",
    "gn:asciiname":"Caoshou",
    "gn:country_code":"CN",
    "gn:dem":56,
    "gn:feature_class":"P",
    "gn:feature_code":"PPL",
    "gn:name":"Caoshou",
    "gn:population":0,
    "gn:timezone":"Asia/Shanghai",
    "iso:country":"CN",
    "name:zho_x_preferred":[
        "\u64cd\u5b88"
    ],
    "wof:name":"Caoshou",
    "wof:placetype":"locality"
},
  "geometry": {"coordinates":[115.05756,36.08828],"type":"Point"}
}