{
  "type": "Feature",
  "properties": {
    "gn:admin1_code":"29.0",
    "gn:asciiname":"Shangpanjia",
    "gn:country_code":"CN",
    "gn:dem":2132,
    "gn:feature_class":"P",
    "gn:feature_code":"PPL",
    "gn:name":"Shangpanjia",
    "gn:population":0,
    "gn:timezone":"Asia/Shanghai",
    "iso:country":"CN",
    "name:zho_x_preferred":[
        "\u4e0a\u6f58\u5bb6"
    ],
    "wof:name":"Shangpanjia",
    "wof:placetype":"locality"
},
  "geometry": {"coordinates":[100.509,24.9073],"type":"Point"}
}