{
  "type": "Feature",
  "properties": {
    "gn:admin1_code":"29.0",
    "gn:asciiname":"Tuantian",
    "gn:country_code":"CN",
    "gn:dem":1788,
    "gn:feature_class":"P",
    "gn:feature_code":"PPL",
    "gn:name":"Tuantian",
    "gn:population":0,
    "gn:timezone":"Asia/Shanghai",
    "iso:country":"CN",
    "name:zho_x_preferred":[
        "\u56e2\u7530"
    ],
    "wof:name":"Tuantian",
    "wof:placetype":"locality"
},
  "geometry": {"coordinates":[101.69,23.602],"type":"Point"}
}