{
  "type": "Feature",
  "properties": {
    "gn:admin1_code":"04",
    "gn:asciiname":"Zhangshecun",
    "gn:country_code":"CN",
    "gn:dem":5,
    "gn:feature_class":"P",
    "gn:feature_code":"PPL",
    "gn:name":"Zhangshecun",
    "gn:population":0,
    "gn:timezone":"Asia/Shanghai",
    "iso:country":"CN",
    "name:und_x_variant":[
        "Zhangshe",
        "\u5f20\u820d",
        "Chang-she-chen",
        "Zhangshecun"
    ],
    "name:zho_x_preferred":[
        "\u5f20\u820d\u6751"
    ],
    "wof:name":"Zhangshecun",
    "wof:placetype":"locality"
},
  "geometry": {"coordinates":[120.13428,31.56671],"type":"Point"}
}