{
  "type": "Feature",
  "properties": {
    "gn:admin1_code":"12.0",
    "gn:asciiname":"Longdongwan",
    "gn:country_code":"CN",
    "gn:dem":813,
    "gn:feature_class":"P",
    "gn:feature_code":"PPL",
    "gn:name":"Longdongwan",
    "gn:population":0,
    "gn:timezone":"Asia/Shanghai",
    "iso:country":"CN",
    "name:zho_x_preferred":[
        "\u9f99\u6d1e\u6e7e"
    ],
    "wof:name":"Longdongwan",
    "wof:placetype":"locality"
},
  "geometry": {"coordinates":[110.30061000000001,30.41621],"type":"Point"}
}