{
  "type": "Feature",
  "properties": {
    "gn:admin1_code":"12.0",
    "gn:asciiname":"Jianjiahe",
    "gn:country_code":"CN",
    "gn:dem":311,
    "gn:feature_class":"P",
    "gn:feature_code":"PPL",
    "gn:name":"Jianjiahe",
    "gn:population":0,
    "gn:timezone":"Asia/Shanghai",
    "iso:country":"CN",
    "name:zho_x_preferred":[
        "\u7b80\u5bb6\u6cb3"
    ],
    "wof:name":"Jianjiahe",
    "wof:placetype":"locality"
},
  "geometry": {"coordinates":[111.73511000000001,31.7419],"type":"Point"}
}