{
  "type": "Feature",
  "properties": {
    "gn:admin1_code":"29.0",
    "gn:asciiname":"Lalie'ejian",
    "gn:country_code":"CN",
    "gn:dem":2200,
    "gn:feature_class":"P",
    "gn:feature_code":"PPL",
    "gn:name":"Lalie\u2019ejian",
    "gn:population":0,
    "gn:timezone":"Asia/Shanghai",
    "iso:country":"CN",
    "name:und_x_variant":[
        "Lalie\u2019ejian"
    ],
    "name:zho_x_preferred":[
        "\u62c9\u5217\u4fc4\u5c16"
    ],
    "wof:name":"Lalie'ejian",
    "wof:placetype":"locality"
},
  "geometry": {"coordinates":[101.446,26.0643],"type":"Point"}
}