{
  "type": "Feature",
  "properties": {
    "gn:admin1_code":"19.0",
    "gn:asciiname":"Wangjiatun",
    "gn:country_code":"CN",
    "gn:dem":124,
    "gn:feature_class":"P",
    "gn:feature_code":"PPL",
    "gn:name":"Wangjiatun",
    "gn:population":0,
    "gn:timezone":"Asia/Shanghai",
    "iso:country":"CN",
    "name:und_x_variant":[
        "\u6c6a\u5bb6\u5c6f"
    ],
    "name:zho_x_preferred":[
        "\u6c6a\u5bb6\u5c6f"
    ],
    "wof:name":"Wangjiatun",
    "wof:placetype":"locality"
},
  "geometry": {"coordinates":[120.17095999999999,40.66112],"type":"Point"}
}