{
  "type": "Feature",
  "properties": {
    "gn:admin1_code":"9.0",
    "gn:asciiname":"Gezhuang",
    "gn:country_code":"CN",
    "gn:dem":53,
    "gn:feature_class":"P",
    "gn:feature_code":"PPL",
    "gn:name":"Gezhuang",
    "gn:population":0,
    "gn:timezone":"Asia/Shanghai",
    "iso:country":"CN",
    "name:zho_x_preferred":[
        "\u845b\u5e84"
    ],
    "wof:name":"Gezhuang",
    "wof:placetype":"locality"
},
  "geometry": {"coordinates":[114.43854,33.0612],"type":"Point"}
}