{
  "type": "Feature",
  "properties": {
    "gn:admin1_code":"3.0",
    "gn:asciiname":"Woshang",
    "gn:country_code":"CN",
    "gn:dem":151,
    "gn:feature_class":"P",
    "gn:feature_code":"PPL",
    "gn:name":"Woshang",
    "gn:population":0,
    "gn:timezone":"Asia/Shanghai",
    "iso:country":"CN",
    "name:zho_x_preferred":[
        "\u6c83\u4e0a"
    ],
    "wof:name":"Woshang",
    "wof:placetype":"locality"
},
  "geometry": {"coordinates":[114.274,27.9306],"type":"Point"}
}