{
  "type": "Feature",
  "properties": {
    "gn:admin1_code":"32.0",
    "gn:asciiname":"Huilong'an",
    "gn:country_code":"CN",
    "gn:dem":492,
    "gn:feature_class":"P",
    "gn:feature_code":"PPL",
    "gn:name":"Huilong\u2019an",
    "gn:population":0,
    "gn:timezone":"Asia/Shanghai",
    "iso:country":"CN",
    "name:zho_x_preferred":[
        "\u56de\u9f99\u5eb5"
    ],
    "name:zho_x_variant":[
        "Huilong\u2019an"
    ],
    "wof:name":"Huilong'an",
    "wof:placetype":"locality"
},
  "geometry": {"coordinates":[103.7774,30.34045],"type":"Point"}
}