{
  "type": "Feature",
  "properties": {
    "gn:admin1_code":"21.0",
    "gn:asciiname":"Xiaohongzhuang",
    "gn:country_code":"CN",
    "gn:dem":2047,
    "gn:feature_class":"P",
    "gn:feature_code":"PPL",
    "gn:name":"Xiaohongzhuang",
    "gn:population":0,
    "gn:timezone":"Asia/Shanghai",
    "iso:country":"CN",
    "name:zho_x_preferred":[
        "\u5c0f\u7ea2\u5e84"
    ],
    "wof:name":"Xiaohongzhuang",
    "wof:placetype":"locality"
},
  "geometry": {"coordinates":[105.68600000000001,36.0373],"type":"Point"}
}