{
  "type": "Feature",
  "properties": {
    "gn:admin1_code":"26",
    "gn:asciiname":"Cuijiatou",
    "gn:country_code":"CN",
    "gn:dem":945,
    "gn:feature_class":"P",
    "gn:feature_code":"PPLA4",
    "gn:name":"Cuijiatou",
    "gn:population":0,
    "gn:timezone":"Asia/Shanghai",
    "iso:country":"CN",
    "name:und_x_variant":[
        "\u5d14\u5bb6\u5934",
        "Cuijiatou Zhen",
        "\u5d14\u5bb6\u5934\u9547"
    ],
    "wof:name":"Cuijiatou",
    "wof:placetype":"locality"
},
  "geometry": {"coordinates":[107.23177,34.63645],"type":"Point"}
}