{
  "type": "Feature",
  "properties": {
    "gn:admin1_code":"32.0",
    "gn:asciiname":"Yimudi",
    "gn:country_code":"CN",
    "gn:dem":2649,
    "gn:feature_class":"P",
    "gn:feature_code":"PPL",
    "gn:name":"Yimudi",
    "gn:population":0,
    "gn:timezone":"Asia/Shanghai",
    "iso:country":"CN",
    "name:zho_x_preferred":[
        "\u5b9c\u7267\u5730"
    ],
    "wof:name":"Yimudi",
    "wof:placetype":"locality"
},
  "geometry": {"coordinates":[102.7501,28.2142],"type":"Point"}
}