{
  "type": "Feature",
  "properties": {
    "gn:admin1_code":"19.0",
    "gn:asciiname":"Dongtai",
    "gn:country_code":"CN",
    "gn:dem":73,
    "gn:feature_class":"P",
    "gn:feature_code":"PPL",
    "gn:name":"Dongtai",
    "gn:population":0,
    "gn:timezone":"Asia/Shanghai",
    "iso:country":"CN",
    "name:und_x_variant":[
        "\u4e1c\u53f0"
    ],
    "name:zho_x_preferred":[
        "\u4e1c\u53f0"
    ],
    "wof:name":"Dongtai",
    "wof:placetype":"locality"
},
  "geometry": {"coordinates":[123.70440000000001,41.78811],"type":"Point"}
}