{
  "type": "Feature",
  "properties": {
    "gn:admin1_code":"19.0",
    "gn:asciiname":"Dongtai",
    "gn:country_code":"CN",
    "gn:dem":73,
    "gn:feature_class":"P",
    "gn:feature_code":"PPL",
    "gn:name":"Dongtai",
    "gn:population":0,
    "gn:timezone":"Asia/Shanghai",
    "iso:country":"CN",
    "name:ceb_x_preferred":[
        "Dongtai Shi"
    ],
    "name:deu_x_preferred":[
        "Dongtai"
    ],
    "name:epo_x_preferred":[
        "Dongtaj"
    ],
    "name:fra_x_preferred":[
        "Dongtai"
    ],
    "name:ita_x_preferred":[
        "Dongtai"
    ],
    "name:jpn_x_preferred":[
        "\u6771\u53f0\u5e02"
    ],
    "name:kik_x_preferred":[
        "Dongtai"
    ],
    "name:kor_x_preferred":[
        "\ub465\ud0c0\uc774\uc2dc"
    ],
    "name:mlg_x_preferred":[
        "Dongtai"
    ],
    "name:nor_x_preferred":[
        "Dongtai"
    ],
    "name:pam_x_preferred":[
        "Dongtai"
    ],
    "name:rus_x_preferred":[
        "\u0414\u0443\u043d\u0442\u0430\u0439"
    ],
    "name:swe_x_preferred":[
        "Dongtai"
    ],
    "name:tgl_x_preferred":[
        "Dongtai"
    ],
    "name:urd_x_preferred":[
        "\u062f\u0648\u0646\u06af\u062a\u0627\u0626\u06cc"
    ],
    "name:vie_x_preferred":[
        "\u0110\u00f4ng \u0110\u00e0i"
    ],
    "name:war_x_preferred":[
        "Dongtai"
    ],
    "name:wuu_x_preferred":[
        "\u4e1c\u53f0\u5e02"
    ],
    "name:zho_x_preferred":[
        "\u4e1c\u53f0"
    ],
    "name:zho_x_variant":[
        "\u4e1c\u53f0\u5e02"
    ],
    "wof:name":"Dongtai",
    "wof:placetype":"locality"
},
  "geometry": {"coordinates":[123.70440000000001,41.78811],"type":"Point"}
}