{
  "type": "Feature",
  "properties": {
    "gn:admin1_code":"3.0",
    "gn:asciiname":"Jiaobutan",
    "gn:country_code":"CN",
    "gn:dem":171,
    "gn:feature_class":"P",
    "gn:feature_code":"PPL",
    "gn:name":"Jiaobutan",
    "gn:population":0,
    "gn:timezone":"Asia/Shanghai",
    "iso:country":"CN",
    "name:zho_x_preferred":[
        "\u7126\u57e0\u6ee9"
    ],
    "wof:name":"Jiaobutan",
    "wof:placetype":"locality"
},
  "geometry": {"coordinates":[114.395,29.0519],"type":"Point"}
}