{
  "type": "Feature",
  "properties": {
    "gn:admin1_code":"18",
    "gn:asciiname":"Mabaozhai",
    "gn:country_code":"CN",
    "gn:dem":1671,
    "gn:feature_class":"P",
    "gn:feature_code":"PPL",
    "gn:name":"Mabaozhai",
    "gn:population":0,
    "gn:timezone":"Asia/Shanghai",
    "iso:country":"CN",
    "name:zho_x_preferred":[
        "\u9a6c\u4fdd\u5be8"
    ],
    "wof:name":"Mabaozhai",
    "wof:placetype":"locality"
},
  "geometry": {"coordinates":[105.672,27.4388],"type":"Point"}
}