{
  "type": "Feature",
  "properties": {
    "gn:admin1_code":"19",
    "gn:asciiname":"Monjianghong",
    "gn:country_code":"CN",
    "gn:dem":466,
    "gn:feature_class":"P",
    "gn:feature_code":"PPL",
    "gn:name":"Monjianghong",
    "gn:population":0,
    "gn:timezone":"Asia/Shanghai",
    "iso:country":"CN",
    "wof:name":"Monjianghong",
    "wof:placetype":"locality"
},
  "geometry": {"coordinates":[125.38333,40.66667],"type":"Point"}
}