{
  "type": "Feature",
  "properties": {
    "gn:admin1_code":"08",
    "gn:asciiname":"Mugouhe",
    "gn:country_code":"CN",
    "gn:dem":315,
    "gn:feature_class":"P",
    "gn:feature_code":"PPL",
    "gn:name":"Mugouhe",
    "gn:population":0,
    "gn:timezone":"Asia/Shanghai",
    "iso:country":"CN",
    "name:und_x_variant":[
        "Mu-kou-ho",
        "Mugouhe"
    ],
    "wof:name":"Mugouhe",
    "wof:placetype":"locality"
},
  "geometry": {"coordinates":[127.18953999999999,48.49176],"type":"Point"}
}