{
  "type": "Feature",
  "properties": {
    "gn:admin1_code":"24.0",
    "gn:asciiname":"Beita",
    "gn:country_code":"CN",
    "gn:dem":1080,
    "gn:feature_class":"P",
    "gn:feature_code":"PPL",
    "gn:name":"Beita",
    "gn:population":0,
    "gn:timezone":"Asia/Shanghai",
    "iso:country":"CN",
    "name:deu_x_preferred":[
        "Beita"
    ],
    "name:fra_x_preferred":[
        "Beita"
    ],
    "name:zho_x_preferred":[
        "\u8d1d\u5854"
    ],
    "wof:name":"Beita",
    "wof:placetype":"locality"
},
  "geometry": {"coordinates":[111.0819,38.68467],"type":"Point"}
}