{
  "type": "Feature",
  "properties": {
    "gn:admin1_code":"1.0",
    "gn:asciiname":"Gongyicun",
    "gn:country_code":"CN",
    "gn:dem":50,
    "gn:feature_class":"P",
    "gn:feature_code":"PPL",
    "gn:name":"Gongyicun",
    "gn:population":0,
    "gn:timezone":"Asia/Shanghai",
    "iso:country":"CN",
    "name:zho_x_preferred":[
        "\u516c\u4e49\u6751"
    ],
    "wof:name":"Gongyicun",
    "wof:placetype":"locality"
},
  "geometry": {"coordinates":[116.97505,31.35967],"type":"Point"}
}