{
  "type": "Feature",
  "properties": {
    "gn:admin1_code":"9",
    "gn:asciiname":"Xiezhuyuan",
    "gn:country_code":"CN",
    "gn:dem":44,
    "gn:feature_class":"P",
    "gn:feature_code":"PPL",
    "gn:name":"Xiezhuyuan",
    "gn:population":0,
    "gn:timezone":"Asia/Shanghai",
    "iso:country":"CN",
    "name:zho_x_preferred":[
        "\u8c22\u7af9\u56ed"
    ],
    "wof:name":"Xiezhuyuan",
    "wof:placetype":"locality"
},
  "geometry": {"coordinates":[115.194,33.7182],"type":"Point"}
}