{
  "type": "Feature",
  "properties": {
    "gn:admin1_code":"26.0",
    "gn:asciiname":"Houchuancun",
    "gn:country_code":"CN",
    "gn:dem":1025,
    "gn:feature_class":"P",
    "gn:feature_code":"PPL",
    "gn:name":"Houchuancun",
    "gn:population":0,
    "gn:timezone":"Asia/Shanghai",
    "iso:country":"CN",
    "name:zho_x_preferred":[
        "\u540e\u5ddd\u6751"
    ],
    "wof:name":"Houchuancun",
    "wof:placetype":"locality"
},
  "geometry": {"coordinates":[108.10093000000001,35.15288],"type":"Point"}
}