{
  "type": "Feature",
  "properties": {
    "gn:admin1_code":"10",
    "gn:asciiname":"Shangshihao",
    "gn:country_code":"CN",
    "gn:dem":1405,
    "gn:feature_class":"P",
    "gn:feature_code":"PPLF",
    "gn:name":"Shangshihao",
    "gn:population":0,
    "gn:timezone":"Asia/Shanghai",
    "iso:country":"CN",
    "name:zho_x_preferred":[
        "\u4e0a\u5341\u53f7"
    ],
    "wof:name":"Shangshihao",
    "wof:placetype":"locality"
},
  "geometry": {"coordinates":[117.59532,42.41402],"type":"Point"}
}