{
  "type": "Feature",
  "properties": {
    "gn:admin1_code":"26",
    "gn:asciiname":"Dongjiayaokeng",
    "gn:cc2":"CN",
    "gn:country_code":"CN",
    "gn:dem":1420,
    "gn:feature_class":"P",
    "gn:feature_code":"PPL",
    "gn:name":"Dongjiayaokeng",
    "gn:population":0,
    "gn:timezone":"Asia/Shanghai",
    "iso:country":"CN",
    "name:und_x_variant":[
        "Tung-chia-yao-k\u2019eng",
        "Dongjiayaokeng"
    ],
    "wof:name":"Dongjiayaokeng",
    "wof:placetype":"locality"
},
  "geometry": {"coordinates":[109.01667,37.36667],"type":"Point"}
}