{
  "type": "Feature",
  "properties": {
    "gn:admin1_code":"26.0",
    "gn:asciiname":"Shishuigounao",
    "gn:country_code":"CN",
    "gn:dem":1686,
    "gn:feature_class":"P",
    "gn:feature_code":"PPL",
    "gn:name":"Shishuigounao",
    "gn:population":0,
    "gn:timezone":"Asia/Shanghai",
    "iso:country":"CN",
    "name:zho_x_preferred":[
        "\u77f3\u6c34\u6c9f\u8111"
    ],
    "wof:name":"Shishuigounao",
    "wof:placetype":"locality"
},
  "geometry": {"coordinates":[109.24701,32.11652],"type":"Point"}
}