{
  "type": "Feature",
  "properties": {
    "gn:admin1_code":"8.0",
    "gn:asciiname":"Ha'ertong",
    "gn:country_code":"CN",
    "gn:dem":136,
    "gn:feature_class":"P",
    "gn:feature_code":"PPL",
    "gn:name":"Ha\u2019ertong",
    "gn:population":0,
    "gn:timezone":"Asia/Shanghai",
    "iso:country":"CN",
    "name:und_x_variant":[
        "Ha\u2019ertong"
    ],
    "name:zho_x_preferred":[
        "\u54c8\u5c14\u901a"
    ],
    "wof:name":"Ha'ertong",
    "wof:placetype":"locality"
},
  "geometry": {"coordinates":[123.76667,46.65375],"type":"Point"}
}