{
  "type": "Feature",
  "properties": {
    "gn:admin1_code":"26",
    "gn:asciiname":"Bailashu",
    "gn:cc2":"CN",
    "gn:country_code":"CN",
    "gn:dem":550,
    "gn:feature_class":"P",
    "gn:feature_code":"PPL",
    "gn:name":"Bailashu",
    "gn:population":0,
    "gn:timezone":"Asia/Shanghai",
    "iso:country":"CN",
    "name:und_x_variant":[
        "Pai-la-shu",
        "Bailashu"
    ],
    "wof:name":"Bailashu",
    "wof:placetype":"locality"
},
  "geometry": {"coordinates":[108.27249999999999,32.68028],"type":"Point"}
}