{
  "type": "Feature",
  "properties": {
    "gn:admin1_code":"24.0",
    "gn:asciiname":"Xingyangzhuang",
    "gn:country_code":"CN",
    "gn:dem":482,
    "gn:feature_class":"P",
    "gn:feature_code":"PPL",
    "gn:name":"Xingyangzhuang",
    "gn:population":0,
    "gn:timezone":"Asia/Shanghai",
    "iso:country":"CN",
    "name:und_x_variant":[
        "\u5174\u6768\u5e84"
    ],
    "wof:name":"Xingyangzhuang",
    "wof:placetype":"locality"
},
  "geometry": {"coordinates":[111.12757000000001,35.28273],"type":"Point"}
}