{
  "type": "Feature",
  "properties": {
    "gn:admin1_code":"29",
    "gn:asciiname":"Tianshengqiao",
    "gn:country_code":"CN",
    "gn:dem":1516,
    "gn:feature_class":"P",
    "gn:feature_code":"PPL",
    "gn:name":"Tianshengqiao",
    "gn:population":0,
    "gn:timezone":"Asia/Shanghai",
    "iso:country":"CN",
    "name:zho_x_preferred":[
        "\u5929\u751f\u6865"
    ],
    "wof:name":"Tianshengqiao",
    "wof:placetype":"locality"
},
  "geometry": {"coordinates":[105.40000000000001,23.5067],"type":"Point"}
}