{
  "type": "Feature",
  "properties": {
    "gn:admin1_code":"16.0",
    "gn:asciiname":"Yaolang",
    "gn:country_code":"CN",
    "gn:dem":46,
    "gn:feature_class":"P",
    "gn:feature_code":"PPL",
    "gn:name":"Yaolang",
    "gn:population":0,
    "gn:timezone":"Asia/Shanghai",
    "iso:country":"CN",
    "name:zho_x_preferred":[
        "\u9065\u6717"
    ],
    "wof:name":"Yaolang",
    "wof:placetype":"locality"
},
  "geometry": {"coordinates":[110.378,23.663],"type":"Point"}
}