{
  "type": "Feature",
  "properties": {
    "gn:admin1_code":"31.0",
    "gn:asciiname":"Shawei",
    "gn:country_code":"CN",
    "gn:dem":13,
    "gn:feature_class":"P",
    "gn:feature_code":"PPL",
    "gn:name":"Shawei",
    "gn:population":0,
    "gn:timezone":"Asia/Shanghai",
    "iso:country":"CN",
    "name:zho_x_preferred":[
        "Shawei"
    ],
    "name:zho_x_variant":[
        "\u6c99\u5c3e"
    ],
    "wof:name":"Shawei",
    "wof:placetype":"locality"
},
  "geometry": {"coordinates":[110.82995,19.5959],"type":"Point"}
}