{
  "type": "Feature",
  "properties": {
    "gn:admin1_code":"30.0",
    "gn:asciiname":"Meilu",
    "gn:country_code":"CN",
    "gn:dem":28,
    "gn:feature_class":"P",
    "gn:feature_code":"PPLA3",
    "gn:name":"Meilu",
    "gn:population":0,
    "gn:timezone":"Asia/Urumqi",
    "iso:country":"CN",
    "name:und_x_variant":[
        "Meilu Jiedao"
    ],
    "name:zho_x_preferred":[
        "\u6885\u83c9"
    ],
    "name:zho_x_variant":[
        "\u6885\u83c9\u8857\u9053"
    ],
    "wof:name":"Meilu",
    "wof:placetype":"locality"
},
  "geometry": {"coordinates":[110.77555,21.43412],"type":"Point"}
}