{
  "type": "Feature",
  "properties": {
    "gn:admin1_code":"14.0",
    "gn:asciiname":"Morongwa",
    "gn:country_code":"CN",
    "gn:dem":4689,
    "gn:feature_class":"P",
    "gn:feature_code":"PPL",
    "gn:name":"Morongwa",
    "gn:population":0,
    "gn:timezone":"Asia/Urumqi",
    "iso:country":"CN",
    "name:bod_x_preferred":[
        "Morongwa"
    ],
    "name:zho_x_preferred":[
        "\u83ab\u8363\u74e6"
    ],
    "wof:name":"Morongwa",
    "wof:placetype":"locality"
},
  "geometry": {"coordinates":[97.602,30.802],"type":"Point"}
}