{
  "type": "Feature",
  "properties": {
    "gn:admin1_code":"29.0",
    "gn:asciiname":"Jinzhongcun",
    "gn:country_code":"CN",
    "gn:dem":2007,
    "gn:feature_class":"P",
    "gn:feature_code":"PPL",
    "gn:name":"Jinzhongcun",
    "gn:population":0,
    "gn:timezone":"Asia/Shanghai",
    "iso:country":"CN",
    "name:zho_x_preferred":[
        "\u91d1\u949f\u6751"
    ],
    "wof:name":"Jinzhongcun",
    "wof:placetype":"locality"
},
  "geometry": {"coordinates":[102.831,25.2366],"type":"Point"}
}