{
  "type": "Feature",
  "properties": {
    "gn:admin1_code":"11.0",
    "gn:asciiname":"Goupo",
    "gn:country_code":"CN",
    "gn:dem":457,
    "gn:feature_class":"P",
    "gn:feature_code":"PPL",
    "gn:name":"Goupo",
    "gn:population":0,
    "gn:timezone":"Asia/Shanghai",
    "iso:country":"CN",
    "name:zho_x_preferred":[
        "\u72d7\u5761"
    ],
    "wof:name":"Goupo",
    "wof:placetype":"locality"
},
  "geometry": {"coordinates":[113.67298999999998,28.36764],"type":"Point"}
}