{
  "type": "Feature",
  "properties": {
    "gn:admin1_code":"5.0",
    "gn:asciiname":"Guzimiao",
    "gn:country_code":"CN",
    "gn:dem":360,
    "gn:feature_class":"P",
    "gn:feature_code":"PPL",
    "gn:name":"Guzimiao",
    "gn:population":0,
    "gn:timezone":"Asia/Shanghai",
    "iso:country":"CN",
    "name:zho_x_preferred":[
        "\u5b64\u5b50\u5e99"
    ],
    "wof:name":"Guzimiao",
    "wof:placetype":"locality"
},
  "geometry": {"coordinates":[125.58017,42.90805],"type":"Point"}
}