{
  "type": "Feature",
  "properties": {
    "gn:admin1_code":"18.0",
    "gn:asciiname":"Shangzhaotian",
    "gn:country_code":"CN",
    "gn:dem":682,
    "gn:feature_class":"P",
    "gn:feature_code":"PPL",
    "gn:name":"Shangzhaotian",
    "gn:population":0,
    "gn:timezone":"Asia/Shanghai",
    "iso:country":"CN",
    "name:zho_x_preferred":[
        "\u4e0a\u53ec\u7530"
    ],
    "wof:name":"Shangzhaotian",
    "wof:placetype":"locality"
},
  "geometry": {"coordinates":[109.42,27.5566],"type":"Point"}
}