{
  "type": "Feature",
  "properties": {
    "gn:admin1_code":"15.0",
    "gn:asciiname":"Haojiazui",
    "gn:country_code":"CN",
    "gn:dem":1246,
    "gn:feature_class":"P",
    "gn:feature_code":"PPL",
    "gn:name":"Haojiazui",
    "gn:population":0,
    "gn:timezone":"Asia/Shanghai",
    "iso:country":"CN",
    "name:zho_x_preferred":[
        "\u6d69\u5bb6\u5480"
    ],
    "wof:name":"Haojiazui",
    "wof:placetype":"locality"
},
  "geometry": {"coordinates":[107.791,35.5665],"type":"Point"}
}