{
  "type": "Feature",
  "properties": {
    "gn:admin1_code":"9",
    "gn:asciiname":"Chenzhuang",
    "gn:country_code":"CN",
    "gn:dem":44,
    "gn:feature_class":"P",
    "gn:feature_code":"PPL",
    "gn:name":"Chenzhuang",
    "gn:population":0,
    "gn:timezone":"Asia/Shanghai",
    "iso:country":"CN",
    "name:ceb_x_preferred":[
        "Chenzhuang"
    ],
    "name:swe_x_preferred":[
        "Chenzhuang"
    ],
    "name:zho_x_preferred":[
        "\u9648\u5e84"
    ],
    "wof:name":"Chenzhuang",
    "wof:placetype":"locality"
},
  "geometry": {"coordinates":[116.03400000000001,34.2486],"type":"Point"}
}