{
  "type": "Feature",
  "properties": {
    "gn:admin1_code":"22.0",
    "gn:asciiname":"Yulinkoucun",
    "gn:country_code":"CN",
    "gn:dem":521,
    "gn:feature_class":"P",
    "gn:feature_code":"PPL",
    "gn:name":"Yulinkoucun",
    "gn:population":0,
    "gn:timezone":"Asia/Shanghai",
    "iso:country":"CN",
    "name:zho_x_preferred":[
        "\u9c7c\u6797\u53e3\u6751"
    ],
    "wof:name":"Yulinkoucun",
    "wof:placetype":"locality"
},
  "geometry": {"coordinates":[115.96253,40.23786],"type":"Point"}
}