{
  "type": "Feature",
  "properties": {
    "gn:admin1_code":"26.0",
    "gn:asciiname":"Santaizhuangcun",
    "gn:country_code":"CN",
    "gn:dem":1182,
    "gn:feature_class":"P",
    "gn:feature_code":"PPL",
    "gn:name":"Santaizhuangcun",
    "gn:population":0,
    "gn:timezone":"Asia/Shanghai",
    "iso:country":"CN",
    "name:zho_x_preferred":[
        "\u4e09\u53f0\u5e84\u6751"
    ],
    "wof:name":"Santaizhuangcun",
    "wof:placetype":"locality"
},
  "geometry": {"coordinates":[109.64175,36.30196],"type":"Point"}
}