{
  "type": "Feature",
  "properties": {
    "gn:admin1_code":"25.0",
    "gn:asciiname":"Ren'erzhuangcun",
    "gn:country_code":"CN",
    "gn:dem":42,
    "gn:feature_class":"P",
    "gn:feature_code":"PPL",
    "gn:name":"Ren\u2019erzhuangcun",
    "gn:population":0,
    "gn:timezone":"Asia/Shanghai",
    "iso:country":"CN",
    "name:und_x_variant":[
        "Ren\u2019erzhuangcun"
    ],
    "name:zho_x_preferred":[
        "\u4ec1\u4e8c\u5e84\u6751"
    ],
    "wof:name":"Ren'erzhuangcun",
    "wof:placetype":"locality"
},
  "geometry": {"coordinates":[115.5534,36.472],"type":"Point"}
}