{
  "type": "Feature",
  "properties": {
    "gn:admin1_code":"29.0",
    "gn:asciiname":"Shangpijiangjie",
    "gn:country_code":"CN",
    "gn:dem":1909,
    "gn:feature_class":"P",
    "gn:feature_code":"PPL",
    "gn:name":"Shangpijiangjie",
    "gn:population":0,
    "gn:timezone":"Asia/Shanghai",
    "iso:country":"CN",
    "name:zho_x_preferred":[
        "\u4e0a\u76ae\u5320\u8857"
    ],
    "wof:name":"Shangpijiangjie",
    "wof:placetype":"locality"
},
  "geometry": {"coordinates":[103.648,27.3788],"type":"Point"}
}