{
  "type": "Feature",
  "properties": {
    "gn:admin1_code":"2.0",
    "gn:asciiname":"Pingtouqiao",
    "gn:country_code":"CN",
    "gn:dem":4,
    "gn:feature_class":"P",
    "gn:feature_code":"PPL",
    "gn:name":"Pingtouqiao",
    "gn:population":0,
    "gn:timezone":"Asia/Shanghai",
    "iso:country":"CN",
    "name:und_x_variant":[
        "\u5e73\u5934\u6865"
    ],
    "wof:name":"Pingtouqiao",
    "wof:placetype":"locality"
},
  "geometry": {"coordinates":[120.59784000000001,30.6037],"type":"Point"}
}