{
  "type": "Feature",
  "properties": {
    "gn:admin1_code":"14.0",
    "gn:asciiname":"Caipengcun",
    "gn:country_code":"CN",
    "gn:dem":4143,
    "gn:feature_class":"P",
    "gn:feature_code":"PPL",
    "gn:name":"Caipengcun",
    "gn:population":0,
    "gn:timezone":"Asia/Urumqi",
    "iso:country":"CN",
    "name:zho_x_preferred":[
        "\u624d\u670b\u6751"
    ],
    "wof:name":"Caipengcun",
    "wof:placetype":"locality"
},
  "geometry": {"coordinates":[91.82113,28.91689],"type":"Point"}
}