{
  "type": "Feature",
  "properties": {
    "gn:admin1_code":"9.0",
    "gn:asciiname":"Shi'erhui",
    "gn:country_code":"CN",
    "gn:dem":720,
    "gn:feature_class":"P",
    "gn:feature_code":"PPL",
    "gn:name":"Shi\u2019erhui",
    "gn:population":0,
    "gn:timezone":"Asia/Shanghai",
    "iso:country":"CN",
    "name:und_x_variant":[
        "Shi\u2019erhui"
    ],
    "name:zho_x_preferred":[
        "\u5341\u4e8c\u4f1a"
    ],
    "wof:name":"Shi'erhui",
    "wof:placetype":"locality"
},
  "geometry": {"coordinates":[113.12967999999999,35.30158],"type":"Point"}
}