{
  "type": "Feature",
  "properties": {
    "gn:admin1_code":"10",
    "gn:asciiname":"Fuchengzi",
    "gn:country_code":"CN",
    "gn:dem":1084,
    "gn:feature_class":"P",
    "gn:feature_code":"PPL",
    "gn:name":"Fuchengzi",
    "gn:population":0,
    "gn:timezone":"Asia/Shanghai",
    "iso:country":"CN",
    "name:zho_x_preferred":[
        "\u5bcc\u57ce\u5b50"
    ],
    "wof:name":"Fuchengzi",
    "wof:placetype":"locality"
},
  "geometry": {"coordinates":[117.71516,42.14866],"type":"Point"}
}