{
  "type": "Feature",
  "properties": {
    "gn:admin1_code":"18",
    "gn:asciiname":"Tangguan",
    "gn:country_code":"CN",
    "gn:dem":1652,
    "gn:feature_class":"P",
    "gn:feature_code":"PPL",
    "gn:name":"Tangguan",
    "gn:population":0,
    "gn:timezone":"Asia/Shanghai",
    "iso:country":"CN",
    "name:zho_x_preferred":[
        "\u5510\u5b98"
    ],
    "wof:name":"Tangguan",
    "wof:placetype":"locality"
},
  "geometry": {"coordinates":[105.21299999999999,27.3114],"type":"Point"}
}