{
  "type": "Feature",
  "properties": {
    "gn:admin1_code":"11.0",
    "gn:asciiname":"Bijiashan",
    "gn:country_code":"CN",
    "gn:dem":212,
    "gn:feature_class":"P",
    "gn:feature_code":"PPL",
    "gn:name":"Bijiashan",
    "gn:population":0,
    "gn:timezone":"Asia/Shanghai",
    "iso:country":"CN",
    "name:zho_x_preferred":[
        "\u6bd5\u5bb6\u5c71"
    ],
    "wof:name":"Bijiashan",
    "wof:placetype":"locality"
},
  "geometry": {"coordinates":[110.59788,28.65776],"type":"Point"}
}