{
  "type": "Feature",
  "properties": {
    "gn:admin1_code":"29.0",
    "gn:asciiname":"Qiujiacun",
    "gn:country_code":"CN",
    "gn:dem":2232,
    "gn:feature_class":"P",
    "gn:feature_code":"PPL",
    "gn:name":"Qiujiacun",
    "gn:population":0,
    "gn:timezone":"Asia/Shanghai",
    "iso:country":"CN",
    "name:zho_x_preferred":[
        "\u90b1\u5bb6\u6751"
    ],
    "wof:name":"Qiujiacun",
    "wof:placetype":"locality"
},
  "geometry": {"coordinates":[103.30800000000001,26.5584],"type":"Point"}
}