{
  "type": "Feature",
  "properties": {
    "gn:admin1_code":"30.0",
    "gn:asciiname":"Lanzhou",
    "gn:country_code":"CN",
    "gn:dem":5,
    "gn:feature_class":"P",
    "gn:feature_code":"PPL",
    "gn:name":"Lanzhou",
    "gn:population":0,
    "gn:timezone":"Asia/Shanghai",
    "iso:country":"CN",
    "name:rus_x_preferred":[
        "\u041b\u0430\u043d\u044c\u0447\u0436\u043e\u0443"
    ],
    "wof:name":"Lanzhou",
    "wof:placetype":"locality"
},
  "geometry": {"coordinates":[112.73372999999999,23.08964],"type":"Point"}
}