{
  "type": "Feature",
  "properties": {
    "gn:admin1_code":"22",
    "gn:asciiname":"Sanbu",
    "gn:country_code":"CN",
    "gn:dem":498,
    "gn:feature_class":"P",
    "gn:feature_code":"PPL",
    "gn:name":"Sanbu",
    "gn:population":0,
    "gn:timezone":"Asia/Shanghai",
    "iso:country":"CN",
    "name:und_x_variant":[
        "San-pao",
        "San-p\u2019u",
        "Sanbu"
    ],
    "name:zho_x_preferred":[
        "\u4e09\u5821"
    ],
    "wof:name":"Sanbu",
    "wof:placetype":"locality"
},
  "geometry": {"coordinates":[116.03175,40.3361],"type":"Point"}
}