{
  "type": "Feature",
  "properties": {
    "gn:admin1_code":"24.0",
    "gn:asciiname":"Dongpucun",
    "gn:country_code":"CN",
    "gn:dem":467,
    "gn:feature_class":"P",
    "gn:feature_code":"PPL",
    "gn:name":"Dongpucun",
    "gn:population":0,
    "gn:timezone":"Asia/Shanghai",
    "iso:country":"CN",
    "name:zho_x_preferred":[
        "\u4e1c\u84b2\u6751"
    ],
    "wof:name":"Dongpucun",
    "wof:placetype":"locality"
},
  "geometry": {"coordinates":[110.84667,35.55346],"type":"Point"}
}