{
  "type": "Feature",
  "properties": {
    "gn:admin1_code":"10",
    "gn:asciiname":"Xiaowangzhuang",
    "gn:country_code":"CN",
    "gn:dem":43,
    "gn:feature_class":"P",
    "gn:feature_code":"PPL",
    "gn:name":"Xiaowangzhuang",
    "gn:population":0,
    "gn:timezone":"Asia/Shanghai",
    "iso:country":"CN",
    "name:zho_x_preferred":[
        "\u5c0f\u738b\u5e84"
    ],
    "wof:name":"Xiaowangzhuang",
    "wof:placetype":"locality"
},
  "geometry": {"coordinates":[115.03764,36.70948],"type":"Point"}
}