{
  "type": "Feature",
  "properties": {
    "gn:admin1_code":"29.0",
    "gn:asciiname":"Shiyanjiao",
    "gn:country_code":"CN",
    "gn:dem":1680,
    "gn:feature_class":"P",
    "gn:feature_code":"PPL",
    "gn:name":"Shiyanjiao",
    "gn:population":0,
    "gn:timezone":"Asia/Shanghai",
    "iso:country":"CN",
    "name:zho_x_preferred":[
        "\u77f3\u5ca9\u811a"
    ],
    "wof:name":"Shiyanjiao",
    "wof:placetype":"locality"
},
  "geometry": {"coordinates":[103.71299999999999,24.2478],"type":"Point"}
}