{
  "type": "Feature",
  "properties": {
    "gn:admin1_code":"29",
    "gn:asciiname":"Wanzizhai",
    "gn:country_code":"CN",
    "gn:dem":1443,
    "gn:feature_class":"P",
    "gn:feature_code":"PPL",
    "gn:name":"Wanzizhai",
    "gn:population":0,
    "gn:timezone":"Asia/Shanghai",
    "iso:country":"CN",
    "name:zho_x_preferred":[
        "\u6e7e\u5b50\u5be8"
    ],
    "wof:name":"Wanzizhai",
    "wof:placetype":"locality"
},
  "geometry": {"coordinates":[102.577,23.7885],"type":"Point"}
}