{
  "type": "Feature",
  "properties": {
    "gn:admin1_code":"24.0",
    "gn:asciiname":"Fujiazhuang",
    "gn:country_code":"CN",
    "gn:dem":2356,
    "gn:feature_class":"P",
    "gn:feature_code":"PPL",
    "gn:name":"Fujiazhuang",
    "gn:population":0,
    "gn:timezone":"Asia/Shanghai",
    "iso:country":"CN",
    "name:zho_x_preferred":[
        "\u5bcc\u5bb6\u5e84"
    ],
    "wof:name":"Fujiazhuang",
    "wof:placetype":"locality"
},
  "geometry": {"coordinates":[113.51011,39.02649],"type":"Point"}
}