{
  "type": "Feature",
  "properties": {
    "gn:admin1_code":"9.0",
    "gn:asciiname":"Shenzhuang",
    "gn:country_code":"CN",
    "gn:dem":40,
    "gn:feature_class":"P",
    "gn:feature_code":"PPL",
    "gn:name":"Shenzhuang",
    "gn:population":0,
    "gn:timezone":"Asia/Shanghai",
    "iso:country":"CN",
    "name:zho_x_preferred":[
        "\u7533\u5e84"
    ],
    "wof:name":"Shenzhuang",
    "wof:placetype":"locality"
},
  "geometry": {"coordinates":[115.10207,32.40209],"type":"Point"}
}