{
  "type": "Feature",
  "properties": {
    "gn:admin1_code":"12.0",
    "gn:asciiname":"Yangjiadun",
    "gn:country_code":"CN",
    "gn:dem":909,
    "gn:feature_class":"P",
    "gn:feature_code":"PPL",
    "gn:name":"Yangjiadun",
    "gn:population":0,
    "gn:timezone":"Asia/Shanghai",
    "iso:country":"CN",
    "name:zho_x_preferred":[
        "Yangjiadun"
    ],
    "name:zho_x_variant":[
        "\u6768\u5bb6\u58a9"
    ],
    "wof:name":"Yangjiadun",
    "wof:placetype":"locality"
},
  "geometry": {"coordinates":[111.10702000000001,30.05473],"type":"Point"}
}