{
  "type": "Feature",
  "properties": {
    "gn:admin1_code":"10.0",
    "gn:asciiname":"Zangxiaozhuang",
    "gn:country_code":"CN",
    "gn:dem":11,
    "gn:feature_class":"P",
    "gn:feature_code":"PPL",
    "gn:name":"Zangxiaozhuang",
    "gn:population":0,
    "gn:timezone":"Asia/Shanghai",
    "iso:country":"CN",
    "name:zho_x_preferred":[
        "\u81e7\u5c0f\u5e84"
    ],
    "wof:name":"Zangxiaozhuang",
    "wof:placetype":"locality"
},
  "geometry": {"coordinates":[116.614,38.325],"type":"Point"}
}