{
  "type": "Feature",
  "properties": {
    "gn:admin1_code":"2",
    "gn:asciiname":"Jiexi",
    "gn:country_code":"CN",
    "gn:dem":455,
    "gn:feature_class":"P",
    "gn:feature_code":"PPL",
    "gn:name":"Jiexi",
    "gn:population":0,
    "gn:timezone":"Asia/Shanghai",
    "iso:country":"CN",
    "name:zho_x_preferred":[
        "\u73a0\u6eaa"
    ],
    "wof:name":"Jiexi",
    "wof:placetype":"locality"
},
  "geometry": {"coordinates":[120.62944,29.35833],"type":"Point"}
}