{
  "type": "Feature",
  "properties": {
    "gn:admin1_code":"29.0",
    "gn:asciiname":"Daxinshan",
    "gn:country_code":"CN",
    "gn:dem":3000,
    "gn:feature_class":"P",
    "gn:feature_code":"PPL",
    "gn:name":"Daxinshan",
    "gn:population":0,
    "gn:timezone":"Asia/Shanghai",
    "iso:country":"CN",
    "name:zho_x_preferred":[
        "\u5927\u65b0\u5c71"
    ],
    "wof:name":"Daxinshan",
    "wof:placetype":"locality"
},
  "geometry": {"coordinates":[102.55,26.201],"type":"Point"}
}