{
  "type": "Feature",
  "properties": {
    "gn:admin1_code":"15.0",
    "gn:asciiname":"Yuehouqu",
    "gn:country_code":"CN",
    "gn:dem":1889,
    "gn:feature_class":"P",
    "gn:feature_code":"PPL",
    "gn:name":"Yuehouqu",
    "gn:population":0,
    "gn:timezone":"Asia/Shanghai",
    "iso:country":"CN",
    "name:und_x_variant":[
        "\u5cb3\u540e\u6e20"
    ],
    "wof:name":"Yuehouqu",
    "wof:placetype":"locality"
},
  "geometry": {"coordinates":[106.75491,36.76174],"type":"Point"}
}