{
  "type": "Feature",
  "properties": {
    "gn:admin1_code":"12.0",
    "gn:asciiname":"Zhangshou Sicun",
    "gn:country_code":"CN",
    "gn:dem":64,
    "gn:feature_class":"P",
    "gn:feature_code":"PPL",
    "gn:name":"Zhangshou Sicun",
    "gn:population":0,
    "gn:timezone":"Asia/Shanghai",
    "iso:country":"CN",
    "name:zho_x_preferred":[
        "\u5f20\u5bff\u56db\u6751"
    ],
    "wof:name":"Zhangshou Sicun",
    "wof:placetype":"locality"
},
  "geometry": {"coordinates":[114.28898,31.02011],"type":"Point"}
}