{
  "type": "Feature",
  "properties": {
    "gn:admin1_code":"30",
    "gn:asciiname":"Xiling",
    "gn:country_code":"CN",
    "gn:dem":15,
    "gn:feature_class":"P",
    "gn:feature_code":"PPL",
    "gn:name":"Xiling",
    "gn:population":0,
    "gn:timezone":"Asia/Shanghai",
    "iso:country":"CN",
    "name:ceb_x_preferred":[
        "Xiling"
    ],
    "name:deu_x_preferred":[
        "Xiling"
    ],
    "name:nor_x_preferred":[
        "Xiling"
    ],
    "name:zho_x_preferred":[
        "\u897f\u5cad"
    ],
    "wof:name":"Xiling",
    "wof:placetype":"locality"
},
  "geometry": {"coordinates":[116.8912,23.74768],"type":"Point"}
}