{
  "type": "Feature",
  "properties": {
    "gn:admin1_code":"29",
    "gn:asciiname":"Shaowatang",
    "gn:country_code":"CN",
    "gn:dem":1977,
    "gn:feature_class":"P",
    "gn:feature_code":"PPL",
    "gn:name":"Shaowatang",
    "gn:population":0,
    "gn:timezone":"Asia/Shanghai",
    "iso:country":"CN",
    "name:zho_x_preferred":[
        "\u70e7\u74e6\u5858"
    ],
    "wof:name":"Shaowatang",
    "wof:placetype":"locality"
},
  "geometry": {"coordinates":[102.601,23.4214],"type":"Point"}
}