{
  "type": "Feature",
  "properties": {
    "gn:admin1_code":"02",
    "gn:asciiname":"Gujiayan",
    "gn:country_code":"CN",
    "gn:dem":4,
    "gn:feature_class":"P",
    "gn:feature_code":"PPL",
    "gn:name":"Gujiayan",
    "gn:population":0,
    "gn:timezone":"Asia/Shanghai",
    "iso:country":"CN",
    "name:und_x_variant":[
        "\u8c37\u5bb6\u5830",
        "Kuo-chia-yen"
    ],
    "wof:name":"Gujiayan",
    "wof:placetype":"locality"
},
  "geometry": {"coordinates":[121.12417000000001,30.09722],"type":"Point"}
}