{
  "type": "Feature",
  "properties": {
    "gn:admin1_code":"9.0",
    "gn:asciiname":"Lugang",
    "gn:country_code":"CN",
    "gn:dem":58,
    "gn:feature_class":"P",
    "gn:feature_code":"PPL",
    "gn:name":"L\u00fcgang",
    "gn:population":0,
    "gn:timezone":"Asia/Shanghai",
    "iso:country":"CN",
    "name:ceb_x_preferred":[
        "Lugang"
    ],
    "name:swe_x_preferred":[
        "Lugang"
    ],
    "name:und_x_variant":[
        "L\u00fcgang"
    ],
    "name:zho_x_preferred":[
        "\u5415\u5c97"
    ],
    "wof:name":"Lugang",
    "wof:placetype":"locality"
},
  "geometry": {"coordinates":[115.55792,32.03591],"type":"Point"}
}