{
  "type": "Feature",
  "properties": {
    "gn:admin1_code":"11",
    "gn:asciiname":"Tangshitou",
    "gn:country_code":"CN",
    "gn:dem":329,
    "gn:feature_class":"P",
    "gn:feature_code":"PPL",
    "gn:name":"Tangshitou",
    "gn:population":0,
    "gn:timezone":"Asia/Shanghai",
    "iso:country":"CN",
    "name:zho_x_preferred":[
        "\u5858\u5e02\u5934"
    ],
    "wof:name":"Tangshitou",
    "wof:placetype":"locality"
},
  "geometry": {"coordinates":[111.19167,27.23389],"type":"Point"}
}