{
  "type": "Feature",
  "properties": {
    "gn:admin1_code":"18",
    "gn:asciiname":"Siguanying",
    "gn:country_code":"CN",
    "gn:dem":1742,
    "gn:feature_class":"P",
    "gn:feature_code":"PPL",
    "gn:name":"Siguanying",
    "gn:population":0,
    "gn:timezone":"Asia/Shanghai",
    "iso:country":"CN",
    "name:zho_x_preferred":[
        "\u56db\u5b98\u8425"
    ],
    "wof:name":"Siguanying",
    "wof:placetype":"locality"
},
  "geometry": {"coordinates":[104.782,25.8871],"type":"Point"}
}