{
  "type": "Feature",
  "properties": {
    "gn:admin1_code":"28",
    "gn:asciiname":"Yunshu",
    "gn:country_code":"CN",
    "gn:dem":7,
    "gn:feature_class":"P",
    "gn:feature_code":"PPL",
    "gn:name":"Yunshu",
    "gn:population":0,
    "gn:timezone":"Asia/Shanghai",
    "iso:country":"CN",
    "name:zho_x_preferred":[
        "\u8fd0\u8f93"
    ],
    "wof:name":"Yunshu",
    "wof:placetype":"locality"
},
  "geometry": {"coordinates":[117.22583,38.85611],"type":"Point"}
}