{
  "type": "Feature",
  "properties": {
    "gn:admin1_code":"16.0",
    "gn:asciiname":"Nongwen",
    "gn:country_code":"CN",
    "gn:dem":1013,
    "gn:feature_class":"P",
    "gn:feature_code":"PPL",
    "gn:name":"Nongwen",
    "gn:population":0,
    "gn:timezone":"Asia/Shanghai",
    "iso:country":"CN",
    "name:zho_x_preferred":[
        "\u5f04\u6587"
    ],
    "wof:name":"Nongwen",
    "wof:placetype":"locality"
},
  "geometry": {"coordinates":[105.86,23.4981],"type":"Point"}
}