{
  "type": "Feature",
  "properties": {
    "gn:admin1_code":"01",
    "gn:asciiname":"Guqiao",
    "gn:cc2":"CN",
    "gn:country_code":"CN",
    "gn:dem":24,
    "gn:feature_class":"P",
    "gn:feature_code":"PPL",
    "gn:name":"Guqiao",
    "gn:population":0,
    "gn:timezone":"Asia/Shanghai",
    "iso:country":"CN",
    "name:und_x_variant":[
        "Ku-chia-ch\u2019iao",
        "Ku-ch\u2019iao",
        "Guqiao"
    ],
    "wof:name":"Guqiao",
    "wof:placetype":"locality"
},
  "geometry": {"coordinates":[116.53167000000001,32.8275],"type":"Point"}
}