{
  "type": "Feature",
  "properties": {
    "gn:admin1_code":"15.0",
    "gn:asciiname":"Qingni",
    "gn:country_code":"CN",
    "gn:dem":1101,
    "gn:feature_class":"P",
    "gn:feature_code":"PPL",
    "gn:name":"Qingni",
    "gn:population":0,
    "gn:timezone":"Asia/Shanghai",
    "iso:country":"CN",
    "name:und_x_variant":[
        "\u9752\u6ce5"
    ],
    "wof:name":"Qingni",
    "wof:placetype":"locality"
},
  "geometry": {"coordinates":[106.11603999999998,33.70769],"type":"Point"}
}