{
  "type": "Feature",
  "properties": {
    "gn:admin1_code":"5.0",
    "gn:asciiname":"Jinmagang",
    "gn:country_code":"CN",
    "gn:dem":197,
    "gn:feature_class":"P",
    "gn:feature_code":"PPL",
    "gn:name":"Jinmagang",
    "gn:population":0,
    "gn:timezone":"Asia/Shanghai",
    "iso:country":"CN",
    "name:zho_x_preferred":[
        "\u91d1\u9a6c\u5c97"
    ],
    "wof:name":"Jinmagang",
    "wof:placetype":"locality"
},
  "geometry": {"coordinates":[124.11118999999999,43.8739],"type":"Point"}
}