{
  "type": "Feature",
  "properties": {
    "gn:admin1_code":"16.0",
    "gn:asciiname":"Xiaxiantao",
    "gn:country_code":"CN",
    "gn:dem":782,
    "gn:feature_class":"P",
    "gn:feature_code":"PPL",
    "gn:name":"Xiaxiantao",
    "gn:population":0,
    "gn:timezone":"Asia/Shanghai",
    "iso:country":"CN",
    "name:zho_x_preferred":[
        "\u4e0b\u4ed9\u6843"
    ],
    "wof:name":"Xiaxiantao",
    "wof:placetype":"locality"
},
  "geometry": {"coordinates":[108.58,25.3212],"type":"Point"}
}