{
  "type": "Feature",
  "properties": {
    "gn:admin1_code":"5.0",
    "gn:asciiname":"Dongxinglongtun",
    "gn:country_code":"CN",
    "gn:dem":342,
    "gn:feature_class":"P",
    "gn:feature_code":"PPL",
    "gn:name":"Dongxinglongtun",
    "gn:population":0,
    "gn:timezone":"Asia/Shanghai",
    "iso:country":"CN",
    "name:zho_x_preferred":[
        "\u4e1c\u5174\u9f99\u5c6f"
    ],
    "wof:name":"Dongxinglongtun",
    "wof:placetype":"locality"
},
  "geometry": {"coordinates":[125.93838,42.87216],"type":"Point"}
}