{
  "type": "Feature",
  "properties": {
    "gn:admin1_code":"10",
    "gn:asciiname":"Naohaiying",
    "gn:country_code":"CN",
    "gn:dem":1348,
    "gn:feature_class":"P",
    "gn:feature_code":"PPL",
    "gn:name":"Naohaiying",
    "gn:population":0,
    "gn:timezone":"Asia/Shanghai",
    "iso:country":"CN",
    "name:zho_x_preferred":[
        "\u6dd6\u6d77\u8425"
    ],
    "wof:name":"Naohaiying",
    "wof:placetype":"locality"
},
  "geometry": {"coordinates":[114.48694,41.43024000000001],"type":"Point"}
}