{
  "type": "Feature",
  "properties": {
    "gn:admin1_code":"18",
    "gn:asciiname":"Lushan",
    "gn:cc2":"CN",
    "gn:country_code":"CN",
    "gn:dem":884,
    "gn:feature_class":"P",
    "gn:feature_code":"PPL",
    "gn:name":"Lushan",
    "gn:population":0,
    "gn:timezone":"Asia/Shanghai",
    "iso:country":"CN",
    "name:und_x_variant":[
        "Ch\u2019ing-p\u2019ing",
        "Lu-shan-hsien",
        "Qingping",
        "Lu-shan-hsien-ch\u2019eng",
        "L\u00fc-shan-miao-tsu-tzu-chih-hsien",
        "Lushan"
    ],
    "wof:name":"Lushan",
    "wof:placetype":"locality"
},
  "geometry": {"coordinates":[107.78333000000001,26.65],"type":"Point"}
}