{
  "type": "Feature",
  "properties": {
    "gn:admin1_code":"02",
    "gn:asciiname":"Beijiao",
    "gn:country_code":"CN",
    "gn:dem":8,
    "gn:feature_class":"P",
    "gn:feature_code":"PPL",
    "gn:name":"Beijiao",
    "gn:population":0,
    "gn:timezone":"Asia/Shanghai",
    "iso:country":"CN",
    "name:ceb_x_preferred":[
        "Beijiao"
    ],
    "name:deu_x_preferred":[
        "Beijiao"
    ],
    "name:swe_x_preferred":[
        "Beijiao"
    ],
    "wof:name":"Beijiao",
    "wof:placetype":"locality"
},
  "geometry": {"coordinates":[121.5825,29.90111],"type":"Point"}
}