{
  "type": "Feature",
  "properties": {
    "gn:admin1_code":"25.0",
    "gn:asciiname":"Dongdaogezhuang",
    "gn:country_code":"CN",
    "gn:dem":104,
    "gn:feature_class":"P",
    "gn:feature_code":"PPL",
    "gn:name":"Dongdaogezhuang",
    "gn:population":0,
    "gn:timezone":"Asia/Shanghai",
    "iso:country":"CN",
    "name:zho_x_preferred":[
        "\u4e1c\u9053\u683c\u5e84"
    ],
    "wof:name":"Dongdaogezhuang",
    "wof:placetype":"locality"
},
  "geometry": {"coordinates":[120.3847,36.88632],"type":"Point"}
}