{
  "type": "Feature",
  "properties": {
    "gn:admin1_code":"1.0",
    "gn:asciiname":"Zhengqiaocun",
    "gn:country_code":"CN",
    "gn:dem":36,
    "gn:feature_class":"P",
    "gn:feature_code":"PPL",
    "gn:name":"Zhengqiaocun",
    "gn:population":0,
    "gn:timezone":"Asia/Shanghai",
    "iso:country":"CN",
    "name:zho_x_preferred":[
        "\u90d1\u6865\u6751"
    ],
    "wof:name":"Zhengqiaocun",
    "wof:placetype":"locality"
},
  "geometry": {"coordinates":[118.16087,32.09102],"type":"Point"}
}