{
  "type": "Feature",
  "properties": {
    "gn:admin1_code":"30.0",
    "gn:asciiname":"Potoumian",
    "gn:country_code":"CN",
    "gn:dem":378,
    "gn:feature_class":"P",
    "gn:feature_code":"PPL",
    "gn:name":"Potoumian",
    "gn:population":0,
    "gn:timezone":"Asia/Shanghai",
    "iso:country":"CN",
    "name:zho_x_preferred":[
        "\u5761\u5934\u9762"
    ],
    "wof:name":"Potoumian",
    "wof:placetype":"locality"
},
  "geometry": {"coordinates":[112.03898,23.41594],"type":"Point"}
}