{
  "type": "Feature",
  "properties": {
    "gn:admin1_code":"29",
    "gn:asciiname":"Laomuzhai",
    "gn:country_code":"CN",
    "gn:dem":1395,
    "gn:feature_class":"P",
    "gn:feature_code":"PPL",
    "gn:name":"Laomuzhai",
    "gn:population":0,
    "gn:timezone":"Asia/Shanghai",
    "iso:country":"CN",
    "name:zho_x_preferred":[
        "\u8001\u6728\u5be8"
    ],
    "wof:name":"Laomuzhai",
    "wof:placetype":"locality"
},
  "geometry": {"coordinates":[101.947,23.9016],"type":"Point"}
}