{
  "type": "Feature",
  "properties": {
    "gn:admin1_code":"15.0",
    "gn:asciiname":"Baijia Yantou",
    "gn:country_code":"CN",
    "gn:dem":1971,
    "gn:feature_class":"P",
    "gn:feature_code":"PPL",
    "gn:name":"Baijia Yantou",
    "gn:population":0,
    "gn:timezone":"Asia/Shanghai",
    "iso:country":"CN",
    "name:zho_x_preferred":[
        "\u767d\u5bb6\u5ca9\u5934"
    ],
    "wof:name":"Baijia Yantou",
    "wof:placetype":"locality"
},
  "geometry": {"coordinates":[103.19199999999999,36.4157],"type":"Point"}
}