{
  "type": "Feature",
  "properties": {
    "gn:admin1_code":"29.0",
    "gn:asciiname":"Heiwadi",
    "gn:country_code":"CN",
    "gn:dem":1978,
    "gn:feature_class":"P",
    "gn:feature_code":"PPL",
    "gn:name":"Heiwadi",
    "gn:population":0,
    "gn:timezone":"Asia/Shanghai",
    "iso:country":"CN",
    "name:zho_x_preferred":[
        "\u9ed1\u5a03\u5e95"
    ],
    "wof:name":"Heiwadi",
    "wof:placetype":"locality"
},
  "geometry": {"coordinates":[98.6007,27.7799],"type":"Point"}
}