{
  "type": "Feature",
  "properties": {
    "gn:admin1_code":"19.0",
    "gn:asciiname":"Yingjiecun",
    "gn:country_code":"CN",
    "gn:dem":45,
    "gn:feature_class":"P",
    "gn:feature_code":"PPL",
    "gn:name":"Yingjiecun",
    "gn:population":0,
    "gn:timezone":"Asia/Shanghai",
    "iso:country":"CN",
    "name:zho_x_preferred":[
        "\u82f1\u6770\u6751"
    ],
    "wof:name":"Yingjiecun",
    "wof:placetype":"locality"
},
  "geometry": {"coordinates":[122.72629999999999,39.23869000000001],"type":"Point"}
}