{
  "type": "Feature",
  "properties": {
    "gn:admin1_code":"16.0",
    "gn:asciiname":"Duliucun",
    "gn:country_code":"CN",
    "gn:dem":414,
    "gn:feature_class":"P",
    "gn:feature_code":"PPL",
    "gn:name":"Duliucun",
    "gn:population":0,
    "gn:timezone":"Asia/Shanghai",
    "iso:country":"CN",
    "name:zho_x_preferred":[
        "\u90fd\u516d\u6751"
    ],
    "wof:name":"Duliucun",
    "wof:placetype":"locality"
},
  "geometry": {"coordinates":[108.84999999999999,24.1569],"type":"Point"}
}