{
  "type": "Feature",
  "properties": {
    "gn:admin1_code":"8.0",
    "gn:asciiname":"Erdaogangcun",
    "gn:country_code":"CN",
    "gn:dem":63,
    "gn:feature_class":"P",
    "gn:feature_code":"PPL",
    "gn:name":"Erdaogangcun",
    "gn:population":0,
    "gn:timezone":"Asia/Shanghai",
    "iso:country":"CN",
    "name:zho_x_preferred":[
        "\u4e8c\u9053\u5c97\u6751"
    ],
    "wof:name":"Erdaogangcun",
    "wof:placetype":"locality"
},
  "geometry": {"coordinates":[131.8219,47.08904],"type":"Point"}
}