{
  "type": "Feature",
  "properties": {
    "gn:admin1_code":"26",
    "gn:asciiname":"Qianzuili",
    "gn:country_code":"CN",
    "gn:dem":862,
    "gn:feature_class":"P",
    "gn:feature_code":"PPL",
    "gn:name":"Qianzuili",
    "gn:population":0,
    "gn:timezone":"Asia/Shanghai",
    "iso:country":"CN",
    "name:und_x_variant":[
        "\u524d\u5480\u91cc"
    ],
    "name:zho_x_preferred":[
        "\u524d\u5480\u91cc"
    ],
    "wof:name":"Qianzuili",
    "wof:placetype":"locality"
},
  "geometry": {"coordinates":[108.47111,34.77889],"type":"Point"}
}