{
  "type": "Feature",
  "properties": {
    "gn:admin1_code":"19.0",
    "gn:asciiname":"Damolike",
    "gn:country_code":"CN",
    "gn:dem":108,
    "gn:feature_class":"P",
    "gn:feature_code":"PPL",
    "gn:name":"Damolike",
    "gn:population":0,
    "gn:timezone":"Asia/Shanghai",
    "iso:country":"CN",
    "name:zho_x_preferred":[
        "\u5927\u83ab\u529b\u514b"
    ],
    "wof:name":"Damolike",
    "wof:placetype":"locality"
},
  "geometry": {"coordinates":[123.12255999999999,42.73897],"type":"Point"}
}