{
  "type": "Feature",
  "properties": {
    "gn:admin1_code":"32.0",
    "gn:asciiname":"Tianxingzhai",
    "gn:country_code":"CN",
    "gn:dem":467,
    "gn:feature_class":"P",
    "gn:feature_code":"PPL",
    "gn:name":"Tianxingzhai",
    "gn:population":0,
    "gn:timezone":"Asia/Shanghai",
    "iso:country":"CN",
    "name:zho_x_preferred":[
        "\u5929\u661f\u5be8"
    ],
    "wof:name":"Tianxingzhai",
    "wof:placetype":"locality"
},
  "geometry": {"coordinates":[106.64400000000001,31.833],"type":"Point"}
}