{
  "type": "Feature",
  "properties": {
    "gn:admin1_code":"12.0",
    "gn:asciiname":"Lipowan",
    "gn:country_code":"CN",
    "gn:dem":137,
    "gn:feature_class":"P",
    "gn:feature_code":"PPL",
    "gn:name":"Lipowan",
    "gn:population":0,
    "gn:timezone":"Asia/Shanghai",
    "iso:country":"CN",
    "name:zho_x_preferred":[
        "\u68a8\u5761\u6e7e"
    ],
    "wof:name":"Lipowan",
    "wof:placetype":"locality"
},
  "geometry": {"coordinates":[113.70349,31.74886],"type":"Point"}
}