{
  "type": "Feature",
  "properties": {
    "gn:admin1_code":"12",
    "gn:asciiname":"Shuangliu",
    "gn:country_code":"CN",
    "gn:dem":27,
    "gn:feature_class":"P",
    "gn:feature_code":"PPLA4",
    "gn:name":"Shuangliu",
    "gn:population":0,
    "gn:timezone":"Asia/Shanghai",
    "iso:country":"CN",
    "name:und_x_variant":[
        "\u53cc\u67f3",
        "Shuangliu Jiedao",
        "\u53cc\u67f3\u8857\u9053"
    ],
    "wof:name":"Shuangliu",
    "wof:placetype":"locality"
},
  "geometry": {"coordinates":[114.64179,30.5922],"type":"Point"}
}