{
  "type": "Feature",
  "properties": {
    "gn:admin1_code":"11",
    "gn:asciiname":"Baimatian",
    "gn:country_code":"CN",
    "gn:dem":314,
    "gn:feature_class":"P",
    "gn:feature_code":"PPL",
    "gn:name":"Baimatian",
    "gn:population":0,
    "gn:timezone":"Asia/Shanghai",
    "iso:country":"CN",
    "wof:name":"Baimatian",
    "wof:placetype":"locality"
},
  "geometry": {"coordinates":[110.80806,26.50278],"type":"Point"}
}