{
  "type": "Feature",
  "properties": {
    "gn:admin1_code":"16",
    "gn:asciiname":"Lingzhun",
    "gn:country_code":"CN",
    "gn:dem":876,
    "gn:feature_class":"P",
    "gn:feature_code":"PPL",
    "gn:name":"Lingzhun",
    "gn:population":0,
    "gn:timezone":"Asia/Shanghai",
    "iso:country":"CN",
    "name:und_x_variant":[
        "Ling-chun-hsiang",
        "Lingzhun"
    ],
    "name:zho_x_preferred":[
        "\u51cc\u51c6"
    ],
    "wof:name":"Lingzhun",
    "wof:placetype":"locality"
},
  "geometry": {"coordinates":[106.206,23.1592],"type":"Point"}
}