{
  "type": "Feature",
  "properties": {
    "gn:admin1_code":"15.0",
    "gn:asciiname":"Yinziwa",
    "gn:country_code":"CN",
    "gn:dem":1463,
    "gn:feature_class":"P",
    "gn:feature_code":"PPL",
    "gn:name":"Yinziwa",
    "gn:population":0,
    "gn:timezone":"Asia/Shanghai",
    "iso:country":"CN",
    "name:zho_x_preferred":[
        "\u7aa8\u5b50\u6d3c"
    ],
    "wof:name":"Yinziwa",
    "wof:placetype":"locality"
},
  "geometry": {"coordinates":[106.71299999999999,35.6172],"type":"Point"}
}