{
  "type": "Feature",
  "properties": {
    "gn:admin1_code":"11",
    "gn:asciiname":"Lengshuipu",
    "gn:country_code":"CN",
    "gn:dem":211,
    "gn:feature_class":"P",
    "gn:feature_code":"PPL",
    "gn:name":"Lengshuipu",
    "gn:population":0,
    "gn:timezone":"Asia/Shanghai",
    "iso:country":"CN",
    "name:zho_x_preferred":[
        "\u51b7\u6c34\u94fa"
    ],
    "wof:name":"Lengshuipu",
    "wof:placetype":"locality"
},
  "geometry": {"coordinates":[112.02889,25.55222],"type":"Point"}
}