{
  "type": "Feature",
  "properties": {
    "gn:admin1_code":"3.0",
    "gn:asciiname":"Songlingxia",
    "gn:country_code":"CN",
    "gn:dem":44,
    "gn:feature_class":"P",
    "gn:feature_code":"PPL",
    "gn:name":"Songlingxia",
    "gn:population":0,
    "gn:timezone":"Asia/Shanghai",
    "iso:country":"CN",
    "name:und_x_variant":[
        "\u677e\u5cad\u4e0b"
    ],
    "wof:name":"Songlingxia",
    "wof:placetype":"locality"
},
  "geometry": {"coordinates":[116.79949999999999,29.86822],"type":"Point"}
}