{
  "type": "Feature",
  "properties": {
    "gn:admin1_code":"25",
    "gn:asciiname":"Jizhuang",
    "gn:country_code":"CN",
    "gn:dem":60,
    "gn:feature_class":"P",
    "gn:feature_code":"PPL",
    "gn:name":"Jizhuang",
    "gn:population":0,
    "gn:timezone":"Asia/Shanghai",
    "iso:country":"CN",
    "name:zho_x_preferred":[
        "\u7eaa\u5e84"
    ],
    "wof:name":"Jizhuang",
    "wof:placetype":"locality"
},
  "geometry": {"coordinates":[118.447,34.7115],"type":"Point"}
}