{
  "type": "Feature",
  "properties": {
    "gn:admin1_code":"24.0",
    "gn:asciiname":"Jishancun",
    "gn:country_code":"CN",
    "gn:dem":400,
    "gn:feature_class":"P",
    "gn:feature_code":"PPL",
    "gn:name":"Jishancun",
    "gn:population":0,
    "gn:timezone":"Asia/Shanghai",
    "iso:country":"CN",
    "name:zho_x_preferred":[
        "\u79ef\u5584\u6751"
    ],
    "wof:name":"Jishancun",
    "wof:placetype":"locality"
},
  "geometry": {"coordinates":[110.46465999999999,35.04449],"type":"Point"}
}