{
  "type": "Feature",
  "properties": {
    "gn:admin1_code":"16.0",
    "gn:asciiname":"Bade",
    "gn:country_code":"CN",
    "gn:dem":353,
    "gn:feature_class":"P",
    "gn:feature_code":"PPL",
    "gn:name":"Bade",
    "gn:population":0,
    "gn:timezone":"Asia/Shanghai",
    "iso:country":"CN",
    "name:ceb_x_preferred":[
        "Bade"
    ],
    "name:deu_x_preferred":[
        "Bade"
    ],
    "name:fra_x_preferred":[
        "Bade"
    ],
    "name:glg_x_preferred":[
        "Bade"
    ],
    "name:ita_x_preferred":[
        "Bade"
    ],
    "name:kat_x_preferred":[
        "\u10d1\u10d0\u10d3\u10d4"
    ],
    "name:nld_x_preferred":[
        "Bade"
    ],
    "name:rus_x_preferred":[
        "\u0411\u0430\u0434\u0435"
    ],
    "name:swe_x_preferred":[
        "Bade"
    ],
    "name:zho_x_preferred":[
        "\u5df4\u7684"
    ],
    "wof:name":"Bade",
    "wof:placetype":"locality"
},
  "geometry": {"coordinates":[107.57599999999999,21.6703],"type":"Point"}
}