{
  "type": "Feature",
  "properties": {
    "gn:admin1_code":"32.0",
    "gn:asciiname":"Shitagou",
    "gn:country_code":"CN",
    "gn:dem":414,
    "gn:feature_class":"P",
    "gn:feature_code":"PPL",
    "gn:name":"Shitagou",
    "gn:population":0,
    "gn:timezone":"Asia/Shanghai",
    "iso:country":"CN",
    "name:zho_x_preferred":[
        "\u77f3\u5854\u6c9f"
    ],
    "wof:name":"Shitagou",
    "wof:placetype":"locality"
},
  "geometry": {"coordinates":[104.127,29.6794],"type":"Point"}
}