{
  "type": "Feature",
  "properties": {
    "gn:admin1_code":"12.0",
    "gn:asciiname":"Lianyudi",
    "gn:country_code":"CN",
    "gn:dem":25,
    "gn:feature_class":"P",
    "gn:feature_code":"PPL",
    "gn:name":"Lianyudi",
    "gn:population":0,
    "gn:timezone":"Asia/Shanghai",
    "iso:country":"CN",
    "name:zho_x_preferred":[
        "\u9ca2\u9c7c\u5730"
    ],
    "wof:name":"Lianyudi",
    "wof:placetype":"locality"
},
  "geometry": {"coordinates":[113.94878,30.83784],"type":"Point"}
}