{
  "type": "Feature",
  "properties": {
    "gn:admin1_code":"25",
    "gn:asciiname":"Wangcan Wuzi",
    "gn:country_code":"CN",
    "gn:dem":4,
    "gn:feature_class":"P",
    "gn:feature_code":"PPL",
    "gn:name":"Wangcan Wuzi",
    "gn:population":0,
    "gn:timezone":"Asia/Shanghai",
    "iso:country":"CN",
    "name:zho_x_preferred":[
        "\u738b\u53c2\u5c4b\u5b50"
    ],
    "wof:name":"Wangcan Wuzi",
    "wof:placetype":"locality"
},
  "geometry": {"coordinates":[118.246,38.0107],"type":"Point"}
}