{
  "type": "Feature",
  "properties": {
    "gn:admin1_code":"12.0",
    "gn:asciiname":"Maojialiangzi",
    "gn:country_code":"CN",
    "gn:dem":1181,
    "gn:feature_class":"P",
    "gn:feature_code":"PPL",
    "gn:name":"Maojialiangzi",
    "gn:population":0,
    "gn:timezone":"Asia/Shanghai",
    "iso:country":"CN",
    "name:zho_x_preferred":[
        "\u6bdb\u5bb6\u7cb1\u5b50"
    ],
    "wof:name":"Maojialiangzi",
    "wof:placetype":"locality"
},
  "geometry": {"coordinates":[109.82075,30.26855],"type":"Point"}
}