{
  "type": "Feature",
  "properties": {
    "gn:admin1_code":"25",
    "gn:asciiname":"Zhanglou",
    "gn:country_code":"CN",
    "gn:dem":28,
    "gn:feature_class":"P",
    "gn:feature_code":"PPL",
    "gn:name":"Zhanglou",
    "gn:population":0,
    "gn:timezone":"Asia/Shanghai",
    "iso:country":"CN",
    "name:zho_x_preferred":[
        "\u5f20\u697c"
    ],
    "wof:name":"Zhanglou",
    "wof:placetype":"locality"
},
  "geometry": {"coordinates":[117.755,34.6335],"type":"Point"}
}