{
  "type": "Feature",
  "properties": {
    "gn:admin1_code":"4.0",
    "gn:asciiname":"Damuqiaodai",
    "gn:country_code":"CN",
    "gn:dem":2,
    "gn:feature_class":"P",
    "gn:feature_code":"PPL",
    "gn:name":"Damuqiaodai",
    "gn:population":0,
    "gn:timezone":"Asia/Shanghai",
    "iso:country":"CN",
    "name:und_x_variant":[
        "\u5927\u6728\u6865\u5788"
    ],
    "name:zho_x_preferred":[
        "\u5927\u6728\u6865\u5788"
    ],
    "wof:name":"Damuqiaodai",
    "wof:placetype":"locality"
},
  "geometry": {"coordinates":[120.36342999999999,32.10716],"type":"Point"}
}