{
  "type": "Feature",
  "properties": {
    "gn:admin1_code":"25.0",
    "gn:asciiname":"Qiansunjiazhuang",
    "gn:country_code":"CN",
    "gn:dem":35,
    "gn:feature_class":"P",
    "gn:feature_code":"PPL",
    "gn:name":"Qiansunjiazhuang",
    "gn:population":0,
    "gn:timezone":"Asia/Shanghai",
    "iso:country":"CN",
    "name:zho_x_preferred":[
        "\u524d\u5b59\u5bb6\u5e84"
    ],
    "wof:name":"Qiansunjiazhuang",
    "wof:placetype":"locality"
},
  "geometry": {"coordinates":[119.54212,36.49347],"type":"Point"}
}