{
  "type": "Feature",
  "properties": {
    "gn:admin1_code":"8.0",
    "gn:asciiname":"Dalazicun",
    "gn:country_code":"CN",
    "gn:dem":294,
    "gn:feature_class":"P",
    "gn:feature_code":"PPL",
    "gn:name":"Dalazicun",
    "gn:population":0,
    "gn:timezone":"Asia/Shanghai",
    "iso:country":"CN",
    "name:zho_x_preferred":[
        "\u5927\u782c\u5b50\u6751"
    ],
    "wof:name":"Dalazicun",
    "wof:placetype":"locality"
},
  "geometry": {"coordinates":[130.41935000000001,45.3454],"type":"Point"}
}