{
  "type": "Feature",
  "properties": {
    "gn:admin1_code":"14",
    "gn:asciiname":"Desizuokuo",
    "gn:country_code":"CN",
    "gn:dem":4380,
    "gn:feature_class":"P",
    "gn:feature_code":"PPL",
    "gn:name":"Desizuokuo",
    "gn:population":0,
    "gn:timezone":"Asia/Urumqi",
    "iso:country":"CN",
    "name:zho_x_preferred":[
        "\u5f97\u53f8\u4f5c\u62ec"
    ],
    "wof:name":"Desizuokuo",
    "wof:placetype":"locality"
},
  "geometry": {"coordinates":[89.095,29.2796],"type":"Point"}
}