{
  "type": "Feature",
  "properties": {
    "gn:admin1_code":"15.0",
    "gn:asciiname":"Caimajia",
    "gn:country_code":"CN",
    "gn:dem":2043,
    "gn:feature_class":"P",
    "gn:feature_code":"PPL",
    "gn:name":"Caimajia",
    "gn:population":0,
    "gn:timezone":"Asia/Shanghai",
    "iso:country":"CN",
    "name:zho_x_preferred":[
        "\u8521\u9a6c\u5bb6"
    ],
    "wof:name":"Caimajia",
    "wof:placetype":"locality"
},
  "geometry": {"coordinates":[103.32899999999999,35.5877],"type":"Point"}
}