{
  "type": "Feature",
  "properties": {
    "gn:admin1_code":"11.0",
    "gn:asciiname":"Zhoujiawan",
    "gn:country_code":"CN",
    "gn:dem":109,
    "gn:feature_class":"P",
    "gn:feature_code":"PPL",
    "gn:name":"Zhoujiawan",
    "gn:population":0,
    "gn:timezone":"Asia/Shanghai",
    "iso:country":"CN",
    "name:zho_x_preferred":[
        "\u5468\u5bb6\u6e7e"
    ],
    "wof:name":"Zhoujiawan",
    "wof:placetype":"locality"
},
  "geometry": {"coordinates":[113.20041999999999,27.1943],"type":"Point"}
}