{
  "type": "Feature",
  "properties": {
    "gn:admin1_code":"29.0",
    "gn:asciiname":"Shanggungang",
    "gn:country_code":"CN",
    "gn:dem":1833,
    "gn:feature_class":"P",
    "gn:feature_code":"PPL",
    "gn:name":"Shanggungang",
    "gn:population":0,
    "gn:timezone":"Asia/Shanghai",
    "iso:country":"CN",
    "name:zho_x_preferred":[
        "\u4e0a\u6eda\u7f38"
    ],
    "wof:name":"Shanggungang",
    "wof:placetype":"locality"
},
  "geometry": {"coordinates":[100.02200000000001,24.1142],"type":"Point"}
}