{
  "type": "Feature",
  "properties": {
    "gn:admin1_code":"29.0",
    "gn:asciiname":"Cihang",
    "gn:country_code":"CN",
    "gn:dem":2009,
    "gn:feature_class":"P",
    "gn:feature_code":"PPL",
    "gn:name":"Cihang",
    "gn:population":0,
    "gn:timezone":"Asia/Shanghai",
    "iso:country":"CN",
    "name:zho_x_preferred":[
        "\u6148\u822a"
    ],
    "wof:name":"Cihang",
    "wof:placetype":"locality"
},
  "geometry": {"coordinates":[100.32899999999999,25.5876],"type":"Point"}
}