{
  "type": "Feature",
  "properties": {
    "gn:admin1_code":"8.0",
    "gn:asciiname":"Jinshantun",
    "gn:country_code":"CN",
    "gn:dem":191,
    "gn:feature_class":"P",
    "gn:feature_code":"PPL",
    "gn:name":"Jinshantun",
    "gn:population":0,
    "gn:timezone":"Asia/Shanghai",
    "iso:country":"CN",
    "name:zho_x_preferred":[
        "\u91d1\u5c71\u5c6f"
    ],
    "wof:name":"Jinshantun",
    "wof:placetype":"locality"
},
  "geometry": {"coordinates":[128.34880999999999,45.54001],"type":"Point"}
}