{
  "type": "Feature",
  "properties": {
    "gn:admin1_code":"12.0",
    "gn:asciiname":"Yanwugou",
    "gn:country_code":"CN",
    "gn:dem":578,
    "gn:feature_class":"P",
    "gn:feature_code":"PPL",
    "gn:name":"Yanwugou",
    "gn:population":0,
    "gn:timezone":"Asia/Shanghai",
    "iso:country":"CN",
    "name:zho_x_preferred":[
        "\u5ca9\u5c4b\u6c9f"
    ],
    "wof:name":"Yanwugou",
    "wof:placetype":"locality"
},
  "geometry": {"coordinates":[110.99129000000001,31.01173],"type":"Point"}
}