{
  "type": "Feature",
  "properties": {
    "gn:admin1_code":"29",
    "gn:asciiname":"Shangdabao",
    "gn:country_code":"CN",
    "gn:dem":1459,
    "gn:feature_class":"P",
    "gn:feature_code":"PPL",
    "gn:name":"Shangdabao",
    "gn:population":0,
    "gn:timezone":"Asia/Shanghai",
    "iso:country":"CN",
    "name:zho_x_preferred":[
        "\u4e0a\u8fbe\u4fdd"
    ],
    "wof:name":"Shangdabao",
    "wof:placetype":"locality"
},
  "geometry": {"coordinates":[104.794,23.699],"type":"Point"}
}