{
  "type": "Feature",
  "properties": {
    "gn:admin1_code":"18",
    "gn:asciiname":"Jichangbu",
    "gn:country_code":"CN",
    "gn:dem":1236,
    "gn:feature_class":"P",
    "gn:feature_code":"PPL",
    "gn:name":"Jichangbu",
    "gn:population":0,
    "gn:timezone":"Asia/Shanghai",
    "iso:country":"CN",
    "name:zho_x_preferred":[
        "\u9e21\u573a\u5821"
    ],
    "wof:name":"Jichangbu",
    "wof:placetype":"locality"
},
  "geometry": {"coordinates":[106.331,26.6449],"type":"Point"}
}