{
  "type": "Feature",
  "properties": {
    "gn:admin1_code":"26.0",
    "gn:asciiname":"Liangqucun",
    "gn:country_code":"CN",
    "gn:dem":1009,
    "gn:feature_class":"P",
    "gn:feature_code":"PPL",
    "gn:name":"Liangqucun",
    "gn:population":0,
    "gn:timezone":"Asia/Shanghai",
    "iso:country":"CN",
    "name:zho_x_preferred":[
        "\u6881\u6e20\u6751"
    ],
    "wof:name":"Liangqucun",
    "wof:placetype":"locality"
},
  "geometry": {"coordinates":[109.86086,38.02402],"type":"Point"}
}