{
  "type": "Feature",
  "properties": {
    "gn:admin1_code":"29.0",
    "gn:asciiname":"Hebian Xiazhai",
    "gn:country_code":"CN",
    "gn:dem":1866,
    "gn:feature_class":"P",
    "gn:feature_code":"PPL",
    "gn:name":"Hebian Xiazhai",
    "gn:population":0,
    "gn:timezone":"Asia/Shanghai",
    "iso:country":"CN",
    "name:zho_x_preferred":[
        "\u6cb3\u8fb9\u4e0b\u5be8"
    ],
    "wof:name":"Hebian Xiazhai",
    "wof:placetype":"locality"
},
  "geometry": {"coordinates":[98.01949999999999,24.9963],"type":"Point"}
}