{
  "type": "Feature",
  "properties": {
    "gn:admin1_code":"25.0",
    "gn:asciiname":"Beisushijia",
    "gn:country_code":"CN",
    "gn:dem":24,
    "gn:feature_class":"P",
    "gn:feature_code":"PPL",
    "gn:name":"Beisushijia",
    "gn:population":0,
    "gn:timezone":"Asia/Shanghai",
    "iso:country":"CN",
    "name:zho_x_preferred":[
        "\u5317\u5bbf\u77f3\u5bb6"
    ],
    "wof:name":"Beisushijia",
    "wof:placetype":"locality"
},
  "geometry": {"coordinates":[120.46425000000001,37.65539],"type":"Point"}
}