{
  "type": "Feature",
  "properties": {
    "gn:admin1_code":"32.0",
    "gn:asciiname":"Sanchang",
    "gn:country_code":"CN",
    "gn:dem":1470,
    "gn:feature_class":"P",
    "gn:feature_code":"PPL",
    "gn:name":"Sanchang",
    "gn:population":0,
    "gn:timezone":"Asia/Shanghai",
    "iso:country":"CN",
    "name:zho_x_preferred":[
        "\u4e09\u573a"
    ],
    "wof:name":"Sanchang",
    "wof:placetype":"locality"
},
  "geometry": {"coordinates":[103.72799999999999,31.5698],"type":"Point"}
}