{
  "type": "Feature",
  "properties": {
    "gn:admin1_code":"13",
    "gn:asciiname":"Langan",
    "gn:country_code":"CN",
    "gn:dem":255,
    "gn:feature_class":"P",
    "gn:feature_code":"PPL",
    "gn:name":"Langan",
    "gn:population":0,
    "gn:timezone":"Asia/Urumqi",
    "iso:country":"CN",
    "name:ceb_x_preferred":[
        "Langan"
    ],
    "name:deu_x_preferred":[
        "Langan"
    ],
    "name:fra_x_preferred":[
        "Langan"
    ],
    "name:und_x_variant":[
        "\u5170\u5e72"
    ],
    "wof:name":"Langan",
    "wof:placetype":"locality"
},
  "geometry": {"coordinates":[90.12088,42.81336],"type":"Point"}
}