{
  "type": "Feature",
  "properties": {
    "gn:admin1_code":"10.0",
    "gn:asciiname":"Huangyukeng",
    "gn:country_code":"CN",
    "gn:dem":694,
    "gn:feature_class":"P",
    "gn:feature_code":"PPL",
    "gn:name":"Huangyukeng",
    "gn:population":0,
    "gn:timezone":"Asia/Shanghai",
    "iso:country":"CN",
    "name:zho_x_preferred":[
        "\u9ec4\u9c7c\u5751"
    ],
    "wof:name":"Huangyukeng",
    "wof:placetype":"locality"
},
  "geometry": {"coordinates":[117.26916,40.35044],"type":"Point"}
}