{
  "type": "Feature",
  "properties": {
    "gn:admin1_code":"19",
    "gn:asciiname":"Jiubing",
    "gn:country_code":"CN",
    "gn:dem":218,
    "gn:feature_class":"P",
    "gn:feature_code":"PPLA4",
    "gn:name":"Jiubing",
    "gn:population":0,
    "gn:timezone":"Asia/Shanghai",
    "iso:country":"CN",
    "name:und_x_variant":[
        "Chiu-ping-t\u2019ai",
        "Jiubing Xiang",
        "Jiubingtai",
        "Jiubing",
        "\u6551\u5175",
        "\u6551\u5175\u4e61"
    ],
    "wof:name":"Jiubing",
    "wof:placetype":"locality"
},
  "geometry": {"coordinates":[124.10993000000001,41.64225],"type":"Point"}
}