{
  "type": "Feature",
  "properties": {
    "gn:admin1_code":"25",
    "gn:asciiname":"Zhaodong",
    "gn:country_code":"CN",
    "gn:dem":15,
    "gn:feature_class":"P",
    "gn:feature_code":"PPL",
    "gn:name":"Zhaodong",
    "gn:population":0,
    "gn:timezone":"Asia/Shanghai",
    "iso:country":"CN",
    "name:ara_x_preferred":[
        "\u062c\u0627\u0648\u062f\u0648\u0646\u063a"
    ],
    "name:ceb_x_preferred":[
        "Zhaodong"
    ],
    "name:deu_x_preferred":[
        "Zhaodong"
    ],
    "name:fin_x_preferred":[
        "Zhaodong"
    ],
    "name:fra_x_preferred":[
        "Zhaodong"
    ],
    "name:ita_x_preferred":[
        "Zhaodong"
    ],
    "name:jpn_x_preferred":[
        "\u8087\u6771\u5e02"
    ],
    "name:kik_x_preferred":[
        "Zhaodong"
    ],
    "name:kor_x_preferred":[
        "\uc790\uc624\ub465\uc2dc"
    ],
    "name:mlg_x_preferred":[
        "Zhaodong"
    ],
    "name:nor_x_preferred":[
        "Zhaodong"
    ],
    "name:pam_x_preferred":[
        "Zhaodong"
    ],
    "name:rus_x_preferred":[
        "\u0427\u0436\u0430\u043e\u0434\u0443\u043d"
    ],
    "name:swe_x_preferred":[
        "Zhaodong"
    ],
    "name:urd_x_preferred":[
        "\u0698\u0627\u0648\u062f\u0648\u0646\u06af"
    ],
    "name:vie_x_preferred":[
        "Tri\u1ec7u \u0110\u00f4ng"
    ],
    "name:war_x_preferred":[
        "Zhaodong"
    ],
    "name:zho_x_preferred":[
        "\u8d75\u4e1c"
    ],
    "name:zho_x_variant":[
        "\u8087\u4e1c\u5e02"
    ],
    "wof:name":"Zhaodong",
    "wof:placetype":"locality"
},
  "geometry": {"coordinates":[117.39100000000001,37.2706],"type":"Point"}
}