{
  "type": "Feature",
  "properties": {
    "gn:admin1_code":"19.0",
    "gn:asciiname":"Hongzhangzi",
    "gn:country_code":"CN",
    "gn:dem":526,
    "gn:feature_class":"P",
    "gn:feature_code":"PPL",
    "gn:name":"Hongzhangzi",
    "gn:population":0,
    "gn:timezone":"Asia/Shanghai",
    "iso:country":"CN",
    "name:zho_x_preferred":[
        "\u6d2a\u6756\u5b50"
    ],
    "wof:name":"Hongzhangzi",
    "wof:placetype":"locality"
},
  "geometry": {"coordinates":[119.461,40.5638],"type":"Point"}
}