{
  "type": "Feature",
  "properties": {
    "gn:admin1_code":"25",
    "gn:asciiname":"Hongchuan",
    "gn:country_code":"CN",
    "gn:dem":50,
    "gn:feature_class":"P",
    "gn:feature_code":"PPL",
    "gn:name":"Hongchuan",
    "gn:population":0,
    "gn:timezone":"Asia/Shanghai",
    "iso:country":"CN",
    "name:und_x_variant":[
        "Hung-ch\u2019uan-chi",
        "Hongchuankou",
        "Hung-ch\u2019uan-k\u2019ou",
        "Hongchuan"
    ],
    "wof:name":"Hongchuan",
    "wof:placetype":"locality"
},
  "geometry": {"coordinates":[115.68694000000001,35.53833],"type":"Point"}
}