{
  "type": "Feature",
  "properties": {
    "gn:admin1_code":"10.0",
    "gn:asciiname":"Xishaijiashan",
    "gn:country_code":"CN",
    "gn:dem":84,
    "gn:feature_class":"P",
    "gn:feature_code":"PPL",
    "gn:name":"Xishaijiashan",
    "gn:population":0,
    "gn:timezone":"Asia/Shanghai",
    "iso:country":"CN",
    "name:zho_x_preferred":[
        "\u897f\u6652\u7532\u5c71"
    ],
    "wof:name":"Xishaijiashan",
    "wof:placetype":"locality"
},
  "geometry": {"coordinates":[118.77076,40.0686],"type":"Point"}
}