{
  "type": "Feature",
  "properties": {
    "gn:admin1_code":"4.0",
    "gn:asciiname":"Yuejiangxin",
    "gn:country_code":"CN",
    "gn:dem":4,
    "gn:feature_class":"P",
    "gn:feature_code":"PPL",
    "gn:name":"Yuejiangxin",
    "gn:population":0,
    "gn:timezone":"Asia/Shanghai",
    "iso:country":"CN",
    "name:zho_x_preferred":[
        "\u8d8a\u6c5f\u65b0"
    ],
    "wof:name":"Yuejiangxin",
    "wof:placetype":"locality"
},
  "geometry": {"coordinates":[120.82108999999998,32.02839],"type":"Point"}
}