{
  "type": "Feature",
  "properties": {
    "gn:admin1_code":"1.0",
    "gn:asciiname":"Xiaonicun",
    "gn:country_code":"CN",
    "gn:dem":71,
    "gn:feature_class":"P",
    "gn:feature_code":"PPL",
    "gn:name":"Xiaonicun",
    "gn:population":0,
    "gn:timezone":"Asia/Shanghai",
    "iso:country":"CN",
    "name:und_x_variant":[
        "Xiaoni"
    ],
    "name:zho_x_preferred":[
        "\u5c0f\u502a\u6751"
    ],
    "wof:name":"Xiaonicun",
    "wof:placetype":"locality"
},
  "geometry": {"coordinates":[118.18397,32.52435],"type":"Point"}
}