{
  "type": "Feature",
  "properties": {
    "gn:admin1_code":"15.0",
    "gn:asciiname":"Qianjiacha",
    "gn:country_code":"CN",
    "gn:dem":1794,
    "gn:feature_class":"P",
    "gn:feature_code":"PPL",
    "gn:name":"Qianjiacha",
    "gn:population":0,
    "gn:timezone":"Asia/Shanghai",
    "iso:country":"CN",
    "name:zho_x_preferred":[
        "\u6b20\u5bb6\u5c94"
    ],
    "wof:name":"Qianjiacha",
    "wof:placetype":"locality"
},
  "geometry": {"coordinates":[105.008,36.0814],"type":"Point"}
}