{
  "type": "Feature",
  "properties": {
    "gn:admin1_code":"4.0",
    "gn:asciiname":"Bianjiashe",
    "gn:country_code":"CN",
    "gn:dem":1,
    "gn:feature_class":"P",
    "gn:feature_code":"PPL",
    "gn:name":"Bianjiashe",
    "gn:population":0,
    "gn:timezone":"Asia/Shanghai",
    "iso:country":"CN",
    "name:zho_x_preferred":[
        "\u535e\u5bb6\u820d"
    ],
    "wof:name":"Bianjiashe",
    "wof:placetype":"locality"
},
  "geometry": {"coordinates":[120.08199999999999,33.1919],"type":"Point"}
}