{
  "type": "Feature",
  "properties": {
    "gn:admin1_code":"24.0",
    "gn:asciiname":"Zhangsiyao",
    "gn:country_code":"CN",
    "gn:dem":1166,
    "gn:feature_class":"P",
    "gn:feature_code":"PPL",
    "gn:name":"Zhangsiyao",
    "gn:population":0,
    "gn:timezone":"Asia/Shanghai",
    "iso:country":"CN",
    "name:zho_x_preferred":[
        "\u5f20\u5bfa\u7a91"
    ],
    "wof:name":"Zhangsiyao",
    "wof:placetype":"locality"
},
  "geometry": {"coordinates":[113.15703000000001,40.11326],"type":"Point"}
}