{
  "type": "Feature",
  "properties": {
    "gn:admin1_code":"14.0",
    "gn:asciiname":"Qieqieka",
    "gn:country_code":"CN",
    "gn:dem":4039,
    "gn:feature_class":"P",
    "gn:feature_code":"PPL",
    "gn:name":"Qieqieka",
    "gn:population":0,
    "gn:timezone":"Asia/Urumqi",
    "iso:country":"CN",
    "name:zho_x_preferred":[
        "\u5207\u5207\u5361"
    ],
    "wof:name":"Qieqieka",
    "wof:placetype":"locality"
},
  "geometry": {"coordinates":[95.35406,31.58474],"type":"Point"}
}