{
  "type": "Feature",
  "properties": {
    "gn:admin1_code":"33.0",
    "gn:asciiname":"Lianqiu",
    "gn:country_code":"CN",
    "gn:dem":262,
    "gn:feature_class":"P",
    "gn:feature_code":"PPL",
    "gn:name":"Lianqiu",
    "gn:population":0,
    "gn:timezone":"Asia/Shanghai",
    "iso:country":"CN",
    "name:zho_x_preferred":[
        "\u8fde\u4e18"
    ],
    "wof:name":"Lianqiu",
    "wof:placetype":"locality"
},
  "geometry": {"coordinates":[106.09972999999999,29.28325],"type":"Point"}
}