{
  "type": "Feature",
  "properties": {
    "gn:admin1_code":"14.0",
    "gn:asciiname":"Xiluo Niuchang",
    "gn:country_code":"CN",
    "gn:dem":3945,
    "gn:feature_class":"P",
    "gn:feature_code":"PPLF",
    "gn:name":"Xiluo Niuchang",
    "gn:population":0,
    "gn:timezone":"Asia/Urumqi",
    "iso:country":"CN",
    "name:zho_x_preferred":[
        "\u4e60\u6d1b\u725b\u573a"
    ],
    "wof:name":"Xiluo Niuchang",
    "wof:placetype":"locality"
},
  "geometry": {"coordinates":[98.39303,29.75172],"type":"Point"}
}