{
  "type": "Feature",
  "properties": {
    "gn:admin1_code":"32.0",
    "gn:asciiname":"Wuyi",
    "gn:country_code":"CN",
    "gn:dem":3127,
    "gn:feature_class":"P",
    "gn:feature_code":"PPL",
    "gn:name":"Wuyi",
    "gn:population":0,
    "gn:timezone":"Asia/Shanghai",
    "iso:country":"CN",
    "name:ceb_x_preferred":[
        "Wuyi"
    ],
    "name:deu_x_preferred":[
        "Wuyi"
    ],
    "name:fas_x_preferred":[
        "\u0648\u0648 \u06cc\u06cc"
    ],
    "name:fra_x_preferred":[
        "Wuyi"
    ],
    "name:kor_x_preferred":[
        "\uc6b0\uc774\ud604"
    ],
    "name:nor_x_preferred":[
        "Wuyi"
    ],
    "name:swe_x_preferred":[
        "Wuyi"
    ],
    "name:zho_x_preferred":[
        "\u543e\u4f0a"
    ],
    "wof:name":"Wuyi",
    "wof:placetype":"locality"
},
  "geometry": {"coordinates":[100.98205,32.07126],"type":"Point"}
}