{
  "type": "Feature",
  "properties": {
    "gn:admin1_code":"1.0",
    "gn:asciiname":"Xinshanhecun",
    "gn:country_code":"CN",
    "gn:dem":25,
    "gn:feature_class":"P",
    "gn:feature_code":"PPL",
    "gn:name":"Xinshanhecun",
    "gn:population":0,
    "gn:timezone":"Asia/Shanghai",
    "iso:country":"CN",
    "name:und_x_variant":[
        "Xinshanhe"
    ],
    "name:zho_x_preferred":[
        "\u65b0\u5c71\u6cb3\u6751"
    ],
    "wof:name":"Xinshanhecun",
    "wof:placetype":"locality"
},
  "geometry": {"coordinates":[116.99017000000001,33.07282],"type":"Point"}
}