{
  "type": "Feature",
  "properties": {
    "gn:admin1_code":"29.0",
    "gn:asciiname":"Shangyinajia",
    "gn:country_code":"CN",
    "gn:dem":1485,
    "gn:feature_class":"P",
    "gn:feature_code":"PPL",
    "gn:name":"Shangyinajia",
    "gn:population":0,
    "gn:timezone":"Asia/Shanghai",
    "iso:country":"CN",
    "name:zho_x_preferred":[
        "\u4e0a\u4ee5\u90a3\u621b"
    ],
    "wof:name":"Shangyinajia",
    "wof:placetype":"locality"
},
  "geometry": {"coordinates":[104.032,23.7542],"type":"Point"}
}