{
  "type": "Feature",
  "properties": {
    "gn:admin1_code":"19.0",
    "gn:asciiname":"Xinlituncun",
    "gn:country_code":"CN",
    "gn:dem":651,
    "gn:feature_class":"P",
    "gn:feature_code":"PPL",
    "gn:name":"Xinlituncun",
    "gn:population":0,
    "gn:timezone":"Asia/Shanghai",
    "iso:country":"CN",
    "name:zho_x_preferred":[
        "\u65b0\u7acb\u5c6f\u6751"
    ],
    "wof:name":"Xinlituncun",
    "wof:placetype":"locality"
},
  "geometry": {"coordinates":[119.77182000000001,42.07241],"type":"Point"}
}