{
  "type": "Feature",
  "properties": {
    "gn:admin1_code":"21.0",
    "gn:asciiname":"Erbukeng Dadui",
    "gn:country_code":"CN",
    "gn:dem":1465,
    "gn:feature_class":"P",
    "gn:feature_code":"PPLF",
    "gn:name":"Erbukeng Dadui",
    "gn:population":0,
    "gn:timezone":"Asia/Shanghai",
    "iso:country":"CN",
    "name:zho_x_preferred":[
        "\u4e8c\u6b65\u5751\u5927\u961f"
    ],
    "wof:name":"Erbukeng Dadui",
    "wof:placetype":"locality"
},
  "geometry": {"coordinates":[107.065,38.0818],"type":"Point"}
}