{
  "type": "Feature",
  "properties": {
    "gn:admin1_code":"5.0",
    "gn:asciiname":"Badaoling",
    "gn:country_code":"CN",
    "gn:dem":262,
    "gn:feature_class":"P",
    "gn:feature_code":"PPL",
    "gn:name":"Badaoling",
    "gn:population":0,
    "gn:timezone":"Asia/Shanghai",
    "iso:country":"CN",
    "name:zho_x_preferred":[
        "\u516b\u9053\u5cad"
    ],
    "wof:name":"Badaoling",
    "wof:placetype":"locality"
},
  "geometry": {"coordinates":[127.0218,44.28018],"type":"Point"}
}