{
  "type": "Feature",
  "properties": {
    "gn:admin1_code":"12.0",
    "gn:asciiname":"Yejiaya",
    "gn:country_code":"CN",
    "gn:dem":811,
    "gn:feature_class":"P",
    "gn:feature_code":"PPL",
    "gn:name":"Yejiaya",
    "gn:population":0,
    "gn:timezone":"Asia/Shanghai",
    "iso:country":"CN",
    "name:zho_x_preferred":[
        "\u53f6\u5bb6\u57ad"
    ],
    "wof:name":"Yejiaya",
    "wof:placetype":"locality"
},
  "geometry": {"coordinates":[111.04819999999999,32.41704],"type":"Point"}
}