{
  "type": "Feature",
  "properties": {
    "gn:admin1_code":"14.0",
    "gn:asciiname":"Xisuomugunba",
    "gn:country_code":"CN",
    "gn:dem":4629,
    "gn:feature_class":"P",
    "gn:feature_code":"PPL",
    "gn:name":"Xisuomugunba",
    "gn:population":0,
    "gn:timezone":"Asia/Urumqi",
    "iso:country":"CN",
    "name:zho_x_preferred":[
        "\u897f\u7d22\u6728\u68cd\u5df4"
    ],
    "wof:name":"Xisuomugunba",
    "wof:placetype":"locality"
},
  "geometry": {"coordinates":[86.5264,29.4863],"type":"Point"}
}