{
  "type": "Feature",
  "properties": {
    "gn:admin1_code":"07",
    "gn:asciiname":"Jiazike",
    "gn:country_code":"CN",
    "gn:dem":247,
    "gn:feature_class":"P",
    "gn:feature_code":"PPL",
    "gn:name":"Jiazike",
    "gn:population":0,
    "gn:timezone":"Asia/Shanghai",
    "iso:country":"CN",
    "name:zho_x_preferred":[
        "\u7532\u5b50\u7aa0"
    ],
    "wof:name":"Jiazike",
    "wof:placetype":"locality"
},
  "geometry": {"coordinates":[117.26287000000001,25.87935],"type":"Point"}
}