{
  "type": "Feature",
  "properties": {
    "gn:admin1_code":"3.0",
    "gn:asciiname":"Xiajia Ping",
    "gn:country_code":"CN",
    "gn:dem":46,
    "gn:feature_class":"P",
    "gn:feature_code":"PPL",
    "gn:name":"Xiajia Ping",
    "gn:population":0,
    "gn:timezone":"Asia/Shanghai",
    "iso:country":"CN",
    "name:und_x_variant":[
        "\u4e0b\u5bb6\u576a"
    ],
    "wof:name":"Xiajia Ping",
    "wof:placetype":"locality"
},
  "geometry": {"coordinates":[116.74646,28.2982],"type":"Point"}
}