{
  "type": "Feature",
  "properties": {
    "gn:admin1_code":"18",
    "gn:asciiname":"Shiqiang Yuanzi",
    "gn:country_code":"CN",
    "gn:dem":2193,
    "gn:feature_class":"P",
    "gn:feature_code":"PPL",
    "gn:name":"Shiqiang Yuanzi",
    "gn:population":0,
    "gn:timezone":"Asia/Shanghai",
    "iso:country":"CN",
    "name:zho_x_preferred":[
        "\u77f3\u5899\u9662\u5b50"
    ],
    "wof:name":"Shiqiang Yuanzi",
    "wof:placetype":"locality"
},
  "geometry": {"coordinates":[104.352,26.9493],"type":"Point"}
}