{
  "type": "Feature",
  "properties": {
    "gn:admin1_code":"30.0",
    "gn:asciiname":"Chaigougeng",
    "gn:country_code":"CN",
    "gn:dem":342,
    "gn:feature_class":"P",
    "gn:feature_code":"PPL",
    "gn:name":"Chaigougeng",
    "gn:population":0,
    "gn:timezone":"Asia/Shanghai",
    "iso:country":"CN",
    "name:zho_x_preferred":[
        "\u8c7a\u72d7\u57c2"
    ],
    "wof:name":"Chaigougeng",
    "wof:placetype":"locality"
},
  "geometry": {"coordinates":[113.35252,23.8715],"type":"Point"}
}