{
  "type": "Feature",
  "properties": {
    "gn:admin1_code":"8.0",
    "gn:asciiname":"Xingsheng",
    "gn:country_code":"CN",
    "gn:dem":178,
    "gn:feature_class":"P",
    "gn:feature_code":"PPL",
    "gn:name":"Xingsheng",
    "gn:population":0,
    "gn:timezone":"Asia/Shanghai",
    "iso:country":"CN",
    "name:zho_x_preferred":[
        "\u5174\u80dc"
    ],
    "wof:name":"Xingsheng",
    "wof:placetype":"locality"
},
  "geometry": {"coordinates":[123.32358000000001,47.6734],"type":"Point"}
}