{
  "type": "Feature",
  "properties": {
    "gn:admin1_code":"29",
    "gn:asciiname":"Xiaozhangguo",
    "gn:country_code":"CN",
    "gn:dem":1477,
    "gn:feature_class":"P",
    "gn:feature_code":"PPL",
    "gn:name":"Xiaozhangguo",
    "gn:population":0,
    "gn:timezone":"Asia/Shanghai",
    "iso:country":"CN",
    "name:zho_x_preferred":[
        "\u5c0f\u4e08\u679c"
    ],
    "wof:name":"Xiaozhangguo",
    "wof:placetype":"locality"
},
  "geometry": {"coordinates":[104.95699999999999,23.6399],"type":"Point"}
}