{
  "type": "Feature",
  "properties": {
    "gn:admin1_code":"25",
    "gn:asciiname":"Shanhoucaojia",
    "gn:country_code":"CN",
    "gn:dem":110,
    "gn:feature_class":"P",
    "gn:feature_code":"PPL",
    "gn:name":"Shanhoucaojia",
    "gn:population":0,
    "gn:timezone":"Asia/Shanghai",
    "iso:country":"CN",
    "name:zho_x_preferred":[
        "\u5c71\u540e\u66f9\u5bb6"
    ],
    "wof:name":"Shanhoucaojia",
    "wof:placetype":"locality"
},
  "geometry": {"coordinates":[120.708,37.5896],"type":"Point"}
}