{
  "type": "Feature",
  "properties": {
    "gn:admin1_code":"11.0",
    "gn:asciiname":"Maoli'an",
    "gn:country_code":"CN",
    "gn:dem":733,
    "gn:feature_class":"P",
    "gn:feature_code":"PPL",
    "gn:name":"Maoli\u2019an",
    "gn:population":0,
    "gn:timezone":"Asia/Shanghai",
    "iso:country":"CN",
    "name:und_x_variant":[
        "Maoli\u2019an"
    ],
    "name:zho_x_preferred":[
        "\u8305\u91cc\u5b89"
    ],
    "wof:name":"Maoli'an",
    "wof:placetype":"locality"
},
  "geometry": {"coordinates":[110.53131999999999,27.71309],"type":"Point"}
}