{
  "type": "Feature",
  "properties": {
    "gn:admin1_code":"15.0",
    "gn:asciiname":"Zaoshuping",
    "gn:country_code":"CN",
    "gn:dem":1357,
    "gn:feature_class":"P",
    "gn:feature_code":"PPL",
    "gn:name":"Zaoshuping",
    "gn:population":0,
    "gn:timezone":"Asia/Shanghai",
    "iso:country":"CN",
    "name:und_x_variant":[
        "\u67a3\u6811\u576a"
    ],
    "wof:name":"Zaoshuping",
    "wof:placetype":"locality"
},
  "geometry": {"coordinates":[107.93008,36.41216],"type":"Point"}
}