{
  "type": "Feature",
  "properties": {
    "gn:admin1_code":"32.0",
    "gn:asciiname":"Paotongwan",
    "gn:country_code":"CN",
    "gn:dem":328,
    "gn:feature_class":"P",
    "gn:feature_code":"PPL",
    "gn:name":"Paotongwan",
    "gn:population":0,
    "gn:timezone":"Asia/Shanghai",
    "iso:country":"CN",
    "name:zho_x_preferred":[
        "\u6ce1\u6850\u6e7e"
    ],
    "wof:name":"Paotongwan",
    "wof:placetype":"locality"
},
  "geometry": {"coordinates":[105.26314000000001,28.37275],"type":"Point"}
}