{
  "type": "Feature",
  "properties": {
    "gn:admin1_code":"32.0",
    "gn:asciiname":"Luobugou",
    "gn:country_code":"CN",
    "gn:dem":2703,
    "gn:feature_class":"P",
    "gn:feature_code":"PPL",
    "gn:name":"Luobugou",
    "gn:population":0,
    "gn:timezone":"Asia/Shanghai",
    "iso:country":"CN",
    "name:zho_x_preferred":[
        "\u841d\u535c\u6c9f"
    ],
    "wof:name":"Luobugou",
    "wof:placetype":"locality"
},
  "geometry": {"coordinates":[103.751,32.1286],"type":"Point"}
}