{
  "type": "Feature",
  "properties": {
    "gn:admin1_code":"22",
    "gn:asciiname":"Laba Goumen",
    "gn:country_code":"CN",
    "gn:dem":466,
    "gn:feature_class":"P",
    "gn:feature_code":"PPLA4",
    "gn:name":"Laba Goumen",
    "gn:population":0,
    "gn:timezone":"Asia/Shanghai",
    "iso:country":"CN",
    "name:und_x_variant":[
        "La-pa-kou-men",
        "Laba Goumen",
        "Laba Goumen Manzuxiang"
    ],
    "name:zho_x_preferred":[
        "\u5587\u53ed\u6c9f\u95e8"
    ],
    "name:zho_x_variant":[
        "\u5587\u53ed\u6c9f\u95e8\u6ee1\u65cf\u4e61"
    ],
    "wof:name":"Laba Goumen",
    "wof:placetype":"locality"
},
  "geometry": {"coordinates":[116.61633999999999,40.8978],"type":"Point"}
}