{
  "type": "Feature",
  "properties": {
    "gn:admin1_code":"18",
    "gn:asciiname":"Guanyinsi",
    "gn:country_code":"CN",
    "gn:dem":368,
    "gn:feature_class":"P",
    "gn:feature_code":"PPL",
    "gn:name":"Guanyinsi",
    "gn:population":0,
    "gn:timezone":"Asia/Shanghai",
    "iso:country":"CN",
    "name:zho_x_preferred":[
        "\u89c2\u97f3\u5bfa"
    ],
    "wof:name":"Guanyinsi",
    "wof:placetype":"locality"
},
  "geometry": {"coordinates":[105.785,28.5504],"type":"Point"}
}