{
  "type": "Feature",
  "properties": {
    "gn:admin1_code":"30.0",
    "gn:asciiname":"deng zhan hu",
    "gn:country_code":"CN",
    "gn:dem":5,
    "gn:feature_class":"P",
    "gn:feature_code":"PPL",
    "gn:name":"\u706f\u76cf\u6e56",
    "gn:population":0,
    "gn:timezone":"Asia/Shanghai",
    "iso:country":"CN",
    "name:und_x_variant":[
        "\u706f\u76cf\u6e56"
    ],
    "name:zho_x_preferred":[
        "\u4e1c\u6e7e"
    ],
    "wof:name":"deng zhan hu",
    "wof:placetype":"locality"
},
  "geometry": {"coordinates":[113.01322999999999,22.66836],"type":"Point"}
}