{
  "type": "Feature",
  "properties": {
    "gn:admin1_code":"12.0",
    "gn:asciiname":"Luohetang",
    "gn:country_code":"CN",
    "gn:dem":91,
    "gn:feature_class":"P",
    "gn:feature_code":"PPL",
    "gn:name":"Luohetang",
    "gn:population":0,
    "gn:timezone":"Asia/Shanghai",
    "iso:country":"CN",
    "name:zho_x_preferred":[
        "Luohetang"
    ],
    "name:zho_x_variant":[
        "\u7f57\u5408\u5858"
    ],
    "wof:name":"Luohetang",
    "wof:placetype":"locality"
},
  "geometry": {"coordinates":[115.14643999999998,30.80084],"type":"Point"}
}