{
  "type": "Feature",
  "properties": {
    "gn:admin1_code":"18",
    "gn:asciiname":"Shitouhe",
    "gn:country_code":"CN",
    "gn:dem":1773,
    "gn:feature_class":"P",
    "gn:feature_code":"PPL",
    "gn:name":"Shitouhe",
    "gn:population":0,
    "gn:timezone":"Asia/Shanghai",
    "iso:country":"CN",
    "name:zho_x_preferred":[
        "\u77f3\u5934\u6cb3"
    ],
    "wof:name":"Shitouhe",
    "wof:placetype":"locality"
},
  "geometry": {"coordinates":[104.739,25.9227],"type":"Point"}
}