{
  "type": "Feature",
  "properties": {
    "gn:admin1_code":"29.0",
    "gn:asciiname":"Tangpo",
    "gn:country_code":"CN",
    "gn:dem":3425,
    "gn:feature_class":"P",
    "gn:feature_code":"PPL",
    "gn:name":"Tangpo",
    "gn:population":0,
    "gn:timezone":"Asia/Shanghai",
    "iso:country":"CN",
    "name:zho_x_preferred":[
        "\u5510\u5761"
    ],
    "wof:name":"Tangpo",
    "wof:placetype":"locality"
},
  "geometry": {"coordinates":[99.8446,27.807],"type":"Point"}
}