{
  "type": "Feature",
  "properties": {
    "gn:admin1_code":"30",
    "gn:asciiname":"Jishan Nongchang",
    "gn:country_code":"CN",
    "gn:dem":37,
    "gn:feature_class":"P",
    "gn:feature_code":"PPLF",
    "gn:name":"Jishan Nongchang",
    "gn:population":0,
    "gn:timezone":"Asia/Shanghai",
    "iso:country":"CN",
    "name:zho_x_preferred":[
        "\u9e21\u5c71\u519c\u573a"
    ],
    "wof:name":"Jishan Nongchang",
    "wof:placetype":"locality"
},
  "geometry": {"coordinates":[112.23657,21.91354],"type":"Point"}
}