{
  "type": "Feature",
  "properties": {
    "gn:admin1_code":"11.0",
    "gn:asciiname":"Runianchong",
    "gn:country_code":"CN",
    "gn:dem":278,
    "gn:feature_class":"P",
    "gn:feature_code":"PPL",
    "gn:name":"Runianchong",
    "gn:population":0,
    "gn:timezone":"Asia/Shanghai",
    "iso:country":"CN",
    "name:zho_x_preferred":[
        "\u5982\u5e74\u51b2"
    ],
    "wof:name":"Runianchong",
    "wof:placetype":"locality"
},
  "geometry": {"coordinates":[111.90251000000001,26.94873],"type":"Point"}
}