{
  "type": "Feature",
  "properties": {
    "gn:admin1_code":"10",
    "gn:asciiname":"Beixiaoying",
    "gn:country_code":"CN",
    "gn:dem":17,
    "gn:feature_class":"P",
    "gn:feature_code":"PPL",
    "gn:name":"Beixiaoying",
    "gn:population":0,
    "gn:timezone":"Asia/Shanghai",
    "iso:country":"CN",
    "name:zho_x_preferred":[
        "\u5317\u5c0f\u8425"
    ],
    "wof:name":"Beixiaoying",
    "wof:placetype":"locality"
},
  "geometry": {"coordinates":[116.69228,39.47282],"type":"Point"}
}