{
  "type": "Feature",
  "properties": {
    "gn:admin1_code":"19.0",
    "gn:asciiname":"Fanjiagou",
    "gn:country_code":"CN",
    "gn:dem":302,
    "gn:feature_class":"P",
    "gn:feature_code":"PPL",
    "gn:name":"Fanjiagou",
    "gn:population":0,
    "gn:timezone":"Asia/Shanghai",
    "iso:country":"CN",
    "name:und_x_variant":[
        "\u6a0a\u5bb6\u6c9f"
    ],
    "wof:name":"Fanjiagou",
    "wof:placetype":"locality"
},
  "geometry": {"coordinates":[123.86903999999998,40.76116],"type":"Point"}
}