{
  "type": "Feature",
  "properties": {
    "gn:admin1_code":"12.0",
    "gn:asciiname":"Guantangzhao",
    "gn:country_code":"CN",
    "gn:dem":54,
    "gn:feature_class":"P",
    "gn:feature_code":"PPL",
    "gn:name":"Guantangzhao",
    "gn:population":0,
    "gn:timezone":"Asia/Shanghai",
    "iso:country":"CN",
    "name:zho_x_preferred":[
        "\u5b98\u5858\u8d75"
    ],
    "wof:name":"Guantangzhao",
    "wof:placetype":"locality"
},
  "geometry": {"coordinates":[114.72726000000002,30.99659],"type":"Point"}
}