{
  "type": "Feature",
  "properties": {
    "gn:admin1_code":"19.0",
    "gn:asciiname":"Jixianggoucun",
    "gn:country_code":"CN",
    "gn:dem":377,
    "gn:feature_class":"P",
    "gn:feature_code":"PPL",
    "gn:name":"Jixianggoucun",
    "gn:population":0,
    "gn:timezone":"Asia/Shanghai",
    "iso:country":"CN",
    "name:zho_x_preferred":[
        "\u5409\u7965\u6c9f\u6751"
    ],
    "wof:name":"Jixianggoucun",
    "wof:placetype":"locality"
},
  "geometry": {"coordinates":[120.67164,42.05837],"type":"Point"}
}