{
  "type": "Feature",
  "properties": {
    "gn:admin1_code":"14.0",
    "gn:asciiname":"Juede",
    "gn:country_code":"CN",
    "gn:dem":4011,
    "gn:feature_class":"P",
    "gn:feature_code":"PPL",
    "gn:name":"Juede",
    "gn:population":0,
    "gn:timezone":"Asia/Urumqi",
    "iso:country":"CN",
    "name:zho_x_preferred":[
        "\u89c9\u5fb7"
    ],
    "wof:name":"Juede",
    "wof:placetype":"locality"
},
  "geometry": {"coordinates":[97.58477999999999,29.63725],"type":"Point"}
}