{
  "type": "Feature",
  "properties": {
    "gn:admin1_code":"2.0",
    "gn:asciiname":"Zhimu",
    "gn:country_code":"CN",
    "gn:dem":692,
    "gn:feature_class":"P",
    "gn:feature_code":"PPL",
    "gn:name":"Zhimu",
    "gn:population":0,
    "gn:timezone":"Asia/Shanghai",
    "iso:country":"CN",
    "name:zho_x_preferred":[
        "\u652f\u6728"
    ],
    "wof:name":"Zhimu",
    "wof:placetype":"locality"
},
  "geometry": {"coordinates":[119.27743999999998,28.38746],"type":"Point"}
}