{
  "type": "Feature",
  "properties": {
    "gn:admin1_code":"12.0",
    "gn:asciiname":"Shanghuang Jinkou",
    "gn:country_code":"CN",
    "gn:dem":21,
    "gn:feature_class":"P",
    "gn:feature_code":"PPL",
    "gn:name":"Shanghuang Jinkou",
    "gn:population":0,
    "gn:timezone":"Asia/Shanghai",
    "iso:country":"CN",
    "name:und_x_variant":[
        "\u4e0a\u9ec4\u91d1\u53e3"
    ],
    "wof:name":"Shanghuang Jinkou",
    "wof:placetype":"locality"
},
  "geometry": {"coordinates":[114.15873000000001,30.59407],"type":"Point"}
}