{
  "type": "Feature",
  "properties": {
    "gn:admin1_code":"18.0",
    "gn:asciiname":"Xiaopaijia",
    "gn:country_code":"CN",
    "gn:dem":854,
    "gn:feature_class":"P",
    "gn:feature_code":"PPL",
    "gn:name":"Xiaopaijia",
    "gn:population":0,
    "gn:timezone":"Asia/Shanghai",
    "iso:country":"CN",
    "name:zho_x_preferred":[
        "\u5c0f\u6392\u7532"
    ],
    "wof:name":"Xiaopaijia",
    "wof:placetype":"locality"
},
  "geometry": {"coordinates":[107.85899999999999,26.2307],"type":"Point"}
}