{
  "type": "Feature",
  "properties": {
    "gn:admin1_code":"2.0",
    "gn:asciiname":"Yanxi",
    "gn:country_code":"CN",
    "gn:dem":183,
    "gn:feature_class":"P",
    "gn:feature_code":"PPL",
    "gn:name":"Yanxi",
    "gn:population":0,
    "gn:timezone":"Asia/Shanghai",
    "iso:country":"CN",
    "name:ceb_x_preferred":[
        "Yanxi"
    ],
    "name:deu_x_preferred":[
        "Yanxi"
    ],
    "name:swe_x_preferred":[
        "Yanxi"
    ],
    "name:zho_x_preferred":[
        "\u5ca9\u897f"
    ],
    "wof:name":"Yanxi",
    "wof:placetype":"locality"
},
  "geometry": {"coordinates":[119.47117,28.40533],"type":"Point"}
}