{
  "type": "Feature",
  "properties": {
    "gn:admin1_code":"16.0",
    "gn:asciiname":"Antang",
    "gn:country_code":"CN",
    "gn:dem":283,
    "gn:feature_class":"P",
    "gn:feature_code":"PPL",
    "gn:name":"Antang",
    "gn:population":0,
    "gn:timezone":"Asia/Shanghai",
    "iso:country":"CN",
    "name:zho_x_preferred":[
        "\u5b89\u5858"
    ],
    "wof:name":"Antang",
    "wof:placetype":"locality"
},
  "geometry": {"coordinates":[108.447,23.5713],"type":"Point"}
}