{
  "type": "Feature",
  "properties": {
    "gn:admin1_code":"4.0",
    "gn:asciiname":"Xiaoshanzicun",
    "gn:country_code":"CN",
    "gn:dem":30,
    "gn:feature_class":"P",
    "gn:feature_code":"PPL",
    "gn:name":"Xiaoshanzicun",
    "gn:population":0,
    "gn:timezone":"Asia/Shanghai",
    "iso:country":"CN",
    "name:zho_x_preferred":[
        "\u5c0f\u5c71\u5b50\u6751"
    ],
    "wof:name":"Xiaoshanzicun",
    "wof:placetype":"locality"
},
  "geometry": {"coordinates":[117.52472,34.39447],"type":"Point"}
}