{
  "type": "Feature",
  "properties": {
    "gn:admin1_code":"15.0",
    "gn:asciiname":"Honghua Yuanzi",
    "gn:country_code":"CN",
    "gn:dem":1306,
    "gn:feature_class":"P",
    "gn:feature_code":"PPL",
    "gn:name":"Honghua Yuanzi",
    "gn:population":0,
    "gn:timezone":"Asia/Shanghai",
    "iso:country":"CN",
    "name:zho_x_preferred":[
        "\u7ea2\u82b1\u56ed\u5b50"
    ],
    "wof:name":"Honghua Yuanzi",
    "wof:placetype":"locality"
},
  "geometry": {"coordinates":[107.161,35.7541],"type":"Point"}
}