{
  "type": "Feature",
  "properties": {
    "gn:admin1_code":"16",
    "gn:asciiname":"Shangdatang",
    "gn:country_code":"CN",
    "gn:dem":702,
    "gn:feature_class":"P",
    "gn:feature_code":"PPL",
    "gn:name":"Shangdatang",
    "gn:population":0,
    "gn:timezone":"Asia/Shanghai",
    "iso:country":"CN",
    "name:zho_x_preferred":[
        "\u4e0a\u5927\u5858"
    ],
    "wof:name":"Shangdatang",
    "wof:placetype":"locality"
},
  "geometry": {"coordinates":[110.07899999999999,25.8076],"type":"Point"}
}