{
  "type": "Feature",
  "properties": {
    "gn:admin1_code":"4.0",
    "gn:asciiname":"Sundun",
    "gn:country_code":"CN",
    "gn:dem":1,
    "gn:feature_class":"P",
    "gn:feature_code":"PPL",
    "gn:name":"Sundun",
    "gn:population":0,
    "gn:timezone":"Asia/Shanghai",
    "iso:country":"CN",
    "name:zho_x_preferred":[
        "Sundun"
    ],
    "name:zho_x_variant":[
        "\u5b59\u58a9"
    ],
    "wof:name":"Sundun",
    "wof:placetype":"locality"
},
  "geometry": {"coordinates":[119.80118,33.64429000000001],"type":"Point"}
}