{
  "type": "Feature",
  "properties": {
    "gn:admin1_code":"26.0",
    "gn:asciiname":"Erbagou",
    "gn:country_code":"CN",
    "gn:dem":1199,
    "gn:feature_class":"P",
    "gn:feature_code":"PPL",
    "gn:name":"Erbagou",
    "gn:population":0,
    "gn:timezone":"Asia/Shanghai",
    "iso:country":"CN",
    "name:und_x_variant":[
        "\u8033\u6252\u6c9f"
    ],
    "wof:name":"Erbagou",
    "wof:placetype":"locality"
},
  "geometry": {"coordinates":[108.03312,33.51515999999999],"type":"Point"}
}