{
  "type": "Feature",
  "properties": {
    "gn:admin1_code":"24",
    "gn:asciiname":"Ducun",
    "gn:cc2":"CN",
    "gn:country_code":"CN",
    "gn:dem":1130,
    "gn:feature_class":"P",
    "gn:feature_code":"PPL",
    "gn:name":"Ducun",
    "gn:population":0,
    "gn:timezone":"Asia/Shanghai",
    "iso:country":"CN",
    "name:ceb_x_preferred":[
        "Ducun"
    ],
    "name:swe_x_preferred":[
        "Ducun"
    ],
    "name:und_x_variant":[
        "Tu-ts\u2019un"
    ],
    "wof:name":"Ducun",
    "wof:placetype":"locality"
},
  "geometry": {"coordinates":[111.52249999999999,37.22278],"type":"Point"}
}