{
  "type": "Feature",
  "properties": {
    "gn:admin1_code":"4.0",
    "gn:asciiname":"Qiandushan",
    "gn:country_code":"CN",
    "gn:dem":10,
    "gn:feature_class":"P",
    "gn:feature_code":"PPL",
    "gn:name":"Qiandushan",
    "gn:population":0,
    "gn:timezone":"Asia/Shanghai",
    "iso:country":"CN",
    "name:zho_x_preferred":[
        "\u524d\u6e21\u5584"
    ],
    "wof:name":"Qiandushan",
    "wof:placetype":"locality"
},
  "geometry": {"coordinates":[119.80267000000001,32.01377],"type":"Point"}
}