{
  "type": "Feature",
  "properties": {
    "gn:admin1_code":"6.0",
    "gn:asciiname":"Guowenge",
    "gn:country_code":"CN",
    "gn:dem":3727,
    "gn:feature_class":"P",
    "gn:feature_code":"PPL",
    "gn:name":"Guowenge",
    "gn:population":0,
    "gn:timezone":"Asia/Urumqi",
    "iso:country":"CN",
    "name:zho_x_preferred":[
        "\u679c\u6587\u683c"
    ],
    "wof:name":"Guowenge",
    "wof:placetype":"locality"
},
  "geometry": {"coordinates":[97.26606,32.1335],"type":"Point"}
}