{
  "type": "Feature",
  "properties": {
    "gn:admin1_code":"15.0",
    "gn:asciiname":"Jicangguo",
    "gn:country_code":"CN",
    "gn:dem":3059,
    "gn:feature_class":"P",
    "gn:feature_code":"PPL",
    "gn:name":"Jicangguo",
    "gn:population":0,
    "gn:timezone":"Asia/Shanghai",
    "iso:country":"CN",
    "name:zho_x_preferred":[
        "\u5409\u4ed3\u679c"
    ],
    "wof:name":"Jicangguo",
    "wof:placetype":"locality"
},
  "geometry": {"coordinates":[102.83799999999999,34.6104],"type":"Point"}
}