{
  "type": "Feature",
  "properties": {
    "gn:admin1_code":"3.0",
    "gn:asciiname":"Zhushan",
    "gn:country_code":"CN",
    "gn:dem":540,
    "gn:feature_class":"P",
    "gn:feature_code":"PPL",
    "gn:name":"Zhushan",
    "gn:population":0,
    "gn:timezone":"Asia/Shanghai",
    "iso:country":"CN",
    "name:ceb_x_preferred":[
        "Zhushan"
    ],
    "name:deu_x_preferred":[
        "Zhushan"
    ],
    "name:fra_x_preferred":[
        "Zhushan"
    ],
    "name:nor_x_preferred":[
        "Zhushan"
    ],
    "name:swe_x_preferred":[
        "Zhushan"
    ],
    "name:und_x_variant":[
        "\u6731\u5c71"
    ],
    "wof:name":"Zhushan",
    "wof:placetype":"locality"
},
  "geometry": {"coordinates":[117.83768000000001,29.5255],"type":"Point"}
}