{
  "type": "Feature",
  "properties": {
    "gn:admin1_code":"8.0",
    "gn:asciiname":"Daqingshancun",
    "gn:country_code":"CN",
    "gn:dem":347,
    "gn:feature_class":"P",
    "gn:feature_code":"PPL",
    "gn:name":"Daqingshancun",
    "gn:population":0,
    "gn:timezone":"Asia/Shanghai",
    "iso:country":"CN",
    "name:zho_x_preferred":[
        "\u5927\u9752\u5c71\u6751"
    ],
    "wof:name":"Daqingshancun",
    "wof:placetype":"locality"
},
  "geometry": {"coordinates":[128.48974999999999,44.79397],"type":"Point"}
}