{
  "type": "Feature",
  "properties": {
    "gn:admin1_code":"25.0",
    "gn:asciiname":"Tianjiayaocun",
    "gn:country_code":"CN",
    "gn:dem":14,
    "gn:feature_class":"P",
    "gn:feature_code":"PPL",
    "gn:name":"Tianjiayaocun",
    "gn:population":0,
    "gn:timezone":"Asia/Shanghai",
    "iso:country":"CN",
    "name:zho_x_preferred":[
        "\u7530\u5bb6\u7a91\u6751"
    ],
    "wof:name":"Tianjiayaocun",
    "wof:placetype":"locality"
},
  "geometry": {"coordinates":[120.0204,36.09362],"type":"Point"}
}