{
  "type": "Feature",
  "properties": {
    "gn:admin1_code":"30.0",
    "gn:asciiname":"Xindong",
    "gn:country_code":"CN",
    "gn:dem":422,
    "gn:feature_class":"P",
    "gn:feature_code":"PPL",
    "gn:name":"Xindong",
    "gn:population":0,
    "gn:timezone":"Asia/Shanghai",
    "iso:country":"CN",
    "name:zho_x_preferred":[
        "Xindong"
    ],
    "name:zho_x_variant":[
        "\u65b0\u5cd2"
    ],
    "wof:name":"Xindong",
    "wof:placetype":"locality"
},
  "geometry": {"coordinates":[114.03910999999999,24.14554],"type":"Point"}
}