{
  "type": "Feature",
  "properties": {
    "gn:admin1_code":"29.0",
    "gn:asciiname":"Dachezhang",
    "gn:country_code":"CN",
    "gn:dem":1939,
    "gn:feature_class":"P",
    "gn:feature_code":"PPL",
    "gn:name":"Dachezhang",
    "gn:population":0,
    "gn:timezone":"Asia/Shanghai",
    "iso:country":"CN",
    "name:zho_x_preferred":[
        "\u5927\u8f66\u7ae0"
    ],
    "wof:name":"Dachezhang",
    "wof:placetype":"locality"
},
  "geometry": {"coordinates":[103.44799999999999,25.4548],"type":"Point"}
}