{
  "type": "Feature",
  "properties": {
    "gn:admin1_code":"31",
    "gn:asciiname":"Limushan Caifachang Sanxingjian Zuoyequ",
    "gn:country_code":"CN",
    "gn:dem":674,
    "gn:feature_class":"P",
    "gn:feature_code":"PPLF",
    "gn:name":"Limushan Caifachang Sanxingjian Zuoyequ",
    "gn:population":0,
    "gn:timezone":"Asia/Shanghai",
    "iso:country":"CN",
    "name:und_x_variant":[
        "\u9ece\u6bcd\u5c71\u91c7\u4f10\u573a\u4e09\u661f\u5c16\u4f5c\u4e1a\u533a",
        "Sifenqu",
        "\u56db\u5206\u533a"
    ],
    "wof:name":"Limushan Caifachang Sanxingjian Zuoyequ",
    "wof:placetype":"locality"
},
  "geometry": {"coordinates":[109.71608000000001,19.17195],"type":"Point"}
}