{
  "type": "Feature",
  "properties": {
    "gn:admin1_code":"11.0",
    "gn:asciiname":"Lingguan Miaoqian",
    "gn:country_code":"CN",
    "gn:dem":224,
    "gn:feature_class":"P",
    "gn:feature_code":"PPL",
    "gn:name":"Lingguan Miaoqian",
    "gn:population":0,
    "gn:timezone":"Asia/Shanghai",
    "iso:country":"CN",
    "name:zho_x_preferred":[
        "\u7075\u5b98\u5e99\u524d"
    ],
    "wof:name":"Lingguan Miaoqian",
    "wof:placetype":"locality"
},
  "geometry": {"coordinates":[113.63275,27.27598],"type":"Point"}
}