{
  "type": "Feature",
  "properties": {
    "gn:admin1_code":"4.0",
    "gn:asciiname":"Gaoqiaocun",
    "gn:country_code":"CN",
    "gn:dem":1,
    "gn:feature_class":"P",
    "gn:feature_code":"PPL",
    "gn:name":"Gaoqiaocun",
    "gn:population":0,
    "gn:timezone":"Asia/Shanghai",
    "iso:country":"CN",
    "name:zho_x_preferred":[
        "\u9ad8\u6865\u6751"
    ],
    "wof:name":"Gaoqiaocun",
    "wof:placetype":"locality"
},
  "geometry": {"coordinates":[119.82752000000001,33.45227],"type":"Point"}
}