{
  "type": "Feature",
  "properties": {
    "gn:admin1_code":"4.0",
    "gn:asciiname":"Dahehuachen",
    "gn:country_code":"CN",
    "gn:dem":48,
    "gn:feature_class":"P",
    "gn:feature_code":"PPL",
    "gn:name":"Dahehuachen",
    "gn:population":0,
    "gn:timezone":"Asia/Shanghai",
    "iso:country":"CN",
    "name:zho_x_preferred":[
        "\u5927\u8377\u82b1\u9648"
    ],
    "wof:name":"Dahehuachen",
    "wof:placetype":"locality"
},
  "geometry": {"coordinates":[118.78698,32.44999],"type":"Point"}
}