{
  "type": "Feature",
  "properties": {
    "gn:admin1_code":"3.0",
    "gn:asciiname":"Shipingshang",
    "gn:country_code":"CN",
    "gn:dem":318,
    "gn:feature_class":"P",
    "gn:feature_code":"PPL",
    "gn:name":"Shipingshang",
    "gn:population":0,
    "gn:timezone":"Asia/Shanghai",
    "iso:country":"CN",
    "name:und_x_variant":[
        "\u77f3\u576a\u4e0a"
    ],
    "wof:name":"Shipingshang",
    "wof:placetype":"locality"
},
  "geometry": {"coordinates":[116.29627000000001,26.45596],"type":"Point"}
}