{
  "type": "Feature",
  "properties": {
    "gn:admin1_code":"9",
    "gn:asciiname":"Lingbao Yuanyichang",
    "gn:country_code":"CN",
    "gn:dem":920,
    "gn:feature_class":"P",
    "gn:feature_code":"PPLF",
    "gn:name":"Lingbao Yuanyichang",
    "gn:population":0,
    "gn:timezone":"Asia/Shanghai",
    "iso:country":"CN",
    "wof:name":"Lingbao Yuanyichang",
    "wof:placetype":"locality"
},
  "geometry": {"coordinates":[111.03361,34.43972],"type":"Point"}
}