{
  "type": "Feature",
  "properties": {
    "gn:admin1_code":"16.0",
    "gn:asciiname":"Wangzhoucheng",
    "gn:country_code":"CN",
    "gn:dem":55,
    "gn:feature_class":"P",
    "gn:feature_code":"PPL",
    "gn:name":"Wangzhoucheng",
    "gn:population":0,
    "gn:timezone":"Asia/Shanghai",
    "iso:country":"CN",
    "name:zho_x_preferred":[
        "\u671b\u5dde\u57ce"
    ],
    "wof:name":"Wangzhoucheng",
    "wof:placetype":"locality"
},
  "geometry": {"coordinates":[109.032,22.1469],"type":"Point"}
}