{
  "type": "Feature",
  "properties": {
    "gn:admin1_code":"11",
    "gn:asciiname":"Zhaiyang",
    "gn:country_code":"CN",
    "gn:dem":230,
    "gn:feature_class":"P",
    "gn:feature_code":"PPLA4",
    "gn:name":"Zhaiyang",
    "gn:population":0,
    "gn:timezone":"Asia/Shanghai",
    "iso:country":"CN",
    "name:und_x_variant":[
        "Zhaiyang Xiang"
    ],
    "name:zho_x_preferred":[
        "\u5be8\u9633"
    ],
    "name:zho_x_variant":[
        "\u5be8\u9633\u4e61"
    ],
    "wof:name":"Zhaiyang",
    "wof:placetype":"locality"
},
  "geometry": {"coordinates":[109.65269000000001,28.30988],"type":"Point"}
}