{
  "type": "Feature",
  "properties": {
    "gn:admin1_code":"10",
    "gn:asciiname":"Houshuiquanyingzi",
    "gn:country_code":"CN",
    "gn:dem":1398,
    "gn:feature_class":"P",
    "gn:feature_code":"PPL",
    "gn:name":"Houshuiquanyingzi",
    "gn:population":0,
    "gn:timezone":"Asia/Shanghai",
    "iso:country":"CN",
    "wof:name":"Houshuiquanyingzi",
    "wof:placetype":"locality"
},
  "geometry": {"coordinates":[115.73888999999998,41.77722],"type":"Point"}
}