{
  "type": "Feature",
  "properties": {
    "gn:admin1_code":"2.0",
    "gn:asciiname":"Lingkou",
    "gn:country_code":"CN",
    "gn:dem":120,
    "gn:feature_class":"P",
    "gn:feature_code":"PPL",
    "gn:name":"Lingkou",
    "gn:population":0,
    "gn:timezone":"Asia/Shanghai",
    "iso:country":"CN",
    "name:zho_x_preferred":[
        "\u5cad\u53e3"
    ],
    "wof:name":"Lingkou",
    "wof:placetype":"locality"
},
  "geometry": {"coordinates":[121.35523999999999,29.90596],"type":"Point"}
}