{
  "type": "Feature",
  "properties": {
    "gn:admin1_code":"3",
    "gn:asciiname":"Bangangdong",
    "gn:country_code":"CN",
    "gn:dem":623,
    "gn:feature_class":"P",
    "gn:feature_code":"PPL",
    "gn:name":"Bangangdong",
    "gn:population":0,
    "gn:timezone":"Asia/Shanghai",
    "iso:country":"CN",
    "name:zho_x_preferred":[
        "\u677f\u5c97\u6d1e"
    ],
    "wof:name":"Bangangdong",
    "wof:placetype":"locality"
},
  "geometry": {"coordinates":[114.122,26.3815],"type":"Point"}
}