{
  "type": "Feature",
  "properties": {
    "gn:admin1_code":"2",
    "gn:asciiname":"Huangsha",
    "gn:country_code":"CN",
    "gn:dem":1021,
    "gn:feature_class":"P",
    "gn:feature_code":"PPL",
    "gn:name":"Huangsha",
    "gn:population":0,
    "gn:timezone":"Asia/Shanghai",
    "iso:country":"CN",
    "name:zho_x_preferred":[
        "\u9ec4\u6c99"
    ],
    "wof:name":"Huangsha",
    "wof:placetype":"locality"
},
  "geometry": {"coordinates":[119.29889,27.59222],"type":"Point"}
}