{
  "type": "Feature",
  "properties": {
    "gn:admin1_code":"14.0",
    "gn:asciiname":"Desha",
    "gn:country_code":"CN",
    "gn:dem":3863,
    "gn:feature_class":"P",
    "gn:feature_code":"PPL",
    "gn:name":"Desha",
    "gn:population":0,
    "gn:timezone":"Asia/Urumqi",
    "iso:country":"CN",
    "name:zho_x_preferred":[
        "\u5f97\u6c99"
    ],
    "wof:name":"Desha",
    "wof:placetype":"locality"
},
  "geometry": {"coordinates":[92.48053,29.15424],"type":"Point"}
}