{
  "type": "Feature",
  "properties": {
    "gn:admin1_code":"6.0",
    "gn:asciiname":"Rushiqi",
    "gn:country_code":"CN",
    "gn:dem":2368,
    "gn:feature_class":"P",
    "gn:feature_code":"PPL",
    "gn:name":"Rushiqi",
    "gn:population":0,
    "gn:timezone":"Asia/Shanghai",
    "iso:country":"CN",
    "name:zho_x_preferred":[
        "\u5982\u4ec0\u5176"
    ],
    "wof:name":"Rushiqi",
    "wof:placetype":"locality"
},
  "geometry": {"coordinates":[101.94232,35.9393],"type":"Point"}
}