{
  "type": "Feature",
  "properties": {
    "gn:admin1_code":"21.0",
    "gn:asciiname":"Zhaomajing",
    "gn:country_code":"CN",
    "gn:dem":1956,
    "gn:feature_class":"P",
    "gn:feature_code":"PPL",
    "gn:name":"Zhaomajing",
    "gn:population":0,
    "gn:timezone":"Asia/Shanghai",
    "iso:country":"CN",
    "name:zho_x_preferred":[
        "\u8d75\u9a6c\u4e95"
    ],
    "wof:name":"Zhaomajing",
    "wof:placetype":"locality"
},
  "geometry": {"coordinates":[105.26900000000001,37.1633],"type":"Point"}
}