{
  "type": "Feature",
  "properties": {
    "gn:admin1_code":"31",
    "gn:asciiname":"Bolang",
    "gn:country_code":"CN",
    "gn:dem":83,
    "gn:feature_class":"P",
    "gn:feature_code":"PPL",
    "gn:name":"Bolang",
    "gn:population":0,
    "gn:timezone":"Asia/Shanghai",
    "iso:country":"CN",
    "name:und_x_variant":[
        "\u535a\u90ce"
    ],
    "wof:name":"Bolang",
    "wof:placetype":"locality"
},
  "geometry": {"coordinates":[109.747,19.7189],"type":"Point"}
}