{
  "type": "Feature",
  "properties": {
    "gn:admin1_code":"19.0",
    "gn:asciiname":"Kangjia",
    "gn:country_code":"CN",
    "gn:dem":147,
    "gn:feature_class":"P",
    "gn:feature_code":"PPL",
    "gn:name":"Kangjia",
    "gn:population":0,
    "gn:timezone":"Asia/Shanghai",
    "iso:country":"CN",
    "name:und_x_variant":[
        "\u5eb7\u5bb6"
    ],
    "name:zho_x_preferred":[
        "\u5eb7\u5bb6"
    ],
    "wof:name":"Kangjia",
    "wof:placetype":"locality"
},
  "geometry": {"coordinates":[124.33678999999999,40.55689],"type":"Point"}
}