{
  "type": "Feature",
  "properties": {
    "gn:admin1_code":"7.0",
    "gn:asciiname":"Zhuzhongkeng",
    "gn:country_code":"CN",
    "gn:dem":509,
    "gn:feature_class":"P",
    "gn:feature_code":"PPL",
    "gn:name":"Zhuzhongkeng",
    "gn:population":0,
    "gn:timezone":"Asia/Shanghai",
    "iso:country":"CN",
    "name:zho_x_preferred":[
        "\u6731\u4e2d\u5751"
    ],
    "wof:name":"Zhuzhongkeng",
    "wof:placetype":"locality"
},
  "geometry": {"coordinates":[116.94826999999999,24.95295],"type":"Point"}
}