{
  "type": "Feature",
  "properties": {
    "gn:admin1_code":"4.0",
    "gn:asciiname":"Huaizheng",
    "gn:country_code":"CN",
    "gn:dem":4,
    "gn:feature_class":"P",
    "gn:feature_code":"PPL",
    "gn:name":"Huaizheng",
    "gn:population":0,
    "gn:timezone":"Asia/Shanghai",
    "iso:country":"CN",
    "name:und_x_variant":[
        "\u6dee\u6b63"
    ],
    "wof:name":"Huaizheng",
    "wof:placetype":"locality"
},
  "geometry": {"coordinates":[120.43022000000001,33.37308],"type":"Point"}
}