{
  "type": "Feature",
  "properties": {
    "gn:admin1_code":"14.0",
    "gn:asciiname":"Saiyalaiqinma",
    "gn:country_code":"CN",
    "gn:dem":4684,
    "gn:feature_class":"P",
    "gn:feature_code":"PPL",
    "gn:name":"Saiyalaiqinma",
    "gn:population":0,
    "gn:timezone":"Asia/Urumqi",
    "iso:country":"CN",
    "name:zho_x_preferred":[
        "\u8d5b\u4e9a\u6765\u94a6\u739b"
    ],
    "wof:name":"Saiyalaiqinma",
    "wof:placetype":"locality"
},
  "geometry": {"coordinates":[91.34904,32.13607],"type":"Point"}
}