{
  "type": "Feature",
  "properties": {
    "gn:admin1_code":"8.0",
    "gn:asciiname":"E'er'e",
    "gn:country_code":"CN",
    "gn:dem":134,
    "gn:feature_class":"P",
    "gn:feature_code":"PPL",
    "gn:name":"E\u2019er\u2019e",
    "gn:population":0,
    "gn:timezone":"Asia/Shanghai",
    "iso:country":"CN",
    "name:und_x_variant":[
        "E\u2019er\u2019e"
    ],
    "name:zho_x_preferred":[
        "\u989d\u5c14\u989d"
    ],
    "wof:name":"E'er'e",
    "wof:placetype":"locality"
},
  "geometry": {"coordinates":[124.34166999999999,45.81051],"type":"Point"}
}