{
  "type": "Feature",
  "properties": {
    "gn:admin1_code":"8.0",
    "gn:asciiname":"Huanglaogeda",
    "gn:country_code":"CN",
    "gn:dem":222,
    "gn:feature_class":"P",
    "gn:feature_code":"PPL",
    "gn:name":"Huanglaogeda",
    "gn:population":0,
    "gn:timezone":"Asia/Shanghai",
    "iso:country":"CN",
    "name:zho_x_preferred":[
        "\u9ec4\u8001\u7599\u7629"
    ],
    "wof:name":"Huanglaogeda",
    "wof:placetype":"locality"
},
  "geometry": {"coordinates":[127.38008000000001,46.70579],"type":"Point"}
}