{
  "type": "Feature",
  "properties": {
    "gn:admin1_code":"08",
    "gn:asciiname":"Dong'an",
    "gn:country_code":"CN",
    "gn:dem":44,
    "gn:feature_class":"P",
    "gn:feature_code":"PPL",
    "gn:name":"Dong\u2019an",
    "gn:population":0,
    "gn:timezone":"Asia/Shanghai",
    "iso:country":"CN",
    "name:und_x_variant":[
        "Tung-an-chen",
        "Tung-an",
        "Ch\u2019e-an-chen",
        "Dong\u2019an"
    ],
    "wof:name":"Dong'an",
    "wof:placetype":"locality"
},
  "geometry": {"coordinates":[134.12833000000001,47.32417],"type":"Point"}
}