{
  "type": "Feature",
  "properties": {
    "gn:admin1_code":"3.0",
    "gn:asciiname":"Dajiling",
    "gn:country_code":"CN",
    "gn:dem":186,
    "gn:feature_class":"P",
    "gn:feature_code":"PPL",
    "gn:name":"Dajiling",
    "gn:population":0,
    "gn:timezone":"Asia/Shanghai",
    "iso:country":"CN",
    "name:und_x_variant":[
        "\u5927\u6d4e\u5cad"
    ],
    "wof:name":"Dajiling",
    "wof:placetype":"locality"
},
  "geometry": {"coordinates":[117.15344,29.14545],"type":"Point"}
}