{
  "type": "Feature",
  "properties": {
    "gn:admin1_code":"8.0",
    "gn:asciiname":"Qunyingcun",
    "gn:country_code":"CN",
    "gn:dem":210,
    "gn:feature_class":"P",
    "gn:feature_code":"PPL",
    "gn:name":"Qunyingcun",
    "gn:population":0,
    "gn:timezone":"Asia/Shanghai",
    "iso:country":"CN",
    "name:zho_x_preferred":[
        "\u7fa4\u82f1\u6751"
    ],
    "wof:name":"Qunyingcun",
    "wof:placetype":"locality"
},
  "geometry": {"coordinates":[130.68431000000001,46.44402],"type":"Point"}
}