{
  "type": "Feature",
  "properties": {
    "gn:admin1_code":"30.0",
    "gn:asciiname":"Shulouqiu",
    "gn:country_code":"CN",
    "gn:dem":201,
    "gn:feature_class":"P",
    "gn:feature_code":"PPL",
    "gn:name":"Shulouqiu",
    "gn:population":0,
    "gn:timezone":"Asia/Shanghai",
    "iso:country":"CN",
    "name:zho_x_preferred":[
        "Shulouqiu"
    ],
    "name:zho_x_variant":[
        "\u4e66\u697c\u4e18"
    ],
    "wof:name":"Shulouqiu",
    "wof:placetype":"locality"
},
  "geometry": {"coordinates":[113.93917,25.32361],"type":"Point"}
}