{
  "type": "Feature",
  "properties": {
    "gn:admin1_code":"9.0",
    "gn:asciiname":"Yuwangmiao",
    "gn:country_code":"CN",
    "gn:dem":166,
    "gn:feature_class":"P",
    "gn:feature_code":"PPL",
    "gn:name":"Yuwangmiao",
    "gn:population":0,
    "gn:timezone":"Asia/Shanghai",
    "iso:country":"CN",
    "name:zho_x_preferred":[
        "\u79b9\u738b\u5e99"
    ],
    "wof:name":"Yuwangmiao",
    "wof:placetype":"locality"
},
  "geometry": {"coordinates":[112.14648,32.96671],"type":"Point"}
}