{
  "type": "Feature",
  "properties": {
    "gn:admin1_code":"18",
    "gn:asciiname":"Dahuadi",
    "gn:country_code":"CN",
    "gn:dem":956,
    "gn:feature_class":"P",
    "gn:feature_code":"PPL",
    "gn:name":"Dahuadi",
    "gn:population":0,
    "gn:timezone":"Asia/Shanghai",
    "iso:country":"CN",
    "name:zho_x_preferred":[
        "\u5927\u82b1\u5730"
    ],
    "wof:name":"Dahuadi",
    "wof:placetype":"locality"
},
  "geometry": {"coordinates":[105.717,25.4667],"type":"Point"}
}