{
  "type": "Feature",
  "properties": {
    "gn:admin1_code":"11.0",
    "gn:asciiname":"Bailinglong",
    "gn:country_code":"CN",
    "gn:dem":481,
    "gn:feature_class":"P",
    "gn:feature_code":"PPL",
    "gn:name":"Bailinglong",
    "gn:population":0,
    "gn:timezone":"Asia/Shanghai",
    "iso:country":"CN",
    "name:zho_x_preferred":[
        "\u767d\u5cad\u5785"
    ],
    "wof:name":"Bailinglong",
    "wof:placetype":"locality"
},
  "geometry": {"coordinates":[113.30301,27.3883],"type":"Point"}
}