{
  "type": "Feature",
  "properties": {
    "gn:admin1_code":"8.0",
    "gn:asciiname":"Fuguicun",
    "gn:country_code":"CN",
    "gn:dem":185,
    "gn:feature_class":"P",
    "gn:feature_code":"PPL",
    "gn:name":"Fuguicun",
    "gn:population":0,
    "gn:timezone":"Asia/Shanghai",
    "iso:country":"CN",
    "name:zho_x_preferred":[
        "\u5bcc\u8d35\u6751"
    ],
    "wof:name":"Fuguicun",
    "wof:placetype":"locality"
},
  "geometry": {"coordinates":[126.12976,46.90955],"type":"Point"}
}