{
  "type": "Feature",
  "properties": {
    "gn:admin1_code":"4.0",
    "gn:asciiname":"Yeyuanzhuang",
    "gn:country_code":"CN",
    "gn:dem":3,
    "gn:feature_class":"P",
    "gn:feature_code":"PPL",
    "gn:name":"Yeyuanzhuang",
    "gn:population":0,
    "gn:timezone":"Asia/Shanghai",
    "iso:country":"CN",
    "name:zho_x_preferred":[
        "Yeyuanzhuang"
    ],
    "name:zho_x_variant":[
        "\u91ce\u8881\u5e84"
    ],
    "wof:name":"Yeyuanzhuang",
    "wof:placetype":"locality"
},
  "geometry": {"coordinates":[121.09704000000001,32.46904],"type":"Point"}
}