{
  "type": "Feature",
  "properties": {
    "gn:admin1_code":"26",
    "gn:asciiname":"Dahuangyuan",
    "gn:country_code":"CN",
    "gn:dem":661,
    "gn:feature_class":"P",
    "gn:feature_code":"PPL",
    "gn:name":"Dahuangyuan",
    "gn:population":0,
    "gn:timezone":"Asia/Shanghai",
    "iso:country":"CN",
    "name:und_x_variant":[
        "Ta-huang-y\u00fcan",
        "Dahuangyuan",
        "\u5927\u9ec4\u9662"
    ],
    "wof:name":"Dahuangyuan",
    "wof:placetype":"locality"
},
  "geometry": {"coordinates":[106.42045,33.26965999999999],"type":"Point"}
}