{
  "type": "Feature",
  "properties": {
    "gn:admin1_code":"26.0",
    "gn:asciiname":"Lanjiagou",
    "gn:country_code":"CN",
    "gn:dem":948,
    "gn:feature_class":"P",
    "gn:feature_code":"PPL",
    "gn:name":"Lanjiagou",
    "gn:population":0,
    "gn:timezone":"Asia/Shanghai",
    "iso:country":"CN",
    "name:und_x_variant":[
        "\u5170\u5bb6\u6c9f"
    ],
    "wof:name":"Lanjiagou",
    "wof:placetype":"locality"
},
  "geometry": {"coordinates":[106.41118,32.92258],"type":"Point"}
}