{
  "type": "Feature",
  "properties": {
    "gn:admin1_code":"13.0",
    "gn:asciiname":"Saner Tuanchang",
    "gn:country_code":"CN",
    "gn:dem":869,
    "gn:feature_class":"P",
    "gn:feature_code":"PPLF",
    "gn:name":"Saner Tuanchang",
    "gn:population":0,
    "gn:timezone":"Asia/Urumqi",
    "iso:country":"CN",
    "name:zho_x_preferred":[
        "\u4e09\u4e8c\u56e2\u573a"
    ],
    "wof:name":"Saner Tuanchang",
    "wof:placetype":"locality"
},
  "geometry": {"coordinates":[86.94438000000002,40.88399],"type":"Point"}
}