{
  "type": "Feature",
  "properties": {
    "gn:admin1_code":"4.0",
    "gn:asciiname":"Lijiazhuang",
    "gn:country_code":"CN",
    "gn:dem":3,
    "gn:feature_class":"P",
    "gn:feature_code":"PPL",
    "gn:name":"Lijiazhuang",
    "gn:population":0,
    "gn:timezone":"Asia/Shanghai",
    "iso:country":"CN",
    "name:zho_x_preferred":[
        "Lijiazhuang"
    ],
    "name:zho_x_variant":[
        "\u674e\u5bb6\u5e84"
    ],
    "wof:name":"Lijiazhuang",
    "wof:placetype":"locality"
},
  "geometry": {"coordinates":[119.78598,33.44174],"type":"Point"}
}