{
  "type": "Feature",
  "properties": {
    "gn:admin1_code":"13.0",
    "gn:asciiname":"Kawake",
    "gn:country_code":"CN",
    "gn:dem":3831,
    "gn:feature_class":"P",
    "gn:feature_code":"PPL",
    "gn:name":"Kawake",
    "gn:population":0,
    "gn:timezone":"Asia/Shanghai",
    "iso:country":"CN",
    "name:zho_x_preferred":[
        "\u5580\u74e6\u514b"
    ],
    "wof:name":"Kawake",
    "wof:placetype":"locality"
},
  "geometry": {"coordinates":[78.45483,36.24685],"type":"Point"}
}