{
  "type": "Feature",
  "properties": {
    "gn:admin1_code":"32.0",
    "gn:asciiname":"Qingping",
    "gn:country_code":"CN",
    "gn:dem":886,
    "gn:feature_class":"P",
    "gn:feature_code":"PPL",
    "gn:name":"Qingping",
    "gn:population":0,
    "gn:timezone":"Asia/Shanghai",
    "iso:country":"CN",
    "name:zho_x_preferred":[
        "\u6e05\u5e73"
    ],
    "wof:name":"Qingping",
    "wof:placetype":"locality"
},
  "geometry": {"coordinates":[104.11369000000001,31.54565],"type":"Point"}
}