{
  "type": "Feature",
  "properties": {
    "gn:admin1_code":"04",
    "gn:asciiname":"Longgu",
    "gn:cc2":"CN",
    "gn:country_code":"CN",
    "gn:dem":37,
    "gn:feature_class":"P",
    "gn:feature_code":"PPL",
    "gn:name":"Longgu",
    "gn:population":0,
    "gn:timezone":"Asia/Shanghai",
    "iso:country":"CN",
    "name:und_x_variant":[
        "Lung-ku",
        "Lung-ku-chi",
        "Longgu"
    ],
    "wof:name":"Longgu",
    "wof:placetype":"locality"
},
  "geometry": {"coordinates":[116.80667,34.90333],"type":"Point"}
}