{
  "type": "Feature",
  "properties": {
    "gn:admin1_code":"29.0",
    "gn:asciiname":"Fatunan",
    "gn:country_code":"CN",
    "gn:dem":1613,
    "gn:feature_class":"P",
    "gn:feature_code":"PPL",
    "gn:name":"Fatunan",
    "gn:population":0,
    "gn:timezone":"Asia/Shanghai",
    "iso:country":"CN",
    "name:und_x_variant":[
        "\u6cd5\u571f\u5357"
    ],
    "wof:name":"Fatunan",
    "wof:placetype":"locality"
},
  "geometry": {"coordinates":[103.27658,26.97169],"type":"Point"}
}