{
  "type": "Feature",
  "properties": {
    "gn:admin1_code":"5.0",
    "gn:asciiname":"Dawangtun",
    "gn:country_code":"CN",
    "gn:dem":385,
    "gn:feature_class":"P",
    "gn:feature_code":"PPL",
    "gn:name":"Dawangtun",
    "gn:population":0,
    "gn:timezone":"Asia/Shanghai",
    "iso:country":"CN",
    "name:zho_x_preferred":[
        "\u5927\u671b\u5c6f"
    ],
    "wof:name":"Dawangtun",
    "wof:placetype":"locality"
},
  "geometry": {"coordinates":[125.45932000000001,42.9993],"type":"Point"}
}