{
  "type": "Feature",
  "properties": {
    "gn:admin1_code":"19",
    "gn:asciiname":"Paozi",
    "gn:cc2":"CN",
    "gn:country_code":"CN",
    "gn:dem":85,
    "gn:feature_class":"P",
    "gn:feature_code":"PPL",
    "gn:name":"Paozi",
    "gn:population":0,
    "gn:timezone":"Asia/Shanghai",
    "iso:country":"CN",
    "name:und_x_variant":[
        "P\u2019ao-tzu",
        "Paozi"
    ],
    "wof:name":"Paozi",
    "wof:placetype":"locality"
},
  "geometry": {"coordinates":[122.31667,42.21667],"type":"Point"}
}