{
  "type": "Feature",
  "properties": {
    "gn:admin1_code":"32.0",
    "gn:asciiname":"Dere",
    "gn:country_code":"CN",
    "gn:dem":3403,
    "gn:feature_class":"P",
    "gn:feature_code":"PPL",
    "gn:name":"Dere",
    "gn:population":0,
    "gn:timezone":"Asia/Shanghai",
    "iso:country":"CN",
    "name:ceb_x_preferred":[
        "Dere"
    ],
    "name:deu_x_preferred":[
        "Dere"
    ],
    "name:rus_x_preferred":[
        "\u0414\u0435\u0440\u0435"
    ],
    "name:swe_x_preferred":[
        "Dere"
    ],
    "name:ukr_x_preferred":[
        "\u0414\u0435\u0440\u0435"
    ],
    "name:zho_x_preferred":[
        "\u5fb7\u70ed"
    ],
    "wof:name":"Dere",
    "wof:placetype":"locality"
},
  "geometry": {"coordinates":[101.43300000000001,32.1474],"type":"Point"}
}