{
  "type": "Feature",
  "properties": {
    "gn:admin1_code":"11.0",
    "gn:asciiname":"Baishixi",
    "gn:country_code":"CN",
    "gn:dem":92,
    "gn:feature_class":"P",
    "gn:feature_code":"PPL",
    "gn:name":"Baishixi",
    "gn:population":0,
    "gn:timezone":"Asia/Shanghai",
    "iso:country":"CN",
    "name:zho_x_preferred":[
        "\u767d\u77f3\u6eaa"
    ],
    "wof:name":"Baishixi",
    "wof:placetype":"locality"
},
  "geometry": {"coordinates":[111.05553,28.84041],"type":"Point"}
}