{
  "type": "Feature",
  "properties": {
    "gn:admin1_code":"29.0",
    "gn:asciiname":"Laojiangtian",
    "gn:country_code":"CN",
    "gn:dem":1312,
    "gn:feature_class":"P",
    "gn:feature_code":"PPL",
    "gn:name":"Laojiangtian",
    "gn:population":0,
    "gn:timezone":"Asia/Shanghai",
    "iso:country":"CN",
    "name:zho_x_preferred":[
        "\u8001\u5320\u7530"
    ],
    "wof:name":"Laojiangtian",
    "wof:placetype":"locality"
},
  "geometry": {"coordinates":[99.5925,24.6408],"type":"Point"}
}