{
  "type": "Feature",
  "properties": {
    "gn:admin1_code":"5.0",
    "gn:asciiname":"Babaogou",
    "gn:country_code":"CN",
    "gn:dem":513,
    "gn:feature_class":"P",
    "gn:feature_code":"PPL",
    "gn:name":"Babaogou",
    "gn:population":0,
    "gn:timezone":"Asia/Shanghai",
    "iso:country":"CN",
    "name:und_x_variant":[
        "\u516b\u5b9d\u6c9f"
    ],
    "wof:name":"Babaogou",
    "wof:placetype":"locality"
},
  "geometry": {"coordinates":[125.91749,41.90091],"type":"Point"}
}