{
  "type": "Feature",
  "properties": {
    "gn:admin1_code":"1.0",
    "gn:asciiname":"Xuegangcun",
    "gn:country_code":"CN",
    "gn:dem":27,
    "gn:feature_class":"P",
    "gn:feature_code":"PPL",
    "gn:name":"Xuegangcun",
    "gn:population":0,
    "gn:timezone":"Asia/Shanghai",
    "iso:country":"CN",
    "name:zho_x_preferred":[
        "\u859b\u5c97\u6751"
    ],
    "wof:name":"Xuegangcun",
    "wof:placetype":"locality"
},
  "geometry": {"coordinates":[116.38236999999999,32.24536],"type":"Point"}
}