{
  "type": "Feature",
  "properties": {
    "gn:admin1_code":"26.0",
    "gn:asciiname":"Nandong",
    "gn:country_code":"CN",
    "gn:dem":479,
    "gn:feature_class":"P",
    "gn:feature_code":"PPL",
    "gn:name":"Nandong",
    "gn:population":0,
    "gn:timezone":"Asia/Shanghai",
    "iso:country":"CN",
    "name:fas_x_preferred":[
        "\u0646\u0627\u0646\u062f\u0648\u0646\u06af"
    ],
    "name:zho_x_preferred":[
        "\u5357\u8463"
    ],
    "name:zho_x_variant":[
        "\u5357\u8463\u9547"
    ],
    "wof:name":"Nandong",
    "wof:placetype":"locality"
},
  "geometry": {"coordinates":[109.24057000000001,34.81814],"type":"Point"}
}