{
  "type": "Feature",
  "properties": {
    "gn:admin1_code":"29.0",
    "gn:asciiname":"Dasuyi",
    "gn:country_code":"CN",
    "gn:dem":2100,
    "gn:feature_class":"P",
    "gn:feature_code":"PPL",
    "gn:name":"Dasuyi",
    "gn:population":0,
    "gn:timezone":"Asia/Shanghai",
    "iso:country":"CN",
    "name:zho_x_preferred":[
        "\u5927\u5bbf\u8863"
    ],
    "wof:name":"Dasuyi",
    "wof:placetype":"locality"
},
  "geometry": {"coordinates":[103.602,24.2699],"type":"Point"}
}