{
  "type": "Feature",
  "properties": {
    "gn:admin1_code":"32.0",
    "gn:asciiname":"Yinggezui",
    "gn:country_code":"CN",
    "gn:dem":1343,
    "gn:feature_class":"P",
    "gn:feature_code":"PPL",
    "gn:name":"Yinggezui",
    "gn:population":0,
    "gn:timezone":"Asia/Shanghai",
    "iso:country":"CN",
    "name:zho_x_preferred":[
        "\u9e66\u54e5\u5480"
    ],
    "wof:name":"Yinggezui",
    "wof:placetype":"locality"
},
  "geometry": {"coordinates":[104.21491,31.6558],"type":"Point"}
}