{
  "type": "Feature",
  "properties": {
    "gn:admin1_code":"21.0",
    "gn:asciiname":"Tangbu",
    "gn:country_code":"CN",
    "gn:dem":1507,
    "gn:feature_class":"P",
    "gn:feature_code":"PPL",
    "gn:name":"Tangbu",
    "gn:population":0,
    "gn:timezone":"Asia/Shanghai",
    "iso:country":"CN",
    "name:und_x_variant":[
        "\u5510\u5821"
    ],
    "name:zho_x_preferred":[
        "\u5510\u5821"
    ],
    "wof:name":"Tangbu",
    "wof:placetype":"locality"
},
  "geometry": {"coordinates":[106.12942,36.37471],"type":"Point"}
}