{
  "type": "Feature",
  "properties": {
    "gn:admin1_code":"3",
    "gn:asciiname":"Shiwo",
    "gn:country_code":"CN",
    "gn:dem":312,
    "gn:feature_class":"P",
    "gn:feature_code":"PPL",
    "gn:name":"Shiwo",
    "gn:population":0,
    "gn:timezone":"Asia/Shanghai",
    "iso:country":"CN",
    "name:zho_x_preferred":[
        "\u77f3\u7a9d"
    ],
    "wof:name":"Shiwo",
    "wof:placetype":"locality"
},
  "geometry": {"coordinates":[114.25801,26.0987],"type":"Point"}
}