{
  "type": "Feature",
  "properties": {
    "gn:admin1_code":"21.0",
    "gn:asciiname":"Qianwei Yidui",
    "gn:country_code":"CN",
    "gn:dem":1093,
    "gn:feature_class":"P",
    "gn:feature_code":"PPLF",
    "gn:name":"Qianwei Yidui",
    "gn:population":0,
    "gn:timezone":"Asia/Shanghai",
    "iso:country":"CN",
    "name:zho_x_preferred":[
        "\u524d\u536b\u4e00\u961f"
    ],
    "wof:name":"Qianwei Yidui",
    "wof:placetype":"locality"
},
  "geometry": {"coordinates":[106.73699999999999,39.0747],"type":"Point"}
}