{
  "type": "Feature",
  "properties": {
    "gn:admin1_code":"9.0",
    "gn:asciiname":"Madigou",
    "gn:country_code":"CN",
    "gn:dem":941,
    "gn:feature_class":"P",
    "gn:feature_code":"PPL",
    "gn:name":"Madigou",
    "gn:population":0,
    "gn:timezone":"Asia/Shanghai",
    "iso:country":"CN",
    "name:zho_x_preferred":[
        "\u9ebb\u5730\u6c9f"
    ],
    "wof:name":"Madigou",
    "wof:placetype":"locality"
},
  "geometry": {"coordinates":[110.62548,34.44315],"type":"Point"}
}