{
  "type": "Feature",
  "properties": {
    "gn:admin1_code":"7",
    "gn:asciiname":"Xiahecun",
    "gn:country_code":"CN",
    "gn:dem":24,
    "gn:feature_class":"P",
    "gn:feature_code":"PPL",
    "gn:name":"Xiahecun",
    "gn:population":0,
    "gn:timezone":"Asia/Shanghai",
    "iso:country":"CN",
    "name:und_x_variant":[
        "\u4e0b\u6cb3\u6751",
        "Xiahe"
    ],
    "name:zho_x_preferred":[
        "\u4e0b\u6cb3"
    ],
    "wof:name":"Xiahecun",
    "wof:placetype":"locality"
},
  "geometry": {"coordinates":[117.28106,24.02129],"type":"Point"}
}