{
  "type": "Feature",
  "properties": {
    "gn:admin1_code":"19.0",
    "gn:asciiname":"Yushiling",
    "gn:country_code":"CN",
    "gn:dem":35,
    "gn:feature_class":"P",
    "gn:feature_code":"PPL",
    "gn:name":"Yushiling",
    "gn:population":0,
    "gn:timezone":"Asia/Shanghai",
    "iso:country":"CN",
    "name:zho_x_preferred":[
        "\u7389\u77f3\u5cad"
    ],
    "wof:name":"Yushiling",
    "wof:placetype":"locality"
},
  "geometry": {"coordinates":[123.29028,39.91394],"type":"Point"}
}