{
  "type": "Feature",
  "properties": {
    "gn:admin1_code":"15.0",
    "gn:asciiname":"Hejia",
    "gn:country_code":"CN",
    "gn:dem":1728,
    "gn:feature_class":"P",
    "gn:feature_code":"PPL",
    "gn:name":"Hejia",
    "gn:population":0,
    "gn:timezone":"Asia/Shanghai",
    "iso:country":"CN",
    "name:und_x_variant":[
        "\u4f55\u5bb6"
    ],
    "wof:name":"Hejia",
    "wof:placetype":"locality"
},
  "geometry": {"coordinates":[105.88933,35.25355],"type":"Point"}
}