{
  "type": "Feature",
  "properties": {
    "gn:admin1_code":"26.0",
    "gn:asciiname":"Hejiagou",
    "gn:country_code":"CN",
    "gn:dem":1272,
    "gn:feature_class":"P",
    "gn:feature_code":"PPL",
    "gn:name":"Hejiagou",
    "gn:population":0,
    "gn:timezone":"Asia/Shanghai",
    "iso:country":"CN",
    "name:zho_x_preferred":[
        "\u8d3a\u5bb6\u6c9f"
    ],
    "wof:name":"Hejiagou",
    "wof:placetype":"locality"
},
  "geometry": {"coordinates":[109.70878999999999,35.82044000000001],"type":"Point"}
}