{
  "type": "Feature",
  "properties": {
    "gn:admin1_code":"6.0",
    "gn:asciiname":"Jieguanling",
    "gn:country_code":"CN",
    "gn:dem":2367,
    "gn:feature_class":"P",
    "gn:feature_code":"PPL",
    "gn:name":"Jieguanling",
    "gn:population":0,
    "gn:timezone":"Asia/Shanghai",
    "iso:country":"CN",
    "name:und_x_variant":[
        "\u63a5\u5b98\u5cad"
    ],
    "wof:name":"Jieguanling",
    "wof:placetype":"locality"
},
  "geometry": {"coordinates":[102.91849000000001,35.99261],"type":"Point"}
}