{
  "type": "Feature",
  "properties": {
    "gn:admin1_code":"14.0",
    "gn:asciiname":"Kadacun",
    "gn:country_code":"CN",
    "gn:dem":2690,
    "gn:feature_class":"P",
    "gn:feature_code":"PPL",
    "gn:name":"Kadacun",
    "gn:population":0,
    "gn:timezone":"Asia/Urumqi",
    "iso:country":"CN",
    "name:bod_x_preferred":[
        "Kadag"
    ],
    "name:zho_x_preferred":[
        "\u5361\u8fbe\u6751"
    ],
    "wof:name":"Kadacun",
    "wof:placetype":"locality"
},
  "geometry": {"coordinates":[95.63909,29.91036],"type":"Point"}
}