{
  "type": "Feature",
  "properties": {
    "gn:admin1_code":"10.0",
    "gn:asciiname":"Panzhuangzi",
    "gn:country_code":"CN",
    "gn:dem":26,
    "gn:feature_class":"P",
    "gn:feature_code":"PPL",
    "gn:name":"Panzhuangzi",
    "gn:population":0,
    "gn:timezone":"Asia/Shanghai",
    "iso:country":"CN",
    "name:zho_x_preferred":[
        "\u6f58\u5e84\u5b50"
    ],
    "wof:name":"Panzhuangzi",
    "wof:placetype":"locality"
},
  "geometry": {"coordinates":[117.86896000000002,39.9079],"type":"Point"}
}