{
  "type": "Feature",
  "properties": {
    "gn:admin1_code":"25",
    "gn:asciiname":"Xujiadian",
    "gn:country_code":"CN",
    "gn:dem":17,
    "gn:feature_class":"P",
    "gn:feature_code":"PPL",
    "gn:name":"Xujiadian",
    "gn:population":0,
    "gn:timezone":"Asia/Shanghai",
    "iso:country":"CN",
    "name:zho_x_preferred":[
        "\u5f90\u5bb6\u5e97"
    ],
    "name:zho_x_variant":[
        "\u5f90\u5bb6\u5e97\u9547"
    ],
    "wof:name":"Xujiadian",
    "wof:placetype":"locality"
},
  "geometry": {"coordinates":[116.96599999999999,37.1783],"type":"Point"}
}