{
  "type": "Feature",
  "properties": {
    "gn:admin1_code":"30.0",
    "gn:asciiname":"Huan'an",
    "gn:country_code":"CN",
    "gn:dem":16,
    "gn:feature_class":"P",
    "gn:feature_code":"PPL",
    "gn:name":"Huan\u2019an",
    "gn:population":0,
    "gn:timezone":"Asia/Shanghai",
    "iso:country":"CN",
    "name:und_x_variant":[
        "Huan\u2019an"
    ],
    "name:zho_x_preferred":[
        "\u73af\u5b89"
    ],
    "wof:name":"Huan'an",
    "wof:placetype":"locality"
},
  "geometry": {"coordinates":[112.76969,22.17628],"type":"Point"}
}