{
  "type": "Feature",
  "properties": {
    "gn:admin1_code":"4.0",
    "gn:asciiname":"Qiaoxu",
    "gn:country_code":"CN",
    "gn:dem":5,
    "gn:feature_class":"P",
    "gn:feature_code":"PPL",
    "gn:name":"Qiaoxu",
    "gn:population":0,
    "gn:timezone":"Asia/Shanghai",
    "iso:country":"CN",
    "name:zho_x_preferred":[
        "Qiaoxu"
    ],
    "name:zho_x_variant":[
        "\u4e54\u5729"
    ],
    "wof:name":"Qiaoxu",
    "wof:placetype":"locality"
},
  "geometry": {"coordinates":[119.24532000000001,34.2219],"type":"Point"}
}