{
  "type": "Feature",
  "properties": {
    "gn:admin1_code":"4.0",
    "gn:asciiname":"Dahuazi",
    "gn:country_code":"CN",
    "gn:dem":5,
    "gn:feature_class":"P",
    "gn:feature_code":"PPL",
    "gn:name":"Dahuazi",
    "gn:population":0,
    "gn:timezone":"Asia/Shanghai",
    "iso:country":"CN",
    "name:zho_x_preferred":[
        "Dahuazi"
    ],
    "name:zho_x_variant":[
        "\u5927\u5212\u5b50"
    ],
    "wof:name":"Dahuazi",
    "wof:placetype":"locality"
},
  "geometry": {"coordinates":[121.26937,31.98336],"type":"Point"}
}