{
  "type": "Feature",
  "properties": {
    "gn:admin1_code":"3.0",
    "gn:asciiname":"Huashuxia",
    "gn:country_code":"CN",
    "gn:dem":85,
    "gn:feature_class":"P",
    "gn:feature_code":"PPL",
    "gn:name":"Huashuxia",
    "gn:population":0,
    "gn:timezone":"Asia/Shanghai",
    "iso:country":"CN",
    "name:und_x_variant":[
        "\u82b1\u6811\u4e0b"
    ],
    "wof:name":"Huashuxia",
    "wof:placetype":"locality"
},
  "geometry": {"coordinates":[114.74911000000002,27.11566],"type":"Point"}
}