{
  "type": "Feature",
  "properties": {
    "gn:admin1_code":"16",
    "gn:asciiname":"Danzhuping",
    "gn:country_code":"CN",
    "gn:dem":489,
    "gn:feature_class":"P",
    "gn:feature_code":"PPL",
    "gn:name":"Danzhuping",
    "gn:population":0,
    "gn:timezone":"Asia/Shanghai",
    "iso:country":"CN",
    "name:zho_x_preferred":[
        "\u4e39\u7af9\u576a"
    ],
    "wof:name":"Danzhuping",
    "wof:placetype":"locality"
},
  "geometry": {"coordinates":[109.93600000000001,25.4182],"type":"Point"}
}