{
  "type": "Feature",
  "properties": {
    "gn:admin1_code":"31",
    "gn:asciiname":"Qiaozhong",
    "gn:country_code":"CN",
    "gn:dem":39,
    "gn:feature_class":"P",
    "gn:feature_code":"PPL",
    "gn:name":"Qiaozhong",
    "gn:population":0,
    "gn:timezone":"Asia/Shanghai",
    "iso:country":"CN",
    "name:und_x_variant":[
        "\u6865\u4e2d"
    ],
    "wof:name":"Qiaozhong",
    "wof:placetype":"locality"
},
  "geometry": {"coordinates":[110.14476999999999,18.70412],"type":"Point"}
}