{
  "type": "Feature",
  "properties": {
    "gn:admin1_code":"30",
    "gn:asciiname":"Shuibei",
    "gn:country_code":"CN",
    "gn:dem":835,
    "gn:feature_class":"P",
    "gn:feature_code":"PPL",
    "gn:name":"Shuibei",
    "gn:population":0,
    "gn:timezone":"Asia/Shanghai",
    "iso:country":"CN",
    "wof:name":"Shuibei",
    "wof:placetype":"locality"
},
  "geometry": {"coordinates":[115.90667000000001,23.64417000000001],"type":"Point"}
}