{
  "type": "Feature",
  "properties": {
    "gn:admin1_code":"21.0",
    "gn:asciiname":"Majiabuzi",
    "gn:country_code":"CN",
    "gn:dem":1668,
    "gn:feature_class":"P",
    "gn:feature_code":"PPL",
    "gn:name":"Majiabuzi",
    "gn:population":0,
    "gn:timezone":"Asia/Shanghai",
    "iso:country":"CN",
    "name:und_x_variant":[
        "\u9a6c\u5bb6\u5821\u5b50"
    ],
    "name:zho_x_preferred":[
        "\u9a6c\u5bb6\u5821\u5b50"
    ],
    "wof:name":"Majiabuzi",
    "wof:placetype":"locality"
},
  "geometry": {"coordinates":[106.37477,36.96042],"type":"Point"}
}