{
  "type": "Feature",
  "properties": {
    "gn:admin1_code":"11",
    "gn:asciiname":"Taoshu'ao",
    "gn:country_code":"CN",
    "gn:dem":670,
    "gn:feature_class":"P",
    "gn:feature_code":"PPL",
    "gn:name":"Taoshu\u2019ao",
    "gn:population":0,
    "gn:timezone":"Asia/Shanghai",
    "iso:country":"CN",
    "name:und_x_variant":[
        "Taoshu\u2019ao"
    ],
    "name:zho_x_preferred":[
        "\u6843\u6811\u5773"
    ],
    "wof:name":"Taoshu'ao",
    "wof:placetype":"locality"
},
  "geometry": {"coordinates":[111.62316,27.81519],"type":"Point"}
}