{
  "type": "Feature",
  "properties": {
    "gn:admin1_code":"33.0",
    "gn:asciiname":"Shichaomen",
    "gn:country_code":"CN",
    "gn:dem":362,
    "gn:feature_class":"P",
    "gn:feature_code":"PPL",
    "gn:name":"Shichaomen",
    "gn:population":0,
    "gn:timezone":"Asia/Shanghai",
    "iso:country":"CN",
    "name:zho_x_preferred":[
        "\u77f3\u671d\u95e8"
    ],
    "wof:name":"Shichaomen",
    "wof:placetype":"locality"
},
  "geometry": {"coordinates":[106.67700000000001,28.9469],"type":"Point"}
}