{
  "type": "Feature",
  "properties": {
    "gn:admin1_code":"25",
    "gn:asciiname":"Zhu'a",
    "gn:country_code":"CN",
    "gn:dem":480,
    "gn:feature_class":"P",
    "gn:feature_code":"PPL",
    "gn:name":"Zhu\u2019a",
    "gn:population":0,
    "gn:timezone":"Asia/Shanghai",
    "iso:country":"CN",
    "name:und_x_variant":[
        "Zhu\u2019a"
    ],
    "name:zho_x_preferred":[
        "\u6731\u963f"
    ],
    "wof:name":"Zhu'a",
    "wof:placetype":"locality"
},
  "geometry": {"coordinates":[118.07599999999999,36.2722],"type":"Point"}
}