{
  "type": "Feature",
  "properties": {
    "gn:admin1_code":"1.0",
    "gn:asciiname":"Jiangqiaocun",
    "gn:country_code":"CN",
    "gn:dem":30,
    "gn:feature_class":"P",
    "gn:feature_code":"PPL",
    "gn:name":"Jiangqiaocun",
    "gn:population":0,
    "gn:timezone":"Asia/Shanghai",
    "iso:country":"CN",
    "name:zho_x_preferred":[
        "\u6c5f\u6865\u6751"
    ],
    "wof:name":"Jiangqiaocun",
    "wof:placetype":"locality"
},
  "geometry": {"coordinates":[116.20638999999998,33.23812],"type":"Point"}
}