{
  "type": "Feature",
  "properties": {
    "gn:admin1_code":"2.0",
    "gn:asciiname":"Xidantou",
    "gn:country_code":"CN",
    "gn:dem":1035,
    "gn:feature_class":"P",
    "gn:feature_code":"PPL",
    "gn:name":"Xidantou",
    "gn:population":0,
    "gn:timezone":"Asia/Shanghai",
    "iso:country":"CN",
    "name:zho_x_preferred":[
        "\u897f\u62c5\u5934"
    ],
    "wof:name":"Xidantou",
    "wof:placetype":"locality"
},
  "geometry": {"coordinates":[119.00236,28.77941],"type":"Point"}
}