{
  "type": "Feature",
  "properties": {
    "gn:admin1_code":"8.0",
    "gn:asciiname":"Pingyuan Liudui",
    "gn:country_code":"CN",
    "gn:dem":245,
    "gn:feature_class":"P",
    "gn:feature_code":"PPLF",
    "gn:name":"Pingyuan Liudui",
    "gn:population":0,
    "gn:timezone":"Asia/Shanghai",
    "iso:country":"CN",
    "name:zho_x_preferred":[
        "\u5e73\u539f\u516d\u961f"
    ],
    "wof:name":"Pingyuan Liudui",
    "wof:placetype":"locality"
},
  "geometry": {"coordinates":[124.95547999999999,48.33363],"type":"Point"}
}