{
  "type": "Feature",
  "properties": {
    "gn:admin1_code":"1.0",
    "gn:asciiname":"Zhaolukoucun",
    "gn:country_code":"CN",
    "gn:dem":37,
    "gn:feature_class":"P",
    "gn:feature_code":"PPL",
    "gn:name":"Zhaolukoucun",
    "gn:population":0,
    "gn:timezone":"Asia/Shanghai",
    "iso:country":"CN",
    "name:zho_x_preferred":[
        "\u8d75\u8def\u53e3\u6751"
    ],
    "wof:name":"Zhaolukoucun",
    "wof:placetype":"locality"
},
  "geometry": {"coordinates":[115.58728000000001,33.21928],"type":"Point"}
}