{
  "type": "Feature",
  "properties": {
    "gn:admin1_code":"32.0",
    "gn:asciiname":"Caojiagou",
    "gn:country_code":"CN",
    "gn:dem":777,
    "gn:feature_class":"P",
    "gn:feature_code":"PPL",
    "gn:name":"Caojiagou",
    "gn:population":0,
    "gn:timezone":"Asia/Shanghai",
    "iso:country":"CN",
    "name:und_x_variant":[
        "\u6f15\u5bb6\u6c9f"
    ],
    "wof:name":"Caojiagou",
    "wof:placetype":"locality"
},
  "geometry": {"coordinates":[106.89603,32.3964],"type":"Point"}
}