{
  "type": "Feature",
  "properties": {
    "gn:admin1_code":"12.0",
    "gn:asciiname":"Shuangmiaofan",
    "gn:country_code":"CN",
    "gn:dem":86,
    "gn:feature_class":"P",
    "gn:feature_code":"PPL",
    "gn:name":"Shuangmiaofan",
    "gn:population":0,
    "gn:timezone":"Asia/Shanghai",
    "iso:country":"CN",
    "name:zho_x_preferred":[
        "\u53cc\u5e99\u7548"
    ],
    "wof:name":"Shuangmiaofan",
    "wof:placetype":"locality"
},
  "geometry": {"coordinates":[112.30811,32.00809],"type":"Point"}
}