{
  "type": "Feature",
  "properties": {
    "gn:admin1_code":"16.0",
    "gn:asciiname":"Nazao",
    "gn:country_code":"CN",
    "gn:dem":220,
    "gn:feature_class":"P",
    "gn:feature_code":"PPL",
    "gn:name":"Nazao",
    "gn:population":0,
    "gn:timezone":"Asia/Shanghai",
    "iso:country":"CN",
    "name:zho_x_preferred":[
        "\u90a3\u9020"
    ],
    "wof:name":"Nazao",
    "wof:placetype":"locality"
},
  "geometry": {"coordinates":[107.72199999999999,22.8472],"type":"Point"}
}