{
  "type": "Feature",
  "properties": {
    "gn:admin1_code":"14.0",
    "gn:asciiname":"Meiyue",
    "gn:country_code":"CN",
    "gn:dem":3611,
    "gn:feature_class":"P",
    "gn:feature_code":"PPL",
    "gn:name":"Meiyue",
    "gn:population":0,
    "gn:timezone":"Asia/Urumqi",
    "iso:country":"CN",
    "name:zho_x_preferred":[
        "\u7f8e\u7ea6"
    ],
    "wof:name":"Meiyue",
    "wof:placetype":"locality"
},
  "geometry": {"coordinates":[90.95352,29.46688],"type":"Point"}
}