{
  "type": "Feature",
  "properties": {
    "gn:admin1_code":"10",
    "gn:asciiname":"Macheng",
    "gn:cc2":"CN",
    "gn:country_code":"CN",
    "gn:dem":21,
    "gn:feature_class":"P",
    "gn:feature_code":"PPL",
    "gn:name":"Macheng",
    "gn:population":0,
    "gn:timezone":"Asia/Shanghai",
    "iso:country":"CN",
    "name:und_x_variant":[
        "Ma-ch\u2019eng-chen",
        "Macheng"
    ],
    "wof:name":"Macheng",
    "wof:placetype":"locality"
},
  "geometry": {"coordinates":[118.81667,39.63333],"type":"Point"}
}