{
  "type": "Feature",
  "properties": {
    "gn:admin1_code":"10",
    "gn:asciiname":"Macheng",
    "gn:cc2":"CN",
    "gn:country_code":"CN",
    "gn:dem":21,
    "gn:feature_class":"P",
    "gn:feature_code":"PPL",
    "gn:name":"Macheng",
    "gn:population":0,
    "gn:timezone":"Asia/Shanghai",
    "iso:country":"CN",
    "name:ceb_x_preferred":[
        "Macheng Shi"
    ],
    "name:deu_x_preferred":[
        "Macheng"
    ],
    "name:fin_x_preferred":[
        "Macheng"
    ],
    "name:fra_x_preferred":[
        "Macheng"
    ],
    "name:ita_x_preferred":[
        "Macheng"
    ],
    "name:jpn_x_preferred":[
        "\u9ebb\u57ce\u5e02"
    ],
    "name:kik_x_preferred":[
        "Macheng"
    ],
    "name:kor_x_preferred":[
        "\ub9c8\uccad\uc2dc"
    ],
    "name:mlg_x_preferred":[
        "Macheng"
    ],
    "name:nor_x_preferred":[
        "Macheng"
    ],
    "name:pam_x_preferred":[
        "Macheng"
    ],
    "name:pol_x_preferred":[
        "Macheng"
    ],
    "name:swe_x_preferred":[
        "Macheng"
    ],
    "name:und_x_variant":[
        "Ma-ch\u2019eng-chen",
        "Macheng"
    ],
    "name:urd_x_preferred":[
        "\u0645\u0627\u0686\u06cc\u0646\u06af"
    ],
    "name:vie_x_preferred":[
        "Ma Th\u00e0nh"
    ],
    "name:war_x_preferred":[
        "Macheng"
    ],
    "name:zho_x_preferred":[
        "\u9ebb\u57ce\u5e02"
    ],
    "wof:name":"Macheng",
    "wof:placetype":"locality"
},
  "geometry": {"coordinates":[118.81667,39.63333],"type":"Point"}
}