{
  "type": "Feature",
  "properties": {
    "gn:admin1_code":"18.0",
    "gn:asciiname":"Caiqin",
    "gn:country_code":"CN",
    "gn:dem":880,
    "gn:feature_class":"P",
    "gn:feature_code":"PPL",
    "gn:name":"Caiqin",
    "gn:population":0,
    "gn:timezone":"Asia/Shanghai",
    "iso:country":"CN",
    "name:zho_x_preferred":[
        "\u91c7\u82b9"
    ],
    "wof:name":"Caiqin",
    "wof:placetype":"locality"
},
  "geometry": {"coordinates":[108.946,26.6362],"type":"Point"}
}