{
  "type": "Feature",
  "properties": {
    "gn:admin1_code":"19.0",
    "gn:asciiname":"Qiantieshifang",
    "gn:country_code":"CN",
    "gn:dem":5,
    "gn:feature_class":"P",
    "gn:feature_code":"PPL",
    "gn:name":"Qiantieshifang",
    "gn:population":0,
    "gn:timezone":"Asia/Shanghai",
    "iso:country":"CN",
    "name:zho_x_preferred":[
        "\u524d\u94c1\u77f3\u623f"
    ],
    "wof:name":"Qiantieshifang",
    "wof:placetype":"locality"
},
  "geometry": {"coordinates":[122.51000000000001,41.0327],"type":"Point"}
}