{
  "type": "Feature",
  "properties": {
    "gn:admin1_code":"29.0",
    "gn:asciiname":"Hapi",
    "gn:country_code":"CN",
    "gn:dem":3396,
    "gn:feature_class":"P",
    "gn:feature_code":"PPL",
    "gn:name":"Hapi",
    "gn:population":0,
    "gn:timezone":"Asia/Shanghai",
    "iso:country":"CN",
    "name:ceb_x_preferred":[
        "Hapi"
    ],
    "name:ces_x_preferred":[
        "Hapi"
    ],
    "name:deu_x_preferred":[
        "Hapi"
    ],
    "name:nld_x_preferred":[
        "Hapi"
    ],
    "name:pol_x_preferred":[
        "Hapi"
    ],
    "name:rus_x_preferred":[
        "\u0425\u0430\u043f\u0438"
    ],
    "name:slk_x_preferred":[
        "Hapi"
    ],
    "name:swe_x_preferred":[
        "Hapi"
    ],
    "name:zho_x_preferred":[
        "\u54c8\u5339"
    ],
    "wof:name":"Hapi",
    "wof:placetype":"locality"
},
  "geometry": {"coordinates":[99.7813,27.8342],"type":"Point"}
}