{
  "type": "Feature",
  "properties": {
    "gn:admin1_code":"14.0",
    "gn:asciiname":"Lourikao",
    "gn:country_code":"CN",
    "gn:dem":4159,
    "gn:feature_class":"P",
    "gn:feature_code":"PPL",
    "gn:name":"Lourikao",
    "gn:population":0,
    "gn:timezone":"Asia/Urumqi",
    "iso:country":"CN",
    "name:zho_x_preferred":[
        "\u5a04\u65e5\u8003"
    ],
    "wof:name":"Lourikao",
    "wof:placetype":"locality"
},
  "geometry": {"coordinates":[97.08696999999999,31.91768],"type":"Point"}
}