{
  "type": "Feature",
  "properties": {
    "gn:admin1_code":"5.0",
    "gn:asciiname":"Long'anbu",
    "gn:country_code":"CN",
    "gn:dem":260,
    "gn:feature_class":"P",
    "gn:feature_code":"PPL",
    "gn:name":"Long\u2019anbu",
    "gn:population":0,
    "gn:timezone":"Asia/Shanghai",
    "iso:country":"CN",
    "name:und_x_variant":[
        "Long\u2019anbu"
    ],
    "name:zho_x_preferred":[
        "\u9f99\u5b89\u5821"
    ],
    "wof:name":"Long'anbu",
    "wof:placetype":"locality"
},
  "geometry": {"coordinates":[127.16603000000001,44.38112],"type":"Point"}
}