{
  "type": "Feature",
  "properties": {
    "gn:admin1_code":"12.0",
    "gn:asciiname":"Zengdian",
    "gn:country_code":"CN",
    "gn:dem":60,
    "gn:feature_class":"P",
    "gn:feature_code":"PPLA4",
    "gn:name":"Zengdian",
    "gn:population":0,
    "gn:timezone":"Asia/Shanghai",
    "iso:country":"CN",
    "name:und_x_variant":[
        "Tseng-chia-tien",
        "Zengdian",
        "\u66fe\u5e97",
        "Zengdian Zhen",
        "\u66fe\u5e97\u9547"
    ],
    "wof:name":"Zengdian",
    "wof:placetype":"locality"
},
  "geometry": {"coordinates":[113.77027,31.12582],"type":"Point"}
}