{
  "type": "Feature",
  "properties": {
    "gn:admin1_code":"7.0",
    "gn:asciiname":"Qiuzhu",
    "gn:country_code":"CN",
    "gn:dem":105,
    "gn:feature_class":"P",
    "gn:feature_code":"PPL",
    "gn:name":"Qiuzhu",
    "gn:population":0,
    "gn:timezone":"Asia/Shanghai",
    "iso:country":"CN",
    "name:und_x_variant":[
        "\u79cb\u7af9"
    ],
    "wof:name":"Qiuzhu",
    "wof:placetype":"locality"
},
  "geometry": {"coordinates":[119.72029000000001,26.61351],"type":"Point"}
}