{
  "type": "Feature",
  "properties": {
    "gn:admin1_code":"24.0",
    "gn:asciiname":"Shuanma",
    "gn:country_code":"CN",
    "gn:dem":1368,
    "gn:feature_class":"P",
    "gn:feature_code":"PPL",
    "gn:name":"Shuanma",
    "gn:population":0,
    "gn:timezone":"Asia/Shanghai",
    "iso:country":"CN",
    "name:zho_x_preferred":[
        "\u62f4\u9a6c"
    ],
    "wof:name":"Shuanma",
    "wof:placetype":"locality"
},
  "geometry": {"coordinates":[113.29362999999999,36.81471],"type":"Point"}
}