{
  "type": "Feature",
  "properties": {
    "gn:admin1_code":"24.0",
    "gn:asciiname":"Datanliang",
    "gn:country_code":"CN",
    "gn:dem":2005,
    "gn:feature_class":"P",
    "gn:feature_code":"PPL",
    "gn:name":"Datanliang",
    "gn:population":0,
    "gn:timezone":"Asia/Shanghai",
    "iso:country":"CN",
    "name:und_x_variant":[
        "\u5927\u6ee9\u6881"
    ],
    "name:zho_x_preferred":[
        "\u5927\u6ee9\u6881"
    ],
    "wof:name":"Datanliang",
    "wof:placetype":"locality"
},
  "geometry": {"coordinates":[112.95705,39.25232000000001],"type":"Point"}
}