{
  "type": "Feature",
  "properties": {
    "gn:admin1_code":"14.0",
    "gn:asciiname":"Wai'eluoma",
    "gn:country_code":"CN",
    "gn:dem":4652,
    "gn:feature_class":"P",
    "gn:feature_code":"PPL",
    "gn:name":"Wai\u2019eluoma",
    "gn:population":0,
    "gn:timezone":"Asia/Urumqi",
    "iso:country":"CN",
    "name:und_x_variant":[
        "Wai\u2019eluoma"
    ],
    "name:zho_x_preferred":[
        "\u6b6a\u989d\u7f57\u739b"
    ],
    "wof:name":"Wai'eluoma",
    "wof:placetype":"locality"
},
  "geometry": {"coordinates":[85.12869999999999,32.299],"type":"Point"}
}