{
  "type": "Feature",
  "properties": {
    "gn:admin1_code":"12.0",
    "gn:asciiname":"Hehuayuedi",
    "gn:country_code":"CN",
    "gn:dem":39,
    "gn:feature_class":"P",
    "gn:feature_code":"PPL",
    "gn:name":"Hehuayuedi",
    "gn:population":0,
    "gn:timezone":"Asia/Shanghai",
    "iso:country":"CN",
    "name:zho_x_preferred":[
        "\u8377\u82b1\u6708\u5824"
    ],
    "wof:name":"Hehuayuedi",
    "wof:placetype":"locality"
},
  "geometry": {"coordinates":[112.6733,30.56453],"type":"Point"}
}