{
  "type": "Feature",
  "properties": {
    "gn:admin1_code":"3.0",
    "gn:asciiname":"Mashi",
    "gn:country_code":"CN",
    "gn:dem":169,
    "gn:feature_class":"P",
    "gn:feature_code":"PPL",
    "gn:name":"Mashi",
    "gn:population":0,
    "gn:timezone":"Asia/Shanghai",
    "iso:country":"CN",
    "name:fra_x_preferred":[
        "Mashi"
    ],
    "name:hau_x_preferred":[
        "Mashi"
    ],
    "name:ita_x_preferred":[
        "Mashi"
    ],
    "name:spa_x_preferred":[
        "Mashi"
    ],
    "name:zho_x_preferred":[
        "\u9ebb\u77f3"
    ],
    "wof:name":"Mashi",
    "wof:placetype":"locality"
},
  "geometry": {"coordinates":[113.94,27.0893],"type":"Point"}
}