{
  "type": "Feature",
  "properties": {
    "gn:admin1_code":"9.0",
    "gn:asciiname":"Wangsi'an",
    "gn:country_code":"CN",
    "gn:dem":54,
    "gn:feature_class":"P",
    "gn:feature_code":"PPL",
    "gn:name":"Wangsi\u2019an",
    "gn:population":0,
    "gn:timezone":"Asia/Shanghai",
    "iso:country":"CN",
    "name:und_x_variant":[
        "Wangsi\u2019an"
    ],
    "name:zho_x_preferred":[
        "\u738b\u5bfa\u5b89"
    ],
    "wof:name":"Wangsi'an",
    "wof:placetype":"locality"
},
  "geometry": {"coordinates":[114.75360000000001,33.96100999999999],"type":"Point"}
}