{
  "type": "Feature",
  "properties": {
    "gn:admin1_code":"32.0",
    "gn:asciiname":"Yanjiaping",
    "gn:country_code":"CN",
    "gn:dem":1042,
    "gn:feature_class":"P",
    "gn:feature_code":"PPL",
    "gn:name":"Yanjiaping",
    "gn:population":0,
    "gn:timezone":"Asia/Shanghai",
    "iso:country":"CN",
    "name:und_x_variant":[
        "\u96c1\u5bb6\u576a"
    ],
    "wof:name":"Yanjiaping",
    "wof:placetype":"locality"
},
  "geometry": {"coordinates":[106.14767000000001,32.13938],"type":"Point"}
}