{
  "type": "Feature",
  "properties": {
    "gn:admin1_code":"11.0",
    "gn:asciiname":"Wazhai",
    "gn:country_code":"CN",
    "gn:dem":636,
    "gn:feature_class":"P",
    "gn:feature_code":"PPL",
    "gn:name":"Wazhai",
    "gn:population":0,
    "gn:timezone":"Asia/Shanghai",
    "iso:country":"CN",
    "name:zho_x_preferred":[
        "\u74e6\u5be8"
    ],
    "wof:name":"Wazhai",
    "wof:placetype":"locality"
},
  "geometry": {"coordinates":[110.39623,27.15817],"type":"Point"}
}