{
  "type": "Feature",
  "properties": {
    "gn:admin1_code":"9",
    "gn:asciiname":"Huamali",
    "gn:country_code":"CN",
    "gn:dem":51,
    "gn:feature_class":"P",
    "gn:feature_code":"PPL",
    "gn:name":"Huamali",
    "gn:population":0,
    "gn:timezone":"Asia/Shanghai",
    "iso:country":"CN",
    "name:zho_x_preferred":[
        "\u82b1\u9a6c\u674e"
    ],
    "wof:name":"Huamali",
    "wof:placetype":"locality"
},
  "geometry": {"coordinates":[115.26600000000001,34.0498],"type":"Point"}
}