{
  "type": "Feature",
  "properties": {
    "gn:admin1_code":"6.0",
    "gn:asciiname":"Lab",
    "gn:country_code":"CN",
    "gn:dem":3854,
    "gn:feature_class":"P",
    "gn:feature_code":"PPLA4",
    "gn:name":"Lab",
    "gn:population":0,
    "gn:timezone":"Asia/Urumqi",
    "iso:country":"CN",
    "name:bod_x_preferred":[
        "Lab"
    ],
    "name:fra_x_preferred":[
        "Lab"
    ],
    "name:nld_x_preferred":[
        "Lab"
    ],
    "name:nor_x_preferred":[
        "Lab"
    ],
    "name:pol_x_preferred":[
        "Lab"
    ],
    "name:swe_x_preferred":[
        "Lab"
    ],
    "name:und_x_variant":[
        "Labu",
        "Labu Xiang",
        "Lasitong"
    ],
    "name:zho_x_preferred":[
        "\u62c9\u5e03"
    ],
    "name:zho_x_variant":[
        "\u62c9\u5e03\u4e61",
        "\u62c9\u53f8\u901a"
    ],
    "wof:name":"Lab",
    "wof:placetype":"locality"
},
  "geometry": {"coordinates":[97.14169,33.27168],"type":"Point"}
}