{
  "type": "Feature",
  "properties": {
    "gn:admin1_code":"9.0",
    "gn:asciiname":"Xinzhuangpo",
    "gn:country_code":"CN",
    "gn:dem":108,
    "gn:feature_class":"P",
    "gn:feature_code":"PPL",
    "gn:name":"Xinzhuangpo",
    "gn:population":0,
    "gn:timezone":"Asia/Shanghai",
    "iso:country":"CN",
    "name:zho_x_preferred":[
        "\u8f9b\u5e84\u5761"
    ],
    "wof:name":"Xinzhuangpo",
    "wof:placetype":"locality"
},
  "geometry": {"coordinates":[113.68756999999999,34.22053],"type":"Point"}
}