{
  "type": "Feature",
  "properties": {
    "gn:admin1_code":"16.0",
    "gn:asciiname":"Nonglun",
    "gn:country_code":"CN",
    "gn:dem":708,
    "gn:feature_class":"P",
    "gn:feature_code":"PPL",
    "gn:name":"Nonglun",
    "gn:population":0,
    "gn:timezone":"Asia/Shanghai",
    "iso:country":"CN",
    "name:zho_x_preferred":[
        "\u5f04\u4f26"
    ],
    "wof:name":"Nonglun",
    "wof:placetype":"locality"
},
  "geometry": {"coordinates":[107.17400000000001,24.3492],"type":"Point"}
}