{
  "type": "Feature",
  "properties": {
    "gn:admin1_code":"8.0",
    "gn:asciiname":"Deyuancun",
    "gn:country_code":"CN",
    "gn:dem":303,
    "gn:feature_class":"P",
    "gn:feature_code":"PPL",
    "gn:name":"Deyuancun",
    "gn:population":0,
    "gn:timezone":"Asia/Shanghai",
    "iso:country":"CN",
    "name:zho_x_preferred":[
        "\u5fb7\u6e90\u6751"
    ],
    "wof:name":"Deyuancun",
    "wof:placetype":"locality"
},
  "geometry": {"coordinates":[123.01399000000001,47.52633],"type":"Point"}
}