{
  "type": "Feature",
  "properties": {
    "gn:admin1_code":"26.0",
    "gn:asciiname":"Baijia Huochang",
    "gn:country_code":"CN",
    "gn:dem":1191,
    "gn:feature_class":"P",
    "gn:feature_code":"PPL",
    "gn:name":"Baijia Huochang",
    "gn:population":0,
    "gn:timezone":"Asia/Shanghai",
    "iso:country":"CN",
    "name:zho_x_preferred":[
        "\u767d\u5bb6\u4f19\u573a"
    ],
    "wof:name":"Baijia Huochang",
    "wof:placetype":"locality"
},
  "geometry": {"coordinates":[109.575,38.5964],"type":"Point"}
}