{
  "type": "Feature",
  "properties": {
    "gn:admin1_code":"29.0",
    "gn:asciiname":"Ake",
    "gn:country_code":"CN",
    "gn:dem":1087,
    "gn:feature_class":"P",
    "gn:feature_code":"PPL",
    "gn:name":"Ake",
    "gn:population":0,
    "gn:timezone":"Asia/Shanghai",
    "iso:country":"CN",
    "name:deu_x_preferred":[
        "Ak\u00e9"
    ],
    "name:eus_x_preferred":[
        "Ak\u00e9"
    ],
    "name:fra_x_preferred":[
        "Ake"
    ],
    "name:hun_x_preferred":[
        "Ak\u00e9"
    ],
    "name:ita_x_preferred":[
        "Ak\u00e9"
    ],
    "name:mkd_x_preferred":[
        "\u0410\u043a\u0435"
    ],
    "name:spa_x_preferred":[
        "Ak\u00e9"
    ],
    "name:zho_x_preferred":[
        "\u963f\u514b"
    ],
    "wof:name":"Ake",
    "wof:placetype":"locality"
},
  "geometry": {"coordinates":[100.663,21.7701],"type":"Point"}
}