{
  "type": "Feature",
  "properties": {
    "gn:admin1_code":"29.0",
    "gn:asciiname":"Humen",
    "gn:country_code":"CN",
    "gn:dem":1512,
    "gn:feature_class":"P",
    "gn:feature_code":"PPL",
    "gn:name":"Humen",
    "gn:population":0,
    "gn:timezone":"Asia/Shanghai",
    "iso:country":"CN",
    "name:rus_x_preferred":[
        "\u0425\u0443\u043c\u044d\u043d\u044c"
    ],
    "name:zho_x_preferred":[
        "\u6237\u95e8"
    ],
    "wof:name":"Humen",
    "wof:placetype":"locality"
},
  "geometry": {"coordinates":[99.14060000000001,23.4278],"type":"Point"}
}