{
  "type": "Feature",
  "properties": {
    "gn:admin1_code":"25",
    "gn:asciiname":"Dongbijia Yicun",
    "gn:country_code":"CN",
    "gn:dem":7,
    "gn:feature_class":"P",
    "gn:feature_code":"PPL",
    "gn:name":"Dongbijia Yicun",
    "gn:population":0,
    "gn:timezone":"Asia/Shanghai",
    "iso:country":"CN",
    "name:zho_x_preferred":[
        "\u4e1c\u6bd5\u5bb6\u4e00\u6751"
    ],
    "wof:name":"Dongbijia Yicun",
    "wof:placetype":"locality"
},
  "geometry": {"coordinates":[118.94540000000001,36.92975],"type":"Point"}
}