{
  "type": "Feature",
  "properties": {
    "gn:admin1_code":"9.0",
    "gn:asciiname":"Xiaomeigou",
    "gn:country_code":"CN",
    "gn:dem":1314,
    "gn:feature_class":"P",
    "gn:feature_code":"PPL",
    "gn:name":"Xiaomeigou",
    "gn:population":0,
    "gn:timezone":"Asia/Shanghai",
    "iso:country":"CN",
    "name:zho_x_preferred":[
        "\u5c0f\u6ca1\u6c9f"
    ],
    "wof:name":"Xiaomeigou",
    "wof:placetype":"locality"
},
  "geometry": {"coordinates":[111.64772000000001,33.9032],"type":"Point"}
}