{
  "type": "Feature",
  "properties": {
    "gn:admin1_code":"30.0",
    "gn:asciiname":"Ma'ao",
    "gn:country_code":"CN",
    "gn:dem":398,
    "gn:feature_class":"P",
    "gn:feature_code":"PPL",
    "gn:name":"Ma\u2019ao",
    "gn:population":0,
    "gn:timezone":"Asia/Shanghai",
    "iso:country":"CN",
    "name:zho_x_preferred":[
        "Ma\u2019ao"
    ],
    "name:zho_x_variant":[
        "\u9ebb\u5773"
    ],
    "wof:name":"Ma'ao",
    "wof:placetype":"locality"
},
  "geometry": {"coordinates":[112.65694000000001,24.035],"type":"Point"}
}