{
  "type": "Feature",
  "properties": {
    "gn:admin1_code":"14.0",
    "gn:asciiname":"Gamuwangcun",
    "gn:country_code":"CN",
    "gn:dem":4039,
    "gn:feature_class":"P",
    "gn:feature_code":"PPL",
    "gn:name":"Gamuwangcun",
    "gn:population":0,
    "gn:timezone":"Asia/Urumqi",
    "iso:country":"CN",
    "name:zho_x_preferred":[
        "\u560e\u6728\u65fa\u6751"
    ],
    "wof:name":"Gamuwangcun",
    "wof:placetype":"locality"
},
  "geometry": {"coordinates":[94.99061,31.16387000000001],"type":"Point"}
}