{
  "type": "Feature",
  "properties": {
    "gn:admin1_code":"29.0",
    "gn:asciiname":"Dawumulong",
    "gn:country_code":"CN",
    "gn:dem":1627,
    "gn:feature_class":"P",
    "gn:feature_code":"PPL",
    "gn:name":"Dawumulong",
    "gn:population":0,
    "gn:timezone":"Asia/Shanghai",
    "iso:country":"CN",
    "name:zho_x_preferred":[
        "\u5927\u4e4c\u6728\u9f99"
    ],
    "wof:name":"Dawumulong",
    "wof:placetype":"locality"
},
  "geometry": {"coordinates":[100.315,24.8612],"type":"Point"}
}