{
  "type": "Feature",
  "properties": {
    "gn:admin1_code":"19.0",
    "gn:asciiname":"Minjiatun",
    "gn:country_code":"CN",
    "gn:dem":141,
    "gn:feature_class":"P",
    "gn:feature_code":"PPL",
    "gn:name":"Minjiatun",
    "gn:population":0,
    "gn:timezone":"Asia/Shanghai",
    "iso:country":"CN",
    "name:zho_x_preferred":[
        "\u6c11\u5bb6\u5c6f"
    ],
    "wof:name":"Minjiatun",
    "wof:placetype":"locality"
},
  "geometry": {"coordinates":[122.73087,42.62779000000001],"type":"Point"}
}