{
  "type": "Feature",
  "properties": {
    "gn:admin1_code":"14.0",
    "gn:asciiname":"Beini",
    "gn:country_code":"CN",
    "gn:dem":4191,
    "gn:feature_class":"P",
    "gn:feature_code":"PPL",
    "gn:name":"Beini",
    "gn:population":0,
    "gn:timezone":"Asia/Urumqi",
    "iso:country":"CN",
    "name:zho_x_preferred":[
        "\u80cc\u5c3c"
    ],
    "wof:name":"Beini",
    "wof:placetype":"locality"
},
  "geometry": {"coordinates":[92.84977000000001,31.55732],"type":"Point"}
}