{
  "type": "Feature",
  "properties": {
    "gn:admin1_code":"29",
    "gn:asciiname":"Shicaohe",
    "gn:country_code":"CN",
    "gn:dem":2013,
    "gn:feature_class":"P",
    "gn:feature_code":"PPL",
    "gn:name":"Shicaohe",
    "gn:population":0,
    "gn:timezone":"Asia/Shanghai",
    "iso:country":"CN",
    "name:zho_x_preferred":[
        "\u77f3\u69fd\u6cb3"
    ],
    "wof:name":"Shicaohe",
    "wof:placetype":"locality"
},
  "geometry": {"coordinates":[102.411,24.5511],"type":"Point"}
}