{
  "type": "Feature",
  "properties": {
    "gn:admin1_code":"18",
    "gn:asciiname":"Zhangfengwan",
    "gn:country_code":"CN",
    "gn:dem":718,
    "gn:feature_class":"P",
    "gn:feature_code":"PPL",
    "gn:name":"Zhangfengwan",
    "gn:population":0,
    "gn:timezone":"Asia/Shanghai",
    "iso:country":"CN",
    "name:zho_x_preferred":[
        "\u5f20\u51e4\u6e7e"
    ],
    "wof:name":"Zhangfengwan",
    "wof:placetype":"locality"
},
  "geometry": {"coordinates":[107.831,27.5428],"type":"Point"}
}