{
  "type": "Feature",
  "properties": {
    "gn:admin1_code":"11.0",
    "gn:asciiname":"Lishan",
    "gn:country_code":"CN",
    "gn:dem":73,
    "gn:feature_class":"P",
    "gn:feature_code":"PPL",
    "gn:name":"Lishan",
    "gn:population":0,
    "gn:timezone":"Asia/Shanghai",
    "iso:country":"CN",
    "name:zho_x_preferred":[
        "\u6817\u5c71"
    ],
    "wof:name":"Lishan",
    "wof:placetype":"locality"
},
  "geometry": {"coordinates":[113.55728999999999,28.08906],"type":"Point"}
}