{
  "type": "Feature",
  "properties": {
    "gn:admin1_code":"12.0",
    "gn:asciiname":"Chahe",
    "gn:country_code":"CN",
    "gn:dem":25,
    "gn:feature_class":"P",
    "gn:feature_code":"PPLA4",
    "gn:name":"Chahe",
    "gn:population":0,
    "gn:timezone":"Asia/Shanghai",
    "iso:country":"CN",
    "name:ceb_x_preferred":[
        "Chahe"
    ],
    "name:swe_x_preferred":[
        "Chahe"
    ],
    "name:und_x_variant":[
        "Chahe Zhen"
    ],
    "name:zho_x_preferred":[
        "\u6c4a\u6cb3"
    ],
    "name:zho_x_variant":[
        "\u6c4a\u6cb3\u9547"
    ],
    "wof:name":"Chahe",
    "wof:placetype":"locality"
},
  "geometry": {"coordinates":[113.46637,29.99902],"type":"Point"}
}