{
  "type": "Feature",
  "properties": {
    "gn:admin1_code":"30",
    "gn:asciiname":"Puxia",
    "gn:country_code":"CN",
    "gn:dem":218,
    "gn:feature_class":"P",
    "gn:feature_code":"PPL",
    "gn:name":"Puxia",
    "gn:population":0,
    "gn:timezone":"Asia/Shanghai",
    "iso:country":"CN",
    "name:zho_x_preferred":[
        "\u94fa\u4e0b"
    ],
    "wof:name":"Puxia",
    "wof:placetype":"locality"
},
  "geometry": {"coordinates":[115.86837,24.67082000000001],"type":"Point"}
}