{
  "type": "Feature",
  "properties": {
    "gn:admin1_code":"12.0",
    "gn:asciiname":"Baiguo",
    "gn:country_code":"CN",
    "gn:dem":795,
    "gn:feature_class":"P",
    "gn:feature_code":"PPLA4",
    "gn:name":"Baiguo",
    "gn:population":0,
    "gn:timezone":"Asia/Shanghai",
    "iso:country":"CN",
    "name:und_x_variant":[
        "Baiguo Xiang"
    ],
    "name:zho_x_preferred":[
        "\u767d\u679c"
    ],
    "name:zho_x_variant":[
        "\u767d\u679c\u4e61"
    ],
    "wof:name":"Baiguo",
    "wof:placetype":"locality"
},
  "geometry": {"coordinates":[109.33305,30.22773],"type":"Point"}
}