{
  "type": "Feature",
  "properties": {
    "gn:admin1_code":"7.0",
    "gn:asciiname":"Jingdouqian",
    "gn:country_code":"CN",
    "gn:dem":941,
    "gn:feature_class":"P",
    "gn:feature_code":"PPL",
    "gn:name":"Jingdouqian",
    "gn:population":0,
    "gn:timezone":"Asia/Shanghai",
    "iso:country":"CN",
    "name:zho_x_preferred":[
        "\u4e95\u515c\u524d"
    ],
    "wof:name":"Jingdouqian",
    "wof:placetype":"locality"
},
  "geometry": {"coordinates":[118.99733000000001,26.83234],"type":"Point"}
}