{
  "type": "Feature",
  "properties": {
    "gn:admin1_code":"16",
    "gn:asciiname":"Heli",
    "gn:cc2":"CN",
    "gn:country_code":"CN",
    "gn:dem":107,
    "gn:feature_class":"P",
    "gn:feature_code":"PPL",
    "gn:name":"Heli",
    "gn:population":0,
    "gn:timezone":"Asia/Shanghai",
    "iso:country":"CN",
    "name:cat_x_preferred":[
        "Heli"
    ],
    "name:deu_x_preferred":[
        "Heli"
    ],
    "name:fin_x_preferred":[
        "Heli"
    ],
    "name:nld_x_preferred":[
        "Heli"
    ],
    "name:und_x_variant":[
        "Ho-li"
    ],
    "wof:name":"Heli",
    "wof:placetype":"locality"
},
  "geometry": {"coordinates":[108.93333,23.71667],"type":"Point"}
}