{
  "type": "Feature",
  "properties": {
    "gn:admin1_code":"3.0",
    "gn:asciiname":"Laowuchang",
    "gn:country_code":"CN",
    "gn:dem":283,
    "gn:feature_class":"P",
    "gn:feature_code":"PPL",
    "gn:name":"Laowuchang",
    "gn:population":0,
    "gn:timezone":"Asia/Shanghai",
    "iso:country":"CN",
    "name:und_x_variant":[
        "\u8001\u5c4b\u573a"
    ],
    "wof:name":"Laowuchang",
    "wof:placetype":"locality"
},
  "geometry": {"coordinates":[116.22835000000001,26.37622],"type":"Point"}
}