{
  "type": "Feature",
  "properties": {
    "gn:admin1_code":"5.0",
    "gn:asciiname":"Xiaolongguagou",
    "gn:country_code":"CN",
    "gn:dem":596,
    "gn:feature_class":"P",
    "gn:feature_code":"PPL",
    "gn:name":"Xiaolongguagou",
    "gn:population":0,
    "gn:timezone":"Asia/Shanghai",
    "iso:country":"CN",
    "name:und_x_variant":[
        "\u5c0f\u9f99\u74dc\u6c9f"
    ],
    "wof:name":"Xiaolongguagou",
    "wof:placetype":"locality"
},
  "geometry": {"coordinates":[126.02347,41.95464000000001],"type":"Point"}
}