{
  "type": "Feature",
  "properties": {
    "gn:admin1_code":"02",
    "gn:asciiname":"Liutangting",
    "gn:country_code":"CN",
    "gn:dem":10,
    "gn:feature_class":"P",
    "gn:feature_code":"PPLA4",
    "gn:name":"Liutangting",
    "gn:population":0,
    "gn:timezone":"Asia/Shanghai",
    "iso:country":"CN",
    "name:und_x_variant":[
        "\u516d\u5858\u4ead",
        "Chongshou",
        "Chongshou Zhen",
        "\u5d07\u5bff\u9547",
        "\u5d07\u5bff"
    ],
    "wof:name":"Liutangting",
    "wof:placetype":"locality"
},
  "geometry": {"coordinates":[121.26488999999999,30.27588],"type":"Point"}
}