{
  "type": "Feature",
  "properties": {
    "gn:admin1_code":"7.0",
    "gn:asciiname":"Qianling",
    "gn:country_code":"CN",
    "gn:dem":27,
    "gn:feature_class":"P",
    "gn:feature_code":"PPL",
    "gn:name":"Qianling",
    "gn:population":0,
    "gn:timezone":"Asia/Shanghai",
    "iso:country":"CN",
    "name:zho_x_preferred":[
        "\u524d\u5cad"
    ],
    "wof:name":"Qianling",
    "wof:placetype":"locality"
},
  "geometry": {"coordinates":[119.53454000000001,25.46843],"type":"Point"}
}