{
  "type": "Feature",
  "properties": {
    "gn:admin1_code":"29.0",
    "gn:asciiname":"Nixi",
    "gn:country_code":"CN",
    "gn:dem":3154,
    "gn:feature_class":"P",
    "gn:feature_code":"PPL",
    "gn:name":"Nixi",
    "gn:population":0,
    "gn:timezone":"Asia/Shanghai",
    "iso:country":"CN",
    "name:zho_x_preferred":[
        "\u5c3c\u897f"
    ],
    "wof:name":"Nixi",
    "wof:placetype":"locality"
},
  "geometry": {"coordinates":[99.8113,27.4991],"type":"Point"}
}