{
  "type": "Feature",
  "properties": {
    "gn:admin1_code":"9",
    "gn:asciiname":"Mahan",
    "gn:country_code":"CN",
    "gn:dem":54,
    "gn:feature_class":"P",
    "gn:feature_code":"PPL",
    "gn:name":"Mahan",
    "gn:population":0,
    "gn:timezone":"Asia/Shanghai",
    "iso:country":"CN",
    "name:ceb_x_preferred":[
        "Mahan"
    ],
    "name:deu_x_preferred":[
        "Mahan"
    ],
    "name:fra_x_preferred":[
        "Mahan"
    ],
    "name:jpn_x_preferred":[
        "\u30de\u30cf\u30f3"
    ],
    "name:pol_x_preferred":[
        "Mahan"
    ],
    "name:por_x_preferred":[
        "Mahan"
    ],
    "name:rus_x_preferred":[
        "\u041c\u0430\u0445\u0430\u043d"
    ],
    "name:swe_x_preferred":[
        "Mahan"
    ],
    "name:ukr_x_preferred":[
        "\u041c\u0430\u0445\u0430\u043d"
    ],
    "name:zho_x_preferred":[
        "\u9a6c\u97e9"
    ],
    "wof:name":"Mahan",
    "wof:placetype":"locality"
},
  "geometry": {"coordinates":[115.01872,35.90973],"type":"Point"}
}