{
  "type": "Feature",
  "properties": {
    "gn:admin1_code":"9",
    "gn:asciiname":"Mahan",
    "gn:country_code":"CN",
    "gn:dem":54,
    "gn:feature_class":"P",
    "gn:feature_code":"PPL",
    "gn:name":"Mahan",
    "gn:population":0,
    "gn:timezone":"Asia/Shanghai",
    "iso:country":"CN",
    "name:zho_x_preferred":[
        "\u9a6c\u97e9"
    ],
    "wof:name":"Mahan",
    "wof:placetype":"locality"
},
  "geometry": {"coordinates":[115.01872,35.90973],"type":"Point"}
}