{
  "type": "Feature",
  "properties": {
    "gn:admin1_code":"12.0",
    "gn:asciiname":"Sanchakou",
    "gn:country_code":"CN",
    "gn:dem":846,
    "gn:feature_class":"P",
    "gn:feature_code":"PPL",
    "gn:name":"Sanchakou",
    "gn:population":0,
    "gn:timezone":"Asia/Shanghai",
    "iso:country":"CN",
    "name:zho_x_preferred":[
        "\u4e09\u5c94\u53e3"
    ],
    "wof:name":"Sanchakou",
    "wof:placetype":"locality"
},
  "geometry": {"coordinates":[111.13261,31.81444],"type":"Point"}
}