{
  "type": "Feature",
  "properties": {
    "gn:admin1_code":"3.0",
    "gn:asciiname":"Hubaigangwangjia",
    "gn:country_code":"CN",
    "gn:dem":24,
    "gn:feature_class":"P",
    "gn:feature_code":"PPL",
    "gn:name":"Hubaigangwangjia",
    "gn:population":0,
    "gn:timezone":"Asia/Shanghai",
    "iso:country":"CN",
    "name:und_x_variant":[
        "\u864e\u62dc\u5c97\u6c6a\u5bb6"
    ],
    "wof:name":"Hubaigangwangjia",
    "wof:placetype":"locality"
},
  "geometry": {"coordinates":[116.27001,28.40879],"type":"Point"}
}