{
  "type": "Feature",
  "properties": {
    "gn:admin1_code":"5.0",
    "gn:asciiname":"Liudahucun",
    "gn:country_code":"CN",
    "gn:dem":216,
    "gn:feature_class":"P",
    "gn:feature_code":"PPL",
    "gn:name":"Liudahucun",
    "gn:population":0,
    "gn:timezone":"Asia/Shanghai",
    "iso:country":"CN",
    "name:zho_x_preferred":[
        "\u516d\u5927\u6237\u6751"
    ],
    "wof:name":"Liudahucun",
    "wof:placetype":"locality"
},
  "geometry": {"coordinates":[125.79797000000001,45.06542],"type":"Point"}
}