{
  "type": "Feature",
  "properties": {
    "gn:admin1_code":"30.0",
    "gn:asciiname":"Citangli",
    "gn:country_code":"CN",
    "gn:dem":185,
    "gn:feature_class":"P",
    "gn:feature_code":"PPL",
    "gn:name":"Citangli",
    "gn:population":0,
    "gn:timezone":"Asia/Shanghai",
    "iso:country":"CN",
    "name:zho_x_preferred":[
        "Citangli"
    ],
    "name:zho_x_variant":[
        "\u7960\u5802\u91cc"
    ],
    "wof:name":"Citangli",
    "wof:placetype":"locality"
},
  "geometry": {"coordinates":[115.4075,24.17361],"type":"Point"}
}