{
  "type": "Feature",
  "properties": {
    "gn:admin1_code":"25",
    "gn:asciiname":"Dongfuzhuang",
    "gn:country_code":"CN",
    "gn:dem":76,
    "gn:feature_class":"P",
    "gn:feature_code":"PPL",
    "gn:name":"Dongfuzhuang",
    "gn:population":0,
    "gn:timezone":"Asia/Shanghai",
    "iso:country":"CN",
    "name:zho_x_preferred":[
        "\u4e1c\u4f0f\u5e84"
    ],
    "wof:name":"Dongfuzhuang",
    "wof:placetype":"locality"
},
  "geometry": {"coordinates":[116.602,36.1148],"type":"Point"}
}