{
  "type": "Feature",
  "properties": {
    "gn:admin1_code":"32.0",
    "gn:asciiname":"Aladuola",
    "gn:country_code":"CN",
    "gn:dem":4229,
    "gn:feature_class":"P",
    "gn:feature_code":"PPL",
    "gn:name":"Aladuola",
    "gn:population":0,
    "gn:timezone":"Asia/Shanghai",
    "iso:country":"CN",
    "name:zho_x_preferred":[
        "\u963f\u62c9\u591a\u62c9"
    ],
    "wof:name":"Aladuola",
    "wof:placetype":"locality"
},
  "geometry": {"coordinates":[100.764,29.7343],"type":"Point"}
}