{
  "type": "Feature",
  "properties": {
    "gn:admin1_code":"12",
    "gn:asciiname":"Baiyangba",
    "gn:cc2":"CN",
    "gn:country_code":"CN",
    "gn:dem":1157,
    "gn:feature_class":"P",
    "gn:feature_code":"PPL",
    "gn:name":"Baiyangba",
    "gn:population":0,
    "gn:timezone":"Asia/Shanghai",
    "iso:country":"CN",
    "name:und_x_variant":[
        "Pai-yang",
        "Pai-yang-pa",
        "Baiyangba"
    ],
    "wof:name":"Baiyangba",
    "wof:placetype":"locality"
},
  "geometry": {"coordinates":[108.90000000000001,30.46667],"type":"Point"}
}