{
  "type": "Feature",
  "properties": {
    "gn:admin1_code":"12.0",
    "gn:asciiname":"Yangci",
    "gn:country_code":"CN",
    "gn:dem":69,
    "gn:feature_class":"P",
    "gn:feature_code":"PPL",
    "gn:name":"Yangci",
    "gn:population":0,
    "gn:timezone":"Asia/Shanghai",
    "iso:country":"CN",
    "name:zho_x_preferred":[
        "Yangci"
    ],
    "name:zho_x_variant":[
        "\u6768\u7960"
    ],
    "wof:name":"Yangci",
    "wof:placetype":"locality"
},
  "geometry": {"coordinates":[115.22893000000001,30.6108],"type":"Point"}
}