{
  "type": "Feature",
  "properties": {
    "gn:admin1_code":"4.0",
    "gn:asciiname":"Donghuxincun",
    "gn:country_code":"CN",
    "gn:dem":5,
    "gn:feature_class":"P",
    "gn:feature_code":"PPL",
    "gn:name":"Donghuxincun",
    "gn:population":0,
    "gn:timezone":"Asia/Shanghai",
    "iso:country":"CN",
    "name:zho_x_preferred":[
        "\u4e1c\u6d52\u65b0\u6751"
    ],
    "wof:name":"Donghuxincun",
    "wof:placetype":"locality"
},
  "geometry": {"coordinates":[119.93680999999999,32.71576],"type":"Point"}
}