{
  "type": "Feature",
  "properties": {
    "gn:admin1_code":"10",
    "gn:asciiname":"Wudaodong",
    "gn:country_code":"CN",
    "gn:dem":78,
    "gn:feature_class":"P",
    "gn:feature_code":"PPL",
    "gn:name":"Wudaodong",
    "gn:population":0,
    "gn:timezone":"Asia/Shanghai",
    "iso:country":"CN",
    "name:zho_x_preferred":[
        "\u4e94\u9053\u6d1e"
    ],
    "wof:name":"Wudaodong",
    "wof:placetype":"locality"
},
  "geometry": {"coordinates":[117.67331,40.14719],"type":"Point"}
}