{
  "type": "Feature",
  "properties": {
    "gn:admin1_code":"9.0",
    "gn:asciiname":"Guojinggu",
    "gn:country_code":"CN",
    "gn:dem":59,
    "gn:feature_class":"P",
    "gn:feature_code":"PPL",
    "gn:name":"Guojinggu",
    "gn:population":0,
    "gn:timezone":"Asia/Shanghai",
    "iso:country":"CN",
    "name:zho_x_preferred":[
        "\u90ed\u4e95\u56fa"
    ],
    "wof:name":"Guojinggu",
    "wof:placetype":"locality"
},
  "geometry": {"coordinates":[114.58951999999999,35.77486],"type":"Point"}
}