{
  "type": "Feature",
  "properties": {
    "gn:admin1_code":"16.0",
    "gn:asciiname":"Qianglong",
    "gn:country_code":"CN",
    "gn:dem":188,
    "gn:feature_class":"P",
    "gn:feature_code":"PPL",
    "gn:name":"Qianglong",
    "gn:population":0,
    "gn:timezone":"Asia/Shanghai",
    "iso:country":"CN",
    "name:zho_x_preferred":[
        "\u5f3a\u9f99"
    ],
    "wof:name":"Qianglong",
    "wof:placetype":"locality"
},
  "geometry": {"coordinates":[108.645,23.7492],"type":"Point"}
}