{
  "type": "Feature",
  "properties": {
    "gn:admin1_code":"10.0",
    "gn:asciiname":"Beixukou",
    "gn:country_code":"CN",
    "gn:dem":13,
    "gn:feature_class":"P",
    "gn:feature_code":"PPL",
    "gn:name":"Beixukou",
    "gn:population":0,
    "gn:timezone":"Asia/Shanghai",
    "iso:country":"CN",
    "name:zho_x_preferred":[
        "\u5317\u7eea\u53e3"
    ],
    "wof:name":"Beixukou",
    "wof:placetype":"locality"
},
  "geometry": {"coordinates":[115.822,38.5798],"type":"Point"}
}