{
  "type": "Feature",
  "properties": {
    "gn:admin1_code":"7",
    "gn:asciiname":"Xiabiyuan",
    "gn:country_code":"CN",
    "gn:dem":371,
    "gn:feature_class":"P",
    "gn:feature_code":"PPL",
    "gn:name":"Xiabiyuan",
    "gn:population":0,
    "gn:timezone":"Asia/Shanghai",
    "iso:country":"CN",
    "name:zho_x_preferred":[
        "\u4e0b\u58c1\u9662"
    ],
    "wof:name":"Xiabiyuan",
    "wof:placetype":"locality"
},
  "geometry": {"coordinates":[118.8361,25.48131],"type":"Point"}
}