{
  "type": "Feature",
  "properties": {
    "gn:admin1_code":"30.0",
    "gn:asciiname":"Dengxintang",
    "gn:country_code":"CN",
    "gn:dem":178,
    "gn:feature_class":"P",
    "gn:feature_code":"PPL",
    "gn:name":"Dengxintang",
    "gn:population":0,
    "gn:timezone":"Asia/Shanghai",
    "iso:country":"CN",
    "name:zho_x_preferred":[
        "Dengxintang"
    ],
    "name:zho_x_variant":[
        "\u767b\u5fc3\u5858"
    ],
    "wof:name":"Dengxintang",
    "wof:placetype":"locality"
},
  "geometry": {"coordinates":[115.34721999999999,24.10667],"type":"Point"}
}