{
  "type": "Feature",
  "properties": {
    "gn:admin1_code":"10.0",
    "gn:asciiname":"Bijiazhuang",
    "gn:country_code":"CN",
    "gn:dem":1207,
    "gn:feature_class":"P",
    "gn:feature_code":"PPL",
    "gn:name":"Bijiazhuang",
    "gn:population":0,
    "gn:timezone":"Asia/Shanghai",
    "iso:country":"CN",
    "name:zho_x_preferred":[
        "\u6bd5\u5bb6\u5e84"
    ],
    "wof:name":"Bijiazhuang",
    "wof:placetype":"locality"
},
  "geometry": {"coordinates":[114.80119000000001,39.57552],"type":"Point"}
}