{
  "type": "Feature",
  "properties": {
    "gn:admin1_code":"16.0",
    "gn:asciiname":"Jiangzhi",
    "gn:country_code":"CN",
    "gn:dem":265,
    "gn:feature_class":"P",
    "gn:feature_code":"PPL",
    "gn:name":"Jiangzhi",
    "gn:population":0,
    "gn:timezone":"Asia/Shanghai",
    "iso:country":"CN",
    "name:zho_x_preferred":[
        "\u5320\u7eb8"
    ],
    "wof:name":"Jiangzhi",
    "wof:placetype":"locality"
},
  "geometry": {"coordinates":[106.73099999999999,22.1101],"type":"Point"}
}