{
  "type": "Feature",
  "properties": {
    "gn:admin1_code":"18",
    "gn:asciiname":"Changtiankan",
    "gn:country_code":"CN",
    "gn:dem":838,
    "gn:feature_class":"P",
    "gn:feature_code":"PPL",
    "gn:name":"Changtiankan",
    "gn:population":0,
    "gn:timezone":"Asia/Shanghai",
    "iso:country":"CN",
    "name:zho_x_preferred":[
        "\u957f\u7530\u574e"
    ],
    "wof:name":"Changtiankan",
    "wof:placetype":"locality"
},
  "geometry": {"coordinates":[107.753,28.1575],"type":"Point"}
}