{
  "type": "Feature",
  "properties": {
    "gn:admin1_code":"26.0",
    "gn:asciiname":"Luojiapocun",
    "gn:country_code":"CN",
    "gn:dem":529,
    "gn:feature_class":"P",
    "gn:feature_code":"PPL",
    "gn:name":"Luojiapocun",
    "gn:population":0,
    "gn:timezone":"Asia/Shanghai",
    "iso:country":"CN",
    "name:zho_x_preferred":[
        "\u7f57\u5bb6\u5761\u6751"
    ],
    "wof:name":"Luojiapocun",
    "wof:placetype":"locality"
},
  "geometry": {"coordinates":[109.12633,32.55853],"type":"Point"}
}