{
  "type": "Feature",
  "properties": {
    "gn:admin1_code":"16.0",
    "gn:asciiname":"Xiazangdong",
    "gn:country_code":"CN",
    "gn:dem":299,
    "gn:feature_class":"P",
    "gn:feature_code":"PPL",
    "gn:name":"Xiazangdong",
    "gn:population":0,
    "gn:timezone":"Asia/Shanghai",
    "iso:country":"CN",
    "name:zho_x_preferred":[
        "\u4e0b\u846c\u5cd2"
    ],
    "wof:name":"Xiazangdong",
    "wof:placetype":"locality"
},
  "geometry": {"coordinates":[107.896,24.69],"type":"Point"}
}