{
  "type": "Feature",
  "properties": {
    "gn:admin1_code":"19.0",
    "gn:asciiname":"Daposhan",
    "gn:country_code":"CN",
    "gn:dem":340,
    "gn:feature_class":"P",
    "gn:feature_code":"PPL",
    "gn:name":"Daposhan",
    "gn:population":0,
    "gn:timezone":"Asia/Shanghai",
    "iso:country":"CN",
    "name:zho_x_preferred":[
        "\u5927\u8feb\u5c71"
    ],
    "wof:name":"Daposhan",
    "wof:placetype":"locality"
},
  "geometry": {"coordinates":[124.32599999999999,42.1778],"type":"Point"}
}