{
  "type": "Feature",
  "properties": {
    "gn:admin1_code":"26.0",
    "gn:asciiname":"Jiheyuan",
    "gn:country_code":"CN",
    "gn:dem":1108,
    "gn:feature_class":"P",
    "gn:feature_code":"PPL",
    "gn:name":"Jiheyuan",
    "gn:population":0,
    "gn:timezone":"Asia/Shanghai",
    "iso:country":"CN",
    "name:und_x_variant":[
        "\u5409\u548c\u56ed"
    ],
    "wof:name":"Jiheyuan",
    "wof:placetype":"locality"
},
  "geometry": {"coordinates":[106.66288,34.01368],"type":"Point"}
}