{
  "type": "Feature",
  "properties": {
    "gn:admin1_code":"25",
    "gn:asciiname":"Bole",
    "gn:country_code":"CN",
    "gn:dem":46,
    "gn:feature_class":"P",
    "gn:feature_code":"PPL",
    "gn:name":"Bole",
    "gn:population":0,
    "gn:timezone":"Asia/Shanghai",
    "iso:country":"CN",
    "name:ceb_x_preferred":[
        "Bole"
    ],
    "name:deu_x_preferred":[
        "Bole"
    ],
    "name:fra_x_preferred":[
        "Bole"
    ],
    "name:ita_x_preferred":[
        "Bole"
    ],
    "name:nld_x_preferred":[
        "Bole"
    ],
    "name:pol_x_preferred":[
        "Bole"
    ],
    "name:swe_x_preferred":[
        "Bole"
    ],
    "name:wln_x_preferred":[
        "Bole"
    ],
    "wof:name":"Bole",
    "wof:placetype":"locality"
},
  "geometry": {"coordinates":[115.83028,35.00861],"type":"Point"}
}