{
  "type": "Feature",
  "properties": {
    "gn:admin1_code":"32.0",
    "gn:asciiname":"Kezenuo",
    "gn:country_code":"CN",
    "gn:dem":3735,
    "gn:feature_class":"P",
    "gn:feature_code":"PPL",
    "gn:name":"Kezenuo",
    "gn:population":0,
    "gn:timezone":"Asia/Shanghai",
    "iso:country":"CN",
    "name:zho_x_preferred":[
        "\u514b\u5219\u8bfa"
    ],
    "wof:name":"Kezenuo",
    "wof:placetype":"locality"
},
  "geometry": {"coordinates":[100.839,29.1694],"type":"Point"}
}