{
  "type": "Feature",
  "properties": {
    "gn:admin1_code":"29",
    "gn:asciiname":"Sanjianpo",
    "gn:country_code":"CN",
    "gn:dem":1811,
    "gn:feature_class":"P",
    "gn:feature_code":"PPL",
    "gn:name":"Sanjianpo",
    "gn:population":0,
    "gn:timezone":"Asia/Shanghai",
    "iso:country":"CN",
    "name:zho_x_preferred":[
        "\u4e09\u89c1\u5761"
    ],
    "wof:name":"Sanjianpo",
    "wof:placetype":"locality"
},
  "geometry": {"coordinates":[102.68300000000001,23.3807],"type":"Point"}
}