{
  "type": "Feature",
  "properties": {
    "gn:admin1_code":"21.0",
    "gn:asciiname":"Yanjiaping",
    "gn:country_code":"CN",
    "gn:dem":1756,
    "gn:feature_class":"P",
    "gn:feature_code":"PPL",
    "gn:name":"Yanjiaping",
    "gn:population":0,
    "gn:timezone":"Asia/Shanghai",
    "iso:country":"CN",
    "name:und_x_variant":[
        "\u5261\u5bb6\u576a"
    ],
    "name:zho_x_preferred":[
        "\u5261\u5bb6\u576a"
    ],
    "wof:name":"Yanjiaping",
    "wof:placetype":"locality"
},
  "geometry": {"coordinates":[105.83971,35.56775],"type":"Point"}
}