{
  "type": "Feature",
  "properties": {
    "gn:admin1_code":"15.0",
    "gn:asciiname":"Dongpo",
    "gn:country_code":"CN",
    "gn:dem":1951,
    "gn:feature_class":"P",
    "gn:feature_code":"PPL",
    "gn:name":"Dongpo",
    "gn:population":0,
    "gn:timezone":"Asia/Shanghai",
    "iso:country":"CN",
    "name:deu_x_preferred":[
        "Dongpo"
    ],
    "name:fra_x_preferred":[
        "Dongpo"
    ],
    "name:zho_x_preferred":[
        "\u4e1c\u5761"
    ],
    "wof:name":"Dongpo",
    "wof:placetype":"locality"
},
  "geometry": {"coordinates":[105.07899999999999,36.22],"type":"Point"}
}