{
  "type": "Feature",
  "properties": {
    "gn:admin1_code":"32.0",
    "gn:asciiname":"Zuowucun",
    "gn:country_code":"CN",
    "gn:dem":3467,
    "gn:feature_class":"P",
    "gn:feature_code":"PPL",
    "gn:name":"Zuowucun",
    "gn:population":0,
    "gn:timezone":"Asia/Shanghai",
    "iso:country":"CN",
    "name:zho_x_preferred":[
        "\u4f5c\u4e94\u6751"
    ],
    "wof:name":"Zuowucun",
    "wof:placetype":"locality"
},
  "geometry": {"coordinates":[100.083,30.407],"type":"Point"}
}