{
  "type": "Feature",
  "properties": {
    "gn:admin1_code":"1.0",
    "gn:asciiname":"Xiaxidi",
    "gn:country_code":"CN",
    "gn:dem":348,
    "gn:feature_class":"P",
    "gn:feature_code":"PPL",
    "gn:name":"Xiaxidi",
    "gn:population":0,
    "gn:timezone":"Asia/Shanghai",
    "iso:country":"CN",
    "name:zho_x_preferred":[
        "\u4e0b\u83e5\u837b"
    ],
    "wof:name":"Xiaxidi",
    "wof:placetype":"locality"
},
  "geometry": {"coordinates":[117.98992,30.52645],"type":"Point"}
}