{
  "type": "Feature",
  "properties": {
    "gn:admin1_code":"5.0",
    "gn:asciiname":"Qigeding",
    "gn:country_code":"CN",
    "gn:dem":196,
    "gn:feature_class":"P",
    "gn:feature_code":"PPL",
    "gn:name":"Qigeding",
    "gn:population":0,
    "gn:timezone":"Asia/Shanghai",
    "iso:country":"CN",
    "name:und_x_variant":[
        "\u4e03\u4e2a\u9876"
    ],
    "wof:name":"Qigeding",
    "wof:placetype":"locality"
},
  "geometry": {"coordinates":[125.73645,40.91416],"type":"Point"}
}