{
  "type": "Feature",
  "properties": {
    "gn:admin1_code":"19.0",
    "gn:asciiname":"Gaozhangzi",
    "gn:country_code":"CN",
    "gn:dem":351,
    "gn:feature_class":"P",
    "gn:feature_code":"PPL",
    "gn:name":"Gaozhangzi",
    "gn:population":0,
    "gn:timezone":"Asia/Shanghai",
    "iso:country":"CN",
    "name:zho_x_preferred":[
        "\u9ad8\u6756\u5b50"
    ],
    "wof:name":"Gaozhangzi",
    "wof:placetype":"locality"
},
  "geometry": {"coordinates":[120.34128,41.78998],"type":"Point"}
}