{
  "type": "Feature",
  "properties": {
    "gn:admin1_code":"32.0",
    "gn:asciiname":"Budong",
    "gn:country_code":"CN",
    "gn:dem":3968,
    "gn:feature_class":"P",
    "gn:feature_code":"PPL",
    "gn:name":"Budong",
    "gn:population":0,
    "gn:timezone":"Asia/Shanghai",
    "iso:country":"CN",
    "name:zho_x_preferred":[
        "\u4e0d\u4e1c"
    ],
    "wof:name":"Budong",
    "wof:placetype":"locality"
},
  "geometry": {"coordinates":[98.8994,31.7224],"type":"Point"}
}