{
  "type": "Feature",
  "properties": {
    "gn:admin1_code":"14.0",
    "gn:asciiname":"Xiongguo",
    "gn:country_code":"CN",
    "gn:dem":4325,
    "gn:feature_class":"P",
    "gn:feature_code":"PPL",
    "gn:name":"Xiongguo",
    "gn:population":0,
    "gn:timezone":"Asia/Urumqi",
    "iso:country":"CN",
    "name:zho_x_preferred":[
        "\u96c4\u679c"
    ],
    "wof:name":"Xiongguo",
    "wof:placetype":"locality"
},
  "geometry": {"coordinates":[93.83011,31.23454000000001],"type":"Point"}
}