{
  "type": "Feature",
  "properties": {
    "gn:admin1_code":"1.0",
    "gn:asciiname":"Huazhuangcun",
    "gn:country_code":"CN",
    "gn:dem":46,
    "gn:feature_class":"P",
    "gn:feature_code":"PPL",
    "gn:name":"Huazhuangcun",
    "gn:population":0,
    "gn:timezone":"Asia/Shanghai",
    "iso:country":"CN",
    "name:zho_x_preferred":[
        "\u82b1\u5e84\u6751"
    ],
    "wof:name":"Huazhuangcun",
    "wof:placetype":"locality"
},
  "geometry": {"coordinates":[116.88733999999999,34.39708],"type":"Point"}
}