{
  "type": "Feature",
  "properties": {
    "gn:admin1_code":"16.0",
    "gn:asciiname":"Tuoxin",
    "gn:country_code":"CN",
    "gn:dem":855,
    "gn:feature_class":"P",
    "gn:feature_code":"PPL",
    "gn:name":"Tuoxin",
    "gn:population":0,
    "gn:timezone":"Asia/Shanghai",
    "iso:country":"CN",
    "name:zho_x_preferred":[
        "\u9a6e\u4fe1"
    ],
    "wof:name":"Tuoxin",
    "wof:placetype":"locality"
},
  "geometry": {"coordinates":[106.23,23.4397],"type":"Point"}
}