{
  "type": "Feature",
  "properties": {
    "gn:admin1_code":"18",
    "gn:asciiname":"Fanjia Wuji",
    "gn:country_code":"CN",
    "gn:dem":752,
    "gn:feature_class":"P",
    "gn:feature_code":"PPL",
    "gn:name":"Fanjia Wuji",
    "gn:population":0,
    "gn:timezone":"Asia/Shanghai",
    "iso:country":"CN",
    "name:zho_x_preferred":[
        "\u8303\u5bb6\u5c4b\u57fa"
    ],
    "wof:name":"Fanjia Wuji",
    "wof:placetype":"locality"
},
  "geometry": {"coordinates":[107.32599999999999,28.165],"type":"Point"}
}