{
  "type": "Feature",
  "properties": {
    "gn:admin1_code":"30.0",
    "gn:asciiname":"Jilongpu",
    "gn:country_code":"CN",
    "gn:dem":287,
    "gn:feature_class":"P",
    "gn:feature_code":"PPL",
    "gn:name":"Jilongpu",
    "gn:population":0,
    "gn:timezone":"Asia/Shanghai",
    "iso:country":"CN",
    "name:zho_x_preferred":[
        "\u9e21\u7b3c\u94fa"
    ],
    "wof:name":"Jilongpu",
    "wof:placetype":"locality"
},
  "geometry": {"coordinates":[113.69253999999999,24.53337],"type":"Point"}
}