{
  "type": "Feature",
  "properties": {
    "gn:admin1_code":"11.0",
    "gn:asciiname":"Yangmaotan",
    "gn:country_code":"CN",
    "gn:dem":83,
    "gn:feature_class":"P",
    "gn:feature_code":"PPL",
    "gn:name":"Yangmaotan",
    "gn:population":0,
    "gn:timezone":"Asia/Shanghai",
    "iso:country":"CN",
    "name:zho_x_preferred":[
        "Yangmaotan"
    ],
    "name:zho_x_variant":[
        "\u7f8a\u6bdb\u6ee9"
    ],
    "wof:name":"Yangmaotan",
    "wof:placetype":"locality"
},
  "geometry": {"coordinates":[111.39096000000001,29.2834],"type":"Point"}
}