{
  "type": "Feature",
  "properties": {
    "gn:admin1_code":"15.0",
    "gn:asciiname":"Xincheng",
    "gn:country_code":"CN",
    "gn:dem":1367,
    "gn:feature_class":"P",
    "gn:feature_code":"PPL",
    "gn:name":"Xincheng",
    "gn:population":0,
    "gn:timezone":"Asia/Shanghai",
    "iso:country":"CN",
    "name:zho_x_preferred":[
        "\u65b0\u57ce"
    ],
    "wof:name":"Xincheng",
    "wof:placetype":"locality"
},
  "geometry": {"coordinates":[107.34999999999999,35.5875],"type":"Point"}
}