{
  "type": "Feature",
  "properties": {
    "gn:admin1_code":"14.0",
    "gn:asciiname":"Laweijia Xingdongre",
    "gn:country_code":"CN",
    "gn:dem":2451,
    "gn:feature_class":"P",
    "gn:feature_code":"PPL",
    "gn:name":"Laweijia Xingdongre",
    "gn:population":0,
    "gn:timezone":"Asia/Urumqi",
    "iso:country":"CN",
    "name:zho_x_preferred":[
        "\u62c9\u7ef4\u52a0\u5174\u4e1c\u70ed"
    ],
    "wof:name":"Laweijia Xingdongre",
    "wof:placetype":"locality"
},
  "geometry": {"coordinates":[94.88299000000001,30.0027],"type":"Point"}
}