{
  "type": "Feature",
  "properties": {
    "gn:admin1_code":"24.0",
    "gn:asciiname":"Xunzhen",
    "gn:cc2":"CN",
    "gn:country_code":"CN",
    "gn:dem":863,
    "gn:feature_class":"P",
    "gn:feature_code":"PPL",
    "gn:name":"Xunzhen",
    "gn:population":0,
    "gn:timezone":"Asia/Shanghai",
    "iso:country":"CN",
    "name:und_x_variant":[
        "Ho-ch\u2019\u00fc",
        "Hs\u00fcn-chen",
        "Ho-ch\u2019\u00fc-hsien",
        "Hs\u00fcn-chien-ssu",
        "Xunzhen"
    ],
    "wof:name":"Xunzhen",
    "wof:placetype":"locality"
},
  "geometry": {"coordinates":[111.25221999999999,39.29667],"type":"Point"}
}