{
  "type": "Feature",
  "properties": {
    "gn:admin1_code":"1.0",
    "gn:asciiname":"Kongdiancun",
    "gn:country_code":"CN",
    "gn:dem":48,
    "gn:feature_class":"P",
    "gn:feature_code":"PPL",
    "gn:name":"Kongdiancun",
    "gn:population":0,
    "gn:timezone":"Asia/Shanghai",
    "iso:country":"CN",
    "name:zho_x_preferred":[
        "\u5b54\u5e97\u6751"
    ],
    "wof:name":"Kongdiancun",
    "wof:placetype":"locality"
},
  "geometry": {"coordinates":[116.42309,31.78098],"type":"Point"}
}