{
  "type": "Feature",
  "properties": {
    "gn:admin1_code":"29.0",
    "gn:asciiname":"Tazhakou",
    "gn:country_code":"CN",
    "gn:dem":1320,
    "gn:feature_class":"P",
    "gn:feature_code":"PPL",
    "gn:name":"Tazhakou",
    "gn:population":0,
    "gn:timezone":"Asia/Shanghai",
    "iso:country":"CN",
    "name:zho_x_preferred":[
        "\u4ed6\u672d\u53e3"
    ],
    "wof:name":"Tazhakou",
    "wof:placetype":"locality"
},
  "geometry": {"coordinates":[103.241,23.4685],"type":"Point"}
}