{
  "type": "Feature",
  "properties": {
    "gn:admin1_code":"32.0",
    "gn:asciiname":"Xiuzigou",
    "gn:country_code":"CN",
    "gn:dem":2635,
    "gn:feature_class":"P",
    "gn:feature_code":"PPL",
    "gn:name":"Xiuzigou",
    "gn:population":0,
    "gn:timezone":"Asia/Shanghai",
    "iso:country":"CN",
    "name:zho_x_preferred":[
        "\u4fee\u5b50\u6c9f"
    ],
    "wof:name":"Xiuzigou",
    "wof:placetype":"locality"
},
  "geometry": {"coordinates":[102.49299999999999,27.6043],"type":"Point"}
}