{
  "type": "Feature",
  "properties": {
    "gn:admin1_code":"16.0",
    "gn:asciiname":"Guligou",
    "gn:country_code":"CN",
    "gn:dem":1071,
    "gn:feature_class":"P",
    "gn:feature_code":"PPL",
    "gn:name":"Guligou",
    "gn:population":0,
    "gn:timezone":"Asia/Shanghai",
    "iso:country":"CN",
    "name:zho_x_preferred":[
        "\u8c37\u91cc\u6c9f"
    ],
    "wof:name":"Guligou",
    "wof:placetype":"locality"
},
  "geometry": {"coordinates":[106.508,24.7007],"type":"Point"}
}