{
  "type": "Feature",
  "properties": {
    "gn:admin1_code":"4.0",
    "gn:asciiname":"Sunzhuang",
    "gn:country_code":"CN",
    "gn:dem":6,
    "gn:feature_class":"P",
    "gn:feature_code":"PPLA4",
    "gn:name":"Sunzhuang",
    "gn:population":0,
    "gn:timezone":"Asia/Shanghai",
    "iso:country":"CN",
    "name:und_x_variant":[
        "Sunzhuang Zhen"
    ],
    "name:zho_x_preferred":[
        "\u5b59\u5e84"
    ],
    "name:zho_x_variant":[
        "\u5b59\u5e84\u9547"
    ],
    "wof:name":"Sunzhuang",
    "wof:placetype":"locality"
},
  "geometry": {"coordinates":[120.39236,32.43834],"type":"Point"}
}