{
  "type": "Feature",
  "properties": {
    "gn:admin1_code":"29.0",
    "gn:asciiname":"Yagong",
    "gn:country_code":"CN",
    "gn:dem":2866,
    "gn:feature_class":"P",
    "gn:feature_code":"PPL",
    "gn:name":"Yagong",
    "gn:population":0,
    "gn:timezone":"Asia/Shanghai",
    "iso:country":"CN",
    "name:zho_x_preferred":[
        "\u4e9a\u8d21"
    ],
    "wof:name":"Yagong",
    "wof:placetype":"locality"
},
  "geometry": {"coordinates":[98.74639999999999,28.5984],"type":"Point"}
}