{
  "type": "Feature",
  "properties": {
    "gn:admin1_code":"12.0",
    "gn:asciiname":"Yumen",
    "gn:country_code":"CN",
    "gn:dem":27,
    "gn:feature_class":"P",
    "gn:feature_code":"PPL",
    "gn:name":"Yumen",
    "gn:population":0,
    "gn:timezone":"Asia/Shanghai",
    "iso:country":"CN",
    "name:ceb_x_preferred":[
        "Yumen"
    ],
    "name:zho_x_preferred":[
        "\u4f59\u95e8"
    ],
    "wof:name":"Yumen",
    "wof:placetype":"locality"
},
  "geometry": {"coordinates":[113.82543,30.4835],"type":"Point"}
}