{
  "type": "Feature",
  "properties": {
    "gn:admin1_code":"16.0",
    "gn:asciiname":"Xinduping",
    "gn:country_code":"CN",
    "gn:dem":293,
    "gn:feature_class":"P",
    "gn:feature_code":"PPL",
    "gn:name":"Xinduping",
    "gn:population":0,
    "gn:timezone":"Asia/Shanghai",
    "iso:country":"CN",
    "name:zho_x_preferred":[
        "\u65b0\u6e21\u576a"
    ],
    "wof:name":"Xinduping",
    "wof:placetype":"locality"
},
  "geometry": {"coordinates":[110.996,24.7669],"type":"Point"}
}