{
  "type": "Feature",
  "properties": {
    "gn:admin1_code":"1.0",
    "gn:asciiname":"Xuejicun",
    "gn:country_code":"CN",
    "gn:dem":47,
    "gn:feature_class":"P",
    "gn:feature_code":"PPL",
    "gn:name":"Xuejicun",
    "gn:population":0,
    "gn:timezone":"Asia/Shanghai",
    "iso:country":"CN",
    "name:zho_x_preferred":[
        "\u859b\u96c6\u6751"
    ],
    "wof:name":"Xuejicun",
    "wof:placetype":"locality"
},
  "geometry": {"coordinates":[117.6478,32.05665],"type":"Point"}
}