{
  "type": "Feature",
  "properties": {
    "gn:admin1_code":"32.0",
    "gn:asciiname":"Chenjiaba",
    "gn:country_code":"CN",
    "gn:dem":398,
    "gn:feature_class":"P",
    "gn:feature_code":"PPL",
    "gn:name":"Chenjiaba",
    "gn:population":0,
    "gn:timezone":"Asia/Shanghai",
    "iso:country":"CN",
    "name:zho_x_preferred":[
        "\u9648\u5bb6\u575d"
    ],
    "wof:name":"Chenjiaba",
    "wof:placetype":"locality"
},
  "geometry": {"coordinates":[104.50657,30.12746],"type":"Point"}
}