{
  "type": "Feature",
  "properties": {
    "gn:admin1_code":"14.0",
    "gn:asciiname":"Shahuo",
    "gn:country_code":"CN",
    "gn:dem":3398,
    "gn:feature_class":"P",
    "gn:feature_code":"PPL",
    "gn:name":"Shahuo",
    "gn:population":0,
    "gn:timezone":"Asia/Urumqi",
    "iso:country":"CN",
    "name:zho_x_preferred":[
        "\u6c99\u706b"
    ],
    "wof:name":"Shahuo",
    "wof:placetype":"locality"
},
  "geometry": {"coordinates":[97.41755000000001,29.63399],"type":"Point"}
}