{
  "type": "Feature",
  "properties": {
    "gn:admin1_code":"31.0",
    "gn:asciiname":"Jiarong",
    "gn:country_code":"CN",
    "gn:dem":23,
    "gn:feature_class":"P",
    "gn:feature_code":"PPL",
    "gn:name":"Jiarong",
    "gn:population":0,
    "gn:timezone":"Asia/Shanghai",
    "iso:country":"CN",
    "name:zho_x_preferred":[
        "\u52a0\u8363"
    ],
    "wof:name":"Jiarong",
    "wof:placetype":"locality"
},
  "geometry": {"coordinates":[110.45278,19.01922],"type":"Point"}
}