{
  "type": "Feature",
  "properties": {
    "gn:admin1_code":"20.0",
    "gn:asciiname":"Zhimulun Erdui",
    "gn:country_code":"CN",
    "gn:dem":291,
    "gn:feature_class":"P",
    "gn:feature_code":"PPLF",
    "gn:name":"Zhimulun Erdui",
    "gn:population":0,
    "gn:timezone":"Asia/Shanghai",
    "iso:country":"CN",
    "name:zho_x_preferred":[
        "\u77e5\u6728\u4f26\u4e8c\u961f"
    ],
    "wof:name":"Zhimulun Erdui",
    "wof:placetype":"locality"
},
  "geometry": {"coordinates":[123.26712000000001,48.30057],"type":"Point"}
}