{
  "type": "Feature",
  "properties": {
    "gn:admin1_code":"29.0",
    "gn:asciiname":"Niushizhai",
    "gn:country_code":"CN",
    "gn:dem":1392,
    "gn:feature_class":"P",
    "gn:feature_code":"PPL",
    "gn:name":"Niushizhai",
    "gn:population":0,
    "gn:timezone":"Asia/Shanghai",
    "iso:country":"CN",
    "name:zho_x_preferred":[
        "\u725b\u5c4e\u5be8"
    ],
    "wof:name":"Niushizhai",
    "wof:placetype":"locality"
},
  "geometry": {"coordinates":[103.02200000000001,23.2703],"type":"Point"}
}