{
  "type": "Feature",
  "properties": {
    "gn:admin1_code":"4.0",
    "gn:asciiname":"Dexingzudi",
    "gn:country_code":"CN",
    "gn:dem":2,
    "gn:feature_class":"P",
    "gn:feature_code":"PPL",
    "gn:name":"Dexingzudi",
    "gn:population":0,
    "gn:timezone":"Asia/Shanghai",
    "iso:country":"CN",
    "name:zho_x_preferred":[
        "Dexingzudi"
    ],
    "name:zho_x_variant":[
        "\u5fb7\u5174\u79df\u5730"
    ],
    "wof:name":"Dexingzudi",
    "wof:placetype":"locality"
},
  "geometry": {"coordinates":[119.598,34.27595],"type":"Point"}
}