{
  "type": "Feature",
  "properties": {
    "gn:admin1_code":"30.0",
    "gn:asciiname":"Xibaotian",
    "gn:country_code":"CN",
    "gn:dem":198,
    "gn:feature_class":"P",
    "gn:feature_code":"PPL",
    "gn:name":"Xibaotian",
    "gn:population":0,
    "gn:timezone":"Asia/Shanghai",
    "iso:country":"CN",
    "name:zho_x_preferred":[
        "\u7ec6\u5b9d\u7530"
    ],
    "wof:name":"Xibaotian",
    "wof:placetype":"locality"
},
  "geometry": {"coordinates":[112.19253,22.52281],"type":"Point"}
}