{
  "type": "Feature",
  "properties": {
    "gn:admin1_code":"32.0",
    "gn:asciiname":"Yunli",
    "gn:country_code":"CN",
    "gn:dem":767,
    "gn:feature_class":"P",
    "gn:feature_code":"PPL",
    "gn:name":"Yunli",
    "gn:population":0,
    "gn:timezone":"Asia/Shanghai",
    "iso:country":"CN",
    "name:tha_x_preferred":[
        "\u0e2d\u0e34\u0e49\u0e19\u0e2b\u0e25\u0e35\u0e48"
    ],
    "name:vie_x_preferred":[
        "D\u1eadn L\u1ec5"
    ],
    "name:zho_x_preferred":[
        "\u4e91\u91cc"
    ],
    "wof:name":"Yunli",
    "wof:placetype":"locality"
},
  "geometry": {"coordinates":[104.54600000000001,31.8817],"type":"Point"}
}