{
  "type": "Feature",
  "properties": {
    "gn:admin1_code":"11.0",
    "gn:asciiname":"Huangyoudong",
    "gn:country_code":"CN",
    "gn:dem":600,
    "gn:feature_class":"P",
    "gn:feature_code":"PPL",
    "gn:name":"Huangyoudong",
    "gn:population":0,
    "gn:timezone":"Asia/Shanghai",
    "iso:country":"CN",
    "name:zho_x_preferred":[
        "\u9ec4\u6709\u6d1e"
    ],
    "wof:name":"Huangyoudong",
    "wof:placetype":"locality"
},
  "geometry": {"coordinates":[110.592,27.41046],"type":"Point"}
}