{
  "type": "Feature",
  "properties": {
    "gn:admin1_code":"2.0",
    "gn:asciiname":"Weicun",
    "gn:country_code":"CN",
    "gn:dem":162,
    "gn:feature_class":"P",
    "gn:feature_code":"PPL",
    "gn:name":"Weicun",
    "gn:population":0,
    "gn:timezone":"Asia/Shanghai",
    "iso:country":"CN",
    "name:zho_x_preferred":[
        "\u5c09\u6751"
    ],
    "wof:name":"Weicun",
    "wof:placetype":"locality"
},
  "geometry": {"coordinates":[120.56049,29.80109],"type":"Point"}
}