{
  "type": "Feature",
  "properties": {
    "gn:admin1_code":"5.0",
    "gn:asciiname":"Duanjicun",
    "gn:country_code":"CN",
    "gn:dem":217,
    "gn:feature_class":"P",
    "gn:feature_code":"PPL",
    "gn:name":"Duanjicun",
    "gn:population":0,
    "gn:timezone":"Asia/Shanghai",
    "iso:country":"CN",
    "name:zho_x_preferred":[
        "\u6bb5\u5409\u6751"
    ],
    "wof:name":"Duanjicun",
    "wof:placetype":"locality"
},
  "geometry": {"coordinates":[126.62138,43.74821],"type":"Point"}
}