{
  "type": "Feature",
  "properties": {
    "gn:admin1_code":"18",
    "gn:asciiname":"Xinmao",
    "gn:country_code":"CN",
    "gn:dem":1520,
    "gn:feature_class":"P",
    "gn:feature_code":"PPL",
    "gn:name":"Xinmao",
    "gn:population":0,
    "gn:timezone":"Asia/Shanghai",
    "iso:country":"CN",
    "name:zho_x_preferred":[
        "\u65b0\u732b"
    ],
    "wof:name":"Xinmao",
    "wof:placetype":"locality"
},
  "geometry": {"coordinates":[105.38200000000001,26.7591],"type":"Point"}
}