{
  "type": "Feature",
  "properties": {
    "gn:admin1_code":"1.0",
    "gn:asciiname":"Xigaocun",
    "gn:country_code":"CN",
    "gn:dem":52,
    "gn:feature_class":"P",
    "gn:feature_code":"PPL",
    "gn:name":"Xigaocun",
    "gn:population":0,
    "gn:timezone":"Asia/Shanghai",
    "iso:country":"CN",
    "name:und_x_variant":[
        "Hsi-kao-tien",
        "Xigaodian",
        "Xigao",
        "Xigaocun"
    ],
    "name:zho_x_preferred":[
        "\u897f\u768b\u6751"
    ],
    "wof:name":"Xigaocun",
    "wof:placetype":"locality"
},
  "geometry": {"coordinates":[116.10272999999999,31.98518],"type":"Point"}
}