{
  "type": "Feature",
  "properties": {
    "gn:admin1_code":"9",
    "gn:asciiname":"Gezhenyuan",
    "gn:country_code":"CN",
    "gn:dem":51,
    "gn:feature_class":"P",
    "gn:feature_code":"PPL",
    "gn:name":"Gezhenyuan",
    "gn:population":0,
    "gn:timezone":"Asia/Shanghai",
    "iso:country":"CN",
    "name:zho_x_preferred":[
        "\u683c\u9488\u56ed"
    ],
    "wof:name":"Gezhenyuan",
    "wof:placetype":"locality"
},
  "geometry": {"coordinates":[115.33053,35.82793],"type":"Point"}
}