{
  "type": "Feature",
  "properties": {
    "gn:admin1_code":"14.0",
    "gn:asciiname":"Zhuozha",
    "gn:country_code":"CN",
    "gn:dem":5133,
    "gn:feature_class":"P",
    "gn:feature_code":"PPL",
    "gn:name":"Zhuozha",
    "gn:population":0,
    "gn:timezone":"Asia/Urumqi",
    "iso:country":"CN",
    "name:zho_x_preferred":[
        "\u5353\u6e23"
    ],
    "wof:name":"Zhuozha",
    "wof:placetype":"locality"
},
  "geometry": {"coordinates":[86.15649999999999,31.3304],"type":"Point"}
}