{
  "type": "Feature",
  "properties": {
    "gn:admin1_code":"30.0",
    "gn:asciiname":"Weidi",
    "gn:country_code":"CN",
    "gn:dem":51,
    "gn:feature_class":"P",
    "gn:feature_code":"PPLA4",
    "gn:name":"Weidi",
    "gn:population":0,
    "gn:timezone":"Asia/Shanghai",
    "iso:country":"CN",
    "name:und_x_variant":[
        "Wei-ti-hs\u00fc",
        "Wei-ti",
        "Weidi",
        "Weidi Zhen",
        "\u56f4\u5e95\u9547"
    ],
    "name:zho_x_preferred":[
        "\u56f4\u5e95"
    ],
    "wof:name":"Weidi",
    "wof:placetype":"locality"
},
  "geometry": {"coordinates":[111.66667,22.71328],"type":"Point"}
}