{
  "type": "Feature",
  "properties": {
    "gn:admin1_code":"16.0",
    "gn:asciiname":"Danan",
    "gn:country_code":"CN",
    "gn:dem":308,
    "gn:feature_class":"P",
    "gn:feature_code":"PPL",
    "gn:name":"Danan",
    "gn:population":0,
    "gn:timezone":"Asia/Shanghai",
    "iso:country":"CN",
    "name:hun_x_preferred":[
        "Danan"
    ],
    "name:ita_x_preferred":[
        "Danan"
    ],
    "name:zho_x_preferred":[
        "\u5927\u96be"
    ],
    "wof:name":"Danan",
    "wof:placetype":"locality"
},
  "geometry": {"coordinates":[109.111,25.0929],"type":"Point"}
}