{
  "type": "Feature",
  "properties": {
    "gn:admin1_code":"21.0",
    "gn:asciiname":"Ganchengzi",
    "gn:country_code":"CN",
    "gn:dem":1163,
    "gn:feature_class":"P",
    "gn:feature_code":"PPL",
    "gn:name":"Ganchengzi",
    "gn:population":0,
    "gn:timezone":"Asia/Shanghai",
    "iso:country":"CN",
    "name:zho_x_preferred":[
        "\u7518\u57ce\u5b50"
    ],
    "wof:name":"Ganchengzi",
    "wof:placetype":"locality"
},
  "geometry": {"coordinates":[105.937,38.1269],"type":"Point"}
}