{
  "type": "Feature",
  "properties": {
    "gn:admin1_code":"16.0",
    "gn:asciiname":"Xiadiling",
    "gn:country_code":"CN",
    "gn:dem":43,
    "gn:feature_class":"P",
    "gn:feature_code":"PPL",
    "gn:name":"Xiadiling",
    "gn:population":0,
    "gn:timezone":"Asia/Shanghai",
    "iso:country":"CN",
    "name:zho_x_preferred":[
        "\u4e0b\u4f4e\u5cad"
    ],
    "wof:name":"Xiadiling",
    "wof:placetype":"locality"
},
  "geometry": {"coordinates":[109.64100000000001,22.0064],"type":"Point"}
}