{
  "type": "Feature",
  "properties": {
    "gn:admin1_code":"18",
    "gn:asciiname":"Xuetang Yuanzi",
    "gn:country_code":"CN",
    "gn:dem":1221,
    "gn:feature_class":"P",
    "gn:feature_code":"PPL",
    "gn:name":"Xuetang Yuanzi",
    "gn:population":0,
    "gn:timezone":"Asia/Shanghai",
    "iso:country":"CN",
    "name:zho_x_preferred":[
        "\u5b66\u5802\u9662\u5b50"
    ],
    "wof:name":"Xuetang Yuanzi",
    "wof:placetype":"locality"
},
  "geometry": {"coordinates":[107.074,28.1319],"type":"Point"}
}