{
  "type": "Feature",
  "properties": {
    "gn:admin1_code":"29.0",
    "gn:asciiname":"Amihe",
    "gn:country_code":"CN",
    "gn:dem":1681,
    "gn:feature_class":"P",
    "gn:feature_code":"PPL",
    "gn:name":"Amihe",
    "gn:population":0,
    "gn:timezone":"Asia/Shanghai",
    "iso:country":"CN",
    "name:zho_x_preferred":[
        "\u963f\u5bc6\u6cb3"
    ],
    "wof:name":"Amihe",
    "wof:placetype":"locality"
},
  "geometry": {"coordinates":[98.64360000000001,24.1945],"type":"Point"}
}