{
  "type": "Feature",
  "properties": {
    "gn:admin1_code":"32.0",
    "gn:asciiname":"Huangjin",
    "gn:country_code":"CN",
    "gn:dem":366,
    "gn:feature_class":"P",
    "gn:feature_code":"PPL",
    "gn:name":"Huangjin",
    "gn:population":0,
    "gn:timezone":"Asia/Shanghai",
    "iso:country":"CN",
    "name:ceb_x_preferred":[
        "Huangjin"
    ],
    "name:swe_x_preferred":[
        "Huangjin"
    ],
    "name:zho_x_preferred":[
        "\u9ec4\u91d1"
    ],
    "wof:name":"Huangjin",
    "wof:placetype":"locality"
},
  "geometry": {"coordinates":[107.84711,31.6126],"type":"Point"}
}