{
  "type": "Feature",
  "properties": {
    "gn:admin1_code":"29.0",
    "gn:asciiname":"Pingba",
    "gn:country_code":"CN",
    "gn:dem":1913,
    "gn:feature_class":"P",
    "gn:feature_code":"PPL",
    "gn:name":"Pingba",
    "gn:population":0,
    "gn:timezone":"Asia/Shanghai",
    "iso:country":"CN",
    "name:zho_x_preferred":[
        "\u5e73\u575d"
    ],
    "wof:name":"Pingba",
    "wof:placetype":"locality"
},
  "geometry": {"coordinates":[98.3314,24.7134],"type":"Point"}
}