{
  "type": "Feature",
  "properties": {
    "gn:admin1_code":"30.0",
    "gn:asciiname":"Ximeicun",
    "gn:country_code":"CN",
    "gn:dem":11,
    "gn:feature_class":"P",
    "gn:feature_code":"PPL",
    "gn:name":"Ximeicun",
    "gn:population":0,
    "gn:timezone":"Asia/Shanghai",
    "iso:country":"CN",
    "name:zho_x_preferred":[
        "\u6eaa\u7f8e\u6751"
    ],
    "wof:name":"Ximeicun",
    "wof:placetype":"locality"
},
  "geometry": {"coordinates":[117.13341,23.60989],"type":"Point"}
}