{
  "type": "Feature",
  "properties": {
    "gn:admin1_code":"4.0",
    "gn:asciiname":"Weijiao",
    "gn:cc2":"CN",
    "gn:country_code":"CN",
    "gn:dem":5,
    "gn:feature_class":"P",
    "gn:feature_code":"PPL",
    "gn:name":"Weijiao",
    "gn:population":0,
    "gn:timezone":"Asia/Shanghai",
    "iso:country":"CN",
    "name:und_x_variant":[
        "Hs\u00fc-chiao",
        "Y\u00fc-chiao",
        "Wei-chiao-chen",
        "Y\u00fc-chiao-chen",
        "Weijiaozhen",
        "Weijiao"
    ],
    "wof:name":"Weijiao",
    "wof:placetype":"locality"
},
  "geometry": {"coordinates":[121.61417,31.85167],"type":"Point"}
}