{
  "type": "Feature",
  "properties": {
    "gn:admin1_code":"12.0",
    "gn:asciiname":"Lijiaya",
    "gn:country_code":"CN",
    "gn:dem":1382,
    "gn:feature_class":"P",
    "gn:feature_code":"PPL",
    "gn:name":"Lijiaya",
    "gn:population":0,
    "gn:timezone":"Asia/Shanghai",
    "iso:country":"CN",
    "name:zho_x_preferred":[
        "\u674e\u5bb6\u57ad"
    ],
    "wof:name":"Lijiaya",
    "wof:placetype":"locality"
},
  "geometry": {"coordinates":[110.97929999999999,31.24527],"type":"Point"}
}