{
  "type": "Feature",
  "properties": {
    "gn:admin1_code":"26.0",
    "gn:asciiname":"Leiliang",
    "gn:country_code":"CN",
    "gn:dem":1109,
    "gn:feature_class":"P",
    "gn:feature_code":"PPL",
    "gn:name":"Leiliang",
    "gn:population":0,
    "gn:timezone":"Asia/Shanghai",
    "iso:country":"CN",
    "name:zho_x_preferred":[
        "\u96f7\u6881"
    ],
    "wof:name":"Leiliang",
    "wof:placetype":"locality"
},
  "geometry": {"coordinates":[109.29061000000002,38.10254000000001],"type":"Point"}
}