{
  "type": "Feature",
  "properties": {
    "gn:admin1_code":"9.0",
    "gn:asciiname":"Xishuanghe",
    "gn:country_code":"CN",
    "gn:dem":106,
    "gn:feature_class":"P",
    "gn:feature_code":"PPL",
    "gn:name":"Xishuanghe",
    "gn:population":0,
    "gn:timezone":"Asia/Shanghai",
    "iso:country":"CN",
    "name:und_x_variant":[
        "Hsi-shuang-ho",
        "Xishuanghe",
        "\u897f\u53cc\u6cb3"
    ],
    "wof:name":"Xishuanghe",
    "wof:placetype":"locality"
},
  "geometry": {"coordinates":[113.96108999999998,31.96013],"type":"Point"}
}