{
  "type": "Feature",
  "properties": {
    "gn:admin1_code":"11",
    "gn:asciiname":"Guyang",
    "gn:country_code":"CN",
    "gn:dem":364,
    "gn:feature_class":"P",
    "gn:feature_code":"PPLA3",
    "gn:name":"Guyang",
    "gn:population":0,
    "gn:timezone":"Asia/Shanghai",
    "iso:country":"CN",
    "name:und_x_variant":[
        "Ku-chang-hsien",
        "Guzhang",
        "Ku-chang",
        "Guyang",
        "Guzhang Xian"
    ],
    "name:zho_x_preferred":[
        "Ku-chang-p\u2019ing"
    ],
    "name:zho_x_variant":[
        "\u53e4\u9633",
        "\u53e4\u4e08\u53bf"
    ],
    "wof:name":"Guyang",
    "wof:placetype":"locality"
},
  "geometry": {"coordinates":[109.93253,28.61385],"type":"Point"}
}