{
  "type": "Feature",
  "properties": {
    "gn:admin1_code":"7.0",
    "gn:asciiname":"Huyong",
    "gn:country_code":"CN",
    "gn:dem":797,
    "gn:feature_class":"P",
    "gn:feature_code":"PPL",
    "gn:name":"Huyong",
    "gn:population":0,
    "gn:timezone":"Asia/Shanghai",
    "iso:country":"CN",
    "name:zho_x_preferred":[
        "\u58f6\u6c38"
    ],
    "wof:name":"Huyong",
    "wof:placetype":"locality"
},
  "geometry": {"coordinates":[118.10429999999999,25.49092000000001],"type":"Point"}
}