{
  "type": "Feature",
  "properties": {
    "gn:admin1_code":"16.0",
    "gn:asciiname":"Luli",
    "gn:country_code":"CN",
    "gn:dem":209,
    "gn:feature_class":"P",
    "gn:feature_code":"PPL",
    "gn:name":"Luli",
    "gn:population":0,
    "gn:timezone":"Asia/Shanghai",
    "iso:country":"CN",
    "name:deu_x_preferred":[
        "Elulaios"
    ],
    "name:fra_x_preferred":[
        "Louli"
    ],
    "name:nld_x_preferred":[
        "Elulaios"
    ],
    "name:por_x_preferred":[
        "Luli"
    ],
    "name:rus_x_preferred":[
        "\u042d\u043b\u0443\u043b\u0430\u0439"
    ],
    "name:spa_x_preferred":[
        "Elulayo"
    ],
    "name:zho_x_preferred":[
        "\u82a6\u7b20"
    ],
    "wof:name":"Luli",
    "wof:placetype":"locality"
},
  "geometry": {"coordinates":[108.67700000000001,23.7122],"type":"Point"}
}