{
  "type": "Feature",
  "properties": {
    "gn:admin1_code":"19",
    "gn:asciiname":"Changdianhekou",
    "gn:cc2":"CN",
    "gn:country_code":"CN",
    "gn:dem":50,
    "gn:feature_class":"P",
    "gn:feature_code":"PPL",
    "gn:name":"Changdianhekou",
    "gn:population":0,
    "gn:timezone":"Asia/Shanghai",
    "iso:country":"CN",
    "name:und_x_variant":[
        "Shang-ho-k\u2019ou",
        "Ch\u2019ang-chiang-ch\u2019eng",
        "Shanghekou",
        "Ch\u2019ang-tien-ho-k\u2019ou",
        "Ch\u2019ang-tien-ch\u2019eng",
        "Ho-k\u2019ou",
        "Changdianhekou"
    ],
    "wof:name":"Changdianhekou",
    "wof:placetype":"locality"
},
  "geometry": {"coordinates":[124.81638999999998,40.41667],"type":"Point"}
}