{
  "type": "Feature",
  "properties": {
    "gn:admin1_code":"30.0",
    "gn:asciiname":"Jinshengcun",
    "gn:country_code":"CN",
    "gn:dem":154,
    "gn:feature_class":"P",
    "gn:feature_code":"PPL",
    "gn:name":"Jinshengcun",
    "gn:population":0,
    "gn:timezone":"Asia/Shanghai",
    "iso:country":"CN",
    "name:zho_x_preferred":[
        "\u91d1\u58f0\u6751"
    ],
    "wof:name":"Jinshengcun",
    "wof:placetype":"locality"
},
  "geometry": {"coordinates":[116.02821000000002,24.19782],"type":"Point"}
}