{
  "type": "Feature",
  "properties": {
    "gn:admin1_code":"7.0",
    "gn:asciiname":"Xudun",
    "gn:country_code":"CN",
    "gn:dem":286,
    "gn:feature_class":"P",
    "gn:feature_code":"PPL",
    "gn:name":"Xudun",
    "gn:population":0,
    "gn:timezone":"Asia/Shanghai",
    "iso:country":"CN",
    "name:und_x_variant":[
        "\u5f90\u58a9"
    ],
    "name:zho_x_preferred":[
        "\u5f90\u58a9"
    ],
    "wof:name":"Xudun",
    "wof:placetype":"locality"
},
  "geometry": {"coordinates":[118.00037,26.40792],"type":"Point"}
}