{
  "type": "Feature",
  "properties": {
    "gn:admin1_code":"18",
    "gn:asciiname":"Xinyuan",
    "gn:country_code":"CN",
    "gn:dem":1137,
    "gn:feature_class":"P",
    "gn:feature_code":"PPL",
    "gn:name":"Xinyuan",
    "gn:population":0,
    "gn:timezone":"Asia/Shanghai",
    "iso:country":"CN",
    "name:zho_x_preferred":[
        "\u65b0\u82d1"
    ],
    "wof:name":"Xinyuan",
    "wof:placetype":"locality"
},
  "geometry": {"coordinates":[105.852,26.0501],"type":"Point"}
}