{
  "type": "Feature",
  "properties": {
    "gn:admin1_code":"25.0",
    "gn:asciiname":"Guge",
    "gn:country_code":"CN",
    "gn:dem":52,
    "gn:feature_class":"P",
    "gn:feature_code":"PPL",
    "gn:name":"Guge",
    "gn:population":0,
    "gn:timezone":"Asia/Shanghai",
    "iso:country":"CN",
    "name:ben_x_preferred":[
        "\u0997\u09c1\u099c"
    ],
    "name:cat_x_preferred":[
        "Guge"
    ],
    "name:deu_x_preferred":[
        "Guge"
    ],
    "name:hin_x_preferred":[
        "\u0917\u0941\u0917\u0947"
    ],
    "name:jpn_x_preferred":[
        "\u30b0\u30b2\u738b\u56fd"
    ],
    "name:kor_x_preferred":[
        "\uad6c\uac8c \uc655\uad6d"
    ],
    "name:nld_x_preferred":[
        "Guge"
    ],
    "name:nor_x_preferred":[
        "Guge"
    ],
    "name:pnb_x_preferred":[
        "\u06af\u06af\u06d2 \u0631\u0627\u062c"
    ],
    "name:por_x_preferred":[
        "Guge"
    ],
    "name:rus_x_preferred":[
        "\u0413\u0443\u0433\u0435"
    ],
    "name:spa_x_preferred":[
        "Guge"
    ],
    "name:swe_x_preferred":[
        "Guge"
    ],
    "name:vie_x_preferred":[
        "C\u1ed5 C\u00e1ch"
    ],
    "name:zho_x_preferred":[
        "\u53e4\u683c"
    ],
    "name:zho_x_variant":[
        "\u53e4\u683c\u738b\u671d"
    ],
    "wof:name":"Guge",
    "wof:placetype":"locality"
},
  "geometry": {"coordinates":[122.33387999999999,37.14711],"type":"Point"}
}