{
  "type": "Feature",
  "properties": {
    "gn:admin1_code":"3.0",
    "gn:asciiname":"Dawankou",
    "gn:country_code":"CN",
    "gn:dem":167,
    "gn:feature_class":"P",
    "gn:feature_code":"PPL",
    "gn:name":"Dawankou",
    "gn:population":0,
    "gn:timezone":"Asia/Shanghai",
    "iso:country":"CN",
    "name:und_x_variant":[
        "\u5927\u6e7e\u53e3"
    ],
    "wof:name":"Dawankou",
    "wof:placetype":"locality"
},
  "geometry": {"coordinates":[115.72413,26.21633],"type":"Point"}
}