{
  "type": "Feature",
  "properties": {
    "gn:admin1_code":"12.0",
    "gn:asciiname":"Woniukeng",
    "gn:country_code":"CN",
    "gn:dem":222,
    "gn:feature_class":"P",
    "gn:feature_code":"PPL",
    "gn:name":"Woniukeng",
    "gn:population":0,
    "gn:timezone":"Asia/Shanghai",
    "iso:country":"CN",
    "name:zho_x_preferred":[
        "\u5367\u725b\u5751"
    ],
    "wof:name":"Woniukeng",
    "wof:placetype":"locality"
},
  "geometry": {"coordinates":[112.60643,31.82573],"type":"Point"}
}