{
  "type": "Feature",
  "properties": {
    "gn:admin1_code":"4.0",
    "gn:asciiname":"Daizhuangcun",
    "gn:country_code":"CN",
    "gn:dem":1,
    "gn:feature_class":"P",
    "gn:feature_code":"PPL",
    "gn:name":"Daizhuangcun",
    "gn:population":0,
    "gn:timezone":"Asia/Shanghai",
    "iso:country":"CN",
    "name:zho_x_preferred":[
        "\u6234\u5e84\u6751"
    ],
    "wof:name":"Daizhuangcun",
    "wof:placetype":"locality"
},
  "geometry": {"coordinates":[119.57629,33.30133],"type":"Point"}
}