{
  "type": "Feature",
  "properties": {
    "gn:admin1_code":"15",
    "gn:asciiname":"Mawu",
    "gn:cc2":"CN",
    "gn:country_code":"CN",
    "gn:dem":2058,
    "gn:feature_class":"P",
    "gn:feature_code":"PPL",
    "gn:name":"Mawu",
    "gn:population":0,
    "gn:timezone":"Asia/Shanghai",
    "iso:country":"CN",
    "name:bul_x_preferred":[
        "\u041c\u0430\u0432\u0443"
    ],
    "name:fin_x_preferred":[
        "Mawu"
    ],
    "name:fra_x_preferred":[
        "Mawu"
    ],
    "name:nld_x_preferred":[
        "Mawu"
    ],
    "name:por_x_preferred":[
        "Mawu"
    ],
    "name:slv_x_preferred":[
        "Mawu"
    ],
    "name:swe_x_preferred":[
        "Mawu"
    ],
    "name:tur_x_preferred":[
        "Mawu"
    ],
    "name:und_x_variant":[
        "Ma-wu-chen"
    ],
    "wof:name":"Mawu",
    "wof:placetype":"locality"
},
  "geometry": {"coordinates":[104.91472,34.42639],"type":"Point"}
}