{
  "type": "Feature",
  "properties": {
    "gn:admin1_code":"32.0",
    "gn:asciiname":"Jingzi",
    "gn:country_code":"CN",
    "gn:dem":468,
    "gn:feature_class":"P",
    "gn:feature_code":"PPL",
    "gn:name":"Jingzi",
    "gn:population":0,
    "gn:timezone":"Asia/Shanghai",
    "iso:country":"CN",
    "name:zho_x_preferred":[
        "\u955c\u5b50"
    ],
    "wof:name":"Jingzi",
    "wof:placetype":"locality"
},
  "geometry": {"coordinates":[106.04300000000001,31.8409],"type":"Point"}
}