{
  "type": "Feature",
  "properties": {
    "gn:admin1_code":"10",
    "gn:asciiname":"Hongshanzui",
    "gn:country_code":"CN",
    "gn:dem":494,
    "gn:feature_class":"P",
    "gn:feature_code":"PPL",
    "gn:name":"Hongshanzui",
    "gn:population":0,
    "gn:timezone":"Asia/Shanghai",
    "iso:country":"CN",
    "name:zho_x_preferred":[
        "\u7ea2\u5c71\u5634"
    ],
    "wof:name":"Hongshanzui",
    "wof:placetype":"locality"
},
  "geometry": {"coordinates":[118.64575000000001,40.97621],"type":"Point"}
}