{
  "type": "Feature",
  "properties": {
    "gn:admin1_code":"3.0",
    "gn:asciiname":"Qinglan Nongchang",
    "gn:country_code":"CN",
    "gn:dem":44,
    "gn:feature_class":"P",
    "gn:feature_code":"PPLF",
    "gn:name":"Qinglan Nongchang",
    "gn:population":0,
    "gn:timezone":"Asia/Shanghai",
    "iso:country":"CN",
    "name:und_x_variant":[
        "\u9752\u5c9a\u519c\u573a"
    ],
    "wof:name":"Qinglan Nongchang",
    "wof:placetype":"locality"
},
  "geometry": {"coordinates":[115.82107999999999,28.73718],"type":"Point"}
}