{
  "type": "Feature",
  "properties": {
    "gn:admin1_code":"20.0",
    "gn:asciiname":"Gala Gana",
    "gn:country_code":"CN",
    "gn:dem":580,
    "gn:feature_class":"P",
    "gn:feature_code":"PPL",
    "gn:name":"Gala Gana",
    "gn:population":0,
    "gn:timezone":"Asia/Shanghai",
    "iso:country":"CN",
    "name:zho_x_preferred":[
        "\u560e\u62c9\u560e\u90a3"
    ],
    "wof:name":"Gala Gana",
    "wof:placetype":"locality"
},
  "geometry": {"coordinates":[119.91912000000001,50.54861],"type":"Point"}
}