{
  "type": "Feature",
  "properties": {
    "gn:admin1_code":"10",
    "gn:asciiname":"Laochangzi",
    "gn:country_code":"CN",
    "gn:dem":1325,
    "gn:feature_class":"P",
    "gn:feature_code":"PPL",
    "gn:name":"Laochangzi",
    "gn:population":0,
    "gn:timezone":"Asia/Shanghai",
    "iso:country":"CN",
    "name:zho_x_preferred":[
        "\u8001\u573a\u5b50"
    ],
    "wof:name":"Laochangzi",
    "wof:placetype":"locality"
},
  "geometry": {"coordinates":[116.27328,41.10712],"type":"Point"}
}