{
  "type": "Feature",
  "properties": {
    "gn:admin1_code":"21.0",
    "gn:asciiname":"Baziqu",
    "gn:country_code":"CN",
    "gn:dem":1233,
    "gn:feature_class":"P",
    "gn:feature_code":"PPL",
    "gn:name":"Baziqu",
    "gn:population":0,
    "gn:timezone":"Asia/Shanghai",
    "iso:country":"CN",
    "name:zho_x_preferred":[
        "\u516b\u5b57\u6e20"
    ],
    "wof:name":"Baziqu",
    "wof:placetype":"locality"
},
  "geometry": {"coordinates":[105.17,37.5282],"type":"Point"}
}