{
  "type": "Feature",
  "properties": {
    "gn:admin1_code":"26.0",
    "gn:asciiname":"Yangpotoucun",
    "gn:country_code":"CN",
    "gn:dem":1494,
    "gn:feature_class":"P",
    "gn:feature_code":"PPL",
    "gn:name":"Yangpotoucun",
    "gn:population":0,
    "gn:timezone":"Asia/Shanghai",
    "iso:country":"CN",
    "name:zho_x_preferred":[
        "\u9633\u5761\u5934\u6751"
    ],
    "wof:name":"Yangpotoucun",
    "wof:placetype":"locality"
},
  "geometry": {"coordinates":[108.46773,35.25412],"type":"Point"}
}