{
  "type": "Feature",
  "properties": {
    "gn:admin1_code":"1.0",
    "gn:asciiname":"Xingou",
    "gn:country_code":"CN",
    "gn:dem":11,
    "gn:feature_class":"P",
    "gn:feature_code":"PPL",
    "gn:name":"Xingou",
    "gn:population":0,
    "gn:timezone":"Asia/Shanghai",
    "iso:country":"CN",
    "name:und_x_variant":[
        "Hsin-kou-chen",
        "Hsin-kou",
        "Xingou"
    ],
    "name:zho_x_preferred":[
        "\u65b0\u6c9f"
    ],
    "wof:name":"Xingou",
    "wof:placetype":"locality"
},
  "geometry": {"coordinates":[117.94325000000001,31.09193],"type":"Point"}
}