{
  "type": "Feature",
  "properties": {
    "gn:admin1_code":"12.0",
    "gn:asciiname":"Changzhuyuan",
    "gn:country_code":"CN",
    "gn:dem":43,
    "gn:feature_class":"P",
    "gn:feature_code":"PPL",
    "gn:name":"Changzhuyuan",
    "gn:population":0,
    "gn:timezone":"Asia/Shanghai",
    "iso:country":"CN",
    "name:zho_x_preferred":[
        "\u957f\u7af9\u56ed"
    ],
    "wof:name":"Changzhuyuan",
    "wof:placetype":"locality"
},
  "geometry": {"coordinates":[112.18183999999999,29.81053],"type":"Point"}
}