{
  "type": "Feature",
  "properties": {
    "gn:admin1_code":"5.0",
    "gn:asciiname":"Dahe Xicun",
    "gn:country_code":"CN",
    "gn:dem":206,
    "gn:feature_class":"P",
    "gn:feature_code":"PPL",
    "gn:name":"Dahe Xicun",
    "gn:population":0,
    "gn:timezone":"Asia/Shanghai",
    "iso:country":"CN",
    "name:zho_x_preferred":[
        "\u5927\u6cb3\u897f\u6751"
    ],
    "wof:name":"Dahe Xicun",
    "wof:placetype":"locality"
},
  "geometry": {"coordinates":[124.4695,43.12179],"type":"Point"}
}