{
  "type": "Feature",
  "properties": {
    "gn:admin1_code":"4.0",
    "gn:asciiname":"Shidang",
    "gn:country_code":"CN",
    "gn:dem":3,
    "gn:feature_class":"P",
    "gn:feature_code":"PPL",
    "gn:name":"Shidang",
    "gn:population":0,
    "gn:timezone":"Asia/Shanghai",
    "iso:country":"CN",
    "name:zho_x_preferred":[
        "Shidang"
    ],
    "name:zho_x_variant":[
        "\u53f2\u8361"
    ],
    "wof:name":"Shidang",
    "wof:placetype":"locality"
},
  "geometry": {"coordinates":[119.40389999999999,33.54644],"type":"Point"}
}