{
  "type": "Feature",
  "properties": {
    "gn:admin1_code":"19.0",
    "gn:asciiname":"Loujiatun",
    "gn:country_code":"CN",
    "gn:dem":60,
    "gn:feature_class":"P",
    "gn:feature_code":"PPL",
    "gn:name":"Loujiatun",
    "gn:population":0,
    "gn:timezone":"Asia/Shanghai",
    "iso:country":"CN",
    "name:zho_x_preferred":[
        "\u5a04\u5bb6\u5c6f"
    ],
    "wof:name":"Loujiatun",
    "wof:placetype":"locality"
},
  "geometry": {"coordinates":[122.89924999999999,39.91098],"type":"Point"}
}