{
  "type": "Feature",
  "properties": {
    "gn:admin1_code":"16.0",
    "gn:asciiname":"Huntun",
    "gn:country_code":"CN",
    "gn:dem":524,
    "gn:feature_class":"P",
    "gn:feature_code":"PPL",
    "gn:name":"Huntun",
    "gn:population":0,
    "gn:timezone":"Asia/Shanghai",
    "iso:country":"CN",
    "name:zho_x_preferred":[
        "\u6df7\u5c6f"
    ],
    "wof:name":"Huntun",
    "wof:placetype":"locality"
},
  "geometry": {"coordinates":[106.58,24.2201],"type":"Point"}
}