{
  "type": "Feature",
  "properties": {
    "gn:admin1_code":"15.0",
    "gn:asciiname":"Liangpuya",
    "gn:country_code":"CN",
    "gn:dem":982,
    "gn:feature_class":"P",
    "gn:feature_code":"PPL",
    "gn:name":"Liangpuya",
    "gn:population":0,
    "gn:timezone":"Asia/Shanghai",
    "iso:country":"CN",
    "name:und_x_variant":[
        "\u4e24\u94fa\u57ad"
    ],
    "wof:name":"Liangpuya",
    "wof:placetype":"locality"
},
  "geometry": {"coordinates":[106.14854,33.75499],"type":"Point"}
}