{
  "type": "Feature",
  "properties": {
    "gn:admin1_code":"14.0",
    "gn:asciiname":"Ogpu",
    "gn:country_code":"CN",
    "gn:dem":4003,
    "gn:feature_class":"P",
    "gn:feature_code":"PPL",
    "gn:name":"Ogpu",
    "gn:population":0,
    "gn:timezone":"Asia/Urumqi",
    "iso:country":"CN",
    "name:bod_x_preferred":[
        "Ogpu"
    ],
    "name:zho_x_preferred":[
        "Wopu"
    ],
    "name:zho_x_variant":[
        "\u7a9d\u666e"
    ],
    "wof:name":"Ogpu",
    "wof:placetype":"locality"
},
  "geometry": {"coordinates":[94.501,30.301],"type":"Point"}
}