{
  "type": "Feature",
  "properties": {
    "gn:admin1_code":"29",
    "gn:asciiname":"Sanxiangdong",
    "gn:country_code":"CN",
    "gn:dem":936,
    "gn:feature_class":"P",
    "gn:feature_code":"PPL",
    "gn:name":"Sanxiangdong",
    "gn:population":0,
    "gn:timezone":"Asia/Shanghai",
    "iso:country":"CN",
    "name:zho_x_preferred":[
        "\u4e09\u6e58\u6d1e"
    ],
    "wof:name":"Sanxiangdong",
    "wof:placetype":"locality"
},
  "geometry": {"coordinates":[105.78700000000001,23.9225],"type":"Point"}
}