{
  "type": "Feature",
  "properties": {
    "gn:admin1_code":"8.0",
    "gn:asciiname":"Hutougou",
    "gn:country_code":"CN",
    "gn:dem":183,
    "gn:feature_class":"P",
    "gn:feature_code":"PPL",
    "gn:name":"Hutougou",
    "gn:population":0,
    "gn:timezone":"Asia/Shanghai",
    "iso:country":"CN",
    "name:zho_x_preferred":[
        "\u80e1\u5934\u6c9f"
    ],
    "wof:name":"Hutougou",
    "wof:placetype":"locality"
},
  "geometry": {"coordinates":[126.80717,45.67491],"type":"Point"}
}