{
  "type": "Feature",
  "properties": {
    "gn:admin1_code":"8.0",
    "gn:asciiname":"Gaoshifutun",
    "gn:country_code":"CN",
    "gn:dem":186,
    "gn:feature_class":"P",
    "gn:feature_code":"PPL",
    "gn:name":"Gaoshifutun",
    "gn:population":0,
    "gn:timezone":"Asia/Shanghai",
    "iso:country":"CN",
    "name:zho_x_preferred":[
        "\u9ad8\u58eb\u5bcc\u5c6f"
    ],
    "wof:name":"Gaoshifutun",
    "wof:placetype":"locality"
},
  "geometry": {"coordinates":[125.71373,46.52813],"type":"Point"}
}