{
  "type": "Feature",
  "properties": {
    "gn:admin1_code":"8.0",
    "gn:asciiname":"Lifengcun",
    "gn:country_code":"CN",
    "gn:dem":74,
    "gn:feature_class":"P",
    "gn:feature_code":"PPL",
    "gn:name":"Lifengcun",
    "gn:population":0,
    "gn:timezone":"Asia/Shanghai",
    "iso:country":"CN",
    "name:zho_x_preferred":[
        "\u68a8\u4e30\u6751"
    ],
    "wof:name":"Lifengcun",
    "wof:placetype":"locality"
},
  "geometry": {"coordinates":[131.13437999999999,47.05516],"type":"Point"}
}