{
  "type": "Feature",
  "properties": {
    "gn:admin1_code":"14.0",
    "gn:asciiname":"Xiazha",
    "gn:country_code":"CN",
    "gn:dem":3961,
    "gn:feature_class":"P",
    "gn:feature_code":"PPL",
    "gn:name":"Xiazha",
    "gn:population":0,
    "gn:timezone":"Asia/Urumqi",
    "iso:country":"CN",
    "name:zho_x_preferred":[
        "\u4e0b\u624e"
    ],
    "wof:name":"Xiazha",
    "wof:placetype":"locality"
},
  "geometry": {"coordinates":[87.7221,29.2213],"type":"Point"}
}