{
  "type": "Feature",
  "properties": {
    "gn:admin1_code":"32.0",
    "gn:asciiname":"Shiniu",
    "gn:country_code":"CN",
    "gn:dem":402,
    "gn:feature_class":"P",
    "gn:feature_code":"PPL",
    "gn:name":"Shiniu",
    "gn:population":0,
    "gn:timezone":"Asia/Shanghai",
    "iso:country":"CN",
    "name:zho_x_preferred":[
        "\u77f3\u725b"
    ],
    "wof:name":"Shiniu",
    "wof:placetype":"locality"
},
  "geometry": {"coordinates":[105.419,30.9791],"type":"Point"}
}