{
  "type": "Feature",
  "properties": {
    "gn:admin1_code":"24.0",
    "gn:asciiname":"Putita",
    "gn:country_code":"CN",
    "gn:dem":1276,
    "gn:feature_class":"P",
    "gn:feature_code":"PPL",
    "gn:name":"Putita",
    "gn:population":0,
    "gn:timezone":"Asia/Shanghai",
    "iso:country":"CN",
    "name:zho_x_preferred":[
        "\u83e9\u63d0\u5854"
    ],
    "wof:name":"Putita",
    "wof:placetype":"locality"
},
  "geometry": {"coordinates":[112.45018,36.58299],"type":"Point"}
}