{
  "type": "Feature",
  "properties": {
    "gn:admin1_code":"30.0",
    "gn:asciiname":"Maiwen Shangcun",
    "gn:country_code":"CN",
    "gn:dem":20,
    "gn:feature_class":"P",
    "gn:feature_code":"PPL",
    "gn:name":"Maiwen Shangcun",
    "gn:population":0,
    "gn:timezone":"Asia/Urumqi",
    "iso:country":"CN",
    "name:zho_x_preferred":[
        "\u8fc8\u6c76\u4e0a\u6751"
    ],
    "wof:name":"Maiwen Shangcun",
    "wof:placetype":"locality"
},
  "geometry": {"coordinates":[110.01143,20.34418],"type":"Point"}
}