{
  "type": "Feature",
  "properties": {
    "gn:admin1_code":"19.0",
    "gn:asciiname":"Liujiatuozi",
    "gn:country_code":"CN",
    "gn:dem":85,
    "gn:feature_class":"P",
    "gn:feature_code":"PPL",
    "gn:name":"Liujiatuozi",
    "gn:population":0,
    "gn:timezone":"Asia/Shanghai",
    "iso:country":"CN",
    "name:zho_x_preferred":[
        "\u5218\u5bb6\u5768\u5b50"
    ],
    "wof:name":"Liujiatuozi",
    "wof:placetype":"locality"
},
  "geometry": {"coordinates":[123.55307999999999,42.86162],"type":"Point"}
}