{
  "type": "Feature",
  "properties": {
    "gn:admin1_code":"10",
    "gn:asciiname":"Xidajiayu",
    "gn:country_code":"CN",
    "gn:dem":298,
    "gn:feature_class":"P",
    "gn:feature_code":"PPL",
    "gn:name":"Xidajiayu",
    "gn:population":0,
    "gn:timezone":"Asia/Shanghai",
    "iso:country":"CN",
    "name:zho_x_preferred":[
        "\u897f\u5927\u5bb6\u5cea"
    ],
    "wof:name":"Xidajiayu",
    "wof:placetype":"locality"
},
  "geometry": {"coordinates":[114.26900000000001,37.5784],"type":"Point"}
}