{
  "type": "Feature",
  "properties": {
    "gn:admin1_code":"4.0",
    "gn:asciiname":"Wangxiaozhuang",
    "gn:country_code":"CN",
    "gn:dem":8,
    "gn:feature_class":"P",
    "gn:feature_code":"PPL",
    "gn:name":"Wangxiaozhuang",
    "gn:population":0,
    "gn:timezone":"Asia/Shanghai",
    "iso:country":"CN",
    "name:zho_x_preferred":[
        "Wangxiaozhuang"
    ],
    "name:zho_x_variant":[
        "\u738b\u5c0f\u5e84"
    ],
    "wof:name":"Wangxiaozhuang",
    "wof:placetype":"locality"
},
  "geometry": {"coordinates":[119.40554,33.02965],"type":"Point"}
}