{
  "type": "Feature",
  "properties": {
    "gn:admin1_code":"4.0",
    "gn:asciiname":"Jujiazhuang",
    "gn:country_code":"CN",
    "gn:dem":4,
    "gn:feature_class":"P",
    "gn:feature_code":"PPL",
    "gn:name":"Jujiazhuang",
    "gn:population":0,
    "gn:timezone":"Asia/Shanghai",
    "iso:country":"CN",
    "name:zho_x_preferred":[
        "\u97a0\u5bb6\u5e84"
    ],
    "wof:name":"Jujiazhuang",
    "wof:placetype":"locality"
},
  "geometry": {"coordinates":[120.69216000000002,32.33669],"type":"Point"}
}