{
  "type": "Feature",
  "properties": {
    "gn:admin1_code":"29.0",
    "gn:asciiname":"Manjiaotang",
    "gn:country_code":"CN",
    "gn:dem":956,
    "gn:feature_class":"P",
    "gn:feature_code":"PPL",
    "gn:name":"Manjiaotang",
    "gn:population":0,
    "gn:timezone":"Asia/Shanghai",
    "iso:country":"CN",
    "name:zho_x_preferred":[
        "\u66fc\u89d2\u5858"
    ],
    "wof:name":"Manjiaotang",
    "wof:placetype":"locality"
},
  "geometry": {"coordinates":[101.03400000000001,22.5465],"type":"Point"}
}