{
  "type": "Feature",
  "properties": {
    "gn:admin1_code":"11.0",
    "gn:asciiname":"Xinjialong",
    "gn:country_code":"CN",
    "gn:dem":40,
    "gn:feature_class":"P",
    "gn:feature_code":"PPL",
    "gn:name":"Xinjialong",
    "gn:population":0,
    "gn:timezone":"Asia/Shanghai",
    "iso:country":"CN",
    "name:zho_x_preferred":[
        "\u65b0\u5bb6\u5784"
    ],
    "wof:name":"Xinjialong",
    "wof:placetype":"locality"
},
  "geometry": {"coordinates":[113.37548,29.63803],"type":"Point"}
}