{
  "type": "Feature",
  "properties": {
    "gn:admin1_code":"4.0",
    "gn:asciiname":"Qianyuan",
    "gn:country_code":"CN",
    "gn:dem":1,
    "gn:feature_class":"P",
    "gn:feature_code":"PPL",
    "gn:name":"Qianyuan",
    "gn:population":0,
    "gn:timezone":"Asia/Shanghai",
    "iso:country":"CN",
    "name:und_x_variant":[
        "Hanyuan"
    ],
    "name:zho_x_preferred":[
        "\u4e7e\u56ed"
    ],
    "name:zho_x_variant":[
        "\u97e9\u56ed"
    ],
    "wof:name":"Qianyuan",
    "wof:placetype":"locality"
},
  "geometry": {"coordinates":[120.28683999999998,32.97105999999999],"type":"Point"}
}