{
  "type": "Feature",
  "properties": {
    "gn:admin1_code":"9.0",
    "gn:asciiname":"Huichunyin",
    "gn:country_code":"CN",
    "gn:dem":1164,
    "gn:feature_class":"P",
    "gn:feature_code":"PPL",
    "gn:name":"Huichunyin",
    "gn:population":0,
    "gn:timezone":"Asia/Shanghai",
    "iso:country":"CN",
    "name:zho_x_preferred":[
        "\u8334\u693f\u9634"
    ],
    "wof:name":"Huichunyin",
    "wof:placetype":"locality"
},
  "geometry": {"coordinates":[111.16583,34.38679],"type":"Point"}
}