{
  "type": "Feature",
  "properties": {
    "gn:admin1_code":"11",
    "gn:asciiname":"Guizhuxi",
    "gn:country_code":"CN",
    "gn:dem":241,
    "gn:feature_class":"P",
    "gn:feature_code":"PPL",
    "gn:name":"Guizhuxi",
    "gn:population":0,
    "gn:timezone":"Asia/Shanghai",
    "iso:country":"CN",
    "name:zho_x_preferred":[
        "\u6842\u7af9\u6eaa"
    ],
    "wof:name":"Guizhuxi",
    "wof:placetype":"locality"
},
  "geometry": {"coordinates":[109.99418,27.83856],"type":"Point"}
}