{
  "type": "Feature",
  "properties": {
    "gn:admin1_code":"11.0",
    "gn:asciiname":"Meishulong",
    "gn:country_code":"CN",
    "gn:dem":522,
    "gn:feature_class":"P",
    "gn:feature_code":"PPL",
    "gn:name":"Meishulong",
    "gn:population":0,
    "gn:timezone":"Asia/Shanghai",
    "iso:country":"CN",
    "name:zho_x_preferred":[
        "\u6885\u6811\u5785"
    ],
    "wof:name":"Meishulong",
    "wof:placetype":"locality"
},
  "geometry": {"coordinates":[113.53322,25.65143],"type":"Point"}
}