{
  "type": "Feature",
  "properties": {
    "gn:admin1_code":"16",
    "gn:asciiname":"Naxiao",
    "gn:cc2":"CN",
    "gn:country_code":"CN",
    "gn:dem":390,
    "gn:feature_class":"P",
    "gn:feature_code":"PPL",
    "gn:name":"Naxiao",
    "gn:population":0,
    "gn:timezone":"Asia/Shanghai",
    "iso:country":"CN",
    "name:und_x_variant":[
        "Na-hsiao",
        "Naxiao"
    ],
    "wof:name":"Naxiao",
    "wof:placetype":"locality"
},
  "geometry": {"coordinates":[106.79555999999999,22.15],"type":"Point"}
}