{
  "type": "Feature",
  "properties": {
    "gn:admin1_code":"29.0",
    "gn:asciiname":"Laobiga",
    "gn:country_code":"CN",
    "gn:dem":1642,
    "gn:feature_class":"P",
    "gn:feature_code":"PPL",
    "gn:name":"Laobiga",
    "gn:population":0,
    "gn:timezone":"Asia/Shanghai",
    "iso:country":"CN",
    "name:zho_x_preferred":[
        "\u8001\u78a7\u560e"
    ],
    "wof:name":"Laobiga",
    "wof:placetype":"locality"
},
  "geometry": {"coordinates":[103.20099999999999,26.0069],"type":"Point"}
}