{
  "type": "Feature",
  "properties": {
    "gn:admin1_code":"30.0",
    "gn:asciiname":"Lubicun",
    "gn:country_code":"CN",
    "gn:dem":10,
    "gn:feature_class":"P",
    "gn:feature_code":"PPL",
    "gn:name":"Lubicun",
    "gn:population":0,
    "gn:timezone":"Asia/Shanghai",
    "iso:country":"CN",
    "name:zho_x_preferred":[
        "\u8def\u7be6\u6751"
    ],
    "wof:name":"Lubicun",
    "wof:placetype":"locality"
},
  "geometry": {"coordinates":[116.41213,23.57881],"type":"Point"}
}