{
  "type": "Feature",
  "properties": {
    "gn:admin1_code":"29.0",
    "gn:asciiname":"Huangcaoling",
    "gn:country_code":"CN",
    "gn:dem":1385,
    "gn:feature_class":"P",
    "gn:feature_code":"PPL",
    "gn:name":"Huangcaoling",
    "gn:population":0,
    "gn:timezone":"Asia/Shanghai",
    "iso:country":"CN",
    "name:zho_x_preferred":[
        "\u9ec4\u8349\u5cad"
    ],
    "wof:name":"Huangcaoling",
    "wof:placetype":"locality"
},
  "geometry": {"coordinates":[100.477,22.9982],"type":"Point"}
}