{
  "type": "Feature",
  "properties": {
    "gn:admin1_code":"8.0",
    "gn:asciiname":"Xinglecun",
    "gn:country_code":"CN",
    "gn:dem":178,
    "gn:feature_class":"P",
    "gn:feature_code":"PPL",
    "gn:name":"Xinglecun",
    "gn:population":0,
    "gn:timezone":"Asia/Shanghai",
    "iso:country":"CN",
    "name:zho_x_preferred":[
        "\u5174\u4e50\u6751"
    ],
    "wof:name":"Xinglecun",
    "wof:placetype":"locality"
},
  "geometry": {"coordinates":[125.20699999999999,47.52465],"type":"Point"}
}