{
  "type": "Feature",
  "properties": {
    "gn:admin1_code":"2.0",
    "gn:asciiname":"Jinjia'ao",
    "gn:country_code":"CN",
    "gn:dem":50,
    "gn:feature_class":"P",
    "gn:feature_code":"PPL",
    "gn:name":"Jinjia\u2019ao",
    "gn:population":0,
    "gn:timezone":"Asia/Shanghai",
    "iso:country":"CN",
    "name:und_x_variant":[
        "Jinjia\u2019ao"
    ],
    "name:zho_x_preferred":[
        "\u91d1\u5bb6\u5c99"
    ],
    "wof:name":"Jinjia'ao",
    "wof:placetype":"locality"
},
  "geometry": {"coordinates":[121.74200999999999,29.411],"type":"Point"}
}