{
  "type": "Feature",
  "properties": {
    "gn:admin1_code":"3.0",
    "gn:asciiname":"Zhoujia",
    "gn:country_code":"CN",
    "gn:dem":53,
    "gn:feature_class":"P",
    "gn:feature_code":"PPL",
    "gn:name":"Zhoujia",
    "gn:population":0,
    "gn:timezone":"Asia/Shanghai",
    "iso:country":"CN",
    "name:und_x_variant":[
        "\u5468\u5bb6"
    ],
    "wof:name":"Zhoujia",
    "wof:placetype":"locality"
},
  "geometry": {"coordinates":[116.25384,27.82626],"type":"Point"}
}