{
  "type": "Feature",
  "properties": {
    "gn:admin1_code":"14.0",
    "gn:asciiname":"Cangcun",
    "gn:country_code":"CN",
    "gn:dem":3773,
    "gn:feature_class":"P",
    "gn:feature_code":"PPL",
    "gn:name":"Cangcun",
    "gn:population":0,
    "gn:timezone":"Asia/Urumqi",
    "iso:country":"CN",
    "name:zho_x_preferred":[
        "\u85cf\u6751"
    ],
    "wof:name":"Cangcun",
    "wof:placetype":"locality"
},
  "geometry": {"coordinates":[93.03106,28.82156],"type":"Point"}
}