{
  "type": "Feature",
  "properties": {
    "gn:admin1_code":"1.0",
    "gn:asciiname":"Xin'an",
    "gn:country_code":"CN",
    "gn:dem":38,
    "gn:feature_class":"P",
    "gn:feature_code":"PPL",
    "gn:name":"Xin\u2019an",
    "gn:population":0,
    "gn:timezone":"Asia/Shanghai",
    "iso:country":"CN",
    "name:und_x_variant":[
        "Hsin-an-chi",
        "Hsin-an",
        "Xin\u2019an"
    ],
    "wof:name":"Xin'an",
    "wof:placetype":"locality"
},
  "geometry": {"coordinates":[116.49417,31.86389],"type":"Point"}
}