{
  "type": "Feature",
  "properties": {
    "gn:admin1_code":"31",
    "gn:asciiname":"Yahan",
    "gn:country_code":"CN",
    "gn:dem":297,
    "gn:feature_class":"P",
    "gn:feature_code":"PPL",
    "gn:name":"Yahan",
    "gn:population":0,
    "gn:timezone":"Asia/Shanghai",
    "iso:country":"CN",
    "name:und_x_variant":[
        "\u7259\u5bd2"
    ],
    "wof:name":"Yahan",
    "wof:placetype":"locality"
},
  "geometry": {"coordinates":[109.67218,19.06109],"type":"Point"}
}