{
  "type": "Feature",
  "properties": {
    "gn:admin1_code":"12.0",
    "gn:asciiname":"Caijia",
    "gn:country_code":"CN",
    "gn:dem":118,
    "gn:feature_class":"P",
    "gn:feature_code":"PPL",
    "gn:name":"Caijia",
    "gn:population":0,
    "gn:timezone":"Asia/Shanghai",
    "iso:country":"CN",
    "name:zho_x_preferred":[
        "Caijia"
    ],
    "name:zho_x_variant":[
        "\u8521\u5bb6"
    ],
    "wof:name":"Caijia",
    "wof:placetype":"locality"
},
  "geometry": {"coordinates":[114.24491,29.57565],"type":"Point"}
}