{
  "type": "Feature",
  "properties": {
    "gn:admin1_code":"11",
    "gn:asciiname":"Xiaopengzai",
    "gn:country_code":"CN",
    "gn:dem":842,
    "gn:feature_class":"P",
    "gn:feature_code":"PPL",
    "gn:name":"Xiaopengzai",
    "gn:population":0,
    "gn:timezone":"Asia/Shanghai",
    "iso:country":"CN",
    "name:zho_x_preferred":[
        "\u5c0f\u670b\u5d3d"
    ],
    "wof:name":"Xiaopengzai",
    "wof:placetype":"locality"
},
  "geometry": {"coordinates":[111.75185999999999,25.11767],"type":"Point"}
}