{
  "type": "Feature",
  "properties": {
    "gn:admin1_code":"12.0",
    "gn:asciiname":"Fengshuzui",
    "gn:country_code":"CN",
    "gn:dem":33,
    "gn:feature_class":"P",
    "gn:feature_code":"PPL",
    "gn:name":"Fengshuzui",
    "gn:population":0,
    "gn:timezone":"Asia/Shanghai",
    "iso:country":"CN",
    "name:zho_x_preferred":[
        "Fengshuzui"
    ],
    "name:zho_x_variant":[
        "\u67ab\u6811\u5480"
    ],
    "wof:name":"Fengshuzui",
    "wof:placetype":"locality"
},
  "geometry": {"coordinates":[115.28351000000001,30.45117],"type":"Point"}
}