{
  "type": "Feature",
  "properties": {
    "gn:admin1_code":"9",
    "gn:asciiname":"Houchenjia",
    "gn:country_code":"CN",
    "gn:dem":51,
    "gn:feature_class":"P",
    "gn:feature_code":"PPL",
    "gn:name":"Houchenjia",
    "gn:population":0,
    "gn:timezone":"Asia/Shanghai",
    "iso:country":"CN",
    "name:zho_x_preferred":[
        "\u540e\u9648\u5bb6"
    ],
    "wof:name":"Houchenjia",
    "wof:placetype":"locality"
},
  "geometry": {"coordinates":[115.21084999999999,36.10962],"type":"Point"}
}