{
  "type": "Feature",
  "properties": {
    "gn:admin1_code":"11.0",
    "gn:asciiname":"Zhuchong",
    "gn:country_code":"CN",
    "gn:dem":382,
    "gn:feature_class":"P",
    "gn:feature_code":"PPL",
    "gn:name":"Zhuchong",
    "gn:population":0,
    "gn:timezone":"Asia/Shanghai",
    "iso:country":"CN",
    "name:zho_x_preferred":[
        "\u7af9\u51b2"
    ],
    "wof:name":"Zhuchong",
    "wof:placetype":"locality"
},
  "geometry": {"coordinates":[109.82326999999999,26.91918],"type":"Point"}
}