{
  "type": "Feature",
  "properties": {
    "gn:admin1_code":"19.0",
    "gn:asciiname":"Tangjiatun",
    "gn:country_code":"CN",
    "gn:dem":10,
    "gn:feature_class":"P",
    "gn:feature_code":"PPL",
    "gn:name":"Tangjiatun",
    "gn:population":0,
    "gn:timezone":"Asia/Shanghai",
    "iso:country":"CN",
    "name:und_x_variant":[
        "\u5510\u5bb6\u5c6f"
    ],
    "name:zho_x_preferred":[
        "\u5510\u5bb6\u5c6f"
    ],
    "wof:name":"Tangjiatun",
    "wof:placetype":"locality"
},
  "geometry": {"coordinates":[122.43852,41.45578],"type":"Point"}
}