{
  "type": "Feature",
  "properties": {
    "gn:admin1_code":"19.0",
    "gn:asciiname":"Tuwobu",
    "gn:country_code":"CN",
    "gn:dem":256,
    "gn:feature_class":"P",
    "gn:feature_code":"PPL",
    "gn:name":"Tuwobu",
    "gn:population":0,
    "gn:timezone":"Asia/Shanghai",
    "iso:country":"CN",
    "name:und_x_variant":[
        "Tuwopu",
        "Tuwobu"
    ],
    "name:zho_x_preferred":[
        "\u571f\u7a9d\u5821"
    ],
    "wof:name":"Tuwobu",
    "wof:placetype":"locality"
},
  "geometry": {"coordinates":[124.678,42.1005],"type":"Point"}
}