{
  "type": "Feature",
  "properties": {
    "gn:admin1_code":"1.0",
    "gn:asciiname":"Rufangshan Linchang",
    "gn:country_code":"CN",
    "gn:dem":99,
    "gn:feature_class":"P",
    "gn:feature_code":"PPLF",
    "gn:name":"Rufangshan Linchang",
    "gn:population":0,
    "gn:timezone":"Asia/Shanghai",
    "iso:country":"CN",
    "wof:name":"Rufangshan Linchang",
    "wof:placetype":"locality"
},
  "geometry": {"coordinates":[118.26654000000001,31.92147000000001],"type":"Point"}
}