{
  "type": "Feature",
  "properties": {
    "gn:admin1_code":"30.0",
    "gn:asciiname":"Beijiao",
    "gn:country_code":"CN",
    "gn:dem":26,
    "gn:feature_class":"P",
    "gn:feature_code":"PPL",
    "gn:name":"Beijiao",
    "gn:population":0,
    "gn:timezone":"Asia/Shanghai",
    "iso:country":"CN",
    "name:ceb_x_preferred":[
        "Beijiao"
    ],
    "name:deu_x_preferred":[
        "Beijiao"
    ],
    "name:swe_x_preferred":[
        "Beijiao"
    ],
    "name:zho_x_preferred":[
        "\u9642\u89d2"
    ],
    "wof:name":"Beijiao",
    "wof:placetype":"locality"
},
  "geometry": {"coordinates":[114.49502,22.8224],"type":"Point"}
}