{
  "type": "Feature",
  "properties": {
    "gn:admin1_code":"16",
    "gn:asciiname":"Tianzhuangqi",
    "gn:country_code":"CN",
    "gn:dem":663,
    "gn:feature_class":"P",
    "gn:feature_code":"PPL",
    "gn:name":"Tianzhuangqi",
    "gn:population":0,
    "gn:timezone":"Asia/Shanghai",
    "iso:country":"CN",
    "name:zho_x_preferred":[
        "\u7530\u5e84\u5c90"
    ],
    "wof:name":"Tianzhuangqi",
    "wof:placetype":"locality"
},
  "geometry": {"coordinates":[110.82899999999999,25.2086],"type":"Point"}
}