{
  "type": "Feature",
  "properties": {
    "gn:admin1_code":"32.0",
    "gn:asciiname":"Yixicun",
    "gn:country_code":"CN",
    "gn:dem":3351,
    "gn:feature_class":"P",
    "gn:feature_code":"PPL",
    "gn:name":"Yixicun",
    "gn:population":0,
    "gn:timezone":"Asia/Shanghai",
    "iso:country":"CN",
    "name:zho_x_preferred":[
        "\u4f9d\u897f\u6751"
    ],
    "wof:name":"Yixicun",
    "wof:placetype":"locality"
},
  "geometry": {"coordinates":[100.315,30.9192],"type":"Point"}
}