{
  "type": "Feature",
  "properties": {
    "gn:admin1_code":"14.0",
    "gn:asciiname":"Parma",
    "gn:country_code":"CN",
    "gn:dem":4576,
    "gn:feature_class":"P",
    "gn:feature_code":"PPLF",
    "gn:name":"Parma",
    "gn:population":0,
    "gn:timezone":"Asia/Urumqi",
    "iso:country":"CN",
    "name:bod_x_preferred":[
        "Parma"
    ],
    "name:zho_x_preferred":[
        "Ba\u2019erma"
    ],
    "name:zho_x_variant":[
        "\u5df4\u5c14\u9a6c",
        "Ruga",
        "\u5982\u560e"
    ],
    "wof:name":"Parma",
    "wof:placetype":"locality"
},
  "geometry": {"coordinates":[84.33333,31.16667],"type":"Point"}
}