{
  "type": "Feature",
  "properties": {
    "gn:admin1_code":"14",
    "gn:asciiname":"Yangbai",
    "gn:country_code":"CN",
    "gn:dem":3966,
    "gn:feature_class":"P",
    "gn:feature_code":"PPL",
    "gn:name":"Yangbai",
    "gn:population":0,
    "gn:timezone":"Asia/Urumqi",
    "iso:country":"CN",
    "name:zho_x_preferred":[
        "\u592e\u767d"
    ],
    "wof:name":"Yangbai",
    "wof:placetype":"locality"
},
  "geometry": {"coordinates":[89.4798,28.9984],"type":"Point"}
}