{
  "type": "Feature",
  "properties": {
    "gn:admin1_code":"12.0",
    "gn:asciiname":"Mochilong",
    "gn:country_code":"CN",
    "gn:dem":82,
    "gn:feature_class":"P",
    "gn:feature_code":"PPL",
    "gn:name":"Mochilong",
    "gn:population":0,
    "gn:timezone":"Asia/Shanghai",
    "iso:country":"CN",
    "name:zho_x_preferred":[
        "Mochilong"
    ],
    "name:zho_x_variant":[
        "\u58a8\u6c60\u5784"
    ],
    "wof:name":"Mochilong",
    "wof:placetype":"locality"
},
  "geometry": {"coordinates":[114.96724,29.70438],"type":"Point"}
}