{
  "type": "Feature",
  "properties": {
    "gn:admin1_code":"30.0",
    "gn:asciiname":"Guozai",
    "gn:country_code":"CN",
    "gn:dem":611,
    "gn:feature_class":"P",
    "gn:feature_code":"PPL",
    "gn:name":"Guozai",
    "gn:population":0,
    "gn:timezone":"Asia/Shanghai",
    "iso:country":"CN",
    "name:zho_x_preferred":[
        "\u9505\u4ed4"
    ],
    "wof:name":"Guozai",
    "wof:placetype":"locality"
},
  "geometry": {"coordinates":[112.61056000000001,24.14583],"type":"Point"}
}