{
  "type": "Feature",
  "properties": {
    "gn:admin1_code":"26.0",
    "gn:asciiname":"Nanyuanpan",
    "gn:country_code":"CN",
    "gn:dem":1426,
    "gn:feature_class":"P",
    "gn:feature_code":"PPL",
    "gn:name":"Nanyuanpan",
    "gn:population":0,
    "gn:timezone":"Asia/Shanghai",
    "iso:country":"CN",
    "name:zho_x_preferred":[
        "\u5357\u586c\u7554"
    ],
    "wof:name":"Nanyuanpan",
    "wof:placetype":"locality"
},
  "geometry": {"coordinates":[109.22226000000001,37.61704],"type":"Point"}
}