{
  "type": "Feature",
  "properties": {
    "gn:admin1_code":"14.0",
    "gn:asciiname":"Jima",
    "gn:country_code":"CN",
    "gn:dem":4366,
    "gn:feature_class":"P",
    "gn:feature_code":"PPL",
    "gn:name":"Jima",
    "gn:population":0,
    "gn:timezone":"Asia/Urumqi",
    "iso:country":"CN",
    "name:zho_x_preferred":[
        "\u9e21\u9a6c"
    ],
    "wof:name":"Jima",
    "wof:placetype":"locality"
},
  "geometry": {"coordinates":[91.19277,29.17274],"type":"Point"}
}