{
  "type": "Feature",
  "properties": {
    "gn:admin1_code":"2.0",
    "gn:asciiname":"Rongsheng",
    "gn:country_code":"CN",
    "gn:dem":45,
    "gn:feature_class":"P",
    "gn:feature_code":"PPL",
    "gn:name":"Rongsheng",
    "gn:population":0,
    "gn:timezone":"Asia/Shanghai",
    "iso:country":"CN",
    "name:zho_x_preferred":[
        "\u8363\u80dc"
    ],
    "wof:name":"Rongsheng",
    "wof:placetype":"locality"
},
  "geometry": {"coordinates":[122.08163,30.06715],"type":"Point"}
}