{
  "type": "Feature",
  "properties": {
    "gn:admin1_code":"10.0",
    "gn:asciiname":"Yuquanli",
    "gn:country_code":"CN",
    "gn:dem":25,
    "gn:feature_class":"P",
    "gn:feature_code":"PPL",
    "gn:name":"Yuquanli",
    "gn:population":0,
    "gn:timezone":"Asia/Shanghai",
    "iso:country":"CN",
    "name:zho_x_preferred":[
        "\u7389\u6cc9\u91cc"
    ],
    "wof:name":"Yuquanli",
    "wof:placetype":"locality"
},
  "geometry": {"coordinates":[119.57626999999999,39.95847],"type":"Point"}
}