{
  "type": "Feature",
  "properties": {
    "gn:admin1_code":"31",
    "gn:asciiname":"Dongtai Nongchang",
    "gn:country_code":"CN",
    "gn:dem":33,
    "gn:feature_class":"P",
    "gn:feature_code":"PPLF",
    "gn:name":"Dongtai Nongchang",
    "gn:population":0,
    "gn:timezone":"Asia/Shanghai",
    "iso:country":"CN",
    "wof:name":"Dongtai Nongchang",
    "wof:placetype":"locality"
},
  "geometry": {"coordinates":[110.22111,19.12083],"type":"Point"}
}