{
  "type": "Feature",
  "properties": {
    "gn:admin1_code":"1.0",
    "gn:asciiname":"Yuwa",
    "gn:country_code":"CN",
    "gn:dem":36,
    "gn:feature_class":"P",
    "gn:feature_code":"PPL",
    "gn:name":"Yuwa",
    "gn:population":0,
    "gn:timezone":"Asia/Shanghai",
    "iso:country":"CN",
    "name:und_x_variant":[
        "Y\u00fc-chia-wa",
        "Nan-hsin-chieh",
        "Yuwa"
    ],
    "name:zho_x_preferred":[
        "\u4e8e\u6d3c"
    ],
    "wof:name":"Yuwa",
    "wof:placetype":"locality"
},
  "geometry": {"coordinates":[118.78386999999999,32.60651],"type":"Point"}
}