{
  "type": "Feature",
  "properties": {
    "gn:admin1_code":"24.0",
    "gn:asciiname":"Qiuquan",
    "gn:country_code":"CN",
    "gn:dem":623,
    "gn:feature_class":"P",
    "gn:feature_code":"PPL",
    "gn:name":"Qiuquan",
    "gn:population":0,
    "gn:timezone":"Asia/Shanghai",
    "iso:country":"CN",
    "name:zho_x_preferred":[
        "\u79cb\u6cc9"
    ],
    "wof:name":"Qiuquan",
    "wof:placetype":"locality"
},
  "geometry": {"coordinates":[112.58901000000002,35.29965],"type":"Point"}
}