{
  "type": "Feature",
  "properties": {
    "gn:admin1_code":"8.0",
    "gn:asciiname":"Juxingcun",
    "gn:country_code":"CN",
    "gn:dem":184,
    "gn:feature_class":"P",
    "gn:feature_code":"PPL",
    "gn:name":"Juxingcun",
    "gn:population":0,
    "gn:timezone":"Asia/Shanghai",
    "iso:country":"CN",
    "name:zho_x_preferred":[
        "\u5de8\u661f\u6751"
    ],
    "wof:name":"Juxingcun",
    "wof:placetype":"locality"
},
  "geometry": {"coordinates":[125.74782999999999,46.64166],"type":"Point"}
}