{
  "type": "Feature",
  "properties": {
    "gn:admin1_code":"16.0",
    "gn:asciiname":"Taining",
    "gn:country_code":"CN",
    "gn:dem":78,
    "gn:feature_class":"P",
    "gn:feature_code":"PPL",
    "gn:name":"Taining",
    "gn:population":0,
    "gn:timezone":"Asia/Shanghai",
    "iso:country":"CN",
    "name:zho_x_preferred":[
        "\u592a\u5b81"
    ],
    "wof:name":"Taining",
    "wof:placetype":"locality"
},
  "geometry": {"coordinates":[109.48999999999999,22.7071],"type":"Point"}
}