{
  "type": "Feature",
  "properties": {
    "gn:admin1_code":"29.0",
    "gn:asciiname":"Guangyi",
    "gn:country_code":"CN",
    "gn:dem":2399,
    "gn:feature_class":"P",
    "gn:feature_code":"PPL",
    "gn:name":"Guangyi",
    "gn:population":0,
    "gn:timezone":"Asia/Shanghai",
    "iso:country":"CN",
    "name:zho_x_preferred":[
        "\u5e7f\u9091"
    ],
    "wof:name":"Guangyi",
    "wof:placetype":"locality"
},
  "geometry": {"coordinates":[99.315,24.8176],"type":"Point"}
}