{
  "type": "Feature",
  "properties": {
    "gn:admin1_code":"26.0",
    "gn:asciiname":"Tuanwanzhang",
    "gn:country_code":"CN",
    "gn:dem":1560,
    "gn:feature_class":"P",
    "gn:feature_code":"PPL",
    "gn:name":"Tuanwanzhang",
    "gn:population":0,
    "gn:timezone":"Asia/Shanghai",
    "iso:country":"CN",
    "name:zho_x_preferred":[
        "\u56e2\u6e7e\u638c"
    ],
    "wof:name":"Tuanwanzhang",
    "wof:placetype":"locality"
},
  "geometry": {"coordinates":[107.46791,37.07448],"type":"Point"}
}