{
  "type": "Feature",
  "properties": {
    "gn:admin1_code":"8.0",
    "gn:asciiname":"Jianshuicun",
    "gn:country_code":"CN",
    "gn:dem":164,
    "gn:feature_class":"P",
    "gn:feature_code":"PPL",
    "gn:name":"Jianshuicun",
    "gn:population":0,
    "gn:timezone":"Asia/Shanghai",
    "iso:country":"CN",
    "name:zho_x_preferred":[
        "\u78b1\u6c34\u6751"
    ],
    "wof:name":"Jianshuicun",
    "wof:placetype":"locality"
},
  "geometry": {"coordinates":[123.08669999999999,46.86637],"type":"Point"}
}