{
  "type": "Feature",
  "properties": {
    "gn:admin1_code":"19.0",
    "gn:asciiname":"Fanzhangzi",
    "gn:country_code":"CN",
    "gn:dem":434,
    "gn:feature_class":"P",
    "gn:feature_code":"PPL",
    "gn:name":"Fanzhangzi",
    "gn:population":0,
    "gn:timezone":"Asia/Shanghai",
    "iso:country":"CN",
    "name:zho_x_preferred":[
        "\u8303\u6756\u5b50"
    ],
    "wof:name":"Fanzhangzi",
    "wof:placetype":"locality"
},
  "geometry": {"coordinates":[119.37578999999999,40.87404],"type":"Point"}
}