{
  "type": "Feature",
  "properties": {
    "gn:admin1_code":"16",
    "gn:asciiname":"Shangtaoyuan",
    "gn:country_code":"CN",
    "gn:dem":252,
    "gn:feature_class":"P",
    "gn:feature_code":"PPL",
    "gn:name":"Shangtaoyuan",
    "gn:population":0,
    "gn:timezone":"Asia/Shanghai",
    "iso:country":"CN",
    "name:zho_x_preferred":[
        "\u4e0a\u6843\u6e90"
    ],
    "wof:name":"Shangtaoyuan",
    "wof:placetype":"locality"
},
  "geometry": {"coordinates":[110.447,25.0299],"type":"Point"}
}