{
  "type": "Feature",
  "properties": {
    "gn:admin1_code":"15.0",
    "gn:asciiname":"Xinshan",
    "gn:country_code":"CN",
    "gn:dem":2045,
    "gn:feature_class":"P",
    "gn:feature_code":"PPL",
    "gn:name":"Xinshan",
    "gn:population":0,
    "gn:timezone":"Asia/Shanghai",
    "iso:country":"CN",
    "name:und_x_variant":[
        "\u65b0\u5c71"
    ],
    "wof:name":"Xinshan",
    "wof:placetype":"locality"
},
  "geometry": {"coordinates":[105.31061,35.43461],"type":"Point"}
}