{
  "type": "Feature",
  "properties": {
    "gn:admin1_code":"4.0",
    "gn:asciiname":"Qianjin Jiuzu",
    "gn:country_code":"CN",
    "gn:dem":1,
    "gn:feature_class":"P",
    "gn:feature_code":"PPLF",
    "gn:name":"Qianjin Jiuzu",
    "gn:population":0,
    "gn:timezone":"Asia/Shanghai",
    "iso:country":"CN",
    "name:zho_x_preferred":[
        "\u524d\u8fdb\u4e5d\u7ec4"
    ],
    "wof:name":"Qianjin Jiuzu",
    "wof:placetype":"locality"
},
  "geometry": {"coordinates":[120.371,33.4948],"type":"Point"}
}