{
  "type": "Feature",
  "properties": {
    "gn:admin1_code":"32.0",
    "gn:asciiname":"Zhoujiaping",
    "gn:country_code":"CN",
    "gn:dem":591,
    "gn:feature_class":"P",
    "gn:feature_code":"PPL",
    "gn:name":"Zhoujiaping",
    "gn:population":0,
    "gn:timezone":"Asia/Shanghai",
    "iso:country":"CN",
    "name:zho_x_preferred":[
        "\u5468\u5bb6\u576a"
    ],
    "wof:name":"Zhoujiaping",
    "wof:placetype":"locality"
},
  "geometry": {"coordinates":[104.75700999999999,29.67601],"type":"Point"}
}