{
  "type": "Feature",
  "properties": {
    "gn:admin1_code":"24.0",
    "gn:asciiname":"Datuo",
    "gn:country_code":"CN",
    "gn:dem":1582,
    "gn:feature_class":"P",
    "gn:feature_code":"PPL",
    "gn:name":"Datuo",
    "gn:population":0,
    "gn:timezone":"Asia/Shanghai",
    "iso:country":"CN",
    "name:zho_x_preferred":[
        "\u8fbe\u9a7c"
    ],
    "wof:name":"Datuo",
    "wof:placetype":"locality"
},
  "geometry": {"coordinates":[113.64969000000001,36.04829],"type":"Point"}
}