{
  "type": "Feature",
  "properties": {
    "gn:admin1_code":"19.0",
    "gn:asciiname":"Beijiangcun",
    "gn:country_code":"CN",
    "gn:dem":192,
    "gn:feature_class":"P",
    "gn:feature_code":"PPL",
    "gn:name":"Beijiangcun",
    "gn:population":0,
    "gn:timezone":"Asia/Shanghai",
    "iso:country":"CN",
    "name:zho_x_preferred":[
        "\u5317\u6c5f\u6751"
    ],
    "wof:name":"Beijiangcun",
    "wof:placetype":"locality"
},
  "geometry": {"coordinates":[125.16352999999999,40.69073],"type":"Point"}
}