{
  "type": "Feature",
  "properties": {
    "gn:admin1_code":"8.0",
    "gn:asciiname":"Tieshan Sandui",
    "gn:country_code":"CN",
    "gn:dem":381,
    "gn:feature_class":"P",
    "gn:feature_code":"PPLF",
    "gn:name":"Tieshan Sandui",
    "gn:population":0,
    "gn:timezone":"Asia/Shanghai",
    "iso:country":"CN",
    "name:zho_x_preferred":[
        "\u94c1\u5c71\u4e09\u961f"
    ],
    "wof:name":"Tieshan Sandui",
    "wof:placetype":"locality"
},
  "geometry": {"coordinates":[126.47175,50.9375],"type":"Point"}
}