{
  "type": "Feature",
  "properties": {
    "gn:admin1_code":"9.0",
    "gn:asciiname":"Heilongmiao",
    "gn:country_code":"CN",
    "gn:dem":157,
    "gn:feature_class":"P",
    "gn:feature_code":"PPL",
    "gn:name":"Heilongmiao",
    "gn:population":0,
    "gn:timezone":"Asia/Shanghai",
    "iso:country":"CN",
    "name:zho_x_preferred":[
        "\u9ed1\u9f99\u5e99"
    ],
    "wof:name":"Heilongmiao",
    "wof:placetype":"locality"
},
  "geometry": {"coordinates":[112.05106000000001,32.93972],"type":"Point"}
}