{
  "type": "Feature",
  "properties": {
    "gn:admin1_code":"30.0",
    "gn:asciiname":"Yanyan",
    "gn:country_code":"CN",
    "gn:dem":122,
    "gn:feature_class":"P",
    "gn:feature_code":"PPL",
    "gn:name":"Yanyan",
    "gn:population":0,
    "gn:timezone":"Asia/Shanghai",
    "iso:country":"CN",
    "name:zho_x_preferred":[
        "Yanyan"
    ],
    "name:zho_x_variant":[
        "\u71d5\u5ca9"
    ],
    "wof:name":"Yanyan",
    "wof:placetype":"locality"
},
  "geometry": {"coordinates":[112.45611,24.53056],"type":"Point"}
}