{
  "type": "Feature",
  "properties": {
    "gn:admin1_code":"4.0",
    "gn:asciiname":"Tianmiaocun",
    "gn:country_code":"CN",
    "gn:dem":26,
    "gn:feature_class":"P",
    "gn:feature_code":"PPL",
    "gn:name":"Tianmiaocun",
    "gn:population":0,
    "gn:timezone":"Asia/Shanghai",
    "iso:country":"CN",
    "name:zho_x_preferred":[
        "\u5929\u5e99\u6751"
    ],
    "wof:name":"Tianmiaocun",
    "wof:placetype":"locality"
},
  "geometry": {"coordinates":[117.83289000000001,34.31848],"type":"Point"}
}