{
  "type": "Feature",
  "properties": {
    "gn:admin1_code":"11.0",
    "gn:asciiname":"Zhongzila",
    "gn:country_code":"CN",
    "gn:dem":625,
    "gn:feature_class":"P",
    "gn:feature_code":"PPL",
    "gn:name":"Zhongzila",
    "gn:population":0,
    "gn:timezone":"Asia/Shanghai",
    "iso:country":"CN",
    "name:zho_x_preferred":[
        "\u4e2d\u5b50\u814a"
    ],
    "wof:name":"Zhongzila",
    "wof:placetype":"locality"
},
  "geometry": {"coordinates":[109.38446999999999,28.39153],"type":"Point"}
}