{
  "type": "Feature",
  "properties": {
    "gn:admin1_code":"32.0",
    "gn:asciiname":"Xiaqishan",
    "gn:country_code":"CN",
    "gn:dem":773,
    "gn:feature_class":"P",
    "gn:feature_code":"PPL",
    "gn:name":"Xiaqishan",
    "gn:population":0,
    "gn:timezone":"Asia/Shanghai",
    "iso:country":"CN",
    "name:zho_x_preferred":[
        "\u4e0b\u542f\u5c71"
    ],
    "wof:name":"Xiaqishan",
    "wof:placetype":"locality"
},
  "geometry": {"coordinates":[107.59166,31.90177000000001],"type":"Point"}
}