{
  "type": "Feature",
  "properties": {
    "gn:admin1_code":"29.0",
    "gn:asciiname":"Jiuhua",
    "gn:country_code":"CN",
    "gn:dem":2119,
    "gn:feature_class":"P",
    "gn:feature_code":"PPL",
    "gn:name":"Jiuhua",
    "gn:population":0,
    "gn:timezone":"Asia/Shanghai",
    "iso:country":"CN",
    "name:und_x_variant":[
        "\u4e5d\u534e"
    ],
    "wof:name":"Jiuhua",
    "wof:placetype":"locality"
},
  "geometry": {"coordinates":[102.7604,25.70551],"type":"Point"}
}