{
  "type": "Feature",
  "properties": {
    "gn:admin1_code":"1.0",
    "gn:asciiname":"Mianxianwu",
    "gn:country_code":"CN",
    "gn:dem":297,
    "gn:feature_class":"P",
    "gn:feature_code":"PPL",
    "gn:name":"Mianxianwu",
    "gn:population":0,
    "gn:timezone":"Asia/Shanghai",
    "iso:country":"CN",
    "name:zho_x_preferred":[
        "\u68c9\u7ebf\u575e"
    ],
    "wof:name":"Mianxianwu",
    "wof:placetype":"locality"
},
  "geometry": {"coordinates":[118.73604,30.41558],"type":"Point"}
}