{
  "type": "Feature",
  "properties": {
    "gn:admin1_code":"7.0",
    "gn:asciiname":"Dongjie",
    "gn:country_code":"CN",
    "gn:dem":11,
    "gn:feature_class":"P",
    "gn:feature_code":"PPLA3",
    "gn:name":"Dongjie",
    "gn:population":0,
    "gn:timezone":"Asia/Shanghai",
    "iso:country":"CN",
    "name:und_x_variant":[
        "\u4e1c\u8857",
        "Dongjie Jiedao",
        "\u4e1c\u8857\u8857\u9053"
    ],
    "name:zho_x_preferred":[
        "Dongjie"
    ],
    "wof:name":"Dongjie",
    "wof:placetype":"locality"
},
  "geometry": {"coordinates":[119.29449,26.08823],"type":"Point"}
}