{
  "type": "Feature",
  "properties": {
    "gn:admin1_code":"29",
    "gn:asciiname":"Xiaoyishe",
    "gn:country_code":"CN",
    "gn:dem":1908,
    "gn:feature_class":"P",
    "gn:feature_code":"PPL",
    "gn:name":"Xiaoyishe",
    "gn:population":0,
    "gn:timezone":"Asia/Shanghai",
    "iso:country":"CN",
    "name:zho_x_preferred":[
        "\u5c0f\u9091\u820d"
    ],
    "wof:name":"Xiaoyishe",
    "wof:placetype":"locality"
},
  "geometry": {"coordinates":[101.443,24.8362],"type":"Point"}
}