{
  "type": "Feature",
  "properties": {
    "gn:admin1_code":"16.0",
    "gn:asciiname":"Qincaichong",
    "gn:country_code":"CN",
    "gn:dem":391,
    "gn:feature_class":"P",
    "gn:feature_code":"PPL",
    "gn:name":"Qincaichong",
    "gn:population":0,
    "gn:timezone":"Asia/Shanghai",
    "iso:country":"CN",
    "name:zho_x_preferred":[
        "\u82b9\u83dc\u51b2"
    ],
    "wof:name":"Qincaichong",
    "wof:placetype":"locality"
},
  "geometry": {"coordinates":[110.929,24.872],"type":"Point"}
}