{
  "type": "Feature",
  "properties": {
    "gn:admin1_code":"29.0",
    "gn:asciiname":"Nagu",
    "gn:country_code":"CN",
    "gn:dem":2103,
    "gn:feature_class":"P",
    "gn:feature_code":"PPL",
    "gn:name":"Nagu",
    "gn:population":0,
    "gn:timezone":"Asia/Shanghai",
    "iso:country":"CN",
    "name:zho_x_preferred":[
        "\u90a3\u59d1"
    ],
    "wof:name":"Nagu",
    "wof:placetype":"locality"
},
  "geometry": {"coordinates":[104.47499999999999,26.3631],"type":"Point"}
}