{
  "type": "Feature",
  "properties": {
    "gn:admin1_code":"2.0",
    "gn:asciiname":"Baixianshan Linqu",
    "gn:country_code":"CN",
    "gn:dem":373,
    "gn:feature_class":"P",
    "gn:feature_code":"PPLF",
    "gn:name":"Baixianshan Linqu",
    "gn:population":0,
    "gn:timezone":"Asia/Shanghai",
    "iso:country":"CN",
    "name:zho_x_preferred":[
        "\u767d\u4ed9\u5c71\u6797\u533a"
    ],
    "wof:name":"Baixianshan Linqu",
    "wof:placetype":"locality"
},
  "geometry": {"coordinates":[121.77549999999999,29.40888],"type":"Point"}
}