{
  "type": "Feature",
  "properties": {
    "gn:admin1_code":"19.0",
    "gn:asciiname":"Yangcezi",
    "gn:country_code":"CN",
    "gn:dem":350,
    "gn:feature_class":"P",
    "gn:feature_code":"PPL",
    "gn:name":"Yangcezi",
    "gn:population":0,
    "gn:timezone":"Asia/Shanghai",
    "iso:country":"CN",
    "name:und_x_variant":[
        "\u6837\u518c\u5b50"
    ],
    "name:zho_x_preferred":[
        "\u6837\u518c\u5b50"
    ],
    "wof:name":"Yangcezi",
    "wof:placetype":"locality"
},
  "geometry": {"coordinates":[124.88074,40.97136],"type":"Point"}
}