{
  "type": "Feature",
  "properties": {
    "gn:admin1_code":"32.0",
    "gn:asciiname":"Yanjing",
    "gn:country_code":"CN",
    "gn:dem":2550,
    "gn:feature_class":"P",
    "gn:feature_code":"PPLA3",
    "gn:name":"Yanjing",
    "gn:population":0,
    "gn:timezone":"Asia/Shanghai",
    "iso:country":"CN",
    "name:ara_x_preferred":[
        "\u064a\u0627\u0646\u062c\u064a\u0646\u063a"
    ],
    "name:nor_x_preferred":[
        "Fanyang"
    ],
    "name:und_x_variant":[
        "Pai-yen-ching",
        "Yen-ching",
        "Yanyuan",
        "Yen-ching-hsiang",
        "Yen-y\u00fcan",
        "Yanjing"
    ],
    "name:zho_x_preferred":[
        "\u76d0\u4e95"
    ],
    "wof:name":"Yanjing",
    "wof:placetype":"locality"
},
  "geometry": {"coordinates":[101.50968,27.42699],"type":"Point"}
}