{
  "type": "Feature",
  "properties": {
    "gn:admin1_code":"24.0",
    "gn:asciiname":"Houjiao",
    "gn:country_code":"CN",
    "gn:dem":1378,
    "gn:feature_class":"P",
    "gn:feature_code":"PPL",
    "gn:name":"Houjiao",
    "gn:population":0,
    "gn:timezone":"Asia/Shanghai",
    "iso:country":"CN",
    "name:zho_x_preferred":[
        "\u540e\u4ea4"
    ],
    "wof:name":"Houjiao",
    "wof:placetype":"locality"
},
  "geometry": {"coordinates":[112.1439,35.42484],"type":"Point"}
}