{
  "type": "Feature",
  "properties": {
    "gn:admin1_code":"2",
    "gn:asciiname":"Jianzhoucun",
    "gn:country_code":"CN",
    "gn:dem":460,
    "gn:feature_class":"P",
    "gn:feature_code":"PPL",
    "gn:name":"Jianzhoucun",
    "gn:population":0,
    "gn:timezone":"Asia/Shanghai",
    "iso:country":"CN",
    "name:und_x_variant":[
        "Jianzhou",
        "Jianzhoucun"
    ],
    "name:zho_x_preferred":[
        "\u622c\u5dde\u6751"
    ],
    "wof:name":"Jianzhoucun",
    "wof:placetype":"locality"
},
  "geometry": {"coordinates":[119.91571,27.45392],"type":"Point"}
}