{
  "type": "Feature",
  "properties": {
    "gn:admin1_code":"3.0",
    "gn:asciiname":"Shengbei",
    "gn:country_code":"CN",
    "gn:dem":110,
    "gn:feature_class":"P",
    "gn:feature_code":"PPL",
    "gn:name":"Shengbei",
    "gn:population":0,
    "gn:timezone":"Asia/Shanghai",
    "iso:country":"CN",
    "name:und_x_variant":[
        "\u5d4a\u5317"
    ],
    "wof:name":"Shengbei",
    "wof:placetype":"locality"
},
  "geometry": {"coordinates":[116.55670000000001,27.2054],"type":"Point"}
}