{
  "type": "Feature",
  "properties": {
    "gn:admin1_code":"32.0",
    "gn:asciiname":"Maolinxiang",
    "gn:country_code":"CN",
    "gn:dem":392,
    "gn:feature_class":"P",
    "gn:feature_code":"PPL",
    "gn:name":"Maolinxiang",
    "gn:population":0,
    "gn:timezone":"Asia/Shanghai",
    "iso:country":"CN",
    "name:zho_x_preferred":[
        "\u6bdb\u6797\u5df7"
    ],
    "wof:name":"Maolinxiang",
    "wof:placetype":"locality"
},
  "geometry": {"coordinates":[103.84768,29.8751],"type":"Point"}
}