{
  "type": "Feature",
  "properties": {
    "gn:admin1_code":"8.0",
    "gn:asciiname":"Yufacun",
    "gn:country_code":"CN",
    "gn:dem":89,
    "gn:feature_class":"P",
    "gn:feature_code":"PPL",
    "gn:name":"Yufacun",
    "gn:population":0,
    "gn:timezone":"Asia/Shanghai",
    "iso:country":"CN",
    "name:zho_x_preferred":[
        "\u80b2\u53d1\u6751"
    ],
    "wof:name":"Yufacun",
    "wof:placetype":"locality"
},
  "geometry": {"coordinates":[129.93916999999999,48.98851],"type":"Point"}
}