{
  "type": "Feature",
  "properties": {
    "gn:admin1_code":"15.0",
    "gn:asciiname":"Chujia Goumen",
    "gn:country_code":"CN",
    "gn:dem":1477,
    "gn:feature_class":"P",
    "gn:feature_code":"PPL",
    "gn:name":"Chujia Goumen",
    "gn:population":0,
    "gn:timezone":"Asia/Shanghai",
    "iso:country":"CN",
    "name:zho_x_preferred":[
        "\u695a\u5bb6\u6c9f\u95e8"
    ],
    "wof:name":"Chujia Goumen",
    "wof:placetype":"locality"
},
  "geometry": {"coordinates":[105.15300000000001,34.2444],"type":"Point"}
}