{
  "type": "Feature",
  "properties": {
    "gn:admin1_code":"19.0",
    "gn:asciiname":"Hongqilingcun",
    "gn:country_code":"CN",
    "gn:dem":188,
    "gn:feature_class":"P",
    "gn:feature_code":"PPL",
    "gn:name":"Hongqilingcun",
    "gn:population":0,
    "gn:timezone":"Asia/Shanghai",
    "iso:country":"CN",
    "name:zho_x_preferred":[
        "\u7ea2\u65d7\u5cad\u6751"
    ],
    "wof:name":"Hongqilingcun",
    "wof:placetype":"locality"
},
  "geometry": {"coordinates":[122.8648,40.55517],"type":"Point"}
}