{
  "type": "Feature",
  "properties": {
    "gn:admin1_code":"30.0",
    "gn:asciiname":"Yongbian",
    "gn:country_code":"CN",
    "gn:dem":33,
    "gn:feature_class":"P",
    "gn:feature_code":"PPL",
    "gn:name":"Yongbian",
    "gn:population":0,
    "gn:timezone":"Asia/Shanghai",
    "iso:country":"CN",
    "name:und_x_variant":[
        "\u6d8c\u8fb9"
    ],
    "name:zho_x_preferred":[
        "\u6d8c\u8fb9"
    ],
    "wof:name":"Yongbian",
    "wof:placetype":"locality"
},
  "geometry": {"coordinates":[113.31564,22.91689],"type":"Point"}
}