{
  "type": "Feature",
  "properties": {
    "gn:admin1_code":"02",
    "gn:asciiname":"Qiuwangcun",
    "gn:country_code":"CN",
    "gn:dem":39,
    "gn:feature_class":"P",
    "gn:feature_code":"PPL",
    "gn:name":"Qiuwangcun",
    "gn:population":0,
    "gn:timezone":"Asia/Shanghai",
    "iso:country":"CN",
    "name:und_x_variant":[
        "Ch\u2019iu-wang",
        "Yanmen",
        "Qiuwang",
        "\u90b1\u738b",
        "Qiuwangcun"
    ],
    "name:zho_x_preferred":[
        "\u90b1\u738b\u6751"
    ],
    "wof:name":"Qiuwangcun",
    "wof:placetype":"locality"
},
  "geometry": {"coordinates":[121.56873,30.06488],"type":"Point"}
}