{
  "type": "Feature",
  "properties": {
    "gn:admin1_code":"16.0",
    "gn:asciiname":"Xincun'er",
    "gn:country_code":"CN",
    "gn:dem":40,
    "gn:feature_class":"P",
    "gn:feature_code":"PPL",
    "gn:name":"Xincun\u2019er",
    "gn:population":0,
    "gn:timezone":"Asia/Shanghai",
    "iso:country":"CN",
    "name:und_x_variant":[
        "Xincun\u2019er"
    ],
    "name:zho_x_preferred":[
        "\u65b0\u6751\u513f"
    ],
    "wof:name":"Xincun'er",
    "wof:placetype":"locality"
},
  "geometry": {"coordinates":[110.20699999999999,23.4966],"type":"Point"}
}