{
  "type": "Feature",
  "properties": {
    "gn:admin1_code":"8.0",
    "gn:asciiname":"Linhecun",
    "gn:country_code":"CN",
    "gn:dem":265,
    "gn:feature_class":"P",
    "gn:feature_code":"PPL",
    "gn:name":"Linhecun",
    "gn:population":0,
    "gn:timezone":"Asia/Shanghai",
    "iso:country":"CN",
    "name:zho_x_preferred":[
        "\u4e34\u6cb3\u6751"
    ],
    "wof:name":"Linhecun",
    "wof:placetype":"locality"
},
  "geometry": {"coordinates":[126.48902,48.61812000000001],"type":"Point"}
}