{
  "type": "Feature",
  "properties": {
    "gn:admin1_code":"2.0",
    "gn:asciiname":"Dabeishan",
    "gn:country_code":"CN",
    "gn:dem":34,
    "gn:feature_class":"P",
    "gn:feature_code":"PPL",
    "gn:name":"Dabeishan",
    "gn:population":0,
    "gn:timezone":"Asia/Shanghai",
    "iso:country":"CN",
    "name:zho_x_preferred":[
        "\u5927\u8d1d\u5c71"
    ],
    "wof:name":"Dabeishan",
    "wof:placetype":"locality"
},
  "geometry": {"coordinates":[121.65586999999999,29.44832],"type":"Point"}
}