{
  "type": "Feature",
  "properties": {
    "gn:admin1_code":"12.0",
    "gn:asciiname":"Qiwudun",
    "gn:country_code":"CN",
    "gn:dem":24,
    "gn:feature_class":"P",
    "gn:feature_code":"PPL",
    "gn:name":"Qiwudun",
    "gn:population":0,
    "gn:timezone":"Asia/Shanghai",
    "iso:country":"CN",
    "name:zho_x_preferred":[
        "\u4e03\u5c4b\u58a9"
    ],
    "wof:name":"Qiwudun",
    "wof:placetype":"locality"
},
  "geometry": {"coordinates":[113.26774,29.93953],"type":"Point"}
}