{
  "type": "Feature",
  "properties": {
    "gn:admin1_code":"24",
    "gn:asciiname":"Xinzhouwo",
    "gn:cc2":"CN",
    "gn:country_code":"CN",
    "gn:dem":1252,
    "gn:feature_class":"P",
    "gn:feature_code":"PPL",
    "gn:name":"Xinzhouwo",
    "gn:population":0,
    "gn:timezone":"Asia/Shanghai",
    "iso:country":"CN",
    "name:und_x_variant":[
        "Hsin-chou-wo",
        "Xinzhouwo"
    ],
    "wof:name":"Xinzhouwo",
    "wof:placetype":"locality"
},
  "geometry": {"coordinates":[113.09999999999999,40.05],"type":"Point"}
}