{
  "type": "Feature",
  "properties": {
    "gn:admin1_code":"24.0",
    "gn:asciiname":"Xiaxin'an",
    "gn:country_code":"CN",
    "gn:dem":1251,
    "gn:feature_class":"P",
    "gn:feature_code":"PPL",
    "gn:name":"Xiaxin\u2019an",
    "gn:population":0,
    "gn:timezone":"Asia/Shanghai",
    "iso:country":"CN",
    "name:und_x_variant":[
        "\u4e0b\u8f9b\u5b89"
    ],
    "name:zho_x_preferred":[
        "Xiaxin\u2019an"
    ],
    "name:zho_x_variant":[
        "\u4e0b\u8f9b\u5b89"
    ],
    "wof:name":"Xiaxin'an",
    "wof:placetype":"locality"
},
  "geometry": {"coordinates":[113.64081000000002,39.84423],"type":"Point"}
}