{
  "type": "Feature",
  "properties": {
    "gn:admin1_code":"19.0",
    "gn:asciiname":"Simajiazi",
    "gn:country_code":"CN",
    "gn:dem":95,
    "gn:feature_class":"P",
    "gn:feature_code":"PPL",
    "gn:name":"Simajiazi",
    "gn:population":0,
    "gn:timezone":"Asia/Shanghai",
    "iso:country":"CN",
    "name:zho_x_preferred":[
        "\u56db\u9a6c\u67b6\u5b50"
    ],
    "wof:name":"Simajiazi",
    "wof:placetype":"locality"
},
  "geometry": {"coordinates":[123.617,43.0396],"type":"Point"}
}