{
  "type": "Feature",
  "properties": {
    "gn:admin1_code":"11.0",
    "gn:asciiname":"Fanong",
    "gn:country_code":"CN",
    "gn:dem":94,
    "gn:feature_class":"P",
    "gn:feature_code":"PPL",
    "gn:name":"Fanong",
    "gn:population":0,
    "gn:timezone":"Asia/Shanghai",
    "iso:country":"CN",
    "name:zho_x_preferred":[
        "\u53d1\u519c"
    ],
    "wof:name":"Fanong",
    "wof:placetype":"locality"
},
  "geometry": {"coordinates":[113.2316,26.98952],"type":"Point"}
}