{
  "type": "Feature",
  "properties": {
    "gn:admin1_code":"9.0",
    "gn:asciiname":"Wenzhuang",
    "gn:country_code":"CN",
    "gn:dem":46,
    "gn:feature_class":"P",
    "gn:feature_code":"PPL",
    "gn:name":"Wenzhuang",
    "gn:population":0,
    "gn:timezone":"Asia/Shanghai",
    "iso:country":"CN",
    "name:zho_x_preferred":[
        "\u6587\u5e84"
    ],
    "wof:name":"Wenzhuang",
    "wof:placetype":"locality"
},
  "geometry": {"coordinates":[114.90971999999999,32.43864],"type":"Point"}
}