{
  "type": "Feature",
  "properties": {
    "gn:admin1_code":"9.0",
    "gn:asciiname":"Xingyao",
    "gn:country_code":"CN",
    "gn:dem":592,
    "gn:feature_class":"P",
    "gn:feature_code":"PPL",
    "gn:name":"Xingyao",
    "gn:population":0,
    "gn:timezone":"Asia/Shanghai",
    "iso:country":"CN",
    "name:zho_x_preferred":[
        "\u90a2\u7a91"
    ],
    "wof:name":"Xingyao",
    "wof:placetype":"locality"
},
  "geometry": {"coordinates":[113.05497,34.20848],"type":"Point"}
}