{
  "type": "Feature",
  "properties": {
    "gn:admin1_code":"11.0",
    "gn:asciiname":"Longliwu",
    "gn:country_code":"CN",
    "gn:dem":232,
    "gn:feature_class":"P",
    "gn:feature_code":"PPL",
    "gn:name":"Longliwu",
    "gn:population":0,
    "gn:timezone":"Asia/Shanghai",
    "iso:country":"CN",
    "name:zho_x_preferred":[
        "\u5785\u91cc\u5c4b"
    ],
    "wof:name":"Longliwu",
    "wof:placetype":"locality"
},
  "geometry": {"coordinates":[113.86897,26.9057],"type":"Point"}
}