{
  "type": "Feature",
  "properties": {
    "gn:admin1_code":"16.0",
    "gn:asciiname":"Dabantai",
    "gn:country_code":"CN",
    "gn:dem":759,
    "gn:feature_class":"P",
    "gn:feature_code":"PPL",
    "gn:name":"Dabantai",
    "gn:population":0,
    "gn:timezone":"Asia/Shanghai",
    "iso:country":"CN",
    "name:zho_x_preferred":[
        "\u5927\u677f\u53f0"
    ],
    "wof:name":"Dabantai",
    "wof:placetype":"locality"
},
  "geometry": {"coordinates":[107.071,25.3863],"type":"Point"}
}