{
  "type": "Feature",
  "properties": {
    "gn:admin1_code":"30.0",
    "gn:asciiname":"Fengguangcun",
    "gn:country_code":"CN",
    "gn:dem":378,
    "gn:feature_class":"P",
    "gn:feature_code":"PPL",
    "gn:name":"Fengguangcun",
    "gn:population":0,
    "gn:timezone":"Asia/Shanghai",
    "iso:country":"CN",
    "name:und_x_variant":[
        "Fengguang"
    ],
    "name:zho_x_preferred":[
        "\u51e4\u5149\u6751"
    ],
    "name:zho_x_variant":[
        "\u98ce\u5149"
    ],
    "wof:name":"Fengguangcun",
    "wof:placetype":"locality"
},
  "geometry": {"coordinates":[116.65657,23.88211],"type":"Point"}
}