{
  "type": "Feature",
  "properties": {
    "gn:admin1_code":"12.0",
    "gn:asciiname":"Dongbeizhou",
    "gn:country_code":"CN",
    "gn:dem":30,
    "gn:feature_class":"P",
    "gn:feature_code":"PPL",
    "gn:name":"Dongbeizhou",
    "gn:population":0,
    "gn:timezone":"Asia/Shanghai",
    "iso:country":"CN",
    "name:zho_x_preferred":[
        "\u4e1c\u5317\u6d32"
    ],
    "wof:name":"Dongbeizhou",
    "wof:placetype":"locality"
},
  "geometry": {"coordinates":[113.06725,29.54856],"type":"Point"}
}