{
  "type": "Feature",
  "properties": {
    "iso:country":"CN",
    "qs:name":"\u8428\u8fe6",
    "qs:name_adm0":"\u4e2d\u570b",
    "qs:name_adm1":"\u897f\u85cf\u81ea\u6cbb\u533a",
    "qs:photos":353,
    "qs:photos_1k":72,
    "qs:photos_9k":2,
    "qs:photos_9r":5,
    "qs:photos_all":353,
    "qs:photos_sr":6,
    "qs:placetype":"Town",
    "qs:pop_sr":"0",
    "wd:wordcount":119,
    "wof:name":"\u8428\u8fe6",
    "wof:placetype":"locality"
},
  "geometry": {"coordinates":[88.016452,28.90961],"type":"Point"}
}