{
  "type": "Feature",
  "properties": {
    "iso:country":"CN",
    "name:bod_x_preferred":[
        "\u0f66\u0f0b\u0f66\u0f90\u0fb1\u0f0b\u0f62\u0fab\u0f7c\u0f44\u0f0b\u0f0d"
    ],
    "name:ceb_x_preferred":[
        "Sajia Xian"
    ],
    "name:deu_x_preferred":[
        "Sa\u2019gya"
    ],
    "name:eng_x_preferred":[
        "Sa'gya County"
    ],
    "name:fas_x_preferred":[
        "\u0634\u0647\u0631\u0633\u062a\u0627\u0646 \u0633\u0627\u06af\u06cc\u0627"
    ],
    "name:gan_x_preferred":[
        "\u8428\u8fe6\u53bf"
    ],
    "name:jpn_x_preferred":[
        "\u30b5\u30ad\u30e3\u770c"
    ],
    "name:kor_x_preferred":[
        "\uc2f8\uc790\ud604"
    ],
    "name:nan_x_preferred":[
        "Sa'gya-ko\u0101n"
    ],
    "name:nld_x_preferred":[
        "Sakya"
    ],
    "name:nob_x_preferred":[
        "Sa'gya"
    ],
    "name:pol_x_preferred":[
        "Sa\u2019gya"
    ],
    "name:rus_x_preferred":[
        "\u0421\u0430\u043a\u044c\u044f"
    ],
    "name:swe_x_preferred":[
        "Sakya"
    ],
    "name:urd_x_preferred":[
        "\u0633\u0627\u06af\u06cc\u0627 \u06a9\u0627\u0624\u0646\u0679\u06cc"
    ],
    "name:vie_x_preferred":[
        "Sa'gya"
    ],
    "name:wuu_x_preferred":[
        "\u8428\u8fe6\u53bf"
    ],
    "name:zho_x_preferred":[
        "\u8428\u8fe6\u53bf"
    ],
    "qs:name":"\u8428\u8fe6",
    "qs:name_adm0":"\u4e2d\u570b",
    "qs:name_adm1":"\u897f\u85cf\u81ea\u6cbb\u533a",
    "qs:photos":353,
    "qs:photos_1k":72,
    "qs:photos_9k":2,
    "qs:photos_9r":5,
    "qs:photos_all":353,
    "qs:photos_sr":6,
    "qs:placetype":"Town",
    "qs:pop_sr":"0",
    "wd:wordcount":119,
    "wof:name":"\u8428\u8fe6",
    "wof:placetype":"locality"
},
  "geometry": {"coordinates":[88.016452,28.90961],"type":"Point"}
}