{
  "type": "Feature",
  "properties": {
    "gn:admin1_code":"7",
    "gn:asciiname":"Dingliao",
    "gn:country_code":"CN",
    "gn:dem":531,
    "gn:feature_class":"P",
    "gn:feature_code":"PPL",
    "gn:name":"Dingliao",
    "gn:population":0,
    "gn:timezone":"Asia/Shanghai",
    "iso:country":"CN",
    "name:zho_x_preferred":[
        "\u9876\u5bee"
    ],
    "wof:name":"Dingliao",
    "wof:placetype":"locality"
},
  "geometry": {"coordinates":[118.0346,24.97777],"type":"Point"}
}