{
  "type": "Feature",
  "properties": {
    "gn:admin1_code":"9",
    "gn:asciiname":"Shanyuantuan",
    "gn:country_code":"CN",
    "gn:dem":53,
    "gn:feature_class":"P",
    "gn:feature_code":"PPL",
    "gn:name":"Shanyuantuan",
    "gn:population":0,
    "gn:timezone":"Asia/Shanghai",
    "iso:country":"CN",
    "name:zho_x_preferred":[
        "\u5584\u7f18\u7583"
    ],
    "wof:name":"Shanyuantuan",
    "wof:placetype":"locality"
},
  "geometry": {"coordinates":[115.10123,36.08198],"type":"Point"}
}