{
  "type": "Feature",
  "properties": {
    "gn:admin1_code":"12.0",
    "gn:asciiname":"Hongtugou",
    "gn:country_code":"CN",
    "gn:dem":441,
    "gn:feature_class":"P",
    "gn:feature_code":"PPL",
    "gn:name":"Hongtugou",
    "gn:population":0,
    "gn:timezone":"Asia/Shanghai",
    "iso:country":"CN",
    "name:zho_x_preferred":[
        "\u7ea2\u571f\u6c9f"
    ],
    "wof:name":"Hongtugou",
    "wof:placetype":"locality"
},
  "geometry": {"coordinates":[111.86159000000001,31.53271],"type":"Point"}
}