{
  "type": "Feature",
  "properties": {
    "gn:admin1_code":"32.0",
    "gn:asciiname":"Yuwazhai",
    "gn:country_code":"CN",
    "gn:dem":2606,
    "gn:feature_class":"P",
    "gn:feature_code":"PPL",
    "gn:name":"Yuwazhai",
    "gn:population":0,
    "gn:timezone":"Asia/Shanghai",
    "iso:country":"CN",
    "name:zho_x_preferred":[
        "\u7389\u74e6\u5be8"
    ],
    "wof:name":"Yuwazhai",
    "wof:placetype":"locality"
},
  "geometry": {"coordinates":[103.88751999999999,33.64108],"type":"Point"}
}