{
  "type": "Feature",
  "properties": {
    "gn:admin1_code":"33",
    "gn:asciiname":"Pingtan",
    "gn:country_code":"CN",
    "gn:dem":264,
    "gn:feature_class":"P",
    "gn:feature_code":"PPLA4",
    "gn:name":"Pingtan",
    "gn:population":0,
    "gn:timezone":"Asia/Shanghai",
    "iso:country":"CN",
    "name:ceb_x_preferred":[
        "Pingtan"
    ],
    "name:und_x_variant":[
        "Pingtan Zhen"
    ],
    "name:zho_x_preferred":[
        "\u5e73\u6ee9"
    ],
    "name:zho_x_variant":[
        "\u5e73\u6ee9\u9547"
    ],
    "wof:name":"Pingtan",
    "wof:placetype":"locality"
},
  "geometry": {"coordinates":[105.87782,29.84594],"type":"Point"}
}