{
  "type": "Feature",
  "properties": {
    "gn:admin1_code":"7.0",
    "gn:asciiname":"Wuchangping",
    "gn:country_code":"CN",
    "gn:dem":344,
    "gn:feature_class":"P",
    "gn:feature_code":"PPL",
    "gn:name":"Wuchangping",
    "gn:population":0,
    "gn:timezone":"Asia/Shanghai",
    "iso:country":"CN",
    "name:und_x_variant":[
        "\u5c4b\u957f\u576a"
    ],
    "name:zho_x_preferred":[
        "\u5c4b\u957f\u576a"
    ],
    "wof:name":"Wuchangping",
    "wof:placetype":"locality"
},
  "geometry": {"coordinates":[116.65598,26.29471],"type":"Point"}
}