{
  "type": "Feature",
  "properties": {
    "gn:admin1_code":"29.0",
    "gn:asciiname":"Kuanhaizi",
    "gn:country_code":"CN",
    "gn:dem":2576,
    "gn:feature_class":"P",
    "gn:feature_code":"PPL",
    "gn:name":"Kuanhaizi",
    "gn:population":0,
    "gn:timezone":"Asia/Shanghai",
    "iso:country":"CN",
    "name:zho_x_preferred":[
        "\u5bbd\u6d77\u5b50"
    ],
    "wof:name":"Kuanhaizi",
    "wof:placetype":"locality"
},
  "geometry": {"coordinates":[102.961,25.584],"type":"Point"}
}