{
  "type": "Feature",
  "properties": {
    "gn:admin1_code":"16.0",
    "gn:asciiname":"Gengbang",
    "gn:country_code":"CN",
    "gn:dem":848,
    "gn:feature_class":"P",
    "gn:feature_code":"PPL",
    "gn:name":"Gengbang",
    "gn:population":0,
    "gn:timezone":"Asia/Shanghai",
    "iso:country":"CN",
    "name:zho_x_preferred":[
        "\u66f4\u68d2"
    ],
    "wof:name":"Gengbang",
    "wof:placetype":"locality"
},
  "geometry": {"coordinates":[105.86199999999999,23.2892],"type":"Point"}
}