{
  "type": "Feature",
  "properties": {
    "gn:admin1_code":"12.0",
    "gn:asciiname":"Jinzhuping",
    "gn:country_code":"CN",
    "gn:dem":267,
    "gn:feature_class":"P",
    "gn:feature_code":"PPL",
    "gn:name":"Jinzhuping",
    "gn:population":0,
    "gn:timezone":"Asia/Shanghai",
    "iso:country":"CN",
    "name:zho_x_preferred":[
        "Jinzhuping"
    ],
    "name:zho_x_variant":[
        "\u91d1\u7af9\u576a"
    ],
    "wof:name":"Jinzhuping",
    "wof:placetype":"locality"
},
  "geometry": {"coordinates":[111.40701,30.99702000000001],"type":"Point"}
}