{
  "type": "Feature",
  "properties": {
    "gn:admin1_code":"15.0",
    "gn:asciiname":"Zhangqu",
    "gn:country_code":"CN",
    "gn:dem":1306,
    "gn:feature_class":"P",
    "gn:feature_code":"PPL",
    "gn:name":"Zhangqu",
    "gn:population":0,
    "gn:timezone":"Asia/Shanghai",
    "iso:country":"CN",
    "name:zho_x_preferred":[
        "\u638c\u66f2"
    ],
    "wof:name":"Zhangqu",
    "wof:placetype":"locality"
},
  "geometry": {"coordinates":[107.256,35.3266],"type":"Point"}
}