{
  "type": "Feature",
  "properties": {
    "gn:admin1_code":"24.0",
    "gn:asciiname":"Baishuilingcun",
    "gn:country_code":"CN",
    "gn:dem":883,
    "gn:feature_class":"P",
    "gn:feature_code":"PPL",
    "gn:name":"Baishuilingcun",
    "gn:population":0,
    "gn:timezone":"Asia/Shanghai",
    "iso:country":"CN",
    "name:zho_x_preferred":[
        "\u767d\u6c34\u5cad\u6751"
    ],
    "wof:name":"Baishuilingcun",
    "wof:placetype":"locality"
},
  "geometry": {"coordinates":[114.18817,39.122],"type":"Point"}
}