{
  "type": "Feature",
  "properties": {
    "gn:admin1_code":"26.0",
    "gn:asciiname":"Pangjiayaozecun",
    "gn:country_code":"CN",
    "gn:dem":1094,
    "gn:feature_class":"P",
    "gn:feature_code":"PPL",
    "gn:name":"Pangjiayaozecun",
    "gn:population":0,
    "gn:timezone":"Asia/Shanghai",
    "iso:country":"CN",
    "name:zho_x_preferred":[
        "\u5e9e\u5bb6\u7a91\u5219\u6751"
    ],
    "wof:name":"Pangjiayaozecun",
    "wof:placetype":"locality"
},
  "geometry": {"coordinates":[110.23963000000001,38.41869000000001],"type":"Point"}
}