{
  "type": "Feature",
  "properties": {
    "gn:admin1_code":"29.0",
    "gn:asciiname":"Bangdang",
    "gn:country_code":"CN",
    "gn:dem":1581,
    "gn:feature_class":"P",
    "gn:feature_code":"PPL",
    "gn:name":"Bangdang",
    "gn:population":0,
    "gn:timezone":"Asia/Shanghai",
    "iso:country":"CN",
    "name:zho_x_preferred":[
        "\u68d2\u5f53"
    ],
    "wof:name":"Bangdang",
    "wof:placetype":"locality"
},
  "geometry": {"coordinates":[98.6708,27.8985],"type":"Point"}
}