{
  "type": "Feature",
  "properties": {
    "gn:admin1_code":"12.0",
    "gn:asciiname":"Houshangou",
    "gn:country_code":"CN",
    "gn:dem":525,
    "gn:feature_class":"P",
    "gn:feature_code":"PPL",
    "gn:name":"Houshangou",
    "gn:population":0,
    "gn:timezone":"Asia/Shanghai",
    "iso:country":"CN",
    "name:zho_x_preferred":[
        "\u540e\u5c71\u6c9f"
    ],
    "wof:name":"Houshangou",
    "wof:placetype":"locality"
},
  "geometry": {"coordinates":[109.53706,30.21446],"type":"Point"}
}