{
  "type": "Feature",
  "properties": {
    "gn:admin1_code":"16.0",
    "gn:asciiname":"Weibang",
    "gn:country_code":"CN",
    "gn:dem":837,
    "gn:feature_class":"P",
    "gn:feature_code":"PPL",
    "gn:name":"Weibang",
    "gn:population":0,
    "gn:timezone":"Asia/Shanghai",
    "iso:country":"CN",
    "name:zho_x_preferred":[
        "\u5c3e\u90a6"
    ],
    "wof:name":"Weibang",
    "wof:placetype":"locality"
},
  "geometry": {"coordinates":[105.843,24.6712],"type":"Point"}
}