{
  "type": "Feature",
  "properties": {
    "gn:country":"CN",
    "gn:fcode":"ADM3",
    "gn:population":0,
    "iso:country":"CN",
    "name:und_x_variant":[
        "Chao-tung Hsien"
    ],
    "name:zho_x_preferred":[
        "\u8087\u4e1c\u5e02"
    ],
    "name:zho_x_variant":[
        "\u8087\u4e1c"
    ],
    "qs:name":"Zhaodong Shi",
    "qs:photos_9r":0,
    "qs:photos_sr":0,
    "qs:pop_sr":"0",
    "wof:name":"Zhaodong Shi",
    "wof:placetype":"localadmin",
    "wof:population":0
},
  "geometry": {"coordinates":[125.96398000000001,46.06928],"type":"Point"}
}