{
  "type": "Feature",
  "properties": {
    "gn:admin1_code":"29.0",
    "gn:asciiname":"Caohaizi",
    "gn:country_code":"CN",
    "gn:dem":2120,
    "gn:feature_class":"P",
    "gn:feature_code":"PPL",
    "gn:name":"Caohaizi",
    "gn:population":0,
    "gn:timezone":"Asia/Shanghai",
    "iso:country":"CN",
    "name:und_x_variant":[
        "\u8349\u6d77\u5b50"
    ],
    "wof:name":"Caohaizi",
    "wof:placetype":"locality"
},
  "geometry": {"coordinates":[102.61911000000001,25.91525],"type":"Point"}
}