{
  "type": "Feature",
  "properties": {
    "gn:admin1_code":"19.0",
    "gn:asciiname":"Jiangzhangzicun",
    "gn:country_code":"CN",
    "gn:dem":239,
    "gn:feature_class":"P",
    "gn:feature_code":"PPL",
    "gn:name":"Jiangzhangzicun",
    "gn:population":0,
    "gn:timezone":"Asia/Shanghai",
    "iso:country":"CN",
    "name:zho_x_preferred":[
        "\u59dc\u6756\u5b50\u6751"
    ],
    "wof:name":"Jiangzhangzicun",
    "wof:placetype":"locality"
},
  "geometry": {"coordinates":[120.29962,41.12898],"type":"Point"}
}