{
  "type": "Feature",
  "properties": {
    "gn:admin1_code":"26.0",
    "gn:asciiname":"Qianhuaping",
    "gn:country_code":"CN",
    "gn:dem":1377,
    "gn:feature_class":"P",
    "gn:feature_code":"PPL",
    "gn:name":"Qianhuaping",
    "gn:population":0,
    "gn:timezone":"Asia/Shanghai",
    "iso:country":"CN",
    "name:zho_x_preferred":[
        "\u524d\u534e\u576a"
    ],
    "wof:name":"Qianhuaping",
    "wof:placetype":"locality"
},
  "geometry": {"coordinates":[110.08132999999999,35.47025],"type":"Point"}
}