{
  "type": "Feature",
  "properties": {
    "gn:admin1_code":"32.0",
    "gn:asciiname":"Xianhuan",
    "gn:country_code":"CN",
    "gn:dem":3919,
    "gn:feature_class":"P",
    "gn:feature_code":"PPL",
    "gn:name":"Xianhuan",
    "gn:population":0,
    "gn:timezone":"Asia/Shanghai",
    "iso:country":"CN",
    "name:zho_x_preferred":[
        "\u5148\u6b22"
    ],
    "wof:name":"Xianhuan",
    "wof:placetype":"locality"
},
  "geometry": {"coordinates":[101.28700000000001,28.0776],"type":"Point"}
}