{
  "type": "Feature",
  "properties": {
    "gn:admin1_code":"11",
    "gn:asciiname":"Huaqiaoshi",
    "gn:cc2":"CN",
    "gn:country_code":"CN",
    "gn:dem":383,
    "gn:feature_class":"P",
    "gn:feature_code":"PPL",
    "gn:name":"Huaqiaoshi",
    "gn:population":0,
    "gn:timezone":"Asia/Shanghai",
    "iso:country":"CN",
    "name:und_x_variant":[
        "Hua-ch\u2019iao-shih",
        "Huaqiaoshi"
    ],
    "wof:name":"Huaqiaoshi",
    "wof:placetype":"locality"
},
  "geometry": {"coordinates":[112.01667,25.78333],"type":"Point"}
}