{
  "type": "Feature",
  "properties": {
    "gn:admin1_code":"2.0",
    "gn:asciiname":"Qiulan",
    "gn:country_code":"CN",
    "gn:dem":227,
    "gn:feature_class":"P",
    "gn:feature_code":"PPL",
    "gn:name":"Qiulan",
    "gn:population":0,
    "gn:timezone":"Asia/Shanghai",
    "iso:country":"CN",
    "name:und_x_variant":[
        "\u4e18\u5170",
        "Qiulan"
    ],
    "wof:name":"Qiulan",
    "wof:placetype":"locality"
},
  "geometry": {"coordinates":[119.50221999999999,27.86838],"type":"Point"}
}