{
  "type": "Feature",
  "properties": {
    "gn:admin1_code":"32.0",
    "gn:asciiname":"Yuanshanpo",
    "gn:country_code":"CN",
    "gn:dem":468,
    "gn:feature_class":"P",
    "gn:feature_code":"PPL",
    "gn:name":"Yuanshanpo",
    "gn:population":0,
    "gn:timezone":"Asia/Shanghai",
    "iso:country":"CN",
    "name:zho_x_preferred":[
        "\u56ed\u5c71\u5761"
    ],
    "wof:name":"Yuanshanpo",
    "wof:placetype":"locality"
},
  "geometry": {"coordinates":[104.72481000000001,28.60383],"type":"Point"}
}