{
  "type": "Feature",
  "properties": {
    "gn:admin1_code":"26.0",
    "gn:asciiname":"Wangqucun",
    "gn:country_code":"CN",
    "gn:dem":1317,
    "gn:feature_class":"P",
    "gn:feature_code":"PPL",
    "gn:name":"Wangqucun",
    "gn:population":0,
    "gn:timezone":"Asia/Shanghai",
    "iso:country":"CN",
    "name:zho_x_preferred":[
        "\u738b\u6e20\u6751"
    ],
    "wof:name":"Wangqucun",
    "wof:placetype":"locality"
},
  "geometry": {"coordinates":[108.92106,37.06857],"type":"Point"}
}