{
  "type": "Feature",
  "properties": {
    "gn:admin1_code":"11.0",
    "gn:asciiname":"Sharen'ao",
    "gn:country_code":"CN",
    "gn:dem":69,
    "gn:feature_class":"P",
    "gn:feature_code":"PPL",
    "gn:name":"Sharen\u2019ao",
    "gn:population":0,
    "gn:timezone":"Asia/Shanghai",
    "iso:country":"CN",
    "name:und_x_variant":[
        "Sharen\u2019ao"
    ],
    "name:zho_x_preferred":[
        "\u6740\u4eba\u5773"
    ],
    "wof:name":"Sharen'ao",
    "wof:placetype":"locality"
},
  "geometry": {"coordinates":[112.86114999999999,27.42228],"type":"Point"}
}