{
  "type": "Feature",
  "properties": {
    "gn:admin1_code":"29.0",
    "gn:asciiname":"Huotou",
    "gn:country_code":"CN",
    "gn:dem":2162,
    "gn:feature_class":"P",
    "gn:feature_code":"PPL",
    "gn:name":"Huotou",
    "gn:population":0,
    "gn:timezone":"Asia/Shanghai",
    "iso:country":"CN",
    "name:zho_x_preferred":[
        "\u706b\u5934"
    ],
    "wof:name":"Huotou",
    "wof:placetype":"locality"
},
  "geometry": {"coordinates":[99.158,27.2939],"type":"Point"}
}