{
  "type": "Feature",
  "properties": {
    "gn:admin1_code":"2",
    "gn:asciiname":"Baisha",
    "gn:country_code":"CN",
    "gn:dem":93,
    "gn:feature_class":"P",
    "gn:feature_code":"PPLA4",
    "gn:name":"Baisha",
    "gn:population":0,
    "gn:timezone":"Asia/Shanghai",
    "iso:country":"CN",
    "name:ceb_x_preferred":[
        "Baisha"
    ],
    "name:deu_x_preferred":[
        "Baisha"
    ],
    "name:fra_x_preferred":[
        "Baisha"
    ],
    "name:nld_x_preferred":[
        "Baisha"
    ],
    "name:und_x_variant":[
        "\u767d\u6c99",
        "Baisha",
        "Baisha Xiang"
    ],
    "name:zho_x_preferred":[
        "\u767d\u6c99\u4e61"
    ],
    "wof:name":"Baisha",
    "wof:placetype":"locality"
},
  "geometry": {"coordinates":[119.72747,29.30668],"type":"Point"}
}