{
  "type": "Feature",
  "properties": {
    "gn:admin1_code":"19.0",
    "gn:asciiname":"Jiqingcun",
    "gn:country_code":"CN",
    "gn:dem":51,
    "gn:feature_class":"P",
    "gn:feature_code":"PPL",
    "gn:name":"Jiqingcun",
    "gn:population":0,
    "gn:timezone":"Asia/Shanghai",
    "iso:country":"CN",
    "name:zho_x_preferred":[
        "\u5409\u5e86\u6751"
    ],
    "wof:name":"Jiqingcun",
    "wof:placetype":"locality"
},
  "geometry": {"coordinates":[122.70504,39.69836],"type":"Point"}
}