{
  "type": "Feature",
  "properties": {
    "gn:admin1_code":"29.0",
    "gn:asciiname":"Yangchang",
    "gn:country_code":"CN",
    "gn:dem":2533,
    "gn:feature_class":"P",
    "gn:feature_code":"PPLF",
    "gn:name":"Yangchang",
    "gn:population":0,
    "gn:timezone":"Asia/Shanghai",
    "iso:country":"CN",
    "name:und_x_variant":[
        "\u7f8a\u573a"
    ],
    "wof:name":"Yangchang",
    "wof:placetype":"locality"
},
  "geometry": {"coordinates":[103.0348,27.02803],"type":"Point"}
}