{
  "type": "Feature",
  "properties": {
    "gn:admin1_code":"2.0",
    "gn:asciiname":"Caizhudai",
    "gn:country_code":"CN",
    "gn:dem":11,
    "gn:feature_class":"P",
    "gn:feature_code":"PPL",
    "gn:name":"Caizhudai",
    "gn:population":0,
    "gn:timezone":"Asia/Shanghai",
    "iso:country":"CN",
    "name:und_x_variant":[
        "\u8d22\u4e3b\u57ed"
    ],
    "wof:name":"Caizhudai",
    "wof:placetype":"locality"
},
  "geometry": {"coordinates":[120.08863999999998,30.09541],"type":"Point"}
}