{
  "type": "Feature",
  "properties": {
    "gn:admin1_code":"10",
    "gn:asciiname":"Gahaigou",
    "gn:country_code":"CN",
    "gn:dem":660,
    "gn:feature_class":"P",
    "gn:feature_code":"PPL",
    "gn:name":"Gahaigou",
    "gn:population":0,
    "gn:timezone":"Asia/Shanghai",
    "iso:country":"CN",
    "name:zho_x_preferred":[
        "\u560e\u6d77\u6c9f"
    ],
    "wof:name":"Gahaigou",
    "wof:placetype":"locality"
},
  "geometry": {"coordinates":[119.00187,41.24566],"type":"Point"}
}