{
  "type": "Feature",
  "properties": {
    "gn:admin1_code":"12.0",
    "gn:asciiname":"Shangfengjia",
    "gn:country_code":"CN",
    "gn:dem":116,
    "gn:feature_class":"P",
    "gn:feature_code":"PPL",
    "gn:name":"Shangfengjia",
    "gn:population":0,
    "gn:timezone":"Asia/Shanghai",
    "iso:country":"CN",
    "name:zho_x_preferred":[
        "\u4e0a\u51af\u5bb6"
    ],
    "wof:name":"Shangfengjia",
    "wof:placetype":"locality"
},
  "geometry": {"coordinates":[112.14349,32.2485],"type":"Point"}
}