{
  "type": "Feature",
  "properties": {
    "gn:admin1_code":"19.0",
    "gn:asciiname":"Laochang",
    "gn:country_code":"CN",
    "gn:dem":369,
    "gn:feature_class":"P",
    "gn:feature_code":"PPL",
    "gn:name":"Laochang",
    "gn:population":0,
    "gn:timezone":"Asia/Shanghai",
    "iso:country":"CN",
    "name:und_x_variant":[
        "\u8001\u573a"
    ],
    "name:zho_x_preferred":[
        "\u8001\u573a"
    ],
    "wof:name":"Laochang",
    "wof:placetype":"locality"
},
  "geometry": {"coordinates":[124.732,42.9918],"type":"Point"}
}