{
  "type": "Feature",
  "properties": {
    "gn:admin1_code":"12.0",
    "gn:asciiname":"Qiaomaitang",
    "gn:country_code":"CN",
    "gn:dem":230,
    "gn:feature_class":"P",
    "gn:feature_code":"PPL",
    "gn:name":"Qiaomaitang",
    "gn:population":0,
    "gn:timezone":"Asia/Shanghai",
    "iso:country":"CN",
    "name:zho_x_preferred":[
        "Qiaomaitang"
    ],
    "name:zho_x_variant":[
        "\u835e\u9ea6\u5858"
    ],
    "wof:name":"Qiaomaitang",
    "wof:placetype":"locality"
},
  "geometry": {"coordinates":[115.49216,29.89245],"type":"Point"}
}