{
  "type": "Feature",
  "properties": {
    "gn:admin1_code":"26",
    "gn:asciiname":"Jinshuigou",
    "gn:cc2":"CN",
    "gn:country_code":"CN",
    "gn:dem":343,
    "gn:feature_class":"P",
    "gn:feature_code":"PPL",
    "gn:name":"Jinshuigou",
    "gn:population":0,
    "gn:timezone":"Asia/Shanghai",
    "iso:country":"CN",
    "name:und_x_variant":[
        "Chin-shui-kou",
        "Jinshuigou"
    ],
    "wof:name":"Jinshuigou",
    "wof:placetype":"locality"
},
  "geometry": {"coordinates":[110.21666999999999,34.98333],"type":"Point"}
}