{
  "type": "Feature",
  "properties": {
    "gn:admin1_code":"29.0",
    "gn:asciiname":"Jujiaping",
    "gn:country_code":"CN",
    "gn:dem":965,
    "gn:feature_class":"P",
    "gn:feature_code":"PPL",
    "gn:name":"Jujiaping",
    "gn:population":0,
    "gn:timezone":"Asia/Shanghai",
    "iso:country":"CN",
    "name:zho_x_preferred":[
        "\u805a\u5bb6\u576a"
    ],
    "wof:name":"Jujiaping",
    "wof:placetype":"locality"
},
  "geometry": {"coordinates":[104.587,27.7819],"type":"Point"}
}