{
  "type": "Feature",
  "properties": {
    "gn:admin1_code":"11.0",
    "gn:asciiname":"Sanzichang",
    "gn:country_code":"CN",
    "gn:dem":74,
    "gn:feature_class":"P",
    "gn:feature_code":"PPL",
    "gn:name":"Sanzichang",
    "gn:population":0,
    "gn:timezone":"Asia/Shanghai",
    "iso:country":"CN",
    "name:zho_x_preferred":[
        "\u4e09\u5b57\u573a"
    ],
    "wof:name":"Sanzichang",
    "wof:placetype":"locality"
},
  "geometry": {"coordinates":[112.32980999999999,26.97251],"type":"Point"}
}