{
  "type": "Feature",
  "properties": {
    "gn:admin1_code":"1.0",
    "gn:asciiname":"Hefancun",
    "gn:country_code":"CN",
    "gn:dem":428,
    "gn:feature_class":"P",
    "gn:feature_code":"PPL",
    "gn:name":"Hefancun",
    "gn:population":0,
    "gn:timezone":"Asia/Shanghai",
    "iso:country":"CN",
    "name:zho_x_preferred":[
        "\u4f55\u7548\u6751"
    ],
    "wof:name":"Hefancun",
    "wof:placetype":"locality"
},
  "geometry": {"coordinates":[115.53506000000002,31.38366],"type":"Point"}
}