{
  "type": "Feature",
  "properties": {
    "gn:admin1_code":"9.0",
    "gn:asciiname":"Hongchunsi",
    "gn:country_code":"CN",
    "gn:dem":925,
    "gn:feature_class":"P",
    "gn:feature_code":"PPL",
    "gn:name":"Hongchunsi",
    "gn:population":0,
    "gn:timezone":"Asia/Shanghai",
    "iso:country":"CN",
    "name:zho_x_preferred":[
        "\u7ea2\u6625\u5bfa"
    ],
    "wof:name":"Hongchunsi",
    "wof:placetype":"locality"
},
  "geometry": {"coordinates":[112.32523,33.87969],"type":"Point"}
}