{
  "type": "Feature",
  "properties": {
    "gn:admin1_code":"8.0",
    "gn:asciiname":"Liniutun",
    "gn:country_code":"CN",
    "gn:dem":138,
    "gn:feature_class":"P",
    "gn:feature_code":"PPL",
    "gn:name":"Liniutun",
    "gn:population":0,
    "gn:timezone":"Asia/Shanghai",
    "iso:country":"CN",
    "name:zho_x_preferred":[
        "\u674e\u725b\u5c6f"
    ],
    "wof:name":"Liniutun",
    "wof:placetype":"locality"
},
  "geometry": {"coordinates":[127.01369,45.88773],"type":"Point"}
}