{
  "type": "Feature",
  "properties": {
    "gn:admin1_code":"4.0",
    "gn:asciiname":"Jinlizhuang",
    "gn:country_code":"CN",
    "gn:dem":7,
    "gn:feature_class":"P",
    "gn:feature_code":"PPL",
    "gn:name":"Jinlizhuang",
    "gn:population":0,
    "gn:timezone":"Asia/Shanghai",
    "iso:country":"CN",
    "name:zho_x_preferred":[
        "Jinlizhuang"
    ],
    "name:zho_x_variant":[
        "\u91d1\u674e\u5e84"
    ],
    "wof:name":"Jinlizhuang",
    "wof:placetype":"locality"
},
  "geometry": {"coordinates":[119.01211000000001,33.21388],"type":"Point"}
}