{
  "type": "Feature",
  "properties": {
    "gn:admin1_code":"24.0",
    "gn:asciiname":"Qianhuangqian",
    "gn:country_code":"CN",
    "gn:dem":1306,
    "gn:feature_class":"P",
    "gn:feature_code":"PPL",
    "gn:name":"Qianhuangqian",
    "gn:population":0,
    "gn:timezone":"Asia/Shanghai",
    "iso:country":"CN",
    "name:zho_x_preferred":[
        "\u524d\u9ec4\u7b7e"
    ],
    "wof:name":"Qianhuangqian",
    "wof:placetype":"locality"
},
  "geometry": {"coordinates":[111.6144,38.38732],"type":"Point"}
}