{
  "type": "Feature",
  "properties": {
    "gn:admin1_code":"4.0",
    "gn:asciiname":"Jizhuangcun",
    "gn:country_code":"CN",
    "gn:dem":2,
    "gn:feature_class":"P",
    "gn:feature_code":"PPL",
    "gn:name":"Jizhuangcun",
    "gn:population":0,
    "gn:timezone":"Asia/Shanghai",
    "iso:country":"CN",
    "name:und_x_variant":[
        "Jizhuang",
        "\u5409\u5e84",
        "Jizhuangcun"
    ],
    "name:zho_x_preferred":[
        "\u5409\u5e84\u6751"
    ],
    "wof:name":"Jizhuangcun",
    "wof:placetype":"locality"
},
  "geometry": {"coordinates":[119.88129000000001,33.4751],"type":"Point"}
}