{
  "type": "Feature",
  "properties": {
    "gn:admin1_code":"25.0",
    "gn:asciiname":"Xiaotunquan",
    "gn:country_code":"CN",
    "gn:dem":37,
    "gn:feature_class":"P",
    "gn:feature_code":"PPL",
    "gn:name":"Xiaotunquan",
    "gn:population":0,
    "gn:timezone":"Asia/Shanghai",
    "iso:country":"CN",
    "name:zho_x_preferred":[
        "\u5c0f\u5c6f\u5708"
    ],
    "wof:name":"Xiaotunquan",
    "wof:placetype":"locality"
},
  "geometry": {"coordinates":[121.66123,37.32854],"type":"Point"}
}