{
  "type": "Feature",
  "properties": {
    "gn:admin1_code":"14.0",
    "gn:asciiname":"Xuemangba",
    "gn:country_code":"CN",
    "gn:dem":4420,
    "gn:feature_class":"P",
    "gn:feature_code":"PPL",
    "gn:name":"Xuemangba",
    "gn:population":0,
    "gn:timezone":"Asia/Urumqi",
    "iso:country":"CN",
    "name:zho_x_preferred":[
        "\u5b66\u832b\u5df4"
    ],
    "wof:name":"Xuemangba",
    "wof:placetype":"locality"
},
  "geometry": {"coordinates":[85.2302,28.902],"type":"Point"}
}