{
  "type": "Feature",
  "properties": {
    "gn:admin1_code":"8.0",
    "gn:asciiname":"Qiujiayoufang",
    "gn:country_code":"CN",
    "gn:dem":301,
    "gn:feature_class":"P",
    "gn:feature_code":"PPL",
    "gn:name":"Qiujiayoufang",
    "gn:population":0,
    "gn:timezone":"Asia/Shanghai",
    "iso:country":"CN",
    "name:zho_x_preferred":[
        "\u90b1\u5bb6\u6cb9\u623f"
    ],
    "wof:name":"Qiujiayoufang",
    "wof:placetype":"locality"
},
  "geometry": {"coordinates":[125.82581,48.22344],"type":"Point"}
}