{
  "type": "Feature",
  "properties": {
    "gn:admin1_code":"9",
    "gn:asciiname":"Qianzhangzhao",
    "gn:country_code":"CN",
    "gn:dem":56,
    "gn:feature_class":"P",
    "gn:feature_code":"PPL",
    "gn:name":"Qianzhangzhao",
    "gn:population":0,
    "gn:timezone":"Asia/Shanghai",
    "iso:country":"CN",
    "name:zho_x_preferred":[
        "\u524d\u5f20\u8d75"
    ],
    "wof:name":"Qianzhangzhao",
    "wof:placetype":"locality"
},
  "geometry": {"coordinates":[115.58235000000001,35.7622],"type":"Point"}
}