{
  "type": "Feature",
  "properties": {
    "gn:admin1_code":"32.0",
    "gn:asciiname":"Qiaodipo",
    "gn:country_code":"CN",
    "gn:dem":1825,
    "gn:feature_class":"P",
    "gn:feature_code":"PPL",
    "gn:name":"Qiaodipo",
    "gn:population":0,
    "gn:timezone":"Asia/Shanghai",
    "iso:country":"CN",
    "name:zho_x_preferred":[
        "\u4e54\u5730\u5761"
    ],
    "wof:name":"Qiaodipo",
    "wof:placetype":"locality"
},
  "geometry": {"coordinates":[102.054,27.6314],"type":"Point"}
}