{
  "type": "Feature",
  "properties": {
    "gn:admin1_code":"30",
    "gn:asciiname":"Fuchucun",
    "gn:country_code":"CN",
    "gn:dem":8,
    "gn:feature_class":"P",
    "gn:feature_code":"PPL",
    "gn:name":"Fuchucun",
    "gn:population":0,
    "gn:timezone":"Asia/Urumqi",
    "iso:country":"CN",
    "name:zho_x_preferred":[
        "\u7b26\u5904\u6751"
    ],
    "wof:name":"Fuchucun",
    "wof:placetype":"locality"
},
  "geometry": {"coordinates":[109.95243000000001,20.98652],"type":"Point"}
}