{
  "type": "Feature",
  "properties": {
    "gn:admin1_code":"29.0",
    "gn:asciiname":"Bendizhai",
    "gn:country_code":"CN",
    "gn:dem":1871,
    "gn:feature_class":"P",
    "gn:feature_code":"PPL",
    "gn:name":"Bendizhai",
    "gn:population":0,
    "gn:timezone":"Asia/Shanghai",
    "iso:country":"CN",
    "name:zho_x_preferred":[
        "\u672c\u5730\u5be8"
    ],
    "wof:name":"Bendizhai",
    "wof:placetype":"locality"
},
  "geometry": {"coordinates":[104.145,27.4642],"type":"Point"}
}