{
  "type": "Feature",
  "properties": {
    "gn:admin1_code":"5.0",
    "gn:asciiname":"Dongshuangshanzi",
    "gn:country_code":"CN",
    "gn:dem":167,
    "gn:feature_class":"P",
    "gn:feature_code":"PPL",
    "gn:name":"Dongshuangshanzi",
    "gn:population":0,
    "gn:timezone":"Asia/Shanghai",
    "iso:country":"CN",
    "name:zho_x_preferred":[
        "\u4e1c\u53cc\u5c71\u5b50"
    ],
    "wof:name":"Dongshuangshanzi",
    "wof:placetype":"locality"
},
  "geometry": {"coordinates":[124.0102,43.42622],"type":"Point"}
}