{
  "type": "Feature",
  "properties": {
    "gn:admin1_code":"24",
    "gn:asciiname":"Zhangguantun",
    "gn:country_code":"CN",
    "gn:dem":1057,
    "gn:feature_class":"P",
    "gn:feature_code":"PPL",
    "gn:name":"Zhangguantun",
    "gn:population":0,
    "gn:timezone":"Asia/Shanghai",
    "iso:country":"CN",
    "name:und_x_variant":[
        "Chang-kuan-t\u2019un",
        "Zhangguantun"
    ],
    "name:zho_x_preferred":[
        "\u5f20\u5b98\u5c6f"
    ],
    "wof:name":"Zhangguantun",
    "wof:placetype":"locality"
},
  "geometry": {"coordinates":[113.7223,40.2331],"type":"Point"}
}