{
  "type": "Feature",
  "properties": {
    "gn:admin1_code":"11.0",
    "gn:asciiname":"Yangjiawan",
    "gn:country_code":"CN",
    "gn:dem":51,
    "gn:feature_class":"P",
    "gn:feature_code":"PPL",
    "gn:name":"Yangjiawan",
    "gn:population":0,
    "gn:timezone":"Asia/Shanghai",
    "iso:country":"CN",
    "name:zho_x_preferred":[
        "\u9633\u5bb6\u6e7e"
    ],
    "wof:name":"Yangjiawan",
    "wof:placetype":"locality"
},
  "geometry": {"coordinates":[112.84829999999999,27.20017],"type":"Point"}
}