{
  "type": "Feature",
  "properties": {
    "gn:admin1_code":"18",
    "gn:asciiname":"Baiguo",
    "gn:country_code":"CN",
    "gn:dem":347,
    "gn:feature_class":"P",
    "gn:feature_code":"PPL",
    "gn:name":"Baiguo",
    "gn:population":0,
    "gn:timezone":"Asia/Shanghai",
    "iso:country":"CN",
    "name:zho_x_preferred":[
        "\u767d\u679c"
    ],
    "wof:name":"Baiguo",
    "wof:placetype":"locality"
},
  "geometry": {"coordinates":[106.699,25.2249],"type":"Point"}
}