{
  "type": "Feature",
  "properties": {
    "gn:admin1_code":"8.0",
    "gn:asciiname":"Xiweizi",
    "gn:country_code":"CN",
    "gn:dem":396,
    "gn:feature_class":"P",
    "gn:feature_code":"PPL",
    "gn:name":"Xiweizi",
    "gn:population":0,
    "gn:timezone":"Asia/Shanghai",
    "iso:country":"CN",
    "name:und_x_variant":[
        "\u897f\u5d34\u5b50"
    ],
    "wof:name":"Xiweizi",
    "wof:placetype":"locality"
},
  "geometry": {"coordinates":[130.79191,43.63913],"type":"Point"}
}