{
  "type": "Feature",
  "properties": {
    "gn:admin1_code":"9.0",
    "gn:asciiname":"Yanlingguan",
    "gn:country_code":"CN",
    "gn:dem":785,
    "gn:feature_class":"P",
    "gn:feature_code":"PPL",
    "gn:name":"Yanlingguan",
    "gn:population":0,
    "gn:timezone":"Asia/Shanghai",
    "iso:country":"CN",
    "name:zho_x_preferred":[
        "\u96c1\u7fce\u5173"
    ],
    "wof:name":"Yanlingguan",
    "wof:placetype":"locality"
},
  "geometry": {"coordinates":[111.38311000000002,34.6263],"type":"Point"}
}