{
  "type": "Feature",
  "properties": {
    "gn:admin1_code":"11.0",
    "gn:asciiname":"Fangdoudi",
    "gn:country_code":"CN",
    "gn:dem":31,
    "gn:feature_class":"P",
    "gn:feature_code":"PPL",
    "gn:name":"Fangdoudi",
    "gn:population":0,
    "gn:timezone":"Asia/Shanghai",
    "iso:country":"CN",
    "name:zho_x_preferred":[
        "Fangdoudi"
    ],
    "name:zho_x_variant":[
        "\u65b9\u6597\u5824"
    ],
    "wof:name":"Fangdoudi",
    "wof:placetype":"locality"
},
  "geometry": {"coordinates":[112.05477,28.90657],"type":"Point"}
}