{
  "type": "Feature",
  "properties": {
    "gn:admin1_code":"30.0",
    "gn:asciiname":"Shasongcun",
    "gn:country_code":"CN",
    "gn:dem":17,
    "gn:feature_class":"P",
    "gn:feature_code":"PPL",
    "gn:name":"Shasongcun",
    "gn:population":0,
    "gn:timezone":"Asia/Shanghai",
    "iso:country":"CN",
    "name:zho_x_preferred":[
        "\u7802\u677e\u6751"
    ],
    "wof:name":"Shasongcun",
    "wof:placetype":"locality"
},
  "geometry": {"coordinates":[116.35093999999999,23.57361],"type":"Point"}
}