{
  "type": "Feature",
  "properties": {
    "gn:admin1_code":"1.0",
    "gn:asciiname":"Heshanggang",
    "gn:country_code":"CN",
    "gn:dem":10,
    "gn:feature_class":"P",
    "gn:feature_code":"PPL",
    "gn:name":"Heshanggang",
    "gn:population":0,
    "gn:timezone":"Asia/Shanghai",
    "iso:country":"CN",
    "name:zho_x_preferred":[
        "\u6cb3\u4e0a\u6e2f"
    ],
    "wof:name":"Heshanggang",
    "wof:placetype":"locality"
},
  "geometry": {"coordinates":[118.52278,31.41252],"type":"Point"}
}