{
  "type": "Feature",
  "properties": {
    "gn:admin1_code":"11.0",
    "gn:asciiname":"Zhushanxi",
    "gn:country_code":"CN",
    "gn:dem":284,
    "gn:feature_class":"P",
    "gn:feature_code":"PPL",
    "gn:name":"Zhushanxi",
    "gn:population":0,
    "gn:timezone":"Asia/Shanghai",
    "iso:country":"CN",
    "name:zho_x_preferred":[
        "\u4e3b\u5c71\u6eaa"
    ],
    "wof:name":"Zhushanxi",
    "wof:placetype":"locality"
},
  "geometry": {"coordinates":[109.56328000000001,27.02534],"type":"Point"}
}