{
  "type": "Feature",
  "properties": {
    "gn:admin1_code":"26",
    "gn:asciiname":"Xiayueliangping",
    "gn:country_code":"CN",
    "gn:dem":1298,
    "gn:feature_class":"P",
    "gn:feature_code":"PPL",
    "gn:name":"Xiayueliangping",
    "gn:population":0,
    "gn:timezone":"Asia/Shanghai",
    "iso:country":"CN",
    "name:zho_x_preferred":[
        "\u4e0b\u6708\u4eae\u576a"
    ],
    "wof:name":"Xiayueliangping",
    "wof:placetype":"locality"
},
  "geometry": {"coordinates":[108.28649,33.61436],"type":"Point"}
}