{
  "type": "Feature",
  "properties": {
    "gn:admin1_code":"22.0",
    "gn:asciiname":"Baotaicun",
    "gn:country_code":"CN",
    "gn:dem":52,
    "gn:feature_class":"P",
    "gn:feature_code":"PPL",
    "gn:name":"Baotaicun",
    "gn:population":0,
    "gn:timezone":"Asia/Shanghai",
    "iso:country":"CN",
    "name:zho_x_preferred":[
        "\u8446\u53f0\u6751"
    ],
    "wof:name":"Baotaicun",
    "wof:placetype":"locality"
},
  "geometry": {"coordinates":[116.28440999999999,39.807],"type":"Point"}
}