{
  "type": "Feature",
  "properties": {
    "gn:admin1_code":"30.0",
    "gn:asciiname":"Shizhai",
    "gn:country_code":"CN",
    "gn:dem":573,
    "gn:feature_class":"P",
    "gn:feature_code":"PPL",
    "gn:name":"Shizhai",
    "gn:population":0,
    "gn:timezone":"Asia/Shanghai",
    "iso:country":"CN",
    "name:zho_x_preferred":[
        "Shizhai"
    ],
    "name:zho_x_variant":[
        "\u77f3\u5be8"
    ],
    "wof:name":"Shizhai",
    "wof:placetype":"locality"
},
  "geometry": {"coordinates":[112.59472,24.70972],"type":"Point"}
}