{
  "type": "Feature",
  "properties": {
    "gn:admin1_code":"7.0",
    "gn:asciiname":"Xia'an",
    "gn:country_code":"CN",
    "gn:dem":325,
    "gn:feature_class":"P",
    "gn:feature_code":"PPL",
    "gn:name":"Xia\u2019an",
    "gn:population":0,
    "gn:timezone":"Asia/Shanghai",
    "iso:country":"CN",
    "name:und_x_variant":[
        "Xia\u2019an"
    ],
    "name:zho_x_preferred":[
        "\u4e0b\u5eb5"
    ],
    "wof:name":"Xia'an",
    "wof:placetype":"locality"
},
  "geometry": {"coordinates":[117.93178,25.0917],"type":"Point"}
}