{
  "type": "Feature",
  "properties": {
    "gn:admin1_code":"9.0",
    "gn:asciiname":"Hongshiyan",
    "gn:country_code":"CN",
    "gn:dem":65,
    "gn:feature_class":"P",
    "gn:feature_code":"PPL",
    "gn:name":"Hongshiyan",
    "gn:population":0,
    "gn:timezone":"Asia/Shanghai",
    "iso:country":"CN",
    "name:zho_x_preferred":[
        "\u6d2a\u6c0f\u5830"
    ],
    "wof:name":"Hongshiyan",
    "wof:placetype":"locality"
},
  "geometry": {"coordinates":[115.03247,31.93311],"type":"Point"}
}