{
  "type": "Feature",
  "properties": {
    "gn:admin1_code":"24.0",
    "gn:asciiname":"Hongwuling",
    "gn:country_code":"CN",
    "gn:dem":989,
    "gn:feature_class":"P",
    "gn:feature_code":"PPL",
    "gn:name":"Hongwuling",
    "gn:population":0,
    "gn:timezone":"Asia/Shanghai",
    "iso:country":"CN",
    "name:zho_x_preferred":[
        "\u7ea2\u6b66\u5cad"
    ],
    "wof:name":"Hongwuling",
    "wof:placetype":"locality"
},
  "geometry": {"coordinates":[110.50763999999999,36.77332],"type":"Point"}
}