{
  "type": "Feature",
  "properties": {
    "gn:admin1_code":"30.0",
    "gn:asciiname":"Mulanshan",
    "gn:country_code":"CN",
    "gn:dem":106,
    "gn:feature_class":"P",
    "gn:feature_code":"PPL",
    "gn:name":"Mulanshan",
    "gn:population":0,
    "gn:timezone":"Asia/Shanghai",
    "iso:country":"CN",
    "name:zho_x_preferred":[
        "\u6728\u5170\u5c71"
    ],
    "wof:name":"Mulanshan",
    "wof:placetype":"locality"
},
  "geometry": {"coordinates":[111.65352,22.61666],"type":"Point"}
}