{
  "type": "Feature",
  "properties": {
    "gn:admin1_code":"5.0",
    "gn:asciiname":"Jipingcun",
    "gn:country_code":"CN",
    "gn:dem":143,
    "gn:feature_class":"P",
    "gn:feature_code":"PPL",
    "gn:name":"Jipingcun",
    "gn:population":0,
    "gn:timezone":"Asia/Shanghai",
    "iso:country":"CN",
    "name:zho_x_preferred":[
        "\u53ca\u5e73\u6751"
    ],
    "wof:name":"Jipingcun",
    "wof:placetype":"locality"
},
  "geometry": {"coordinates":[123.55386,44.93548],"type":"Point"}
}