{
  "type": "Feature",
  "properties": {
    "gn:admin1_code":"1.0",
    "gn:asciiname":"Xiangdaocun",
    "gn:country_code":"CN",
    "gn:dem":55,
    "gn:feature_class":"P",
    "gn:feature_code":"PPL",
    "gn:name":"Xiangdaocun",
    "gn:population":0,
    "gn:timezone":"Asia/Shanghai",
    "iso:country":"CN",
    "name:zho_x_preferred":[
        "\u54cd\u5bfc\u6751"
    ],
    "wof:name":"Xiangdaocun",
    "wof:placetype":"locality"
},
  "geometry": {"coordinates":[117.60541000000001,32.22039],"type":"Point"}
}