{
  "type": "Feature",
  "properties": {
    "gn:admin1_code":"16.0",
    "gn:asciiname":"Waipeng",
    "gn:country_code":"CN",
    "gn:dem":207,
    "gn:feature_class":"P",
    "gn:feature_code":"PPL",
    "gn:name":"Waipeng",
    "gn:population":0,
    "gn:timezone":"Asia/Shanghai",
    "iso:country":"CN",
    "name:zho_x_preferred":[
        "\u6b6a\u84ec"
    ],
    "wof:name":"Waipeng",
    "wof:placetype":"locality"
},
  "geometry": {"coordinates":[108.59999999999999,23.7526],"type":"Point"}
}