{
  "type": "Feature",
  "properties": {
    "gn:admin1_code":"30.0",
    "gn:asciiname":"Kewu",
    "gn:country_code":"CN",
    "gn:dem":380,
    "gn:feature_class":"P",
    "gn:feature_code":"PPL",
    "gn:name":"Kewu",
    "gn:population":0,
    "gn:timezone":"Asia/Shanghai",
    "iso:country":"CN",
    "name:zho_x_preferred":[
        "Kewu"
    ],
    "name:zho_x_variant":[
        "\u79d1\u5c4b"
    ],
    "wof:name":"Kewu",
    "wof:placetype":"locality"
},
  "geometry": {"coordinates":[114.33385,24.54068],"type":"Point"}
}