{
  "type": "Feature",
  "properties": {
    "gn:admin1_code":"11.0",
    "gn:asciiname":"Xuanchang",
    "gn:country_code":"CN",
    "gn:dem":423,
    "gn:feature_class":"P",
    "gn:feature_code":"PPL",
    "gn:name":"Xuanchang",
    "gn:population":0,
    "gn:timezone":"Asia/Shanghai",
    "iso:country":"CN",
    "name:zho_x_preferred":[
        "\u9009\u573a"
    ],
    "wof:name":"Xuanchang",
    "wof:placetype":"locality"
},
  "geometry": {"coordinates":[110.3272,28.10707],"type":"Point"}
}