{
  "type": "Feature",
  "properties": {
    "gn:admin1_code":"6.0",
    "gn:asciiname":"Yari Hatu",
    "gn:country_code":"CN",
    "gn:dem":3296,
    "gn:feature_class":"P",
    "gn:feature_code":"PPL",
    "gn:name":"Yari Hatu",
    "gn:population":0,
    "gn:timezone":"Asia/Urumqi",
    "iso:country":"CN",
    "name:zho_x_preferred":[
        "\u96c5\u65e5\u54c8\u56fe"
    ],
    "wof:name":"Yari Hatu",
    "wof:placetype":"locality"
},
  "geometry": {"coordinates":[97.41267000000001,35.91657],"type":"Point"}
}