{
  "type": "Feature",
  "properties": {
    "gn:admin1_code":"29",
    "gn:asciiname":"Agang",
    "gn:country_code":"CN",
    "gn:dem":1972,
    "gn:feature_class":"P",
    "gn:feature_code":"PPL",
    "gn:name":"Agang",
    "gn:population":0,
    "gn:timezone":"Asia/Shanghai",
    "iso:country":"CN",
    "name:zho_x_preferred":[
        "\u963f\u5c97"
    ],
    "wof:name":"Agang",
    "wof:placetype":"locality"
},
  "geometry": {"coordinates":[104.128,25.0732],"type":"Point"}
}