{
  "type": "Feature",
  "properties": {
    "gn:admin1_code":"4.0",
    "gn:asciiname":"Xianzhuang",
    "gn:country_code":"CN",
    "gn:dem":9,
    "gn:feature_class":"P",
    "gn:feature_code":"PPL",
    "gn:name":"Xianzhuang",
    "gn:population":0,
    "gn:timezone":"Asia/Shanghai",
    "iso:country":"CN",
    "name:zho_x_preferred":[
        "\u4ed9\u5e84"
    ],
    "wof:name":"Xianzhuang",
    "wof:placetype":"locality"
},
  "geometry": {"coordinates":[119.68671000000001,32.11194],"type":"Point"}
}