{
  "type": "Feature",
  "properties": {
    "gn:admin1_code":"26.0",
    "gn:asciiname":"Shahezhen",
    "gn:country_code":"CN",
    "gn:dem":538,
    "gn:feature_class":"P",
    "gn:feature_code":"PPL",
    "gn:name":"Shahezhen",
    "gn:population":0,
    "gn:timezone":"Asia/Shanghai",
    "iso:country":"CN",
    "name:und_x_variant":[
        "\u6c99\u6cb3\u9547"
    ],
    "wof:name":"Shahezhen",
    "wof:placetype":"locality"
},
  "geometry": {"coordinates":[107.51243999999998,32.96845],"type":"Point"}
}