{
  "type": "Feature",
  "properties": {
    "gn:admin1_code":"11.0",
    "gn:asciiname":"Shuajiamiao",
    "gn:country_code":"CN",
    "gn:dem":66,
    "gn:feature_class":"P",
    "gn:feature_code":"PPL",
    "gn:name":"Shuajiamiao",
    "gn:population":0,
    "gn:timezone":"Asia/Shanghai",
    "iso:country":"CN",
    "name:zho_x_preferred":[
        "Shuajiamiao"
    ],
    "name:zho_x_variant":[
        "\u800d\u5bb6\u5e99"
    ],
    "wof:name":"Shuajiamiao",
    "wof:placetype":"locality"
},
  "geometry": {"coordinates":[111.58573,29.1123],"type":"Point"}
}