{
  "type": "Feature",
  "properties": {
    "gn:admin1_code":"33.0",
    "gn:asciiname":"Tianxing",
    "gn:country_code":"CN",
    "gn:dem":301,
    "gn:feature_class":"P",
    "gn:feature_code":"PPLA4",
    "gn:name":"Tianxing",
    "gn:population":0,
    "gn:timezone":"Asia/Shanghai",
    "iso:country":"CN",
    "name:und_x_variant":[
        "Tianxing Xiang",
        "Shuangyuanxi"
    ],
    "name:zho_x_preferred":[
        "\u5929\u661f"
    ],
    "name:zho_x_variant":[
        "\u5929\u661f\u4e61",
        "\u53cc\u6e90\u6eaa"
    ],
    "wof:name":"Tianxing",
    "wof:placetype":"locality"
},
  "geometry": {"coordinates":[109.5399,31.47085],"type":"Point"}
}