{
  "type": "Feature",
  "properties": {
    "gn:admin1_code":"3.0",
    "gn:asciiname":"Wangyang",
    "gn:country_code":"CN",
    "gn:dem":827,
    "gn:feature_class":"P",
    "gn:feature_code":"PPL",
    "gn:name":"Wangyang",
    "gn:population":0,
    "gn:timezone":"Asia/Shanghai",
    "iso:country":"CN",
    "name:zho_x_preferred":[
        "\u6c6a\u6d0b"
    ],
    "wof:name":"Wangyang",
    "wof:placetype":"locality"
},
  "geometry": {"coordinates":[117.92,28.8386],"type":"Point"}
}