{
  "type": "Feature",
  "properties": {
    "gn:admin1_code":"32.0",
    "gn:asciiname":"Tadun",
    "gn:country_code":"CN",
    "gn:dem":3142,
    "gn:feature_class":"P",
    "gn:feature_code":"PPL",
    "gn:name":"Tadun",
    "gn:population":0,
    "gn:timezone":"Asia/Shanghai",
    "iso:country":"CN",
    "name:jpn_x_preferred":[
        "\u30c8\u30a6\u9813"
    ],
    "name:tha_x_preferred":[
        "\u0e40\u0e1b\u0e4a\u0e01\u0e15\u0e38\u0e49\u0e19"
    ],
    "name:vie_x_preferred":[
        "\u0110\u1ea1p \u0110\u1ed1n"
    ],
    "name:zho_x_preferred":[
        "\u5854\u6566"
    ],
    "wof:name":"Tadun",
    "wof:placetype":"locality"
},
  "geometry": {"coordinates":[100.221,30.8941],"type":"Point"}
}