{
  "type": "Feature",
  "properties": {
    "gn:admin1_code":"32.0",
    "gn:asciiname":"Tadun",
    "gn:country_code":"CN",
    "gn:dem":3142,
    "gn:feature_class":"P",
    "gn:feature_code":"PPL",
    "gn:name":"Tadun",
    "gn:population":0,
    "gn:timezone":"Asia/Shanghai",
    "iso:country":"CN",
    "name:zho_x_preferred":[
        "\u5854\u6566"
    ],
    "wof:name":"Tadun",
    "wof:placetype":"locality"
},
  "geometry": {"coordinates":[100.221,30.8941],"type":"Point"}
}