{
  "type": "Feature",
  "properties": {
    "gn:admin1_code":"20.0",
    "gn:asciiname":"Yaobeigou",
    "gn:country_code":"CN",
    "gn:dem":746,
    "gn:feature_class":"P",
    "gn:feature_code":"PPL",
    "gn:name":"Yaobeigou",
    "gn:population":0,
    "gn:timezone":"Asia/Shanghai",
    "iso:country":"CN",
    "name:zho_x_preferred":[
        "\u7a91\u5317\u6c9f"
    ],
    "wof:name":"Yaobeigou",
    "wof:placetype":"locality"
},
  "geometry": {"coordinates":[121.8359,48.77302],"type":"Point"}
}