{
  "type": "Feature",
  "properties": {
    "gn:admin1_code":"0.0",
    "gn:asciiname":"Hsu-ch'ip",
    "gn:country_code":"CN",
    "gn:dem":371,
    "gn:feature_class":"P",
    "gn:feature_code":"PPL",
    "gn:name":"Hs\u00fc-ch\u2019ip",
    "gn:population":0,
    "gn:timezone":"Asia/Shanghai",
    "iso:country":"CN",
    "wof:name":"Hsu-ch'ip",
    "wof:placetype":"locality"
},
  "geometry": {"coordinates":[107.36613,21.78569],"type":"Point"}
}