{
  "type": "Feature",
  "properties": {
    "gn:admin1_code":"9.0",
    "gn:asciiname":"Liumashenzhuang",
    "gn:country_code":"CN",
    "gn:dem":102,
    "gn:feature_class":"P",
    "gn:feature_code":"PPL",
    "gn:name":"Liumashenzhuang",
    "gn:population":0,
    "gn:timezone":"Asia/Shanghai",
    "iso:country":"CN",
    "name:zho_x_preferred":[
        "\u5218\u9ebb\u7533\u5e84"
    ],
    "wof:name":"Liumashenzhuang",
    "wof:placetype":"locality"
},
  "geometry": {"coordinates":[113.74218999999999,34.22093],"type":"Point"}
}