{
  "type": "Feature",
  "properties": {
    "gn:admin1_code":"29.0",
    "gn:asciiname":"Longshu",
    "gn:country_code":"CN",
    "gn:dem":1870,
    "gn:feature_class":"P",
    "gn:feature_code":"PPL",
    "gn:name":"Longshu",
    "gn:population":0,
    "gn:timezone":"Asia/Shanghai",
    "iso:country":"CN",
    "name:zho_x_preferred":[
        "\u9f99\u6811"
    ],
    "wof:name":"Longshu",
    "wof:placetype":"locality"
},
  "geometry": {"coordinates":[100.89400000000001,24.9401],"type":"Point"}
}