{
  "type": "Feature",
  "properties": {
    "gn:admin1_code":"3.0",
    "gn:asciiname":"Xiaxiwu",
    "gn:country_code":"CN",
    "gn:dem":96,
    "gn:feature_class":"P",
    "gn:feature_code":"PPL",
    "gn:name":"Xiaxiwu",
    "gn:population":0,
    "gn:timezone":"Asia/Shanghai",
    "iso:country":"CN",
    "name:zho_x_preferred":[
        "\u4e0b\u897f\u5434"
    ],
    "wof:name":"Xiaxiwu",
    "wof:placetype":"locality"
},
  "geometry": {"coordinates":[117.30500000000001,28.6978],"type":"Point"}
}