{
  "type": "Feature",
  "properties": {
    "gn:admin1_code":"29.0",
    "gn:asciiname":"Nanjingli",
    "gn:country_code":"CN",
    "gn:dem":1413,
    "gn:feature_class":"P",
    "gn:feature_code":"PPL",
    "gn:name":"Nanjingli",
    "gn:population":0,
    "gn:timezone":"Asia/Shanghai",
    "iso:country":"CN",
    "name:zho_x_preferred":[
        "\u5357\u4eac\u91cc"
    ],
    "wof:name":"Nanjingli",
    "wof:placetype":"locality"
},
  "geometry": {"coordinates":[97.8344,24.0926],"type":"Point"}
}