{
  "type": "Feature",
  "properties": {
    "gn:admin1_code":"30",
    "gn:asciiname":"Tangjia Linchang",
    "gn:country_code":"CN",
    "gn:dem":29,
    "gn:feature_class":"P",
    "gn:feature_code":"PPLF",
    "gn:name":"Tangjia Linchang",
    "gn:population":0,
    "gn:timezone":"Asia/Urumqi",
    "iso:country":"CN",
    "wof:name":"Tangjia Linchang",
    "wof:placetype":"locality"
},
  "geometry": {"coordinates":[109.84528,20.81167],"type":"Point"}
}