{
  "type": "Feature",
  "properties": {
    "gn:admin1_code":"16.0",
    "gn:asciiname":"Dongneicun",
    "gn:country_code":"CN",
    "gn:dem":452,
    "gn:feature_class":"P",
    "gn:feature_code":"PPL",
    "gn:name":"Dongneicun",
    "gn:population":0,
    "gn:timezone":"Asia/Shanghai",
    "iso:country":"CN",
    "name:zho_x_preferred":[
        "\u6d1e\u5185\u6751"
    ],
    "wof:name":"Dongneicun",
    "wof:placetype":"locality"
},
  "geometry": {"coordinates":[106.80200000000001,23.2532],"type":"Point"}
}