{
  "type": "Feature",
  "properties": {
    "gn:admin1_code":"1.0",
    "gn:asciiname":"Renmiaocun",
    "gn:country_code":"CN",
    "gn:dem":28,
    "gn:feature_class":"P",
    "gn:feature_code":"PPL",
    "gn:name":"Renmiaocun",
    "gn:population":0,
    "gn:timezone":"Asia/Shanghai",
    "iso:country":"CN",
    "name:zho_x_preferred":[
        "\u4efb\u5e99\u6751"
    ],
    "wof:name":"Renmiaocun",
    "wof:placetype":"locality"
},
  "geometry": {"coordinates":[117.74733000000001,33.87685],"type":"Point"}
}