{
  "type": "Feature",
  "properties": {
    "gn:admin1_code":"24.0",
    "gn:asciiname":"Chishuicun",
    "gn:country_code":"CN",
    "gn:dem":1063,
    "gn:feature_class":"P",
    "gn:feature_code":"PPL",
    "gn:name":"Chishuicun",
    "gn:population":0,
    "gn:timezone":"Asia/Shanghai",
    "iso:country":"CN",
    "name:zho_x_preferred":[
        "\u8d64\u6c34\u6751"
    ],
    "wof:name":"Chishuicun",
    "wof:placetype":"locality"
},
  "geometry": {"coordinates":[112.48766000000001,38.4963],"type":"Point"}
}