{
  "type": "Feature",
  "properties": {
    "gn:admin1_code":"5.0",
    "gn:asciiname":"Qianwunugechi",
    "gn:country_code":"CN",
    "gn:dem":146,
    "gn:feature_class":"P",
    "gn:feature_code":"PPL",
    "gn:name":"Qianwunugechi",
    "gn:population":0,
    "gn:timezone":"Asia/Shanghai",
    "iso:country":"CN",
    "name:zho_x_preferred":[
        "\u524d\u4e4c\u52aa\u683c\u5c3a"
    ],
    "wof:name":"Qianwunugechi",
    "wof:placetype":"locality"
},
  "geometry": {"coordinates":[123.15876000000002,44.99121],"type":"Point"}
}