{
  "type": "Feature",
  "properties": {
    "gn:admin1_code":"1.0",
    "gn:asciiname":"Zhangdiancun",
    "gn:country_code":"CN",
    "gn:dem":39,
    "gn:feature_class":"P",
    "gn:feature_code":"PPL",
    "gn:name":"Zhangdiancun",
    "gn:population":0,
    "gn:timezone":"Asia/Shanghai",
    "iso:country":"CN",
    "name:zho_x_preferred":[
        "\u5f20\u5e97\u6751"
    ],
    "wof:name":"Zhangdiancun",
    "wof:placetype":"locality"
},
  "geometry": {"coordinates":[117.00660000000001,31.6267],"type":"Point"}
}