{
  "type": "Feature",
  "properties": {
    "gn:admin1_code":"03",
    "gn:asciiname":"Daxi",
    "gn:country_code":"CN",
    "gn:dem":21,
    "gn:feature_class":"P",
    "gn:feature_code":"PPLA4",
    "gn:name":"Daxi",
    "gn:population":0,
    "gn:timezone":"Asia/Shanghai",
    "iso:country":"CN",
    "name:und_x_variant":[
        "Ta-hsi-tu",
        "Daxi",
        "\u5927\u6eaa",
        "Daxidu",
        "Daxi Xiang",
        "\u5927\u6eaa\u4e61"
    ],
    "wof:name":"Daxi",
    "wof:placetype":"locality"
},
  "geometry": {"coordinates":[116.69826999999999,28.58819],"type":"Point"}
}