{
  "type": "Feature",
  "properties": {
    "gn:admin1_code":"1.0",
    "gn:asciiname":"Xuelincun",
    "gn:country_code":"CN",
    "gn:dem":17,
    "gn:feature_class":"P",
    "gn:feature_code":"PPL",
    "gn:name":"Xuelincun",
    "gn:population":0,
    "gn:timezone":"Asia/Shanghai",
    "iso:country":"CN",
    "name:zho_x_preferred":[
        "\u859b\u6797\u6751"
    ],
    "wof:name":"Xuelincun",
    "wof:placetype":"locality"
},
  "geometry": {"coordinates":[117.79170999999999,33.117],"type":"Point"}
}