{
  "type": "Feature",
  "properties": {
    "gn:admin1_code":"32.0",
    "gn:asciiname":"Niulushang",
    "gn:country_code":"CN",
    "gn:dem":1418,
    "gn:feature_class":"P",
    "gn:feature_code":"PPL",
    "gn:name":"Niulushang",
    "gn:population":0,
    "gn:timezone":"Asia/Shanghai",
    "iso:country":"CN",
    "name:zho_x_preferred":[
        "\u725b\u8def\u4e0a"
    ],
    "wof:name":"Niulushang",
    "wof:placetype":"locality"
},
  "geometry": {"coordinates":[102.592,29.2652],"type":"Point"}
}