{
  "type": "Feature",
  "properties": {
    "gn:admin1_code":"11.0",
    "gn:asciiname":"Ziqiang",
    "gn:country_code":"CN",
    "gn:dem":373,
    "gn:feature_class":"P",
    "gn:feature_code":"PPL",
    "gn:name":"Ziqiang",
    "gn:population":0,
    "gn:timezone":"Asia/Shanghai",
    "iso:country":"CN",
    "name:zho_x_preferred":[
        "\u81ea\u5f3a"
    ],
    "wof:name":"Ziqiang",
    "wof:placetype":"locality"
},
  "geometry": {"coordinates":[109.66356,28.39379000000001],"type":"Point"}
}