{
  "type": "Feature",
  "properties": {
    "gn:admin1_code":"12.0",
    "gn:asciiname":"Xuzong",
    "gn:country_code":"CN",
    "gn:dem":38,
    "gn:feature_class":"P",
    "gn:feature_code":"PPL",
    "gn:name":"Xuzong",
    "gn:population":0,
    "gn:timezone":"Asia/Shanghai",
    "iso:country":"CN",
    "name:und_x_variant":[
        "\u8bb8\u5b97"
    ],
    "wof:name":"Xuzong",
    "wof:placetype":"locality"
},
  "geometry": {"coordinates":[114.29404,30.22789],"type":"Point"}
}