{
  "type": "Feature",
  "properties": {
    "gn:admin1_code":"19.0",
    "gn:asciiname":"Gaolicheng",
    "gn:country_code":"CN",
    "gn:dem":79,
    "gn:feature_class":"P",
    "gn:feature_code":"PPL",
    "gn:name":"Gaolicheng",
    "gn:population":0,
    "gn:timezone":"Asia/Shanghai",
    "iso:country":"CN",
    "name:zho_x_preferred":[
        "\u9ad8\u4e3d\u57ce"
    ],
    "wof:name":"Gaolicheng",
    "wof:placetype":"locality"
},
  "geometry": {"coordinates":[121.898,39.7395],"type":"Point"}
}