{
  "type": "Feature",
  "properties": {
    "gn:admin1_code":"12.0",
    "gn:asciiname":"Guanjia Xinwan",
    "gn:country_code":"CN",
    "gn:dem":159,
    "gn:feature_class":"P",
    "gn:feature_code":"PPL",
    "gn:name":"Guanjia Xinwan",
    "gn:population":0,
    "gn:timezone":"Asia/Shanghai",
    "iso:country":"CN",
    "name:zho_x_preferred":[
        "\u7ba1\u5bb6\u65b0\u5846"
    ],
    "wof:name":"Guanjia Xinwan",
    "wof:placetype":"locality"
},
  "geometry": {"coordinates":[113.63608000000001,32.22946],"type":"Point"}
}