{
  "type": "Feature",
  "properties": {
    "gn:admin1_code":"11.0",
    "gn:asciiname":"Yunleishan",
    "gn:country_code":"CN",
    "gn:dem":29,
    "gn:feature_class":"P",
    "gn:feature_code":"PPL",
    "gn:name":"Yunleishan",
    "gn:population":0,
    "gn:timezone":"Asia/Shanghai",
    "iso:country":"CN",
    "name:zho_x_preferred":[
        "\u4e91\u96f7\u5c71"
    ],
    "wof:name":"Yunleishan",
    "wof:placetype":"locality"
},
  "geometry": {"coordinates":[112.66531999999999,28.55709],"type":"Point"}
}