{
  "type": "Feature",
  "properties": {
    "gn:admin1_code":"7.0",
    "gn:asciiname":"Hamashi",
    "gn:country_code":"CN",
    "gn:dem":435,
    "gn:feature_class":"P",
    "gn:feature_code":"PPL",
    "gn:name":"Hamashi",
    "gn:population":0,
    "gn:timezone":"Asia/Shanghai",
    "iso:country":"CN",
    "name:zho_x_preferred":[
        "\u86e4\u87c6\u77f3"
    ],
    "wof:name":"Hamashi",
    "wof:placetype":"locality"
},
  "geometry": {"coordinates":[119.38403999999998,26.4381],"type":"Point"}
}