{
  "type": "Feature",
  "properties": {
    "gn:admin1_code":"18.0",
    "gn:asciiname":"Guanjiang",
    "gn:country_code":"CN",
    "gn:dem":627,
    "gn:feature_class":"P",
    "gn:feature_code":"PPL",
    "gn:name":"Guanjiang",
    "gn:population":0,
    "gn:timezone":"Asia/Shanghai",
    "iso:country":"CN",
    "name:zho_x_preferred":[
        "\u5173\u6c5f"
    ],
    "wof:name":"Guanjiang",
    "wof:placetype":"locality"
},
  "geometry": {"coordinates":[109.023,27.5235],"type":"Point"}
}