{
  "type": "Feature",
  "properties": {
    "gn:admin1_code":"9.0",
    "gn:asciiname":"Mazhai",
    "gn:country_code":"CN",
    "gn:dem":286,
    "gn:feature_class":"P",
    "gn:feature_code":"PPL",
    "gn:name":"Mazhai",
    "gn:population":0,
    "gn:timezone":"Asia/Shanghai",
    "iso:country":"CN",
    "name:ind_x_preferred":[
        "Mazhai"
    ],
    "name:tam_x_preferred":[
        "\u0bae\u0bb4\u0bc8"
    ],
    "name:zho_x_preferred":[
        "\u9a6c\u5be8"
    ],
    "wof:name":"Mazhai",
    "wof:placetype":"locality"
},
  "geometry": {"coordinates":[113.31440000000001,34.55529],"type":"Point"}
}