{
  "type": "Feature",
  "properties": {
    "gn:admin1_code":"16.0",
    "gn:asciiname":"Jintou",
    "gn:country_code":"CN",
    "gn:dem":141,
    "gn:feature_class":"P",
    "gn:feature_code":"PPL",
    "gn:name":"Jintou",
    "gn:population":0,
    "gn:timezone":"Asia/Shanghai",
    "iso:country":"CN",
    "name:zho_x_preferred":[
        "\u9526\u5934"
    ],
    "wof:name":"Jintou",
    "wof:placetype":"locality"
},
  "geometry": {"coordinates":[107.31399999999999,22.0609],"type":"Point"}
}