{
  "type": "Feature",
  "properties": {
    "gn:admin1_code":"30.0",
    "gn:asciiname":"Dushui",
    "gn:country_code":"CN",
    "gn:dem":21,
    "gn:feature_class":"P",
    "gn:feature_code":"PPL",
    "gn:name":"Dushui",
    "gn:population":0,
    "gn:timezone":"Asia/Shanghai",
    "iso:country":"CN",
    "name:zho_x_preferred":[
        "\u6e21\u6c34"
    ],
    "wof:name":"Dushui",
    "wof:placetype":"locality"
},
  "geometry": {"coordinates":[112.57478999999999,22.85074],"type":"Point"}
}