{
  "type": "Feature",
  "properties": {
    "gn:admin1_code":"4.0",
    "gn:asciiname":"Liuxiaojicun",
    "gn:country_code":"CN",
    "gn:dem":44,
    "gn:feature_class":"P",
    "gn:feature_code":"PPL",
    "gn:name":"Liuxiaojicun",
    "gn:population":0,
    "gn:timezone":"Asia/Shanghai",
    "iso:country":"CN",
    "name:zho_x_preferred":[
        "\u5218\u5c0f\u96c6\u6751"
    ],
    "wof:name":"Liuxiaojicun",
    "wof:placetype":"locality"
},
  "geometry": {"coordinates":[116.38171,34.67572],"type":"Point"}
}