{
  "type": "Feature",
  "properties": {
    "gn:admin1_code":"32.0",
    "gn:asciiname":"Gelunda",
    "gn:country_code":"CN",
    "gn:dem":3583,
    "gn:feature_class":"P",
    "gn:feature_code":"PPL",
    "gn:name":"Gelunda",
    "gn:population":0,
    "gn:timezone":"Asia/Shanghai",
    "iso:country":"CN",
    "name:zho_x_preferred":[
        "\u683c\u4f26\u8fbe"
    ],
    "wof:name":"Gelunda",
    "wof:placetype":"locality"
},
  "geometry": {"coordinates":[99.9773,31.657],"type":"Point"}
}