{
  "type": "Feature",
  "properties": {
    "gn:admin1_code":"11.0",
    "gn:asciiname":"Yantianwan",
    "gn:country_code":"CN",
    "gn:dem":433,
    "gn:feature_class":"P",
    "gn:feature_code":"PPL",
    "gn:name":"Yantianwan",
    "gn:population":0,
    "gn:timezone":"Asia/Shanghai",
    "iso:country":"CN",
    "name:zho_x_preferred":[
        "\u781a\u7530\u6e7e"
    ],
    "wof:name":"Yantianwan",
    "wof:placetype":"locality"
},
  "geometry": {"coordinates":[109.38936,26.70425],"type":"Point"}
}