{
  "type": "Feature",
  "properties": {
    "gn:admin1_code":"32.0",
    "gn:asciiname":"Huangdimiao",
    "gn:country_code":"CN",
    "gn:dem":1170,
    "gn:feature_class":"P",
    "gn:feature_code":"PPL",
    "gn:name":"Huangdimiao",
    "gn:population":0,
    "gn:timezone":"Asia/Shanghai",
    "iso:country":"CN",
    "name:zho_x_preferred":[
        "\u7687\u5e1d\u5e99"
    ],
    "wof:name":"Huangdimiao",
    "wof:placetype":"locality"
},
  "geometry": {"coordinates":[104.476,32.0194],"type":"Point"}
}