{
  "type": "Feature",
  "properties": {
    "gn:admin1_code":"18",
    "gn:asciiname":"Huangnijing",
    "gn:country_code":"CN",
    "gn:dem":859,
    "gn:feature_class":"P",
    "gn:feature_code":"PPL",
    "gn:name":"Huangnijing",
    "gn:population":0,
    "gn:timezone":"Asia/Shanghai",
    "iso:country":"CN",
    "name:zho_x_preferred":[
        "\u9ec4\u6ce5\u4e95"
    ],
    "wof:name":"Huangnijing",
    "wof:placetype":"locality"
},
  "geometry": {"coordinates":[106.85299999999999,27.3459],"type":"Point"}
}