{
  "type": "Feature",
  "properties": {
    "gn:admin1_code":"9.0",
    "gn:asciiname":"Heshangzhai",
    "gn:country_code":"CN",
    "gn:dem":104,
    "gn:feature_class":"P",
    "gn:feature_code":"PPL",
    "gn:name":"Heshangzhai",
    "gn:population":0,
    "gn:timezone":"Asia/Shanghai",
    "iso:country":"CN",
    "name:zho_x_preferred":[
        "\u4f55\u4e0a\u5be8"
    ],
    "wof:name":"Heshangzhai",
    "wof:placetype":"locality"
},
  "geometry": {"coordinates":[112.60368,32.71953],"type":"Point"}
}