{
  "type": "Feature",
  "properties": {
    "gn:admin1_code":"6.0",
    "gn:asciiname":"Shangxitai",
    "gn:country_code":"CN",
    "gn:dem":3234,
    "gn:feature_class":"P",
    "gn:feature_code":"PPL",
    "gn:name":"Shangxitai",
    "gn:population":0,
    "gn:timezone":"Asia/Urumqi",
    "iso:country":"CN",
    "name:und_x_variant":[
        "\u4e0a\u897f\u53f0"
    ],
    "wof:name":"Shangxitai",
    "wof:placetype":"locality"
},
  "geometry": {"coordinates":[98.08159999999999,36.24908],"type":"Point"}
}