{
  "type": "Feature",
  "properties": {
    "gn:admin1_code":"11.0",
    "gn:asciiname":"Tiantangwan",
    "gn:country_code":"CN",
    "gn:dem":70,
    "gn:feature_class":"P",
    "gn:feature_code":"PPL",
    "gn:name":"Tiantangwan",
    "gn:population":0,
    "gn:timezone":"Asia/Shanghai",
    "iso:country":"CN",
    "name:zho_x_preferred":[
        "\u7530\u5858\u6e7e"
    ],
    "wof:name":"Tiantangwan",
    "wof:placetype":"locality"
},
  "geometry": {"coordinates":[113.26683,28.7671],"type":"Point"}
}