{
  "type": "Feature",
  "properties": {
    "gn:admin1_code":"24.0",
    "gn:asciiname":"Cailinli",
    "gn:country_code":"CN",
    "gn:dem":1963,
    "gn:feature_class":"P",
    "gn:feature_code":"PPL",
    "gn:name":"Cailinli",
    "gn:population":0,
    "gn:timezone":"Asia/Shanghai",
    "iso:country":"CN",
    "name:zho_x_preferred":[
        "\u6750\u6797\u91cc"
    ],
    "wof:name":"Cailinli",
    "wof:placetype":"locality"
},
  "geometry": {"coordinates":[113.80577,38.768],"type":"Point"}
}