{
  "type": "Feature",
  "properties": {
    "gn:admin1_code":"24.0",
    "gn:asciiname":"Luotuojie",
    "gn:country_code":"CN",
    "gn:dem":1663,
    "gn:feature_class":"P",
    "gn:feature_code":"PPL",
    "gn:name":"Luotuojie",
    "gn:population":0,
    "gn:timezone":"Asia/Shanghai",
    "iso:country":"CN",
    "name:und_x_variant":[
        "\u9a86\u9a7c\u754c"
    ],
    "name:zho_x_preferred":[
        "\u9a86\u9a7c\u754c"
    ],
    "wof:name":"Luotuojie",
    "wof:placetype":"locality"
},
  "geometry": {"coordinates":[113.73195,39.61143],"type":"Point"}
}