{
  "type": "Feature",
  "properties": {
    "gn:admin1_code":"32.0",
    "gn:asciiname":"Siqie",
    "gn:country_code":"CN",
    "gn:dem":2503,
    "gn:feature_class":"P",
    "gn:feature_code":"PPL",
    "gn:name":"Siqie",
    "gn:population":0,
    "gn:timezone":"Asia/Shanghai",
    "iso:country":"CN",
    "name:zho_x_preferred":[
        "\u56db\u4e14"
    ],
    "wof:name":"Siqie",
    "wof:placetype":"locality"
},
  "geometry": {"coordinates":[102.78700000000001,27.6957],"type":"Point"}
}