{
  "type": "Feature",
  "properties": {
    "gn:admin1_code":"32.0",
    "gn:asciiname":"Huangjue'ao",
    "gn:country_code":"CN",
    "gn:dem":341,
    "gn:feature_class":"P",
    "gn:feature_code":"PPL",
    "gn:name":"Huangjue\u2019ao",
    "gn:population":0,
    "gn:timezone":"Asia/Shanghai",
    "iso:country":"CN",
    "name:zho_x_preferred":[
        "\u9ec4\u6877\u5773"
    ],
    "name:zho_x_variant":[
        "Huangjue\u2019ao"
    ],
    "wof:name":"Huangjue'ao",
    "wof:placetype":"locality"
},
  "geometry": {"coordinates":[105.333,29.68474],"type":"Point"}
}