{
  "type": "Feature",
  "properties": {
    "gn:admin1_code":"18.0",
    "gn:asciiname":"Helishu",
    "gn:country_code":"CN",
    "gn:dem":690,
    "gn:feature_class":"P",
    "gn:feature_code":"PPL",
    "gn:name":"Helishu",
    "gn:population":0,
    "gn:timezone":"Asia/Shanghai",
    "iso:country":"CN",
    "name:zho_x_preferred":[
        "\u79be\u68a8\u6811"
    ],
    "wof:name":"Helishu",
    "wof:placetype":"locality"
},
  "geometry": {"coordinates":[108.23999999999999,27.0297],"type":"Point"}
}