{
  "type": "Feature",
  "properties": {
    "gn:admin1_code":"07",
    "gn:asciiname":"Waitun",
    "gn:country_code":"CN",
    "gn:dem":437,
    "gn:feature_class":"P",
    "gn:feature_code":"PPLA4",
    "gn:name":"Waitun",
    "gn:population":0,
    "gn:timezone":"Asia/Shanghai",
    "iso:country":"CN",
    "name:und_x_variant":[
        "Waitun Xiang"
    ],
    "name:zho_x_preferred":[
        "\u5916\u5c6f"
    ],
    "name:zho_x_variant":[
        "\u5916\u5c6f\u4e61"
    ],
    "wof:name":"Waitun",
    "wof:placetype":"locality"
},
  "geometry": {"coordinates":[118.98806,27.33472],"type":"Point"}
}