{
  "type": "Feature",
  "properties": {
    "gn:admin1_code":"19.0",
    "gn:asciiname":"Laohugou",
    "gn:country_code":"CN",
    "gn:dem":140,
    "gn:feature_class":"P",
    "gn:feature_code":"PPL",
    "gn:name":"Laohugou",
    "gn:population":0,
    "gn:timezone":"Asia/Shanghai",
    "iso:country":"CN",
    "name:zho_x_preferred":[
        "\u8001\u864e\u6c9f"
    ],
    "wof:name":"Laohugou",
    "wof:placetype":"locality"
},
  "geometry": {"coordinates":[124.21174999999999,42.6081],"type":"Point"}
}