{
  "type": "Feature",
  "properties": {
    "gn:admin1_code":"9.0",
    "gn:asciiname":"Dahaozhuang",
    "gn:country_code":"CN",
    "gn:dem":55,
    "gn:feature_class":"P",
    "gn:feature_code":"PPL",
    "gn:name":"Dahaozhuang",
    "gn:population":0,
    "gn:timezone":"Asia/Shanghai",
    "iso:country":"CN",
    "name:zho_x_preferred":[
        "\u5927\u90dd\u5e84"
    ],
    "wof:name":"Dahaozhuang",
    "wof:placetype":"locality"
},
  "geometry": {"coordinates":[114.51899,32.72094],"type":"Point"}
}