{
  "type": "Feature",
  "properties": {
    "gn:admin1_code":"1.0",
    "gn:asciiname":"Yanghuomiaocun",
    "gn:country_code":"CN",
    "gn:dem":27,
    "gn:feature_class":"P",
    "gn:feature_code":"PPL",
    "gn:name":"Yanghuomiaocun",
    "gn:population":0,
    "gn:timezone":"Asia/Shanghai",
    "iso:country":"CN",
    "name:zho_x_preferred":[
        "\u6768\u706b\u5e99\u6751"
    ],
    "wof:name":"Yanghuomiaocun",
    "wof:placetype":"locality"
},
  "geometry": {"coordinates":[117.04058999999999,33.50893],"type":"Point"}
}