{
  "type": "Feature",
  "properties": {
    "gn:admin1_code":"30",
    "gn:asciiname":"Shangjiao",
    "gn:country_code":"CN",
    "gn:dem":111,
    "gn:feature_class":"P",
    "gn:feature_code":"PPL",
    "gn:name":"Shangjiao",
    "gn:population":0,
    "gn:timezone":"Asia/Urumqi",
    "iso:country":"CN",
    "name:zho_x_preferred":[
        "\u4e0a\u89d2"
    ],
    "wof:name":"Shangjiao",
    "wof:placetype":"locality"
},
  "geometry": {"coordinates":[111.31529,21.78994],"type":"Point"}
}