{
  "type": "Feature",
  "properties": {
    "gn:admin1_code":"29.0",
    "gn:asciiname":"Shangbangzhang",
    "gn:country_code":"CN",
    "gn:dem":1818,
    "gn:feature_class":"P",
    "gn:feature_code":"PPL",
    "gn:name":"Shangbangzhang",
    "gn:population":0,
    "gn:timezone":"Asia/Shanghai",
    "iso:country":"CN",
    "name:zho_x_preferred":[
        "\u4e0a\u90a6\u638c"
    ],
    "wof:name":"Shangbangzhang",
    "wof:placetype":"locality"
},
  "geometry": {"coordinates":[98.0947,24.5673],"type":"Point"}
}