{
  "type": "Feature",
  "properties": {
    "gn:admin1_code":"24",
    "gn:asciiname":"Jicun",
    "gn:cc2":"CN",
    "gn:country_code":"CN",
    "gn:dem":744,
    "gn:feature_class":"P",
    "gn:feature_code":"PPL",
    "gn:name":"Jicun",
    "gn:population":0,
    "gn:timezone":"Asia/Shanghai",
    "iso:country":"CN",
    "name:und_x_variant":[
        "Chi-ts\u2019un",
        "Chi-ts\u2019un-chen",
        "Jicun"
    ],
    "wof:name":"Jicun",
    "wof:placetype":"locality"
},
  "geometry": {"coordinates":[111.96528000000001,37.33028],"type":"Point"}
}