{
  "type": "Feature",
  "properties": {
    "gn:admin1_code":"29",
    "gn:asciiname":"Niuchangba",
    "gn:country_code":"CN",
    "gn:dem":1162,
    "gn:feature_class":"P",
    "gn:feature_code":"PPL",
    "gn:name":"Niuchangba",
    "gn:population":0,
    "gn:timezone":"Asia/Shanghai",
    "iso:country":"CN",
    "name:zho_x_preferred":[
        "\u725b\u573a\u575d"
    ],
    "wof:name":"Niuchangba",
    "wof:placetype":"locality"
},
  "geometry": {"coordinates":[104.883,23.5138],"type":"Point"}
}