{
  "type": "Feature",
  "properties": {
    "gn:admin1_code":"33.0",
    "gn:asciiname":"Yantangwan",
    "gn:country_code":"CN",
    "gn:dem":827,
    "gn:feature_class":"P",
    "gn:feature_code":"PPL",
    "gn:name":"Yantangwan",
    "gn:population":0,
    "gn:timezone":"Asia/Shanghai",
    "iso:country":"CN",
    "name:zho_x_preferred":[
        "\u5830\u5858\u6e7e"
    ],
    "wof:name":"Yantangwan",
    "wof:placetype":"locality"
},
  "geometry": {"coordinates":[109.56711,30.91666],"type":"Point"}
}