{
  "type": "Feature",
  "properties": {
    "gn:admin1_code":"10",
    "gn:asciiname":"Ershisanhao",
    "gn:country_code":"CN",
    "gn:dem":976,
    "gn:feature_class":"P",
    "gn:feature_code":"PPLF",
    "gn:name":"Ershisanhao",
    "gn:population":0,
    "gn:timezone":"Asia/Shanghai",
    "iso:country":"CN",
    "name:zho_x_preferred":[
        "\u4e8c\u5341\u4e09\u53f7"
    ],
    "wof:name":"Ershisanhao",
    "wof:placetype":"locality"
},
  "geometry": {"coordinates":[117.64921,42.05827],"type":"Point"}
}