{
  "type": "Feature",
  "properties": {
    "gn:admin1_code":"19.0",
    "gn:asciiname":"Yingnan",
    "gn:country_code":"CN",
    "gn:dem":70,
    "gn:feature_class":"P",
    "gn:feature_code":"PPL",
    "gn:name":"Yingnan",
    "gn:population":0,
    "gn:timezone":"Asia/Shanghai",
    "iso:country":"CN",
    "name:zho_x_preferred":[
        "Yingnan"
    ],
    "name:zho_x_variant":[
        "\u82f1\u5357"
    ],
    "wof:name":"Yingnan",
    "wof:placetype":"locality"
},
  "geometry": {"coordinates":[122.90403999999999,40.85099],"type":"Point"}
}