{
  "type": "Feature",
  "properties": {
    "gn:admin1_code":"19.0",
    "gn:asciiname":"Zhaojiawazi",
    "gn:country_code":"CN",
    "gn:dem":296,
    "gn:feature_class":"P",
    "gn:feature_code":"PPL",
    "gn:name":"Zhaojiawazi",
    "gn:population":0,
    "gn:timezone":"Asia/Shanghai",
    "iso:country":"CN",
    "name:und_x_variant":[
        "\u8d75\u5bb6\u6d3c\u5b50"
    ],
    "name:zho_x_preferred":[
        "\u8d75\u5bb6\u6d3c\u5b50"
    ],
    "wof:name":"Zhaojiawazi",
    "wof:placetype":"locality"
},
  "geometry": {"coordinates":[120.36145999999999,41.73371],"type":"Point"}
}