{
  "type": "Feature",
  "properties": {
    "gn:admin1_code":"8.0",
    "gn:asciiname":"Daotiancun",
    "gn:country_code":"CN",
    "gn:dem":148,
    "gn:feature_class":"P",
    "gn:feature_code":"PPL",
    "gn:name":"Daotiancun",
    "gn:population":0,
    "gn:timezone":"Asia/Shanghai",
    "iso:country":"CN",
    "name:zho_x_preferred":[
        "\u7a3b\u7530\u6751"
    ],
    "wof:name":"Daotiancun",
    "wof:placetype":"locality"
},
  "geometry": {"coordinates":[123.79919,47.17573],"type":"Point"}
}