{
  "type": "Feature",
  "properties": {
    "gn:admin1_code":"10",
    "gn:asciiname":"Xiyongfengbu",
    "gn:country_code":"CN",
    "gn:dem":1137,
    "gn:feature_class":"P",
    "gn:feature_code":"PPL",
    "gn:name":"Xiyongfengbu",
    "gn:population":0,
    "gn:timezone":"Asia/Shanghai",
    "iso:country":"CN",
    "name:und_x_variant":[
        "Hsi-yung-feng-p\u2019u",
        "Xiyongfengpu",
        "Xiyongfengbu"
    ],
    "name:zho_x_preferred":[
        "\u897f\u6c38\u4e30\u5821"
    ],
    "wof:name":"Xiyongfengbu",
    "wof:placetype":"locality"
},
  "geometry": {"coordinates":[114.53836,40.90732],"type":"Point"}
}