{
  "type": "Feature",
  "properties": {
    "gn:admin1_code":"12.0",
    "gn:asciiname":"Shizuishanxin",
    "gn:country_code":"CN",
    "gn:dem":63,
    "gn:feature_class":"P",
    "gn:feature_code":"PPL",
    "gn:name":"Shizuishanxin",
    "gn:population":0,
    "gn:timezone":"Asia/Shanghai",
    "iso:country":"CN",
    "name:zho_x_preferred":[
        "Shizuishanxin"
    ],
    "name:zho_x_variant":[
        "\u77f3\u5480\u5c71\u65b0"
    ],
    "wof:name":"Shizuishanxin",
    "wof:placetype":"locality"
},
  "geometry": {"coordinates":[111.77186,30.15378],"type":"Point"}
}