{
  "type": "Feature",
  "properties": {
    "gn:admin1_code":"25",
    "gn:asciiname":"Dashu",
    "gn:cc2":"CN",
    "gn:country_code":"CN",
    "gn:dem":96,
    "gn:feature_class":"P",
    "gn:feature_code":"PPL",
    "gn:name":"Dashu",
    "gn:population":0,
    "gn:timezone":"Asia/Shanghai",
    "iso:country":"CN",
    "name:und_x_variant":[
        "Ta-shu",
        "Dashu"
    ],
    "wof:name":"Dashu",
    "wof:placetype":"locality"
},
  "geometry": {"coordinates":[117.08333,35.45],"type":"Point"}
}