{
  "type": "Feature",
  "properties": {
    "gn:admin1_code":"12.0",
    "gn:asciiname":"Houping",
    "gn:country_code":"CN",
    "gn:dem":1496,
    "gn:feature_class":"P",
    "gn:feature_code":"PPL",
    "gn:name":"Houping",
    "gn:population":0,
    "gn:timezone":"Asia/Shanghai",
    "iso:country":"CN",
    "name:zho_x_preferred":[
        "\u540e\u576a"
    ],
    "wof:name":"Houping",
    "wof:placetype":"locality"
},
  "geometry": {"coordinates":[110.10011000000002,30.26024],"type":"Point"}
}