{
  "type": "Feature",
  "properties": {
    "gn:admin1_code":"9.0",
    "gn:asciiname":"Songlaoqiao",
    "gn:country_code":"CN",
    "gn:dem":59,
    "gn:feature_class":"P",
    "gn:feature_code":"PPL",
    "gn:name":"Songlaoqiao",
    "gn:population":0,
    "gn:timezone":"Asia/Shanghai",
    "iso:country":"CN",
    "name:zho_x_preferred":[
        "\u5b8b\u8001\u6865"
    ],
    "wof:name":"Songlaoqiao",
    "wof:placetype":"locality"
},
  "geometry": {"coordinates":[114.13227999999999,33.8412],"type":"Point"}
}