{
  "type": "Feature",
  "properties": {
    "gn:admin1_code":"32.0",
    "gn:asciiname":"Luxigou",
    "gn:country_code":"CN",
    "gn:dem":559,
    "gn:feature_class":"P",
    "gn:feature_code":"PPL",
    "gn:name":"Luxigou",
    "gn:population":0,
    "gn:timezone":"Asia/Shanghai",
    "iso:country":"CN",
    "name:zho_x_preferred":[
        "\u9e7f\u6eaa\u6c9f"
    ],
    "wof:name":"Luxigou",
    "wof:placetype":"locality"
},
  "geometry": {"coordinates":[107.121,31.8647],"type":"Point"}
}