{
  "type": "Feature",
  "properties": {
    "gn:admin1_code":"9.0",
    "gn:asciiname":"Xiaojie",
    "gn:country_code":"CN",
    "gn:dem":364,
    "gn:feature_class":"P",
    "gn:feature_code":"PPL",
    "gn:name":"Xiaojie",
    "gn:population":0,
    "gn:timezone":"Asia/Shanghai",
    "iso:country":"CN",
    "name:ceb_x_preferred":[
        "Xiaojie"
    ],
    "name:deu_x_preferred":[
        "Xiaojie"
    ],
    "name:swe_x_preferred":[
        "Xiaojie"
    ],
    "name:zho_x_preferred":[
        "\u5c0f\u8857"
    ],
    "wof:name":"Xiaojie",
    "wof:placetype":"locality"
},
  "geometry": {"coordinates":[111.50391,34.36234],"type":"Point"}
}