{
  "type": "Feature",
  "properties": {
    "gn:admin1_code":"05",
    "gn:asciiname":"Hengdaohezicun",
    "gn:country_code":"CN",
    "gn:dem":512,
    "gn:feature_class":"P",
    "gn:feature_code":"PPL",
    "gn:name":"Hengdaohezicun",
    "gn:population":0,
    "gn:timezone":"Asia/Shanghai",
    "iso:country":"CN",
    "name:und_x_variant":[
        "Hengdaohezi",
        "Hengdaohezicun"
    ],
    "name:zho_x_preferred":[
        "\u6a2a\u9053\u6cb3\u5b50"
    ],
    "name:zho_x_variant":[
        "\u6a2a\u9053\u6cb3\u5b50\u6751"
    ],
    "wof:name":"Hengdaohezicun",
    "wof:placetype":"locality"
},
  "geometry": {"coordinates":[126.33922,41.82174000000001],"type":"Point"}
}