{
  "type": "Feature",
  "properties": {
    "gn:admin1_code":"9.0",
    "gn:asciiname":"Laorenzhuang",
    "gn:country_code":"CN",
    "gn:dem":75,
    "gn:feature_class":"P",
    "gn:feature_code":"PPL",
    "gn:name":"Laorenzhuang",
    "gn:population":0,
    "gn:timezone":"Asia/Shanghai",
    "iso:country":"CN",
    "name:zho_x_preferred":[
        "\u8001\u4efb\u5e84"
    ],
    "wof:name":"Laorenzhuang",
    "wof:placetype":"locality"
},
  "geometry": {"coordinates":[114.10896,35.20436],"type":"Point"}
}