{
  "type": "Feature",
  "properties": {
    "gn:admin1_code":"21",
    "gn:asciiname":"Majiahu",
    "gn:country_code":"CN",
    "gn:dem":1134,
    "gn:feature_class":"P",
    "gn:feature_code":"PPL",
    "gn:name":"Majiahu",
    "gn:population":0,
    "gn:timezone":"Asia/Shanghai",
    "iso:country":"CN",
    "name:und_x_variant":[
        "Majiahu Xiang"
    ],
    "name:zho_x_preferred":[
        "\u9a6c\u5bb6\u6e56"
    ],
    "name:zho_x_variant":[
        "\u9a6c\u5bb6\u6e56\u4e61"
    ],
    "wof:name":"Majiahu",
    "wof:placetype":"locality"
},
  "geometry": {"coordinates":[106.13692,37.892],"type":"Point"}
}