{
  "type": "Feature",
  "properties": {
    "gn:admin1_code":"26.0",
    "gn:asciiname":"Shizuizi",
    "gn:country_code":"CN",
    "gn:dem":1133,
    "gn:feature_class":"P",
    "gn:feature_code":"PPL",
    "gn:name":"Shizuizi",
    "gn:population":0,
    "gn:timezone":"Asia/Shanghai",
    "iso:country":"CN",
    "name:und_x_variant":[
        "\u77f3\u5480\u5b50"
    ],
    "wof:name":"Shizuizi",
    "wof:placetype":"locality"
},
  "geometry": {"coordinates":[109.48812,34.04363],"type":"Point"}
}