{
  "type": "Feature",
  "properties": {
    "gn:admin1_code":"1.0",
    "gn:asciiname":"Xuehucun",
    "gn:country_code":"CN",
    "gn:dem":25,
    "gn:feature_class":"P",
    "gn:feature_code":"PPL",
    "gn:name":"Xuehucun",
    "gn:population":0,
    "gn:timezone":"Asia/Shanghai",
    "iso:country":"CN",
    "name:zho_x_preferred":[
        "\u859b\u80e1\u6751"
    ],
    "wof:name":"Xuehucun",
    "wof:placetype":"locality"
},
  "geometry": {"coordinates":[116.88339999999999,33.49714],"type":"Point"}
}