{
  "type": "Feature",
  "properties": {
    "gn:admin1_code":"16.0",
    "gn:asciiname":"Haosheng",
    "gn:country_code":"CN",
    "gn:dem":543,
    "gn:feature_class":"P",
    "gn:feature_code":"PPL",
    "gn:name":"Haosheng",
    "gn:population":0,
    "gn:timezone":"Asia/Shanghai",
    "iso:country":"CN",
    "name:zho_x_preferred":[
        "\u597d\u76db"
    ],
    "wof:name":"Haosheng",
    "wof:placetype":"locality"
},
  "geometry": {"coordinates":[107.012,22.8485],"type":"Point"}
}