{
  "type": "Feature",
  "properties": {
    "gn:admin1_code":"13",
    "gn:asciiname":"Tuomuniya Kanzi'erjing",
    "gn:country_code":"CN",
    "gn:dem":-25,
    "gn:feature_class":"P",
    "gn:feature_code":"PPL",
    "gn:name":"Tuomuniya Kanzi\u2019erjing",
    "gn:population":0,
    "gn:timezone":"Asia/Urumqi",
    "iso:country":"CN",
    "name:und_x_variant":[
        "Tuomuniya Kanzi\u2019erjing",
        "\u6258\u6728\u5c3c\u4e9a\u574e\u5b5c\u513f\u4e95"
    ],
    "wof:name":"Tuomuniya Kanzi'erjing",
    "wof:placetype":"locality"
},
  "geometry": {"coordinates":[89.85834,42.59907000000001],"type":"Point"}
}