{
  "type": "Feature",
  "properties": {
    "gn:admin1_code":"15.0",
    "gn:asciiname":"Xingjia",
    "gn:country_code":"CN",
    "gn:dem":2243,
    "gn:feature_class":"P",
    "gn:feature_code":"PPL",
    "gn:name":"Xingjia",
    "gn:population":0,
    "gn:timezone":"Asia/Shanghai",
    "iso:country":"CN",
    "name:und_x_variant":[
        "\u90a2\u5bb6"
    ],
    "wof:name":"Xingjia",
    "wof:placetype":"locality"
},
  "geometry": {"coordinates":[102.88606,35.74589],"type":"Point"}
}