{
  "type": "Feature",
  "properties": {
    "gn:admin1_code":"14",
    "gn:asciiname":"Niwudang",
    "gn:country_code":"CN",
    "gn:dem":4767,
    "gn:feature_class":"P",
    "gn:feature_code":"PPL",
    "gn:name":"Niwudang",
    "gn:population":0,
    "gn:timezone":"Asia/Urumqi",
    "iso:country":"CN",
    "name:zho_x_preferred":[
        "\u5c3c\u4e4c\u5f53"
    ],
    "wof:name":"Niwudang",
    "wof:placetype":"locality"
},
  "geometry": {"coordinates":[89.84780000000001,29.6676],"type":"Point"}
}