{
  "type": "Feature",
  "properties": {
    "gn:admin1_code":"29.0",
    "gn:asciiname":"Xiaoludeke",
    "gn:country_code":"CN",
    "gn:dem":1565,
    "gn:feature_class":"P",
    "gn:feature_code":"PPL",
    "gn:name":"Xiaoludeke",
    "gn:population":0,
    "gn:timezone":"Asia/Shanghai",
    "iso:country":"CN",
    "name:zho_x_preferred":[
        "\u5c0f\u9c81\u5f97\u514b"
    ],
    "wof:name":"Xiaoludeke",
    "wof:placetype":"locality"
},
  "geometry": {"coordinates":[104.375,24.9867],"type":"Point"}
}