{
  "type": "Feature",
  "properties": {
    "gn:admin1_code":"04",
    "gn:asciiname":"Yinshanhu Nongchang",
    "gn:country_code":"CN",
    "gn:dem":2,
    "gn:feature_class":"P",
    "gn:feature_code":"PPLF",
    "gn:name":"Yinshanhu Nongchang",
    "gn:population":0,
    "gn:timezone":"Asia/Shanghai",
    "iso:country":"CN",
    "wof:name":"Yinshanhu Nongchang",
    "wof:placetype":"locality"
},
  "geometry": {"coordinates":[120.68277999999999,31.24389],"type":"Point"}
}