{
  "type": "Feature",
  "properties": {
    "gn:admin1_code":"8.0",
    "gn:asciiname":"Dalicun",
    "gn:country_code":"CN",
    "gn:dem":295,
    "gn:feature_class":"P",
    "gn:feature_code":"PPL",
    "gn:name":"Dalicun",
    "gn:population":0,
    "gn:timezone":"Asia/Shanghai",
    "iso:country":"CN",
    "name:zho_x_preferred":[
        "\u8fbe\u91cc\u6751"
    ],
    "wof:name":"Dalicun",
    "wof:placetype":"locality"
},
  "geometry": {"coordinates":[128.76174,46.95938],"type":"Point"}
}