{
  "type": "Feature",
  "properties": {
    "gn:admin1_code":"4.0",
    "gn:asciiname":"Maipo",
    "gn:country_code":"CN",
    "gn:dem":82,
    "gn:feature_class":"P",
    "gn:feature_code":"PPL",
    "gn:name":"Maipo",
    "gn:population":0,
    "gn:timezone":"Asia/Shanghai",
    "iso:country":"CN",
    "name:deu_x_preferred":[
        "Maipo"
    ],
    "name:fra_x_preferred":[
        "Maipo"
    ],
    "name:kat_x_preferred":[
        "\u10db\u10d0\u10d8\u10de\u10dd"
    ],
    "name:nld_x_preferred":[
        "Maipo"
    ],
    "name:por_x_preferred":[
        "Maipo"
    ],
    "name:rus_x_preferred":[
        "\u041c\u0430\u0439\u043f\u043e"
    ],
    "name:slk_x_preferred":[
        "Maipo"
    ],
    "name:spa_x_preferred":[
        "Maipo"
    ],
    "name:zho_x_preferred":[
        "\u9ea6\u5761"
    ],
    "wof:name":"Maipo",
    "wof:placetype":"locality"
},
  "geometry": {"coordinates":[119.05622,31.37354],"type":"Point"}
}