{
  "type": "Feature",
  "properties": {
    "gn:admin1_code":"22.0",
    "gn:asciiname":"Dongdiancun",
    "gn:country_code":"CN",
    "gn:dem":31,
    "gn:feature_class":"P",
    "gn:feature_code":"PPL",
    "gn:name":"Dongdiancun",
    "gn:population":0,
    "gn:timezone":"Asia/Shanghai",
    "iso:country":"CN",
    "name:zho_x_preferred":[
        "\u4e1c\u5e97\u6751"
    ],
    "wof:name":"Dongdiancun",
    "wof:placetype":"locality"
},
  "geometry": {"coordinates":[116.55266,39.75308],"type":"Point"}
}