{
  "type": "Feature",
  "properties": {
    "gn:admin1_code":"18",
    "gn:asciiname":"Tianxingqiao",
    "gn:country_code":"CN",
    "gn:dem":1581,
    "gn:feature_class":"P",
    "gn:feature_code":"PPL",
    "gn:name":"Tianxingqiao",
    "gn:population":0,
    "gn:timezone":"Asia/Shanghai",
    "iso:country":"CN",
    "name:zho_x_preferred":[
        "\u5929\u661f\u6865"
    ],
    "wof:name":"Tianxingqiao",
    "wof:placetype":"locality"
},
  "geometry": {"coordinates":[105.501,27.4131],"type":"Point"}
}