{
  "type": "Feature",
  "properties": {
    "gn:admin1_code":"30.0",
    "gn:asciiname":"Kemulang",
    "gn:country_code":"CN",
    "gn:dem":140,
    "gn:feature_class":"P",
    "gn:feature_code":"PPL",
    "gn:name":"Kemulang",
    "gn:population":0,
    "gn:timezone":"Asia/Shanghai",
    "iso:country":"CN",
    "name:zho_x_preferred":[
        "\u67ef\u6728\u5d00"
    ],
    "wof:name":"Kemulang",
    "wof:placetype":"locality"
},
  "geometry": {"coordinates":[112.25006,23.99078],"type":"Point"}
}