{
  "type": "Feature",
  "properties": {
    "gn:admin1_code":"16.0",
    "gn:asciiname":"Shengman",
    "gn:country_code":"CN",
    "gn:dem":450,
    "gn:feature_class":"P",
    "gn:feature_code":"PPL",
    "gn:name":"Shengman",
    "gn:population":0,
    "gn:timezone":"Asia/Shanghai",
    "iso:country":"CN",
    "name:zho_x_preferred":[
        "\u751f\u6ee1"
    ],
    "wof:name":"Shengman",
    "wof:placetype":"locality"
},
  "geometry": {"coordinates":[107.255,24.499],"type":"Point"}
}