{
  "type": "Feature",
  "properties": {
    "gn:admin1_code":"5.0",
    "gn:asciiname":"Zengshengcun",
    "gn:country_code":"CN",
    "gn:dem":147,
    "gn:feature_class":"P",
    "gn:feature_code":"PPL",
    "gn:name":"Zengshengcun",
    "gn:population":0,
    "gn:timezone":"Asia/Shanghai",
    "iso:country":"CN",
    "name:zho_x_preferred":[
        "\u589e\u80dc\u6751"
    ],
    "wof:name":"Zengshengcun",
    "wof:placetype":"locality"
},
  "geometry": {"coordinates":[122.81622,45.30941],"type":"Point"}
}