{
  "type": "Feature",
  "properties": {
    "gn:admin1_code":"9.0",
    "gn:asciiname":"Dafangzhuang",
    "gn:country_code":"CN",
    "gn:dem":101,
    "gn:feature_class":"P",
    "gn:feature_code":"PPL",
    "gn:name":"Dafangzhuang",
    "gn:population":0,
    "gn:timezone":"Asia/Shanghai",
    "iso:country":"CN",
    "name:zho_x_preferred":[
        "\u5927\u65b9\u5e84"
    ],
    "wof:name":"Dafangzhuang",
    "wof:placetype":"locality"
},
  "geometry": {"coordinates":[112.78986999999999,32.63708],"type":"Point"}
}