{
  "type": "Feature",
  "properties": {
    "gn:admin1_code":"02",
    "gn:asciiname":"Shangbaiyancun",
    "gn:country_code":"CN",
    "gn:dem":31,
    "gn:feature_class":"P",
    "gn:feature_code":"PPL",
    "gn:name":"Shangbaiyancun",
    "gn:population":0,
    "gn:timezone":"Asia/Shanghai",
    "iso:country":"CN",
    "name:und_x_variant":[
        "Wai-pai-yen",
        "Shangbaiyan",
        "Shangbaiyancun"
    ],
    "name:zho_x_preferred":[
        "\u4e0a\u767d\u5ca9"
    ],
    "name:zho_x_variant":[
        "\u4e0a\u767d\u5ca9\u6751"
    ],
    "wof:name":"Shangbaiyancun",
    "wof:placetype":"locality"
},
  "geometry": {"coordinates":[120.65123,28.09854],"type":"Point"}
}