{
  "type": "Feature",
  "properties": {
    "gn:admin1_code":"26.0",
    "gn:asciiname":"Niejiahecun",
    "gn:country_code":"CN",
    "gn:dem":1090,
    "gn:feature_class":"P",
    "gn:feature_code":"PPL",
    "gn:name":"Niejiahecun",
    "gn:population":0,
    "gn:timezone":"Asia/Shanghai",
    "iso:country":"CN",
    "name:zho_x_preferred":[
        "\u8042\u5bb6\u6cb3\u6751"
    ],
    "wof:name":"Niejiahecun",
    "wof:placetype":"locality"
},
  "geometry": {"coordinates":[108.85973,35.16814],"type":"Point"}
}