{
  "type": "Feature",
  "properties": {
    "gn:admin1_code":"19.0",
    "gn:asciiname":"Maqiantai",
    "gn:country_code":"CN",
    "gn:dem":100,
    "gn:feature_class":"P",
    "gn:feature_code":"PPL",
    "gn:name":"Maqiantai",
    "gn:population":0,
    "gn:timezone":"Asia/Shanghai",
    "iso:country":"CN",
    "name:zho_x_preferred":[
        "\u9a6c\u5343\u53f0"
    ],
    "wof:name":"Maqiantai",
    "wof:placetype":"locality"
},
  "geometry": {"coordinates":[124.01072000000001,42.67336],"type":"Point"}
}