{
  "type": "Feature",
  "properties": {
    "gn:admin1_code":"11",
    "gn:asciiname":"Qingshanmiao",
    "gn:country_code":"CN",
    "gn:dem":721,
    "gn:feature_class":"P",
    "gn:feature_code":"PPL",
    "gn:name":"Qingshanmiao",
    "gn:population":0,
    "gn:timezone":"Asia/Shanghai",
    "iso:country":"CN",
    "name:und_x_variant":[
        "Qingshan"
    ],
    "name:zho_x_preferred":[
        "\u9752\u5c71\u5e99"
    ],
    "wof:name":"Qingshanmiao",
    "wof:placetype":"locality"
},
  "geometry": {"coordinates":[110.69649,27.35999],"type":"Point"}
}