{
  "type": "Feature",
  "properties": {
    "gn:admin1_code":"12.0",
    "gn:asciiname":"Shuiquanwan",
    "gn:country_code":"CN",
    "gn:dem":697,
    "gn:feature_class":"P",
    "gn:feature_code":"PPL",
    "gn:name":"Shuiquanwan",
    "gn:population":0,
    "gn:timezone":"Asia/Shanghai",
    "iso:country":"CN",
    "name:zho_x_preferred":[
        "\u6c34\u6cc9\u6e7e"
    ],
    "wof:name":"Shuiquanwan",
    "wof:placetype":"locality"
},
  "geometry": {"coordinates":[111.67775,31.52437],"type":"Point"}
}