{
  "type": "Feature",
  "properties": {
    "gn:admin1_code":"12.0",
    "gn:asciiname":"Guodihu",
    "gn:country_code":"CN",
    "gn:dem":34,
    "gn:feature_class":"P",
    "gn:feature_code":"PPL",
    "gn:name":"Guodihu",
    "gn:population":0,
    "gn:timezone":"Asia/Shanghai",
    "iso:country":"CN",
    "name:zho_x_preferred":[
        "\u9505\u5e95\u6e56"
    ],
    "wof:name":"Guodihu",
    "wof:placetype":"locality"
},
  "geometry": {"coordinates":[112.57364,29.65163],"type":"Point"}
}