{
  "type": "Feature",
  "properties": {
    "gn:admin1_code":"3.0",
    "gn:asciiname":"Beitou",
    "gn:country_code":"CN",
    "gn:dem":104,
    "gn:feature_class":"P",
    "gn:feature_code":"PPL",
    "gn:name":"Beitou",
    "gn:population":0,
    "gn:timezone":"Asia/Shanghai",
    "iso:country":"CN",
    "name:und_x_variant":[
        "\u9642\u5934"
    ],
    "wof:name":"Beitou",
    "wof:placetype":"locality"
},
  "geometry": {"coordinates":[114.369,27.0267],"type":"Point"}
}