{
  "type": "Feature",
  "properties": {
    "gn:admin1_code":"4.0",
    "gn:asciiname":"Xiaohe",
    "gn:country_code":"CN",
    "gn:dem":8,
    "gn:feature_class":"P",
    "gn:feature_code":"PPL",
    "gn:name":"Xiaohe",
    "gn:population":0,
    "gn:timezone":"Asia/Shanghai",
    "iso:country":"CN",
    "name:zho_x_preferred":[
        "Xiaohe"
    ],
    "name:zho_x_variant":[
        "\u5c0f\u8d3a"
    ],
    "wof:name":"Xiaohe",
    "wof:placetype":"locality"
},
  "geometry": {"coordinates":[119.07493999999998,33.82315],"type":"Point"}
}