{
  "type": "Feature",
  "properties": {
    "gn:admin1_code":"3.0",
    "gn:asciiname":"Zhoudaowu",
    "gn:country_code":"CN",
    "gn:dem":355,
    "gn:feature_class":"P",
    "gn:feature_code":"PPL",
    "gn:name":"Zhoudaowu",
    "gn:population":0,
    "gn:timezone":"Asia/Shanghai",
    "iso:country":"CN",
    "name:zho_x_preferred":[
        "\u5468\u9053\u575e"
    ],
    "wof:name":"Zhoudaowu",
    "wof:placetype":"locality"
},
  "geometry": {"coordinates":[117.896,28.1345],"type":"Point"}
}