{
  "type": "Feature",
  "properties": {
    "gn:admin1_code":"32.0",
    "gn:asciiname":"Zhongxing",
    "gn:country_code":"CN",
    "gn:dem":531,
    "gn:feature_class":"P",
    "gn:feature_code":"PPL",
    "gn:name":"Zhongxing",
    "gn:population":0,
    "gn:timezone":"Asia/Shanghai",
    "iso:country":"CN",
    "name:ceb_x_preferred":[
        "Zhongxing"
    ],
    "name:deu_x_preferred":[
        "Zhongxing"
    ],
    "name:pol_x_preferred":[
        "Zhongxing"
    ],
    "name:swe_x_preferred":[
        "Zhongxing"
    ],
    "name:zho_x_preferred":[
        "\u91cd\u5174"
    ],
    "wof:name":"Zhongxing",
    "wof:placetype":"locality"
},
  "geometry": {"coordinates":[105.654,28.6161],"type":"Point"}
}