{
  "type": "Feature",
  "properties": {
    "gn:admin1_code":"29.0",
    "gn:asciiname":"Shangkangjia",
    "gn:country_code":"CN",
    "gn:dem":1936,
    "gn:feature_class":"P",
    "gn:feature_code":"PPL",
    "gn:name":"Shangkangjia",
    "gn:population":0,
    "gn:timezone":"Asia/Shanghai",
    "iso:country":"CN",
    "name:zho_x_preferred":[
        "\u4e0a\u5eb7\u5bb6"
    ],
    "wof:name":"Shangkangjia",
    "wof:placetype":"locality"
},
  "geometry": {"coordinates":[100.06100000000001,23.6102],"type":"Point"}
}