{
  "type": "Feature",
  "properties": {
    "gn:admin1_code":"22.0",
    "gn:asciiname":"Wangjiashancun",
    "gn:country_code":"CN",
    "gn:dem":539,
    "gn:feature_class":"P",
    "gn:feature_code":"PPL",
    "gn:name":"Wangjiashancun",
    "gn:population":0,
    "gn:timezone":"Asia/Shanghai",
    "iso:country":"CN",
    "name:zho_x_preferred":[
        "\u738b\u5bb6\u5c71\u6751"
    ],
    "wof:name":"Wangjiashancun",
    "wof:placetype":"locality"
},
  "geometry": {"coordinates":[116.18913000000001,40.50561],"type":"Point"}
}