{
  "type": "Feature",
  "properties": {
    "gn:admin1_code":"11",
    "gn:asciiname":"Shibitang",
    "gn:country_code":"CN",
    "gn:dem":103,
    "gn:feature_class":"P",
    "gn:feature_code":"PPL",
    "gn:name":"Shibitang",
    "gn:population":0,
    "gn:timezone":"Asia/Shanghai",
    "iso:country":"CN",
    "name:zho_x_preferred":[
        "\u77f3\u78a7\u5858"
    ],
    "wof:name":"Shibitang",
    "wof:placetype":"locality"
},
  "geometry": {"coordinates":[112.47762,27.66252],"type":"Point"}
}