{
  "type": "Feature",
  "properties": {
    "gn:admin1_code":"15.0",
    "gn:asciiname":"Laozhuanghe",
    "gn:country_code":"CN",
    "gn:dem":1393,
    "gn:feature_class":"P",
    "gn:feature_code":"PPL",
    "gn:name":"Laozhuanghe",
    "gn:population":0,
    "gn:timezone":"Asia/Shanghai",
    "iso:country":"CN",
    "name:zho_x_preferred":[
        "\u8001\u5e84\u6cb3"
    ],
    "wof:name":"Laozhuanghe",
    "wof:placetype":"locality"
},
  "geometry": {"coordinates":[108.414,36.3809],"type":"Point"}
}