{
  "type": "Feature",
  "properties": {
    "gn:admin1_code":"18",
    "gn:asciiname":"Niupizhai",
    "gn:country_code":"CN",
    "gn:dem":555,
    "gn:feature_class":"P",
    "gn:feature_code":"PPL",
    "gn:name":"Niupizhai",
    "gn:population":0,
    "gn:timezone":"Asia/Shanghai",
    "iso:country":"CN",
    "name:zho_x_preferred":[
        "\u725b\u76ae\u5be8"
    ],
    "wof:name":"Niupizhai",
    "wof:placetype":"locality"
},
  "geometry": {"coordinates":[106.666,25.4552],"type":"Point"}
}