{
  "type": "Feature",
  "properties": {
    "gn:admin1_code":"15.0",
    "gn:asciiname":"Xiaozhaizi",
    "gn:country_code":"CN",
    "gn:dem":2009,
    "gn:feature_class":"P",
    "gn:feature_code":"PPL",
    "gn:name":"Xiaozhaizi",
    "gn:population":0,
    "gn:timezone":"Asia/Shanghai",
    "iso:country":"CN",
    "name:zho_x_preferred":[
        "\u5c0f\u5be8\u5b50"
    ],
    "wof:name":"Xiaozhaizi",
    "wof:placetype":"locality"
},
  "geometry": {"coordinates":[101.111,38.6141],"type":"Point"}
}