{
  "type": "Feature",
  "properties": {
    "gn:admin1_code":"11",
    "gn:asciiname":"Chonggaolei",
    "gn:country_code":"CN",
    "gn:dem":937,
    "gn:feature_class":"P",
    "gn:feature_code":"PPL",
    "gn:name":"Chonggaolei",
    "gn:population":0,
    "gn:timezone":"Asia/Shanghai",
    "iso:country":"CN",
    "name:und_x_variant":[
        "\u5d07\u9ad8\u6f2f",
        "Chonggaolei"
    ],
    "wof:name":"Chonggaolei",
    "wof:placetype":"locality"
},
  "geometry": {"coordinates":[112.00639,25.96056],"type":"Point"}
}