{
  "type": "Feature",
  "properties": {
    "gn:admin1_code":"02",
    "gn:asciiname":"Wan'ao",
    "gn:country_code":"CN",
    "gn:dem":10,
    "gn:feature_class":"P",
    "gn:feature_code":"PPL",
    "gn:name":"Wan\u2019ao",
    "gn:population":0,
    "gn:timezone":"Asia/Shanghai",
    "iso:country":"CN",
    "name:zho_x_preferred":[
        "Wan-ao-t\u2019ou"
    ],
    "name:zho_x_variant":[
        "Wan-ao-ch\u2019ien-shan",
        "Wan\u2019ao"
    ],
    "wof:name":"Wan'ao",
    "wof:placetype":"locality"
},
  "geometry": {"coordinates":[120.96222,28.09278],"type":"Point"}
}