{
  "type": "Feature",
  "properties": {
    "gn:admin1_code":"4.0",
    "gn:asciiname":"Zhongbei",
    "gn:country_code":"CN",
    "gn:dem":3,
    "gn:feature_class":"P",
    "gn:feature_code":"PPL",
    "gn:name":"Zhongbei",
    "gn:population":0,
    "gn:timezone":"Asia/Shanghai",
    "iso:country":"CN",
    "name:zho_x_preferred":[
        "Zhongbei"
    ],
    "name:zho_x_variant":[
        "\u4e2d\u5317",
        "\u4e2d\u5317\u9547"
    ],
    "wof:name":"Zhongbei",
    "wof:placetype":"locality"
},
  "geometry": {"coordinates":[121.72351999999999,31.81753],"type":"Point"}
}