{
  "type": "Feature",
  "properties": {
    "gn:admin1_code":"7.0",
    "gn:asciiname":"Chikeng",
    "gn:country_code":"CN",
    "gn:dem":364,
    "gn:feature_class":"P",
    "gn:feature_code":"PPL",
    "gn:name":"Chikeng",
    "gn:population":0,
    "gn:timezone":"Asia/Shanghai",
    "iso:country":"CN",
    "name:und_x_variant":[
        "\u8d64\u5751"
    ],
    "wof:name":"Chikeng",
    "wof:placetype":"locality"
},
  "geometry": {"coordinates":[116.76909999999999,26.73062],"type":"Point"}
}