{
  "type": "Feature",
  "properties": {
    "gn:admin1_code":"8.0",
    "gn:asciiname":"Daguangxing Zhuangtun",
    "gn:country_code":"CN",
    "gn:dem":162,
    "gn:feature_class":"P",
    "gn:feature_code":"PPL",
    "gn:name":"Daguangxing Zhuangtun",
    "gn:population":0,
    "gn:timezone":"Asia/Shanghai",
    "iso:country":"CN",
    "name:zho_x_preferred":[
        "\u5927\u5e7f\u5174\u5e84\u5c6f"
    ],
    "wof:name":"Daguangxing Zhuangtun",
    "wof:placetype":"locality"
},
  "geometry": {"coordinates":[127.40463,45.8001],"type":"Point"}
}