{
  "type": "Feature",
  "properties": {
    "gn:admin1_code":"11.0",
    "gn:asciiname":"Huangjiachong",
    "gn:country_code":"CN",
    "gn:dem":429,
    "gn:feature_class":"P",
    "gn:feature_code":"PPL",
    "gn:name":"Huangjiachong",
    "gn:population":0,
    "gn:timezone":"Asia/Shanghai",
    "iso:country":"CN",
    "name:zho_x_preferred":[
        "\u9ec4\u5bb6\u51b2"
    ],
    "wof:name":"Huangjiachong",
    "wof:placetype":"locality"
},
  "geometry": {"coordinates":[110.61351999999999,27.17153],"type":"Point"}
}