{
  "type": "Feature",
  "properties": {
    "gn:admin1_code":"19.0",
    "gn:asciiname":"Lufangsicun",
    "gn:country_code":"CN",
    "gn:dem":38,
    "gn:feature_class":"P",
    "gn:feature_code":"PPL",
    "gn:name":"L\u00fcfangsicun",
    "gn:population":0,
    "gn:timezone":"Asia/Shanghai",
    "iso:country":"CN",
    "name:und_x_variant":[
        "L\u00fcfangsicun"
    ],
    "name:zho_x_preferred":[
        "\u5415\u65b9\u5bfa\u6751"
    ],
    "wof:name":"Lufangsicun",
    "wof:placetype":"locality"
},
  "geometry": {"coordinates":[123.37376,41.4207],"type":"Point"}
}