{
  "type": "Feature",
  "properties": {
    "gn:admin1_code":"26.0",
    "gn:asciiname":"Baijiadian",
    "gn:country_code":"CN",
    "gn:dem":902,
    "gn:feature_class":"P",
    "gn:feature_code":"PPL",
    "gn:name":"Baijiadian",
    "gn:population":0,
    "gn:timezone":"Asia/Shanghai",
    "iso:country":"CN",
    "name:und_x_variant":[
        "\u767d\u5bb6\u5e97"
    ],
    "wof:name":"Baijiadian",
    "wof:placetype":"locality"
},
  "geometry": {"coordinates":[106.94468000000001,33.53139],"type":"Point"}
}