{
  "type": "Feature",
  "properties": {
    "gn:admin1_code":"10.0",
    "gn:asciiname":"Lujiazhuang",
    "gn:country_code":"CN",
    "gn:dem":18,
    "gn:feature_class":"P",
    "gn:feature_code":"PPL",
    "gn:name":"L\u00fcjiazhuang",
    "gn:population":0,
    "gn:timezone":"Asia/Shanghai",
    "iso:country":"CN",
    "name:und_x_variant":[
        "L\u00fcjiazhuang"
    ],
    "name:zho_x_preferred":[
        "\u5415\u5bb6\u5e84"
    ],
    "wof:name":"Lujiazhuang",
    "wof:placetype":"locality"
},
  "geometry": {"coordinates":[115.843,38.3224],"type":"Point"}
}