{
  "type": "Feature",
  "properties": {
    "gn:admin1_code":"11.0",
    "gn:asciiname":"Da'aoshang",
    "gn:country_code":"CN",
    "gn:dem":559,
    "gn:feature_class":"P",
    "gn:feature_code":"PPL",
    "gn:name":"Da\u2019aoshang",
    "gn:population":0,
    "gn:timezone":"Asia/Shanghai",
    "iso:country":"CN",
    "name:und_x_variant":[
        "Da\u2019aoshang"
    ],
    "name:zho_x_preferred":[
        "\u5927\u51f9\u4e0a"
    ],
    "wof:name":"Da'aoshang",
    "wof:placetype":"locality"
},
  "geometry": {"coordinates":[112.75032,25.43789],"type":"Point"}
}