{
  "type": "Feature",
  "properties": {
    "gn:admin1_code":"26.0",
    "gn:asciiname":"Wuzhuangze",
    "gn:country_code":"CN",
    "gn:dem":1130,
    "gn:feature_class":"P",
    "gn:feature_code":"PPL",
    "gn:name":"Wuzhuangze",
    "gn:population":0,
    "gn:timezone":"Asia/Shanghai",
    "iso:country":"CN",
    "name:zho_x_preferred":[
        "\u5434\u5e84\u5219"
    ],
    "wof:name":"Wuzhuangze",
    "wof:placetype":"locality"
},
  "geometry": {"coordinates":[110.82752000000001,38.86977],"type":"Point"}
}