{
  "type": "Feature",
  "properties": {
    "gn:admin1_code":"26.0",
    "gn:asciiname":"Yuzijiao",
    "gn:country_code":"CN",
    "gn:dem":1085,
    "gn:feature_class":"P",
    "gn:feature_code":"PPL",
    "gn:name":"Yuzijiao",
    "gn:population":0,
    "gn:timezone":"Asia/Shanghai",
    "iso:country":"CN",
    "name:und_x_variant":[
        "\u828b\u5b50\u7a96"
    ],
    "wof:name":"Yuzijiao",
    "wof:placetype":"locality"
},
  "geometry": {"coordinates":[107.81314999999999,34.65933],"type":"Point"}
}