{
  "type": "Feature",
  "properties": {
    "gn:admin1_code":"16.0",
    "gn:asciiname":"Basi",
    "gn:country_code":"CN",
    "gn:dem":185,
    "gn:feature_class":"P",
    "gn:feature_code":"PPL",
    "gn:name":"Basi",
    "gn:population":0,
    "gn:timezone":"Asia/Shanghai",
    "iso:country":"CN",
    "name:cat_x_preferred":[
        "Basi"
    ],
    "name:ilo_x_preferred":[
        "Basi"
    ],
    "name:ita_x_preferred":[
        "Basi"
    ],
    "name:lit_x_preferred":[
        "Basis"
    ],
    "name:spa_x_preferred":[
        "Basi"
    ],
    "name:zho_x_preferred":[
        "\u5c9c\u5bfa"
    ],
    "wof:name":"Basi",
    "wof:placetype":"locality"
},
  "geometry": {"coordinates":[107.47199999999999,22.2831],"type":"Point"}
}