{
  "type": "Feature",
  "properties": {
    "gn:admin1_code":"16",
    "gn:asciiname":"Zhuma'ao",
    "gn:country_code":"CN",
    "gn:dem":559,
    "gn:feature_class":"P",
    "gn:feature_code":"PPL",
    "gn:name":"Zhuma\u2019ao",
    "gn:population":0,
    "gn:timezone":"Asia/Shanghai",
    "iso:country":"CN",
    "name:und_x_variant":[
        "Zhuma\u2019ao"
    ],
    "name:zho_x_preferred":[
        "\u7af9\u9a6c\u5773"
    ],
    "wof:name":"Zhuma'ao",
    "wof:placetype":"locality"
},
  "geometry": {"coordinates":[110.333,25.9513],"type":"Point"}
}