{
  "type": "Feature",
  "properties": {
    "gn:admin1_code":"10",
    "gn:asciiname":"Nanqingyanggou",
    "gn:country_code":"CN",
    "gn:dem":1034,
    "gn:feature_class":"P",
    "gn:feature_code":"PPL",
    "gn:name":"Nanqingyanggou",
    "gn:population":0,
    "gn:timezone":"Asia/Shanghai",
    "iso:country":"CN",
    "name:zho_x_preferred":[
        "\u5357\u9752\u7f8a\u6c9f"
    ],
    "wof:name":"Nanqingyanggou",
    "wof:placetype":"locality"
},
  "geometry": {"coordinates":[115.77679999999999,40.85878],"type":"Point"}
}