{
  "type": "Feature",
  "properties": {
    "gn:admin1_code":"25",
    "gn:asciiname":"Qingyunshan",
    "gn:country_code":"CN",
    "gn:dem":249,
    "gn:feature_class":"P",
    "gn:feature_code":"PPL",
    "gn:name":"Qingyunshan",
    "gn:population":0,
    "gn:timezone":"Asia/Shanghai",
    "iso:country":"CN",
    "name:zho_x_preferred":[
        "\u9752\u4e91\u5c71"
    ],
    "name:zho_x_variant":[
        "\u5e86\u4e91\u5c71\u8857\u9053"
    ],
    "wof:name":"Qingyunshan",
    "wof:placetype":"locality"
},
  "geometry": {"coordinates":[117.81999999999999,35.8746],"type":"Point"}
}