{
  "type": "Feature",
  "properties": {
    "gn:admin1_code":"29.0",
    "gn:asciiname":"Sanhechang",
    "gn:country_code":"CN",
    "gn:dem":2263,
    "gn:feature_class":"P",
    "gn:feature_code":"PPL",
    "gn:name":"Sanhechang",
    "gn:population":0,
    "gn:timezone":"Asia/Shanghai",
    "iso:country":"CN",
    "name:zho_x_preferred":[
        "\u4e09\u5408\u573a"
    ],
    "wof:name":"Sanhechang",
    "wof:placetype":"locality"
},
  "geometry": {"coordinates":[103.41800000000001,27.2193],"type":"Point"}
}