{
  "type": "Feature",
  "properties": {
    "gn:admin1_code":"15.0",
    "gn:asciiname":"Shanghao Sidui",
    "gn:country_code":"CN",
    "gn:dem":1236,
    "gn:feature_class":"P",
    "gn:feature_code":"PPLF",
    "gn:name":"Shanghao Sidui",
    "gn:population":0,
    "gn:timezone":"Asia/Shanghai",
    "iso:country":"CN",
    "name:zho_x_preferred":[
        "\u4e0a\u53f7\u56db\u961f"
    ],
    "wof:name":"Shanghao Sidui",
    "wof:placetype":"locality"
},
  "geometry": {"coordinates":[98.8729,40.1652],"type":"Point"}
}