{
  "type": "Feature",
  "properties": {
    "gn:admin1_code":"2.0",
    "gn:asciiname":"Shanghailing",
    "gn:country_code":"CN",
    "gn:dem":120,
    "gn:feature_class":"P",
    "gn:feature_code":"PPL",
    "gn:name":"Shanghailing",
    "gn:population":0,
    "gn:timezone":"Asia/Shanghai",
    "iso:country":"CN",
    "name:zho_x_preferred":[
        "\u4e0a\u6d77\u5cad"
    ],
    "wof:name":"Shanghailing",
    "wof:placetype":"locality"
},
  "geometry": {"coordinates":[121.04246000000001,29.46815],"type":"Point"}
}