{
  "type": "Feature",
  "properties": {
    "gn:admin1_code":"11",
    "gn:asciiname":"Duikuantang",
    "gn:country_code":"CN",
    "gn:dem":86,
    "gn:feature_class":"P",
    "gn:feature_code":"PPL",
    "gn:name":"Duikuantang",
    "gn:population":0,
    "gn:timezone":"Asia/Shanghai",
    "iso:country":"CN",
    "name:zho_x_preferred":[
        "\u5bf9\u5bbd\u5858"
    ],
    "wof:name":"Duikuantang",
    "wof:placetype":"locality"
},
  "geometry": {"coordinates":[112.44848,26.80988],"type":"Point"}
}