{
  "type": "Feature",
  "properties": {
    "gn:admin1_code":"5.0",
    "gn:asciiname":"Chengke Wobu",
    "gn:country_code":"CN",
    "gn:dem":192,
    "gn:feature_class":"P",
    "gn:feature_code":"PPL",
    "gn:name":"Chengke Wobu",
    "gn:population":0,
    "gn:timezone":"Asia/Shanghai",
    "iso:country":"CN",
    "name:zho_x_preferred":[
        "\u7a0b\u514b\u7a9d\u5821"
    ],
    "wof:name":"Chengke Wobu",
    "wof:placetype":"locality"
},
  "geometry": {"coordinates":[125.4004,45.04362],"type":"Point"}
}