{
  "type": "Feature",
  "properties": {
    "gn:admin1_code":"1.0",
    "gn:asciiname":"Zhuangyuancun",
    "gn:country_code":"CN",
    "gn:dem":185,
    "gn:feature_class":"P",
    "gn:feature_code":"PPL",
    "gn:name":"Zhuangyuancun",
    "gn:population":0,
    "gn:timezone":"Asia/Shanghai",
    "iso:country":"CN",
    "name:und_x_variant":[
        "Zhuangyuan"
    ],
    "name:zho_x_preferred":[
        "\u5e84\u6e90\u6751"
    ],
    "wof:name":"Zhuangyuancun",
    "wof:placetype":"locality"
},
  "geometry": {"coordinates":[118.48273,29.81348],"type":"Point"}
}