{
  "type": "Feature",
  "properties": {
    "gn:admin1_code":"24",
    "gn:asciiname":"Zhuangpo",
    "gn:country_code":"CN",
    "gn:dem":1233,
    "gn:feature_class":"P",
    "gn:feature_code":"PPL",
    "gn:name":"Zhuangpo",
    "gn:population":0,
    "gn:timezone":"Asia/Shanghai",
    "iso:country":"CN",
    "wof:name":"Zhuangpo",
    "wof:placetype":"locality"
},
  "geometry": {"coordinates":[112.65167,35.94806],"type":"Point"}
}