{
  "type": "Feature",
  "properties": {
    "gn:admin1_code":"32.0",
    "gn:asciiname":"Majing",
    "gn:country_code":"CN",
    "gn:dem":523,
    "gn:feature_class":"P",
    "gn:feature_code":"PPL",
    "gn:name":"Majing",
    "gn:population":0,
    "gn:timezone":"Asia/Shanghai",
    "iso:country":"CN",
    "name:zho_x_preferred":[
        "\u9a6c\u4e95"
    ],
    "wof:name":"Majing",
    "wof:placetype":"locality"
},
  "geometry": {"coordinates":[104.11906999999999,31.06001],"type":"Point"}
}