{
  "type": "Feature",
  "properties": {
    "gn:admin1_code":"19.0",
    "gn:asciiname":"Zhongxiangtun",
    "gn:country_code":"CN",
    "gn:dem":311,
    "gn:feature_class":"P",
    "gn:feature_code":"PPL",
    "gn:name":"Zhongxiangtun",
    "gn:population":0,
    "gn:timezone":"Asia/Shanghai",
    "iso:country":"CN",
    "name:und_x_variant":[
        "\u4e2d\u7965\u5c6f"
    ],
    "name:zho_x_preferred":[
        "\u4e2d\u7965\u5c6f"
    ],
    "wof:name":"Zhongxiangtun",
    "wof:placetype":"locality"
},
  "geometry": {"coordinates":[124.929,42.7193],"type":"Point"}
}