{
  "type": "Feature",
  "properties": {
    "gn:admin1_code":"29.0",
    "gn:asciiname":"Lubenkang",
    "gn:country_code":"CN",
    "gn:dem":2232,
    "gn:feature_class":"P",
    "gn:feature_code":"PPL",
    "gn:name":"Lubenkang",
    "gn:population":0,
    "gn:timezone":"Asia/Shanghai",
    "iso:country":"CN",
    "name:zho_x_preferred":[
        "\u8def\u672c\u6297"
    ],
    "wof:name":"Lubenkang",
    "wof:placetype":"locality"
},
  "geometry": {"coordinates":[98.91840000000001,26.4507],"type":"Point"}
}