{
  "type": "Feature",
  "properties": {
    "gn:admin1_code":"29.0",
    "gn:asciiname":"Lagegong",
    "gn:country_code":"CN",
    "gn:dem":1393,
    "gn:feature_class":"P",
    "gn:feature_code":"PPL",
    "gn:name":"Lagegong",
    "gn:population":0,
    "gn:timezone":"Asia/Shanghai",
    "iso:country":"CN",
    "name:zho_x_preferred":[
        "\u62c9\u683c\u62f1"
    ],
    "wof:name":"Lagegong",
    "wof:placetype":"locality"
},
  "geometry": {"coordinates":[97.78400000000001,24.6566],"type":"Point"}
}