{
  "type": "Feature",
  "properties": {
    "gn:admin1_code":"19.0",
    "gn:asciiname":"Houyaobu",
    "gn:country_code":"CN",
    "gn:dem":69,
    "gn:feature_class":"P",
    "gn:feature_code":"PPL",
    "gn:name":"Houyaobu",
    "gn:population":0,
    "gn:timezone":"Asia/Shanghai",
    "iso:country":"CN",
    "name:zho_x_preferred":[
        "\u540e\u8170\u5821"
    ],
    "wof:name":"Houyaobu",
    "wof:placetype":"locality"
},
  "geometry": {"coordinates":[123.679,42.4211],"type":"Point"}
}