{
  "type": "Feature",
  "properties": {
    "gn:admin1_code":"1.0",
    "gn:asciiname":"Xintiancun",
    "gn:country_code":"CN",
    "gn:dem":92,
    "gn:feature_class":"P",
    "gn:feature_code":"PPL",
    "gn:name":"Xintiancun",
    "gn:population":0,
    "gn:timezone":"Asia/Shanghai",
    "iso:country":"CN",
    "name:zho_x_preferred":[
        "\u65b0\u7530\u6751"
    ],
    "wof:name":"Xintiancun",
    "wof:placetype":"locality"
},
  "geometry": {"coordinates":[118.77869,30.75311],"type":"Point"}
}