{
  "type": "Feature",
  "properties": {
    "gn:admin1_code":"32.0",
    "gn:asciiname":"Wangjia",
    "gn:country_code":"CN",
    "gn:dem":1256,
    "gn:feature_class":"P",
    "gn:feature_code":"PPLA4",
    "gn:name":"Wangjia",
    "gn:population":0,
    "gn:timezone":"Asia/Shanghai",
    "iso:country":"CN",
    "name:und_x_variant":[
        "Wangjia Xiang",
        "\u6c6a\u5bb6\u4e61"
    ],
    "name:zho_x_preferred":[
        "\u6c6a\u5bb6"
    ],
    "wof:name":"Wangjia",
    "wof:placetype":"locality"
},
  "geometry": {"coordinates":[106.15694000000001,32.52508],"type":"Point"}
}