{
  "type": "Feature",
  "properties": {
    "gn:admin1_code":"4.0",
    "gn:asciiname":"Xinzao Sanzu",
    "gn:country_code":"CN",
    "gn:dem":5,
    "gn:feature_class":"P",
    "gn:feature_code":"PPLF",
    "gn:name":"Xinzao Sanzu",
    "gn:population":0,
    "gn:timezone":"Asia/Shanghai",
    "iso:country":"CN",
    "name:und_x_variant":[
        "\u65b0\u7076\u4e09\u7ec4"
    ],
    "name:zho_x_preferred":[
        "\u65b0\u7076\u4e09\u7ec4"
    ],
    "wof:name":"Xinzao Sanzu",
    "wof:placetype":"locality"
},
  "geometry": {"coordinates":[120.47613,32.93935],"type":"Point"}
}