{
  "type": "Feature",
  "properties": {
    "gn:admin1_code":"18",
    "gn:asciiname":"Shuangkeng",
    "gn:country_code":"CN",
    "gn:dem":1414,
    "gn:feature_class":"P",
    "gn:feature_code":"PPL",
    "gn:name":"Shuangkeng",
    "gn:population":0,
    "gn:timezone":"Asia/Shanghai",
    "iso:country":"CN",
    "name:zho_x_preferred":[
        "\u53cc\u5751"
    ],
    "wof:name":"Shuangkeng",
    "wof:placetype":"locality"
},
  "geometry": {"coordinates":[105.833,26.346],"type":"Point"}
}