{
  "type": "Feature",
  "properties": {
    "gn:admin1_code":"3",
    "gn:asciiname":"Shigangshang",
    "gn:country_code":"CN",
    "gn:dem":30,
    "gn:feature_class":"P",
    "gn:feature_code":"PPL",
    "gn:name":"Shigangshang",
    "gn:population":0,
    "gn:timezone":"Asia/Shanghai",
    "iso:country":"CN",
    "name:und_x_variant":[
        "\u77f3\u5c97\u4e0a"
    ],
    "wof:name":"Shigangshang",
    "wof:placetype":"locality"
},
  "geometry": {"coordinates":[115.46144,27.97892],"type":"Point"}
}