{
  "type": "Feature",
  "properties": {
    "gn:admin1_code":"3.0",
    "gn:asciiname":"Fengjia",
    "gn:country_code":"CN",
    "gn:dem":27,
    "gn:feature_class":"P",
    "gn:feature_code":"PPL",
    "gn:name":"Fengjia",
    "gn:population":0,
    "gn:timezone":"Asia/Shanghai",
    "iso:country":"CN",
    "name:und_x_variant":[
        "\u51af\u5bb6"
    ],
    "wof:name":"Fengjia",
    "wof:placetype":"locality"
},
  "geometry": {"coordinates":[116.05831000000001,29.69033],"type":"Point"}
}