{
  "type": "Feature",
  "properties": {
    "gn:admin1_code":"10.0",
    "gn:asciiname":"Liaodaobei",
    "gn:country_code":"CN",
    "gn:dem":1757,
    "gn:feature_class":"P",
    "gn:feature_code":"PPL",
    "gn:name":"Liaodaobei",
    "gn:population":0,
    "gn:timezone":"Asia/Shanghai",
    "iso:country":"CN",
    "name:zho_x_preferred":[
        "\u8fbd\u9053\u80cc"
    ],
    "wof:name":"Liaodaobei",
    "wof:placetype":"locality"
},
  "geometry": {"coordinates":[113.82445,38.84669],"type":"Point"}
}