{
  "type": "Feature",
  "properties": {
    "gn:admin1_code":"30.0",
    "gn:asciiname":"Qingyangcun",
    "gn:country_code":"CN",
    "gn:dem":17,
    "gn:feature_class":"P",
    "gn:feature_code":"PPL",
    "gn:name":"Qingyangcun",
    "gn:population":0,
    "gn:timezone":"Asia/Shanghai",
    "iso:country":"CN",
    "name:zho_x_preferred":[
        "\u9752\u6d0b\u6751"
    ],
    "wof:name":"Qingyangcun",
    "wof:placetype":"locality"
},
  "geometry": {"coordinates":[116.28697,23.3641],"type":"Point"}
}