{
  "type": "Feature",
  "properties": {
    "gn:admin1_code":"29.0",
    "gn:asciiname":"Heimatang",
    "gn:country_code":"CN",
    "gn:dem":2132,
    "gn:feature_class":"P",
    "gn:feature_code":"PPL",
    "gn:name":"Heimatang",
    "gn:population":0,
    "gn:timezone":"Asia/Shanghai",
    "iso:country":"CN",
    "name:zho_x_preferred":[
        "\u9ed1\u9a6c\u5858"
    ],
    "wof:name":"Heimatang",
    "wof:placetype":"locality"
},
  "geometry": {"coordinates":[99.0608,23.7064],"type":"Point"}
}