{
  "type": "Feature",
  "properties": {
    "gn:admin1_code":"11.0",
    "gn:asciiname":"Luchangli",
    "gn:country_code":"CN",
    "gn:dem":500,
    "gn:feature_class":"P",
    "gn:feature_code":"PPL",
    "gn:name":"Luchangli",
    "gn:population":0,
    "gn:timezone":"Asia/Shanghai",
    "iso:country":"CN",
    "name:zho_x_preferred":[
        "\u7089\u5382\u91cc"
    ],
    "wof:name":"Luchangli",
    "wof:placetype":"locality"
},
  "geometry": {"coordinates":[110.23618,26.60334000000001],"type":"Point"}
}