{
  "type": "Feature",
  "properties": {
    "gn:admin1_code":"2.0",
    "gn:asciiname":"Niutouling",
    "gn:country_code":"CN",
    "gn:dem":292,
    "gn:feature_class":"P",
    "gn:feature_code":"PPL",
    "gn:name":"Niutouling",
    "gn:population":0,
    "gn:timezone":"Asia/Shanghai",
    "iso:country":"CN",
    "name:zho_x_preferred":[
        "\u725b\u5934\u5cad"
    ],
    "wof:name":"Niutouling",
    "wof:placetype":"locality"
},
  "geometry": {"coordinates":[120.04770000000001,29.93761],"type":"Point"}
}