{
  "type": "Feature",
  "properties": {
    "gn:admin1_code":"32.0",
    "gn:asciiname":"Haihansi",
    "gn:country_code":"CN",
    "gn:dem":324,
    "gn:feature_class":"P",
    "gn:feature_code":"PPL",
    "gn:name":"Haihansi",
    "gn:population":0,
    "gn:timezone":"Asia/Shanghai",
    "iso:country":"CN",
    "name:zho_x_preferred":[
        "\u6d77\u6db5\u5bfa"
    ],
    "wof:name":"Haihansi",
    "wof:placetype":"locality"
},
  "geometry": {"coordinates":[105.94731000000002,28.75727],"type":"Point"}
}