{
  "type": "Feature",
  "properties": {
    "gn:admin1_code":"21.0",
    "gn:asciiname":"Hongbeicun",
    "gn:country_code":"CN",
    "gn:dem":1105,
    "gn:feature_class":"P",
    "gn:feature_code":"PPL",
    "gn:name":"Hongbeicun",
    "gn:population":0,
    "gn:timezone":"Asia/Shanghai",
    "iso:country":"CN",
    "name:zho_x_preferred":[
        "\u6d2a\u5317\u6751"
    ],
    "wof:name":"Hongbeicun",
    "wof:placetype":"locality"
},
  "geometry": {"coordinates":[106.277,38.772],"type":"Point"}
}