{
  "type": "Feature",
  "properties": {
    "gn:admin1_code":"14.0",
    "gn:asciiname":"Dabacun",
    "gn:country_code":"CN",
    "gn:dem":4180,
    "gn:feature_class":"P",
    "gn:feature_code":"PPL",
    "gn:name":"Dabacun",
    "gn:population":0,
    "gn:timezone":"Asia/Shanghai",
    "iso:country":"CN",
    "name:zho_x_preferred":[
        "\u8fbe\u5df4\u6751"
    ],
    "wof:name":"Dabacun",
    "wof:placetype":"locality"
},
  "geometry": {"coordinates":[79.92399999999998,31.2283],"type":"Point"}
}