{
  "type": "Feature",
  "properties": {
    "gn:admin1_code":"32.0",
    "gn:asciiname":"Kejiaba",
    "gn:country_code":"CN",
    "gn:dem":1343,
    "gn:feature_class":"P",
    "gn:feature_code":"PPL",
    "gn:name":"Kejiaba",
    "gn:population":0,
    "gn:timezone":"Asia/Shanghai",
    "iso:country":"CN",
    "name:und_x_variant":[
        "\u67ef\u5bb6\u575d"
    ],
    "wof:name":"Kejiaba",
    "wof:placetype":"locality"
},
  "geometry": {"coordinates":[106.5621,32.50731],"type":"Point"}
}