{
  "type": "Feature",
  "properties": {
    "gn:admin1_code":"11.0",
    "gn:asciiname":"Wuguibei",
    "gn:country_code":"CN",
    "gn:dem":137,
    "gn:feature_class":"P",
    "gn:feature_code":"PPL",
    "gn:name":"Wuguibei",
    "gn:population":0,
    "gn:timezone":"Asia/Shanghai",
    "iso:country":"CN",
    "name:zho_x_preferred":[
        "\u4e4c\u9f9f\u80cc"
    ],
    "wof:name":"Wuguibei",
    "wof:placetype":"locality"
},
  "geometry": {"coordinates":[110.43644999999999,28.45037],"type":"Point"}
}