{
  "type": "Feature",
  "properties": {
    "gn:admin1_code":"32.0",
    "gn:asciiname":"Yunhe",
    "gn:country_code":"CN",
    "gn:dem":400,
    "gn:feature_class":"P",
    "gn:feature_code":"PPL",
    "gn:name":"Yunhe",
    "gn:population":0,
    "gn:timezone":"Asia/Shanghai",
    "iso:country":"CN",
    "name:ceb_x_preferred":[
        "Yunhe"
    ],
    "name:deu_x_preferred":[
        "Yunhe"
    ],
    "name:fra_x_preferred":[
        "Yunhe"
    ],
    "name:nor_x_preferred":[
        "Yunhe"
    ],
    "name:swe_x_preferred":[
        "Yunhe"
    ],
    "name:und_x_variant":[
        "Y\u00fcn-lung",
        "Yunlong",
        "Yunhe"
    ],
    "name:zho_x_preferred":[
        "\u4e91\u5408"
    ],
    "wof:name":"Yunhe",
    "wof:placetype":"locality"
},
  "geometry": {"coordinates":[104.75511,30.5121],"type":"Point"}
}