{
  "type": "Feature",
  "properties": {
    "gn:admin1_code":"14.0",
    "gn:asciiname":"Nieru",
    "gn:country_code":"CN",
    "gn:dem":4486,
    "gn:feature_class":"P",
    "gn:feature_code":"PPLA4",
    "gn:name":"Nieru",
    "gn:population":0,
    "gn:timezone":"Asia/Urumqi",
    "iso:country":"CN",
    "name:bod_x_preferred":[
        "Ny\u00earu"
    ],
    "name:ceb_x_preferred":[
        "Nierudui"
    ],
    "name:msa_x_preferred":[
        "Ny\u00earu"
    ],
    "name:swe_x_preferred":[
        "Nierudui"
    ],
    "name:und_x_variant":[
        "Ny\u00earu",
        "Nieru Xiang"
    ],
    "name:zho_x_preferred":[
        "Nieru"
    ],
    "name:zho_x_variant":[
        "\u6d85\u5982",
        "Nailong",
        "\u4e43\u9686",
        "\u6d85\u5982\u4e61",
        "\u6d85\u5982\u5806\u4e61"
    ],
    "wof:name":"Nieru",
    "wof:placetype":"locality"
},
  "geometry": {"coordinates":[89.85041,28.52517000000001],"type":"Point"}
}