{
  "type": "Feature",
  "properties": {
    "gn:admin1_code":"8.0",
    "gn:asciiname":"Yuwentaotun",
    "gn:country_code":"CN",
    "gn:dem":226,
    "gn:feature_class":"P",
    "gn:feature_code":"PPL",
    "gn:name":"Yuwentaotun",
    "gn:population":0,
    "gn:timezone":"Asia/Shanghai",
    "iso:country":"CN",
    "name:zho_x_preferred":[
        "\u4e8e\u6587\u6d9b\u5c6f"
    ],
    "wof:name":"Yuwentaotun",
    "wof:placetype":"locality"
},
  "geometry": {"coordinates":[124.24829,48.48551],"type":"Point"}
}