{
  "type": "Feature",
  "properties": {
    "gn:admin1_code":"4.0",
    "gn:asciiname":"Dajiegou",
    "gn:country_code":"CN",
    "gn:dem":8,
    "gn:feature_class":"P",
    "gn:feature_code":"PPL",
    "gn:name":"Dajiegou",
    "gn:population":0,
    "gn:timezone":"Asia/Shanghai",
    "iso:country":"CN",
    "name:zho_x_preferred":[
        "\u5927\u754c\u6c9f"
    ],
    "wof:name":"Dajiegou",
    "wof:placetype":"locality"
},
  "geometry": {"coordinates":[119.75548999999999,31.87231],"type":"Point"}
}