{
  "type": "Feature",
  "properties": {
    "gn:admin1_code":"18",
    "gn:asciiname":"Dabanshan",
    "gn:country_code":"CN",
    "gn:dem":1753,
    "gn:feature_class":"P",
    "gn:feature_code":"PPL",
    "gn:name":"Dabanshan",
    "gn:population":0,
    "gn:timezone":"Asia/Shanghai",
    "iso:country":"CN",
    "name:zho_x_preferred":[
        "\u5927\u534a\u5c71"
    ],
    "wof:name":"Dabanshan",
    "wof:placetype":"locality"
},
  "geometry": {"coordinates":[104.483,25.9635],"type":"Point"}
}