{
  "type": "Feature",
  "properties": {
    "gn:admin1_code":"15.0",
    "gn:asciiname":"Saiding",
    "gn:country_code":"CN",
    "gn:dem":2955,
    "gn:feature_class":"P",
    "gn:feature_code":"PPL",
    "gn:name":"Saiding",
    "gn:population":0,
    "gn:timezone":"Asia/Shanghai",
    "iso:country":"CN",
    "name:zho_x_preferred":[
        "\u8d5b\u9f0e"
    ],
    "wof:name":"Saiding",
    "wof:placetype":"locality"
},
  "geometry": {"coordinates":[99.8231,38.8075],"type":"Point"}
}