{
  "type": "Feature",
  "properties": {
    "gn:admin1_code":"16.0",
    "gn:asciiname":"Qicun",
    "gn:country_code":"CN",
    "gn:dem":541,
    "gn:feature_class":"P",
    "gn:feature_code":"PPL",
    "gn:name":"Qicun",
    "gn:population":0,
    "gn:timezone":"Asia/Shanghai",
    "iso:country":"CN",
    "name:zho_x_preferred":[
        "\u5447\u6751"
    ],
    "wof:name":"Qicun",
    "wof:placetype":"locality"
},
  "geometry": {"coordinates":[107.33199999999999,25.1435],"type":"Point"}
}