{
  "type": "Feature",
  "properties": {
    "gn:admin1_code":"30.0",
    "gn:asciiname":"Laijiashan",
    "gn:country_code":"CN",
    "gn:dem":811,
    "gn:feature_class":"P",
    "gn:feature_code":"PPL",
    "gn:name":"Laijiashan",
    "gn:population":0,
    "gn:timezone":"Asia/Shanghai",
    "iso:country":"CN",
    "name:zho_x_preferred":[
        "\u8d56\u5bb6\u5c71"
    ],
    "wof:name":"Laijiashan",
    "wof:placetype":"locality"
},
  "geometry": {"coordinates":[113.26582999999999,24.42611],"type":"Point"}
}