{
  "type": "Feature",
  "properties": {
    "gn:admin1_code":"2.0",
    "gn:asciiname":"Xiang'ao",
    "gn:country_code":"CN",
    "gn:dem":12,
    "gn:feature_class":"P",
    "gn:feature_code":"PPL",
    "gn:name":"Xiang\u2019ao",
    "gn:population":0,
    "gn:timezone":"Asia/Shanghai",
    "iso:country":"CN",
    "name:und_x_variant":[
        "Xiang\u2019ao"
    ],
    "name:zho_x_preferred":[
        "\u76f8\u5c99"
    ],
    "wof:name":"Xiang'ao",
    "wof:placetype":"locality"
},
  "geometry": {"coordinates":[121.3978,30.03892],"type":"Point"}
}