{
  "type": "Feature",
  "properties": {
    "gn:admin1_code":"26.0",
    "gn:asciiname":"Laobuzicun",
    "gn:country_code":"CN",
    "gn:dem":414,
    "gn:feature_class":"P",
    "gn:feature_code":"PPL",
    "gn:name":"Laobuzicun",
    "gn:population":0,
    "gn:timezone":"Asia/Shanghai",
    "iso:country":"CN",
    "name:und_x_variant":[
        "Laobuzi"
    ],
    "name:zho_x_preferred":[
        "\u8001\u5821\u5b50\u6751"
    ],
    "name:zho_x_variant":[
        "\u8001\u5821\u5b50"
    ],
    "wof:name":"Laobuzicun",
    "wof:placetype":"locality"
},
  "geometry": {"coordinates":[108.39493,34.1765],"type":"Point"}
}