{
  "type": "Feature",
  "properties": {
    "gn:admin1_code":"11.0",
    "gn:asciiname":"Suoyitian",
    "gn:country_code":"CN",
    "gn:dem":486,
    "gn:feature_class":"P",
    "gn:feature_code":"PPL",
    "gn:name":"Suoyitian",
    "gn:population":0,
    "gn:timezone":"Asia/Shanghai",
    "iso:country":"CN",
    "name:zho_x_preferred":[
        "\u84d1\u8863\u7530"
    ],
    "wof:name":"Suoyitian",
    "wof:placetype":"locality"
},
  "geometry": {"coordinates":[112.06622,28.37119],"type":"Point"}
}