{
  "type": "Feature",
  "properties": {
    "gn:admin1_code":"25",
    "gn:asciiname":"Liangshuizhen",
    "gn:cc2":"CN",
    "gn:country_code":"CN",
    "gn:dem":33,
    "gn:feature_class":"P",
    "gn:feature_code":"PPL",
    "gn:name":"Liangshuizhen",
    "gn:population":0,
    "gn:timezone":"Asia/Shanghai",
    "iso:country":"CN",
    "name:und_x_variant":[
        "Liang-shui-chen",
        "Liangshuizhen"
    ],
    "wof:name":"Liangshuizhen",
    "wof:placetype":"locality"
},
  "geometry": {"coordinates":[115.88833,36.57611],"type":"Point"}
}