{
  "type": "Feature",
  "properties": {
    "gn:admin1_code":"18.0",
    "gn:asciiname":"Guankou",
    "gn:country_code":"CN",
    "gn:dem":863,
    "gn:feature_class":"P",
    "gn:feature_code":"PPL",
    "gn:name":"Guankou",
    "gn:population":0,
    "gn:timezone":"Asia/Shanghai",
    "iso:country":"CN",
    "wof:name":"Guankou",
    "wof:placetype":"locality"
},
  "geometry": {"coordinates":[107.88889,28.01556],"type":"Point"}
}