{
  "type": "Feature",
  "properties": {
    "gn:admin1_code":"32.0",
    "gn:asciiname":"Zhangjia Huafangzi",
    "gn:country_code":"CN",
    "gn:dem":443,
    "gn:feature_class":"P",
    "gn:feature_code":"PPL",
    "gn:name":"Zhangjia Huafangzi",
    "gn:population":0,
    "gn:timezone":"Asia/Shanghai",
    "iso:country":"CN",
    "name:zho_x_preferred":[
        "\u5f20\u5bb6\u82b1\u623f\u5b50"
    ],
    "wof:name":"Zhangjia Huafangzi",
    "wof:placetype":"locality"
},
  "geometry": {"coordinates":[105.0819,30.18695],"type":"Point"}
}