{
  "type": "Feature",
  "properties": {
    "gn:admin1_code":"2.0",
    "gn:asciiname":"Wuyingwu",
    "gn:country_code":"CN",
    "gn:dem":251,
    "gn:feature_class":"P",
    "gn:feature_code":"PPL",
    "gn:name":"Wuyingwu",
    "gn:population":0,
    "gn:timezone":"Asia/Shanghai",
    "iso:country":"CN",
    "name:zho_x_preferred":[
        "\u4e4c\u9e70\u575e"
    ],
    "wof:name":"Wuyingwu",
    "wof:placetype":"locality"
},
  "geometry": {"coordinates":[118.36481999999999,28.9335],"type":"Point"}
}