{
  "type": "Feature",
  "properties": {
    "gn:admin1_code":"2",
    "gn:asciiname":"Tangbian",
    "gn:country_code":"CN",
    "gn:dem":120,
    "gn:feature_class":"P",
    "gn:feature_code":"PPL",
    "gn:name":"Tangbian",
    "gn:population":0,
    "gn:timezone":"Asia/Shanghai",
    "iso:country":"CN",
    "name:und_x_variant":[
        "\u5858\u8fb9"
    ],
    "wof:name":"Tangbian",
    "wof:placetype":"locality"
},
  "geometry": {"coordinates":[119.07389000000001,29.77083],"type":"Point"}
}