{
  "type": "Feature",
  "properties": {
    "gn:admin1_code":"26.0",
    "gn:asciiname":"Jiangjiapan",
    "gn:country_code":"CN",
    "gn:dem":1420,
    "gn:feature_class":"P",
    "gn:feature_code":"PPL",
    "gn:name":"Jiangjiapan",
    "gn:population":0,
    "gn:timezone":"Asia/Shanghai",
    "iso:country":"CN",
    "name:zho_x_preferred":[
        "\u848b\u5bb6\u7554"
    ],
    "wof:name":"Jiangjiapan",
    "wof:placetype":"locality"
},
  "geometry": {"coordinates":[108.87457000000001,36.7454],"type":"Point"}
}