{
  "type": "Feature",
  "properties": {
    "gn:admin1_code":"20.0",
    "gn:asciiname":"Dizihao",
    "gn:country_code":"CN",
    "gn:dem":1684,
    "gn:feature_class":"P",
    "gn:feature_code":"PPL",
    "gn:name":"Dizihao",
    "gn:population":0,
    "gn:timezone":"Asia/Shanghai",
    "iso:country":"CN",
    "name:und_x_variant":[
        "\u5730\u5b57\u53f7"
    ],
    "wof:name":"Dizihao",
    "wof:placetype":"locality"
},
  "geometry": {"coordinates":[110.83152,40.92161],"type":"Point"}
}