{
  "type": "Feature",
  "properties": {
    "gn:admin1_code":"33.0",
    "gn:asciiname":"Gaipingshang",
    "gn:country_code":"CN",
    "gn:dem":768,
    "gn:feature_class":"P",
    "gn:feature_code":"PPL",
    "gn:name":"Gaipingshang",
    "gn:population":0,
    "gn:timezone":"Asia/Shanghai",
    "iso:country":"CN",
    "name:zho_x_preferred":[
        "\u76d6\u576a\u4e0a"
    ],
    "wof:name":"Gaipingshang",
    "wof:placetype":"locality"
},
  "geometry": {"coordinates":[108.67374,28.653],"type":"Point"}
}