{
  "type": "Feature",
  "properties": {
    "gn:admin1_code":"24.0",
    "gn:asciiname":"Xiaolingdi",
    "gn:country_code":"CN",
    "gn:dem":1402,
    "gn:feature_class":"P",
    "gn:feature_code":"PPL",
    "gn:name":"Xiaolingdi",
    "gn:population":0,
    "gn:timezone":"Asia/Shanghai",
    "iso:country":"CN",
    "name:zho_x_preferred":[
        "\u5c0f\u5cad\u5e95"
    ],
    "wof:name":"Xiaolingdi",
    "wof:placetype":"locality"
},
  "geometry": {"coordinates":[112.18510999999999,36.81691],"type":"Point"}
}