{
  "type": "Feature",
  "properties": {
    "gn:admin1_code":"25.0",
    "gn:asciiname":"Wangjia Huangsuo",
    "gn:country_code":"CN",
    "gn:dem":53,
    "gn:feature_class":"P",
    "gn:feature_code":"PPL",
    "gn:name":"Wangjia Huangsuo",
    "gn:population":0,
    "gn:timezone":"Asia/Shanghai",
    "iso:country":"CN",
    "name:zho_x_preferred":[
        "\u738b\u5bb6\u9ec4\u6240"
    ],
    "wof:name":"Wangjia Huangsuo",
    "wof:placetype":"locality"
},
  "geometry": {"coordinates":[119.11807,35.14098],"type":"Point"}
}