{
  "type": "Feature",
  "properties": {
    "gn:admin1_code":"30",
    "gn:asciiname":"Ancunzai",
    "gn:country_code":"CN",
    "gn:dem":25,
    "gn:feature_class":"P",
    "gn:feature_code":"PPL",
    "gn:name":"Ancunzai",
    "gn:population":0,
    "gn:timezone":"Asia/Urumqi",
    "iso:country":"CN",
    "name:zho_x_preferred":[
        "\u5cb8\u6751\u4ed4"
    ],
    "wof:name":"Ancunzai",
    "wof:placetype":"locality"
},
  "geometry": {"coordinates":[109.97346,21.41133],"type":"Point"}
}