{
  "type": "Feature",
  "properties": {
    "gn:admin1_code":"4.0",
    "gn:asciiname":"Yuanfengcun",
    "gn:country_code":"CN",
    "gn:dem":1,
    "gn:feature_class":"P",
    "gn:feature_code":"PPL",
    "gn:name":"Yuanfengcun",
    "gn:population":0,
    "gn:timezone":"Asia/Shanghai",
    "iso:country":"CN",
    "name:zho_x_preferred":[
        "\u5143\u4e30\u6751"
    ],
    "wof:name":"Yuanfengcun",
    "wof:placetype":"locality"
},
  "geometry": {"coordinates":[120.59613,33.18073],"type":"Point"}
}