{
  "type": "Feature",
  "properties": {
    "gn:admin1_code":"7.0",
    "gn:asciiname":"Zujiaocun",
    "gn:country_code":"CN",
    "gn:dem":239,
    "gn:feature_class":"P",
    "gn:feature_code":"PPL",
    "gn:name":"Zujiaocun",
    "gn:population":0,
    "gn:timezone":"Asia/Shanghai",
    "iso:country":"CN",
    "name:zho_x_preferred":[
        "\u7956\u6559\u6751"
    ],
    "wof:name":"Zujiaocun",
    "wof:placetype":"locality"
},
  "geometry": {"coordinates":[117.32262,26.7039],"type":"Point"}
}