{
  "type": "Feature",
  "properties": {
    "gn:admin1_code":"4.0",
    "gn:asciiname":"Gangnancun",
    "gn:country_code":"CN",
    "gn:dem":3,
    "gn:feature_class":"P",
    "gn:feature_code":"PPL",
    "gn:name":"Gangnancun",
    "gn:population":0,
    "gn:timezone":"Asia/Shanghai",
    "iso:country":"CN",
    "name:zho_x_preferred":[
        "\u6e2f\u5357\u6751"
    ],
    "wof:name":"Gangnancun",
    "wof:placetype":"locality"
},
  "geometry": {"coordinates":[119.40308,33.95288],"type":"Point"}
}