{
  "type": "Feature",
  "properties": {
    "gn:admin1_code":"02",
    "gn:asciiname":"Xianfuquanshan Chachang",
    "gn:country_code":"CN",
    "gn:dem":81,
    "gn:feature_class":"P",
    "gn:feature_code":"PPL",
    "gn:name":"Xianfuquanshan Chachang",
    "gn:population":0,
    "gn:timezone":"Asia/Shanghai",
    "iso:country":"CN",
    "wof:name":"Xianfuquanshan Chachang",
    "wof:placetype":"locality"
},
  "geometry": {"coordinates":[121.70028000000001,29.74056],"type":"Point"}
}