{
  "type": "Feature",
  "properties": {
    "gn:admin1_code":"32.0",
    "gn:asciiname":"Yun'an",
    "gn:country_code":"CN",
    "gn:dem":422,
    "gn:feature_class":"P",
    "gn:feature_code":"PPL",
    "gn:name":"Yun\u2019an",
    "gn:population":0,
    "gn:timezone":"Asia/Shanghai",
    "iso:country":"CN",
    "name:und_x_variant":[
        "Yun\u2019an"
    ],
    "name:zho_x_preferred":[
        "\u4e91\u5b89"
    ],
    "wof:name":"Yun'an",
    "wof:placetype":"locality"
},
  "geometry": {"coordinates":[105.651,31.4344],"type":"Point"}
}