{
  "type": "Feature",
  "properties": {
    "gn:admin1_code":"12.0",
    "gn:asciiname":"Guijiazui",
    "gn:country_code":"CN",
    "gn:dem":36,
    "gn:feature_class":"P",
    "gn:feature_code":"PPL",
    "gn:name":"Guijiazui",
    "gn:population":0,
    "gn:timezone":"Asia/Shanghai",
    "iso:country":"CN",
    "name:zho_x_preferred":[
        "\u6842\u5bb6\u5480"
    ],
    "wof:name":"Guijiazui",
    "wof:placetype":"locality"
},
  "geometry": {"coordinates":[112.10556,29.91234],"type":"Point"}
}