{
  "type": "Feature",
  "properties": {
    "gn:admin1_code":"16.0",
    "gn:asciiname":"Shetou",
    "gn:country_code":"CN",
    "gn:dem":122,
    "gn:feature_class":"P",
    "gn:feature_code":"PPL",
    "gn:name":"Shetou",
    "gn:population":0,
    "gn:timezone":"Asia/Shanghai",
    "iso:country":"CN",
    "name:hak_x_preferred":[
        "Sa-th\u00e8u-hi\u00f4ng"
    ],
    "name:ita_x_preferred":[
        "Shetou"
    ],
    "name:jpn_x_preferred":[
        "\u793e\u982d\u90f7"
    ],
    "name:kor_x_preferred":[
        "\uc11c\ud130\uc6b0\ud5a5"
    ],
    "name:pol_x_preferred":[
        "Shetou"
    ],
    "name:vie_x_preferred":[
        "X\u00e3 \u0110\u1ea7u"
    ],
    "name:zho_x_preferred":[
        "\u793e\u5934"
    ],
    "name:zho_x_variant":[
        "\u793e\u982d\u9109"
    ],
    "wof:name":"Shetou",
    "wof:placetype":"locality"
},
  "geometry": {"coordinates":[109.29000000000001,22.5357],"type":"Point"}
}