{
  "type": "Feature",
  "properties": {
    "gn:admin1_code":"30.0",
    "gn:asciiname":"Shizikou",
    "gn:country_code":"CN",
    "gn:dem":173,
    "gn:feature_class":"P",
    "gn:feature_code":"PPL",
    "gn:name":"Shizikou",
    "gn:population":0,
    "gn:timezone":"Asia/Shanghai",
    "iso:country":"CN",
    "name:zho_x_preferred":[
        "Shizikou"
    ],
    "name:zho_x_variant":[
        "\u72ee\u5b50\u53e3"
    ],
    "wof:name":"Shizikou",
    "wof:placetype":"locality"
},
  "geometry": {"coordinates":[114.72628,24.14854],"type":"Point"}
}