{
  "type": "Feature",
  "properties": {
    "gn:admin1_code":"9.0",
    "gn:asciiname":"Luyan",
    "gn:country_code":"CN",
    "gn:dem":127,
    "gn:feature_class":"P",
    "gn:feature_code":"PPL",
    "gn:name":"Luyan",
    "gn:population":0,
    "gn:timezone":"Asia/Shanghai",
    "iso:country":"CN",
    "name:zho_x_preferred":[
        "\u8def\u6cbf"
    ],
    "wof:name":"Luyan",
    "wof:placetype":"locality"
},
  "geometry": {"coordinates":[115.24742000000001,31.81318],"type":"Point"}
}