{
  "type": "Feature",
  "properties": {
    "gn:admin1_code":"13",
    "gn:asciiname":"Hairoulixiangyue Mailisi",
    "gn:country_code":"CN",
    "gn:dem":238,
    "gn:feature_class":"P",
    "gn:feature_code":"PPL",
    "gn:name":"Hairoulixiangyue Mailisi",
    "gn:population":0,
    "gn:timezone":"Asia/Urumqi",
    "iso:country":"CN",
    "name:und_x_variant":[
        "\u6d77\u8089\u529b\u4e61\u7ea6\u4e70\u91cc\u65af"
    ],
    "wof:name":"Hairoulixiangyue Mailisi",
    "wof:placetype":"locality"
},
  "geometry": {"coordinates":[88.47931,42.96485],"type":"Point"}
}