{
  "type": "Feature",
  "properties": {
    "gn:admin1_code":"3.0",
    "gn:asciiname":"Liangshanli",
    "gn:country_code":"CN",
    "gn:dem":21,
    "gn:feature_class":"P",
    "gn:feature_code":"PPL",
    "gn:name":"Liangshanli",
    "gn:population":0,
    "gn:timezone":"Asia/Shanghai",
    "iso:country":"CN",
    "name:und_x_variant":[
        "\u4e24\u5c71\u91cc"
    ],
    "wof:name":"Liangshanli",
    "wof:placetype":"locality"
},
  "geometry": {"coordinates":[115.99693000000001,28.71499],"type":"Point"}
}