{
  "type": "Feature",
  "properties": {
    "gn:admin1_code":"16.0",
    "gn:asciiname":"Zhongbu",
    "gn:country_code":"CN",
    "gn:dem":986,
    "gn:feature_class":"P",
    "gn:feature_code":"PPL",
    "gn:name":"Zhongbu",
    "gn:population":0,
    "gn:timezone":"Asia/Shanghai",
    "iso:country":"CN",
    "name:zho_x_preferred":[
        "\u4e2d\u5821"
    ],
    "wof:name":"Zhongbu",
    "wof:placetype":"locality"
},
  "geometry": {"coordinates":[107.09,25.4888],"type":"Point"}
}