{
  "type": "Feature",
  "properties": {
    "gn:admin1_code":"15.0",
    "gn:asciiname":"Zuojiazhuang",
    "gn:country_code":"CN",
    "gn:dem":1473,
    "gn:feature_class":"P",
    "gn:feature_code":"PPL",
    "gn:name":"Zuojiazhuang",
    "gn:population":0,
    "gn:timezone":"Asia/Shanghai",
    "iso:country":"CN",
    "name:zho_x_preferred":[
        "\u5de6\u5bb6\u5e84"
    ],
    "wof:name":"Zuojiazhuang",
    "wof:placetype":"locality"
},
  "geometry": {"coordinates":[100.19199999999999,39.1088],"type":"Point"}
}