{
  "type": "Feature",
  "properties": {
    "gn:admin1_code":"3.0",
    "gn:asciiname":"Lanjia",
    "gn:country_code":"CN",
    "gn:dem":557,
    "gn:feature_class":"P",
    "gn:feature_code":"PPL",
    "gn:name":"Lanjia",
    "gn:population":0,
    "gn:timezone":"Asia/Shanghai",
    "iso:country":"CN",
    "name:und_x_variant":[
        "\u5170\u5bb6"
    ],
    "wof:name":"Lanjia",
    "wof:placetype":"locality"
},
  "geometry": {"coordinates":[114.25847,28.56723],"type":"Point"}
}