{
  "type": "Feature",
  "properties": {
    "gn:admin1_code":"16.0",
    "gn:asciiname":"Jingdong",
    "gn:country_code":"CN",
    "gn:dem":404,
    "gn:feature_class":"P",
    "gn:feature_code":"PPL",
    "gn:name":"Jingdong",
    "gn:population":0,
    "gn:timezone":"Asia/Shanghai",
    "iso:country":"CN",
    "name:zho_x_preferred":[
        "\u4eac\u5cd2"
    ],
    "wof:name":"Jingdong",
    "wof:placetype":"locality"
},
  "geometry": {"coordinates":[107.98699999999999,24.6855],"type":"Point"}
}