{
  "type": "Feature",
  "properties": {
    "gn:admin1_code":"25.0",
    "gn:asciiname":"Mujituncun",
    "gn:country_code":"CN",
    "gn:dem":34,
    "gn:feature_class":"P",
    "gn:feature_code":"PPL",
    "gn:name":"Mujituncun",
    "gn:population":0,
    "gn:timezone":"Asia/Shanghai",
    "iso:country":"CN",
    "name:zho_x_preferred":[
        "\u6bcd\u9e21\u5c6f\u6751"
    ],
    "wof:name":"Mujituncun",
    "wof:placetype":"locality"
},
  "geometry": {"coordinates":[121.75227,36.98253],"type":"Point"}
}