{
  "type": "Feature",
  "properties": {
    "gn:admin1_code":"16.0",
    "gn:asciiname":"Zhugenpo",
    "gn:country_code":"CN",
    "gn:dem":86,
    "gn:feature_class":"P",
    "gn:feature_code":"PPL",
    "gn:name":"Zhugenpo",
    "gn:population":0,
    "gn:timezone":"Asia/Shanghai",
    "iso:country":"CN",
    "name:zho_x_preferred":[
        "\u7af9\u6839\u5761"
    ],
    "wof:name":"Zhugenpo",
    "wof:placetype":"locality"
},
  "geometry": {"coordinates":[110.11499999999999,21.9602],"type":"Point"}
}