{
  "type": "Feature",
  "properties": {
    "gn:admin1_code":"7",
    "gn:asciiname":"Tangkeng",
    "gn:country_code":"CN",
    "gn:dem":29,
    "gn:feature_class":"P",
    "gn:feature_code":"PPL",
    "gn:name":"Tangkeng",
    "gn:population":0,
    "gn:timezone":"Asia/Shanghai",
    "iso:country":"CN",
    "name:zho_x_preferred":[
        "\u6c64\u5751"
    ],
    "wof:name":"Tangkeng",
    "wof:placetype":"locality"
},
  "geometry": {"coordinates":[117.39095,24.45937],"type":"Point"}
}