{
  "type": "Feature",
  "properties": {
    "gn:admin1_code":"13",
    "gn:asciiname":"Mamai'er Daban",
    "gn:country_code":"CN",
    "gn:dem":2155,
    "gn:feature_class":"P",
    "gn:feature_code":"PPL",
    "gn:name":"Mamai\u2019er Daban",
    "gn:population":0,
    "gn:timezone":"Asia/Urumqi",
    "iso:country":"CN",
    "name:und_x_variant":[
        "Mamai\u2019er Daban",
        "\u9a6c\u4e70\u5c14\u8fbe\u5742"
    ],
    "wof:name":"Mamai'er Daban",
    "wof:placetype":"locality"
},
  "geometry": {"coordinates":[89.74991999999997,43.22600000000001],"type":"Point"}
}