{
  "type": "Feature",
  "properties": {
    "gn:admin1_code":"15.0",
    "gn:asciiname":"Xihonghao Sandui",
    "gn:country_code":"CN",
    "gn:dem":1455,
    "gn:feature_class":"P",
    "gn:feature_code":"PPLF",
    "gn:name":"Xihonghao Sandui",
    "gn:population":0,
    "gn:timezone":"Asia/Shanghai",
    "iso:country":"CN",
    "name:zho_x_preferred":[
        "\u897f\u7ea2\u53f7\u4e09\u961f"
    ],
    "wof:name":"Xihonghao Sandui",
    "wof:placetype":"locality"
},
  "geometry": {"coordinates":[97.07940000000001,40.338],"type":"Point"}
}