{
  "type": "Feature",
  "properties": {
    "gn:admin1_code":"1.0",
    "gn:asciiname":"Guanhuang",
    "gn:country_code":"CN",
    "gn:dem":70,
    "gn:feature_class":"P",
    "gn:feature_code":"PPL",
    "gn:name":"Guanhuang",
    "gn:population":0,
    "gn:timezone":"Asia/Shanghai",
    "iso:country":"CN",
    "name:zho_x_preferred":[
        "\u5173\u9ec4"
    ],
    "wof:name":"Guanhuang",
    "wof:placetype":"locality"
},
  "geometry": {"coordinates":[118.13048000000001,31.81937000000001],"type":"Point"}
}