{
  "type": "Feature",
  "properties": {
    "gn:admin1_code":"23.0",
    "gn:asciiname":"Caijiazhai",
    "gn:country_code":"CN",
    "gn:dem":7,
    "gn:feature_class":"P",
    "gn:feature_code":"PPL",
    "gn:name":"Caijiazhai",
    "gn:population":0,
    "gn:timezone":"Asia/Shanghai",
    "iso:country":"CN",
    "name:und_x_variant":[
        "\u8521\u5bb6\u5b85"
    ],
    "wof:name":"Caijiazhai",
    "wof:placetype":"locality"
},
  "geometry": {"coordinates":[121.51518,30.94616],"type":"Point"}
}