{
  "type": "Feature",
  "properties": {
    "gn:admin1_code":"24.0",
    "gn:asciiname":"Jiangtangcun",
    "gn:country_code":"CN",
    "gn:dem":1447,
    "gn:feature_class":"P",
    "gn:feature_code":"PPL",
    "gn:name":"Jiangtangcun",
    "gn:population":0,
    "gn:timezone":"Asia/Shanghai",
    "iso:country":"CN",
    "name:und_x_variant":[
        "\u8bb2\u5802\u6751"
    ],
    "name:zho_x_preferred":[
        "\u8bb2\u5802\u6751"
    ],
    "wof:name":"Jiangtangcun",
    "wof:placetype":"locality"
},
  "geometry": {"coordinates":[113.07431,38.98768],"type":"Point"}
}