{
  "type": "Feature",
  "properties": {
    "gn:admin1_code":"32.0",
    "gn:asciiname":"Xiadengbo",
    "gn:country_code":"CN",
    "gn:dem":3539,
    "gn:feature_class":"P",
    "gn:feature_code":"PPL",
    "gn:name":"Xiadengbo",
    "gn:population":0,
    "gn:timezone":"Asia/Shanghai",
    "iso:country":"CN",
    "name:zho_x_preferred":[
        "\u4e0b\u9093\u6ce2"
    ],
    "wof:name":"Xiadengbo",
    "wof:placetype":"locality"
},
  "geometry": {"coordinates":[99.9243,29.4792],"type":"Point"}
}