{
  "type": "Feature",
  "properties": {
    "gn:admin1_code":"30.0",
    "gn:asciiname":"Shaquzhai",
    "gn:country_code":"CN",
    "gn:dem":85,
    "gn:feature_class":"P",
    "gn:feature_code":"PPL",
    "gn:name":"Shaquzhai",
    "gn:population":0,
    "gn:timezone":"Asia/Shanghai",
    "iso:country":"CN",
    "name:zho_x_preferred":[
        "\u6c99\u5c48\u5be8"
    ],
    "wof:name":"Shaquzhai",
    "wof:placetype":"locality"
},
  "geometry": {"coordinates":[112.19785,23.71909],"type":"Point"}
}