{
  "type": "Feature",
  "properties": {
    "gn:admin1_code":"32.0",
    "gn:asciiname":"Magushiwo",
    "gn:country_code":"CN",
    "gn:dem":2987,
    "gn:feature_class":"P",
    "gn:feature_code":"PPL",
    "gn:name":"Magushiwo",
    "gn:population":0,
    "gn:timezone":"Asia/Shanghai",
    "iso:country":"CN",
    "name:zho_x_preferred":[
        "\u739b\u8c37\u77f3\u7a9d"
    ],
    "wof:name":"Magushiwo",
    "wof:placetype":"locality"
},
  "geometry": {"coordinates":[102.57899999999999,28.0825],"type":"Point"}
}