{
  "type": "Feature",
  "properties": {
    "gn:admin1_code":"24.0",
    "gn:asciiname":"Fenyangling",
    "gn:country_code":"CN",
    "gn:dem":534,
    "gn:feature_class":"P",
    "gn:feature_code":"PPL",
    "gn:name":"Fenyangling",
    "gn:population":0,
    "gn:timezone":"Asia/Shanghai",
    "iso:country":"CN",
    "name:und_x_variant":[
        "\u6c7e\u9633\u5cad"
    ],
    "wof:name":"Fenyangling",
    "wof:placetype":"locality"
},
  "geometry": {"coordinates":[111.25297999999999,35.7822],"type":"Point"}
}