{
  "type": "Feature",
  "properties": {
    "gn:admin1_code":"29.0",
    "gn:asciiname":"Xiaojujie",
    "gn:country_code":"CN",
    "gn:dem":2064,
    "gn:feature_class":"P",
    "gn:feature_code":"PPL",
    "gn:name":"Xiaojujie",
    "gn:population":0,
    "gn:timezone":"Asia/Shanghai",
    "iso:country":"CN",
    "name:zho_x_preferred":[
        "\u5c0f\u82f4\u8857"
    ],
    "wof:name":"Xiaojujie",
    "wof:placetype":"locality"
},
  "geometry": {"coordinates":[101.07599999999999,25.3698],"type":"Point"}
}