{
  "type": "Feature",
  "properties": {
    "gn:admin1_code":"10",
    "gn:asciiname":"Helugou",
    "gn:country_code":"CN",
    "gn:dem":1030,
    "gn:feature_class":"P",
    "gn:feature_code":"PPL",
    "gn:name":"Helugou",
    "gn:population":0,
    "gn:timezone":"Asia/Shanghai",
    "iso:country":"CN",
    "name:zho_x_preferred":[
        "\u6cb3\u8def\u6c9f"
    ],
    "wof:name":"Helugou",
    "wof:placetype":"locality"
},
  "geometry": {"coordinates":[115.99196000000001,41.09062],"type":"Point"}
}