{
  "type": "Feature",
  "properties": {
    "gn:admin1_code":"11",
    "gn:asciiname":"Gumuyan",
    "gn:country_code":"CN",
    "gn:dem":134,
    "gn:feature_class":"P",
    "gn:feature_code":"PPL",
    "gn:name":"Gumuyan",
    "gn:population":0,
    "gn:timezone":"Asia/Shanghai",
    "iso:country":"CN",
    "name:zho_x_preferred":[
        "\u53e4\u6728\u5830"
    ],
    "wof:name":"Gumuyan",
    "wof:placetype":"locality"
},
  "geometry": {"coordinates":[111.73014000000001,26.8184],"type":"Point"}
}