{
  "type": "Feature",
  "properties": {
    "gn:admin1_code":"32.0",
    "gn:asciiname":"Xiazhongshanzi",
    "gn:country_code":"CN",
    "gn:dem":1102,
    "gn:feature_class":"P",
    "gn:feature_code":"PPL",
    "gn:name":"Xiazhongshanzi",
    "gn:population":0,
    "gn:timezone":"Asia/Shanghai",
    "iso:country":"CN",
    "name:und_x_variant":[
        "\u4e0b\u4e2d\u5c71\u5b50"
    ],
    "wof:name":"Xiazhongshanzi",
    "wof:placetype":"locality"
},
  "geometry": {"coordinates":[106.12741,32.26854],"type":"Point"}
}