{
  "type": "Feature",
  "properties": {
    "iso:country":"CN",
    "name:eng_x_preferred":[
        "Xikou"
    ],
    "name:zho_x_preferred":[
        "\u6eaa\u53e3\u9547"
    ],
    "qs:name":"\u6eaa\u53e3\u9547",
    "qs:name_adm0":"\u4e2d\u570b",
    "qs:name_adm1":"\u6d59\u6c5f\u7701",
    "qs:photos":73,
    "qs:photos_1k":15,
    "qs:photos_9k":1,
    "qs:photos_9r":2,
    "qs:photos_all":73,
    "qs:photos_sr":2,
    "qs:placetype":"Town",
    "qs:pop_sr":"0",
    "wof:name":"Xikou",
    "wof:placetype":"locality"
},
  "geometry": {"coordinates":[121.2761,29.680819],"type":"Point"}
}