{
  "type": "Feature",
  "properties": {
    "gn:country":"CN",
    "gn:fcode":"PPL",
    "gn:population":81408,
    "iso:country":"CN",
    "name:rus_x_preferred":[
        "\u042e\u0439\u0434\u0443\u043d"
    ],
    "name:und_x_variant":[
        "Baxian"
    ],
    "qs:name":"\u6e14\u6d1e\u9547",
    "qs:name_adm0":"\u4e2d\u570b",
    "qs:name_adm1":"\u91cd\u5e86\u76f4\u8f96\u5e02",
    "qs:photos_9r":0,
    "qs:photos_sr":0,
    "qs:placetype":"Town",
    "qs:pop_sr":"8",
    "wof:name":"\u6e14\u6d1e\u9547",
    "wof:placetype":"locality",
    "wof:population":81408
},
  "geometry": {"coordinates":[106.51944,29.385],"type":"Point"}
}