{
  "type": "Feature",
  "properties": {
    "gn:admin1_code":"07",
    "gn:asciiname":"Shanghoucun",
    "gn:country_code":"CN",
    "gn:dem":1161,
    "gn:feature_class":"P",
    "gn:feature_code":"PPL",
    "gn:name":"Shanghoucun",
    "gn:population":0,
    "gn:timezone":"Asia/Shanghai",
    "iso:country":"CN",
    "name:zho_x_preferred":[
        "\u4e0a\u540e\u6751"
    ],
    "wof:name":"Shanghoucun",
    "wof:placetype":"locality"
},
  "geometry": {"coordinates":[118.62472,26.82081],"type":"Point"}
}