{
  "type": "Feature",
  "properties": {
    "gn:admin1_code":"26.0",
    "gn:asciiname":"Sanfucun",
    "gn:country_code":"CN",
    "gn:dem":485,
    "gn:feature_class":"P",
    "gn:feature_code":"PPL",
    "gn:name":"Sanfucun",
    "gn:population":0,
    "gn:timezone":"Asia/Shanghai",
    "iso:country":"CN",
    "name:zho_x_preferred":[
        "\u4e09\u5e9c\u6751"
    ],
    "wof:name":"Sanfucun",
    "wof:placetype":"locality"
},
  "geometry": {"coordinates":[109.33148,34.4505],"type":"Point"}
}