{
  "type": "Feature",
  "properties": {
    "gn:admin1_code":"7",
    "gn:asciiname":"Xuxikeng",
    "gn:country_code":"CN",
    "gn:dem":38,
    "gn:feature_class":"P",
    "gn:feature_code":"PPL",
    "gn:name":"Xuxikeng",
    "gn:population":0,
    "gn:timezone":"Asia/Shanghai",
    "iso:country":"CN",
    "name:zho_x_preferred":[
        "\u8bb8\u897f\u5751"
    ],
    "wof:name":"Xuxikeng",
    "wof:placetype":"locality"
},
  "geometry": {"coordinates":[118.49609,24.67431],"type":"Point"}
}