{
  "type": "Feature",
  "properties": {
    "gn:admin1_code":"21.0",
    "gn:asciiname":"Huabushan",
    "gn:country_code":"CN",
    "gn:dem":1214,
    "gn:feature_class":"P",
    "gn:feature_code":"PPL",
    "gn:name":"Huabushan",
    "gn:population":0,
    "gn:timezone":"Asia/Shanghai",
    "iso:country":"CN",
    "name:zho_x_preferred":[
        "\u82b1\u5e03\u5c71"
    ],
    "wof:name":"Huabushan",
    "wof:placetype":"locality"
},
  "geometry": {"coordinates":[105.944,38.2519],"type":"Point"}
}