{
  "type": "Feature",
  "properties": {
    "gn:admin1_code":"10",
    "gn:asciiname":"Boluokeng",
    "gn:country_code":"CN",
    "gn:dem":530,
    "gn:feature_class":"P",
    "gn:feature_code":"PPL",
    "gn:name":"Boluokeng",
    "gn:population":0,
    "gn:timezone":"Asia/Shanghai",
    "iso:country":"CN",
    "name:zho_x_preferred":[
        "\u6872\u6924\u5751"
    ],
    "wof:name":"Boluokeng",
    "wof:placetype":"locality"
},
  "geometry": {"coordinates":[117.62591,40.3625],"type":"Point"}
}