{
  "type": "Feature",
  "properties": {
    "gn:admin1_code":"19.0",
    "gn:asciiname":"Sandaogoucun",
    "gn:country_code":"CN",
    "gn:dem":281,
    "gn:feature_class":"P",
    "gn:feature_code":"PPL",
    "gn:name":"Sandaogoucun",
    "gn:population":0,
    "gn:timezone":"Asia/Shanghai",
    "iso:country":"CN",
    "name:zho_x_preferred":[
        "\u4e09\u9053\u6c9f\u6751"
    ],
    "wof:name":"Sandaogoucun",
    "wof:placetype":"locality"
},
  "geometry": {"coordinates":[124.57899999999999,40.6775],"type":"Point"}
}