{
  "type": "Feature",
  "properties": {
    "gn:admin1_code":"29.0",
    "gn:asciiname":"Baishahecun",
    "gn:country_code":"CN",
    "gn:dem":2318,
    "gn:feature_class":"P",
    "gn:feature_code":"PPL",
    "gn:name":"Baishahecun",
    "gn:population":0,
    "gn:timezone":"Asia/Shanghai",
    "iso:country":"CN",
    "name:zho_x_preferred":[
        "\u767d\u6c99\u6cb3\u6751"
    ],
    "wof:name":"Baishahecun",
    "wof:placetype":"locality"
},
  "geometry": {"coordinates":[101.051,25.6196],"type":"Point"}
}