{
  "type": "Feature",
  "properties": {
    "gn:admin1_code":"4.0",
    "gn:asciiname":"Qingdun",
    "gn:country_code":"CN",
    "gn:dem":6,
    "gn:feature_class":"P",
    "gn:feature_code":"PPL",
    "gn:name":"Qingdun",
    "gn:population":0,
    "gn:timezone":"Asia/Shanghai",
    "iso:country":"CN",
    "name:zho_x_preferred":[
        "Qingdun"
    ],
    "name:zho_x_variant":[
        "\u9752\u58a9"
    ],
    "wof:name":"Qingdun",
    "wof:placetype":"locality"
},
  "geometry": {"coordinates":[119.23174,33.71221],"type":"Point"}
}