{
  "type": "Feature",
  "properties": {
    "gn:admin1_code":"11",
    "gn:asciiname":"Fenshuiling",
    "gn:country_code":"CN",
    "gn:dem":655,
    "gn:feature_class":"P",
    "gn:feature_code":"PPL",
    "gn:name":"Fenshuiling",
    "gn:population":0,
    "gn:timezone":"Asia/Shanghai",
    "iso:country":"CN",
    "name:und_x_variant":[
        "\u5206\u6c34\u5cad",
        "Fenshuiling"
    ],
    "wof:name":"Fenshuiling",
    "wof:placetype":"locality"
},
  "geometry": {"coordinates":[112.05306000000002,26.0225],"type":"Point"}
}