{
  "type": "Feature",
  "properties": {
    "gn:admin1_code":"26.0",
    "gn:asciiname":"Quanpo",
    "gn:country_code":"CN",
    "gn:dem":1251,
    "gn:feature_class":"P",
    "gn:feature_code":"PPL",
    "gn:name":"Quanpo",
    "gn:population":0,
    "gn:timezone":"Asia/Shanghai",
    "iso:country":"CN",
    "name:zho_x_preferred":[
        "\u5168\u5761"
    ],
    "wof:name":"Quanpo",
    "wof:placetype":"locality"
},
  "geometry": {"coordinates":[109.77182000000001,35.5656],"type":"Point"}
}