{
  "type": "Feature",
  "properties": {
    "gn:admin1_code":"14.0",
    "gn:asciiname":"Luxiacun",
    "gn:country_code":"CN",
    "gn:dem":2953,
    "gn:feature_class":"P",
    "gn:feature_code":"PPL",
    "gn:name":"Luxiacun",
    "gn:population":0,
    "gn:timezone":"Asia/Urumqi",
    "iso:country":"CN",
    "name:zho_x_preferred":[
        "\u9c81\u590f\u6751"
    ],
    "wof:name":"Luxiacun",
    "wof:placetype":"locality"
},
  "geometry": {"coordinates":[94.64746,29.45783],"type":"Point"}
}