{
  "type": "Feature",
  "properties": {
    "gn:admin1_code":"25",
    "gn:asciiname":"Dong'anjing",
    "gn:country_code":"CN",
    "gn:dem":78,
    "gn:feature_class":"P",
    "gn:feature_code":"PPL",
    "gn:name":"Dong\u2019anjing",
    "gn:population":0,
    "gn:timezone":"Asia/Shanghai",
    "iso:country":"CN",
    "name:und_x_variant":[
        "Dong\u2019anjing"
    ],
    "name:zho_x_preferred":[
        "\u4e1c\u5b89\u9759"
    ],
    "wof:name":"Dong'anjing",
    "wof:placetype":"locality"
},
  "geometry": {"coordinates":[118.423,35.1931],"type":"Point"}
}