{
  "type": "Feature",
  "properties": {
    "gn:admin1_code":"4.0",
    "gn:asciiname":"Lingdongcun",
    "gn:country_code":"CN",
    "gn:dem":23,
    "gn:feature_class":"P",
    "gn:feature_code":"PPL",
    "gn:name":"Lingdongcun",
    "gn:population":0,
    "gn:timezone":"Asia/Shanghai",
    "iso:country":"CN",
    "name:zho_x_preferred":[
        "\u9675\u4e1c\u6751"
    ],
    "wof:name":"Lingdongcun",
    "wof:placetype":"locality"
},
  "geometry": {"coordinates":[118.328,34.0248],"type":"Point"}
}