{
  "type": "Feature",
  "properties": {
    "gn:admin1_code":"26.0",
    "gn:asciiname":"Toudaogounao",
    "gn:country_code":"CN",
    "gn:dem":1982,
    "gn:feature_class":"P",
    "gn:feature_code":"PPL",
    "gn:name":"Toudaogounao",
    "gn:population":0,
    "gn:timezone":"Asia/Shanghai",
    "iso:country":"CN",
    "name:zho_x_preferred":[
        "\u5934\u9053\u6c9f\u8111"
    ],
    "wof:name":"Toudaogounao",
    "wof:placetype":"locality"
},
  "geometry": {"coordinates":[109.23087,32.06804],"type":"Point"}
}