{
  "type": "Feature",
  "properties": {
    "gn:admin1_code":"32.0",
    "gn:asciiname":"Huangcaoliang",
    "gn:country_code":"CN",
    "gn:dem":2146,
    "gn:feature_class":"P",
    "gn:feature_code":"PPL",
    "gn:name":"Huangcaoliang",
    "gn:population":0,
    "gn:timezone":"Asia/Shanghai",
    "iso:country":"CN",
    "name:zho_x_preferred":[
        "\u9ec4\u8349\u6881"
    ],
    "wof:name":"Huangcaoliang",
    "wof:placetype":"locality"
},
  "geometry": {"coordinates":[101.935,28.5499],"type":"Point"}
}