{
  "type": "Feature",
  "properties": {
    "gn:admin1_code":"26.0",
    "gn:asciiname":"Beibaidicun",
    "gn:country_code":"CN",
    "gn:dem":737,
    "gn:feature_class":"P",
    "gn:feature_code":"PPL",
    "gn:name":"Beibaidicun",
    "gn:population":0,
    "gn:timezone":"Asia/Shanghai",
    "iso:country":"CN",
    "name:zho_x_preferred":[
        "\u5317\u767d\u5824\u6751"
    ],
    "wof:name":"Beibaidicun",
    "wof:placetype":"locality"
},
  "geometry": {"coordinates":[109.62772,35.13674],"type":"Point"}
}