{
  "type": "Feature",
  "properties": {
    "gn:admin1_code":"7",
    "gn:asciiname":"Hongcuo",
    "gn:country_code":"CN",
    "gn:dem":591,
    "gn:feature_class":"P",
    "gn:feature_code":"PPL",
    "gn:name":"Hongcuo",
    "gn:population":0,
    "gn:timezone":"Asia/Shanghai",
    "iso:country":"CN",
    "name:zho_x_preferred":[
        "\u6d2a\u539d"
    ],
    "wof:name":"Hongcuo",
    "wof:placetype":"locality"
},
  "geometry": {"coordinates":[118.79971999999999,25.73167],"type":"Point"}
}