{
  "type": "Feature",
  "properties": {
    "gn:admin1_code":"32.0",
    "gn:asciiname":"Puxing",
    "gn:country_code":"CN",
    "gn:dem":324,
    "gn:feature_class":"P",
    "gn:feature_code":"PPL",
    "gn:name":"Puxing",
    "gn:population":0,
    "gn:timezone":"Asia/Shanghai",
    "iso:country":"CN",
    "name:zho_x_preferred":[
        "\u666e\u5174"
    ],
    "wof:name":"Puxing",
    "wof:placetype":"locality"
},
  "geometry": {"coordinates":[105.12808,30.6919],"type":"Point"}
}