{
  "type": "Feature",
  "properties": {
    "gn:admin1_code":"11.0",
    "gn:asciiname":"Shuiluotian",
    "gn:country_code":"CN",
    "gn:dem":365,
    "gn:feature_class":"P",
    "gn:feature_code":"PPL",
    "gn:name":"Shuiluotian",
    "gn:population":0,
    "gn:timezone":"Asia/Shanghai",
    "iso:country":"CN",
    "name:zho_x_preferred":[
        "\u6c34\u843d\u7530"
    ],
    "wof:name":"Shuiluotian",
    "wof:placetype":"locality"
},
  "geometry": {"coordinates":[110.51600000000001,27.58592],"type":"Point"}
}