{
  "type": "Feature",
  "properties": {
    "gn:admin1_code":"29",
    "gn:asciiname":"Laochang",
    "gn:country_code":"CN",
    "gn:dem":2250,
    "gn:feature_class":"P",
    "gn:feature_code":"PPL",
    "gn:name":"Laochang",
    "gn:population":0,
    "gn:timezone":"Asia/Shanghai",
    "iso:country":"CN",
    "wof:name":"Laochang",
    "wof:placetype":"locality"
},
  "geometry": {"coordinates":[104.58333,25.23333],"type":"Point"}
}