{
  "type": "Feature",
  "properties": {
    "gn:admin1_code":"5.0",
    "gn:asciiname":"Xiweizigou",
    "gn:country_code":"CN",
    "gn:dem":212,
    "gn:feature_class":"P",
    "gn:feature_code":"PPL",
    "gn:name":"Xiweizigou",
    "gn:population":0,
    "gn:timezone":"Asia/Shanghai",
    "iso:country":"CN",
    "name:zho_x_preferred":[
        "\u897f\u82c7\u5b50\u6c9f"
    ],
    "wof:name":"Xiweizigou",
    "wof:placetype":"locality"
},
  "geometry": {"coordinates":[126.85695,44.84319],"type":"Point"}
}