{
  "type": "Feature",
  "properties": {
    "gn:admin1_code":"3.0",
    "gn:asciiname":"Jigao",
    "gn:country_code":"CN",
    "gn:dem":62,
    "gn:feature_class":"P",
    "gn:feature_code":"PPL",
    "gn:name":"Jigao",
    "gn:population":0,
    "gn:timezone":"Asia/Shanghai",
    "iso:country":"CN",
    "name:und_x_variant":[
        "\u6781\u9ad8"
    ],
    "wof:name":"Jigao",
    "wof:placetype":"locality"
},
  "geometry": {"coordinates":[117.37672000000001,29.44611],"type":"Point"}
}