{
  "type": "Feature",
  "properties": {
    "gn:admin1_code":"24.0",
    "gn:asciiname":"Pianjiacha",
    "gn:country_code":"CN",
    "gn:dem":1602,
    "gn:feature_class":"P",
    "gn:feature_code":"PPL",
    "gn:name":"Pianjiacha",
    "gn:population":0,
    "gn:timezone":"Asia/Shanghai",
    "iso:country":"CN",
    "name:zho_x_preferred":[
        "\u504f\u5bb6\u5c94"
    ],
    "wof:name":"Pianjiacha",
    "wof:placetype":"locality"
},
  "geometry": {"coordinates":[111.37444000000001,38.12257],"type":"Point"}
}