{
  "type": "Feature",
  "properties": {
    "gn:admin1_code":"1.0",
    "gn:asciiname":"Jinloucun",
    "gn:country_code":"CN",
    "gn:dem":29,
    "gn:feature_class":"P",
    "gn:feature_code":"PPL",
    "gn:name":"Jinloucun",
    "gn:population":0,
    "gn:timezone":"Asia/Shanghai",
    "iso:country":"CN",
    "name:zho_x_preferred":[
        "\u9773\u697c\u6751"
    ],
    "wof:name":"Jinloucun",
    "wof:placetype":"locality"
},
  "geometry": {"coordinates":[116.45287999999999,32.71033],"type":"Point"}
}