{
  "type": "Feature",
  "properties": {
    "gn:admin1_code":"3.0",
    "gn:asciiname":"Xinchangli",
    "gn:country_code":"CN",
    "gn:dem":564,
    "gn:feature_class":"P",
    "gn:feature_code":"PPL",
    "gn:name":"Xinchangli",
    "gn:population":0,
    "gn:timezone":"Asia/Shanghai",
    "iso:country":"CN",
    "name:zho_x_preferred":[
        "\u65b0\u5382\u91cc"
    ],
    "wof:name":"Xinchangli",
    "wof:placetype":"locality"
},
  "geometry": {"coordinates":[115.045,28.7403],"type":"Point"}
}