{
  "type": "Feature",
  "properties": {
    "gn:admin1_code":"15.0",
    "gn:asciiname":"Xiecha",
    "gn:country_code":"CN",
    "gn:dem":1572,
    "gn:feature_class":"P",
    "gn:feature_code":"PPL",
    "gn:name":"Xiecha",
    "gn:population":0,
    "gn:timezone":"Asia/Shanghai",
    "iso:country":"CN",
    "name:zho_x_preferred":[
        "\u659c\u5c94"
    ],
    "wof:name":"Xiecha",
    "wof:placetype":"locality"
},
  "geometry": {"coordinates":[106.95,35.9549],"type":"Point"}
}