{
  "type": "Feature",
  "properties": {
    "gn:admin1_code":"32.0",
    "gn:asciiname":"Yujian",
    "gn:country_code":"CN",
    "gn:dem":376,
    "gn:feature_class":"P",
    "gn:feature_code":"PPL",
    "gn:name":"Yujian",
    "gn:population":0,
    "gn:timezone":"Asia/Shanghai",
    "iso:country":"CN",
    "name:zho_x_preferred":[
        "\u6e14\u7bad"
    ],
    "wof:name":"Yujian",
    "wof:placetype":"locality"
},
  "geometry": {"coordinates":[105.40635,29.39294000000001],"type":"Point"}
}