{
  "type": "Feature",
  "properties": {
    "gn:admin1_code":"10",
    "gn:asciiname":"Mayiwa",
    "gn:country_code":"CN",
    "gn:dem":1086,
    "gn:feature_class":"P",
    "gn:feature_code":"PPL",
    "gn:name":"Mayiwa",
    "gn:population":0,
    "gn:timezone":"Asia/Shanghai",
    "iso:country":"CN",
    "name:zho_x_preferred":[
        "\u8682\u8681\u6d3c"
    ],
    "wof:name":"Mayiwa",
    "wof:placetype":"locality"
},
  "geometry": {"coordinates":[115.86047000000001,40.95048],"type":"Point"}
}