{
  "type": "Feature",
  "properties": {
    "gn:admin1_code":"26",
    "gn:asciiname":"Huangjialing",
    "gn:cc2":"CN",
    "gn:country_code":"CN",
    "gn:dem":1260,
    "gn:feature_class":"P",
    "gn:feature_code":"PPL",
    "gn:name":"Huangjialing",
    "gn:population":0,
    "gn:timezone":"Asia/Shanghai",
    "iso:country":"CN",
    "name:und_x_variant":[
        "Huang-chia-ling",
        "Huangjialing"
    ],
    "wof:name":"Huangjialing",
    "wof:placetype":"locality"
},
  "geometry": {"coordinates":[108.91667,36.25],"type":"Point"}
}