{
  "type": "Feature",
  "properties": {
    "gn:admin1_code":"32.0",
    "gn:asciiname":"Xiba",
    "gn:country_code":"CN",
    "gn:dem":3670,
    "gn:feature_class":"P",
    "gn:feature_code":"PPL",
    "gn:name":"Xiba",
    "gn:population":0,
    "gn:timezone":"Asia/Shanghai",
    "iso:country":"CN",
    "name:zho_x_preferred":[
        "\u897f\u575d"
    ],
    "wof:name":"Xiba",
    "wof:placetype":"locality"
},
  "geometry": {"coordinates":[99.46478999999999,32.05629],"type":"Point"}
}