{
  "type": "Feature",
  "properties": {
    "gn:admin1_code":"26.0",
    "gn:asciiname":"Yangxinzhuang",
    "gn:country_code":"CN",
    "gn:dem":1617,
    "gn:feature_class":"P",
    "gn:feature_code":"PPL",
    "gn:name":"Yangxinzhuang",
    "gn:population":0,
    "gn:timezone":"Asia/Shanghai",
    "iso:country":"CN",
    "name:zho_x_preferred":[
        "\u6768\u65b0\u5e84"
    ],
    "wof:name":"Yangxinzhuang",
    "wof:placetype":"locality"
},
  "geometry": {"coordinates":[107.84281,37.19332],"type":"Point"}
}