{
  "type": "Feature",
  "properties": {
    "gn:admin1_code":"20",
    "gn:asciiname":"Amgalang Muchang",
    "gn:country_code":"CN",
    "gn:dem":1200,
    "gn:feature_class":"P",
    "gn:feature_code":"PPLF",
    "gn:name":"Amgalang Muchang",
    "gn:population":0,
    "gn:timezone":"Asia/Shanghai",
    "iso:country":"CN",
    "name:und_x_variant":[
        "A-mu-ku-lang-mu-ch\u2019ang",
        "Amgalang Muchang"
    ],
    "wof:name":"Amgalang Muchang",
    "wof:placetype":"locality"
},
  "geometry": {"coordinates":[111.60028,42.33194],"type":"Point"}
}