{
  "type": "Feature",
  "properties": {
    "gn:admin1_code":"2.0",
    "gn:asciiname":"Jiaoxia",
    "gn:country_code":"CN",
    "gn:dem":277,
    "gn:feature_class":"P",
    "gn:feature_code":"PPL",
    "gn:name":"Jiaoxia",
    "gn:population":0,
    "gn:timezone":"Asia/Shanghai",
    "iso:country":"CN",
    "name:zho_x_preferred":[
        "\u7126\u4e0b"
    ],
    "wof:name":"Jiaoxia",
    "wof:placetype":"locality"
},
  "geometry": {"coordinates":[119.90472,28.22695],"type":"Point"}
}