{
  "type": "Feature",
  "properties": {
    "gn:admin1_code":"15.0",
    "gn:asciiname":"Chenwangzhuang",
    "gn:country_code":"CN",
    "gn:dem":1931,
    "gn:feature_class":"P",
    "gn:feature_code":"PPL",
    "gn:name":"Chenwangzhuang",
    "gn:population":0,
    "gn:timezone":"Asia/Shanghai",
    "iso:country":"CN",
    "name:zho_x_preferred":[
        "\u9648\u738b\u5e84"
    ],
    "wof:name":"Chenwangzhuang",
    "wof:placetype":"locality"
},
  "geometry": {"coordinates":[105.40000000000001,36.2164],"type":"Point"}
}