{
  "type": "Feature",
  "properties": {
    "gn:admin1_code":"30.0",
    "gn:asciiname":"Baoliancun",
    "gn:country_code":"CN",
    "gn:dem":10,
    "gn:feature_class":"P",
    "gn:feature_code":"PPL",
    "gn:name":"Baoliancun",
    "gn:population":0,
    "gn:timezone":"Asia/Shanghai",
    "iso:country":"CN",
    "name:zho_x_preferred":[
        "\u5b9d\u8054\u6751"
    ],
    "wof:name":"Baoliancun",
    "wof:placetype":"locality"
},
  "geometry": {"coordinates":[116.18792999999999,23.52961],"type":"Point"}
}