{
  "type": "Feature",
  "properties": {
    "gn:admin1_code":"11.0",
    "gn:asciiname":"Zhangyinchong",
    "gn:country_code":"CN",
    "gn:dem":87,
    "gn:feature_class":"P",
    "gn:feature_code":"PPL",
    "gn:name":"Zhangyinchong",
    "gn:population":0,
    "gn:timezone":"Asia/Shanghai",
    "iso:country":"CN",
    "name:zho_x_preferred":[
        "\u5f20\u5bc5\u51b2"
    ],
    "wof:name":"Zhangyinchong",
    "wof:placetype":"locality"
},
  "geometry": {"coordinates":[113.0561,28.117],"type":"Point"}
}