{
  "type": "Feature",
  "properties": {
    "gn:admin1_code":"1.0",
    "gn:asciiname":"Linnancun",
    "gn:country_code":"CN",
    "gn:dem":31,
    "gn:feature_class":"P",
    "gn:feature_code":"PPL",
    "gn:name":"Linnancun",
    "gn:population":0,
    "gn:timezone":"Asia/Shanghai",
    "iso:country":"CN",
    "name:zho_x_preferred":[
        "\u4e34\u5357\u6751"
    ],
    "wof:name":"Linnancun",
    "wof:placetype":"locality"
},
  "geometry": {"coordinates":[116.55768999999999,33.68263],"type":"Point"}
}