{
  "type": "Feature",
  "properties": {
    "gn:admin1_code":"8.0",
    "gn:asciiname":"Jinxing Badui",
    "gn:country_code":"CN",
    "gn:dem":221,
    "gn:feature_class":"P",
    "gn:feature_code":"PPLF",
    "gn:name":"Jinxing Badui",
    "gn:population":0,
    "gn:timezone":"Asia/Shanghai",
    "iso:country":"CN",
    "name:zho_x_preferred":[
        "\u91d1\u661f\u516b\u961f"
    ],
    "wof:name":"Jinxing Badui",
    "wof:placetype":"locality"
},
  "geometry": {"coordinates":[124.98493000000001,47.93838],"type":"Point"}
}