{
  "type": "Feature",
  "properties": {
    "gn:admin1_code":"1.0",
    "gn:asciiname":"Shanbeiwu",
    "gn:country_code":"CN",
    "gn:dem":187,
    "gn:feature_class":"P",
    "gn:feature_code":"PPL",
    "gn:name":"Shanbeiwu",
    "gn:population":0,
    "gn:timezone":"Asia/Shanghai",
    "iso:country":"CN",
    "name:zho_x_preferred":[
        "\u5c71\u80cc\u575e"
    ],
    "wof:name":"Shanbeiwu",
    "wof:placetype":"locality"
},
  "geometry": {"coordinates":[117.76392,29.93076],"type":"Point"}
}