{
  "type": "Feature",
  "properties": {
    "gn:admin1_code":"32.0",
    "gn:asciiname":"Aniangzhai",
    "gn:country_code":"CN",
    "gn:dem":2419,
    "gn:feature_class":"P",
    "gn:feature_code":"PPL",
    "gn:name":"Aniangzhai",
    "gn:population":0,
    "gn:timezone":"Asia/Shanghai",
    "iso:country":"CN",
    "name:zho_x_preferred":[
        "\u963f\u5a18\u5be8"
    ],
    "wof:name":"Aniangzhai",
    "wof:placetype":"locality"
},
  "geometry": {"coordinates":[102.03100000000001,30.9832],"type":"Point"}
}