{
  "type": "Feature",
  "properties": {
    "gn:admin1_code":"19",
    "gn:asciiname":"Longtouyingzi",
    "gn:country_code":"CN",
    "gn:dem":604,
    "gn:feature_class":"P",
    "gn:feature_code":"PPL",
    "gn:name":"Longtouyingzi",
    "gn:population":0,
    "gn:timezone":"Asia/Shanghai",
    "iso:country":"CN",
    "name:und_x_variant":[
        "Lung-t\u2019ou-ying-tzu",
        "Longtouyingzi"
    ],
    "name:zho_x_preferred":[
        "\u9f99\u5934\u8425\u5b50"
    ],
    "wof:name":"Longtouyingzi",
    "wof:placetype":"locality"
},
  "geometry": {"coordinates":[119.70399999999999,42.0515],"type":"Point"}
}