{
  "type": "Feature",
  "properties": {
    "gn:admin1_code":"25",
    "gn:asciiname":"Shanli Beicun",
    "gn:country_code":"CN",
    "gn:dem":116,
    "gn:feature_class":"P",
    "gn:feature_code":"PPL",
    "gn:name":"Shanli Beicun",
    "gn:population":0,
    "gn:timezone":"Asia/Shanghai",
    "iso:country":"CN",
    "name:zho_x_preferred":[
        "\u5c71\u91cc\u5317\u6751"
    ],
    "wof:name":"Shanli Beicun",
    "wof:placetype":"locality"
},
  "geometry": {"coordinates":[118.712,34.96],"type":"Point"}
}