{
  "type": "Feature",
  "properties": {
    "gn:admin1_code":"32.0",
    "gn:asciiname":"Shuiguanchang",
    "gn:country_code":"CN",
    "gn:dem":606,
    "gn:feature_class":"P",
    "gn:feature_code":"PPL",
    "gn:name":"Shuiguanchang",
    "gn:population":0,
    "gn:timezone":"Asia/Shanghai",
    "iso:country":"CN",
    "name:zho_x_preferred":[
        "\u6c34\u704c\u573a"
    ],
    "wof:name":"Shuiguanchang",
    "wof:placetype":"locality"
},
  "geometry": {"coordinates":[105.49867999999999,31.37887000000001],"type":"Point"}
}