{
  "type": "Feature",
  "properties": {
    "gn:admin1_code":"26.0",
    "gn:asciiname":"Chunhecun",
    "gn:country_code":"CN",
    "gn:dem":329,
    "gn:feature_class":"P",
    "gn:feature_code":"PPL",
    "gn:name":"Chunhecun",
    "gn:population":0,
    "gn:timezone":"Asia/Shanghai",
    "iso:country":"CN",
    "name:zho_x_preferred":[
        "\u6625\u548c\u6751"
    ],
    "wof:name":"Chunhecun",
    "wof:placetype":"locality"
},
  "geometry": {"coordinates":[110.20253,34.69444],"type":"Point"}
}