{
  "type": "Feature",
  "properties": {
    "gn:admin1_code":"11.0",
    "gn:asciiname":"Tulou",
    "gn:country_code":"CN",
    "gn:dem":104,
    "gn:feature_class":"P",
    "gn:feature_code":"PPL",
    "gn:name":"Tulou",
    "gn:population":0,
    "gn:timezone":"Asia/Shanghai",
    "iso:country":"CN",
    "name:deu_x_preferred":[
        "Tulou"
    ],
    "name:epo_x_preferred":[
        "Tulou"
    ],
    "name:fra_x_preferred":[
        "Tulou"
    ],
    "name:ita_x_preferred":[
        "Tulou"
    ],
    "name:pol_x_preferred":[
        "Tulou"
    ],
    "name:vie_x_preferred":[
        "Th\u1ed5 l\u00e2u"
    ],
    "name:zho_x_preferred":[
        "\u571f\u697c"
    ],
    "wof:name":"Tulou",
    "wof:placetype":"locality"
},
  "geometry": {"coordinates":[113.33812,27.15262],"type":"Point"}
}