{
  "type": "Feature",
  "properties": {
    "gn:admin1_code":"29",
    "gn:asciiname":"Wajiadi",
    "gn:country_code":"CN",
    "gn:dem":1806,
    "gn:feature_class":"P",
    "gn:feature_code":"PPL",
    "gn:name":"Wajiadi",
    "gn:population":0,
    "gn:timezone":"Asia/Shanghai",
    "iso:country":"CN",
    "name:zho_x_preferred":[
        "\u74e6\u5bb6\u5e95"
    ],
    "wof:name":"Wajiadi",
    "wof:placetype":"locality"
},
  "geometry": {"coordinates":[102.20650999999999,24.8331],"type":"Point"}
}