{
  "type": "Feature",
  "properties": {
    "gn:admin1_code":"16.0",
    "gn:asciiname":"Gongli",
    "gn:country_code":"CN",
    "gn:dem":442,
    "gn:feature_class":"P",
    "gn:feature_code":"PPL",
    "gn:name":"Gongli",
    "gn:population":0,
    "gn:timezone":"Asia/Shanghai",
    "iso:country":"CN",
    "name:zho_x_preferred":[
        "\u4f9b\u7acb"
    ],
    "wof:name":"Gongli",
    "wof:placetype":"locality"
},
  "geometry": {"coordinates":[106.208,24.1733],"type":"Point"}
}