{
  "type": "Feature",
  "properties": {
    "gn:admin1_code":"18",
    "gn:asciiname":"Gaoba",
    "gn:country_code":"CN",
    "gn:dem":958,
    "gn:feature_class":"P",
    "gn:feature_code":"PPL",
    "gn:name":"Gaoba",
    "gn:population":0,
    "gn:timezone":"Asia/Shanghai",
    "iso:country":"CN",
    "name:zho_x_preferred":[
        "\u9ad8\u575d"
    ],
    "wof:name":"Gaoba",
    "wof:placetype":"locality"
},
  "geometry": {"coordinates":[107.42400000000001,27.2229],"type":"Point"}
}