{
  "type": "Feature",
  "properties": {
    "gn:admin1_code":"9",
    "gn:asciiname":"Jiazhuangnan",
    "gn:country_code":"CN",
    "gn:dem":66,
    "gn:feature_class":"P",
    "gn:feature_code":"PPL",
    "gn:name":"Jiazhuangnan",
    "gn:population":0,
    "gn:timezone":"Asia/Shanghai",
    "iso:country":"CN",
    "name:zho_x_preferred":[
        "\u8d3e\u5e84\u5357"
    ],
    "wof:name":"Jiazhuangnan",
    "wof:placetype":"locality"
},
  "geometry": {"coordinates":[115.33,34.6452],"type":"Point"}
}