{
  "type": "Feature",
  "properties": {
    "gn:admin1_code":"3.0",
    "gn:asciiname":"Hejiapeng",
    "gn:country_code":"CN",
    "gn:dem":182,
    "gn:feature_class":"P",
    "gn:feature_code":"PPL",
    "gn:name":"Hejiapeng",
    "gn:population":0,
    "gn:timezone":"Asia/Shanghai",
    "iso:country":"CN",
    "name:und_x_variant":[
        "\u4f55\u5bb6\u68da"
    ],
    "wof:name":"Hejiapeng",
    "wof:placetype":"locality"
},
  "geometry": {"coordinates":[114.474,27.0399],"type":"Point"}
}