{
  "type": "Feature",
  "properties": {
    "gn:admin1_code":"8.0",
    "gn:asciiname":"Huchengtun",
    "gn:country_code":"CN",
    "gn:dem":180,
    "gn:feature_class":"P",
    "gn:feature_code":"PPL",
    "gn:name":"Huchengtun",
    "gn:population":0,
    "gn:timezone":"Asia/Shanghai",
    "iso:country":"CN",
    "name:zho_x_preferred":[
        "\u62a4\u57ce\u5c6f"
    ],
    "wof:name":"Huchengtun",
    "wof:placetype":"locality"
},
  "geometry": {"coordinates":[128.10903000000002,45.43313],"type":"Point"}
}