{
  "type": "Feature",
  "properties": {
    "gn:admin1_code":"29.0",
    "gn:asciiname":"Kelang",
    "gn:country_code":"CN",
    "gn:dem":1535,
    "gn:feature_class":"P",
    "gn:feature_code":"PPL",
    "gn:name":"Kelang",
    "gn:population":0,
    "gn:timezone":"Asia/Shanghai",
    "iso:country":"CN",
    "name:ara_x_preferred":[
        "\u0643\u064a\u0644\u0627\u0646\u063a"
    ],
    "name:ceb_x_preferred":[
        "Pulau Kelang"
    ],
    "name:zho_x_preferred":[
        "\u514b\u6717"
    ],
    "name:zho_x_variant":[
        "\u514b\u6717\u5c9b"
    ],
    "wof:name":"Kelang",
    "wof:placetype":"locality"
},
  "geometry": {"coordinates":[101.09999999999999,22.9911],"type":"Point"}
}