{
  "type": "Feature",
  "properties": {
    "gn:admin1_code":"29.0",
    "gn:asciiname":"Huigongqing",
    "gn:country_code":"CN",
    "gn:dem":1293,
    "gn:feature_class":"P",
    "gn:feature_code":"PPL",
    "gn:name":"Huigongqing",
    "gn:population":0,
    "gn:timezone":"Asia/Shanghai",
    "iso:country":"CN",
    "name:zho_x_preferred":[
        "\u7070\u5f13\u7b90"
    ],
    "wof:name":"Huigongqing",
    "wof:placetype":"locality"
},
  "geometry": {"coordinates":[101.48699999999999,26.4958],"type":"Point"}
}