{
  "type": "Feature",
  "properties": {
    "gn:admin1_code":"21.0",
    "gn:asciiname":"Xiyidou",
    "gn:country_code":"CN",
    "gn:dem":1098,
    "gn:feature_class":"P",
    "gn:feature_code":"PPL",
    "gn:name":"Xiyidou",
    "gn:population":0,
    "gn:timezone":"Asia/Shanghai",
    "iso:country":"CN",
    "name:zho_x_preferred":[
        "\u897f\u4e00\u6597"
    ],
    "wof:name":"Xiyidou",
    "wof:placetype":"locality"
},
  "geometry": {"coordinates":[106.375,38.9563],"type":"Point"}
}