{
  "type": "Feature",
  "properties": {
    "gn:admin1_code":"20.0",
    "gn:asciiname":"Daqi Wudui",
    "gn:country_code":"CN",
    "gn:dem":466,
    "gn:feature_class":"P",
    "gn:feature_code":"PPLF",
    "gn:name":"Daqi Wudui",
    "gn:population":0,
    "gn:timezone":"Asia/Shanghai",
    "iso:country":"CN",
    "name:zho_x_preferred":[
        "\u5927\u65d7\u4e94\u961f"
    ],
    "wof:name":"Daqi Wudui",
    "wof:placetype":"locality"
},
  "geometry": {"coordinates":[122.41643000000001,47.93227],"type":"Point"}
}