{
  "type": "Feature",
  "properties": {
    "gn:admin1_code":"4.0",
    "gn:asciiname":"Qiandazhuang",
    "gn:country_code":"CN",
    "gn:dem":1,
    "gn:feature_class":"P",
    "gn:feature_code":"PPL",
    "gn:name":"Qiandazhuang",
    "gn:population":0,
    "gn:timezone":"Asia/Shanghai",
    "iso:country":"CN",
    "name:zho_x_preferred":[
        "Qiandazhuang"
    ],
    "name:zho_x_variant":[
        "\u94b1\u5927\u5e84"
    ],
    "wof:name":"Qiandazhuang",
    "wof:placetype":"locality"
},
  "geometry": {"coordinates":[119.27013999999998,33.29646],"type":"Point"}
}