{
  "type": "Feature",
  "properties": {
    "gn:admin1_code":"15.0",
    "gn:asciiname":"Jingjia Zhuangzi",
    "gn:country_code":"CN",
    "gn:dem":1099,
    "gn:feature_class":"P",
    "gn:feature_code":"PPL",
    "gn:name":"Jingjia Zhuangzi",
    "gn:population":0,
    "gn:timezone":"Asia/Shanghai",
    "iso:country":"CN",
    "name:zho_x_preferred":[
        "\u666f\u5bb6\u5e84\u5b50"
    ],
    "wof:name":"Jingjia Zhuangzi",
    "wof:placetype":"locality"
},
  "geometry": {"coordinates":[107.271,35.2066],"type":"Point"}
}