{
  "type": "Feature",
  "properties": {
    "gn:admin1_code":"29.0",
    "gn:asciiname":"Tianzizhuang",
    "gn:country_code":"CN",
    "gn:dem":2161,
    "gn:feature_class":"P",
    "gn:feature_code":"PPL",
    "gn:name":"Tianzizhuang",
    "gn:population":0,
    "gn:timezone":"Asia/Shanghai",
    "iso:country":"CN",
    "name:zho_x_preferred":[
        "\u5929\u5b50\u5e84"
    ],
    "wof:name":"Tianzizhuang",
    "wof:placetype":"locality"
},
  "geometry": {"coordinates":[99.98480000000001,26.2908],"type":"Point"}
}