{
  "type": "Feature",
  "properties": {
    "gn:admin1_code":"26.0",
    "gn:asciiname":"Huaguoping",
    "gn:country_code":"CN",
    "gn:dem":967,
    "gn:feature_class":"P",
    "gn:feature_code":"PPL",
    "gn:name":"Huaguoping",
    "gn:population":0,
    "gn:timezone":"Asia/Shanghai",
    "iso:country":"CN",
    "name:zho_x_preferred":[
        "\u82b1\u679c\u576a"
    ],
    "wof:name":"Huaguoping",
    "wof:placetype":"locality"
},
  "geometry": {"coordinates":[108.96441000000002,32.96846],"type":"Point"}
}