{
  "type": "Feature",
  "properties": {
    "gn:admin1_code":"14.0",
    "gn:asciiname":"Bayigong",
    "gn:country_code":"CN",
    "gn:dem":3809,
    "gn:feature_class":"P",
    "gn:feature_code":"PPL",
    "gn:name":"Bayigong",
    "gn:population":0,
    "gn:timezone":"Asia/Urumqi",
    "iso:country":"CN",
    "name:zho_x_preferred":[
        "\u5df4\u4ee5\u5de5"
    ],
    "wof:name":"Bayigong",
    "wof:placetype":"locality"
},
  "geometry": {"coordinates":[97.79512,32.48263],"type":"Point"}
}