{
  "type": "Feature",
  "properties": {
    "gn:admin1_code":"1.0",
    "gn:asciiname":"Heyingcun",
    "gn:country_code":"CN",
    "gn:dem":28,
    "gn:feature_class":"P",
    "gn:feature_code":"PPL",
    "gn:name":"Heyingcun",
    "gn:population":0,
    "gn:timezone":"Asia/Shanghai",
    "iso:country":"CN",
    "name:zho_x_preferred":[
        "\u4f55\u90e2\u6751"
    ],
    "wof:name":"Heyingcun",
    "wof:placetype":"locality"
},
  "geometry": {"coordinates":[116.02722,32.65889],"type":"Point"}
}