{
  "type": "Feature",
  "properties": {
    "gn:admin1_code":"10.0",
    "gn:asciiname":"Wuzhuangzi Dongpai",
    "gn:country_code":"CN",
    "gn:dem":7,
    "gn:feature_class":"P",
    "gn:feature_code":"PPL",
    "gn:name":"Wuzhuangzi Dongpai",
    "gn:population":0,
    "gn:timezone":"Asia/Shanghai",
    "iso:country":"CN",
    "name:zho_x_preferred":[
        "\u5434\u5e84\u5b50\u4e1c\u6392"
    ],
    "wof:name":"Wuzhuangzi Dongpai",
    "wof:placetype":"locality"
},
  "geometry": {"coordinates":[117.122,38.4188],"type":"Point"}
}