{
  "type": "Feature",
  "properties": {
    "gn:admin1_code":"20.0",
    "gn:asciiname":"Laohua Jiatun",
    "gn:country_code":"CN",
    "gn:dem":184,
    "gn:feature_class":"P",
    "gn:feature_code":"PPL",
    "gn:name":"Laohua Jiatun",
    "gn:population":0,
    "gn:timezone":"Asia/Shanghai",
    "iso:country":"CN",
    "name:zho_x_preferred":[
        "\u8001\u534e\u5bb6\u5c6f"
    ],
    "wof:name":"Laohua Jiatun",
    "wof:placetype":"locality"
},
  "geometry": {"coordinates":[124.41356,48.3231],"type":"Point"}
}