{
  "type": "Feature",
  "properties": {
    "gn:admin1_code":"31",
    "gn:asciiname":"Xinningpo",
    "gn:country_code":"CN",
    "gn:dem":73,
    "gn:feature_class":"P",
    "gn:feature_code":"PPL",
    "gn:name":"Xinningpo",
    "gn:population":0,
    "gn:timezone":"Asia/Shanghai",
    "iso:country":"CN",
    "name:und_x_variant":[
        "\u65b0\u5b81\u5761"
    ],
    "wof:name":"Xinningpo",
    "wof:placetype":"locality"
},
  "geometry": {"coordinates":[108.836,19.1138],"type":"Point"}
}