{
  "type": "Feature",
  "properties": {
    "gn:admin1_code":"11.0",
    "gn:asciiname":"Xujia",
    "gn:country_code":"CN",
    "gn:dem":115,
    "gn:feature_class":"P",
    "gn:feature_code":"PPL",
    "gn:name":"Xujia",
    "gn:population":0,
    "gn:timezone":"Asia/Shanghai",
    "iso:country":"CN",
    "name:zho_x_preferred":[
        "\u5f90\u5bb6"
    ],
    "wof:name":"Xujia",
    "wof:placetype":"locality"
},
  "geometry": {"coordinates":[112.69817999999999,26.39875],"type":"Point"}
}