{
  "type": "Feature",
  "properties": {
    "gn:admin1_code":"11.0",
    "gn:asciiname":"Dimentian",
    "gn:country_code":"CN",
    "gn:dem":718,
    "gn:feature_class":"P",
    "gn:feature_code":"PPL",
    "gn:name":"Dimentian",
    "gn:population":0,
    "gn:timezone":"Asia/Shanghai",
    "iso:country":"CN",
    "name:zho_x_preferred":[
        "\u5730\u95e8\u7530"
    ],
    "wof:name":"Dimentian",
    "wof:placetype":"locality"
},
  "geometry": {"coordinates":[109.39766000000002,27.26159],"type":"Point"}
}