{
  "type": "Feature",
  "properties": {
    "gn:admin1_code":"4.0",
    "gn:asciiname":"Shixiaoxu",
    "gn:country_code":"CN",
    "gn:dem":4,
    "gn:feature_class":"P",
    "gn:feature_code":"PPL",
    "gn:name":"Shixiaoxu",
    "gn:population":0,
    "gn:timezone":"Asia/Shanghai",
    "iso:country":"CN",
    "name:zho_x_preferred":[
        "\u5341\u5c0f\u5729"
    ],
    "wof:name":"Shixiaoxu",
    "wof:placetype":"locality"
},
  "geometry": {"coordinates":[120.77624,32.07805],"type":"Point"}
}