{
  "type": "Feature",
  "properties": {
    "gn:admin1_code":"15.0",
    "gn:asciiname":"Lujiayuan",
    "gn:country_code":"CN",
    "gn:dem":932,
    "gn:feature_class":"P",
    "gn:feature_code":"PPL",
    "gn:name":"L\u00fcjiayuan",
    "gn:population":0,
    "gn:timezone":"Asia/Shanghai",
    "iso:country":"CN",
    "name:und_x_variant":[
        "L\u00fcjiayuan",
        "\u5415\u5bb6\u9662"
    ],
    "wof:name":"Lujiayuan",
    "wof:placetype":"locality"
},
  "geometry": {"coordinates":[105.77851,33.0384],"type":"Point"}
}