{
  "type": "Feature",
  "properties": {
    "gn:admin1_code":"5.0",
    "gn:asciiname":"Hongguangcun",
    "gn:country_code":"CN",
    "gn:dem":229,
    "gn:feature_class":"P",
    "gn:feature_code":"PPL",
    "gn:name":"Hongguangcun",
    "gn:population":0,
    "gn:timezone":"Asia/Shanghai",
    "iso:country":"CN",
    "name:zho_x_preferred":[
        "\u7ea2\u5149\u6751"
    ],
    "wof:name":"Hongguangcun",
    "wof:placetype":"locality"
},
  "geometry": {"coordinates":[126.99760000000001,44.44886],"type":"Point"}
}