{
  "type": "Feature",
  "properties": {
    "gn:admin1_code":"02",
    "gn:asciiname":"Meixiancun",
    "gn:country_code":"CN",
    "gn:dem":10,
    "gn:feature_class":"P",
    "gn:feature_code":"PPL",
    "gn:name":"Meixiancun",
    "gn:population":0,
    "gn:timezone":"Asia/Shanghai",
    "iso:country":"CN",
    "name:und_x_variant":[
        "Meixian"
    ],
    "name:zho_x_preferred":[
        "\u6885\u5c98\u6751"
    ],
    "wof:name":"Meixiancun",
    "wof:placetype":"locality"
},
  "geometry": {"coordinates":[121.28583999999999,28.75385],"type":"Point"}
}