{
  "type": "Feature",
  "properties": {
    "gn:admin1_code":"15.0",
    "gn:asciiname":"Dushanzi",
    "gn:country_code":"CN",
    "gn:dem":1880,
    "gn:feature_class":"P",
    "gn:feature_code":"PPL",
    "gn:name":"Dushanzi",
    "gn:population":0,
    "gn:timezone":"Asia/Shanghai",
    "iso:country":"CN",
    "name:zho_x_preferred":[
        "\u72ec\u5c71\u5b50"
    ],
    "wof:name":"Dushanzi",
    "wof:placetype":"locality"
},
  "geometry": {"coordinates":[104.074,36.6923],"type":"Point"}
}