{
  "type": "Feature",
  "properties": {
    "gn:admin1_code":"32.0",
    "gn:asciiname":"Lingqi",
    "gn:country_code":"CN",
    "gn:dem":771,
    "gn:feature_class":"P",
    "gn:feature_code":"PPL",
    "gn:name":"Lingqi",
    "gn:population":0,
    "gn:timezone":"Asia/Shanghai",
    "iso:country":"CN",
    "name:zho_x_preferred":[
        "\u94c3\u65d7"
    ],
    "wof:name":"Lingqi",
    "wof:placetype":"locality"
},
  "geometry": {"coordinates":[105.767,31.7319],"type":"Point"}
}