{
  "type": "Feature",
  "properties": {
    "gn:admin1_code":"14.0",
    "gn:asciiname":"Tari",
    "gn:country_code":"CN",
    "gn:dem":4969,
    "gn:feature_class":"P",
    "gn:feature_code":"PPLF",
    "gn:name":"Tari",
    "gn:population":0,
    "gn:timezone":"Asia/Urumqi",
    "iso:country":"CN",
    "name:bod_x_preferred":[
        "Tari"
    ],
    "name:zho_x_preferred":[
        "Teri"
    ],
    "name:zho_x_variant":[
        "\u7279\u65e5",
        "Quxia",
        "\u66f2\u4e0b"
    ],
    "wof:name":"Tari",
    "wof:placetype":"locality"
},
  "geometry": {"coordinates":[91.40300000000001,28.903],"type":"Point"}
}