{
  "type": "Feature",
  "properties": {
    "gn:country":"CN",
    "gn:fcode":"ADM3",
    "gn:population":0,
    "iso:country":"CN",
    "name:ceb_x_preferred":[
        "Luwan Qu"
    ],
    "name:deu_x_preferred":[
        "Luwan"
    ],
    "name:eng_x_preferred":[
        "Luwan District"
    ],
    "name:eus_x_preferred":[
        "Luwan Barrutia"
    ],
    "name:jpn_x_preferred":[
        "\u76e7\u6e7e\u533a"
    ],
    "name:kor_x_preferred":[
        "\ub8e8\uc644 \uad6c"
    ],
    "name:kor_x_variant":[
        "\ub8e8\uc644\uad6c"
    ],
    "name:nld_x_preferred":[
        "Luwan"
    ],
    "name:nob_x_preferred":[
        "Luwan"
    ],
    "name:ron_x_preferred":[
        "Districtul Luwan"
    ],
    "name:rus_x_preferred":[
        "\u041b\u0443\u0432\u0430\u043d\u044c"
    ],
    "name:spa_x_preferred":[
        "Luwan"
    ],
    "name:swe_x_preferred":[
        "Luwan"
    ],
    "name:ukr_x_preferred":[
        "\u0420\u0430\u0439\u043e\u043d \u041b\u0443\u0432\u0430\u043d\u044c"
    ],
    "name:vie_x_preferred":[
        "L\u00f4 Loan"
    ],
    "name:wuu_x_preferred":[
        "\u5362\u6e7e\u533a"
    ],
    "name:zho_x_preferred":[
        "\u5362\u6e7e\u533a"
    ],
    "qs:name":"Luwan Qu",
    "qs:photos_9r":0,
    "qs:photos_sr":0,
    "qs:pop_sr":"0",
    "wd:wordcount":310,
    "wof:name":"Luwan Qu",
    "wof:placetype":"localadmin",
    "wof:population":0
},
  "geometry": {"coordinates":[121.4623,31.20925],"type":"Point"}
}