{
  "type": "Feature",
  "properties": {
    "gn:country":"CN",
    "gn:fcode":"ADM3",
    "gn:pop":0,
    "iso:country":"CN",
    "name:unk_x_variant":[
        "Luwan District"
    ],
    "name:zho_x_preferred":[
        "\u5362\u6e7e\u533a"
    ],
    "qs:name":"Luwan Qu",
    "qs:photos_9r":0,
    "qs:photos_sr":0,
    "qs:pop_sr":"0",
    "wd:wordcount":310,
    "wof:name":"Luwan Qu",
    "wof:placetype":"localadmin",
    "wof:population":0
},
  "geometry": {"coordinates":[121.4623,31.20925],"type":"Point"}
}