{
  "type": "Feature",
  "properties": {
    "gn:admin1_code":"3.0",
    "gn:asciiname":"Xita",
    "gn:country_code":"CN",
    "gn:dem":594,
    "gn:feature_class":"P",
    "gn:feature_code":"PPL",
    "gn:name":"Xita",
    "gn:population":0,
    "gn:timezone":"Asia/Shanghai",
    "iso:country":"CN",
    "name:jpn_x_preferred":[
        "\u897f\u5854"
    ],
    "name:und_x_variant":[
        "\u897f\u5854"
    ],
    "name:zho_x_preferred":[
        "\u897f\u5854\u8857"
    ],
    "wof:name":"Xita",
    "wof:placetype":"locality"
},
  "geometry": {"coordinates":[114.75801,28.68409],"type":"Point"}
}