{
  "type": "Feature",
  "properties": {
    "gn:admin1_code":"32.0",
    "gn:asciiname":"Jiefangping",
    "gn:country_code":"CN",
    "gn:dem":2387,
    "gn:feature_class":"P",
    "gn:feature_code":"PPL",
    "gn:name":"Jiefangping",
    "gn:population":0,
    "gn:timezone":"Asia/Shanghai",
    "iso:country":"CN",
    "name:zho_x_preferred":[
        "\u89e3\u653e\u576a"
    ],
    "wof:name":"Jiefangping",
    "wof:placetype":"locality"
},
  "geometry": {"coordinates":[103.051,28.6896],"type":"Point"}
}