{
  "type": "Feature",
  "properties": {
    "gn:admin1_code":"11.0",
    "gn:asciiname":"Majia Citang",
    "gn:country_code":"CN",
    "gn:dem":93,
    "gn:feature_class":"P",
    "gn:feature_code":"PPL",
    "gn:name":"Majia Citang",
    "gn:population":0,
    "gn:timezone":"Asia/Shanghai",
    "iso:country":"CN",
    "name:zho_x_preferred":[
        "\u9a6c\u5bb6\u7960\u5802"
    ],
    "wof:name":"Majia Citang",
    "wof:placetype":"locality"
},
  "geometry": {"coordinates":[112.8826,27.56462],"type":"Point"}
}