{
  "type": "Feature",
  "properties": {
    "gn:admin1_code":"8.0",
    "gn:asciiname":"Gongyihao",
    "gn:country_code":"CN",
    "gn:dem":179,
    "gn:feature_class":"P",
    "gn:feature_code":"PPL",
    "gn:name":"Gongyihao",
    "gn:population":0,
    "gn:timezone":"Asia/Shanghai",
    "iso:country":"CN",
    "name:zho_x_preferred":[
        "\u516c\u4e49\u53f7"
    ],
    "wof:name":"Gongyihao",
    "wof:placetype":"locality"
},
  "geometry": {"coordinates":[125.7119,46.59354],"type":"Point"}
}