{
  "type": "Feature",
  "properties": {
    "gn:admin1_code":"29.0",
    "gn:asciiname":"Laoqintian",
    "gn:country_code":"CN",
    "gn:dem":1104,
    "gn:feature_class":"P",
    "gn:feature_code":"PPL",
    "gn:name":"Laoqintian",
    "gn:population":0,
    "gn:timezone":"Asia/Shanghai",
    "iso:country":"CN",
    "name:zho_x_preferred":[
        "\u8001\u52e4\u7530"
    ],
    "wof:name":"Laoqintian",
    "wof:placetype":"locality"
},
  "geometry": {"coordinates":[101.33799999999999,23.2299],"type":"Point"}
}