{
  "type": "Feature",
  "properties": {
    "gn:admin1_code":"29",
    "gn:asciiname":"Keguan",
    "gn:country_code":"CN",
    "gn:dem":1652,
    "gn:feature_class":"P",
    "gn:feature_code":"PPL",
    "gn:name":"Keguan",
    "gn:population":0,
    "gn:timezone":"Asia/Shanghai",
    "iso:country":"CN",
    "name:zho_x_preferred":[
        "\u53ef\u5b98"
    ],
    "wof:name":"Keguan",
    "wof:placetype":"locality"
},
  "geometry": {"coordinates":[102.48388,24.2561],"type":"Point"}
}