{
  "type": "Feature",
  "properties": {
    "gn:admin1_code":"4.0",
    "gn:asciiname":"Beiren",
    "gn:country_code":"CN",
    "gn:dem":2,
    "gn:feature_class":"P",
    "gn:feature_code":"PPL",
    "gn:name":"Beiren",
    "gn:population":0,
    "gn:timezone":"Asia/Shanghai",
    "iso:country":"CN",
    "name:zho_x_preferred":[
        "Beiren"
    ],
    "name:zho_x_variant":[
        "\u5317\u4efb"
    ],
    "wof:name":"Beiren",
    "wof:placetype":"locality"
},
  "geometry": {"coordinates":[119.83014,33.22107],"type":"Point"}
}