{
  "type": "Feature",
  "properties": {
    "gn:admin1_code":"25",
    "gn:asciiname":"Beigushi",
    "gn:country_code":"CN",
    "gn:dem":80,
    "gn:feature_class":"P",
    "gn:feature_code":"PPL",
    "gn:name":"Beigushi",
    "gn:population":0,
    "gn:timezone":"Asia/Shanghai",
    "iso:country":"CN",
    "name:zho_x_preferred":[
        "\u5317\u53e4\u77f3"
    ],
    "wof:name":"Beigushi",
    "wof:placetype":"locality"
},
  "geometry": {"coordinates":[117.229,35.0081],"type":"Point"}
}