{
  "type": "Feature",
  "properties": {
    "gn:admin1_code":"4.0",
    "gn:asciiname":"Houmali",
    "gn:country_code":"CN",
    "gn:dem":31,
    "gn:feature_class":"P",
    "gn:feature_code":"PPL",
    "gn:name":"Houmali",
    "gn:population":0,
    "gn:timezone":"Asia/Shanghai",
    "iso:country":"CN",
    "name:zho_x_preferred":[
        "\u540e\u9a6c\u91cc"
    ],
    "wof:name":"Houmali",
    "wof:placetype":"locality"
},
  "geometry": {"coordinates":[119.25623,31.98617],"type":"Point"}
}