{
  "type": "Feature",
  "properties": {
    "gn:admin1_code":"11.0",
    "gn:asciiname":"Dangpuli",
    "gn:country_code":"CN",
    "gn:dem":51,
    "gn:feature_class":"P",
    "gn:feature_code":"PPL",
    "gn:name":"Dangpuli",
    "gn:population":0,
    "gn:timezone":"Asia/Shanghai",
    "iso:country":"CN",
    "name:zho_x_preferred":[
        "\u5f53\u94fa\u91cc"
    ],
    "wof:name":"Dangpuli",
    "wof:placetype":"locality"
},
  "geometry": {"coordinates":[113.17538999999999,28.05272],"type":"Point"}
}