{
  "type": "Feature",
  "properties": {
    "gn:admin1_code":"14.0",
    "gn:asciiname":"Suzha",
    "gn:country_code":"CN",
    "gn:dem":4441,
    "gn:feature_class":"P",
    "gn:feature_code":"PPL",
    "gn:name":"Suzha",
    "gn:population":0,
    "gn:timezone":"Asia/Urumqi",
    "iso:country":"CN",
    "name:zho_x_preferred":[
        "\u82cf\u624e"
    ],
    "wof:name":"Suzha",
    "wof:placetype":"locality"
},
  "geometry": {"coordinates":[91.43741,28.95705],"type":"Point"}
}