{
  "type": "Feature",
  "properties": {
    "gn:admin1_code":"19.0",
    "gn:asciiname":"Liangzigou",
    "gn:country_code":"CN",
    "gn:dem":181,
    "gn:feature_class":"P",
    "gn:feature_code":"PPL",
    "gn:name":"Liangzigou",
    "gn:population":0,
    "gn:timezone":"Asia/Shanghai",
    "iso:country":"CN",
    "name:und_x_variant":[
        "\u4eae\u5b50\u6c9f"
    ],
    "wof:name":"Liangzigou",
    "wof:placetype":"locality"
},
  "geometry": {"coordinates":[123.35432,40.68483],"type":"Point"}
}