{
  "type": "Feature",
  "properties": {
    "gn:admin1_code":"5.0",
    "gn:asciiname":"Hulintun",
    "gn:country_code":"CN",
    "gn:dem":157,
    "gn:feature_class":"P",
    "gn:feature_code":"PPL",
    "gn:name":"Hulintun",
    "gn:population":0,
    "gn:timezone":"Asia/Shanghai",
    "iso:country":"CN",
    "name:zho_x_preferred":[
        "\u62a4\u6797\u5c6f"
    ],
    "wof:name":"Hulintun",
    "wof:placetype":"locality"
},
  "geometry": {"coordinates":[122.68079,44.57873],"type":"Point"}
}