{
  "type": "Feature",
  "properties": {
    "gn:admin1_code":"21.0",
    "gn:asciiname":"Hejiashanzhuang",
    "gn:country_code":"CN",
    "gn:dem":1984,
    "gn:feature_class":"P",
    "gn:feature_code":"PPL",
    "gn:name":"Hejiashanzhuang",
    "gn:population":0,
    "gn:timezone":"Asia/Shanghai",
    "iso:country":"CN",
    "name:zho_x_preferred":[
        "\u8d3a\u5bb6\u5c71\u5e84"
    ],
    "wof:name":"Hejiashanzhuang",
    "wof:placetype":"locality"
},
  "geometry": {"coordinates":[106.50897999999999,36.47964],"type":"Point"}
}