{
  "type": "Feature",
  "properties": {
    "gn:admin1_code":"11",
    "gn:asciiname":"Liaojiawan",
    "gn:country_code":"CN",
    "gn:dem":437,
    "gn:feature_class":"P",
    "gn:feature_code":"PPL",
    "gn:name":"Liaojiawan",
    "gn:population":0,
    "gn:timezone":"Asia/Shanghai",
    "iso:country":"CN",
    "wof:name":"Liaojiawan",
    "wof:placetype":"locality"
},
  "geometry": {"coordinates":[113.00278,25.55861],"type":"Point"}
}