{
  "type": "Feature",
  "properties": {
    "gn:admin1_code":"9.0",
    "gn:asciiname":"Cuiwan",
    "gn:country_code":"CN",
    "gn:dem":162,
    "gn:feature_class":"P",
    "gn:feature_code":"PPL",
    "gn:name":"Cuiwan",
    "gn:population":0,
    "gn:timezone":"Asia/Shanghai",
    "iso:country":"CN",
    "name:zho_x_preferred":[
        "\u5d14\u6e7e"
    ],
    "wof:name":"Cuiwan",
    "wof:placetype":"locality"
},
  "geometry": {"coordinates":[111.52369,32.95518],"type":"Point"}
}