{
  "type": "Feature",
  "properties": {
    "gn:admin1_code":"16.0",
    "gn:asciiname":"Shengang",
    "gn:country_code":"CN",
    "gn:dem":15,
    "gn:feature_class":"P",
    "gn:feature_code":"PPL",
    "gn:name":"Shengang",
    "gn:population":0,
    "gn:timezone":"Asia/Shanghai",
    "iso:country":"CN",
    "name:deu_x_preferred":[
        "Shengang"
    ],
    "name:zho_x_preferred":[
        "\u6df1\u6e2f"
    ],
    "wof:name":"Shengang",
    "wof:placetype":"locality"
},
  "geometry": {"coordinates":[108.637,21.8111],"type":"Point"}
}