{
  "type": "Feature",
  "properties": {
    "gn:admin1_code":"30.0",
    "gn:asciiname":"Dongnan",
    "gn:country_code":"CN",
    "gn:dem":334,
    "gn:feature_class":"P",
    "gn:feature_code":"PPL",
    "gn:name":"Dongnan",
    "gn:population":0,
    "gn:timezone":"Asia/Shanghai",
    "iso:country":"CN",
    "name:zho_x_preferred":[
        "Dongnan"
    ],
    "name:zho_x_variant":[
        "\u4e1c\u5357"
    ],
    "wof:name":"Dongnan",
    "wof:placetype":"locality"
},
  "geometry": {"coordinates":[112.03667,24.23306],"type":"Point"}
}