{
  "type": "Feature",
  "properties": {
    "gn:admin1_code":"29",
    "gn:asciiname":"Zhezuobo",
    "gn:country_code":"CN",
    "gn:dem":1808,
    "gn:feature_class":"P",
    "gn:feature_code":"PPL",
    "gn:name":"Zhezuobo",
    "gn:population":0,
    "gn:timezone":"Asia/Shanghai",
    "iso:country":"CN",
    "name:zho_x_preferred":[
        "\u6298\u5de6\u7c38"
    ],
    "wof:name":"Zhezuobo",
    "wof:placetype":"locality"
},
  "geometry": {"coordinates":[101.242,24.7216],"type":"Point"}
}