{
  "type": "Feature",
  "properties": {
    "gn:admin1_code":"9.0",
    "gn:asciiname":"Banpodian",
    "gn:country_code":"CN",
    "gn:dem":67,
    "gn:feature_class":"P",
    "gn:feature_code":"PPL",
    "gn:name":"Banpodian",
    "gn:population":0,
    "gn:timezone":"Asia/Shanghai",
    "iso:country":"CN",
    "name:zho_x_preferred":[
        "\u534a\u5761\u5e97"
    ],
    "wof:name":"Banpodian",
    "wof:placetype":"locality"
},
  "geometry": {"coordinates":[114.29721000000001,33.13774],"type":"Point"}
}