{
  "type": "Feature",
  "properties": {
    "gn:admin1_code":"26.0",
    "gn:asciiname":"Jiujianwu",
    "gn:country_code":"CN",
    "gn:dem":1364,
    "gn:feature_class":"P",
    "gn:feature_code":"PPL",
    "gn:name":"Jiujianwu",
    "gn:population":0,
    "gn:timezone":"Asia/Shanghai",
    "iso:country":"CN",
    "name:und_x_variant":[
        "Jiucaiping"
    ],
    "name:zho_x_preferred":[
        "\u4e5d\u95f4\u5c4b"
    ],
    "wof:name":"Jiujianwu",
    "wof:placetype":"locality"
},
  "geometry": {"coordinates":[108.59088,33.4994],"type":"Point"}
}