{
  "type": "Feature",
  "properties": {
    "gn:admin1_code":"9.0",
    "gn:asciiname":"Liuyuankou",
    "gn:country_code":"CN",
    "gn:dem":85,
    "gn:feature_class":"P",
    "gn:feature_code":"PPL",
    "gn:name":"Liuyuankou",
    "gn:population":0,
    "gn:timezone":"Asia/Shanghai",
    "iso:country":"CN",
    "name:zho_x_preferred":[
        "\u67f3\u56ed\u53e3"
    ],
    "wof:name":"Liuyuankou",
    "wof:placetype":"locality"
},
  "geometry": {"coordinates":[113.82791,34.76991],"type":"Point"}
}