{
  "type": "Feature",
  "properties": {
    "gn:admin1_code":"10.0",
    "gn:asciiname":"Yaojiafen",
    "gn:country_code":"CN",
    "gn:dem":703,
    "gn:feature_class":"P",
    "gn:feature_code":"PPL",
    "gn:name":"Yaojiafen",
    "gn:population":0,
    "gn:timezone":"Asia/Shanghai",
    "iso:country":"CN",
    "name:zho_x_preferred":[
        "\u59da\u5bb6\u575f"
    ],
    "wof:name":"Yaojiafen",
    "wof:placetype":"locality"
},
  "geometry": {"coordinates":[115.05862999999999,40.66692000000001],"type":"Point"}
}