{
  "type": "Feature",
  "properties": {
    "gn:admin1_code":"16.0",
    "gn:asciiname":"Peiji",
    "gn:country_code":"CN",
    "gn:dem":395,
    "gn:feature_class":"P",
    "gn:feature_code":"PPL",
    "gn:name":"Peiji",
    "gn:population":0,
    "gn:timezone":"Asia/Shanghai",
    "iso:country":"CN",
    "name:zho_x_preferred":[
        "\u57f9\u5409"
    ],
    "wof:name":"Peiji",
    "wof:placetype":"locality"
},
  "geometry": {"coordinates":[109.32899999999999,25.7134],"type":"Point"}
}