{
  "type": "Feature",
  "properties": {
    "gn:admin1_code":"11.0",
    "gn:asciiname":"Laozhaigou",
    "gn:country_code":"CN",
    "gn:dem":348,
    "gn:feature_class":"P",
    "gn:feature_code":"PPL",
    "gn:name":"Laozhaigou",
    "gn:population":0,
    "gn:timezone":"Asia/Shanghai",
    "iso:country":"CN",
    "name:zho_x_preferred":[
        "\u8001\u5be8\u6c9f"
    ],
    "wof:name":"Laozhaigou",
    "wof:placetype":"locality"
},
  "geometry": {"coordinates":[109.73808,29.01616],"type":"Point"}
}