{
  "type": "Feature",
  "properties": {
    "gn:admin1_code":"12.0",
    "gn:asciiname":"Binjiang",
    "gn:country_code":"CN",
    "gn:dem":19,
    "gn:feature_class":"P",
    "gn:feature_code":"PPL",
    "gn:name":"Binjiang",
    "gn:population":0,
    "gn:timezone":"Asia/Shanghai",
    "iso:country":"CN",
    "name:zho_x_preferred":[
        "\u6ee8\u6c5f"
    ],
    "wof:name":"Binjiang",
    "wof:placetype":"locality"
},
  "geometry": {"coordinates":[116.12354000000001,29.83466],"type":"Point"}
}