{
  "type": "Feature",
  "properties": {
    "gn:admin1_code":"14.0",
    "gn:asciiname":"Jizha",
    "gn:country_code":"CN",
    "gn:dem":4677,
    "gn:feature_class":"P",
    "gn:feature_code":"PPL",
    "gn:name":"Jizha",
    "gn:population":0,
    "gn:timezone":"Asia/Urumqi",
    "iso:country":"CN",
    "name:zho_x_preferred":[
        "\u5409\u624e"
    ],
    "wof:name":"Jizha",
    "wof:placetype":"locality"
},
  "geometry": {"coordinates":[86.7487,29.489],"type":"Point"}
}