{
  "type": "Feature",
  "properties": {
    "gn:admin1_code":"16.0",
    "gn:asciiname":"Babailing",
    "gn:country_code":"CN",
    "gn:dem":218,
    "gn:feature_class":"P",
    "gn:feature_code":"PPL",
    "gn:name":"Babailing",
    "gn:population":0,
    "gn:timezone":"Asia/Shanghai",
    "iso:country":"CN",
    "name:zho_x_preferred":[
        "\u516b\u767e\u5cad"
    ],
    "wof:name":"Babailing",
    "wof:placetype":"locality"
},
  "geometry": {"coordinates":[111.349,24.8835],"type":"Point"}
}