{
  "type": "Feature",
  "properties": {
    "gn:admin1_code":"26.0",
    "gn:asciiname":"Zhangzhuangcun",
    "gn:country_code":"CN",
    "gn:dem":1090,
    "gn:feature_class":"P",
    "gn:feature_code":"PPL",
    "gn:name":"Zhangzhuangcun",
    "gn:population":0,
    "gn:timezone":"Asia/Shanghai",
    "iso:country":"CN",
    "name:zho_x_preferred":[
        "\u5f20\u5e84\u6751"
    ],
    "wof:name":"Zhangzhuangcun",
    "wof:placetype":"locality"
},
  "geometry": {"coordinates":[109.55953999999998,36.70256],"type":"Point"}
}