{
  "type": "Feature",
  "properties": {
    "gn:admin1_code":"25",
    "gn:asciiname":"Dongquanli",
    "gn:country_code":"CN",
    "gn:dem":239,
    "gn:feature_class":"P",
    "gn:feature_code":"PPL",
    "gn:name":"Dongquanli",
    "gn:population":0,
    "gn:timezone":"Asia/Shanghai",
    "iso:country":"CN",
    "name:zho_x_preferred":[
        "\u4e1c\u5708\u91cc"
    ],
    "wof:name":"Dongquanli",
    "wof:placetype":"locality"
},
  "geometry": {"coordinates":[117.395,35.4444],"type":"Point"}
}