{
  "type": "Feature",
  "properties": {
    "gn:admin1_code":"33.0",
    "gn:asciiname":"Xiangdong",
    "gn:country_code":"CN",
    "gn:dem":510,
    "gn:feature_class":"P",
    "gn:feature_code":"PPL",
    "gn:name":"Xiangdong",
    "gn:population":0,
    "gn:timezone":"Asia/Shanghai",
    "iso:country":"CN",
    "name:zho_x_preferred":[
        "\u5411\u4e1c"
    ],
    "wof:name":"Xiangdong",
    "wof:placetype":"locality"
},
  "geometry": {"coordinates":[108.68266,30.66278],"type":"Point"}
}