{
  "type": "Feature",
  "properties": {
    "gn:admin1_code":"8.0",
    "gn:asciiname":"Ronghuacun",
    "gn:country_code":"CN",
    "gn:dem":182,
    "gn:feature_class":"P",
    "gn:feature_code":"PPL",
    "gn:name":"Ronghuacun",
    "gn:population":0,
    "gn:timezone":"Asia/Shanghai",
    "iso:country":"CN",
    "name:zho_x_preferred":[
        "\u8363\u534e\u6751"
    ],
    "wof:name":"Ronghuacun",
    "wof:placetype":"locality"
},
  "geometry": {"coordinates":[130.56471000000002,46.19849],"type":"Point"}
}