{
  "type": "Feature",
  "properties": {
    "gn:admin1_code":"10",
    "gn:asciiname":"Henghezi",
    "gn:country_code":"CN",
    "gn:dem":1365,
    "gn:feature_class":"P",
    "gn:feature_code":"PPL",
    "gn:name":"Henghezi",
    "gn:population":0,
    "gn:timezone":"Asia/Shanghai",
    "iso:country":"CN",
    "name:zho_x_preferred":[
        "\u6a2a\u6cb3\u5b50"
    ],
    "wof:name":"Henghezi",
    "wof:placetype":"locality"
},
  "geometry": {"coordinates":[117.05313999999998,42.12199],"type":"Point"}
}