{
  "type": "Feature",
  "properties": {
    "gn:admin1_code":"11",
    "gn:asciiname":"Shuangheting",
    "gn:country_code":"CN",
    "gn:dem":152,
    "gn:feature_class":"P",
    "gn:feature_code":"PPL",
    "gn:name":"Shuangheting",
    "gn:population":0,
    "gn:timezone":"Asia/Shanghai",
    "iso:country":"CN",
    "name:zho_x_preferred":[
        "\u53cc\u5408\u4ead"
    ],
    "wof:name":"Shuangheting",
    "wof:placetype":"locality"
},
  "geometry": {"coordinates":[111.85827,26.86975],"type":"Point"}
}