{
  "type": "Feature",
  "properties": {
    "gn:admin1_code":"4.0",
    "gn:asciiname":"Nianqizong",
    "gn:country_code":"CN",
    "gn:dem":2,
    "gn:feature_class":"P",
    "gn:feature_code":"PPL",
    "gn:name":"Nianqizong",
    "gn:population":0,
    "gn:timezone":"Asia/Shanghai",
    "iso:country":"CN",
    "name:und_x_variant":[
        "\u5ff5\u4e03\u603b"
    ],
    "wof:name":"Nianqizong",
    "wof:placetype":"locality"
},
  "geometry": {"coordinates":[121.54541,32.04846],"type":"Point"}
}