{
  "type": "Feature",
  "properties": {
    "gn:admin1_code":"4.0",
    "gn:asciiname":"Buxujie",
    "gn:country_code":"CN",
    "gn:dem":7,
    "gn:feature_class":"P",
    "gn:feature_code":"PPL",
    "gn:name":"Buxujie",
    "gn:population":0,
    "gn:timezone":"Asia/Shanghai",
    "iso:country":"CN",
    "name:zho_x_preferred":[
        "Buxujie"
    ],
    "name:zho_x_variant":[
        "\u535c\u5729\u8857"
    ],
    "wof:name":"Buxujie",
    "wof:placetype":"locality"
},
  "geometry": {"coordinates":[119.17637000000001,33.89032],"type":"Point"}
}