{
  "type": "Feature",
  "properties": {
    "gn:admin1_code":"29",
    "gn:asciiname":"Longjie",
    "gn:cc2":"CN",
    "gn:country_code":"CN",
    "gn:dem":1375,
    "gn:feature_class":"P",
    "gn:feature_code":"PPL",
    "gn:name":"Longjie",
    "gn:population":0,
    "gn:timezone":"Asia/Shanghai",
    "iso:country":"CN",
    "name:und_x_variant":[
        "Lung-chieh",
        "Longjie"
    ],
    "wof:name":"Longjie",
    "wof:placetype":"locality"
},
  "geometry": {"coordinates":[101.90000000000001,25.95],"type":"Point"}
}