{
  "type": "Feature",
  "properties": {
    "gn:admin1_code":"24.0",
    "gn:asciiname":"Shangxinfo",
    "gn:country_code":"CN",
    "gn:dem":1034,
    "gn:feature_class":"P",
    "gn:feature_code":"PPL",
    "gn:name":"Shangxinfo",
    "gn:population":0,
    "gn:timezone":"Asia/Shanghai",
    "iso:country":"CN",
    "name:zho_x_preferred":[
        "\u4e0a\u8f9b\u4f5b"
    ],
    "wof:name":"Shangxinfo",
    "wof:placetype":"locality"
},
  "geometry": {"coordinates":[111.97754,36.4224],"type":"Point"}
}