{
  "type": "Feature",
  "properties": {
    "gn:admin1_code":"12",
    "gn:asciiname":"Luyanyi",
    "gn:cc2":"CN",
    "gn:country_code":"CN",
    "gn:dem":89,
    "gn:feature_class":"P",
    "gn:feature_code":"PPL",
    "gn:name":"L\u00fcyanyi",
    "gn:population":0,
    "gn:timezone":"Asia/Shanghai",
    "iso:country":"CN",
    "name:und_x_variant":[
        "L\u00fc-yen-i",
        "L\u00fcyanyi"
    ],
    "wof:name":"Luyanyi",
    "wof:placetype":"locality"
},
  "geometry": {"coordinates":[112.23333,32.26667],"type":"Point"}
}