{
  "type": "Feature",
  "properties": {
    "gn:admin1_code":"4.0",
    "gn:asciiname":"Donghuzhuang",
    "gn:country_code":"CN",
    "gn:dem":16,
    "gn:feature_class":"P",
    "gn:feature_code":"PPL",
    "gn:name":"Donghuzhuang",
    "gn:population":0,
    "gn:timezone":"Asia/Shanghai",
    "iso:country":"CN",
    "name:zho_x_preferred":[
        "\u4e1c\u80e1\u5e84"
    ],
    "wof:name":"Donghuzhuang",
    "wof:placetype":"locality"
},
  "geometry": {"coordinates":[118.50700000000001,33.949],"type":"Point"}
}