{
  "type": "Feature",
  "properties": {
    "gn:admin1_code":"11.0",
    "gn:asciiname":"Bajiao Dawu",
    "gn:country_code":"CN",
    "gn:dem":97,
    "gn:feature_class":"P",
    "gn:feature_code":"PPL",
    "gn:name":"Bajiao Dawu",
    "gn:population":0,
    "gn:timezone":"Asia/Shanghai",
    "iso:country":"CN",
    "name:zho_x_preferred":[
        "\u82ad\u8549\u5927\u5c4b"
    ],
    "wof:name":"Bajiao Dawu",
    "wof:placetype":"locality"
},
  "geometry": {"coordinates":[113.58405999999999,29.23514],"type":"Point"}
}