{
  "type": "Feature",
  "properties": {
    "gn:admin1_code":"3.0",
    "gn:asciiname":"Xiaokeng",
    "gn:country_code":"CN",
    "gn:dem":108,
    "gn:feature_class":"P",
    "gn:feature_code":"PPL",
    "gn:name":"Xiaokeng",
    "gn:population":0,
    "gn:timezone":"Asia/Shanghai",
    "iso:country":"CN",
    "name:und_x_variant":[
        "\u5c0f\u5751"
    ],
    "wof:name":"Xiaokeng",
    "wof:placetype":"locality"
},
  "geometry": {"coordinates":[115.02782999999999,27.25772000000001],"type":"Point"}
}