{
  "type": "Feature",
  "properties": {
    "gn:admin1_code":"12.0",
    "gn:asciiname":"Luopangang",
    "gn:country_code":"CN",
    "gn:dem":72,
    "gn:feature_class":"P",
    "gn:feature_code":"PPL",
    "gn:name":"Luopangang",
    "gn:population":0,
    "gn:timezone":"Asia/Shanghai",
    "iso:country":"CN",
    "name:zho_x_preferred":[
        "\u7f57\u76d8\u5c97"
    ],
    "wof:name":"Luopangang",
    "wof:placetype":"locality"
},
  "geometry": {"coordinates":[113.91046,31.32261],"type":"Point"}
}