{
  "type": "Feature",
  "properties": {
    "gn:admin1_code":"31",
    "gn:asciiname":"Chunyuan",
    "gn:country_code":"CN",
    "gn:dem":5,
    "gn:feature_class":"P",
    "gn:feature_code":"PPL",
    "gn:name":"Chunyuan",
    "gn:population":0,
    "gn:timezone":"Asia/Shanghai",
    "iso:country":"CN",
    "name:und_x_variant":[
        "\u6625\u56ed"
    ],
    "wof:name":"Chunyuan",
    "wof:placetype":"locality"
},
  "geometry": {"coordinates":[110.497,18.7876],"type":"Point"}
}