{
  "type": "Feature",
  "properties": {
    "gn:admin1_code":"29",
    "gn:asciiname":"Da'an",
    "gn:country_code":"CN",
    "gn:dem":470,
    "gn:feature_class":"P",
    "gn:feature_code":"PPL",
    "gn:name":"Da\u2019an",
    "gn:population":0,
    "gn:timezone":"Asia/Shanghai",
    "iso:country":"CN",
    "name:und_x_variant":[
        "Da\u2019an"
    ],
    "name:zho_x_preferred":[
        "\u8fbe\u5cb8"
    ],
    "wof:name":"Da'an",
    "wof:placetype":"locality"
},
  "geometry": {"coordinates":[106.05200000000001,23.9894],"type":"Point"}
}