{
  "type": "Feature",
  "properties": {
    "gn:admin1_code":"6.0",
    "gn:asciiname":"Duoniang",
    "gn:country_code":"CN",
    "gn:dem":3917,
    "gn:feature_class":"P",
    "gn:feature_code":"PPL",
    "gn:name":"Duoniang",
    "gn:population":0,
    "gn:timezone":"Asia/Shanghai",
    "iso:country":"CN",
    "name:zho_x_preferred":[
        "\u591a\u5a18"
    ],
    "wof:name":"Duoniang",
    "wof:placetype":"locality"
},
  "geometry": {"coordinates":[100.17318,32.9116],"type":"Point"}
}