{
  "type": "Feature",
  "properties": {
    "gn:admin1_code":"8.0",
    "gn:asciiname":"Dongfanghong Yi'ersidui Wopeng",
    "gn:country_code":"CN",
    "gn:dem":167,
    "gn:feature_class":"P",
    "gn:feature_code":"PPLF",
    "gn:name":"Dongfanghong Yi\u2019ersidui Wopeng",
    "gn:population":0,
    "gn:timezone":"Asia/Shanghai",
    "iso:country":"CN",
    "name:und_x_variant":[
        "Dongfanghong Yi\u2019ersidui Wopeng"
    ],
    "name:zho_x_preferred":[
        "\u4e1c\u65b9\u7ea2\u4e00\u4e8c\u56db\u961f\u7a9d\u68da"
    ],
    "wof:name":"Dongfanghong Yi'ersidui Wopeng",
    "wof:placetype":"locality"
},
  "geometry": {"coordinates":[125.48841000000002,47.04439],"type":"Point"}
}