{
  "type": "Feature",
  "properties": {
    "gn:admin1_code":"22.0",
    "gn:asciiname":"Taishangcun",
    "gn:country_code":"CN",
    "gn:dem":485,
    "gn:feature_class":"P",
    "gn:feature_code":"PPL",
    "gn:name":"Taishangcun",
    "gn:population":0,
    "gn:timezone":"Asia/Shanghai",
    "iso:country":"CN",
    "name:zho_x_preferred":[
        "\u53f0\u4e0a\u6751"
    ],
    "wof:name":"Taishangcun",
    "wof:placetype":"locality"
},
  "geometry": {"coordinates":[116.62882999999999,40.79419],"type":"Point"}
}