{
  "type": "Feature",
  "properties": {
    "gn:admin1_code":"9.0",
    "gn:asciiname":"Lugangzhai",
    "gn:country_code":"CN",
    "gn:dem":124,
    "gn:feature_class":"P",
    "gn:feature_code":"PPL",
    "gn:name":"Lugangzhai",
    "gn:population":0,
    "gn:timezone":"Asia/Shanghai",
    "iso:country":"CN",
    "name:zho_x_preferred":[
        "\u5362\u5c97\u5be8"
    ],
    "wof:name":"Lugangzhai",
    "wof:placetype":"locality"
},
  "geometry": {"coordinates":[111.99254000000001,32.63157],"type":"Point"}
}