{
  "type": "Feature",
  "properties": {
    "gn:admin1_code":"9.0",
    "gn:asciiname":"Shangxiaolou",
    "gn:country_code":"CN",
    "gn:dem":166,
    "gn:feature_class":"P",
    "gn:feature_code":"PPL",
    "gn:name":"Shangxiaolou",
    "gn:population":0,
    "gn:timezone":"Asia/Shanghai",
    "iso:country":"CN",
    "name:zho_x_preferred":[
        "\u4e0a\u8096\u697c"
    ],
    "wof:name":"Shangxiaolou",
    "wof:placetype":"locality"
},
  "geometry": {"coordinates":[113.78005,32.54887],"type":"Point"}
}