{
  "type": "Feature",
  "properties": {
    "gn:admin1_code":"8.0",
    "gn:asciiname":"Yangqinghe",
    "gn:country_code":"CN",
    "gn:dem":136,
    "gn:feature_class":"P",
    "gn:feature_code":"PPL",
    "gn:name":"Yangqinghe",
    "gn:population":0,
    "gn:timezone":"Asia/Shanghai",
    "iso:country":"CN",
    "name:zho_x_preferred":[
        "\u6768\u6e05\u548c"
    ],
    "wof:name":"Yangqinghe",
    "wof:placetype":"locality"
},
  "geometry": {"coordinates":[124.99024,46.11055],"type":"Point"}
}