{
  "type": "Feature",
  "properties": {
    "gn:admin1_code":"18",
    "gn:asciiname":"Laozhaitu",
    "gn:country_code":"CN",
    "gn:dem":1751,
    "gn:feature_class":"P",
    "gn:feature_code":"PPL",
    "gn:name":"Laozhaitu",
    "gn:population":0,
    "gn:timezone":"Asia/Shanghai",
    "iso:country":"CN",
    "name:zho_x_preferred":[
        "\u8001\u5be8\u571f"
    ],
    "wof:name":"Laozhaitu",
    "wof:placetype":"locality"
},
  "geometry": {"coordinates":[105.405,26.6295],"type":"Point"}
}