{
  "type": "Feature",
  "properties": {
    "gn:admin1_code":"13",
    "gn:asciiname":"Qiakema Ketashi",
    "gn:country_code":"CN",
    "gn:dem":1940,
    "gn:feature_class":"P",
    "gn:feature_code":"PPL",
    "gn:name":"Qiakema Ketashi",
    "gn:population":0,
    "gn:timezone":"Asia/Urumqi",
    "iso:country":"CN",
    "name:zho_x_preferred":[
        "\u6070\u514b\u9a6c\u514b\u5854\u4ec0"
    ],
    "wof:name":"Qiakema Ketashi",
    "wof:placetype":"locality"
},
  "geometry": {"coordinates":[94.94074999999999,42.86973],"type":"Point"}
}