{
  "type": "Feature",
  "properties": {
    "gn:admin1_code":"14.0",
    "gn:asciiname":"Ka'egongcun",
    "gn:country_code":"CN",
    "gn:dem":4011,
    "gn:feature_class":"P",
    "gn:feature_code":"PPL",
    "gn:name":"Ka\u2019egongcun",
    "gn:population":0,
    "gn:timezone":"Asia/Urumqi",
    "iso:country":"CN",
    "name:und_x_variant":[
        "Ka\u2019egongcun"
    ],
    "name:zho_x_preferred":[
        "\u5494\u4fc4\u8d21\u6751"
    ],
    "wof:name":"Ka'egongcun",
    "wof:placetype":"locality"
},
  "geometry": {"coordinates":[94.28543000000001,31.6738],"type":"Point"}
}