{
  "type": "Feature",
  "properties": {
    "gn:admin1_code":"3.0",
    "gn:asciiname":"Guangzhou",
    "gn:country_code":"CN",
    "gn:dem":366,
    "gn:feature_class":"P",
    "gn:feature_code":"PPL",
    "gn:name":"Guangzhou",
    "gn:population":0,
    "gn:timezone":"Asia/Shanghai",
    "iso:country":"CN",
    "name:und_x_variant":[
        "\u5e7f\u6d32"
    ],
    "wof:name":"Guangzhou",
    "wof:placetype":"locality"
},
  "geometry": {"coordinates":[114.13426,27.38164],"type":"Point"}
}