{
  "type": "Feature",
  "properties": {
    "gn:admin1_code":"32.0",
    "gn:asciiname":"Song'antong",
    "gn:country_code":"CN",
    "gn:dem":3094,
    "gn:feature_class":"P",
    "gn:feature_code":"PPL",
    "gn:name":"Song\u2019antong",
    "gn:population":0,
    "gn:timezone":"Asia/Shanghai",
    "iso:country":"CN",
    "name:und_x_variant":[
        "Song\u2019antong"
    ],
    "name:zho_x_preferred":[
        "\u677e\u5b89\u901a"
    ],
    "wof:name":"Song'antong",
    "wof:placetype":"locality"
},
  "geometry": {"coordinates":[99.91330000000001,29.1424],"type":"Point"}
}