{
  "type": "Feature",
  "properties": {
    "gn:admin1_code":"3.0",
    "gn:asciiname":"Laowudi",
    "gn:country_code":"CN",
    "gn:dem":67,
    "gn:feature_class":"P",
    "gn:feature_code":"PPL",
    "gn:name":"Laowudi",
    "gn:population":0,
    "gn:timezone":"Asia/Shanghai",
    "iso:country":"CN",
    "name:und_x_variant":[
        "\u8001\u5c4b\u5e95"
    ],
    "wof:name":"Laowudi",
    "wof:placetype":"locality"
},
  "geometry": {"coordinates":[116.94316000000001,28.51944],"type":"Point"}
}