{
  "type": "Feature",
  "properties": {
    "gn:admin1_code":"11.0",
    "gn:asciiname":"Huangtianlong",
    "gn:country_code":"CN",
    "gn:dem":1229,
    "gn:feature_class":"P",
    "gn:feature_code":"PPL",
    "gn:name":"Huangtianlong",
    "gn:population":0,
    "gn:timezone":"Asia/Shanghai",
    "iso:country":"CN",
    "name:zho_x_preferred":[
        "\u8352\u7530\u5785"
    ],
    "wof:name":"Huangtianlong",
    "wof:placetype":"locality"
},
  "geometry": {"coordinates":[113.92256999999999,26.26104],"type":"Point"}
}