{
  "type": "Feature",
  "properties": {
    "gn:admin1_code":"15.0",
    "gn:asciiname":"Yaozhuangxia",
    "gn:country_code":"CN",
    "gn:dem":2031,
    "gn:feature_class":"P",
    "gn:feature_code":"PPL",
    "gn:name":"Yaozhuangxia",
    "gn:population":0,
    "gn:timezone":"Asia/Shanghai",
    "iso:country":"CN",
    "name:und_x_variant":[
        "\u8170\u5e84\u4e0b"
    ],
    "wof:name":"Yaozhuangxia",
    "wof:placetype":"locality"
},
  "geometry": {"coordinates":[104.88906,34.5775],"type":"Point"}
}