{
  "type": "Feature",
  "properties": {
    "gn:admin1_code":"1.0",
    "gn:asciiname":"Qianlicun",
    "gn:country_code":"CN",
    "gn:dem":23,
    "gn:feature_class":"P",
    "gn:feature_code":"PPL",
    "gn:name":"Qianlicun",
    "gn:population":0,
    "gn:timezone":"Asia/Shanghai",
    "iso:country":"CN",
    "name:zho_x_preferred":[
        "\u524d\u674e\u6751"
    ],
    "wof:name":"Qianlicun",
    "wof:placetype":"locality"
},
  "geometry": {"coordinates":[117.75473999999998,33.56713],"type":"Point"}
}