{
  "type": "Feature",
  "properties": {
    "gn:admin1_code":"4.0",
    "gn:asciiname":"Dongdaxu",
    "gn:country_code":"CN",
    "gn:dem":9,
    "gn:feature_class":"P",
    "gn:feature_code":"PPL",
    "gn:name":"Dongdaxu",
    "gn:population":0,
    "gn:timezone":"Asia/Shanghai",
    "iso:country":"CN",
    "name:zho_x_preferred":[
        "\u4e1c\u5927\u5729"
    ],
    "wof:name":"Dongdaxu",
    "wof:placetype":"locality"
},
  "geometry": {"coordinates":[119.92301999999999,32.04277],"type":"Point"}
}