{
  "type": "Feature",
  "properties": {
    "gn:admin1_code":"21.0",
    "gn:asciiname":"Dongtaishang",
    "gn:country_code":"CN",
    "gn:dem":1721,
    "gn:feature_class":"P",
    "gn:feature_code":"PPL",
    "gn:name":"Dongtaishang",
    "gn:population":0,
    "gn:timezone":"Asia/Shanghai",
    "iso:country":"CN",
    "name:und_x_variant":[
        "\u4e1c\u53f0\u4e0a"
    ],
    "name:zho_x_preferred":[
        "\u4e1c\u53f0\u4e0a"
    ],
    "wof:name":"Dongtaishang",
    "wof:placetype":"locality"
},
  "geometry": {"coordinates":[106.31162,36.23816],"type":"Point"}
}