{
  "type": "Feature",
  "properties": {
    "gn:admin1_code":"4.0",
    "gn:asciiname":"Dunnancun",
    "gn:country_code":"CN",
    "gn:dem":11,
    "gn:feature_class":"P",
    "gn:feature_code":"PPL",
    "gn:name":"Dunnancun",
    "gn:population":0,
    "gn:timezone":"Asia/Shanghai",
    "iso:country":"CN",
    "name:zho_x_preferred":[
        "\u58a9\u5357\u6751"
    ],
    "wof:name":"Dunnancun",
    "wof:placetype":"locality"
},
  "geometry": {"coordinates":[118.93071999999999,33.29431],"type":"Point"}
}