{
  "type": "Feature",
  "properties": {
    "gn:admin1_code":"11.0",
    "gn:asciiname":"Xipu",
    "gn:country_code":"CN",
    "gn:dem":237,
    "gn:feature_class":"P",
    "gn:feature_code":"PPL",
    "gn:name":"Xipu",
    "gn:population":0,
    "gn:timezone":"Asia/Shanghai",
    "iso:country":"CN",
    "name:deu_x_preferred":[
        "Xipu"
    ],
    "name:zho_x_preferred":[
        "\u897f\u6d66"
    ],
    "wof:name":"Xipu",
    "wof:placetype":"locality"
},
  "geometry": {"coordinates":[110.74007,29.2956],"type":"Point"}
}