{
  "type": "Feature",
  "properties": {
    "gn:admin1_code":"30",
    "gn:asciiname":"Kuzhuping",
    "gn:country_code":"CN",
    "gn:dem":463,
    "gn:feature_class":"P",
    "gn:feature_code":"PPL",
    "gn:name":"Kuzhuping",
    "gn:population":0,
    "gn:timezone":"Asia/Shanghai",
    "iso:country":"CN",
    "name:zho_x_preferred":[
        "\u82e6\u7af9\u576a"
    ],
    "name:zho_x_variant":[
        "\u82e6\u7af9\u576a\u4e61"
    ],
    "wof:name":"Kuzhuping",
    "wof:placetype":"locality"
},
  "geometry": {"coordinates":[116.40018999999999,23.83786],"type":"Point"}
}