{
  "type": "Feature",
  "properties": {
    "gn:admin1_code":"29.0",
    "gn:asciiname":"Xiaoxingzhai",
    "gn:country_code":"CN",
    "gn:dem":1316,
    "gn:feature_class":"P",
    "gn:feature_code":"PPL",
    "gn:name":"Xiaoxingzhai",
    "gn:population":0,
    "gn:timezone":"Asia/Shanghai",
    "iso:country":"CN",
    "name:zho_x_preferred":[
        "\u5c0f\u661f\u5be8"
    ],
    "wof:name":"Xiaoxingzhai",
    "wof:placetype":"locality"
},
  "geometry": {"coordinates":[98.9802,25.0486],"type":"Point"}
}