{
  "type": "Feature",
  "properties": {
    "gn:admin1_code":"15.0",
    "gn:asciiname":"Goujiayuan",
    "gn:country_code":"CN",
    "gn:dem":1556,
    "gn:feature_class":"P",
    "gn:feature_code":"PPL",
    "gn:name":"Goujiayuan",
    "gn:population":0,
    "gn:timezone":"Asia/Shanghai",
    "iso:country":"CN",
    "name:und_x_variant":[
        "\u82df\u5bb6\u586c"
    ],
    "wof:name":"Goujiayuan",
    "wof:placetype":"locality"
},
  "geometry": {"coordinates":[107.55676,36.49362],"type":"Point"}
}