{
  "type": "Feature",
  "properties": {
    "gn:admin1_code":"30.0",
    "gn:asciiname":"Huangwuzai",
    "gn:country_code":"CN",
    "gn:dem":129,
    "gn:feature_class":"P",
    "gn:feature_code":"PPL",
    "gn:name":"Huangwuzai",
    "gn:population":0,
    "gn:timezone":"Asia/Shanghai",
    "iso:country":"CN",
    "name:zho_x_preferred":[
        "\u9ec4\u5c4b\u4ed4"
    ],
    "wof:name":"Huangwuzai",
    "wof:placetype":"locality"
},
  "geometry": {"coordinates":[114.96758,23.80906],"type":"Point"}
}