{
  "type": "Feature",
  "properties": {
    "gn:admin1_code":"18",
    "gn:asciiname":"Yemaodong",
    "gn:country_code":"CN",
    "gn:dem":1225,
    "gn:feature_class":"P",
    "gn:feature_code":"PPL",
    "gn:name":"Yemaodong",
    "gn:population":0,
    "gn:timezone":"Asia/Shanghai",
    "iso:country":"CN",
    "name:zho_x_preferred":[
        "\u91ce\u732b\u6d1e"
    ],
    "wof:name":"Yemaodong",
    "wof:placetype":"locality"
},
  "geometry": {"coordinates":[107.794,28.6724],"type":"Point"}
}