{
  "type": "Feature",
  "properties": {
    "gn:admin1_code":"20.0",
    "gn:asciiname":"Yangluotan",
    "gn:country_code":"CN",
    "gn:dem":1034,
    "gn:feature_class":"P",
    "gn:feature_code":"PPL",
    "gn:name":"Yangluotan",
    "gn:population":0,
    "gn:timezone":"Asia/Shanghai",
    "iso:country":"CN",
    "name:und_x_variant":[
        "\u6768\u843d\u6ee9"
    ],
    "wof:name":"Yangluotan",
    "wof:placetype":"locality"
},
  "geometry": {"coordinates":[111.43344,39.88584],"type":"Point"}
}