{
  "type": "Feature",
  "properties": {
    "gn:admin1_code":"30.0",
    "gn:asciiname":"Xiapudong",
    "gn:country_code":"CN",
    "gn:dem":225,
    "gn:feature_class":"P",
    "gn:feature_code":"PPL",
    "gn:name":"Xiapudong",
    "gn:population":0,
    "gn:timezone":"Asia/Shanghai",
    "iso:country":"CN",
    "name:zho_x_preferred":[
        "\u4e0b\u84b2\u578c"
    ],
    "wof:name":"Xiapudong",
    "wof:placetype":"locality"
},
  "geometry": {"coordinates":[111.36337,22.63198],"type":"Point"}
}