{
  "type": "Feature",
  "properties": {
    "gn:admin1_code":"18",
    "gn:asciiname":"Huangyang",
    "gn:country_code":"CN",
    "gn:dem":1166,
    "gn:feature_class":"P",
    "gn:feature_code":"PPL",
    "gn:name":"Huangyang",
    "gn:population":0,
    "gn:timezone":"Asia/Shanghai",
    "iso:country":"CN",
    "name:zho_x_preferred":[
        "\u9ec4\u6d0b"
    ],
    "wof:name":"Huangyang",
    "wof:placetype":"locality"
},
  "geometry": {"coordinates":[108.04600000000001,28.6777],"type":"Point"}
}