{
  "type": "Feature",
  "properties": {
    "gn:admin1_code":"25",
    "gn:asciiname":"Nanlijiazhuang",
    "gn:country_code":"CN",
    "gn:dem":61,
    "gn:feature_class":"P",
    "gn:feature_code":"PPL",
    "gn:name":"Nanlijiazhuang",
    "gn:population":0,
    "gn:timezone":"Asia/Shanghai",
    "iso:country":"CN",
    "name:zho_x_preferred":[
        "\u5357\u674e\u5bb6\u5e84"
    ],
    "wof:name":"Nanlijiazhuang",
    "wof:placetype":"locality"
},
  "geometry": {"coordinates":[116.919,35.646],"type":"Point"}
}