{
  "type": "Feature",
  "properties": {
    "gn:admin1_code":"15.0",
    "gn:asciiname":"Huagou",
    "gn:country_code":"CN",
    "gn:dem":1937,
    "gn:feature_class":"P",
    "gn:feature_code":"PPL",
    "gn:name":"Huagou",
    "gn:population":0,
    "gn:timezone":"Asia/Shanghai",
    "iso:country":"CN",
    "name:und_x_variant":[
        "\u5316\u6c9f"
    ],
    "wof:name":"Huagou",
    "wof:placetype":"locality"
},
  "geometry": {"coordinates":[105.4744,35.53931],"type":"Point"}
}