{
  "type": "Feature",
  "properties": {
    "gn:admin1_code":"29",
    "gn:asciiname":"Xiabenpi",
    "gn:country_code":"CN",
    "gn:dem":2279,
    "gn:feature_class":"P",
    "gn:feature_code":"PPL",
    "gn:name":"Xiabenpi",
    "gn:population":0,
    "gn:timezone":"Asia/Shanghai",
    "iso:country":"CN",
    "name:zho_x_preferred":[
        "\u4e0b\u672c\u76ae"
    ],
    "wof:name":"Xiabenpi",
    "wof:placetype":"locality"
},
  "geometry": {"coordinates":[101.95399999999999,24.1706],"type":"Point"}
}