{
  "type": "Feature",
  "properties": {
    "gn:admin1_code":"24",
    "gn:asciiname":"Xiwozui",
    "gn:cc2":"CN",
    "gn:country_code":"CN",
    "gn:dem":1239,
    "gn:feature_class":"P",
    "gn:feature_code":"PPL",
    "gn:name":"Xiwozui",
    "gn:population":0,
    "gn:timezone":"Asia/Shanghai",
    "iso:country":"CN",
    "name:und_x_variant":[
        "Hsi-wo-tsui",
        "Xiwozui"
    ],
    "wof:name":"Xiwozui",
    "wof:placetype":"locality"
},
  "geometry": {"coordinates":[113.11667,40.01667],"type":"Point"}
}