{
  "type": "Feature",
  "properties": {
    "gn:admin1_code":"12.0",
    "gn:asciiname":"Tuanchengshan",
    "gn:country_code":"CN",
    "gn:dem":25,
    "gn:feature_class":"P",
    "gn:feature_code":"PPLA4",
    "gn:name":"Tuanchengshan",
    "gn:population":0,
    "gn:timezone":"Asia/Shanghai",
    "iso:country":"CN",
    "name:und_x_variant":[
        "\u56e2\u57ce\u5c71"
    ],
    "name:zho_x_preferred":[
        "Tuanchengshan Jiedao"
    ],
    "name:zho_x_variant":[
        "\u56e2\u57ce\u5c71\u8857\u9053"
    ],
    "wof:name":"Tuanchengshan",
    "wof:placetype":"locality"
},
  "geometry": {"coordinates":[115.02867999999999,30.20192],"type":"Point"}
}