{
  "type": "Feature",
  "properties": {
    "gn:admin1_code":"18.0",
    "gn:asciiname":"Zaimen",
    "gn:country_code":"CN",
    "gn:dem":816,
    "gn:feature_class":"P",
    "gn:feature_code":"PPL",
    "gn:name":"Zaimen",
    "gn:population":0,
    "gn:timezone":"Asia/Shanghai",
    "iso:country":"CN",
    "name:zho_x_preferred":[
        "\u5bb0\u95f7"
    ],
    "wof:name":"Zaimen",
    "wof:placetype":"locality"
},
  "geometry": {"coordinates":[108.65300000000001,26.0103],"type":"Point"}
}