{
  "type": "Feature",
  "properties": {
    "gn:admin1_code":"30.0",
    "gn:asciiname":"Xiayunzhou",
    "gn:country_code":"CN",
    "gn:dem":137,
    "gn:feature_class":"P",
    "gn:feature_code":"PPL",
    "gn:name":"Xiayunzhou",
    "gn:population":0,
    "gn:timezone":"Asia/Shanghai",
    "iso:country":"CN",
    "name:zho_x_preferred":[
        "\u4e0b\u4e91\u6d32"
    ],
    "wof:name":"Xiayunzhou",
    "wof:placetype":"locality"
},
  "geometry": {"coordinates":[112.31138,23.40598],"type":"Point"}
}