{
  "type": "Feature",
  "properties": {
    "gn:admin1_code":"22",
    "gn:asciiname":"Donggaocun",
    "gn:country_code":"CN",
    "gn:dem":31,
    "gn:feature_class":"P",
    "gn:feature_code":"PPLA4",
    "gn:name":"Donggaocun",
    "gn:population":0,
    "gn:timezone":"Asia/Shanghai",
    "iso:country":"CN",
    "name:und_x_variant":[
        "Tung-kao-chuang",
        "Tung-kao-ts\u2019un",
        "Donggaocun",
        "Donggaocun Zhen"
    ],
    "name:zho_x_preferred":[
        "\u4e1c\u9ad8\u6751"
    ],
    "name:zho_x_variant":[
        "\u4e1c\u9ad8\u6751\u9547"
    ],
    "wof:name":"Donggaocun",
    "wof:placetype":"locality"
},
  "geometry": {"coordinates":[117.11190000000001,40.10653],"type":"Point"}
}