{
  "type": "Feature",
  "properties": {
    "gn:admin1_code":"32.0",
    "gn:asciiname":"Yeze",
    "gn:country_code":"CN",
    "gn:dem":4312,
    "gn:feature_class":"P",
    "gn:feature_code":"PPL",
    "gn:name":"Yeze",
    "gn:population":0,
    "gn:timezone":"Asia/Shanghai",
    "iso:country":"CN",
    "name:zho_x_preferred":[
        "\u53f6\u6cfd"
    ],
    "wof:name":"Yeze",
    "wof:placetype":"locality"
},
  "geometry": {"coordinates":[100.066,28.1069],"type":"Point"}
}