{
  "type": "Feature",
  "properties": {
    "gn:admin1_code":"1.0",
    "gn:asciiname":"Yudayingcun",
    "gn:country_code":"CN",
    "gn:dem":24,
    "gn:feature_class":"P",
    "gn:feature_code":"PPL",
    "gn:name":"Yudayingcun",
    "gn:population":0,
    "gn:timezone":"Asia/Shanghai",
    "iso:country":"CN",
    "name:zho_x_preferred":[
        "\u4f59\u5927\u90e2\u6751"
    ],
    "wof:name":"Yudayingcun",
    "wof:placetype":"locality"
},
  "geometry": {"coordinates":[117.01895,32.9889],"type":"Point"}
}