{
  "type": "Feature",
  "properties": {
    "gn:admin1_code":"24",
    "gn:asciiname":"Xiawuqi",
    "gn:country_code":"CN",
    "gn:dem":1154,
    "gn:feature_class":"P",
    "gn:feature_code":"PPL",
    "gn:name":"Xiawuqi",
    "gn:population":0,
    "gn:timezone":"Asia/Shanghai",
    "iso:country":"CN",
    "name:und_x_variant":[
        "Hsia-wu-ch\u2019i",
        "Xiawuqi"
    ],
    "name:zho_x_preferred":[
        "\u4e0b\u543e\u5176"
    ],
    "wof:name":"Xiawuqi",
    "wof:placetype":"locality"
},
  "geometry": {"coordinates":[113.89691000000001,40.19995],"type":"Point"}
}