{
  "type": "Feature",
  "properties": {
    "gn:admin1_code":"32.0",
    "gn:asciiname":"Daban",
    "gn:country_code":"CN",
    "gn:dem":3250,
    "gn:feature_class":"P",
    "gn:feature_code":"PPL",
    "gn:name":"Daban",
    "gn:population":0,
    "gn:timezone":"Asia/Shanghai",
    "iso:country":"CN",
    "name:ceb_x_preferred":[
        "Daban"
    ],
    "name:swe_x_preferred":[
        "Daban"
    ],
    "name:zho_x_preferred":[
        "\u5927\u677f"
    ],
    "wof:name":"Daban",
    "wof:placetype":"locality"
},
  "geometry": {"coordinates":[102.41963,31.53727],"type":"Point"}
}