{
  "type": "Feature",
  "properties": {
    "gn:admin1_code":"32.0",
    "gn:asciiname":"Niduo",
    "gn:country_code":"CN",
    "gn:dem":2495,
    "gn:feature_class":"P",
    "gn:feature_code":"PPL",
    "gn:name":"Niduo",
    "gn:population":0,
    "gn:timezone":"Asia/Shanghai",
    "iso:country":"CN",
    "name:zho_x_preferred":[
        "\u5c3c\u591a"
    ],
    "wof:name":"Niduo",
    "wof:placetype":"locality"
},
  "geometry": {"coordinates":[100.87757000000001,28.20197000000001],"type":"Point"}
}