{
  "type": "Feature",
  "properties": {
    "gn:admin1_code":"15.0",
    "gn:asciiname":"Wenjiapo",
    "gn:country_code":"CN",
    "gn:dem":1921,
    "gn:feature_class":"P",
    "gn:feature_code":"PPL",
    "gn:name":"Wenjiapo",
    "gn:population":0,
    "gn:timezone":"Asia/Shanghai",
    "iso:country":"CN",
    "name:und_x_variant":[
        "\u6e29\u5bb6\u5761"
    ],
    "wof:name":"Wenjiapo",
    "wof:placetype":"locality"
},
  "geometry": {"coordinates":[104.82253,34.6699],"type":"Point"}
}