{
  "type": "Feature",
  "properties": {
    "gn:admin1_code":"01",
    "gn:asciiname":"Tongcheng",
    "gn:country_code":"CN",
    "gn:dem":18,
    "gn:feature_class":"P",
    "gn:feature_code":"PPLA4",
    "gn:name":"Tongcheng",
    "gn:population":0,
    "gn:timezone":"Asia/Shanghai",
    "iso:country":"CN",
    "name:und_x_variant":[
        "T\u2019ung-ch\u2019eng-chen",
        "T\u2019ung-ch\u2019eng",
        "Tongcheng",
        "Tongcheng Zhen"
    ],
    "name:zho_x_preferred":[
        "\u94dc\u57ce"
    ],
    "wof:name":"Tongcheng",
    "wof:placetype":"locality"
},
  "geometry": {"coordinates":[118.93203,32.89848],"type":"Point"}
}