{
  "type": "Feature",
  "properties": {
    "gn:admin1_code":"19.0",
    "gn:asciiname":"Xiyingzi",
    "gn:country_code":"CN",
    "gn:dem":35,
    "gn:feature_class":"P",
    "gn:feature_code":"PPL",
    "gn:name":"Xiyingzi",
    "gn:population":0,
    "gn:timezone":"Asia/Shanghai",
    "iso:country":"CN",
    "name:zho_x_preferred":[
        "\u897f\u8425\u5b50"
    ],
    "wof:name":"Xiyingzi",
    "wof:placetype":"locality"
},
  "geometry": {"coordinates":[122.5677,41.92482],"type":"Point"}
}