{
  "type": "Feature",
  "properties": {
    "gn:admin1_code":"3.0",
    "gn:asciiname":"Chengtangwu",
    "gn:country_code":"CN",
    "gn:dem":187,
    "gn:feature_class":"P",
    "gn:feature_code":"PPL",
    "gn:name":"Chengtangwu",
    "gn:population":0,
    "gn:timezone":"Asia/Shanghai",
    "iso:country":"CN",
    "name:zho_x_preferred":[
        "\u7a0b\u5858\u575e"
    ],
    "wof:name":"Chengtangwu",
    "wof:placetype":"locality"
},
  "geometry": {"coordinates":[117.5478,28.4636],"type":"Point"}
}