{
  "type": "Feature",
  "properties": {
    "gn:admin1_code":"7",
    "gn:asciiname":"Yuyao",
    "gn:country_code":"CN",
    "gn:dem":15,
    "gn:feature_class":"P",
    "gn:feature_code":"PPL",
    "gn:name":"Yuyao",
    "gn:population":0,
    "gn:timezone":"Asia/Shanghai",
    "iso:country":"CN",
    "name:zho_x_preferred":[
        "\u7389\u7476"
    ],
    "wof:name":"Yuyao",
    "wof:placetype":"locality"
},
  "geometry": {"coordinates":[119.56543000000001,25.53164],"type":"Point"}
}