{
  "type": "Feature",
  "properties": {
    "gn:admin1_code":"29.0",
    "gn:asciiname":"Pengding",
    "gn:country_code":"CN",
    "gn:dem":2609,
    "gn:feature_class":"P",
    "gn:feature_code":"PPL",
    "gn:name":"Pengding",
    "gn:population":0,
    "gn:timezone":"Asia/Shanghai",
    "iso:country":"CN",
    "name:zho_x_preferred":[
        "\u5f6d\u4e01"
    ],
    "wof:name":"Pengding",
    "wof:placetype":"locality"
},
  "geometry": {"coordinates":[99.69499999999999,28.612],"type":"Point"}
}