{
  "type": "Feature",
  "properties": {
    "gn:admin1_code":"15.0",
    "gn:asciiname":"Xiyuan",
    "gn:country_code":"CN",
    "gn:dem":1044,
    "gn:feature_class":"P",
    "gn:feature_code":"PPL",
    "gn:name":"Xiyuan",
    "gn:population":0,
    "gn:timezone":"Asia/Shanghai",
    "iso:country":"CN",
    "name:und_x_variant":[
        "\u897f\u5143"
    ],
    "name:zho_x_preferred":[
        "\u897f\u5143"
    ],
    "wof:name":"Xiyuan",
    "wof:placetype":"locality"
},
  "geometry": {"coordinates":[104.66271,32.95598],"type":"Point"}
}