{
  "type": "Feature",
  "properties": {
    "gn:admin1_code":"7",
    "gn:asciiname":"Xinju",
    "gn:country_code":"CN",
    "gn:dem":32,
    "gn:feature_class":"P",
    "gn:feature_code":"PPL",
    "gn:name":"Xinju",
    "gn:population":0,
    "gn:timezone":"Asia/Shanghai",
    "iso:country":"CN",
    "name:und_x_variant":[
        "Hsin-ch\u00fc",
        "Xinju"
    ],
    "name:zho_x_preferred":[
        "\u65b0\u5c40"
    ],
    "wof:name":"Xinju",
    "wof:placetype":"locality"
},
  "geometry": {"coordinates":[119.39469,25.76512],"type":"Point"}
}