{
  "type": "Feature",
  "properties": {
    "gn:admin1_code":"10.0",
    "gn:asciiname":"Duanbu'ao",
    "gn:country_code":"CN",
    "gn:dem":1217,
    "gn:feature_class":"P",
    "gn:feature_code":"PPL",
    "gn:name":"Duanbu\u2019ao",
    "gn:population":0,
    "gn:timezone":"Asia/Shanghai",
    "iso:country":"CN",
    "name:und_x_variant":[
        "Duanbu\u2019ao"
    ],
    "name:zho_x_preferred":[
        "\u6bb5\u535c\u51f9"
    ],
    "wof:name":"Duanbu'ao",
    "wof:placetype":"locality"
},
  "geometry": {"coordinates":[113.87636000000001,38.80257],"type":"Point"}
}