{
  "type": "Feature",
  "properties": {
    "gn:admin1_code":"7",
    "gn:asciiname":"Zhoutou",
    "gn:country_code":"CN",
    "gn:dem":9,
    "gn:feature_class":"P",
    "gn:feature_code":"PPL",
    "gn:name":"Zhoutou",
    "gn:population":0,
    "gn:timezone":"Asia/Shanghai",
    "iso:country":"CN",
    "name:zho_x_preferred":[
        "\u6d32\u5934"
    ],
    "wof:name":"Zhoutou",
    "wof:placetype":"locality"
},
  "geometry": {"coordinates":[119.2456,25.94709],"type":"Point"}
}