{
  "type": "Feature",
  "properties": {
    "gn:admin1_code":"30.0",
    "gn:asciiname":"Nachajiu",
    "gn:country_code":"CN",
    "gn:dem":68,
    "gn:feature_class":"P",
    "gn:feature_code":"PPL",
    "gn:name":"Nachajiu",
    "gn:population":0,
    "gn:timezone":"Asia/Urumqi",
    "iso:country":"CN",
    "name:zho_x_preferred":[
        "\u90a3\u5bdf\u65e7"
    ],
    "wof:name":"Nachajiu",
    "wof:placetype":"locality"
},
  "geometry": {"coordinates":[110.31644,20.37131],"type":"Point"}
}