{
  "type": "Feature",
  "properties": {
    "gn:admin1_code":"3.0",
    "gn:asciiname":"Gaoqikeng",
    "gn:country_code":"CN",
    "gn:dem":589,
    "gn:feature_class":"P",
    "gn:feature_code":"PPL",
    "gn:name":"Gaoqikeng",
    "gn:population":0,
    "gn:timezone":"Asia/Shanghai",
    "iso:country":"CN",
    "name:und_x_variant":[
        "\u9ad8\u78dc\u5751"
    ],
    "wof:name":"Gaoqikeng",
    "wof:placetype":"locality"
},
  "geometry": {"coordinates":[116.41406000000001,26.31146],"type":"Point"}
}