{
  "type": "Feature",
  "properties": {
    "gn:admin1_code":"14.0",
    "gn:asciiname":"Aolong",
    "gn:country_code":"CN",
    "gn:dem":2981,
    "gn:feature_class":"P",
    "gn:feature_code":"PPL",
    "gn:name":"Aolong",
    "gn:population":0,
    "gn:timezone":"Asia/Urumqi",
    "iso:country":"CN",
    "name:zho_x_preferred":[
        "\u50b2\u9f99"
    ],
    "wof:name":"Aolong",
    "wof:placetype":"locality"
},
  "geometry": {"coordinates":[97.99333,30.132],"type":"Point"}
}