{
  "type": "Feature",
  "properties": {
    "gn:admin1_code":"24.0",
    "gn:asciiname":"Wengchengkou",
    "gn:country_code":"CN",
    "gn:dem":1120,
    "gn:feature_class":"P",
    "gn:feature_code":"PPL",
    "gn:name":"Wengchengkou",
    "gn:population":0,
    "gn:timezone":"Asia/Shanghai",
    "iso:country":"CN",
    "name:und_x_variant":[
        "\u74ee\u57ce\u53e3"
    ],
    "name:zho_x_preferred":[
        "\u74ee\u57ce\u53e3"
    ],
    "wof:name":"Wengchengkou",
    "wof:placetype":"locality"
},
  "geometry": {"coordinates":[113.46775,39.81635],"type":"Point"}
}