{
  "type": "Feature",
  "properties": {
    "gn:admin1_code":"21.0",
    "gn:asciiname":"Malugou",
    "gn:country_code":"CN",
    "gn:dem":2308,
    "gn:feature_class":"P",
    "gn:feature_code":"PPL",
    "gn:name":"Malugou",
    "gn:population":0,
    "gn:timezone":"Asia/Shanghai",
    "iso:country":"CN",
    "name:zho_x_preferred":[
        "\u9a6c\u9e7f\u6c9f"
    ],
    "wof:name":"Malugou",
    "wof:placetype":"locality"
},
  "geometry": {"coordinates":[106.208,35.4631],"type":"Point"}
}