{
  "type": "Feature",
  "properties": {
    "gn:admin1_code":"16",
    "gn:asciiname":"Longgongshui",
    "gn:country_code":"CN",
    "gn:dem":265,
    "gn:feature_class":"P",
    "gn:feature_code":"PPL",
    "gn:name":"Longgongshui",
    "gn:population":0,
    "gn:timezone":"Asia/Shanghai",
    "iso:country":"CN",
    "name:zho_x_preferred":[
        "\u9f99\u5bab\u6c34"
    ],
    "wof:name":"Longgongshui",
    "wof:placetype":"locality"
},
  "geometry": {"coordinates":[110.119,25.9009],"type":"Point"}
}