{
  "type": "Feature",
  "properties": {
    "gn:admin1_code":"4.0",
    "gn:asciiname":"Youyi",
    "gn:country_code":"CN",
    "gn:dem":21,
    "gn:feature_class":"P",
    "gn:feature_code":"PPL",
    "gn:name":"Youyi",
    "gn:population":0,
    "gn:timezone":"Asia/Shanghai",
    "iso:country":"CN",
    "name:ceb_x_preferred":[
        "Youyi"
    ],
    "name:deu_x_preferred":[
        "Youyi"
    ],
    "name:zho_x_preferred":[
        "\u53cb\u8c0a"
    ],
    "name:zho_x_variant":[
        "\u53cb\u8abc"
    ],
    "wof:name":"Youyi",
    "wof:placetype":"locality"
},
  "geometry": {"coordinates":[119.3252,32.42475],"type":"Point"}
}