{
  "type": "Feature",
  "properties": {
    "gn:admin1_code":"9",
    "gn:asciiname":"Zuojia",
    "gn:country_code":"CN",
    "gn:dem":51,
    "gn:feature_class":"P",
    "gn:feature_code":"PPL",
    "gn:name":"Zuojia",
    "gn:population":0,
    "gn:timezone":"Asia/Shanghai",
    "iso:country":"CN",
    "name:zho_x_preferred":[
        "\u5de6\u5bb6"
    ],
    "wof:name":"Zuojia",
    "wof:placetype":"locality"
},
  "geometry": {"coordinates":[115.26300000000001,35.9516],"type":"Point"}
}