{
  "type": "Feature",
  "properties": {
    "gn:admin1_code":"1.0",
    "gn:asciiname":"Lingguang",
    "gn:country_code":"CN",
    "gn:dem":404,
    "gn:feature_class":"P",
    "gn:feature_code":"PPL",
    "gn:name":"Lingguang",
    "gn:population":0,
    "gn:timezone":"Asia/Shanghai",
    "iso:country":"CN",
    "name:zho_x_preferred":[
        "\u9675\u5149"
    ],
    "wof:name":"Lingguang",
    "wof:placetype":"locality"
},
  "geometry": {"coordinates":[118.14841,29.92063],"type":"Point"}
}