{
  "type": "Feature",
  "properties": {
    "gn:admin1_code":"13",
    "gn:asciiname":"Ayidingkule",
    "gn:country_code":"CN",
    "gn:dem":1316,
    "gn:feature_class":"P",
    "gn:feature_code":"PPL",
    "gn:name":"Ayidingkule",
    "gn:population":0,
    "gn:timezone":"Asia/Shanghai",
    "iso:country":"CN",
    "name:und_x_variant":[
        "\u963f\u4f9d\u4e01\u5e93\u52d2"
    ],
    "wof:name":"Ayidingkule",
    "wof:placetype":"locality"
},
  "geometry": {"coordinates":[77.37066999999998,37.94694000000001],"type":"Point"}
}