{
  "type": "Feature",
  "properties": {
    "gn:admin1_code":"16.0",
    "gn:asciiname":"Yanka",
    "gn:country_code":"CN",
    "gn:dem":865,
    "gn:feature_class":"P",
    "gn:feature_code":"PPL",
    "gn:name":"Yanka",
    "gn:population":0,
    "gn:timezone":"Asia/Shanghai",
    "iso:country":"CN",
    "name:bel_x_preferred":[
        "\u042f\u043d\u043a\u0430"
    ],
    "name:ceb_x_preferred":[
        "Yanka"
    ],
    "name:fra_x_preferred":[
        "Yanka"
    ],
    "name:rus_x_preferred":[
        "\u042f\u043d\u043a\u0430"
    ],
    "name:swe_x_preferred":[
        "Yanka"
    ],
    "name:ukr_x_preferred":[
        "\u042f\u043d\u043a\u0430"
    ],
    "name:zho_x_preferred":[
        "\u5ca9\u5361"
    ],
    "wof:name":"Yanka",
    "wof:placetype":"locality"
},
  "geometry": {"coordinates":[105.077,24.8989],"type":"Point"}
}