{
  "type": "Feature",
  "properties": {
    "gn:admin1_code":"7",
    "gn:asciiname":"Xiongzhuang",
    "gn:country_code":"CN",
    "gn:dem":647,
    "gn:feature_class":"P",
    "gn:feature_code":"PPL",
    "gn:name":"Xiongzhuang",
    "gn:population":0,
    "gn:timezone":"Asia/Shanghai",
    "iso:country":"CN",
    "name:und_x_variant":[
        "\u718a\u72b6",
        "Xiongzhuang"
    ],
    "wof:name":"Xiongzhuang",
    "wof:placetype":"locality"
},
  "geometry": {"coordinates":[119.85563,27.29339],"type":"Point"}
}