{
  "type": "Feature",
  "properties": {
    "gn:admin1_code":"26.0",
    "gn:asciiname":"Dayinxinggou",
    "gn:country_code":"CN",
    "gn:dem":799,
    "gn:feature_class":"P",
    "gn:feature_code":"PPL",
    "gn:name":"Dayinxinggou",
    "gn:population":0,
    "gn:timezone":"Asia/Shanghai",
    "iso:country":"CN",
    "name:zho_x_preferred":[
        "\u5927\u94f6\u674f\u6c9f"
    ],
    "wof:name":"Dayinxinggou",
    "wof:placetype":"locality"
},
  "geometry": {"coordinates":[108.68004999999999,32.45327],"type":"Point"}
}