{
  "type": "Feature",
  "properties": {
    "gn:admin1_code":"3.0",
    "gn:asciiname":"Taipingwucun",
    "gn:country_code":"CN",
    "gn:dem":22,
    "gn:feature_class":"P",
    "gn:feature_code":"PPL",
    "gn:name":"Taipingwucun",
    "gn:population":0,
    "gn:timezone":"Asia/Shanghai",
    "iso:country":"CN",
    "name:und_x_variant":[
        "\u592a\u5e73\u5434\u6751"
    ],
    "wof:name":"Taipingwucun",
    "wof:placetype":"locality"
},
  "geometry": {"coordinates":[116.02988000000001,28.60531],"type":"Point"}
}