{
  "type": "Feature",
  "properties": {
    "gn:admin1_code":"11.0",
    "gn:asciiname":"Yuefuguai",
    "gn:country_code":"CN",
    "gn:dem":36,
    "gn:feature_class":"P",
    "gn:feature_code":"PPL",
    "gn:name":"Yuefuguai",
    "gn:population":0,
    "gn:timezone":"Asia/Shanghai",
    "iso:country":"CN",
    "name:zho_x_preferred":[
        "Yuefuguai"
    ],
    "name:zho_x_variant":[
        "\u4e50\u5e9c\u62d0"
    ],
    "wof:name":"Yuefuguai",
    "wof:placetype":"locality"
},
  "geometry": {"coordinates":[112.02828999999998,29.50152000000001],"type":"Point"}
}