{
  "type": "Feature",
  "properties": {
    "gn:admin1_code":"5.0",
    "gn:asciiname":"Shisanhaocun",
    "gn:country_code":"CN",
    "gn:dem":216,
    "gn:feature_class":"P",
    "gn:feature_code":"PPL",
    "gn:name":"Shisanhaocun",
    "gn:population":0,
    "gn:timezone":"Asia/Shanghai",
    "iso:country":"CN",
    "name:zho_x_preferred":[
        "\u5341\u4e09\u53f7\u6751"
    ],
    "wof:name":"Shisanhaocun",
    "wof:placetype":"locality"
},
  "geometry": {"coordinates":[126.30911999999999,45.01258],"type":"Point"}
}