{
  "type": "Feature",
  "properties": {
    "gn:admin1_code":"5.0",
    "gn:asciiname":"Sandaogoucun",
    "gn:country_code":"CN",
    "gn:dem":145,
    "gn:feature_class":"P",
    "gn:feature_code":"PPL",
    "gn:name":"Sandaogoucun",
    "gn:population":0,
    "gn:timezone":"Asia/Shanghai",
    "iso:country":"CN",
    "name:zho_x_preferred":[
        "\u4e09\u9053\u6c9f\u6751"
    ],
    "wof:name":"Sandaogoucun",
    "wof:placetype":"locality"
},
  "geometry": {"coordinates":[129.76419000000001,43.17256],"type":"Point"}
}