{
  "type": "Feature",
  "properties": {
    "gn:admin1_code":"25.0",
    "gn:asciiname":"Shanmabucun",
    "gn:country_code":"CN",
    "gn:dem":47,
    "gn:feature_class":"P",
    "gn:feature_code":"PPL",
    "gn:name":"Shanmabucun",
    "gn:population":0,
    "gn:timezone":"Asia/Shanghai",
    "iso:country":"CN",
    "name:zho_x_preferred":[
        "\u5c71\u9a6c\u57e0\u6751"
    ],
    "wof:name":"Shanmabucun",
    "wof:placetype":"locality"
},
  "geometry": {"coordinates":[122.01268,37.28258],"type":"Point"}
}