{
  "type": "Feature",
  "properties": {
    "gn:admin1_code":"16",
    "gn:asciiname":"Gengxin",
    "gn:cc2":"CN",
    "gn:country_code":"CN",
    "gn:dem":467,
    "gn:feature_class":"P",
    "gn:feature_code":"PPL",
    "gn:name":"Gengxin",
    "gn:population":0,
    "gn:timezone":"Asia/Shanghai",
    "iso:country":"CN",
    "name:und_x_variant":[
        "Keng-hsin",
        "Gengxin"
    ],
    "wof:name":"Gengxin",
    "wof:placetype":"locality"
},
  "geometry": {"coordinates":[106.86667,24.68333],"type":"Point"}
}