{
  "type": "Feature",
  "properties": {
    "gn:admin1_code":"11.0",
    "gn:asciiname":"Liufangwan",
    "gn:country_code":"CN",
    "gn:dem":154,
    "gn:feature_class":"P",
    "gn:feature_code":"PPL",
    "gn:name":"Liufangwan",
    "gn:population":0,
    "gn:timezone":"Asia/Shanghai",
    "iso:country":"CN",
    "name:zho_x_preferred":[
        "\u516d\u623f\u6e7e"
    ],
    "wof:name":"Liufangwan",
    "wof:placetype":"locality"
},
  "geometry": {"coordinates":[113.60487999999999,28.19871],"type":"Point"}
}