{
  "type": "Feature",
  "properties": {
    "gn:admin1_code":"30",
    "gn:asciiname":"Fucheng",
    "gn:country_code":"CN",
    "gn:dem":63,
    "gn:feature_class":"P",
    "gn:feature_code":"PPLA4",
    "gn:name":"Fucheng",
    "gn:population":0,
    "gn:timezone":"Asia/Shanghai",
    "iso:country":"CN",
    "name:ceb_x_preferred":[
        "Fucheng"
    ],
    "name:deu_x_preferred":[
        "Fucheng"
    ],
    "name:fra_x_preferred":[
        "Fucheng"
    ],
    "name:nor_x_preferred":[
        "Fucheng"
    ],
    "name:swe_x_preferred":[
        "Fucheng"
    ],
    "name:und_x_variant":[
        "\u9644\u57ce",
        "Fucheng Zhen",
        "\u9644\u57ce\u9547"
    ],
    "wof:name":"Fucheng",
    "wof:placetype":"locality"
},
  "geometry": {"coordinates":[115.23154,24.10015],"type":"Point"}
}