{
  "type": "Feature",
  "properties": {
    "gn:country":"CN",
    "gn:fcode":"ADM3",
    "gn:population":0,
    "iso:country":"CN",
    "name:und_x_variant":[
        "Hsing-i Hsien"
    ],
    "name:zho_x_preferred":[
        "\u5174\u4e49\u5e02"
    ],
    "name:zho_x_variant":[
        "\u5174\u4e49"
    ],
    "qs:name":"Xingyi Shi",
    "qs:photos_9r":0,
    "qs:photos_sr":0,
    "qs:pop_sr":"0",
    "wof:name":"Xingyi Shi",
    "wof:placetype":"localadmin",
    "wof:population":0
},
  "geometry": {"coordinates":[104.7954,25.0997],"type":"Point"}
}