{
  "type": "Feature",
  "properties": {
    "gn:admin1_code":"11.0",
    "gn:asciiname":"Chenlongjie",
    "gn:country_code":"CN",
    "gn:dem":261,
    "gn:feature_class":"P",
    "gn:feature_code":"PPL",
    "gn:name":"Chenlongjie",
    "gn:population":0,
    "gn:timezone":"Asia/Shanghai",
    "iso:country":"CN",
    "name:zho_x_preferred":[
        "\u9648\u9f99\u754c"
    ],
    "wof:name":"Chenlongjie",
    "wof:placetype":"locality"
},
  "geometry": {"coordinates":[110.47183,28.4647],"type":"Point"}
}