{
  "type": "Feature",
  "properties": {
    "gn:admin1_code":"25.0",
    "gn:asciiname":"Zhengjiazhuangcun",
    "gn:country_code":"CN",
    "gn:dem":12,
    "gn:feature_class":"P",
    "gn:feature_code":"PPL",
    "gn:name":"Zhengjiazhuangcun",
    "gn:population":0,
    "gn:timezone":"Asia/Shanghai",
    "iso:country":"CN",
    "name:zho_x_preferred":[
        "\u90d1\u5bb6\u5e84\u6751"
    ],
    "wof:name":"Zhengjiazhuangcun",
    "wof:placetype":"locality"
},
  "geometry": {"coordinates":[119.61951999999999,36.50288],"type":"Point"}
}