{
  "type": "Feature",
  "properties": {
    "gn:admin1_code":"7.0",
    "gn:asciiname":"Duiguo",
    "gn:country_code":"CN",
    "gn:dem":214,
    "gn:feature_class":"P",
    "gn:feature_code":"PPL",
    "gn:name":"Duiguo",
    "gn:population":0,
    "gn:timezone":"Asia/Shanghai",
    "iso:country":"CN",
    "name:zho_x_preferred":[
        "\u5bf9\u8fc7"
    ],
    "wof:name":"Duiguo",
    "wof:placetype":"locality"
},
  "geometry": {"coordinates":[118.00991,27.30418],"type":"Point"}
}