{
  "type": "Feature",
  "properties": {
    "gn:admin1_code":"8.0",
    "gn:asciiname":"Qubaihuchangtun",
    "gn:country_code":"CN",
    "gn:dem":235,
    "gn:feature_class":"P",
    "gn:feature_code":"PPL",
    "gn:name":"Qubaihuchangtun",
    "gn:population":0,
    "gn:timezone":"Asia/Shanghai",
    "iso:country":"CN",
    "name:zho_x_preferred":[
        "\u66f2\u767e\u6237\u957f\u5c6f"
    ],
    "wof:name":"Qubaihuchangtun",
    "wof:placetype":"locality"
},
  "geometry": {"coordinates":[125.80199,47.06726],"type":"Point"}
}