{
  "type": "Feature",
  "properties": {
    "gn:admin1_code":"19.0",
    "gn:asciiname":"Erdao Fangzicun",
    "gn:country_code":"CN",
    "gn:dem":105,
    "gn:feature_class":"P",
    "gn:feature_code":"PPL",
    "gn:name":"Erdao Fangzicun",
    "gn:population":0,
    "gn:timezone":"Asia/Shanghai",
    "iso:country":"CN",
    "name:und_x_variant":[
        "Erdaofangzicun",
        "Erdao Fangzicun"
    ],
    "name:zho_x_preferred":[
        "\u4e8c\u9053\u623f\u5b50\u6751"
    ],
    "wof:name":"Erdao Fangzicun",
    "wof:placetype":"locality"
},
  "geometry": {"coordinates":[119.98718999999998,40.49136],"type":"Point"}
}