{
  "type": "Feature",
  "properties": {
    "gn:admin1_code":"4.0",
    "gn:asciiname":"Zhangjialaoyuan",
    "gn:country_code":"CN",
    "gn:dem":5,
    "gn:feature_class":"P",
    "gn:feature_code":"PPL",
    "gn:name":"Zhangjialaoyuan",
    "gn:population":0,
    "gn:timezone":"Asia/Shanghai",
    "iso:country":"CN",
    "name:zho_x_preferred":[
        "Zhangjialaoyuan"
    ],
    "name:zho_x_variant":[
        "\u5f20\u5bb6\u8001\u9662"
    ],
    "wof:name":"Zhangjialaoyuan",
    "wof:placetype":"locality"
},
  "geometry": {"coordinates":[119.6073,33.91970999999999],"type":"Point"}
}