{
  "type": "Feature",
  "properties": {
    "gn:admin1_code":"21.0",
    "gn:asciiname":"Mi'alijing",
    "gn:country_code":"CN",
    "gn:dem":1113,
    "gn:feature_class":"P",
    "gn:feature_code":"PPL",
    "gn:name":"Mi\u2019alijing",
    "gn:population":0,
    "gn:timezone":"Asia/Shanghai",
    "iso:country":"CN",
    "name:und_x_variant":[
        "Mi\u2019alijing"
    ],
    "name:zho_x_preferred":[
        "\u7c73\u963f\u91cc\u4e95"
    ],
    "wof:name":"Mi'alijing",
    "wof:placetype":"locality"
},
  "geometry": {"coordinates":[106.81999999999999,38.8773],"type":"Point"}
}