{
  "type": "Feature",
  "properties": {
    "gn:admin1_code":"19.0",
    "gn:asciiname":"Dongjialincun",
    "gn:country_code":"CN",
    "gn:dem":441,
    "gn:feature_class":"P",
    "gn:feature_code":"PPL",
    "gn:name":"Dongjialincun",
    "gn:population":0,
    "gn:timezone":"Asia/Shanghai",
    "iso:country":"CN",
    "name:zho_x_preferred":[
        "\u8463\u5bb6\u6797\u6751"
    ],
    "wof:name":"Dongjialincun",
    "wof:placetype":"locality"
},
  "geometry": {"coordinates":[120.012,41.7199],"type":"Point"}
}