{
  "type": "Feature",
  "properties": {
    "gn:admin1_code":"11",
    "gn:asciiname":"Zhushan Yuanzi",
    "gn:country_code":"CN",
    "gn:dem":342,
    "gn:feature_class":"P",
    "gn:feature_code":"PPL",
    "gn:name":"Zhushan Yuanzi",
    "gn:population":0,
    "gn:timezone":"Asia/Shanghai",
    "iso:country":"CN",
    "name:zho_x_preferred":[
        "\u7af9\u5c71\u9662\u5b50"
    ],
    "wof:name":"Zhushan Yuanzi",
    "wof:placetype":"locality"
},
  "geometry": {"coordinates":[111.32089999999999,26.85933],"type":"Point"}
}