{
  "type": "Feature",
  "properties": {
    "gn:admin1_code":"20.0",
    "gn:asciiname":"Guo'enbo Getuo",
    "gn:country_code":"CN",
    "gn:dem":337,
    "gn:feature_class":"P",
    "gn:feature_code":"PPL",
    "gn:name":"Guo\u2019enbo Getuo",
    "gn:population":0,
    "gn:timezone":"Asia/Shanghai",
    "iso:country":"CN",
    "name:und_x_variant":[
        "Guo\u2019enbo Getuo"
    ],
    "name:zho_x_preferred":[
        "\u90ed\u6069\u535a\u683c\u6258"
    ],
    "wof:name":"Guo'enbo Getuo",
    "wof:placetype":"locality"
},
  "geometry": {"coordinates":[124.25469,49.10323],"type":"Point"}
}