{
  "type": "Feature",
  "properties": {
    "gn:admin1_code":"7.0",
    "gn:asciiname":"Baitaishan",
    "gn:country_code":"CN",
    "gn:dem":408,
    "gn:feature_class":"P",
    "gn:feature_code":"PPL",
    "gn:name":"Baitaishan",
    "gn:population":0,
    "gn:timezone":"Asia/Shanghai",
    "iso:country":"CN",
    "name:zho_x_preferred":[
        "\u767d\u592a\u5c71"
    ],
    "wof:name":"Baitaishan",
    "wof:placetype":"locality"
},
  "geometry": {"coordinates":[118.58523,28.01024],"type":"Point"}
}