{
  "type": "Feature",
  "properties": {
    "gn:admin1_code":"29.0",
    "gn:asciiname":"Songtian",
    "gn:country_code":"CN",
    "gn:dem":1572,
    "gn:feature_class":"P",
    "gn:feature_code":"PPL",
    "gn:name":"Songtian",
    "gn:population":0,
    "gn:timezone":"Asia/Shanghai",
    "iso:country":"CN",
    "name:und_x_variant":[
        "\u677e\u7530"
    ],
    "wof:name":"Songtian",
    "wof:placetype":"locality"
},
  "geometry": {"coordinates":[103.52276999999999,27.80707],"type":"Point"}
}