{
  "type": "Feature",
  "properties": {
    "gn:admin1_code":"9.0",
    "gn:asciiname":"Laofandian",
    "gn:country_code":"CN",
    "gn:dem":77,
    "gn:feature_class":"P",
    "gn:feature_code":"PPL",
    "gn:name":"Laofandian",
    "gn:population":0,
    "gn:timezone":"Asia/Shanghai",
    "iso:country":"CN",
    "name:zho_x_preferred":[
        "\u8001\u996d\u5e97"
    ],
    "wof:name":"Laofandian",
    "wof:placetype":"locality"
},
  "geometry": {"coordinates":[114.28523,34.67402],"type":"Point"}
}