{
  "type": "Feature",
  "properties": {
    "gn:admin1_code":"8.0",
    "gn:asciiname":"Limin Qidui",
    "gn:country_code":"CN",
    "gn:dem":236,
    "gn:feature_class":"P",
    "gn:feature_code":"PPLF",
    "gn:name":"Limin Qidui",
    "gn:population":0,
    "gn:timezone":"Asia/Shanghai",
    "iso:country":"CN",
    "name:zho_x_preferred":[
        "\u5229\u6c11\u4e03\u961f"
    ],
    "wof:name":"Limin Qidui",
    "wof:placetype":"locality"
},
  "geometry": {"coordinates":[125.86958,48.54034],"type":"Point"}
}