{
  "type": "Feature",
  "properties": {
    "gn:admin1_code":"25",
    "gn:asciiname":"Peiziyan",
    "gn:country_code":"CN",
    "gn:dem":64,
    "gn:feature_class":"P",
    "gn:feature_code":"PPL",
    "gn:name":"Peiziyan",
    "gn:population":0,
    "gn:timezone":"Asia/Shanghai",
    "iso:country":"CN",
    "name:zho_x_preferred":[
        "\u88f4\u5b50\u5ca9"
    ],
    "wof:name":"Peiziyan",
    "wof:placetype":"locality"
},
  "geometry": {"coordinates":[115.041,35.0825],"type":"Point"}
}