{
  "type": "Feature",
  "properties": {
    "gn:admin1_code":"19",
    "gn:asciiname":"Ping-kou-tzu",
    "gn:country_code":"CN",
    "gn:dem":428,
    "gn:feature_class":"P",
    "gn:feature_code":"PPL",
    "gn:name":"Ping-kou-tzu",
    "gn:population":0,
    "gn:timezone":"Asia/Shanghai",
    "iso:country":"CN",
    "wof:name":"Ping-kou-tzu",
    "wof:placetype":"locality"
},
  "geometry": {"coordinates":[125.15722,41.02306],"type":"Point"}
}