{
  "type": "Feature",
  "properties": {
    "gn:admin1_code":"1.0",
    "gn:asciiname":"Wangcaocun",
    "gn:country_code":"CN",
    "gn:dem":331,
    "gn:feature_class":"P",
    "gn:feature_code":"PPL",
    "gn:name":"Wangcaocun",
    "gn:population":0,
    "gn:timezone":"Asia/Shanghai",
    "iso:country":"CN",
    "name:zho_x_preferred":[
        "\u671b\u66f9\u6751"
    ],
    "wof:name":"Wangcaocun",
    "wof:placetype":"locality"
},
  "geometry": {"coordinates":[116.77292,31.02908],"type":"Point"}
}