{
  "type": "Feature",
  "properties": {
    "gn:admin1_code":"8.0",
    "gn:asciiname":"Xiao Liudui",
    "gn:country_code":"CN",
    "gn:dem":139,
    "gn:feature_class":"P",
    "gn:feature_code":"PPLF",
    "gn:name":"Xiao Liudui",
    "gn:population":0,
    "gn:timezone":"Asia/Shanghai",
    "iso:country":"CN",
    "name:zho_x_preferred":[
        "\u5c0f\u516d\u961f"
    ],
    "wof:name":"Xiao Liudui",
    "wof:placetype":"locality"
},
  "geometry": {"coordinates":[129.74723999999998,45.82224],"type":"Point"}
}