{
  "type": "Feature",
  "properties": {
    "gn:admin1_code":"32.0",
    "gn:asciiname":"Huashengou",
    "gn:country_code":"CN",
    "gn:dem":455,
    "gn:feature_class":"P",
    "gn:feature_code":"PPL",
    "gn:name":"Huashengou",
    "gn:population":0,
    "gn:timezone":"Asia/Shanghai",
    "iso:country":"CN",
    "name:zho_x_preferred":[
        "\u5212\u795e\u6c9f"
    ],
    "wof:name":"Huashengou",
    "wof:placetype":"locality"
},
  "geometry": {"coordinates":[103.56399999999999,29.7855],"type":"Point"}
}