{
  "type": "Feature",
  "properties": {
    "gn:admin1_code":"29.0",
    "gn:asciiname":"Yigengzhe",
    "gn:country_code":"CN",
    "gn:dem":1625,
    "gn:feature_class":"P",
    "gn:feature_code":"PPL",
    "gn:name":"Yigengzhe",
    "gn:population":0,
    "gn:timezone":"Asia/Shanghai",
    "iso:country":"CN",
    "name:zho_x_preferred":[
        "\u8fe4\u66f4\u8005"
    ],
    "wof:name":"Yigengzhe",
    "wof:placetype":"locality"
},
  "geometry": {"coordinates":[104.684,25.2403],"type":"Point"}
}