{
  "type": "Feature",
  "properties": {
    "gn:admin1_code":"30.0",
    "gn:asciiname":"Antang",
    "gn:country_code":"CN",
    "gn:dem":591,
    "gn:feature_class":"P",
    "gn:feature_code":"PPL",
    "gn:name":"Antang",
    "gn:population":0,
    "gn:timezone":"Asia/Shanghai",
    "iso:country":"CN",
    "name:zho_x_preferred":[
        "Antang"
    ],
    "name:zho_x_variant":[
        "\u5b89\u5858"
    ],
    "wof:name":"Antang",
    "wof:placetype":"locality"
},
  "geometry": {"coordinates":[112.04000000000001,24.48833],"type":"Point"}
}