{
  "type": "Feature",
  "properties": {
    "gn:admin1_code":"1.0",
    "gn:asciiname":"Jiangchencun",
    "gn:country_code":"CN",
    "gn:dem":24,
    "gn:feature_class":"P",
    "gn:feature_code":"PPL",
    "gn:name":"Jiangchencun",
    "gn:population":0,
    "gn:timezone":"Asia/Shanghai",
    "iso:country":"CN",
    "name:zho_x_preferred":[
        "\u6c5f\u9648\u6751"
    ],
    "wof:name":"Jiangchencun",
    "wof:placetype":"locality"
},
  "geometry": {"coordinates":[116.98444000000001,32.63459],"type":"Point"}
}