{
  "type": "Feature",
  "properties": {
    "gn:admin1_code":"24",
    "gn:asciiname":"Lirenpo",
    "gn:country_code":"CN",
    "gn:dem":605,
    "gn:feature_class":"P",
    "gn:feature_code":"PPL",
    "gn:name":"Lirenpo",
    "gn:population":0,
    "gn:timezone":"Asia/Shanghai",
    "iso:country":"CN",
    "name:und_x_variant":[
        "Li-jen-p\u2019o",
        "Lirenpo"
    ],
    "name:zho_x_preferred":[
        "\u91cc\u4ec1\u5761"
    ],
    "wof:name":"Lirenpo",
    "wof:placetype":"locality"
},
  "geometry": {"coordinates":[110.46929,36.36198],"type":"Point"}
}