{
  "type": "Feature",
  "properties": {
    "gn:admin1_code":"11.0",
    "gn:asciiname":"Majiaxi",
    "gn:country_code":"CN",
    "gn:dem":607,
    "gn:feature_class":"P",
    "gn:feature_code":"PPL",
    "gn:name":"Majiaxi",
    "gn:population":0,
    "gn:timezone":"Asia/Shanghai",
    "iso:country":"CN",
    "name:zho_x_preferred":[
        "\u9a6c\u5bb6\u6eaa"
    ],
    "wof:name":"Majiaxi",
    "wof:placetype":"locality"
},
  "geometry": {"coordinates":[110.02432,29.56389],"type":"Point"}
}