{
  "type": "Feature",
  "properties": {
    "gn:country":"CN",
    "gn:fcode":"PPLA4",
    "gn:pop":0,
    "iso:country":"CN",
    "name:deu_x_preferred":[
        "Anting"
    ],
    "name:eng_x_preferred":[
        "Anting"
    ],
    "name:fas_x_preferred":[
        "\u0627\u0646\u062a\u06cc\u0646\u06af"
    ],
    "name:fra_x_preferred":[
        "Anting"
    ],
    "name:jpn_x_preferred":[
        "\u5b89\u4ead\u93ae"
    ],
    "name:nld_x_preferred":[
        "Anting"
    ],
    "name:swe_x_preferred":[
        "Anting"
    ],
    "name:ukr_x_preferred":[
        "\u0410\u043d\u044c\u0442\u0456\u043d"
    ],
    "name:unk_x_variant":[
        "An-t\u2019ing-chen"
    ],
    "name:zho_x_preferred":[
        "\u5b89\u4ead\u9547"
    ],
    "qs:name":"Anting",
    "qs:photos_9r":0,
    "qs:photos_sr":0,
    "qs:pop_sr":"0",
    "wd:wordcount":489,
    "wof:name":"Anting",
    "wof:placetype":"locality",
    "wof:population":0
},
  "geometry": {"coordinates":[121.1576,31.2989],"type":"Point"}
}