{
  "type": "Feature",
  "properties": {
    "gn:admin1_code":"15.0",
    "gn:asciiname":"Ejiawan",
    "gn:country_code":"CN",
    "gn:dem":1787,
    "gn:feature_class":"P",
    "gn:feature_code":"PPL",
    "gn:name":"Ejiawan",
    "gn:population":0,
    "gn:timezone":"Asia/Shanghai",
    "iso:country":"CN",
    "name:zho_x_preferred":[
        "\u9102\u5bb6\u6e7e"
    ],
    "wof:name":"Ejiawan",
    "wof:placetype":"locality"
},
  "geometry": {"coordinates":[105.04505,33.46759],"type":"Point"}
}