{
  "type": "Feature",
  "properties": {
    "gn:admin1_code":"11.0",
    "gn:asciiname":"Haozhuhu",
    "gn:country_code":"CN",
    "gn:dem":30,
    "gn:feature_class":"P",
    "gn:feature_code":"PPL",
    "gn:name":"Haozhuhu",
    "gn:population":0,
    "gn:timezone":"Asia/Shanghai",
    "iso:country":"CN",
    "name:zho_x_preferred":[
        "\u84bf\u7af9\u6e56"
    ],
    "wof:name":"Haozhuhu",
    "wof:placetype":"locality"
},
  "geometry": {"coordinates":[112.39431,28.94709000000001],"type":"Point"}
}