{
  "type": "Feature",
  "properties": {
    "gn:admin1_code":"29.0",
    "gn:asciiname":"Xiakeluo",
    "gn:country_code":"CN",
    "gn:dem":1886,
    "gn:feature_class":"P",
    "gn:feature_code":"PPL",
    "gn:name":"Xiakeluo",
    "gn:population":0,
    "gn:timezone":"Asia/Shanghai",
    "iso:country":"CN",
    "name:zho_x_preferred":[
        "\u4e0b\u67ef\u7f57"
    ],
    "wof:name":"Xiakeluo",
    "wof:placetype":"locality"
},
  "geometry": {"coordinates":[100.59,26.8844],"type":"Point"}
}