{
  "type": "Feature",
  "properties": {
    "gn:admin1_code":"26.0",
    "gn:asciiname":"Libaotacun",
    "gn:country_code":"CN",
    "gn:dem":1377,
    "gn:feature_class":"P",
    "gn:feature_code":"PPL",
    "gn:name":"Libaotacun",
    "gn:population":0,
    "gn:timezone":"Asia/Shanghai",
    "iso:country":"CN",
    "name:zho_x_preferred":[
        "\u674e\u5b9d\u5854\u6751"
    ],
    "wof:name":"Libaotacun",
    "wof:placetype":"locality"
},
  "geometry": {"coordinates":[109.14866000000001,37.17268],"type":"Point"}
}