{
  "type": "Feature",
  "properties": {
    "gn:admin1_code":"4.0",
    "gn:asciiname":"Luzhuang",
    "gn:country_code":"CN",
    "gn:dem":24,
    "gn:feature_class":"P",
    "gn:feature_code":"PPL",
    "gn:name":"Luzhuang",
    "gn:population":0,
    "gn:timezone":"Asia/Shanghai",
    "iso:country":"CN",
    "name:zho_x_preferred":[
        "\u9646\u5e84"
    ],
    "wof:name":"Luzhuang",
    "wof:placetype":"locality"
},
  "geometry": {"coordinates":[118.41800000000001,34.0873],"type":"Point"}
}