{
  "type": "Feature",
  "properties": {
    "gn:admin1_code":"9.0",
    "gn:asciiname":"Dahanchanggou",
    "gn:country_code":"CN",
    "gn:dem":817,
    "gn:feature_class":"P",
    "gn:feature_code":"PPL",
    "gn:name":"Dahanchanggou",
    "gn:population":0,
    "gn:timezone":"Asia/Shanghai",
    "iso:country":"CN",
    "name:zho_x_preferred":[
        "\u5927\u61a8\u957f\u6c9f"
    ],
    "wof:name":"Dahanchanggou",
    "wof:placetype":"locality"
},
  "geometry": {"coordinates":[111.65689,33.98296],"type":"Point"}
}