{
  "type": "Feature",
  "properties": {
    "gn:admin1_code":"14.0",
    "gn:asciiname":"Wenjire",
    "gn:country_code":"CN",
    "gn:dem":4521,
    "gn:feature_class":"P",
    "gn:feature_code":"PPL",
    "gn:name":"Wenjire",
    "gn:population":0,
    "gn:timezone":"Asia/Urumqi",
    "iso:country":"CN",
    "name:zho_x_preferred":[
        "\u7a33\u51e0\u70ed"
    ],
    "wof:name":"Wenjire",
    "wof:placetype":"locality"
},
  "geometry": {"coordinates":[96.42497,29.70005],"type":"Point"}
}