{
  "type": "Feature",
  "properties": {
    "gn:admin1_code":"7.0",
    "gn:asciiname":"Dawang'ao",
    "gn:country_code":"CN",
    "gn:dem":1250,
    "gn:feature_class":"P",
    "gn:feature_code":"PPL",
    "gn:name":"Dawang\u2019ao",
    "gn:population":0,
    "gn:timezone":"Asia/Shanghai",
    "iso:country":"CN",
    "name:zho_x_preferred":[
        "\u5927\u738b\u51f9"
    ],
    "name:zho_x_variant":[
        "Dawang\u2019ao"
    ],
    "wof:name":"Dawang'ao",
    "wof:placetype":"locality"
},
  "geometry": {"coordinates":[117.9943,27.96205],"type":"Point"}
}