{
  "type": "Feature",
  "properties": {
    "gn:admin1_code":"24",
    "gn:asciiname":"Chenjiashe",
    "gn:country_code":"CN",
    "gn:dem":1413,
    "gn:feature_class":"P",
    "gn:feature_code":"PPL",
    "gn:name":"Chenjiashe",
    "gn:population":0,
    "gn:timezone":"Asia/Shanghai",
    "iso:country":"CN",
    "name:und_x_variant":[
        "Ch\u2019en-chia-chuang",
        "Chenjiazhuang",
        "Chenjiashe"
    ],
    "name:zho_x_preferred":[
        "\u9648\u5bb6\u793e"
    ],
    "wof:name":"Chenjiashe",
    "wof:placetype":"locality"
},
  "geometry": {"coordinates":[112.23671000000002,37.74615],"type":"Point"}
}