{
  "type": "Feature",
  "properties": {
    "gn:admin1_code":"5.0",
    "gn:asciiname":"Gaoli Gouzi",
    "gn:country_code":"CN",
    "gn:dem":757,
    "gn:feature_class":"P",
    "gn:feature_code":"PPL",
    "gn:name":"Gaoli Gouzi",
    "gn:population":0,
    "gn:timezone":"Asia/Shanghai",
    "iso:country":"CN",
    "name:und_x_variant":[
        "\u9ad8\u4e3d\u6c9f\u5b50"
    ],
    "wof:name":"Gaoli Gouzi",
    "wof:placetype":"locality"
},
  "geometry": {"coordinates":[127.19902999999999,41.86909],"type":"Point"}
}