{
  "type": "Feature",
  "properties": {
    "gn:admin1_code":"26.0",
    "gn:asciiname":"Xuezhen",
    "gn:country_code":"CN",
    "gn:dem":577,
    "gn:feature_class":"P",
    "gn:feature_code":"PPLA4",
    "gn:name":"Xuezhen",
    "gn:population":0,
    "gn:timezone":"Asia/Shanghai",
    "iso:country":"CN",
    "name:und_x_variant":[
        "Hsieh-chia-chen",
        "Hs\u00fceh-chen",
        "Hs\u00fceh-chia-chen",
        "Xuezhen"
    ],
    "wof:name":"Xuezhen",
    "wof:placetype":"locality"
},
  "geometry": {"coordinates":[109.29652,34.95475],"type":"Point"}
}