{
  "type": "Feature",
  "properties": {
    "gn:admin1_code":"24.0",
    "gn:asciiname":"Dongxu",
    "gn:country_code":"CN",
    "gn:dem":487,
    "gn:feature_class":"P",
    "gn:feature_code":"PPL",
    "gn:name":"Dongxu",
    "gn:population":0,
    "gn:timezone":"Asia/Shanghai",
    "iso:country":"CN",
    "name:und_x_variant":[
        "\u4e1c\u8bb8"
    ],
    "name:zho_x_preferred":[
        "\u4e1c\u8bb8"
    ],
    "wof:name":"Dongxu",
    "wof:placetype":"locality"
},
  "geometry": {"coordinates":[111.50402,35.69008],"type":"Point"}
}