{
  "type": "Feature",
  "properties": {
    "gn:admin1_code":"24.0",
    "gn:asciiname":"Juzicun",
    "gn:country_code":"CN",
    "gn:dem":1149,
    "gn:feature_class":"P",
    "gn:feature_code":"PPL",
    "gn:name":"Juzicun",
    "gn:population":0,
    "gn:timezone":"Asia/Shanghai",
    "iso:country":"CN",
    "name:zho_x_preferred":[
        "\u5c45\u5b50\u6751"
    ],
    "wof:name":"Juzicun",
    "wof:placetype":"locality"
},
  "geometry": {"coordinates":[110.88697000000001,36.67999],"type":"Point"}
}