{
  "type": "Feature",
  "properties": {
    "gn:admin1_code":"2.0",
    "gn:asciiname":"Shangchepan",
    "gn:country_code":"CN",
    "gn:dem":3,
    "gn:feature_class":"P",
    "gn:feature_code":"PPL",
    "gn:name":"Shangchepan",
    "gn:population":0,
    "gn:timezone":"Asia/Shanghai",
    "iso:country":"CN",
    "name:und_x_variant":[
        "\u4e0a\u8f66\u76d8"
    ],
    "wof:name":"Shangchepan",
    "wof:placetype":"locality"
},
  "geometry": {"coordinates":[120.08608999999998,30.71362],"type":"Point"}
}