{
  "type": "Feature",
  "properties": {
    "gn:admin1_code":"3.0",
    "gn:asciiname":"Huangceyuan",
    "gn:country_code":"CN",
    "gn:dem":274,
    "gn:feature_class":"P",
    "gn:feature_code":"PPL",
    "gn:name":"Huangceyuan",
    "gn:population":0,
    "gn:timezone":"Asia/Shanghai",
    "iso:country":"CN",
    "name:zho_x_preferred":[
        "\u9ec4\u7b56\u6e90"
    ],
    "wof:name":"Huangceyuan",
    "wof:placetype":"locality"
},
  "geometry": {"coordinates":[117.09314999999999,27.73829000000001],"type":"Point"}
}