{
  "type": "Feature",
  "properties": {
    "gn:admin1_code":"7.0",
    "gn:asciiname":"Xiashi'er'an",
    "gn:country_code":"CN",
    "gn:dem":470,
    "gn:feature_class":"P",
    "gn:feature_code":"PPL",
    "gn:name":"Xiashi\u2019er\u2019an",
    "gn:population":0,
    "gn:timezone":"Asia/Shanghai",
    "iso:country":"CN",
    "name:und_x_variant":[
        "Xiashi\u2019er\u2019an"
    ],
    "name:zho_x_preferred":[
        "\u4e0b\u5341\u4e8c\u5cb8"
    ],
    "wof:name":"Xiashi'er'an",
    "wof:placetype":"locality"
},
  "geometry": {"coordinates":[118.34891,25.50023],"type":"Point"}
}