{
  "type": "Feature",
  "properties": {
    "gn:admin1_code":"3",
    "gn:asciiname":"Gongren",
    "gn:country_code":"CN",
    "gn:dem":193,
    "gn:feature_class":"P",
    "gn:feature_code":"PPL",
    "gn:name":"Gongren",
    "gn:population":0,
    "gn:timezone":"Asia/Shanghai",
    "iso:country":"CN",
    "name:zho_x_preferred":[
        "\u5de5\u4eba"
    ],
    "wof:name":"Gongren",
    "wof:placetype":"locality"
},
  "geometry": {"coordinates":[114.307,25.4013],"type":"Point"}
}