{
  "type": "Feature",
  "properties": {
    "gn:admin1_code":"15.0",
    "gn:asciiname":"Jianjiagou",
    "gn:country_code":"CN",
    "gn:dem":1484,
    "gn:feature_class":"P",
    "gn:feature_code":"PPL",
    "gn:name":"Jianjiagou",
    "gn:population":0,
    "gn:timezone":"Asia/Shanghai",
    "iso:country":"CN",
    "name:und_x_variant":[
        "\u8e47\u5bb6\u6c9f"
    ],
    "wof:name":"Jianjiagou",
    "wof:placetype":"locality"
},
  "geometry": {"coordinates":[105.42171,33.31871],"type":"Point"}
}