{
  "type": "Feature",
  "properties": {
    "gn:admin1_code":"29.0",
    "gn:asciiname":"Houying",
    "gn:country_code":"CN",
    "gn:dem":2198,
    "gn:feature_class":"P",
    "gn:feature_code":"PPL",
    "gn:name":"Houying",
    "gn:population":0,
    "gn:timezone":"Asia/Shanghai",
    "iso:country":"CN",
    "name:zho_x_preferred":[
        "\u540e\u8425"
    ],
    "wof:name":"Houying",
    "wof:placetype":"locality"
},
  "geometry": {"coordinates":[99.922,26.5397],"type":"Point"}
}