{
  "type": "Feature",
  "properties": {
    "gn:admin1_code":"10.0",
    "gn:asciiname":"Xihuayuan",
    "gn:country_code":"CN",
    "gn:dem":736,
    "gn:feature_class":"P",
    "gn:feature_code":"PPL",
    "gn:name":"Xihuayuan",
    "gn:population":0,
    "gn:timezone":"Asia/Shanghai",
    "iso:country":"CN",
    "name:zho_x_preferred":[
        "\u897f\u82b1\u56ed"
    ],
    "wof:name":"Xihuayuan",
    "wof:placetype":"locality"
},
  "geometry": {"coordinates":[117.38766,40.36034],"type":"Point"}
}