{
  "type": "Feature",
  "properties": {
    "gn:admin1_code":"30.0",
    "gn:asciiname":"Zhuwu",
    "gn:country_code":"CN",
    "gn:dem":170,
    "gn:feature_class":"P",
    "gn:feature_code":"PPL",
    "gn:name":"Zhuwu",
    "gn:population":0,
    "gn:timezone":"Asia/Shanghai",
    "iso:country":"CN",
    "name:zho_x_preferred":[
        "\u6731\u5c4b"
    ],
    "name:zho_x_variant":[
        "\u6731\u5434\u9547"
    ],
    "wof:name":"Zhuwu",
    "wof:placetype":"locality"
},
  "geometry": {"coordinates":[111.52538,23.07191],"type":"Point"}
}