{
  "type": "Feature",
  "properties": {
    "gn:admin1_code":"25",
    "gn:asciiname":"Beilongjiao",
    "gn:country_code":"CN",
    "gn:dem":263,
    "gn:feature_class":"P",
    "gn:feature_code":"PPL",
    "gn:name":"Beilongjiao",
    "gn:population":0,
    "gn:timezone":"Asia/Shanghai",
    "iso:country":"CN",
    "name:zho_x_preferred":[
        "\u5317\u9f99\u89d2"
    ],
    "wof:name":"Beilongjiao",
    "wof:placetype":"locality"
},
  "geometry": {"coordinates":[117.681,36.3387],"type":"Point"}
}