{
  "type": "Feature",
  "properties": {
    "gn:admin1_code":"8.0",
    "gn:asciiname":"Houyonglicun",
    "gn:country_code":"CN",
    "gn:dem":128,
    "gn:feature_class":"P",
    "gn:feature_code":"PPL",
    "gn:name":"Houyonglicun",
    "gn:population":0,
    "gn:timezone":"Asia/Shanghai",
    "iso:country":"CN",
    "name:zho_x_preferred":[
        "\u540e\u6c38\u5229\u6751"
    ],
    "wof:name":"Houyonglicun",
    "wof:placetype":"locality"
},
  "geometry": {"coordinates":[124.99366999999999,45.54883],"type":"Point"}
}