{
  "type": "Feature",
  "properties": {
    "gn:admin1_code":"14.0",
    "gn:asciiname":"Zhuguyi",
    "gn:country_code":"CN",
    "gn:dem":3804,
    "gn:feature_class":"P",
    "gn:feature_code":"PPL",
    "gn:name":"Zhuguyi",
    "gn:population":0,
    "gn:timezone":"Asia/Urumqi",
    "iso:country":"CN",
    "name:zho_x_preferred":[
        "\u4e3b\u56fa\u610f"
    ],
    "wof:name":"Zhuguyi",
    "wof:placetype":"locality"
},
  "geometry": {"coordinates":[95.77446,31.1353],"type":"Point"}
}