{
  "type": "Feature",
  "properties": {
    "gn:admin1_code":"23.0",
    "gn:asciiname":"Tongpu",
    "gn:country_code":"CN",
    "gn:dem":3,
    "gn:feature_class":"P",
    "gn:feature_code":"PPL",
    "gn:name":"Tongpu",
    "gn:population":0,
    "gn:timezone":"Asia/Shanghai",
    "iso:country":"CN",
    "name:und_x_variant":[
        "\u6f7c\u6d66"
    ],
    "wof:name":"Tongpu",
    "wof:placetype":"locality"
},
  "geometry": {"coordinates":[121.23472,31.3115],"type":"Point"}
}