{
  "type": "Feature",
  "properties": {
    "gn:admin1_code":"24.0",
    "gn:asciiname":"Silikou",
    "gn:country_code":"CN",
    "gn:dem":1336,
    "gn:feature_class":"P",
    "gn:feature_code":"PPL",
    "gn:name":"Silikou",
    "gn:population":0,
    "gn:timezone":"Asia/Shanghai",
    "iso:country":"CN",
    "name:bul_x_preferred":[
        "\u0421\u0438\u043b\u0438\u043a\u0443"
    ],
    "name:ceb_x_preferred":[
        "Sil\u00edkou"
    ],
    "name:ell_x_preferred":[
        "\u03a3\u03c5\u03bb\u03af\u03ba\u03bf\u03c5"
    ],
    "name:fas_x_preferred":[
        "\u0633\u06cc\u0644\u06cc\u06a9\u0648"
    ],
    "name:fra_x_preferred":[
        "Syl\u00edkou"
    ],
    "name:pol_x_preferred":[
        "Siliku"
    ],
    "name:spa_x_preferred":[
        "Silikou"
    ],
    "name:swe_x_preferred":[
        "Sil\u00edkou"
    ],
    "name:urd_x_preferred":[
        "\u0633\u06cc\u0644\u06cc\u06a9\u0648"
    ],
    "name:zho_x_preferred":[
        "\u56db\u91cc\u53e3"
    ],
    "wof:name":"Silikou",
    "wof:placetype":"locality"
},
  "geometry": {"coordinates":[113.24802,35.47585],"type":"Point"}
}