{
  "type": "Feature",
  "properties": {
    "gn:admin1_code":"24.0",
    "gn:asciiname":"Silikou",
    "gn:country_code":"CN",
    "gn:dem":1336,
    "gn:feature_class":"P",
    "gn:feature_code":"PPL",
    "gn:name":"Silikou",
    "gn:population":0,
    "gn:timezone":"Asia/Shanghai",
    "iso:country":"CN",
    "name:zho_x_preferred":[
        "\u56db\u91cc\u53e3"
    ],
    "wof:name":"Silikou",
    "wof:placetype":"locality"
},
  "geometry": {"coordinates":[113.24802,35.47585],"type":"Point"}
}