{
  "type": "Feature",
  "properties": {
    "gn:admin1_code":"20.0",
    "gn:asciiname":"Ximata",
    "gn:country_code":"CN",
    "gn:dem":1613,
    "gn:feature_class":"P",
    "gn:feature_code":"PPL",
    "gn:name":"Ximata",
    "gn:population":0,
    "gn:timezone":"Asia/Shanghai",
    "iso:country":"CN",
    "name:und_x_variant":[
        "\u5e2d\u9ebb\u5854"
    ],
    "wof:name":"Ximata",
    "wof:placetype":"locality"
},
  "geometry": {"coordinates":[110.2047,41.14903],"type":"Point"}
}