{
  "type": "Feature",
  "properties": {
    "gn:admin1_code":"29.0",
    "gn:asciiname":"Bashala",
    "gn:country_code":"CN",
    "gn:dem":2278,
    "gn:feature_class":"P",
    "gn:feature_code":"PPL",
    "gn:name":"Bashala",
    "gn:population":0,
    "gn:timezone":"Asia/Shanghai",
    "iso:country":"CN",
    "name:zho_x_preferred":[
        "\u5427\u6c99\u5566"
    ],
    "wof:name":"Bashala",
    "wof:placetype":"locality"
},
  "geometry": {"coordinates":[100.727,26.9176],"type":"Point"}
}