{
  "type": "Feature",
  "properties": {
    "gn:admin1_code":"10",
    "gn:asciiname":"Tudongzi",
    "gn:country_code":"CN",
    "gn:dem":740,
    "gn:feature_class":"P",
    "gn:feature_code":"PPL",
    "gn:name":"Tudongzi",
    "gn:population":0,
    "gn:timezone":"Asia/Shanghai",
    "iso:country":"CN",
    "name:zho_x_preferred":[
        "\u571f\u6d1e\u5b50"
    ],
    "wof:name":"Tudongzi",
    "wof:placetype":"locality"
},
  "geometry": {"coordinates":[118.95334,41.22578],"type":"Point"}
}