{
  "type": "Feature",
  "properties": {
    "gn:admin1_code":"19.0",
    "gn:asciiname":"Guanyingou",
    "gn:country_code":"CN",
    "gn:dem":108,
    "gn:feature_class":"P",
    "gn:feature_code":"PPL",
    "gn:name":"Guanyingou",
    "gn:population":0,
    "gn:timezone":"Asia/Shanghai",
    "iso:country":"CN",
    "name:und_x_variant":[
        "\u89c2\u97f3\u6c9f"
    ],
    "wof:name":"Guanyingou",
    "wof:placetype":"locality"
},
  "geometry": {"coordinates":[123.20801000000002,40.20808],"type":"Point"}
}