{
  "type": "Feature",
  "properties": {
    "gn:admin1_code":"09",
    "gn:asciiname":"Gaobu",
    "gn:country_code":"CN",
    "gn:dem":49,
    "gn:feature_class":"P",
    "gn:feature_code":"PPL",
    "gn:name":"Gaobu",
    "gn:population":0,
    "gn:timezone":"Asia/Shanghai",
    "iso:country":"CN",
    "name:sco_x_preferred":[
        "Gaobu"
    ],
    "wof:name":"Gaobu",
    "wof:placetype":"locality"
},
  "geometry": {"coordinates":[115.14667,35.95361],"type":"Point"}
}