{
  "type": "Feature",
  "properties": {
    "gn:admin1_code":"18",
    "gn:asciiname":"Pingliang",
    "gn:country_code":"CN",
    "gn:dem":667,
    "gn:feature_class":"P",
    "gn:feature_code":"PPL",
    "gn:name":"Pingliang",
    "gn:population":0,
    "gn:timezone":"Asia/Shanghai",
    "iso:country":"CN",
    "name:ara_x_preferred":[
        "\u0628\u064a\u0646\u063a\u0644\u064a\u0627\u0646\u063a"
    ],
    "name:ast_x_preferred":[
        "Pingliang"
    ],
    "name:cdo_x_preferred":[
        "B\u00ecng-li\u00f2ng"
    ],
    "name:ceb_x_preferred":[
        "Pingliang"
    ],
    "name:ces_x_preferred":[
        "Pching-liang"
    ],
    "name:dan_x_preferred":[
        "Pingliang"
    ],
    "name:deu_x_preferred":[
        "Pingliang"
    ],
    "name:eus_x_preferred":[
        "Pingliang"
    ],
    "name:fas_x_preferred":[
        "\u067e\u06cc\u0646\u06af\u0644\u06cc\u0627\u0646\u06af"
    ],
    "name:fin_x_preferred":[
        "Pingliang"
    ],
    "name:fra_x_preferred":[
        "Pingliang"
    ],
    "name:hye_x_preferred":[
        "\u054a\u056b\u056c\u056b\u0561\u0576"
    ],
    "name:ita_x_preferred":[
        "Pingliang"
    ],
    "name:jpn_x_preferred":[
        "\u5e73\u6dbc\u5e02"
    ],
    "name:kik_x_preferred":[
        "Pingliang"
    ],
    "name:kor_x_preferred":[
        "\ud551\ub7c9\uc2dc"
    ],
    "name:mlg_x_preferred":[
        "Pingliang"
    ],
    "name:nld_x_preferred":[
        "Pingliang"
    ],
    "name:nno_x_preferred":[
        "Pingliang"
    ],
    "name:nor_x_preferred":[
        "Pingliang"
    ],
    "name:pam_x_preferred":[
        "Pingliang"
    ],
    "name:pnb_x_preferred":[
        "\u067e\u0646\u06af\u0644\u06cc\u0627\u0646\u06af"
    ],
    "name:pol_x_preferred":[
        "Pingliang"
    ],
    "name:por_x_preferred":[
        "Pingliang"
    ],
    "name:rus_x_preferred":[
        "\u041f\u0438\u043d\u043b\u044f\u043d"
    ],
    "name:spa_x_preferred":[
        "Pingliang"
    ],
    "name:swe_x_preferred":[
        "Pingliang"
    ],
    "name:tgl_x_preferred":[
        "Pingliang"
    ],
    "name:tur_x_preferred":[
        "Pingliang"
    ],
    "name:urd_x_preferred":[
        "\u067e\u0646\u06af\u0644\u06cc\u0627\u0646\u06af"
    ],
    "name:vie_x_preferred":[
        "B\u00ecnh L\u01b0\u01a1ng"
    ],
    "name:war_x_preferred":[
        "Pingliang"
    ],
    "name:wuu_x_preferred":[
        "\u5e73\u51c9\u5e02"
    ],
    "name:zho_x_preferred":[
        "\u5e73\u51c9\u5e02"
    ],
    "wof:name":"Pingliang",
    "wof:placetype":"locality"
},
  "geometry": {"coordinates":[107.81833,26.77],"type":"Point"}
}