{
  "type": "Feature",
  "properties": {
    "gn:admin1_code":"29.0",
    "gn:asciiname":"Shangqingbian",
    "gn:country_code":"CN",
    "gn:dem":2039,
    "gn:feature_class":"P",
    "gn:feature_code":"PPL",
    "gn:name":"Shangqingbian",
    "gn:population":0,
    "gn:timezone":"Asia/Shanghai",
    "iso:country":"CN",
    "name:zho_x_preferred":[
        "\u4e0a\u7b90\u8fb9"
    ],
    "wof:name":"Shangqingbian",
    "wof:placetype":"locality"
},
  "geometry": {"coordinates":[103.873,27.5683],"type":"Point"}
}