{
  "type": "Feature",
  "properties": {
    "gn:admin1_code":"10",
    "gn:asciiname":"Hanzhangzi",
    "gn:country_code":"CN",
    "gn:dem":787,
    "gn:feature_class":"P",
    "gn:feature_code":"PPL",
    "gn:name":"Hanzhangzi",
    "gn:population":0,
    "gn:timezone":"Asia/Shanghai",
    "iso:country":"CN",
    "name:zho_x_preferred":[
        "\u97e9\u6756\u5b50"
    ],
    "wof:name":"Hanzhangzi",
    "wof:placetype":"locality"
},
  "geometry": {"coordinates":[118.60184,41.22432],"type":"Point"}
}