{
  "type": "Feature",
  "properties": {
    "gn:admin1_code":"26",
    "gn:asciiname":"Beisi",
    "gn:cc2":"CN",
    "gn:country_code":"CN",
    "gn:dem":1519,
    "gn:feature_class":"P",
    "gn:feature_code":"PPL",
    "gn:name":"Beisi",
    "gn:population":0,
    "gn:timezone":"Asia/Shanghai",
    "iso:country":"CN",
    "name:und_x_variant":[
        "Pei-ssu",
        "Beisi"
    ],
    "wof:name":"Beisi",
    "wof:placetype":"locality"
},
  "geometry": {"coordinates":[108.64167,35.47083],"type":"Point"}
}