{
  "type": "Feature",
  "properties": {
    "gn:admin1_code":"26.0",
    "gn:asciiname":"Beitoucun",
    "gn:country_code":"CN",
    "gn:dem":617,
    "gn:feature_class":"P",
    "gn:feature_code":"PPL",
    "gn:name":"Beitoucun",
    "gn:population":0,
    "gn:timezone":"Asia/Shanghai",
    "iso:country":"CN",
    "name:zho_x_preferred":[
        "\u5317\u5934\u6751"
    ],
    "wof:name":"Beitoucun",
    "wof:placetype":"locality"
},
  "geometry": {"coordinates":[110.34281,35.42011],"type":"Point"}
}