{
  "type": "Feature",
  "properties": {
    "gn:admin1_code":"10.0",
    "gn:asciiname":"Tieling",
    "gn:country_code":"CN",
    "gn:dem":291,
    "gn:feature_class":"P",
    "gn:feature_code":"PPL",
    "gn:name":"Tieling",
    "gn:population":0,
    "gn:timezone":"Asia/Shanghai",
    "iso:country":"CN",
    "name:afr_x_preferred":[
        "Tieling"
    ],
    "name:ara_x_preferred":[
        "\u062a\u064a\u0644\u064a\u0646\u063a"
    ],
    "name:cdo_x_preferred":[
        "Ti\u00e9k-li\u0101ng"
    ],
    "name:ceb_x_preferred":[
        "Tieling Shi"
    ],
    "name:ces_x_preferred":[
        "Tchie-ling"
    ],
    "name:dan_x_preferred":[
        "Tieling"
    ],
    "name:deu_x_preferred":[
        "Tieling"
    ],
    "name:eus_x_preferred":[
        "Tieling"
    ],
    "name:fas_x_preferred":[
        "\u062a\u06cc\u0644\u06cc\u0646\u06af"
    ],
    "name:fin_x_preferred":[
        "Tieling"
    ],
    "name:fra_x_preferred":[
        "Tieling"
    ],
    "name:ita_x_preferred":[
        "Tieling"
    ],
    "name:jpn_x_preferred":[
        "\u9244\u5dba\u5e02"
    ],
    "name:kik_x_preferred":[
        "Tieling"
    ],
    "name:kor_x_preferred":[
        "\ud184\ub9c1\uc2dc"
    ],
    "name:mlg_x_preferred":[
        "Tieling"
    ],
    "name:nld_x_preferred":[
        "Tieling"
    ],
    "name:nno_x_preferred":[
        "Tieling"
    ],
    "name:nor_x_preferred":[
        "Tieling"
    ],
    "name:pol_x_preferred":[
        "Tieling"
    ],
    "name:rus_x_preferred":[
        "\u0422\u0435\u043b\u0438\u043d"
    ],
    "name:spa_x_preferred":[
        "Tieling"
    ],
    "name:srp_x_preferred":[
        "\u0422\u0458\u0435\u043b\u0438\u043d\u0433"
    ],
    "name:swe_x_preferred":[
        "Tieling"
    ],
    "name:tur_x_preferred":[
        "Tieling"
    ],
    "name:und_x_variant":[
        "\u94c1\u5cad"
    ],
    "name:urd_x_preferred":[
        "\u062a\u06cc\u0626\u0644\u0646\u06af"
    ],
    "name:vie_x_preferred":[
        "Thi\u1ebft L\u0129nh"
    ],
    "name:war_x_preferred":[
        "Tieling"
    ],
    "name:wuu_x_preferred":[
        "\u94c1\u5cad\u5e02"
    ],
    "name:zho_x_preferred":[
        "\u94c1\u5cad\u5e02"
    ],
    "wof:name":"Tieling",
    "wof:placetype":"locality"
},
  "geometry": {"coordinates":[114.43836,38.81709],"type":"Point"}
}