{
  "type": "Feature",
  "properties": {
    "gn:admin1_code":"4.0",
    "gn:asciiname":"Zhaoshun Bazu",
    "gn:country_code":"CN",
    "gn:dem":0,
    "gn:feature_class":"P",
    "gn:feature_code":"PPLF",
    "gn:name":"Zhaoshun Bazu",
    "gn:population":0,
    "gn:timezone":"Asia/Shanghai",
    "iso:country":"CN",
    "name:zho_x_preferred":[
        "\u5146\u987a\u516b\u7ec4"
    ],
    "wof:name":"Zhaoshun Bazu",
    "wof:placetype":"locality"
},
  "geometry": {"coordinates":[120.377,33.3031],"type":"Point"}
}