{
  "type": "Feature",
  "properties": {
    "gn:admin1_code":"01",
    "gn:asciiname":"Chihe",
    "gn:cc2":"CN",
    "gn:country_code":"CN",
    "gn:dem":33,
    "gn:feature_class":"P",
    "gn:feature_code":"PPL",
    "gn:name":"Chihe",
    "gn:population":0,
    "gn:timezone":"Asia/Shanghai",
    "iso:country":"CN",
    "name:und_x_variant":[
        "Ch\u2019ih-ho-chen",
        "Ch\u2019ih-ho",
        "Chihe"
    ],
    "wof:name":"Chihe",
    "wof:placetype":"locality"
},
  "geometry": {"coordinates":[117.94667,32.52056],"type":"Point"}
}