{
  "type": "Feature",
  "properties": {
    "gn:admin1_code":"1.0",
    "gn:asciiname":"Caotangcun",
    "gn:country_code":"CN",
    "gn:dem":16,
    "gn:feature_class":"P",
    "gn:feature_code":"PPL",
    "gn:name":"Caotangcun",
    "gn:population":0,
    "gn:timezone":"Asia/Shanghai",
    "iso:country":"CN",
    "name:zho_x_preferred":[
        "\u8349\u5858\u6751"
    ],
    "wof:name":"Caotangcun",
    "wof:placetype":"locality"
},
  "geometry": {"coordinates":[117.90358000000001,30.88343],"type":"Point"}
}