{
  "type": "Feature",
  "properties": {
    "gn:admin1_code":"11",
    "gn:asciiname":"Shangshanxia",
    "gn:country_code":"CN",
    "gn:dem":264,
    "gn:feature_class":"P",
    "gn:feature_code":"PPL",
    "gn:name":"Shangshanxia",
    "gn:population":0,
    "gn:timezone":"Asia/Shanghai",
    "iso:country":"CN",
    "name:zho_x_preferred":[
        "\u4e0a\u5c71\u4e0b"
    ],
    "wof:name":"Shangshanxia",
    "wof:placetype":"locality"
},
  "geometry": {"coordinates":[112.34056,25.44139],"type":"Point"}
}