{
  "type": "Feature",
  "properties": {
    "gn:admin1_code":"4.0",
    "gn:asciiname":"Huangtangcun",
    "gn:country_code":"CN",
    "gn:dem":5,
    "gn:feature_class":"P",
    "gn:feature_code":"PPL",
    "gn:name":"Huangtangcun",
    "gn:population":0,
    "gn:timezone":"Asia/Shanghai",
    "iso:country":"CN",
    "name:zho_x_preferred":[
        "\u9ec4\u8361\u6751"
    ],
    "wof:name":"Huangtangcun",
    "wof:placetype":"locality"
},
  "geometry": {"coordinates":[119.32489,34.30689],"type":"Point"}
}