{
  "type": "Feature",
  "properties": {
    "gn:admin1_code":"26.0",
    "gn:asciiname":"Xiakouyi",
    "gn:country_code":"CN",
    "gn:dem":703,
    "gn:feature_class":"P",
    "gn:feature_code":"PPLA4",
    "gn:name":"Xiakouyi",
    "gn:population":0,
    "gn:timezone":"Asia/Shanghai",
    "iso:country":"CN",
    "name:und_x_variant":[
        "Hsia-k\u2019ou-i",
        "Xiakouyi",
        "\u7856\u53e3\u9a7f",
        "Xiakouyi Zhen",
        "\u7856\u53e3\u9a7f\u9547"
    ],
    "wof:name":"Xiakouyi",
    "wof:placetype":"locality"
},
  "geometry": {"coordinates":[106.40751000000002,33.21117],"type":"Point"}
}