{
  "type": "Feature",
  "properties": {
    "gn:admin1_code":"21.0",
    "gn:asciiname":"Xiaodianzi Qidui",
    "gn:country_code":"CN",
    "gn:dem":1102,
    "gn:feature_class":"P",
    "gn:feature_code":"PPLF",
    "gn:name":"Xiaodianzi Qidui",
    "gn:population":0,
    "gn:timezone":"Asia/Shanghai",
    "iso:country":"CN",
    "name:zho_x_preferred":[
        "\u5c0f\u5e97\u5b50\u4e03\u961f"
    ],
    "wof:name":"Xiaodianzi Qidui",
    "wof:placetype":"locality"
},
  "geometry": {"coordinates":[106.486,38.7233],"type":"Point"}
}