{
  "type": "Feature",
  "properties": {
    "gn:admin1_code":"33.0",
    "gn:asciiname":"Majun",
    "gn:country_code":"CN",
    "gn:dem":634,
    "gn:feature_class":"P",
    "gn:feature_code":"PPL",
    "gn:name":"Majun",
    "gn:population":0,
    "gn:timezone":"Asia/Shanghai",
    "iso:country":"CN",
    "name:zho_x_preferred":[
        "\u9a6c\u519b"
    ],
    "wof:name":"Majun",
    "wof:placetype":"locality"
},
  "geometry": {"coordinates":[109.17256,31.11122],"type":"Point"}
}