{
  "type": "Feature",
  "properties": {
    "gn:admin1_code":"4.0",
    "gn:asciiname":"Helinfangcun",
    "gn:country_code":"CN",
    "gn:dem":9,
    "gn:feature_class":"P",
    "gn:feature_code":"PPL",
    "gn:name":"Helinfangcun",
    "gn:population":0,
    "gn:timezone":"Asia/Shanghai",
    "iso:country":"CN",
    "name:zho_x_preferred":[
        "\u6cb3\u6797\u574a\u6751"
    ],
    "wof:name":"Helinfangcun",
    "wof:placetype":"locality"
},
  "geometry": {"coordinates":[120.71572999999999,31.74912],"type":"Point"}
}