{
  "type": "Feature",
  "properties": {
    "gn:admin1_code":"7",
    "gn:asciiname":"Puning",
    "gn:country_code":"CN",
    "gn:dem":187,
    "gn:feature_class":"P",
    "gn:feature_code":"PPL",
    "gn:name":"Puning",
    "gn:population":0,
    "gn:timezone":"Asia/Shanghai",
    "iso:country":"CN",
    "name:ara_x_preferred":[
        "\u0628\u064a\u0646\u064a\u0646\u063a"
    ],
    "name:ceb_x_preferred":[
        "Puning"
    ],
    "name:ces_x_preferred":[
        "Pchu-ning"
    ],
    "name:deu_x_preferred":[
        "Puning"
    ],
    "name:fas_x_preferred":[
        "\u067e\u0648\u0646\u06cc\u0646\u06af"
    ],
    "name:fin_x_preferred":[
        "Puning"
    ],
    "name:fra_x_preferred":[
        "Puning"
    ],
    "name:ind_x_preferred":[
        "Puning"
    ],
    "name:ita_x_preferred":[
        "Puning"
    ],
    "name:jpn_x_preferred":[
        "\u666e\u5be7\u5e02"
    ],
    "name:kik_x_preferred":[
        "Puning"
    ],
    "name:kor_x_preferred":[
        "\ud478\ub2dd\uc2dc"
    ],
    "name:mlg_x_preferred":[
        "Puning"
    ],
    "name:mwl_x_preferred":[
        "Puning"
    ],
    "name:nor_x_preferred":[
        "Puning"
    ],
    "name:pam_x_preferred":[
        "Puning"
    ],
    "name:pnb_x_preferred":[
        "\u067e\u0648\u0646\u06cc\u0646\u06af"
    ],
    "name:swe_x_preferred":[
        "Puning"
    ],
    "name:und_x_variant":[
        "\u57d4\u5b81"
    ],
    "name:urd_x_preferred":[
        "\u067e\u0648\u0646\u06cc\u0646\u06af"
    ],
    "name:vie_x_preferred":[
        "Ph\u1ed5 Ninh"
    ],
    "name:zho_x_preferred":[
        "\u666e\u5b81\u5e02"
    ],
    "wof:name":"Puning",
    "wof:placetype":"locality"
},
  "geometry": {"coordinates":[118.33359,26.17316],"type":"Point"}
}