{
  "type": "Feature",
  "properties": {
    "gn:admin1_code":"7",
    "gn:asciiname":"Puning",
    "gn:country_code":"CN",
    "gn:dem":187,
    "gn:feature_class":"P",
    "gn:feature_code":"PPL",
    "gn:name":"Puning",
    "gn:population":0,
    "gn:timezone":"Asia/Shanghai",
    "iso:country":"CN",
    "name:und_x_variant":[
        "\u57d4\u5b81"
    ],
    "wof:name":"Puning",
    "wof:placetype":"locality"
},
  "geometry": {"coordinates":[118.33359,26.17316],"type":"Point"}
}