{
  "type": "Feature",
  "properties": {
    "gn:admin1_code":"4.0",
    "gn:asciiname":"Nanxuzhuang",
    "gn:country_code":"CN",
    "gn:dem":5,
    "gn:feature_class":"P",
    "gn:feature_code":"PPL",
    "gn:name":"Nanxuzhuang",
    "gn:population":0,
    "gn:timezone":"Asia/Shanghai",
    "iso:country":"CN",
    "name:zho_x_preferred":[
        "Nanxuzhuang"
    ],
    "name:zho_x_variant":[
        "\u5357\u5f90\u5e84"
    ],
    "wof:name":"Nanxuzhuang",
    "wof:placetype":"locality"
},
  "geometry": {"coordinates":[119.06256,34.73258],"type":"Point"}
}