{
  "type": "Feature",
  "properties": {
    "gn:admin1_code":"3",
    "gn:asciiname":"Dianbei",
    "gn:country_code":"CN",
    "gn:dem":200,
    "gn:feature_class":"P",
    "gn:feature_code":"PPL",
    "gn:name":"Dianbei",
    "gn:population":0,
    "gn:timezone":"Asia/Shanghai",
    "iso:country":"CN",
    "name:und_x_variant":[
        "\u5e97\u80cc"
    ],
    "wof:name":"Dianbei",
    "wof:placetype":"locality"
},
  "geometry": {"coordinates":[116.04924,26.28392],"type":"Point"}
}