{
  "type": "Feature",
  "properties": {
    "gn:admin1_code":"18.0",
    "gn:asciiname":"Lagela",
    "gn:country_code":"CN",
    "gn:dem":893,
    "gn:feature_class":"P",
    "gn:feature_code":"PPL",
    "gn:name":"Lagela",
    "gn:population":0,
    "gn:timezone":"Asia/Shanghai",
    "iso:country":"CN",
    "name:zho_x_preferred":[
        "\u62c9\u683c\u814a"
    ],
    "wof:name":"Lagela",
    "wof:placetype":"locality"
},
  "geometry": {"coordinates":[107.66500000000001,25.3257],"type":"Point"}
}