{
  "type": "Feature",
  "properties": {
    "gn:admin1_code":"16",
    "gn:asciiname":"Guimei",
    "gn:country_code":"CN",
    "gn:dem":576,
    "gn:feature_class":"P",
    "gn:feature_code":"PPL",
    "gn:name":"Guimei",
    "gn:population":0,
    "gn:timezone":"Asia/Shanghai",
    "iso:country":"CN",
    "name:zho_x_preferred":[
        "\u5f52\u7f8e"
    ],
    "wof:name":"Guimei",
    "wof:placetype":"locality"
},
  "geometry": {"coordinates":[109.34999999999999,25.8244],"type":"Point"}
}