{
  "type": "Feature",
  "properties": {
    "gn:admin1_code":"3.0",
    "gn:asciiname":"Yanglongcun",
    "gn:country_code":"CN",
    "gn:dem":24,
    "gn:feature_class":"P",
    "gn:feature_code":"PPL",
    "gn:name":"Yanglongcun",
    "gn:population":0,
    "gn:timezone":"Asia/Shanghai",
    "iso:country":"CN",
    "name:und_x_variant":[
        "\u6768\u5784\u6751"
    ],
    "wof:name":"Yanglongcun",
    "wof:placetype":"locality"
},
  "geometry": {"coordinates":[116.47069999999999,28.52621],"type":"Point"}
}