{
  "type": "Feature",
  "properties": {
    "gn:admin1_code":"32.0",
    "gn:asciiname":"Wagou",
    "gn:country_code":"CN",
    "gn:dem":2775,
    "gn:feature_class":"P",
    "gn:feature_code":"PPL",
    "gn:name":"Wagou",
    "gn:population":0,
    "gn:timezone":"Asia/Shanghai",
    "iso:country":"CN",
    "name:fra_x_preferred":[
        "Wagou"
    ],
    "name:zho_x_preferred":[
        "\u74e6\u6c9f"
    ],
    "wof:name":"Wagou",
    "wof:placetype":"locality"
},
  "geometry": {"coordinates":[102.93000000000001,27.6685],"type":"Point"}
}