{
  "type": "Feature",
  "properties": {
    "gn:admin1_code":"26.0",
    "gn:asciiname":"Youfangtai",
    "gn:cc2":"CN",
    "gn:country_code":"CN",
    "gn:dem":1408,
    "gn:feature_class":"P",
    "gn:feature_code":"PPL",
    "gn:name":"Youfangtai",
    "gn:population":0,
    "gn:timezone":"Asia/Shanghai",
    "iso:country":"CN",
    "name:und_x_variant":[
        "Yu-fang-t\u2019ai",
        "Youfangtai"
    ],
    "wof:name":"Youfangtai",
    "wof:placetype":"locality"
},
  "geometry": {"coordinates":[109.07639,35.31111],"type":"Point"}
}