{
  "type": "Feature",
  "properties": {
    "gn:admin1_code":"8.0",
    "gn:asciiname":"Shengli'ercun",
    "gn:country_code":"CN",
    "gn:dem":159,
    "gn:feature_class":"P",
    "gn:feature_code":"PPL",
    "gn:name":"Shengli\u2019ercun",
    "gn:population":0,
    "gn:timezone":"Asia/Shanghai",
    "iso:country":"CN",
    "name:und_x_variant":[
        "Shengli\u2019ercun"
    ],
    "name:zho_x_preferred":[
        "\u80dc\u5229\u4e8c\u6751"
    ],
    "wof:name":"Shengli'ercun",
    "wof:placetype":"locality"
},
  "geometry": {"coordinates":[126.78343999999998,46.51313],"type":"Point"}
}