{
  "type": "Feature",
  "properties": {
    "gn:admin1_code":"5.0",
    "gn:asciiname":"Qianyingzicun",
    "gn:country_code":"CN",
    "gn:dem":132,
    "gn:feature_class":"P",
    "gn:feature_code":"PPL",
    "gn:name":"Qianyingzicun",
    "gn:population":0,
    "gn:timezone":"Asia/Shanghai",
    "iso:country":"CN",
    "name:zho_x_preferred":[
        "\u524d\u8425\u5b50\u6751"
    ],
    "wof:name":"Qianyingzicun",
    "wof:placetype":"locality"
},
  "geometry": {"coordinates":[124.67871,45.04772],"type":"Point"}
}