{
  "type": "Feature",
  "properties": {
    "gn:admin1_code":"25.0",
    "gn:asciiname":"Maliankoucun",
    "gn:country_code":"CN",
    "gn:dem":140,
    "gn:feature_class":"P",
    "gn:feature_code":"PPL",
    "gn:name":"Maliankoucun",
    "gn:population":0,
    "gn:timezone":"Asia/Shanghai",
    "iso:country":"CN",
    "name:zho_x_preferred":[
        "\u9a6c\u8fde\u53e3\u6751"
    ],
    "wof:name":"Maliankoucun",
    "wof:placetype":"locality"
},
  "geometry": {"coordinates":[119.52030999999999,35.74744000000001],"type":"Point"}
}