{
  "type": "Feature",
  "properties": {
    "gn:admin1_code":"11.0",
    "gn:asciiname":"Dafanjialong",
    "gn:country_code":"CN",
    "gn:dem":86,
    "gn:feature_class":"P",
    "gn:feature_code":"PPL",
    "gn:name":"Dafanjialong",
    "gn:population":0,
    "gn:timezone":"Asia/Shanghai",
    "iso:country":"CN",
    "name:zho_x_preferred":[
        "\u5927\u8303\u5bb6\u5785"
    ],
    "wof:name":"Dafanjialong",
    "wof:placetype":"locality"
},
  "geometry": {"coordinates":[112.57285,26.98823],"type":"Point"}
}