{
  "type": "Feature",
  "properties": {
    "gn:admin1_code":"33.0",
    "gn:asciiname":"Hutang",
    "gn:country_code":"CN",
    "gn:dem":251,
    "gn:feature_class":"P",
    "gn:feature_code":"PPL",
    "gn:name":"Hutang",
    "gn:population":0,
    "gn:timezone":"Asia/Shanghai",
    "iso:country":"CN",
    "name:zho_x_preferred":[
        "\u6e56\u5858"
    ],
    "wof:name":"Hutang",
    "wof:placetype":"locality"
},
  "geometry": {"coordinates":[106.20757,30.19042],"type":"Point"}
}