{
  "type": "Feature",
  "properties": {
    "gn:admin1_code":"32.0",
    "gn:asciiname":"Jinlongsi",
    "gn:country_code":"CN",
    "gn:dem":541,
    "gn:feature_class":"P",
    "gn:feature_code":"PPL",
    "gn:name":"Jinlongsi",
    "gn:population":0,
    "gn:timezone":"Asia/Shanghai",
    "iso:country":"CN",
    "name:zho_x_preferred":[
        "\u91d1\u9f99\u5bfa"
    ],
    "wof:name":"Jinlongsi",
    "wof:placetype":"locality"
},
  "geometry": {"coordinates":[104.657,31.6178],"type":"Point"}
}