{
  "type": "Feature",
  "properties": {
    "gn:admin1_code":"26.0",
    "gn:asciiname":"Yinbianli",
    "gn:country_code":"CN",
    "gn:dem":1497,
    "gn:feature_class":"P",
    "gn:feature_code":"PPL",
    "gn:name":"Yinbianli",
    "gn:population":0,
    "gn:timezone":"Asia/Shanghai",
    "iso:country":"CN",
    "name:und_x_variant":[
        "Yin-chia-pa",
        "Yinjiaba",
        "Yinbianli",
        "\u9634\u78a5\u91cc"
    ],
    "wof:name":"Yinbianli",
    "wof:placetype":"locality"
},
  "geometry": {"coordinates":[106.44889999999999,32.71582],"type":"Point"}
}