{
  "type": "Feature",
  "properties": {
    "gn:admin1_code":"14.0",
    "gn:asciiname":"Gongcicun",
    "gn:country_code":"CN",
    "gn:dem":2902,
    "gn:feature_class":"P",
    "gn:feature_code":"PPL",
    "gn:name":"Gongcicun",
    "gn:population":0,
    "gn:timezone":"Asia/Urumqi",
    "iso:country":"CN",
    "name:zho_x_preferred":[
        "\u8d21\u6b21\u6751"
    ],
    "wof:name":"Gongcicun",
    "wof:placetype":"locality"
},
  "geometry": {"coordinates":[94.65022,30.02115],"type":"Point"}
}