{
  "type": "Feature",
  "properties": {
    "gn:admin1_code":"26.0",
    "gn:asciiname":"Hejiahecun",
    "gn:country_code":"CN",
    "gn:dem":614,
    "gn:feature_class":"P",
    "gn:feature_code":"PPL",
    "gn:name":"Hejiahecun",
    "gn:population":0,
    "gn:timezone":"Asia/Shanghai",
    "iso:country":"CN",
    "name:zho_x_preferred":[
        "\u8d3a\u5bb6\u6cb3\u6751"
    ],
    "wof:name":"Hejiahecun",
    "wof:placetype":"locality"
},
  "geometry": {"coordinates":[110.35415999999999,36.84324],"type":"Point"}
}