{
  "type": "Feature",
  "properties": {
    "gn:admin1_code":"18.0",
    "gn:asciiname":"Guantang",
    "gn:country_code":"CN",
    "gn:dem":615,
    "gn:feature_class":"P",
    "gn:feature_code":"PPL",
    "gn:name":"Guantang",
    "gn:population":0,
    "gn:timezone":"Asia/Shanghai",
    "iso:country":"CN",
    "name:zho_x_preferred":[
        "\u5173\u5858"
    ],
    "wof:name":"Guantang",
    "wof:placetype":"locality"
},
  "geometry": {"coordinates":[108.59399999999999,27.0655],"type":"Point"}
}