{
  "type": "Feature",
  "properties": {
    "gn:admin1_code":"4.0",
    "gn:asciiname":"Xinzhou",
    "gn:country_code":"CN",
    "gn:dem":5,
    "gn:feature_class":"P",
    "gn:feature_code":"PPL",
    "gn:name":"Xinzhou",
    "gn:population":0,
    "gn:timezone":"Asia/Shanghai",
    "iso:country":"CN",
    "name:und_x_variant":[
        "\u65b0\u6d32"
    ],
    "wof:name":"Xinzhou",
    "wof:placetype":"locality"
},
  "geometry": {"coordinates":[118.87935,32.23905],"type":"Point"}
}