{
  "type": "Feature",
  "properties": {
    "gn:admin1_code":"11.0",
    "gn:asciiname":"Baohegang",
    "gn:country_code":"CN",
    "gn:dem":89,
    "gn:feature_class":"P",
    "gn:feature_code":"PPL",
    "gn:name":"Baohegang",
    "gn:population":0,
    "gn:timezone":"Asia/Shanghai",
    "iso:country":"CN",
    "name:zho_x_preferred":[
        "Baohegang"
    ],
    "name:zho_x_variant":[
        "\u4fdd\u548c\u6e2f"
    ],
    "wof:name":"Baohegang",
    "wof:placetype":"locality"
},
  "geometry": {"coordinates":[111.13025,29.2067],"type":"Point"}
}