{
  "type": "Feature",
  "properties": {
    "gn:admin1_code":"11.0",
    "gn:asciiname":"Centan Nongchang Erdadui",
    "gn:country_code":"CN",
    "gn:dem":35,
    "gn:feature_class":"P",
    "gn:feature_code":"PPLF",
    "gn:name":"Centan Nongchang Erdadui",
    "gn:population":0,
    "gn:timezone":"Asia/Shanghai",
    "iso:country":"CN",
    "name:zho_x_preferred":[
        "Centan Nongchang Erdadui"
    ],
    "name:zho_x_variant":[
        "\u6d94\u6fb9\u519c\u573a\u4e8c\u5927\u961f"
    ],
    "wof:name":"Centan Nongchang Erdadui",
    "wof:placetype":"locality"
},
  "geometry": {"coordinates":[111.87396,29.68373],"type":"Point"}
}