{
  "type": "Feature",
  "properties": {
    "gn:admin1_code":"10.0",
    "gn:asciiname":"Dongzhaotong",
    "gn:country_code":"CN",
    "gn:dem":71,
    "gn:feature_class":"P",
    "gn:feature_code":"PPL",
    "gn:name":"Dongzhaotong",
    "gn:population":0,
    "gn:timezone":"Asia/Shanghai",
    "iso:country":"CN",
    "name:und_x_variant":[
        "\u4e1c\u5146\u901a"
    ],
    "wof:name":"Dongzhaotong",
    "wof:placetype":"locality"
},
  "geometry": {"coordinates":[114.60533999999998,38.07283],"type":"Point"}
}