{
  "type": "Feature",
  "properties": {
    "gn:admin1_code":"11",
    "gn:asciiname":"Yijia",
    "gn:country_code":"CN",
    "gn:dem":582,
    "gn:feature_class":"P",
    "gn:feature_code":"PPL",
    "gn:name":"Yijia",
    "gn:population":0,
    "gn:timezone":"Asia/Shanghai",
    "iso:country":"CN",
    "name:und_x_variant":[
        "\u6613\u5bb6",
        "Yijia"
    ],
    "wof:name":"Yijia",
    "wof:placetype":"locality"
},
  "geometry": {"coordinates":[111.60639,25.75444],"type":"Point"}
}