{
  "type": "Feature",
  "properties": {
    "gn:admin1_code":"30.0",
    "gn:asciiname":"Xizhuli",
    "gn:country_code":"CN",
    "gn:dem":4,
    "gn:feature_class":"P",
    "gn:feature_code":"PPL",
    "gn:name":"Xizhuli",
    "gn:population":0,
    "gn:timezone":"Asia/Shanghai",
    "iso:country":"CN",
    "name:zho_x_preferred":[
        "\u6eaa\u7af9\u91cc"
    ],
    "wof:name":"Xizhuli",
    "wof:placetype":"locality"
},
  "geometry": {"coordinates":[112.72781000000001,22.4215],"type":"Point"}
}