{
  "type": "Feature",
  "properties": {
    "gn:admin1_code":"12.0",
    "gn:asciiname":"Dongchang",
    "gn:country_code":"CN",
    "gn:dem":34,
    "gn:feature_class":"P",
    "gn:feature_code":"PPL",
    "gn:name":"Dongchang",
    "gn:population":0,
    "gn:timezone":"Asia/Shanghai",
    "iso:country":"CN",
    "name:ceb_x_preferred":[
        "Dongchang"
    ],
    "name:deu_x_preferred":[
        "Dongchang"
    ],
    "name:zho_x_preferred":[
        "\u8463\u573a"
    ],
    "wof:name":"Dongchang",
    "wof:placetype":"locality"
},
  "geometry": {"coordinates":[112.60729000000001,30.61355],"type":"Point"}
}