{
  "type": "Feature",
  "properties": {
    "gn:admin1_code":"19.0",
    "gn:asciiname":"Qinjiagou",
    "gn:country_code":"CN",
    "gn:dem":230,
    "gn:feature_class":"P",
    "gn:feature_code":"PPL",
    "gn:name":"Qinjiagou",
    "gn:population":0,
    "gn:timezone":"Asia/Shanghai",
    "iso:country":"CN",
    "name:zho_x_preferred":[
        "\u79e6\u5bb6\u6c9f"
    ],
    "wof:name":"Qinjiagou",
    "wof:placetype":"locality"
},
  "geometry": {"coordinates":[120.80398,41.1259],"type":"Point"}
}