{
  "type": "Feature",
  "properties": {
    "gn:admin1_code":"28.0",
    "gn:asciiname":"Nanyingmen",
    "gn:country_code":"CN",
    "gn:dem":7,
    "gn:feature_class":"P",
    "gn:feature_code":"PPLA4",
    "gn:name":"Nanyingmen",
    "gn:population":0,
    "gn:timezone":"Asia/Shanghai",
    "iso:country":"CN",
    "name:und_x_variant":[
        "Nanyingmen Jiedao"
    ],
    "name:zho_x_preferred":[
        "\u5357\u8425\u95e8"
    ],
    "name:zho_x_variant":[
        "\u5357\u8425\u95e8\u8857\u9053"
    ],
    "wof:name":"Nanyingmen",
    "wof:placetype":"locality"
},
  "geometry": {"coordinates":[117.1788,39.11707],"type":"Point"}
}