{
  "type": "Feature",
  "properties": {
    "gn:admin1_code":"10",
    "gn:asciiname":"Xihuagou",
    "gn:country_code":"CN",
    "gn:dem":750,
    "gn:feature_class":"P",
    "gn:feature_code":"PPL",
    "gn:name":"Xihuagou",
    "gn:population":0,
    "gn:timezone":"Asia/Shanghai",
    "iso:country":"CN",
    "name:zho_x_preferred":[
        "\u897f\u82b1\u6c9f"
    ],
    "wof:name":"Xihuagou",
    "wof:placetype":"locality"
},
  "geometry": {"coordinates":[114.011,37.2763],"type":"Point"}
}