{
  "type": "Feature",
  "properties": {
    "gn:admin1_code":"26",
    "gn:asciiname":"Nanyicun",
    "gn:country_code":"CN",
    "gn:dem":349,
    "gn:feature_class":"P",
    "gn:feature_code":"PPL",
    "gn:name":"Nanyicun",
    "gn:population":0,
    "gn:timezone":"Asia/Shanghai",
    "iso:country":"CN",
    "name:zho_x_preferred":[
        "\u5357\u5f0b\u6751"
    ],
    "wof:name":"Nanyicun",
    "wof:placetype":"locality"
},
  "geometry": {"coordinates":[109.43680999999999,34.56377],"type":"Point"}
}