{
  "type": "Feature",
  "properties": {
    "gn:admin1_code":"2.0",
    "gn:asciiname":"Chengmen",
    "gn:country_code":"CN",
    "gn:dem":64,
    "gn:feature_class":"P",
    "gn:feature_code":"PPL",
    "gn:name":"Chengmen",
    "gn:population":0,
    "gn:timezone":"Asia/Shanghai",
    "iso:country":"CN",
    "name:zho_x_preferred":[
        "\u57ce\u95e8"
    ],
    "wof:name":"Chengmen",
    "wof:placetype":"locality"
},
  "geometry": {"coordinates":[120.08741999999999,28.13557],"type":"Point"}
}