{
  "type": "Feature",
  "properties": {
    "gn:admin1_code":"8.0",
    "gn:asciiname":"Wangpaotun",
    "gn:country_code":"CN",
    "gn:dem":185,
    "gn:feature_class":"P",
    "gn:feature_code":"PPL",
    "gn:name":"Wangpaotun",
    "gn:population":0,
    "gn:timezone":"Asia/Shanghai",
    "iso:country":"CN",
    "name:zho_x_preferred":[
        "\u738b\u70ae\u5c6f"
    ],
    "wof:name":"Wangpaotun",
    "wof:placetype":"locality"
},
  "geometry": {"coordinates":[126.76616,46.74413],"type":"Point"}
}