{
  "type": "Feature",
  "properties": {
    "gn:admin1_code":"33.0",
    "gn:asciiname":"Guangfo",
    "gn:country_code":"CN",
    "gn:dem":531,
    "gn:feature_class":"P",
    "gn:feature_code":"PPL",
    "gn:name":"Guangfo",
    "gn:population":0,
    "gn:timezone":"Asia/Shanghai",
    "iso:country":"CN",
    "name:zho_x_preferred":[
        "\u5e7f\u4f5b"
    ],
    "wof:name":"Guangfo",
    "wof:placetype":"locality"
},
  "geometry": {"coordinates":[106.72163999999999,29.86234],"type":"Point"}
}