{
  "type": "Feature",
  "properties": {
    "gn:admin1_code":"25",
    "gn:asciiname":"Xilonggang",
    "gn:country_code":"CN",
    "gn:dem":123,
    "gn:feature_class":"P",
    "gn:feature_code":"PPL",
    "gn:name":"Xilonggang",
    "gn:population":0,
    "gn:timezone":"Asia/Shanghai",
    "iso:country":"CN",
    "name:zho_x_preferred":[
        "\u897f\u9f99\u5c97"
    ],
    "wof:name":"Xilonggang",
    "wof:placetype":"locality"
},
  "geometry": {"coordinates":[117.98399999999999,35.3953],"type":"Point"}
}