{
  "type": "Feature",
  "properties": {
    "gn:admin1_code":"16",
    "gn:asciiname":"Caojiachong",
    "gn:country_code":"CN",
    "gn:dem":390,
    "gn:feature_class":"P",
    "gn:feature_code":"PPL",
    "gn:name":"Caojiachong",
    "gn:population":0,
    "gn:timezone":"Asia/Shanghai",
    "iso:country":"CN",
    "name:zho_x_preferred":[
        "\u66f9\u5bb6\u51b2"
    ],
    "wof:name":"Caojiachong",
    "wof:placetype":"locality"
},
  "geometry": {"coordinates":[110.66200000000001,26.0677],"type":"Point"}
}