{
  "type": "Feature",
  "properties": {
    "gn:admin1_code":"29",
    "gn:asciiname":"Beizhini",
    "gn:country_code":"CN",
    "gn:dem":1198,
    "gn:feature_class":"P",
    "gn:feature_code":"PPL",
    "gn:name":"Beizhini",
    "gn:population":0,
    "gn:timezone":"Asia/Shanghai",
    "iso:country":"CN",
    "name:zho_x_preferred":[
        "\u5317\u4e4b\u4f60"
    ],
    "wof:name":"Beizhini",
    "wof:placetype":"locality"
},
  "geometry": {"coordinates":[101.91500000000001,23.8463],"type":"Point"}
}