{
  "type": "Feature",
  "properties": {
    "gn:admin1_code":"2.0",
    "gn:asciiname":"Xiaowuli",
    "gn:country_code":"CN",
    "gn:dem":15,
    "gn:feature_class":"P",
    "gn:feature_code":"PPL",
    "gn:name":"Xiaowuli",
    "gn:population":0,
    "gn:timezone":"Asia/Shanghai",
    "iso:country":"CN",
    "name:und_x_variant":[
        "\u5c0f\u575e\u91cc",
        "Xiaowuli"
    ],
    "wof:name":"Xiaowuli",
    "wof:placetype":"locality"
},
  "geometry": {"coordinates":[119.93079,29.98924],"type":"Point"}
}