{
  "type": "Feature",
  "properties": {
    "gn:admin1_code":"7.0",
    "gn:asciiname":"Guangxiao",
    "gn:country_code":"CN",
    "gn:dem":97,
    "gn:feature_class":"P",
    "gn:feature_code":"PPL",
    "gn:name":"Guangxiao",
    "gn:population":0,
    "gn:timezone":"Asia/Shanghai",
    "iso:country":"CN",
    "name:zho_x_preferred":[
        "\u5149\u5b5d"
    ],
    "wof:name":"Guangxiao",
    "wof:placetype":"locality"
},
  "geometry": {"coordinates":[118.08181,24.99858],"type":"Point"}
}