{
  "type": "Feature",
  "properties": {
    "gn:admin1_code":"29.0",
    "gn:asciiname":"Laocunzi",
    "gn:country_code":"CN",
    "gn:dem":2372,
    "gn:feature_class":"P",
    "gn:feature_code":"PPL",
    "gn:name":"Laocunzi",
    "gn:population":0,
    "gn:timezone":"Asia/Shanghai",
    "iso:country":"CN",
    "name:zho_x_preferred":[
        "\u8001\u6751\u5b50"
    ],
    "wof:name":"Laocunzi",
    "wof:placetype":"locality"
},
  "geometry": {"coordinates":[102.88200000000001,25.9431],"type":"Point"}
}