{
  "type": "Feature",
  "properties": {
    "gn:admin1_code":"11.0",
    "gn:asciiname":"Zhendeqiao",
    "gn:country_code":"CN",
    "gn:dem":34,
    "gn:feature_class":"P",
    "gn:feature_code":"PPLA4",
    "gn:name":"Zhendeqiao",
    "gn:population":0,
    "gn:timezone":"Asia/Shanghai",
    "iso:country":"CN",
    "name:und_x_variant":[
        "\u9547\u5fb7\u6865",
        "Zhendeqiao Zhen",
        "\u9547\u5fb7\u6865\u9547"
    ],
    "wof:name":"Zhendeqiao",
    "wof:placetype":"locality"
},
  "geometry": {"coordinates":[111.82807,29.13794],"type":"Point"}
}