{
  "type": "Feature",
  "properties": {
    "gn:admin1_code":"16.0",
    "gn:asciiname":"Basha",
    "gn:country_code":"CN",
    "gn:dem":506,
    "gn:feature_class":"P",
    "gn:feature_code":"PPL",
    "gn:name":"Basha",
    "gn:population":0,
    "gn:timezone":"Asia/Shanghai",
    "iso:country":"CN",
    "name:zho_x_preferred":[
        "\u516b\u6c99"
    ],
    "wof:name":"Basha",
    "wof:placetype":"locality"
},
  "geometry": {"coordinates":[105.583,24.1407],"type":"Point"}
}