{
  "type": "Feature",
  "properties": {
    "gn:admin1_code":"16.0",
    "gn:asciiname":"Laoxuchang",
    "gn:country_code":"CN",
    "gn:dem":839,
    "gn:feature_class":"P",
    "gn:feature_code":"PPL",
    "gn:name":"Laoxuchang",
    "gn:population":0,
    "gn:timezone":"Asia/Shanghai",
    "iso:country":"CN",
    "name:zho_x_preferred":[
        "\u8001\u5729\u573a"
    ],
    "wof:name":"Laoxuchang",
    "wof:placetype":"locality"
},
  "geometry": {"coordinates":[107.649,24.9147],"type":"Point"}
}