{
  "type": "Feature",
  "properties": {
    "gn:admin1_code":"32.0",
    "gn:asciiname":"Hanjia Citang",
    "gn:country_code":"CN",
    "gn:dem":520,
    "gn:feature_class":"P",
    "gn:feature_code":"PPL",
    "gn:name":"Hanjia Citang",
    "gn:population":0,
    "gn:timezone":"Asia/Shanghai",
    "iso:country":"CN",
    "name:zho_x_preferred":[
        "\u97e9\u5bb6\u7960\u5802"
    ],
    "wof:name":"Hanjia Citang",
    "wof:placetype":"locality"
},
  "geometry": {"coordinates":[105.81147,32.45531],"type":"Point"}
}