{
  "type": "Feature",
  "properties": {
    "gn:admin1_code":"32.0",
    "gn:asciiname":"Huguo",
    "gn:country_code":"CN",
    "gn:dem":571,
    "gn:feature_class":"P",
    "gn:feature_code":"PPL",
    "gn:name":"Huguo",
    "gn:population":0,
    "gn:timezone":"Asia/Shanghai",
    "iso:country":"CN",
    "name:deu_x_preferred":[
        "Huguo"
    ],
    "name:zho_x_preferred":[
        "\u62a4\u56fd"
    ],
    "wof:name":"Huguo",
    "wof:placetype":"locality"
},
  "geometry": {"coordinates":[103.95399999999999,30.9512],"type":"Point"}
}