{
  "type": "Feature",
  "properties": {
    "gn:admin1_code":"19.0",
    "gn:asciiname":"Xiliushugou",
    "gn:country_code":"CN",
    "gn:dem":239,
    "gn:feature_class":"P",
    "gn:feature_code":"PPL",
    "gn:name":"Xiliushugou",
    "gn:population":0,
    "gn:timezone":"Asia/Shanghai",
    "iso:country":"CN",
    "name:zho_x_preferred":[
        "\u897f\u67f3\u6811\u6c9f"
    ],
    "wof:name":"Xiliushugou",
    "wof:placetype":"locality"
},
  "geometry": {"coordinates":[120.92100000000001,41.4558],"type":"Point"}
}