{
  "type": "Feature",
  "properties": {
    "gn:admin1_code":"12.0",
    "gn:asciiname":"Heping",
    "gn:country_code":"CN",
    "gn:dem":1455,
    "gn:feature_class":"P",
    "gn:feature_code":"PPL",
    "gn:name":"Heping",
    "gn:population":0,
    "gn:timezone":"Asia/Shanghai",
    "iso:country":"CN",
    "name:zho_x_preferred":[
        "\u8d3a\u576a"
    ],
    "wof:name":"Heping",
    "wof:placetype":"locality"
},
  "geometry": {"coordinates":[110.70819,30.81701],"type":"Point"}
}