{
  "type": "Feature",
  "properties": {
    "gn:admin1_code":"16.0",
    "gn:asciiname":"Tianyan",
    "gn:country_code":"CN",
    "gn:dem":28,
    "gn:feature_class":"P",
    "gn:feature_code":"PPL",
    "gn:name":"Tianyan",
    "gn:population":0,
    "gn:timezone":"Asia/Shanghai",
    "iso:country":"CN",
    "name:zho_x_preferred":[
        "\u5929\u5ca9"
    ],
    "wof:name":"Tianyan",
    "wof:placetype":"locality"
},
  "geometry": {"coordinates":[108.31399999999999,21.9525],"type":"Point"}
}