{
  "type": "Feature",
  "properties": {
    "gn:admin1_code":"11",
    "gn:asciiname":"Shidongqiao",
    "gn:country_code":"CN",
    "gn:dem":104,
    "gn:feature_class":"P",
    "gn:feature_code":"PPL",
    "gn:name":"Shidongqiao",
    "gn:population":0,
    "gn:timezone":"Asia/Shanghai",
    "iso:country":"CN",
    "name:zho_x_preferred":[
        "\u77f3\u6d1e\u6865"
    ],
    "wof:name":"Shidongqiao",
    "wof:placetype":"locality"
},
  "geometry": {"coordinates":[112.30083999999999,26.67383],"type":"Point"}
}