{
  "type": "Feature",
  "properties": {
    "gn:admin1_code":"08",
    "gn:asciiname":"Fukeshan",
    "gn:cc2":"CN",
    "gn:country_code":"CN",
    "gn:dem":541,
    "gn:feature_class":"P",
    "gn:feature_code":"PPL",
    "gn:name":"Fukeshan",
    "gn:population":0,
    "gn:timezone":"Asia/Shanghai",
    "iso:country":"CN",
    "name:und_x_variant":[
        "Fu-k\u2019o-shan",
        "Fukeshan"
    ],
    "wof:name":"Fukeshan",
    "wof:placetype":"locality"
},
  "geometry": {"coordinates":[121.95,52.65],"type":"Point"}
}