{
  "type": "Feature",
  "properties": {
    "gn:admin1_code":"03",
    "gn:asciiname":"Maodian",
    "gn:country_code":"CN",
    "gn:dem":118,
    "gn:feature_class":"P",
    "gn:feature_code":"PPLA4",
    "gn:name":"Maodian",
    "gn:population":0,
    "gn:timezone":"Asia/Shanghai",
    "iso:country":"CN",
    "name:und_x_variant":[
        "Mao-tien",
        "Maodian",
        "\u8305\u5e97",
        "Maodian Zhen",
        "\u8305\u5e97\u9547"
    ],
    "wof:name":"Maodian",
    "wof:placetype":"locality"
},
  "geometry": {"coordinates":[115.04482,25.90583],"type":"Point"}
}