{
  "type": "Feature",
  "properties": {
    "gn:admin1_code":"9",
    "gn:asciiname":"Lulou",
    "gn:country_code":"CN",
    "gn:dem":59,
    "gn:feature_class":"P",
    "gn:feature_code":"PPL",
    "gn:name":"Lulou",
    "gn:population":0,
    "gn:timezone":"Asia/Shanghai",
    "iso:country":"CN",
    "name:zho_x_preferred":[
        "\u9c81\u697c"
    ],
    "wof:name":"Lulou",
    "wof:placetype":"locality"
},
  "geometry": {"coordinates":[115.063,34.3782],"type":"Point"}
}