{
  "type": "Feature",
  "properties": {
    "gn:admin1_code":"8.0",
    "gn:asciiname":"Qianguanjialu",
    "gn:country_code":"CN",
    "gn:dem":182,
    "gn:feature_class":"P",
    "gn:feature_code":"PPL",
    "gn:name":"Qianguanjialu",
    "gn:population":0,
    "gn:timezone":"Asia/Shanghai",
    "iso:country":"CN",
    "name:zho_x_preferred":[
        "\u524d\u5173\u5bb6\u7089"
    ],
    "wof:name":"Qianguanjialu",
    "wof:placetype":"locality"
},
  "geometry": {"coordinates":[127.38468,45.02511],"type":"Point"}
}