{
  "type": "Feature",
  "properties": {
    "gn:admin1_code":"25",
    "gn:asciiname":"Zifangmu",
    "gn:country_code":"CN",
    "gn:dem":47,
    "gn:feature_class":"P",
    "gn:feature_code":"PPL",
    "gn:name":"Zifangmu",
    "gn:population":0,
    "gn:timezone":"Asia/Shanghai",
    "iso:country":"CN",
    "name:und_x_variant":[
        "Zifangdong"
    ],
    "name:zho_x_preferred":[
        "\u5b50\u623f\u5893"
    ],
    "name:zho_x_variant":[
        "\u5b50\u623f\u4e1c"
    ],
    "wof:name":"Zifangmu",
    "wof:placetype":"locality"
},
  "geometry": {"coordinates":[115.851,35.7533],"type":"Point"}
}