{
  "type": "Feature",
  "properties": {
    "gn:admin1_code":"26.0",
    "gn:asciiname":"Yintuocun",
    "gn:country_code":"CN",
    "gn:dem":993,
    "gn:feature_class":"P",
    "gn:feature_code":"PPL",
    "gn:name":"Yintuocun",
    "gn:population":0,
    "gn:timezone":"Asia/Shanghai",
    "iso:country":"CN",
    "name:zho_x_preferred":[
        "\u5370\u9a6e\u6751"
    ],
    "wof:name":"Yintuocun",
    "wof:placetype":"locality"
},
  "geometry": {"coordinates":[110.22337,36.75593],"type":"Point"}
}