{
  "type": "Feature",
  "properties": {
    "gn:admin1_code":"25.0",
    "gn:asciiname":"Dongdongmen",
    "gn:cc2":"CN",
    "gn:country_code":"CN",
    "gn:dem":38,
    "gn:feature_class":"P",
    "gn:feature_code":"PPL",
    "gn:name":"Dongdongmen",
    "gn:population":0,
    "gn:timezone":"Asia/Shanghai",
    "iso:country":"CN",
    "name:zho_x_preferred":[
        "\u4e1c\u6d1e\u95e8"
    ],
    "wof:name":"Dongdongmen",
    "wof:placetype":"locality"
},
  "geometry": {"coordinates":[120.11123000000001,36.00477],"type":"Point"}
}