{
  "type": "Feature",
  "properties": {
    "gn:admin1_code":"26.0",
    "gn:asciiname":"Yangzhuangkecun",
    "gn:country_code":"CN",
    "gn:dem":1170,
    "gn:feature_class":"P",
    "gn:feature_code":"PPL",
    "gn:name":"Yangzhuangkecun",
    "gn:population":0,
    "gn:timezone":"Asia/Shanghai",
    "iso:country":"CN",
    "name:zho_x_preferred":[
        "\u6768\u5e84\u79d1\u6751"
    ],
    "wof:name":"Yangzhuangkecun",
    "wof:placetype":"locality"
},
  "geometry": {"coordinates":[109.42034,36.35948],"type":"Point"}
}