{
  "type": "Feature",
  "properties": {
    "gn:admin1_code":"30",
    "gn:admin2_code":"1787530.0",
    "gn:asciiname":"Chepo",
    "gn:country_code":"CN",
    "gn:dem":28,
    "gn:feature_class":"P",
    "gn:feature_code":"PPL",
    "gn:name":"Chepo",
    "gn:population":0,
    "gn:timezone":"Asia/Shanghai",
    "iso:country":"CN",
    "name:ita_x_preferred":[
        "Chepo"
    ],
    "name:zho_x_preferred":[
        "\u8f66\u5761"
    ],
    "wof:name":"Chepo",
    "wof:placetype":"locality"
},
  "geometry": {"coordinates":[111.89404,22.33466],"type":"Point"}
}