{
  "type": "Feature",
  "properties": {
    "gn:admin1_code":"30",
    "gn:asciiname":"Changping",
    "gn:country_code":"CN",
    "gn:dem":65,
    "gn:feature_class":"P",
    "gn:feature_code":"PPL",
    "gn:name":"Changping",
    "gn:population":0,
    "gn:timezone":"Asia/Urumqi",
    "iso:country":"CN",
    "name:ceb_x_preferred":[
        "Changping"
    ],
    "name:ces_x_preferred":[
        "\u010cchang-pching"
    ],
    "name:mlg_x_preferred":[
        "Changping"
    ],
    "name:swe_x_preferred":[
        "Changping"
    ],
    "name:zho_x_preferred":[
        "\u660c\u5e73"
    ],
    "wof:name":"Changping",
    "wof:placetype":"locality"
},
  "geometry": {"coordinates":[110.02528999999998,20.70109],"type":"Point"}
}