{
  "type": "Feature",
  "properties": {
    "gn:admin1_code":"9.0",
    "gn:asciiname":"Shuanglunhe",
    "gn:country_code":"CN",
    "gn:dem":73,
    "gn:feature_class":"P",
    "gn:feature_code":"PPL",
    "gn:name":"Shuanglunhe",
    "gn:population":0,
    "gn:timezone":"Asia/Shanghai",
    "iso:country":"CN",
    "name:zho_x_preferred":[
        "\u53cc\u8f6e\u6cb3"
    ],
    "wof:name":"Shuanglunhe",
    "wof:placetype":"locality"
},
  "geometry": {"coordinates":[115.11497,31.85093],"type":"Point"}
}