{
  "type": "Feature",
  "properties": {
    "gn:admin1_code":"7.0",
    "gn:asciiname":"Luojingxi",
    "gn:country_code":"CN",
    "gn:dem":825,
    "gn:feature_class":"P",
    "gn:feature_code":"PPL",
    "gn:name":"Luojingxi",
    "gn:population":0,
    "gn:timezone":"Asia/Shanghai",
    "iso:country":"CN",
    "name:und_x_variant":[
        "\u843d\u4e95\u6eaa"
    ],
    "name:zho_x_preferred":[
        "\u843d\u4e95\u6eaa"
    ],
    "wof:name":"Luojingxi",
    "wof:placetype":"locality"
},
  "geometry": {"coordinates":[116.98983,27.05662],"type":"Point"}
}