{
  "type": "Feature",
  "properties": {
    "gn:admin1_code":"1.0",
    "gn:asciiname":"Gaojiancun",
    "gn:country_code":"CN",
    "gn:dem":134,
    "gn:feature_class":"P",
    "gn:feature_code":"PPL",
    "gn:name":"Gaojiancun",
    "gn:population":0,
    "gn:timezone":"Asia/Shanghai",
    "iso:country":"CN",
    "name:und_x_variant":[
        "Gaojian"
    ],
    "name:zho_x_preferred":[
        "\u9ad8\u7b80\u6751"
    ],
    "name:zho_x_variant":[
        "\u9ad8\u67a7"
    ],
    "wof:name":"Gaojiancun",
    "wof:placetype":"locality"
},
  "geometry": {"coordinates":[118.27368,29.68652],"type":"Point"}
}