{
  "type": "Feature",
  "properties": {
    "gn:admin1_code":"25",
    "gn:asciiname":"Xibojiwang",
    "gn:country_code":"CN",
    "gn:dem":13,
    "gn:feature_class":"P",
    "gn:feature_code":"PPL",
    "gn:name":"Xibojiwang",
    "gn:population":0,
    "gn:timezone":"Asia/Shanghai",
    "iso:country":"CN",
    "name:zho_x_preferred":[
        "\u897f\u7c38\u7b95\u738b"
    ],
    "wof:name":"Xibojiwang",
    "wof:placetype":"locality"
},
  "geometry": {"coordinates":[117.745,37.3159],"type":"Point"}
}