{
  "type": "Feature",
  "properties": {
    "gn:admin1_code":"12.0",
    "gn:asciiname":"Maoliuwan",
    "gn:country_code":"CN",
    "gn:dem":108,
    "gn:feature_class":"P",
    "gn:feature_code":"PPL",
    "gn:name":"Maoliuwan",
    "gn:population":0,
    "gn:timezone":"Asia/Shanghai",
    "iso:country":"CN",
    "name:und_x_variant":[
        "\u8302\u516d\u5846"
    ],
    "wof:name":"Maoliuwan",
    "wof:placetype":"locality"
},
  "geometry": {"coordinates":[115.43098999999999,30.46498],"type":"Point"}
}