{
  "type": "Feature",
  "properties": {
    "gn:admin1_code":"14.0",
    "gn:asciiname":"Ringtor",
    "gn:country_code":"CN",
    "gn:dem":5134,
    "gn:feature_class":"P",
    "gn:feature_code":"PPLF",
    "gn:name":"Ringtor",
    "gn:population":0,
    "gn:timezone":"Asia/Urumqi",
    "iso:country":"CN",
    "name:bod_x_preferred":[
        "Ringtor"
    ],
    "name:zho_x_preferred":[
        "Renduo"
    ],
    "name:zho_x_variant":[
        "\u4ec1\u591a"
    ],
    "wof:name":"Ringtor",
    "wof:placetype":"locality"
},
  "geometry": {"coordinates":[83.41667,31.45],"type":"Point"}
}