{
  "type": "Feature",
  "properties": {
    "gn:admin1_code":"16.0",
    "gn:asciiname":"Shanzaidong",
    "gn:country_code":"CN",
    "gn:dem":184,
    "gn:feature_class":"P",
    "gn:feature_code":"PPL",
    "gn:name":"Shanzaidong",
    "gn:population":0,
    "gn:timezone":"Asia/Shanghai",
    "iso:country":"CN",
    "name:zho_x_preferred":[
        "\u5c71\u5d3d\u5cd2"
    ],
    "wof:name":"Shanzaidong",
    "wof:placetype":"locality"
},
  "geometry": {"coordinates":[108.533,24.4978],"type":"Point"}
}