{
  "type": "Feature",
  "properties": {
    "gn:admin1_code":"8.0",
    "gn:asciiname":"Dongliujiucun",
    "gn:country_code":"CN",
    "gn:dem":233,
    "gn:feature_class":"P",
    "gn:feature_code":"PPL",
    "gn:name":"Dongliujiucun",
    "gn:population":0,
    "gn:timezone":"Asia/Shanghai",
    "iso:country":"CN",
    "name:zho_x_preferred":[
        "\u4e1c\u516d\u4e5d\u6751"
    ],
    "wof:name":"Dongliujiucun",
    "wof:placetype":"locality"
},
  "geometry": {"coordinates":[122.91589,46.94913],"type":"Point"}
}