{
  "type": "Feature",
  "properties": {
    "gn:admin1_code":"3.0",
    "gn:asciiname":"Matang Liujia",
    "gn:country_code":"CN",
    "gn:dem":46,
    "gn:feature_class":"P",
    "gn:feature_code":"PPL",
    "gn:name":"Matang Liujia",
    "gn:population":0,
    "gn:timezone":"Asia/Shanghai",
    "iso:country":"CN",
    "name:zho_x_preferred":[
        "\u9ebb\u5858\u5218\u5bb6"
    ],
    "wof:name":"Matang Liujia",
    "wof:placetype":"locality"
},
  "geometry": {"coordinates":[117.05732,28.38231],"type":"Point"}
}