{
  "type": "Feature",
  "properties": {
    "gn:admin1_code":"05",
    "gn:asciiname":"Nadanbo",
    "gn:cc2":"CN",
    "gn:country_code":"CN",
    "gn:dem":282,
    "gn:feature_class":"P",
    "gn:feature_code":"PPL",
    "gn:name":"Nadanbo",
    "gn:population":0,
    "gn:timezone":"Asia/Shanghai",
    "iso:country":"CN",
    "name:und_x_variant":[
        "Na-tan-po",
        "Nadanbo"
    ],
    "wof:name":"Nadanbo",
    "wof:placetype":"locality"
},
  "geometry": {"coordinates":[125.47944,43.18083],"type":"Point"}
}