{
  "type": "Feature",
  "properties": {
    "gn:admin1_code":"24.0",
    "gn:asciiname":"Hejiapo",
    "gn:country_code":"CN",
    "gn:dem":650,
    "gn:feature_class":"P",
    "gn:feature_code":"PPL",
    "gn:name":"Hejiapo",
    "gn:population":0,
    "gn:timezone":"Asia/Shanghai",
    "iso:country":"CN",
    "name:zho_x_preferred":[
        "\u8d3a\u5bb6\u5761"
    ],
    "wof:name":"Hejiapo",
    "wof:placetype":"locality"
},
  "geometry": {"coordinates":[110.50823,36.47091],"type":"Point"}
}