{
  "type": "Feature",
  "properties": {
    "gn:admin1_code":"26.0",
    "gn:asciiname":"Qilimiao",
    "gn:country_code":"CN",
    "gn:dem":894,
    "gn:feature_class":"P",
    "gn:feature_code":"PPL",
    "gn:name":"Qilimiao",
    "gn:population":0,
    "gn:timezone":"Asia/Shanghai",
    "iso:country":"CN",
    "name:und_x_variant":[
        "\u4e03\u91cc\u5e99"
    ],
    "wof:name":"Qilimiao",
    "wof:placetype":"locality"
},
  "geometry": {"coordinates":[109.17004,33.99322],"type":"Point"}
}