{
  "type": "Feature",
  "properties": {
    "gn:admin1_code":"29.0",
    "gn:asciiname":"Baijifan",
    "gn:country_code":"CN",
    "gn:dem":1819,
    "gn:feature_class":"P",
    "gn:feature_code":"PPL",
    "gn:name":"Baijifan",
    "gn:population":0,
    "gn:timezone":"Asia/Shanghai",
    "iso:country":"CN",
    "wof:name":"Baijifan",
    "wof:placetype":"locality"
},
  "geometry": {"coordinates":[99.09999999999999,27.35],"type":"Point"}
}