{
  "type": "Feature",
  "properties": {
    "gn:admin1_code":"4.0",
    "gn:asciiname":"Hongzhuangcun",
    "gn:country_code":"CN",
    "gn:dem":4,
    "gn:feature_class":"P",
    "gn:feature_code":"PPL",
    "gn:name":"Hongzhuangcun",
    "gn:population":0,
    "gn:timezone":"Asia/Shanghai",
    "iso:country":"CN",
    "name:zho_x_preferred":[
        "\u7ea2\u5e84\u6751"
    ],
    "wof:name":"Hongzhuangcun",
    "wof:placetype":"locality"
},
  "geometry": {"coordinates":[120.63231,31.23688],"type":"Point"}
}