{
  "type": "Feature",
  "properties": {
    "gn:admin1_code":"10",
    "gn:asciiname":"Damiao",
    "gn:country_code":"CN",
    "gn:dem":634,
    "gn:feature_class":"P",
    "gn:feature_code":"PPL",
    "gn:name":"Damiao",
    "gn:population":0,
    "gn:timezone":"Asia/Shanghai",
    "iso:country":"CN",
    "wof:name":"Damiao",
    "wof:placetype":"locality"
},
  "geometry": {"coordinates":[117.72583,40.42667],"type":"Point"}
}