{
  "type": "Feature",
  "properties": {
    "gn:admin1_code":"10",
    "gn:asciiname":"Yuquanzhuang",
    "gn:country_code":"CN",
    "gn:dem":20,
    "gn:feature_class":"P",
    "gn:feature_code":"PPL",
    "gn:name":"Yuquanzhuang",
    "gn:population":0,
    "gn:timezone":"Asia/Shanghai",
    "iso:country":"CN",
    "name:zho_x_preferred":[
        "\u7389\u6cc9\u5e84"
    ],
    "wof:name":"Yuquanzhuang",
    "wof:placetype":"locality"
},
  "geometry": {"coordinates":[116.35590999999999,37.65003],"type":"Point"}
}