{
  "type": "Feature",
  "properties": {
    "gn:admin1_code":"11.0",
    "gn:asciiname":"Cheshapo",
    "gn:country_code":"CN",
    "gn:dem":397,
    "gn:feature_class":"P",
    "gn:feature_code":"PPL",
    "gn:name":"Cheshapo",
    "gn:population":0,
    "gn:timezone":"Asia/Shanghai",
    "iso:country":"CN",
    "name:zho_x_preferred":[
        "\u626f\u6c99\u5761"
    ],
    "wof:name":"Cheshapo",
    "wof:placetype":"locality"
},
  "geometry": {"coordinates":[109.34193,29.05353],"type":"Point"}
}