{
  "type": "Feature",
  "properties": {
    "gn:admin1_code":"3.0",
    "gn:asciiname":"Miaoqian Jiangjia",
    "gn:country_code":"CN",
    "gn:dem":63,
    "gn:feature_class":"P",
    "gn:feature_code":"PPL",
    "gn:name":"Miaoqian Jiangjia",
    "gn:population":0,
    "gn:timezone":"Asia/Shanghai",
    "iso:country":"CN",
    "name:zho_x_preferred":[
        "\u5e99\u524d\u6c5f\u5bb6"
    ],
    "wof:name":"Miaoqian Jiangjia",
    "wof:placetype":"locality"
},
  "geometry": {"coordinates":[117.20350999999999,28.44274],"type":"Point"}
}