{
  "type": "Feature",
  "properties": {
    "gn:admin1_code":"24.0",
    "gn:asciiname":"Nanzhida",
    "gn:country_code":"CN",
    "gn:dem":1889,
    "gn:feature_class":"P",
    "gn:feature_code":"PPL",
    "gn:name":"Nanzhida",
    "gn:population":0,
    "gn:timezone":"Asia/Shanghai",
    "iso:country":"CN",
    "name:zho_x_preferred":[
        "\u5357\u81f3\u8fbe"
    ],
    "wof:name":"Nanzhida",
    "wof:placetype":"locality"
},
  "geometry": {"coordinates":[111.79854,38.56685],"type":"Point"}
}