{
  "type": "Feature",
  "properties": {
    "gn:admin1_code":"1.0",
    "gn:asciiname":"Danqiaocun",
    "gn:country_code":"CN",
    "gn:dem":33,
    "gn:feature_class":"P",
    "gn:feature_code":"PPL",
    "gn:name":"Danqiaocun",
    "gn:population":0,
    "gn:timezone":"Asia/Shanghai",
    "iso:country":"CN",
    "name:zho_x_preferred":[
        "\u5355\u6865\u6751"
    ],
    "wof:name":"Danqiaocun",
    "wof:placetype":"locality"
},
  "geometry": {"coordinates":[115.75449,32.88558],"type":"Point"}
}