{
  "type": "Feature",
  "properties": {
    "gn:admin1_code":"26.0",
    "gn:asciiname":"Xizhuangzhen",
    "gn:cc2":"CN",
    "gn:country_code":"CN",
    "gn:dem":488,
    "gn:feature_class":"P",
    "gn:feature_code":"PPL",
    "gn:name":"Xizhuangzhen",
    "gn:population":0,
    "gn:timezone":"Asia/Shanghai",
    "iso:country":"CN",
    "name:und_x_variant":[
        "Hsi-chuang-chen",
        "Xizhuang",
        "Hsi-chia-chuang",
        "Hsi-chuang",
        "Xizhuangzhen"
    ],
    "wof:name":"Xizhuangzhen",
    "wof:placetype":"locality"
},
  "geometry": {"coordinates":[110.44611,35.53917],"type":"Point"}
}