{
  "type": "Feature",
  "properties": {
    "gn:admin1_code":"8.0",
    "gn:asciiname":"Nuanquan Yicun",
    "gn:country_code":"CN",
    "gn:dem":197,
    "gn:feature_class":"P",
    "gn:feature_code":"PPL",
    "gn:name":"Nuanquan Yicun",
    "gn:population":0,
    "gn:timezone":"Asia/Shanghai",
    "iso:country":"CN",
    "name:zho_x_preferred":[
        "\u6696\u6cc9\u4e00\u6751"
    ],
    "wof:name":"Nuanquan Yicun",
    "wof:placetype":"locality"
},
  "geometry": {"coordinates":[131.05816999999999,44.0977],"type":"Point"}
}