{
  "type": "Feature",
  "properties": {
    "gn:admin1_code":"12.0",
    "gn:asciiname":"Tayuanjie",
    "gn:country_code":"CN",
    "gn:dem":516,
    "gn:feature_class":"P",
    "gn:feature_code":"PPL",
    "gn:name":"Tayuanjie",
    "gn:population":0,
    "gn:timezone":"Asia/Shanghai",
    "iso:country":"CN",
    "name:zho_x_preferred":[
        "\u5854\u9662\u8857"
    ],
    "wof:name":"Tayuanjie",
    "wof:placetype":"locality"
},
  "geometry": {"coordinates":[110.26211000000001,32.36415],"type":"Point"}
}