{
  "type": "Feature",
  "properties": {
    "gn:admin1_code":"32.0",
    "gn:asciiname":"Yide",
    "gn:country_code":"CN",
    "gn:dem":3817,
    "gn:feature_class":"P",
    "gn:feature_code":"PPL",
    "gn:name":"Yide",
    "gn:population":0,
    "gn:timezone":"Asia/Shanghai",
    "iso:country":"CN",
    "name:zho_x_preferred":[
        "\u4ee5\u5fb7"
    ],
    "wof:name":"Yide",
    "wof:placetype":"locality"
},
  "geometry": {"coordinates":[99.32429999999999,29.588],"type":"Point"}
}