{
  "type": "Feature",
  "properties": {
    "gn:admin1_code":"15.0",
    "gn:asciiname":"Lijiazui",
    "gn:country_code":"CN",
    "gn:dem":1023,
    "gn:feature_class":"P",
    "gn:feature_code":"PPL",
    "gn:name":"Lijiazui",
    "gn:population":0,
    "gn:timezone":"Asia/Shanghai",
    "iso:country":"CN",
    "name:zho_x_preferred":[
        "\u674e\u5bb6\u5480"
    ],
    "wof:name":"Lijiazui",
    "wof:placetype":"locality"
},
  "geometry": {"coordinates":[107.893,35.5182],"type":"Point"}
}