{
  "type": "Feature",
  "properties": {
    "gn:admin1_code":"2.0",
    "gn:asciiname":"Shangnankeng",
    "gn:country_code":"CN",
    "gn:dem":980,
    "gn:feature_class":"P",
    "gn:feature_code":"PPL",
    "gn:name":"Shangnankeng",
    "gn:population":0,
    "gn:timezone":"Asia/Shanghai",
    "iso:country":"CN",
    "name:und_x_variant":[
        "\u4e0a\u5357\u5751",
        "Shangnankeng"
    ],
    "wof:name":"Shangnankeng",
    "wof:placetype":"locality"
},
  "geometry": {"coordinates":[119.32035,27.94627],"type":"Point"}
}