{
  "type": "Feature",
  "properties": {
    "gn:admin1_code":"9.0",
    "gn:asciiname":"Xingfuzhai",
    "gn:country_code":"CN",
    "gn:dem":319,
    "gn:feature_class":"P",
    "gn:feature_code":"PPL",
    "gn:name":"Xingfuzhai",
    "gn:population":0,
    "gn:timezone":"Asia/Shanghai",
    "iso:country":"CN",
    "name:zho_x_preferred":[
        "\u5e78\u798f\u5be8"
    ],
    "wof:name":"Xingfuzhai",
    "wof:placetype":"locality"
},
  "geometry": {"coordinates":[112.37262,34.28433],"type":"Point"}
}