{
  "type": "Feature",
  "properties": {
    "gn:admin1_code":"26",
    "gn:asciiname":"Fujiazhuang",
    "gn:country_code":"CN",
    "gn:dem":564,
    "gn:feature_class":"P",
    "gn:feature_code":"PPL",
    "gn:name":"Fujiazhuang",
    "gn:population":0,
    "gn:timezone":"Asia/Shanghai",
    "iso:country":"CN",
    "name:zho_x_preferred":[
        "\u4ed8\u5bb6\u5e84"
    ],
    "wof:name":"Fujiazhuang",
    "wof:placetype":"locality"
},
  "geometry": {"coordinates":[108.04731,34.36199000000001],"type":"Point"}
}