{
  "type": "Feature",
  "properties": {
    "gn:admin1_code":"19.0",
    "gn:asciiname":"Lujia Wopu",
    "gn:country_code":"CN",
    "gn:dem":317,
    "gn:feature_class":"P",
    "gn:feature_code":"PPL",
    "gn:name":"L\u00fcjia Wopu",
    "gn:population":0,
    "gn:timezone":"Asia/Shanghai",
    "iso:country":"CN",
    "name:und_x_variant":[
        "L\u00fcjia Wopu"
    ],
    "name:zho_x_preferred":[
        "\u5415\u5bb6\u7a9d\u94fa"
    ],
    "wof:name":"Lujia Wopu",
    "wof:placetype":"locality"
},
  "geometry": {"coordinates":[120.28247,41.68354],"type":"Point"}
}