{
  "type": "Feature",
  "properties": {
    "gn:admin1_code":"14.0",
    "gn:asciiname":"Rongba",
    "gn:country_code":"CN",
    "gn:dem":4116,
    "gn:feature_class":"P",
    "gn:feature_code":"PPL",
    "gn:name":"Rongba",
    "gn:population":0,
    "gn:timezone":"Asia/Urumqi",
    "iso:country":"CN",
    "name:zho_x_preferred":[
        "\u8363\u5df4"
    ],
    "wof:name":"Rongba",
    "wof:placetype":"locality"
},
  "geometry": {"coordinates":[97.96029,29.50641],"type":"Point"}
}