{
  "type": "Feature",
  "properties": {
    "gn:admin1_code":"2.0",
    "gn:asciiname":"Du'ao",
    "gn:country_code":"CN",
    "gn:dem":1007,
    "gn:feature_class":"P",
    "gn:feature_code":"PPL",
    "gn:name":"Du\u2019ao",
    "gn:population":0,
    "gn:timezone":"Asia/Shanghai",
    "iso:country":"CN",
    "name:hrv_x_preferred":[
        "Du'ao"
    ],
    "name:ind_x_preferred":[
        "Du'ao"
    ],
    "name:kor_x_preferred":[
        "\ucd08 \ub3c4\uc624"
    ],
    "name:und_x_variant":[
        "Du\u2019ao"
    ],
    "name:zho_x_preferred":[
        "\u675c\u5c99"
    ],
    "wof:name":"Du'ao",
    "wof:placetype":"locality"
},
  "geometry": {"coordinates":[119.19328,27.43998],"type":"Point"}
}