{
  "type": "Feature",
  "properties": {
    "gn:admin1_code":"14",
    "gn:asciiname":"Qiangzhadong",
    "gn:country_code":"CN",
    "gn:dem":4017,
    "gn:feature_class":"P",
    "gn:feature_code":"PPL",
    "gn:name":"Qiangzhadong",
    "gn:population":0,
    "gn:timezone":"Asia/Urumqi",
    "iso:country":"CN",
    "name:zho_x_preferred":[
        "\u5f3a\u624e\u4e1c"
    ],
    "wof:name":"Qiangzhadong",
    "wof:placetype":"locality"
},
  "geometry": {"coordinates":[89.5889,28.9259],"type":"Point"}
}