{
  "type": "Feature",
  "properties": {
    "gn:admin1_code":"26.0",
    "gn:asciiname":"Liangjia Maocun",
    "gn:country_code":"CN",
    "gn:dem":974,
    "gn:feature_class":"P",
    "gn:feature_code":"PPL",
    "gn:name":"Liangjia Maocun",
    "gn:population":0,
    "gn:timezone":"Asia/Shanghai",
    "iso:country":"CN",
    "name:zho_x_preferred":[
        "\u6881\u5bb6\u5cc1\u6751"
    ],
    "wof:name":"Liangjia Maocun",
    "wof:placetype":"locality"
},
  "geometry": {"coordinates":[110.52,38.3192],"type":"Point"}
}