{
  "type": "Feature",
  "properties": {
    "gn:admin1_code":"25",
    "gn:asciiname":"Dongluogezhuang",
    "gn:country_code":"CN",
    "gn:dem":54,
    "gn:feature_class":"P",
    "gn:feature_code":"PPL",
    "gn:name":"Dongluogezhuang",
    "gn:population":0,
    "gn:timezone":"Asia/Shanghai",
    "iso:country":"CN",
    "name:zho_x_preferred":[
        "\u4e1c\u7f57\u683c\u5e84"
    ],
    "wof:name":"Dongluogezhuang",
    "wof:placetype":"locality"
},
  "geometry": {"coordinates":[121.093,37.4978],"type":"Point"}
}