{
  "type": "Feature",
  "properties": {
    "gn:admin1_code":"26.0",
    "gn:asciiname":"Tanbei",
    "gn:country_code":"CN",
    "gn:dem":613,
    "gn:feature_class":"P",
    "gn:feature_code":"PPL",
    "gn:name":"Tanbei",
    "gn:population":0,
    "gn:timezone":"Asia/Shanghai",
    "iso:country":"CN",
    "name:und_x_variant":[
        "\u6ee9\u80cc"
    ],
    "wof:name":"Tanbei",
    "wof:placetype":"locality"
},
  "geometry": {"coordinates":[107.8437,33.30915],"type":"Point"}
}