{
  "type": "Feature",
  "properties": {
    "gn:admin1_code":"15",
    "gn:asciiname":"Aihaodian",
    "gn:country_code":"CN",
    "gn:dem":1675,
    "gn:feature_class":"P",
    "gn:feature_code":"PPL",
    "gn:name":"Aihaodian",
    "gn:population":0,
    "gn:timezone":"Asia/Shanghai",
    "iso:country":"CN",
    "name:zho_x_preferred":[
        "\u827e\u84bf\u5e97"
    ],
    "wof:name":"Aihaodian",
    "wof:placetype":"locality"
},
  "geometry": {"coordinates":[108.574,35.5817],"type":"Point"}
}