{
  "type": "Feature",
  "properties": {
    "gn:admin1_code":"26.0",
    "gn:asciiname":"Jiacuncun",
    "gn:country_code":"CN",
    "gn:dem":1206,
    "gn:feature_class":"P",
    "gn:feature_code":"PPL",
    "gn:name":"Jiacuncun",
    "gn:population":0,
    "gn:timezone":"Asia/Shanghai",
    "iso:country":"CN",
    "name:zho_x_preferred":[
        "\u8d3e\u6751\u6751"
    ],
    "wof:name":"Jiacuncun",
    "wof:placetype":"locality"
},
  "geometry": {"coordinates":[108.25185,35.11152],"type":"Point"}
}