{
  "type": "Feature",
  "properties": {
    "gn:admin1_code":"3.0",
    "gn:asciiname":"Hongjiayuan",
    "gn:country_code":"CN",
    "gn:dem":21,
    "gn:feature_class":"P",
    "gn:feature_code":"PPL",
    "gn:name":"Hongjiayuan",
    "gn:population":0,
    "gn:timezone":"Asia/Shanghai",
    "iso:country":"CN",
    "name:und_x_variant":[
        "\u6d2a\u5bb6\u6e90"
    ],
    "wof:name":"Hongjiayuan",
    "wof:placetype":"locality"
},
  "geometry": {"coordinates":[116.08025000000001,28.74298],"type":"Point"}
}