{
  "type": "Feature",
  "properties": {
    "gn:admin1_code":"26.0",
    "gn:asciiname":"Wutai Linchang",
    "gn:country_code":"CN",
    "gn:dem":649,
    "gn:feature_class":"P",
    "gn:feature_code":"PPLF",
    "gn:name":"Wutai Linchang",
    "gn:population":0,
    "gn:timezone":"Asia/Shanghai",
    "iso:country":"CN",
    "name:zho_x_preferred":[
        "\u4e94\u53f0\u6797\u573a"
    ],
    "wof:name":"Wutai Linchang",
    "wof:placetype":"locality"
},
  "geometry": {"coordinates":[108.93595999999999,34.02267],"type":"Point"}
}