{
  "type": "Feature",
  "properties": {
    "gn:admin1_code":"29.0",
    "gn:asciiname":"Datun",
    "gn:country_code":"CN",
    "gn:dem":2064,
    "gn:feature_class":"P",
    "gn:feature_code":"PPL",
    "gn:name":"Datun",
    "gn:population":0,
    "gn:timezone":"Asia/Shanghai",
    "iso:country":"CN",
    "name:und_x_variant":[
        "\u5927\u5c6f"
    ],
    "wof:name":"Datun",
    "wof:placetype":"locality"
},
  "geometry": {"coordinates":[103.63548,25.6522],"type":"Point"}
}