{
  "type": "Feature",
  "properties": {
    "gn:admin1_code":"16.0",
    "gn:asciiname":"Naxiong",
    "gn:country_code":"CN",
    "gn:dem":314,
    "gn:feature_class":"P",
    "gn:feature_code":"PPL",
    "gn:name":"Naxiong",
    "gn:population":0,
    "gn:timezone":"Asia/Shanghai",
    "iso:country":"CN",
    "name:zho_x_preferred":[
        "\u7eb3\u96c4"
    ],
    "wof:name":"Naxiong",
    "wof:placetype":"locality"
},
  "geometry": {"coordinates":[107.55200000000001,24.4525],"type":"Point"}
}