{
  "type": "Feature",
  "properties": {
    "gn:admin1_code":"29",
    "gn:asciiname":"Dashanbao",
    "gn:country_code":"CN",
    "gn:dem":2892,
    "gn:feature_class":"P",
    "gn:feature_code":"PPL",
    "gn:name":"Dashanbao",
    "gn:population":0,
    "gn:timezone":"Asia/Shanghai",
    "iso:country":"CN",
    "wof:name":"Dashanbao",
    "wof:placetype":"locality"
},
  "geometry": {"coordinates":[103.26667,27.46667],"type":"Point"}
}