{
  "type": "Feature",
  "properties": {
    "gn:admin1_code":"1.0",
    "gn:asciiname":"Fumashan",
    "gn:country_code":"CN",
    "gn:dem":16,
    "gn:feature_class":"P",
    "gn:feature_code":"PPL",
    "gn:name":"Fumashan",
    "gn:population":0,
    "gn:timezone":"Asia/Shanghai",
    "iso:country":"CN",
    "name:zho_x_preferred":[
        "Fumashan"
    ],
    "name:zho_x_variant":[
        "\u9a78\u9a6c\u5c71"
    ],
    "wof:name":"Fumashan",
    "wof:placetype":"locality"
},
  "geometry": {"coordinates":[119.01035,31.00773],"type":"Point"}
}