{
  "type": "Feature",
  "properties": {
    "gn:admin1_code":"02",
    "gn:asciiname":"Lihai",
    "gn:country_code":"CN",
    "gn:dem":12,
    "gn:feature_class":"P",
    "gn:feature_code":"PPLA4",
    "gn:name":"Lihai",
    "gn:population":0,
    "gn:timezone":"Asia/Shanghai",
    "iso:country":"CN",
    "name:und_x_variant":[
        "Li-hai-so",
        "Li-hai-so-ch\u2019eng",
        "Lihai",
        "\u6ca5\u6d77",
        "Lihai Zhen",
        "\u6ca5\u6d77\u9547"
    ],
    "wof:name":"Lihai",
    "wof:placetype":"locality"
},
  "geometry": {"coordinates":[120.75802,30.12006],"type":"Point"}
}