{
  "type": "Feature",
  "properties": {
    "gn:admin1_code":"1.0",
    "gn:asciiname":"Baliduncun",
    "gn:country_code":"CN",
    "gn:dem":24,
    "gn:feature_class":"P",
    "gn:feature_code":"PPL",
    "gn:name":"Baliduncun",
    "gn:population":0,
    "gn:timezone":"Asia/Shanghai",
    "iso:country":"CN",
    "name:zho_x_preferred":[
        "\u516b\u91cc\u987f\u6751"
    ],
    "wof:name":"Baliduncun",
    "wof:placetype":"locality"
},
  "geometry": {"coordinates":[117.00113,33.40591],"type":"Point"}
}