{
  "type": "Feature",
  "properties": {
    "gn:admin1_code":"1.0",
    "gn:asciiname":"Zhaishancun",
    "gn:country_code":"CN",
    "gn:dem":45,
    "gn:feature_class":"P",
    "gn:feature_code":"PPL",
    "gn:name":"Zhaishancun",
    "gn:population":0,
    "gn:timezone":"Asia/Shanghai",
    "iso:country":"CN",
    "name:zho_x_preferred":[
        "\u5be8\u5c71\u6751"
    ],
    "wof:name":"Zhaishancun",
    "wof:placetype":"locality"
},
  "geometry": {"coordinates":[117.82914,31.88796],"type":"Point"}
}