{
  "type": "Feature",
  "properties": {
    "gn:admin1_code":"30.0",
    "gn:asciiname":"Lushidong",
    "gn:country_code":"CN",
    "gn:dem":302,
    "gn:feature_class":"P",
    "gn:feature_code":"PPL",
    "gn:name":"Lushidong",
    "gn:population":0,
    "gn:timezone":"Asia/Shanghai",
    "iso:country":"CN",
    "name:zho_x_preferred":[
        "\u9e7f\u72ee\u6d1e"
    ],
    "wof:name":"Lushidong",
    "wof:placetype":"locality"
},
  "geometry": {"coordinates":[112.87611,24.40111],"type":"Point"}
}