{
  "type": "Feature",
  "properties": {
    "gn:admin1_code":"24.0",
    "gn:asciiname":"Changshengshancun",
    "gn:country_code":"CN",
    "gn:dem":1079,
    "gn:feature_class":"P",
    "gn:feature_code":"PPL",
    "gn:name":"Changshengshancun",
    "gn:population":0,
    "gn:timezone":"Asia/Shanghai",
    "iso:country":"CN",
    "name:zho_x_preferred":[
        "\u5e38\u80dc\u5c71\u6751"
    ],
    "wof:name":"Changshengshancun",
    "wof:placetype":"locality"
},
  "geometry": {"coordinates":[114.16414,40.65269],"type":"Point"}
}