{
  "type": "Feature",
  "properties": {
    "gn:admin1_code":"26.0",
    "gn:asciiname":"Cuijiagou",
    "gn:country_code":"CN",
    "gn:dem":993,
    "gn:feature_class":"P",
    "gn:feature_code":"PPL",
    "gn:name":"Cuijiagou",
    "gn:population":0,
    "gn:timezone":"Asia/Shanghai",
    "iso:country":"CN",
    "name:und_x_variant":[
        "\u5d14\u5bb6\u6c9f"
    ],
    "wof:name":"Cuijiagou",
    "wof:placetype":"locality"
},
  "geometry": {"coordinates":[106.35738000000001,32.76571],"type":"Point"}
}