{
  "type": "Feature",
  "properties": {
    "gn:admin1_code":"1.0",
    "gn:asciiname":"Chenshiyuancun",
    "gn:country_code":"CN",
    "gn:dem":40,
    "gn:feature_class":"P",
    "gn:feature_code":"PPL",
    "gn:name":"Chenshiyuancun",
    "gn:population":0,
    "gn:timezone":"Asia/Shanghai",
    "iso:country":"CN",
    "name:zho_x_preferred":[
        "\u9648\u67ff\u56ed\u6751"
    ],
    "wof:name":"Chenshiyuancun",
    "wof:placetype":"locality"
},
  "geometry": {"coordinates":[116.77987,34.23398],"type":"Point"}
}