{
  "type": "Feature",
  "properties": {
    "gn:admin1_code":"3",
    "gn:asciiname":"Fangcun",
    "gn:country_code":"CN",
    "gn:dem":97,
    "gn:feature_class":"P",
    "gn:feature_code":"PPL",
    "gn:name":"Fangcun",
    "gn:population":0,
    "gn:timezone":"Asia/Shanghai",
    "iso:country":"CN",
    "name:ceb_x_preferred":[
        "Fangcun"
    ],
    "name:swe_x_preferred":[
        "Fangcun"
    ],
    "name:und_x_variant":[
        "\u65b9\u6751"
    ],
    "wof:name":"Fangcun",
    "wof:placetype":"locality"
},
  "geometry": {"coordinates":[117.66453,29.16575],"type":"Point"}
}