{
  "type": "Feature",
  "properties": {
    "gn:admin1_code":"12.0",
    "gn:asciiname":"Senpu",
    "gn:country_code":"CN",
    "gn:dem":45,
    "gn:feature_class":"P",
    "gn:feature_code":"PPL",
    "gn:name":"Senpu",
    "gn:population":0,
    "gn:timezone":"Asia/Shanghai",
    "iso:country":"CN",
    "name:zho_x_preferred":[
        "Senpu"
    ],
    "name:zho_x_variant":[
        "\u68ee\u94fa"
    ],
    "wof:name":"Senpu",
    "wof:placetype":"locality"
},
  "geometry": {"coordinates":[115.01788999999999,29.84971],"type":"Point"}
}