{
  "type": "Feature",
  "properties": {
    "gn:admin1_code":"26.0",
    "gn:asciiname":"Baijiajiaocun",
    "gn:country_code":"CN",
    "gn:dem":926,
    "gn:feature_class":"P",
    "gn:feature_code":"PPL",
    "gn:name":"Baijiajiaocun",
    "gn:population":0,
    "gn:timezone":"Asia/Shanghai",
    "iso:country":"CN",
    "name:zho_x_preferred":[
        "\u767d\u5bb6\u89d2\u6751"
    ],
    "wof:name":"Baijiajiaocun",
    "wof:placetype":"locality"
},
  "geometry": {"coordinates":[109.89191,36.60671],"type":"Point"}
}