{
  "type": "Feature",
  "properties": {
    "gn:admin1_code":"1.0",
    "gn:asciiname":"Baishuiqiao",
    "gn:country_code":"CN",
    "gn:dem":137,
    "gn:feature_class":"P",
    "gn:feature_code":"PPL",
    "gn:name":"Baishuiqiao",
    "gn:population":0,
    "gn:timezone":"Asia/Shanghai",
    "iso:country":"CN",
    "name:und_x_variant":[
        "\u767d\u6c34\u6865"
    ],
    "name:zho_x_preferred":[
        "Baishuiqiao"
    ],
    "wof:name":"Baishuiqiao",
    "wof:placetype":"locality"
},
  "geometry": {"coordinates":[118.90476,30.63916],"type":"Point"}
}