{
  "type": "Feature",
  "properties": {
    "gn:admin1_code":"10.0",
    "gn:asciiname":"Dongsuchengzi",
    "gn:country_code":"CN",
    "gn:dem":2,
    "gn:feature_class":"P",
    "gn:feature_code":"PPL",
    "gn:name":"Dongsuchengzi",
    "gn:population":0,
    "gn:timezone":"Asia/Shanghai",
    "iso:country":"CN",
    "name:zho_x_preferred":[
        "\u4e1c\u82cf\u9423\u5b50"
    ],
    "wof:name":"Dongsuchengzi",
    "wof:placetype":"locality"
},
  "geometry": {"coordinates":[119.32205,39.73195],"type":"Point"}
}