{
  "type": "Feature",
  "properties": {
    "gn:admin1_code":"15.0",
    "gn:asciiname":"Yufu",
    "gn:country_code":"CN",
    "gn:dem":1323,
    "gn:feature_class":"P",
    "gn:feature_code":"PPL",
    "gn:name":"Yufu",
    "gn:population":0,
    "gn:timezone":"Asia/Shanghai",
    "iso:country":"CN",
    "name:ara_x_preferred":[
        "\u064a\u0648\u0641\u0648"
    ],
    "name:bul_x_preferred":[
        "\u042e\u0444\u0443"
    ],
    "name:ceb_x_preferred":[
        "Yufu-shi"
    ],
    "name:deu_x_preferred":[
        "Yufu"
    ],
    "name:fas_x_preferred":[
        "\u06cc\u0648\u0641\u0648"
    ],
    "name:fin_x_preferred":[
        "Yufu"
    ],
    "name:fra_x_preferred":[
        "Yufu"
    ],
    "name:glg_x_preferred":[
        "Yufu"
    ],
    "name:ita_x_preferred":[
        "Yufu"
    ],
    "name:jpn_x_preferred":[
        "\u7531\u5e03\u5e02"
    ],
    "name:kor_x_preferred":[
        "\uc720\ud6c4\uc2dc"
    ],
    "name:mzn_x_preferred":[
        "\u06cc\u0648\u0641\u0648"
    ],
    "name:nld_x_preferred":[
        "Yufu"
    ],
    "name:pol_x_preferred":[
        "Yufu"
    ],
    "name:ron_x_preferred":[
        "Yufu"
    ],
    "name:rus_x_preferred":[
        "\u042e\u0444\u0443"
    ],
    "name:swe_x_preferred":[
        "Yufu"
    ],
    "name:tgl_x_preferred":[
        "Yufu"
    ],
    "name:tum_x_preferred":[
        "Yufu"
    ],
    "name:tur_x_preferred":[
        "Yufu"
    ],
    "name:ukr_x_preferred":[
        "\u042e\u0444\u0443"
    ],
    "name:urd_x_preferred":[
        "\u06cc\u0648\u0641\u0648"
    ],
    "name:vie_x_preferred":[
        "Yufu"
    ],
    "name:war_x_preferred":[
        "Yufu"
    ],
    "name:zho_x_preferred":[
        "\u80b2\u5bcc"
    ],
    "name:zho_x_variant":[
        "\u7531\u5e03\u5e02"
    ],
    "wof:name":"Yufu",
    "wof:placetype":"locality"
},
  "geometry": {"coordinates":[103.551,38.9476],"type":"Point"}
}