{
  "type": "Feature",
  "properties": {
    "gn:admin1_code":"9.0",
    "gn:asciiname":"Damengcun",
    "gn:country_code":"CN",
    "gn:dem":74,
    "gn:feature_class":"P",
    "gn:feature_code":"PPL",
    "gn:name":"Damengcun",
    "gn:population":0,
    "gn:timezone":"Asia/Shanghai",
    "iso:country":"CN",
    "name:zho_x_preferred":[
        "\u5927\u5b5f\u6751"
    ],
    "wof:name":"Damengcun",
    "wof:placetype":"locality"
},
  "geometry": {"coordinates":[113.83456,33.85117],"type":"Point"}
}