{
  "type": "Feature",
  "properties": {
    "gn:admin1_code":"12.0",
    "gn:asciiname":"Shangtiankeng",
    "gn:country_code":"CN",
    "gn:dem":1606,
    "gn:feature_class":"P",
    "gn:feature_code":"PPL",
    "gn:name":"Shangtiankeng",
    "gn:population":0,
    "gn:timezone":"Asia/Shanghai",
    "iso:country":"CN",
    "name:zho_x_preferred":[
        "\u4e0a\u5929\u5751"
    ],
    "wof:name":"Shangtiankeng",
    "wof:placetype":"locality"
},
  "geometry": {"coordinates":[109.63897,33.23261],"type":"Point"}
}