{
  "type": "Feature",
  "properties": {
    "gn:admin1_code":"5.0",
    "gn:asciiname":"Huaijiadian",
    "gn:country_code":"CN",
    "gn:dem":219,
    "gn:feature_class":"P",
    "gn:feature_code":"PPL",
    "gn:name":"Huaijiadian",
    "gn:population":0,
    "gn:timezone":"Asia/Shanghai",
    "iso:country":"CN",
    "name:zho_x_preferred":[
        "\u6000\u5bb6\u5e97"
    ],
    "wof:name":"Huaijiadian",
    "wof:placetype":"locality"
},
  "geometry": {"coordinates":[126.61771,44.09366],"type":"Point"}
}