{
  "type": "Feature",
  "properties": {
    "gn:admin1_code":"11.0",
    "gn:asciiname":"Lashu'ao",
    "gn:country_code":"CN",
    "gn:dem":266,
    "gn:feature_class":"P",
    "gn:feature_code":"PPL",
    "gn:name":"Lashu\u2019ao",
    "gn:population":0,
    "gn:timezone":"Asia/Shanghai",
    "iso:country":"CN",
    "name:und_x_variant":[
        "Lashu\u2019ao"
    ],
    "name:zho_x_preferred":[
        "\u814a\u6811\u5773"
    ],
    "wof:name":"Lashu'ao",
    "wof:placetype":"locality"
},
  "geometry": {"coordinates":[111.18904999999999,26.96427000000001],"type":"Point"}
}