{
  "type": "Feature",
  "properties": {
    "gn:admin1_code":"24.0",
    "gn:asciiname":"Yangjiagetai",
    "gn:country_code":"CN",
    "gn:dem":1313,
    "gn:feature_class":"P",
    "gn:feature_code":"PPL",
    "gn:name":"Yangjiagetai",
    "gn:population":0,
    "gn:timezone":"Asia/Shanghai",
    "iso:country":"CN",
    "name:zho_x_preferred":[
        "\u6768\u5bb6\u572a\u53f0"
    ],
    "wof:name":"Yangjiagetai",
    "wof:placetype":"locality"
},
  "geometry": {"coordinates":[111.20255,38.26124],"type":"Point"}
}