{
  "type": "Feature",
  "properties": {
    "gn:admin1_code":"2.0",
    "gn:asciiname":"Longjing",
    "gn:country_code":"CN",
    "gn:dem":1143,
    "gn:feature_class":"P",
    "gn:feature_code":"PPL",
    "gn:name":"Longjing",
    "gn:population":0,
    "gn:timezone":"Asia/Shanghai",
    "iso:country":"CN",
    "name:und_x_variant":[
        "\u9f99\u4e95",
        "Longjing"
    ],
    "wof:name":"Longjing",
    "wof:placetype":"locality"
},
  "geometry": {"coordinates":[119.33319,27.91096],"type":"Point"}
}