{
  "type": "Feature",
  "properties": {
    "gn:admin1_code":"29.0",
    "gn:asciiname":"Sangushui",
    "gn:country_code":"CN",
    "gn:dem":2703,
    "gn:feature_class":"P",
    "gn:feature_code":"PPL",
    "gn:name":"Sangushui",
    "gn:population":0,
    "gn:timezone":"Asia/Shanghai",
    "iso:country":"CN",
    "name:zho_x_preferred":[
        "\u4e09\u80a1\u6c34"
    ],
    "wof:name":"Sangushui",
    "wof:placetype":"locality"
},
  "geometry": {"coordinates":[103.22199999999999,26.9219],"type":"Point"}
}