{
  "type": "Feature",
  "properties": {
    "gn:admin1_code":"18",
    "gn:asciiname":"Yusa",
    "gn:country_code":"CN",
    "gn:dem":1222,
    "gn:feature_class":"P",
    "gn:feature_code":"PPL",
    "gn:name":"Yusa",
    "gn:population":0,
    "gn:timezone":"Asia/Shanghai",
    "iso:country":"CN",
    "name:fra_x_preferred":[
        "Yusa"
    ],
    "name:spa_x_preferred":[
        "Yusa"
    ],
    "name:zho_x_preferred":[
        "\u96e8\u6d12"
    ],
    "wof:name":"Yusa",
    "wof:placetype":"locality"
},
  "geometry": {"coordinates":[106.75,27.1086],"type":"Point"}
}