{
  "type": "Feature",
  "properties": {
    "gn:admin1_code":"1.0",
    "gn:asciiname":"Zhangjiaqiao",
    "gn:country_code":"CN",
    "gn:dem":23,
    "gn:feature_class":"P",
    "gn:feature_code":"PPL",
    "gn:name":"Zhangjiaqiao",
    "gn:population":0,
    "gn:timezone":"Asia/Shanghai",
    "iso:country":"CN",
    "name:zho_x_preferred":[
        "Zhangjiaqiao"
    ],
    "name:zho_x_variant":[
        "\u5f20\u5bb6\u6865"
    ],
    "wof:name":"Zhangjiaqiao",
    "wof:placetype":"locality"
},
  "geometry": {"coordinates":[118.92519,30.84755],"type":"Point"}
}