{
  "type": "Feature",
  "properties": {
    "gn:admin1_code":"32.0",
    "gn:asciiname":"Niubazi",
    "gn:country_code":"CN",
    "gn:dem":267,
    "gn:feature_class":"P",
    "gn:feature_code":"PPL",
    "gn:name":"Niubazi",
    "gn:population":0,
    "gn:timezone":"Asia/Shanghai",
    "iso:country":"CN",
    "name:zho_x_preferred":[
        "\u725b\u575d\u5b50"
    ],
    "wof:name":"Niubazi",
    "wof:placetype":"locality"
},
  "geometry": {"coordinates":[105.17704999999999,29.03955],"type":"Point"}
}