{
  "type": "Feature",
  "properties": {
    "gn:admin1_code":"18.0",
    "gn:asciiname":"Daxigou",
    "gn:country_code":"CN",
    "gn:dem":830,
    "gn:feature_class":"P",
    "gn:feature_code":"PPL",
    "gn:name":"Daxigou",
    "gn:population":0,
    "gn:timezone":"Asia/Shanghai",
    "iso:country":"CN",
    "name:zho_x_preferred":[
        "\u5927\u6eaa\u6c9f"
    ],
    "wof:name":"Daxigou",
    "wof:placetype":"locality"
},
  "geometry": {"coordinates":[108.636,27.7239],"type":"Point"}
}