{
  "type": "Feature",
  "properties": {
    "gn:admin1_code":"10",
    "gn:asciiname":"Xingjia",
    "gn:country_code":"CN",
    "gn:dem":1464,
    "gn:feature_class":"P",
    "gn:feature_code":"PPL",
    "gn:name":"Xingjia",
    "gn:population":0,
    "gn:timezone":"Asia/Shanghai",
    "iso:country":"CN",
    "name:zho_x_preferred":[
        "\u90a2\u5bb6"
    ],
    "wof:name":"Xingjia",
    "wof:placetype":"locality"
},
  "geometry": {"coordinates":[114.06234000000001,41.26718],"type":"Point"}
}