{
  "type": "Feature",
  "properties": {
    "gn:admin1_code":"19.0",
    "gn:asciiname":"Xiaoliujia Buzi",
    "gn:country_code":"CN",
    "gn:dem":441,
    "gn:feature_class":"P",
    "gn:feature_code":"PPL",
    "gn:name":"Xiaoliujia Buzi",
    "gn:population":0,
    "gn:timezone":"Asia/Shanghai",
    "iso:country":"CN",
    "name:und_x_variant":[
        "Xiaoliujiabaozi",
        "Xiaoliujia Buzi"
    ],
    "name:zho_x_preferred":[
        "\u5c0f\u5218\u5bb6\u5821\u5b50"
    ],
    "wof:name":"Xiaoliujia Buzi",
    "wof:placetype":"locality"
},
  "geometry": {"coordinates":[123.63409,40.74554000000001],"type":"Point"}
}