{
  "type": "Feature",
  "properties": {
    "gn:admin1_code":"4.0",
    "gn:asciiname":"Nalou",
    "gn:country_code":"CN",
    "gn:dem":5,
    "gn:feature_class":"P",
    "gn:feature_code":"PPL",
    "gn:name":"Nalou",
    "gn:population":0,
    "gn:timezone":"Asia/Shanghai",
    "iso:country":"CN",
    "name:zho_x_preferred":[
        "Nalou"
    ],
    "name:zho_x_variant":[
        "\u90a3\u697c"
    ],
    "wof:name":"Nalou",
    "wof:placetype":"locality"
},
  "geometry": {"coordinates":[119.18044,34.32168],"type":"Point"}
}