{
  "type": "Feature",
  "properties": {
    "gn:admin1_code":"29.0",
    "gn:asciiname":"Huitupo",
    "gn:country_code":"CN",
    "gn:dem":1544,
    "gn:feature_class":"P",
    "gn:feature_code":"PPL",
    "gn:name":"Huitupo",
    "gn:population":0,
    "gn:timezone":"Asia/Shanghai",
    "iso:country":"CN",
    "name:zho_x_preferred":[
        "\u7070\u571f\u5761"
    ],
    "wof:name":"Huitupo",
    "wof:placetype":"locality"
},
  "geometry": {"coordinates":[103.687,23.8775],"type":"Point"}
}