{
  "type": "Feature",
  "properties": {
    "gn:admin1_code":"32.0",
    "gn:asciiname":"Rongzhongcun",
    "gn:country_code":"CN",
    "gn:dem":3360,
    "gn:feature_class":"P",
    "gn:feature_code":"PPL",
    "gn:name":"Rongzhongcun",
    "gn:population":0,
    "gn:timezone":"Asia/Shanghai",
    "iso:country":"CN",
    "name:zho_x_preferred":[
        "\u8363\u4e2d\u6751"
    ],
    "wof:name":"Rongzhongcun",
    "wof:placetype":"locality"
},
  "geometry": {"coordinates":[100.295,30.4033],"type":"Point"}
}