{
  "type": "Feature",
  "properties": {
    "gn:admin1_code":"5.0",
    "gn:asciiname":"Qianyao",
    "gn:country_code":"CN",
    "gn:dem":156,
    "gn:feature_class":"P",
    "gn:feature_code":"PPL",
    "gn:name":"Qianyao",
    "gn:population":0,
    "gn:timezone":"Asia/Shanghai",
    "iso:country":"CN",
    "name:zho_x_preferred":[
        "\u524d\u7a91"
    ],
    "wof:name":"Qianyao",
    "wof:placetype":"locality"
},
  "geometry": {"coordinates":[125.99666000000001,44.69232],"type":"Point"}
}