{
  "type": "Feature",
  "properties": {
    "gn:admin1_code":"32.0",
    "gn:asciiname":"Eman",
    "gn:country_code":"CN",
    "gn:dem":2102,
    "gn:feature_class":"P",
    "gn:feature_code":"PPL",
    "gn:name":"Eman",
    "gn:population":0,
    "gn:timezone":"Asia/Shanghai",
    "iso:country":"CN",
    "name:zho_x_preferred":[
        "\u4fc4\u6ee1"
    ],
    "wof:name":"Eman",
    "wof:placetype":"locality"
},
  "geometry": {"coordinates":[101.92400000000001,30.9057],"type":"Point"}
}