{
  "type": "Feature",
  "properties": {
    "gn:admin1_code":"26.0",
    "gn:asciiname":"Xiying",
    "gn:cc2":"CN",
    "gn:country_code":"CN",
    "gn:dem":502,
    "gn:feature_class":"P",
    "gn:feature_code":"PPL",
    "gn:name":"Xiying",
    "gn:population":0,
    "gn:timezone":"Asia/Shanghai",
    "iso:country":"CN",
    "name:und_x_variant":[
        "Hsi-man-ying",
        "Hsi-ying",
        "Xiying"
    ],
    "wof:name":"Xiying",
    "wof:placetype":"locality"
},
  "geometry": {"coordinates":[109.75611000000001,32.74111],"type":"Point"}
}