{
  "type": "Feature",
  "properties": {
    "gn:admin1_code":"29.0",
    "gn:asciiname":"Wuyuemiao",
    "gn:country_code":"CN",
    "gn:dem":1991,
    "gn:feature_class":"P",
    "gn:feature_code":"PPL",
    "gn:name":"Wuyuemiao",
    "gn:population":0,
    "gn:timezone":"Asia/Shanghai",
    "iso:country":"CN",
    "name:zho_x_preferred":[
        "\u4e94\u6708\u5e99"
    ],
    "wof:name":"Wuyuemiao",
    "wof:placetype":"locality"
},
  "geometry": {"coordinates":[103.705,28.0685],"type":"Point"}
}