{
  "type": "Feature",
  "properties": {
    "gn:admin1_code":"19.0",
    "gn:asciiname":"Huanggoumen",
    "gn:country_code":"CN",
    "gn:dem":68,
    "gn:feature_class":"P",
    "gn:feature_code":"PPL",
    "gn:name":"Huanggoumen",
    "gn:population":0,
    "gn:timezone":"Asia/Shanghai",
    "iso:country":"CN",
    "name:zho_x_preferred":[
        "\u8352\u6c9f\u95e8"
    ],
    "wof:name":"Huanggoumen",
    "wof:placetype":"locality"
},
  "geometry": {"coordinates":[124.28189,40.21095],"type":"Point"}
}