{
  "type": "Feature",
  "properties": {
    "gn:admin1_code":"12.0",
    "gn:asciiname":"Gaojiadizhonghe",
    "gn:country_code":"CN",
    "gn:dem":29,
    "gn:feature_class":"P",
    "gn:feature_code":"PPL",
    "gn:name":"Gaojiadizhonghe",
    "gn:population":0,
    "gn:timezone":"Asia/Shanghai",
    "iso:country":"CN",
    "name:zho_x_preferred":[
        "\u9ad8\u5bb6\u5824\u4e2d\u6cb3"
    ],
    "wof:name":"Gaojiadizhonghe",
    "wof:placetype":"locality"
},
  "geometry": {"coordinates":[113.07809,29.69602],"type":"Point"}
}