{
  "type": "Feature",
  "properties": {
    "gn:admin1_code":"8.0",
    "gn:asciiname":"Longjiangcun",
    "gn:country_code":"CN",
    "gn:dem":177,
    "gn:feature_class":"P",
    "gn:feature_code":"PPL",
    "gn:name":"Longjiangcun",
    "gn:population":0,
    "gn:timezone":"Asia/Shanghai",
    "iso:country":"CN",
    "name:zho_x_preferred":[
        "\u9f99\u6c5f\u6751"
    ],
    "wof:name":"Longjiangcun",
    "wof:placetype":"locality"
},
  "geometry": {"coordinates":[124.55799,48.15004],"type":"Point"}
}