{
  "type": "Feature",
  "properties": {
    "gn:admin1_code":"19.0",
    "gn:asciiname":"Bangchuigou",
    "gn:country_code":"CN",
    "gn:dem":363,
    "gn:feature_class":"P",
    "gn:feature_code":"PPL",
    "gn:name":"Bangchuigou",
    "gn:population":0,
    "gn:timezone":"Asia/Shanghai",
    "iso:country":"CN",
    "name:zho_x_preferred":[
        "\u68d2\u68f0\u6c9f"
    ],
    "wof:name":"Bangchuigou",
    "wof:placetype":"locality"
},
  "geometry": {"coordinates":[125.33765,41.54034],"type":"Point"}
}