{
  "type": "Feature",
  "properties": {
    "gn:admin1_code":"20.0",
    "gn:asciiname":"Nantucheng",
    "gn:country_code":"CN",
    "gn:dem":1681,
    "gn:feature_class":"P",
    "gn:feature_code":"PPL",
    "gn:name":"Nantucheng",
    "gn:population":0,
    "gn:timezone":"Asia/Shanghai",
    "iso:country":"CN",
    "name:und_x_variant":[
        "\u5357\u571f\u57ce"
    ],
    "wof:name":"Nantucheng",
    "wof:placetype":"locality"
},
  "geometry": {"coordinates":[111.15112999999999,41.09954000000001],"type":"Point"}
}