{
  "type": "Feature",
  "properties": {
    "gn:admin1_code":"21.0",
    "gn:asciiname":"Hongzhuang",
    "gn:country_code":"CN",
    "gn:dem":1525,
    "gn:feature_class":"P",
    "gn:feature_code":"PPL",
    "gn:name":"Hongzhuang",
    "gn:population":0,
    "gn:timezone":"Asia/Shanghai",
    "iso:country":"CN",
    "name:und_x_variant":[
        "\u7ea2\u5e84"
    ],
    "name:zho_x_preferred":[
        "\u7ea2\u5e84"
    ],
    "wof:name":"Hongzhuang",
    "wof:placetype":"locality"
},
  "geometry": {"coordinates":[106.16714,36.32351],"type":"Point"}
}