{
  "type": "Feature",
  "properties": {
    "gn:admin1_code":"19.0",
    "gn:asciiname":"Shuiquangou",
    "gn:country_code":"CN",
    "gn:dem":159,
    "gn:feature_class":"P",
    "gn:feature_code":"PPL",
    "gn:name":"Shuiquangou",
    "gn:population":0,
    "gn:timezone":"Asia/Shanghai",
    "iso:country":"CN",
    "name:zho_x_preferred":[
        "\u6c34\u6cc9\u6c9f"
    ],
    "wof:name":"Shuiquangou",
    "wof:placetype":"locality"
},
  "geometry": {"coordinates":[121.32899999999999,41.7183],"type":"Point"}
}