{
  "type": "Feature",
  "properties": {
    "gn:admin1_code":"32.0",
    "gn:asciiname":"Shenggedong",
    "gn:country_code":"CN",
    "gn:dem":3884,
    "gn:feature_class":"P",
    "gn:feature_code":"PPL",
    "gn:name":"Shenggedong",
    "gn:population":0,
    "gn:timezone":"Asia/Shanghai",
    "iso:country":"CN",
    "name:zho_x_preferred":[
        "\u751f\u5404\u6d1e"
    ],
    "wof:name":"Shenggedong",
    "wof:placetype":"locality"
},
  "geometry": {"coordinates":[98.75991999999999,31.05467],"type":"Point"}
}