{
  "type": "Feature",
  "properties": {
    "gn:admin1_code":"21.0",
    "gn:asciiname":"Shangtaozi",
    "gn:country_code":"CN",
    "gn:dem":1715,
    "gn:feature_class":"P",
    "gn:feature_code":"PPL",
    "gn:name":"Shangtaozi",
    "gn:population":0,
    "gn:timezone":"Asia/Shanghai",
    "iso:country":"CN",
    "name:zho_x_preferred":[
        "\u4e0a\u5957\u5b50"
    ],
    "wof:name":"Shangtaozi",
    "wof:placetype":"locality"
},
  "geometry": {"coordinates":[105.98099999999999,36.6939],"type":"Point"}
}