{
  "type": "Feature",
  "properties": {
    "gn:admin1_code":"29.0",
    "gn:asciiname":"Bilang",
    "gn:country_code":"CN",
    "gn:dem":3323,
    "gn:feature_class":"P",
    "gn:feature_code":"PPL",
    "gn:name":"Bilang",
    "gn:population":0,
    "gn:timezone":"Asia/Shanghai",
    "iso:country":"CN",
    "name:zho_x_preferred":[
        "\u6bd4\u6d6a"
    ],
    "wof:name":"Bilang",
    "wof:placetype":"locality"
},
  "geometry": {"coordinates":[99.6572,27.8957],"type":"Point"}
}