{
  "type": "Feature",
  "properties": {
    "gn:admin1_code":"24",
    "gn:asciiname":"Qidaocun",
    "gn:country_code":"CN",
    "gn:dem":892,
    "gn:feature_class":"P",
    "gn:feature_code":"PPL",
    "gn:name":"Qidaocun",
    "gn:population":0,
    "gn:timezone":"Asia/Shanghai",
    "iso:country":"CN",
    "name:und_x_variant":[
        "Teng-t\u2019a",
        "Ch\u2019i-tao-ts\u2019un",
        "Dengta",
        "Ch\u2019i-tao",
        "Qidao",
        "Qidaocun"
    ],
    "name:zho_x_preferred":[
        "\u5c90\u9053\u6751"
    ],
    "wof:name":"Qidaocun",
    "wof:placetype":"locality"
},
  "geometry": {"coordinates":[110.98448,37.84768],"type":"Point"}
}