{
  "type": "Feature",
  "properties": {
    "gn:admin1_code":"2",
    "gn:asciiname":"Huimingsi",
    "gn:country_code":"CN",
    "gn:dem":700,
    "gn:feature_class":"P",
    "gn:feature_code":"PPL",
    "gn:name":"Huimingsi",
    "gn:population":0,
    "gn:timezone":"Asia/Shanghai",
    "iso:country":"CN",
    "name:zho_x_preferred":[
        "\u60e0\u660e\u5bfa"
    ],
    "wof:name":"Huimingsi",
    "wof:placetype":"locality"
},
  "geometry": {"coordinates":[119.64610999999999,27.9475],"type":"Point"}
}