{
  "type": "Feature",
  "properties": {
    "gn:admin1_code":"32.0",
    "gn:asciiname":"Shiyanzi",
    "gn:country_code":"CN",
    "gn:dem":1015,
    "gn:feature_class":"P",
    "gn:feature_code":"PPL",
    "gn:name":"Shiyanzi",
    "gn:population":0,
    "gn:timezone":"Asia/Shanghai",
    "iso:country":"CN",
    "name:zho_x_preferred":[
        "\u77f3\u5830\u5b50"
    ],
    "wof:name":"Shiyanzi",
    "wof:placetype":"locality"
},
  "geometry": {"coordinates":[104.61678999999999,28.21701],"type":"Point"}
}