{
  "type": "Feature",
  "properties": {
    "gn:admin1_code":"19.0",
    "gn:asciiname":"Erdabu",
    "gn:country_code":"CN",
    "gn:dem":15,
    "gn:feature_class":"P",
    "gn:feature_code":"PPL",
    "gn:name":"Erdabu",
    "gn:population":0,
    "gn:timezone":"Asia/Shanghai",
    "iso:country":"CN",
    "name:und_x_variant":[
        "Erdapu",
        "\u4e8c\u5927\u5821",
        "Erdabu"
    ],
    "wof:name":"Erdabu",
    "wof:placetype":"locality"
},
  "geometry": {"coordinates":[122.65478,40.90543],"type":"Point"}
}