{
  "type": "Feature",
  "properties": {
    "gn:admin1_code":"11.0",
    "gn:asciiname":"Bailizhuang",
    "gn:country_code":"CN",
    "gn:dem":912,
    "gn:feature_class":"P",
    "gn:feature_code":"PPL",
    "gn:name":"Bailizhuang",
    "gn:population":0,
    "gn:timezone":"Asia/Shanghai",
    "iso:country":"CN",
    "name:zho_x_preferred":[
        "\u767e\u91cc\u5e84"
    ],
    "wof:name":"Bailizhuang",
    "wof:placetype":"locality"
},
  "geometry": {"coordinates":[109.91013999999998,29.67015],"type":"Point"}
}