{
  "type": "Feature",
  "properties": {
    "gn:admin1_code":"07",
    "gn:asciiname":"Yingpan",
    "gn:country_code":"CN",
    "gn:dem":366,
    "gn:feature_class":"P",
    "gn:feature_code":"PPL",
    "gn:name":"Yingpan",
    "gn:population":0,
    "gn:timezone":"Asia/Shanghai",
    "iso:country":"CN",
    "name:zho_x_preferred":[
        "\u8425\u76d8"
    ],
    "wof:name":"Yingpan",
    "wof:placetype":"locality"
},
  "geometry": {"coordinates":[117.12021,25.20295],"type":"Point"}
}