{
  "type": "Feature",
  "properties": {
    "gn:admin1_code":"3.0",
    "gn:asciiname":"Pengxia",
    "gn:country_code":"CN",
    "gn:dem":50,
    "gn:feature_class":"P",
    "gn:feature_code":"PPL",
    "gn:name":"Pengxia",
    "gn:population":0,
    "gn:timezone":"Asia/Shanghai",
    "iso:country":"CN",
    "name:und_x_variant":[
        "\u68da\u4e0b"
    ],
    "wof:name":"Pengxia",
    "wof:placetype":"locality"
},
  "geometry": {"coordinates":[114.97067,28.24402000000001],"type":"Point"}
}