{
  "type": "Feature",
  "properties": {
    "gn:admin1_code":"18",
    "gn:asciiname":"Sanchagou",
    "gn:country_code":"CN",
    "gn:dem":888,
    "gn:feature_class":"P",
    "gn:feature_code":"PPL",
    "gn:name":"Sanchagou",
    "gn:population":0,
    "gn:timezone":"Asia/Shanghai",
    "iso:country":"CN",
    "name:zho_x_preferred":[
        "\u4e09\u5c94\u6c9f"
    ],
    "wof:name":"Sanchagou",
    "wof:placetype":"locality"
},
  "geometry": {"coordinates":[106.688,27.5137],"type":"Point"}
}