{
  "type": "Feature",
  "properties": {
    "gn:admin1_code":"12.0",
    "gn:asciiname":"Duidongping",
    "gn:country_code":"CN",
    "gn:dem":1553,
    "gn:feature_class":"P",
    "gn:feature_code":"PPL",
    "gn:name":"Duidongping",
    "gn:population":0,
    "gn:timezone":"Asia/Shanghai",
    "iso:country":"CN",
    "name:zho_x_preferred":[
        "\u5bf9\u4e1c\u576a"
    ],
    "wof:name":"Duidongping",
    "wof:placetype":"locality"
},
  "geometry": {"coordinates":[110.56416000000002,31.6143],"type":"Point"}
}