{
  "type": "Feature",
  "properties": {
    "gn:admin1_code":"18",
    "gn:asciiname":"Bushang",
    "gn:country_code":"CN",
    "gn:dem":1166,
    "gn:feature_class":"P",
    "gn:feature_code":"PPL",
    "gn:name":"Bushang",
    "gn:population":0,
    "gn:timezone":"Asia/Shanghai",
    "iso:country":"CN",
    "name:zho_x_preferred":[
        "\u5821\u4e0a"
    ],
    "wof:name":"Bushang",
    "wof:placetype":"locality"
},
  "geometry": {"coordinates":[108.054,28.5026],"type":"Point"}
}