{
  "type": "Feature",
  "properties": {
    "gn:admin1_code":"15.0",
    "gn:asciiname":"Qidaogou Nongchang Yidui",
    "gn:country_code":"CN",
    "gn:dem":1386,
    "gn:feature_class":"P",
    "gn:feature_code":"PPLF",
    "gn:name":"Qidaogou Nongchang Yidui",
    "gn:population":0,
    "gn:timezone":"Asia/Urumqi",
    "iso:country":"CN",
    "name:eng_x_preferred":[
        "Qidaogou Nongchang First Dui"
    ],
    "name:zho_x_preferred":[
        "\u4e03\u9053\u6c9f\u519c\u573a\u4e00\u961f"
    ],
    "wof:name":"Qidaogou Nongchang Yidui",
    "wof:placetype":"locality"
},
  "geometry": {"coordinates":[96.6639,40.49269],"type":"Point"}
}