{
  "type": "Feature",
  "properties": {
    "gn:admin1_code":"14.0",
    "gn:asciiname":"Niangmaicun",
    "gn:country_code":"CN",
    "gn:dem":3559,
    "gn:feature_class":"P",
    "gn:feature_code":"PPL",
    "gn:name":"Niangmaicun",
    "gn:population":0,
    "gn:timezone":"Asia/Urumqi",
    "iso:country":"CN",
    "name:zho_x_preferred":[
        "\u5a18\u9ea6\u6751"
    ],
    "wof:name":"Niangmaicun",
    "wof:placetype":"locality"
},
  "geometry": {"coordinates":[98.31014,31.69441],"type":"Point"}
}