{
  "type": "Feature",
  "properties": {
    "gn:admin1_code":"9.0",
    "gn:asciiname":"Qianzhangqiao",
    "gn:country_code":"CN",
    "gn:dem":42,
    "gn:feature_class":"P",
    "gn:feature_code":"PPL",
    "gn:name":"Qianzhangqiao",
    "gn:population":0,
    "gn:timezone":"Asia/Shanghai",
    "iso:country":"CN",
    "name:zho_x_preferred":[
        "\u524d\u5f20\u6865"
    ],
    "wof:name":"Qianzhangqiao",
    "wof:placetype":"locality"
},
  "geometry": {"coordinates":[115.17261999999999,32.76188],"type":"Point"}
}