{
  "type": "Feature",
  "properties": {
    "gn:admin1_code":"04",
    "gn:asciiname":"Shichengcun",
    "gn:country_code":"CN",
    "gn:dem":44,
    "gn:feature_class":"P",
    "gn:feature_code":"PPL",
    "gn:name":"Shichengcun",
    "gn:population":0,
    "gn:timezone":"Asia/Shanghai",
    "iso:country":"CN",
    "name:und_x_variant":[
        "Shih-ch\u2019eng",
        "Shicheng",
        "Shichengcun"
    ],
    "name:zho_x_preferred":[
        "\u98df\u57ce\u6751"
    ],
    "wof:name":"Shichengcun",
    "wof:placetype":"locality"
},
  "geometry": {"coordinates":[116.69513000000001,34.5545],"type":"Point"}
}