{
  "type": "Feature",
  "properties": {
    "gn:admin1_code":"3.0",
    "gn:asciiname":"Tanshanyuan",
    "gn:country_code":"CN",
    "gn:dem":70,
    "gn:feature_class":"P",
    "gn:feature_code":"PPL",
    "gn:name":"Tanshanyuan",
    "gn:population":0,
    "gn:timezone":"Asia/Shanghai",
    "iso:country":"CN",
    "name:und_x_variant":[
        "\u575b\u5c71\u56ed"
    ],
    "wof:name":"Tanshanyuan",
    "wof:placetype":"locality"
},
  "geometry": {"coordinates":[115.009,27.47598],"type":"Point"}
}