{
  "type": "Feature",
  "properties": {
    "gn:admin1_code":"25.0",
    "gn:asciiname":"Jiaocunmiaocun",
    "gn:country_code":"CN",
    "gn:dem":57,
    "gn:feature_class":"P",
    "gn:feature_code":"PPL",
    "gn:name":"Jiaocunmiaocun",
    "gn:population":0,
    "gn:timezone":"Asia/Shanghai",
    "iso:country":"CN",
    "name:zho_x_preferred":[
        "\u7126\u6751\u5e99\u6751"
    ],
    "wof:name":"Jiaocunmiaocun",
    "wof:placetype":"locality"
},
  "geometry": {"coordinates":[115.32331000000001,34.94165],"type":"Point"}
}