{
  "type": "Feature",
  "properties": {
    "gn:admin1_code":"29.0",
    "gn:asciiname":"Xiantang",
    "gn:country_code":"CN",
    "gn:dem":2089,
    "gn:feature_class":"P",
    "gn:feature_code":"PPL",
    "gn:name":"Xiantang",
    "gn:population":0,
    "gn:timezone":"Asia/Shanghai",
    "iso:country":"CN",
    "name:zho_x_preferred":[
        "\u9677\u5858"
    ],
    "wof:name":"Xiantang",
    "wof:placetype":"locality"
},
  "geometry": {"coordinates":[102.623,25.4684],"type":"Point"}
}