{
  "type": "Feature",
  "properties": {
    "gn:admin1_code":"29",
    "gn:asciiname":"Xiadiandong",
    "gn:country_code":"CN",
    "gn:dem":1231,
    "gn:feature_class":"P",
    "gn:feature_code":"PPL",
    "gn:name":"Xiadiandong",
    "gn:population":0,
    "gn:timezone":"Asia/Shanghai",
    "iso:country":"CN",
    "name:zho_x_preferred":[
        "\u4e0b\u7535\u6d1e"
    ],
    "wof:name":"Xiadiandong",
    "wof:placetype":"locality"
},
  "geometry": {"coordinates":[104.617,23.5009],"type":"Point"}
}