{
  "type": "Feature",
  "properties": {
    "gn:admin1_code":"8.0",
    "gn:asciiname":"Xinqingcun",
    "gn:country_code":"CN",
    "gn:dem":375,
    "gn:feature_class":"P",
    "gn:feature_code":"PPL",
    "gn:name":"Xinqingcun",
    "gn:population":0,
    "gn:timezone":"Asia/Shanghai",
    "iso:country":"CN",
    "name:zho_x_preferred":[
        "\u65b0\u9752\u6751"
    ],
    "wof:name":"Xinqingcun",
    "wof:placetype":"locality"
},
  "geometry": {"coordinates":[126.85226000000002,50.58246],"type":"Point"}
}