{
  "type": "Feature",
  "properties": {
    "gn:admin1_code":"24.0",
    "gn:asciiname":"Xinpu",
    "gn:country_code":"CN",
    "gn:dem":1010,
    "gn:feature_class":"P",
    "gn:feature_code":"PPL",
    "gn:name":"Xinpu",
    "gn:population":0,
    "gn:timezone":"Asia/Shanghai",
    "iso:country":"CN",
    "name:und_x_variant":[
        "\u65b0\u94fa"
    ],
    "wof:name":"Xinpu",
    "wof:placetype":"locality"
},
  "geometry": {"coordinates":[113.17372,39.88894000000001],"type":"Point"}
}