{
  "type": "Feature",
  "properties": {
    "gn:admin1_code":"18",
    "gn:asciiname":"Caijia Yanjiao",
    "gn:country_code":"CN",
    "gn:dem":1972,
    "gn:feature_class":"P",
    "gn:feature_code":"PPL",
    "gn:name":"Caijia Yanjiao",
    "gn:population":0,
    "gn:timezone":"Asia/Shanghai",
    "iso:country":"CN",
    "name:zho_x_preferred":[
        "\u8521\u5bb6\u5ca9\u811a"
    ],
    "wof:name":"Caijia Yanjiao",
    "wof:placetype":"locality"
},
  "geometry": {"coordinates":[104.14700000000001,27.232],"type":"Point"}
}