{
  "type": "Feature",
  "properties": {
    "gn:admin1_code":"3",
    "gn:asciiname":"Caoshi'ao",
    "gn:country_code":"CN",
    "gn:dem":128,
    "gn:feature_class":"P",
    "gn:feature_code":"PPL",
    "gn:name":"Caoshi\u2019ao",
    "gn:population":0,
    "gn:timezone":"Asia/Shanghai",
    "iso:country":"CN",
    "name:und_x_variant":[
        "Caoshi\u2019ao"
    ],
    "name:zho_x_preferred":[
        "\u8349\u5e02\u5773"
    ],
    "wof:name":"Caoshi'ao",
    "wof:placetype":"locality"
},
  "geometry": {"coordinates":[114.18756999999999,26.97343],"type":"Point"}
}