{
  "type": "Feature",
  "properties": {
    "gn:admin1_code":"5.0",
    "gn:asciiname":"Daguan Yingzi",
    "gn:country_code":"CN",
    "gn:dem":159,
    "gn:feature_class":"P",
    "gn:feature_code":"PPL",
    "gn:name":"Daguan Yingzi",
    "gn:population":0,
    "gn:timezone":"Asia/Shanghai",
    "iso:country":"CN",
    "name:zho_x_preferred":[
        "\u5927\u5b98\u8425\u5b50"
    ],
    "wof:name":"Daguan Yingzi",
    "wof:placetype":"locality"
},
  "geometry": {"coordinates":[122.7311,44.93827],"type":"Point"}
}