{
  "type": "Feature",
  "properties": {
    "gn:admin1_code":"15.0",
    "gn:asciiname":"Caimuche",
    "gn:country_code":"CN",
    "gn:dem":3198,
    "gn:feature_class":"P",
    "gn:feature_code":"PPL",
    "gn:name":"Caimuche",
    "gn:population":0,
    "gn:timezone":"Asia/Shanghai",
    "iso:country":"CN",
    "name:und_x_variant":[
        "\u624d\u6728\u8f66"
    ],
    "wof:name":"Caimuche",
    "wof:placetype":"locality"
},
  "geometry": {"coordinates":[103.41161,34.87168],"type":"Point"}
}