{
  "type": "Feature",
  "properties": {
    "gn:admin1_code":"15.0",
    "gn:asciiname":"Quedixia",
    "gn:country_code":"CN",
    "gn:dem":2206,
    "gn:feature_class":"P",
    "gn:feature_code":"PPL",
    "gn:name":"Quedixia",
    "gn:population":0,
    "gn:timezone":"Asia/Shanghai",
    "iso:country":"CN",
    "name:und_x_variant":[
        "\u96c0\u5e95\u4e0b"
    ],
    "name:zho_x_preferred":[
        "\u96c0\u5e95\u4e0b"
    ],
    "wof:name":"Quedixia",
    "wof:placetype":"locality"
},
  "geometry": {"coordinates":[104.92026,33.92583],"type":"Point"}
}