{
  "type": "Feature",
  "properties": {
    "gn:admin1_code":"8.0",
    "gn:asciiname":"Xinwangcun",
    "gn:country_code":"CN",
    "gn:dem":251,
    "gn:feature_class":"P",
    "gn:feature_code":"PPL",
    "gn:name":"Xinwangcun",
    "gn:population":0,
    "gn:timezone":"Asia/Shanghai",
    "iso:country":"CN",
    "name:zho_x_preferred":[
        "\u65b0\u65fa\u6751"
    ],
    "wof:name":"Xinwangcun",
    "wof:placetype":"locality"
},
  "geometry": {"coordinates":[125.84786,47.51432],"type":"Point"}
}