{
  "type": "Feature",
  "properties": {
    "gn:admin1_code":"32.0",
    "gn:asciiname":"Longtansi",
    "gn:country_code":"CN",
    "gn:dem":791,
    "gn:feature_class":"P",
    "gn:feature_code":"PPL",
    "gn:name":"Longtansi",
    "gn:population":0,
    "gn:timezone":"Asia/Shanghai",
    "iso:country":"CN",
    "name:zho_x_preferred":[
        "\u9f99\u6ee9\u5bfa"
    ],
    "wof:name":"Longtansi",
    "wof:placetype":"locality"
},
  "geometry": {"coordinates":[103.14,30.1689],"type":"Point"}
}