{
  "type": "Feature",
  "properties": {
    "gn:admin1_code":"19",
    "gn:asciiname":"Sifangtai",
    "gn:country_code":"CN",
    "gn:dem":21,
    "gn:feature_class":"P",
    "gn:feature_code":"PPL",
    "gn:name":"Sifangtai",
    "gn:population":0,
    "gn:timezone":"Asia/Shanghai",
    "iso:country":"CN",
    "name:und_x_variant":[
        "Ssu-fang-t\u2019ai",
        "Sifangtai"
    ],
    "name:zho_x_preferred":[
        "\u56db\u65b9\u53f0"
    ],
    "wof:name":"Sifangtai",
    "wof:placetype":"locality"
},
  "geometry": {"coordinates":[122.95005999999999,41.57006],"type":"Point"}
}