{
  "type": "Feature",
  "properties": {
    "gn:admin1_code":"29",
    "gn:asciiname":"Sachongdian",
    "gn:country_code":"CN",
    "gn:dem":905,
    "gn:feature_class":"P",
    "gn:feature_code":"PPL",
    "gn:name":"Sachongdian",
    "gn:population":0,
    "gn:timezone":"Asia/Shanghai",
    "iso:country":"CN",
    "name:zho_x_preferred":[
        "\u6d12\u51b2\u70b9"
    ],
    "wof:name":"Sachongdian",
    "wof:placetype":"locality"
},
  "geometry": {"coordinates":[101.965,24.2766],"type":"Point"}
}