{
  "type": "Feature",
  "properties": {
    "gn:admin1_code":"4.0",
    "gn:asciiname":"Huanglianshan",
    "gn:country_code":"CN",
    "gn:dem":20,
    "gn:feature_class":"P",
    "gn:feature_code":"PPL",
    "gn:name":"Huanglianshan",
    "gn:population":0,
    "gn:timezone":"Asia/Shanghai",
    "iso:country":"CN",
    "name:zho_x_preferred":[
        "\u9ec4\u8fde\u5c71"
    ],
    "wof:name":"Huanglianshan",
    "wof:placetype":"locality"
},
  "geometry": {"coordinates":[119.69072,32.07097],"type":"Point"}
}