{
  "type": "Feature",
  "properties": {
    "gn:admin1_code":"21.0",
    "gn:asciiname":"Hong'an",
    "gn:country_code":"CN",
    "gn:dem":1365,
    "gn:feature_class":"P",
    "gn:feature_code":"PPL",
    "gn:name":"Hong\u2019an",
    "gn:population":0,
    "gn:timezone":"Asia/Shanghai",
    "iso:country":"CN",
    "name:und_x_variant":[
        "Hong\u2019an"
    ],
    "name:zho_x_preferred":[
        "\u7ea2\u5cb8"
    ],
    "wof:name":"Hong'an",
    "wof:placetype":"locality"
},
  "geometry": {"coordinates":[105.965,36.879],"type":"Point"}
}