{
  "type": "Feature",
  "properties": {
    "gn:admin1_code":"1.0",
    "gn:asciiname":"Nanliuqiaocun",
    "gn:country_code":"CN",
    "gn:dem":27,
    "gn:feature_class":"P",
    "gn:feature_code":"PPL",
    "gn:name":"Nanliuqiaocun",
    "gn:population":0,
    "gn:timezone":"Asia/Shanghai",
    "iso:country":"CN",
    "name:zho_x_preferred":[
        "\u5357\u5218\u6865\u6751"
    ],
    "wof:name":"Nanliuqiaocun",
    "wof:placetype":"locality"
},
  "geometry": {"coordinates":[117.22572,33.85257],"type":"Point"}
}