{
  "type": "Feature",
  "properties": {
    "gn:admin1_code":"14.0",
    "gn:asciiname":"Pagpoda",
    "gn:country_code":"CN",
    "gn:dem":4425,
    "gn:feature_class":"P",
    "gn:feature_code":"PPL",
    "gn:name":"Pagpoda",
    "gn:population":0,
    "gn:timezone":"Asia/Urumqi",
    "iso:country":"CN",
    "name:bod_x_preferred":[
        "Pagpoda"
    ],
    "name:zho_x_preferred":[
        "Paboda"
    ],
    "name:zho_x_variant":[
        "\u5e15\u6ce2\u8fbe"
    ],
    "wof:name":"Pagpoda",
    "wof:placetype":"locality"
},
  "geometry": {"coordinates":[93.901,32.001],"type":"Point"}
}