{
  "type": "Feature",
  "properties": {
    "gn:admin1_code":"29.0",
    "gn:asciiname":"Meiziqing",
    "gn:country_code":"CN",
    "gn:dem":1386,
    "gn:feature_class":"P",
    "gn:feature_code":"PPL",
    "gn:name":"Meiziqing",
    "gn:population":0,
    "gn:timezone":"Asia/Shanghai",
    "iso:country":"CN",
    "name:zho_x_preferred":[
        "\u6885\u5b50\u7b90"
    ],
    "wof:name":"Meiziqing",
    "wof:placetype":"locality"
},
  "geometry": {"coordinates":[100.836,24.5362],"type":"Point"}
}