{
  "type": "Feature",
  "properties": {
    "gn:admin1_code":"19.0",
    "gn:asciiname":"Xiaogutun",
    "gn:country_code":"CN",
    "gn:dem":10,
    "gn:feature_class":"P",
    "gn:feature_code":"PPL",
    "gn:name":"Xiaogutun",
    "gn:population":0,
    "gn:timezone":"Asia/Shanghai",
    "iso:country":"CN",
    "name:zho_x_preferred":[
        "\u5c0f\u8c37\u5c6f"
    ],
    "wof:name":"Xiaogutun",
    "wof:placetype":"locality"
},
  "geometry": {"coordinates":[120.47799999999999,40.3633],"type":"Point"}
}