{
  "type": "Feature",
  "properties": {
    "gn:admin1_code":"11.0",
    "gn:asciiname":"Niuzhawan",
    "gn:country_code":"CN",
    "gn:dem":1173,
    "gn:feature_class":"P",
    "gn:feature_code":"PPL",
    "gn:name":"Niuzhawan",
    "gn:population":0,
    "gn:timezone":"Asia/Shanghai",
    "iso:country":"CN",
    "name:zho_x_preferred":[
        "Niuzhawan"
    ],
    "name:zho_x_variant":[
        "\u725b\u69a8\u6e7e"
    ],
    "wof:name":"Niuzhawan",
    "wof:placetype":"locality"
},
  "geometry": {"coordinates":[110.53385,30.0253],"type":"Point"}
}