{
  "type": "Feature",
  "properties": {
    "gn:admin1_code":"8.0",
    "gn:asciiname":"Mingdecun",
    "gn:country_code":"CN",
    "gn:dem":79,
    "gn:feature_class":"P",
    "gn:feature_code":"PPL",
    "gn:name":"Mingdecun",
    "gn:population":0,
    "gn:timezone":"Asia/Shanghai",
    "iso:country":"CN",
    "name:zho_x_preferred":[
        "\u660e\u5fb7\u6751"
    ],
    "wof:name":"Mingdecun",
    "wof:placetype":"locality"
},
  "geometry": {"coordinates":[130.33741000000001,46.86997],"type":"Point"}
}