{
  "type": "Feature",
  "properties": {
    "gn:admin1_code":"29.0",
    "gn:asciiname":"Huangzhulin",
    "gn:country_code":"CN",
    "gn:dem":1959,
    "gn:feature_class":"P",
    "gn:feature_code":"PPL",
    "gn:name":"Huangzhulin",
    "gn:population":0,
    "gn:timezone":"Asia/Shanghai",
    "iso:country":"CN",
    "name:zho_x_preferred":[
        "\u9ec4\u7af9\u6797"
    ],
    "wof:name":"Huangzhulin",
    "wof:placetype":"locality"
},
  "geometry": {"coordinates":[103.771,27.3524],"type":"Point"}
}