{
  "type": "Feature",
  "properties": {
    "gn:admin1_code":"31.0",
    "gn:asciiname":"Donghong Ershisidui",
    "gn:country_code":"CN",
    "gn:dem":106,
    "gn:feature_class":"P",
    "gn:feature_code":"PPLF",
    "gn:name":"Donghong Ershisidui",
    "gn:population":0,
    "gn:timezone":"Asia/Shanghai",
    "iso:country":"CN",
    "name:und_x_variant":[
        "\u4e1c\u7ea2\u4e8c\u56db\u961f"
    ],
    "wof:name":"Donghong Ershisidui",
    "wof:placetype":"locality"
},
  "geometry": {"coordinates":[110.52334999999999,19.4582],"type":"Point"}
}