{
  "type": "Feature",
  "properties": {
    "gn:admin1_code":"12.0",
    "gn:asciiname":"Liyuanyuan",
    "gn:country_code":"CN",
    "gn:dem":16,
    "gn:feature_class":"P",
    "gn:feature_code":"PPL",
    "gn:name":"Liyuanyuan",
    "gn:population":0,
    "gn:timezone":"Asia/Shanghai",
    "iso:country":"CN",
    "name:zho_x_preferred":[
        "\u674e\u56ed\u57b8"
    ],
    "wof:name":"Liyuanyuan",
    "wof:placetype":"locality"
},
  "geometry": {"coordinates":[115.69018,29.92291],"type":"Point"}
}