{
  "type": "Feature",
  "properties": {
    "gn:admin1_code":"4.0",
    "gn:asciiname":"Huangsha",
    "gn:country_code":"CN",
    "gn:dem":2,
    "gn:feature_class":"P",
    "gn:feature_code":"PPL",
    "gn:name":"Huangsha",
    "gn:population":0,
    "gn:timezone":"Asia/Shanghai",
    "iso:country":"CN",
    "name:zho_x_preferred":[
        "Huangsha"
    ],
    "name:zho_x_variant":[
        "\u9ec4\u6c99"
    ],
    "wof:name":"Huangsha",
    "wof:placetype":"locality"
},
  "geometry": {"coordinates":[119.15998,34.80856],"type":"Point"}
}