{
  "type": "Feature",
  "properties": {
    "gn:admin1_code":"6.0",
    "gn:asciiname":"Chalengkou",
    "gn:country_code":"CN",
    "gn:dem":2788,
    "gn:feature_class":"P",
    "gn:feature_code":"PPL",
    "gn:name":"Chalengkou",
    "gn:population":0,
    "gn:timezone":"Asia/Urumqi",
    "iso:country":"CN",
    "wof:name":"Chalengkou",
    "wof:placetype":"locality"
},
  "geometry": {"coordinates":[93.90000000000001,38.03333],"type":"Point"}
}