{
  "type": "Feature",
  "properties": {
    "gn:admin1_code":"6.0",
    "gn:asciiname":"Shi'er Zhongdui",
    "gn:country_code":"CN",
    "gn:dem":3200,
    "gn:feature_class":"P",
    "gn:feature_code":"PPLF",
    "gn:name":"Shi\u2019er Zhongdui",
    "gn:population":0,
    "gn:timezone":"Asia/Shanghai",
    "iso:country":"CN",
    "name:und_x_variant":[
        "Shi\u2019er Zhongdui",
        "\u5341\u4e8c\u4e2d\u961f"
    ],
    "wof:name":"Shi'er Zhongdui",
    "wof:placetype":"locality"
},
  "geometry": {"coordinates":[100.34829000000001,35.67137],"type":"Point"}
}