{
  "type": "Feature",
  "properties": {
    "gn:admin1_code":"29.0",
    "gn:asciiname":"Shangguangling",
    "gn:country_code":"CN",
    "gn:dem":1388,
    "gn:feature_class":"P",
    "gn:feature_code":"PPL",
    "gn:name":"Shangguangling",
    "gn:population":0,
    "gn:timezone":"Asia/Shanghai",
    "iso:country":"CN",
    "name:zho_x_preferred":[
        "\u4e0a\u5e7f\u4ee4"
    ],
    "wof:name":"Shangguangling",
    "wof:placetype":"locality"
},
  "geometry": {"coordinates":[98.0665,24.8401],"type":"Point"}
}