{
  "type": "Feature",
  "properties": {
    "gn:admin1_code":"8.0",
    "gn:asciiname":"Sandao Pancha",
    "gn:country_code":"CN",
    "gn:dem":299,
    "gn:feature_class":"P",
    "gn:feature_code":"PPL",
    "gn:name":"Sandao Pancha",
    "gn:population":0,
    "gn:timezone":"Asia/Shanghai",
    "iso:country":"CN",
    "name:zho_x_preferred":[
        "\u4e09\u9053\u76d8\u67e5"
    ],
    "wof:name":"Sandao Pancha",
    "wof:placetype":"locality"
},
  "geometry": {"coordinates":[126.19127,51.76685],"type":"Point"}
}