{
  "type": "Feature",
  "properties": {
    "gn:admin1_code":"22.0",
    "gn:asciiname":"Louzishuicun",
    "gn:country_code":"CN",
    "gn:dem":71,
    "gn:feature_class":"P",
    "gn:feature_code":"PPL",
    "gn:name":"Louzishuicun",
    "gn:population":0,
    "gn:timezone":"Asia/Shanghai",
    "iso:country":"CN",
    "name:zho_x_preferred":[
        "\u5a04\u5b50\u6c34\u6751"
    ],
    "wof:name":"Louzishuicun",
    "wof:placetype":"locality"
},
  "geometry": {"coordinates":[115.91001,39.66434],"type":"Point"}
}