{
  "type": "Feature",
  "properties": {
    "gn:admin1_code":"22.0",
    "gn:asciiname":"Shuangwopucun",
    "gn:country_code":"CN",
    "gn:dem":508,
    "gn:feature_class":"P",
    "gn:feature_code":"PPL",
    "gn:name":"Shuangwopucun",
    "gn:population":0,
    "gn:timezone":"Asia/Shanghai",
    "iso:country":"CN",
    "name:zho_x_preferred":[
        "\u53cc\u7a9d\u94fa\u6751"
    ],
    "wof:name":"Shuangwopucun",
    "wof:placetype":"locality"
},
  "geometry": {"coordinates":[116.86364,40.67317],"type":"Point"}
}