{
  "type": "Feature",
  "properties": {
    "gn:admin1_code":"2.0",
    "gn:asciiname":"Jiangxuanjia",
    "gn:country_code":"CN",
    "gn:dem":209,
    "gn:feature_class":"P",
    "gn:feature_code":"PPL",
    "gn:name":"Jiangxuanjia",
    "gn:population":0,
    "gn:timezone":"Asia/Shanghai",
    "iso:country":"CN",
    "name:zho_x_preferred":[
        "\u59dc\u5ba3\u5bb6"
    ],
    "wof:name":"Jiangxuanjia",
    "wof:placetype":"locality"
},
  "geometry": {"coordinates":[119.50237,27.86709],"type":"Point"}
}