{
  "type": "Feature",
  "properties": {
    "gn:admin1_code":"15.0",
    "gn:asciiname":"Lujiagou",
    "gn:country_code":"CN",
    "gn:dem":2117,
    "gn:feature_class":"P",
    "gn:feature_code":"PPL",
    "gn:name":"Lujiagou",
    "gn:population":0,
    "gn:timezone":"Asia/Shanghai",
    "iso:country":"CN",
    "name:zho_x_preferred":[
        "\u9c81\u5bb6\u6c9f"
    ],
    "wof:name":"Lujiagou",
    "wof:placetype":"locality"
},
  "geometry": {"coordinates":[104.303,35.9932],"type":"Point"}
}