{
  "type": "Feature",
  "properties": {
    "gn:admin1_code":"26.0",
    "gn:asciiname":"Shequ",
    "gn:country_code":"CN",
    "gn:dem":1516,
    "gn:feature_class":"P",
    "gn:feature_code":"PPL",
    "gn:name":"Shequ",
    "gn:population":0,
    "gn:timezone":"Asia/Shanghai",
    "iso:country":"CN",
    "name:zho_x_preferred":[
        "\u4f58\u6e20"
    ],
    "wof:name":"Shequ",
    "wof:placetype":"locality"
},
  "geometry": {"coordinates":[108.02331,37.4044],"type":"Point"}
}