{
  "type": "Feature",
  "properties": {
    "gn:admin1_code":"26.0",
    "gn:asciiname":"Shequ",
    "gn:country_code":"CN",
    "gn:dem":1516,
    "gn:feature_class":"P",
    "gn:feature_code":"PPL",
    "gn:name":"Shequ",
    "gn:population":0,
    "gn:timezone":"Asia/Shanghai",
    "iso:country":"CN",
    "name:deu_x_preferred":[
        "Einwohnergemeinschaft"
    ],
    "name:rus_x_preferred":[
        "\u041c\u0438\u043a\u0440\u043e\u0440\u0430\u0439\u043e\u043d"
    ],
    "name:uig_x_preferred":[
        "\u0645\u06d5\u06be\u06d5\u0644\u0644\u06d5"
    ],
    "name:zho_x_preferred":[
        "\u4f58\u6e20"
    ],
    "name:zho_x_variant":[
        "\u793e\u533a"
    ],
    "wof:name":"Shequ",
    "wof:placetype":"locality"
},
  "geometry": {"coordinates":[108.02331,37.4044],"type":"Point"}
}