{
  "type": "Feature",
  "properties": {
    "gn:admin1_code":"2.0",
    "gn:asciiname":"Baijiaowu",
    "gn:country_code":"CN",
    "gn:dem":424,
    "gn:feature_class":"P",
    "gn:feature_code":"PPL",
    "gn:name":"Baijiaowu",
    "gn:population":0,
    "gn:timezone":"Asia/Shanghai",
    "iso:country":"CN",
    "name:zho_x_preferred":[
        "\u767e\u811a\u575e"
    ],
    "wof:name":"Baijiaowu",
    "wof:placetype":"locality"
},
  "geometry": {"coordinates":[119.79841,29.31443],"type":"Point"}
}