{
  "type": "Feature",
  "properties": {
    "gn:admin1_code":"2.0",
    "gn:asciiname":"Waidakeng",
    "gn:country_code":"CN",
    "gn:dem":316,
    "gn:feature_class":"P",
    "gn:feature_code":"PPL",
    "gn:name":"Waidakeng",
    "gn:population":0,
    "gn:timezone":"Asia/Shanghai",
    "iso:country":"CN",
    "name:zho_x_preferred":[
        "\u5916\u5927\u5751"
    ],
    "wof:name":"Waidakeng",
    "wof:placetype":"locality"
},
  "geometry": {"coordinates":[121.08355,29.4277],"type":"Point"}
}