{
  "type": "Feature",
  "properties": {
    "gn:admin1_code":"30.0",
    "gn:asciiname":"Shanghuangdicun",
    "gn:country_code":"CN",
    "gn:dem":423,
    "gn:feature_class":"P",
    "gn:feature_code":"PPL",
    "gn:name":"Shanghuangdicun",
    "gn:population":0,
    "gn:timezone":"Asia/Shanghai",
    "iso:country":"CN",
    "name:zho_x_preferred":[
        "\u4e0a\u9ec4\u5730\u6751"
    ],
    "wof:name":"Shanghuangdicun",
    "wof:placetype":"locality"
},
  "geometry": {"coordinates":[116.01733,24.6646],"type":"Point"}
}