{
  "type": "Feature",
  "properties": {
    "gn:admin1_code":"18",
    "gn:asciiname":"Datuzhai",
    "gn:country_code":"CN",
    "gn:dem":1460,
    "gn:feature_class":"P",
    "gn:feature_code":"PPL",
    "gn:name":"Datuzhai",
    "gn:population":0,
    "gn:timezone":"Asia/Shanghai",
    "iso:country":"CN",
    "name:zho_x_preferred":[
        "\u5927\u571f\u5be8"
    ],
    "wof:name":"Datuzhai",
    "wof:placetype":"locality"
},
  "geometry": {"coordinates":[105.36,26.8567],"type":"Point"}
}