{
  "type": "Feature",
  "properties": {
    "gn:admin1_code":"12.0",
    "gn:asciiname":"Panjiashan",
    "gn:country_code":"CN",
    "gn:dem":98,
    "gn:feature_class":"P",
    "gn:feature_code":"PPL",
    "gn:name":"Panjiashan",
    "gn:population":0,
    "gn:timezone":"Asia/Shanghai",
    "iso:country":"CN",
    "name:zho_x_preferred":[
        "Panjiashan"
    ],
    "name:zho_x_variant":[
        "\u6f58\u5bb6\u5c71"
    ],
    "wof:name":"Panjiashan",
    "wof:placetype":"locality"
},
  "geometry": {"coordinates":[111.81838999999999,30.63064],"type":"Point"}
}