{
  "type": "Feature",
  "properties": {
    "gn:admin1_code":"29.0",
    "gn:asciiname":"Qianzhe Shangzhai",
    "gn:country_code":"CN",
    "gn:dem":1335,
    "gn:feature_class":"P",
    "gn:feature_code":"PPL",
    "gn:name":"Qianzhe Shangzhai",
    "gn:population":0,
    "gn:timezone":"Asia/Shanghai",
    "iso:country":"CN",
    "name:zho_x_preferred":[
        "\u8c26\u54f2\u4e0a\u5be8"
    ],
    "wof:name":"Qianzhe Shangzhai",
    "wof:placetype":"locality"
},
  "geometry": {"coordinates":[100.008,22.8001],"type":"Point"}
}