{
  "type": "Feature",
  "properties": {
    "gn:admin1_code":"14",
    "gn:asciiname":"Onggo",
    "gn:country_code":"CN",
    "gn:dem":4530,
    "gn:feature_class":"P",
    "gn:feature_code":"PPL",
    "gn:name":"Onggo",
    "gn:population":0,
    "gn:timezone":"Asia/Urumqi",
    "iso:country":"CN",
    "name:bod_x_preferred":[
        "\u0f60\u0f7c\u0f44\u0f0b\u0f58\u0f42\u0f7c"
    ],
    "wof:name":"Onggo",
    "wof:placetype":"locality"
},
  "geometry": {"coordinates":[90.37903,28.92223],"type":"Point"}
}