{
  "type": "Feature",
  "properties": {
    "gn:admin1_code":"19.0",
    "gn:asciiname":"Kangzhangzi",
    "gn:country_code":"CN",
    "gn:dem":674,
    "gn:feature_class":"P",
    "gn:feature_code":"PPL",
    "gn:name":"Kangzhangzi",
    "gn:population":0,
    "gn:timezone":"Asia/Shanghai",
    "iso:country":"CN",
    "name:und_x_variant":[
        "\u5eb7\u6756\u5b50"
    ],
    "name:zho_x_preferred":[
        "\u5eb7\u6756\u5b50"
    ],
    "wof:name":"Kangzhangzi",
    "wof:placetype":"locality"
},
  "geometry": {"coordinates":[119.91822000000001,41.52031],"type":"Point"}
}