{
  "type": "Feature",
  "properties": {
    "gn:admin1_code":"5.0",
    "gn:asciiname":"Naizijing",
    "gn:country_code":"CN",
    "gn:dem":138,
    "gn:feature_class":"P",
    "gn:feature_code":"PPL",
    "gn:name":"Naizijing",
    "gn:population":0,
    "gn:timezone":"Asia/Shanghai",
    "iso:country":"CN",
    "name:zho_x_preferred":[
        "\u4e43\u5b57\u4e95"
    ],
    "wof:name":"Naizijing",
    "wof:placetype":"locality"
},
  "geometry": {"coordinates":[123.67919999999999,45.00178],"type":"Point"}
}