{
  "type": "Feature",
  "properties": {
    "gn:admin1_code":"30.0",
    "gn:asciiname":"Zhaidianxin",
    "gn:country_code":"CN",
    "gn:dem":45,
    "gn:feature_class":"P",
    "gn:feature_code":"PPL",
    "gn:name":"Zhaidianxin",
    "gn:population":0,
    "gn:timezone":"Asia/Shanghai",
    "iso:country":"CN",
    "name:zho_x_preferred":[
        "\u5b85\u4f43\u65b0"
    ],
    "wof:name":"Zhaidianxin",
    "wof:placetype":"locality"
},
  "geometry": {"coordinates":[112.60679,22.64458],"type":"Point"}
}