{
  "type": "Feature",
  "properties": {
    "gn:admin1_code":"4.0",
    "gn:asciiname":"Mengzhuang",
    "gn:country_code":"CN",
    "gn:dem":0,
    "gn:feature_class":"P",
    "gn:feature_code":"PPL",
    "gn:name":"Mengzhuang",
    "gn:population":0,
    "gn:timezone":"Asia/Shanghai",
    "iso:country":"CN",
    "name:zho_x_preferred":[
        "Mengzhuang"
    ],
    "name:zho_x_variant":[
        "\u5b5f\u5e84"
    ],
    "wof:name":"Mengzhuang",
    "wof:placetype":"locality"
},
  "geometry": {"coordinates":[119.7424,33.32071],"type":"Point"}
}