{
  "type": "Feature",
  "properties": {
    "gn:admin1_code":"19.0",
    "gn:asciiname":"Qianshicun",
    "gn:country_code":"CN",
    "gn:dem":23,
    "gn:feature_class":"P",
    "gn:feature_code":"PPL",
    "gn:name":"Qianshicun",
    "gn:population":0,
    "gn:timezone":"Asia/Shanghai",
    "iso:country":"CN",
    "name:zho_x_preferred":[
        "\u524d\u77f3\u6751"
    ],
    "wof:name":"Qianshicun",
    "wof:placetype":"locality"
},
  "geometry": {"coordinates":[122.68000000000001,40.849],"type":"Point"}
}