{
  "type": "Feature",
  "properties": {
    "gn:admin1_code":"33.0",
    "gn:asciiname":"Lanbazi",
    "gn:country_code":"CN",
    "gn:dem":1299,
    "gn:feature_class":"P",
    "gn:feature_code":"PPL",
    "gn:name":"Lanbazi",
    "gn:population":0,
    "gn:timezone":"Asia/Shanghai",
    "iso:country":"CN",
    "name:zho_x_preferred":[
        "\u6ee5\u575d\u5b50"
    ],
    "wof:name":"Lanbazi",
    "wof:placetype":"locality"
},
  "geometry": {"coordinates":[107.98378999999998,29.14454000000001],"type":"Point"}
}