{
  "type": "Feature",
  "properties": {
    "gn:admin1_code":"14.0",
    "gn:asciiname":"Naixi",
    "gn:country_code":"CN",
    "gn:dem":3899,
    "gn:feature_class":"P",
    "gn:feature_code":"PPL",
    "gn:name":"Naixi",
    "gn:population":0,
    "gn:timezone":"Asia/Urumqi",
    "iso:country":"CN",
    "name:bod_x_preferred":[
        "\u0f42\u0f53\u0f66\u0f0b\u0f56\u0f5e\u0f72"
    ],
    "name:msa_x_preferred":[
        "Naixi"
    ],
    "name:zho_x_preferred":[
        "\u4e43\u897f"
    ],
    "wof:name":"Naixi",
    "wof:placetype":"locality"
},
  "geometry": {"coordinates":[91.37569000000001,28.35424],"type":"Point"}
}