{
  "type": "Feature",
  "properties": {
    "gn:admin1_code":"3.0",
    "gn:asciiname":"Xiamazhou",
    "gn:country_code":"CN",
    "gn:dem":112,
    "gn:feature_class":"P",
    "gn:feature_code":"PPL",
    "gn:name":"Xiamazhou",
    "gn:population":0,
    "gn:timezone":"Asia/Shanghai",
    "iso:country":"CN",
    "name:und_x_variant":[
        "\u4e0b\u9ebb\u5dde"
    ],
    "wof:name":"Xiamazhou",
    "wof:placetype":"locality"
},
  "geometry": {"coordinates":[116.17103,27.43486],"type":"Point"}
}