{
  "type": "Feature",
  "properties": {
    "gn:admin1_code":"16.0",
    "gn:asciiname":"Longmen",
    "gn:country_code":"CN",
    "gn:dem":177,
    "gn:feature_class":"P",
    "gn:feature_code":"PPL",
    "gn:name":"Longmen",
    "gn:population":0,
    "gn:timezone":"Asia/Shanghai",
    "iso:country":"CN",
    "name:ceb_x_preferred":[
        "Longmen"
    ],
    "name:deu_x_preferred":[
        "Longmen"
    ],
    "name:fra_x_preferred":[
        "Longmen"
    ],
    "name:mlg_x_preferred":[
        "Longmen"
    ],
    "name:nor_x_preferred":[
        "Longmen"
    ],
    "name:pol_x_preferred":[
        "Longmen"
    ],
    "name:vie_x_preferred":[
        "Long M\u00f4n"
    ],
    "name:zho_x_preferred":[
        "\u9647\u95e8"
    ],
    "wof:name":"Longmen",
    "wof:placetype":"locality"
},
  "geometry": {"coordinates":[107.03400000000001,22.3075],"type":"Point"}
}