{
  "type": "Feature",
  "properties": {
    "gn:admin1_code":"29.0",
    "gn:asciiname":"Dasongpo",
    "gn:country_code":"CN",
    "gn:dem":1169,
    "gn:feature_class":"P",
    "gn:feature_code":"PPL",
    "gn:name":"Dasongpo",
    "gn:population":0,
    "gn:timezone":"Asia/Shanghai",
    "iso:country":"CN",
    "name:zho_x_preferred":[
        "\u5927\u677e\u5761"
    ],
    "wof:name":"Dasongpo",
    "wof:placetype":"locality"
},
  "geometry": {"coordinates":[98.6746,24.7278],"type":"Point"}
}