{
  "type": "Feature",
  "properties": {
    "gn:admin1_code":"11",
    "gn:asciiname":"Renwan",
    "gn:cc2":"CN",
    "gn:country_code":"CN",
    "gn:dem":103,
    "gn:feature_class":"P",
    "gn:feature_code":"PPL",
    "gn:name":"Renwan",
    "gn:population":0,
    "gn:timezone":"Asia/Shanghai",
    "iso:country":"CN",
    "name:und_x_variant":[
        "Hengchong",
        "Renwan"
    ],
    "wof:name":"Renwan",
    "wof:placetype":"locality"
},
  "geometry": {"coordinates":[111.58222000000001,26.41167],"type":"Point"}
}