{
  "type": "Feature",
  "properties": {
    "gn:admin1_code":"7",
    "gn:asciiname":"Yuanpan",
    "gn:country_code":"CN",
    "gn:dem":272,
    "gn:feature_class":"P",
    "gn:feature_code":"PPL",
    "gn:name":"Yuanpan",
    "gn:population":0,
    "gn:timezone":"Asia/Shanghai",
    "iso:country":"CN",
    "name:zho_x_preferred":[
        "\u5458\u76d8"
    ],
    "wof:name":"Yuanpan",
    "wof:placetype":"locality"
},
  "geometry": {"coordinates":[118.68513,27.91508],"type":"Point"}
}