{
  "type": "Feature",
  "properties": {
    "gn:admin1_code":"16.0",
    "gn:asciiname":"Weitu",
    "gn:country_code":"CN",
    "gn:dem":1176,
    "gn:feature_class":"P",
    "gn:feature_code":"PPL",
    "gn:name":"Weitu",
    "gn:population":0,
    "gn:timezone":"Asia/Shanghai",
    "iso:country":"CN",
    "name:zho_x_preferred":[
        "\u5c3e\u571f"
    ],
    "wof:name":"Weitu",
    "wof:placetype":"locality"
},
  "geometry": {"coordinates":[106.396,24.3282],"type":"Point"}
}