{
  "type": "Feature",
  "properties": {
    "gn:admin1_code":"26.0",
    "gn:asciiname":"Tangjiawan",
    "gn:country_code":"CN",
    "gn:dem":1153,
    "gn:feature_class":"P",
    "gn:feature_code":"PPL",
    "gn:name":"Tangjiawan",
    "gn:population":0,
    "gn:timezone":"Asia/Shanghai",
    "iso:country":"CN",
    "name:und_x_variant":[
        "\u5510\u5bb6\u6e7e"
    ],
    "wof:name":"Tangjiawan",
    "wof:placetype":"locality"
},
  "geometry": {"coordinates":[106.85248,33.57535],"type":"Point"}
}