{
  "type": "Feature",
  "properties": {
    "gn:admin1_code":"29.0",
    "gn:asciiname":"Kaladi",
    "gn:country_code":"CN",
    "gn:dem":2399,
    "gn:feature_class":"P",
    "gn:feature_code":"PPL",
    "gn:name":"Kaladi",
    "gn:population":0,
    "gn:timezone":"Asia/Shanghai",
    "iso:country":"CN",
    "name:zho_x_preferred":[
        "\u5361\u62c9\u5730"
    ],
    "wof:name":"Kaladi",
    "wof:placetype":"locality"
},
  "geometry": {"coordinates":[101.264,25.9425],"type":"Point"}
}