{
  "type": "Feature",
  "properties": {
    "gn:admin1_code":"19.0",
    "gn:asciiname":"Shiqiaozicun",
    "gn:country_code":"CN",
    "gn:dem":356,
    "gn:feature_class":"P",
    "gn:feature_code":"PPL",
    "gn:name":"Shiqiaozicun",
    "gn:population":0,
    "gn:timezone":"Asia/Shanghai",
    "iso:country":"CN",
    "name:zho_x_preferred":[
        "\u77f3\u6865\u5b50\u6751"
    ],
    "wof:name":"Shiqiaozicun",
    "wof:placetype":"locality"
},
  "geometry": {"coordinates":[120.126,40.9958],"type":"Point"}
}