{
  "type": "Feature",
  "properties": {
    "gn:admin1_code":"24.0",
    "gn:asciiname":"Nanshusi",
    "gn:country_code":"CN",
    "gn:dem":527,
    "gn:feature_class":"P",
    "gn:feature_code":"PPL",
    "gn:name":"Nanshusi",
    "gn:population":0,
    "gn:timezone":"Asia/Shanghai",
    "iso:country":"CN",
    "name:und_x_variant":[
        "\u5357\u5c5e\u5bfa"
    ],
    "wof:name":"Nanshusi",
    "wof:placetype":"locality"
},
  "geometry": {"coordinates":[111.59283000000001,35.60707],"type":"Point"}
}