{
  "type": "Feature",
  "properties": {
    "gn:admin1_code":"16.0",
    "gn:asciiname":"Zhegu",
    "gn:country_code":"CN",
    "gn:dem":97,
    "gn:feature_class":"P",
    "gn:feature_code":"PPL",
    "gn:name":"Zhegu",
    "gn:population":0,
    "gn:timezone":"Asia/Shanghai",
    "iso:country":"CN",
    "name:zho_x_preferred":[
        "\u9e67\u9e2a"
    ],
    "wof:name":"Zhegu",
    "wof:placetype":"locality"
},
  "geometry": {"coordinates":[110.14100000000001,23.1399],"type":"Point"}
}