{
  "type": "Feature",
  "properties": {
    "gn:admin1_code":"1.0",
    "gn:asciiname":"Chengnan",
    "gn:country_code":"CN",
    "gn:dem":8,
    "gn:feature_class":"P",
    "gn:feature_code":"PPL",
    "gn:name":"Chengnan",
    "gn:population":0,
    "gn:timezone":"Asia/Shanghai",
    "iso:country":"CN",
    "name:ceb_x_preferred":[
        "Chengnan"
    ],
    "name:deu_x_preferred":[
        "Chengnan"
    ],
    "name:swe_x_preferred":[
        "Chengnan"
    ],
    "name:zho_x_preferred":[
        "\u57ce\u5357"
    ],
    "wof:name":"Chengnan",
    "wof:placetype":"locality"
},
  "geometry": {"coordinates":[118.35465000000001,31.69794000000001],"type":"Point"}
}