{
  "type": "Feature",
  "properties": {
    "gn:admin1_code":"19.0",
    "gn:asciiname":"Pengjia Wazi",
    "gn:country_code":"CN",
    "gn:dem":143,
    "gn:feature_class":"P",
    "gn:feature_code":"PPL",
    "gn:name":"Pengjia Wazi",
    "gn:population":0,
    "gn:timezone":"Asia/Shanghai",
    "iso:country":"CN",
    "name:zho_x_preferred":[
        "\u5f6d\u5bb6\u6d3c\u5b50"
    ],
    "wof:name":"Pengjia Wazi",
    "wof:placetype":"locality"
},
  "geometry": {"coordinates":[124.125,43.0148],"type":"Point"}
}