{
  "type": "Feature",
  "properties": {
    "gn:admin1_code":"32.0",
    "gn:asciiname":"Jiesi",
    "gn:country_code":"CN",
    "gn:dem":2754,
    "gn:feature_class":"P",
    "gn:feature_code":"PPL",
    "gn:name":"Jiesi",
    "gn:population":0,
    "gn:timezone":"Asia/Shanghai",
    "iso:country":"CN",
    "name:zho_x_preferred":[
        "\u7ed3\u65af"
    ],
    "wof:name":"Jiesi",
    "wof:placetype":"locality"
},
  "geometry": {"coordinates":[102.53655999999999,31.10871],"type":"Point"}
}