{
  "type": "Feature",
  "properties": {
    "gn:admin1_code":"15.0",
    "gn:asciiname":"Huangciliang",
    "gn:country_code":"CN",
    "gn:dem":1241,
    "gn:feature_class":"P",
    "gn:feature_code":"PPL",
    "gn:name":"Huangciliang",
    "gn:population":0,
    "gn:timezone":"Asia/Shanghai",
    "iso:country":"CN",
    "name:zho_x_preferred":[
        "\u9ec4\u8328\u6881"
    ],
    "wof:name":"Huangciliang",
    "wof:placetype":"locality"
},
  "geometry": {"coordinates":[99.0393,40.0452],"type":"Point"}
}