{
  "type": "Feature",
  "properties": {
    "gn:admin1_code":"30",
    "gn:asciiname":"Ganmuwan",
    "gn:country_code":"CN",
    "gn:dem":433,
    "gn:feature_class":"P",
    "gn:feature_code":"PPL",
    "gn:name":"Ganmuwan",
    "gn:population":0,
    "gn:timezone":"Asia/Shanghai",
    "iso:country":"CN",
    "name:zho_x_preferred":[
        "\u7518\u6728\u6e7e"
    ],
    "wof:name":"Ganmuwan",
    "wof:placetype":"locality"
},
  "geometry": {"coordinates":[111.48394,22.32316],"type":"Point"}
}