{
  "type": "Feature",
  "properties": {
    "gn:admin1_code":"19.0",
    "gn:asciiname":"Tanghecun",
    "gn:country_code":"CN",
    "gn:dem":49,
    "gn:feature_class":"P",
    "gn:feature_code":"PPL",
    "gn:name":"Tanghecun",
    "gn:population":0,
    "gn:timezone":"Asia/Shanghai",
    "iso:country":"CN",
    "name:zho_x_preferred":[
        "\u6c64\u6cb3\u6751"
    ],
    "wof:name":"Tanghecun",
    "wof:placetype":"locality"
},
  "geometry": {"coordinates":[124.15363000000001,40.32376],"type":"Point"}
}