{
  "type": "Feature",
  "properties": {
    "gn:admin1_code":"16.0",
    "gn:asciiname":"Bachao",
    "gn:country_code":"CN",
    "gn:dem":814,
    "gn:feature_class":"P",
    "gn:feature_code":"PPL",
    "gn:name":"Bachao",
    "gn:population":0,
    "gn:timezone":"Asia/Shanghai",
    "iso:country":"CN",
    "name:zho_x_preferred":[
        "\u5df4\u671d"
    ],
    "wof:name":"Bachao",
    "wof:placetype":"locality"
},
  "geometry": {"coordinates":[107.197,24.4071],"type":"Point"}
}