{
  "type": "Feature",
  "properties": {
    "gn:admin1_code":"4.0",
    "gn:asciiname":"Xinhankoucun",
    "gn:country_code":"CN",
    "gn:dem":4,
    "gn:feature_class":"P",
    "gn:feature_code":"PPL",
    "gn:name":"Xinhankoucun",
    "gn:population":0,
    "gn:timezone":"Asia/Shanghai",
    "iso:country":"CN",
    "name:zho_x_preferred":[
        "\u65b0\u97e9\u53e3\u6751"
    ],
    "wof:name":"Xinhankoucun",
    "wof:placetype":"locality"
},
  "geometry": {"coordinates":[119.18792999999999,35.00787],"type":"Point"}
}