{
  "type": "Feature",
  "properties": {
    "gn:admin1_code":"24.0",
    "gn:asciiname":"Caojiazhuang",
    "gn:country_code":"CN",
    "gn:dem":981,
    "gn:feature_class":"P",
    "gn:feature_code":"PPL",
    "gn:name":"Caojiazhuang",
    "gn:population":0,
    "gn:timezone":"Asia/Shanghai",
    "iso:country":"CN",
    "name:zho_x_preferred":[
        "\u66f9\u5bb6\u5e84"
    ],
    "wof:name":"Caojiazhuang",
    "wof:placetype":"locality"
},
  "geometry": {"coordinates":[110.56023999999999,35.98285],"type":"Point"}
}