{
  "type": "Feature",
  "properties": {
    "gn:admin1_code":"26.0",
    "gn:asciiname":"Xieshui",
    "gn:country_code":"CN",
    "gn:dem":539,
    "gn:feature_class":"P",
    "gn:feature_code":"PPLA4",
    "gn:name":"Xieshui",
    "gn:population":0,
    "gn:timezone":"Asia/Shanghai",
    "iso:country":"CN",
    "name:und_x_variant":[
        "\u534f\u7a0e",
        "Xieshui Zhen",
        "\u534f\u7a0e\u9547"
    ],
    "wof:name":"Xieshui",
    "wof:placetype":"locality"
},
  "geometry": {"coordinates":[106.90931999999999,33.0043],"type":"Point"}
}