{
  "type": "Feature",
  "properties": {
    "gn:admin1_code":"3.0",
    "gn:asciiname":"Huangchong",
    "gn:country_code":"CN",
    "gn:dem":115,
    "gn:feature_class":"P",
    "gn:feature_code":"PPL",
    "gn:name":"Huangchong",
    "gn:population":0,
    "gn:timezone":"Asia/Shanghai",
    "iso:country":"CN",
    "name:und_x_variant":[
        "\u9ec4\u51b2"
    ],
    "wof:name":"Huangchong",
    "wof:placetype":"locality"
},
  "geometry": {"coordinates":[114.82592,27.28387],"type":"Point"}
}