{
  "type": "Feature",
  "properties": {
    "gn:admin1_code":"32.0",
    "gn:asciiname":"Damaiba",
    "gn:country_code":"CN",
    "gn:dem":357,
    "gn:feature_class":"P",
    "gn:feature_code":"PPL",
    "gn:name":"Damaiba",
    "gn:population":0,
    "gn:timezone":"Asia/Shanghai",
    "iso:country":"CN",
    "name:zho_x_preferred":[
        "\u5927\u9ea6\u575d"
    ],
    "wof:name":"Damaiba",
    "wof:placetype":"locality"
},
  "geometry": {"coordinates":[104.63611,28.81948],"type":"Point"}
}