{
  "type": "Feature",
  "properties": {
    "gn:admin1_code":"8.0",
    "gn:asciiname":"Hexicun",
    "gn:country_code":"CN",
    "gn:dem":319,
    "gn:feature_class":"P",
    "gn:feature_code":"PPL",
    "gn:name":"Hexicun",
    "gn:population":0,
    "gn:timezone":"Asia/Shanghai",
    "iso:country":"CN",
    "name:zho_x_preferred":[
        "\u6cb3\u897f\u6751"
    ],
    "wof:name":"Hexicun",
    "wof:placetype":"locality"
},
  "geometry": {"coordinates":[128.58680000000001,44.79454000000001],"type":"Point"}
}