{
  "type": "Feature",
  "properties": {
    "gn:admin1_code":"16.0",
    "gn:asciiname":"Pingliang",
    "gn:country_code":"CN",
    "gn:dem":520,
    "gn:feature_class":"P",
    "gn:feature_code":"PPL",
    "gn:name":"Pingliang",
    "gn:population":0,
    "gn:timezone":"Asia/Shanghai",
    "iso:country":"CN",
    "name:zho_x_preferred":[
        "\u5e73\u91cf"
    ],
    "wof:name":"Pingliang",
    "wof:placetype":"locality"
},
  "geometry": {"coordinates":[106.89700000000001,23.2723],"type":"Point"}
}