{
  "type": "Feature",
  "properties": {
    "gn:admin1_code":"9.0",
    "gn:asciiname":"Zhangwangtun",
    "gn:country_code":"CN",
    "gn:dem":114,
    "gn:feature_class":"P",
    "gn:feature_code":"PPL",
    "gn:name":"Zhangwangtun",
    "gn:population":0,
    "gn:timezone":"Asia/Shanghai",
    "iso:country":"CN",
    "name:zho_x_preferred":[
        "\u5f20\u738b\u5c6f"
    ],
    "wof:name":"Zhangwangtun",
    "wof:placetype":"locality"
},
  "geometry": {"coordinates":[114.00082999999999,35.47245],"type":"Point"}
}