{
  "type": "Feature",
  "properties": {
    "gn:admin1_code":"16.0",
    "gn:asciiname":"Daleluo",
    "gn:country_code":"CN",
    "gn:dem":259,
    "gn:feature_class":"P",
    "gn:feature_code":"PPL",
    "gn:name":"Daleluo",
    "gn:population":0,
    "gn:timezone":"Asia/Shanghai",
    "iso:country":"CN",
    "name:zho_x_preferred":[
        "\u5927\u52d2\u7f57"
    ],
    "wof:name":"Daleluo",
    "wof:placetype":"locality"
},
  "geometry": {"coordinates":[108.98399999999999,24.869],"type":"Point"}
}