{
  "type": "Feature",
  "properties": {
    "gn:admin1_code":"3.0",
    "gn:asciiname":"Lishuliucun",
    "gn:country_code":"CN",
    "gn:dem":63,
    "gn:feature_class":"P",
    "gn:feature_code":"PPL",
    "gn:name":"Lishuliucun",
    "gn:population":0,
    "gn:timezone":"Asia/Shanghai",
    "iso:country":"CN",
    "name:und_x_variant":[
        "\u6817\u6811\u5218\u6751"
    ],
    "wof:name":"Lishuliucun",
    "wof:placetype":"locality"
},
  "geometry": {"coordinates":[115.60812,28.61663],"type":"Point"}
}