{
  "type": "Feature",
  "properties": {
    "gn:admin1_code":"32.0",
    "gn:asciiname":"Tuanlin",
    "gn:country_code":"CN",
    "gn:dem":278,
    "gn:feature_class":"P",
    "gn:feature_code":"PPL",
    "gn:name":"Tuanlin",
    "gn:population":0,
    "gn:timezone":"Asia/Shanghai",
    "iso:country":"CN",
    "name:zho_x_preferred":[
        "\u56e2\u6797"
    ],
    "wof:name":"Tuanlin",
    "wof:placetype":"locality"
},
  "geometry": {"coordinates":[106.98699999999999,31.0526],"type":"Point"}
}