{
  "type": "Feature",
  "properties": {
    "gn:admin1_code":"11.0",
    "gn:asciiname":"Dongshilang",
    "gn:country_code":"CN",
    "gn:dem":174,
    "gn:feature_class":"P",
    "gn:feature_code":"PPL",
    "gn:name":"Dongshilang",
    "gn:population":0,
    "gn:timezone":"Asia/Shanghai",
    "iso:country":"CN",
    "name:zho_x_preferred":[
        "\u4e1c\u77f3\u6d6a"
    ],
    "wof:name":"Dongshilang",
    "wof:placetype":"locality"
},
  "geometry": {"coordinates":[113.27679000000001,25.91638],"type":"Point"}
}