{
  "type": "Feature",
  "properties": {
    "gn:admin1_code":"4.0",
    "gn:asciiname":"Henghe Sanzu",
    "gn:country_code":"CN",
    "gn:dem":7,
    "gn:feature_class":"P",
    "gn:feature_code":"PPLF",
    "gn:name":"Henghe Sanzu",
    "gn:population":0,
    "gn:timezone":"Asia/Shanghai",
    "iso:country":"CN",
    "name:zho_x_preferred":[
        "\u6a2a\u6cb3\u4e09\u7ec4"
    ],
    "wof:name":"Henghe Sanzu",
    "wof:placetype":"locality"
},
  "geometry": {"coordinates":[120.84361,32.03839],"type":"Point"}
}