{
  "type": "Feature",
  "properties": {
    "gn:admin1_code":"20.0",
    "gn:asciiname":"Gechou Aobao",
    "gn:country_code":"CN",
    "gn:dem":1851,
    "gn:feature_class":"P",
    "gn:feature_code":"PPL",
    "gn:name":"Gechou Aobao",
    "gn:population":0,
    "gn:timezone":"Asia/Shanghai",
    "iso:country":"CN",
    "name:und_x_variant":[
        "\u572a\u81ed\u6556\u5305"
    ],
    "wof:name":"Gechou Aobao",
    "wof:placetype":"locality"
},
  "geometry": {"coordinates":[110.60004000000001,41.19593],"type":"Point"}
}