{
  "type": "Feature",
  "properties": {
    "gn:admin1_code":"5.0",
    "gn:asciiname":"Xujiadagou",
    "gn:country_code":"CN",
    "gn:dem":474,
    "gn:feature_class":"P",
    "gn:feature_code":"PPL",
    "gn:name":"Xujiadagou",
    "gn:population":0,
    "gn:timezone":"Asia/Shanghai",
    "iso:country":"CN",
    "name:und_x_variant":[
        "\u5f90\u5bb6\u5927\u6c9f"
    ],
    "wof:name":"Xujiadagou",
    "wof:placetype":"locality"
},
  "geometry": {"coordinates":[125.6425,41.62109],"type":"Point"}
}