{
  "type": "Feature",
  "properties": {
    "gn:admin1_code":"19.0",
    "gn:asciiname":"Halagangzi",
    "gn:country_code":"CN",
    "gn:dem":44,
    "gn:feature_class":"P",
    "gn:feature_code":"PPL",
    "gn:name":"Halagangzi",
    "gn:population":0,
    "gn:timezone":"Asia/Shanghai",
    "iso:country":"CN",
    "name:zho_x_preferred":[
        "\u54c8\u62c9\u5c97\u5b50"
    ],
    "wof:name":"Halagangzi",
    "wof:placetype":"locality"
},
  "geometry": {"coordinates":[122.76000000000001,42.0641],"type":"Point"}
}