{
  "type": "Feature",
  "properties": {
    "gn:admin1_code":"31.0",
    "gn:asciiname":"Wenjiao",
    "gn:country_code":"CN",
    "gn:dem":9,
    "gn:feature_class":"P",
    "gn:feature_code":"PPLA4",
    "gn:name":"Wenjiao",
    "gn:population":0,
    "gn:timezone":"Asia/Shanghai",
    "iso:country":"CN",
    "name:und_x_variant":[
        "Mankiao",
        "Wen-chiao-shih",
        "Wunkao",
        "Wenjiao",
        "\u6587\u6559",
        "Wenjiao Zhen",
        "\u6587\u6559\u9547"
    ],
    "wof:name":"Wenjiao",
    "wof:placetype":"locality"
},
  "geometry": {"coordinates":[110.90674,19.66992],"type":"Point"}
}