{
  "type": "Feature",
  "properties": {
    "gn:admin1_code":"24",
    "gn:asciiname":"Tailin",
    "gn:cc2":"CN",
    "gn:country_code":"CN",
    "gn:dem":1303,
    "gn:feature_class":"P",
    "gn:feature_code":"PPL",
    "gn:name":"Tailin",
    "gn:population":0,
    "gn:timezone":"Asia/Shanghai",
    "iso:country":"CN",
    "name:und_x_variant":[
        "Ta-lin-li",
        "Tailin"
    ],
    "wof:name":"Tailin",
    "wof:placetype":"locality"
},
  "geometry": {"coordinates":[111.34999999999999,36.46667],"type":"Point"}
}