{
  "type": "Feature",
  "properties": {
    "gn:admin1_code":"29.0",
    "gn:asciiname":"Axinzhai",
    "gn:country_code":"CN",
    "gn:dem":1315,
    "gn:feature_class":"P",
    "gn:feature_code":"PPL",
    "gn:name":"Axinzhai",
    "gn:population":0,
    "gn:timezone":"Asia/Shanghai",
    "iso:country":"CN",
    "name:zho_x_preferred":[
        "\u963f\u65b0\u5be8"
    ],
    "wof:name":"Axinzhai",
    "wof:placetype":"locality"
},
  "geometry": {"coordinates":[103.059,23.6264],"type":"Point"}
}