{
  "type": "Feature",
  "properties": {
    "gn:admin1_code":"29.0",
    "gn:asciiname":"Gebai",
    "gn:country_code":"CN",
    "gn:dem":1840,
    "gn:feature_class":"P",
    "gn:feature_code":"PPL",
    "gn:name":"Gebai",
    "gn:population":0,
    "gn:timezone":"Asia/Shanghai",
    "iso:country":"CN",
    "name:zho_x_preferred":[
        "\u6208\u767d"
    ],
    "wof:name":"Gebai",
    "wof:placetype":"locality"
},
  "geometry": {"coordinates":[103.102,23.5169],"type":"Point"}
}