{
  "type": "Feature",
  "properties": {
    "gn:admin1_code":"32.0",
    "gn:asciiname":"Wenjia Gujing",
    "gn:country_code":"CN",
    "gn:dem":508,
    "gn:feature_class":"P",
    "gn:feature_code":"PPL",
    "gn:name":"Wenjia Gujing",
    "gn:population":0,
    "gn:timezone":"Asia/Shanghai",
    "iso:country":"CN",
    "name:zho_x_preferred":[
        "\u6e29\u5bb6\u53e4\u4e95"
    ],
    "wof:name":"Wenjia Gujing",
    "wof:placetype":"locality"
},
  "geometry": {"coordinates":[104.18077,30.42651],"type":"Point"}
}