{
  "type": "Feature",
  "properties": {
    "gn:admin1_code":"15.0",
    "gn:asciiname":"Yunmutou",
    "gn:country_code":"CN",
    "gn:dem":2247,
    "gn:feature_class":"P",
    "gn:feature_code":"PPL",
    "gn:name":"Yunmutou",
    "gn:population":0,
    "gn:timezone":"Asia/Urumqi",
    "iso:country":"CN",
    "name:zho_x_preferred":[
        "\u4e91\u6bcd\u5934"
    ],
    "wof:name":"Yunmutou",
    "wof:placetype":"locality"
},
  "geometry": {"coordinates":[96.0762,41.4687],"type":"Point"}
}