{
  "type": "Feature",
  "properties": {
    "gn:admin1_code":"6.0",
    "gn:asciiname":"Jiaohuoga",
    "gn:country_code":"CN",
    "gn:dem":3863,
    "gn:feature_class":"P",
    "gn:feature_code":"PPL",
    "gn:name":"Jiaohuoga",
    "gn:population":0,
    "gn:timezone":"Asia/Urumqi",
    "iso:country":"CN",
    "name:zho_x_preferred":[
        "\u80f6\u706b\u5c15"
    ],
    "wof:name":"Jiaohuoga",
    "wof:placetype":"locality"
},
  "geometry": {"coordinates":[96.17964000000001,32.52741],"type":"Point"}
}