{
  "type": "Feature",
  "properties": {
    "gn:admin1_code":"15.0",
    "gn:asciiname":"Jinmashan",
    "gn:country_code":"CN",
    "gn:dem":1635,
    "gn:feature_class":"P",
    "gn:feature_code":"PPL",
    "gn:name":"Jinmashan",
    "gn:population":0,
    "gn:timezone":"Asia/Shanghai",
    "iso:country":"CN",
    "name:zho_x_preferred":[
        "\u8fdb\u9a6c\u5c71"
    ],
    "wof:name":"Jinmashan",
    "wof:placetype":"locality"
},
  "geometry": {"coordinates":[105.60599999999999,34.8521],"type":"Point"}
}