{
  "type": "Feature",
  "properties": {
    "gn:admin1_code":"14.0",
    "gn:asciiname":"Ejunda",
    "gn:country_code":"CN",
    "gn:dem":4078,
    "gn:feature_class":"P",
    "gn:feature_code":"PPL",
    "gn:name":"Ejunda",
    "gn:population":0,
    "gn:timezone":"Asia/Urumqi",
    "iso:country":"CN",
    "name:zho_x_preferred":[
        "\u989d\u519b\u8fbe"
    ],
    "wof:name":"Ejunda",
    "wof:placetype":"locality"
},
  "geometry": {"coordinates":[96.54031999999999,31.16543],"type":"Point"}
}