{
  "type": "Feature",
  "properties": {
    "gn:admin1_code":"02",
    "gn:asciiname":"Waigaoni",
    "gn:cc2":"CN",
    "gn:country_code":"CN",
    "gn:dem":5,
    "gn:feature_class":"P",
    "gn:feature_code":"PPL",
    "gn:name":"Waigaoni",
    "gn:population":0,
    "gn:timezone":"Asia/Shanghai",
    "iso:country":"CN",
    "name:und_x_variant":[
        "Wai-kao-ni",
        "Waigaoni"
    ],
    "wof:name":"Waigaoni",
    "wof:placetype":"locality"
},
  "geometry": {"coordinates":[121.75972,29.54806],"type":"Point"}
}