{
  "type": "Feature",
  "properties": {
    "gn:admin1_code":"8.0",
    "gn:asciiname":"Qianguanjiadian",
    "gn:country_code":"CN",
    "gn:dem":142,
    "gn:feature_class":"P",
    "gn:feature_code":"PPL",
    "gn:name":"Qianguanjiadian",
    "gn:population":0,
    "gn:timezone":"Asia/Shanghai",
    "iso:country":"CN",
    "name:zho_x_preferred":[
        "\u524d\u5173\u5bb6\u5e97"
    ],
    "wof:name":"Qianguanjiadian",
    "wof:placetype":"locality"
},
  "geometry": {"coordinates":[124.09266,47.10969],"type":"Point"}
}