{
  "type": "Feature",
  "properties": {
    "gn:admin1_code":"9.0",
    "gn:asciiname":"Dawangzhuang",
    "gn:country_code":"CN",
    "gn:dem":122,
    "gn:feature_class":"P",
    "gn:feature_code":"PPL",
    "gn:name":"Dawangzhuang",
    "gn:population":0,
    "gn:timezone":"Asia/Shanghai",
    "iso:country":"CN",
    "name:und_x_variant":[
        "\u5927\u738b\u5e84",
        "Dawangzhuang"
    ],
    "wof:name":"Dawangzhuang",
    "wof:placetype":"locality"
},
  "geometry": {"coordinates":[112.96213,33.74078],"type":"Point"}
}