{
  "type": "Feature",
  "properties": {
    "gn:admin1_code":"26.0",
    "gn:asciiname":"Xizigoucun",
    "gn:country_code":"CN",
    "gn:dem":1163,
    "gn:feature_class":"P",
    "gn:feature_code":"PPL",
    "gn:name":"Xizigoucun",
    "gn:population":0,
    "gn:timezone":"Asia/Shanghai",
    "iso:country":"CN",
    "name:zho_x_preferred":[
        "\u5e2d\u5b50\u6c9f\u6751"
    ],
    "wof:name":"Xizigoucun",
    "wof:placetype":"locality"
},
  "geometry": {"coordinates":[109.70067,37.26206],"type":"Point"}
}