{
  "type": "Feature",
  "properties": {
    "gn:admin1_code":"30.0",
    "gn:asciiname":"Liangjia",
    "gn:country_code":"CN",
    "gn:dem":-2,
    "gn:feature_class":"P",
    "gn:feature_code":"PPL",
    "gn:name":"Liangjia",
    "gn:population":0,
    "gn:timezone":"Asia/Shanghai",
    "iso:country":"CN",
    "name:zho_x_preferred":[
        "\u6881\u5bb6"
    ],
    "wof:name":"Liangjia",
    "wof:placetype":"locality"
},
  "geometry": {"coordinates":[113.00978000000001,22.51255],"type":"Point"}
}