{
  "type": "Feature",
  "properties": {
    "gn:admin1_code":"8.0",
    "gn:asciiname":"Ershiliuzhan",
    "gn:country_code":"CN",
    "gn:dem":277,
    "gn:feature_class":"P",
    "gn:feature_code":"PPL",
    "gn:name":"Ershiliuzhan",
    "gn:population":0,
    "gn:timezone":"Asia/Shanghai",
    "iso:country":"CN",
    "name:zho_x_preferred":[
        "\u4e8c\u5341\u516d\u7ad9"
    ],
    "wof:name":"Ershiliuzhan",
    "wof:placetype":"locality"
},
  "geometry": {"coordinates":[123.58823999999998,53.38868000000001],"type":"Point"}
}