{
  "type": "Feature",
  "properties": {
    "gn:admin1_code":"11.0",
    "gn:asciiname":"Dingshan",
    "gn:country_code":"CN",
    "gn:dem":52,
    "gn:feature_class":"P",
    "gn:feature_code":"PPL",
    "gn:name":"Dingshan",
    "gn:population":0,
    "gn:timezone":"Asia/Shanghai",
    "iso:country":"CN",
    "name:zho_x_preferred":[
        "\u9f0e\u5c71"
    ],
    "wof:name":"Dingshan",
    "wof:placetype":"locality"
},
  "geometry": {"coordinates":[112.57855000000001,29.58443],"type":"Point"}
}