{
  "type": "Feature",
  "properties": {
    "gn:admin1_code":"32.0",
    "gn:asciiname":"Agaxi",
    "gn:country_code":"CN",
    "gn:dem":3631,
    "gn:feature_class":"P",
    "gn:feature_code":"PPL",
    "gn:name":"Agaxi",
    "gn:population":0,
    "gn:timezone":"Asia/Shanghai",
    "iso:country":"CN",
    "name:zho_x_preferred":[
        "\u963f\u560e\u897f"
    ],
    "wof:name":"Agaxi",
    "wof:placetype":"locality"
},
  "geometry": {"coordinates":[101.607,30.0904],"type":"Point"}
}