{
  "type": "Feature",
  "properties": {
    "gn:admin1_code":"3.0",
    "gn:asciiname":"Laopengxia",
    "gn:country_code":"CN",
    "gn:dem":27,
    "gn:feature_class":"P",
    "gn:feature_code":"PPL",
    "gn:name":"Laopengxia",
    "gn:population":0,
    "gn:timezone":"Asia/Shanghai",
    "iso:country":"CN",
    "name:und_x_variant":[
        "\u8001\u68da\u4e0b"
    ],
    "wof:name":"Laopengxia",
    "wof:placetype":"locality"
},
  "geometry": {"coordinates":[116.35187000000001,28.6698],"type":"Point"}
}