{
  "type": "Feature",
  "properties": {
    "gn:admin1_code":"3.0",
    "gn:asciiname":"Shixigang",
    "gn:country_code":"CN",
    "gn:dem":115,
    "gn:feature_class":"P",
    "gn:feature_code":"PPL",
    "gn:name":"Shixigang",
    "gn:population":0,
    "gn:timezone":"Asia/Shanghai",
    "iso:country":"CN",
    "name:und_x_variant":[
        "\u77f3\u6eaa\u6e2f"
    ],
    "wof:name":"Shixigang",
    "wof:placetype":"locality"
},
  "geometry": {"coordinates":[114.98057,26.21874],"type":"Point"}
}