{
  "type": "Feature",
  "properties": {
    "gn:admin1_code":"4.0",
    "gn:asciiname":"Yunan",
    "gn:country_code":"CN",
    "gn:dem":5,
    "gn:feature_class":"P",
    "gn:feature_code":"PPL",
    "gn:name":"Yunan",
    "gn:population":0,
    "gn:timezone":"Asia/Shanghai",
    "iso:country":"CN",
    "name:ara_x_preferred":[
        "\u064a\u0648\u0646\u0627\u0646"
    ],
    "name:ceb_x_preferred":[
        "Yunan"
    ],
    "name:msa_x_preferred":[
        "Yunani"
    ],
    "name:tur_x_preferred":[
        "Yunan"
    ],
    "name:zho_x_preferred":[
        "\u4f59\u5357"
    ],
    "wof:name":"Yunan",
    "wof:placetype":"locality"
},
  "geometry": {"coordinates":[121.3571,32.0208],"type":"Point"}
}