{
  "type": "Feature",
  "properties": {
    "gn:admin1_code":"12.0",
    "gn:asciiname":"Haokou Zhen",
    "gn:country_code":"CN",
    "gn:dem":33,
    "gn:feature_class":"P",
    "gn:feature_code":"PPL",
    "gn:name":"Haokou Zhen",
    "gn:population":0,
    "gn:timezone":"Asia/Shanghai",
    "iso:country":"CN",
    "name:zho_x_preferred":[
        "\u6d69\u53e3\u9547"
    ],
    "wof:name":"Haokou Zhen",
    "wof:placetype":"locality"
},
  "geometry": {"coordinates":[112.63993000000001,30.38128],"type":"Point"}
}