{
  "type": "Feature",
  "properties": {
    "gn:admin1_code":"2.0",
    "gn:asciiname":"Xiatianfan",
    "gn:country_code":"CN",
    "gn:dem":123,
    "gn:feature_class":"P",
    "gn:feature_code":"PPL",
    "gn:name":"Xiatianfan",
    "gn:population":0,
    "gn:timezone":"Asia/Shanghai",
    "iso:country":"CN",
    "name:zho_x_preferred":[
        "\u4e0b\u7530\u7548"
    ],
    "wof:name":"Xiatianfan",
    "wof:placetype":"locality"
},
  "geometry": {"coordinates":[120.3139,29.42451],"type":"Point"}
}