{
  "type": "Feature",
  "properties": {
    "gn:admin1_code":"11.0",
    "gn:asciiname":"Fei'eshuxia",
    "gn:country_code":"CN",
    "gn:dem":143,
    "gn:feature_class":"P",
    "gn:feature_code":"PPL",
    "gn:name":"Fei\u2019eshuxia",
    "gn:population":0,
    "gn:timezone":"Asia/Shanghai",
    "iso:country":"CN",
    "name:und_x_variant":[
        "Fei\u2019eshuxia"
    ],
    "name:zho_x_preferred":[
        "\u98de\u86fe\u6811\u4e0b"
    ],
    "wof:name":"Fei'eshuxia",
    "wof:placetype":"locality"
},
  "geometry": {"coordinates":[113.29013,27.25121],"type":"Point"}
}