{
  "type": "Feature",
  "properties": {
    "gn:admin1_code":"11.0",
    "gn:asciiname":"Jiwoling",
    "gn:country_code":"CN",
    "gn:dem":30,
    "gn:feature_class":"P",
    "gn:feature_code":"PPL",
    "gn:name":"Jiwoling",
    "gn:population":0,
    "gn:timezone":"Asia/Shanghai",
    "iso:country":"CN",
    "name:zho_x_preferred":[
        "\u9e21\u7a9d\u5cad"
    ],
    "wof:name":"Jiwoling",
    "wof:placetype":"locality"
},
  "geometry": {"coordinates":[112.29164,29.16268],"type":"Point"}
}