{
  "type": "Feature",
  "properties": {
    "gn:admin1_code":"18",
    "gn:asciiname":"Caoziba",
    "gn:country_code":"CN",
    "gn:dem":728,
    "gn:feature_class":"P",
    "gn:feature_code":"PPL",
    "gn:name":"Caoziba",
    "gn:population":0,
    "gn:timezone":"Asia/Shanghai",
    "iso:country":"CN",
    "name:zho_x_preferred":[
        "\u8349\u5b50\u575d"
    ],
    "wof:name":"Caoziba",
    "wof:placetype":"locality"
},
  "geometry": {"coordinates":[107.31399999999999,28.2371],"type":"Point"}
}