{
  "type": "Feature",
  "properties": {
    "gn:admin1_code":"15.0",
    "gn:asciiname":"Yanghua",
    "gn:country_code":"CN",
    "gn:dem":2504,
    "gn:feature_class":"P",
    "gn:feature_code":"PPL",
    "gn:name":"Yanghua",
    "gn:population":0,
    "gn:timezone":"Asia/Shanghai",
    "iso:country":"CN",
    "name:und_x_variant":[
        "\u7f8a\u5316",
        "Yanghuacun",
        "\u7f8a\u5316\u6751"
    ],
    "wof:name":"Yanghua",
    "wof:placetype":"locality"
},
  "geometry": {"coordinates":[103.64769,34.56352],"type":"Point"}
}