{
  "type": "Feature",
  "properties": {
    "gn:admin1_code":"29.0",
    "gn:asciiname":"Manka",
    "gn:country_code":"CN",
    "gn:dem":1155,
    "gn:feature_class":"P",
    "gn:feature_code":"PPL",
    "gn:name":"Manka",
    "gn:population":0,
    "gn:timezone":"Asia/Shanghai",
    "iso:country":"CN",
    "name:zho_x_preferred":[
        "\u66fc\u5361"
    ],
    "wof:name":"Manka",
    "wof:placetype":"locality"
},
  "geometry": {"coordinates":[98.9076,23.7928],"type":"Point"}
}