{
  "type": "Feature",
  "properties": {
    "gn:admin1_code":"12.0",
    "gn:asciiname":"Xinyang",
    "gn:country_code":"CN",
    "gn:dem":909,
    "gn:feature_class":"P",
    "gn:feature_code":"PPL",
    "gn:name":"Xinyang",
    "gn:population":0,
    "gn:timezone":"Asia/Shanghai",
    "iso:country":"CN",
    "name:zho_x_preferred":[
        "\u65b0\u9633"
    ],
    "wof:name":"Xinyang",
    "wof:placetype":"locality"
},
  "geometry": {"coordinates":[108.75971,29.94692],"type":"Point"}
}