{
  "type": "Feature",
  "properties": {
    "gn:admin1_code":"12.0",
    "gn:asciiname":"Xinyang",
    "gn:country_code":"CN",
    "gn:dem":909,
    "gn:feature_class":"P",
    "gn:feature_code":"PPL",
    "gn:name":"Xinyang",
    "gn:population":0,
    "gn:timezone":"Asia/Shanghai",
    "iso:country":"CN",
    "name:afr_x_preferred":[
        "Xinyang"
    ],
    "name:ara_x_preferred":[
        "\u0634\u064a\u0646\u064a\u0627\u0646\u062c"
    ],
    "name:bul_x_preferred":[
        "\u0421\u0438\u043d\u044f\u043d"
    ],
    "name:cat_x_preferred":[
        "Xinyang"
    ],
    "name:cdo_x_preferred":[
        "S\u00e9ng-i\u00f2ng"
    ],
    "name:ceb_x_preferred":[
        "Xinyang"
    ],
    "name:ces_x_preferred":[
        "Sin-jang"
    ],
    "name:dan_x_preferred":[
        "Xinyang"
    ],
    "name:deu_x_preferred":[
        "Xinyang"
    ],
    "name:epo_x_preferred":[
        "\u015cjinjango"
    ],
    "name:eus_x_preferred":[
        "Xinyang"
    ],
    "name:fas_x_preferred":[
        "\u0634\u06cc\u0646\u200c\u06cc\u0627\u0646\u06af"
    ],
    "name:fin_x_preferred":[
        "Xinyang"
    ],
    "name:fra_x_preferred":[
        "Xinyang"
    ],
    "name:ind_x_preferred":[
        "Xinyang"
    ],
    "name:ita_x_preferred":[
        "Xinyang"
    ],
    "name:jpn_x_preferred":[
        "\u4fe1\u967d\u5e02"
    ],
    "name:kor_x_preferred":[
        "\uc2e0\uc591\uc2dc"
    ],
    "name:lit_x_preferred":[
        "Sinjangas"
    ],
    "name:mlg_x_preferred":[
        "Xinyang"
    ],
    "name:nld_x_preferred":[
        "Xinyang"
    ],
    "name:nno_x_preferred":[
        "Xinyang"
    ],
    "name:nor_x_preferred":[
        "Xinyang"
    ],
    "name:pam_x_preferred":[
        "Xinyang"
    ],
    "name:pol_x_preferred":[
        "Xinyang"
    ],
    "name:por_x_preferred":[
        "Xinyang"
    ],
    "name:rus_x_preferred":[
        "\u0421\u0438\u043d\u044c\u044f\u043d"
    ],
    "name:spa_x_preferred":[
        "Xinyang"
    ],
    "name:srp_x_preferred":[
        "\u0421\u0438\u043d\u0458\u0430\u043d\u0433"
    ],
    "name:swe_x_preferred":[
        "Xinyang"
    ],
    "name:tur_x_preferred":[
        "Xinyang"
    ],
    "name:uig_x_preferred":[
        "Shinyang shehiri"
    ],
    "name:urd_x_preferred":[
        "\u0634\u0646\u06cc\u0627\u0646\u06af"
    ],
    "name:vie_x_preferred":[
        "T\u00edn D\u01b0\u01a1ng"
    ],
    "name:war_x_preferred":[
        "Xinyang"
    ],
    "name:wuu_x_preferred":[
        "\u4fe1\u9633\u5e02"
    ],
    "name:zho_x_preferred":[
        "\u65b0\u9633"
    ],
    "name:zho_x_variant":[
        "\u4fe1\u9633\u5e02"
    ],
    "wof:name":"Xinyang",
    "wof:placetype":"locality"
},
  "geometry": {"coordinates":[108.75971,29.94692],"type":"Point"}
}