{
  "type": "Feature",
  "properties": {
    "gn:admin1_code":"32.0",
    "gn:asciiname":"Luojiaoxing",
    "gn:country_code":"CN",
    "gn:dem":294,
    "gn:feature_class":"P",
    "gn:feature_code":"PPL",
    "gn:name":"Luojiaoxing",
    "gn:population":0,
    "gn:timezone":"Asia/Shanghai",
    "iso:country":"CN",
    "name:zho_x_preferred":[
        "\u843d\u89d2\u661f"
    ],
    "wof:name":"Luojiaoxing",
    "wof:placetype":"locality"
},
  "geometry": {"coordinates":[104.69331,28.71297],"type":"Point"}
}