{
  "type": "Feature",
  "properties": {
    "gn:admin1_code":"32.0",
    "gn:asciiname":"Ganbu",
    "gn:country_code":"CN",
    "gn:dem":3897,
    "gn:feature_class":"P",
    "gn:feature_code":"PPL",
    "gn:name":"Ganbu",
    "gn:population":0,
    "gn:timezone":"Asia/Shanghai",
    "iso:country":"CN",
    "name:zho_x_preferred":[
        "\u5e72\u8865"
    ],
    "wof:name":"Ganbu",
    "wof:placetype":"locality"
},
  "geometry": {"coordinates":[98.9414,32.5572],"type":"Point"}
}