{
  "type": "Feature",
  "properties": {
    "gn:admin1_code":"03",
    "gn:asciiname":"Guangmingtang",
    "gn:country_code":"CN",
    "gn:dem":52,
    "gn:feature_class":"P",
    "gn:feature_code":"PPL",
    "gn:name":"Guangmingtang",
    "gn:population":0,
    "gn:timezone":"Asia/Shanghai",
    "iso:country":"CN",
    "name:und_x_variant":[
        "Fugang",
        "Kuang-mao-t\u2019an",
        "Guangmingtang",
        "\u5e7f\u660e\u5802"
    ],
    "wof:name":"Guangmingtang",
    "wof:placetype":"locality"
},
  "geometry": {"coordinates":[117.25409999999999,29.5056],"type":"Point"}
}