{
  "type": "Feature",
  "properties": {
    "gn:admin1_code":"19.0",
    "gn:asciiname":"Xiaohemugou",
    "gn:country_code":"CN",
    "gn:dem":535,
    "gn:feature_class":"P",
    "gn:feature_code":"PPL",
    "gn:name":"Xiaohemugou",
    "gn:population":0,
    "gn:timezone":"Asia/Shanghai",
    "iso:country":"CN",
    "name:zho_x_preferred":[
        "\u5c0f\u548c\u7766\u6c9f"
    ],
    "wof:name":"Xiaohemugou",
    "wof:placetype":"locality"
},
  "geometry": {"coordinates":[119.53951000000001,41.35346],"type":"Point"}
}