{
  "type": "Feature",
  "properties": {
    "gn:admin1_code":"13",
    "gn:asciiname":"Gongqingtuan Nongchang",
    "gn:country_code":"CN",
    "gn:dem":460,
    "gn:feature_class":"P",
    "gn:feature_code":"PPLF",
    "gn:name":"Gongqingtuan Nongchang",
    "gn:population":0,
    "gn:timezone":"Asia/Urumqi",
    "iso:country":"CN",
    "name:zho_x_preferred":[
        "\u5171\u9752\u56e2\u519c\u573a"
    ],
    "wof:name":"Gongqingtuan Nongchang",
    "wof:placetype":"locality"
},
  "geometry": {"coordinates":[87.43188000000001,44.29205],"type":"Point"}
}