{
  "type": "Feature",
  "properties": {
    "gn:admin1_code":"12.0",
    "gn:asciiname":"Huifengting",
    "gn:country_code":"CN",
    "gn:dem":24,
    "gn:feature_class":"P",
    "gn:feature_code":"PPL",
    "gn:name":"Huifengting",
    "gn:population":0,
    "gn:timezone":"Asia/Shanghai",
    "iso:country":"CN",
    "name:zho_x_preferred":[
        "\u56de\u98ce\u4ead"
    ],
    "wof:name":"Huifengting",
    "wof:placetype":"locality"
},
  "geometry": {"coordinates":[113.87866,30.14132],"type":"Point"}
}