{
  "type": "Feature",
  "properties": {
    "gn:admin1_code":"2.0",
    "gn:asciiname":"Zihongshan",
    "gn:country_code":"CN",
    "gn:dem":103,
    "gn:feature_class":"P",
    "gn:feature_code":"PPL",
    "gn:name":"Zihongshan",
    "gn:population":0,
    "gn:timezone":"Asia/Shanghai",
    "iso:country":"CN",
    "name:zho_x_preferred":[
        "\u7d2b\u6d2a\u5c71"
    ],
    "wof:name":"Zihongshan",
    "wof:placetype":"locality"
},
  "geometry": {"coordinates":[120.53272,29.8889],"type":"Point"}
}