{
  "type": "Feature",
  "properties": {
    "gn:admin1_code":"22.0",
    "gn:asciiname":"Beizhangzhuangcun",
    "gn:country_code":"CN",
    "gn:dem":599,
    "gn:feature_class":"P",
    "gn:feature_code":"PPL",
    "gn:name":"Beizhangzhuangcun",
    "gn:population":0,
    "gn:timezone":"Asia/Shanghai",
    "iso:country":"CN",
    "name:zho_x_preferred":[
        "\u5317\u5f20\u5e84\u6751"
    ],
    "wof:name":"Beizhangzhuangcun",
    "wof:placetype":"locality"
},
  "geometry": {"coordinates":[116.06994,40.58705],"type":"Point"}
}