{
  "type": "Feature",
  "properties": {
    "gn:admin1_code":"20.0",
    "gn:asciiname":"Hujia Jigede",
    "gn:country_code":"CN",
    "gn:dem":1007,
    "gn:feature_class":"P",
    "gn:feature_code":"PPL",
    "gn:name":"Hujia Jigede",
    "gn:population":0,
    "gn:timezone":"Asia/Shanghai",
    "iso:country":"CN",
    "name:zho_x_preferred":[
        "\u80e1\u5bb6\u79ef\u683c\u5f97"
    ],
    "wof:name":"Hujia Jigede",
    "wof:placetype":"locality"
},
  "geometry": {"coordinates":[100.46738000000001,41.5041],"type":"Point"}
}