{
  "type": "Feature",
  "properties": {
    "gn:admin1_code":"32.0",
    "gn:asciiname":"Chadian",
    "gn:country_code":"CN",
    "gn:dem":643,
    "gn:feature_class":"P",
    "gn:feature_code":"PPL",
    "gn:name":"Chadian",
    "gn:population":0,
    "gn:timezone":"Asia/Shanghai",
    "iso:country":"CN",
    "name:ceb_x_preferred":[
        "Chadian"
    ],
    "name:swe_x_preferred":[
        "Chadian"
    ],
    "name:zho_x_preferred":[
        "\u8336\u5e97"
    ],
    "wof:name":"Chadian",
    "wof:placetype":"locality"
},
  "geometry": {"coordinates":[107.42889,31.32738],"type":"Point"}
}