{
  "type": "Feature",
  "properties": {
    "gn:admin1_code":"14.0",
    "gn:asciiname":"Pengcai",
    "gn:country_code":"CN",
    "gn:dem":2971,
    "gn:feature_class":"P",
    "gn:feature_code":"PPL",
    "gn:name":"Pengcai",
    "gn:population":0,
    "gn:timezone":"Asia/Urumqi",
    "iso:country":"CN",
    "name:zho_x_preferred":[
        "\u670b\u6750"
    ],
    "wof:name":"Pengcai",
    "wof:placetype":"locality"
},
  "geometry": {"coordinates":[94.73895,29.44849],"type":"Point"}
}