{
  "type": "Feature",
  "properties": {
    "gn:admin1_code":"5.0",
    "gn:asciiname":"Jinfutun",
    "gn:country_code":"CN",
    "gn:dem":209,
    "gn:feature_class":"P",
    "gn:feature_code":"PPL",
    "gn:name":"Jinfutun",
    "gn:population":0,
    "gn:timezone":"Asia/Shanghai",
    "iso:country":"CN",
    "name:zho_x_preferred":[
        "\u91d1\u798f\u5c6f"
    ],
    "wof:name":"Jinfutun",
    "wof:placetype":"locality"
},
  "geometry": {"coordinates":[125.05159,44.41444],"type":"Point"}
}