{
  "type": "Feature",
  "properties": {
    "gn:admin1_code":"32.0",
    "gn:asciiname":"Lantianchong",
    "gn:country_code":"CN",
    "gn:dem":388,
    "gn:feature_class":"P",
    "gn:feature_code":"PPL",
    "gn:name":"Lantianchong",
    "gn:population":0,
    "gn:timezone":"Asia/Shanghai",
    "iso:country":"CN",
    "name:zho_x_preferred":[
        "\u6ee5\u7530\u51b2"
    ],
    "wof:name":"Lantianchong",
    "wof:placetype":"locality"
},
  "geometry": {"coordinates":[103.79331999999999,29.69482],"type":"Point"}
}