{
  "type": "Feature",
  "properties": {
    "gn:admin1_code":"24.0",
    "gn:asciiname":"Huojiaping",
    "gn:country_code":"CN",
    "gn:dem":974,
    "gn:feature_class":"P",
    "gn:feature_code":"PPL",
    "gn:name":"Huojiaping",
    "gn:population":0,
    "gn:timezone":"Asia/Shanghai",
    "iso:country":"CN",
    "name:zho_x_preferred":[
        "\u970d\u5bb6\u576a"
    ],
    "wof:name":"Huojiaping",
    "wof:placetype":"locality"
},
  "geometry": {"coordinates":[111.43684,36.66174],"type":"Point"}
}