{
  "type": "Feature",
  "properties": {
    "gn:admin1_code":"1.0",
    "gn:asciiname":"Meichengcun",
    "gn:country_code":"CN",
    "gn:dem":24,
    "gn:feature_class":"P",
    "gn:feature_code":"PPL",
    "gn:name":"Meichengcun",
    "gn:population":0,
    "gn:timezone":"Asia/Shanghai",
    "iso:country":"CN",
    "name:zho_x_preferred":[
        "\u6885\u57ce\u6751"
    ],
    "wof:name":"Meichengcun",
    "wof:placetype":"locality"
},
  "geometry": {"coordinates":[116.83165,30.81595],"type":"Point"}
}