{
  "type": "Feature",
  "properties": {
    "gn:admin1_code":"12.0",
    "gn:asciiname":"Tupu",
    "gn:country_code":"CN",
    "gn:dem":73,
    "gn:feature_class":"P",
    "gn:feature_code":"PPL",
    "gn:name":"Tupu",
    "gn:population":0,
    "gn:timezone":"Asia/Shanghai",
    "iso:country":"CN",
    "name:fra_x_preferred":[
        "Toupou"
    ],
    "name:heb_x_preferred":[
        "\u05d8\u05d5\u05e4\u05d5"
    ],
    "name:hun_x_preferred":[
        "Tupu"
    ],
    "name:ita_x_preferred":[
        "Tupu"
    ],
    "name:nld_x_preferred":[
        "Tupu"
    ],
    "name:zho_x_preferred":[
        "\u51c3\u94fa"
    ],
    "wof:name":"Tupu",
    "wof:placetype":"locality"
},
  "geometry": {"coordinates":[115.61409999999999,30.41231],"type":"Point"}
}