{
  "type": "Feature",
  "properties": {
    "gn:admin1_code":"14.0",
    "gn:asciiname":"Wurecun",
    "gn:country_code":"CN",
    "gn:dem":3667,
    "gn:feature_class":"P",
    "gn:feature_code":"PPL",
    "gn:name":"Wurecun",
    "gn:population":0,
    "gn:timezone":"Asia/Urumqi",
    "iso:country":"CN",
    "name:zho_x_preferred":[
        "\u4e4c\u70ed\u6751"
    ],
    "wof:name":"Wurecun",
    "wof:placetype":"locality"
},
  "geometry": {"coordinates":[96.29074,31.8632],"type":"Point"}
}