{
  "type": "Feature",
  "properties": {
    "gn:admin1_code":"13.0",
    "gn:asciiname":"Sarbulak",
    "gn:cc2":"CN",
    "gn:country_code":"CN",
    "gn:dem":868,
    "gn:feature_class":"P",
    "gn:feature_code":"PPL",
    "gn:name":"Sarbulak",
    "gn:population":0,
    "gn:timezone":"Asia/Shanghai",
    "iso:country":"CN",
    "name:uig_x_preferred":[
        "Sarbulak\u0329"
    ],
    "name:uig_x_variant":[
        "Sarbulaq",
        "\u0633\u0627\u0631\u0628\u06c7\u0644\u0627\u0642",
        "\u0421\u0430\u0440\u0431\u0443\u043b\u0430\u049b"
    ],
    "name:und_x_variant":[
        "Sarbulak Xiang",
        "Sarbulak"
    ],
    "wof:name":"Sarbulak",
    "wof:placetype":"locality"
},
  "geometry": {"coordinates":[81.03639,44.21194000000001],"type":"Point"}
}