{
  "type": "Feature",
  "properties": {
    "gn:admin1_code":"32.0",
    "gn:asciiname":"Dapianpo",
    "gn:country_code":"CN",
    "gn:dem":1339,
    "gn:feature_class":"P",
    "gn:feature_code":"PPL",
    "gn:name":"Dapianpo",
    "gn:population":0,
    "gn:timezone":"Asia/Shanghai",
    "iso:country":"CN",
    "name:zho_x_preferred":[
        "\u5927\u7247\u5761"
    ],
    "wof:name":"Dapianpo",
    "wof:placetype":"locality"
},
  "geometry": {"coordinates":[102.31072,27.33615],"type":"Point"}
}