{
  "type": "Feature",
  "properties": {
    "gn:admin1_code":"20.0",
    "gn:asciiname":"Maoduqing",
    "gn:country_code":"CN",
    "gn:dem":1421,
    "gn:feature_class":"P",
    "gn:feature_code":"PPL",
    "gn:name":"Maoduqing",
    "gn:population":0,
    "gn:timezone":"Asia/Shanghai",
    "iso:country":"CN",
    "name:und_x_variant":[
        "\u536f\u72ec\u5e86"
    ],
    "wof:name":"Maoduqing",
    "wof:placetype":"locality"
},
  "geometry": {"coordinates":[111.70144000000001,41.01591],"type":"Point"}
}