{
  "type": "Feature",
  "properties": {
    "gn:admin1_code":"4.0",
    "gn:asciiname":"Gangxicun",
    "gn:country_code":"CN",
    "gn:dem":6,
    "gn:feature_class":"P",
    "gn:feature_code":"PPL",
    "gn:name":"Gangxicun",
    "gn:population":0,
    "gn:timezone":"Asia/Shanghai",
    "iso:country":"CN",
    "name:zho_x_preferred":[
        "\u6e2f\u897f\u6751"
    ],
    "wof:name":"Gangxicun",
    "wof:placetype":"locality"
},
  "geometry": {"coordinates":[119.39471,33.96149],"type":"Point"}
}