{
  "type": "Feature",
  "properties": {
    "gn:admin1_code":"26",
    "gn:asciiname":"Haizemiao",
    "gn:cc2":"CN",
    "gn:country_code":"CN",
    "gn:dem":1052,
    "gn:feature_class":"P",
    "gn:feature_code":"PPL",
    "gn:name":"Haizemiao",
    "gn:population":0,
    "gn:timezone":"Asia/Shanghai",
    "iso:country":"CN",
    "name:und_x_variant":[
        "Hai-tse-miao",
        "Haizemiao"
    ],
    "wof:name":"Haizemiao",
    "wof:placetype":"locality"
},
  "geometry": {"coordinates":[111.07250000000001,39.105],"type":"Point"}
}