{
  "type": "Feature",
  "properties": {
    "gn:admin1_code":"25.0",
    "gn:asciiname":"Xizhongjing",
    "gn:country_code":"CN",
    "gn:dem":31,
    "gn:feature_class":"P",
    "gn:feature_code":"PPL",
    "gn:name":"Xizhongjing",
    "gn:population":0,
    "gn:timezone":"Asia/Shanghai",
    "iso:country":"CN",
    "name:zho_x_preferred":[
        "\u897f\u4e2d\u8346"
    ],
    "wof:name":"Xizhongjing",
    "wof:placetype":"locality"
},
  "geometry": {"coordinates":[120.6375,36.71621],"type":"Point"}
}