{
  "type": "Feature",
  "properties": {
    "gn:admin1_code":"3.0",
    "gn:asciiname":"Xianankeng",
    "gn:country_code":"CN",
    "gn:dem":207,
    "gn:feature_class":"P",
    "gn:feature_code":"PPL",
    "gn:name":"Xianankeng",
    "gn:population":0,
    "gn:timezone":"Asia/Shanghai",
    "iso:country":"CN",
    "name:und_x_variant":[
        "\u4e0b\u5357\u5751"
    ],
    "wof:name":"Xianankeng",
    "wof:placetype":"locality"
},
  "geometry": {"coordinates":[115.77146,25.44733],"type":"Point"}
}