{
  "type": "Feature",
  "properties": {
    "gn:admin1_code":"5.0",
    "gn:asciiname":"Dongyuancun",
    "gn:country_code":"CN",
    "gn:dem":229,
    "gn:feature_class":"P",
    "gn:feature_code":"PPL",
    "gn:name":"Dongyuancun",
    "gn:population":0,
    "gn:timezone":"Asia/Shanghai",
    "iso:country":"CN",
    "name:zho_x_preferred":[
        "\u4e1c\u56ed\u6751"
    ],
    "wof:name":"Dongyuancun",
    "wof:placetype":"locality"
},
  "geometry": {"coordinates":[124.96026000000001,43.55821],"type":"Point"}
}