{
  "type": "Feature",
  "properties": {
    "gn:admin1_code":"29.0",
    "gn:asciiname":"Mengnan",
    "gn:country_code":"CN",
    "gn:dem":1822,
    "gn:feature_class":"P",
    "gn:feature_code":"PPL",
    "gn:name":"Mengnan",
    "gn:population":0,
    "gn:timezone":"Asia/Shanghai",
    "iso:country":"CN",
    "name:zho_x_preferred":[
        "\u52d0\u56e1"
    ],
    "wof:name":"Mengnan",
    "wof:placetype":"locality"
},
  "geometry": {"coordinates":[100.515,21.6575],"type":"Point"}
}