{
  "type": "Feature",
  "properties": {
    "gn:admin1_code":"9.0",
    "gn:asciiname":"Erlangmiao",
    "gn:country_code":"CN",
    "gn:dem":99,
    "gn:feature_class":"P",
    "gn:feature_code":"PPL",
    "gn:name":"Erlangmiao",
    "gn:population":0,
    "gn:timezone":"Asia/Shanghai",
    "iso:country":"CN",
    "name:zho_x_preferred":[
        "\u4e8c\u90ce\u5e99"
    ],
    "wof:name":"Erlangmiao",
    "wof:placetype":"locality"
},
  "geometry": {"coordinates":[113.78503000000001,34.71212],"type":"Point"}
}