{
  "type": "Feature",
  "properties": {
    "gn:admin1_code":"11",
    "gn:asciiname":"Bashigong",
    "gn:country_code":"CN",
    "gn:dem":256,
    "gn:feature_class":"P",
    "gn:feature_code":"PPL",
    "gn:name":"Bashigong",
    "gn:population":0,
    "gn:timezone":"Asia/Shanghai",
    "iso:country":"CN",
    "name:zho_x_preferred":[
        "\u516b\u5341\u5de5"
    ],
    "wof:name":"Bashigong",
    "wof:placetype":"locality"
},
  "geometry": {"coordinates":[111.04615,25.05449],"type":"Point"}
}