{
  "type": "Feature",
  "properties": {
    "gn:admin1_code":"8.0",
    "gn:asciiname":"Lipingcun",
    "gn:country_code":"CN",
    "gn:dem":202,
    "gn:feature_class":"P",
    "gn:feature_code":"PPL",
    "gn:name":"Lipingcun",
    "gn:population":0,
    "gn:timezone":"Asia/Shanghai",
    "iso:country":"CN",
    "name:zho_x_preferred":[
        "\u7acb\u5e73\u6751"
    ],
    "wof:name":"Lipingcun",
    "wof:placetype":"locality"
},
  "geometry": {"coordinates":[127.31892000000001,46.53635],"type":"Point"}
}