{
  "type": "Feature",
  "properties": {
    "gn:admin1_code":"4.0",
    "gn:asciiname":"Qinggaocun",
    "gn:country_code":"CN",
    "gn:dem":19,
    "gn:feature_class":"P",
    "gn:feature_code":"PPL",
    "gn:name":"Qinggaocun",
    "gn:population":0,
    "gn:timezone":"Asia/Shanghai",
    "iso:country":"CN",
    "name:zho_x_preferred":[
        "\u6e05\u9ad8\u6751"
    ],
    "wof:name":"Qinggaocun",
    "wof:placetype":"locality"
},
  "geometry": {"coordinates":[118.47790999999999,33.91089],"type":"Point"}
}