{
  "type": "Feature",
  "properties": {
    "gn:admin1_code":"4.0",
    "gn:asciiname":"Yuye",
    "gn:country_code":"CN",
    "gn:dem":5,
    "gn:feature_class":"P",
    "gn:feature_code":"PPLF",
    "gn:name":"Yuye",
    "gn:population":0,
    "gn:timezone":"Asia/Shanghai",
    "iso:country":"CN",
    "name:zho_x_preferred":[
        "Yuye"
    ],
    "name:zho_x_variant":[
        "\u6e14\u4e1a"
    ],
    "wof:name":"Yuye",
    "wof:placetype":"locality"
},
  "geometry": {"coordinates":[121.81657,31.91624],"type":"Point"}
}