{
  "type": "Feature",
  "properties": {
    "gn:admin1_code":"8.0",
    "gn:asciiname":"Gaoshengtun",
    "gn:country_code":"CN",
    "gn:dem":91,
    "gn:feature_class":"P",
    "gn:feature_code":"PPL",
    "gn:name":"Gaoshengtun",
    "gn:population":0,
    "gn:timezone":"Asia/Shanghai",
    "iso:country":"CN",
    "name:zho_x_preferred":[
        "\u9ad8\u5347\u5c6f"
    ],
    "wof:name":"Gaoshengtun",
    "wof:placetype":"locality"
},
  "geometry": {"coordinates":[130.14875000000001,48.91079000000001],"type":"Point"}
}