{
  "type": "Feature",
  "properties": {
    "gn:admin1_code":"14.0",
    "gn:asciiname":"Shuigang",
    "gn:country_code":"CN",
    "gn:dem":3939,
    "gn:feature_class":"P",
    "gn:feature_code":"PPL",
    "gn:name":"Shuigang",
    "gn:population":0,
    "gn:timezone":"Asia/Urumqi",
    "iso:country":"CN",
    "name:zho_x_preferred":[
        "\u6c34\u5c97"
    ],
    "wof:name":"Shuigang",
    "wof:placetype":"locality"
},
  "geometry": {"coordinates":[91.367,29.96441],"type":"Point"}
}