{
  "type": "Feature",
  "properties": {
    "gn:admin1_code":"21.0",
    "gn:asciiname":"Lujia Xinzhuang",
    "gn:country_code":"CN",
    "gn:dem":1753,
    "gn:feature_class":"P",
    "gn:feature_code":"PPL",
    "gn:name":"L\u00fcjia Xinzhuang",
    "gn:population":0,
    "gn:timezone":"Asia/Shanghai",
    "iso:country":"CN",
    "name:und_x_variant":[
        "L\u00fcjia Xinzhuang"
    ],
    "name:zho_x_preferred":[
        "\u5415\u5bb6\u65b0\u5e84"
    ],
    "wof:name":"Lujia Xinzhuang",
    "wof:placetype":"locality"
},
  "geometry": {"coordinates":[105.04000000000001,37.1002],"type":"Point"}
}