{
  "type": "Feature",
  "properties": {
    "gn:admin1_code":"19.0",
    "gn:asciiname":"Weizigoucun",
    "gn:country_code":"CN",
    "gn:dem":122,
    "gn:feature_class":"P",
    "gn:feature_code":"PPL",
    "gn:name":"Weizigoucun",
    "gn:population":0,
    "gn:timezone":"Asia/Shanghai",
    "iso:country":"CN",
    "name:zho_x_preferred":[
        "\u82c7\u5b50\u6c9f\u6751"
    ],
    "wof:name":"Weizigoucun",
    "wof:placetype":"locality"
},
  "geometry": {"coordinates":[120.102,40.4349],"type":"Point"}
}