{
  "type": "Feature",
  "properties": {
    "gn:admin1_code":"29.0",
    "gn:asciiname":"Changliangzi",
    "gn:country_code":"CN",
    "gn:dem":1417,
    "gn:feature_class":"P",
    "gn:feature_code":"PPL",
    "gn:name":"Changliangzi",
    "gn:population":0,
    "gn:timezone":"Asia/Shanghai",
    "iso:country":"CN",
    "name:zho_x_preferred":[
        "\u957f\u6881\u5b50"
    ],
    "wof:name":"Changliangzi",
    "wof:placetype":"locality"
},
  "geometry": {"coordinates":[100.51300000000001,22.6981],"type":"Point"}
}