{
  "type": "Feature",
  "properties": {
    "gn:admin1_code":"30",
    "gn:asciiname":"Poweicun",
    "gn:country_code":"CN",
    "gn:dem":11,
    "gn:feature_class":"P",
    "gn:feature_code":"PPL",
    "gn:name":"Poweicun",
    "gn:population":0,
    "gn:timezone":"Asia/Urumqi",
    "iso:country":"CN",
    "name:zho_x_preferred":[
        "\u5761\u5c3e\u6751"
    ],
    "wof:name":"Poweicun",
    "wof:placetype":"locality"
},
  "geometry": {"coordinates":[110.42435999999999,21.15992],"type":"Point"}
}