{
  "type": "Feature",
  "properties": {
    "gn:admin1_code":"6.0",
    "gn:asciiname":"Eheke",
    "gn:country_code":"CN",
    "gn:dem":3528,
    "gn:feature_class":"P",
    "gn:feature_code":"PPL",
    "gn:name":"Eheke",
    "gn:population":0,
    "gn:timezone":"Asia/Shanghai",
    "iso:country":"CN",
    "name:deu_x_preferred":[
        "Eheke"
    ],
    "name:zho_x_preferred":[
        "\u997f\u5408\u79d1"
    ],
    "wof:name":"Eheke",
    "wof:placetype":"locality"
},
  "geometry": {"coordinates":[100.86461,34.51048],"type":"Point"}
}