{
  "type": "Feature",
  "properties": {
    "gn:admin1_code":"29.0",
    "gn:asciiname":"Shanglongdian",
    "gn:country_code":"CN",
    "gn:dem":1708,
    "gn:feature_class":"P",
    "gn:feature_code":"PPL",
    "gn:name":"Shanglongdian",
    "gn:population":0,
    "gn:timezone":"Asia/Shanghai",
    "iso:country":"CN",
    "name:zho_x_preferred":[
        "\u4e0a\u9f99\u7538"
    ],
    "wof:name":"Shanglongdian",
    "wof:placetype":"locality"
},
  "geometry": {"coordinates":[103.78100000000001,24.5061],"type":"Point"}
}