{
  "type": "Feature",
  "properties": {
    "gn:admin1_code":"4.0",
    "gn:asciiname":"Hua'aitoucun",
    "gn:country_code":"CN",
    "gn:dem":19,
    "gn:feature_class":"P",
    "gn:feature_code":"PPL",
    "gn:name":"Hua\u2019aitoucun",
    "gn:population":0,
    "gn:timezone":"Asia/Shanghai",
    "iso:country":"CN",
    "name:und_x_variant":[
        "Hua\u2019aitoucun"
    ],
    "name:zho_x_preferred":[
        "\u82b1\u57c3\u5934\u6751"
    ],
    "wof:name":"Hua'aitoucun",
    "wof:placetype":"locality"
},
  "geometry": {"coordinates":[119.17688,35.0791],"type":"Point"}
}