{
  "type": "Feature",
  "properties": {
    "gn:admin1_code":"26.0",
    "gn:asciiname":"Qiulinzicun",
    "gn:country_code":"CN",
    "gn:dem":664,
    "gn:feature_class":"P",
    "gn:feature_code":"PPL",
    "gn:name":"Qiulinzicun",
    "gn:population":0,
    "gn:timezone":"Asia/Shanghai",
    "iso:country":"CN",
    "name:zho_x_preferred":[
        "\u4e18\u6797\u5b50\u6751"
    ],
    "wof:name":"Qiulinzicun",
    "wof:placetype":"locality"
},
  "geometry": {"coordinates":[109.96063999999998,33.34562],"type":"Point"}
}