{
  "type": "Feature",
  "properties": {
    "gn:admin1_code":"18",
    "gn:asciiname":"Weigan",
    "gn:country_code":"CN",
    "gn:dem":632,
    "gn:feature_class":"P",
    "gn:feature_code":"PPL",
    "gn:name":"Weigan",
    "gn:population":0,
    "gn:timezone":"Asia/Shanghai",
    "iso:country":"CN",
    "name:zho_x_preferred":[
        "\u5c3e\u5e72"
    ],
    "wof:name":"Weigan",
    "wof:placetype":"locality"
},
  "geometry": {"coordinates":[106.104,24.8715],"type":"Point"}
}