{
  "type": "Feature",
  "properties": {
    "gn:admin1_code":"19.0",
    "gn:asciiname":"Lizenggou",
    "gn:country_code":"CN",
    "gn:dem":164,
    "gn:feature_class":"P",
    "gn:feature_code":"PPL",
    "gn:name":"Lizenggou",
    "gn:population":0,
    "gn:timezone":"Asia/Shanghai",
    "iso:country":"CN",
    "name:und_x_variant":[
        "\u5229\u589e\u6c9f"
    ],
    "wof:name":"Lizenggou",
    "wof:placetype":"locality"
},
  "geometry": {"coordinates":[122.45699999999999,40.0181],"type":"Point"}
}