{
  "type": "Feature",
  "properties": {
    "gn:admin1_code":"30.0",
    "gn:asciiname":"Lancun",
    "gn:country_code":"CN",
    "gn:dem":24,
    "gn:feature_class":"P",
    "gn:feature_code":"PPL",
    "gn:name":"Lancun",
    "gn:population":0,
    "gn:timezone":"Asia/Shanghai",
    "iso:country":"CN",
    "name:zho_x_preferred":[
        "\u84dd\u6751"
    ],
    "wof:name":"Lancun",
    "wof:placetype":"locality"
},
  "geometry": {"coordinates":[111.83956000000001,23.20328],"type":"Point"}
}