{
  "type": "Feature",
  "properties": {
    "gn:admin1_code":"11.0",
    "gn:asciiname":"Patoujiang",
    "gn:country_code":"CN",
    "gn:dem":537,
    "gn:feature_class":"P",
    "gn:feature_code":"PPL",
    "gn:name":"Patoujiang",
    "gn:population":0,
    "gn:timezone":"Asia/Shanghai",
    "iso:country":"CN",
    "name:zho_x_preferred":[
        "\u8db4\u5934\u6c5f"
    ],
    "wof:name":"Patoujiang",
    "wof:placetype":"locality"
},
  "geometry": {"coordinates":[110.22619,26.99494],"type":"Point"}
}