{
  "type": "Feature",
  "properties": {
    "gn:admin1_code":"7.0",
    "gn:asciiname":"Keli",
    "gn:country_code":"CN",
    "gn:dem":478,
    "gn:feature_class":"P",
    "gn:feature_code":"PPL",
    "gn:name":"Keli",
    "gn:population":0,
    "gn:timezone":"Asia/Shanghai",
    "iso:country":"CN",
    "name:zho_x_preferred":[
        "\u79d1\u91cc"
    ],
    "wof:name":"Keli",
    "wof:placetype":"locality"
},
  "geometry": {"coordinates":[116.46396,25.21981],"type":"Point"}
}