{
  "type": "Feature",
  "properties": {
    "gn:admin1_code":"9.0",
    "gn:asciiname":"Zhongqu",
    "gn:country_code":"CN",
    "gn:dem":63,
    "gn:feature_class":"P",
    "gn:feature_code":"PPL",
    "gn:name":"Zhongqu",
    "gn:population":0,
    "gn:timezone":"Asia/Shanghai",
    "iso:country":"CN",
    "name:zho_x_preferred":[
        "\u91cd\u6e20"
    ],
    "wof:name":"Zhongqu",
    "wof:placetype":"locality"
},
  "geometry": {"coordinates":[114.09610000000001,33.30645],"type":"Point"}
}