{
  "type": "Feature",
  "properties": {
    "gn:admin1_code":"26",
    "gn:asciiname":"Bailuchu",
    "gn:country_code":"CN",
    "gn:dem":1281,
    "gn:feature_class":"P",
    "gn:feature_code":"PPL",
    "gn:name":"Bailuchu",
    "gn:population":0,
    "gn:timezone":"Asia/Shanghai",
    "iso:country":"CN",
    "wof:name":"Bailuchu",
    "wof:placetype":"locality"
},
  "geometry": {"coordinates":[110.49556,33.30639],"type":"Point"}
}