{
  "type": "Feature",
  "properties": {
    "gn:admin1_code":"32.0",
    "gn:asciiname":"Fanlong",
    "gn:country_code":"CN",
    "gn:dem":495,
    "gn:feature_class":"P",
    "gn:feature_code":"PPL",
    "gn:name":"Fanlong",
    "gn:population":0,
    "gn:timezone":"Asia/Shanghai",
    "iso:country":"CN",
    "name:zho_x_preferred":[
        "\u51e1\u9f99"
    ],
    "wof:name":"Fanlong",
    "wof:placetype":"locality"
},
  "geometry": {"coordinates":[104.76900000000001,30.9389],"type":"Point"}
}