{
  "type": "Feature",
  "properties": {
    "gn:admin1_code":"30",
    "gn:asciiname":"Lingbei",
    "gn:country_code":"CN",
    "gn:dem":124,
    "gn:feature_class":"P",
    "gn:feature_code":"PPLA4",
    "gn:name":"Lingbei",
    "gn:population":0,
    "gn:timezone":"Asia/Urumqi",
    "iso:country":"CN",
    "name:und_x_variant":[
        "\u5cad\u5317",
        "Lingbei",
        "Lingbei Zhen",
        "\u5cad\u5317\u9547"
    ],
    "wof:name":"Lingbei",
    "wof:placetype":"locality"
},
  "geometry": {"coordinates":[110.16416,21.26355],"type":"Point"}
}