{
  "type": "Feature",
  "properties": {
    "gn:admin1_code":"16",
    "gn:asciiname":"Daoshui",
    "gn:cc2":"CN",
    "gn:country_code":"CN",
    "gn:dem":32,
    "gn:feature_class":"P",
    "gn:feature_code":"PPL",
    "gn:name":"Daoshui",
    "gn:population":0,
    "gn:timezone":"Asia/Shanghai",
    "iso:country":"CN",
    "name:und_x_variant":[
        "Tao-shui",
        "Tao-shui-hs\u00fc",
        "Tao-shui-chieh",
        "Daoshui"
    ],
    "wof:name":"Daoshui",
    "wof:placetype":"locality"
},
  "geometry": {"coordinates":[111.13333,23.56667],"type":"Point"}
}