{
  "type": "Feature",
  "properties": {
    "gn:admin1_code":"5.0",
    "gn:asciiname":"Huxiacun",
    "gn:country_code":"CN",
    "gn:dem":497,
    "gn:feature_class":"P",
    "gn:feature_code":"PPL",
    "gn:name":"Huxiacun",
    "gn:population":0,
    "gn:timezone":"Asia/Shanghai",
    "iso:country":"CN",
    "name:zho_x_preferred":[
        "\u6e56\u4e0b\u6751"
    ],
    "wof:name":"Huxiacun",
    "wof:placetype":"locality"
},
  "geometry": {"coordinates":[126.25479,41.90242],"type":"Point"}
}