{
  "type": "Feature",
  "properties": {
    "gn:admin1_code":"7",
    "gn:asciiname":"Diandou",
    "gn:country_code":"CN",
    "gn:dem":355,
    "gn:feature_class":"P",
    "gn:feature_code":"PPL",
    "gn:name":"Diandou",
    "gn:population":0,
    "gn:timezone":"Asia/Shanghai",
    "iso:country":"CN",
    "name:und_x_variant":[
        "\u5e97\u515c"
    ],
    "wof:name":"Diandou",
    "wof:placetype":"locality"
},
  "geometry": {"coordinates":[119.63833,27.34139],"type":"Point"}
}