{
  "type": "Feature",
  "properties": {
    "gn:admin1_code":"16.0",
    "gn:asciiname":"Mada",
    "gn:country_code":"CN",
    "gn:dem":1420,
    "gn:feature_class":"P",
    "gn:feature_code":"PPL",
    "gn:name":"Mada",
    "gn:population":0,
    "gn:timezone":"Asia/Shanghai",
    "iso:country":"CN",
    "name:fra_x_preferred":[
        "Mada"
    ],
    "name:zho_x_preferred":[
        "\u9a6c\u5927"
    ],
    "wof:name":"Mada",
    "wof:placetype":"locality"
},
  "geometry": {"coordinates":[105.047,24.6452],"type":"Point"}
}