{
  "type": "Feature",
  "properties": {
    "gn:admin1_code":"2.0",
    "gn:asciiname":"Laoshan",
    "gn:country_code":"CN",
    "gn:dem":197,
    "gn:feature_class":"P",
    "gn:feature_code":"PPL",
    "gn:name":"Laoshan",
    "gn:population":0,
    "gn:timezone":"Asia/Shanghai",
    "iso:country":"CN",
    "name:und_x_variant":[
        "\u7262\u5c71"
    ],
    "wof:name":"Laoshan",
    "wof:placetype":"locality"
},
  "geometry": {"coordinates":[119.56242,30.22901],"type":"Point"}
}