{
  "type": "Feature",
  "properties": {
    "gn:admin1_code":"9.0",
    "gn:asciiname":"Wanglaojia",
    "gn:country_code":"CN",
    "gn:dem":41,
    "gn:feature_class":"P",
    "gn:feature_code":"PPL",
    "gn:name":"Wanglaojia",
    "gn:population":0,
    "gn:timezone":"Asia/Shanghai",
    "iso:country":"CN",
    "name:zho_x_preferred":[
        "\u738b\u8001\u5bb6"
    ],
    "wof:name":"Wanglaojia",
    "wof:placetype":"locality"
},
  "geometry": {"coordinates":[115.31162,33.47376],"type":"Point"}
}