{
  "type": "Feature",
  "properties": {
    "gn:admin1_code":"3",
    "gn:asciiname":"Zengwu",
    "gn:country_code":"CN",
    "gn:dem":182,
    "gn:feature_class":"P",
    "gn:feature_code":"PPL",
    "gn:name":"Zengwu",
    "gn:population":0,
    "gn:timezone":"Asia/Shanghai",
    "iso:country":"CN",
    "name:zho_x_preferred":[
        "\u66fe\u5c4b"
    ],
    "wof:name":"Zengwu",
    "wof:placetype":"locality"
},
  "geometry": {"coordinates":[114.93300000000001,25.4859],"type":"Point"}
}