{
  "type": "Feature",
  "properties": {
    "gn:admin1_code":"33.0",
    "gn:asciiname":"Lishiwan",
    "gn:country_code":"CN",
    "gn:dem":1299,
    "gn:feature_class":"P",
    "gn:feature_code":"PPL",
    "gn:name":"Lishiwan",
    "gn:population":0,
    "gn:timezone":"Asia/Shanghai",
    "iso:country":"CN",
    "name:zho_x_preferred":[
        "\u7acb\u77f3\u6e7e"
    ],
    "wof:name":"Lishiwan",
    "wof:placetype":"locality"
},
  "geometry": {"coordinates":[108.47642999999999,32.09084],"type":"Point"}
}