{
  "type": "Feature",
  "properties": {
    "gn:admin1_code":"30.0",
    "gn:asciiname":"Fenggang",
    "gn:country_code":"CN",
    "gn:dem":30,
    "gn:feature_class":"P",
    "gn:feature_code":"PPL",
    "gn:name":"Fenggang",
    "gn:population":0,
    "gn:timezone":"Asia/Shanghai",
    "iso:country":"CN",
    "name:ceb_x_preferred":[
        "Fenggang"
    ],
    "name:deu_x_preferred":[
        "Fenggang"
    ],
    "name:zho_x_preferred":[
        "\u51e4\u5188"
    ],
    "wof:name":"Fenggang",
    "wof:placetype":"locality"
},
  "geometry": {"coordinates":[114.80571999999999,23.03966],"type":"Point"}
}