{
  "type": "Feature",
  "properties": {
    "gn:admin1_code":"30.0",
    "gn:asciiname":"Xiaping Shacun",
    "gn:country_code":"CN",
    "gn:dem":67,
    "gn:feature_class":"P",
    "gn:feature_code":"PPL",
    "gn:name":"Xiaping Shacun",
    "gn:population":0,
    "gn:timezone":"Asia/Shanghai",
    "iso:country":"CN",
    "name:zho_x_preferred":[
        "\u4e0b\u576a\u6c99\u6751"
    ],
    "wof:name":"Xiaping Shacun",
    "wof:placetype":"locality"
},
  "geometry": {"coordinates":[116.59633999999998,24.53293],"type":"Point"}
}