{
  "type": "Feature",
  "properties": {
    "gn:admin1_code":"1.0",
    "gn:asciiname":"Ducicun",
    "gn:country_code":"CN",
    "gn:dem":43,
    "gn:feature_class":"P",
    "gn:feature_code":"PPL",
    "gn:name":"Ducicun",
    "gn:population":0,
    "gn:timezone":"Asia/Shanghai",
    "iso:country":"CN",
    "name:zho_x_preferred":[
        "\u675c\u7960\u6751"
    ],
    "wof:name":"Ducicun",
    "wof:placetype":"locality"
},
  "geometry": {"coordinates":[116.17892999999999,31.95057000000001],"type":"Point"}
}