{
  "type": "Feature",
  "properties": {
    "gn:admin1_code":"12.0",
    "gn:asciiname":"Babaimu",
    "gn:country_code":"CN",
    "gn:dem":35,
    "gn:feature_class":"P",
    "gn:feature_code":"PPL",
    "gn:name":"Babaimu",
    "gn:population":0,
    "gn:timezone":"Asia/Shanghai",
    "iso:country":"CN",
    "name:zho_x_preferred":[
        "\u516b\u767e\u4ea9"
    ],
    "wof:name":"Babaimu",
    "wof:placetype":"locality"
},
  "geometry": {"coordinates":[112.06726999999999,30.11913],"type":"Point"}
}