{
  "type": "Feature",
  "properties": {
    "gn:admin1_code":"03",
    "gn:asciiname":"Pencheng",
    "gn:cc2":"CN",
    "gn:country_code":"CN",
    "gn:dem":20,
    "gn:feature_class":"P",
    "gn:feature_code":"PPL",
    "gn:name":"Pencheng",
    "gn:population":0,
    "gn:timezone":"Asia/Shanghai",
    "iso:country":"CN",
    "name:und_x_variant":[
        "Jui-ch\u2019ang-hsien",
        "Ruichang",
        "Jui-ch\u2019ang",
        "Pencheng"
    ],
    "wof:name":"Pencheng",
    "wof:placetype":"locality"
},
  "geometry": {"coordinates":[115.65000000000001,29.66667],"type":"Point"}
}