{
  "type": "Feature",
  "properties": {
    "gn:admin1_code":"8.0",
    "gn:asciiname":"Yulincun",
    "gn:country_code":"CN",
    "gn:dem":225,
    "gn:feature_class":"P",
    "gn:feature_code":"PPL",
    "gn:name":"Yulincun",
    "gn:population":0,
    "gn:timezone":"Asia/Shanghai",
    "iso:country":"CN",
    "name:zho_x_preferred":[
        "\u4e8e\u6797\u6751"
    ],
    "wof:name":"Yulincun",
    "wof:placetype":"locality"
},
  "geometry": {"coordinates":[129.42143000000002,46.80613],"type":"Point"}
}