{
  "type": "Feature",
  "properties": {
    "gn:admin1_code":"26.0",
    "gn:asciiname":"Abaoye",
    "gn:country_code":"CN",
    "gn:dem":1330,
    "gn:feature_class":"P",
    "gn:feature_code":"PPL",
    "gn:name":"Abaoye",
    "gn:population":0,
    "gn:timezone":"Asia/Shanghai",
    "iso:country":"CN",
    "name:zho_x_preferred":[
        "\u554a\u5305\u4e5f"
    ],
    "wof:name":"Abaoye",
    "wof:placetype":"locality"
},
  "geometry": {"coordinates":[110.11698,39.09735],"type":"Point"}
}