{
  "type": "Feature",
  "properties": {
    "gn:admin1_code":"29.0",
    "gn:asciiname":"Luomakou",
    "gn:country_code":"CN",
    "gn:dem":1557,
    "gn:feature_class":"P",
    "gn:feature_code":"PPL",
    "gn:name":"Luomakou",
    "gn:population":0,
    "gn:timezone":"Asia/Shanghai",
    "iso:country":"CN",
    "name:zho_x_preferred":[
        "\u9aa1\u9a6c\u53e3"
    ],
    "wof:name":"Luomakou",
    "wof:placetype":"locality"
},
  "geometry": {"coordinates":[103.39700000000001,27.116],"type":"Point"}
}