{
  "type": "Feature",
  "properties": {
    "gn:admin1_code":"8.0",
    "gn:asciiname":"Meiyaogou",
    "gn:country_code":"CN",
    "gn:dem":232,
    "gn:feature_class":"P",
    "gn:feature_code":"PPL",
    "gn:name":"Meiyaogou",
    "gn:population":0,
    "gn:timezone":"Asia/Shanghai",
    "iso:country":"CN",
    "name:und_x_variant":[
        "\u7164\u7a91\u6c9f"
    ],
    "wof:name":"Meiyaogou",
    "wof:placetype":"locality"
},
  "geometry": {"coordinates":[127.28728999999998,49.9635],"type":"Point"}
}