{
  "type": "Feature",
  "properties": {
    "gn:admin1_code":"26.0",
    "gn:asciiname":"Yanglukeng",
    "gn:country_code":"CN",
    "gn:dem":1334,
    "gn:feature_class":"P",
    "gn:feature_code":"PPL",
    "gn:name":"Yanglukeng",
    "gn:population":0,
    "gn:timezone":"Asia/Shanghai",
    "iso:country":"CN",
    "name:zho_x_preferred":[
        "\u7f8a\u8def\u5751"
    ],
    "wof:name":"Yanglukeng",
    "wof:placetype":"locality"
},
  "geometry": {"coordinates":[108.82329,37.60088],"type":"Point"}
}