{
  "type": "Feature",
  "properties": {
    "gn:admin1_code":"33.0",
    "gn:asciiname":"Shuxiang",
    "gn:country_code":"CN",
    "gn:dem":667,
    "gn:feature_class":"P",
    "gn:feature_code":"PPL",
    "gn:name":"Shuxiang",
    "gn:population":0,
    "gn:timezone":"Asia/Shanghai",
    "iso:country":"CN",
    "name:zho_x_preferred":[
        "\u4e66\u9999"
    ],
    "wof:name":"Shuxiang",
    "wof:placetype":"locality"
},
  "geometry": {"coordinates":[108.03021,31.09497],"type":"Point"}
}