{
  "type": "Feature",
  "properties": {
    "gn:admin1_code":"11.0",
    "gn:asciiname":"Meiziwan",
    "gn:country_code":"CN",
    "gn:dem":181,
    "gn:feature_class":"P",
    "gn:feature_code":"PPL",
    "gn:name":"Meiziwan",
    "gn:population":0,
    "gn:timezone":"Asia/Shanghai",
    "iso:country":"CN",
    "name:zho_x_preferred":[
        "\u6885\u5b50\u6e7e"
    ],
    "wof:name":"Meiziwan",
    "wof:placetype":"locality"
},
  "geometry": {"coordinates":[113.25612,27.42963],"type":"Point"}
}