{
  "type": "Feature",
  "properties": {
    "gn:admin1_code":"33.0",
    "gn:asciiname":"Daqiao",
    "gn:country_code":"CN",
    "gn:dem":267,
    "gn:feature_class":"P",
    "gn:feature_code":"PPL",
    "gn:name":"Daqiao",
    "gn:population":0,
    "gn:timezone":"Asia/Shanghai",
    "iso:country":"CN",
    "name:ceb_x_preferred":[
        "Daqiao"
    ],
    "name:deu_x_preferred":[
        "Daqiao"
    ],
    "name:swe_x_preferred":[
        "Daqiao"
    ],
    "name:zho_x_preferred":[
        "\u5927\u6865"
    ],
    "wof:name":"Daqiao",
    "wof:placetype":"locality"
},
  "geometry": {"coordinates":[109.25803999999999,28.76461],"type":"Point"}
}