{
  "type": "Feature",
  "properties": {
    "gn:admin1_code":"29.0",
    "gn:asciiname":"Xiaotang",
    "gn:country_code":"CN",
    "gn:dem":1538,
    "gn:feature_class":"P",
    "gn:feature_code":"PPL",
    "gn:name":"Xiaotang",
    "gn:population":0,
    "gn:timezone":"Asia/Shanghai",
    "iso:country":"CN",
    "name:zho_x_preferred":[
        "\u785d\u5858"
    ],
    "wof:name":"Xiaotang",
    "wof:placetype":"locality"
},
  "geometry": {"coordinates":[98.19329999999999,25.3049],"type":"Point"}
}