{
  "type": "Feature",
  "properties": {
    "gn:admin1_code":"1.0",
    "gn:asciiname":"Yanwancun",
    "gn:country_code":"CN",
    "gn:dem":81,
    "gn:feature_class":"P",
    "gn:feature_code":"PPL",
    "gn:name":"Yanwancun",
    "gn:population":0,
    "gn:timezone":"Asia/Shanghai",
    "iso:country":"CN",
    "name:zho_x_preferred":[
        "\u5ca9\u6e7e\u6751"
    ],
    "wof:name":"Yanwancun",
    "wof:placetype":"locality"
},
  "geometry": {"coordinates":[116.49036,31.52359],"type":"Point"}
}