{
  "type": "Feature",
  "properties": {
    "gn:admin1_code":"29",
    "gn:asciiname":"Lutong",
    "gn:country_code":"CN",
    "gn:dem":1614,
    "gn:feature_class":"P",
    "gn:feature_code":"PPL",
    "gn:name":"Lutong",
    "gn:population":0,
    "gn:timezone":"Asia/Shanghai",
    "iso:country":"CN",
    "name:zho_x_preferred":[
        "\u8def\u901a"
    ],
    "wof:name":"Lutong",
    "wof:placetype":"locality"
},
  "geometry": {"coordinates":[102.065,23.6612],"type":"Point"}
}