{
  "type": "Feature",
  "properties": {
    "gn:admin1_code":"15.0",
    "gn:asciiname":"Guojia Yangou",
    "gn:country_code":"CN",
    "gn:dem":1625,
    "gn:feature_class":"P",
    "gn:feature_code":"PPL",
    "gn:name":"Guojia Yangou",
    "gn:population":0,
    "gn:timezone":"Asia/Shanghai",
    "iso:country":"CN",
    "name:zho_x_preferred":[
        "\u90ed\u5bb6\u6cbf\u6c9f"
    ],
    "wof:name":"Guojia Yangou",
    "wof:placetype":"locality"
},
  "geometry": {"coordinates":[100.158,38.9422],"type":"Point"}
}