{
  "type": "Feature",
  "properties": {
    "gn:admin1_code":"2.0",
    "gn:asciiname":"Dongluhua",
    "gn:country_code":"CN",
    "gn:dem":7,
    "gn:feature_class":"P",
    "gn:feature_code":"PPL",
    "gn:name":"Dongl\u00fchua",
    "gn:population":0,
    "gn:timezone":"Asia/Shanghai",
    "iso:country":"CN",
    "name:und_x_variant":[
        "Dongl\u00fchua"
    ],
    "name:zho_x_preferred":[
        "\u4e1c\u7eff\u534e"
    ],
    "wof:name":"Dongluhua",
    "wof:placetype":"locality"
},
  "geometry": {"coordinates":[122.65037,30.82034],"type":"Point"}
}