{
  "type": "Feature",
  "properties": {
    "gn:admin1_code":"29.0",
    "gn:asciiname":"Xialude",
    "gn:country_code":"CN",
    "gn:dem":1508,
    "gn:feature_class":"P",
    "gn:feature_code":"PPL",
    "gn:name":"Xialude",
    "gn:population":0,
    "gn:timezone":"Asia/Shanghai",
    "iso:country":"CN",
    "name:zho_x_preferred":[
        "\u4e0b\u8def\u5f97"
    ],
    "wof:name":"Xialude",
    "wof:placetype":"locality"
},
  "geometry": {"coordinates":[103.937,23.6821],"type":"Point"}
}