{
  "type": "Feature",
  "properties": {
    "gn:admin1_code":"14.0",
    "gn:asciiname":"Danjia",
    "gn:country_code":"CN",
    "gn:dem":4340,
    "gn:feature_class":"P",
    "gn:feature_code":"PPL",
    "gn:name":"Danjia",
    "gn:population":0,
    "gn:timezone":"Asia/Urumqi",
    "iso:country":"CN",
    "name:ceb_x_preferred":[
        "Danjia"
    ],
    "name:swe_x_preferred":[
        "Danjia"
    ],
    "name:zho_x_preferred":[
        "\u4e39\u5bb6"
    ],
    "wof:name":"Danjia",
    "wof:placetype":"locality"
},
  "geometry": {"coordinates":[94.17673000000001,29.40159],"type":"Point"}
}