{
  "type": "Feature",
  "properties": {
    "gn:admin1_code":"26.0",
    "gn:asciiname":"Liaoyegou",
    "gn:country_code":"CN",
    "gn:dem":1098,
    "gn:feature_class":"P",
    "gn:feature_code":"PPL",
    "gn:name":"Liaoyegou",
    "gn:population":0,
    "gn:timezone":"Asia/Shanghai",
    "iso:country":"CN",
    "name:und_x_variant":[
        "\u84fc\u53f6\u6c9f"
    ],
    "wof:name":"Liaoyegou",
    "wof:placetype":"locality"
},
  "geometry": {"coordinates":[107.15403999999999,33.40042],"type":"Point"}
}