{
  "type": "Feature",
  "properties": {
    "gn:admin1_code":"29.0",
    "gn:asciiname":"Chaqing",
    "gn:country_code":"CN",
    "gn:dem":1307,
    "gn:feature_class":"P",
    "gn:feature_code":"PPL",
    "gn:name":"Chaqing",
    "gn:population":0,
    "gn:timezone":"Asia/Shanghai",
    "iso:country":"CN",
    "name:zho_x_preferred":[
        "\u5c94\u7b90"
    ],
    "wof:name":"Chaqing",
    "wof:placetype":"locality"
},
  "geometry": {"coordinates":[101.45399999999999,22.8698],"type":"Point"}
}