{
  "type": "Feature",
  "properties": {
    "gn:admin1_code":"18.0",
    "gn:asciiname":"Shangbali",
    "gn:country_code":"CN",
    "gn:dem":453,
    "gn:feature_class":"P",
    "gn:feature_code":"PPL",
    "gn:name":"Shangbali",
    "gn:population":0,
    "gn:timezone":"Asia/Shanghai",
    "iso:country":"CN",
    "name:zho_x_preferred":[
        "\u4e0a\u516b\u91cc"
    ],
    "wof:name":"Shangbali",
    "wof:placetype":"locality"
},
  "geometry": {"coordinates":[108.965,26.41800000000001],"type":"Point"}
}