{
  "type": "Feature",
  "properties": {
    "gn:admin1_code":"11",
    "gn:asciiname":"Sanchashui",
    "gn:country_code":"CN",
    "gn:dem":837,
    "gn:feature_class":"P",
    "gn:feature_code":"PPL",
    "gn:name":"Sanchashui",
    "gn:population":0,
    "gn:timezone":"Asia/Shanghai",
    "iso:country":"CN",
    "name:zho_x_preferred":[
        "\u4e09\u5c94\u6c34"
    ],
    "wof:name":"Sanchashui",
    "wof:placetype":"locality"
},
  "geometry": {"coordinates":[111.91294000000001,26.14351],"type":"Point"}
}