{
  "type": "Feature",
  "properties": {
    "gn:admin1_code":"03",
    "gn:asciiname":"Dukou",
    "gn:country_code":"CN",
    "gn:dem":105,
    "gn:feature_class":"P",
    "gn:feature_code":"PPL",
    "gn:name":"Dukou",
    "gn:population":0,
    "gn:timezone":"Asia/Shanghai",
    "iso:country":"CN",
    "name:und_x_variant":[
        "Tu-k\u2019ou",
        "Dukou",
        "\u6e0e\u53e3"
    ],
    "wof:name":"Dukou",
    "wof:placetype":"locality"
},
  "geometry": {"coordinates":[118.34197,28.64795],"type":"Point"}
}