{
  "type": "Feature",
  "properties": {
    "gn:admin1_code":"32.0",
    "gn:asciiname":"Foyemiao",
    "gn:country_code":"CN",
    "gn:dem":1000,
    "gn:feature_class":"P",
    "gn:feature_code":"PPL",
    "gn:name":"Foyemiao",
    "gn:population":0,
    "gn:timezone":"Asia/Shanghai",
    "iso:country":"CN",
    "name:zho_x_preferred":[
        "\u4f5b\u7237\u5e99"
    ],
    "wof:name":"Foyemiao",
    "wof:placetype":"locality"
},
  "geometry": {"coordinates":[104.371,31.6498],"type":"Point"}
}