{
  "type": "Feature",
  "properties": {
    "gn:admin1_code":"15.0",
    "gn:asciiname":"Huanghua Nongchang Shijiudui",
    "gn:country_code":"CN",
    "gn:dem":1359,
    "gn:feature_class":"P",
    "gn:feature_code":"PPLF",
    "gn:name":"Huanghua Nongchang Shijiudui",
    "gn:population":0,
    "gn:timezone":"Asia/Shanghai",
    "iso:country":"CN",
    "name:eng_x_preferred":[
        "Huanghua Nongchang Nineteen Dui"
    ],
    "name:zho_x_preferred":[
        "\u9ec4\u82b1\u519c\u573a\u5341\u4e5d\u961f"
    ],
    "wof:name":"Huanghua Nongchang Shijiudui",
    "wof:placetype":"locality"
},
  "geometry": {"coordinates":[97.21644000000001,40.44293],"type":"Point"}
}