{
  "type": "Feature",
  "properties": {
    "gn:admin1_code":"18",
    "gn:asciiname":"Hebatou",
    "gn:country_code":"CN",
    "gn:dem":2268,
    "gn:feature_class":"P",
    "gn:feature_code":"PPL",
    "gn:name":"Hebatou",
    "gn:population":0,
    "gn:timezone":"Asia/Shanghai",
    "iso:country":"CN",
    "name:zho_x_preferred":[
        "\u6cb3\u575d\u5934"
    ],
    "wof:name":"Hebatou",
    "wof:placetype":"locality"
},
  "geometry": {"coordinates":[104.643,26.8894],"type":"Point"}
}