{
  "type": "Feature",
  "properties": {
    "gn:admin1_code":"19.0",
    "gn:asciiname":"Shengjiagou",
    "gn:country_code":"CN",
    "gn:dem":14,
    "gn:feature_class":"P",
    "gn:feature_code":"PPL",
    "gn:name":"Shengjiagou",
    "gn:population":0,
    "gn:timezone":"Asia/Shanghai",
    "iso:country":"CN",
    "name:und_x_variant":[
        "\u76db\u5bb6\u6c9f"
    ],
    "name:zho_x_preferred":[
        "\u76db\u5bb6\u6c9f"
    ],
    "wof:name":"Shengjiagou",
    "wof:placetype":"locality"
},
  "geometry": {"coordinates":[121.20498000000001,38.7832],"type":"Point"}
}