{
  "type": "Feature",
  "properties": {
    "gn:admin1_code":"7",
    "gn:asciiname":"Leicuo",
    "gn:country_code":"CN",
    "gn:dem":285,
    "gn:feature_class":"P",
    "gn:feature_code":"PPL",
    "gn:name":"Leicuo",
    "gn:population":0,
    "gn:timezone":"Asia/Shanghai",
    "iso:country":"CN",
    "name:und_x_variant":[
        "\u96f7\u539d"
    ],
    "wof:name":"Leicuo",
    "wof:placetype":"locality"
},
  "geometry": {"coordinates":[118.78778,27.73389],"type":"Point"}
}