{
  "type": "Feature",
  "properties": {
    "gn:admin1_code":"7",
    "gn:asciiname":"Shibishi",
    "gn:country_code":"CN",
    "gn:dem":15,
    "gn:feature_class":"P",
    "gn:feature_code":"PPL",
    "gn:name":"Shibishi",
    "gn:population":0,
    "gn:timezone":"Asia/Shanghai",
    "iso:country":"CN",
    "name:zho_x_preferred":[
        "\u77f3\u58c1\u65bd"
    ],
    "wof:name":"Shibishi",
    "wof:placetype":"locality"
},
  "geometry": {"coordinates":[117.76833000000001,24.66528],"type":"Point"}
}