{
  "type": "Feature",
  "properties": {
    "gn:admin1_code":"20.0",
    "gn:asciiname":"Huge Jiletu",
    "gn:country_code":"CN",
    "gn:dem":696,
    "gn:feature_class":"P",
    "gn:feature_code":"PPL",
    "gn:name":"Huge Jiletu",
    "gn:population":0,
    "gn:timezone":"Asia/Shanghai",
    "iso:country":"CN",
    "name:zho_x_preferred":[
        "\u547c\u683c\u5409\u52d2\u56fe"
    ],
    "wof:name":"Huge Jiletu",
    "wof:placetype":"locality"
},
  "geometry": {"coordinates":[118.60883,48.35919000000001],"type":"Point"}
}