{
  "type": "Feature",
  "properties": {
    "gn:admin1_code":"12.0",
    "gn:asciiname":"Caijiagujing",
    "gn:country_code":"CN",
    "gn:dem":47,
    "gn:feature_class":"P",
    "gn:feature_code":"PPL",
    "gn:name":"Caijiagujing",
    "gn:population":0,
    "gn:timezone":"Asia/Shanghai",
    "iso:country":"CN",
    "name:zho_x_preferred":[
        "\u8521\u5bb6\u53e4\u4e95"
    ],
    "wof:name":"Caijiagujing",
    "wof:placetype":"locality"
},
  "geometry": {"coordinates":[113.91606000000002,31.18606],"type":"Point"}
}