{
  "type": "Feature",
  "properties": {
    "gn:admin1_code":"32.0",
    "gn:asciiname":"Hajue",
    "gn:country_code":"CN",
    "gn:dem":2461,
    "gn:feature_class":"P",
    "gn:feature_code":"PPL",
    "gn:name":"Hajue",
    "gn:population":0,
    "gn:timezone":"Asia/Shanghai",
    "iso:country":"CN",
    "name:zho_x_preferred":[
        "\u54c8\u89c9"
    ],
    "wof:name":"Hajue",
    "wof:placetype":"locality"
},
  "geometry": {"coordinates":[102.87192,28.29431],"type":"Point"}
}