{
  "type": "Feature",
  "properties": {
    "gn:admin1_code":"3.0",
    "gn:asciiname":"Cimeihuangjia",
    "gn:country_code":"CN",
    "gn:dem":77,
    "gn:feature_class":"P",
    "gn:feature_code":"PPL",
    "gn:name":"Cimeihuangjia",
    "gn:population":0,
    "gn:timezone":"Asia/Shanghai",
    "iso:country":"CN",
    "name:und_x_variant":[
        "\u6148\u7709\u9ec4\u5bb6"
    ],
    "wof:name":"Cimeihuangjia",
    "wof:placetype":"locality"
},
  "geometry": {"coordinates":[116.74151999999999,28.08937],"type":"Point"}
}