{
  "type": "Feature",
  "properties": {
    "gn:admin1_code":"3",
    "gn:asciiname":"Zifu",
    "gn:country_code":"CN",
    "gn:dem":104,
    "gn:feature_class":"P",
    "gn:feature_code":"PPL",
    "gn:name":"Zifu",
    "gn:population":0,
    "gn:timezone":"Asia/Shanghai",
    "iso:country":"CN",
    "name:ceb_x_preferred":[
        "Zifu"
    ],
    "name:fas_x_preferred":[
        "\u0632\u06cc\u0641\u0648"
    ],
    "name:fra_x_preferred":[
        "Zifu"
    ],
    "name:jpn_x_preferred":[
        "\u8cc7\u798f\u93ae"
    ],
    "name:swe_x_preferred":[
        "Zifu"
    ],
    "name:und_x_variant":[
        "\u8d44\u798f"
    ],
    "name:zho_x_preferred":[
        "\u8d44\u798f\u9547"
    ],
    "wof:name":"Zifu",
    "wof:placetype":"locality"
},
  "geometry": {"coordinates":[116.93932,27.41367],"type":"Point"}
}