{
  "type": "Feature",
  "properties": {
    "gn:admin1_code":"11.0",
    "gn:asciiname":"Shizichong",
    "gn:country_code":"CN",
    "gn:dem":157,
    "gn:feature_class":"P",
    "gn:feature_code":"PPL",
    "gn:name":"Shizichong",
    "gn:population":0,
    "gn:timezone":"Asia/Shanghai",
    "iso:country":"CN",
    "name:zho_x_preferred":[
        "Shizichong"
    ],
    "name:zho_x_variant":[
        "\u72ee\u5b50\u51b2"
    ],
    "wof:name":"Shizichong",
    "wof:placetype":"locality"
},
  "geometry": {"coordinates":[111.40279,29.79334],"type":"Point"}
}