{
  "type": "Feature",
  "properties": {
    "gn:admin1_code":"4.0",
    "gn:asciiname":"Yangtianzhuang",
    "gn:country_code":"CN",
    "gn:dem":5,
    "gn:feature_class":"P",
    "gn:feature_code":"PPL",
    "gn:name":"Yangtianzhuang",
    "gn:population":0,
    "gn:timezone":"Asia/Shanghai",
    "iso:country":"CN",
    "name:zho_x_preferred":[
        "\u6768\u5929\u5e84"
    ],
    "wof:name":"Yangtianzhuang",
    "wof:placetype":"locality"
},
  "geometry": {"coordinates":[120.72341000000002,32.18886],"type":"Point"}
}