{
  "type": "Feature",
  "properties": {
    "iso:country":"CN",
    "name:ara_x_preferred":[
        "\u0645\u0637\u0627\u0631 \u0641\u0648\u0634\u0627\u0646 \u0634\u0627\u062f\u064a"
    ],
    "name:ceb_x_preferred":[
        "Foshan Shadi Airport"
    ],
    "name:eng_x_preferred":[
        "Foshan Shadi Airport"
    ],
    "name:fas_x_preferred":[
        "\u0641\u0631\u0648\u062f\u06af\u0627\u0647 \u0641\u0648\u0634\u0627\u0646 \u0634\u0627\u062f\u06cc"
    ],
    "name:fra_x_preferred":[
        "A\u00e9roport de Foshan Shadi"
    ],
    "name:jpn_x_preferred":[
        "Lingling Airport"
    ],
    "name:jpn_x_variant":[
        "\u4ecf\u5c71\u6c99\u5824\u7a7a\u6e2f"
    ],
    "name:kor_x_preferred":[
        "\ud3ec\uc0b0 \uc0ac\ub514 \uacf5\ud56d"
    ],
    "name:pol_x_preferred":[
        "Port lotniczy Foshan"
    ],
    "name:ron_x_preferred":[
        "Aeroportul Foshan Shadi"
    ],
    "name:swe_x_preferred":[
        "Foshan Shadi Airport"
    ],
    "name:tgk_x_preferred":[
        "\u0424\u0443\u0440\u0443\u0434\u0433\u043e\u04b3\u0438 \u0444\u0443\u0448\u043e\u043d \u0448\u043e\u0434\u04e3"
    ],
    "name:vie_x_preferred":[
        "S\u00e2n bay Sa \u0110\u00ea Ph\u1eadt S\u01a1n"
    ],
    "name:yue_x_preferred":[
        "\u4f5b\u5c71\u6c99\u5824\u6a5f\u5834"
    ],
    "name:zho_x_preferred":[
        "\u4f5b\u5c71\u6c99\u5824\u6a5f\u5834"
    ],
    "name:zho_yue_x_preferred":[
        "\u4f5b\u5c71\u6c99\u5824\u6a5f\u5834"
    ],
    "oa:elevation_ft":"6",
    "oa:type":"medium_airport",
    "wd:wordcount":130,
    "woe:hierarchy":{
        "country_id":23424781,
        "county_id":26198244,
        "localadmin_id":20071189,
        "planet_id":1,
        "state_id":12578019
    },
    "wof:name":"Shadi Airport",
    "wof:placetype":"campus"
},
  "geometry": {"coordinates":[113.07083333333,23.0825],"type":"Point"}
}