{
  "type": "Feature",
  "properties": {
    "gn:admin1_code":"29.0",
    "gn:asciiname":"Mengnai Xinzhai",
    "gn:country_code":"CN",
    "gn:dem":1417,
    "gn:feature_class":"P",
    "gn:feature_code":"PPL",
    "gn:name":"Mengnai Xinzhai",
    "gn:population":0,
    "gn:timezone":"Asia/Shanghai",
    "iso:country":"CN",
    "name:zho_x_preferred":[
        "\u52d0\u4e43\u65b0\u5be8"
    ],
    "wof:name":"Mengnai Xinzhai",
    "wof:placetype":"locality"
},
  "geometry": {"coordinates":[100.268,22.3365],"type":"Point"}
}