{
  "type": "Feature",
  "properties": {
    "gn:admin1_code":"18",
    "gn:asciiname":"Chuantounan",
    "gn:country_code":"CN",
    "gn:dem":599,
    "gn:feature_class":"P",
    "gn:feature_code":"PPL",
    "gn:name":"Chuantounan",
    "gn:population":0,
    "gn:timezone":"Asia/Shanghai",
    "iso:country":"CN",
    "name:zho_x_preferred":[
        "\u8239\u5934\u6960"
    ],
    "wof:name":"Chuantounan",
    "wof:placetype":"locality"
},
  "geometry": {"coordinates":[107.279,27.2504],"type":"Point"}
}