{
  "type": "Feature",
  "properties": {
    "gn:admin1_code":"16",
    "gn:asciiname":"Changxu",
    "gn:country_code":"CN",
    "gn:dem":173,
    "gn:feature_class":"P",
    "gn:feature_code":"PPL",
    "gn:name":"Changxu",
    "gn:population":0,
    "gn:timezone":"Asia/Shanghai",
    "iso:country":"CN",
    "name:und_x_variant":[
        "Ch\u2019ang-hs\u00fc",
        "Changxu"
    ],
    "name:zho_x_preferred":[
        "\u5382\u5729"
    ],
    "wof:name":"Changxu",
    "wof:placetype":"locality"
},
  "geometry": {"coordinates":[108.69799999999999,23.741],"type":"Point"}
}