{
  "type": "Feature",
  "properties": {
    "gn:admin1_code":"26.0",
    "gn:asciiname":"Huapingzinao",
    "gn:country_code":"CN",
    "gn:dem":1057,
    "gn:feature_class":"P",
    "gn:feature_code":"PPL",
    "gn:name":"Huapingzinao",
    "gn:population":0,
    "gn:timezone":"Asia/Shanghai",
    "iso:country":"CN",
    "name:zho_x_preferred":[
        "\u82b1\u74f6\u5b50\u8111"
    ],
    "wof:name":"Huapingzinao",
    "wof:placetype":"locality"
},
  "geometry": {"coordinates":[110.50792,33.60766],"type":"Point"}
}