{
  "type": "Feature",
  "properties": {
    "gn:admin1_code":"32.0",
    "gn:asciiname":"Luoguopu",
    "gn:country_code":"CN",
    "gn:dem":689,
    "gn:feature_class":"P",
    "gn:feature_code":"PPL",
    "gn:name":"Luoguopu",
    "gn:population":0,
    "gn:timezone":"Asia/Shanghai",
    "iso:country":"CN",
    "name:zho_x_preferred":[
        "\u9523\u9505\u94fa"
    ],
    "wof:name":"Luoguopu",
    "wof:placetype":"locality"
},
  "geometry": {"coordinates":[106.90058000000001,30.37862],"type":"Point"}
}