{
  "type": "Feature",
  "properties": {
    "gn:admin1_code":"29.0",
    "gn:asciiname":"Xinguangxin",
    "gn:country_code":"CN",
    "gn:dem":932,
    "gn:feature_class":"P",
    "gn:feature_code":"PPL",
    "gn:name":"Xinguangxin",
    "gn:population":0,
    "gn:timezone":"Asia/Shanghai",
    "iso:country":"CN",
    "name:zho_x_preferred":[
        "\u65b0\u5149\u4fe1"
    ],
    "wof:name":"Xinguangxin",
    "wof:placetype":"locality"
},
  "geometry": {"coordinates":[98.48269999999999,24.4537],"type":"Point"}
}