{
  "type": "Feature",
  "properties": {
    "gn:admin1_code":"30.0",
    "gn:asciiname":"Dajin",
    "gn:country_code":"CN",
    "gn:dem":12,
    "gn:feature_class":"P",
    "gn:feature_code":"PPL",
    "gn:name":"Dajin",
    "gn:population":0,
    "gn:timezone":"Asia/Shanghai",
    "iso:country":"CN",
    "name:zho_x_preferred":[
        "\u5927\u6d25"
    ],
    "wof:name":"Dajin",
    "wof:placetype":"locality"
},
  "geometry": {"coordinates":[112.57431,22.13871],"type":"Point"}
}