{
  "type": "Feature",
  "properties": {
    "gn:admin1_code":"23.0",
    "gn:asciiname":"Hengtangqiao",
    "gn:country_code":"CN",
    "gn:dem":5,
    "gn:feature_class":"P",
    "gn:feature_code":"PPL",
    "gn:name":"Hengtangqiao",
    "gn:population":0,
    "gn:timezone":"Asia/Shanghai",
    "iso:country":"CN",
    "name:und_x_variant":[
        "\u6a2a\u5858\u6865"
    ],
    "wof:name":"Hengtangqiao",
    "wof:placetype":"locality"
},
  "geometry": {"coordinates":[121.28395999999999,31.12715],"type":"Point"}
}