{
  "type": "Feature",
  "properties": {
    "gn:admin1_code":"32.0",
    "gn:asciiname":"Xianfengguan",
    "gn:country_code":"CN",
    "gn:dem":409,
    "gn:feature_class":"P",
    "gn:feature_code":"PPL",
    "gn:name":"Xianfengguan",
    "gn:population":0,
    "gn:timezone":"Asia/Shanghai",
    "iso:country":"CN",
    "name:zho_x_preferred":[
        "\u5148\u950b\u89c2"
    ],
    "wof:name":"Xianfengguan",
    "wof:placetype":"locality"
},
  "geometry": {"coordinates":[106.509,30.6675],"type":"Point"}
}