{
  "type": "Feature",
  "properties": {
    "gn:admin1_code":"5.0",
    "gn:asciiname":"Chuntiancun",
    "gn:country_code":"CN",
    "gn:dem":245,
    "gn:feature_class":"P",
    "gn:feature_code":"PPL",
    "gn:name":"Chuntiancun",
    "gn:population":0,
    "gn:timezone":"Asia/Shanghai",
    "iso:country":"CN",
    "name:zho_x_preferred":[
        "\u6625\u7530\u6751"
    ],
    "wof:name":"Chuntiancun",
    "wof:placetype":"locality"
},
  "geometry": {"coordinates":[127.02363,44.40684],"type":"Point"}
}