{
  "type": "Feature",
  "properties": {
    "gn:admin1_code":"23.0",
    "gn:asciiname":"Jiaotongxu",
    "gn:country_code":"CN",
    "gn:dem":5,
    "gn:feature_class":"P",
    "gn:feature_code":"PPL",
    "gn:name":"Jiaotongxu",
    "gn:population":0,
    "gn:timezone":"Asia/Shanghai",
    "iso:country":"CN",
    "name:zho_x_preferred":[
        "Jiaotongxu"
    ],
    "name:zho_x_variant":[
        "\u4ea4\u901a\u5729"
    ],
    "wof:name":"Jiaotongxu",
    "wof:placetype":"locality"
},
  "geometry": {"coordinates":[121.6671,31.4213],"type":"Point"}
}