{
  "type": "Feature",
  "properties": {
    "gn:admin1_code":"5.0",
    "gn:asciiname":"Nongminhui",
    "gn:country_code":"CN",
    "gn:dem":220,
    "gn:feature_class":"P",
    "gn:feature_code":"PPLF",
    "gn:name":"Nongminhui",
    "gn:population":0,
    "gn:timezone":"Asia/Shanghai",
    "iso:country":"CN",
    "name:zho_x_preferred":[
        "\u519c\u6c11\u4f1a"
    ],
    "wof:name":"Nongminhui",
    "wof:placetype":"locality"
},
  "geometry": {"coordinates":[125.70159,43.58146],"type":"Point"}
}