{
  "type": "Feature",
  "properties": {
    "gn:admin1_code":"3.0",
    "gn:asciiname":"Tanzaiqian",
    "gn:country_code":"CN",
    "gn:dem":203,
    "gn:feature_class":"P",
    "gn:feature_code":"PPL",
    "gn:name":"Tanzaiqian",
    "gn:population":0,
    "gn:timezone":"Asia/Shanghai",
    "iso:country":"CN",
    "name:zho_x_preferred":[
        "\u8c2d\u4ed4\u524d"
    ],
    "wof:name":"Tanzaiqian",
    "wof:placetype":"locality"
},
  "geometry": {"coordinates":[113.88500000000001,27.5147],"type":"Point"}
}