{
  "type": "Feature",
  "properties": {
    "gn:admin1_code":"30.0",
    "gn:asciiname":"Chengping",
    "gn:country_code":"CN",
    "gn:dem":136,
    "gn:feature_class":"P",
    "gn:feature_code":"PPL",
    "gn:name":"Chengping",
    "gn:population":0,
    "gn:timezone":"Asia/Shanghai",
    "iso:country":"CN",
    "name:zho_x_preferred":[
        "\u627f\u5e73"
    ],
    "wof:name":"Chengping",
    "wof:placetype":"locality"
},
  "geometry": {"coordinates":[114.3587,25.15086],"type":"Point"}
}