{
  "type": "Feature",
  "properties": {
    "gn:admin1_code":"25",
    "gn:asciiname":"Tengjiacun",
    "gn:country_code":"CN",
    "gn:dem":16,
    "gn:feature_class":"P",
    "gn:feature_code":"PPL",
    "gn:name":"Tengjiacun",
    "gn:population":0,
    "gn:timezone":"Asia/Shanghai",
    "iso:country":"CN",
    "name:zho_x_preferred":[
        "\u6ed5\u5bb6\u6751"
    ],
    "wof:name":"Tengjiacun",
    "wof:placetype":"locality"
},
  "geometry": {"coordinates":[119.49299999999999,35.4287],"type":"Point"}
}