{
  "type": "Feature",
  "properties": {
    "gn:admin1_code":"31",
    "gn:asciiname":"Baoping",
    "gn:country_code":"CN",
    "gn:dem":68,
    "gn:feature_class":"P",
    "gn:feature_code":"PPL",
    "gn:name":"Baoping",
    "gn:population":0,
    "gn:timezone":"Asia/Shanghai",
    "iso:country":"CN",
    "name:und_x_variant":[
        "Pao-p\u2019ing",
        "Baoping",
        "\u4fdd\u5e73"
    ],
    "wof:name":"Baoping",
    "wof:placetype":"locality"
},
  "geometry": {"coordinates":[108.88688999999999,19.29876],"type":"Point"}
}