{
  "type": "Feature",
  "properties": {
    "gn:admin1_code":"31.0",
    "gn:asciiname":"Bianfang",
    "gn:country_code":"CN",
    "gn:dem":22,
    "gn:feature_class":"P",
    "gn:feature_code":"PPL",
    "gn:name":"Bianfang",
    "gn:population":0,
    "gn:timezone":"Asia/Shanghai",
    "iso:country":"CN",
    "name:zho_x_preferred":[
        "\u8fb9\u574a"
    ],
    "wof:name":"Bianfang",
    "wof:placetype":"locality"
},
  "geometry": {"coordinates":[109.33067,19.66929],"type":"Point"}
}