{
  "type": "Feature",
  "properties": {
    "gn:admin1_code":"11.0",
    "gn:asciiname":"Jindu",
    "gn:country_code":"CN",
    "gn:dem":430,
    "gn:feature_class":"P",
    "gn:feature_code":"PPL",
    "gn:name":"Jindu",
    "gn:population":0,
    "gn:timezone":"Asia/Shanghai",
    "iso:country":"CN",
    "name:zho_x_preferred":[
        "Jindu"
    ],
    "name:zho_x_variant":[
        "\u91d1\u675c"
    ],
    "wof:name":"Jindu",
    "wof:placetype":"locality"
},
  "geometry": {"coordinates":[110.64716,29.37351],"type":"Point"}
}