{
  "type": "Feature",
  "properties": {
    "gn:admin1_code":"5.0",
    "gn:asciiname":"Haolataoge",
    "gn:country_code":"CN",
    "gn:dem":210,
    "gn:feature_class":"P",
    "gn:feature_code":"PPL",
    "gn:name":"Haolataoge",
    "gn:population":0,
    "gn:timezone":"Asia/Shanghai",
    "iso:country":"CN",
    "name:zho_x_preferred":[
        "\u597d\u62c9\u5957\u683c"
    ],
    "wof:name":"Haolataoge",
    "wof:placetype":"locality"
},
  "geometry": {"coordinates":[124.5162,44.56429],"type":"Point"}
}