{
  "type": "Feature",
  "properties": {
    "gn:admin1_code":"02",
    "gn:asciiname":"Shanghuangqiaocun",
    "gn:country_code":"CN",
    "gn:dem":334,
    "gn:feature_class":"P",
    "gn:feature_code":"PPL",
    "gn:name":"Shanghuangqiaocun",
    "gn:population":0,
    "gn:timezone":"Asia/Shanghai",
    "iso:country":"CN",
    "name:und_x_variant":[
        "Shang-huang-ch\u2019iao",
        "Shanghuangqiao",
        "Shanghuangqiaocun"
    ],
    "name:zho_x_preferred":[
        "\u5c1a\u9ec4\u6865"
    ],
    "name:zho_x_variant":[
        "\u5c1a\u9ec4\u6865\u6751"
    ],
    "wof:name":"Shanghuangqiaocun",
    "wof:placetype":"locality"
},
  "geometry": {"coordinates":[120.28229,28.9411],"type":"Point"}
}