{
  "type": "Feature",
  "properties": {
    "gn:admin1_code":"4.0",
    "gn:asciiname":"Magoucun",
    "gn:country_code":"CN",
    "gn:dem":29,
    "gn:feature_class":"P",
    "gn:feature_code":"PPL",
    "gn:name":"Magoucun",
    "gn:population":0,
    "gn:timezone":"Asia/Shanghai",
    "iso:country":"CN",
    "name:zho_x_preferred":[
        "\u9ebb\u6c9f\u6751"
    ],
    "wof:name":"Magoucun",
    "wof:placetype":"locality"
},
  "geometry": {"coordinates":[117.52831999999999,34.29852],"type":"Point"}
}