{
  "type": "Feature",
  "properties": {
    "gn:admin1_code":"7",
    "gn:asciiname":"Chengbian",
    "gn:country_code":"CN",
    "gn:dem":14,
    "gn:feature_class":"P",
    "gn:feature_code":"PPL",
    "gn:name":"Chengbian",
    "gn:population":0,
    "gn:timezone":"Asia/Shanghai",
    "iso:country":"CN",
    "name:und_x_variant":[
        "Ch\u2019eng-pien",
        "Chengbian"
    ],
    "name:zho_x_preferred":[
        "\u57d5\u8fb9"
    ],
    "wof:name":"Chengbian",
    "wof:placetype":"locality"
},
  "geometry": {"coordinates":[119.56435999999999,25.54325],"type":"Point"}
}