{
  "type": "Feature",
  "properties": {
    "gn:admin1_code":"15.0",
    "gn:asciiname":"Wujia Buzi",
    "gn:country_code":"CN",
    "gn:dem":1267,
    "gn:feature_class":"P",
    "gn:feature_code":"PPL",
    "gn:name":"Wujia Buzi",
    "gn:population":0,
    "gn:timezone":"Asia/Shanghai",
    "iso:country":"CN",
    "name:zho_x_preferred":[
        "\u5434\u5bb6\u5821\u5b50"
    ],
    "wof:name":"Wujia Buzi",
    "wof:placetype":"locality"
},
  "geometry": {"coordinates":[106.96899999999999,35.6913],"type":"Point"}
}