{
  "type": "Feature",
  "properties": {
    "gn:admin1_code":"29.0",
    "gn:asciiname":"Lebaidi",
    "gn:country_code":"CN",
    "gn:dem":1870,
    "gn:feature_class":"P",
    "gn:feature_code":"PPL",
    "gn:name":"Lebaidi",
    "gn:population":0,
    "gn:timezone":"Asia/Shanghai",
    "iso:country":"CN",
    "name:zho_x_preferred":[
        "\u4e50\u767d\u5730"
    ],
    "wof:name":"Lebaidi",
    "wof:placetype":"locality"
},
  "geometry": {"coordinates":[104.569,26.2985],"type":"Point"}
}