{
  "type": "Feature",
  "properties": {
    "gn:admin1_code":"4.0",
    "gn:asciiname":"Jiangzhuangcun",
    "gn:country_code":"CN",
    "gn:dem":28,
    "gn:feature_class":"P",
    "gn:feature_code":"PPL",
    "gn:name":"Jiangzhuangcun",
    "gn:population":0,
    "gn:timezone":"Asia/Shanghai",
    "iso:country":"CN",
    "name:und_x_variant":[
        "Jiangzhuang",
        "Jiangzhuangcun"
    ],
    "name:zho_x_preferred":[
        "\u59dc\u5e84"
    ],
    "name:zho_x_variant":[
        "\u59dc\u5e84\u6751"
    ],
    "wof:name":"Jiangzhuangcun",
    "wof:placetype":"locality"
},
  "geometry": {"coordinates":[118.68012,34.57568],"type":"Point"}
}