{
  "type": "Feature",
  "properties": {
    "gn:admin1_code":"10",
    "gn:asciiname":"Huangdipu",
    "gn:cc2":"CN",
    "gn:country_code":"CN",
    "gn:dem":11,
    "gn:feature_class":"P",
    "gn:feature_code":"PPL",
    "gn:name":"Huangdipu",
    "gn:population":0,
    "gn:timezone":"Asia/Shanghai",
    "iso:country":"CN",
    "name:und_x_variant":[
        "Huang-ti-p\u2019u",
        "Huangdipu"
    ],
    "wof:name":"Huangdipu",
    "wof:placetype":"locality"
},
  "geometry": {"coordinates":[116.66667,38.23333],"type":"Point"}
}