{
  "type": "Feature",
  "properties": {
    "gn:admin1_code":"1.0",
    "gn:asciiname":"Niuduwancun",
    "gn:country_code":"CN",
    "gn:dem":28,
    "gn:feature_class":"P",
    "gn:feature_code":"PPL",
    "gn:name":"Niuduwancun",
    "gn:population":0,
    "gn:timezone":"Asia/Shanghai",
    "iso:country":"CN",
    "name:zho_x_preferred":[
        "\u725b\u728a\u6e7e\u6751"
    ],
    "wof:name":"Niuduwancun",
    "wof:placetype":"locality"
},
  "geometry": {"coordinates":[116.3515,32.57349],"type":"Point"}
}