{
  "type": "Feature",
  "properties": {
    "gn:admin1_code":"8.0",
    "gn:asciiname":"Mengdehe",
    "gn:country_code":"CN",
    "gn:dem":476,
    "gn:feature_class":"P",
    "gn:feature_code":"PPL",
    "gn:name":"Mengdehe",
    "gn:population":0,
    "gn:timezone":"Asia/Shanghai",
    "iso:country":"CN",
    "name:und_x_variant":[
        "\u5b5f\u5fb7\u6cb3"
    ],
    "wof:name":"Mengdehe",
    "wof:placetype":"locality"
},
  "geometry": {"coordinates":[126.25073999999999,49.88267000000001],"type":"Point"}
}