{
  "type": "Feature",
  "properties": {
    "gn:admin1_code":"29.0",
    "gn:asciiname":"Lawo",
    "gn:country_code":"CN",
    "gn:dem":1795,
    "gn:feature_class":"P",
    "gn:feature_code":"PPL",
    "gn:name":"Lawo",
    "gn:population":0,
    "gn:timezone":"Asia/Shanghai",
    "iso:country":"CN",
    "name:zho_x_preferred":[
        "\u814a\u7a9d"
    ],
    "wof:name":"Lawo",
    "wof:placetype":"locality"
},
  "geometry": {"coordinates":[104.09999999999999,23.3319],"type":"Point"}
}