{
  "type": "Feature",
  "properties": {
    "gn:admin1_code":"16.0",
    "gn:asciiname":"Mawu",
    "gn:country_code":"CN",
    "gn:dem":48,
    "gn:feature_class":"P",
    "gn:feature_code":"PPL",
    "gn:name":"Mawu",
    "gn:population":0,
    "gn:timezone":"Asia/Shanghai",
    "iso:country":"CN",
    "name:bul_x_preferred":[
        "\u041c\u0430\u0432\u0443"
    ],
    "name:fin_x_preferred":[
        "Mawu"
    ],
    "name:fra_x_preferred":[
        "Mawu"
    ],
    "name:nld_x_preferred":[
        "Mawu"
    ],
    "name:por_x_preferred":[
        "Mawu"
    ],
    "name:slv_x_preferred":[
        "Mawu"
    ],
    "name:swe_x_preferred":[
        "Mawu"
    ],
    "name:tur_x_preferred":[
        "Mawu"
    ],
    "name:zho_x_preferred":[
        "\u9a6c\u5c4b"
    ],
    "wof:name":"Mawu",
    "wof:placetype":"locality"
},
  "geometry": {"coordinates":[109.476,22.0583],"type":"Point"}
}