{
  "type": "Feature",
  "properties": {
    "gn:admin1_code":"9.0",
    "gn:asciiname":"Shitan Hekou",
    "gn:country_code":"CN",
    "gn:dem":661,
    "gn:feature_class":"P",
    "gn:feature_code":"PPL",
    "gn:name":"Shitan Hekou",
    "gn:population":0,
    "gn:timezone":"Asia/Shanghai",
    "iso:country":"CN",
    "name:zho_x_preferred":[
        "\u77f3\u70ad\u6cb3\u53e3"
    ],
    "wof:name":"Shitan Hekou",
    "wof:placetype":"locality"
},
  "geometry": {"coordinates":[110.78637000000001,33.97503],"type":"Point"}
}