{
  "type": "Feature",
  "properties": {
    "gn:admin1_code":"25",
    "gn:asciiname":"Mazhenguang Yicun",
    "gn:country_code":"CN",
    "gn:dem":9,
    "gn:feature_class":"P",
    "gn:feature_code":"PPL",
    "gn:name":"Mazhenguang Yicun",
    "gn:population":0,
    "gn:timezone":"Asia/Shanghai",
    "iso:country":"CN",
    "name:zho_x_preferred":[
        "\u9a6c\u9547\u5e7f\u4e00\u6751"
    ],
    "wof:name":"Mazhenguang Yicun",
    "wof:placetype":"locality"
},
  "geometry": {"coordinates":[118.22199999999999,37.6323],"type":"Point"}
}