{
  "type": "Feature",
  "properties": {
    "gn:admin1_code":"32.0",
    "gn:asciiname":"Zhuojigengba",
    "gn:country_code":"CN",
    "gn:dem":4117,
    "gn:feature_class":"P",
    "gn:feature_code":"PPL",
    "gn:name":"Zhuojigengba",
    "gn:population":0,
    "gn:timezone":"Asia/Shanghai",
    "iso:country":"CN",
    "name:zho_x_preferred":[
        "\u5353\u57fa\u66f4\u5df4"
    ],
    "wof:name":"Zhuojigengba",
    "wof:placetype":"locality"
},
  "geometry": {"coordinates":[100.43744,31.23506],"type":"Point"}
}