{
  "type": "Feature",
  "properties": {
    "gn:admin1_code":"11.0",
    "gn:asciiname":"Huangmingxi",
    "gn:country_code":"CN",
    "gn:dem":623,
    "gn:feature_class":"P",
    "gn:feature_code":"PPL",
    "gn:name":"Huangmingxi",
    "gn:population":0,
    "gn:timezone":"Asia/Shanghai",
    "iso:country":"CN",
    "name:zho_x_preferred":[
        "\u9ec4\u660e\u6eaa"
    ],
    "wof:name":"Huangmingxi",
    "wof:placetype":"locality"
},
  "geometry": {"coordinates":[110.48098,28.81368],"type":"Point"}
}