{
  "type": "Feature",
  "properties": {
    "gn:admin1_code":"19.0",
    "gn:asciiname":"Moujiatun",
    "gn:country_code":"CN",
    "gn:dem":12,
    "gn:feature_class":"P",
    "gn:feature_code":"PPL",
    "gn:name":"Moujiatun",
    "gn:population":0,
    "gn:timezone":"Asia/Shanghai",
    "iso:country":"CN",
    "name:zho_x_preferred":[
        "\u725f\u5bb6\u5c6f"
    ],
    "wof:name":"Moujiatun",
    "wof:placetype":"locality"
},
  "geometry": {"coordinates":[123.70399999999999,39.8783],"type":"Point"}
}