{
  "type": "Feature",
  "properties": {
    "gn:admin1_code":"18.0",
    "gn:asciiname":"Liangka",
    "gn:country_code":"CN",
    "gn:dem":1049,
    "gn:feature_class":"P",
    "gn:feature_code":"PPL",
    "gn:name":"Liangka",
    "gn:population":0,
    "gn:timezone":"Asia/Shanghai",
    "iso:country":"CN",
    "name:zho_x_preferred":[
        "\u4e24\u5361"
    ],
    "wof:name":"Liangka",
    "wof:placetype":"locality"
},
  "geometry": {"coordinates":[107.67400000000001,26.5358],"type":"Point"}
}