{
  "type": "Feature",
  "properties": {
    "gn:admin1_code":"29.0",
    "gn:asciiname":"Magela",
    "gn:country_code":"CN",
    "gn:dem":3335,
    "gn:feature_class":"P",
    "gn:feature_code":"PPL",
    "gn:name":"Magela",
    "gn:population":0,
    "gn:timezone":"Asia/Shanghai",
    "iso:country":"CN",
    "name:zho_x_preferred":[
        "\u9a6c\u683c\u62c9"
    ],
    "wof:name":"Magela",
    "wof:placetype":"locality"
},
  "geometry": {"coordinates":[98.9384,27.5461],"type":"Point"}
}