{
  "type": "Feature",
  "properties": {
    "gn:admin1_code":"19.0",
    "gn:asciiname":"Gangjiabu",
    "gn:country_code":"CN",
    "gn:dem":127,
    "gn:feature_class":"P",
    "gn:feature_code":"PPL",
    "gn:name":"Gangjiabu",
    "gn:population":0,
    "gn:timezone":"Asia/Shanghai",
    "iso:country":"CN",
    "name:zho_x_preferred":[
        "\u521a\u5bb6\u5821"
    ],
    "wof:name":"Gangjiabu",
    "wof:placetype":"locality"
},
  "geometry": {"coordinates":[122.59099999999999,39.9851],"type":"Point"}
}