{
  "type": "Feature",
  "properties": {
    "gn:admin1_code":"24.0",
    "gn:asciiname":"Xiyaozhuangcun",
    "gn:country_code":"CN",
    "gn:dem":526,
    "gn:feature_class":"P",
    "gn:feature_code":"PPL",
    "gn:name":"Xiyaozhuangcun",
    "gn:population":0,
    "gn:timezone":"Asia/Shanghai",
    "iso:country":"CN",
    "name:zho_x_preferred":[
        "\u897f\u59da\u5e84\u6751"
    ],
    "wof:name":"Xiyaozhuangcun",
    "wof:placetype":"locality"
},
  "geometry": {"coordinates":[110.86202,35.22112],"type":"Point"}
}