{
  "type": "Feature",
  "properties": {
    "gn:admin1_code":"30.0",
    "gn:asciiname":"Tianliao Xincun",
    "gn:country_code":"CN",
    "gn:dem":0,
    "gn:feature_class":"P",
    "gn:feature_code":"PPL",
    "gn:name":"Tianliao Xincun",
    "gn:population":0,
    "gn:timezone":"Asia/Shanghai",
    "iso:country":"CN",
    "name:zho_x_preferred":[
        "\u7530\u5bee\u65b0\u6751"
    ],
    "wof:name":"Tianliao Xincun",
    "wof:placetype":"locality"
},
  "geometry": {"coordinates":[113.05755000000001,22.32223],"type":"Point"}
}