{
  "type": "Feature",
  "properties": {
    "gn:admin1_code":"14.0",
    "gn:asciiname":"Zhuobucun",
    "gn:country_code":"CN",
    "gn:dem":4807,
    "gn:feature_class":"P",
    "gn:feature_code":"PPL",
    "gn:name":"Zhuobucun",
    "gn:population":0,
    "gn:timezone":"Asia/Urumqi",
    "iso:country":"CN",
    "name:zho_x_preferred":[
        "\u5353\u5e03\u6751"
    ],
    "wof:name":"Zhuobucun",
    "wof:placetype":"locality"
},
  "geometry": {"coordinates":[92.51642,32.14015999999999],"type":"Point"}
}