{
  "type": "Feature",
  "properties": {
    "gn:admin1_code":"5.0",
    "gn:asciiname":"Yongchangcun",
    "gn:country_code":"CN",
    "gn:dem":320,
    "gn:feature_class":"P",
    "gn:feature_code":"PPL",
    "gn:name":"Yongchangcun",
    "gn:population":0,
    "gn:timezone":"Asia/Shanghai",
    "iso:country":"CN",
    "name:zho_x_preferred":[
        "\u6c38\u957f\u6751"
    ],
    "wof:name":"Yongchangcun",
    "wof:placetype":"locality"
},
  "geometry": {"coordinates":[125.88670999999999,42.49453],"type":"Point"}
}