{
  "type": "Feature",
  "properties": {
    "gn:admin1_code":"26.0",
    "gn:asciiname":"Caowan Goucun",
    "gn:country_code":"CN",
    "gn:dem":1025,
    "gn:feature_class":"P",
    "gn:feature_code":"PPL",
    "gn:name":"Caowan Goucun",
    "gn:population":0,
    "gn:timezone":"Asia/Shanghai",
    "iso:country":"CN",
    "name:zho_x_preferred":[
        "\u8349\u6e7e\u6c9f\u6751"
    ],
    "wof:name":"Caowan Goucun",
    "wof:placetype":"locality"
},
  "geometry": {"coordinates":[110.22199999999999,38.5662],"type":"Point"}
}