{
  "type": "Feature",
  "properties": {
    "gn:admin1_code":"15.0",
    "gn:asciiname":"Haizitan",
    "gn:country_code":"CN",
    "gn:dem":1821,
    "gn:feature_class":"P",
    "gn:feature_code":"PPL",
    "gn:name":"Haizitan",
    "gn:population":0,
    "gn:timezone":"Asia/Shanghai",
    "iso:country":"CN",
    "name:zho_x_preferred":[
        "\u6d77\u5b50\u6ee9"
    ],
    "wof:name":"Haizitan",
    "wof:placetype":"locality"
},
  "geometry": {"coordinates":[104.819,36.9127],"type":"Point"}
}