{
  "type": "Feature",
  "properties": {
    "gn:admin1_code":"19.0",
    "gn:asciiname":"Sankuaishi Linchang",
    "gn:country_code":"CN",
    "gn:dem":390,
    "gn:feature_class":"P",
    "gn:feature_code":"PPLF",
    "gn:name":"Sankuaishi Linchang",
    "gn:population":0,
    "gn:timezone":"Asia/Shanghai",
    "iso:country":"CN",
    "name:und_x_variant":[
        "Sankuaishi Linchang Gongqu",
        "\u4e09\u5757\u77f3\u6797\u573a\u5de5\u533a",
        "Sankuaishi Linchang",
        "\u4e09\u5757\u77f3\u6797\u573a"
    ],
    "name:zho_x_preferred":[
        "\u4e09\u5757\u77f3\u6797\u573a\u5de5\u533a"
    ],
    "wof:name":"Sankuaishi Linchang",
    "wof:placetype":"locality"
},
  "geometry": {"coordinates":[124.39346999999999,41.70399000000001],"type":"Point"}
}