{
  "type": "Feature",
  "properties": {
    "gn:admin1_code":"30.0",
    "gn:asciiname":"Tieshanyangcun",
    "gn:country_code":"CN",
    "gn:dem":9,
    "gn:feature_class":"P",
    "gn:feature_code":"PPL",
    "gn:name":"Tieshanyangcun",
    "gn:population":0,
    "gn:timezone":"Asia/Shanghai",
    "iso:country":"CN",
    "name:zho_x_preferred":[
        "\u94c1\u5c71\u6d0b\u6751"
    ],
    "wof:name":"Tieshanyangcun",
    "wof:placetype":"locality"
},
  "geometry": {"coordinates":[116.18611,23.35315],"type":"Point"}
}