{
  "type": "Feature",
  "properties": {
    "gn:admin1_code":"01",
    "gn:asciiname":"Qingshui",
    "gn:country_code":"CN",
    "gn:dem":10,
    "gn:feature_class":"P",
    "gn:feature_code":"PPLA4",
    "gn:name":"Qingshui",
    "gn:population":0,
    "gn:timezone":"Asia/Shanghai",
    "iso:country":"CN",
    "name:ceb_x_preferred":[
        "Qingshui"
    ],
    "name:deu_x_preferred":[
        "Qingshui"
    ],
    "name:und_x_variant":[
        "Ch\u2019ing-shui-ho",
        "Qingshuizhen",
        "Ch\u2019ing-shui-chen",
        "Qingshui Jiedao",
        "\u6e05\u6c34\u8857\u9053",
        "Qingshui"
    ],
    "name:zho_x_preferred":[
        "\u6e05\u6c34"
    ],
    "wof:name":"Qingshui",
    "wof:placetype":"locality"
},
  "geometry": {"coordinates":[118.47743,31.3181],"type":"Point"}
}