{
  "type": "Feature",
  "properties": {
    "gn:admin1_code":"2.0",
    "gn:asciiname":"Shiliao",
    "gn:country_code":"CN",
    "gn:dem":5,
    "gn:feature_class":"P",
    "gn:feature_code":"PPL",
    "gn:name":"Shiliao",
    "gn:population":0,
    "gn:timezone":"Asia/Shanghai",
    "iso:country":"CN",
    "name:zho_x_preferred":[
        "\u77f3\u5bee"
    ],
    "wof:name":"Shiliao",
    "wof:placetype":"locality"
},
  "geometry": {"coordinates":[120.71581,30.66691],"type":"Point"}
}