{
  "type": "Feature",
  "properties": {
    "gn:admin1_code":"32.0",
    "gn:asciiname":"Tangjiagou",
    "gn:country_code":"CN",
    "gn:dem":328,
    "gn:feature_class":"P",
    "gn:feature_code":"PPL",
    "gn:name":"Tangjiagou",
    "gn:population":0,
    "gn:timezone":"Asia/Shanghai",
    "iso:country":"CN",
    "name:zho_x_preferred":[
        "\u5510\u5bb6\u6c9f"
    ],
    "wof:name":"Tangjiagou",
    "wof:placetype":"locality"
},
  "geometry": {"coordinates":[106.367,30.9275],"type":"Point"}
}