{
  "type": "Feature",
  "properties": {
    "gn:admin1_code":"4.0",
    "gn:asciiname":"Tanjiacun",
    "gn:country_code":"CN",
    "gn:dem":8,
    "gn:feature_class":"P",
    "gn:feature_code":"PPL",
    "gn:name":"Tanjiacun",
    "gn:population":0,
    "gn:timezone":"Asia/Shanghai",
    "iso:country":"CN",
    "name:zho_x_preferred":[
        "\u63a2\u9a7e\u6751"
    ],
    "wof:name":"Tanjiacun",
    "wof:placetype":"locality"
},
  "geometry": {"coordinates":[118.70532,34.25787],"type":"Point"}
}