{
  "type": "Feature",
  "properties": {
    "gn:admin1_code":"24",
    "gn:asciiname":"Langzhai",
    "gn:country_code":"CN",
    "gn:dem":824,
    "gn:feature_class":"P",
    "gn:feature_code":"PPL",
    "gn:name":"Langzhai",
    "gn:population":0,
    "gn:timezone":"Asia/Shanghai",
    "iso:country":"CN",
    "name:und_x_variant":[
        "Lang-chai",
        "Langzhai"
    ],
    "name:zho_x_preferred":[
        "\u90ce\u5be8"
    ],
    "wof:name":"Langzhai",
    "wof:placetype":"locality"
},
  "geometry": {"coordinates":[112.32034,35.96064000000001],"type":"Point"}
}