{
  "type": "Feature",
  "properties": {
    "gn:admin1_code":"26.0",
    "gn:asciiname":"Taoyuangou",
    "gn:country_code":"CN",
    "gn:dem":748,
    "gn:feature_class":"P",
    "gn:feature_code":"PPL",
    "gn:name":"Taoyuangou",
    "gn:population":0,
    "gn:timezone":"Asia/Shanghai",
    "iso:country":"CN",
    "name:zho_x_preferred":[
        "\u6843\u56ed\u6c9f"
    ],
    "wof:name":"Taoyuangou",
    "wof:placetype":"locality"
},
  "geometry": {"coordinates":[109.88212,33.31091],"type":"Point"}
}