{
  "type": "Feature",
  "properties": {
    "gn:admin1_code":"33.0",
    "gn:asciiname":"Datan",
    "gn:country_code":"CN",
    "gn:dem":596,
    "gn:feature_class":"P",
    "gn:feature_code":"PPL",
    "gn:name":"Datan",
    "gn:population":0,
    "gn:timezone":"Asia/Shanghai",
    "iso:country":"CN",
    "name:zho_x_preferred":[
        "\u5927\u6ee9"
    ],
    "wof:name":"Datan",
    "wof:placetype":"locality"
},
  "geometry": {"coordinates":[108.83662,29.14462],"type":"Point"}
}