{
  "type": "Feature",
  "properties": {
    "gn:admin1_code":"4.0",
    "gn:asciiname":"Caoducun",
    "gn:country_code":"CN",
    "gn:dem":25,
    "gn:feature_class":"P",
    "gn:feature_code":"PPL",
    "gn:name":"Caoducun",
    "gn:population":0,
    "gn:timezone":"Asia/Shanghai",
    "iso:country":"CN",
    "name:zho_x_preferred":[
        "\u66f9\u6e21\u6751"
    ],
    "wof:name":"Caoducun",
    "wof:placetype":"locality"
},
  "geometry": {"coordinates":[118.57349000000001,33.74652],"type":"Point"}
}