{
  "type": "Feature",
  "properties": {
    "gn:admin1_code":"15.0",
    "gn:asciiname":"Pinghetang",
    "gn:country_code":"CN",
    "gn:dem":2328,
    "gn:feature_class":"P",
    "gn:feature_code":"PPL",
    "gn:name":"Pinghetang",
    "gn:population":0,
    "gn:timezone":"Asia/Shanghai",
    "iso:country":"CN",
    "name:zho_x_preferred":[
        "\u5e73\u548c\u5802"
    ],
    "wof:name":"Pinghetang",
    "wof:placetype":"locality"
},
  "geometry": {"coordinates":[104.449,36.1188],"type":"Point"}
}