{
  "type": "Feature",
  "properties": {
    "gn:admin1_code":"26",
    "gn:asciiname":"Liujiawan",
    "gn:country_code":"CN",
    "gn:dem":658,
    "gn:feature_class":"P",
    "gn:feature_code":"PPL",
    "gn:name":"Liujiawan",
    "gn:population":0,
    "gn:timezone":"Asia/Shanghai",
    "iso:country":"CN",
    "wof:name":"Liujiawan",
    "wof:placetype":"locality"
},
  "geometry": {"coordinates":[110.72972,33.61139],"type":"Point"}
}