{
  "type": "Feature",
  "properties": {
    "gn:admin1_code":"10",
    "gn:asciiname":"Caoniangou",
    "gn:country_code":"CN",
    "gn:dem":1561,
    "gn:feature_class":"P",
    "gn:feature_code":"PPL",
    "gn:name":"Caoniangou",
    "gn:population":0,
    "gn:timezone":"Asia/Shanghai",
    "iso:country":"CN",
    "name:zho_x_preferred":[
        "\u69fd\u78be\u6c9f"
    ],
    "wof:name":"Caoniangou",
    "wof:placetype":"locality"
},
  "geometry": {"coordinates":[114.3058,41.08073],"type":"Point"}
}