{
  "type": "Feature",
  "properties": {
    "gn:admin1_code":"33.0",
    "gn:asciiname":"Shanpingshang",
    "gn:country_code":"CN",
    "gn:dem":928,
    "gn:feature_class":"P",
    "gn:feature_code":"PPL",
    "gn:name":"Shanpingshang",
    "gn:population":0,
    "gn:timezone":"Asia/Shanghai",
    "iso:country":"CN",
    "name:zho_x_preferred":[
        "\u5c71\u576a\u4e0a"
    ],
    "wof:name":"Shanpingshang",
    "wof:placetype":"locality"
},
  "geometry": {"coordinates":[106.697,28.514],"type":"Point"}
}