{
  "type": "Feature",
  "properties": {
    "gn:admin1_code":"32.0",
    "gn:asciiname":"Luoliucun",
    "gn:country_code":"CN",
    "gn:dem":3526,
    "gn:feature_class":"P",
    "gn:feature_code":"PPL",
    "gn:name":"Luoliucun",
    "gn:population":0,
    "gn:timezone":"Asia/Shanghai",
    "iso:country":"CN",
    "name:zho_x_preferred":[
        "\u6d1b\u516d\u6751"
    ],
    "wof:name":"Luoliucun",
    "wof:placetype":"locality"
},
  "geometry": {"coordinates":[100.033,30.7892],"type":"Point"}
}