{
  "type": "Feature",
  "properties": {
    "gn:admin1_code":"32.0",
    "gn:asciiname":"Sishuizha",
    "gn:country_code":"CN",
    "gn:dem":2936,
    "gn:feature_class":"P",
    "gn:feature_code":"PPL",
    "gn:name":"Sishuizha",
    "gn:population":0,
    "gn:timezone":"Asia/Shanghai",
    "iso:country":"CN",
    "name:zho_x_preferred":[
        "\u56db\u6c34\u95f8"
    ],
    "wof:name":"Sishuizha",
    "wof:placetype":"locality"
},
  "geometry": {"coordinates":[102.84031,31.52476],"type":"Point"}
}