{
  "type": "Feature",
  "properties": {
    "gn:admin1_code":"16.0",
    "gn:asciiname":"Longfei",
    "gn:country_code":"CN",
    "gn:dem":391,
    "gn:feature_class":"P",
    "gn:feature_code":"PPL",
    "gn:name":"Longfei",
    "gn:population":0,
    "gn:timezone":"Asia/Shanghai",
    "iso:country":"CN",
    "name:zho_x_preferred":[
        "\u9647\u80a5"
    ],
    "wof:name":"Longfei",
    "wof:placetype":"locality"
},
  "geometry": {"coordinates":[106.81999999999999,22.5811],"type":"Point"}
}