{
  "type": "Feature",
  "properties": {
    "gn:admin1_code":"4.0",
    "gn:asciiname":"Yanxu",
    "gn:country_code":"CN",
    "gn:dem":6,
    "gn:feature_class":"P",
    "gn:feature_code":"PPL",
    "gn:name":"Yanxu",
    "gn:population":0,
    "gn:timezone":"Asia/Shanghai",
    "iso:country":"CN",
    "name:und_x_variant":[
        "\u4e25\u5f90"
    ],
    "name:zho_x_preferred":[
        "\u4e25\u5f90"
    ],
    "wof:name":"Yanxu",
    "wof:placetype":"locality"
},
  "geometry": {"coordinates":[120.17057,32.28803],"type":"Point"}
}