{
  "type": "Feature",
  "properties": {
    "gn:admin1_code":"31.0",
    "gn:asciiname":"Zhongliao",
    "gn:country_code":"CN",
    "gn:dem":29,
    "gn:feature_class":"P",
    "gn:feature_code":"PPL",
    "gn:name":"Zhongliao",
    "gn:population":0,
    "gn:timezone":"Asia/Shanghai",
    "iso:country":"CN",
    "name:deu_x_preferred":[
        "Zhongliao"
    ],
    "name:hak_x_preferred":[
        "Ch\u00fbng-li\u00e0u-hi\u00f4ng"
    ],
    "name:jpn_x_preferred":[
        "\u4e2d\u5bee\u90f7"
    ],
    "name:kor_x_preferred":[
        "\uc911\ub7b4\uc624\ud5a5"
    ],
    "name:pol_x_preferred":[
        "Zhongliao"
    ],
    "name:vie_x_preferred":[
        "Trung Li\u00eau"
    ],
    "name:zho_x_preferred":[
        "\u4e2d\u5ed6"
    ],
    "name:zho_x_variant":[
        "\u4e2d\u5bee\u9109"
    ],
    "wof:name":"Zhongliao",
    "wof:placetype":"locality"
},
  "geometry": {"coordinates":[109.62988,18.33246],"type":"Point"}
}