{
  "type": "Feature",
  "properties": {
    "gn:admin1_code":"18",
    "gn:asciiname":"Xiaohongzhai",
    "gn:country_code":"CN",
    "gn:dem":1341,
    "gn:feature_class":"P",
    "gn:feature_code":"PPL",
    "gn:name":"Xiaohongzhai",
    "gn:population":0,
    "gn:timezone":"Asia/Shanghai",
    "iso:country":"CN",
    "name:zho_x_preferred":[
        "\u5c0f\u6d2a\u5be8"
    ],
    "wof:name":"Xiaohongzhai",
    "wof:placetype":"locality"
},
  "geometry": {"coordinates":[106.541,27.0556],"type":"Point"}
}