{
  "type": "Feature",
  "properties": {
    "gn:admin1_code":"31.0",
    "gn:asciiname":"Yachong",
    "gn:country_code":"CN",
    "gn:dem":230,
    "gn:feature_class":"P",
    "gn:feature_code":"PPL",
    "gn:name":"Yachong",
    "gn:population":0,
    "gn:timezone":"Asia/Shanghai",
    "iso:country":"CN",
    "name:und_x_variant":[
        "\u7259\u51b2"
    ],
    "wof:name":"Yachong",
    "wof:placetype":"locality"
},
  "geometry": {"coordinates":[109.41916999999999,18.79726],"type":"Point"}
}