{
  "type": "Feature",
  "properties": {
    "gn:admin1_code":"30.0",
    "gn:asciiname":"Zhouwu",
    "gn:country_code":"CN",
    "gn:dem":221,
    "gn:feature_class":"P",
    "gn:feature_code":"PPL",
    "gn:name":"Zhouwu",
    "gn:population":0,
    "gn:timezone":"Asia/Shanghai",
    "iso:country":"CN",
    "name:zho_x_preferred":[
        "Zhouwu"
    ],
    "name:zho_x_variant":[
        "\u5468\u5c4b"
    ],
    "wof:name":"Zhouwu",
    "wof:placetype":"locality"
},
  "geometry": {"coordinates":[115.13611000000002,24.6175],"type":"Point"}
}