{
  "type": "Feature",
  "properties": {
    "gn:admin1_code":"16",
    "gn:asciiname":"Maoping",
    "gn:country_code":"CN",
    "gn:dem":490,
    "gn:feature_class":"P",
    "gn:feature_code":"PPL",
    "gn:name":"Maoping",
    "gn:population":0,
    "gn:timezone":"Asia/Shanghai",
    "iso:country":"CN",
    "name:ceb_x_preferred":[
        "Maoping"
    ],
    "name:deu_x_preferred":[
        "Maoping"
    ],
    "name:swe_x_preferred":[
        "Maoping"
    ],
    "name:zho_x_preferred":[
        "\u8305\u576a"
    ],
    "wof:name":"Maoping",
    "wof:placetype":"locality"
},
  "geometry": {"coordinates":[110.625,24.3556],"type":"Point"}
}