{
  "type": "Feature",
  "properties": {
    "gn:admin1_code":"1.0",
    "gn:asciiname":"Chaoshancun",
    "gn:country_code":"CN",
    "gn:dem":33,
    "gn:feature_class":"P",
    "gn:feature_code":"PPL",
    "gn:name":"Chaoshancun",
    "gn:population":0,
    "gn:timezone":"Asia/Shanghai",
    "iso:country":"CN",
    "name:zho_x_preferred":[
        "\u671d\u5c71\u6751"
    ],
    "wof:name":"Chaoshancun",
    "wof:placetype":"locality"
},
  "geometry": {"coordinates":[117.89466000000002,30.91599],"type":"Point"}
}