{
  "type": "Feature",
  "properties": {
    "gn:admin1_code":"29.0",
    "gn:asciiname":"Dashuijing",
    "gn:country_code":"CN",
    "gn:dem":1849,
    "gn:feature_class":"P",
    "gn:feature_code":"PPL",
    "gn:name":"Dashuijing",
    "gn:population":0,
    "gn:timezone":"Asia/Shanghai",
    "iso:country":"CN",
    "name:zho_x_preferred":[
        "\u5927\u6c34\u4e95"
    ],
    "wof:name":"Dashuijing",
    "wof:placetype":"locality"
},
  "geometry": {"coordinates":[103.10599999999999,26.5216],"type":"Point"}
}