{
  "type": "Feature",
  "properties": {
    "gn:admin1_code":"30",
    "gn:asciiname":"Jinchetian",
    "gn:country_code":"CN",
    "gn:dem":496,
    "gn:feature_class":"P",
    "gn:feature_code":"PPL",
    "gn:name":"Jinchetian",
    "gn:population":0,
    "gn:timezone":"Asia/Shanghai",
    "iso:country":"CN",
    "name:zho_x_preferred":[
        "\u91d1\u8f66\u7530"
    ],
    "wof:name":"Jinchetian",
    "wof:placetype":"locality"
},
  "geometry": {"coordinates":[116.37025,23.6983],"type":"Point"}
}