{
  "type": "Feature",
  "properties": {
    "gn:admin1_code":"19",
    "gn:asciiname":"Donglaotaichaoxianzuxiang",
    "gn:cc2":"CN",
    "gn:country_code":"CN",
    "gn:dem":243,
    "gn:feature_class":"P",
    "gn:feature_code":"PPL",
    "gn:name":"Donglaotaichaoxianzuxiang",
    "gn:population":0,
    "gn:timezone":"Asia/Shanghai",
    "iso:country":"CN",
    "name:und_x_variant":[
        "Tung-lao-t\u2019ai",
        "Donglaotaichaoxianzuxiang"
    ],
    "wof:name":"Donglaotaichaoxianzuxiang",
    "wof:placetype":"locality"
},
  "geometry": {"coordinates":[125.33611000000001,41.30056],"type":"Point"}
}