{
  "type": "Feature",
  "properties": {
    "gn:admin1_code":"11.0",
    "gn:asciiname":"Nianyuxing",
    "gn:country_code":"CN",
    "gn:dem":85,
    "gn:feature_class":"P",
    "gn:feature_code":"PPL",
    "gn:name":"Nianyuxing",
    "gn:population":0,
    "gn:timezone":"Asia/Shanghai",
    "iso:country":"CN",
    "name:zho_x_preferred":[
        "\u9c87\u9c7c\u5f62"
    ],
    "wof:name":"Nianyuxing",
    "wof:placetype":"locality"
},
  "geometry": {"coordinates":[112.16767,28.72236],"type":"Point"}
}