{
  "type": "Feature",
  "properties": {
    "gn:admin1_code":"19.0",
    "gn:asciiname":"Nanweizi",
    "gn:country_code":"CN",
    "gn:dem":204,
    "gn:feature_class":"P",
    "gn:feature_code":"PPL",
    "gn:name":"Nanweizi",
    "gn:population":0,
    "gn:timezone":"Asia/Shanghai",
    "iso:country":"CN",
    "name:und_x_variant":[
        "\u5357\u9688\u5b50"
    ],
    "wof:name":"Nanweizi",
    "wof:placetype":"locality"
},
  "geometry": {"coordinates":[123.32702999999999,40.65538],"type":"Point"}
}