{
  "type": "Feature",
  "properties": {
    "gn:admin1_code":"2.0",
    "gn:asciiname":"Tianqing",
    "gn:country_code":"CN",
    "gn:dem":7,
    "gn:feature_class":"P",
    "gn:feature_code":"PPL",
    "gn:name":"Tianqing",
    "gn:population":0,
    "gn:timezone":"Asia/Shanghai",
    "iso:country":"CN",
    "name:jpn_x_preferred":[
        "\u5929\u6176"
    ],
    "name:und_x_variant":[
        "\u7530\u9752"
    ],
    "wof:name":"Tianqing",
    "wof:placetype":"locality"
},
  "geometry": {"coordinates":[120.72246,30.95348],"type":"Point"}
}