{
  "type": "Feature",
  "properties": {
    "gn:admin1_code":"10.0",
    "gn:asciiname":"Shilipu",
    "gn:country_code":"CN",
    "gn:dem":28,
    "gn:feature_class":"P",
    "gn:feature_code":"PPL",
    "gn:name":"Shilipu",
    "gn:population":0,
    "gn:timezone":"Asia/Shanghai",
    "iso:country":"CN",
    "name:ceb_x_preferred":[
        "Shilipu"
    ],
    "name:swe_x_preferred":[
        "Shilipu"
    ],
    "name:zho_x_preferred":[
        "\u5341\u91cc\u94fa"
    ],
    "wof:name":"Shilipu",
    "wof:placetype":"locality"
},
  "geometry": {"coordinates":[115.40600000000001,38.5683],"type":"Point"}
}