{
  "type": "Feature",
  "properties": {
    "gn:admin1_code":"29.0",
    "gn:asciiname":"Dianyang",
    "gn:country_code":"CN",
    "gn:dem":1826,
    "gn:feature_class":"P",
    "gn:feature_code":"PPLA3",
    "gn:name":"Dianyang",
    "gn:population":0,
    "gn:timezone":"Asia/Shanghai",
    "iso:country":"CN",
    "name:und_x_variant":[
        "Shih-tien-chieh",
        "Shih-tien-chen",
        "Shih-tien",
        "Dianyang",
        "Shidian"
    ],
    "name:zho_x_preferred":[
        "\u7538\u9633"
    ],
    "name:zho_x_variant":[
        "Shik\u00fcan"
    ],
    "wof:name":"Dianyang",
    "wof:placetype":"locality"
},
  "geometry": {"coordinates":[99.15919,24.70261],"type":"Point"}
}