{
  "type": "Feature",
  "properties": {
    "gn:admin1_code":"19",
    "gn:asciiname":"Wuliangdian",
    "gn:cc2":"CN",
    "gn:country_code":"CN",
    "gn:dem":32,
    "gn:feature_class":"P",
    "gn:feature_code":"PPL",
    "gn:name":"Wuliangdian",
    "gn:population":0,
    "gn:timezone":"Asia/Shanghai",
    "iso:country":"CN",
    "name:und_x_variant":[
        "Wu-liang-tien",
        "Wuliangdian"
    ],
    "wof:name":"Wuliangdian",
    "wof:placetype":"locality"
},
  "geometry": {"coordinates":[122.26667,41.86667],"type":"Point"}
}