{
  "type": "Feature",
  "properties": {
    "gn:admin1_code":"9.0",
    "gn:asciiname":"Duzhuangcun",
    "gn:country_code":"CN",
    "gn:dem":117,
    "gn:feature_class":"P",
    "gn:feature_code":"PPL",
    "gn:name":"Duzhuangcun",
    "gn:population":0,
    "gn:timezone":"Asia/Shanghai",
    "iso:country":"CN",
    "name:zho_x_preferred":[
        "\u675c\u5e84\u6751"
    ],
    "wof:name":"Duzhuangcun",
    "wof:placetype":"locality"
},
  "geometry": {"coordinates":[113.06576,33.70026],"type":"Point"}
}