{
  "type": "Feature",
  "properties": {
    "gn:admin1_code":"2.0",
    "gn:asciiname":"Nanqiaotou",
    "gn:country_code":"CN",
    "gn:dem":8,
    "gn:feature_class":"P",
    "gn:feature_code":"PPL",
    "gn:name":"Nanqiaotou",
    "gn:population":0,
    "gn:timezone":"Asia/Shanghai",
    "iso:country":"CN",
    "name:und_x_variant":[
        "\u5357\u6865\u5934"
    ],
    "wof:name":"Nanqiaotou",
    "wof:placetype":"locality"
},
  "geometry": {"coordinates":[120.54228000000001,30.61042],"type":"Point"}
}