{
  "type": "Feature",
  "properties": {
    "gn:admin1_code":"15.0",
    "gn:asciiname":"Yangquantou",
    "gn:country_code":"CN",
    "gn:dem":1865,
    "gn:feature_class":"P",
    "gn:feature_code":"PPL",
    "gn:name":"Yangquantou",
    "gn:population":0,
    "gn:timezone":"Asia/Shanghai",
    "iso:country":"CN",
    "name:und_x_variant":[
        "\u7f8a\u5708\u5934"
    ],
    "wof:name":"Yangquantou",
    "wof:placetype":"locality"
},
  "geometry": {"coordinates":[105.22626,33.32173],"type":"Point"}
}