{
  "type": "Feature",
  "properties": {
    "gn:admin1_code":"12.0",
    "gn:asciiname":"Changlinggang",
    "gn:country_code":"CN",
    "gn:dem":90,
    "gn:feature_class":"P",
    "gn:feature_code":"PPL",
    "gn:name":"Changlinggang",
    "gn:population":0,
    "gn:timezone":"Asia/Shanghai",
    "iso:country":"CN",
    "name:zho_x_preferred":[
        "\u957f\u5cad\u5c97"
    ],
    "wof:name":"Changlinggang",
    "wof:placetype":"locality"
},
  "geometry": {"coordinates":[114.74863000000001,31.24692000000001],"type":"Point"}
}