{
  "type": "Feature",
  "properties": {
    "gn:admin1_code":"29.0",
    "gn:asciiname":"Gehai Laozhai",
    "gn:country_code":"CN",
    "gn:dem":1231,
    "gn:feature_class":"P",
    "gn:feature_code":"PPL",
    "gn:name":"Gehai Laozhai",
    "gn:population":0,
    "gn:timezone":"Asia/Shanghai",
    "iso:country":"CN",
    "name:zho_x_preferred":[
        "\u6208\u6d77\u8001\u5be8"
    ],
    "wof:name":"Gehai Laozhai",
    "wof:placetype":"locality"
},
  "geometry": {"coordinates":[99.6433,22.6741],"type":"Point"}
}