{
  "type": "Feature",
  "properties": {
    "gn:admin1_code":"19.0",
    "gn:asciiname":"Tongtaigou",
    "gn:country_code":"CN",
    "gn:dem":185,
    "gn:feature_class":"P",
    "gn:feature_code":"PPL",
    "gn:name":"Tongtaigou",
    "gn:population":0,
    "gn:timezone":"Asia/Shanghai",
    "iso:country":"CN",
    "name:und_x_variant":[
        "\u4f5f\u592a\u6c9f"
    ],
    "wof:name":"Tongtaigou",
    "wof:placetype":"locality"
},
  "geometry": {"coordinates":[124.17272,41.83473],"type":"Point"}
}