{
  "type": "Feature",
  "properties": {
    "gn:admin1_code":"9.0",
    "gn:asciiname":"Ligou",
    "gn:country_code":"CN",
    "gn:dem":772,
    "gn:feature_class":"P",
    "gn:feature_code":"PPL",
    "gn:name":"Ligou",
    "gn:population":0,
    "gn:timezone":"Asia/Shanghai",
    "iso:country":"CN",
    "name:zho_x_preferred":[
        "\u91cc\u6c9f"
    ],
    "wof:name":"Ligou",
    "wof:placetype":"locality"
},
  "geometry": {"coordinates":[111.03785000000001,33.55083],"type":"Point"}
}