{
  "type": "Feature",
  "properties": {
    "gn:admin1_code":"29",
    "gn:asciiname":"Luoshuidong",
    "gn:country_code":"CN",
    "gn:dem":1859,
    "gn:feature_class":"P",
    "gn:feature_code":"PPL",
    "gn:name":"Luoshuidong",
    "gn:population":0,
    "gn:timezone":"Asia/Shanghai",
    "iso:country":"CN",
    "name:zho_x_preferred":[
        "\u843d\u6c34\u6d1e"
    ],
    "wof:name":"Luoshuidong",
    "wof:placetype":"locality"
},
  "geometry": {"coordinates":[102.738,24.0513],"type":"Point"}
}