{
  "type": "Feature",
  "properties": {
    "gn:admin1_code":"06",
    "gn:asciiname":"Dehenglong",
    "gn:country_code":"CN",
    "gn:dem":2861,
    "gn:feature_class":"P",
    "gn:feature_code":"PPLA4",
    "gn:name":"Dehenglong",
    "gn:population":0,
    "gn:timezone":"Asia/Shanghai",
    "iso:country":"CN",
    "name:und_x_variant":[
        "\u5fb7\u6052\u9686",
        "Dehenglong Xiang",
        "\u5fb7\u6052\u9686\u4e61"
    ],
    "wof:name":"Dehenglong",
    "wof:placetype":"locality"
},
  "geometry": {"coordinates":[102.14395,35.97472],"type":"Point"}
}