{
  "type": "Feature",
  "properties": {
    "gn:admin1_code":"29.0",
    "gn:asciiname":"Bashang",
    "gn:country_code":"CN",
    "gn:dem":904,
    "gn:feature_class":"P",
    "gn:feature_code":"PPL",
    "gn:name":"Bashang",
    "gn:population":0,
    "gn:timezone":"Asia/Shanghai",
    "iso:country":"CN",
    "name:zho_x_preferred":[
        "\u575d\u5c1a"
    ],
    "wof:name":"Bashang",
    "wof:placetype":"locality"
},
  "geometry": {"coordinates":[100.563,22.2696],"type":"Point"}
}