{
  "type": "Feature",
  "properties": {
    "gn:admin1_code":"29.0",
    "gn:asciiname":"Hongwafang",
    "gn:country_code":"CN",
    "gn:dem":1978,
    "gn:feature_class":"P",
    "gn:feature_code":"PPL",
    "gn:name":"Hongwafang",
    "gn:population":0,
    "gn:timezone":"Asia/Shanghai",
    "iso:country":"CN",
    "name:zho_x_preferred":[
        "\u7ea2\u74e6\u623f"
    ],
    "wof:name":"Hongwafang",
    "wof:placetype":"locality"
},
  "geometry": {"coordinates":[103.73399999999999,25.6343],"type":"Point"}
}