{
  "type": "Feature",
  "properties": {
    "gn:admin1_code":"4.0",
    "gn:asciiname":"Wangdailou",
    "gn:country_code":"CN",
    "gn:dem":3,
    "gn:feature_class":"P",
    "gn:feature_code":"PPL",
    "gn:name":"Wangdailou",
    "gn:population":0,
    "gn:timezone":"Asia/Shanghai",
    "iso:country":"CN",
    "name:zho_x_preferred":[
        "\u738b\u6234\u697c"
    ],
    "wof:name":"Wangdailou",
    "wof:placetype":"locality"
},
  "geometry": {"coordinates":[119.91245000000001,33.06345],"type":"Point"}
}