{
  "type": "Feature",
  "properties": {
    "gn:admin1_code":"19.0",
    "gn:asciiname":"Yayaogou",
    "gn:country_code":"CN",
    "gn:dem":297,
    "gn:feature_class":"P",
    "gn:feature_code":"PPL",
    "gn:name":"Yayaogou",
    "gn:population":0,
    "gn:timezone":"Asia/Shanghai",
    "iso:country":"CN",
    "name:und_x_variant":[
        "\u538b\u836f\u6c9f"
    ],
    "wof:name":"Yayaogou",
    "wof:placetype":"locality"
},
  "geometry": {"coordinates":[123.2749,40.78722],"type":"Point"}
}