{
  "type": "Feature",
  "properties": {
    "gn:admin1_code":"12.0",
    "gn:asciiname":"Maojialong",
    "gn:country_code":"CN",
    "gn:dem":50,
    "gn:feature_class":"P",
    "gn:feature_code":"PPL",
    "gn:name":"Maojialong",
    "gn:population":0,
    "gn:timezone":"Asia/Shanghai",
    "iso:country":"CN",
    "name:zho_x_preferred":[
        "Maojialong"
    ],
    "name:zho_x_variant":[
        "\u6bdb\u5bb6\u5784"
    ],
    "wof:name":"Maojialong",
    "wof:placetype":"locality"
},
  "geometry": {"coordinates":[114.47733999999998,29.91116],"type":"Point"}
}