{
  "type": "Feature",
  "properties": {
    "gn:admin1_code":"12.0",
    "gn:asciiname":"Zhijiping",
    "gn:country_code":"CN",
    "gn:dem":1014,
    "gn:feature_class":"P",
    "gn:feature_code":"PPL",
    "gn:name":"Zhijiping",
    "gn:population":0,
    "gn:timezone":"Asia/Shanghai",
    "iso:country":"CN",
    "name:zho_x_preferred":[
        "\u96c9\u9e21\u576a"
    ],
    "wof:name":"Zhijiping",
    "wof:placetype":"locality"
},
  "geometry": {"coordinates":[110.27531,29.83265],"type":"Point"}
}