{
  "type": "Feature",
  "properties": {
    "gn:admin1_code":"15.0",
    "gn:asciiname":"Yejiayao",
    "gn:country_code":"CN",
    "gn:dem":1472,
    "gn:feature_class":"P",
    "gn:feature_code":"PPL",
    "gn:name":"Yejiayao",
    "gn:population":0,
    "gn:timezone":"Asia/Shanghai",
    "iso:country":"CN",
    "name:zho_x_preferred":[
        "\u53f6\u5bb6\u7a91"
    ],
    "wof:name":"Yejiayao",
    "wof:placetype":"locality"
},
  "geometry": {"coordinates":[104.76000000000001,36.3659],"type":"Point"}
}