{
  "type": "Feature",
  "properties": {
    "gn:admin1_code":"15.0",
    "gn:asciiname":"Mapaoquan",
    "gn:country_code":"CN",
    "gn:dem":1841,
    "gn:feature_class":"P",
    "gn:feature_code":"PPL",
    "gn:name":"Mapaoquan",
    "gn:population":0,
    "gn:timezone":"Asia/Shanghai",
    "iso:country":"CN",
    "name:zho_x_preferred":[
        "\u9a6c\u8dd1\u6cc9"
    ],
    "wof:name":"Mapaoquan",
    "wof:placetype":"locality"
},
  "geometry": {"coordinates":[103.571,36.3694],"type":"Point"}
}