{
  "type": "Feature",
  "properties": {
    "gn:admin1_code":"12.0",
    "gn:asciiname":"Weijiagou",
    "gn:country_code":"CN",
    "gn:dem":481,
    "gn:feature_class":"P",
    "gn:feature_code":"PPL",
    "gn:name":"Weijiagou",
    "gn:population":0,
    "gn:timezone":"Asia/Shanghai",
    "iso:country":"CN",
    "name:zho_x_preferred":[
        "\u9b4f\u5bb6\u6c9f"
    ],
    "wof:name":"Weijiagou",
    "wof:placetype":"locality"
},
  "geometry": {"coordinates":[110.57210000000001,32.39484],"type":"Point"}
}