{
  "type": "Feature",
  "properties": {
    "gn:admin1_code":"3.0",
    "gn:asciiname":"Qiuchongwu",
    "gn:country_code":"CN",
    "gn:dem":104,
    "gn:feature_class":"P",
    "gn:feature_code":"PPL",
    "gn:name":"Qiuchongwu",
    "gn:population":0,
    "gn:timezone":"Asia/Shanghai",
    "iso:country":"CN",
    "name:und_x_variant":[
        "\u4e18\u51b2\u575e"
    ],
    "wof:name":"Qiuchongwu",
    "wof:placetype":"locality"
},
  "geometry": {"coordinates":[117.22609,29.18121],"type":"Point"}
}