{
  "type": "Feature",
  "properties": {
    "gn:admin1_code":"32.0",
    "gn:asciiname":"Yanziyan",
    "gn:country_code":"CN",
    "gn:dem":475,
    "gn:feature_class":"P",
    "gn:feature_code":"PPL",
    "gn:name":"Yanziyan",
    "gn:population":0,
    "gn:timezone":"Asia/Shanghai",
    "iso:country":"CN",
    "name:zho_x_preferred":[
        "\u71d5\u5b50\u5ca9"
    ],
    "wof:name":"Yanziyan",
    "wof:placetype":"locality"
},
  "geometry": {"coordinates":[107.87,30.9923],"type":"Point"}
}