{
  "type": "Feature",
  "properties": {
    "gn:admin1_code":"16",
    "gn:asciiname":"Tonglao",
    "gn:cc2":"CN",
    "gn:country_code":"CN",
    "gn:dem":306,
    "gn:feature_class":"P",
    "gn:feature_code":"PPL",
    "gn:name":"Tonglao",
    "gn:population":0,
    "gn:timezone":"Asia/Shanghai",
    "iso:country":"CN",
    "name:und_x_variant":[
        "T\u2019ung-lao",
        "Tung-lao-hs\u00fc",
        "Tonglao"
    ],
    "wof:name":"Tonglao",
    "wof:placetype":"locality"
},
  "geometry": {"coordinates":[107.42028000000001,23.76778],"type":"Point"}
}