{
  "type": "Feature",
  "properties": {
    "gn:admin1_code":"29.0",
    "gn:asciiname":"Palong Laozhai",
    "gn:country_code":"CN",
    "gn:dem":804,
    "gn:feature_class":"P",
    "gn:feature_code":"PPL",
    "gn:name":"Palong Laozhai",
    "gn:population":0,
    "gn:timezone":"Asia/Shanghai",
    "iso:country":"CN",
    "name:zho_x_preferred":[
        "\u6015\u9f99\u8001\u5be8"
    ],
    "wof:name":"Palong Laozhai",
    "wof:placetype":"locality"
},
  "geometry": {"coordinates":[101.39400000000001,21.5674],"type":"Point"}
}