{
  "type": "Feature",
  "properties": {
    "gn:admin1_code":"11",
    "gn:asciiname":"Panguchong",
    "gn:country_code":"CN",
    "gn:dem":151,
    "gn:feature_class":"P",
    "gn:feature_code":"PPL",
    "gn:name":"Panguchong",
    "gn:population":0,
    "gn:timezone":"Asia/Shanghai",
    "iso:country":"CN",
    "name:zho_x_preferred":[
        "\u76d8\u53e4\u51b2"
    ],
    "wof:name":"Panguchong",
    "wof:placetype":"locality"
},
  "geometry": {"coordinates":[112.41123,27.48424],"type":"Point"}
}