{
  "type": "Feature",
  "properties": {
    "gn:admin1_code":"18.0",
    "gn:asciiname":"Yuhuang",
    "gn:country_code":"CN",
    "gn:dem":643,
    "gn:feature_class":"P",
    "gn:feature_code":"PPL",
    "gn:name":"Yuhuang",
    "gn:population":0,
    "gn:timezone":"Asia/Shanghai",
    "iso:country":"CN",
    "wof:name":"Yuhuang",
    "wof:placetype":"locality"
},
  "geometry": {"coordinates":[106.06139,28.55444],"type":"Point"}
}