{
  "type": "Feature",
  "properties": {
    "gn:admin1_code":"5.0",
    "gn:asciiname":"Liujiazicun",
    "gn:country_code":"CN",
    "gn:dem":210,
    "gn:feature_class":"P",
    "gn:feature_code":"PPL",
    "gn:name":"Liujiazicun",
    "gn:population":0,
    "gn:timezone":"Asia/Shanghai",
    "iso:country":"CN",
    "name:zho_x_preferred":[
        "\u516d\u5bb6\u5b50\u6751"
    ],
    "wof:name":"Liujiazicun",
    "wof:placetype":"locality"
},
  "geometry": {"coordinates":[124.12163,44.0412],"type":"Point"}
}