{
  "type": "Feature",
  "properties": {
    "gn:admin1_code":"15.0",
    "gn:asciiname":"Xueshanxiang",
    "gn:country_code":"CN",
    "gn:dem":2114,
    "gn:feature_class":"P",
    "gn:feature_code":"PPL",
    "gn:name":"Xueshanxiang",
    "gn:population":0,
    "gn:timezone":"Asia/Shanghai",
    "iso:country":"CN",
    "name:und_x_variant":[
        "\u96ea\u5c71\u4e61"
    ],
    "wof:name":"Xueshanxiang",
    "wof:placetype":"locality"
},
  "geometry": {"coordinates":[104.39527,34.96986],"type":"Point"}
}