{
  "type": "Feature",
  "properties": {
    "gn:admin1_code":"15.0",
    "gn:asciiname":"Haopingli",
    "gn:country_code":"CN",
    "gn:dem":1256,
    "gn:feature_class":"P",
    "gn:feature_code":"PPL",
    "gn:name":"Haopingli",
    "gn:population":0,
    "gn:timezone":"Asia/Shanghai",
    "iso:country":"CN",
    "name:und_x_variant":[
        "\u84bf\u576a\u91cc"
    ],
    "wof:name":"Haopingli",
    "wof:placetype":"locality"
},
  "geometry": {"coordinates":[105.67533,33.15049],"type":"Point"}
}