{
  "type": "Feature",
  "properties": {
    "gn:admin1_code":"12.0",
    "gn:asciiname":"Zhumuyuan",
    "gn:country_code":"CN",
    "gn:dem":177,
    "gn:feature_class":"P",
    "gn:feature_code":"PPL",
    "gn:name":"Zhumuyuan",
    "gn:population":0,
    "gn:timezone":"Asia/Shanghai",
    "iso:country":"CN",
    "name:zho_x_preferred":[
        "Zhumuyuan"
    ],
    "name:zho_x_variant":[
        "\u732a\u6bcd\u56ed"
    ],
    "wof:name":"Zhumuyuan",
    "wof:placetype":"locality"
},
  "geometry": {"coordinates":[111.33163,30.57636],"type":"Point"}
}