{
  "type": "Feature",
  "properties": {
    "gn:admin1_code":"29",
    "gn:asciiname":"Zhouguan",
    "gn:country_code":"CN",
    "gn:dem":1725,
    "gn:feature_class":"P",
    "gn:feature_code":"PPL",
    "gn:name":"Zhouguan",
    "gn:population":0,
    "gn:timezone":"Asia/Shanghai",
    "iso:country":"CN",
    "name:zho_x_preferred":[
        "\u5468\u5b98"
    ],
    "wof:name":"Zhouguan",
    "wof:placetype":"locality"
},
  "geometry": {"coordinates":[102.73663999999999,24.3228],"type":"Point"}
}