{
  "type": "Feature",
  "properties": {
    "gn:admin1_code":"10",
    "gn:asciiname":"Zhonglinchen",
    "gn:country_code":"CN",
    "gn:dem":23,
    "gn:feature_class":"P",
    "gn:feature_code":"PPL",
    "gn:name":"Zhonglinchen",
    "gn:population":0,
    "gn:timezone":"Asia/Shanghai",
    "iso:country":"CN",
    "name:zho_x_preferred":[
        "\u4e2d\u4e34\u9648"
    ],
    "wof:name":"Zhonglinchen",
    "wof:placetype":"locality"
},
  "geometry": {"coordinates":[116.11431,37.81857],"type":"Point"}
}