{
  "type": "Feature",
  "properties": {
    "gn:admin1_code":"14.0",
    "gn:asciiname":"Fa'erma",
    "gn:country_code":"CN",
    "gn:dem":4800,
    "gn:feature_class":"P",
    "gn:feature_code":"PPL",
    "gn:name":"Fa\u2019erma",
    "gn:population":0,
    "gn:timezone":"Asia/Urumqi",
    "iso:country":"CN",
    "name:und_x_variant":[
        "Fa\u2019erma"
    ],
    "name:zho_x_preferred":[
        "\u53d1\u4e8c\u9a6c"
    ],
    "wof:name":"Fa'erma",
    "wof:placetype":"locality"
},
  "geometry": {"coordinates":[94.02697999999999,31.35511],"type":"Point"}
}