{
  "type": "Feature",
  "properties": {
    "gn:admin1_code":"8.0",
    "gn:asciiname":"Songshugoucun",
    "gn:country_code":"CN",
    "gn:dem":180,
    "gn:feature_class":"P",
    "gn:feature_code":"PPL",
    "gn:name":"Songshugoucun",
    "gn:population":0,
    "gn:timezone":"Asia/Shanghai",
    "iso:country":"CN",
    "name:zho_x_preferred":[
        "\u677e\u6811\u6c9f\u6751"
    ],
    "wof:name":"Songshugoucun",
    "wof:placetype":"locality"
},
  "geometry": {"coordinates":[127.34402,49.98953],"type":"Point"}
}