{
  "type": "Feature",
  "properties": {
    "gn:admin1_code":"3.0",
    "gn:asciiname":"Yanxia",
    "gn:country_code":"CN",
    "gn:dem":196,
    "gn:feature_class":"P",
    "gn:feature_code":"PPL",
    "gn:name":"Yanxia",
    "gn:population":0,
    "gn:timezone":"Asia/Shanghai",
    "iso:country":"CN",
    "name:und_x_variant":[
        "\u5ca9\u4e0b"
    ],
    "wof:name":"Yanxia",
    "wof:placetype":"locality"
},
  "geometry": {"coordinates":[114.36354,27.41303],"type":"Point"}
}