{
  "type": "Feature",
  "properties": {
    "gn:admin1_code":"3.0",
    "gn:asciiname":"Dishuiyan",
    "gn:country_code":"CN",
    "gn:dem":224,
    "gn:feature_class":"P",
    "gn:feature_code":"PPL",
    "gn:name":"Dishuiyan",
    "gn:population":0,
    "gn:timezone":"Asia/Shanghai",
    "iso:country":"CN",
    "name:und_x_variant":[
        "\u6ef4\u6c34\u5ca9"
    ],
    "wof:name":"Dishuiyan",
    "wof:placetype":"locality"
},
  "geometry": {"coordinates":[115.06005999999999,29.33754],"type":"Point"}
}