{
  "type": "Feature",
  "properties": {
    "gn:admin1_code":"29.0",
    "gn:asciiname":"Guluba",
    "gn:country_code":"CN",
    "gn:dem":2655,
    "gn:feature_class":"P",
    "gn:feature_code":"PPL",
    "gn:name":"Guluba",
    "gn:population":0,
    "gn:timezone":"Asia/Shanghai",
    "iso:country":"CN",
    "name:zho_x_preferred":[
        "\u53e4\u9c81\u5df4"
    ],
    "wof:name":"Guluba",
    "wof:placetype":"locality"
},
  "geometry": {"coordinates":[100.13500000000001,27.3829],"type":"Point"}
}