{
  "type": "Feature",
  "properties": {
    "gn:admin1_code":"22.0",
    "gn:asciiname":"Longbaoyucun",
    "gn:country_code":"CN",
    "gn:dem":326,
    "gn:feature_class":"P",
    "gn:feature_code":"PPL",
    "gn:name":"Longbaoyucun",
    "gn:population":0,
    "gn:timezone":"Asia/Shanghai",
    "iso:country":"CN",
    "name:zho_x_preferred":[
        "\u9f99\u5b9d\u5cea\u6751"
    ],
    "wof:name":"Longbaoyucun",
    "wof:placetype":"locality"
},
  "geometry": {"coordinates":[115.88423,39.70314000000001],"type":"Point"}
}