{
  "type": "Feature",
  "properties": {
    "gn:admin1_code":"10.0",
    "gn:asciiname":"Minjian",
    "gn:country_code":"CN",
    "gn:dem":17,
    "gn:feature_class":"P",
    "gn:feature_code":"PPL",
    "gn:name":"Minjian",
    "gn:population":0,
    "gn:timezone":"Asia/Shanghai",
    "iso:country":"CN",
    "name:zho_x_preferred":[
        "\u6c11\u5efa"
    ],
    "wof:name":"Minjian",
    "wof:placetype":"locality"
},
  "geometry": {"coordinates":[116.01000000000001,38.0748],"type":"Point"}
}