{
  "type": "Feature",
  "properties": {
    "gn:admin1_code":"14.0",
    "gn:asciiname":"Selacun",
    "gn:country_code":"CN",
    "gn:dem":3616,
    "gn:feature_class":"P",
    "gn:feature_code":"PPL",
    "gn:name":"Selacun",
    "gn:population":0,
    "gn:timezone":"Asia/Urumqi",
    "iso:country":"CN",
    "name:zho_x_preferred":[
        "\u8272\u62c9\u6751"
    ],
    "wof:name":"Selacun",
    "wof:placetype":"locality"
},
  "geometry": {"coordinates":[92.55909,28.97421],"type":"Point"}
}