{
  "type": "Feature",
  "properties": {
    "gn:admin1_code":"16.0",
    "gn:asciiname":"Shanghengli",
    "gn:country_code":"CN",
    "gn:dem":952,
    "gn:feature_class":"P",
    "gn:feature_code":"PPL",
    "gn:name":"Shanghengli",
    "gn:population":0,
    "gn:timezone":"Asia/Shanghai",
    "iso:country":"CN",
    "name:zho_x_preferred":[
        "\u4e0a\u6a2a\u91cc"
    ],
    "wof:name":"Shanghengli",
    "wof:placetype":"locality"
},
  "geometry": {"coordinates":[107.044,24.9856],"type":"Point"}
}