{
  "type": "Feature",
  "properties": {
    "gn:admin1_code":"26.0",
    "gn:asciiname":"Cao'erwan",
    "gn:country_code":"CN",
    "gn:dem":468,
    "gn:feature_class":"P",
    "gn:feature_code":"PPL",
    "gn:name":"Cao\u2019erwan",
    "gn:population":0,
    "gn:timezone":"Asia/Shanghai",
    "iso:country":"CN",
    "name:und_x_variant":[
        "Cao\u2019erwan",
        "Can\u2019erwan"
    ],
    "name:zho_x_preferred":[
        "\u66f9\u513f\u6e7e"
    ],
    "wof:name":"Cao'erwan",
    "wof:placetype":"locality"
},
  "geometry": {"coordinates":[109.14713,33.20734],"type":"Point"}
}