{
  "type": "Feature",
  "properties": {
    "gn:admin1_code":"21.0",
    "gn:asciiname":"Yehedun",
    "gn:country_code":"CN",
    "gn:dem":1367,
    "gn:feature_class":"P",
    "gn:feature_code":"PPL",
    "gn:name":"Yehedun",
    "gn:population":0,
    "gn:timezone":"Asia/Shanghai",
    "iso:country":"CN",
    "name:zho_x_preferred":[
        "\u53f6\u5408\u58a9"
    ],
    "wof:name":"Yehedun",
    "wof:placetype":"locality"
},
  "geometry": {"coordinates":[106.733,37.7716],"type":"Point"}
}