{
  "type": "Feature",
  "properties": {
    "gn:admin1_code":"5.0",
    "gn:asciiname":"Sipingshan",
    "gn:country_code":"CN",
    "gn:dem":184,
    "gn:feature_class":"P",
    "gn:feature_code":"PPL",
    "gn:name":"Sipingshan",
    "gn:population":0,
    "gn:timezone":"Asia/Shanghai",
    "iso:country":"CN",
    "name:zho_x_preferred":[
        "\u56db\u5e73\u5c71"
    ],
    "wof:name":"Sipingshan",
    "wof:placetype":"locality"
},
  "geometry": {"coordinates":[124.92907,44.93637],"type":"Point"}
}