{
  "type": "Feature",
  "properties": {
    "gn:admin1_code":"4.0",
    "gn:asciiname":"Huanzidong",
    "gn:country_code":"CN",
    "gn:dem":1,
    "gn:feature_class":"P",
    "gn:feature_code":"PPL",
    "gn:name":"Huanzidong",
    "gn:population":0,
    "gn:timezone":"Asia/Shanghai",
    "iso:country":"CN",
    "name:zho_x_preferred":[
        "\u737e\u5b50\u6d1e"
    ],
    "wof:name":"Huanzidong",
    "wof:placetype":"locality"
},
  "geometry": {"coordinates":[120.23636,32.07854],"type":"Point"}
}