{
  "type": "Feature",
  "properties": {
    "gn:admin1_code":"8.0",
    "gn:asciiname":"Fujiatun",
    "gn:country_code":"CN",
    "gn:dem":157,
    "gn:feature_class":"P",
    "gn:feature_code":"PPL",
    "gn:name":"Fujiatun",
    "gn:population":0,
    "gn:timezone":"Asia/Shanghai",
    "iso:country":"CN",
    "name:zho_x_preferred":[
        "\u4ed8\u5bb6\u5c6f"
    ],
    "wof:name":"Fujiatun",
    "wof:placetype":"locality"
},
  "geometry": {"coordinates":[127.05295,45.80611],"type":"Point"}
}