{
  "type": "Feature",
  "properties": {
    "gn:admin1_code":"12.0",
    "gn:asciiname":"Feihaiqiao",
    "gn:country_code":"CN",
    "gn:dem":52,
    "gn:feature_class":"P",
    "gn:feature_code":"PPL",
    "gn:name":"Feihaiqiao",
    "gn:population":0,
    "gn:timezone":"Asia/Shanghai",
    "iso:country":"CN",
    "name:zho_x_preferred":[
        "Feihaiqiao"
    ],
    "name:zho_x_variant":[
        "\u8d39\u6d77\u6865"
    ],
    "wof:name":"Feihaiqiao",
    "wof:placetype":"locality"
},
  "geometry": {"coordinates":[115.19029,30.01694],"type":"Point"}
}