{
  "type": "Feature",
  "properties": {
    "gn:admin1_code":"4.0",
    "gn:asciiname":"Miaoxiangcun",
    "gn:country_code":"CN",
    "gn:dem":9,
    "gn:feature_class":"P",
    "gn:feature_code":"PPL",
    "gn:name":"Miaoxiangcun",
    "gn:population":0,
    "gn:timezone":"Asia/Shanghai",
    "iso:country":"CN",
    "name:zho_x_preferred":[
        "\u7f2a\u5df7\u6751"
    ],
    "wof:name":"Miaoxiangcun",
    "wof:placetype":"locality"
},
  "geometry": {"coordinates":[120.40082,31.81814],"type":"Point"}
}