{
  "type": "Feature",
  "properties": {
    "gn:admin1_code":"30",
    "gn:asciiname":"Bainitang",
    "gn:country_code":"CN",
    "gn:dem":60,
    "gn:feature_class":"P",
    "gn:feature_code":"PPL",
    "gn:name":"Bainitang",
    "gn:population":0,
    "gn:timezone":"Asia/Urumqi",
    "iso:country":"CN",
    "name:zho_x_preferred":[
        "\u767d\u576d\u5858"
    ],
    "wof:name":"Bainitang",
    "wof:placetype":"locality"
},
  "geometry": {"coordinates":[110.95504,21.83559],"type":"Point"}
}