{
  "type": "Feature",
  "properties": {
    "gn:admin1_code":"19.0",
    "gn:asciiname":"Mu'ergangzi",
    "gn:country_code":"CN",
    "gn:dem":21,
    "gn:feature_class":"P",
    "gn:feature_code":"PPL",
    "gn:name":"Mu\u2019ergangzi",
    "gn:population":0,
    "gn:timezone":"Asia/Shanghai",
    "iso:country":"CN",
    "name:zho_x_preferred":[
        "Mu\u2019ergangzi"
    ],
    "name:zho_x_variant":[
        "\u6728\u8033\u5c97\u5b50"
    ],
    "wof:name":"Mu'ergangzi",
    "wof:placetype":"locality"
},
  "geometry": {"coordinates":[122.88039000000001,41.63865],"type":"Point"}
}