{
  "type": "Feature",
  "properties": {
    "gn:admin1_code":"25",
    "gn:asciiname":"Jiagushan",
    "gn:country_code":"CN",
    "gn:dem":166,
    "gn:feature_class":"P",
    "gn:feature_code":"PPL",
    "gn:name":"Jiagushan",
    "gn:population":0,
    "gn:timezone":"Asia/Shanghai",
    "iso:country":"CN",
    "name:zho_x_preferred":[
        "\u5939\u8c37\u5c71"
    ],
    "wof:name":"Jiagushan",
    "wof:placetype":"locality"
},
  "geometry": {"coordinates":[117.16500000000001,35.601],"type":"Point"}
}