{
  "type": "Feature",
  "properties": {
    "gn:admin1_code":"32.0",
    "gn:asciiname":"Yucitang",
    "gn:country_code":"CN",
    "gn:dem":370,
    "gn:feature_class":"P",
    "gn:feature_code":"PPL",
    "gn:name":"Yucitang",
    "gn:population":0,
    "gn:timezone":"Asia/Shanghai",
    "iso:country":"CN",
    "name:zho_x_preferred":[
        "\u4f59\u7960\u5802"
    ],
    "wof:name":"Yucitang",
    "wof:placetype":"locality"
},
  "geometry": {"coordinates":[105.551,28.8091],"type":"Point"}
}