{
  "type": "Feature",
  "properties": {
    "gn:admin1_code":"19.0",
    "gn:asciiname":"Batuyingzi Houjie",
    "gn:country_code":"CN",
    "gn:dem":194,
    "gn:feature_class":"P",
    "gn:feature_code":"PPL",
    "gn:name":"Batuyingzi Houjie",
    "gn:population":0,
    "gn:timezone":"Asia/Shanghai",
    "iso:country":"CN",
    "name:und_x_variant":[
        "\u5df4\u5410\u8425\u5b50\u540e\u8857"
    ],
    "name:zho_x_preferred":[
        "\u5df4\u5410\u8425\u5b50\u540e\u8857"
    ],
    "wof:name":"Batuyingzi Houjie",
    "wof:placetype":"locality"
},
  "geometry": {"coordinates":[120.81913,41.90156],"type":"Point"}
}