{
  "type": "Feature",
  "properties": {
    "gn:admin1_code":"5.0",
    "gn:asciiname":"Shanyanggou",
    "gn:country_code":"CN",
    "gn:dem":739,
    "gn:feature_class":"P",
    "gn:feature_code":"PPL",
    "gn:name":"Shanyanggou",
    "gn:population":0,
    "gn:timezone":"Asia/Shanghai",
    "iso:country":"CN",
    "name:und_x_variant":[
        "Shanyangqu",
        "Shan-yang-ch\u2019\u00fc",
        "Shanyanggou",
        "\u5c71\u7f8a\u6c9f"
    ],
    "wof:name":"Shanyanggou",
    "wof:placetype":"locality"
},
  "geometry": {"coordinates":[129.10723999999999,42.26164],"type":"Point"}
}