{
  "type": "Feature",
  "properties": {
    "gn:admin1_code":"16.0",
    "gn:asciiname":"Huayi",
    "gn:country_code":"CN",
    "gn:dem":393,
    "gn:feature_class":"P",
    "gn:feature_code":"PPL",
    "gn:name":"Huayi",
    "gn:population":0,
    "gn:timezone":"Asia/Shanghai",
    "iso:country":"CN",
    "name:zho_x_preferred":[
        "\u82b1\u8863"
    ],
    "wof:name":"Huayi",
    "wof:placetype":"locality"
},
  "geometry": {"coordinates":[108.374,23.6932],"type":"Point"}
}