{
  "type": "Feature",
  "properties": {
    "gn:admin1_code":"20.0",
    "gn:asciiname":"Guosanyao",
    "gn:country_code":"CN",
    "gn:dem":1226,
    "gn:feature_class":"P",
    "gn:feature_code":"PPL",
    "gn:name":"Guosanyao",
    "gn:population":0,
    "gn:timezone":"Asia/Shanghai",
    "iso:country":"CN",
    "name:und_x_variant":[
        "\u90ed\u4e09\u7a91"
    ],
    "wof:name":"Guosanyao",
    "wof:placetype":"locality"
},
  "geometry": {"coordinates":[111.65038,39.93029],"type":"Point"}
}