{
  "type": "Feature",
  "properties": {
    "gn:admin1_code":"20",
    "gn:asciiname":"Xishanzui",
    "gn:cc2":"CN",
    "gn:country_code":"CN",
    "gn:dem":1024,
    "gn:feature_class":"P",
    "gn:feature_code":"PPL",
    "gn:name":"Xishanzui",
    "gn:population":0,
    "gn:timezone":"Asia/Shanghai",
    "iso:country":"CN",
    "name:und_x_variant":[
        "Shuang-ch\u2019uan-tien",
        "Xishanzui Zhen",
        "Xishanzui"
    ],
    "wof:name":"Xishanzui",
    "wof:placetype":"locality"
},
  "geometry": {"coordinates":[108.64610999999999,40.71417],"type":"Point"}
}