{
  "type": "Feature",
  "properties": {
    "gn:admin1_code":"19",
    "gn:asciiname":"Changhadacun",
    "gn:country_code":"CN",
    "gn:dem":193,
    "gn:feature_class":"P",
    "gn:feature_code":"PPL",
    "gn:name":"Changhadacun",
    "gn:population":0,
    "gn:timezone":"Asia/Shanghai",
    "iso:country":"CN",
    "name:und_x_variant":[
        "Changhada"
    ],
    "name:zho_x_preferred":[
        "\u957f\u54c8\u8fbe\u6751"
    ],
    "wof:name":"Changhadacun",
    "wof:placetype":"locality"
},
  "geometry": {"coordinates":[121.76667,42.01667],"type":"Point"}
}