{
  "type": "Feature",
  "properties": {
    "gn:admin1_code":"30",
    "gn:asciiname":"Shatang",
    "gn:country_code":"CN",
    "gn:dem":7,
    "gn:feature_class":"P",
    "gn:feature_code":"PPLA4",
    "gn:name":"Shatang",
    "gn:population":0,
    "gn:timezone":"Asia/Shanghai",
    "iso:country":"CN",
    "name:und_x_variant":[
        "Shatang Zhen",
        "\u6c99\u5858\u9547"
    ],
    "name:zho_x_preferred":[
        "\u6c99\u5858"
    ],
    "wof:name":"Shatang",
    "wof:placetype":"locality"
},
  "geometry": {"coordinates":[112.58683000000001,22.45823],"type":"Point"}
}