{
  "type": "Feature",
  "properties": {
    "gn:admin1_code":"12.0",
    "gn:asciiname":"Mujiangtai",
    "gn:country_code":"CN",
    "gn:dem":34,
    "gn:feature_class":"P",
    "gn:feature_code":"PPL",
    "gn:name":"Mujiangtai",
    "gn:population":0,
    "gn:timezone":"Asia/Shanghai",
    "iso:country":"CN",
    "name:zho_x_preferred":[
        "\u6728\u5320\u53f0"
    ],
    "wof:name":"Mujiangtai",
    "wof:placetype":"locality"
},
  "geometry": {"coordinates":[112.7229,30.65529],"type":"Point"}
}