{
  "type": "Feature",
  "properties": {
    "gn:admin1_code":"11.0",
    "gn:asciiname":"Shexing",
    "gn:country_code":"CN",
    "gn:dem":666,
    "gn:feature_class":"P",
    "gn:feature_code":"PPL",
    "gn:name":"Shexing",
    "gn:population":0,
    "gn:timezone":"Asia/Shanghai",
    "iso:country":"CN",
    "name:zho_x_preferred":[
        "\u86c7\u5f62"
    ],
    "wof:name":"Shexing",
    "wof:placetype":"locality"
},
  "geometry": {"coordinates":[113.81018,25.76661],"type":"Point"}
}