{
  "type": "Feature",
  "properties": {
    "gn:admin1_code":"8.0",
    "gn:asciiname":"Houguandi",
    "gn:country_code":"CN",
    "gn:dem":138,
    "gn:feature_class":"P",
    "gn:feature_code":"PPL",
    "gn:name":"Houguandi",
    "gn:population":0,
    "gn:timezone":"Asia/Shanghai",
    "iso:country":"CN",
    "name:zho_x_preferred":[
        "\u540e\u5b98\u5730"
    ],
    "wof:name":"Houguandi",
    "wof:placetype":"locality"
},
  "geometry": {"coordinates":[124.05394,46.13941],"type":"Point"}
}