{
  "type": "Feature",
  "properties": {
    "gn:admin1_code":"29",
    "gn:asciiname":"Xinshao",
    "gn:country_code":"CN",
    "gn:dem":1897,
    "gn:feature_class":"P",
    "gn:feature_code":"PPL",
    "gn:name":"Xinshao",
    "gn:population":0,
    "gn:timezone":"Asia/Shanghai",
    "iso:country":"CN",
    "name:zho_x_preferred":[
        "\u65b0\u54e8"
    ],
    "wof:name":"Xinshao",
    "wof:placetype":"locality"
},
  "geometry": {"coordinates":[103.355,24.5757],"type":"Point"}
}