{
  "type": "Feature",
  "properties": {
    "gn:admin1_code":"15.0",
    "gn:asciiname":"Wangjia Gouli",
    "gn:country_code":"CN",
    "gn:dem":1698,
    "gn:feature_class":"P",
    "gn:feature_code":"PPL",
    "gn:name":"Wangjia Gouli",
    "gn:population":0,
    "gn:timezone":"Asia/Shanghai",
    "iso:country":"CN",
    "name:zho_x_preferred":[
        "\u738b\u5bb6\u6c9f\u91cc"
    ],
    "wof:name":"Wangjia Gouli",
    "wof:placetype":"locality"
},
  "geometry": {"coordinates":[106.254,34.8077],"type":"Point"}
}