{
  "type": "Feature",
  "properties": {
    "gn:admin1_code":"32.0",
    "gn:asciiname":"Laobuzi",
    "gn:country_code":"CN",
    "gn:dem":866,
    "gn:feature_class":"P",
    "gn:feature_code":"PPL",
    "gn:name":"Laobuzi",
    "gn:population":0,
    "gn:timezone":"Asia/Shanghai",
    "iso:country":"CN",
    "name:zho_x_preferred":[
        "\u8001\u5821\u5b50"
    ],
    "wof:name":"Laobuzi",
    "wof:placetype":"locality"
},
  "geometry": {"coordinates":[102.39700000000001,29.2498],"type":"Point"}
}