{
  "type": "Feature",
  "properties": {
    "gn:admin1_code":"22.0",
    "gn:asciiname":"Hongsicun",
    "gn:country_code":"CN",
    "gn:dem":47,
    "gn:feature_class":"P",
    "gn:feature_code":"PPL",
    "gn:name":"Hongsicun",
    "gn:population":0,
    "gn:timezone":"Asia/Shanghai",
    "iso:country":"CN",
    "name:zho_x_preferred":[
        "\u7ea2\u5bfa\u6751"
    ],
    "wof:name":"Hongsicun",
    "wof:placetype":"locality"
},
  "geometry": {"coordinates":[116.78807999999999,40.1731],"type":"Point"}
}