{
  "type": "Feature",
  "properties": {
    "gn:admin1_code":"3.0",
    "gn:asciiname":"Qianyeshan",
    "gn:country_code":"CN",
    "gn:dem":52,
    "gn:feature_class":"P",
    "gn:feature_code":"PPL",
    "gn:name":"Qianyeshan",
    "gn:population":0,
    "gn:timezone":"Asia/Shanghai",
    "iso:country":"CN",
    "name:und_x_variant":[
        "\u5343\u53f6\u5c71"
    ],
    "wof:name":"Qianyeshan",
    "wof:placetype":"locality"
},
  "geometry": {"coordinates":[115.16643000000001,28.13537],"type":"Point"}
}