{
  "type": "Feature",
  "properties": {
    "gn:admin1_code":"9.0",
    "gn:asciiname":"Hulutao",
    "gn:country_code":"CN",
    "gn:dem":264,
    "gn:feature_class":"P",
    "gn:feature_code":"PPL",
    "gn:name":"Hulutao",
    "gn:population":0,
    "gn:timezone":"Asia/Shanghai",
    "iso:country":"CN",
    "name:zho_x_preferred":[
        "\u846b\u82a6\u5957"
    ],
    "wof:name":"Hulutao",
    "wof:placetype":"locality"
},
  "geometry": {"coordinates":[112.80916999999999,33.53533],"type":"Point"}
}