{
  "type": "Feature",
  "properties": {
    "gn:admin1_code":"29.0",
    "gn:asciiname":"Huangcaodi",
    "gn:country_code":"CN",
    "gn:dem":1360,
    "gn:feature_class":"P",
    "gn:feature_code":"PPL",
    "gn:name":"Huangcaodi",
    "gn:population":0,
    "gn:timezone":"Asia/Shanghai",
    "iso:country":"CN",
    "name:zho_x_preferred":[
        "\u9ec4\u8349\u5730"
    ],
    "wof:name":"Huangcaodi",
    "wof:placetype":"locality"
},
  "geometry": {"coordinates":[100.916,24.8717],"type":"Point"}
}