{
  "type": "Feature",
  "properties": {
    "gn:admin1_code":"9",
    "gn:asciiname":"Lizijian",
    "gn:country_code":"CN",
    "gn:dem":55,
    "gn:feature_class":"P",
    "gn:feature_code":"PPL",
    "gn:name":"Lizijian",
    "gn:population":0,
    "gn:timezone":"Asia/Shanghai",
    "iso:country":"CN",
    "name:zho_x_preferred":[
        "\u674e\u5b50\u8350"
    ],
    "wof:name":"Lizijian",
    "wof:placetype":"locality"
},
  "geometry": {"coordinates":[115.29300000000001,34.4163],"type":"Point"}
}