{
  "type": "Feature",
  "properties": {
    "gn:admin1_code":"30",
    "gn:asciiname":"Dananshan",
    "gn:country_code":"CN",
    "gn:dem":27,
    "gn:feature_class":"P",
    "gn:feature_code":"PPLA4",
    "gn:name":"Dananshan",
    "gn:population":0,
    "gn:timezone":"Asia/Shanghai",
    "iso:country":"CN",
    "name:und_x_variant":[
        "Dananshan Zhen",
        "\u5927\u5357\u5c71\u9547"
    ],
    "name:zho_x_preferred":[
        "\u5927\u5357\u5c71"
    ],
    "wof:name":"Dananshan",
    "wof:placetype":"locality"
},
  "geometry": {"coordinates":[116.17542,23.25838],"type":"Point"}
}