{
  "type": "Feature",
  "properties": {
    "gn:admin1_code":"1.0",
    "gn:asciiname":"Guansicun",
    "gn:country_code":"CN",
    "gn:dem":30,
    "gn:feature_class":"P",
    "gn:feature_code":"PPL",
    "gn:name":"Guansicun",
    "gn:population":0,
    "gn:timezone":"Asia/Shanghai",
    "iso:country":"CN",
    "name:zho_x_preferred":[
        "\u5173\u5bfa\u6751"
    ],
    "wof:name":"Guansicun",
    "wof:placetype":"locality"
},
  "geometry": {"coordinates":[116.27012999999999,32.95301],"type":"Point"}
}