{
  "type": "Feature",
  "properties": {
    "gn:admin1_code":"3.0",
    "gn:asciiname":"Qimutang",
    "gn:country_code":"CN",
    "gn:dem":86,
    "gn:feature_class":"P",
    "gn:feature_code":"PPL",
    "gn:name":"Qimutang",
    "gn:population":0,
    "gn:timezone":"Asia/Shanghai",
    "iso:country":"CN",
    "name:und_x_variant":[
        "\u4e03\u4ea9\u5858"
    ],
    "wof:name":"Qimutang",
    "wof:placetype":"locality"
},
  "geometry": {"coordinates":[114.80351,27.43805],"type":"Point"}
}