{
  "type": "Feature",
  "properties": {
    "gn:admin1_code":"4.0",
    "gn:asciiname":"Huapeng",
    "gn:country_code":"CN",
    "gn:dem":5,
    "gn:feature_class":"P",
    "gn:feature_code":"PPL",
    "gn:name":"Huapeng",
    "gn:population":0,
    "gn:timezone":"Asia/Shanghai",
    "iso:country":"CN",
    "name:und_x_variant":[
        "\u82b1\u5f6d"
    ],
    "name:zho_x_preferred":[
        "\u82b1\u5f6d"
    ],
    "wof:name":"Huapeng",
    "wof:placetype":"locality"
},
  "geometry": {"coordinates":[120.02831,32.37377],"type":"Point"}
}