{
  "type": "Feature",
  "properties": {
    "gn:admin1_code":"18.0",
    "gn:asciiname":"Kebing",
    "gn:country_code":"CN",
    "gn:dem":1170,
    "gn:feature_class":"P",
    "gn:feature_code":"PPL",
    "gn:name":"Kebing",
    "gn:population":0,
    "gn:timezone":"Asia/Shanghai",
    "iso:country":"CN",
    "name:zho_x_preferred":[
        "\u52ca\u70b3"
    ],
    "wof:name":"Kebing",
    "wof:placetype":"locality"
},
  "geometry": {"coordinates":[106.33199999999999,26.0281],"type":"Point"}
}