{
  "type": "Feature",
  "properties": {
    "gn:admin1_code":"11.0",
    "gn:asciiname":"Liujia Huawu",
    "gn:country_code":"CN",
    "gn:dem":155,
    "gn:feature_class":"P",
    "gn:feature_code":"PPL",
    "gn:name":"Liujia Huawu",
    "gn:population":0,
    "gn:timezone":"Asia/Shanghai",
    "iso:country":"CN",
    "name:zho_x_preferred":[
        "\u5218\u5bb6\u82b1\u5c4b"
    ],
    "wof:name":"Liujia Huawu",
    "wof:placetype":"locality"
},
  "geometry": {"coordinates":[111.97127999999999,27.81974],"type":"Point"}
}