{
  "type": "Feature",
  "properties": {
    "gn:admin1_code":"04",
    "gn:asciiname":"Tingtaijicun",
    "gn:country_code":"CN",
    "gn:dem":41,
    "gn:feature_class":"P",
    "gn:feature_code":"PPL",
    "gn:name":"Tingtaijicun",
    "gn:population":0,
    "gn:timezone":"Asia/Shanghai",
    "iso:country":"CN",
    "name:und_x_variant":[
        "T\u2019ing-t\u2019ai-chi",
        "Tingtaiji",
        "Tingtaijicun"
    ],
    "name:zho_x_preferred":[
        "\u4ead\u53f0\u96c6\u6751"
    ],
    "wof:name":"Tingtaijicun",
    "wof:placetype":"locality"
},
  "geometry": {"coordinates":[116.68488000000001,34.78113],"type":"Point"}
}