{
  "type": "Feature",
  "properties": {
    "gn:admin1_code":"24.0",
    "gn:asciiname":"Yuanzhigou",
    "gn:country_code":"CN",
    "gn:dem":1571,
    "gn:feature_class":"P",
    "gn:feature_code":"PPL",
    "gn:name":"Yuanzhigou",
    "gn:population":0,
    "gn:timezone":"Asia/Shanghai",
    "iso:country":"CN",
    "name:zho_x_preferred":[
        "\u5143\u53ea\u6c9f"
    ],
    "wof:name":"Yuanzhigou",
    "wof:placetype":"locality"
},
  "geometry": {"coordinates":[111.45891,38.29955],"type":"Point"}
}