{
  "type": "Feature",
  "properties": {
    "gn:admin1_code":"32.0",
    "gn:asciiname":"Mitanggou",
    "gn:country_code":"CN",
    "gn:dem":1940,
    "gn:feature_class":"P",
    "gn:feature_code":"PPL",
    "gn:name":"Mitanggou",
    "gn:population":0,
    "gn:timezone":"Asia/Shanghai",
    "iso:country":"CN",
    "name:zho_x_preferred":[
        "\u8ff7\u5858\u6c9f"
    ],
    "wof:name":"Mitanggou",
    "wof:placetype":"locality"
},
  "geometry": {"coordinates":[101.61129,27.13589],"type":"Point"}
}