{
  "type": "Feature",
  "properties": {
    "gn:admin1_code":"14",
    "gn:asciiname":"Gebe",
    "gn:country_code":"CN",
    "gn:dem":3709,
    "gn:feature_class":"P",
    "gn:feature_code":"PPL",
    "gn:name":"G\u00eab\u00ea",
    "gn:population":0,
    "gn:timezone":"Asia/Urumqi",
    "iso:country":"CN",
    "name:ara_x_preferred":[
        "\u062c\u064a\u0628\u064a"
    ],
    "name:bod_x_preferred":[
        "\u0f51\u0f42\u0f7a\u0f0b\u0f60\u0f56\u0f7a\u0f63"
    ],
    "name:ceb_x_preferred":[
        "Pulau Gebe"
    ],
    "name:fra_x_preferred":[
        "Gebe"
    ],
    "name:ind_x_preferred":[
        "Pulau Gebe"
    ],
    "name:ita_x_preferred":[
        "Gebe"
    ],
    "name:jav_x_preferred":[
        "Gebe"
    ],
    "name:msa_x_preferred":[
        "Gebe"
    ],
    "name:nld_x_preferred":[
        "Gebe"
    ],
    "name:pol_x_preferred":[
        "Gebe"
    ],
    "name:swe_x_preferred":[
        "Pulau Gebe"
    ],
    "wof:name":"Gebe",
    "wof:placetype":"locality"
},
  "geometry": {"coordinates":[90.21172,29.34423],"type":"Point"}
}