{
  "type": "Feature",
  "properties": {
    "gn:admin1_code":"32.0",
    "gn:asciiname":"Diaogongzhai",
    "gn:country_code":"CN",
    "gn:dem":2900,
    "gn:feature_class":"P",
    "gn:feature_code":"PPL",
    "gn:name":"Diaogongzhai",
    "gn:population":0,
    "gn:timezone":"Asia/Shanghai",
    "iso:country":"CN",
    "name:zho_x_preferred":[
        "\u5201\u516c\u5be8"
    ],
    "wof:name":"Diaogongzhai",
    "wof:placetype":"locality"
},
  "geometry": {"coordinates":[103.581,32.159],"type":"Point"}
}