{
  "type": "Feature",
  "properties": {
    "gn:admin1_code":"29",
    "gn:asciiname":"Dashuichong",
    "gn:country_code":"CN",
    "gn:dem":1829,
    "gn:feature_class":"P",
    "gn:feature_code":"PPL",
    "gn:name":"Dashuichong",
    "gn:population":0,
    "gn:timezone":"Asia/Shanghai",
    "iso:country":"CN",
    "name:zho_x_preferred":[
        "\u5927\u6c34\u51b2"
    ],
    "wof:name":"Dashuichong",
    "wof:placetype":"locality"
},
  "geometry": {"coordinates":[102.42207000000001,24.25875],"type":"Point"}
}