{
  "type": "Feature",
  "properties": {
    "gn:admin1_code":"12.0",
    "gn:asciiname":"Dangwang",
    "gn:country_code":"CN",
    "gn:dem":14,
    "gn:feature_class":"P",
    "gn:feature_code":"PPL",
    "gn:name":"Dangwang",
    "gn:population":0,
    "gn:timezone":"Asia/Shanghai",
    "iso:country":"CN",
    "name:und_x_variant":[
        "\u6321\u7f51"
    ],
    "wof:name":"Dangwang",
    "wof:placetype":"locality"
},
  "geometry": {"coordinates":[114.68899,30.43182],"type":"Point"}
}