{
  "type": "Feature",
  "properties": {
    "gn:admin1_code":"19.0",
    "gn:asciiname":"Huaiziwo",
    "gn:country_code":"CN",
    "gn:dem":9,
    "gn:feature_class":"P",
    "gn:feature_code":"PPL",
    "gn:name":"Huaiziwo",
    "gn:population":0,
    "gn:timezone":"Asia/Shanghai",
    "iso:country":"CN",
    "name:zho_x_preferred":[
        "\u69d0\u5b50\u7a9d"
    ],
    "wof:name":"Huaiziwo",
    "wof:placetype":"locality"
},
  "geometry": {"coordinates":[122.60856,41.27848],"type":"Point"}
}