{
  "type": "Feature",
  "properties": {
    "gn:admin1_code":"19.0",
    "gn:asciiname":"Meijiacun",
    "gn:country_code":"CN",
    "gn:dem":3,
    "gn:feature_class":"P",
    "gn:feature_code":"PPL",
    "gn:name":"Meijiacun",
    "gn:population":0,
    "gn:timezone":"Asia/Shanghai",
    "iso:country":"CN",
    "name:und_x_variant":[
        "Meijiawobao",
        "Meijia Wobu"
    ],
    "name:zho_x_preferred":[
        "\u6885\u5bb6\u6751"
    ],
    "name:zho_x_variant":[
        "\u6885\u5bb6\u7a9d\u5821"
    ],
    "wof:name":"Meijiacun",
    "wof:placetype":"locality"
},
  "geometry": {"coordinates":[122.42865999999999,41.4134],"type":"Point"}
}