{
  "type": "Feature",
  "properties": {
    "gn:admin1_code":"10.0",
    "gn:asciiname":"Dasonglin",
    "gn:country_code":"CN",
    "gn:dem":20,
    "gn:feature_class":"P",
    "gn:feature_code":"PPL",
    "gn:name":"Dasonglin",
    "gn:population":0,
    "gn:timezone":"Asia/Shanghai",
    "iso:country":"CN",
    "name:zho_x_preferred":[
        "\u5927\u677e\u6797"
    ],
    "wof:name":"Dasonglin",
    "wof:placetype":"locality"
},
  "geometry": {"coordinates":[118.46284,39.51633],"type":"Point"}
}