{
  "type": "Feature",
  "properties": {
    "gn:admin1_code":"12.0",
    "gn:asciiname":"Shuizhuxi",
    "gn:country_code":"CN",
    "gn:dem":782,
    "gn:feature_class":"P",
    "gn:feature_code":"PPL",
    "gn:name":"Shuizhuxi",
    "gn:population":0,
    "gn:timezone":"Asia/Shanghai",
    "iso:country":"CN",
    "name:zho_x_preferred":[
        "\u6c34\u7af9\u6eaa"
    ],
    "wof:name":"Shuizhuxi",
    "wof:placetype":"locality"
},
  "geometry": {"coordinates":[110.53230000000001,29.72911],"type":"Point"}
}