{
  "type": "Feature",
  "properties": {
    "gn:admin1_code":"11",
    "gn:asciiname":"Liangshan",
    "gn:country_code":"CN",
    "gn:dem":449,
    "gn:feature_class":"P",
    "gn:feature_code":"PPL",
    "gn:name":"Liangshan",
    "gn:population":0,
    "gn:timezone":"Asia/Shanghai",
    "iso:country":"CN",
    "name:ceb_x_preferred":[
        "Liangshan"
    ],
    "name:deu_x_preferred":[
        "Liangshan"
    ],
    "name:fra_x_preferred":[
        "Liangshan"
    ],
    "name:nor_x_preferred":[
        "Liangshan"
    ],
    "name:pol_x_preferred":[
        "Liangshan"
    ],
    "name:swe_x_preferred":[
        "Liangshan"
    ],
    "wof:name":"Liangshan",
    "wof:placetype":"locality"
},
  "geometry": {"coordinates":[110.77222,26.75361],"type":"Point"}
}