{
  "type": "Feature",
  "properties": {
    "gn:admin1_code":"32.0",
    "gn:asciiname":"Changma",
    "gn:country_code":"CN",
    "gn:dem":2707,
    "gn:feature_class":"P",
    "gn:feature_code":"PPL",
    "gn:name":"Changma",
    "gn:population":0,
    "gn:timezone":"Asia/Shanghai",
    "iso:country":"CN",
    "name:zho_x_preferred":[
        "\u957f\u9ebb"
    ],
    "wof:name":"Changma",
    "wof:placetype":"locality"
},
  "geometry": {"coordinates":[101.40600000000001,27.6458],"type":"Point"}
}