{
  "type": "Feature",
  "properties": {
    "gn:admin1_code":"29.0",
    "gn:asciiname":"Xiyangtangcun",
    "gn:country_code":"CN",
    "gn:dem":3110,
    "gn:feature_class":"P",
    "gn:feature_code":"PPL",
    "gn:name":"Xiyangtangcun",
    "gn:population":0,
    "gn:timezone":"Asia/Shanghai",
    "iso:country":"CN",
    "name:zho_x_preferred":[
        "\u6d17\u7f8a\u5858\u6751"
    ],
    "wof:name":"Xiyangtangcun",
    "wof:placetype":"locality"
},
  "geometry": {"coordinates":[103.14,27.0883],"type":"Point"}
}