{
  "type": "Feature",
  "properties": {
    "gn:admin1_code":"12.0",
    "gn:asciiname":"Zhulinzui",
    "gn:country_code":"CN",
    "gn:dem":31,
    "gn:feature_class":"P",
    "gn:feature_code":"PPL",
    "gn:name":"Zhulinzui",
    "gn:population":0,
    "gn:timezone":"Asia/Shanghai",
    "iso:country":"CN",
    "name:zho_x_preferred":[
        "\u7af9\u6797\u5480"
    ],
    "wof:name":"Zhulinzui",
    "wof:placetype":"locality"
},
  "geometry": {"coordinates":[113.88757,30.47305],"type":"Point"}
}