{
  "type": "Feature",
  "properties": {
    "gn:admin1_code":"20",
    "gn:asciiname":"Huang-t'u-ch'ang-tzu",
    "gn:country_code":"CN",
    "gn:dem":1312,
    "gn:feature_class":"P",
    "gn:feature_code":"PPL",
    "gn:name":"Huang-t\u2019u-ch\u2019ang-tzu",
    "gn:population":0,
    "gn:timezone":"Asia/Shanghai",
    "iso:country":"CN",
    "wof:name":"Huang-t'u-ch'ang-tzu",
    "wof:placetype":"locality"
},
  "geometry": {"coordinates":[116.41,42.23806],"type":"Point"}
}