{
  "type": "Feature",
  "properties": {
    "gn:admin1_code":"6.0",
    "gn:asciiname":"Niqingka",
    "gn:country_code":"CN",
    "gn:dem":3825,
    "gn:feature_class":"P",
    "gn:feature_code":"PPL",
    "gn:name":"Niqingka",
    "gn:population":0,
    "gn:timezone":"Asia/Urumqi",
    "iso:country":"CN",
    "name:zho_x_preferred":[
        "\u5c3c\u9752\u5361"
    ],
    "wof:name":"Niqingka",
    "wof:placetype":"locality"
},
  "geometry": {"coordinates":[96.93619,32.35472],"type":"Point"}
}