{
  "type": "Feature",
  "properties": {
    "gn:admin1_code":"15.0",
    "gn:asciiname":"Aihaogou",
    "gn:country_code":"CN",
    "gn:dem":2254,
    "gn:feature_class":"P",
    "gn:feature_code":"PPL",
    "gn:name":"Aihaogou",
    "gn:population":0,
    "gn:timezone":"Asia/Shanghai",
    "iso:country":"CN",
    "name:und_x_variant":[
        "\u827e\u84bf\u6c9f"
    ],
    "wof:name":"Aihaogou",
    "wof:placetype":"locality"
},
  "geometry": {"coordinates":[105.09166,35.30988],"type":"Point"}
}