{
  "type": "Feature",
  "properties": {
    "gn:admin1_code":"30.0",
    "gn:asciiname":"Houhai",
    "gn:country_code":"CN",
    "gn:dem":12,
    "gn:feature_class":"P",
    "gn:feature_code":"PPL",
    "gn:name":"Houhai",
    "gn:population":0,
    "gn:timezone":"Asia/Shanghai",
    "iso:country":"CN",
    "name:chv_x_preferred":[
        "\u0425\u043e\u0443\u0445\u0430\u0439"
    ],
    "name:deu_x_preferred":[
        "Houhai"
    ],
    "name:fin_x_preferred":[
        "Houhai"
    ],
    "name:ita_x_preferred":[
        "Houhai"
    ],
    "name:nor_x_preferred":[
        "Houhai"
    ],
    "name:rus_x_preferred":[
        "\u0425\u043e\u0443\u0445\u0430\u0439"
    ],
    "name:swe_x_preferred":[
        "Houhai"
    ],
    "name:zho_x_preferred":[
        "\u540e\u6d77"
    ],
    "wof:name":"Houhai",
    "wof:placetype":"locality"
},
  "geometry": {"coordinates":[113.92546000000002,22.51226],"type":"Point"}
}