{
  "type": "Feature",
  "properties": {
    "gn:admin1_code":"16.0",
    "gn:asciiname":"Dongguaping",
    "gn:country_code":"CN",
    "gn:dem":190,
    "gn:feature_class":"P",
    "gn:feature_code":"PPL",
    "gn:name":"Dongguaping",
    "gn:population":0,
    "gn:timezone":"Asia/Shanghai",
    "iso:country":"CN",
    "name:zho_x_preferred":[
        "\u4e1c\u74dc\u576a"
    ],
    "wof:name":"Dongguaping",
    "wof:placetype":"locality"
},
  "geometry": {"coordinates":[111.762,24.4022],"type":"Point"}
}