{
  "type": "Feature",
  "properties": {
    "gn:admin1_code":"32",
    "gn:asciiname":"Jingxi",
    "gn:cc2":"CN",
    "gn:country_code":"CN",
    "gn:dem":411,
    "gn:feature_class":"P",
    "gn:feature_code":"PPL",
    "gn:name":"Jingxi",
    "gn:population":0,
    "gn:timezone":"Asia/Shanghai",
    "iso:country":"CN",
    "name:ceb_x_preferred":[
        "Jingxi"
    ],
    "name:rus_x_preferred":[
        "\u0426\u0437\u0438\u043d\u0441\u0438"
    ],
    "name:und_x_variant":[
        "Ching-hsi"
    ],
    "wof:name":"Jingxi",
    "wof:placetype":"locality"
},
  "geometry": {"coordinates":[106.66667,30.68333],"type":"Point"}
}