{
  "type": "Feature",
  "properties": {
    "gn:admin1_code":"19.0",
    "gn:asciiname":"Dasijiazicun",
    "gn:country_code":"CN",
    "gn:dem":150,
    "gn:feature_class":"P",
    "gn:feature_code":"PPL",
    "gn:name":"Dasijiazicun",
    "gn:population":0,
    "gn:timezone":"Asia/Shanghai",
    "iso:country":"CN",
    "name:zho_x_preferred":[
        "\u5927\u56db\u5bb6\u5b50\u6751"
    ],
    "wof:name":"Dasijiazicun",
    "wof:placetype":"locality"
},
  "geometry": {"coordinates":[122.842,42.5611],"type":"Point"}
}