{
  "type": "Feature",
  "properties": {
    "gn:admin1_code":"3.0",
    "gn:asciiname":"Jiujingkeng",
    "gn:country_code":"CN",
    "gn:dem":668,
    "gn:feature_class":"P",
    "gn:feature_code":"PPL",
    "gn:name":"Jiujingkeng",
    "gn:population":0,
    "gn:timezone":"Asia/Shanghai",
    "iso:country":"CN",
    "name:zho_x_preferred":[
        "\u4e5d\u4e95\u5751"
    ],
    "wof:name":"Jiujingkeng",
    "wof:placetype":"locality"
},
  "geometry": {"coordinates":[118.01208,28.08433],"type":"Point"}
}