{
  "type": "Feature",
  "properties": {
    "gn:admin1_code":"12.0",
    "gn:asciiname":"Xiayangjiagou",
    "gn:country_code":"CN",
    "gn:dem":444,
    "gn:feature_class":"P",
    "gn:feature_code":"PPL",
    "gn:name":"Xiayangjiagou",
    "gn:population":0,
    "gn:timezone":"Asia/Shanghai",
    "iso:country":"CN",
    "name:zho_x_preferred":[
        "\u4e0b\u6768\u5bb6\u6c9f"
    ],
    "wof:name":"Xiayangjiagou",
    "wof:placetype":"locality"
},
  "geometry": {"coordinates":[111.79009000000001,31.52968],"type":"Point"}
}