{
  "type": "Feature",
  "properties": {
    "gn:admin1_code":"32.0",
    "gn:asciiname":"Huangjia Dawan",
    "gn:country_code":"CN",
    "gn:dem":563,
    "gn:feature_class":"P",
    "gn:feature_code":"PPL",
    "gn:name":"Huangjia Dawan",
    "gn:population":0,
    "gn:timezone":"Asia/Shanghai",
    "iso:country":"CN",
    "name:zho_x_preferred":[
        "\u9ec4\u5bb6\u5927\u5f2f"
    ],
    "wof:name":"Huangjia Dawan",
    "wof:placetype":"locality"
},
  "geometry": {"coordinates":[107.00502,30.30768],"type":"Point"}
}