{
  "type": "Feature",
  "properties": {
    "gn:admin1_code":"12.0",
    "gn:asciiname":"Duanjiawan",
    "gn:country_code":"CN",
    "gn:dem":42,
    "gn:feature_class":"P",
    "gn:feature_code":"PPL",
    "gn:name":"Duanjiawan",
    "gn:population":0,
    "gn:timezone":"Asia/Shanghai",
    "iso:country":"CN",
    "name:zho_x_preferred":[
        "Duanjiawan"
    ],
    "name:zho_x_variant":[
        "\u6bb5\u5bb6\u6e7e"
    ],
    "wof:name":"Duanjiawan",
    "wof:placetype":"locality"
},
  "geometry": {"coordinates":[111.90591999999999,30.31445],"type":"Point"}
}