{
  "type": "Feature",
  "properties": {
    "gn:admin1_code":"32.0",
    "gn:asciiname":"Eruoju",
    "gn:country_code":"CN",
    "gn:dem":2038,
    "gn:feature_class":"P",
    "gn:feature_code":"PPL",
    "gn:name":"Eruoju",
    "gn:population":0,
    "gn:timezone":"Asia/Shanghai",
    "iso:country":"CN",
    "name:zho_x_preferred":[
        "\u4fc4\u82e5\u5c45"
    ],
    "wof:name":"Eruoju",
    "wof:placetype":"locality"
},
  "geometry": {"coordinates":[103.992,32.3467],"type":"Point"}
}