{
  "type": "Feature",
  "properties": {
    "gn:admin1_code":"11",
    "gn:asciiname":"Dachongling",
    "gn:country_code":"CN",
    "gn:dem":179,
    "gn:feature_class":"P",
    "gn:feature_code":"PPL",
    "gn:name":"Dachongling",
    "gn:population":0,
    "gn:timezone":"Asia/Shanghai",
    "iso:country":"CN",
    "name:zho_x_preferred":[
        "\u5927\u51b2\u5cad"
    ],
    "wof:name":"Dachongling",
    "wof:placetype":"locality"
},
  "geometry": {"coordinates":[111.61197,25.45615],"type":"Point"}
}