{
  "type": "Feature",
  "properties": {
    "gn:admin1_code":"12.0",
    "gn:asciiname":"Magupo",
    "gn:country_code":"CN",
    "gn:dem":667,
    "gn:feature_class":"P",
    "gn:feature_code":"PPL",
    "gn:name":"Magupo",
    "gn:population":0,
    "gn:timezone":"Asia/Shanghai",
    "iso:country":"CN",
    "name:zho_x_preferred":[
        "\u9a6c\u53e4\u5761"
    ],
    "wof:name":"Magupo",
    "wof:placetype":"locality"
},
  "geometry": {"coordinates":[110.44555,30.50171],"type":"Point"}
}