{
  "type": "Feature",
  "properties": {
    "gn:admin1_code":"32.0",
    "gn:asciiname":"Xintianpang",
    "gn:country_code":"CN",
    "gn:dem":473,
    "gn:feature_class":"P",
    "gn:feature_code":"PPL",
    "gn:name":"Xintianpang",
    "gn:population":0,
    "gn:timezone":"Asia/Shanghai",
    "iso:country":"CN",
    "name:zho_x_preferred":[
        "\u65b0\u7530\u65c1"
    ],
    "wof:name":"Xintianpang",
    "wof:placetype":"locality"
},
  "geometry": {"coordinates":[105.07903,28.51634],"type":"Point"}
}