{
  "type": "Feature",
  "properties": {
    "gn:admin1_code":"21.0",
    "gn:asciiname":"Nangoumen Yangquan",
    "gn:country_code":"CN",
    "gn:dem":1666,
    "gn:feature_class":"P",
    "gn:feature_code":"PPL",
    "gn:name":"Nangoumen Yangquan",
    "gn:population":0,
    "gn:timezone":"Asia/Shanghai",
    "iso:country":"CN",
    "name:zho_x_preferred":[
        "\u5357\u6c9f\u95e8\u7f8a\u5708"
    ],
    "wof:name":"Nangoumen Yangquan",
    "wof:placetype":"locality"
},
  "geometry": {"coordinates":[106.098,38.9018],"type":"Point"}
}