{
  "type": "Feature",
  "properties": {
    "gn:admin1_code":"24.0",
    "gn:asciiname":"Shanconglin",
    "gn:country_code":"CN",
    "gn:dem":1755,
    "gn:feature_class":"P",
    "gn:feature_code":"PPL",
    "gn:name":"Shanconglin",
    "gn:population":0,
    "gn:timezone":"Asia/Shanghai",
    "iso:country":"CN",
    "name:und_x_variant":[
        "\u5c71\u4e1b\u6797"
    ],
    "name:zho_x_preferred":[
        "\u5c71\u4e1b\u6797"
    ],
    "wof:name":"Shanconglin",
    "wof:placetype":"locality"
},
  "geometry": {"coordinates":[112.04836,38.97495],"type":"Point"}
}