{
  "type": "Feature",
  "properties": {
    "gn:admin1_code":"14.0",
    "gn:asciiname":"Rimacun",
    "gn:country_code":"CN",
    "gn:dem":1435,
    "gn:feature_class":"P",
    "gn:feature_code":"PPL",
    "gn:name":"Rimacun",
    "gn:population":0,
    "gn:timezone":"Asia/Urumqi",
    "iso:country":"CN",
    "name:bod_x_preferred":[
        "Rima"
    ],
    "name:und_x_variant":[
        "Chayu Gongshe"
    ],
    "name:zho_x_preferred":[
        "\u65e5\u739b\u6751"
    ],
    "name:zho_x_variant":[
        "\u65e5\u739b",
        "\u5bdf\u9685\u516c\u793e"
    ],
    "wof:name":"Rimacun",
    "wof:placetype":"locality"
},
  "geometry": {"coordinates":[97.05741,28.43623],"type":"Point"}
}