{
  "type": "Feature",
  "properties": {
    "gn:admin1_code":"5.0",
    "gn:asciiname":"Xiaolingcun",
    "gn:country_code":"CN",
    "gn:dem":118,
    "gn:feature_class":"P",
    "gn:feature_code":"PPL",
    "gn:name":"Xiaolingcun",
    "gn:population":0,
    "gn:timezone":"Asia/Shanghai",
    "iso:country":"CN",
    "name:zho_x_preferred":[
        "\u5c0f\u9675\u6751"
    ],
    "wof:name":"Xiaolingcun",
    "wof:placetype":"locality"
},
  "geometry": {"coordinates":[123.84378999999998,43.57541],"type":"Point"}
}