{
  "type": "Feature",
  "properties": {
    "gn:admin1_code":"8.0",
    "gn:asciiname":"Lixiaotang",
    "gn:country_code":"CN",
    "gn:dem":253,
    "gn:feature_class":"P",
    "gn:feature_code":"PPL",
    "gn:name":"Lixiaotang",
    "gn:population":0,
    "gn:timezone":"Asia/Shanghai",
    "iso:country":"CN",
    "name:zho_x_preferred":[
        "\u674e\u5c0f\u5802"
    ],
    "wof:name":"Lixiaotang",
    "wof:placetype":"locality"
},
  "geometry": {"coordinates":[126.07792999999999,48.52628],"type":"Point"}
}