{
  "type": "Feature",
  "properties": {
    "gn:admin1_code":"32.0",
    "gn:asciiname":"Yujiagou",
    "gn:country_code":"CN",
    "gn:dem":846,
    "gn:feature_class":"P",
    "gn:feature_code":"PPL",
    "gn:name":"Yujiagou",
    "gn:population":0,
    "gn:timezone":"Asia/Shanghai",
    "iso:country":"CN",
    "name:zho_x_preferred":[
        "\u55bb\u5bb6\u6c9f"
    ],
    "wof:name":"Yujiagou",
    "wof:placetype":"locality"
},
  "geometry": {"coordinates":[106.22593999999999,28.68382],"type":"Point"}
}