{
  "type": "Feature",
  "properties": {
    "gn:admin1_code":"15.0",
    "gn:asciiname":"Wenchenggou",
    "gn:country_code":"CN",
    "gn:dem":1859,
    "gn:feature_class":"P",
    "gn:feature_code":"PPL",
    "gn:name":"Wenchenggou",
    "gn:population":0,
    "gn:timezone":"Asia/Shanghai",
    "iso:country":"CN",
    "name:zho_x_preferred":[
        "\u6e29\u6210\u6c9f"
    ],
    "wof:name":"Wenchenggou",
    "wof:placetype":"locality"
},
  "geometry": {"coordinates":[103.232,36.2999],"type":"Point"}
}