{
  "type": "Feature",
  "properties": {
    "gn:admin1_code":"32.0",
    "gn:asciiname":"Chabaya",
    "gn:country_code":"CN",
    "gn:dem":956,
    "gn:feature_class":"P",
    "gn:feature_code":"PPL",
    "gn:name":"Chabaya",
    "gn:population":0,
    "gn:timezone":"Asia/Shanghai",
    "iso:country":"CN",
    "name:zho_x_preferred":[
        "\u8336\u575d\u57ad"
    ],
    "wof:name":"Chabaya",
    "wof:placetype":"locality"
},
  "geometry": {"coordinates":[107.241,32.3036],"type":"Point"}
}