{
  "type": "Feature",
  "properties": {
    "gn:country":"CN",
    "gn:fcode":"PPL",
    "gn:population":940,
    "iso:country":"CN",
    "name:und_x_variant":[
        "Pai-mao-p\u2019ing"
    ],
    "qs:name":"Baimaoping",
    "qs:photos_9r":0,
    "qs:photos_sr":0,
    "qs:pop_sr":"2",
    "wof:name":"Baimaoping",
    "wof:placetype":"locality",
    "wof:population":940
},
  "geometry": {"coordinates":[110.36389,26.26194],"type":"Point"}
}