{
  "type": "Feature",
  "properties": {
    "gn:admin1_code":"26.0",
    "gn:asciiname":"Anshancun",
    "gn:country_code":"CN",
    "gn:dem":1108,
    "gn:feature_class":"P",
    "gn:feature_code":"PPL",
    "gn:name":"Anshancun",
    "gn:population":0,
    "gn:timezone":"Asia/Shanghai",
    "iso:country":"CN",
    "name:zho_x_preferred":[
        "\u5b89\u5584\u6751"
    ],
    "wof:name":"Anshancun",
    "wof:placetype":"locality"
},
  "geometry": {"coordinates":[109.39796,35.72304000000001],"type":"Point"}
}