{
  "type": "Feature",
  "properties": {
    "gn:admin1_code":"20.0",
    "gn:asciiname":"Hayan Hudong",
    "gn:country_code":"CN",
    "gn:dem":1454,
    "gn:feature_class":"P",
    "gn:feature_code":"PPLA4",
    "gn:name":"Hayan Hudong",
    "gn:population":0,
    "gn:timezone":"Asia/Shanghai",
    "iso:country":"CN",
    "name:und_x_variant":[
        "\u54c8\u5f66\u5ffd\u6d1e",
        "Hayan Hudong Sumu",
        "\u54c8\u5f66\u5ffd\u6d1e\u82cf\u6728"
    ],
    "wof:name":"Hayan Hudong",
    "wof:placetype":"locality"
},
  "geometry": {"coordinates":[113.30316000000001,41.44587],"type":"Point"}
}