{
  "type": "Feature",
  "properties": {
    "gn:admin1_code":"19.0",
    "gn:asciiname":"Gaotaibucun",
    "gn:country_code":"CN",
    "gn:dem":168,
    "gn:feature_class":"P",
    "gn:feature_code":"PPL",
    "gn:name":"Gaotaibucun",
    "gn:population":0,
    "gn:timezone":"Asia/Shanghai",
    "iso:country":"CN",
    "name:zho_x_preferred":[
        "\u9ad8\u53f0\u5821\u6751"
    ],
    "wof:name":"Gaotaibucun",
    "wof:placetype":"locality"
},
  "geometry": {"coordinates":[124.562,40.839],"type":"Point"}
}