{
  "type": "Feature",
  "properties": {
    "gn:admin1_code":"26.0",
    "gn:asciiname":"Laoshugou",
    "gn:country_code":"CN",
    "gn:dem":1053,
    "gn:feature_class":"P",
    "gn:feature_code":"PPL",
    "gn:name":"Laoshugou",
    "gn:population":0,
    "gn:timezone":"Asia/Shanghai",
    "iso:country":"CN",
    "name:zho_x_preferred":[
        "\u8001\u9f20\u6c9f"
    ],
    "wof:name":"Laoshugou",
    "wof:placetype":"locality"
},
  "geometry": {"coordinates":[109.47168000000001,33.40685],"type":"Point"}
}