{
  "type": "Feature",
  "properties": {
    "gn:admin1_code":"32.0",
    "gn:asciiname":"Shabai",
    "gn:country_code":"CN",
    "gn:dem":697,
    "gn:feature_class":"P",
    "gn:feature_code":"PPL",
    "gn:name":"Shabai",
    "gn:population":0,
    "gn:timezone":"Asia/Shanghai",
    "iso:country":"CN",
    "name:zho_x_preferred":[
        "\u6749\u67cf"
    ],
    "wof:name":"Shabai",
    "wof:placetype":"locality"
},
  "geometry": {"coordinates":[103.89100000000001,31.0733],"type":"Point"}
}