{
  "type": "Feature",
  "properties": {
    "gn:admin1_code":"02",
    "gn:asciiname":"Butoutang",
    "gn:cc2":"CN",
    "gn:country_code":"CN",
    "gn:dem":18,
    "gn:feature_class":"P",
    "gn:feature_code":"PPL",
    "gn:name":"Butoutang",
    "gn:population":0,
    "gn:timezone":"Asia/Shanghai",
    "iso:country":"CN",
    "name:und_x_variant":[
        "Pu-t\u2019ou-t\u2019ang",
        "Butoutang",
        "\u57e0\u5934\u5802"
    ],
    "wof:name":"Butoutang",
    "wof:placetype":"locality"
},
  "geometry": {"coordinates":[121.32639,28.63667],"type":"Point"}
}