{
  "type": "Feature",
  "properties": {
    "gn:admin1_code":"14",
    "gn:asciiname":"Naga",
    "gn:country_code":"CN",
    "gn:dem":3868,
    "gn:feature_class":"P",
    "gn:feature_code":"PPL",
    "gn:name":"Naga",
    "gn:population":0,
    "gn:timezone":"Asia/Urumqi",
    "iso:country":"CN",
    "name:zho_x_preferred":[
        "\u90a3\u560e"
    ],
    "wof:name":"Naga",
    "wof:placetype":"locality"
},
  "geometry": {"coordinates":[89.1123,29.182],"type":"Point"}
}