{
  "type": "Feature",
  "properties": {
    "gn:admin1_code":"32.0",
    "gn:asciiname":"Luxi",
    "gn:country_code":"CN",
    "gn:dem":359,
    "gn:feature_class":"P",
    "gn:feature_code":"PPL",
    "gn:name":"Luxi",
    "gn:population":0,
    "gn:timezone":"Asia/Shanghai",
    "iso:country":"CN",
    "name:zho_x_preferred":[
        "\u6cf8\u6eaa"
    ],
    "wof:name":"Luxi",
    "wof:placetype":"locality"
},
  "geometry": {"coordinates":[106.202,31.3456],"type":"Point"}
}