{
  "type": "Feature",
  "properties": {
    "gn:admin1_code":"8.0",
    "gn:asciiname":"Gaopeidongtun",
    "gn:country_code":"CN",
    "gn:dem":167,
    "gn:feature_class":"P",
    "gn:feature_code":"PPL",
    "gn:name":"Gaopeidongtun",
    "gn:population":0,
    "gn:timezone":"Asia/Shanghai",
    "iso:country":"CN",
    "name:zho_x_preferred":[
        "\u9ad8\u57f9\u4e1c\u5c6f"
    ],
    "wof:name":"Gaopeidongtun",
    "wof:placetype":"locality"
},
  "geometry": {"coordinates":[125.06865999999999,47.57677],"type":"Point"}
}