{
  "type": "Feature",
  "properties": {
    "gn:admin1_code":"32.0",
    "gn:asciiname":"Qixian'ao",
    "gn:country_code":"CN",
    "gn:dem":426,
    "gn:feature_class":"P",
    "gn:feature_code":"PPL",
    "gn:name":"Qixian\u2019ao",
    "gn:population":0,
    "gn:timezone":"Asia/Shanghai",
    "iso:country":"CN",
    "name:und_x_variant":[
        "Qixian\u2019ao"
    ],
    "name:zho_x_preferred":[
        "\u4e03\u8d24\u5773"
    ],
    "wof:name":"Qixian'ao",
    "wof:placetype":"locality"
},
  "geometry": {"coordinates":[104.858,30.013],"type":"Point"}
}