{
  "type": "Feature",
  "properties": {
    "gn:admin1_code":"04",
    "gn:asciiname":"Pantangcun",
    "gn:country_code":"CN",
    "gn:dem":34,
    "gn:feature_class":"P",
    "gn:feature_code":"PPL",
    "gn:name":"Pantangcun",
    "gn:population":0,
    "gn:timezone":"Asia/Shanghai",
    "iso:country":"CN",
    "name:und_x_variant":[
        "P\u2019an-t\u2019ang-chen",
        "Pantang",
        "Pantangcun"
    ],
    "name:zho_x_preferred":[
        "\u6f58\u5858"
    ],
    "name:zho_x_variant":[
        "\u6f58\u5858\u6751"
    ],
    "wof:name":"Pantangcun",
    "wof:placetype":"locality"
},
  "geometry": {"coordinates":[117.32111,34.16467],"type":"Point"}
}