{
  "type": "Feature",
  "properties": {
    "gn:admin1_code":"5.0",
    "gn:asciiname":"Sanjiaosicun",
    "gn:country_code":"CN",
    "gn:dem":209,
    "gn:feature_class":"P",
    "gn:feature_code":"PPL",
    "gn:name":"Sanjiaosicun",
    "gn:population":0,
    "gn:timezone":"Asia/Shanghai",
    "iso:country":"CN",
    "name:zho_x_preferred":[
        "\u4e09\u6559\u5bfa\u6751"
    ],
    "wof:name":"Sanjiaosicun",
    "wof:placetype":"locality"
},
  "geometry": {"coordinates":[124.41549000000001,44.17782],"type":"Point"}
}