{
  "type": "Feature",
  "properties": {
    "gn:admin1_code":"16.0",
    "gn:asciiname":"Wuliang",
    "gn:country_code":"CN",
    "gn:dem":153,
    "gn:feature_class":"P",
    "gn:feature_code":"PPL",
    "gn:name":"Wuliang",
    "gn:population":0,
    "gn:timezone":"Asia/Shanghai",
    "iso:country":"CN",
    "name:zho_x_preferred":[
        "\u65e0\u91cf"
    ],
    "wof:name":"Wuliang",
    "wof:placetype":"locality"
},
  "geometry": {"coordinates":[111.378,23.8316],"type":"Point"}
}