{
  "type": "Feature",
  "properties": {
    "gn:admin1_code":"29.0",
    "gn:asciiname":"Lilazhai",
    "gn:country_code":"CN",
    "gn:dem":1242,
    "gn:feature_class":"P",
    "gn:feature_code":"PPL",
    "gn:name":"Lilazhai",
    "gn:population":0,
    "gn:timezone":"Asia/Shanghai",
    "iso:country":"CN",
    "name:zho_x_preferred":[
        "\u7406\u62c9\u5be8"
    ],
    "wof:name":"Lilazhai",
    "wof:placetype":"locality"
},
  "geometry": {"coordinates":[103.901,22.951],"type":"Point"}
}