{
  "type": "Feature",
  "properties": {
    "gn:admin1_code":"15.0",
    "gn:asciiname":"Zhaogou",
    "gn:country_code":"CN",
    "gn:dem":1552,
    "gn:feature_class":"P",
    "gn:feature_code":"PPL",
    "gn:name":"Zhaogou",
    "gn:population":0,
    "gn:timezone":"Asia/Shanghai",
    "iso:country":"CN",
    "name:und_x_variant":[
        "\u8d75\u6c9f"
    ],
    "wof:name":"Zhaogou",
    "wof:placetype":"locality"
},
  "geometry": {"coordinates":[105.398,33.42318],"type":"Point"}
}