{
  "type": "Feature",
  "properties": {
    "gn:admin1_code":"30",
    "gn:asciiname":"Fengcun",
    "gn:country_code":"CN",
    "gn:dem":36,
    "gn:feature_class":"P",
    "gn:feature_code":"PPL",
    "gn:name":"Fengcun",
    "gn:population":0,
    "gn:timezone":"Asia/Urumqi",
    "iso:country":"CN",
    "name:zho_x_preferred":[
        "\u4e30\u6751"
    ],
    "wof:name":"Fengcun",
    "wof:placetype":"locality"
},
  "geometry": {"coordinates":[110.44853000000001,21.75064],"type":"Point"}
}