{
  "type": "Feature",
  "properties": {
    "gn:admin1_code":"5.0",
    "gn:asciiname":"Xinlicun",
    "gn:country_code":"CN",
    "gn:dem":235,
    "gn:feature_class":"P",
    "gn:feature_code":"PPL",
    "gn:name":"Xinlicun",
    "gn:population":0,
    "gn:timezone":"Asia/Shanghai",
    "iso:country":"CN",
    "name:zho_x_preferred":[
        "\u65b0\u7acb\u6751"
    ],
    "wof:name":"Xinlicun",
    "wof:placetype":"locality"
},
  "geometry": {"coordinates":[125.63146999999999,43.89486],"type":"Point"}
}