{
  "type": "Feature",
  "properties": {
    "gn:admin1_code":"3.0",
    "gn:asciiname":"Neiqiu",
    "gn:country_code":"CN",
    "gn:dem":310,
    "gn:feature_class":"P",
    "gn:feature_code":"PPL",
    "gn:name":"Neiqiu",
    "gn:population":0,
    "gn:timezone":"Asia/Shanghai",
    "iso:country":"CN",
    "name:und_x_variant":[
        "\u5185\u90b1"
    ],
    "wof:name":"Neiqiu",
    "wof:placetype":"locality"
},
  "geometry": {"coordinates":[114.73303,29.06648],"type":"Point"}
}