{
  "type": "Feature",
  "properties": {
    "gn:admin1_code":"30.0",
    "gn:asciiname":"Tianbian",
    "gn:country_code":"CN",
    "gn:dem":404,
    "gn:feature_class":"P",
    "gn:feature_code":"PPL",
    "gn:name":"Tianbian",
    "gn:population":0,
    "gn:timezone":"Asia/Shanghai",
    "iso:country":"CN",
    "name:zho_x_preferred":[
        "Tianbian"
    ],
    "name:zho_x_variant":[
        "\u7530\u8fb9"
    ],
    "wof:name":"Tianbian",
    "wof:placetype":"locality"
},
  "geometry": {"coordinates":[112.64082999999999,24.13111],"type":"Point"}
}