{
  "type": "Feature",
  "properties": {
    "gn:admin1_code":"2.0",
    "gn:asciiname":"Dongjiashan",
    "gn:country_code":"CN",
    "gn:dem":756,
    "gn:feature_class":"P",
    "gn:feature_code":"PPL",
    "gn:name":"Dongjiashan",
    "gn:population":0,
    "gn:timezone":"Asia/Shanghai",
    "iso:country":"CN",
    "name:zho_x_preferred":[
        "\u4e1c\u5bb6\u5c71"
    ],
    "wof:name":"Dongjiashan",
    "wof:placetype":"locality"
},
  "geometry": {"coordinates":[118.67359999999999,28.34664],"type":"Point"}
}