{
  "type": "Feature",
  "properties": {
    "gn:admin1_code":"7.0",
    "gn:asciiname":"Liushuikeng",
    "gn:country_code":"CN",
    "gn:dem":771,
    "gn:feature_class":"P",
    "gn:feature_code":"PPL",
    "gn:name":"Liushuikeng",
    "gn:population":0,
    "gn:timezone":"Asia/Shanghai",
    "iso:country":"CN",
    "name:zho_x_preferred":[
        "\u6d41\u6c34\u5751"
    ],
    "wof:name":"Liushuikeng",
    "wof:placetype":"locality"
},
  "geometry": {"coordinates":[119.34858,26.70375],"type":"Point"}
}