{
  "type": "Feature",
  "properties": {
    "gn:admin1_code":"18",
    "gn:asciiname":"Ronghong",
    "gn:country_code":"CN",
    "gn:dem":1258,
    "gn:feature_class":"P",
    "gn:feature_code":"PPL",
    "gn:name":"Ronghong",
    "gn:population":0,
    "gn:timezone":"Asia/Shanghai",
    "iso:country":"CN",
    "name:zho_x_preferred":[
        "\u5197\u6d2a"
    ],
    "wof:name":"Ronghong",
    "wof:placetype":"locality"
},
  "geometry": {"coordinates":[105.62,25.0206],"type":"Point"}
}