{
  "type": "Feature",
  "properties": {
    "iso:country":"CN",
    "name:cdo_x_preferred":[
        "D\u1e73\u0306ng-g\u00e2ing"
    ],
    "name:ceb_x_preferred":[
        "Zhong Xian"
    ],
    "name:deu_x_preferred":[
        "Zhong"
    ],
    "name:eng_x_preferred":[
        "Zhong County"
    ],
    "name:eus_x_preferred":[
        "Zhong konderria"
    ],
    "name:fas_x_preferred":[
        "\u0634\u0647\u0631\u0633\u062a\u0627\u0646 \u0698\u0648\u0646\u06af"
    ],
    "name:gan_x_preferred":[
        "\u5fe0\u53bf"
    ],
    "name:ind_x_preferred":[
        "County Zhong"
    ],
    "name:jpn_x_preferred":[
        "\u5fe0\u770c"
    ],
    "name:kor_x_preferred":[
        "\uc911\ud604"
    ],
    "name:mwl_x_preferred":[
        "Zhong"
    ],
    "name:nan_x_preferred":[
        "Tiong-ko\u0101n"
    ],
    "name:nld_x_preferred":[
        "Zhong"
    ],
    "name:nob_x_preferred":[
        "Zhong"
    ],
    "name:rus_x_preferred":[
        "\u0427\u0436\u0443\u043d\u0441\u044f\u043d\u044c"
    ],
    "name:swe_x_preferred":[
        "Zhong"
    ],
    "name:tur_x_preferred":[
        "Zhong"
    ],
    "name:urd_x_preferred":[
        "\u0698\u0648\u0646\u06af \u06a9\u0627\u0624\u0646\u0679\u06cc"
    ],
    "name:vie_x_preferred":[
        "Trung"
    ],
    "name:wuu_x_preferred":[
        "\u5fe0\u53bf"
    ],
    "name:yue_x_preferred":[
        "\u5fe0\u7e23"
    ],
    "name:zho_x_preferred":[
        "\u5fe0\u53bf"
    ],
    "qs:name":"\u5fe0\u7e23",
    "qs:name_adm0":"\u4e2d\u570b",
    "qs:name_adm1":"\u91cd\u5e86\u76f4\u8f96\u5e02",
    "qs:photos":161,
    "qs:photos_1k":33,
    "qs:photos_9k":1,
    "qs:photos_9r":4,
    "qs:photos_all":191,
    "qs:photos_sr":4,
    "qs:placetype":"LocalAdmin",
    "qs:pop_sr":"0",
    "wd:wordcount":104,
    "wof:name":"\u5fe0\u7e23",
    "wof:placetype":"localadmin"
},
  "geometry": {"coordinates":[108.0605,30.310333],"type":"Point"}
}