{
  "type": "Feature",
  "properties": {
    "iso:country":"CN",
    "qs:name":"\u5fe0\u7e23",
    "qs:name_adm0":"\u4e2d\u570b",
    "qs:name_adm1":"\u91cd\u5e86\u76f4\u8f96\u5e02",
    "qs:photos":161,
    "qs:photos_1k":33,
    "qs:photos_9k":1,
    "qs:photos_9r":4,
    "qs:photos_all":191,
    "qs:photos_sr":4,
    "qs:placetype":"LocalAdmin",
    "qs:pop_sr":"0",
    "wd:wordcount":104,
    "wof:name":"\u5fe0\u7e23",
    "wof:placetype":"localadmin"
},
  "geometry": {"coordinates":[108.0605,30.310333],"type":"Point"}
}