{
  "type": "Feature",
  "properties": {
    "gn:admin1_code":"7.0",
    "gn:asciiname":"Bailukeng",
    "gn:country_code":"CN",
    "gn:dem":81,
    "gn:feature_class":"P",
    "gn:feature_code":"PPL",
    "gn:name":"Bailukeng",
    "gn:population":0,
    "gn:timezone":"Asia/Shanghai",
    "iso:country":"CN",
    "name:zho_x_preferred":[
        "\u767d\u9732\u5751"
    ],
    "wof:name":"Bailukeng",
    "wof:placetype":"locality"
},
  "geometry": {"coordinates":[119.88706999999999,26.74108],"type":"Point"}
}