{
  "type": "Feature",
  "properties": {
    "gn:admin1_code":"32.0",
    "gn:asciiname":"Huaihuadian",
    "gn:country_code":"CN",
    "gn:dem":413,
    "gn:feature_class":"P",
    "gn:feature_code":"PPL",
    "gn:name":"Huaihuadian",
    "gn:population":0,
    "gn:timezone":"Asia/Shanghai",
    "iso:country":"CN",
    "name:zho_x_preferred":[
        "\u69d0\u82b1\u5e97"
    ],
    "wof:name":"Huaihuadian",
    "wof:placetype":"locality"
},
  "geometry": {"coordinates":[105.14,30.8471],"type":"Point"}
}