{
  "type": "Feature",
  "properties": {
    "gn:admin1_code":"33.0",
    "gn:asciiname":"Xintianpo",
    "gn:country_code":"CN",
    "gn:dem":1135,
    "gn:feature_class":"P",
    "gn:feature_code":"PPL",
    "gn:name":"Xintianpo",
    "gn:population":0,
    "gn:timezone":"Asia/Shanghai",
    "iso:country":"CN",
    "name:zho_x_preferred":[
        "\u65b0\u7530\u5761"
    ],
    "wof:name":"Xintianpo",
    "wof:placetype":"locality"
},
  "geometry": {"coordinates":[108.00429,29.22802],"type":"Point"}
}