{
  "type": "Feature",
  "properties": {
    "gn:admin1_code":"29.0",
    "gn:asciiname":"Mianhualin",
    "gn:country_code":"CN",
    "gn:dem":1793,
    "gn:feature_class":"P",
    "gn:feature_code":"PPL",
    "gn:name":"Mianhualin",
    "gn:population":0,
    "gn:timezone":"Asia/Shanghai",
    "iso:country":"CN",
    "name:zho_x_preferred":[
        "\u68c9\u82b1\u6797"
    ],
    "wof:name":"Mianhualin",
    "wof:placetype":"locality"
},
  "geometry": {"coordinates":[99.7835,24.4495],"type":"Point"}
}