{
  "type": "Feature",
  "properties": {
    "gn:admin1_code":"32.0",
    "gn:asciiname":"Honghuatang",
    "gn:country_code":"CN",
    "gn:dem":613,
    "gn:feature_class":"P",
    "gn:feature_code":"PPL",
    "gn:name":"Honghuatang",
    "gn:population":0,
    "gn:timezone":"Asia/Shanghai",
    "iso:country":"CN",
    "name:zho_x_preferred":[
        "\u7ea2\u82b1\u5858"
    ],
    "wof:name":"Honghuatang",
    "wof:placetype":"locality"
},
  "geometry": {"coordinates":[103.21899999999999,30.2777],"type":"Point"}
}