{
  "type": "Feature",
  "properties": {
    "gn:admin1_code":"26.0",
    "gn:asciiname":"Fanshipancun",
    "gn:country_code":"CN",
    "gn:dem":980,
    "gn:feature_class":"P",
    "gn:feature_code":"PPL",
    "gn:name":"Fanshipancun",
    "gn:population":0,
    "gn:timezone":"Asia/Shanghai",
    "iso:country":"CN",
    "name:zho_x_preferred":[
        "\u8303\u77f3\u7554\u6751"
    ],
    "wof:name":"Fanshipancun",
    "wof:placetype":"locality"
},
  "geometry": {"coordinates":[110.11037,37.55374000000001],"type":"Point"}
}