{
  "type": "Feature",
  "properties": {
    "gn:admin1_code":"13",
    "gn:asciiname":"Ainiwati",
    "gn:country_code":"CN",
    "gn:dem":1063,
    "gn:feature_class":"P",
    "gn:feature_code":"PPL",
    "gn:name":"Ainiwati",
    "gn:population":0,
    "gn:timezone":"Asia/Shanghai",
    "iso:country":"CN",
    "name:und_x_variant":[
        "\u827e\u5c3c\u74e6\u63d0"
    ],
    "wof:name":"Ainiwati",
    "wof:placetype":"locality"
},
  "geometry": {"coordinates":[80.35755,40.87486],"type":"Point"}
}