{
  "type": "Feature",
  "properties": {
    "gn:admin1_code":"29.0",
    "gn:asciiname":"Shupian",
    "gn:country_code":"CN",
    "gn:dem":2376,
    "gn:feature_class":"P",
    "gn:feature_code":"PPL",
    "gn:name":"Shupian",
    "gn:population":0,
    "gn:timezone":"Asia/Shanghai",
    "iso:country":"CN",
    "name:zho_x_preferred":[
        "\u672f\u7247"
    ],
    "wof:name":"Shupian",
    "wof:placetype":"locality"
},
  "geometry": {"coordinates":[99.1952,27.2545],"type":"Point"}
}