{
  "type": "Feature",
  "properties": {
    "gn:admin1_code":"11.0",
    "gn:asciiname":"Jiudouyu",
    "gn:country_code":"CN",
    "gn:dem":388,
    "gn:feature_class":"P",
    "gn:feature_code":"PPL",
    "gn:name":"Jiudouyu",
    "gn:population":0,
    "gn:timezone":"Asia/Shanghai",
    "iso:country":"CN",
    "name:zho_x_preferred":[
        "\u4e5d\u6597\u5cea"
    ],
    "wof:name":"Jiudouyu",
    "wof:placetype":"locality"
},
  "geometry": {"coordinates":[110.80275,29.72407],"type":"Point"}
}