{
  "type": "Feature",
  "properties": {
    "gn:admin1_code":"4.0",
    "gn:asciiname":"Lugengshang",
    "gn:country_code":"CN",
    "gn:dem":5,
    "gn:feature_class":"P",
    "gn:feature_code":"PPL",
    "gn:name":"Lugengshang",
    "gn:population":0,
    "gn:timezone":"Asia/Shanghai",
    "iso:country":"CN",
    "name:und_x_variant":[
        "\u9646\u66f4\u4e0a"
    ],
    "name:zho_x_preferred":[
        "\u9646\u66f4\u4e0a"
    ],
    "wof:name":"Lugengshang",
    "wof:placetype":"locality"
},
  "geometry": {"coordinates":[120.54286999999999,31.4849],"type":"Point"}
}