{
  "type": "Feature",
  "properties": {
    "gn:admin1_code":"24.0",
    "gn:asciiname":"Xiaokouzi",
    "gn:country_code":"CN",
    "gn:dem":1507,
    "gn:feature_class":"P",
    "gn:feature_code":"PPL",
    "gn:name":"Xiaokouzi",
    "gn:population":0,
    "gn:timezone":"Asia/Shanghai",
    "iso:country":"CN",
    "name:zho_x_preferred":[
        "\u5c0f\u53e3\u5b50"
    ],
    "wof:name":"Xiaokouzi",
    "wof:placetype":"locality"
},
  "geometry": {"coordinates":[111.86796,38.89957],"type":"Point"}
}