{
  "type": "Feature",
  "properties": {
    "gn:admin1_code":"13",
    "gn:asciiname":"Yujiazhuang",
    "gn:country_code":"CN",
    "gn:dem":3636,
    "gn:feature_class":"P",
    "gn:feature_code":"PPL",
    "gn:name":"Yujiazhuang",
    "gn:population":0,
    "gn:timezone":"Asia/Urumqi",
    "iso:country":"CN",
    "name:zho_x_preferred":[
        "\u4fde\u5bb6\u5e84"
    ],
    "wof:name":"Yujiazhuang",
    "wof:placetype":"locality"
},
  "geometry": {"coordinates":[88.62768,43.75756],"type":"Point"}
}