{
  "type": "Feature",
  "properties": {
    "gn:admin1_code":"24.0",
    "gn:asciiname":"Yangshe",
    "gn:country_code":"CN",
    "gn:dem":522,
    "gn:feature_class":"P",
    "gn:feature_code":"PPL",
    "gn:name":"Yangshe",
    "gn:population":0,
    "gn:timezone":"Asia/Shanghai",
    "iso:country":"CN",
    "name:zho_x_preferred":[
        "\u9633\u793e"
    ],
    "wof:name":"Yangshe",
    "wof:placetype":"locality"
},
  "geometry": {"coordinates":[111.34074,35.31584],"type":"Point"}
}