{
  "type": "Feature",
  "properties": {
    "gn:admin1_code":"4.0",
    "gn:asciiname":"Lugongshi",
    "gn:country_code":"CN",
    "gn:dem":5,
    "gn:feature_class":"P",
    "gn:feature_code":"PPL",
    "gn:name":"Lugongshi",
    "gn:population":0,
    "gn:timezone":"Asia/Shanghai",
    "iso:country":"CN",
    "name:und_x_variant":[
        "\u9646\u516c\u5e02"
    ],
    "wof:name":"Lugongshi",
    "wof:placetype":"locality"
},
  "geometry": {"coordinates":[121.20466,31.62825],"type":"Point"}
}