{
  "type": "Feature",
  "properties": {
    "gn:admin1_code":"11.0",
    "gn:asciiname":"Houjushi",
    "gn:country_code":"CN",
    "gn:dem":302,
    "gn:feature_class":"P",
    "gn:feature_code":"PPL",
    "gn:name":"Houjushi",
    "gn:population":0,
    "gn:timezone":"Asia/Shanghai",
    "iso:country":"CN",
    "name:zho_x_preferred":[
        "\u4faf\u5c45\u5ba4"
    ],
    "wof:name":"Houjushi",
    "wof:placetype":"locality"
},
  "geometry": {"coordinates":[112.62105,25.64603],"type":"Point"}
}