{
  "type": "Feature",
  "properties": {
    "gn:admin1_code":"11.0",
    "gn:asciiname":"Huaqiaoping",
    "gn:country_code":"CN",
    "gn:dem":68,
    "gn:feature_class":"P",
    "gn:feature_code":"PPL",
    "gn:name":"Huaqiaoping",
    "gn:population":0,
    "gn:timezone":"Asia/Shanghai",
    "iso:country":"CN",
    "name:zho_x_preferred":[
        "\u82b1\u6865\u576a"
    ],
    "wof:name":"Huaqiaoping",
    "wof:placetype":"locality"
},
  "geometry": {"coordinates":[111.90741,28.5919],"type":"Point"}
}