{
  "type": "Feature",
  "properties": {
    "gn:admin1_code":"32.0",
    "gn:asciiname":"Yijiapu",
    "gn:country_code":"CN",
    "gn:dem":2367,
    "gn:feature_class":"P",
    "gn:feature_code":"PPL",
    "gn:name":"Yijiapu",
    "gn:population":0,
    "gn:timezone":"Asia/Shanghai",
    "iso:country":"CN",
    "name:zho_x_preferred":[
        "\u4e00\u5bb6\u94fa"
    ],
    "wof:name":"Yijiapu",
    "wof:placetype":"locality"
},
  "geometry": {"coordinates":[102.42095,27.71153],"type":"Point"}
}