{
  "type": "Feature",
  "properties": {
    "gn:admin1_code":"19.0",
    "gn:asciiname":"Xindianzi",
    "gn:country_code":"CN",
    "gn:dem":12,
    "gn:feature_class":"P",
    "gn:feature_code":"PPL",
    "gn:name":"Xindianzi",
    "gn:population":0,
    "gn:timezone":"Asia/Shanghai",
    "iso:country":"CN",
    "name:zho_x_preferred":[
        "\u65b0\u7538\u5b50"
    ],
    "wof:name":"Xindianzi",
    "wof:placetype":"locality"
},
  "geometry": {"coordinates":[121.55092999999999,41.25217],"type":"Point"}
}