{
  "type": "Feature",
  "properties": {
    "gn:admin1_code":"9.0",
    "gn:asciiname":"Balicha",
    "gn:country_code":"CN",
    "gn:dem":52,
    "gn:feature_class":"P",
    "gn:feature_code":"PPL",
    "gn:name":"Balicha",
    "gn:population":0,
    "gn:timezone":"Asia/Shanghai",
    "iso:country":"CN",
    "name:zho_x_preferred":[
        "\u516b\u91cc\u5c94"
    ],
    "wof:name":"Balicha",
    "wof:placetype":"locality"
},
  "geometry": {"coordinates":[114.38423,33.03312],"type":"Point"}
}