{
  "type": "Feature",
  "properties": {
    "gn:admin1_code":"19.0",
    "gn:asciiname":"Qingshicun",
    "gn:country_code":"CN",
    "gn:dem":220,
    "gn:feature_class":"P",
    "gn:feature_code":"PPL",
    "gn:name":"Qingshicun",
    "gn:population":0,
    "gn:timezone":"Asia/Shanghai",
    "iso:country":"CN",
    "name:zho_x_preferred":[
        "\u9752\u77f3\u6751"
    ],
    "wof:name":"Qingshicun",
    "wof:placetype":"locality"
},
  "geometry": {"coordinates":[124.33378,42.86561],"type":"Point"}
}