{
  "type": "Feature",
  "properties": {
    "gn:admin1_code":"21.0",
    "gn:asciiname":"Xialuchaliwan",
    "gn:country_code":"CN",
    "gn:dem":1736,
    "gn:feature_class":"P",
    "gn:feature_code":"PPL",
    "gn:name":"Xialuchaliwan",
    "gn:population":0,
    "gn:timezone":"Asia/Shanghai",
    "iso:country":"CN",
    "name:zho_x_preferred":[
        "\u4e0b\u82a6\u5c94\u91cc\u6e7e"
    ],
    "wof:name":"Xialuchaliwan",
    "wof:placetype":"locality"
},
  "geometry": {"coordinates":[106.78618,36.01568],"type":"Point"}
}