{
  "type": "Feature",
  "properties": {
    "gn:admin1_code":"4.0",
    "gn:asciiname":"Yaojiatou",
    "gn:country_code":"CN",
    "gn:dem":6,
    "gn:feature_class":"P",
    "gn:feature_code":"PPL",
    "gn:name":"Yaojiatou",
    "gn:population":0,
    "gn:timezone":"Asia/Shanghai",
    "iso:country":"CN",
    "name:und_x_variant":[
        "\u59da\u5bb6\u5934"
    ],
    "name:zho_x_preferred":[
        "\u59da\u5bb6\u5934"
    ],
    "wof:name":"Yaojiatou",
    "wof:placetype":"locality"
},
  "geometry": {"coordinates":[120.09838000000001,31.84822],"type":"Point"}
}