{
  "type": "Feature",
  "properties": {
    "gn:admin1_code":"11.0",
    "gn:asciiname":"Zhaojianzhong",
    "gn:country_code":"CN",
    "gn:dem":97,
    "gn:feature_class":"P",
    "gn:feature_code":"PPL",
    "gn:name":"Zhaojianzhong",
    "gn:population":0,
    "gn:timezone":"Asia/Shanghai",
    "iso:country":"CN",
    "name:zho_x_preferred":[
        "\u8d75\u5efa\u4e2d"
    ],
    "wof:name":"Zhaojianzhong",
    "wof:placetype":"locality"
},
  "geometry": {"coordinates":[113.13648000000001,29.27244],"type":"Point"}
}