{
  "type": "Feature",
  "properties": {
    "gn:admin1_code":"12.0",
    "gn:asciiname":"Jiuliwan",
    "gn:country_code":"CN",
    "gn:dem":154,
    "gn:feature_class":"P",
    "gn:feature_code":"PPL",
    "gn:name":"Jiuliwan",
    "gn:population":0,
    "gn:timezone":"Asia/Shanghai",
    "iso:country":"CN",
    "name:zho_x_preferred":[
        "\u4e5d\u91cc\u6e7e"
    ],
    "wof:name":"Jiuliwan",
    "wof:placetype":"locality"
},
  "geometry": {"coordinates":[113.31601000000001,32.12528],"type":"Point"}
}