{
  "type": "Feature",
  "properties": {
    "gn:admin1_code":"2.0",
    "gn:asciiname":"Shenzhongwu",
    "gn:country_code":"CN",
    "gn:dem":63,
    "gn:feature_class":"P",
    "gn:feature_code":"PPL",
    "gn:name":"Shenzhongwu",
    "gn:population":0,
    "gn:timezone":"Asia/Shanghai",
    "iso:country":"CN",
    "name:und_x_variant":[
        "\u6c88\u4e2d\u575e"
    ],
    "wof:name":"Shenzhongwu",
    "wof:placetype":"locality"
},
  "geometry": {"coordinates":[119.90234,30.56078],"type":"Point"}
}