{
  "type": "Feature",
  "properties": {
    "gn:admin1_code":"15.0",
    "gn:asciiname":"Xiaoshila",
    "gn:country_code":"CN",
    "gn:dem":2383,
    "gn:feature_class":"P",
    "gn:feature_code":"PPL",
    "gn:name":"Xiaoshila",
    "gn:population":0,
    "gn:timezone":"Asia/Shanghai",
    "iso:country":"CN",
    "name:zho_x_preferred":[
        "\u5c0f\u4ec0\u62c9"
    ],
    "wof:name":"Xiaoshila",
    "wof:placetype":"locality"
},
  "geometry": {"coordinates":[102.92400000000001,36.6743],"type":"Point"}
}