{
  "type": "Feature",
  "properties": {
    "gn:admin1_code":"15.0",
    "gn:asciiname":"Hualing",
    "gn:country_code":"CN",
    "gn:dem":2349,
    "gn:feature_class":"P",
    "gn:feature_code":"PPL",
    "gn:name":"Hualing",
    "gn:population":0,
    "gn:timezone":"Asia/Shanghai",
    "iso:country":"CN",
    "name:zho_x_preferred":[
        "\u6866\u5cad"
    ],
    "wof:name":"Hualing",
    "wof:placetype":"locality"
},
  "geometry": {"coordinates":[104.18000000000001,35.7252],"type":"Point"}
}