{
  "type": "Feature",
  "properties": {
    "gn:admin1_code":"30",
    "gn:asciiname":"Dongyongkou",
    "gn:country_code":"CN",
    "gn:dem":200,
    "gn:feature_class":"P",
    "gn:feature_code":"PPL",
    "gn:name":"Dongyongkou",
    "gn:population":0,
    "gn:timezone":"Asia/Shanghai",
    "iso:country":"CN",
    "name:und_x_variant":[
        "Tung-yung",
        "Dongyong",
        "Dongyongkou"
    ],
    "name:zho_x_preferred":[
        "\u4e1c\u57c7\u53e3"
    ],
    "wof:name":"Dongyongkou",
    "wof:placetype":"locality"
},
  "geometry": {"coordinates":[111.39763000000001,22.78244],"type":"Point"}
}