{
  "type": "Feature",
  "properties": {
    "gn:admin1_code":"1.0",
    "gn:asciiname":"Huhu Jiedao",
    "gn:country_code":"CN",
    "gn:dem":52,
    "gn:feature_class":"P",
    "gn:feature_code":"PPL",
    "gn:name":"Huhu Jiedao",
    "gn:population":0,
    "gn:timezone":"Asia/Shanghai",
    "iso:country":"CN",
    "name:zho_x_preferred":[
        "\u6237\u80e1\u8857\u9053"
    ],
    "wof:name":"Huhu Jiedao",
    "wof:placetype":"locality"
},
  "geometry": {"coordinates":[116.0163,32.11072],"type":"Point"}
}