{
  "type": "Feature",
  "properties": {
    "gn:admin1_code":"2",
    "gn:asciiname":"Chuancun",
    "gn:country_code":"CN",
    "gn:dem":230,
    "gn:feature_class":"P",
    "gn:feature_code":"PPL",
    "gn:name":"Chuancun",
    "gn:population":0,
    "gn:timezone":"Asia/Shanghai",
    "iso:country":"CN",
    "name:und_x_variant":[
        "\u8239\u6751"
    ],
    "wof:name":"Chuancun",
    "wof:placetype":"locality"
},
  "geometry": {"coordinates":[119.67328000000001,30.42749],"type":"Point"}
}