{
  "type": "Feature",
  "properties": {
    "gn:admin1_code":"4.0",
    "gn:asciiname":"Houding Jiaxu",
    "gn:country_code":"CN",
    "gn:dem":5,
    "gn:feature_class":"P",
    "gn:feature_code":"PPL",
    "gn:name":"Houding Jiaxu",
    "gn:population":0,
    "gn:timezone":"Asia/Shanghai",
    "iso:country":"CN",
    "name:und_x_variant":[
        "\u540e\u4e01\u5bb6\u5729"
    ],
    "name:zho_x_preferred":[
        "\u540e\u4e01\u5bb6\u5729"
    ],
    "wof:name":"Houding Jiaxu",
    "wof:placetype":"locality"
},
  "geometry": {"coordinates":[120.50393,31.98339],"type":"Point"}
}