{
  "type": "Feature",
  "properties": {
    "gn:admin1_code":"5.0",
    "gn:asciiname":"Sipingshancun",
    "gn:country_code":"CN",
    "gn:dem":224,
    "gn:feature_class":"P",
    "gn:feature_code":"PPL",
    "gn:name":"Sipingshancun",
    "gn:population":0,
    "gn:timezone":"Asia/Shanghai",
    "iso:country":"CN",
    "name:zho_x_preferred":[
        "\u56db\u5e73\u5c71\u6751"
    ],
    "wof:name":"Sipingshancun",
    "wof:placetype":"locality"
},
  "geometry": {"coordinates":[124.54875,44.46305],"type":"Point"}
}