{
  "type": "Feature",
  "properties": {
    "gn:admin1_code":"29",
    "gn:asciiname":"Geyong",
    "gn:country_code":"CN",
    "gn:dem":1441,
    "gn:feature_class":"P",
    "gn:feature_code":"PPL",
    "gn:name":"Geyong",
    "gn:population":0,
    "gn:timezone":"Asia/Shanghai",
    "iso:country":"CN",
    "name:zho_x_preferred":[
        "\u9769\u5eb8"
    ],
    "wof:name":"Geyong",
    "wof:placetype":"locality"
},
  "geometry": {"coordinates":[104.795,24.1795],"type":"Point"}
}