{
  "type": "Feature",
  "properties": {
    "gn:admin1_code":"4.0",
    "gn:asciiname":"Guanxi",
    "gn:country_code":"CN",
    "gn:dem":13,
    "gn:feature_class":"P",
    "gn:feature_code":"PPL",
    "gn:name":"Guanxi",
    "gn:population":0,
    "gn:timezone":"Asia/Shanghai",
    "iso:country":"CN",
    "name:ast_x_preferred":[
        "Guanxi"
    ],
    "name:cat_x_preferred":[
        "Guanxi"
    ],
    "name:deu_x_preferred":[
        "Guanxi"
    ],
    "name:eus_x_preferred":[
        "Gu\u0101nxi"
    ],
    "name:fra_x_preferred":[
        "Guanxi"
    ],
    "name:heb_x_preferred":[
        "\u05d2\u05d5\u05d0\u05e0\u05e9\u05d9"
    ],
    "name:ita_x_preferred":[
        "Guanxi"
    ],
    "name:nor_x_preferred":[
        "Guanxi"
    ],
    "name:rus_x_preferred":[
        "\u0413\u0443\u0430\u043d\u044c\u0441\u0438"
    ],
    "name:spa_x_preferred":[
        "Guanxi"
    ],
    "name:swe_x_preferred":[
        "Guanxi"
    ],
    "name:zho_x_preferred":[
        "\u89c2\u6eaa"
    ],
    "name:zho_x_variant":[
        "\u5173\u7cfb"
    ],
    "wof:name":"Guanxi",
    "wof:placetype":"locality"
},
  "geometry": {"coordinates":[119.15470999999999,31.38979],"type":"Point"}
}