{
  "type": "Feature",
  "properties": {
    "gn:admin1_code":"4.0",
    "gn:asciiname":"Han'ercun",
    "gn:country_code":"CN",
    "gn:dem":26,
    "gn:feature_class":"P",
    "gn:feature_code":"PPL",
    "gn:name":"Han\u2019ercun",
    "gn:population":0,
    "gn:timezone":"Asia/Shanghai",
    "iso:country":"CN",
    "name:und_x_variant":[
        "Han\u2019ercun"
    ],
    "name:zho_x_preferred":[
        "\u97e9\u4e8c\u6751"
    ],
    "wof:name":"Han'ercun",
    "wof:placetype":"locality"
},
  "geometry": {"coordinates":[117.827,33.9333],"type":"Point"}
}