{
  "type": "Feature",
  "properties": {
    "gn:admin1_code":"9.0",
    "gn:asciiname":"Houping",
    "gn:country_code":"CN",
    "gn:dem":795,
    "gn:feature_class":"P",
    "gn:feature_code":"PPL",
    "gn:name":"Houping",
    "gn:population":0,
    "gn:timezone":"Asia/Shanghai",
    "iso:country":"CN",
    "name:und_x_variant":[
        "\u540e\u576a",
        "Houping"
    ],
    "wof:name":"Houping",
    "wof:placetype":"locality"
},
  "geometry": {"coordinates":[112.24066000000001,33.87209],"type":"Point"}
}