{
  "type": "Feature",
  "properties": {
    "gn:admin1_code":"19.0",
    "gn:asciiname":"Yejiacun",
    "gn:country_code":"CN",
    "gn:dem":172,
    "gn:feature_class":"P",
    "gn:feature_code":"PPL",
    "gn:name":"Yejiacun",
    "gn:population":0,
    "gn:timezone":"Asia/Shanghai",
    "iso:country":"CN",
    "name:und_x_variant":[
        "\u53f6\u5bb6\u6751"
    ],
    "name:zho_x_preferred":[
        "\u53f6\u5bb6\u6751"
    ],
    "wof:name":"Yejiacun",
    "wof:placetype":"locality"
},
  "geometry": {"coordinates":[124.52445,42.53884],"type":"Point"}
}