{
  "type": "Feature",
  "properties": {
    "gn:admin1_code":"24.0",
    "gn:asciiname":"Rongjiazhuang",
    "gn:country_code":"CN",
    "gn:dem":621,
    "gn:feature_class":"P",
    "gn:feature_code":"PPL",
    "gn:name":"Rongjiazhuang",
    "gn:population":0,
    "gn:timezone":"Asia/Shanghai",
    "iso:country":"CN",
    "name:zho_x_preferred":[
        "\u620e\u5bb6\u5e84"
    ],
    "wof:name":"Rongjiazhuang",
    "wof:placetype":"locality"
},
  "geometry": {"coordinates":[113.22568,38.49855],"type":"Point"}
}