{
  "type": "Feature",
  "properties": {
    "gn:admin1_code":"5.0",
    "gn:asciiname":"Xixuetangdi",
    "gn:country_code":"CN",
    "gn:dem":140,
    "gn:feature_class":"P",
    "gn:feature_code":"PPL",
    "gn:name":"Xixuetangdi",
    "gn:population":0,
    "gn:timezone":"Asia/Shanghai",
    "iso:country":"CN",
    "name:zho_x_preferred":[
        "\u897f\u5b66\u5802\u5730"
    ],
    "wof:name":"Xixuetangdi",
    "wof:placetype":"locality"
},
  "geometry": {"coordinates":[123.25641,45.41103],"type":"Point"}
}