{
  "type": "Feature",
  "properties": {
    "gn:admin1_code":"05",
    "gn:asciiname":"Hamar",
    "gn:country_code":"CN",
    "gn:dem":222,
    "gn:feature_class":"P",
    "gn:feature_code":"PPL",
    "gn:name":"Hamar",
    "gn:population":0,
    "gn:timezone":"Asia/Shanghai",
    "iso:country":"CN",
    "name:ara_x_preferred":[
        "\u0647\u0627\u0645\u0631"
    ],
    "name:azb_x_preferred":[
        "\u0647\u0627\u0645\u0627\u0631"
    ],
    "name:ben_x_preferred":[
        "\u09b9\u09cd\u09af\u09be\u09ae\u09be\u09b0"
    ],
    "name:ceb_x_preferred":[
        "Hamar"
    ],
    "name:ell_x_preferred":[
        "\u03a7\u03ac\u03bc\u03b1\u03c1"
    ],
    "name:est_x_preferred":[
        "Hamar"
    ],
    "name:hin_x_preferred":[
        "\u0939\u092e\u093e\u0930"
    ],
    "name:isl_x_preferred":[
        "Hamar"
    ],
    "name:nno_x_preferred":[
        "Hamar"
    ],
    "name:swe_x_preferred":[
        "Hamar"
    ],
    "wof:name":"Hamar",
    "wof:placetype":"locality"
},
  "geometry": {"coordinates":[125.03333000000001,44.93333],"type":"Point"}
}