{
  "type": "Feature",
  "properties": {
    "gn:admin1_code":"19.0",
    "gn:asciiname":"Waipabaoshan",
    "gn:country_code":"CN",
    "gn:dem":244,
    "gn:feature_class":"P",
    "gn:feature_code":"PPL",
    "gn:name":"Waipabaoshan",
    "gn:population":0,
    "gn:timezone":"Asia/Shanghai",
    "iso:country":"CN",
    "name:zho_x_preferred":[
        "\u5916\u722c\u5b9d\u5c71"
    ],
    "wof:name":"Waipabaoshan",
    "wof:placetype":"locality"
},
  "geometry": {"coordinates":[125.337,41.1014],"type":"Point"}
}