{
  "type": "Feature",
  "properties": {
    "gn:admin1_code":"25",
    "gn:asciiname":"Zhaohu",
    "gn:country_code":"CN",
    "gn:dem":23,
    "gn:feature_class":"P",
    "gn:feature_code":"PPL",
    "gn:name":"Zhaohu",
    "gn:population":0,
    "gn:timezone":"Asia/Shanghai",
    "iso:country":"CN",
    "name:zho_x_preferred":[
        "\u8d75\u80e1"
    ],
    "name:zho_x_variant":[
        "\u8d75\u864e\u9547"
    ],
    "wof:name":"Zhaohu",
    "wof:placetype":"locality"
},
  "geometry": {"coordinates":[117.139,37.003],"type":"Point"}
}