{
  "type": "Feature",
  "properties": {
    "gn:admin1_code":"1.0",
    "gn:asciiname":"Xingzhuangcun",
    "gn:country_code":"CN",
    "gn:dem":33,
    "gn:feature_class":"P",
    "gn:feature_code":"PPL",
    "gn:name":"Xingzhuangcun",
    "gn:population":0,
    "gn:timezone":"Asia/Shanghai",
    "iso:country":"CN",
    "name:zho_x_preferred":[
        "\u90a2\u5e84\u6751"
    ],
    "wof:name":"Xingzhuangcun",
    "wof:placetype":"locality"
},
  "geometry": {"coordinates":[115.84665,32.74511],"type":"Point"}
}