{
  "type": "Feature",
  "properties": {
    "gn:admin1_code":"11",
    "gn:asciiname":"Guojia",
    "gn:country_code":"CN",
    "gn:dem":210,
    "gn:feature_class":"P",
    "gn:feature_code":"PPL",
    "gn:name":"Guojia",
    "gn:population":0,
    "gn:timezone":"Asia/Shanghai",
    "iso:country":"CN",
    "name:zho_x_preferred":[
        "\u90ed\u5bb6"
    ],
    "wof:name":"Guojia",
    "wof:placetype":"locality"
},
  "geometry": {"coordinates":[111.16276999999999,26.4086],"type":"Point"}
}