{
  "type": "Feature",
  "properties": {
    "gn:admin1_code":"29.0",
    "gn:asciiname":"Shudugang",
    "gn:country_code":"CN",
    "gn:dem":3699,
    "gn:feature_class":"P",
    "gn:feature_code":"PPL",
    "gn:name":"Shudugang",
    "gn:population":0,
    "gn:timezone":"Asia/Shanghai",
    "iso:country":"CN",
    "name:zho_x_preferred":[
        "\u5c5e\u90fd\u5c97"
    ],
    "wof:name":"Shudugang",
    "wof:placetype":"locality"
},
  "geometry": {"coordinates":[99.92059999999999,27.8947],"type":"Point"}
}