{
  "type": "Feature",
  "properties": {
    "gn:admin1_code":"30.0",
    "gn:asciiname":"Miaoling",
    "gn:country_code":"CN",
    "gn:dem":489,
    "gn:feature_class":"P",
    "gn:feature_code":"PPL",
    "gn:name":"Miaoling",
    "gn:population":0,
    "gn:timezone":"Asia/Shanghai",
    "iso:country":"CN",
    "name:zho_x_preferred":[
        "Miaoling"
    ],
    "name:zho_x_variant":[
        "\u82d7\u5cad"
    ],
    "wof:name":"Miaoling",
    "wof:placetype":"locality"
},
  "geometry": {"coordinates":[114.92972,24.60306],"type":"Point"}
}