{
  "type": "Feature",
  "properties": {
    "gn:admin1_code":"11.0",
    "gn:asciiname":"Liushuqiao",
    "gn:country_code":"CN",
    "gn:dem":77,
    "gn:feature_class":"P",
    "gn:feature_code":"PPL",
    "gn:name":"Liushuqiao",
    "gn:population":0,
    "gn:timezone":"Asia/Shanghai",
    "iso:country":"CN",
    "name:zho_x_preferred":[
        "Liushuqiao"
    ],
    "name:zho_x_variant":[
        "\u67f3\u6811\u6865"
    ],
    "wof:name":"Liushuqiao",
    "wof:placetype":"locality"
},
  "geometry": {"coordinates":[111.78162,29.20566],"type":"Point"}
}