{
  "type": "Feature",
  "properties": {
    "gn:admin1_code":"10",
    "gn:asciiname":"Chuanlin",
    "gn:country_code":"CN",
    "gn:dem":33,
    "gn:feature_class":"P",
    "gn:feature_code":"PPL",
    "gn:name":"Chuanlin",
    "gn:population":0,
    "gn:timezone":"Asia/Shanghai",
    "iso:country":"CN",
    "name:und_x_variant":[
        "Lin-ch\u2019uan",
        "Ch\u2019uan-lin-chen",
        "Chuanlin"
    ],
    "name:zho_x_preferred":[
        "\u5ddd\u6797"
    ],
    "wof:name":"Chuanlin",
    "wof:placetype":"locality"
},
  "geometry": {"coordinates":[118.64967,39.60473],"type":"Point"}
}