{
  "type": "Feature",
  "properties": {
    "gn:admin1_code":"30",
    "gn:asciiname":"Pengcun",
    "gn:country_code":"CN",
    "gn:dem":18,
    "gn:feature_class":"P",
    "gn:feature_code":"PPL",
    "gn:name":"Pengcun",
    "gn:population":0,
    "gn:timezone":"Asia/Urumqi",
    "iso:country":"CN",
    "name:zho_x_preferred":[
        "\u5f6d\u6751"
    ],
    "wof:name":"Pengcun",
    "wof:placetype":"locality"
},
  "geometry": {"coordinates":[110.86409999999999,21.60463],"type":"Point"}
}