{
  "type": "Feature",
  "properties": {
    "gn:admin1_code":"16.0",
    "gn:asciiname":"Liubao",
    "gn:country_code":"CN",
    "gn:dem":192,
    "gn:feature_class":"P",
    "gn:feature_code":"PPL",
    "gn:name":"Liubao",
    "gn:population":0,
    "gn:timezone":"Asia/Shanghai",
    "iso:country":"CN",
    "name:zho_x_preferred":[
        "\u516d\u4fdd"
    ],
    "wof:name":"Liubao",
    "wof:placetype":"locality"
},
  "geometry": {"coordinates":[109.45699999999999,23.5524],"type":"Point"}
}