{
  "type": "Feature",
  "properties": {
    "gn:admin1_code":"15.0",
    "gn:asciiname":"Guanzhuangzitan",
    "gn:country_code":"CN",
    "gn:dem":1904,
    "gn:feature_class":"P",
    "gn:feature_code":"PPL",
    "gn:name":"Guanzhuangzitan",
    "gn:population":0,
    "gn:timezone":"Asia/Shanghai",
    "iso:country":"CN",
    "name:zho_x_preferred":[
        "\u5b98\u5e84\u5b50\u6ee9"
    ],
    "wof:name":"Guanzhuangzitan",
    "wof:placetype":"locality"
},
  "geometry": {"coordinates":[103.67100000000001,37.5032],"type":"Point"}
}