{
  "type": "Feature",
  "properties": {
    "gn:admin1_code":"12.0",
    "gn:asciiname":"Guojia Wukeng",
    "gn:country_code":"CN",
    "gn:dem":1521,
    "gn:feature_class":"P",
    "gn:feature_code":"PPL",
    "gn:name":"Guojia Wukeng",
    "gn:population":0,
    "gn:timezone":"Asia/Shanghai",
    "iso:country":"CN",
    "name:zho_x_preferred":[
        "Guojia Wukeng"
    ],
    "name:zho_x_variant":[
        "\u90ed\u5bb6\u5c4b\u5751"
    ],
    "wof:name":"Guojia Wukeng",
    "wof:placetype":"locality"
},
  "geometry": {"coordinates":[110.41434,29.89074],"type":"Point"}
}