{
  "type": "Feature",
  "properties": {
    "gn:admin1_code":"30.0",
    "gn:asciiname":"Tianzikeng",
    "gn:country_code":"CN",
    "gn:dem":447,
    "gn:feature_class":"P",
    "gn:feature_code":"PPL",
    "gn:name":"Tianzikeng",
    "gn:population":0,
    "gn:timezone":"Asia/Urumqi",
    "iso:country":"CN",
    "name:zho_x_preferred":[
        "\u7530\u5b50\u5751"
    ],
    "wof:name":"Tianzikeng",
    "wof:placetype":"locality"
},
  "geometry": {"coordinates":[111.47360999999999,22.34836],"type":"Point"}
}