{
  "type": "Feature",
  "properties": {
    "gn:admin1_code":"33.0",
    "gn:asciiname":"Hetao",
    "gn:country_code":"CN",
    "gn:dem":1550,
    "gn:feature_class":"P",
    "gn:feature_code":"PPL",
    "gn:name":"Hetao",
    "gn:population":0,
    "gn:timezone":"Asia/Shanghai",
    "iso:country":"CN",
    "name:zho_x_preferred":[
        "\u6838\u6843"
    ],
    "wof:name":"Hetao",
    "wof:placetype":"locality"
},
  "geometry": {"coordinates":[108.19667,29.74178],"type":"Point"}
}