{
  "type": "Feature",
  "properties": {
    "gn:admin1_code":"26.0",
    "gn:asciiname":"Yujiacun",
    "gn:country_code":"CN",
    "gn:dem":351,
    "gn:feature_class":"P",
    "gn:feature_code":"PPL",
    "gn:name":"Yujiacun",
    "gn:population":0,
    "gn:timezone":"Asia/Shanghai",
    "iso:country":"CN",
    "name:zho_x_preferred":[
        "\u9c7c\u5bb6\u6751"
    ],
    "wof:name":"Yujiacun",
    "wof:placetype":"locality"
},
  "geometry": {"coordinates":[109.54566,34.67162],"type":"Point"}
}