{
  "type": "Feature",
  "properties": {
    "gn:admin1_code":"32.0",
    "gn:asciiname":"Erjiasi",
    "gn:country_code":"CN",
    "gn:dem":371,
    "gn:feature_class":"P",
    "gn:feature_code":"PPL",
    "gn:name":"Erjiasi",
    "gn:population":0,
    "gn:timezone":"Asia/Shanghai",
    "iso:country":"CN",
    "name:zho_x_preferred":[
        "\u4e8c\u5bb6\u5bfa"
    ],
    "wof:name":"Erjiasi",
    "wof:placetype":"locality"
},
  "geometry": {"coordinates":[106.28,30.7519],"type":"Point"}
}