{
  "type": "Feature",
  "properties": {
    "gn:admin1_code":"18",
    "gn:asciiname":"Shuitangzhai",
    "gn:country_code":"CN",
    "gn:dem":1767,
    "gn:feature_class":"P",
    "gn:feature_code":"PPL",
    "gn:name":"Shuitangzhai",
    "gn:population":0,
    "gn:timezone":"Asia/Shanghai",
    "iso:country":"CN",
    "name:zho_x_preferred":[
        "\u6c34\u5858\u5be8"
    ],
    "wof:name":"Shuitangzhai",
    "wof:placetype":"locality"
},
  "geometry": {"coordinates":[104.88800000000001,26.2034],"type":"Point"}
}