{
  "type": "Feature",
  "properties": {
    "gn:admin1_code":"4.0",
    "gn:asciiname":"Lucaiyuan",
    "gn:country_code":"CN",
    "gn:dem":20,
    "gn:feature_class":"P",
    "gn:feature_code":"PPL",
    "gn:name":"Lucaiyuan",
    "gn:population":0,
    "gn:timezone":"Asia/Shanghai",
    "iso:country":"CN",
    "name:zho_x_preferred":[
        "\u5362\u83dc\u56ed"
    ],
    "wof:name":"Lucaiyuan",
    "wof:placetype":"locality"
},
  "geometry": {"coordinates":[118.90300000000001,33.5339],"type":"Point"}
}