{
  "type": "Feature",
  "properties": {
    "gn:admin1_code":"2.0",
    "gn:asciiname":"Maojiayang",
    "gn:country_code":"CN",
    "gn:dem":10,
    "gn:feature_class":"P",
    "gn:feature_code":"PPL",
    "gn:name":"Maojiayang",
    "gn:population":0,
    "gn:timezone":"Asia/Shanghai",
    "iso:country":"CN",
    "name:und_x_variant":[
        "\u6bdb\u5bb6\u6d0b"
    ],
    "wof:name":"Maojiayang",
    "wof:placetype":"locality"
},
  "geometry": {"coordinates":[119.82698000000001,30.80769],"type":"Point"}
}