{
  "type": "Feature",
  "properties": {
    "gn:admin1_code":"29.0",
    "gn:asciiname":"Zengyaomei",
    "gn:country_code":"CN",
    "gn:dem":2100,
    "gn:feature_class":"P",
    "gn:feature_code":"PPL",
    "gn:name":"Zengyaomei",
    "gn:population":0,
    "gn:timezone":"Asia/Shanghai",
    "iso:country":"CN",
    "name:und_x_variant":[
        "Zengmemei"
    ],
    "name:zho_x_preferred":[
        "\u589e\u4e48\u6885"
    ],
    "wof:name":"Zengyaomei",
    "wof:placetype":"locality"
},
  "geometry": {"coordinates":[101.407,25.9469],"type":"Point"}
}