{
  "type": "Feature",
  "properties": {
    "gn:admin1_code":"3.0",
    "gn:asciiname":"Xinpingcun",
    "gn:country_code":"CN",
    "gn:dem":533,
    "gn:feature_class":"P",
    "gn:feature_code":"PPL",
    "gn:name":"Xinpingcun",
    "gn:population":0,
    "gn:timezone":"Asia/Shanghai",
    "iso:country":"CN",
    "name:und_x_variant":[
        "\u65b0\u576a\u6751"
    ],
    "wof:name":"Xinpingcun",
    "wof:placetype":"locality"
},
  "geometry": {"coordinates":[116.47897,26.51132],"type":"Point"}
}