{
  "type": "Feature",
  "properties": {
    "gn:admin1_code":"11",
    "gn:asciiname":"Xia'ergongchong",
    "gn:country_code":"CN",
    "gn:dem":459,
    "gn:feature_class":"P",
    "gn:feature_code":"PPL",
    "gn:name":"Xia\u2019ergongchong",
    "gn:population":0,
    "gn:timezone":"Asia/Shanghai",
    "iso:country":"CN",
    "name:und_x_variant":[
        "Xia\u2019ergongchong"
    ],
    "name:zho_x_preferred":[
        "\u4e0b\u4e8c\u516c\u51b2"
    ],
    "wof:name":"Xia'ergongchong",
    "wof:placetype":"locality"
},
  "geometry": {"coordinates":[111.64655,27.94069],"type":"Point"}
}