{
  "type": "Feature",
  "properties": {
    "gn:admin1_code":"18",
    "gn:asciiname":"Guantianba",
    "gn:country_code":"CN",
    "gn:dem":568,
    "gn:feature_class":"P",
    "gn:feature_code":"PPL",
    "gn:name":"Guantianba",
    "gn:population":0,
    "gn:timezone":"Asia/Shanghai",
    "iso:country":"CN",
    "name:zho_x_preferred":[
        "\u5b98\u7530\u575d"
    ],
    "wof:name":"Guantianba",
    "wof:placetype":"locality"
},
  "geometry": {"coordinates":[108.13,28.239],"type":"Point"}
}