{
  "type": "Feature",
  "properties": {
    "gn:admin1_code":"19.0",
    "gn:asciiname":"Haosijiazicun",
    "gn:country_code":"CN",
    "gn:dem":282,
    "gn:feature_class":"P",
    "gn:feature_code":"PPL",
    "gn:name":"Haosijiazicun",
    "gn:population":0,
    "gn:timezone":"Asia/Shanghai",
    "iso:country":"CN",
    "name:zho_x_preferred":[
        "\u597d\u56db\u5bb6\u5b50\u6751"
    ],
    "wof:name":"Haosijiazicun",
    "wof:placetype":"locality"
},
  "geometry": {"coordinates":[121.529,42.1769],"type":"Point"}
}