{
  "type": "Feature",
  "properties": {
    "gn:admin1_code":"24.0",
    "gn:asciiname":"Yushuwan",
    "gn:country_code":"CN",
    "gn:dem":1527,
    "gn:feature_class":"P",
    "gn:feature_code":"PPL",
    "gn:name":"Yushuwan",
    "gn:population":0,
    "gn:timezone":"Asia/Shanghai",
    "iso:country":"CN",
    "name:zho_x_preferred":[
        "\u6986\u6811\u6e7e"
    ],
    "wof:name":"Yushuwan",
    "wof:placetype":"locality"
},
  "geometry": {"coordinates":[113.27046,37.36944],"type":"Point"}
}