{
  "type": "Feature",
  "properties": {
    "gn:admin1_code":"11.0",
    "gn:asciiname":"Shibanqiao",
    "gn:country_code":"CN",
    "gn:dem":93,
    "gn:feature_class":"P",
    "gn:feature_code":"PPL",
    "gn:name":"Shibanqiao",
    "gn:population":0,
    "gn:timezone":"Asia/Shanghai",
    "iso:country":"CN",
    "name:zho_x_preferred":[
        "\u77f3\u677f\u6865"
    ],
    "wof:name":"Shibanqiao",
    "wof:placetype":"locality"
},
  "geometry": {"coordinates":[113.46151,28.55199],"type":"Point"}
}