{
  "type": "Feature",
  "properties": {
    "gn:admin1_code":"26",
    "gn:asciiname":"Zaozhuang",
    "gn:country_code":"CN",
    "gn:dem":434,
    "gn:feature_class":"P",
    "gn:feature_code":"PPL",
    "gn:name":"Zaozhuang",
    "gn:population":0,
    "gn:timezone":"Asia/Shanghai",
    "iso:country":"CN",
    "name:afr_x_preferred":[
        "Zaozhuang"
    ],
    "name:ara_x_preferred":[
        "\u062a\u0633\u0627\u0648\u062a\u0634\u0648\u0627\u0646\u063a"
    ],
    "name:ast_x_preferred":[
        "Zaozhuang"
    ],
    "name:cdo_x_preferred":[
        "C\u014d\u0324-c\u014fng"
    ],
    "name:ceb_x_preferred":[
        "Zaozhuang"
    ],
    "name:ces_x_preferred":[
        "Cao-\u010duang"
    ],
    "name:che_x_preferred":[
        "\u0426\u0437\u0430\u043e\u0447\u0436\u0443\u0430\u043d"
    ],
    "name:dan_x_preferred":[
        "Zaozhuang"
    ],
    "name:deu_x_preferred":[
        "Zaozhuang"
    ],
    "name:epo_x_preferred":[
        "Zaozhuang"
    ],
    "name:eus_x_preferred":[
        "Zaozhuang"
    ],
    "name:fas_x_preferred":[
        "\u0632\u0627\u0648\u0698\u0648\u0627\u0646\u06af"
    ],
    "name:fin_x_preferred":[
        "Zaozhuang"
    ],
    "name:fra_x_preferred":[
        "Zaozhuang"
    ],
    "name:heb_x_preferred":[
        "\u05d6\u05d0\u05d5\u05d6'\u05d5\u05d0\u05e0\u05d2"
    ],
    "name:hun_x_preferred":[
        "Csaocsuang"
    ],
    "name:ita_x_preferred":[
        "Zaozhuang"
    ],
    "name:jpn_x_preferred":[
        "\u68d7\u8358\u5e02"
    ],
    "name:kik_x_preferred":[
        "Zaozhuang"
    ],
    "name:kor_x_preferred":[
        "\uc9dc\uc624\uc8a1\uc2dc"
    ],
    "name:mlg_x_preferred":[
        "Zaozhuang"
    ],
    "name:nld_x_preferred":[
        "Zaozhuang"
    ],
    "name:nno_x_preferred":[
        "Zaozhuang"
    ],
    "name:nor_x_preferred":[
        "Zaozhuang"
    ],
    "name:pol_x_preferred":[
        "Zaozhuang"
    ],
    "name:rus_x_preferred":[
        "\u0426\u0437\u0430\u043e\u0447\u0436\u0443\u0430\u043d"
    ],
    "name:spa_x_preferred":[
        "Zaozhuang"
    ],
    "name:swe_x_preferred":[
        "Zaozhuang"
    ],
    "name:tgl_x_preferred":[
        "Zaozhuang"
    ],
    "name:tur_x_preferred":[
        "Zaozhuang"
    ],
    "name:urd_x_preferred":[
        "\u0632\u0627\u0648\u0698\u0648\u0627\u0646\u06af"
    ],
    "name:vie_x_preferred":[
        "T\u1ea3o Trang"
    ],
    "name:war_x_preferred":[
        "Zaozhuang"
    ],
    "name:wuu_x_preferred":[
        "\u67a3\u5e84\u5e02"
    ],
    "name:zho_x_preferred":[
        "\u7682\u5e84"
    ],
    "name:zho_x_variant":[
        "\u67a3\u5e84\u5e02"
    ],
    "wof:name":"Zaozhuang",
    "wof:placetype":"locality"
},
  "geometry": {"coordinates":[108.29859999999999,34.28846],"type":"Point"}
}