{
  "type": "Feature",
  "properties": {
    "gn:admin1_code":"26",
    "gn:asciiname":"Zaozhuang",
    "gn:country_code":"CN",
    "gn:dem":434,
    "gn:feature_class":"P",
    "gn:feature_code":"PPL",
    "gn:name":"Zaozhuang",
    "gn:population":0,
    "gn:timezone":"Asia/Shanghai",
    "iso:country":"CN",
    "name:rus_x_preferred":[
        "\u0426\u0437\u0430\u043e\u0447\u0436\u0443\u0430\u043d"
    ],
    "name:zho_x_preferred":[
        "\u7682\u5e84"
    ],
    "wof:name":"Zaozhuang",
    "wof:placetype":"locality"
},
  "geometry": {"coordinates":[108.29859999999999,34.28846],"type":"Point"}
}