{
  "type": "Feature",
  "properties": {
    "gn:admin1_code":"2.0",
    "gn:asciiname":"Tanshang",
    "gn:country_code":"CN",
    "gn:dem":284,
    "gn:feature_class":"P",
    "gn:feature_code":"PPL",
    "gn:name":"Tanshang",
    "gn:population":0,
    "gn:timezone":"Asia/Shanghai",
    "iso:country":"CN",
    "name:und_x_variant":[
        "\u5766\u4e0a"
    ],
    "wof:name":"Tanshang",
    "wof:placetype":"locality"
},
  "geometry": {"coordinates":[119.48112999999999,30.3125],"type":"Point"}
}