{
  "type": "Feature",
  "properties": {
    "gn:admin1_code":"12.0",
    "gn:asciiname":"Baizhishu",
    "gn:country_code":"CN",
    "gn:dem":23,
    "gn:feature_class":"P",
    "gn:feature_code":"PPL",
    "gn:name":"Baizhishu",
    "gn:population":0,
    "gn:timezone":"Asia/Shanghai",
    "iso:country":"CN",
    "name:zho_x_preferred":[
        "\u767d\u679d\u6811"
    ],
    "wof:name":"Baizhishu",
    "wof:placetype":"locality"
},
  "geometry": {"coordinates":[113.90546999999999,30.80949],"type":"Point"}
}