{
  "type": "Feature",
  "properties": {
    "gn:admin1_code":"6.0",
    "gn:asciiname":"Baijiaji",
    "gn:country_code":"CN",
    "gn:dem":2757,
    "gn:feature_class":"P",
    "gn:feature_code":"PPLA4",
    "gn:name":"Baijiaji",
    "gn:population":0,
    "gn:timezone":"Asia/Shanghai",
    "iso:country":"CN",
    "name:und_x_variant":[
        "\u767d\u52a0\u96c6",
        "Tajiazangzuxiang",
        "Tajiazangzu",
        "\u5854\u52a0\u85cf\u65cf\u4e61",
        "\u5854\u52a0\u85cf\u65cf"
    ],
    "wof:name":"Baijiaji",
    "wof:placetype":"locality"
},
  "geometry": {"coordinates":[102.63772,35.97029000000001],"type":"Point"}
}