{
  "type": "Feature",
  "properties": {
    "gn:admin1_code":"7.0",
    "gn:asciiname":"Zhongnan",
    "gn:country_code":"CN",
    "gn:dem":472,
    "gn:feature_class":"P",
    "gn:feature_code":"PPL",
    "gn:name":"Zhongnan",
    "gn:population":0,
    "gn:timezone":"Asia/Shanghai",
    "iso:country":"CN",
    "name:zho_x_preferred":[
        "\u4e2d\u5357"
    ],
    "wof:name":"Zhongnan",
    "wof:placetype":"locality"
},
  "geometry": {"coordinates":[116.69638999999999,25.90853],"type":"Point"}
}