{
  "type": "Feature",
  "properties": {
    "gn:admin1_code":"32.0",
    "gn:asciiname":"Baiyangping",
    "gn:country_code":"CN",
    "gn:dem":1174,
    "gn:feature_class":"P",
    "gn:feature_code":"PPL",
    "gn:name":"Baiyangping",
    "gn:population":0,
    "gn:timezone":"Asia/Shanghai",
    "iso:country":"CN",
    "name:zho_x_preferred":[
        "\u767d\u6768\u576a"
    ],
    "wof:name":"Baiyangping",
    "wof:placetype":"locality"
},
  "geometry": {"coordinates":[103.18899999999999,30.436],"type":"Point"}
}