{
  "type": "Feature",
  "properties": {
    "gn:admin1_code":"12.0",
    "gn:asciiname":"Chen'an Yicun",
    "gn:country_code":"CN",
    "gn:dem":31,
    "gn:feature_class":"P",
    "gn:feature_code":"PPL",
    "gn:name":"Chen\u2019an Yicun",
    "gn:population":0,
    "gn:timezone":"Asia/Shanghai",
    "iso:country":"CN",
    "name:und_x_variant":[
        "Chen\u2019an Yicun"
    ],
    "name:zho_x_preferred":[
        "\u9648\u5b89\u4e00\u6751"
    ],
    "wof:name":"Chen'an Yicun",
    "wof:placetype":"locality"
},
  "geometry": {"coordinates":[114.36396999999999,30.30039],"type":"Point"}
}