{
  "type": "Feature",
  "properties": {
    "iso:country":"CN",
    "qs:name":"\u842c\u53bf\u5e02",
    "qs:name_adm0":"\u4e2d\u570b",
    "qs:name_adm1":"\u91cd\u5e86\u76f4\u8f96\u5e02",
    "qs:photos":7,
    "qs:photos_1k":1,
    "qs:photos_9k":2,
    "qs:photos_9r":5,
    "qs:photos_all":414,
    "qs:photos_sr":1,
    "qs:placetype":"LocalAdmin",
    "qs:pop_sr":"0",
    "wof:name":"\u842c\u53bf\u5e02",
    "wof:placetype":"localadmin"
},
  "geometry": {"coordinates":[108.39042600000001,30.821252],"type":"Point"}
}