{
  "type": "Feature",
  "properties": {
    "gn:admin1_code":"26.0",
    "gn:asciiname":"Yangheba",
    "gn:cc2":"CN",
    "gn:country_code":"CN",
    "gn:dem":488,
    "gn:feature_class":"P",
    "gn:feature_code":"PPL",
    "gn:name":"Yangheba",
    "gn:population":0,
    "gn:timezone":"Asia/Shanghai",
    "iso:country":"CN",
    "name:und_x_variant":[
        "Yang-ho-pa",
        "Yangheba"
    ],
    "wof:name":"Yangheba",
    "wof:placetype":"locality"
},
  "geometry": {"coordinates":[107.74250000000001,32.92055999999999],"type":"Point"}
}