{
  "type": "Feature",
  "properties": {
    "gn:admin1_code":"3.0",
    "gn:asciiname":"Yunzhangge Fengyuelou",
    "gn:country_code":"CN",
    "gn:dem":41,
    "gn:feature_class":"P",
    "gn:feature_code":"PPL",
    "gn:name":"Yunzhangge Fengyuelou",
    "gn:population":0,
    "gn:timezone":"Asia/Shanghai",
    "iso:country":"CN",
    "name:und_x_variant":[
        "\u4e91\u7ae0\u9601\u98ce\u6708\u697c"
    ],
    "wof:name":"Yunzhangge Fengyuelou",
    "wof:placetype":"locality"
},
  "geometry": {"coordinates":[114.99527,27.12075],"type":"Point"}
}