{
  "type": "Feature",
  "properties": {
    "gn:admin1_code":"4.0",
    "gn:asciiname":"Song'ancun",
    "gn:country_code":"CN",
    "gn:dem":43,
    "gn:feature_class":"P",
    "gn:feature_code":"PPL",
    "gn:name":"Song\u2019ancun",
    "gn:population":0,
    "gn:timezone":"Asia/Shanghai",
    "iso:country":"CN",
    "name:und_x_variant":[
        "Song\u2019ancun"
    ],
    "name:zho_x_preferred":[
        "\u5b8b\u5eb5\u6751"
    ],
    "wof:name":"Song'ancun",
    "wof:placetype":"locality"
},
  "geometry": {"coordinates":[116.75372,34.71191],"type":"Point"}
}