{
  "type": "Feature",
  "properties": {
    "gn:admin1_code":"18.0",
    "gn:asciiname":"Guduo",
    "gn:country_code":"CN",
    "gn:dem":859,
    "gn:feature_class":"P",
    "gn:feature_code":"PPL",
    "gn:name":"Guduo",
    "gn:population":0,
    "gn:timezone":"Asia/Shanghai",
    "iso:country":"CN",
    "name:zho_x_preferred":[
        "\u59d1\u591a"
    ],
    "wof:name":"Guduo",
    "wof:placetype":"locality"
},
  "geometry": {"coordinates":[107.809,25.6821],"type":"Point"}
}