{
  "type": "Feature",
  "properties": {
    "gn:admin1_code":"11.0",
    "gn:asciiname":"Nanzhuwan",
    "gn:country_code":"CN",
    "gn:dem":576,
    "gn:feature_class":"P",
    "gn:feature_code":"PPL",
    "gn:name":"Nanzhuwan",
    "gn:population":0,
    "gn:timezone":"Asia/Shanghai",
    "iso:country":"CN",
    "name:zho_x_preferred":[
        "\u5357\u7af9\u6e7e"
    ],
    "wof:name":"Nanzhuwan",
    "wof:placetype":"locality"
},
  "geometry": {"coordinates":[110.74406,27.86961],"type":"Point"}
}