{
  "type": "Feature",
  "properties": {
    "gn:admin1_code":"19.0",
    "gn:asciiname":"Huajialing",
    "gn:country_code":"CN",
    "gn:dem":119,
    "gn:feature_class":"P",
    "gn:feature_code":"PPL",
    "gn:name":"Huajialing",
    "gn:population":0,
    "gn:timezone":"Asia/Shanghai",
    "iso:country":"CN",
    "name:zho_x_preferred":[
        "\u82b1\u5bb6\u5cad"
    ],
    "wof:name":"Huajialing",
    "wof:placetype":"locality"
},
  "geometry": {"coordinates":[123.72333,41.50555],"type":"Point"}
}