{
  "type": "Feature",
  "properties": {
    "gn:admin1_code":"16.0",
    "gn:asciiname":"Liuji",
    "gn:country_code":"CN",
    "gn:dem":142,
    "gn:feature_class":"P",
    "gn:feature_code":"PPL",
    "gn:name":"Liuji",
    "gn:population":0,
    "gn:timezone":"Asia/Shanghai",
    "iso:country":"CN",
    "name:ceb_x_preferred":[
        "Liuji"
    ],
    "name:deu_x_preferred":[
        "Liuji"
    ],
    "name:swe_x_preferred":[
        "Liuji"
    ],
    "name:zho_x_preferred":[
        "\u516d\u6025"
    ],
    "wof:name":"Liuji",
    "wof:placetype":"locality"
},
  "geometry": {"coordinates":[110.908,24.1753],"type":"Point"}
}