{
  "type": "Feature",
  "properties": {
    "gn:admin1_code":"5.0",
    "gn:asciiname":"Fangniu Wobu",
    "gn:country_code":"CN",
    "gn:dem":173,
    "gn:feature_class":"P",
    "gn:feature_code":"PPL",
    "gn:name":"Fangniu Wobu",
    "gn:population":0,
    "gn:timezone":"Asia/Shanghai",
    "iso:country":"CN",
    "name:zho_x_preferred":[
        "\u653e\u725b\u7a9d\u5821"
    ],
    "wof:name":"Fangniu Wobu",
    "wof:placetype":"locality"
},
  "geometry": {"coordinates":[125.84516000000001,44.17834000000001],"type":"Point"}
}