{
  "type": "Feature",
  "properties": {
    "gn:admin1_code":"05",
    "gn:asciiname":"Fangchang",
    "gn:country_code":"CN",
    "gn:dem":770,
    "gn:feature_class":"P",
    "gn:feature_code":"PPL",
    "gn:name":"Fangchang",
    "gn:population":0,
    "gn:timezone":"Asia/Shanghai",
    "iso:country":"CN",
    "name:und_x_variant":[
        "\u623f\u573a"
    ],
    "wof:name":"Fangchang",
    "wof:placetype":"locality"
},
  "geometry": {"coordinates":[127.37287999999999,42.09631],"type":"Point"}
}