{
  "type": "Feature",
  "properties": {
    "gn:admin1_code":"25.0",
    "gn:asciiname":"Xuejiazhuangcun",
    "gn:country_code":"CN",
    "gn:dem":35,
    "gn:feature_class":"P",
    "gn:feature_code":"PPL",
    "gn:name":"Xuejiazhuangcun",
    "gn:population":0,
    "gn:timezone":"Asia/Shanghai",
    "iso:country":"CN",
    "name:zho_x_preferred":[
        "\u859b\u5bb6\u5e84\u6751"
    ],
    "wof:name":"Xuejiazhuangcun",
    "wof:placetype":"locality"
},
  "geometry": {"coordinates":[119.9846,36.02808],"type":"Point"}
}