{
  "type": "Feature",
  "properties": {
    "gn:admin1_code":"1.0",
    "gn:asciiname":"Longmiancun",
    "gn:country_code":"CN",
    "gn:dem":117,
    "gn:feature_class":"P",
    "gn:feature_code":"PPL",
    "gn:name":"Longmiancun",
    "gn:population":0,
    "gn:timezone":"Asia/Shanghai",
    "iso:country":"CN",
    "name:und_x_variant":[
        "Longmian"
    ],
    "name:zho_x_preferred":[
        "\u9f99\u7720\u6751"
    ],
    "wof:name":"Longmiancun",
    "wof:placetype":"locality"
},
  "geometry": {"coordinates":[116.9059,31.09071],"type":"Point"}
}