{
  "type": "Feature",
  "properties": {
    "gn:admin1_code":"19.0",
    "gn:asciiname":"Lishanzui",
    "gn:country_code":"CN",
    "gn:dem":33,
    "gn:feature_class":"P",
    "gn:feature_code":"PPL",
    "gn:name":"Lishanzui",
    "gn:population":0,
    "gn:timezone":"Asia/Shanghai",
    "iso:country":"CN",
    "name:zho_x_preferred":[
        "\u674e\u5c71\u5480"
    ],
    "wof:name":"Lishanzui",
    "wof:placetype":"locality"
},
  "geometry": {"coordinates":[121.87269000000001,39.84783],"type":"Point"}
}