{
  "type": "Feature",
  "properties": {
    "gn:admin1_code":"10",
    "gn:asciiname":"Shenglizhuang",
    "gn:country_code":"CN",
    "gn:dem":1363,
    "gn:feature_class":"P",
    "gn:feature_code":"PPL",
    "gn:name":"Shenglizhuang",
    "gn:population":0,
    "gn:timezone":"Asia/Shanghai",
    "iso:country":"CN",
    "name:zho_x_preferred":[
        "\u80dc\u5229\u5e84"
    ],
    "wof:name":"Shenglizhuang",
    "wof:placetype":"locality"
},
  "geometry": {"coordinates":[115.08677,41.60219],"type":"Point"}
}