{
  "type": "Feature",
  "properties": {
    "gn:admin1_code":"5.0",
    "gn:asciiname":"Juliangtun",
    "gn:country_code":"CN",
    "gn:dem":146,
    "gn:feature_class":"P",
    "gn:feature_code":"PPL",
    "gn:name":"Juliangtun",
    "gn:population":0,
    "gn:timezone":"Asia/Shanghai",
    "iso:country":"CN",
    "name:zho_x_preferred":[
        "\u805a\u7cae\u5c6f"
    ],
    "wof:name":"Juliangtun",
    "wof:placetype":"locality"
},
  "geometry": {"coordinates":[123.17247999999999,44.61912],"type":"Point"}
}