{
  "type": "Feature",
  "properties": {
    "gn:admin1_code":"3.0",
    "gn:asciiname":"Guowutan",
    "gn:country_code":"CN",
    "gn:dem":107,
    "gn:feature_class":"P",
    "gn:feature_code":"PPL",
    "gn:name":"Guowutan",
    "gn:population":0,
    "gn:timezone":"Asia/Shanghai",
    "iso:country":"CN",
    "name:und_x_variant":[
        "\u90ed\u5c4b\u6ee9"
    ],
    "wof:name":"Guowutan",
    "wof:placetype":"locality"
},
  "geometry": {"coordinates":[115.08176,25.89695],"type":"Point"}
}