{
  "type": "Feature",
  "properties": {
    "gn:admin1_code":"21.0",
    "gn:asciiname":"Libashi Duantou",
    "gn:country_code":"CN",
    "gn:dem":1632,
    "gn:feature_class":"P",
    "gn:feature_code":"PPL",
    "gn:name":"Libashi Duantou",
    "gn:population":0,
    "gn:timezone":"Asia/Shanghai",
    "iso:country":"CN",
    "name:zho_x_preferred":[
        "\u674e\u628a\u5f0f\u6bb5\u5934"
    ],
    "wof:name":"Libashi Duantou",
    "wof:placetype":"locality"
},
  "geometry": {"coordinates":[106.07599999999999,37.0787],"type":"Point"}
}