{
  "type": "Feature",
  "properties": {
    "gn:admin1_code":"25",
    "gn:asciiname":"Fangjia",
    "gn:country_code":"CN",
    "gn:dem":45,
    "gn:feature_class":"P",
    "gn:feature_code":"PPL",
    "gn:name":"Fangjia",
    "gn:population":0,
    "gn:timezone":"Asia/Shanghai",
    "iso:country":"CN",
    "name:zho_x_preferred":[
        "\u623f\u5bb6"
    ],
    "wof:name":"Fangjia",
    "wof:placetype":"locality"
},
  "geometry": {"coordinates":[115.92425,35.89992],"type":"Point"}
}