{
  "type": "Feature",
  "properties": {
    "gn:country":"CN",
    "gn:fcode":"PPL",
    "gn:pop":737,
    "iso:country":"CN",
    "name:unk_x_variant":[
        "Hsin-an-chen"
    ],
    "qs:name":"Xin\u2019anzhen",
    "qs:photos_9r":0,
    "qs:photos_sr":0,
    "qs:pop_sr":"2",
    "wd:wordcount":41,
    "wof:name":"Xin\u2019anzhen",
    "wof:placetype":"locality",
    "wof:population":737
},
  "geometry": {"coordinates":[117.53333000000001,39.75194],"type":"Point"}
}