{
  "type": "Feature",
  "properties": {
    "gn:country":"CN",
    "gn:fcode":"PPL",
    "gn:population":737,
    "iso:country":"CN",
    "name:deu_x_preferred":[
        "Guannan"
    ],
    "name:fas_x_preferred":[
        "\u0634\u0647\u0631\u0633\u062a\u0627\u0646 \u06af\u0648\u0627\u0646\u0646\u0627\u0646"
    ],
    "name:jpn_x_preferred":[
        "\u704c\u5357\u770c"
    ],
    "name:kor_x_preferred":[
        "\uad00\ub09c\ud604"
    ],
    "name:nor_x_preferred":[
        "Guannan"
    ],
    "name:rus_x_preferred":[
        "\u0413\u0443\u0430\u043d\u044c\u043d\u0430\u043d\u044c"
    ],
    "name:swe_x_preferred":[
        "Guannan"
    ],
    "name:und_x_variant":[
        "Hsin-an-chen"
    ],
    "name:urd_x_preferred":[
        "\u06af\u0648\u0627\u0646\u0646\u0627\u0646 \u06a9\u0627\u0624\u0646\u0679\u06cc"
    ],
    "name:vie_x_preferred":[
        "Qu\u00e1n Nam"
    ],
    "name:zho_x_preferred":[
        "\u704c\u5357\u53bf"
    ],
    "qs:name":"Xin\u2019anzhen",
    "qs:photos_9r":0,
    "qs:photos_sr":0,
    "qs:pop_sr":"2",
    "wd:wordcount":41,
    "wof:name":"Xin\u2019anzhen",
    "wof:placetype":"locality",
    "wof:population":737
},
  "geometry": {"coordinates":[117.53333000000001,39.75194],"type":"Point"}
}