{
  "type": "Feature",
  "properties": {
    "gn:admin1_code":"20.0",
    "gn:asciiname":"Qianliu Tonghao",
    "gn:country_code":"CN",
    "gn:dem":1689,
    "gn:feature_class":"P",
    "gn:feature_code":"PPL",
    "gn:name":"Qianliu Tonghao",
    "gn:population":0,
    "gn:timezone":"Asia/Shanghai",
    "iso:country":"CN",
    "name:und_x_variant":[
        "\u524d\u6d41\u901a\u58d5"
    ],
    "wof:name":"Qianliu Tonghao",
    "wof:placetype":"locality"
},
  "geometry": {"coordinates":[110.78958,41.3239],"type":"Point"}
}