{
  "type": "Feature",
  "properties": {
    "gn:admin1_code":"8.0",
    "gn:asciiname":"Changshuihe Nongchang Xumuchang",
    "gn:country_code":"CN",
    "gn:dem":331,
    "gn:feature_class":"P",
    "gn:feature_code":"PPLF",
    "gn:name":"Changshuihe Nongchang Xumuchang",
    "gn:population":0,
    "gn:timezone":"Asia/Shanghai",
    "iso:country":"CN",
    "name:zho_x_preferred":[
        "\u957f\u6c34\u6cb3\u519c\u573a\u755c\u7267\u573a"
    ],
    "wof:name":"Changshuihe Nongchang Xumuchang",
    "wof:placetype":"locality"
},
  "geometry": {"coordinates":[126.94669,48.50135],"type":"Point"}
}