{
  "type": "Feature",
  "properties": {
    "gn:admin1_code":"25",
    "gn:asciiname":"Bugetun",
    "gn:country_code":"CN",
    "gn:dem":49,
    "gn:feature_class":"P",
    "gn:feature_code":"PPL",
    "gn:name":"Bugetun",
    "gn:population":0,
    "gn:timezone":"Asia/Shanghai",
    "iso:country":"CN",
    "name:zho_x_preferred":[
        "\u535c\u5404\u5c6f"
    ],
    "wof:name":"Bugetun",
    "wof:placetype":"locality"
},
  "geometry": {"coordinates":[115.831,35.7895],"type":"Point"}
}