{
  "type": "Feature",
  "properties": {
    "gn:admin1_code":"5.0",
    "gn:asciiname":"Jingjia Wobu",
    "gn:country_code":"CN",
    "gn:dem":145,
    "gn:feature_class":"P",
    "gn:feature_code":"PPL",
    "gn:name":"Jingjia Wobu",
    "gn:population":0,
    "gn:timezone":"Asia/Shanghai",
    "iso:country":"CN",
    "name:zho_x_preferred":[
        "\u4e95\u5bb6\u7a9d\u5821"
    ],
    "wof:name":"Jingjia Wobu",
    "wof:placetype":"locality"
},
  "geometry": {"coordinates":[123.4696,44.50417],"type":"Point"}
}