{
  "type": "Feature",
  "properties": {
    "gn:admin1_code":"5.0",
    "gn:asciiname":"Bawangzhuang",
    "gn:country_code":"CN",
    "gn:dem":168,
    "gn:feature_class":"P",
    "gn:feature_code":"PPL",
    "gn:name":"Bawangzhuang",
    "gn:population":0,
    "gn:timezone":"Asia/Shanghai",
    "iso:country":"CN",
    "name:zho_x_preferred":[
        "\u9738\u738b\u5e84"
    ],
    "wof:name":"Bawangzhuang",
    "wof:placetype":"locality"
},
  "geometry": {"coordinates":[124.43527,43.35055],"type":"Point"}
}