{
  "type": "Feature",
  "properties": {
    "gn:admin1_code":"4.0",
    "gn:asciiname":"Yuejin Hezhuang",
    "gn:country_code":"CN",
    "gn:dem":7,
    "gn:feature_class":"P",
    "gn:feature_code":"PPL",
    "gn:name":"Yuejin Hezhuang",
    "gn:population":0,
    "gn:timezone":"Asia/Shanghai",
    "iso:country":"CN",
    "name:zho_x_preferred":[
        "\u8dc3\u8fdb\u6cb3\u5e84"
    ],
    "wof:name":"Yuejin Hezhuang",
    "wof:placetype":"locality"
},
  "geometry": {"coordinates":[119.22579,32.91759],"type":"Point"}
}