{
  "type": "Feature",
  "properties": {
    "gn:admin1_code":"16.0",
    "gn:asciiname":"Hanshu",
    "gn:country_code":"CN",
    "gn:dem":793,
    "gn:feature_class":"P",
    "gn:feature_code":"PPL",
    "gn:name":"Hanshu",
    "gn:population":0,
    "gn:timezone":"Asia/Shanghai",
    "iso:country":"CN",
    "name:zho_x_preferred":[
        "\u5bd2\u8212"
    ],
    "wof:name":"Hanshu",
    "wof:placetype":"locality"
},
  "geometry": {"coordinates":[105.584,24.3458],"type":"Point"}
}