{
  "type": "Feature",
  "properties": {
    "gn:admin1_code":"11.0",
    "gn:asciiname":"Shuidiwan",
    "gn:country_code":"CN",
    "gn:dem":299,
    "gn:feature_class":"P",
    "gn:feature_code":"PPL",
    "gn:name":"Shuidiwan",
    "gn:population":0,
    "gn:timezone":"Asia/Shanghai",
    "iso:country":"CN",
    "name:zho_x_preferred":[
        "\u6c34\u6ef4\u6e7e"
    ],
    "wof:name":"Shuidiwan",
    "wof:placetype":"locality"
},
  "geometry": {"coordinates":[109.89847,27.20913],"type":"Point"}
}