{
  "type": "Feature",
  "properties": {
    "gn:admin1_code":"15.0",
    "gn:asciiname":"Lenggan",
    "gn:country_code":"CN",
    "gn:dem":2260,
    "gn:feature_class":"P",
    "gn:feature_code":"PPL",
    "gn:name":"Lenggan",
    "gn:population":0,
    "gn:timezone":"Asia/Shanghai",
    "iso:country":"CN",
    "name:zho_x_preferred":[
        "\u5844\u5e72"
    ],
    "wof:name":"Lenggan",
    "wof:placetype":"locality"
},
  "geometry": {"coordinates":[103.742,35.3236],"type":"Point"}
}