{
  "type": "Feature",
  "properties": {
    "gn:admin1_code":"14.0",
    "gn:asciiname":"Quzhen",
    "gn:country_code":"CN",
    "gn:dem":4435,
    "gn:feature_class":"P",
    "gn:feature_code":"PPL",
    "gn:name":"Quzhen",
    "gn:population":0,
    "gn:timezone":"Asia/Urumqi",
    "iso:country":"CN",
    "name:zho_x_preferred":[
        "\u66f2\u771f"
    ],
    "wof:name":"Quzhen",
    "wof:placetype":"locality"
},
  "geometry": {"coordinates":[92.20592000000001,28.91289],"type":"Point"}
}