{
  "type": "Feature",
  "properties": {
    "gn:admin1_code":"24.0",
    "gn:asciiname":"Yaozhuang",
    "gn:cc2":"CN",
    "gn:country_code":"CN",
    "gn:dem":942,
    "gn:feature_class":"P",
    "gn:feature_code":"PPL",
    "gn:name":"Yaozhuang",
    "gn:population":0,
    "gn:timezone":"Asia/Shanghai",
    "iso:country":"CN",
    "name:und_x_variant":[
        "Yao-chuang",
        "Yaozhuang"
    ],
    "wof:name":"Yaozhuang",
    "wof:placetype":"locality"
},
  "geometry": {"coordinates":[111.12888999999998,39.00556],"type":"Point"}
}