{
  "type": "Feature",
  "properties": {
    "gn:admin1_code":"26.0",
    "gn:asciiname":"Madi Goucun",
    "gn:country_code":"CN",
    "gn:dem":1181,
    "gn:feature_class":"P",
    "gn:feature_code":"PPL",
    "gn:name":"Madi Goucun",
    "gn:population":0,
    "gn:timezone":"Asia/Shanghai",
    "iso:country":"CN",
    "name:zho_x_preferred":[
        "\u9ebb\u5730\u6c9f\u6751"
    ],
    "wof:name":"Madi Goucun",
    "wof:placetype":"locality"
},
  "geometry": {"coordinates":[109.422,37.5197],"type":"Point"}
}