{
  "type": "Feature",
  "properties": {
    "gn:admin1_code":"26.0",
    "gn:asciiname":"Qujiawancun",
    "gn:country_code":"CN",
    "gn:dem":796,
    "gn:feature_class":"P",
    "gn:feature_code":"PPL",
    "gn:name":"Qujiawancun",
    "gn:population":0,
    "gn:timezone":"Asia/Shanghai",
    "iso:country":"CN",
    "name:zho_x_preferred":[
        "\u5c48\u5bb6\u6e7e\u6751"
    ],
    "wof:name":"Qujiawancun",
    "wof:placetype":"locality"
},
  "geometry": {"coordinates":[107.0154,34.7737],"type":"Point"}
}