{
  "type": "Feature",
  "properties": {
    "gn:admin1_code":"11.0",
    "gn:asciiname":"Wakeng",
    "gn:country_code":"CN",
    "gn:dem":759,
    "gn:feature_class":"P",
    "gn:feature_code":"PPL",
    "gn:name":"Wakeng",
    "gn:population":0,
    "gn:timezone":"Asia/Shanghai",
    "iso:country":"CN",
    "name:zho_x_preferred":[
        "\u74e6\u5751"
    ],
    "wof:name":"Wakeng",
    "wof:placetype":"locality"
},
  "geometry": {"coordinates":[113.36305,25.51715],"type":"Point"}
}