{
  "type": "Feature",
  "properties": {
    "gn:admin1_code":"2.0",
    "gn:asciiname":"Fengshutou",
    "gn:country_code":"CN",
    "gn:dem":151,
    "gn:feature_class":"P",
    "gn:feature_code":"PPL",
    "gn:name":"Fengshutou",
    "gn:population":0,
    "gn:timezone":"Asia/Shanghai",
    "iso:country":"CN",
    "name:zho_x_preferred":[
        "\u67ab\u6811\u5934"
    ],
    "wof:name":"Fengshutou",
    "wof:placetype":"locality"
},
  "geometry": {"coordinates":[120.36802,29.45709],"type":"Point"}
}