{
  "type": "Feature",
  "properties": {
    "gn:admin1_code":"3.0",
    "gn:asciiname":"Chengshang Wangjia",
    "gn:country_code":"CN",
    "gn:dem":40,
    "gn:feature_class":"P",
    "gn:feature_code":"PPL",
    "gn:name":"Chengshang Wangjia",
    "gn:population":0,
    "gn:timezone":"Asia/Shanghai",
    "iso:country":"CN",
    "name:und_x_variant":[
        "\u57ce\u4e0a\u738b\u5bb6"
    ],
    "wof:name":"Chengshang Wangjia",
    "wof:placetype":"locality"
},
  "geometry": {"coordinates":[116.95726999999999,28.39925],"type":"Point"}
}