{
  "type": "Feature",
  "properties": {
    "gn:admin1_code":"32.0",
    "gn:asciiname":"Lepa",
    "gn:country_code":"CN",
    "gn:dem":2125,
    "gn:feature_class":"P",
    "gn:feature_code":"PPL",
    "gn:name":"Lepa",
    "gn:population":0,
    "gn:timezone":"Asia/Shanghai",
    "iso:country":"CN",
    "name:ceb_x_preferred":[
        "Lepa"
    ],
    "name:deu_x_preferred":[
        "Lepa"
    ],
    "name:swe_x_preferred":[
        "Lepa"
    ],
    "name:zho_x_preferred":[
        "\u52d2\u5e15"
    ],
    "wof:name":"Lepa",
    "wof:placetype":"locality"
},
  "geometry": {"coordinates":[102.271,28.6981],"type":"Point"}
}