{
  "type": "Feature",
  "properties": {
    "gn:admin1_code":"16.0",
    "gn:asciiname":"Longzhuashan",
    "gn:country_code":"CN",
    "gn:dem":619,
    "gn:feature_class":"P",
    "gn:feature_code":"PPL",
    "gn:name":"Longzhuashan",
    "gn:population":0,
    "gn:timezone":"Asia/Shanghai",
    "iso:country":"CN",
    "name:zho_x_preferred":[
        "\u9f99\u722a\u5c71"
    ],
    "wof:name":"Longzhuashan",
    "wof:placetype":"locality"
},
  "geometry": {"coordinates":[107.68899999999999,24.9486],"type":"Point"}
}