{
  "type": "Feature",
  "properties": {
    "gn:admin1_code":"30.0",
    "gn:asciiname":"Nanmuzhai",
    "gn:country_code":"CN",
    "gn:dem":59,
    "gn:feature_class":"P",
    "gn:feature_code":"PPL",
    "gn:name":"Nanmuzhai",
    "gn:population":0,
    "gn:timezone":"Asia/Shanghai",
    "iso:country":"CN",
    "name:zho_x_preferred":[
        "\u5357\u6728\u5be8"
    ],
    "wof:name":"Nanmuzhai",
    "wof:placetype":"locality"
},
  "geometry": {"coordinates":[112.31746,23.62829],"type":"Point"}
}