{
  "type": "Feature",
  "properties": {
    "gn:admin1_code":"29.0",
    "gn:asciiname":"Dongjia Lada",
    "gn:country_code":"CN",
    "gn:dem":2780,
    "gn:feature_class":"P",
    "gn:feature_code":"PPL",
    "gn:name":"Dongjia Lada",
    "gn:population":0,
    "gn:timezone":"Asia/Shanghai",
    "iso:country":"CN",
    "name:zho_x_preferred":[
        "\u8463\u5bb6\u62c9\u6253"
    ],
    "wof:name":"Dongjia Lada",
    "wof:placetype":"locality"
},
  "geometry": {"coordinates":[101.009,26.9805],"type":"Point"}
}