{
  "type": "Feature",
  "properties": {
    "gn:admin1_code":"18.0",
    "gn:asciiname":"Donggan",
    "gn:country_code":"CN",
    "gn:dem":538,
    "gn:feature_class":"P",
    "gn:feature_code":"PPL",
    "gn:name":"Donggan",
    "gn:population":0,
    "gn:timezone":"Asia/Shanghai",
    "iso:country":"CN",
    "name:zho_x_preferred":[
        "\u61c2\u5e72"
    ],
    "wof:name":"Donggan",
    "wof:placetype":"locality"
},
  "geometry": {"coordinates":[107.768,25.8458],"type":"Point"}
}