{
  "type": "Feature",
  "properties": {
    "gn:admin1_code":"19.0",
    "gn:asciiname":"Banjiegou",
    "gn:country_code":"CN",
    "gn:dem":234,
    "gn:feature_class":"P",
    "gn:feature_code":"PPL",
    "gn:name":"Banjiegou",
    "gn:population":0,
    "gn:timezone":"Asia/Shanghai",
    "iso:country":"CN",
    "name:und_x_variant":[
        "\u534a\u622a\u6c9f"
    ],
    "wof:name":"Banjiegou",
    "wof:placetype":"locality"
},
  "geometry": {"coordinates":[122.43764,40.16118],"type":"Point"}
}