{
  "type": "Feature",
  "properties": {
    "gn:admin1_code":"25",
    "gn:asciiname":"Hougengjiabu",
    "gn:country_code":"CN",
    "gn:dem":87,
    "gn:feature_class":"P",
    "gn:feature_code":"PPL",
    "gn:name":"Hougengjiabu",
    "gn:population":0,
    "gn:timezone":"Asia/Shanghai",
    "iso:country":"CN",
    "name:zho_x_preferred":[
        "\u540e\u803f\u5bb6\u57e0"
    ],
    "wof:name":"Hougengjiabu",
    "wof:placetype":"locality"
},
  "geometry": {"coordinates":[118.181,35.171],"type":"Point"}
}