{
  "type": "Feature",
  "properties": {
    "gn:admin1_code":"18",
    "gn:asciiname":"Shuangdong Caozi",
    "gn:country_code":"CN",
    "gn:dem":1328,
    "gn:feature_class":"P",
    "gn:feature_code":"PPL",
    "gn:name":"Shuangdong Caozi",
    "gn:population":0,
    "gn:timezone":"Asia/Shanghai",
    "iso:country":"CN",
    "name:zho_x_preferred":[
        "\u53cc\u6d1e\u69fd\u5b50"
    ],
    "wof:name":"Shuangdong Caozi",
    "wof:placetype":"locality"
},
  "geometry": {"coordinates":[106.04900000000001,27.367],"type":"Point"}
}