{
  "type": "Feature",
  "properties": {
    "gn:admin1_code":"26.0",
    "gn:asciiname":"Huayuancun",
    "gn:country_code":"CN",
    "gn:dem":690,
    "gn:feature_class":"P",
    "gn:feature_code":"PPL",
    "gn:name":"Huayuancun",
    "gn:population":0,
    "gn:timezone":"Asia/Shanghai",
    "iso:country":"CN",
    "name:und_x_variant":[
        "\u82b1\u56ed\u6751"
    ],
    "wof:name":"Huayuancun",
    "wof:placetype":"locality"
},
  "geometry": {"coordinates":[107.45643,33.34162],"type":"Point"}
}