{
  "type": "Feature",
  "properties": {
    "gn:admin1_code":"25.0",
    "gn:asciiname":"Xijiaolan",
    "gn:country_code":"CN",
    "gn:dem":16,
    "gn:feature_class":"P",
    "gn:feature_code":"PPL",
    "gn:name":"Xijiaolan",
    "gn:population":0,
    "gn:timezone":"Asia/Shanghai",
    "iso:country":"CN",
    "name:zho_x_preferred":[
        "\u897f\u89d2\u5170"
    ],
    "wof:name":"Xijiaolan",
    "wof:placetype":"locality"
},
  "geometry": {"coordinates":[119.57722,36.56954],"type":"Point"}
}