{
  "type": "Feature",
  "properties": {
    "gn:admin1_code":"2.0",
    "gn:asciiname":"Qingchengkeng",
    "gn:country_code":"CN",
    "gn:dem":729,
    "gn:feature_class":"P",
    "gn:feature_code":"PPL",
    "gn:name":"Qingchengkeng",
    "gn:population":0,
    "gn:timezone":"Asia/Shanghai",
    "iso:country":"CN",
    "name:zho_x_preferred":[
        "\u9752\u57ce\u5751"
    ],
    "wof:name":"Qingchengkeng",
    "wof:placetype":"locality"
},
  "geometry": {"coordinates":[119.00641,28.4292],"type":"Point"}
}