{
  "type": "Feature",
  "properties": {
    "gn:admin1_code":"29.0",
    "gn:asciiname":"Ankang",
    "gn:country_code":"CN",
    "gn:dem":2148,
    "gn:feature_class":"P",
    "gn:feature_code":"PPL",
    "gn:name":"Ankang",
    "gn:population":0,
    "gn:timezone":"Asia/Shanghai",
    "iso:country":"CN",
    "name:ara_x_preferred":[
        "\u0622\u0646\u0643\u0627\u0646\u063a"
    ],
    "name:bxr_x_preferred":[
        "\u0410\u043d\u044c\u043a\u0430\u043d"
    ],
    "name:cdo_x_preferred":[
        "\u0102ng-k\u014fng"
    ],
    "name:ceb_x_preferred":[
        "Ankang"
    ],
    "name:ces_x_preferred":[
        "An-kchang"
    ],
    "name:dan_x_preferred":[
        "Ankang"
    ],
    "name:deu_x_preferred":[
        "Ankang"
    ],
    "name:eus_x_preferred":[
        "Ankang"
    ],
    "name:fas_x_preferred":[
        "\u0622\u0646\u06a9\u0627\u0646\u06af"
    ],
    "name:fin_x_preferred":[
        "Ankang"
    ],
    "name:fra_x_preferred":[
        "Ankang"
    ],
    "name:heb_x_preferred":[
        "\u05d0\u05e0\u05e7\u05d0\u05e0\u05d2"
    ],
    "name:hun_x_preferred":[
        "Ankang"
    ],
    "name:hye_x_preferred":[
        "\u0531\u0576\u056f\u0561\u0576"
    ],
    "name:ind_x_preferred":[
        "Ankang"
    ],
    "name:ita_x_preferred":[
        "Ankang"
    ],
    "name:jpn_x_preferred":[
        "\u5b89\u5eb7\u5e02"
    ],
    "name:kaz_x_preferred":[
        "\u0410\u043d\u044c\u043a\u0430\u043d"
    ],
    "name:kik_x_preferred":[
        "Ankang"
    ],
    "name:kor_x_preferred":[
        "\uc548\uce89\uc2dc"
    ],
    "name:lit_x_preferred":[
        "Ankangas"
    ],
    "name:mlg_x_preferred":[
        "Ankang"
    ],
    "name:nld_x_preferred":[
        "Ankang"
    ],
    "name:nno_x_preferred":[
        "Ankang"
    ],
    "name:nor_x_preferred":[
        "Ankang"
    ],
    "name:pol_x_preferred":[
        "Ankang"
    ],
    "name:por_x_preferred":[
        "Ankang"
    ],
    "name:rus_x_preferred":[
        "\u0410\u043d\u044c\u043a\u0430\u043d"
    ],
    "name:spa_x_preferred":[
        "Ankang"
    ],
    "name:swe_x_preferred":[
        "Ankang"
    ],
    "name:tur_x_preferred":[
        "Ankang"
    ],
    "name:urd_x_preferred":[
        "\u0627\u0646\u06a9\u0627\u0646\u06af"
    ],
    "name:vie_x_preferred":[
        "An Khang"
    ],
    "name:war_x_preferred":[
        "Ankang"
    ],
    "name:zho_x_preferred":[
        "\u5b89\u5eb7"
    ],
    "name:zho_x_variant":[
        "\u5b89\u5eb7\u5e02"
    ],
    "wof:name":"Ankang",
    "wof:placetype":"locality"
},
  "geometry": {"coordinates":[102.517,25.9438],"type":"Point"}
}