{
  "type": "Feature",
  "properties": {
    "gn:admin1_code":"20.0",
    "gn:asciiname":"Nanliang",
    "gn:country_code":"CN",
    "gn:dem":1490,
    "gn:feature_class":"P",
    "gn:feature_code":"PPL",
    "gn:name":"Nanliang",
    "gn:population":0,
    "gn:timezone":"Asia/Shanghai",
    "iso:country":"CN",
    "name:und_x_variant":[
        "\u5357\u6881"
    ],
    "wof:name":"Nanliang",
    "wof:placetype":"locality"
},
  "geometry": {"coordinates":[113.31274000000001,41.24986],"type":"Point"}
}