{
  "type": "Feature",
  "properties": {
    "gn:admin1_code":"26.0",
    "gn:asciiname":"Gaojiahecun",
    "gn:country_code":"CN",
    "gn:dem":1280,
    "gn:feature_class":"P",
    "gn:feature_code":"PPL",
    "gn:name":"Gaojiahecun",
    "gn:population":0,
    "gn:timezone":"Asia/Shanghai",
    "iso:country":"CN",
    "name:zho_x_preferred":[
        "\u9ad8\u5bb6\u6cb3\u6751"
    ],
    "wof:name":"Gaojiahecun",
    "wof:placetype":"locality"
},
  "geometry": {"coordinates":[108.60131,34.98366],"type":"Point"}
}