{
  "type": "Feature",
  "properties": {
    "gn:admin1_code":"15.0",
    "gn:asciiname":"Yinwa",
    "gn:country_code":"CN",
    "gn:dem":1944,
    "gn:feature_class":"P",
    "gn:feature_code":"PPL",
    "gn:name":"Yinwa",
    "gn:population":0,
    "gn:timezone":"Asia/Shanghai",
    "iso:country":"CN",
    "name:und_x_variant":[
        "\u9634\u5c72"
    ],
    "wof:name":"Yinwa",
    "wof:placetype":"locality"
},
  "geometry": {"coordinates":[104.81314999999999,34.60851],"type":"Point"}
}