{
  "type": "Feature",
  "properties": {
    "gn:admin1_code":"26.0",
    "gn:asciiname":"Zhenjiamaocun",
    "gn:country_code":"CN",
    "gn:dem":1421,
    "gn:feature_class":"P",
    "gn:feature_code":"PPL",
    "gn:name":"Zhenjiamaocun",
    "gn:population":0,
    "gn:timezone":"Asia/Shanghai",
    "iso:country":"CN",
    "name:zho_x_preferred":[
        "\u7504\u5bb6\u5cc1\u6751"
    ],
    "wof:name":"Zhenjiamaocun",
    "wof:placetype":"locality"
},
  "geometry": {"coordinates":[108.6931,36.71213],"type":"Point"}
}