{
  "type": "Feature",
  "properties": {
    "gn:admin1_code":"14.0",
    "gn:asciiname":"Rika",
    "gn:country_code":"CN",
    "gn:dem":3589,
    "gn:feature_class":"P",
    "gn:feature_code":"PPL",
    "gn:name":"Rika",
    "gn:population":0,
    "gn:timezone":"Asia/Urumqi",
    "iso:country":"CN",
    "name:bod_x_preferred":[
        "Rika"
    ],
    "name:ceb_x_preferred":[
        "Rika"
    ],
    "name:deu_x_preferred":[
        "Rika"
    ],
    "name:fra_x_preferred":[
        "Rika"
    ],
    "name:hrv_x_preferred":[
        "Rika"
    ],
    "name:ita_x_preferred":[
        "Rika"
    ],
    "name:nld_x_preferred":[
        "Rika"
    ],
    "name:rus_x_preferred":[
        "\u0420\u0438\u043a\u0430"
    ],
    "name:srp_x_preferred":[
        "\u0420\u0438\u043a\u0430"
    ],
    "name:swe_x_preferred":[
        "Rika"
    ],
    "name:zho_x_preferred":[
        "Riga"
    ],
    "name:zho_x_variant":[
        "\u65e5\u560e"
    ],
    "wof:name":"Rika",
    "wof:placetype":"locality"
},
  "geometry": {"coordinates":[97.605,28.805],"type":"Point"}
}