{
  "type": "Feature",
  "properties": {
    "gn:admin1_code":"5.0",
    "gn:asciiname":"Sanmenxucun",
    "gn:country_code":"CN",
    "gn:dem":204,
    "gn:feature_class":"P",
    "gn:feature_code":"PPL",
    "gn:name":"Sanmenxucun",
    "gn:population":0,
    "gn:timezone":"Asia/Shanghai",
    "iso:country":"CN",
    "name:zho_x_preferred":[
        "\u4e09\u95e8\u5f90\u6751"
    ],
    "wof:name":"Sanmenxucun",
    "wof:placetype":"locality"
},
  "geometry": {"coordinates":[125.46232999999999,44.75531],"type":"Point"}
}