{
  "type": "Feature",
  "properties": {
    "gn:admin1_code":"7",
    "gn:asciiname":"Changting",
    "gn:country_code":"CN",
    "gn:dem":33,
    "gn:feature_class":"P",
    "gn:feature_code":"PPL",
    "gn:name":"Changting",
    "gn:population":0,
    "gn:timezone":"Asia/Shanghai",
    "iso:country":"CN",
    "name:und_x_variant":[
        "\u957f\u6c40",
        "Changting"
    ],
    "wof:name":"Changting",
    "wof:placetype":"locality"
},
  "geometry": {"coordinates":[119.63283,27.13538],"type":"Point"}
}