{
  "type": "Feature",
  "properties": {
    "gn:admin1_code":"8.0",
    "gn:asciiname":"Qianchengcun",
    "gn:country_code":"CN",
    "gn:dem":141,
    "gn:feature_class":"P",
    "gn:feature_code":"PPL",
    "gn:name":"Qianchengcun",
    "gn:population":0,
    "gn:timezone":"Asia/Shanghai",
    "iso:country":"CN",
    "name:zho_x_preferred":[
        "\u524d\u7a0b\u6751"
    ],
    "wof:name":"Qianchengcun",
    "wof:placetype":"locality"
},
  "geometry": {"coordinates":[123.30897,46.53448],"type":"Point"}
}