{
  "type": "Feature",
  "properties": {
    "gn:admin1_code":"9.0",
    "gn:asciiname":"Houwulitun",
    "gn:country_code":"CN",
    "gn:dem":64,
    "gn:feature_class":"P",
    "gn:feature_code":"PPL",
    "gn:name":"Houwulitun",
    "gn:population":0,
    "gn:timezone":"Asia/Shanghai",
    "iso:country":"CN",
    "name:zho_x_preferred":[
        "\u540e\u4e94\u91cc\u5c6f"
    ],
    "wof:name":"Houwulitun",
    "wof:placetype":"locality"
},
  "geometry": {"coordinates":[114.52439,35.53207000000001],"type":"Point"}
}