{
  "type": "Feature",
  "properties": {
    "gn:admin1_code":"4.0",
    "gn:asciiname":"Xiaoshaojia",
    "gn:country_code":"CN",
    "gn:dem":16,
    "gn:feature_class":"P",
    "gn:feature_code":"PPL",
    "gn:name":"Xiaoshaojia",
    "gn:population":0,
    "gn:timezone":"Asia/Shanghai",
    "iso:country":"CN",
    "name:zho_x_preferred":[
        "\u5c0f\u90b5\u5bb6"
    ],
    "wof:name":"Xiaoshaojia",
    "wof:placetype":"locality"
},
  "geometry": {"coordinates":[118.8113,31.74163],"type":"Point"}
}