{
  "type": "Feature",
  "properties": {
    "gn:admin1_code":"32.0",
    "gn:asciiname":"Sixia Qiancun",
    "gn:country_code":"CN",
    "gn:dem":2377,
    "gn:feature_class":"P",
    "gn:feature_code":"PPL",
    "gn:name":"Sixia Qiancun",
    "gn:population":0,
    "gn:timezone":"Asia/Shanghai",
    "iso:country":"CN",
    "name:zho_x_preferred":[
        "\u56db\u5477\u5343\u6751"
    ],
    "wof:name":"Sixia Qiancun",
    "wof:placetype":"locality"
},
  "geometry": {"coordinates":[102.94443,28.57797],"type":"Point"}
}