{
  "type": "Feature",
  "properties": {
    "gn:admin1_code":"9.0",
    "gn:asciiname":"Huanggufan",
    "gn:country_code":"CN",
    "gn:dem":113,
    "gn:feature_class":"P",
    "gn:feature_code":"PPL",
    "gn:name":"Huanggufan",
    "gn:population":0,
    "gn:timezone":"Asia/Shanghai",
    "iso:country":"CN",
    "name:zho_x_preferred":[
        "\u9ec4\u8c37\u7548"
    ],
    "wof:name":"Huanggufan",
    "wof:placetype":"locality"
},
  "geometry": {"coordinates":[114.78422,31.51092],"type":"Point"}
}