{
  "type": "Feature",
  "properties": {
    "gn:admin1_code":"1.0",
    "gn:asciiname":"Dawanlu",
    "gn:country_code":"CN",
    "gn:dem":6,
    "gn:feature_class":"P",
    "gn:feature_code":"PPL",
    "gn:name":"Dawanlu",
    "gn:population":0,
    "gn:timezone":"Asia/Shanghai",
    "iso:country":"CN",
    "name:zho_x_preferred":[
        "\u5927\u6e7e\u9c81"
    ],
    "wof:name":"Dawanlu",
    "wof:placetype":"locality"
},
  "geometry": {"coordinates":[118.08015,31.33865],"type":"Point"}
}