{
  "type": "Feature",
  "properties": {
    "gn:admin1_code":"7.0",
    "gn:asciiname":"Keliao",
    "gn:country_code":"CN",
    "gn:dem":120,
    "gn:feature_class":"P",
    "gn:feature_code":"PPL",
    "gn:name":"Keliao",
    "gn:population":0,
    "gn:timezone":"Asia/Shanghai",
    "iso:country":"CN",
    "name:zho_x_preferred":[
        "\u5ba2\u5bee"
    ],
    "wof:name":"Keliao",
    "wof:placetype":"locality"
},
  "geometry": {"coordinates":[117.27943999999999,24.15139],"type":"Point"}
}