{
  "type": "Feature",
  "properties": {
    "gn:admin1_code":"3.0",
    "gn:asciiname":"Changxiacun",
    "gn:country_code":"CN",
    "gn:dem":48,
    "gn:feature_class":"P",
    "gn:feature_code":"PPL",
    "gn:name":"Changxiacun",
    "gn:population":0,
    "gn:timezone":"Asia/Shanghai",
    "iso:country":"CN",
    "name:zho_x_preferred":[
        "\u660c\u4e0b\u6751"
    ],
    "wof:name":"Changxiacun",
    "wof:placetype":"locality"
},
  "geometry": {"coordinates":[115.11199999999999,27.9781],"type":"Point"}
}