{
  "type": "Feature",
  "properties": {
    "gn:admin1_code":"1.0",
    "gn:asciiname":"Fatangcun",
    "gn:country_code":"CN",
    "gn:dem":29,
    "gn:feature_class":"P",
    "gn:feature_code":"PPL",
    "gn:name":"Fatangcun",
    "gn:population":0,
    "gn:timezone":"Asia/Shanghai",
    "iso:country":"CN",
    "name:zho_x_preferred":[
        "\u6cd5\u5802\u6751"
    ],
    "wof:name":"Fatangcun",
    "wof:placetype":"locality"
},
  "geometry": {"coordinates":[116.03588999999999,33.09308],"type":"Point"}
}