{
  "type": "Feature",
  "properties": {
    "gn:admin1_code":"11.0",
    "gn:asciiname":"Yanglijia",
    "gn:country_code":"CN",
    "gn:dem":73,
    "gn:feature_class":"P",
    "gn:feature_code":"PPL",
    "gn:name":"Yanglijia",
    "gn:population":0,
    "gn:timezone":"Asia/Shanghai",
    "iso:country":"CN",
    "name:zho_x_preferred":[
        "\u6768\u674e\u5bb6"
    ],
    "wof:name":"Yanglijia",
    "wof:placetype":"locality"
},
  "geometry": {"coordinates":[113.37654000000001,29.08462],"type":"Point"}
}