{
  "type": "Feature",
  "properties": {
    "gn:admin1_code":"18",
    "gn:asciiname":"Longyuansi",
    "gn:country_code":"CN",
    "gn:dem":742,
    "gn:feature_class":"P",
    "gn:feature_code":"PPL",
    "gn:name":"Longyuansi",
    "gn:population":0,
    "gn:timezone":"Asia/Shanghai",
    "iso:country":"CN",
    "name:zho_x_preferred":[
        "\u9f99\u6e90\u5bfa"
    ],
    "wof:name":"Longyuansi",
    "wof:placetype":"locality"
},
  "geometry": {"coordinates":[106.541,28.0317],"type":"Point"}
}