{
  "type": "Feature",
  "properties": {
    "gn:admin1_code":"30",
    "gn:asciiname":"Shangyangtao",
    "gn:country_code":"CN",
    "gn:dem":68,
    "gn:feature_class":"P",
    "gn:feature_code":"PPL",
    "gn:name":"Shangyangtao",
    "gn:population":0,
    "gn:timezone":"Asia/Shanghai",
    "iso:country":"CN",
    "name:zho_x_preferred":[
        "\u4e0a\u6d0b\u9676"
    ],
    "wof:name":"Shangyangtao",
    "wof:placetype":"locality"
},
  "geometry": {"coordinates":[116.68785,24.4961],"type":"Point"}
}