{
  "type": "Feature",
  "properties": {
    "gn:admin1_code":"8.0",
    "gn:asciiname":"Qinglongshancun",
    "gn:country_code":"CN",
    "gn:dem":159,
    "gn:feature_class":"P",
    "gn:feature_code":"PPL",
    "gn:name":"Qinglongshancun",
    "gn:population":0,
    "gn:timezone":"Asia/Shanghai",
    "iso:country":"CN",
    "name:zho_x_preferred":[
        "\u9752\u9f99\u5c71\u6751"
    ],
    "wof:name":"Qinglongshancun",
    "wof:placetype":"locality"
},
  "geometry": {"coordinates":[125.40815000000001,46.35477],"type":"Point"}
}