{
  "type": "Feature",
  "properties": {
    "gn:admin1_code":"15.0",
    "gn:asciiname":"Shijiayu",
    "gn:country_code":"CN",
    "gn:dem":2480,
    "gn:feature_class":"P",
    "gn:feature_code":"PPL",
    "gn:name":"Shijiayu",
    "gn:population":0,
    "gn:timezone":"Asia/Shanghai",
    "iso:country":"CN",
    "name:zho_x_preferred":[
        "\u77f3\u5bb6\u5cea"
    ],
    "wof:name":"Shijiayu",
    "wof:placetype":"locality"
},
  "geometry": {"coordinates":[104.6223,33.79306],"type":"Point"}
}