{
  "type": "Feature",
  "properties": {
    "gn:admin1_code":"19.0",
    "gn:asciiname":"Shixiazicun",
    "gn:country_code":"CN",
    "gn:dem":215,
    "gn:feature_class":"P",
    "gn:feature_code":"PPL",
    "gn:name":"Shixiazicun",
    "gn:population":0,
    "gn:timezone":"Asia/Shanghai",
    "iso:country":"CN",
    "name:zho_x_preferred":[
        "\u77f3\u5323\u5b50\u6751"
    ],
    "wof:name":"Shixiazicun",
    "wof:placetype":"locality"
},
  "geometry": {"coordinates":[121.583,41.4769],"type":"Point"}
}