{
  "type": "Feature",
  "properties": {
    "gn:admin1_code":"25",
    "gn:asciiname":"Xicaishi Yicun",
    "gn:country_code":"CN",
    "gn:dem":158,
    "gn:feature_class":"P",
    "gn:feature_code":"PPL",
    "gn:name":"Xicaishi Yicun",
    "gn:population":0,
    "gn:timezone":"Asia/Shanghai",
    "iso:country":"CN",
    "name:zho_x_preferred":[
        "\u897f\u5f69\u77f3\u4e00\u6751"
    ],
    "wof:name":"Xicaishi Yicun",
    "wof:placetype":"locality"
},
  "geometry": {"coordinates":[117.256,36.6486],"type":"Point"}
}