{
  "type": "Feature",
  "properties": {
    "gn:admin1_code":"24.0",
    "gn:asciiname":"Beiniuchicun",
    "gn:country_code":"CN",
    "gn:dem":645,
    "gn:feature_class":"P",
    "gn:feature_code":"PPL",
    "gn:name":"Beiniuchicun",
    "gn:population":0,
    "gn:timezone":"Asia/Shanghai",
    "iso:country":"CN",
    "name:zho_x_preferred":[
        "\u5317\u725b\u6c60\u6751"
    ],
    "wof:name":"Beiniuchicun",
    "wof:placetype":"locality"
},
  "geometry": {"coordinates":[110.88724999999999,35.40668],"type":"Point"}
}