{
  "type": "Feature",
  "properties": {
    "gn:admin1_code":"29.0",
    "gn:asciiname":"Yezhutang",
    "gn:country_code":"CN",
    "gn:dem":1941,
    "gn:feature_class":"P",
    "gn:feature_code":"PPL",
    "gn:name":"Yezhutang",
    "gn:population":0,
    "gn:timezone":"Asia/Shanghai",
    "iso:country":"CN",
    "name:zho_x_preferred":[
        "\u91ce\u732a\u5858"
    ],
    "wof:name":"Yezhutang",
    "wof:placetype":"locality"
},
  "geometry": {"coordinates":[99.7739,24.1268],"type":"Point"}
}