{
  "type": "Feature",
  "properties": {
    "gn:admin1_code":"22.0",
    "gn:asciiname":"Xianninghou",
    "gn:country_code":"CN",
    "gn:dem":34,
    "gn:feature_class":"P",
    "gn:feature_code":"PPL",
    "gn:name":"Xianninghou",
    "gn:population":0,
    "gn:timezone":"Asia/Shanghai",
    "iso:country":"CN",
    "name:zho_x_preferred":[
        "\u54b8\u5b81\u4faf"
    ],
    "wof:name":"Xianninghou",
    "wof:placetype":"locality"
},
  "geometry": {"coordinates":[116.57979,39.89489],"type":"Point"}
}