{
  "type": "Feature",
  "properties": {
    "gn:admin1_code":"32.0",
    "gn:asciiname":"Yongcheng",
    "gn:country_code":"CN",
    "gn:dem":997,
    "gn:feature_class":"P",
    "gn:feature_code":"PPL",
    "gn:name":"Yongcheng",
    "gn:population":0,
    "gn:timezone":"Asia/Shanghai",
    "iso:country":"CN",
    "name:ara_x_preferred":[
        "\u064a\u0648\u0646\u063a\u062a\u0634\u064a\u0646\u063a"
    ],
    "name:deu_x_preferred":[
        "Yongcheng"
    ],
    "name:fra_x_preferred":[
        "Yongcheng"
    ],
    "name:ita_x_preferred":[
        "Yongcheng"
    ],
    "name:jpn_x_preferred":[
        "\u6c38\u57ce\u5e02"
    ],
    "name:kik_x_preferred":[
        "Yongcheng"
    ],
    "name:kor_x_preferred":[
        "\uc735\uccad\uc2dc"
    ],
    "name:mlg_x_preferred":[
        "Yongcheng"
    ],
    "name:nor_x_preferred":[
        "Yongcheng"
    ],
    "name:pam_x_preferred":[
        "Yongcheng"
    ],
    "name:rus_x_preferred":[
        "\u042e\u043d\u0447\u044d\u043d"
    ],
    "name:swe_x_preferred":[
        "Yongcheng"
    ],
    "name:urd_x_preferred":[
        "\u06cc\u0648\u0646\u06af\u0686\u06cc\u0646\u06af"
    ],
    "name:vie_x_preferred":[
        "V\u0129nh Th\u00e0nh"
    ],
    "name:zho_x_preferred":[
        "\u6c38\u57ce"
    ],
    "name:zho_x_variant":[
        "\u6c38\u57ce\u5e02"
    ],
    "wof:name":"Yongcheng",
    "wof:placetype":"locality"
},
  "geometry": {"coordinates":[104.67700000000001,31.9347],"type":"Point"}
}