{
  "type": "Feature",
  "properties": {
    "gn:admin1_code":"32.0",
    "gn:asciiname":"Yongcheng",
    "gn:country_code":"CN",
    "gn:dem":997,
    "gn:feature_class":"P",
    "gn:feature_code":"PPL",
    "gn:name":"Yongcheng",
    "gn:population":0,
    "gn:timezone":"Asia/Shanghai",
    "iso:country":"CN",
    "name:zho_x_preferred":[
        "\u6c38\u57ce"
    ],
    "wof:name":"Yongcheng",
    "wof:placetype":"locality"
},
  "geometry": {"coordinates":[104.67700000000001,31.9347],"type":"Point"}
}