{
  "type": "Feature",
  "properties": {
    "gn:admin1_code":"2.0",
    "gn:asciiname":"Dishangang",
    "gn:country_code":"CN",
    "gn:dem":11,
    "gn:feature_class":"P",
    "gn:feature_code":"PPL",
    "gn:name":"Dishangang",
    "gn:population":0,
    "gn:timezone":"Asia/Shanghai",
    "iso:country":"CN",
    "name:zho_x_preferred":[
        "\u5730\u5c71\u5c97"
    ],
    "wof:name":"Dishangang",
    "wof:placetype":"locality"
},
  "geometry": {"coordinates":[121.63294999999999,28.34572],"type":"Point"}
}