{
  "type": "Feature",
  "properties": {
    "gn:admin1_code":"12.0",
    "gn:asciiname":"Huangmaogang",
    "gn:country_code":"CN",
    "gn:dem":1027,
    "gn:feature_class":"P",
    "gn:feature_code":"PPL",
    "gn:name":"Huangmaogang",
    "gn:population":0,
    "gn:timezone":"Asia/Shanghai",
    "iso:country":"CN",
    "name:zho_x_preferred":[
        "\u9ec4\u732b\u5c97"
    ],
    "wof:name":"Huangmaogang",
    "wof:placetype":"locality"
},
  "geometry": {"coordinates":[111.24236000000001,31.20396],"type":"Point"}
}