{
  "type": "Feature",
  "properties": {
    "gn:admin1_code":"7.0",
    "gn:asciiname":"Liuyu",
    "gn:country_code":"CN",
    "gn:dem":22,
    "gn:feature_class":"P",
    "gn:feature_code":"PPL",
    "gn:name":"Liuyu",
    "gn:population":0,
    "gn:timezone":"Asia/Shanghai",
    "iso:country":"CN",
    "name:zho_x_preferred":[
        "\u516d\u5c7f"
    ],
    "wof:name":"Liuyu",
    "wof:placetype":"locality"
},
  "geometry": {"coordinates":[119.67607,26.84232],"type":"Point"}
}