{
  "type": "Feature",
  "properties": {
    "gn:admin1_code":"26.0",
    "gn:asciiname":"Niuticun",
    "gn:country_code":"CN",
    "gn:dem":481,
    "gn:feature_class":"P",
    "gn:feature_code":"PPL",
    "gn:name":"Niuticun",
    "gn:population":0,
    "gn:timezone":"Asia/Shanghai",
    "iso:country":"CN",
    "name:zho_x_preferred":[
        "\u725b\u8e44\u6751"
    ],
    "wof:name":"Niuticun",
    "wof:placetype":"locality"
},
  "geometry": {"coordinates":[107.86060000000001,34.2528],"type":"Point"}
}