{
  "type": "Feature",
  "properties": {
    "gn:admin1_code":"11.0",
    "gn:asciiname":"Xiaomuping",
    "gn:country_code":"CN",
    "gn:dem":177,
    "gn:feature_class":"P",
    "gn:feature_code":"PPL",
    "gn:name":"Xiaomuping",
    "gn:population":0,
    "gn:timezone":"Asia/Shanghai",
    "iso:country":"CN",
    "name:zho_x_preferred":[
        "\u5c0f\u6728\u576a"
    ],
    "wof:name":"Xiaomuping",
    "wof:placetype":"locality"
},
  "geometry": {"coordinates":[113.52182999999999,28.57283],"type":"Point"}
}