{
  "type": "Feature",
  "properties": {
    "gn:admin1_code":"29.0",
    "gn:asciiname":"Gangoutian",
    "gn:country_code":"CN",
    "gn:dem":1216,
    "gn:feature_class":"P",
    "gn:feature_code":"PPL",
    "gn:name":"Gangoutian",
    "gn:population":0,
    "gn:timezone":"Asia/Shanghai",
    "iso:country":"CN",
    "name:zho_x_preferred":[
        "\u5e72\u6c9f\u7530"
    ],
    "wof:name":"Gangoutian",
    "wof:placetype":"locality"
},
  "geometry": {"coordinates":[98.66930000000001,24.5162],"type":"Point"}
}