{
  "type": "Feature",
  "properties": {
    "gn:admin1_code":"30.0",
    "gn:asciiname":"Tieling",
    "gn:country_code":"CN",
    "gn:dem":264,
    "gn:feature_class":"P",
    "gn:feature_code":"PPL",
    "gn:name":"Tieling",
    "gn:population":0,
    "gn:timezone":"Asia/Shanghai",
    "iso:country":"CN",
    "name:zho_x_preferred":[
        "Tieling"
    ],
    "name:zho_x_variant":[
        "\u94c1\u5cad"
    ],
    "wof:name":"Tieling",
    "wof:placetype":"locality"
},
  "geometry": {"coordinates":[115.03194000000001,24.67417],"type":"Point"}
}