{
  "type": "Feature",
  "properties": {
    "gn:admin1_code":"15.0",
    "gn:asciiname":"Zhuxia",
    "gn:country_code":"CN",
    "gn:dem":1380,
    "gn:feature_class":"P",
    "gn:feature_code":"PPL",
    "gn:name":"Zhuxia",
    "gn:population":0,
    "gn:timezone":"Asia/Shanghai",
    "iso:country":"CN",
    "name:und_x_variant":[
        "\u6731\u5ce1"
    ],
    "wof:name":"Zhuxia",
    "wof:placetype":"locality"
},
  "geometry": {"coordinates":[105.6024,35.01600999999999],"type":"Point"}
}