{
  "type": "Feature",
  "properties": {
    "gn:admin1_code":"4.0",
    "gn:asciiname":"Gezhuangcun",
    "gn:country_code":"CN",
    "gn:dem":27,
    "gn:feature_class":"P",
    "gn:feature_code":"PPL",
    "gn:name":"Gezhuangcun",
    "gn:population":0,
    "gn:timezone":"Asia/Shanghai",
    "iso:country":"CN",
    "name:zho_x_preferred":[
        "\u845b\u5e84\u6751"
    ],
    "wof:name":"Gezhuangcun",
    "wof:placetype":"locality"
},
  "geometry": {"coordinates":[117.7089,33.90882],"type":"Point"}
}