{
  "type": "Feature",
  "properties": {
    "gn:admin1_code":"7.0",
    "gn:asciiname":"Meibin",
    "gn:country_code":"CN",
    "gn:dem":76,
    "gn:feature_class":"P",
    "gn:feature_code":"PPL",
    "gn:name":"Meibin",
    "gn:population":0,
    "gn:timezone":"Asia/Shanghai",
    "iso:country":"CN",
    "name:zho_x_preferred":[
        "\u7f8e\u6ee8"
    ],
    "wof:name":"Meibin",
    "wof:placetype":"locality"
},
  "geometry": {"coordinates":[118.11295,25.14913],"type":"Point"}
}