{
  "type": "Feature",
  "properties": {
    "gn:admin1_code":"4.0",
    "gn:asciiname":"Huzhu",
    "gn:country_code":"CN",
    "gn:dem":5,
    "gn:feature_class":"P",
    "gn:feature_code":"PPL",
    "gn:name":"Huzhu",
    "gn:population":0,
    "gn:timezone":"Asia/Shanghai",
    "iso:country":"CN",
    "name:und_x_variant":[
        "\u4e92\u52a9"
    ],
    "wof:name":"Huzhu",
    "wof:placetype":"locality"
},
  "geometry": {"coordinates":[121.44762,32.08192],"type":"Point"}
}