{
  "type": "Feature",
  "properties": {
    "gn:admin1_code":"12",
    "gn:asciiname":"Shuigu",
    "gn:country_code":"CN",
    "gn:dem":1145,
    "gn:feature_class":"P",
    "gn:feature_code":"PPL",
    "gn:name":"Shuigu",
    "gn:population":0,
    "gn:timezone":"Asia/Shanghai",
    "iso:country":"CN",
    "wof:name":"Shuigu",
    "wof:placetype":"locality"
},
  "geometry": {"coordinates":[110.18333,30.68333],"type":"Point"}
}