{
  "type": "Feature",
  "properties": {
    "gn:admin1_code":"26.0",
    "gn:asciiname":"Yikentuola Sandui",
    "gn:country_code":"CN",
    "gn:dem":1270,
    "gn:feature_class":"P",
    "gn:feature_code":"PPLF",
    "gn:name":"Yikentuola Sandui",
    "gn:population":0,
    "gn:timezone":"Asia/Shanghai",
    "iso:country":"CN",
    "name:zho_x_preferred":[
        "\u4f9d\u80af\u6258\u62c9\u4e09\u961f"
    ],
    "wof:name":"Yikentuola Sandui",
    "wof:placetype":"locality"
},
  "geometry": {"coordinates":[109.84286000000002,38.95403],"type":"Point"}
}