{
  "type": "Feature",
  "properties": {
    "gn:admin1_code":"32.0",
    "gn:asciiname":"Dengganping",
    "gn:country_code":"CN",
    "gn:dem":1391,
    "gn:feature_class":"P",
    "gn:feature_code":"PPL",
    "gn:name":"Dengganping",
    "gn:population":0,
    "gn:timezone":"Asia/Shanghai",
    "iso:country":"CN",
    "name:zho_x_preferred":[
        "\u706f\u6746\u576a"
    ],
    "wof:name":"Dengganping",
    "wof:placetype":"locality"
},
  "geometry": {"coordinates":[102.77683,30.19978],"type":"Point"}
}