{
  "type": "Feature",
  "properties": {
    "gn:admin1_code":"24.0",
    "gn:asciiname":"Banjiazhuang",
    "gn:country_code":"CN",
    "gn:dem":1305,
    "gn:feature_class":"P",
    "gn:feature_code":"PPL",
    "gn:name":"Banjiazhuang",
    "gn:population":0,
    "gn:timezone":"Asia/Shanghai",
    "iso:country":"CN",
    "name:zho_x_preferred":[
        "\u73ed\u5bb6\u5e84"
    ],
    "wof:name":"Banjiazhuang",
    "wof:placetype":"locality"
},
  "geometry": {"coordinates":[111.07827,36.69971],"type":"Point"}
}