{
  "type": "Feature",
  "properties": {
    "gn:admin1_code":"30.0",
    "gn:asciiname":"Chaoxili",
    "gn:country_code":"CN",
    "gn:dem":26,
    "gn:feature_class":"P",
    "gn:feature_code":"PPL",
    "gn:name":"Chaoxili",
    "gn:population":0,
    "gn:timezone":"Asia/Shanghai",
    "iso:country":"CN",
    "name:zho_x_preferred":[
        "\u6f6e\u6eaa\u91cc"
    ],
    "wof:name":"Chaoxili",
    "wof:placetype":"locality"
},
  "geometry": {"coordinates":[112.30817,22.01288],"type":"Point"}
}