{
  "type": "Feature",
  "properties": {
    "gn:admin1_code":"9",
    "gn:asciiname":"Wuzhuangzhai",
    "gn:country_code":"CN",
    "gn:dem":67,
    "gn:feature_class":"P",
    "gn:feature_code":"PPL",
    "gn:name":"Wuzhuangzhai",
    "gn:population":0,
    "gn:timezone":"Asia/Shanghai",
    "iso:country":"CN",
    "name:zho_x_preferred":[
        "\u5434\u5e84\u5be8"
    ],
    "wof:name":"Wuzhuangzhai",
    "wof:placetype":"locality"
},
  "geometry": {"coordinates":[115.29900000000001,34.8073],"type":"Point"}
}