{
  "type": "Feature",
  "properties": {
    "gn:admin1_code":"32",
    "gn:asciiname":"Damiaoshan",
    "gn:country_code":"CN",
    "gn:dem":273,
    "gn:feature_class":"P",
    "gn:feature_code":"PPL",
    "gn:name":"Damiaoshan",
    "gn:population":0,
    "gn:timezone":"Asia/Shanghai",
    "iso:country":"CN",
    "name:zho_x_preferred":[
        "\u5927\u5e99\u5c71"
    ],
    "wof:name":"Damiaoshan",
    "wof:placetype":"locality"
},
  "geometry": {"coordinates":[106.62412,30.33675],"type":"Point"}
}