{
  "type": "Feature",
  "properties": {
    "gn:admin1_code":"24.0",
    "gn:asciiname":"Dunzhangzhuang",
    "gn:country_code":"CN",
    "gn:dem":596,
    "gn:feature_class":"P",
    "gn:feature_code":"PPL",
    "gn:name":"Dunzhangzhuang",
    "gn:population":0,
    "gn:timezone":"Asia/Shanghai",
    "iso:country":"CN",
    "name:zho_x_preferred":[
        "\u58a9\u5f20\u5e84"
    ],
    "wof:name":"Dunzhangzhuang",
    "wof:placetype":"locality"
},
  "geometry": {"coordinates":[111.00075,35.29088],"type":"Point"}
}