{
  "type": "Feature",
  "properties": {
    "gn:admin1_code":"10",
    "gn:asciiname":"Malanguan",
    "gn:country_code":"CN",
    "gn:dem":126,
    "gn:feature_class":"P",
    "gn:feature_code":"PPL",
    "gn:name":"Malanguan",
    "gn:population":0,
    "gn:timezone":"Asia/Shanghai",
    "iso:country":"CN",
    "name:und_x_variant":[
        "Ma-lan-kuan",
        "Malanguan"
    ],
    "name:zho_x_preferred":[
        "\u9a6c\u5170\u5173"
    ],
    "wof:name":"Malanguan",
    "wof:placetype":"locality"
},
  "geometry": {"coordinates":[117.67675,40.21762],"type":"Point"}
}