{
  "type": "Feature",
  "properties": {
    "gn:admin1_code":"1.0",
    "gn:asciiname":"Lishuang Lingxia",
    "gn:country_code":"CN",
    "gn:dem":428,
    "gn:feature_class":"P",
    "gn:feature_code":"PPL",
    "gn:name":"Lishuang Lingxia",
    "gn:population":0,
    "gn:timezone":"Asia/Shanghai",
    "iso:country":"CN",
    "name:und_x_variant":[
        "\u91cc\u53cc\u5cad\u4e0b"
    ],
    "wof:name":"Lishuang Lingxia",
    "wof:placetype":"locality"
},
  "geometry": {"coordinates":[118.6125,30.225],"type":"Point"}
}