{
  "type": "Feature",
  "properties": {
    "gn:admin1_code":"14.0",
    "gn:asciiname":"Jucun",
    "gn:country_code":"CN",
    "gn:dem":3899,
    "gn:feature_class":"P",
    "gn:feature_code":"PPL",
    "gn:name":"Jucun",
    "gn:population":0,
    "gn:timezone":"Asia/Urumqi",
    "iso:country":"CN",
    "name:bod_x_preferred":[
        "Jucun"
    ],
    "name:und_x_variant":[
        "Jiucun"
    ],
    "name:zho_x_preferred":[
        "\u4e45\u6751"
    ],
    "name:zho_x_variant":[
        "Fanshen Gongshe",
        "\u7ffb\u8eab\u516c\u793e"
    ],
    "wof:name":"Jucun",
    "wof:placetype":"locality"
},
  "geometry": {"coordinates":[91.66221,29.06059],"type":"Point"}
}