{
  "type": "Feature",
  "properties": {
    "gn:admin1_code":"29",
    "gn:asciiname":"Badou",
    "gn:country_code":"CN",
    "gn:dem":604,
    "gn:feature_class":"P",
    "gn:feature_code":"PPL",
    "gn:name":"Badou",
    "gn:population":0,
    "gn:timezone":"Asia/Shanghai",
    "iso:country":"CN",
    "name:ara_x_preferred":[
        "\u0628\u0627\u062f\u0648"
    ],
    "name:ceb_x_preferred":[
        "Badou"
    ],
    "name:fra_x_preferred":[
        "Badou"
    ],
    "name:frr_x_preferred":[
        "Badou"
    ],
    "name:ita_x_preferred":[
        "Badou"
    ],
    "name:pol_x_preferred":[
        "Badou"
    ],
    "name:ron_x_preferred":[
        "Badou"
    ],
    "name:rus_x_preferred":[
        "\u0411\u0430\u0434\u0443"
    ],
    "name:zho_x_preferred":[
        "\u516b\u6597"
    ],
    "wof:name":"Badou",
    "wof:placetype":"locality"
},
  "geometry": {"coordinates":[104.93600000000001,23.2941],"type":"Point"}
}