{
  "type": "Feature",
  "properties": {
    "gn:admin1_code":"26.0",
    "gn:asciiname":"Yayao Goucun",
    "gn:country_code":"CN",
    "gn:dem":999,
    "gn:feature_class":"P",
    "gn:feature_code":"PPL",
    "gn:name":"Yayao Goucun",
    "gn:population":0,
    "gn:timezone":"Asia/Shanghai",
    "iso:country":"CN",
    "name:zho_x_preferred":[
        "\u5d16\u8170\u6c9f\u6751"
    ],
    "wof:name":"Yayao Goucun",
    "wof:placetype":"locality"
},
  "geometry": {"coordinates":[110.288,37.3082],"type":"Point"}
}