{
  "type": "Feature",
  "properties": {
    "gn:admin1_code":"16.0",
    "gn:asciiname":"Hanshan",
    "gn:country_code":"CN",
    "gn:dem":117,
    "gn:feature_class":"P",
    "gn:feature_code":"PPL",
    "gn:name":"Hanshan",
    "gn:population":0,
    "gn:timezone":"Asia/Shanghai",
    "iso:country":"CN",
    "name:ceb_x_preferred":[
        "Hanshan"
    ],
    "name:deu_x_preferred":[
        "Hanshan"
    ],
    "name:fra_x_preferred":[
        "Hanshan"
    ],
    "name:nor_x_preferred":[
        "Hanshan"
    ],
    "name:spa_x_preferred":[
        "Hanshan"
    ],
    "name:zho_x_preferred":[
        "\u5bd2\u5c71"
    ],
    "wof:name":"Hanshan",
    "wof:placetype":"locality"
},
  "geometry": {"coordinates":[110.108,22.7399],"type":"Point"}
}