{
  "type": "Feature",
  "properties": {
    "gn:admin1_code":"32",
    "gn:asciiname":"Songlinping",
    "gn:country_code":"CN",
    "gn:dem":1764,
    "gn:feature_class":"P",
    "gn:feature_code":"PPL",
    "gn:name":"Songlinping",
    "gn:population":0,
    "gn:timezone":"Asia/Shanghai",
    "iso:country":"CN",
    "wof:name":"Songlinping",
    "wof:placetype":"locality"
},
  "geometry": {"coordinates":[102.63333,27.23333],"type":"Point"}
}