{
  "type": "Feature",
  "properties": {
    "gn:admin1_code":"12.0",
    "gn:asciiname":"Gufengsi",
    "gn:country_code":"CN",
    "gn:dem":36,
    "gn:feature_class":"P",
    "gn:feature_code":"PPL",
    "gn:name":"Gufengsi",
    "gn:population":0,
    "gn:timezone":"Asia/Shanghai",
    "iso:country":"CN",
    "name:zho_x_preferred":[
        "\u53e4\u5cf0\u5bfa"
    ],
    "wof:name":"Gufengsi",
    "wof:placetype":"locality"
},
  "geometry": {"coordinates":[113.62451,31.05678],"type":"Point"}
}