{
  "type": "Feature",
  "properties": {
    "gn:admin1_code":"1.0",
    "gn:asciiname":"Chenzhuang",
    "gn:country_code":"CN",
    "gn:dem":36,
    "gn:feature_class":"P",
    "gn:feature_code":"PPL",
    "gn:name":"Chenzhuang",
    "gn:population":0,
    "gn:timezone":"Asia/Shanghai",
    "iso:country":"CN",
    "name:ceb_x_preferred":[
        "Chenzhuang"
    ],
    "name:swe_x_preferred":[
        "Chenzhuang"
    ],
    "wof:name":"Chenzhuang",
    "wof:placetype":"locality"
},
  "geometry": {"coordinates":[115.45833,32.75],"type":"Point"}
}