{
  "type": "Feature",
  "properties": {
    "gn:admin1_code":"32.0",
    "gn:asciiname":"Kule",
    "gn:country_code":"CN",
    "gn:dem":2770,
    "gn:feature_class":"P",
    "gn:feature_code":"PPL",
    "gn:name":"Kule",
    "gn:population":0,
    "gn:timezone":"Asia/Shanghai",
    "iso:country":"CN",
    "name:zho_x_preferred":[
        "\u82e6\u4e50"
    ],
    "wof:name":"Kule",
    "wof:placetype":"locality"
},
  "geometry": {"coordinates":[101.06699999999999,30.1344],"type":"Point"}
}