{
  "type": "Feature",
  "properties": {
    "gn:admin1_code":"16.0",
    "gn:asciiname":"Xiayuandong",
    "gn:country_code":"CN",
    "gn:dem":283,
    "gn:feature_class":"P",
    "gn:feature_code":"PPL",
    "gn:name":"Xiayuandong",
    "gn:population":0,
    "gn:timezone":"Asia/Shanghai",
    "iso:country":"CN",
    "name:zho_x_preferred":[
        "\u4e0b\u6e90\u6d1e"
    ],
    "wof:name":"Xiayuandong",
    "wof:placetype":"locality"
},
  "geometry": {"coordinates":[111.233,24.7546],"type":"Point"}
}