{
  "type": "Feature",
  "properties": {
    "gn:admin1_code":"3.0",
    "gn:asciiname":"Dongxi",
    "gn:country_code":"CN",
    "gn:dem":33,
    "gn:feature_class":"P",
    "gn:feature_code":"PPLA4",
    "gn:name":"Dongxi",
    "gn:population":0,
    "gn:timezone":"Asia/Shanghai",
    "iso:country":"CN",
    "name:und_x_variant":[
        "\u4e1c\u6eaa",
        "Dongxi Xiang",
        "\u4e1c\u6eaa\u4e61"
    ],
    "wof:name":"Dongxi",
    "wof:placetype":"locality"
},
  "geometry": {"coordinates":[117.01266,29.13566],"type":"Point"}
}