{
  "type": "Feature",
  "properties": {
    "gn:admin1_code":"07",
    "gn:asciiname":"Waikeng",
    "gn:country_code":"CN",
    "gn:dem":401,
    "gn:feature_class":"P",
    "gn:feature_code":"PPL",
    "gn:name":"Waikeng",
    "gn:population":0,
    "gn:timezone":"Asia/Shanghai",
    "iso:country":"CN",
    "name:und_x_variant":[
        "Jinshanqiao",
        "Waikeng"
    ],
    "name:zho_x_preferred":[
        "\u5916\u5751"
    ],
    "wof:name":"Waikeng",
    "wof:placetype":"locality"
},
  "geometry": {"coordinates":[117.52266000000002,24.93763],"type":"Point"}
}