{
  "type": "Feature",
  "properties": {
    "gn:admin1_code":"4.0",
    "gn:asciiname":"Bashangxu",
    "gn:country_code":"CN",
    "gn:dem":5,
    "gn:feature_class":"P",
    "gn:feature_code":"PPL",
    "gn:name":"Bashangxu",
    "gn:population":0,
    "gn:timezone":"Asia/Shanghai",
    "iso:country":"CN",
    "name:zho_x_preferred":[
        "\u575d\u4e0a\u5729"
    ],
    "wof:name":"Bashangxu",
    "wof:placetype":"locality"
},
  "geometry": {"coordinates":[119.73437,32.26025],"type":"Point"}
}