{
  "type": "Feature",
  "properties": {
    "gn:admin1_code":"32.0",
    "gn:asciiname":"Zuoge",
    "gn:country_code":"CN",
    "gn:dem":3378,
    "gn:feature_class":"P",
    "gn:feature_code":"PPL",
    "gn:name":"Zuoge",
    "gn:population":0,
    "gn:timezone":"Asia/Shanghai",
    "iso:country":"CN",
    "name:zho_x_preferred":[
        "\u4f5c\u683c"
    ],
    "wof:name":"Zuoge",
    "wof:placetype":"locality"
},
  "geometry": {"coordinates":[100.46029,30.49676],"type":"Point"}
}