{
  "type": "Feature",
  "properties": {
    "gn:admin1_code":"2.0",
    "gn:asciiname":"Zhige",
    "gn:country_code":"CN",
    "gn:dem":11,
    "gn:feature_class":"P",
    "gn:feature_code":"PPL",
    "gn:name":"Zhige",
    "gn:population":0,
    "gn:timezone":"Asia/Shanghai",
    "iso:country":"CN",
    "name:und_x_variant":[
        "\u667a\u683c"
    ],
    "wof:name":"Zhige",
    "wof:placetype":"locality"
},
  "geometry": {"coordinates":[120.32447000000001,30.29617],"type":"Point"}
}