{
  "type": "Feature",
  "properties": {
    "gn:admin1_code":"8.0",
    "gn:asciiname":"Tuanjie",
    "gn:country_code":"CN",
    "gn:dem":152,
    "gn:feature_class":"P",
    "gn:feature_code":"PPL",
    "gn:name":"Tuanjie",
    "gn:population":0,
    "gn:timezone":"Asia/Shanghai",
    "iso:country":"CN",
    "name:zho_x_preferred":[
        "\u56e2\u7ed3"
    ],
    "wof:name":"Tuanjie",
    "wof:placetype":"locality"
},
  "geometry": {"coordinates":[124.77912999999999,47.2256],"type":"Point"}
}