{
  "type": "Feature",
  "properties": {
    "gn:admin1_code":"15.0",
    "gn:asciiname":"Fu'an",
    "gn:country_code":"CN",
    "gn:dem":1688,
    "gn:feature_class":"P",
    "gn:feature_code":"PPL",
    "gn:name":"Fu\u2019an",
    "gn:population":0,
    "gn:timezone":"Asia/Shanghai",
    "iso:country":"CN",
    "name:und_x_variant":[
        "Fu\u2019an"
    ],
    "name:zho_x_preferred":[
        "\u798f\u5b89"
    ],
    "wof:name":"Fu'an",
    "wof:placetype":"locality"
},
  "geometry": {"coordinates":[103.871,37.5712],"type":"Point"}
}