{
  "type": "Feature",
  "properties": {
    "gn:admin1_code":"26.0",
    "gn:asciiname":"Yanglumao",
    "gn:country_code":"CN",
    "gn:dem":1001,
    "gn:feature_class":"P",
    "gn:feature_code":"PPL",
    "gn:name":"Yanglumao",
    "gn:population":0,
    "gn:timezone":"Asia/Shanghai",
    "iso:country":"CN",
    "name:zho_x_preferred":[
        "\u9633\u8def\u5cc1"
    ],
    "wof:name":"Yanglumao",
    "wof:placetype":"locality"
},
  "geometry": {"coordinates":[109.85563999999999,37.57751],"type":"Point"}
}