{
  "type": "Feature",
  "properties": {
    "gn:admin1_code":"32.0",
    "gn:asciiname":"Laoheyan",
    "gn:country_code":"CN",
    "gn:dem":355,
    "gn:feature_class":"P",
    "gn:feature_code":"PPL",
    "gn:name":"Laoheyan",
    "gn:population":0,
    "gn:timezone":"Asia/Shanghai",
    "iso:country":"CN",
    "name:zho_x_preferred":[
        "\u8001\u6cb3\u5830"
    ],
    "wof:name":"Laoheyan",
    "wof:placetype":"locality"
},
  "geometry": {"coordinates":[105.24048999999999,29.66526],"type":"Point"}
}