{
  "type": "Feature",
  "properties": {
    "gn:admin1_code":"7.0",
    "gn:asciiname":"Gongyu",
    "gn:country_code":"CN",
    "gn:dem":968,
    "gn:feature_class":"P",
    "gn:feature_code":"PPL",
    "gn:name":"Gongyu",
    "gn:population":0,
    "gn:timezone":"Asia/Shanghai",
    "iso:country":"CN",
    "name:zho_x_preferred":[
        "\u5171\u88d5"
    ],
    "wof:name":"Gongyu",
    "wof:placetype":"locality"
},
  "geometry": {"coordinates":[117.47208999999999,25.94658],"type":"Point"}
}