{
  "type": "Feature",
  "properties": {
    "gn:admin1_code":"29.0",
    "gn:asciiname":"Huihuideng",
    "gn:country_code":"CN",
    "gn:dem":1794,
    "gn:feature_class":"P",
    "gn:feature_code":"PPL",
    "gn:name":"Huihuideng",
    "gn:population":0,
    "gn:timezone":"Asia/Shanghai",
    "iso:country":"CN",
    "name:zho_x_preferred":[
        "\u56de\u8f89\u767b"
    ],
    "wof:name":"Huihuideng",
    "wof:placetype":"locality"
},
  "geometry": {"coordinates":[100.17700000000001,25.4483],"type":"Point"}
}