{
  "type": "Feature",
  "properties": {
    "gn:admin1_code":"19.0",
    "gn:asciiname":"Zhutuncun",
    "gn:country_code":"CN",
    "gn:dem":68,
    "gn:feature_class":"P",
    "gn:feature_code":"PPL",
    "gn:name":"Zhutuncun",
    "gn:population":0,
    "gn:timezone":"Asia/Shanghai",
    "iso:country":"CN",
    "name:zho_x_preferred":[
        "\u6731\u5c6f\u6751"
    ],
    "wof:name":"Zhutuncun",
    "wof:placetype":"locality"
},
  "geometry": {"coordinates":[121.71599999999999,41.5577],"type":"Point"}
}