{
  "type": "Feature",
  "properties": {
    "gn:admin1_code":"30",
    "gn:asciiname":"Shangdaimei",
    "gn:country_code":"CN",
    "gn:dem":8,
    "gn:feature_class":"P",
    "gn:feature_code":"PPL",
    "gn:name":"Shangdaimei",
    "gn:population":0,
    "gn:timezone":"Asia/Shanghai",
    "iso:country":"CN",
    "name:zho_x_preferred":[
        "\u4e0a\u5cb1\u7f8e"
    ],
    "wof:name":"Shangdaimei",
    "wof:placetype":"locality"
},
  "geometry": {"coordinates":[116.79853,23.54147],"type":"Point"}
}