{
  "type": "Feature",
  "properties": {
    "gn:admin1_code":"9.0",
    "gn:asciiname":"Sanwangzhuang",
    "gn:country_code":"CN",
    "gn:dem":164,
    "gn:feature_class":"P",
    "gn:feature_code":"PPL",
    "gn:name":"Sanwangzhuang",
    "gn:population":0,
    "gn:timezone":"Asia/Shanghai",
    "iso:country":"CN",
    "name:zho_x_preferred":[
        "\u4e09\u738b\u5e84"
    ],
    "wof:name":"Sanwangzhuang",
    "wof:placetype":"locality"
},
  "geometry": {"coordinates":[114.18362,35.75136],"type":"Point"}
}