{
  "type": "Feature",
  "properties": {
    "gn:admin1_code":"3.0",
    "gn:asciiname":"Mangtouwo",
    "gn:country_code":"CN",
    "gn:dem":510,
    "gn:feature_class":"P",
    "gn:feature_code":"PPL",
    "gn:name":"Mangtouwo",
    "gn:population":0,
    "gn:timezone":"Asia/Shanghai",
    "iso:country":"CN",
    "name:und_x_variant":[
        "\u8292\u5934\u7a9d"
    ],
    "wof:name":"Mangtouwo",
    "wof:placetype":"locality"
},
  "geometry": {"coordinates":[115.00537,26.45089],"type":"Point"}
}