{
  "type": "Feature",
  "properties": {
    "gn:country":"CN",
    "gn:fcode":"ADM3",
    "gn:pop":0,
    "iso:country":"CN",
    "name:unk_x_variant":[
        "T\u2019ung-tzu Hsien"
    ],
    "name:zho_x_preferred":[
        "\u6850\u6893\u53bf"
    ],
    "name:zho_x_variant":[
        "\u6850\u6893"
    ],
    "qs:name":"Tongzi Xian",
    "qs:photos_9r":0,
    "qs:photos_sr":0,
    "qs:pop_sr":"0",
    "wof:name":"Tongzi Xian",
    "wof:placetype":"localadmin",
    "wof:population":0
},
  "geometry": {"coordinates":[106.83942999999999,28.28274],"type":"Point"}
}