{
  "type": "Feature",
  "properties": {
    "gn:admin1_code":"30.0",
    "gn:asciiname":"Xialaisheng",
    "gn:country_code":"CN",
    "gn:dem":2,
    "gn:feature_class":"P",
    "gn:feature_code":"PPL",
    "gn:name":"Xialaisheng",
    "gn:population":0,
    "gn:timezone":"Asia/Shanghai",
    "iso:country":"CN",
    "name:zho_x_preferred":[
        "\u4e0b\u8d56\u751f"
    ],
    "wof:name":"Xialaisheng",
    "wof:placetype":"locality"
},
  "geometry": {"coordinates":[113.46592,22.70568],"type":"Point"}
}