{
  "type": "Feature",
  "properties": {
    "gn:admin1_code":"32.0",
    "gn:asciiname":"Sanjia Puzi",
    "gn:country_code":"CN",
    "gn:dem":2035,
    "gn:feature_class":"P",
    "gn:feature_code":"PPL",
    "gn:name":"Sanjia Puzi",
    "gn:population":0,
    "gn:timezone":"Asia/Shanghai",
    "iso:country":"CN",
    "name:zho_x_preferred":[
        "\u4e09\u5bb6\u94fa\u5b50"
    ],
    "wof:name":"Sanjia Puzi",
    "wof:placetype":"locality"
},
  "geometry": {"coordinates":[102.02,28.1058],"type":"Point"}
}