{
  "type": "Feature",
  "properties": {
    "gn:admin1_code":"26",
    "gn:asciiname":"Shimadao",
    "gn:country_code":"CN",
    "gn:dem":912,
    "gn:feature_class":"P",
    "gn:feature_code":"PPL",
    "gn:name":"Shimadao",
    "gn:population":0,
    "gn:timezone":"Asia/Shanghai",
    "iso:country":"CN",
    "name:zho_x_preferred":[
        "\u77f3\u9a6c\u9053"
    ],
    "wof:name":"Shimadao",
    "wof:placetype":"locality"
},
  "geometry": {"coordinates":[108.21444,34.57306],"type":"Point"}
}