{
  "type": "Feature",
  "properties": {
    "gn:admin1_code":"2.0",
    "gn:asciiname":"Caoshan",
    "gn:country_code":"CN",
    "gn:dem":202,
    "gn:feature_class":"P",
    "gn:feature_code":"PPL",
    "gn:name":"Caoshan",
    "gn:population":0,
    "gn:timezone":"Asia/Shanghai",
    "iso:country":"CN",
    "name:und_x_variant":[
        "\u8349\u5c71",
        "Caoshan"
    ],
    "wof:name":"Caoshan",
    "wof:placetype":"locality"
},
  "geometry": {"coordinates":[119.78942000000001,29.40732],"type":"Point"}
}