{
  "type": "Feature",
  "properties": {
    "gn:admin1_code":"11.0",
    "gn:asciiname":"Huagongqiao",
    "gn:country_code":"CN",
    "gn:dem":282,
    "gn:feature_class":"P",
    "gn:feature_code":"PPL",
    "gn:name":"Huagongqiao",
    "gn:population":0,
    "gn:timezone":"Asia/Shanghai",
    "iso:country":"CN",
    "name:zho_x_preferred":[
        "\u534e\u516c\u6865"
    ],
    "wof:name":"Huagongqiao",
    "wof:placetype":"locality"
},
  "geometry": {"coordinates":[113.78845,28.54954],"type":"Point"}
}