{
  "type": "Feature",
  "properties": {
    "gn:admin1_code":"13.0",
    "gn:asciiname":"Tuoma Beixi",
    "gn:country_code":"CN",
    "gn:dem":1651,
    "gn:feature_class":"P",
    "gn:feature_code":"PPL",
    "gn:name":"Tuoma Beixi",
    "gn:population":0,
    "gn:timezone":"Asia/Shanghai",
    "iso:country":"CN",
    "name:und_x_variant":[
        "\u6258\u9a6c\u8d1d\u5e0c"
    ],
    "wof:name":"Tuoma Beixi",
    "wof:placetype":"locality"
},
  "geometry": {"coordinates":[75.83367,38.92343],"type":"Point"}
}