{
  "type": "Feature",
  "properties": {
    "gn:admin1_code":"10",
    "gn:asciiname":"Datianwa",
    "gn:cc2":"CN",
    "gn:country_code":"CN",
    "gn:dem":991,
    "gn:feature_class":"P",
    "gn:feature_code":"PPL",
    "gn:name":"Datianwa",
    "gn:population":0,
    "gn:timezone":"Asia/Shanghai",
    "iso:country":"CN",
    "name:und_x_variant":[
        "Ta-t\u2019ien-wa",
        "Datianwa"
    ],
    "wof:name":"Datianwa",
    "wof:placetype":"locality"
},
  "geometry": {"coordinates":[114.69110999999999,40.22028],"type":"Point"}
}