{
  "type": "Feature",
  "properties": {
    "gn:admin1_code":"1.0",
    "gn:asciiname":"Xinkaicun",
    "gn:country_code":"CN",
    "gn:dem":14,
    "gn:feature_class":"P",
    "gn:feature_code":"PPL",
    "gn:name":"Xinkaicun",
    "gn:population":0,
    "gn:timezone":"Asia/Shanghai",
    "iso:country":"CN",
    "name:zho_x_preferred":[
        "\u65b0\u5f00\u6751"
    ],
    "wof:name":"Xinkaicun",
    "wof:placetype":"locality"
},
  "geometry": {"coordinates":[117.35075999999999,30.70519],"type":"Point"}
}