{
  "type": "Feature",
  "properties": {
    "gn:admin1_code":"6.0",
    "gn:asciiname":"Chaha",
    "gn:country_code":"CN",
    "gn:dem":4040,
    "gn:feature_class":"P",
    "gn:feature_code":"PPL",
    "gn:name":"Chaha",
    "gn:population":0,
    "gn:timezone":"Asia/Urumqi",
    "iso:country":"CN",
    "name:zho_x_preferred":[
        "\u67e5\u54c8"
    ],
    "wof:name":"Chaha",
    "wof:placetype":"locality"
},
  "geometry": {"coordinates":[95.72687000000001,32.53107],"type":"Point"}
}