{
  "type": "Feature",
  "properties": {
    "gn:admin1_code":"19.0",
    "gn:asciiname":"Xianyu",
    "gn:country_code":"CN",
    "gn:dem":60,
    "gn:feature_class":"P",
    "gn:feature_code":"PPL",
    "gn:name":"Xianyu",
    "gn:population":0,
    "gn:timezone":"Asia/Shanghai",
    "iso:country":"CN",
    "name:und_x_variant":[
        "\u73b0\u5cea"
    ],
    "name:zho_x_preferred":[
        "\u73b0\u5cea"
    ],
    "wof:name":"Xianyu",
    "wof:placetype":"locality"
},
  "geometry": {"coordinates":[122.59625,40.46049],"type":"Point"}
}