{
  "type": "Feature",
  "properties": {
    "gn:admin1_code":"07",
    "gn:asciiname":"Kuge",
    "gn:country_code":"CN",
    "gn:dem":760,
    "gn:feature_class":"P",
    "gn:feature_code":"PPL",
    "gn:name":"Kuge",
    "gn:population":0,
    "gn:timezone":"Asia/Shanghai",
    "iso:country":"CN",
    "name:zho_x_preferred":[
        "\u82e6\u683c"
    ],
    "wof:name":"Kuge",
    "wof:placetype":"locality"
},
  "geometry": {"coordinates":[118.28905,25.71912],"type":"Point"}
}