{
  "type": "Feature",
  "properties": {
    "gn:admin1_code":"07",
    "gn:asciiname":"Kuge",
    "gn:country_code":"CN",
    "gn:dem":760,
    "gn:feature_class":"P",
    "gn:feature_code":"PPL",
    "gn:name":"Kuge",
    "gn:population":0,
    "gn:timezone":"Asia/Shanghai",
    "iso:country":"CN",
    "name:cat_x_preferred":[
        "Kuge"
    ],
    "name:deu_x_preferred":[
        "Kuge"
    ],
    "name:fas_x_preferred":[
        "\u06a9\u0648\u06af\u0647"
    ],
    "name:fra_x_preferred":[
        "Kuge"
    ],
    "name:ita_x_preferred":[
        "Kuge"
    ],
    "name:pol_x_preferred":[
        "Kuge"
    ],
    "name:por_x_preferred":[
        "Kuge"
    ],
    "name:rus_x_preferred":[
        "\u041a\u0443\u0433\u044d"
    ],
    "name:spa_x_preferred":[
        "Kuge"
    ],
    "name:swe_x_preferred":[
        "Kuge"
    ],
    "name:tha_x_preferred":[
        "\u0e04\u0e39\u0e40\u0e07\u0e30"
    ],
    "name:tur_x_preferred":[
        "Kuge"
    ],
    "name:ukr_x_preferred":[
        "\u041a\u0443\u0491\u0435"
    ],
    "name:vie_x_preferred":[
        "Kuge"
    ],
    "name:zho_x_preferred":[
        "\u82e6\u683c"
    ],
    "wof:name":"Kuge",
    "wof:placetype":"locality"
},
  "geometry": {"coordinates":[118.28905,25.71912],"type":"Point"}
}