{
  "type": "Feature",
  "properties": {
    "gn:admin1_code":"18.0",
    "gn:asciiname":"Kongguan",
    "gn:country_code":"CN",
    "gn:dem":1547,
    "gn:feature_class":"P",
    "gn:feature_code":"PPL",
    "gn:name":"Kongguan",
    "gn:population":0,
    "gn:timezone":"Asia/Shanghai",
    "iso:country":"CN",
    "name:zho_x_preferred":[
        "\u5b54\u5b98"
    ],
    "wof:name":"Kongguan",
    "wof:placetype":"locality"
},
  "geometry": {"coordinates":[104.712,25.8589],"type":"Point"}
}