{
  "type": "Feature",
  "properties": {
    "gn:admin1_code":"25.0",
    "gn:asciiname":"Mating Wangjia",
    "gn:country_code":"CN",
    "gn:dem":9,
    "gn:feature_class":"P",
    "gn:feature_code":"PPL",
    "gn:name":"Mating Wangjia",
    "gn:population":0,
    "gn:timezone":"Asia/Shanghai",
    "iso:country":"CN",
    "name:zho_x_preferred":[
        "\u9a6c\u4ead\u738b\u5bb6"
    ],
    "wof:name":"Mating Wangjia",
    "wof:placetype":"locality"
},
  "geometry": {"coordinates":[120.33748,37.61615],"type":"Point"}
}