{
  "type": "Feature",
  "properties": {
    "gn:admin1_code":"18",
    "gn:asciiname":"Hebianzhai",
    "gn:country_code":"CN",
    "gn:dem":951,
    "gn:feature_class":"P",
    "gn:feature_code":"PPL",
    "gn:name":"Hebianzhai",
    "gn:population":0,
    "gn:timezone":"Asia/Shanghai",
    "iso:country":"CN",
    "name:zho_x_preferred":[
        "\u6cb3\u8fb9\u5be8"
    ],
    "wof:name":"Hebianzhai",
    "wof:placetype":"locality"
},
  "geometry": {"coordinates":[106.15000000000001,26.7892],"type":"Point"}
}