{
  "type": "Feature",
  "properties": {
    "gn:admin1_code":"2.0",
    "gn:asciiname":"Dapanxi",
    "gn:country_code":"CN",
    "gn:dem":430,
    "gn:feature_class":"P",
    "gn:feature_code":"PPL",
    "gn:name":"Dapanxi",
    "gn:population":0,
    "gn:timezone":"Asia/Shanghai",
    "iso:country":"CN",
    "name:zho_x_preferred":[
        "\u5927\u87e0\u6eaa"
    ],
    "wof:name":"Dapanxi",
    "wof:placetype":"locality"
},
  "geometry": {"coordinates":[120.68962000000001,29.30887],"type":"Point"}
}