{
  "type": "Feature",
  "properties": {
    "gn:admin1_code":"16.0",
    "gn:asciiname":"Mindongkou",
    "gn:country_code":"CN",
    "gn:dem":205,
    "gn:feature_class":"P",
    "gn:feature_code":"PPL",
    "gn:name":"Mindongkou",
    "gn:population":0,
    "gn:timezone":"Asia/Shanghai",
    "iso:country":"CN",
    "name:zho_x_preferred":[
        "\u6c11\u6d1e\u53e3"
    ],
    "wof:name":"Mindongkou",
    "wof:placetype":"locality"
},
  "geometry": {"coordinates":[108.998,25.2649],"type":"Point"}
}