{
  "type": "Feature",
  "properties": {
    "gn:admin1_code":"18",
    "gn:asciiname":"Liangshuigou Yangchang",
    "gn:country_code":"CN",
    "gn:dem":2387,
    "gn:feature_class":"P",
    "gn:feature_code":"PPLF",
    "gn:name":"Liangshuigou Yangchang",
    "gn:population":0,
    "gn:timezone":"Asia/Shanghai",
    "iso:country":"CN",
    "name:zho_x_preferred":[
        "\u51c9\u6c34\u6c9f\u7f8a\u573a"
    ],
    "wof:name":"Liangshuigou Yangchang",
    "wof:placetype":"locality"
},
  "geometry": {"coordinates":[104.471,26.9758],"type":"Point"}
}