{
  "type": "Feature",
  "properties": {
    "gn:admin1_code":"03",
    "gn:asciiname":"Sanlong",
    "gn:country_code":"CN",
    "gn:dem":42,
    "gn:feature_class":"P",
    "gn:feature_code":"PPLA4",
    "gn:name":"Sanlong",
    "gn:population":0,
    "gn:timezone":"Asia/Shanghai",
    "iso:country":"CN",
    "name:und_x_variant":[
        "San-lung",
        "San-lung-shih",
        "San-lung-chieh",
        "Sanlong",
        "\u4e09\u9f99",
        "Sanlong Xiang",
        "\u4e09\u9f99\u4e61"
    ],
    "wof:name":"Sanlong",
    "wof:placetype":"locality"
},
  "geometry": {"coordinates":[117.14511,29.38529],"type":"Point"}
}