{
  "type": "Feature",
  "properties": {
    "gn:admin1_code":"14.0",
    "gn:asciiname":"Zhuochi",
    "gn:country_code":"CN",
    "gn:dem":3838,
    "gn:feature_class":"P",
    "gn:feature_code":"PPL",
    "gn:name":"Zhuochi",
    "gn:population":0,
    "gn:timezone":"Asia/Urumqi",
    "iso:country":"CN",
    "name:zho_x_preferred":[
        "\u5353\u6c60"
    ],
    "wof:name":"Zhuochi",
    "wof:placetype":"locality"
},
  "geometry": {"coordinates":[96.30079000000001,31.73906],"type":"Point"}
}