{
  "type": "Feature",
  "properties": {
    "gn:admin1_code":"8.0",
    "gn:asciiname":"Dahei",
    "gn:country_code":"CN",
    "gn:dem":156,
    "gn:feature_class":"P",
    "gn:feature_code":"PPL",
    "gn:name":"Dahei",
    "gn:population":0,
    "gn:timezone":"Asia/Shanghai",
    "iso:country":"CN",
    "name:zho_x_preferred":[
        "\u5927\u9ed1"
    ],
    "wof:name":"Dahei",
    "wof:placetype":"locality"
},
  "geometry": {"coordinates":[123.43087,47.17509],"type":"Point"}
}