{
  "type": "Feature",
  "properties": {
    "gn:admin1_code":"31.0",
    "gn:asciiname":"Sanlian",
    "gn:country_code":"CN",
    "gn:dem":335,
    "gn:feature_class":"P",
    "gn:feature_code":"PPL",
    "gn:name":"Sanlian",
    "gn:population":0,
    "gn:timezone":"Asia/Shanghai",
    "iso:country":"CN",
    "name:und_x_variant":[
        "\u4e09\u8054"
    ],
    "name:zho_x_preferred":[
        "\u4e09\u8054"
    ],
    "wof:name":"Sanlian",
    "wof:placetype":"locality"
},
  "geometry": {"coordinates":[109.63136000000002,18.97131],"type":"Point"}
}