{
  "type": "Feature",
  "properties": {
    "gn:admin1_code":"9.0",
    "gn:asciiname":"Xixue",
    "gn:country_code":"CN",
    "gn:dem":122,
    "gn:feature_class":"P",
    "gn:feature_code":"PPL",
    "gn:name":"Xixue",
    "gn:population":0,
    "gn:timezone":"Asia/Shanghai",
    "iso:country":"CN",
    "name:und_x_variant":[
        "\u897f\u5b66",
        "Xixue"
    ],
    "wof:name":"Xixue",
    "wof:placetype":"locality"
},
  "geometry": {"coordinates":[112.89757,33.00603],"type":"Point"}
}