{
  "type": "Feature",
  "properties": {
    "gn:admin1_code":"10",
    "gn:asciiname":"Xiniuzhuang",
    "gn:country_code":"CN",
    "gn:dem":33,
    "gn:feature_class":"P",
    "gn:feature_code":"PPL",
    "gn:name":"Xiniuzhuang",
    "gn:population":0,
    "gn:timezone":"Asia/Shanghai",
    "iso:country":"CN",
    "name:zho_x_preferred":[
        "\u897f\u725b\u5e84"
    ],
    "wof:name":"Xiniuzhuang",
    "wof:placetype":"locality"
},
  "geometry": {"coordinates":[115.774,37.1967],"type":"Point"}
}