{
  "type": "Feature",
  "properties": {
    "gn:admin1_code":"16.0",
    "gn:asciiname":"Jiantou",
    "gn:country_code":"CN",
    "gn:dem":171,
    "gn:feature_class":"P",
    "gn:feature_code":"PPL",
    "gn:name":"Jiantou",
    "gn:population":0,
    "gn:timezone":"Asia/Shanghai",
    "iso:country":"CN",
    "name:zho_x_preferred":[
        "\u67a7\u5934"
    ],
    "wof:name":"Jiantou",
    "wof:placetype":"locality"
},
  "geometry": {"coordinates":[111.215,22.8574],"type":"Point"}
}