{
  "type": "Feature",
  "properties": {
    "gn:admin1_code":"30",
    "gn:asciiname":"Houtang",
    "gn:country_code":"CN",
    "gn:dem":48,
    "gn:feature_class":"P",
    "gn:feature_code":"PPL",
    "gn:name":"Houtang",
    "gn:population":0,
    "gn:timezone":"Asia/Urumqi",
    "iso:country":"CN",
    "name:zho_x_preferred":[
        "\u540e\u5858"
    ],
    "wof:name":"Houtang",
    "wof:placetype":"locality"
},
  "geometry": {"coordinates":[109.97481999999999,20.68975],"type":"Point"}
}