{
  "type": "Feature",
  "properties": {
    "gn:admin1_code":"3.0",
    "gn:asciiname":"Shangpingcun",
    "gn:country_code":"CN",
    "gn:dem":637,
    "gn:feature_class":"P",
    "gn:feature_code":"PPL",
    "gn:name":"Shangpingcun",
    "gn:population":0,
    "gn:timezone":"Asia/Shanghai",
    "iso:country":"CN",
    "name:und_x_variant":[
        "\u4e0a\u576a\u6751"
    ],
    "wof:name":"Shangpingcun",
    "wof:placetype":"locality"
},
  "geometry": {"coordinates":[116.52397000000001,26.51542],"type":"Point"}
}