{
  "type": "Feature",
  "properties": {
    "gn:admin1_code":"11.0",
    "gn:asciiname":"Qishizhuangshang",
    "gn:country_code":"CN",
    "gn:dem":178,
    "gn:feature_class":"P",
    "gn:feature_code":"PPL",
    "gn:name":"Qishizhuangshang",
    "gn:population":0,
    "gn:timezone":"Asia/Shanghai",
    "iso:country":"CN",
    "name:zho_x_preferred":[
        "\u5c90\u77f3\u5e84\u4e0a"
    ],
    "wof:name":"Qishizhuangshang",
    "wof:placetype":"locality"
},
  "geometry": {"coordinates":[112.47655,25.82657],"type":"Point"}
}