{
  "type": "Feature",
  "properties": {
    "gn:admin1_code":"14.0",
    "gn:asciiname":"Sangduocun",
    "gn:country_code":"CN",
    "gn:dem":4666,
    "gn:feature_class":"P",
    "gn:feature_code":"PPL",
    "gn:name":"Sangduocun",
    "gn:population":0,
    "gn:timezone":"Asia/Urumqi",
    "iso:country":"CN",
    "name:zho_x_preferred":[
        "\u6851\u591a\u6751"
    ],
    "wof:name":"Sangduocun",
    "wof:placetype":"locality"
},
  "geometry": {"coordinates":[92.01117000000001,31.28172],"type":"Point"}
}