{
  "type": "Feature",
  "properties": {
    "gn:admin1_code":"22.0",
    "gn:asciiname":"Guantou",
    "gn:country_code":"CN",
    "gn:dem":31,
    "gn:feature_class":"P",
    "gn:feature_code":"PPL",
    "gn:name":"Guantou",
    "gn:population":0,
    "gn:timezone":"Asia/Shanghai",
    "iso:country":"CN",
    "name:zho_x_preferred":[
        "\u7ba1\u5934"
    ],
    "wof:name":"Guantou",
    "wof:placetype":"locality"
},
  "geometry": {"coordinates":[116.60798,40.02277],"type":"Point"}
}