{
  "type": "Feature",
  "properties": {
    "gn:admin1_code":"4.0",
    "gn:asciiname":"Wugangcun",
    "gn:country_code":"CN",
    "gn:dem":14,
    "gn:feature_class":"P",
    "gn:feature_code":"PPL",
    "gn:name":"Wugangcun",
    "gn:population":0,
    "gn:timezone":"Asia/Shanghai",
    "iso:country":"CN",
    "name:zho_x_preferred":[
        "\u5deb\u5c97\u6751"
    ],
    "wof:name":"Wugangcun",
    "wof:placetype":"locality"
},
  "geometry": {"coordinates":[119.30486999999999,32.12769],"type":"Point"}
}