{
  "type": "Feature",
  "properties": {
    "gn:admin1_code":"8.0",
    "gn:asciiname":"Hujia Wopeng",
    "gn:country_code":"CN",
    "gn:dem":225,
    "gn:feature_class":"P",
    "gn:feature_code":"PPL",
    "gn:name":"Hujia Wopeng",
    "gn:population":0,
    "gn:timezone":"Asia/Shanghai",
    "iso:country":"CN",
    "name:zho_x_preferred":[
        "\u80e1\u5bb6\u7a9d\u68da"
    ],
    "wof:name":"Hujia Wopeng",
    "wof:placetype":"locality"
},
  "geometry": {"coordinates":[125.2576,49.28769000000001],"type":"Point"}
}