{
  "type": "Feature",
  "properties": {
    "gn:admin1_code":"26.0",
    "gn:asciiname":"Shipeicun",
    "gn:country_code":"CN",
    "gn:dem":966,
    "gn:feature_class":"P",
    "gn:feature_code":"PPL",
    "gn:name":"Shipeicun",
    "gn:population":0,
    "gn:timezone":"Asia/Shanghai",
    "iso:country":"CN",
    "name:zho_x_preferred":[
        "\u77f3\u57f9\u6751"
    ],
    "wof:name":"Shipeicun",
    "wof:placetype":"locality"
},
  "geometry": {"coordinates":[110.30110000000001,36.11243],"type":"Point"}
}