{
  "type": "Feature",
  "properties": {
    "gn:admin1_code":"3.0",
    "gn:asciiname":"Emeifan",
    "gn:country_code":"CN",
    "gn:dem":546,
    "gn:feature_class":"P",
    "gn:feature_code":"PPL",
    "gn:name":"Emeifan",
    "gn:population":0,
    "gn:timezone":"Asia/Shanghai",
    "iso:country":"CN",
    "name:zho_x_preferred":[
        "\u9e45\u7709\u7548"
    ],
    "wof:name":"Emeifan",
    "wof:placetype":"locality"
},
  "geometry": {"coordinates":[117.93300000000001,28.0067],"type":"Point"}
}