{
  "type": "Feature",
  "properties": {
    "gn:admin1_code":"8.0",
    "gn:asciiname":"Jubaotun",
    "gn:country_code":"CN",
    "gn:dem":143,
    "gn:feature_class":"P",
    "gn:feature_code":"PPL",
    "gn:name":"Jubaotun",
    "gn:population":0,
    "gn:timezone":"Asia/Shanghai",
    "iso:country":"CN",
    "name:zho_x_preferred":[
        "\u5de8\u5b9d\u5c6f"
    ],
    "wof:name":"Jubaotun",
    "wof:placetype":"locality"
},
  "geometry": {"coordinates":[125.08873,46.43644000000001],"type":"Point"}
}