{
  "type": "Feature",
  "properties": {
    "gn:admin1_code":"32.0",
    "gn:asciiname":"Waniwo",
    "gn:country_code":"CN",
    "gn:dem":2075,
    "gn:feature_class":"P",
    "gn:feature_code":"PPL",
    "gn:name":"Waniwo",
    "gn:population":0,
    "gn:timezone":"Asia/Shanghai",
    "iso:country":"CN",
    "name:zho_x_preferred":[
        "\u74e6\u5c3c\u6c83"
    ],
    "wof:name":"Waniwo",
    "wof:placetype":"locality"
},
  "geometry": {"coordinates":[103.309,27.9545],"type":"Point"}
}