{
  "type": "Feature",
  "properties": {
    "gn:gn_country":"CN",
    "gn:gn_fcode":"PPL",
    "gn:gn_pop":130218,
    "gn:population":130218,
    "iso:country":"CN",
    "name:unk_x_variant":[
        "Sung-chiang-hsien"
    ],
    "qs_pg:aaroncc":"CN",
    "qs_pg:gn_country":"CN",
    "qs_pg:gn_fcode":"PPL",
    "qs_pg:gn_pop":130218,
    "qs_pg:name":"\u677e\u6c5f",
    "qs_pg:name_adm0":"\u4e2d\u570b",
    "qs_pg:name_adm1":"\u4e0a\u6d77\u76f4\u8f96\u5e02",
    "qs_pg:photos":13,
    "qs_pg:photos_1k":3,
    "qs_pg:photos_9k":1,
    "qs_pg:photos_9r":1,
    "qs_pg:photos_all":13,
    "qs_pg:photos_sr":1,
    "qs_pg:pop_sr":9,
    "qs_pg:qs_pg_placetype":"neighbourhood",
    "qs_pg:qs_pg_placetype_gp":"Suburb",
    "qs_pg:woe_adm0":23424781,
    "woe:adm0_id":23424781,
    "woe:name_adm0":"\u4e2d\u570b",
    "woe:name_adm1":"\u4e0a\u6d77\u76f4\u8f96\u5e02",
    "woe:placetype":"Suburb",
    "wof:name":"\u677e\u6c5f",
    "wof:placetype":"neighbourhood",
    "wof:population":130218
},
  "geometry": {"coordinates":[121.2146,31.03595],"type":"Point"}
}