{
  "type": "Feature",
  "properties": {
    "gn:admin1_code":"32.0",
    "gn:asciiname":"Taipingba",
    "gn:country_code":"CN",
    "gn:dem":329,
    "gn:feature_class":"P",
    "gn:feature_code":"PPL",
    "gn:name":"Taipingba",
    "gn:population":0,
    "gn:timezone":"Asia/Shanghai",
    "iso:country":"CN",
    "name:zho_x_preferred":[
        "\u592a\u5e73\u575d"
    ],
    "wof:name":"Taipingba",
    "wof:placetype":"locality"
},
  "geometry": {"coordinates":[105.003,29.6387],"type":"Point"}
}