{
  "type": "Feature",
  "properties": {
    "gn:admin1_code":"1.0",
    "gn:asciiname":"Qianfengcun",
    "gn:country_code":"CN",
    "gn:dem":31,
    "gn:feature_class":"P",
    "gn:feature_code":"PPL",
    "gn:name":"Qianfengcun",
    "gn:population":0,
    "gn:timezone":"Asia/Shanghai",
    "iso:country":"CN",
    "name:zho_x_preferred":[
        "\u5343\u5cf0\u6751"
    ],
    "wof:name":"Qianfengcun",
    "wof:placetype":"locality"
},
  "geometry": {"coordinates":[118.37128,30.88287],"type":"Point"}
}