{
  "type": "Feature",
  "properties": {
    "gn:admin1_code":"26.0",
    "gn:asciiname":"Huangshaqidun",
    "gn:country_code":"CN",
    "gn:dem":1170,
    "gn:feature_class":"P",
    "gn:feature_code":"PPL",
    "gn:name":"Huangshaqidun",
    "gn:population":0,
    "gn:timezone":"Asia/Shanghai",
    "iso:country":"CN",
    "name:zho_x_preferred":[
        "\u9ec4\u6c99\u4e03\u58a9"
    ],
    "wof:name":"Huangshaqidun",
    "wof:placetype":"locality"
},
  "geometry": {"coordinates":[109.54423,38.21426],"type":"Point"}
}