{
  "type": "Feature",
  "properties": {
    "gn:admin1_code":"1.0",
    "gn:asciiname":"Liuhucun",
    "gn:country_code":"CN",
    "gn:dem":57,
    "gn:feature_class":"P",
    "gn:feature_code":"PPL",
    "gn:name":"Liuhucun",
    "gn:population":0,
    "gn:timezone":"Asia/Shanghai",
    "iso:country":"CN",
    "name:zho_x_preferred":[
        "\u5218\u6237\u6751"
    ],
    "wof:name":"Liuhucun",
    "wof:placetype":"locality"
},
  "geometry": {"coordinates":[117.50042999999999,32.02417],"type":"Point"}
}