{
  "type": "Feature",
  "properties": {
    "gn:admin1_code":"4.0",
    "gn:asciiname":"Jiebeicun",
    "gn:country_code":"CN",
    "gn:dem":3,
    "gn:feature_class":"P",
    "gn:feature_code":"PPL",
    "gn:name":"Jiebeicun",
    "gn:population":0,
    "gn:timezone":"Asia/Shanghai",
    "iso:country":"CN",
    "name:zho_x_preferred":[
        "\u8857\u5317\u6751"
    ],
    "wof:name":"Jiebeicun",
    "wof:placetype":"locality"
},
  "geometry": {"coordinates":[120.76971,32.68268],"type":"Point"}
}