{
  "type": "Feature",
  "properties": {
    "gn:admin1_code":"24.0",
    "gn:asciiname":"Niushiyao",
    "gn:country_code":"CN",
    "gn:dem":1345,
    "gn:feature_class":"P",
    "gn:feature_code":"PPL",
    "gn:name":"Niushiyao",
    "gn:population":0,
    "gn:timezone":"Asia/Shanghai",
    "iso:country":"CN",
    "name:zho_x_preferred":[
        "\u725b\u77f3\u7a91"
    ],
    "wof:name":"Niushiyao",
    "wof:placetype":"locality"
},
  "geometry": {"coordinates":[113.59307,36.05747],"type":"Point"}
}