{
  "type": "Feature",
  "properties": {
    "gn:admin1_code":"32.0",
    "gn:asciiname":"Jizha",
    "gn:country_code":"CN",
    "gn:dem":3715,
    "gn:feature_class":"P",
    "gn:feature_code":"PPL",
    "gn:name":"Jizha",
    "gn:population":0,
    "gn:timezone":"Asia/Shanghai",
    "iso:country":"CN",
    "name:zho_x_preferred":[
        "\u5409\u624e"
    ],
    "wof:name":"Jizha",
    "wof:placetype":"locality"
},
  "geometry": {"coordinates":[100.405,31.7798],"type":"Point"}
}