{
  "type": "Feature",
  "properties": {
    "gn:admin1_code":"09",
    "gn:asciiname":"Shiliang",
    "gn:cc2":"CN",
    "gn:country_code":"CN",
    "gn:dem":42,
    "gn:feature_class":"P",
    "gn:feature_code":"PPL",
    "gn:name":"Shiliang",
    "gn:population":0,
    "gn:timezone":"Asia/Shanghai",
    "iso:country":"CN",
    "name:und_x_variant":[
        "Shih-liang",
        "Shilyantszi",
        "Shih-liang-chi",
        "Shiliang"
    ],
    "wof:name":"Shiliang",
    "wof:placetype":"locality"
},
  "geometry": {"coordinates":[115.21666999999999,33.86667],"type":"Point"}
}