{
  "type": "Feature",
  "properties": {
    "gn:admin1_code":"29.0",
    "gn:asciiname":"Zhamiao",
    "gn:country_code":"CN",
    "gn:dem":2313,
    "gn:feature_class":"P",
    "gn:feature_code":"PPL",
    "gn:name":"Zhamiao",
    "gn:population":0,
    "gn:timezone":"Asia/Shanghai",
    "iso:country":"CN",
    "name:zho_x_preferred":[
        "\u624e\u82d7"
    ],
    "wof:name":"Zhamiao",
    "wof:placetype":"locality"
},
  "geometry": {"coordinates":[100.842,26.2594],"type":"Point"}
}