{
  "type": "Feature",
  "properties": {
    "gn:admin1_code":"29.0",
    "gn:asciiname":"Laozhuji",
    "gn:country_code":"CN",
    "gn:dem":2201,
    "gn:feature_class":"P",
    "gn:feature_code":"PPL",
    "gn:name":"Laozhuji",
    "gn:population":0,
    "gn:timezone":"Asia/Shanghai",
    "iso:country":"CN",
    "name:zho_x_preferred":[
        "\u8001\u9a7b\u57fa"
    ],
    "wof:name":"Laozhuji",
    "wof:placetype":"locality"
},
  "geometry": {"coordinates":[103.015,25.6728],"type":"Point"}
}