{
  "type": "Feature",
  "properties": {
    "gn:admin1_code":"3.0",
    "gn:asciiname":"Jiuxing",
    "gn:country_code":"CN",
    "gn:dem":656,
    "gn:feature_class":"P",
    "gn:feature_code":"PPL",
    "gn:name":"Jiuxing",
    "gn:population":0,
    "gn:timezone":"Asia/Shanghai",
    "iso:country":"CN",
    "name:und_x_variant":[
        "\u4e5d\u661f"
    ],
    "wof:name":"Jiuxing",
    "wof:placetype":"locality"
},
  "geometry": {"coordinates":[114.79121000000001,28.81737],"type":"Point"}
}