{
  "type": "Feature",
  "properties": {
    "gn:admin1_code":"11",
    "gn:asciiname":"Shitao",
    "gn:country_code":"CN",
    "gn:dem":366,
    "gn:feature_class":"P",
    "gn:feature_code":"PPL",
    "gn:name":"Shitao",
    "gn:population":0,
    "gn:timezone":"Asia/Shanghai",
    "iso:country":"CN",
    "name:ara_x_preferred":[
        "\u0634\u064a \u062a\u0627\u0648"
    ],
    "name:ast_x_preferred":[
        "Shitao"
    ],
    "name:bak_x_preferred":[
        "\u0428\u0438\u0442\u0430\u043e"
    ],
    "name:cat_x_preferred":[
        "Shitao"
    ],
    "name:ces_x_preferred":[
        "\u0160\u2019-tchao"
    ],
    "name:deu_x_preferred":[
        "Shi Tao"
    ],
    "name:fra_x_preferred":[
        "Shitao"
    ],
    "name:gle_x_preferred":[
        "Shitao"
    ],
    "name:glg_x_preferred":[
        "Shitao"
    ],
    "name:ind_x_preferred":[
        "Shitao"
    ],
    "name:ita_x_preferred":[
        "Shitao"
    ],
    "name:lat_x_preferred":[
        "Shitao"
    ],
    "name:mlg_x_preferred":[
        "Shitao"
    ],
    "name:nld_x_preferred":[
        "Shitao"
    ],
    "name:nor_x_preferred":[
        "Shitao"
    ],
    "name:pan_x_preferred":[
        "\u0a38\u0a3c\u0a40\u0a24\u0a3e\u0a13"
    ],
    "name:pol_x_preferred":[
        "Shitao"
    ],
    "name:rus_x_preferred":[
        "\u0428\u0438\u0442\u0430\u043e"
    ],
    "name:spa_x_preferred":[
        "Shitao"
    ],
    "name:ukr_x_preferred":[
        "\u0428\u0438\u0442\u0430\u043e"
    ],
    "name:yor_x_preferred":[
        "Shitao"
    ],
    "name:zho_x_preferred":[
        "\u77f3\u9676"
    ],
    "wof:name":"Shitao",
    "wof:placetype":"locality"
},
  "geometry": {"coordinates":[111.76546,27.94114],"type":"Point"}
}