{
  "type": "Feature",
  "properties": {
    "gn:admin1_code":"29.0",
    "gn:asciiname":"Tutubai",
    "gn:country_code":"CN",
    "gn:dem":1673,
    "gn:feature_class":"P",
    "gn:feature_code":"PPL",
    "gn:name":"Tutubai",
    "gn:population":0,
    "gn:timezone":"Asia/Shanghai",
    "iso:country":"CN",
    "name:zho_x_preferred":[
        "\u7a81\u5410\u767d"
    ],
    "wof:name":"Tutubai",
    "wof:placetype":"locality"
},
  "geometry": {"coordinates":[103.501,23.231],"type":"Point"}
}