{
  "type": "Feature",
  "properties": {
    "gn:admin1_code":"10.0",
    "gn:asciiname":"Shuangling",
    "gn:country_code":"CN",
    "gn:dem":17,
    "gn:feature_class":"P",
    "gn:feature_code":"PPL",
    "gn:name":"Shuangling",
    "gn:population":0,
    "gn:timezone":"Asia/Shanghai",
    "iso:country":"CN",
    "name:zho_x_preferred":[
        "\u53cc\u5cad"
    ],
    "wof:name":"Shuangling",
    "wof:placetype":"locality"
},
  "geometry": {"coordinates":[116.169,38.1274],"type":"Point"}
}