{
  "type": "Feature",
  "properties": {
    "gn:admin1_code":"9",
    "gn:asciiname":"Qincundian",
    "gn:country_code":"CN",
    "gn:dem":53,
    "gn:feature_class":"P",
    "gn:feature_code":"PPL",
    "gn:name":"Qincundian",
    "gn:population":0,
    "gn:timezone":"Asia/Shanghai",
    "iso:country":"CN",
    "name:zho_x_preferred":[
        "\u79e6\u6751\u5e97"
    ],
    "wof:name":"Qincundian",
    "wof:placetype":"locality"
},
  "geometry": {"coordinates":[115.09162000000001,36.0157],"type":"Point"}
}