{
  "type": "Feature",
  "properties": {
    "gn:admin1_code":"1.0",
    "gn:asciiname":"Tangoucun",
    "gn:country_code":"CN",
    "gn:dem":44,
    "gn:feature_class":"P",
    "gn:feature_code":"PPL",
    "gn:name":"Tangoucun",
    "gn:population":0,
    "gn:timezone":"Asia/Shanghai",
    "iso:country":"CN",
    "name:zho_x_preferred":[
        "\u8c2d\u6c9f\u6751"
    ],
    "wof:name":"Tangoucun",
    "wof:placetype":"locality"
},
  "geometry": {"coordinates":[115.64608,33.88407],"type":"Point"}
}