{
  "type": "Feature",
  "properties": {
    "gn:admin1_code":"7.0",
    "gn:asciiname":"Qingtang",
    "gn:country_code":"CN",
    "gn:dem":430,
    "gn:feature_class":"P",
    "gn:feature_code":"PPL",
    "gn:name":"Qingtang",
    "gn:population":0,
    "gn:timezone":"Asia/Shanghai",
    "iso:country":"CN",
    "name:und_x_variant":[
        "\u6e05\u5858"
    ],
    "name:zho_x_preferred":[
        "\u6e05\u5858"
    ],
    "wof:name":"Qingtang",
    "wof:placetype":"locality"
},
  "geometry": {"coordinates":[116.77923,26.28136],"type":"Point"}
}