{
  "type": "Feature",
  "properties": {
    "gn:admin1_code":"2",
    "gn:asciiname":"Zuoshi",
    "gn:country_code":"CN",
    "gn:dem":670,
    "gn:feature_class":"P",
    "gn:feature_code":"PPL",
    "gn:name":"Zuoshi",
    "gn:population":0,
    "gn:timezone":"Asia/Shanghai",
    "iso:country":"CN",
    "name:zho_x_preferred":[
        "\u5750\u77f3"
    ],
    "wof:name":"Zuoshi",
    "wof:placetype":"locality"
},
  "geometry": {"coordinates":[119.39833,27.70083],"type":"Point"}
}