{
  "type": "Feature",
  "properties": {
    "gn:country":"CN",
    "gn:fcode":"PPL",
    "gn:pop":65411,
    "iso:country":"CN",
    "name:unk_x_variant":[
        "Tan-ch\u2019eng"
    ],
    "name:zho_x_preferred":[
        "\u65b0\u57ce"
    ],
    "qs:name":"\u90f8\u57ce",
    "qs:name_adm0":"\u4e2d\u570b",
    "qs:name_adm1":"\u6cb3\u5357\u7701",
    "qs:photos_9r":0,
    "qs:photos_sr":0,
    "qs:placetype":"Town",
    "qs:pop_sr":"8",
    "wof:name":"\u90f8\u57ce",
    "wof:placetype":"locality",
    "wof:population":65411
},
  "geometry": {"coordinates":[115.18333,33.63333],"type":"Point"}
}