{
  "type": "Feature",
  "properties": {
    "gn:admin1_code":"11.0",
    "gn:asciiname":"Majiayu",
    "gn:country_code":"CN",
    "gn:dem":471,
    "gn:feature_class":"P",
    "gn:feature_code":"PPL",
    "gn:name":"Majiayu",
    "gn:population":0,
    "gn:timezone":"Asia/Shanghai",
    "iso:country":"CN",
    "name:zho_x_preferred":[
        "Majiayu"
    ],
    "name:zho_x_variant":[
        "\u9a6c\u5bb6\u5cea"
    ],
    "wof:name":"Majiayu",
    "wof:placetype":"locality"
},
  "geometry": {"coordinates":[110.6204,28.96214],"type":"Point"}
}