{
  "type": "Feature",
  "properties": {
    "gn:admin1_code":"16.0",
    "gn:asciiname":"Zengzidong",
    "gn:country_code":"CN",
    "gn:dem":47,
    "gn:feature_class":"P",
    "gn:feature_code":"PPL",
    "gn:name":"Zengzidong",
    "gn:population":0,
    "gn:timezone":"Asia/Shanghai",
    "iso:country":"CN",
    "name:zho_x_preferred":[
        "\u66fe\u5b50\u6d1e"
    ],
    "wof:name":"Zengzidong",
    "wof:placetype":"locality"
},
  "geometry": {"coordinates":[110.883,23.2539],"type":"Point"}
}