{
  "type": "Feature",
  "properties": {
    "gn:admin1_code":"4.0",
    "gn:asciiname":"Zhumatou",
    "gn:country_code":"CN",
    "gn:dem":2,
    "gn:feature_class":"P",
    "gn:feature_code":"PPL",
    "gn:name":"Zhumatou",
    "gn:population":0,
    "gn:timezone":"Asia/Shanghai",
    "iso:country":"CN",
    "name:und_x_variant":[
        "\u6731\u7801\u5934"
    ],
    "name:zho_x_preferred":[
        "\u6731\u7801\u5934"
    ],
    "wof:name":"Zhumatou",
    "wof:placetype":"locality"
},
  "geometry": {"coordinates":[120.64021,31.1822],"type":"Point"}
}