{
  "type": "Feature",
  "properties": {
    "gn:admin1_code":"10",
    "gn:asciiname":"Pangjiabu",
    "gn:cc2":"CN",
    "gn:country_code":"CN",
    "gn:dem":1037,
    "gn:feature_class":"P",
    "gn:feature_code":"PPL",
    "gn:name":"Pangjiabu",
    "gn:population":0,
    "gn:timezone":"Asia/Shanghai",
    "iso:country":"CN",
    "name:und_x_variant":[
        "P\u2019ang-chia-p\u2019u",
        "P\u2019ang-chia-pao",
        "Pangjiabu"
    ],
    "wof:name":"Pangjiabu",
    "wof:placetype":"locality"
},
  "geometry": {"coordinates":[115.44611,40.6475],"type":"Point"}
}