{
  "type": "Feature",
  "properties": {
    "gn:admin1_code":"5",
    "gn:asciiname":"Sandaopiaohe",
    "gn:country_code":"CN",
    "gn:dem":328,
    "gn:feature_class":"P",
    "gn:feature_code":"PPL",
    "gn:name":"Sandaopiaohe",
    "gn:population":0,
    "gn:timezone":"Asia/Shanghai",
    "iso:country":"CN",
    "name:zho_x_preferred":[
        "\u4e09\u9053\u6f02\u6cb3"
    ],
    "wof:name":"Sandaopiaohe",
    "wof:placetype":"locality"
},
  "geometry": {"coordinates":[127.459,43.3674],"type":"Point"}
}