{
  "type": "Feature",
  "properties": {
    "gn:admin1_code":"10",
    "gn:asciiname":"Dongdao",
    "gn:country_code":"CN",
    "gn:dem":474,
    "gn:feature_class":"P",
    "gn:feature_code":"PPL",
    "gn:name":"Dongdao",
    "gn:population":0,
    "gn:timezone":"Asia/Shanghai",
    "iso:country":"CN",
    "wof:name":"Dongdao",
    "wof:placetype":"locality"
},
  "geometry": {"coordinates":[118.64472000000001,40.94222],"type":"Point"}
}