{
  "type": "Feature",
  "properties": {
    "gn:admin1_code":"7.0",
    "gn:asciiname":"Zengfangcun",
    "gn:country_code":"CN",
    "gn:dem":274,
    "gn:feature_class":"P",
    "gn:feature_code":"PPL",
    "gn:name":"Zengfangcun",
    "gn:population":0,
    "gn:timezone":"Asia/Shanghai",
    "iso:country":"CN",
    "name:zho_x_preferred":[
        "\u589e\u574a\u6751"
    ],
    "wof:name":"Zengfangcun",
    "wof:placetype":"locality"
},
  "geometry": {"coordinates":[117.35630999999999,26.24262],"type":"Point"}
}