{
  "type": "Feature",
  "properties": {
    "gn:admin1_code":"2",
    "gn:asciiname":"Balu",
    "gn:country_code":"CN",
    "gn:dem":933,
    "gn:feature_class":"P",
    "gn:feature_code":"PPL",
    "gn:name":"Balu",
    "gn:population":0,
    "gn:timezone":"Asia/Shanghai",
    "iso:country":"CN",
    "name:ceb_x_preferred":[
        "Balu"
    ],
    "name:deu_x_preferred":[
        "Balu"
    ],
    "name:rus_x_preferred":[
        "\u0411\u0430\u043b\u0443"
    ],
    "name:swe_x_preferred":[
        "Balu"
    ],
    "name:zho_x_preferred":[
        "\u516b\u7089"
    ],
    "wof:name":"Balu",
    "wof:placetype":"locality"
},
  "geometry": {"coordinates":[119.27361000000001,27.51167],"type":"Point"}
}