{
  "type": "Feature",
  "properties": {
    "gn:admin1_code":"32.0",
    "gn:asciiname":"Yidageng",
    "gn:country_code":"CN",
    "gn:dem":751,
    "gn:feature_class":"P",
    "gn:feature_code":"PPL",
    "gn:name":"Yidageng",
    "gn:population":0,
    "gn:timezone":"Asia/Shanghai",
    "iso:country":"CN",
    "name:zho_x_preferred":[
        "\u6613\u5927\u57c2"
    ],
    "wof:name":"Yidageng",
    "wof:placetype":"locality"
},
  "geometry": {"coordinates":[103.41871,30.08777000000001],"type":"Point"}
}