{
  "type": "Feature",
  "properties": {
    "gn:admin1_code":"11.0",
    "gn:asciiname":"Zhangjiaguai",
    "gn:country_code":"CN",
    "gn:dem":34,
    "gn:feature_class":"P",
    "gn:feature_code":"PPL",
    "gn:name":"Zhangjiaguai",
    "gn:population":0,
    "gn:timezone":"Asia/Shanghai",
    "iso:country":"CN",
    "name:zho_x_preferred":[
        "Zhangjiaguai"
    ],
    "name:zho_x_variant":[
        "\u5f20\u5bb6\u62d0"
    ],
    "wof:name":"Zhangjiaguai",
    "wof:placetype":"locality"
},
  "geometry": {"coordinates":[112.06328999999999,29.66957],"type":"Point"}
}