{
  "type": "Feature",
  "properties": {
    "gn:admin1_code":"12.0",
    "gn:asciiname":"Shanlong Liujia",
    "gn:country_code":"CN",
    "gn:dem":59,
    "gn:feature_class":"P",
    "gn:feature_code":"PPL",
    "gn:name":"Shanlong Liujia",
    "gn:population":0,
    "gn:timezone":"Asia/Shanghai",
    "iso:country":"CN",
    "name:zho_x_preferred":[
        "\u5c71\u5784\u5218\u5bb6"
    ],
    "wof:name":"Shanlong Liujia",
    "wof:placetype":"locality"
},
  "geometry": {"coordinates":[113.69486999999999,29.66253],"type":"Point"}
}