{
  "type": "Feature",
  "properties": {
    "gn:admin1_code":"8.0",
    "gn:asciiname":"Aiquncun",
    "gn:country_code":"CN",
    "gn:dem":217,
    "gn:feature_class":"P",
    "gn:feature_code":"PPL",
    "gn:name":"Aiquncun",
    "gn:population":0,
    "gn:timezone":"Asia/Shanghai",
    "iso:country":"CN",
    "name:zho_x_preferred":[
        "\u7231\u7fa4\u6751"
    ],
    "wof:name":"Aiquncun",
    "wof:placetype":"locality"
},
  "geometry": {"coordinates":[125.66732,47.46832],"type":"Point"}
}