{
  "type": "Feature",
  "properties": {
    "gn:admin1_code":"30.0",
    "gn:asciiname":"Pengxiacun",
    "gn:country_code":"CN",
    "gn:dem":162,
    "gn:feature_class":"P",
    "gn:feature_code":"PPL",
    "gn:name":"Pengxiacun",
    "gn:population":0,
    "gn:timezone":"Asia/Shanghai",
    "iso:country":"CN",
    "name:zho_x_preferred":[
        "\u84ec\u4e0b\u6751"
    ],
    "wof:name":"Pengxiacun",
    "wof:placetype":"locality"
},
  "geometry": {"coordinates":[116.43105,24.46293],"type":"Point"}
}