{
  "type": "Feature",
  "properties": {
    "gn:admin1_code":"4.0",
    "gn:asciiname":"Dabei'an",
    "gn:country_code":"CN",
    "gn:dem":8,
    "gn:feature_class":"P",
    "gn:feature_code":"PPL",
    "gn:name":"Dabei\u2019an",
    "gn:population":0,
    "gn:timezone":"Asia/Shanghai",
    "iso:country":"CN",
    "name:und_x_variant":[
        "Dabei\u2019an"
    ],
    "name:zho_x_preferred":[
        "\u5927\u60b2\u5eb5"
    ],
    "wof:name":"Dabei'an",
    "wof:placetype":"locality"
},
  "geometry": {"coordinates":[120.14144,32.08839],"type":"Point"}
}