{
  "type": "Feature",
  "properties": {
    "gn:admin1_code":"25",
    "gn:asciiname":"Qianlinzi",
    "gn:country_code":"CN",
    "gn:dem":90,
    "gn:feature_class":"P",
    "gn:feature_code":"PPL",
    "gn:name":"Qianlinzi",
    "gn:population":0,
    "gn:timezone":"Asia/Shanghai",
    "iso:country":"CN",
    "name:zho_x_preferred":[
        "\u524d\u6797\u5b50"
    ],
    "wof:name":"Qianlinzi",
    "wof:placetype":"locality"
},
  "geometry": {"coordinates":[118.54600000000001,35.31],"type":"Point"}
}