{
  "type": "Feature",
  "properties": {
    "gn:admin1_code":"7.0",
    "gn:asciiname":"Hangxiacun",
    "gn:country_code":"CN",
    "gn:dem":300,
    "gn:feature_class":"P",
    "gn:feature_code":"PPL",
    "gn:name":"Hangxiacun",
    "gn:population":0,
    "gn:timezone":"Asia/Shanghai",
    "iso:country":"CN",
    "name:zho_x_preferred":[
        "\u676d\u4e0b\u6751"
    ],
    "wof:name":"Hangxiacun",
    "wof:placetype":"locality"
},
  "geometry": {"coordinates":[118.46302,27.42557],"type":"Point"}
}