{
  "type": "Feature",
  "properties": {
    "gn:admin1_code":"15",
    "gn:asciiname":"Gangouyi",
    "gn:country_code":"CN",
    "gn:dem":1634,
    "gn:feature_class":"P",
    "gn:feature_code":"PPLA4",
    "gn:name":"Gangouyi",
    "gn:population":0,
    "gn:timezone":"Asia/Shanghai",
    "iso:country":"CN",
    "name:und_x_variant":[
        "Kan-kou-i",
        "Gangouyi",
        "\u7518\u6c9f\u9a7f"
    ],
    "wof:name":"Gangouyi",
    "wof:placetype":"locality"
},
  "geometry": {"coordinates":[105.01878000000001,35.95632],"type":"Point"}
}