{
  "type": "Feature",
  "properties": {
    "gn:admin1_code":"11.0",
    "gn:asciiname":"Tanjia Laowu",
    "gn:country_code":"CN",
    "gn:dem":52,
    "gn:feature_class":"P",
    "gn:feature_code":"PPL",
    "gn:name":"Tanjia Laowu",
    "gn:population":0,
    "gn:timezone":"Asia/Shanghai",
    "iso:country":"CN",
    "name:zho_x_preferred":[
        "\u8c2d\u5bb6\u8001\u5c4b"
    ],
    "wof:name":"Tanjia Laowu",
    "wof:placetype":"locality"
},
  "geometry": {"coordinates":[112.81591,28.4777],"type":"Point"}
}