{
  "type": "Feature",
  "properties": {
    "gn:admin1_code":"30",
    "gn:asciiname":"Likeng",
    "gn:country_code":"CN",
    "gn:dem":235,
    "gn:feature_class":"P",
    "gn:feature_code":"PPL",
    "gn:name":"Likeng",
    "gn:population":0,
    "gn:timezone":"Asia/Shanghai",
    "iso:country":"CN",
    "name:und_x_variant":[
        "\u793c\u5751"
    ],
    "wof:name":"Likeng",
    "wof:placetype":"locality"
},
  "geometry": {"coordinates":[115.29325,23.42146],"type":"Point"}
}