{
  "type": "Feature",
  "properties": {
    "gn:admin1_code":"14.0",
    "gn:asciiname":"Kebo",
    "gn:country_code":"CN",
    "gn:dem":3919,
    "gn:feature_class":"P",
    "gn:feature_code":"PPLF",
    "gn:name":"Kebo",
    "gn:population":0,
    "gn:timezone":"Asia/Urumqi",
    "iso:country":"CN",
    "name:bod_x_preferred":[
        "K\u00eabo"
    ],
    "name:zho_x_preferred":[
        "Kebo"
    ],
    "name:zho_x_variant":[
        "\u514b\u6ce2"
    ],
    "wof:name":"Kebo",
    "wof:placetype":"locality"
},
  "geometry": {"coordinates":[98.801,30.301],"type":"Point"}
}