{
  "type": "Feature",
  "properties": {
    "gn:admin1_code":"32.0",
    "gn:asciiname":"Xinshiba",
    "gn:country_code":"CN",
    "gn:dem":647,
    "gn:feature_class":"P",
    "gn:feature_code":"PPL",
    "gn:name":"Xinshiba",
    "gn:population":0,
    "gn:timezone":"Asia/Shanghai",
    "iso:country":"CN",
    "name:zho_x_preferred":[
        "\u65b0\u77f3\u575d"
    ],
    "wof:name":"Xinshiba",
    "wof:placetype":"locality"
},
  "geometry": {"coordinates":[105.98098,28.76899],"type":"Point"}
}