{
  "type": "Feature",
  "properties": {
    "gn:admin1_code":"29",
    "gn:asciiname":"Qiezu",
    "gn:country_code":"CN",
    "gn:dem":1164,
    "gn:feature_class":"P",
    "gn:feature_code":"PPL",
    "gn:name":"Qiezu",
    "gn:population":0,
    "gn:timezone":"Asia/Shanghai",
    "iso:country":"CN",
    "name:zho_x_preferred":[
        "\u4e14\u79df"
    ],
    "wof:name":"Qiezu",
    "wof:placetype":"locality"
},
  "geometry": {"coordinates":[101.678,23.9891],"type":"Point"}
}