{
  "type": "Feature",
  "properties": {
    "gn:admin1_code":"29.0",
    "gn:asciiname":"Chashanzhai",
    "gn:country_code":"CN",
    "gn:dem":1185,
    "gn:feature_class":"P",
    "gn:feature_code":"PPL",
    "gn:name":"Chashanzhai",
    "gn:population":0,
    "gn:timezone":"Asia/Shanghai",
    "iso:country":"CN",
    "name:zho_x_preferred":[
        "\u8336\u5c71\u5be8"
    ],
    "wof:name":"Chashanzhai",
    "wof:placetype":"locality"
},
  "geometry": {"coordinates":[98.2572,24.3828],"type":"Point"}
}