{
  "type": "Feature",
  "properties": {
    "gn:admin1_code":"8.0",
    "gn:asciiname":"Huashuchuancun",
    "gn:country_code":"CN",
    "gn:dem":82,
    "gn:feature_class":"P",
    "gn:feature_code":"PPL",
    "gn:name":"Huashuchuancun",
    "gn:population":0,
    "gn:timezone":"Asia/Shanghai",
    "iso:country":"CN",
    "name:zho_x_preferred":[
        "\u6866\u6811\u5ddd\u6751"
    ],
    "wof:name":"Huashuchuancun",
    "wof:placetype":"locality"
},
  "geometry": {"coordinates":[130.73840000000001,46.91501],"type":"Point"}
}