{
  "type": "Feature",
  "properties": {
    "gn:admin1_code":"1.0",
    "gn:asciiname":"Laoyachong",
    "gn:country_code":"CN",
    "gn:dem":25,
    "gn:feature_class":"P",
    "gn:feature_code":"PPL",
    "gn:name":"Laoyachong",
    "gn:population":0,
    "gn:timezone":"Asia/Shanghai",
    "iso:country":"CN",
    "name:zho_x_preferred":[
        "\u8001\u7259\u51b2"
    ],
    "wof:name":"Laoyachong",
    "wof:placetype":"locality"
},
  "geometry": {"coordinates":[118.74611000000002,31.60289],"type":"Point"}
}