{
  "type": "Feature",
  "properties": {
    "gn:admin1_code":"5.0",
    "gn:asciiname":"Dongxintun",
    "gn:country_code":"CN",
    "gn:dem":157,
    "gn:feature_class":"P",
    "gn:feature_code":"PPL",
    "gn:name":"Dongxintun",
    "gn:population":0,
    "gn:timezone":"Asia/Shanghai",
    "iso:country":"CN",
    "name:zho_x_preferred":[
        "\u4e1c\u65b0\u5c6f"
    ],
    "wof:name":"Dongxintun",
    "wof:placetype":"locality"
},
  "geometry": {"coordinates":[122.52686,44.43754000000001],"type":"Point"}
}