{
  "type": "Feature",
  "properties": {
    "gn:admin1_code":"20",
    "gn:asciiname":"Yu-ch'uan-kao",
    "gn:country_code":"CN",
    "gn:dem":413,
    "gn:feature_class":"P",
    "gn:feature_code":"PPL",
    "gn:name":"Y\u00fc-ch\u2019\u00fcan-kao",
    "gn:population":0,
    "gn:timezone":"Asia/Shanghai",
    "iso:country":"CN",
    "wof:name":"Yu-ch'uan-kao",
    "wof:placetype":"locality"
},
  "geometry": {"coordinates":[119.82222,42.90806],"type":"Point"}
}