{
  "type": "Feature",
  "properties": {
    "gn:admin1_code":"11.0",
    "gn:asciiname":"Lizigou",
    "gn:country_code":"CN",
    "gn:dem":666,
    "gn:feature_class":"P",
    "gn:feature_code":"PPL",
    "gn:name":"Lizigou",
    "gn:population":0,
    "gn:timezone":"Asia/Shanghai",
    "iso:country":"CN",
    "name:zho_x_preferred":[
        "Lizigou"
    ],
    "name:zho_x_variant":[
        "\u6817\u5b50\u6c9f"
    ],
    "wof:name":"Lizigou",
    "wof:placetype":"locality"
},
  "geometry": {"coordinates":[110.99202,28.87364],"type":"Point"}
}