{
  "type": "Feature",
  "properties": {
    "gn:admin1_code":"25",
    "gn:asciiname":"Lihuma",
    "gn:country_code":"CN",
    "gn:dem":14,
    "gn:feature_class":"P",
    "gn:feature_code":"PPL",
    "gn:name":"Lihuma",
    "gn:population":0,
    "gn:timezone":"Asia/Shanghai",
    "iso:country":"CN",
    "name:zho_x_preferred":[
        "\u674e\u80e1\u9a6c"
    ],
    "wof:name":"Lihuma",
    "wof:placetype":"locality"
},
  "geometry": {"coordinates":[117.267,37.8178],"type":"Point"}
}