{
  "type": "Feature",
  "properties": {
    "gn:admin1_code":"24",
    "gn:asciiname":"Nanlongquan",
    "gn:country_code":"CN",
    "gn:dem":1332,
    "gn:feature_class":"P",
    "gn:feature_code":"PPL",
    "gn:name":"Nanlongquan",
    "gn:population":0,
    "gn:timezone":"Asia/Shanghai",
    "iso:country":"CN",
    "name:und_x_variant":[
        "Nan-lung-ch\u2019\u00fcan",
        "Nanlongquan"
    ],
    "name:zho_x_preferred":[
        "\u5357\u9f99\u6cc9"
    ],
    "wof:name":"Nanlongquan",
    "wof:placetype":"locality"
},
  "geometry": {"coordinates":[112.42012,38.2417],"type":"Point"}
}