{
  "type": "Feature",
  "properties": {
    "gn:admin1_code":"07",
    "gn:asciiname":"Yanke",
    "gn:country_code":"CN",
    "gn:dem":32,
    "gn:feature_class":"P",
    "gn:feature_code":"PPL",
    "gn:name":"Yanke",
    "gn:population":0,
    "gn:timezone":"Asia/Shanghai",
    "iso:country":"CN",
    "name:und_x_variant":[
        "Yanqiu",
        "Yanke"
    ],
    "name:zho_x_preferred":[
        "\u71d5\u7aa0"
    ],
    "wof:name":"Yanke",
    "wof:placetype":"locality"
},
  "geometry": {"coordinates":[120.33735,27.23574],"type":"Point"}
}