{
  "type": "Feature",
  "properties": {
    "gn:admin1_code":"26.0",
    "gn:asciiname":"Hejia Chacun",
    "gn:country_code":"CN",
    "gn:dem":1053,
    "gn:feature_class":"P",
    "gn:feature_code":"PPL",
    "gn:name":"Hejia Chacun",
    "gn:population":0,
    "gn:timezone":"Asia/Shanghai",
    "iso:country":"CN",
    "name:zho_x_preferred":[
        "\u8d3a\u5bb6\u5c94\u6751"
    ],
    "wof:name":"Hejia Chacun",
    "wof:placetype":"locality"
},
  "geometry": {"coordinates":[110.21599999999999,37.3255],"type":"Point"}
}