{
  "type": "Feature",
  "properties": {
    "gn:admin1_code":"29.0",
    "gn:asciiname":"Sijiaodi",
    "gn:country_code":"CN",
    "gn:dem":1860,
    "gn:feature_class":"P",
    "gn:feature_code":"PPL",
    "gn:name":"Sijiaodi",
    "gn:population":0,
    "gn:timezone":"Asia/Shanghai",
    "iso:country":"CN",
    "name:zho_x_preferred":[
        "\u5bfa\u811a\u5e95"
    ],
    "wof:name":"Sijiaodi",
    "wof:placetype":"locality"
},
  "geometry": {"coordinates":[99.7749,25.3311],"type":"Point"}
}