{
  "type": "Feature",
  "properties": {
    "gn:admin1_code":"12.0",
    "gn:asciiname":"Jinxiangping",
    "gn:country_code":"CN",
    "gn:dem":307,
    "gn:feature_class":"P",
    "gn:feature_code":"PPL",
    "gn:name":"Jinxiangping",
    "gn:population":0,
    "gn:timezone":"Asia/Shanghai",
    "iso:country":"CN",
    "name:zho_x_preferred":[
        "\u91d1\u9576\u576a"
    ],
    "wof:name":"Jinxiangping",
    "wof:placetype":"locality"
},
  "geometry": {"coordinates":[111.65982,31.3935],"type":"Point"}
}