{
  "type": "Feature",
  "properties": {
    "gn:admin1_code":"19.0",
    "gn:asciiname":"Renhecun",
    "gn:country_code":"CN",
    "gn:dem":167,
    "gn:feature_class":"P",
    "gn:feature_code":"PPL",
    "gn:name":"Renhecun",
    "gn:population":0,
    "gn:timezone":"Asia/Shanghai",
    "iso:country":"CN",
    "name:zho_x_preferred":[
        "\u4efb\u5408\u6751"
    ],
    "wof:name":"Renhecun",
    "wof:placetype":"locality"
},
  "geometry": {"coordinates":[120.348,40.661],"type":"Point"}
}