{
  "type": "Feature",
  "properties": {
    "gn:admin1_code":"18",
    "gn:asciiname":"Luchupo",
    "gn:country_code":"CN",
    "gn:dem":1659,
    "gn:feature_class":"P",
    "gn:feature_code":"PPL",
    "gn:name":"Luchupo",
    "gn:population":0,
    "gn:timezone":"Asia/Shanghai",
    "iso:country":"CN",
    "name:zho_x_preferred":[
        "\u9c81\u695a\u5761"
    ],
    "wof:name":"Luchupo",
    "wof:placetype":"locality"
},
  "geometry": {"coordinates":[104.69199999999999,25.3498],"type":"Point"}
}