{
  "type": "Feature",
  "properties": {
    "gn:admin1_code":"20.0",
    "gn:asciiname":"Xigouzhang",
    "gn:country_code":"CN",
    "gn:dem":1735,
    "gn:feature_class":"P",
    "gn:feature_code":"PPL",
    "gn:name":"Xigouzhang",
    "gn:population":0,
    "gn:timezone":"Asia/Shanghai",
    "iso:country":"CN",
    "name:und_x_variant":[
        "\u897f\u6c9f\u638c"
    ],
    "wof:name":"Xigouzhang",
    "wof:placetype":"locality"
},
  "geometry": {"coordinates":[113.77377,40.60897],"type":"Point"}
}