{
  "type": "Feature",
  "properties": {
    "gn:admin1_code":"18",
    "gn:asciiname":"Shizitian",
    "gn:country_code":"CN",
    "gn:dem":927,
    "gn:feature_class":"P",
    "gn:feature_code":"PPL",
    "gn:name":"Shizitian",
    "gn:population":0,
    "gn:timezone":"Asia/Shanghai",
    "iso:country":"CN",
    "name:zho_x_preferred":[
        "\u5341\u5b57\u7530"
    ],
    "wof:name":"Shizitian",
    "wof:placetype":"locality"
},
  "geometry": {"coordinates":[106.786,27.5102],"type":"Point"}
}