{
  "type": "Feature",
  "properties": {
    "gn:admin1_code":"29",
    "gn:asciiname":"Chisongping",
    "gn:country_code":"CN",
    "gn:dem":2190,
    "gn:feature_class":"P",
    "gn:feature_code":"PPL",
    "gn:name":"Chisongping",
    "gn:population":0,
    "gn:timezone":"Asia/Shanghai",
    "iso:country":"CN",
    "name:zho_x_preferred":[
        "\u8d64\u677e\u576a"
    ],
    "wof:name":"Chisongping",
    "wof:placetype":"locality"
},
  "geometry": {"coordinates":[102.619,24.919],"type":"Point"}
}