{
  "type": "Feature",
  "properties": {
    "gn:admin1_code":"12",
    "gn:asciiname":"Daliu",
    "gn:country_code":"CN",
    "gn:dem":781,
    "gn:feature_class":"P",
    "gn:feature_code":"PPLA4",
    "gn:name":"Daliu",
    "gn:population":0,
    "gn:timezone":"Asia/Shanghai",
    "iso:country":"CN",
    "name:und_x_variant":[
        "Daliu Xiang"
    ],
    "name:zho_x_preferred":[
        "\u5927\u67f3"
    ],
    "name:zho_x_variant":[
        "\u5927\u67f3\u4e61"
    ],
    "wof:name":"Daliu",
    "wof:placetype":"locality"
},
  "geometry": {"coordinates":[110.73643,33.01608],"type":"Point"}
}