{
  "type": "Feature",
  "properties": {
    "gn:admin1_code":"11",
    "gn:asciiname":"Menggongshan",
    "gn:country_code":"CN",
    "gn:dem":121,
    "gn:feature_class":"P",
    "gn:feature_code":"PPL",
    "gn:name":"Menggongshan",
    "gn:population":0,
    "gn:timezone":"Asia/Shanghai",
    "iso:country":"CN",
    "name:und_x_variant":[
        "Meng-kung-shan",
        "Menggongshan"
    ],
    "name:zho_x_preferred":[
        "\u5b5f\u516c\u5c71"
    ],
    "wof:name":"Menggongshan",
    "wof:placetype":"locality"
},
  "geometry": {"coordinates":[111.7475,26.41991],"type":"Point"}
}