{
  "type": "Feature",
  "properties": {
    "gn:admin1_code":"7.0",
    "gn:asciiname":"Laohuku",
    "gn:country_code":"CN",
    "gn:dem":587,
    "gn:feature_class":"P",
    "gn:feature_code":"PPL",
    "gn:name":"Laohuku",
    "gn:population":0,
    "gn:timezone":"Asia/Shanghai",
    "iso:country":"CN",
    "name:und_x_variant":[
        "\u8001\u864e\u7a9f"
    ],
    "name:zho_x_preferred":[
        "\u8001\u864e\u7a9f"
    ],
    "wof:name":"Laohuku",
    "wof:placetype":"locality"
},
  "geometry": {"coordinates":[116.56285,26.78707],"type":"Point"}
}