{
  "type": "Feature",
  "properties": {
    "gn:admin1_code":"8.0",
    "gn:asciiname":"Liaoyuancun",
    "gn:country_code":"CN",
    "gn:dem":54,
    "gn:feature_class":"P",
    "gn:feature_code":"PPL",
    "gn:name":"Liaoyuancun",
    "gn:population":0,
    "gn:timezone":"Asia/Shanghai",
    "iso:country":"CN",
    "name:zho_x_preferred":[
        "\u71ce\u539f\u6751"
    ],
    "wof:name":"Liaoyuancun",
    "wof:placetype":"locality"
},
  "geometry": {"coordinates":[132.58681000000001,47.57182],"type":"Point"}
}