{
  "type": "Feature",
  "properties": {
    "gn:admin1_code":"1.0",
    "gn:asciiname":"Sanxucun",
    "gn:country_code":"CN",
    "gn:dem":5,
    "gn:feature_class":"P",
    "gn:feature_code":"PPL",
    "gn:name":"Sanxucun",
    "gn:population":0,
    "gn:timezone":"Asia/Shanghai",
    "iso:country":"CN",
    "name:zho_x_preferred":[
        "\u4e09\u5729\u6751"
    ],
    "wof:name":"Sanxucun",
    "wof:placetype":"locality"
},
  "geometry": {"coordinates":[118.11476,31.38885],"type":"Point"}
}