{
  "type": "Feature",
  "properties": {
    "gn:admin1_code":"25",
    "gn:asciiname":"Suozhuang",
    "gn:country_code":"CN",
    "gn:dem":183,
    "gn:feature_class":"P",
    "gn:feature_code":"PPL",
    "gn:name":"Suozhuang",
    "gn:population":0,
    "gn:timezone":"Asia/Shanghai",
    "iso:country":"CN",
    "name:zho_x_preferred":[
        "\u68ad\u5e84"
    ],
    "wof:name":"Suozhuang",
    "wof:placetype":"locality"
},
  "geometry": {"coordinates":[118.57899999999999,36.3295],"type":"Point"}
}