{
  "type": "Feature",
  "properties": {
    "gn:admin1_code":"1.0",
    "gn:asciiname":"Shanggangcun",
    "gn:country_code":"CN",
    "gn:dem":42,
    "gn:feature_class":"P",
    "gn:feature_code":"PPL",
    "gn:name":"Shanggangcun",
    "gn:population":0,
    "gn:timezone":"Asia/Shanghai",
    "iso:country":"CN",
    "name:zho_x_preferred":[
        "\u4e0a\u5c97\u6751"
    ],
    "wof:name":"Shanggangcun",
    "wof:placetype":"locality"
},
  "geometry": {"coordinates":[117.93080999999999,32.72757],"type":"Point"}
}