{
  "type": "Feature",
  "properties": {
    "gn:admin1_code":"25",
    "gn:asciiname":"Guansihoucun",
    "gn:country_code":"CN",
    "gn:dem":169,
    "gn:feature_class":"P",
    "gn:feature_code":"PPL",
    "gn:name":"Guansihoucun",
    "gn:population":0,
    "gn:timezone":"Asia/Shanghai",
    "iso:country":"CN",
    "name:und_x_variant":[
        "Guanyangsi"
    ],
    "name:zho_x_preferred":[
        "\u5173\u53f8\u540e\u6751"
    ],
    "wof:name":"Guansihoucun",
    "wof:placetype":"locality"
},
  "geometry": {"coordinates":[117.67452,35.17947],"type":"Point"}
}