{
  "type": "Feature",
  "properties": {
    "gn:admin1_code":"4.0",
    "gn:asciiname":"Qianxiang",
    "gn:country_code":"CN",
    "gn:dem":7,
    "gn:feature_class":"P",
    "gn:feature_code":"PPL",
    "gn:name":"Qianxiang",
    "gn:population":0,
    "gn:timezone":"Asia/Shanghai",
    "iso:country":"CN",
    "name:und_x_variant":[
        "\u524d\u5df7"
    ],
    "name:zho_x_preferred":[
        "\u524d\u5df7"
    ],
    "wof:name":"Qianxiang",
    "wof:placetype":"locality"
},
  "geometry": {"coordinates":[120.53286,31.3798],"type":"Point"}
}