{
  "type": "Feature",
  "properties": {
    "gn:admin1_code":"12.0",
    "gn:asciiname":"Banzhuyuan",
    "gn:country_code":"CN",
    "gn:dem":608,
    "gn:feature_class":"P",
    "gn:feature_code":"PPL",
    "gn:name":"Banzhuyuan",
    "gn:population":0,
    "gn:timezone":"Asia/Shanghai",
    "iso:country":"CN",
    "name:zho_x_preferred":[
        "\u6591\u7af9\u56ed"
    ],
    "wof:name":"Banzhuyuan",
    "wof:placetype":"locality"
},
  "geometry": {"coordinates":[109.50964,30.02972],"type":"Point"}
}