{
  "type": "Feature",
  "properties": {
    "gn:admin1_code":"15.0",
    "gn:asciiname":"Xianmatai",
    "gn:country_code":"CN",
    "gn:dem":2469,
    "gn:feature_class":"P",
    "gn:feature_code":"PPL",
    "gn:name":"Xianmatai",
    "gn:population":0,
    "gn:timezone":"Asia/Shanghai",
    "iso:country":"CN",
    "name:zho_x_preferred":[
        "\u732e\u9a6c\u53f0"
    ],
    "wof:name":"Xianmatai",
    "wof:placetype":"locality"
},
  "geometry": {"coordinates":[105.18899999999999,36.5121],"type":"Point"}
}