{
  "type": "Feature",
  "properties": {
    "gn:admin1_code":"12.0",
    "gn:asciiname":"Xiaguhe",
    "gn:country_code":"CN",
    "gn:dem":28,
    "gn:feature_class":"P",
    "gn:feature_code":"PPL",
    "gn:name":"Xiaguhe",
    "gn:population":0,
    "gn:timezone":"Asia/Shanghai",
    "iso:country":"CN",
    "name:zho_x_preferred":[
        "\u4e0b\u53e4\u6cb3"
    ],
    "wof:name":"Xiaguhe",
    "wof:placetype":"locality"
},
  "geometry": {"coordinates":[113.73829000000001,30.05923],"type":"Point"}
}