{
  "type": "Feature",
  "properties": {
    "gn:admin1_code":"19.0",
    "gn:asciiname":"Yaowangmiao",
    "gn:country_code":"CN",
    "gn:dem":34,
    "gn:feature_class":"P",
    "gn:feature_code":"PPL",
    "gn:name":"Yaowangmiao",
    "gn:population":0,
    "gn:timezone":"Asia/Shanghai",
    "iso:country":"CN",
    "name:zho_x_preferred":[
        "\u836f\u738b\u5e99"
    ],
    "wof:name":"Yaowangmiao",
    "wof:placetype":"locality"
},
  "geometry": {"coordinates":[120.271,40.4337],"type":"Point"}
}