{
  "type": "Feature",
  "properties": {
    "gn:admin1_code":"19.0",
    "gn:asciiname":"Liangzhongchangcun",
    "gn:country_code":"CN",
    "gn:dem":122,
    "gn:feature_class":"P",
    "gn:feature_code":"PPL",
    "gn:name":"Liangzhongchangcun",
    "gn:population":0,
    "gn:timezone":"Asia/Shanghai",
    "iso:country":"CN",
    "name:zho_x_preferred":[
        "\u826f\u79cd\u573a\u6751"
    ],
    "wof:name":"Liangzhongchangcun",
    "wof:placetype":"locality"
},
  "geometry": {"coordinates":[122.99047,42.67513],"type":"Point"}
}