{
  "type": "Feature",
  "properties": {
    "gn:admin1_code":"9.0",
    "gn:asciiname":"Youhe",
    "gn:cc2":"CN",
    "gn:country_code":"CN",
    "gn:dem":88,
    "gn:feature_class":"P",
    "gn:feature_code":"PPL",
    "gn:name":"Youhe",
    "gn:population":0,
    "gn:timezone":"Asia/Shanghai",
    "iso:country":"CN",
    "name:und_x_variant":[
        "Yu-ho",
        "Youhe"
    ],
    "wof:name":"Youhe",
    "wof:placetype":"locality"
},
  "geometry": {"coordinates":[113.90000000000001,32.23639],"type":"Point"}
}