{
  "type": "Feature",
  "properties": {
    "gn:admin1_code":"4.0",
    "gn:asciiname":"Daxinzhuangcun",
    "gn:country_code":"CN",
    "gn:dem":24,
    "gn:feature_class":"P",
    "gn:feature_code":"PPL",
    "gn:name":"Daxinzhuangcun",
    "gn:population":0,
    "gn:timezone":"Asia/Shanghai",
    "iso:country":"CN",
    "name:zho_x_preferred":[
        "\u5927\u65b0\u5e84\u6751"
    ],
    "wof:name":"Daxinzhuangcun",
    "wof:placetype":"locality"
},
  "geometry": {"coordinates":[117.98248,34.28668],"type":"Point"}
}