{
  "type": "Feature",
  "properties": {
    "gn:admin1_code":"5.0",
    "gn:asciiname":"Changgangzi",
    "gn:country_code":"CN",
    "gn:dem":130,
    "gn:feature_class":"P",
    "gn:feature_code":"PPL",
    "gn:name":"Changgangzi",
    "gn:population":0,
    "gn:timezone":"Asia/Shanghai",
    "iso:country":"CN",
    "name:zho_x_preferred":[
        "\u957f\u5c97\u5b50"
    ],
    "wof:name":"Changgangzi",
    "wof:placetype":"locality"
},
  "geometry": {"coordinates":[123.81901000000001,45.86715],"type":"Point"}
}