{
  "type": "Feature",
  "properties": {
    "gn:admin1_code":"30.0",
    "gn:asciiname":"Shaotaokeng",
    "gn:country_code":"CN",
    "gn:dem":475,
    "gn:feature_class":"P",
    "gn:feature_code":"PPL",
    "gn:name":"Shaotaokeng",
    "gn:population":0,
    "gn:timezone":"Asia/Shanghai",
    "iso:country":"CN",
    "name:zho_x_preferred":[
        "\u70e7\u9676\u5751"
    ],
    "wof:name":"Shaotaokeng",
    "wof:placetype":"locality"
},
  "geometry": {"coordinates":[115.35706999999999,23.25565],"type":"Point"}
}