{
  "type": "Feature",
  "properties": {
    "gn:admin1_code":"8.0",
    "gn:asciiname":"Yangmu",
    "gn:country_code":"CN",
    "gn:dem":480,
    "gn:feature_class":"P",
    "gn:feature_code":"PPL",
    "gn:name":"Yangmu",
    "gn:population":0,
    "gn:timezone":"Asia/Shanghai",
    "iso:country":"CN",
    "name:und_x_variant":[
        "\u6768\u6728"
    ],
    "wof:name":"Yangmu",
    "wof:placetype":"locality"
},
  "geometry": {"coordinates":[130.5994,44.09667],"type":"Point"}
}