{
  "type": "Feature",
  "properties": {
    "gn:admin1_code":"23.0",
    "gn:asciiname":"Changzheng Nongchang Jiudui",
    "gn:country_code":"CN",
    "gn:dem":4,
    "gn:feature_class":"P",
    "gn:feature_code":"PPLF",
    "gn:name":"Changzheng Nongchang Jiudui",
    "gn:population":0,
    "gn:timezone":"Asia/Shanghai",
    "iso:country":"CN",
    "name:zho_x_preferred":[
        "Changzheng Nongchang Jiudui"
    ],
    "name:zho_x_variant":[
        "\u957f\u5f81\u519c\u573a\u4e5d\u961f"
    ],
    "wof:name":"Changzheng Nongchang Jiudui",
    "wof:placetype":"locality"
},
  "geometry": {"coordinates":[121.41387,31.75605],"type":"Point"}
}