{
  "type": "Feature",
  "properties": {
    "gn:admin1_code":"8.0",
    "gn:asciiname":"Daliujia",
    "gn:country_code":"CN",
    "gn:dem":209,
    "gn:feature_class":"P",
    "gn:feature_code":"PPL",
    "gn:name":"Daliujia",
    "gn:population":0,
    "gn:timezone":"Asia/Shanghai",
    "iso:country":"CN",
    "name:zho_x_preferred":[
        "\u5927\u516d\u5bb6"
    ],
    "wof:name":"Daliujia",
    "wof:placetype":"locality"
},
  "geometry": {"coordinates":[127.27128,44.70553],"type":"Point"}
}