{
  "type": "Feature",
  "properties": {
    "gn:admin1_code":"26.0",
    "gn:asciiname":"Jinhui",
    "gn:country_code":"CN",
    "gn:dem":702,
    "gn:feature_class":"P",
    "gn:feature_code":"PPLA4",
    "gn:name":"Jinhui",
    "gn:population":0,
    "gn:timezone":"Asia/Shanghai",
    "iso:country":"CN",
    "name:zho_x_preferred":[
        "\u91d1\u60e0"
    ],
    "wof:name":"Jinhui",
    "wof:placetype":"locality"
},
  "geometry": {"coordinates":[109.70008,34.43079],"type":"Point"}
}