{
  "type": "Feature",
  "properties": {
    "gn:admin1_code":"32.0",
    "gn:asciiname":"Guandongcun",
    "gn:country_code":"CN",
    "gn:dem":475,
    "gn:feature_class":"P",
    "gn:feature_code":"PPL",
    "gn:name":"Guandongcun",
    "gn:population":0,
    "gn:timezone":"Asia/Shanghai",
    "iso:country":"CN",
    "name:zho_x_preferred":[
        "\u89c2\u4e1c\u6751"
    ],
    "wof:name":"Guandongcun",
    "wof:placetype":"locality"
},
  "geometry": {"coordinates":[104.074,30.527],"type":"Point"}
}