{
  "type": "Feature",
  "properties": {
    "gn:admin1_code":"19.0",
    "gn:asciiname":"Xiaoheyan",
    "gn:country_code":"CN",
    "gn:dem":44,
    "gn:feature_class":"P",
    "gn:feature_code":"PPL",
    "gn:name":"Xiaoheyan",
    "gn:population":0,
    "gn:timezone":"Asia/Shanghai",
    "iso:country":"CN",
    "name:und_x_variant":[
        "\u5c0f\u6cb3\u6cbf"
    ],
    "name:zho_x_preferred":[
        "\u5c0f\u6cb3\u6cbf"
    ],
    "wof:name":"Xiaoheyan",
    "wof:placetype":"locality"
},
  "geometry": {"coordinates":[122.79196,39.83808],"type":"Point"}
}