{
  "type": "Feature",
  "properties": {
    "gn:admin1_code":"26.0",
    "gn:asciiname":"Caijiagou",
    "gn:country_code":"CN",
    "gn:dem":1295,
    "gn:feature_class":"P",
    "gn:feature_code":"PPL",
    "gn:name":"Caijiagou",
    "gn:population":0,
    "gn:timezone":"Asia/Shanghai",
    "iso:country":"CN",
    "name:und_x_variant":[
        "\u8521\u5bb6\u6c9f"
    ],
    "wof:name":"Caijiagou",
    "wof:placetype":"locality"
},
  "geometry": {"coordinates":[106.97538,33.73477],"type":"Point"}
}