{
  "type": "Feature",
  "properties": {
    "gn:admin1_code":"26.0",
    "gn:asciiname":"Yuejiaping",
    "gn:country_code":"CN",
    "gn:dem":1473,
    "gn:feature_class":"P",
    "gn:feature_code":"PPL",
    "gn:name":"Yuejiaping",
    "gn:population":0,
    "gn:timezone":"Asia/Shanghai",
    "iso:country":"CN",
    "name:zho_x_preferred":[
        "\u5cb3\u5bb6\u576a"
    ],
    "wof:name":"Yuejiaping",
    "wof:placetype":"locality"
},
  "geometry": {"coordinates":[110.03171,35.49002],"type":"Point"}
}