{
  "type": "Feature",
  "properties": {
    "gn:admin1_code":"14.0",
    "gn:asciiname":"Reyiwawa",
    "gn:country_code":"CN",
    "gn:dem":4140,
    "gn:feature_class":"P",
    "gn:feature_code":"PPL",
    "gn:name":"Reyiwawa",
    "gn:population":0,
    "gn:timezone":"Asia/Urumqi",
    "iso:country":"CN",
    "name:zho_x_preferred":[
        "\u70ed\u4ee5\u6d3c\u6d3c"
    ],
    "wof:name":"Reyiwawa",
    "wof:placetype":"locality"
},
  "geometry": {"coordinates":[97.44745,30.56174],"type":"Point"}
}