{
  "type": "Feature",
  "properties": {
    "gn:admin1_code":"32.0",
    "gn:asciiname":"Mazu",
    "gn:country_code":"CN",
    "gn:dem":2856,
    "gn:feature_class":"P",
    "gn:feature_code":"PPL",
    "gn:name":"Mazu",
    "gn:population":0,
    "gn:timezone":"Asia/Shanghai",
    "iso:country":"CN",
    "name:aze_x_preferred":[
        "Matszu"
    ],
    "name:cat_x_preferred":[
        "Mazu"
    ],
    "name:cdo_x_preferred":[
        "M\u0101-c\u016b"
    ],
    "name:ces_x_preferred":[
        "Ma-cu"
    ],
    "name:deu_x_preferred":[
        "Mazu"
    ],
    "name:ell_x_preferred":[
        "\u039c\u03ac\u03c4\u03c3\u03bf\u03c5"
    ],
    "name:epo_x_preferred":[
        "Mazu"
    ],
    "name:fin_x_preferred":[
        "Mazu"
    ],
    "name:fra_x_preferred":[
        "Mazu"
    ],
    "name:hak_x_preferred":[
        "M\u00e2-ch\u00fa"
    ],
    "name:hun_x_preferred":[
        "Ma-cu"
    ],
    "name:nld_x_preferred":[
        "Tianhou"
    ],
    "name:nor_x_preferred":[
        "Mazu"
    ],
    "name:pol_x_preferred":[
        "Mazu"
    ],
    "name:por_x_preferred":[
        "Mazu"
    ],
    "name:rus_x_preferred":[
        "\u041c\u0430\u0446\u0437\u0443"
    ],
    "name:spa_x_preferred":[
        "Matsu"
    ],
    "name:tha_x_preferred":[
        "\u0e21\u0e48\u0e32\u0e08\u0e49\u0e2d\u0e42\u0e1b\u0e4b"
    ],
    "name:tur_x_preferred":[
        "Matsu"
    ],
    "name:zho_x_preferred":[
        "\u9a6c\u7956"
    ],
    "wof:name":"Mazu",
    "wof:placetype":"locality"
},
  "geometry": {"coordinates":[103.37934,27.84664],"type":"Point"}
}