{
  "type": "Feature",
  "properties": {
    "gn:admin1_code":"32.0",
    "gn:asciiname":"Mazu",
    "gn:country_code":"CN",
    "gn:dem":2856,
    "gn:feature_class":"P",
    "gn:feature_code":"PPL",
    "gn:name":"Mazu",
    "gn:population":0,
    "gn:timezone":"Asia/Shanghai",
    "iso:country":"CN",
    "name:zho_x_preferred":[
        "\u9a6c\u7956"
    ],
    "wof:name":"Mazu",
    "wof:placetype":"locality"
},
  "geometry": {"coordinates":[103.37934,27.84664],"type":"Point"}
}