{
  "type": "Feature",
  "properties": {
    "gn:admin1_code":"29",
    "gn:asciiname":"Lelang",
    "gn:country_code":"CN",
    "gn:dem":1897,
    "gn:feature_class":"P",
    "gn:feature_code":"PPL",
    "gn:name":"Lelang",
    "gn:population":0,
    "gn:timezone":"Asia/Shanghai",
    "iso:country":"CN",
    "name:zho_x_preferred":[
        "\u4e50\u6717"
    ],
    "wof:name":"Lelang",
    "wof:placetype":"locality"
},
  "geometry": {"coordinates":[102.80200000000001,25.4919],"type":"Point"}
}