{
  "type": "Feature",
  "properties": {
    "gn:admin1_code":"30.0",
    "gn:asciiname":"Yirong",
    "gn:country_code":"CN",
    "gn:dem":43,
    "gn:feature_class":"P",
    "gn:feature_code":"PPLA4",
    "gn:name":"Yirong",
    "gn:population":0,
    "gn:timezone":"Asia/Shanghai",
    "iso:country":"CN",
    "name:und_x_variant":[
        "\u4e49\u5bb9",
        "Yirong Zhen",
        "\u4e49\u5bb9\u9547"
    ],
    "wof:name":"Yirong",
    "wof:placetype":"locality"
},
  "geometry": {"coordinates":[114.83103,23.5229],"type":"Point"}
}