{
  "type": "Feature",
  "properties": {
    "gn:admin1_code":"21.0",
    "gn:asciiname":"Tongjiquan",
    "gn:country_code":"CN",
    "gn:dem":1389,
    "gn:feature_class":"P",
    "gn:feature_code":"PPL",
    "gn:name":"Tongjiquan",
    "gn:population":0,
    "gn:timezone":"Asia/Shanghai",
    "iso:country":"CN",
    "name:zho_x_preferred":[
        "\u4f5f\u8bb0\u5708"
    ],
    "wof:name":"Tongjiquan",
    "wof:placetype":"locality"
},
  "geometry": {"coordinates":[107.34399999999999,37.7153],"type":"Point"}
}