{
  "type": "Feature",
  "properties": {
    "gn:admin1_code":"9.0",
    "gn:asciiname":"Yaogoukou",
    "gn:country_code":"CN",
    "gn:dem":764,
    "gn:feature_class":"P",
    "gn:feature_code":"PPL",
    "gn:name":"Yaogoukou",
    "gn:population":0,
    "gn:timezone":"Asia/Shanghai",
    "iso:country":"CN",
    "name:zho_x_preferred":[
        "\u7a91\u6c9f\u53e3"
    ],
    "wof:name":"Yaogoukou",
    "wof:placetype":"locality"
},
  "geometry": {"coordinates":[110.59813,34.03541],"type":"Point"}
}