{
  "type": "Feature",
  "properties": {
    "gn:admin1_code":"07",
    "gn:asciiname":"Tubao",
    "gn:cc2":"CN",
    "gn:country_code":"CN",
    "gn:dem":264,
    "gn:feature_class":"P",
    "gn:feature_code":"PPL",
    "gn:name":"Tubao",
    "gn:population":0,
    "gn:timezone":"Asia/Shanghai",
    "iso:country":"CN",
    "name:bcl_x_preferred":[
        "Tubao"
    ],
    "name:ceb_x_preferred":[
        "Tubao"
    ],
    "name:deu_x_preferred":[
        "Tubao"
    ],
    "name:fas_x_preferred":[
        "\u062a\u0648\u0628\u0648"
    ],
    "name:fra_x_preferred":[
        "Tubao"
    ],
    "name:ilo_x_preferred":[
        "Tubao"
    ],
    "name:ind_x_preferred":[
        "Tubao"
    ],
    "name:ita_x_preferred":[
        "Tubao"
    ],
    "name:nld_x_preferred":[
        "Tubao"
    ],
    "name:nor_x_preferred":[
        "Tubao"
    ],
    "name:pag_x_preferred":[
        "Tubao"
    ],
    "name:pam_x_preferred":[
        "Tubao"
    ],
    "name:spa_x_preferred":[
        "Tubao"
    ],
    "name:swe_x_preferred":[
        "Tubao"
    ],
    "name:szl_x_preferred":[
        "Tubao"
    ],
    "name:tgl_x_preferred":[
        "Tubao"
    ],
    "name:und_x_variant":[
        "T\u2019u-pao",
        "T\u2019u-pao-chieh"
    ],
    "name:urd_x_preferred":[
        "\u062a\u0648\u0628\u0648\u0627"
    ],
    "name:vie_x_preferred":[
        "Tubao"
    ],
    "name:war_x_preferred":[
        "Tubao"
    ],
    "wof:name":"Tubao",
    "wof:placetype":"locality"
},
  "geometry": {"coordinates":[118.15971999999999,26.43694],"type":"Point"}
}