{
  "type": "Feature",
  "properties": {
    "gn:admin1_code":"29.0",
    "gn:asciiname":"Wu'a",
    "gn:country_code":"CN",
    "gn:dem":1204,
    "gn:feature_class":"P",
    "gn:feature_code":"PPL",
    "gn:name":"Wu\u2019a",
    "gn:population":0,
    "gn:timezone":"Asia/Shanghai",
    "iso:country":"CN",
    "name:und_x_variant":[
        "Wu\u2019a"
    ],
    "name:zho_x_preferred":[
        "\u4e94\u963f"
    ],
    "wof:name":"Wu'a",
    "wof:placetype":"locality"
},
  "geometry": {"coordinates":[99.4657,22.6197],"type":"Point"}
}