{
  "type": "Feature",
  "properties": {
    "gn:admin1_code":"3.0",
    "gn:asciiname":"Taqianpai",
    "gn:country_code":"CN",
    "gn:dem":49,
    "gn:feature_class":"P",
    "gn:feature_code":"PPL",
    "gn:name":"Taqianpai",
    "gn:population":0,
    "gn:timezone":"Asia/Shanghai",
    "iso:country":"CN",
    "name:und_x_variant":[
        "\u5854\u524d\u6392"
    ],
    "wof:name":"Taqianpai",
    "wof:placetype":"locality"
},
  "geometry": {"coordinates":[114.98545,27.05226],"type":"Point"}
}