{
  "type": "Feature",
  "properties": {
    "gn:admin1_code":"7.0",
    "gn:asciiname":"Qianyuanqiao",
    "gn:country_code":"CN",
    "gn:dem":244,
    "gn:feature_class":"P",
    "gn:feature_code":"PPL",
    "gn:name":"Qianyuanqiao",
    "gn:population":0,
    "gn:timezone":"Asia/Shanghai",
    "iso:country":"CN",
    "name:zho_x_preferred":[
        "\u94b1\u56ed\u6865"
    ],
    "wof:name":"Qianyuanqiao",
    "wof:placetype":"locality"
},
  "geometry": {"coordinates":[118.76219,27.55341],"type":"Point"}
}