{
  "type": "Feature",
  "properties": {
    "gn:admin1_code":"25",
    "gn:asciiname":"Zhangyicun",
    "gn:country_code":"CN",
    "gn:dem":64,
    "gn:feature_class":"P",
    "gn:feature_code":"PPL",
    "gn:name":"Zhangyicun",
    "gn:population":0,
    "gn:timezone":"Asia/Shanghai",
    "iso:country":"CN",
    "name:zho_x_preferred":[
        "\u5f20\u4e00\u6751"
    ],
    "wof:name":"Zhangyicun",
    "wof:placetype":"locality"
},
  "geometry": {"coordinates":[118.09099999999999,36.768],"type":"Point"}
}