{
  "type": "Feature",
  "properties": {
    "gn:admin1_code":"3.0",
    "gn:asciiname":"Guangfangkou",
    "gn:country_code":"CN",
    "gn:dem":242,
    "gn:feature_class":"P",
    "gn:feature_code":"PPL",
    "gn:name":"Guangfangkou",
    "gn:population":0,
    "gn:timezone":"Asia/Shanghai",
    "iso:country":"CN",
    "name:und_x_variant":[
        "\u5e7f\u574a\u53e3"
    ],
    "wof:name":"Guangfangkou",
    "wof:placetype":"locality"
},
  "geometry": {"coordinates":[116.25888999999999,26.92585],"type":"Point"}
}