{
  "type": "Feature",
  "properties": {
    "iso:country":"CN",
    "qs:name":"\u4e5d\u6c5f\u5e02",
    "qs:name_adm0":"\u4e2d\u570b",
    "qs:name_adm1":"\u6c5f\u897f\u7701",
    "qs:photos":257,
    "qs:photos_1k":52,
    "qs:photos_9k":5,
    "qs:photos_9r":7,
    "qs:photos_all":1139,
    "qs:photos_sr":5,
    "qs:placetype":"LocalAdmin",
    "qs:pop_sr":"0",
    "wof:name":"\u4e5d\u6c5f\u5e02",
    "wof:placetype":"localadmin"
},
  "geometry": {"coordinates":[115.973052,29.602118],"type":"Point"}
}