{
  "type": "Feature",
  "properties": {
    "gn:admin1_code":"29.0",
    "gn:asciiname":"Bomiluo",
    "gn:country_code":"CN",
    "gn:dem":2817,
    "gn:feature_class":"P",
    "gn:feature_code":"PPL",
    "gn:name":"Bomiluo",
    "gn:population":0,
    "gn:timezone":"Asia/Shanghai",
    "iso:country":"CN",
    "name:zho_x_preferred":[
        "\u6ce2\u7c73\u843d"
    ],
    "wof:name":"Bomiluo",
    "wof:placetype":"locality"
},
  "geometry": {"coordinates":[99.6324,26.8038],"type":"Point"}
}