{
  "type": "Feature",
  "properties": {
    "gn:admin1_code":"25",
    "gn:asciiname":"Baishuyuan",
    "gn:country_code":"CN",
    "gn:dem":46,
    "gn:feature_class":"P",
    "gn:feature_code":"PPL",
    "gn:name":"Baishuyuan",
    "gn:population":0,
    "gn:timezone":"Asia/Shanghai",
    "iso:country":"CN",
    "name:zho_x_preferred":[
        "\u67cf\u6811\u56ed"
    ],
    "wof:name":"Baishuyuan",
    "wof:placetype":"locality"
},
  "geometry": {"coordinates":[116.32299999999999,34.7057],"type":"Point"}
}