{
  "type": "Feature",
  "properties": {
    "gn:admin1_code":"10",
    "gn:asciiname":"Yaogezhuang",
    "gn:country_code":"CN",
    "gn:dem":41,
    "gn:feature_class":"P",
    "gn:feature_code":"PPL",
    "gn:name":"Yaogezhuang",
    "gn:population":0,
    "gn:timezone":"Asia/Shanghai",
    "iso:country":"CN",
    "name:und_x_variant":[
        "Yao-ko-chuang",
        "Yaokezhuang",
        "Yaogezhuang"
    ],
    "name:zho_x_preferred":[
        "\u59da\u5404\u5e84"
    ],
    "wof:name":"Yaogezhuang",
    "wof:placetype":"locality"
},
  "geometry": {"coordinates":[117.73528,40.08694000000001],"type":"Point"}
}