{
  "type": "Feature",
  "properties": {
    "gn:admin1_code":"11.0",
    "gn:asciiname":"Wanzishan",
    "gn:country_code":"CN",
    "gn:dem":156,
    "gn:feature_class":"P",
    "gn:feature_code":"PPL",
    "gn:name":"Wanzishan",
    "gn:population":0,
    "gn:timezone":"Asia/Shanghai",
    "iso:country":"CN",
    "name:zho_x_preferred":[
        "\u4e38\u5b50\u5c71"
    ],
    "wof:name":"Wanzishan",
    "wof:placetype":"locality"
},
  "geometry": {"coordinates":[112.04478,27.73248],"type":"Point"}
}