{
  "type": "Feature",
  "properties": {
    "gn:admin1_code":"16.0",
    "gn:asciiname":"Guide",
    "gn:country_code":"CN",
    "gn:dem":47,
    "gn:feature_class":"P",
    "gn:feature_code":"PPL",
    "gn:name":"Guide",
    "gn:population":0,
    "gn:timezone":"Asia/Shanghai",
    "iso:country":"CN",
    "name:fas_x_preferred":[
        "\u0631\u0627\u0647\u0646\u0645\u0627"
    ],
    "name:fry_x_preferred":[
        "Gids"
    ],
    "name:kor_x_preferred":[
        "\uac00\uc774\ub4dc"
    ],
    "name:kor_x_variant":[
        "\uae38\uc7a1\uc774"
    ],
    "name:nld_x_preferred":[
        "Guide"
    ],
    "name:pol_x_preferred":[
        "Guide"
    ],
    "name:por_x_preferred":[
        "Guide"
    ],
    "name:rus_x_preferred":[
        "\u0413\u0443\u0439\u0434\u044d"
    ],
    "name:swe_x_preferred":[
        "Guide"
    ],
    "name:tur_x_preferred":[
        "Guide"
    ],
    "name:ukr_x_preferred":[
        "\u0413\u0443\u0439\u0434\u0435"
    ],
    "name:urd_x_preferred":[
        "\u06af\u0627\u0626\u06cc\u0688"
    ],
    "name:vie_x_preferred":[
        "Qu\u00fd \u0110\u1ee9c"
    ],
    "name:zho_cn_x_preferred":[
        "\u8d35\u5fb7"
    ],
    "name:zho_tw_x_preferred":[
        "\u8cb4\u5fb7"
    ],
    "name:zho_x_preferred":[
        "\u8d35\u5fb7"
    ],
    "wof:name":"Guide",
    "wof:placetype":"locality"
},
  "geometry": {"coordinates":[110.065,23.4435],"type":"Point"}
}