{
  "type": "Feature",
  "properties": {
    "gn:admin1_code":"16.0",
    "gn:asciiname":"Guide",
    "gn:country_code":"CN",
    "gn:dem":47,
    "gn:feature_class":"P",
    "gn:feature_code":"PPL",
    "gn:name":"Guide",
    "gn:population":0,
    "gn:timezone":"Asia/Shanghai",
    "iso:country":"CN",
    "name:fas_x_preferred":[
        "\u0631\u0627\u0647\u0646\u0645\u0627"
    ],
    "name:fry_x_preferred":[
        "Gids"
    ],
    "name:kor_x_preferred":[
        "\uae38\uc7a1\uc774"
    ],
    "name:zho_x_preferred":[
        "\u8d35\u5fb7"
    ],
    "wof:name":"Guide",
    "wof:placetype":"locality"
},
  "geometry": {"coordinates":[110.065,23.4435],"type":"Point"}
}