{
  "type": "Feature",
  "properties": {
    "gn:admin1_code":"7.0",
    "gn:asciiname":"Gaoqi",
    "gn:country_code":"CN",
    "gn:dem":6,
    "gn:feature_class":"P",
    "gn:feature_code":"PPL",
    "gn:name":"Gaoqi",
    "gn:population":0,
    "gn:timezone":"Asia/Shanghai",
    "iso:country":"CN",
    "name:zho_x_preferred":[
        "\u9ad8\u5c90"
    ],
    "wof:name":"Gaoqi",
    "wof:placetype":"locality"
},
  "geometry": {"coordinates":[119.21853,26.00852],"type":"Point"}
}