{
  "type": "Feature",
  "properties": {
    "gn:admin1_code":"14.0",
    "gn:asciiname":"Yangmo",
    "gn:country_code":"CN",
    "gn:dem":4682,
    "gn:feature_class":"P",
    "gn:feature_code":"PPL",
    "gn:name":"Yangmo",
    "gn:population":0,
    "gn:timezone":"Asia/Urumqi",
    "iso:country":"CN",
    "name:bod_x_preferred":[
        "Yangmo"
    ],
    "name:zho_x_preferred":[
        "\u592e\u83ab"
    ],
    "name:zho_x_variant":[
        "Kangri Gongshe",
        "\u5eb7\u65e5\u516c\u793e"
    ],
    "wof:name":"Yangmo",
    "wof:placetype":"locality"
},
  "geometry": {"coordinates":[90.501,32.001],"type":"Point"}
}