{
  "type": "Feature",
  "properties": {
    "gn:admin1_code":"20.0",
    "gn:asciiname":"Dongkunqian",
    "gn:country_code":"CN",
    "gn:dem":178,
    "gn:feature_class":"P",
    "gn:feature_code":"PPL",
    "gn:name":"Dongkunqian",
    "gn:population":0,
    "gn:timezone":"Asia/Shanghai",
    "iso:country":"CN",
    "name:zho_x_preferred":[
        "\u4e1c\u5764\u6d45"
    ],
    "wof:name":"Dongkunqian",
    "wof:placetype":"locality"
},
  "geometry": {"coordinates":[124.50211000000002,48.22814],"type":"Point"}
}