{
  "type": "Feature",
  "properties": {
    "gn:admin1_code":"12.0",
    "gn:asciiname":"Xibianwa",
    "gn:country_code":"CN",
    "gn:dem":116,
    "gn:feature_class":"P",
    "gn:feature_code":"PPL",
    "gn:name":"Xibianwa",
    "gn:population":0,
    "gn:timezone":"Asia/Shanghai",
    "iso:country":"CN",
    "name:zho_x_preferred":[
        "\u897f\u8fb9\u6d3c"
    ],
    "wof:name":"Xibianwa",
    "wof:placetype":"locality"
},
  "geometry": {"coordinates":[113.40325,31.51347],"type":"Point"}
}