{
  "type": "Feature",
  "properties": {
    "gn:admin1_code":"4.0",
    "gn:asciiname":"Zhen'ercun",
    "gn:country_code":"CN",
    "gn:dem":0,
    "gn:feature_class":"P",
    "gn:feature_code":"PPL",
    "gn:name":"Zhen\u2019ercun",
    "gn:population":0,
    "gn:timezone":"Asia/Shanghai",
    "iso:country":"CN",
    "name:und_x_variant":[
        "Zhen\u2019ercun"
    ],
    "name:zho_x_preferred":[
        "\u9547\u4e8c\u6751"
    ],
    "wof:name":"Zhen'ercun",
    "wof:placetype":"locality"
},
  "geometry": {"coordinates":[120.00409000000001,33.13812],"type":"Point"}
}