{
  "type": "Feature",
  "properties": {
    "gn:admin1_code":"26.0",
    "gn:asciiname":"Dazicun",
    "gn:country_code":"CN",
    "gn:dem":1096,
    "gn:feature_class":"P",
    "gn:feature_code":"PPL",
    "gn:name":"Dazicun",
    "gn:population":0,
    "gn:timezone":"Asia/Shanghai",
    "iso:country":"CN",
    "name:zho_x_preferred":[
        "\u5927\u5b50\u6751"
    ],
    "wof:name":"Dazicun",
    "wof:placetype":"locality"
},
  "geometry": {"coordinates":[110.27379999999999,36.16802],"type":"Point"}
}