{
  "type": "Feature",
  "properties": {
    "gn:admin1_code":"12.0",
    "gn:asciiname":"Taojiagang",
    "gn:country_code":"CN",
    "gn:dem":87,
    "gn:feature_class":"P",
    "gn:feature_code":"PPL",
    "gn:name":"Taojiagang",
    "gn:population":0,
    "gn:timezone":"Asia/Shanghai",
    "iso:country":"CN",
    "name:zho_x_preferred":[
        "\u6843\u5bb6\u5c97"
    ],
    "wof:name":"Taojiagang",
    "wof:placetype":"locality"
},
  "geometry": {"coordinates":[114.82071999999999,31.20934],"type":"Point"}
}