{
  "type": "Feature",
  "properties": {
    "gn:admin1_code":"14.0",
    "gn:asciiname":"Toyardo",
    "gn:country_code":"CN",
    "gn:dem":4261,
    "gn:feature_class":"P",
    "gn:feature_code":"PPL",
    "gn:name":"Toyardo",
    "gn:population":0,
    "gn:timezone":"Asia/Urumqi",
    "iso:country":"CN",
    "name:bod_x_preferred":[
        "Toyardo"
    ],
    "name:zho_x_preferred":[
        "Tuoyaduo"
    ],
    "name:zho_x_variant":[
        "\u6258\u5440\u591a"
    ],
    "wof:name":"Toyardo",
    "wof:placetype":"locality"
},
  "geometry": {"coordinates":[92.602,31.502],"type":"Point"}
}