{
  "type": "Feature",
  "properties": {
    "gn:admin1_code":"11.0",
    "gn:asciiname":"Yunpanta",
    "gn:country_code":"CN",
    "gn:dem":937,
    "gn:feature_class":"P",
    "gn:feature_code":"PPL",
    "gn:name":"Yunpanta",
    "gn:population":0,
    "gn:timezone":"Asia/Shanghai",
    "iso:country":"CN",
    "name:zho_x_preferred":[
        "\u4e91\u76d8\u584c"
    ],
    "wof:name":"Yunpanta",
    "wof:placetype":"locality"
},
  "geometry": {"coordinates":[110.66513,29.84562],"type":"Point"}
}