{
  "type": "Feature",
  "properties": {
    "gn:admin1_code":"18",
    "gn:asciiname":"Chegutun",
    "gn:country_code":"CN",
    "gn:dem":878,
    "gn:feature_class":"P",
    "gn:feature_code":"PPL",
    "gn:name":"Chegutun",
    "gn:population":0,
    "gn:timezone":"Asia/Shanghai",
    "iso:country":"CN",
    "name:zho_x_preferred":[
        "\u626f\u53e4\u5c6f"
    ],
    "wof:name":"Chegutun",
    "wof:placetype":"locality"
},
  "geometry": {"coordinates":[106.24299999999999,27.7524],"type":"Point"}
}