{
  "type": "Feature",
  "properties": {
    "gn:admin1_code":"3.0",
    "gn:asciiname":"Yaofan",
    "gn:country_code":"CN",
    "gn:dem":93,
    "gn:feature_class":"P",
    "gn:feature_code":"PPL",
    "gn:name":"Yaofan",
    "gn:population":0,
    "gn:timezone":"Asia/Shanghai",
    "iso:country":"CN",
    "name:zho_x_preferred":[
        "\u7476\u7548"
    ],
    "wof:name":"Yaofan",
    "wof:placetype":"locality"
},
  "geometry": {"coordinates":[117.55567000000001,28.78809],"type":"Point"}
}