{
  "type": "Feature",
  "properties": {
    "gn:country":"CN",
    "gn:fcode":"ADM3",
    "gn:pop":0,
    "iso:country":"CN",
    "name:unk_x_variant":[
        "Yung-hsin Hsien"
    ],
    "name:zho_x_preferred":[
        "\u6c38\u65b0\u53bf"
    ],
    "name:zho_x_variant":[
        "\u6c38\u65b0"
    ],
    "qs:name":"Yongxin Xian",
    "qs:photos_9r":0,
    "qs:photos_sr":0,
    "qs:pop_sr":"0",
    "wd:wordcount":73,
    "wof:name":"Yongxin Xian",
    "wof:placetype":"localadmin",
    "wof:population":0
},
  "geometry": {"coordinates":[114.14933000000001,26.96689],"type":"Point"}
}