{
  "type": "Feature",
  "properties": {
    "gn:country":"CN",
    "gn:fcode":"ADM3",
    "gn:population":0,
    "iso:country":"CN",
    "name:deu_x_preferred":[
        "Yongxin"
    ],
    "name:eng_x_preferred":[
        "Yongxin County"
    ],
    "name:fas_x_preferred":[
        "\u0634\u0647\u0631\u0633\u062a\u0627\u0646 \u06cc\u0648\u0646\u06af\u0634\u06cc\u0646"
    ],
    "name:fin_x_preferred":[
        "Yongxin"
    ],
    "name:gan_x_preferred":[
        "\u6c38\u65b0"
    ],
    "name:jpn_x_preferred":[
        "\u6c38\u65b0\u770c"
    ],
    "name:kor_x_preferred":[
        "\uc735\uc2e0\ud604"
    ],
    "name:nan_x_preferred":[
        "\u00c9ng-sin-ko\u0101n"
    ],
    "name:nld_x_preferred":[
        "Yongxin"
    ],
    "name:nob_x_preferred":[
        "Yongxin"
    ],
    "name:rus_x_preferred":[
        "\u042e\u043d\u0441\u0438\u043d\u044c"
    ],
    "name:swe_x_preferred":[
        "Yongxin"
    ],
    "name:und_x_variant":[
        "Yung-hsin Hsien"
    ],
    "name:urd_x_preferred":[
        "\u0648\u0646\u06af\u0634\u0646 \u06a9\u0627\u0624\u0646\u0679\u06cc"
    ],
    "name:vie_x_preferred":[
        "V\u0129nh T\u00e2n"
    ],
    "name:wuu_x_preferred":[
        "\u6c38\u65b0\u53bf"
    ],
    "name:yue_x_preferred":[
        "\u6c38\u65b0"
    ],
    "name:zho_x_preferred":[
        "\u6c38\u65b0\u53bf"
    ],
    "name:zho_x_variant":[
        "\u6c38\u65b0"
    ],
    "qs:name":"Yongxin Xian",
    "qs:photos_9r":0,
    "qs:photos_sr":0,
    "qs:pop_sr":"0",
    "wd:wordcount":73,
    "wof:name":"Yongxin Xian",
    "wof:placetype":"localadmin",
    "wof:population":0
},
  "geometry": {"coordinates":[114.14933000000001,26.96689],"type":"Point"}
}