{
  "type": "Feature",
  "properties": {
    "gn:admin1_code":"29",
    "gn:asciiname":"Xiaohe",
    "gn:country_code":"CN",
    "gn:dem":1962,
    "gn:feature_class":"P",
    "gn:feature_code":"PPL",
    "gn:name":"Xiaohe",
    "gn:population":0,
    "gn:timezone":"Asia/Shanghai",
    "iso:country":"CN",
    "wof:name":"Xiaohe",
    "wof:placetype":"locality"
},
  "geometry": {"coordinates":[102.83889000000001,25.19472],"type":"Point"}
}