{
  "type": "Feature",
  "properties": {
    "gn:admin1_code":"2.0",
    "gn:asciiname":"Xiaolingtou",
    "gn:country_code":"CN",
    "gn:dem":197,
    "gn:feature_class":"P",
    "gn:feature_code":"PPL",
    "gn:name":"Xiaolingtou",
    "gn:population":0,
    "gn:timezone":"Asia/Shanghai",
    "iso:country":"CN",
    "name:und_x_variant":[
        "\u5c0f\u5cad\u5934"
    ],
    "wof:name":"Xiaolingtou",
    "wof:placetype":"locality"
},
  "geometry": {"coordinates":[119.77437999999999,30.04886],"type":"Point"}
}