{
  "type": "Feature",
  "properties": {
    "gn:admin1_code":"3.0",
    "gn:asciiname":"Chenjia Dawu",
    "gn:country_code":"CN",
    "gn:dem":187,
    "gn:feature_class":"P",
    "gn:feature_code":"PPL",
    "gn:name":"Chenjia Dawu",
    "gn:population":0,
    "gn:timezone":"Asia/Shanghai",
    "iso:country":"CN",
    "name:und_x_variant":[
        "\u9648\u5bb6\u5927\u5c4b"
    ],
    "wof:name":"Chenjia Dawu",
    "wof:placetype":"locality"
},
  "geometry": {"coordinates":[115.40017,29.1453],"type":"Point"}
}