{
  "type": "Feature",
  "properties": {
    "gn:admin1_code":"32.0",
    "gn:asciiname":"Daqiaodi",
    "gn:country_code":"CN",
    "gn:dem":2271,
    "gn:feature_class":"P",
    "gn:feature_code":"PPL",
    "gn:name":"Daqiaodi",
    "gn:population":0,
    "gn:timezone":"Asia/Shanghai",
    "iso:country":"CN",
    "name:zho_x_preferred":[
        "\u5927\u835e\u5730"
    ],
    "wof:name":"Daqiaodi",
    "wof:placetype":"locality"
},
  "geometry": {"coordinates":[102.56417999999999,27.12244],"type":"Point"}
}