{
  "type": "Feature",
  "properties": {
    "gn:admin1_code":"33.0",
    "gn:asciiname":"Ping'an",
    "gn:country_code":"CN",
    "gn:dem":234,
    "gn:feature_class":"P",
    "gn:feature_code":"PPL",
    "gn:name":"Ping\u2019an",
    "gn:population":0,
    "gn:timezone":"Asia/Shanghai",
    "iso:country":"CN",
    "name:ceb_x_preferred":[
        "Ping'an"
    ],
    "name:deu_x_preferred":[
        "Ping\u2019an"
    ],
    "name:fra_x_preferred":[
        "Pingan"
    ],
    "name:nld_x_preferred":[
        "Ping An"
    ],
    "name:zho_x_preferred":[
        "\u5e73\u5b89"
    ],
    "wof:name":"Ping'an",
    "wof:placetype":"locality"
},
  "geometry": {"coordinates":[107.34362,29.59069],"type":"Point"}
}