{
  "type": "Feature",
  "properties": {
    "gn:admin1_code":"24.0",
    "gn:asciiname":"Yangshicun",
    "gn:country_code":"CN",
    "gn:dem":1086,
    "gn:feature_class":"P",
    "gn:feature_code":"PPL",
    "gn:name":"Yangshicun",
    "gn:population":0,
    "gn:timezone":"Asia/Shanghai",
    "iso:country":"CN",
    "name:zho_x_preferred":[
        "\u9633\u77f3\u6751"
    ],
    "wof:name":"Yangshicun",
    "wof:placetype":"locality"
},
  "geometry": {"coordinates":[111.25905,37.54554],"type":"Point"}
}