{
  "type": "Feature",
  "properties": {
    "gn:admin1_code":"12.0",
    "gn:asciiname":"Yaohuashu",
    "gn:country_code":"CN",
    "gn:dem":38,
    "gn:feature_class":"P",
    "gn:feature_code":"PPL",
    "gn:name":"Yaohuashu",
    "gn:population":0,
    "gn:timezone":"Asia/Shanghai",
    "iso:country":"CN",
    "name:zho_x_preferred":[
        "\u59da\u82b1\u6811"
    ],
    "wof:name":"Yaohuashu",
    "wof:placetype":"locality"
},
  "geometry": {"coordinates":[112.12927999999999,30.39054],"type":"Point"}
}