{
  "type": "Feature",
  "properties": {
    "gn:admin1_code":"26.0",
    "gn:asciiname":"Majiahecun",
    "gn:country_code":"CN",
    "gn:dem":990,
    "gn:feature_class":"P",
    "gn:feature_code":"PPL",
    "gn:name":"Majiahecun",
    "gn:population":0,
    "gn:timezone":"Asia/Shanghai",
    "iso:country":"CN",
    "name:zho_x_preferred":[
        "\u9a6c\u5bb6\u6cb3\u6751"
    ],
    "wof:name":"Majiahecun",
    "wof:placetype":"locality"
},
  "geometry": {"coordinates":[110.00144,37.06731],"type":"Point"}
}