{
  "type": "Feature",
  "properties": {
    "gn:admin1_code":"32.0",
    "gn:asciiname":"Wanping",
    "gn:country_code":"CN",
    "gn:dem":1680,
    "gn:feature_class":"P",
    "gn:feature_code":"PPL",
    "gn:name":"Wanping",
    "gn:population":0,
    "gn:timezone":"Asia/Shanghai",
    "iso:country":"CN",
    "name:zho_x_preferred":[
        "\u4e07\u576a"
    ],
    "wof:name":"Wanping",
    "wof:placetype":"locality"
},
  "geometry": {"coordinates":[102.73399999999999,29.2407],"type":"Point"}
}