{
  "type": "Feature",
  "properties": {
    "gn:admin1_code":"15.0",
    "gn:asciiname":"Louzhuang",
    "gn:country_code":"CN",
    "gn:dem":1632,
    "gn:feature_class":"P",
    "gn:feature_code":"PPL",
    "gn:name":"Louzhuang",
    "gn:population":0,
    "gn:timezone":"Asia/Shanghai",
    "iso:country":"CN",
    "name:zho_x_preferred":[
        "\u697c\u5e84"
    ],
    "wof:name":"Louzhuang",
    "wof:placetype":"locality"
},
  "geometry": {"coordinates":[102.67100000000001,37.8456],"type":"Point"}
}