{
  "type": "Feature",
  "properties": {
    "gn:admin1_code":"6.0",
    "gn:asciiname":"Sejiagai",
    "gn:country_code":"CN",
    "gn:dem":4470,
    "gn:feature_class":"P",
    "gn:feature_code":"PPL",
    "gn:name":"Sejiagai",
    "gn:population":0,
    "gn:timezone":"Asia/Urumqi",
    "iso:country":"CN",
    "name:zho_x_preferred":[
        "\u8272\u52a0\u6539"
    ],
    "wof:name":"Sejiagai",
    "wof:placetype":"locality"
},
  "geometry": {"coordinates":[95.67477,31.86958],"type":"Point"}
}