{
  "type": "Feature",
  "properties": {
    "gn:admin1_code":"2.0",
    "gn:asciiname":"Qianjiazhuang",
    "gn:country_code":"CN",
    "gn:dem":6,
    "gn:feature_class":"P",
    "gn:feature_code":"PPL",
    "gn:name":"Qianjiazhuang",
    "gn:population":0,
    "gn:timezone":"Asia/Shanghai",
    "iso:country":"CN",
    "name:und_x_variant":[
        "\u94b1\u5bb6\u5e84"
    ],
    "wof:name":"Qianjiazhuang",
    "wof:placetype":"locality"
},
  "geometry": {"coordinates":[120.49281000000001,30.71356],"type":"Point"}
}