{
  "type": "Feature",
  "properties": {
    "gn:admin1_code":"3.0",
    "gn:asciiname":"Maoshancun",
    "gn:country_code":"CN",
    "gn:dem":17,
    "gn:feature_class":"P",
    "gn:feature_code":"PPL",
    "gn:name":"Maoshancun",
    "gn:population":0,
    "gn:timezone":"Asia/Shanghai",
    "iso:country":"CN",
    "name:und_x_variant":[
        "\u8305\u5c71\u6751"
    ],
    "wof:name":"Maoshancun",
    "wof:placetype":"locality"
},
  "geometry": {"coordinates":[116.23747,28.74241],"type":"Point"}
}