{
  "type": "Feature",
  "properties": {
    "gn:admin1_code":"16.0",
    "gn:asciiname":"Yaoshao",
    "gn:country_code":"CN",
    "gn:dem":763,
    "gn:feature_class":"P",
    "gn:feature_code":"PPL",
    "gn:name":"Yaoshao",
    "gn:population":0,
    "gn:timezone":"Asia/Shanghai",
    "iso:country":"CN",
    "name:und_x_variant":[
        "Meshao",
        "Yaoshao"
    ],
    "name:zho_x_preferred":[
        "\u4e48\u54e8"
    ],
    "wof:name":"Yaoshao",
    "wof:placetype":"locality"
},
  "geometry": {"coordinates":[107.104,25.3941],"type":"Point"}
}