{
  "type": "Feature",
  "properties": {
    "gn:admin1_code":"07",
    "gn:asciiname":"Fengqi",
    "gn:country_code":"CN",
    "gn:dem":460,
    "gn:feature_class":"P",
    "gn:feature_code":"PPL",
    "gn:name":"Fengqi",
    "gn:population":0,
    "gn:timezone":"Asia/Shanghai",
    "iso:country":"CN",
    "name:zho_x_preferred":[
        "\u51e4\u5c90"
    ],
    "wof:name":"Fengqi",
    "wof:placetype":"locality"
},
  "geometry": {"coordinates":[120.04713,27.19259000000001],"type":"Point"}
}