{
  "type": "Feature",
  "properties": {
    "gn:admin1_code":"26.0",
    "gn:asciiname":"Longshitianhe",
    "gn:country_code":"CN",
    "gn:dem":900,
    "gn:feature_class":"P",
    "gn:feature_code":"PPL",
    "gn:name":"Longshitianhe",
    "gn:population":0,
    "gn:timezone":"Asia/Shanghai",
    "iso:country":"CN",
    "name:zho_x_preferred":[
        "\u9f99\u77f3\u5929\u6cb3"
    ],
    "wof:name":"Longshitianhe",
    "wof:placetype":"locality"
},
  "geometry": {"coordinates":[110.27108,36.90017],"type":"Point"}
}