{
  "type": "Feature",
  "properties": {
    "gn:admin1_code":"15.0",
    "gn:asciiname":"Midiwan",
    "gn:country_code":"CN",
    "gn:dem":2053,
    "gn:feature_class":"P",
    "gn:feature_code":"PPL",
    "gn:name":"Midiwan",
    "gn:population":0,
    "gn:timezone":"Asia/Shanghai",
    "iso:country":"CN",
    "name:zho_x_preferred":[
        "\u7cdc\u5730\u6e7e"
    ],
    "wof:name":"Midiwan",
    "wof:placetype":"locality"
},
  "geometry": {"coordinates":[104.321,35.9303],"type":"Point"}
}