{
  "type": "Feature",
  "properties": {
    "gn:admin1_code":"3",
    "gn:asciiname":"Xiaoshi",
    "gn:country_code":"CN",
    "gn:dem":208,
    "gn:feature_class":"P",
    "gn:feature_code":"PPL",
    "gn:name":"Xiaoshi",
    "gn:population":0,
    "gn:timezone":"Asia/Shanghai",
    "iso:country":"CN",
    "name:ceb_x_preferred":[
        "Xiaoshi"
    ],
    "name:swe_x_preferred":[
        "Xiaoshi"
    ],
    "name:zho_x_preferred":[
        "\u5c0f\u77f3"
    ],
    "wof:name":"Xiaoshi",
    "wof:placetype":"locality"
},
  "geometry": {"coordinates":[114.697,25.3758],"type":"Point"}
}