{
  "type": "Feature",
  "properties": {
    "gn:admin1_code":"14",
    "gn:asciiname":"Saigui",
    "gn:country_code":"CN",
    "gn:dem":3989,
    "gn:feature_class":"P",
    "gn:feature_code":"PPL",
    "gn:name":"Saigui",
    "gn:population":0,
    "gn:timezone":"Asia/Urumqi",
    "iso:country":"CN",
    "name:zho_x_preferred":[
        "\u8d5b\u8d35"
    ],
    "wof:name":"Saigui",
    "wof:placetype":"locality"
},
  "geometry": {"coordinates":[88.5634,29.1565],"type":"Point"}
}