{
  "type": "Feature",
  "properties": {
    "gn:admin1_code":"19.0",
    "gn:asciiname":"Huoshigangzi",
    "gn:country_code":"CN",
    "gn:dem":87,
    "gn:feature_class":"P",
    "gn:feature_code":"PPL",
    "gn:name":"Huoshigangzi",
    "gn:population":0,
    "gn:timezone":"Asia/Shanghai",
    "iso:country":"CN",
    "name:zho_x_preferred":[
        "\u706b\u77f3\u5c97\u5b50"
    ],
    "wof:name":"Huoshigangzi",
    "wof:placetype":"locality"
},
  "geometry": {"coordinates":[123.02,42.6106],"type":"Point"}
}