{
  "type": "Feature",
  "properties": {
    "gn:admin1_code":"32.0",
    "gn:asciiname":"Xiangbisi",
    "gn:country_code":"CN",
    "gn:dem":730,
    "gn:feature_class":"P",
    "gn:feature_code":"PPL",
    "gn:name":"Xiangbisi",
    "gn:population":0,
    "gn:timezone":"Asia/Shanghai",
    "iso:country":"CN",
    "name:zho_x_preferred":[
        "\u8c61\u9f3b\u5bfa"
    ],
    "wof:name":"Xiangbisi",
    "wof:placetype":"locality"
},
  "geometry": {"coordinates":[105.117,28.1988],"type":"Point"}
}