{
  "type": "Feature",
  "properties": {
    "gn:admin1_code":"30.0",
    "gn:asciiname":"Yangcunzai",
    "gn:country_code":"CN",
    "gn:dem":36,
    "gn:feature_class":"P",
    "gn:feature_code":"PPL",
    "gn:name":"Yangcunzai",
    "gn:population":0,
    "gn:timezone":"Asia/Shanghai",
    "iso:country":"CN",
    "name:zho_x_preferred":[
        "\u6768\u6751\u4ed4"
    ],
    "wof:name":"Yangcunzai",
    "wof:placetype":"locality"
},
  "geometry": {"coordinates":[114.56729,23.49889],"type":"Point"}
}