{
  "type": "Feature",
  "properties": {
    "gn:admin1_code":"14.0",
    "gn:asciiname":"Zizhongcun",
    "gn:country_code":"CN",
    "gn:dem":4158,
    "gn:feature_class":"P",
    "gn:feature_code":"PPL",
    "gn:name":"Zizhongcun",
    "gn:population":0,
    "gn:timezone":"Asia/Urumqi",
    "iso:country":"CN",
    "name:zho_x_preferred":[
        "\u5b5c\u4e2d\u6751"
    ],
    "wof:name":"Zizhongcun",
    "wof:placetype":"locality"
},
  "geometry": {"coordinates":[97.70868,30.79689],"type":"Point"}
}