{
  "type": "Feature",
  "properties": {
    "gn:admin1_code":"7.0",
    "gn:asciiname":"Antougang",
    "gn:country_code":"CN",
    "gn:dem":673,
    "gn:feature_class":"P",
    "gn:feature_code":"PPL",
    "gn:name":"Antougang",
    "gn:population":0,
    "gn:timezone":"Asia/Shanghai",
    "iso:country":"CN",
    "name:zho_x_preferred":[
        "\u5b89\u5934\u5188"
    ],
    "wof:name":"Antougang",
    "wof:placetype":"locality"
},
  "geometry": {"coordinates":[119.48755,26.61694],"type":"Point"}
}