{
  "type": "Feature",
  "properties": {
    "gn:admin1_code":"10",
    "gn:asciiname":"Laowangjia",
    "gn:country_code":"CN",
    "gn:dem":667,
    "gn:feature_class":"P",
    "gn:feature_code":"PPL",
    "gn:name":"Laowangjia",
    "gn:population":0,
    "gn:timezone":"Asia/Shanghai",
    "iso:country":"CN",
    "name:zho_x_preferred":[
        "\u8001\u738b\u5bb6"
    ],
    "wof:name":"Laowangjia",
    "wof:placetype":"locality"
},
  "geometry": {"coordinates":[118.83722,40.57488],"type":"Point"}
}