{
  "type": "Feature",
  "properties": {
    "gn:admin1_code":"32.0",
    "gn:asciiname":"Tianjiawan",
    "gn:country_code":"CN",
    "gn:dem":627,
    "gn:feature_class":"P",
    "gn:feature_code":"PPL",
    "gn:name":"Tianjiawan",
    "gn:population":0,
    "gn:timezone":"Asia/Shanghai",
    "iso:country":"CN",
    "name:zho_x_preferred":[
        "\u7530\u5bb6\u6e7e"
    ],
    "wof:name":"Tianjiawan",
    "wof:placetype":"locality"
},
  "geometry": {"coordinates":[104.99601,31.55898],"type":"Point"}
}