{
  "type": "Feature",
  "properties": {
    "gn:admin1_code":"05",
    "gn:asciiname":"Ch'ing-kou-tzu",
    "gn:country_code":"CN",
    "gn:dem":550,
    "gn:feature_class":"P",
    "gn:feature_code":"PPL",
    "gn:name":"Ch\u2019ing-kou-tzu",
    "gn:population":0,
    "gn:timezone":"Asia/Shanghai",
    "iso:country":"CN",
    "wof:name":"Ch'ing-kou-tzu",
    "wof:placetype":"locality"
},
  "geometry": {"coordinates":[126.17833,41.64444],"type":"Point"}
}