{
  "type": "Feature",
  "properties": {
    "gn:admin1_code":"29.0",
    "gn:asciiname":"Huibaoshang",
    "gn:country_code":"CN",
    "gn:dem":1560,
    "gn:feature_class":"P",
    "gn:feature_code":"PPL",
    "gn:name":"Huibaoshang",
    "gn:population":0,
    "gn:timezone":"Asia/Shanghai",
    "iso:country":"CN",
    "name:zho_x_preferred":[
        "\u7070\u5305\u4e0a"
    ],
    "wof:name":"Huibaoshang",
    "wof:placetype":"locality"
},
  "geometry": {"coordinates":[104.895,27.6647],"type":"Point"}
}