{
  "type": "Feature",
  "properties": {
    "gn:admin1_code":"32",
    "gn:asciiname":"Duanjia Shijiao",
    "gn:country_code":"CN",
    "gn:dem":1048,
    "gn:feature_class":"P",
    "gn:feature_code":"PPL",
    "gn:name":"Duanjia Shijiao",
    "gn:population":0,
    "gn:timezone":"Asia/Shanghai",
    "iso:country":"CN",
    "name:zho_x_preferred":[
        "\u6bb5\u5bb6\u77f3\u7126"
    ],
    "wof:name":"Duanjia Shijiao",
    "wof:placetype":"locality"
},
  "geometry": {"coordinates":[107.7893,32.04355],"type":"Point"}
}