{
  "type": "Feature",
  "properties": {
    "gn:admin1_code":"08",
    "gn:asciiname":"Xiaoheyan",
    "gn:country_code":"CN",
    "gn:dem":49,
    "gn:feature_class":"P",
    "gn:feature_code":"PPL",
    "gn:name":"Xiaoheyan",
    "gn:population":0,
    "gn:timezone":"Asia/Shanghai",
    "iso:country":"CN",
    "name:zho_x_preferred":[
        "\u5c0f\u6cb3\u6cbf"
    ],
    "wof:name":"Xiaoheyan",
    "wof:placetype":"locality"
},
  "geometry": {"coordinates":[134.37437,47.76517],"type":"Point"}
}