{
  "type": "Feature",
  "properties": {
    "gn:admin1_code":"21.0",
    "gn:asciiname":"Wujiahouwan",
    "gn:country_code":"CN",
    "gn:dem":2035,
    "gn:feature_class":"P",
    "gn:feature_code":"PPL",
    "gn:name":"Wujiahouwan",
    "gn:population":0,
    "gn:timezone":"Asia/Shanghai",
    "iso:country":"CN",
    "name:zho_x_preferred":[
        "\u5434\u5bb6\u540e\u6e7e"
    ],
    "wof:name":"Wujiahouwan",
    "wof:placetype":"locality"
},
  "geometry": {"coordinates":[105.9884,35.78431],"type":"Point"}
}