{
  "type": "Feature",
  "properties": {
    "gn:admin1_code":"29.0",
    "gn:asciiname":"Yangjiazhai",
    "gn:country_code":"CN",
    "gn:dem":1390,
    "gn:feature_class":"P",
    "gn:feature_code":"PPL",
    "gn:name":"Yangjiazhai",
    "gn:population":0,
    "gn:timezone":"Asia/Shanghai",
    "iso:country":"CN",
    "name:zho_x_preferred":[
        "\u6768\u5bb6\u5be8"
    ],
    "wof:name":"Yangjiazhai",
    "wof:placetype":"locality"
},
  "geometry": {"coordinates":[99.5063,24.7702],"type":"Point"}
}