{
  "type": "Feature",
  "properties": {
    "gn:admin1_code":"26.0",
    "gn:asciiname":"Shuangshancun",
    "gn:country_code":"CN",
    "gn:dem":1284,
    "gn:feature_class":"P",
    "gn:feature_code":"PPL",
    "gn:name":"Shuangshancun",
    "gn:population":0,
    "gn:timezone":"Asia/Shanghai",
    "iso:country":"CN",
    "name:zho_x_preferred":[
        "\u53cc\u5c71\u6751"
    ],
    "wof:name":"Shuangshancun",
    "wof:placetype":"locality"
},
  "geometry": {"coordinates":[110.01607,38.41403],"type":"Point"}
}