{
  "type": "Feature",
  "properties": {
    "gn:admin1_code":"11.0",
    "gn:asciiname":"Huayuzui",
    "gn:country_code":"CN",
    "gn:dem":107,
    "gn:feature_class":"P",
    "gn:feature_code":"PPL",
    "gn:name":"Huayuzui",
    "gn:population":0,
    "gn:timezone":"Asia/Shanghai",
    "iso:country":"CN",
    "name:zho_x_preferred":[
        "\u534e\u9c7c\u5634"
    ],
    "wof:name":"Huayuzui",
    "wof:placetype":"locality"
},
  "geometry": {"coordinates":[113.36973,27.18326],"type":"Point"}
}