{
  "type": "Feature",
  "properties": {
    "gn:admin1_code":"9.0",
    "gn:asciiname":"Toudaoyin",
    "gn:country_code":"CN",
    "gn:dem":1376,
    "gn:feature_class":"P",
    "gn:feature_code":"PPL",
    "gn:name":"Toudaoyin",
    "gn:population":0,
    "gn:timezone":"Asia/Shanghai",
    "iso:country":"CN",
    "name:zho_x_preferred":[
        "\u5934\u9053\u9634"
    ],
    "wof:name":"Toudaoyin",
    "wof:placetype":"locality"
},
  "geometry": {"coordinates":[111.82701000000002,34.28854],"type":"Point"}
}