{
  "type": "Feature",
  "properties": {
    "gn:admin1_code":"31.0",
    "gn:asciiname":"Shangguoshan",
    "gn:country_code":"CN",
    "gn:dem":15,
    "gn:feature_class":"P",
    "gn:feature_code":"PPL",
    "gn:name":"Shangguoshan",
    "gn:population":0,
    "gn:timezone":"Asia/Shanghai",
    "iso:country":"CN",
    "name:zho_x_preferred":[
        "\u4e0a\u679c\u5c71"
    ],
    "wof:name":"Shangguoshan",
    "wof:placetype":"locality"
},
  "geometry": {"coordinates":[110.40349000000001,18.83915],"type":"Point"}
}