{
  "type": "Feature",
  "properties": {
    "gn:admin1_code":"29.0",
    "gn:asciiname":"Chujiushan",
    "gn:country_code":"CN",
    "gn:dem":1954,
    "gn:feature_class":"P",
    "gn:feature_code":"PPL",
    "gn:name":"Chujiushan",
    "gn:population":0,
    "gn:timezone":"Asia/Shanghai",
    "iso:country":"CN",
    "name:zho_x_preferred":[
        "\u6775\u81fc\u5c71"
    ],
    "wof:name":"Chujiushan",
    "wof:placetype":"locality"
},
  "geometry": {"coordinates":[100.286,24.3446],"type":"Point"}
}