{
  "type": "Feature",
  "properties": {
    "gn:admin1_code":"02",
    "gn:asciiname":"Baofu",
    "gn:country_code":"CN",
    "gn:dem":150,
    "gn:feature_class":"P",
    "gn:feature_code":"PPL",
    "gn:name":"Baofu",
    "gn:population":0,
    "gn:timezone":"Asia/Shanghai",
    "iso:country":"CN",
    "name:und_x_variant":[
        "Pao-fu",
        "Baofu",
        "\u62a5\u798f",
        "Baofu Zhen",
        "\u62a5\u798f\u9547"
    ],
    "wof:name":"Baofu",
    "wof:placetype":"locality"
},
  "geometry": {"coordinates":[119.47539999999999,30.51338],"type":"Point"}
}