{
  "type": "Feature",
  "properties": {
    "gn:admin1_code":"3",
    "gn:asciiname":"Shangzhi",
    "gn:country_code":"CN",
    "gn:dem":272,
    "gn:feature_class":"P",
    "gn:feature_code":"PPL",
    "gn:name":"Shangzhi",
    "gn:population":0,
    "gn:timezone":"Asia/Shanghai",
    "iso:country":"CN",
    "name:ara_x_preferred":[
        "\u0634\u0627\u0646\u063a\u0632\u064a"
    ],
    "name:ceb_x_preferred":[
        "Shangzhi"
    ],
    "name:deu_x_preferred":[
        "Shangzhi"
    ],
    "name:eus_x_preferred":[
        "Shangzhi"
    ],
    "name:fra_x_preferred":[
        "Shangzhi"
    ],
    "name:glg_x_preferred":[
        "Shangzhi"
    ],
    "name:hin_x_preferred":[
        "\u0936\u093e\u0902\u0917\u091d\u0940"
    ],
    "name:ita_x_preferred":[
        "Shangzhi"
    ],
    "name:jpn_x_preferred":[
        "\u5c1a\u5fd7\u5e02"
    ],
    "name:kik_x_preferred":[
        "Shangzhi"
    ],
    "name:kor_x_preferred":[
        "\uc0c1\uc988\uc2dc"
    ],
    "name:mlg_x_preferred":[
        "Shangzhi"
    ],
    "name:nor_x_preferred":[
        "Shangzhi"
    ],
    "name:pam_x_preferred":[
        "Shangzhi"
    ],
    "name:rus_x_preferred":[
        "\u0428\u0430\u043d\u0447\u0436\u0438"
    ],
    "name:spa_x_preferred":[
        "Shangzhi"
    ],
    "name:swe_x_preferred":[
        "Shangzhi"
    ],
    "name:tgl_x_preferred":[
        "Shangzhi"
    ],
    "name:urd_x_preferred":[
        "\u0634\u0627\u0646\u06af\u0698\u06cc"
    ],
    "name:vie_x_preferred":[
        "Th\u01b0\u1ee3ng Ch\u00ed"
    ],
    "name:war_x_preferred":[
        "Shangzhi"
    ],
    "name:zho_x_preferred":[
        "\u4e0a\u5cd9"
    ],
    "name:zho_x_variant":[
        "\u5c1a\u5fd7\u5e02"
    ],
    "wof:name":"Shangzhi",
    "wof:placetype":"locality"
},
  "geometry": {"coordinates":[114.11201,25.78436],"type":"Point"}
}