{
  "type": "Feature",
  "properties": {
    "gn:admin1_code":"26.0",
    "gn:asciiname":"Xiangshuping",
    "gn:country_code":"CN",
    "gn:dem":1052,
    "gn:feature_class":"P",
    "gn:feature_code":"PPL",
    "gn:name":"Xiangshuping",
    "gn:population":0,
    "gn:timezone":"Asia/Shanghai",
    "iso:country":"CN",
    "name:zho_x_preferred":[
        "\u9999\u6811\u576a"
    ],
    "wof:name":"Xiangshuping",
    "wof:placetype":"locality"
},
  "geometry": {"coordinates":[107.9919,32.69730999999999],"type":"Point"}
}