{
  "type": "Feature",
  "properties": {
    "gn:admin1_code":"32.0",
    "gn:asciiname":"Mule",
    "gn:country_code":"CN",
    "gn:dem":3164,
    "gn:feature_class":"P",
    "gn:feature_code":"PPL",
    "gn:name":"Mule",
    "gn:population":0,
    "gn:timezone":"Asia/Shanghai",
    "iso:country":"CN",
    "name:zho_x_preferred":[
        "\u6728\u52d2"
    ],
    "wof:name":"Mule",
    "wof:placetype":"locality"
},
  "geometry": {"coordinates":[102.08592,31.88402],"type":"Point"}
}