{
  "type": "Feature",
  "properties": {
    "gn:admin1_code":"8.0",
    "gn:asciiname":"Yingkou",
    "gn:country_code":"CN",
    "gn:dem":143,
    "gn:feature_class":"P",
    "gn:feature_code":"PPL",
    "gn:name":"Yingkou",
    "gn:population":0,
    "gn:timezone":"Asia/Shanghai",
    "iso:country":"CN",
    "name:afr_x_preferred":[
        "Yingkou"
    ],
    "name:ara_x_preferred":[
        "\u064a\u0646\u063a\u0643\u0648"
    ],
    "name:bul_x_preferred":[
        "\u0418\u043d\u043a\u043e\u0443"
    ],
    "name:cat_x_preferred":[
        "Yingkou"
    ],
    "name:cdo_x_preferred":[
        "\u00ccng-k\u0101u"
    ],
    "name:ceb_x_preferred":[
        "Yingkou"
    ],
    "name:ces_x_preferred":[
        "Jing-kchou"
    ],
    "name:dan_x_preferred":[
        "Yingkou"
    ],
    "name:deu_x_preferred":[
        "Yingkou"
    ],
    "name:epo_x_preferred":[
        "Inkou"
    ],
    "name:eus_x_preferred":[
        "Yingkou"
    ],
    "name:fas_x_preferred":[
        "\u06cc\u06cc\u0646\u06af\u06a9\u0648"
    ],
    "name:fin_x_preferred":[
        "Yingkou"
    ],
    "name:fra_x_preferred":[
        "Yingkou"
    ],
    "name:glg_x_preferred":[
        "Yingkou"
    ],
    "name:ind_x_preferred":[
        "Yingkou"
    ],
    "name:ita_x_preferred":[
        "Yingkou"
    ],
    "name:jpn_x_preferred":[
        "\u55b6\u53e3\u5e02"
    ],
    "name:kik_x_preferred":[
        "Yingkou"
    ],
    "name:kor_x_preferred":[
        "\uc789\ucee4\uc6b0\uc2dc"
    ],
    "name:mlg_x_preferred":[
        "Yingkou"
    ],
    "name:mya_x_preferred":[
        "\u101a\u1004\u103a\u1038\u1001\u102d\u102f\u1019\u103c\u102d\u102f\u1037"
    ],
    "name:nld_x_preferred":[
        "Yingkou"
    ],
    "name:nno_x_preferred":[
        "Yingkou"
    ],
    "name:nor_x_preferred":[
        "Yingkou"
    ],
    "name:oci_x_preferred":[
        "Yingkou"
    ],
    "name:pol_x_preferred":[
        "Yingkou"
    ],
    "name:rus_x_preferred":[
        "\u0418\u043d\u043a\u043e\u0443"
    ],
    "name:spa_x_preferred":[
        "Yingk\u00f3u"
    ],
    "name:srp_x_preferred":[
        "\u0408\u0438\u043d\u0433\u043a\u043e\u0443"
    ],
    "name:swe_x_preferred":[
        "Yingkou"
    ],
    "name:tur_x_preferred":[
        "Yingkou"
    ],
    "name:uig_x_preferred":[
        "\u064a\u0649\u06ad\u0643\u06c7 \u0634\u06d5\u06be\u0649\u0631\u0649"
    ],
    "name:ukr_x_preferred":[
        "\u0407\u043d\u043a\u043e\u0443"
    ],
    "name:urd_x_preferred":[
        "\u06cc\u0646\u06af\u06a9\u0648"
    ],
    "name:vie_x_preferred":[
        "Dinh Kh\u1ea9u"
    ],
    "name:war_x_preferred":[
        "Yingkou"
    ],
    "name:wuu_x_preferred":[
        "\u8425\u53e3\u5e02"
    ],
    "name:zho_x_preferred":[
        "\u8425\u53e3"
    ],
    "name:zho_x_variant":[
        "\u8425\u53e3\u5e02"
    ],
    "wof:name":"Yingkou",
    "wof:placetype":"locality"
},
  "geometry": {"coordinates":[127.81416000000002,45.79254],"type":"Point"}
}