{
  "type": "Feature",
  "properties": {
    "gn:admin1_code":"8.0",
    "gn:asciiname":"Yingkou",
    "gn:country_code":"CN",
    "gn:dem":143,
    "gn:feature_class":"P",
    "gn:feature_code":"PPL",
    "gn:name":"Yingkou",
    "gn:population":0,
    "gn:timezone":"Asia/Shanghai",
    "iso:country":"CN",
    "name:zho_x_preferred":[
        "\u8425\u53e3"
    ],
    "wof:name":"Yingkou",
    "wof:placetype":"locality"
},
  "geometry": {"coordinates":[127.81416000000002,45.79254],"type":"Point"}
}