{
  "type": "Feature",
  "properties": {
    "gn:admin1_code":"1.0",
    "gn:asciiname":"Wamiaocun",
    "gn:country_code":"CN",
    "gn:dem":88,
    "gn:feature_class":"P",
    "gn:feature_code":"PPL",
    "gn:name":"Wamiaocun",
    "gn:population":0,
    "gn:timezone":"Asia/Shanghai",
    "iso:country":"CN",
    "name:zho_x_preferred":[
        "\u74e6\u5e99\u6751"
    ],
    "wof:name":"Wamiaocun",
    "wof:placetype":"locality"
},
  "geometry": {"coordinates":[118.04949000000001,32.41519],"type":"Point"}
}