{
  "type": "Feature",
  "properties": {
    "gn:admin1_code":"26",
    "gn:asciiname":"Ma'e",
    "gn:country_code":"CN",
    "gn:dem":651,
    "gn:feature_class":"P",
    "gn:feature_code":"PPLA4",
    "gn:name":"Ma\u2019e",
    "gn:population":0,
    "gn:timezone":"Asia/Shanghai",
    "iso:country":"CN",
    "name:und_x_variant":[
        "Ma-o-chen",
        "Ma-o",
        "Ma\u2019e"
    ],
    "name:zho_x_preferred":[
        "\u9a6c\u989d"
    ],
    "name:zho_x_variant":[
        "Ma\u2019e Zhen",
        "\u9a6c\u989d\u9547"
    ],
    "wof:name":"Ma'e",
    "wof:placetype":"locality"
},
  "geometry": {"coordinates":[108.93028,34.82444],"type":"Point"}
}