{
  "type": "Feature",
  "properties": {
    "gn:admin1_code":"24.0",
    "gn:asciiname":"Shanshuicun",
    "gn:country_code":"CN",
    "gn:dem":1501,
    "gn:feature_class":"P",
    "gn:feature_code":"PPL",
    "gn:name":"Shanshuicun",
    "gn:population":0,
    "gn:timezone":"Asia/Shanghai",
    "iso:country":"CN",
    "name:zho_x_preferred":[
        "\u5c71\u6c34\u6751"
    ],
    "wof:name":"Shanshuicun",
    "wof:placetype":"locality"
},
  "geometry": {"coordinates":[110.91622,35.87565],"type":"Point"}
}