{
  "type": "Feature",
  "properties": {
    "gn:admin1_code":"30",
    "gn:asciiname":"Fenmian",
    "gn:country_code":"CN",
    "gn:dem":42,
    "gn:feature_class":"P",
    "gn:feature_code":"PPL",
    "gn:name":"Fenmian",
    "gn:population":0,
    "gn:timezone":"Asia/Shanghai",
    "iso:country":"CN",
    "name:zho_x_preferred":[
        "\u575f\u9762"
    ],
    "wof:name":"Fenmian",
    "wof:placetype":"locality"
},
  "geometry": {"coordinates":[111.63052999999999,21.64745],"type":"Point"}
}