{
  "type": "Feature",
  "properties": {
    "gn:admin1_code":"18.0",
    "gn:asciiname":"Luoli",
    "gn:country_code":"CN",
    "gn:dem":540,
    "gn:feature_class":"P",
    "gn:feature_code":"PPL",
    "gn:name":"Luoli",
    "gn:population":0,
    "gn:timezone":"Asia/Shanghai",
    "iso:country":"CN",
    "name:zho_x_preferred":[
        "\u88f8\u91cc"
    ],
    "wof:name":"Luoli",
    "wof:placetype":"locality"
},
  "geometry": {"coordinates":[109.011,25.6204],"type":"Point"}
}