{
  "type": "Feature",
  "properties": {
    "gn:admin1_code":"12.0",
    "gn:asciiname":"Yujiahe",
    "gn:country_code":"CN",
    "gn:dem":75,
    "gn:feature_class":"P",
    "gn:feature_code":"PPL",
    "gn:name":"Yujiahe",
    "gn:population":0,
    "gn:timezone":"Asia/Shanghai",
    "iso:country":"CN",
    "name:zho_x_preferred":[
        "\u4f59\u5bb6\u6cb3"
    ],
    "wof:name":"Yujiahe",
    "wof:placetype":"locality"
},
  "geometry": {"coordinates":[113.93944999999999,31.55581],"type":"Point"}
}