{
  "type": "Feature",
  "properties": {
    "gn:admin1_code":"29.0",
    "gn:asciiname":"Dalishi",
    "gn:country_code":"CN",
    "gn:dem":1507,
    "gn:feature_class":"P",
    "gn:feature_code":"PPL",
    "gn:name":"Dalishi",
    "gn:population":0,
    "gn:timezone":"Asia/Shanghai",
    "iso:country":"CN",
    "name:zho_x_preferred":[
        "\u5927\u91cc\u77f3"
    ],
    "wof:name":"Dalishi",
    "wof:placetype":"locality"
},
  "geometry": {"coordinates":[99.75449999999999,22.3913],"type":"Point"}
}