{
  "type": "Feature",
  "properties": {
    "gn:admin1_code":"26.0",
    "gn:asciiname":"Qianshuta",
    "gn:country_code":"CN",
    "gn:dem":1313,
    "gn:feature_class":"P",
    "gn:feature_code":"PPL",
    "gn:name":"Qianshuta",
    "gn:population":0,
    "gn:timezone":"Asia/Shanghai",
    "iso:country":"CN",
    "name:zho_x_preferred":[
        "\u5343\u6811\u5854"
    ],
    "wof:name":"Qianshuta",
    "wof:placetype":"locality"
},
  "geometry": {"coordinates":[110.03952,38.48196],"type":"Point"}
}