{
  "type": "Feature",
  "properties": {
    "gn:admin1_code":"32.0",
    "gn:asciiname":"Daijiazui",
    "gn:country_code":"CN",
    "gn:dem":344,
    "gn:feature_class":"P",
    "gn:feature_code":"PPL",
    "gn:name":"Daijiazui",
    "gn:population":0,
    "gn:timezone":"Asia/Shanghai",
    "iso:country":"CN",
    "name:zho_x_preferred":[
        "\u6234\u5bb6\u5480"
    ],
    "wof:name":"Daijiazui",
    "wof:placetype":"locality"
},
  "geometry": {"coordinates":[104.87701,28.56272],"type":"Point"}
}