{
  "type": "Feature",
  "properties": {
    "gn:admin1_code":"4.0",
    "gn:asciiname":"Guandong",
    "gn:country_code":"CN",
    "gn:dem":10,
    "gn:feature_class":"P",
    "gn:feature_code":"PPL",
    "gn:name":"Guandong",
    "gn:population":0,
    "gn:timezone":"Asia/Shanghai",
    "iso:country":"CN",
    "name:deu_x_preferred":[
        "Guandong"
    ],
    "name:zho_x_preferred":[
        "\u5b98\u4e1c"
    ],
    "wof:name":"Guandong",
    "wof:placetype":"locality"
},
  "geometry": {"coordinates":[120.10227999999999,32.17424],"type":"Point"}
}