{
  "type": "Feature",
  "properties": {
    "gn:admin1_code":"1.0",
    "gn:asciiname":"Wanhe Nongchang",
    "gn:country_code":"CN",
    "gn:dem":19,
    "gn:feature_class":"P",
    "gn:feature_code":"PPLF",
    "gn:name":"Wanhe Nongchang",
    "gn:population":0,
    "gn:timezone":"Asia/Shanghai",
    "iso:country":"CN",
    "wof:name":"Wanhe Nongchang",
    "wof:placetype":"locality"
},
  "geometry": {"coordinates":[116.86388999999998,30.41944],"type":"Point"}
}