{
  "type": "Feature",
  "properties": {
    "gn:admin1_code":"11.0",
    "gn:asciiname":"Jiucaitang",
    "gn:country_code":"CN",
    "gn:dem":1182,
    "gn:feature_class":"P",
    "gn:feature_code":"PPL",
    "gn:name":"Jiucaitang",
    "gn:population":0,
    "gn:timezone":"Asia/Shanghai",
    "iso:country":"CN",
    "name:zho_x_preferred":[
        "\u97ed\u83dc\u5858"
    ],
    "wof:name":"Jiucaitang",
    "wof:placetype":"locality"
},
  "geometry": {"coordinates":[109.27025999999999,28.94394],"type":"Point"}
}