{
  "type": "Feature",
  "properties": {
    "gn:admin1_code":"2.0",
    "gn:asciiname":"Mukenghu",
    "gn:country_code":"CN",
    "gn:dem":59,
    "gn:feature_class":"P",
    "gn:feature_code":"PPL",
    "gn:name":"Mukenghu",
    "gn:population":0,
    "gn:timezone":"Asia/Shanghai",
    "iso:country":"CN",
    "name:zho_x_preferred":[
        "\u6728\u5751\u80e1"
    ],
    "wof:name":"Mukenghu",
    "wof:placetype":"locality"
},
  "geometry": {"coordinates":[121.37770999999999,29.26988],"type":"Point"}
}