{
  "type": "Feature",
  "properties": {
    "gn:admin1_code":"5.0",
    "gn:asciiname":"Yongxingtun",
    "gn:country_code":"CN",
    "gn:dem":458,
    "gn:feature_class":"P",
    "gn:feature_code":"PPL",
    "gn:name":"Yongxingtun",
    "gn:population":0,
    "gn:timezone":"Asia/Shanghai",
    "iso:country":"CN",
    "name:und_x_variant":[
        "\u6c38\u5174\u5c6f"
    ],
    "wof:name":"Yongxingtun",
    "wof:placetype":"locality"
},
  "geometry": {"coordinates":[129.03286,42.96401],"type":"Point"}
}