{
  "type": "Feature",
  "properties": {
    "gn:admin1_code":"15.0",
    "gn:asciiname":"Zhangjiaping",
    "gn:country_code":"CN",
    "gn:dem":1707,
    "gn:feature_class":"P",
    "gn:feature_code":"PPL",
    "gn:name":"Zhangjiaping",
    "gn:population":0,
    "gn:timezone":"Asia/Shanghai",
    "iso:country":"CN",
    "name:zho_x_preferred":[
        "\u5f20\u5bb6\u576a"
    ],
    "wof:name":"Zhangjiaping",
    "wof:placetype":"locality"
},
  "geometry": {"coordinates":[105.009,36.0082],"type":"Point"}
}