{
  "type": "Feature",
  "properties": {
    "gn:admin1_code":"13.0",
    "gn:asciiname":"Serike",
    "gn:country_code":"CN",
    "gn:dem":1380,
    "gn:feature_class":"P",
    "gn:feature_code":"PPL",
    "gn:name":"Serike",
    "gn:population":0,
    "gn:timezone":"Asia/Shanghai",
    "iso:country":"CN",
    "name:zho_x_preferred":[
        "\u8272\u65e5\u514b"
    ],
    "wof:name":"Serike",
    "wof:placetype":"locality"
},
  "geometry": {"coordinates":[79.98581999999998,37.10666],"type":"Point"}
}