{
  "type": "Feature",
  "properties": {
    "gn:admin1_code":"19.0",
    "gn:asciiname":"Liangjiajie",
    "gn:country_code":"CN",
    "gn:dem":2,
    "gn:feature_class":"P",
    "gn:feature_code":"PPL",
    "gn:name":"Liangjiajie",
    "gn:population":0,
    "gn:timezone":"Asia/Shanghai",
    "iso:country":"CN",
    "name:zho_x_preferred":[
        "\u6881\u5bb6\u8857"
    ],
    "wof:name":"Liangjiajie",
    "wof:placetype":"locality"
},
  "geometry": {"coordinates":[122.104,41.0017],"type":"Point"}
}