{
  "type": "Feature",
  "properties": {
    "gn:admin1_code":"13",
    "gn:asciiname":"Bashituo Zakeqi",
    "gn:country_code":"CN",
    "gn:dem":1321,
    "gn:feature_class":"P",
    "gn:feature_code":"PPL",
    "gn:name":"Bashituo Zakeqi",
    "gn:population":0,
    "gn:timezone":"Asia/Shanghai",
    "iso:country":"CN",
    "name:und_x_variant":[
        "\u5df4\u4ec0\u6258\u624e\u514b\u5176"
    ],
    "wof:name":"Bashituo Zakeqi",
    "wof:placetype":"locality"
},
  "geometry": {"coordinates":[77.14986,38.13841],"type":"Point"}
}