{
  "type": "Feature",
  "properties": {
    "gn:admin1_code":"21.0",
    "gn:asciiname":"Shangmachang",
    "gn:country_code":"CN",
    "gn:dem":2281,
    "gn:feature_class":"P",
    "gn:feature_code":"PPL",
    "gn:name":"Shangmachang",
    "gn:population":0,
    "gn:timezone":"Asia/Shanghai",
    "iso:country":"CN",
    "name:zho_x_preferred":[
        "\u4e0a\u9a6c\u573a"
    ],
    "wof:name":"Shangmachang",
    "wof:placetype":"locality"
},
  "geometry": {"coordinates":[106.09,35.9129],"type":"Point"}
}