{
  "type": "Feature",
  "properties": {
    "gn:admin1_code":"15.0",
    "gn:asciiname":"Yangjiadazhuang",
    "gn:country_code":"CN",
    "gn:dem":2330,
    "gn:feature_class":"P",
    "gn:feature_code":"PPL",
    "gn:name":"Yangjiadazhuang",
    "gn:population":0,
    "gn:timezone":"Asia/Shanghai",
    "iso:country":"CN",
    "name:und_x_variant":[
        "\u6768\u5bb6\u5927\u5e84"
    ],
    "wof:name":"Yangjiadazhuang",
    "wof:placetype":"locality"
},
  "geometry": {"coordinates":[103.864,35.0222],"type":"Point"}
}