{
  "type": "Feature",
  "properties": {
    "gn:admin1_code":"26.0",
    "gn:asciiname":"Dahongya",
    "gn:country_code":"CN",
    "gn:dem":1446,
    "gn:feature_class":"P",
    "gn:feature_code":"PPL",
    "gn:name":"Dahongya",
    "gn:population":0,
    "gn:timezone":"Asia/Shanghai",
    "iso:country":"CN",
    "name:zho_x_preferred":[
        "\u5927\u7ea2\u5d16"
    ],
    "wof:name":"Dahongya",
    "wof:placetype":"locality"
},
  "geometry": {"coordinates":[107.38911,32.62893],"type":"Point"}
}