{
  "type": "Feature",
  "properties": {
    "gn:admin1_code":"19.0",
    "gn:asciiname":"Yaobuzi",
    "gn:country_code":"CN",
    "gn:dem":4,
    "gn:feature_class":"P",
    "gn:feature_code":"PPL",
    "gn:name":"Yaobuzi",
    "gn:population":0,
    "gn:timezone":"Asia/Shanghai",
    "iso:country":"CN",
    "name:und_x_variant":[
        "Yaobaozi",
        "Yaobuzi"
    ],
    "name:zho_x_preferred":[
        "\u8170\u5821\u5b50"
    ],
    "wof:name":"Yaobuzi",
    "wof:placetype":"locality"
},
  "geometry": {"coordinates":[121.92975,41.1993],"type":"Point"}
}