{
  "type": "Feature",
  "properties": {
    "gn:admin1_code":"31",
    "gn:asciiname":"Xiaoqiancun",
    "gn:country_code":"CN",
    "gn:dem":35,
    "gn:feature_class":"P",
    "gn:feature_code":"PPL",
    "gn:name":"Xiaoqiancun",
    "gn:population":0,
    "gn:timezone":"Asia/Shanghai",
    "iso:country":"CN",
    "name:und_x_variant":[
        "Xiaogancun"
    ],
    "name:zho_x_preferred":[
        "\u5c0f\u5343\u6751"
    ],
    "wof:name":"Xiaoqiancun",
    "wof:placetype":"locality"
},
  "geometry": {"coordinates":[109.35899999999999,19.67095],"type":"Point"}
}