{
  "type": "Feature",
  "properties": {
    "gn:admin1_code":"30",
    "gn:asciiname":"Yushuishe",
    "gn:country_code":"CN",
    "gn:dem":279,
    "gn:feature_class":"P",
    "gn:feature_code":"PPL",
    "gn:name":"Yushuishe",
    "gn:population":0,
    "gn:timezone":"Asia/Shanghai",
    "iso:country":"CN",
    "name:zho_x_preferred":[
        "\u4f59\u6c34\u8f0b"
    ],
    "wof:name":"Yushuishe",
    "wof:placetype":"locality"
},
  "geometry": {"coordinates":[116.74932,24.423],"type":"Point"}
}