{
  "type": "Feature",
  "properties": {
    "gn:admin1_code":"19.0",
    "gn:asciiname":"Lingdongcun",
    "gn:country_code":"CN",
    "gn:dem":21,
    "gn:feature_class":"P",
    "gn:feature_code":"PPL",
    "gn:name":"Lingdongcun",
    "gn:population":0,
    "gn:timezone":"Asia/Shanghai",
    "iso:country":"CN",
    "name:zho_x_preferred":[
        "\u51cc\u4e1c\u6751"
    ],
    "wof:name":"Lingdongcun",
    "wof:placetype":"locality"
},
  "geometry": {"coordinates":[121.36799999999999,41.1692],"type":"Point"}
}