{
  "type": "Feature",
  "properties": {
    "gn:admin1_code":"12.0",
    "gn:asciiname":"Yujiaxiang",
    "gn:country_code":"CN",
    "gn:dem":35,
    "gn:feature_class":"P",
    "gn:feature_code":"PPL",
    "gn:name":"Yujiaxiang",
    "gn:population":0,
    "gn:timezone":"Asia/Shanghai",
    "iso:country":"CN",
    "name:zho_x_preferred":[
        "\u55bb\u5bb6\u5df7"
    ],
    "wof:name":"Yujiaxiang",
    "wof:placetype":"locality"
},
  "geometry": {"coordinates":[113.9965,30.5865],"type":"Point"}
}