{
  "type": "Feature",
  "properties": {
    "gn:admin1_code":"12.0",
    "gn:asciiname":"Mahaodu",
    "gn:country_code":"CN",
    "gn:dem":27,
    "gn:feature_class":"P",
    "gn:feature_code":"PPL",
    "gn:name":"Mahaodu",
    "gn:population":0,
    "gn:timezone":"Asia/Shanghai",
    "iso:country":"CN",
    "name:zho_x_preferred":[
        "\u9ebb\u6fe0\u6e21"
    ],
    "wof:name":"Mahaodu",
    "wof:placetype":"locality"
},
  "geometry": {"coordinates":[113.29317,30.0651],"type":"Point"}
}