{
  "type": "Feature",
  "properties": {
    "gn:admin1_code":"1.0",
    "gn:asciiname":"Beijiecun",
    "gn:country_code":"CN",
    "gn:dem":33,
    "gn:feature_class":"P",
    "gn:feature_code":"PPL",
    "gn:name":"Beijiecun",
    "gn:population":0,
    "gn:timezone":"Asia/Shanghai",
    "iso:country":"CN",
    "name:zho_x_preferred":[
        "\u5317\u8857\u6751"
    ],
    "wof:name":"Beijiecun",
    "wof:placetype":"locality"
},
  "geometry": {"coordinates":[115.92407,33.13269],"type":"Point"}
}