{
  "type": "Feature",
  "properties": {
    "gn:admin1_code":"19.0",
    "gn:asciiname":"Jingangshan",
    "gn:country_code":"CN",
    "gn:dem":180,
    "gn:feature_class":"P",
    "gn:feature_code":"PPL",
    "gn:name":"Jingangshan",
    "gn:population":0,
    "gn:timezone":"Asia/Shanghai",
    "iso:country":"CN",
    "name:zho_x_preferred":[
        "\u91d1\u521a\u5c71"
    ],
    "wof:name":"Jingangshan",
    "wof:placetype":"locality"
},
  "geometry": {"coordinates":[121.1318,41.44986],"type":"Point"}
}