{
  "type": "Feature",
  "properties": {
    "gn:admin1_code":"16.0",
    "gn:asciiname":"Xiecun",
    "gn:country_code":"CN",
    "gn:dem":340,
    "gn:feature_class":"P",
    "gn:feature_code":"PPL",
    "gn:name":"Xiecun",
    "gn:population":0,
    "gn:timezone":"Asia/Shanghai",
    "iso:country":"CN",
    "name:zho_x_preferred":[
        "\u8c22\u6751"
    ],
    "wof:name":"Xiecun",
    "wof:placetype":"locality"
},
  "geometry": {"coordinates":[108.95399999999999,24.7876],"type":"Point"}
}