{
  "type": "Feature",
  "properties": {
    "gn:admin1_code":"16.0",
    "gn:asciiname":"Dajiao",
    "gn:country_code":"CN",
    "gn:dem":1159,
    "gn:feature_class":"P",
    "gn:feature_code":"PPL",
    "gn:name":"Dajiao",
    "gn:population":0,
    "gn:timezone":"Asia/Shanghai",
    "iso:country":"CN",
    "name:zho_x_preferred":[
        "\u6253\u89d2"
    ],
    "wof:name":"Dajiao",
    "wof:placetype":"locality"
},
  "geometry": {"coordinates":[106.22199999999999,24.4486],"type":"Point"}
}