{
  "type": "Feature",
  "properties": {
    "gn:admin1_code":"2.0",
    "gn:asciiname":"Leishi",
    "gn:country_code":"CN",
    "gn:dem":606,
    "gn:feature_class":"P",
    "gn:feature_code":"PPL",
    "gn:name":"Leishi",
    "gn:population":0,
    "gn:timezone":"Asia/Shanghai",
    "iso:country":"CN",
    "name:zho_x_preferred":[
        "\u96f7\u77f3"
    ],
    "wof:name":"Leishi",
    "wof:placetype":"locality"
},
  "geometry": {"coordinates":[119.74630000000001,27.51889000000001],"type":"Point"}
}