{
  "type": "Feature",
  "properties": {
    "gn:admin1_code":"29.0",
    "gn:asciiname":"Weijiachong",
    "gn:country_code":"CN",
    "gn:dem":2867,
    "gn:feature_class":"P",
    "gn:feature_code":"PPL",
    "gn:name":"Weijiachong",
    "gn:population":0,
    "gn:timezone":"Asia/Shanghai",
    "iso:country":"CN",
    "name:zho_x_preferred":[
        "\u9b4f\u5bb6\u51b2"
    ],
    "wof:name":"Weijiachong",
    "wof:placetype":"locality"
},
  "geometry": {"coordinates":[102.929,26.2616],"type":"Point"}
}