{
  "type": "Feature",
  "properties": {
    "gn:admin1_code":"3.0",
    "gn:asciiname":"Zhoushang Dengjia",
    "gn:country_code":"CN",
    "gn:dem":32,
    "gn:feature_class":"P",
    "gn:feature_code":"PPL",
    "gn:name":"Zhoushang Dengjia",
    "gn:population":0,
    "gn:timezone":"Asia/Shanghai",
    "iso:country":"CN",
    "name:und_x_variant":[
        "\u6d32\u4e0a\u9093\u5bb6"
    ],
    "wof:name":"Zhoushang Dengjia",
    "wof:placetype":"locality"
},
  "geometry": {"coordinates":[116.28027,28.10848],"type":"Point"}
}