{
  "type": "Feature",
  "properties": {
    "gn:admin1_code":"5.0",
    "gn:asciiname":"Lijia Gangzi",
    "gn:country_code":"CN",
    "gn:dem":227,
    "gn:feature_class":"P",
    "gn:feature_code":"PPL",
    "gn:name":"Lijia Gangzi",
    "gn:population":0,
    "gn:timezone":"Asia/Shanghai",
    "iso:country":"CN",
    "name:zho_x_preferred":[
        "\u674e\u5bb6\u5c97\u5b50"
    ],
    "wof:name":"Lijia Gangzi",
    "wof:placetype":"locality"
},
  "geometry": {"coordinates":[124.98497,43.34088],"type":"Point"}
}