{
  "type": "Feature",
  "properties": {
    "gn:admin1_code":"14.0",
    "gn:asciiname":"Mageban",
    "gn:country_code":"CN",
    "gn:dem":4218,
    "gn:feature_class":"P",
    "gn:feature_code":"PPL",
    "gn:name":"Mageban",
    "gn:population":0,
    "gn:timezone":"Asia/Urumqi",
    "iso:country":"CN",
    "name:zho_x_preferred":[
        "\u9a6c\u5404\u73ed"
    ],
    "wof:name":"Mageban",
    "wof:placetype":"locality"
},
  "geometry": {"coordinates":[96.89927,31.09456],"type":"Point"}
}