{
  "type": "Feature",
  "properties": {
    "gn:admin1_code":"10",
    "gn:asciiname":"Sanlang",
    "gn:cc2":"CN",
    "gn:country_code":"CN",
    "gn:dem":29,
    "gn:feature_class":"P",
    "gn:feature_code":"PPL",
    "gn:name":"Sanlang",
    "gn:population":0,
    "gn:timezone":"Asia/Shanghai",
    "iso:country":"CN",
    "name:und_x_variant":[
        "San-lang-chen",
        "Sanlang"
    ],
    "wof:name":"Sanlang",
    "wof:placetype":"locality"
},
  "geometry": {"coordinates":[115.88167,37.46],"type":"Point"}
}