{
  "type": "Feature",
  "properties": {
    "gn:admin1_code":"12.0",
    "gn:asciiname":"Xiaojingshulin",
    "gn:country_code":"CN",
    "gn:dem":199,
    "gn:feature_class":"P",
    "gn:feature_code":"PPL",
    "gn:name":"Xiaojingshulin",
    "gn:population":0,
    "gn:timezone":"Asia/Shanghai",
    "iso:country":"CN",
    "name:zho_x_preferred":[
        "\u5c0f\u8346\u6811\u6797"
    ],
    "wof:name":"Xiaojingshulin",
    "wof:placetype":"locality"
},
  "geometry": {"coordinates":[112.6729,31.6971],"type":"Point"}
}