{
  "type": "Feature",
  "properties": {
    "gn:admin1_code":"32.0",
    "gn:asciiname":"Re'ermaima",
    "gn:country_code":"CN",
    "gn:dem":3552,
    "gn:feature_class":"P",
    "gn:feature_code":"PPL",
    "gn:name":"Re\u2019ermaima",
    "gn:population":0,
    "gn:timezone":"Asia/Shanghai",
    "iso:country":"CN",
    "name:zho_x_preferred":[
        "\u60f9\u5c14\u8fc8\u9a6c"
    ],
    "name:zho_x_variant":[
        "Re\u2019ermaima"
    ],
    "wof:name":"Re'ermaima",
    "wof:placetype":"locality"
},
  "geometry": {"coordinates":[102.94034000000001,33.93398],"type":"Point"}
}