{
  "type": "Feature",
  "properties": {
    "gn:admin1_code":"7.0",
    "gn:asciiname":"Chepan",
    "gn:country_code":"CN",
    "gn:dem":564,
    "gn:feature_class":"P",
    "gn:feature_code":"PPL",
    "gn:name":"Chepan",
    "gn:population":0,
    "gn:timezone":"Asia/Shanghai",
    "iso:country":"CN",
    "name:zho_x_preferred":[
        "\u8f66\u76d8"
    ],
    "wof:name":"Chepan",
    "wof:placetype":"locality"
},
  "geometry": {"coordinates":[119.30146000000001,26.98109],"type":"Point"}
}