{
  "type": "Feature",
  "properties": {
    "gn:admin1_code":"5.0",
    "gn:asciiname":"Palicun",
    "gn:country_code":"CN",
    "gn:dem":872,
    "gn:feature_class":"P",
    "gn:feature_code":"PPL",
    "gn:name":"Palicun",
    "gn:population":0,
    "gn:timezone":"Asia/Shanghai",
    "iso:country":"CN",
    "name:zho_x_preferred":[
        "\u722c\u529b\u6751"
    ],
    "wof:name":"Palicun",
    "wof:placetype":"locality"
},
  "geometry": {"coordinates":[127.4962,41.60412],"type":"Point"}
}