{
  "type": "Feature",
  "properties": {
    "gn:admin1_code":"29",
    "gn:asciiname":"Adou",
    "gn:country_code":"CN",
    "gn:dem":1869,
    "gn:feature_class":"P",
    "gn:feature_code":"PPL",
    "gn:name":"Adou",
    "gn:population":0,
    "gn:timezone":"Asia/Shanghai",
    "iso:country":"CN",
    "name:zho_x_preferred":[
        "\u963f\u8c46"
    ],
    "wof:name":"Adou",
    "wof:placetype":"locality"
},
  "geometry": {"coordinates":[102.709,24.3908],"type":"Point"}
}