{
  "type": "Feature",
  "properties": {
    "gn:admin1_code":"15.0",
    "gn:asciiname":"Kangjiawan",
    "gn:country_code":"CN",
    "gn:dem":1710,
    "gn:feature_class":"P",
    "gn:feature_code":"PPL",
    "gn:name":"Kangjiawan",
    "gn:population":0,
    "gn:timezone":"Asia/Shanghai",
    "iso:country":"CN",
    "name:und_x_variant":[
        "\u5eb7\u5bb6\u6e7e"
    ],
    "wof:name":"Kangjiawan",
    "wof:placetype":"locality"
},
  "geometry": {"coordinates":[106.24982,33.68607],"type":"Point"}
}