{
  "type": "Feature",
  "properties": {
    "gn:admin1_code":"14.0",
    "gn:asciiname":"Naglado",
    "gn:country_code":"CN",
    "gn:dem":4738,
    "gn:feature_class":"P",
    "gn:feature_code":"PPL",
    "gn:name":"Naglado",
    "gn:population":0,
    "gn:timezone":"Asia/Urumqi",
    "iso:country":"CN",
    "name:bod_x_preferred":[
        "Naglado"
    ],
    "name:zho_x_preferred":[
        "Naladuo"
    ],
    "name:zho_x_variant":[
        "\u7eb3\u62c9\u591a"
    ],
    "wof:name":"Naglado",
    "wof:placetype":"locality"
},
  "geometry": {"coordinates":[97.30200000000001,31.302],"type":"Point"}
}