{
  "type": "Feature",
  "properties": {
    "gn:admin1_code":"19.0",
    "gn:asciiname":"Houdafang",
    "gn:country_code":"CN",
    "gn:dem":106,
    "gn:feature_class":"P",
    "gn:feature_code":"PPL",
    "gn:name":"Houdafang",
    "gn:population":0,
    "gn:timezone":"Asia/Shanghai",
    "iso:country":"CN",
    "name:zho_x_preferred":[
        "\u540e\u5927\u574a"
    ],
    "wof:name":"Houdafang",
    "wof:placetype":"locality"
},
  "geometry": {"coordinates":[123.70099999999999,43.1152],"type":"Point"}
}