{
  "type": "Feature",
  "properties": {
    "gn:admin1_code":"3.0",
    "gn:asciiname":"Zhiguang Liangzhongchang",
    "gn:country_code":"CN",
    "gn:dem":38,
    "gn:feature_class":"P",
    "gn:feature_code":"PPLF",
    "gn:name":"Zhiguang Liangzhongchang",
    "gn:population":0,
    "gn:timezone":"Asia/Shanghai",
    "iso:country":"CN",
    "name:zho_x_preferred":[
        "\u5fd7\u5149\u826f\u79cd\u573a"
    ],
    "wof:name":"Zhiguang Liangzhongchang",
    "wof:placetype":"locality"
},
  "geometry": {"coordinates":[117.04076999999999,28.39185],"type":"Point"}
}