{
  "type": "Feature",
  "properties": {
    "gn:admin1_code":"15.0",
    "gn:asciiname":"Xiejiazhuang",
    "gn:country_code":"CN",
    "gn:dem":2124,
    "gn:feature_class":"P",
    "gn:feature_code":"PPL",
    "gn:name":"Xiejiazhuang",
    "gn:population":0,
    "gn:timezone":"Asia/Shanghai",
    "iso:country":"CN",
    "name:und_x_variant":[
        "\u8c22\u5bb6\u5e84"
    ],
    "wof:name":"Xiejiazhuang",
    "wof:placetype":"locality"
},
  "geometry": {"coordinates":[104.66867999999999,34.56403],"type":"Point"}
}