{
  "type": "Feature",
  "properties": {
    "gn:admin1_code":"25.0",
    "gn:asciiname":"Juwucun",
    "gn:country_code":"CN",
    "gn:dem":94,
    "gn:feature_class":"P",
    "gn:feature_code":"PPL",
    "gn:name":"Juwucun",
    "gn:population":0,
    "gn:timezone":"Asia/Shanghai",
    "iso:country":"CN",
    "name:zho_x_preferred":[
        "\u5de8\u5c4b\u6751"
    ],
    "wof:name":"Juwucun",
    "wof:placetype":"locality"
},
  "geometry": {"coordinates":[120.72346,37.15396],"type":"Point"}
}