{
  "type": "Feature",
  "properties": {
    "gn:admin1_code":"10.0",
    "gn:asciiname":"Sengfatou",
    "gn:country_code":"CN",
    "gn:dem":27,
    "gn:feature_class":"P",
    "gn:feature_code":"PPL",
    "gn:name":"Sengfatou",
    "gn:population":0,
    "gn:timezone":"Asia/Shanghai",
    "iso:country":"CN",
    "name:zho_x_preferred":[
        "\u50e7\u57a1\u5934"
    ],
    "wof:name":"Sengfatou",
    "wof:placetype":"locality"
},
  "geometry": {"coordinates":[116.52311,39.45225],"type":"Point"}
}