{
  "type": "Feature",
  "properties": {
    "gn:admin1_code":"15.0",
    "gn:asciiname":"Duiqiwan",
    "gn:country_code":"CN",
    "gn:dem":2147,
    "gn:feature_class":"P",
    "gn:feature_code":"PPL",
    "gn:name":"Duiqiwan",
    "gn:population":0,
    "gn:timezone":"Asia/Shanghai",
    "iso:country":"CN",
    "name:und_x_variant":[
        "\u5bf9\u9f50\u6e7e"
    ],
    "name:zho_x_preferred":[
        "\u5bf9\u9f50\u6e7e"
    ],
    "wof:name":"Duiqiwan",
    "wof:placetype":"locality"
},
  "geometry": {"coordinates":[104.69868,34.00548],"type":"Point"}
}