{
  "type": "Feature",
  "properties": {
    "gn:admin1_code":"10.0",
    "gn:asciiname":"Shangda Liushu",
    "gn:country_code":"CN",
    "gn:dem":900,
    "gn:feature_class":"P",
    "gn:feature_code":"PPL",
    "gn:name":"Shangda Liushu",
    "gn:population":0,
    "gn:timezone":"Asia/Shanghai",
    "iso:country":"CN",
    "name:zho_x_preferred":[
        "\u4e0a\u5927\u67f3\u6811"
    ],
    "wof:name":"Shangda Liushu",
    "wof:placetype":"locality"
},
  "geometry": {"coordinates":[113.98702,40.0453],"type":"Point"}
}