{
  "type": "Feature",
  "properties": {
    "gn:admin1_code":"29.0",
    "gn:asciiname":"Laozhongshan",
    "gn:country_code":"CN",
    "gn:dem":1773,
    "gn:feature_class":"P",
    "gn:feature_code":"PPL",
    "gn:name":"Laozhongshan",
    "gn:population":0,
    "gn:timezone":"Asia/Shanghai",
    "iso:country":"CN",
    "name:zho_x_preferred":[
        "\u8001\u4e2d\u5c71"
    ],
    "wof:name":"Laozhongshan",
    "wof:placetype":"locality"
},
  "geometry": {"coordinates":[98.1388,24.499],"type":"Point"}
}