{
  "type": "Feature",
  "properties": {
    "gn:admin1_code":"19.0",
    "gn:asciiname":"Heichaogou",
    "gn:country_code":"CN",
    "gn:dem":91,
    "gn:feature_class":"P",
    "gn:feature_code":"PPL",
    "gn:name":"Heichaogou",
    "gn:population":0,
    "gn:timezone":"Asia/Shanghai",
    "iso:country":"CN",
    "name:zho_x_preferred":[
        "\u9ed1\u6f6e\u6c9f"
    ],
    "wof:name":"Heichaogou",
    "wof:placetype":"locality"
},
  "geometry": {"coordinates":[120.0403,40.47224],"type":"Point"}
}