{
  "type": "Feature",
  "properties": {
    "gn:admin1_code":"15.0",
    "gn:asciiname":"Dabuli",
    "gn:country_code":"CN",
    "gn:dem":1030,
    "gn:feature_class":"P",
    "gn:feature_code":"PPL",
    "gn:name":"Dabuli",
    "gn:population":0,
    "gn:timezone":"Asia/Shanghai",
    "iso:country":"CN",
    "name:zho_x_preferred":[
        "\u5927\u5821\u91cc"
    ],
    "wof:name":"Dabuli",
    "wof:placetype":"locality"
},
  "geometry": {"coordinates":[104.90143,33.40295],"type":"Point"}
}