{
  "type": "Feature",
  "properties": {
    "gn:admin1_code":"26.0",
    "gn:asciiname":"Laoyoufang",
    "gn:country_code":"CN",
    "gn:dem":1229,
    "gn:feature_class":"P",
    "gn:feature_code":"PPL",
    "gn:name":"Laoyoufang",
    "gn:population":0,
    "gn:timezone":"Asia/Shanghai",
    "iso:country":"CN",
    "name:zho_x_preferred":[
        "\u8001\u6cb9\u623f"
    ],
    "wof:name":"Laoyoufang",
    "wof:placetype":"locality"
},
  "geometry": {"coordinates":[110.41831000000001,33.77896],"type":"Point"}
}