{
  "type": "Feature",
  "properties": {
    "gn:admin1_code":"14.0",
    "gn:asciiname":"Kurucun",
    "gn:country_code":"CN",
    "gn:dem":4418,
    "gn:feature_class":"P",
    "gn:feature_code":"PPL",
    "gn:name":"Kurucun",
    "gn:population":0,
    "gn:timezone":"Asia/Urumqi",
    "iso:country":"CN",
    "name:zho_x_preferred":[
        "\u67af\u5982\u6751"
    ],
    "wof:name":"Kurucun",
    "wof:placetype":"locality"
},
  "geometry": {"coordinates":[93.33936,32.30945999999999],"type":"Point"}
}