{
  "type": "Feature",
  "properties": {
    "gn:admin1_code":"7.0",
    "gn:asciiname":"Qishang",
    "gn:country_code":"CN",
    "gn:dem":466,
    "gn:feature_class":"P",
    "gn:feature_code":"PPL",
    "gn:name":"Qishang",
    "gn:population":0,
    "gn:timezone":"Asia/Shanghai",
    "iso:country":"CN",
    "name:und_x_variant":[
        "\u78dc\u4e0a"
    ],
    "wof:name":"Qishang",
    "wof:placetype":"locality"
},
  "geometry": {"coordinates":[116.88952999999999,26.82816],"type":"Point"}
}