{
  "type": "Feature",
  "properties": {
    "gn:admin1_code":"8.0",
    "gn:asciiname":"Dongchengcun",
    "gn:country_code":"CN",
    "gn:dem":74,
    "gn:feature_class":"P",
    "gn:feature_code":"PPL",
    "gn:name":"Dongchengcun",
    "gn:population":0,
    "gn:timezone":"Asia/Shanghai",
    "iso:country":"CN",
    "name:zho_x_preferred":[
        "\u4e1c\u57ce\u6751"
    ],
    "wof:name":"Dongchengcun",
    "wof:placetype":"locality"
},
  "geometry": {"coordinates":[130.69508999999999,47.12749],"type":"Point"}
}