{
  "type": "Feature",
  "properties": {
    "gn:admin1_code":"14.0",
    "gn:asciiname":"Zhaguo Niuchang",
    "gn:country_code":"CN",
    "gn:dem":4265,
    "gn:feature_class":"P",
    "gn:feature_code":"PPLF",
    "gn:name":"Zhaguo Niuchang",
    "gn:population":0,
    "gn:timezone":"Asia/Urumqi",
    "iso:country":"CN",
    "name:zho_x_preferred":[
        "\u624e\u679c\u725b\u573a"
    ],
    "wof:name":"Zhaguo Niuchang",
    "wof:placetype":"locality"
},
  "geometry": {"coordinates":[98.47949,29.69288],"type":"Point"}
}