{
  "type": "Feature",
  "properties": {
    "gn:admin1_code":"1.0",
    "gn:asciiname":"Wangjiayuan",
    "gn:country_code":"CN",
    "gn:dem":539,
    "gn:feature_class":"P",
    "gn:feature_code":"PPL",
    "gn:name":"Wangjiayuan",
    "gn:population":0,
    "gn:timezone":"Asia/Shanghai",
    "iso:country":"CN",
    "name:und_x_variant":[
        "\u738b\u5bb6\u6e90"
    ],
    "wof:name":"Wangjiayuan",
    "wof:placetype":"locality"
},
  "geometry": {"coordinates":[118.58591,30.14684],"type":"Point"}
}