{
  "type": "Feature",
  "properties": {
    "gn:admin1_code":"31",
    "gn:asciiname":"Baozhi",
    "gn:country_code":"CN",
    "gn:dem":6,
    "gn:feature_class":"P",
    "gn:feature_code":"PPL",
    "gn:name":"Baozhi",
    "gn:population":0,
    "gn:timezone":"Asia/Shanghai",
    "iso:country":"CN",
    "name:und_x_variant":[
        "Pao Chih",
        "Baozhi",
        "\u5b9d\u5cd9"
    ],
    "wof:name":"Baozhi",
    "wof:placetype":"locality"
},
  "geometry": {"coordinates":[110.758,19.4376],"type":"Point"}
}