{
  "type": "Feature",
  "properties": {
    "gn:admin1_code":"32.0",
    "gn:asciiname":"Mao'ergou",
    "gn:country_code":"CN",
    "gn:dem":336,
    "gn:feature_class":"P",
    "gn:feature_code":"PPL",
    "gn:name":"Mao\u2019ergou",
    "gn:population":0,
    "gn:timezone":"Asia/Shanghai",
    "iso:country":"CN",
    "name:zho_x_preferred":[
        "\u732b\u513f\u6c9f"
    ],
    "name:zho_x_variant":[
        "Mao\u2019ergou"
    ],
    "wof:name":"Mao'ergou",
    "wof:placetype":"locality"
},
  "geometry": {"coordinates":[105.22747,30.58331],"type":"Point"}
}