{
  "type": "Feature",
  "properties": {
    "gn:admin1_code":"29",
    "gn:asciiname":"Banggu",
    "gn:country_code":"CN",
    "gn:dem":1357,
    "gn:feature_class":"P",
    "gn:feature_code":"PPL",
    "gn:name":"Banggu",
    "gn:population":0,
    "gn:timezone":"Asia/Shanghai",
    "iso:country":"CN",
    "wof:name":"Banggu",
    "wof:placetype":"locality"
},
  "geometry": {"coordinates":[104.57778,23.38028],"type":"Point"}
}