{
  "type": "Feature",
  "properties": {
    "gn:admin1_code":"24.0",
    "gn:asciiname":"Cigouying",
    "gn:country_code":"CN",
    "gn:dem":863,
    "gn:feature_class":"P",
    "gn:feature_code":"PPL",
    "gn:name":"Cigouying",
    "gn:population":0,
    "gn:timezone":"Asia/Shanghai",
    "iso:country":"CN",
    "name:und_x_variant":[
        "\u8328\u6c9f\u8425"
    ],
    "name:zho_x_preferred":[
        "\u8328\u6c9f\u8425"
    ],
    "wof:name":"Cigouying",
    "wof:placetype":"locality"
},
  "geometry": {"coordinates":[113.92211,39.10181],"type":"Point"}
}