{
  "type": "Feature",
  "properties": {
    "gn:admin1_code":"07",
    "gn:asciiname":"Pengkeng",
    "gn:country_code":"CN",
    "gn:dem":845,
    "gn:feature_class":"P",
    "gn:feature_code":"PPL",
    "gn:name":"Pengkeng",
    "gn:population":0,
    "gn:timezone":"Asia/Shanghai",
    "iso:country":"CN",
    "name:zho_x_preferred":[
        "\u5f6d\u5751"
    ],
    "wof:name":"Pengkeng",
    "wof:placetype":"locality"
},
  "geometry": {"coordinates":[118.24401,25.79826],"type":"Point"}
}