{
  "type": "Feature",
  "properties": {
    "gn:admin1_code":"02",
    "gn:asciiname":"Qu Linchang",
    "gn:country_code":"CN",
    "gn:dem":168,
    "gn:feature_class":"P",
    "gn:feature_code":"PPLF",
    "gn:name":"Qu Linchang",
    "gn:population":0,
    "gn:timezone":"Asia/Shanghai",
    "iso:country":"CN",
    "wof:name":"Qu Linchang",
    "wof:placetype":"locality"
},
  "geometry": {"coordinates":[121.87166999999999,29.83861],"type":"Point"}
}