{
  "type": "Feature",
  "properties": {
    "gn:admin1_code":"15.0",
    "gn:asciiname":"Renjiamo",
    "gn:country_code":"CN",
    "gn:dem":2163,
    "gn:feature_class":"P",
    "gn:feature_code":"PPL",
    "gn:name":"Renjiamo",
    "gn:population":0,
    "gn:timezone":"Asia/Shanghai",
    "iso:country":"CN",
    "name:zho_x_preferred":[
        "\u4efb\u5bb6\u78e8"
    ],
    "wof:name":"Renjiamo",
    "wof:placetype":"locality"
},
  "geometry": {"coordinates":[104.10899999999999,35.203],"type":"Point"}
}