{
  "type": "Feature",
  "properties": {
    "gn:admin1_code":"19.0",
    "gn:asciiname":"Koubuyingzicun",
    "gn:country_code":"CN",
    "gn:dem":234,
    "gn:feature_class":"P",
    "gn:feature_code":"PPL",
    "gn:name":"Koubuyingzicun",
    "gn:population":0,
    "gn:timezone":"Asia/Shanghai",
    "iso:country":"CN",
    "name:zho_x_preferred":[
        "\u6263\u535c\u8425\u5b50\u6751"
    ],
    "wof:name":"Koubuyingzicun",
    "wof:placetype":"locality"
},
  "geometry": {"coordinates":[120.605,41.8488],"type":"Point"}
}