{
  "type": "Feature",
  "properties": {
    "gn:admin1_code":"1.0",
    "gn:asciiname":"Qiuyingcun",
    "gn:country_code":"CN",
    "gn:dem":44,
    "gn:feature_class":"P",
    "gn:feature_code":"PPL",
    "gn:name":"Qiuyingcun",
    "gn:population":0,
    "gn:timezone":"Asia/Shanghai",
    "iso:country":"CN",
    "name:zho_x_preferred":[
        "\u90b1\u90e2\u6751"
    ],
    "wof:name":"Qiuyingcun",
    "wof:placetype":"locality"
},
  "geometry": {"coordinates":[118.05352999999999,32.67287],"type":"Point"}
}