{
  "type": "Feature",
  "properties": {
    "gn:admin1_code":"30.0",
    "gn:asciiname":"Muqiantang",
    "gn:country_code":"CN",
    "gn:dem":170,
    "gn:feature_class":"P",
    "gn:feature_code":"PPL",
    "gn:name":"Muqiantang",
    "gn:population":0,
    "gn:timezone":"Asia/Shanghai",
    "iso:country":"CN",
    "name:zho_x_preferred":[
        "Muqiantang"
    ],
    "name:zho_x_variant":[
        "\u6155\u524d\u5802"
    ],
    "wof:name":"Muqiantang",
    "wof:placetype":"locality"
},
  "geometry": {"coordinates":[115.41056,24.22167],"type":"Point"}
}