{
  "type": "Feature",
  "properties": {
    "gn:admin1_code":"12.0",
    "gn:asciiname":"Weijia",
    "gn:country_code":"CN",
    "gn:dem":25,
    "gn:feature_class":"P",
    "gn:feature_code":"PPL",
    "gn:name":"Weijia",
    "gn:population":0,
    "gn:timezone":"Asia/Shanghai",
    "iso:country":"CN",
    "name:zho_x_preferred":[
        "\u9b4f\u5bb6"
    ],
    "wof:name":"Weijia",
    "wof:placetype":"locality"
},
  "geometry": {"coordinates":[113.79783999999999,30.7137],"type":"Point"}
}