{
  "type": "Feature",
  "properties": {
    "gn:admin1_code":"2",
    "gn:asciiname":"Lujiatou",
    "gn:country_code":"CN",
    "gn:dem":169,
    "gn:feature_class":"P",
    "gn:feature_code":"PPL",
    "gn:name":"Lujiatou",
    "gn:population":0,
    "gn:timezone":"Asia/Shanghai",
    "iso:country":"CN",
    "name:und_x_variant":[
        "\u82a6\u5bb6\u5934"
    ],
    "wof:name":"Lujiatou",
    "wof:placetype":"locality"
},
  "geometry": {"coordinates":[119.68805999999999,30.14889],"type":"Point"}
}