{
  "type": "Feature",
  "properties": {
    "gn:admin1_code":"18.0",
    "gn:asciiname":"Machangcun",
    "gn:country_code":"CN",
    "gn:dem":462,
    "gn:feature_class":"P",
    "gn:feature_code":"PPL",
    "gn:name":"Machangcun",
    "gn:population":0,
    "gn:timezone":"Asia/Shanghai",
    "iso:country":"CN",
    "name:zho_x_preferred":[
        "\u9a6c\u573a\u6751"
    ],
    "wof:name":"Machangcun",
    "wof:placetype":"locality"
},
  "geometry": {"coordinates":[107.78700000000001,25.9938],"type":"Point"}
}