{
  "type": "Feature",
  "properties": {
    "gn:admin1_code":"26.0",
    "gn:asciiname":"Yinglicun",
    "gn:country_code":"CN",
    "gn:dem":519,
    "gn:feature_class":"P",
    "gn:feature_code":"PPL",
    "gn:name":"Yinglicun",
    "gn:population":0,
    "gn:timezone":"Asia/Shanghai",
    "iso:country":"CN",
    "name:zho_x_preferred":[
        "\u82f1\u674e\u6751"
    ],
    "wof:name":"Yinglicun",
    "wof:placetype":"locality"
},
  "geometry": {"coordinates":[109.393,34.42513],"type":"Point"}
}