{
  "type": "Feature",
  "properties": {
    "gn:admin1_code":"10",
    "gn:asciiname":"Wangjiahe",
    "gn:country_code":"CN",
    "gn:dem":53,
    "gn:feature_class":"P",
    "gn:feature_code":"PPL",
    "gn:name":"Wangjiahe",
    "gn:population":0,
    "gn:timezone":"Asia/Shanghai",
    "iso:country":"CN",
    "name:zho_x_preferred":[
        "\u738b\u5939\u6cb3"
    ],
    "wof:name":"Wangjiahe",
    "wof:placetype":"locality"
},
  "geometry": {"coordinates":[115.01505,36.23261],"type":"Point"}
}