{
  "type": "Feature",
  "properties": {
    "gn:admin1_code":"1.0",
    "gn:asciiname":"Zhuduntou",
    "gn:country_code":"CN",
    "gn:dem":9,
    "gn:feature_class":"P",
    "gn:feature_code":"PPL",
    "gn:name":"Zhuduntou",
    "gn:population":0,
    "gn:timezone":"Asia/Shanghai",
    "iso:country":"CN",
    "name:zho_x_preferred":[
        "\u7af9\u58a9\u5934"
    ],
    "wof:name":"Zhuduntou",
    "wof:placetype":"locality"
},
  "geometry": {"coordinates":[119.16755000000001,31.28273],"type":"Point"}
}