{
  "type": "Feature",
  "properties": {
    "gn:admin1_code":"22.0",
    "gn:asciiname":"Kaijiazhuang",
    "gn:country_code":"CN",
    "gn:dem":73,
    "gn:feature_class":"P",
    "gn:feature_code":"PPL",
    "gn:name":"Kaijiazhuang",
    "gn:population":0,
    "gn:timezone":"Asia/Shanghai",
    "iso:country":"CN",
    "name:zho_x_preferred":[
        "\u51ef\u7532\u5e84"
    ],
    "wof:name":"Kaijiazhuang",
    "wof:placetype":"locality"
},
  "geometry": {"coordinates":[116.56726,40.34584],"type":"Point"}
}