{
  "type": "Feature",
  "properties": {
    "gn:admin1_code":"26.0",
    "gn:asciiname":"Yishancun",
    "gn:country_code":"CN",
    "gn:dem":1191,
    "gn:feature_class":"P",
    "gn:feature_code":"PPL",
    "gn:name":"Yishancun",
    "gn:population":0,
    "gn:timezone":"Asia/Shanghai",
    "iso:country":"CN",
    "name:zho_x_preferred":[
        "\u8863\u5584\u6751"
    ],
    "wof:name":"Yishancun",
    "wof:placetype":"locality"
},
  "geometry": {"coordinates":[110.15562,36.3446],"type":"Point"}
}