{
  "type": "Feature",
  "properties": {
    "gn:admin1_code":"9.0",
    "gn:asciiname":"Zaiwan",
    "gn:country_code":"CN",
    "gn:dem":201,
    "gn:feature_class":"P",
    "gn:feature_code":"PPL",
    "gn:name":"Zaiwan",
    "gn:population":0,
    "gn:timezone":"Asia/Shanghai",
    "iso:country":"CN",
    "name:zho_x_preferred":[
        "\u5bb0\u6e7e"
    ],
    "wof:name":"Zaiwan",
    "wof:placetype":"locality"
},
  "geometry": {"coordinates":[113.39536,35.3933],"type":"Point"}
}