{
  "type": "Feature",
  "properties": {
    "gn:admin1_code":"32.0",
    "gn:asciiname":"Sanhedong",
    "gn:country_code":"CN",
    "gn:dem":441,
    "gn:feature_class":"P",
    "gn:feature_code":"PPL",
    "gn:name":"Sanhedong",
    "gn:population":0,
    "gn:timezone":"Asia/Shanghai",
    "iso:country":"CN",
    "name:zho_x_preferred":[
        "\u4e09\u6cb3\u6d1e"
    ],
    "wof:name":"Sanhedong",
    "wof:placetype":"locality"
},
  "geometry": {"coordinates":[104.944,30.461],"type":"Point"}
}