{
  "type": "Feature",
  "properties": {
    "gn:admin1_code":"32.0",
    "gn:asciiname":"Cizhuqing",
    "gn:country_code":"CN",
    "gn:dem":2035,
    "gn:feature_class":"P",
    "gn:feature_code":"PPL",
    "gn:name":"Cizhuqing",
    "gn:population":0,
    "gn:timezone":"Asia/Shanghai",
    "iso:country":"CN",
    "name:zho_x_preferred":[
        "\u523a\u7af9\u7b90"
    ],
    "wof:name":"Cizhuqing",
    "wof:placetype":"locality"
},
  "geometry": {"coordinates":[102.315,26.3132],"type":"Point"}
}