{
  "type": "Feature",
  "properties": {
    "gn:admin1_code":"32.0",
    "gn:asciiname":"Yuri",
    "gn:country_code":"CN",
    "gn:dem":2761,
    "gn:feature_class":"P",
    "gn:feature_code":"PPL",
    "gn:name":"Yuri",
    "gn:population":0,
    "gn:timezone":"Asia/Shanghai",
    "iso:country":"CN",
    "name:ara_x_preferred":[
        "\u064a\u0648\u0631\u064a"
    ],
    "name:ceb_x_preferred":[
        "Yuri"
    ],
    "name:est_x_preferred":[
        "Juri"
    ],
    "name:fas_x_preferred":[
        "\u06cc\u0648\u0631\u06cc"
    ],
    "name:fin_x_preferred":[
        "Yuri"
    ],
    "name:fra_x_preferred":[
        "Yuri"
    ],
    "name:heb_x_preferred":[
        "\u05d9\u05d5\u05e8\u05d9"
    ],
    "name:ita_x_preferred":[
        "Yuri"
    ],
    "name:kor_x_preferred":[
        "\uc720\ub9ac"
    ],
    "name:nld_x_preferred":[
        "Yuri"
    ],
    "name:rus_x_preferred":[
        "\u042e\u0440\u0438"
    ],
    "name:slk_x_preferred":[
        "Yuri"
    ],
    "name:spa_x_preferred":[
        "Yuri"
    ],
    "name:swe_x_preferred":[
        "Yuri"
    ],
    "name:tgl_x_preferred":[
        "Yuri"
    ],
    "name:tha_x_preferred":[
        "\u0e22\u0e39\u0e23\u0e34"
    ],
    "name:ukr_x_preferred":[
        "\u042e\u0440\u0456"
    ],
    "name:vie_x_preferred":[
        "Yuri"
    ],
    "name:zho_x_preferred":[
        "\u96e8\u65e5"
    ],
    "wof:name":"Yuri",
    "wof:placetype":"locality"
},
  "geometry": {"coordinates":[101.127,29.4186],"type":"Point"}
}