{
  "type": "Feature",
  "properties": {
    "gn:admin1_code":"32.0",
    "gn:asciiname":"Shigeng",
    "gn:country_code":"CN",
    "gn:dem":3136,
    "gn:feature_class":"P",
    "gn:feature_code":"PPL",
    "gn:name":"Shigeng",
    "gn:population":0,
    "gn:timezone":"Asia/Shanghai",
    "iso:country":"CN",
    "name:zho_x_preferred":[
        "\u77f3\u57c2"
    ],
    "wof:name":"Shigeng",
    "wof:placetype":"locality"
},
  "geometry": {"coordinates":[101.33965999999999,28.83809],"type":"Point"}
}