{
  "type": "Feature",
  "properties": {
    "gn:admin1_code":"8.0",
    "gn:asciiname":"Hongquancun",
    "gn:country_code":"CN",
    "gn:dem":108,
    "gn:feature_class":"P",
    "gn:feature_code":"PPL",
    "gn:name":"Hongquancun",
    "gn:population":0,
    "gn:timezone":"Asia/Shanghai",
    "iso:country":"CN",
    "name:zho_x_preferred":[
        "\u6d2a\u6cc9\u6751"
    ],
    "wof:name":"Hongquancun",
    "wof:placetype":"locality"
},
  "geometry": {"coordinates":[132.17233000000002,46.18644000000001],"type":"Point"}
}