{
  "type": "Feature",
  "properties": {
    "gn:admin1_code":"12.0",
    "gn:asciiname":"Laohuangjiawan",
    "gn:country_code":"CN",
    "gn:dem":29,
    "gn:feature_class":"P",
    "gn:feature_code":"PPL",
    "gn:name":"Laohuangjiawan",
    "gn:population":0,
    "gn:timezone":"Asia/Shanghai",
    "iso:country":"CN",
    "name:zho_x_preferred":[
        "\u8001\u9ec4\u5bb6\u6e7e"
    ],
    "wof:name":"Laohuangjiawan",
    "wof:placetype":"locality"
},
  "geometry": {"coordinates":[113.07656,30.14313],"type":"Point"}
}