{
  "type": "Feature",
  "properties": {
    "gn:admin1_code":"07",
    "gn:asciiname":"Bili",
    "gn:cc2":"CN",
    "gn:country_code":"CN",
    "gn:dem":160,
    "gn:feature_class":"P",
    "gn:feature_code":"PPL",
    "gn:name":"Bili",
    "gn:population":0,
    "gn:timezone":"Asia/Shanghai",
    "iso:country":"CN",
    "name:bre_x_preferred":[
        "Bili"
    ],
    "name:ceb_x_preferred":[
        "Bili"
    ],
    "name:fra_x_preferred":[
        "Bili"
    ],
    "name:kat_x_preferred":[
        "\u10d1\u10d8\u10da\u10d8"
    ],
    "name:swe_x_preferred":[
        "Bili"
    ],
    "name:und_x_variant":[
        "Pi-li"
    ],
    "wof:name":"Bili",
    "wof:placetype":"locality"
},
  "geometry": {"coordinates":[119.71917000000001,26.46667],"type":"Point"}
}