{
  "type": "Feature",
  "properties": {
    "gn:admin1_code":"9.0",
    "gn:asciiname":"Lihua",
    "gn:country_code":"CN",
    "gn:dem":40,
    "gn:feature_class":"P",
    "gn:feature_code":"PPL",
    "gn:name":"Lihua",
    "gn:population":0,
    "gn:timezone":"Asia/Shanghai",
    "iso:country":"CN",
    "name:zho_x_preferred":[
        "\u68a8\u94e7"
    ],
    "wof:name":"Lihua",
    "wof:placetype":"locality"
},
  "geometry": {"coordinates":[115.57250000000001,33.61046],"type":"Point"}
}