{
  "type": "Feature",
  "properties": {
    "gn:admin1_code":"6.0",
    "gn:asciiname":"Baojiawanzi",
    "gn:country_code":"CN",
    "gn:dem":2324,
    "gn:feature_class":"P",
    "gn:feature_code":"PPL",
    "gn:name":"Baojiawanzi",
    "gn:population":0,
    "gn:timezone":"Asia/Shanghai",
    "iso:country":"CN",
    "name:und_x_variant":[
        "\u9c8d\u5bb6\u6e7e\u5b50"
    ],
    "wof:name":"Baojiawanzi",
    "wof:placetype":"locality"
},
  "geometry": {"coordinates":[102.74892,35.91211],"type":"Point"}
}