{
  "type": "Feature",
  "properties": {
    "gn:admin1_code":"11.0",
    "gn:asciiname":"Xinmatang",
    "gn:country_code":"CN",
    "gn:dem":149,
    "gn:feature_class":"P",
    "gn:feature_code":"PPL",
    "gn:name":"Xinmatang",
    "gn:population":0,
    "gn:timezone":"Asia/Shanghai",
    "iso:country":"CN",
    "name:zho_x_preferred":[
        "\u65b0\u9ebb\u5858"
    ],
    "wof:name":"Xinmatang",
    "wof:placetype":"locality"
},
  "geometry": {"coordinates":[111.39513999999998,26.36057000000001],"type":"Point"}
}