{
  "type": "Feature",
  "properties": {
    "gn:admin1_code":"21.0",
    "gn:asciiname":"Gangou",
    "gn:country_code":"CN",
    "gn:dem":2159,
    "gn:feature_class":"P",
    "gn:feature_code":"PPL",
    "gn:name":"Gangou",
    "gn:population":0,
    "gn:timezone":"Asia/Shanghai",
    "iso:country":"CN",
    "name:zho_x_preferred":[
        "\u7518\u6c9f"
    ],
    "wof:name":"Gangou",
    "wof:placetype":"locality"
},
  "geometry": {"coordinates":[105.611,36.1185],"type":"Point"}
}