{
  "type": "Feature",
  "properties": {
    "gn:admin1_code":"8.0",
    "gn:asciiname":"Zhanshancun",
    "gn:country_code":"CN",
    "gn:dem":71,
    "gn:feature_class":"P",
    "gn:feature_code":"PPL",
    "gn:name":"Zhanshancun",
    "gn:population":0,
    "gn:timezone":"Asia/Shanghai",
    "iso:country":"CN",
    "name:zho_x_preferred":[
        "\u5360\u5c71\u6751"
    ],
    "wof:name":"Zhanshancun",
    "wof:placetype":"locality"
},
  "geometry": {"coordinates":[131.85497000000001,47.21089],"type":"Point"}
}