{
  "type": "Feature",
  "properties": {
    "gn:admin1_code":"10.0",
    "gn:asciiname":"Beiqing Shiling",
    "gn:country_code":"CN",
    "gn:dem":620,
    "gn:feature_class":"P",
    "gn:feature_code":"PPL",
    "gn:name":"Beiqing Shiling",
    "gn:population":0,
    "gn:timezone":"Asia/Shanghai",
    "iso:country":"CN",
    "name:zho_x_preferred":[
        "\u5317\u9752\u77f3\u5cad"
    ],
    "wof:name":"Beiqing Shiling",
    "wof:placetype":"locality"
},
  "geometry": {"coordinates":[117.43512,40.41278],"type":"Point"}
}