{
  "type": "Feature",
  "properties": {
    "gn:admin1_code":"24.0",
    "gn:asciiname":"Wulongchuan",
    "gn:cc2":"CN",
    "gn:country_code":"CN",
    "gn:dem":1692,
    "gn:feature_class":"P",
    "gn:feature_code":"PPL",
    "gn:name":"Wulongchuan",
    "gn:population":0,
    "gn:timezone":"Asia/Shanghai",
    "iso:country":"CN",
    "name:und_x_variant":[
        "Wu-lung-ch\u2019uan",
        "Wulongchuan"
    ],
    "wof:name":"Wulongchuan",
    "wof:placetype":"locality"
},
  "geometry": {"coordinates":[112.09999999999999,36.61667],"type":"Point"}
}