{
  "type": "Feature",
  "properties": {
    "gn:admin1_code":"26.0",
    "gn:asciiname":"Hezuishang",
    "gn:country_code":"CN",
    "gn:dem":766,
    "gn:feature_class":"P",
    "gn:feature_code":"PPL",
    "gn:name":"Hezuishang",
    "gn:population":0,
    "gn:timezone":"Asia/Shanghai",
    "iso:country":"CN",
    "name:und_x_variant":[
        "\u6cb3\u5480\u4e0a"
    ],
    "wof:name":"Hezuishang",
    "wof:placetype":"locality"
},
  "geometry": {"coordinates":[106.42515,32.90146],"type":"Point"}
}