{
  "type": "Feature",
  "properties": {
    "gn:admin1_code":"12.0",
    "gn:asciiname":"Changcheng",
    "gn:country_code":"CN",
    "gn:dem":97,
    "gn:feature_class":"P",
    "gn:feature_code":"PPL",
    "gn:name":"Changcheng",
    "gn:population":0,
    "gn:timezone":"Asia/Shanghai",
    "iso:country":"CN",
    "name:zho_x_preferred":[
        "Changcheng"
    ],
    "name:zho_x_variant":[
        "\u957f\u57ce"
    ],
    "wof:name":"Changcheng",
    "wof:placetype":"locality"
},
  "geometry": {"coordinates":[114.15062,29.56694],"type":"Point"}
}