{
  "type": "Feature",
  "properties": {
    "gn:admin1_code":"9.0",
    "gn:asciiname":"Dazhouzhuang",
    "gn:country_code":"CN",
    "gn:dem":76,
    "gn:feature_class":"P",
    "gn:feature_code":"PPL",
    "gn:name":"Dazhouzhuang",
    "gn:population":0,
    "gn:timezone":"Asia/Shanghai",
    "iso:country":"CN",
    "name:zho_x_preferred":[
        "\u5927\u5468\u5e84"
    ],
    "wof:name":"Dazhouzhuang",
    "wof:placetype":"locality"
},
  "geometry": {"coordinates":[114.37202000000001,32.7329],"type":"Point"}
}