{
  "type": "Feature",
  "properties": {
    "gn:admin1_code":"32.0",
    "gn:asciiname":"Luobuchong",
    "gn:country_code":"CN",
    "gn:dem":3121,
    "gn:feature_class":"P",
    "gn:feature_code":"PPL",
    "gn:name":"Luobuchong",
    "gn:population":0,
    "gn:timezone":"Asia/Shanghai",
    "iso:country":"CN",
    "name:zho_x_preferred":[
        "\u841d\u535c\u51b2"
    ],
    "wof:name":"Luobuchong",
    "wof:placetype":"locality"
},
  "geometry": {"coordinates":[103.577,32.3634],"type":"Point"}
}