{
  "type": "Feature",
  "properties": {
    "gn:admin1_code":"12.0",
    "gn:asciiname":"Fanjiawan",
    "gn:country_code":"CN",
    "gn:dem":21,
    "gn:feature_class":"P",
    "gn:feature_code":"PPL",
    "gn:name":"Fanjiawan",
    "gn:population":0,
    "gn:timezone":"Asia/Shanghai",
    "iso:country":"CN",
    "name:und_x_variant":[
        "\u8303\u5bb6\u5846"
    ],
    "wof:name":"Fanjiawan",
    "wof:placetype":"locality"
},
  "geometry": {"coordinates":[114.80835,30.63613],"type":"Point"}
}