{
  "type": "Feature",
  "properties": {
    "gn:admin1_code":"1.0",
    "gn:asciiname":"Guanyicun",
    "gn:country_code":"CN",
    "gn:dem":31,
    "gn:feature_class":"P",
    "gn:feature_code":"PPL",
    "gn:name":"Guanyicun",
    "gn:population":0,
    "gn:timezone":"Asia/Shanghai",
    "iso:country":"CN",
    "name:und_x_variant":[
        "Guanyi"
    ],
    "name:zho_x_preferred":[
        "\u9986\u9a7f\u6751"
    ],
    "wof:name":"Guanyicun",
    "wof:placetype":"locality"
},
  "geometry": {"coordinates":[117.13934999999999,31.70754],"type":"Point"}
}