{
  "type": "Feature",
  "properties": {
    "gn:admin1_code":"9.0",
    "gn:asciiname":"Baiguimiao",
    "gn:country_code":"CN",
    "gn:dem":52,
    "gn:feature_class":"P",
    "gn:feature_code":"PPL",
    "gn:name":"Baiguimiao",
    "gn:population":0,
    "gn:timezone":"Asia/Shanghai",
    "iso:country":"CN",
    "name:zho_x_preferred":[
        "\u767d\u572d\u5e99"
    ],
    "wof:name":"Baiguimiao",
    "wof:placetype":"locality"
},
  "geometry": {"coordinates":[114.41719000000001,33.28135],"type":"Point"}
}