{
  "type": "Feature",
  "properties": {
    "gn:admin1_code":"14.0",
    "gn:asciiname":"Luochicun",
    "gn:country_code":"CN",
    "gn:dem":3689,
    "gn:feature_class":"P",
    "gn:feature_code":"PPL",
    "gn:name":"Luochicun",
    "gn:population":0,
    "gn:timezone":"Asia/Urumqi",
    "iso:country":"CN",
    "name:zho_x_preferred":[
        "\u6d1b\u6c60\u6751"
    ],
    "wof:name":"Luochicun",
    "wof:placetype":"locality"
},
  "geometry": {"coordinates":[94.06345,29.97665],"type":"Point"}
}