{
  "type": "Feature",
  "properties": {
    "gn:admin1_code":"32.0",
    "gn:asciiname":"Huangtian",
    "gn:country_code":"CN",
    "gn:dem":1672,
    "gn:feature_class":"P",
    "gn:feature_code":"PPL",
    "gn:name":"Huangtian",
    "gn:population":0,
    "gn:timezone":"Asia/Shanghai",
    "iso:country":"CN",
    "name:zho_x_preferred":[
        "\u8352\u7530"
    ],
    "wof:name":"Huangtian",
    "wof:placetype":"locality"
},
  "geometry": {"coordinates":[101.65779000000001,26.9749],"type":"Point"}
}