{
  "type": "Feature",
  "properties": {
    "gn:admin1_code":"18.0",
    "gn:asciiname":"Xiaotanghe",
    "gn:country_code":"CN",
    "gn:dem":600,
    "gn:feature_class":"P",
    "gn:feature_code":"PPL",
    "gn:name":"Xiaotanghe",
    "gn:population":0,
    "gn:timezone":"Asia/Shanghai",
    "iso:country":"CN",
    "name:zho_x_preferred":[
        "\u5c0f\u5858\u6cb3"
    ],
    "wof:name":"Xiaotanghe",
    "wof:placetype":"locality"
},
  "geometry": {"coordinates":[108.042,27.0602],"type":"Point"}
}