{
  "type": "Feature",
  "properties": {
    "gn:admin1_code":"15.0",
    "gn:asciiname":"Quegou",
    "gn:country_code":"CN",
    "gn:dem":2232,
    "gn:feature_class":"P",
    "gn:feature_code":"PPL",
    "gn:name":"Quegou",
    "gn:population":0,
    "gn:timezone":"Asia/Shanghai",
    "iso:country":"CN",
    "name:und_x_variant":[
        "\u786e\u6c9f"
    ],
    "wof:name":"Quegou",
    "wof:placetype":"locality"
},
  "geometry": {"coordinates":[104.22881,34.13645],"type":"Point"}
}