{
  "type": "Feature",
  "properties": {
    "gn:admin1_code":"10.0",
    "gn:asciiname":"Qingningbu",
    "gn:country_code":"CN",
    "gn:dem":644,
    "gn:feature_class":"P",
    "gn:feature_code":"PPL",
    "gn:name":"Qingningbu",
    "gn:population":0,
    "gn:timezone":"Asia/Shanghai",
    "iso:country":"CN",
    "name:zho_x_preferred":[
        "\u6e05\u5b81\u5821"
    ],
    "wof:name":"Qingningbu",
    "wof:placetype":"locality"
},
  "geometry": {"coordinates":[115.16095,40.39862],"type":"Point"}
}