{
  "type": "Feature",
  "properties": {
    "gn:admin1_code":"11.0",
    "gn:asciiname":"Zhoujia Yuanzi",
    "gn:country_code":"CN",
    "gn:dem":323,
    "gn:feature_class":"P",
    "gn:feature_code":"PPL",
    "gn:name":"Zhoujia Yuanzi",
    "gn:population":0,
    "gn:timezone":"Asia/Shanghai",
    "iso:country":"CN",
    "name:zho_x_preferred":[
        "\u5468\u5bb6\u9662\u5b50"
    ],
    "wof:name":"Zhoujia Yuanzi",
    "wof:placetype":"locality"
},
  "geometry": {"coordinates":[110.54396,27.68125],"type":"Point"}
}