{
  "type": "Feature",
  "properties": {
    "gn:admin1_code":"32.0",
    "gn:asciiname":"Labu",
    "gn:country_code":"CN",
    "gn:dem":1876,
    "gn:feature_class":"P",
    "gn:feature_code":"PPL",
    "gn:name":"Labu",
    "gn:population":0,
    "gn:timezone":"Asia/Shanghai",
    "iso:country":"CN",
    "name:ceb_x_preferred":[
        "Labu"
    ],
    "name:deu_x_preferred":[
        "Labu"
    ],
    "name:msa_x_preferred":[
        "Labu"
    ],
    "name:swe_x_preferred":[
        "Labu"
    ],
    "name:zho_x_preferred":[
        "\u62c9\u5821"
    ],
    "wof:name":"Labu",
    "wof:placetype":"locality"
},
  "geometry": {"coordinates":[102.873,27.1134],"type":"Point"}
}