{
  "type": "Feature",
  "properties": {
    "gn:admin1_code":"19.0",
    "gn:asciiname":"Muyingzi",
    "gn:country_code":"CN",
    "gn:dem":526,
    "gn:feature_class":"P",
    "gn:feature_code":"PPL",
    "gn:name":"Muyingzi",
    "gn:population":0,
    "gn:timezone":"Asia/Shanghai",
    "iso:country":"CN",
    "name:zho_x_preferred":[
        "\u6728\u8425\u5b50"
    ],
    "wof:name":"Muyingzi",
    "wof:placetype":"locality"
},
  "geometry": {"coordinates":[119.43573000000001,41.40325],"type":"Point"}
}