{
  "type": "Feature",
  "properties": {
    "gn:admin1_code":"11.0",
    "gn:asciiname":"Zhubaozhai",
    "gn:country_code":"CN",
    "gn:dem":203,
    "gn:feature_class":"P",
    "gn:feature_code":"PPL",
    "gn:name":"Zhubaozhai",
    "gn:population":0,
    "gn:timezone":"Asia/Shanghai",
    "iso:country":"CN",
    "name:zho_x_preferred":[
        "\u73e0\u5b9d\u5be8"
    ],
    "wof:name":"Zhubaozhai",
    "wof:placetype":"locality"
},
  "geometry": {"coordinates":[109.97208000000001,27.8499],"type":"Point"}
}