{
  "type": "Feature",
  "properties": {
    "gn:admin1_code":"3.0",
    "gn:asciiname":"Ganfang",
    "gn:country_code":"CN",
    "gn:dem":229,
    "gn:feature_class":"P",
    "gn:feature_code":"PPL",
    "gn:name":"Ganfang",
    "gn:population":0,
    "gn:timezone":"Asia/Shanghai",
    "iso:country":"CN",
    "name:und_x_variant":[
        "\u7518\u574a"
    ],
    "wof:name":"Ganfang",
    "wof:placetype":"locality"
},
  "geometry": {"coordinates":[116.31959999999999,27.09837000000001],"type":"Point"}
}