{
  "type": "Feature",
  "properties": {
    "gn:admin1_code":"30.0",
    "gn:asciiname":"Zengcun",
    "gn:country_code":"CN",
    "gn:dem":80,
    "gn:feature_class":"P",
    "gn:feature_code":"PPL",
    "gn:name":"Zengcun",
    "gn:population":0,
    "gn:timezone":"Asia/Shanghai",
    "iso:country":"CN",
    "name:zho_x_preferred":[
        "\u66fe\u6751"
    ],
    "name:zho_x_variant":[
        "\u589e\u6751\u9547"
    ],
    "wof:name":"Zengcun",
    "wof:placetype":"locality"
},
  "geometry": {"coordinates":[111.95681999999999,24.02853],"type":"Point"}
}