{
  "type": "Feature",
  "properties": {
    "gn:admin1_code":"25",
    "gn:asciiname":"Shangqijiayu",
    "gn:country_code":"CN",
    "gn:dem":343,
    "gn:feature_class":"P",
    "gn:feature_code":"PPL",
    "gn:name":"Shangqijiayu",
    "gn:population":0,
    "gn:timezone":"Asia/Shanghai",
    "iso:country":"CN",
    "name:zho_x_preferred":[
        "\u4e0a\u4e93\u5bb6\u5cea"
    ],
    "wof:name":"Shangqijiayu",
    "wof:placetype":"locality"
},
  "geometry": {"coordinates":[117.624,36.117],"type":"Point"}
}