{
  "type": "Feature",
  "properties": {
    "gn:admin1_code":"12.0",
    "gn:asciiname":"Lujiapu",
    "gn:country_code":"CN",
    "gn:dem":34,
    "gn:feature_class":"P",
    "gn:feature_code":"PPL",
    "gn:name":"Lujiapu",
    "gn:population":0,
    "gn:timezone":"Asia/Shanghai",
    "iso:country":"CN",
    "name:zho_x_preferred":[
        "\u8def\u5bb6\u94fa"
    ],
    "wof:name":"Lujiapu",
    "wof:placetype":"locality"
},
  "geometry": {"coordinates":[112.38703999999998,29.68524],"type":"Point"}
}