{
  "type": "Feature",
  "properties": {
    "gn:admin1_code":"8.0",
    "gn:asciiname":"Beifang Erdui",
    "gn:country_code":"CN",
    "gn:dem":333,
    "gn:feature_class":"P",
    "gn:feature_code":"PPLF",
    "gn:name":"Beifang Erdui",
    "gn:population":0,
    "gn:timezone":"Asia/Shanghai",
    "iso:country":"CN",
    "name:zho_x_preferred":[
        "\u5317\u65b9\u4e8c\u961f"
    ],
    "wof:name":"Beifang Erdui",
    "wof:placetype":"locality"
},
  "geometry": {"coordinates":[125.81869,50.57795],"type":"Point"}
}