{
  "type": "Feature",
  "properties": {
    "gn:admin1_code":"19.0",
    "gn:asciiname":"Daxing",
    "gn:country_code":"CN",
    "gn:dem":175,
    "gn:feature_class":"P",
    "gn:feature_code":"PPL",
    "gn:name":"Daxing",
    "gn:population":0,
    "gn:timezone":"Asia/Shanghai",
    "iso:country":"CN",
    "name:und_x_variant":[
        "\u5927\u5174"
    ],
    "name:zho_x_preferred":[
        "\u5927\u5174"
    ],
    "wof:name":"Daxing",
    "wof:placetype":"locality"
},
  "geometry": {"coordinates":[124.2343,40.73628],"type":"Point"}
}