{
  "type": "Feature",
  "properties": {
    "gn:admin1_code":"14.0",
    "gn:asciiname":"Weijiabuwa",
    "gn:country_code":"CN",
    "gn:dem":3962,
    "gn:feature_class":"P",
    "gn:feature_code":"PPL",
    "gn:name":"Weijiabuwa",
    "gn:population":0,
    "gn:timezone":"Asia/Urumqi",
    "iso:country":"CN",
    "name:zho_x_preferred":[
        "\u7ef4\u52a0\u5e03\u74e6"
    ],
    "wof:name":"Weijiabuwa",
    "wof:placetype":"locality"
},
  "geometry": {"coordinates":[98.13573,30.51698],"type":"Point"}
}