{
  "type": "Feature",
  "properties": {
    "gn:country":"CN",
    "gn:fcode":"PPLA3",
    "gn:population":130387,
    "iso:country":"CN",
    "name:und_x_variant":[
        "Wuning"
    ],
    "name:zho_x_preferred":[
        "\u4e1c\u9633"
    ],
    "name:zho_x_variant":[
        "\u4e1c\u9633\u5e02"
    ],
    "qs_pg:aaroncc":"CN",
    "qs_pg:gn_country":"CN",
    "qs_pg:gn_fcode":"PPLA3",
    "qs_pg:gn_pop":130387,
    "qs_pg:name":"\u4e1c\u9633\u5e02",
    "qs_pg:name_adm0":"\u4e2d\u570b",
    "qs_pg:name_adm1":"\u6d59\u6c5f\u7701",
    "qs_pg:photos":2,
    "qs_pg:photos_1k":1,
    "qs_pg:photos_9k":1,
    "qs_pg:photos_9r":1,
    "qs_pg:photos_all":2,
    "qs_pg:photos_sr":1,
    "qs_pg:pop_sr":9,
    "qs_pg:qs_pg_placetype":"localadmin",
    "qs_pg:qs_pg_placetype_gp":"LocalAdmin",
    "qs_pg:woe_adm0":23424781,
    "woe:adm0_id":23424781,
    "woe:name_adm0":"\u4e2d\u570b",
    "woe:name_adm1":"\u6d59\u6c5f\u7701",
    "woe:placetype":"LocalAdmin",
    "wof:name":"\u4e1c\u9633\u5e02",
    "wof:placetype":"localadmin",
    "wof:population":130387
},
  "geometry": {"coordinates":[120.22528,29.26778],"type":"Point"}
}