{
  "type": "Feature",
  "properties": {
    "gn:admin1_code":"10",
    "gn:asciiname":"Langtuozi",
    "gn:country_code":"CN",
    "gn:dem":3,
    "gn:feature_class":"P",
    "gn:feature_code":"PPL",
    "gn:name":"Langtuozi",
    "gn:population":0,
    "gn:timezone":"Asia/Shanghai",
    "iso:country":"CN",
    "name:zho_x_preferred":[
        "\u72fc\u5768\u5b50"
    ],
    "wof:name":"Langtuozi",
    "wof:placetype":"locality"
},
  "geometry": {"coordinates":[117.79900000000001,38.2956],"type":"Point"}
}