{
  "type": "Feature",
  "properties": {
    "gn:admin1_code":"14.0",
    "gn:asciiname":"Wakorruwa",
    "gn:country_code":"CN",
    "gn:dem":4840,
    "gn:feature_class":"P",
    "gn:feature_code":"PPL",
    "gn:name":"Wakorruwa",
    "gn:population":0,
    "gn:timezone":"Asia/Urumqi",
    "iso:country":"CN",
    "name:bod_x_preferred":[
        "Wakorruwa"
    ],
    "name:zho_x_preferred":[
        "Wagaoraowa"
    ],
    "name:zho_x_variant":[
        "\u54c7\u9ad8\u7ed5\u54c7"
    ],
    "wof:name":"Wakorruwa",
    "wof:placetype":"locality"
},
  "geometry": {"coordinates":[97.301,31.601],"type":"Point"}
}