{
  "type": "Feature",
  "properties": {
    "gn:admin1_code":"26.0",
    "gn:asciiname":"Liqucun",
    "gn:country_code":"CN",
    "gn:dem":1055,
    "gn:feature_class":"P",
    "gn:feature_code":"PPL",
    "gn:name":"Liqucun",
    "gn:population":0,
    "gn:timezone":"Asia/Shanghai",
    "iso:country":"CN",
    "name:zho_x_preferred":[
        "\u674e\u6e20\u6751"
    ],
    "wof:name":"Liqucun",
    "wof:placetype":"locality"
},
  "geometry": {"coordinates":[109.62175000000001,36.86461],"type":"Point"}
}