{
  "type": "Feature",
  "properties": {
    "gn:admin1_code":"29.0",
    "gn:asciiname":"Lengdangboqing",
    "gn:country_code":"CN",
    "gn:dem":2383,
    "gn:feature_class":"P",
    "gn:feature_code":"PPL",
    "gn:name":"Lengdangboqing",
    "gn:population":0,
    "gn:timezone":"Asia/Shanghai",
    "iso:country":"CN",
    "name:zho_x_preferred":[
        "\u695e\u5f53\u7c38\u7b90"
    ],
    "wof:name":"Lengdangboqing",
    "wof:placetype":"locality"
},
  "geometry": {"coordinates":[101.039,25.643],"type":"Point"}
}