{
  "type": "Feature",
  "properties": {
    "gn:admin1_code":"30.0",
    "gn:asciiname":"Juzai",
    "gn:country_code":"CN",
    "gn:dem":19,
    "gn:feature_class":"P",
    "gn:feature_code":"PPL",
    "gn:name":"Juzai",
    "gn:population":0,
    "gn:timezone":"Asia/Shanghai",
    "iso:country":"CN",
    "name:zho_x_preferred":[
        "\u6854\u4ed4"
    ],
    "wof:name":"Juzai",
    "wof:placetype":"locality"
},
  "geometry": {"coordinates":[112.90215000000001,22.62552],"type":"Point"}
}