{
  "type": "Feature",
  "properties": {
    "gn:admin1_code":"26.0",
    "gn:asciiname":"Shaojiawan",
    "gn:country_code":"CN",
    "gn:dem":1042,
    "gn:feature_class":"P",
    "gn:feature_code":"PPL",
    "gn:name":"Shaojiawan",
    "gn:population":0,
    "gn:timezone":"Asia/Shanghai",
    "iso:country":"CN",
    "name:und_x_variant":[
        "\u90b5\u5bb6\u6e7e"
    ],
    "wof:name":"Shaojiawan",
    "wof:placetype":"locality"
},
  "geometry": {"coordinates":[106.92752,33.45023],"type":"Point"}
}