{
  "type": "Feature",
  "properties": {
    "gn:admin1_code":"16.0",
    "gn:asciiname":"Xiaojiahao",
    "gn:country_code":"CN",
    "gn:dem":375,
    "gn:feature_class":"P",
    "gn:feature_code":"PPL",
    "gn:name":"Xiaojiahao",
    "gn:population":0,
    "gn:timezone":"Asia/Shanghai",
    "iso:country":"CN",
    "name:zho_x_preferred":[
        "\u5c0f\u52a0\u597d"
    ],
    "wof:name":"Xiaojiahao",
    "wof:placetype":"locality"
},
  "geometry": {"coordinates":[108.211,24.6232],"type":"Point"}
}