{
  "type": "Feature",
  "properties": {
    "gn:admin1_code":"18",
    "gn:asciiname":"Shihuolu",
    "gn:country_code":"CN",
    "gn:dem":932,
    "gn:feature_class":"P",
    "gn:feature_code":"PPL",
    "gn:name":"Shihuolu",
    "gn:population":0,
    "gn:timezone":"Asia/Shanghai",
    "iso:country":"CN",
    "name:zho_x_preferred":[
        "\u77f3\u706b\u7089"
    ],
    "wof:name":"Shihuolu",
    "wof:placetype":"locality"
},
  "geometry": {"coordinates":[107.59699999999999,27.6509],"type":"Point"}
}