{
  "type": "Feature",
  "properties": {
    "gn:admin1_code":"25",
    "gn:asciiname":"Rongzhuang",
    "gn:country_code":"CN",
    "gn:dem":48,
    "gn:feature_class":"P",
    "gn:feature_code":"PPL",
    "gn:name":"Rongzhuang",
    "gn:population":0,
    "gn:timezone":"Asia/Shanghai",
    "iso:country":"CN",
    "name:zho_x_preferred":[
        "\u8363\u5e84"
    ],
    "wof:name":"Rongzhuang",
    "wof:placetype":"locality"
},
  "geometry": {"coordinates":[115.98699999999999,34.7082],"type":"Point"}
}