{
  "type": "Feature",
  "properties": {
    "gn:admin1_code":"8.0",
    "gn:asciiname":"Chagandaobao",
    "gn:country_code":"CN",
    "gn:dem":172,
    "gn:feature_class":"P",
    "gn:feature_code":"PPL",
    "gn:name":"Chagandaobao",
    "gn:population":0,
    "gn:timezone":"Asia/Shanghai",
    "iso:country":"CN",
    "name:zho_x_preferred":[
        "\u67e5\u5e72\u9053\u5b9d"
    ],
    "wof:name":"Chagandaobao",
    "wof:placetype":"locality"
},
  "geometry": {"coordinates":[125.71156000000001,45.8873],"type":"Point"}
}