{
  "type": "Feature",
  "properties": {
    "gn:admin1_code":"07",
    "gn:asciiname":"Xiashi Huangfeng",
    "gn:country_code":"CN",
    "gn:dem":286,
    "gn:feature_class":"P",
    "gn:feature_code":"PPL",
    "gn:name":"Xiashi Huangfeng",
    "gn:population":0,
    "gn:timezone":"Asia/Shanghai",
    "iso:country":"CN",
    "name:zho_x_preferred":[
        "\u4e0b\u77f3\u9ec4\u5cf0"
    ],
    "wof:name":"Xiashi Huangfeng",
    "wof:placetype":"locality"
},
  "geometry": {"coordinates":[116.04911,24.9339],"type":"Point"}
}