{
  "type": "Feature",
  "properties": {
    "gn:admin1_code":"14.0",
    "gn:asciiname":"Zhalaxia",
    "gn:country_code":"CN",
    "gn:dem":4156,
    "gn:feature_class":"P",
    "gn:feature_code":"PPL",
    "gn:name":"Zhalaxia",
    "gn:population":0,
    "gn:timezone":"Asia/Urumqi",
    "iso:country":"CN",
    "name:zho_x_preferred":[
        "\u624e\u62c9\u5477"
    ],
    "wof:name":"Zhalaxia",
    "wof:placetype":"locality"
},
  "geometry": {"coordinates":[98.82603,29.45248],"type":"Point"}
}