{
  "type": "Feature",
  "properties": {
    "gn:admin1_code":"32.0",
    "gn:asciiname":"Gesha",
    "gn:country_code":"CN",
    "gn:dem":3429,
    "gn:feature_class":"P",
    "gn:feature_code":"PPL",
    "gn:name":"Gesha",
    "gn:population":0,
    "gn:timezone":"Asia/Shanghai",
    "iso:country":"CN",
    "name:zho_x_preferred":[
        "\u683c\u6c99"
    ],
    "wof:name":"Gesha",
    "wof:placetype":"locality"
},
  "geometry": {"coordinates":[99.26519999999999,31.5124],"type":"Point"}
}