{
  "type": "Feature",
  "properties": {
    "gn:admin1_code":"32.0",
    "gn:asciiname":"Hualongmen",
    "gn:country_code":"CN",
    "gn:dem":525,
    "gn:feature_class":"P",
    "gn:feature_code":"PPL",
    "gn:name":"Hualongmen",
    "gn:population":0,
    "gn:timezone":"Asia/Shanghai",
    "iso:country":"CN",
    "name:zho_x_preferred":[
        "\u82b1\u9f99\u95e8"
    ],
    "wof:name":"Hualongmen",
    "wof:placetype":"locality"
},
  "geometry": {"coordinates":[104.08774,31.00003],"type":"Point"}
}