{
  "type": "Feature",
  "properties": {
    "gn:admin1_code":"14.0",
    "gn:asciiname":"Dangdacun",
    "gn:country_code":"CN",
    "gn:dem":3913,
    "gn:feature_class":"P",
    "gn:feature_code":"PPL",
    "gn:name":"Dangdacun",
    "gn:population":0,
    "gn:timezone":"Asia/Urumqi",
    "iso:country":"CN",
    "name:zho_x_preferred":[
        "\u5f53\u8fbe\u6751"
    ],
    "wof:name":"Dangdacun",
    "wof:placetype":"locality"
},
  "geometry": {"coordinates":[94.28995999999999,31.6684],"type":"Point"}
}