{
  "type": "Feature",
  "properties": {
    "gn:admin1_code":"11",
    "gn:asciiname":"Shihuayuan",
    "gn:country_code":"CN",
    "gn:dem":374,
    "gn:feature_class":"P",
    "gn:feature_code":"PPL",
    "gn:name":"Shihuayuan",
    "gn:population":0,
    "gn:timezone":"Asia/Shanghai",
    "iso:country":"CN",
    "name:zho_x_preferred":[
        "\u67ff\u82b1\u56ed"
    ],
    "wof:name":"Shihuayuan",
    "wof:placetype":"locality"
},
  "geometry": {"coordinates":[111.01672000000001,27.26938],"type":"Point"}
}