{
  "type": "Feature",
  "properties": {
    "gn:admin1_code":"26.0",
    "gn:asciiname":"Mochakou",
    "gn:country_code":"CN",
    "gn:dem":1243,
    "gn:feature_class":"P",
    "gn:feature_code":"PPL",
    "gn:name":"Mochakou",
    "gn:population":0,
    "gn:timezone":"Asia/Shanghai",
    "iso:country":"CN",
    "name:zho_x_preferred":[
        "\u78e8\u5c94\u53e3"
    ],
    "wof:name":"Mochakou",
    "wof:placetype":"locality"
},
  "geometry": {"coordinates":[109.72566,34.14436],"type":"Point"}
}