{
  "type": "Feature",
  "properties": {
    "gn:admin1_code":"32.0",
    "gn:asciiname":"Yalongjiang",
    "gn:country_code":"CN",
    "gn:dem":1190,
    "gn:feature_class":"P",
    "gn:feature_code":"PPL",
    "gn:name":"Yalongjiang",
    "gn:population":0,
    "gn:timezone":"Asia/Shanghai",
    "iso:country":"CN",
    "name:zho_x_preferred":[
        "\u96c5\u783b\u6c5f"
    ],
    "wof:name":"Yalongjiang",
    "wof:placetype":"locality"
},
  "geometry": {"coordinates":[101.80500000000001,27.0991],"type":"Point"}
}