{
  "type": "Feature",
  "properties": {
    "gn:admin1_code":"1.0",
    "gn:asciiname":"Fo'ancun",
    "gn:country_code":"CN",
    "gn:dem":24,
    "gn:feature_class":"P",
    "gn:feature_code":"PPL",
    "gn:name":"Fo\u2019ancun",
    "gn:population":0,
    "gn:timezone":"Asia/Shanghai",
    "iso:country":"CN",
    "name:und_x_variant":[
        "Fo\u2019ancun"
    ],
    "name:zho_x_preferred":[
        "\u4f5b\u5eb5\u6751"
    ],
    "wof:name":"Fo'ancun",
    "wof:placetype":"locality"
},
  "geometry": {"coordinates":[116.31482,31.9936],"type":"Point"}
}