{
  "type": "Feature",
  "properties": {
    "gn:admin1_code":"12.0",
    "gn:asciiname":"Huachu'ao",
    "gn:country_code":"CN",
    "gn:dem":131,
    "gn:feature_class":"P",
    "gn:feature_code":"PPL",
    "gn:name":"Huachu\u2019ao",
    "gn:population":0,
    "gn:timezone":"Asia/Shanghai",
    "iso:country":"CN",
    "name:und_x_variant":[
        "Huachu\u2019ao"
    ],
    "name:zho_x_preferred":[
        "\u534e\u695a\u5773"
    ],
    "wof:name":"Huachu'ao",
    "wof:placetype":"locality"
},
  "geometry": {"coordinates":[113.99177,29.58053],"type":"Point"}
}