{
  "type": "Feature",
  "properties": {
    "gn:admin1_code":"19.0",
    "gn:asciiname":"Baishagou",
    "gn:country_code":"CN",
    "gn:dem":161,
    "gn:feature_class":"P",
    "gn:feature_code":"PPL",
    "gn:name":"Baishagou",
    "gn:population":0,
    "gn:timezone":"Asia/Shanghai",
    "iso:country":"CN",
    "name:und_x_variant":[
        "\u767d\u6c99\u6c9f"
    ],
    "wof:name":"Baishagou",
    "wof:placetype":"locality"
},
  "geometry": {"coordinates":[122.92637999999999,40.63468],"type":"Point"}
}