{
  "type": "Feature",
  "properties": {
    "gn:admin1_code":"25.0",
    "gn:asciiname":"Patou Zhangjia",
    "gn:country_code":"CN",
    "gn:dem":142,
    "gn:feature_class":"P",
    "gn:feature_code":"PPL",
    "gn:name":"Patou Zhangjia",
    "gn:population":0,
    "gn:timezone":"Asia/Shanghai",
    "iso:country":"CN",
    "name:zho_x_preferred":[
        "\u6252\u5934\u5f20\u5bb6"
    ],
    "wof:name":"Patou Zhangjia",
    "wof:placetype":"locality"
},
  "geometry": {"coordinates":[120.27200999999999,37.1073],"type":"Point"}
}