{
  "type": "Feature",
  "properties": {
    "gn:admin1_code":"10.0",
    "gn:asciiname":"Zhangliji",
    "gn:cc2":"CN",
    "gn:country_code":"CN",
    "gn:dem":67,
    "gn:feature_class":"P",
    "gn:feature_code":"PPL",
    "gn:name":"Zhangliji",
    "gn:population":0,
    "gn:timezone":"Asia/Shanghai",
    "iso:country":"CN",
    "name:und_x_variant":[
        "Chang-li-chi",
        "Zhangliji"
    ],
    "wof:name":"Zhangliji",
    "wof:placetype":"locality"
},
  "geometry": {"coordinates":[114.48999999999999,36.37361],"type":"Point"}
}