{
  "type": "Feature",
  "properties": {
    "gn:admin1_code":"15.0",
    "gn:asciiname":"Caoluwa",
    "gn:country_code":"CN",
    "gn:dem":2056,
    "gn:feature_class":"P",
    "gn:feature_code":"PPL",
    "gn:name":"Caoluwa",
    "gn:population":0,
    "gn:timezone":"Asia/Shanghai",
    "iso:country":"CN",
    "name:zho_x_preferred":[
        "\u8349\u8def\u6d3c"
    ],
    "wof:name":"Caoluwa",
    "wof:placetype":"locality"
},
  "geometry": {"coordinates":[105.127,36.8122],"type":"Point"}
}