{
  "type": "Feature",
  "properties": {
    "gn:admin1_code":"14.0",
    "gn:asciiname":"Rabba",
    "gn:country_code":"CN",
    "gn:dem":4934,
    "gn:feature_class":"P",
    "gn:feature_code":"PPL",
    "gn:name":"Rabba",
    "gn:population":0,
    "gn:timezone":"Asia/Urumqi",
    "iso:country":"CN",
    "name:bod_x_preferred":[
        "Rabba"
    ],
    "name:ceb_x_preferred":[
        "Ar Rabbah"
    ],
    "name:deu_x_preferred":[
        "Rabbat-Moab"
    ],
    "name:fra_x_preferred":[
        "Rabba"
    ],
    "name:nno_x_preferred":[
        "Rabba"
    ],
    "name:pol_x_preferred":[
        "Ar-Rabba"
    ],
    "name:swe_x_preferred":[
        "Rabba"
    ],
    "name:zho_x_preferred":[
        "Reba"
    ],
    "name:zho_x_variant":[
        "\u70ed\u5df4",
        "Zhonglinka Qu",
        "\u4e2d\u6797\u5361\u533a"
    ],
    "wof:name":"Rabba",
    "wof:placetype":"locality"
},
  "geometry": {"coordinates":[97.401,29.601],"type":"Point"}
}