{
  "type": "Feature",
  "properties": {
    "gn:admin1_code":"9.0",
    "gn:asciiname":"Sangshuping",
    "gn:country_code":"CN",
    "gn:dem":456,
    "gn:feature_class":"P",
    "gn:feature_code":"PPL",
    "gn:name":"Sangshuping",
    "gn:population":0,
    "gn:timezone":"Asia/Shanghai",
    "iso:country":"CN",
    "name:und_x_variant":[
        "\u6851\u6811\u576a",
        "Sangshuping"
    ],
    "wof:name":"Sangshuping",
    "wof:placetype":"locality"
},
  "geometry": {"coordinates":[112.10102000000001,33.60684000000001],"type":"Point"}
}