{
  "type": "Feature",
  "properties": {
    "gn:admin1_code":"29.0",
    "gn:asciiname":"Dashuigou",
    "gn:country_code":"CN",
    "gn:dem":1923,
    "gn:feature_class":"P",
    "gn:feature_code":"PPL",
    "gn:name":"Dashuigou",
    "gn:population":0,
    "gn:timezone":"Asia/Shanghai",
    "iso:country":"CN",
    "name:zho_x_preferred":[
        "\u5927\u6c34\u6c9f"
    ],
    "wof:name":"Dashuigou",
    "wof:placetype":"locality"
},
  "geometry": {"coordinates":[98.8436,24.7263],"type":"Point"}
}