{
  "type": "Feature",
  "properties": {
    "gn:admin1_code":"5.0",
    "gn:asciiname":"Chenjia Wobucun",
    "gn:country_code":"CN",
    "gn:dem":216,
    "gn:feature_class":"P",
    "gn:feature_code":"PPL",
    "gn:name":"Chenjia Wobucun",
    "gn:population":0,
    "gn:timezone":"Asia/Shanghai",
    "iso:country":"CN",
    "name:zho_x_preferred":[
        "\u9648\u5bb6\u7a9d\u5821\u6751"
    ],
    "wof:name":"Chenjia Wobucun",
    "wof:placetype":"locality"
},
  "geometry": {"coordinates":[124.67632999999999,43.91124],"type":"Point"}
}