{
  "type": "Feature",
  "properties": {
    "gn:admin1_code":"25.0",
    "gn:asciiname":"Shangliu Lianzhuang",
    "gn:country_code":"CN",
    "gn:dem":112,
    "gn:feature_class":"P",
    "gn:feature_code":"PPL",
    "gn:name":"Shangliu Lianzhuang",
    "gn:population":0,
    "gn:timezone":"Asia/Shanghai",
    "iso:country":"CN",
    "name:zho_x_preferred":[
        "\u4e0a\u67f3\u8fde\u5e84"
    ],
    "wof:name":"Shangliu Lianzhuang",
    "wof:placetype":"locality"
},
  "geometry": {"coordinates":[120.36702,37.094],"type":"Point"}
}