{
  "type": "Feature",
  "properties": {
    "gn:admin1_code":"26.0",
    "gn:asciiname":"Zhuanmiaocun",
    "gn:country_code":"CN",
    "gn:dem":548,
    "gn:feature_class":"P",
    "gn:feature_code":"PPL",
    "gn:name":"Zhuanmiaocun",
    "gn:population":0,
    "gn:timezone":"Asia/Shanghai",
    "iso:country":"CN",
    "name:und_x_variant":[
        "\u7816\u5e99\u6751"
    ],
    "wof:name":"Zhuanmiaocun",
    "wof:placetype":"locality"
},
  "geometry": {"coordinates":[107.54172,33.15702],"type":"Point"}
}