{
  "type": "Feature",
  "properties": {
    "gn:admin1_code":"20",
    "gn:asciiname":"Tara Gol",
    "gn:cc2":"CN",
    "gn:country_code":"CN",
    "gn:dem":1438,
    "gn:feature_class":"P",
    "gn:feature_code":"PPL",
    "gn:name":"Tara Gol",
    "gn:population":0,
    "gn:timezone":"Asia/Shanghai",
    "iso:country":"CN",
    "name:und_x_variant":[
        "Tara Gol Xiang",
        "Tarian Gol",
        "T\u2019a-la-kou",
        "Tara Gol"
    ],
    "wof:name":"Tara Gol",
    "wof:placetype":"locality"
},
  "geometry": {"coordinates":[109.03528,40.08222],"type":"Point"}
}