{
  "type": "Feature",
  "properties": {
    "gn:admin1_code":"21.0",
    "gn:asciiname":"Xianfeng Qidui",
    "gn:country_code":"CN",
    "gn:dem":1093,
    "gn:feature_class":"P",
    "gn:feature_code":"PPLF",
    "gn:name":"Xianfeng Qidui",
    "gn:population":0,
    "gn:timezone":"Asia/Shanghai",
    "iso:country":"CN",
    "name:zho_x_preferred":[
        "\u5148\u950b\u4e03\u961f"
    ],
    "wof:name":"Xianfeng Qidui",
    "wof:placetype":"locality"
},
  "geometry": {"coordinates":[106.777,39.1116],"type":"Point"}
}