{
  "type": "Feature",
  "properties": {
    "gn:admin1_code":"30.0",
    "gn:asciiname":"Qiaoxincun",
    "gn:country_code":"CN",
    "gn:dem":16,
    "gn:feature_class":"P",
    "gn:feature_code":"PPL",
    "gn:name":"Qiaoxincun",
    "gn:population":0,
    "gn:timezone":"Asia/Shanghai",
    "iso:country":"CN",
    "name:zho_x_preferred":[
        "\u6865\u65b0\u6751"
    ],
    "wof:name":"Qiaoxincun",
    "wof:placetype":"locality"
},
  "geometry": {"coordinates":[112.48439999999999,22.51312],"type":"Point"}
}