{
  "type": "Feature",
  "properties": {
    "gn:admin1_code":"1.0",
    "gn:asciiname":"Yong'ancun",
    "gn:country_code":"CN",
    "gn:dem":155,
    "gn:feature_class":"P",
    "gn:feature_code":"PPL",
    "gn:name":"Yong\u2019ancun",
    "gn:population":0,
    "gn:timezone":"Asia/Shanghai",
    "iso:country":"CN",
    "name:und_x_variant":[
        "Yong\u2019ancun"
    ],
    "name:zho_x_preferred":[
        "\u6c38\u5b89\u6751"
    ],
    "wof:name":"Yong'ancun",
    "wof:placetype":"locality"
},
  "geometry": {"coordinates":[117.91939000000001,30.43771],"type":"Point"}
}