{
  "type": "Feature",
  "properties": {
    "gn:admin1_code":"20.0",
    "gn:asciiname":"Beihao",
    "gn:country_code":"CN",
    "gn:dem":1758,
    "gn:feature_class":"P",
    "gn:feature_code":"PPL",
    "gn:name":"Beihao",
    "gn:population":0,
    "gn:timezone":"Asia/Shanghai",
    "iso:country":"CN",
    "name:und_x_variant":[
        "\u5317\u53f7"
    ],
    "wof:name":"Beihao",
    "wof:placetype":"locality"
},
  "geometry": {"coordinates":[113.35107000000001,41.16633],"type":"Point"}
}