{
  "type": "Feature",
  "properties": {
    "gn:admin1_code":"30.0",
    "gn:asciiname":"Chayuan",
    "gn:country_code":"CN",
    "gn:dem":725,
    "gn:feature_class":"P",
    "gn:feature_code":"PPL",
    "gn:name":"Chayuan",
    "gn:population":0,
    "gn:timezone":"Asia/Shanghai",
    "iso:country":"CN",
    "name:zho_x_preferred":[
        "Chayuan"
    ],
    "name:zho_x_variant":[
        "\u8336\u5706"
    ],
    "wof:name":"Chayuan",
    "wof:placetype":"locality"
},
  "geometry": {"coordinates":[113.05361000000001,25.01278],"type":"Point"}
}