{
  "type": "Feature",
  "properties": {
    "gn:admin1_code":"5.0",
    "gn:asciiname":"Qianxishan",
    "gn:country_code":"CN",
    "gn:dem":135,
    "gn:feature_class":"P",
    "gn:feature_code":"PPL",
    "gn:name":"Qianxishan",
    "gn:population":0,
    "gn:timezone":"Asia/Shanghai",
    "iso:country":"CN",
    "name:zho_x_preferred":[
        "\u524d\u897f\u5c71"
    ],
    "wof:name":"Qianxishan",
    "wof:placetype":"locality"
},
  "geometry": {"coordinates":[123.6164,45.11921],"type":"Point"}
}