{
  "type": "Feature",
  "properties": {
    "gn:admin1_code":"11",
    "gn:asciiname":"Pingchong",
    "gn:country_code":"CN",
    "gn:dem":900,
    "gn:feature_class":"P",
    "gn:feature_code":"PPL",
    "gn:name":"Pingchong",
    "gn:population":0,
    "gn:timezone":"Asia/Shanghai",
    "iso:country":"CN",
    "name:zho_x_preferred":[
        "\u576a\u51b2"
    ],
    "wof:name":"Pingchong",
    "wof:placetype":"locality"
},
  "geometry": {"coordinates":[112.3441,25.21885],"type":"Point"}
}