{
  "type": "Feature",
  "properties": {
    "gn:admin1_code":"5.0",
    "gn:asciiname":"Xiaowulantu",
    "gn:country_code":"CN",
    "gn:dem":138,
    "gn:feature_class":"P",
    "gn:feature_code":"PPL",
    "gn:name":"Xiaowulantu",
    "gn:population":0,
    "gn:timezone":"Asia/Shanghai",
    "iso:country":"CN",
    "name:zho_x_preferred":[
        "\u5c0f\u4e4c\u5170\u5410"
    ],
    "wof:name":"Xiaowulantu",
    "wof:placetype":"locality"
},
  "geometry": {"coordinates":[123.76268,46.23348],"type":"Point"}
}