{
  "type": "Feature",
  "properties": {
    "gn:admin1_code":"25",
    "gn:asciiname":"Shagouya",
    "gn:country_code":"CN",
    "gn:dem":94,
    "gn:feature_class":"P",
    "gn:feature_code":"PPL",
    "gn:name":"Shagouya",
    "gn:population":0,
    "gn:timezone":"Asia/Shanghai",
    "iso:country":"CN",
    "name:zho_x_preferred":[
        "\u6c99\u6c9f\u5d16"
    ],
    "wof:name":"Shagouya",
    "wof:placetype":"locality"
},
  "geometry": {"coordinates":[118.17700000000001,35.1241],"type":"Point"}
}