{
  "type": "Feature",
  "properties": {
    "gn:admin1_code":"8.0",
    "gn:asciiname":"Changshou",
    "gn:country_code":"CN",
    "gn:dem":192,
    "gn:feature_class":"P",
    "gn:feature_code":"PPLA4",
    "gn:name":"Changshou",
    "gn:population":0,
    "gn:timezone":"Asia/Shanghai",
    "iso:country":"CN",
    "name:deu_x_preferred":[
        "Changshou"
    ],
    "name:und_x_variant":[
        "Changshou Xiang"
    ],
    "name:zho_x_preferred":[
        "\u957f\u5bff"
    ],
    "name:zho_x_variant":[
        "\u957f\u5bff\u4e61"
    ],
    "wof:name":"Changshou",
    "wof:placetype":"locality"
},
  "geometry": {"coordinates":[127.93293,45.2696],"type":"Point"}
}