{
  "type": "Feature",
  "properties": {
    "gn:admin1_code":"26.0",
    "gn:asciiname":"Tanligou",
    "gn:country_code":"CN",
    "gn:dem":704,
    "gn:feature_class":"P",
    "gn:feature_code":"PPL",
    "gn:name":"Tanligou",
    "gn:population":0,
    "gn:timezone":"Asia/Shanghai",
    "iso:country":"CN",
    "name:und_x_variant":[
        "\u6f6d\u674e\u6c9f"
    ],
    "wof:name":"Tanligou",
    "wof:placetype":"locality"
},
  "geometry": {"coordinates":[107.77857,33.11891],"type":"Point"}
}