{
  "type": "Feature",
  "properties": {
    "gn:admin1_code":"29.0",
    "gn:asciiname":"Mozu",
    "gn:country_code":"CN",
    "gn:dem":2256,
    "gn:feature_class":"P",
    "gn:feature_code":"PPL",
    "gn:name":"Mozu",
    "gn:population":0,
    "gn:timezone":"Asia/Shanghai",
    "iso:country":"CN",
    "name:spa_x_preferred":[
        "Mozu"
    ],
    "name:zho_x_preferred":[
        "\u83ab\u7956"
    ],
    "wof:name":"Mozu",
    "wof:placetype":"locality"
},
  "geometry": {"coordinates":[102.512,25.8862],"type":"Point"}
}