{
  "type": "Feature",
  "properties": {
    "gn:admin1_code":"15.0",
    "gn:asciiname":"Gounao Shangcun",
    "gn:country_code":"CN",
    "gn:dem":1434,
    "gn:feature_class":"P",
    "gn:feature_code":"PPL",
    "gn:name":"Gounao Shangcun",
    "gn:population":0,
    "gn:timezone":"Asia/Shanghai",
    "iso:country":"CN",
    "name:zho_x_preferred":[
        "\u6c9f\u8111\u4e0a\u6751"
    ],
    "wof:name":"Gounao Shangcun",
    "wof:placetype":"locality"
},
  "geometry": {"coordinates":[108.19799999999999,36.0676],"type":"Point"}
}