{
  "type": "Feature",
  "properties": {
    "gn:admin1_code":"10",
    "gn:asciiname":"Shangsihao",
    "gn:country_code":"CN",
    "gn:dem":1103,
    "gn:feature_class":"P",
    "gn:feature_code":"PPLF",
    "gn:name":"Shangsihao",
    "gn:population":0,
    "gn:timezone":"Asia/Shanghai",
    "iso:country":"CN",
    "name:zho_x_preferred":[
        "\u4e0a\u56db\u53f7"
    ],
    "wof:name":"Shangsihao",
    "wof:placetype":"locality"
},
  "geometry": {"coordinates":[117.23026000000002,41.96897],"type":"Point"}
}