{
  "type": "Feature",
  "properties": {
    "gn:admin1_code":"04",
    "gn:asciiname":"Yongfengcun",
    "gn:country_code":"CN",
    "gn:dem":3,
    "gn:feature_class":"P",
    "gn:feature_code":"PPL",
    "gn:name":"Yongfengcun",
    "gn:population":0,
    "gn:timezone":"Asia/Shanghai",
    "iso:country":"CN",
    "name:und_x_variant":[
        "Yongfeng",
        "\u6c38\u4e30",
        "Yongfengcun"
    ],
    "name:zho_x_preferred":[
        "\u6c38\u4e30\u6751"
    ],
    "wof:name":"Yongfengcun",
    "wof:placetype":"locality"
},
  "geometry": {"coordinates":[120.69750999999999,31.86352],"type":"Point"}
}