{
  "type": "Feature",
  "properties": {
    "gn:admin1_code":"6.0",
    "gn:asciiname":"Yidadui",
    "gn:country_code":"CN",
    "gn:dem":2785,
    "gn:feature_class":"P",
    "gn:feature_code":"PPLF",
    "gn:name":"Yidadui",
    "gn:population":0,
    "gn:timezone":"Asia/Urumqi",
    "iso:country":"CN",
    "name:und_x_variant":[
        "\u4e00\u5927\u961f"
    ],
    "wof:name":"Yidadui",
    "wof:placetype":"locality"
},
  "geometry": {"coordinates":[96.49214000000001,36.43483],"type":"Point"}
}