{
  "type": "Feature",
  "properties": {
    "gn:admin1_code":"02",
    "gn:asciiname":"Xialuo",
    "gn:cc2":"CN",
    "gn:country_code":"CN",
    "gn:dem":6,
    "gn:feature_class":"P",
    "gn:feature_code":"PPL",
    "gn:name":"Xialuo",
    "gn:population":0,
    "gn:timezone":"Asia/Shanghai",
    "iso:country":"CN",
    "name:und_x_variant":[
        "Hsia-lou",
        "Xialuo"
    ],
    "wof:name":"Xialuo",
    "wof:placetype":"locality"
},
  "geometry": {"coordinates":[121.46805999999999,28.5625],"type":"Point"}
}