{
  "type": "Feature",
  "properties": {
    "gn:admin1_code":"1.0",
    "gn:asciiname":"Linhucun",
    "gn:country_code":"CN",
    "gn:dem":26,
    "gn:feature_class":"P",
    "gn:feature_code":"PPL",
    "gn:name":"Linhucun",
    "gn:population":0,
    "gn:timezone":"Asia/Shanghai",
    "iso:country":"CN",
    "name:zho_x_preferred":[
        "\u6797\u62a4\u6751"
    ],
    "wof:name":"Linhucun",
    "wof:placetype":"locality"
},
  "geometry": {"coordinates":[116.89821999999999,32.91037],"type":"Point"}
}