{
  "type": "Feature",
  "properties": {
    "gn:admin1_code":"32.0",
    "gn:asciiname":"Gengshiri'a",
    "gn:country_code":"CN",
    "gn:dem":4182,
    "gn:feature_class":"P",
    "gn:feature_code":"PPL",
    "gn:name":"Gengshiri\u2019a",
    "gn:population":0,
    "gn:timezone":"Asia/Shanghai",
    "iso:country":"CN",
    "name:zho_x_preferred":[
        "\u66f4\u53f2\u65e5\u963f"
    ],
    "name:zho_x_variant":[
        "Gengshiri\u2019a"
    ],
    "wof:name":"Gengshiri'a",
    "wof:placetype":"locality"
},
  "geometry": {"coordinates":[97.42703,32.94821],"type":"Point"}
}