{
  "type": "Feature",
  "properties": {
    "gn:admin1_code":"15",
    "gn:asciiname":"Wenquan",
    "gn:country_code":"CN",
    "gn:dem":1722,
    "gn:feature_class":"P",
    "gn:feature_code":"PPL",
    "gn:name":"Wenquan",
    "gn:population":0,
    "gn:timezone":"Asia/Shanghai",
    "iso:country":"CN",
    "name:ceb_x_preferred":[
        "Wenquan"
    ],
    "name:deu_x_preferred":[
        "Wenquan"
    ],
    "name:swe_x_preferred":[
        "Wenquan"
    ],
    "name:zho_x_preferred":[
        "\u6e29\u6cc9"
    ],
    "wof:name":"Wenquan",
    "wof:placetype":"locality"
},
  "geometry": {"coordinates":[105.03888999999999,34.66806],"type":"Point"}
}