{
  "type": "Feature",
  "properties": {
    "gn:admin1_code":"10",
    "gn:asciiname":"Baiyunzhang",
    "gn:country_code":"CN",
    "gn:dem":299,
    "gn:feature_class":"P",
    "gn:feature_code":"PPL",
    "gn:name":"Baiyunzhang",
    "gn:population":0,
    "gn:timezone":"Asia/Shanghai",
    "iso:country":"CN",
    "name:zho_x_preferred":[
        "\u767d\u4e91\u638c"
    ],
    "wof:name":"Baiyunzhang",
    "wof:placetype":"locality"
},
  "geometry": {"coordinates":[114.253,37.4624],"type":"Point"}
}