{
  "type": "Feature",
  "properties": {
    "gn:admin1_code":"14.0",
    "gn:asciiname":"Gongqulangbacun",
    "gn:country_code":"CN",
    "gn:dem":4537,
    "gn:feature_class":"P",
    "gn:feature_code":"PPL",
    "gn:name":"Gongqulangbacun",
    "gn:population":0,
    "gn:timezone":"Asia/Urumqi",
    "iso:country":"CN",
    "name:zho_x_preferred":[
        "\u8d21\u66f2\u6717\u5df4\u6751"
    ],
    "wof:name":"Gongqulangbacun",
    "wof:placetype":"locality"
},
  "geometry": {"coordinates":[91.44995,31.4679],"type":"Point"}
}