{
  "type": "Feature",
  "properties": {
    "gn:admin1_code":"16.0",
    "gn:asciiname":"Pingshan",
    "gn:country_code":"CN",
    "gn:dem":77,
    "gn:feature_class":"P",
    "gn:feature_code":"PPL",
    "gn:name":"Pingshan",
    "gn:population":0,
    "gn:timezone":"Asia/Shanghai",
    "iso:country":"CN",
    "name:ceb_x_preferred":[
        "Pingshan"
    ],
    "name:deu_x_preferred":[
        "Pingshan"
    ],
    "name:fra_x_preferred":[
        "Pingshan"
    ],
    "name:mlg_x_preferred":[
        "Pingshan"
    ],
    "name:nor_x_preferred":[
        "Pingshan"
    ],
    "name:rus_x_preferred":[
        "\u041f\u0438\u043d\u0448\u0430\u043d\u044c"
    ],
    "name:swe_x_preferred":[
        "Pingshan"
    ],
    "name:zho_x_preferred":[
        "\u5e73\u5c71"
    ],
    "wof:name":"Pingshan",
    "wof:placetype":"locality"
},
  "geometry": {"coordinates":[110.988,23.7369],"type":"Point"}
}