{
  "type": "Feature",
  "properties": {
    "gn:admin1_code":"3.0",
    "gn:asciiname":"Shuangxi",
    "gn:country_code":"CN",
    "gn:dem":279,
    "gn:feature_class":"P",
    "gn:feature_code":"PPL",
    "gn:name":"Shuangxi",
    "gn:population":0,
    "gn:timezone":"Asia/Shanghai",
    "iso:country":"CN",
    "name:zho_x_preferred":[
        "\u53cc\u6eaa"
    ],
    "wof:name":"Shuangxi",
    "wof:placetype":"locality"
},
  "geometry": {"coordinates":[117.79535,28.72801],"type":"Point"}
}