{
  "type": "Feature",
  "properties": {
    "gn:admin1_code":"11.0",
    "gn:asciiname":"Batijie",
    "gn:country_code":"CN",
    "gn:dem":924,
    "gn:feature_class":"P",
    "gn:feature_code":"PPL",
    "gn:name":"Batijie",
    "gn:population":0,
    "gn:timezone":"Asia/Shanghai",
    "iso:country":"CN",
    "name:zho_x_preferred":[
        "\u6252\u68af\u754c"
    ],
    "wof:name":"Batijie",
    "wof:placetype":"locality"
},
  "geometry": {"coordinates":[109.767,29.5481],"type":"Point"}
}