{
  "type": "Feature",
  "properties": {
    "gn:admin1_code":"25",
    "gn:asciiname":"Houchawancun",
    "gn:country_code":"CN",
    "gn:dem":29,
    "gn:feature_class":"P",
    "gn:feature_code":"PPL",
    "gn:name":"Houchawancun",
    "gn:population":0,
    "gn:timezone":"Asia/Shanghai",
    "iso:country":"CN",
    "name:und_x_variant":[
        "Houchawan",
        "Houchawancun"
    ],
    "name:zho_x_preferred":[
        "\u540e\u5c94\u6e7e"
    ],
    "name:zho_x_variant":[
        "\u540e\u5c94\u6e7e\u6751"
    ],
    "wof:name":"Houchawancun",
    "wof:placetype":"locality"
},
  "geometry": {"coordinates":[120.28505,36.00809],"type":"Point"}
}