{
  "type": "Feature",
  "properties": {
    "gn:admin1_code":"25",
    "gn:asciiname":"Suanliuzhuang",
    "gn:country_code":"CN",
    "gn:dem":55,
    "gn:feature_class":"P",
    "gn:feature_code":"PPL",
    "gn:name":"Suanliuzhuang",
    "gn:population":0,
    "gn:timezone":"Asia/Shanghai",
    "iso:country":"CN",
    "name:zho_x_preferred":[
        "\u849c\u5218\u5e84"
    ],
    "wof:name":"Suanliuzhuang",
    "wof:placetype":"locality"
},
  "geometry": {"coordinates":[115.386,35.02],"type":"Point"}
}