{
  "type": "Feature",
  "properties": {
    "gn:admin1_code":"3.0",
    "gn:asciiname":"Pengfang Zhoujia",
    "gn:country_code":"CN",
    "gn:dem":31,
    "gn:feature_class":"P",
    "gn:feature_code":"PPL",
    "gn:name":"Pengfang Zhoujia",
    "gn:population":0,
    "gn:timezone":"Asia/Shanghai",
    "iso:country":"CN",
    "name:und_x_variant":[
        "\u5f6d\u574a\u5468\u5bb6"
    ],
    "wof:name":"Pengfang Zhoujia",
    "wof:placetype":"locality"
},
  "geometry": {"coordinates":[117.09511999999999,29.21815],"type":"Point"}
}