{
  "type": "Feature",
  "properties": {
    "gn:admin1_code":"18",
    "gn:asciiname":"Fashe",
    "gn:country_code":"CN",
    "gn:dem":1207,
    "gn:feature_class":"P",
    "gn:feature_code":"PPL",
    "gn:name":"Fashe",
    "gn:population":0,
    "gn:timezone":"Asia/Shanghai",
    "iso:country":"CN",
    "wof:name":"Fashe",
    "wof:placetype":"locality"
},
  "geometry": {"coordinates":[104.96666999999999,26.16667],"type":"Point"}
}