{
  "type": "Feature",
  "properties": {
    "gn:admin1_code":"11.0",
    "gn:asciiname":"Yangjia Yuanzi",
    "gn:country_code":"CN",
    "gn:dem":235,
    "gn:feature_class":"P",
    "gn:feature_code":"PPL",
    "gn:name":"Yangjia Yuanzi",
    "gn:population":0,
    "gn:timezone":"Asia/Shanghai",
    "iso:country":"CN",
    "name:zho_x_preferred":[
        "Yangjia Yuanzi"
    ],
    "name:zho_x_variant":[
        "\u6768\u5bb6\u9662\u5b50"
    ],
    "wof:name":"Yangjia Yuanzi",
    "wof:placetype":"locality"
},
  "geometry": {"coordinates":[111.12193000000001,29.73991],"type":"Point"}
}