{
  "type": "Feature",
  "properties": {
    "gn:admin1_code":"32.0",
    "gn:asciiname":"Tiantai",
    "gn:country_code":"CN",
    "gn:dem":668,
    "gn:feature_class":"P",
    "gn:feature_code":"PPL",
    "gn:name":"Tiantai",
    "gn:population":0,
    "gn:timezone":"Asia/Shanghai",
    "iso:country":"CN",
    "name:cat_x_preferred":[
        "Budisme Tiantai"
    ],
    "name:deu_x_preferred":[
        "Tiantai zong"
    ],
    "name:est_x_preferred":[
        "Tiantai"
    ],
    "name:eus_x_preferred":[
        "Tiantai"
    ],
    "name:fas_x_preferred":[
        "\u062a\u06cc\u0627\u0646\u062a\u0627\u06cc"
    ],
    "name:fin_x_preferred":[
        "Tiantai"
    ],
    "name:fra_x_preferred":[
        "Tiantai"
    ],
    "name:hun_x_preferred":[
        "Tientaj"
    ],
    "name:ind_x_preferred":[
        "Tiantai"
    ],
    "name:ita_x_preferred":[
        "Buddhismo Ti\u0101nt\u00e1i"
    ],
    "name:jpn_x_preferred":[
        "\u5929\u53f0\u5b97"
    ],
    "name:kor_x_preferred":[
        "\ucc9c\ud0dc\uc885"
    ],
    "name:nor_x_preferred":[
        "Tiantai"
    ],
    "name:pol_x_preferred":[
        "Tiantai"
    ],
    "name:por_x_preferred":[
        "Tiantai"
    ],
    "name:rus_x_preferred":[
        "\u0422\u044f\u043d\u044c\u0442\u0430\u0439"
    ],
    "name:srp_x_preferred":[
        "Tiantai"
    ],
    "name:swe_x_preferred":[
        "Tiantai"
    ],
    "name:tha_x_preferred":[
        "\u0e40\u0e17\u0e35\u0e22\u0e19\u0e44\u0e16"
    ],
    "name:tur_x_preferred":[
        "Tiantai"
    ],
    "name:wuu_x_preferred":[
        "\u5929\u53f0\u5b97"
    ],
    "name:zho_x_preferred":[
        "\u5929\u53f0"
    ],
    "name:zho_x_variant":[
        "\u5929\u53f0\u5b97"
    ],
    "wof:name":"Tiantai",
    "wof:placetype":"locality"
},
  "geometry": {"coordinates":[105.593,31.9367],"type":"Point"}
}