{
  "type": "Feature",
  "properties": {
    "gn:admin1_code":"14.0",
    "gn:asciiname":"Benla",
    "gn:country_code":"CN",
    "gn:dem":4319,
    "gn:feature_class":"P",
    "gn:feature_code":"PPL",
    "gn:name":"Benla",
    "gn:population":0,
    "gn:timezone":"Asia/Urumqi",
    "iso:country":"CN",
    "name:zho_x_preferred":[
        "\u672c\u62c9"
    ],
    "wof:name":"Benla",
    "wof:placetype":"locality"
},
  "geometry": {"coordinates":[91.18628,30.49651],"type":"Point"}
}