{
  "type": "Feature",
  "properties": {
    "gn:admin1_code":"10.0",
    "gn:asciiname":"Zhangtai",
    "gn:cc2":"CN",
    "gn:country_code":"CN",
    "gn:dem":32,
    "gn:feature_class":"P",
    "gn:feature_code":"PPL",
    "gn:name":"Zhangtai",
    "gn:population":0,
    "gn:timezone":"Asia/Shanghai",
    "iso:country":"CN",
    "name:und_x_variant":[
        "Ta-chang-t\u2019ai",
        "Chang-t\u2019ai",
        "Zhangtai"
    ],
    "wof:name":"Zhangtai",
    "wof:placetype":"locality"
},
  "geometry": {"coordinates":[115.30833,37.13556],"type":"Point"}
}