{
  "type": "Feature",
  "properties": {
    "gn:admin1_code":"8.0",
    "gn:asciiname":"Pu'an",
    "gn:country_code":"CN",
    "gn:dem":163,
    "gn:feature_class":"P",
    "gn:feature_code":"PPL",
    "gn:name":"Pu\u2019an",
    "gn:population":0,
    "gn:timezone":"Asia/Shanghai",
    "iso:country":"CN",
    "name:zho_x_preferred":[
        "Pu\u2019an"
    ],
    "name:zho_x_variant":[
        "\u666e\u5b89"
    ],
    "wof:name":"Pu'an",
    "wof:placetype":"locality"
},
  "geometry": {"coordinates":[127.97623,45.8321],"type":"Point"}
}