{
  "type": "Feature",
  "properties": {
    "gn:admin1_code":"12.0",
    "gn:asciiname":"Xiaojiamiao",
    "gn:country_code":"CN",
    "gn:dem":77,
    "gn:feature_class":"P",
    "gn:feature_code":"PPL",
    "gn:name":"Xiaojiamiao",
    "gn:population":0,
    "gn:timezone":"Asia/Shanghai",
    "iso:country":"CN",
    "name:zho_x_preferred":[
        "Xiaojiamiao"
    ],
    "name:zho_x_variant":[
        "\u8096\u5bb6\u5e99"
    ],
    "wof:name":"Xiaojiamiao",
    "wof:placetype":"locality"
},
  "geometry": {"coordinates":[111.75988999999998,30.56499],"type":"Point"}
}