{
  "type": "Feature",
  "properties": {
    "gn:admin1_code":"1.0",
    "gn:asciiname":"Duxicun",
    "gn:country_code":"CN",
    "gn:dem":34,
    "gn:feature_class":"P",
    "gn:feature_code":"PPL",
    "gn:name":"Duxicun",
    "gn:population":0,
    "gn:timezone":"Asia/Shanghai",
    "iso:country":"CN",
    "name:zho_x_preferred":[
        "\u675c\u6eaa\u6751"
    ],
    "wof:name":"Duxicun",
    "wof:placetype":"locality"
},
  "geometry": {"coordinates":[116.24985,30.14304000000001],"type":"Point"}
}