{
  "type": "Feature",
  "properties": {
    "gn:admin1_code":"29.0",
    "gn:asciiname":"Huoshaoqing",
    "gn:country_code":"CN",
    "gn:dem":2088,
    "gn:feature_class":"P",
    "gn:feature_code":"PPL",
    "gn:name":"Huoshaoqing",
    "gn:population":0,
    "gn:timezone":"Asia/Shanghai",
    "iso:country":"CN",
    "name:zho_x_preferred":[
        "\u706b\u70e7\u7b90"
    ],
    "wof:name":"Huoshaoqing",
    "wof:placetype":"locality"
},
  "geometry": {"coordinates":[103.681,25.3901],"type":"Point"}
}