{
  "type": "Feature",
  "properties": {
    "gn:admin1_code":"21.0",
    "gn:asciiname":"Shaojiaquan",
    "gn:country_code":"CN",
    "gn:dem":1308,
    "gn:feature_class":"P",
    "gn:feature_code":"PPL",
    "gn:name":"Shaojiaquan",
    "gn:population":0,
    "gn:timezone":"Asia/Shanghai",
    "iso:country":"CN",
    "name:zho_x_preferred":[
        "\u90b5\u5bb6\u5708"
    ],
    "wof:name":"Shaojiaquan",
    "wof:placetype":"locality"
},
  "geometry": {"coordinates":[106.593,37.6782],"type":"Point"}
}