{
  "type": "Feature",
  "properties": {
    "gn:admin1_code":"12.0",
    "gn:asciiname":"Zhaojiawan",
    "gn:country_code":"CN",
    "gn:dem":57,
    "gn:feature_class":"P",
    "gn:feature_code":"PPL",
    "gn:name":"Zhaojiawan",
    "gn:population":0,
    "gn:timezone":"Asia/Shanghai",
    "iso:country":"CN",
    "name:und_x_variant":[
        "\u8d75\u5bb6\u5846"
    ],
    "wof:name":"Zhaojiawan",
    "wof:placetype":"locality"
},
  "geometry": {"coordinates":[115.18339,30.45312],"type":"Point"}
}