{
  "type": "Feature",
  "properties": {
    "gn:admin1_code":"33.0",
    "gn:asciiname":"Xianglu",
    "gn:country_code":"CN",
    "gn:dem":816,
    "gn:feature_class":"P",
    "gn:feature_code":"PPL",
    "gn:name":"Xianglu",
    "gn:population":0,
    "gn:timezone":"Asia/Shanghai",
    "iso:country":"CN",
    "name:zho_x_preferred":[
        "\u9999\u7089"
    ],
    "wof:name":"Xianglu",
    "wof:placetype":"locality"
},
  "geometry": {"coordinates":[108.32546000000001,30.89129],"type":"Point"}
}