{
  "type": "Feature",
  "properties": {
    "gn:admin1_code":"32.0",
    "gn:asciiname":"Renzhu",
    "gn:country_code":"CN",
    "gn:dem":3923,
    "gn:feature_class":"P",
    "gn:feature_code":"PPL",
    "gn:name":"Renzhu",
    "gn:population":0,
    "gn:timezone":"Asia/Shanghai",
    "iso:country":"CN",
    "name:zho_x_preferred":[
        "\u4ec1\u795d"
    ],
    "wof:name":"Renzhu",
    "wof:placetype":"locality"
},
  "geometry": {"coordinates":[101.672,29.5779],"type":"Point"}
}