{
  "type": "Feature",
  "properties": {
    "gn:admin1_code":"29.0",
    "gn:asciiname":"Jinfeng Yakou",
    "gn:country_code":"CN",
    "gn:dem":2894,
    "gn:feature_class":"P",
    "gn:feature_code":"PPL",
    "gn:name":"Jinfeng Yakou",
    "gn:population":0,
    "gn:timezone":"Asia/Shanghai",
    "iso:country":"CN",
    "name:zho_x_preferred":[
        "\u7d27\u98ce\u57ad\u53e3"
    ],
    "wof:name":"Jinfeng Yakou",
    "wof:placetype":"locality"
},
  "geometry": {"coordinates":[103.50700000000001,27.6626],"type":"Point"}
}