{
  "type": "Feature",
  "properties": {
    "gn:admin1_code":"5.0",
    "gn:asciiname":"Wudaocha",
    "gn:country_code":"CN",
    "gn:dem":772,
    "gn:feature_class":"P",
    "gn:feature_code":"PPL",
    "gn:name":"Wudaocha",
    "gn:population":0,
    "gn:timezone":"Asia/Shanghai",
    "iso:country":"CN",
    "name:und_x_variant":[
        "\u4e94\u9053\u5c94"
    ],
    "wof:name":"Wudaocha",
    "wof:placetype":"locality"
},
  "geometry": {"coordinates":[126.29640000000001,41.69492],"type":"Point"}
}