{
  "type": "Feature",
  "properties": {
    "gn:admin1_code":"1.0",
    "gn:asciiname":"Changchongcun",
    "gn:country_code":"CN",
    "gn:dem":44,
    "gn:feature_class":"P",
    "gn:feature_code":"PPL",
    "gn:name":"Changchongcun",
    "gn:population":0,
    "gn:timezone":"Asia/Shanghai",
    "iso:country":"CN",
    "name:zho_x_preferred":[
        "\u957f\u51b2\u6751"
    ],
    "wof:name":"Changchongcun",
    "wof:placetype":"locality"
},
  "geometry": {"coordinates":[116.69687,31.40559],"type":"Point"}
}