{
  "type": "Feature",
  "properties": {
    "gn:admin1_code":"3.0",
    "gn:asciiname":"Yaopinggang",
    "gn:country_code":"CN",
    "gn:dem":217,
    "gn:feature_class":"P",
    "gn:feature_code":"PPL",
    "gn:name":"Yaopinggang",
    "gn:population":0,
    "gn:timezone":"Asia/Shanghai",
    "iso:country":"CN",
    "name:und_x_variant":[
        "\u59da\u576a\u6e2f"
    ],
    "wof:name":"Yaopinggang",
    "wof:placetype":"locality"
},
  "geometry": {"coordinates":[114.20108999999999,28.94214],"type":"Point"}
}