{
  "type": "Feature",
  "properties": {
    "gn:admin1_code":"11.0",
    "gn:asciiname":"Guanchangping",
    "gn:country_code":"CN",
    "gn:dem":147,
    "gn:feature_class":"P",
    "gn:feature_code":"PPL",
    "gn:name":"Guanchangping",
    "gn:population":0,
    "gn:timezone":"Asia/Shanghai",
    "iso:country":"CN",
    "name:zho_x_preferred":[
        "Guanchangping"
    ],
    "name:zho_x_variant":[
        "\u5b98\u573a\u576a"
    ],
    "wof:name":"Guanchangping",
    "wof:placetype":"locality"
},
  "geometry": {"coordinates":[111.19757,29.35772],"type":"Point"}
}