{
  "type": "Feature",
  "properties": {
    "gn:admin1_code":"26.0",
    "gn:asciiname":"Zhaowan",
    "gn:cc2":"CN",
    "gn:country_code":"CN",
    "gn:dem":527,
    "gn:feature_class":"P",
    "gn:feature_code":"PPL",
    "gn:name":"Zhaowan",
    "gn:population":0,
    "gn:timezone":"Asia/Shanghai",
    "iso:country":"CN",
    "name:und_x_variant":[
        "Chao-chia-wan",
        "Chao-wan",
        "Zhaowan"
    ],
    "wof:name":"Zhaowan",
    "wof:placetype":"locality"
},
  "geometry": {"coordinates":[109.14583,32.99610999999999],"type":"Point"}
}