{
  "type": "Feature",
  "properties": {
    "gn:admin1_code":"30.0",
    "gn:asciiname":"Beikengcun",
    "gn:country_code":"CN",
    "gn:dem":30,
    "gn:feature_class":"P",
    "gn:feature_code":"PPL",
    "gn:name":"Beikengcun",
    "gn:population":0,
    "gn:timezone":"Asia/Shanghai",
    "iso:country":"CN",
    "name:zho_x_preferred":[
        "\u9642\u5751\u6751"
    ],
    "wof:name":"Beikengcun",
    "wof:placetype":"locality"
},
  "geometry": {"coordinates":[113.10120999999999,23.58489],"type":"Point"}
}