{
  "type": "Feature",
  "properties": {
    "gn:admin1_code":"14.0",
    "gn:asciiname":"Yimitong",
    "gn:country_code":"CN",
    "gn:dem":4129,
    "gn:feature_class":"P",
    "gn:feature_code":"PPL",
    "gn:name":"Yimitong",
    "gn:population":0,
    "gn:timezone":"Asia/Urumqi",
    "iso:country":"CN",
    "name:zho_x_preferred":[
        "\u76ca\u7c73\u75db"
    ],
    "wof:name":"Yimitong",
    "wof:placetype":"locality"
},
  "geometry": {"coordinates":[97.40759,30.15523],"type":"Point"}
}