{
  "type": "Feature",
  "properties": {
    "gn:admin1_code":"30.0",
    "gn:asciiname":"Yetiancun",
    "gn:country_code":"CN",
    "gn:dem":175,
    "gn:feature_class":"P",
    "gn:feature_code":"PPL",
    "gn:name":"Yetiancun",
    "gn:population":0,
    "gn:timezone":"Asia/Shanghai",
    "iso:country":"CN",
    "name:zho_x_preferred":[
        "\u53f6\u7530\u6751"
    ],
    "wof:name":"Yetiancun",
    "wof:placetype":"locality"
},
  "geometry": {"coordinates":[116.05983000000001,23.99687],"type":"Point"}
}