{
  "type": "Feature",
  "properties": {
    "gn:admin1_code":"16.0",
    "gn:asciiname":"Xiangcaoping",
    "gn:country_code":"CN",
    "gn:dem":850,
    "gn:feature_class":"P",
    "gn:feature_code":"PPL",
    "gn:name":"Xiangcaoping",
    "gn:population":0,
    "gn:timezone":"Asia/Shanghai",
    "iso:country":"CN",
    "name:zho_x_preferred":[
        "\u9999\u8349\u576a"
    ],
    "wof:name":"Xiangcaoping",
    "wof:placetype":"locality"
},
  "geometry": {"coordinates":[111.187,24.7794],"type":"Point"}
}