{
  "type": "Feature",
  "properties": {
    "gn:admin1_code":"29.0",
    "gn:asciiname":"Doutankou",
    "gn:country_code":"CN",
    "gn:dem":1001,
    "gn:feature_class":"P",
    "gn:feature_code":"PPL",
    "gn:name":"Doutankou",
    "gn:population":0,
    "gn:timezone":"Asia/Shanghai",
    "iso:country":"CN",
    "name:zho_x_preferred":[
        "\u9661\u6ee9\u53e3"
    ],
    "wof:name":"Doutankou",
    "wof:placetype":"locality"
},
  "geometry": {"coordinates":[103.23,27.153],"type":"Point"}
}