{
  "type": "Feature",
  "properties": {
    "gn:admin1_code":"2.0",
    "gn:asciiname":"Zhilin",
    "gn:country_code":"CN",
    "gn:dem":486,
    "gn:feature_class":"P",
    "gn:feature_code":"PPL",
    "gn:name":"Zhilin",
    "gn:population":0,
    "gn:timezone":"Asia/Shanghai",
    "iso:country":"CN",
    "name:zho_x_preferred":[
        "\u690d\u6797"
    ],
    "wof:name":"Zhilin",
    "wof:placetype":"locality"
},
  "geometry": {"coordinates":[120.78901999999999,29.25337],"type":"Point"}
}