{
  "type": "Feature",
  "properties": {
    "gn:admin1_code":"14.0",
    "gn:asciiname":"Tongga",
    "gn:country_code":"CN",
    "gn:dem":4820,
    "gn:feature_class":"P",
    "gn:feature_code":"PPLF",
    "gn:name":"Tongga",
    "gn:population":0,
    "gn:timezone":"Asia/Urumqi",
    "iso:country":"CN",
    "name:bod_x_preferred":[
        "Tongga"
    ],
    "name:zho_x_preferred":[
        "\u901a\u560e"
    ],
    "wof:name":"Tongga",
    "wof:placetype":"locality"
},
  "geometry": {"coordinates":[90.908,29.608],"type":"Point"}
}