{
  "type": "Feature",
  "properties": {
    "gn:admin1_code":"3.0",
    "gn:asciiname":"Longwangge",
    "gn:country_code":"CN",
    "gn:dem":196,
    "gn:feature_class":"P",
    "gn:feature_code":"PPL",
    "gn:name":"Longwangge",
    "gn:population":0,
    "gn:timezone":"Asia/Shanghai",
    "iso:country":"CN",
    "name:und_x_variant":[
        "\u9f99\u738b\u9601"
    ],
    "wof:name":"Longwangge",
    "wof:placetype":"locality"
},
  "geometry": {"coordinates":[115.56816000000001,26.70056],"type":"Point"}
}