{
  "type": "Feature",
  "properties": {
    "gn:admin1_code":"14.0",
    "gn:asciiname":"Duiwa",
    "gn:country_code":"CN",
    "gn:dem":3599,
    "gn:feature_class":"P",
    "gn:feature_code":"PPL",
    "gn:name":"Duiwa",
    "gn:population":0,
    "gn:timezone":"Asia/Urumqi",
    "iso:country":"CN",
    "name:zho_x_preferred":[
        "\u5bf9\u74e6"
    ],
    "wof:name":"Duiwa",
    "wof:placetype":"locality"
},
  "geometry": {"coordinates":[98.81358,29.28239],"type":"Point"}
}