{
  "type": "Feature",
  "properties": {
    "gn:admin1_code":"29.0",
    "gn:asciiname":"Ladiancun",
    "gn:country_code":"CN",
    "gn:dem":968,
    "gn:feature_class":"P",
    "gn:feature_code":"PPL",
    "gn:name":"Ladiancun",
    "gn:population":0,
    "gn:timezone":"Asia/Shanghai",
    "iso:country":"CN",
    "name:zho_x_preferred":[
        "\u814a\u7538\u6751"
    ],
    "wof:name":"Ladiancun",
    "wof:placetype":"locality"
},
  "geometry": {"coordinates":[101.874,25.9459],"type":"Point"}
}