{
  "type": "Feature",
  "properties": {
    "gn:admin1_code":"11.0",
    "gn:asciiname":"Suoyichong",
    "gn:country_code":"CN",
    "gn:dem":420,
    "gn:feature_class":"P",
    "gn:feature_code":"PPL",
    "gn:name":"Suoyichong",
    "gn:population":0,
    "gn:timezone":"Asia/Shanghai",
    "iso:country":"CN",
    "name:zho_x_preferred":[
        "\u84d1\u8863\u51b2"
    ],
    "wof:name":"Suoyichong",
    "wof:placetype":"locality"
},
  "geometry": {"coordinates":[109.53312,26.71272],"type":"Point"}
}