{
  "type": "Feature",
  "properties": {
    "gn:admin1_code":"15.0",
    "gn:asciiname":"Liuhe",
    "gn:country_code":"CN",
    "gn:dem":1222,
    "gn:feature_class":"P",
    "gn:feature_code":"PPL",
    "gn:name":"Liuhe",
    "gn:population":0,
    "gn:timezone":"Asia/Shanghai",
    "iso:country":"CN",
    "name:ceb_x_preferred":[
        "Liuhe"
    ],
    "name:deu_x_preferred":[
        "Liuhe"
    ],
    "name:zho_x_preferred":[
        "\u5218\u6cb3"
    ],
    "wof:name":"Liuhe",
    "wof:placetype":"locality"
},
  "geometry": {"coordinates":[105.02048000000001,33.82771],"type":"Point"}
}