{
  "type": "Feature",
  "properties": {
    "gn:admin1_code":"15.0",
    "gn:asciiname":"Weijitan",
    "gn:country_code":"CN",
    "gn:dem":2740,
    "gn:feature_class":"P",
    "gn:feature_code":"PPL",
    "gn:name":"Weijitan",
    "gn:population":0,
    "gn:timezone":"Asia/Shanghai",
    "iso:country":"CN",
    "name:zho_x_preferred":[
        "\u7ef4\u82a8\u6ee9"
    ],
    "wof:name":"Weijitan",
    "wof:placetype":"locality"
},
  "geometry": {"coordinates":[102.968,36.9745],"type":"Point"}
}