{
  "type": "Feature",
  "properties": {
    "gn:admin1_code":"10",
    "gn:asciiname":"Taiziying",
    "gn:cc2":"CN",
    "gn:country_code":"CN",
    "gn:dem":1218,
    "gn:feature_class":"P",
    "gn:feature_code":"PPL",
    "gn:name":"Taiziying",
    "gn:population":0,
    "gn:timezone":"Asia/Shanghai",
    "iso:country":"CN",
    "name:und_x_variant":[
        "T\u2019ai-tzu-ying",
        "Taiziying"
    ],
    "wof:name":"Taiziying",
    "wof:placetype":"locality"
},
  "geometry": {"coordinates":[116.51667,41.75],"type":"Point"}
}