{
  "type": "Feature",
  "properties": {
    "gn:admin1_code":"7.0",
    "gn:asciiname":"Dianyang",
    "gn:country_code":"CN",
    "gn:dem":589,
    "gn:feature_class":"P",
    "gn:feature_code":"PPL",
    "gn:name":"Dianyang",
    "gn:population":0,
    "gn:timezone":"Asia/Shanghai",
    "iso:country":"CN",
    "name:zho_x_preferred":[
        "\u70b9\u6d0b"
    ],
    "wof:name":"Dianyang",
    "wof:placetype":"locality"
},
  "geometry": {"coordinates":[119.2094,26.30724],"type":"Point"}
}