{
  "type": "Feature",
  "properties": {
    "gn:admin1_code":"30.0",
    "gn:asciiname":"Yingbu",
    "gn:country_code":"CN",
    "gn:dem":3,
    "gn:feature_class":"P",
    "gn:feature_code":"PPL",
    "gn:name":"Yingbu",
    "gn:population":0,
    "gn:timezone":"Asia/Shanghai",
    "iso:country":"CN",
    "name:zho_x_preferred":[
        "\u786c\u6b65"
    ],
    "wof:name":"Yingbu",
    "wof:placetype":"locality"
},
  "geometry": {"coordinates":[112.41074,22.07949],"type":"Point"}
}