{
  "type": "Feature",
  "properties": {
    "gn:admin1_code":"7.0",
    "gn:asciiname":"Tangqueli",
    "gn:country_code":"CN",
    "gn:dem":232,
    "gn:feature_class":"P",
    "gn:feature_code":"PPL",
    "gn:name":"Tangqueli",
    "gn:population":0,
    "gn:timezone":"Asia/Shanghai",
    "iso:country":"CN",
    "name:zho_x_preferred":[
        "\u5858\u57c6\u91cc"
    ],
    "wof:name":"Tangqueli",
    "wof:placetype":"locality"
},
  "geometry": {"coordinates":[116.63122,24.73678],"type":"Point"}
}