{
  "type": "Feature",
  "properties": {
    "gn:admin1_code":"12.0",
    "gn:asciiname":"Zhubasi",
    "gn:country_code":"CN",
    "gn:dem":956,
    "gn:feature_class":"P",
    "gn:feature_code":"PPL",
    "gn:name":"Zhubasi",
    "gn:population":0,
    "gn:timezone":"Asia/Shanghai",
    "iso:country":"CN",
    "name:zho_x_preferred":[
        "\u7af9\u6252\u5bfa"
    ],
    "wof:name":"Zhubasi",
    "wof:placetype":"locality"
},
  "geometry": {"coordinates":[110.74542,33.1245],"type":"Point"}
}