{
  "type": "Feature",
  "properties": {
    "gn:admin1_code":"30",
    "gn:asciiname":"Yangtianhu",
    "gn:country_code":"CN",
    "gn:dem":400,
    "gn:feature_class":"P",
    "gn:feature_code":"PPL",
    "gn:name":"Yangtianhu",
    "gn:population":0,
    "gn:timezone":"Asia/Shanghai",
    "iso:country":"CN",
    "name:zho_x_preferred":[
        "\u4ef0\u5929\u6e56"
    ],
    "wof:name":"Yangtianhu",
    "wof:placetype":"locality"
},
  "geometry": {"coordinates":[116.48857,24.48465],"type":"Point"}
}