{
  "type": "Feature",
  "properties": {
    "gn:admin1_code":"4.0",
    "gn:asciiname":"Duanshan",
    "gn:country_code":"CN",
    "gn:dem":9,
    "gn:feature_class":"P",
    "gn:feature_code":"PPL",
    "gn:name":"Duanshan",
    "gn:population":0,
    "gn:timezone":"Asia/Shanghai",
    "iso:country":"CN",
    "name:zho_x_preferred":[
        "\u65ad\u5c71"
    ],
    "wof:name":"Duanshan",
    "wof:placetype":"locality"
},
  "geometry": {"coordinates":[119.30113,31.49604],"type":"Point"}
}