{
  "type": "Feature",
  "properties": {
    "gn:admin1_code":"22.0",
    "gn:asciiname":"Xuzhuangzicun",
    "gn:country_code":"CN",
    "gn:dem":41,
    "gn:feature_class":"P",
    "gn:feature_code":"PPL",
    "gn:name":"Xuzhuangzicun",
    "gn:population":0,
    "gn:timezone":"Asia/Shanghai",
    "iso:country":"CN",
    "name:zho_x_preferred":[
        "\u8bb8\u5e84\u5b50\u6751"
    ],
    "wof:name":"Xuzhuangzicun",
    "wof:placetype":"locality"
},
  "geometry": {"coordinates":[116.16609,39.65249],"type":"Point"}
}