{
  "type": "Feature",
  "properties": {
    "gn:admin1_code":"30",
    "gn:asciiname":"Changtangkeng",
    "gn:country_code":"CN",
    "gn:dem":49,
    "gn:feature_class":"P",
    "gn:feature_code":"PPL",
    "gn:name":"Changtangkeng",
    "gn:population":0,
    "gn:timezone":"Asia/Urumqi",
    "iso:country":"CN",
    "name:zho_x_preferred":[
        "\u957f\u5858\u5751"
    ],
    "wof:name":"Changtangkeng",
    "wof:placetype":"locality"
},
  "geometry": {"coordinates":[110.89999,21.93701],"type":"Point"}
}