{
  "type": "Feature",
  "properties": {
    "gn:admin1_code":"16.0",
    "gn:asciiname":"Gaotun",
    "gn:country_code":"CN",
    "gn:dem":358,
    "gn:feature_class":"P",
    "gn:feature_code":"PPL",
    "gn:name":"Gaotun",
    "gn:population":0,
    "gn:timezone":"Asia/Shanghai",
    "iso:country":"CN",
    "name:zho_x_preferred":[
        "\u544a\u5c6f"
    ],
    "wof:name":"Gaotun",
    "wof:placetype":"locality"
},
  "geometry": {"coordinates":[107.084,24.2987],"type":"Point"}
}