{
  "type": "Feature",
  "properties": {
    "gn:admin1_code":"9",
    "gn:asciiname":"Nangoucun Qianjie",
    "gn:country_code":"CN",
    "gn:dem":54,
    "gn:feature_class":"P",
    "gn:feature_code":"PPL",
    "gn:name":"Nangoucun Qianjie",
    "gn:population":0,
    "gn:timezone":"Asia/Shanghai",
    "iso:country":"CN",
    "name:zho_x_preferred":[
        "\u5357\u6c9f\u6751\u524d\u8857"
    ],
    "wof:name":"Nangoucun Qianjie",
    "wof:placetype":"locality"
},
  "geometry": {"coordinates":[114.89700000000001,36.0859],"type":"Point"}
}