{
  "type": "Feature",
  "properties": {
    "gn:admin1_code":"18",
    "gn:asciiname":"Laogoudong",
    "gn:country_code":"CN",
    "gn:dem":2263,
    "gn:feature_class":"P",
    "gn:feature_code":"PPL",
    "gn:name":"Laogoudong",
    "gn:population":0,
    "gn:timezone":"Asia/Shanghai",
    "iso:country":"CN",
    "name:zho_x_preferred":[
        "\u8001\u72d7\u6d1e"
    ],
    "wof:name":"Laogoudong",
    "wof:placetype":"locality"
},
  "geometry": {"coordinates":[104.407,27.0503],"type":"Point"}
}