{
  "type": "Feature",
  "properties": {
    "gn:admin1_code":"11.0",
    "gn:asciiname":"Fengshandian",
    "gn:country_code":"CN",
    "gn:dem":328,
    "gn:feature_class":"P",
    "gn:feature_code":"PPL",
    "gn:name":"Fengshandian",
    "gn:population":0,
    "gn:timezone":"Asia/Shanghai",
    "iso:country":"CN",
    "name:zho_x_preferred":[
        "\u67ab\u5c71\u6bbf"
    ],
    "wof:name":"Fengshandian",
    "wof:placetype":"locality"
},
  "geometry": {"coordinates":[110.67945,27.20797],"type":"Point"}
}