{
  "type": "Feature",
  "properties": {
    "gn:admin1_code":"32.0",
    "gn:asciiname":"Aotian",
    "gn:country_code":"CN",
    "gn:dem":1139,
    "gn:feature_class":"P",
    "gn:feature_code":"PPL",
    "gn:name":"Aotian",
    "gn:population":0,
    "gn:timezone":"Asia/Shanghai",
    "iso:country":"CN",
    "name:zho_x_preferred":[
        "\u5773\u7530"
    ],
    "wof:name":"Aotian",
    "wof:placetype":"locality"
},
  "geometry": {"coordinates":[103.78400000000001,28.6154],"type":"Point"}
}