{
  "type": "Feature",
  "properties": {
    "gn:admin1_code":"19.0",
    "gn:asciiname":"Suijiabu",
    "gn:country_code":"CN",
    "gn:dem":112,
    "gn:feature_class":"P",
    "gn:feature_code":"PPL",
    "gn:name":"Suijiabu",
    "gn:population":0,
    "gn:timezone":"Asia/Shanghai",
    "iso:country":"CN",
    "name:und_x_variant":[
        "Suijiabao",
        "\u968f\u5bb6\u5821",
        "Suijiabu"
    ],
    "name:zho_x_preferred":[
        "\u968f\u5bb6\u5821"
    ],
    "wof:name":"Suijiabu",
    "wof:placetype":"locality"
},
  "geometry": {"coordinates":[124.83108,40.49263],"type":"Point"}
}