{
  "type": "Feature",
  "properties": {
    "gn:admin1_code":"07",
    "gn:asciiname":"Xiaotaixi",
    "gn:country_code":"CN",
    "gn:dem":339,
    "gn:feature_class":"P",
    "gn:feature_code":"PPL",
    "gn:name":"Xiaotaixi",
    "gn:population":0,
    "gn:timezone":"Asia/Shanghai",
    "iso:country":"CN",
    "name:zho_x_preferred":[
        "\u5c0f\u82d4\u6eaa"
    ],
    "wof:name":"Xiaotaixi",
    "wof:placetype":"locality"
},
  "geometry": {"coordinates":[117.17278,25.9625],"type":"Point"}
}