{
  "type": "Feature",
  "properties": {
    "gn:admin1_code":"16.0",
    "gn:asciiname":"Longdu",
    "gn:country_code":"CN",
    "gn:dem":93,
    "gn:feature_class":"P",
    "gn:feature_code":"PPL",
    "gn:name":"Longdu",
    "gn:population":0,
    "gn:timezone":"Asia/Shanghai",
    "iso:country":"CN",
    "name:fas_x_preferred":[
        "\u0644\u0648\u0646\u06af\u062f\u0648"
    ],
    "name:zho_x_preferred":[
        "\u9f99\u6e21"
    ],
    "name:zho_x_variant":[
        "\u9686\u90fd\u9547"
    ],
    "wof:name":"Longdu",
    "wof:placetype":"locality"
},
  "geometry": {"coordinates":[109.774,24.3115],"type":"Point"}
}