{
  "type": "Feature",
  "properties": {
    "gn:admin1_code":"29.0",
    "gn:asciiname":"Da'oudi",
    "gn:country_code":"CN",
    "gn:dem":2274,
    "gn:feature_class":"P",
    "gn:feature_code":"PPL",
    "gn:name":"Da\u2019oudi",
    "gn:population":0,
    "gn:timezone":"Asia/Shanghai",
    "iso:country":"CN",
    "name:und_x_variant":[
        "Da\u2019oudi"
    ],
    "name:zho_x_preferred":[
        "\u5927\u6b27\u5e95"
    ],
    "wof:name":"Da'oudi",
    "wof:placetype":"locality"
},
  "geometry": {"coordinates":[99.4114,26.2798],"type":"Point"}
}