{
  "type": "Feature",
  "properties": {
    "gn:admin1_code":"18.0",
    "gn:asciiname":"Xiazhaiping",
    "gn:country_code":"CN",
    "gn:dem":449,
    "gn:feature_class":"P",
    "gn:feature_code":"PPL",
    "gn:name":"Xiazhaiping",
    "gn:population":0,
    "gn:timezone":"Asia/Shanghai",
    "iso:country":"CN",
    "name:zho_x_preferred":[
        "\u4e0b\u5be8\u5e73"
    ],
    "wof:name":"Xiazhaiping",
    "wof:placetype":"locality"
},
  "geometry": {"coordinates":[107.82299999999999,25.3485],"type":"Point"}
}