{
  "type": "Feature",
  "properties": {
    "gn:admin1_code":"13.0",
    "gn:asciiname":"Wuru Mudou",
    "gn:country_code":"CN",
    "gn:dem":3434,
    "gn:feature_class":"P",
    "gn:feature_code":"PPL",
    "gn:name":"Wuru Mudou",
    "gn:population":0,
    "gn:timezone":"Asia/Shanghai",
    "iso:country":"CN",
    "name:und_x_variant":[
        "\u4e4c\u5982\u6728\u90fd"
    ],
    "wof:name":"Wuru Mudou",
    "wof:placetype":"locality"
},
  "geometry": {"coordinates":[76.06841999999997,38.33416],"type":"Point"}
}