{
  "type": "Feature",
  "properties": {
    "gn:admin1_code":"32.0",
    "gn:asciiname":"Shichang",
    "gn:country_code":"CN",
    "gn:dem":314,
    "gn:feature_class":"P",
    "gn:feature_code":"PPL",
    "gn:name":"Shichang",
    "gn:population":0,
    "gn:timezone":"Asia/Shanghai",
    "iso:country":"CN",
    "name:zho_x_preferred":[
        "\u77f3\u957f"
    ],
    "wof:name":"Shichang",
    "wof:placetype":"locality"
},
  "geometry": {"coordinates":[105.309,30.5901],"type":"Point"}
}