{
  "type": "Feature",
  "properties": {
    "gn:admin1_code":"19.0",
    "gn:asciiname":"Gujiazicun",
    "gn:country_code":"CN",
    "gn:dem":247,
    "gn:feature_class":"P",
    "gn:feature_code":"PPL",
    "gn:name":"Gujiazicun",
    "gn:population":0,
    "gn:timezone":"Asia/Shanghai",
    "iso:country":"CN",
    "name:zho_x_preferred":[
        "\u53e4\u5bb6\u5b50\u6751"
    ],
    "wof:name":"Gujiazicun",
    "wof:placetype":"locality"
},
  "geometry": {"coordinates":[123.54774,41.01999],"type":"Point"}
}