{
  "type": "Feature",
  "properties": {
    "gn:admin1_code":"29.0",
    "gn:asciiname":"Meijiaying",
    "gn:country_code":"CN",
    "gn:dem":1961,
    "gn:feature_class":"P",
    "gn:feature_code":"PPL",
    "gn:name":"Meijiaying",
    "gn:population":0,
    "gn:timezone":"Asia/Shanghai",
    "iso:country":"CN",
    "name:zho_x_preferred":[
        "\u6885\u5bb6\u8425"
    ],
    "wof:name":"Meijiaying",
    "wof:placetype":"locality"
},
  "geometry": {"coordinates":[103.742,27.3984],"type":"Point"}
}