{
  "type": "Feature",
  "properties": {
    "gn:admin1_code":"7",
    "gn:asciiname":"Chilou",
    "gn:country_code":"CN",
    "gn:dem":251,
    "gn:feature_class":"P",
    "gn:feature_code":"PPL",
    "gn:name":"Chilou",
    "gn:population":0,
    "gn:timezone":"Asia/Shanghai",
    "iso:country":"CN",
    "name:und_x_variant":[
        "\u8d64\u697c"
    ],
    "name:zho_x_preferred":[
        "\u8d64\u697c"
    ],
    "wof:name":"Chilou",
    "wof:placetype":"locality"
},
  "geometry": {"coordinates":[117.375,23.97556],"type":"Point"}
}