{
  "type": "Feature",
  "properties": {
    "gn:admin1_code":"14.0",
    "gn:asciiname":"Toimai",
    "gn:country_code":"CN",
    "gn:dem":4660,
    "gn:feature_class":"P",
    "gn:feature_code":"PPL",
    "gn:name":"Toimai",
    "gn:population":0,
    "gn:timezone":"Asia/Urumqi",
    "iso:country":"CN",
    "name:bod_x_preferred":[
        "Toimai"
    ],
    "name:zho_x_preferred":[
        "Tuimei"
    ],
    "name:zho_x_variant":[
        "\u9000\u7f8e",
        "Duoxiong Gongshe",
        "\u591a\u96c4\u516c\u793e"
    ],
    "wof:name":"Toimai",
    "wof:placetype":"locality"
},
  "geometry": {"coordinates":[87.301,29.301],"type":"Point"}
}