{
  "type": "Feature",
  "properties": {
    "gn:admin1_code":"1.0",
    "gn:asciiname":"Banziqiao",
    "gn:country_code":"CN",
    "gn:dem":87,
    "gn:feature_class":"P",
    "gn:feature_code":"PPL",
    "gn:name":"Banziqiao",
    "gn:population":0,
    "gn:timezone":"Asia/Shanghai",
    "iso:country":"CN",
    "name:zho_x_preferred":[
        "Banziqiao"
    ],
    "name:zho_x_variant":[
        "\u677f\u5b50\u6865"
    ],
    "wof:name":"Banziqiao",
    "wof:placetype":"locality"
},
  "geometry": {"coordinates":[119.23681000000001,30.83725],"type":"Point"}
}