{
  "type": "Feature",
  "properties": {
    "gn:admin1_code":"20.0",
    "gn:asciiname":"Nankunqian",
    "gn:country_code":"CN",
    "gn:dem":173,
    "gn:feature_class":"P",
    "gn:feature_code":"PPL",
    "gn:name":"Nankunqian",
    "gn:population":0,
    "gn:timezone":"Asia/Shanghai",
    "iso:country":"CN",
    "name:zho_x_preferred":[
        "\u5357\u5764\u6d45"
    ],
    "wof:name":"Nankunqian",
    "wof:placetype":"locality"
},
  "geometry": {"coordinates":[124.45283999999999,48.18309],"type":"Point"}
}