{
  "type": "Feature",
  "properties": {
    "gn:admin1_code":"26.0",
    "gn:asciiname":"Huangmaogou",
    "gn:country_code":"CN",
    "gn:dem":729,
    "gn:feature_class":"P",
    "gn:feature_code":"PPL",
    "gn:name":"Huangmaogou",
    "gn:population":0,
    "gn:timezone":"Asia/Shanghai",
    "iso:country":"CN",
    "name:zho_x_preferred":[
        "\u9ec4\u732b\u6c9f"
    ],
    "wof:name":"Huangmaogou",
    "wof:placetype":"locality"
},
  "geometry": {"coordinates":[110.99006,33.35302],"type":"Point"}
}