{
  "type": "Feature",
  "properties": {
    "gn:admin1_code":"9.0",
    "gn:asciiname":"Bianzhai",
    "gn:country_code":"CN",
    "gn:dem":64,
    "gn:feature_class":"P",
    "gn:feature_code":"PPL",
    "gn:name":"Bianzhai",
    "gn:population":0,
    "gn:timezone":"Asia/Shanghai",
    "iso:country":"CN",
    "name:zho_x_preferred":[
        "\u6c74\u5be8"
    ],
    "wof:name":"Bianzhai",
    "wof:placetype":"locality"
},
  "geometry": {"coordinates":[114.56071,34.26479],"type":"Point"}
}