{
  "type": "Feature",
  "properties": {
    "gn:admin1_code":"30.0",
    "gn:asciiname":"Xichen",
    "gn:country_code":"CN",
    "gn:dem":322,
    "gn:feature_class":"P",
    "gn:feature_code":"PPL",
    "gn:name":"Xichen",
    "gn:population":0,
    "gn:timezone":"Asia/Shanghai",
    "iso:country":"CN",
    "name:zho_x_preferred":[
        "\u7ec6\u9648"
    ],
    "wof:name":"Xichen",
    "wof:placetype":"locality"
},
  "geometry": {"coordinates":[113.71532000000001,24.44062000000001],"type":"Point"}
}