{
  "type": "Feature",
  "properties": {
    "gn:admin1_code":"7.0",
    "gn:asciiname":"Wudongshe",
    "gn:country_code":"CN",
    "gn:dem":528,
    "gn:feature_class":"P",
    "gn:feature_code":"PPL",
    "gn:name":"Wudongshe",
    "gn:population":0,
    "gn:timezone":"Asia/Shanghai",
    "iso:country":"CN",
    "name:und_x_variant":[
        "\u543e\u4e1c\u756c"
    ],
    "wof:name":"Wudongshe",
    "wof:placetype":"locality"
},
  "geometry": {"coordinates":[116.94814,26.59595],"type":"Point"}
}