{
  "type": "Feature",
  "properties": {
    "gn:admin1_code":"18.0",
    "gn:asciiname":"Maoyan",
    "gn:country_code":"CN",
    "gn:dem":588,
    "gn:feature_class":"P",
    "gn:feature_code":"PPL",
    "gn:name":"Maoyan",
    "gn:population":0,
    "gn:timezone":"Asia/Shanghai",
    "iso:country":"CN",
    "name:zho_x_preferred":[
        "\u6bdb\u5830"
    ],
    "wof:name":"Maoyan",
    "wof:placetype":"locality"
},
  "geometry": {"coordinates":[109.07899999999999,28.1703],"type":"Point"}
}