{
  "type": "Feature",
  "properties": {
    "gn:admin1_code":"12.0",
    "gn:asciiname":"Miaohu",
    "gn:country_code":"CN",
    "gn:dem":30,
    "gn:feature_class":"P",
    "gn:feature_code":"PPL",
    "gn:name":"Miaohu",
    "gn:population":0,
    "gn:timezone":"Asia/Shanghai",
    "iso:country":"CN",
    "name:eng_x_historical":[
        "Miao hu"
    ],
    "name:eng_x_preferred":[
        "Miao hu"
    ],
    "name:zho_x_preferred":[
        "\u82d7\u6e56"
    ],
    "wof:name":"Miaohu",
    "wof:placetype":"locality"
},
  "geometry": {"coordinates":[113.97085,30.65957],"type":"Point"}
}