{
  "type": "Feature",
  "properties": {
    "gn:admin1_code":"12.0",
    "gn:asciiname":"Dongzhong",
    "gn:country_code":"CN",
    "gn:dem":32,
    "gn:feature_class":"P",
    "gn:feature_code":"PPLA4",
    "gn:name":"Dongzhong",
    "gn:population":0,
    "gn:timezone":"Asia/Shanghai",
    "iso:country":"CN",
    "name:und_x_variant":[
        "Dongzhong Zhen"
    ],
    "name:zho_x_preferred":[
        "\u578c\u51a2"
    ],
    "name:zho_x_variant":[
        "\u578c\u51a2\u9547"
    ],
    "wof:name":"Dongzhong",
    "wof:placetype":"locality"
},
  "geometry": {"coordinates":[113.43086,30.77392],"type":"Point"}
}