{
  "type": "Feature",
  "properties": {
    "gn:admin1_code":"14.0",
    "gn:asciiname":"Mengang",
    "gn:country_code":"CN",
    "gn:dem":4777,
    "gn:feature_class":"P",
    "gn:feature_code":"PPL",
    "gn:name":"Mengang",
    "gn:population":0,
    "gn:timezone":"Asia/Urumqi",
    "iso:country":"CN",
    "name:fra_x_preferred":[
        "Mengang"
    ],
    "name:ita_x_preferred":[
        "Mengang"
    ],
    "name:msa_x_preferred":[
        "Mengang"
    ],
    "name:spa_x_preferred":[
        "Mengang"
    ],
    "name:zho_x_preferred":[
        "\u4eec\u7f38"
    ],
    "wof:name":"Mengang",
    "wof:placetype":"locality"
},
  "geometry": {"coordinates":[85.2968,30.7625],"type":"Point"}
}