{
  "type": "Feature",
  "properties": {
    "gn:admin1_code":"15.0",
    "gn:asciiname":"Xia'ershui",
    "gn:country_code":"CN",
    "gn:dem":2643,
    "gn:feature_class":"P",
    "gn:feature_code":"PPL",
    "gn:name":"Xia\u2019ershui",
    "gn:population":0,
    "gn:timezone":"Asia/Shanghai",
    "iso:country":"CN",
    "name:und_x_variant":[
        "Xia\u2019ershui"
    ],
    "name:zho_x_preferred":[
        "\u7856\u513f\u6c34"
    ],
    "wof:name":"Xia'ershui",
    "wof:placetype":"locality"
},
  "geometry": {"coordinates":[103.623,37.049],"type":"Point"}
}