{
  "type": "Feature",
  "properties": {
    "gn:admin1_code":"9.0",
    "gn:asciiname":"Dianxing",
    "gn:country_code":"CN",
    "gn:dem":39,
    "gn:feature_class":"P",
    "gn:feature_code":"PPL",
    "gn:name":"Dianxing",
    "gn:population":0,
    "gn:timezone":"Asia/Shanghai",
    "iso:country":"CN",
    "name:zho_x_preferred":[
        "\u4f43\u884c"
    ],
    "wof:name":"Dianxing",
    "wof:placetype":"locality"
},
  "geometry": {"coordinates":[115.77813999999999,32.20209000000001],"type":"Point"}
}