{
  "type": "Feature",
  "properties": {
    "gn:admin1_code":"24.0",
    "gn:asciiname":"Yaozhuocun",
    "gn:country_code":"CN",
    "gn:dem":489,
    "gn:feature_class":"P",
    "gn:feature_code":"PPL",
    "gn:name":"Yaozhuocun",
    "gn:population":0,
    "gn:timezone":"Asia/Shanghai",
    "iso:country":"CN",
    "name:zho_x_preferred":[
        "\u59da\u5353\u6751"
    ],
    "wof:name":"Yaozhuocun",
    "wof:placetype":"locality"
},
  "geometry": {"coordinates":[110.37944,35.11122],"type":"Point"}
}