{
  "type": "Feature",
  "properties": {
    "gn:admin1_code":"29.0",
    "gn:asciiname":"Yingmenkou",
    "gn:country_code":"CN",
    "gn:dem":2098,
    "gn:feature_class":"P",
    "gn:feature_code":"PPL",
    "gn:name":"Yingmenkou",
    "gn:population":0,
    "gn:timezone":"Asia/Shanghai",
    "iso:country":"CN",
    "name:zho_x_preferred":[
        "\u8425\u95e8\u53e3"
    ],
    "wof:name":"Yingmenkou",
    "wof:placetype":"locality"
},
  "geometry": {"coordinates":[101.06100000000001,26.574],"type":"Point"}
}