{
  "type": "Feature",
  "properties": {
    "gn:admin1_code":"11.0",
    "gn:asciiname":"Zhumaqiao",
    "gn:country_code":"CN",
    "gn:dem":256,
    "gn:feature_class":"P",
    "gn:feature_code":"PPL",
    "gn:name":"Zhumaqiao",
    "gn:population":0,
    "gn:timezone":"Asia/Shanghai",
    "iso:country":"CN",
    "name:zho_x_preferred":[
        "\u9a7b\u9a6c\u6865"
    ],
    "wof:name":"Zhumaqiao",
    "wof:placetype":"locality"
},
  "geometry": {"coordinates":[111.61242,27.16601],"type":"Point"}
}