{
  "type": "Feature",
  "properties": {
    "gn:admin1_code":"9.0",
    "gn:asciiname":"Wanzihe",
    "gn:country_code":"CN",
    "gn:dem":233,
    "gn:feature_class":"P",
    "gn:feature_code":"PPL",
    "gn:name":"Wanzihe",
    "gn:population":0,
    "gn:timezone":"Asia/Shanghai",
    "iso:country":"CN",
    "name:zho_x_preferred":[
        "\u6e7e\u5b50\u6cb3"
    ],
    "wof:name":"Wanzihe",
    "wof:placetype":"locality"
},
  "geometry": {"coordinates":[113.37214,34.50380999999999],"type":"Point"}
}