{
  "type": "Feature",
  "properties": {
    "gn:admin1_code":"32.0",
    "gn:asciiname":"Yangjiaba",
    "gn:country_code":"CN",
    "gn:dem":448,
    "gn:feature_class":"P",
    "gn:feature_code":"PPL",
    "gn:name":"Yangjiaba",
    "gn:population":0,
    "gn:timezone":"Asia/Shanghai",
    "iso:country":"CN",
    "name:zho_x_preferred":[
        "\u6768\u5bb6\u575d"
    ],
    "wof:name":"Yangjiaba",
    "wof:placetype":"locality"
},
  "geometry": {"coordinates":[107.85599999999999,31.1252],"type":"Point"}
}