{
  "type": "Feature",
  "properties": {
    "gn:admin1_code":"7.0",
    "gn:asciiname":"Jiansancun",
    "gn:country_code":"CN",
    "gn:dem":353,
    "gn:feature_class":"P",
    "gn:feature_code":"PPL",
    "gn:name":"Jiansancun",
    "gn:population":0,
    "gn:timezone":"Asia/Shanghai",
    "iso:country":"CN",
    "name:zho_x_preferred":[
        "\u5efa\u4e09\u6751"
    ],
    "wof:name":"Jiansancun",
    "wof:placetype":"locality"
},
  "geometry": {"coordinates":[116.97085,24.29845],"type":"Point"}
}