{
  "type": "Feature",
  "properties": {
    "gn:admin1_code":"30",
    "gn:asciiname":"Qunjing",
    "gn:country_code":"CN",
    "gn:dem":18,
    "gn:feature_class":"P",
    "gn:feature_code":"PPL",
    "gn:name":"Qunjing",
    "gn:population":0,
    "gn:timezone":"Asia/Urumqi",
    "iso:country":"CN",
    "name:zho_x_preferred":[
        "\u7fa4\u4e95"
    ],
    "wof:name":"Qunjing",
    "wof:placetype":"locality"
},
  "geometry": {"coordinates":[110.30911999999999,21.14404],"type":"Point"}
}