{
  "type": "Feature",
  "properties": {
    "gn:admin1_code":"12.0",
    "gn:asciiname":"Chunshuping",
    "gn:country_code":"CN",
    "gn:dem":917,
    "gn:feature_class":"P",
    "gn:feature_code":"PPL",
    "gn:name":"Chunshuping",
    "gn:population":0,
    "gn:timezone":"Asia/Shanghai",
    "iso:country":"CN",
    "name:zho_x_preferred":[
        "Chunshuping"
    ],
    "name:zho_x_variant":[
        "\u6625\u6811\u576a"
    ],
    "wof:name":"Chunshuping",
    "wof:placetype":"locality"
},
  "geometry": {"coordinates":[111.15376000000001,30.3951],"type":"Point"}
}