{
  "type": "Feature",
  "properties": {
    "gn:admin1_code":"11.0",
    "gn:asciiname":"Xiaole",
    "gn:country_code":"CN",
    "gn:dem":30,
    "gn:feature_class":"P",
    "gn:feature_code":"PPL",
    "gn:name":"Xiaole",
    "gn:population":0,
    "gn:timezone":"Asia/Shanghai",
    "iso:country":"CN",
    "name:zho_x_preferred":[
        "\u6653\u4e50"
    ],
    "wof:name":"Xiaole",
    "wof:placetype":"locality"
},
  "geometry": {"coordinates":[112.65613999999999,29.02567],"type":"Point"}
}