{
  "type": "Feature",
  "properties": {
    "gn:admin1_code":"26.0",
    "gn:asciiname":"Manpocun",
    "gn:country_code":"CN",
    "gn:dem":569,
    "gn:feature_class":"P",
    "gn:feature_code":"PPL",
    "gn:name":"Manpocun",
    "gn:population":0,
    "gn:timezone":"Asia/Shanghai",
    "iso:country":"CN",
    "name:und_x_variant":[
        "\u6162\u5761\u6751"
    ],
    "wof:name":"Manpocun",
    "wof:placetype":"locality"
},
  "geometry": {"coordinates":[107.06291,32.99672],"type":"Point"}
}