{
  "type": "Feature",
  "properties": {
    "gn:admin1_code":"25",
    "gn:asciiname":"Xing Yicun",
    "gn:country_code":"CN",
    "gn:dem":154,
    "gn:feature_class":"P",
    "gn:feature_code":"PPL",
    "gn:name":"Xing Yicun",
    "gn:population":0,
    "gn:timezone":"Asia/Shanghai",
    "iso:country":"CN",
    "name:zho_x_preferred":[
        "\u90a2\u4e00\u6751"
    ],
    "wof:name":"Xing Yicun",
    "wof:placetype":"locality"
},
  "geometry": {"coordinates":[118.74299999999999,35.5939],"type":"Point"}
}