{
  "type": "Feature",
  "properties": {
    "gn:admin1_code":"33.0",
    "gn:asciiname":"Niuping",
    "gn:country_code":"CN",
    "gn:dem":1613,
    "gn:feature_class":"P",
    "gn:feature_code":"PPL",
    "gn:name":"Niuping",
    "gn:population":0,
    "gn:timezone":"Asia/Shanghai",
    "iso:country":"CN",
    "name:zho_x_preferred":[
        "\u725b\u576a"
    ],
    "wof:name":"Niuping",
    "wof:placetype":"locality"
},
  "geometry": {"coordinates":[107.61091,29.55955],"type":"Point"}
}