{
  "type": "Feature",
  "properties": {
    "gn:admin1_code":"19",
    "gn:asciiname":"Daxuecun",
    "gn:country_code":"CN",
    "gn:dem":20,
    "gn:feature_class":"P",
    "gn:feature_code":"PPL",
    "gn:name":"Daxuecun",
    "gn:population":0,
    "gn:timezone":"Asia/Shanghai",
    "iso:country":"CN",
    "name:und_x_variant":[
        "Daxue"
    ],
    "name:zho_x_preferred":[
        "\u5927\u859b\u6751"
    ],
    "wof:name":"Daxuecun",
    "wof:placetype":"locality"
},
  "geometry": {"coordinates":[121.18683,41.17864],"type":"Point"}
}