{
  "type": "Feature",
  "properties": {
    "gn:admin1_code":"32.0",
    "gn:asciiname":"Maopingshan",
    "gn:country_code":"CN",
    "gn:dem":1327,
    "gn:feature_class":"P",
    "gn:feature_code":"PPL",
    "gn:name":"Maopingshan",
    "gn:population":0,
    "gn:timezone":"Asia/Shanghai",
    "iso:country":"CN",
    "name:und_x_variant":[
        "\u6bdb\u576a\u5c71"
    ],
    "wof:name":"Maopingshan",
    "wof:placetype":"locality"
},
  "geometry": {"coordinates":[106.59162999999999,32.40770999999999],"type":"Point"}
}