{
  "type": "Feature",
  "properties": {
    "gn:admin1_code":"4.0",
    "gn:asciiname":"Xinliuxu",
    "gn:country_code":"CN",
    "gn:dem":6,
    "gn:feature_class":"P",
    "gn:feature_code":"PPLF",
    "gn:name":"Xinliuxu",
    "gn:population":0,
    "gn:timezone":"Asia/Shanghai",
    "iso:country":"CN",
    "name:zho_x_preferred":[
        "\u65b0\u516d\u5729"
    ],
    "wof:name":"Xinliuxu",
    "wof:placetype":"locality"
},
  "geometry": {"coordinates":[120.08602999999999,32.00153],"type":"Point"}
}