{
  "type": "Feature",
  "properties": {
    "gn:admin1_code":"14.0",
    "gn:asciiname":"Zhalha",
    "gn:country_code":"CN",
    "gn:dem":2131,
    "gn:feature_class":"P",
    "gn:feature_code":"PPL",
    "gn:name":"Zhalha",
    "gn:population":0,
    "gn:timezone":"Asia/Urumqi",
    "iso:country":"CN",
    "name:bod_x_preferred":[
        "Zhalha"
    ],
    "name:zho_x_preferred":[
        "Zhala"
    ],
    "name:zho_x_variant":[
        "\u624e\u62c9"
    ],
    "wof:name":"Zhalha",
    "wof:placetype":"locality"
},
  "geometry": {"coordinates":[97.34001000000001,28.62203],"type":"Point"}
}