{
  "type": "Feature",
  "properties": {
    "gn:admin1_code":"5.0",
    "gn:asciiname":"Gangzicun",
    "gn:country_code":"CN",
    "gn:dem":422,
    "gn:feature_class":"P",
    "gn:feature_code":"PPL",
    "gn:name":"Gangzicun",
    "gn:population":0,
    "gn:timezone":"Asia/Shanghai",
    "iso:country":"CN",
    "name:zho_x_preferred":[
        "\u5c97\u5b50\u6751"
    ],
    "wof:name":"Gangzicun",
    "wof:placetype":"locality"
},
  "geometry": {"coordinates":[128.34988999999999,43.53813],"type":"Point"}
}