{
  "type": "Feature",
  "properties": {
    "gn:admin1_code":"21.0",
    "gn:asciiname":"Yumin",
    "gn:country_code":"CN",
    "gn:dem":1097,
    "gn:feature_class":"P",
    "gn:feature_code":"PPL",
    "gn:name":"Yumin",
    "gn:population":0,
    "gn:timezone":"Asia/Shanghai",
    "iso:country":"CN",
    "name:ceb_x_preferred":[
        "Yumin"
    ],
    "name:zho_x_preferred":[
        "\u88d5\u6c11"
    ],
    "wof:name":"Yumin",
    "wof:placetype":"locality"
},
  "geometry": {"coordinates":[106.694,38.9443],"type":"Point"}
}