{
  "type": "Feature",
  "properties": {
    "gn:admin1_code":"2.0",
    "gn:asciiname":"Zhoucun",
    "gn:country_code":"CN",
    "gn:dem":89,
    "gn:feature_class":"P",
    "gn:feature_code":"PPL",
    "gn:name":"Zhoucun",
    "gn:population":0,
    "gn:timezone":"Asia/Shanghai",
    "iso:country":"CN",
    "name:und_x_variant":[
        "\u5468\u6751",
        "Zhoucun"
    ],
    "wof:name":"Zhoucun",
    "wof:placetype":"locality"
},
  "geometry": {"coordinates":[119.26177,29.24035],"type":"Point"}
}