{
  "type": "Feature",
  "properties": {
    "gn:admin1_code":"19.0",
    "gn:asciiname":"Jianglanqi",
    "gn:country_code":"CN",
    "gn:dem":185,
    "gn:feature_class":"P",
    "gn:feature_code":"PPL",
    "gn:name":"Jianglanqi",
    "gn:population":0,
    "gn:timezone":"Asia/Shanghai",
    "iso:country":"CN",
    "name:zho_x_preferred":[
        "\u6c5f\u5170\u65d7"
    ],
    "wof:name":"Jianglanqi",
    "wof:placetype":"locality"
},
  "geometry": {"coordinates":[120.71599999999999,41.8477],"type":"Point"}
}