{
  "type": "Feature",
  "properties": {
    "gn:admin1_code":"4.0",
    "gn:asciiname":"Huanxi",
    "gn:country_code":"CN",
    "gn:dem":5,
    "gn:feature_class":"P",
    "gn:feature_code":"PPL",
    "gn:name":"Huanxi",
    "gn:population":0,
    "gn:timezone":"Asia/Shanghai",
    "iso:country":"CN",
    "name:zho_x_preferred":[
        "Huanxi"
    ],
    "name:zho_x_variant":[
        "\u73af\u897f"
    ],
    "wof:name":"Huanxi",
    "wof:placetype":"locality"
},
  "geometry": {"coordinates":[121.0535,32.52727],"type":"Point"}
}