{
  "type": "Feature",
  "properties": {
    "gn:admin1_code":"10",
    "gn:asciiname":"Jinjiagou",
    "gn:country_code":"CN",
    "gn:dem":106,
    "gn:feature_class":"P",
    "gn:feature_code":"PPL",
    "gn:name":"Jinjiagou",
    "gn:population":0,
    "gn:timezone":"Asia/Shanghai",
    "iso:country":"CN",
    "name:zho_x_preferred":[
        "\u91d1\u5bb6\u6c9f"
    ],
    "wof:name":"Jinjiagou",
    "wof:placetype":"locality"
},
  "geometry": {"coordinates":[118.49223000000001,40.17155],"type":"Point"}
}