{
  "type": "Feature",
  "properties": {
    "gn:admin1_code":"29.0",
    "gn:asciiname":"Shangbanliang",
    "gn:country_code":"CN",
    "gn:dem":1278,
    "gn:feature_class":"P",
    "gn:feature_code":"PPL",
    "gn:name":"Shangbanliang",
    "gn:population":0,
    "gn:timezone":"Asia/Shanghai",
    "iso:country":"CN",
    "name:zho_x_preferred":[
        "\u4e0a\u73ed\u826f"
    ],
    "wof:name":"Shangbanliang",
    "wof:placetype":"locality"
},
  "geometry": {"coordinates":[101.44199999999999,23.7488],"type":"Point"}
}