{
  "type": "Feature",
  "properties": {
    "gn:admin1_code":"10.0",
    "gn:asciiname":"Taibuling",
    "gn:country_code":"CN",
    "gn:dem":598,
    "gn:feature_class":"P",
    "gn:feature_code":"PPL",
    "gn:name":"Taibuling",
    "gn:population":0,
    "gn:timezone":"Asia/Shanghai",
    "iso:country":"CN",
    "name:zho_x_preferred":[
        "\u592a\u5821\u5cad"
    ],
    "wof:name":"Taibuling",
    "wof:placetype":"locality"
},
  "geometry": {"coordinates":[113.75588,38.56297],"type":"Point"}
}