{
  "type": "Feature",
  "properties": {
    "gn:admin1_code":"13",
    "gn:asciiname":"Sailicun",
    "gn:country_code":"CN",
    "gn:dem":1285,
    "gn:feature_class":"P",
    "gn:feature_code":"PPL",
    "gn:name":"Sailicun",
    "gn:population":0,
    "gn:timezone":"Asia/Shanghai",
    "iso:country":"CN",
    "name:und_x_variant":[
        "\u8d5b\u529b\u6751"
    ],
    "wof:name":"Sailicun",
    "wof:placetype":"locality"
},
  "geometry": {"coordinates":[77.27216,38.13741],"type":"Point"}
}