{
  "type": "Feature",
  "properties": {
    "gn:admin1_code":"10.0",
    "gn:asciiname":"Laozhan",
    "gn:country_code":"CN",
    "gn:dem":36,
    "gn:feature_class":"P",
    "gn:feature_code":"PPL",
    "gn:name":"Laozhan",
    "gn:population":0,
    "gn:timezone":"Asia/Shanghai",
    "iso:country":"CN",
    "name:zho_x_preferred":[
        "\u8001\u7ad9"
    ],
    "wof:name":"Laozhan",
    "wof:placetype":"locality"
},
  "geometry": {"coordinates":[118.75911000000001,39.75245],"type":"Point"}
}