{
  "type": "Feature",
  "properties": {
    "gn:admin1_code":"9.0",
    "gn:asciiname":"Laohuwa",
    "gn:country_code":"CN",
    "gn:dem":348,
    "gn:feature_class":"P",
    "gn:feature_code":"PPL",
    "gn:name":"Laohuwa",
    "gn:population":0,
    "gn:timezone":"Asia/Shanghai",
    "iso:country":"CN",
    "name:zho_x_preferred":[
        "\u8001\u864e\u6d3c"
    ],
    "wof:name":"Laohuwa",
    "wof:placetype":"locality"
},
  "geometry": {"coordinates":[112.32398000000001,34.44219],"type":"Point"}
}