{
  "type": "Feature",
  "properties": {
    "gn:admin1_code":"15.0",
    "gn:asciiname":"Huigouli",
    "gn:country_code":"CN",
    "gn:dem":2357,
    "gn:feature_class":"P",
    "gn:feature_code":"PPL",
    "gn:name":"Huigouli",
    "gn:population":0,
    "gn:timezone":"Asia/Shanghai",
    "iso:country":"CN",
    "name:zho_x_preferred":[
        "\u56de\u6c9f\u91cc"
    ],
    "wof:name":"Huigouli",
    "wof:placetype":"locality"
},
  "geometry": {"coordinates":[104.527,35.3384],"type":"Point"}
}