{
  "type": "Feature",
  "properties": {
    "gn:admin1_code":"32.0",
    "gn:asciiname":"Zhongda",
    "gn:country_code":"CN",
    "gn:dem":2650,
    "gn:feature_class":"P",
    "gn:feature_code":"PPL",
    "gn:name":"Zhongda",
    "gn:population":0,
    "gn:timezone":"Asia/Shanghai",
    "iso:country":"CN",
    "name:ita_x_preferred":[
        "Zhongda"
    ],
    "name:zho_x_preferred":[
        "\u4ef2\u8fbe"
    ],
    "wof:name":"Zhongda",
    "wof:placetype":"locality"
},
  "geometry": {"coordinates":[99.7824,28.7632],"type":"Point"}
}