{
  "type": "Feature",
  "properties": {
    "gn:admin1_code":"5.0",
    "gn:asciiname":"Xiaoqi Keshu",
    "gn:country_code":"CN",
    "gn:dem":119,
    "gn:feature_class":"P",
    "gn:feature_code":"PPL",
    "gn:name":"Xiaoqi Keshu",
    "gn:population":0,
    "gn:timezone":"Asia/Shanghai",
    "iso:country":"CN",
    "name:zho_x_preferred":[
        "\u5c0f\u4e03\u68f5\u6811"
    ],
    "wof:name":"Xiaoqi Keshu",
    "wof:placetype":"locality"
},
  "geometry": {"coordinates":[123.72767,43.56488],"type":"Point"}
}