{
  "type": "Feature",
  "properties": {
    "gn:admin1_code":"29.0",
    "gn:asciiname":"Chenjia",
    "gn:country_code":"CN",
    "gn:dem":1630,
    "gn:feature_class":"P",
    "gn:feature_code":"PPL",
    "gn:name":"Chenjia",
    "gn:population":0,
    "gn:timezone":"Asia/Shanghai",
    "iso:country":"CN",
    "name:zho_x_preferred":[
        "\u9648\u5bb6"
    ],
    "wof:name":"Chenjia",
    "wof:placetype":"locality"
},
  "geometry": {"coordinates":[100.544,24.1593],"type":"Point"}
}