{
  "type": "Feature",
  "properties": {
    "gn:admin1_code":"11",
    "gn:asciiname":"Shangguanxi",
    "gn:country_code":"CN",
    "gn:dem":285,
    "gn:feature_class":"P",
    "gn:feature_code":"PPL",
    "gn:name":"Shangguanxi",
    "gn:population":0,
    "gn:timezone":"Asia/Shanghai",
    "iso:country":"CN",
    "name:zho_x_preferred":[
        "\u4e0a\u5b98\u6eaa"
    ],
    "wof:name":"Shangguanxi",
    "wof:placetype":"locality"
},
  "geometry": {"coordinates":[111.54319,27.65972],"type":"Point"}
}