{
  "type": "Feature",
  "properties": {
    "gn:admin1_code":"23.0",
    "gn:asciiname":"Laosun Jiatang",
    "gn:country_code":"CN",
    "gn:dem":4,
    "gn:feature_class":"P",
    "gn:feature_code":"PPL",
    "gn:name":"Laosun Jiatang",
    "gn:population":0,
    "gn:timezone":"Asia/Shanghai",
    "iso:country":"CN",
    "name:zho_x_preferred":[
        "Laosun Jiatang"
    ],
    "name:zho_x_variant":[
        "\u8001\u5b59\u5bb6\u5858"
    ],
    "wof:name":"Laosun Jiatang",
    "wof:placetype":"locality"
},
  "geometry": {"coordinates":[121.45099999999999,31.04447],"type":"Point"}
}