{
  "type": "Feature",
  "properties": {
    "gn:admin1_code":"4.0",
    "gn:asciiname":"Wangjiapeng",
    "gn:country_code":"CN",
    "gn:dem":48,
    "gn:feature_class":"P",
    "gn:feature_code":"PPL",
    "gn:name":"Wangjiapeng",
    "gn:population":0,
    "gn:timezone":"Asia/Shanghai",
    "iso:country":"CN",
    "name:zho_x_preferred":[
        "\u738b\u5bb6\u68da"
    ],
    "wof:name":"Wangjiapeng",
    "wof:placetype":"locality"
},
  "geometry": {"coordinates":[119.29631000000001,31.84014],"type":"Point"}
}