{
  "type": "Feature",
  "properties": {
    "gn:admin1_code":"4.0",
    "gn:asciiname":"Sanlijing",
    "gn:country_code":"CN",
    "gn:dem":24,
    "gn:feature_class":"P",
    "gn:feature_code":"PPL",
    "gn:name":"Sanlijing",
    "gn:population":0,
    "gn:timezone":"Asia/Shanghai",
    "iso:country":"CN",
    "name:zho_x_preferred":[
        "\u4e09\u91cc\u4e95"
    ],
    "wof:name":"Sanlijing",
    "wof:placetype":"locality"
},
  "geometry": {"coordinates":[119.15393,31.96228],"type":"Point"}
}