{
  "type": "Feature",
  "properties": {
    "gn:admin1_code":"24.0",
    "gn:asciiname":"Dahenggou",
    "gn:country_code":"CN",
    "gn:dem":972,
    "gn:feature_class":"P",
    "gn:feature_code":"PPL",
    "gn:name":"Dahenggou",
    "gn:population":0,
    "gn:timezone":"Asia/Shanghai",
    "iso:country":"CN",
    "name:zho_x_preferred":[
        "\u5927\u6a2a\u6c9f"
    ],
    "wof:name":"Dahenggou",
    "wof:placetype":"locality"
},
  "geometry": {"coordinates":[113.38118,38.07294],"type":"Point"}
}