{
  "type": "Feature",
  "properties": {
    "gn:admin1_code":"32.0",
    "gn:asciiname":"Gaodongchang",
    "gn:country_code":"CN",
    "gn:dem":265,
    "gn:feature_class":"P",
    "gn:feature_code":"PPL",
    "gn:name":"Gaodongchang",
    "gn:population":0,
    "gn:timezone":"Asia/Shanghai",
    "iso:country":"CN",
    "name:zho_x_preferred":[
        "\u9ad8\u6d1e\u573a"
    ],
    "wof:name":"Gaodongchang",
    "wof:placetype":"locality"
},
  "geometry": {"coordinates":[105.43474000000001,28.75746],"type":"Point"}
}