{
  "type": "Feature",
  "properties": {
    "gn:admin1_code":"32.0",
    "gn:asciiname":"Huangshuikou",
    "gn:country_code":"CN",
    "gn:dem":867,
    "gn:feature_class":"P",
    "gn:feature_code":"PPL",
    "gn:name":"Huangshuikou",
    "gn:population":0,
    "gn:timezone":"Asia/Shanghai",
    "iso:country":"CN",
    "name:zho_x_preferred":[
        "\u9ec4\u6c34\u53e3"
    ],
    "wof:name":"Huangshuikou",
    "wof:placetype":"locality"
},
  "geometry": {"coordinates":[104.85442,28.12315],"type":"Point"}
}