{
  "type": "Feature",
  "properties": {
    "gn:admin1_code":"11.0",
    "gn:asciiname":"Sumixi",
    "gn:country_code":"CN",
    "gn:dem":228,
    "gn:feature_class":"P",
    "gn:feature_code":"PPL",
    "gn:name":"Sumixi",
    "gn:population":0,
    "gn:timezone":"Asia/Shanghai",
    "iso:country":"CN",
    "name:zho_x_preferred":[
        "\u7c9f\u7c73\u6eaa"
    ],
    "wof:name":"Sumixi",
    "wof:placetype":"locality"
},
  "geometry": {"coordinates":[111.44874,28.32207],"type":"Point"}
}