{
  "type": "Feature",
  "properties": {
    "gn:admin1_code":"1.0",
    "gn:asciiname":"Xiaoyuanshan",
    "gn:country_code":"CN",
    "gn:dem":126,
    "gn:feature_class":"P",
    "gn:feature_code":"PPL",
    "gn:name":"Xiaoyuanshan",
    "gn:population":0,
    "gn:timezone":"Asia/Shanghai",
    "iso:country":"CN",
    "name:zho_x_preferred":[
        "\u5c0f\u6e90\u5c71"
    ],
    "wof:name":"Xiaoyuanshan",
    "wof:placetype":"locality"
},
  "geometry": {"coordinates":[116.85722,29.60391],"type":"Point"}
}