{
  "type": "Feature",
  "properties": {
    "gn:admin1_code":"8.0",
    "gn:asciiname":"Xichengzicun",
    "gn:country_code":"CN",
    "gn:dem":155,
    "gn:feature_class":"P",
    "gn:feature_code":"PPL",
    "gn:name":"Xichengzicun",
    "gn:population":0,
    "gn:timezone":"Asia/Shanghai",
    "iso:country":"CN",
    "name:zho_x_preferred":[
        "\u897f\u57ce\u5b50\u6751"
    ],
    "wof:name":"Xichengzicun",
    "wof:placetype":"locality"
},
  "geometry": {"coordinates":[126.58941000000002,45.25607],"type":"Point"}
}