{
  "type": "Feature",
  "properties": {
    "gn:admin1_code":"3.0",
    "gn:asciiname":"Dianbeishan",
    "gn:country_code":"CN",
    "gn:dem":162,
    "gn:feature_class":"P",
    "gn:feature_code":"PPL",
    "gn:name":"Dianbeishan",
    "gn:population":0,
    "gn:timezone":"Asia/Shanghai",
    "iso:country":"CN",
    "name:und_x_variant":[
        "\u5e97\u80cc\u5c71"
    ],
    "wof:name":"Dianbeishan",
    "wof:placetype":"locality"
},
  "geometry": {"coordinates":[115.6614,27.15234],"type":"Point"}
}