{
  "type": "Feature",
  "properties": {
    "gn:admin1_code":"02",
    "gn:asciiname":"Erliushicun",
    "gn:country_code":"CN",
    "gn:dem":10,
    "gn:feature_class":"P",
    "gn:feature_code":"PPL",
    "gn:name":"Erliushicun",
    "gn:population":0,
    "gn:timezone":"Asia/Shanghai",
    "iso:country":"CN",
    "name:und_x_variant":[
        "Erh-liu-shih",
        "Erliushi",
        "\u4e8c\u516d\u5e02",
        "Erliushicun"
    ],
    "name:zho_x_preferred":[
        "\u4e8c\u516d\u5e02\u6751"
    ],
    "wof:name":"Erliushicun",
    "wof:placetype":"locality"
},
  "geometry": {"coordinates":[121.37549,30.0163],"type":"Point"}
}