{
  "type": "Feature",
  "properties": {
    "gn:admin1_code":"3.0",
    "gn:asciiname":"Lixishan",
    "gn:country_code":"CN",
    "gn:dem":485,
    "gn:feature_class":"P",
    "gn:feature_code":"PPL",
    "gn:name":"Lixishan",
    "gn:population":0,
    "gn:timezone":"Asia/Shanghai",
    "iso:country":"CN",
    "name:und_x_variant":[
        "\u91cc\u897f\u5c71"
    ],
    "wof:name":"Lixishan",
    "wof:placetype":"locality"
},
  "geometry": {"coordinates":[116.06585,27.3555],"type":"Point"}
}