{
  "type": "Feature",
  "properties": {
    "gn:admin1_code":"15.0",
    "gn:asciiname":"Fenshuigou",
    "gn:country_code":"CN",
    "gn:dem":1514,
    "gn:feature_class":"P",
    "gn:feature_code":"PPL",
    "gn:name":"Fenshuigou",
    "gn:population":0,
    "gn:timezone":"Asia/Shanghai",
    "iso:country":"CN",
    "name:zho_x_preferred":[
        "\u5206\u6c34\u6c9f"
    ],
    "wof:name":"Fenshuigou",
    "wof:placetype":"locality"
},
  "geometry": {"coordinates":[100.22499999999999,39.028],"type":"Point"}
}