{
  "type": "Feature",
  "properties": {
    "gn:admin1_code":"32.0",
    "gn:asciiname":"Jinzhuba",
    "gn:country_code":"CN",
    "gn:dem":1414,
    "gn:feature_class":"P",
    "gn:feature_code":"PPL",
    "gn:name":"Jinzhuba",
    "gn:population":0,
    "gn:timezone":"Asia/Shanghai",
    "iso:country":"CN",
    "name:zho_x_preferred":[
        "\u91d1\u7af9\u575d"
    ],
    "wof:name":"Jinzhuba",
    "wof:placetype":"locality"
},
  "geometry": {"coordinates":[105.851,28.2111],"type":"Point"}
}