{
  "type": "Feature",
  "properties": {
    "gn:admin1_code":"15.0",
    "gn:asciiname":"Yinpozhuang",
    "gn:country_code":"CN",
    "gn:dem":1938,
    "gn:feature_class":"P",
    "gn:feature_code":"PPL",
    "gn:name":"Yinpozhuang",
    "gn:population":0,
    "gn:timezone":"Asia/Shanghai",
    "iso:country":"CN",
    "name:und_x_variant":[
        "\u9634\u5761\u5e84"
    ],
    "wof:name":"Yinpozhuang",
    "wof:placetype":"locality"
},
  "geometry": {"coordinates":[105.32738999999999,35.77865999999999],"type":"Point"}
}