{
  "type": "Feature",
  "properties": {
    "gn:admin1_code":"2",
    "gn:asciiname":"Dingcun",
    "gn:country_code":"CN",
    "gn:dem":331,
    "gn:feature_class":"P",
    "gn:feature_code":"PPL",
    "gn:name":"Dingcun",
    "gn:population":0,
    "gn:timezone":"Asia/Shanghai",
    "iso:country":"CN",
    "name:swe_x_preferred":[
        "Dingcun"
    ],
    "name:uzb_x_preferred":[
        "Dinsun"
    ],
    "name:zho_x_preferred":[
        "\u5b9a\u6751"
    ],
    "wof:name":"Dingcun",
    "wof:placetype":"locality"
},
  "geometry": {"coordinates":[118.65204,28.41347],"type":"Point"}
}