{
  "type": "Feature",
  "properties": {
    "gn:admin1_code":"3.0",
    "gn:asciiname":"Lingxiahucun",
    "gn:country_code":"CN",
    "gn:dem":29,
    "gn:feature_class":"P",
    "gn:feature_code":"PPL",
    "gn:name":"Lingxiahucun",
    "gn:population":0,
    "gn:timezone":"Asia/Shanghai",
    "iso:country":"CN",
    "name:und_x_variant":[
        "\u5cad\u4e0b\u80e1\u6751"
    ],
    "wof:name":"Lingxiahucun",
    "wof:placetype":"locality"
},
  "geometry": {"coordinates":[116.16433000000001,28.38487000000001],"type":"Point"}
}