{
  "type": "Feature",
  "properties": {
    "gn:admin1_code":"3.0",
    "gn:asciiname":"Langshankou",
    "gn:country_code":"CN",
    "gn:dem":89,
    "gn:feature_class":"P",
    "gn:feature_code":"PPL",
    "gn:name":"Langshankou",
    "gn:population":0,
    "gn:timezone":"Asia/Shanghai",
    "iso:country":"CN",
    "name:und_x_variant":[
        "\u6717\u5c71\u53e3"
    ],
    "wof:name":"Langshankou",
    "wof:placetype":"locality"
},
  "geometry": {"coordinates":[116.83526000000001,27.96877000000001],"type":"Point"}
}