{
  "type": "Feature",
  "properties": {
    "gn:admin1_code":"5.0",
    "gn:asciiname":"Xiao'erdaogou",
    "gn:country_code":"CN",
    "gn:dem":270,
    "gn:feature_class":"P",
    "gn:feature_code":"PPL",
    "gn:name":"Xiao\u2019erdaogou",
    "gn:population":0,
    "gn:timezone":"Asia/Shanghai",
    "iso:country":"CN",
    "name:und_x_variant":[
        "Xiao\u2019erdaogou"
    ],
    "name:zho_x_preferred":[
        "\u5c0f\u4e8c\u9053\u6c9f"
    ],
    "wof:name":"Xiao'erdaogou",
    "wof:placetype":"locality"
},
  "geometry": {"coordinates":[126.01912,44.15342],"type":"Point"}
}