{
  "type": "Feature",
  "properties": {
    "gn:admin1_code":"7.0",
    "gn:asciiname":"Taolin",
    "gn:country_code":"CN",
    "gn:dem":480,
    "gn:feature_class":"P",
    "gn:feature_code":"PPL",
    "gn:name":"Taolin",
    "gn:population":0,
    "gn:timezone":"Asia/Shanghai",
    "iso:country":"CN",
    "name:zho_x_preferred":[
        "\u6843\u6797"
    ],
    "wof:name":"Taolin",
    "wof:placetype":"locality"
},
  "geometry": {"coordinates":[117.58287,25.69635],"type":"Point"}
}