{
  "type": "Feature",
  "properties": {
    "gn:admin1_code":"15.0",
    "gn:asciiname":"Dongjiaping",
    "gn:country_code":"CN",
    "gn:dem":1658,
    "gn:feature_class":"P",
    "gn:feature_code":"PPL",
    "gn:name":"Dongjiaping",
    "gn:population":0,
    "gn:timezone":"Asia/Shanghai",
    "iso:country":"CN",
    "name:zho_x_preferred":[
        "\u8463\u5bb6\u576a"
    ],
    "wof:name":"Dongjiaping",
    "wof:placetype":"locality"
},
  "geometry": {"coordinates":[105.127,34.6953],"type":"Point"}
}