{
  "type": "Feature",
  "properties": {
    "gn:admin1_code":"29.0",
    "gn:asciiname":"Dapingzi",
    "gn:country_code":"CN",
    "gn:dem":1908,
    "gn:feature_class":"P",
    "gn:feature_code":"PPL",
    "gn:name":"Dapingzi",
    "gn:population":0,
    "gn:timezone":"Asia/Shanghai",
    "iso:country":"CN",
    "name:und_x_variant":[
        "\u5927\u576a\u5b50"
    ],
    "wof:name":"Dapingzi",
    "wof:placetype":"locality"
},
  "geometry": {"coordinates":[103.908,27.6935],"type":"Point"}
}