{
  "type": "Feature",
  "properties": {
    "gn:admin1_code":"15.0",
    "gn:asciiname":"Shatu Yaoxian",
    "gn:country_code":"CN",
    "gn:dem":1543,
    "gn:feature_class":"P",
    "gn:feature_code":"PPL",
    "gn:name":"Shatu Yaoxian",
    "gn:population":0,
    "gn:timezone":"Asia/Shanghai",
    "iso:country":"CN",
    "name:zho_x_preferred":[
        "\u6c99\u571f\u5d3e\u5c98"
    ],
    "wof:name":"Shatu Yaoxian",
    "wof:placetype":"locality"
},
  "geometry": {"coordinates":[107.17700000000001,37.1247],"type":"Point"}
}