{
  "type": "Feature",
  "properties": {
    "gn:country":"CN",
    "gn:fcode":"PPL",
    "gn:population":93174,
    "iso:country":"CN",
    "name:ceb_x_preferred":[
        "Changping"
    ],
    "name:ces_x_preferred":[
        "\u010cchang-pching"
    ],
    "name:mlg_x_preferred":[
        "Changping"
    ],
    "name:rus_x_preferred":[
        "\u0427\u0430\u043d\u043f\u0438\u043d"
    ],
    "name:swe_x_preferred":[
        "Changping"
    ],
    "name:und_x_variant":[
        "Ch\u2019ang-p\u2019ing-ch\u2019\u00fc"
    ],
    "name:zho_x_preferred":[
        "\u660c\u5e73"
    ],
    "ne:ADM0CAP":0.0,
    "ne:ADM0NAME":"China",
    "ne:ADM0_A3":"CHN",
    "ne:ADM1NAME":"Beijing",
    "ne:ADMIN1_COD":22,
    "ne:CAPALT":0,
    "ne:CHANGED":0,
    "ne:CHECKME":0,
    "ne:COMPARE":0,
    "ne:DIFFASCII":0,
    "ne:ELEVATION":0.0,
    "ne:FEATURECLA":"Populated place",
    "ne:FEATURE_CL":"P",
    "ne:FEATURE_CO":"PPL",
    "ne:GEONAMEID":2038154,
    "ne:GEONAMESNO":"Geonames ascii name + lat.d + long.d matching.",
    "ne:GN_ASCII":"Changping",
    "ne:GN_POP":93174,
    "ne:GTOPO30":51.0,
    "ne:ISO_A2":"CN",
    "ne:LABELRANK":1,
    "ne:LATITUDE":40.224766,
    "ne:LONGITUDE":116.194396,
    "ne:LS_MATCH":1,
    "ne:LS_NAME":"Changping",
    "ne:MAX_AREAKM":407.0,
    "ne:MAX_AREAMI":157.0,
    "ne:MAX_BBXMAX":116.425,
    "ne:MAX_BBXMIN":116.033333,
    "ne:MAX_BBYMAX":40.291667,
    "ne:MAX_BBYMIN":39.92374,
    "ne:MAX_NATSCA":20.0,
    "ne:MAX_PERKM":569.0,
    "ne:MAX_PERMI":354.0,
    "ne:MAX_POP10":848928,
    "ne:MAX_POP20":848928,
    "ne:MAX_POP300":0,
    "ne:MAX_POP310":0,
    "ne:MAX_POP50":0,
    "ne:MEAN_BBXC":116.220658,
    "ne:MEAN_BBYC":40.139151,
    "ne:MEGACITY":0,
    "ne:MIN_AREAKM":407.0,
    "ne:MIN_AREAMI":157.0,
    "ne:MIN_BBXMAX":116.425,
    "ne:MIN_BBXMIN":116.033333,
    "ne:MIN_BBYMAX":40.291667,
    "ne:MIN_BBYMIN":39.92374,
    "ne:MIN_PERKM":569.0,
    "ne:MIN_PERMI":354.0,
    "ne:NAME":"Changping",
    "ne:NAMEASCII":"Changping",
    "ne:NAMEDIFF":0,
    "ne:NATSCALE":20,
    "ne:POP1950":0,
    "ne:POP1955":0,
    "ne:POP1960":0,
    "ne:POP1965":0,
    "ne:POP1970":0,
    "ne:POP1975":0,
    "ne:POP1980":0,
    "ne:POP1985":0,
    "ne:POP1990":0,
    "ne:POP1995":0,
    "ne:POP2000":0,
    "ne:POP2005":0,
    "ne:POP2010":0,
    "ne:POP2015":0,
    "ne:POP2020":0,
    "ne:POP2025":0,
    "ne:POP2050":0,
    "ne:POP_MAX":614821,
    "ne:POP_MIN":130000,
    "ne:POP_OTHER":887567,
    "ne:RANK_MAX":11,
    "ne:RANK_MIN":9,
    "ne:SCALERANK":7,
    "ne:SOV0NAME":"China",
    "ne:SOV_A3":"CHN",
    "ne:TIMEZONE":"Asia/Harbin",
    "ne:UN_FID":0,
    "ne:UN_LAT":0.0,
    "ne:UN_LONG":0.0,
    "ne:WORLDCITY":0,
    "qs:name":"Changping",
    "qs:photos_9r":0,
    "qs:photos_sr":0,
    "qs:pop_sr":"11",
    "wd:wordcount":135,
    "wof:name":"Changping",
    "wof:placetype":"locality",
    "wof:population":93174
},
  "geometry": {"coordinates":[116.23471000000001,40.21612],"type":"Point"}
}