{
  "type": "Feature",
  "properties": {
    "gn:admin1_code":"18",
    "gn:asciiname":"Hongzipo",
    "gn:country_code":"CN",
    "gn:dem":892,
    "gn:feature_class":"P",
    "gn:feature_code":"PPL",
    "gn:name":"Hongzipo",
    "gn:population":0,
    "gn:timezone":"Asia/Shanghai",
    "iso:country":"CN",
    "name:zho_x_preferred":[
        "\u7ea2\u5b50\u5761"
    ],
    "wof:name":"Hongzipo",
    "wof:placetype":"locality"
},
  "geometry": {"coordinates":[107.806,27.6548],"type":"Point"}
}