{
  "type": "Feature",
  "properties": {
    "gn:admin1_code":"15.0",
    "gn:asciiname":"Xiajiagou",
    "gn:country_code":"CN",
    "gn:dem":2595,
    "gn:feature_class":"P",
    "gn:feature_code":"PPL",
    "gn:name":"Xiajiagou",
    "gn:population":0,
    "gn:timezone":"Asia/Shanghai",
    "iso:country":"CN",
    "name:zho_x_preferred":[
        "\u4e0b\u5939\u6c9f"
    ],
    "wof:name":"Xiajiagou",
    "wof:placetype":"locality"
},
  "geometry": {"coordinates":[103.39100000000001,37.2401],"type":"Point"}
}