{
  "type": "Feature",
  "properties": {
    "gn:admin1_code":"9.0",
    "gn:asciiname":"Nigouhe",
    "gn:country_code":"CN",
    "gn:dem":221,
    "gn:feature_class":"P",
    "gn:feature_code":"PPL",
    "gn:name":"Nigouhe",
    "gn:population":0,
    "gn:timezone":"Asia/Shanghai",
    "iso:country":"CN",
    "name:zho_x_preferred":[
        "\u6ce5\u6c9f\u6cb3"
    ],
    "wof:name":"Nigouhe",
    "wof:placetype":"locality"
},
  "geometry": {"coordinates":[112.54924,35.0224],"type":"Point"}
}