{
  "type": "Feature",
  "properties": {
    "gn:admin1_code":"24.0",
    "gn:asciiname":"Sizhuang",
    "gn:country_code":"CN",
    "gn:dem":894,
    "gn:feature_class":"P",
    "gn:feature_code":"PPL",
    "gn:name":"Sizhuang",
    "gn:population":0,
    "gn:timezone":"Asia/Shanghai",
    "iso:country":"CN",
    "name:zho_x_preferred":[
        "\u5bfa\u5e84"
    ],
    "wof:name":"Sizhuang",
    "wof:placetype":"locality"
},
  "geometry": {"coordinates":[112.63594000000001,38.05962],"type":"Point"}
}