{
  "type": "Feature",
  "properties": {
    "gn:admin1_code":"14",
    "gn:asciiname":"Rubinggang",
    "gn:country_code":"CN",
    "gn:dem":3438,
    "gn:feature_class":"P",
    "gn:feature_code":"PPL",
    "gn:name":"Rubinggang",
    "gn:population":0,
    "gn:timezone":"Asia/Urumqi",
    "iso:country":"CN",
    "name:zho_x_preferred":[
        "\u6c5d\u4e19\u5c97"
    ],
    "wof:name":"Rubinggang",
    "wof:placetype":"locality"
},
  "geometry": {"coordinates":[88.9628,27.5202],"type":"Point"}
}