{
  "type": "Feature",
  "properties": {
    "gn:admin1_code":"21.0",
    "gn:asciiname":"Zhangya",
    "gn:country_code":"CN",
    "gn:dem":1662,
    "gn:feature_class":"P",
    "gn:feature_code":"PPL",
    "gn:name":"Zhangya",
    "gn:population":0,
    "gn:timezone":"Asia/Shanghai",
    "iso:country":"CN",
    "name:und_x_variant":[
        "\u5f20\u5d16"
    ],
    "name:zho_x_preferred":[
        "\u5f20\u5d16"
    ],
    "wof:name":"Zhangya",
    "wof:placetype":"locality"
},
  "geometry": {"coordinates":[106.31480000000001,36.19846],"type":"Point"}
}