{
  "type": "Feature",
  "properties": {
    "gn:admin1_code":"3.0",
    "gn:asciiname":"Dahugang",
    "gn:country_code":"CN",
    "gn:dem":77,
    "gn:feature_class":"P",
    "gn:feature_code":"PPL",
    "gn:name":"Dahugang",
    "gn:population":0,
    "gn:timezone":"Asia/Shanghai",
    "iso:country":"CN",
    "name:und_x_variant":[
        "\u5927\u6e56\u5c97"
    ],
    "wof:name":"Dahugang",
    "wof:placetype":"locality"
},
  "geometry": {"coordinates":[115.02051000000002,26.75254],"type":"Point"}
}