{
  "type": "Feature",
  "properties": {
    "gn:admin1_code":"16.0",
    "gn:asciiname":"Genggu",
    "gn:country_code":"CN",
    "gn:dem":537,
    "gn:feature_class":"P",
    "gn:feature_code":"PPL",
    "gn:name":"Genggu",
    "gn:population":0,
    "gn:timezone":"Asia/Shanghai",
    "iso:country":"CN",
    "name:zho_x_preferred":[
        "\u66f4\u53e4"
    ],
    "wof:name":"Genggu",
    "wof:placetype":"locality"
},
  "geometry": {"coordinates":[110.992,22.7987],"type":"Point"}
}