{
  "type": "Feature",
  "properties": {
    "gn:admin1_code":"33.0",
    "gn:asciiname":"Malankou",
    "gn:country_code":"CN",
    "gn:dem":410,
    "gn:feature_class":"P",
    "gn:feature_code":"PPL",
    "gn:name":"Malankou",
    "gn:population":0,
    "gn:timezone":"Asia/Shanghai",
    "iso:country":"CN",
    "name:zho_x_preferred":[
        "\u9a6c\u70c2\u53e3"
    ],
    "wof:name":"Malankou",
    "wof:placetype":"locality"
},
  "geometry": {"coordinates":[109.67547999999999,31.60322],"type":"Point"}
}