{
  "type": "Feature",
  "properties": {
    "gn:admin1_code":"30",
    "gn:asciiname":"Luxia",
    "gn:country_code":"CN",
    "gn:dem":373,
    "gn:feature_class":"P",
    "gn:feature_code":"PPL",
    "gn:name":"Luxia",
    "gn:population":0,
    "gn:timezone":"Asia/Shanghai",
    "iso:country":"CN",
    "name:und_x_variant":[
        "\u8def\u4e0b"
    ],
    "wof:name":"Luxia",
    "wof:placetype":"locality"
},
  "geometry": {"coordinates":[114.33808000000001,23.93071],"type":"Point"}
}