{
  "type": "Feature",
  "properties": {
    "gn:admin1_code":"32.0",
    "gn:asciiname":"Tingfang",
    "gn:country_code":"CN",
    "gn:dem":411,
    "gn:feature_class":"P",
    "gn:feature_code":"PPL",
    "gn:name":"Tingfang",
    "gn:population":0,
    "gn:timezone":"Asia/Shanghai",
    "iso:country":"CN",
    "name:zho_x_preferred":[
        "\u5385\u623f"
    ],
    "wof:name":"Tingfang",
    "wof:placetype":"locality"
},
  "geometry": {"coordinates":[105.565,29.7556],"type":"Point"}
}