{
  "type": "Feature",
  "properties": {
    "gn:admin1_code":"26.0",
    "gn:asciiname":"Manaogou",
    "gn:country_code":"CN",
    "gn:dem":738,
    "gn:feature_class":"P",
    "gn:feature_code":"PPL",
    "gn:name":"Manaogou",
    "gn:population":0,
    "gn:timezone":"Asia/Shanghai",
    "iso:country":"CN",
    "name:zho_x_preferred":[
        "\u9a6c\u8111\u6c9f"
    ],
    "wof:name":"Manaogou",
    "wof:placetype":"locality"
},
  "geometry": {"coordinates":[109.02885000000001,33.32444],"type":"Point"}
}