{
  "type": "Feature",
  "properties": {
    "gn:admin1_code":"4.0",
    "gn:asciiname":"Lijiaqiaodai",
    "gn:country_code":"CN",
    "gn:dem":4,
    "gn:feature_class":"P",
    "gn:feature_code":"PPL",
    "gn:name":"Lijiaqiaodai",
    "gn:population":0,
    "gn:timezone":"Asia/Shanghai",
    "iso:country":"CN",
    "name:zho_x_preferred":[
        "\u674e\u5bb6\u6865\u5788"
    ],
    "wof:name":"Lijiaqiaodai",
    "wof:placetype":"locality"
},
  "geometry": {"coordinates":[120.34244,32.06662],"type":"Point"}
}