{
  "type": "Feature",
  "properties": {
    "gn:admin1_code":"30.0",
    "gn:asciiname":"Shuizhaicun",
    "gn:country_code":"CN",
    "gn:dem":10,
    "gn:feature_class":"P",
    "gn:feature_code":"PPL",
    "gn:name":"Shuizhaicun",
    "gn:population":0,
    "gn:timezone":"Asia/Shanghai",
    "iso:country":"CN",
    "name:zho_x_preferred":[
        "\u6c34\u5be8\u6751"
    ],
    "wof:name":"Shuizhaicun",
    "wof:placetype":"locality"
},
  "geometry": {"coordinates":[116.31023999999999,23.37117000000001],"type":"Point"}
}