{
  "type": "Feature",
  "properties": {
    "gn:admin1_code":"25.0",
    "gn:asciiname":"Zoujiacun",
    "gn:country_code":"CN",
    "gn:dem":168,
    "gn:feature_class":"P",
    "gn:feature_code":"PPL",
    "gn:name":"Zoujiacun",
    "gn:population":0,
    "gn:timezone":"Asia/Shanghai",
    "iso:country":"CN",
    "name:zho_x_preferred":[
        "\u90b9\u5bb6\u6751"
    ],
    "wof:name":"Zoujiacun",
    "wof:placetype":"locality"
},
  "geometry": {"coordinates":[120.78091000000001,37.38377],"type":"Point"}
}