{
  "type": "Feature",
  "properties": {
    "gn:admin1_code":"29",
    "gn:asciiname":"Laotanshan",
    "gn:country_code":"CN",
    "gn:dem":1395,
    "gn:feature_class":"P",
    "gn:feature_code":"PPL",
    "gn:name":"Laotanshan",
    "gn:population":0,
    "gn:timezone":"Asia/Shanghai",
    "iso:country":"CN",
    "name:zho_x_preferred":[
        "\u8001\u70ad\u5c71"
    ],
    "wof:name":"Laotanshan",
    "wof:placetype":"locality"
},
  "geometry": {"coordinates":[105.145,23.9466],"type":"Point"}
}