{
  "type": "Feature",
  "properties": {
    "gn:admin1_code":"21.0",
    "gn:asciiname":"Qingshimao",
    "gn:country_code":"CN",
    "gn:dem":1557,
    "gn:feature_class":"P",
    "gn:feature_code":"PPL",
    "gn:name":"Qingshimao",
    "gn:population":0,
    "gn:timezone":"Asia/Shanghai",
    "iso:country":"CN",
    "name:zho_x_preferred":[
        "\u9752\u77f3\u5cc1"
    ],
    "wof:name":"Qingshimao",
    "wof:placetype":"locality"
},
  "geometry": {"coordinates":[107.137,37.4335],"type":"Point"}
}