{
  "type": "Feature",
  "properties": {
    "gn:admin1_code":"29.0",
    "gn:asciiname":"Changtangli",
    "gn:country_code":"CN",
    "gn:dem":1833,
    "gn:feature_class":"P",
    "gn:feature_code":"PPL",
    "gn:name":"Changtangli",
    "gn:population":0,
    "gn:timezone":"Asia/Shanghai",
    "iso:country":"CN",
    "name:zho_x_preferred":[
        "\u5e38\u5858\u91cc"
    ],
    "wof:name":"Changtangli",
    "wof:placetype":"locality"
},
  "geometry": {"coordinates":[103.711,25.0413],"type":"Point"}
}