{
  "type": "Feature",
  "properties": {
    "gn:admin1_code":"12.0",
    "gn:asciiname":"Xinwangchang",
    "gn:country_code":"CN",
    "gn:dem":53,
    "gn:feature_class":"P",
    "gn:feature_code":"PPL",
    "gn:name":"Xinwangchang",
    "gn:population":0,
    "gn:timezone":"Asia/Shanghai",
    "iso:country":"CN",
    "name:zho_x_preferred":[
        "\u65b0\u738b\u573a"
    ],
    "wof:name":"Xinwangchang",
    "wof:placetype":"locality"
},
  "geometry": {"coordinates":[113.18941,30.98506],"type":"Point"}
}