{
  "type": "Feature",
  "properties": {
    "gn:admin1_code":"24.0",
    "gn:asciiname":"Gujiawan",
    "gn:country_code":"CN",
    "gn:dem":1032,
    "gn:feature_class":"P",
    "gn:feature_code":"PPL",
    "gn:name":"Gujiawan",
    "gn:population":0,
    "gn:timezone":"Asia/Shanghai",
    "iso:country":"CN",
    "name:zho_x_preferred":[
        "\u987e\u5bb6\u6e7e"
    ],
    "wof:name":"Gujiawan",
    "wof:placetype":"locality"
},
  "geometry": {"coordinates":[113.99381,40.33074000000001],"type":"Point"}
}