{
  "type": "Feature",
  "properties": {
    "gn:admin1_code":"32.0",
    "gn:asciiname":"Sihetou",
    "gn:country_code":"CN",
    "gn:dem":690,
    "gn:feature_class":"P",
    "gn:feature_code":"PPL",
    "gn:name":"Sihetou",
    "gn:population":0,
    "gn:timezone":"Asia/Shanghai",
    "iso:country":"CN",
    "name:zho_x_preferred":[
        "\u56db\u5408\u5934"
    ],
    "wof:name":"Sihetou",
    "wof:placetype":"locality"
},
  "geometry": {"coordinates":[105.85914,28.08841],"type":"Point"}
}