{
  "type": "Feature",
  "properties": {
    "gn:admin1_code":"29.0",
    "gn:asciiname":"Laidaisi",
    "gn:country_code":"CN",
    "gn:dem":1455,
    "gn:feature_class":"P",
    "gn:feature_code":"PPL",
    "gn:name":"Laidaisi",
    "gn:population":0,
    "gn:timezone":"Asia/Shanghai",
    "iso:country":"CN",
    "name:zho_x_preferred":[
        "\u6765\u4ee3\u53f8"
    ],
    "wof:name":"Laidaisi",
    "wof:placetype":"locality"
},
  "geometry": {"coordinates":[99.63509999999999,22.855],"type":"Point"}
}