{
  "type": "Feature",
  "properties": {
    "gn:admin1_code":"5.0",
    "gn:asciiname":"Penyaocun",
    "gn:country_code":"CN",
    "gn:dem":207,
    "gn:feature_class":"P",
    "gn:feature_code":"PPL",
    "gn:name":"Penyaocun",
    "gn:population":0,
    "gn:timezone":"Asia/Shanghai",
    "iso:country":"CN",
    "name:zho_x_preferred":[
        "\u76c6\u7a91\u6751"
    ],
    "wof:name":"Penyaocun",
    "wof:placetype":"locality"
},
  "geometry": {"coordinates":[126.27162,44.11789],"type":"Point"}
}