{
  "type": "Feature",
  "properties": {
    "gn:admin1_code":"29.0",
    "gn:asciiname":"Daxiechang",
    "gn:country_code":"CN",
    "gn:dem":1410,
    "gn:feature_class":"P",
    "gn:feature_code":"PPL",
    "gn:name":"Daxiechang",
    "gn:population":0,
    "gn:timezone":"Asia/Shanghai",
    "iso:country":"CN",
    "name:zho_x_preferred":[
        "\u5927\u6b47\u573a"
    ],
    "wof:name":"Daxiechang",
    "wof:placetype":"locality"
},
  "geometry": {"coordinates":[98.9393,24.4448],"type":"Point"}
}