{
  "type": "Feature",
  "properties": {
    "gn:admin1_code":"20",
    "gn:asciiname":"Har Nur",
    "gn:country_code":"CN",
    "gn:dem":685,
    "gn:feature_class":"P",
    "gn:feature_code":"PPLA4",
    "gn:name":"Har Nur",
    "gn:population":0,
    "gn:timezone":"Asia/Shanghai",
    "iso:country":"CN",
    "name:und_x_variant":[
        "Ha-jih-nu-la",
        "Har Nur",
        "Harinuo\u2019er",
        "Harinuo\u2019er Sumu"
    ],
    "name:zho_x_preferred":[
        "\u54c8\u65e5\u8bfa\u5c14"
    ],
    "name:zho_x_variant":[
        "\u54c8\u65e5\u8bfa\u5c14\u82cf\u6728"
    ],
    "wof:name":"Har Nur",
    "wof:placetype":"locality"
},
  "geometry": {"coordinates":[120.08347999999999,45.6374],"type":"Point"}
}