{
  "type": "Feature",
  "properties": {
    "gn:admin1_code":"20.0",
    "gn:asciiname":"Haoyari Aobao",
    "gn:country_code":"CN",
    "gn:dem":564,
    "gn:feature_class":"P",
    "gn:feature_code":"PPL",
    "gn:name":"Haoyari Aobao",
    "gn:population":0,
    "gn:timezone":"Asia/Shanghai",
    "iso:country":"CN",
    "name:zho_x_preferred":[
        "\u6d69\u96c5\u65e5\u6556\u5305"
    ],
    "wof:name":"Haoyari Aobao",
    "wof:placetype":"locality"
},
  "geometry": {"coordinates":[116.62195,48.59517],"type":"Point"}
}