{
  "type": "Feature",
  "properties": {
    "gn:admin1_code":"14.0",
    "gn:asciiname":"Xieduicun",
    "gn:country_code":"CN",
    "gn:dem":4621,
    "gn:feature_class":"P",
    "gn:feature_code":"PPL",
    "gn:name":"Xieduicun",
    "gn:population":0,
    "gn:timezone":"Asia/Urumqi",
    "iso:country":"CN",
    "name:zho_x_preferred":[
        "\u534f\u5806\u6751"
    ],
    "wof:name":"Xieduicun",
    "wof:placetype":"locality"
},
  "geometry": {"coordinates":[97.59505,31.08549],"type":"Point"}
}