{
  "type": "Feature",
  "properties": {
    "gn:admin1_code":"1.0",
    "gn:asciiname":"Zhoulingcun",
    "gn:country_code":"CN",
    "gn:dem":411,
    "gn:feature_class":"P",
    "gn:feature_code":"PPL",
    "gn:name":"Zhoulingcun",
    "gn:population":0,
    "gn:timezone":"Asia/Shanghai",
    "iso:country":"CN",
    "name:zho_x_preferred":[
        "\u5468\u5cad\u6751"
    ],
    "wof:name":"Zhoulingcun",
    "wof:placetype":"locality"
},
  "geometry": {"coordinates":[115.96956000000002,30.58731],"type":"Point"}
}