{
  "type": "Feature",
  "properties": {
    "gn:admin1_code":"1.0",
    "gn:asciiname":"Qianjiangcun",
    "gn:country_code":"CN",
    "gn:dem":39,
    "gn:feature_class":"P",
    "gn:feature_code":"PPL",
    "gn:name":"Qianjiangcun",
    "gn:population":0,
    "gn:timezone":"Asia/Shanghai",
    "iso:country":"CN",
    "name:zho_x_preferred":[
        "\u524d\u848b\u6751"
    ],
    "wof:name":"Qianjiangcun",
    "wof:placetype":"locality"
},
  "geometry": {"coordinates":[115.51328999999998,33.38950999999999],"type":"Point"}
}