{
  "type": "Feature",
  "properties": {
    "gn:admin1_code":"9.0",
    "gn:asciiname":"Guanzhai",
    "gn:country_code":"CN",
    "gn:dem":62,
    "gn:feature_class":"P",
    "gn:feature_code":"PPL",
    "gn:name":"Guanzhai",
    "gn:population":0,
    "gn:timezone":"Asia/Shanghai",
    "iso:country":"CN",
    "name:zho_x_preferred":[
        "\u89c2\u5be8"
    ],
    "wof:name":"Guanzhai",
    "wof:placetype":"locality"
},
  "geometry": {"coordinates":[114.68667000000001,35.82783],"type":"Point"}
}