{
  "type": "Feature",
  "properties": {
    "gn:admin1_code":"1.0",
    "gn:asciiname":"Dongshutou",
    "gn:country_code":"CN",
    "gn:dem":59,
    "gn:feature_class":"P",
    "gn:feature_code":"PPL",
    "gn:name":"Dongshutou",
    "gn:population":0,
    "gn:timezone":"Asia/Shanghai",
    "iso:country":"CN",
    "name:zho_x_preferred":[
        "\u8463\u6811\u5934"
    ],
    "wof:name":"Dongshutou",
    "wof:placetype":"locality"
},
  "geometry": {"coordinates":[119.33624,31.19695],"type":"Point"}
}