{
  "type": "Feature",
  "properties": {
    "gn:admin1_code":"4.0",
    "gn:asciiname":"Yihe",
    "gn:country_code":"CN",
    "gn:dem":3,
    "gn:feature_class":"P",
    "gn:feature_code":"PPL",
    "gn:name":"Yihe",
    "gn:population":0,
    "gn:timezone":"Asia/Shanghai",
    "iso:country":"CN",
    "name:und_x_variant":[
        "\u4e49\u548c"
    ],
    "name:zho_x_preferred":[
        "\u4e49\u548c"
    ],
    "wof:name":"Yihe",
    "wof:placetype":"locality"
},
  "geometry": {"coordinates":[119.98196000000002,32.56272],"type":"Point"}
}