{
  "type": "Feature",
  "properties": {
    "gn:country":"CN",
    "gn:fcode":"ADM3",
    "gn:pop":0,
    "iso:country":"CN",
    "name:unk_x_variant":[
        "Y\u00fc-ch\u2019eng Hsien"
    ],
    "name:zho_x_preferred":[
        "\u865e\u57ce\u53bf"
    ],
    "name:zho_x_variant":[
        "\u865e\u57ce"
    ],
    "qs:name":"Yucheng Xian",
    "qs:photos_9r":0,
    "qs:photos_sr":0,
    "qs:pop_sr":"0",
    "wd:wordcount":107,
    "wof:name":"Yucheng Xian",
    "wof:placetype":"localadmin",
    "wof:population":0
},
  "geometry": {"coordinates":[115.85361,34.32333],"type":"Point"}
}