{
  "type": "Feature",
  "properties": {
    "gn:country":"CN",
    "gn:fcode":"ADM3",
    "gn:pop":0,
    "iso:country":"CN",
    "name:ceb_x_preferred":[
        "Yucheng Xian"
    ],
    "name:deu_x_preferred":[
        "Yucheng"
    ],
    "name:eng_x_preferred":[
        "Yucheng County"
    ],
    "name:fas_x_preferred":[
        "\u0634\u0647\u0631\u0633\u062a\u0627\u0646 \u06cc\u0648\u0686\u0646\u06af"
    ],
    "name:gan_x_preferred":[
        "\u865e\u57ce\u53bf"
    ],
    "name:jpn_x_preferred":[
        "\u865e\u57ce\u770c"
    ],
    "name:kor_x_preferred":[
        "\uc704\uccad\ud604"
    ],
    "name:nan_x_preferred":[
        "G\u00fb-si\u00e2\u207f-ko\u0101n"
    ],
    "name:nld_x_preferred":[
        "Yucheng"
    ],
    "name:nob_x_preferred":[
        "Yucheng"
    ],
    "name:rus_x_preferred":[
        "\u042e\u0439\u0447\u044d\u043d"
    ],
    "name:swe_x_preferred":[
        "Yucheng"
    ],
    "name:tur_x_preferred":[
        "Yucheng County"
    ],
    "name:unk_x_variant":[
        "Y\u00fc-ch\u2019eng Hsien"
    ],
    "name:urd_x_preferred":[
        "\u06cc\u0648\u0686\u06cc\u0646\u06af \u06a9\u0627\u0624\u0646\u0679\u06cc"
    ],
    "name:vie_x_preferred":[
        "Ngu Th\u00e0nh"
    ],
    "name:wuu_x_preferred":[
        "\u865e\u57ce\u53bf"
    ],
    "name:yue_x_preferred":[
        "\u865e\u57ce"
    ],
    "name:zho_x_preferred":[
        "\u865e\u57ce\u53bf"
    ],
    "name:zho_x_variant":[
        "\u865e\u57ce"
    ],
    "qs:name":"Yucheng Xian",
    "qs:photos_9r":0,
    "qs:photos_sr":0,
    "qs:pop_sr":"0",
    "wd:wordcount":107,
    "wof:name":"Yucheng Xian",
    "wof:placetype":"localadmin",
    "wof:population":0
},
  "geometry": {"coordinates":[115.85361,34.32333],"type":"Point"}
}