{
  "type": "Feature",
  "properties": {
    "gn:admin1_code":"2.0",
    "gn:asciiname":"Xia'ao",
    "gn:country_code":"CN",
    "gn:dem":316,
    "gn:feature_class":"P",
    "gn:feature_code":"PPL",
    "gn:name":"Xia\u2019ao",
    "gn:population":0,
    "gn:timezone":"Asia/Shanghai",
    "iso:country":"CN",
    "name:und_x_variant":[
        "Xia\u2019ao"
    ],
    "name:zho_x_preferred":[
        "\u971e\u5c99"
    ],
    "wof:name":"Xia'ao",
    "wof:placetype":"locality"
},
  "geometry": {"coordinates":[120.90388,28.28543],"type":"Point"}
}