{
  "type": "Feature",
  "properties": {
    "gn:admin1_code":"20.0",
    "gn:asciiname":"Yangsangou",
    "gn:country_code":"CN",
    "gn:dem":1715,
    "gn:feature_class":"P",
    "gn:feature_code":"PPL",
    "gn:name":"Yangsangou",
    "gn:population":0,
    "gn:timezone":"Asia/Shanghai",
    "iso:country":"CN",
    "name:und_x_variant":[
        "\u6768\u4e09\u6c9f"
    ],
    "wof:name":"Yangsangou",
    "wof:placetype":"locality"
},
  "geometry": {"coordinates":[110.41524,40.95902],"type":"Point"}
}