{
  "type": "Feature",
  "properties": {
    "gn:admin1_code":"14.0",
    "gn:asciiname":"Chixika",
    "gn:country_code":"CN",
    "gn:dem":4067,
    "gn:feature_class":"P",
    "gn:feature_code":"PPL",
    "gn:name":"Chixika",
    "gn:population":0,
    "gn:timezone":"Asia/Urumqi",
    "iso:country":"CN",
    "name:bod_x_preferred":[
        "Chixika"
    ],
    "name:zho_x_preferred":[
        "Zhixika"
    ],
    "name:zho_x_variant":[
        "\u652f\u6eaa\u5361",
        "Zhilang Gongshe",
        "\u652f\u6717\u516c\u793e"
    ],
    "wof:name":"Chixika",
    "wof:placetype":"locality"
},
  "geometry": {"coordinates":[91.905,28.905],"type":"Point"}
}