{
  "type": "Feature",
  "properties": {
    "gn:admin1_code":"04",
    "gn:asciiname":"Guanhu",
    "gn:cc2":"CN",
    "gn:country_code":"CN",
    "gn:dem":27,
    "gn:feature_class":"P",
    "gn:feature_code":"PPL",
    "gn:name":"Guanhu",
    "gn:population":0,
    "gn:timezone":"Asia/Shanghai",
    "iso:country":"CN",
    "name:und_x_variant":[
        "Kuan-hu",
        "Kuan-hu-chen",
        "Guanhu"
    ],
    "wof:name":"Guanhu",
    "wof:placetype":"locality"
},
  "geometry": {"coordinates":[117.99527999999999,34.42528],"type":"Point"}
}