{
  "type": "Feature",
  "properties": {
    "gn:admin1_code":"26.0",
    "gn:asciiname":"Majia Pucun",
    "gn:country_code":"CN",
    "gn:dem":1096,
    "gn:feature_class":"P",
    "gn:feature_code":"PPL",
    "gn:name":"Majia Pucun",
    "gn:population":0,
    "gn:timezone":"Asia/Shanghai",
    "iso:country":"CN",
    "name:zho_x_preferred":[
        "\u9a6c\u5bb6\u94fa\u6751"
    ],
    "wof:name":"Majia Pucun",
    "wof:placetype":"locality"
},
  "geometry": {"coordinates":[110.297,37.8493],"type":"Point"}
}