{
  "type": "Feature",
  "properties": {
    "gn:admin1_code":"8.0",
    "gn:asciiname":"Hongjian",
    "gn:country_code":"CN",
    "gn:dem":157,
    "gn:feature_class":"P",
    "gn:feature_code":"PPL",
    "gn:name":"Hongjian",
    "gn:population":0,
    "gn:timezone":"Asia/Shanghai",
    "iso:country":"CN",
    "name:zho_x_preferred":[
        "\u5b8f\u5efa"
    ],
    "wof:name":"Hongjian",
    "wof:placetype":"locality"
},
  "geometry": {"coordinates":[124.90089999999999,47.25744],"type":"Point"}
}