{
  "type": "Feature",
  "properties": {
    "gn:admin1_code":"10",
    "gn:asciiname":"Maohuqing",
    "gn:country_code":"CN",
    "gn:dem":1384,
    "gn:feature_class":"P",
    "gn:feature_code":"PPL",
    "gn:name":"Maohuqing",
    "gn:population":0,
    "gn:timezone":"Asia/Shanghai",
    "iso:country":"CN",
    "name:zho_x_preferred":[
        "\u6bdb\u80e1\u5e86"
    ],
    "wof:name":"Maohuqing",
    "wof:placetype":"locality"
},
  "geometry": {"coordinates":[114.22381,41.73881],"type":"Point"}
}