{
  "type": "Feature",
  "properties": {
    "gn:admin1_code":"25",
    "gn:asciiname":"Songjiazhuang",
    "gn:country_code":"CN",
    "gn:dem":271,
    "gn:feature_class":"P",
    "gn:feature_code":"PPL",
    "gn:name":"Songjiazhuang",
    "gn:population":0,
    "gn:timezone":"Asia/Shanghai",
    "iso:country":"CN",
    "name:zho_x_preferred":[
        "\u5b8b\u5bb6\u5e84"
    ],
    "wof:name":"Songjiazhuang",
    "wof:placetype":"locality"
},
  "geometry": {"coordinates":[118.378,36.5275],"type":"Point"}
}