{
  "type": "Feature",
  "properties": {
    "gn:admin1_code":"23.0",
    "gn:asciiname":"Yubei Erdui",
    "gn:country_code":"CN",
    "gn:dem":2,
    "gn:feature_class":"P",
    "gn:feature_code":"PPLF",
    "gn:name":"Yubei Erdui",
    "gn:population":0,
    "gn:timezone":"Asia/Shanghai",
    "iso:country":"CN",
    "name:zho_x_preferred":[
        "Yubei Erdui"
    ],
    "name:zho_x_variant":[
        "\u88d5\u5317\u4e8c\u961f"
    ],
    "wof:name":"Yubei Erdui",
    "wof:placetype":"locality"
},
  "geometry": {"coordinates":[121.85348,31.52883],"type":"Point"}
}