{
  "type": "Feature",
  "properties": {
    "gn:admin1_code":"11.0",
    "gn:asciiname":"Paxi",
    "gn:country_code":"CN",
    "gn:dem":295,
    "gn:feature_class":"P",
    "gn:feature_code":"PPL",
    "gn:name":"Paxi",
    "gn:population":0,
    "gn:timezone":"Asia/Shanghai",
    "iso:country":"CN",
    "name:bre_x_preferred":[
        "Paksos"
    ],
    "name:bul_x_preferred":[
        "\u041f\u0430\u043a\u0441\u043e\u0441"
    ],
    "name:cat_x_preferred":[
        "Paxos"
    ],
    "name:ceb_x_preferred":[
        "Pax\u00f3s"
    ],
    "name:ces_x_preferred":[
        "Paxos"
    ],
    "name:dan_x_preferred":[
        "Paxi"
    ],
    "name:deu_x_preferred":[
        "Paxos"
    ],
    "name:ell_x_preferred":[
        "\u03a0\u03b1\u03be\u03bf\u03af"
    ],
    "name:est_x_preferred":[
        "Paxo\u00ed"
    ],
    "name:fin_x_preferred":[
        "Pax\u00f3s"
    ],
    "name:fra_x_preferred":[
        "Paxos"
    ],
    "name:glg_x_preferred":[
        "Paxoi"
    ],
    "name:heb_x_preferred":[
        "\u05e4\u05d0\u05e7\u05e1\u05d9"
    ],
    "name:hun_x_preferred":[
        "Pax\u00ed"
    ],
    "name:hye_x_preferred":[
        "\u054a\u0561\u0584\u057d\u0578\u057d"
    ],
    "name:lit_x_preferred":[
        "Paksis"
    ],
    "name:mkd_x_preferred":[
        "\u041f\u0430\u043a\u0441\u0438"
    ],
    "name:nld_x_preferred":[
        "Paxi"
    ],
    "name:nno_x_preferred":[
        "Pax\u00ed"
    ],
    "name:nor_x_preferred":[
        "Paxos"
    ],
    "name:pol_x_preferred":[
        "Paksos"
    ],
    "name:ron_x_preferred":[
        "Paxos"
    ],
    "name:rus_x_preferred":[
        "\u041f\u0430\u043a\u0441\u0438"
    ],
    "name:spa_x_preferred":[
        "Paxo\u00ed"
    ],
    "name:sqi_x_preferred":[
        "Pakso"
    ],
    "name:srp_x_preferred":[
        "\u041f\u0430\u043a\u0441\u0438"
    ],
    "name:swe_x_preferred":[
        "Paxos"
    ],
    "name:tur_x_preferred":[
        "Paksu"
    ],
    "name:ukr_x_preferred":[
        "\u041f\u0430\u043a\u0441\u043e\u0441"
    ],
    "name:vie_x_preferred":[
        "Paxi"
    ],
    "name:zho_x_preferred":[
        "\u7436\u6eaa"
    ],
    "name:zho_x_variant":[
        "\u5e15\u514b\u897f\u5c9b"
    ],
    "wof:name":"Paxi",
    "wof:placetype":"locality"
},
  "geometry": {"coordinates":[112.43891000000001,25.50092],"type":"Point"}
}