{
  "type": "Feature",
  "properties": {
    "gn:admin1_code":"11.0",
    "gn:asciiname":"Paxi",
    "gn:country_code":"CN",
    "gn:dem":295,
    "gn:feature_class":"P",
    "gn:feature_code":"PPL",
    "gn:name":"Paxi",
    "gn:population":0,
    "gn:timezone":"Asia/Shanghai",
    "iso:country":"CN",
    "name:zho_x_preferred":[
        "\u7436\u6eaa"
    ],
    "wof:name":"Paxi",
    "wof:placetype":"locality"
},
  "geometry": {"coordinates":[112.43891000000001,25.50092],"type":"Point"}
}