{
  "type": "Feature",
  "properties": {
    "gn:admin1_code":"14.0",
    "gn:asciiname":"Qude",
    "gn:country_code":"CN",
    "gn:dem":4314,
    "gn:feature_class":"P",
    "gn:feature_code":"PPL",
    "gn:name":"Qude",
    "gn:population":0,
    "gn:timezone":"Asia/Urumqi",
    "iso:country":"CN",
    "name:zho_x_preferred":[
        "\u66f2\u5fb7"
    ],
    "wof:name":"Qude",
    "wof:placetype":"locality"
},
  "geometry": {"coordinates":[93.66392,30.04678],"type":"Point"}
}