{
  "type": "Feature",
  "properties": {
    "gn:admin1_code":"11.0",
    "gn:asciiname":"Zhoutouwan",
    "gn:country_code":"CN",
    "gn:dem":128,
    "gn:feature_class":"P",
    "gn:feature_code":"PPL",
    "gn:name":"Zhoutouwan",
    "gn:population":0,
    "gn:timezone":"Asia/Shanghai",
    "iso:country":"CN",
    "name:zho_x_preferred":[
        "\u6d32\u5934\u6e7e"
    ],
    "wof:name":"Zhoutouwan",
    "wof:placetype":"locality"
},
  "geometry": {"coordinates":[113.36065000000001,26.49637],"type":"Point"}
}