{
  "type": "Feature",
  "properties": {
    "gn:admin1_code":"8.0",
    "gn:asciiname":"Tengjia Shaoguo",
    "gn:country_code":"CN",
    "gn:dem":154,
    "gn:feature_class":"P",
    "gn:feature_code":"PPL",
    "gn:name":"Tengjia Shaoguo",
    "gn:population":0,
    "gn:timezone":"Asia/Shanghai",
    "iso:country":"CN",
    "name:zho_x_preferred":[
        "\u6ed5\u5bb6\u70e7\u9505"
    ],
    "wof:name":"Tengjia Shaoguo",
    "wof:placetype":"locality"
},
  "geometry": {"coordinates":[126.96735,46.81572],"type":"Point"}
}