{
  "type": "Feature",
  "properties": {
    "gn:admin1_code":"32.0",
    "gn:asciiname":"Cibulaiwo",
    "gn:country_code":"CN",
    "gn:dem":1898,
    "gn:feature_class":"P",
    "gn:feature_code":"PPL",
    "gn:name":"Cibulaiwo",
    "gn:population":0,
    "gn:timezone":"Asia/Shanghai",
    "iso:country":"CN",
    "name:zho_x_preferred":[
        "\u6b64\u4e0d\u6765\u7a9d"
    ],
    "wof:name":"Cibulaiwo",
    "wof:placetype":"locality"
},
  "geometry": {"coordinates":[102.598,27.6747],"type":"Point"}
}