{
  "type": "Feature",
  "properties": {
    "gn:admin1_code":"5.0",
    "gn:asciiname":"Baoshantun",
    "gn:country_code":"CN",
    "gn:dem":516,
    "gn:feature_class":"P",
    "gn:feature_code":"PPL",
    "gn:name":"Baoshantun",
    "gn:population":0,
    "gn:timezone":"Asia/Shanghai",
    "iso:country":"CN",
    "name:und_x_variant":[
        "\u5b9d\u5c71\u5c6f"
    ],
    "wof:name":"Baoshantun",
    "wof:placetype":"locality"
},
  "geometry": {"coordinates":[127.64994,42.85866],"type":"Point"}
}