{
  "type": "Feature",
  "properties": {
    "gn:admin1_code":"32.0",
    "gn:asciiname":"Lihuo",
    "gn:country_code":"CN",
    "gn:dem":2838,
    "gn:feature_class":"P",
    "gn:feature_code":"PPL",
    "gn:name":"Lihuo",
    "gn:population":0,
    "gn:timezone":"Asia/Shanghai",
    "iso:country":"CN",
    "name:zho_x_preferred":[
        "\u529b\u6d3b"
    ],
    "wof:name":"Lihuo",
    "wof:placetype":"locality"
},
  "geometry": {"coordinates":[102.64100000000001,28.2381],"type":"Point"}
}