{
  "type": "Feature",
  "properties": {
    "gn:admin1_code":"8.0",
    "gn:asciiname":"Erdaogou Yitun",
    "gn:country_code":"CN",
    "gn:dem":256,
    "gn:feature_class":"P",
    "gn:feature_code":"PPL",
    "gn:name":"Erdaogou Yitun",
    "gn:population":0,
    "gn:timezone":"Asia/Shanghai",
    "iso:country":"CN",
    "name:zho_x_preferred":[
        "\u4e8c\u9053\u6c9f\u4e00\u5c6f"
    ],
    "wof:name":"Erdaogou Yitun",
    "wof:placetype":"locality"
},
  "geometry": {"coordinates":[122.87914000000001,47.59729],"type":"Point"}
}