{
  "type": "Feature",
  "properties": {
    "gn:admin1_code":"02",
    "gn:asciiname":"Duntou",
    "gn:country_code":"CN",
    "gn:dem":97,
    "gn:feature_class":"P",
    "gn:feature_code":"PPLA4",
    "gn:name":"Duntou",
    "gn:population":0,
    "gn:timezone":"Asia/Shanghai",
    "iso:country":"CN",
    "name:und_x_variant":[
        "\u58a9\u5934",
        "Duntou",
        "Duntou Zhen"
    ],
    "name:zho_x_preferred":[
        "\u58a9\u5934\u9547"
    ],
    "wof:name":"Duntou",
    "wof:placetype":"locality"
},
  "geometry": {"coordinates":[119.75391999999999,29.35047],"type":"Point"}
}