{
  "type": "Feature",
  "properties": {
    "gn:admin1_code":"6.0",
    "gn:asciiname":"Domba",
    "gn:country_code":"CN",
    "gn:dem":4066,
    "gn:feature_class":"P",
    "gn:feature_code":"PPLA4",
    "gn:name":"Domba",
    "gn:population":0,
    "gn:timezone":"Asia/Urumqi",
    "iso:country":"CN",
    "name:und_x_variant":[
        "Tung-pa",
        "Domba",
        "Dongba",
        "Dongba Xiang",
        "Lugouka"
    ],
    "name:zho_x_preferred":[
        "\u4e1c\u575d"
    ],
    "name:zho_x_variant":[
        "\u4e1c\u575d\u4e61",
        "\u82a6\u6c9f\u5361"
    ],
    "wof:name":"Domba",
    "wof:placetype":"locality"
},
  "geometry": {"coordinates":[95.58463999999999,32.31121],"type":"Point"}
}