{
  "type": "Feature",
  "properties": {
    "gn:admin1_code":"6.0",
    "gn:asciiname":"Domba",
    "gn:country_code":"CN",
    "gn:dem":4066,
    "gn:feature_class":"P",
    "gn:feature_code":"PPLA4",
    "gn:name":"Domba",
    "gn:population":0,
    "gn:timezone":"Asia/Urumqi",
    "iso:country":"CN",
    "name:bih_x_preferred":[
        "\u0921\u094b\u092e"
    ],
    "name:hrv_x_preferred":[
        "Dom"
    ],
    "name:spa_x_preferred":[
        "Dom"
    ],
    "name:tam_x_preferred":[
        "\u0ba4\u0bca\u0bae\u0bcd\u0baa\u0ba9\u0bcd"
    ],
    "name:tel_x_preferred":[
        "\u0c26\u0c4a\u0c2e\u0c4d\u0c2e\u0c30\u0c3f"
    ],
    "name:und_x_variant":[
        "Tung-pa",
        "Domba",
        "Dongba",
        "Dongba Xiang",
        "Lugouka"
    ],
    "name:zho_x_preferred":[
        "\u4e1c\u575d"
    ],
    "name:zho_x_variant":[
        "\u4e1c\u575d\u4e61",
        "\u82a6\u6c9f\u5361"
    ],
    "wof:name":"Domba",
    "wof:placetype":"locality"
},
  "geometry": {"coordinates":[95.58463999999999,32.31121],"type":"Point"}
}