{
  "type": "Feature",
  "properties": {
    "gn:admin1_code":"2.0",
    "gn:asciiname":"Panjiawu",
    "gn:country_code":"CN",
    "gn:dem":471,
    "gn:feature_class":"P",
    "gn:feature_code":"PPL",
    "gn:name":"Panjiawu",
    "gn:population":0,
    "gn:timezone":"Asia/Shanghai",
    "iso:country":"CN",
    "name:zho_x_preferred":[
        "\u6f58\u5bb6\u575e"
    ],
    "wof:name":"Panjiawu",
    "wof:placetype":"locality"
},
  "geometry": {"coordinates":[118.62206999999999,28.49666],"type":"Point"}
}