{
  "type": "Feature",
  "properties": {
    "gn:admin1_code":"10",
    "gn:asciiname":"Xiaolaoguanzhai",
    "gn:country_code":"CN",
    "gn:dem":38,
    "gn:feature_class":"P",
    "gn:feature_code":"PPL",
    "gn:name":"Xiaolaoguanzhai",
    "gn:population":0,
    "gn:timezone":"Asia/Shanghai",
    "iso:country":"CN",
    "name:zho_x_preferred":[
        "\u5c0f\u8001\u5b98\u5be8"
    ],
    "wof:name":"Xiaolaoguanzhai",
    "wof:placetype":"locality"
},
  "geometry": {"coordinates":[115.44027,36.80168],"type":"Point"}
}