{
  "type": "Feature",
  "properties": {
    "gn:admin1_code":"9.0",
    "gn:asciiname":"Beijingzhang",
    "gn:country_code":"CN",
    "gn:dem":58,
    "gn:feature_class":"P",
    "gn:feature_code":"PPL",
    "gn:name":"Beijingzhang",
    "gn:population":0,
    "gn:timezone":"Asia/Shanghai",
    "iso:country":"CN",
    "name:zho_x_preferred":[
        "\u5317\u8346\u5f20"
    ],
    "wof:name":"Beijingzhang",
    "wof:placetype":"locality"
},
  "geometry": {"coordinates":[114.75132000000001,36.02958],"type":"Point"}
}