{
  "type": "Feature",
  "properties": {
    "gn:admin1_code":"8.0",
    "gn:asciiname":"Renlicun",
    "gn:country_code":"CN",
    "gn:dem":244,
    "gn:feature_class":"P",
    "gn:feature_code":"PPL",
    "gn:name":"Renlicun",
    "gn:population":0,
    "gn:timezone":"Asia/Shanghai",
    "iso:country":"CN",
    "name:zho_x_preferred":[
        "\u4ec1\u793c\u6751"
    ],
    "wof:name":"Renlicun",
    "wof:placetype":"locality"
},
  "geometry": {"coordinates":[125.42986999999999,47.64359],"type":"Point"}
}