{
  "type": "Feature",
  "properties": {
    "gn:admin1_code":"18.0",
    "gn:asciiname":"Censuan",
    "gn:country_code":"CN",
    "gn:dem":440,
    "gn:feature_class":"P",
    "gn:feature_code":"PPL",
    "gn:name":"Censuan",
    "gn:population":0,
    "gn:timezone":"Asia/Shanghai",
    "iso:country":"CN",
    "name:zho_x_preferred":[
        "\u5c91\u7b97"
    ],
    "wof:name":"Censuan",
    "wof:placetype":"locality"
},
  "geometry": {"coordinates":[108.497,26.0117],"type":"Point"}
}