{
  "type": "Feature",
  "properties": {
    "gn:admin1_code":"12.0",
    "gn:asciiname":"Liuxiewan",
    "gn:country_code":"CN",
    "gn:dem":27,
    "gn:feature_class":"P",
    "gn:feature_code":"PPL",
    "gn:name":"Liuxiewan",
    "gn:population":0,
    "gn:timezone":"Asia/Shanghai",
    "iso:country":"CN",
    "name:zho_x_preferred":[
        "\u5218\u8c22\u6e7e"
    ],
    "wof:name":"Liuxiewan",
    "wof:placetype":"locality"
},
  "geometry": {"coordinates":[112.78051000000001,30.02867],"type":"Point"}
}