{
  "type": "Feature",
  "properties": {
    "gn:admin1_code":"32.0",
    "gn:asciiname":"Lengleng",
    "gn:country_code":"CN",
    "gn:dem":3339,
    "gn:feature_class":"P",
    "gn:feature_code":"PPL",
    "gn:name":"Lengleng",
    "gn:population":0,
    "gn:timezone":"Asia/Shanghai",
    "iso:country":"CN",
    "name:zho_x_preferred":[
        "\u51b7\u51b7"
    ],
    "wof:name":"Lengleng",
    "wof:placetype":"locality"
},
  "geometry": {"coordinates":[101.14700000000001,31.0157],"type":"Point"}
}