{
  "type": "Feature",
  "properties": {
    "gn:admin1_code":"24.0",
    "gn:asciiname":"Dongyanwan",
    "gn:country_code":"CN",
    "gn:dem":1600,
    "gn:feature_class":"P",
    "gn:feature_code":"PPL",
    "gn:name":"Dongyanwan",
    "gn:population":0,
    "gn:timezone":"Asia/Shanghai",
    "iso:country":"CN",
    "name:zho_x_preferred":[
        "\u4e1c\u781a\u6e7e"
    ],
    "wof:name":"Dongyanwan",
    "wof:placetype":"locality"
},
  "geometry": {"coordinates":[112.31247999999999,38.38777],"type":"Point"}
}