{
  "type": "Feature",
  "properties": {
    "gn:admin1_code":"30.0",
    "gn:asciiname":"Baifengang",
    "gn:country_code":"CN",
    "gn:dem":279,
    "gn:feature_class":"P",
    "gn:feature_code":"PPL",
    "gn:name":"Baifengang",
    "gn:population":0,
    "gn:timezone":"Asia/Urumqi",
    "iso:country":"CN",
    "name:zho_x_preferred":[
        "\u767d\u575f\u5c97"
    ],
    "wof:name":"Baifengang",
    "wof:placetype":"locality"
},
  "geometry": {"coordinates":[111.03937000000001,22.53906],"type":"Point"}
}