{
  "type": "Feature",
  "properties": {
    "gn:admin1_code":"12.0",
    "gn:asciiname":"Zhangmuba",
    "gn:country_code":"CN",
    "gn:dem":1349,
    "gn:feature_class":"P",
    "gn:feature_code":"PPL",
    "gn:name":"Zhangmuba",
    "gn:population":0,
    "gn:timezone":"Asia/Shanghai",
    "iso:country":"CN",
    "name:zho_x_preferred":[
        "\u6a1f\u6728\u575d"
    ],
    "wof:name":"Zhangmuba",
    "wof:placetype":"locality"
},
  "geometry": {"coordinates":[109.87821,30.41486],"type":"Point"}
}