{
  "type": "Feature",
  "properties": {
    "gn:admin1_code":"32.0",
    "gn:asciiname":"Malaofate",
    "gn:country_code":"CN",
    "gn:dem":1644,
    "gn:feature_class":"P",
    "gn:feature_code":"PPL",
    "gn:name":"Malaofate",
    "gn:population":0,
    "gn:timezone":"Asia/Shanghai",
    "iso:country":"CN",
    "name:zho_x_preferred":[
        "\u9a6c\u8001\u6cd5\u7279"
    ],
    "wof:name":"Malaofate",
    "wof:placetype":"locality"
},
  "geometry": {"coordinates":[102.6403,27.64702],"type":"Point"}
}