{
  "type": "Feature",
  "properties": {
    "gn:admin1_code":"5.0",
    "gn:asciiname":"Yangcaogoucun",
    "gn:country_code":"CN",
    "gn:dem":225,
    "gn:feature_class":"P",
    "gn:feature_code":"PPL",
    "gn:name":"Yangcaogoucun",
    "gn:population":0,
    "gn:timezone":"Asia/Shanghai",
    "iso:country":"CN",
    "name:zho_x_preferred":[
        "\u7f8a\u8349\u6c9f\u6751"
    ],
    "wof:name":"Yangcaogoucun",
    "wof:placetype":"locality"
},
  "geometry": {"coordinates":[125.59251999999999,43.97856],"type":"Point"}
}