{
  "type": "Feature",
  "properties": {
    "gn:admin1_code":"18",
    "gn:asciiname":"Fazhuzhai",
    "gn:country_code":"CN",
    "gn:dem":1752,
    "gn:feature_class":"P",
    "gn:feature_code":"PPL",
    "gn:name":"Fazhuzhai",
    "gn:population":0,
    "gn:timezone":"Asia/Shanghai",
    "iso:country":"CN",
    "name:zho_x_preferred":[
        "\u6cd5\u682a\u5be8"
    ],
    "wof:name":"Fazhuzhai",
    "wof:placetype":"locality"
},
  "geometry": {"coordinates":[105.078,26.9733],"type":"Point"}
}