{
  "type": "Feature",
  "properties": {
    "gn:admin1_code":"2.0",
    "gn:asciiname":"Dawantan",
    "gn:country_code":"CN",
    "gn:dem":736,
    "gn:feature_class":"P",
    "gn:feature_code":"PPL",
    "gn:name":"Dawantan",
    "gn:population":0,
    "gn:timezone":"Asia/Shanghai",
    "iso:country":"CN",
    "name:zho_x_preferred":[
        "\u5927\u6e7e\u6f6d"
    ],
    "wof:name":"Dawantan",
    "wof:placetype":"locality"
},
  "geometry": {"coordinates":[120.01663000000001,28.20674],"type":"Point"}
}