{
  "type": "Feature",
  "properties": {
    "gn:admin1_code":"2.0",
    "gn:asciiname":"Datong",
    "gn:country_code":"CN",
    "gn:dem":191,
    "gn:feature_class":"P",
    "gn:feature_code":"PPL",
    "gn:name":"Datong",
    "gn:population":0,
    "gn:timezone":"Asia/Shanghai",
    "iso:country":"CN",
    "name:afr_x_preferred":[
        "Datong"
    ],
    "name:ara_x_preferred":[
        "\u062f\u0627\u062a\u0648\u0646\u063a"
    ],
    "name:bre_x_preferred":[
        "Datong"
    ],
    "name:bul_x_preferred":[
        "\u0414\u0430\u0442\u0443\u043d"
    ],
    "name:cat_x_preferred":[
        "Datong"
    ],
    "name:cdo_x_preferred":[
        "D\u00e2i-d\u00f9ng"
    ],
    "name:ceb_x_preferred":[
        "Datong Shi"
    ],
    "name:ces_x_preferred":[
        "Ta-tchung"
    ],
    "name:dan_x_preferred":[
        "Datong"
    ],
    "name:deu_x_preferred":[
        "Datong"
    ],
    "name:epo_x_preferred":[
        "Datongo"
    ],
    "name:eus_x_preferred":[
        "Datong"
    ],
    "name:fas_x_preferred":[
        "\u062f\u0627\u062a\u0648\u0646\u06af"
    ],
    "name:fin_x_preferred":[
        "Datong"
    ],
    "name:fra_x_preferred":[
        "Datong"
    ],
    "name:heb_x_preferred":[
        "\u05d3\u05d0\u05d8\u05d5\u05e0\u05d2"
    ],
    "name:hun_x_preferred":[
        "Datong"
    ],
    "name:ina_x_preferred":[
        "Datong"
    ],
    "name:ind_x_preferred":[
        "Datong"
    ],
    "name:ita_x_preferred":[
        "Datong"
    ],
    "name:jpn_x_preferred":[
        "\u5927\u540c\u5e02"
    ],
    "name:kaz_x_preferred":[
        "\u0414\u0430\u0442\u0443\u043d"
    ],
    "name:kik_x_preferred":[
        "Datong"
    ],
    "name:kor_x_preferred":[
        "\ub2e4\ud241\uc2dc"
    ],
    "name:lit_x_preferred":[
        "Datongas"
    ],
    "name:mlg_x_preferred":[
        "Datong"
    ],
    "name:mon_x_preferred":[
        "\u0414\u0430\u0442\u0443\u043d"
    ],
    "name:nld_x_preferred":[
        "Datong"
    ],
    "name:nno_x_preferred":[
        "Datong"
    ],
    "name:nor_x_preferred":[
        "Datong"
    ],
    "name:pol_x_preferred":[
        "Datong"
    ],
    "name:por_x_preferred":[
        "Datong"
    ],
    "name:rus_x_preferred":[
        "\u0414\u0430\u0442\u0443\u043d"
    ],
    "name:spa_x_preferred":[
        "Datong"
    ],
    "name:srp_x_preferred":[
        "\u0414\u0430\u0442\u0443\u043d\u0433"
    ],
    "name:swe_x_preferred":[
        "Datong"
    ],
    "name:tgl_x_preferred":[
        "Datong"
    ],
    "name:tur_x_preferred":[
        "Datong"
    ],
    "name:uig_x_preferred":[
        "\u062f\u0627\u062a\u06c7\u06ad \u0634\u06d5\u06be\u0649\u0631"
    ],
    "name:ukr_x_preferred":[
        "\u0414\u0430\u0442\u0443\u043d"
    ],
    "name:urd_x_preferred":[
        "\u062f\u0627\u062a\u0648\u0646\u06af"
    ],
    "name:vie_x_preferred":[
        "\u0110\u1ea1i \u0110\u1ed3ng"
    ],
    "name:war_x_preferred":[
        "Datong"
    ],
    "name:wuu_x_preferred":[
        "\u5927\u540c\u5e02"
    ],
    "name:zho_x_preferred":[
        "\u5927\u540c"
    ],
    "name:zho_x_variant":[
        "\u5927\u540c\u5e02"
    ],
    "wof:name":"Datong",
    "wof:placetype":"locality"
},
  "geometry": {"coordinates":[118.48186,28.48695],"type":"Point"}
}