{
  "type": "Feature",
  "properties": {
    "gn:admin1_code":"11",
    "gn:asciiname":"Dama",
    "gn:country_code":"CN",
    "gn:dem":450,
    "gn:feature_class":"P",
    "gn:feature_code":"PPL",
    "gn:name":"Dama",
    "gn:population":0,
    "gn:timezone":"Asia/Shanghai",
    "iso:country":"CN",
    "name:und_x_variant":[
        "Ta-ma-ying",
        "Damaying",
        "Dama"
    ],
    "name:zho_x_preferred":[
        "\u5927\u9ebb"
    ],
    "name:zho_x_variant":[
        "\u5927\u9ebb\u8425"
    ],
    "wof:name":"Dama",
    "wof:placetype":"locality"
},
  "geometry": {"coordinates":[112.13661,25.21523],"type":"Point"}
}