{
  "type": "Feature",
  "properties": {
    "gn:admin1_code":"8.0",
    "gn:asciiname":"Tuolimucun",
    "gn:country_code":"CN",
    "gn:dem":139,
    "gn:feature_class":"P",
    "gn:feature_code":"PPL",
    "gn:name":"Tuolimucun",
    "gn:population":0,
    "gn:timezone":"Asia/Shanghai",
    "iso:country":"CN",
    "name:zho_x_preferred":[
        "\u6258\u529b\u6728\u6751"
    ],
    "wof:name":"Tuolimucun",
    "wof:placetype":"locality"
},
  "geometry": {"coordinates":[127.35861,49.86386],"type":"Point"}
}