{
  "type": "Feature",
  "properties": {
    "gn:admin1_code":"32",
    "gn:asciiname":"Shiwengzi",
    "gn:country_code":"CN",
    "gn:dem":768,
    "gn:feature_class":"P",
    "gn:feature_code":"PPL",
    "gn:name":"Shiwengzi",
    "gn:population":0,
    "gn:timezone":"Asia/Shanghai",
    "iso:country":"CN",
    "name:zho_x_preferred":[
        "\u77f3\u74ee\u5b50"
    ],
    "wof:name":"Shiwengzi",
    "wof:placetype":"locality"
},
  "geometry": {"coordinates":[105.44528,32.25769],"type":"Point"}
}