{
  "type": "Feature",
  "properties": {
    "gn:admin1_code":"3.0",
    "gn:asciiname":"Zhangxiawei",
    "gn:country_code":"CN",
    "gn:dem":284,
    "gn:feature_class":"P",
    "gn:feature_code":"PPL",
    "gn:name":"Zhangxiawei",
    "gn:population":0,
    "gn:timezone":"Asia/Shanghai",
    "iso:country":"CN",
    "name:zho_x_preferred":[
        "\u6a1f\u4e0b\u5c3e"
    ],
    "wof:name":"Zhangxiawei",
    "wof:placetype":"locality"
},
  "geometry": {"coordinates":[114.878,25.012],"type":"Point"}
}