{
  "type": "Feature",
  "properties": {
    "gn:admin1_code":"8.0",
    "gn:asciiname":"Shiliuhu",
    "gn:country_code":"CN",
    "gn:dem":148,
    "gn:feature_class":"P",
    "gn:feature_code":"PPL",
    "gn:name":"Shiliuhu",
    "gn:population":0,
    "gn:timezone":"Asia/Shanghai",
    "iso:country":"CN",
    "name:zho_x_preferred":[
        "\u5341\u516d\u6237"
    ],
    "wof:name":"Shiliuhu",
    "wof:placetype":"locality"
},
  "geometry": {"coordinates":[124.83449,46.50027],"type":"Point"}
}