{
  "type": "Feature",
  "properties": {
    "gn:admin1_code":"2.0",
    "gn:asciiname":"Hengling",
    "gn:country_code":"CN",
    "gn:dem":260,
    "gn:feature_class":"P",
    "gn:feature_code":"PPL",
    "gn:name":"Hengling",
    "gn:population":0,
    "gn:timezone":"Asia/Shanghai",
    "iso:country":"CN",
    "name:und_x_variant":[
        "\u6a2a\u5cad"
    ],
    "wof:name":"Hengling",
    "wof:placetype":"locality"
},
  "geometry": {"coordinates":[119.84411,30.6824],"type":"Point"}
}