{
  "type": "Feature",
  "properties": {
    "gn:admin1_code":"18",
    "gn:asciiname":"Zhala",
    "gn:country_code":"CN",
    "gn:dem":1292,
    "gn:feature_class":"P",
    "gn:feature_code":"PPL",
    "gn:name":"Zhala",
    "gn:population":0,
    "gn:timezone":"Asia/Shanghai",
    "iso:country":"CN",
    "name:zho_x_preferred":[
        "\u55b3\u5566"
    ],
    "wof:name":"Zhala",
    "wof:placetype":"locality"
},
  "geometry": {"coordinates":[105.328,25.3878],"type":"Point"}
}