{
  "type": "Feature",
  "properties": {
    "gn:admin1_code":"15.0",
    "gn:asciiname":"Gaolingzi",
    "gn:country_code":"CN",
    "gn:dem":1581,
    "gn:feature_class":"P",
    "gn:feature_code":"PPL",
    "gn:name":"Gaolingzi",
    "gn:population":0,
    "gn:timezone":"Asia/Shanghai",
    "iso:country":"CN",
    "name:und_x_variant":[
        "\u9ad8\u5cad\u5b50"
    ],
    "wof:name":"Gaolingzi",
    "wof:placetype":"locality"
},
  "geometry": {"coordinates":[107.60104,36.56114],"type":"Point"}
}