{
  "type": "Feature",
  "properties": {
    "gn:admin1_code":"29",
    "gn:asciiname":"Maileguo",
    "gn:country_code":"CN",
    "gn:dem":1975,
    "gn:feature_class":"P",
    "gn:feature_code":"PPL",
    "gn:name":"Maileguo",
    "gn:population":0,
    "gn:timezone":"Asia/Shanghai",
    "iso:country":"CN",
    "name:zho_x_preferred":[
        "\u9ea6\u52d2\u679c"
    ],
    "wof:name":"Maileguo",
    "wof:placetype":"locality"
},
  "geometry": {"coordinates":[102.989,24.1071],"type":"Point"}
}