{
  "type": "Feature",
  "properties": {
    "gn:admin1_code":"32.0",
    "gn:asciiname":"Jinyin",
    "gn:country_code":"CN",
    "gn:dem":918,
    "gn:feature_class":"P",
    "gn:feature_code":"PPL",
    "gn:name":"Jinyin",
    "gn:population":0,
    "gn:timezone":"Asia/Shanghai",
    "iso:country":"CN",
    "name:und_x_variant":[
        "\u91d1\u94f6"
    ],
    "wof:name":"Jinyin",
    "wof:placetype":"locality"
},
  "geometry": {"coordinates":[106.13033,32.38652],"type":"Point"}
}