{
  "type": "Feature",
  "properties": {
    "gn:admin1_code":"29.0",
    "gn:asciiname":"Shuiqingdeng",
    "gn:country_code":"CN",
    "gn:dem":2418,
    "gn:feature_class":"P",
    "gn:feature_code":"PPL",
    "gn:name":"Shuiqingdeng",
    "gn:population":0,
    "gn:timezone":"Asia/Shanghai",
    "iso:country":"CN",
    "name:zho_x_preferred":[
        "\u6c34\u6e05\u767b"
    ],
    "wof:name":"Shuiqingdeng",
    "wof:placetype":"locality"
},
  "geometry": {"coordinates":[99.1561,26.9549],"type":"Point"}
}