{
  "type": "Feature",
  "properties": {
    "gn:admin1_code":"11.0",
    "gn:asciiname":"Shijiti",
    "gn:country_code":"CN",
    "gn:dem":119,
    "gn:feature_class":"P",
    "gn:feature_code":"PPL",
    "gn:name":"Shijiti",
    "gn:population":0,
    "gn:timezone":"Asia/Shanghai",
    "iso:country":"CN",
    "name:zho_x_preferred":[
        "\u77f3\u9e21\u557c"
    ],
    "wof:name":"Shijiti",
    "wof:placetype":"locality"
},
  "geometry": {"coordinates":[112.31567,27.89321],"type":"Point"}
}