{
  "type": "Feature",
  "properties": {
    "gn:admin1_code":"15.0",
    "gn:asciiname":"Lingshang",
    "gn:country_code":"CN",
    "gn:dem":2843,
    "gn:feature_class":"P",
    "gn:feature_code":"PPL",
    "gn:name":"Lingshang",
    "gn:population":0,
    "gn:timezone":"Asia/Shanghai",
    "iso:country":"CN",
    "name:und_x_variant":[
        "\u5cad\u4e0a"
    ],
    "wof:name":"Lingshang",
    "wof:placetype":"locality"
},
  "geometry": {"coordinates":[103.60505000000001,34.64518],"type":"Point"}
}