{
  "type": "Feature",
  "properties": {
    "gn:admin1_code":"3.0",
    "gn:asciiname":"Yuekengli",
    "gn:country_code":"CN",
    "gn:dem":349,
    "gn:feature_class":"P",
    "gn:feature_code":"PPL",
    "gn:name":"Yuekengli",
    "gn:population":0,
    "gn:timezone":"Asia/Shanghai",
    "iso:country":"CN",
    "name:und_x_variant":[
        "\u6708\u5751\u91cc"
    ],
    "wof:name":"Yuekengli",
    "wof:placetype":"locality"
},
  "geometry": {"coordinates":[115.2439,29.18415],"type":"Point"}
}