{
  "type": "Feature",
  "properties": {
    "gn:admin1_code":"32.0",
    "gn:asciiname":"Haizikou",
    "gn:country_code":"CN",
    "gn:dem":2668,
    "gn:feature_class":"P",
    "gn:feature_code":"PPL",
    "gn:name":"Haizikou",
    "gn:population":0,
    "gn:timezone":"Asia/Shanghai",
    "iso:country":"CN",
    "name:zho_x_preferred":[
        "\u6d77\u5b50\u53e3"
    ],
    "wof:name":"Haizikou",
    "wof:placetype":"locality"
},
  "geometry": {"coordinates":[103.76600000000001,33.2639],"type":"Point"}
}