{
  "type": "Feature",
  "properties": {
    "gn:admin1_code":"8.0",
    "gn:asciiname":"Xiweizicun",
    "gn:country_code":"CN",
    "gn:dem":318,
    "gn:feature_class":"P",
    "gn:feature_code":"PPL",
    "gn:name":"Xiweizicun",
    "gn:population":0,
    "gn:timezone":"Asia/Shanghai",
    "iso:country":"CN",
    "name:zho_x_preferred":[
        "\u897f\u5d34\u5b50\u6751"
    ],
    "wof:name":"Xiweizicun",
    "wof:placetype":"locality"
},
  "geometry": {"coordinates":[130.27838,44.5677],"type":"Point"}
}