{
  "type": "Feature",
  "properties": {
    "gn:admin1_code":"26.0",
    "gn:asciiname":"Dabaiguoyuan",
    "gn:country_code":"CN",
    "gn:dem":1278,
    "gn:feature_class":"P",
    "gn:feature_code":"PPL",
    "gn:name":"Dabaiguoyuan",
    "gn:population":0,
    "gn:timezone":"Asia/Shanghai",
    "iso:country":"CN",
    "name:zho_x_preferred":[
        "\u5927\u767d\u679c\u56ed"
    ],
    "wof:name":"Dabaiguoyuan",
    "wof:placetype":"locality"
},
  "geometry": {"coordinates":[109.93022000000001,33.22978],"type":"Point"}
}