{
  "type": "Feature",
  "properties": {
    "gn:admin1_code":"26",
    "gn:asciiname":"Huangjia Heba",
    "gn:country_code":"CN",
    "gn:dem":729,
    "gn:feature_class":"P",
    "gn:feature_code":"PPL",
    "gn:name":"Huangjia Heba",
    "gn:population":0,
    "gn:timezone":"Asia/Shanghai",
    "iso:country":"CN",
    "name:zho_x_preferred":[
        "\u9ec4\u5bb6\u6cb3\u575d"
    ],
    "wof:name":"Huangjia Heba",
    "wof:placetype":"locality"
},
  "geometry": {"coordinates":[107.79806000000001,33.18444],"type":"Point"}
}