{
  "type": "Feature",
  "properties": {
    "gn:admin1_code":"7.0",
    "gn:asciiname":"Tingxia",
    "gn:country_code":"CN",
    "gn:dem":8,
    "gn:feature_class":"P",
    "gn:feature_code":"PPL",
    "gn:name":"Tingxia",
    "gn:population":0,
    "gn:timezone":"Asia/Shanghai",
    "iso:country":"CN",
    "name:und_x_variant":[
        "\u4ead\u4e0b"
    ],
    "name:zho_x_preferred":[
        "Tingxia"
    ],
    "wof:name":"Tingxia",
    "wof:placetype":"locality"
},
  "geometry": {"coordinates":[119.23556000000001,26.11356],"type":"Point"}
}