{
  "type": "Feature",
  "properties": {
    "gn:admin1_code":"19.0",
    "gn:asciiname":"Xiaobu",
    "gn:country_code":"CN",
    "gn:dem":349,
    "gn:feature_class":"P",
    "gn:feature_code":"PPL",
    "gn:name":"Xiaobu",
    "gn:population":0,
    "gn:timezone":"Asia/Shanghai",
    "iso:country":"CN",
    "name:und_x_variant":[
        "Xiaopu",
        "Xiaobu"
    ],
    "name:zho_x_preferred":[
        "\u5c0f\u5821"
    ],
    "wof:name":"Xiaobu",
    "wof:placetype":"locality"
},
  "geometry": {"coordinates":[124.79000000000001,42.2798],"type":"Point"}
}