{
  "type": "Feature",
  "properties": {
    "gn:admin1_code":"04",
    "gn:asciiname":"Hutoucun",
    "gn:country_code":"CN",
    "gn:dem":10,
    "gn:feature_class":"P",
    "gn:feature_code":"PPL",
    "gn:name":"Hutoucun",
    "gn:population":0,
    "gn:timezone":"Asia/Shanghai",
    "iso:country":"CN",
    "name:und_x_variant":[
        "Hu-t\u2019ou-chen",
        "Hutou",
        "Hutoucun"
    ],
    "name:zho_x_preferred":[
        "\u6e56\u5934"
    ],
    "name:zho_x_variant":[
        "\u6e56\u5934\u6751"
    ],
    "wof:name":"Hutoucun",
    "wof:placetype":"locality"
},
  "geometry": {"coordinates":[119.61511000000002,31.62347],"type":"Point"}
}