{
  "type": "Feature",
  "properties": {
    "gn:admin1_code":"32.0",
    "gn:asciiname":"Qijiatun",
    "gn:country_code":"CN",
    "gn:dem":1515,
    "gn:feature_class":"P",
    "gn:feature_code":"PPL",
    "gn:name":"Qijiatun",
    "gn:population":0,
    "gn:timezone":"Asia/Shanghai",
    "iso:country":"CN",
    "name:zho_x_preferred":[
        "\u9f50\u5bb6\u5c6f"
    ],
    "wof:name":"Qijiatun",
    "wof:placetype":"locality"
},
  "geometry": {"coordinates":[102.242,27.8865],"type":"Point"}
}