{
  "type": "Feature",
  "properties": {
    "gn:admin1_code":"18.0",
    "gn:asciiname":"Mangzhai",
    "gn:country_code":"CN",
    "gn:dem":756,
    "gn:feature_class":"P",
    "gn:feature_code":"PPL",
    "gn:name":"Mangzhai",
    "gn:population":0,
    "gn:timezone":"Asia/Shanghai",
    "iso:country":"CN",
    "name:zho_x_preferred":[
        "\u5fd9\u5be8"
    ],
    "wof:name":"Mangzhai",
    "wof:placetype":"locality"
},
  "geometry": {"coordinates":[108.85899999999999,26.1755],"type":"Point"}
}