{
  "type": "Feature",
  "properties": {
    "gn:admin1_code":"15.0",
    "gn:asciiname":"Wangjia Yatou",
    "gn:country_code":"CN",
    "gn:dem":2075,
    "gn:feature_class":"P",
    "gn:feature_code":"PPL",
    "gn:name":"Wangjia Yatou",
    "gn:population":0,
    "gn:timezone":"Asia/Shanghai",
    "iso:country":"CN",
    "name:zho_x_preferred":[
        "\u738b\u5bb6\u5d16\u5934"
    ],
    "wof:name":"Wangjia Yatou",
    "wof:placetype":"locality"
},
  "geometry": {"coordinates":[103.13500000000001,35.5174],"type":"Point"}
}