{
  "type": "Feature",
  "properties": {
    "gn:admin1_code":"8.0",
    "gn:asciiname":"Xiangqiancun",
    "gn:country_code":"CN",
    "gn:dem":220,
    "gn:feature_class":"P",
    "gn:feature_code":"PPL",
    "gn:name":"Xiangqiancun",
    "gn:population":0,
    "gn:timezone":"Asia/Shanghai",
    "iso:country":"CN",
    "name:zho_x_preferred":[
        "\u5411\u524d\u6751"
    ],
    "wof:name":"Xiangqiancun",
    "wof:placetype":"locality"
},
  "geometry": {"coordinates":[127.50462,46.62929000000001],"type":"Point"}
}