{
  "type": "Feature",
  "properties": {
    "gn:admin1_code":"14.0",
    "gn:asciiname":"Omaciu",
    "gn:country_code":"CN",
    "gn:dem":4690,
    "gn:feature_class":"P",
    "gn:feature_code":"PPL",
    "gn:name":"Omaciu",
    "gn:population":0,
    "gn:timezone":"Asia/Urumqi",
    "iso:country":"CN",
    "name:bod_x_preferred":[
        "Omaciu"
    ],
    "name:zho_x_preferred":[
        "Womaciwu"
    ],
    "name:zho_x_variant":[
        "\u6c83\u739b\u6b21\u4e4c",
        "Ejumaima Gongshe",
        "\u54e6\u5c45\u4e70\u9a6c\u516c\u793e",
        "\u6c83\u9a6c\u6b21\u4e4c"
    ],
    "wof:name":"Omaciu",
    "wof:placetype":"locality"
},
  "geometry": {"coordinates":[86.79859999999999,32.2051],"type":"Point"}
}