{
  "type": "Feature",
  "properties": {
    "gn:admin1_code":"04",
    "gn:asciiname":"Dagang",
    "gn:cc2":"CN",
    "gn:country_code":"CN",
    "gn:dem":2,
    "gn:feature_class":"P",
    "gn:feature_code":"PPL",
    "gn:name":"Dagang",
    "gn:population":0,
    "gn:timezone":"Asia/Shanghai",
    "iso:country":"CN",
    "name:und_x_variant":[
        "Ta-kang",
        "Ta-kang-chen",
        "Dagang"
    ],
    "wof:name":"Dagang",
    "wof:placetype":"locality"
},
  "geometry": {"coordinates":[120.11278,33.17722],"type":"Point"}
}