{
  "type": "Feature",
  "properties": {
    "gn:admin1_code":"14.0",
    "gn:asciiname":"Dengyoujiu",
    "gn:country_code":"CN",
    "gn:dem":4344,
    "gn:feature_class":"P",
    "gn:feature_code":"PPL",
    "gn:name":"Dengyoujiu",
    "gn:population":0,
    "gn:timezone":"Asia/Urumqi",
    "iso:country":"CN",
    "name:zho_x_preferred":[
        "\u706f\u5c24\u7396"
    ],
    "wof:name":"Dengyoujiu",
    "wof:placetype":"locality"
},
  "geometry": {"coordinates":[94.63137999999999,29.80972],"type":"Point"}
}