{
  "type": "Feature",
  "properties": {
    "gn:admin1_code":"3.0",
    "gn:asciiname":"Caotangwan",
    "gn:country_code":"CN",
    "gn:dem":33,
    "gn:feature_class":"P",
    "gn:feature_code":"PPL",
    "gn:name":"Caotangwan",
    "gn:population":0,
    "gn:timezone":"Asia/Shanghai",
    "iso:country":"CN",
    "name:und_x_variant":[
        "\u8349\u5858\u6e7e"
    ],
    "wof:name":"Caotangwan",
    "wof:placetype":"locality"
},
  "geometry": {"coordinates":[116.38379999999999,29.81129],"type":"Point"}
}