{
  "type": "Feature",
  "properties": {
    "gn:admin1_code":"18.0",
    "gn:asciiname":"Xiayangtuan",
    "gn:country_code":"CN",
    "gn:dem":431,
    "gn:feature_class":"P",
    "gn:feature_code":"PPL",
    "gn:name":"Xiayangtuan",
    "gn:population":0,
    "gn:timezone":"Asia/Shanghai",
    "iso:country":"CN",
    "name:zho_x_preferred":[
        "\u4e0b\u7f8a\u56e2"
    ],
    "wof:name":"Xiayangtuan",
    "wof:placetype":"locality"
},
  "geometry": {"coordinates":[109.197,26.3615],"type":"Point"}
}