{
  "type": "Feature",
  "properties": {
    "gn:admin1_code":"2.0",
    "gn:asciiname":"Daxijiang",
    "gn:country_code":"CN",
    "gn:dem":15,
    "gn:feature_class":"P",
    "gn:feature_code":"PPL",
    "gn:name":"Daxijiang",
    "gn:population":0,
    "gn:timezone":"Asia/Shanghai",
    "iso:country":"CN",
    "name:zho_x_preferred":[
        "\u5927\u6eaa\u848b"
    ],
    "wof:name":"Daxijiang",
    "wof:placetype":"locality"
},
  "geometry": {"coordinates":[121.82177,29.4788],"type":"Point"}
}