{
  "type": "Feature",
  "properties": {
    "gn:admin1_code":"5.0",
    "gn:asciiname":"Changshoutun",
    "gn:country_code":"CN",
    "gn:dem":386,
    "gn:feature_class":"P",
    "gn:feature_code":"PPL",
    "gn:name":"Changshoutun",
    "gn:population":0,
    "gn:timezone":"Asia/Shanghai",
    "iso:country":"CN",
    "name:und_x_variant":[
        "\u957f\u5bff\u5c6f"
    ],
    "wof:name":"Changshoutun",
    "wof:placetype":"locality"
},
  "geometry": {"coordinates":[126.94311999999999,43.05794],"type":"Point"}
}