{
  "type": "Feature",
  "properties": {
    "gn:admin1_code":"26.0",
    "gn:asciiname":"Yangjia Wuchang",
    "gn:country_code":"CN",
    "gn:dem":618,
    "gn:feature_class":"P",
    "gn:feature_code":"PPL",
    "gn:name":"Yangjia Wuchang",
    "gn:population":0,
    "gn:timezone":"Asia/Shanghai",
    "iso:country":"CN",
    "name:zho_x_preferred":[
        "\u6768\u5bb6\u5c4b\u573a"
    ],
    "wof:name":"Yangjia Wuchang",
    "wof:placetype":"locality"
},
  "geometry": {"coordinates":[110.68124,33.40454],"type":"Point"}
}