{
  "type": "Feature",
  "properties": {
    "gn:admin1_code":"10",
    "gn:asciiname":"Linjiaying",
    "gn:country_code":"CN",
    "gn:dem":1209,
    "gn:feature_class":"P",
    "gn:feature_code":"PPL",
    "gn:name":"Linjiaying",
    "gn:population":0,
    "gn:timezone":"Asia/Shanghai",
    "iso:country":"CN",
    "name:zho_x_preferred":[
        "\u6797\u5bb6\u8425"
    ],
    "wof:name":"Linjiaying",
    "wof:placetype":"locality"
},
  "geometry": {"coordinates":[116.86099,41.56506],"type":"Point"}
}