{
  "type": "Feature",
  "properties": {
    "gn:admin1_code":"3.0",
    "gn:asciiname":"Sannao Wujia",
    "gn:country_code":"CN",
    "gn:dem":33,
    "gn:feature_class":"P",
    "gn:feature_code":"PPL",
    "gn:name":"Sannao Wujia",
    "gn:population":0,
    "gn:timezone":"Asia/Shanghai",
    "iso:country":"CN",
    "name:und_x_variant":[
        "\u4e09\u8111\u5434\u5bb6"
    ],
    "wof:name":"Sannao Wujia",
    "wof:placetype":"locality"
},
  "geometry": {"coordinates":[116.86660000000001,28.32817],"type":"Point"}
}