{
  "type": "Feature",
  "properties": {
    "gn:admin1_code":"10.0",
    "gn:asciiname":"Zhaobazhuang",
    "gn:country_code":"CN",
    "gn:dem":29,
    "gn:feature_class":"P",
    "gn:feature_code":"PPL",
    "gn:name":"Zhaobazhuang",
    "gn:population":0,
    "gn:timezone":"Asia/Shanghai",
    "iso:country":"CN",
    "name:zho_x_preferred":[
        "\u8d75\u516b\u5e84"
    ],
    "wof:name":"Zhaobazhuang",
    "wof:placetype":"locality"
},
  "geometry": {"coordinates":[115.512,38.1673],"type":"Point"}
}