{
  "type": "Feature",
  "properties": {
    "gn:admin1_code":"31.0",
    "gn:asciiname":"Xin'andui",
    "gn:country_code":"CN",
    "gn:dem":175,
    "gn:feature_class":"P",
    "gn:feature_code":"PPL",
    "gn:name":"Xin\u2019andui",
    "gn:population":0,
    "gn:timezone":"Asia/Shanghai",
    "iso:country":"CN",
    "name:zho_x_preferred":[
        "Xin\u2019andui"
    ],
    "name:zho_x_variant":[
        "\u65b0\u5b89\u961f"
    ],
    "wof:name":"Xin'andui",
    "wof:placetype":"locality"
},
  "geometry": {"coordinates":[109.93765,18.9407],"type":"Point"}
}