{
  "type": "Feature",
  "properties": {
    "gn:admin1_code":"6.0",
    "gn:asciiname":"De'ang",
    "gn:country_code":"CN",
    "gn:dem":3602,
    "gn:feature_class":"P",
    "gn:feature_code":"PPL",
    "gn:name":"De\u2019ang",
    "gn:population":0,
    "gn:timezone":"Asia/Shanghai",
    "iso:country":"CN",
    "name:und_x_variant":[
        "De\u2019ang"
    ],
    "name:zho_x_preferred":[
        "\u5fb7\u6602"
    ],
    "wof:name":"De'ang",
    "wof:placetype":"locality"
},
  "geometry": {"coordinates":[100.69226999999999,32.93747],"type":"Point"}
}