{
  "type": "Feature",
  "properties": {
    "gn:admin1_code":"12.0",
    "gn:asciiname":"Zimutan",
    "gn:country_code":"CN",
    "gn:dem":1067,
    "gn:feature_class":"P",
    "gn:feature_code":"PPL",
    "gn:name":"Zimutan",
    "gn:population":0,
    "gn:timezone":"Asia/Shanghai",
    "iso:country":"CN",
    "name:zho_x_preferred":[
        "\u5b50\u6bcd\u6f6d"
    ],
    "wof:name":"Zimutan",
    "wof:placetype":"locality"
},
  "geometry": {"coordinates":[109.93646,30.74774],"type":"Point"}
}