{
  "type": "Feature",
  "properties": {
    "gn:admin1_code":"1.0",
    "gn:asciiname":"Dahucun",
    "gn:country_code":"CN",
    "gn:dem":58,
    "gn:feature_class":"P",
    "gn:feature_code":"PPL",
    "gn:name":"Dahucun",
    "gn:population":0,
    "gn:timezone":"Asia/Shanghai",
    "iso:country":"CN",
    "name:zho_x_preferred":[
        "\u5927\u80e1\u6751"
    ],
    "wof:name":"Dahucun",
    "wof:placetype":"locality"
},
  "geometry": {"coordinates":[117.76007,32.12447],"type":"Point"}
}