{
  "type": "Feature",
  "properties": {
    "gn:admin1_code":"5.0",
    "gn:asciiname":"Liujia Weizicun",
    "gn:country_code":"CN",
    "gn:dem":131,
    "gn:feature_class":"P",
    "gn:feature_code":"PPL",
    "gn:name":"Liujia Weizicun",
    "gn:population":0,
    "gn:timezone":"Asia/Shanghai",
    "iso:country":"CN",
    "name:zho_x_preferred":[
        "\u5218\u5bb6\u56f4\u5b50\u6751"
    ],
    "wof:name":"Liujia Weizicun",
    "wof:placetype":"locality"
},
  "geometry": {"coordinates":[124.63906,45.20083],"type":"Point"}
}