{
  "type": "Feature",
  "properties": {
    "gn:admin1_code":"9.0",
    "gn:asciiname":"Liupo",
    "gn:country_code":"CN",
    "gn:dem":540,
    "gn:feature_class":"P",
    "gn:feature_code":"PPL",
    "gn:name":"Liupo",
    "gn:population":0,
    "gn:timezone":"Asia/Shanghai",
    "iso:country":"CN",
    "name:und_x_variant":[
        "\u5218\u5761",
        "Liupo"
    ],
    "wof:name":"Liupo",
    "wof:placetype":"locality"
},
  "geometry": {"coordinates":[112.02976,33.2968],"type":"Point"}
}