{
  "type": "Feature",
  "properties": {
    "gn:admin1_code":"18",
    "gn:asciiname":"Rongyao",
    "gn:country_code":"CN",
    "gn:dem":1286,
    "gn:feature_class":"P",
    "gn:feature_code":"PPL",
    "gn:name":"Rongyao",
    "gn:population":0,
    "gn:timezone":"Asia/Shanghai",
    "iso:country":"CN",
    "name:zho_x_preferred":[
        "\u5197\u8981"
    ],
    "wof:name":"Rongyao",
    "wof:placetype":"locality"
},
  "geometry": {"coordinates":[105.31999999999999,25.1091],"type":"Point"}
}