{
  "type": "Feature",
  "properties": {
    "gn:admin1_code":"30.0",
    "gn:asciiname":"Chashan'ao",
    "gn:country_code":"CN",
    "gn:dem":92,
    "gn:feature_class":"P",
    "gn:feature_code":"PPL",
    "gn:name":"Chashan\u2019ao",
    "gn:population":0,
    "gn:timezone":"Asia/Shanghai",
    "iso:country":"CN",
    "name:zho_x_preferred":[
        "Chashan\u2019ao"
    ],
    "name:zho_x_variant":[
        "\u8336\u5c71\u5773"
    ],
    "wof:name":"Chashan'ao",
    "wof:placetype":"locality"
},
  "geometry": {"coordinates":[113.41097000000001,24.91997000000001],"type":"Point"}
}