{
  "type": "Feature",
  "properties": {
    "gn:admin1_code":"30",
    "gn:asciiname":"Chikeng",
    "gn:country_code":"CN",
    "gn:dem":293,
    "gn:feature_class":"P",
    "gn:feature_code":"PPLA4",
    "gn:name":"Chikeng",
    "gn:population":0,
    "gn:timezone":"Asia/Shanghai",
    "iso:country":"CN",
    "name:und_x_variant":[
        "Chikeng Zhen",
        "\u8d64\u5751\u9547"
    ],
    "name:zho_x_preferred":[
        "\u8d64\u5751"
    ],
    "wof:name":"Chikeng",
    "wof:placetype":"locality"
},
  "geometry": {"coordinates":[112.47692000000001,23.85097],"type":"Point"}
}