{
  "type": "Feature",
  "properties": {
    "gn:admin1_code":"32.0",
    "gn:asciiname":"Zidu",
    "gn:country_code":"CN",
    "gn:dem":2748,
    "gn:feature_class":"P",
    "gn:feature_code":"PPL",
    "gn:name":"Zidu",
    "gn:population":0,
    "gn:timezone":"Asia/Shanghai",
    "iso:country":"CN",
    "name:zho_x_preferred":[
        "\u81ea\u90fd"
    ],
    "wof:name":"Zidu",
    "wof:placetype":"locality"
},
  "geometry": {"coordinates":[102.384,27.9703],"type":"Point"}
}