{
  "type": "Feature",
  "properties": {
    "gn:admin1_code":"10",
    "gn:asciiname":"Dijiucun",
    "gn:country_code":"CN",
    "gn:dem":27,
    "gn:feature_class":"P",
    "gn:feature_code":"PPL",
    "gn:name":"Dijiucun",
    "gn:population":0,
    "gn:timezone":"Asia/Shanghai",
    "iso:country":"CN",
    "name:zho_x_preferred":[
        "\u7b2c\u4e5d\u6751"
    ],
    "wof:name":"Dijiucun",
    "wof:placetype":"locality"
},
  "geometry": {"coordinates":[116.23846,37.37366],"type":"Point"}
}