{
  "type": "Feature",
  "properties": {
    "gn:admin1_code":"18",
    "gn:asciiname":"Yandiba",
    "gn:country_code":"CN",
    "gn:dem":1147,
    "gn:feature_class":"P",
    "gn:feature_code":"PPL",
    "gn:name":"Yandiba",
    "gn:population":0,
    "gn:timezone":"Asia/Shanghai",
    "iso:country":"CN",
    "name:zho_x_preferred":[
        "\u5ca9\u5e95\u575d"
    ],
    "wof:name":"Yandiba",
    "wof:placetype":"locality"
},
  "geometry": {"coordinates":[106.42100000000001,27.9355],"type":"Point"}
}