{
  "type": "Feature",
  "properties": {
    "gn:admin1_code":"15.0",
    "gn:asciiname":"Chuncha",
    "gn:country_code":"CN",
    "gn:dem":1517,
    "gn:feature_class":"P",
    "gn:feature_code":"PPL",
    "gn:name":"Chuncha",
    "gn:population":0,
    "gn:timezone":"Asia/Shanghai",
    "iso:country":"CN",
    "name:zho_x_preferred":[
        "\u6625\u5c94"
    ],
    "wof:name":"Chuncha",
    "wof:placetype":"locality"
},
  "geometry": {"coordinates":[106.98099999999999,35.8057],"type":"Point"}
}