{
  "type": "Feature",
  "properties": {
    "gn:admin1_code":"6.0",
    "gn:asciiname":"Minzhu",
    "gn:country_code":"CN",
    "gn:dem":3695,
    "gn:feature_class":"P",
    "gn:feature_code":"PPL",
    "gn:name":"Minzhu",
    "gn:population":0,
    "gn:timezone":"Asia/Urumqi",
    "iso:country":"CN",
    "name:zho_x_preferred":[
        "\u6c11\u4e3b"
    ],
    "wof:name":"Minzhu",
    "wof:placetype":"locality"
},
  "geometry": {"coordinates":[97.00783,32.98984],"type":"Point"}
}