{
  "type": "Feature",
  "properties": {
    "gn:admin1_code":"24",
    "gn:asciiname":"Liaoyuan",
    "gn:country_code":"CN",
    "gn:dem":1070,
    "gn:feature_class":"P",
    "gn:feature_code":"PPL",
    "gn:name":"Liaoyuan",
    "gn:population":0,
    "gn:timezone":"Asia/Shanghai",
    "iso:country":"CN",
    "wof:name":"Liaoyuan",
    "wof:placetype":"locality"
},
  "geometry": {"coordinates":[112.79111,37.12278],"type":"Point"}
}