{
  "type": "Feature",
  "properties": {
    "gn:admin1_code":"26.0",
    "gn:asciiname":"Qiancuncun",
    "gn:country_code":"CN",
    "gn:dem":1226,
    "gn:feature_class":"P",
    "gn:feature_code":"PPL",
    "gn:name":"Qiancuncun",
    "gn:population":0,
    "gn:timezone":"Asia/Shanghai",
    "iso:country":"CN",
    "name:zho_x_preferred":[
        "\u524d\u6751\u6751"
    ],
    "wof:name":"Qiancuncun",
    "wof:placetype":"locality"
},
  "geometry": {"coordinates":[108.19945,35.25597],"type":"Point"}
}