{
  "type": "Feature",
  "properties": {
    "gn:admin1_code":"2.0",
    "gn:asciiname":"Xiaoquanxi",
    "gn:country_code":"CN",
    "gn:dem":128,
    "gn:feature_class":"P",
    "gn:feature_code":"PPL",
    "gn:name":"Xiaoquanxi",
    "gn:population":0,
    "gn:timezone":"Asia/Shanghai",
    "iso:country":"CN",
    "name:zho_x_preferred":[
        "\u5c0f\u6cc9\u6eaa"
    ],
    "wof:name":"Xiaoquanxi",
    "wof:placetype":"locality"
},
  "geometry": {"coordinates":[120.75725,29.35246],"type":"Point"}
}