{
  "type": "Feature",
  "properties": {
    "gn:admin1_code":"4.0",
    "gn:asciiname":"Ganbucun",
    "gn:country_code":"CN",
    "gn:dem":11,
    "gn:feature_class":"P",
    "gn:feature_code":"PPL",
    "gn:name":"Ganbucun",
    "gn:population":0,
    "gn:timezone":"Asia/Shanghai",
    "iso:country":"CN",
    "name:zho_x_preferred":[
        "\u8d76\u57e0\u6751"
    ],
    "wof:name":"Ganbucun",
    "wof:placetype":"locality"
},
  "geometry": {"coordinates":[118.67828,34.24689],"type":"Point"}
}