{
  "type": "Feature",
  "properties": {
    "gn:admin1_code":"15.0",
    "gn:asciiname":"Yuantai",
    "gn:country_code":"CN",
    "gn:dem":1377,
    "gn:feature_class":"P",
    "gn:feature_code":"PPL",
    "gn:name":"Yuantai",
    "gn:population":0,
    "gn:timezone":"Asia/Shanghai",
    "iso:country":"CN",
    "name:zho_x_preferred":[
        "\u5143\u53f0"
    ],
    "wof:name":"Yuantai",
    "wof:placetype":"locality"
},
  "geometry": {"coordinates":[103.10599999999999,38.5648],"type":"Point"}
}