{
  "type": "Feature",
  "properties": {
    "gn:admin1_code":"1.0",
    "gn:asciiname":"Taoxinzhuangcun",
    "gn:country_code":"CN",
    "gn:dem":38,
    "gn:feature_class":"P",
    "gn:feature_code":"PPL",
    "gn:name":"Taoxinzhuangcun",
    "gn:population":0,
    "gn:timezone":"Asia/Shanghai",
    "iso:country":"CN",
    "name:zho_x_preferred":[
        "\u9676\u65b0\u5e84\u6751"
    ],
    "wof:name":"Taoxinzhuangcun",
    "wof:placetype":"locality"
},
  "geometry": {"coordinates":[115.24821,32.77991],"type":"Point"}
}