{
  "type": "Feature",
  "properties": {
    "gn:admin1_code":"3.0",
    "gn:asciiname":"Huaqiao",
    "gn:country_code":"CN",
    "gn:dem":67,
    "gn:feature_class":"P",
    "gn:feature_code":"PPL",
    "gn:name":"Huaqiao",
    "gn:population":0,
    "gn:timezone":"Asia/Shanghai",
    "iso:country":"CN",
    "name:ceb_x_preferred":[
        "Huaqiao"
    ],
    "name:deu_x_preferred":[
        "Huaqiao"
    ],
    "name:swe_x_preferred":[
        "Huaqiao"
    ],
    "name:zho_x_preferred":[
        "\u753b\u6865"
    ],
    "wof:name":"Huaqiao",
    "wof:placetype":"locality"
},
  "geometry": {"coordinates":[117.08015,28.5541],"type":"Point"}
}