{
  "type": "Feature",
  "properties": {
    "gn:admin1_code":"02",
    "gn:asciiname":"Meiyu",
    "gn:country_code":"CN",
    "gn:dem":6,
    "gn:feature_class":"P",
    "gn:feature_code":"PPL",
    "gn:name":"Meiyu",
    "gn:population":0,
    "gn:timezone":"Asia/Shanghai",
    "iso:country":"CN",
    "name:und_x_variant":[
        "Yutou",
        "Meiyu"
    ],
    "name:zho_x_preferred":[
        "Ma-y\u00fc-t\u2019u"
    ],
    "wof:name":"Meiyu",
    "wof:placetype":"locality"
},
  "geometry": {"coordinates":[120.44374999999999,27.81273],"type":"Point"}
}