{
  "type": "Feature",
  "properties": {
    "gn:admin1_code":"30.0",
    "gn:asciiname":"Shuiyangcun",
    "gn:country_code":"CN",
    "gn:dem":5,
    "gn:feature_class":"P",
    "gn:feature_code":"PPL",
    "gn:name":"Shuiyangcun",
    "gn:population":0,
    "gn:timezone":"Asia/Shanghai",
    "iso:country":"CN",
    "name:zho_x_preferred":[
        "\u6c34\u6d0b\u6751"
    ],
    "wof:name":"Shuiyangcun",
    "wof:placetype":"locality"
},
  "geometry": {"coordinates":[112.58216000000002,21.6441],"type":"Point"}
}