{
  "type": "Feature",
  "properties": {
    "gn:admin1_code":"4.0",
    "gn:asciiname":"Houhuangyaozhuang",
    "gn:country_code":"CN",
    "gn:dem":0,
    "gn:feature_class":"P",
    "gn:feature_code":"PPL",
    "gn:name":"Houhuangyaozhuang",
    "gn:population":0,
    "gn:timezone":"Asia/Shanghai",
    "iso:country":"CN",
    "name:zho_x_preferred":[
        "Houhuangyaozhuang"
    ],
    "name:zho_x_variant":[
        "\u540e\u9ec4\u7a91\u5e84"
    ],
    "wof:name":"Houhuangyaozhuang",
    "wof:placetype":"locality"
},
  "geometry": {"coordinates":[119.73251999999999,34.3764],"type":"Point"}
}