{
  "type": "Feature",
  "properties": {
    "gn:admin1_code":"6.0",
    "gn:asciiname":"Zhenbanong",
    "gn:country_code":"CN",
    "gn:dem":4402,
    "gn:feature_class":"P",
    "gn:feature_code":"PPL",
    "gn:name":"Zhenbanong",
    "gn:population":0,
    "gn:timezone":"Asia/Urumqi",
    "iso:country":"CN",
    "name:zho_x_preferred":[
        "\u9547\u5df4\u5f04"
    ],
    "wof:name":"Zhenbanong",
    "wof:placetype":"locality"
},
  "geometry": {"coordinates":[96.37257,31.89786],"type":"Point"}
}