{
  "type": "Feature",
  "properties": {
    "gn:admin1_code":"15.0",
    "gn:asciiname":"Yuanzi",
    "gn:country_code":"CN",
    "gn:dem":1171,
    "gn:feature_class":"P",
    "gn:feature_code":"PPL",
    "gn:name":"Yuanzi",
    "gn:population":0,
    "gn:timezone":"Asia/Shanghai",
    "iso:country":"CN",
    "name:zho_x_preferred":[
        "\u56ed\u5b50"
    ],
    "wof:name":"Yuanzi",
    "wof:placetype":"locality"
},
  "geometry": {"coordinates":[106.232,34.5095],"type":"Point"}
}