{
  "type": "Feature",
  "properties": {
    "gn:admin1_code":"3.0",
    "gn:asciiname":"Hedongcun",
    "gn:country_code":"CN",
    "gn:dem":21,
    "gn:feature_class":"P",
    "gn:feature_code":"PPL",
    "gn:name":"Hedongcun",
    "gn:population":0,
    "gn:timezone":"Asia/Shanghai",
    "iso:country":"CN",
    "name:und_x_variant":[
        "\u6cb3\u4e1c\u6751"
    ],
    "wof:name":"Hedongcun",
    "wof:placetype":"locality"
},
  "geometry": {"coordinates":[116.87494,28.83841],"type":"Point"}
}