{
  "type": "Feature",
  "properties": {
    "gn:admin1_code":"3.0",
    "gn:asciiname":"Lianggang",
    "gn:country_code":"CN",
    "gn:dem":164,
    "gn:feature_class":"P",
    "gn:feature_code":"PPL",
    "gn:name":"Lianggang",
    "gn:population":0,
    "gn:timezone":"Asia/Shanghai",
    "iso:country":"CN",
    "name:und_x_variant":[
        "\u826f\u5c97"
    ],
    "wof:name":"Lianggang",
    "wof:placetype":"locality"
},
  "geometry": {"coordinates":[114.59357,29.00619],"type":"Point"}
}