{
  "type": "Feature",
  "properties": {
    "gn:admin1_code":"12.0",
    "gn:asciiname":"Jinjianao",
    "gn:country_code":"CN",
    "gn:dem":885,
    "gn:feature_class":"P",
    "gn:feature_code":"PPL",
    "gn:name":"Jinjianao",
    "gn:population":0,
    "gn:timezone":"Asia/Shanghai",
    "iso:country":"CN",
    "name:zho_x_preferred":[
        "Jinjianao"
    ],
    "name:zho_x_variant":[
        "\u91d1\u5bb6\u57b4"
    ],
    "wof:name":"Jinjianao",
    "wof:placetype":"locality"
},
  "geometry": {"coordinates":[111.2948,30.13078],"type":"Point"}
}