{
  "type": "Feature",
  "properties": {
    "gn:admin1_code":"26",
    "gn:asciiname":"Nantianguo",
    "gn:country_code":"CN",
    "gn:dem":568,
    "gn:feature_class":"P",
    "gn:feature_code":"PPL",
    "gn:name":"Nantianguo",
    "gn:population":0,
    "gn:timezone":"Asia/Shanghai",
    "iso:country":"CN",
    "name:zho_x_preferred":[
        "\u5357\u7530\u679c"
    ],
    "wof:name":"Nantianguo",
    "wof:placetype":"locality"
},
  "geometry": {"coordinates":[108.29944,34.37639],"type":"Point"}
}