{
  "type": "Feature",
  "properties": {
    "gn:admin1_code":"25.0",
    "gn:asciiname":"Dongkuangjiatun",
    "gn:country_code":"CN",
    "gn:dem":37,
    "gn:feature_class":"P",
    "gn:feature_code":"PPL",
    "gn:name":"Dongkuangjiatun",
    "gn:population":0,
    "gn:timezone":"Asia/Shanghai",
    "iso:country":"CN",
    "name:zho_x_preferred":[
        "\u4e1c\u593c\u5bb6\u5c6f"
    ],
    "wof:name":"Dongkuangjiatun",
    "wof:placetype":"locality"
},
  "geometry": {"coordinates":[119.55768,36.4738],"type":"Point"}
}