{
  "type": "Feature",
  "properties": {
    "gn:admin1_code":"11",
    "gn:asciiname":"Zaohechong",
    "gn:country_code":"CN",
    "gn:dem":102,
    "gn:feature_class":"P",
    "gn:feature_code":"PPL",
    "gn:name":"Zaohechong",
    "gn:population":0,
    "gn:timezone":"Asia/Shanghai",
    "iso:country":"CN",
    "name:zho_x_preferred":[
        "\u65e9\u79be\u51b2"
    ],
    "wof:name":"Zaohechong",
    "wof:placetype":"locality"
},
  "geometry": {"coordinates":[112.40124,26.63321],"type":"Point"}
}