{
  "type": "Feature",
  "properties": {
    "gn:admin1_code":"19.0",
    "gn:asciiname":"Zhongxingtun",
    "gn:country_code":"CN",
    "gn:dem":135,
    "gn:feature_class":"P",
    "gn:feature_code":"PPL",
    "gn:name":"Zhongxingtun",
    "gn:population":0,
    "gn:timezone":"Asia/Shanghai",
    "iso:country":"CN",
    "name:zho_x_preferred":[
        "\u91cd\u5174\u5c6f"
    ],
    "wof:name":"Zhongxingtun",
    "wof:placetype":"locality"
},
  "geometry": {"coordinates":[122.67,39.7733],"type":"Point"}
}