{
  "type": "Feature",
  "properties": {
    "gn:admin1_code":"26.0",
    "gn:asciiname":"Gaofang",
    "gn:country_code":"CN",
    "gn:dem":1226,
    "gn:feature_class":"P",
    "gn:feature_code":"PPL",
    "gn:name":"Gaofang",
    "gn:population":0,
    "gn:timezone":"Asia/Shanghai",
    "iso:country":"CN",
    "name:zho_x_preferred":[
        "\u9ad8\u574a"
    ],
    "wof:name":"Gaofang",
    "wof:placetype":"locality"
},
  "geometry": {"coordinates":[109.60503,36.35355],"type":"Point"}
}