{
  "type": "Feature",
  "properties": {
    "gn:admin1_code":"3.0",
    "gn:asciiname":"Yangdi",
    "gn:country_code":"CN",
    "gn:dem":416,
    "gn:feature_class":"P",
    "gn:feature_code":"PPLA4",
    "gn:name":"Yangdi",
    "gn:population":0,
    "gn:timezone":"Asia/Shanghai",
    "iso:country":"CN",
    "name:und_x_variant":[
        "\u6d0b\u5730",
        "Yangdi Xiang",
        "\u6d0b\u5730\u4e61"
    ],
    "wof:name":"Yangdi",
    "wof:placetype":"locality"
},
  "geometry": {"coordinates":[116.32814999999999,26.04864],"type":"Point"}
}