{
  "type": "Feature",
  "properties": {
    "gn:admin1_code":"9.0",
    "gn:asciiname":"Gaozhai",
    "gn:country_code":"CN",
    "gn:dem":43,
    "gn:feature_class":"P",
    "gn:feature_code":"PPL",
    "gn:name":"Gaozhai",
    "gn:population":0,
    "gn:timezone":"Asia/Shanghai",
    "iso:country":"CN",
    "name:zho_x_preferred":[
        "\u9ad8\u5be8"
    ],
    "wof:name":"Gaozhai",
    "wof:placetype":"locality"
},
  "geometry": {"coordinates":[114.9012,32.82761],"type":"Point"}
}