{
  "type": "Feature",
  "properties": {
    "gn:admin1_code":"9.0",
    "gn:asciiname":"Silangyao",
    "gn:country_code":"CN",
    "gn:dem":456,
    "gn:feature_class":"P",
    "gn:feature_code":"PPL",
    "gn:name":"Silangyao",
    "gn:population":0,
    "gn:timezone":"Asia/Shanghai",
    "iso:country":"CN",
    "name:zho_x_preferred":[
        "\u5bfa\u90ce\u8170"
    ],
    "wof:name":"Silangyao",
    "wof:placetype":"locality"
},
  "geometry": {"coordinates":[112.34564,34.98971],"type":"Point"}
}