{
  "type": "Feature",
  "properties": {
    "gn:admin1_code":"4.0",
    "gn:asciiname":"Hanzhuang",
    "gn:country_code":"CN",
    "gn:dem":5,
    "gn:feature_class":"P",
    "gn:feature_code":"PPL",
    "gn:name":"Hanzhuang",
    "gn:population":0,
    "gn:timezone":"Asia/Shanghai",
    "iso:country":"CN",
    "name:zho_x_preferred":[
        "Hanzhuang"
    ],
    "name:zho_x_variant":[
        "\u97e9\u5e84"
    ],
    "wof:name":"Hanzhuang",
    "wof:placetype":"locality"
},
  "geometry": {"coordinates":[119.59639,33.06183],"type":"Point"}
}