{
  "type": "Feature",
  "properties": {
    "gn:admin1_code":"32.0",
    "gn:asciiname":"Kecuo",
    "gn:country_code":"CN",
    "gn:dem":3771,
    "gn:feature_class":"P",
    "gn:feature_code":"PPL",
    "gn:name":"Kecuo",
    "gn:population":0,
    "gn:timezone":"Asia/Shanghai",
    "iso:country":"CN",
    "name:zho_x_preferred":[
        "\u67ef\u9519"
    ],
    "wof:name":"Kecuo",
    "wof:placetype":"locality"
},
  "geometry": {"coordinates":[98.78939,31.58299],"type":"Point"}
}