{
  "type": "Feature",
  "properties": {
    "gn:admin1_code":"10",
    "gn:asciiname":"Caozixiang",
    "gn:country_code":"CN",
    "gn:dem":490,
    "gn:feature_class":"P",
    "gn:feature_code":"PPL",
    "gn:name":"Caozixiang",
    "gn:population":0,
    "gn:timezone":"Asia/Shanghai",
    "iso:country":"CN",
    "name:zho_x_preferred":[
        "\u66f9\u5b50\u5df7"
    ],
    "wof:name":"Caozixiang",
    "wof:placetype":"locality"
},
  "geometry": {"coordinates":[113.98399999999999,36.6924],"type":"Point"}
}