{
  "type": "Feature",
  "properties": {
    "gn:admin1_code":"18",
    "gn:asciiname":"Shabatian",
    "gn:country_code":"CN",
    "gn:dem":1085,
    "gn:feature_class":"P",
    "gn:feature_code":"PPL",
    "gn:name":"Shabatian",
    "gn:population":0,
    "gn:timezone":"Asia/Shanghai",
    "iso:country":"CN",
    "name:zho_x_preferred":[
        "\u6c99\u575d\u7530"
    ],
    "wof:name":"Shabatian",
    "wof:placetype":"locality"
},
  "geometry": {"coordinates":[105.581,27.5574],"type":"Point"}
}