{
  "type": "Feature",
  "properties": {
    "gn:admin1_code":"3.0",
    "gn:asciiname":"Yumaoshan",
    "gn:country_code":"CN",
    "gn:dem":578,
    "gn:feature_class":"P",
    "gn:feature_code":"PPL",
    "gn:name":"Yumaoshan",
    "gn:population":0,
    "gn:timezone":"Asia/Shanghai",
    "iso:country":"CN",
    "name:zho_x_preferred":[
        "\u4f59\u8c8c\u5c71"
    ],
    "wof:name":"Yumaoshan",
    "wof:placetype":"locality"
},
  "geometry": {"coordinates":[117.90204,28.77002],"type":"Point"}
}