{
  "type": "Feature",
  "properties": {
    "gn:admin1_code":"9",
    "gn:asciiname":"Xiaheti",
    "gn:country_code":"CN",
    "gn:dem":616,
    "gn:feature_class":"P",
    "gn:feature_code":"PPL",
    "gn:name":"Xiaheti",
    "gn:population":0,
    "gn:timezone":"Asia/Shanghai",
    "iso:country":"CN",
    "wof:name":"Xiaheti",
    "wof:placetype":"locality"
},
  "geometry": {"coordinates":[111.58306,34.53167],"type":"Point"}
}