{
  "type": "Feature",
  "properties": {
    "gn:admin1_code":"15.0",
    "gn:asciiname":"Hongya",
    "gn:country_code":"CN",
    "gn:dem":2691,
    "gn:feature_class":"P",
    "gn:feature_code":"PPL",
    "gn:name":"Hongya",
    "gn:population":0,
    "gn:timezone":"Asia/Shanghai",
    "iso:country":"CN",
    "name:und_x_variant":[
        "\u7ea2\u5d16"
    ],
    "wof:name":"Hongya",
    "wof:placetype":"locality"
},
  "geometry": {"coordinates":[103.62289,34.66939],"type":"Point"}
}