{
  "type": "Feature",
  "properties": {
    "gn:admin1_code":"2.0",
    "gn:asciiname":"Dixingnong",
    "gn:country_code":"CN",
    "gn:dem":476,
    "gn:feature_class":"P",
    "gn:feature_code":"PPL",
    "gn:name":"Dixingnong",
    "gn:population":0,
    "gn:timezone":"Asia/Shanghai",
    "iso:country":"CN",
    "name:zho_x_preferred":[
        "\u5e95\u90a2\u5f04"
    ],
    "wof:name":"Dixingnong",
    "wof:placetype":"locality"
},
  "geometry": {"coordinates":[119.99420000000001,28.65603],"type":"Point"}
}