{
  "type": "Feature",
  "properties": {
    "gn:admin1_code":"4.0",
    "gn:asciiname":"Dunyigang",
    "gn:country_code":"CN",
    "gn:dem":4,
    "gn:feature_class":"P",
    "gn:feature_code":"PPL",
    "gn:name":"Dunyigang",
    "gn:population":0,
    "gn:timezone":"Asia/Shanghai",
    "iso:country":"CN",
    "name:und_x_variant":[
        "\u58a9\u4e49\u6e2f"
    ],
    "name:zho_x_preferred":[
        "\u58a9\u4e49\u6e2f"
    ],
    "wof:name":"Dunyigang",
    "wof:placetype":"locality"
},
  "geometry": {"coordinates":[120.42907,32.08718],"type":"Point"}
}