{
  "type": "Feature",
  "properties": {
    "gn:admin1_code":"32.0",
    "gn:asciiname":"Tiziyan",
    "gn:country_code":"CN",
    "gn:dem":383,
    "gn:feature_class":"P",
    "gn:feature_code":"PPL",
    "gn:name":"Tiziyan",
    "gn:population":0,
    "gn:timezone":"Asia/Shanghai",
    "iso:country":"CN",
    "name:zho_x_preferred":[
        "\u68af\u5b50\u5ca9"
    ],
    "wof:name":"Tiziyan",
    "wof:placetype":"locality"
},
  "geometry": {"coordinates":[105.35599999999999,29.7877],"type":"Point"}
}