{
  "type": "Feature",
  "properties": {
    "gn:admin1_code":"3.0",
    "gn:asciiname":"Dieshan",
    "gn:country_code":"CN",
    "gn:dem":62,
    "gn:feature_class":"P",
    "gn:feature_code":"PPLA4",
    "gn:name":"Dieshan",
    "gn:population":0,
    "gn:timezone":"Asia/Shanghai",
    "iso:country":"CN",
    "name:und_x_variant":[
        "Dieshan Zhen",
        "\u53e0\u5c71\u9547",
        "Dieshan"
    ],
    "name:zho_x_preferred":[
        "\u53e0\u5c71"
    ],
    "wof:name":"Dieshan",
    "wof:placetype":"locality"
},
  "geometry": {"coordinates":[117.50866000000001,28.21421],"type":"Point"}
}