{
  "type": "Feature",
  "properties": {
    "gn:admin1_code":"26.0",
    "gn:asciiname":"Qijihalang",
    "gn:country_code":"CN",
    "gn:dem":1260,
    "gn:feature_class":"P",
    "gn:feature_code":"PPL",
    "gn:name":"Qijihalang",
    "gn:population":0,
    "gn:timezone":"Asia/Shanghai",
    "iso:country":"CN",
    "name:zho_x_preferred":[
        "\u8d77\u9e21\u54c8\u6d6a"
    ],
    "wof:name":"Qijihalang",
    "wof:placetype":"locality"
},
  "geometry": {"coordinates":[110.09404000000001,38.96577],"type":"Point"}
}