{
  "type": "Feature",
  "properties": {
    "gn:admin1_code":"30",
    "gn:asciiname":"Tangcao",
    "gn:country_code":"CN",
    "gn:dem":5,
    "gn:feature_class":"P",
    "gn:feature_code":"PPL",
    "gn:name":"Tangcao",
    "gn:population":0,
    "gn:timezone":"Asia/Urumqi",
    "iso:country":"CN",
    "name:zho_x_preferred":[
        "\u5858\u8349"
    ],
    "wof:name":"Tangcao",
    "wof:placetype":"locality"
},
  "geometry": {"coordinates":[110.53733,21.43241],"type":"Point"}
}