{
  "type": "Feature",
  "properties": {
    "gn:admin1_code":"26.0",
    "gn:asciiname":"Yangpo Zhuang",
    "gn:country_code":"CN",
    "gn:dem":1606,
    "gn:feature_class":"P",
    "gn:feature_code":"PPL",
    "gn:name":"Yangpo Zhuang",
    "gn:population":0,
    "gn:timezone":"Asia/Shanghai",
    "iso:country":"CN",
    "name:und_x_variant":[
        "\u9633\u5761\u5e84"
    ],
    "wof:name":"Yangpo Zhuang",
    "wof:placetype":"locality"
},
  "geometry": {"coordinates":[107.27743,34.04642],"type":"Point"}
}