{
  "type": "Feature",
  "properties": {
    "gn:admin1_code":"14.0",
    "gn:asciiname":"Dingze",
    "gn:country_code":"CN",
    "gn:dem":4467,
    "gn:feature_class":"P",
    "gn:feature_code":"PPL",
    "gn:name":"Dingze",
    "gn:population":0,
    "gn:timezone":"Asia/Shanghai",
    "iso:country":"CN",
    "name:bod_x_preferred":[
        "D\u00eangz\u00ea"
    ],
    "name:msa_x_preferred":[
        "D\u00eangz\u00ea"
    ],
    "name:und_x_variant":[
        "Dingzecun"
    ],
    "name:zho_x_preferred":[
        "Dingze"
    ],
    "name:zho_x_variant":[
        "\u4e01\u5219",
        "\u4e01\u5219\u6751"
    ],
    "wof:name":"Dingze",
    "wof:placetype":"locality"
},
  "geometry": {"coordinates":[81.42426,32.81475],"type":"Point"}
}