{
  "type": "Feature",
  "properties": {
    "gn:admin1_code":"8.0",
    "gn:asciiname":"Yuxin",
    "gn:country_code":"CN",
    "gn:dem":106,
    "gn:feature_class":"P",
    "gn:feature_code":"PPL",
    "gn:name":"Yuxin",
    "gn:population":0,
    "gn:timezone":"Asia/Shanghai",
    "iso:country":"CN",
    "name:zho_x_preferred":[
        "\u80b2\u65b0"
    ],
    "wof:name":"Yuxin",
    "wof:placetype":"locality"
},
  "geometry": {"coordinates":[129.86598000000001,49.01241],"type":"Point"}
}