{
  "type": "Feature",
  "properties": {
    "gn:admin1_code":"30.0",
    "gn:asciiname":"Sanyingcun",
    "gn:country_code":"CN",
    "gn:dem":13,
    "gn:feature_class":"P",
    "gn:feature_code":"PPL",
    "gn:name":"Sanyingcun",
    "gn:population":0,
    "gn:timezone":"Asia/Shanghai",
    "iso:country":"CN",
    "name:und_x_variant":[
        "Sanying"
    ],
    "name:zho_x_preferred":[
        "\u4e09\u82f1\u6751"
    ],
    "name:zho_x_variant":[
        "\u4e09\u82f1"
    ],
    "wof:name":"Sanyingcun",
    "wof:placetype":"locality"
},
  "geometry": {"coordinates":[116.64481000000001,23.56733],"type":"Point"}
}