{
  "type": "Feature",
  "properties": {
    "gn:admin1_code":"2.0",
    "gn:asciiname":"Shangye",
    "gn:country_code":"CN",
    "gn:dem":103,
    "gn:feature_class":"P",
    "gn:feature_code":"PPL",
    "gn:name":"Shangye",
    "gn:population":0,
    "gn:timezone":"Asia/Shanghai",
    "iso:country":"CN",
    "name:und_x_variant":[
        "\u4e0a\u53f6",
        "Shangye"
    ],
    "wof:name":"Shangye",
    "wof:placetype":"locality"
},
  "geometry": {"coordinates":[119.82856,29.98626],"type":"Point"}
}