{
  "type": "Feature",
  "properties": {
    "gn:admin1_code":"2.0",
    "gn:asciiname":"Huangguan Ni'ao",
    "gn:country_code":"CN",
    "gn:dem":3,
    "gn:feature_class":"P",
    "gn:feature_code":"PPL",
    "gn:name":"Huangguan Ni\u2019ao",
    "gn:population":0,
    "gn:timezone":"Asia/Shanghai",
    "iso:country":"CN",
    "name:und_x_variant":[
        "Huangguan Ni\u2019ao"
    ],
    "name:zho_x_preferred":[
        "\u9ec4\u5b98\u6ce5\u5c99"
    ],
    "wof:name":"Huangguan Ni'ao",
    "wof:placetype":"locality"
},
  "geometry": {"coordinates":[122.21362000000001,30.26999],"type":"Point"}
}