{
  "type": "Feature",
  "properties": {
    "gn:admin1_code":"29.0",
    "gn:asciiname":"Duoyishu",
    "gn:country_code":"CN",
    "gn:dem":1864,
    "gn:feature_class":"P",
    "gn:feature_code":"PPL",
    "gn:name":"Duoyishu",
    "gn:population":0,
    "gn:timezone":"Asia/Shanghai",
    "iso:country":"CN",
    "name:zho_x_preferred":[
        "\u591a\u4f9d\u6811"
    ],
    "wof:name":"Duoyishu",
    "wof:placetype":"locality"
},
  "geometry": {"coordinates":[100.70699999999999,25.0679],"type":"Point"}
}