{
  "type": "Feature",
  "properties": {
    "gn:admin1_code":"24.0",
    "gn:asciiname":"Guojiacun",
    "gn:country_code":"CN",
    "gn:dem":990,
    "gn:feature_class":"P",
    "gn:feature_code":"PPL",
    "gn:name":"Guojiacun",
    "gn:population":0,
    "gn:timezone":"Asia/Shanghai",
    "iso:country":"CN",
    "name:zho_x_preferred":[
        "\u90ed\u5bb6\u6751"
    ],
    "wof:name":"Guojiacun",
    "wof:placetype":"locality"
},
  "geometry": {"coordinates":[111.46717,36.6544],"type":"Point"}
}