{
  "type": "Feature",
  "properties": {
    "gn:admin1_code":"1.0",
    "gn:asciiname":"Jinwancun",
    "gn:country_code":"CN",
    "gn:dem":39,
    "gn:feature_class":"P",
    "gn:feature_code":"PPL",
    "gn:name":"Jinwancun",
    "gn:population":0,
    "gn:timezone":"Asia/Shanghai",
    "iso:country":"CN",
    "name:zho_x_preferred":[
        "\u91d1\u6e7e\u6751"
    ],
    "wof:name":"Jinwancun",
    "wof:placetype":"locality"
},
  "geometry": {"coordinates":[116.21017000000001,31.92968],"type":"Point"}
}