{
  "type": "Feature",
  "properties": {
    "gn:admin1_code":"30.0",
    "gn:asciiname":"Dajiangping",
    "gn:country_code":"CN",
    "gn:dem":141,
    "gn:feature_class":"P",
    "gn:feature_code":"PPL",
    "gn:name":"Dajiangping",
    "gn:population":0,
    "gn:timezone":"Asia/Shanghai",
    "iso:country":"CN",
    "name:zho_x_preferred":[
        "\u5927\u964d\u576a"
    ],
    "wof:name":"Dajiangping",
    "wof:placetype":"locality"
},
  "geometry": {"coordinates":[112.17324000000001,23.19259],"type":"Point"}
}