{
  "type": "Feature",
  "properties": {
    "gn:admin1_code":"15.0",
    "gn:asciiname":"Nigelong",
    "gn:country_code":"CN",
    "gn:dem":2745,
    "gn:feature_class":"P",
    "gn:feature_code":"PPL",
    "gn:name":"Nigelong",
    "gn:population":0,
    "gn:timezone":"Asia/Shanghai",
    "iso:country":"CN",
    "name:und_x_variant":[
        "\u5c3c\u683c\u9686"
    ],
    "wof:name":"Nigelong",
    "wof:placetype":"locality"
},
  "geometry": {"coordinates":[103.48448999999999,34.62655],"type":"Point"}
}