{
  "type": "Feature",
  "properties": {
    "gn:admin1_code":"8.0",
    "gn:asciiname":"Xiaojiangjiagou",
    "gn:country_code":"CN",
    "gn:dem":229,
    "gn:feature_class":"P",
    "gn:feature_code":"PPL",
    "gn:name":"Xiaojiangjiagou",
    "gn:population":0,
    "gn:timezone":"Asia/Shanghai",
    "iso:country":"CN",
    "name:zho_x_preferred":[
        "\u5c0f\u59dc\u5bb6\u6c9f"
    ],
    "wof:name":"Xiaojiangjiagou",
    "wof:placetype":"locality"
},
  "geometry": {"coordinates":[127.98599,44.96516],"type":"Point"}
}