{
  "type": "Feature",
  "properties": {
    "gn:admin1_code":"26.0",
    "gn:asciiname":"Hantacun",
    "gn:country_code":"CN",
    "gn:dem":1045,
    "gn:feature_class":"P",
    "gn:feature_code":"PPL",
    "gn:name":"Hantacun",
    "gn:population":0,
    "gn:timezone":"Asia/Shanghai",
    "iso:country":"CN",
    "name:zho_x_preferred":[
        "\u97e9\u5854\u6751"
    ],
    "wof:name":"Hantacun",
    "wof:placetype":"locality"
},
  "geometry": {"coordinates":[109.94877,37.91711],"type":"Point"}
}