{
  "type": "Feature",
  "properties": {
    "gn:admin1_code":"8.0",
    "gn:asciiname":"Qiyicun",
    "gn:country_code":"CN",
    "gn:dem":141,
    "gn:feature_class":"P",
    "gn:feature_code":"PPL",
    "gn:name":"Qiyicun",
    "gn:population":0,
    "gn:timezone":"Asia/Shanghai",
    "iso:country":"CN",
    "name:zho_x_preferred":[
        "\u4e03\u4e00\u6751"
    ],
    "wof:name":"Qiyicun",
    "wof:placetype":"locality"
},
  "geometry": {"coordinates":[127.33093,46.0178],"type":"Point"}
}