{
  "type": "Feature",
  "properties": {
    "gn:admin1_code":"32.0",
    "gn:asciiname":"Dafentian",
    "gn:country_code":"CN",
    "gn:dem":1366,
    "gn:feature_class":"P",
    "gn:feature_code":"PPL",
    "gn:name":"Dafentian",
    "gn:population":0,
    "gn:timezone":"Asia/Shanghai",
    "iso:country":"CN",
    "name:zho_x_preferred":[
        "\u5927\u4efd\u7530"
    ],
    "wof:name":"Dafentian",
    "wof:placetype":"locality"
},
  "geometry": {"coordinates":[101.77200000000001,26.3449],"type":"Point"}
}