{
  "type": "Feature",
  "properties": {
    "gn:admin1_code":"18.0",
    "gn:asciiname":"Pingkou",
    "gn:country_code":"CN",
    "gn:dem":821,
    "gn:feature_class":"P",
    "gn:feature_code":"PPL",
    "gn:name":"Pingkou",
    "gn:population":0,
    "gn:timezone":"Asia/Shanghai",
    "iso:country":"CN",
    "name:zho_x_preferred":[
        "\u5e73\u53e3"
    ],
    "wof:name":"Pingkou",
    "wof:placetype":"locality"
},
  "geometry": {"coordinates":[107.548,26.1647],"type":"Point"}
}