{
  "type": "Feature",
  "properties": {
    "gn:admin1_code":"7.0",
    "gn:asciiname":"Huangmaosi",
    "gn:country_code":"CN",
    "gn:dem":334,
    "gn:feature_class":"P",
    "gn:feature_code":"PPL",
    "gn:name":"Huangmaosi",
    "gn:population":0,
    "gn:timezone":"Asia/Shanghai",
    "iso:country":"CN",
    "name:zho_x_preferred":[
        "\u9ec4\u8305\u5bfa"
    ],
    "wof:name":"Huangmaosi",
    "wof:placetype":"locality"
},
  "geometry": {"coordinates":[117.36442,27.71653],"type":"Point"}
}