{
  "type": "Feature",
  "properties": {
    "gn:admin1_code":"10",
    "gn:asciiname":"Xitucheng",
    "gn:country_code":"CN",
    "gn:dem":1498,
    "gn:feature_class":"P",
    "gn:feature_code":"PPL",
    "gn:name":"Xitucheng",
    "gn:population":0,
    "gn:timezone":"Asia/Shanghai",
    "iso:country":"CN",
    "name:zho_x_preferred":[
        "\u897f\u571f\u57ce"
    ],
    "wof:name":"Xitucheng",
    "wof:placetype":"locality"
},
  "geometry": {"coordinates":[115.37611,41.09638],"type":"Point"}
}