{
  "type": "Feature",
  "properties": {
    "gn:admin1_code":"5.0",
    "gn:asciiname":"Liushui Gongshe Wopeng",
    "gn:country_code":"CN",
    "gn:dem":139,
    "gn:feature_class":"P",
    "gn:feature_code":"PPLF",
    "gn:name":"Liushui Gongshe Wopeng",
    "gn:population":0,
    "gn:timezone":"Asia/Shanghai",
    "iso:country":"CN",
    "name:zho_x_preferred":[
        "\u6d41\u6c34\u516c\u793e\u7a9d\u68da"
    ],
    "wof:name":"Liushui Gongshe Wopeng",
    "wof:placetype":"locality"
},
  "geometry": {"coordinates":[123.56966,44.60813],"type":"Point"}
}