{
  "type": "Feature",
  "properties": {
    "gn:admin1_code":"15.0",
    "gn:asciiname":"Dazhuangke",
    "gn:country_code":"CN",
    "gn:dem":2280,
    "gn:feature_class":"P",
    "gn:feature_code":"PPL",
    "gn:name":"Dazhuangke",
    "gn:population":0,
    "gn:timezone":"Asia/Shanghai",
    "iso:country":"CN",
    "name:und_x_variant":[
        "\u5927\u5e84\u7aa0"
    ],
    "name:zho_x_preferred":[
        "\u5927\u5e84\u7aa0"
    ],
    "wof:name":"Dazhuangke",
    "wof:placetype":"locality"
},
  "geometry": {"coordinates":[104.93122,33.61393],"type":"Point"}
}