{
  "type": "Feature",
  "properties": {
    "gn:admin1_code":"2.0",
    "gn:asciiname":"Wukeng",
    "gn:country_code":"CN",
    "gn:dem":407,
    "gn:feature_class":"P",
    "gn:feature_code":"PPL",
    "gn:name":"Wukeng",
    "gn:population":0,
    "gn:timezone":"Asia/Shanghai",
    "iso:country":"CN",
    "name:zho_x_preferred":[
        "\u4e4c\u5751"
    ],
    "wof:name":"Wukeng",
    "wof:placetype":"locality"
},
  "geometry": {"coordinates":[121.22177000000001,29.76643],"type":"Point"}
}