{
  "type": "Feature",
  "properties": {
    "gn:admin1_code":"4.0",
    "gn:asciiname":"Yunnangang",
    "gn:country_code":"CN",
    "gn:dem":4,
    "gn:feature_class":"P",
    "gn:feature_code":"PPL",
    "gn:name":"Yunnangang",
    "gn:population":0,
    "gn:timezone":"Asia/Shanghai",
    "iso:country":"CN",
    "name:und_x_variant":[
        "\u4e91\u5357\u6e2f"
    ],
    "name:zho_x_preferred":[
        "\u4e91\u5357\u6e2f"
    ],
    "wof:name":"Yunnangang",
    "wof:placetype":"locality"
},
  "geometry": {"coordinates":[120.72175,31.44657],"type":"Point"}
}