{
  "type": "Feature",
  "properties": {
    "gn:admin1_code":"18.0",
    "gn:asciiname":"Shaodong",
    "gn:country_code":"CN",
    "gn:dem":506,
    "gn:feature_class":"P",
    "gn:feature_code":"PPL",
    "gn:name":"Shaodong",
    "gn:population":0,
    "gn:timezone":"Asia/Shanghai",
    "iso:country":"CN",
    "name:zho_x_preferred":[
        "\u7ecd\u6d1e"
    ],
    "wof:name":"Shaodong",
    "wof:placetype":"locality"
},
  "geometry": {"coordinates":[108.673,26.3586],"type":"Point"}
}