{
  "type": "Feature",
  "properties": {
    "gn:admin1_code":"26.0",
    "gn:asciiname":"Gouyucun",
    "gn:country_code":"CN",
    "gn:dem":1071,
    "gn:feature_class":"P",
    "gn:feature_code":"PPL",
    "gn:name":"Gouyucun",
    "gn:population":0,
    "gn:timezone":"Asia/Shanghai",
    "iso:country":"CN",
    "name:zho_x_preferred":[
        "\u6c9f\u5cea\u6751"
    ],
    "wof:name":"Gouyucun",
    "wof:placetype":"locality"
},
  "geometry": {"coordinates":[109.88290000000001,34.48079],"type":"Point"}
}