{
  "type": "Feature",
  "properties": {
    "gn:admin1_code":"13",
    "gn:asciiname":"Yiyike",
    "gn:country_code":"CN",
    "gn:dem":-55,
    "gn:feature_class":"P",
    "gn:feature_code":"PPL",
    "gn:name":"Yiyike",
    "gn:population":0,
    "gn:timezone":"Asia/Urumqi",
    "iso:country":"CN",
    "name:und_x_variant":[
        "\u4f0a\u4f9d\u514b"
    ],
    "wof:name":"Yiyike",
    "wof:placetype":"locality"
},
  "geometry": {"coordinates":[88.78233,42.77195],"type":"Point"}
}