{
  "type": "Feature",
  "properties": {
    "gn:admin1_code":"9.0",
    "gn:asciiname":"Quwa",
    "gn:country_code":"CN",
    "gn:dem":102,
    "gn:feature_class":"P",
    "gn:feature_code":"PPL",
    "gn:name":"Quwa",
    "gn:population":0,
    "gn:timezone":"Asia/Shanghai",
    "iso:country":"CN",
    "name:zho_x_preferred":[
        "\u66f2\u6d3c"
    ],
    "wof:name":"Quwa",
    "wof:placetype":"locality"
},
  "geometry": {"coordinates":[112.65369,32.59237],"type":"Point"}
}