{
  "type": "Feature",
  "properties": {
    "gn:admin1_code":"16.0",
    "gn:asciiname":"Bucheng",
    "gn:country_code":"CN",
    "gn:dem":173,
    "gn:feature_class":"P",
    "gn:feature_code":"PPL",
    "gn:name":"Bucheng",
    "gn:population":0,
    "gn:timezone":"Asia/Shanghai",
    "iso:country":"CN",
    "name:zho_x_preferred":[
        "\u535c\u57ce"
    ],
    "wof:name":"Bucheng",
    "wof:placetype":"locality"
},
  "geometry": {"coordinates":[107.54000000000001,22.2443],"type":"Point"}
}