{
  "type": "Feature",
  "properties": {
    "gn:admin1_code":"3.0",
    "gn:asciiname":"Jingyuan",
    "gn:country_code":"CN",
    "gn:dem":121,
    "gn:feature_class":"P",
    "gn:feature_code":"PPL",
    "gn:name":"Jingyuan",
    "gn:population":0,
    "gn:timezone":"Asia/Shanghai",
    "iso:country":"CN",
    "name:deu_x_preferred":[
        "Jingyuan"
    ],
    "name:fra_x_preferred":[
        "Jingyuan"
    ],
    "name:kor_x_preferred":[
        "\uc9d5\uc704\uc548\ud604"
    ],
    "name:nor_x_preferred":[
        "Jingyuan"
    ],
    "name:pol_x_preferred":[
        "Jingyuan"
    ],
    "name:rus_x_preferred":[
        "\u0426\u0437\u0438\u043d\u044a\u044e\u0430\u043d\u044c"
    ],
    "name:swe_x_preferred":[
        "Jingyuan"
    ],
    "name:zho_x_preferred":[
        "\u955c\u6e90"
    ],
    "wof:name":"Jingyuan",
    "wof:placetype":"locality"
},
  "geometry": {"coordinates":[114.218,27.8582],"type":"Point"}
}