{
  "type": "Feature",
  "properties": {
    "gn:admin1_code":"14.0",
    "gn:asciiname":"Laoyi",
    "gn:country_code":"CN",
    "gn:dem":2815,
    "gn:feature_class":"P",
    "gn:feature_code":"PPL",
    "gn:name":"Laoyi",
    "gn:population":0,
    "gn:timezone":"Asia/Urumqi",
    "iso:country":"CN",
    "name:zho_x_preferred":[
        "\u8001\u8863"
    ],
    "wof:name":"Laoyi",
    "wof:placetype":"locality"
},
  "geometry": {"coordinates":[99.02461,29.58546],"type":"Point"}
}