{
  "type": "Feature",
  "properties": {
    "gn:admin1_code":"16",
    "gn:asciiname":"Mayan",
    "gn:country_code":"CN",
    "gn:dem":344,
    "gn:feature_class":"P",
    "gn:feature_code":"PPL",
    "gn:name":"Mayan",
    "gn:population":0,
    "gn:timezone":"Asia/Shanghai",
    "iso:country":"CN",
    "name:ceb_x_preferred":[
        "Mayan"
    ],
    "name:deu_x_preferred":[
        "Mayan"
    ],
    "name:swe_x_preferred":[
        "Mayan"
    ],
    "name:zho_x_preferred":[
        "\u9a6c\u773c"
    ],
    "wof:name":"Mayan",
    "wof:placetype":"locality"
},
  "geometry": {"coordinates":[110.869,25.205],"type":"Point"}
}