{
  "type": "Feature",
  "properties": {
    "gn:admin1_code":"11.0",
    "gn:asciiname":"Yantangzhou",
    "gn:country_code":"CN",
    "gn:dem":630,
    "gn:feature_class":"P",
    "gn:feature_code":"PPL",
    "gn:name":"Yantangzhou",
    "gn:population":0,
    "gn:timezone":"Asia/Shanghai",
    "iso:country":"CN",
    "name:zho_x_preferred":[
        "\u4e25\u5858\u5468"
    ],
    "wof:name":"Yantangzhou",
    "wof:placetype":"locality"
},
  "geometry": {"coordinates":[111.80612000000001,27.44165],"type":"Point"}
}