{
  "type": "Feature",
  "properties": {
    "gn:admin1_code":"30.0",
    "gn:asciiname":"Datangxin",
    "gn:country_code":"CN",
    "gn:dem":576,
    "gn:feature_class":"P",
    "gn:feature_code":"PPL",
    "gn:name":"Datangxin",
    "gn:population":0,
    "gn:timezone":"Asia/Shanghai",
    "iso:country":"CN",
    "name:zho_x_preferred":[
        "\u5927\u5858\u5fc3"
    ],
    "wof:name":"Datangxin",
    "wof:placetype":"locality"
},
  "geometry": {"coordinates":[111.96706,23.63313],"type":"Point"}
}