{
  "type": "Feature",
  "properties": {
    "gn:admin1_code":"14.0",
    "gn:asciiname":"Kalong",
    "gn:country_code":"CN",
    "gn:dem":4113,
    "gn:feature_class":"P",
    "gn:feature_code":"PPL",
    "gn:name":"Kalong",
    "gn:population":0,
    "gn:timezone":"Asia/Urumqi",
    "iso:country":"CN",
    "name:zho_x_preferred":[
        "\u5361\u9f99"
    ],
    "wof:name":"Kalong",
    "wof:placetype":"locality"
},
  "geometry": {"coordinates":[91.19056,28.28198],"type":"Point"}
}