{
  "type": "Feature",
  "properties": {
    "gn:admin1_code":"9",
    "gn:asciiname":"Sishanmiao",
    "gn:country_code":"CN",
    "gn:dem":444,
    "gn:feature_class":"P",
    "gn:feature_code":"PPL",
    "gn:name":"Sishanmiao",
    "gn:population":0,
    "gn:timezone":"Asia/Shanghai",
    "iso:country":"CN",
    "wof:name":"Sishanmiao",
    "wof:placetype":"locality"
},
  "geometry": {"coordinates":[111.30138999999998,33.45028],"type":"Point"}
}