{
  "type": "Feature",
  "properties": {
    "gn:admin1_code":"10.0",
    "gn:asciiname":"Dongcaolu",
    "gn:country_code":"CN",
    "gn:dem":25,
    "gn:feature_class":"P",
    "gn:feature_code":"PPL",
    "gn:name":"Dongcaolu",
    "gn:population":0,
    "gn:timezone":"Asia/Shanghai",
    "iso:country":"CN",
    "name:zho_x_preferred":[
        "\u4e1c\u8349\u82a6"
    ],
    "wof:name":"Dongcaolu",
    "wof:placetype":"locality"
},
  "geometry": {"coordinates":[115.751,38.2659],"type":"Point"}
}