{
  "type": "Feature",
  "properties": {
    "gn:admin1_code":"30",
    "gn:asciiname":"Lunxia",
    "gn:country_code":"CN",
    "gn:dem":372,
    "gn:feature_class":"P",
    "gn:feature_code":"PPL",
    "gn:name":"Lunxia",
    "gn:population":0,
    "gn:timezone":"Asia/Shanghai",
    "iso:country":"CN",
    "name:zho_x_preferred":[
        "\u4ed1\u4e0b"
    ],
    "wof:name":"Lunxia",
    "wof:placetype":"locality"
},
  "geometry": {"coordinates":[115.50041,23.69414],"type":"Point"}
}