{
  "type": "Feature",
  "properties": {
    "gn:admin1_code":"8.0",
    "gn:asciiname":"Wangxiaobandian",
    "gn:country_code":"CN",
    "gn:dem":254,
    "gn:feature_class":"P",
    "gn:feature_code":"PPL",
    "gn:name":"Wangxiaobandian",
    "gn:population":0,
    "gn:timezone":"Asia/Shanghai",
    "iso:country":"CN",
    "name:zho_x_preferred":[
        "\u738b\u5c0f\u73ed\u5e97"
    ],
    "wof:name":"Wangxiaobandian",
    "wof:placetype":"locality"
},
  "geometry": {"coordinates":[126.23721999999999,47.85428],"type":"Point"}
}