{
  "type": "Feature",
  "properties": {
    "gn:admin1_code":"7.0",
    "gn:asciiname":"Dianshangpai",
    "gn:country_code":"CN",
    "gn:dem":333,
    "gn:feature_class":"P",
    "gn:feature_code":"PPL",
    "gn:name":"Dianshangpai",
    "gn:population":0,
    "gn:timezone":"Asia/Shanghai",
    "iso:country":"CN",
    "name:zho_x_preferred":[
        "\u5e97\u4e0a\u6392"
    ],
    "wof:name":"Dianshangpai",
    "wof:placetype":"locality"
},
  "geometry": {"coordinates":[116.83571000000001,26.77968],"type":"Point"}
}