{
  "type": "Feature",
  "properties": {
    "gn:admin1_code":"32.0",
    "gn:asciiname":"Geda",
    "gn:country_code":"CN",
    "gn:dem":2997,
    "gn:feature_class":"P",
    "gn:feature_code":"PPL",
    "gn:name":"Geda",
    "gn:population":0,
    "gn:timezone":"Asia/Shanghai",
    "iso:country":"CN",
    "name:zho_x_preferred":[
        "\u683c\u8fbe"
    ],
    "wof:name":"Geda",
    "wof:placetype":"locality"
},
  "geometry": {"coordinates":[102.179,31.8452],"type":"Point"}
}