{
  "type": "Feature",
  "properties": {
    "gn:admin1_code":"30",
    "gn:asciiname":"Nan'an",
    "gn:country_code":"CN",
    "gn:dem":23,
    "gn:feature_class":"P",
    "gn:feature_code":"PPL",
    "gn:name":"Nan\u2019an",
    "gn:population":0,
    "gn:timezone":"Asia/Shanghai",
    "iso:country":"CN",
    "name:zho_x_preferred":[
        "Nan\u2019an"
    ],
    "wof:name":"Nan'an",
    "wof:placetype":"locality"
},
  "geometry": {"coordinates":[111.51000000000001,21.54361],"type":"Point"}
}