{
  "type": "Feature",
  "properties": {
    "gn:admin1_code":"21.0",
    "gn:asciiname":"Xingjiayao",
    "gn:country_code":"CN",
    "gn:dem":1313,
    "gn:feature_class":"P",
    "gn:feature_code":"PPL",
    "gn:name":"Xingjiayao",
    "gn:population":0,
    "gn:timezone":"Asia/Shanghai",
    "iso:country":"CN",
    "name:zho_x_preferred":[
        "\u884c\u5bb6\u7a91"
    ],
    "wof:name":"Xingjiayao",
    "wof:placetype":"locality"
},
  "geometry": {"coordinates":[105.79300000000001,37.417],"type":"Point"}
}