{
  "type": "Feature",
  "properties": {
    "gn:admin1_code":"23.0",
    "gn:asciiname":"Hengzhao",
    "gn:country_code":"CN",
    "gn:dem":6,
    "gn:feature_class":"P",
    "gn:feature_code":"PPL",
    "gn:name":"Hengzhao",
    "gn:population":0,
    "gn:timezone":"Asia/Shanghai",
    "iso:country":"CN",
    "name:und_x_variant":[
        "\u6a2a\u53ec"
    ],
    "wof:name":"Hengzhao",
    "wof:placetype":"locality"
},
  "geometry": {"coordinates":[121.23556000000001,30.76364],"type":"Point"}
}