{
  "type": "Feature",
  "properties": {
    "gn:admin1_code":"16.0",
    "gn:asciiname":"Shuweila",
    "gn:country_code":"CN",
    "gn:dem":356,
    "gn:feature_class":"P",
    "gn:feature_code":"PPL",
    "gn:name":"Shuweila",
    "gn:population":0,
    "gn:timezone":"Asia/Shanghai",
    "iso:country":"CN",
    "name:zho_x_preferred":[
        "\u6811\u5a01\u62c9"
    ],
    "wof:name":"Shuweila",
    "wof:placetype":"locality"
},
  "geometry": {"coordinates":[108.541,23.6882],"type":"Point"}
}