{
  "type": "Feature",
  "properties": {
    "gn:admin1_code":"1.0",
    "gn:asciiname":"Liulaojia",
    "gn:country_code":"CN",
    "gn:dem":35,
    "gn:feature_class":"P",
    "gn:feature_code":"PPL",
    "gn:name":"Liulaojia",
    "gn:population":0,
    "gn:timezone":"Asia/Shanghai",
    "iso:country":"CN",
    "wof:name":"Liulaojia",
    "wof:placetype":"locality"
},
  "geometry": {"coordinates":[115.60833,33.29167],"type":"Point"}
}