{
  "type": "Feature",
  "properties": {
    "gn:admin1_code":"15.0",
    "gn:asciiname":"Dazhuangzi",
    "gn:country_code":"CN",
    "gn:dem":2193,
    "gn:feature_class":"P",
    "gn:feature_code":"PPL",
    "gn:name":"Dazhuangzi",
    "gn:population":0,
    "gn:timezone":"Asia/Shanghai",
    "iso:country":"CN",
    "name:zho_x_preferred":[
        "\u5927\u5e84\u5b50"
    ],
    "wof:name":"Dazhuangzi",
    "wof:placetype":"locality"
},
  "geometry": {"coordinates":[103.739,36.7521],"type":"Point"}
}