{
  "type": "Feature",
  "properties": {
    "gn:admin1_code":"3.0",
    "gn:asciiname":"Tangjialong",
    "gn:country_code":"CN",
    "gn:dem":550,
    "gn:feature_class":"P",
    "gn:feature_code":"PPL",
    "gn:name":"Tangjialong",
    "gn:population":0,
    "gn:timezone":"Asia/Shanghai",
    "iso:country":"CN",
    "name:und_x_variant":[
        "\u5510\u5bb6\u5785"
    ],
    "wof:name":"Tangjialong",
    "wof:placetype":"locality"
},
  "geometry": {"coordinates":[114.39306999999999,29.32443],"type":"Point"}
}