{
  "type": "Feature",
  "properties": {
    "gn:admin1_code":"18.0",
    "gn:asciiname":"Xiaohe",
    "gn:country_code":"CN",
    "gn:dem":611,
    "gn:feature_class":"P",
    "gn:feature_code":"PPL",
    "gn:name":"Xiaohe",
    "gn:population":0,
    "gn:timezone":"Asia/Shanghai",
    "iso:country":"CN",
    "name:ceb_x_preferred":[
        "Xiaohe"
    ],
    "name:deu_x_preferred":[
        "Xiaohe"
    ],
    "name:nor_x_preferred":[
        "Xiaohe"
    ],
    "name:swe_x_preferred":[
        "Xiaohe"
    ],
    "wof:name":"Xiaohe",
    "wof:placetype":"locality"
},
  "geometry": {"coordinates":[105.63278,27.65667],"type":"Point"}
}