{
  "type": "Feature",
  "properties": {
    "gn:admin1_code":"4.0",
    "gn:asciiname":"Jijicun",
    "gn:country_code":"CN",
    "gn:dem":27,
    "gn:feature_class":"P",
    "gn:feature_code":"PPL",
    "gn:name":"Jijicun",
    "gn:population":0,
    "gn:timezone":"Asia/Shanghai",
    "iso:country":"CN",
    "name:und_x_variant":[
        "Jiji",
        "Jijicun"
    ],
    "name:zho_x_preferred":[
        "\u7eaa\u96c6"
    ],
    "name:zho_x_variant":[
        "\u7eaa\u96c6\u6751"
    ],
    "wof:name":"Jijicun",
    "wof:placetype":"locality"
},
  "geometry": {"coordinates":[118.0907,34.31708],"type":"Point"}
}