{
  "type": "Feature",
  "properties": {
    "gn:admin1_code":"15.0",
    "gn:asciiname":"Sangjiazhuang",
    "gn:country_code":"CN",
    "gn:dem":1379,
    "gn:feature_class":"P",
    "gn:feature_code":"PPL",
    "gn:name":"Sangjiazhuang",
    "gn:population":0,
    "gn:timezone":"Asia/Shanghai",
    "iso:country":"CN",
    "name:zho_x_preferred":[
        "\u6851\u5bb6\u5e84"
    ],
    "wof:name":"Sangjiazhuang",
    "wof:placetype":"locality"
},
  "geometry": {"coordinates":[103.09,38.5557],"type":"Point"}
}