{
  "type": "Feature",
  "properties": {
    "gn:admin1_code":"7",
    "gn:asciiname":"Sanfuyang",
    "gn:country_code":"CN",
    "gn:dem":409,
    "gn:feature_class":"P",
    "gn:feature_code":"PPL",
    "gn:name":"Sanfuyang",
    "gn:population":0,
    "gn:timezone":"Asia/Shanghai",
    "iso:country":"CN",
    "name:zho_x_preferred":[
        "\u4e09\u5bcc\u6d0b"
    ],
    "wof:name":"Sanfuyang",
    "wof:placetype":"locality"
},
  "geometry": {"coordinates":[118.66696,25.76365],"type":"Point"}
}