{
  "type": "Feature",
  "properties": {
    "gn:admin1_code":"30",
    "gn:asciiname":"Shuangluo",
    "gn:country_code":"CN",
    "gn:dem":168,
    "gn:feature_class":"P",
    "gn:feature_code":"PPL",
    "gn:name":"Shuangluo",
    "gn:population":0,
    "gn:timezone":"Asia/Shanghai",
    "iso:country":"CN",
    "name:und_x_variant":[
        "Shuang-lo",
        "Shuangluo"
    ],
    "name:zho_x_preferred":[
        "\u53cc\u7f57"
    ],
    "wof:name":"Shuangluo",
    "wof:placetype":"locality"
},
  "geometry": {"coordinates":[116.94275,23.95268],"type":"Point"}
}