{
  "type": "Feature",
  "properties": {
    "gn:admin1_code":"2.0",
    "gn:asciiname":"Qianwang",
    "gn:country_code":"CN",
    "gn:dem":58,
    "gn:feature_class":"P",
    "gn:feature_code":"PPL",
    "gn:name":"Qianwang",
    "gn:population":0,
    "gn:timezone":"Asia/Shanghai",
    "iso:country":"CN",
    "name:und_x_variant":[
        "\u524d\u738b",
        "Qianwang"
    ],
    "wof:name":"Qianwang",
    "wof:placetype":"locality"
},
  "geometry": {"coordinates":[119.98783,29.20785],"type":"Point"}
}