{
  "type": "Feature",
  "properties": {
    "gn:admin1_code":"10.0",
    "gn:asciiname":"Baidaokou",
    "gn:country_code":"CN",
    "gn:dem":16,
    "gn:feature_class":"P",
    "gn:feature_code":"PPL",
    "gn:name":"Baidaokou",
    "gn:population":0,
    "gn:timezone":"Asia/Shanghai",
    "iso:country":"CN",
    "name:zho_x_preferred":[
        "\u767e\u9053\u53e3"
    ],
    "wof:name":"Baidaokou",
    "wof:placetype":"locality"
},
  "geometry": {"coordinates":[115.881,38.3759],"type":"Point"}
}