{
  "type": "Feature",
  "properties": {
    "gn:admin1_code":"25",
    "gn:asciiname":"Dongxizuo",
    "gn:country_code":"CN",
    "gn:dem":59,
    "gn:feature_class":"P",
    "gn:feature_code":"PPL",
    "gn:name":"Dongxizuo",
    "gn:population":0,
    "gn:timezone":"Asia/Shanghai",
    "iso:country":"CN",
    "name:zho_x_preferred":[
        "\u4e1c\u897f\u67de"
    ],
    "wof:name":"Dongxizuo",
    "wof:placetype":"locality"
},
  "geometry": {"coordinates":[118.044,34.9173],"type":"Point"}
}