{
  "type": "Feature",
  "properties": {
    "gn:admin1_code":"15.0",
    "gn:asciiname":"Shangya",
    "gn:country_code":"CN",
    "gn:dem":1487,
    "gn:feature_class":"P",
    "gn:feature_code":"PPL",
    "gn:name":"Shangya",
    "gn:population":0,
    "gn:timezone":"Asia/Shanghai",
    "iso:country":"CN",
    "name:zho_x_preferred":[
        "\u4e0a\u5d16"
    ],
    "wof:name":"Shangya",
    "wof:placetype":"locality"
},
  "geometry": {"coordinates":[100.337,38.9932],"type":"Point"}
}