{
  "type": "Feature",
  "properties": {
    "gn:admin1_code":"7.0",
    "gn:asciiname":"Lalitang",
    "gn:country_code":"CN",
    "gn:dem":217,
    "gn:feature_class":"P",
    "gn:feature_code":"PPL",
    "gn:name":"Lalitang",
    "gn:population":0,
    "gn:timezone":"Asia/Shanghai",
    "iso:country":"CN",
    "name:zho_x_preferred":[
        "\u814a\u68a8\u5858"
    ],
    "wof:name":"Lalitang",
    "wof:placetype":"locality"
},
  "geometry": {"coordinates":[116.35995,25.11855],"type":"Point"}
}