{
  "type": "Feature",
  "properties": {
    "gn:admin1_code":"26.0",
    "gn:asciiname":"Yousongyan",
    "gn:country_code":"CN",
    "gn:dem":1154,
    "gn:feature_class":"P",
    "gn:feature_code":"PPL",
    "gn:name":"Yousongyan",
    "gn:population":0,
    "gn:timezone":"Asia/Shanghai",
    "iso:country":"CN",
    "name:zho_x_preferred":[
        "\u6cb9\u677e\u5ca9"
    ],
    "wof:name":"Yousongyan",
    "wof:placetype":"locality"
},
  "geometry": {"coordinates":[108.24505000000001,32.65317],"type":"Point"}
}