{
  "type": "Feature",
  "properties": {
    "gn:admin1_code":"4.0",
    "gn:asciiname":"Guantang",
    "gn:country_code":"CN",
    "gn:dem":8,
    "gn:feature_class":"P",
    "gn:feature_code":"PPL",
    "gn:name":"Guantang",
    "gn:population":0,
    "gn:timezone":"Asia/Shanghai",
    "iso:country":"CN",
    "name:zho_x_preferred":[
        "Guantang"
    ],
    "name:zho_x_variant":[
        "\u5b98\u5858"
    ],
    "wof:name":"Guantang",
    "wof:placetype":"locality"
},
  "geometry": {"coordinates":[119.0677,33.52949],"type":"Point"}
}