{
  "type": "Feature",
  "properties": {
    "gn:admin1_code":"9.0",
    "gn:asciiname":"Beizhuang",
    "gn:country_code":"CN",
    "gn:dem":206,
    "gn:feature_class":"P",
    "gn:feature_code":"PPL",
    "gn:name":"Beizhuang",
    "gn:population":0,
    "gn:timezone":"Asia/Shanghai",
    "iso:country":"CN",
    "name:und_x_variant":[
        "\u5317\u5e84",
        "Beizhuang"
    ],
    "wof:name":"Beizhuang",
    "wof:placetype":"locality"
},
  "geometry": {"coordinates":[112.47314,33.45475],"type":"Point"}
}