{
  "type": "Feature",
  "properties": {
    "gn:admin1_code":"19.0",
    "gn:asciiname":"Zhujia Wobu",
    "gn:country_code":"CN",
    "gn:dem":506,
    "gn:feature_class":"P",
    "gn:feature_code":"PPL",
    "gn:name":"Zhujia Wobu",
    "gn:population":0,
    "gn:timezone":"Asia/Shanghai",
    "iso:country":"CN",
    "name:zho_x_preferred":[
        "\u6731\u5bb6\u7a9d\u5821"
    ],
    "wof:name":"Zhujia Wobu",
    "wof:placetype":"locality"
},
  "geometry": {"coordinates":[120.02321999999999,41.7997],"type":"Point"}
}