{
  "type": "Feature",
  "properties": {
    "gn:admin1_code":"29.0",
    "gn:asciiname":"Xiahaiyi",
    "gn:country_code":"CN",
    "gn:dem":1913,
    "gn:feature_class":"P",
    "gn:feature_code":"PPL",
    "gn:name":"Xiahaiyi",
    "gn:population":0,
    "gn:timezone":"Asia/Shanghai",
    "iso:country":"CN",
    "name:zho_x_preferred":[
        "\u4e0b\u6d77\u5b9c"
    ],
    "wof:name":"Xiahaiyi",
    "wof:placetype":"locality"
},
  "geometry": {"coordinates":[103.479,24.6043],"type":"Point"}
}