{
  "type": "Feature",
  "properties": {
    "gn:admin1_code":"19.0",
    "gn:asciiname":"Wukeyangshu",
    "gn:country_code":"CN",
    "gn:dem":557,
    "gn:feature_class":"P",
    "gn:feature_code":"PPL",
    "gn:name":"Wukeyangshu",
    "gn:population":0,
    "gn:timezone":"Asia/Shanghai",
    "iso:country":"CN",
    "name:und_x_variant":[
        "\u4e94\u68f5\u6768\u6811"
    ],
    "wof:name":"Wukeyangshu",
    "wof:placetype":"locality"
},
  "geometry": {"coordinates":[124.76384,41.82736],"type":"Point"}
}