{
  "type": "Feature",
  "properties": {
    "gn:admin1_code":"18",
    "gn:asciiname":"Yinlong",
    "gn:country_code":"CN",
    "gn:dem":1168,
    "gn:feature_class":"P",
    "gn:feature_code":"PPL",
    "gn:name":"Yinlong",
    "gn:population":0,
    "gn:timezone":"Asia/Shanghai",
    "iso:country":"CN",
    "name:cat_x_preferred":[
        "Yinlong"
    ],
    "name:ces_x_preferred":[
        "Yinlong"
    ],
    "name:deu_x_preferred":[
        "Yinlong"
    ],
    "name:fas_x_preferred":[
        "\u06cc\u06cc\u0646\u200c\u0644\u0627\u0646\u06af"
    ],
    "name:fra_x_preferred":[
        "Yinlong"
    ],
    "name:heb_x_preferred":[
        "\u05d9\u05d9\u05e0\u05dc\u05d5\u05e0\u05d2"
    ],
    "name:hun_x_preferred":[
        "Yinlong"
    ],
    "name:ita_x_preferred":[
        "Yinlong downsi"
    ],
    "name:jpn_x_preferred":[
        "\u30a4\u30f3\u30ed\u30f3\u30b0"
    ],
    "name:mal_x_preferred":[
        "\u0d2f\u0d3f\u0d7b\u0d32\u0d4b\u0d19\u0d4d\u0d19\u0d4d\u200c"
    ],
    "name:nld_x_preferred":[
        "Yinlong"
    ],
    "name:ori_x_preferred":[
        "Yinlong"
    ],
    "name:pol_x_preferred":[
        "Jinlong"
    ],
    "name:por_x_preferred":[
        "Yinlong"
    ],
    "name:rus_x_preferred":[
        "Yinlong"
    ],
    "name:spa_x_preferred":[
        "Yinlong"
    ],
    "name:swe_x_preferred":[
        "Yinlong"
    ],
    "name:ukr_x_preferred":[
        "\u0406\u043d\u044c\u043b\u0443\u043d"
    ],
    "name:vie_x_preferred":[
        "Yinlong"
    ],
    "name:zho_x_preferred":[
        "\u94f6\u9f99"
    ],
    "name:zho_x_variant":[
        "\u96b1\u9f8d\u5c6c"
    ],
    "wof:name":"Yinlong",
    "wof:placetype":"locality"
},
  "geometry": {"coordinates":[106.187,28.2998],"type":"Point"}
}