{
  "type": "Feature",
  "properties": {
    "gn:admin1_code":"18",
    "gn:asciiname":"Yinlong",
    "gn:country_code":"CN",
    "gn:dem":1168,
    "gn:feature_class":"P",
    "gn:feature_code":"PPL",
    "gn:name":"Yinlong",
    "gn:population":0,
    "gn:timezone":"Asia/Shanghai",
    "iso:country":"CN",
    "name:zho_x_preferred":[
        "\u94f6\u9f99"
    ],
    "wof:name":"Yinlong",
    "wof:placetype":"locality"
},
  "geometry": {"coordinates":[106.187,28.2998],"type":"Point"}
}