{
  "type": "Feature",
  "properties": {
    "gn:admin1_code":"26.0",
    "gn:asciiname":"Xiaguodiancun",
    "gn:country_code":"CN",
    "gn:dem":744,
    "gn:feature_class":"P",
    "gn:feature_code":"PPL",
    "gn:name":"Xiaguodiancun",
    "gn:population":0,
    "gn:timezone":"Asia/Shanghai",
    "iso:country":"CN",
    "name:zho_x_preferred":[
        "\u4e0b\u90ed\u5e97\u6751"
    ],
    "wof:name":"Xiaguodiancun",
    "wof:placetype":"locality"
},
  "geometry": {"coordinates":[107.43689000000001,34.44953],"type":"Point"}
}