{
  "type": "Feature",
  "properties": {
    "gn:admin1_code":"32.0",
    "gn:asciiname":"Baocheng",
    "gn:country_code":"CN",
    "gn:dem":355,
    "gn:feature_class":"P",
    "gn:feature_code":"PPL",
    "gn:name":"Baocheng",
    "gn:population":0,
    "gn:timezone":"Asia/Shanghai",
    "iso:country":"CN",
    "name:deu_x_preferred":[
        "Baocheng"
    ],
    "name:zho_x_preferred":[
        "\u5b9d\u57ce"
    ],
    "wof:name":"Baocheng",
    "wof:placetype":"locality"
},
  "geometry": {"coordinates":[106.76188,30.84097],"type":"Point"}
}