{
  "type": "Feature",
  "properties": {
    "gn:admin1_code":"24.0",
    "gn:asciiname":"Dianzishang",
    "gn:country_code":"CN",
    "gn:dem":1585,
    "gn:feature_class":"P",
    "gn:feature_code":"PPL",
    "gn:name":"Dianzishang",
    "gn:population":0,
    "gn:timezone":"Asia/Shanghai",
    "iso:country":"CN",
    "name:zho_x_preferred":[
        "\u5e97\u5b50\u4e0a"
    ],
    "wof:name":"Dianzishang",
    "wof:placetype":"locality"
},
  "geometry": {"coordinates":[111.30638999999999,38.25384],"type":"Point"}
}