{
  "type": "Feature",
  "properties": {
    "gn:admin1_code":"12.0",
    "gn:asciiname":"Chajiapo",
    "gn:country_code":"CN",
    "gn:dem":49,
    "gn:feature_class":"P",
    "gn:feature_code":"PPL",
    "gn:name":"Chajiapo",
    "gn:population":0,
    "gn:timezone":"Asia/Shanghai",
    "iso:country":"CN",
    "name:zho_x_preferred":[
        "\u6942\u5bb6\u5761"
    ],
    "wof:name":"Chajiapo",
    "wof:placetype":"locality"
},
  "geometry": {"coordinates":[113.63314,29.74404],"type":"Point"}
}