{
  "type": "Feature",
  "properties": {
    "gn:admin1_code":"15.0",
    "gn:asciiname":"Taipingbu",
    "gn:country_code":"CN",
    "gn:dem":1691,
    "gn:feature_class":"P",
    "gn:feature_code":"PPL",
    "gn:name":"Taipingbu",
    "gn:population":0,
    "gn:timezone":"Asia/Shanghai",
    "iso:country":"CN",
    "name:zho_x_preferred":[
        "\u592a\u5e73\u5821"
    ],
    "wof:name":"Taipingbu",
    "wof:placetype":"locality"
},
  "geometry": {"coordinates":[104.16800000000001,35.9716],"type":"Point"}
}