{
  "type": "Feature",
  "properties": {
    "gn:admin1_code":"8.0",
    "gn:asciiname":"Qinghai Erdui",
    "gn:country_code":"CN",
    "gn:dem":361,
    "gn:feature_class":"P",
    "gn:feature_code":"PPLF",
    "gn:name":"Qinghai Erdui",
    "gn:population":0,
    "gn:timezone":"Asia/Shanghai",
    "iso:country":"CN",
    "name:zho_x_preferred":[
        "\u9752\u6d77\u4e8c\u961f"
    ],
    "wof:name":"Qinghai Erdui",
    "wof:placetype":"locality"
},
  "geometry": {"coordinates":[126.1174,49.23753],"type":"Point"}
}