{
  "type": "Feature",
  "properties": {
    "gn:admin1_code":"16",
    "gn:asciiname":"Dabanqiao",
    "gn:country_code":"CN",
    "gn:dem":296,
    "gn:feature_class":"P",
    "gn:feature_code":"PPL",
    "gn:name":"Dabanqiao",
    "gn:population":0,
    "gn:timezone":"Asia/Shanghai",
    "iso:country":"CN",
    "name:zho_x_preferred":[
        "\u5927\u677f\u6865"
    ],
    "wof:name":"Dabanqiao",
    "wof:placetype":"locality"
},
  "geometry": {"coordinates":[110.625,25.3816],"type":"Point"}
}