{
  "type": "Feature",
  "properties": {
    "gn:admin1_code":"33.0",
    "gn:asciiname":"Changyi",
    "gn:country_code":"CN",
    "gn:dem":606,
    "gn:feature_class":"P",
    "gn:feature_code":"PPL",
    "gn:name":"Changyi",
    "gn:population":0,
    "gn:timezone":"Asia/Shanghai",
    "iso:country":"CN",
    "name:ceb_x_preferred":[
        "Changyi"
    ],
    "name:deu_x_preferred":[
        "Changyi"
    ],
    "name:fra_x_preferred":[
        "Changyi"
    ],
    "name:nor_x_preferred":[
        "Changyi"
    ],
    "name:rus_x_preferred":[
        "\u0427\u0430\u043d\u044a\u0438"
    ],
    "name:swe_x_preferred":[
        "Changyi"
    ],
    "name:zho_x_preferred":[
        "\u957f\u76ca"
    ],
    "wof:name":"Changyi",
    "wof:placetype":"locality"
},
  "geometry": {"coordinates":[107.0544,29.71865],"type":"Point"}
}