{
  "type": "Feature",
  "properties": {
    "gn:admin1_code":"9.0",
    "gn:asciiname":"Fudonggou",
    "gn:country_code":"CN",
    "gn:dem":348,
    "gn:feature_class":"P",
    "gn:feature_code":"PPL",
    "gn:name":"Fudonggou",
    "gn:population":0,
    "gn:timezone":"Asia/Shanghai",
    "iso:country":"CN",
    "name:zho_x_preferred":[
        "\u4ed8\u4e1c\u6c9f"
    ],
    "wof:name":"Fudonggou",
    "wof:placetype":"locality"
},
  "geometry": {"coordinates":[113.88123,35.94821],"type":"Point"}
}