{
  "type": "Feature",
  "properties": {
    "gn:admin1_code":"02",
    "gn:asciiname":"Hutiancun",
    "gn:country_code":"CN",
    "gn:dem":6,
    "gn:feature_class":"P",
    "gn:feature_code":"PPL",
    "gn:name":"Hutiancun",
    "gn:population":0,
    "gn:timezone":"Asia/Shanghai",
    "iso:country":"CN",
    "name:und_x_variant":[
        "Hutian"
    ],
    "name:zho_x_preferred":[
        "\u6e56\u7530\u6751"
    ],
    "wof:name":"Hutiancun",
    "wof:placetype":"locality"
},
  "geometry": {"coordinates":[121.43962000000001,28.59004],"type":"Point"}
}