{
  "type": "Feature",
  "properties": {
    "gn:admin1_code":"30",
    "gn:asciiname":"Qixing'an",
    "gn:country_code":"CN",
    "gn:dem":864,
    "gn:feature_class":"P",
    "gn:feature_code":"PPL",
    "gn:name":"Qixing\u2019an",
    "gn:population":0,
    "gn:timezone":"Asia/Shanghai",
    "iso:country":"CN",
    "name:zho_x_preferred":[
        "\u4e03\u661f\u5b89"
    ],
    "name:zho_x_variant":[
        "Qixing\u2019an",
        "\u4e03\u661f\u6848"
    ],
    "wof:name":"Qixing'an",
    "wof:placetype":"locality"
},
  "geometry": {"coordinates":[116.64655999999999,23.97544],"type":"Point"}
}