{
  "type": "Feature",
  "properties": {
    "gn:admin1_code":"15.0",
    "gn:asciiname":"Xiayinwa",
    "gn:country_code":"CN",
    "gn:dem":2046,
    "gn:feature_class":"P",
    "gn:feature_code":"PPL",
    "gn:name":"Xiayinwa",
    "gn:population":0,
    "gn:timezone":"Asia/Shanghai",
    "iso:country":"CN",
    "name:zho_x_preferred":[
        "\u4e0b\u9634\u6d3c"
    ],
    "wof:name":"Xiayinwa",
    "wof:placetype":"locality"
},
  "geometry": {"coordinates":[103.669,35.8033],"type":"Point"}
}