{
  "type": "Feature",
  "properties": {
    "gn:admin1_code":"18",
    "gn:asciiname":"Shibanlin",
    "gn:country_code":"CN",
    "gn:dem":1222,
    "gn:feature_class":"P",
    "gn:feature_code":"PPL",
    "gn:name":"Shibanlin",
    "gn:population":0,
    "gn:timezone":"Asia/Shanghai",
    "iso:country":"CN",
    "name:zho_x_preferred":[
        "\u77f3\u677f\u6797"
    ],
    "wof:name":"Shibanlin",
    "wof:placetype":"locality"
},
  "geometry": {"coordinates":[107.282,27.1709],"type":"Point"}
}