{
  "type": "Feature",
  "properties": {
    "gn:admin1_code":"18.0",
    "gn:asciiname":"Pingsun",
    "gn:country_code":"CN",
    "gn:dem":1027,
    "gn:feature_class":"P",
    "gn:feature_code":"PPL",
    "gn:name":"Pingsun",
    "gn:population":0,
    "gn:timezone":"Asia/Shanghai",
    "iso:country":"CN",
    "name:zho_x_preferred":[
        "\u5e73\u7b0b"
    ],
    "wof:name":"Pingsun",
    "wof:placetype":"locality"
},
  "geometry": {"coordinates":[108.69799999999999,26.4272],"type":"Point"}
}