{
  "type": "Feature",
  "properties": {
    "gn:admin1_code":"29.0",
    "gn:asciiname":"Heilucun",
    "gn:country_code":"CN",
    "gn:dem":2326,
    "gn:feature_class":"P",
    "gn:feature_code":"PPL",
    "gn:name":"Heilucun",
    "gn:population":0,
    "gn:timezone":"Asia/Shanghai",
    "iso:country":"CN",
    "name:zho_x_preferred":[
        "\u9ed1\u9c81\u6751"
    ],
    "wof:name":"Heilucun",
    "wof:placetype":"locality"
},
  "geometry": {"coordinates":[103.44199999999999,27.2455],"type":"Point"}
}