{
  "type": "Feature",
  "properties": {
    "gn:admin1_code":"9",
    "gn:asciiname":"Weizhuang",
    "gn:country_code":"CN",
    "gn:dem":62,
    "gn:feature_class":"P",
    "gn:feature_code":"PPL",
    "gn:name":"Weizhuang",
    "gn:population":0,
    "gn:timezone":"Asia/Shanghai",
    "iso:country":"CN",
    "name:zho_x_preferred":[
        "\u4f4d\u5e84"
    ],
    "wof:name":"Weizhuang",
    "wof:placetype":"locality"
},
  "geometry": {"coordinates":[114.855,35.6804],"type":"Point"}
}