{
  "type": "Feature",
  "properties": {
    "gn:admin1_code":"15.0",
    "gn:asciiname":"Chengcao",
    "gn:country_code":"CN",
    "gn:dem":1363,
    "gn:feature_class":"P",
    "gn:feature_code":"PPL",
    "gn:name":"Chengcao",
    "gn:population":0,
    "gn:timezone":"Asia/Shanghai",
    "iso:country":"CN",
    "name:zho_x_preferred":[
        "\u6a59\u69fd"
    ],
    "wof:name":"Chengcao",
    "wof:placetype":"locality"
},
  "geometry": {"coordinates":[103.14400000000001,38.6644],"type":"Point"}
}