{
  "type": "Feature",
  "properties": {
    "gn:admin1_code":"21.0",
    "gn:asciiname":"Heiyaodong",
    "gn:country_code":"CN",
    "gn:dem":1994,
    "gn:feature_class":"P",
    "gn:feature_code":"PPL",
    "gn:name":"Heiyaodong",
    "gn:population":0,
    "gn:timezone":"Asia/Shanghai",
    "iso:country":"CN",
    "name:zho_x_preferred":[
        "\u9ed1\u7a91\u6d1e"
    ],
    "wof:name":"Heiyaodong",
    "wof:placetype":"locality"
},
  "geometry": {"coordinates":[105.887,36.098],"type":"Point"}
}