{
  "type": "Feature",
  "properties": {
    "gn:admin1_code":"15.0",
    "gn:asciiname":"Ganjiangba",
    "gn:country_code":"CN",
    "gn:dem":1387,
    "gn:feature_class":"P",
    "gn:feature_code":"PPL",
    "gn:name":"Ganjiangba",
    "gn:population":0,
    "gn:timezone":"Asia/Shanghai",
    "iso:country":"CN",
    "name:und_x_variant":[
        "\u5e72\u6c5f\u575d"
    ],
    "wof:name":"Ganjiangba",
    "wof:placetype":"locality"
},
  "geometry": {"coordinates":[105.56094,33.08399],"type":"Point"}
}