{
  "type": "Feature",
  "properties": {
    "gn:admin1_code":"32.0",
    "gn:asciiname":"Niuwangbao",
    "gn:country_code":"CN",
    "gn:dem":660,
    "gn:feature_class":"P",
    "gn:feature_code":"PPL",
    "gn:name":"Niuwangbao",
    "gn:population":0,
    "gn:timezone":"Asia/Shanghai",
    "iso:country":"CN",
    "name:zho_x_preferred":[
        "\u725b\u738b\u5305"
    ],
    "wof:name":"Niuwangbao",
    "wof:placetype":"locality"
},
  "geometry": {"coordinates":[106.366,31.8232],"type":"Point"}
}