{
  "type": "Feature",
  "properties": {
    "gn:admin1_code":"29.0",
    "gn:asciiname":"Dashiyan",
    "gn:country_code":"CN",
    "gn:dem":2761,
    "gn:feature_class":"P",
    "gn:feature_code":"PPL",
    "gn:name":"Dashiyan",
    "gn:population":0,
    "gn:timezone":"Asia/Shanghai",
    "iso:country":"CN",
    "name:und_x_variant":[
        "\u5927\u77f3\u5ca9"
    ],
    "wof:name":"Dashiyan",
    "wof:placetype":"locality"
},
  "geometry": {"coordinates":[103.38262,26.35592],"type":"Point"}
}