{
  "type": "Feature",
  "properties": {
    "gn:admin1_code":"3.0",
    "gn:asciiname":"Tulong",
    "gn:country_code":"CN",
    "gn:dem":397,
    "gn:feature_class":"P",
    "gn:feature_code":"PPL",
    "gn:name":"Tulong",
    "gn:population":0,
    "gn:timezone":"Asia/Shanghai",
    "iso:country":"CN",
    "name:und_x_variant":[
        "\u571f\u9f99"
    ],
    "wof:name":"Tulong",
    "wof:placetype":"locality"
},
  "geometry": {"coordinates":[115.5407,26.51797],"type":"Point"}
}