{
  "type": "Feature",
  "properties": {
    "gn:admin1_code":"24",
    "gn:asciiname":"Lichuan",
    "gn:cc2":"CN",
    "gn:country_code":"CN",
    "gn:dem":842,
    "gn:feature_class":"P",
    "gn:feature_code":"PPL",
    "gn:name":"Lichuan",
    "gn:population":0,
    "gn:timezone":"Asia/Shanghai",
    "iso:country":"CN",
    "name:ceb_x_preferred":[
        "Lichuan"
    ],
    "name:deu_x_preferred":[
        "Lichuan"
    ],
    "name:fra_x_preferred":[
        "Lichuan"
    ],
    "name:nor_x_preferred":[
        "Lichuan"
    ],
    "name:swe_x_preferred":[
        "Lichuan"
    ],
    "name:und_x_variant":[
        "Li-ch\u2019uan-chen",
        "Li-ch\u2019uan-ts\u2019un"
    ],
    "wof:name":"Lichuan",
    "wof:placetype":"locality"
},
  "geometry": {"coordinates":[112.75333000000001,35.37833],"type":"Point"}
}