{
  "type": "Feature",
  "properties": {
    "gn:admin1_code":"14.0",
    "gn:asciiname":"Duotong",
    "gn:country_code":"CN",
    "gn:dem":3542,
    "gn:feature_class":"P",
    "gn:feature_code":"PPL",
    "gn:name":"Duotong",
    "gn:population":0,
    "gn:timezone":"Asia/Urumqi",
    "iso:country":"CN",
    "name:zho_x_preferred":[
        "\u591a\u540c"
    ],
    "wof:name":"Duotong",
    "wof:placetype":"locality"
},
  "geometry": {"coordinates":[97.0791,31.70346],"type":"Point"}
}