{
  "type": "Feature",
  "properties": {
    "gn:admin1_code":"1.0",
    "gn:asciiname":"Liudiancun",
    "gn:country_code":"CN",
    "gn:dem":28,
    "gn:feature_class":"P",
    "gn:feature_code":"PPL",
    "gn:name":"Liudiancun",
    "gn:population":0,
    "gn:timezone":"Asia/Shanghai",
    "iso:country":"CN",
    "name:zho_x_preferred":[
        "\u5218\u5e97\u6751"
    ],
    "wof:name":"Liudiancun",
    "wof:placetype":"locality"
},
  "geometry": {"coordinates":[117.05997000000001,31.59394],"type":"Point"}
}