{
  "type": "Feature",
  "properties": {
    "gn:admin1_code":"15.0",
    "gn:asciiname":"Duanwan",
    "gn:country_code":"CN",
    "gn:dem":1874,
    "gn:feature_class":"P",
    "gn:feature_code":"PPL",
    "gn:name":"Duanwan",
    "gn:population":0,
    "gn:timezone":"Asia/Shanghai",
    "iso:country":"CN",
    "name:zho_x_preferred":[
        "\u7aef\u6e7e"
    ],
    "wof:name":"Duanwan",
    "wof:placetype":"locality"
},
  "geometry": {"coordinates":[106.136,35.1844],"type":"Point"}
}