{
  "type": "Feature",
  "properties": {
    "gn:admin1_code":"02",
    "gn:asciiname":"Paimentoucun",
    "gn:country_code":"CN",
    "gn:dem":14,
    "gn:feature_class":"P",
    "gn:feature_code":"PPL",
    "gn:name":"Paimentoucun",
    "gn:population":0,
    "gn:timezone":"Asia/Shanghai",
    "iso:country":"CN",
    "name:und_x_variant":[
        "P\u2019ai-men-t\u2019ou",
        "Paimentou",
        "Paimentoucun"
    ],
    "name:zho_x_preferred":[
        "\u724c\u95e8\u5934"
    ],
    "name:zho_x_variant":[
        "\u724c\u95e8\u5934\u6751"
    ],
    "wof:name":"Paimentoucun",
    "wof:placetype":"locality"
},
  "geometry": {"coordinates":[121.51868,29.59308],"type":"Point"}
}