{
  "type": "Feature",
  "properties": {
    "gn:admin1_code":"3.0",
    "gn:asciiname":"Lijingcun",
    "gn:country_code":"CN",
    "gn:dem":213,
    "gn:feature_class":"P",
    "gn:feature_code":"PPL",
    "gn:name":"Lijingcun",
    "gn:population":0,
    "gn:timezone":"Asia/Shanghai",
    "iso:country":"CN",
    "name:und_x_variant":[
        "\u91cc\u8ff3\u6751"
    ],
    "wof:name":"Lijingcun",
    "wof:placetype":"locality"
},
  "geometry": {"coordinates":[115.93249,26.14222],"type":"Point"}
}