{
  "type": "Feature",
  "properties": {
    "gn:admin1_code":"29.0",
    "gn:asciiname":"Guojiao",
    "gn:country_code":"CN",
    "gn:dem":1029,
    "gn:feature_class":"P",
    "gn:feature_code":"PPL",
    "gn:name":"Guojiao",
    "gn:population":0,
    "gn:timezone":"Asia/Shanghai",
    "iso:country":"CN",
    "name:zho_x_preferred":[
        "\u679c\u89d2"
    ],
    "wof:name":"Guojiao",
    "wof:placetype":"locality"
},
  "geometry": {"coordinates":[99.4885,22.687],"type":"Point"}
}