{
  "type": "Feature",
  "properties": {
    "gn:admin1_code":"12.0",
    "gn:asciiname":"Xuyuanwan",
    "gn:country_code":"CN",
    "gn:dem":31,
    "gn:feature_class":"P",
    "gn:feature_code":"PPL",
    "gn:name":"Xuyuanwan",
    "gn:population":0,
    "gn:timezone":"Asia/Shanghai",
    "iso:country":"CN",
    "name:zho_x_preferred":[
        "\u5f90\u8fdc\u6e7e"
    ],
    "wof:name":"Xuyuanwan",
    "wof:placetype":"locality"
},
  "geometry": {"coordinates":[114.77435,30.97342],"type":"Point"}
}