{
  "type": "Feature",
  "properties": {
    "gn:admin1_code":"2.0",
    "gn:asciiname":"Wangchuanbang",
    "gn:country_code":"CN",
    "gn:dem":6,
    "gn:feature_class":"P",
    "gn:feature_code":"PPL",
    "gn:name":"Wangchuanbang",
    "gn:population":0,
    "gn:timezone":"Asia/Shanghai",
    "iso:country":"CN",
    "name:zho_x_preferred":[
        "\u7f51\u8239\u6d5c"
    ],
    "wof:name":"Wangchuanbang",
    "wof:placetype":"locality"
},
  "geometry": {"coordinates":[121.12475000000001,30.77243],"type":"Point"}
}