{
  "type": "Feature",
  "properties": {
    "gn:admin1_code":"2.0",
    "gn:asciiname":"Qiancheng",
    "gn:country_code":"CN",
    "gn:dem":6,
    "gn:feature_class":"P",
    "gn:feature_code":"PPL",
    "gn:name":"Qiancheng",
    "gn:population":0,
    "gn:timezone":"Asia/Shanghai",
    "iso:country":"CN",
    "name:swe_x_preferred":[
        "Qiancheng"
    ],
    "name:und_x_variant":[
        "\u524d\u57ce"
    ],
    "name:zho_x_preferred":[
        "Qiancheng"
    ],
    "name:zho_x_variant":[
        "\u9ed4\u57ce\u9547"
    ],
    "wof:name":"Qiancheng",
    "wof:placetype":"locality"
},
  "geometry": {"coordinates":[120.05916000000001,30.94931],"type":"Point"}
}