{
  "type": "Feature",
  "properties": {
    "gn:admin1_code":"4.0",
    "gn:asciiname":"Chengwen",
    "gn:country_code":"CN",
    "gn:dem":2,
    "gn:feature_class":"P",
    "gn:feature_code":"PPL",
    "gn:name":"Chengwen",
    "gn:population":0,
    "gn:timezone":"Asia/Shanghai",
    "iso:country":"CN",
    "name:und_x_variant":[
        "\u6210\u6587"
    ],
    "wof:name":"Chengwen",
    "wof:placetype":"locality"
},
  "geometry": {"coordinates":[120.45036,32.94678],"type":"Point"}
}