{
  "type": "Feature",
  "properties": {
    "gn:admin1_code":"19.0",
    "gn:asciiname":"Kongjia Buzicun",
    "gn:country_code":"CN",
    "gn:dem":335,
    "gn:feature_class":"P",
    "gn:feature_code":"PPL",
    "gn:name":"Kongjia Buzicun",
    "gn:population":0,
    "gn:timezone":"Asia/Shanghai",
    "iso:country":"CN",
    "name:zho_x_preferred":[
        "\u5b54\u5bb6\u5821\u5b50\u6751"
    ],
    "wof:name":"Kongjia Buzicun",
    "wof:placetype":"locality"
},
  "geometry": {"coordinates":[124.321,41.2534],"type":"Point"}
}