{
  "type": "Feature",
  "properties": {
    "gn:admin1_code":"18",
    "gn:asciiname":"Laopodi",
    "gn:country_code":"CN",
    "gn:dem":1177,
    "gn:feature_class":"P",
    "gn:feature_code":"PPL",
    "gn:name":"Laopodi",
    "gn:population":0,
    "gn:timezone":"Asia/Shanghai",
    "iso:country":"CN",
    "name:zho_x_preferred":[
        "\u8001\u5761\u5e95"
    ],
    "wof:name":"Laopodi",
    "wof:placetype":"locality"
},
  "geometry": {"coordinates":[105.178,26.2661],"type":"Point"}
}