{
  "type": "Feature",
  "properties": {
    "gn:admin1_code":"11.0",
    "gn:asciiname":"Aokanshang",
    "gn:country_code":"CN",
    "gn:dem":305,
    "gn:feature_class":"P",
    "gn:feature_code":"PPL",
    "gn:name":"Aokanshang",
    "gn:population":0,
    "gn:timezone":"Asia/Shanghai",
    "iso:country":"CN",
    "name:zho_x_preferred":[
        "\u5773\u574e\u4e0a"
    ],
    "wof:name":"Aokanshang",
    "wof:placetype":"locality"
},
  "geometry": {"coordinates":[109.85912999999999,27.34864],"type":"Point"}
}