{
  "type": "Feature",
  "properties": {
    "gn:admin1_code":"8.0",
    "gn:asciiname":"Xunke Sanfenchang Sandui",
    "gn:country_code":"CN",
    "gn:dem":263,
    "gn:feature_class":"P",
    "gn:feature_code":"PPLF",
    "gn:name":"Xunke Sanfenchang Sandui",
    "gn:population":0,
    "gn:timezone":"Asia/Shanghai",
    "iso:country":"CN",
    "name:zho_x_preferred":[
        "\u900a\u514b\u4e09\u5206\u573a\u4e09\u961f"
    ],
    "wof:name":"Xunke Sanfenchang Sandui",
    "wof:placetype":"locality"
},
  "geometry": {"coordinates":[127.93403000000001,49.1902],"type":"Point"}
}