{
  "type": "Feature",
  "properties": {
    "gn:admin1_code":"8.0",
    "gn:asciiname":"Zhangfengshan",
    "gn:country_code":"CN",
    "gn:dem":166,
    "gn:feature_class":"P",
    "gn:feature_code":"PPL",
    "gn:name":"Zhangfengshan",
    "gn:population":0,
    "gn:timezone":"Asia/Shanghai",
    "iso:country":"CN",
    "name:zho_x_preferred":[
        "\u5f20\u51e4\u5c71"
    ],
    "wof:name":"Zhangfengshan",
    "wof:placetype":"locality"
},
  "geometry": {"coordinates":[126.59542,46.7853],"type":"Point"}
}