{
  "type": "Feature",
  "properties": {
    "gn:admin1_code":"30",
    "gn:asciiname":"Qingtong",
    "gn:cc2":"CN",
    "gn:country_code":"CN",
    "gn:dem":14,
    "gn:feature_class":"P",
    "gn:feature_code":"PPL",
    "gn:name":"Qingtong",
    "gn:population":0,
    "gn:timezone":"Asia/Urumqi",
    "iso:country":"CN",
    "name:zho_x_preferred":[
        "Ch\u2019ing-t\u2019ung-hsi-ts\u2019un"
    ],
    "name:zho_x_variant":[
        "\u9752\u6850",
        "\u9752\u540c\u9547"
    ],
    "wof:name":"Qingtong",
    "wof:placetype":"locality"
},
  "geometry": {"coordinates":[110.02056,20.36556],"type":"Point"}
}