{
  "type": "Feature",
  "properties": {
    "gn:admin1_code":"7",
    "gn:asciiname":"Hecun",
    "gn:country_code":"CN",
    "gn:dem":1126,
    "gn:feature_class":"P",
    "gn:feature_code":"PPL",
    "gn:name":"Hecun",
    "gn:population":0,
    "gn:timezone":"Asia/Shanghai",
    "iso:country":"CN",
    "name:ceb_x_preferred":[
        "Hecun"
    ],
    "name:swe_x_preferred":[
        "Hecun"
    ],
    "wof:name":"Hecun",
    "wof:placetype":"locality"
},
  "geometry": {"coordinates":[117.38139,24.97722000000001],"type":"Point"}
}