{
  "type": "Feature",
  "properties": {
    "gn:admin1_code":"16.0",
    "gn:asciiname":"Dadongzi",
    "gn:country_code":"CN",
    "gn:dem":1124,
    "gn:feature_class":"P",
    "gn:feature_code":"PPL",
    "gn:name":"Dadongzi",
    "gn:population":0,
    "gn:timezone":"Asia/Shanghai",
    "iso:country":"CN",
    "name:zho_x_preferred":[
        "\u5927\u5cd2\u5b50"
    ],
    "wof:name":"Dadongzi",
    "wof:placetype":"locality"
},
  "geometry": {"coordinates":[106.464,24.6505],"type":"Point"}
}