{
  "type": "Feature",
  "properties": {
    "gn:admin1_code":"06",
    "gn:asciiname":"Rongwo",
    "gn:country_code":"CN",
    "gn:dem":2506,
    "gn:feature_class":"P",
    "gn:feature_code":"PPLA3",
    "gn:name":"Rongwo",
    "gn:population":0,
    "gn:timezone":"Asia/Shanghai",
    "iso:country":"CN",
    "name:und_x_variant":[
        "Lung-wu-ssu",
        "Tunzhen\u2019",
        "Lung-wu",
        "T\u2019ung-jen",
        "Lung-wu-chen",
        "T\u2019ung-jen-hsien",
        "Rongwo",
        "\u9686\u52a1",
        "\u9686\u52a1\u9547",
        "Longwu Zhen",
        "Tongren Xian",
        "Tongren"
    ],
    "name:zho_x_preferred":[
        "\u540c\u4ec1"
    ],
    "name:zho_x_variant":[
        "\u540c\u4ec1\u53bf"
    ],
    "wof:name":"Rongwo",
    "wof:placetype":"locality"
},
  "geometry": {"coordinates":[102.01600000000001,35.51483],"type":"Point"}
}