{
  "type": "Feature",
  "properties": {
    "gn:admin1_code":"19",
    "gn:asciiname":"Santangcun",
    "gn:country_code":"CN",
    "gn:dem":15,
    "gn:feature_class":"P",
    "gn:feature_code":"PPL",
    "gn:name":"Santangcun",
    "gn:population":0,
    "gn:timezone":"Asia/Shanghai",
    "iso:country":"CN",
    "name:und_x_variant":[
        "Santang"
    ],
    "name:zho_x_preferred":[
        "\u4e09\u5802\u6751"
    ],
    "wof:name":"Santangcun",
    "wof:placetype":"locality"
},
  "geometry": {"coordinates":[121.44970000000001,39.59824],"type":"Point"}
}