{
  "type": "Feature",
  "properties": {
    "gn:admin1_code":"19.0",
    "gn:asciiname":"Youwu",
    "gn:country_code":"CN",
    "gn:dem":40,
    "gn:feature_class":"P",
    "gn:feature_code":"PPL",
    "gn:name":"Youwu",
    "gn:population":0,
    "gn:timezone":"Asia/Shanghai",
    "iso:country":"CN",
    "name:und_x_variant":[
        "\u5c24\u68a7"
    ],
    "wof:name":"Youwu",
    "wof:placetype":"locality"
},
  "geometry": {"coordinates":[122.84276,40.87955],"type":"Point"}
}