{
  "type": "Feature",
  "properties": {
    "gn:admin1_code":"12.0",
    "gn:asciiname":"Minjiatian",
    "gn:country_code":"CN",
    "gn:dem":66,
    "gn:feature_class":"P",
    "gn:feature_code":"PPL",
    "gn:name":"Minjiatian",
    "gn:population":0,
    "gn:timezone":"Asia/Shanghai",
    "iso:country":"CN",
    "name:zho_x_preferred":[
        "\u95f5\u5bb6\u7530"
    ],
    "wof:name":"Minjiatian",
    "wof:placetype":"locality"
},
  "geometry": {"coordinates":[114.49422,31.16136],"type":"Point"}
}