{
  "type": "Feature",
  "properties": {
    "gn:admin1_code":"15.0",
    "gn:asciiname":"Wotuo",
    "gn:country_code":"CN",
    "gn:dem":1303,
    "gn:feature_class":"P",
    "gn:feature_code":"PPL",
    "gn:name":"Wotuo",
    "gn:population":0,
    "gn:timezone":"Asia/Shanghai",
    "iso:country":"CN",
    "name:zho_x_preferred":[
        "\u6da1\u5768"
    ],
    "wof:name":"Wotuo",
    "wof:placetype":"locality"
},
  "geometry": {"coordinates":[105.59099999999999,34.9759],"type":"Point"}
}