{
  "type": "Feature",
  "properties": {
    "gn:admin1_code":"19.0",
    "gn:asciiname":"Damachangcun",
    "gn:country_code":"CN",
    "gn:dem":491,
    "gn:feature_class":"P",
    "gn:feature_code":"PPL",
    "gn:name":"Damachangcun",
    "gn:population":0,
    "gn:timezone":"Asia/Shanghai",
    "iso:country":"CN",
    "name:zho_x_preferred":[
        "\u5927\u9a6c\u573a\u6751"
    ],
    "name:zho_x_variant":[
        "\u5927\u9a6c\u5382\u6751"
    ],
    "wof:name":"Damachangcun",
    "wof:placetype":"locality"
},
  "geometry": {"coordinates":[119.99370999999999,41.76821],"type":"Point"}
}