{
  "type": "Feature",
  "properties": {
    "gn:admin1_code":"19.0",
    "gn:asciiname":"Huweitang",
    "gn:country_code":"CN",
    "gn:dem":4,
    "gn:feature_class":"P",
    "gn:feature_code":"PPL",
    "gn:name":"Huweitang",
    "gn:population":0,
    "gn:timezone":"Asia/Shanghai",
    "iso:country":"CN",
    "name:zho_x_preferred":[
        "\u80e1\u82c7\u5858"
    ],
    "wof:name":"Huweitang",
    "wof:placetype":"locality"
},
  "geometry": {"coordinates":[121.51600000000001,40.9952],"type":"Point"}
}