{
  "type": "Feature",
  "properties": {
    "gn:admin1_code":"14.0",
    "gn:asciiname":"Riyom",
    "gn:country_code":"CN",
    "gn:dem":4260,
    "gn:feature_class":"P",
    "gn:feature_code":"PPLF",
    "gn:name":"Riyom",
    "gn:population":0,
    "gn:timezone":"Asia/Urumqi",
    "iso:country":"CN",
    "name:bod_x_preferred":[
        "Riyom"
    ],
    "name:zho_x_preferred":[
        "Riyong"
    ],
    "name:zho_x_variant":[
        "\u65e5\u62e5",
        "Danagongba",
        "\u8fbe\u7eb3\u8d21\u5df4"
    ],
    "wof:name":"Riyom",
    "wof:placetype":"locality"
},
  "geometry": {"coordinates":[92.601,31.501],"type":"Point"}
}