{
  "type": "Feature",
  "properties": {
    "gn:admin1_code":"32.0",
    "gn:asciiname":"Fuxing",
    "gn:country_code":"CN",
    "gn:dem":558,
    "gn:feature_class":"P",
    "gn:feature_code":"PPL",
    "gn:name":"Fuxing",
    "gn:population":0,
    "gn:timezone":"Asia/Shanghai",
    "iso:country":"CN",
    "name:ceb_x_preferred":[
        "Fuxing"
    ],
    "name:deu_x_preferred":[
        "Fuxing"
    ],
    "name:fra_x_preferred":[
        "Fuxing"
    ],
    "name:jpn_x_preferred":[
        "\u5fa9\u8208"
    ],
    "name:nor_x_preferred":[
        "Fuxing"
    ],
    "name:vie_x_preferred":[
        "Ph\u1ee5c H\u01b0ng"
    ],
    "name:zho_x_preferred":[
        "\u590d\u5174"
    ],
    "wof:name":"Fuxing",
    "wof:placetype":"locality"
},
  "geometry": {"coordinates":[104.002,30.9741],"type":"Point"}
}