{
  "type": "Feature",
  "properties": {
    "gn:admin1_code":"32.0",
    "gn:asciiname":"Youcaoyan",
    "gn:country_code":"CN",
    "gn:dem":385,
    "gn:feature_class":"P",
    "gn:feature_code":"PPL",
    "gn:name":"Youcaoyan",
    "gn:population":0,
    "gn:timezone":"Asia/Shanghai",
    "iso:country":"CN",
    "name:zho_x_preferred":[
        "\u6cb9\u8349\u5830"
    ],
    "wof:name":"Youcaoyan",
    "wof:placetype":"locality"
},
  "geometry": {"coordinates":[105.128,30.3136],"type":"Point"}
}