{
  "type": "Feature",
  "properties": {
    "gn:admin1_code":"9.0",
    "gn:asciiname":"Qiankeng",
    "gn:country_code":"CN",
    "gn:dem":951,
    "gn:feature_class":"P",
    "gn:feature_code":"PPL",
    "gn:name":"Qiankeng",
    "gn:population":0,
    "gn:timezone":"Asia/Shanghai",
    "iso:country":"CN",
    "name:zho_x_preferred":[
        "\u524d\u5751"
    ],
    "wof:name":"Qiankeng",
    "wof:placetype":"locality"
},
  "geometry": {"coordinates":[111.62866,34.05924],"type":"Point"}
}