{
  "type": "Feature",
  "properties": {
    "gn:admin1_code":"32.0",
    "gn:asciiname":"Baoguangsi",
    "gn:country_code":"CN",
    "gn:dem":641,
    "gn:feature_class":"P",
    "gn:feature_code":"PPL",
    "gn:name":"Baoguangsi",
    "gn:population":0,
    "gn:timezone":"Asia/Shanghai",
    "iso:country":"CN",
    "name:zho_x_preferred":[
        "\u5b9d\u5149\u5bfa"
    ],
    "wof:name":"Baoguangsi",
    "wof:placetype":"locality"
},
  "geometry": {"coordinates":[103.77406000000001,30.93323],"type":"Point"}
}