{
  "type": "Feature",
  "properties": {
    "gn:admin1_code":"3.0",
    "gn:asciiname":"Aobei",
    "gn:country_code":"CN",
    "gn:dem":293,
    "gn:feature_class":"P",
    "gn:feature_code":"PPL",
    "gn:name":"Aobei",
    "gn:population":0,
    "gn:timezone":"Asia/Shanghai",
    "iso:country":"CN",
    "name:und_x_variant":[
        "\u5787\u80cc"
    ],
    "wof:name":"Aobei",
    "wof:placetype":"locality"
},
  "geometry": {"coordinates":[115.69291,26.48732],"type":"Point"}
}