{
  "type": "Feature",
  "properties": {
    "gn:admin1_code":"11",
    "gn:asciiname":"Sigu",
    "gn:cc2":"CN",
    "gn:country_code":"CN",
    "gn:dem":347,
    "gn:feature_class":"P",
    "gn:feature_code":"PPL",
    "gn:name":"Sigu",
    "gn:population":0,
    "gn:timezone":"Asia/Shanghai",
    "iso:country":"CN",
    "name:und_x_variant":[
        "Ssu-ku",
        "Sigu"
    ],
    "wof:name":"Sigu",
    "wof:placetype":"locality"
},
  "geometry": {"coordinates":[111.67028000000001,27.83194],"type":"Point"}
}