{
  "type": "Feature",
  "properties": {
    "gn:admin1_code":"3.0",
    "gn:asciiname":"Zhuxingli",
    "gn:country_code":"CN",
    "gn:dem":110,
    "gn:feature_class":"P",
    "gn:feature_code":"PPL",
    "gn:name":"Zhuxingli",
    "gn:population":0,
    "gn:timezone":"Asia/Shanghai",
    "iso:country":"CN",
    "name:zho_x_preferred":[
        "\u732a\u5f62\u91cc"
    ],
    "wof:name":"Zhuxingli",
    "wof:placetype":"locality"
},
  "geometry": {"coordinates":[113.76000000000001,27.5642],"type":"Point"}
}