{
  "type": "Feature",
  "properties": {
    "gn:admin1_code":"3.0",
    "gn:asciiname":"Chongsheng",
    "gn:country_code":"CN",
    "gn:dem":274,
    "gn:feature_class":"P",
    "gn:feature_code":"PPL",
    "gn:name":"Chongsheng",
    "gn:population":0,
    "gn:timezone":"Asia/Shanghai",
    "iso:country":"CN",
    "name:und_x_variant":[
        "\u5d07\u80dc"
    ],
    "wof:name":"Chongsheng",
    "wof:placetype":"locality"
},
  "geometry": {"coordinates":[115.37251999999999,26.56235],"type":"Point"}
}