{
  "type": "Feature",
  "properties": {
    "gn:admin1_code":"9.0",
    "gn:asciiname":"Zhujingou",
    "gn:country_code":"CN",
    "gn:dem":483,
    "gn:feature_class":"P",
    "gn:feature_code":"PPL",
    "gn:name":"Zhujingou",
    "gn:population":0,
    "gn:timezone":"Asia/Shanghai",
    "iso:country":"CN",
    "name:zho_x_preferred":[
        "\u7af9\u8fdb\u6c9f"
    ],
    "wof:name":"Zhujingou",
    "wof:placetype":"locality"
},
  "geometry": {"coordinates":[111.23738,33.37847],"type":"Point"}
}