{
  "type": "Feature",
  "properties": {
    "gn:admin1_code":"16",
    "gn:asciiname":"Diantangbian",
    "gn:country_code":"CN",
    "gn:dem":529,
    "gn:feature_class":"P",
    "gn:feature_code":"PPL",
    "gn:name":"Diantangbian",
    "gn:population":0,
    "gn:timezone":"Asia/Shanghai",
    "iso:country":"CN",
    "name:zho_x_preferred":[
        "\u975b\u5858\u8fb9"
    ],
    "wof:name":"Diantangbian",
    "wof:placetype":"locality"
},
  "geometry": {"coordinates":[110.592,25.7574],"type":"Point"}
}