{
  "type": "Feature",
  "properties": {
    "gn:admin1_code":"9.0",
    "gn:asciiname":"Gezhuang",
    "gn:country_code":"CN",
    "gn:dem":208,
    "gn:feature_class":"P",
    "gn:feature_code":"PPL",
    "gn:name":"Gezhuang",
    "gn:population":0,
    "gn:timezone":"Asia/Shanghai",
    "iso:country":"CN",
    "name:und_x_variant":[
        "\u845b\u5e84",
        "Gezhuang"
    ],
    "wof:name":"Gezhuang",
    "wof:placetype":"locality"
},
  "geometry": {"coordinates":[112.81449000000001,33.58447],"type":"Point"}
}