{
  "type": "Feature",
  "properties": {
    "gn:admin1_code":"19.0",
    "gn:asciiname":"Xiaoqiong Bangzigou",
    "gn:country_code":"CN",
    "gn:dem":139,
    "gn:feature_class":"P",
    "gn:feature_code":"PPL",
    "gn:name":"Xiaoqiong Bangzigou",
    "gn:population":0,
    "gn:timezone":"Asia/Shanghai",
    "iso:country":"CN",
    "name:zho_x_preferred":[
        "\u5c0f\u7a77\u68d2\u5b50\u6c9f"
    ],
    "wof:name":"Xiaoqiong Bangzigou",
    "wof:placetype":"locality"
},
  "geometry": {"coordinates":[125.52128999999999,40.75093],"type":"Point"}
}