{
  "type": "Feature",
  "properties": {
    "gn:admin1_code":"3.0",
    "gn:asciiname":"Shuangxi",
    "gn:country_code":"CN",
    "gn:dem":352,
    "gn:feature_class":"P",
    "gn:feature_code":"PPL",
    "gn:name":"Shuangxi",
    "gn:population":0,
    "gn:timezone":"Asia/Shanghai",
    "iso:country":"CN",
    "name:ceb_x_preferred":[
        "Shuangxi"
    ],
    "name:deu_x_preferred":[
        "Shuangxi"
    ],
    "name:swe_x_preferred":[
        "Shuangxi"
    ],
    "name:und_x_variant":[
        "\u53cc\u6eaa"
    ],
    "wof:name":"Shuangxi",
    "wof:placetype":"locality"
},
  "geometry": {"coordinates":[114.17247999999999,28.65022],"type":"Point"}
}