{
  "type": "Feature",
  "properties": {
    "gn:admin1_code":"7.0",
    "gn:asciiname":"Xiaqu",
    "gn:country_code":"CN",
    "gn:dem":369,
    "gn:feature_class":"P",
    "gn:feature_code":"PPLA4",
    "gn:name":"Xiaqu",
    "gn:population":0,
    "gn:timezone":"Asia/Shanghai",
    "iso:country":"CN",
    "name:und_x_variant":[
        "Xiaqu Xiang",
        "\u4e0b\u6e20\u4e61"
    ],
    "name:zho_x_preferred":[
        "\u4e0b\u6e20"
    ],
    "wof:name":"Xiaqu",
    "wof:placetype":"locality"
},
  "geometry": {"coordinates":[117.15654000000001,26.8237],"type":"Point"}
}