{
  "type": "Feature",
  "properties": {
    "gn:admin1_code":"1.0",
    "gn:asciiname":"Dongjiaocun",
    "gn:country_code":"CN",
    "gn:dem":44,
    "gn:feature_class":"P",
    "gn:feature_code":"PPL",
    "gn:name":"Dongjiaocun",
    "gn:population":0,
    "gn:timezone":"Asia/Shanghai",
    "iso:country":"CN",
    "name:zho_x_preferred":[
        "\u4e1c\u90ca\u6751"
    ],
    "wof:name":"Dongjiaocun",
    "wof:placetype":"locality"
},
  "geometry": {"coordinates":[116.97607000000001,31.0553],"type":"Point"}
}