{
  "type": "Feature",
  "properties": {
    "gn:admin1_code":"9.0",
    "gn:asciiname":"Xiakuitang",
    "gn:country_code":"CN",
    "gn:dem":115,
    "gn:feature_class":"P",
    "gn:feature_code":"PPL",
    "gn:name":"Xiakuitang",
    "gn:population":0,
    "gn:timezone":"Asia/Shanghai",
    "iso:country":"CN",
    "name:zho_x_preferred":[
        "\u4e0b\u6127\u5802"
    ],
    "wof:name":"Xiakuitang",
    "wof:placetype":"locality"
},
  "geometry": {"coordinates":[115.21639,31.81501],"type":"Point"}
}