{
  "type": "Feature",
  "properties": {
    "gn:admin1_code":"25",
    "gn:asciiname":"Houzhuque",
    "gn:country_code":"CN",
    "gn:dem":227,
    "gn:feature_class":"P",
    "gn:feature_code":"PPL",
    "gn:name":"Houzhuque",
    "gn:population":0,
    "gn:timezone":"Asia/Shanghai",
    "iso:country":"CN",
    "name:zho_x_preferred":[
        "\u540e\u6731\u96c0"
    ],
    "wof:name":"Houzhuque",
    "wof:placetype":"locality"
},
  "geometry": {"coordinates":[118.663,36.0456],"type":"Point"}
}