{
  "type": "Feature",
  "properties": {
    "gn:admin1_code":"2.0",
    "gn:asciiname":"Jianxin",
    "gn:country_code":"CN",
    "gn:dem":21,
    "gn:feature_class":"P",
    "gn:feature_code":"PPL",
    "gn:name":"Jianxin",
    "gn:population":0,
    "gn:timezone":"Asia/Shanghai",
    "iso:country":"CN",
    "name:zho_x_preferred":[
        "\u5efa\u65b0"
    ],
    "wof:name":"Jianxin",
    "wof:placetype":"locality"
},
  "geometry": {"coordinates":[121.08087999999999,28.29434],"type":"Point"}
}