{
  "type": "Feature",
  "properties": {
    "gn:admin1_code":"20",
    "gn:asciiname":"Chenjiagou",
    "gn:country_code":"CN",
    "gn:dem":1476,
    "gn:feature_class":"P",
    "gn:feature_code":"PPL",
    "gn:name":"Chenjiagou",
    "gn:population":0,
    "gn:timezone":"Asia/Shanghai",
    "iso:country":"CN",
    "wof:name":"Chenjiagou",
    "wof:placetype":"locality"
},
  "geometry": {"coordinates":[113.98860999999999,41.83722],"type":"Point"}
}