{
  "type": "Feature",
  "properties": {
    "gn:admin1_code":"7.0",
    "gn:asciiname":"Zaoxi",
    "gn:country_code":"CN",
    "gn:dem":380,
    "gn:feature_class":"P",
    "gn:feature_code":"PPL",
    "gn:name":"Zaoxi",
    "gn:population":0,
    "gn:timezone":"Asia/Shanghai",
    "iso:country":"CN",
    "name:zho_x_preferred":[
        "\u8e81\u6eaa"
    ],
    "wof:name":"Zaoxi",
    "wof:placetype":"locality"
},
  "geometry": {"coordinates":[117.17518,25.86712],"type":"Point"}
}