{
  "type": "Feature",
  "properties": {
    "gn:admin1_code":"2.0",
    "gn:asciiname":"Xi'an",
    "gn:country_code":"CN",
    "gn:dem":5,
    "gn:feature_class":"P",
    "gn:feature_code":"PPL",
    "gn:name":"Xi\u2019an",
    "gn:population":0,
    "gn:timezone":"Asia/Shanghai",
    "iso:country":"CN",
    "name:und_x_variant":[
        "Xi\u2019an",
        "\u897f\u5cb8"
    ],
    "wof:name":"Xi'an",
    "wof:placetype":"locality"
},
  "geometry": {"coordinates":[120.4725,30.74092000000001],"type":"Point"}
}