{
  "type": "Feature",
  "properties": {
    "gn:admin1_code":"1.0",
    "gn:asciiname":"Guducun",
    "gn:country_code":"CN",
    "gn:dem":5,
    "gn:feature_class":"P",
    "gn:feature_code":"PPL",
    "gn:name":"Guducun",
    "gn:population":0,
    "gn:timezone":"Asia/Shanghai",
    "iso:country":"CN",
    "name:zho_x_preferred":[
        "\u987e\u6e21\u6751"
    ],
    "wof:name":"Guducun",
    "wof:placetype":"locality"
},
  "geometry": {"coordinates":[117.72595,31.16987],"type":"Point"}
}