{
  "type": "Feature",
  "properties": {
    "gn:admin1_code":"15.0",
    "gn:asciiname":"Suzhoumiao",
    "gn:country_code":"CN",
    "gn:dem":1133,
    "gn:feature_class":"P",
    "gn:feature_code":"PPL",
    "gn:name":"Suzhoumiao",
    "gn:population":0,
    "gn:timezone":"Asia/Urumqi",
    "iso:country":"CN",
    "name:zho_x_preferred":[
        "\u8083\u5dde\u5e99"
    ],
    "wof:name":"Suzhoumiao",
    "wof:placetype":"locality"
},
  "geometry": {"coordinates":[94.6392,40.175],"type":"Point"}
}