{
  "type": "Feature",
  "properties": {
    "gn:admin1_code":"14.0",
    "gn:asciiname":"Dazhang",
    "gn:country_code":"CN",
    "gn:dem":4598,
    "gn:feature_class":"P",
    "gn:feature_code":"PPL",
    "gn:name":"Dazhang",
    "gn:population":0,
    "gn:timezone":"Asia/Urumqi",
    "iso:country":"CN",
    "name:zho_x_preferred":[
        "\u642d\u7ae0"
    ],
    "wof:name":"Dazhang",
    "wof:placetype":"locality"
},
  "geometry": {"coordinates":[86.6574,29.4177],"type":"Point"}
}