{
  "type": "Feature",
  "properties": {
    "gn:admin1_code":"15.0",
    "gn:asciiname":"Dujia Zuitou",
    "gn:country_code":"CN",
    "gn:dem":1894,
    "gn:feature_class":"P",
    "gn:feature_code":"PPL",
    "gn:name":"Dujia Zuitou",
    "gn:population":0,
    "gn:timezone":"Asia/Shanghai",
    "iso:country":"CN",
    "name:zho_x_preferred":[
        "\u675c\u5bb6\u5634\u5934"
    ],
    "wof:name":"Dujia Zuitou",
    "wof:placetype":"locality"
},
  "geometry": {"coordinates":[103.828,35.5747],"type":"Point"}
}