{
  "type": "Feature",
  "properties": {
    "gn:admin1_code":"07",
    "gn:asciiname":"Degongting",
    "gn:country_code":"CN",
    "gn:dem":291,
    "gn:feature_class":"P",
    "gn:feature_code":"PPL",
    "gn:name":"Degongting",
    "gn:population":0,
    "gn:timezone":"Asia/Shanghai",
    "iso:country":"CN",
    "name:zho_x_preferred":[
        "\u5fb7\u529f\u4ead"
    ],
    "wof:name":"Degongting",
    "wof:placetype":"locality"
},
  "geometry": {"coordinates":[120.24847,27.41416],"type":"Point"}
}