{
  "type": "Feature",
  "properties": {
    "gn:admin1_code":"1.0",
    "gn:asciiname":"Dasongcun",
    "gn:country_code":"CN",
    "gn:dem":31,
    "gn:feature_class":"P",
    "gn:feature_code":"PPL",
    "gn:name":"Dasongcun",
    "gn:population":0,
    "gn:timezone":"Asia/Shanghai",
    "iso:country":"CN",
    "name:zho_x_preferred":[
        "\u5927\u5b8b\u6751"
    ],
    "wof:name":"Dasongcun",
    "wof:placetype":"locality"
},
  "geometry": {"coordinates":[118.09896999999999,32.79007],"type":"Point"}
}