{
  "type": "Feature",
  "properties": {
    "gn:admin1_code":"32.0",
    "gn:asciiname":"Kaka",
    "gn:country_code":"CN",
    "gn:dem":2015,
    "gn:feature_class":"P",
    "gn:feature_code":"PPL",
    "gn:name":"Kaka",
    "gn:population":0,
    "gn:timezone":"Asia/Shanghai",
    "iso:country":"CN",
    "name:zho_x_preferred":[
        "\u5361\u5361"
    ],
    "wof:name":"Kaka",
    "wof:placetype":"locality"
},
  "geometry": {"coordinates":[101.86454999999999,31.04281],"type":"Point"}
}