{
  "type": "Feature",
  "properties": {
    "gn:admin1_code":"14.0",
    "gn:asciiname":"Gacang",
    "gn:country_code":"CN",
    "gn:dem":4552,
    "gn:feature_class":"P",
    "gn:feature_code":"PPL",
    "gn:name":"Gacang",
    "gn:population":0,
    "gn:timezone":"Asia/Urumqi",
    "iso:country":"CN",
    "name:bod_x_preferred":[
        "Gacang"
    ],
    "name:zho_x_preferred":[
        "\u560e\u4ed3"
    ],
    "name:zho_x_variant":[
        "Caizha Gongshe",
        "\u624d\u624e\u516c\u793e"
    ],
    "wof:name":"Gacang",
    "wof:placetype":"locality"
},
  "geometry": {"coordinates":[84.501,31.301],"type":"Point"}
}