{
  "type": "Feature",
  "properties": {
    "gn:admin1_code":"04",
    "gn:asciiname":"Changqingsha",
    "gn:country_code":"CN",
    "gn:dem":4,
    "gn:feature_class":"P",
    "gn:feature_code":"PPL",
    "gn:name":"Changqingsha",
    "gn:population":0,
    "gn:timezone":"Asia/Shanghai",
    "iso:country":"CN",
    "name:und_x_variant":[
        "\u957f\u9752\u6c99"
    ],
    "wof:name":"Changqingsha",
    "wof:placetype":"locality"
},
  "geometry": {"coordinates":[120.59332999999999,32.04639],"type":"Point"}
}