{
  "type": "Feature",
  "properties": {
    "gn:admin1_code":"26",
    "gn:asciiname":"Balipingcun",
    "gn:country_code":"CN",
    "gn:dem":1305,
    "gn:feature_class":"P",
    "gn:feature_code":"PPL",
    "gn:name":"Balipingcun",
    "gn:population":0,
    "gn:timezone":"Asia/Shanghai",
    "iso:country":"CN",
    "name:und_x_variant":[
        "Pa-li-p\u2019ing",
        "Baliping",
        "Balipingcun"
    ],
    "name:zho_x_preferred":[
        "\u516b\u91cc\u576a\u6751"
    ],
    "wof:name":"Balipingcun",
    "wof:placetype":"locality"
},
  "geometry": {"coordinates":[108.52804999999999,33.81703],"type":"Point"}
}