{
  "type": "Feature",
  "properties": {
    "gn:admin1_code":"1.0",
    "gn:asciiname":"Liangqiaocun",
    "gn:country_code":"CN",
    "gn:dem":29,
    "gn:feature_class":"P",
    "gn:feature_code":"PPL",
    "gn:name":"Liangqiaocun",
    "gn:population":0,
    "gn:timezone":"Asia/Shanghai",
    "iso:country":"CN",
    "name:zho_x_preferred":[
        "\u6881\u6865\u6751"
    ],
    "wof:name":"Liangqiaocun",
    "wof:placetype":"locality"
},
  "geometry": {"coordinates":[116.45923999999999,33.08823],"type":"Point"}
}