{
  "type": "Feature",
  "properties": {
    "gn:admin1_code":"15.0",
    "gn:asciiname":"Zhaojiaquan",
    "gn:country_code":"CN",
    "gn:dem":1420,
    "gn:feature_class":"P",
    "gn:feature_code":"PPL",
    "gn:name":"Zhaojiaquan",
    "gn:population":0,
    "gn:timezone":"Asia/Shanghai",
    "iso:country":"CN",
    "name:zho_x_preferred":[
        "\u8d75\u5bb6\u5708"
    ],
    "wof:name":"Zhaojiaquan",
    "wof:placetype":"locality"
},
  "geometry": {"coordinates":[103.44,38.368],"type":"Point"}
}