{
  "type": "Feature",
  "properties": {
    "gn:admin1_code":"15.0",
    "gn:asciiname":"Weijiazhuang",
    "gn:country_code":"CN",
    "gn:dem":1637,
    "gn:feature_class":"P",
    "gn:feature_code":"PPL",
    "gn:name":"Weijiazhuang",
    "gn:population":0,
    "gn:timezone":"Asia/Shanghai",
    "iso:country":"CN",
    "name:zho_x_preferred":[
        "\u9b4f\u5bb6\u5e84"
    ],
    "wof:name":"Weijiazhuang",
    "wof:placetype":"locality"
},
  "geometry": {"coordinates":[103.949,36.3155],"type":"Point"}
}