{
  "type": "Feature",
  "properties": {
    "gn:admin1_code":"9",
    "gn:asciiname":"Xiaoshiziwai",
    "gn:country_code":"CN",
    "gn:dem":53,
    "gn:feature_class":"P",
    "gn:feature_code":"PPL",
    "gn:name":"Xiaoshiziwai",
    "gn:population":0,
    "gn:timezone":"Asia/Shanghai",
    "iso:country":"CN",
    "name:zho_x_preferred":[
        "\u5c0f\u4ec0\u5b57\u5916"
    ],
    "wof:name":"Xiaoshiziwai",
    "wof:placetype":"locality"
},
  "geometry": {"coordinates":[115.21057,35.90125],"type":"Point"}
}