{
  "type": "Feature",
  "properties": {
    "gn:admin1_code":"12.0",
    "gn:asciiname":"Zhuyouqiao Shaojia",
    "gn:country_code":"CN",
    "gn:dem":29,
    "gn:feature_class":"P",
    "gn:feature_code":"PPL",
    "gn:name":"Zhuyouqiao Shaojia",
    "gn:population":0,
    "gn:timezone":"Asia/Shanghai",
    "iso:country":"CN",
    "name:zho_x_preferred":[
        "Zhuyouqiao Shaojia"
    ],
    "name:zho_x_variant":[
        "\u6731\u6cb9\u6865\u90b5\u5bb6"
    ],
    "wof:name":"Zhuyouqiao Shaojia",
    "wof:placetype":"locality"
},
  "geometry": {"coordinates":[115.10384999999999,30.15034],"type":"Point"}
}