{
  "type": "Feature",
  "properties": {
    "gn:admin1_code":"1.0",
    "gn:asciiname":"Wagangcun",
    "gn:country_code":"CN",
    "gn:dem":26,
    "gn:feature_class":"P",
    "gn:feature_code":"PPL",
    "gn:name":"Wagangcun",
    "gn:population":0,
    "gn:timezone":"Asia/Shanghai",
    "iso:country":"CN",
    "name:zho_x_preferred":[
        "\u74e6\u5c97\u6751"
    ],
    "wof:name":"Wagangcun",
    "wof:placetype":"locality"
},
  "geometry": {"coordinates":[116.91431,32.29651],"type":"Point"}
}