{
  "type": "Feature",
  "properties": {
    "gn:admin1_code":"19.0",
    "gn:asciiname":"Jiangjia Weizi",
    "gn:country_code":"CN",
    "gn:dem":110,
    "gn:feature_class":"P",
    "gn:feature_code":"PPL",
    "gn:name":"Jiangjia Weizi",
    "gn:population":0,
    "gn:timezone":"Asia/Shanghai",
    "iso:country":"CN",
    "name:zho_x_preferred":[
        "\u59dc\u5bb6\u9688\u5b50"
    ],
    "wof:name":"Jiangjia Weizi",
    "wof:placetype":"locality"
},
  "geometry": {"coordinates":[122.20766,39.73878],"type":"Point"}
}