{
  "type": "Feature",
  "properties": {
    "gn:admin1_code":"32.0",
    "gn:asciiname":"Jintouzhai",
    "gn:country_code":"CN",
    "gn:dem":4180,
    "gn:feature_class":"P",
    "gn:feature_code":"PPL",
    "gn:name":"Jintouzhai",
    "gn:population":0,
    "gn:timezone":"Asia/Shanghai",
    "iso:country":"CN",
    "name:zho_x_preferred":[
        "\u5c3d\u5934\u5be8"
    ],
    "wof:name":"Jintouzhai",
    "wof:placetype":"locality"
},
  "geometry": {"coordinates":[101.51922999999999,30.87605],"type":"Point"}
}