{
  "type": "Feature",
  "properties": {
    "iso:country":"CN",
    "qs:name":"\u5357\u5145",
    "qs:name_adm0":"\u4e2d\u570b",
    "qs:name_adm1":"\u56db\u5ddd\u7701",
    "qs:photos":72,
    "qs:photos_1k":15,
    "qs:photos_9k":1,
    "qs:photos_9r":2,
    "qs:photos_all":72,
    "qs:photos_sr":2,
    "qs:placetype":"Town",
    "qs:pop_sr":"0",
    "wof:name":"\u5357\u5145",
    "wof:placetype":"locality"
},
  "geometry": {"coordinates":[106.083511,30.791838],"type":"Point"}
}