{
  "type": "Feature",
  "properties": {
    "gn:admin1_code":"24.0",
    "gn:asciiname":"Xigai",
    "gn:country_code":"CN",
    "gn:dem":1111,
    "gn:feature_class":"P",
    "gn:feature_code":"PPL",
    "gn:name":"Xigai",
    "gn:population":0,
    "gn:timezone":"Asia/Shanghai",
    "iso:country":"CN",
    "name:zho_x_preferred":[
        "\u5e2d\u76d6"
    ],
    "wof:name":"Xigai",
    "wof:placetype":"locality"
},
  "geometry": {"coordinates":[110.93561,36.43167],"type":"Point"}
}