{
  "type": "Feature",
  "properties": {
    "gn:admin1_code":"14",
    "gn:asciiname":"Kurcur",
    "gn:country_code":"CN",
    "gn:dem":4279,
    "gn:feature_class":"P",
    "gn:feature_code":"PPL",
    "gn:name":"Kurcur",
    "gn:population":0,
    "gn:timezone":"Asia/Urumqi",
    "iso:country":"CN",
    "name:bod_x_preferred":[
        "\u0f42\u0f74\u0f62\u0f0b\u0f58\u0f5a\u0f74\u0f62"
    ],
    "name:bod_x_variant":[
        "\u0f58\u0f5a\u0f74\u0f62"
    ],
    "name:und_x_variant":[
        "Cur"
    ],
    "wof:name":"Kurcur",
    "wof:placetype":"locality"
},
  "geometry": {"coordinates":[90.99263000000001,28.40733],"type":"Point"}
}