{
  "type": "Feature",
  "properties": {
    "gn:admin1_code":"16.0",
    "gn:asciiname":"Shiling'er",
    "gn:country_code":"CN",
    "gn:dem":39,
    "gn:feature_class":"P",
    "gn:feature_code":"PPL",
    "gn:name":"Shiling\u2019er",
    "gn:population":0,
    "gn:timezone":"Asia/Shanghai",
    "iso:country":"CN",
    "name:und_x_variant":[
        "Shiling\u2019er"
    ],
    "name:zho_x_preferred":[
        "\u77f3\u5cad\u513f"
    ],
    "wof:name":"Shiling'er",
    "wof:placetype":"locality"
},
  "geometry": {"coordinates":[110.345,23.6399],"type":"Point"}
}