{
  "type": "Feature",
  "properties": {
    "gn:admin1_code":"26.0",
    "gn:asciiname":"Feizhuhe",
    "gn:country_code":"CN",
    "gn:dem":1391,
    "gn:feature_class":"P",
    "gn:feature_code":"PPL",
    "gn:name":"Feizhuhe",
    "gn:population":0,
    "gn:timezone":"Asia/Shanghai",
    "iso:country":"CN",
    "name:zho_x_preferred":[
        "\u80a5\u732a\u6cb3"
    ],
    "wof:name":"Feizhuhe",
    "wof:placetype":"locality"
},
  "geometry": {"coordinates":[108.73248,35.38501],"type":"Point"}
}