{
  "type": "Feature",
  "properties": {
    "gn:admin1_code":"19.0",
    "gn:asciiname":"Biangoucun",
    "gn:country_code":"CN",
    "gn:dem":248,
    "gn:feature_class":"P",
    "gn:feature_code":"PPL",
    "gn:name":"Biangoucun",
    "gn:population":0,
    "gn:timezone":"Asia/Shanghai",
    "iso:country":"CN",
    "name:zho_x_preferred":[
        "\u8fb9\u6c9f\u6751"
    ],
    "wof:name":"Biangoucun",
    "wof:placetype":"locality"
},
  "geometry": {"coordinates":[124.43544,40.49314],"type":"Point"}
}