{
  "type": "Feature",
  "properties": {
    "gn:admin1_code":"8.0",
    "gn:asciiname":"Lianshengcun",
    "gn:country_code":"CN",
    "gn:dem":153,
    "gn:feature_class":"P",
    "gn:feature_code":"PPL",
    "gn:name":"Lianshengcun",
    "gn:population":0,
    "gn:timezone":"Asia/Shanghai",
    "iso:country":"CN",
    "name:zho_x_preferred":[
        "\u8fde\u751f\u6751"
    ],
    "wof:name":"Lianshengcun",
    "wof:placetype":"locality"
},
  "geometry": {"coordinates":[126.31516000000001,46.98433],"type":"Point"}
}