{
  "type": "Feature",
  "properties": {
    "gn:admin1_code":"26.0",
    "gn:asciiname":"Fumacun",
    "gn:country_code":"CN",
    "gn:dem":378,
    "gn:feature_class":"P",
    "gn:feature_code":"PPL",
    "gn:name":"Fumacun",
    "gn:population":0,
    "gn:timezone":"Asia/Shanghai",
    "iso:country":"CN",
    "name:und_x_variant":[
        "Fuma"
    ],
    "name:zho_x_preferred":[
        "\u9a78\u9a6c\u6751"
    ],
    "name:zho_x_variant":[
        "\u4ed8\u9a6c"
    ],
    "wof:name":"Fumacun",
    "wof:placetype":"locality"
},
  "geometry": {"coordinates":[109.40604999999999,34.71697],"type":"Point"}
}