{
  "type": "Feature",
  "properties": {
    "gn:admin1_code":"29.0",
    "gn:asciiname":"Agaoluo",
    "gn:country_code":"CN",
    "gn:dem":2570,
    "gn:feature_class":"P",
    "gn:feature_code":"PPL",
    "gn:name":"Agaoluo",
    "gn:population":0,
    "gn:timezone":"Asia/Shanghai",
    "iso:country":"CN",
    "name:zho_x_preferred":[
        "\u963f\u9ad8\u6d1b"
    ],
    "wof:name":"Agaoluo",
    "wof:placetype":"locality"
},
  "geometry": {"coordinates":[100.657,27.4806],"type":"Point"}
}