{
  "type": "Feature",
  "properties": {
    "gn:admin1_code":"13",
    "gn:asciiname":"Bashisidai",
    "gn:country_code":"CN",
    "gn:dem":1299,
    "gn:feature_class":"P",
    "gn:feature_code":"PPL",
    "gn:name":"Bashisidai",
    "gn:population":0,
    "gn:timezone":"Asia/Shanghai",
    "iso:country":"CN",
    "name:und_x_variant":[
        "\u5df4\u4ec0\u65af\u4ee3",
        "Bashisidaicun"
    ],
    "name:zho_x_preferred":[
        "\u5df4\u4ec0\u65af\u4ee3\u6751"
    ],
    "wof:name":"Bashisidai",
    "wof:placetype":"locality"
},
  "geometry": {"coordinates":[76.11463000000001,39.5279],"type":"Point"}
}