{
  "type": "Feature",
  "properties": {
    "gn:admin1_code":"1.0",
    "gn:asciiname":"Tangzhaocun",
    "gn:country_code":"CN",
    "gn:dem":73,
    "gn:feature_class":"P",
    "gn:feature_code":"PPL",
    "gn:name":"Tangzhaocun",
    "gn:population":0,
    "gn:timezone":"Asia/Shanghai",
    "iso:country":"CN",
    "name:zho_x_preferred":[
        "\u5858\u8d75\u6751"
    ],
    "wof:name":"Tangzhaocun",
    "wof:placetype":"locality"
},
  "geometry": {"coordinates":[117.78497,32.20515],"type":"Point"}
}