{
  "type": "Feature",
  "properties": {
    "gn:admin1_code":"32.0",
    "gn:asciiname":"Zibei Yuexia",
    "gn:country_code":"CN",
    "gn:dem":3028,
    "gn:feature_class":"P",
    "gn:feature_code":"PPL",
    "gn:name":"Zibei Yuexia",
    "gn:population":0,
    "gn:timezone":"Asia/Shanghai",
    "iso:country":"CN",
    "name:zho_x_preferred":[
        "\u81ea\u80cc\u7ea6\u5477"
    ],
    "wof:name":"Zibei Yuexia",
    "wof:placetype":"locality"
},
  "geometry": {"coordinates":[102.755,28.5343],"type":"Point"}
}