{
  "type": "Feature",
  "properties": {
    "gn:admin1_code":"13.0",
    "gn:asciiname":"Pa-ko-sha-lo",
    "gn:country_code":"CN",
    "gn:dem":1055,
    "gn:feature_class":"P",
    "gn:feature_code":"PPL",
    "gn:name":"Pa-ko-sha-lo",
    "gn:population":0,
    "gn:timezone":"Asia/Urumqi",
    "iso:country":"CN",
    "wof:name":"Pa-ko-sha-lo",
    "wof:placetype":"locality"
},
  "geometry": {"coordinates":[86.47221999999999,41.95278],"type":"Point"}
}