{
  "type": "Feature",
  "properties": {
    "gn:admin1_code":"16.0",
    "gn:asciiname":"Longguang",
    "gn:country_code":"CN",
    "gn:dem":119,
    "gn:feature_class":"P",
    "gn:feature_code":"PPL",
    "gn:name":"Longguang",
    "gn:population":0,
    "gn:timezone":"Asia/Shanghai",
    "iso:country":"CN",
    "name:zho_x_preferred":[
        "\u9686\u5149"
    ],
    "wof:name":"Longguang",
    "wof:placetype":"locality"
},
  "geometry": {"coordinates":[108.658,23.9772],"type":"Point"}
}