{
  "type": "Feature",
  "properties": {
    "gn:admin1_code":"4.0",
    "gn:asciiname":"Longgangzhen",
    "gn:country_code":"CN",
    "gn:dem":10,
    "gn:feature_class":"P",
    "gn:feature_code":"PPL",
    "gn:name":"Longgangzhen",
    "gn:population":0,
    "gn:timezone":"Asia/Shanghai",
    "iso:country":"CN",
    "name:zho_x_preferred":[
        "\u9f99\u5c97\u9547"
    ],
    "wof:name":"Longgangzhen",
    "wof:placetype":"locality"
},
  "geometry": {"coordinates":[118.767,34.345],"type":"Point"}
}