{
  "type": "Feature",
  "properties": {
    "gn:admin1_code":"1.0",
    "gn:asciiname":"Huayuan",
    "gn:country_code":"CN",
    "gn:dem":56,
    "gn:feature_class":"P",
    "gn:feature_code":"PPL",
    "gn:name":"Huayuan",
    "gn:population":0,
    "gn:timezone":"Asia/Shanghai",
    "iso:country":"CN",
    "name:ceb_x_preferred":[
        "Huayuan"
    ],
    "name:deu_x_preferred":[
        "Huayuan"
    ],
    "name:kor_x_preferred":[
        "\ud654\uc704\uc548"
    ],
    "name:zho_x_preferred":[
        "Huayuan"
    ],
    "name:zho_x_variant":[
        "\u82b1\u56ed"
    ],
    "wof:name":"Huayuan",
    "wof:placetype":"locality"
},
  "geometry": {"coordinates":[119.58503,31.01852],"type":"Point"}
}