{
  "type": "Feature",
  "properties": {
    "gn:admin1_code":"14.0",
    "gn:asciiname":"Huazhucun",
    "gn:country_code":"CN",
    "gn:dem":4345,
    "gn:feature_class":"P",
    "gn:feature_code":"PPL",
    "gn:name":"Huazhucun",
    "gn:population":0,
    "gn:timezone":"Asia/Urumqi",
    "iso:country":"CN",
    "name:zho_x_preferred":[
        "\u534e\u73e0\u6751"
    ],
    "wof:name":"Huazhucun",
    "wof:placetype":"locality"
},
  "geometry": {"coordinates":[90.15269000000001,29.23378],"type":"Point"}
}