{
  "type": "Feature",
  "properties": {
    "gn:admin1_code":"30",
    "gn:asciiname":"Duonianshan",
    "gn:country_code":"CN",
    "gn:dem":24,
    "gn:feature_class":"P",
    "gn:feature_code":"PPL",
    "gn:name":"Duonianshan",
    "gn:population":0,
    "gn:timezone":"Asia/Shanghai",
    "iso:country":"CN",
    "name:zho_x_preferred":[
        "\u591a\u5e74\u5c71"
    ],
    "wof:name":"Duonianshan",
    "wof:placetype":"locality"
},
  "geometry": {"coordinates":[116.21565,23.25946],"type":"Point"}
}