{
  "type": "Feature",
  "properties": {
    "gn:admin1_code":"11.0",
    "gn:asciiname":"Luoziya",
    "gn:country_code":"CN",
    "gn:dem":791,
    "gn:feature_class":"P",
    "gn:feature_code":"PPL",
    "gn:name":"Luoziya",
    "gn:population":0,
    "gn:timezone":"Asia/Shanghai",
    "iso:country":"CN",
    "name:zho_x_preferred":[
        "\u9aa1\u5b50\u57ad"
    ],
    "wof:name":"Luoziya",
    "wof:placetype":"locality"
},
  "geometry": {"coordinates":[110.82859000000001,29.43076],"type":"Point"}
}