{
  "type": "Feature",
  "properties": {
    "gn:admin1_code":"14.0",
    "gn:asciiname":"Ruocun",
    "gn:country_code":"CN",
    "gn:dem":4061,
    "gn:feature_class":"P",
    "gn:feature_code":"PPL",
    "gn:name":"Ruocun",
    "gn:population":0,
    "gn:timezone":"Asia/Urumqi",
    "iso:country":"CN",
    "name:zho_x_preferred":[
        "\u82e5\u6751"
    ],
    "wof:name":"Ruocun",
    "wof:placetype":"locality"
},
  "geometry": {"coordinates":[94.97725,30.88237],"type":"Point"}
}