{
  "type": "Feature",
  "properties": {
    "gn:admin1_code":"30.0",
    "gn:asciiname":"Xinlaichen",
    "gn:country_code":"CN",
    "gn:dem":176,
    "gn:feature_class":"P",
    "gn:feature_code":"PPL",
    "gn:name":"Xinlaichen",
    "gn:population":0,
    "gn:timezone":"Asia/Shanghai",
    "iso:country":"CN",
    "name:zho_x_preferred":[
        "\u65b0\u6765\u9648"
    ],
    "wof:name":"Xinlaichen",
    "wof:placetype":"locality"
},
  "geometry": {"coordinates":[115.15922999999999,23.52234],"type":"Point"}
}