{
  "type": "Feature",
  "properties": {
    "gn:admin1_code":"16",
    "gn:asciiname":"Ganzi",
    "gn:country_code":"CN",
    "gn:dem":355,
    "gn:feature_class":"P",
    "gn:feature_code":"PPL",
    "gn:name":"Ganzi",
    "gn:population":0,
    "gn:timezone":"Asia/Shanghai",
    "iso:country":"CN",
    "name:ceb_x_preferred":[
        "Ganzi"
    ],
    "name:deu_x_preferred":[
        "Ganzi"
    ],
    "name:swe_x_preferred":[
        "Ganzi"
    ],
    "name:zho_x_preferred":[
        "\u67d1\u5b50"
    ],
    "wof:name":"Ganzi",
    "wof:placetype":"locality"
},
  "geometry": {"coordinates":[110.496,25.1052],"type":"Point"}
}