{
  "type": "Feature",
  "properties": {
    "gn:admin1_code":"25.0",
    "gn:asciiname":"Dazhongxing",
    "gn:country_code":"CN",
    "gn:dem":61,
    "gn:feature_class":"P",
    "gn:feature_code":"PPL",
    "gn:name":"Dazhongxing",
    "gn:population":0,
    "gn:timezone":"Asia/Shanghai",
    "iso:country":"CN",
    "name:zho_x_preferred":[
        "\u5927\u91cd\u5174"
    ],
    "wof:name":"Dazhongxing",
    "wof:placetype":"locality"
},
  "geometry": {"coordinates":[119.4773,36.05893],"type":"Point"}
}