{
  "type": "Feature",
  "properties": {
    "gn:admin1_code":"32.0",
    "gn:asciiname":"Hongliang",
    "gn:country_code":"CN",
    "gn:dem":2499,
    "gn:feature_class":"P",
    "gn:feature_code":"PPL",
    "gn:name":"Hongliang",
    "gn:population":0,
    "gn:timezone":"Asia/Shanghai",
    "iso:country":"CN",
    "name:zho_x_preferred":[
        "\u7ea2\u6881"
    ],
    "wof:name":"Hongliang",
    "wof:placetype":"locality"
},
  "geometry": {"coordinates":[102.843,27.1041],"type":"Point"}
}