{
  "type": "Feature",
  "properties": {
    "gn:admin1_code":"32.0",
    "gn:asciiname":"Sihe",
    "gn:country_code":"CN",
    "gn:dem":600,
    "gn:feature_class":"P",
    "gn:feature_code":"PPL",
    "gn:name":"Sihe",
    "gn:population":0,
    "gn:timezone":"Asia/Shanghai",
    "iso:country":"CN",
    "name:zho_x_preferred":[
        "\u56db\u5408"
    ],
    "wof:name":"Sihe",
    "wof:placetype":"locality"
},
  "geometry": {"coordinates":[105.23099999999999,31.9176],"type":"Point"}
}