{
  "type": "Feature",
  "properties": {
    "gn:admin1_code":"24.0",
    "gn:asciiname":"Taoqu",
    "gn:country_code":"CN",
    "gn:dem":892,
    "gn:feature_class":"P",
    "gn:feature_code":"PPL",
    "gn:name":"Taoqu",
    "gn:population":0,
    "gn:timezone":"Asia/Shanghai",
    "iso:country":"CN",
    "name:zho_x_preferred":[
        "\u6843\u66f2"
    ],
    "wof:name":"Taoqu",
    "wof:placetype":"locality"
},
  "geometry": {"coordinates":[112.22812999999999,36.1815],"type":"Point"}
}