{
  "type": "Feature",
  "properties": {
    "gn:admin1_code":"30.0",
    "gn:asciiname":"Xinzhicun",
    "gn:country_code":"CN",
    "gn:dem":4,
    "gn:feature_class":"P",
    "gn:feature_code":"PPL",
    "gn:name":"Xinzhicun",
    "gn:population":0,
    "gn:timezone":"Asia/Shanghai",
    "iso:country":"CN",
    "name:zho_x_preferred":[
        "\u65b0\u7f6e\u6751"
    ],
    "wof:name":"Xinzhicun",
    "wof:placetype":"locality"
},
  "geometry": {"coordinates":[115.57483999999999,22.84378],"type":"Point"}
}