{
  "type": "Feature",
  "properties": {
    "gn:admin1_code":"15.0",
    "gn:asciiname":"Maogeda",
    "gn:country_code":"CN",
    "gn:dem":956,
    "gn:feature_class":"P",
    "gn:feature_code":"PPL",
    "gn:name":"Maogeda",
    "gn:population":0,
    "gn:timezone":"Asia/Shanghai",
    "iso:country":"CN",
    "name:zho_x_preferred":[
        "\u6bdb\u7599\u7629"
    ],
    "wof:name":"Maogeda",
    "wof:placetype":"locality"
},
  "geometry": {"coordinates":[105.44199999999999,32.7385],"type":"Point"}
}