{
  "type": "Feature",
  "properties": {
    "gn:admin1_code":"7",
    "gn:asciiname":"Huangbu",
    "gn:country_code":"CN",
    "gn:dem":421,
    "gn:feature_class":"P",
    "gn:feature_code":"PPLA4",
    "gn:name":"Huangbu",
    "gn:population":0,
    "gn:timezone":"Asia/Shanghai",
    "iso:country":"CN",
    "name:und_x_variant":[
        "\u9ec4\u57e0"
    ],
    "wof:name":"Huangbu",
    "wof:placetype":"locality"
},
  "geometry": {"coordinates":[116.65326,26.7421],"type":"Point"}
}