{
  "type": "Feature",
  "properties": {
    "gn:admin1_code":"26.0",
    "gn:asciiname":"Gaoyuansicun",
    "gn:country_code":"CN",
    "gn:dem":522,
    "gn:feature_class":"P",
    "gn:feature_code":"PPL",
    "gn:name":"Gaoyuansicun",
    "gn:population":0,
    "gn:timezone":"Asia/Shanghai",
    "iso:country":"CN",
    "name:und_x_variant":[
        "\u9ad8\u539f\u5bfa\u6751"
    ],
    "wof:name":"Gaoyuansicun",
    "wof:placetype":"locality"
},
  "geometry": {"coordinates":[107.66051000000002,33.25254],"type":"Point"}
}