{
  "type": "Feature",
  "properties": {
    "gn:admin1_code":"15.0",
    "gn:asciiname":"Jiuzhuang Wowo",
    "gn:country_code":"CN",
    "gn:dem":1772,
    "gn:feature_class":"P",
    "gn:feature_code":"PPL",
    "gn:name":"Jiuzhuang Wowo",
    "gn:population":0,
    "gn:timezone":"Asia/Shanghai",
    "iso:country":"CN",
    "name:zho_x_preferred":[
        "\u65e7\u5e84\u7a9d\u7a9d"
    ],
    "wof:name":"Jiuzhuang Wowo",
    "wof:placetype":"locality"
},
  "geometry": {"coordinates":[105.193,36.8839],"type":"Point"}
}