{
  "type": "Feature",
  "properties": {
    "gn:admin1_code":"5.0",
    "gn:asciiname":"Lanjiacun",
    "gn:country_code":"CN",
    "gn:dem":198,
    "gn:feature_class":"P",
    "gn:feature_code":"PPL",
    "gn:name":"Lanjiacun",
    "gn:population":0,
    "gn:timezone":"Asia/Shanghai",
    "iso:country":"CN",
    "name:zho_x_preferred":[
        "\u84dd\u5bb6\u6751"
    ],
    "wof:name":"Lanjiacun",
    "wof:placetype":"locality"
},
  "geometry": {"coordinates":[125.34381,44.08957],"type":"Point"}
}