{
  "type": "Feature",
  "properties": {
    "gn:admin1_code":"11.0",
    "gn:asciiname":"Qingshuiyuan",
    "gn:country_code":"CN",
    "gn:dem":158,
    "gn:feature_class":"P",
    "gn:feature_code":"PPL",
    "gn:name":"Qingshuiyuan",
    "gn:population":0,
    "gn:timezone":"Asia/Shanghai",
    "iso:country":"CN",
    "name:zho_x_preferred":[
        "\u6e05\u6c34\u6e90"
    ],
    "wof:name":"Qingshuiyuan",
    "wof:placetype":"locality"
},
  "geometry": {"coordinates":[113.57661,29.42487],"type":"Point"}
}