{
  "type": "Feature",
  "properties": {
    "gn:admin1_code":"3.0",
    "gn:asciiname":"Doumen",
    "gn:country_code":"CN",
    "gn:dem":96,
    "gn:feature_class":"P",
    "gn:feature_code":"PPL",
    "gn:name":"Doumen",
    "gn:population":0,
    "gn:timezone":"Asia/Shanghai",
    "iso:country":"CN",
    "name:ceb_x_preferred":[
        "Doumen"
    ],
    "name:deu_x_preferred":[
        "Doumen"
    ],
    "name:und_x_variant":[
        "\u6597\u95e8"
    ],
    "wof:name":"Doumen",
    "wof:placetype":"locality"
},
  "geometry": {"coordinates":[114.53073999999999,28.13362],"type":"Point"}
}