{
  "type": "Feature",
  "properties": {
    "gn:admin1_code":"15.0",
    "gn:asciiname":"Weiwen",
    "gn:country_code":"CN",
    "gn:dem":1828,
    "gn:feature_class":"P",
    "gn:feature_code":"PPL",
    "gn:name":"Weiwen",
    "gn:population":0,
    "gn:timezone":"Asia/Shanghai",
    "iso:country":"CN",
    "name:zho_x_preferred":[
        "\u851a\u6587"
    ],
    "wof:name":"Weiwen",
    "wof:placetype":"locality"
},
  "geometry": {"coordinates":[105.839,34.9412],"type":"Point"}
}