{
  "type": "Feature",
  "properties": {
    "gn:admin1_code":"5.0",
    "gn:asciiname":"Toudaoquancun",
    "gn:country_code":"CN",
    "gn:dem":154,
    "gn:feature_class":"P",
    "gn:feature_code":"PPL",
    "gn:name":"Toudaoquancun",
    "gn:population":0,
    "gn:timezone":"Asia/Shanghai",
    "iso:country":"CN",
    "name:zho_x_preferred":[
        "\u5934\u9053\u5708\u6751"
    ],
    "wof:name":"Toudaoquancun",
    "wof:placetype":"locality"
},
  "geometry": {"coordinates":[124.36408,43.80301],"type":"Point"}
}