{
  "type": "Feature",
  "properties": {
    "gn:admin1_code":"9.0",
    "gn:asciiname":"Yuchong",
    "gn:country_code":"CN",
    "gn:dem":107,
    "gn:feature_class":"P",
    "gn:feature_code":"PPL",
    "gn:name":"Yuchong",
    "gn:population":0,
    "gn:timezone":"Asia/Shanghai",
    "iso:country":"CN",
    "name:zho_x_preferred":[
        "\u4f59\u51b2"
    ],
    "wof:name":"Yuchong",
    "wof:placetype":"locality"
},
  "geometry": {"coordinates":[114.01855999999999,32.57624000000001],"type":"Point"}
}