{
  "type": "Feature",
  "properties": {
    "gn:admin1_code":"32.0",
    "gn:asciiname":"Yilishuiliang",
    "gn:country_code":"CN",
    "gn:dem":2694,
    "gn:feature_class":"P",
    "gn:feature_code":"PPL",
    "gn:name":"Yilishuiliang",
    "gn:population":0,
    "gn:timezone":"Asia/Shanghai",
    "iso:country":"CN",
    "name:zho_x_preferred":[
        "\u4e00\u91cc\u6c34\u51c9"
    ],
    "wof:name":"Yilishuiliang",
    "wof:placetype":"locality"
},
  "geometry": {"coordinates":[102.833,28.0928],"type":"Point"}
}