{
  "type": "Feature",
  "properties": {
    "gn:admin1_code":"14.0",
    "gn:asciiname":"Luoqiong",
    "gn:country_code":"CN",
    "gn:dem":4452,
    "gn:feature_class":"P",
    "gn:feature_code":"PPL",
    "gn:name":"Luoqiong",
    "gn:population":0,
    "gn:timezone":"Asia/Urumqi",
    "iso:country":"CN",
    "name:zho_x_preferred":[
        "\u7f57\u7a77"
    ],
    "wof:name":"Luoqiong",
    "wof:placetype":"locality"
},
  "geometry": {"coordinates":[88.214,28.3272],"type":"Point"}
}