{
  "type": "Feature",
  "properties": {
    "gn:admin1_code":"26.0",
    "gn:asciiname":"Dapinggoukou",
    "gn:country_code":"CN",
    "gn:dem":1608,
    "gn:feature_class":"P",
    "gn:feature_code":"PPL",
    "gn:name":"Dapinggoukou",
    "gn:population":0,
    "gn:timezone":"Asia/Shanghai",
    "iso:country":"CN",
    "name:zho_x_preferred":[
        "\u5927\u5e73\u6c9f\u53e3"
    ],
    "wof:name":"Dapinggoukou",
    "wof:placetype":"locality"
},
  "geometry": {"coordinates":[109.30307999999999,33.84165],"type":"Point"}
}