{
  "type": "Feature",
  "properties": {
    "gn:admin1_code":"14.0",
    "gn:asciiname":"Lalong",
    "gn:country_code":"CN",
    "gn:dem":4296,
    "gn:feature_class":"P",
    "gn:feature_code":"PPL",
    "gn:name":"Lalong",
    "gn:population":0,
    "gn:timezone":"Asia/Urumqi",
    "iso:country":"CN",
    "name:zho_x_preferred":[
        "\u62c9\u5784"
    ],
    "wof:name":"Lalong",
    "wof:placetype":"locality"
},
  "geometry": {"coordinates":[97.37737,30.29229],"type":"Point"}
}