{
  "type": "Feature",
  "properties": {
    "gn:admin1_code":"10",
    "gn:asciiname":"Xiaofanzhangzi",
    "gn:country_code":"CN",
    "gn:dem":424,
    "gn:feature_class":"P",
    "gn:feature_code":"PPL",
    "gn:name":"Xiaofanzhangzi",
    "gn:population":0,
    "gn:timezone":"Asia/Shanghai",
    "iso:country":"CN",
    "name:zho_x_preferred":[
        "\u5c0f\u8303\u6756\u5b50"
    ],
    "wof:name":"Xiaofanzhangzi",
    "wof:placetype":"locality"
},
  "geometry": {"coordinates":[118.31683,40.90961],"type":"Point"}
}