{
  "type": "Feature",
  "properties": {
    "gn:admin1_code":"16.0",
    "gn:asciiname":"Hecanglingjiao",
    "gn:country_code":"CN",
    "gn:dem":38,
    "gn:feature_class":"P",
    "gn:feature_code":"PPL",
    "gn:name":"Hecanglingjiao",
    "gn:population":0,
    "gn:timezone":"Asia/Shanghai",
    "iso:country":"CN",
    "name:zho_x_preferred":[
        "\u79be\u4ed3\u5cad\u811a"
    ],
    "wof:name":"Hecanglingjiao",
    "wof:placetype":"locality"
},
  "geometry": {"coordinates":[109.709,22.0469],"type":"Point"}
}