{
  "type": "Feature",
  "properties": {
    "gn:admin1_code":"7",
    "gn:asciiname":"Dongzhushan",
    "gn:country_code":"CN",
    "gn:dem":10,
    "gn:feature_class":"P",
    "gn:feature_code":"PPL",
    "gn:name":"Dongzhushan",
    "gn:population":0,
    "gn:timezone":"Asia/Shanghai",
    "iso:country":"CN",
    "name:zho_x_preferred":[
        "\u4e1c\u73e0\u5c71"
    ],
    "wof:name":"Dongzhushan",
    "wof:placetype":"locality"
},
  "geometry": {"coordinates":[119.60157,25.78694],"type":"Point"}
}