{
  "type": "Feature",
  "properties": {
    "gn:admin1_code":"25.0",
    "gn:asciiname":"Wujiacun",
    "gn:country_code":"CN",
    "gn:dem":46,
    "gn:feature_class":"P",
    "gn:feature_code":"PPL",
    "gn:name":"Wujiacun",
    "gn:population":0,
    "gn:timezone":"Asia/Shanghai",
    "iso:country":"CN",
    "name:zho_x_preferred":[
        "\u5434\u5bb6\u6751"
    ],
    "wof:name":"Wujiacun",
    "wof:placetype":"locality"
},
  "geometry": {"coordinates":[120.63576,37.57339],"type":"Point"}
}