{
  "type": "Feature",
  "properties": {
    "gn:admin1_code":"15.0",
    "gn:asciiname":"Luo'erqu",
    "gn:country_code":"CN",
    "gn:dem":1367,
    "gn:feature_class":"P",
    "gn:feature_code":"PPL",
    "gn:name":"Luo\u2019erqu",
    "gn:population":0,
    "gn:timezone":"Asia/Shanghai",
    "iso:country":"CN",
    "name:und_x_variant":[
        "Luo\u2019erqu"
    ],
    "name:zho_x_preferred":[
        "\u7f57\u513f\u66f2"
    ],
    "wof:name":"Luo'erqu",
    "wof:placetype":"locality"
},
  "geometry": {"coordinates":[105.13500000000001,34.7698],"type":"Point"}
}