{
  "type": "Feature",
  "properties": {
    "gn:admin1_code":"19.0",
    "gn:asciiname":"Qingshilingcun",
    "gn:country_code":"CN",
    "gn:dem":19,
    "gn:feature_class":"P",
    "gn:feature_code":"PPL",
    "gn:name":"Qingshilingcun",
    "gn:population":0,
    "gn:timezone":"Asia/Shanghai",
    "iso:country":"CN",
    "name:und_x_variant":[
        "\u9752\u77f3\u5cad\u6751"
    ],
    "wof:name":"Qingshilingcun",
    "wof:placetype":"locality"
},
  "geometry": {"coordinates":[122.41113,40.46297],"type":"Point"}
}