{
  "type": "Feature",
  "properties": {
    "gn:admin1_code":"15.0",
    "gn:asciiname":"Changjia Yawan",
    "gn:country_code":"CN",
    "gn:dem":1559,
    "gn:feature_class":"P",
    "gn:feature_code":"PPL",
    "gn:name":"Changjia Yawan",
    "gn:population":0,
    "gn:timezone":"Asia/Shanghai",
    "iso:country":"CN",
    "name:zho_x_preferred":[
        "\u5e38\u5bb6\u5d16\u6e7e"
    ],
    "wof:name":"Changjia Yawan",
    "wof:placetype":"locality"
},
  "geometry": {"coordinates":[105.224,34.9657],"type":"Point"}
}