{
  "type": "Feature",
  "properties": {
    "gn:admin1_code":"10.0",
    "gn:asciiname":"Gaoguzi",
    "gn:country_code":"CN",
    "gn:dem":6,
    "gn:feature_class":"P",
    "gn:feature_code":"PPL",
    "gn:name":"Gaoguzi",
    "gn:population":0,
    "gn:timezone":"Asia/Shanghai",
    "iso:country":"CN",
    "name:zho_x_preferred":[
        "\u9ad8\u6cbd\u5b50"
    ],
    "wof:name":"Gaoguzi",
    "wof:placetype":"locality"
},
  "geometry": {"coordinates":[117.57617999999999,39.75192],"type":"Point"}
}