{
  "type": "Feature",
  "properties": {
    "gn:admin1_code":"2.0",
    "gn:asciiname":"Zhengwu",
    "gn:country_code":"CN",
    "gn:dem":269,
    "gn:feature_class":"P",
    "gn:feature_code":"PPL",
    "gn:name":"Zhengwu",
    "gn:population":0,
    "gn:timezone":"Asia/Shanghai",
    "iso:country":"CN",
    "name:und_x_variant":[
        "\u6b63\u575e"
    ],
    "wof:name":"Zhengwu",
    "wof:placetype":"locality"
},
  "geometry": {"coordinates":[119.29465999999999,29.90157],"type":"Point"}
}