{
  "type": "Feature",
  "properties": {
    "gn:admin1_code":"5.0",
    "gn:asciiname":"Xijiaxintun",
    "gn:country_code":"CN",
    "gn:dem":241,
    "gn:feature_class":"P",
    "gn:feature_code":"PPL",
    "gn:name":"Xijiaxintun",
    "gn:population":0,
    "gn:timezone":"Asia/Shanghai",
    "iso:country":"CN",
    "name:zho_x_preferred":[
        "\u897f\u52a0\u4fe1\u5c6f"
    ],
    "wof:name":"Xijiaxintun",
    "wof:placetype":"locality"
},
  "geometry": {"coordinates":[125.47828,43.63666],"type":"Point"}
}