{
  "type": "Feature",
  "properties": {
    "gn:admin1_code":"19",
    "gn:asciiname":"Jiudaolingmanzu",
    "gn:cc2":"CN",
    "gn:country_code":"CN",
    "gn:dem":91,
    "gn:feature_class":"P",
    "gn:feature_code":"PPL",
    "gn:name":"Jiudaolingmanzu",
    "gn:population":0,
    "gn:timezone":"Asia/Shanghai",
    "iso:country":"CN",
    "name:und_x_variant":[
        "Jiudaoling",
        "Jiudaolingmanzu"
    ],
    "wof:name":"Jiudaolingmanzu",
    "wof:placetype":"locality"
},
  "geometry": {"coordinates":[121.31332999999999,41.58833],"type":"Point"}
}