{
  "type": "Feature",
  "properties": {
    "gn:admin1_code":"11",
    "gn:asciiname":"Lengshuixi",
    "gn:country_code":"CN",
    "gn:dem":226,
    "gn:feature_class":"P",
    "gn:feature_code":"PPL",
    "gn:name":"Lengshuixi",
    "gn:population":0,
    "gn:timezone":"Asia/Shanghai",
    "iso:country":"CN",
    "name:und_x_variant":[
        "\u51b7\u6c34\u6eaa",
        "Lengshuixi"
    ],
    "wof:name":"Lengshuixi",
    "wof:placetype":"locality"
},
  "geometry": {"coordinates":[110.73803999999998,29.5899],"type":"Point"}
}