{
  "type": "Feature",
  "properties": {
    "gn:admin1_code":"19.0",
    "gn:asciiname":"Danjiadiancun",
    "gn:country_code":"CN",
    "gn:dem":265,
    "gn:feature_class":"P",
    "gn:feature_code":"PPL",
    "gn:name":"Danjiadiancun",
    "gn:population":0,
    "gn:timezone":"Asia/Shanghai",
    "iso:country":"CN",
    "name:zho_x_preferred":[
        "\u5355\u5bb6\u5e97\u6751"
    ],
    "wof:name":"Danjiadiancun",
    "wof:placetype":"locality"
},
  "geometry": {"coordinates":[120.37671,41.30583],"type":"Point"}
}