{
  "type": "Feature",
  "properties": {
    "gn:admin1_code":"1.0",
    "gn:asciiname":"Wujicun",
    "gn:country_code":"CN",
    "gn:dem":27,
    "gn:feature_class":"P",
    "gn:feature_code":"PPL",
    "gn:name":"Wujicun",
    "gn:population":0,
    "gn:timezone":"Asia/Shanghai",
    "iso:country":"CN",
    "name:und_x_variant":[
        "Wuji"
    ],
    "name:zho_x_preferred":[
        "\u4e4c\u96c6\u6751"
    ],
    "wof:name":"Wujicun",
    "wof:placetype":"locality"
},
  "geometry": {"coordinates":[116.74628,33.33392],"type":"Point"}
}