{
  "type": "Feature",
  "properties": {
    "gn:admin1_code":"26.0",
    "gn:asciiname":"Wafanggou",
    "gn:country_code":"CN",
    "gn:dem":975,
    "gn:feature_class":"P",
    "gn:feature_code":"PPL",
    "gn:name":"Wafanggou",
    "gn:population":0,
    "gn:timezone":"Asia/Shanghai",
    "iso:country":"CN",
    "name:und_x_variant":[
        "\u74e6\u623f\u6c9f"
    ],
    "wof:name":"Wafanggou",
    "wof:placetype":"locality"
},
  "geometry": {"coordinates":[106.72808999999999,33.2829],"type":"Point"}
}