{
  "type": "Feature",
  "properties": {
    "gn:admin1_code":"11.0",
    "gn:asciiname":"Yaxi",
    "gn:country_code":"CN",
    "gn:dem":431,
    "gn:feature_class":"P",
    "gn:feature_code":"PPL",
    "gn:name":"Yaxi",
    "gn:population":0,
    "gn:timezone":"Asia/Shanghai",
    "iso:country":"CN",
    "name:fas_x_preferred":[
        "\u06cc\u0627\u0634\u06cc"
    ],
    "name:urd_x_preferred":[
        "\u06cc\u0627\u06a9\u0634\u06cc"
    ],
    "name:zho_x_preferred":[
        "\u9e2d\u6eaa"
    ],
    "name:zho_x_variant":[
        "\u5d16\u897f\u9547"
    ],
    "wof:name":"Yaxi",
    "wof:placetype":"locality"
},
  "geometry": {"coordinates":[110.249,28.43944],"type":"Point"}
}