{
  "type": "Feature",
  "properties": {
    "gn:admin1_code":"32.0",
    "gn:asciiname":"Wulingou",
    "gn:country_code":"CN",
    "gn:dem":365,
    "gn:feature_class":"P",
    "gn:feature_code":"PPL",
    "gn:name":"Wulingou",
    "gn:population":0,
    "gn:timezone":"Asia/Shanghai",
    "iso:country":"CN",
    "name:zho_x_preferred":[
        "\u5434\u6797\u6c9f"
    ],
    "wof:name":"Wulingou",
    "wof:placetype":"locality"
},
  "geometry": {"coordinates":[104.943,29.9203],"type":"Point"}
}