{
  "type": "Feature",
  "properties": {
    "gn:admin1_code":"30.0",
    "gn:asciiname":"Shatian",
    "gn:country_code":"CN",
    "gn:dem":341,
    "gn:feature_class":"P",
    "gn:feature_code":"PPL",
    "gn:name":"Shatian",
    "gn:population":0,
    "gn:timezone":"Asia/Shanghai",
    "iso:country":"CN",
    "name:zho_x_preferred":[
        "Shatian"
    ],
    "name:zho_x_variant":[
        "\u6c99\u7530"
    ],
    "wof:name":"Shatian",
    "wof:placetype":"locality"
},
  "geometry": {"coordinates":[112.505,24.45083],"type":"Point"}
}