{
  "type": "Feature",
  "properties": {
    "gn:admin1_code":"5",
    "gn:asciiname":"Xiaobeigou",
    "gn:country_code":"CN",
    "gn:dem":296,
    "gn:feature_class":"P",
    "gn:feature_code":"PPL",
    "gn:name":"Xiaobeigou",
    "gn:population":0,
    "gn:timezone":"Asia/Shanghai",
    "iso:country":"CN",
    "name:zho_x_preferred":[
        "\u5c0f\u5317\u6c9f"
    ],
    "wof:name":"Xiaobeigou",
    "wof:placetype":"locality"
},
  "geometry": {"coordinates":[127.34738,43.67081],"type":"Point"}
}