{
  "type": "Feature",
  "properties": {
    "gn:admin1_code":"9.0",
    "gn:asciiname":"Houtian",
    "gn:country_code":"CN",
    "gn:dem":61,
    "gn:feature_class":"P",
    "gn:feature_code":"PPL",
    "gn:name":"Houtian",
    "gn:population":0,
    "gn:timezone":"Asia/Shanghai",
    "iso:country":"CN",
    "name:zho_x_preferred":[
        "\u5019\u5929"
    ],
    "wof:name":"Houtian",
    "wof:placetype":"locality"
},
  "geometry": {"coordinates":[114.58038999999999,34.23879],"type":"Point"}
}