{
  "type": "Feature",
  "properties": {
    "gn:admin1_code":"10.0",
    "gn:asciiname":"Beipucheng",
    "gn:country_code":"CN",
    "gn:dem":66,
    "gn:feature_class":"P",
    "gn:feature_code":"PPL",
    "gn:name":"Beipucheng",
    "gn:population":0,
    "gn:timezone":"Asia/Shanghai",
    "iso:country":"CN",
    "name:und_x_variant":[
        "\u5317\u84b2\u57ce"
    ],
    "wof:name":"Beipucheng",
    "wof:placetype":"locality"
},
  "geometry": {"coordinates":[114.73495,38.19645],"type":"Point"}
}