{
  "type": "Feature",
  "properties": {
    "gn:admin1_code":"29.0",
    "gn:asciiname":"Xinjiezi",
    "gn:country_code":"CN",
    "gn:dem":1796,
    "gn:feature_class":"P",
    "gn:feature_code":"PPL",
    "gn:name":"Xinjiezi",
    "gn:population":0,
    "gn:timezone":"Asia/Shanghai",
    "iso:country":"CN",
    "name:zho_x_preferred":[
        "\u65b0\u8857\u5b50"
    ],
    "wof:name":"Xinjiezi",
    "wof:placetype":"locality"
},
  "geometry": {"coordinates":[103.928,24.2565],"type":"Point"}
}