{
  "type": "Feature",
  "properties": {
    "gn:admin1_code":"12.0",
    "gn:asciiname":"Yantangping",
    "gn:country_code":"CN",
    "gn:dem":703,
    "gn:feature_class":"P",
    "gn:feature_code":"PPL",
    "gn:name":"Yantangping",
    "gn:population":0,
    "gn:timezone":"Asia/Shanghai",
    "iso:country":"CN",
    "name:zho_x_preferred":[
        "\u5830\u5858\u576a"
    ],
    "wof:name":"Yantangping",
    "wof:placetype":"locality"
},
  "geometry": {"coordinates":[109.55029999999999,30.49793],"type":"Point"}
}