{
  "type": "Feature",
  "properties": {
    "gn:admin1_code":"3.0",
    "gn:asciiname":"Fuxi",
    "gn:country_code":"CN",
    "gn:dem":114,
    "gn:feature_class":"P",
    "gn:feature_code":"PPL",
    "gn:name":"Fuxi",
    "gn:population":0,
    "gn:timezone":"Asia/Shanghai",
    "iso:country":"CN",
    "name:und_x_variant":[
        "\u6d6e\u6eaa"
    ],
    "wof:name":"Fuxi",
    "wof:placetype":"locality"
},
  "geometry": {"coordinates":[117.74554999999999,29.4225],"type":"Point"}
}