{
  "type": "Feature",
  "properties": {
    "gn:admin1_code":"04",
    "gn:asciiname":"Jiangying",
    "gn:cc2":"CN",
    "gn:country_code":"CN",
    "gn:dem":-1,
    "gn:feature_class":"P",
    "gn:feature_code":"PPL",
    "gn:name":"Jiangying",
    "gn:population":0,
    "gn:timezone":"Asia/Shanghai",
    "iso:country":"CN",
    "name:und_x_variant":[
        "Chiang-ying",
        "Tsiangyin",
        "Chiang-yen",
        "Jiangying"
    ],
    "wof:name":"Jiangying",
    "wof:placetype":"locality"
},
  "geometry": {"coordinates":[119.65000000000001,33.43333],"type":"Point"}
}