{
  "type": "Feature",
  "properties": {
    "gn:admin1_code":"12.0",
    "gn:asciiname":"Dahongyu",
    "gn:country_code":"CN",
    "gn:dem":339,
    "gn:feature_class":"P",
    "gn:feature_code":"PPL",
    "gn:name":"Dahongyu",
    "gn:population":0,
    "gn:timezone":"Asia/Shanghai",
    "iso:country":"CN",
    "name:zho_x_preferred":[
        "\u5927\u6d2a\u5cea"
    ],
    "wof:name":"Dahongyu",
    "wof:placetype":"locality"
},
  "geometry": {"coordinates":[111.28934,32.05671],"type":"Point"}
}