{
  "type": "Feature",
  "properties": {
    "gn:admin1_code":"5.0",
    "gn:asciiname":"Zhuxiancun",
    "gn:country_code":"CN",
    "gn:dem":163,
    "gn:feature_class":"P",
    "gn:feature_code":"PPL",
    "gn:name":"Zhuxiancun",
    "gn:population":0,
    "gn:timezone":"Asia/Shanghai",
    "iso:country":"CN",
    "name:zho_x_preferred":[
        "\u6731\u4ed9\u6751"
    ],
    "wof:name":"Zhuxiancun",
    "wof:placetype":"locality"
},
  "geometry": {"coordinates":[125.93311,40.98212],"type":"Point"}
}