{
  "type": "Feature",
  "properties": {
    "gn:admin1_code":"26.0",
    "gn:asciiname":"Lucaowan",
    "gn:country_code":"CN",
    "gn:dem":1224,
    "gn:feature_class":"P",
    "gn:feature_code":"PPL",
    "gn:name":"Lucaowan",
    "gn:population":0,
    "gn:timezone":"Asia/Shanghai",
    "iso:country":"CN",
    "name:zho_x_preferred":[
        "\u82a6\u8349\u6e7e"
    ],
    "wof:name":"Lucaowan",
    "wof:placetype":"locality"
},
  "geometry": {"coordinates":[110.63634,38.9874],"type":"Point"}
}