{
  "type": "Feature",
  "properties": {
    "gn:admin1_code":"25",
    "gn:asciiname":"Qianzhangjiacun",
    "gn:country_code":"CN",
    "gn:dem":66,
    "gn:feature_class":"P",
    "gn:feature_code":"PPL",
    "gn:name":"Qianzhangjiacun",
    "gn:population":0,
    "gn:timezone":"Asia/Shanghai",
    "iso:country":"CN",
    "name:zho_x_preferred":[
        "\u524d\u5f20\u5bb6\u6751"
    ],
    "wof:name":"Qianzhangjiacun",
    "wof:placetype":"locality"
},
  "geometry": {"coordinates":[116.949,35.6467],"type":"Point"}
}