{
  "type": "Feature",
  "properties": {
    "gn:admin1_code":"32.0",
    "gn:asciiname":"Ranfang",
    "gn:country_code":"CN",
    "gn:dem":378,
    "gn:feature_class":"P",
    "gn:feature_code":"PPL",
    "gn:name":"Ranfang",
    "gn:population":0,
    "gn:timezone":"Asia/Shanghai",
    "iso:country":"CN",
    "name:zho_x_preferred":[
        "\u67d3\u623f"
    ],
    "wof:name":"Ranfang",
    "wof:placetype":"locality"
},
  "geometry": {"coordinates":[104.32899999999999,29.9939],"type":"Point"}
}