{
  "type": "Feature",
  "properties": {
    "gn:admin1_code":"19.0",
    "gn:asciiname":"Dazhucun",
    "gn:country_code":"CN",
    "gn:dem":39,
    "gn:feature_class":"P",
    "gn:feature_code":"PPL",
    "gn:name":"Dazhucun",
    "gn:population":0,
    "gn:timezone":"Asia/Shanghai",
    "iso:country":"CN",
    "name:und_x_variant":[
        "Dazhusanbao",
        "Dazhusanbu"
    ],
    "name:zho_x_preferred":[
        "\u5927\u795d\u6751"
    ],
    "name:zho_x_variant":[
        "\u5927\u795d\u4e09\u5821"
    ],
    "wof:name":"Dazhucun",
    "wof:placetype":"locality"
},
  "geometry": {"coordinates":[123.17998,41.67402],"type":"Point"}
}