{
  "type": "Feature",
  "properties": {
    "gn:admin1_code":"15.0",
    "gn:asciiname":"Majiaping",
    "gn:country_code":"CN",
    "gn:dem":1886,
    "gn:feature_class":"P",
    "gn:feature_code":"PPL",
    "gn:name":"Majiaping",
    "gn:population":0,
    "gn:timezone":"Asia/Shanghai",
    "iso:country":"CN",
    "name:zho_x_preferred":[
        "\u9a6c\u5bb6\u576a"
    ],
    "wof:name":"Majiaping",
    "wof:placetype":"locality"
},
  "geometry": {"coordinates":[104.83199999999999,35.843],"type":"Point"}
}