{
  "type": "Feature",
  "properties": {
    "gn:admin1_code":"3.0",
    "gn:asciiname":"Yuanqian",
    "gn:country_code":"CN",
    "gn:dem":89,
    "gn:feature_class":"P",
    "gn:feature_code":"PPL",
    "gn:name":"Yuanqian",
    "gn:population":0,
    "gn:timezone":"Asia/Shanghai",
    "iso:country":"CN",
    "name:und_x_variant":[
        "\u9662\u524d"
    ],
    "wof:name":"Yuanqian",
    "wof:placetype":"locality"
},
  "geometry": {"coordinates":[114.88196000000001,27.47028],"type":"Point"}
}