{
  "type": "Feature",
  "properties": {
    "gn:admin1_code":"29.0",
    "gn:asciiname":"Wangjiafen",
    "gn:country_code":"CN",
    "gn:dem":1921,
    "gn:feature_class":"P",
    "gn:feature_code":"PPL",
    "gn:name":"Wangjiafen",
    "gn:population":0,
    "gn:timezone":"Asia/Shanghai",
    "iso:country":"CN",
    "name:zho_x_preferred":[
        "\u738b\u5bb6\u575f"
    ],
    "wof:name":"Wangjiafen",
    "wof:placetype":"locality"
},
  "geometry": {"coordinates":[104.268,26.0079],"type":"Point"}
}