{
  "type": "Feature",
  "properties": {
    "gn:admin1_code":"16.0",
    "gn:asciiname":"Mendong",
    "gn:country_code":"CN",
    "gn:dem":810,
    "gn:feature_class":"P",
    "gn:feature_code":"PPL",
    "gn:name":"Mendong",
    "gn:population":0,
    "gn:timezone":"Asia/Shanghai",
    "iso:country":"CN",
    "name:zho_x_preferred":[
        "\u95e8\u6d1e"
    ],
    "wof:name":"Mendong",
    "wof:placetype":"locality"
},
  "geometry": {"coordinates":[107.70399999999999,24.4119],"type":"Point"}
}