{
  "type": "Feature",
  "properties": {
    "gn:admin1_code":"16.0",
    "gn:asciiname":"Fenghuang",
    "gn:country_code":"CN",
    "gn:dem":103,
    "gn:feature_class":"P",
    "gn:feature_code":"PPL",
    "gn:name":"Fenghuang",
    "gn:population":0,
    "gn:timezone":"Asia/Shanghai",
    "iso:country":"CN",
    "name:zho_x_preferred":[
        "\u51e4\u51f0"
    ],
    "wof:name":"Fenghuang",
    "wof:placetype":"locality"
},
  "geometry": {"coordinates":[108.76300000000001,23.8317],"type":"Point"}
}