{
  "type": "Feature",
  "properties": {
    "gn:admin1_code":"1.0",
    "gn:asciiname":"Tangshancun",
    "gn:country_code":"CN",
    "gn:dem":30,
    "gn:feature_class":"P",
    "gn:feature_code":"PPL",
    "gn:name":"Tangshancun",
    "gn:population":0,
    "gn:timezone":"Asia/Shanghai",
    "iso:country":"CN",
    "name:zho_x_preferred":[
        "\u6c64\u5c71\u6751"
    ],
    "wof:name":"Tangshancun",
    "wof:placetype":"locality"
},
  "geometry": {"coordinates":[117.94383999999999,31.65477000000001],"type":"Point"}
}