{
  "type": "Feature",
  "properties": {
    "gn:admin1_code":"12.0",
    "gn:asciiname":"Xiangjia Citang",
    "gn:country_code":"CN",
    "gn:dem":17,
    "gn:feature_class":"P",
    "gn:feature_code":"PPL",
    "gn:name":"Xiangjia Citang",
    "gn:population":0,
    "gn:timezone":"Asia/Shanghai",
    "iso:country":"CN",
    "name:zho_x_preferred":[
        "\u9879\u5bb6\u7960\u5802"
    ],
    "wof:name":"Xiangjia Citang",
    "wof:placetype":"locality"
},
  "geometry": {"coordinates":[115.87009999999999,29.8522],"type":"Point"}
}