{
  "type": "Feature",
  "properties": {
    "gn:admin1_code":"16.0",
    "gn:asciiname":"Liuli",
    "gn:country_code":"CN",
    "gn:dem":265,
    "gn:feature_class":"P",
    "gn:feature_code":"PPL",
    "gn:name":"Liuli",
    "gn:population":0,
    "gn:timezone":"Asia/Shanghai",
    "iso:country":"CN",
    "name:ceb_x_preferred":[
        "Liuli"
    ],
    "name:deu_x_preferred":[
        "Liuli"
    ],
    "name:swa_x_preferred":[
        "Liuli"
    ],
    "name:zho_x_preferred":[
        "\u516d\u5398"
    ],
    "wof:name":"Liuli",
    "wof:placetype":"locality"
},
  "geometry": {"coordinates":[108.05500000000001,22.063],"type":"Point"}
}