{
  "type": "Feature",
  "properties": {
    "gn:admin1_code":"9.0",
    "gn:asciiname":"Laoliaojia",
    "gn:country_code":"CN",
    "gn:dem":289,
    "gn:feature_class":"P",
    "gn:feature_code":"PPL",
    "gn:name":"Laoliaojia",
    "gn:population":0,
    "gn:timezone":"Asia/Shanghai",
    "iso:country":"CN",
    "name:zho_x_preferred":[
        "\u8001\u5ed6\u5bb6"
    ],
    "wof:name":"Laoliaojia",
    "wof:placetype":"locality"
},
  "geometry": {"coordinates":[113.41454,32.64278],"type":"Point"}
}