{
  "type": "Feature",
  "properties": {
    "gn:admin1_code":"29.0",
    "gn:asciiname":"Wenbang",
    "gn:country_code":"CN",
    "gn:dem":1565,
    "gn:feature_class":"P",
    "gn:feature_code":"PPL",
    "gn:name":"Wenbang",
    "gn:population":0,
    "gn:timezone":"Asia/Shanghai",
    "iso:country":"CN",
    "name:zho_x_preferred":[
        "\u6587\u699c"
    ],
    "wof:name":"Wenbang",
    "wof:placetype":"locality"
},
  "geometry": {"coordinates":[100.76600000000001,23.9078],"type":"Point"}
}