{
  "type": "Feature",
  "properties": {
    "gn:admin1_code":"4.0",
    "gn:asciiname":"Tuotou",
    "gn:country_code":"CN",
    "gn:dem":17,
    "gn:feature_class":"P",
    "gn:feature_code":"PPL",
    "gn:name":"Tuotou",
    "gn:population":0,
    "gn:timezone":"Asia/Shanghai",
    "iso:country":"CN",
    "name:zho_x_preferred":[
        "\u9a7c\u5934"
    ],
    "wof:name":"Tuotou",
    "wof:placetype":"locality"
},
  "geometry": {"coordinates":[119.10343,31.54585],"type":"Point"}
}