{
  "type": "Feature",
  "properties": {
    "gn:admin1_code":"32.0",
    "gn:asciiname":"Santaichang",
    "gn:country_code":"CN",
    "gn:dem":793,
    "gn:feature_class":"P",
    "gn:feature_code":"PPL",
    "gn:name":"Santaichang",
    "gn:population":0,
    "gn:timezone":"Asia/Shanghai",
    "iso:country":"CN",
    "name:zho_x_preferred":[
        "\u4e09\u53f0\u573a"
    ],
    "wof:name":"Santaichang",
    "wof:placetype":"locality"
},
  "geometry": {"coordinates":[107.352,31.3612],"type":"Point"}
}