{
  "type": "Feature",
  "properties": {
    "gn:admin1_code":"30.0",
    "gn:asciiname":"Wawei",
    "gn:country_code":"CN",
    "gn:dem":28,
    "gn:feature_class":"P",
    "gn:feature_code":"PPL",
    "gn:name":"Wawei",
    "gn:population":0,
    "gn:timezone":"Asia/Urumqi",
    "iso:country":"CN",
    "name:zho_x_preferred":[
        "\u6316\u5c3e"
    ],
    "wof:name":"Wawei",
    "wof:placetype":"locality"
},
  "geometry": {"coordinates":[110.25886,20.28896],"type":"Point"}
}