{
  "type": "Feature",
  "properties": {
    "gn:admin1_code":"19.0",
    "gn:asciiname":"Xiaguchengzicun",
    "gn:country_code":"CN",
    "gn:dem":241,
    "gn:feature_class":"P",
    "gn:feature_code":"PPL",
    "gn:name":"Xiaguchengzicun",
    "gn:population":0,
    "gn:timezone":"Asia/Shanghai",
    "iso:country":"CN",
    "name:zho_x_preferred":[
        "\u4e0b\u53e4\u57ce\u5b50\u6751"
    ],
    "wof:name":"Xiaguchengzicun",
    "wof:placetype":"locality"
},
  "geometry": {"coordinates":[125.328,41.2802],"type":"Point"}
}