{
  "type": "Feature",
  "properties": {
    "gn:admin1_code":"4.0",
    "gn:asciiname":"Hongfeng Wuzu",
    "gn:country_code":"CN",
    "gn:dem":0,
    "gn:feature_class":"P",
    "gn:feature_code":"PPLF",
    "gn:name":"Hongfeng Wuzu",
    "gn:population":0,
    "gn:timezone":"Asia/Shanghai",
    "iso:country":"CN",
    "name:zho_x_preferred":[
        "\u5b8f\u4e30\u4e94\u7ec4"
    ],
    "wof:name":"Hongfeng Wuzu",
    "wof:placetype":"locality"
},
  "geometry": {"coordinates":[119.988,33.8316],"type":"Point"}
}