{
  "type": "Feature",
  "properties": {
    "gn:admin1_code":"19.0",
    "gn:asciiname":"Xiaojiangzhangzi",
    "gn:country_code":"CN",
    "gn:dem":568,
    "gn:feature_class":"P",
    "gn:feature_code":"PPL",
    "gn:name":"Xiaojiangzhangzi",
    "gn:population":0,
    "gn:timezone":"Asia/Shanghai",
    "iso:country":"CN",
    "name:und_x_variant":[
        "\u5c0f\u59dc\u6756\u5b50"
    ],
    "name:zho_x_preferred":[
        "\u5c0f\u59dc\u6756\u5b50"
    ],
    "wof:name":"Xiaojiangzhangzi",
    "wof:placetype":"locality"
},
  "geometry": {"coordinates":[119.464,40.6168],"type":"Point"}
}