{
  "type": "Feature",
  "properties": {
    "gn:admin1_code":"5.0",
    "gn:asciiname":"Wangjia Gangzi",
    "gn:country_code":"CN",
    "gn:dem":134,
    "gn:feature_class":"P",
    "gn:feature_code":"PPL",
    "gn:name":"Wangjia Gangzi",
    "gn:population":0,
    "gn:timezone":"Asia/Shanghai",
    "iso:country":"CN",
    "name:zho_x_preferred":[
        "\u738b\u5bb6\u5c97\u5b50"
    ],
    "wof:name":"Wangjia Gangzi",
    "wof:placetype":"locality"
},
  "geometry": {"coordinates":[123.90501,46.21279000000001],"type":"Point"}
}