{
  "type": "Feature",
  "properties": {
    "gn:admin1_code":"7",
    "gn:asciiname":"Xiacuo",
    "gn:country_code":"CN",
    "gn:dem":553,
    "gn:feature_class":"P",
    "gn:feature_code":"PPL",
    "gn:name":"Xiacuo",
    "gn:population":0,
    "gn:timezone":"Asia/Shanghai",
    "iso:country":"CN",
    "name:zho_x_preferred":[
        "\u4e0b\u539d"
    ],
    "wof:name":"Xiacuo",
    "wof:placetype":"locality"
},
  "geometry": {"coordinates":[117.40743999999999,24.87034],"type":"Point"}
}