{
  "type": "Feature",
  "properties": {
    "gn:admin1_code":"7.0",
    "gn:asciiname":"Kanzaijiao",
    "gn:country_code":"CN",
    "gn:dem":55,
    "gn:feature_class":"P",
    "gn:feature_code":"PPL",
    "gn:name":"Kanzaijiao",
    "gn:population":0,
    "gn:timezone":"Asia/Shanghai",
    "iso:country":"CN",
    "name:zho_x_preferred":[
        "\u574e\u4ed4\u811a"
    ],
    "wof:name":"Kanzaijiao",
    "wof:placetype":"locality"
},
  "geometry": {"coordinates":[117.56853999999998,24.27946],"type":"Point"}
}