{
  "type": "Feature",
  "properties": {
    "gn:admin1_code":"19.0",
    "gn:asciiname":"Hongtaizicun",
    "gn:country_code":"CN",
    "gn:dem":101,
    "gn:feature_class":"P",
    "gn:feature_code":"PPL",
    "gn:name":"Hongtaizicun",
    "gn:population":0,
    "gn:timezone":"Asia/Shanghai",
    "iso:country":"CN",
    "name:zho_x_preferred":[
        "\u7ea2\u53f0\u5b50\u6751"
    ],
    "wof:name":"Hongtaizicun",
    "wof:placetype":"locality"
},
  "geometry": {"coordinates":[121.331,41.6229],"type":"Point"}
}