{
  "type": "Feature",
  "properties": {
    "gn:admin1_code":"09",
    "gn:asciiname":"Erlangmiao",
    "gn:cc2":"CN",
    "gn:country_code":"CN",
    "gn:dem":362,
    "gn:feature_class":"P",
    "gn:feature_code":"PPL",
    "gn:name":"Erlangmiao",
    "gn:population":0,
    "gn:timezone":"Asia/Shanghai",
    "iso:country":"CN",
    "name:und_x_variant":[
        "Erh-lang-miao",
        "Erlangmiao"
    ],
    "wof:name":"Erlangmiao",
    "wof:placetype":"locality"
},
  "geometry": {"coordinates":[112.37833000000001,33.74722],"type":"Point"}
}