{
  "type": "Feature",
  "properties": {
    "gn:admin1_code":"18.0",
    "gn:asciiname":"Longjiao",
    "gn:country_code":"CN",
    "gn:dem":1018,
    "gn:feature_class":"P",
    "gn:feature_code":"PPL",
    "gn:name":"Longjiao",
    "gn:population":0,
    "gn:timezone":"Asia/Shanghai",
    "iso:country":"CN",
    "name:zho_x_preferred":[
        "\u9f99\u89d2"
    ],
    "wof:name":"Longjiao",
    "wof:placetype":"locality"
},
  "geometry": {"coordinates":[107.72199999999999,26.5716],"type":"Point"}
}