{
  "type": "Feature",
  "properties": {
    "gn:admin1_code":"15.0",
    "gn:asciiname":"Yanglaowan",
    "gn:country_code":"CN",
    "gn:dem":1464,
    "gn:feature_class":"P",
    "gn:feature_code":"PPL",
    "gn:name":"Yanglaowan",
    "gn:population":0,
    "gn:timezone":"Asia/Shanghai",
    "iso:country":"CN",
    "name:und_x_variant":[
        "\u6768\u8001\u6e7e"
    ],
    "wof:name":"Yanglaowan",
    "wof:placetype":"locality"
},
  "geometry": {"coordinates":[107.84589,36.7141],"type":"Point"}
}