{
  "type": "Feature",
  "properties": {
    "gn:admin1_code":"25",
    "gn:asciiname":"Lixinjibei",
    "gn:country_code":"CN",
    "gn:dem":61,
    "gn:feature_class":"P",
    "gn:feature_code":"PPL",
    "gn:name":"Lixinjibei",
    "gn:population":0,
    "gn:timezone":"Asia/Shanghai",
    "iso:country":"CN",
    "name:zho_x_preferred":[
        "\u674e\u65b0\u96c6\u5317"
    ],
    "wof:name":"Lixinjibei",
    "wof:placetype":"locality"
},
  "geometry": {"coordinates":[115.917,34.6119],"type":"Point"}
}