{
  "type": "Feature",
  "properties": {
    "gn:admin1_code":"8.0",
    "gn:asciiname":"Genan",
    "gn:country_code":"CN",
    "gn:dem":63,
    "gn:feature_class":"P",
    "gn:feature_code":"PPL",
    "gn:name":"Genan",
    "gn:population":0,
    "gn:timezone":"Asia/Shanghai",
    "iso:country":"CN",
    "name:fas_x_preferred":[
        "\u06af\u0646\u0627\u0646"
    ],
    "name:msa_x_preferred":[
        "Genan"
    ],
    "name:zho_x_preferred":[
        "\u845b\u5357"
    ],
    "wof:name":"Genan",
    "wof:placetype":"locality"
},
  "geometry": {"coordinates":[133.94044,47.20816],"type":"Point"}
}