{
  "type": "Feature",
  "properties": {
    "gn:country":"CN",
    "gn:fcode":"PPL",
    "gn:population":97026,
    "iso:country":"CN",
    "name:ceb_x_preferred":[
        "Fangshan"
    ],
    "name:ces_x_preferred":[
        "Fang-\u0161an"
    ],
    "name:deu_x_preferred":[
        "Fangshan"
    ],
    "name:fra_x_preferred":[
        "Fangshan"
    ],
    "name:mlg_x_preferred":[
        "Fangshan"
    ],
    "name:nor_x_preferred":[
        "Fangshan"
    ],
    "name:rus_x_preferred":[
        "\u0424\u0430\u043d\u0448\u0430\u043d\u044c"
    ],
    "name:swe_x_preferred":[
        "Fangshan"
    ],
    "name:und_x_variant":[
        "Ta-fang-shan"
    ],
    "name:zho_x_preferred":[
        "\u623f\u5c71"
    ],
    "qs:name":"Fangshan",
    "qs:photos_9r":0,
    "qs:photos_sr":0,
    "qs:pop_sr":"8",
    "wd:wordcount":76,
    "wof:name":"Fangshan",
    "wof:placetype":"locality",
    "wof:population":97026
},
  "geometry": {"coordinates":[115.99250000000001,39.69833],"type":"Point"}
}