{
  "type": "Feature",
  "properties": {
    "gn:country":"CN",
    "gn:fcode":"PPL",
    "gn:pop":97026,
    "iso:country":"CN",
    "name:unk_x_variant":[
        "Ta-fang-shan"
    ],
    "name:zho_x_preferred":[
        "\u623f\u5c71"
    ],
    "qs:name":"Fangshan",
    "qs:photos_9r":0,
    "qs:photos_sr":0,
    "qs:pop_sr":"8",
    "wd:wordcount":76,
    "wof:name":"Fangshan",
    "wof:placetype":"locality",
    "wof:population":97026
},
  "geometry": {"coordinates":[115.99250000000001,39.69833],"type":"Point"}
}