{
  "type": "Feature",
  "properties": {
    "gn:admin1_code":"4.0",
    "gn:asciiname":"Yurencun",
    "gn:country_code":"CN",
    "gn:dem":1,
    "gn:feature_class":"P",
    "gn:feature_code":"PPL",
    "gn:name":"Yurencun",
    "gn:population":0,
    "gn:timezone":"Asia/Shanghai",
    "iso:country":"CN",
    "name:zho_x_preferred":[
        "\u4e8e\u4efb\u6751"
    ],
    "wof:name":"Yurencun",
    "wof:placetype":"locality"
},
  "geometry": {"coordinates":[119.85413,33.21612],"type":"Point"}
}