{
  "type": "Feature",
  "properties": {
    "gn:admin1_code":"9.0",
    "gn:asciiname":"Zhumaozhao",
    "gn:country_code":"CN",
    "gn:dem":73,
    "gn:feature_class":"P",
    "gn:feature_code":"PPL",
    "gn:name":"Zhumaozhao",
    "gn:population":0,
    "gn:timezone":"Asia/Shanghai",
    "iso:country":"CN",
    "name:zho_x_preferred":[
        "\u6731\u6bdb\u8d75"
    ],
    "wof:name":"Zhumaozhao",
    "wof:placetype":"locality"
},
  "geometry": {"coordinates":[114.00881,34.20457],"type":"Point"}
}