{
  "type": "Feature",
  "properties": {
    "gn:admin1_code":"9.0",
    "gn:asciiname":"Daping",
    "gn:country_code":"CN",
    "gn:dem":423,
    "gn:feature_class":"P",
    "gn:feature_code":"PPL",
    "gn:name":"Daping",
    "gn:population":0,
    "gn:timezone":"Asia/Shanghai",
    "iso:country":"CN",
    "name:ceb_x_preferred":[
        "Daping"
    ],
    "name:deu_x_preferred":[
        "Daping"
    ],
    "name:swe_x_preferred":[
        "Daping"
    ],
    "name:und_x_variant":[
        "\u5927\u576a",
        "Daping"
    ],
    "wof:name":"Daping",
    "wof:placetype":"locality"
},
  "geometry": {"coordinates":[112.23706,33.19518],"type":"Point"}
}