{
  "type": "Feature",
  "properties": {
    "gn:admin1_code":"32.0",
    "gn:asciiname":"Laohuofang",
    "gn:country_code":"CN",
    "gn:dem":1887,
    "gn:feature_class":"P",
    "gn:feature_code":"PPL",
    "gn:name":"Laohuofang",
    "gn:population":0,
    "gn:timezone":"Asia/Shanghai",
    "iso:country":"CN",
    "name:zho_x_preferred":[
        "\u8001\u4f19\u623f"
    ],
    "wof:name":"Laohuofang",
    "wof:placetype":"locality"
},
  "geometry": {"coordinates":[102.443,27.0237],"type":"Point"}
}