{
  "type": "Feature",
  "properties": {
    "gn:admin1_code":"2.0",
    "gn:asciiname":"Yan'ao",
    "gn:country_code":"CN",
    "gn:dem":235,
    "gn:feature_class":"P",
    "gn:feature_code":"PPL",
    "gn:name":"Yan\u2019ao",
    "gn:population":0,
    "gn:timezone":"Asia/Shanghai",
    "iso:country":"CN",
    "name:und_x_variant":[
        "Yan\u2019ao"
    ],
    "name:zho_x_preferred":[
        "\u6cbf\u5c99"
    ],
    "wof:name":"Yan'ao",
    "wof:placetype":"locality"
},
  "geometry": {"coordinates":[120.41517,27.22148],"type":"Point"}
}