{
  "type": "Feature",
  "properties": {
    "gn:admin1_code":"1.0",
    "gn:asciiname":"Shuishangduicun",
    "gn:country_code":"CN",
    "gn:dem":50,
    "gn:feature_class":"P",
    "gn:feature_code":"PPLF",
    "gn:name":"Shuishangduicun",
    "gn:population":0,
    "gn:timezone":"Asia/Shanghai",
    "iso:country":"CN",
    "name:und_x_variant":[
        "Shuishangdui",
        "Shuishangduicun"
    ],
    "name:zho_x_preferred":[
        "\u6c34\u4e0a\u961f"
    ],
    "name:zho_x_variant":[
        "\u6c34\u4e0a\u961f\u6751"
    ],
    "wof:name":"Shuishangduicun",
    "wof:placetype":"locality"
},
  "geometry": {"coordinates":[118.9439,31.20499],"type":"Point"}
}