{
  "type": "Feature",
  "properties": {
    "gn:admin1_code":"11",
    "gn:asciiname":"Yuankou",
    "gn:country_code":"CN",
    "gn:dem":640,
    "gn:feature_class":"P",
    "gn:feature_code":"PPLA4",
    "gn:name":"Yuankou",
    "gn:population":0,
    "gn:timezone":"Asia/Shanghai",
    "iso:country":"CN",
    "name:und_x_variant":[
        "Yuankou Yaozuxiang",
        "\u6e90\u53e3\u7476\u65cf\u4e61",
        "Yuankou"
    ],
    "name:zho_x_preferred":[
        "\u6e90\u53e3"
    ],
    "wof:name":"Yuankou",
    "wof:placetype":"locality"
},
  "geometry": {"coordinates":[111.05528,25.00083],"type":"Point"}
}