{
  "type": "Feature",
  "properties": {
    "gn:admin1_code":"10",
    "gn:asciiname":"Dahuangliang",
    "gn:country_code":"CN",
    "gn:dem":1126,
    "gn:feature_class":"P",
    "gn:feature_code":"PPL",
    "gn:name":"Dahuangliang",
    "gn:population":0,
    "gn:timezone":"Asia/Shanghai",
    "iso:country":"CN",
    "name:zho_x_preferred":[
        "\u5927\u9ec4\u6881"
    ],
    "wof:name":"Dahuangliang",
    "wof:placetype":"locality"
},
  "geometry": {"coordinates":[116.90004999999999,41.4911],"type":"Point"}
}