{
  "type": "Feature",
  "properties": {
    "gn:admin1_code":"32.0",
    "gn:asciiname":"Dengjunba",
    "gn:country_code":"CN",
    "gn:dem":3225,
    "gn:feature_class":"P",
    "gn:feature_code":"PPL",
    "gn:name":"Dengjunba",
    "gn:population":0,
    "gn:timezone":"Asia/Shanghai",
    "iso:country":"CN",
    "name:zho_x_preferred":[
        "\u767b\u5747\u575d"
    ],
    "wof:name":"Dengjunba",
    "wof:placetype":"locality"
},
  "geometry": {"coordinates":[103.224,33.5796],"type":"Point"}
}