{
  "type": "Feature",
  "properties": {
    "gn:admin1_code":"31.0",
    "gn:asciiname":"Dui'e",
    "gn:country_code":"CN",
    "gn:dem":316,
    "gn:feature_class":"P",
    "gn:feature_code":"PPL",
    "gn:name":"Dui\u2019e",
    "gn:population":0,
    "gn:timezone":"Asia/Shanghai",
    "iso:country":"CN",
    "name:und_x_variant":[
        "\u5bf9\u4fc4"
    ],
    "name:zho_x_preferred":[
        "Dui\u2019e"
    ],
    "name:zho_x_variant":[
        "\u5bf9\u4fc4"
    ],
    "wof:name":"Dui'e",
    "wof:placetype":"locality"
},
  "geometry": {"coordinates":[109.41198,19.25902],"type":"Point"}
}