{
  "type": "Feature",
  "properties": {
    "gn:admin1_code":"19.0",
    "gn:asciiname":"Laojuntun",
    "gn:country_code":"CN",
    "gn:dem":11,
    "gn:feature_class":"P",
    "gn:feature_code":"PPL",
    "gn:name":"Laojuntun",
    "gn:population":0,
    "gn:timezone":"Asia/Shanghai",
    "iso:country":"CN",
    "name:zho_x_preferred":[
        "\u8001\u541b\u5c6f"
    ],
    "wof:name":"Laojuntun",
    "wof:placetype":"locality"
},
  "geometry": {"coordinates":[121.56899,41.08431],"type":"Point"}
}