{
  "type": "Feature",
  "properties": {
    "gn:admin1_code":"12.0",
    "gn:asciiname":"Xianchi",
    "gn:country_code":"CN",
    "gn:dem":780,
    "gn:feature_class":"P",
    "gn:feature_code":"PPL",
    "gn:name":"Xianchi",
    "gn:population":0,
    "gn:timezone":"Asia/Shanghai",
    "iso:country":"CN",
    "name:zho_x_preferred":[
        "\u54b8\u6c60"
    ],
    "wof:name":"Xianchi",
    "wof:placetype":"locality"
},
  "geometry": {"coordinates":[110.21608000000001,31.90569],"type":"Point"}
}