{
  "type": "Feature",
  "properties": {
    "gn:admin1_code":"16",
    "gn:asciiname":"Xiebishan",
    "gn:country_code":"CN",
    "gn:dem":1029,
    "gn:feature_class":"P",
    "gn:feature_code":"PPL",
    "gn:name":"Xiebishan",
    "gn:population":0,
    "gn:timezone":"Asia/Shanghai",
    "iso:country":"CN",
    "name:zho_x_preferred":[
        "\u631f\u58c1\u5c71"
    ],
    "wof:name":"Xiebishan",
    "wof:placetype":"locality"
},
  "geometry": {"coordinates":[110.456,25.936],"type":"Point"}
}