{
  "type": "Feature",
  "properties": {
    "gn:admin1_code":"10",
    "gn:asciiname":"Cuijia Buzi",
    "gn:country_code":"CN",
    "gn:dem":291,
    "gn:feature_class":"P",
    "gn:feature_code":"PPL",
    "gn:name":"Cuijia Buzi",
    "gn:population":0,
    "gn:timezone":"Asia/Shanghai",
    "iso:country":"CN",
    "name:und_x_variant":[
        "Ts\u2019ui-chia-p\u2019u",
        "Cuijiabaozi",
        "Cuijia Buzi"
    ],
    "name:zho_x_preferred":[
        "\u5d14\u5bb6\u5821\u5b50"
    ],
    "wof:name":"Cuijia Buzi",
    "wof:placetype":"locality"
},
  "geometry": {"coordinates":[118.49639000000001,40.34444000000001],"type":"Point"}
}