{
  "type": "Feature",
  "properties": {
    "gn:admin1_code":"29.0",
    "gn:asciiname":"Bahongcun",
    "gn:country_code":"CN",
    "gn:dem":2183,
    "gn:feature_class":"P",
    "gn:feature_code":"PPL",
    "gn:name":"Bahongcun",
    "gn:population":0,
    "gn:timezone":"Asia/Shanghai",
    "iso:country":"CN",
    "name:zho_x_preferred":[
        "\u5df4\u6d2a\u6751"
    ],
    "wof:name":"Bahongcun",
    "wof:placetype":"locality"
},
  "geometry": {"coordinates":[102.613,25.8364],"type":"Point"}
}