{
  "type": "Feature",
  "properties": {
    "gn:admin1_code":"24",
    "gn:asciiname":"Lingyunkou",
    "gn:country_code":"CN",
    "gn:dem":1137,
    "gn:feature_class":"P",
    "gn:feature_code":"PPL",
    "gn:name":"Lingyunkou",
    "gn:population":0,
    "gn:timezone":"Asia/Shanghai",
    "iso:country":"CN",
    "name:und_x_variant":[
        "\u51cc\u4e91\u53e3"
    ],
    "wof:name":"Lingyunkou",
    "wof:placetype":"locality"
},
  "geometry": {"coordinates":[113.54803,39.57949],"type":"Point"}
}