{
  "type": "Feature",
  "properties": {
    "gn:admin1_code":"10.0",
    "gn:asciiname":"Nanmugou",
    "gn:country_code":"CN",
    "gn:dem":674,
    "gn:feature_class":"P",
    "gn:feature_code":"PPL",
    "gn:name":"Nanmugou",
    "gn:population":0,
    "gn:timezone":"Asia/Shanghai",
    "iso:country":"CN",
    "name:zho_x_preferred":[
        "\u6960\u6728\u6c9f"
    ],
    "wof:name":"Nanmugou",
    "wof:placetype":"locality"
},
  "geometry": {"coordinates":[117.55897,40.37152],"type":"Point"}
}