{
  "type": "Feature",
  "properties": {
    "gn:admin1_code":"16",
    "gn:asciiname":"Ma'e",
    "gn:country_code":"CN",
    "gn:dem":501,
    "gn:feature_class":"P",
    "gn:feature_code":"PPL",
    "gn:name":"Ma\u2019e",
    "gn:population":0,
    "gn:timezone":"Asia/Shanghai",
    "iso:country":"CN",
    "name:und_x_variant":[
        "Ma\u2019e"
    ],
    "name:zho_x_preferred":[
        "\u9a6c\u5384"
    ],
    "wof:name":"Ma'e",
    "wof:placetype":"locality"
},
  "geometry": {"coordinates":[110.071,25.6114],"type":"Point"}
}