{
  "type": "Feature",
  "properties": {
    "gn:admin1_code":"5.0",
    "gn:asciiname":"Wangzhongcun",
    "gn:country_code":"CN",
    "gn:dem":186,
    "gn:feature_class":"P",
    "gn:feature_code":"PPL",
    "gn:name":"Wangzhongcun",
    "gn:population":0,
    "gn:timezone":"Asia/Shanghai",
    "iso:country":"CN",
    "name:zho_x_preferred":[
        "\u738b\u4e2d\u6751"
    ],
    "wof:name":"Wangzhongcun",
    "wof:placetype":"locality"
},
  "geometry": {"coordinates":[125.53736000000001,44.45793],"type":"Point"}
}