{
  "type": "Feature",
  "properties": {
    "gn:admin1_code":"8.0",
    "gn:asciiname":"Wu'ancun",
    "gn:country_code":"CN",
    "gn:dem":125,
    "gn:feature_class":"P",
    "gn:feature_code":"PPL",
    "gn:name":"Wu\u2019ancun",
    "gn:population":0,
    "gn:timezone":"Asia/Shanghai",
    "iso:country":"CN",
    "name:und_x_variant":[
        "Wu\u2019ancun"
    ],
    "name:zho_x_preferred":[
        "\u4e94\u5b89\u6751"
    ],
    "wof:name":"Wu'ancun",
    "wof:placetype":"locality"
},
  "geometry": {"coordinates":[127.53701,45.88065],"type":"Point"}
}