{
  "type": "Feature",
  "properties": {
    "gn:admin1_code":"30",
    "gn:asciiname":"Luozhou",
    "gn:country_code":"CN",
    "gn:dem":24,
    "gn:feature_class":"P",
    "gn:feature_code":"PPLA3",
    "gn:name":"Luozhou",
    "gn:population":0,
    "gn:timezone":"Asia/Urumqi",
    "iso:country":"CN",
    "name:und_x_variant":[
        "Luozhou Jiedao",
        "\u7f57\u5dde\u8857\u9053"
    ],
    "name:zho_x_preferred":[
        "\u7f57\u5dde"
    ],
    "wof:name":"Luozhou",
    "wof:placetype":"locality"
},
  "geometry": {"coordinates":[110.27705,21.60589],"type":"Point"}
}