{
  "type": "Feature",
  "properties": {
    "gn:admin1_code":"26.0",
    "gn:asciiname":"Shangwanli",
    "gn:country_code":"CN",
    "gn:dem":1814,
    "gn:feature_class":"P",
    "gn:feature_code":"PPL",
    "gn:name":"Shangwanli",
    "gn:population":0,
    "gn:timezone":"Asia/Shanghai",
    "iso:country":"CN",
    "name:zho_x_preferred":[
        "\u4e0a\u6e7e\u91cc"
    ],
    "wof:name":"Shangwanli",
    "wof:placetype":"locality"
},
  "geometry": {"coordinates":[106.6045,34.57119],"type":"Point"}
}