{
  "type": "Feature",
  "properties": {
    "gn:admin1_code":"4.0",
    "gn:asciiname":"Cuiwafang",
    "gn:country_code":"CN",
    "gn:dem":4,
    "gn:feature_class":"P",
    "gn:feature_code":"PPL",
    "gn:name":"Cuiwafang",
    "gn:population":0,
    "gn:timezone":"Asia/Shanghai",
    "iso:country":"CN",
    "name:zho_x_preferred":[
        "Cuiwafang"
    ],
    "name:zho_x_variant":[
        "\u5d14\u74e6\u623f"
    ],
    "wof:name":"Cuiwafang",
    "wof:placetype":"locality"
},
  "geometry": {"coordinates":[119.25391999999999,34.02295],"type":"Point"}
}