{
  "type": "Feature",
  "properties": {
    "gn:admin1_code":"1.0",
    "gn:asciiname":"Yaobancun",
    "gn:country_code":"CN",
    "gn:dem":17,
    "gn:feature_class":"P",
    "gn:feature_code":"PPL",
    "gn:name":"Yaobancun",
    "gn:population":0,
    "gn:timezone":"Asia/Shanghai",
    "iso:country":"CN",
    "name:zho_x_preferred":[
        "\u59da\u5742\u6751"
    ],
    "wof:name":"Yaobancun",
    "wof:placetype":"locality"
},
  "geometry": {"coordinates":[117.32053999999999,30.72451],"type":"Point"}
}