{
  "type": "Feature",
  "properties": {
    "gn:admin1_code":"30.0",
    "gn:asciiname":"Lizhiwancun",
    "gn:country_code":"CN",
    "gn:dem":21,
    "gn:feature_class":"P",
    "gn:feature_code":"PPL",
    "gn:name":"Lizhiwancun",
    "gn:population":0,
    "gn:timezone":"Asia/Shanghai",
    "iso:country":"CN",
    "name:zho_x_preferred":[
        "\u8354\u679d\u6e7e\u6751"
    ],
    "wof:name":"Lizhiwancun",
    "wof:placetype":"locality"
},
  "geometry": {"coordinates":[112.62251000000001,21.697],"type":"Point"}
}