{
  "type": "Feature",
  "properties": {
    "gn:admin1_code":"30.0",
    "gn:asciiname":"Fuwaicun",
    "gn:country_code":"CN",
    "gn:dem":87,
    "gn:feature_class":"P",
    "gn:feature_code":"PPL",
    "gn:name":"Fuwaicun",
    "gn:population":0,
    "gn:timezone":"Asia/Shanghai",
    "iso:country":"CN",
    "name:zho_x_preferred":[
        "\u6276\u5916\u6751"
    ],
    "wof:name":"Fuwaicun",
    "wof:placetype":"locality"
},
  "geometry": {"coordinates":[116.09072999999999,24.27997],"type":"Point"}
}