{
  "type": "Feature",
  "properties": {
    "gn:admin1_code":"11.0",
    "gn:asciiname":"Longshanggang",
    "gn:country_code":"CN",
    "gn:dem":197,
    "gn:feature_class":"P",
    "gn:feature_code":"PPL",
    "gn:name":"Longshanggang",
    "gn:population":0,
    "gn:timezone":"Asia/Shanghai",
    "iso:country":"CN",
    "name:zho_x_preferred":[
        "\u9f99\u4e0a\u5c97"
    ],
    "wof:name":"Longshanggang",
    "wof:placetype":"locality"
},
  "geometry": {"coordinates":[110.61645,29.48382],"type":"Point"}
}