{
  "type": "Feature",
  "properties": {
    "gn:admin1_code":"19.0",
    "gn:asciiname":"Puheyan",
    "gn:country_code":"CN",
    "gn:dem":10,
    "gn:feature_class":"P",
    "gn:feature_code":"PPL",
    "gn:name":"Puheyan",
    "gn:population":0,
    "gn:timezone":"Asia/Shanghai",
    "iso:country":"CN",
    "name:und_x_variant":[
        "\u84b2\u6cb3\u6cbf"
    ],
    "name:zho_x_preferred":[
        "\u84b2\u6cb3\u6cbf"
    ],
    "wof:name":"Puheyan",
    "wof:placetype":"locality"
},
  "geometry": {"coordinates":[122.74947,41.43053],"type":"Point"}
}