{
  "type": "Feature",
  "properties": {
    "gn:admin1_code":"25",
    "gn:asciiname":"Beifenghuangling",
    "gn:country_code":"CN",
    "gn:dem":136,
    "gn:feature_class":"P",
    "gn:feature_code":"PPL",
    "gn:name":"Beifenghuangling",
    "gn:population":0,
    "gn:timezone":"Asia/Shanghai",
    "iso:country":"CN",
    "name:zho_x_preferred":[
        "\u5317\u51e4\u51f0\u5cad"
    ],
    "wof:name":"Beifenghuangling",
    "wof:placetype":"locality"
},
  "geometry": {"coordinates":[117.566,34.9198],"type":"Point"}
}