{
  "type": "Feature",
  "properties": {
    "gn:admin1_code":"15.0",
    "gn:asciiname":"Dangjiachuan",
    "gn:country_code":"CN",
    "gn:dem":1655,
    "gn:feature_class":"P",
    "gn:feature_code":"PPL",
    "gn:name":"Dangjiachuan",
    "gn:population":0,
    "gn:timezone":"Asia/Shanghai",
    "iso:country":"CN",
    "name:zho_x_preferred":[
        "\u515a\u5bb6\u5ddd"
    ],
    "wof:name":"Dangjiachuan",
    "wof:placetype":"locality"
},
  "geometry": {"coordinates":[104.791,37.2068],"type":"Point"}
}