{
  "type": "Feature",
  "properties": {
    "gn:admin1_code":"14",
    "gn:asciiname":"Boiga",
    "gn:country_code":"CN",
    "gn:dem":4376,
    "gn:feature_class":"P",
    "gn:feature_code":"PPL",
    "gn:name":"Boiga",
    "gn:population":0,
    "gn:timezone":"Asia/Urumqi",
    "iso:country":"CN",
    "name:ara_x_preferred":[
        "\u0628\u0648\u064a\u0642\u0629"
    ],
    "name:bel_x_preferred":[
        "Boiga"
    ],
    "name:bod_x_preferred":[
        "\u0f66\u0fa4\u0f7c\u0f66\u0f0b\u0f51\u0f42\u0f60"
    ],
    "name:bod_x_variant":[
        "\u0f66\u0fa4\u0f7c\u0f66\u0f0b\u0f58\u0f41\u0f62"
    ],
    "name:bul_x_preferred":[
        "\u0411\u043e\u0439\u0433\u0438"
    ],
    "name:ceb_x_preferred":[
        "Boiga"
    ],
    "name:ces_x_preferred":[
        "Bojga"
    ],
    "name:deu_x_preferred":[
        "Nachtbaumnattern"
    ],
    "name:est_x_preferred":[
        "Boiga"
    ],
    "name:eus_x_preferred":[
        "Boiga"
    ],
    "name:fra_x_preferred":[
        "Boiga"
    ],
    "name:heb_x_preferred":[
        "\u05d1\u05d5\u05d9\u05d2\u05d4"
    ],
    "name:hun_x_preferred":[
        "Boiga"
    ],
    "name:ind_x_preferred":[
        "Ular kucing"
    ],
    "name:ita_x_preferred":[
        "Boiga"
    ],
    "name:jpn_x_preferred":[
        "\u30aa\u30aa\u30ac\u30b7\u30e9\u5c5e"
    ],
    "name:kaz_x_preferred":[
        "\u0411\u043e\u0439\u0433\u0430\u043b\u0430\u0440"
    ],
    "name:lit_x_preferred":[
        "Boigos"
    ],
    "name:nld_x_preferred":[
        "Nachtboomslangen"
    ],
    "name:pol_x_preferred":[
        "Boiga"
    ],
    "name:por_x_preferred":[
        "Boiga"
    ],
    "name:ron_x_preferred":[
        "Boiga"
    ],
    "name:rus_x_preferred":[
        "\u0411\u043e\u0439\u0433\u0438"
    ],
    "name:sin_x_preferred":[
        "\u0db8\u0dcf\u0db4\u0dd2\u0dbd\u0dca \u0d9c\u0dab\u0dba"
    ],
    "name:spa_x_preferred":[
        "Boiga"
    ],
    "name:swe_x_preferred":[
        "Boiga"
    ],
    "name:tha_x_preferred":[
        "\u0e07\u0e39\u0e15\u0e32\u0e41\u0e21\u0e27"
    ],
    "name:ukr_x_preferred":[
        "\u0411\u043e\u0439\u0433\u0430"
    ],
    "name:und_x_variant":[
        "Boga",
        "Boikar"
    ],
    "name:uzb_x_preferred":[
        "Boygalar"
    ],
    "name:vie_x_preferred":[
        "Boiga"
    ],
    "name:war_x_preferred":[
        "Boiga"
    ],
    "name:zho_x_preferred":[
        "\u6ce2\u560e"
    ],
    "name:zho_x_variant":[
        "\u6797\u86c7\u5c6c"
    ],
    "wof:name":"Boiga",
    "wof:placetype":"locality"
},
  "geometry": {"coordinates":[91.44762,28.39638],"type":"Point"}
}