{
  "type": "Feature",
  "properties": {
    "gn:admin1_code":"14",
    "gn:asciiname":"Boiga",
    "gn:country_code":"CN",
    "gn:dem":4376,
    "gn:feature_class":"P",
    "gn:feature_code":"PPL",
    "gn:name":"Boiga",
    "gn:population":0,
    "gn:timezone":"Asia/Urumqi",
    "iso:country":"CN",
    "name:bod_x_preferred":[
        "\u0f66\u0fa4\u0f7c\u0f66\u0f0b\u0f51\u0f42\u0f60"
    ],
    "name:bod_x_variant":[
        "\u0f66\u0fa4\u0f7c\u0f66\u0f0b\u0f58\u0f41\u0f62"
    ],
    "name:und_x_variant":[
        "Boga",
        "Boikar"
    ],
    "name:zho_x_preferred":[
        "\u6ce2\u560e"
    ],
    "wof:name":"Boiga",
    "wof:placetype":"locality"
},
  "geometry": {"coordinates":[91.44762,28.39638],"type":"Point"}
}