{
  "type": "Feature",
  "properties": {
    "gn:admin1_code":"5.0",
    "gn:asciiname":"Malugou Beicha",
    "gn:country_code":"CN",
    "gn:dem":516,
    "gn:feature_class":"P",
    "gn:feature_code":"PPL",
    "gn:name":"Malugou Beicha",
    "gn:population":0,
    "gn:timezone":"Asia/Shanghai",
    "iso:country":"CN",
    "name:und_x_variant":[
        "\u9a6c\u9e7f\u6c9f\u5317\u5c94"
    ],
    "wof:name":"Malugou Beicha",
    "wof:placetype":"locality"
},
  "geometry": {"coordinates":[126.01482,41.92959000000001],"type":"Point"}
}