{
  "type": "Feature",
  "properties": {
    "gn:admin1_code":"33",
    "gn:asciiname":"Jinzisi",
    "gn:country_code":"CN",
    "gn:dem":393,
    "gn:feature_class":"P",
    "gn:feature_code":"PPL",
    "gn:name":"Jinzisi",
    "gn:population":0,
    "gn:timezone":"Asia/Shanghai",
    "iso:country":"CN",
    "name:zho_x_preferred":[
        "\u91d1\u7d2b\u5bfa"
    ],
    "wof:name":"Jinzisi",
    "wof:placetype":"locality"
},
  "geometry": {"coordinates":[106.36651999999999,29.14858],"type":"Point"}
}