{
  "type": "Feature",
  "properties": {
    "gn:admin1_code":"4.0",
    "gn:asciiname":"Sanguanmiaocun",
    "gn:country_code":"CN",
    "gn:dem":41,
    "gn:feature_class":"P",
    "gn:feature_code":"PPL",
    "gn:name":"Sanguanmiaocun",
    "gn:population":0,
    "gn:timezone":"Asia/Shanghai",
    "iso:country":"CN",
    "name:zho_x_preferred":[
        "\u4e09\u5b98\u5e99\u6751"
    ],
    "wof:name":"Sanguanmiaocun",
    "wof:placetype":"locality"
},
  "geometry": {"coordinates":[116.49213,34.83429],"type":"Point"}
}