{
  "type": "Feature",
  "properties": {
    "gn:admin1_code":"19.0",
    "gn:asciiname":"Nansanjiazi",
    "gn:country_code":"CN",
    "gn:dem":192,
    "gn:feature_class":"P",
    "gn:feature_code":"PPL",
    "gn:name":"Nansanjiazi",
    "gn:population":0,
    "gn:timezone":"Asia/Shanghai",
    "iso:country":"CN",
    "name:zho_x_preferred":[
        "\u5357\u4e09\u5bb6\u5b50"
    ],
    "wof:name":"Nansanjiazi",
    "wof:placetype":"locality"
},
  "geometry": {"coordinates":[121.36877,41.94825],"type":"Point"}
}