{
  "type": "Feature",
  "properties": {
    "gn:admin1_code":"14",
    "gn:asciiname":"Seniang",
    "gn:country_code":"CN",
    "gn:dem":4821,
    "gn:feature_class":"P",
    "gn:feature_code":"PPL",
    "gn:name":"Seniang",
    "gn:population":0,
    "gn:timezone":"Asia/Urumqi",
    "iso:country":"CN",
    "name:zho_x_preferred":[
        "\u8272\u5a18"
    ],
    "wof:name":"Seniang",
    "wof:placetype":"locality"
},
  "geometry": {"coordinates":[88.7764,30.5713],"type":"Point"}
}