{
  "type": "Feature",
  "properties": {
    "gn:admin1_code":"14.0",
    "gn:asciiname":"Genqiong",
    "gn:country_code":"CN",
    "gn:dem":4543,
    "gn:feature_class":"P",
    "gn:feature_code":"PPL",
    "gn:name":"Genqiong",
    "gn:population":0,
    "gn:timezone":"Asia/Urumqi",
    "iso:country":"CN",
    "name:zho_x_preferred":[
        "\u6839\u743c"
    ],
    "wof:name":"Genqiong",
    "wof:placetype":"locality"
},
  "geometry": {"coordinates":[83.8623,32.7007],"type":"Point"}
}