{
  "type": "Feature",
  "properties": {
    "gn:admin1_code":"32.0",
    "gn:asciiname":"Rupo",
    "gn:country_code":"CN",
    "gn:dem":2639,
    "gn:feature_class":"P",
    "gn:feature_code":"PPL",
    "gn:name":"Rupo",
    "gn:population":0,
    "gn:timezone":"Asia/Shanghai",
    "iso:country":"CN",
    "name:zho_x_preferred":[
        "\u6c5d\u5a46"
    ],
    "wof:name":"Rupo",
    "wof:placetype":"locality"
},
  "geometry": {"coordinates":[102.577,28.3629],"type":"Point"}
}