{
  "type": "Feature",
  "properties": {
    "gn:admin1_code":"23",
    "gn:asciiname":"Ping'an",
    "gn:country_code":"CN",
    "gn:dem":5,
    "gn:feature_class":"P",
    "gn:feature_code":"PPL",
    "gn:name":"Ping\u2019an",
    "gn:population":0,
    "gn:timezone":"Asia/Shanghai",
    "iso:country":"CN",
    "name:ceb_x_preferred":[
        "Ping'an"
    ],
    "name:deu_x_preferred":[
        "Ping\u2019an"
    ],
    "name:fra_x_preferred":[
        "Pingan"
    ],
    "name:nld_x_preferred":[
        "Ping An"
    ],
    "name:und_x_variant":[
        "Ping\u2019anle",
        "P\u2019ing-an-le",
        "\u5e73\u5b89"
    ],
    "wof:name":"Ping'an",
    "wof:placetype":"locality"
},
  "geometry": {"coordinates":[121.72941000000002,30.90229],"type":"Point"}
}