{
  "type": "Feature",
  "properties": {
    "gn:admin1_code":"11.0",
    "gn:asciiname":"Dushuzhai",
    "gn:country_code":"CN",
    "gn:dem":584,
    "gn:feature_class":"P",
    "gn:feature_code":"PPL",
    "gn:name":"Dushuzhai",
    "gn:population":0,
    "gn:timezone":"Asia/Shanghai",
    "iso:country":"CN",
    "name:zho_x_preferred":[
        "\u72ec\u6811\u5be8"
    ],
    "wof:name":"Dushuzhai",
    "wof:placetype":"locality"
},
  "geometry": {"coordinates":[110.15031,26.03346],"type":"Point"}
}