{
  "type": "Feature",
  "properties": {
    "gn:admin1_code":"4.0",
    "gn:asciiname":"Gaocaoxu",
    "gn:country_code":"CN",
    "gn:dem":3,
    "gn:feature_class":"P",
    "gn:feature_code":"PPL",
    "gn:name":"Gaocaoxu",
    "gn:population":0,
    "gn:timezone":"Asia/Shanghai",
    "iso:country":"CN",
    "name:zho_x_preferred":[
        "\u4e0a\u65b0\u6865"
    ],
    "wof:name":"Gaocaoxu",
    "wof:placetype":"locality"
},
  "geometry": {"coordinates":[119.7268,32.27904],"type":"Point"}
}