{
  "type": "Feature",
  "properties": {
    "gn:admin1_code":"2.0",
    "gn:asciiname":"Lancaohe",
    "gn:country_code":"CN",
    "gn:dem":574,
    "gn:feature_class":"P",
    "gn:feature_code":"PPL",
    "gn:name":"Lancaohe",
    "gn:population":0,
    "gn:timezone":"Asia/Shanghai",
    "iso:country":"CN",
    "name:zho_x_preferred":[
        "\u5170\u8349\u6cb3"
    ],
    "wof:name":"Lancaohe",
    "wof:placetype":"locality"
},
  "geometry": {"coordinates":[119.18586999999999,29.87247],"type":"Point"}
}