{
  "type": "Feature",
  "properties": {
    "gn:admin1_code":"13",
    "gn:asciiname":"Qiapu",
    "gn:country_code":"CN",
    "gn:dem":654,
    "gn:feature_class":"P",
    "gn:feature_code":"PPL",
    "gn:name":"Qiapu",
    "gn:population":0,
    "gn:timezone":"Asia/Urumqi",
    "iso:country":"CN",
    "name:zho_x_preferred":[
        "\u6070\u666e"
    ],
    "wof:name":"Qiapu",
    "wof:placetype":"locality"
},
  "geometry": {"coordinates":[92.93333,42.96588],"type":"Point"}
}