{
  "type": "Feature",
  "properties": {
    "gn:admin1_code":"15.0",
    "gn:asciiname":"Tiejialingzi",
    "gn:country_code":"CN",
    "gn:dem":1310,
    "gn:feature_class":"P",
    "gn:feature_code":"PPL",
    "gn:name":"Tiejialingzi",
    "gn:population":0,
    "gn:timezone":"Asia/Shanghai",
    "iso:country":"CN",
    "name:und_x_variant":[
        "\u94c1\u5bb6\u5cad\u5b50"
    ],
    "wof:name":"Tiejialingzi",
    "wof:placetype":"locality"
},
  "geometry": {"coordinates":[107.85211,36.25611],"type":"Point"}
}