{
  "type": "Feature",
  "properties": {
    "gn:admin1_code":"3.0",
    "gn:asciiname":"Xinsheqian",
    "gn:country_code":"CN",
    "gn:dem":85,
    "gn:feature_class":"P",
    "gn:feature_code":"PPL",
    "gn:name":"Xinsheqian",
    "gn:population":0,
    "gn:timezone":"Asia/Shanghai",
    "iso:country":"CN",
    "name:und_x_variant":[
        "\u65b0\u793e\u524d"
    ],
    "wof:name":"Xinsheqian",
    "wof:placetype":"locality"
},
  "geometry": {"coordinates":[114.75765,27.16999],"type":"Point"}
}