{
  "type": "Feature",
  "properties": {
    "gn:admin1_code":"1.0",
    "gn:asciiname":"Fangjia",
    "gn:country_code":"CN",
    "gn:dem":6,
    "gn:feature_class":"P",
    "gn:feature_code":"PPL",
    "gn:name":"Fangjia",
    "gn:population":0,
    "gn:timezone":"Asia/Shanghai",
    "iso:country":"CN",
    "name:zho_x_preferred":[
        "\u65b9\u5bb6"
    ],
    "wof:name":"Fangjia",
    "wof:placetype":"locality"
},
  "geometry": {"coordinates":[118.42552000000001,31.17835],"type":"Point"}
}