{
  "type": "Feature",
  "properties": {
    "gn:admin1_code":"32.0",
    "gn:asciiname":"Lugangba",
    "gn:country_code":"CN",
    "gn:dem":412,
    "gn:feature_class":"P",
    "gn:feature_code":"PPL",
    "gn:name":"Lugangba",
    "gn:population":0,
    "gn:timezone":"Asia/Shanghai",
    "iso:country":"CN",
    "name:zho_x_preferred":[
        "\u9732\u7f38\u575d"
    ],
    "wof:name":"Lugangba",
    "wof:placetype":"locality"
},
  "geometry": {"coordinates":[104.16500000000001,29.8278],"type":"Point"}
}