{
  "type": "Feature",
  "properties": {
    "gn:admin1_code":"33.0",
    "gn:asciiname":"Shuangzhu",
    "gn:country_code":"CN",
    "gn:dem":1455,
    "gn:feature_class":"P",
    "gn:feature_code":"PPL",
    "gn:name":"Shuangzhu",
    "gn:population":0,
    "gn:timezone":"Asia/Shanghai",
    "iso:country":"CN",
    "name:zho_x_preferred":[
        "\u53cc\u7af9"
    ],
    "wof:name":"Shuangzhu",
    "wof:placetype":"locality"
},
  "geometry": {"coordinates":[109.01533000000001,31.84165],"type":"Point"}
}