{
  "type": "Feature",
  "properties": {
    "gn:admin1_code":"18",
    "gn:asciiname":"Huajiang",
    "gn:cc2":"CN",
    "gn:country_code":"CN",
    "gn:dem":1203,
    "gn:feature_class":"P",
    "gn:feature_code":"PPL",
    "gn:name":"Huajiang",
    "gn:population":0,
    "gn:timezone":"Asia/Shanghai",
    "iso:country":"CN",
    "name:und_x_variant":[
        "Kuan-ling-hsien",
        "Mu-i",
        "Kuan-ling",
        "Hua-chiang-chen",
        "Chiu-kuan-ling",
        "Kwanlunghsien",
        "Hua-chiang",
        "Mu-i-ssu",
        "Kwanling-hsien",
        "Huajiang"
    ],
    "wof:name":"Huajiang",
    "wof:placetype":"locality"
},
  "geometry": {"coordinates":[105.59999999999999,25.75],"type":"Point"}
}