{
  "type": "Feature",
  "properties": {
    "gn:admin1_code":"7.0",
    "gn:asciiname":"Jiyuan",
    "gn:country_code":"CN",
    "gn:dem":167,
    "gn:feature_class":"P",
    "gn:feature_code":"PPL",
    "gn:name":"Jiyuan",
    "gn:population":0,
    "gn:timezone":"Asia/Shanghai",
    "iso:country":"CN",
    "name:ast_x_preferred":[
        "Jiyuan"
    ],
    "name:cdo_x_preferred":[
        "C\u00e1\u0324-ngu\u00f2ng"
    ],
    "name:deu_x_preferred":[
        "Jiyuan"
    ],
    "name:eus_x_preferred":[
        "Jiyuan"
    ],
    "name:fas_x_preferred":[
        "\u062c\u06cc\u0648\u0627\u0646"
    ],
    "name:fin_x_preferred":[
        "Jiyuan"
    ],
    "name:fra_x_preferred":[
        "Jiyuan"
    ],
    "name:ita_x_preferred":[
        "Jiyuan"
    ],
    "name:jpn_x_preferred":[
        "\u6e08\u6e90\u5e02"
    ],
    "name:kik_x_preferred":[
        "Jiyuan"
    ],
    "name:kor_x_preferred":[
        "\uc9c0\uc704\uc548\uc2dc"
    ],
    "name:mlg_x_preferred":[
        "Jiyuan"
    ],
    "name:nld_x_preferred":[
        "Jiyuan"
    ],
    "name:nno_x_preferred":[
        "Jiyuan"
    ],
    "name:nor_x_preferred":[
        "Jiyuan"
    ],
    "name:pam_x_preferred":[
        "Jiyuan"
    ],
    "name:pol_x_preferred":[
        "Jiyuan"
    ],
    "name:rus_x_preferred":[
        "\u0426\u0437\u0438\u044e\u0430\u043d\u044c"
    ],
    "name:spa_x_preferred":[
        "Jiyuan"
    ],
    "name:swe_x_preferred":[
        "Jiyuan"
    ],
    "name:tur_x_preferred":[
        "Jiyuan"
    ],
    "name:urd_x_preferred":[
        "\u062c\u06cc\u06cc\u0648\u0627\u0646"
    ],
    "name:vie_x_preferred":[
        "T\u1ebf Nguy\u00ean"
    ],
    "name:war_x_preferred":[
        "Jiyuan"
    ],
    "name:zho_x_preferred":[
        "\u8bb0\u6e90"
    ],
    "name:zho_x_variant":[
        "\u6d4e\u6e90\u5e02"
    ],
    "wof:name":"Jiyuan",
    "wof:placetype":"locality"
},
  "geometry": {"coordinates":[118.53794000000001,27.18366],"type":"Point"}
}