{
  "type": "Feature",
  "properties": {
    "gn:admin1_code":"7.0",
    "gn:asciiname":"Jiyuan",
    "gn:country_code":"CN",
    "gn:dem":167,
    "gn:feature_class":"P",
    "gn:feature_code":"PPL",
    "gn:name":"Jiyuan",
    "gn:population":0,
    "gn:timezone":"Asia/Shanghai",
    "iso:country":"CN",
    "name:zho_x_preferred":[
        "\u8bb0\u6e90"
    ],
    "wof:name":"Jiyuan",
    "wof:placetype":"locality"
},
  "geometry": {"coordinates":[118.53794000000001,27.18366],"type":"Point"}
}