{
  "type": "Feature",
  "properties": {
    "gn:country":"CN",
    "gn:fcode":"ADM3",
    "gn:pop":0,
    "iso:country":"CN",
    "name:ceb_x_preferred":[
        "Panyu Qu"
    ],
    "name:cym_x_preferred":[
        "Ardal Panyu"
    ],
    "name:dan_x_preferred":[
        "Panyu"
    ],
    "name:deu_x_preferred":[
        "Panyu"
    ],
    "name:eng_x_preferred":[
        "panyu"
    ],
    "name:eng_x_variant":[
        "panyu qu",
        "Panyu District"
    ],
    "name:eus_x_preferred":[
        "Panyu Barrutia"
    ],
    "name:fas_x_preferred":[
        "\u067e\u0627\u0646\u06cc\u0648"
    ],
    "name:gan_x_preferred":[
        "\u756a\u79ba\u533a"
    ],
    "name:hak_x_preferred":[
        "F\u00e2n-ny\u00ee-kh\u00ee"
    ],
    "name:jpn_x_preferred":[
        "\u756a\u79ba\u533a"
    ],
    "name:kor_x_preferred":[
        "\ud310\uc704\uad6c"
    ],
    "name:lav_x_preferred":[
        "Pa\u0146jui cjui"
    ],
    "name:mwl_x_preferred":[
        "Panyu"
    ],
    "name:nan_x_preferred":[
        "Hoan-g\u00fb-khu"
    ],
    "name:nld_x_preferred":[
        "Panyu"
    ],
    "name:nob_x_preferred":[
        "Panyu"
    ],
    "name:pol_x_preferred":[
        "Panyu"
    ],
    "name:sco_x_preferred":[
        "Panyu Destrict"
    ],
    "name:spa_x_preferred":[
        "Panyu"
    ],
    "name:swe_x_preferred":[
        "Panyu"
    ],
    "name:unk_x_variant":[
        "P\u2019an-y\u00fc Hsien"
    ],
    "name:vie_x_preferred":[
        "Phi\u00ean Ngung"
    ],
    "name:wuu_x_preferred":[
        "\u756a\u79ba\u533a"
    ],
    "name:yue_x_preferred":[
        "\u756a\u79ba"
    ],
    "name:zho_x_preferred":[
        "\u756a\u79ba\u533a"
    ],
    "name:zho_x_variant":[
        "\u756a\u79ba"
    ],
    "qs:name":"Panyu Qu",
    "qs:photos_9r":0,
    "qs:photos_sr":0,
    "qs:pop_sr":"0",
    "wd:wordcount":1046,
    "wof:name":"Panyu Qu",
    "wof:placetype":"localadmin",
    "wof:population":0
},
  "geometry": {"coordinates":[113.35523999999999,22.93572],"type":"Point"}
}