{
  "type": "Feature",
  "properties": {
    "gn:admin1_code":"11",
    "gn:asciiname":"Shangkuangjia",
    "gn:country_code":"CN",
    "gn:dem":536,
    "gn:feature_class":"P",
    "gn:feature_code":"PPL",
    "gn:name":"Shangkuangjia",
    "gn:population":0,
    "gn:timezone":"Asia/Shanghai",
    "iso:country":"CN",
    "name:zho_x_preferred":[
        "\u4e0a\u909d\u5bb6"
    ],
    "wof:name":"Shangkuangjia",
    "wof:placetype":"locality"
},
  "geometry": {"coordinates":[111.78428999999998,25.08555],"type":"Point"}
}