{
  "type": "Feature",
  "properties": {
    "gn:admin1_code":"1.0",
    "gn:asciiname":"Shuguangcun",
    "gn:country_code":"CN",
    "gn:dem":58,
    "gn:feature_class":"P",
    "gn:feature_code":"PPL",
    "gn:name":"Shuguangcun",
    "gn:population":0,
    "gn:timezone":"Asia/Shanghai",
    "iso:country":"CN",
    "name:zho_x_preferred":[
        "\u66d9\u5149\u6751"
    ],
    "wof:name":"Shuguangcun",
    "wof:placetype":"locality"
},
  "geometry": {"coordinates":[116.49929,30.39915],"type":"Point"}
}