{
  "type": "Feature",
  "properties": {
    "gn:admin1_code":"32.0",
    "gn:asciiname":"Maluoqiao",
    "gn:country_code":"CN",
    "gn:dem":3597,
    "gn:feature_class":"P",
    "gn:feature_code":"PPL",
    "gn:name":"Maluoqiao",
    "gn:population":0,
    "gn:timezone":"Asia/Shanghai",
    "iso:country":"CN",
    "name:zho_x_preferred":[
        "\u739b\u6d1b\u4e54"
    ],
    "wof:name":"Maluoqiao",
    "wof:placetype":"locality"
},
  "geometry": {"coordinates":[101.435,29.5184],"type":"Point"}
}