{
  "type": "Feature",
  "properties": {
    "gn:admin1_code":"26.0",
    "gn:asciiname":"Tianxinwo",
    "gn:country_code":"CN",
    "gn:dem":1159,
    "gn:feature_class":"P",
    "gn:feature_code":"PPL",
    "gn:name":"Tianxinwo",
    "gn:population":0,
    "gn:timezone":"Asia/Shanghai",
    "iso:country":"CN",
    "name:und_x_variant":[
        "\u5929\u5fc3\u7a9d"
    ],
    "wof:name":"Tianxinwo",
    "wof:placetype":"locality"
},
  "geometry": {"coordinates":[107.34831,33.66866],"type":"Point"}
}