{
  "type": "Feature",
  "properties": {
    "gn:admin1_code":"10",
    "gn:asciiname":"Qinghetang",
    "gn:country_code":"CN",
    "gn:dem":228,
    "gn:feature_class":"P",
    "gn:feature_code":"PPL",
    "gn:name":"Qinghetang",
    "gn:population":0,
    "gn:timezone":"Asia/Shanghai",
    "iso:country":"CN",
    "name:zho_x_preferred":[
        "\u6e05\u6cb3\u5858"
    ],
    "wof:name":"Qinghetang",
    "wof:placetype":"locality"
},
  "geometry": {"coordinates":[118.22753,40.57523],"type":"Point"}
}