{
  "type": "Feature",
  "properties": {
    "gn:admin1_code":"12.0",
    "gn:asciiname":"Tanhutai",
    "gn:country_code":"CN",
    "gn:dem":36,
    "gn:feature_class":"P",
    "gn:feature_code":"PPL",
    "gn:name":"Tanhutai",
    "gn:population":0,
    "gn:timezone":"Asia/Shanghai",
    "iso:country":"CN",
    "name:zho_x_preferred":[
        "\u6f6d\u6e56\u53f0"
    ],
    "wof:name":"Tanhutai",
    "wof:placetype":"locality"
},
  "geometry": {"coordinates":[112.83546,30.53774],"type":"Point"}
}