{
  "type": "Feature",
  "properties": {
    "gn:admin1_code":"12.0",
    "gn:asciiname":"Ganzhuangping",
    "gn:country_code":"CN",
    "gn:dem":1078,
    "gn:feature_class":"P",
    "gn:feature_code":"PPL",
    "gn:name":"Ganzhuangping",
    "gn:population":0,
    "gn:timezone":"Asia/Shanghai",
    "iso:country":"CN",
    "name:zho_x_preferred":[
        "\u5e72\u6869\u576a"
    ],
    "wof:name":"Ganzhuangping",
    "wof:placetype":"locality"
},
  "geometry": {"coordinates":[108.80547,29.81461],"type":"Point"}
}