{
  "type": "Feature",
  "properties": {
    "gn:admin1_code":"16",
    "gn:asciiname":"Liuxi",
    "gn:country_code":"CN",
    "gn:dem":326,
    "gn:feature_class":"P",
    "gn:feature_code":"PPL",
    "gn:name":"Liuxi",
    "gn:population":0,
    "gn:timezone":"Asia/Shanghai",
    "iso:country":"CN",
    "name:zho_x_preferred":[
        "\u516d\u6eaa"
    ],
    "wof:name":"Liuxi",
    "wof:placetype":"locality"
},
  "geometry": {"coordinates":[109.56399999999999,25.5108],"type":"Point"}
}