{
  "type": "Feature",
  "properties": {
    "gn:admin1_code":"29.0",
    "gn:asciiname":"Qilongshan",
    "gn:country_code":"CN",
    "gn:dem":2632,
    "gn:feature_class":"P",
    "gn:feature_code":"PPL",
    "gn:name":"Qilongshan",
    "gn:population":0,
    "gn:timezone":"Asia/Shanghai",
    "iso:country":"CN",
    "name:zho_x_preferred":[
        "\u9a91\u9f99\u5c71"
    ],
    "wof:name":"Qilongshan",
    "wof:placetype":"locality"
},
  "geometry": {"coordinates":[99.8103,26.079],"type":"Point"}
}