{
  "type": "Feature",
  "properties": {
    "gn:admin1_code":"18",
    "gn:asciiname":"Pingrao",
    "gn:country_code":"CN",
    "gn:dem":519,
    "gn:feature_class":"P",
    "gn:feature_code":"PPL",
    "gn:name":"Pingrao",
    "gn:population":0,
    "gn:timezone":"Asia/Shanghai",
    "iso:country":"CN",
    "name:zho_x_preferred":[
        "\u5e73\u7ed5"
    ],
    "wof:name":"Pingrao",
    "wof:placetype":"locality"
},
  "geometry": {"coordinates":[105.98699999999999,24.9688],"type":"Point"}
}