{
  "type": "Feature",
  "properties": {
    "gn:admin1_code":"19.0",
    "gn:asciiname":"Heigangcun",
    "gn:country_code":"CN",
    "gn:dem":26,
    "gn:feature_class":"P",
    "gn:feature_code":"PPL",
    "gn:name":"Heigangcun",
    "gn:population":0,
    "gn:timezone":"Asia/Shanghai",
    "iso:country":"CN",
    "name:zho_x_preferred":[
        "\u9ed1\u5c97\u6751"
    ],
    "wof:name":"Heigangcun",
    "wof:placetype":"locality"
},
  "geometry": {"coordinates":[122.699,41.89100000000001],"type":"Point"}
}