{
  "type": "Feature",
  "properties": {
    "gn:admin1_code":"18",
    "gn:asciiname":"Fengyan",
    "gn:country_code":"CN",
    "gn:dem":1110,
    "gn:feature_class":"P",
    "gn:feature_code":"PPL",
    "gn:name":"Fengyan",
    "gn:population":0,
    "gn:timezone":"Asia/Shanghai",
    "iso:country":"CN",
    "name:zho_x_preferred":[
        "\u5cf0\u5ca9"
    ],
    "wof:name":"Fengyan",
    "wof:placetype":"locality"
},
  "geometry": {"coordinates":[106.872,28.0917],"type":"Point"}
}