{
  "type": "Feature",
  "properties": {
    "gn:admin1_code":"7",
    "gn:asciiname":"Shanhu",
    "gn:country_code":"CN",
    "gn:dem":305,
    "gn:feature_class":"P",
    "gn:feature_code":"PPLA4",
    "gn:name":"Shanhu",
    "gn:population":0,
    "gn:timezone":"Asia/Shanghai",
    "iso:country":"CN",
    "name:und_x_variant":[
        "\u73ca\u745a",
        "Shanhu Xiang",
        "\u73ca\u745a\u4e61"
    ],
    "wof:name":"Shanhu",
    "wof:placetype":"locality"
},
  "geometry": {"coordinates":[116.32722,25.23111],"type":"Point"}
}