{
  "type": "Feature",
  "properties": {
    "gn:admin1_code":"7.0",
    "gn:asciiname":"Huyangzhai",
    "gn:country_code":"CN",
    "gn:dem":387,
    "gn:feature_class":"P",
    "gn:feature_code":"PPL",
    "gn:name":"Huyangzhai",
    "gn:population":0,
    "gn:timezone":"Asia/Shanghai",
    "iso:country":"CN",
    "name:zho_x_preferred":[
        "\u6e56\u6d0b\u5be8"
    ],
    "wof:name":"Huyangzhai",
    "wof:placetype":"locality"
},
  "geometry": {"coordinates":[116.99405,25.01837],"type":"Point"}
}