{
  "type": "Feature",
  "properties": {
    "gn:admin1_code":"26",
    "gn:asciiname":"Nanwei",
    "gn:country_code":"CN",
    "gn:dem":497,
    "gn:feature_class":"P",
    "gn:feature_code":"PPLA4",
    "gn:name":"Nanwei",
    "gn:population":0,
    "gn:timezone":"Asia/Shanghai",
    "iso:country":"CN",
    "name:und_x_variant":[
        "Nanwei Zhen",
        "Nanwei"
    ],
    "name:zho_x_preferred":[
        "\u5357\u4f4d"
    ],
    "name:zho_x_variant":[
        "\u5357\u4f4d\u9547"
    ],
    "wof:name":"Nanwei",
    "wof:placetype":"locality"
},
  "geometry": {"coordinates":[108.54222,34.3575],"type":"Point"}
}