{
  "type": "Feature",
  "properties": {
    "gn:admin1_code":"26.0",
    "gn:asciiname":"Fenshanwan",
    "gn:country_code":"CN",
    "gn:dem":670,
    "gn:feature_class":"P",
    "gn:feature_code":"PPL",
    "gn:name":"Fenshanwan",
    "gn:population":0,
    "gn:timezone":"Asia/Shanghai",
    "iso:country":"CN",
    "name:und_x_variant":[
        "\u575f\u5c71\u6e7e"
    ],
    "wof:name":"Fenshanwan",
    "wof:placetype":"locality"
},
  "geometry": {"coordinates":[107.43619,32.90156],"type":"Point"}
}