{
  "type": "Feature",
  "properties": {
    "gn:admin1_code":"29.0",
    "gn:asciiname":"Xiquewo",
    "gn:country_code":"CN",
    "gn:dem":1844,
    "gn:feature_class":"P",
    "gn:feature_code":"PPL",
    "gn:name":"Xiquewo",
    "gn:population":0,
    "gn:timezone":"Asia/Shanghai",
    "iso:country":"CN",
    "name:zho_x_preferred":[
        "\u559c\u9e4a\u7a9d"
    ],
    "wof:name":"Xiquewo",
    "wof:placetype":"locality"
},
  "geometry": {"coordinates":[101.58,25.2419],"type":"Point"}
}