{
  "type": "Feature",
  "properties": {
    "gn:admin1_code":"1.0",
    "gn:asciiname":"Beicaiqiaocun",
    "gn:country_code":"CN",
    "gn:dem":27,
    "gn:feature_class":"P",
    "gn:feature_code":"PPL",
    "gn:name":"Beicaiqiaocun",
    "gn:population":0,
    "gn:timezone":"Asia/Shanghai",
    "iso:country":"CN",
    "name:zho_x_preferred":[
        "\u5317\u8521\u6865\u6751"
    ],
    "wof:name":"Beicaiqiaocun",
    "wof:placetype":"locality"
},
  "geometry": {"coordinates":[117.12537,33.56912],"type":"Point"}
}