{
  "type": "Feature",
  "properties": {
    "gn:admin1_code":"18",
    "gn:asciiname":"Mayichi",
    "gn:country_code":"CN",
    "gn:dem":1692,
    "gn:feature_class":"P",
    "gn:feature_code":"PPL",
    "gn:name":"Mayichi",
    "gn:population":0,
    "gn:timezone":"Asia/Shanghai",
    "iso:country":"CN",
    "name:zho_x_preferred":[
        "\u8682\u8681\u6c60"
    ],
    "wof:name":"Mayichi",
    "wof:placetype":"locality"
},
  "geometry": {"coordinates":[104.917,25.7331],"type":"Point"}
}