{
  "type": "Feature",
  "properties": {
    "gn:admin1_code":"3.0",
    "gn:asciiname":"Xia'an",
    "gn:country_code":"CN",
    "gn:dem":161,
    "gn:feature_class":"P",
    "gn:feature_code":"PPL",
    "gn:name":"Xia\u2019an",
    "gn:population":0,
    "gn:timezone":"Asia/Shanghai",
    "iso:country":"CN",
    "name:und_x_variant":[
        "Xia\u2019an",
        "\u4e0b\u5b89"
    ],
    "wof:name":"Xia'an",
    "wof:placetype":"locality"
},
  "geometry": {"coordinates":[115.63028,25.7944],"type":"Point"}
}