{
  "type": "Feature",
  "properties": {
    "gn:admin1_code":"12.0",
    "gn:asciiname":"Baishuiyukou",
    "gn:country_code":"CN",
    "gn:dem":283,
    "gn:feature_class":"P",
    "gn:feature_code":"PPL",
    "gn:name":"Baishuiyukou",
    "gn:population":0,
    "gn:timezone":"Asia/Shanghai",
    "iso:country":"CN",
    "name:zho_x_preferred":[
        "\u767d\u6c34\u5cea\u53e3"
    ],
    "wof:name":"Baishuiyukou",
    "wof:placetype":"locality"
},
  "geometry": {"coordinates":[111.38839,32.04968],"type":"Point"}
}