{
  "type": "Feature",
  "properties": {
    "gn:admin1_code":"4.0",
    "gn:asciiname":"Xilinzicun",
    "gn:country_code":"CN",
    "gn:dem":5,
    "gn:feature_class":"P",
    "gn:feature_code":"PPL",
    "gn:name":"Xilinzicun",
    "gn:population":0,
    "gn:timezone":"Asia/Shanghai",
    "iso:country":"CN",
    "name:zho_x_preferred":[
        "\u897f\u6797\u5b50\u6751"
    ],
    "wof:name":"Xilinzicun",
    "wof:placetype":"locality"
},
  "geometry": {"coordinates":[119.24572999999999,35.0769],"type":"Point"}
}