{
  "type": "Feature",
  "properties": {
    "gn:admin1_code":"25",
    "gn:asciiname":"Daniuwang",
    "gn:country_code":"CN",
    "gn:dem":21,
    "gn:feature_class":"P",
    "gn:feature_code":"PPL",
    "gn:name":"Daniuwang",
    "gn:population":0,
    "gn:timezone":"Asia/Shanghai",
    "iso:country":"CN",
    "name:zho_x_preferred":[
        "\u5927\u725b\u738b"
    ],
    "wof:name":"Daniuwang",
    "wof:placetype":"locality"
},
  "geometry": {"coordinates":[117.413,37.0701],"type":"Point"}
}