{
  "type": "Feature",
  "properties": {
    "gn:admin1_code":"11.0",
    "gn:asciiname":"Yanjia",
    "gn:country_code":"CN",
    "gn:dem":131,
    "gn:feature_class":"P",
    "gn:feature_code":"PPL",
    "gn:name":"Yanjia",
    "gn:population":0,
    "gn:timezone":"Asia/Shanghai",
    "iso:country":"CN",
    "name:zho_x_preferred":[
        "\u9122\u5bb6"
    ],
    "wof:name":"Yanjia",
    "wof:placetype":"locality"
},
  "geometry": {"coordinates":[110.68626999999999,28.67356],"type":"Point"}
}