{
  "type": "Feature",
  "properties": {
    "gn:admin1_code":"19",
    "gn:asciiname":"Basiyingzi",
    "gn:country_code":"CN",
    "gn:dem":244,
    "gn:feature_class":"P",
    "gn:feature_code":"PPL",
    "gn:name":"Basiyingzi",
    "gn:population":0,
    "gn:timezone":"Asia/Shanghai",
    "iso:country":"CN",
    "name:zho_x_preferred":[
        "\u5df4\u601d\u8425\u5b50"
    ],
    "wof:name":"Basiyingzi",
    "wof:placetype":"locality"
},
  "geometry": {"coordinates":[121.13200000000001,41.865],"type":"Point"}
}