{
  "type": "Feature",
  "properties": {
    "gn:admin1_code":"31.0",
    "gn:asciiname":"Laoqu",
    "gn:country_code":"CN",
    "gn:dem":33,
    "gn:feature_class":"P",
    "gn:feature_code":"PPL",
    "gn:name":"Laoqu",
    "gn:population":0,
    "gn:timezone":"Asia/Shanghai",
    "iso:country":"CN",
    "name:und_x_variant":[
        "\u8001\u533a"
    ],
    "wof:name":"Laoqu",
    "wof:placetype":"locality"
},
  "geometry": {"coordinates":[110.40483999999999,19.07286],"type":"Point"}
}