{
  "type": "Feature",
  "properties": {
    "gn:admin1_code":"11",
    "gn:asciiname":"Luojiachong",
    "gn:country_code":"CN",
    "gn:dem":193,
    "gn:feature_class":"P",
    "gn:feature_code":"PPL",
    "gn:name":"Luojiachong",
    "gn:population":0,
    "gn:timezone":"Asia/Shanghai",
    "iso:country":"CN",
    "wof:name":"Luojiachong",
    "wof:placetype":"locality"
},
  "geometry": {"coordinates":[111.72638999999999,27.80833],"type":"Point"}
}