{
  "type": "Feature",
  "properties": {
    "gn:admin1_code":"10",
    "gn:asciiname":"Wopu Tougou",
    "gn:country_code":"CN",
    "gn:dem":932,
    "gn:feature_class":"P",
    "gn:feature_code":"PPL",
    "gn:name":"Wopu Tougou",
    "gn:population":0,
    "gn:timezone":"Asia/Shanghai",
    "iso:country":"CN",
    "name:zho_x_preferred":[
        "\u7a9d\u94fa\u5934\u6c9f"
    ],
    "wof:name":"Wopu Tougou",
    "wof:placetype":"locality"
},
  "geometry": {"coordinates":[117.8875,41.51506],"type":"Point"}
}