{
  "type": "Feature",
  "properties": {
    "gn:admin1_code":"5.0",
    "gn:asciiname":"Sanshiqihao",
    "gn:country_code":"CN",
    "gn:dem":144,
    "gn:feature_class":"P",
    "gn:feature_code":"PPL",
    "gn:name":"Sanshiqihao",
    "gn:population":0,
    "gn:timezone":"Asia/Shanghai",
    "iso:country":"CN",
    "name:zho_x_preferred":[
        "\u4e09\u5341\u4e03\u53f7"
    ],
    "wof:name":"Sanshiqihao",
    "wof:placetype":"locality"
},
  "geometry": {"coordinates":[123.48291,44.61632],"type":"Point"}
}