{
  "type": "Feature",
  "properties": {
    "gn:admin1_code":"12.0",
    "gn:asciiname":"Gaoshouwan",
    "gn:country_code":"CN",
    "gn:dem":39,
    "gn:feature_class":"P",
    "gn:feature_code":"PPL",
    "gn:name":"Gaoshouwan",
    "gn:population":0,
    "gn:timezone":"Asia/Shanghai",
    "iso:country":"CN",
    "name:zho_x_preferred":[
        "Gaoshouwan"
    ],
    "name:zho_x_variant":[
        "\u9550\u624b\u6e7e"
    ],
    "wof:name":"Gaoshouwan",
    "wof:placetype":"locality"
},
  "geometry": {"coordinates":[111.88397000000001,30.1963],"type":"Point"}
}