{
  "type": "Feature",
  "properties": {
    "gn:admin1_code":"26.0",
    "gn:asciiname":"Leinancun",
    "gn:country_code":"CN",
    "gn:dem":436,
    "gn:feature_class":"P",
    "gn:feature_code":"PPL",
    "gn:name":"Leinancun",
    "gn:population":0,
    "gn:timezone":"Asia/Shanghai",
    "iso:country":"CN",
    "name:zho_x_preferred":[
        "\u96f7\u5357\u6751"
    ],
    "wof:name":"Leinancun",
    "wof:placetype":"locality"
},
  "geometry": {"coordinates":[110.18388,34.95780999999999],"type":"Point"}
}