{
  "type": "Feature",
  "properties": {
    "gn:admin1_code":"8.0",
    "gn:asciiname":"Gangshiyao",
    "gn:country_code":"CN",
    "gn:dem":228,
    "gn:feature_class":"P",
    "gn:feature_code":"PPL",
    "gn:name":"Gangshiyao",
    "gn:population":0,
    "gn:timezone":"Asia/Shanghai",
    "iso:country":"CN",
    "name:zho_x_preferred":[
        "\u94a2\u77f3\u7a91"
    ],
    "wof:name":"Gangshiyao",
    "wof:placetype":"locality"
},
  "geometry": {"coordinates":[127.18736,45.37569000000001],"type":"Point"}
}