{
  "type": "Feature",
  "properties": {
    "gn:admin1_code":"4.0",
    "gn:asciiname":"Xiaoliukou",
    "gn:country_code":"CN",
    "gn:dem":4,
    "gn:feature_class":"P",
    "gn:feature_code":"PPL",
    "gn:name":"Xiaoliukou",
    "gn:population":0,
    "gn:timezone":"Asia/Shanghai",
    "iso:country":"CN",
    "name:zho_x_preferred":[
        "\u5c0f\u67f3\u53e3"
    ],
    "wof:name":"Xiaoliukou",
    "wof:placetype":"locality"
},
  "geometry": {"coordinates":[118.90600000000001,34.2659],"type":"Point"}
}