{
  "type": "Feature",
  "properties": {
    "gn:admin1_code":"11.0",
    "gn:asciiname":"Baichuanyuan",
    "gn:country_code":"CN",
    "gn:dem":316,
    "gn:feature_class":"P",
    "gn:feature_code":"PPL",
    "gn:name":"Baichuanyuan",
    "gn:population":0,
    "gn:timezone":"Asia/Shanghai",
    "iso:country":"CN",
    "name:zho_x_preferred":[
        "\u767d\u5ddd\u56ed"
    ],
    "wof:name":"Baichuanyuan",
    "wof:placetype":"locality"
},
  "geometry": {"coordinates":[110.81870000000001,28.31101],"type":"Point"}
}