{
  "type": "Feature",
  "properties": {
    "gn:admin1_code":"29",
    "gn:asciiname":"Shibanfang",
    "gn:country_code":"CN",
    "gn:dem":1472,
    "gn:feature_class":"P",
    "gn:feature_code":"PPL",
    "gn:name":"Shibanfang",
    "gn:population":0,
    "gn:timezone":"Asia/Shanghai",
    "iso:country":"CN",
    "name:zho_x_preferred":[
        "\u77f3\u677f\u623f"
    ],
    "wof:name":"Shibanfang",
    "wof:placetype":"locality"
},
  "geometry": {"coordinates":[104.524,23.9297],"type":"Point"}
}