{
  "type": "Feature",
  "properties": {
    "gn:admin1_code":"3.0",
    "gn:asciiname":"Miankou",
    "gn:country_code":"CN",
    "gn:dem":115,
    "gn:feature_class":"P",
    "gn:feature_code":"PPL",
    "gn:name":"Miankou",
    "gn:population":0,
    "gn:timezone":"Asia/Shanghai",
    "iso:country":"CN",
    "name:und_x_variant":[
        "\u6c94\u53e3"
    ],
    "wof:name":"Miankou",
    "wof:placetype":"locality"
},
  "geometry": {"coordinates":[115.08481999999999,26.61106],"type":"Point"}
}