{
  "type": "Feature",
  "properties": {
    "gn:admin1_code":"29.0",
    "gn:asciiname":"Kaziqing",
    "gn:country_code":"CN",
    "gn:dem":1580,
    "gn:feature_class":"P",
    "gn:feature_code":"PPL",
    "gn:name":"Kaziqing",
    "gn:population":0,
    "gn:timezone":"Asia/Shanghai",
    "iso:country":"CN",
    "name:zho_x_preferred":[
        "\u5361\u5b50\u7b90"
    ],
    "wof:name":"Kaziqing",
    "wof:placetype":"locality"
},
  "geometry": {"coordinates":[104.346,23.7555],"type":"Point"}
}