{
  "type": "Feature",
  "properties": {
    "gn:admin1_code":"3.0",
    "gn:asciiname":"Maojiaxie",
    "gn:country_code":"CN",
    "gn:dem":361,
    "gn:feature_class":"P",
    "gn:feature_code":"PPL",
    "gn:name":"Maojiaxie",
    "gn:population":0,
    "gn:timezone":"Asia/Shanghai",
    "iso:country":"CN",
    "name:und_x_variant":[
        "\u6bdb\u5bb6\u659c"
    ],
    "wof:name":"Maojiaxie",
    "wof:placetype":"locality"
},
  "geometry": {"coordinates":[116.04971999999999,26.96988],"type":"Point"}
}