{
  "type": "Feature",
  "properties": {
    "gn:admin1_code":"24.0",
    "gn:asciiname":"Haidong",
    "gn:country_code":"CN",
    "gn:dem":792,
    "gn:feature_class":"P",
    "gn:feature_code":"PPL",
    "gn:name":"Haidong",
    "gn:population":0,
    "gn:timezone":"Asia/Shanghai",
    "iso:country":"CN",
    "name:zho_x_preferred":[
        "\u6d77\u4e1c"
    ],
    "wof:name":"Haidong",
    "wof:placetype":"locality"
},
  "geometry": {"coordinates":[112.33195000000001,35.92132],"type":"Point"}
}