{
  "type": "Feature",
  "properties": {
    "gn:admin1_code":"24.0",
    "gn:asciiname":"Haidong",
    "gn:country_code":"CN",
    "gn:dem":792,
    "gn:feature_class":"P",
    "gn:feature_code":"PPL",
    "gn:name":"Haidong",
    "gn:population":0,
    "gn:timezone":"Asia/Shanghai",
    "iso:country":"CN",
    "name:ara_x_preferred":[
        "\u0647\u0627\u064a\u062f\u0648\u0646\u063a"
    ],
    "name:cat_x_preferred":[
        "Haidong"
    ],
    "name:cdo_x_preferred":[
        "H\u0101i-d\u0115\u0324ng"
    ],
    "name:ces_x_preferred":[
        "Chaj-tung"
    ],
    "name:dan_x_preferred":[
        "Haidong"
    ],
    "name:deu_x_preferred":[
        "Haidong"
    ],
    "name:est_x_preferred":[
        "Haidongi ringkond"
    ],
    "name:eus_x_preferred":[
        "Haidong Prefektura"
    ],
    "name:fas_x_preferred":[
        "\u0647\u0627\u06cc\u062f\u0648\u0646\u06af"
    ],
    "name:fin_x_preferred":[
        "Haidong"
    ],
    "name:fra_x_preferred":[
        "Haidong"
    ],
    "name:jpn_x_preferred":[
        "\u6d77\u6771\u5e02"
    ],
    "name:kik_x_preferred":[
        "Haidong"
    ],
    "name:kor_x_preferred":[
        "\ud558\uc774\ub465\uc2dc"
    ],
    "name:mon_x_preferred":[
        "\u0425\u0430\u0439\u0434\u0443\u043d \u0445\u043e\u0442"
    ],
    "name:nld_x_preferred":[
        "Prefectuur Haidong"
    ],
    "name:nor_x_preferred":[
        "Haidong"
    ],
    "name:pol_x_preferred":[
        "Haidong"
    ],
    "name:rus_x_preferred":[
        "\u0425\u0430\u0439\u0434\u0443\u043d"
    ],
    "name:spa_x_preferred":[
        "Haidong"
    ],
    "name:swe_x_preferred":[
        "Haidong"
    ],
    "name:tur_x_preferred":[
        "Haidong"
    ],
    "name:ukr_x_preferred":[
        "\u0425\u0430\u0439\u0434\u0443\u043d"
    ],
    "name:urd_x_preferred":[
        "\u06c1\u0627\u0626\u06cc\u062f\u0648\u0646\u06af"
    ],
    "name:vie_x_preferred":[
        "H\u1ea3i \u0110\u00f4ng"
    ],
    "name:zho_x_preferred":[
        "\u6d77\u4e1c"
    ],
    "name:zho_x_variant":[
        "\u6d77\u4e1c\u5e02"
    ],
    "wof:name":"Haidong",
    "wof:placetype":"locality"
},
  "geometry": {"coordinates":[112.33195000000001,35.92132],"type":"Point"}
}