{
  "type": "Feature",
  "properties": {
    "gn:admin1_code":"08",
    "gn:asciiname":"Wenchun",
    "gn:country_code":"CN",
    "gn:dem":244,
    "gn:feature_class":"P",
    "gn:feature_code":"PPLA4",
    "gn:name":"Wenchun",
    "gn:population":0,
    "gn:timezone":"Asia/Shanghai",
    "iso:country":"CN",
    "name:und_x_variant":[
        "Wen-ch\u2019un-ts\u2019un",
        "Wenchun",
        "Wenchun Zhen"
    ],
    "name:zho_x_preferred":[
        "\u6e29\u6625"
    ],
    "name:zho_x_variant":[
        "\u6e29\u6625\u9547"
    ],
    "wof:name":"Wenchun",
    "wof:placetype":"locality"
},
  "geometry": {"coordinates":[129.48696000000001,44.43013],"type":"Point"}
}