{
  "type": "Feature",
  "properties": {
    "gn:admin1_code":"20.0",
    "gn:asciiname":"Makela",
    "gn:country_code":"CN",
    "gn:dem":296,
    "gn:feature_class":"P",
    "gn:feature_code":"PPL",
    "gn:name":"Makela",
    "gn:population":0,
    "gn:timezone":"Asia/Shanghai",
    "iso:country":"CN",
    "name:zho_x_preferred":[
        "\u9a6c\u514b\u62c9"
    ],
    "wof:name":"Makela",
    "wof:placetype":"locality"
},
  "geometry": {"coordinates":[123.70241,49.09898],"type":"Point"}
}