{
  "type": "Feature",
  "properties": {
    "gn:admin1_code":"29.0",
    "gn:asciiname":"Jiujia",
    "gn:country_code":"CN",
    "gn:dem":1528,
    "gn:feature_class":"P",
    "gn:feature_code":"PPL",
    "gn:name":"Jiujia",
    "gn:population":0,
    "gn:timezone":"Asia/Shanghai",
    "iso:country":"CN",
    "name:zho_x_preferred":[
        "\u65e7\u5bb6"
    ],
    "wof:name":"Jiujia",
    "wof:placetype":"locality"
},
  "geometry": {"coordinates":[100.077,23.1415],"type":"Point"}
}