{
  "type": "Feature",
  "properties": {
    "gn:admin1_code":"12.0",
    "gn:asciiname":"Gujing",
    "gn:country_code":"CN",
    "gn:dem":997,
    "gn:feature_class":"P",
    "gn:feature_code":"PPL",
    "gn:name":"Gujing",
    "gn:population":0,
    "gn:timezone":"Asia/Shanghai",
    "iso:country":"CN",
    "name:zho_x_preferred":[
        "\u53e4\u4e95"
    ],
    "wof:name":"Gujing",
    "wof:placetype":"locality"
},
  "geometry": {"coordinates":[111.53852000000001,31.44704],"type":"Point"}
}