{
  "type": "Feature",
  "properties": {
    "gn:admin1_code":"3.0",
    "gn:asciiname":"Langshudi",
    "gn:country_code":"CN",
    "gn:dem":148,
    "gn:feature_class":"P",
    "gn:feature_code":"PPL",
    "gn:name":"Langshudi",
    "gn:population":0,
    "gn:timezone":"Asia/Shanghai",
    "iso:country":"CN",
    "name:zho_x_preferred":[
        "\u6994\u6811\u5e95"
    ],
    "wof:name":"Langshudi",
    "wof:placetype":"locality"
},
  "geometry": {"coordinates":[117.57798,28.79199],"type":"Point"}
}