{
  "type": "Feature",
  "properties": {
    "gn:admin1_code":"8.0",
    "gn:asciiname":"Jingjia Wopeng",
    "gn:country_code":"CN",
    "gn:dem":269,
    "gn:feature_class":"P",
    "gn:feature_code":"PPL",
    "gn:name":"Jingjia Wopeng",
    "gn:population":0,
    "gn:timezone":"Asia/Shanghai",
    "iso:country":"CN",
    "name:zho_x_preferred":[
        "\u4e95\u5bb6\u7a9d\u68da"
    ],
    "wof:name":"Jingjia Wopeng",
    "wof:placetype":"locality"
},
  "geometry": {"coordinates":[123.18772,47.78163],"type":"Point"}
}