{
  "type": "Feature",
  "properties": {
    "gn:admin1_code":"20.0",
    "gn:asciiname":"Shuangqingshan",
    "gn:country_code":"CN",
    "gn:dem":351,
    "gn:feature_class":"P",
    "gn:feature_code":"PPL",
    "gn:name":"Shuangqingshan",
    "gn:population":0,
    "gn:timezone":"Asia/Shanghai",
    "iso:country":"CN",
    "name:zho_x_preferred":[
        "\u53cc\u9752\u5c71"
    ],
    "wof:name":"Shuangqingshan",
    "wof:placetype":"locality"
},
  "geometry": {"coordinates":[124.01222,49.02972000000001],"type":"Point"}
}