{
  "type": "Feature",
  "properties": {
    "gn:admin1_code":"15.0",
    "gn:asciiname":"Lucaotaizi",
    "gn:country_code":"CN",
    "gn:dem":1748,
    "gn:feature_class":"P",
    "gn:feature_code":"PPL",
    "gn:name":"Lucaotaizi",
    "gn:population":0,
    "gn:timezone":"Asia/Shanghai",
    "iso:country":"CN",
    "name:zho_x_preferred":[
        "\u82a6\u8349\u53f0\u5b50"
    ],
    "wof:name":"Lucaotaizi",
    "wof:placetype":"locality"
},
  "geometry": {"coordinates":[100.655,39.2583],"type":"Point"}
}