{
  "type": "Feature",
  "properties": {
    "gn:admin1_code":"12.0",
    "gn:asciiname":"Yangye",
    "gn:country_code":"CN",
    "gn:dem":28,
    "gn:feature_class":"P",
    "gn:feature_code":"PPLA4",
    "gn:name":"Yangye",
    "gn:population":0,
    "gn:timezone":"Asia/Shanghai",
    "iso:country":"CN",
    "name:und_x_variant":[
        "\u6768\u53f6"
    ],
    "name:zho_x_preferred":[
        "Yangye Zhen"
    ],
    "name:zho_x_variant":[
        "\u6768\u53f6\u9547"
    ],
    "wof:name":"Yangye",
    "wof:placetype":"locality"
},
  "geometry": {"coordinates":[115.06641,30.31506],"type":"Point"}
}