{
  "type": "Feature",
  "properties": {
    "gn:admin1_code":"1.0",
    "gn:asciiname":"Yaozhuangcun",
    "gn:country_code":"CN",
    "gn:dem":30,
    "gn:feature_class":"P",
    "gn:feature_code":"PPL",
    "gn:name":"Yaozhuangcun",
    "gn:population":0,
    "gn:timezone":"Asia/Shanghai",
    "iso:country":"CN",
    "name:zho_x_preferred":[
        "\u7a91\u5e84\u6751"
    ],
    "wof:name":"Yaozhuangcun",
    "wof:placetype":"locality"
},
  "geometry": {"coordinates":[115.95851999999999,33.13952],"type":"Point"}
}