{
  "type": "Feature",
  "properties": {
    "gn:admin1_code":"12.0",
    "gn:asciiname":"Shanhuazui",
    "gn:country_code":"CN",
    "gn:dem":692,
    "gn:feature_class":"P",
    "gn:feature_code":"PPL",
    "gn:name":"Shanhuazui",
    "gn:population":0,
    "gn:timezone":"Asia/Shanghai",
    "iso:country":"CN",
    "name:zho_x_preferred":[
        "\u5c71\u82b1\u5480"
    ],
    "wof:name":"Shanhuazui",
    "wof:placetype":"locality"
},
  "geometry": {"coordinates":[109.84061,30.29922],"type":"Point"}
}