{
  "type": "Feature",
  "properties": {
    "gn:admin1_code":"4.0",
    "gn:asciiname":"Xiaduanshi",
    "gn:country_code":"CN",
    "gn:dem":51,
    "gn:feature_class":"P",
    "gn:feature_code":"PPL",
    "gn:name":"Xiaduanshi",
    "gn:population":0,
    "gn:timezone":"Asia/Shanghai",
    "iso:country":"CN",
    "name:zho_x_preferred":[
        "\u4e0b\u65ad\u77f3"
    ],
    "wof:name":"Xiaduanshi",
    "wof:placetype":"locality"
},
  "geometry": {"coordinates":[118.74522,31.91956],"type":"Point"}
}