{
  "type": "Feature",
  "properties": {
    "gn:admin1_code":"15.0",
    "gn:asciiname":"Mudipo",
    "gn:country_code":"CN",
    "gn:dem":3033,
    "gn:feature_class":"P",
    "gn:feature_code":"PPL",
    "gn:name":"Mudipo",
    "gn:population":0,
    "gn:timezone":"Asia/Shanghai",
    "iso:country":"CN",
    "name:und_x_variant":[
        "\u6728\u5730\u5761"
    ],
    "name:zho_x_preferred":[
        "\u76ee\u5730\u5761"
    ],
    "wof:name":"Mudipo",
    "wof:placetype":"locality"
},
  "geometry": {"coordinates":[103.467,34.7324],"type":"Point"}
}