{
  "type": "Feature",
  "properties": {
    "gn:admin1_code":"12.0",
    "gn:asciiname":"Zhujia Shangwan",
    "gn:country_code":"CN",
    "gn:dem":33,
    "gn:feature_class":"P",
    "gn:feature_code":"PPL",
    "gn:name":"Zhujia Shangwan",
    "gn:population":0,
    "gn:timezone":"Asia/Shanghai",
    "iso:country":"CN",
    "name:und_x_variant":[
        "\u795d\u5bb6\u4e0a\u6e7e"
    ],
    "wof:name":"Zhujia Shangwan",
    "wof:placetype":"locality"
},
  "geometry": {"coordinates":[114.12871,30.8203],"type":"Point"}
}