{
  "type": "Feature",
  "properties": {
    "gn:admin1_code":"18.0",
    "gn:asciiname":"Muyu",
    "gn:country_code":"CN",
    "gn:dem":831,
    "gn:feature_class":"P",
    "gn:feature_code":"PPL",
    "gn:name":"Muyu",
    "gn:population":0,
    "gn:timezone":"Asia/Shanghai",
    "iso:country":"CN",
    "name:zho_x_preferred":[
        "\u6bcd\u6b32"
    ],
    "wof:name":"Muyu",
    "wof:placetype":"locality"
},
  "geometry": {"coordinates":[107.813,25.2622],"type":"Point"}
}