{
  "type": "Feature",
  "properties": {
    "gn:admin1_code":"19.0",
    "gn:asciiname":"Kouzilicun",
    "gn:country_code":"CN",
    "gn:dem":113,
    "gn:feature_class":"P",
    "gn:feature_code":"PPL",
    "gn:name":"Kouzilicun",
    "gn:population":0,
    "gn:timezone":"Asia/Shanghai",
    "iso:country":"CN",
    "name:zho_x_preferred":[
        "\u53e3\u5b50\u91cc\u6751"
    ],
    "wof:name":"Kouzilicun",
    "wof:placetype":"locality"
},
  "geometry": {"coordinates":[124.12907,40.37069],"type":"Point"}
}