{
  "type": "Feature",
  "properties": {
    "gn:admin1_code":"4.0",
    "gn:asciiname":"Pengjingcun",
    "gn:country_code":"CN",
    "gn:dem":27,
    "gn:feature_class":"P",
    "gn:feature_code":"PPL",
    "gn:name":"Pengjingcun",
    "gn:population":0,
    "gn:timezone":"Asia/Shanghai",
    "iso:country":"CN",
    "name:zho_x_preferred":[
        "\u5f6d\u4e95\u6751"
    ],
    "wof:name":"Pengjingcun",
    "wof:placetype":"locality"
},
  "geometry": {"coordinates":[117.81152,33.81988],"type":"Point"}
}