{
  "type": "Feature",
  "properties": {
    "gn:admin1_code":"3.0",
    "gn:asciiname":"Xiajiao",
    "gn:country_code":"CN",
    "gn:dem":60,
    "gn:feature_class":"P",
    "gn:feature_code":"PPL",
    "gn:name":"Xiajiao",
    "gn:population":0,
    "gn:timezone":"Asia/Shanghai",
    "iso:country":"CN",
    "name:und_x_variant":[
        "\u4e0b\u90ca"
    ],
    "wof:name":"Xiajiao",
    "wof:placetype":"locality"
},
  "geometry": {"coordinates":[115.37569000000001,27.19319],"type":"Point"}
}