{
  "type": "Feature",
  "properties": {
    "gn:admin1_code":"26.0",
    "gn:asciiname":"Qiaoshang",
    "gn:country_code":"CN",
    "gn:dem":934,
    "gn:feature_class":"P",
    "gn:feature_code":"PPL",
    "gn:name":"Qiaoshang",
    "gn:population":0,
    "gn:timezone":"Asia/Shanghai",
    "iso:country":"CN",
    "name:und_x_variant":[
        "\u6865\u4e0a"
    ],
    "wof:name":"Qiaoshang",
    "wof:placetype":"locality"
},
  "geometry": {"coordinates":[106.1991,33.26552],"type":"Point"}
}