{
  "type": "Feature",
  "properties": {
    "gn:admin1_code":"33.0",
    "gn:asciiname":"Dabu Liangzi",
    "gn:country_code":"CN",
    "gn:dem":349,
    "gn:feature_class":"P",
    "gn:feature_code":"PPL",
    "gn:name":"Dabu Liangzi",
    "gn:population":0,
    "gn:timezone":"Asia/Shanghai",
    "iso:country":"CN",
    "name:zho_x_preferred":[
        "\u5927\u5821\u6881\u5b50"
    ],
    "wof:name":"Dabu Liangzi",
    "wof:placetype":"locality"
},
  "geometry": {"coordinates":[106.36913,30.16114],"type":"Point"}
}