{
  "type": "Feature",
  "properties": {
    "gn:admin1_code":"16.0",
    "gn:asciiname":"Tunbian",
    "gn:country_code":"CN",
    "gn:dem":315,
    "gn:feature_class":"P",
    "gn:feature_code":"PPL",
    "gn:name":"Tunbian",
    "gn:population":0,
    "gn:timezone":"Asia/Shanghai",
    "iso:country":"CN",
    "name:zho_x_preferred":[
        "\u541e\u4fbf"
    ],
    "wof:name":"Tunbian",
    "wof:placetype":"locality"
},
  "geometry": {"coordinates":[107.93899999999999,23.9063],"type":"Point"}
}