{
  "type": "Feature",
  "properties": {
    "gn:admin1_code":"29.0",
    "gn:asciiname":"Luojia Pingzi",
    "gn:country_code":"CN",
    "gn:dem":1733,
    "gn:feature_class":"P",
    "gn:feature_code":"PPL",
    "gn:name":"Luojia Pingzi",
    "gn:population":0,
    "gn:timezone":"Asia/Shanghai",
    "iso:country":"CN",
    "name:zho_x_preferred":[
        "\u7f57\u5bb6\u576a\u5b50"
    ],
    "wof:name":"Luojia Pingzi",
    "wof:placetype":"locality"
},
  "geometry": {"coordinates":[104.15900000000001,27.2816],"type":"Point"}
}