{
  "type": "Feature",
  "properties": {
    "gn:admin1_code":"2.0",
    "gn:asciiname":"Shejiawu",
    "gn:country_code":"CN",
    "gn:dem":260,
    "gn:feature_class":"P",
    "gn:feature_code":"PPL",
    "gn:name":"Shejiawu",
    "gn:population":0,
    "gn:timezone":"Asia/Shanghai",
    "iso:country":"CN",
    "name:und_x_variant":[
        "\u4f58\u5bb6\u575e",
        "Shejiawu"
    ],
    "wof:name":"Shejiawu",
    "wof:placetype":"locality"
},
  "geometry": {"coordinates":[119.43953,29.69035],"type":"Point"}
}