{
  "type": "Feature",
  "properties": {
    "gn:admin1_code":"16.0",
    "gn:asciiname":"Dadou",
    "gn:country_code":"CN",
    "gn:dem":747,
    "gn:feature_class":"P",
    "gn:feature_code":"PPL",
    "gn:name":"Dadou",
    "gn:population":0,
    "gn:timezone":"Asia/Shanghai",
    "iso:country":"CN",
    "name:ceb_x_preferred":[
        "Dadou"
    ],
    "name:deu_x_preferred":[
        "Dadou"
    ],
    "name:fra_x_preferred":[
        "Dadou"
    ],
    "name:pol_x_preferred":[
        "Dadou"
    ],
    "name:por_x_preferred":[
        "Rio Dadou"
    ],
    "name:srp_x_preferred":[
        "\u0414\u0430\u0434\u0443"
    ],
    "name:zho_x_preferred":[
        "\u5927\u6597"
    ],
    "name:zho_x_variant":[
        "\u9054\u675c\u6cb3"
    ],
    "wof:name":"Dadou",
    "wof:placetype":"locality"
},
  "geometry": {"coordinates":[108.85899999999999,25.3153],"type":"Point"}
}