{
  "type": "Feature",
  "properties": {
    "gn:admin1_code":"3",
    "gn:asciiname":"Shangyuan",
    "gn:country_code":"CN",
    "gn:dem":73,
    "gn:feature_class":"P",
    "gn:feature_code":"PPL",
    "gn:name":"Shangyuan",
    "gn:population":0,
    "gn:timezone":"Asia/Shanghai",
    "iso:country":"CN",
    "name:zho_x_preferred":[
        "\u4e0a\u6e90"
    ],
    "name:zho_x_variant":[
        "\u4e0a\u5143"
    ],
    "wof:name":"Shangyuan",
    "wof:placetype":"locality"
},
  "geometry": {"coordinates":[114.742,26.5997],"type":"Point"}
}