{
  "type": "Feature",
  "properties": {
    "gn:admin1_code":"04",
    "gn:asciiname":"Baduicun",
    "gn:country_code":"CN",
    "gn:dem":3,
    "gn:feature_class":"P",
    "gn:feature_code":"PPLF",
    "gn:name":"Baduicun",
    "gn:population":0,
    "gn:timezone":"Asia/Shanghai",
    "iso:country":"CN",
    "name:und_x_variant":[
        "Pa-tui-yao-chuang",
        "Pa-tzu-yao-chuang",
        "Pa-tui",
        "Badui",
        "\u516b\u961f",
        "Baduicun"
    ],
    "name:zho_x_preferred":[
        "\u516b\u961f\u6751"
    ],
    "wof:name":"Baduicun",
    "wof:placetype":"locality"
},
  "geometry": {"coordinates":[119.73792,34.32830999999999],"type":"Point"}
}