{
  "type": "Feature",
  "properties": {
    "gn:admin1_code":"29.0",
    "gn:asciiname":"Waitaiji",
    "gn:country_code":"CN",
    "gn:dem":2009,
    "gn:feature_class":"P",
    "gn:feature_code":"PPL",
    "gn:name":"Waitaiji",
    "gn:population":0,
    "gn:timezone":"Asia/Shanghai",
    "iso:country":"CN",
    "name:zho_x_preferred":[
        "\u5916\u592a\u5409"
    ],
    "wof:name":"Waitaiji",
    "wof:placetype":"locality"
},
  "geometry": {"coordinates":[101.18000000000001,25.3373],"type":"Point"}
}