{
  "type": "Feature",
  "properties": {
    "gn:admin1_code":"30",
    "gn:asciiname":"Lingwei",
    "gn:country_code":"CN",
    "gn:dem":52,
    "gn:feature_class":"P",
    "gn:feature_code":"PPL",
    "gn:name":"Lingwei",
    "gn:population":0,
    "gn:timezone":"Asia/Urumqi",
    "iso:country":"CN",
    "name:zho_x_preferred":[
        "\u5cad\u5c3e"
    ],
    "wof:name":"Lingwei",
    "wof:placetype":"locality"
},
  "geometry": {"coordinates":[110.19031,21.73156],"type":"Point"}
}