{
  "type": "Feature",
  "properties": {
    "gn:admin1_code":"12.0",
    "gn:asciiname":"Zhuangwuchong",
    "gn:country_code":"CN",
    "gn:dem":40,
    "gn:feature_class":"P",
    "gn:feature_code":"PPL",
    "gn:name":"Zhuangwuchong",
    "gn:population":0,
    "gn:timezone":"Asia/Shanghai",
    "iso:country":"CN",
    "name:zho_x_preferred":[
        "\u5e84\u5c4b\u51b2"
    ],
    "wof:name":"Zhuangwuchong",
    "wof:placetype":"locality"
},
  "geometry": {"coordinates":[113.59713000000001,29.81444],"type":"Point"}
}