{
  "type": "Feature",
  "properties": {
    "gn:admin1_code":"24.0",
    "gn:asciiname":"Yanjiazhuangcun",
    "gn:country_code":"CN",
    "gn:dem":574,
    "gn:feature_class":"P",
    "gn:feature_code":"PPL",
    "gn:name":"Yanjiazhuangcun",
    "gn:population":0,
    "gn:timezone":"Asia/Shanghai",
    "iso:country":"CN",
    "name:zho_x_preferred":[
        "\u95eb\u5bb6\u5e84\u6751"
    ],
    "wof:name":"Yanjiazhuangcun",
    "wof:placetype":"locality"
},
  "geometry": {"coordinates":[110.66952999999999,35.21576],"type":"Point"}
}