{
  "type": "Feature",
  "properties": {
    "gn:admin1_code":"32.0",
    "gn:asciiname":"Chayong",
    "gn:country_code":"CN",
    "gn:dem":3747,
    "gn:feature_class":"P",
    "gn:feature_code":"PPL",
    "gn:name":"Chayong",
    "gn:population":0,
    "gn:timezone":"Asia/Shanghai",
    "iso:country":"CN",
    "name:zho_x_preferred":[
        "\u8336\u62e5"
    ],
    "wof:name":"Chayong",
    "wof:placetype":"locality"
},
  "geometry": {"coordinates":[99.8172,29.2913],"type":"Point"}
}