{
  "type": "Feature",
  "properties": {
    "gn:admin1_code":"25.0",
    "gn:asciiname":"Cheyuankou",
    "gn:country_code":"CN",
    "gn:dem":104,
    "gn:feature_class":"P",
    "gn:feature_code":"PPL",
    "gn:name":"Cheyuankou",
    "gn:population":0,
    "gn:timezone":"Asia/Shanghai",
    "iso:country":"CN",
    "name:zho_x_preferred":[
        "\u8f66\u5143\u53e3"
    ],
    "wof:name":"Cheyuankou",
    "wof:placetype":"locality"
},
  "geometry": {"coordinates":[120.42986000000001,37.17037],"type":"Point"}
}