{
  "type": "Feature",
  "properties": {
    "gn:admin1_code":"12.0",
    "gn:asciiname":"Diluoshu",
    "gn:country_code":"CN",
    "gn:dem":96,
    "gn:feature_class":"P",
    "gn:feature_code":"PPL",
    "gn:name":"Diluoshu",
    "gn:population":0,
    "gn:timezone":"Asia/Shanghai",
    "iso:country":"CN",
    "name:zho_x_preferred":[
        "\u4f4e\u6d1b\u6811"
    ],
    "wof:name":"Diluoshu",
    "wof:placetype":"locality"
},
  "geometry": {"coordinates":[112.02218999999999,31.90362],"type":"Point"}
}