{
  "type": "Feature",
  "properties": {
    "gn:admin1_code":"2.0",
    "gn:asciiname":"Du'aohongjia",
    "gn:country_code":"CN",
    "gn:dem":48,
    "gn:feature_class":"P",
    "gn:feature_code":"PPL",
    "gn:name":"Du\u2019aohongjia",
    "gn:population":0,
    "gn:timezone":"Asia/Shanghai",
    "iso:country":"CN",
    "name:und_x_variant":[
        "Du\u2019aohongjia"
    ],
    "name:zho_x_preferred":[
        "\u675c\u5c99\u6d2a\u5bb6"
    ],
    "wof:name":"Du'aohongjia",
    "wof:placetype":"locality"
},
  "geometry": {"coordinates":[121.36353,30.08029],"type":"Point"}
}