{
  "type": "Feature",
  "properties": {
    "gn:admin1_code":"25",
    "gn:asciiname":"Donghuanghe",
    "gn:country_code":"CN",
    "gn:dem":79,
    "gn:feature_class":"P",
    "gn:feature_code":"PPL",
    "gn:name":"Donghuanghe",
    "gn:population":0,
    "gn:timezone":"Asia/Shanghai",
    "iso:country":"CN",
    "name:zho_x_preferred":[
        "\u4e1c\u9ec4\u6cb3"
    ],
    "wof:name":"Donghuanghe",
    "wof:placetype":"locality"
},
  "geometry": {"coordinates":[118.63,35.0206],"type":"Point"}
}