{
  "type": "Feature",
  "properties": {
    "gn:admin1_code":"12.0",
    "gn:asciiname":"Houtang",
    "gn:country_code":"CN",
    "gn:dem":917,
    "gn:feature_class":"P",
    "gn:feature_code":"PPL",
    "gn:name":"Houtang",
    "gn:population":0,
    "gn:timezone":"Asia/Shanghai",
    "iso:country":"CN",
    "name:zho_x_preferred":[
        "\u540e\u5858"
    ],
    "wof:name":"Houtang",
    "wof:placetype":"locality"
},
  "geometry": {"coordinates":[110.05638999999999,30.46868],"type":"Point"}
}