{
  "type": "Feature",
  "properties": {
    "gn:admin1_code":"8.0",
    "gn:asciiname":"Ershiwuzhancun",
    "gn:country_code":"CN",
    "gn:dem":270,
    "gn:feature_class":"P",
    "gn:feature_code":"PPL",
    "gn:name":"Ershiwuzhancun",
    "gn:population":0,
    "gn:timezone":"Asia/Shanghai",
    "iso:country":"CN",
    "name:zho_x_preferred":[
        "\u4e8c\u5341\u4e94\u7ad9\u6751"
    ],
    "wof:name":"Ershiwuzhancun",
    "wof:placetype":"locality"
},
  "geometry": {"coordinates":[123.80091000000002,53.2735],"type":"Point"}
}