{
  "type": "Feature",
  "properties": {
    "gn:country":"CN",
    "gn:fcode":"PPL",
    "gn:population":77472,
    "iso:country":"CN",
    "name:und_x_variant":[
        "Lin-ch\u2019\u00fc"
    ],
    "qs:name":"\u4e34\u6710",
    "qs:name_adm0":"\u4e2d\u570b",
    "qs:name_adm1":"\u5c71\u4e1c\u7701",
    "qs:photos_9k":1,
    "qs:photos_9r":1,
    "qs:photos_all":14,
    "qs:photos_sr":0,
    "qs:placetype":"Town",
    "qs:pop_sr":"8",
    "wof:name":"\u4e34\u6710",
    "wof:placetype":"locality",
    "wof:population":77472
},
  "geometry": {"coordinates":[118.53972,36.51556],"type":"Point"}
}