{
  "type": "Feature",
  "properties": {
    "gn:admin1_code":"7.0",
    "gn:asciiname":"Changyang",
    "gn:country_code":"CN",
    "gn:dem":830,
    "gn:feature_class":"P",
    "gn:feature_code":"PPL",
    "gn:name":"Changyang",
    "gn:population":0,
    "gn:timezone":"Asia/Shanghai",
    "iso:country":"CN",
    "name:zho_x_preferred":[
        "Changyang"
    ],
    "name:zho_x_variant":[
        "\u957f\u6d0b",
        "\u957f\u9633"
    ],
    "wof:name":"Changyang",
    "wof:placetype":"locality"
},
  "geometry": {"coordinates":[118.93805999999999,26.74694],"type":"Point"}
}