{
  "type": "Feature",
  "properties": {
    "gn:admin1_code":"11.0",
    "gn:asciiname":"Mitangwo",
    "gn:country_code":"CN",
    "gn:dem":624,
    "gn:feature_class":"P",
    "gn:feature_code":"PPL",
    "gn:name":"Mitangwo",
    "gn:population":0,
    "gn:timezone":"Asia/Shanghai",
    "iso:country":"CN",
    "name:zho_x_preferred":[
        "\u5bc6\u7cd6\u7a9d"
    ],
    "wof:name":"Mitangwo",
    "wof:placetype":"locality"
},
  "geometry": {"coordinates":[113.08297,25.51641],"type":"Point"}
}