{
  "type": "Feature",
  "properties": {
    "gn:admin1_code":"32.0",
    "gn:asciiname":"Diaobengyan",
    "gn:country_code":"CN",
    "gn:dem":1295,
    "gn:feature_class":"P",
    "gn:feature_code":"PPL",
    "gn:name":"Diaobengyan",
    "gn:population":0,
    "gn:timezone":"Asia/Shanghai",
    "iso:country":"CN",
    "name:zho_x_preferred":[
        "\u540a\u5d29\u5ca9"
    ],
    "wof:name":"Diaobengyan",
    "wof:placetype":"locality"
},
  "geometry": {"coordinates":[103.24299999999999,29.2772],"type":"Point"}
}