{
  "type": "Feature",
  "properties": {
    "gn:admin1_code":"1.0",
    "gn:asciiname":"Yongshengxucun",
    "gn:country_code":"CN",
    "gn:dem":7,
    "gn:feature_class":"P",
    "gn:feature_code":"PPL",
    "gn:name":"Yongshengxucun",
    "gn:population":0,
    "gn:timezone":"Asia/Shanghai",
    "iso:country":"CN",
    "name:zho_x_preferred":[
        "\u6c38\u80dc\u5729\u6751"
    ],
    "wof:name":"Yongshengxucun",
    "wof:placetype":"locality"
},
  "geometry": {"coordinates":[118.0029,31.39085],"type":"Point"}
}