{
  "type": "Feature",
  "properties": {
    "gn:admin1_code":"32.0",
    "gn:asciiname":"Zuma",
    "gn:country_code":"CN",
    "gn:dem":1712,
    "gn:feature_class":"P",
    "gn:feature_code":"PPL",
    "gn:name":"Zuma",
    "gn:population":0,
    "gn:timezone":"Asia/Shanghai",
    "iso:country":"CN",
    "name:ceb_x_preferred":[
        "Zuma"
    ],
    "name:ces_x_preferred":[
        "Zuma"
    ],
    "name:deu_x_preferred":[
        "Zuma"
    ],
    "name:fra_x_preferred":[
        "Zuma"
    ],
    "name:ita_x_preferred":[
        "Zuma"
    ],
    "name:lav_x_preferred":[
        "Zuma"
    ],
    "name:nds_x_preferred":[
        "Zuma"
    ],
    "name:nld_x_preferred":[
        "Zuma"
    ],
    "name:pol_x_preferred":[
        "Zuma"
    ],
    "name:por_x_preferred":[
        "Zuma"
    ],
    "name:spa_x_preferred":[
        "Zuma"
    ],
    "name:swe_x_preferred":[
        "Zuma"
    ],
    "name:tgl_x_preferred":[
        "Zuma"
    ],
    "name:tur_x_preferred":[
        "Zuma"
    ],
    "name:zho_x_preferred":[
        "\u7956\u9a6c"
    ],
    "wof:name":"Zuma",
    "wof:placetype":"locality"
},
  "geometry": {"coordinates":[103.053,28.8605],"type":"Point"}
}