{
  "type": "Feature",
  "properties": {
    "gn:admin1_code":"32.0",
    "gn:asciiname":"Zuma",
    "gn:country_code":"CN",
    "gn:dem":1712,
    "gn:feature_class":"P",
    "gn:feature_code":"PPL",
    "gn:name":"Zuma",
    "gn:population":0,
    "gn:timezone":"Asia/Shanghai",
    "iso:country":"CN",
    "name:zho_x_preferred":[
        "\u7956\u9a6c"
    ],
    "wof:name":"Zuma",
    "wof:placetype":"locality"
},
  "geometry": {"coordinates":[103.053,28.8605],"type":"Point"}
}