{
  "type": "Feature",
  "properties": {
    "gn:admin1_code":"8.0",
    "gn:asciiname":"Xixiancun",
    "gn:country_code":"CN",
    "gn:dem":156,
    "gn:feature_class":"P",
    "gn:feature_code":"PPL",
    "gn:name":"Xixiancun",
    "gn:population":0,
    "gn:timezone":"Asia/Shanghai",
    "iso:country":"CN",
    "name:zho_x_preferred":[
        "\u5e0c\u8d24\u6751"
    ],
    "wof:name":"Xixiancun",
    "wof:placetype":"locality"
},
  "geometry": {"coordinates":[126.04331000000001,45.30789],"type":"Point"}
}