{
  "type": "Feature",
  "properties": {
    "gn:admin1_code":"12.0",
    "gn:asciiname":"Gengjiawan",
    "gn:country_code":"CN",
    "gn:dem":129,
    "gn:feature_class":"P",
    "gn:feature_code":"PPL",
    "gn:name":"Gengjiawan",
    "gn:population":0,
    "gn:timezone":"Asia/Shanghai",
    "iso:country":"CN",
    "name:zho_x_preferred":[
        "\u803f\u5bb6\u5846"
    ],
    "wof:name":"Gengjiawan",
    "wof:placetype":"locality"
},
  "geometry": {"coordinates":[112.83683000000001,32.02988],"type":"Point"}
}