{
  "type": "Feature",
  "properties": {
    "gn:admin1_code":"24.0",
    "gn:asciiname":"Dongdingwangcun",
    "gn:country_code":"CN",
    "gn:dem":505,
    "gn:feature_class":"P",
    "gn:feature_code":"PPL",
    "gn:name":"Dongdingwangcun",
    "gn:population":0,
    "gn:timezone":"Asia/Shanghai",
    "iso:country":"CN",
    "name:zho_x_preferred":[
        "\u4e1c\u4e01\u738b\u6751"
    ],
    "wof:name":"Dongdingwangcun",
    "wof:placetype":"locality"
},
  "geometry": {"coordinates":[110.5951,35.42492],"type":"Point"}
}