{
  "type": "Feature",
  "properties": {
    "gn:admin1_code":"24.0",
    "gn:asciiname":"Nanjiangcun",
    "gn:country_code":"CN",
    "gn:dem":1206,
    "gn:feature_class":"P",
    "gn:feature_code":"PPL",
    "gn:name":"Nanjiangcun",
    "gn:population":0,
    "gn:timezone":"Asia/Shanghai",
    "iso:country":"CN",
    "name:zho_x_preferred":[
        "\u5357\u848b\u6751"
    ],
    "wof:name":"Nanjiangcun",
    "wof:placetype":"locality"
},
  "geometry": {"coordinates":[113.01018000000001,38.09449],"type":"Point"}
}