{
  "type": "Feature",
  "properties": {
    "gn:admin1_code":"3.0",
    "gn:asciiname":"Tongjia",
    "gn:country_code":"CN",
    "gn:dem":80,
    "gn:feature_class":"P",
    "gn:feature_code":"PPL",
    "gn:name":"Tongjia",
    "gn:population":0,
    "gn:timezone":"Asia/Shanghai",
    "iso:country":"CN",
    "name:zho_x_preferred":[
        "\u7ae5\u5bb6"
    ],
    "wof:name":"Tongjia",
    "wof:placetype":"locality"
},
  "geometry": {"coordinates":[117.51318999999999,28.67653],"type":"Point"}
}