{
  "type": "Feature",
  "properties": {
    "gn:admin1_code":"15.0",
    "gn:asciiname":"Daquan",
    "gn:cc2":"CN",
    "gn:country_code":"CN",
    "gn:dem":1767,
    "gn:feature_class":"P",
    "gn:feature_code":"PPL",
    "gn:name":"Daquan",
    "gn:population":0,
    "gn:timezone":"Asia/Urumqi",
    "iso:country":"CN",
    "name:und_x_variant":[
        "Ta-ch\u2019\u00fcan",
        "Datsyuan\u2019",
        "Daquan"
    ],
    "wof:name":"Daquan",
    "wof:placetype":"locality"
},
  "geometry": {"coordinates":[95.25,41.31667],"type":"Point"}
}