{
  "type": "Feature",
  "properties": {
    "gn:admin1_code":"11",
    "gn:asciiname":"Lengshuidong",
    "gn:country_code":"CN",
    "gn:dem":85,
    "gn:feature_class":"P",
    "gn:feature_code":"PPL",
    "gn:name":"Lengshuidong",
    "gn:population":0,
    "gn:timezone":"Asia/Shanghai",
    "iso:country":"CN",
    "name:und_x_variant":[
        "Lengshui",
        "Lengshuidong"
    ],
    "name:zho_x_preferred":[
        "\u51b7\u6c34\u6d1e"
    ],
    "wof:name":"Lengshuidong",
    "wof:placetype":"locality"
},
  "geometry": {"coordinates":[112.38923,26.38627],"type":"Point"}
}