{
  "type": "Feature",
  "properties": {
    "gn:admin1_code":"32",
    "gn:asciiname":"Yongfengchang",
    "gn:country_code":"CN",
    "gn:dem":406,
    "gn:feature_class":"P",
    "gn:feature_code":"PPL",
    "gn:name":"Yongfengchang",
    "gn:population":0,
    "gn:timezone":"Asia/Shanghai",
    "iso:country":"CN",
    "name:und_x_variant":[
        "Wenfeng",
        "Yongfengchang"
    ],
    "name:zho_x_preferred":[
        "\u6c38\u5cf0\u573a"
    ],
    "wof:name":"Yongfengchang",
    "wof:placetype":"locality"
},
  "geometry": {"coordinates":[105.19486999999999,29.85753],"type":"Point"}
}