{
  "type": "Feature",
  "properties": {
    "gn:admin1_code":"30.0",
    "gn:asciiname":"Chang'an",
    "gn:country_code":"CN",
    "gn:dem":14,
    "gn:feature_class":"P",
    "gn:feature_code":"PPL",
    "gn:name":"Chang\u2019an",
    "gn:population":0,
    "gn:timezone":"Asia/Shanghai",
    "iso:country":"CN",
    "name:und_x_variant":[
        "Chang\u2019an"
    ],
    "name:zho_x_preferred":[
        "\u9577\u5b89"
    ],
    "wof:name":"Chang'an",
    "wof:placetype":"locality"
},
  "geometry": {"coordinates":[112.66278,22.31732],"type":"Point"}
}