{
  "type": "Feature",
  "properties": {
    "gn:admin1_code":"30.0",
    "gn:asciiname":"Youkeng",
    "gn:country_code":"CN",
    "gn:dem":322,
    "gn:feature_class":"P",
    "gn:feature_code":"PPL",
    "gn:name":"Youkeng",
    "gn:population":0,
    "gn:timezone":"Asia/Shanghai",
    "iso:country":"CN",
    "name:zho_x_preferred":[
        "Youkeng"
    ],
    "name:zho_x_variant":[
        "\u53f3\u5751"
    ],
    "wof:name":"Youkeng",
    "wof:placetype":"locality"
},
  "geometry": {"coordinates":[114.72911000000001,24.32439],"type":"Point"}
}