{
  "type": "Feature",
  "properties": {
    "gn:admin1_code":"11.0",
    "gn:asciiname":"Maoshan",
    "gn:country_code":"CN",
    "gn:dem":929,
    "gn:feature_class":"P",
    "gn:feature_code":"PPL",
    "gn:name":"Maoshan",
    "gn:population":0,
    "gn:timezone":"Asia/Shanghai",
    "iso:country":"CN",
    "name:zho_x_preferred":[
        "\u732b\u5c71"
    ],
    "wof:name":"Maoshan",
    "wof:placetype":"locality"
},
  "geometry": {"coordinates":[112.63755999999999,27.1799],"type":"Point"}
}