{
  "type": "Feature",
  "properties": {
    "gn:admin1_code":"15.0",
    "gn:asciiname":"Congdi",
    "gn:country_code":"CN",
    "gn:dem":2753,
    "gn:feature_class":"P",
    "gn:feature_code":"PPL",
    "gn:name":"Congdi",
    "gn:population":0,
    "gn:timezone":"Asia/Shanghai",
    "iso:country":"CN",
    "name:und_x_variant":[
        "\u8471\u5730"
    ],
    "wof:name":"Congdi",
    "wof:placetype":"locality"
},
  "geometry": {"coordinates":[103.42,34.12105],"type":"Point"}
}