{
  "type": "Feature",
  "properties": {
    "gn:admin1_code":"24.0",
    "gn:asciiname":"Mengjiatacun",
    "gn:country_code":"CN",
    "gn:dem":959,
    "gn:feature_class":"P",
    "gn:feature_code":"PPL",
    "gn:name":"Mengjiatacun",
    "gn:population":0,
    "gn:timezone":"Asia/Shanghai",
    "iso:country":"CN",
    "name:zho_x_preferred":[
        "\u5b5f\u5bb6\u584c\u6751"
    ],
    "wof:name":"Mengjiatacun",
    "wof:placetype":"locality"
},
  "geometry": {"coordinates":[110.80916999999999,37.03657000000001],"type":"Point"}
}