{
  "type": "Feature",
  "properties": {
    "gn:admin1_code":"02",
    "gn:asciiname":"Liuke",
    "gn:country_code":"CN",
    "gn:dem":221,
    "gn:feature_class":"P",
    "gn:feature_code":"PPL",
    "gn:name":"Liuke",
    "gn:population":0,
    "gn:timezone":"Asia/Shanghai",
    "iso:country":"CN",
    "name:zho_x_preferred":[
        "Liu-k\u2019o-ts\u2019un"
    ],
    "name:zho_x_variant":[
        "\u516d\u79d1"
    ],
    "wof:name":"Liuke",
    "wof:placetype":"locality"
},
  "geometry": {"coordinates":[120.32761000000001,27.92828],"type":"Point"}
}