{
  "type": "Feature",
  "properties": {
    "gn:admin1_code":"30.0",
    "gn:asciiname":"Kuibeicun",
    "gn:country_code":"CN",
    "gn:dem":40,
    "gn:feature_class":"P",
    "gn:feature_code":"PPL",
    "gn:name":"Kuibeicun",
    "gn:population":0,
    "gn:timezone":"Asia/Shanghai",
    "iso:country":"CN",
    "name:zho_x_preferred":[
        "Kuibei"
    ],
    "name:zho_x_variant":[
        "\u8475\u80cc",
        "\u8475\u80cc\u6751"
    ],
    "wof:name":"Kuibeicun",
    "wof:placetype":"locality"
},
  "geometry": {"coordinates":[112.80222000000001,23.63222],"type":"Point"}
}