{
  "type": "Feature",
  "properties": {
    "gn:admin1_code":"9.0",
    "gn:asciiname":"Dongguanzhuang",
    "gn:country_code":"CN",
    "gn:dem":386,
    "gn:feature_class":"P",
    "gn:feature_code":"PPL",
    "gn:name":"Dongguanzhuang",
    "gn:population":0,
    "gn:timezone":"Asia/Shanghai",
    "iso:country":"CN",
    "name:zho_x_preferred":[
        "\u4e1c\u5b98\u5e84"
    ],
    "wof:name":"Dongguanzhuang",
    "wof:placetype":"locality"
},
  "geometry": {"coordinates":[112.13682,34.32455],"type":"Point"}
}