{
  "type": "Feature",
  "properties": {
    "gn:admin1_code":"30.0",
    "gn:asciiname":"Tielujing",
    "gn:country_code":"CN",
    "gn:dem":167,
    "gn:feature_class":"P",
    "gn:feature_code":"PPL",
    "gn:name":"Tielujing",
    "gn:population":0,
    "gn:timezone":"Asia/Shanghai",
    "iso:country":"CN",
    "name:zho_x_preferred":[
        "\u94c1\u7089\u5f84"
    ],
    "wof:name":"Tielujing",
    "wof:placetype":"locality"
},
  "geometry": {"coordinates":[114.76363000000001,23.34089],"type":"Point"}
}