{
  "type": "Feature",
  "properties": {
    "gn:admin1_code":"18",
    "gn:asciiname":"Badeng",
    "gn:country_code":"CN",
    "gn:dem":461,
    "gn:feature_class":"P",
    "gn:feature_code":"PPL",
    "gn:name":"Badeng",
    "gn:population":0,
    "gn:timezone":"Asia/Shanghai",
    "iso:country":"CN",
    "name:zho_x_preferred":[
        "\u628a\u7b49"
    ],
    "wof:name":"Badeng",
    "wof:placetype":"locality"
},
  "geometry": {"coordinates":[106.58,25.201],"type":"Point"}
}