{
  "type": "Feature",
  "properties": {
    "gn:admin1_code":"15.0",
    "gn:asciiname":"Liyuanpan",
    "gn:country_code":"CN",
    "gn:dem":1733,
    "gn:feature_class":"P",
    "gn:feature_code":"PPL",
    "gn:name":"Liyuanpan",
    "gn:population":0,
    "gn:timezone":"Asia/Shanghai",
    "iso:country":"CN",
    "name:und_x_variant":[
        "\u674e\u586c\u7554"
    ],
    "wof:name":"Liyuanpan",
    "wof:placetype":"locality"
},
  "geometry": {"coordinates":[107.50740999999999,36.86491],"type":"Point"}
}