{
  "type": "Feature",
  "properties": {
    "gn:admin1_code":"30.0",
    "gn:asciiname":"Zoumaling",
    "gn:country_code":"CN",
    "gn:dem":184,
    "gn:feature_class":"P",
    "gn:feature_code":"PPL",
    "gn:name":"Zoumaling",
    "gn:population":0,
    "gn:timezone":"Asia/Shanghai",
    "iso:country":"CN",
    "name:zho_x_preferred":[
        "Zoumaling"
    ],
    "name:zho_x_variant":[
        "\u8d70\u9a6c\u5cad"
    ],
    "wof:name":"Zoumaling",
    "wof:placetype":"locality"
},
  "geometry": {"coordinates":[113.11083000000001,25.32694],"type":"Point"}
}