{
  "type": "Feature",
  "properties": {
    "gn:admin1_code":"7.0",
    "gn:asciiname":"Qixing",
    "gn:country_code":"CN",
    "gn:dem":514,
    "gn:feature_class":"P",
    "gn:feature_code":"PPL",
    "gn:name":"Qixing",
    "gn:population":0,
    "gn:timezone":"Asia/Shanghai",
    "iso:country":"CN",
    "name:zho_x_preferred":[
        "\u65d7\u661f"
    ],
    "wof:name":"Qixing",
    "wof:placetype":"locality"
},
  "geometry": {"coordinates":[118.49002,25.28948],"type":"Point"}
}