{
  "type": "Feature",
  "properties": {
    "gn:admin1_code":"29.0",
    "gn:asciiname":"Yantang",
    "gn:country_code":"CN",
    "gn:dem":1980,
    "gn:feature_class":"P",
    "gn:feature_code":"PPL",
    "gn:name":"Yantang",
    "gn:population":0,
    "gn:timezone":"Asia/Shanghai",
    "iso:country":"CN",
    "name:ceb_x_preferred":[
        "Yantang"
    ],
    "name:deu_x_preferred":[
        "Yantang"
    ],
    "name:swe_x_preferred":[
        "Yantang"
    ],
    "name:zho_x_preferred":[
        "\u76d0\u5858"
    ],
    "wof:name":"Yantang",
    "wof:placetype":"locality"
},
  "geometry": {"coordinates":[103.55800000000001,26.2818],"type":"Point"}
}