{
  "type": "Feature",
  "properties": {
    "gn:admin1_code":"24.0",
    "gn:asciiname":"Zhuanqu",
    "gn:country_code":"CN",
    "gn:dem":802,
    "gn:feature_class":"P",
    "gn:feature_code":"PPL",
    "gn:name":"Zhuanqu",
    "gn:population":0,
    "gn:timezone":"Asia/Shanghai",
    "iso:country":"CN",
    "name:zho_x_preferred":[
        "\u8f6c\u66f2"
    ],
    "wof:name":"Zhuanqu",
    "wof:placetype":"locality"
},
  "geometry": {"coordinates":[110.97371,35.69557000000001],"type":"Point"}
}