{
  "type": "Feature",
  "properties": {
    "gn:admin1_code":"4.0",
    "gn:asciiname":"Siding",
    "gn:country_code":"CN",
    "gn:dem":25,
    "gn:feature_class":"P",
    "gn:feature_code":"PPL",
    "gn:name":"Siding",
    "gn:population":0,
    "gn:timezone":"Asia/Shanghai",
    "iso:country":"CN",
    "name:deu_x_preferred":[
        "Holzfassade"
    ],
    "name:fra_x_preferred":[
        "Bardage"
    ],
    "name:pol_x_preferred":[
        "Siding"
    ],
    "name:rus_x_preferred":[
        "\u0421\u0430\u0439\u0434\u0438\u043d\u0433"
    ],
    "name:tat_x_preferred":[
        "\u0421\u0430\u0439\u0434\u0438\u043d\u0433"
    ],
    "name:zho_x_preferred":[
        "\u56db\u4e01"
    ],
    "wof:name":"Siding",
    "wof:placetype":"locality"
},
  "geometry": {"coordinates":[118.113,33.887],"type":"Point"}
}