{
  "type": "Feature",
  "properties": {
    "gn:admin1_code":"21.0",
    "gn:asciiname":"Honggeda",
    "gn:country_code":"CN",
    "gn:dem":1485,
    "gn:feature_class":"P",
    "gn:feature_code":"PPL",
    "gn:name":"Honggeda",
    "gn:population":0,
    "gn:timezone":"Asia/Shanghai",
    "iso:country":"CN",
    "name:zho_x_preferred":[
        "\u7ea2\u572a\u7629"
    ],
    "wof:name":"Honggeda",
    "wof:placetype":"locality"
},
  "geometry": {"coordinates":[107.09099999999999,38.0841],"type":"Point"}
}