{
  "type": "Feature",
  "properties": {
    "gn:admin1_code":"14.0",
    "gn:asciiname":"Gomang",
    "gn:country_code":"CN",
    "gn:dem":4740,
    "gn:feature_class":"P",
    "gn:feature_code":"PPLF",
    "gn:name":"Gomang",
    "gn:population":0,
    "gn:timezone":"Asia/Urumqi",
    "iso:country":"CN",
    "name:bod_x_preferred":[
        "Gomang"
    ],
    "name:zho_x_preferred":[
        "Guomang"
    ],
    "name:zho_x_variant":[
        "\u679c\u8292",
        "Naguo",
        "\u90a3\u679c"
    ],
    "wof:name":"Gomang",
    "wof:placetype":"locality"
},
  "geometry": {"coordinates":[89.90100000000002,31.601],"type":"Point"}
}