{
  "type": "Feature",
  "properties": {
    "gn:admin1_code":"32.0",
    "gn:asciiname":"Xiangjiahe",
    "gn:country_code":"CN",
    "gn:dem":384,
    "gn:feature_class":"P",
    "gn:feature_code":"PPL",
    "gn:name":"Xiangjiahe",
    "gn:population":0,
    "gn:timezone":"Asia/Shanghai",
    "iso:country":"CN",
    "name:zho_x_preferred":[
        "\u5411\u5bb6\u6cb3"
    ],
    "wof:name":"Xiangjiahe",
    "wof:placetype":"locality"
},
  "geometry": {"coordinates":[105.33499999999999,29.3838],"type":"Point"}
}