{
  "type": "Feature",
  "properties": {
    "gn:admin1_code":"1.0",
    "gn:asciiname":"Fangyuan",
    "gn:country_code":"CN",
    "gn:dem":43,
    "gn:feature_class":"P",
    "gn:feature_code":"PPL",
    "gn:name":"Fangyuan",
    "gn:population":0,
    "gn:timezone":"Asia/Shanghai",
    "iso:country":"CN",
    "name:hak_x_preferred":[
        "F\u00f4ng-yen-hi\u00f4ng"
    ],
    "name:ita_x_preferred":[
        "Fangyuan"
    ],
    "name:jpn_x_preferred":[
        "\u82b3\u82d1\u90f7"
    ],
    "name:kor_x_preferred":[
        "\ud321\uc704\uc548\ud5a5"
    ],
    "name:pol_x_preferred":[
        "Fangyuan"
    ],
    "name:vie_x_preferred":[
        "Ph\u01b0\u01a1ng Uy\u1ec3n"
    ],
    "name:zho_x_preferred":[
        "\u65b9\u56ed"
    ],
    "name:zho_x_variant":[
        "\u82b3\u82d1\u9109"
    ],
    "wof:name":"Fangyuan",
    "wof:placetype":"locality"
},
  "geometry": {"coordinates":[115.79528999999999,33.86353],"type":"Point"}
}