{
  "type": "Feature",
  "properties": {
    "gn:admin1_code":"26",
    "gn:asciiname":"Jinjiayao",
    "gn:country_code":"CN",
    "gn:dem":399,
    "gn:feature_class":"P",
    "gn:feature_code":"PPL",
    "gn:name":"Jinjiayao",
    "gn:population":0,
    "gn:timezone":"Asia/Shanghai",
    "iso:country":"CN",
    "name:und_x_variant":[
        "\u91d1\u5bb6\u5c27",
        "Jinjiayao"
    ],
    "wof:name":"Jinjiayao",
    "wof:placetype":"locality"
},
  "geometry": {"coordinates":[109.10903999999999,34.65847],"type":"Point"}
}