{
  "type": "Feature",
  "properties": {
    "gn:admin1_code":"25",
    "gn:asciiname":"Mujia",
    "gn:country_code":"CN",
    "gn:dem":16,
    "gn:feature_class":"P",
    "gn:feature_code":"PPL",
    "gn:name":"Mujia",
    "gn:population":0,
    "gn:timezone":"Asia/Shanghai",
    "iso:country":"CN",
    "name:zho_x_preferred":[
        "\u7a46\u5bb6"
    ],
    "wof:name":"Mujia",
    "wof:placetype":"locality"
},
  "geometry": {"coordinates":[117.066,37.4852],"type":"Point"}
}