{
  "type": "Feature",
  "properties": {
    "gn:admin1_code":"9.0",
    "gn:asciiname":"Kejiapo",
    "gn:country_code":"CN",
    "gn:dem":303,
    "gn:feature_class":"P",
    "gn:feature_code":"PPL",
    "gn:name":"Kejiapo",
    "gn:population":0,
    "gn:timezone":"Asia/Shanghai",
    "iso:country":"CN",
    "name:zho_x_preferred":[
        "\u67ef\u5bb6\u5761"
    ],
    "wof:name":"Kejiapo",
    "wof:placetype":"locality"
},
  "geometry": {"coordinates":[111.26938,32.93648],"type":"Point"}
}