{
  "type": "Feature",
  "properties": {
    "gn:admin1_code":"9",
    "gn:asciiname":"Dongjindian",
    "gn:country_code":"CN",
    "gn:dem":306,
    "gn:feature_class":"P",
    "gn:feature_code":"PPL",
    "gn:name":"Dongjindian",
    "gn:population":0,
    "gn:timezone":"Asia/Shanghai",
    "iso:country":"CN",
    "wof:name":"Dongjindian",
    "wof:placetype":"locality"
},
  "geometry": {"coordinates":[113.04277999999999,34.37694],"type":"Point"}
}