{
  "type": "Feature",
  "properties": {
    "gn:admin1_code":"3.0",
    "gn:asciiname":"Zishan",
    "gn:country_code":"CN",
    "gn:dem":129,
    "gn:feature_class":"P",
    "gn:feature_code":"PPLA4",
    "gn:name":"Zishan",
    "gn:population":0,
    "gn:timezone":"Asia/Shanghai",
    "iso:country":"CN",
    "name:und_x_variant":[
        "Tzeshansu",
        "Tzu-shan",
        "Tzu-shan-hs\u00fc",
        "Tzu-shan-shih",
        "Zishan",
        "\u6893\u5c71",
        "Zishan Zhen",
        "\u6893\u5c71\u9547"
    ],
    "wof:name":"Zishan",
    "wof:placetype":"locality"
},
  "geometry": {"coordinates":[115.54122,25.95995],"type":"Point"}
}