{
  "type": "Feature",
  "properties": {
    "gn:admin1_code":"4.0",
    "gn:asciiname":"Houmengcun",
    "gn:country_code":"CN",
    "gn:dem":40,
    "gn:feature_class":"P",
    "gn:feature_code":"PPL",
    "gn:name":"Houmengcun",
    "gn:population":0,
    "gn:timezone":"Asia/Shanghai",
    "iso:country":"CN",
    "name:zho_x_preferred":[
        "\u540e\u5b5f\u6751"
    ],
    "wof:name":"Houmengcun",
    "wof:placetype":"locality"
},
  "geometry": {"coordinates":[116.85889,34.67273],"type":"Point"}
}