{
  "type": "Feature",
  "properties": {
    "gn:admin1_code":"11.0",
    "gn:asciiname":"Niaotang",
    "gn:country_code":"CN",
    "gn:dem":455,
    "gn:feature_class":"P",
    "gn:feature_code":"PPL",
    "gn:name":"Niaotang",
    "gn:population":0,
    "gn:timezone":"Asia/Shanghai",
    "iso:country":"CN",
    "name:zho_x_preferred":[
        "\u9e1f\u5858"
    ],
    "wof:name":"Niaotang",
    "wof:placetype":"locality"
},
  "geometry": {"coordinates":[110.28998,26.51684],"type":"Point"}
}