{
  "type": "Feature",
  "properties": {
    "gn:admin1_code":"12.0",
    "gn:asciiname":"Tianpuwan",
    "gn:country_code":"CN",
    "gn:dem":59,
    "gn:feature_class":"P",
    "gn:feature_code":"PPL",
    "gn:name":"Tianpuwan",
    "gn:population":0,
    "gn:timezone":"Asia/Shanghai",
    "iso:country":"CN",
    "name:und_x_variant":[
        "\u7530\u94fa\u5846"
    ],
    "wof:name":"Tianpuwan",
    "wof:placetype":"locality"
},
  "geometry": {"coordinates":[114.97494,30.87225],"type":"Point"}
}