{
  "type": "Feature",
  "properties": {
    "gn:admin1_code":"16.0",
    "gn:asciiname":"Gongguinao",
    "gn:country_code":"CN",
    "gn:dem":372,
    "gn:feature_class":"P",
    "gn:feature_code":"PPL",
    "gn:name":"Gongguinao",
    "gn:population":0,
    "gn:timezone":"Asia/Shanghai",
    "iso:country":"CN",
    "name:zho_x_preferred":[
        "\u516c\u8d35\u8111"
    ],
    "wof:name":"Gongguinao",
    "wof:placetype":"locality"
},
  "geometry": {"coordinates":[110.886,24.0241],"type":"Point"}
}