{
  "type": "Feature",
  "properties": {
    "gn:admin1_code":"23",
    "gn:asciiname":"Dianfeng",
    "gn:country_code":"CN",
    "gn:dem":6,
    "gn:feature_class":"P",
    "gn:feature_code":"PPL",
    "gn:name":"Dianfeng",
    "gn:population":0,
    "gn:timezone":"Asia/Shanghai",
    "iso:country":"CN",
    "name:und_x_variant":[
        "\u6dc0\u5cf0"
    ],
    "wof:name":"Dianfeng",
    "wof:placetype":"locality"
},
  "geometry": {"coordinates":[120.98715,31.08997],"type":"Point"}
}