{
  "type": "Feature",
  "properties": {
    "gn:admin1_code":"11.0",
    "gn:asciiname":"Angdonghu",
    "gn:country_code":"CN",
    "gn:dem":539,
    "gn:feature_class":"P",
    "gn:feature_code":"PPL",
    "gn:name":"Angdonghu",
    "gn:population":0,
    "gn:timezone":"Asia/Shanghai",
    "iso:country":"CN",
    "name:zho_x_preferred":[
        "\u6602\u6d1e\u6e56"
    ],
    "wof:name":"Angdonghu",
    "wof:placetype":"locality"
},
  "geometry": {"coordinates":[109.56690999999999,28.78611],"type":"Point"}
}