{
  "type": "Feature",
  "properties": {
    "gn:admin1_code":"21.0",
    "gn:asciiname":"Xixiangzi",
    "gn:country_code":"CN",
    "gn:dem":1799,
    "gn:feature_class":"P",
    "gn:feature_code":"PPL",
    "gn:name":"Xixiangzi",
    "gn:population":0,
    "gn:timezone":"Asia/Shanghai",
    "iso:country":"CN",
    "name:und_x_variant":[
        "\u897f\u5df7\u5b50"
    ],
    "name:zho_x_preferred":[
        "\u897f\u5df7\u5b50"
    ],
    "wof:name":"Xixiangzi",
    "wof:placetype":"locality"
},
  "geometry": {"coordinates":[106.25364999999999,36.43639],"type":"Point"}
}