{
  "type": "Feature",
  "properties": {
    "gn:admin1_code":"7",
    "gn:asciiname":"Xiahu",
    "gn:country_code":"CN",
    "gn:dem":46,
    "gn:feature_class":"P",
    "gn:feature_code":"PPL",
    "gn:name":"Xiahu",
    "gn:population":0,
    "gn:timezone":"Asia/Shanghai",
    "iso:country":"CN",
    "name:und_x_variant":[
        "\u4e0b\u6e56"
    ],
    "wof:name":"Xiahu",
    "wof:placetype":"locality"
},
  "geometry": {"coordinates":[120.31083,26.93472],"type":"Point"}
}