{
  "type": "Feature",
  "properties": {
    "gn:admin1_code":"4.0",
    "gn:asciiname":"Xu'erfang",
    "gn:country_code":"CN",
    "gn:dem":5,
    "gn:feature_class":"P",
    "gn:feature_code":"PPL",
    "gn:name":"Xu\u2019erfang",
    "gn:population":0,
    "gn:timezone":"Asia/Shanghai",
    "iso:country":"CN",
    "name:und_x_variant":[
        "Xu\u2019erfang"
    ],
    "name:zho_x_preferred":[
        "\u5f90\u4e8c\u623f"
    ],
    "wof:name":"Xu'erfang",
    "wof:placetype":"locality"
},
  "geometry": {"coordinates":[119.36641000000002,32.30781],"type":"Point"}
}