{
  "type": "Feature",
  "properties": {
    "gn:admin1_code":"3.0",
    "gn:asciiname":"Xiaxinwu",
    "gn:country_code":"CN",
    "gn:dem":245,
    "gn:feature_class":"P",
    "gn:feature_code":"PPL",
    "gn:name":"Xiaxinwu",
    "gn:population":0,
    "gn:timezone":"Asia/Shanghai",
    "iso:country":"CN",
    "name:und_x_variant":[
        "\u4e0b\u65b0\u5c4b"
    ],
    "wof:name":"Xiaxinwu",
    "wof:placetype":"locality"
},
  "geometry": {"coordinates":[116.12063000000001,26.13941],"type":"Point"}
}