{
  "type": "Feature",
  "properties": {
    "gn:admin1_code":"32.0",
    "gn:asciiname":"Shifanzeng",
    "gn:country_code":"CN",
    "gn:dem":642,
    "gn:feature_class":"P",
    "gn:feature_code":"PPL",
    "gn:name":"Shifanzeng",
    "gn:population":0,
    "gn:timezone":"Asia/Shanghai",
    "iso:country":"CN",
    "name:zho_x_preferred":[
        "\u77f3\u996d\u7511"
    ],
    "wof:name":"Shifanzeng",
    "wof:placetype":"locality"
},
  "geometry": {"coordinates":[106.00521000000001,28.84114000000001],"type":"Point"}
}