{
  "type": "Feature",
  "properties": {
    "gn:admin1_code":"18",
    "gn:asciiname":"Ranjiaoba",
    "gn:country_code":"CN",
    "gn:dem":676,
    "gn:feature_class":"P",
    "gn:feature_code":"PPL",
    "gn:name":"Ranjiaoba",
    "gn:population":0,
    "gn:timezone":"Asia/Shanghai",
    "iso:country":"CN",
    "name:zho_x_preferred":[
        "\u5189\u89d2\u575d"
    ],
    "wof:name":"Ranjiaoba",
    "wof:placetype":"locality"
},
  "geometry": {"coordinates":[107.602,28.8802],"type":"Point"}
}