{
  "type": "Feature",
  "properties": {
    "gn:admin1_code":"10.0",
    "gn:asciiname":"Xihuangni",
    "gn:country_code":"CN",
    "gn:dem":218,
    "gn:feature_class":"P",
    "gn:feature_code":"PPL",
    "gn:name":"Xihuangni",
    "gn:population":0,
    "gn:timezone":"Asia/Shanghai",
    "iso:country":"CN",
    "name:zho_x_preferred":[
        "\u897f\u9ec4\u6ce5"
    ],
    "wof:name":"Xihuangni",
    "wof:placetype":"locality"
},
  "geometry": {"coordinates":[113.8604,38.35202],"type":"Point"}
}