{
  "type": "Feature",
  "properties": {
    "gn:admin1_code":"29.0",
    "gn:asciiname":"Xinjin",
    "gn:country_code":"CN",
    "gn:dem":1950,
    "gn:feature_class":"P",
    "gn:feature_code":"PPL",
    "gn:name":"Xinjin",
    "gn:population":0,
    "gn:timezone":"Asia/Shanghai",
    "iso:country":"CN",
    "name:zho_x_preferred":[
        "\u65b0\u8fdb"
    ],
    "wof:name":"Xinjin",
    "wof:placetype":"locality"
},
  "geometry": {"coordinates":[100.23399999999999,24.7886],"type":"Point"}
}