{
  "type": "Feature",
  "properties": {
    "gn:admin1_code":"32.0",
    "gn:asciiname":"Zuangen",
    "gn:country_code":"CN",
    "gn:dem":2694,
    "gn:feature_class":"P",
    "gn:feature_code":"PPL",
    "gn:name":"Zuangen",
    "gn:population":0,
    "gn:timezone":"Asia/Shanghai",
    "iso:country":"CN",
    "name:zho_x_preferred":[
        "\u94bb\u6839"
    ],
    "wof:name":"Zuangen",
    "wof:placetype":"locality"
},
  "geometry": {"coordinates":[100.593,28.537],"type":"Point"}
}