{
  "type": "Feature",
  "properties": {
    "gn:admin1_code":"10",
    "gn:asciiname":"Yu-shu-kou",
    "gn:country_code":"CN",
    "gn:dem":431,
    "gn:feature_class":"P",
    "gn:feature_code":"PPL",
    "gn:name":"Y\u00fc-shu-kou",
    "gn:population":0,
    "gn:timezone":"Asia/Shanghai",
    "iso:country":"CN",
    "wof:name":"Yu-shu-kou",
    "wof:placetype":"locality"
},
  "geometry": {"coordinates":[117.71528000000001,40.58778],"type":"Point"}
}