{
  "type": "Feature",
  "properties": {
    "gn:admin1_code":"25",
    "gn:asciiname":"Xixinzhuang",
    "gn:country_code":"CN",
    "gn:dem":146,
    "gn:feature_class":"P",
    "gn:feature_code":"PPL",
    "gn:name":"Xixinzhuang",
    "gn:population":0,
    "gn:timezone":"Asia/Shanghai",
    "iso:country":"CN",
    "name:zho_x_preferred":[
        "\u897f\u8f9b\u5e84"
    ],
    "wof:name":"Xixinzhuang",
    "wof:placetype":"locality"
},
  "geometry": {"coordinates":[118.24299999999999,35.6441],"type":"Point"}
}