{
  "type": "Feature",
  "properties": {
    "gn:admin1_code":"19.0",
    "gn:asciiname":"Dachaocun",
    "gn:country_code":"CN",
    "gn:dem":15,
    "gn:feature_class":"P",
    "gn:feature_code":"PPL",
    "gn:name":"Dachaocun",
    "gn:population":0,
    "gn:timezone":"Asia/Shanghai",
    "iso:country":"CN",
    "name:zho_x_preferred":[
        "\u8fbe\u671d\u6751"
    ],
    "wof:name":"Dachaocun",
    "wof:placetype":"locality"
},
  "geometry": {"coordinates":[122.90600000000001,41.1588],"type":"Point"}
}