{
  "type": "Feature",
  "properties": {
    "gn:admin1_code":"3",
    "gn:asciiname":"Xiuluo",
    "gn:country_code":"CN",
    "gn:dem":311,
    "gn:feature_class":"P",
    "gn:feature_code":"PPL",
    "gn:name":"Xiuluo",
    "gn:population":0,
    "gn:timezone":"Asia/Shanghai",
    "iso:country":"CN",
    "name:zho_x_preferred":[
        "\u79c0\u7f57"
    ],
    "wof:name":"Xiuluo",
    "wof:placetype":"locality"
},
  "geometry": {"coordinates":[114.53400000000001,26.0812],"type":"Point"}
}