{
  "type": "Feature",
  "properties": {
    "gn:admin1_code":"29.0",
    "gn:asciiname":"Laoma",
    "gn:country_code":"CN",
    "gn:dem":1403,
    "gn:feature_class":"P",
    "gn:feature_code":"PPL",
    "gn:name":"Laoma",
    "gn:population":0,
    "gn:timezone":"Asia/Shanghai",
    "iso:country":"CN",
    "name:zho_x_preferred":[
        "\u8001\u9a6c"
    ],
    "wof:name":"Laoma",
    "wof:placetype":"locality"
},
  "geometry": {"coordinates":[99.709,22.1254],"type":"Point"}
}