{
  "type": "Feature",
  "properties": {
    "gn:admin1_code":"18",
    "gn:asciiname":"Maobuchu",
    "gn:country_code":"CN",
    "gn:dem":1966,
    "gn:feature_class":"P",
    "gn:feature_code":"PPL",
    "gn:name":"Maobuchu",
    "gn:population":0,
    "gn:timezone":"Asia/Shanghai",
    "iso:country":"CN",
    "name:zho_x_preferred":[
        "\u6bdb\u900b\u521d"
    ],
    "wof:name":"Maobuchu",
    "wof:placetype":"locality"
},
  "geometry": {"coordinates":[104.733,26.7591],"type":"Point"}
}