{
  "type": "Feature",
  "properties": {
    "gn:admin1_code":"32.0",
    "gn:asciiname":"Karigong",
    "gn:country_code":"CN",
    "gn:dem":2765,
    "gn:feature_class":"P",
    "gn:feature_code":"PPL",
    "gn:name":"Karigong",
    "gn:population":0,
    "gn:timezone":"Asia/Shanghai",
    "iso:country":"CN",
    "name:zho_x_preferred":[
        "\u5361\u65e5\u5171"
    ],
    "wof:name":"Karigong",
    "wof:placetype":"locality"
},
  "geometry": {"coordinates":[99.2628,28.4737],"type":"Point"}
}