{
  "type": "Feature",
  "properties": {
    "gn:admin1_code":"1.0",
    "gn:asciiname":"Laowucun",
    "gn:country_code":"CN",
    "gn:dem":51,
    "gn:feature_class":"P",
    "gn:feature_code":"PPL",
    "gn:name":"Laowucun",
    "gn:population":0,
    "gn:timezone":"Asia/Shanghai",
    "iso:country":"CN",
    "name:und_x_variant":[
        "Laowu",
        "Laowucun"
    ],
    "name:zho_x_preferred":[
        "\u8001\u5c4b"
    ],
    "name:zho_x_variant":[
        "\u8001\u5c4b\u6751"
    ],
    "wof:name":"Laowucun",
    "wof:placetype":"locality"
},
  "geometry": {"coordinates":[118.5397,30.94648],"type":"Point"}
}