{
  "type": "Feature",
  "properties": {
    "gn:admin1_code":"26",
    "gn:asciiname":"Shahezi",
    "gn:cc2":"CN",
    "gn:country_code":"CN",
    "gn:dem":667,
    "gn:feature_class":"P",
    "gn:feature_code":"PPL",
    "gn:name":"Shahezi",
    "gn:population":0,
    "gn:timezone":"Asia/Shanghai",
    "iso:country":"CN",
    "name:und_x_variant":[
        "Sha-ho-chieh",
        "Sha-ho-tzu",
        "Shahezi"
    ],
    "wof:name":"Shahezi",
    "wof:placetype":"locality"
},
  "geometry": {"coordinates":[110.02139,33.82],"type":"Point"}
}