{
  "type": "Feature",
  "properties": {
    "gn:admin1_code":"2.0",
    "gn:asciiname":"Juezhi",
    "gn:country_code":"CN",
    "gn:dem":25,
    "gn:feature_class":"P",
    "gn:feature_code":"PPL",
    "gn:name":"Juezhi",
    "gn:population":0,
    "gn:timezone":"Asia/Shanghai",
    "iso:country":"CN",
    "name:zho_x_preferred":[
        "\u73a8\u829d"
    ],
    "wof:name":"Juezhi",
    "wof:placetype":"locality"
},
  "geometry": {"coordinates":[120.71924,29.54309000000001],"type":"Point"}
}