{
  "type": "Feature",
  "properties": {
    "gn:admin1_code":"24.0",
    "gn:asciiname":"Beihuqiao",
    "gn:country_code":"CN",
    "gn:dem":780,
    "gn:feature_class":"P",
    "gn:feature_code":"PPL",
    "gn:name":"Beihuqiao",
    "gn:population":0,
    "gn:timezone":"Asia/Shanghai",
    "iso:country":"CN",
    "name:zho_x_preferred":[
        "\u5317\u80e1\u4e54"
    ],
    "wof:name":"Beihuqiao",
    "wof:placetype":"locality"
},
  "geometry": {"coordinates":[112.62311,37.61365],"type":"Point"}
}