{
  "type": "Feature",
  "properties": {
    "gn:admin1_code":"20.0",
    "gn:asciiname":"Shicangyao",
    "gn:country_code":"CN",
    "gn:dem":1137,
    "gn:feature_class":"P",
    "gn:feature_code":"PPL",
    "gn:name":"Shicangyao",
    "gn:population":0,
    "gn:timezone":"Asia/Shanghai",
    "iso:country":"CN",
    "name:und_x_variant":[
        "\u77f3\u82cd\u7a91"
    ],
    "wof:name":"Shicangyao",
    "wof:placetype":"locality"
},
  "geometry": {"coordinates":[111.61292,39.96685],"type":"Point"}
}