{
  "type": "Feature",
  "properties": {
    "gn:admin1_code":"15.0",
    "gn:asciiname":"Meiwan",
    "gn:country_code":"CN",
    "gn:dem":1984,
    "gn:feature_class":"P",
    "gn:feature_code":"PPL",
    "gn:name":"Meiwan",
    "gn:population":0,
    "gn:timezone":"Asia/Shanghai",
    "iso:country":"CN",
    "name:zho_x_preferred":[
        "\u7164\u6e7e"
    ],
    "wof:name":"Meiwan",
    "wof:placetype":"locality"
},
  "geometry": {"coordinates":[105.304,34.4646],"type":"Point"}
}