{
  "type": "Feature",
  "properties": {
    "gn:admin1_code":"26.0",
    "gn:asciiname":"Wanghutaicun",
    "gn:country_code":"CN",
    "gn:dem":1482,
    "gn:feature_class":"P",
    "gn:feature_code":"PPL",
    "gn:name":"Wanghutaicun",
    "gn:population":0,
    "gn:timezone":"Asia/Shanghai",
    "iso:country":"CN",
    "name:zho_x_preferred":[
        "\u738b\u864e\u53f0\u6751"
    ],
    "wof:name":"Wanghutaicun",
    "wof:placetype":"locality"
},
  "geometry": {"coordinates":[107.36368,37.16946],"type":"Point"}
}