{
  "type": "Feature",
  "properties": {
    "gn:admin1_code":"10",
    "gn:asciiname":"Beiyanchi",
    "gn:country_code":"CN",
    "gn:dem":40,
    "gn:feature_class":"P",
    "gn:feature_code":"PPL",
    "gn:name":"Beiyanchi",
    "gn:population":0,
    "gn:timezone":"Asia/Shanghai",
    "iso:country":"CN",
    "name:zho_x_preferred":[
        "\u5317\u781a\u6c60"
    ],
    "wof:name":"Beiyanchi",
    "wof:placetype":"locality"
},
  "geometry": {"coordinates":[114.84399999999999,36.8118],"type":"Point"}
}