{
  "type": "Feature",
  "properties": {
    "gn:admin1_code":"1.0",
    "gn:asciiname":"Liufangcun",
    "gn:country_code":"CN",
    "gn:dem":79,
    "gn:feature_class":"P",
    "gn:feature_code":"PPL",
    "gn:name":"Liufangcun",
    "gn:population":0,
    "gn:timezone":"Asia/Shanghai",
    "iso:country":"CN",
    "name:zho_x_preferred":[
        "\u516d\u623f\u6751"
    ],
    "wof:name":"Liufangcun",
    "wof:placetype":"locality"
},
  "geometry": {"coordinates":[117.51175000000001,30.19041],"type":"Point"}
}