{
  "type": "Feature",
  "properties": {
    "gn:admin1_code":"21.0",
    "gn:asciiname":"Xiaoshahe",
    "gn:country_code":"CN",
    "gn:dem":2202,
    "gn:feature_class":"P",
    "gn:feature_code":"PPL",
    "gn:name":"Xiaoshahe",
    "gn:population":0,
    "gn:timezone":"Asia/Shanghai",
    "iso:country":"CN",
    "name:zho_x_preferred":[
        "\u5c0f\u6c99\u6cb3"
    ],
    "wof:name":"Xiaoshahe",
    "wof:placetype":"locality"
},
  "geometry": {"coordinates":[105.568,36.2169],"type":"Point"}
}