{
  "type": "Feature",
  "properties": {
    "gn:admin1_code":"26.0",
    "gn:asciiname":"Liujiamaocun",
    "gn:country_code":"CN",
    "gn:dem":1415,
    "gn:feature_class":"P",
    "gn:feature_code":"PPL",
    "gn:name":"Liujiamaocun",
    "gn:population":0,
    "gn:timezone":"Asia/Shanghai",
    "iso:country":"CN",
    "name:zho_x_preferred":[
        "\u5218\u5bb6\u5cc1\u6751"
    ],
    "wof:name":"Liujiamaocun",
    "wof:placetype":"locality"
},
  "geometry": {"coordinates":[109.01215000000001,37.48127],"type":"Point"}
}