{
  "type": "Feature",
  "properties": {
    "gn:admin1_code":"18",
    "gn:asciiname":"Xuantang",
    "gn:country_code":"CN",
    "gn:dem":835,
    "gn:feature_class":"P",
    "gn:feature_code":"PPL",
    "gn:name":"Xuantang",
    "gn:population":0,
    "gn:timezone":"Asia/Shanghai",
    "iso:country":"CN",
    "name:zho_x_preferred":[
        "\u65cb\u5858"
    ],
    "wof:name":"Xuantang",
    "wof:placetype":"locality"
},
  "geometry": {"coordinates":[108.089,28.9712],"type":"Point"}
}