{
  "type": "Feature",
  "properties": {
    "gn:admin1_code":"26.0",
    "gn:asciiname":"Baijiqing Yaochang",
    "gn:country_code":"CN",
    "gn:dem":1189,
    "gn:feature_class":"P",
    "gn:feature_code":"PPL",
    "gn:name":"Baijiqing Yaochang",
    "gn:population":0,
    "gn:timezone":"Asia/Shanghai",
    "iso:country":"CN",
    "name:zho_x_preferred":[
        "\u767e\u9e21\u503e\u836f\u5382"
    ],
    "wof:name":"Baijiqing Yaochang",
    "wof:placetype":"locality"
},
  "geometry": {"coordinates":[110.57666999999999,33.71015],"type":"Point"}
}