{
  "type": "Feature",
  "properties": {
    "gn:admin1_code":"18",
    "gn:asciiname":"Guanjiayuan",
    "gn:country_code":"CN",
    "gn:dem":2223,
    "gn:feature_class":"P",
    "gn:feature_code":"PPL",
    "gn:name":"Guanjiayuan",
    "gn:population":0,
    "gn:timezone":"Asia/Shanghai",
    "iso:country":"CN",
    "name:zho_x_preferred":[
        "\u7ba1\u5bb6\u9662"
    ],
    "wof:name":"Guanjiayuan",
    "wof:placetype":"locality"
},
  "geometry": {"coordinates":[104.413,27.113],"type":"Point"}
}