{
  "type": "Feature",
  "properties": {
    "gn:admin1_code":"19.0",
    "gn:asciiname":"Guanjia Wobu",
    "gn:country_code":"CN",
    "gn:dem":31,
    "gn:feature_class":"P",
    "gn:feature_code":"PPL",
    "gn:name":"Guanjia Wobu",
    "gn:population":0,
    "gn:timezone":"Asia/Shanghai",
    "iso:country":"CN",
    "name:und_x_variant":[
        "Guanjiawobao",
        "Guanjia Wobu"
    ],
    "name:zho_x_preferred":[
        "\u5173\u5bb6\u7a9d\u5821"
    ],
    "wof:name":"Guanjia Wobu",
    "wof:placetype":"locality"
},
  "geometry": {"coordinates":[122.85927,41.89828],"type":"Point"}
}