{
  "type": "Feature",
  "properties": {
    "gn:admin1_code":"18",
    "gn:asciiname":"Kushuitang",
    "gn:country_code":"CN",
    "gn:dem":2110,
    "gn:feature_class":"P",
    "gn:feature_code":"PPL",
    "gn:name":"Kushuitang",
    "gn:population":0,
    "gn:timezone":"Asia/Shanghai",
    "iso:country":"CN",
    "name:zho_x_preferred":[
        "\u67af\u6c34\u5858"
    ],
    "wof:name":"Kushuitang",
    "wof:placetype":"locality"
},
  "geometry": {"coordinates":[103.90000000000001,27.2764],"type":"Point"}
}