{
  "type": "Feature",
  "properties": {
    "gn:admin1_code":"30",
    "gn:asciiname":"Zeyingli",
    "gn:country_code":"CN",
    "gn:dem":531,
    "gn:feature_class":"P",
    "gn:feature_code":"PPL",
    "gn:name":"Zeyingli",
    "gn:population":0,
    "gn:timezone":"Asia/Shanghai",
    "iso:country":"CN",
    "name:zho_x_preferred":[
        "\u6cfd\u8425\u91cc"
    ],
    "wof:name":"Zeyingli",
    "wof:placetype":"locality"
},
  "geometry": {"coordinates":[116.11893999999999,24.0026],"type":"Point"}
}