{
  "type": "Feature",
  "properties": {
    "gn:admin1_code":"32.0",
    "gn:asciiname":"Kurong",
    "gn:country_code":"CN",
    "gn:dem":3233,
    "gn:feature_class":"P",
    "gn:feature_code":"PPL",
    "gn:name":"Kurong",
    "gn:population":0,
    "gn:timezone":"Asia/Shanghai",
    "iso:country":"CN",
    "name:zho_x_preferred":[
        "\u5e93\u7ed2"
    ],
    "wof:name":"Kurong",
    "wof:placetype":"locality"
},
  "geometry": {"coordinates":[100.58422,28.8507],"type":"Point"}
}