{
  "type": "Feature",
  "properties": {
    "gn:admin1_code":"1.0",
    "gn:asciiname":"Danshancun",
    "gn:country_code":"CN",
    "gn:dem":56,
    "gn:feature_class":"P",
    "gn:feature_code":"PPL",
    "gn:name":"Danshancun",
    "gn:population":0,
    "gn:timezone":"Asia/Shanghai",
    "iso:country":"CN",
    "name:zho_x_preferred":[
        "\u5355\u5c71\u6751"
    ],
    "wof:name":"Danshancun",
    "wof:placetype":"locality"
},
  "geometry": {"coordinates":[117.58271999999999,32.6891],"type":"Point"}
}