{
  "type": "Feature",
  "properties": {
    "gn:admin1_code":"02",
    "gn:asciiname":"Heshang",
    "gn:country_code":"CN",
    "gn:dem":32,
    "gn:feature_class":"P",
    "gn:feature_code":"PPLA4",
    "gn:name":"Heshang",
    "gn:population":0,
    "gn:timezone":"Asia/Shanghai",
    "iso:country":"CN",
    "name:und_x_variant":[
        "Ho-shang-tien",
        "Ho-chen",
        "Ho-shang-chen",
        "Heshang",
        "\u6cb3\u4e0a",
        "Heshang Zhen"
    ],
    "name:zho_x_preferred":[
        "\u6cb3\u4e0a\u9547"
    ],
    "name:zho_x_variant":[
        "\u6cb3\u4e0a"
    ],
    "wof:name":"Heshang",
    "wof:placetype":"locality"
},
  "geometry": {"coordinates":[120.16068,29.94341],"type":"Point"}
}