{
  "type": "Feature",
  "properties": {
    "gn:admin1_code":"19.0",
    "gn:asciiname":"Yaosu Jiatun",
    "gn:country_code":"CN",
    "gn:dem":157,
    "gn:feature_class":"P",
    "gn:feature_code":"PPL",
    "gn:name":"Yaosu Jiatun",
    "gn:population":0,
    "gn:timezone":"Asia/Shanghai",
    "iso:country":"CN",
    "name:zho_x_preferred":[
        "\u8170\u82cf\u5bb6\u5c6f"
    ],
    "wof:name":"Yaosu Jiatun",
    "wof:placetype":"locality"
},
  "geometry": {"coordinates":[124.258,42.9758],"type":"Point"}
}