{
  "type": "Feature",
  "properties": {
    "gn:admin1_code":"19.0",
    "gn:asciiname":"Wangjiagang",
    "gn:country_code":"CN",
    "gn:dem":18,
    "gn:feature_class":"P",
    "gn:feature_code":"PPL",
    "gn:name":"Wangjiagang",
    "gn:population":0,
    "gn:timezone":"Asia/Shanghai",
    "iso:country":"CN",
    "name:und_x_variant":[
        "\u738b\u5bb6\u5c97"
    ],
    "name:zho_x_preferred":[
        "\u738b\u5bb6\u5c97"
    ],
    "wof:name":"Wangjiagang",
    "wof:placetype":"locality"
},
  "geometry": {"coordinates":[122.75854,41.5972],"type":"Point"}
}