{
  "type": "Feature",
  "properties": {
    "gn:admin1_code":"24.0",
    "gn:asciiname":"Nanguocun",
    "gn:country_code":"CN",
    "gn:dem":944,
    "gn:feature_class":"P",
    "gn:feature_code":"PPL",
    "gn:name":"Nanguocun",
    "gn:population":0,
    "gn:timezone":"Asia/Shanghai",
    "iso:country":"CN",
    "name:zho_x_preferred":[
        "\u5357\u90ed\u6751"
    ],
    "wof:name":"Nanguocun",
    "wof:placetype":"locality"
},
  "geometry": {"coordinates":[112.92041,36.03538],"type":"Point"}
}