{
  "type": "Feature",
  "properties": {
    "gn:admin1_code":"30.0",
    "gn:asciiname":"Liwucun",
    "gn:country_code":"CN",
    "gn:dem":238,
    "gn:feature_class":"P",
    "gn:feature_code":"PPL",
    "gn:name":"Liwucun",
    "gn:population":0,
    "gn:timezone":"Asia/Urumqi",
    "iso:country":"CN",
    "name:zho_x_preferred":[
        "\u91cc\u4e94\u6751"
    ],
    "wof:name":"Liwucun",
    "wof:placetype":"locality"
},
  "geometry": {"coordinates":[110.95862,22.54058],"type":"Point"}
}