{
  "type": "Feature",
  "properties": {
    "gn:admin1_code":"8.0",
    "gn:asciiname":"Menggutun",
    "gn:country_code":"CN",
    "gn:dem":128,
    "gn:feature_class":"P",
    "gn:feature_code":"PPL",
    "gn:name":"Menggutun",
    "gn:population":0,
    "gn:timezone":"Asia/Shanghai",
    "iso:country":"CN",
    "name:zho_x_preferred":[
        "\u8499\u53e4\u5c6f"
    ],
    "wof:name":"Menggutun",
    "wof:placetype":"locality"
},
  "geometry": {"coordinates":[125.17116,45.5424],"type":"Point"}
}