{
  "type": "Feature",
  "properties": {
    "gn:admin1_code":"18.0",
    "gn:asciiname":"Wanquan",
    "gn:country_code":"CN",
    "gn:dem":1841,
    "gn:feature_class":"P",
    "gn:feature_code":"PPL",
    "gn:name":"Wanquan",
    "gn:population":0,
    "gn:timezone":"Asia/Shanghai",
    "iso:country":"CN",
    "name:ceb_x_preferred":[
        "Wanquan"
    ],
    "name:deu_x_preferred":[
        "Wanquan"
    ],
    "name:zho_x_preferred":[
        "\u4e07\u5168"
    ],
    "wof:name":"Wanquan",
    "wof:placetype":"locality"
},
  "geometry": {"coordinates":[105.011,26.5877],"type":"Point"}
}