{
  "type": "Feature",
  "properties": {
    "gn:admin1_code":"13.0",
    "gn:asciiname":"Tuogayila",
    "gn:country_code":"CN",
    "gn:dem":1398,
    "gn:feature_class":"P",
    "gn:feature_code":"PPL",
    "gn:name":"Tuogayila",
    "gn:population":0,
    "gn:timezone":"Asia/Shanghai",
    "iso:country":"CN",
    "name:zho_x_preferred":[
        "\u6258\u5c15\u4f9d\u62c9"
    ],
    "wof:name":"Tuogayila",
    "wof:placetype":"locality"
},
  "geometry": {"coordinates":[79.90358000000001,37.08929000000001],"type":"Point"}
}