{
  "type": "Feature",
  "properties": {
    "gn:admin1_code":"13",
    "gn:asciiname":"Outula Tongluke",
    "gn:country_code":"CN",
    "gn:dem":1266,
    "gn:feature_class":"P",
    "gn:feature_code":"PPL",
    "gn:name":"Outula Tongluke",
    "gn:population":0,
    "gn:timezone":"Asia/Shanghai",
    "iso:country":"CN",
    "name:zho_x_preferred":[
        "\u6b27\u5410\u62c9\u901a\u9c81\u514b"
    ],
    "wof:name":"Outula Tongluke",
    "wof:placetype":"locality"
},
  "geometry": {"coordinates":[76.22288,39.18644000000001],"type":"Point"}
}