{
  "type": "Feature",
  "properties": {
    "gn:admin1_code":"14",
    "gn:asciiname":"Jilong",
    "gn:country_code":"CN",
    "gn:dem":4676,
    "gn:feature_class":"P",
    "gn:feature_code":"PPL",
    "gn:name":"Jilong",
    "gn:population":0,
    "gn:timezone":"Asia/Urumqi",
    "iso:country":"CN",
    "name:zho_x_preferred":[
        "\u5409\u9f99"
    ],
    "wof:name":"Jilong",
    "wof:placetype":"locality"
},
  "geometry": {"coordinates":[89.1366,29.8139],"type":"Point"}
}