{
  "type": "Feature",
  "properties": {
    "gn:admin1_code":"26.0",
    "gn:asciiname":"Xuanwo",
    "gn:cc2":"CN",
    "gn:country_code":"CN",
    "gn:dem":340,
    "gn:feature_class":"P",
    "gn:feature_code":"PPL",
    "gn:name":"Xuanwo",
    "gn:population":0,
    "gn:timezone":"Asia/Shanghai",
    "iso:country":"CN",
    "name:und_x_variant":[
        "Hs\u00fcan-wo",
        "Xuanwo"
    ],
    "wof:name":"Xuanwo",
    "wof:placetype":"locality"
},
  "geometry": {"coordinates":[108.36833,32.74944],"type":"Point"}
}