{
  "type": "Feature",
  "properties": {
    "gn:admin1_code":"16.0",
    "gn:asciiname":"Liuqin",
    "gn:country_code":"CN",
    "gn:dem":108,
    "gn:feature_class":"P",
    "gn:feature_code":"PPL",
    "gn:name":"Liuqin",
    "gn:population":0,
    "gn:timezone":"Asia/Shanghai",
    "iso:country":"CN",
    "name:ara_x_preferred":[
        "\u0644\u064a\u0648 \u062a\u0634\u064a\u0646"
    ],
    "name:deu_x_preferred":[
        "Liuqin"
    ],
    "name:epo_x_preferred":[
        "Liu\u0109ino"
    ],
    "name:fra_x_preferred":[
        "Liuqin"
    ],
    "name:spa_x_preferred":[
        "Liuqin"
    ],
    "name:tam_x_preferred":[
        "\u0bb2\u0bbf\u0baf\u0bc1\u0b9a\u0bbf\u0ba9\u0bcd"
    ],
    "name:zho_x_preferred":[
        "\u516d\u7434"
    ],
    "wof:name":"Liuqin",
    "wof:placetype":"locality"
},
  "geometry": {"coordinates":[110.90600000000001,24.1917],"type":"Point"}
}