{
  "type": "Feature",
  "properties": {
    "gn:admin1_code":"16.0",
    "gn:asciiname":"Liuqin",
    "gn:country_code":"CN",
    "gn:dem":108,
    "gn:feature_class":"P",
    "gn:feature_code":"PPL",
    "gn:name":"Liuqin",
    "gn:population":0,
    "gn:timezone":"Asia/Shanghai",
    "iso:country":"CN",
    "name:zho_x_preferred":[
        "\u516d\u7434"
    ],
    "wof:name":"Liuqin",
    "wof:placetype":"locality"
},
  "geometry": {"coordinates":[110.90600000000001,24.1917],"type":"Point"}
}