{
  "type": "Feature",
  "properties": {
    "gn:admin1_code":"14.0",
    "gn:asciiname":"Sexiong",
    "gn:country_code":"CN",
    "gn:dem":4344,
    "gn:feature_class":"P",
    "gn:feature_code":"PPLA4",
    "gn:name":"Sexiong",
    "gn:population":0,
    "gn:timezone":"Asia/Urumqi",
    "iso:country":"CN",
    "name:bod_x_preferred":[
        "S\u00earxong"
    ],
    "name:und_x_variant":[
        "Naruduo",
        "Sexiong Xiang"
    ],
    "name:zho_x_preferred":[
        "\u8272\u96c4"
    ],
    "name:zho_x_variant":[
        "\u7eb3\u6c5d\u591a",
        "\u8272\u96c4\u4e61"
    ],
    "wof:name":"Sexiong",
    "wof:placetype":"locality"
},
  "geometry": {"coordinates":[92.83446000000001,31.40079],"type":"Point"}
}