{
  "type": "Feature",
  "properties": {
    "gn:admin1_code":"32.0",
    "gn:asciiname":"Ganshangding",
    "gn:country_code":"CN",
    "gn:dem":993,
    "gn:feature_class":"P",
    "gn:feature_code":"PPL",
    "gn:name":"Ganshangding",
    "gn:population":0,
    "gn:timezone":"Asia/Shanghai",
    "iso:country":"CN",
    "name:zho_x_preferred":[
        "\u7518\u4e0a\u9876"
    ],
    "wof:name":"Ganshangding",
    "wof:placetype":"locality"
},
  "geometry": {"coordinates":[103.19499999999999,29.6367],"type":"Point"}
}