{
  "type": "Feature",
  "properties": {
    "gn:admin1_code":"25",
    "gn:asciiname":"Lizhuangxia",
    "gn:country_code":"CN",
    "gn:dem":160,
    "gn:feature_class":"P",
    "gn:feature_code":"PPL",
    "gn:name":"Lizhuangxia",
    "gn:population":0,
    "gn:timezone":"Asia/Shanghai",
    "iso:country":"CN",
    "name:und_x_variant":[
        "\u91cc\u5e84\u4e0b"
    ],
    "wof:name":"Lizhuangxia",
    "wof:placetype":"locality"
},
  "geometry": {"coordinates":[119.005,35.71726],"type":"Point"}
}