{
  "type": "Feature",
  "properties": {
    "gn:admin1_code":"04",
    "gn:asciiname":"Taowu",
    "gn:country_code":"CN",
    "gn:dem":16,
    "gn:feature_class":"P",
    "gn:feature_code":"PPLA4",
    "gn:name":"Taowu",
    "gn:population":0,
    "gn:timezone":"Asia/Shanghai",
    "iso:country":"CN",
    "name:und_x_variant":[
        "T\u2019ao-wu-chen",
        "Taowu Zhen",
        "\u9676\u5434\u9547",
        "Taowu"
    ],
    "name:zho_x_preferred":[
        "\u9676\u5434"
    ],
    "wof:name":"Taowu",
    "wof:placetype":"locality"
},
  "geometry": {"coordinates":[118.77124999999999,31.77725],"type":"Point"}
}