{
  "type": "Feature",
  "properties": {
    "gn:admin1_code":"18.0",
    "gn:asciiname":"Yujiayan",
    "gn:country_code":"CN",
    "gn:dem":709,
    "gn:feature_class":"P",
    "gn:feature_code":"PPL",
    "gn:name":"Yujiayan",
    "gn:population":0,
    "gn:timezone":"Asia/Shanghai",
    "iso:country":"CN",
    "name:zho_x_preferred":[
        "\u55bb\u5bb6\u5ca9"
    ],
    "wof:name":"Yujiayan",
    "wof:placetype":"locality"
},
  "geometry": {"coordinates":[108.54600000000001,28.2663],"type":"Point"}
}