{
  "type": "Feature",
  "properties": {
    "gn:admin1_code":"5.0",
    "gn:asciiname":"Chaozicun",
    "gn:country_code":"CN",
    "gn:dem":142,
    "gn:feature_class":"P",
    "gn:feature_code":"PPL",
    "gn:name":"Chaozicun",
    "gn:population":0,
    "gn:timezone":"Asia/Shanghai",
    "iso:country":"CN",
    "name:zho_x_preferred":[
        "\u671d\u5b57\u6751"
    ],
    "wof:name":"Chaozicun",
    "wof:placetype":"locality"
},
  "geometry": {"coordinates":[123.81194000000001,44.97185],"type":"Point"}
}