{
  "type": "Feature",
  "properties": {
    "gn:admin1_code":"15.0",
    "gn:asciiname":"Jinpingxiang",
    "gn:country_code":"CN",
    "gn:dem":2005,
    "gn:feature_class":"P",
    "gn:feature_code":"PPL",
    "gn:name":"Jinpingxiang",
    "gn:population":0,
    "gn:timezone":"Asia/Shanghai",
    "iso:country":"CN",
    "name:und_x_variant":[
        "\u9526\u5c4f\u4e61"
    ],
    "wof:name":"Jinpingxiang",
    "wof:placetype":"locality"
},
  "geometry": {"coordinates":[105.08608,35.26737],"type":"Point"}
}