{
  "type": "Feature",
  "properties": {
    "gn:admin1_code":"24.0",
    "gn:asciiname":"Xihuqiao",
    "gn:country_code":"CN",
    "gn:dem":779,
    "gn:feature_class":"P",
    "gn:feature_code":"PPL",
    "gn:name":"Xihuqiao",
    "gn:population":0,
    "gn:timezone":"Asia/Shanghai",
    "iso:country":"CN",
    "name:zho_x_preferred":[
        "\u897f\u80e1\u4e54"
    ],
    "wof:name":"Xihuqiao",
    "wof:placetype":"locality"
},
  "geometry": {"coordinates":[112.60339999999999,37.59298],"type":"Point"}
}