{
  "type": "Feature",
  "properties": {
    "gn:admin1_code":"18.0",
    "gn:asciiname":"Ping'ai",
    "gn:country_code":"CN",
    "gn:dem":788,
    "gn:feature_class":"P",
    "gn:feature_code":"PPL",
    "gn:name":"Ping\u2019ai",
    "gn:population":0,
    "gn:timezone":"Asia/Shanghai",
    "iso:country":"CN",
    "name:und_x_variant":[
        "Ping\u2019ai"
    ],
    "name:zho_x_preferred":[
        "\u5e73\u827e"
    ],
    "wof:name":"Ping'ai",
    "wof:placetype":"locality"
},
  "geometry": {"coordinates":[106.59999999999999,25.2858],"type":"Point"}
}