{
  "type": "Feature",
  "properties": {
    "gn:admin1_code":"3.0",
    "gn:asciiname":"Guangming",
    "gn:country_code":"CN",
    "gn:dem":16,
    "gn:feature_class":"P",
    "gn:feature_code":"PPL",
    "gn:name":"Guangming",
    "gn:population":0,
    "gn:timezone":"Asia/Shanghai",
    "iso:country":"CN",
    "name:ceb_x_preferred":[
        "Guangming"
    ],
    "name:deu_x_preferred":[
        "Guangming"
    ],
    "name:jpn_x_preferred":[
        "\u5149\u660e"
    ],
    "name:mlg_x_preferred":[
        "Guangming"
    ],
    "name:swe_x_preferred":[
        "Guangming"
    ],
    "name:zho_x_preferred":[
        "\u5149\u660e"
    ],
    "wof:name":"Guangming",
    "wof:placetype":"locality"
},
  "geometry": {"coordinates":[116.18447,28.79185],"type":"Point"}
}