{
  "type": "Feature",
  "properties": {
    "gn:admin1_code":"8.0",
    "gn:asciiname":"Kaoshantun",
    "gn:country_code":"CN",
    "gn:dem":217,
    "gn:feature_class":"P",
    "gn:feature_code":"PPL",
    "gn:name":"Kaoshantun",
    "gn:population":0,
    "gn:timezone":"Asia/Shanghai",
    "iso:country":"CN",
    "name:zho_x_preferred":[
        "\u9760\u5c71\u5c6f"
    ],
    "wof:name":"Kaoshantun",
    "wof:placetype":"locality"
},
  "geometry": {"coordinates":[127.00613,47.49439],"type":"Point"}
}