{
  "type": "Feature",
  "properties": {
    "gn:admin1_code":"14.0",
    "gn:asciiname":"Digu",
    "gn:country_code":"CN",
    "gn:dem":3909,
    "gn:feature_class":"P",
    "gn:feature_code":"PPL",
    "gn:name":"Digu",
    "gn:population":0,
    "gn:timezone":"Asia/Urumqi",
    "iso:country":"CN",
    "name:zho_x_preferred":[
        "\u654c\u53e4"
    ],
    "wof:name":"Digu",
    "wof:placetype":"locality"
},
  "geometry": {"coordinates":[88.1705,29.3705],"type":"Point"}
}