{
  "type": "Feature",
  "properties": {
    "gn:admin1_code":"32.0",
    "gn:asciiname":"Shaofang",
    "gn:country_code":"CN",
    "gn:dem":2218,
    "gn:feature_class":"P",
    "gn:feature_code":"PPL",
    "gn:name":"Shaofang",
    "gn:population":0,
    "gn:timezone":"Asia/Shanghai",
    "iso:country":"CN",
    "name:zho_x_preferred":[
        "\u54e8\u623f"
    ],
    "wof:name":"Shaofang",
    "wof:placetype":"locality"
},
  "geometry": {"coordinates":[101.916,28.027],"type":"Point"}
}