{
  "type": "Feature",
  "properties": {
    "gn:admin1_code":"16.0",
    "gn:asciiname":"Gaohuangding",
    "gn:country_code":"CN",
    "gn:dem":565,
    "gn:feature_class":"P",
    "gn:feature_code":"PPL",
    "gn:name":"Gaohuangding",
    "gn:population":0,
    "gn:timezone":"Asia/Shanghai",
    "iso:country":"CN",
    "name:zho_x_preferred":[
        "\u9ad8\u8352\u9876"
    ],
    "wof:name":"Gaohuangding",
    "wof:placetype":"locality"
},
  "geometry": {"coordinates":[110.32599999999999,22.9238],"type":"Point"}
}