{
  "type": "Feature",
  "properties": {
    "gn:admin1_code":"31.0",
    "gn:asciiname":"Fanda",
    "gn:country_code":"CN",
    "gn:dem":193,
    "gn:feature_class":"P",
    "gn:feature_code":"PPL",
    "gn:name":"Fanda",
    "gn:population":0,
    "gn:timezone":"Asia/Shanghai",
    "iso:country":"CN",
    "name:zho_x_preferred":[
        "\u756a\u6253"
    ],
    "wof:name":"Fanda",
    "wof:placetype":"locality"
},
  "geometry": {"coordinates":[109.5868,19.28574],"type":"Point"}
}