{
  "type": "Feature",
  "properties": {
    "gn:admin1_code":"11",
    "gn:asciiname":"Ailin'an",
    "gn:country_code":"CN",
    "gn:dem":462,
    "gn:feature_class":"P",
    "gn:feature_code":"PPL",
    "gn:name":"Ailin\u2019an",
    "gn:population":0,
    "gn:timezone":"Asia/Shanghai",
    "iso:country":"CN",
    "name:und_x_variant":[
        "\u972d\u6797\u5eb5",
        "Ailin\u2019an"
    ],
    "wof:name":"Ailin'an",
    "wof:placetype":"locality"
},
  "geometry": {"coordinates":[112.24028,25.465],"type":"Point"}
}