{
  "type": "Feature",
  "properties": {
    "gn:admin1_code":"20.0",
    "gn:asciiname":"Sandaoqiao Sidui",
    "gn:country_code":"CN",
    "gn:dem":474,
    "gn:feature_class":"P",
    "gn:feature_code":"PPLF",
    "gn:name":"Sandaoqiao Sidui",
    "gn:population":0,
    "gn:timezone":"Asia/Shanghai",
    "iso:country":"CN",
    "name:zho_x_preferred":[
        "\u4e09\u9053\u6865\u56db\u961f"
    ],
    "wof:name":"Sandaoqiao Sidui",
    "wof:placetype":"locality"
},
  "geometry": {"coordinates":[122.53779,48.20113],"type":"Point"}
}