{
  "type": "Feature",
  "properties": {
    "gn:admin1_code":"9.0",
    "gn:asciiname":"Heilongmiaogou",
    "gn:country_code":"CN",
    "gn:dem":491,
    "gn:feature_class":"P",
    "gn:feature_code":"PPL",
    "gn:name":"Heilongmiaogou",
    "gn:population":0,
    "gn:timezone":"Asia/Shanghai",
    "iso:country":"CN",
    "name:zho_x_preferred":[
        "\u9ed1\u9f99\u5e99\u6c9f"
    ],
    "wof:name":"Heilongmiaogou",
    "wof:placetype":"locality"
},
  "geometry": {"coordinates":[111.29393,33.3384],"type":"Point"}
}