{
  "type": "Feature",
  "properties": {
    "gn:admin1_code":"13.0",
    "gn:asciiname":"Atibeishen",
    "gn:country_code":"CN",
    "gn:dem":1261,
    "gn:feature_class":"P",
    "gn:feature_code":"PPL",
    "gn:name":"Atibeishen",
    "gn:population":0,
    "gn:timezone":"Asia/Shanghai",
    "iso:country":"CN",
    "name:zho_x_preferred":[
        "\u963f\u63d0\u8d1d\u4ec0"
    ],
    "wof:name":"Atibeishen",
    "wof:placetype":"locality"
},
  "geometry": {"coordinates":[80.36898000000002,37.65688],"type":"Point"}
}