{
  "type": "Feature",
  "properties": {
    "gn:admin1_code":"0.0",
    "gn:asciiname":"Kao-t'ien",
    "gn:country_code":"CN",
    "gn:dem":1651,
    "gn:feature_class":"P",
    "gn:feature_code":"PPL",
    "gn:name":"Kao-t\u2019ien",
    "gn:population":0,
    "gn:timezone":"Asia/Shanghai",
    "iso:country":"CN",
    "wof:name":"Kao-t'ien",
    "wof:placetype":"locality"
},
  "geometry": {"coordinates":[99.23224,24.00387000000001],"type":"Point"}
}