{
  "type": "Feature",
  "properties": {
    "gn:admin1_code":"16",
    "gn:asciiname":"Lijian",
    "gn:cc2":"CN",
    "gn:country_code":"CN",
    "gn:dem":131,
    "gn:feature_class":"P",
    "gn:feature_code":"PPL",
    "gn:name":"Lijian",
    "gn:population":0,
    "gn:timezone":"Asia/Shanghai",
    "iso:country":"CN",
    "name:und_x_variant":[
        "Li-chien-hs\u00fc",
        "Li-chien",
        "Lijian"
    ],
    "wof:name":"Lijian",
    "wof:placetype":"locality"
},
  "geometry": {"coordinates":[108.16417,23.20722],"type":"Point"}
}