{
  "type": "Feature",
  "properties": {
    "gn:admin1_code":"12.0",
    "gn:asciiname":"Qingshantou",
    "gn:country_code":"CN",
    "gn:dem":404,
    "gn:feature_class":"P",
    "gn:feature_code":"PPL",
    "gn:name":"Qingshantou",
    "gn:population":0,
    "gn:timezone":"Asia/Shanghai",
    "iso:country":"CN",
    "name:zho_x_preferred":[
        "Qingshantou"
    ],
    "name:zho_x_variant":[
        "\u9752\u5c71\u5934"
    ],
    "wof:name":"Qingshantou",
    "wof:placetype":"locality"
},
  "geometry": {"coordinates":[111.10324,30.51581],"type":"Point"}
}