{
  "type": "Feature",
  "properties": {
    "gn:admin1_code":"18",
    "gn:asciiname":"Tiangouzhai",
    "gn:country_code":"CN",
    "gn:dem":1149,
    "gn:feature_class":"P",
    "gn:feature_code":"PPL",
    "gn:name":"Tiangouzhai",
    "gn:population":0,
    "gn:timezone":"Asia/Shanghai",
    "iso:country":"CN",
    "name:zho_x_preferred":[
        "\u5929\u6c9f\u5be8"
    ],
    "wof:name":"Tiangouzhai",
    "wof:placetype":"locality"
},
  "geometry": {"coordinates":[106.30800000000001,25.5067],"type":"Point"}
}