{
  "type": "Feature",
  "properties": {
    "gn:admin1_code":"10",
    "gn:asciiname":"Laohujia",
    "gn:country_code":"CN",
    "gn:dem":318,
    "gn:feature_class":"P",
    "gn:feature_code":"PPL",
    "gn:name":"Laohujia",
    "gn:population":0,
    "gn:timezone":"Asia/Shanghai",
    "iso:country":"CN",
    "name:zho_x_preferred":[
        "\u8001\u6237\u5bb6"
    ],
    "wof:name":"Laohujia",
    "wof:placetype":"locality"
},
  "geometry": {"coordinates":[118.03834999999999,40.35393],"type":"Point"}
}