{
  "type": "Feature",
  "properties": {
    "gn:admin1_code":"10",
    "gn:asciiname":"Qiansandaoliang",
    "gn:country_code":"CN",
    "gn:dem":1462,
    "gn:feature_class":"P",
    "gn:feature_code":"PPL",
    "gn:name":"Qiansandaoliang",
    "gn:population":0,
    "gn:timezone":"Asia/Shanghai",
    "iso:country":"CN",
    "name:zho_x_preferred":[
        "\u524d\u4e09\u9053\u6881"
    ],
    "wof:name":"Qiansandaoliang",
    "wof:placetype":"locality"
},
  "geometry": {"coordinates":[116.26555999999999,41.84696],"type":"Point"}
}