{
  "type": "Feature",
  "properties": {
    "gn:admin1_code":"24.0",
    "gn:asciiname":"Ximazhuangcun",
    "gn:country_code":"CN",
    "gn:dem":943,
    "gn:feature_class":"P",
    "gn:feature_code":"PPL",
    "gn:name":"Ximazhuangcun",
    "gn:population":0,
    "gn:timezone":"Asia/Shanghai",
    "iso:country":"CN",
    "name:zho_x_preferred":[
        "\u6d17\u9a6c\u5e84\u6751"
    ],
    "wof:name":"Ximazhuangcun",
    "wof:placetype":"locality"
},
  "geometry": {"coordinates":[114.38236999999999,39.78903],"type":"Point"}
}