{
  "type": "Feature",
  "properties": {
    "gn:admin1_code":"26.0",
    "gn:asciiname":"Yangxiaomujia Goucun",
    "gn:country_code":"CN",
    "gn:dem":1026,
    "gn:feature_class":"P",
    "gn:feature_code":"PPL",
    "gn:name":"Yangxiaomujia Goucun",
    "gn:population":0,
    "gn:timezone":"Asia/Shanghai",
    "iso:country":"CN",
    "name:zho_x_preferred":[
        "\u6768\u5c0f\u6155\u5bb6\u6c9f\u6751"
    ],
    "wof:name":"Yangxiaomujia Goucun",
    "wof:placetype":"locality"
},
  "geometry": {"coordinates":[110.22199999999999,37.2802],"type":"Point"}
}