{
  "type": "Feature",
  "properties": {
    "gn:admin1_code":"1.0",
    "gn:asciiname":"Xunzhucun",
    "gn:country_code":"CN",
    "gn:dem":37,
    "gn:feature_class":"P",
    "gn:feature_code":"PPL",
    "gn:name":"Xunzhucun",
    "gn:population":0,
    "gn:timezone":"Asia/Shanghai",
    "iso:country":"CN",
    "name:zho_x_preferred":[
        "\u8340\u7af9\u6751"
    ],
    "wof:name":"Xunzhucun",
    "wof:placetype":"locality"
},
  "geometry": {"coordinates":[118.66809000000001,30.99689],"type":"Point"}
}