{
  "type": "Feature",
  "properties": {
    "gn:admin1_code":"26.0",
    "gn:asciiname":"Shanshupingcun",
    "gn:country_code":"CN",
    "gn:dem":1226,
    "gn:feature_class":"P",
    "gn:feature_code":"PPL",
    "gn:name":"Shanshupingcun",
    "gn:population":0,
    "gn:timezone":"Asia/Shanghai",
    "iso:country":"CN",
    "name:zho_x_preferred":[
        "\u5c71\u6811\u576a\u6751"
    ],
    "wof:name":"Shanshupingcun",
    "wof:placetype":"locality"
},
  "geometry": {"coordinates":[110.03391000000001,36.42468],"type":"Point"}
}