{
  "type": "Feature",
  "properties": {
    "gn:admin1_code":"20.0",
    "gn:asciiname":"Zhongzhaogou",
    "gn:country_code":"CN",
    "gn:dem":1643,
    "gn:feature_class":"P",
    "gn:feature_code":"PPL",
    "gn:name":"Zhongzhaogou",
    "gn:population":0,
    "gn:timezone":"Asia/Shanghai",
    "iso:country":"CN",
    "name:und_x_variant":[
        "\u4e2d\u53ec\u6c9f"
    ],
    "wof:name":"Zhongzhaogou",
    "wof:placetype":"locality"
},
  "geometry": {"coordinates":[109.83683000000001,41.12369],"type":"Point"}
}