{
  "type": "Feature",
  "properties": {
    "gn:admin1_code":"18",
    "gn:asciiname":"Liaoli",
    "gn:country_code":"CN",
    "gn:dem":280,
    "gn:feature_class":"P",
    "gn:feature_code":"PPL",
    "gn:name":"Liaoli",
    "gn:population":0,
    "gn:timezone":"Asia/Shanghai",
    "iso:country":"CN",
    "name:zho_x_preferred":[
        "\u6599\u91cc"
    ],
    "wof:name":"Liaoli",
    "wof:placetype":"locality"
},
  "geometry": {"coordinates":[108.459,25.933],"type":"Point"}
}