{
  "type": "Feature",
  "properties": {
    "gn:admin1_code":"1.0",
    "gn:asciiname":"Shanzhaocun",
    "gn:country_code":"CN",
    "gn:dem":19,
    "gn:feature_class":"P",
    "gn:feature_code":"PPL",
    "gn:name":"Shanzhaocun",
    "gn:population":0,
    "gn:timezone":"Asia/Shanghai",
    "iso:country":"CN",
    "name:zho_x_preferred":[
        "\u5c71\u8d75\u6751"
    ],
    "wof:name":"Shanzhaocun",
    "wof:placetype":"locality"
},
  "geometry": {"coordinates":[117.68613000000001,31.39512],"type":"Point"}
}