{
  "type": "Feature",
  "properties": {
    "gn:admin1_code":"3.0",
    "gn:asciiname":"Shangnanfeng",
    "gn:country_code":"CN",
    "gn:dem":453,
    "gn:feature_class":"P",
    "gn:feature_code":"PPL",
    "gn:name":"Shangnanfeng",
    "gn:population":0,
    "gn:timezone":"Asia/Shanghai",
    "iso:country":"CN",
    "name:zho_x_preferred":[
        "\u4e0a\u5357\u5cf0"
    ],
    "wof:name":"Shangnanfeng",
    "wof:placetype":"locality"
},
  "geometry": {"coordinates":[117.83032,28.63634],"type":"Point"}
}