{
  "type": "Feature",
  "properties": {
    "gn:admin1_code":"11",
    "gn:asciiname":"Kaijing",
    "gn:country_code":"CN",
    "gn:dem":233,
    "gn:feature_class":"P",
    "gn:feature_code":"PPL",
    "gn:name":"Kaijing",
    "gn:population":0,
    "gn:timezone":"Asia/Shanghai",
    "iso:country":"CN",
    "name:zho_x_preferred":[
        "\u5f00\u4e95"
    ],
    "wof:name":"Kaijing",
    "wof:placetype":"locality"
},
  "geometry": {"coordinates":[111.12873999999999,25.08289],"type":"Point"}
}