{
  "type": "Feature",
  "properties": {
    "gn:admin1_code":"30.0",
    "gn:asciiname":"Shangzhonghuang",
    "gn:country_code":"CN",
    "gn:dem":49,
    "gn:feature_class":"P",
    "gn:feature_code":"PPL",
    "gn:name":"Shangzhonghuang",
    "gn:population":0,
    "gn:timezone":"Asia/Shanghai",
    "iso:country":"CN",
    "name:zho_x_preferred":[
        "\u4e0a\u4e2d\u9ec4"
    ],
    "wof:name":"Shangzhonghuang",
    "wof:placetype":"locality"
},
  "geometry": {"coordinates":[112.25913,22.62769],"type":"Point"}
}