{
  "type": "Feature",
  "properties": {
    "gn:admin1_code":"10.0",
    "gn:asciiname":"Xixiakou",
    "gn:country_code":"CN",
    "gn:dem":76,
    "gn:feature_class":"P",
    "gn:feature_code":"PPL",
    "gn:name":"Xixiakou",
    "gn:population":0,
    "gn:timezone":"Asia/Shanghai",
    "iso:country":"CN",
    "name:zho_x_preferred":[
        "\u897f\u5ce1\u53e3"
    ],
    "wof:name":"Xixiakou",
    "wof:placetype":"locality"
},
  "geometry": {"coordinates":[118.62397,40.11459],"type":"Point"}
}