{
  "type": "Feature",
  "properties": {
    "gn:admin1_code":"3.0",
    "gn:asciiname":"Yukoukeng",
    "gn:country_code":"CN",
    "gn:dem":540,
    "gn:feature_class":"P",
    "gn:feature_code":"PPL",
    "gn:name":"Yukoukeng",
    "gn:population":0,
    "gn:timezone":"Asia/Shanghai",
    "iso:country":"CN",
    "name:und_x_variant":[
        "\u9c7c\u53e3\u5751"
    ],
    "wof:name":"Yukoukeng",
    "wof:placetype":"locality"
},
  "geometry": {"coordinates":[115.84007,26.97547],"type":"Point"}
}