{
  "type": "Feature",
  "properties": {
    "gn:admin1_code":"30.0",
    "gn:asciiname":"Pingpucun",
    "gn:country_code":"CN",
    "gn:dem":340,
    "gn:feature_class":"P",
    "gn:feature_code":"PPL",
    "gn:name":"Pingpucun",
    "gn:population":0,
    "gn:timezone":"Asia/Shanghai",
    "iso:country":"CN",
    "name:und_x_variant":[
        "Pingpu"
    ],
    "name:zho_x_preferred":[
        "\u576a\u57d4\u6751"
    ],
    "wof:name":"Pingpucun",
    "wof:placetype":"locality"
},
  "geometry": {"coordinates":[115.92227,24.14387],"type":"Point"}
}