{
  "type": "Feature",
  "properties": {
    "gn:admin1_code":"16.0",
    "gn:asciiname":"Yuanli",
    "gn:country_code":"CN",
    "gn:dem":585,
    "gn:feature_class":"P",
    "gn:feature_code":"PPL",
    "gn:name":"Yuanli",
    "gn:population":0,
    "gn:timezone":"Asia/Shanghai",
    "iso:country":"CN",
    "name:zho_x_preferred":[
        "\u5143\u91cc"
    ],
    "wof:name":"Yuanli",
    "wof:placetype":"locality"
},
  "geometry": {"coordinates":[106.806,25.1333],"type":"Point"}
}