{
  "type": "Feature",
  "properties": {
    "gn:admin1_code":"15.0",
    "gn:asciiname":"Jinjiayao",
    "gn:country_code":"CN",
    "gn:dem":1895,
    "gn:feature_class":"P",
    "gn:feature_code":"PPL",
    "gn:name":"Jinjiayao",
    "gn:population":0,
    "gn:timezone":"Asia/Shanghai",
    "iso:country":"CN",
    "name:zho_x_preferred":[
        "\u91d1\u5bb6\u7a91"
    ],
    "wof:name":"Jinjiayao",
    "wof:placetype":"locality"
},
  "geometry": {"coordinates":[104.86199999999999,35.9981],"type":"Point"}
}