{
  "type": "Feature",
  "properties": {
    "gn:admin1_code":"26",
    "gn:asciiname":"Xianshili",
    "gn:country_code":"CN",
    "gn:dem":361,
    "gn:feature_class":"P",
    "gn:feature_code":"PPL",
    "gn:name":"Xianshili",
    "gn:population":0,
    "gn:timezone":"Asia/Shanghai",
    "iso:country":"CN",
    "name:zho_x_preferred":[
        "\u8d24\u58eb\u674e"
    ],
    "wof:name":"Xianshili",
    "wof:placetype":"locality"
},
  "geometry": {"coordinates":[109.38369,34.59398],"type":"Point"}
}