{
  "type": "Feature",
  "properties": {
    "gn:admin1_code":"10",
    "gn:asciiname":"Yuanquanchang",
    "gn:country_code":"CN",
    "gn:dem":1416,
    "gn:feature_class":"P",
    "gn:feature_code":"PPL",
    "gn:name":"Yuanquanchang",
    "gn:population":0,
    "gn:timezone":"Asia/Shanghai",
    "iso:country":"CN",
    "name:zho_x_preferred":[
        "\u5143\u6cc9\u5382"
    ],
    "wof:name":"Yuanquanchang",
    "wof:placetype":"locality"
},
  "geometry": {"coordinates":[114.62569999999999,41.14447],"type":"Point"}
}