{
  "type": "Feature",
  "properties": {
    "gn:admin1_code":"29.0",
    "gn:asciiname":"Guoji",
    "gn:country_code":"CN",
    "gn:dem":1818,
    "gn:feature_class":"P",
    "gn:feature_code":"PPL",
    "gn:name":"Guoji",
    "gn:population":0,
    "gn:timezone":"Asia/Shanghai",
    "iso:country":"CN",
    "name:zho_x_preferred":[
        "\u679c\u5409"
    ],
    "wof:name":"Guoji",
    "wof:placetype":"locality"
},
  "geometry": {"coordinates":[103.685,24.5552],"type":"Point"}
}