{
  "type": "Feature",
  "properties": {
    "gn:admin1_code":"11.0",
    "gn:asciiname":"Shuangmen",
    "gn:country_code":"CN",
    "gn:dem":433,
    "gn:feature_class":"P",
    "gn:feature_code":"PPL",
    "gn:name":"Shuangmen",
    "gn:population":0,
    "gn:timezone":"Asia/Shanghai",
    "iso:country":"CN",
    "name:zho_x_preferred":[
        "\u53cc\u95e8"
    ],
    "wof:name":"Shuangmen",
    "wof:placetype":"locality"
},
  "geometry": {"coordinates":[109.95428,26.77719],"type":"Point"}
}