{
  "type": "Feature",
  "properties": {
    "gn:admin1_code":"6.0",
    "gn:asciiname":"Wushi'er Daoban",
    "gn:country_code":"CN",
    "gn:dem":3294,
    "gn:feature_class":"P",
    "gn:feature_code":"PPL",
    "gn:name":"Wushi\u2019er Daoban",
    "gn:population":0,
    "gn:timezone":"Asia/Urumqi",
    "iso:country":"CN",
    "name:und_x_variant":[
        "Wushi\u2019er Daoban",
        "\u4e94\u5341\u4e8c\u9053\u73ed"
    ],
    "wof:name":"Wushi'er Daoban",
    "wof:placetype":"locality"
},
  "geometry": {"coordinates":[94.81983,35.99982],"type":"Point"}
}