{
  "type": "Feature",
  "properties": {
    "gn:admin1_code":"8.0",
    "gn:asciiname":"Lihongmingtun",
    "gn:country_code":"CN",
    "gn:dem":229,
    "gn:feature_class":"P",
    "gn:feature_code":"PPL",
    "gn:name":"Lihongmingtun",
    "gn:population":0,
    "gn:timezone":"Asia/Shanghai",
    "iso:country":"CN",
    "name:zho_x_preferred":[
        "\u674e\u6d2a\u660e\u5c6f"
    ],
    "wof:name":"Lihongmingtun",
    "wof:placetype":"locality"
},
  "geometry": {"coordinates":[125.74289,47.21888],"type":"Point"}
}