{
  "type": "Feature",
  "properties": {
    "gn:admin1_code":"19.0",
    "gn:asciiname":"Jijiazi",
    "gn:country_code":"CN",
    "gn:dem":552,
    "gn:feature_class":"P",
    "gn:feature_code":"PPL",
    "gn:name":"Jijiazi",
    "gn:population":0,
    "gn:timezone":"Asia/Shanghai",
    "iso:country":"CN",
    "name:zho_x_preferred":[
        "\u51e0\u5bb6\u5b50"
    ],
    "wof:name":"Jijiazi",
    "wof:placetype":"locality"
},
  "geometry": {"coordinates":[124.78691000000001,41.17025],"type":"Point"}
}