{
  "type": "Feature",
  "properties": {
    "gn:admin1_code":"30.0",
    "gn:asciiname":"Foshi",
    "gn:country_code":"CN",
    "gn:dem":160,
    "gn:feature_class":"P",
    "gn:feature_code":"PPL",
    "gn:name":"Foshi",
    "gn:population":0,
    "gn:timezone":"Asia/Shanghai",
    "iso:country":"CN",
    "name:zho_x_preferred":[
        "\u4f5b\u5e02"
    ],
    "wof:name":"Foshi",
    "wof:placetype":"locality"
},
  "geometry": {"coordinates":[112.74444,23.92361],"type":"Point"}
}