{
  "type": "Feature",
  "properties": {
    "gn:admin1_code":"12.0",
    "gn:asciiname":"Dengtou",
    "gn:country_code":"CN",
    "gn:dem":62,
    "gn:feature_class":"P",
    "gn:feature_code":"PPL",
    "gn:name":"Dengtou",
    "gn:population":0,
    "gn:timezone":"Asia/Shanghai",
    "iso:country":"CN",
    "name:zho_x_preferred":[
        "Dengtou"
    ],
    "name:zho_x_variant":[
        "\u706f\u5934"
    ],
    "wof:name":"Dengtou",
    "wof:placetype":"locality"
},
  "geometry": {"coordinates":[115.01922,29.98195],"type":"Point"}
}