{
  "type": "Feature",
  "properties": {
    "gn:admin1_code":"32.0",
    "gn:asciiname":"Lingpaishi",
    "gn:country_code":"CN",
    "gn:dem":4210,
    "gn:feature_class":"P",
    "gn:feature_code":"PPL",
    "gn:name":"Lingpaishi",
    "gn:population":0,
    "gn:timezone":"Asia/Shanghai",
    "iso:country":"CN",
    "name:zho_x_preferred":[
        "\u4ee4\u724c\u77f3"
    ],
    "wof:name":"Lingpaishi",
    "wof:placetype":"locality"
},
  "geometry": {"coordinates":[101.17084,29.11975],"type":"Point"}
}