{
  "type": "Feature",
  "properties": {
    "gn:admin1_code":"11",
    "gn:asciiname":"Zhichong",
    "gn:country_code":"CN",
    "gn:dem":84,
    "gn:feature_class":"P",
    "gn:feature_code":"PPL",
    "gn:name":"Zhichong",
    "gn:population":0,
    "gn:timezone":"Asia/Shanghai",
    "iso:country":"CN",
    "name:zho_x_preferred":[
        "\u76f4\u51b2"
    ],
    "wof:name":"Zhichong",
    "wof:placetype":"locality"
},
  "geometry": {"coordinates":[112.4945,27.76766],"type":"Point"}
}