{
  "type": "Feature",
  "properties": {
    "gn:admin1_code":"23.0",
    "gn:asciiname":"Caibang",
    "gn:country_code":"CN",
    "gn:dem":6,
    "gn:feature_class":"P",
    "gn:feature_code":"PPL",
    "gn:name":"Caibang",
    "gn:population":0,
    "gn:timezone":"Asia/Shanghai",
    "iso:country":"CN",
    "name:und_x_variant":[
        "\u8521\u6d5c"
    ],
    "wof:name":"Caibang",
    "wof:placetype":"locality"
},
  "geometry": {"coordinates":[120.94392999999999,31.118],"type":"Point"}
}