{
  "type": "Feature",
  "properties": {
    "gn:admin1_code":"30.0",
    "gn:asciiname":"Tiantanggang",
    "gn:country_code":"CN",
    "gn:dem":404,
    "gn:feature_class":"P",
    "gn:feature_code":"PPL",
    "gn:name":"Tiantanggang",
    "gn:population":0,
    "gn:timezone":"Asia/Urumqi",
    "iso:country":"CN",
    "name:zho_x_preferred":[
        "\u5929\u5802\u5c97"
    ],
    "wof:name":"Tiantanggang",
    "wof:placetype":"locality"
},
  "geometry": {"coordinates":[110.85942,22.58056],"type":"Point"}
}