{
  "type": "Feature",
  "properties": {
    "gn:admin1_code":"7",
    "gn:asciiname":"Shexin",
    "gn:country_code":"CN",
    "gn:dem":358,
    "gn:feature_class":"P",
    "gn:feature_code":"PPL",
    "gn:name":"Shexin",
    "gn:population":0,
    "gn:timezone":"Asia/Shanghai",
    "iso:country":"CN",
    "name:und_x_variant":[
        "\u7572\u5fc3",
        "Yuxin"
    ],
    "wof:name":"Shexin",
    "wof:placetype":"locality"
},
  "geometry": {"coordinates":[116.39255,25.43831],"type":"Point"}
}