{
  "type": "Feature",
  "properties": {
    "gn:admin1_code":"2.0",
    "gn:asciiname":"Xiachangkeng",
    "gn:country_code":"CN",
    "gn:dem":427,
    "gn:feature_class":"P",
    "gn:feature_code":"PPL",
    "gn:name":"Xiachangkeng",
    "gn:population":0,
    "gn:timezone":"Asia/Shanghai",
    "iso:country":"CN",
    "name:zho_x_preferred":[
        "\u4e0b\u660c\u5751"
    ],
    "wof:name":"Xiachangkeng",
    "wof:placetype":"locality"
},
  "geometry": {"coordinates":[119.65761000000001,28.6567],"type":"Point"}
}