{
  "type": "Feature",
  "properties": {
    "gn:admin1_code":"11.0",
    "gn:asciiname":"Shanshuitou",
    "gn:country_code":"CN",
    "gn:dem":75,
    "gn:feature_class":"P",
    "gn:feature_code":"PPL",
    "gn:name":"Shanshuitou",
    "gn:population":0,
    "gn:timezone":"Asia/Shanghai",
    "iso:country":"CN",
    "name:zho_x_preferred":[
        "\u5c71\u6c34\u5934"
    ],
    "wof:name":"Shanshuitou",
    "wof:placetype":"locality"
},
  "geometry": {"coordinates":[113.3847,28.02664],"type":"Point"}
}