{
  "type": "Feature",
  "properties": {
    "gn:admin1_code":"16.0",
    "gn:asciiname":"Jiangshitan",
    "gn:country_code":"CN",
    "gn:dem":20,
    "gn:feature_class":"P",
    "gn:feature_code":"PPL",
    "gn:name":"Jiangshitan",
    "gn:population":0,
    "gn:timezone":"Asia/Shanghai",
    "iso:country":"CN",
    "name:zho_x_preferred":[
        "\u6c5f\u77f3\u6f6d"
    ],
    "wof:name":"Jiangshitan",
    "wof:placetype":"locality"
},
  "geometry": {"coordinates":[108.497,21.678],"type":"Point"}
}