{
  "type": "Feature",
  "properties": {
    "gn:admin1_code":"8.0",
    "gn:asciiname":"Binghugou",
    "gn:country_code":"CN",
    "gn:dem":397,
    "gn:feature_class":"P",
    "gn:feature_code":"PPL",
    "gn:name":"Binghugou",
    "gn:population":0,
    "gn:timezone":"Asia/Shanghai",
    "iso:country":"CN",
    "name:zho_x_preferred":[
        "\u51b0\u6e56\u6c9f"
    ],
    "wof:name":"Binghugou",
    "wof:placetype":"locality"
},
  "geometry": {"coordinates":[128.75479999999999,44.87894],"type":"Point"}
}