{
  "type": "Feature",
  "properties": {
    "gn:admin1_code":"18.0",
    "gn:asciiname":"Longlisi",
    "gn:country_code":"CN",
    "gn:dem":464,
    "gn:feature_class":"P",
    "gn:feature_code":"PPL",
    "gn:name":"Longlisi",
    "gn:population":0,
    "gn:timezone":"Asia/Shanghai",
    "iso:country":"CN",
    "name:zho_x_preferred":[
        "\u9f99\u91cc\u53f8"
    ],
    "wof:name":"Longlisi",
    "wof:placetype":"locality"
},
  "geometry": {"coordinates":[109.062,26.4111],"type":"Point"}
}