{
  "type": "Feature",
  "properties": {
    "gn:admin1_code":"9.0",
    "gn:asciiname":"Qilijing",
    "gn:country_code":"CN",
    "gn:dem":121,
    "gn:feature_class":"P",
    "gn:feature_code":"PPL",
    "gn:name":"Qilijing",
    "gn:population":0,
    "gn:timezone":"Asia/Shanghai",
    "iso:country":"CN",
    "name:zho_x_preferred":[
        "\u4e03\u91cc\u4e95"
    ],
    "wof:name":"Qilijing",
    "wof:placetype":"locality"
},
  "geometry": {"coordinates":[113.70316,34.42558],"type":"Point"}
}