{
  "type": "Feature",
  "properties": {
    "gn:admin1_code":"12.0",
    "gn:asciiname":"Shuidong",
    "gn:country_code":"CN",
    "gn:dem":900,
    "gn:feature_class":"P",
    "gn:feature_code":"PPL",
    "gn:name":"Shuidong",
    "gn:population":0,
    "gn:timezone":"Asia/Shanghai",
    "iso:country":"CN",
    "name:zho_x_preferred":[
        "\u6c34\u6d1e"
    ],
    "wof:name":"Shuidong",
    "wof:placetype":"locality"
},
  "geometry": {"coordinates":[109.69906,30.33207],"type":"Point"}
}