{
  "type": "Feature",
  "properties": {
    "gn:admin1_code":"12.0",
    "gn:asciiname":"Dahongtan",
    "gn:country_code":"CN",
    "gn:dem":250,
    "gn:feature_class":"P",
    "gn:feature_code":"PPL",
    "gn:name":"Dahongtan",
    "gn:population":0,
    "gn:timezone":"Asia/Shanghai",
    "iso:country":"CN",
    "name:zho_x_preferred":[
        "\u5927\u6d2a\u6ee9"
    ],
    "wof:name":"Dahongtan",
    "wof:placetype":"locality"
},
  "geometry": {"coordinates":[111.30446999999999,32.03897],"type":"Point"}
}