{
  "type": "Feature",
  "properties": {
    "gn:admin1_code":"16.0",
    "gn:asciiname":"Weining",
    "gn:country_code":"CN",
    "gn:dem":132,
    "gn:feature_class":"P",
    "gn:feature_code":"PPL",
    "gn:name":"Weining",
    "gn:population":0,
    "gn:timezone":"Asia/Shanghai",
    "iso:country":"CN",
    "name:ceb_x_preferred":[
        "Weining"
    ],
    "name:zho_x_preferred":[
        "\u97e6\u5b81"
    ],
    "wof:name":"Weining",
    "wof:placetype":"locality"
},
  "geometry": {"coordinates":[107.042,23.7068],"type":"Point"}
}