{
  "type": "Feature",
  "properties": {
    "gn:admin1_code":"11.0",
    "gn:asciiname":"Jianquangongci",
    "gn:country_code":"CN",
    "gn:dem":88,
    "gn:feature_class":"P",
    "gn:feature_code":"PPL",
    "gn:name":"Jianquangongci",
    "gn:population":0,
    "gn:timezone":"Asia/Shanghai",
    "iso:country":"CN",
    "name:zho_x_preferred":[
        "\u76d1\u6cc9\u516c\u7960"
    ],
    "wof:name":"Jianquangongci",
    "wof:placetype":"locality"
},
  "geometry": {"coordinates":[112.74797,27.22593],"type":"Point"}
}