{
  "type": "Feature",
  "properties": {
    "gn:admin1_code":"29.0",
    "gn:asciiname":"Dayuanpu",
    "gn:country_code":"CN",
    "gn:dem":1273,
    "gn:feature_class":"P",
    "gn:feature_code":"PPL",
    "gn:name":"Dayuanpu",
    "gn:population":0,
    "gn:timezone":"Asia/Shanghai",
    "iso:country":"CN",
    "name:zho_x_preferred":[
        "\u5927\u56ed\u5703"
    ],
    "wof:name":"Dayuanpu",
    "wof:placetype":"locality"
},
  "geometry": {"coordinates":[100.66200000000001,23.1701],"type":"Point"}
}