{
  "type": "Feature",
  "properties": {
    "gn:admin1_code":"14.0",
    "gn:asciiname":"Lari",
    "gn:country_code":"CN",
    "gn:dem":3609,
    "gn:feature_class":"P",
    "gn:feature_code":"PPL",
    "gn:name":"Lari",
    "gn:population":0,
    "gn:timezone":"Asia/Urumqi",
    "iso:country":"CN",
    "name:zho_x_preferred":[
        "\u62c9\u65e5"
    ],
    "wof:name":"Lari",
    "wof:placetype":"locality"
},
  "geometry": {"coordinates":[96.93299,30.0395],"type":"Point"}
}