{
  "type": "Feature",
  "properties": {
    "gn:admin1_code":"11",
    "gn:asciiname":"Xintangfu",
    "gn:country_code":"CN",
    "gn:dem":226,
    "gn:feature_class":"P",
    "gn:feature_code":"PPL",
    "gn:name":"Xintangfu",
    "gn:population":0,
    "gn:timezone":"Asia/Shanghai",
    "iso:country":"CN",
    "name:zho_x_preferred":[
        "\u65b0\u5858\u798f"
    ],
    "wof:name":"Xintangfu",
    "wof:placetype":"locality"
},
  "geometry": {"coordinates":[111.49063,25.47171],"type":"Point"}
}