{
  "type": "Feature",
  "properties": {
    "gn:admin1_code":"7.0",
    "gn:asciiname":"Shi'an",
    "gn:country_code":"CN",
    "gn:dem":164,
    "gn:feature_class":"P",
    "gn:feature_code":"PPL",
    "gn:name":"Shi\u2019an",
    "gn:population":0,
    "gn:timezone":"Asia/Shanghai",
    "iso:country":"CN",
    "name:und_x_variant":[
        "Shi\u2019an"
    ],
    "name:zho_x_preferred":[
        "\u77f3\u5eb5"
    ],
    "wof:name":"Shi'an",
    "wof:placetype":"locality"
},
  "geometry": {"coordinates":[118.01152999999999,27.3558],"type":"Point"}
}