{
  "type": "Feature",
  "properties": {
    "gn:admin1_code":"29.0",
    "gn:asciiname":"Xiaomengmeng",
    "gn:country_code":"CN",
    "gn:dem":1495,
    "gn:feature_class":"P",
    "gn:feature_code":"PPL",
    "gn:name":"Xiaomengmeng",
    "gn:population":0,
    "gn:timezone":"Asia/Shanghai",
    "iso:country":"CN",
    "name:zho_x_preferred":[
        "\u5c0f\u731b\u731b"
    ],
    "wof:name":"Xiaomengmeng",
    "wof:placetype":"locality"
},
  "geometry": {"coordinates":[100.096,24.3876],"type":"Point"}
}