{
  "type": "Feature",
  "properties": {
    "gn:admin1_code":"26",
    "gn:asciiname":"Xuegu",
    "gn:country_code":"CN",
    "gn:dem":436,
    "gn:feature_class":"P",
    "gn:feature_code":"PPL",
    "gn:name":"Xuegu",
    "gn:population":0,
    "gn:timezone":"Asia/Shanghai",
    "iso:country":"CN",
    "name:zho_x_preferred":[
        "\u859b\u56fa"
    ],
    "wof:name":"Xuegu",
    "wof:placetype":"locality"
},
  "geometry": {"coordinates":[108.28762,34.25699],"type":"Point"}
}