{
  "type": "Feature",
  "properties": {
    "gn:admin1_code":"3.0",
    "gn:asciiname":"Duanjiache",
    "gn:country_code":"CN",
    "gn:dem":54,
    "gn:feature_class":"P",
    "gn:feature_code":"PPL",
    "gn:name":"Duanjiache",
    "gn:population":0,
    "gn:timezone":"Asia/Shanghai",
    "iso:country":"CN",
    "name:und_x_variant":[
        "\u5845\u5bb6\u8f66"
    ],
    "wof:name":"Duanjiache",
    "wof:placetype":"locality"
},
  "geometry": {"coordinates":[116.09010000000001,27.79707],"type":"Point"}
}