{
  "type": "Feature",
  "properties": {
    "gn:admin1_code":"26.0",
    "gn:asciiname":"Xiwucun",
    "gn:country_code":"CN",
    "gn:dem":1235,
    "gn:feature_class":"P",
    "gn:feature_code":"PPL",
    "gn:name":"Xiwucun",
    "gn:population":0,
    "gn:timezone":"Asia/Shanghai",
    "iso:country":"CN",
    "name:zho_x_preferred":[
        "\u897f\u6b66\u6751"
    ],
    "wof:name":"Xiwucun",
    "wof:placetype":"locality"
},
  "geometry": {"coordinates":[109.52033,35.88265999999999],"type":"Point"}
}