{
  "type": "Feature",
  "properties": {
    "gn:admin1_code":"2.0",
    "gn:asciiname":"Gulingkeng",
    "gn:country_code":"CN",
    "gn:dem":468,
    "gn:feature_class":"P",
    "gn:feature_code":"PPL",
    "gn:name":"Gulingkeng",
    "gn:population":0,
    "gn:timezone":"Asia/Shanghai",
    "iso:country":"CN",
    "name:zho_x_preferred":[
        "\u53e4\u5cad\u5751"
    ],
    "wof:name":"Gulingkeng",
    "wof:placetype":"locality"
},
  "geometry": {"coordinates":[118.9696,27.78726],"type":"Point"}
}