{
  "type": "Feature",
  "properties": {
    "gn:admin1_code":"9.0",
    "gn:asciiname":"Xindianpu",
    "gn:cc2":"CN",
    "gn:country_code":"CN",
    "gn:dem":90,
    "gn:feature_class":"P",
    "gn:feature_code":"PPL",
    "gn:name":"Xindianpu",
    "gn:population":0,
    "gn:timezone":"Asia/Shanghai",
    "iso:country":"CN",
    "name:und_x_variant":[
        "Hsin-tien-p\u2019u",
        "Xindian",
        "Hsin-tien",
        "Xindianpu"
    ],
    "wof:name":"Xindianpu",
    "wof:placetype":"locality"
},
  "geometry": {"coordinates":[112.30278,32.40833],"type":"Point"}
}