{
  "type": "Feature",
  "properties": {
    "gn:admin1_code":"25",
    "gn:asciiname":"Chongyi",
    "gn:country_code":"CN",
    "gn:dem":113,
    "gn:feature_class":"P",
    "gn:feature_code":"PPL",
    "gn:name":"Chongyi",
    "gn:population":0,
    "gn:timezone":"Asia/Shanghai",
    "iso:country":"CN",
    "name:zho_x_preferred":[
        "\u5d07\u4e49"
    ],
    "wof:name":"Chongyi",
    "wof:placetype":"locality"
},
  "geometry": {"coordinates":[117.023,35.4179],"type":"Point"}
}