{
  "type": "Feature",
  "properties": {
    "gn:admin1_code":"12.0",
    "gn:asciiname":"Tanyugounao",
    "gn:country_code":"CN",
    "gn:dem":789,
    "gn:feature_class":"P",
    "gn:feature_code":"PPL",
    "gn:name":"Tanyugounao",
    "gn:population":0,
    "gn:timezone":"Asia/Shanghai",
    "iso:country":"CN",
    "name:zho_x_preferred":[
        "\u8c2d\u4f59\u6c9f\u8111"
    ],
    "wof:name":"Tanyugounao",
    "wof:placetype":"locality"
},
  "geometry": {"coordinates":[110.18801999999999,32.01065],"type":"Point"}
}