{
  "type": "Feature",
  "properties": {
    "gn:admin1_code":"32.0",
    "gn:asciiname":"Qiboji",
    "gn:country_code":"CN",
    "gn:dem":1330,
    "gn:feature_class":"P",
    "gn:feature_code":"PPL",
    "gn:name":"Qiboji",
    "gn:population":0,
    "gn:timezone":"Asia/Shanghai",
    "iso:country":"CN",
    "name:zho_x_preferred":[
        "\u4e03\u7c38\u7b95"
    ],
    "wof:name":"Qiboji",
    "wof:placetype":"locality"
},
  "geometry": {"coordinates":[104.74736,32.20693],"type":"Point"}
}