{
  "type": "Feature",
  "properties": {
    "gn:admin1_code":"11",
    "gn:asciiname":"Tangzhaimian",
    "gn:country_code":"CN",
    "gn:dem":522,
    "gn:feature_class":"P",
    "gn:feature_code":"PPL",
    "gn:name":"Tangzhaimian",
    "gn:population":0,
    "gn:timezone":"Asia/Shanghai",
    "iso:country":"CN",
    "name:zho_x_preferred":[
        "\u5858\u5be8\u9762"
    ],
    "wof:name":"Tangzhaimian",
    "wof:placetype":"locality"
},
  "geometry": {"coordinates":[111.76106,25.2831],"type":"Point"}
}