{
  "type": "Feature",
  "properties": {
    "gn:admin1_code":"12.0",
    "gn:asciiname":"Linjiapo",
    "gn:country_code":"CN",
    "gn:dem":104,
    "gn:feature_class":"P",
    "gn:feature_code":"PPL",
    "gn:name":"Linjiapo",
    "gn:population":0,
    "gn:timezone":"Asia/Shanghai",
    "iso:country":"CN",
    "name:zho_x_preferred":[
        "\u6797\u5bb6\u5761"
    ],
    "wof:name":"Linjiapo",
    "wof:placetype":"locality"
},
  "geometry": {"coordinates":[112.16005,31.37137],"type":"Point"}
}