{
  "type": "Feature",
  "properties": {
    "gn:admin1_code":"26.0",
    "gn:asciiname":"Nihekoucun",
    "gn:country_code":"CN",
    "gn:dem":953,
    "gn:feature_class":"P",
    "gn:feature_code":"PPL",
    "gn:name":"Nihekoucun",
    "gn:population":0,
    "gn:timezone":"Asia/Shanghai",
    "iso:country":"CN",
    "name:zho_x_preferred":[
        "\u6ce5\u6cb3\u53e3\u6751"
    ],
    "wof:name":"Nihekoucun",
    "wof:placetype":"locality"
},
  "geometry": {"coordinates":[109.84546,36.67179],"type":"Point"}
}