{
  "type": "Feature",
  "properties": {
    "gn:admin1_code":"12.0",
    "gn:asciiname":"Fenghuang Dadui",
    "gn:country_code":"CN",
    "gn:dem":42,
    "gn:feature_class":"P",
    "gn:feature_code":"PPLF",
    "gn:name":"Fenghuang Dadui",
    "gn:population":0,
    "gn:timezone":"Asia/Shanghai",
    "iso:country":"CN",
    "name:zho_x_preferred":[
        "Fenghuang Dadui"
    ],
    "name:zho_x_variant":[
        "\u51e4\u51f0\u5927\u961f"
    ],
    "wof:name":"Fenghuang Dadui",
    "wof:placetype":"locality"
},
  "geometry": {"coordinates":[114.06026,29.88161],"type":"Point"}
}