{
  "type": "Feature",
  "properties": {
    "gn:admin1_code":"32.0",
    "gn:asciiname":"Houposhu",
    "gn:country_code":"CN",
    "gn:dem":1288,
    "gn:feature_class":"P",
    "gn:feature_code":"PPL",
    "gn:name":"Houposhu",
    "gn:population":0,
    "gn:timezone":"Asia/Shanghai",
    "iso:country":"CN",
    "name:zho_x_preferred":[
        "\u539a\u6734\u6811"
    ],
    "wof:name":"Houposhu",
    "wof:placetype":"locality"
},
  "geometry": {"coordinates":[104.63481,32.20047],"type":"Point"}
}