{
  "type": "Feature",
  "properties": {
    "gn:admin1_code":"33.0",
    "gn:asciiname":"Tingxi",
    "gn:country_code":"CN",
    "gn:dem":203,
    "gn:feature_class":"P",
    "gn:feature_code":"PPL",
    "gn:name":"Tingxi",
    "gn:population":0,
    "gn:timezone":"Asia/Shanghai",
    "iso:country":"CN",
    "name:zho_x_preferred":[
        "\u6c40\u6eaa"
    ],
    "wof:name":"Tingxi",
    "wof:placetype":"locality"
},
  "geometry": {"coordinates":[107.84443,30.04369],"type":"Point"}
}