{
  "type": "Feature",
  "properties": {
    "gn:admin1_code":"3.0",
    "gn:asciiname":"Xianyuanzhuang",
    "gn:country_code":"CN",
    "gn:dem":162,
    "gn:feature_class":"P",
    "gn:feature_code":"PPL",
    "gn:name":"Xianyuanzhuang",
    "gn:population":0,
    "gn:timezone":"Asia/Shanghai",
    "iso:country":"CN",
    "name:und_x_variant":[
        "\u4ed9\u6e90\u5e84"
    ],
    "wof:name":"Xianyuanzhuang",
    "wof:placetype":"locality"
},
  "geometry": {"coordinates":[116.89086,27.87523],"type":"Point"}
}