{
  "type": "Feature",
  "properties": {
    "gn:admin1_code":"5.0",
    "gn:asciiname":"Sanshijiucun",
    "gn:country_code":"CN",
    "gn:dem":149,
    "gn:feature_class":"P",
    "gn:feature_code":"PPL",
    "gn:name":"Sanshijiucun",
    "gn:population":0,
    "gn:timezone":"Asia/Shanghai",
    "iso:country":"CN",
    "name:zho_x_preferred":[
        "\u4e09\u5341\u4e5d\u6751"
    ],
    "wof:name":"Sanshijiucun",
    "wof:placetype":"locality"
},
  "geometry": {"coordinates":[123.21099,44.45599],"type":"Point"}
}