{
  "type": "Feature",
  "properties": {
    "gn:admin1_code":"30",
    "gn:asciiname":"Toubuhe",
    "gn:country_code":"CN",
    "gn:dem":54,
    "gn:feature_class":"P",
    "gn:feature_code":"PPL",
    "gn:name":"Toubuhe",
    "gn:population":0,
    "gn:timezone":"Asia/Shanghai",
    "iso:country":"CN",
    "name:zho_x_preferred":[
        "\u5934\u6b65\u6cb3"
    ],
    "wof:name":"Toubuhe",
    "wof:placetype":"locality"
},
  "geometry": {"coordinates":[112.23524999999999,23.20935],"type":"Point"}
}