{
  "type": "Feature",
  "properties": {
    "gn:admin1_code":"12.0",
    "gn:asciiname":"Tieluzhai",
    "gn:country_code":"CN",
    "gn:dem":1298,
    "gn:feature_class":"P",
    "gn:feature_code":"PPL",
    "gn:name":"Tieluzhai",
    "gn:population":0,
    "gn:timezone":"Asia/Shanghai",
    "iso:country":"CN",
    "name:zho_x_preferred":[
        "\u94c1\u7089\u5be8"
    ],
    "wof:name":"Tieluzhai",
    "wof:placetype":"locality"
},
  "geometry": {"coordinates":[108.90031,30.37501],"type":"Point"}
}