{
  "type": "Feature",
  "properties": {
    "gn:admin1_code":"3.0",
    "gn:asciiname":"Hanfang Dingjia",
    "gn:country_code":"CN",
    "gn:dem":39,
    "gn:feature_class":"P",
    "gn:feature_code":"PPL",
    "gn:name":"Hanfang Dingjia",
    "gn:population":0,
    "gn:timezone":"Asia/Shanghai",
    "iso:country":"CN",
    "name:und_x_variant":[
        "\u97e9\u574a\u4e01\u5bb6"
    ],
    "wof:name":"Hanfang Dingjia",
    "wof:placetype":"locality"
},
  "geometry": {"coordinates":[116.34314999999999,27.95133],"type":"Point"}
}