{
  "type": "Feature",
  "properties": {
    "gn:admin1_code":"7.0",
    "gn:asciiname":"Xiaotao",
    "gn:country_code":"CN",
    "gn:dem":246,
    "gn:feature_class":"P",
    "gn:feature_code":"PPLA4",
    "gn:name":"Xiaotao",
    "gn:population":0,
    "gn:timezone":"Asia/Shanghai",
    "iso:country":"CN",
    "name:und_x_variant":[
        "Ning-yang-hsien",
        "Hsiao-t\u2019ao",
        "Ning-yang",
        "Hsiao-t\u2019ao-hs\u00fc",
        "Xiaotao",
        "Xiaotao Zhen"
    ],
    "name:zho_x_preferred":[
        "\u5c0f\u9676"
    ],
    "name:zho_x_variant":[
        "\u5c0f\u9676\u9547"
    ],
    "wof:name":"Xiaotao",
    "wof:placetype":"locality"
},
  "geometry": {"coordinates":[117.12297,25.73075],"type":"Point"}
}