{
  "type": "Feature",
  "properties": {
    "gn:admin1_code":"24.0",
    "gn:asciiname":"Beizhangcun",
    "gn:country_code":"CN",
    "gn:dem":521,
    "gn:feature_class":"P",
    "gn:feature_code":"PPL",
    "gn:name":"Beizhangcun",
    "gn:population":0,
    "gn:timezone":"Asia/Shanghai",
    "iso:country":"CN",
    "name:zho_x_preferred":[
        "\u5317\u5f20\u6751"
    ],
    "wof:name":"Beizhangcun",
    "wof:placetype":"locality"
},
  "geometry": {"coordinates":[110.56778,35.15022],"type":"Point"}
}