{
  "type": "Feature",
  "properties": {
    "gn:admin1_code":"30",
    "gn:asciiname":"Caojiangxu",
    "gn:country_code":"CN",
    "gn:dem":45,
    "gn:feature_class":"P",
    "gn:feature_code":"PPL",
    "gn:name":"Caojiangxu",
    "gn:population":0,
    "gn:timezone":"Asia/Urumqi",
    "iso:country":"CN",
    "name:zho_x_preferred":[
        "\u66f9\u6c5f\u5729"
    ],
    "wof:name":"Caojiangxu",
    "wof:placetype":"locality"
},
  "geometry": {"coordinates":[110.90260000000001,21.97764],"type":"Point"}
}