{
  "type": "Feature",
  "properties": {
    "gn:admin1_code":"29.0",
    "gn:asciiname":"Shuilu",
    "gn:country_code":"CN",
    "gn:dem":1992,
    "gn:feature_class":"P",
    "gn:feature_code":"PPL",
    "gn:name":"Shuilu",
    "gn:population":0,
    "gn:timezone":"Asia/Shanghai",
    "iso:country":"CN",
    "name:zho_x_preferred":[
        "\u6c34\u7089"
    ],
    "wof:name":"Shuilu",
    "wof:placetype":"locality"
},
  "geometry": {"coordinates":[99.80029999999999,24.9974],"type":"Point"}
}