{
  "type": "Feature",
  "properties": {
    "gn:admin1_code":"19.0",
    "gn:asciiname":"Yangguangcun",
    "gn:country_code":"CN",
    "gn:dem":231,
    "gn:feature_class":"P",
    "gn:feature_code":"PPL",
    "gn:name":"Yangguangcun",
    "gn:population":0,
    "gn:timezone":"Asia/Shanghai",
    "iso:country":"CN",
    "name:zho_x_preferred":[
        "\u9633\u5e7f\u6751"
    ],
    "wof:name":"Yangguangcun",
    "wof:placetype":"locality"
},
  "geometry": {"coordinates":[125.509,40.8731],"type":"Point"}
}