{
  "type": "Feature",
  "properties": {
    "gn:admin1_code":"26",
    "gn:asciiname":"Shunning",
    "gn:country_code":"CN",
    "gn:dem":1412,
    "gn:feature_class":"P",
    "gn:feature_code":"PPL",
    "gn:name":"Shunning",
    "gn:population":0,
    "gn:timezone":"Asia/Shanghai",
    "iso:country":"CN",
    "name:heb_x_preferred":[
        "\u05d7\u05e8\u05dd \u05d7\u05d1\u05e8\u05ea\u05d9"
    ],
    "name:jpn_x_preferred":[
        "\u5171\u540c\u7d76\u4ea4"
    ],
    "name:swe_x_preferred":[
        "Utfrysning"
    ],
    "wof:name":"Shunning",
    "wof:placetype":"locality"
},
  "geometry": {"coordinates":[108.63333,36.95],"type":"Point"}
}