{
  "type": "Feature",
  "properties": {
    "gn:admin1_code":"20.0",
    "gn:asciiname":"Wudazhan",
    "gn:cc2":"CN",
    "gn:country_code":"CN",
    "gn:dem":1208,
    "gn:feature_class":"P",
    "gn:feature_code":"PPL",
    "gn:name":"Wudazhan",
    "gn:population":0,
    "gn:timezone":"Asia/Shanghai",
    "iso:country":"CN",
    "name:und_x_variant":[
        "Wu-ta-chan",
        "Wudazhan"
    ],
    "wof:name":"Wudazhan",
    "wof:placetype":"locality"
},
  "geometry": {"coordinates":[106.68333,39.41667],"type":"Point"}
}