{
  "type": "Feature",
  "properties": {
    "gn:admin1_code":"4.0",
    "gn:asciiname":"Sanlidang",
    "gn:country_code":"CN",
    "gn:dem":5,
    "gn:feature_class":"P",
    "gn:feature_code":"PPL",
    "gn:name":"Sanlidang",
    "gn:population":0,
    "gn:timezone":"Asia/Shanghai",
    "iso:country":"CN",
    "name:und_x_variant":[
        "\u4e09\u91cc\u8361"
    ],
    "name:zho_x_preferred":[
        "\u4e09\u91cc\u8361"
    ],
    "wof:name":"Sanlidang",
    "wof:placetype":"locality"
},
  "geometry": {"coordinates":[120.02028,32.58974],"type":"Point"}
}