{
  "type": "Feature",
  "properties": {
    "gn:admin1_code":"1.0",
    "gn:asciiname":"Zhanjiagang",
    "gn:country_code":"CN",
    "gn:dem":27,
    "gn:feature_class":"P",
    "gn:feature_code":"PPL",
    "gn:name":"Zhanjiagang",
    "gn:population":0,
    "gn:timezone":"Asia/Shanghai",
    "iso:country":"CN",
    "name:zho_x_preferred":[
        "\u8a79\u5bb6\u5c97"
    ],
    "wof:name":"Zhanjiagang",
    "wof:placetype":"locality"
},
  "geometry": {"coordinates":[116.28789999999999,32.6463],"type":"Point"}
}