{
  "type": "Feature",
  "properties": {
    "gn:admin1_code":"1.0",
    "gn:asciiname":"Zhaomiaocun",
    "gn:country_code":"CN",
    "gn:dem":39,
    "gn:feature_class":"P",
    "gn:feature_code":"PPL",
    "gn:name":"Zhaomiaocun",
    "gn:population":0,
    "gn:timezone":"Asia/Shanghai",
    "iso:country":"CN",
    "name:zho_x_preferred":[
        "\u8d75\u5e99\u6751"
    ],
    "wof:name":"Zhaomiaocun",
    "wof:placetype":"locality"
},
  "geometry": {"coordinates":[115.25524,32.90988],"type":"Point"}
}