{
  "type": "Feature",
  "properties": {
    "gn:admin1_code":"11",
    "gn:asciiname":"Youpuli",
    "gn:country_code":"CN",
    "gn:dem":151,
    "gn:feature_class":"P",
    "gn:feature_code":"PPL",
    "gn:name":"Youpuli",
    "gn:population":0,
    "gn:timezone":"Asia/Shanghai",
    "iso:country":"CN",
    "name:zho_x_preferred":[
        "\u6cb9\u94fa\u91cc"
    ],
    "wof:name":"Youpuli",
    "wof:placetype":"locality"
},
  "geometry": {"coordinates":[111.53035,26.31858],"type":"Point"}
}