{
  "type": "Feature",
  "properties": {
    "gn:admin1_code":"29.0",
    "gn:asciiname":"Xiabing'an",
    "gn:country_code":"CN",
    "gn:dem":1416,
    "gn:feature_class":"P",
    "gn:feature_code":"PPL",
    "gn:name":"Xiabing\u2019an",
    "gn:population":0,
    "gn:timezone":"Asia/Shanghai",
    "iso:country":"CN",
    "name:und_x_variant":[
        "Xiabing\u2019an"
    ],
    "name:zho_x_preferred":[
        "\u4e0b\u79c9\u5b89"
    ],
    "wof:name":"Xiabing'an",
    "wof:placetype":"locality"
},
  "geometry": {"coordinates":[101.471,23.1274],"type":"Point"}
}