{
  "type": "Feature",
  "properties": {
    "gn:admin1_code":"7.0",
    "gn:asciiname":"He'an",
    "gn:country_code":"CN",
    "gn:dem":553,
    "gn:feature_class":"P",
    "gn:feature_code":"PPL",
    "gn:name":"He\u2019an",
    "gn:population":0,
    "gn:timezone":"Asia/Shanghai",
    "iso:country":"CN",
    "name:und_x_variant":[
        "He\u2019an"
    ],
    "name:zho_x_preferred":[
        "\u548c\u5b89"
    ],
    "wof:name":"He'an",
    "wof:placetype":"locality"
},
  "geometry": {"coordinates":[116.26345000000001,24.97091],"type":"Point"}
}