{
  "type": "Feature",
  "properties": {
    "gn:admin1_code":"29.0",
    "gn:asciiname":"Jingfan",
    "gn:country_code":"CN",
    "gn:dem":1160,
    "gn:feature_class":"P",
    "gn:feature_code":"PPL",
    "gn:name":"Jingfan",
    "gn:population":0,
    "gn:timezone":"Asia/Shanghai",
    "iso:country":"CN",
    "name:zho_x_preferred":[
        "\u666f\u8303"
    ],
    "wof:name":"Jingfan",
    "wof:placetype":"locality"
},
  "geometry": {"coordinates":[100.83,24.4717],"type":"Point"}
}