{
  "type": "Feature",
  "properties": {
    "gn:admin1_code":"30.0",
    "gn:asciiname":"Banpu",
    "gn:country_code":"CN",
    "gn:dem":6,
    "gn:feature_class":"P",
    "gn:feature_code":"PPL",
    "gn:name":"Banpu",
    "gn:population":0,
    "gn:timezone":"Asia/Shanghai",
    "iso:country":"CN",
    "name:deu_x_preferred":[
        "Banpu"
    ],
    "name:jpn_x_preferred":[
        "\u30d0\u30f3\u30d7\u30fc"
    ],
    "name:tha_x_preferred":[
        "\u0e1a\u0e49\u0e32\u0e19\u0e1b\u0e39"
    ],
    "name:zho_x_preferred":[
        "\u534a\u57d4"
    ],
    "wof:name":"Banpu",
    "wof:placetype":"locality"
},
  "geometry": {"coordinates":[115.57312,22.89058],"type":"Point"}
}