{
  "type": "Feature",
  "properties": {
    "gn:admin1_code":"30.0",
    "gn:asciiname":"Hengshanbei",
    "gn:country_code":"CN",
    "gn:dem":686,
    "gn:feature_class":"P",
    "gn:feature_code":"PPL",
    "gn:name":"Hengshanbei",
    "gn:population":0,
    "gn:timezone":"Asia/Shanghai",
    "iso:country":"CN",
    "name:zho_x_preferred":[
        "Hengshanbei"
    ],
    "name:zho_x_variant":[
        "\u6a2a\u5c71\u8d1d"
    ],
    "wof:name":"Hengshanbei",
    "wof:placetype":"locality"
},
  "geometry": {"coordinates":[115.39111,24.68556],"type":"Point"}
}