{
  "type": "Feature",
  "properties": {
    "gn:admin1_code":"12.0",
    "gn:asciiname":"Ningjiayu",
    "gn:country_code":"CN",
    "gn:dem":117,
    "gn:feature_class":"P",
    "gn:feature_code":"PPL",
    "gn:name":"Ningjiayu",
    "gn:population":0,
    "gn:timezone":"Asia/Shanghai",
    "iso:country":"CN",
    "name:zho_x_preferred":[
        "Ningjiayu"
    ],
    "name:zho_x_variant":[
        "\u5b81\u5bb6\u5cea"
    ],
    "wof:name":"Ningjiayu",
    "wof:placetype":"locality"
},
  "geometry": {"coordinates":[111.58938000000001,29.91559],"type":"Point"}
}