{
  "type": "Feature",
  "properties": {
    "gn:admin1_code":"32.0",
    "gn:asciiname":"Liang'an",
    "gn:country_code":"CN",
    "gn:dem":644,
    "gn:feature_class":"P",
    "gn:feature_code":"PPL",
    "gn:name":"Liang\u2019an",
    "gn:population":0,
    "gn:timezone":"Asia/Shanghai",
    "iso:country":"CN",
    "name:und_x_variant":[
        "Liang\u2019an"
    ],
    "name:zho_x_preferred":[
        "\u4e24\u5cb8"
    ],
    "wof:name":"Liang'an",
    "wof:placetype":"locality"
},
  "geometry": {"coordinates":[104.887,28.2717],"type":"Point"}
}