{
  "type": "Feature",
  "properties": {
    "gn:admin1_code":"08",
    "gn:asciiname":"Hexiaohuaitun",
    "gn:country_code":"CN",
    "gn:dem":137,
    "gn:feature_class":"P",
    "gn:feature_code":"PPL",
    "gn:name":"Hexiaohuaitun",
    "gn:population":0,
    "gn:timezone":"Asia/Shanghai",
    "iso:country":"CN",
    "name:und_x_variant":[
        "Ho-hsiao-huai",
        "Hexiaohuaitun"
    ],
    "name:zho_x_preferred":[
        "\u4f55\u5c0f\u6000\u5c6f"
    ],
    "wof:name":"Hexiaohuaitun",
    "wof:placetype":"locality"
},
  "geometry": {"coordinates":[126.28167000000001,46.56056],"type":"Point"}
}