{
  "type": "Feature",
  "properties": {
    "gn:admin1_code":"13",
    "gn:asciiname":"Saikailesayi",
    "gn:country_code":"CN",
    "gn:dem":1523,
    "gn:feature_class":"P",
    "gn:feature_code":"PPL",
    "gn:name":"Saikailesayi",
    "gn:population":0,
    "gn:timezone":"Asia/Urumqi",
    "iso:country":"CN",
    "name:und_x_variant":[
        "\u8d5b\u5f00\u52d2\u8428\u4f9d"
    ],
    "wof:name":"Saikailesayi",
    "wof:placetype":"locality"
},
  "geometry": {"coordinates":[91.46733999999999,43.9532],"type":"Point"}
}