{
  "type": "Feature",
  "properties": {
    "gn:admin1_code":"2.0",
    "gn:asciiname":"Taotianmen",
    "gn:country_code":"CN",
    "gn:dem":14,
    "gn:feature_class":"P",
    "gn:feature_code":"PPL",
    "gn:name":"Taotianmen",
    "gn:population":0,
    "gn:timezone":"Asia/Shanghai",
    "iso:country":"CN",
    "name:zho_x_preferred":[
        "\u6843\u5929\u95e8"
    ],
    "wof:name":"Taotianmen",
    "wof:placetype":"locality"
},
  "geometry": {"coordinates":[121.94795999999999,30.10022],"type":"Point"}
}