{
  "type": "Feature",
  "properties": {
    "gn:admin1_code":"5.0",
    "gn:asciiname":"Sanmen Songjia",
    "gn:country_code":"CN",
    "gn:dem":182,
    "gn:feature_class":"P",
    "gn:feature_code":"PPL",
    "gn:name":"Sanmen Songjia",
    "gn:population":0,
    "gn:timezone":"Asia/Shanghai",
    "iso:country":"CN",
    "name:zho_x_preferred":[
        "\u4e09\u95e8\u5b8b\u5bb6"
    ],
    "wof:name":"Sanmen Songjia",
    "wof:placetype":"locality"
},
  "geometry": {"coordinates":[124.33597,43.4256],"type":"Point"}
}