{
  "type": "Feature",
  "properties": {
    "gn:admin1_code":"19.0",
    "gn:asciiname":"Chahuayingzi",
    "gn:country_code":"CN",
    "gn:dem":625,
    "gn:feature_class":"P",
    "gn:feature_code":"PPL",
    "gn:name":"Chahuayingzi",
    "gn:population":0,
    "gn:timezone":"Asia/Shanghai",
    "iso:country":"CN",
    "name:zho_x_preferred":[
        "\u63d2\u82b1\u8425\u5b50"
    ],
    "wof:name":"Chahuayingzi",
    "wof:placetype":"locality"
},
  "geometry": {"coordinates":[119.71323,42.11128],"type":"Point"}
}