{
  "type": "Feature",
  "properties": {
    "gn:admin1_code":"15.0",
    "gn:asciiname":"Songhuangwan",
    "gn:country_code":"CN",
    "gn:dem":1441,
    "gn:feature_class":"P",
    "gn:feature_code":"PPL",
    "gn:name":"Songhuangwan",
    "gn:population":0,
    "gn:timezone":"Asia/Shanghai",
    "iso:country":"CN",
    "name:und_x_variant":[
        "\u5b8b\u9ec4\u6e7e"
    ],
    "wof:name":"Songhuangwan",
    "wof:placetype":"locality"
},
  "geometry": {"coordinates":[107.68254,36.69165],"type":"Point"}
}