{
  "type": "Feature",
  "properties": {
    "gn:admin1_code":"4.0",
    "gn:asciiname":"Shahuitou",
    "gn:country_code":"CN",
    "gn:dem":12,
    "gn:feature_class":"P",
    "gn:feature_code":"PPL",
    "gn:name":"Shahuitou",
    "gn:population":0,
    "gn:timezone":"Asia/Shanghai",
    "iso:country":"CN",
    "name:zho_x_preferred":[
        "\u6c99\u7070\u5934"
    ],
    "wof:name":"Shahuitou",
    "wof:placetype":"locality"
},
  "geometry": {"coordinates":[119.7141,32.11407],"type":"Point"}
}