{
  "type": "Feature",
  "properties": {
    "gn:admin1_code":"5.0",
    "gn:asciiname":"Xiaobu",
    "gn:country_code":"CN",
    "gn:dem":512,
    "gn:feature_class":"P",
    "gn:feature_code":"PPL",
    "gn:name":"Xiaobu",
    "gn:population":0,
    "gn:timezone":"Asia/Shanghai",
    "iso:country":"CN",
    "name:und_x_variant":[
        "Xiaobao",
        "\u5c0f\u5821",
        "Xiaobu"
    ],
    "wof:name":"Xiaobu",
    "wof:placetype":"locality"
},
  "geometry": {"coordinates":[125.31146,41.92119],"type":"Point"}
}