{
  "type": "Feature",
  "properties": {
    "gn:admin1_code":"10",
    "gn:asciiname":"Aobao Gounao",
    "gn:country_code":"CN",
    "gn:dem":1032,
    "gn:feature_class":"P",
    "gn:feature_code":"PPL",
    "gn:name":"Aobao Gounao",
    "gn:population":0,
    "gn:timezone":"Asia/Shanghai",
    "iso:country":"CN",
    "name:zho_x_preferred":[
        "\u6556\u5305\u6c9f\u8111"
    ],
    "wof:name":"Aobao Gounao",
    "wof:placetype":"locality"
},
  "geometry": {"coordinates":[117.27118,41.71257],"type":"Point"}
}