{
  "type": "Feature",
  "properties": {
    "gn:admin1_code":"20",
    "gn:asciiname":"Xishan",
    "gn:cc2":"CN",
    "gn:country_code":"CN",
    "gn:dem":604,
    "gn:feature_class":"P",
    "gn:feature_code":"PPL",
    "gn:name":"Xishan",
    "gn:population":0,
    "gn:timezone":"Asia/Shanghai",
    "iso:country":"CN",
    "name:und_x_variant":[
        "Hsi-shan",
        "Xishan"
    ],
    "wof:name":"Xishan",
    "wof:placetype":"locality"
},
  "geometry": {"coordinates":[119.05833,42.60472],"type":"Point"}
}