{
  "type": "Feature",
  "properties": {
    "gn:admin1_code":"2.0",
    "gn:asciiname":"Lidong",
    "gn:country_code":"CN",
    "gn:dem":7,
    "gn:feature_class":"P",
    "gn:feature_code":"PPL",
    "gn:name":"Lidong",
    "gn:population":0,
    "gn:timezone":"Asia/Shanghai",
    "iso:country":"CN",
    "name:afr_x_preferred":[
        "Lidong"
    ],
    "name:cdo_x_preferred":[
        "L\u012dk-d\u0115\u0324ng"
    ],
    "name:hak_x_preferred":[
        "Li\u030dp-t\u00fbng"
    ],
    "name:swe_x_preferred":[
        "Lidong"
    ],
    "name:und_x_variant":[
        "\u6ca5\u4e1c",
        "Lidongzhen",
        "\u6ca5\u4e1c\u9547"
    ],
    "name:vie_x_preferred":[
        "L\u1eadp \u0111\u00f4ng"
    ],
    "name:zha_x_preferred":[
        "Laebdoeng"
    ],
    "wof:name":"Lidong",
    "wof:placetype":"locality"
},
  "geometry": {"coordinates":[120.782,30.10592],"type":"Point"}
}