{
  "type": "Feature",
  "properties": {
    "gn:admin1_code":"25",
    "gn:asciiname":"Donggengwang",
    "gn:country_code":"CN",
    "gn:dem":48,
    "gn:feature_class":"P",
    "gn:feature_code":"PPL",
    "gn:name":"Donggengwang",
    "gn:population":0,
    "gn:timezone":"Asia/Shanghai",
    "iso:country":"CN",
    "name:zho_x_preferred":[
        "\u4e1c\u803f\u738b"
    ],
    "wof:name":"Donggengwang",
    "wof:placetype":"locality"
},
  "geometry": {"coordinates":[115.452,35.9298],"type":"Point"}
}