{
  "type": "Feature",
  "properties": {
    "gn:admin1_code":"16.0",
    "gn:asciiname":"Bujin",
    "gn:country_code":"CN",
    "gn:dem":536,
    "gn:feature_class":"P",
    "gn:feature_code":"PPL",
    "gn:name":"Bujin",
    "gn:population":0,
    "gn:timezone":"Asia/Shanghai",
    "iso:country":"CN",
    "name:ara_x_preferred":[
        "\u0628\u0648\u062c\u064a\u0646"
    ],
    "name:ceb_x_preferred":[
        "B\u016bj\u012bn"
    ],
    "name:fas_x_preferred":[
        "\u0628\u0648\u062c\u06cc\u0646"
    ],
    "name:msa_x_preferred":[
        "Bujin"
    ],
    "name:swe_x_preferred":[
        "B\u016bj\u012bn"
    ],
    "name:zho_x_preferred":[
        "\u5e03\u8fdb"
    ],
    "wof:name":"Bujin",
    "wof:placetype":"locality"
},
  "geometry": {"coordinates":[106.839,22.9243],"type":"Point"}
}