{
  "type": "Feature",
  "properties": {
    "gn:admin1_code":"16.0",
    "gn:asciiname":"Sanlu",
    "gn:country_code":"CN",
    "gn:dem":908,
    "gn:feature_class":"P",
    "gn:feature_code":"PPL",
    "gn:name":"Sanlu",
    "gn:population":0,
    "gn:timezone":"Asia/Shanghai",
    "iso:country":"CN",
    "name:zho_x_preferred":[
        "\u4e09\u9c81"
    ],
    "wof:name":"Sanlu",
    "wof:placetype":"locality"
},
  "geometry": {"coordinates":[106.048,23.1744],"type":"Point"}
}