{
  "type": "Feature",
  "properties": {
    "gn:admin1_code":"30",
    "gn:asciiname":"Dongtang",
    "gn:cc2":"CN",
    "gn:country_code":"CN",
    "gn:dem":4,
    "gn:feature_class":"P",
    "gn:feature_code":"PPL",
    "gn:name":"Dongtang",
    "gn:population":0,
    "gn:timezone":"Asia/Urumqi",
    "iso:country":"CN",
    "name:zho_x_preferred":[
        "Tung-t\u2019ang"
    ],
    "wof:name":"Dongtang",
    "wof:placetype":"locality"
},
  "geometry": {"coordinates":[110.41028,20.68778],"type":"Point"}
}