{
  "type": "Feature",
  "properties": {
    "gn:admin1_code":"4.0",
    "gn:asciiname":"Cha'an",
    "gn:country_code":"CN",
    "gn:dem":2,
    "gn:feature_class":"P",
    "gn:feature_code":"PPL",
    "gn:name":"Cha\u2019an",
    "gn:population":0,
    "gn:timezone":"Asia/Shanghai",
    "iso:country":"CN",
    "name:zho_x_preferred":[
        "Cha\u2019an"
    ],
    "name:zho_x_variant":[
        "\u8336\u5eb5",
        "\u8336\u5eb5\u9547"
    ],
    "wof:name":"Cha'an",
    "wof:placetype":"locality"
},
  "geometry": {"coordinates":[119.43344999999999,33.00793],"type":"Point"}
}