{
  "type": "Feature",
  "properties": {
    "gn:admin1_code":"1.0",
    "gn:asciiname":"Tiansicun",
    "gn:country_code":"CN",
    "gn:dem":22,
    "gn:feature_class":"P",
    "gn:feature_code":"PPL",
    "gn:name":"Tiansicun",
    "gn:population":0,
    "gn:timezone":"Asia/Shanghai",
    "iso:country":"CN",
    "name:zho_x_preferred":[
        "\u5929\u5bfa\u6751"
    ],
    "wof:name":"Tiansicun",
    "wof:placetype":"locality"
},
  "geometry": {"coordinates":[117.25485999999999,33.22431],"type":"Point"}
}