{
  "type": "Feature",
  "properties": {
    "gn:admin1_code":"32",
    "gn:asciiname":"Longquanguan",
    "gn:country_code":"CN",
    "gn:dem":467,
    "gn:feature_class":"P",
    "gn:feature_code":"PPL",
    "gn:name":"Longquanguan",
    "gn:population":0,
    "gn:timezone":"Asia/Shanghai",
    "iso:country":"CN",
    "name:zho_x_preferred":[
        "\u9f99\u6cc9\u7f50"
    ],
    "wof:name":"Longquanguan",
    "wof:placetype":"locality"
},
  "geometry": {"coordinates":[106.53279999999999,30.45232],"type":"Point"}
}