{
  "type": "Feature",
  "properties": {
    "gn:admin1_code":"7",
    "gn:asciiname":"Yangjiaxi",
    "gn:country_code":"CN",
    "gn:dem":578,
    "gn:feature_class":"P",
    "gn:feature_code":"PPL",
    "gn:name":"Yangjiaxi",
    "gn:population":0,
    "gn:timezone":"Asia/Shanghai",
    "iso:country":"CN",
    "name:und_x_variant":[
        "\u6768\u5bb6\u6eaa",
        "Yangjiaxi"
    ],
    "wof:name":"Yangjiaxi",
    "wof:placetype":"locality"
},
  "geometry": {"coordinates":[119.93362,27.10784],"type":"Point"}
}