{
  "type": "Feature",
  "properties": {
    "gn:admin1_code":"25",
    "gn:asciiname":"Houlaowang",
    "gn:country_code":"CN",
    "gn:dem":51,
    "gn:feature_class":"P",
    "gn:feature_code":"PPL",
    "gn:name":"Houlaowang",
    "gn:population":0,
    "gn:timezone":"Asia/Shanghai",
    "iso:country":"CN",
    "name:zho_x_preferred":[
        "\u540e\u8001\u738b"
    ],
    "wof:name":"Houlaowang",
    "wof:placetype":"locality"
},
  "geometry": {"coordinates":[115.66257,35.624],"type":"Point"}
}