{
  "type": "Feature",
  "properties": {
    "gn:admin1_code":"26",
    "gn:asciiname":"Longting",
    "gn:cc2":"CN",
    "gn:country_code":"CN",
    "gn:dem":480,
    "gn:feature_class":"P",
    "gn:feature_code":"PPL",
    "gn:name":"Longting",
    "gn:population":0,
    "gn:timezone":"Asia/Shanghai",
    "iso:country":"CN",
    "name:und_x_variant":[
        "Longtingpu",
        "Lung-t\u2019ing",
        "Longting"
    ],
    "wof:name":"Longting",
    "wof:placetype":"locality"
},
  "geometry": {"coordinates":[107.65694000000001,33.21],"type":"Point"}
}