{
  "type": "Feature",
  "properties": {
    "gn:admin1_code":"26.0",
    "gn:asciiname":"Baimugou",
    "gn:country_code":"CN",
    "gn:dem":721,
    "gn:feature_class":"P",
    "gn:feature_code":"PPL",
    "gn:name":"Baimugou",
    "gn:population":0,
    "gn:timezone":"Asia/Shanghai",
    "iso:country":"CN",
    "name:zho_x_preferred":[
        "\u67cf\u6728\u6c9f"
    ],
    "wof:name":"Baimugou",
    "wof:placetype":"locality"
},
  "geometry": {"coordinates":[110.81388,33.15977],"type":"Point"}
}