{
  "type": "Feature",
  "properties": {
    "gn:admin1_code":"15.0",
    "gn:asciiname":"Kajia",
    "gn:country_code":"CN",
    "gn:dem":3093,
    "gn:feature_class":"P",
    "gn:feature_code":"PPL",
    "gn:name":"Kajia",
    "gn:population":0,
    "gn:timezone":"Asia/Shanghai",
    "iso:country":"CN",
    "name:und_x_variant":[
        "\u5361\u52a0"
    ],
    "wof:name":"Kajia",
    "wof:placetype":"locality"
},
  "geometry": {"coordinates":[102.44213999999999,35.35809000000001],"type":"Point"}
}