{
  "type": "Feature",
  "properties": {
    "gn:admin1_code":"7.0",
    "gn:asciiname":"Shangxiangtikeng",
    "gn:country_code":"CN",
    "gn:dem":271,
    "gn:feature_class":"P",
    "gn:feature_code":"PPL",
    "gn:name":"Shangxiangtikeng",
    "gn:population":0,
    "gn:timezone":"Asia/Shanghai",
    "iso:country":"CN",
    "name:zho_x_preferred":[
        "\u4e0a\u8c61\u8e44\u5751"
    ],
    "wof:name":"Shangxiangtikeng",
    "wof:placetype":"locality"
},
  "geometry": {"coordinates":[116.5187,24.8178],"type":"Point"}
}