{
  "type": "Feature",
  "properties": {
    "gn:admin1_code":"11.0",
    "gn:asciiname":"Liuzhenxiang",
    "gn:country_code":"CN",
    "gn:dem":50,
    "gn:feature_class":"P",
    "gn:feature_code":"PPL",
    "gn:name":"Liuzhenxiang",
    "gn:population":0,
    "gn:timezone":"Asia/Shanghai",
    "iso:country":"CN",
    "name:zho_x_preferred":[
        "\u5218\u796f\u7965"
    ],
    "wof:name":"Liuzhenxiang",
    "wof:placetype":"locality"
},
  "geometry": {"coordinates":[113.42067,29.12254],"type":"Point"}
}