{
  "type": "Feature",
  "properties": {
    "gn:admin1_code":"11.0",
    "gn:asciiname":"Bugutang",
    "gn:country_code":"CN",
    "gn:dem":129,
    "gn:feature_class":"P",
    "gn:feature_code":"PPL",
    "gn:name":"Bugutang",
    "gn:population":0,
    "gn:timezone":"Asia/Shanghai",
    "iso:country":"CN",
    "name:zho_x_preferred":[
        "\u5e03\u8c37\u5858"
    ],
    "wof:name":"Bugutang",
    "wof:placetype":"locality"
},
  "geometry": {"coordinates":[112.52576999999999,27.22389],"type":"Point"}
}