{
  "type": "Feature",
  "properties": {
    "gn:admin1_code":"4.0",
    "gn:asciiname":"Huanchi",
    "gn:country_code":"CN",
    "gn:dem":5,
    "gn:feature_class":"P",
    "gn:feature_code":"PPL",
    "gn:name":"Huanchi",
    "gn:population":0,
    "gn:timezone":"Asia/Shanghai",
    "iso:country":"CN",
    "name:zho_x_preferred":[
        "\u73af\u6c60"
    ],
    "wof:name":"Huanchi",
    "wof:placetype":"locality"
},
  "geometry": {"coordinates":[120.42852999999999,32.1709],"type":"Point"}
}