{
  "type": "Feature",
  "properties": {
    "gn:admin1_code":"26.0",
    "gn:asciiname":"Guzhuangkuo",
    "gn:country_code":"CN",
    "gn:dem":1299,
    "gn:feature_class":"P",
    "gn:feature_code":"PPL",
    "gn:name":"Guzhuangkuo",
    "gn:population":0,
    "gn:timezone":"Asia/Shanghai",
    "iso:country":"CN",
    "name:zho_x_preferred":[
        "\u53e4\u5e84\u5ed3"
    ],
    "wof:name":"Guzhuangkuo",
    "wof:placetype":"locality"
},
  "geometry": {"coordinates":[108.93595000000001,37.07095],"type":"Point"}
}