{
  "type": "Feature",
  "properties": {
    "gn:admin1_code":"19.0",
    "gn:asciiname":"Chuangoucun",
    "gn:country_code":"CN",
    "gn:dem":182,
    "gn:feature_class":"P",
    "gn:feature_code":"PPL",
    "gn:name":"Chuangoucun",
    "gn:population":0,
    "gn:timezone":"Asia/Shanghai",
    "iso:country":"CN",
    "name:und_x_variant":[
        "\u5ddd\u6c9f\u6751"
    ],
    "name:zho_x_preferred":[
        "\u5ddd\u6c9f\u6751"
    ],
    "wof:name":"Chuangoucun",
    "wof:placetype":"locality"
},
  "geometry": {"coordinates":[125.60877000000001,40.87382],"type":"Point"}
}