{
  "type": "Feature",
  "properties": {
    "gn:admin1_code":"26",
    "gn:asciiname":"Ningshan Chengguanzhen",
    "gn:country_code":"CN",
    "gn:dem":911,
    "gn:feature_class":"P",
    "gn:feature_code":"PPLA3",
    "gn:name":"Ningshan Chengguanzhen",
    "gn:population":0,
    "gn:timezone":"Asia/Shanghai",
    "iso:country":"CN",
    "name:und_x_variant":[
        "Jiuningshan",
        "Ningsiating",
        "Lao-ch\u2019eng",
        "Ningshen-hsien",
        "Chiu-ning-shan",
        "Ning-shan-hsien",
        "Ninshan",
        "Ningshan",
        "Ningshan Chengguanzhen",
        "Ningshan Xian"
    ],
    "name:zho_x_preferred":[
        "\u5b81\u9655\u57ce\u5173\u9547"
    ],
    "name:zho_x_variant":[
        "\u5b81\u9655\u53bf"
    ],
    "wof:name":"Ningshan Chengguanzhen",
    "wof:placetype":"locality"
},
  "geometry": {"coordinates":[108.30685,33.33153],"type":"Point"}
}