{
  "type": "Feature",
  "properties": {
    "gn:admin1_code":"4.0",
    "gn:asciiname":"Quyangcun",
    "gn:country_code":"CN",
    "gn:dem":21,
    "gn:feature_class":"P",
    "gn:feature_code":"PPL",
    "gn:name":"Quyangcun",
    "gn:population":0,
    "gn:timezone":"Asia/Shanghai",
    "iso:country":"CN",
    "name:und_x_variant":[
        "\u66f2\u9633\u6751"
    ],
    "wof:name":"Quyangcun",
    "wof:placetype":"locality"
},
  "geometry": {"coordinates":[118.68828999999999,34.45392],"type":"Point"}
}