{
  "type": "Feature",
  "properties": {
    "gn:admin1_code":"7",
    "gn:asciiname":"Tianzhong",
    "gn:country_code":"CN",
    "gn:dem":23,
    "gn:feature_class":"P",
    "gn:feature_code":"PPL",
    "gn:name":"Tianzhong",
    "gn:population":0,
    "gn:timezone":"Asia/Shanghai",
    "iso:country":"CN",
    "name:hak_x_preferred":[
        "Thi\u00e8n-ch\u00fbng-ch\u1e73\u0301n"
    ],
    "name:ita_x_preferred":[
        "Tianzhong"
    ],
    "name:jpn_x_preferred":[
        "\u7530\u4e2d\u93ae"
    ],
    "name:kor_x_preferred":[
        "\ud188\uc911\uc9c4"
    ],
    "name:pol_x_preferred":[
        "Tianzhong"
    ],
    "name:vie_x_preferred":[
        "\u0110i\u1ec1n Trung"
    ],
    "name:zho_x_preferred":[
        "\u7530\u4e2d"
    ],
    "name:zho_x_variant":[
        "\u7530\u4e2d\u93ae"
    ],
    "wof:name":"Tianzhong",
    "wof:placetype":"locality"
},
  "geometry": {"coordinates":[119.78833,25.53917],"type":"Point"}
}