{
  "type": "Feature",
  "properties": {
    "gn:admin1_code":"12.0",
    "gn:asciiname":"Huoguanmiao",
    "gn:country_code":"CN",
    "gn:dem":38,
    "gn:feature_class":"P",
    "gn:feature_code":"PPL",
    "gn:name":"Huoguanmiao",
    "gn:population":0,
    "gn:timezone":"Asia/Shanghai",
    "iso:country":"CN",
    "name:und_x_variant":[
        "\u706b\u5b98\u5e99"
    ],
    "wof:name":"Huoguanmiao",
    "wof:placetype":"locality"
},
  "geometry": {"coordinates":[114.45504,30.63083],"type":"Point"}
}