{
  "type": "Feature",
  "properties": {
    "gn:admin1_code":"9.0",
    "gn:asciiname":"Dashiqiao",
    "gn:country_code":"CN",
    "gn:dem":130,
    "gn:feature_class":"P",
    "gn:feature_code":"PPL",
    "gn:name":"Dashiqiao",
    "gn:population":0,
    "gn:timezone":"Asia/Shanghai",
    "iso:country":"CN",
    "name:und_x_variant":[
        "\u5927\u77f3\u6865"
    ],
    "name:zho_x_preferred":[
        "\u5927\u77f3\u6865"
    ],
    "wof:name":"Dashiqiao",
    "wof:placetype":"locality"
},
  "geometry": {"coordinates":[113.01421999999999,33.02032],"type":"Point"}
}