{
  "type": "Feature",
  "properties": {
    "gn:admin1_code":"9.0",
    "gn:asciiname":"Dashiqiao",
    "gn:country_code":"CN",
    "gn:dem":130,
    "gn:feature_class":"P",
    "gn:feature_code":"PPL",
    "gn:name":"Dashiqiao",
    "gn:population":0,
    "gn:timezone":"Asia/Shanghai",
    "iso:country":"CN",
    "name:ara_x_preferred":[
        "\u062f\u0627\u0634\u064a\u062a\u0634\u064a\u0627\u0648"
    ],
    "name:ceb_x_preferred":[
        "Dashiqiao City"
    ],
    "name:deu_x_preferred":[
        "Dashiqiao"
    ],
    "name:fra_x_preferred":[
        "Dashiqiao"
    ],
    "name:ita_x_preferred":[
        "Dashiqiao"
    ],
    "name:jpn_x_preferred":[
        "\u5927\u77f3\u6a4b\u5e02"
    ],
    "name:kik_x_preferred":[
        "Dashiqiao"
    ],
    "name:kor_x_preferred":[
        "\ub2e4\uc2a4\ucc28\uc624\uc2dc"
    ],
    "name:mlg_x_preferred":[
        "Dashiqiao"
    ],
    "name:nld_x_preferred":[
        "Dashiqiao"
    ],
    "name:nor_x_preferred":[
        "Dashiqiao"
    ],
    "name:rus_x_preferred":[
        "\u0414\u0430\u0448\u0438\u0446\u044f\u043e"
    ],
    "name:swe_x_preferred":[
        "Dashiqiao"
    ],
    "name:und_x_variant":[
        "\u5927\u77f3\u6865"
    ],
    "name:urd_x_preferred":[
        "\u062f\u0627\u0634\u06cc\u0686\u06cc\u0627\u0648"
    ],
    "name:zho_x_preferred":[
        "\u5927\u77f3\u6865"
    ],
    "name:zho_x_variant":[
        "\u5927\u77f3\u6865\u5e02"
    ],
    "wof:name":"Dashiqiao",
    "wof:placetype":"locality"
},
  "geometry": {"coordinates":[113.01421999999999,33.02032],"type":"Point"}
}