{
  "type": "Feature",
  "properties": {
    "gn:admin1_code":"8.0",
    "gn:asciiname":"Sihaotun",
    "gn:country_code":"CN",
    "gn:dem":183,
    "gn:feature_class":"P",
    "gn:feature_code":"PPL",
    "gn:name":"Sihaotun",
    "gn:population":0,
    "gn:timezone":"Asia/Shanghai",
    "iso:country":"CN",
    "name:zho_x_preferred":[
        "\u56db\u53f7\u5c6f"
    ],
    "wof:name":"Sihaotun",
    "wof:placetype":"locality"
},
  "geometry": {"coordinates":[125.16128999999999,47.60224],"type":"Point"}
}