{
  "type": "Feature",
  "properties": {
    "gn:admin1_code":"25",
    "gn:asciiname":"Qianhantaoyuan",
    "gn:country_code":"CN",
    "gn:dem":144,
    "gn:feature_class":"P",
    "gn:feature_code":"PPL",
    "gn:name":"Qianhantaoyuan",
    "gn:population":0,
    "gn:timezone":"Asia/Shanghai",
    "iso:country":"CN",
    "name:zho_x_preferred":[
        "\u524d\u97e9\u6843\u56ed"
    ],
    "wof:name":"Qianhantaoyuan",
    "wof:placetype":"locality"
},
  "geometry": {"coordinates":[117.083,35.3187],"type":"Point"}
}