{
  "type": "Feature",
  "properties": {
    "gn:admin1_code":"10.0",
    "gn:asciiname":"Nanwangda",
    "gn:country_code":"CN",
    "gn:dem":14,
    "gn:feature_class":"P",
    "gn:feature_code":"PPL",
    "gn:name":"Nanwangda",
    "gn:population":0,
    "gn:timezone":"Asia/Shanghai",
    "iso:country":"CN",
    "name:zho_x_preferred":[
        "\u5357\u738b\u5927"
    ],
    "wof:name":"Nanwangda",
    "wof:placetype":"locality"
},
  "geometry": {"coordinates":[116.505,38.3356],"type":"Point"}
}