{
  "type": "Feature",
  "properties": {
    "gn:admin1_code":"32.0",
    "gn:asciiname":"Lugao",
    "gn:country_code":"CN",
    "gn:dem":603,
    "gn:feature_class":"P",
    "gn:feature_code":"PPL",
    "gn:name":"Lugao",
    "gn:population":0,
    "gn:timezone":"Asia/Shanghai",
    "iso:country":"CN",
    "name:zho_x_preferred":[
        "\u82a6\u7a3f"
    ],
    "wof:name":"Lugao",
    "wof:placetype":"locality"
},
  "geometry": {"coordinates":[103.20547000000001,27.54244000000001],"type":"Point"}
}