{
  "type": "Feature",
  "properties": {
    "gn:admin1_code":"05",
    "gn:asciiname":"Sanyuanpu",
    "gn:cc2":"CN",
    "gn:country_code":"CN",
    "gn:dem":409,
    "gn:feature_class":"P",
    "gn:feature_code":"PPL",
    "gn:name":"Sanyuanpu",
    "gn:population":0,
    "gn:timezone":"Asia/Shanghai",
    "iso:country":"CN",
    "name:und_x_variant":[
        "San-y\u00fcan",
        "Sanyuanpu"
    ],
    "wof:name":"Sanyuanpu",
    "wof:placetype":"locality"
},
  "geometry": {"coordinates":[125.75055999999999,42.06167],"type":"Point"}
}