{
  "type": "Feature",
  "properties": {
    "gn:admin1_code":"30.0",
    "gn:asciiname":"Longjing",
    "gn:country_code":"CN",
    "gn:dem":314,
    "gn:feature_class":"P",
    "gn:feature_code":"PPL",
    "gn:name":"Longjing",
    "gn:population":0,
    "gn:timezone":"Asia/Shanghai",
    "iso:country":"CN",
    "name:zho_x_preferred":[
        "\u9f99\u666f"
    ],
    "wof:name":"Longjing",
    "wof:placetype":"locality"
},
  "geometry": {"coordinates":[111.29136,22.81789],"type":"Point"}
}