{
  "type": "Feature",
  "properties": {
    "gn:admin1_code":"29",
    "gn:asciiname":"Caodianjie",
    "gn:country_code":"CN",
    "gn:dem":1881,
    "gn:feature_class":"P",
    "gn:feature_code":"PPLA4",
    "gn:name":"Caodianjie",
    "gn:population":0,
    "gn:timezone":"Asia/Shanghai",
    "iso:country":"CN",
    "name:und_x_variant":[
        "\u8349\u7538\u8857",
        "Caodian Zhen",
        "Caodian",
        "\u8349\u7538\u9547",
        "Caodianjie"
    ],
    "name:zho_x_preferred":[
        "\u8349\u7538"
    ],
    "wof:name":"Caodianjie",
    "wof:placetype":"locality"
},
  "geometry": {"coordinates":[103.05114,24.87181],"type":"Point"}
}