{
  "type": "Feature",
  "properties": {
    "gn:admin1_code":"7",
    "gn:asciiname":"Qianlin",
    "gn:country_code":"CN",
    "gn:dem":11,
    "gn:feature_class":"P",
    "gn:feature_code":"PPL",
    "gn:name":"Qianlin",
    "gn:population":0,
    "gn:timezone":"Asia/Shanghai",
    "iso:country":"CN",
    "name:zho_x_preferred":[
        "\u524d\u6797"
    ],
    "wof:name":"Qianlin",
    "wof:placetype":"locality"
},
  "geometry": {"coordinates":[118.88608000000001,24.95507000000001],"type":"Point"}
}