{
  "type": "Feature",
  "properties": {
    "gn:admin1_code":"31.0",
    "gn:asciiname":"Xinxing",
    "gn:country_code":"CN",
    "gn:dem":64,
    "gn:feature_class":"P",
    "gn:feature_code":"PPL",
    "gn:name":"Xinxing",
    "gn:population":0,
    "gn:timezone":"Asia/Shanghai",
    "iso:country":"CN",
    "name:und_x_variant":[
        "\u65b0\u5174"
    ],
    "wof:name":"Xinxing",
    "wof:placetype":"locality"
},
  "geometry": {"coordinates":[109.74160999999999,18.50921],"type":"Point"}
}