{
  "type": "Feature",
  "properties": {
    "gn:admin1_code":"29.0",
    "gn:asciiname":"Zhuanfang",
    "gn:country_code":"CN",
    "gn:dem":645,
    "gn:feature_class":"P",
    "gn:feature_code":"PPL",
    "gn:name":"Zhuanfang",
    "gn:population":0,
    "gn:timezone":"Asia/Shanghai",
    "iso:country":"CN",
    "name:zho_x_preferred":[
        "\u7816\u623f"
    ],
    "wof:name":"Zhuanfang",
    "wof:placetype":"locality"
},
  "geometry": {"coordinates":[104.366,27.9363],"type":"Point"}
}