{
  "type": "Feature",
  "properties": {
    "gn:admin1_code":"12.0",
    "gn:asciiname":"Liansanpo",
    "gn:country_code":"CN",
    "gn:dem":1168,
    "gn:feature_class":"P",
    "gn:feature_code":"PPL",
    "gn:name":"Liansanpo",
    "gn:population":0,
    "gn:timezone":"Asia/Shanghai",
    "iso:country":"CN",
    "name:zho_x_preferred":[
        "\u8fde\u4e09\u5761"
    ],
    "wof:name":"Liansanpo",
    "wof:placetype":"locality"
},
  "geometry": {"coordinates":[110.30918,30.88554],"type":"Point"}
}