{
  "type": "Feature",
  "properties": {
    "gn:admin1_code":"25",
    "gn:asciiname":"Huiquan",
    "gn:country_code":"CN",
    "gn:dem":389,
    "gn:feature_class":"P",
    "gn:feature_code":"PPL",
    "gn:name":"Huiquan",
    "gn:population":0,
    "gn:timezone":"Asia/Shanghai",
    "iso:country":"CN",
    "name:zho_x_preferred":[
        "\u8f89\u6cc9"
    ],
    "wof:name":"Huiquan",
    "wof:placetype":"locality"
},
  "geometry": {"coordinates":[118.547,36.1194],"type":"Point"}
}