{
  "type": "Feature",
  "properties": {
    "gn:admin1_code":"33.0",
    "gn:asciiname":"Shangshawan",
    "gn:country_code":"CN",
    "gn:dem":515,
    "gn:feature_class":"P",
    "gn:feature_code":"PPL",
    "gn:name":"Shangshawan",
    "gn:population":0,
    "gn:timezone":"Asia/Shanghai",
    "iso:country":"CN",
    "name:zho_x_preferred":[
        "\u4e0a\u6c99\u5f2f"
    ],
    "wof:name":"Shangshawan",
    "wof:placetype":"locality"
},
  "geometry": {"coordinates":[108.52743,28.66441],"type":"Point"}
}