{
  "type": "Feature",
  "properties": {
    "gn:admin1_code":"4.0",
    "gn:asciiname":"Yanxingqiao",
    "gn:country_code":"CN",
    "gn:dem":57,
    "gn:feature_class":"P",
    "gn:feature_code":"PPL",
    "gn:name":"Yanxingqiao",
    "gn:population":0,
    "gn:timezone":"Asia/Shanghai",
    "iso:country":"CN",
    "name:zho_x_preferred":[
        "\u96c1\u884c\u6865"
    ],
    "wof:name":"Yanxingqiao",
    "wof:placetype":"locality"
},
  "geometry": {"coordinates":[119.16463,31.68844],"type":"Point"}
}