{
  "type": "Feature",
  "properties": {
    "gn:admin1_code":"7",
    "gn:asciiname":"Gebei",
    "gn:country_code":"CN",
    "gn:dem":503,
    "gn:feature_class":"P",
    "gn:feature_code":"PPL",
    "gn:name":"Gebei",
    "gn:population":0,
    "gn:timezone":"Asia/Shanghai",
    "iso:country":"CN",
    "name:zho_x_preferred":[
        "\u9694\u80cc"
    ],
    "wof:name":"Gebei",
    "wof:placetype":"locality"
},
  "geometry": {"coordinates":[117.01851000000001,24.10511],"type":"Point"}
}