{
  "type": "Feature",
  "properties": {
    "gn:admin1_code":"1.0",
    "gn:asciiname":"Xiaoqianjiancun",
    "gn:country_code":"CN",
    "gn:dem":133,
    "gn:feature_class":"P",
    "gn:feature_code":"PPL",
    "gn:name":"Xiaoqianjiancun",
    "gn:population":0,
    "gn:timezone":"Asia/Shanghai",
    "iso:country":"CN",
    "name:zho_x_preferred":[
        "\u5c0f\u4e7e\u6da7\u6751"
    ],
    "wof:name":"Xiaoqianjiancun",
    "wof:placetype":"locality"
},
  "geometry": {"coordinates":[116.1579,31.44065],"type":"Point"}
}