{
  "type": "Feature",
  "properties": {
    "gn:admin1_code":"26.0",
    "gn:asciiname":"Yushuyuan",
    "gn:country_code":"CN",
    "gn:dem":1250,
    "gn:feature_class":"P",
    "gn:feature_code":"PPL",
    "gn:name":"Yushuyuan",
    "gn:population":0,
    "gn:timezone":"Asia/Shanghai",
    "iso:country":"CN",
    "name:zho_x_preferred":[
        "\u6986\u6811\u586c"
    ],
    "wof:name":"Yushuyuan",
    "wof:placetype":"locality"
},
  "geometry": {"coordinates":[109.06783,36.03618],"type":"Point"}
}