{
  "type": "Feature",
  "properties": {
    "gn:admin1_code":"19.0",
    "gn:asciiname":"Yujiadian",
    "gn:country_code":"CN",
    "gn:dem":21,
    "gn:feature_class":"P",
    "gn:feature_code":"PPL",
    "gn:name":"Yujiadian",
    "gn:population":0,
    "gn:timezone":"Asia/Shanghai",
    "iso:country":"CN",
    "name:und_x_variant":[
        "\u4e8e\u5bb6\u5e97"
    ],
    "name:zho_x_preferred":[
        "\u4e8e\u5bb6\u5e97"
    ],
    "wof:name":"Yujiadian",
    "wof:placetype":"locality"
},
  "geometry": {"coordinates":[123.17892999999999,39.81117],"type":"Point"}
}