{
  "type": "Feature",
  "properties": {
    "gn:admin1_code":"26.0",
    "gn:asciiname":"Zhongyaocun",
    "gn:country_code":"CN",
    "gn:dem":572,
    "gn:feature_class":"P",
    "gn:feature_code":"PPL",
    "gn:name":"Zhongyaocun",
    "gn:population":0,
    "gn:timezone":"Asia/Shanghai",
    "iso:country":"CN",
    "name:zho_x_preferred":[
        "\u4e2d\u5c27\u6751"
    ],
    "wof:name":"Zhongyaocun",
    "wof:placetype":"locality"
},
  "geometry": {"coordinates":[109.70323999999999,35.03488],"type":"Point"}
}