{
  "type": "Feature",
  "properties": {
    "gn:admin1_code":"2.0",
    "gn:asciiname":"Xuehuashan",
    "gn:country_code":"CN",
    "gn:dem":37,
    "gn:feature_class":"P",
    "gn:feature_code":"PPL",
    "gn:name":"Xuehuashan",
    "gn:population":0,
    "gn:timezone":"Asia/Shanghai",
    "iso:country":"CN",
    "name:zho_x_preferred":[
        "\u96ea\u82b1\u5c71"
    ],
    "wof:name":"Xuehuashan",
    "wof:placetype":"locality"
},
  "geometry": {"coordinates":[119.85893,31.12636],"type":"Point"}
}