{
  "type": "Feature",
  "properties": {
    "gn:admin1_code":"13.0",
    "gn:asciiname":"Tijian",
    "gn:country_code":"CN",
    "gn:dem":1212,
    "gn:feature_class":"P",
    "gn:feature_code":"PPL",
    "gn:name":"Tijian",
    "gn:population":0,
    "gn:timezone":"Asia/Shanghai",
    "iso:country":"CN",
    "name:zho_x_preferred":[
        "\u63d0\u575a"
    ],
    "wof:name":"Tijian",
    "wof:placetype":"locality"
},
  "geometry": {"coordinates":[76.56737,39.74922],"type":"Point"}
}