{
  "type": "Feature",
  "properties": {
    "gn:admin1_code":"26.0",
    "gn:asciiname":"Damiaogou",
    "gn:country_code":"CN",
    "gn:dem":1216,
    "gn:feature_class":"P",
    "gn:feature_code":"PPL",
    "gn:name":"Damiaogou",
    "gn:population":0,
    "gn:timezone":"Asia/Shanghai",
    "iso:country":"CN",
    "name:zho_x_preferred":[
        "\u5927\u5e99\u6c9f"
    ],
    "wof:name":"Damiaogou",
    "wof:placetype":"locality"
},
  "geometry": {"coordinates":[109.74298,33.66453],"type":"Point"}
}