{
  "type": "Feature",
  "properties": {
    "gn:admin1_code":"19.0",
    "gn:asciiname":"Xiaotiechang",
    "gn:country_code":"CN",
    "gn:dem":138,
    "gn:feature_class":"P",
    "gn:feature_code":"PPL",
    "gn:name":"Xiaotiechang",
    "gn:population":0,
    "gn:timezone":"Asia/Shanghai",
    "iso:country":"CN",
    "name:zho_x_preferred":[
        "\u5c0f\u94c1\u5382"
    ],
    "wof:name":"Xiaotiechang",
    "wof:placetype":"locality"
},
  "geometry": {"coordinates":[121.502,41.6127],"type":"Point"}
}