{
  "type": "Feature",
  "properties": {
    "gn:admin1_code":"19.0",
    "gn:asciiname":"Zhengyangtun",
    "gn:country_code":"CN",
    "gn:dem":251,
    "gn:feature_class":"P",
    "gn:feature_code":"PPL",
    "gn:name":"Zhengyangtun",
    "gn:population":0,
    "gn:timezone":"Asia/Shanghai",
    "iso:country":"CN",
    "name:zho_x_preferred":[
        "\u6b63\u9633\u5c6f"
    ],
    "wof:name":"Zhengyangtun",
    "wof:placetype":"locality"
},
  "geometry": {"coordinates":[124.816,42.958],"type":"Point"}
}