{
  "type": "Feature",
  "properties": {
    "gn:admin1_code":"3.0",
    "gn:asciiname":"Hufengshan Lindui",
    "gn:country_code":"CN",
    "gn:dem":121,
    "gn:feature_class":"P",
    "gn:feature_code":"PPLF",
    "gn:name":"Hufengshan Lindui",
    "gn:population":0,
    "gn:timezone":"Asia/Shanghai",
    "iso:country":"CN",
    "name:und_x_variant":[
        "\u864e\u5cf0\u5c71\u6797\u961f"
    ],
    "wof:name":"Hufengshan Lindui",
    "wof:placetype":"locality"
},
  "geometry": {"coordinates":[116.93937,29.4815],"type":"Point"}
}