{
  "type": "Feature",
  "properties": {
    "gn:admin1_code":"30",
    "gn:asciiname":"Puzhao",
    "gn:country_code":"CN",
    "gn:dem":47,
    "gn:feature_class":"P",
    "gn:feature_code":"PPL",
    "gn:name":"Puzhao",
    "gn:population":0,
    "gn:timezone":"Asia/Shanghai",
    "iso:country":"CN",
    "name:zho_x_preferred":[
        "\u84b2\u6cbc"
    ],
    "wof:name":"Puzhao",
    "wof:placetype":"locality"
},
  "geometry": {"coordinates":[111.42511,22.03997],"type":"Point"}
}