{
  "type": "Feature",
  "properties": {
    "gn:admin1_code":"19.0",
    "gn:asciiname":"Lanmu Tougou",
    "gn:country_code":"CN",
    "gn:dem":269,
    "gn:feature_class":"P",
    "gn:feature_code":"PPL",
    "gn:name":"Lanmu Tougou",
    "gn:population":0,
    "gn:timezone":"Asia/Shanghai",
    "iso:country":"CN",
    "name:und_x_variant":[
        "\u70c2\u6728\u5934\u6c9f"
    ],
    "wof:name":"Lanmu Tougou",
    "wof:placetype":"locality"
},
  "geometry": {"coordinates":[122.90685000000001,40.05171],"type":"Point"}
}