{
  "type": "Feature",
  "properties": {
    "gn:admin1_code":"18.0",
    "gn:asciiname":"Baiben",
    "gn:country_code":"CN",
    "gn:dem":636,
    "gn:feature_class":"P",
    "gn:feature_code":"PPL",
    "gn:name":"Baiben",
    "gn:population":0,
    "gn:timezone":"Asia/Shanghai",
    "iso:country":"CN",
    "name:zho_x_preferred":[
        "\u767d\u574c"
    ],
    "wof:name":"Baiben",
    "wof:placetype":"locality"
},
  "geometry": {"coordinates":[109.253,26.8213],"type":"Point"}
}