{
  "type": "Feature",
  "properties": {
    "gn:admin1_code":"16.0",
    "gn:asciiname":"Baliucun",
    "gn:country_code":"CN",
    "gn:dem":443,
    "gn:feature_class":"P",
    "gn:feature_code":"PPL",
    "gn:name":"Baliucun",
    "gn:population":0,
    "gn:timezone":"Asia/Shanghai",
    "iso:country":"CN",
    "name:zho_x_preferred":[
        "\u5df4\u516d\u6751"
    ],
    "wof:name":"Baliucun",
    "wof:placetype":"locality"
},
  "geometry": {"coordinates":[107.36499999999999,23.7022],"type":"Point"}
}