{
  "type": "Feature",
  "properties": {
    "gn:admin1_code":"29.0",
    "gn:asciiname":"Yushichang",
    "gn:country_code":"CN",
    "gn:dem":2672,
    "gn:feature_class":"P",
    "gn:feature_code":"PPL",
    "gn:name":"Yushichang",
    "gn:population":0,
    "gn:timezone":"Asia/Shanghai",
    "iso:country":"CN",
    "name:zho_x_preferred":[
        "\u7389\u72ee\u573a"
    ],
    "wof:name":"Yushichang",
    "wof:placetype":"locality"
},
  "geometry": {"coordinates":[99.44280000000001,26.9009],"type":"Point"}
}