{
  "type": "Feature",
  "properties": {
    "gn:admin1_code":"4.0",
    "gn:asciiname":"Liusigang",
    "gn:country_code":"CN",
    "gn:dem":2,
    "gn:feature_class":"P",
    "gn:feature_code":"PPL",
    "gn:name":"Liusigang",
    "gn:population":0,
    "gn:timezone":"Asia/Shanghai",
    "iso:country":"CN",
    "name:zho_x_preferred":[
        "\u67f3\u6cd7\u6e2f"
    ],
    "wof:name":"Liusigang",
    "wof:placetype":"locality"
},
  "geometry": {"coordinates":[119.8693,32.0803],"type":"Point"}
}