{
  "type": "Feature",
  "properties": {
    "gn:admin1_code":"29.0",
    "gn:asciiname":"Lianping",
    "gn:country_code":"CN",
    "gn:dem":2158,
    "gn:feature_class":"P",
    "gn:feature_code":"PPL",
    "gn:name":"Lianping",
    "gn:population":0,
    "gn:timezone":"Asia/Shanghai",
    "iso:country":"CN",
    "name:zho_x_preferred":[
        "\u7ec3\u576a"
    ],
    "wof:name":"Lianping",
    "wof:placetype":"locality"
},
  "geometry": {"coordinates":[99.96639999999999,25.7708],"type":"Point"}
}