{
  "type": "Feature",
  "properties": {
    "gn:admin1_code":"02",
    "gn:asciiname":"Baixiang",
    "gn:cc2":"CN",
    "gn:country_code":"CN",
    "gn:dem":9,
    "gn:feature_class":"P",
    "gn:feature_code":"PPL",
    "gn:name":"Baixiang",
    "gn:population":0,
    "gn:timezone":"Asia/Shanghai",
    "iso:country":"CN",
    "name:und_x_variant":[
        "Pai-hsiang-shih",
        "Baixiang"
    ],
    "wof:name":"Baixiang",
    "wof:placetype":"locality"
},
  "geometry": {"coordinates":[120.67917,27.93361],"type":"Point"}
}