{
  "type": "Feature",
  "properties": {
    "gn:admin1_code":"14.0",
    "gn:asciiname":"Jiayi",
    "gn:country_code":"CN",
    "gn:dem":3238,
    "gn:feature_class":"P",
    "gn:feature_code":"PPL",
    "gn:name":"Jiayi",
    "gn:population":0,
    "gn:timezone":"Asia/Urumqi",
    "iso:country":"CN",
    "name:ceb_x_preferred":[
        "Jiayi"
    ],
    "name:zho_x_preferred":[
        "\u7532\u4e49"
    ],
    "wof:name":"Jiayi",
    "wof:placetype":"locality"
},
  "geometry": {"coordinates":[94.38905,29.65613],"type":"Point"}
}