{
  "type": "Feature",
  "properties": {
    "gn:admin1_code":"29",
    "gn:asciiname":"Chushuidong",
    "gn:country_code":"CN",
    "gn:dem":829,
    "gn:feature_class":"P",
    "gn:feature_code":"PPL",
    "gn:name":"Chushuidong",
    "gn:population":0,
    "gn:timezone":"Asia/Shanghai",
    "iso:country":"CN",
    "name:zho_x_preferred":[
        "\u51fa\u6c34\u6d1e"
    ],
    "wof:name":"Chushuidong",
    "wof:placetype":"locality"
},
  "geometry": {"coordinates":[105.029,24.3283],"type":"Point"}
}