{
  "type": "Feature",
  "properties": {
    "gn:admin1_code":"16.0",
    "gn:asciiname":"Neidangzhan",
    "gn:country_code":"CN",
    "gn:dem":967,
    "gn:feature_class":"P",
    "gn:feature_code":"PPL",
    "gn:name":"Neidangzhan",
    "gn:population":0,
    "gn:timezone":"Asia/Shanghai",
    "iso:country":"CN",
    "name:zho_x_preferred":[
        "\u5185\u5f53\u7ad9"
    ],
    "wof:name":"Neidangzhan",
    "wof:placetype":"locality"
},
  "geometry": {"coordinates":[106.562,24.7747],"type":"Point"}
}