{
  "type": "Feature",
  "properties": {
    "gn:admin1_code":"3.0",
    "gn:asciiname":"Yangmenqiao",
    "gn:country_code":"CN",
    "gn:dem":107,
    "gn:feature_class":"P",
    "gn:feature_code":"PPL",
    "gn:name":"Yangmenqiao",
    "gn:population":0,
    "gn:timezone":"Asia/Shanghai",
    "iso:country":"CN",
    "name:und_x_variant":[
        "\u6768\u95e8\u6865"
    ],
    "wof:name":"Yangmenqiao",
    "wof:placetype":"locality"
},
  "geometry": {"coordinates":[114.94535999999999,28.53965],"type":"Point"}
}