{
  "type": "Feature",
  "properties": {
    "gn:admin1_code":"1.0",
    "gn:asciiname":"Simiaocun",
    "gn:country_code":"CN",
    "gn:dem":21,
    "gn:feature_class":"P",
    "gn:feature_code":"PPL",
    "gn:name":"Simiaocun",
    "gn:population":0,
    "gn:timezone":"Asia/Shanghai",
    "iso:country":"CN",
    "name:zho_x_preferred":[
        "\u53f8\u5e99\u6751"
    ],
    "wof:name":"Simiaocun",
    "wof:placetype":"locality"
},
  "geometry": {"coordinates":[117.59192,33.68469],"type":"Point"}
}