{
  "type": "Feature",
  "properties": {
    "gn:admin1_code":"29",
    "gn:asciiname":"Lantande",
    "gn:country_code":"CN",
    "gn:dem":1596,
    "gn:feature_class":"P",
    "gn:feature_code":"PPL",
    "gn:name":"Lantande",
    "gn:population":0,
    "gn:timezone":"Asia/Shanghai",
    "iso:country":"CN",
    "name:zho_x_preferred":[
        "\u5170\u6ee9\u5f97"
    ],
    "wof:name":"Lantande",
    "wof:placetype":"locality"
},
  "geometry": {"coordinates":[104.986,23.776],"type":"Point"}
}