{
  "type": "Feature",
  "properties": {
    "gn:admin1_code":"21.0",
    "gn:asciiname":"Jizhaike",
    "gn:country_code":"CN",
    "gn:dem":1691,
    "gn:feature_class":"P",
    "gn:feature_code":"PPL",
    "gn:name":"Jizhaike",
    "gn:population":0,
    "gn:timezone":"Asia/Shanghai",
    "iso:country":"CN",
    "name:zho_x_preferred":[
        "\u59ec\u5be8\u67ef"
    ],
    "wof:name":"Jizhaike",
    "wof:placetype":"locality"
},
  "geometry": {"coordinates":[105.23999999999999,36.9497],"type":"Point"}
}