{
  "type": "Feature",
  "properties": {
    "gn:admin1_code":"10",
    "gn:asciiname":"Hecun",
    "gn:country_code":"CN",
    "gn:dem":73,
    "gn:feature_class":"P",
    "gn:feature_code":"PPL",
    "gn:name":"Hecun",
    "gn:population":0,
    "gn:timezone":"Asia/Shanghai",
    "iso:country":"CN",
    "name:ceb_x_preferred":[
        "Hecun"
    ],
    "name:swe_x_preferred":[
        "Hecun"
    ],
    "name:zho_x_preferred":[
        "\u8d3a\u6751"
    ],
    "wof:name":"Hecun",
    "wof:placetype":"locality"
},
  "geometry": {"coordinates":[114.533,36.2863],"type":"Point"}
}