{
  "type": "Feature",
  "properties": {
    "gn:admin1_code":"32.0",
    "gn:asciiname":"Zhangjiadi",
    "gn:country_code":"CN",
    "gn:dem":1846,
    "gn:feature_class":"P",
    "gn:feature_code":"PPL",
    "gn:name":"Zhangjiadi",
    "gn:population":0,
    "gn:timezone":"Asia/Shanghai",
    "iso:country":"CN",
    "name:zho_x_preferred":[
        "\u5f20\u5bb6\u5730"
    ],
    "wof:name":"Zhangjiadi",
    "wof:placetype":"locality"
},
  "geometry": {"coordinates":[102.53100000000001,29.4621],"type":"Point"}
}