{
  "type": "Feature",
  "properties": {
    "gn:admin1_code":"26.0",
    "gn:asciiname":"Zaolinzi",
    "gn:country_code":"CN",
    "gn:dem":766,
    "gn:feature_class":"P",
    "gn:feature_code":"PPL",
    "gn:name":"Zaolinzi",
    "gn:population":0,
    "gn:timezone":"Asia/Shanghai",
    "iso:country":"CN",
    "name:zho_x_preferred":[
        "\u67a3\u6797\u5b50"
    ],
    "wof:name":"Zaolinzi",
    "wof:placetype":"locality"
},
  "geometry": {"coordinates":[110.13079,36.53589],"type":"Point"}
}