{
  "type": "Feature",
  "properties": {
    "gn:admin1_code":"4.0",
    "gn:asciiname":"Shaojiahe",
    "gn:country_code":"CN",
    "gn:dem":4,
    "gn:feature_class":"P",
    "gn:feature_code":"PPL",
    "gn:name":"Shaojiahe",
    "gn:population":0,
    "gn:timezone":"Asia/Shanghai",
    "iso:country":"CN",
    "name:zho_x_preferred":[
        "\u90b5\u5bb6\u6cb3"
    ],
    "wof:name":"Shaojiahe",
    "wof:placetype":"locality"
},
  "geometry": {"coordinates":[119.4718,32.94821],"type":"Point"}
}