{
  "type": "Feature",
  "properties": {
    "gn:admin1_code":"14.0",
    "gn:asciiname":"Tacun",
    "gn:country_code":"CN",
    "gn:dem":3930,
    "gn:feature_class":"P",
    "gn:feature_code":"PPL",
    "gn:name":"Tacun",
    "gn:population":0,
    "gn:timezone":"Asia/Urumqi",
    "iso:country":"CN",
    "name:zho_x_preferred":[
        "\u5854\u6751"
    ],
    "wof:name":"Tacun",
    "wof:placetype":"locality"
},
  "geometry": {"coordinates":[85.98950000000001,28.2108],"type":"Point"}
}