{
  "type": "Feature",
  "properties": {
    "gn:admin1_code":"16.0",
    "gn:asciiname":"Xiasu",
    "gn:country_code":"CN",
    "gn:dem":272,
    "gn:feature_class":"P",
    "gn:feature_code":"PPL",
    "gn:name":"Xiasu",
    "gn:population":0,
    "gn:timezone":"Asia/Shanghai",
    "iso:country":"CN",
    "name:zho_x_preferred":[
        "\u4e0b\u82cf"
    ],
    "wof:name":"Xiasu",
    "wof:placetype":"locality"
},
  "geometry": {"coordinates":[108.77,23.7528],"type":"Point"}
}