{
  "type": "Feature",
  "properties": {
    "gn:admin1_code":"21.0",
    "gn:asciiname":"Hua'erwan",
    "gn:country_code":"CN",
    "gn:dem":1569,
    "gn:feature_class":"P",
    "gn:feature_code":"PPL",
    "gn:name":"Hua\u2019erwan",
    "gn:population":0,
    "gn:timezone":"Asia/Shanghai",
    "iso:country":"CN",
    "name:und_x_variant":[
        "Hua\u2019erwan"
    ],
    "name:zho_x_preferred":[
        "\u82b1\u513f\u6e7e"
    ],
    "wof:name":"Hua'erwan",
    "wof:placetype":"locality"
},
  "geometry": {"coordinates":[106.494,35.9536],"type":"Point"}
}