{
  "type": "Feature",
  "properties": {
    "gn:admin1_code":"30",
    "gn:asciiname":"Lailishan",
    "gn:country_code":"CN",
    "gn:dem":793,
    "gn:feature_class":"P",
    "gn:feature_code":"PPL",
    "gn:name":"Lailishan",
    "gn:population":0,
    "gn:timezone":"Asia/Shanghai",
    "iso:country":"CN",
    "name:zho_x_preferred":[
        "\u765e\u75e2\u5c71"
    ],
    "wof:name":"Lailishan",
    "wof:placetype":"locality"
},
  "geometry": {"coordinates":[116.59010000000001,24.08872],"type":"Point"}
}