{
  "type": "Feature",
  "properties": {
    "gn:admin1_code":"1.0",
    "gn:asciiname":"Liangshancun",
    "gn:country_code":"CN",
    "gn:dem":19,
    "gn:feature_class":"P",
    "gn:feature_code":"PPL",
    "gn:name":"Liangshancun",
    "gn:population":0,
    "gn:timezone":"Asia/Shanghai",
    "iso:country":"CN",
    "name:zho_x_preferred":[
        "\u6881\u5c71\u6751"
    ],
    "wof:name":"Liangshancun",
    "wof:placetype":"locality"
},
  "geometry": {"coordinates":[117.20650999999999,31.36477],"type":"Point"}
}