{
  "type": "Feature",
  "properties": {
    "gn:admin1_code":"14.0",
    "gn:asciiname":"Emaka",
    "gn:country_code":"CN",
    "gn:dem":4542,
    "gn:feature_class":"P",
    "gn:feature_code":"PPL",
    "gn:name":"Emaka",
    "gn:population":0,
    "gn:timezone":"Asia/Urumqi",
    "iso:country":"CN",
    "name:zho_x_preferred":[
        "\u4fc4\u739b\u5361"
    ],
    "wof:name":"Emaka",
    "wof:placetype":"locality"
},
  "geometry": {"coordinates":[94.33207,31.37537],"type":"Point"}
}