{
  "type": "Feature",
  "properties": {
    "gn:admin1_code":"5.0",
    "gn:asciiname":"Huanghua Dianzi",
    "gn:country_code":"CN",
    "gn:dem":153,
    "gn:feature_class":"P",
    "gn:feature_code":"PPL",
    "gn:name":"Huanghua Dianzi",
    "gn:population":0,
    "gn:timezone":"Asia/Shanghai",
    "iso:country":"CN",
    "name:zho_x_preferred":[
        "\u9ec4\u82b1\u7538\u5b50"
    ],
    "wof:name":"Huanghua Dianzi",
    "wof:placetype":"locality"
},
  "geometry": {"coordinates":[122.61539999999999,45.31072],"type":"Point"}
}