{
  "type": "Feature",
  "properties": {
    "gn:admin1_code":"16.0",
    "gn:asciiname":"Youtaibiao",
    "gn:country_code":"CN",
    "gn:dem":107,
    "gn:feature_class":"P",
    "gn:feature_code":"PPL",
    "gn:name":"Youtaibiao",
    "gn:population":0,
    "gn:timezone":"Asia/Shanghai",
    "iso:country":"CN",
    "name:zho_x_preferred":[
        "\u7531\u592a\u8868"
    ],
    "wof:name":"Youtaibiao",
    "wof:placetype":"locality"
},
  "geometry": {"coordinates":[110.542,23.2742],"type":"Point"}
}