{
  "type": "Feature",
  "properties": {
    "gn:admin1_code":"14.0",
    "gn:asciiname":"Ri'azeka",
    "gn:country_code":"CN",
    "gn:dem":4027,
    "gn:feature_class":"P",
    "gn:feature_code":"PPL",
    "gn:name":"Ri\u2019azeka",
    "gn:population":0,
    "gn:timezone":"Asia/Urumqi",
    "iso:country":"CN",
    "name:und_x_variant":[
        "Ri\u2019azeka"
    ],
    "name:zho_x_preferred":[
        "\u65e5\u963f\u5219\u5361"
    ],
    "wof:name":"Ri'azeka",
    "wof:placetype":"locality"
},
  "geometry": {"coordinates":[97.83795000000001,32.45241],"type":"Point"}
}