{
  "type": "Feature",
  "properties": {
    "gn:admin1_code":"4.0",
    "gn:asciiname":"Jiezhizha Xincun",
    "gn:country_code":"CN",
    "gn:dem":4,
    "gn:feature_class":"P",
    "gn:feature_code":"PPL",
    "gn:name":"Jiezhizha Xincun",
    "gn:population":0,
    "gn:timezone":"Asia/Shanghai",
    "iso:country":"CN",
    "name:zho_x_preferred":[
        "\u8282\u5236\u95f8\u65b0\u6751"
    ],
    "wof:name":"Jiezhizha Xincun",
    "wof:placetype":"locality"
},
  "geometry": {"coordinates":[120.82966999999999,32.02242],"type":"Point"}
}