{
  "type": "Feature",
  "properties": {
    "gn:admin1_code":"3",
    "gn:asciiname":"Dutouxu",
    "gn:country_code":"CN",
    "gn:dem":222,
    "gn:feature_class":"P",
    "gn:feature_code":"PPL",
    "gn:name":"Dutouxu",
    "gn:population":0,
    "gn:timezone":"Asia/Shanghai",
    "iso:country":"CN",
    "name:und_x_variant":[
        "\u6e21\u5934\u5729"
    ],
    "wof:name":"Dutouxu",
    "wof:placetype":"locality"
},
  "geometry": {"coordinates":[115.88086,26.06532],"type":"Point"}
}