{
  "type": "Feature",
  "properties": {
    "gn:admin1_code":"01",
    "gn:asciiname":"Sicheng",
    "gn:country_code":"CN",
    "gn:dem":20,
    "gn:feature_class":"P",
    "gn:feature_code":"PPLA3",
    "gn:name":"Sicheng",
    "gn:population":0,
    "gn:timezone":"Asia/Shanghai",
    "iso:country":"CN",
    "name:und_x_variant":[
        "Szehsien",
        "Ssu-chou",
        "Szechow",
        "Ssu",
        "Szu-hsien",
        "Ssu-hsien",
        "Suhsien",
        "Sixian",
        "Sicheng"
    ],
    "name:zho_x_preferred":[
        "\u6cd7\u57ce"
    ],
    "wof:name":"Sicheng",
    "wof:placetype":"locality"
},
  "geometry": {"coordinates":[117.85679,33.48936],"type":"Point"}
}