{
  "type": "Feature",
  "properties": {
    "gn:admin1_code":"29.0",
    "gn:asciiname":"Malushan",
    "gn:country_code":"CN",
    "gn:dem":1886,
    "gn:feature_class":"P",
    "gn:feature_code":"PPL",
    "gn:name":"Malushan",
    "gn:population":0,
    "gn:timezone":"Asia/Shanghai",
    "iso:country":"CN",
    "name:zho_x_preferred":[
        "\u9a6c\u9e7f\u5c71"
    ],
    "wof:name":"Malushan",
    "wof:placetype":"locality"
},
  "geometry": {"coordinates":[99.63939999999999,24.01],"type":"Point"}
}