{
  "type": "Feature",
  "properties": {
    "gn:admin1_code":"4.0",
    "gn:asciiname":"Xiaojie",
    "gn:country_code":"CN",
    "gn:dem":7,
    "gn:feature_class":"P",
    "gn:feature_code":"PPL",
    "gn:name":"Xiaojie",
    "gn:population":0,
    "gn:timezone":"Asia/Shanghai",
    "iso:country":"CN",
    "name:ceb_x_preferred":[
        "Xiaojie"
    ],
    "name:deu_x_preferred":[
        "Xiaojie"
    ],
    "name:swe_x_preferred":[
        "Xiaojie"
    ],
    "wof:name":"Xiaojie",
    "wof:placetype":"locality"
},
  "geometry": {"coordinates":[119.76667,34.07917],"type":"Point"}
}