{
  "type": "Feature",
  "properties": {
    "gn:admin1_code":"10",
    "gn:asciiname":"Jizhazi",
    "gn:country_code":"CN",
    "gn:dem":639,
    "gn:feature_class":"P",
    "gn:feature_code":"PPL",
    "gn:name":"Jizhazi",
    "gn:population":0,
    "gn:timezone":"Asia/Shanghai",
    "iso:country":"CN",
    "name:zho_x_preferred":[
        "\u5b63\u6805\u5b50"
    ],
    "wof:name":"Jizhazi",
    "wof:placetype":"locality"
},
  "geometry": {"coordinates":[116.77929,41.05844],"type":"Point"}
}