{
  "type": "Feature",
  "properties": {
    "gn:admin1_code":"30",
    "gn:asciiname":"Xiabeidong",
    "gn:country_code":"CN",
    "gn:dem":27,
    "gn:feature_class":"P",
    "gn:feature_code":"PPL",
    "gn:name":"Xiabeidong",
    "gn:population":0,
    "gn:timezone":"Asia/Urumqi",
    "iso:country":"CN",
    "name:zho_x_preferred":[
        "\u4e0b\u80cc\u578c"
    ],
    "wof:name":"Xiabeidong",
    "wof:placetype":"locality"
},
  "geometry": {"coordinates":[110.58417,21.53772],"type":"Point"}
}