{
  "type": "Feature",
  "properties": {
    "gn:admin1_code":"26.0",
    "gn:asciiname":"Wazijie",
    "gn:cc2":"CN",
    "gn:country_code":"CN",
    "gn:dem":1030,
    "gn:feature_class":"P",
    "gn:feature_code":"PPL",
    "gn:name":"Wazijie",
    "gn:population":0,
    "gn:timezone":"Asia/Shanghai",
    "iso:country":"CN",
    "name:und_x_variant":[
        "Wa-tzu-chieh",
        "Wazijie"
    ],
    "wof:name":"Wazijie",
    "wof:placetype":"locality"
},
  "geometry": {"coordinates":[110.00667,35.96],"type":"Point"}
}