{
  "type": "Feature",
  "properties": {
    "gn:admin1_code":"14.0",
    "gn:asciiname":"Jiadaima",
    "gn:country_code":"CN",
    "gn:dem":4773,
    "gn:feature_class":"P",
    "gn:feature_code":"PPL",
    "gn:name":"Jiadaima",
    "gn:population":0,
    "gn:timezone":"Asia/Urumqi",
    "iso:country":"CN",
    "name:zho_x_preferred":[
        "\u52a0\u5446\u739b"
    ],
    "wof:name":"Jiadaima",
    "wof:placetype":"locality"
},
  "geometry": {"coordinates":[92.63582,32.10498],"type":"Point"}
}