{
  "type": "Feature",
  "properties": {
    "gn:admin1_code":"11.0",
    "gn:asciiname":"Liujiaqiao",
    "gn:country_code":"CN",
    "gn:dem":45,
    "gn:feature_class":"P",
    "gn:feature_code":"PPL",
    "gn:name":"Liujiaqiao",
    "gn:population":0,
    "gn:timezone":"Asia/Shanghai",
    "iso:country":"CN",
    "name:zho_x_preferred":[
        "Liujiaqiao"
    ],
    "name:zho_x_variant":[
        "\u5218\u5bb6\u6865"
    ],
    "wof:name":"Liujiaqiao",
    "wof:placetype":"locality"
},
  "geometry": {"coordinates":[111.78874,29.15298],"type":"Point"}
}