{
  "type": "Feature",
  "properties": {
    "gn:admin1_code":"32.0",
    "gn:asciiname":"Ze'erwa",
    "gn:country_code":"CN",
    "gn:dem":3327,
    "gn:feature_class":"P",
    "gn:feature_code":"PPL",
    "gn:name":"Ze\u2019erwa",
    "gn:population":0,
    "gn:timezone":"Asia/Shanghai",
    "iso:country":"CN",
    "name:und_x_variant":[
        "Ze\u2019erwa"
    ],
    "name:zho_x_preferred":[
        "\u6cfd\u5c14\u74e6"
    ],
    "wof:name":"Ze'erwa",
    "wof:placetype":"locality"
},
  "geometry": {"coordinates":[101.566,32.2597],"type":"Point"}
}