{
  "type": "Feature",
  "properties": {
    "gn:admin1_code":"15",
    "gn:asciiname":"Gucheng",
    "gn:country_code":"CN",
    "gn:dem":1147,
    "gn:feature_class":"P",
    "gn:feature_code":"PPL",
    "gn:name":"Gucheng",
    "gn:population":0,
    "gn:timezone":"Asia/Shanghai",
    "iso:country":"CN",
    "name:ceb_x_preferred":[
        "Gucheng"
    ],
    "name:deu_x_preferred":[
        "Gucheng"
    ],
    "name:est_x_preferred":[
        "Gucheng"
    ],
    "name:fra_x_preferred":[
        "Gucheng"
    ],
    "name:kor_x_preferred":[
        "\uad6c\uccad\ud604"
    ],
    "name:nor_x_preferred":[
        "Gucheng"
    ],
    "name:swe_x_preferred":[
        "Gucheng"
    ],
    "wof:name":"Gucheng",
    "wof:placetype":"locality"
},
  "geometry": {"coordinates":[108.22472,35.85694],"type":"Point"}
}