{
  "type": "Feature",
  "properties": {
    "gn:admin1_code":"8.0",
    "gn:asciiname":"Guangrong Sidui",
    "gn:country_code":"CN",
    "gn:dem":240,
    "gn:feature_class":"P",
    "gn:feature_code":"PPLF",
    "gn:name":"Guangrong Sidui",
    "gn:population":0,
    "gn:timezone":"Asia/Shanghai",
    "iso:country":"CN",
    "name:zho_x_preferred":[
        "\u5149\u8363\u56db\u961f"
    ],
    "wof:name":"Guangrong Sidui",
    "wof:placetype":"locality"
},
  "geometry": {"coordinates":[124.8366,48.79021],"type":"Point"}
}