{
  "type": "Feature",
  "properties": {
    "gn:admin1_code":"9.0",
    "gn:asciiname":"Xuzhuangcun",
    "gn:country_code":"CN",
    "gn:dem":66,
    "gn:feature_class":"P",
    "gn:feature_code":"PPL",
    "gn:name":"Xuzhuangcun",
    "gn:population":0,
    "gn:timezone":"Asia/Shanghai",
    "iso:country":"CN",
    "name:und_x_variant":[
        "\u8bb8\u5e84\u6751"
    ],
    "name:zho_x_preferred":[
        "\u8bb8\u5e84\u6751"
    ],
    "wof:name":"Xuzhuangcun",
    "wof:placetype":"locality"
},
  "geometry": {"coordinates":[113.98045,33.97313],"type":"Point"}
}