{
  "type": "Feature",
  "properties": {
    "gn:admin1_code":"8.0",
    "gn:asciiname":"Bayiliulingliu Budui Nongchang",
    "gn:country_code":"CN",
    "gn:dem":290,
    "gn:feature_class":"P",
    "gn:feature_code":"PPLF",
    "gn:name":"Bayiliulingliu Budui Nongchang",
    "gn:population":0,
    "gn:timezone":"Asia/Shanghai",
    "iso:country":"CN",
    "name:zho_x_preferred":[
        "\u516b\u4e00\u516d\u96f6\u516d\u90e8\u961f\u519c\u573a"
    ],
    "wof:name":"Bayiliulingliu Budui Nongchang",
    "wof:placetype":"locality"
},
  "geometry": {"coordinates":[125.43838,49.67914],"type":"Point"}
}