{
  "type": "Feature",
  "properties": {
    "gn:admin1_code":"4.0",
    "gn:asciiname":"Xiajiayuan",
    "gn:country_code":"CN",
    "gn:dem":4,
    "gn:feature_class":"P",
    "gn:feature_code":"PPL",
    "gn:name":"Xiajiayuan",
    "gn:population":0,
    "gn:timezone":"Asia/Shanghai",
    "iso:country":"CN",
    "name:und_x_variant":[
        "\u590f\u5bb6\u56ed"
    ],
    "wof:name":"Xiajiayuan",
    "wof:placetype":"locality"
},
  "geometry": {"coordinates":[121.0654,32.23618],"type":"Point"}
}