{
  "type": "Feature",
  "properties": {
    "gn:admin1_code":"14",
    "gn:asciiname":"Qure",
    "gn:country_code":"CN",
    "gn:dem":4079,
    "gn:feature_class":"P",
    "gn:feature_code":"PPL",
    "gn:name":"Qure",
    "gn:population":0,
    "gn:timezone":"Asia/Urumqi",
    "iso:country":"CN",
    "name:zho_x_preferred":[
        "\u66f2\u70ed"
    ],
    "wof:name":"Qure",
    "wof:placetype":"locality"
},
  "geometry": {"coordinates":[89.6617,28.8464],"type":"Point"}
}