{
  "type": "Feature",
  "properties": {
    "gn:admin1_code":"25",
    "gn:asciiname":"Shengfuling",
    "gn:country_code":"CN",
    "gn:dem":122,
    "gn:feature_class":"P",
    "gn:feature_code":"PPL",
    "gn:name":"Shengfuling",
    "gn:population":0,
    "gn:timezone":"Asia/Shanghai",
    "iso:country":"CN",
    "name:zho_x_preferred":[
        "\u5723\u5e9c\u5cad"
    ],
    "wof:name":"Shengfuling",
    "wof:placetype":"locality"
},
  "geometry": {"coordinates":[117.10899999999999,35.7218],"type":"Point"}
}