{
  "type": "Feature",
  "properties": {
    "gn:admin1_code":"11.0",
    "gn:asciiname":"Maoliwan",
    "gn:country_code":"CN",
    "gn:dem":477,
    "gn:feature_class":"P",
    "gn:feature_code":"PPL",
    "gn:name":"Maoliwan",
    "gn:population":0,
    "gn:timezone":"Asia/Shanghai",
    "iso:country":"CN",
    "name:zho_x_preferred":[
        "\u6bdb\u91cc\u6e7e"
    ],
    "wof:name":"Maoliwan",
    "wof:placetype":"locality"
},
  "geometry": {"coordinates":[111.88405,25.97758],"type":"Point"}
}