{
  "type": "Feature",
  "properties": {
    "gn:admin1_code":"26.0",
    "gn:asciiname":"Miaohuohuo",
    "gn:country_code":"CN",
    "gn:dem":1489,
    "gn:feature_class":"P",
    "gn:feature_code":"PPL",
    "gn:name":"Miaohuohuo",
    "gn:population":0,
    "gn:timezone":"Asia/Shanghai",
    "iso:country":"CN",
    "name:zho_x_preferred":[
        "\u5e99\u4f19\u4f19"
    ],
    "wof:name":"Miaohuohuo",
    "wof:placetype":"locality"
},
  "geometry": {"coordinates":[106.71104,34.9399],"type":"Point"}
}