{
  "type": "Feature",
  "properties": {
    "gn:admin1_code":"14.0",
    "gn:asciiname":"Nanmu",
    "gn:country_code":"CN",
    "gn:dem":4493,
    "gn:feature_class":"P",
    "gn:feature_code":"PPL",
    "gn:name":"Nanmu",
    "gn:population":0,
    "gn:timezone":"Asia/Urumqi",
    "iso:country":"CN",
    "name:zho_x_preferred":[
        "\u5357\u6728"
    ],
    "wof:name":"Nanmu",
    "wof:placetype":"locality"
},
  "geometry": {"coordinates":[86.789,31.601],"type":"Point"}
}