{
  "type": "Feature",
  "properties": {
    "gn:admin1_code":"19.0",
    "gn:asciiname":"Shihuiyao Xigou",
    "gn:country_code":"CN",
    "gn:dem":91,
    "gn:feature_class":"P",
    "gn:feature_code":"PPL",
    "gn:name":"Shihuiyao Xigou",
    "gn:population":0,
    "gn:timezone":"Asia/Shanghai",
    "iso:country":"CN",
    "name:zho_x_preferred":[
        "\u77f3\u7070\u7a91\u897f\u6c9f"
    ],
    "wof:name":"Shihuiyao Xigou",
    "wof:placetype":"locality"
},
  "geometry": {"coordinates":[122.56174,40.49025],"type":"Point"}
}