{
  "type": "Feature",
  "properties": {
    "gn:admin1_code":"29",
    "gn:asciiname":"Candoutian",
    "gn:country_code":"CN",
    "gn:dem":1450,
    "gn:feature_class":"P",
    "gn:feature_code":"PPL",
    "gn:name":"Candoutian",
    "gn:population":0,
    "gn:timezone":"Asia/Shanghai",
    "iso:country":"CN",
    "name:zho_x_preferred":[
        "\u8695\u8c46\u7530"
    ],
    "wof:name":"Candoutian",
    "wof:placetype":"locality"
},
  "geometry": {"coordinates":[101.709,24.3994],"type":"Point"}
}