{
  "type": "Feature",
  "properties": {
    "gn:admin1_code":"26.0",
    "gn:asciiname":"Longdengcun",
    "gn:country_code":"CN",
    "gn:dem":721,
    "gn:feature_class":"P",
    "gn:feature_code":"PPL",
    "gn:name":"Longdengcun",
    "gn:population":0,
    "gn:timezone":"Asia/Shanghai",
    "iso:country":"CN",
    "name:zho_x_preferred":[
        "\u9f99\u706f\u6751"
    ],
    "wof:name":"Longdengcun",
    "wof:placetype":"locality"
},
  "geometry": {"coordinates":[107.40228,32.80862],"type":"Point"}
}