{
  "type": "Feature",
  "properties": {
    "gn:admin1_code":"10",
    "gn:asciiname":"Xihuluwan",
    "gn:country_code":"CN",
    "gn:dem":24,
    "gn:feature_class":"P",
    "gn:feature_code":"PPL",
    "gn:name":"Xihuluwan",
    "gn:population":0,
    "gn:timezone":"Asia/Shanghai",
    "iso:country":"CN",
    "name:zho_x_preferred":[
        "\u897f\u846b\u82a6\u6e7e"
    ],
    "wof:name":"Xihuluwan",
    "wof:placetype":"locality"
},
  "geometry": {"coordinates":[115.181,37.5566],"type":"Point"}
}