{
  "type": "Feature",
  "properties": {
    "gn:admin1_code":"11.0",
    "gn:asciiname":"Zhishan'an",
    "gn:country_code":"CN",
    "gn:dem":82,
    "gn:feature_class":"P",
    "gn:feature_code":"PPL",
    "gn:name":"Zhishan\u2019an",
    "gn:population":0,
    "gn:timezone":"Asia/Shanghai",
    "iso:country":"CN",
    "name:und_x_variant":[
        "Zhishan\u2019an"
    ],
    "name:zho_x_preferred":[
        "\u667a\u5c71\u5b89"
    ],
    "wof:name":"Zhishan'an",
    "wof:placetype":"locality"
},
  "geometry": {"coordinates":[112.67626,28.28],"type":"Point"}
}