{
  "type": "Feature",
  "properties": {
    "gn:admin1_code":"2.0",
    "gn:asciiname":"Lihoukeng",
    "gn:country_code":"CN",
    "gn:dem":416,
    "gn:feature_class":"P",
    "gn:feature_code":"PPL",
    "gn:name":"Lihoukeng",
    "gn:population":0,
    "gn:timezone":"Asia/Shanghai",
    "iso:country":"CN",
    "name:zho_x_preferred":[
        "\u91cc\u540e\u5751"
    ],
    "wof:name":"Lihoukeng",
    "wof:placetype":"locality"
},
  "geometry": {"coordinates":[120.88055,28.98635],"type":"Point"}
}