{
  "type": "Feature",
  "properties": {
    "gn:admin1_code":"5.0",
    "gn:asciiname":"Maweishan",
    "gn:country_code":"CN",
    "gn:dem":273,
    "gn:feature_class":"P",
    "gn:feature_code":"PPL",
    "gn:name":"Maweishan",
    "gn:population":0,
    "gn:timezone":"Asia/Shanghai",
    "iso:country":"CN",
    "name:zho_x_preferred":[
        "\u9a6c\u5c3e\u5c71"
    ],
    "wof:name":"Maweishan",
    "wof:placetype":"locality"
},
  "geometry": {"coordinates":[126.86669999999999,43.92307],"type":"Point"}
}