{
  "type": "Feature",
  "properties": {
    "gn:admin1_code":"6.0",
    "gn:asciiname":"Nalongduo",
    "gn:country_code":"CN",
    "gn:dem":4228,
    "gn:feature_class":"P",
    "gn:feature_code":"PPL",
    "gn:name":"Nalongduo",
    "gn:population":0,
    "gn:timezone":"Asia/Urumqi",
    "iso:country":"CN",
    "name:zho_x_preferred":[
        "\u90a3\u9f99\u591a"
    ],
    "wof:name":"Nalongduo",
    "wof:placetype":"locality"
},
  "geometry": {"coordinates":[97.24142000000001,32.48034000000001],"type":"Point"}
}