{
  "type": "Feature",
  "properties": {
    "gn:admin1_code":"14.0",
    "gn:asciiname":"Dikacun",
    "gn:country_code":"CN",
    "gn:dem":3792,
    "gn:feature_class":"P",
    "gn:feature_code":"PPL",
    "gn:name":"Dikacun",
    "gn:population":0,
    "gn:timezone":"Asia/Urumqi",
    "iso:country":"CN",
    "name:zho_x_preferred":[
        "\u5730\u5361\u6751"
    ],
    "wof:name":"Dikacun",
    "wof:placetype":"locality"
},
  "geometry": {"coordinates":[98.22305,31.05715],"type":"Point"}
}