{
  "type": "Feature",
  "properties": {
    "iso:country":"CN",
    "qs:name":"\u4e39\u5df4",
    "qs:name_adm0":"\u4e2d\u570b",
    "qs:name_adm1":"\u56db\u5ddd\u7701",
    "qs:photos":550,
    "qs:photos_1k":111,
    "qs:photos_9k":2,
    "qs:photos_9r":5,
    "qs:photos_all":550,
    "qs:photos_sr":7,
    "qs:placetype":"Town",
    "qs:pop_sr":"0",
    "wd:wordcount":40,
    "wof:name":"\u4e39\u5df4",
    "wof:placetype":"locality"
},
  "geometry": {"coordinates":[101.87707899999999,30.892],"type":"Point"}
}