{
  "type": "Feature",
  "properties": {
    "iso:country":"CN",
    "name:ara_x_preferred":[
        "\u0645\u062d\u0627\u0641\u0638\u0629 \u062f\u0627\u0646\u0628\u0627"
    ],
    "name:ben_x_preferred":[
        "\u09a1\u09be\u09a8\u09ac\u09be \u09aa\u09cd\u09b0\u09a6\u09c7\u09b6"
    ],
    "name:bod_x_preferred":[
        "\u0f62\u0f7c\u0f44\u0f0b\u0f56\u0fb2\u0f42\u0f0d"
    ],
    "name:deu_x_preferred":[
        "Rongzhag"
    ],
    "name:eng_x_preferred":[
        "Danba County"
    ],
    "name:fas_x_preferred":[
        "\u0634\u0647\u0631\u0633\u062a\u0627\u0646 \u062f\u0627\u0646\u0628\u0627"
    ],
    "name:gan_x_preferred":[
        "\u4e39\u5df4\u53bf"
    ],
    "name:jpn_x_preferred":[
        "\u4e39\u5df4\u770c"
    ],
    "name:kor_x_preferred":[
        "\ub2e8\ubc14\ud604"
    ],
    "name:nan_x_preferred":[
        "Rongzhag-ko\u0101n"
    ],
    "name:nld_x_preferred":[
        "Rongzhag"
    ],
    "name:nob_x_preferred":[
        "Danba"
    ],
    "name:rus_x_preferred":[
        "\u0420\u043e\u043d\u0433\u0434\u0436\u0430\u0433"
    ],
    "name:spa_x_preferred":[
        "Rongzhag"
    ],
    "name:spa_x_variant":[
        "Danba"
    ],
    "name:swe_x_preferred":[
        "Danba"
    ],
    "name:ukr_x_preferred":[
        "\u0414\u0430\u043d\u044c\u0431\u0430"
    ],
    "name:vie_x_preferred":[
        "\u0110an Ba"
    ],
    "name:wuu_x_preferred":[
        "\u4e39\u5df4\u53bf"
    ],
    "name:zho_x_preferred":[
        "\u4e39\u5df4\u53bf"
    ],
    "qs:name":"\u4e39\u5df4",
    "qs:name_adm0":"\u4e2d\u570b",
    "qs:name_adm1":"\u56db\u5ddd\u7701",
    "qs:photos":550,
    "qs:photos_1k":111,
    "qs:photos_9k":2,
    "qs:photos_9r":5,
    "qs:photos_all":550,
    "qs:photos_sr":7,
    "qs:placetype":"Town",
    "qs:pop_sr":"0",
    "wd:wordcount":40,
    "wof:name":"\u4e39\u5df4",
    "wof:placetype":"locality"
},
  "geometry": {"coordinates":[101.87707899999999,30.892],"type":"Point"}
}