{
  "type": "Feature",
  "properties": {
    "gn:admin1_code":"12",
    "gn:asciiname":"Tingsiqiao",
    "gn:country_code":"CN",
    "gn:dem":27,
    "gn:feature_class":"P",
    "gn:feature_code":"PPLA4",
    "gn:name":"Tingsiqiao",
    "gn:population":0,
    "gn:timezone":"Asia/Shanghai",
    "iso:country":"CN",
    "name:und_x_variant":[
        "Ting-sze-chiao",
        "Tingszekiao",
        "T\u2019ing-ssu-ch\u2019iao",
        "Tingsiqiao",
        "\u6c40\u6cd7\u6865",
        "Tingsiqiao Zhen",
        "\u6c40\u6cd7\u6865\u9547"
    ],
    "wof:name":"Tingsiqiao",
    "wof:placetype":"locality"
},
  "geometry": {"coordinates":[114.16691000000002,29.81668],"type":"Point"}
}