{
  "type": "Feature",
  "properties": {
    "gn:admin1_code":"15.0",
    "gn:asciiname":"Baiquangou",
    "gn:country_code":"CN",
    "gn:dem":1196,
    "gn:feature_class":"P",
    "gn:feature_code":"PPL",
    "gn:name":"Baiquangou",
    "gn:population":0,
    "gn:timezone":"Asia/Shanghai",
    "iso:country":"CN",
    "name:zho_x_preferred":[
        "\u767e\u6cc9\u6c9f"
    ],
    "wof:name":"Baiquangou",
    "wof:placetype":"locality"
},
  "geometry": {"coordinates":[107.16200000000001,35.3775],"type":"Point"}
}