{
  "type": "Feature",
  "properties": {
    "gn:admin1_code":"29",
    "gn:asciiname":"Maocaofang",
    "gn:country_code":"CN",
    "gn:dem":2055,
    "gn:feature_class":"P",
    "gn:feature_code":"PPL",
    "gn:name":"Maocaofang",
    "gn:population":0,
    "gn:timezone":"Asia/Shanghai",
    "iso:country":"CN",
    "name:zho_x_preferred":[
        "\u8305\u8349\u623f"
    ],
    "wof:name":"Maocaofang",
    "wof:placetype":"locality"
},
  "geometry": {"coordinates":[102.785,24.5404],"type":"Point"}
}