{
  "type": "Feature",
  "properties": {
    "gn:admin1_code":"15.0",
    "gn:asciiname":"Mingxing",
    "gn:country_code":"CN",
    "gn:dem":1839,
    "gn:feature_class":"P",
    "gn:feature_code":"PPL",
    "gn:name":"Mingxing",
    "gn:population":0,
    "gn:timezone":"Asia/Shanghai",
    "iso:country":"CN",
    "name:und_x_variant":[
        "\u660e\u661f"
    ],
    "wof:name":"Mingxing",
    "wof:placetype":"locality"
},
  "geometry": {"coordinates":[105.26628999999998,35.42938],"type":"Point"}
}