{
  "type": "Feature",
  "properties": {
    "gn:admin1_code":"26.0",
    "gn:asciiname":"Huanghuaishu",
    "gn:country_code":"CN",
    "gn:dem":1339,
    "gn:feature_class":"P",
    "gn:feature_code":"PPL",
    "gn:name":"Huanghuaishu",
    "gn:population":0,
    "gn:timezone":"Asia/Shanghai",
    "iso:country":"CN",
    "name:und_x_variant":[
        "\u9ec4\u69d0\u6811"
    ],
    "wof:name":"Huanghuaishu",
    "wof:placetype":"locality"
},
  "geometry": {"coordinates":[107.34954,34.20563],"type":"Point"}
}