{
  "type": "Feature",
  "properties": {
    "gn:admin1_code":"8.0",
    "gn:asciiname":"Wuxingcun",
    "gn:country_code":"CN",
    "gn:dem":476,
    "gn:feature_class":"P",
    "gn:feature_code":"PPL",
    "gn:name":"Wuxingcun",
    "gn:population":0,
    "gn:timezone":"Asia/Shanghai",
    "iso:country":"CN",
    "name:zho_x_preferred":[
        "\u4e94\u5174\u6751"
    ],
    "wof:name":"Wuxingcun",
    "wof:placetype":"locality"
},
  "geometry": {"coordinates":[130.19952000000001,44.79846],"type":"Point"}
}