{
  "type": "Feature",
  "properties": {
    "gn:admin1_code":"3.0",
    "gn:asciiname":"Xiacheng",
    "gn:country_code":"CN",
    "gn:dem":43,
    "gn:feature_class":"P",
    "gn:feature_code":"PPL",
    "gn:name":"Xiacheng",
    "gn:population":0,
    "gn:timezone":"Asia/Shanghai",
    "iso:country":"CN",
    "name:zho_x_preferred":[
        "\u4e0b\u7a0b"
    ],
    "wof:name":"Xiacheng",
    "wof:placetype":"locality"
},
  "geometry": {"coordinates":[115.41800000000001,28.3676],"type":"Point"}
}