{
  "type": "Feature",
  "properties": {
    "gn:admin1_code":"32.0",
    "gn:asciiname":"Erlangqiao",
    "gn:country_code":"CN",
    "gn:dem":401,
    "gn:feature_class":"P",
    "gn:feature_code":"PPL",
    "gn:name":"Erlangqiao",
    "gn:population":0,
    "gn:timezone":"Asia/Shanghai",
    "iso:country":"CN",
    "name:zho_x_preferred":[
        "\u4e8c\u90ce\u6865"
    ],
    "wof:name":"Erlangqiao",
    "wof:placetype":"locality"
},
  "geometry": {"coordinates":[107.626,31.0066],"type":"Point"}
}