{
  "type": "Feature",
  "properties": {
    "gn:admin1_code":"30.0",
    "gn:asciiname":"Siqianxu",
    "gn:country_code":"CN",
    "gn:dem":6,
    "gn:feature_class":"P",
    "gn:feature_code":"PPL",
    "gn:name":"Siqianxu",
    "gn:population":0,
    "gn:timezone":"Asia/Shanghai",
    "iso:country":"CN",
    "name:zho_x_preferred":[
        "\u5bfa\u524d\u5729"
    ],
    "wof:name":"Siqianxu",
    "wof:placetype":"locality"
},
  "geometry": {"coordinates":[112.71735,22.41703],"type":"Point"}
}