{
  "type": "Feature",
  "properties": {
    "gn:admin1_code":"15.0",
    "gn:asciiname":"Lijiawan",
    "gn:country_code":"CN",
    "gn:dem":1888,
    "gn:feature_class":"P",
    "gn:feature_code":"PPL",
    "gn:name":"Lijiawan",
    "gn:population":0,
    "gn:timezone":"Asia/Shanghai",
    "iso:country":"CN",
    "name:und_x_variant":[
        "\u674e\u5bb6\u6e7e"
    ],
    "wof:name":"Lijiawan",
    "wof:placetype":"locality"
},
  "geometry": {"coordinates":[105.26900000000001,35.995],"type":"Point"}
}