{
  "type": "Feature",
  "properties": {
    "gn:admin1_code":"11",
    "gn:asciiname":"Yantangli",
    "gn:country_code":"CN",
    "gn:dem":677,
    "gn:feature_class":"P",
    "gn:feature_code":"PPL",
    "gn:name":"Yantangli",
    "gn:population":0,
    "gn:timezone":"Asia/Shanghai",
    "iso:country":"CN",
    "name:zho_x_preferred":[
        "\u6edf\u5858\u91cc"
    ],
    "wof:name":"Yantangli",
    "wof:placetype":"locality"
},
  "geometry": {"coordinates":[111.68021,27.92569],"type":"Point"}
}