{
  "type": "Feature",
  "properties": {
    "gn:admin1_code":"15.0",
    "gn:asciiname":"Rouwuke",
    "gn:country_code":"CN",
    "gn:dem":2894,
    "gn:feature_class":"P",
    "gn:feature_code":"PPL",
    "gn:name":"Rouwuke",
    "gn:population":0,
    "gn:timezone":"Asia/Shanghai",
    "iso:country":"CN",
    "name:zho_x_preferred":[
        "\u8089\u543e\u53ef"
    ],
    "wof:name":"Rouwuke",
    "wof:placetype":"locality"
},
  "geometry": {"coordinates":[102.867,34.797],"type":"Point"}
}