{
  "type": "Feature",
  "properties": {
    "gn:admin1_code":"8.0",
    "gn:asciiname":"Ailucun",
    "gn:country_code":"CN",
    "gn:dem":281,
    "gn:feature_class":"P",
    "gn:feature_code":"PPL",
    "gn:name":"Ailucun",
    "gn:population":0,
    "gn:timezone":"Asia/Shanghai",
    "iso:country":"CN",
    "name:zho_x_preferred":[
        "\u7231\u8def\u6751"
    ],
    "wof:name":"Ailucun",
    "wof:placetype":"locality"
},
  "geometry": {"coordinates":[129.32894999999999,44.18965],"type":"Point"}
}