{
  "type": "Feature",
  "properties": {
    "gn:admin1_code":"30.0",
    "gn:asciiname":"Guo'erwu",
    "gn:country_code":"CN",
    "gn:dem":35,
    "gn:feature_class":"P",
    "gn:feature_code":"PPL",
    "gn:name":"Guo\u2019erwu",
    "gn:population":0,
    "gn:timezone":"Asia/Shanghai",
    "iso:country":"CN",
    "name:zho_x_preferred":[
        "Guo\u2019erwu"
    ],
    "name:zho_x_variant":[
        "\u9505\u8033\u5c4b"
    ],
    "wof:name":"Guo'erwu",
    "wof:placetype":"locality"
},
  "geometry": {"coordinates":[113.38667,24.08944],"type":"Point"}
}