{
  "type": "Feature",
  "properties": {
    "gn:admin1_code":"29.0",
    "gn:asciiname":"Erdaowan",
    "gn:country_code":"CN",
    "gn:dem":2309,
    "gn:feature_class":"P",
    "gn:feature_code":"PPL",
    "gn:name":"Erdaowan",
    "gn:population":0,
    "gn:timezone":"Asia/Shanghai",
    "iso:country":"CN",
    "name:zho_x_preferred":[
        "\u4e8c\u9053\u6e7e"
    ],
    "wof:name":"Erdaowan",
    "wof:placetype":"locality"
},
  "geometry": {"coordinates":[100.55,26.3441],"type":"Point"}
}