{
  "type": "Feature",
  "properties": {
    "gn:admin1_code":"25.0",
    "gn:asciiname":"Zhaikecun",
    "gn:country_code":"CN",
    "gn:dem":66,
    "gn:feature_class":"P",
    "gn:feature_code":"PPL",
    "gn:name":"Zhaikecun",
    "gn:population":0,
    "gn:timezone":"Asia/Shanghai",
    "iso:country":"CN",
    "name:zho_x_preferred":[
        "\u5b85\u79d1\u6751"
    ],
    "wof:name":"Zhaikecun",
    "wof:placetype":"locality"
},
  "geometry": {"coordinates":[119.28734,36.31187],"type":"Point"}
}