{
  "type": "Feature",
  "properties": {
    "gn:admin1_code":"3.0",
    "gn:asciiname":"Qingguo",
    "gn:country_code":"CN",
    "gn:dem":31,
    "gn:feature_class":"P",
    "gn:feature_code":"PPL",
    "gn:name":"Qingguo",
    "gn:population":0,
    "gn:timezone":"Asia/Shanghai",
    "iso:country":"CN",
    "name:und_x_variant":[
        "\u9752\u90ed"
    ],
    "wof:name":"Qingguo",
    "wof:placetype":"locality"
},
  "geometry": {"coordinates":[115.50351999999999,28.04347000000001],"type":"Point"}
}