{
  "type": "Feature",
  "properties": {
    "gn:admin1_code":"30.0",
    "gn:asciiname":"Shecuozhoucun",
    "gn:country_code":"CN",
    "gn:dem":13,
    "gn:feature_class":"P",
    "gn:feature_code":"PPL",
    "gn:name":"Shecuozhoucun",
    "gn:population":0,
    "gn:timezone":"Asia/Shanghai",
    "iso:country":"CN",
    "name:zho_x_preferred":[
        "\u4f58\u539d\u6d32\u6751"
    ],
    "wof:name":"Shecuozhoucun",
    "wof:placetype":"locality"
},
  "geometry": {"coordinates":[116.6915,23.56387],"type":"Point"}
}