{
  "type": "Feature",
  "properties": {
    "gn:admin1_code":"11.0",
    "gn:asciiname":"Weijiaping",
    "gn:country_code":"CN",
    "gn:dem":229,
    "gn:feature_class":"P",
    "gn:feature_code":"PPL",
    "gn:name":"Weijiaping",
    "gn:population":0,
    "gn:timezone":"Asia/Shanghai",
    "iso:country":"CN",
    "name:zho_x_preferred":[
        "\u6845\u5bb6\u576a"
    ],
    "wof:name":"Weijiaping",
    "wof:placetype":"locality"
},
  "geometry": {"coordinates":[113.19773000000001,26.45074],"type":"Point"}
}