{
  "type": "Feature",
  "properties": {
    "gn:admin1_code":"15.0",
    "gn:asciiname":"Shengounao",
    "gn:country_code":"CN",
    "gn:dem":2103,
    "gn:feature_class":"P",
    "gn:feature_code":"PPL",
    "gn:name":"Shengounao",
    "gn:population":0,
    "gn:timezone":"Asia/Shanghai",
    "iso:country":"CN",
    "name:zho_x_preferred":[
        "\u6df1\u6c9f\u8111"
    ],
    "wof:name":"Shengounao",
    "wof:placetype":"locality"
},
  "geometry": {"coordinates":[103.14700000000001,36.464],"type":"Point"}
}