{
  "type": "Feature",
  "properties": {
    "gn:admin1_code":"33.0",
    "gn:asciiname":"Daoxiang",
    "gn:country_code":"CN",
    "gn:dem":327,
    "gn:feature_class":"P",
    "gn:feature_code":"PPL",
    "gn:name":"Daoxiang",
    "gn:population":0,
    "gn:timezone":"Asia/Shanghai",
    "iso:country":"CN",
    "name:zho_x_preferred":[
        "\u7a3b\u9999"
    ],
    "wof:name":"Daoxiang",
    "wof:placetype":"locality"
},
  "geometry": {"coordinates":[106.03749999999999,29.66559],"type":"Point"}
}