{
  "type": "Feature",
  "properties": {
    "gn:admin1_code":"19.0",
    "gn:asciiname":"Haolibao",
    "gn:country_code":"CN",
    "gn:dem":154,
    "gn:feature_class":"P",
    "gn:feature_code":"PPL",
    "gn:name":"Haolibao",
    "gn:population":0,
    "gn:timezone":"Asia/Shanghai",
    "iso:country":"CN",
    "name:und_x_variant":[
        "\u6d69\u529b\u4fdd"
    ],
    "name:zho_x_preferred":[
        "\u6d69\u529b\u4fdd"
    ],
    "wof:name":"Haolibao",
    "wof:placetype":"locality"
},
  "geometry": {"coordinates":[122.74299999999999,42.6512],"type":"Point"}
}