{
  "type": "Feature",
  "properties": {
    "gn:admin1_code":"29.0",
    "gn:asciiname":"Yanshuigou",
    "gn:country_code":"CN",
    "gn:dem":1473,
    "gn:feature_class":"P",
    "gn:feature_code":"PPL",
    "gn:name":"Yanshuigou",
    "gn:population":0,
    "gn:timezone":"Asia/Shanghai",
    "iso:country":"CN",
    "name:zho_x_preferred":[
        "\u76d0\u6c34\u6c9f"
    ],
    "wof:name":"Yanshuigou",
    "wof:placetype":"locality"
},
  "geometry": {"coordinates":[103.093,26.5013],"type":"Point"}
}