{
  "type": "Feature",
  "properties": {
    "gn:admin1_code":"19.0",
    "gn:asciiname":"Binggou",
    "gn:country_code":"CN",
    "gn:dem":26,
    "gn:feature_class":"P",
    "gn:feature_code":"PPL",
    "gn:name":"Binggou",
    "gn:population":0,
    "gn:timezone":"Asia/Shanghai",
    "iso:country":"CN",
    "name:und_x_variant":[
        "\u51b0\u6c9f"
    ],
    "wof:name":"Binggou",
    "wof:placetype":"locality"
},
  "geometry": {"coordinates":[123.52024,40.13654],"type":"Point"}
}