{
  "type": "Feature",
  "properties": {
    "gn:admin1_code":"19.0",
    "gn:asciiname":"Zhangjia Yingzi",
    "gn:country_code":"CN",
    "gn:dem":296,
    "gn:feature_class":"P",
    "gn:feature_code":"PPL",
    "gn:name":"Zhangjia Yingzi",
    "gn:population":0,
    "gn:timezone":"Asia/Shanghai",
    "iso:country":"CN",
    "name:und_x_variant":[
        "\u5f20\u5bb6\u8425\u5b50"
    ],
    "name:zho_x_preferred":[
        "\u5f20\u5bb6\u8425\u5b50"
    ],
    "wof:name":"Zhangjia Yingzi",
    "wof:placetype":"locality"
},
  "geometry": {"coordinates":[119.97418999999999,41.2661],"type":"Point"}
}