{
  "type": "Feature",
  "properties": {
    "gn:admin1_code":"26.0",
    "gn:asciiname":"Qinggangling",
    "gn:country_code":"CN",
    "gn:dem":925,
    "gn:feature_class":"P",
    "gn:feature_code":"PPL",
    "gn:name":"Qinggangling",
    "gn:population":0,
    "gn:timezone":"Asia/Shanghai",
    "iso:country":"CN",
    "name:und_x_variant":[
        "\u9752\u5c97\u5cad"
    ],
    "wof:name":"Qinggangling",
    "wof:placetype":"locality"
},
  "geometry": {"coordinates":[106.99102000000001,33.71413],"type":"Point"}
}