{
  "type": "Feature",
  "properties": {
    "gn:admin1_code":"16.0",
    "gn:asciiname":"Jinli",
    "gn:country_code":"CN",
    "gn:dem":926,
    "gn:feature_class":"P",
    "gn:feature_code":"PPL",
    "gn:name":"Jinli",
    "gn:population":0,
    "gn:timezone":"Asia/Shanghai",
    "iso:country":"CN",
    "name:ita_x_preferred":[
        "Jin Li"
    ],
    "name:zho_x_preferred":[
        "\u91d1\u91cc"
    ],
    "name:zho_x_variant":[
        "\u9526\u91cc\u53e4\u8857"
    ],
    "wof:name":"Jinli",
    "wof:placetype":"locality"
},
  "geometry": {"coordinates":[107.29000000000001,25.4983],"type":"Point"}
}