{
  "type": "Feature",
  "properties": {
    "gn:admin1_code":"8.0",
    "gn:asciiname":"Fushantun",
    "gn:country_code":"CN",
    "gn:dem":182,
    "gn:feature_class":"P",
    "gn:feature_code":"PPL",
    "gn:name":"Fushantun",
    "gn:population":0,
    "gn:timezone":"Asia/Shanghai",
    "iso:country":"CN",
    "name:zho_x_preferred":[
        "\u798f\u5c71\u5c6f"
    ],
    "wof:name":"Fushantun",
    "wof:placetype":"locality"
},
  "geometry": {"coordinates":[128.45258999999999,45.42318],"type":"Point"}
}