{
  "type": "Feature",
  "properties": {
    "gn:admin1_code":"12.0",
    "gn:asciiname":"Laowuchong",
    "gn:country_code":"CN",
    "gn:dem":1607,
    "gn:feature_class":"P",
    "gn:feature_code":"PPL",
    "gn:name":"Laowuchong",
    "gn:population":0,
    "gn:timezone":"Asia/Shanghai",
    "iso:country":"CN",
    "name:zho_x_preferred":[
        "\u8001\u5c4b\u51b2"
    ],
    "wof:name":"Laowuchong",
    "wof:placetype":"locality"
},
  "geometry": {"coordinates":[110.65687,30.5026],"type":"Point"}
}