{
  "type": "Feature",
  "properties": {
    "gn:admin1_code":"12.0",
    "gn:asciiname":"Yangjiahe",
    "gn:country_code":"CN",
    "gn:dem":430,
    "gn:feature_class":"P",
    "gn:feature_code":"PPL",
    "gn:name":"Yangjiahe",
    "gn:population":0,
    "gn:timezone":"Asia/Shanghai",
    "iso:country":"CN",
    "name:zho_x_preferred":[
        "Yangjiahe"
    ],
    "name:zho_x_variant":[
        "\u6768\u5bb6\u6cb3"
    ],
    "wof:name":"Yangjiahe",
    "wof:placetype":"locality"
},
  "geometry": {"coordinates":[111.29208,31.00254],"type":"Point"}
}