{
  "type": "Feature",
  "properties": {
    "gn:admin1_code":"15.0",
    "gn:asciiname":"Heluojia",
    "gn:country_code":"CN",
    "gn:dem":2365,
    "gn:feature_class":"P",
    "gn:feature_code":"PPL",
    "gn:name":"Heluojia",
    "gn:population":0,
    "gn:timezone":"Asia/Shanghai",
    "iso:country":"CN",
    "name:zho_x_preferred":[
        "\u4f55\u7f57\u5bb6"
    ],
    "wof:name":"Heluojia",
    "wof:placetype":"locality"
},
  "geometry": {"coordinates":[102.932,36.7227],"type":"Point"}
}