{
  "type": "Feature",
  "properties": {
    "gn:admin1_code":"24.0",
    "gn:asciiname":"Shiziling",
    "gn:country_code":"CN",
    "gn:dem":1284,
    "gn:feature_class":"P",
    "gn:feature_code":"PPL",
    "gn:name":"Shiziling",
    "gn:population":0,
    "gn:timezone":"Asia/Shanghai",
    "iso:country":"CN",
    "name:zho_x_preferred":[
        "\u5341\u5b57\u5cad"
    ],
    "wof:name":"Shiziling",
    "wof:placetype":"locality"
},
  "geometry": {"coordinates":[112.75891,35.85995],"type":"Point"}
}