{
  "type": "Feature",
  "properties": {
    "gn:admin1_code":"1.0",
    "gn:asciiname":"Xinguangcun",
    "gn:country_code":"CN",
    "gn:dem":55,
    "gn:feature_class":"P",
    "gn:feature_code":"PPL",
    "gn:name":"Xinguangcun",
    "gn:population":0,
    "gn:timezone":"Asia/Shanghai",
    "iso:country":"CN",
    "name:zho_x_preferred":[
        "\u65b0\u5149\u6751"
    ],
    "wof:name":"Xinguangcun",
    "wof:placetype":"locality"
},
  "geometry": {"coordinates":[116.87642,31.76444],"type":"Point"}
}