{
  "type": "Feature",
  "properties": {
    "gn:admin1_code":"4.0",
    "gn:asciiname":"Shigou'aicun",
    "gn:country_code":"CN",
    "gn:dem":27,
    "gn:feature_class":"P",
    "gn:feature_code":"PPL",
    "gn:name":"Shigou\u2019aicun",
    "gn:population":0,
    "gn:timezone":"Asia/Shanghai",
    "iso:country":"CN",
    "name:und_x_variant":[
        "Shigou\u2019aicun"
    ],
    "name:zho_x_preferred":[
        "\u77f3\u6c9f\u57c3\u6751"
    ],
    "wof:name":"Shigou'aicun",
    "wof:placetype":"locality"
},
  "geometry": {"coordinates":[118.78192,34.81171],"type":"Point"}
}