{
  "type": "Feature",
  "properties": {
    "gn:admin1_code":"10",
    "gn:asciiname":"Xiganhezi",
    "gn:country_code":"CN",
    "gn:dem":195,
    "gn:feature_class":"P",
    "gn:feature_code":"PPL",
    "gn:name":"Xiganhezi",
    "gn:population":0,
    "gn:timezone":"Asia/Shanghai",
    "iso:country":"CN",
    "name:zho_x_preferred":[
        "\u897f\u8d76\u6cb3\u5b50"
    ],
    "wof:name":"Xiganhezi",
    "wof:placetype":"locality"
},
  "geometry": {"coordinates":[119.20261000000001,40.44294],"type":"Point"}
}