{
  "type": "Feature",
  "properties": {
    "gn:admin1_code":"2.0",
    "gn:asciiname":"Cheta",
    "gn:country_code":"CN",
    "gn:dem":7,
    "gn:feature_class":"P",
    "gn:feature_code":"PPL",
    "gn:name":"Cheta",
    "gn:population":0,
    "gn:timezone":"Asia/Shanghai",
    "iso:country":"CN",
    "name:bul_x_preferred":[
        "\u0427\u0435\u0442\u0430"
    ],
    "name:mkd_x_preferred":[
        "\u0427\u0435\u0442\u0430"
    ],
    "name:pol_x_preferred":[
        "Czeta"
    ],
    "name:und_x_variant":[
        "\u8f66\u5854"
    ],
    "wof:name":"Cheta",
    "wof:placetype":"locality"
},
  "geometry": {"coordinates":[120.45950000000001,30.71295],"type":"Point"}
}