{
  "type": "Feature",
  "properties": {
    "gn:admin1_code":"26.0",
    "gn:asciiname":"Dujiadafang",
    "gn:country_code":"CN",
    "gn:dem":505,
    "gn:feature_class":"P",
    "gn:feature_code":"PPL",
    "gn:name":"Dujiadafang",
    "gn:population":0,
    "gn:timezone":"Asia/Shanghai",
    "iso:country":"CN",
    "name:zho_x_preferred":[
        "\u675c\u5bb6\u5927\u623f"
    ],
    "wof:name":"Dujiadafang",
    "wof:placetype":"locality"
},
  "geometry": {"coordinates":[108.92622,32.47816],"type":"Point"}
}