{
  "type": "Feature",
  "properties": {
    "gn:admin1_code":"29.0",
    "gn:asciiname":"Laodapingzi",
    "gn:country_code":"CN",
    "gn:dem":1364,
    "gn:feature_class":"P",
    "gn:feature_code":"PPL",
    "gn:name":"Laodapingzi",
    "gn:population":0,
    "gn:timezone":"Asia/Shanghai",
    "iso:country":"CN",
    "name:zho_x_preferred":[
        "\u8001\u5927\u576a\u5b50"
    ],
    "wof:name":"Laodapingzi",
    "wof:placetype":"locality"
},
  "geometry": {"coordinates":[98.8182,24.9606],"type":"Point"}
}