{
  "type": "Feature",
  "properties": {
    "gn:admin1_code":"25",
    "gn:asciiname":"Dashabuzhuang",
    "gn:country_code":"CN",
    "gn:dem":7,
    "gn:feature_class":"P",
    "gn:feature_code":"PPL",
    "gn:name":"Dashabuzhuang",
    "gn:population":0,
    "gn:timezone":"Asia/Shanghai",
    "iso:country":"CN",
    "name:zho_x_preferred":[
        "\u5927\u6c99\u57e0\u5e84"
    ],
    "wof:name":"Dashabuzhuang",
    "wof:placetype":"locality"
},
  "geometry": {"coordinates":[119.941,37.3146],"type":"Point"}
}