{
  "type": "Feature",
  "properties": {
    "gn:admin1_code":"7",
    "gn:asciiname":"Huangcha",
    "gn:country_code":"CN",
    "gn:dem":98,
    "gn:feature_class":"P",
    "gn:feature_code":"PPL",
    "gn:name":"Huangcha",
    "gn:population":0,
    "gn:timezone":"Asia/Shanghai",
    "iso:country":"CN",
    "name:und_x_variant":[
        "\u9ec4\u8336"
    ],
    "name:zho_x_preferred":[
        "\u9ec4\u8336"
    ],
    "wof:name":"Huangcha",
    "wof:placetype":"locality"
},
  "geometry": {"coordinates":[117.02278,23.96528],"type":"Point"}
}