{
  "type": "Feature",
  "properties": {
    "gn:admin1_code":"16.0",
    "gn:asciiname":"Jiushe",
    "gn:country_code":"CN",
    "gn:dem":156,
    "gn:feature_class":"P",
    "gn:feature_code":"PPL",
    "gn:name":"Jiushe",
    "gn:population":0,
    "gn:timezone":"Asia/Shanghai",
    "iso:country":"CN",
    "name:zho_x_preferred":[
        "\u65e7\u793e"
    ],
    "wof:name":"Jiushe",
    "wof:placetype":"locality"
},
  "geometry": {"coordinates":[110.32599999999999,23.1387],"type":"Point"}
}