{
  "type": "Feature",
  "properties": {
    "gn:admin1_code":"20.0",
    "gn:asciiname":"Yutaigou",
    "gn:country_code":"CN",
    "gn:dem":1576,
    "gn:feature_class":"P",
    "gn:feature_code":"PPL",
    "gn:name":"Yutaigou",
    "gn:population":0,
    "gn:timezone":"Asia/Shanghai",
    "iso:country":"CN",
    "name:und_x_variant":[
        "\u4f59\u592a\u6c9f"
    ],
    "wof:name":"Yutaigou",
    "wof:placetype":"locality"
},
  "geometry": {"coordinates":[110.02641,41.25248],"type":"Point"}
}