{
  "type": "Feature",
  "properties": {
    "gn:admin1_code":"29.0",
    "gn:asciiname":"Banshan",
    "gn:country_code":"CN",
    "gn:dem":2160,
    "gn:feature_class":"P",
    "gn:feature_code":"PPL",
    "gn:name":"Banshan",
    "gn:population":0,
    "gn:timezone":"Asia/Shanghai",
    "iso:country":"CN",
    "name:und_x_variant":[
        "\u534a\u5c71"
    ],
    "wof:name":"Banshan",
    "wof:placetype":"locality"
},
  "geometry": {"coordinates":[104.51860000000001,26.50631],"type":"Point"}
}