{
  "type": "Feature",
  "properties": {
    "gn:admin1_code":"15.0",
    "gn:asciiname":"Wangfu",
    "gn:country_code":"CN",
    "gn:dem":1853,
    "gn:feature_class":"P",
    "gn:feature_code":"PPL",
    "gn:name":"Wangfu",
    "gn:population":0,
    "gn:timezone":"Asia/Shanghai",
    "iso:country":"CN",
    "name:zho_x_preferred":[
        "\u738b\u4ed8"
    ],
    "wof:name":"Wangfu",
    "wof:placetype":"locality"
},
  "geometry": {"coordinates":[105.94199999999999,34.7866],"type":"Point"}
}