{
  "type": "Feature",
  "properties": {
    "gn:admin1_code":"15",
    "gn:asciiname":"Dayekou",
    "gn:country_code":"CN",
    "gn:dem":2839,
    "gn:feature_class":"P",
    "gn:feature_code":"PPL",
    "gn:name":"Dayekou",
    "gn:population":0,
    "gn:timezone":"Asia/Shanghai",
    "iso:country":"CN",
    "name:zho_x_preferred":[
        "\u5927\u91ce\u53e3"
    ],
    "wof:name":"Dayekou",
    "wof:placetype":"locality"
},
  "geometry": {"coordinates":[100.255,38.542],"type":"Point"}
}