{
  "type": "Feature",
  "properties": {
    "gn:admin1_code":"10",
    "gn:asciiname":"Kouzhuang",
    "gn:country_code":"CN",
    "gn:dem":31,
    "gn:feature_class":"P",
    "gn:feature_code":"PPL",
    "gn:name":"Kouzhuang",
    "gn:population":0,
    "gn:timezone":"Asia/Shanghai",
    "iso:country":"CN",
    "name:zho_x_preferred":[
        "\u53e9\u5e84"
    ],
    "wof:name":"Kouzhuang",
    "wof:placetype":"locality"
},
  "geometry": {"coordinates":[115.90600000000001,37.2264],"type":"Point"}
}