{
  "type": "Feature",
  "properties": {
    "gn:admin1_code":"32.0",
    "gn:asciiname":"Qinggang",
    "gn:country_code":"CN",
    "gn:dem":838,
    "gn:feature_class":"P",
    "gn:feature_code":"PPL",
    "gn:name":"Qinggang",
    "gn:population":0,
    "gn:timezone":"Asia/Shanghai",
    "iso:country":"CN",
    "name:ara_x_preferred":[
        "\u062a\u0634\u064a\u0646\u0643\u0627\u0646\u063a"
    ],
    "name:ben_x_preferred":[
        "\u0995\u09c1\u0987\u0982\u0997\u09cd\u09af\u09be\u0982"
    ],
    "name:deu_x_preferred":[
        "Qinggang"
    ],
    "name:ell_x_preferred":[
        "\u039a\u03b9\u03bd\u03b3\u03ba\u03b3\u03ba\u03ac\u03bd\u03b3\u03ba"
    ],
    "name:eng_x_preferred":[
        "Qinggang"
    ],
    "name:fas_x_preferred":[
        "\u0686\u06cc\u0646\u06af\u06af\u0627\u0646\u06af"
    ],
    "name:fra_x_preferred":[
        "Qinggang"
    ],
    "name:heb_x_preferred":[
        "\u05e7\u05d5\u05d5\u05d9\u05e0\u05d2\u05d0\u05e0\u05d2"
    ],
    "name:hin_x_preferred":[
        "\u0915\u093f\u0902\u0917\u0948\u0902\u0917"
    ],
    "name:hun_x_preferred":[
        "Qinggang"
    ],
    "name:ind_x_preferred":[
        "Qinggang"
    ],
    "name:ita_x_preferred":[
        "Qinggang"
    ],
    "name:jpn_x_preferred":[
        "\u9752\u5ca1\u93ae"
    ],
    "name:kor_x_preferred":[
        "\uce6d\uac15"
    ],
    "name:nld_x_preferred":[
        "Qinggang"
    ],
    "name:pol_x_preferred":[
        "Qinggang"
    ],
    "name:por_x_preferred":[
        "Qinggang"
    ],
    "name:rus_x_preferred":[
        "\u0426\u0438\u043d\u0433\u0430\u043d"
    ],
    "name:spa_x_preferred":[
        "Qinggang"
    ],
    "name:tur_x_preferred":[
        "Qinggang"
    ],
    "name:ukr_x_preferred":[
        "\u0426\u0438\u043d\u0433\u0430\u043d"
    ],
    "name:urd_x_preferred":[
        "\u0642\u0646\u06af\u0627\u0646\u06af"
    ],
    "name:vie_x_preferred":[
        "Thanh C\u01b0\u01a1ng"
    ],
    "name:zho_x_preferred":[
        "\u9752\u5188"
    ],
    "wof:name":"Qinggang",
    "wof:placetype":"locality"
},
  "geometry": {"coordinates":[104.70099999999999,32.3638],"type":"Point"}
}