{
  "type": "Feature",
  "properties": {
    "gn:admin1_code":"15.0",
    "gn:asciiname":"Changyaoxian",
    "gn:country_code":"CN",
    "gn:dem":1621,
    "gn:feature_class":"P",
    "gn:feature_code":"PPL",
    "gn:name":"Changyaoxian",
    "gn:population":0,
    "gn:timezone":"Asia/Shanghai",
    "iso:country":"CN",
    "name:und_x_variant":[
        "\u5e38\u5d3e\u5c98"
    ],
    "wof:name":"Changyaoxian",
    "wof:placetype":"locality"
},
  "geometry": {"coordinates":[107.01161999999999,36.38178],"type":"Point"}
}