{
  "type": "Feature",
  "properties": {
    "gn:admin1_code":"11.0",
    "gn:asciiname":"Shanchong'ao",
    "gn:country_code":"CN",
    "gn:dem":205,
    "gn:feature_class":"P",
    "gn:feature_code":"PPL",
    "gn:name":"Shanchong\u2019ao",
    "gn:population":0,
    "gn:timezone":"Asia/Shanghai",
    "iso:country":"CN",
    "name:und_x_variant":[
        "Shanchong\u2019ao"
    ],
    "name:zho_x_preferred":[
        "\u5c71\u51b2\u5773"
    ],
    "wof:name":"Shanchong'ao",
    "wof:placetype":"locality"
},
  "geometry": {"coordinates":[113.27795,25.94916],"type":"Point"}
}