{
  "type": "Feature",
  "properties": {
    "gn:admin1_code":"15.0",
    "gn:asciiname":"Zhamatan",
    "gn:country_code":"CN",
    "gn:dem":2139,
    "gn:feature_class":"P",
    "gn:feature_code":"PPL",
    "gn:name":"Zhamatan",
    "gn:population":0,
    "gn:timezone":"Asia/Shanghai",
    "iso:country":"CN",
    "name:und_x_variant":[
        "\u624e\u9a6c\u6ee9"
    ],
    "wof:name":"Zhamatan",
    "wof:placetype":"locality"
},
  "geometry": {"coordinates":[104.36104,34.6951],"type":"Point"}
}