{
  "type": "Feature",
  "properties": {
    "gn:admin1_code":"11.0",
    "gn:asciiname":"Gantianjie",
    "gn:country_code":"CN",
    "gn:dem":320,
    "gn:feature_class":"P",
    "gn:feature_code":"PPL",
    "gn:name":"Gantianjie",
    "gn:population":0,
    "gn:timezone":"Asia/Shanghai",
    "iso:country":"CN",
    "name:zho_x_preferred":[
        "\u5e72\u7530\u754c"
    ],
    "wof:name":"Gantianjie",
    "wof:placetype":"locality"
},
  "geometry": {"coordinates":[110.94823,28.10005],"type":"Point"}
}