{
  "type": "Feature",
  "properties": {
    "gn:admin1_code":"29.0",
    "gn:asciiname":"Shanshuping",
    "gn:country_code":"CN",
    "gn:dem":956,
    "gn:feature_class":"P",
    "gn:feature_code":"PPL",
    "gn:name":"Shanshuping",
    "gn:population":0,
    "gn:timezone":"Asia/Shanghai",
    "iso:country":"CN",
    "name:und_x_variant":[
        "\u6749\u6811\u576a"
    ],
    "wof:name":"Shanshuping",
    "wof:placetype":"locality"
},
  "geometry": {"coordinates":[103.816,28.5623],"type":"Point"}
}