{
  "type": "Feature",
  "properties": {
    "gn:admin1_code":"4.0",
    "gn:asciiname":"Wangjiaxu",
    "gn:country_code":"CN",
    "gn:dem":4,
    "gn:feature_class":"P",
    "gn:feature_code":"PPL",
    "gn:name":"Wangjiaxu",
    "gn:population":0,
    "gn:timezone":"Asia/Shanghai",
    "iso:country":"CN",
    "name:zho_x_preferred":[
        "\u738b\u5bb6\u5729"
    ],
    "wof:name":"Wangjiaxu",
    "wof:placetype":"locality"
},
  "geometry": {"coordinates":[120.11897999999999,32.01121],"type":"Point"}
}