{
  "type": "Feature",
  "properties": {
    "gn:admin1_code":"3",
    "gn:asciiname":"Hangshan",
    "gn:country_code":"CN",
    "gn:dem":159,
    "gn:feature_class":"P",
    "gn:feature_code":"PPL",
    "gn:name":"Hangshan",
    "gn:population":0,
    "gn:timezone":"Asia/Shanghai",
    "iso:country":"CN",
    "name:und_x_variant":[
        "\u676d\u5c71"
    ],
    "wof:name":"Hangshan",
    "wof:placetype":"locality"
},
  "geometry": {"coordinates":[116.68895999999999,27.05893],"type":"Point"}
}