{
  "type": "Feature",
  "properties": {
    "gn:admin1_code":"29.0",
    "gn:asciiname":"Datuanshan",
    "gn:country_code":"CN",
    "gn:dem":1900,
    "gn:feature_class":"P",
    "gn:feature_code":"PPL",
    "gn:name":"Datuanshan",
    "gn:population":0,
    "gn:timezone":"Asia/Shanghai",
    "iso:country":"CN",
    "name:zho_x_preferred":[
        "\u5927\u56e2\u5c71"
    ],
    "wof:name":"Datuanshan",
    "wof:placetype":"locality"
},
  "geometry": {"coordinates":[102.65300000000001,25.0615],"type":"Point"}
}