{
  "type": "Feature",
  "properties": {
    "gn:admin1_code":"18.0",
    "gn:asciiname":"Sanchachong",
    "gn:country_code":"CN",
    "gn:dem":827,
    "gn:feature_class":"P",
    "gn:feature_code":"PPL",
    "gn:name":"Sanchachong",
    "gn:population":0,
    "gn:timezone":"Asia/Shanghai",
    "iso:country":"CN",
    "name:zho_x_preferred":[
        "\u4e09\u5c94\u51b2"
    ],
    "wof:name":"Sanchachong",
    "wof:placetype":"locality"
},
  "geometry": {"coordinates":[107.92400000000001,27.0687],"type":"Point"}
}