{
  "type": "Feature",
  "properties": {
    "gn:admin1_code":"12.0",
    "gn:asciiname":"Shangwangjiatai",
    "gn:country_code":"CN",
    "gn:dem":29,
    "gn:feature_class":"P",
    "gn:feature_code":"PPL",
    "gn:name":"Shangwangjiatai",
    "gn:population":0,
    "gn:timezone":"Asia/Shanghai",
    "iso:country":"CN",
    "name:zho_x_preferred":[
        "\u4e0a\u738b\u5bb6\u53f0"
    ],
    "wof:name":"Shangwangjiatai",
    "wof:placetype":"locality"
},
  "geometry": {"coordinates":[113.12211000000001,30.21272],"type":"Point"}
}