{
  "type": "Feature",
  "properties": {
    "gn:admin1_code":"24.0",
    "gn:asciiname":"Zuanmu",
    "gn:country_code":"CN",
    "gn:dem":1172,
    "gn:feature_class":"P",
    "gn:feature_code":"PPL",
    "gn:name":"Zuanmu",
    "gn:population":0,
    "gn:timezone":"Asia/Shanghai",
    "iso:country":"CN",
    "name:und_x_variant":[
        "Tsuan-mu",
        "Tso-shui",
        "Zuanmu"
    ],
    "name:zho_x_preferred":[
        "\u7e82\u6728"
    ],
    "wof:name":"Zuanmu",
    "wof:placetype":"locality"
},
  "geometry": {"coordinates":[112.99679,37.67029],"type":"Point"}
}