{
  "type": "Feature",
  "properties": {
    "gn:admin1_code":"15.0",
    "gn:asciiname":"Zhangshangtai",
    "gn:country_code":"CN",
    "gn:dem":1466,
    "gn:feature_class":"P",
    "gn:feature_code":"PPL",
    "gn:name":"Zhangshangtai",
    "gn:population":0,
    "gn:timezone":"Asia/Shanghai",
    "iso:country":"CN",
    "name:und_x_variant":[
        "\u5f20\u4e0a\u53f0"
    ],
    "wof:name":"Zhangshangtai",
    "wof:placetype":"locality"
},
  "geometry": {"coordinates":[107.02867000000001,36.31112],"type":"Point"}
}