{
  "type": "Feature",
  "properties": {
    "gn:admin1_code":"9",
    "gn:asciiname":"Luli",
    "gn:country_code":"CN",
    "gn:dem":56,
    "gn:feature_class":"P",
    "gn:feature_code":"PPL",
    "gn:name":"Luli",
    "gn:population":0,
    "gn:timezone":"Asia/Shanghai",
    "iso:country":"CN",
    "name:zho_x_preferred":[
        "\u82a6\u91cc"
    ],
    "wof:name":"Luli",
    "wof:placetype":"locality"
},
  "geometry": {"coordinates":[115.07899999999999,35.5606],"type":"Point"}
}