{
  "type": "Feature",
  "properties": {
    "gn:admin1_code":"3.0",
    "gn:asciiname":"Yanbei",
    "gn:country_code":"CN",
    "gn:dem":97,
    "gn:feature_class":"P",
    "gn:feature_code":"PPL",
    "gn:name":"Yanbei",
    "gn:population":0,
    "gn:timezone":"Asia/Shanghai",
    "iso:country":"CN",
    "name:und_x_variant":[
        "\u7814\u9642"
    ],
    "wof:name":"Yanbei",
    "wof:placetype":"locality"
},
  "geometry": {"coordinates":[114.45626,28.19311],"type":"Point"}
}