{
  "type": "Feature",
  "properties": {
    "gn:admin1_code":"15.0",
    "gn:asciiname":"Manshuitan Sandui",
    "gn:country_code":"CN",
    "gn:dem":1397,
    "gn:feature_class":"P",
    "gn:feature_code":"PPLF",
    "gn:name":"Manshuitan Sandui",
    "gn:population":0,
    "gn:timezone":"Asia/Shanghai",
    "iso:country":"CN",
    "name:zho_x_preferred":[
        "\u6f2b\u6c34\u6ee9\u4e09\u961f"
    ],
    "wof:name":"Manshuitan Sandui",
    "wof:placetype":"locality"
},
  "geometry": {"coordinates":[98.8004,39.6699],"type":"Point"}
}