{
  "type": "Feature",
  "properties": {
    "gn:admin1_code":"12.0",
    "gn:asciiname":"Budai",
    "gn:country_code":"CN",
    "gn:dem":680,
    "gn:feature_class":"P",
    "gn:feature_code":"PPL",
    "gn:name":"Budai",
    "gn:population":0,
    "gn:timezone":"Asia/Shanghai",
    "iso:country":"CN",
    "name:zho_x_preferred":[
        "Budai"
    ],
    "name:zho_x_variant":[
        "\u5e03\u888b"
    ],
    "wof:name":"Budai",
    "wof:placetype":"locality"
},
  "geometry": {"coordinates":[109.64518,29.71237],"type":"Point"}
}