{
  "type": "Feature",
  "properties": {
    "gn:admin1_code":"12.0",
    "gn:asciiname":"Budai",
    "gn:country_code":"CN",
    "gn:dem":680,
    "gn:feature_class":"P",
    "gn:feature_code":"PPL",
    "gn:name":"Budai",
    "gn:population":0,
    "gn:timezone":"Asia/Shanghai",
    "iso:country":"CN",
    "name:asm_x_preferred":[
        "\u09ac\u09c1\u09a6\u09be\u0987"
    ],
    "name:ast_x_preferred":[
        "Hotei"
    ],
    "name:ben_x_preferred":[
        "\u09ac\u09c1\u09a6\u09be\u0987"
    ],
    "name:bre_x_preferred":[
        "Hotei"
    ],
    "name:ces_x_preferred":[
        "Hotei"
    ],
    "name:deu_x_preferred":[
        "Budai"
    ],
    "name:fas_x_preferred":[
        "\u0628\u0648\u062f\u0627\u06cc"
    ],
    "name:fin_x_preferred":[
        "Budai"
    ],
    "name:fra_x_preferred":[
        "Budai"
    ],
    "name:glg_x_preferred":[
        "Hotei"
    ],
    "name:heb_x_preferred":[
        "\u05d1\u05d5\u05d3\u05d0\u05d9"
    ],
    "name:hun_x_preferred":[
        "Pu-taj"
    ],
    "name:ind_x_preferred":[
        "Budai"
    ],
    "name:ita_x_preferred":[
        "Budai"
    ],
    "name:mal_x_preferred":[
        "\u0d2c\u0d41\u0d26\u0d3e\u0d2f\u0d4d"
    ],
    "name:nor_x_preferred":[
        "Budai"
    ],
    "name:pan_x_preferred":[
        "\u0a2c\u0a42\u0a26\u0a3e\u0a08"
    ],
    "name:ron_x_preferred":[
        "Budai"
    ],
    "name:rus_x_preferred":[
        "\u0425\u043e\u0442\u044d\u0439"
    ],
    "name:spa_x_preferred":[
        "Hotei"
    ],
    "name:srp_x_preferred":[
        "\u0411\u0443\u0434\u0430\u0438"
    ],
    "name:swe_x_preferred":[
        "Budai"
    ],
    "name:tur_x_preferred":[
        "G\u00fclen Buda"
    ],
    "name:vie_x_preferred":[
        "B\u1ed1 \u0110\u1ea1i"
    ],
    "name:zho_x_preferred":[
        "Budai"
    ],
    "name:zho_x_variant":[
        "\u5e03\u888b",
        "\u5e03\u888b\u548c\u5c1a"
    ],
    "wof:name":"Budai",
    "wof:placetype":"locality"
},
  "geometry": {"coordinates":[109.64518,29.71237],"type":"Point"}
}