{
  "type": "Feature",
  "properties": {
    "gn:admin1_code":"1.0",
    "gn:asciiname":"Kuandiancun",
    "gn:country_code":"CN",
    "gn:dem":55,
    "gn:feature_class":"P",
    "gn:feature_code":"PPL",
    "gn:name":"Kuandiancun",
    "gn:population":0,
    "gn:timezone":"Asia/Shanghai",
    "iso:country":"CN",
    "name:zho_x_preferred":[
        "\u5bbd\u5e97\u6751"
    ],
    "wof:name":"Kuandiancun",
    "wof:placetype":"locality"
},
  "geometry": {"coordinates":[116.03883,32.28962],"type":"Point"}
}