{
  "type": "Feature",
  "properties": {
    "gn:admin1_code":"14.0",
    "gn:asciiname":"Baleqiecun",
    "gn:country_code":"CN",
    "gn:dem":4916,
    "gn:feature_class":"P",
    "gn:feature_code":"PPL",
    "gn:name":"Baleqiecun",
    "gn:population":0,
    "gn:timezone":"Asia/Urumqi",
    "iso:country":"CN",
    "name:zho_x_preferred":[
        "\u5df4\u52d2\u5207\u6751"
    ],
    "wof:name":"Baleqiecun",
    "wof:placetype":"locality"
},
  "geometry": {"coordinates":[91.81417999999999,32.43916],"type":"Point"}
}