{
  "type": "Feature",
  "properties": {
    "gn:admin1_code":"19.0",
    "gn:asciiname":"Wendaocun",
    "gn:country_code":"CN",
    "gn:dem":143,
    "gn:feature_class":"P",
    "gn:feature_code":"PPL",
    "gn:name":"Wendaocun",
    "gn:population":0,
    "gn:timezone":"Asia/Shanghai",
    "iso:country":"CN",
    "name:zho_x_preferred":[
        "\u6e29\u9053\u6751"
    ],
    "wof:name":"Wendaocun",
    "wof:placetype":"locality"
},
  "geometry": {"coordinates":[124.14100000000001,41.7716],"type":"Point"}
}