{
  "type": "Feature",
  "properties": {
    "gn:admin1_code":"12.0",
    "gn:asciiname":"Huangtiangou",
    "gn:country_code":"CN",
    "gn:dem":413,
    "gn:feature_class":"P",
    "gn:feature_code":"PPL",
    "gn:name":"Huangtiangou",
    "gn:population":0,
    "gn:timezone":"Asia/Shanghai",
    "iso:country":"CN",
    "name:zho_x_preferred":[
        "\u8352\u7530\u6c9f"
    ],
    "wof:name":"Huangtiangou",
    "wof:placetype":"locality"
},
  "geometry": {"coordinates":[114.27799,31.73056],"type":"Point"}
}