{
  "type": "Feature",
  "properties": {
    "gn:admin1_code":"29",
    "gn:asciiname":"Wunaoshan",
    "gn:country_code":"CN",
    "gn:dem":2218,
    "gn:feature_class":"P",
    "gn:feature_code":"PPL",
    "gn:name":"Wunaoshan",
    "gn:population":0,
    "gn:timezone":"Asia/Shanghai",
    "iso:country":"CN",
    "name:zho_x_preferred":[
        "\u4e94\u8111\u5c71"
    ],
    "wof:name":"Wunaoshan",
    "wof:placetype":"locality"
},
  "geometry": {"coordinates":[102.872,24.1215],"type":"Point"}
}