{
  "type": "Feature",
  "properties": {
    "gn:admin1_code":"30.0",
    "gn:asciiname":"Longwan",
    "gn:country_code":"CN",
    "gn:dem":26,
    "gn:feature_class":"P",
    "gn:feature_code":"PPL",
    "gn:name":"Longwan",
    "gn:population":0,
    "gn:timezone":"Asia/Shanghai",
    "iso:country":"CN",
    "name:zho_x_preferred":[
        "\u9f8d\u7063"
    ],
    "wof:name":"Longwan",
    "wof:placetype":"locality"
},
  "geometry": {"coordinates":[112.38594000000001,22.35392],"type":"Point"}
}