{
  "type": "Feature",
  "properties": {
    "gn:admin1_code":"26.0",
    "gn:asciiname":"Baitugou",
    "gn:country_code":"CN",
    "gn:dem":1355,
    "gn:feature_class":"P",
    "gn:feature_code":"PPL",
    "gn:name":"Baitugou",
    "gn:population":0,
    "gn:timezone":"Asia/Shanghai",
    "iso:country":"CN",
    "name:zho_x_preferred":[
        "\u767d\u571f\u6c9f"
    ],
    "wof:name":"Baitugou",
    "wof:placetype":"locality"
},
  "geometry": {"coordinates":[108.15201999999999,36.89064000000001],"type":"Point"}
}