{
  "type": "Feature",
  "properties": {
    "gn:admin1_code":"11.0",
    "gn:asciiname":"Yanziwo",
    "gn:country_code":"CN",
    "gn:dem":31,
    "gn:feature_class":"P",
    "gn:feature_code":"PPL",
    "gn:name":"Yanziwo",
    "gn:population":0,
    "gn:timezone":"Asia/Shanghai",
    "iso:country":"CN",
    "name:zho_x_preferred":[
        "\u71d5\u5b50\u7a9d"
    ],
    "wof:name":"Yanziwo",
    "wof:placetype":"locality"
},
  "geometry": {"coordinates":[112.48336999999999,29.60994],"type":"Point"}
}