{
  "type": "Feature",
  "properties": {
    "gn:admin1_code":"19.0",
    "gn:asciiname":"Luoquan Gouwai",
    "gn:country_code":"CN",
    "gn:dem":112,
    "gn:feature_class":"P",
    "gn:feature_code":"PPL",
    "gn:name":"Luoquan Gouwai",
    "gn:population":0,
    "gn:timezone":"Asia/Shanghai",
    "iso:country":"CN",
    "name:und_x_variant":[
        "\u7f57\u5708\u6c9f\u5916"
    ],
    "wof:name":"Luoquan Gouwai",
    "wof:placetype":"locality"
},
  "geometry": {"coordinates":[123.47615,40.3726],"type":"Point"}
}