{
  "type": "Feature",
  "properties": {
    "gn:admin1_code":"19.0",
    "gn:asciiname":"Chentai",
    "gn:country_code":"CN",
    "gn:dem":33,
    "gn:feature_class":"P",
    "gn:feature_code":"PPL",
    "gn:name":"Chentai",
    "gn:population":0,
    "gn:timezone":"Asia/Shanghai",
    "iso:country":"CN",
    "name:zho_x_preferred":[
        "\u9648\u53f0"
    ],
    "wof:name":"Chentai",
    "wof:placetype":"locality"
},
  "geometry": {"coordinates":[123.09581,41.93904000000001],"type":"Point"}
}