{
  "type": "Feature",
  "properties": {
    "gn:admin1_code":"14.0",
    "gn:asciiname":"Luogelang",
    "gn:country_code":"CN",
    "gn:dem":4521,
    "gn:feature_class":"P",
    "gn:feature_code":"PPL",
    "gn:name":"Luogelang",
    "gn:population":0,
    "gn:timezone":"Asia/Urumqi",
    "iso:country":"CN",
    "name:zho_x_preferred":[
        "\u6d1b\u4e2a\u6717"
    ],
    "wof:name":"Luogelang",
    "wof:placetype":"locality"
},
  "geometry": {"coordinates":[91.95847999999999,31.45436],"type":"Point"}
}