{
  "type": "Feature",
  "properties": {
    "gn:admin1_code":"7",
    "gn:asciiname":"Zhuhengshan",
    "gn:country_code":"CN",
    "gn:dem":7,
    "gn:feature_class":"P",
    "gn:feature_code":"PPL",
    "gn:name":"Zhuhengshan",
    "gn:population":0,
    "gn:timezone":"Asia/Shanghai",
    "iso:country":"CN",
    "name:und_x_variant":[
        "\u7af9\u6841\u5c71"
    ],
    "name:zho_x_preferred":[
        "\u7af9\u6841\u5c71"
    ],
    "wof:name":"Zhuhengshan",
    "wof:placetype":"locality"
},
  "geometry": {"coordinates":[117.27417,23.63917],"type":"Point"}
}