{
  "type": "Feature",
  "properties": {
    "gn:admin1_code":"30.0",
    "gn:asciiname":"Tangtouxia",
    "gn:country_code":"CN",
    "gn:dem":120,
    "gn:feature_class":"P",
    "gn:feature_code":"PPL",
    "gn:name":"Tangtouxia",
    "gn:population":0,
    "gn:timezone":"Asia/Shanghai",
    "iso:country":"CN",
    "name:zho_x_preferred":[
        "\u5858\u5934\u4e0b"
    ],
    "wof:name":"Tangtouxia",
    "wof:placetype":"locality"
},
  "geometry": {"coordinates":[115.89798999999999,24.03291],"type":"Point"}
}