{
  "type": "Feature",
  "properties": {
    "gn:admin1_code":"4.0",
    "gn:asciiname":"Guanjingcun",
    "gn:country_code":"CN",
    "gn:dem":5,
    "gn:feature_class":"P",
    "gn:feature_code":"PPL",
    "gn:name":"Guanjingcun",
    "gn:population":0,
    "gn:timezone":"Asia/Shanghai",
    "iso:country":"CN",
    "name:zho_x_preferred":[
        "\u5b98\u6cfe\u6751"
    ],
    "wof:name":"Guanjingcun",
    "wof:placetype":"locality"
},
  "geometry": {"coordinates":[120.28557000000001,31.74219],"type":"Point"}
}