{
  "type": "Feature",
  "properties": {
    "gn:admin1_code":"9.0",
    "gn:asciiname":"Xixiacao",
    "gn:country_code":"CN",
    "gn:dem":168,
    "gn:feature_class":"P",
    "gn:feature_code":"PPL",
    "gn:name":"Xixiacao",
    "gn:population":0,
    "gn:timezone":"Asia/Shanghai",
    "iso:country":"CN",
    "name:zho_x_preferred":[
        "\u897f\u4e0b\u66f9"
    ],
    "wof:name":"Xixiacao",
    "wof:placetype":"locality"
},
  "geometry": {"coordinates":[113.48926000000002,33.0883],"type":"Point"}
}