{
  "type": "Feature",
  "properties": {
    "gn:admin1_code":"25.0",
    "gn:asciiname":"Houdianzicun",
    "gn:country_code":"CN",
    "gn:dem":128,
    "gn:feature_class":"P",
    "gn:feature_code":"PPL",
    "gn:name":"Houdianzicun",
    "gn:population":0,
    "gn:timezone":"Asia/Shanghai",
    "iso:country":"CN",
    "name:zho_x_preferred":[
        "\u540e\u5e97\u5b50\u6751"
    ],
    "wof:name":"Houdianzicun",
    "wof:placetype":"locality"
},
  "geometry": {"coordinates":[120.02104,37.14086],"type":"Point"}
}