{
  "type": "Feature",
  "properties": {
    "gn:admin1_code":"10",
    "gn:asciiname":"Xiaoliaodong",
    "gn:country_code":"CN",
    "gn:dem":393,
    "gn:feature_class":"P",
    "gn:feature_code":"PPL",
    "gn:name":"Xiaoliaodong",
    "gn:population":0,
    "gn:timezone":"Asia/Shanghai",
    "iso:country":"CN",
    "name:zho_x_preferred":[
        "\u5c0f\u8fbd\u4e1c"
    ],
    "wof:name":"Xiaoliaodong",
    "wof:placetype":"locality"
},
  "geometry": {"coordinates":[117.02336,40.94384],"type":"Point"}
}