{
  "type": "Feature",
  "properties": {
    "gn:admin1_code":"9",
    "gn:asciiname":"Qianbanqiao",
    "gn:country_code":"CN",
    "gn:dem":37,
    "gn:feature_class":"P",
    "gn:feature_code":"PPL",
    "gn:name":"Qianbanqiao",
    "gn:population":0,
    "gn:timezone":"Asia/Shanghai",
    "iso:country":"CN",
    "name:zho_x_preferred":[
        "\u524d\u677f\u6865"
    ],
    "wof:name":"Qianbanqiao",
    "wof:placetype":"locality"
},
  "geometry": {"coordinates":[116.23999999999999,34.0744],"type":"Point"}
}