{
  "type": "Feature",
  "properties": {
    "gn:admin1_code":"21.0",
    "gn:asciiname":"Linjiagou",
    "gn:country_code":"CN",
    "gn:dem":1996,
    "gn:feature_class":"P",
    "gn:feature_code":"PPL",
    "gn:name":"Linjiagou",
    "gn:population":0,
    "gn:timezone":"Asia/Shanghai",
    "iso:country":"CN",
    "name:und_x_variant":[
        "\u6797\u5bb6\u6c9f"
    ],
    "name:zho_x_preferred":[
        "\u6797\u5bb6\u6c9f"
    ],
    "wof:name":"Linjiagou",
    "wof:placetype":"locality"
},
  "geometry": {"coordinates":[105.76813,35.8768],"type":"Point"}
}