{
  "type": "Feature",
  "properties": {
    "gn:admin1_code":"2.0",
    "gn:asciiname":"Shangongxu",
    "gn:country_code":"CN",
    "gn:dem":149,
    "gn:feature_class":"P",
    "gn:feature_code":"PPL",
    "gn:name":"Shangongxu",
    "gn:population":0,
    "gn:timezone":"Asia/Shanghai",
    "iso:country":"CN",
    "name:zho_x_preferred":[
        "\u5c71\u516c\u5729"
    ],
    "wof:name":"Shangongxu",
    "wof:placetype":"locality"
},
  "geometry": {"coordinates":[118.86563999999998,28.8015],"type":"Point"}
}