{
  "type": "Feature",
  "properties": {
    "gn:admin1_code":"4.0",
    "gn:asciiname":"Faqing",
    "gn:country_code":"CN",
    "gn:dem":2,
    "gn:feature_class":"P",
    "gn:feature_code":"PPL",
    "gn:name":"Faqing",
    "gn:population":0,
    "gn:timezone":"Asia/Shanghai",
    "iso:country":"CN",
    "name:zho_x_preferred":[
        "Faqing"
    ],
    "name:zho_x_variant":[
        "\u6cd5\u6e05"
    ],
    "wof:name":"Faqing",
    "wof:placetype":"locality"
},
  "geometry": {"coordinates":[119.65105,33.07526],"type":"Point"}
}