{
  "type": "Feature",
  "properties": {
    "gn:admin1_code":"29.0",
    "gn:asciiname":"Chichangping",
    "gn:country_code":"CN",
    "gn:dem":2060,
    "gn:feature_class":"P",
    "gn:feature_code":"PPL",
    "gn:name":"Chichangping",
    "gn:population":0,
    "gn:timezone":"Asia/Shanghai",
    "iso:country":"CN",
    "name:zho_x_preferred":[
        "\u6c60\u573a\u576a"
    ],
    "wof:name":"Chichangping",
    "wof:placetype":"locality"
},
  "geometry": {"coordinates":[99.39060000000001,26.2284],"type":"Point"}
}