{
  "type": "Feature",
  "properties": {
    "gn:admin1_code":"4.0",
    "gn:asciiname":"Zhuchencun",
    "gn:country_code":"CN",
    "gn:dem":13,
    "gn:feature_class":"P",
    "gn:feature_code":"PPL",
    "gn:name":"Zhuchencun",
    "gn:population":0,
    "gn:timezone":"Asia/Shanghai",
    "iso:country":"CN",
    "name:zho_x_preferred":[
        "\u6731\u9648\u6751"
    ],
    "wof:name":"Zhuchencun",
    "wof:placetype":"locality"
},
  "geometry": {"coordinates":[119.44268999999998,33.69629],"type":"Point"}
}