{
  "type": "Feature",
  "properties": {
    "gn:admin1_code":"26.0",
    "gn:asciiname":"Liutikou",
    "gn:country_code":"CN",
    "gn:dem":1133,
    "gn:feature_class":"P",
    "gn:feature_code":"PPL",
    "gn:name":"Liutikou",
    "gn:population":0,
    "gn:timezone":"Asia/Shanghai",
    "iso:country":"CN",
    "name:zho_x_preferred":[
        "\u7559\u9898\u53e3"
    ],
    "wof:name":"Liutikou",
    "wof:placetype":"locality"
},
  "geometry": {"coordinates":[110.14681000000002,34.24432],"type":"Point"}
}