{
  "type": "Feature",
  "properties": {
    "gn:admin1_code":"9.0",
    "gn:asciiname":"Zhongtang",
    "gn:country_code":"CN",
    "gn:dem":249,
    "gn:feature_class":"P",
    "gn:feature_code":"PPL",
    "gn:name":"Zhongtang",
    "gn:population":0,
    "gn:timezone":"Asia/Shanghai",
    "iso:country":"CN",
    "name:sco_x_preferred":[
        "Zhongtang"
    ],
    "name:zho_x_preferred":[
        "\u4e2d\u6c64"
    ],
    "wof:name":"Zhongtang",
    "wof:placetype":"locality"
},
  "geometry": {"coordinates":[112.56784,33.74834],"type":"Point"}
}