{
  "type": "Feature",
  "properties": {
    "gn:admin1_code":"29.0",
    "gn:asciiname":"Shabacun",
    "gn:country_code":"CN",
    "gn:dem":1679,
    "gn:feature_class":"P",
    "gn:feature_code":"PPL",
    "gn:name":"Shabacun",
    "gn:population":0,
    "gn:timezone":"Asia/Shanghai",
    "iso:country":"CN",
    "name:zho_x_preferred":[
        "\u6c99\u575d\u6751"
    ],
    "wof:name":"Shabacun",
    "wof:placetype":"locality"
},
  "geometry": {"coordinates":[103.42100000000001,27.1198],"type":"Point"}
}