{
  "type": "Feature",
  "properties": {
    "gn:admin1_code":"6.0",
    "gn:asciiname":"Shangcaitang",
    "gn:country_code":"CN",
    "gn:dem":2360,
    "gn:feature_class":"P",
    "gn:feature_code":"PPL",
    "gn:name":"Shangcaitang",
    "gn:population":0,
    "gn:timezone":"Asia/Shanghai",
    "iso:country":"CN",
    "name:zho_x_preferred":[
        "\u4e0a\u624d\u5802"
    ],
    "wof:name":"Shangcaitang",
    "wof:placetype":"locality"
},
  "geometry": {"coordinates":[101.41575,35.95408],"type":"Point"}
}