{
  "type": "Feature",
  "properties": {
    "gn:admin1_code":"02",
    "gn:asciiname":"Xianmeihu Nongchang",
    "gn:country_code":"CN",
    "gn:dem":9,
    "gn:feature_class":"P",
    "gn:feature_code":"PPLF",
    "gn:name":"Xianmeihu Nongchang",
    "gn:population":0,
    "gn:timezone":"Asia/Shanghai",
    "iso:country":"CN",
    "name:und_x_variant":[
        "Mei-hu",
        "Xianmeihu Nongchang"
    ],
    "wof:name":"Xianmeihu Nongchang",
    "wof:placetype":"locality"
},
  "geometry": {"coordinates":[121.67583,29.80833],"type":"Point"}
}