{
  "type": "Feature",
  "properties": {
    "gn:admin1_code":"32.0",
    "gn:asciiname":"Denglongshi",
    "gn:country_code":"CN",
    "gn:dem":559,
    "gn:feature_class":"P",
    "gn:feature_code":"PPL",
    "gn:name":"Denglongshi",
    "gn:population":0,
    "gn:timezone":"Asia/Shanghai",
    "iso:country":"CN",
    "name:zho_x_preferred":[
        "\u706f\u7b3c\u77f3"
    ],
    "wof:name":"Denglongshi",
    "wof:placetype":"locality"
},
  "geometry": {"coordinates":[104.34,29.70652],"type":"Point"}
}