{
  "type": "Feature",
  "properties": {
    "gn:admin1_code":"19.0",
    "gn:asciiname":"Zhengtuncun",
    "gn:country_code":"CN",
    "gn:dem":9,
    "gn:feature_class":"P",
    "gn:feature_code":"PPL",
    "gn:name":"Zhengtuncun",
    "gn:population":0,
    "gn:timezone":"Asia/Shanghai",
    "iso:country":"CN",
    "name:zho_x_preferred":[
        "\u90d1\u5c6f\u6751"
    ],
    "wof:name":"Zhengtuncun",
    "wof:placetype":"locality"
},
  "geometry": {"coordinates":[122.2544,40.38375],"type":"Point"}
}