{
  "type": "Feature",
  "properties": {
    "gn:admin1_code":"25",
    "gn:asciiname":"Zhaoxiangfang",
    "gn:country_code":"CN",
    "gn:dem":37,
    "gn:feature_class":"P",
    "gn:feature_code":"PPL",
    "gn:name":"Zhaoxiangfang",
    "gn:population":0,
    "gn:timezone":"Asia/Shanghai",
    "iso:country":"CN",
    "name:zho_x_preferred":[
        "\u8d75\u9999\u574a"
    ],
    "wof:name":"Zhaoxiangfang",
    "wof:placetype":"locality"
},
  "geometry": {"coordinates":[115.82998000000001,36.60212],"type":"Point"}
}