{
  "type": "Feature",
  "properties": {
    "gn:admin1_code":"19.0",
    "gn:asciiname":"Yao'aohan Wobu",
    "gn:country_code":"CN",
    "gn:dem":163,
    "gn:feature_class":"P",
    "gn:feature_code":"PPL",
    "gn:name":"Yao\u2019aohan Wobu",
    "gn:population":0,
    "gn:timezone":"Asia/Shanghai",
    "iso:country":"CN",
    "name:und_x_variant":[
        "Yao\u2019aohan Wobu"
    ],
    "name:zho_x_preferred":[
        "Yao\u2019aohanwobao"
    ],
    "name:zho_x_variant":[
        "\u8170\u6556\u6c49\u7a9d\u5821"
    ],
    "wof:name":"Yao'aohan Wobu",
    "wof:placetype":"locality"
},
  "geometry": {"coordinates":[122.09027,42.47407000000001],"type":"Point"}
}