{
  "type": "Feature",
  "properties": {
    "gn:admin1_code":"01",
    "gn:asciiname":"Tangqiaocun",
    "gn:country_code":"CN",
    "gn:dem":21,
    "gn:feature_class":"P",
    "gn:feature_code":"PPL",
    "gn:name":"Tangqiaocun",
    "gn:population":0,
    "gn:timezone":"Asia/Shanghai",
    "iso:country":"CN",
    "name:und_x_variant":[
        "T\u2019ang-ch\u2019iao",
        "Tangqiao",
        "Tangqiaocun"
    ],
    "name:zho_x_preferred":[
        "\u6c64\u6865\u6751"
    ],
    "wof:name":"Tangqiaocun",
    "wof:placetype":"locality"
},
  "geometry": {"coordinates":[119.25293000000001,31.2019],"type":"Point"}
}