{
  "type": "Feature",
  "properties": {
    "gn:admin1_code":"24.0",
    "gn:asciiname":"Yongjingcheng",
    "gn:country_code":"CN",
    "gn:dem":1060,
    "gn:feature_class":"P",
    "gn:feature_code":"PPL",
    "gn:name":"Yongjingcheng",
    "gn:population":0,
    "gn:timezone":"Asia/Shanghai",
    "iso:country":"CN",
    "name:zho_x_preferred":[
        "\u6c38\u9759\u57ce"
    ],
    "wof:name":"Yongjingcheng",
    "wof:placetype":"locality"
},
  "geometry": {"coordinates":[112.80758,39.6267],"type":"Point"}
}