{
  "type": "Feature",
  "properties": {
    "gn:admin1_code":"33.0",
    "gn:asciiname":"Xishanping",
    "gn:country_code":"CN",
    "gn:dem":601,
    "gn:feature_class":"P",
    "gn:feature_code":"PPL",
    "gn:name":"Xishanping",
    "gn:population":0,
    "gn:timezone":"Asia/Shanghai",
    "iso:country":"CN",
    "name:zho_x_preferred":[
        "\u897f\u5c71\u576a"
    ],
    "wof:name":"Xishanping",
    "wof:placetype":"locality"
},
  "geometry": {"coordinates":[109.05422,28.91735],"type":"Point"}
}