{
  "type": "Feature",
  "properties": {
    "gn:admin1_code":"18",
    "gn:asciiname":"Xihuaxi",
    "gn:country_code":"CN",
    "gn:dem":528,
    "gn:feature_class":"P",
    "gn:feature_code":"PPL",
    "gn:name":"Xihuaxi",
    "gn:population":0,
    "gn:timezone":"Asia/Shanghai",
    "iso:country":"CN",
    "name:zho_x_preferred":[
        "\u6d17\u534e\u6eaa"
    ],
    "wof:name":"Xihuaxi",
    "wof:placetype":"locality"
},
  "geometry": {"coordinates":[108.188,28.3859],"type":"Point"}
}