{
  "type": "Feature",
  "properties": {
    "gn:admin1_code":"21.0",
    "gn:asciiname":"Miaozui",
    "gn:country_code":"CN",
    "gn:dem":1967,
    "gn:feature_class":"P",
    "gn:feature_code":"PPL",
    "gn:name":"Miaozui",
    "gn:population":0,
    "gn:timezone":"Asia/Shanghai",
    "iso:country":"CN",
    "name:zho_x_preferred":[
        "\u5e99\u5480"
    ],
    "wof:name":"Miaozui",
    "wof:placetype":"locality"
},
  "geometry": {"coordinates":[105.52397000000001,35.78095],"type":"Point"}
}