{
  "type": "Feature",
  "properties": {
    "gn:admin1_code":"16.0",
    "gn:asciiname":"Jiahe",
    "gn:country_code":"CN",
    "gn:dem":482,
    "gn:feature_class":"P",
    "gn:feature_code":"PPL",
    "gn:name":"Jiahe",
    "gn:population":0,
    "gn:timezone":"Asia/Shanghai",
    "iso:country":"CN",
    "name:zho_x_preferred":[
        "\u52a0\u79be"
    ],
    "wof:name":"Jiahe",
    "wof:placetype":"locality"
},
  "geometry": {"coordinates":[108.212,23.9928],"type":"Point"}
}