{
  "type": "Feature",
  "properties": {
    "gn:admin1_code":"7",
    "gn:asciiname":"Anjing",
    "gn:country_code":"CN",
    "gn:dem":91,
    "gn:feature_class":"P",
    "gn:feature_code":"PPL",
    "gn:name":"Anjing",
    "gn:population":0,
    "gn:timezone":"Asia/Shanghai",
    "iso:country":"CN",
    "name:zho_x_preferred":[
        "\u6697\u5f84"
    ],
    "wof:name":"Anjing",
    "wof:placetype":"locality"
},
  "geometry": {"coordinates":[117.23083,24.09694],"type":"Point"}
}