{
  "type": "Feature",
  "properties": {
    "gn:admin1_code":"30",
    "gn:asciiname":"Bopu",
    "gn:country_code":"CN",
    "gn:dem":11,
    "gn:feature_class":"P",
    "gn:feature_code":"PPLA4",
    "gn:name":"Bopu",
    "gn:population":0,
    "gn:timezone":"Asia/Urumqi",
    "iso:country":"CN",
    "name:und_x_variant":[
        "Bopu Jiedao",
        "\u535a\u94fa\u8857\u9053"
    ],
    "name:zho_x_preferred":[
        "\u535a\u94fa"
    ],
    "wof:name":"Bopu",
    "wof:placetype":"locality"
},
  "geometry": {"coordinates":[110.7941,21.44896],"type":"Point"}
}