{
  "type": "Feature",
  "properties": {
    "gn:admin1_code":"32.0",
    "gn:asciiname":"Shimen",
    "gn:country_code":"CN",
    "gn:dem":883,
    "gn:feature_class":"P",
    "gn:feature_code":"PPL",
    "gn:name":"Shimen",
    "gn:population":0,
    "gn:timezone":"Asia/Shanghai",
    "iso:country":"CN",
    "name:ceb_x_preferred":[
        "Shimen"
    ],
    "name:deu_x_preferred":[
        "Shimen"
    ],
    "name:nor_x_preferred":[
        "Shimen"
    ],
    "name:zho_x_preferred":[
        "\u77f3\u95e8"
    ],
    "wof:name":"Shimen",
    "wof:placetype":"locality"
},
  "geometry": {"coordinates":[107.812,31.4922],"type":"Point"}
}