{
  "type": "Feature",
  "properties": {
    "gn:admin1_code":"12.0",
    "gn:asciiname":"Longjiayuan",
    "gn:country_code":"CN",
    "gn:dem":886,
    "gn:feature_class":"P",
    "gn:feature_code":"PPL",
    "gn:name":"Longjiayuan",
    "gn:population":0,
    "gn:timezone":"Asia/Shanghai",
    "iso:country":"CN",
    "name:zho_x_preferred":[
        "\u9f99\u5bb6\u9662"
    ],
    "wof:name":"Longjiayuan",
    "wof:placetype":"locality"
},
  "geometry": {"coordinates":[109.06617,29.87861],"type":"Point"}
}