{
  "type": "Feature",
  "properties": {
    "gn:admin1_code":"18",
    "gn:asciiname":"Changfeng",
    "gn:country_code":"CN",
    "gn:dem":653,
    "gn:feature_class":"P",
    "gn:feature_code":"PPLA4",
    "gn:name":"Changfeng",
    "gn:population":0,
    "gn:timezone":"Asia/Shanghai",
    "iso:country":"CN",
    "name:fra_x_preferred":[
        "Changfeng"
    ],
    "name:pol_x_preferred":[
        "Changfeng"
    ],
    "name:und_x_variant":[
        "Changfeng Tujiazu Xiang"
    ],
    "name:zho_x_preferred":[
        "\u957f\u4e30"
    ],
    "name:zho_x_variant":[
        "\u957f\u4e30\u571f\u5bb6\u65cf\u4e61"
    ],
    "wof:name":"Changfeng",
    "wof:placetype":"locality"
},
  "geometry": {"coordinates":[108.08328,28.42164],"type":"Point"}
}