{
  "type": "Feature",
  "properties": {
    "gn:admin1_code":"1.0",
    "gn:asciiname":"Wangyuecun",
    "gn:country_code":"CN",
    "gn:dem":28,
    "gn:feature_class":"P",
    "gn:feature_code":"PPL",
    "gn:name":"Wangyuecun",
    "gn:population":0,
    "gn:timezone":"Asia/Shanghai",
    "iso:country":"CN",
    "name:zho_x_preferred":[
        "\u671b\u6708\u6751"
    ],
    "wof:name":"Wangyuecun",
    "wof:placetype":"locality"
},
  "geometry": {"coordinates":[116.54161000000001,33.25162],"type":"Point"}
}