{
  "type": "Feature",
  "properties": {
    "gn:admin1_code":"15.0",
    "gn:asciiname":"Dongzhuang",
    "gn:country_code":"CN",
    "gn:dem":1823,
    "gn:feature_class":"P",
    "gn:feature_code":"PPL",
    "gn:name":"Dongzhuang",
    "gn:population":0,
    "gn:timezone":"Asia/Shanghai",
    "iso:country":"CN",
    "name:zho_x_preferred":[
        "\u4e1c\u5e84"
    ],
    "wof:name":"Dongzhuang",
    "wof:placetype":"locality"
},
  "geometry": {"coordinates":[106.453,35.6993],"type":"Point"}
}