{
  "type": "Feature",
  "properties": {
    "gn:admin1_code":"32.0",
    "gn:asciiname":"Xijiao Hegou",
    "gn:country_code":"CN",
    "gn:dem":2302,
    "gn:feature_class":"P",
    "gn:feature_code":"PPL",
    "gn:name":"Xijiao Hegou",
    "gn:population":0,
    "gn:timezone":"Asia/Shanghai",
    "iso:country":"CN",
    "name:zho_x_preferred":[
        "\u6d17\u811a\u6cb3\u6c9f"
    ],
    "wof:name":"Xijiao Hegou",
    "wof:placetype":"locality"
},
  "geometry": {"coordinates":[102.508,28.3008],"type":"Point"}
}