{
  "type": "Feature",
  "properties": {
    "gn:admin1_code":"18",
    "gn:asciiname":"Shanglihuping",
    "gn:country_code":"CN",
    "gn:dem":484,
    "gn:feature_class":"P",
    "gn:feature_code":"PPL",
    "gn:name":"Shanglihuping",
    "gn:population":0,
    "gn:timezone":"Asia/Shanghai",
    "iso:country":"CN",
    "name:zho_x_preferred":[
        "\u4e0a\u91cc\u6237\u576a"
    ],
    "wof:name":"Shanglihuping",
    "wof:placetype":"locality"
},
  "geometry": {"coordinates":[108.39400000000001,28.4017],"type":"Point"}
}