{
  "type": "Feature",
  "properties": {
    "gn:admin1_code":"11.0",
    "gn:asciiname":"Mayuanzhou",
    "gn:country_code":"CN",
    "gn:dem":75,
    "gn:feature_class":"P",
    "gn:feature_code":"PPL",
    "gn:name":"Mayuanzhou",
    "gn:population":0,
    "gn:timezone":"Asia/Shanghai",
    "iso:country":"CN",
    "name:zho_x_preferred":[
        "\u9ebb\u56ed\u6d32"
    ],
    "wof:name":"Mayuanzhou",
    "wof:placetype":"locality"
},
  "geometry": {"coordinates":[112.76761999999999,28.1804],"type":"Point"}
}