{
  "type": "Feature",
  "properties": {
    "gn:admin1_code":"30.0",
    "gn:asciiname":"Shanghuyang",
    "gn:country_code":"CN",
    "gn:dem":408,
    "gn:feature_class":"P",
    "gn:feature_code":"PPL",
    "gn:name":"Shanghuyang",
    "gn:population":0,
    "gn:timezone":"Asia/Shanghai",
    "iso:country":"CN",
    "name:zho_x_preferred":[
        "Shanghuyang"
    ],
    "name:zho_x_variant":[
        "\u4e0a\u6e56\u6d0b"
    ],
    "wof:name":"Shanghuyang",
    "wof:placetype":"locality"
},
  "geometry": {"coordinates":[114.43378,24.35756],"type":"Point"}
}