{
  "type": "Feature",
  "properties": {
    "gn:admin1_code":"12.0",
    "gn:asciiname":"Ancangping",
    "gn:country_code":"CN",
    "gn:dem":958,
    "gn:feature_class":"P",
    "gn:feature_code":"PPL",
    "gn:name":"Ancangping",
    "gn:population":0,
    "gn:timezone":"Asia/Shanghai",
    "iso:country":"CN",
    "name:zho_x_preferred":[
        "\u5b89\u4ed3\u576a"
    ],
    "wof:name":"Ancangping",
    "wof:placetype":"locality"
},
  "geometry": {"coordinates":[110.88043999999999,30.92931],"type":"Point"}
}