{
  "type": "Feature",
  "properties": {
    "gn:admin1_code":"5.0",
    "gn:asciiname":"Dongzhaojiagoucun",
    "gn:country_code":"CN",
    "gn:dem":186,
    "gn:feature_class":"P",
    "gn:feature_code":"PPL",
    "gn:name":"Dongzhaojiagoucun",
    "gn:population":0,
    "gn:timezone":"Asia/Shanghai",
    "iso:country":"CN",
    "name:zho_x_preferred":[
        "\u4e1c\u8d75\u5bb6\u6c9f\u6751"
    ],
    "wof:name":"Dongzhaojiagoucun",
    "wof:placetype":"locality"
},
  "geometry": {"coordinates":[125.12931,44.47958],"type":"Point"}
}