{
  "type": "Feature",
  "properties": {
    "gn:admin1_code":"11",
    "gn:asciiname":"Shishan Tangjia",
    "gn:country_code":"CN",
    "gn:dem":242,
    "gn:feature_class":"P",
    "gn:feature_code":"PPL",
    "gn:name":"Shishan Tangjia",
    "gn:population":0,
    "gn:timezone":"Asia/Shanghai",
    "iso:country":"CN",
    "name:zho_x_preferred":[
        "\u77f3\u5c71\u5510\u5bb6"
    ],
    "wof:name":"Shishan Tangjia",
    "wof:placetype":"locality"
},
  "geometry": {"coordinates":[111.23939,26.94166],"type":"Point"}
}