{
  "type": "Feature",
  "properties": {
    "gn:admin1_code":"33.0",
    "gn:asciiname":"Shuizhu",
    "gn:country_code":"CN",
    "gn:dem":425,
    "gn:feature_class":"P",
    "gn:feature_code":"PPL",
    "gn:name":"Shuizhu",
    "gn:population":0,
    "gn:timezone":"Asia/Shanghai",
    "iso:country":"CN",
    "name:jpn_x_preferred":[
        "\u6c34\u716e\u8089\u7247"
    ],
    "name:spa_x_preferred":[
        "Shuizhu"
    ],
    "name:zho_x_preferred":[
        "\u6c34\u7af9"
    ],
    "name:zho_x_variant":[
        "\u6c34\u716e\u8089\u7247"
    ],
    "wof:name":"Shuizhu",
    "wof:placetype":"locality"
},
  "geometry": {"coordinates":[106.688,29.311],"type":"Point"}
}