{
  "type": "Feature",
  "properties": {
    "gn:admin1_code":"29.0",
    "gn:asciiname":"Guanghui Xiacun",
    "gn:country_code":"CN",
    "gn:dem":1313,
    "gn:feature_class":"P",
    "gn:feature_code":"PPL",
    "gn:name":"Guanghui Xiacun",
    "gn:population":0,
    "gn:timezone":"Asia/Shanghai",
    "iso:country":"CN",
    "name:zho_x_preferred":[
        "\u5149\u8f89\u4e0b\u6751"
    ],
    "wof:name":"Guanghui Xiacun",
    "wof:placetype":"locality"
},
  "geometry": {"coordinates":[101.667,25.8425],"type":"Point"}
}