{
  "type": "Feature",
  "properties": {
    "gn:admin1_code":"10",
    "gn:asciiname":"Wanlianghouzhuang",
    "gn:country_code":"CN",
    "gn:dem":19,
    "gn:feature_class":"P",
    "gn:feature_code":"PPL",
    "gn:name":"Wanlianghouzhuang",
    "gn:population":0,
    "gn:timezone":"Asia/Shanghai",
    "iso:country":"CN",
    "name:zho_x_preferred":[
        "\u4e07\u7cae\u4faf\u5e84"
    ],
    "wof:name":"Wanlianghouzhuang",
    "wof:placetype":"locality"
},
  "geometry": {"coordinates":[116.47955,37.67506],"type":"Point"}
}