{
  "type": "Feature",
  "properties": {
    "gn:admin1_code":"13",
    "gn:asciiname":"Hulugou",
    "gn:country_code":"CN",
    "gn:dem":1656,
    "gn:feature_class":"P",
    "gn:feature_code":"PPL",
    "gn:name":"Hulugou",
    "gn:population":0,
    "gn:timezone":"Asia/Urumqi",
    "iso:country":"CN",
    "name:zho_x_preferred":[
        "\u846b\u82a6\u6c9f"
    ],
    "wof:name":"Hulugou",
    "wof:placetype":"locality"
},
  "geometry": {"coordinates":[93.51391,43.21699],"type":"Point"}
}