{
  "type": "Feature",
  "properties": {
    "gn:admin1_code":"24",
    "gn:asciiname":"Shangyao",
    "gn:cc2":"CN",
    "gn:country_code":"CN",
    "gn:dem":748,
    "gn:feature_class":"P",
    "gn:feature_code":"PPL",
    "gn:name":"Shangyao",
    "gn:population":0,
    "gn:timezone":"Asia/Shanghai",
    "iso:country":"CN",
    "name:und_x_variant":[
        "Shuang-yao-chen",
        "Shang-yao-ts\u2019un",
        "Shang-yao-chen",
        "Shangyao"
    ],
    "wof:name":"Shangyao",
    "wof:placetype":"locality"
},
  "geometry": {"coordinates":[113.25444,36.51694000000001],"type":"Point"}
}