{
  "type": "Feature",
  "properties": {
    "gn:admin1_code":"26.0",
    "gn:asciiname":"Yuanshantai",
    "gn:country_code":"CN",
    "gn:dem":1095,
    "gn:feature_class":"P",
    "gn:feature_code":"PPL",
    "gn:name":"Yuanshantai",
    "gn:population":0,
    "gn:timezone":"Asia/Shanghai",
    "iso:country":"CN",
    "name:zho_x_preferred":[
        "\u56ed\u5c71\u53f0"
    ],
    "wof:name":"Yuanshantai",
    "wof:placetype":"locality"
},
  "geometry": {"coordinates":[109.58925000000001,37.6214],"type":"Point"}
}