{
  "type": "Feature",
  "properties": {
    "gn:admin1_code":"11",
    "gn:asciiname":"Zhuyetang",
    "gn:country_code":"CN",
    "gn:dem":174,
    "gn:feature_class":"P",
    "gn:feature_code":"PPL",
    "gn:name":"Zhuyetang",
    "gn:population":0,
    "gn:timezone":"Asia/Shanghai",
    "iso:country":"CN",
    "name:zho_x_preferred":[
        "\u7af9\u53f6\u5858"
    ],
    "wof:name":"Zhuyetang",
    "wof:placetype":"locality"
},
  "geometry": {"coordinates":[113.16927,26.26745],"type":"Point"}
}