{
  "type": "Feature",
  "properties": {
    "gn:admin1_code":"25.0",
    "gn:asciiname":"Beixiaocheng",
    "gn:country_code":"CN",
    "gn:dem":15,
    "gn:feature_class":"P",
    "gn:feature_code":"PPL",
    "gn:name":"Beixiaocheng",
    "gn:population":0,
    "gn:timezone":"Asia/Shanghai",
    "iso:country":"CN",
    "name:zho_x_preferred":[
        "\u5317\u5c0f\u57ce"
    ],
    "wof:name":"Beixiaocheng",
    "wof:placetype":"locality"
},
  "geometry": {"coordinates":[122.02813,37.40724],"type":"Point"}
}