{
  "type": "Feature",
  "properties": {
    "gn:admin1_code":"32.0",
    "gn:asciiname":"Yanling",
    "gn:country_code":"CN",
    "gn:dem":318,
    "gn:feature_class":"P",
    "gn:feature_code":"PPLA3",
    "gn:name":"Yanling",
    "gn:population":0,
    "gn:timezone":"Asia/Shanghai",
    "iso:country":"CN",
    "name:ceb_x_preferred":[
        "Yanling"
    ],
    "name:deu_x_preferred":[
        "Yanling"
    ],
    "name:fra_x_preferred":[
        "Yanling"
    ],
    "name:kor_x_preferred":[
        "\uc60c\ub9c1\ud604"
    ],
    "name:nor_x_preferred":[
        "Yanling"
    ],
    "name:rus_x_preferred":[
        "\u042f\u043d\u044c\u043b\u0438\u043d"
    ],
    "name:swe_x_preferred":[
        "Yanling"
    ],
    "name:und_x_variant":[
        "Wei-y\u00fcan-hsien",
        "Weiyuan",
        "Yanling"
    ],
    "name:zho_x_preferred":[
        "\u4e25\u9675"
    ],
    "wof:name":"Yanling",
    "wof:placetype":"locality"
},
  "geometry": {"coordinates":[104.66108,29.53065],"type":"Point"}
}