{
  "type": "Feature",
  "properties": {
    "gn:admin1_code":"3.0",
    "gn:asciiname":"Fushan",
    "gn:country_code":"CN",
    "gn:dem":42,
    "gn:feature_class":"P",
    "gn:feature_code":"PPL",
    "gn:name":"Fushan",
    "gn:population":0,
    "gn:timezone":"Asia/Shanghai",
    "iso:country":"CN",
    "name:und_x_variant":[
        "\u5bcc\u5c71"
    ],
    "wof:name":"Fushan",
    "wof:placetype":"locality"
},
  "geometry": {"coordinates":[115.4853,28.56911],"type":"Point"}
}