{
  "type": "Feature",
  "properties": {
    "gn:admin1_code":"8.0",
    "gn:asciiname":"Bin'ancun",
    "gn:country_code":"CN",
    "gn:dem":135,
    "gn:feature_class":"P",
    "gn:feature_code":"PPL",
    "gn:name":"Bin\u2019ancun",
    "gn:population":0,
    "gn:timezone":"Asia/Shanghai",
    "iso:country":"CN",
    "name:und_x_variant":[
        "Bin\u2019ancun"
    ],
    "name:zho_x_preferred":[
        "\u5bbe\u5b89\u6751"
    ],
    "wof:name":"Bin'ancun",
    "wof:placetype":"locality"
},
  "geometry": {"coordinates":[127.74594,45.84208],"type":"Point"}
}