{
  "type": "Feature",
  "properties": {
    "gn:admin1_code":"5.0",
    "gn:asciiname":"Shaping",
    "gn:country_code":"CN",
    "gn:dem":187,
    "gn:feature_class":"P",
    "gn:feature_code":"PPL",
    "gn:name":"Shaping",
    "gn:population":0,
    "gn:timezone":"Asia/Shanghai",
    "iso:country":"CN",
    "name:und_x_variant":[
        "\u6c99\u576a"
    ],
    "wof:name":"Shaping",
    "wof:placetype":"locality"
},
  "geometry": {"coordinates":[129.75766999999999,42.63617],"type":"Point"}
}