{
  "type": "Feature",
  "properties": {
    "gn:admin1_code":"22",
    "gn:asciiname":"Xiaotangshan",
    "gn:country_code":"CN",
    "gn:dem":39,
    "gn:feature_class":"P",
    "gn:feature_code":"PPLA4",
    "gn:name":"Xiaotangshan",
    "gn:population":0,
    "gn:timezone":"Asia/Shanghai",
    "iso:country":"CN",
    "name:und_x_variant":[
        "Hsiao-t\u2019ang-shan",
        "Ta-t\u2019ang-shan",
        "T\u2019ang-shan",
        "Xiaotangshan",
        "Xiaotangshan Zhen"
    ],
    "name:zho_x_preferred":[
        "\u5c0f\u6c64\u5c71"
    ],
    "name:zho_x_variant":[
        "\u5c0f\u6c64\u5c71\u9547"
    ],
    "wof:name":"Xiaotangshan",
    "wof:placetype":"locality"
},
  "geometry": {"coordinates":[116.38455999999999,40.17663],"type":"Point"}
}