{
  "type": "Feature",
  "properties": {
    "gn:admin1_code":"4.0",
    "gn:asciiname":"Donghai Fenchang Wulian",
    "gn:country_code":"CN",
    "gn:dem":6,
    "gn:feature_class":"P",
    "gn:feature_code":"PPLF",
    "gn:name":"Donghai Fenchang Wulian",
    "gn:population":0,
    "gn:timezone":"Asia/Shanghai",
    "iso:country":"CN",
    "name:zho_x_preferred":[
        "\u4e1c\u6d77\u5206\u573a\u4e94\u8fde"
    ],
    "wof:name":"Donghai Fenchang Wulian",
    "wof:placetype":"locality"
},
  "geometry": {"coordinates":[120.88495,31.22359],"type":"Point"}
}