{
  "type": "Feature",
  "properties": {
    "gn:admin1_code":"29.0",
    "gn:asciiname":"Manxiu",
    "gn:country_code":"CN",
    "gn:dem":1328,
    "gn:feature_class":"P",
    "gn:feature_code":"PPL",
    "gn:name":"Manxiu",
    "gn:population":0,
    "gn:timezone":"Asia/Shanghai",
    "iso:country":"CN",
    "name:zho_x_preferred":[
        "\u66fc\u79c0"
    ],
    "wof:name":"Manxiu",
    "wof:placetype":"locality"
},
  "geometry": {"coordinates":[101.464,22.0117],"type":"Point"}
}