{
  "type": "Feature",
  "properties": {
    "gn:admin1_code":"26",
    "gn:asciiname":"Jinpenwancun",
    "gn:country_code":"CN",
    "gn:dem":1062,
    "gn:feature_class":"P",
    "gn:feature_code":"PPL",
    "gn:name":"Jinpenwancun",
    "gn:population":0,
    "gn:timezone":"Asia/Shanghai",
    "iso:country":"CN",
    "name:und_x_variant":[
        "Chin-p\u2019en-wan",
        "Chin-ho-wan",
        "Jinpenwan",
        "Jinpenwancun"
    ],
    "name:zho_x_preferred":[
        "\u91d1\u76c6\u6e7e\u6751"
    ],
    "wof:name":"Jinpenwancun",
    "wof:placetype":"locality"
},
  "geometry": {"coordinates":[109.74632,36.37256],"type":"Point"}
}