{
  "type": "Feature",
  "properties": {
    "gn:admin1_code":"25",
    "gn:asciiname":"Panjia",
    "gn:country_code":"CN",
    "gn:dem":20,
    "gn:feature_class":"P",
    "gn:feature_code":"PPL",
    "gn:name":"Panjia",
    "gn:population":0,
    "gn:timezone":"Asia/Shanghai",
    "iso:country":"CN",
    "name:zho_x_preferred":[
        "\u6f58\u5bb6"
    ],
    "wof:name":"Panjia",
    "wof:placetype":"locality"
},
  "geometry": {"coordinates":[117.24299999999999,37.1315],"type":"Point"}
}