{
  "type": "Feature",
  "properties": {
    "gn:admin1_code":"16.0",
    "gn:asciiname":"Shangbalei",
    "gn:country_code":"CN",
    "gn:dem":618,
    "gn:feature_class":"P",
    "gn:feature_code":"PPL",
    "gn:name":"Shangbalei",
    "gn:population":0,
    "gn:timezone":"Asia/Shanghai",
    "iso:country":"CN",
    "name:zho_x_preferred":[
        "\u4e0a\u5df4\u96f7"
    ],
    "wof:name":"Shangbalei",
    "wof:placetype":"locality"
},
  "geometry": {"coordinates":[107.22,25.2975],"type":"Point"}
}