{
  "type": "Feature",
  "properties": {
    "gn:admin1_code":"19.0",
    "gn:asciiname":"Kongjia Wobucun",
    "gn:country_code":"CN",
    "gn:dem":86,
    "gn:feature_class":"P",
    "gn:feature_code":"PPL",
    "gn:name":"Kongjia Wobucun",
    "gn:population":0,
    "gn:timezone":"Asia/Shanghai",
    "iso:country":"CN",
    "name:zho_x_preferred":[
        "\u5b54\u5bb6\u7a9d\u5821\u6751"
    ],
    "wof:name":"Kongjia Wobucun",
    "wof:placetype":"locality"
},
  "geometry": {"coordinates":[123.4269,42.72066],"type":"Point"}
}