{
  "type": "Feature",
  "properties": {
    "gn:admin1_code":"19.0",
    "gn:asciiname":"Banbishancun",
    "gn:country_code":"CN",
    "gn:dem":99,
    "gn:feature_class":"P",
    "gn:feature_code":"PPL",
    "gn:name":"Banbishancun",
    "gn:population":0,
    "gn:timezone":"Asia/Shanghai",
    "iso:country":"CN",
    "name:zho_x_preferred":[
        "\u534a\u58c1\u5c71\u6751"
    ],
    "wof:name":"Banbishancun",
    "wof:placetype":"locality"
},
  "geometry": {"coordinates":[121.18600000000001,41.29277],"type":"Point"}
}