{
  "type": "Feature",
  "properties": {
    "gn:admin1_code":"24.0",
    "gn:asciiname":"Xiwan",
    "gn:country_code":"CN",
    "gn:dem":1548,
    "gn:feature_class":"P",
    "gn:feature_code":"PPL",
    "gn:name":"Xiwan",
    "gn:population":0,
    "gn:timezone":"Asia/Shanghai",
    "iso:country":"CN",
    "name:und_x_variant":[
        "Hsi-wan",
        "Xiwan",
        "\u897f\u6e7e"
    ],
    "wof:name":"Xiwan",
    "wof:placetype":"locality"
},
  "geometry": {"coordinates":[113.79203,39.39082],"type":"Point"}
}