{
  "type": "Feature",
  "properties": {
    "gn:admin1_code":"5.0",
    "gn:asciiname":"Houwu Minggou",
    "gn:country_code":"CN",
    "gn:dem":407,
    "gn:feature_class":"P",
    "gn:feature_code":"PPL",
    "gn:name":"Houwu Minggou",
    "gn:population":0,
    "gn:timezone":"Asia/Shanghai",
    "iso:country":"CN",
    "name:zho_x_preferred":[
        "\u540e\u4e4c\u9e23\u6c9f"
    ],
    "wof:name":"Houwu Minggou",
    "wof:placetype":"locality"
},
  "geometry": {"coordinates":[125.05768999999999,42.6754],"type":"Point"}
}