{
  "type": "Feature",
  "properties": {
    "gn:admin1_code":"9.0",
    "gn:asciiname":"Changtanggeng",
    "gn:country_code":"CN",
    "gn:dem":201,
    "gn:feature_class":"P",
    "gn:feature_code":"PPL",
    "gn:name":"Changtanggeng",
    "gn:population":0,
    "gn:timezone":"Asia/Shanghai",
    "iso:country":"CN",
    "name:zho_x_preferred":[
        "\u957f\u5858\u57c2"
    ],
    "wof:name":"Changtanggeng",
    "wof:placetype":"locality"
},
  "geometry": {"coordinates":[115.24281000000001,31.59681],"type":"Point"}
}