{
  "type": "Feature",
  "properties": {
    "gn:admin1_code":"30.0",
    "gn:asciiname":"Niulutou",
    "gn:country_code":"CN",
    "gn:dem":46,
    "gn:feature_class":"P",
    "gn:feature_code":"PPL",
    "gn:name":"Niulutou",
    "gn:population":0,
    "gn:timezone":"Asia/Shanghai",
    "iso:country":"CN",
    "name:zho_x_preferred":[
        "\u725b\u8def\u5934"
    ],
    "wof:name":"Niulutou",
    "wof:placetype":"locality"
},
  "geometry": {"coordinates":[114.07102999999999,23.33943],"type":"Point"}
}