{
  "type": "Feature",
  "properties": {
    "gn:admin1_code":"19",
    "gn:asciiname":"Erdaohe",
    "gn:cc2":"CN",
    "gn:country_code":"CN",
    "gn:dem":457,
    "gn:feature_class":"P",
    "gn:feature_code":"PPL",
    "gn:name":"Erdaohe",
    "gn:population":0,
    "gn:timezone":"Asia/Shanghai",
    "iso:country":"CN",
    "name:und_x_variant":[
        "Erh-tao-ho-tzu",
        "Erdaohe"
    ],
    "wof:name":"Erdaohe",
    "wof:placetype":"locality"
},
  "geometry": {"coordinates":[125.20139,42.03194000000001],"type":"Point"}
}