{
  "type": "Feature",
  "properties": {
    "gn:admin1_code":"3.0",
    "gn:asciiname":"Zhuhu",
    "gn:country_code":"CN",
    "gn:dem":39,
    "gn:feature_class":"P",
    "gn:feature_code":"PPL",
    "gn:name":"Zhuhu",
    "gn:population":0,
    "gn:timezone":"Asia/Shanghai",
    "iso:country":"CN",
    "name:und_x_variant":[
        "\u73e0\u6e56"
    ],
    "wof:name":"Zhuhu",
    "wof:placetype":"locality"
},
  "geometry": {"coordinates":[115.36147,28.3275],"type":"Point"}
}