{
  "type": "Feature",
  "properties": {
    "gn:admin1_code":"24.0",
    "gn:asciiname":"Dadegou",
    "gn:country_code":"CN",
    "gn:dem":1763,
    "gn:feature_class":"P",
    "gn:feature_code":"PPL",
    "gn:name":"Dadegou",
    "gn:population":0,
    "gn:timezone":"Asia/Shanghai",
    "iso:country":"CN",
    "name:zho_x_preferred":[
        "\u5927\u5fb7\u6c9f"
    ],
    "wof:name":"Dadegou",
    "wof:placetype":"locality"
},
  "geometry": {"coordinates":[112.28095999999999,38.52195],"type":"Point"}
}