{
  "type": "Feature",
  "properties": {
    "gn:admin1_code":"18.0",
    "gn:asciiname":"Shangchangpo",
    "gn:country_code":"CN",
    "gn:dem":712,
    "gn:feature_class":"P",
    "gn:feature_code":"PPL",
    "gn:name":"Shangchangpo",
    "gn:population":0,
    "gn:timezone":"Asia/Shanghai",
    "iso:country":"CN",
    "name:zho_x_preferred":[
        "\u4e0a\u957f\u5761"
    ],
    "wof:name":"Shangchangpo",
    "wof:placetype":"locality"
},
  "geometry": {"coordinates":[108.65000000000001,27.1179],"type":"Point"}
}