{
  "type": "Feature",
  "properties": {
    "gn:admin1_code":"18.0",
    "gn:asciiname":"Niantuan",
    "gn:country_code":"CN",
    "gn:dem":680,
    "gn:feature_class":"P",
    "gn:feature_code":"PPL",
    "gn:name":"Niantuan",
    "gn:population":0,
    "gn:timezone":"Asia/Shanghai",
    "iso:country":"CN",
    "name:zho_x_preferred":[
        "\u78be\u56e2"
    ],
    "wof:name":"Niantuan",
    "wof:placetype":"locality"
},
  "geometry": {"coordinates":[109.21899999999999,26.2963],"type":"Point"}
}