{
  "type": "Feature",
  "properties": {
    "gn:admin1_code":"29.0",
    "gn:asciiname":"Laobiqing",
    "gn:country_code":"CN",
    "gn:dem":1787,
    "gn:feature_class":"P",
    "gn:feature_code":"PPL",
    "gn:name":"Laobiqing",
    "gn:population":0,
    "gn:timezone":"Asia/Shanghai",
    "iso:country":"CN",
    "name:zho_x_preferred":[
        "\u8001\u6bd5\u7b90"
    ],
    "wof:name":"Laobiqing",
    "wof:placetype":"locality"
},
  "geometry": {"coordinates":[101.533,25.8159],"type":"Point"}
}