{
  "type": "Feature",
  "properties": {
    "gn:admin1_code":"16.0",
    "gn:asciiname":"Chihe",
    "gn:country_code":"CN",
    "gn:dem":144,
    "gn:feature_class":"P",
    "gn:feature_code":"PPL",
    "gn:name":"Chihe",
    "gn:population":0,
    "gn:timezone":"Asia/Shanghai",
    "iso:country":"CN",
    "name:zho_x_preferred":[
        "\u6c60\u6cb3"
    ],
    "wof:name":"Chihe",
    "wof:placetype":"locality"
},
  "geometry": {"coordinates":[109.59399999999999,23.3477],"type":"Point"}
}