{
  "type": "Feature",
  "properties": {
    "gn:admin1_code":"2.0",
    "gn:asciiname":"Xiaruoshan",
    "gn:country_code":"CN",
    "gn:dem":593,
    "gn:feature_class":"P",
    "gn:feature_code":"PPL",
    "gn:name":"Xiaruoshan",
    "gn:population":0,
    "gn:timezone":"Asia/Shanghai",
    "iso:country":"CN",
    "name:zho_x_preferred":[
        "\u4e0b\u7bac\u5c71"
    ],
    "wof:name":"Xiaruoshan",
    "wof:placetype":"locality"
},
  "geometry": {"coordinates":[118.54173,28.40658],"type":"Point"}
}