{
  "type": "Feature",
  "properties": {
    "gn:admin1_code":"3.0",
    "gn:asciiname":"Zhangshudun",
    "gn:country_code":"CN",
    "gn:dem":79,
    "gn:feature_class":"P",
    "gn:feature_code":"PPL",
    "gn:name":"Zhangshudun",
    "gn:population":0,
    "gn:timezone":"Asia/Shanghai",
    "iso:country":"CN",
    "name:und_x_variant":[
        "Chang-shu-tun",
        "Zhangshudun"
    ],
    "name:zho_x_preferred":[
        "\u6a1f\u6811\u58a9"
    ],
    "wof:name":"Zhangshudun",
    "wof:placetype":"locality"
},
  "geometry": {"coordinates":[117.4593,28.53935],"type":"Point"}
}