{
  "type": "Feature",
  "properties": {
    "gn:admin1_code":"12.0",
    "gn:asciiname":"Longli",
    "gn:country_code":"CN",
    "gn:dem":20,
    "gn:feature_class":"P",
    "gn:feature_code":"PPL",
    "gn:name":"Longli",
    "gn:population":0,
    "gn:timezone":"Asia/Shanghai",
    "iso:country":"CN",
    "name:zho_x_preferred":[
        "\u5784\u91cc"
    ],
    "wof:name":"Longli",
    "wof:placetype":"locality"
},
  "geometry": {"coordinates":[115.52831999999999,29.8723],"type":"Point"}
}