{
  "type": "Feature",
  "properties": {
    "gn:admin1_code":"30.0",
    "gn:asciiname":"Anjiwei",
    "gn:country_code":"CN",
    "gn:dem":0,
    "gn:feature_class":"P",
    "gn:feature_code":"PPL",
    "gn:name":"Anjiwei",
    "gn:population":0,
    "gn:timezone":"Asia/Shanghai",
    "iso:country":"CN",
    "name:zho_x_preferred":[
        "\u5b89\u5409\u56f4"
    ],
    "wof:name":"Anjiwei",
    "wof:placetype":"locality"
},
  "geometry": {"coordinates":[113.31952,22.35536],"type":"Point"}
}