{
  "type": "Feature",
  "properties": {
    "gn:admin1_code":"16.0",
    "gn:asciiname":"Weidu Xincun",
    "gn:country_code":"CN",
    "gn:dem":103,
    "gn:feature_class":"P",
    "gn:feature_code":"PPL",
    "gn:name":"Weidu Xincun",
    "gn:population":0,
    "gn:timezone":"Asia/Shanghai",
    "iso:country":"CN",
    "name:zho_x_preferred":[
        "\u7ef4\u90fd\u65b0\u6751"
    ],
    "wof:name":"Weidu Xincun",
    "wof:placetype":"locality"
},
  "geometry": {"coordinates":[109.259,23.8097],"type":"Point"}
}