{
  "type": "Feature",
  "properties": {
    "gn:admin1_code":"19.0",
    "gn:asciiname":"Dayutun",
    "gn:country_code":"CN",
    "gn:dem":14,
    "gn:feature_class":"P",
    "gn:feature_code":"PPL",
    "gn:name":"Dayutun",
    "gn:population":0,
    "gn:timezone":"Asia/Shanghai",
    "iso:country":"CN",
    "name:und_x_variant":[
        "\u5927\u88d5\u5c6f"
    ],
    "name:zho_x_preferred":[
        "\u5927\u88d5\u5c6f"
    ],
    "wof:name":"Dayutun",
    "wof:placetype":"locality"
},
  "geometry": {"coordinates":[122.67355000000001,39.55309000000001],"type":"Point"}
}