{
  "type": "Feature",
  "properties": {
    "gn:admin1_code":"11.0",
    "gn:asciiname":"Tudiya",
    "gn:country_code":"CN",
    "gn:dem":642,
    "gn:feature_class":"P",
    "gn:feature_code":"PPL",
    "gn:name":"Tudiya",
    "gn:population":0,
    "gn:timezone":"Asia/Shanghai",
    "iso:country":"CN",
    "name:zho_x_preferred":[
        "\u571f\u5730\u57ad"
    ],
    "wof:name":"Tudiya",
    "wof:placetype":"locality"
},
  "geometry": {"coordinates":[110.23206999999999,29.34486],"type":"Point"}
}