{
  "type": "Feature",
  "properties": {
    "gn:admin1_code":"26.0",
    "gn:asciiname":"Langping",
    "gn:country_code":"CN",
    "gn:dem":1151,
    "gn:feature_class":"P",
    "gn:feature_code":"PPL",
    "gn:name":"Langping",
    "gn:population":0,
    "gn:timezone":"Asia/Shanghai",
    "iso:country":"CN",
    "name:und_x_variant":[
        "\u72fc\u576a"
    ],
    "wof:name":"Langping",
    "wof:placetype":"locality"
},
  "geometry": {"coordinates":[107.13431,34.89248],"type":"Point"}
}