{
  "type": "Feature",
  "properties": {
    "gn:admin1_code":"15.0",
    "gn:asciiname":"Qiaohe",
    "gn:country_code":"CN",
    "gn:dem":1433,
    "gn:feature_class":"P",
    "gn:feature_code":"PPL",
    "gn:name":"Qiaohe",
    "gn:population":0,
    "gn:timezone":"Asia/Shanghai",
    "iso:country":"CN",
    "name:zho_x_preferred":[
        "\u4e54\u6cb3"
    ],
    "wof:name":"Qiaohe",
    "wof:placetype":"locality"
},
  "geometry": {"coordinates":[108.069,36.5146],"type":"Point"}
}