{
  "type": "Feature",
  "properties": {
    "gn:admin1_code":"9",
    "gn:asciiname":"Lipingsi",
    "gn:country_code":"CN",
    "gn:dem":239,
    "gn:feature_class":"P",
    "gn:feature_code":"PPL",
    "gn:name":"Lipingsi",
    "gn:population":0,
    "gn:timezone":"Asia/Shanghai",
    "iso:country":"CN",
    "name:und_x_variant":[
        "\u674e\u576a\u5bfa",
        "Lipingsi"
    ],
    "wof:name":"Lipingsi",
    "wof:placetype":"locality"
},
  "geometry": {"coordinates":[112.27852,33.21232],"type":"Point"}
}