{
  "type": "Feature",
  "properties": {
    "gn:admin1_code":"2.0",
    "gn:asciiname":"Dongjialiao",
    "gn:country_code":"CN",
    "gn:dem":931,
    "gn:feature_class":"P",
    "gn:feature_code":"PPL",
    "gn:name":"Dongjialiao",
    "gn:population":0,
    "gn:timezone":"Asia/Shanghai",
    "iso:country":"CN",
    "name:und_x_variant":[
        "\u4e1c\u5bb6\u5bee",
        "Dongjialiao"
    ],
    "wof:name":"Dongjialiao",
    "wof:placetype":"locality"
},
  "geometry": {"coordinates":[119.82265,27.8239],"type":"Point"}
}