{
  "type": "Feature",
  "properties": {
    "gn:admin1_code":"15.0",
    "gn:asciiname":"Xiaoquanzhan",
    "gn:country_code":"CN",
    "gn:dem":1833,
    "gn:feature_class":"P",
    "gn:feature_code":"PPL",
    "gn:name":"Xiaoquanzhan",
    "gn:population":0,
    "gn:timezone":"Asia/Urumqi",
    "iso:country":"CN",
    "name:zho_x_preferred":[
        "\u5c0f\u6cc9\u7ad9"
    ],
    "wof:name":"Xiaoquanzhan",
    "wof:placetype":"locality"
},
  "geometry": {"coordinates":[95.2987,41.2352],"type":"Point"}
}