{
  "type": "Feature",
  "properties": {
    "gn:country":"CN",
    "gn:fcode":"PPL",
    "gn:pop":125667,
    "iso:country":"CN",
    "name:unk_x_variant":[
        "Weishan"
    ],
    "qs:name":"Xiazhen",
    "qs:photos_9r":0,
    "qs:photos_sr":0,
    "qs:pop_sr":"9",
    "wof:name":"Xiazhen",
    "wof:placetype":"locality",
    "wof:population":125667
},
  "geometry": {"coordinates":[117.11167,34.80222],"type":"Point"}
}