{
  "type": "Feature",
  "properties": {
    "gn:admin1_code":"24.0",
    "gn:asciiname":"Jingju",
    "gn:country_code":"CN",
    "gn:dem":914,
    "gn:feature_class":"P",
    "gn:feature_code":"PPL",
    "gn:name":"Jingju",
    "gn:population":0,
    "gn:timezone":"Asia/Shanghai",
    "iso:country":"CN",
    "name:zho_x_preferred":[
        "\u9756\u5c45"
    ],
    "wof:name":"Jingju",
    "wof:placetype":"locality"
},
  "geometry": {"coordinates":[112.83614,35.9325],"type":"Point"}
}