{
  "type": "Feature",
  "properties": {
    "gn:admin1_code":"3.0",
    "gn:asciiname":"Shitoupai",
    "gn:country_code":"CN",
    "gn:dem":463,
    "gn:feature_class":"P",
    "gn:feature_code":"PPL",
    "gn:name":"Shitoupai",
    "gn:population":0,
    "gn:timezone":"Asia/Shanghai",
    "iso:country":"CN",
    "name:und_x_variant":[
        "\u77f3\u5934\u6392"
    ],
    "wof:name":"Shitoupai",
    "wof:placetype":"locality"
},
  "geometry": {"coordinates":[115.77786,26.63231],"type":"Point"}
}