{
  "type": "Feature",
  "properties": {
    "gn:admin1_code":"26.0",
    "gn:asciiname":"Xiongjia Dianzi",
    "gn:country_code":"CN",
    "gn:dem":1461,
    "gn:feature_class":"P",
    "gn:feature_code":"PPL",
    "gn:name":"Xiongjia Dianzi",
    "gn:population":0,
    "gn:timezone":"Asia/Shanghai",
    "iso:country":"CN",
    "name:und_x_variant":[
        "\u718a\u5bb6\u5e97\u5b50",
        "Xiongjia Dianzi"
    ],
    "wof:name":"Xiongjia Dianzi",
    "wof:placetype":"locality"
},
  "geometry": {"coordinates":[108.04928,33.486],"type":"Point"}
}