{
  "type": "Feature",
  "properties": {
    "gn:admin1_code":"02",
    "gn:asciiname":"Lantiancun",
    "gn:country_code":"CN",
    "gn:dem":546,
    "gn:feature_class":"P",
    "gn:feature_code":"PPL",
    "gn:name":"Lantiancun",
    "gn:population":0,
    "gn:timezone":"Asia/Shanghai",
    "iso:country":"CN",
    "name:und_x_variant":[
        "Lantian",
        "Lantiancun"
    ],
    "name:zho_x_preferred":[
        "\u5170\u7530"
    ],
    "name:zho_x_variant":[
        "\u5170\u7530\u6751"
    ],
    "wof:name":"Lantiancun",
    "wof:placetype":"locality"
},
  "geometry": {"coordinates":[121.36024999999999,28.80784],"type":"Point"}
}