{
  "type": "Feature",
  "properties": {
    "gn:admin1_code":"3.0",
    "gn:asciiname":"Lianqun",
    "gn:country_code":"CN",
    "gn:dem":526,
    "gn:feature_class":"P",
    "gn:feature_code":"PPL",
    "gn:name":"Lianqun",
    "gn:population":0,
    "gn:timezone":"Asia/Shanghai",
    "iso:country":"CN",
    "name:und_x_variant":[
        "\u8054\u7fa4"
    ],
    "wof:name":"Lianqun",
    "wof:placetype":"locality"
},
  "geometry": {"coordinates":[115.64043999999998,25.06769],"type":"Point"}
}