{
  "type": "Feature",
  "properties": {
    "gn:admin1_code":"4.0",
    "gn:asciiname":"Gangban Sanzu",
    "gn:country_code":"CN",
    "gn:dem":10,
    "gn:feature_class":"P",
    "gn:feature_code":"PPLF",
    "gn:name":"Gangban Sanzu",
    "gn:population":0,
    "gn:timezone":"Asia/Shanghai",
    "iso:country":"CN",
    "name:zho_x_preferred":[
        "\u5c97\u5742\u4e09\u7ec4"
    ],
    "wof:name":"Gangban Sanzu",
    "wof:placetype":"locality"
},
  "geometry": {"coordinates":[119.09999999999999,32.8759],"type":"Point"}
}