{
  "type": "Feature",
  "properties": {
    "gn:admin1_code":"24.0",
    "gn:asciiname":"Huawa",
    "gn:country_code":"CN",
    "gn:dem":1467,
    "gn:feature_class":"P",
    "gn:feature_code":"PPL",
    "gn:name":"Huawa",
    "gn:population":0,
    "gn:timezone":"Asia/Shanghai",
    "iso:country":"CN",
    "name:zho_x_preferred":[
        "\u5316\u7a8a"
    ],
    "wof:name":"Huawa",
    "wof:placetype":"locality"
},
  "geometry": {"coordinates":[111.15855000000001,36.92893],"type":"Point"}
}