{
  "type": "Feature",
  "properties": {
    "gn:admin1_code":"10",
    "gn:asciiname":"Wangdu",
    "gn:cc2":"CN",
    "gn:country_code":"CN",
    "gn:dem":48,
    "gn:feature_class":"P",
    "gn:feature_code":"PPL",
    "gn:name":"Wangdu",
    "gn:population":0,
    "gn:timezone":"Asia/Shanghai",
    "iso:country":"CN",
    "name:und_x_variant":[
        "Vandu",
        "Wang-tu-hsien",
        "Wang-tu-ch\u2019eng-kuan",
        "Wang-tu",
        "Wangdu"
    ],
    "wof:name":"Wangdu",
    "wof:placetype":"locality"
},
  "geometry": {"coordinates":[115.14,38.70444000000001],"type":"Point"}
}