{
  "type": "Feature",
  "properties": {
    "gn:admin1_code":"5.0",
    "gn:asciiname":"Changtuozicun",
    "gn:country_code":"CN",
    "gn:dem":205,
    "gn:feature_class":"P",
    "gn:feature_code":"PPL",
    "gn:name":"Changtuozicun",
    "gn:population":0,
    "gn:timezone":"Asia/Shanghai",
    "iso:country":"CN",
    "name:zho_x_preferred":[
        "\u957f\u5768\u5b50\u6751"
    ],
    "wof:name":"Changtuozicun",
    "wof:placetype":"locality"
},
  "geometry": {"coordinates":[124.16427,44.1996],"type":"Point"}
}