{
  "type": "Feature",
  "properties": {
    "gn:admin1_code":"03",
    "gn:asciiname":"Baishaguan",
    "gn:country_code":"CN",
    "gn:dem":96,
    "gn:feature_class":"P",
    "gn:feature_code":"PPL",
    "gn:name":"Baishaguan",
    "gn:population":0,
    "gn:timezone":"Asia/Shanghai",
    "iso:country":"CN",
    "name:und_x_variant":[
        "Pai-sha-kuan",
        "Baishaguan"
    ],
    "name:zho_x_preferred":[
        "\u767d\u6c99\u5173"
    ],
    "wof:name":"Baishaguan",
    "wof:placetype":"locality"
},
  "geometry": {"coordinates":[118.01703999999999,29.09456],"type":"Point"}
}