{
  "type": "Feature",
  "properties": {
    "gn:admin1_code":"6.0",
    "gn:asciiname":"Jianjiannong",
    "gn:country_code":"CN",
    "gn:dem":3915,
    "gn:feature_class":"P",
    "gn:feature_code":"PPL",
    "gn:name":"Jianjiannong",
    "gn:population":0,
    "gn:timezone":"Asia/Urumqi",
    "iso:country":"CN",
    "name:zho_x_preferred":[
        "\u4fed\u4fed\u5f04"
    ],
    "wof:name":"Jianjiannong",
    "wof:placetype":"locality"
},
  "geometry": {"coordinates":[96.14212999999999,32.52245],"type":"Point"}
}