{
  "type": "Feature",
  "properties": {
    "gn:admin1_code":"11.0",
    "gn:asciiname":"Panjialong",
    "gn:country_code":"CN",
    "gn:dem":699,
    "gn:feature_class":"P",
    "gn:feature_code":"PPL",
    "gn:name":"Panjialong",
    "gn:population":0,
    "gn:timezone":"Asia/Shanghai",
    "iso:country":"CN",
    "name:zho_x_preferred":[
        "\u76d8\u5bb6\u9f99"
    ],
    "wof:name":"Panjialong",
    "wof:placetype":"locality"
},
  "geometry": {"coordinates":[108.97131,27.07983],"type":"Point"}
}