{
  "type": "Feature",
  "properties": {
    "gn:admin1_code":"15.0",
    "gn:asciiname":"Mozhuangzi",
    "gn:country_code":"CN",
    "gn:dem":2108,
    "gn:feature_class":"P",
    "gn:feature_code":"PPL",
    "gn:name":"Mozhuangzi",
    "gn:population":0,
    "gn:timezone":"Asia/Shanghai",
    "iso:country":"CN",
    "name:zho_x_preferred":[
        "\u78e8\u5e84\u5b50"
    ],
    "wof:name":"Mozhuangzi",
    "wof:placetype":"locality"
},
  "geometry": {"coordinates":[101.776,38.2697],"type":"Point"}
}