{
  "type": "Feature",
  "properties": {
    "gn:admin1_code":"08",
    "gn:asciiname":"Yanjiang",
    "gn:country_code":"CN",
    "gn:dem":120,
    "gn:feature_class":"P",
    "gn:feature_code":"PPLA4",
    "gn:name":"Yanjiang",
    "gn:population":0,
    "gn:timezone":"Asia/Shanghai",
    "iso:country":"CN",
    "name:und_x_variant":[
        "Huo-erh-mo-chin",
        "Huormojin",
        "Yanjiang",
        "Yanjiang Manzu Dawo\u2019erzu",
        "Yanjiang Manzu Dawo\u2019erzu Xiang"
    ],
    "name:zho_x_preferred":[
        "\u6cbf\u6c5f"
    ],
    "name:zho_x_variant":[
        "\u6cbf\u6c5f\u6ee1\u65cf\u8fbe\u65a1\u5c14\u65cf",
        "\u6cbf\u6c5f\u6ee1\u65cf\u8fbe\u65a1\u5c14\u65cf\u4e61"
    ],
    "wof:name":"Yanjiang",
    "wof:placetype":"locality"
},
  "geometry": {"coordinates":[127.78266000000001,49.57308],"type":"Point"}
}