{
  "type": "Feature",
  "properties": {
    "gn:admin1_code":"32.0",
    "gn:asciiname":"Taikongsi",
    "gn:country_code":"CN",
    "gn:dem":363,
    "gn:feature_class":"P",
    "gn:feature_code":"PPL",
    "gn:name":"Taikongsi",
    "gn:population":0,
    "gn:timezone":"Asia/Shanghai",
    "iso:country":"CN",
    "name:zho_x_preferred":[
        "\u592a\u7a7a\u5bfa"
    ],
    "wof:name":"Taikongsi",
    "wof:placetype":"locality"
},
  "geometry": {"coordinates":[105.38545000000001,30.90489],"type":"Point"}
}