{
  "type": "Feature",
  "properties": {
    "gn:admin1_code":"32.0",
    "gn:asciiname":"Yanjiagou",
    "gn:country_code":"CN",
    "gn:dem":488,
    "gn:feature_class":"P",
    "gn:feature_code":"PPL",
    "gn:name":"Yanjiagou",
    "gn:population":0,
    "gn:timezone":"Asia/Shanghai",
    "iso:country":"CN",
    "name:zho_x_preferred":[
        "\u4e25\u5bb6\u6c9f"
    ],
    "wof:name":"Yanjiagou",
    "wof:placetype":"locality"
},
  "geometry": {"coordinates":[104.86014,30.80882],"type":"Point"}
}