{
  "type": "Feature",
  "properties": {
    "gn:admin1_code":"29.0",
    "gn:asciiname":"Yangtianchong",
    "gn:country_code":"CN",
    "gn:dem":2120,
    "gn:feature_class":"P",
    "gn:feature_code":"PPL",
    "gn:name":"Yangtianchong",
    "gn:population":0,
    "gn:timezone":"Asia/Shanghai",
    "iso:country":"CN",
    "name:zho_x_preferred":[
        "\u79e7\u7530\u51b2"
    ],
    "wof:name":"Yangtianchong",
    "wof:placetype":"locality"
},
  "geometry": {"coordinates":[104.039,25.807],"type":"Point"}
}