{
  "type": "Feature",
  "properties": {
    "gn:admin1_code":"11",
    "gn:asciiname":"Xinwu Liujia",
    "gn:country_code":"CN",
    "gn:dem":118,
    "gn:feature_class":"P",
    "gn:feature_code":"PPL",
    "gn:name":"Xinwu Liujia",
    "gn:population":0,
    "gn:timezone":"Asia/Shanghai",
    "iso:country":"CN",
    "name:zho_x_preferred":[
        "\u65b0\u5c4b\u5218\u5bb6"
    ],
    "wof:name":"Xinwu Liujia",
    "wof:placetype":"locality"
},
  "geometry": {"coordinates":[111.80446000000001,26.40451],"type":"Point"}
}