{
  "type": "Feature",
  "properties": {
    "gn:admin1_code":"7.0",
    "gn:asciiname":"Dianhuashan",
    "gn:country_code":"CN",
    "gn:dem":357,
    "gn:feature_class":"P",
    "gn:feature_code":"PPL",
    "gn:name":"Dianhuashan",
    "gn:population":0,
    "gn:timezone":"Asia/Shanghai",
    "iso:country":"CN",
    "name:zho_x_preferred":[
        "\u7535\u534e\u5c71"
    ],
    "wof:name":"Dianhuashan",
    "wof:placetype":"locality"
},
  "geometry": {"coordinates":[117.61405000000001,27.3519],"type":"Point"}
}