{
  "type": "Feature",
  "properties": {
    "gn:admin1_code":"24.0",
    "gn:asciiname":"Wangguocun",
    "gn:country_code":"CN",
    "gn:dem":738,
    "gn:feature_class":"P",
    "gn:feature_code":"PPL",
    "gn:name":"Wangguocun",
    "gn:population":0,
    "gn:timezone":"Asia/Shanghai",
    "iso:country":"CN",
    "name:zho_x_preferred":[
        "\u738b\u90ed\u6751"
    ],
    "wof:name":"Wangguocun",
    "wof:placetype":"locality"
},
  "geometry": {"coordinates":[112.0531,37.19944],"type":"Point"}
}