{
  "type": "Feature",
  "properties": {
    "gn:admin1_code":"02",
    "gn:asciiname":"Jieyucun",
    "gn:country_code":"CN",
    "gn:dem":9,
    "gn:feature_class":"P",
    "gn:feature_code":"PPL",
    "gn:name":"Jieyucun",
    "gn:population":0,
    "gn:timezone":"Asia/Shanghai",
    "iso:country":"CN",
    "name:und_x_variant":[
        "Jieyu"
    ],
    "name:zho_x_preferred":[
        "\u754c\u5c7f\u6751"
    ],
    "wof:name":"Jieyucun",
    "wof:placetype":"locality"
},
  "geometry": {"coordinates":[121.03198999999999,28.24787],"type":"Point"}
}