{
  "type": "Feature",
  "properties": {
    "gn:admin1_code":"33.0",
    "gn:asciiname":"Louziping",
    "gn:country_code":"CN",
    "gn:dem":1214,
    "gn:feature_class":"P",
    "gn:feature_code":"PPL",
    "gn:name":"Louziping",
    "gn:population":0,
    "gn:timezone":"Asia/Shanghai",
    "iso:country":"CN",
    "name:zho_x_preferred":[
        "\u697c\u5b50\u576a"
    ],
    "wof:name":"Louziping",
    "wof:placetype":"locality"
},
  "geometry": {"coordinates":[109.79712000000001,31.01488],"type":"Point"}
}