{
  "type": "Feature",
  "properties": {
    "gn:admin1_code":"7.0",
    "gn:asciiname":"Kushan",
    "gn:country_code":"CN",
    "gn:dem":349,
    "gn:feature_class":"P",
    "gn:feature_code":"PPL",
    "gn:name":"Kushan",
    "gn:population":0,
    "gn:timezone":"Asia/Shanghai",
    "iso:country":"CN",
    "name:zho_x_preferred":[
        "\u5e93\u5c71"
    ],
    "wof:name":"Kushan",
    "wof:placetype":"locality"
},
  "geometry": {"coordinates":[119.32511,26.87792],"type":"Point"}
}