{
  "type": "Feature",
  "properties": {
    "gn:admin1_code":"16",
    "gn:asciiname":"Lianhua",
    "gn:country_code":"CN",
    "gn:dem":159,
    "gn:feature_class":"P",
    "gn:feature_code":"PPL",
    "gn:name":"Lianhua",
    "gn:population":0,
    "gn:timezone":"Asia/Shanghai",
    "iso:country":"CN",
    "name:ceb_x_preferred":[
        "Lianhua"
    ],
    "name:deu_x_preferred":[
        "Lianhua"
    ],
    "name:nor_x_preferred":[
        "Lianhua"
    ],
    "name:zho_x_preferred":[
        "\u83b2\u82b1"
    ],
    "wof:name":"Lianhua",
    "wof:placetype":"locality"
},
  "geometry": {"coordinates":[110.246,25.3131],"type":"Point"}
}