{
  "type": "Feature",
  "properties": {
    "gn:admin1_code":"11.0",
    "gn:asciiname":"Zhushanwan",
    "gn:country_code":"CN",
    "gn:dem":76,
    "gn:feature_class":"P",
    "gn:feature_code":"PPL",
    "gn:name":"Zhushanwan",
    "gn:population":0,
    "gn:timezone":"Asia/Shanghai",
    "iso:country":"CN",
    "name:zho_x_preferred":[
        "\u7af9\u5c71\u6e7e"
    ],
    "wof:name":"Zhushanwan",
    "wof:placetype":"locality"
},
  "geometry": {"coordinates":[112.86781999999999,26.52959],"type":"Point"}
}