{
  "type": "Feature",
  "properties": {
    "gn:admin1_code":"7",
    "gn:asciiname":"Shangzhai",
    "gn:country_code":"CN",
    "gn:dem":460,
    "gn:feature_class":"P",
    "gn:feature_code":"PPL",
    "gn:name":"Shangzhai",
    "gn:population":0,
    "gn:timezone":"Asia/Shanghai",
    "iso:country":"CN",
    "name:und_x_variant":[
        "\u4e0a\u5b85",
        "Shangzhai"
    ],
    "wof:name":"Shangzhai",
    "wof:placetype":"locality"
},
  "geometry": {"coordinates":[119.84511000000001,27.31416],"type":"Point"}
}