{
  "type": "Feature",
  "properties": {
    "gn:admin1_code":"7.0",
    "gn:asciiname":"Chengongduan",
    "gn:country_code":"CN",
    "gn:dem":511,
    "gn:feature_class":"P",
    "gn:feature_code":"PPL",
    "gn:name":"Chengongduan",
    "gn:population":0,
    "gn:timezone":"Asia/Shanghai",
    "iso:country":"CN",
    "name:und_x_variant":[
        "\u9648\u516c\u5845"
    ],
    "wof:name":"Chengongduan",
    "wof:placetype":"locality"
},
  "geometry": {"coordinates":[116.52752,26.05861],"type":"Point"}
}