{
  "type": "Feature",
  "properties": {
    "gn:admin1_code":"9.0",
    "gn:asciiname":"Hepo",
    "gn:country_code":"CN",
    "gn:dem":206,
    "gn:feature_class":"P",
    "gn:feature_code":"PPL",
    "gn:name":"Hepo",
    "gn:population":0,
    "gn:timezone":"Asia/Shanghai",
    "iso:country":"CN",
    "name:und_x_variant":[
        "\u6cb3\u5761",
        "Hepo"
    ],
    "wof:name":"Hepo",
    "wof:placetype":"locality"
},
  "geometry": {"coordinates":[112.99778999999999,33.36541],"type":"Point"}
}