{
  "type": "Feature",
  "properties": {
    "gn:admin1_code":"19.0",
    "gn:asciiname":"Shawogou",
    "gn:country_code":"CN",
    "gn:dem":144,
    "gn:feature_class":"P",
    "gn:feature_code":"PPL",
    "gn:name":"Shawogou",
    "gn:population":0,
    "gn:timezone":"Asia/Shanghai",
    "iso:country":"CN",
    "name:zho_x_preferred":[
        "\u6c99\u7a9d\u6c9f"
    ],
    "wof:name":"Shawogou",
    "wof:placetype":"locality"
},
  "geometry": {"coordinates":[125.41678,40.73905],"type":"Point"}
}