{
  "type": "Feature",
  "properties": {
    "gn:admin1_code":"18.0",
    "gn:asciiname":"Lueguo",
    "gn:country_code":"CN",
    "gn:dem":860,
    "gn:feature_class":"P",
    "gn:feature_code":"PPL",
    "gn:name":"Lueguo",
    "gn:population":0,
    "gn:timezone":"Asia/Shanghai",
    "iso:country":"CN",
    "name:zho_x_preferred":[
        "\u7565\u679c"
    ],
    "wof:name":"Lueguo",
    "wof:placetype":"locality"
},
  "geometry": {"coordinates":[108.068,26.2417],"type":"Point"}
}