{
  "type": "Feature",
  "properties": {
    "gn:admin1_code":"2.0",
    "gn:asciiname":"Zhong'ao",
    "gn:country_code":"CN",
    "gn:dem":7,
    "gn:feature_class":"P",
    "gn:feature_code":"PPL",
    "gn:name":"Zhong\u2019ao",
    "gn:population":0,
    "gn:timezone":"Asia/Shanghai",
    "iso:country":"CN",
    "name:und_x_variant":[
        "Zhong\u2019ao"
    ],
    "name:zho_x_preferred":[
        "\u4e2d\u5c99"
    ],
    "wof:name":"Zhong'ao",
    "wof:placetype":"locality"
},
  "geometry": {"coordinates":[121.47302000000001,28.4097],"type":"Point"}
}