{
  "type": "Feature",
  "properties": {
    "gn:admin1_code":"29.0",
    "gn:asciiname":"Ercengyan",
    "gn:country_code":"CN",
    "gn:dem":1089,
    "gn:feature_class":"P",
    "gn:feature_code":"PPL",
    "gn:name":"Ercengyan",
    "gn:population":0,
    "gn:timezone":"Asia/Shanghai",
    "iso:country":"CN",
    "name:zho_x_preferred":[
        "\u4e8c\u5c42\u5ca9"
    ],
    "wof:name":"Ercengyan",
    "wof:placetype":"locality"
},
  "geometry": {"coordinates":[105.218,27.7072],"type":"Point"}
}