{
  "type": "Feature",
  "properties": {
    "gn:admin1_code":"32.0",
    "gn:asciiname":"Chahekou",
    "gn:country_code":"CN",
    "gn:dem":351,
    "gn:feature_class":"P",
    "gn:feature_code":"PPL",
    "gn:name":"Chahekou",
    "gn:population":0,
    "gn:timezone":"Asia/Shanghai",
    "iso:country":"CN",
    "name:zho_x_preferred":[
        "\u53c9\u6cb3\u53e3"
    ],
    "wof:name":"Chahekou",
    "wof:placetype":"locality"
},
  "geometry": {"coordinates":[107.15786,30.34208],"type":"Point"}
}