{
  "type": "Feature",
  "properties": {
    "gn:admin1_code":"11.0",
    "gn:asciiname":"Lilaowu",
    "gn:country_code":"CN",
    "gn:dem":76,
    "gn:feature_class":"P",
    "gn:feature_code":"PPL",
    "gn:name":"Lilaowu",
    "gn:population":0,
    "gn:timezone":"Asia/Shanghai",
    "iso:country":"CN",
    "name:zho_x_preferred":[
        "\u674e\u8001\u5c4b"
    ],
    "wof:name":"Lilaowu",
    "wof:placetype":"locality"
},
  "geometry": {"coordinates":[112.55925000000001,26.84923],"type":"Point"}
}