{
  "type": "Feature",
  "properties": {
    "gn:admin1_code":"8.0",
    "gn:asciiname":"Nangang",
    "gn:country_code":"CN",
    "gn:dem":152,
    "gn:feature_class":"P",
    "gn:feature_code":"PPL",
    "gn:name":"Nangang",
    "gn:population":0,
    "gn:timezone":"Asia/Shanghai",
    "iso:country":"CN",
    "name:ceb_x_preferred":[
        "Nangang"
    ],
    "name:deu_x_preferred":[
        "Nangang"
    ],
    "name:eus_x_preferred":[
        "Nangang"
    ],
    "name:fra_x_preferred":[
        "Nangang"
    ],
    "name:kor_x_preferred":[
        "\ub09c\uac15\uad6c"
    ],
    "name:nor_x_preferred":[
        "Nangang"
    ],
    "name:sco_x_preferred":[
        "Nangang"
    ],
    "name:swe_x_preferred":[
        "Nangang"
    ],
    "name:zho_x_preferred":[
        "\u5357\u5c97"
    ],
    "wof:name":"Nangang",
    "wof:placetype":"locality"
},
  "geometry": {"coordinates":[124.53028,47.28293],"type":"Point"}
}