{
  "type": "Feature",
  "properties": {
    "gn:admin1_code":"24.0",
    "gn:asciiname":"Xizhuanggeta",
    "gn:country_code":"CN",
    "gn:dem":966,
    "gn:feature_class":"P",
    "gn:feature_code":"PPL",
    "gn:name":"Xizhuanggeta",
    "gn:population":0,
    "gn:timezone":"Asia/Shanghai",
    "iso:country":"CN",
    "name:zho_x_preferred":[
        "\u897f\u5e84\u572a\u5854"
    ],
    "wof:name":"Xizhuanggeta",
    "wof:placetype":"locality"
},
  "geometry": {"coordinates":[110.48381999999999,36.70327],"type":"Point"}
}