{
  "type": "Feature",
  "properties": {
    "gn:admin1_code":"11.0",
    "gn:asciiname":"Wangmaotian",
    "gn:country_code":"CN",
    "gn:dem":262,
    "gn:feature_class":"P",
    "gn:feature_code":"PPL",
    "gn:name":"Wangmaotian",
    "gn:population":0,
    "gn:timezone":"Asia/Shanghai",
    "iso:country":"CN",
    "name:zho_x_preferred":[
        "\u738b\u6bdb\u7530"
    ],
    "wof:name":"Wangmaotian",
    "wof:placetype":"locality"
},
  "geometry": {"coordinates":[109.71199,28.24969],"type":"Point"}
}