{
  "type": "Feature",
  "properties": {
    "gn:admin1_code":"4.0",
    "gn:asciiname":"Wangfucun",
    "gn:country_code":"CN",
    "gn:dem":3,
    "gn:feature_class":"P",
    "gn:feature_code":"PPL",
    "gn:name":"Wangfucun",
    "gn:population":0,
    "gn:timezone":"Asia/Shanghai",
    "iso:country":"CN",
    "name:zho_x_preferred":[
        "\u738b\u4ed8\u6751"
    ],
    "wof:name":"Wangfucun",
    "wof:placetype":"locality"
},
  "geometry": {"coordinates":[119.18628,34.47748],"type":"Point"}
}