{
  "type": "Feature",
  "properties": {
    "gn:admin1_code":"8.0",
    "gn:asciiname":"Bayancun",
    "gn:country_code":"CN",
    "gn:dem":127,
    "gn:feature_class":"P",
    "gn:feature_code":"PPL",
    "gn:name":"Bayancun",
    "gn:population":0,
    "gn:timezone":"Asia/Shanghai",
    "iso:country":"CN",
    "name:zho_x_preferred":[
        "\u5df4\u5f66\u6751"
    ],
    "wof:name":"Bayancun",
    "wof:placetype":"locality"
},
  "geometry": {"coordinates":[124.16576000000001,45.75466],"type":"Point"}
}