{
  "type": "Feature",
  "properties": {
    "gn:admin1_code":"29.0",
    "gn:asciiname":"Zhuangzihe",
    "gn:country_code":"CN",
    "gn:dem":1305,
    "gn:feature_class":"P",
    "gn:feature_code":"PPL",
    "gn:name":"Zhuangzihe",
    "gn:population":0,
    "gn:timezone":"Asia/Shanghai",
    "iso:country":"CN",
    "name:zho_x_preferred":[
        "\u5e84\u5b50\u6cb3"
    ],
    "wof:name":"Zhuangzihe",
    "wof:placetype":"locality"
},
  "geometry": {"coordinates":[102.88800000000001,23.6417],"type":"Point"}
}