{
  "type": "Feature",
  "properties": {
    "gn:country":"CN",
    "gn:fcode":"ADM3",
    "gn:pop":0,
    "iso:country":"CN",
    "name:unk_x_variant":[
        "Chen-feng Puyi-Miao Autonomous Hsien"
    ],
    "name:zho_x_preferred":[
        "\u8d1e\u4e30\u53bf"
    ],
    "name:zho_x_variant":[
        "\u8d1e\u4e30"
    ],
    "qs:name":"Zhenfeng Xian",
    "qs:photos_9r":0,
    "qs:photos_sr":0,
    "qs:pop_sr":"0",
    "wof:name":"Zhenfeng Xian",
    "wof:placetype":"localadmin",
    "wof:population":0
},
  "geometry": {"coordinates":[105.6417,25.4549],"type":"Point"}
}