{
  "type": "Feature",
  "properties": {
    "gn:admin1_code":"1.0",
    "gn:asciiname":"Sanpucun",
    "gn:country_code":"CN",
    "gn:dem":48,
    "gn:feature_class":"P",
    "gn:feature_code":"PPL",
    "gn:name":"Sanpucun",
    "gn:population":0,
    "gn:timezone":"Asia/Shanghai",
    "iso:country":"CN",
    "name:zho_x_preferred":[
        "\u4e09\u94fa\u6751"
    ],
    "wof:name":"Sanpucun",
    "wof:placetype":"locality"
},
  "geometry": {"coordinates":[116.74418,30.65593],"type":"Point"}
}