{
  "type": "Feature",
  "properties": {
    "gn:admin1_code":"8.0",
    "gn:asciiname":"Qiufengcun",
    "gn:country_code":"CN",
    "gn:dem":198,
    "gn:feature_class":"P",
    "gn:feature_code":"PPL",
    "gn:name":"Qiufengcun",
    "gn:population":0,
    "gn:timezone":"Asia/Shanghai",
    "iso:country":"CN",
    "name:zho_x_preferred":[
        "\u79cb\u4e30\u6751"
    ],
    "wof:name":"Qiufengcun",
    "wof:placetype":"locality"
},
  "geometry": {"coordinates":[130.64600000000002,46.43301],"type":"Point"}
}