{
  "type": "Feature",
  "properties": {
    "gn:admin1_code":"29.0",
    "gn:asciiname":"Manmai",
    "gn:country_code":"CN",
    "gn:dem":1080,
    "gn:feature_class":"P",
    "gn:feature_code":"PPL",
    "gn:name":"Manmai",
    "gn:population":0,
    "gn:timezone":"Asia/Shanghai",
    "iso:country":"CN",
    "name:zho_x_preferred":[
        "\u66fc\u8fc8"
    ],
    "wof:name":"Manmai",
    "wof:placetype":"locality"
},
  "geometry": {"coordinates":[100.34,22.1397],"type":"Point"}
}