{
  "type": "Feature",
  "properties": {
    "gn:admin1_code":"30",
    "gn:asciiname":"Lichangdui",
    "gn:country_code":"CN",
    "gn:dem":54,
    "gn:feature_class":"P",
    "gn:feature_code":"PPLF",
    "gn:name":"Lichangdui",
    "gn:population":0,
    "gn:timezone":"Asia/Urumqi",
    "iso:country":"CN",
    "name:zho_x_preferred":[
        "\u91cc\u573a\u961f"
    ],
    "wof:name":"Lichangdui",
    "wof:placetype":"locality"
},
  "geometry": {"coordinates":[110.19937,21.20806],"type":"Point"}
}