{
  "type": "Feature",
  "properties": {
    "gn:admin1_code":"4.0",
    "gn:asciiname":"Macaoyang",
    "gn:country_code":"CN",
    "gn:dem":3,
    "gn:feature_class":"P",
    "gn:feature_code":"PPL",
    "gn:name":"Macaoyang",
    "gn:population":0,
    "gn:timezone":"Asia/Shanghai",
    "iso:country":"CN",
    "name:zho_x_preferred":[
        "\u9a6c\u8349\u7f8a"
    ],
    "wof:name":"Macaoyang",
    "wof:placetype":"locality"
},
  "geometry": {"coordinates":[119.85953000000001,32.94011],"type":"Point"}
}