{
  "type": "Feature",
  "properties": {
    "gn:admin1_code":"4.0",
    "gn:asciiname":"Dayu Jiadai",
    "gn:country_code":"CN",
    "gn:dem":1,
    "gn:feature_class":"P",
    "gn:feature_code":"PPL",
    "gn:name":"Dayu Jiadai",
    "gn:population":0,
    "gn:timezone":"Asia/Shanghai",
    "iso:country":"CN",
    "name:zho_x_preferred":[
        "\u5927\u4e8e\u5bb6\u5788"
    ],
    "wof:name":"Dayu Jiadai",
    "wof:placetype":"locality"
},
  "geometry": {"coordinates":[120.30155000000001,32.07941],"type":"Point"}
}