{
  "type": "Feature",
  "properties": {
    "gn:admin1_code":"32.0",
    "gn:asciiname":"Jiebaoshan",
    "gn:country_code":"CN",
    "gn:dem":943,
    "gn:feature_class":"P",
    "gn:feature_code":"PPL",
    "gn:name":"Jiebaoshan",
    "gn:population":0,
    "gn:timezone":"Asia/Shanghai",
    "iso:country":"CN",
    "name:zho_x_preferred":[
        "\u7ed3\u5b9d\u5c71"
    ],
    "wof:name":"Jiebaoshan",
    "wof:placetype":"locality"
},
  "geometry": {"coordinates":[105.33941000000002,28.32287],"type":"Point"}
}