{
  "type": "Feature",
  "properties": {
    "gn:admin1_code":"33.0",
    "gn:asciiname":"Baihelinwan",
    "gn:country_code":"CN",
    "gn:dem":378,
    "gn:feature_class":"P",
    "gn:feature_code":"PPL",
    "gn:name":"Baihelinwan",
    "gn:population":0,
    "gn:timezone":"Asia/Shanghai",
    "iso:country":"CN",
    "name:zho_x_preferred":[
        "\u767d\u9e64\u6797\u6e7e"
    ],
    "wof:name":"Baihelinwan",
    "wof:placetype":"locality"
},
  "geometry": {"coordinates":[107.21792000000001,30.02332],"type":"Point"}
}