{
  "type": "Feature",
  "properties": {
    "gn:admin1_code":"31.0",
    "gn:asciiname":"Shangtongtian",
    "gn:country_code":"CN",
    "gn:dem":11,
    "gn:feature_class":"P",
    "gn:feature_code":"PPL",
    "gn:name":"Shangtongtian",
    "gn:population":0,
    "gn:timezone":"Asia/Shanghai",
    "iso:country":"CN",
    "name:zho_x_preferred":[
        "\u4e0a\u901a\u5929"
    ],
    "wof:name":"Shangtongtian",
    "wof:placetype":"locality"
},
  "geometry": {"coordinates":[108.66811,18.97842],"type":"Point"}
}