{
  "type": "Feature",
  "properties": {
    "gn:admin1_code":"16.0",
    "gn:asciiname":"Yangmeijie",
    "gn:country_code":"CN",
    "gn:dem":113,
    "gn:feature_class":"P",
    "gn:feature_code":"PPL",
    "gn:name":"Yangmeijie",
    "gn:population":0,
    "gn:timezone":"Asia/Shanghai",
    "iso:country":"CN",
    "name:zho_x_preferred":[
        "\u6768\u6885\u8857"
    ],
    "wof:name":"Yangmeijie",
    "wof:placetype":"locality"
},
  "geometry": {"coordinates":[110.64100000000001,22.6958],"type":"Point"}
}