{
  "type": "Feature",
  "properties": {
    "gn:admin1_code":"15.0",
    "gn:asciiname":"Zhangyang",
    "gn:country_code":"CN",
    "gn:dem":1876,
    "gn:feature_class":"P",
    "gn:feature_code":"PPL",
    "gn:name":"Zhangyang",
    "gn:population":0,
    "gn:timezone":"Asia/Shanghai",
    "iso:country":"CN",
    "name:und_x_variant":[
        "\u5f20\u9633"
    ],
    "wof:name":"Zhangyang",
    "wof:placetype":"locality"
},
  "geometry": {"coordinates":[105.47983000000001,35.36975],"type":"Point"}
}