{
  "type": "Feature",
  "properties": {
    "gn:admin1_code":"26",
    "gn:asciiname":"Tongrenzhuang",
    "gn:country_code":"CN",
    "gn:dem":371,
    "gn:feature_class":"P",
    "gn:feature_code":"PPL",
    "gn:name":"Tongrenzhuang",
    "gn:population":0,
    "gn:timezone":"Asia/Shanghai",
    "iso:country":"CN",
    "name:und_x_variant":[
        "\u540c\u4ec1\u5e84"
    ],
    "name:zho_x_preferred":[
        "\u540c\u4ec1\u5e84"
    ],
    "wof:name":"Tongrenzhuang",
    "wof:placetype":"locality"
},
  "geometry": {"coordinates":[108.93861,34.43111],"type":"Point"}
}