{
  "type": "Feature",
  "properties": {
    "gn:admin1_code":"4.0",
    "gn:asciiname":"Daiwan",
    "gn:country_code":"CN",
    "gn:dem":6,
    "gn:feature_class":"P",
    "gn:feature_code":"PPL",
    "gn:name":"Daiwan",
    "gn:population":0,
    "gn:timezone":"Asia/Shanghai",
    "iso:country":"CN",
    "name:zho_x_preferred":[
        "\u5788\u6e7e"
    ],
    "wof:name":"Daiwan",
    "wof:placetype":"locality"
},
  "geometry": {"coordinates":[120.29931999999999,32.20328],"type":"Point"}
}