{
  "type": "Feature",
  "properties": {
    "gn:admin1_code":"11",
    "gn:asciiname":"Baiyangtian",
    "gn:cc2":"CN",
    "gn:country_code":"CN",
    "gn:dem":77,
    "gn:feature_class":"P",
    "gn:feature_code":"PPL",
    "gn:name":"Baiyangtian",
    "gn:population":0,
    "gn:timezone":"Asia/Shanghai",
    "iso:country":"CN",
    "name:und_x_variant":[
        "Pai-yang-t\u2019ien",
        "Baiyangtian"
    ],
    "wof:name":"Baiyangtian",
    "wof:placetype":"locality"
},
  "geometry": {"coordinates":[113.40667000000001,29.22528],"type":"Point"}
}