{
  "type": "Feature",
  "properties": {
    "gn:admin1_code":"29",
    "gn:asciiname":"Yadancun",
    "gn:country_code":"CN",
    "gn:dem":1777,
    "gn:feature_class":"P",
    "gn:feature_code":"PPL",
    "gn:name":"Yadancun",
    "gn:population":0,
    "gn:timezone":"Asia/Shanghai",
    "iso:country":"CN",
    "name:zho_x_preferred":[
        "\u9e2d\u86cb\u6751"
    ],
    "wof:name":"Yadancun",
    "wof:placetype":"locality"
},
  "geometry": {"coordinates":[102.97899,24.4539],"type":"Point"}
}