{
  "type": "Feature",
  "properties": {
    "gn:admin1_code":"26.0",
    "gn:asciiname":"Yuanpingcun",
    "gn:country_code":"CN",
    "gn:dem":1123,
    "gn:feature_class":"P",
    "gn:feature_code":"PPL",
    "gn:name":"Yuanpingcun",
    "gn:population":0,
    "gn:timezone":"Asia/Shanghai",
    "iso:country":"CN",
    "name:zho_x_preferred":[
        "\u5143\u576a\u6751"
    ],
    "wof:name":"Yuanpingcun",
    "wof:placetype":"locality"
},
  "geometry": {"coordinates":[109.28588000000001,37.86917],"type":"Point"}
}