{
  "type": "Feature",
  "properties": {
    "gn:admin1_code":"25",
    "gn:asciiname":"Jiahutong",
    "gn:country_code":"CN",
    "gn:dem":55,
    "gn:feature_class":"P",
    "gn:feature_code":"PPL",
    "gn:name":"Jiahutong",
    "gn:population":0,
    "gn:timezone":"Asia/Shanghai",
    "iso:country":"CN",
    "name:zho_x_preferred":[
        "\u8d3e\u80e1\u540c"
    ],
    "wof:name":"Jiahutong",
    "wof:placetype":"locality"
},
  "geometry": {"coordinates":[115.414,35.3315],"type":"Point"}
}