{
  "type": "Feature",
  "properties": {
    "gn:admin1_code":"32.0",
    "gn:asciiname":"Tongling",
    "gn:country_code":"CN",
    "gn:dem":388,
    "gn:feature_class":"P",
    "gn:feature_code":"PPL",
    "gn:name":"Tongling",
    "gn:population":0,
    "gn:timezone":"Asia/Shanghai",
    "iso:country":"CN",
    "name:zho_x_preferred":[
        "\u94dc\u94c3"
    ],
    "wof:name":"Tongling",
    "wof:placetype":"locality"
},
  "geometry": {"coordinates":[104.283,30.0964],"type":"Point"}
}