{
  "type": "Feature",
  "properties": {
    "gn:admin1_code":"32.0",
    "gn:asciiname":"Tongling",
    "gn:country_code":"CN",
    "gn:dem":388,
    "gn:feature_class":"P",
    "gn:feature_code":"PPL",
    "gn:name":"Tongling",
    "gn:population":0,
    "gn:timezone":"Asia/Shanghai",
    "iso:country":"CN",
    "name:ara_x_preferred":[
        "\u062a\u0648\u0646\u063a\u0644\u064a\u0646\u063a"
    ],
    "name:bul_x_preferred":[
        "\u0422\u0443\u043d\u043b\u0438\u043d"
    ],
    "name:cdo_x_preferred":[
        "D\u00e8\u0324ng-l\u00ecng"
    ],
    "name:ces_x_preferred":[
        "Tchung-ling"
    ],
    "name:cym_x_preferred":[
        "Tongling"
    ],
    "name:dan_x_preferred":[
        "Tongling"
    ],
    "name:deu_x_preferred":[
        "Tongling"
    ],
    "name:epo_x_preferred":[
        "Tonglingo"
    ],
    "name:eus_x_preferred":[
        "Tongling"
    ],
    "name:fas_x_preferred":[
        "\u062a\u0627\u0646\u06af\u0644\u06cc\u0646\u06af"
    ],
    "name:fin_x_preferred":[
        "Tongling"
    ],
    "name:fra_x_preferred":[
        "Tongling"
    ],
    "name:hye_x_preferred":[
        "\u054f\u0578\u0582\u0576\u056c\u056b\u0576"
    ],
    "name:ita_x_preferred":[
        "Tongling"
    ],
    "name:jpn_x_preferred":[
        "\u9285\u9675\u5e02"
    ],
    "name:kik_x_preferred":[
        "Tongling"
    ],
    "name:kor_x_preferred":[
        "\ud241\ub9c1\uc2dc"
    ],
    "name:mlg_x_preferred":[
        "Tongling"
    ],
    "name:nld_x_preferred":[
        "Tongling"
    ],
    "name:nno_x_preferred":[
        "Tongling"
    ],
    "name:nor_x_preferred":[
        "Tongling"
    ],
    "name:pam_x_preferred":[
        "Tongling"
    ],
    "name:pnb_x_preferred":[
        "\u062a\u0648\u0646\u06af \u0644\u06cc\u0646\u06af"
    ],
    "name:pol_x_preferred":[
        "Tongling"
    ],
    "name:por_x_preferred":[
        "Tongling"
    ],
    "name:rus_x_preferred":[
        "\u0422\u0443\u043d\u043b\u0438\u043d"
    ],
    "name:spa_x_preferred":[
        "Tongling"
    ],
    "name:srp_x_preferred":[
        "\u0422\u0443\u043d\u0433\u043b\u0438\u043d\u0433"
    ],
    "name:swe_x_preferred":[
        "Tongling"
    ],
    "name:tgl_x_preferred":[
        "Tongling"
    ],
    "name:tur_x_preferred":[
        "Tongling"
    ],
    "name:urd_x_preferred":[
        "\u062a\u0648\u0646\u06af\u0644\u0646\u06af"
    ],
    "name:vie_x_preferred":[
        "\u0110\u1ed3ng L\u0103ng"
    ],
    "name:war_x_preferred":[
        "Tongling"
    ],
    "name:wuu_x_preferred":[
        "\u94dc\u9675\u5e02"
    ],
    "name:zho_x_preferred":[
        "\u94dc\u94c3"
    ],
    "name:zho_x_variant":[
        "\u94dc\u9675\u5e02"
    ],
    "wof:name":"Tongling",
    "wof:placetype":"locality"
},
  "geometry": {"coordinates":[104.283,30.0964],"type":"Point"}
}