{
  "type": "Feature",
  "properties": {
    "gn:admin1_code":"12.0",
    "gn:asciiname":"Sujiatazi",
    "gn:country_code":"CN",
    "gn:dem":30,
    "gn:feature_class":"P",
    "gn:feature_code":"PPL",
    "gn:name":"Sujiatazi",
    "gn:population":0,
    "gn:timezone":"Asia/Shanghai",
    "iso:country":"CN",
    "name:zho_x_preferred":[
        "\u82cf\u5bb6\u5854\u5b50"
    ],
    "wof:name":"Sujiatazi",
    "wof:placetype":"locality"
},
  "geometry": {"coordinates":[113.96834,30.94538],"type":"Point"}
}