{
  "type": "Feature",
  "properties": {
    "gn:admin1_code":"09",
    "gn:asciiname":"Rangdong",
    "gn:cc2":"CN",
    "gn:country_code":"CN",
    "gn:dem":129,
    "gn:feature_class":"P",
    "gn:feature_code":"PPL",
    "gn:name":"Rangdong",
    "gn:population":0,
    "gn:timezone":"Asia/Shanghai",
    "iso:country":"CN",
    "name:und_x_variant":[
        "Jang-tung",
        "Rangdong"
    ],
    "wof:name":"Rangdong",
    "wof:placetype":"locality"
},
  "geometry": {"coordinates":[112.27889,32.8525],"type":"Point"}
}