{
  "type": "Feature",
  "properties": {
    "gn:admin1_code":"30.0",
    "gn:asciiname":"Dakengwei",
    "gn:country_code":"CN",
    "gn:dem":545,
    "gn:feature_class":"P",
    "gn:feature_code":"PPL",
    "gn:name":"Dakengwei",
    "gn:population":0,
    "gn:timezone":"Asia/Urumqi",
    "iso:country":"CN",
    "name:zho_x_preferred":[
        "\u5927\u5751\u5c3e"
    ],
    "wof:name":"Dakengwei",
    "wof:placetype":"locality"
},
  "geometry": {"coordinates":[111.20355000000001,22.49897],"type":"Point"}
}