{
  "type": "Feature",
  "properties": {
    "gn:admin1_code":"2.0",
    "gn:asciiname":"Shuangying",
    "gn:country_code":"CN",
    "gn:dem":133,
    "gn:feature_class":"P",
    "gn:feature_code":"PPL",
    "gn:name":"Shuangying",
    "gn:population":0,
    "gn:timezone":"Asia/Shanghai",
    "iso:country":"CN",
    "name:zho_x_preferred":[
        "\u53cc\u76c8"
    ],
    "wof:name":"Shuangying",
    "wof:placetype":"locality"
},
  "geometry": {"coordinates":[119.09220999999999,28.92093],"type":"Point"}
}