{
  "type": "Feature",
  "properties": {
    "gn:admin1_code":"1.0",
    "gn:asciiname":"Batucun",
    "gn:country_code":"CN",
    "gn:dem":10,
    "gn:feature_class":"P",
    "gn:feature_code":"PPL",
    "gn:name":"Batucun",
    "gn:population":0,
    "gn:timezone":"Asia/Shanghai",
    "iso:country":"CN",
    "name:zho_x_preferred":[
        "\u516b\u51f8\u6751"
    ],
    "wof:name":"Batucun",
    "wof:placetype":"locality"
},
  "geometry": {"coordinates":[118.27352999999999,31.28897000000001],"type":"Point"}
}