{
  "type": "Feature",
  "properties": {
    "gn:admin1_code":"26.0",
    "gn:asciiname":"Dabaishuliang",
    "gn:country_code":"CN",
    "gn:dem":1075,
    "gn:feature_class":"P",
    "gn:feature_code":"PPL",
    "gn:name":"Dabaishuliang",
    "gn:population":0,
    "gn:timezone":"Asia/Shanghai",
    "iso:country":"CN",
    "name:zho_x_preferred":[
        "\u5927\u67cf\u6811\u6881"
    ],
    "wof:name":"Dabaishuliang",
    "wof:placetype":"locality"
},
  "geometry": {"coordinates":[110.27974,38.40525],"type":"Point"}
}