{
  "type": "Feature",
  "properties": {
    "gn:admin1_code":"12.0",
    "gn:asciiname":"Xialiuwan",
    "gn:country_code":"CN",
    "gn:dem":134,
    "gn:feature_class":"P",
    "gn:feature_code":"PPL",
    "gn:name":"Xialiuwan",
    "gn:population":0,
    "gn:timezone":"Asia/Shanghai",
    "iso:country":"CN",
    "name:zho_x_preferred":[
        "\u4e0b\u5218\u6e7e"
    ],
    "wof:name":"Xialiuwan",
    "wof:placetype":"locality"
},
  "geometry": {"coordinates":[111.85548,32.25534],"type":"Point"}
}