{
  "type": "Feature",
  "properties": {
    "gn:admin1_code":"29",
    "gn:asciiname":"Yejiafang",
    "gn:country_code":"CN",
    "gn:dem":1609,
    "gn:feature_class":"P",
    "gn:feature_code":"PPL",
    "gn:name":"Yejiafang",
    "gn:population":0,
    "gn:timezone":"Asia/Shanghai",
    "iso:country":"CN",
    "name:zho_x_preferred":[
        "\u53f6\u5bb6\u623f"
    ],
    "wof:name":"Yejiafang",
    "wof:placetype":"locality"
},
  "geometry": {"coordinates":[102.15456,24.68148],"type":"Point"}
}