{
  "type": "Feature",
  "properties": {
    "gn:admin1_code":"11.0",
    "gn:asciiname":"Maziping",
    "gn:country_code":"CN",
    "gn:dem":232,
    "gn:feature_class":"P",
    "gn:feature_code":"PPL",
    "gn:name":"Maziping",
    "gn:population":0,
    "gn:timezone":"Asia/Shanghai",
    "iso:country":"CN",
    "name:zho_x_preferred":[
        "\u9ebb\u5b50\u576a"
    ],
    "wof:name":"Maziping",
    "wof:placetype":"locality"
},
  "geometry": {"coordinates":[113.68828000000001,27.20685],"type":"Point"}
}