{
  "type": "Feature",
  "properties": {
    "gn:admin1_code":"32.0",
    "gn:asciiname":"Hongxingnian",
    "gn:country_code":"CN",
    "gn:dem":357,
    "gn:feature_class":"P",
    "gn:feature_code":"PPL",
    "gn:name":"Hongxingnian",
    "gn:population":0,
    "gn:timezone":"Asia/Shanghai",
    "iso:country":"CN",
    "name:zho_x_preferred":[
        "\u7ea2\u661f\u57dd"
    ],
    "wof:name":"Hongxingnian",
    "wof:placetype":"locality"
},
  "geometry": {"coordinates":[104.83277,29.46505],"type":"Point"}
}