{
  "type": "Feature",
  "properties": {
    "gn:admin1_code":"8.0",
    "gn:asciiname":"Shiqicun Yidui",
    "gn:country_code":"CN",
    "gn:dem":181,
    "gn:feature_class":"P",
    "gn:feature_code":"PPLF",
    "gn:name":"Shiqicun Yidui",
    "gn:population":0,
    "gn:timezone":"Asia/Shanghai",
    "iso:country":"CN",
    "name:zho_x_preferred":[
        "\u5341\u4e03\u6751\u4e00\u961f"
    ],
    "wof:name":"Shiqicun Yidui",
    "wof:placetype":"locality"
},
  "geometry": {"coordinates":[123.04366,46.9207],"type":"Point"}
}