{
  "type": "Feature",
  "properties": {
    "gn:admin1_code":"10.0",
    "gn:asciiname":"Liguan Gezhuang",
    "gn:country_code":"CN",
    "gn:dem":41,
    "gn:feature_class":"P",
    "gn:feature_code":"PPL",
    "gn:name":"Liguan Gezhuang",
    "gn:population":0,
    "gn:timezone":"Asia/Shanghai",
    "iso:country":"CN",
    "name:zho_x_preferred":[
        "\u674e\u8d2f\u5404\u5e84"
    ],
    "wof:name":"Liguan Gezhuang",
    "wof:placetype":"locality"
},
  "geometry": {"coordinates":[118.94199999999999,39.77492],"type":"Point"}
}