{
  "type": "Feature",
  "properties": {
    "gn:admin1_code":"19.0",
    "gn:asciiname":"Gudonggangzi",
    "gn:country_code":"CN",
    "gn:dem":11,
    "gn:feature_class":"P",
    "gn:feature_code":"PPL",
    "gn:name":"Gudonggangzi",
    "gn:population":0,
    "gn:timezone":"Asia/Shanghai",
    "iso:country":"CN",
    "name:und_x_variant":[
        "\u53e4\u6d1e\u5c97\u5b50"
    ],
    "name:zho_x_preferred":[
        "\u53e4\u6d1e\u5c97\u5b50"
    ],
    "wof:name":"Gudonggangzi",
    "wof:placetype":"locality"
},
  "geometry": {"coordinates":[122.52191000000001,41.47271],"type":"Point"}
}