{
  "type": "Feature",
  "properties": {
    "gn:admin1_code":"32.0",
    "gn:asciiname":"Guoqianyan",
    "gn:country_code":"CN",
    "gn:dem":1940,
    "gn:feature_class":"P",
    "gn:feature_code":"PPL",
    "gn:name":"Guoqianyan",
    "gn:population":0,
    "gn:timezone":"Asia/Shanghai",
    "iso:country":"CN",
    "name:zho_x_preferred":[
        "\u9505\u5343\u5ca9"
    ],
    "wof:name":"Guoqianyan",
    "wof:placetype":"locality"
},
  "geometry": {"coordinates":[101.435,28.1243],"type":"Point"}
}