{
  "type": "Feature",
  "properties": {
    "gn:admin1_code":"11.0",
    "gn:asciiname":"Lutouling",
    "gn:country_code":"CN",
    "gn:dem":427,
    "gn:feature_class":"P",
    "gn:feature_code":"PPL",
    "gn:name":"Lutouling",
    "gn:population":0,
    "gn:timezone":"Asia/Shanghai",
    "iso:country":"CN",
    "name:zho_x_preferred":[
        "\u9c81\u5934\u5cad"
    ],
    "wof:name":"Lutouling",
    "wof:placetype":"locality"
},
  "geometry": {"coordinates":[112.5033,25.53552],"type":"Point"}
}