{
  "type": "Feature",
  "properties": {
    "gn:admin1_code":"32.0",
    "gn:asciiname":"Qiaoting",
    "gn:country_code":"CN",
    "gn:dem":770,
    "gn:feature_class":"P",
    "gn:feature_code":"PPLA4",
    "gn:name":"Qiaoting",
    "gn:population":0,
    "gn:timezone":"Asia/Shanghai",
    "iso:country":"CN",
    "name:und_x_variant":[
        "Qiaoting Xiang",
        "\u6865\u4ead\u4e61"
    ],
    "name:zho_x_preferred":[
        "\u6865\u4ead"
    ],
    "wof:name":"Qiaoting",
    "wof:placetype":"locality"
},
  "geometry": {"coordinates":[106.89823,32.46492],"type":"Point"}
}