{
  "type": "Feature",
  "properties": {
    "gn:admin1_code":"9.0",
    "gn:asciiname":"Dong'an Shangcun",
    "gn:country_code":"CN",
    "gn:dem":1356,
    "gn:feature_class":"P",
    "gn:feature_code":"PPL",
    "gn:name":"Dong\u2019an Shangcun",
    "gn:population":0,
    "gn:timezone":"Asia/Shanghai",
    "iso:country":"CN",
    "name:und_x_variant":[
        "Dong\u2019an Shangcun"
    ],
    "name:zho_x_preferred":[
        "\u4e1c\u5eb5\u4e0a\u6751"
    ],
    "wof:name":"Dong'an Shangcun",
    "wof:placetype":"locality"
},
  "geometry": {"coordinates":[111.53622,34.12813],"type":"Point"}
}