{
  "type": "Feature",
  "properties": {
    "gn:admin1_code":"16.0",
    "gn:asciiname":"Laotangdu",
    "gn:country_code":"CN",
    "gn:dem":160,
    "gn:feature_class":"P",
    "gn:feature_code":"PPL",
    "gn:name":"Laotangdu",
    "gn:population":0,
    "gn:timezone":"Asia/Shanghai",
    "iso:country":"CN",
    "name:zho_x_preferred":[
        "\u8001\u5858\u809a"
    ],
    "wof:name":"Laotangdu",
    "wof:placetype":"locality"
},
  "geometry": {"coordinates":[110.657,23.3393],"type":"Point"}
}