{
  "type": "Feature",
  "properties": {
    "gn:admin1_code":"4.0",
    "gn:asciiname":"Shimenguan",
    "gn:country_code":"CN",
    "gn:dem":44,
    "gn:feature_class":"P",
    "gn:feature_code":"PPL",
    "gn:name":"Shimenguan",
    "gn:population":0,
    "gn:timezone":"Asia/Shanghai",
    "iso:country":"CN",
    "name:und_x_variant":[
        "\u77f3\u95e8\u5173"
    ],
    "wof:name":"Shimenguan",
    "wof:placetype":"locality"
},
  "geometry": {"coordinates":[119.0258,32.00744],"type":"Point"}
}