{
  "type": "Feature",
  "properties": {
    "gn:admin1_code":"19.0",
    "gn:asciiname":"Potaizi",
    "gn:country_code":"CN",
    "gn:dem":86,
    "gn:feature_class":"P",
    "gn:feature_code":"PPL",
    "gn:name":"Potaizi",
    "gn:population":0,
    "gn:timezone":"Asia/Shanghai",
    "iso:country":"CN",
    "name:und_x_variant":[
        "\u7834\u53f0\u5b50"
    ],
    "wof:name":"Potaizi",
    "wof:placetype":"locality"
},
  "geometry": {"coordinates":[122.30176000000002,40.22266],"type":"Point"}
}