{
  "type": "Feature",
  "properties": {
    "gn:admin1_code":"29.0",
    "gn:asciiname":"Gaoliangdi",
    "gn:country_code":"CN",
    "gn:dem":1141,
    "gn:feature_class":"P",
    "gn:feature_code":"PPL",
    "gn:name":"Gaoliangdi",
    "gn:population":0,
    "gn:timezone":"Asia/Shanghai",
    "iso:country":"CN",
    "name:zho_x_preferred":[
        "\u9ad8\u6881\u5730"
    ],
    "wof:name":"Gaoliangdi",
    "wof:placetype":"locality"
},
  "geometry": {"coordinates":[101.03700000000001,24.1586],"type":"Point"}
}