{
  "type": "Feature",
  "properties": {
    "gn:admin1_code":"30.0",
    "gn:asciiname":"Lansha",
    "gn:country_code":"CN",
    "gn:dem":123,
    "gn:feature_class":"P",
    "gn:feature_code":"PPL",
    "gn:name":"Lansha",
    "gn:population":0,
    "gn:timezone":"Asia/Shanghai",
    "iso:country":"CN",
    "name:zho_x_preferred":[
        "\u84dd\u6c99"
    ],
    "wof:name":"Lansha",
    "wof:placetype":"locality"
},
  "geometry": {"coordinates":[113.9312,24.25609],"type":"Point"}
}