{
  "type": "Feature",
  "properties": {
    "gn:admin1_code":"24.0",
    "gn:asciiname":"Caogoucun",
    "gn:country_code":"CN",
    "gn:dem":1674,
    "gn:feature_class":"P",
    "gn:feature_code":"PPL",
    "gn:name":"Caogoucun",
    "gn:population":0,
    "gn:timezone":"Asia/Shanghai",
    "iso:country":"CN",
    "name:zho_x_preferred":[
        "\u8349\u6c9f\u6751"
    ],
    "wof:name":"Caogoucun",
    "wof:placetype":"locality"
},
  "geometry": {"coordinates":[114.38549,40.25377],"type":"Point"}
}