{
  "type": "Feature",
  "properties": {
    "gn:admin1_code":"5.0",
    "gn:asciiname":"Anlecun",
    "gn:country_code":"CN",
    "gn:dem":567,
    "gn:feature_class":"P",
    "gn:feature_code":"PPL",
    "gn:name":"Anlecun",
    "gn:population":0,
    "gn:timezone":"Asia/Shanghai",
    "iso:country":"CN",
    "name:und_x_variant":[
        "\u5b89\u4e86\u6751"
    ],
    "wof:name":"Anlecun",
    "wof:placetype":"locality"
},
  "geometry": {"coordinates":[127.85293,41.41203],"type":"Point"}
}