{
  "type": "Feature",
  "properties": {
    "gn:admin1_code":"3.0",
    "gn:asciiname":"Baishapo",
    "gn:country_code":"CN",
    "gn:dem":193,
    "gn:feature_class":"P",
    "gn:feature_code":"PPL",
    "gn:name":"Baishapo",
    "gn:population":0,
    "gn:timezone":"Asia/Shanghai",
    "iso:country":"CN",
    "name:und_x_variant":[
        "\u767d\u6c99\u5761"
    ],
    "wof:name":"Baishapo",
    "wof:placetype":"locality"
},
  "geometry": {"coordinates":[114.45569999999999,27.48493],"type":"Point"}
}