{
  "type": "Feature",
  "properties": {
    "gn:admin1_code":"26.0",
    "gn:asciiname":"Pizhikang",
    "gn:country_code":"CN",
    "gn:dem":769,
    "gn:feature_class":"P",
    "gn:feature_code":"PPL",
    "gn:name":"Pizhikang",
    "gn:population":0,
    "gn:timezone":"Asia/Shanghai",
    "iso:country":"CN",
    "name:zho_x_preferred":[
        "\u76ae\u7eb8\u7095"
    ],
    "wof:name":"Pizhikang",
    "wof:placetype":"locality"
},
  "geometry": {"coordinates":[110.31921,33.279],"type":"Point"}
}