{
  "type": "Feature",
  "properties": {
    "gn:admin1_code":"19.0",
    "gn:asciiname":"Jiataizi",
    "gn:country_code":"CN",
    "gn:dem":29,
    "gn:feature_class":"P",
    "gn:feature_code":"PPL",
    "gn:name":"Jiataizi",
    "gn:population":0,
    "gn:timezone":"Asia/Shanghai",
    "iso:country":"CN",
    "name:zho_x_preferred":[
        "\u5bb6\u53f0\u5b50"
    ],
    "wof:name":"Jiataizi",
    "wof:placetype":"locality"
},
  "geometry": {"coordinates":[122.22587,39.36324000000001],"type":"Point"}
}