{
  "type": "Feature",
  "properties": {
    "gn:admin1_code":"25",
    "gn:asciiname":"Ganlugou",
    "gn:country_code":"CN",
    "gn:dem":40,
    "gn:feature_class":"P",
    "gn:feature_code":"PPL",
    "gn:name":"Ganlugou",
    "gn:population":0,
    "gn:timezone":"Asia/Shanghai",
    "iso:country":"CN",
    "name:zho_x_preferred":[
        "\u7518\u9732\u6c9f"
    ],
    "wof:name":"Ganlugou",
    "wof:placetype":"locality"
},
  "geometry": {"coordinates":[117.739,34.7328],"type":"Point"}
}