{
  "type": "Feature",
  "properties": {
    "gn:admin1_code":"14.0",
    "gn:asciiname":"Reza",
    "gn:country_code":"CN",
    "gn:dem":4403,
    "gn:feature_class":"P",
    "gn:feature_code":"PPL",
    "gn:name":"Reza",
    "gn:population":0,
    "gn:timezone":"Asia/Urumqi",
    "iso:country":"CN",
    "name:deu_x_preferred":[
        "Reza"
    ],
    "name:fas_x_preferred":[
        "\u0631\u0636\u0627"
    ],
    "name:fra_x_preferred":[
        "Reza"
    ],
    "name:ind_x_preferred":[
        "Reza"
    ],
    "name:spa_x_preferred":[
        "Reza"
    ],
    "name:zho_x_preferred":[
        "\u70ed\u6742"
    ],
    "wof:name":"Reza",
    "wof:placetype":"locality"
},
  "geometry": {"coordinates":[86.9877,28.309],"type":"Point"}
}