{
  "type": "Feature",
  "properties": {
    "gn:admin1_code":"9.0",
    "gn:asciiname":"Manpo",
    "gn:country_code":"CN",
    "gn:dem":359,
    "gn:feature_class":"P",
    "gn:feature_code":"PPL",
    "gn:name":"Manpo",
    "gn:population":0,
    "gn:timezone":"Asia/Shanghai",
    "iso:country":"CN",
    "name:bul_x_preferred":[
        "\u041c\u0430\u043d\u043f\u0445\u043e"
    ],
    "name:ces_x_preferred":[
        "Manpcho"
    ],
    "name:epo_x_preferred":[
        "Manpo"
    ],
    "name:fas_x_preferred":[
        "\u0645\u0627\u0646\u067e\u0648"
    ],
    "name:fin_x_preferred":[
        "Manpo"
    ],
    "name:fra_x_preferred":[
        "Manpho"
    ],
    "name:hun_x_preferred":[
        "Manpho"
    ],
    "name:ita_x_preferred":[
        "Manp'o"
    ],
    "name:jpn_x_preferred":[
        "\u6e80\u6d66\u5e02"
    ],
    "name:kor_x_preferred":[
        "\ub9cc\ud3ec\uc2dc"
    ],
    "name:nld_x_preferred":[
        "Manpo"
    ],
    "name:nor_x_preferred":[
        "Manpo"
    ],
    "name:pol_x_preferred":[
        "Manp'o"
    ],
    "name:por_x_preferred":[
        "Manpo"
    ],
    "name:rus_x_preferred":[
        "\u041c\u0430\u043d\u043f\u0445\u043e"
    ],
    "name:swe_x_preferred":[
        "Manpo"
    ],
    "name:tur_x_preferred":[
        "Manpo"
    ],
    "name:urd_x_preferred":[
        "\u0645\u0627\u0646\u067e\u0648"
    ],
    "name:vie_x_preferred":[
        "Manpo"
    ],
    "name:wuu_x_preferred":[
        "\u6ee1\u6d66\u5e02"
    ],
    "name:zho_x_preferred":[
        "\u5881\u5761"
    ],
    "name:zho_x_variant":[
        "\u6eff\u6d66\u5e02"
    ],
    "wof:name":"Manpo",
    "wof:placetype":"locality"
},
  "geometry": {"coordinates":[113.79595999999999,35.9827],"type":"Point"}
}