{
  "type": "Feature",
  "properties": {
    "gn:admin1_code":"29.0",
    "gn:asciiname":"Tadeju",
    "gn:country_code":"CN",
    "gn:dem":2004,
    "gn:feature_class":"P",
    "gn:feature_code":"PPL",
    "gn:name":"Tadeju",
    "gn:population":0,
    "gn:timezone":"Asia/Shanghai",
    "iso:country":"CN",
    "name:zho_x_preferred":[
        "\u4ed6\u7684\u82f4"
    ],
    "wof:name":"Tadeju",
    "wof:placetype":"locality"
},
  "geometry": {"coordinates":[101.389,26.1218],"type":"Point"}
}