{
  "type": "Feature",
  "properties": {
    "gn:admin1_code":"15.0",
    "gn:asciiname":"Zeji",
    "gn:country_code":"CN",
    "gn:dem":2768,
    "gn:feature_class":"P",
    "gn:feature_code":"PPL",
    "gn:name":"Zeji",
    "gn:population":0,
    "gn:timezone":"Asia/Shanghai",
    "iso:country":"CN",
    "name:und_x_variant":[
        "\u5219\u5409"
    ],
    "wof:name":"Zeji",
    "wof:placetype":"locality"
},
  "geometry": {"coordinates":[103.7109,34.01736],"type":"Point"}
}