{
  "type": "Feature",
  "properties": {
    "gn:admin1_code":"16",
    "gn:asciiname":"Baizhi",
    "gn:country_code":"CN",
    "gn:dem":216,
    "gn:feature_class":"P",
    "gn:feature_code":"PPL",
    "gn:name":"Baizhi",
    "gn:population":0,
    "gn:timezone":"Asia/Shanghai",
    "iso:country":"CN",
    "name:zho_x_preferred":[
        "\u767d\u6307"
    ],
    "wof:name":"Baizhi",
    "wof:placetype":"locality"
},
  "geometry": {"coordinates":[109.57899999999999,25.4608],"type":"Point"}
}