{
  "type": "Feature",
  "properties": {
    "gn:admin1_code":"15.0",
    "gn:asciiname":"Guanjiawan",
    "gn:country_code":"CN",
    "gn:dem":1697,
    "gn:feature_class":"P",
    "gn:feature_code":"PPL",
    "gn:name":"Guanjiawan",
    "gn:population":0,
    "gn:timezone":"Asia/Shanghai",
    "iso:country":"CN",
    "name:zho_x_preferred":[
        "\u5173\u5bb6\u6e7e"
    ],
    "wof:name":"Guanjiawan",
    "wof:placetype":"locality"
},
  "geometry": {"coordinates":[105.077,36.1403],"type":"Point"}
}