{
  "type": "Feature",
  "properties": {
    "gn:admin1_code":"19.0",
    "gn:asciiname":"Xituanshanzi",
    "gn:country_code":"CN",
    "gn:dem":118,
    "gn:feature_class":"P",
    "gn:feature_code":"PPL",
    "gn:name":"Xituanshanzi",
    "gn:population":0,
    "gn:timezone":"Asia/Shanghai",
    "iso:country":"CN",
    "name:zho_x_preferred":[
        "\u897f\u56e2\u5c71\u5b50"
    ],
    "wof:name":"Xituanshanzi",
    "wof:placetype":"locality"
},
  "geometry": {"coordinates":[120.62018,41.03748],"type":"Point"}
}