{
  "type": "Feature",
  "properties": {
    "gn:admin1_code":"15.0",
    "gn:asciiname":"Xiagou",
    "gn:country_code":"CN",
    "gn:dem":1924,
    "gn:feature_class":"P",
    "gn:feature_code":"PPL",
    "gn:name":"Xiagou",
    "gn:population":0,
    "gn:timezone":"Asia/Shanghai",
    "iso:country":"CN",
    "name:zho_x_preferred":[
        "\u4e0b\u6c9f"
    ],
    "wof:name":"Xiagou",
    "wof:placetype":"locality"
},
  "geometry": {"coordinates":[103.777,35.6732],"type":"Point"}
}