{
  "type": "Feature",
  "properties": {
    "gn:admin1_code":"15.0",
    "gn:asciiname":"Shanggou",
    "gn:country_code":"CN",
    "gn:dem":1790,
    "gn:feature_class":"P",
    "gn:feature_code":"PPL",
    "gn:name":"Shanggou",
    "gn:population":0,
    "gn:timezone":"Asia/Shanghai",
    "iso:country":"CN",
    "name:und_x_variant":[
        "\u4e0a\u6c9f"
    ],
    "wof:name":"Shanggou",
    "wof:placetype":"locality"
},
  "geometry": {"coordinates":[104.76958999999999,34.84754],"type":"Point"}
}