{
  "type": "Feature",
  "properties": {
    "gn:admin1_code":"19.0",
    "gn:asciiname":"Shangguan Juenchang",
    "gn:country_code":"CN",
    "gn:dem":56,
    "gn:feature_class":"P",
    "gn:feature_code":"PPL",
    "gn:name":"Shangguan Juenchang",
    "gn:population":0,
    "gn:timezone":"Asia/Shanghai",
    "iso:country":"CN",
    "name:zho_x_preferred":[
        "\u4e0a\u89c2\u519b\u573a"
    ],
    "wof:name":"Shangguan Juenchang",
    "wof:placetype":"locality"
},
  "geometry": {"coordinates":[121.66013999999998,41.45796],"type":"Point"}
}