{
  "type": "Feature",
  "properties": {
    "gn:admin1_code":"2.0",
    "gn:asciiname":"Shangyuan",
    "gn:country_code":"CN",
    "gn:dem":247,
    "gn:feature_class":"P",
    "gn:feature_code":"PPL",
    "gn:name":"Shangyuan",
    "gn:population":0,
    "gn:timezone":"Asia/Shanghai",
    "iso:country":"CN",
    "name:zho_x_preferred":[
        "\u4e0a\u56ed"
    ],
    "name:zho_x_variant":[
        "\u4e0a\u5143"
    ],
    "wof:name":"Shangyuan",
    "wof:placetype":"locality"
},
  "geometry": {"coordinates":[119.9967,28.67501],"type":"Point"}
}