{
  "type": "Feature",
  "properties": {
    "gn:admin1_code":"26.0",
    "gn:asciiname":"Fashifencun",
    "gn:country_code":"CN",
    "gn:dem":552,
    "gn:feature_class":"P",
    "gn:feature_code":"PPL",
    "gn:name":"Fashifencun",
    "gn:population":0,
    "gn:timezone":"Asia/Shanghai",
    "iso:country":"CN",
    "name:und_x_variant":[
        "\u6cd5\u5e08\u575f\u6751"
    ],
    "wof:name":"Fashifencun",
    "wof:placetype":"locality"
},
  "geometry": {"coordinates":[107.58835999999999,33.15249],"type":"Point"}
}