{
  "type": "Feature",
  "properties": {
    "gn:admin1_code":"20.0",
    "gn:asciiname":"Wujingou",
    "gn:country_code":"CN",
    "gn:dem":1565,
    "gn:feature_class":"P",
    "gn:feature_code":"PPL",
    "gn:name":"Wujingou",
    "gn:population":0,
    "gn:timezone":"Asia/Shanghai",
    "iso:country":"CN",
    "name:und_x_variant":[
        "\u4e94\u91d1\u6c9f"
    ],
    "wof:name":"Wujingou",
    "wof:placetype":"locality"
},
  "geometry": {"coordinates":[110.0988,41.15925],"type":"Point"}
}