{
  "type": "Feature",
  "properties": {
    "gn:admin1_code":"25",
    "gn:asciiname":"Hualandian",
    "gn:cc2":"CN",
    "gn:country_code":"CN",
    "gn:dem":53,
    "gn:feature_class":"P",
    "gn:feature_code":"PPL",
    "gn:name":"Hualandian",
    "gn:population":0,
    "gn:timezone":"Asia/Shanghai",
    "iso:country":"CN",
    "name:und_x_variant":[
        "Hua-lan-tien",
        "Hualandian"
    ],
    "wof:name":"Hualandian",
    "wof:placetype":"locality"
},
  "geometry": {"coordinates":[116.33333,36.01667],"type":"Point"}
}