{
  "type": "Feature",
  "properties": {
    "gn:admin1_code":"18.0",
    "gn:asciiname":"Xiawangtai",
    "gn:country_code":"CN",
    "gn:dem":511,
    "gn:feature_class":"P",
    "gn:feature_code":"PPL",
    "gn:name":"Xiawangtai",
    "gn:population":0,
    "gn:timezone":"Asia/Shanghai",
    "iso:country":"CN",
    "name:zho_x_preferred":[
        "\u4e0b\u6c6a\u53f0"
    ],
    "wof:name":"Xiawangtai",
    "wof:placetype":"locality"
},
  "geometry": {"coordinates":[108.83499999999999,26.6005],"type":"Point"}
}