{
  "type": "Feature",
  "properties": {
    "gn:admin1_code":"4.0",
    "gn:asciiname":"Bianhu",
    "gn:country_code":"CN",
    "gn:dem":32,
    "gn:feature_class":"P",
    "gn:feature_code":"PPL",
    "gn:name":"Bianhu",
    "gn:population":0,
    "gn:timezone":"Asia/Shanghai",
    "iso:country":"CN",
    "name:zho_x_preferred":[
        "\u535e\u6e56"
    ],
    "name:zho_x_variant":[
        "\u7de8\u6236\u9f4a\u6c11"
    ],
    "wof:name":"Bianhu",
    "wof:placetype":"locality"
},
  "geometry": {"coordinates":[118.038,34.5854],"type":"Point"}
}