{
  "type": "Feature",
  "properties": {
    "gn:admin1_code":"9.0",
    "gn:asciiname":"Pogen",
    "gn:country_code":"CN",
    "gn:dem":538,
    "gn:feature_class":"P",
    "gn:feature_code":"PPL",
    "gn:name":"Pogen",
    "gn:population":0,
    "gn:timezone":"Asia/Shanghai",
    "iso:country":"CN",
    "name:und_x_variant":[
        "\u5761\u6839",
        "Pogen"
    ],
    "wof:name":"Pogen",
    "wof:placetype":"locality"
},
  "geometry": {"coordinates":[112.07826,33.47212],"type":"Point"}
}