{
  "type": "Feature",
  "properties": {
    "gn:admin1_code":"12.0",
    "gn:asciiname":"Niefujun",
    "gn:country_code":"CN",
    "gn:dem":21,
    "gn:feature_class":"P",
    "gn:feature_code":"PPL",
    "gn:name":"Niefujun",
    "gn:population":0,
    "gn:timezone":"Asia/Shanghai",
    "iso:country":"CN",
    "name:zho_x_preferred":[
        "\u8042\u798f\u4fca"
    ],
    "wof:name":"Niefujun",
    "wof:placetype":"locality"
},
  "geometry": {"coordinates":[115.83882,29.87592],"type":"Point"}
}