{
  "type": "Feature",
  "properties": {
    "gn:admin1_code":"29",
    "gn:asciiname":"Tumuji",
    "gn:country_code":"CN",
    "gn:dem":1906,
    "gn:feature_class":"P",
    "gn:feature_code":"PPL",
    "gn:name":"Tumuji",
    "gn:population":0,
    "gn:timezone":"Asia/Shanghai",
    "iso:country":"CN",
    "name:zho_x_preferred":[
        "\u571f\u6728\u57fa"
    ],
    "wof:name":"Tumuji",
    "wof:placetype":"locality"
},
  "geometry": {"coordinates":[103.339,24.5205],"type":"Point"}
}