{
  "type": "Feature",
  "properties": {
    "gn:admin1_code":"1.0",
    "gn:asciiname":"Chenzhaicun",
    "gn:country_code":"CN",
    "gn:dem":39,
    "gn:feature_class":"P",
    "gn:feature_code":"PPL",
    "gn:name":"Chenzhaicun",
    "gn:population":0,
    "gn:timezone":"Asia/Shanghai",
    "iso:country":"CN",
    "name:zho_x_preferred":[
        "\u9648\u5be8\u6751"
    ],
    "wof:name":"Chenzhaicun",
    "wof:placetype":"locality"
},
  "geometry": {"coordinates":[115.54688,33.28552],"type":"Point"}
}