{
  "type": "Feature",
  "properties": {
    "gn:country":"CN",
    "gn:fcode":"PPL",
    "gn:pop":41484,
    "iso:country":"CN",
    "name:unk_x_variant":[
        "Ku-yeh"
    ],
    "name:zho_x_preferred":[
        "\u53e4\u51b6"
    ],
    "qs:name":"Guye",
    "qs:photos_9r":0,
    "qs:photos_sr":0,
    "qs:pop_sr":"7",
    "wd:wordcount":47,
    "wof:name":"Guye",
    "wof:placetype":"locality",
    "wof:population":41484
},
  "geometry": {"coordinates":[118.41667,39.73333],"type":"Point"}
}