{
  "type": "Feature",
  "properties": {
    "gn:admin1_code":"29",
    "gn:asciiname":"Santangshui",
    "gn:country_code":"CN",
    "gn:dem":1266,
    "gn:feature_class":"P",
    "gn:feature_code":"PPL",
    "gn:name":"Santangshui",
    "gn:population":0,
    "gn:timezone":"Asia/Shanghai",
    "iso:country":"CN",
    "name:zho_x_preferred":[
        "\u4e09\u5858\u6c34"
    ],
    "wof:name":"Santangshui",
    "wof:placetype":"locality"
},
  "geometry": {"coordinates":[104.899,23.4637],"type":"Point"}
}