{
  "type": "Feature",
  "properties": {
    "gn:admin1_code":"33.0",
    "gn:asciiname":"Wuhu",
    "gn:country_code":"CN",
    "gn:dem":687,
    "gn:feature_class":"P",
    "gn:feature_code":"PPL",
    "gn:name":"Wuhu",
    "gn:population":0,
    "gn:timezone":"Asia/Shanghai",
    "iso:country":"CN",
    "name:zho_x_preferred":[
        "\u4e94\u6e56"
    ],
    "wof:name":"Wuhu",
    "wof:placetype":"locality"
},
  "geometry": {"coordinates":[108.47226999999999,31.01224],"type":"Point"}
}