{
  "type": "Feature",
  "properties": {
    "gn:admin1_code":"9.0",
    "gn:asciiname":"Nianpanzhuang",
    "gn:country_code":"CN",
    "gn:dem":231,
    "gn:feature_class":"P",
    "gn:feature_code":"PPL",
    "gn:name":"Nianpanzhuang",
    "gn:population":0,
    "gn:timezone":"Asia/Shanghai",
    "iso:country":"CN",
    "name:zho_x_preferred":[
        "\u78be\u76d8\u5e84"
    ],
    "wof:name":"Nianpanzhuang",
    "wof:placetype":"locality"
},
  "geometry": {"coordinates":[112.56344,33.48031],"type":"Point"}
}