{
  "type": "Feature",
  "properties": {
    "gn:admin1_code":"16.0",
    "gn:asciiname":"Dazhou",
    "gn:country_code":"CN",
    "gn:dem":407,
    "gn:feature_class":"P",
    "gn:feature_code":"PPL",
    "gn:name":"Dazhou",
    "gn:population":0,
    "gn:timezone":"Asia/Shanghai",
    "iso:country":"CN",
    "name:zho_x_preferred":[
        "\u5927\u6d32"
    ],
    "wof:name":"Dazhou",
    "wof:placetype":"locality"
},
  "geometry": {"coordinates":[109.154,25.1261],"type":"Point"}
}