{
  "type": "Feature",
  "properties": {
    "gn:admin1_code":"19.0",
    "gn:asciiname":"Fenghuotaicun",
    "gn:country_code":"CN",
    "gn:dem":25,
    "gn:feature_class":"P",
    "gn:feature_code":"PPL",
    "gn:name":"Fenghuotaicun",
    "gn:population":0,
    "gn:timezone":"Asia/Shanghai",
    "iso:country":"CN",
    "name:zho_x_preferred":[
        "\u70fd\u706b\u53f0\u6751"
    ],
    "wof:name":"Fenghuotaicun",
    "wof:placetype":"locality"
},
  "geometry": {"coordinates":[122.238,39.3741],"type":"Point"}
}