{
  "type": "Feature",
  "properties": {
    "gn:admin1_code":"23.0",
    "gn:asciiname":"Xujiayan",
    "gn:country_code":"CN",
    "gn:dem":2,
    "gn:feature_class":"P",
    "gn:feature_code":"PPL",
    "gn:name":"Xujiayan",
    "gn:population":0,
    "gn:timezone":"Asia/Shanghai",
    "iso:country":"CN",
    "name:zho_x_preferred":[
        "Xujiayan"
    ],
    "name:zho_x_variant":[
        "\u8bb8\u5bb6\u5830"
    ],
    "wof:name":"Xujiayan",
    "wof:placetype":"locality"
},
  "geometry": {"coordinates":[121.15366000000002,31.20933],"type":"Point"}
}