{
  "type": "Feature",
  "properties": {
    "gn:admin1_code":"3.0",
    "gn:asciiname":"Xialiaoyuan",
    "gn:country_code":"CN",
    "gn:dem":246,
    "gn:feature_class":"P",
    "gn:feature_code":"PPL",
    "gn:name":"Xialiaoyuan",
    "gn:population":0,
    "gn:timezone":"Asia/Shanghai",
    "iso:country":"CN",
    "name:und_x_variant":[
        "\u4e0b\u6f66\u6e90"
    ],
    "wof:name":"Xialiaoyuan",
    "wof:placetype":"locality"
},
  "geometry": {"coordinates":[116.13827999999999,26.86158],"type":"Point"}
}