{
  "type": "Feature",
  "properties": {
    "gn:admin1_code":"5.0",
    "gn:asciiname":"Dujiaotun",
    "gn:country_code":"CN",
    "gn:dem":480,
    "gn:feature_class":"P",
    "gn:feature_code":"PPL",
    "gn:name":"Dujiaotun",
    "gn:population":0,
    "gn:timezone":"Asia/Shanghai",
    "iso:country":"CN",
    "name:und_x_variant":[
        "\u72ec\u9a84\u5c6f"
    ],
    "wof:name":"Dujiaotun",
    "wof:placetype":"locality"
},
  "geometry": {"coordinates":[129.17649,42.94794],"type":"Point"}
}