{
  "type": "Feature",
  "properties": {
    "gn:admin1_code":"26",
    "gn:asciiname":"Zhonghecun",
    "gn:country_code":"CN",
    "gn:dem":415,
    "gn:feature_class":"P",
    "gn:feature_code":"PPL",
    "gn:name":"Zhonghecun",
    "gn:population":0,
    "gn:timezone":"Asia/Shanghai",
    "iso:country":"CN",
    "name:zho_x_preferred":[
        "\u4e2d\u5408\u6751"
    ],
    "wof:name":"Zhonghecun",
    "wof:placetype":"locality"
},
  "geometry": {"coordinates":[109.24075999999999,34.70438],"type":"Point"}
}