{
  "type": "Feature",
  "properties": {
    "gn:admin1_code":"8.0",
    "gn:asciiname":"Jingangtai",
    "gn:country_code":"CN",
    "gn:dem":591,
    "gn:feature_class":"P",
    "gn:feature_code":"PPL",
    "gn:name":"Jingangtai",
    "gn:population":0,
    "gn:timezone":"Asia/Shanghai",
    "iso:country":"CN",
    "name:zho_x_preferred":[
        "\u91d1\u94a2\u53f0"
    ],
    "wof:name":"Jingangtai",
    "wof:placetype":"locality"
},
  "geometry": {"coordinates":[130.92014,44.86423],"type":"Point"}
}