{
  "type": "Feature",
  "properties": {
    "gn:admin1_code":"15.0",
    "gn:asciiname":"Wuhe",
    "gn:country_code":"CN",
    "gn:dem":1648,
    "gn:feature_class":"P",
    "gn:feature_code":"PPL",
    "gn:name":"Wuhe",
    "gn:population":0,
    "gn:timezone":"Asia/Shanghai",
    "iso:country":"CN",
    "name:ceb_x_preferred":[
        "Wuhe"
    ],
    "name:deu_x_preferred":[
        "Wuhe"
    ],
    "name:zho_x_preferred":[
        "\u5434\u6cb3"
    ],
    "wof:name":"Wuhe",
    "wof:placetype":"locality"
},
  "geometry": {"coordinates":[106.08499999999999,35.1356],"type":"Point"}
}