{
  "type": "Feature",
  "properties": {
    "gn:admin1_code":"12.0",
    "gn:asciiname":"Nanxindian",
    "gn:country_code":"CN",
    "gn:dem":90,
    "gn:feature_class":"P",
    "gn:feature_code":"PPL",
    "gn:name":"Nanxindian",
    "gn:population":0,
    "gn:timezone":"Asia/Shanghai",
    "iso:country":"CN",
    "name:zho_x_preferred":[
        "\u5357\u65b0\u5e97"
    ],
    "wof:name":"Nanxindian",
    "wof:placetype":"locality"
},
  "geometry": {"coordinates":[114.032,31.67137],"type":"Point"}
}