{
  "type": "Feature",
  "properties": {
    "gn:admin1_code":"9",
    "gn:asciiname":"Wangjiahou",
    "gn:country_code":"CN",
    "gn:dem":703,
    "gn:feature_class":"P",
    "gn:feature_code":"PPL",
    "gn:name":"Wangjiahou",
    "gn:population":0,
    "gn:timezone":"Asia/Shanghai",
    "iso:country":"CN",
    "wof:name":"Wangjiahou",
    "wof:placetype":"locality"
},
  "geometry": {"coordinates":[111.38278,34.77167],"type":"Point"}
}