{
  "type": "Feature",
  "properties": {
    "gn:admin1_code":"19.0",
    "gn:asciiname":"Wangtaizi",
    "gn:country_code":"CN",
    "gn:dem":3,
    "gn:feature_class":"P",
    "gn:feature_code":"PPL",
    "gn:name":"Wangtaizi",
    "gn:population":0,
    "gn:timezone":"Asia/Shanghai",
    "iso:country":"CN",
    "name:zho_x_preferred":[
        "\u738b\u53f0\u5b50"
    ],
    "wof:name":"Wangtaizi",
    "wof:placetype":"locality"
},
  "geometry": {"coordinates":[120.29111,40.18952],"type":"Point"}
}