{
  "type": "Feature",
  "properties": {
    "gn:admin1_code":"26.0",
    "gn:asciiname":"Lishuguacun",
    "gn:country_code":"CN",
    "gn:dem":897,
    "gn:feature_class":"P",
    "gn:feature_code":"PPL",
    "gn:name":"Lishuguacun",
    "gn:population":0,
    "gn:timezone":"Asia/Shanghai",
    "iso:country":"CN",
    "name:zho_x_preferred":[
        "\u68a8\u6811\u576c\u6751"
    ],
    "wof:name":"Lishuguacun",
    "wof:placetype":"locality"
},
  "geometry": {"coordinates":[110.64391000000001,37.73374],"type":"Point"}
}