{
  "type": "Feature",
  "properties": {
    "gn:admin1_code":"14.0",
    "gn:asciiname":"Zari",
    "gn:country_code":"CN",
    "gn:dem":3396,
    "gn:feature_class":"P",
    "gn:feature_code":"PPLA4",
    "gn:name":"Zari",
    "gn:population":0,
    "gn:timezone":"Asia/Urumqi",
    "iso:country":"CN",
    "name:bod_x_preferred":[
        "Zari"
    ],
    "name:hin_x_preferred":[
        "\u091c\u0930\u0940"
    ],
    "name:msa_x_preferred":[
        "Zari"
    ],
    "name:und_x_variant":[
        "Zhari",
        "Majidun",
        "Zari Xiang"
    ],
    "name:zho_x_preferred":[
        "\u624e\u65e5"
    ],
    "name:zho_x_variant":[
        "\u9a6c\u53ca\u58a9",
        "\u624e\u65e5\u4e61"
    ],
    "wof:name":"Zari",
    "wof:placetype":"locality"
},
  "geometry": {"coordinates":[93.36905,28.67338],"type":"Point"}
}