{
  "type": "Feature",
  "properties": {
    "gn:admin1_code":"32.0",
    "gn:asciiname":"Tangfangtou",
    "gn:country_code":"CN",
    "gn:dem":342,
    "gn:feature_class":"P",
    "gn:feature_code":"PPL",
    "gn:name":"Tangfangtou",
    "gn:population":0,
    "gn:timezone":"Asia/Shanghai",
    "iso:country":"CN",
    "name:zho_x_preferred":[
        "\u7cd6\u623f\u5934"
    ],
    "wof:name":"Tangfangtou",
    "wof:placetype":"locality"
},
  "geometry": {"coordinates":[104.895,28.987],"type":"Point"}
}