{
  "type": "Feature",
  "properties": {
    "gn:admin1_code":"30.0",
    "gn:asciiname":"Shanhouchicun",
    "gn:country_code":"CN",
    "gn:dem":28,
    "gn:feature_class":"P",
    "gn:feature_code":"PPL",
    "gn:name":"Shanhouchicun",
    "gn:population":0,
    "gn:timezone":"Asia/Shanghai",
    "iso:country":"CN",
    "name:zho_x_preferred":[
        "\u5c71\u540e\u6c60\u6751"
    ],
    "wof:name":"Shanhouchicun",
    "wof:placetype":"locality"
},
  "geometry": {"coordinates":[116.16553999999999,23.27011],"type":"Point"}
}