{
  "type": "Feature",
  "properties": {
    "gn:admin1_code":"16.0",
    "gn:asciiname":"Qinbu",
    "gn:country_code":"CN",
    "gn:dem":173,
    "gn:feature_class":"P",
    "gn:feature_code":"PPL",
    "gn:name":"Qinbu",
    "gn:population":0,
    "gn:timezone":"Asia/Shanghai",
    "iso:country":"CN",
    "name:zho_x_preferred":[
        "\u82a9\u535c"
    ],
    "wof:name":"Qinbu",
    "wof:placetype":"locality"
},
  "geometry": {"coordinates":[109.456,24.6214],"type":"Point"}
}