{
  "type": "Feature",
  "properties": {
    "gn:admin1_code":"9.0",
    "gn:asciiname":"Gaominggu",
    "gn:country_code":"CN",
    "gn:dem":78,
    "gn:feature_class":"P",
    "gn:feature_code":"PPL",
    "gn:name":"Gaominggu",
    "gn:population":0,
    "gn:timezone":"Asia/Shanghai",
    "iso:country":"CN",
    "name:zho_x_preferred":[
        "\u9ad8\u660e\u53e4"
    ],
    "wof:name":"Gaominggu",
    "wof:placetype":"locality"
},
  "geometry": {"coordinates":[114.0291,35.04673],"type":"Point"}
}