{
  "type": "Feature",
  "properties": {
    "gn:admin1_code":"32.0",
    "gn:asciiname":"Chenjia Tianba",
    "gn:country_code":"CN",
    "gn:dem":425,
    "gn:feature_class":"P",
    "gn:feature_code":"PPL",
    "gn:name":"Chenjia Tianba",
    "gn:population":0,
    "gn:timezone":"Asia/Shanghai",
    "iso:country":"CN",
    "name:zho_x_preferred":[
        "\u9648\u5bb6\u7530\u575d"
    ],
    "wof:name":"Chenjia Tianba",
    "wof:placetype":"locality"
},
  "geometry": {"coordinates":[105.995,31.6212],"type":"Point"}
}