{
  "type": "Feature",
  "properties": {
    "gn:admin1_code":"29.0",
    "gn:asciiname":"Shangmanda",
    "gn:country_code":"CN",
    "gn:dem":1184,
    "gn:feature_class":"P",
    "gn:feature_code":"PPL",
    "gn:name":"Shangmanda",
    "gn:population":0,
    "gn:timezone":"Asia/Shanghai",
    "iso:country":"CN",
    "name:zho_x_preferred":[
        "\u4e0a\u66fc\u8fbe"
    ],
    "wof:name":"Shangmanda",
    "wof:placetype":"locality"
},
  "geometry": {"coordinates":[100.395,22.0192],"type":"Point"}
}