{
  "type": "Feature",
  "properties": {
    "gn:admin1_code":"30.0",
    "gn:asciiname":"Longgengbei",
    "gn:country_code":"CN",
    "gn:dem":141,
    "gn:feature_class":"P",
    "gn:feature_code":"PPL",
    "gn:name":"Longgengbei",
    "gn:population":0,
    "gn:timezone":"Asia/Shanghai",
    "iso:country":"CN",
    "name:zho_x_preferred":[
        "Longgengbei"
    ],
    "name:zho_x_variant":[
        "\u9f99\u9888\u80cc"
    ],
    "wof:name":"Longgengbei",
    "wof:placetype":"locality"
},
  "geometry": {"coordinates":[114.86705000000001,24.07986],"type":"Point"}
}