{
  "type": "Feature",
  "properties": {
    "gn:admin1_code":"2.0",
    "gn:asciiname":"Hushao",
    "gn:country_code":"CN",
    "gn:dem":7,
    "gn:feature_class":"P",
    "gn:feature_code":"PPL",
    "gn:name":"Hushao",
    "gn:population":0,
    "gn:timezone":"Asia/Shanghai",
    "iso:country":"CN",
    "name:und_x_variant":[
        "\u864e\u54e8",
        "Hushaoxiang",
        "\u864e\u54e8\u4e61"
    ],
    "wof:name":"Hushao",
    "wof:placetype":"locality"
},
  "geometry": {"coordinates":[120.46776,30.53777],"type":"Point"}
}