{
  "type": "Feature",
  "properties": {
    "gn:admin1_code":"9.0",
    "gn:asciiname":"Aomiandi",
    "gn:country_code":"CN",
    "gn:dem":475,
    "gn:feature_class":"P",
    "gn:feature_code":"PPL",
    "gn:name":"Aomiandi",
    "gn:population":0,
    "gn:timezone":"Asia/Shanghai",
    "iso:country":"CN",
    "name:zho_x_preferred":[
        "\u50b2\u9762\u5730"
    ],
    "wof:name":"Aomiandi",
    "wof:placetype":"locality"
},
  "geometry": {"coordinates":[113.54682,35.55211],"type":"Point"}
}