{
  "type": "Feature",
  "properties": {
    "gn:admin1_code":"32.0",
    "gn:asciiname":"Yibigu",
    "gn:country_code":"CN",
    "gn:dem":2812,
    "gn:feature_class":"P",
    "gn:feature_code":"PPL",
    "gn:name":"Yibigu",
    "gn:population":0,
    "gn:timezone":"Asia/Shanghai",
    "iso:country":"CN",
    "name:zho_x_preferred":[
        "\u4f9d\u6bd4\u53e4"
    ],
    "wof:name":"Yibigu",
    "wof:placetype":"locality"
},
  "geometry": {"coordinates":[102.68000000000001,28.5902],"type":"Point"}
}