{
  "type": "Feature",
  "properties": {
    "gn:admin1_code":"32.0",
    "gn:asciiname":"Nalaxia",
    "gn:country_code":"CN",
    "gn:dem":3895,
    "gn:feature_class":"P",
    "gn:feature_code":"PPL",
    "gn:name":"Nalaxia",
    "gn:population":0,
    "gn:timezone":"Asia/Shanghai",
    "iso:country":"CN",
    "name:zho_x_preferred":[
        "\u90a3\u62c9\u5477"
    ],
    "wof:name":"Nalaxia",
    "wof:placetype":"locality"
},
  "geometry": {"coordinates":[99.9311,29.0037],"type":"Point"}
}