{
  "type": "Feature",
  "properties": {
    "gn:admin1_code":"33.0",
    "gn:asciiname":"Ziyou",
    "gn:country_code":"CN",
    "gn:dem":336,
    "gn:feature_class":"P",
    "gn:feature_code":"PPL",
    "gn:name":"Ziyou",
    "gn:population":0,
    "gn:timezone":"Asia/Shanghai",
    "iso:country":"CN",
    "name:zho_x_preferred":[
        "\u81ea\u7531"
    ],
    "wof:name":"Ziyou",
    "wof:placetype":"locality"
},
  "geometry": {"coordinates":[106.55500000000001,29.395],"type":"Point"}
}