{
  "type": "Feature",
  "properties": {
    "gn:admin1_code":"11.0",
    "gn:asciiname":"Buzijiao",
    "gn:country_code":"CN",
    "gn:dem":295,
    "gn:feature_class":"P",
    "gn:feature_code":"PPL",
    "gn:name":"Buzijiao",
    "gn:population":0,
    "gn:timezone":"Asia/Shanghai",
    "iso:country":"CN",
    "name:zho_x_preferred":[
        "\u5821\u5b50\u811a"
    ],
    "wof:name":"Buzijiao",
    "wof:placetype":"locality"
},
  "geometry": {"coordinates":[109.69811,26.81461],"type":"Point"}
}