{
  "type": "Feature",
  "properties": {
    "gn:admin1_code":"30",
    "gn:asciiname":"Shitan",
    "gn:country_code":"CN",
    "gn:dem":69,
    "gn:feature_class":"P",
    "gn:feature_code":"PPLA4",
    "gn:name":"Shitan",
    "gn:population":0,
    "gn:timezone":"Asia/Shanghai",
    "iso:country":"CN",
    "name:und_x_variant":[
        "Shih-t\u2019an",
        "Shitan",
        "\u77f3\u6f6d",
        "\u77f3\u6f6d\u9547",
        "Shitan Zhen"
    ],
    "name:zho_x_preferred":[
        "\u77f3\u6f6d\u9547"
    ],
    "wof:name":"Shitan",
    "wof:placetype":"locality"
},
  "geometry": {"coordinates":[112.76376999999999,24.12861],"type":"Point"}
}