{
  "type": "Feature",
  "properties": {
    "gn:admin1_code":"16.0",
    "gn:asciiname":"Xuedong",
    "gn:country_code":"CN",
    "gn:dem":163,
    "gn:feature_class":"P",
    "gn:feature_code":"PPL",
    "gn:name":"Xuedong",
    "gn:population":0,
    "gn:timezone":"Asia/Shanghai",
    "iso:country":"CN",
    "name:zho_x_preferred":[
        "\u5b66\u578c"
    ],
    "wof:name":"Xuedong",
    "wof:placetype":"locality"
},
  "geometry": {"coordinates":[110.366,23.0661],"type":"Point"}
}