{
  "type": "Feature",
  "properties": {
    "gn:admin1_code":"19.0",
    "gn:asciiname":"Erdaolingcun",
    "gn:country_code":"CN",
    "gn:dem":46,
    "gn:feature_class":"P",
    "gn:feature_code":"PPL",
    "gn:name":"Erdaolingcun",
    "gn:population":0,
    "gn:timezone":"Asia/Shanghai",
    "iso:country":"CN",
    "name:zho_x_preferred":[
        "\u4e8c\u9053\u5cad\u6751"
    ],
    "wof:name":"Erdaolingcun",
    "wof:placetype":"locality"
},
  "geometry": {"coordinates":[120.26300000000001,40.3386],"type":"Point"}
}