{
  "type": "Feature",
  "properties": {
    "gn:admin1_code":"16.0",
    "gn:asciiname":"Da'ang",
    "gn:country_code":"CN",
    "gn:dem":892,
    "gn:feature_class":"P",
    "gn:feature_code":"PPL",
    "gn:name":"Da\u2019ang",
    "gn:population":0,
    "gn:timezone":"Asia/Shanghai",
    "iso:country":"CN",
    "name:und_x_variant":[
        "Da\u2019ang"
    ],
    "name:zho_x_preferred":[
        "\u5927\u6602"
    ],
    "wof:name":"Da'ang",
    "wof:placetype":"locality"
},
  "geometry": {"coordinates":[106.11,23.307],"type":"Point"}
}