{
  "type": "Feature",
  "properties": {
    "gn:admin1_code":"15.0",
    "gn:asciiname":"Puxing",
    "gn:country_code":"CN",
    "gn:dem":1783,
    "gn:feature_class":"P",
    "gn:feature_code":"PPL",
    "gn:name":"Puxing",
    "gn:population":0,
    "gn:timezone":"Asia/Shanghai",
    "iso:country":"CN",
    "name:und_x_variant":[
        "\u84b2\u5174"
    ],
    "wof:name":"Puxing",
    "wof:placetype":"locality"
},
  "geometry": {"coordinates":[104.71996,34.99571],"type":"Point"}
}