{
  "type": "Feature",
  "properties": {
    "gn:admin1_code":"15.0",
    "gn:asciiname":"Shatanzhuang",
    "gn:country_code":"CN",
    "gn:dem":1744,
    "gn:feature_class":"P",
    "gn:feature_code":"PPL",
    "gn:name":"Shatanzhuang",
    "gn:population":0,
    "gn:timezone":"Asia/Shanghai",
    "iso:country":"CN",
    "name:zho_x_preferred":[
        "\u6c99\u6ee9\u5e84"
    ],
    "wof:name":"Shatanzhuang",
    "wof:placetype":"locality"
},
  "geometry": {"coordinates":[102.158,38.3308],"type":"Point"}
}