{
  "type": "Feature",
  "properties": {
    "gn:admin1_code":"23.0",
    "gn:asciiname":"Xidai",
    "gn:country_code":"CN",
    "gn:dem":4,
    "gn:feature_class":"P",
    "gn:feature_code":"PPL",
    "gn:name":"Xidai",
    "gn:population":0,
    "gn:timezone":"Asia/Shanghai",
    "iso:country":"CN",
    "name:zho_x_preferred":[
        "Xidai"
    ],
    "name:zho_x_variant":[
        "\u897f\u57ed"
    ],
    "wof:name":"Xidai",
    "wof:placetype":"locality"
},
  "geometry": {"coordinates":[121.17641999999999,31.11694],"type":"Point"}
}