{
  "type": "Feature",
  "properties": {
    "gn:admin1_code":"2.0",
    "gn:asciiname":"Shuangtiaoba",
    "gn:country_code":"CN",
    "gn:dem":7,
    "gn:feature_class":"P",
    "gn:feature_code":"PPL",
    "gn:name":"Shuangtiaoba",
    "gn:population":0,
    "gn:timezone":"Asia/Shanghai",
    "iso:country":"CN",
    "name:und_x_variant":[
        "\u53cc\u6761\u575d"
    ],
    "wof:name":"Shuangtiaoba",
    "wof:placetype":"locality"
},
  "geometry": {"coordinates":[120.27593,30.50675],"type":"Point"}
}