{
  "type": "Feature",
  "properties": {
    "gn:admin1_code":"8.0",
    "gn:asciiname":"Xizhaodi Fangzi",
    "gn:country_code":"CN",
    "gn:dem":136,
    "gn:feature_class":"P",
    "gn:feature_code":"PPL",
    "gn:name":"Xizhaodi Fangzi",
    "gn:population":0,
    "gn:timezone":"Asia/Shanghai",
    "iso:country":"CN",
    "name:zho_x_preferred":[
        "\u897f\u8d75\u5730\u623f\u5b50"
    ],
    "wof:name":"Xizhaodi Fangzi",
    "wof:placetype":"locality"
},
  "geometry": {"coordinates":[124.51209,46.11507],"type":"Point"}
}