{
  "type": "Feature",
  "properties": {
    "gn:admin1_code":"15.0",
    "gn:asciiname":"Donghanjiawan",
    "gn:country_code":"CN",
    "gn:dem":1766,
    "gn:feature_class":"P",
    "gn:feature_code":"PPL",
    "gn:name":"Donghanjiawan",
    "gn:population":0,
    "gn:timezone":"Asia/Shanghai",
    "iso:country":"CN",
    "name:zho_x_preferred":[
        "\u4e1c\u97e9\u5bb6\u6e7e"
    ],
    "wof:name":"Donghanjiawan",
    "wof:placetype":"locality"
},
  "geometry": {"coordinates":[105.33499999999999,34.9054],"type":"Point"}
}