{
  "type": "Feature",
  "properties": {
    "gn:admin1_code":"15.0",
    "gn:asciiname":"Duozhiba",
    "gn:country_code":"CN",
    "gn:dem":2199,
    "gn:feature_class":"P",
    "gn:feature_code":"PPL",
    "gn:name":"Duozhiba",
    "gn:population":0,
    "gn:timezone":"Asia/Shanghai",
    "iso:country":"CN",
    "name:und_x_variant":[
        "\u591a\u652f\u5df4"
    ],
    "wof:name":"Duozhiba",
    "wof:placetype":"locality"
},
  "geometry": {"coordinates":[102.956,35.4125],"type":"Point"}
}