{
  "type": "Feature",
  "properties": {
    "gn:admin1_code":"25.0",
    "gn:asciiname":"Yujiazhuang",
    "gn:country_code":"CN",
    "gn:dem":54,
    "gn:feature_class":"P",
    "gn:feature_code":"PPL",
    "gn:name":"Yujiazhuang",
    "gn:population":0,
    "gn:timezone":"Asia/Shanghai",
    "iso:country":"CN",
    "name:zho_x_preferred":[
        "\u4e8e\u5bb6\u5e84"
    ],
    "wof:name":"Yujiazhuang",
    "wof:placetype":"locality"
},
  "geometry": {"coordinates":[120.64870999999999,36.56502],"type":"Point"}
}