{
  "type": "Feature",
  "properties": {
    "gn:admin1_code":"11.0",
    "gn:asciiname":"Yikou",
    "gn:country_code":"CN",
    "gn:dem":226,
    "gn:feature_class":"P",
    "gn:feature_code":"PPL",
    "gn:name":"Yikou",
    "gn:population":0,
    "gn:timezone":"Asia/Shanghai",
    "iso:country":"CN",
    "name:zho_x_preferred":[
        "\u9091\u53e3"
    ],
    "wof:name":"Yikou",
    "wof:placetype":"locality"
},
  "geometry": {"coordinates":[111.09972999999999,25.0796],"type":"Point"}
}