{
  "type": "Feature",
  "properties": {
    "gn:admin1_code":"30.0",
    "gn:asciiname":"Goudong",
    "gn:country_code":"CN",
    "gn:dem":166,
    "gn:feature_class":"P",
    "gn:feature_code":"PPL",
    "gn:name":"Goudong",
    "gn:population":0,
    "gn:timezone":"Asia/Shanghai",
    "iso:country":"CN",
    "name:zho_x_preferred":[
        "Goudong"
    ],
    "name:zho_x_variant":[
        "\u82df\u5cd2"
    ],
    "wof:name":"Goudong",
    "wof:placetype":"locality"
},
  "geometry": {"coordinates":[114.32599999999999,24.09924],"type":"Point"}
}