{
  "type": "Feature",
  "properties": {
    "gn:admin1_code":"24.0",
    "gn:asciiname":"Dongtoushang",
    "gn:country_code":"CN",
    "gn:dem":1450,
    "gn:feature_class":"P",
    "gn:feature_code":"PPL",
    "gn:name":"Dongtoushang",
    "gn:population":0,
    "gn:timezone":"Asia/Shanghai",
    "iso:country":"CN",
    "name:zho_x_preferred":[
        "\u6d1e\u5934\u4e0a"
    ],
    "wof:name":"Dongtoushang",
    "wof:placetype":"locality"
},
  "geometry": {"coordinates":[113.51373,35.82848],"type":"Point"}
}