{
  "type": "Feature",
  "properties": {
    "gn:admin1_code":"7.0",
    "gn:asciiname":"Cunqian",
    "gn:country_code":"CN",
    "gn:dem":6,
    "gn:feature_class":"P",
    "gn:feature_code":"PPL",
    "gn:name":"Cunqian",
    "gn:population":0,
    "gn:timezone":"Asia/Shanghai",
    "iso:country":"CN",
    "name:zho_x_preferred":[
        "\u6751\u524d"
    ],
    "wof:name":"Cunqian",
    "wof:placetype":"locality"
},
  "geometry": {"coordinates":[119.6528,26.39878],"type":"Point"}
}