{
  "type": "Feature",
  "properties": {
    "gn:admin1_code":"16.0",
    "gn:asciiname":"Dabin",
    "gn:country_code":"CN",
    "gn:dem":81,
    "gn:feature_class":"P",
    "gn:feature_code":"PPL",
    "gn:name":"Dabin",
    "gn:population":0,
    "gn:timezone":"Asia/Shanghai",
    "iso:country":"CN",
    "name:zho_x_preferred":[
        "\u5927\u5bbe"
    ],
    "wof:name":"Dabin",
    "wof:placetype":"locality"
},
  "geometry": {"coordinates":[109.18600000000001,22.4931],"type":"Point"}
}