{
  "type": "Feature",
  "properties": {
    "gn:admin1_code":"12.0",
    "gn:asciiname":"Hongyangou",
    "gn:country_code":"CN",
    "gn:dem":1136,
    "gn:feature_class":"P",
    "gn:feature_code":"PPL",
    "gn:name":"Hongyangou",
    "gn:population":0,
    "gn:timezone":"Asia/Shanghai",
    "iso:country":"CN",
    "name:zho_x_preferred":[
        "\u7ea2\u5ca9\u6c9f"
    ],
    "wof:name":"Hongyangou",
    "wof:placetype":"locality"
},
  "geometry": {"coordinates":[111.11351999999999,31.78017],"type":"Point"}
}