{
  "type": "Feature",
  "properties": {
    "gn:admin1_code":"26.0",
    "gn:asciiname":"Duluoweicun",
    "gn:country_code":"CN",
    "gn:dem":1160,
    "gn:feature_class":"P",
    "gn:feature_code":"PPL",
    "gn:name":"Duluoweicun",
    "gn:population":0,
    "gn:timezone":"Asia/Shanghai",
    "iso:country":"CN",
    "name:zho_x_preferred":[
        "\u675c\u6d1b\u5c3e\u6751"
    ],
    "wof:name":"Duluoweicun",
    "wof:placetype":"locality"
},
  "geometry": {"coordinates":[108.85066999999999,35.63725],"type":"Point"}
}