{
  "type": "Feature",
  "properties": {
    "gn:admin1_code":"16.0",
    "gn:asciiname":"Sisaling",
    "gn:country_code":"CN",
    "gn:dem":62,
    "gn:feature_class":"P",
    "gn:feature_code":"PPL",
    "gn:name":"Sisaling",
    "gn:population":0,
    "gn:timezone":"Asia/Shanghai",
    "iso:country":"CN",
    "name:zho_x_preferred":[
        "\u6cd7\u6d12\u5cad"
    ],
    "wof:name":"Sisaling",
    "wof:placetype":"locality"
},
  "geometry": {"coordinates":[109.065,21.8881],"type":"Point"}
}