{
  "type": "Feature",
  "properties": {
    "gn:admin1_code":"11.0",
    "gn:asciiname":"Huangjia Louwu",
    "gn:country_code":"CN",
    "gn:dem":79,
    "gn:feature_class":"P",
    "gn:feature_code":"PPL",
    "gn:name":"Huangjia Louwu",
    "gn:population":0,
    "gn:timezone":"Asia/Shanghai",
    "iso:country":"CN",
    "name:zho_x_preferred":[
        "Huangjia Louwu"
    ],
    "name:zho_x_variant":[
        "\u9ec4\u5bb6\u697c\u5c4b"
    ],
    "wof:name":"Huangjia Louwu",
    "wof:placetype":"locality"
},
  "geometry": {"coordinates":[111.65006,29.26347],"type":"Point"}
}