{
  "type": "Feature",
  "properties": {
    "gn:admin1_code":"19.0",
    "gn:asciiname":"Tianzhangzi",
    "gn:country_code":"CN",
    "gn:dem":549,
    "gn:feature_class":"P",
    "gn:feature_code":"PPL",
    "gn:name":"Tianzhangzi",
    "gn:population":0,
    "gn:timezone":"Asia/Shanghai",
    "iso:country":"CN",
    "name:zho_x_preferred":[
        "\u7530\u6756\u5b50"
    ],
    "wof:name":"Tianzhangzi",
    "wof:placetype":"locality"
},
  "geometry": {"coordinates":[119.37456,41.08023],"type":"Point"}
}