{
  "type": "Feature",
  "properties": {
    "gn:admin1_code":"12.0",
    "gn:asciiname":"Xiaohexi",
    "gn:cc2":"CN",
    "gn:country_code":"CN",
    "gn:dem":47,
    "gn:feature_class":"P",
    "gn:feature_code":"PPL",
    "gn:name":"Xiaohexi",
    "gn:population":0,
    "gn:timezone":"Asia/Shanghai",
    "iso:country":"CN",
    "name:und_x_variant":[
        "Siaohoki",
        "Hsiao-ho-ch\u2019i-shih",
        "Xiaohexi"
    ],
    "wof:name":"Xiaohexi",
    "wof:placetype":"locality"
},
  "geometry": {"coordinates":[114.05,31.35],"type":"Point"}
}