{
  "type": "Feature",
  "properties": {
    "gn:admin1_code":"6.0",
    "gn:asciiname":"Caoshida",
    "gn:country_code":"CN",
    "gn:dem":3266,
    "gn:feature_class":"P",
    "gn:feature_code":"PPL",
    "gn:name":"Caoshida",
    "gn:population":0,
    "gn:timezone":"Asia/Shanghai",
    "iso:country":"CN",
    "name:und_x_variant":[
        "\u64cd\u4ec0\u8fbe"
    ],
    "wof:name":"Caoshida",
    "wof:placetype":"locality"
},
  "geometry": {"coordinates":[100.0137,35.92312000000001],"type":"Point"}
}