{
  "type": "Feature",
  "properties": {
    "gn:admin1_code":"11.0",
    "gn:asciiname":"Hongshengdian",
    "gn:country_code":"CN",
    "gn:dem":204,
    "gn:feature_class":"P",
    "gn:feature_code":"PPL",
    "gn:name":"Hongshengdian",
    "gn:population":0,
    "gn:timezone":"Asia/Shanghai",
    "iso:country":"CN",
    "name:zho_x_preferred":[
        "\u9e3f\u76db\u5e97"
    ],
    "wof:name":"Hongshengdian",
    "wof:placetype":"locality"
},
  "geometry": {"coordinates":[111.35980000000001,27.79997],"type":"Point"}
}