{
  "type": "Feature",
  "properties": {
    "gn:admin1_code":"02",
    "gn:asciiname":"Dongmen",
    "gn:country_code":"CN",
    "gn:dem":14,
    "gn:feature_class":"P",
    "gn:feature_code":"PPL",
    "gn:name":"Dongmen",
    "gn:population":0,
    "gn:timezone":"Asia/Shanghai",
    "iso:country":"CN",
    "name:ita_x_preferred":[
        "Dongmen"
    ],
    "name:und_x_variant":[
        "Tung-men"
    ],
    "name:zho_x_preferred":[
        "\u4e1c\u95e8"
    ],
    "wof:name":"Dongmen",
    "wof:placetype":"locality"
},
  "geometry": {"coordinates":[121.95408,29.20053],"type":"Point"}
}