{
  "type": "Feature",
  "properties": {
    "gn:admin1_code":"18",
    "gn:asciiname":"Shaobu",
    "gn:country_code":"CN",
    "gn:dem":1266,
    "gn:feature_class":"P",
    "gn:feature_code":"PPL",
    "gn:name":"Shaobu",
    "gn:population":0,
    "gn:timezone":"Asia/Shanghai",
    "iso:country":"CN",
    "name:zho_x_preferred":[
        "\u54e8\u5821"
    ],
    "wof:name":"Shaobu",
    "wof:placetype":"locality"
},
  "geometry": {"coordinates":[106.88500000000001,26.5013],"type":"Point"}
}