{
  "type": "Feature",
  "properties": {
    "gn:admin1_code":"29.0",
    "gn:asciiname":"Dabiaodi",
    "gn:country_code":"CN",
    "gn:dem":1410,
    "gn:feature_class":"P",
    "gn:feature_code":"PPL",
    "gn:name":"Dabiaodi",
    "gn:population":0,
    "gn:timezone":"Asia/Shanghai",
    "iso:country":"CN",
    "name:zho_x_preferred":[
        "\u5927\u8868\u5730"
    ],
    "wof:name":"Dabiaodi",
    "wof:placetype":"locality"
},
  "geometry": {"coordinates":[101.107,23.7372],"type":"Point"}
}