{
  "type": "Feature",
  "properties": {
    "gn:admin1_code":"1.0",
    "gn:asciiname":"Shaoze",
    "gn:country_code":"CN",
    "gn:dem":189,
    "gn:feature_class":"P",
    "gn:feature_code":"PPL",
    "gn:name":"Shaoze",
    "gn:population":0,
    "gn:timezone":"Asia/Shanghai",
    "iso:country":"CN",
    "name:zho_x_preferred":[
        "\u7ecd\u6cfd"
    ],
    "wof:name":"Shaoze",
    "wof:placetype":"locality"
},
  "geometry": {"coordinates":[118.44918,29.73244],"type":"Point"}
}