{
  "type": "Feature",
  "properties": {
    "gn:admin1_code":"21.0",
    "gn:asciiname":"Hujiawanzi",
    "gn:country_code":"CN",
    "gn:dem":1410,
    "gn:feature_class":"P",
    "gn:feature_code":"PPL",
    "gn:name":"Hujiawanzi",
    "gn:population":0,
    "gn:timezone":"Asia/Shanghai",
    "iso:country":"CN",
    "name:und_x_variant":[
        "\u864e\u5bb6\u6e7e\u5b50"
    ],
    "name:zho_x_preferred":[
        "\u864e\u5bb6\u6e7e\u5b50"
    ],
    "wof:name":"Hujiawanzi",
    "wof:placetype":"locality"
},
  "geometry": {"coordinates":[106.07393999999999,36.76559],"type":"Point"}
}