{
  "type": "Feature",
  "properties": {
    "gn:admin1_code":"10",
    "gn:asciiname":"Dayingzi",
    "gn:country_code":"CN",
    "gn:dem":1571,
    "gn:feature_class":"P",
    "gn:feature_code":"PPL",
    "gn:name":"Dayingzi",
    "gn:population":0,
    "gn:timezone":"Asia/Shanghai",
    "iso:country":"CN",
    "name:zho_x_preferred":[
        "\u5927\u8425\u5b50"
    ],
    "wof:name":"Dayingzi",
    "wof:placetype":"locality"
},
  "geometry": {"coordinates":[115.84097,41.36328],"type":"Point"}
}