{
  "type": "Feature",
  "properties": {
    "gn:admin1_code":"16.0",
    "gn:asciiname":"Ouyang Laocun",
    "gn:country_code":"CN",
    "gn:dem":367,
    "gn:feature_class":"P",
    "gn:feature_code":"PPL",
    "gn:name":"Ouyang Laocun",
    "gn:population":0,
    "gn:timezone":"Asia/Shanghai",
    "iso:country":"CN",
    "name:zho_x_preferred":[
        "\u6b27\u9633\u8001\u6751"
    ],
    "wof:name":"Ouyang Laocun",
    "wof:placetype":"locality"
},
  "geometry": {"coordinates":[109.187,23.1588],"type":"Point"}
}