{
  "type": "Feature",
  "properties": {
    "gn:admin1_code":"04",
    "gn:asciiname":"Haiyu",
    "gn:country_code":"CN",
    "gn:dem":0,
    "gn:feature_class":"P",
    "gn:feature_code":"PPL",
    "gn:name":"Haiyu",
    "gn:population":0,
    "gn:timezone":"Asia/Shanghai",
    "iso:country":"CN",
    "name:zho_x_preferred":[
        "\u6d77\u865e"
    ],
    "wof:name":"Haiyu",
    "wof:placetype":"locality"
},
  "geometry": {"coordinates":[120.8708,31.77452000000001],"type":"Point"}
}