{
  "type": "Feature",
  "properties": {
    "gn:admin1_code":"21",
    "gn:asciiname":"Cheng'ershan",
    "gn:country_code":"CN",
    "gn:dem":1966,
    "gn:feature_class":"P",
    "gn:feature_code":"PPL",
    "gn:name":"Cheng\u2019ershan",
    "gn:population":0,
    "gn:timezone":"Asia/Shanghai",
    "iso:country":"CN",
    "name:und_x_variant":[
        "Cheng\u2019ershan",
        "\u7a0b\u513f\u5c71"
    ],
    "wof:name":"Cheng'ershan",
    "wof:placetype":"locality"
},
  "geometry": {"coordinates":[106.33537,36.05954000000001],"type":"Point"}
}