{
  "type": "Feature",
  "properties": {
    "gn:admin1_code":"14.0",
    "gn:asciiname":"Radoi",
    "gn:country_code":"CN",
    "gn:dem":3840,
    "gn:feature_class":"P",
    "gn:feature_code":"PPLF",
    "gn:name":"Radoi",
    "gn:population":0,
    "gn:timezone":"Asia/Urumqi",
    "iso:country":"CN",
    "name:bod_x_preferred":[
        "Radoi"
    ],
    "name:und_x_variant":[
        "Redui"
    ],
    "name:zho_x_preferred":[
        "\u70ed\u5806"
    ],
    "wof:name":"Radoi",
    "wof:placetype":"locality"
},
  "geometry": {"coordinates":[91.00449999999999,29.43576],"type":"Point"}
}