{
  "type": "Feature",
  "properties": {
    "gn:admin1_code":"29.0",
    "gn:asciiname":"Bayi",
    "gn:country_code":"CN",
    "gn:dem":601,
    "gn:feature_class":"P",
    "gn:feature_code":"PPL",
    "gn:name":"Bayi",
    "gn:population":0,
    "gn:timezone":"Asia/Shanghai",
    "iso:country":"CN",
    "name:ceb_x_preferred":[
        "Bayi"
    ],
    "name:deu_x_preferred":[
        "Bayi"
    ],
    "name:fra_x_preferred":[
        "Bayi"
    ],
    "name:rus_x_preferred":[
        "\u0411\u044d\u0439\u0438"
    ],
    "name:swe_x_preferred":[
        "Bayi"
    ],
    "name:zho_x_preferred":[
        "\u5df4\u4e49"
    ],
    "wof:name":"Bayi",
    "wof:placetype":"locality"
},
  "geometry": {"coordinates":[102.66800000000001,22.7895],"type":"Point"}
}