{
  "type": "Feature",
  "properties": {
    "gn:admin1_code":"4.0",
    "gn:asciiname":"Xinyu",
    "gn:country_code":"CN",
    "gn:dem":2,
    "gn:feature_class":"P",
    "gn:feature_code":"PPL",
    "gn:name":"Xinyu",
    "gn:population":0,
    "gn:timezone":"Asia/Shanghai",
    "iso:country":"CN",
    "name:und_x_variant":[
        "\u65b0\u6986"
    ],
    "name:zho_x_preferred":[
        "\u65b0\u6986"
    ],
    "wof:name":"Xinyu",
    "wof:placetype":"locality"
},
  "geometry": {"coordinates":[120.66231000000001,32.99704000000001],"type":"Point"}
}