{
  "type": "Feature",
  "properties": {
    "gn:admin1_code":"4.0",
    "gn:asciiname":"Qinglong",
    "gn:country_code":"CN",
    "gn:dem":4,
    "gn:feature_class":"P",
    "gn:feature_code":"PPL",
    "gn:name":"Qinglong",
    "gn:population":0,
    "gn:timezone":"Asia/Shanghai",
    "iso:country":"CN",
    "name:ceb_x_preferred":[
        "Qinglong"
    ],
    "name:deu_x_preferred":[
        "Qinglong"
    ],
    "name:fra_x_preferred":[
        "Qinglong"
    ],
    "name:jpn_x_preferred":[
        "\u9752\u7adc"
    ],
    "name:kor_x_preferred":[
        "\uccad\ub8e1"
    ],
    "name:nor_x_preferred":[
        "Qinglong"
    ],
    "name:swe_x_preferred":[
        "Qinglong"
    ],
    "name:vie_x_preferred":[
        "Thanh Long"
    ],
    "name:zho_x_preferred":[
        "\u9752\u9f99"
    ],
    "wof:name":"Qinglong",
    "wof:placetype":"locality"
},
  "geometry": {"coordinates":[120.45762999999999,32.08792],"type":"Point"}
}