{
  "type": "Feature",
  "properties": {
    "gn:admin1_code":"15.0",
    "gn:asciiname":"Gujiagou",
    "gn:country_code":"CN",
    "gn:dem":1405,
    "gn:feature_class":"P",
    "gn:feature_code":"PPL",
    "gn:name":"Gujiagou",
    "gn:population":0,
    "gn:timezone":"Asia/Shanghai",
    "iso:country":"CN",
    "name:und_x_variant":[
        "\u53e4\u5bb6\u6c9f"
    ],
    "name:zho_x_preferred":[
        "\u53e4\u5bb6\u6c9f"
    ],
    "wof:name":"Gujiagou",
    "wof:placetype":"locality"
},
  "geometry": {"coordinates":[104.41645,33.11721],"type":"Point"}
}