{
  "type": "Feature",
  "properties": {
    "gn:admin1_code":"11.0",
    "gn:asciiname":"Dianshanli",
    "gn:country_code":"CN",
    "gn:dem":845,
    "gn:feature_class":"P",
    "gn:feature_code":"PPL",
    "gn:name":"Dianshanli",
    "gn:population":0,
    "gn:timezone":"Asia/Shanghai",
    "iso:country":"CN",
    "name:zho_x_preferred":[
        "\u975b\u5c71\u91cc"
    ],
    "wof:name":"Dianshanli",
    "wof:placetype":"locality"
},
  "geometry": {"coordinates":[112.92147,25.58946],"type":"Point"}
}