{
  "type": "Feature",
  "properties": {
    "gn:admin1_code":"16.0",
    "gn:asciiname":"Wenkuang",
    "gn:country_code":"CN",
    "gn:dem":392,
    "gn:feature_class":"P",
    "gn:feature_code":"PPL",
    "gn:name":"Wenkuang",
    "gn:population":0,
    "gn:timezone":"Asia/Shanghai",
    "iso:country":"CN",
    "name:zho_x_preferred":[
        "\u6e29\u77ff"
    ],
    "wof:name":"Wenkuang",
    "wof:placetype":"locality"
},
  "geometry": {"coordinates":[106.45399999999999,23.7412],"type":"Point"}
}