{
  "type": "Feature",
  "properties": {
    "gn:admin1_code":"30",
    "gn:asciiname":"Pingtai",
    "gn:country_code":"CN",
    "gn:dem":45,
    "gn:feature_class":"P",
    "gn:feature_code":"PPLA4",
    "gn:name":"Pingtai",
    "gn:population":0,
    "gn:timezone":"Asia/Shanghai",
    "iso:country":"CN",
    "name:und_x_variant":[
        "\u5e73\u53f0",
        "Pingtai Zhen",
        "\u5e73\u53f0\u9547"
    ],
    "wof:name":"Pingtai",
    "wof:placetype":"locality"
},
  "geometry": {"coordinates":[111.41574,23.25021],"type":"Point"}
}