{
  "type": "Feature",
  "properties": {
    "gn:admin1_code":"29",
    "gn:asciiname":"Liugudi",
    "gn:country_code":"CN",
    "gn:dem":1753,
    "gn:feature_class":"P",
    "gn:feature_code":"PPL",
    "gn:name":"Liugudi",
    "gn:population":0,
    "gn:timezone":"Asia/Shanghai",
    "iso:country":"CN",
    "name:zho_x_preferred":[
        "\u516d\u53e4\u5730"
    ],
    "wof:name":"Liugudi",
    "wof:placetype":"locality"
},
  "geometry": {"coordinates":[104.934,23.709],"type":"Point"}
}