{
  "type": "Feature",
  "properties": {
    "gn:admin1_code":"9.0",
    "gn:asciiname":"Honghe",
    "gn:country_code":"CN",
    "gn:dem":633,
    "gn:feature_class":"P",
    "gn:feature_code":"PPL",
    "gn:name":"Honghe",
    "gn:population":0,
    "gn:timezone":"Asia/Shanghai",
    "iso:country":"CN",
    "name:zho_x_preferred":[
        "\u6d2a\u6cb3"
    ],
    "wof:name":"Honghe",
    "wof:placetype":"locality"
},
  "geometry": {"coordinates":[113.10397,34.63746],"type":"Point"}
}