{
  "type": "Feature",
  "properties": {
    "gn:admin1_code":"29.0",
    "gn:asciiname":"Yangmeipo",
    "gn:country_code":"CN",
    "gn:dem":1906,
    "gn:feature_class":"P",
    "gn:feature_code":"PPL",
    "gn:name":"Yangmeipo",
    "gn:population":0,
    "gn:timezone":"Asia/Shanghai",
    "iso:country":"CN",
    "name:zho_x_preferred":[
        "\u6768\u6885\u5761"
    ],
    "wof:name":"Yangmeipo",
    "wof:placetype":"locality"
},
  "geometry": {"coordinates":[98.84350000000001,24.5536],"type":"Point"}
}