{
  "type": "Feature",
  "properties": {
    "gn:admin1_code":"3.0",
    "gn:asciiname":"Wujiabian",
    "gn:country_code":"CN",
    "gn:dem":66,
    "gn:feature_class":"P",
    "gn:feature_code":"PPL",
    "gn:name":"Wujiabian",
    "gn:population":0,
    "gn:timezone":"Asia/Shanghai",
    "iso:country":"CN",
    "name:und_x_variant":[
        "\u4f0d\u5bb6\u8fb9"
    ],
    "wof:name":"Wujiabian",
    "wof:placetype":"locality"
},
  "geometry": {"coordinates":[115.28451,27.15516],"type":"Point"}
}