{
  "type": "Feature",
  "properties": {
    "gn:admin1_code":"2",
    "gn:asciiname":"Longmen",
    "gn:country_code":"CN",
    "gn:dem":284,
    "gn:feature_class":"P",
    "gn:feature_code":"PPL",
    "gn:name":"Longmen",
    "gn:population":0,
    "gn:timezone":"Asia/Shanghai",
    "iso:country":"CN",
    "name:ceb_x_preferred":[
        "Longmen"
    ],
    "name:deu_x_preferred":[
        "Longmen"
    ],
    "name:fra_x_preferred":[
        "Longmen"
    ],
    "name:mlg_x_preferred":[
        "Longmen"
    ],
    "name:nor_x_preferred":[
        "Longmen"
    ],
    "name:pol_x_preferred":[
        "Longmen"
    ],
    "name:vie_x_preferred":[
        "Long M\u00f4n"
    ],
    "wof:name":"Longmen",
    "wof:placetype":"locality"
},
  "geometry": {"coordinates":[119.51582999999999,28.19639],"type":"Point"}
}