{
  "type": "Feature",
  "properties": {
    "gn:admin1_code":"14.0",
    "gn:asciiname":"Sangyeguobucun",
    "gn:country_code":"CN",
    "gn:dem":4561,
    "gn:feature_class":"P",
    "gn:feature_code":"PPL",
    "gn:name":"Sangyeguobucun",
    "gn:population":0,
    "gn:timezone":"Asia/Urumqi",
    "iso:country":"CN",
    "name:zho_x_preferred":[
        "\u6851\u4e1a\u679c\u5e03\u6751"
    ],
    "wof:name":"Sangyeguobucun",
    "wof:placetype":"locality"
},
  "geometry": {"coordinates":[91.88951,31.28658],"type":"Point"}
}