{
  "type": "Feature",
  "properties": {
    "gn:admin1_code":"08",
    "gn:asciiname":"Dongsheng",
    "gn:country_code":"CN",
    "gn:dem":277,
    "gn:feature_class":"P",
    "gn:feature_code":"PPLA4",
    "gn:name":"Dongsheng",
    "gn:population":0,
    "gn:timezone":"Asia/Shanghai",
    "iso:country":"CN",
    "name:und_x_variant":[
        "Dongsheng Xiang"
    ],
    "name:zho_x_preferred":[
        "\u4e1c\u80dc"
    ],
    "name:zho_x_variant":[
        "\u4e1c\u80dc\u4e61"
    ],
    "wof:name":"Dongsheng",
    "wof:placetype":"locality"
},
  "geometry": {"coordinates":[126.66024,48.23299],"type":"Point"}
}