{
  "type": "Feature",
  "properties": {
    "gn:admin1_code":"26.0",
    "gn:asciiname":"Tanwan",
    "gn:country_code":"CN",
    "gn:dem":1699,
    "gn:feature_class":"P",
    "gn:feature_code":"PPL",
    "gn:name":"Tanwan",
    "gn:population":0,
    "gn:timezone":"Asia/Shanghai",
    "iso:country":"CN",
    "name:und_x_variant":[
        "\u6f6d\u6e7e"
    ],
    "wof:name":"Tanwan",
    "wof:placetype":"locality"
},
  "geometry": {"coordinates":[107.17578,34.01169],"type":"Point"}
}