{
  "type": "Feature",
  "properties": {
    "gn:admin1_code":"07",
    "gn:asciiname":"Anrenxi",
    "gn:country_code":"CN",
    "gn:dem":21,
    "gn:feature_class":"P",
    "gn:feature_code":"PPL",
    "gn:name":"Anrenxi",
    "gn:population":0,
    "gn:timezone":"Asia/Shanghai",
    "iso:country":"CN",
    "name:und_x_variant":[
        "An-jen-hsi",
        "Anrenxi"
    ],
    "name:zho_x_preferred":[
        "\u5b89\u4ec1\u6eaa"
    ],
    "wof:name":"Anrenxi",
    "wof:placetype":"locality"
},
  "geometry": {"coordinates":[118.84090999999999,26.29754],"type":"Point"}
}