{
  "type": "Feature",
  "properties": {
    "gn:admin1_code":"25",
    "gn:asciiname":"Daimi'an",
    "gn:country_code":"CN",
    "gn:dem":268,
    "gn:feature_class":"P",
    "gn:feature_code":"PPL",
    "gn:name":"Daimi\u2019an",
    "gn:population":0,
    "gn:timezone":"Asia/Shanghai",
    "iso:country":"CN",
    "name:und_x_variant":[
        "Daimi\u2019an"
    ],
    "name:zho_x_preferred":[
        "\u5cb1\u5bc6\u5eb5"
    ],
    "wof:name":"Daimi'an",
    "wof:placetype":"locality"
},
  "geometry": {"coordinates":[117.149,36.4113],"type":"Point"}
}