{
  "type": "Feature",
  "properties": {
    "gn:admin1_code":"04",
    "gn:asciiname":"Qiaotou",
    "gn:cc2":"CN",
    "gn:country_code":"CN",
    "gn:dem":7,
    "gn:feature_class":"P",
    "gn:feature_code":"PPL",
    "gn:name":"Qiaotou",
    "gn:population":0,
    "gn:timezone":"Asia/Shanghai",
    "iso:country":"CN",
    "name:ceb_x_preferred":[
        "Qiaotou"
    ],
    "name:deu_x_preferred":[
        "Qiaotou"
    ],
    "name:swe_x_preferred":[
        "Qiaotou"
    ],
    "name:und_x_variant":[
        "Ch\u2019iao-t\u2019ou",
        "Ch\u2019iao-t\u2019ou-chen",
        "Qiaotou"
    ],
    "name:zho_x_preferred":[
        "\u6865\u5934\u9547"
    ],
    "wof:name":"Qiaotou",
    "wof:placetype":"locality"
},
  "geometry": {"coordinates":[118.84999999999999,31.93333],"type":"Point"}
}