{
  "type": "Feature",
  "properties": {
    "gn:admin1_code":"3.0",
    "gn:asciiname":"Hongqiao",
    "gn:country_code":"CN",
    "gn:dem":156,
    "gn:feature_class":"P",
    "gn:feature_code":"PPL",
    "gn:name":"Hongqiao",
    "gn:population":0,
    "gn:timezone":"Asia/Shanghai",
    "iso:country":"CN",
    "name:zho_x_preferred":[
        "\u6d2a\u6865"
    ],
    "wof:name":"Hongqiao",
    "wof:placetype":"locality"
},
  "geometry": {"coordinates":[114.06100000000001,28.0096],"type":"Point"}
}