{
  "type": "Feature",
  "properties": {
    "gn:admin1_code":"10.0",
    "gn:asciiname":"Liuyuanzhuang",
    "gn:country_code":"CN",
    "gn:dem":1167,
    "gn:feature_class":"P",
    "gn:feature_code":"PPL",
    "gn:name":"Liuyuanzhuang",
    "gn:population":0,
    "gn:timezone":"Asia/Shanghai",
    "iso:country":"CN",
    "name:zho_x_preferred":[
        "\u5218\u5143\u5e84"
    ],
    "wof:name":"Liuyuanzhuang",
    "wof:placetype":"locality"
},
  "geometry": {"coordinates":[114.17104,40.17772],"type":"Point"}
}