{
  "type": "Feature",
  "properties": {
    "gn:admin1_code":"32.0",
    "gn:asciiname":"Angke",
    "gn:country_code":"CN",
    "gn:dem":3629,
    "gn:feature_class":"P",
    "gn:feature_code":"PPL",
    "gn:name":"Angke",
    "gn:population":0,
    "gn:timezone":"Asia/Shanghai",
    "iso:country":"CN",
    "name:zho_x_preferred":[
        "\u6602\u67ef"
    ],
    "wof:name":"Angke",
    "wof:placetype":"locality"
},
  "geometry": {"coordinates":[100.899,32.1601],"type":"Point"}
}