{
  "type": "Feature",
  "properties": {
    "gn:admin1_code":"1.0",
    "gn:asciiname":"Huolonggangcun",
    "gn:country_code":"CN",
    "gn:dem":32,
    "gn:feature_class":"P",
    "gn:feature_code":"PPL",
    "gn:name":"Huolonggangcun",
    "gn:population":0,
    "gn:timezone":"Asia/Shanghai",
    "iso:country":"CN",
    "name:zho_x_preferred":[
        "\u706b\u9f99\u5c97\u6751"
    ],
    "wof:name":"Huolonggangcun",
    "wof:placetype":"locality"
},
  "geometry": {"coordinates":[117.04291000000001,31.36371],"type":"Point"}
}