{
  "type": "Feature",
  "properties": {
    "gn:admin1_code":"16.0",
    "gn:asciiname":"Nianxiang",
    "gn:country_code":"CN",
    "gn:dem":436,
    "gn:feature_class":"P",
    "gn:feature_code":"PPL",
    "gn:name":"Nianxiang",
    "gn:population":0,
    "gn:timezone":"Asia/Shanghai",
    "iso:country":"CN",
    "name:zho_x_preferred":[
        "\u5ff5\u7965"
    ],
    "wof:name":"Nianxiang",
    "wof:placetype":"locality"
},
  "geometry": {"coordinates":[106.661,22.9402],"type":"Point"}
}