{
  "type": "Feature",
  "properties": {
    "gn:admin1_code":"3",
    "gn:asciiname":"Xilong",
    "gn:country_code":"CN",
    "gn:dem":392,
    "gn:feature_class":"P",
    "gn:feature_code":"PPL",
    "gn:name":"Xilong",
    "gn:population":0,
    "gn:timezone":"Asia/Shanghai",
    "iso:country":"CN",
    "name:zho_x_preferred":[
        "\u897f\u5785"
    ],
    "wof:name":"Xilong",
    "wof:placetype":"locality"
},
  "geometry": {"coordinates":[114.55500000000001,26.2111],"type":"Point"}
}