{
  "type": "Feature",
  "properties": {
    "gn:admin1_code":"2.0",
    "gn:asciiname":"Yezhujiang",
    "gn:country_code":"CN",
    "gn:dem":713,
    "gn:feature_class":"P",
    "gn:feature_code":"PPL",
    "gn:name":"Yezhujiang",
    "gn:population":0,
    "gn:timezone":"Asia/Shanghai",
    "iso:country":"CN",
    "name:zho_x_preferred":[
        "\u91ce\u732a\u5956"
    ],
    "wof:name":"Yezhujiang",
    "wof:placetype":"locality"
},
  "geometry": {"coordinates":[118.60753,28.29765],"type":"Point"}
}