{
  "type": "Feature",
  "properties": {
    "gn:admin1_code":"3.0",
    "gn:asciiname":"Baisancun",
    "gn:country_code":"CN",
    "gn:dem":286,
    "gn:feature_class":"P",
    "gn:feature_code":"PPL",
    "gn:name":"Baisancun",
    "gn:population":0,
    "gn:timezone":"Asia/Shanghai",
    "iso:country":"CN",
    "name:zho_x_preferred":[
        "\u67cf\u4e09\u6751"
    ],
    "wof:name":"Baisancun",
    "wof:placetype":"locality"
},
  "geometry": {"coordinates":[114.96741000000002,24.72348],"type":"Point"}
}