{
  "type": "Feature",
  "properties": {
    "gn:admin1_code":"29",
    "gn:asciiname":"Mosa",
    "gn:country_code":"CN",
    "gn:dem":1448,
    "gn:feature_class":"P",
    "gn:feature_code":"PPL",
    "gn:name":"Mosa",
    "gn:population":0,
    "gn:timezone":"Asia/Shanghai",
    "iso:country":"CN",
    "name:zho_x_preferred":[
        "\u6469\u6d12"
    ],
    "wof:name":"Mosa",
    "wof:placetype":"locality"
},
  "geometry": {"coordinates":[104.592,23.4328],"type":"Point"}
}