{
  "type": "Feature",
  "properties": {
    "gn:admin1_code":"29.0",
    "gn:asciiname":"Xiaohetou",
    "gn:country_code":"CN",
    "gn:dem":1936,
    "gn:feature_class":"P",
    "gn:feature_code":"PPL",
    "gn:name":"Xiaohetou",
    "gn:population":0,
    "gn:timezone":"Asia/Shanghai",
    "iso:country":"CN",
    "name:zho_x_preferred":[
        "\u5c0f\u6cb3\u5934"
    ],
    "wof:name":"Xiaohetou",
    "wof:placetype":"locality"
},
  "geometry": {"coordinates":[100.887,24.03],"type":"Point"}
}