{
  "type": "Feature",
  "properties": {
    "gn:admin1_code":"8.0",
    "gn:asciiname":"Xingshengtun",
    "gn:country_code":"CN",
    "gn:dem":135,
    "gn:feature_class":"P",
    "gn:feature_code":"PPL",
    "gn:name":"Xingshengtun",
    "gn:population":0,
    "gn:timezone":"Asia/Shanghai",
    "iso:country":"CN",
    "name:zho_x_preferred":[
        "\u5174\u80dc\u5c6f"
    ],
    "wof:name":"Xingshengtun",
    "wof:placetype":"locality"
},
  "geometry": {"coordinates":[128.51907,45.61311],"type":"Point"}
}