{
  "type": "Feature",
  "properties": {
    "gn:admin1_code":"9.0",
    "gn:asciiname":"Xiacaoying",
    "gn:country_code":"CN",
    "gn:dem":123,
    "gn:feature_class":"P",
    "gn:feature_code":"PPL",
    "gn:name":"Xiacaoying",
    "gn:population":0,
    "gn:timezone":"Asia/Shanghai",
    "iso:country":"CN",
    "name:zho_x_preferred":[
        "\u4e0b\u66f9\u8425"
    ],
    "wof:name":"Xiacaoying",
    "wof:placetype":"locality"
},
  "geometry": {"coordinates":[112.67995000000001,32.96461],"type":"Point"}
}