{
  "type": "Feature",
  "properties": {
    "gn:admin1_code":"26.0",
    "gn:asciiname":"Xiajiashan",
    "gn:country_code":"CN",
    "gn:dem":1317,
    "gn:feature_class":"P",
    "gn:feature_code":"PPL",
    "gn:name":"Xiajiashan",
    "gn:population":0,
    "gn:timezone":"Asia/Shanghai",
    "iso:country":"CN",
    "name:und_x_variant":[
        "\u590f\u5bb6\u5c71"
    ],
    "wof:name":"Xiajiashan",
    "wof:placetype":"locality"
},
  "geometry": {"coordinates":[106.81228,32.74609],"type":"Point"}
}