{
  "type": "Feature",
  "properties": {
    "gn:admin1_code":"11",
    "gn:asciiname":"Daligang",
    "gn:country_code":"CN",
    "gn:dem":96,
    "gn:feature_class":"P",
    "gn:feature_code":"PPL",
    "gn:name":"Daligang",
    "gn:population":0,
    "gn:timezone":"Asia/Shanghai",
    "iso:country":"CN",
    "name:zho_x_preferred":[
        "\u5927\u6817\u6e2f\u9547"
    ],
    "wof:name":"Daligang",
    "wof:placetype":"locality"
},
  "geometry": {"coordinates":[111.90000000000001,28.47389],"type":"Point"}
}