{
  "type": "Feature",
  "properties": {
    "gn:admin1_code":"9.0",
    "gn:asciiname":"Bawanggou",
    "gn:country_code":"CN",
    "gn:dem":700,
    "gn:feature_class":"P",
    "gn:feature_code":"PPL",
    "gn:name":"Bawanggou",
    "gn:population":0,
    "gn:timezone":"Asia/Shanghai",
    "iso:country":"CN",
    "name:zho_x_preferred":[
        "\u9738\u738b\u6c9f"
    ],
    "wof:name":"Bawanggou",
    "wof:placetype":"locality"
},
  "geometry": {"coordinates":[111.95941000000001,33.98905],"type":"Point"}
}