{
  "type": "Feature",
  "properties": {
    "gn:admin1_code":"3.0",
    "gn:asciiname":"Shuizhuyuan",
    "gn:country_code":"CN",
    "gn:dem":58,
    "gn:feature_class":"P",
    "gn:feature_code":"PPL",
    "gn:name":"Shuizhuyuan",
    "gn:population":0,
    "gn:timezone":"Asia/Shanghai",
    "iso:country":"CN",
    "name:zho_x_preferred":[
        "\u6c34\u7af9\u6e90"
    ],
    "wof:name":"Shuizhuyuan",
    "wof:placetype":"locality"
},
  "geometry": {"coordinates":[117.45350000000001,28.76388],"type":"Point"}
}