{
  "type": "Feature",
  "properties": {
    "gn:admin1_code":"32.0",
    "gn:asciiname":"Longnanzhai",
    "gn:country_code":"CN",
    "gn:dem":939,
    "gn:feature_class":"P",
    "gn:feature_code":"PPL",
    "gn:name":"Longnanzhai",
    "gn:population":0,
    "gn:timezone":"Asia/Shanghai",
    "iso:country":"CN",
    "name:zho_x_preferred":[
        "\u9f99\u5357\u5be8"
    ],
    "wof:name":"Longnanzhai",
    "wof:placetype":"locality"
},
  "geometry": {"coordinates":[106.09492,27.81513],"type":"Point"}
}