{
  "type": "Feature",
  "properties": {
    "gn:admin1_code":"15.0",
    "gn:asciiname":"Shangguocangtai",
    "gn:country_code":"CN",
    "gn:dem":3088,
    "gn:feature_class":"P",
    "gn:feature_code":"PPL",
    "gn:name":"Shangguocangtai",
    "gn:population":0,
    "gn:timezone":"Asia/Shanghai",
    "iso:country":"CN",
    "name:zho_x_preferred":[
        "\u4e0a\u9505\u82cd\u53f0"
    ],
    "wof:name":"Shangguocangtai",
    "wof:placetype":"locality"
},
  "geometry": {"coordinates":[102.27200000000001,37.4916],"type":"Point"}
}