{
  "type": "Feature",
  "properties": {
    "gn:admin1_code":"21.0",
    "gn:asciiname":"Shangqing Shizui",
    "gn:country_code":"CN",
    "gn:dem":1912,
    "gn:feature_class":"P",
    "gn:feature_code":"PPL",
    "gn:name":"Shangqing Shizui",
    "gn:population":0,
    "gn:timezone":"Asia/Shanghai",
    "iso:country":"CN",
    "name:zho_x_preferred":[
        "\u4e0a\u9752\u77f3\u5480"
    ],
    "wof:name":"Shangqing Shizui",
    "wof:placetype":"locality"
},
  "geometry": {"coordinates":[106.26600000000001,35.8068],"type":"Point"}
}