{
  "type": "Feature",
  "properties": {
    "gn:admin1_code":"5.0",
    "gn:asciiname":"Nandamen",
    "gn:country_code":"CN",
    "gn:dem":684,
    "gn:feature_class":"P",
    "gn:feature_code":"PPL",
    "gn:name":"Nandamen",
    "gn:population":0,
    "gn:timezone":"Asia/Shanghai",
    "iso:country":"CN",
    "name:und_x_variant":[
        "\u5357\u5927\u95e8"
    ],
    "wof:name":"Nandamen",
    "wof:placetype":"locality"
},
  "geometry": {"coordinates":[127.36046,42.20611],"type":"Point"}
}