{
  "type": "Feature",
  "properties": {
    "gn:admin1_code":"29.0",
    "gn:asciiname":"Xiaoxiantang",
    "gn:country_code":"CN",
    "gn:dem":2067,
    "gn:feature_class":"P",
    "gn:feature_code":"PPL",
    "gn:name":"Xiaoxiantang",
    "gn:population":0,
    "gn:timezone":"Asia/Shanghai",
    "iso:country":"CN",
    "name:zho_x_preferred":[
        "\u5c0f\u9677\u5858"
    ],
    "wof:name":"Xiaoxiantang",
    "wof:placetype":"locality"
},
  "geometry": {"coordinates":[103.018,26.3952],"type":"Point"}
}