{
  "type": "Feature",
  "properties": {
    "gn:admin1_code":"32.0",
    "gn:asciiname":"Waluoyizu",
    "gn:country_code":"CN",
    "gn:dem":2846,
    "gn:feature_class":"P",
    "gn:feature_code":"PPL",
    "gn:name":"Waluoyizu",
    "gn:population":0,
    "gn:timezone":"Asia/Shanghai",
    "iso:country":"CN",
    "name:zho_x_preferred":[
        "\u54c7\u843d\u5f5d\u65cf"
    ],
    "wof:name":"Waluoyizu",
    "wof:placetype":"locality"
},
  "geometry": {"coordinates":[101.23388,27.09079],"type":"Point"}
}