{
  "type": "Feature",
  "properties": {
    "gn:admin1_code":"10",
    "gn:asciiname":"Yinmajing",
    "gn:country_code":"CN",
    "gn:dem":1370,
    "gn:feature_class":"P",
    "gn:feature_code":"PPL",
    "gn:name":"Yinmajing",
    "gn:population":0,
    "gn:timezone":"Asia/Shanghai",
    "iso:country":"CN",
    "name:zho_x_preferred":[
        "\u996e\u9a6c\u4e95"
    ],
    "wof:name":"Yinmajing",
    "wof:placetype":"locality"
},
  "geometry": {"coordinates":[115.89448,41.8648],"type":"Point"}
}