{
  "type": "Feature",
  "properties": {
    "gn:admin1_code":"15.0",
    "gn:asciiname":"Xianbei Houcun",
    "gn:country_code":"CN",
    "gn:dem":1927,
    "gn:feature_class":"P",
    "gn:feature_code":"PPL",
    "gn:name":"Xianbei Houcun",
    "gn:population":0,
    "gn:timezone":"Asia/Shanghai",
    "iso:country":"CN",
    "name:zho_x_preferred":[
        "\u5c98\u80cc\u540e\u6751"
    ],
    "wof:name":"Xianbei Houcun",
    "wof:placetype":"locality"
},
  "geometry": {"coordinates":[105.223,36.1356],"type":"Point"}
}