{
  "type": "Feature",
  "properties": {
    "gn:admin1_code":"12.0",
    "gn:asciiname":"Zhayingchang",
    "gn:country_code":"CN",
    "gn:dem":1406,
    "gn:feature_class":"P",
    "gn:feature_code":"PPL",
    "gn:name":"Zhayingchang",
    "gn:population":0,
    "gn:timezone":"Asia/Shanghai",
    "iso:country":"CN",
    "name:zho_x_preferred":[
        "\u624e\u8425\u573a"
    ],
    "wof:name":"Zhayingchang",
    "wof:placetype":"locality"
},
  "geometry": {"coordinates":[111.10553,31.44234],"type":"Point"}
}