{
  "type": "Feature",
  "properties": {
    "gn:admin1_code":"18",
    "gn:asciiname":"Hailian",
    "gn:country_code":"CN",
    "gn:dem":1384,
    "gn:feature_class":"P",
    "gn:feature_code":"PPL",
    "gn:name":"Hailian",
    "gn:population":0,
    "gn:timezone":"Asia/Shanghai",
    "iso:country":"CN",
    "name:zho_x_preferred":[
        "\u6d77\u8054"
    ],
    "wof:name":"Hailian",
    "wof:placetype":"locality"
},
  "geometry": {"coordinates":[105.47199999999999,25.1375],"type":"Point"}
}