{
  "type": "Feature",
  "properties": {
    "gn:admin1_code":"20.0",
    "gn:asciiname":"Erdao Hezi",
    "gn:country_code":"CN",
    "gn:dem":707,
    "gn:feature_class":"P",
    "gn:feature_code":"PPL",
    "gn:name":"Erdao Hezi",
    "gn:population":0,
    "gn:timezone":"Asia/Shanghai",
    "iso:country":"CN",
    "name:zho_x_preferred":[
        "\u4e8c\u9053\u6cb3\u5b50"
    ],
    "wof:name":"Erdao Hezi",
    "wof:placetype":"locality"
},
  "geometry": {"coordinates":[120.76308,50.77382],"type":"Point"}
}