{
  "type": "Feature",
  "properties": {
    "gn:admin1_code":"30",
    "gn:asciiname":"Langtian",
    "gn:country_code":"CN",
    "gn:dem":120,
    "gn:feature_class":"P",
    "gn:feature_code":"PPLA4",
    "gn:name":"Langtian",
    "gn:population":0,
    "gn:timezone":"Asia/Shanghai",
    "iso:country":"CN",
    "name:und_x_variant":[
        "\u5eca\u7530",
        "Langtian Zhen",
        "\u5eca\u7530\u9547"
    ],
    "wof:name":"Langtian",
    "wof:placetype":"locality"
},
  "geometry": {"coordinates":[113.45312,25.15507],"type":"Point"}
}