{
  "type": "Feature",
  "properties": {
    "gn:admin1_code":"18",
    "gn:asciiname":"Maojiaping",
    "gn:country_code":"CN",
    "gn:dem":868,
    "gn:feature_class":"P",
    "gn:feature_code":"PPL",
    "gn:name":"Maojiaping",
    "gn:population":0,
    "gn:timezone":"Asia/Shanghai",
    "iso:country":"CN",
    "name:zho_x_preferred":[
        "\u6bdb\u5bb6\u576a"
    ],
    "wof:name":"Maojiaping",
    "wof:placetype":"locality"
},
  "geometry": {"coordinates":[107.36199999999999,28.1902],"type":"Point"}
}