{
  "type": "Feature",
  "properties": {
    "gn:admin1_code":"18.0",
    "gn:asciiname":"Paiweng",
    "gn:country_code":"CN",
    "gn:dem":904,
    "gn:feature_class":"P",
    "gn:feature_code":"PPL",
    "gn:name":"Paiweng",
    "gn:population":0,
    "gn:timezone":"Asia/Shanghai",
    "iso:country":"CN",
    "name:zho_x_preferred":[
        "\u6392\u7fc1"
    ],
    "wof:name":"Paiweng",
    "wof:placetype":"locality"
},
  "geometry": {"coordinates":[108.04900000000001,26.3508],"type":"Point"}
}