{
  "type": "Feature",
  "properties": {
    "gn:admin1_code":"25.0",
    "gn:asciiname":"Lijiatuancun",
    "gn:country_code":"CN",
    "gn:dem":39,
    "gn:feature_class":"P",
    "gn:feature_code":"PPL",
    "gn:name":"Lijiatuancun",
    "gn:population":0,
    "gn:timezone":"Asia/Shanghai",
    "iso:country":"CN",
    "name:zho_x_preferred":[
        "\u674e\u5bb6\u7583\u6751"
    ],
    "wof:name":"Lijiatuancun",
    "wof:placetype":"locality"
},
  "geometry": {"coordinates":[120.34708999999999,36.40549],"type":"Point"}
}