{
  "type": "Feature",
  "properties": {
    "gn:admin1_code":"10.0",
    "gn:asciiname":"Yangjiazhuang",
    "gn:country_code":"CN",
    "gn:dem":12,
    "gn:feature_class":"P",
    "gn:feature_code":"PPL",
    "gn:name":"Yangjiazhuang",
    "gn:population":0,
    "gn:timezone":"Asia/Shanghai",
    "iso:country":"CN",
    "name:zho_x_preferred":[
        "\u6768\u5bb6\u5e84"
    ],
    "wof:name":"Yangjiazhuang",
    "wof:placetype":"locality"
},
  "geometry": {"coordinates":[117.93518,39.63428],"type":"Point"}
}