{
  "type": "Feature",
  "properties": {
    "gn:admin1_code":"3.0",
    "gn:asciiname":"Nitan",
    "gn:country_code":"CN",
    "gn:dem":162,
    "gn:feature_class":"P",
    "gn:feature_code":"PPL",
    "gn:name":"Nitan",
    "gn:population":0,
    "gn:timezone":"Asia/Shanghai",
    "iso:country":"CN",
    "name:und_x_variant":[
        "\u6ce5\u6f6d"
    ],
    "wof:name":"Nitan",
    "wof:placetype":"locality"
},
  "geometry": {"coordinates":[116.38312000000001,26.7739],"type":"Point"}
}