{
  "type": "Feature",
  "properties": {
    "gn:admin1_code":"26.0",
    "gn:asciiname":"Shang'anmencun",
    "gn:country_code":"CN",
    "gn:dem":1408,
    "gn:feature_class":"P",
    "gn:feature_code":"PPL",
    "gn:name":"Shang\u2019anmencun",
    "gn:population":0,
    "gn:timezone":"Asia/Shanghai",
    "iso:country":"CN",
    "name:und_x_variant":[
        "Shang\u2019anmencun"
    ],
    "name:zho_x_preferred":[
        "\u4e0a\u6697\u95e8\u6751"
    ],
    "wof:name":"Shang'anmencun",
    "wof:placetype":"locality"
},
  "geometry": {"coordinates":[107.607,37.5201],"type":"Point"}
}