{
  "type": "Feature",
  "properties": {
    "gn:admin1_code":"18",
    "gn:asciiname":"Pingdi",
    "gn:cc2":"CN",
    "gn:country_code":"CN",
    "gn:dem":488,
    "gn:feature_class":"P",
    "gn:feature_code":"PPL",
    "gn:name":"Pingdi",
    "gn:population":0,
    "gn:timezone":"Asia/Shanghai",
    "iso:country":"CN",
    "name:und_x_variant":[
        "Pingdi Zhen",
        "Pingdi"
    ],
    "wof:name":"Pingdi",
    "wof:placetype":"locality"
},
  "geometry": {"coordinates":[109.065,27.02333],"type":"Point"}
}