{
  "type": "Feature",
  "properties": {
    "gn:admin1_code":"29",
    "gn:asciiname":"Shanbeihou",
    "gn:country_code":"CN",
    "gn:dem":2105,
    "gn:feature_class":"P",
    "gn:feature_code":"PPL",
    "gn:name":"Shanbeihou",
    "gn:population":0,
    "gn:timezone":"Asia/Shanghai",
    "iso:country":"CN",
    "name:zho_x_preferred":[
        "\u5c71\u80cc\u540e"
    ],
    "wof:name":"Shanbeihou",
    "wof:placetype":"locality"
},
  "geometry": {"coordinates":[102.01779999999999,24.7405],"type":"Point"}
}