{
  "type": "Feature",
  "properties": {
    "gn:admin1_code":"26.0",
    "gn:asciiname":"Dahedi",
    "gn:country_code":"CN",
    "gn:dem":1705,
    "gn:feature_class":"P",
    "gn:feature_code":"PPL",
    "gn:name":"Dahedi",
    "gn:population":0,
    "gn:timezone":"Asia/Shanghai",
    "iso:country":"CN",
    "name:und_x_variant":[
        "\u5927\u6cb3\u5730"
    ],
    "wof:name":"Dahedi",
    "wof:placetype":"locality"
},
  "geometry": {"coordinates":[106.48802999999999,33.31825],"type":"Point"}
}