{
  "type": "Feature",
  "properties": {
    "gn:admin1_code":"12.0",
    "gn:asciiname":"Qianhoupeng",
    "gn:country_code":"CN",
    "gn:dem":28,
    "gn:feature_class":"P",
    "gn:feature_code":"PPL",
    "gn:name":"Qianhoupeng",
    "gn:population":0,
    "gn:timezone":"Asia/Shanghai",
    "iso:country":"CN",
    "name:zho_x_preferred":[
        "\u524d\u540e\u5f6d"
    ],
    "wof:name":"Qianhoupeng",
    "wof:placetype":"locality"
},
  "geometry": {"coordinates":[113.79658000000001,30.97152],"type":"Point"}
}