{
  "type": "Feature",
  "properties": {
    "gn:admin1_code":"14.0",
    "gn:asciiname":"Jiangqiulin",
    "gn:country_code":"CN",
    "gn:dem":3719,
    "gn:feature_class":"P",
    "gn:feature_code":"PPL",
    "gn:name":"Jiangqiulin",
    "gn:population":0,
    "gn:timezone":"Asia/Shanghai",
    "iso:country":"CN",
    "name:zho_x_preferred":[
        "\u6c5f\u79cb\u6797"
    ],
    "wof:name":"Jiangqiulin",
    "wof:placetype":"locality"
},
  "geometry": {"coordinates":[78.7424,32.1488],"type":"Point"}
}