{
  "type": "Feature",
  "properties": {
    "gn:admin1_code":"2.0",
    "gn:asciiname":"Houlunhu",
    "gn:country_code":"CN",
    "gn:dem":56,
    "gn:feature_class":"P",
    "gn:feature_code":"PPL",
    "gn:name":"Houlunhu",
    "gn:population":0,
    "gn:timezone":"Asia/Shanghai",
    "iso:country":"CN",
    "name:und_x_variant":[
        "\u539a\u4f26\u80e1",
        "Houlunhu"
    ],
    "wof:name":"Houlunhu",
    "wof:placetype":"locality"
},
  "geometry": {"coordinates":[119.30141999999999,29.2146],"type":"Point"}
}