{
  "type": "Feature",
  "properties": {
    "gn:admin1_code":"15.0",
    "gn:asciiname":"Weizigou",
    "gn:country_code":"CN",
    "gn:dem":1101,
    "gn:feature_class":"P",
    "gn:feature_code":"PPL",
    "gn:name":"Weizigou",
    "gn:population":0,
    "gn:timezone":"Asia/Shanghai",
    "iso:country":"CN",
    "name:und_x_variant":[
        "\u6e2d\u5b50\u6c9f"
    ],
    "name:zho_x_preferred":[
        "\u6e2d\u5b50\u6c9f"
    ],
    "wof:name":"Weizigou",
    "wof:placetype":"locality"
},
  "geometry": {"coordinates":[104.86981000000002,33.40174],"type":"Point"}
}