{
  "type": "Feature",
  "properties": {
    "gn:admin1_code":"5.0",
    "gn:asciiname":"Houxinhuang",
    "gn:country_code":"CN",
    "gn:dem":133,
    "gn:feature_class":"P",
    "gn:feature_code":"PPL",
    "gn:name":"Houxinhuang",
    "gn:population":0,
    "gn:timezone":"Asia/Shanghai",
    "iso:country":"CN",
    "name:zho_x_preferred":[
        "\u540e\u65b0\u8352"
    ],
    "wof:name":"Houxinhuang",
    "wof:placetype":"locality"
},
  "geometry": {"coordinates":[123.72911000000001,45.63719],"type":"Point"}
}