{
  "type": "Feature",
  "properties": {
    "gn:admin1_code":"20",
    "gn:asciiname":"Luanjing",
    "gn:cc2":"CN",
    "gn:country_code":"CN",
    "gn:dem":1348,
    "gn:feature_class":"P",
    "gn:feature_code":"PPL",
    "gn:name":"Luanjing",
    "gn:population":0,
    "gn:timezone":"Asia/Shanghai",
    "iso:country":"CN",
    "name:und_x_variant":[
        "Luan-ching",
        "Luanjing"
    ],
    "wof:name":"Luanjing",
    "wof:placetype":"locality"
},
  "geometry": {"coordinates":[105.36417,37.96556],"type":"Point"}
}