{
  "type": "Feature",
  "properties": {
    "gn:admin1_code":"19.0",
    "gn:asciiname":"Wanjintai",
    "gn:country_code":"CN",
    "gn:dem":40,
    "gn:feature_class":"P",
    "gn:feature_code":"PPL",
    "gn:name":"Wanjintai",
    "gn:population":0,
    "gn:timezone":"Asia/Shanghai",
    "iso:country":"CN",
    "name:zho_x_preferred":[
        "\u4e07\u91d1\u53f0"
    ],
    "wof:name":"Wanjintai",
    "wof:placetype":"locality"
},
  "geometry": {"coordinates":[123.2372,42.03806],"type":"Point"}
}