{
  "type": "Feature",
  "properties": {
    "gn:admin1_code":"3.0",
    "gn:asciiname":"Longzaichong",
    "gn:country_code":"CN",
    "gn:dem":240,
    "gn:feature_class":"P",
    "gn:feature_code":"PPL",
    "gn:name":"Longzaichong",
    "gn:population":0,
    "gn:timezone":"Asia/Shanghai",
    "iso:country":"CN",
    "name:und_x_variant":[
        "\u9f99\u4ed4\u51b2"
    ],
    "wof:name":"Longzaichong",
    "wof:placetype":"locality"
},
  "geometry": {"coordinates":[114.47674000000001,27.7502],"type":"Point"}
}