{
  "type": "Feature",
  "properties": {
    "gn:admin1_code":"32",
    "gn:asciiname":"Qinghua",
    "gn:country_code":"CN",
    "gn:dem":275,
    "gn:feature_class":"P",
    "gn:feature_code":"PPL",
    "gn:name":"Qinghua",
    "gn:population":0,
    "gn:timezone":"Asia/Shanghai",
    "iso:country":"CN",
    "name:und_x_variant":[
        "Ch\u2019ing-hua-chen",
        "Qinghuazhen",
        "Huayun",
        "Huaying",
        "Qinghua"
    ],
    "wof:name":"Qinghua",
    "wof:placetype":"locality"
},
  "geometry": {"coordinates":[106.66755999999999,30.21322],"type":"Point"}
}