{
  "type": "Feature",
  "properties": {
    "gn:admin1_code":"12.0",
    "gn:asciiname":"Yongjiapo",
    "gn:country_code":"CN",
    "gn:dem":1251,
    "gn:feature_class":"P",
    "gn:feature_code":"PPL",
    "gn:name":"Yongjiapo",
    "gn:population":0,
    "gn:timezone":"Asia/Shanghai",
    "iso:country":"CN",
    "name:zho_x_preferred":[
        "Yongjiapo"
    ],
    "name:zho_x_variant":[
        "\u6c38\u5bb6\u5761"
    ],
    "wof:name":"Yongjiapo",
    "wof:placetype":"locality"
},
  "geometry": {"coordinates":[109.75676,29.76026],"type":"Point"}
}