{
  "type": "Feature",
  "properties": {
    "gn:admin1_code":"29.0",
    "gn:asciiname":"Haoziping",
    "gn:country_code":"CN",
    "gn:dem":1931,
    "gn:feature_class":"P",
    "gn:feature_code":"PPL",
    "gn:name":"Haoziping",
    "gn:population":0,
    "gn:timezone":"Asia/Shanghai",
    "iso:country":"CN",
    "name:zho_x_preferred":[
        "\u84bf\u5b50\u576a"
    ],
    "wof:name":"Haoziping",
    "wof:placetype":"locality"
},
  "geometry": {"coordinates":[101.28100000000001,26.2946],"type":"Point"}
}