{
  "type": "Feature",
  "properties": {
    "gn:admin1_code":"8.0",
    "gn:asciiname":"Caoshantun",
    "gn:country_code":"CN",
    "gn:dem":157,
    "gn:feature_class":"P",
    "gn:feature_code":"PPL",
    "gn:name":"Caoshantun",
    "gn:population":0,
    "gn:timezone":"Asia/Shanghai",
    "iso:country":"CN",
    "name:zho_x_preferred":[
        "\u66f9\u5c71\u5c6f"
    ],
    "wof:name":"Caoshantun",
    "wof:placetype":"locality"
},
  "geometry": {"coordinates":[125.32548,46.29077],"type":"Point"}
}