{
  "type": "Feature",
  "properties": {
    "gn:admin1_code":"1.0",
    "gn:asciiname":"Xialuchong",
    "gn:country_code":"CN",
    "gn:dem":50,
    "gn:feature_class":"P",
    "gn:feature_code":"PPL",
    "gn:name":"Xialuchong",
    "gn:population":0,
    "gn:timezone":"Asia/Shanghai",
    "iso:country":"CN",
    "name:zho_x_preferred":[
        "Xialuchong"
    ],
    "name:zho_x_variant":[
        "\u4e0b\u82a6\u51b2"
    ],
    "wof:name":"Xialuchong",
    "wof:placetype":"locality"
},
  "geometry": {"coordinates":[119.4293,31.05986],"type":"Point"}
}