{
  "type": "Feature",
  "properties": {
    "gn:admin1_code":"04",
    "gn:asciiname":"Nanxinjiecun",
    "gn:country_code":"CN",
    "gn:dem":10,
    "gn:feature_class":"P",
    "gn:feature_code":"PPL",
    "gn:name":"Nanxinjiecun",
    "gn:population":0,
    "gn:timezone":"Asia/Shanghai",
    "iso:country":"CN",
    "name:und_x_variant":[
        "Nanxin",
        "\u5357\u65b0",
        "Nanxinjie",
        "Nanxinjiecun"
    ],
    "name:zho_x_preferred":[
        "\u5357\u65b0\u8857"
    ],
    "name:zho_x_variant":[
        "\u5357\u65b0\u8857\u6751"
    ],
    "wof:name":"Nanxinjiecun",
    "wof:placetype":"locality"
},
  "geometry": {"coordinates":[120.11741000000001,32.29442],"type":"Point"}
}