{
  "type": "Feature",
  "properties": {
    "gn:admin1_code":"12.0",
    "gn:asciiname":"Zheshukou",
    "gn:country_code":"CN",
    "gn:dem":28,
    "gn:feature_class":"P",
    "gn:feature_code":"PPL",
    "gn:name":"Zheshukou",
    "gn:population":0,
    "gn:timezone":"Asia/Shanghai",
    "iso:country":"CN",
    "name:zho_x_preferred":[
        "\u67d8\u6811\u53e3"
    ],
    "wof:name":"Zheshukou",
    "wof:placetype":"locality"
},
  "geometry": {"coordinates":[113.85642,30.72411],"type":"Point"}
}