{
  "type": "Feature",
  "properties": {
    "gn:admin1_code":"32.0",
    "gn:asciiname":"Pengxi",
    "gn:country_code":"CN",
    "gn:dem":3231,
    "gn:feature_class":"P",
    "gn:feature_code":"PPL",
    "gn:name":"Pengxi",
    "gn:population":0,
    "gn:timezone":"Asia/Shanghai",
    "iso:country":"CN",
    "name:zho_x_preferred":[
        "\u5f6d\u6eaa"
    ],
    "wof:name":"Pengxi",
    "wof:placetype":"locality"
},
  "geometry": {"coordinates":[102.70399999999999,34.1108],"type":"Point"}
}