{
  "type": "Feature",
  "properties": {
    "gn:admin1_code":"30.0",
    "gn:asciiname":"Hua'an",
    "gn:country_code":"CN",
    "gn:dem":-3,
    "gn:feature_class":"P",
    "gn:feature_code":"PPL",
    "gn:name":"Hua\u2019an",
    "gn:population":0,
    "gn:timezone":"Asia/Shanghai",
    "iso:country":"CN",
    "name:und_x_variant":[
        "Hua\u2019an"
    ],
    "name:zho_x_preferred":[
        "\u534e\u5b89"
    ],
    "wof:name":"Hua'an",
    "wof:placetype":"locality"
},
  "geometry": {"coordinates":[112.73454,22.29722000000001],"type":"Point"}
}