{
  "type": "Feature",
  "properties": {
    "gn:admin1_code":"26.0",
    "gn:asciiname":"Changliangwan",
    "gn:country_code":"CN",
    "gn:dem":1138,
    "gn:feature_class":"P",
    "gn:feature_code":"PPL",
    "gn:name":"Changliangwan",
    "gn:population":0,
    "gn:timezone":"Asia/Shanghai",
    "iso:country":"CN",
    "name:zho_x_preferred":[
        "\u957f\u6881\u6e7e"
    ],
    "wof:name":"Changliangwan",
    "wof:placetype":"locality"
},
  "geometry": {"coordinates":[109.42489,37.97372],"type":"Point"}
}