{
  "type": "Feature",
  "properties": {
    "gn:admin1_code":"18.0",
    "gn:asciiname":"Diba",
    "gn:country_code":"CN",
    "gn:dem":959,
    "gn:feature_class":"P",
    "gn:feature_code":"PPL",
    "gn:name":"Diba",
    "gn:population":0,
    "gn:timezone":"Asia/Shanghai",
    "iso:country":"CN",
    "name:cat_x_preferred":[
        "Diba"
    ],
    "name:ceb_x_preferred":[
        "Diba"
    ],
    "name:deu_x_preferred":[
        "Diba"
    ],
    "name:fra_x_preferred":[
        "Diba"
    ],
    "name:swe_x_preferred":[
        "Diba"
    ],
    "name:zho_x_preferred":[
        "\u5730\u575d"
    ],
    "wof:name":"Diba",
    "wof:placetype":"locality"
},
  "geometry": {"coordinates":[107.39400000000001,25.4116],"type":"Point"}
}