{
  "type": "Feature",
  "properties": {
    "gn:admin1_code":"18",
    "gn:asciiname":"Laoyuanzi",
    "gn:country_code":"CN",
    "gn:dem":1661,
    "gn:feature_class":"P",
    "gn:feature_code":"PPL",
    "gn:name":"Laoyuanzi",
    "gn:population":0,
    "gn:timezone":"Asia/Shanghai",
    "iso:country":"CN",
    "name:zho_x_preferred":[
        "\u8001\u9662\u5b50"
    ],
    "wof:name":"Laoyuanzi",
    "wof:placetype":"locality"
},
  "geometry": {"coordinates":[104.34699999999999,26.706],"type":"Point"}
}