{
  "type": "Feature",
  "properties": {
    "gn:admin1_code":"19.0",
    "gn:asciiname":"Zangjialiang",
    "gn:country_code":"CN",
    "gn:dem":589,
    "gn:feature_class":"P",
    "gn:feature_code":"PPL",
    "gn:name":"Zangjialiang",
    "gn:population":0,
    "gn:timezone":"Asia/Shanghai",
    "iso:country":"CN",
    "name:zho_x_preferred":[
        "\u81e7\u5bb6\u6881"
    ],
    "wof:name":"Zangjialiang",
    "wof:placetype":"locality"
},
  "geometry": {"coordinates":[119.08960999999999,40.97604000000001],"type":"Point"}
}