{
  "type": "Feature",
  "properties": {
    "gn:admin1_code":"30",
    "gn:asciiname":"Baoping",
    "gn:country_code":"CN",
    "gn:dem":1,
    "gn:feature_class":"P",
    "gn:feature_code":"PPL",
    "gn:name":"Baoping",
    "gn:population":0,
    "gn:timezone":"Asia/Shanghai",
    "iso:country":"CN",
    "name:zho_x_preferred":[
        "\u62a5\u5e73"
    ],
    "wof:name":"Baoping",
    "wof:placetype":"locality"
},
  "geometry": {"coordinates":[111.99787000000001,21.84841],"type":"Point"}
}