{
  "type": "Feature",
  "properties": {
    "gn:admin1_code":"30",
    "gn:asciiname":"Heping Nongchang",
    "gn:country_code":"CN",
    "gn:dem":45,
    "gn:feature_class":"P",
    "gn:feature_code":"PPLF",
    "gn:name":"Heping Nongchang",
    "gn:population":0,
    "gn:timezone":"Asia/Urumqi",
    "iso:country":"CN",
    "wof:name":"Heping Nongchang",
    "wof:placetype":"locality"
},
  "geometry": {"coordinates":[110.42167000000001,21.87944],"type":"Point"}
}