{
  "type": "Feature",
  "properties": {
    "gn:admin1_code":"18",
    "gn:asciiname":"Jiake",
    "gn:country_code":"CN",
    "gn:dem":953,
    "gn:feature_class":"P",
    "gn:feature_code":"PPL",
    "gn:name":"Jiake",
    "gn:population":0,
    "gn:timezone":"Asia/Shanghai",
    "iso:country":"CN",
    "name:zho_x_preferred":[
        "\u52a0\u79d1"
    ],
    "wof:name":"Jiake",
    "wof:placetype":"locality"
},
  "geometry": {"coordinates":[105.33499999999999,27.7272],"type":"Point"}
}