{
  "type": "Feature",
  "properties": {
    "gn:admin1_code":"30.0",
    "gn:asciiname":"Zhongbian",
    "gn:country_code":"CN",
    "gn:dem":3,
    "gn:feature_class":"P",
    "gn:feature_code":"PPL",
    "gn:name":"Zhongbian",
    "gn:population":0,
    "gn:timezone":"Asia/Shanghai",
    "iso:country":"CN",
    "name:zho_x_preferred":[
        "\u9418\u908a"
    ],
    "wof:name":"Zhongbian",
    "wof:placetype":"locality"
},
  "geometry": {"coordinates":[113.10778999999999,23.09698],"type":"Point"}
}