{
  "type": "Feature",
  "properties": {
    "gn:admin1_code":"19.0",
    "gn:asciiname":"Gelihecun",
    "gn:country_code":"CN",
    "gn:dem":9,
    "gn:feature_class":"P",
    "gn:feature_code":"PPL",
    "gn:name":"Gelihecun",
    "gn:population":0,
    "gn:timezone":"Asia/Shanghai",
    "iso:country":"CN",
    "name:zho_x_preferred":[
        "\u86e4\u870a\u6cb3\u6751"
    ],
    "wof:name":"Gelihecun",
    "wof:placetype":"locality"
},
  "geometry": {"coordinates":[122.59099999999999,41.2057],"type":"Point"}
}