{
  "type": "Feature",
  "properties": {
    "gn:admin1_code":"16",
    "gn:asciiname":"Zhaitou",
    "gn:country_code":"CN",
    "gn:dem":188,
    "gn:feature_class":"P",
    "gn:feature_code":"PPL",
    "gn:name":"Zhaitou",
    "gn:population":0,
    "gn:timezone":"Asia/Shanghai",
    "iso:country":"CN",
    "name:zho_x_preferred":[
        "\u658b\u5934"
    ],
    "wof:name":"Zhaitou",
    "wof:placetype":"locality"
},
  "geometry": {"coordinates":[109.971,25.1665],"type":"Point"}
}