{
  "type": "Feature",
  "properties": {
    "gn:admin1_code":"7.0",
    "gn:asciiname":"Zhengdun",
    "gn:country_code":"CN",
    "gn:dem":304,
    "gn:feature_class":"P",
    "gn:feature_code":"PPL",
    "gn:name":"Zhengdun",
    "gn:population":0,
    "gn:timezone":"Asia/Shanghai",
    "iso:country":"CN",
    "name:und_x_variant":[
        "\u90d1\u58a9"
    ],
    "name:zho_x_preferred":[
        "\u90d1\u58a9"
    ],
    "wof:name":"Zhengdun",
    "wof:placetype":"locality"
},
  "geometry": {"coordinates":[118.00141000000001,26.39416],"type":"Point"}
}