{
  "type": "Feature",
  "properties": {
    "gn:admin1_code":"6.0",
    "gn:asciiname":"Shenwu",
    "gn:country_code":"CN",
    "gn:dem":3428,
    "gn:feature_class":"P",
    "gn:feature_code":"PPL",
    "gn:name":"Shenwu",
    "gn:population":0,
    "gn:timezone":"Asia/Shanghai",
    "iso:country":"CN",
    "name:und_x_variant":[
        "\u7533\u543e"
    ],
    "wof:name":"Shenwu",
    "wof:placetype":"locality"
},
  "geometry": {"coordinates":[100.3946,35.34657],"type":"Point"}
}