{
  "type": "Feature",
  "properties": {
    "gn:admin1_code":"30.0",
    "gn:asciiname":"Youmayuan",
    "gn:country_code":"CN",
    "gn:dem":6,
    "gn:feature_class":"P",
    "gn:feature_code":"PPL",
    "gn:name":"Youmayuan",
    "gn:population":0,
    "gn:timezone":"Asia/Shanghai",
    "iso:country":"CN",
    "name:zho_x_preferred":[
        "\u6cb9\u9ebb\u56ed"
    ],
    "wof:name":"Youmayuan",
    "wof:placetype":"locality"
},
  "geometry": {"coordinates":[114.80535,22.63075],"type":"Point"}
}