{
  "type": "Feature",
  "properties": {
    "gn:admin1_code":"4.0",
    "gn:asciiname":"Gejiachuan",
    "gn:country_code":"CN",
    "gn:dem":5,
    "gn:feature_class":"P",
    "gn:feature_code":"PPL",
    "gn:name":"Gejiachuan",
    "gn:population":0,
    "gn:timezone":"Asia/Shanghai",
    "iso:country":"CN",
    "name:und_x_variant":[
        "\u845b\u5bb6\u5ddd"
    ],
    "wof:name":"Gejiachuan",
    "wof:placetype":"locality"
},
  "geometry": {"coordinates":[120.96108999999998,32.05888],"type":"Point"}
}