{
  "type": "Feature",
  "properties": {
    "gn:admin1_code":"18",
    "gn:asciiname":"Haojiawan",
    "gn:country_code":"CN",
    "gn:dem":521,
    "gn:feature_class":"P",
    "gn:feature_code":"PPL",
    "gn:name":"Haojiawan",
    "gn:population":0,
    "gn:timezone":"Asia/Shanghai",
    "iso:country":"CN",
    "name:zho_x_preferred":[
        "\u90dd\u5bb6\u6e7e"
    ],
    "wof:name":"Haojiawan",
    "wof:placetype":"locality"
},
  "geometry": {"coordinates":[108.19199999999999,27.6703],"type":"Point"}
}