{
  "type": "Feature",
  "properties": {
    "gn:admin1_code":"29.0",
    "gn:asciiname":"Xizhou",
    "gn:cc2":"CN",
    "gn:country_code":"CN",
    "gn:dem":1962,
    "gn:feature_class":"P",
    "gn:feature_code":"PPL",
    "gn:name":"Xizhou",
    "gn:population":0,
    "gn:timezone":"Asia/Shanghai",
    "iso:country":"CN",
    "name:deu_x_preferred":[
        "Xizhou"
    ],
    "name:und_x_variant":[
        "Hsi-chou",
        "Siechow"
    ],
    "wof:name":"Xizhou",
    "wof:placetype":"locality"
},
  "geometry": {"coordinates":[100.16667,25.81667],"type":"Point"}
}