{
  "type": "Feature",
  "properties": {
    "gn:admin1_code":"26.0",
    "gn:asciiname":"Tongdonggou",
    "gn:country_code":"CN",
    "gn:dem":1013,
    "gn:feature_class":"P",
    "gn:feature_code":"PPL",
    "gn:name":"Tongdonggou",
    "gn:population":0,
    "gn:timezone":"Asia/Shanghai",
    "iso:country":"CN",
    "name:zho_x_preferred":[
        "\u94dc\u6d1e\u6c9f"
    ],
    "wof:name":"Tongdonggou",
    "wof:placetype":"locality"
},
  "geometry": {"coordinates":[108.9195,33.619],"type":"Point"}
}