{
  "type": "Feature",
  "properties": {
    "gn:admin1_code":"6.0",
    "gn:asciiname":"Ti'eda",
    "gn:country_code":"CN",
    "gn:dem":4265,
    "gn:feature_class":"P",
    "gn:feature_code":"PPL",
    "gn:name":"Ti\u2019eda",
    "gn:population":0,
    "gn:timezone":"Asia/Urumqi",
    "iso:country":"CN",
    "name:und_x_variant":[
        "Ti\u2019eda"
    ],
    "name:zho_x_preferred":[
        "\u66ff\u4fc4\u8fbe"
    ],
    "wof:name":"Ti'eda",
    "wof:placetype":"locality"
},
  "geometry": {"coordinates":[96.80365999999999,33.03235],"type":"Point"}
}