{
  "type": "Feature",
  "properties": {
    "gn:admin1_code":"4.0",
    "gn:asciiname":"Xihu",
    "gn:country_code":"CN",
    "gn:dem":8,
    "gn:feature_class":"P",
    "gn:feature_code":"PPL",
    "gn:name":"Xihu",
    "gn:population":0,
    "gn:timezone":"Asia/Shanghai",
    "iso:country":"CN",
    "name:zho_x_preferred":[
        "Xihu"
    ],
    "name:zho_x_variant":[
        "\u897f\u80e1"
    ],
    "wof:name":"Xihu",
    "wof:placetype":"locality"
},
  "geometry": {"coordinates":[119.15129,34.98402],"type":"Point"}
}