{
  "type": "Feature",
  "properties": {
    "gn:admin1_code":"25",
    "gn:asciiname":"Liangxian",
    "gn:country_code":"CN",
    "gn:dem":323,
    "gn:feature_class":"P",
    "gn:feature_code":"PPL",
    "gn:name":"Liangxian",
    "gn:population":0,
    "gn:timezone":"Asia/Shanghai",
    "iso:country":"CN",
    "name:zho_x_preferred":[
        "\u4e24\u53bf"
    ],
    "wof:name":"Liangxian",
    "wof:placetype":"locality"
},
  "geometry": {"coordinates":[118.34999999999999,36.2321],"type":"Point"}
}