{
  "type": "Feature",
  "properties": {
    "gn:admin1_code":"26.0",
    "gn:asciiname":"Fengsicun",
    "gn:country_code":"CN",
    "gn:dem":1398,
    "gn:feature_class":"P",
    "gn:feature_code":"PPL",
    "gn:name":"Fengsicun",
    "gn:population":0,
    "gn:timezone":"Asia/Shanghai",
    "iso:country":"CN",
    "name:zho_x_preferred":[
        "\u51e4\u5bfa\u6751"
    ],
    "wof:name":"Fengsicun",
    "wof:placetype":"locality"
},
  "geometry": {"coordinates":[108.33663,37.04546],"type":"Point"}
}