{
  "type": "Feature",
  "properties": {
    "gn:admin1_code":"25",
    "gn:asciiname":"Niezhuang",
    "gn:country_code":"CN",
    "gn:dem":24,
    "gn:feature_class":"P",
    "gn:feature_code":"PPL",
    "gn:name":"Niezhuang",
    "gn:population":0,
    "gn:timezone":"Asia/Shanghai",
    "iso:country":"CN",
    "name:zho_x_preferred":[
        "\u8042\u5e84"
    ],
    "wof:name":"Niezhuang",
    "wof:placetype":"locality"
},
  "geometry": {"coordinates":[116.55500000000001,37.0632],"type":"Point"}
}