{
  "type": "Feature",
  "properties": {
    "gn:admin1_code":"8.0",
    "gn:asciiname":"Daheijia Wopeng",
    "gn:country_code":"CN",
    "gn:dem":134,
    "gn:feature_class":"P",
    "gn:feature_code":"PPL",
    "gn:name":"Daheijia Wopeng",
    "gn:population":0,
    "gn:timezone":"Asia/Shanghai",
    "iso:country":"CN",
    "name:zho_x_preferred":[
        "\u5927\u9ed1\u5bb6\u7a9d\u68da"
    ],
    "wof:name":"Daheijia Wopeng",
    "wof:placetype":"locality"
},
  "geometry": {"coordinates":[126.45628000000001,46.51496],"type":"Point"}
}