{
  "type": "Feature",
  "properties": {
    "gn:admin1_code":"2.0",
    "gn:asciiname":"Dakengtou",
    "gn:country_code":"CN",
    "gn:dem":140,
    "gn:feature_class":"P",
    "gn:feature_code":"PPL",
    "gn:name":"Dakengtou",
    "gn:population":0,
    "gn:timezone":"Asia/Shanghai",
    "iso:country":"CN",
    "name:zho_x_preferred":[
        "\u5927\u5751\u5934"
    ],
    "wof:name":"Dakengtou",
    "wof:placetype":"locality"
},
  "geometry": {"coordinates":[119.23259,28.92742],"type":"Point"}
}