{
  "type": "Feature",
  "properties": {
    "gn:admin1_code":"13.0",
    "gn:asciiname":"Sanertuan Yilinglian",
    "gn:country_code":"CN",
    "gn:dem":867,
    "gn:feature_class":"P",
    "gn:feature_code":"PPLF",
    "gn:name":"Sanertuan Yilinglian",
    "gn:population":0,
    "gn:timezone":"Asia/Urumqi",
    "iso:country":"CN",
    "name:zho_x_preferred":[
        "\u4e09\u5c14\u56e2\u4e00\u96f6\u8fde"
    ],
    "wof:name":"Sanertuan Yilinglian",
    "wof:placetype":"locality"
},
  "geometry": {"coordinates":[87.06531,40.86726],"type":"Point"}
}