{
  "type": "Feature",
  "properties": {
    "gn:admin1_code":"7.0",
    "gn:asciiname":"Xiadongkeng",
    "gn:country_code":"CN",
    "gn:dem":281,
    "gn:feature_class":"P",
    "gn:feature_code":"PPL",
    "gn:name":"Xiadongkeng",
    "gn:population":0,
    "gn:timezone":"Asia/Shanghai",
    "iso:country":"CN",
    "name:und_x_variant":[
        "\u4e0b\u4e1c\u5751"
    ],
    "name:zho_x_preferred":[
        "\u4e0b\u4e1c\u5751"
    ],
    "wof:name":"Xiadongkeng",
    "wof:placetype":"locality"
},
  "geometry": {"coordinates":[116.34419,25.59597],"type":"Point"}
}