{
  "type": "Feature",
  "properties": {
    "gn:admin1_code":"4.0",
    "gn:asciiname":"Sheyanggang",
    "gn:country_code":"CN",
    "gn:dem":3,
    "gn:feature_class":"P",
    "gn:feature_code":"PPL",
    "gn:name":"Sheyanggang",
    "gn:population":0,
    "gn:timezone":"Asia/Shanghai",
    "iso:country":"CN",
    "name:und_x_variant":[
        "\u5c04\u9633\u6e2f"
    ],
    "wof:name":"Sheyanggang",
    "wof:placetype":"locality"
},
  "geometry": {"coordinates":[120.42515,33.82232],"type":"Point"}
}