{
  "type": "Feature",
  "properties": {
    "gn:admin1_code":"3.0",
    "gn:asciiname":"Yunxing",
    "gn:country_code":"CN",
    "gn:dem":499,
    "gn:feature_class":"P",
    "gn:feature_code":"PPL",
    "gn:name":"Yunxing",
    "gn:population":0,
    "gn:timezone":"Asia/Shanghai",
    "iso:country":"CN",
    "name:und_x_variant":[
        "\u4e91\u661f"
    ],
    "wof:name":"Yunxing",
    "wof:placetype":"locality"
},
  "geometry": {"coordinates":[114.99634,29.40269],"type":"Point"}
}