{
  "type": "Feature",
  "properties": {
    "gn:admin1_code":"07",
    "gn:asciiname":"Houdeyang",
    "gn:country_code":"CN",
    "gn:dem":826,
    "gn:feature_class":"P",
    "gn:feature_code":"PPL",
    "gn:name":"Houdeyang",
    "gn:population":0,
    "gn:timezone":"Asia/Shanghai",
    "iso:country":"CN",
    "name:zho_x_preferred":[
        "\u539a\u5fb7\u6d0b"
    ],
    "wof:name":"Houdeyang",
    "wof:placetype":"locality"
},
  "geometry": {"coordinates":[118.20083,25.57611],"type":"Point"}
}