{
  "type": "Feature",
  "properties": {
    "gn:admin1_code":"18.0",
    "gn:asciiname":"Hexing",
    "gn:country_code":"CN",
    "gn:dem":756,
    "gn:feature_class":"P",
    "gn:feature_code":"PPLA4",
    "gn:name":"Hexing",
    "gn:population":0,
    "gn:timezone":"Asia/Shanghai",
    "iso:country":"CN",
    "name:ces_x_preferred":[
        "Hexing"
    ],
    "name:fra_x_preferred":[
        "Hexing"
    ],
    "name:mal_x_preferred":[
        "\u0d39\u0d46\u0d15\u0d4d\u0d38\u0d3f\u0d19\u0d4d\u0d19\u0d4d"
    ],
    "name:nld_x_preferred":[
        "Hexing"
    ],
    "name:ori_x_preferred":[
        "Hexing"
    ],
    "name:pol_x_preferred":[
        "Hexing"
    ],
    "name:por_x_preferred":[
        "Hexing qingyi"
    ],
    "name:spa_x_preferred":[
        "Hexing qingyi"
    ],
    "name:und_x_variant":[
        "Puziwan",
        "Hexing Tujiazu Xiang"
    ],
    "name:vie_x_preferred":[
        "Hexing"
    ],
    "name:zho_x_preferred":[
        "\u5408\u5174"
    ],
    "name:zho_x_variant":[
        "\u94fa\u5b50\u6e7e",
        "\u5408\u5174\u571f\u5bb6\u65cf\u4e61",
        "\u9db4\u5f62\u9f8d\u5c6c"
    ],
    "wof:name":"Hexing",
    "wof:placetype":"locality"
},
  "geometry": {"coordinates":[108.06233,28.10154],"type":"Point"}
}