{
  "type": "Feature",
  "properties": {
    "gn:admin1_code":"4.0",
    "gn:asciiname":"Dongshisixu",
    "gn:country_code":"CN",
    "gn:dem":7,
    "gn:feature_class":"P",
    "gn:feature_code":"PPLF",
    "gn:name":"Dongshisixu",
    "gn:population":0,
    "gn:timezone":"Asia/Shanghai",
    "iso:country":"CN",
    "name:zho_x_preferred":[
        "\u4e1c\u5341\u56db\u5729"
    ],
    "wof:name":"Dongshisixu",
    "wof:placetype":"locality"
},
  "geometry": {"coordinates":[120.40201,32.11119],"type":"Point"}
}