{
  "type": "Feature",
  "properties": {
    "gn:admin1_code":"7.0",
    "gn:asciiname":"Shuizhuke",
    "gn:country_code":"CN",
    "gn:dem":322,
    "gn:feature_class":"P",
    "gn:feature_code":"PPL",
    "gn:name":"Shuizhuke",
    "gn:population":0,
    "gn:timezone":"Asia/Shanghai",
    "iso:country":"CN",
    "name:zho_x_preferred":[
        "\u6c34\u7af9\u7aa0"
    ],
    "wof:name":"Shuizhuke",
    "wof:placetype":"locality"
},
  "geometry": {"coordinates":[117.47783,27.79615],"type":"Point"}
}