{
  "type": "Feature",
  "properties": {
    "gn:admin1_code":"26.0",
    "gn:asciiname":"Suijinyicun",
    "gn:country_code":"CN",
    "gn:dem":921,
    "gn:feature_class":"P",
    "gn:feature_code":"PPL",
    "gn:name":"Suijinyicun",
    "gn:population":0,
    "gn:timezone":"Asia/Shanghai",
    "iso:country":"CN",
    "name:zho_x_preferred":[
        "\u788e\u91d1\u9a7f\u6751"
    ],
    "wof:name":"Suijinyicun",
    "wof:placetype":"locality"
},
  "geometry": {"coordinates":[110.05137000000001,37.89731],"type":"Point"}
}