{
  "type": "Feature",
  "properties": {
    "gn:admin1_code":"19.0",
    "gn:asciiname":"Hujiadian",
    "gn:country_code":"CN",
    "gn:dem":133,
    "gn:feature_class":"P",
    "gn:feature_code":"PPL",
    "gn:name":"Hujiadian",
    "gn:population":0,
    "gn:timezone":"Asia/Shanghai",
    "iso:country":"CN",
    "name:zho_x_preferred":[
        "\u80e1\u5bb6\u5e97"
    ],
    "wof:name":"Hujiadian",
    "wof:placetype":"locality"
},
  "geometry": {"coordinates":[124.155,43.2418],"type":"Point"}
}