{
  "type": "Feature",
  "properties": {
    "gn:admin1_code":"11.0",
    "gn:asciiname":"Ainiandao",
    "gn:country_code":"CN",
    "gn:dem":292,
    "gn:feature_class":"P",
    "gn:feature_code":"PPL",
    "gn:name":"Ainiandao",
    "gn:population":0,
    "gn:timezone":"Asia/Shanghai",
    "iso:country":"CN",
    "name:zho_x_preferred":[
        "\u6328\u5e74\u5230"
    ],
    "wof:name":"Ainiandao",
    "wof:placetype":"locality"
},
  "geometry": {"coordinates":[110.41887,28.73414],"type":"Point"}
}