{
  "type": "Feature",
  "properties": {
    "gn:admin1_code":"3.0",
    "gn:asciiname":"Xingekouqian",
    "gn:country_code":"CN",
    "gn:dem":355,
    "gn:feature_class":"P",
    "gn:feature_code":"PPL",
    "gn:name":"Xingekouqian",
    "gn:population":0,
    "gn:timezone":"Asia/Shanghai",
    "iso:country":"CN",
    "name:und_x_variant":[
        "\u65b0\u9694\u53e3\u524d"
    ],
    "wof:name":"Xingekouqian",
    "wof:placetype":"locality"
},
  "geometry": {"coordinates":[116.26049,26.47453],"type":"Point"}
}