{
  "type": "Feature",
  "properties": {
    "gn:admin1_code":"12.0",
    "gn:asciiname":"Zuojiagang",
    "gn:country_code":"CN",
    "gn:dem":71,
    "gn:feature_class":"P",
    "gn:feature_code":"PPL",
    "gn:name":"Zuojiagang",
    "gn:population":0,
    "gn:timezone":"Asia/Shanghai",
    "iso:country":"CN",
    "name:zho_x_preferred":[
        "\u5de6\u5bb6\u5c97"
    ],
    "wof:name":"Zuojiagang",
    "wof:placetype":"locality"
},
  "geometry": {"coordinates":[112.22195000000001,31.34538],"type":"Point"}
}