{
  "type": "Feature",
  "properties": {
    "gn:admin1_code":"05",
    "gn:asciiname":"Xinxing Linchang",
    "gn:country_code":"CN",
    "gn:dem":709,
    "gn:feature_class":"P",
    "gn:feature_code":"PPLF",
    "gn:name":"Xinxing Linchang",
    "gn:population":0,
    "gn:timezone":"Asia/Shanghai",
    "iso:country":"CN",
    "name:und_x_variant":[
        "\u65b0\u5174\u6797\u573a"
    ],
    "wof:name":"Xinxing Linchang",
    "wof:placetype":"locality"
},
  "geometry": {"coordinates":[127.62417000000001,42.54778],"type":"Point"}
}