{
  "type": "Feature",
  "properties": {
    "gn:admin1_code":"12.0",
    "gn:asciiname":"Fengqiao",
    "gn:country_code":"CN",
    "gn:dem":28,
    "gn:feature_class":"P",
    "gn:feature_code":"PPL",
    "gn:name":"Fengqiao",
    "gn:population":0,
    "gn:timezone":"Asia/Shanghai",
    "iso:country":"CN",
    "name:zho_x_preferred":[
        "\u67ab\u6865"
    ],
    "wof:name":"Fengqiao",
    "wof:placetype":"locality"
},
  "geometry": {"coordinates":[113.65886999999999,29.75419],"type":"Point"}
}