{
  "type": "Feature",
  "properties": {
    "gn:admin1_code":"29.0",
    "gn:asciiname":"Fangshan",
    "gn:country_code":"CN",
    "gn:dem":1446,
    "gn:feature_class":"P",
    "gn:feature_code":"PPL",
    "gn:name":"Fangshan",
    "gn:population":0,
    "gn:timezone":"Asia/Shanghai",
    "iso:country":"CN",
    "name:ceb_x_preferred":[
        "Fangshan"
    ],
    "name:ces_x_preferred":[
        "Fang-\u0161an"
    ],
    "name:deu_x_preferred":[
        "Fangshan"
    ],
    "name:fra_x_preferred":[
        "Fangshan"
    ],
    "name:mlg_x_preferred":[
        "Fangshan"
    ],
    "name:nor_x_preferred":[
        "Fangshan"
    ],
    "name:rus_x_preferred":[
        "\u0424\u0430\u043d\u0448\u0430\u043d\u044c"
    ],
    "name:swe_x_preferred":[
        "Fangshan"
    ],
    "name:zho_x_preferred":[
        "\u65b9\u5c71"
    ],
    "wof:name":"Fangshan",
    "wof:placetype":"locality"
},
  "geometry": {"coordinates":[104.402,23.0431],"type":"Point"}
}