{
  "type": "Feature",
  "properties": {
    "gn:admin1_code":"5.0",
    "gn:asciiname":"Yamentun",
    "gn:country_code":"CN",
    "gn:dem":159,
    "gn:feature_class":"P",
    "gn:feature_code":"PPL",
    "gn:name":"Yamentun",
    "gn:population":0,
    "gn:timezone":"Asia/Shanghai",
    "iso:country":"CN",
    "name:zho_x_preferred":[
        "\u8859\u95e8\u5c6f"
    ],
    "wof:name":"Yamentun",
    "wof:placetype":"locality"
},
  "geometry": {"coordinates":[123.4796,44.73632],"type":"Point"}
}