{
  "type": "Feature",
  "properties": {
    "gn:admin1_code":"12.0",
    "gn:asciiname":"Nanmuling",
    "gn:country_code":"CN",
    "gn:dem":746,
    "gn:feature_class":"P",
    "gn:feature_code":"PPL",
    "gn:name":"Nanmuling",
    "gn:population":0,
    "gn:timezone":"Asia/Shanghai",
    "iso:country":"CN",
    "name:zho_x_preferred":[
        "\u6960\u6728\u5cad"
    ],
    "wof:name":"Nanmuling",
    "wof:placetype":"locality"
},
  "geometry": {"coordinates":[109.67316,30.52016],"type":"Point"}
}