{
  "type": "Feature",
  "properties": {
    "gn:admin1_code":"12.0",
    "gn:asciiname":"Wuliangchen",
    "gn:country_code":"CN",
    "gn:dem":34,
    "gn:feature_class":"P",
    "gn:feature_code":"PPL",
    "gn:name":"Wuliangchen",
    "gn:population":0,
    "gn:timezone":"Asia/Shanghai",
    "iso:country":"CN",
    "name:zho_x_preferred":[
        "\u5434\u826f\u81e3"
    ],
    "wof:name":"Wuliangchen",
    "wof:placetype":"locality"
},
  "geometry": {"coordinates":[114.47765,30.07309],"type":"Point"}
}