{
  "type": "Feature",
  "properties": {
    "gn:admin1_code":"4.0",
    "gn:asciiname":"Xigaozhuang",
    "gn:country_code":"CN",
    "gn:dem":5,
    "gn:feature_class":"P",
    "gn:feature_code":"PPL",
    "gn:name":"Xigaozhuang",
    "gn:population":0,
    "gn:timezone":"Asia/Shanghai",
    "iso:country":"CN",
    "name:und_x_variant":[
        "\u897f\u9ad8\u5e84"
    ],
    "name:zho_x_preferred":[
        "\u897f\u9ad8\u5e84"
    ],
    "wof:name":"Xigaozhuang",
    "wof:placetype":"locality"
},
  "geometry": {"coordinates":[120.57061000000002,31.34],"type":"Point"}
}