{
  "type": "Feature",
  "properties": {
    "gn:admin1_code":"11.0",
    "gn:asciiname":"Fengbiantang",
    "gn:country_code":"CN",
    "gn:dem":76,
    "gn:feature_class":"P",
    "gn:feature_code":"PPL",
    "gn:name":"Fengbiantang",
    "gn:population":0,
    "gn:timezone":"Asia/Shanghai",
    "iso:country":"CN",
    "name:zho_x_preferred":[
        "\u51e4\u8fb9\u5858"
    ],
    "wof:name":"Fengbiantang",
    "wof:placetype":"locality"
},
  "geometry": {"coordinates":[112.84059999999999,26.6374],"type":"Point"}
}