{
  "type": "Feature",
  "properties": {
    "gn:admin1_code":"20.0",
    "gn:asciiname":"Sulianhaolai",
    "gn:country_code":"CN",
    "gn:dem":2031,
    "gn:feature_class":"P",
    "gn:feature_code":"PPL",
    "gn:name":"Sulianhaolai",
    "gn:population":0,
    "gn:timezone":"Asia/Shanghai",
    "iso:country":"CN",
    "name:und_x_variant":[
        "\u5bbf\u7ec3\u58d5\u8d56"
    ],
    "wof:name":"Sulianhaolai",
    "wof:placetype":"locality"
},
  "geometry": {"coordinates":[111.82523999999999,41.1999],"type":"Point"}
}