{
  "type": "Feature",
  "properties": {
    "gn:admin1_code":"1.0",
    "gn:asciiname":"Muxiaozhaicun",
    "gn:country_code":"CN",
    "gn:dem":33,
    "gn:feature_class":"P",
    "gn:feature_code":"PPL",
    "gn:name":"Muxiaozhaicun",
    "gn:population":0,
    "gn:timezone":"Asia/Shanghai",
    "iso:country":"CN",
    "name:zho_x_preferred":[
        "\u7a46\u5c0f\u5be8\u6751"
    ],
    "wof:name":"Muxiaozhaicun",
    "wof:placetype":"locality"
},
  "geometry": {"coordinates":[115.8732,33.42839],"type":"Point"}
}