{
  "type": "Feature",
  "properties": {
    "gn:admin1_code":"29.0",
    "gn:asciiname":"Padie",
    "gn:country_code":"CN",
    "gn:dem":776,
    "gn:feature_class":"P",
    "gn:feature_code":"PPL",
    "gn:name":"Padie",
    "gn:population":0,
    "gn:timezone":"Asia/Shanghai",
    "iso:country":"CN",
    "name:zho_x_preferred":[
        "\u6015\u8dcc"
    ],
    "wof:name":"Padie",
    "wof:placetype":"locality"
},
  "geometry": {"coordinates":[100.633,23.0015],"type":"Point"}
}