{
  "type": "Feature",
  "properties": {
    "gn:admin1_code":"12.0",
    "gn:asciiname":"Zhuojiahe",
    "gn:country_code":"CN",
    "gn:dem":123,
    "gn:feature_class":"P",
    "gn:feature_code":"PPL",
    "gn:name":"Zhuojiahe",
    "gn:population":0,
    "gn:timezone":"Asia/Shanghai",
    "iso:country":"CN",
    "name:zho_x_preferred":[
        "\u5353\u5bb6\u6cb3"
    ],
    "wof:name":"Zhuojiahe",
    "wof:placetype":"locality"
},
  "geometry": {"coordinates":[112.80466,31.45689],"type":"Point"}
}