{
  "type": "Feature",
  "properties": {
    "gn:admin1_code":"29.0",
    "gn:asciiname":"Haiziying",
    "gn:country_code":"CN",
    "gn:dem":1776,
    "gn:feature_class":"P",
    "gn:feature_code":"PPL",
    "gn:name":"Haiziying",
    "gn:population":0,
    "gn:timezone":"Asia/Shanghai",
    "iso:country":"CN",
    "name:zho_x_preferred":[
        "\u6d77\u5b50\u8425"
    ],
    "wof:name":"Haiziying",
    "wof:placetype":"locality"
},
  "geometry": {"coordinates":[102.24299999999999,25.3353],"type":"Point"}
}