{
  "type": "Feature",
  "properties": {
    "gn:admin1_code":"9.0",
    "gn:asciiname":"Liuzhong",
    "gn:country_code":"CN",
    "gn:dem":75,
    "gn:feature_class":"P",
    "gn:feature_code":"PPL",
    "gn:name":"Liuzhong",
    "gn:population":0,
    "gn:timezone":"Asia/Shanghai",
    "iso:country":"CN",
    "name:zho_x_preferred":[
        "\u5218\u51a2"
    ],
    "wof:name":"Liuzhong",
    "wof:placetype":"locality"
},
  "geometry": {"coordinates":[114.40864000000001,32.61533],"type":"Point"}
}