{
  "type": "Feature",
  "properties": {
    "gn:admin1_code":"19.0",
    "gn:asciiname":"Honghaiyuye",
    "gn:country_code":"CN",
    "gn:dem":-9999,
    "gn:feature_class":"P",
    "gn:feature_code":"PPLF",
    "gn:name":"Honghaiyuye",
    "gn:population":0,
    "gn:timezone":"Asia/Shanghai",
    "iso:country":"CN",
    "name:und_x_variant":[
        "\u7ea2\u6d77\u6e14\u4e1a"
    ],
    "wof:name":"Honghaiyuye",
    "wof:placetype":"locality"
},
  "geometry": {"coordinates":[122.10477,40.24285],"type":"Point"}
}