{
  "type": "Feature",
  "properties": {
    "gn:admin1_code":"24.0",
    "gn:asciiname":"Gaojia",
    "gn:country_code":"CN",
    "gn:dem":626,
    "gn:feature_class":"P",
    "gn:feature_code":"PPL",
    "gn:name":"Gaojia",
    "gn:population":0,
    "gn:timezone":"Asia/Shanghai",
    "iso:country":"CN",
    "name:und_x_variant":[
        "Kuo-chia-chi",
        "Guojiaji"
    ],
    "name:zho_x_preferred":[
        "\u9ad8\u5bb6"
    ],
    "wof:name":"Gaojia",
    "wof:placetype":"locality"
},
  "geometry": {"coordinates":[111.7891,35.73798],"type":"Point"}
}