{
  "type": "Feature",
  "properties": {
    "gn:admin1_code":"4.0",
    "gn:asciiname":"Qingfeng",
    "gn:country_code":"CN",
    "gn:dem":2,
    "gn:feature_class":"P",
    "gn:feature_code":"PPL",
    "gn:name":"Qingfeng",
    "gn:population":0,
    "gn:timezone":"Asia/Shanghai",
    "iso:country":"CN",
    "name:und_x_variant":[
        "\u5e86\u4e30"
    ],
    "wof:name":"Qingfeng",
    "wof:placetype":"locality"
},
  "geometry": {"coordinates":[121.15393,32.15729],"type":"Point"}
}