{
  "type": "Feature",
  "properties": {
    "gn:admin1_code":"26",
    "gn:asciiname":"Bowangcun",
    "gn:country_code":"CN",
    "gn:dem":544,
    "gn:feature_class":"P",
    "gn:feature_code":"PPL",
    "gn:name":"Bowangcun",
    "gn:population":0,
    "gn:timezone":"Asia/Shanghai",
    "iso:country":"CN",
    "name:zho_x_preferred":[
        "\u73bb\u738b\u6751"
    ],
    "wof:name":"Bowangcun",
    "wof:placetype":"locality"
},
  "geometry": {"coordinates":[109.43281,34.43002],"type":"Point"}
}