{
  "type": "Feature",
  "properties": {
    "gn:admin1_code":"2.0",
    "gn:asciiname":"Yekengwu",
    "gn:country_code":"CN",
    "gn:dem":347,
    "gn:feature_class":"P",
    "gn:feature_code":"PPL",
    "gn:name":"Yekengwu",
    "gn:population":0,
    "gn:timezone":"Asia/Shanghai",
    "iso:country":"CN",
    "name:und_x_variant":[
        "\u53f6\u5751\u575e"
    ],
    "wof:name":"Yekengwu",
    "wof:placetype":"locality"
},
  "geometry": {"coordinates":[119.33116,30.55528],"type":"Point"}
}