{
  "type": "Feature",
  "properties": {
    "gn:admin1_code":"7",
    "gn:asciiname":"Qijiao",
    "gn:country_code":"CN",
    "gn:dem":307,
    "gn:feature_class":"P",
    "gn:feature_code":"PPL",
    "gn:name":"Qijiao",
    "gn:population":0,
    "gn:timezone":"Asia/Shanghai",
    "iso:country":"CN",
    "name:zho_x_preferred":[
        "\u78dc\u811a"
    ],
    "wof:name":"Qijiao",
    "wof:placetype":"locality"
},
  "geometry": {"coordinates":[117.21472,24.57389],"type":"Point"}
}