{
  "type": "Feature",
  "properties": {
    "gn:admin1_code":"2.0",
    "gn:asciiname":"Xiangziao",
    "gn:country_code":"CN",
    "gn:dem":39,
    "gn:feature_class":"P",
    "gn:feature_code":"PPL",
    "gn:name":"Xiangziao",
    "gn:population":0,
    "gn:timezone":"Asia/Shanghai",
    "iso:country":"CN",
    "name:und_x_variant":[
        "\u9999\u5b57\u5c99"
    ],
    "name:zho_x_preferred":[
        "Xiangziao"
    ],
    "wof:name":"Xiangziao",
    "wof:placetype":"locality"
},
  "geometry": {"coordinates":[119.76828,30.26171],"type":"Point"}
}