{
  "type": "Feature",
  "properties": {
    "gn:admin1_code":"1.0",
    "gn:asciiname":"Laoxiahe",
    "gn:country_code":"CN",
    "gn:dem":9,
    "gn:feature_class":"P",
    "gn:feature_code":"PPL",
    "gn:name":"Laoxiahe",
    "gn:population":0,
    "gn:timezone":"Asia/Shanghai",
    "iso:country":"CN",
    "name:zho_x_preferred":[
        "\u59e5\u4e0b\u6cb3"
    ],
    "wof:name":"Laoxiahe",
    "wof:placetype":"locality"
},
  "geometry": {"coordinates":[118.37473,31.59491],"type":"Point"}
}