{
  "type": "Feature",
  "properties": {
    "gn:admin1_code":"32.0",
    "gn:asciiname":"Cilin'an",
    "gn:country_code":"CN",
    "gn:dem":377,
    "gn:feature_class":"P",
    "gn:feature_code":"PPL",
    "gn:name":"Cilin\u2019an",
    "gn:population":0,
    "gn:timezone":"Asia/Shanghai",
    "iso:country":"CN",
    "name:zho_x_preferred":[
        "\u6148\u6797\u5eb5"
    ],
    "name:zho_x_variant":[
        "Cilin\u2019an"
    ],
    "wof:name":"Cilin'an",
    "wof:placetype":"locality"
},
  "geometry": {"coordinates":[104.7876,29.01813],"type":"Point"}
}