{
  "type": "Feature",
  "properties": {
    "gn:admin1_code":"1.0",
    "gn:asciiname":"Songjicun",
    "gn:country_code":"CN",
    "gn:dem":72,
    "gn:feature_class":"P",
    "gn:feature_code":"PPL",
    "gn:name":"Songjicun",
    "gn:population":0,
    "gn:timezone":"Asia/Shanghai",
    "iso:country":"CN",
    "name:zho_x_preferred":[
        "\u5b8b\u96c6\u6751"
    ],
    "wof:name":"Songjicun",
    "wof:placetype":"locality"
},
  "geometry": {"coordinates":[117.54349999999999,32.68621],"type":"Point"}
}