{
  "type": "Feature",
  "properties": {
    "gn:admin1_code":"32.0",
    "gn:asciiname":"Tongdui",
    "gn:country_code":"CN",
    "gn:dem":3560,
    "gn:feature_class":"P",
    "gn:feature_code":"PPL",
    "gn:name":"Tongdui",
    "gn:population":0,
    "gn:timezone":"Asia/Shanghai",
    "iso:country":"CN",
    "name:zho_x_preferred":[
        "\u540c\u5806"
    ],
    "wof:name":"Tongdui",
    "wof:placetype":"locality"
},
  "geometry": {"coordinates":[99.6377,29.2809],"type":"Point"}
}