{
  "type": "Feature",
  "properties": {
    "gn:admin1_code":"4.0",
    "gn:asciiname":"Guihuazhuang",
    "gn:country_code":"CN",
    "gn:dem":7,
    "gn:feature_class":"P",
    "gn:feature_code":"PPL",
    "gn:name":"Guihuazhuang",
    "gn:population":0,
    "gn:timezone":"Asia/Shanghai",
    "iso:country":"CN",
    "name:zho_x_preferred":[
        "\u6842\u82b1\u5e84"
    ],
    "wof:name":"Guihuazhuang",
    "wof:placetype":"locality"
},
  "geometry": {"coordinates":[119.77258,32.10629],"type":"Point"}
}