{
  "type": "Feature",
  "properties": {
    "gn:admin1_code":"19.0",
    "gn:asciiname":"Heping",
    "gn:country_code":"CN",
    "gn:dem":83,
    "gn:feature_class":"P",
    "gn:feature_code":"PPL",
    "gn:name":"Heping",
    "gn:population":0,
    "gn:timezone":"Asia/Shanghai",
    "iso:country":"CN",
    "name:und_x_variant":[
        "\u548c\u5e73"
    ],
    "name:zho_x_preferred":[
        "\u548c\u5e73"
    ],
    "wof:name":"Heping",
    "wof:placetype":"locality"
},
  "geometry": {"coordinates":[123.60157,42.63605],"type":"Point"}
}