{
  "type": "Feature",
  "properties": {
    "gn:admin1_code":"19.0",
    "gn:asciiname":"Heping",
    "gn:country_code":"CN",
    "gn:dem":83,
    "gn:feature_class":"P",
    "gn:feature_code":"PPL",
    "gn:name":"Heping",
    "gn:population":0,
    "gn:timezone":"Asia/Shanghai",
    "iso:country":"CN",
    "name:ceb_x_preferred":[
        "Heping"
    ],
    "name:deu_x_preferred":[
        "Heping"
    ],
    "name:eus_x_preferred":[
        "Heping"
    ],
    "name:fra_x_preferred":[
        "Heping"
    ],
    "name:jpn_x_preferred":[
        "\u548c\u5e73\u533a"
    ],
    "name:kor_x_preferred":[
        "\ud5c8\ud551\uad6c"
    ],
    "name:nor_x_preferred":[
        "Heping"
    ],
    "name:sco_x_preferred":[
        "Heping"
    ],
    "name:swe_x_preferred":[
        "Heping"
    ],
    "name:vie_x_preferred":[
        "H\u00f2a B\u00ecnh"
    ],
    "name:zho_x_preferred":[
        "\u548c\u5e73"
    ],
    "name:zho_x_variant":[
        "\u548c\u5e73\u533a"
    ],
    "wof:name":"Heping",
    "wof:placetype":"locality"
},
  "geometry": {"coordinates":[123.60157,42.63605],"type":"Point"}
}