{
  "type": "Feature",
  "properties": {
    "gn:admin1_code":"1.0",
    "gn:asciiname":"Fangliucun",
    "gn:country_code":"CN",
    "gn:dem":24,
    "gn:feature_class":"P",
    "gn:feature_code":"PPL",
    "gn:name":"Fangliucun",
    "gn:population":0,
    "gn:timezone":"Asia/Shanghai",
    "iso:country":"CN",
    "name:zho_x_preferred":[
        "\u65b9\u5218\u6751"
    ],
    "wof:name":"Fangliucun",
    "wof:placetype":"locality"
},
  "geometry": {"coordinates":[117.31594,33.43619],"type":"Point"}
}