{
  "type": "Feature",
  "properties": {
    "gn:admin1_code":"25.0",
    "gn:asciiname":"Qianliujia",
    "gn:country_code":"CN",
    "gn:dem":128,
    "gn:feature_class":"P",
    "gn:feature_code":"PPL",
    "gn:name":"Qianliujia",
    "gn:population":0,
    "gn:timezone":"Asia/Shanghai",
    "iso:country":"CN",
    "name:zho_x_preferred":[
        "\u524d\u67f3\u5bb6"
    ],
    "wof:name":"Qianliujia",
    "wof:placetype":"locality"
},
  "geometry": {"coordinates":[120.70283999999999,37.55947000000001],"type":"Point"}
}