{
  "type": "Feature",
  "properties": {
    "gn:admin1_code":"15.0",
    "gn:asciiname":"Zhangjiashan",
    "gn:country_code":"CN",
    "gn:dem":2215,
    "gn:feature_class":"P",
    "gn:feature_code":"PPL",
    "gn:name":"Zhangjiashan",
    "gn:population":0,
    "gn:timezone":"Asia/Shanghai",
    "iso:country":"CN",
    "name:zho_x_preferred":[
        "\u5f20\u5bb6\u5c71"
    ],
    "wof:name":"Zhangjiashan",
    "wof:placetype":"locality"
},
  "geometry": {"coordinates":[103.04300000000001,36.1046],"type":"Point"}
}