{
  "type": "Feature",
  "properties": {
    "gn:admin1_code":"32.0",
    "gn:asciiname":"Pogere",
    "gn:country_code":"CN",
    "gn:dem":2579,
    "gn:feature_class":"P",
    "gn:feature_code":"PPL",
    "gn:name":"Pogere",
    "gn:population":0,
    "gn:timezone":"Asia/Shanghai",
    "iso:country":"CN",
    "name:zho_x_preferred":[
        "\u5761\u683c\u60f9"
    ],
    "wof:name":"Pogere",
    "wof:placetype":"locality"
},
  "geometry": {"coordinates":[102.694,28.0357],"type":"Point"}
}