{
  "type": "Feature",
  "properties": {
    "gn:admin1_code":"15.0",
    "gn:asciiname":"Jiashanling",
    "gn:country_code":"CN",
    "gn:dem":1954,
    "gn:feature_class":"P",
    "gn:feature_code":"PPL",
    "gn:name":"Jiashanling",
    "gn:population":0,
    "gn:timezone":"Asia/Shanghai",
    "iso:country":"CN",
    "name:zho_x_preferred":[
        "\u5939\u5c71\u5cad"
    ],
    "wof:name":"Jiashanling",
    "wof:placetype":"locality"
},
  "geometry": {"coordinates":[103.19799999999999,37.5381],"type":"Point"}
}