{
  "type": "Feature",
  "properties": {
    "gn:admin1_code":"9.0",
    "gn:asciiname":"Yingzuiyao",
    "gn:country_code":"CN",
    "gn:dem":513,
    "gn:feature_class":"P",
    "gn:feature_code":"PPL",
    "gn:name":"Yingzuiyao",
    "gn:population":0,
    "gn:timezone":"Asia/Shanghai",
    "iso:country":"CN",
    "name:zho_x_preferred":[
        "\u9e70\u5480\u7a91"
    ],
    "wof:name":"Yingzuiyao",
    "wof:placetype":"locality"
},
  "geometry": {"coordinates":[112.17764,34.00286],"type":"Point"}
}