{
  "type": "Feature",
  "properties": {
    "gn:admin1_code":"25",
    "gn:asciiname":"Tongbincun",
    "gn:country_code":"CN",
    "gn:dem":10,
    "gn:feature_class":"P",
    "gn:feature_code":"PPL",
    "gn:name":"Tongbincun",
    "gn:population":0,
    "gn:timezone":"Asia/Shanghai",
    "iso:country":"CN",
    "name:und_x_variant":[
        "Tongbin",
        "Tongbincun"
    ],
    "name:zho_x_preferred":[
        "\u901a\u6ee8"
    ],
    "name:zho_x_variant":[
        "\u901a\u6ee8\u6751"
    ],
    "wof:name":"Tongbincun",
    "wof:placetype":"locality"
},
  "geometry": {"coordinates":[118.13289,37.25815],"type":"Point"}
}