{
  "type": "Feature",
  "properties": {
    "gn:admin1_code":"4.0",
    "gn:asciiname":"Qiaowangcun",
    "gn:country_code":"CN",
    "gn:dem":10,
    "gn:feature_class":"P",
    "gn:feature_code":"PPL",
    "gn:name":"Qiaowangcun",
    "gn:population":0,
    "gn:timezone":"Asia/Shanghai",
    "iso:country":"CN",
    "name:zho_x_preferred":[
        "\u4e54\u738b\u6751"
    ],
    "wof:name":"Qiaowangcun",
    "wof:placetype":"locality"
},
  "geometry": {"coordinates":[118.69971,33.97992],"type":"Point"}
}