{
  "type": "Feature",
  "properties": {
    "gn:admin1_code":"11.0",
    "gn:asciiname":"Houzidong",
    "gn:country_code":"CN",
    "gn:dem":468,
    "gn:feature_class":"P",
    "gn:feature_code":"PPL",
    "gn:name":"Houzidong",
    "gn:population":0,
    "gn:timezone":"Asia/Shanghai",
    "iso:country":"CN",
    "name:zho_x_preferred":[
        "Houzidong"
    ],
    "name:zho_x_variant":[
        "\u7334\u5b50\u680b"
    ],
    "wof:name":"Houzidong",
    "wof:placetype":"locality"
},
  "geometry": {"coordinates":[114.07156000000001,28.31901],"type":"Point"}
}