{
  "type": "Feature",
  "properties": {
    "gn:admin1_code":"4.0",
    "gn:asciiname":"Yinguanzhuang",
    "gn:country_code":"CN",
    "gn:dem":22,
    "gn:feature_class":"P",
    "gn:feature_code":"PPL",
    "gn:name":"Yinguanzhuang",
    "gn:population":0,
    "gn:timezone":"Asia/Shanghai",
    "iso:country":"CN",
    "name:und_x_variant":[
        "\u5c39\u5b98\u5e84"
    ],
    "wof:name":"Yinguanzhuang",
    "wof:placetype":"locality"
},
  "geometry": {"coordinates":[118.73745,34.46752],"type":"Point"}
}