{
  "type": "Feature",
  "properties": {
    "gn:admin1_code":"26.0",
    "gn:asciiname":"Shiziba",
    "gn:country_code":"CN",
    "gn:dem":1175,
    "gn:feature_class":"P",
    "gn:feature_code":"PPL",
    "gn:name":"Shiziba",
    "gn:population":0,
    "gn:timezone":"Asia/Shanghai",
    "iso:country":"CN",
    "name:und_x_variant":[
        "\u72ee\u5b50\u575d"
    ],
    "wof:name":"Shiziba",
    "wof:placetype":"locality"
},
  "geometry": {"coordinates":[106.97005,33.77197],"type":"Point"}
}