{
  "type": "Feature",
  "properties": {
    "gn:admin1_code":"20",
    "gn:asciiname":"Yong'an",
    "gn:country_code":"CN",
    "gn:dem":362,
    "gn:feature_class":"P",
    "gn:feature_code":"PPLA4",
    "gn:name":"Yong\u2019an",
    "gn:population":0,
    "gn:timezone":"Asia/Shanghai",
    "iso:country":"CN",
    "name:und_x_variant":[
        "Yong\u2019an",
        "Yong\u2019an Zhen"
    ],
    "name:zho_x_preferred":[
        "\u6c38\u5b89"
    ],
    "name:zho_x_variant":[
        "\u6c38\u5b89\u9547"
    ],
    "wof:name":"Yong'an",
    "wof:placetype":"locality"
},
  "geometry": {"coordinates":[121.64068,45.81318],"type":"Point"}
}