{
  "type": "Feature",
  "properties": {
    "gn:admin1_code":"11.0",
    "gn:asciiname":"Lieba",
    "gn:country_code":"CN",
    "gn:dem":661,
    "gn:feature_class":"P",
    "gn:feature_code":"PPL",
    "gn:name":"Lieba",
    "gn:population":0,
    "gn:timezone":"Asia/Shanghai",
    "iso:country":"CN",
    "name:zho_x_preferred":[
        "\u5217\u5df4"
    ],
    "name:zho_x_variant":[
        "\u70c8\u575d"
    ],
    "wof:name":"Lieba",
    "wof:placetype":"locality"
},
  "geometry": {"coordinates":[109.44459000000001,29.12823],"type":"Point"}
}