{
  "type": "Feature",
  "properties": {
    "gn:admin1_code":"32.0",
    "gn:asciiname":"Zela",
    "gn:country_code":"CN",
    "gn:dem":1477,
    "gn:feature_class":"P",
    "gn:feature_code":"PPL",
    "gn:name":"Zela",
    "gn:population":0,
    "gn:timezone":"Asia/Shanghai",
    "iso:country":"CN",
    "name:ceb_x_preferred":[
        "Zela"
    ],
    "name:deu_x_preferred":[
        "Zela"
    ],
    "name:fin_x_preferred":[
        "Zela"
    ],
    "name:swe_x_preferred":[
        "Zela"
    ],
    "name:zho_x_preferred":[
        "\u5219\u62c9"
    ],
    "wof:name":"Zela",
    "wof:placetype":"locality"
},
  "geometry": {"coordinates":[102.62599,28.87274],"type":"Point"}
}