{
  "type": "Feature",
  "properties": {
    "gn:admin1_code":"26.0",
    "gn:asciiname":"Lijiayuan",
    "gn:country_code":"CN",
    "gn:dem":777,
    "gn:feature_class":"P",
    "gn:feature_code":"PPL",
    "gn:name":"Lijiayuan",
    "gn:population":0,
    "gn:timezone":"Asia/Shanghai",
    "iso:country":"CN",
    "name:zho_x_preferred":[
        "\u674e\u5bb6\u9662"
    ],
    "wof:name":"Lijiayuan",
    "wof:placetype":"locality"
},
  "geometry": {"coordinates":[110.52256,34.07719],"type":"Point"}
}