{
  "type": "Feature",
  "properties": {
    "gn:admin1_code":"25.0",
    "gn:asciiname":"Huangtuancun",
    "gn:country_code":"CN",
    "gn:dem":57,
    "gn:feature_class":"P",
    "gn:feature_code":"PPL",
    "gn:name":"Huangtuancun",
    "gn:population":0,
    "gn:timezone":"Asia/Shanghai",
    "iso:country":"CN",
    "name:zho_x_preferred":[
        "\u9ec4\u7583\u6751"
    ],
    "wof:name":"Huangtuancun",
    "wof:placetype":"locality"
},
  "geometry": {"coordinates":[121.70375,36.92086],"type":"Point"}
}