{
  "type": "Feature",
  "properties": {
    "gn:admin1_code":"4.0",
    "gn:asciiname":"Houxiaoxingzhuang",
    "gn:country_code":"CN",
    "gn:dem":3,
    "gn:feature_class":"P",
    "gn:feature_code":"PPL",
    "gn:name":"Houxiaoxingzhuang",
    "gn:population":0,
    "gn:timezone":"Asia/Shanghai",
    "iso:country":"CN",
    "name:zho_x_preferred":[
        "Houxiaoxingzhuang"
    ],
    "name:zho_x_variant":[
        "\u540e\u5c0f\u5174\u5e84"
    ],
    "wof:name":"Houxiaoxingzhuang",
    "wof:placetype":"locality"
},
  "geometry": {"coordinates":[119.19924,34.06619],"type":"Point"}
}