{
  "type": "Feature",
  "properties": {
    "gn:admin1_code":"13",
    "gn:asciiname":"Wentashi",
    "gn:country_code":"CN",
    "gn:dem":1228,
    "gn:feature_class":"P",
    "gn:feature_code":"PPL",
    "gn:name":"Wentashi",
    "gn:population":0,
    "gn:timezone":"Asia/Shanghai",
    "iso:country":"CN",
    "name:zho_x_preferred":[
        "\u6e29\u5854\u4ec0"
    ],
    "wof:name":"Wentashi",
    "wof:placetype":"locality"
},
  "geometry": {"coordinates":[76.41775,39.44858],"type":"Point"}
}