{
  "type": "Feature",
  "properties": {
    "gn:admin1_code":"6.0",
    "gn:asciiname":"Saiqu",
    "gn:country_code":"CN",
    "gn:dem":4037,
    "gn:feature_class":"P",
    "gn:feature_code":"PPL",
    "gn:name":"Saiqu",
    "gn:population":0,
    "gn:timezone":"Asia/Urumqi",
    "iso:country":"CN",
    "name:ceb_x_preferred":[
        "Saixiang"
    ],
    "name:msa_x_preferred":[
        "Saiqu"
    ],
    "name:swe_x_preferred":[
        "Saixiang"
    ],
    "name:zho_x_preferred":[
        "\u8d5b\u66f2"
    ],
    "wof:name":"Saiqu",
    "wof:placetype":"locality"
},
  "geometry": {"coordinates":[95.40555999999999,32.8488],"type":"Point"}
}