{
  "type": "Feature",
  "properties": {
    "gn:admin1_code":"10",
    "gn:asciiname":"Xicaiyu",
    "gn:country_code":"CN",
    "gn:dem":149,
    "gn:feature_class":"P",
    "gn:feature_code":"PPL",
    "gn:name":"Xicaiyu",
    "gn:population":0,
    "gn:timezone":"Asia/Shanghai",
    "iso:country":"CN",
    "name:zho_x_preferred":[
        "\u897f\u8521\u5cea"
    ],
    "wof:name":"Xicaiyu",
    "wof:placetype":"locality"
},
  "geometry": {"coordinates":[119.02394,40.30985],"type":"Point"}
}