{
  "type": "Feature",
  "properties": {
    "gn:admin1_code":"2.0",
    "gn:asciiname":"Baishuihe",
    "gn:country_code":"CN",
    "gn:dem":4,
    "gn:feature_class":"P",
    "gn:feature_code":"PPL",
    "gn:name":"Baishuihe",
    "gn:population":0,
    "gn:timezone":"Asia/Shanghai",
    "iso:country":"CN",
    "name:und_x_variant":[
        "\u767d\u6c34\u6cb3"
    ],
    "wof:name":"Baishuihe",
    "wof:placetype":"locality"
},
  "geometry": {"coordinates":[120.38366000000001,30.7243],"type":"Point"}
}