{
  "type": "Feature",
  "properties": {
    "gn:admin1_code":"19.0",
    "gn:asciiname":"Yangbucun",
    "gn:country_code":"CN",
    "gn:dem":85,
    "gn:feature_class":"P",
    "gn:feature_code":"PPL",
    "gn:name":"Yangbucun",
    "gn:population":0,
    "gn:timezone":"Asia/Shanghai",
    "iso:country":"CN",
    "name:zho_x_preferred":[
        "\u6837\u5821\u6751"
    ],
    "wof:name":"Yangbucun",
    "wof:placetype":"locality"
},
  "geometry": {"coordinates":[123.95232,42.58601],"type":"Point"}
}