{
  "type": "Feature",
  "properties": {
    "gn:admin1_code":"21.0",
    "gn:asciiname":"Bahaoquan",
    "gn:country_code":"CN",
    "gn:dem":1454,
    "gn:feature_class":"P",
    "gn:feature_code":"PPL",
    "gn:name":"Bahaoquan",
    "gn:population":0,
    "gn:timezone":"Asia/Shanghai",
    "iso:country":"CN",
    "name:zho_x_preferred":[
        "\u516b\u53f7\u6cc9"
    ],
    "wof:name":"Bahaoquan",
    "wof:placetype":"locality"
},
  "geometry": {"coordinates":[106.29900000000001,39.205],"type":"Point"}
}