{
  "type": "Feature",
  "properties": {
    "gn:admin1_code":"16.0",
    "gn:asciiname":"Baile",
    "gn:country_code":"CN",
    "gn:dem":989,
    "gn:feature_class":"P",
    "gn:feature_code":"PPL",
    "gn:name":"Baile",
    "gn:population":0,
    "gn:timezone":"Asia/Shanghai",
    "iso:country":"CN",
    "name:zho_x_preferred":[
        "\u767e\u4e50"
    ],
    "wof:name":"Baile",
    "wof:placetype":"locality"
},
  "geometry": {"coordinates":[106.462,24.6759],"type":"Point"}
}