{
  "type": "Feature",
  "properties": {
    "gn:admin1_code":"19.0",
    "gn:asciiname":"Baijiayoufangcun",
    "gn:country_code":"CN",
    "gn:dem":505,
    "gn:feature_class":"P",
    "gn:feature_code":"PPL",
    "gn:name":"Baijiayoufangcun",
    "gn:population":0,
    "gn:timezone":"Asia/Shanghai",
    "iso:country":"CN",
    "name:zho_x_preferred":[
        "\u767d\u5bb6\u6cb9\u574a\u6751"
    ],
    "wof:name":"Baijiayoufangcun",
    "wof:placetype":"locality"
},
  "geometry": {"coordinates":[119.089,41.0286],"type":"Point"}
}