{
  "type": "Feature",
  "properties": {
    "gn:admin1_code":"14",
    "gn:asciiname":"Zonggo",
    "gn:country_code":"CN",
    "gn:dem":4609,
    "gn:feature_class":"P",
    "gn:feature_code":"PPL",
    "gn:name":"Zonggo",
    "gn:population":0,
    "gn:timezone":"Asia/Urumqi",
    "iso:country":"CN",
    "name:bod_x_preferred":[
        "\u0f62\u0fab\u0f7c\u0f44\u0f0b\u0f58\u0f42\u0f7c"
    ],
    "wof:name":"Zonggo",
    "wof:placetype":"locality"
},
  "geometry": {"coordinates":[91.94750000000001,28.63862],"type":"Point"}
}