{
  "type": "Feature",
  "properties": {
    "gn:admin1_code":"15.0",
    "gn:asciiname":"Chengqiangwan",
    "gn:country_code":"CN",
    "gn:dem":1439,
    "gn:feature_class":"P",
    "gn:feature_code":"PPL",
    "gn:name":"Chengqiangwan",
    "gn:population":0,
    "gn:timezone":"Asia/Shanghai",
    "iso:country":"CN",
    "name:zho_x_preferred":[
        "\u57ce\u5899\u6e7e"
    ],
    "wof:name":"Chengqiangwan",
    "wof:placetype":"locality"
},
  "geometry": {"coordinates":[106.91200000000001,35.9257],"type":"Point"}
}