{
  "type": "Feature",
  "properties": {
    "gn:admin1_code":"29.0",
    "gn:asciiname":"Manhong",
    "gn:country_code":"CN",
    "gn:dem":719,
    "gn:feature_class":"P",
    "gn:feature_code":"PPL",
    "gn:name":"Manhong",
    "gn:population":0,
    "gn:timezone":"Asia/Shanghai",
    "iso:country":"CN",
    "name:zho_x_preferred":[
        "\u66fc\u8f70"
    ],
    "wof:name":"Manhong",
    "wof:placetype":"locality"
},
  "geometry": {"coordinates":[100.188,21.7489],"type":"Point"}
}