{
  "type": "Feature",
  "properties": {
    "gn:admin1_code":"5.0",
    "gn:asciiname":"Mengshanbeidong",
    "gn:country_code":"CN",
    "gn:dem":599,
    "gn:feature_class":"P",
    "gn:feature_code":"PPL",
    "gn:name":"Mengshanbeidong",
    "gn:population":0,
    "gn:timezone":"Asia/Shanghai",
    "iso:country":"CN",
    "name:und_x_variant":[
        "\u5b5f\u5c71\u5317\u6d1e"
    ],
    "wof:name":"Mengshanbeidong",
    "wof:placetype":"locality"
},
  "geometry": {"coordinates":[128.87849,42.83468],"type":"Point"}
}