{
  "type": "Feature",
  "properties": {
    "gn:admin1_code":"30.0",
    "gn:asciiname":"Daiwu",
    "gn:country_code":"CN",
    "gn:dem":441,
    "gn:feature_class":"P",
    "gn:feature_code":"PPL",
    "gn:name":"Daiwu",
    "gn:population":0,
    "gn:timezone":"Asia/Shanghai",
    "iso:country":"CN",
    "name:zho_x_preferred":[
        "\u6234\u5c4b"
    ],
    "wof:name":"Daiwu",
    "wof:placetype":"locality"
},
  "geometry": {"coordinates":[113.80176000000002,24.66021],"type":"Point"}
}