{
  "type": "Feature",
  "properties": {
    "gn:admin1_code":"29.0",
    "gn:asciiname":"Taoshulin",
    "gn:country_code":"CN",
    "gn:dem":1929,
    "gn:feature_class":"P",
    "gn:feature_code":"PPL",
    "gn:name":"Taoshulin",
    "gn:population":0,
    "gn:timezone":"Asia/Shanghai",
    "iso:country":"CN",
    "name:zho_x_preferred":[
        "\u6843\u6811\u6797"
    ],
    "wof:name":"Taoshulin",
    "wof:placetype":"locality"
},
  "geometry": {"coordinates":[99.6129,25.4165],"type":"Point"}
}