{
  "type": "Feature",
  "properties": {
    "gn:admin1_code":"11",
    "gn:asciiname":"Qingyeshu",
    "gn:cc2":"CN",
    "gn:country_code":"CN",
    "gn:dem":566,
    "gn:feature_class":"P",
    "gn:feature_code":"PPL",
    "gn:name":"Qingyeshu",
    "gn:population":0,
    "gn:timezone":"Asia/Shanghai",
    "iso:country":"CN",
    "name:und_x_variant":[
        "Ch\u2019ing-yeh-shu",
        "Qingyeshu"
    ],
    "wof:name":"Qingyeshu",
    "wof:placetype":"locality"
},
  "geometry": {"coordinates":[109.80167,27.58528],"type":"Point"}
}