{
  "type": "Feature",
  "properties": {
    "gn:admin1_code":"22",
    "gn:asciiname":"Miyun",
    "gn:country_code":"CN",
    "gn:dem":80,
    "gn:feature_class":"P",
    "gn:feature_code":"PPL",
    "gn:name":"Miyun",
    "gn:population":0,
    "gn:timezone":"Asia/Shanghai",
    "iso:country":"CN",
    "name:und_x_variant":[
        "Mi-y\u00fcn-hsien",
        "Miyun"
    ],
    "name:zho_x_preferred":[
        "\u5bc6\u4e91"
    ],
    "wof:name":"Miyun",
    "wof:placetype":"locality"
},
  "geometry": {"coordinates":[116.84191,40.37587],"type":"Point"}
}