{
  "type": "Feature",
  "properties": {
    "gn:admin1_code":"22",
    "gn:asciiname":"Miyun",
    "gn:country_code":"CN",
    "gn:dem":80,
    "gn:feature_class":"P",
    "gn:feature_code":"PPL",
    "gn:name":"Miyun",
    "gn:population":0,
    "gn:timezone":"Asia/Shanghai",
    "iso:country":"CN",
    "name:ara_x_preferred":[
        "\u0645\u064a\u0648\u0646"
    ],
    "name:ceb_x_preferred":[
        "Miyun Xian"
    ],
    "name:ces_x_preferred":[
        "Mi-j\u00fcn"
    ],
    "name:deu_x_preferred":[
        "Miyun"
    ],
    "name:est_x_preferred":[
        "Miyuni maakond"
    ],
    "name:eus_x_preferred":[
        "Miyun konderria"
    ],
    "name:fas_x_preferred":[
        "\u0645\u06cc\u06cc\u0627\u0646"
    ],
    "name:jpn_x_preferred":[
        "\u5bc6\u96f2\u533a"
    ],
    "name:kor_x_preferred":[
        "\ubbf8\uc708\uad6c"
    ],
    "name:mwl_x_preferred":[
        "Miyun"
    ],
    "name:nor_x_preferred":[
        "Miyun"
    ],
    "name:rus_x_preferred":[
        "\u041c\u0438\u044e\u043d\u044c"
    ],
    "name:sco_x_preferred":[
        "Miyun Coonty"
    ],
    "name:spa_x_preferred":[
        "Miyun"
    ],
    "name:swe_x_preferred":[
        "Miyun"
    ],
    "name:tur_x_preferred":[
        "Miyun"
    ],
    "name:und_x_variant":[
        "Mi-y\u00fcn-hsien"
    ],
    "name:urd_x_preferred":[
        "\u0645\u06cc\u06cc\u0648\u0646 \u0636\u0644\u0639"
    ],
    "name:vie_x_preferred":[
        "M\u1eadt V\u00e2n"
    ],
    "name:zho_x_preferred":[
        "\u5bc6\u4e91"
    ],
    "name:zho_x_variant":[
        "\u5bc6\u4e91\u533a"
    ],
    "wof:name":"Miyun",
    "wof:placetype":"locality"
},
  "geometry": {"coordinates":[116.84191,40.37587],"type":"Point"}
}