{
  "type": "Feature",
  "properties": {
    "gn:admin1_code":"8.0",
    "gn:asciiname":"Gexincun",
    "gn:country_code":"CN",
    "gn:dem":211,
    "gn:feature_class":"P",
    "gn:feature_code":"PPL",
    "gn:name":"Gexincun",
    "gn:population":0,
    "gn:timezone":"Asia/Shanghai",
    "iso:country":"CN",
    "name:zho_x_preferred":[
        "\u9769\u65b0\u6751"
    ],
    "wof:name":"Gexincun",
    "wof:placetype":"locality"
},
  "geometry": {"coordinates":[126.19829,46.66165],"type":"Point"}
}