{
  "type": "Feature",
  "properties": {
    "gn:admin1_code":"12.0",
    "gn:asciiname":"Liufenghuo",
    "gn:country_code":"CN",
    "gn:dem":50,
    "gn:feature_class":"P",
    "gn:feature_code":"PPL",
    "gn:name":"Liufenghuo",
    "gn:population":0,
    "gn:timezone":"Asia/Shanghai",
    "iso:country":"CN",
    "name:und_x_variant":[
        "\u5218\u51e4\u706b"
    ],
    "wof:name":"Liufenghuo",
    "wof:placetype":"locality"
},
  "geometry": {"coordinates":[114.82386,30.1681],"type":"Point"}
}