{
  "type": "Feature",
  "properties": {
    "gn:admin1_code":"3.0",
    "gn:asciiname":"Datiancun",
    "gn:country_code":"CN",
    "gn:dem":50,
    "gn:feature_class":"P",
    "gn:feature_code":"PPL",
    "gn:name":"Datiancun",
    "gn:population":0,
    "gn:timezone":"Asia/Shanghai",
    "iso:country":"CN",
    "name:und_x_variant":[
        "\u5927\u7530\u6751"
    ],
    "wof:name":"Datiancun",
    "wof:placetype":"locality"
},
  "geometry": {"coordinates":[116.17203000000001,28.09436],"type":"Point"}
}