{
  "type": "Feature",
  "properties": {
    "gn:admin1_code":"19.0",
    "gn:asciiname":"Senlintun",
    "gn:country_code":"CN",
    "gn:dem":162,
    "gn:feature_class":"P",
    "gn:feature_code":"PPL",
    "gn:name":"Senlintun",
    "gn:population":0,
    "gn:timezone":"Asia/Shanghai",
    "iso:country":"CN",
    "name:zho_x_preferred":[
        "\u68ee\u6797\u5c6f"
    ],
    "wof:name":"Senlintun",
    "wof:placetype":"locality"
},
  "geometry": {"coordinates":[120.80224,41.6635],"type":"Point"}
}