{
  "type": "Feature",
  "properties": {
    "gn:admin1_code":"26.0",
    "gn:asciiname":"Junyi",
    "gn:country_code":"CN",
    "gn:dem":598,
    "gn:feature_class":"P",
    "gn:feature_code":"PPL",
    "gn:name":"Junyi",
    "gn:population":0,
    "gn:timezone":"Asia/Shanghai",
    "iso:country":"CN",
    "name:und_x_variant":[
        "\u5747\u5b9c"
    ],
    "wof:name":"Junyi",
    "wof:placetype":"locality"
},
  "geometry": {"coordinates":[107.88348000000001,34.40258],"type":"Point"}
}