{
  "type": "Feature",
  "properties": {
    "gn:admin1_code":"12.0",
    "gn:asciiname":"Xincheng",
    "gn:country_code":"CN",
    "gn:dem":124,
    "gn:feature_class":"P",
    "gn:feature_code":"PPLA4",
    "gn:name":"Xincheng",
    "gn:population":0,
    "gn:timezone":"Asia/Shanghai",
    "iso:country":"CN",
    "name:und_x_variant":[
        "Hsin-ch\u2019eng",
        "Xincheng",
        "Xincheng Zhen",
        "\u65b0\u57ce\u9547"
    ],
    "name:zho_x_preferred":[
        "\u65b0\u57ce"
    ],
    "wof:name":"Xincheng",
    "wof:placetype":"locality"
},
  "geometry": {"coordinates":[114.26577,31.48721],"type":"Point"}
}