{
  "type": "Feature",
  "properties": {
    "gn:admin1_code":"15.0",
    "gn:asciiname":"Hebali",
    "gn:country_code":"CN",
    "gn:dem":878,
    "gn:feature_class":"P",
    "gn:feature_code":"PPL",
    "gn:name":"Hebali",
    "gn:population":0,
    "gn:timezone":"Asia/Shanghai",
    "iso:country":"CN",
    "name:zho_x_preferred":[
        "\u6cb3\u575d\u91cc"
    ],
    "wof:name":"Hebali",
    "wof:placetype":"locality"
},
  "geometry": {"coordinates":[105.60299999999999,32.8977],"type":"Point"}
}