{
  "type": "Feature",
  "properties": {
    "gn:admin1_code":"4.0",
    "gn:asciiname":"Chenhuacun",
    "gn:country_code":"CN",
    "gn:dem":6,
    "gn:feature_class":"P",
    "gn:feature_code":"PPL",
    "gn:name":"Chenhuacun",
    "gn:population":0,
    "gn:timezone":"Asia/Shanghai",
    "iso:country":"CN",
    "name:zho_x_preferred":[
        "\u9648\u534e\u6751"
    ],
    "wof:name":"Chenhuacun",
    "wof:placetype":"locality"
},
  "geometry": {"coordinates":[119.17328000000001,33.4657],"type":"Point"}
}