{
  "type": "Feature",
  "properties": {
    "gn:admin1_code":"18",
    "gn:asciiname":"Yanzichong",
    "gn:country_code":"CN",
    "gn:dem":1590,
    "gn:feature_class":"P",
    "gn:feature_code":"PPL",
    "gn:name":"Yanzichong",
    "gn:population":0,
    "gn:timezone":"Asia/Shanghai",
    "iso:country":"CN",
    "name:zho_x_preferred":[
        "\u5ca9\u5b50\u51b2"
    ],
    "wof:name":"Yanzichong",
    "wof:placetype":"locality"
},
  "geometry": {"coordinates":[105.455,25.5788],"type":"Point"}
}