{
  "type": "Feature",
  "properties": {
    "gn:admin1_code":"2.0",
    "gn:asciiname":"Pingshiling",
    "gn:country_code":"CN",
    "gn:dem":6,
    "gn:feature_class":"P",
    "gn:feature_code":"PPL",
    "gn:name":"Pingshiling",
    "gn:population":0,
    "gn:timezone":"Asia/Shanghai",
    "iso:country":"CN",
    "name:zho_x_preferred":[
        "\u5e73\u77f3\u5cad"
    ],
    "wof:name":"Pingshiling",
    "wof:placetype":"locality"
},
  "geometry": {"coordinates":[121.65279,29.23797],"type":"Point"}
}