{
  "type": "Feature",
  "properties": {
    "gn:admin1_code":"10.0",
    "gn:asciiname":"Tielingwa",
    "gn:country_code":"CN",
    "gn:dem":865,
    "gn:feature_class":"P",
    "gn:feature_code":"PPL",
    "gn:name":"Tielingwa",
    "gn:population":0,
    "gn:timezone":"Asia/Shanghai",
    "iso:country":"CN",
    "name:zho_x_preferred":[
        "\u94c1\u5cad\u6d3c"
    ],
    "wof:name":"Tielingwa",
    "wof:placetype":"locality"
},
  "geometry": {"coordinates":[114.21769,39.03918],"type":"Point"}
}