{
  "type": "Feature",
  "properties": {
    "gn:admin1_code":"18",
    "gn:asciiname":"Yejiping",
    "gn:country_code":"CN",
    "gn:dem":2254,
    "gn:feature_class":"P",
    "gn:feature_code":"PPL",
    "gn:name":"Yejiping",
    "gn:population":0,
    "gn:timezone":"Asia/Shanghai",
    "iso:country":"CN",
    "name:zho_x_preferred":[
        "\u91ce\u9e21\u576a"
    ],
    "wof:name":"Yejiping",
    "wof:placetype":"locality"
},
  "geometry": {"coordinates":[104.69,26.463],"type":"Point"}
}