{
  "type": "Feature",
  "properties": {
    "gn:admin1_code":"22.0",
    "gn:asciiname":"Beichengzicun",
    "gn:country_code":"CN",
    "gn:dem":28,
    "gn:feature_class":"P",
    "gn:feature_code":"PPL",
    "gn:name":"Beichengzicun",
    "gn:population":0,
    "gn:timezone":"Asia/Shanghai",
    "iso:country":"CN",
    "name:zho_x_preferred":[
        "\u5317\u57ce\u5b50\u6751"
    ],
    "wof:name":"Beichengzicun",
    "wof:placetype":"locality"
},
  "geometry": {"coordinates":[117.06585,40.16915],"type":"Point"}
}