{
  "type": "Feature",
  "properties": {
    "gn:admin1_code":"30.0",
    "gn:asciiname":"Meiziping",
    "gn:country_code":"CN",
    "gn:dem":301,
    "gn:feature_class":"P",
    "gn:feature_code":"PPL",
    "gn:name":"Meiziping",
    "gn:population":0,
    "gn:timezone":"Asia/Shanghai",
    "iso:country":"CN",
    "name:zho_x_preferred":[
        "Meiziping"
    ],
    "name:zho_x_variant":[
        "\u6885\u5b50\u576a"
    ],
    "wof:name":"Meiziping",
    "wof:placetype":"locality"
},
  "geometry": {"coordinates":[112.98333,25.34194],"type":"Point"}
}