{
  "type": "Feature",
  "properties": {
    "gn:admin1_code":"14.0",
    "gn:asciiname":"Longpanka",
    "gn:country_code":"CN",
    "gn:dem":4375,
    "gn:feature_class":"P",
    "gn:feature_code":"PPL",
    "gn:name":"Longpanka",
    "gn:population":0,
    "gn:timezone":"Asia/Urumqi",
    "iso:country":"CN",
    "name:zho_x_preferred":[
        "\u9f99\u76d8\u5361"
    ],
    "wof:name":"Longpanka",
    "wof:placetype":"locality"
},
  "geometry": {"coordinates":[93.61642000000001,31.52704],"type":"Point"}
}