{
  "type": "Feature",
  "properties": {
    "gn:admin1_code":"1.0",
    "gn:asciiname":"Daxiecun",
    "gn:country_code":"CN",
    "gn:dem":674,
    "gn:feature_class":"P",
    "gn:feature_code":"PPL",
    "gn:name":"Daxiecun",
    "gn:population":0,
    "gn:timezone":"Asia/Shanghai",
    "iso:country":"CN",
    "name:zho_x_preferred":[
        "\u5927\u6b47\u6751"
    ],
    "wof:name":"Daxiecun",
    "wof:placetype":"locality"
},
  "geometry": {"coordinates":[116.46418,31.05538],"type":"Point"}
}