{
  "type": "Feature",
  "properties": {
    "gn:admin1_code":"13",
    "gn:asciiname":"Youkake Ai'ermudong",
    "gn:country_code":"CN",
    "gn:dem":1271,
    "gn:feature_class":"P",
    "gn:feature_code":"PPL",
    "gn:name":"Youkake Ai\u2019ermudong",
    "gn:population":0,
    "gn:timezone":"Asia/Shanghai",
    "iso:country":"CN",
    "name:und_x_variant":[
        "Youkake Ai\u2019ermudong"
    ],
    "name:zho_x_preferred":[
        "\u5c24\u5580\u514b\u827e\u5c14\u6728\u4e1c"
    ],
    "wof:name":"Youkake Ai'ermudong",
    "wof:placetype":"locality"
},
  "geometry": {"coordinates":[76.16459,39.15997],"type":"Point"}
}