{
  "type": "Feature",
  "properties": {
    "gn:admin1_code":"10.0",
    "gn:asciiname":"Xiaoxizhang",
    "gn:country_code":"CN",
    "gn:dem":65,
    "gn:feature_class":"P",
    "gn:feature_code":"PPL",
    "gn:name":"Xiaoxizhang",
    "gn:population":0,
    "gn:timezone":"Asia/Shanghai",
    "iso:country":"CN",
    "name:und_x_variant":[
        "\u5c0f\u897f\u5e10"
    ],
    "wof:name":"Xiaoxizhang",
    "wof:placetype":"locality"
},
  "geometry": {"coordinates":[114.65772,38.03654],"type":"Point"}
}