{
  "type": "Feature",
  "properties": {
    "gn:admin1_code":"30",
    "gn:asciiname":"Bengshan",
    "gn:country_code":"CN",
    "gn:dem":481,
    "gn:feature_class":"P",
    "gn:feature_code":"PPL",
    "gn:name":"Bengshan",
    "gn:population":0,
    "gn:timezone":"Asia/Urumqi",
    "iso:country":"CN",
    "name:zho_x_preferred":[
        "\u5d29\u5c71"
    ],
    "wof:name":"Bengshan",
    "wof:placetype":"locality"
},
  "geometry": {"coordinates":[111.1152,21.93572],"type":"Point"}
}