{
  "type": "Feature",
  "properties": {
    "gn:admin1_code":"11.0",
    "gn:asciiname":"Xiangjiawan",
    "gn:country_code":"CN",
    "gn:dem":163,
    "gn:feature_class":"P",
    "gn:feature_code":"PPL",
    "gn:name":"Xiangjiawan",
    "gn:population":0,
    "gn:timezone":"Asia/Shanghai",
    "iso:country":"CN",
    "name:zho_x_preferred":[
        "Xiangjiawan"
    ],
    "name:zho_x_variant":[
        "\u9879\u5bb6\u6e7e"
    ],
    "wof:name":"Xiangjiawan",
    "wof:placetype":"locality"
},
  "geometry": {"coordinates":[111.05268999999998,29.30861],"type":"Point"}
}