{
  "type": "Feature",
  "properties": {
    "gn:admin1_code":"13",
    "gn:asciiname":"Tuwu",
    "gn:country_code":"CN",
    "gn:dem":585,
    "gn:feature_class":"P",
    "gn:feature_code":"PPL",
    "gn:name":"Tuwu",
    "gn:population":0,
    "gn:timezone":"Asia/Urumqi",
    "iso:country":"CN",
    "name:zho_x_preferred":[
        "\u571f\u5c4b"
    ],
    "wof:name":"Tuwu",
    "wof:placetype":"locality"
},
  "geometry": {"coordinates":[92.63621000000001,42.13508],"type":"Point"}
}