{
  "type": "Feature",
  "properties": {
    "gn:admin1_code":"16.0",
    "gn:asciiname":"Shengguichong",
    "gn:country_code":"CN",
    "gn:dem":109,
    "gn:feature_class":"P",
    "gn:feature_code":"PPL",
    "gn:name":"Shengguichong",
    "gn:population":0,
    "gn:timezone":"Asia/Shanghai",
    "iso:country":"CN",
    "name:zho_x_preferred":[
        "\u751f\u6842\u51b2"
    ],
    "wof:name":"Shengguichong",
    "wof:placetype":"locality"
},
  "geometry": {"coordinates":[110.29600000000001,23.3187],"type":"Point"}
}