{
  "type": "Feature",
  "properties": {
    "gn:admin1_code":"14",
    "gn:asciiname":"Chanaqiang",
    "gn:country_code":"CN",
    "gn:dem":4375,
    "gn:feature_class":"P",
    "gn:feature_code":"PPL",
    "gn:name":"Chanaqiang",
    "gn:population":0,
    "gn:timezone":"Asia/Urumqi",
    "iso:country":"CN",
    "name:zho_x_preferred":[
        "\u67e5\u90a3\u5f3a"
    ],
    "wof:name":"Chanaqiang",
    "wof:placetype":"locality"
},
  "geometry": {"coordinates":[89.45869999999999,28.6249],"type":"Point"}
}