{
  "type": "Feature",
  "properties": {
    "gn:admin1_code":"8.0",
    "gn:asciiname":"Mazi Wopeng",
    "gn:country_code":"CN",
    "gn:dem":137,
    "gn:feature_class":"P",
    "gn:feature_code":"PPL",
    "gn:name":"Mazi Wopeng",
    "gn:population":0,
    "gn:timezone":"Asia/Shanghai",
    "iso:country":"CN",
    "name:zho_x_preferred":[
        "\u9ebb\u5b50\u7a9d\u68da"
    ],
    "wof:name":"Mazi Wopeng",
    "wof:placetype":"locality"
},
  "geometry": {"coordinates":[123.62515999999999,46.2863],"type":"Point"}
}