{
  "type": "Feature",
  "properties": {
    "gn:admin1_code":"12.0",
    "gn:asciiname":"Wudanglu",
    "gn:country_code":"CN",
    "gn:dem":231,
    "gn:feature_class":"P",
    "gn:feature_code":"PPLA4",
    "gn:name":"Wudanglu",
    "gn:population":0,
    "gn:timezone":"Asia/Shanghai",
    "iso:country":"CN",
    "name:und_x_variant":[
        "Wudanglu Jiedao"
    ],
    "name:zho_x_preferred":[
        "\u6b66\u5f53\u8def"
    ],
    "name:zho_x_variant":[
        "\u6b66\u5f53\u8def\u8857\u9053"
    ],
    "wof:name":"Wudanglu",
    "wof:placetype":"locality"
},
  "geometry": {"coordinates":[110.79776,32.59151],"type":"Point"}
}