{
  "type": "Feature",
  "properties": {
    "gn:admin1_code":"30",
    "gn:asciiname":"Diaode",
    "gn:country_code":"CN",
    "gn:dem":16,
    "gn:feature_class":"P",
    "gn:feature_code":"PPL",
    "gn:name":"Diaode",
    "gn:population":0,
    "gn:timezone":"Asia/Urumqi",
    "iso:country":"CN",
    "name:zho_x_preferred":[
        "\u8c03\u5fb7"
    ],
    "wof:name":"Diaode",
    "wof:placetype":"locality"
},
  "geometry": {"coordinates":[110.88534,21.39077],"type":"Point"}
}