{
  "type": "Feature",
  "properties": {
    "gn:admin1_code":"8.0",
    "gn:asciiname":"Xiaosanxing",
    "gn:country_code":"CN",
    "gn:dem":139,
    "gn:feature_class":"P",
    "gn:feature_code":"PPL",
    "gn:name":"Xiaosanxing",
    "gn:population":0,
    "gn:timezone":"Asia/Shanghai",
    "iso:country":"CN",
    "name:zho_x_preferred":[
        "\u5c0f\u4e09\u59d3"
    ],
    "wof:name":"Xiaosanxing",
    "wof:placetype":"locality"
},
  "geometry": {"coordinates":[126.5089,45.68415],"type":"Point"}
}