{
  "type": "Feature",
  "properties": {
    "gn:admin1_code":"19.0",
    "gn:asciiname":"Shimiaozicun",
    "gn:country_code":"CN",
    "gn:dem":41,
    "gn:feature_class":"P",
    "gn:feature_code":"PPL",
    "gn:name":"Shimiaozicun",
    "gn:population":0,
    "gn:timezone":"Asia/Shanghai",
    "iso:country":"CN",
    "name:zho_x_preferred":[
        "\u77f3\u5e99\u5b50\u6751"
    ],
    "wof:name":"Shimiaozicun",
    "wof:placetype":"locality"
},
  "geometry": {"coordinates":[123.041,42.1898],"type":"Point"}
}