{
  "type": "Feature",
  "properties": {
    "gn:admin1_code":"8.0",
    "gn:asciiname":"Wuzuofang",
    "gn:country_code":"CN",
    "gn:dem":154,
    "gn:feature_class":"P",
    "gn:feature_code":"PPL",
    "gn:name":"Wuzuofang",
    "gn:population":0,
    "gn:timezone":"Asia/Shanghai",
    "iso:country":"CN",
    "name:zho_x_preferred":[
        "\u4e94\u5ea7\u623f"
    ],
    "wof:name":"Wuzuofang",
    "wof:placetype":"locality"
},
  "geometry": {"coordinates":[124.81282,47.24748],"type":"Point"}
}