{
  "type": "Feature",
  "properties": {
    "gn:admin1_code":"4.0",
    "gn:asciiname":"Jiangtaozhuang",
    "gn:country_code":"CN",
    "gn:dem":12,
    "gn:feature_class":"P",
    "gn:feature_code":"PPL",
    "gn:name":"Jiangtaozhuang",
    "gn:population":0,
    "gn:timezone":"Asia/Shanghai",
    "iso:country":"CN",
    "name:zho_x_preferred":[
        "\u848b\u9676\u5e84"
    ],
    "wof:name":"Jiangtaozhuang",
    "wof:placetype":"locality"
},
  "geometry": {"coordinates":[118.821,33.1933],"type":"Point"}
}