{
  "type": "Feature",
  "properties": {
    "gn:admin1_code":"19.0",
    "gn:asciiname":"Dujiazhangzi",
    "gn:country_code":"CN",
    "gn:dem":301,
    "gn:feature_class":"P",
    "gn:feature_code":"PPL",
    "gn:name":"Dujiazhangzi",
    "gn:population":0,
    "gn:timezone":"Asia/Shanghai",
    "iso:country":"CN",
    "name:zho_x_preferred":[
        "\u675c\u5bb6\u6756\u5b50"
    ],
    "wof:name":"Dujiazhangzi",
    "wof:placetype":"locality"
},
  "geometry": {"coordinates":[120.76268,42.00418],"type":"Point"}
}