{
  "type": "Feature",
  "properties": {
    "gn:admin1_code":"30.0",
    "gn:asciiname":"Maliaotangcun",
    "gn:country_code":"CN",
    "gn:dem":29,
    "gn:feature_class":"P",
    "gn:feature_code":"PPL",
    "gn:name":"Maliaotangcun",
    "gn:population":0,
    "gn:timezone":"Asia/Shanghai",
    "iso:country":"CN",
    "name:und_x_variant":[
        "Maliaotang"
    ],
    "name:zho_x_preferred":[
        "\u9a6c\u6599\u5802\u6751"
    ],
    "name:zho_x_variant":[
        "\u9a6c\u6599\u5802"
    ],
    "wof:name":"Maliaotangcun",
    "wof:placetype":"locality"
},
  "geometry": {"coordinates":[116.21356000000002,23.6432],"type":"Point"}
}