{
  "type": "Feature",
  "properties": {
    "gn:admin1_code":"29.0",
    "gn:asciiname":"Maliping",
    "gn:country_code":"CN",
    "gn:dem":2496,
    "gn:feature_class":"P",
    "gn:feature_code":"PPL",
    "gn:name":"Maliping",
    "gn:population":0,
    "gn:timezone":"Asia/Shanghai",
    "iso:country":"CN",
    "name:zho_x_preferred":[
        "\u9ebb\u6817\u576a"
    ],
    "wof:name":"Maliping",
    "wof:placetype":"locality"
},
  "geometry": {"coordinates":[103.28700000000001,26.32800000000001],"type":"Point"}
}