{
  "type": "Feature",
  "properties": {
    "gn:admin1_code":"24.0",
    "gn:asciiname":"Shapojiao",
    "gn:country_code":"CN",
    "gn:dem":607,
    "gn:feature_class":"P",
    "gn:feature_code":"PPL",
    "gn:name":"Shapojiao",
    "gn:population":0,
    "gn:timezone":"Asia/Shanghai",
    "iso:country":"CN",
    "name:zho_x_preferred":[
        "\u6c99\u5761\u811a"
    ],
    "wof:name":"Shapojiao",
    "wof:placetype":"locality"
},
  "geometry": {"coordinates":[111.61284999999999,35.21912000000001],"type":"Point"}
}