{
  "type": "Feature",
  "properties": {
    "gn:admin1_code":"4.0",
    "gn:asciiname":"Zhanggaocun",
    "gn:country_code":"CN",
    "gn:dem":16,
    "gn:feature_class":"P",
    "gn:feature_code":"PPL",
    "gn:name":"Zhanggaocun",
    "gn:population":0,
    "gn:timezone":"Asia/Shanghai",
    "iso:country":"CN",
    "name:zho_x_preferred":[
        "\u5f20\u7a3f\u6751"
    ],
    "wof:name":"Zhanggaocun",
    "wof:placetype":"locality"
},
  "geometry": {"coordinates":[118.38208,33.71472],"type":"Point"}
}