{
  "type": "Feature",
  "properties": {
    "gn:admin1_code":"18",
    "gn:asciiname":"Tatu",
    "gn:country_code":"CN",
    "gn:dem":1782,
    "gn:feature_class":"P",
    "gn:feature_code":"PPL",
    "gn:name":"Tatu",
    "gn:population":0,
    "gn:timezone":"Asia/Shanghai",
    "iso:country":"CN",
    "name:zho_x_preferred":[
        "\u8e0f\u571f"
    ],
    "wof:name":"Tatu",
    "wof:placetype":"locality"
},
  "geometry": {"coordinates":[104.92700000000001,26.8875],"type":"Point"}
}