{
  "type": "Feature",
  "properties": {
    "gn:admin1_code":"10",
    "gn:asciiname":"Ershiqihao",
    "gn:country_code":"CN",
    "gn:dem":1032,
    "gn:feature_class":"P",
    "gn:feature_code":"PPLF",
    "gn:name":"Ershiqihao",
    "gn:population":0,
    "gn:timezone":"Asia/Shanghai",
    "iso:country":"CN",
    "name:zho_x_preferred":[
        "\u4e8c\u5341\u4e03\u53f7"
    ],
    "wof:name":"Ershiqihao",
    "wof:placetype":"locality"
},
  "geometry": {"coordinates":[117.53408,42.06328],"type":"Point"}
}