{
  "type": "Feature",
  "properties": {
    "gn:admin1_code":"16.0",
    "gn:asciiname":"Qingshuijiang",
    "gn:country_code":"CN",
    "gn:dem":25,
    "gn:feature_class":"P",
    "gn:feature_code":"PPL",
    "gn:name":"Qingshuijiang",
    "gn:population":0,
    "gn:timezone":"Asia/Shanghai",
    "iso:country":"CN",
    "name:zho_x_preferred":[
        "\u6e05\u6c34\u6c5f"
    ],
    "wof:name":"Qingshuijiang",
    "wof:placetype":"locality"
},
  "geometry": {"coordinates":[108.958,21.6945],"type":"Point"}
}