{
  "type": "Feature",
  "properties": {
    "gn:admin1_code":"16.0",
    "gn:asciiname":"Pingjiu",
    "gn:country_code":"CN",
    "gn:dem":504,
    "gn:feature_class":"P",
    "gn:feature_code":"PPL",
    "gn:name":"Pingjiu",
    "gn:population":0,
    "gn:timezone":"Asia/Shanghai",
    "iso:country":"CN",
    "name:zho_x_preferred":[
        "\u5e73\u7a76"
    ],
    "wof:name":"Pingjiu",
    "wof:placetype":"locality"
},
  "geometry": {"coordinates":[107.116,23.2639],"type":"Point"}
}