{
  "type": "Feature",
  "properties": {
    "gn:admin1_code":"4.0",
    "gn:asciiname":"Huailou",
    "gn:country_code":"CN",
    "gn:dem":8,
    "gn:feature_class":"P",
    "gn:feature_code":"PPL",
    "gn:name":"Huailou",
    "gn:population":0,
    "gn:timezone":"Asia/Shanghai",
    "iso:country":"CN",
    "name:zho_x_preferred":[
        "Huailou"
    ],
    "name:zho_x_variant":[
        "\u69d0\u697c"
    ],
    "wof:name":"Huailou",
    "wof:placetype":"locality"
},
  "geometry": {"coordinates":[119.32646,33.1584],"type":"Point"}
}