{
  "type": "Feature",
  "properties": {
    "gn:admin1_code":"30",
    "gn:asciiname":"Xingxiecun",
    "gn:country_code":"CN",
    "gn:dem":31,
    "gn:feature_class":"P",
    "gn:feature_code":"PPL",
    "gn:name":"Xingxiecun",
    "gn:population":0,
    "gn:timezone":"Asia/Urumqi",
    "iso:country":"CN",
    "name:zho_x_preferred":[
        "\u59d3\u8c22\u6751"
    ],
    "wof:name":"Xingxiecun",
    "wof:placetype":"locality"
},
  "geometry": {"coordinates":[110.05277,21.42754],"type":"Point"}
}