{
  "type": "Feature",
  "properties": {
    "gn:admin1_code":"15.0",
    "gn:asciiname":"Balukou",
    "gn:country_code":"CN",
    "gn:dem":2872,
    "gn:feature_class":"P",
    "gn:feature_code":"PPL",
    "gn:name":"Balukou",
    "gn:population":0,
    "gn:timezone":"Asia/Shanghai",
    "iso:country":"CN",
    "name:und_x_variant":[
        "\u516b\u8def\u53e3",
        "Balukou Daoban",
        "\u516b\u8def\u53e3\u9053\u6591"
    ],
    "wof:name":"Balukou",
    "wof:placetype":"locality"
},
  "geometry": {"coordinates":[103.93306,34.23979],"type":"Point"}
}