{
  "type": "Feature",
  "properties": {
    "gn:admin1_code":"11.0",
    "gn:asciiname":"Chengouchong",
    "gn:country_code":"CN",
    "gn:dem":167,
    "gn:feature_class":"P",
    "gn:feature_code":"PPL",
    "gn:name":"Chengouchong",
    "gn:population":0,
    "gn:timezone":"Asia/Shanghai",
    "iso:country":"CN",
    "name:zho_x_preferred":[
        "\u9648\u94a9\u51b2"
    ],
    "wof:name":"Chengouchong",
    "wof:placetype":"locality"
},
  "geometry": {"coordinates":[113.35119,26.40491],"type":"Point"}
}