{
  "type": "Feature",
  "properties": {
    "gn:admin1_code":"12.0",
    "gn:asciiname":"Xiaolabi",
    "gn:country_code":"CN",
    "gn:dem":877,
    "gn:feature_class":"P",
    "gn:feature_code":"PPL",
    "gn:name":"Xiaolabi",
    "gn:population":0,
    "gn:timezone":"Asia/Shanghai",
    "iso:country":"CN",
    "name:zho_x_preferred":[
        "\u5c0f\u814a\u58c1"
    ],
    "wof:name":"Xiaolabi",
    "wof:placetype":"locality"
},
  "geometry": {"coordinates":[108.89661,29.9435],"type":"Point"}
}