{
  "type": "Feature",
  "properties": {
    "gn:admin1_code":"4.0",
    "gn:asciiname":"Tanghongzhuang",
    "gn:country_code":"CN",
    "gn:dem":1,
    "gn:feature_class":"P",
    "gn:feature_code":"PPL",
    "gn:name":"Tanghongzhuang",
    "gn:population":0,
    "gn:timezone":"Asia/Shanghai",
    "iso:country":"CN",
    "name:zho_x_preferred":[
        "Tanghongzhuang"
    ],
    "name:zho_x_variant":[
        "\u6c64\u6d2a\u5e84"
    ],
    "wof:name":"Tanghongzhuang",
    "wof:placetype":"locality"
},
  "geometry": {"coordinates":[119.05318,34.15852],"type":"Point"}
}