{
  "type": "Feature",
  "properties": {
    "gn:admin1_code":"4.0",
    "gn:asciiname":"Hengloucun",
    "gn:country_code":"CN",
    "gn:dem":26,
    "gn:feature_class":"P",
    "gn:feature_code":"PPL",
    "gn:name":"Hengloucun",
    "gn:population":0,
    "gn:timezone":"Asia/Shanghai",
    "iso:country":"CN",
    "name:zho_x_preferred":[
        "\u8861\u697c\u6751"
    ],
    "wof:name":"Hengloucun",
    "wof:placetype":"locality"
},
  "geometry": {"coordinates":[117.82867,34.28113],"type":"Point"}
}