{
  "type": "Feature",
  "properties": {
    "gn:admin1_code":"21.0",
    "gn:asciiname":"Guanyinmao",
    "gn:country_code":"CN",
    "gn:dem":1702,
    "gn:feature_class":"P",
    "gn:feature_code":"PPL",
    "gn:name":"Guanyinmao",
    "gn:population":0,
    "gn:timezone":"Asia/Shanghai",
    "iso:country":"CN",
    "name:zho_x_preferred":[
        "\u5173\u97f3\u5cc1"
    ],
    "wof:name":"Guanyinmao",
    "wof:placetype":"locality"
},
  "geometry": {"coordinates":[107.095,37.3714],"type":"Point"}
}