{
  "type": "Feature",
  "properties": {
    "gn:admin1_code":"26.0",
    "gn:asciiname":"Shiyaopucun",
    "gn:country_code":"CN",
    "gn:dem":1432,
    "gn:feature_class":"P",
    "gn:feature_code":"PPL",
    "gn:name":"Shiyaopucun",
    "gn:population":0,
    "gn:timezone":"Asia/Shanghai",
    "iso:country":"CN",
    "name:zho_x_preferred":[
        "\u77f3\u7a91\u94fa\u6751"
    ],
    "wof:name":"Shiyaopucun",
    "wof:placetype":"locality"
},
  "geometry": {"coordinates":[106.87246,34.20975],"type":"Point"}
}