{
  "type": "Feature",
  "properties": {
    "gn:admin1_code":"7",
    "gn:asciiname":"Houyang",
    "gn:country_code":"CN",
    "gn:dem":713,
    "gn:feature_class":"P",
    "gn:feature_code":"PPL",
    "gn:name":"Houyang",
    "gn:population":0,
    "gn:timezone":"Asia/Shanghai",
    "iso:country":"CN",
    "name:und_x_variant":[
        "\u540e\u6d0b"
    ],
    "wof:name":"Houyang",
    "wof:placetype":"locality"
},
  "geometry": {"coordinates":[119.3475,27.05167],"type":"Point"}
}