{
  "type": "Feature",
  "properties": {
    "gn:admin1_code":"6.0",
    "gn:asciiname":"Meimo",
    "gn:country_code":"CN",
    "gn:dem":3630,
    "gn:feature_class":"P",
    "gn:feature_code":"PPL",
    "gn:name":"Meimo",
    "gn:population":0,
    "gn:timezone":"Asia/Urumqi",
    "iso:country":"CN",
    "name:zho_x_preferred":[
        "\u7f8e\u83ab"
    ],
    "wof:name":"Meimo",
    "wof:placetype":"locality"
},
  "geometry": {"coordinates":[97.1833,33.0396],"type":"Point"}
}