{
  "type": "Feature",
  "properties": {
    "gn:admin1_code":"12.0",
    "gn:asciiname":"Zhuximu",
    "gn:country_code":"CN",
    "gn:dem":305,
    "gn:feature_class":"P",
    "gn:feature_code":"PPL",
    "gn:name":"Zhuximu",
    "gn:population":0,
    "gn:timezone":"Asia/Shanghai",
    "iso:country":"CN",
    "name:zho_x_preferred":[
        "\u7af9\u6eaa\u5893"
    ],
    "wof:name":"Zhuximu",
    "wof:placetype":"locality"
},
  "geometry": {"coordinates":[110.76385999999999,31.1504],"type":"Point"}
}