{
  "type": "Feature",
  "properties": {
    "gn:admin1_code":"20.0",
    "gn:asciiname":"Tashahe",
    "gn:country_code":"CN",
    "gn:dem":1644,
    "gn:feature_class":"P",
    "gn:feature_code":"PPL",
    "gn:name":"Tashahe",
    "gn:population":0,
    "gn:timezone":"Asia/Shanghai",
    "iso:country":"CN",
    "name:und_x_variant":[
        "\u5854\u6c99\u6838"
    ],
    "wof:name":"Tashahe",
    "wof:placetype":"locality"
},
  "geometry": {"coordinates":[113.00548999999999,41.41659],"type":"Point"}
}