{
  "type": "Feature",
  "properties": {
    "gn:admin1_code":"33.0",
    "gn:asciiname":"Xibei",
    "gn:country_code":"CN",
    "gn:dem":284,
    "gn:feature_class":"P",
    "gn:feature_code":"PPL",
    "gn:name":"Xibei",
    "gn:population":0,
    "gn:timezone":"Asia/Shanghai",
    "iso:country":"CN",
    "name:zho_x_preferred":[
        "\u897f\u5317"
    ],
    "wof:name":"Xibei",
    "wof:placetype":"locality"
},
  "geometry": {"coordinates":[105.96835,29.94792],"type":"Point"}
}