{
  "type": "Feature",
  "properties": {
    "gn:admin1_code":"29.0",
    "gn:asciiname":"Wuguzuo",
    "gn:country_code":"CN",
    "gn:dem":1944,
    "gn:feature_class":"P",
    "gn:feature_code":"PPL",
    "gn:name":"Wuguzuo",
    "gn:population":0,
    "gn:timezone":"Asia/Shanghai",
    "iso:country":"CN",
    "name:zho_x_preferred":[
        "\u4e4c\u59d1\u5ea7"
    ],
    "wof:name":"Wuguzuo",
    "wof:placetype":"locality"
},
  "geometry": {"coordinates":[104.44799999999999,26.042],"type":"Point"}
}