{
  "type": "Feature",
  "properties": {
    "gn:admin1_code":"04",
    "gn:asciiname":"Shigang",
    "gn:country_code":"CN",
    "gn:dem":8,
    "gn:feature_class":"P",
    "gn:feature_code":"PPLA4",
    "gn:name":"Shigang",
    "gn:population":0,
    "gn:timezone":"Asia/Shanghai",
    "iso:country":"CN",
    "name:und_x_variant":[
        "Shih-chiang-chen",
        "Shihkiang",
        "Shih-chiang",
        "Shih-kang",
        "Shih-kang-chen",
        "Shigang",
        "\u77f3\u6e2f",
        "\u77f3\u6e2f\u9547",
        "Shigang Zhen"
    ],
    "wof:name":"Shigang",
    "wof:placetype":"locality"
},
  "geometry": {"coordinates":[120.97487,32.21868],"type":"Point"}
}