{
  "type": "Feature",
  "properties": {
    "gn:admin1_code":"5.0",
    "gn:asciiname":"Wuridanzhao",
    "gn:country_code":"CN",
    "gn:dem":147,
    "gn:feature_class":"P",
    "gn:feature_code":"PPL",
    "gn:name":"Wuridanzhao",
    "gn:population":0,
    "gn:timezone":"Asia/Shanghai",
    "iso:country":"CN",
    "name:zho_x_preferred":[
        "\u4e4c\u65e5\u5355\u662d"
    ],
    "wof:name":"Wuridanzhao",
    "wof:placetype":"locality"
},
  "geometry": {"coordinates":[123.04258,45.44696],"type":"Point"}
}