{
  "type": "Feature",
  "properties": {
    "gn:admin1_code":"24",
    "gn:asciiname":"Anfen",
    "gn:cc2":"CN",
    "gn:country_code":"CN",
    "gn:dem":1187,
    "gn:feature_class":"P",
    "gn:feature_code":"PPL",
    "gn:name":"Anfen",
    "gn:population":0,
    "gn:timezone":"Asia/Shanghai",
    "iso:country":"CN",
    "name:und_x_variant":[
        "An-fen-ts\u2019un",
        "Anfen"
    ],
    "wof:name":"Anfen",
    "wof:placetype":"locality"
},
  "geometry": {"coordinates":[111.03806000000002,35.87722],"type":"Point"}
}