{
  "type": "Feature",
  "properties": {
    "gn:admin1_code":"25",
    "gn:asciiname":"Henanlang Junzhuang",
    "gn:country_code":"CN",
    "gn:dem":86,
    "gn:feature_class":"P",
    "gn:feature_code":"PPL",
    "gn:name":"Henanlang Junzhuang",
    "gn:population":0,
    "gn:timezone":"Asia/Shanghai",
    "iso:country":"CN",
    "name:zho_x_preferred":[
        "\u6cb3\u5357\u90ce\u90e1\u5e84"
    ],
    "wof:name":"Henanlang Junzhuang",
    "wof:placetype":"locality"
},
  "geometry": {"coordinates":[119.239,36.562],"type":"Point"}
}