{
  "type": "Feature",
  "properties": {
    "gn:admin1_code":"25",
    "gn:asciiname":"Xifanjiazhuang",
    "gn:country_code":"CN",
    "gn:dem":136,
    "gn:feature_class":"P",
    "gn:feature_code":"PPL",
    "gn:name":"Xifanjiazhuang",
    "gn:population":0,
    "gn:timezone":"Asia/Shanghai",
    "iso:country":"CN",
    "name:zho_x_preferred":[
        "\u897f\u8303\u5bb6\u5e84"
    ],
    "wof:name":"Xifanjiazhuang",
    "wof:placetype":"locality"
},
  "geometry": {"coordinates":[117.11199999999999,35.7988],"type":"Point"}
}