{
  "type": "Feature",
  "properties": {
    "gn:admin1_code":"5.0",
    "gn:asciiname":"Qianxinglonghe",
    "gn:country_code":"CN",
    "gn:dem":157,
    "gn:feature_class":"P",
    "gn:feature_code":"PPL",
    "gn:name":"Qianxinglonghe",
    "gn:population":0,
    "gn:timezone":"Asia/Shanghai",
    "iso:country":"CN",
    "name:zho_x_preferred":[
        "\u524d\u5174\u9686\u6cb3"
    ],
    "wof:name":"Qianxinglonghe",
    "wof:placetype":"locality"
},
  "geometry": {"coordinates":[122.7368,44.8989],"type":"Point"}
}