{
  "type": "Feature",
  "properties": {
    "gn:admin1_code":"14.0",
    "gn:asciiname":"Ripucun",
    "gn:country_code":"CN",
    "gn:dem":3636,
    "gn:feature_class":"P",
    "gn:feature_code":"PPL",
    "gn:name":"Ripucun",
    "gn:population":0,
    "gn:timezone":"Asia/Urumqi",
    "iso:country":"CN",
    "name:zho_x_preferred":[
        "\u65e5\u666e\u6751"
    ],
    "wof:name":"Ripucun",
    "wof:placetype":"locality"
},
  "geometry": {"coordinates":[94.48575,31.26612],"type":"Point"}
}