{
  "type": "Feature",
  "properties": {
    "gn:admin1_code":"3.0",
    "gn:asciiname":"Beipingshan Linchang",
    "gn:country_code":"CN",
    "gn:dem":481,
    "gn:feature_class":"P",
    "gn:feature_code":"PPLF",
    "gn:name":"Beipingshan Linchang",
    "gn:population":0,
    "gn:timezone":"Asia/Shanghai",
    "iso:country":"CN",
    "name:und_x_variant":[
        "\u5317\u576a\u5c71\u6797\u573a"
    ],
    "wof:name":"Beipingshan Linchang",
    "wof:placetype":"locality"
},
  "geometry": {"coordinates":[115.12991,29.51189],"type":"Point"}
}