{
  "type": "Feature",
  "properties": {
    "gn:admin1_code":"8.0",
    "gn:asciiname":"Taiping Linchang",
    "gn:country_code":"CN",
    "gn:dem":104,
    "gn:feature_class":"P",
    "gn:feature_code":"PPLF",
    "gn:name":"Taiping Linchang",
    "gn:population":0,
    "gn:timezone":"Asia/Shanghai",
    "iso:country":"CN",
    "name:zho_x_preferred":[
        "\u592a\u5e73\u6797\u573a"
    ],
    "wof:name":"Taiping Linchang",
    "wof:placetype":"locality"
},
  "geometry": {"coordinates":[130.30786000000001,48.86348],"type":"Point"}
}