{
  "type": "Feature",
  "properties": {
    "gn:admin1_code":"11.0",
    "gn:asciiname":"Shenjichong",
    "gn:country_code":"CN",
    "gn:dem":505,
    "gn:feature_class":"P",
    "gn:feature_code":"PPL",
    "gn:name":"Shenjichong",
    "gn:population":0,
    "gn:timezone":"Asia/Shanghai",
    "iso:country":"CN",
    "name:zho_x_preferred":[
        "\u795e\u9e21\u51b2"
    ],
    "wof:name":"Shenjichong",
    "wof:placetype":"locality"
},
  "geometry": {"coordinates":[112.72866999999999,26.09173],"type":"Point"}
}