{
  "type": "Feature",
  "properties": {
    "gn:admin1_code":"25.0",
    "gn:asciiname":"Nanqilizhuangcun",
    "gn:country_code":"CN",
    "gn:dem":182,
    "gn:feature_class":"P",
    "gn:feature_code":"PPL",
    "gn:name":"Nanqilizhuangcun",
    "gn:population":0,
    "gn:timezone":"Asia/Shanghai",
    "iso:country":"CN",
    "name:zho_x_preferred":[
        "\u5357\u4e03\u91cc\u5e84\u6751"
    ],
    "wof:name":"Nanqilizhuangcun",
    "wof:placetype":"locality"
},
  "geometry": {"coordinates":[120.80415000000001,37.27752],"type":"Point"}
}