{
  "type": "Feature",
  "properties": {
    "gn:admin1_code":"30.0",
    "gn:asciiname":"Chengnancun",
    "gn:country_code":"CN",
    "gn:dem":5,
    "gn:feature_class":"P",
    "gn:feature_code":"PPL",
    "gn:name":"Chengnancun",
    "gn:population":0,
    "gn:timezone":"Asia/Shanghai",
    "iso:country":"CN",
    "name:zho_x_preferred":[
        "\u57ce\u5357\u6751"
    ],
    "wof:name":"Chengnancun",
    "wof:placetype":"locality"
},
  "geometry": {"coordinates":[116.31726999999999,23.54405],"type":"Point"}
}