{
  "type": "Feature",
  "properties": {
    "gn:admin1_code":"32.0",
    "gn:asciiname":"Shibanxi",
    "gn:country_code":"CN",
    "gn:dem":561,
    "gn:feature_class":"P",
    "gn:feature_code":"PPL",
    "gn:name":"Shibanxi",
    "gn:population":0,
    "gn:timezone":"Asia/Shanghai",
    "iso:country":"CN",
    "name:zho_x_preferred":[
        "\u77f3\u677f\u6eaa"
    ],
    "wof:name":"Shibanxi",
    "wof:placetype":"locality"
},
  "geometry": {"coordinates":[103.33,29.3063],"type":"Point"}
}