{
  "type": "Feature",
  "properties": {
    "gn:admin1_code":"9.0",
    "gn:asciiname":"Yancheng Chengguanzhen",
    "gn:country_code":"CN",
    "gn:dem":69,
    "gn:feature_class":"P",
    "gn:feature_code":"PPLA3",
    "gn:name":"Yancheng Chengguanzhen",
    "gn:population":0,
    "gn:timezone":"Asia/Shanghai",
    "iso:country":"CN",
    "name:und_x_variant":[
        "Yen-ch\u2019eng-hsien",
        "Yen-hsien",
        "Yen-ch\u2019eng",
        "Yancheng",
        "Yancheng Chengguanzhen"
    ],
    "name:zho_x_preferred":[
        "\u90fe\u57ce\u57ce\u5173\u9547"
    ],
    "wof:name":"Yancheng Chengguanzhen",
    "wof:placetype":"locality"
},
  "geometry": {"coordinates":[113.98667,33.58472],"type":"Point"}
}