{
  "type": "Feature",
  "properties": {
    "gn:admin1_code":"32.0",
    "gn:asciiname":"Laoguanfang",
    "gn:country_code":"CN",
    "gn:dem":1635,
    "gn:feature_class":"P",
    "gn:feature_code":"PPL",
    "gn:name":"Laoguanfang",
    "gn:population":0,
    "gn:timezone":"Asia/Shanghai",
    "iso:country":"CN",
    "name:zho_x_preferred":[
        "\u8001\u5b98\u623f"
    ],
    "wof:name":"Laoguanfang",
    "wof:placetype":"locality"
},
  "geometry": {"coordinates":[102.81399999999999,26.3268],"type":"Point"}
}