{
  "type": "Feature",
  "properties": {
    "gn:admin1_code":"12.0",
    "gn:asciiname":"Huangshiban",
    "gn:country_code":"CN",
    "gn:dem":784,
    "gn:feature_class":"P",
    "gn:feature_code":"PPL",
    "gn:name":"Huangshiban",
    "gn:population":0,
    "gn:timezone":"Asia/Shanghai",
    "iso:country":"CN",
    "name:zho_x_preferred":[
        "\u9ec4\u77f3\u677f"
    ],
    "wof:name":"Huangshiban",
    "wof:placetype":"locality"
},
  "geometry": {"coordinates":[110.06952,33.08041],"type":"Point"}
}