{
  "type": "Feature",
  "properties": {
    "gn:admin1_code":"29.0",
    "gn:asciiname":"Shikeshu",
    "gn:country_code":"CN",
    "gn:dem":1061,
    "gn:feature_class":"P",
    "gn:feature_code":"PPL",
    "gn:name":"Shikeshu",
    "gn:population":0,
    "gn:timezone":"Asia/Shanghai",
    "iso:country":"CN",
    "name:zho_x_preferred":[
        "\u5341\u68f5\u6811"
    ],
    "wof:name":"Shikeshu",
    "wof:placetype":"locality"
},
  "geometry": {"coordinates":[101.82299999999999,25.789],"type":"Point"}
}