{
  "type": "Feature",
  "properties": {
    "gn:admin1_code":"32.0",
    "gn:asciiname":"Gaoka",
    "gn:country_code":"CN",
    "gn:dem":3093,
    "gn:feature_class":"P",
    "gn:feature_code":"PPL",
    "gn:name":"Gaoka",
    "gn:population":0,
    "gn:timezone":"Asia/Shanghai",
    "iso:country":"CN",
    "name:zho_x_preferred":[
        "\u9ad8\u5361"
    ],
    "wof:name":"Gaoka",
    "wof:placetype":"locality"
},
  "geometry": {"coordinates":[102.51600000000001,31.3332],"type":"Point"}
}