{
  "type": "Feature",
  "properties": {
    "gn:admin1_code":"18.0",
    "gn:asciiname":"Wuyang",
    "gn:country_code":"CN",
    "gn:dem":814,
    "gn:feature_class":"P",
    "gn:feature_code":"PPL",
    "gn:name":"Wuyang",
    "gn:population":0,
    "gn:timezone":"Asia/Shanghai",
    "iso:country":"CN",
    "name:ceb_x_preferred":[
        "Wuyang"
    ],
    "name:deu_x_preferred":[
        "Wuyang"
    ],
    "name:nor_x_preferred":[
        "Wuyang"
    ],
    "name:zho_x_preferred":[
        "\u6c61\u517b"
    ],
    "wof:name":"Wuyang",
    "wof:placetype":"locality"
},
  "geometry": {"coordinates":[108.533,25.5439],"type":"Point"}
}