{
  "type": "Feature",
  "properties": {
    "gn:admin1_code":"26.0",
    "gn:asciiname":"Gumuwan",
    "gn:country_code":"CN",
    "gn:dem":759,
    "gn:feature_class":"P",
    "gn:feature_code":"PPL",
    "gn:name":"Gumuwan",
    "gn:population":0,
    "gn:timezone":"Asia/Shanghai",
    "iso:country":"CN",
    "name:und_x_variant":[
        "\u53e4\u5893\u6e7e"
    ],
    "wof:name":"Gumuwan",
    "wof:placetype":"locality"
},
  "geometry": {"coordinates":[107.19271999999999,33.51696],"type":"Point"}
}