{
  "type": "Feature",
  "properties": {
    "gn:admin1_code":"3.0",
    "gn:asciiname":"Nanguancun",
    "gn:country_code":"CN",
    "gn:dem":57,
    "gn:feature_class":"P",
    "gn:feature_code":"PPL",
    "gn:name":"Nanguancun",
    "gn:population":0,
    "gn:timezone":"Asia/Shanghai",
    "iso:country":"CN",
    "name:und_x_variant":[
        "\u5357\u5173\u6751"
    ],
    "wof:name":"Nanguancun",
    "wof:placetype":"locality"
},
  "geometry": {"coordinates":[116.62241000000002,28.22707],"type":"Point"}
}