{
  "type": "Feature",
  "properties": {
    "gn:admin1_code":"19.0",
    "gn:asciiname":"Xianjiacun",
    "gn:country_code":"CN",
    "gn:dem":96,
    "gn:feature_class":"P",
    "gn:feature_code":"PPL",
    "gn:name":"Xianjiacun",
    "gn:population":0,
    "gn:timezone":"Asia/Shanghai",
    "iso:country":"CN",
    "name:zho_x_preferred":[
        "\u54b8\u5bb6\u6751"
    ],
    "wof:name":"Xianjiacun",
    "wof:placetype":"locality"
},
  "geometry": {"coordinates":[124.38782,40.46078],"type":"Point"}
}