{
  "type": "Feature",
  "properties": {
    "gn:admin1_code":"12",
    "gn:asciiname":"Tongshankou",
    "gn:country_code":"CN",
    "gn:dem":54,
    "gn:feature_class":"P",
    "gn:feature_code":"PPL",
    "gn:name":"Tongshankou",
    "gn:population":0,
    "gn:timezone":"Asia/Shanghai",
    "iso:country":"CN",
    "name:zho_x_preferred":[
        "\u94dc\u5c71\u53e3"
    ],
    "wof:name":"Tongshankou",
    "wof:placetype":"locality"
},
  "geometry": {"coordinates":[114.82392,30.00655],"type":"Point"}
}