{
  "type": "Feature",
  "properties": {
    "gn:admin1_code":"8.0",
    "gn:asciiname":"Yongyuecun",
    "gn:country_code":"CN",
    "gn:dem":213,
    "gn:feature_class":"P",
    "gn:feature_code":"PPL",
    "gn:name":"Yongyuecun",
    "gn:population":0,
    "gn:timezone":"Asia/Shanghai",
    "iso:country":"CN",
    "name:zho_x_preferred":[
        "\u52c7\u8dc3\u6751"
    ],
    "wof:name":"Yongyuecun",
    "wof:placetype":"locality"
},
  "geometry": {"coordinates":[125.67547999999999,47.14435],"type":"Point"}
}