{
  "type": "Feature",
  "properties": {
    "gn:admin1_code":"29.0",
    "gn:asciiname":"Zhentong Dazhai",
    "gn:country_code":"CN",
    "gn:dem":1705,
    "gn:feature_class":"P",
    "gn:feature_code":"PPL",
    "gn:name":"Zhentong Dazhai",
    "gn:population":0,
    "gn:timezone":"Asia/Shanghai",
    "iso:country":"CN",
    "name:zho_x_preferred":[
        "\u771f\u901a\u5927\u5be8"
    ],
    "wof:name":"Zhentong Dazhai",
    "wof:placetype":"locality"
},
  "geometry": {"coordinates":[97.6795,24.6505],"type":"Point"}
}