{
  "type": "Feature",
  "properties": {
    "gn:admin1_code":"14.0",
    "gn:asciiname":"Yongmuqie",
    "gn:country_code":"CN",
    "gn:dem":4156,
    "gn:feature_class":"P",
    "gn:feature_code":"PPL",
    "gn:name":"Yongmuqie",
    "gn:population":0,
    "gn:timezone":"Asia/Urumqi",
    "iso:country":"CN",
    "name:zho_x_preferred":[
        "\u62e5\u6728\u5207"
    ],
    "wof:name":"Yongmuqie",
    "wof:placetype":"locality"
},
  "geometry": {"coordinates":[92.65391,29.82593],"type":"Point"}
}