{
  "type": "Feature",
  "properties": {
    "gn:admin1_code":"29.0",
    "gn:asciiname":"Tianqiuzi",
    "gn:country_code":"CN",
    "gn:dem":1589,
    "gn:feature_class":"P",
    "gn:feature_code":"PPL",
    "gn:name":"Tianqiuzi",
    "gn:population":0,
    "gn:timezone":"Asia/Shanghai",
    "iso:country":"CN",
    "name:zho_x_preferred":[
        "\u7530\u4e18\u5b50"
    ],
    "wof:name":"Tianqiuzi",
    "wof:placetype":"locality"
},
  "geometry": {"coordinates":[100.64100000000001,26.2054],"type":"Point"}
}