{
  "type": "Feature",
  "properties": {
    "gn:admin1_code":"33.0",
    "gn:asciiname":"Changmuzhuang",
    "gn:country_code":"CN",
    "gn:dem":697,
    "gn:feature_class":"P",
    "gn:feature_code":"PPL",
    "gn:name":"Changmuzhuang",
    "gn:population":0,
    "gn:timezone":"Asia/Shanghai",
    "iso:country":"CN",
    "name:zho_x_preferred":[
        "\u5382\u6728\u5e84"
    ],
    "wof:name":"Changmuzhuang",
    "wof:placetype":"locality"
},
  "geometry": {"coordinates":[109.08365000000001,28.58375],"type":"Point"}
}