{
  "type": "Feature",
  "properties": {
    "gn:admin1_code":"5.0",
    "gn:asciiname":"Wanghedian",
    "gn:country_code":"CN",
    "gn:dem":400,
    "gn:feature_class":"P",
    "gn:feature_code":"PPL",
    "gn:name":"Wanghedian",
    "gn:population":0,
    "gn:timezone":"Asia/Shanghai",
    "iso:country":"CN",
    "name:zho_x_preferred":[
        "\u65fa\u5408\u5e97"
    ],
    "wof:name":"Wanghedian",
    "wof:placetype":"locality"
},
  "geometry": {"coordinates":[126.54398999999999,43.55242],"type":"Point"}
}