{
  "type": "Feature",
  "properties": {
    "gn:admin1_code":"16.0",
    "gn:asciiname":"Fuping",
    "gn:country_code":"CN",
    "gn:dem":107,
    "gn:feature_class":"P",
    "gn:feature_code":"PPL",
    "gn:name":"Fuping",
    "gn:population":0,
    "gn:timezone":"Asia/Shanghai",
    "iso:country":"CN",
    "name:ceb_x_preferred":[
        "Fuping"
    ],
    "name:deu_x_preferred":[
        "Fuping"
    ],
    "name:fra_x_preferred":[
        "Fuping"
    ],
    "name:kor_x_preferred":[
        "\ud478\ud551\ud604"
    ],
    "name:nor_x_preferred":[
        "Fuping"
    ],
    "name:rus_x_preferred":[
        "\u0424\u0443\u043f\u0438\u043d"
    ],
    "name:swe_x_preferred":[
        "Fuping"
    ],
    "name:zho_x_preferred":[
        "\u4f0f\u5e73"
    ],
    "wof:name":"Fuping",
    "wof:placetype":"locality"
},
  "geometry": {"coordinates":[107.09999999999999,23.632],"type":"Point"}
}