{
  "type": "Feature",
  "properties": {
    "gn:admin1_code":"9.0",
    "gn:asciiname":"Laoshanxue",
    "gn:country_code":"CN",
    "gn:dem":242,
    "gn:feature_class":"P",
    "gn:feature_code":"PPL",
    "gn:name":"Laoshanxue",
    "gn:population":0,
    "gn:timezone":"Asia/Shanghai",
    "iso:country":"CN",
    "name:zho_x_preferred":[
        "\u8001\u5c71\u859b"
    ],
    "wof:name":"Laoshanxue",
    "wof:placetype":"locality"
},
  "geometry": {"coordinates":[113.2178,34.08393],"type":"Point"}
}