{
  "type": "Feature",
  "properties": {
    "gn:admin1_code":"10",
    "gn:asciiname":"Fengzhangzi",
    "gn:country_code":"CN",
    "gn:dem":384,
    "gn:feature_class":"P",
    "gn:feature_code":"PPL",
    "gn:name":"Fengzhangzi",
    "gn:population":0,
    "gn:timezone":"Asia/Shanghai",
    "iso:country":"CN",
    "name:zho_x_preferred":[
        "\u51af\u6756\u5b50"
    ],
    "wof:name":"Fengzhangzi",
    "wof:placetype":"locality"
},
  "geometry": {"coordinates":[118.62418,40.67595],"type":"Point"}
}