{
  "type": "Feature",
  "properties": {
    "gn:admin1_code":"2",
    "gn:asciiname":"Shanxiahu",
    "gn:country_code":"CN",
    "gn:dem":32,
    "gn:feature_class":"P",
    "gn:feature_code":"PPLA4",
    "gn:name":"Shanxiahu",
    "gn:population":0,
    "gn:timezone":"Asia/Shanghai",
    "iso:country":"CN",
    "name:und_x_variant":[
        "Shanxiahu Zhen"
    ],
    "name:zho_x_preferred":[
        "\u5c71\u4e0b\u6e56\u9547"
    ],
    "name:zho_x_variant":[
        "\u5c71\u4e0b\u6e56"
    ],
    "wof:name":"Shanxiahu",
    "wof:placetype":"locality"
},
  "geometry": {"coordinates":[120.35296,29.85668],"type":"Point"}
}