{
  "type": "Feature",
  "properties": {
    "gn:admin1_code":"7",
    "gn:asciiname":"Xialongban",
    "gn:country_code":"CN",
    "gn:dem":671,
    "gn:feature_class":"P",
    "gn:feature_code":"PPL",
    "gn:name":"Xialongban",
    "gn:population":0,
    "gn:timezone":"Asia/Shanghai",
    "iso:country":"CN",
    "name:zho_x_preferred":[
        "\u4e0b\u9f99\u5742"
    ],
    "wof:name":"Xialongban",
    "wof:placetype":"locality"
},
  "geometry": {"coordinates":[117.87076,25.23006],"type":"Point"}
}