{
  "type": "Feature",
  "properties": {
    "gn:admin1_code":"32.0",
    "gn:asciiname":"Houba",
    "gn:country_code":"CN",
    "gn:dem":1273,
    "gn:feature_class":"P",
    "gn:feature_code":"PPL",
    "gn:name":"Houba",
    "gn:population":0,
    "gn:timezone":"Asia/Shanghai",
    "iso:country":"CN",
    "name:zho_x_preferred":[
        "\u540e\u575d"
    ],
    "wof:name":"Houba",
    "wof:placetype":"locality"
},
  "geometry": {"coordinates":[103.733,31.2198],"type":"Point"}
}