{
  "type": "Feature",
  "properties": {
    "gn:admin1_code":"32.0",
    "gn:asciiname":"Jilong",
    "gn:country_code":"CN",
    "gn:dem":3208,
    "gn:feature_class":"P",
    "gn:feature_code":"PPL",
    "gn:name":"Jilong",
    "gn:population":0,
    "gn:timezone":"Asia/Shanghai",
    "iso:country":"CN",
    "name:zho_x_preferred":[
        "\u5409\u9f99"
    ],
    "wof:name":"Jilong",
    "wof:placetype":"locality"
},
  "geometry": {"coordinates":[100.327,31.0288],"type":"Point"}
}