{
  "type": "Feature",
  "properties": {
    "gn:admin1_code":"15.0",
    "gn:asciiname":"Tajiazhuang",
    "gn:country_code":"CN",
    "gn:dem":1887,
    "gn:feature_class":"P",
    "gn:feature_code":"PPL",
    "gn:name":"Tajiazhuang",
    "gn:population":0,
    "gn:timezone":"Asia/Shanghai",
    "iso:country":"CN",
    "name:zho_x_preferred":[
        "\u4ed6\u5bb6\u5e84"
    ],
    "wof:name":"Tajiazhuang",
    "wof:placetype":"locality"
},
  "geometry": {"coordinates":[102.754,37.6382],"type":"Point"}
}