{
  "type": "Feature",
  "properties": {
    "gn:admin1_code":"3.0",
    "gn:asciiname":"Yajiaoshu",
    "gn:country_code":"CN",
    "gn:dem":75,
    "gn:feature_class":"P",
    "gn:feature_code":"PPL",
    "gn:name":"Yajiaoshu",
    "gn:population":0,
    "gn:timezone":"Asia/Shanghai",
    "iso:country":"CN",
    "name:und_x_variant":[
        "\u9e2d\u811a\u6811"
    ],
    "wof:name":"Yajiaoshu",
    "wof:placetype":"locality"
},
  "geometry": {"coordinates":[116.71217,27.82754000000001],"type":"Point"}
}