{
  "type": "Feature",
  "properties": {
    "gn:admin1_code":"9.0",
    "gn:asciiname":"Gushigou",
    "gn:country_code":"CN",
    "gn:dem":478,
    "gn:feature_class":"P",
    "gn:feature_code":"PPL",
    "gn:name":"Gushigou",
    "gn:population":0,
    "gn:timezone":"Asia/Shanghai",
    "iso:country":"CN",
    "name:zho_x_preferred":[
        "\u53e4\u77f3\u6c9f"
    ],
    "wof:name":"Gushigou",
    "wof:placetype":"locality"
},
  "geometry": {"coordinates":[113.09108999999999,34.22509],"type":"Point"}
}