{
  "type": "Feature",
  "properties": {
    "gn:admin1_code":"14.0",
    "gn:asciiname":"Hangmuduo",
    "gn:country_code":"CN",
    "gn:dem":4209,
    "gn:feature_class":"P",
    "gn:feature_code":"PPL",
    "gn:name":"Hangmuduo",
    "gn:population":0,
    "gn:timezone":"Asia/Urumqi",
    "iso:country":"CN",
    "name:zho_x_preferred":[
        "\u822a\u6728\u591a"
    ],
    "wof:name":"Hangmuduo",
    "wof:placetype":"locality"
},
  "geometry": {"coordinates":[92.08247,29.71401],"type":"Point"}
}