{
  "type": "Feature",
  "properties": {
    "gn:admin1_code":"26.0",
    "gn:asciiname":"Fangzhaicun",
    "gn:country_code":"CN",
    "gn:dem":435,
    "gn:feature_class":"P",
    "gn:feature_code":"PPL",
    "gn:name":"Fangzhaicun",
    "gn:population":0,
    "gn:timezone":"Asia/Shanghai",
    "iso:country":"CN",
    "name:zho_x_preferred":[
        "\u65b9\u5be8\u6751"
    ],
    "wof:name":"Fangzhaicun",
    "wof:placetype":"locality"
},
  "geometry": {"coordinates":[108.16786,34.2361],"type":"Point"}
}