{
  "type": "Feature",
  "properties": {
    "gn:admin1_code":"11",
    "gn:asciiname":"Fuxiqiao",
    "gn:country_code":"CN",
    "gn:dem":244,
    "gn:feature_class":"P",
    "gn:feature_code":"PPL",
    "gn:name":"Fuxiqiao",
    "gn:population":0,
    "gn:timezone":"Asia/Shanghai",
    "iso:country":"CN",
    "name:zho_x_preferred":[
        "\u4f0f\u6eaa\u6865"
    ],
    "wof:name":"Fuxiqiao",
    "wof:placetype":"locality"
},
  "geometry": {"coordinates":[111.0855,27.02578],"type":"Point"}
}