{
  "type": "Feature",
  "properties": {
    "gn:admin1_code":"32.0",
    "gn:asciiname":"Wadituo",
    "gn:country_code":"CN",
    "gn:dem":2032,
    "gn:feature_class":"P",
    "gn:feature_code":"PPL",
    "gn:name":"Wadituo",
    "gn:population":0,
    "gn:timezone":"Asia/Shanghai",
    "iso:country":"CN",
    "name:zho_x_preferred":[
        "\u6d3c\u5730\u62d6"
    ],
    "wof:name":"Wadituo",
    "wof:placetype":"locality"
},
  "geometry": {"coordinates":[102.946,28.0439],"type":"Point"}
}