{
  "type": "Feature",
  "properties": {
    "gn:admin1_code":"15.0",
    "gn:asciiname":"Lanqiaozi",
    "gn:country_code":"CN",
    "gn:dem":1206,
    "gn:feature_class":"P",
    "gn:feature_code":"PPL",
    "gn:name":"Lanqiaozi",
    "gn:population":0,
    "gn:timezone":"Asia/Shanghai",
    "iso:country":"CN",
    "name:und_x_variant":[
        "\u680f\u6865\u5b50"
    ],
    "wof:name":"Lanqiaozi",
    "wof:placetype":"locality"
},
  "geometry": {"coordinates":[105.24503,32.99004],"type":"Point"}
}