{
  "type": "Feature",
  "properties": {
    "gn:admin1_code":"30",
    "gn:asciiname":"Yanqianlaocun",
    "gn:country_code":"CN",
    "gn:dem":49,
    "gn:feature_class":"P",
    "gn:feature_code":"PPL",
    "gn:name":"Yanqianlaocun",
    "gn:population":0,
    "gn:timezone":"Asia/Shanghai",
    "iso:country":"CN",
    "name:und_x_variant":[
        "Yanqian",
        "Yanqianlaocun"
    ],
    "name:zho_x_preferred":[
        "\u5ca9\u524d\u8001\u6751"
    ],
    "wof:name":"Yanqianlaocun",
    "wof:placetype":"locality"
},
  "geometry": {"coordinates":[116.50485999999999,23.32649],"type":"Point"}
}