{
  "type": "Feature",
  "properties": {
    "gn:admin1_code":"33.0",
    "gn:asciiname":"Yangliugou",
    "gn:country_code":"CN",
    "gn:dem":530,
    "gn:feature_class":"P",
    "gn:feature_code":"PPL",
    "gn:name":"Yangliugou",
    "gn:population":0,
    "gn:timezone":"Asia/Shanghai",
    "iso:country":"CN",
    "name:zho_x_preferred":[
        "\u6768\u67f3\u6c9f"
    ],
    "wof:name":"Yangliugou",
    "wof:placetype":"locality"
},
  "geometry": {"coordinates":[106.69499999999999,28.7374],"type":"Point"}
}