{
  "type": "Feature",
  "properties": {
    "gn:admin1_code":"4.0",
    "gn:asciiname":"Lizhazhuang",
    "gn:country_code":"CN",
    "gn:dem":6,
    "gn:feature_class":"P",
    "gn:feature_code":"PPL",
    "gn:name":"Lizhazhuang",
    "gn:population":0,
    "gn:timezone":"Asia/Shanghai",
    "iso:country":"CN",
    "name:zho_x_preferred":[
        "Lizhazhuang"
    ],
    "name:zho_x_variant":[
        "\u674e\u95f8\u5e84"
    ],
    "wof:name":"Lizhazhuang",
    "wof:placetype":"locality"
},
  "geometry": {"coordinates":[119.20099,33.47028],"type":"Point"}
}