{
  "type": "Feature",
  "properties": {
    "gn:admin1_code":"15.0",
    "gn:asciiname":"Laorenshan",
    "gn:country_code":"CN",
    "gn:dem":1559,
    "gn:feature_class":"P",
    "gn:feature_code":"PPL",
    "gn:name":"Laorenshan",
    "gn:population":0,
    "gn:timezone":"Asia/Shanghai",
    "iso:country":"CN",
    "name:und_x_variant":[
        "\u8001\u4eba\u5c71"
    ],
    "wof:name":"Laorenshan",
    "wof:placetype":"locality"
},
  "geometry": {"coordinates":[105.5728,34.04265],"type":"Point"}
}