{
  "type": "Feature",
  "properties": {
    "gn:admin1_code":"29.0",
    "gn:asciiname":"Baileba",
    "gn:country_code":"CN",
    "gn:dem":1819,
    "gn:feature_class":"P",
    "gn:feature_code":"PPL",
    "gn:name":"Baileba",
    "gn:population":0,
    "gn:timezone":"Asia/Shanghai",
    "iso:country":"CN",
    "name:zho_x_preferred":[
        "\u767e\u4e50\u575d"
    ],
    "wof:name":"Baileba",
    "wof:placetype":"locality"
},
  "geometry": {"coordinates":[103.694,24.6463],"type":"Point"}
}