{
  "type": "Feature",
  "properties": {
    "gn:admin1_code":"1.0",
    "gn:asciiname":"Shaodayingcun",
    "gn:country_code":"CN",
    "gn:dem":31,
    "gn:feature_class":"P",
    "gn:feature_code":"PPL",
    "gn:name":"Shaodayingcun",
    "gn:population":0,
    "gn:timezone":"Asia/Shanghai",
    "iso:country":"CN",
    "name:zho_x_preferred":[
        "\u90b5\u5927\u90e2\u6751"
    ],
    "wof:name":"Shaodayingcun",
    "wof:placetype":"locality"
},
  "geometry": {"coordinates":[117.27376,31.93005],"type":"Point"}
}