{
  "type": "Feature",
  "properties": {
    "gn:admin1_code":"5.0",
    "gn:asciiname":"Jiangdianzi",
    "gn:country_code":"CN",
    "gn:dem":332,
    "gn:feature_class":"P",
    "gn:feature_code":"PPLA4",
    "gn:name":"Jiangdianzi",
    "gn:population":0,
    "gn:timezone":"Asia/Shanghai",
    "iso:country":"CN",
    "name:und_x_variant":[
        "\u6c5f\u7538\u5b50",
        "Jiangdian Zhen",
        "\u6c5f\u7538\u9547"
    ],
    "wof:name":"Jiangdianzi",
    "wof:placetype":"locality"
},
  "geometry": {"coordinates":[125.71319,41.46895],"type":"Point"}
}