{
  "type": "Feature",
  "properties": {
    "gn:admin1_code":"30",
    "gn:asciiname":"Huangzhugen",
    "gn:country_code":"CN",
    "gn:dem":223,
    "gn:feature_class":"P",
    "gn:feature_code":"PPL",
    "gn:name":"Huangzhugen",
    "gn:population":0,
    "gn:timezone":"Asia/Urumqi",
    "iso:country":"CN",
    "name:zho_x_preferred":[
        "\u9ec4\u7af9\u6839"
    ],
    "wof:name":"Huangzhugen",
    "wof:placetype":"locality"
},
  "geometry": {"coordinates":[111.20261000000001,21.95023],"type":"Point"}
}