{
  "type": "Feature",
  "properties": {
    "gn:admin1_code":"23.0",
    "gn:asciiname":"Yinglongmiao",
    "gn:country_code":"CN",
    "gn:dem":4,
    "gn:feature_class":"P",
    "gn:feature_code":"PPL",
    "gn:name":"Yinglongmiao",
    "gn:population":0,
    "gn:timezone":"Asia/Shanghai",
    "iso:country":"CN",
    "name:und_x_variant":[
        "\u8fce\u9f99\u5e99"
    ],
    "wof:name":"Yinglongmiao",
    "wof:placetype":"locality"
},
  "geometry": {"coordinates":[121.39806000000002,30.84144],"type":"Point"}
}