{
  "type": "Feature",
  "properties": {
    "gn:admin1_code":"1.0",
    "gn:asciiname":"Gaozhuangcun",
    "gn:country_code":"CN",
    "gn:dem":33,
    "gn:feature_class":"P",
    "gn:feature_code":"PPL",
    "gn:name":"Gaozhuangcun",
    "gn:population":0,
    "gn:timezone":"Asia/Shanghai",
    "iso:country":"CN",
    "name:und_x_variant":[
        "Gaozhuang"
    ],
    "name:zho_x_preferred":[
        "\u9ad8\u5e84\u6751"
    ],
    "wof:name":"Gaozhuangcun",
    "wof:placetype":"locality"
},
  "geometry": {"coordinates":[115.55829,32.7901],"type":"Point"}
}