{
  "type": "Feature",
  "properties": {
    "gn:admin1_code":"32.0",
    "gn:asciiname":"Chenkang",
    "gn:country_code":"CN",
    "gn:dem":500,
    "gn:feature_class":"P",
    "gn:feature_code":"PPL",
    "gn:name":"Chenkang",
    "gn:population":0,
    "gn:timezone":"Asia/Shanghai",
    "iso:country":"CN",
    "name:zho_x_preferred":[
        "\u6c89\u6297"
    ],
    "wof:name":"Chenkang",
    "wof:placetype":"locality"
},
  "geometry": {"coordinates":[104.85478999999999,31.53],"type":"Point"}
}