{
  "type": "Feature",
  "properties": {
    "gn:admin1_code":"14.0",
    "gn:asciiname":"Jiuwa",
    "gn:country_code":"CN",
    "gn:dem":4456,
    "gn:feature_class":"P",
    "gn:feature_code":"PPL",
    "gn:name":"Jiuwa",
    "gn:population":0,
    "gn:timezone":"Asia/Urumqi",
    "iso:country":"CN",
    "name:zho_x_preferred":[
        "\u4e45\u5a03"
    ],
    "wof:name":"Jiuwa",
    "wof:placetype":"locality"
},
  "geometry": {"coordinates":[88.0043,29.2011],"type":"Point"}
}