{
  "type": "Feature",
  "properties": {
    "gn:admin1_code":"30",
    "gn:asciiname":"Waisha",
    "gn:country_code":"CN",
    "gn:dem":12,
    "gn:feature_class":"P",
    "gn:feature_code":"PPLA4",
    "gn:name":"Waisha",
    "gn:population":0,
    "gn:timezone":"Asia/Shanghai",
    "iso:country":"CN",
    "name:und_x_variant":[
        "Waisha Zhen",
        "\u5916\u7802\u9547"
    ],
    "name:zho_x_preferred":[
        "\u5916\u7802"
    ],
    "wof:name":"Waisha",
    "wof:placetype":"locality"
},
  "geometry": {"coordinates":[116.74974,23.43495],"type":"Point"}
}