{
  "type": "Feature",
  "properties": {
    "gn:admin1_code":"9.0",
    "gn:asciiname":"Muzhai",
    "gn:country_code":"CN",
    "gn:dem":68,
    "gn:feature_class":"P",
    "gn:feature_code":"PPL",
    "gn:name":"Muzhai",
    "gn:population":0,
    "gn:timezone":"Asia/Shanghai",
    "iso:country":"CN",
    "name:zho_x_preferred":[
        "\u6155\u5be8"
    ],
    "wof:name":"Muzhai",
    "wof:placetype":"locality"
},
  "geometry": {"coordinates":[114.24417,34.18277],"type":"Point"}
}