{
  "type": "Feature",
  "properties": {
    "gn:admin1_code":"30.0",
    "gn:asciiname":"Jiuwei",
    "gn:country_code":"CN",
    "gn:dem":528,
    "gn:feature_class":"P",
    "gn:feature_code":"PPL",
    "gn:name":"Jiuwei",
    "gn:population":0,
    "gn:timezone":"Asia/Shanghai",
    "iso:country":"CN",
    "name:zho_x_preferred":[
        "Jiuwei"
    ],
    "name:zho_x_variant":[
        "\u65e7\u56f4"
    ],
    "wof:name":"Jiuwei",
    "wof:placetype":"locality"
},
  "geometry": {"coordinates":[112.47944,24.36444],"type":"Point"}
}