{
  "type": "Feature",
  "properties": {
    "gn:admin1_code":"12",
    "gn:asciiname":"Anjia",
    "gn:country_code":"CN",
    "gn:dem":393,
    "gn:feature_class":"P",
    "gn:feature_code":"PPLA4",
    "gn:name":"Anjia",
    "gn:population":0,
    "gn:timezone":"Asia/Shanghai",
    "iso:country":"CN",
    "name:und_x_variant":[
        "Anjia Xiang"
    ],
    "name:zho_x_preferred":[
        "\u5b89\u5bb6"
    ],
    "name:zho_x_variant":[
        "\u5b89\u5bb6\u4e61"
    ],
    "wof:name":"Anjia",
    "wof:placetype":"locality"
},
  "geometry": {"coordinates":[110.50754999999999,33.0104],"type":"Point"}
}