{
  "type": "Feature",
  "properties": {
    "gn:admin1_code":"18.0",
    "gn:asciiname":"Baiyun",
    "gn:country_code":"CN",
    "gn:dem":1120,
    "gn:feature_class":"P",
    "gn:feature_code":"PPL",
    "gn:name":"Baiyun",
    "gn:population":0,
    "gn:timezone":"Asia/Shanghai",
    "iso:country":"CN",
    "name:ceb_x_preferred":[
        "Baiyun"
    ],
    "name:deu_x_preferred":[
        "Baiyun"
    ],
    "name:eus_x_preferred":[
        "Baiyun barrutia"
    ],
    "name:fra_x_preferred":[
        "Baiyun"
    ],
    "name:jpn_x_preferred":[
        "\u767d\u96f2\u533a"
    ],
    "name:kor_x_preferred":[
        "\ubc14\uc774\uc708\uad6c"
    ],
    "name:nor_x_preferred":[
        "Baiyun"
    ],
    "name:swe_x_preferred":[
        "Baiyun"
    ],
    "name:zho_x_preferred":[
        "\u767d\u4e91\u533a"
    ],
    "wof:name":"Baiyun",
    "wof:placetype":"locality"
},
  "geometry": {"coordinates":[106.03333000000001,25.78333],"type":"Point"}
}