{
  "type": "Feature",
  "properties": {
    "gn:admin1_code":"6.0",
    "gn:asciiname":"Sailisi",
    "gn:country_code":"CN",
    "gn:dem":2960,
    "gn:feature_class":"P",
    "gn:feature_code":"PPL",
    "gn:name":"Sailisi",
    "gn:population":0,
    "gn:timezone":"Asia/Shanghai",
    "iso:country":"CN",
    "name:zho_x_preferred":[
        "\u8d5b\u529b\u5bfa"
    ],
    "wof:name":"Sailisi",
    "wof:placetype":"locality"
},
  "geometry": {"coordinates":[101.79788000000001,36.06237],"type":"Point"}
}