{
  "type": "Feature",
  "properties": {
    "gn:admin1_code":"3.0",
    "gn:asciiname":"Zuzishan",
    "gn:country_code":"CN",
    "gn:dem":16,
    "gn:feature_class":"P",
    "gn:feature_code":"PPL",
    "gn:name":"Zuzishan",
    "gn:population":0,
    "gn:timezone":"Asia/Shanghai",
    "iso:country":"CN",
    "name:und_x_variant":[
        "\u5352\u5b50\u5c71"
    ],
    "wof:name":"Zuzishan",
    "wof:placetype":"locality"
},
  "geometry": {"coordinates":[116.60823000000001,29.30657],"type":"Point"}
}