{
  "type": "Feature",
  "properties": {
    "gn:admin1_code":"07",
    "gn:asciiname":"Muping",
    "gn:country_code":"CN",
    "gn:dem":625,
    "gn:feature_class":"P",
    "gn:feature_code":"PPL",
    "gn:name":"Muping",
    "gn:population":0,
    "gn:timezone":"Asia/Shanghai",
    "iso:country":"CN",
    "name:zho_x_preferred":[
        "\u7766\u576a"
    ],
    "wof:name":"Muping",
    "wof:placetype":"locality"
},
  "geometry": {"coordinates":[117.74827999999999,25.65094],"type":"Point"}
}