{
  "type": "Feature",
  "properties": {
    "gn:admin1_code":"19.0",
    "gn:asciiname":"Datianjiatun",
    "gn:country_code":"CN",
    "gn:dem":117,
    "gn:feature_class":"P",
    "gn:feature_code":"PPL",
    "gn:name":"Datianjiatun",
    "gn:population":0,
    "gn:timezone":"Asia/Shanghai",
    "iso:country":"CN",
    "name:und_x_variant":[
        "\u5927\u7530\u5bb6\u5c6f"
    ],
    "name:zho_x_preferred":[
        "\u5927\u7530\u5bb6\u5c6f"
    ],
    "wof:name":"Datianjiatun",
    "wof:placetype":"locality"
},
  "geometry": {"coordinates":[123.73033,41.64705],"type":"Point"}
}