{
  "type": "Feature",
  "properties": {
    "gn:admin1_code":"32.0",
    "gn:asciiname":"Galan",
    "gn:country_code":"CN",
    "gn:dem":3051,
    "gn:feature_class":"P",
    "gn:feature_code":"PPL",
    "gn:name":"Galan",
    "gn:population":0,
    "gn:timezone":"Asia/Shanghai",
    "iso:country":"CN",
    "name:zho_x_preferred":[
        "\u5c15\u5170"
    ],
    "wof:name":"Galan",
    "wof:placetype":"locality"
},
  "geometry": {"coordinates":[102.08799999999999,31.6628],"type":"Point"}
}