{
  "type": "Feature",
  "properties": {
    "gn:admin1_code":"32.0",
    "gn:asciiname":"Galan",
    "gn:country_code":"CN",
    "gn:dem":3051,
    "gn:feature_class":"P",
    "gn:feature_code":"PPL",
    "gn:name":"Galan",
    "gn:population":0,
    "gn:timezone":"Asia/Shanghai",
    "iso:country":"CN",
    "name:ceb_x_preferred":[
        "Galan"
    ],
    "name:deu_x_preferred":[
        "Galan"
    ],
    "name:fas_x_preferred":[
        "\u06af\u0644\u0627\u0646"
    ],
    "name:fra_x_preferred":[
        "Galan"
    ],
    "name:ita_x_preferred":[
        "Galan"
    ],
    "name:nld_x_preferred":[
        "Galan"
    ],
    "name:swe_x_preferred":[
        "Galan"
    ],
    "name:ukr_x_preferred":[
        "\u0413\u0430\u043b\u0430\u043d"
    ],
    "name:zho_x_preferred":[
        "\u5c15\u5170"
    ],
    "wof:name":"Galan",
    "wof:placetype":"locality"
},
  "geometry": {"coordinates":[102.08799999999999,31.6628],"type":"Point"}
}