{
  "type": "Feature",
  "properties": {
    "gn:admin1_code":"30.0",
    "gn:asciiname":"Shanwei Xincun",
    "gn:country_code":"CN",
    "gn:dem":34,
    "gn:feature_class":"P",
    "gn:feature_code":"PPL",
    "gn:name":"Shanwei Xincun",
    "gn:population":0,
    "gn:timezone":"Asia/Shanghai",
    "iso:country":"CN",
    "name:zho_x_preferred":[
        "\u5c71\u5c3e\u65b0\u6751"
    ],
    "wof:name":"Shanwei Xincun",
    "wof:placetype":"locality"
},
  "geometry": {"coordinates":[116.24827999999999,23.34868],"type":"Point"}
}