{
  "type": "Feature",
  "properties": {
    "gn:admin1_code":"15.0",
    "gn:asciiname":"Huoshaozhai",
    "gn:country_code":"CN",
    "gn:dem":1716,
    "gn:feature_class":"P",
    "gn:feature_code":"PPL",
    "gn:name":"Huoshaozhai",
    "gn:population":0,
    "gn:timezone":"Asia/Shanghai",
    "iso:country":"CN",
    "name:zho_x_preferred":[
        "\u706b\u70e7\u5be8"
    ],
    "wof:name":"Huoshaozhai",
    "wof:placetype":"locality"
},
  "geometry": {"coordinates":[105.486,34.1347],"type":"Point"}
}