{
  "type": "Feature",
  "properties": {
    "gn:admin1_code":"9",
    "gn:asciiname":"Zhangshiqiao",
    "gn:country_code":"CN",
    "gn:dem":47,
    "gn:feature_class":"P",
    "gn:feature_code":"PPL",
    "gn:name":"Zhangshiqiao",
    "gn:population":0,
    "gn:timezone":"Asia/Shanghai",
    "iso:country":"CN",
    "name:zho_x_preferred":[
        "\u5f20\u77f3\u6865"
    ],
    "wof:name":"Zhangshiqiao",
    "wof:placetype":"locality"
},
  "geometry": {"coordinates":[114.934,33.762],"type":"Point"}
}