{
  "type": "Feature",
  "properties": {
    "gn:admin1_code":"26.0",
    "gn:asciiname":"Wuwangmiao",
    "gn:country_code":"CN",
    "gn:dem":499,
    "gn:feature_class":"P",
    "gn:feature_code":"PPL",
    "gn:name":"Wuwangmiao",
    "gn:population":0,
    "gn:timezone":"Asia/Shanghai",
    "iso:country":"CN",
    "name:zho_x_preferred":[
        "\u6b66\u738b\u5e99"
    ],
    "wof:name":"Wuwangmiao",
    "wof:placetype":"locality"
},
  "geometry": {"coordinates":[109.61063,32.81912],"type":"Point"}
}