{
  "type": "Feature",
  "properties": {
    "gn:admin1_code":"25",
    "gn:asciiname":"Nansu",
    "gn:country_code":"CN",
    "gn:dem":40,
    "gn:feature_class":"P",
    "gn:feature_code":"PPL",
    "gn:name":"Nansu",
    "gn:population":0,
    "gn:timezone":"Asia/Shanghai",
    "iso:country":"CN",
    "name:zho_x_preferred":[
        "\u5357\u82cf"
    ],
    "wof:name":"Nansu",
    "wof:placetype":"locality"
},
  "geometry": {"coordinates":[116.73099999999999,35.2928],"type":"Point"}
}