{
  "type": "Feature",
  "properties": {
    "gn:admin1_code":"21.0",
    "gn:asciiname":"Yanjiwan",
    "gn:country_code":"CN",
    "gn:dem":1330,
    "gn:feature_class":"P",
    "gn:feature_code":"PPL",
    "gn:name":"Yanjiwan",
    "gn:population":0,
    "gn:timezone":"Asia/Shanghai",
    "iso:country":"CN",
    "name:zho_x_preferred":[
        "\u4e25\u8bb0\u6e7e"
    ],
    "wof:name":"Yanjiwan",
    "wof:placetype":"locality"
},
  "geometry": {"coordinates":[107.45,37.7872],"type":"Point"}
}