{
  "type": "Feature",
  "properties": {
    "gn:admin1_code":"11",
    "gn:asciiname":"Tangluo",
    "gn:country_code":"CN",
    "gn:dem":230,
    "gn:feature_class":"P",
    "gn:feature_code":"PPL",
    "gn:name":"Tangluo",
    "gn:population":0,
    "gn:timezone":"Asia/Shanghai",
    "iso:country":"CN",
    "name:und_x_variant":[
        "\u5858\u7f57",
        "Tangluo"
    ],
    "wof:name":"Tangluo",
    "wof:placetype":"locality"
},
  "geometry": {"coordinates":[112.26917,25.74444],"type":"Point"}
}