{
  "type": "Feature",
  "properties": {
    "gn:admin1_code":"18",
    "gn:asciiname":"Guanzhai",
    "gn:country_code":"CN",
    "gn:dem":1660,
    "gn:feature_class":"P",
    "gn:feature_code":"PPL",
    "gn:name":"Guanzhai",
    "gn:population":0,
    "gn:timezone":"Asia/Shanghai",
    "iso:country":"CN",
    "name:zho_x_preferred":[
        "\u5173\u5be8"
    ],
    "wof:name":"Guanzhai",
    "wof:placetype":"locality"
},
  "geometry": {"coordinates":[104.849,27.0739],"type":"Point"}
}