{
  "type": "Feature",
  "properties": {
    "gn:admin1_code":"7",
    "gn:asciiname":"Shanxiji",
    "gn:country_code":"CN",
    "gn:dem":446,
    "gn:feature_class":"P",
    "gn:feature_code":"PPL",
    "gn:name":"Shanxiji",
    "gn:population":0,
    "gn:timezone":"Asia/Shanghai",
    "iso:country":"CN",
    "wof:name":"Shanxiji",
    "wof:placetype":"locality"
},
  "geometry": {"coordinates":[117.88028,27.17694],"type":"Point"}
}