{
  "type": "Feature",
  "properties": {
    "gn:admin1_code":"22.0",
    "gn:asciiname":"Taihoucun",
    "gn:country_code":"CN",
    "gn:dem":164,
    "gn:feature_class":"P",
    "gn:feature_code":"PPL",
    "gn:name":"Taihoucun",
    "gn:population":0,
    "gn:timezone":"Asia/Shanghai",
    "iso:country":"CN",
    "name:zho_x_preferred":[
        "\u592a\u540e\u6751"
    ],
    "wof:name":"Taihoucun",
    "wof:placetype":"locality"
},
  "geometry": {"coordinates":[117.10807,40.22236],"type":"Point"}
}