{
  "type": "Feature",
  "properties": {
    "gn:admin1_code":"29.0",
    "gn:asciiname":"Tuandingkou",
    "gn:country_code":"CN",
    "gn:dem":1842,
    "gn:feature_class":"P",
    "gn:feature_code":"PPL",
    "gn:name":"Tuandingkou",
    "gn:population":0,
    "gn:timezone":"Asia/Shanghai",
    "iso:country":"CN",
    "name:zho_x_preferred":[
        "\u56e2\u5b9a\u53e3"
    ],
    "wof:name":"Tuandingkou",
    "wof:placetype":"locality"
},
  "geometry": {"coordinates":[104.60899999999999,27.5151],"type":"Point"}
}