{
  "type": "Feature",
  "properties": {
    "gn:admin1_code":"16",
    "gn:asciiname":"Niujiaoshan",
    "gn:country_code":"CN",
    "gn:dem":202,
    "gn:feature_class":"P",
    "gn:feature_code":"PPL",
    "gn:name":"Niujiaoshan",
    "gn:population":0,
    "gn:timezone":"Asia/Shanghai",
    "iso:country":"CN",
    "name:zho_x_preferred":[
        "\u725b\u89d2\u5c71"
    ],
    "wof:name":"Niujiaoshan",
    "wof:placetype":"locality"
},
  "geometry": {"coordinates":[110.887,24.9181],"type":"Point"}
}