{
  "type": "Feature",
  "properties": {
    "gn:admin1_code":"18",
    "gn:asciiname":"Yangmao",
    "gn:country_code":"CN",
    "gn:dem":1469,
    "gn:feature_class":"P",
    "gn:feature_code":"PPL",
    "gn:name":"Yangmao",
    "gn:population":0,
    "gn:timezone":"Asia/Shanghai",
    "iso:country":"CN",
    "name:zho_x_preferred":[
        "\u9633\u8302"
    ],
    "wof:name":"Yangmao",
    "wof:placetype":"locality"
},
  "geometry": {"coordinates":[105.535,25.1238],"type":"Point"}
}