{
  "type": "Feature",
  "properties": {
    "gn:admin1_code":"12.0",
    "gn:asciiname":"Taibaihu",
    "gn:country_code":"CN",
    "gn:dem":14,
    "gn:feature_class":"P",
    "gn:feature_code":"PPL",
    "gn:name":"Taibaihu",
    "gn:population":0,
    "gn:timezone":"Asia/Shanghai",
    "iso:country":"CN",
    "name:zho_x_preferred":[
        "\u592a\u767d\u6e56"
    ],
    "wof:name":"Taibaihu",
    "wof:placetype":"locality"
},
  "geometry": {"coordinates":[115.76148000000001,29.92645],"type":"Point"}
}