{
  "type": "Feature",
  "properties": {
    "gn:admin1_code":"32.0",
    "gn:asciiname":"Wukuaishi",
    "gn:country_code":"CN",
    "gn:dem":403,
    "gn:feature_class":"P",
    "gn:feature_code":"PPL",
    "gn:name":"Wukuaishi",
    "gn:population":0,
    "gn:timezone":"Asia/Shanghai",
    "iso:country":"CN",
    "name:zho_x_preferred":[
        "\u4e94\u5757\u77f3"
    ],
    "wof:name":"Wukuaishi",
    "wof:placetype":"locality"
},
  "geometry": {"coordinates":[104.70699999999999,29.9271],"type":"Point"}
}