{
  "type": "Feature",
  "properties": {
    "gn:admin1_code":"02",
    "gn:asciiname":"Kongtou",
    "gn:country_code":"CN",
    "gn:dem":28,
    "gn:feature_class":"P",
    "gn:feature_code":"PPL",
    "gn:name":"Kongtou",
    "gn:population":0,
    "gn:timezone":"Asia/Shanghai",
    "iso:country":"CN",
    "name:und_x_variant":[
        "K\u2019ung-t\u2019ou",
        "Kongtou"
    ],
    "wof:name":"Kongtou",
    "wof:placetype":"locality"
},
  "geometry": {"coordinates":[121.17167999999999,28.23658],"type":"Point"}
}