{
  "type": "Feature",
  "properties": {
    "gn:admin1_code":"31.0",
    "gn:asciiname":"Renlong",
    "gn:country_code":"CN",
    "gn:dem":794,
    "gn:feature_class":"P",
    "gn:feature_code":"PPL",
    "gn:name":"Renlong",
    "gn:population":0,
    "gn:timezone":"Asia/Shanghai",
    "iso:country":"CN",
    "name:zho_x_preferred":[
        "\u4ec1\u9f99"
    ],
    "wof:name":"Renlong",
    "wof:placetype":"locality"
},
  "geometry": {"coordinates":[109.46704,18.98427],"type":"Point"}
}