{
  "type": "Feature",
  "properties": {
    "gn:admin1_code":"4.0",
    "gn:asciiname":"Xichengzhang",
    "gn:country_code":"CN",
    "gn:dem":2,
    "gn:feature_class":"P",
    "gn:feature_code":"PPL",
    "gn:name":"Xichengzhang",
    "gn:population":0,
    "gn:timezone":"Asia/Shanghai",
    "iso:country":"CN",
    "name:zho_x_preferred":[
        "\u897f\u6210\u7ae0"
    ],
    "wof:name":"Xichengzhang",
    "wof:placetype":"locality"
},
  "geometry": {"coordinates":[120.24077,33.02885],"type":"Point"}
}