{
  "type": "Feature",
  "properties": {
    "gn:admin1_code":"16.0",
    "gn:asciiname":"Malong",
    "gn:country_code":"CN",
    "gn:dem":616,
    "gn:feature_class":"P",
    "gn:feature_code":"PPL",
    "gn:name":"Malong",
    "gn:population":0,
    "gn:timezone":"Asia/Shanghai",
    "iso:country":"CN",
    "name:zho_x_preferred":[
        "\u5988\u9647"
    ],
    "wof:name":"Malong",
    "wof:placetype":"locality"
},
  "geometry": {"coordinates":[105.44799999999999,24.7795],"type":"Point"}
}