{
  "type": "Feature",
  "properties": {
    "gn:admin1_code":"10.0",
    "gn:asciiname":"Dangjiashan",
    "gn:country_code":"CN",
    "gn:dem":58,
    "gn:feature_class":"P",
    "gn:feature_code":"PPL",
    "gn:name":"Dangjiashan",
    "gn:population":0,
    "gn:timezone":"Asia/Shanghai",
    "iso:country":"CN",
    "name:zho_x_preferred":[
        "\u515a\u5bb6\u5c71"
    ],
    "wof:name":"Dangjiashan",
    "wof:placetype":"locality"
},
  "geometry": {"coordinates":[118.12143,39.95778],"type":"Point"}
}