{
  "type": "Feature",
  "properties": {
    "gn:admin1_code":"15.0",
    "gn:asciiname":"Zhaikenao",
    "gn:country_code":"CN",
    "gn:dem":1964,
    "gn:feature_class":"P",
    "gn:feature_code":"PPL",
    "gn:name":"Zhaikenao",
    "gn:population":0,
    "gn:timezone":"Asia/Shanghai",
    "iso:country":"CN",
    "name:zho_x_preferred":[
        "\u5be8\u79d1\u8111"
    ],
    "wof:name":"Zhaikenao",
    "wof:placetype":"locality"
},
  "geometry": {"coordinates":[105.34,36.0635],"type":"Point"}
}