{
  "type": "Feature",
  "properties": {
    "gn:admin1_code":"15.0",
    "gn:asciiname":"Shangchuan",
    "gn:country_code":"CN",
    "gn:dem":2196,
    "gn:feature_class":"P",
    "gn:feature_code":"PPL",
    "gn:name":"Shangchuan",
    "gn:population":0,
    "gn:timezone":"Asia/Shanghai",
    "iso:country":"CN",
    "name:zho_x_preferred":[
        "\u4e0a\u5ddd"
    ],
    "wof:name":"Shangchuan",
    "wof:placetype":"locality"
},
  "geometry": {"coordinates":[104.43300000000001,35.2764],"type":"Point"}
}