{
  "type": "Feature",
  "properties": {
    "gn:admin1_code":"29.0",
    "gn:asciiname":"Wangjiacun",
    "gn:country_code":"CN",
    "gn:dem":1834,
    "gn:feature_class":"P",
    "gn:feature_code":"PPL",
    "gn:name":"Wangjiacun",
    "gn:population":0,
    "gn:timezone":"Asia/Shanghai",
    "iso:country":"CN",
    "name:zho_x_preferred":[
        "\u738b\u5bb6\u6751"
    ],
    "wof:name":"Wangjiacun",
    "wof:placetype":"locality"
},
  "geometry": {"coordinates":[101.92400000000001,25.2512],"type":"Point"}
}