{
  "type": "Feature",
  "properties": {
    "gn:admin1_code":"12.0",
    "gn:asciiname":"Duandian",
    "gn:country_code":"CN",
    "gn:dem":31,
    "gn:feature_class":"P",
    "gn:feature_code":"PPL",
    "gn:name":"Duandian",
    "gn:population":0,
    "gn:timezone":"Asia/Shanghai",
    "iso:country":"CN",
    "name:und_x_variant":[
        "\u6bb5\u5e97"
    ],
    "wof:name":"Duandian",
    "wof:placetype":"locality"
},
  "geometry": {"coordinates":[114.59877,30.60521],"type":"Point"}
}