{
  "type": "Feature",
  "properties": {
    "gn:admin1_code":"4.0",
    "gn:asciiname":"Liuji",
    "gn:country_code":"CN",
    "gn:dem":8,
    "gn:feature_class":"P",
    "gn:feature_code":"PPL",
    "gn:name":"Liuji",
    "gn:population":0,
    "gn:timezone":"Asia/Shanghai",
    "iso:country":"CN",
    "name:ceb_x_preferred":[
        "Liuji"
    ],
    "name:deu_x_preferred":[
        "Liuji"
    ],
    "name:swe_x_preferred":[
        "Liuji"
    ],
    "name:zho_x_preferred":[
        "Liuji"
    ],
    "name:zho_x_variant":[
        "\u5218\u96c6"
    ],
    "wof:name":"Liuji",
    "wof:placetype":"locality"
},
  "geometry": {"coordinates":[119.00095,33.34789],"type":"Point"}
}