{
  "type": "Feature",
  "properties": {
    "gn:admin1_code":"9.0",
    "gn:asciiname":"Shiyuanqiang",
    "gn:country_code":"CN",
    "gn:dem":147,
    "gn:feature_class":"P",
    "gn:feature_code":"PPL",
    "gn:name":"Shiyuanqiang",
    "gn:population":0,
    "gn:timezone":"Asia/Shanghai",
    "iso:country":"CN",
    "name:und_x_variant":[
        "\u77f3\u9662\u5899"
    ],
    "name:zho_x_preferred":[
        "\u77f3\u9662\u5899"
    ],
    "wof:name":"Shiyuanqiang",
    "wof:placetype":"locality"
},
  "geometry": {"coordinates":[113.00183,33.84386],"type":"Point"}
}