{
  "type": "Feature",
  "properties": {
    "gn:admin1_code":"29",
    "gn:asciiname":"Xianajia",
    "gn:country_code":"CN",
    "gn:dem":1699,
    "gn:feature_class":"P",
    "gn:feature_code":"PPL",
    "gn:name":"Xianajia",
    "gn:population":0,
    "gn:timezone":"Asia/Shanghai",
    "iso:country":"CN",
    "name:zho_x_preferred":[
        "\u4e0b\u90a3\u621b"
    ],
    "wof:name":"Xianajia",
    "wof:placetype":"locality"
},
  "geometry": {"coordinates":[101.971,23.5017],"type":"Point"}
}