{
  "type": "Feature",
  "properties": {
    "gn:admin1_code":"32.0",
    "gn:asciiname":"Bengzhe",
    "gn:country_code":"CN",
    "gn:dem":4086,
    "gn:feature_class":"P",
    "gn:feature_code":"PPL",
    "gn:name":"Bengzhe",
    "gn:population":0,
    "gn:timezone":"Asia/Shanghai",
    "iso:country":"CN",
    "name:zho_x_preferred":[
        "\u5d29\u6298"
    ],
    "wof:name":"Bengzhe",
    "wof:placetype":"locality"
},
  "geometry": {"coordinates":[98.28189,32.21869],"type":"Point"}
}