{
  "type": "Feature",
  "properties": {
    "gn:admin1_code":"32.0",
    "gn:asciiname":"Wangjia Pingzi",
    "gn:country_code":"CN",
    "gn:dem":1889,
    "gn:feature_class":"P",
    "gn:feature_code":"PPL",
    "gn:name":"Wangjia Pingzi",
    "gn:population":0,
    "gn:timezone":"Asia/Shanghai",
    "iso:country":"CN",
    "name:zho_x_preferred":[
        "\u738b\u5bb6\u576a\u5b50"
    ],
    "wof:name":"Wangjia Pingzi",
    "wof:placetype":"locality"
},
  "geometry": {"coordinates":[102.274,27.5125],"type":"Point"}
}