{
  "type": "Feature",
  "properties": {
    "gn:admin1_code":"25.0",
    "gn:asciiname":"Jingangkoucun",
    "gn:country_code":"CN",
    "gn:dem":62,
    "gn:feature_class":"P",
    "gn:feature_code":"PPL",
    "gn:name":"Jingangkoucun",
    "gn:population":0,
    "gn:timezone":"Asia/Shanghai",
    "iso:country":"CN",
    "name:zho_x_preferred":[
        "\u91d1\u5c97\u53e3\u6751"
    ],
    "wof:name":"Jingangkoucun",
    "wof:placetype":"locality"
},
  "geometry": {"coordinates":[120.65589,36.88079000000001],"type":"Point"}
}