{
  "type": "Feature",
  "properties": {
    "gn:admin1_code":"5.0",
    "gn:asciiname":"Xigaojia",
    "gn:country_code":"CN",
    "gn:dem":763,
    "gn:feature_class":"P",
    "gn:feature_code":"PPL",
    "gn:name":"Xigaojia",
    "gn:population":0,
    "gn:timezone":"Asia/Shanghai",
    "iso:country":"CN",
    "name:und_x_variant":[
        "\u897f\u9ad8\u5bb6"
    ],
    "wof:name":"Xigaojia",
    "wof:placetype":"locality"
},
  "geometry": {"coordinates":[127.00454000000001,41.78132],"type":"Point"}
}