{
  "type": "Feature",
  "properties": {
    "gn:admin1_code":"14.0",
    "gn:asciiname":"Bang'a",
    "gn:country_code":"CN",
    "gn:dem":3628,
    "gn:feature_class":"P",
    "gn:feature_code":"PPL",
    "gn:name":"Bang\u2019a",
    "gn:population":0,
    "gn:timezone":"Asia/Urumqi",
    "iso:country":"CN",
    "name:und_x_variant":[
        "Bang\u2019a"
    ],
    "name:zho_x_preferred":[
        "\u5e2e\u963f"
    ],
    "wof:name":"Bang'a",
    "wof:placetype":"locality"
},
  "geometry": {"coordinates":[93.48239,30.05988],"type":"Point"}
}