{
  "type": "Feature",
  "properties": {
    "gn:admin1_code":"4.0",
    "gn:asciiname":"Guyan",
    "gn:country_code":"CN",
    "gn:dem":5,
    "gn:feature_class":"P",
    "gn:feature_code":"PPL",
    "gn:name":"Guyan",
    "gn:population":0,
    "gn:timezone":"Asia/Shanghai",
    "iso:country":"CN",
    "name:zho_x_preferred":[
        "Guyan"
    ],
    "name:zho_x_variant":[
        "\u53e4\u989c"
    ],
    "wof:name":"Guyan",
    "wof:placetype":"locality"
},
  "geometry": {"coordinates":[119.49737,33.61801],"type":"Point"}
}