{
  "type": "Feature",
  "properties": {
    "gn:admin1_code":"12.0",
    "gn:asciiname":"Qijiaya",
    "gn:country_code":"CN",
    "gn:dem":595,
    "gn:feature_class":"P",
    "gn:feature_code":"PPL",
    "gn:name":"Qijiaya",
    "gn:population":0,
    "gn:timezone":"Asia/Shanghai",
    "iso:country":"CN",
    "name:zho_x_preferred":[
        "\u9f50\u5bb6\u57ad"
    ],
    "wof:name":"Qijiaya",
    "wof:placetype":"locality"
},
  "geometry": {"coordinates":[111.20208,32.90105],"type":"Point"}
}