{
  "type": "Feature",
  "properties": {
    "gn:admin1_code":"13.0",
    "gn:asciiname":"Hujirti",
    "gn:country_code":"CN",
    "gn:dem":1172,
    "gn:feature_class":"P",
    "gn:feature_code":"PPLA4",
    "gn:name":"Hujirti",
    "gn:population":0,
    "gn:timezone":"Asia/Shanghai",
    "iso:country":"CN",
    "name:kaz_x_preferred":[
        "Quj\u0131rt\u0131"
    ],
    "name:zho_x_preferred":[
        "Huji'erte Mengguzu Xiang"
    ],
    "name:zho_x_variant":[
        "\u547c\u5409\u5c14\u7279\u8499\u53e4\u65cf\u4e61"
    ],
    "wof:name":"Hujirti",
    "wof:placetype":"locality"
},
  "geometry": {"coordinates":[81.89209,43.22732],"type":"Point"}
}