{
  "type": "Feature",
  "properties": {
    "gn:admin1_code":"24.0",
    "gn:asciiname":"Zhaizi",
    "gn:country_code":"CN",
    "gn:dem":424,
    "gn:feature_class":"P",
    "gn:feature_code":"PPL",
    "gn:name":"Zhaizi",
    "gn:population":0,
    "gn:timezone":"Asia/Shanghai",
    "iso:country":"CN",
    "name:und_x_variant":[
        "\u5be8\u5b50"
    ],
    "wof:name":"Zhaizi",
    "wof:placetype":"locality"
},
  "geometry": {"coordinates":[111.43442,35.93405999999999],"type":"Point"}
}