{
  "type": "Feature",
  "properties": {
    "gn:admin1_code":"9.0",
    "gn:asciiname":"Gedang",
    "gn:country_code":"CN",
    "gn:dem":170,
    "gn:feature_class":"P",
    "gn:feature_code":"PPL",
    "gn:name":"Gedang",
    "gn:population":0,
    "gn:timezone":"Asia/Shanghai",
    "iso:country":"CN",
    "name:zho_x_preferred":[
        "\u572a\u57b1"
    ],
    "wof:name":"Gedang",
    "wof:placetype":"locality"
},
  "geometry": {"coordinates":[112.34757,34.57383],"type":"Point"}
}