{
  "type": "Feature",
  "properties": {
    "gn:admin1_code":"32.0",
    "gn:asciiname":"Huangtianba",
    "gn:country_code":"CN",
    "gn:dem":672,
    "gn:feature_class":"P",
    "gn:feature_code":"PPL",
    "gn:name":"Huangtianba",
    "gn:population":0,
    "gn:timezone":"Asia/Shanghai",
    "iso:country":"CN",
    "name:zho_x_preferred":[
        "\u8352\u7530\u575d"
    ],
    "wof:name":"Huangtianba",
    "wof:placetype":"locality"
},
  "geometry": {"coordinates":[107.51928999999998,31.63772],"type":"Point"}
}