{
  "type": "Feature",
  "properties": {
    "gn:admin1_code":"18",
    "gn:asciiname":"Zhujiadu",
    "gn:country_code":"CN",
    "gn:dem":923,
    "gn:feature_class":"P",
    "gn:feature_code":"PPL",
    "gn:name":"Zhujiadu",
    "gn:population":0,
    "gn:timezone":"Asia/Shanghai",
    "iso:country":"CN",
    "name:zho_x_preferred":[
        "\u7af9\u5bb6\u5ea6"
    ],
    "wof:name":"Zhujiadu",
    "wof:placetype":"locality"
},
  "geometry": {"coordinates":[108.116,28.4311],"type":"Point"}
}