{
  "type": "Feature",
  "properties": {
    "gn:admin1_code":"25",
    "gn:asciiname":"Chang'anzhuang",
    "gn:country_code":"CN",
    "gn:dem":164,
    "gn:feature_class":"P",
    "gn:feature_code":"PPL",
    "gn:name":"Chang\u2019anzhuang",
    "gn:population":0,
    "gn:timezone":"Asia/Shanghai",
    "iso:country":"CN",
    "name:und_x_variant":[
        "Chang\u2019anzhuang"
    ],
    "name:zho_x_preferred":[
        "\u957f\u5b89\u5e84"
    ],
    "wof:name":"Chang'anzhuang",
    "wof:placetype":"locality"
},
  "geometry": {"coordinates":[118.652,35.8437],"type":"Point"}
}