{
  "type": "Feature",
  "properties": {
    "gn:admin1_code":"26.0",
    "gn:asciiname":"Xingmincun",
    "gn:country_code":"CN",
    "gn:dem":908,
    "gn:feature_class":"P",
    "gn:feature_code":"PPL",
    "gn:name":"Xingmincun",
    "gn:population":0,
    "gn:timezone":"Asia/Shanghai",
    "iso:country":"CN",
    "name:zho_x_preferred":[
        "\u5174\u6c11\u6751"
    ],
    "wof:name":"Xingmincun",
    "wof:placetype":"locality"
},
  "geometry": {"coordinates":[109.27213,35.77609],"type":"Point"}
}