{
  "type": "Feature",
  "properties": {
    "gn:admin1_code":"3.0",
    "gn:asciiname":"Shatangli",
    "gn:country_code":"CN",
    "gn:dem":140,
    "gn:feature_class":"P",
    "gn:feature_code":"PPL",
    "gn:name":"Shatangli",
    "gn:population":0,
    "gn:timezone":"Asia/Shanghai",
    "iso:country":"CN",
    "name:und_x_variant":[
        "\u6c99\u5858\u91cc"
    ],
    "wof:name":"Shatangli",
    "wof:placetype":"locality"
},
  "geometry": {"coordinates":[117.66419,29.29702],"type":"Point"}
}