{
  "type": "Feature",
  "properties": {
    "gn:admin1_code":"29",
    "gn:asciiname":"Tianbao",
    "gn:country_code":"CN",
    "gn:dem":652,
    "gn:feature_class":"P",
    "gn:feature_code":"PPL",
    "gn:name":"Tianbao",
    "gn:population":0,
    "gn:timezone":"Asia/Shanghai",
    "iso:country":"CN",
    "name:ceb_x_preferred":[
        "Tianbao"
    ],
    "name:swe_x_preferred":[
        "Tianbao"
    ],
    "name:zho_x_preferred":[
        "\u5929\u4fdd"
    ],
    "wof:name":"Tianbao",
    "wof:placetype":"locality"
},
  "geometry": {"coordinates":[104.807,22.9871],"type":"Point"}
}