{
  "type": "Feature",
  "properties": {
    "gn:admin1_code":"11.0",
    "gn:asciiname":"Xiatuo",
    "gn:country_code":"CN",
    "gn:dem":616,
    "gn:feature_class":"P",
    "gn:feature_code":"PPL",
    "gn:name":"Xiatuo",
    "gn:population":0,
    "gn:timezone":"Asia/Shanghai",
    "iso:country":"CN",
    "name:zho_x_preferred":[
        "\u4e0b\u5768"
    ],
    "wof:name":"Xiatuo",
    "wof:placetype":"locality"
},
  "geometry": {"coordinates":[110.16508,27.63213],"type":"Point"}
}