{
  "type": "Feature",
  "properties": {
    "gn:admin1_code":"10",
    "gn:asciiname":"Nanqiaohe",
    "gn:country_code":"CN",
    "gn:dem":108,
    "gn:feature_class":"P",
    "gn:feature_code":"PPL",
    "gn:name":"Nanqiaohe",
    "gn:population":0,
    "gn:timezone":"Asia/Shanghai",
    "iso:country":"CN",
    "name:zho_x_preferred":[
        "\u5357\u5ced\u6cb3"
    ],
    "wof:name":"Nanqiaohe",
    "wof:placetype":"locality"
},
  "geometry": {"coordinates":[114.36199999999999,36.8233],"type":"Point"}
}