{
  "type": "Feature",
  "properties": {
    "gn:admin1_code":"3.0",
    "gn:asciiname":"Xuzhongshi",
    "gn:country_code":"CN",
    "gn:dem":17,
    "gn:feature_class":"P",
    "gn:feature_code":"PPL",
    "gn:name":"Xuzhongshi",
    "gn:population":0,
    "gn:timezone":"Asia/Shanghai",
    "iso:country":"CN",
    "name:und_x_variant":[
        "\u5f90\u4e2d\u5e02"
    ],
    "wof:name":"Xuzhongshi",
    "wof:placetype":"locality"
},
  "geometry": {"coordinates":[116.73999999999999,28.74551],"type":"Point"}
}