{
  "type": "Feature",
  "properties": {
    "gn:admin1_code":"4.0",
    "gn:asciiname":"Sanxing Sanzu",
    "gn:country_code":"CN",
    "gn:dem":6,
    "gn:feature_class":"P",
    "gn:feature_code":"PPLF",
    "gn:name":"Sanxing Sanzu",
    "gn:population":0,
    "gn:timezone":"Asia/Shanghai",
    "iso:country":"CN",
    "name:zho_x_preferred":[
        "Sanxing Sanzu"
    ],
    "name:zho_x_variant":[
        "\u4e09\u5174\u4e09\u7ec4"
    ],
    "wof:name":"Sanxing Sanzu",
    "wof:placetype":"locality"
},
  "geometry": {"coordinates":[121.54076000000001,32.09189],"type":"Point"}
}