{
  "type": "Feature",
  "properties": {
    "gn:admin1_code":"16.0",
    "gn:asciiname":"Shayinlan",
    "gn:country_code":"CN",
    "gn:dem":29,
    "gn:feature_class":"P",
    "gn:feature_code":"PPL",
    "gn:name":"Shayinlan",
    "gn:population":0,
    "gn:timezone":"Asia/Shanghai",
    "iso:country":"CN",
    "name:zho_x_preferred":[
        "\u6c99\u94f6\u680f"
    ],
    "wof:name":"Shayinlan",
    "wof:placetype":"locality"
},
  "geometry": {"coordinates":[109.544,21.9221],"type":"Point"}
}