{
  "type": "Feature",
  "properties": {
    "gn:admin1_code":"19.0",
    "gn:asciiname":"Fenshuiling",
    "gn:country_code":"CN",
    "gn:dem":139,
    "gn:feature_class":"P",
    "gn:feature_code":"PPL",
    "gn:name":"Fenshuiling",
    "gn:population":0,
    "gn:timezone":"Asia/Shanghai",
    "iso:country":"CN",
    "name:und_x_variant":[
        "\u5206\u6c34\u5cad"
    ],
    "name:zho_x_preferred":[
        "\u5206\u6c34\u5cad"
    ],
    "wof:name":"Fenshuiling",
    "wof:placetype":"locality"
},
  "geometry": {"coordinates":[123.80500000000001,42.1101],"type":"Point"}
}