{
  "type": "Feature",
  "properties": {
    "gn:admin1_code":"19.0",
    "gn:asciiname":"Dawang Zhangzicun",
    "gn:country_code":"CN",
    "gn:dem":544,
    "gn:feature_class":"P",
    "gn:feature_code":"PPL",
    "gn:name":"Dawang Zhangzicun",
    "gn:population":0,
    "gn:timezone":"Asia/Shanghai",
    "iso:country":"CN",
    "name:und_x_variant":[
        "Dawangzhangzicun",
        "Dawangzhangzi",
        "Dawang Zhangzicun"
    ],
    "name:zho_x_preferred":[
        "\u5927\u738b\u6756\u5b50\u6751"
    ],
    "wof:name":"Dawang Zhangzicun",
    "wof:placetype":"locality"
},
  "geometry": {"coordinates":[119.24876999999999,41.1339],"type":"Point"}
}