{
  "type": "Feature",
  "properties": {
    "gn:admin1_code":"16.0",
    "gn:asciiname":"Lizhuzui",
    "gn:country_code":"CN",
    "gn:dem":3,
    "gn:feature_class":"P",
    "gn:feature_code":"PPL",
    "gn:name":"Lizhuzui",
    "gn:population":0,
    "gn:timezone":"Asia/Shanghai",
    "iso:country":"CN",
    "name:zho_x_preferred":[
        "\u7281\u7af9\u5480"
    ],
    "wof:name":"Lizhuzui",
    "wof:placetype":"locality"
},
  "geometry": {"coordinates":[108.313,21.6514],"type":"Point"}
}