{
  "type": "Feature",
  "properties": {
    "gn:admin1_code":"1.0",
    "gn:asciiname":"Xianghecun",
    "gn:country_code":"CN",
    "gn:dem":96,
    "gn:feature_class":"P",
    "gn:feature_code":"PPL",
    "gn:name":"Xianghecun",
    "gn:population":0,
    "gn:timezone":"Asia/Shanghai",
    "iso:country":"CN",
    "name:zho_x_preferred":[
        "\u9879\u6cb3\u6751"
    ],
    "wof:name":"Xianghecun",
    "wof:placetype":"locality"
},
  "geometry": {"coordinates":[116.89032,31.02416],"type":"Point"}
}