{
  "type": "Feature",
  "properties": {
    "gn:admin1_code":"8.0",
    "gn:asciiname":"Qiandayushu",
    "gn:country_code":"CN",
    "gn:dem":139,
    "gn:feature_class":"P",
    "gn:feature_code":"PPL",
    "gn:name":"Qiandayushu",
    "gn:population":0,
    "gn:timezone":"Asia/Shanghai",
    "iso:country":"CN",
    "name:zho_x_preferred":[
        "\u524d\u5927\u6986\u6811"
    ],
    "wof:name":"Qiandayushu",
    "wof:placetype":"locality"
},
  "geometry": {"coordinates":[124.2317,46.59936],"type":"Point"}
}