{
  "type": "Feature",
  "properties": {
    "gn:admin1_code":"31.0",
    "gn:asciiname":"Zhayingdi",
    "gn:country_code":"CN",
    "gn:dem":42,
    "gn:feature_class":"P",
    "gn:feature_code":"PPL",
    "gn:name":"Zhayingdi",
    "gn:population":0,
    "gn:timezone":"Asia/Shanghai",
    "iso:country":"CN",
    "name:zho_x_preferred":[
        "\u624e\u8425\u5730"
    ],
    "wof:name":"Zhayingdi",
    "wof:placetype":"locality"
},
  "geometry": {"coordinates":[109.21451,19.60851],"type":"Point"}
}