{
  "type": "Feature",
  "properties": {
    "gn:admin1_code":"05",
    "gn:asciiname":"Beihenglu",
    "gn:country_code":"CN",
    "gn:dem":259,
    "gn:feature_class":"P",
    "gn:feature_code":"PPL",
    "gn:name":"Beihenglu",
    "gn:population":0,
    "gn:timezone":"Asia/Shanghai",
    "iso:country":"CN",
    "name:und_x_variant":[
        "\u5317\u6a2a\u8def",
        "Heng-lu-kou"
    ],
    "wof:name":"Beihenglu",
    "wof:placetype":"locality"
},
  "geometry": {"coordinates":[125.82417,40.98472],"type":"Point"}
}