{
  "type": "Feature",
  "properties": {
    "gn:admin1_code":"26.0",
    "gn:asciiname":"Zhouxiao",
    "gn:country_code":"CN",
    "gn:dem":625,
    "gn:feature_class":"P",
    "gn:feature_code":"PPL",
    "gn:name":"Zhouxiao",
    "gn:population":0,
    "gn:timezone":"Asia/Shanghai",
    "iso:country":"CN",
    "name:zho_x_preferred":[
        "\u6d32\u5c0f"
    ],
    "wof:name":"Zhouxiao",
    "wof:placetype":"locality"
},
  "geometry": {"coordinates":[108.25773,34.51999],"type":"Point"}
}