{
  "type": "Feature",
  "properties": {
    "gn:admin1_code":"29.0",
    "gn:asciiname":"Lanfengzhai",
    "gn:country_code":"CN",
    "gn:dem":1197,
    "gn:feature_class":"P",
    "gn:feature_code":"PPL",
    "gn:name":"Lanfengzhai",
    "gn:population":0,
    "gn:timezone":"Asia/Shanghai",
    "iso:country":"CN",
    "name:zho_x_preferred":[
        "\u70c2\u98ce\u5be8"
    ],
    "wof:name":"Lanfengzhai",
    "wof:placetype":"locality"
},
  "geometry": {"coordinates":[99.07989999999999,24.586],"type":"Point"}
}