{
  "type": "Feature",
  "properties": {
    "gn:admin1_code":"02",
    "gn:asciiname":"Banjialiancun",
    "gn:country_code":"CN",
    "gn:dem":6,
    "gn:feature_class":"P",
    "gn:feature_code":"PPL",
    "gn:name":"Banjialiancun",
    "gn:population":0,
    "gn:timezone":"Asia/Shanghai",
    "iso:country":"CN",
    "name:und_x_variant":[
        "Pan-chia-lien",
        "Banjialian",
        "Banjialiancun"
    ],
    "name:zho_x_preferred":[
        "\u534a\u6d43\u8fde"
    ],
    "name:zho_x_variant":[
        "\u534a\u6d43\u8fde\u6751"
    ],
    "wof:name":"Banjialiancun",
    "wof:placetype":"locality"
},
  "geometry": {"coordinates":[120.62653,27.45673],"type":"Point"}
}