{
  "type": "Feature",
  "properties": {
    "gn:admin1_code":"11",
    "gn:asciiname":"Mahekou",
    "gn:country_code":"CN",
    "gn:dem":32,
    "gn:feature_class":"P",
    "gn:feature_code":"PPLA4",
    "gn:name":"Mahekou",
    "gn:population":0,
    "gn:timezone":"Asia/Shanghai",
    "iso:country":"CN",
    "name:und_x_variant":[
        "Ma-ho-k\u2019ou",
        "Mahekou",
        "Mahekou Zhen"
    ],
    "name:zho_x_preferred":[
        "\u9ebb\u6cb3\u53e3"
    ],
    "name:zho_x_variant":[
        "\u9ebb\u6cb3\u53e3\u9547"
    ],
    "wof:name":"Mahekou",
    "wof:placetype":"locality"
},
  "geometry": {"coordinates":[112.28139,29.29833],"type":"Point"}
}