{
  "type": "Feature",
  "properties": {
    "gn:admin1_code":"12.0",
    "gn:asciiname":"Dushi",
    "gn:country_code":"CN",
    "gn:dem":518,
    "gn:feature_class":"P",
    "gn:feature_code":"PPL",
    "gn:name":"Dushi",
    "gn:population":0,
    "gn:timezone":"Asia/Shanghai",
    "iso:country":"CN",
    "name:zho_x_preferred":[
        "Dushi"
    ],
    "name:zho_x_variant":[
        "\u72ec\u77f3"
    ],
    "wof:name":"Dushi",
    "wof:placetype":"locality"
},
  "geometry": {"coordinates":[114.42776000000001,29.44899],"type":"Point"}
}