{
  "type": "Feature",
  "properties": {
    "gn:admin1_code":"3",
    "gn:asciiname":"Xinshuitang",
    "gn:country_code":"CN",
    "gn:dem":195,
    "gn:feature_class":"P",
    "gn:feature_code":"PPL",
    "gn:name":"Xinshuitang",
    "gn:population":0,
    "gn:timezone":"Asia/Shanghai",
    "iso:country":"CN",
    "name:zho_x_preferred":[
        "\u65b0\u6c34\u5858"
    ],
    "wof:name":"Xinshuitang",
    "wof:placetype":"locality"
},
  "geometry": {"coordinates":[114.74041,25.41546],"type":"Point"}
}