{
  "type": "Feature",
  "properties": {
    "gn:admin1_code":"4.0",
    "gn:asciiname":"Zhancao",
    "gn:country_code":"CN",
    "gn:dem":13,
    "gn:feature_class":"P",
    "gn:feature_code":"PPL",
    "gn:name":"Zhancao",
    "gn:population":0,
    "gn:timezone":"Asia/Shanghai",
    "iso:country":"CN",
    "name:zho_x_preferred":[
        "\u5360\u66f9"
    ],
    "wof:name":"Zhancao",
    "wof:placetype":"locality"
},
  "geometry": {"coordinates":[118.94712,32.30495999999999],"type":"Point"}
}