{
  "type": "Feature",
  "properties": {
    "gn:admin1_code":"5",
    "gn:asciiname":"Tatougou",
    "gn:country_code":"CN",
    "gn:dem":288,
    "gn:feature_class":"P",
    "gn:feature_code":"PPL",
    "gn:name":"Tatougou",
    "gn:population":0,
    "gn:timezone":"Asia/Shanghai",
    "iso:country":"CN",
    "name:zho_x_preferred":[
        "\u5854\u5934\u6c9f"
    ],
    "wof:name":"Tatougou",
    "wof:placetype":"locality"
},
  "geometry": {"coordinates":[127.24323,43.28555],"type":"Point"}
}