{
  "type": "Feature",
  "properties": {
    "gn:admin1_code":"32.0",
    "gn:asciiname":"Jiawushangzhai",
    "gn:country_code":"CN",
    "gn:dem":2222,
    "gn:feature_class":"P",
    "gn:feature_code":"PPL",
    "gn:name":"Jiawushangzhai",
    "gn:population":0,
    "gn:timezone":"Asia/Shanghai",
    "iso:country":"CN",
    "name:zho_x_preferred":[
        "\u7532\u52ff\u4e0a\u5be8"
    ],
    "wof:name":"Jiawushangzhai",
    "wof:placetype":"locality"
},
  "geometry": {"coordinates":[104.17751,32.99590999999999],"type":"Point"}
}