{
  "type": "Feature",
  "properties": {
    "gn:admin1_code":"19.0",
    "gn:asciiname":"Guangdatun",
    "gn:country_code":"CN",
    "gn:dem":59,
    "gn:feature_class":"P",
    "gn:feature_code":"PPL",
    "gn:name":"Guangdatun",
    "gn:population":0,
    "gn:timezone":"Asia/Shanghai",
    "iso:country":"CN",
    "name:zho_x_preferred":[
        "\u5e7f\u5927\u5c6f"
    ],
    "wof:name":"Guangdatun",
    "wof:placetype":"locality"
},
  "geometry": {"coordinates":[122.718,39.8684],"type":"Point"}
}