{
  "type": "Feature",
  "properties": {
    "gn:admin1_code":"12.0",
    "gn:asciiname":"Dongzixi",
    "gn:country_code":"CN",
    "gn:dem":587,
    "gn:feature_class":"P",
    "gn:feature_code":"PPL",
    "gn:name":"Dongzixi",
    "gn:population":0,
    "gn:timezone":"Asia/Shanghai",
    "iso:country":"CN",
    "name:zho_x_preferred":[
        "\u6d1e\u5b50\u6eaa"
    ],
    "wof:name":"Dongzixi",
    "wof:placetype":"locality"
},
  "geometry": {"coordinates":[109.61563,30.5571],"type":"Point"}
}