{
  "type": "Feature",
  "properties": {
    "gn:admin1_code":"24.0",
    "gn:asciiname":"Gaoshengzhuang",
    "gn:country_code":"CN",
    "gn:dem":1064,
    "gn:feature_class":"P",
    "gn:feature_code":"PPL",
    "gn:name":"Gaoshengzhuang",
    "gn:population":0,
    "gn:timezone":"Asia/Shanghai",
    "iso:country":"CN",
    "name:und_x_variant":[
        "\u9ad8\u5347\u5e84"
    ],
    "name:zho_x_preferred":[
        "\u9ad8\u5347\u5e84"
    ],
    "wof:name":"Gaoshengzhuang",
    "wof:placetype":"locality"
},
  "geometry": {"coordinates":[112.55952000000001,39.25594],"type":"Point"}
}