{
  "type": "Feature",
  "properties": {
    "gn:admin1_code":"03",
    "gn:asciiname":"Huangtan",
    "gn:country_code":"CN",
    "gn:dem":77,
    "gn:feature_class":"P",
    "gn:feature_code":"PPLA4",
    "gn:name":"Huangtan",
    "gn:population":0,
    "gn:timezone":"Asia/Shanghai",
    "iso:country":"CN",
    "name:und_x_variant":[
        "\u9ec4\u575b",
        "Huangtan Xiang",
        "\u9ec4\u575b\u4e61"
    ],
    "wof:name":"Huangtan",
    "wof:placetype":"locality"
},
  "geometry": {"coordinates":[117.07838,29.52239],"type":"Point"}
}