{
  "type": "Feature",
  "properties": {
    "gn:admin1_code":"30",
    "gn:asciiname":"Miaotou",
    "gn:country_code":"CN",
    "gn:dem":-4,
    "gn:feature_class":"P",
    "gn:feature_code":"PPL",
    "gn:name":"Miaotou",
    "gn:population":0,
    "gn:timezone":"Asia/Shanghai",
    "iso:country":"CN",
    "wof:name":"Miaotou",
    "wof:placetype":"locality"
},
  "geometry": {"coordinates":[113.48333,23.08333],"type":"Point"}
}