{
  "type": "Feature",
  "properties": {
    "gn:admin1_code":"15.0",
    "gn:asciiname":"Liuzongqi",
    "gn:country_code":"CN",
    "gn:dem":2176,
    "gn:feature_class":"P",
    "gn:feature_code":"PPL",
    "gn:name":"Liuzongqi",
    "gn:population":0,
    "gn:timezone":"Asia/Shanghai",
    "iso:country":"CN",
    "name:zho_x_preferred":[
        "\u5218\u603b\u65d7"
    ],
    "wof:name":"Liuzongqi",
    "wof:placetype":"locality"
},
  "geometry": {"coordinates":[100.84099999999999,38.4956],"type":"Point"}
}