{
  "type": "Feature",
  "properties": {
    "gn:admin1_code":"24",
    "gn:asciiname":"Quandian",
    "gn:country_code":"CN",
    "gn:dem":1081,
    "gn:feature_class":"P",
    "gn:feature_code":"PPL",
    "gn:name":"Quandian",
    "gn:population":0,
    "gn:timezone":"Asia/Shanghai",
    "iso:country":"CN",
    "name:und_x_variant":[
        "Ch\u2019\u00fcan-tien",
        "Quandian"
    ],
    "name:zho_x_preferred":[
        "\u6743\u5e97"
    ],
    "wof:name":"Quandian",
    "wof:placetype":"locality"
},
  "geometry": {"coordinates":[112.58821,36.96635],"type":"Point"}
}