{
  "type": "Feature",
  "properties": {
    "gn:admin1_code":"11.0",
    "gn:asciiname":"Yuanzui",
    "gn:country_code":"CN",
    "gn:dem":39,
    "gn:feature_class":"P",
    "gn:feature_code":"PPL",
    "gn:name":"Yuanzui",
    "gn:population":0,
    "gn:timezone":"Asia/Shanghai",
    "iso:country":"CN",
    "name:zho_x_preferred":[
        "Yuanzui"
    ],
    "name:zho_x_variant":[
        "\u5143\u5480"
    ],
    "wof:name":"Yuanzui",
    "wof:placetype":"locality"
},
  "geometry": {"coordinates":[111.5166,29.0667],"type":"Point"}
}