{
  "type": "Feature",
  "properties": {
    "gn:admin1_code":"30",
    "gn:asciiname":"Longtang",
    "gn:country_code":"CN",
    "gn:dem":15,
    "gn:feature_class":"P",
    "gn:feature_code":"PPL",
    "gn:name":"Longtang",
    "gn:population":0,
    "gn:timezone":"Asia/Urumqi",
    "iso:country":"CN",
    "name:zho_x_preferred":[
        "\u9f99\u5858"
    ],
    "wof:name":"Longtang",
    "wof:placetype":"locality"
},
  "geometry": {"coordinates":[110.72745999999999,21.46692],"type":"Point"}
}