{
  "type": "Feature",
  "properties": {
    "gn:admin1_code":"2.0",
    "gn:asciiname":"Zhekeng",
    "gn:country_code":"CN",
    "gn:dem":185,
    "gn:feature_class":"P",
    "gn:feature_code":"PPL",
    "gn:name":"Zhekeng",
    "gn:population":0,
    "gn:timezone":"Asia/Shanghai",
    "iso:country":"CN",
    "name:zho_x_preferred":[
        "\u67d8\u5751"
    ],
    "wof:name":"Zhekeng",
    "wof:placetype":"locality"
},
  "geometry": {"coordinates":[120.00172999999999,28.98871],"type":"Point"}
}