{
  "type": "Feature",
  "properties": {
    "gn:admin1_code":"25",
    "gn:asciiname":"Huangtongcun",
    "gn:country_code":"CN",
    "gn:dem":299,
    "gn:feature_class":"P",
    "gn:feature_code":"PPL",
    "gn:name":"Huangtongcun",
    "gn:population":0,
    "gn:timezone":"Asia/Shanghai",
    "iso:country":"CN",
    "name:zho_x_preferred":[
        "\u9ec4\u6850\u6751"
    ],
    "wof:name":"Huangtongcun",
    "wof:placetype":"locality"
},
  "geometry": {"coordinates":[119.062,35.5764],"type":"Point"}
}