{
  "type": "Feature",
  "properties": {
    "gn:admin1_code":"3.0",
    "gn:asciiname":"Changmafeng",
    "gn:country_code":"CN",
    "gn:dem":148,
    "gn:feature_class":"P",
    "gn:feature_code":"PPL",
    "gn:name":"Changmafeng",
    "gn:population":0,
    "gn:timezone":"Asia/Shanghai",
    "iso:country":"CN",
    "name:zho_x_preferred":[
        "\u957f\u9ebb\u4e30"
    ],
    "wof:name":"Changmafeng",
    "wof:placetype":"locality"
},
  "geometry": {"coordinates":[118.30345,28.47474],"type":"Point"}
}