{
  "type": "Feature",
  "properties": {
    "gn:admin1_code":"20.0",
    "gn:asciiname":"Bilige",
    "gn:country_code":"CN",
    "gn:dem":678,
    "gn:feature_class":"P",
    "gn:feature_code":"PPL",
    "gn:name":"Bilige",
    "gn:population":0,
    "gn:timezone":"Asia/Shanghai",
    "iso:country":"CN",
    "name:zho_x_preferred":[
        "\u6bd5\u529b\u683c"
    ],
    "wof:name":"Bilige",
    "wof:placetype":"locality"
},
  "geometry": {"coordinates":[122.17991000000001,50.04048],"type":"Point"}
}