{
  "type": "Feature",
  "properties": {
    "gn:admin1_code":"14.0",
    "gn:asciiname":"Nacangwo",
    "gn:country_code":"CN",
    "gn:dem":4292,
    "gn:feature_class":"P",
    "gn:feature_code":"PPL",
    "gn:name":"Nacangwo",
    "gn:population":0,
    "gn:timezone":"Asia/Urumqi",
    "iso:country":"CN",
    "name:zho_x_preferred":[
        "\u90a3\u85cf\u63e1"
    ],
    "wof:name":"Nacangwo",
    "wof:placetype":"locality"
},
  "geometry": {"coordinates":[87.15730000000001,28.6228],"type":"Point"}
}