{
  "type": "Feature",
  "properties": {
    "gn:admin1_code":"16.0",
    "gn:asciiname":"Renguang",
    "gn:country_code":"CN",
    "gn:dem":484,
    "gn:feature_class":"P",
    "gn:feature_code":"PPL",
    "gn:name":"Renguang",
    "gn:population":0,
    "gn:timezone":"Asia/Shanghai",
    "iso:country":"CN",
    "name:zho_x_preferred":[
        "\u4ec1\u5e7f"
    ],
    "wof:name":"Renguang",
    "wof:placetype":"locality"
},
  "geometry": {"coordinates":[107.727,25.174],"type":"Point"}
}