{
  "type": "Feature",
  "properties": {
    "gn:admin1_code":"12.0",
    "gn:asciiname":"Shuangqiao",
    "gn:country_code":"CN",
    "gn:dem":79,
    "gn:feature_class":"P",
    "gn:feature_code":"PPL",
    "gn:name":"Shuangqiao",
    "gn:population":0,
    "gn:timezone":"Asia/Shanghai",
    "iso:country":"CN",
    "name:ceb_x_preferred":[
        "Shuangqiao"
    ],
    "name:deu_x_preferred":[
        "Shuangqiao"
    ],
    "name:fra_x_preferred":[
        "Shuangqiao"
    ],
    "name:nor_x_preferred":[
        "Shuangqiao"
    ],
    "name:swe_x_preferred":[
        "Shuangqiao"
    ],
    "name:vie_x_preferred":[
        "Song Ki\u1ec1u"
    ],
    "name:zho_x_preferred":[
        "\u53cc\u6865"
    ],
    "wof:name":"Shuangqiao",
    "wof:placetype":"locality"
},
  "geometry": {"coordinates":[114.15432,31.64042],"type":"Point"}
}