{
  "type": "Feature",
  "properties": {
    "gn:admin1_code":"32.0",
    "gn:asciiname":"Tiechangwan",
    "gn:country_code":"CN",
    "gn:dem":664,
    "gn:feature_class":"P",
    "gn:feature_code":"PPL",
    "gn:name":"Tiechangwan",
    "gn:population":0,
    "gn:timezone":"Asia/Shanghai",
    "iso:country":"CN",
    "name:zho_x_preferred":[
        "\u94c1\u5382\u6e7e"
    ],
    "wof:name":"Tiechangwan",
    "wof:placetype":"locality"
},
  "geometry": {"coordinates":[107.217,32.3654],"type":"Point"}
}