{
  "type": "Feature",
  "properties": {
    "gn:admin1_code":"24.0",
    "gn:asciiname":"Sipu",
    "gn:country_code":"CN",
    "gn:dem":1270,
    "gn:feature_class":"P",
    "gn:feature_code":"PPL",
    "gn:name":"Sipu",
    "gn:population":0,
    "gn:timezone":"Asia/Shanghai",
    "iso:country":"CN",
    "name:zho_x_preferred":[
        "\u5bfa\u94fa"
    ],
    "wof:name":"Sipu",
    "wof:placetype":"locality"
},
  "geometry": {"coordinates":[113.46841999999999,35.58229],"type":"Point"}
}