{
  "type": "Feature",
  "properties": {
    "gn:admin1_code":"03",
    "gn:asciiname":"Dafan",
    "gn:cc2":"CN",
    "gn:country_code":"CN",
    "gn:dem":181,
    "gn:feature_class":"P",
    "gn:feature_code":"PPL",
    "gn:name":"Dafan",
    "gn:population":0,
    "gn:timezone":"Asia/Shanghai",
    "iso:country":"CN",
    "name:und_x_variant":[
        "Ta-fan",
        "Dafan"
    ],
    "name:zho_x_preferred":[
        "\u5927\u7548"
    ],
    "wof:name":"Dafan",
    "wof:placetype":"locality"
},
  "geometry": {"coordinates":[118.11472000000001,29.38528],"type":"Point"}
}