{
  "type": "Feature",
  "properties": {
    "gn:admin1_code":"15.0",
    "gn:asciiname":"Yangjia Diwan",
    "gn:country_code":"CN",
    "gn:dem":1512,
    "gn:feature_class":"P",
    "gn:feature_code":"PPL",
    "gn:name":"Yangjia Diwan",
    "gn:population":0,
    "gn:timezone":"Asia/Shanghai",
    "iso:country":"CN",
    "name:zho_x_preferred":[
        "\u6768\u5bb6\u5730\u6e7e"
    ],
    "wof:name":"Yangjia Diwan",
    "wof:placetype":"locality"
},
  "geometry": {"coordinates":[104.34099999999999,36.4704],"type":"Point"}
}