{
  "type": "Feature",
  "properties": {
    "gn:admin1_code":"18",
    "gn:asciiname":"Wuzhai",
    "gn:country_code":"CN",
    "gn:dem":755,
    "gn:feature_class":"P",
    "gn:feature_code":"PPL",
    "gn:name":"Wuzhai",
    "gn:population":0,
    "gn:timezone":"Asia/Shanghai",
    "iso:country":"CN",
    "name:zho_x_preferred":[
        "\u4e94\u5be8"
    ],
    "wof:name":"Wuzhai",
    "wof:placetype":"locality"
},
  "geometry": {"coordinates":[107.10599999999999,27.2335],"type":"Point"}
}