{
  "type": "Feature",
  "properties": {
    "gn:admin1_code":"16.0",
    "gn:asciiname":"Dazeng",
    "gn:country_code":"CN",
    "gn:dem":851,
    "gn:feature_class":"P",
    "gn:feature_code":"PPL",
    "gn:name":"Dazeng",
    "gn:population":0,
    "gn:timezone":"Asia/Shanghai",
    "iso:country":"CN",
    "name:zho_x_preferred":[
        "\u5927\u589e"
    ],
    "wof:name":"Dazeng",
    "wof:placetype":"locality"
},
  "geometry": {"coordinates":[106.21599999999999,23.4191],"type":"Point"}
}