{
  "type": "Feature",
  "properties": {
    "gn:admin1_code":"07",
    "gn:asciiname":"Guanban",
    "gn:country_code":"CN",
    "gn:dem":14,
    "gn:feature_class":"P",
    "gn:feature_code":"PPLA4",
    "gn:name":"Guanban",
    "gn:population":0,
    "gn:timezone":"Asia/Shanghai",
    "iso:country":"CN",
    "name:und_x_variant":[
        "Guanban Zhen"
    ],
    "name:zho_x_preferred":[
        "\u5b98\u5742"
    ],
    "name:zho_x_variant":[
        "\u5b98\u5742\u9547"
    ],
    "wof:name":"Guanban",
    "wof:placetype":"locality"
},
  "geometry": {"coordinates":[119.66974999999999,26.31204],"type":"Point"}
}