{
  "type": "Feature",
  "properties": {
    "gn:admin1_code":"4.0",
    "gn:asciiname":"Xibanluncun",
    "gn:country_code":"CN",
    "gn:dem":7,
    "gn:feature_class":"P",
    "gn:feature_code":"PPL",
    "gn:name":"Xibanluncun",
    "gn:population":0,
    "gn:timezone":"Asia/Shanghai",
    "iso:country":"CN",
    "name:zho_x_preferred":[
        "\u897f\u962a\u4f26\u6751"
    ],
    "wof:name":"Xibanluncun",
    "wof:placetype":"locality"
},
  "geometry": {"coordinates":[119.91773000000001,32.68732],"type":"Point"}
}