{
  "type": "Feature",
  "properties": {
    "gn:admin1_code":"8.0",
    "gn:asciiname":"Quanzitun",
    "gn:country_code":"CN",
    "gn:dem":170,
    "gn:feature_class":"P",
    "gn:feature_code":"PPL",
    "gn:name":"Quanzitun",
    "gn:population":0,
    "gn:timezone":"Asia/Shanghai",
    "iso:country":"CN",
    "name:zho_x_preferred":[
        "\u6cc9\u5b50\u5c6f"
    ],
    "wof:name":"Quanzitun",
    "wof:placetype":"locality"
},
  "geometry": {"coordinates":[127.63739,46.41992],"type":"Point"}
}