{
  "type": "Feature",
  "properties": {
    "gn:admin1_code":"25",
    "gn:asciiname":"Xintun",
    "gn:country_code":"CN",
    "gn:dem":34,
    "gn:feature_class":"P",
    "gn:feature_code":"PPL",
    "gn:name":"Xintun",
    "gn:population":0,
    "gn:timezone":"Asia/Shanghai",
    "iso:country":"CN",
    "name:deu_x_preferred":[
        "Xintun"
    ],
    "name:zho_x_preferred":[
        "\u65b0\u5c6f"
    ],
    "wof:name":"Xintun",
    "wof:placetype":"locality"
},
  "geometry": {"coordinates":[116.712,36.5697],"type":"Point"}
}