{
  "type": "Feature",
  "properties": {
    "gn:admin1_code":"02",
    "gn:asciiname":"Songling",
    "gn:country_code":"CN",
    "gn:dem":12,
    "gn:feature_class":"P",
    "gn:feature_code":"PPL",
    "gn:name":"Songling",
    "gn:population":0,
    "gn:timezone":"Asia/Shanghai",
    "iso:country":"CN",
    "name:und_x_variant":[
        "\u677e\u9675",
        "Sung-ling-shih"
    ],
    "wof:name":"Songling",
    "wof:placetype":"locality"
},
  "geometry": {"coordinates":[120.61252,30.03295],"type":"Point"}
}