{
  "type": "Feature",
  "properties": {
    "gn:admin1_code":"12.0",
    "gn:asciiname":"Linjiahe",
    "gn:country_code":"CN",
    "gn:dem":1106,
    "gn:feature_class":"P",
    "gn:feature_code":"PPL",
    "gn:name":"Linjiahe",
    "gn:population":0,
    "gn:timezone":"Asia/Shanghai",
    "iso:country":"CN",
    "name:zho_x_preferred":[
        "\u6797\u5bb6\u6cb3"
    ],
    "wof:name":"Linjiahe",
    "wof:placetype":"locality"
},
  "geometry": {"coordinates":[109.71979,29.79957000000001],"type":"Point"}
}