{
  "type": "Feature",
  "properties": {
    "gn:admin1_code":"3.0",
    "gn:asciiname":"Fanjia",
    "gn:country_code":"CN",
    "gn:dem":35,
    "gn:feature_class":"P",
    "gn:feature_code":"PPL",
    "gn:name":"Fanjia",
    "gn:population":0,
    "gn:timezone":"Asia/Shanghai",
    "iso:country":"CN",
    "name:und_x_variant":[
        "\u6a0a\u5bb6"
    ],
    "wof:name":"Fanjia",
    "wof:placetype":"locality"
},
  "geometry": {"coordinates":[116.30924,27.98272],"type":"Point"}
}