{
  "type": "Feature",
  "properties": {
    "gn:admin1_code":"29",
    "gn:asciiname":"Xiaobantian",
    "gn:country_code":"CN",
    "gn:dem":1239,
    "gn:feature_class":"P",
    "gn:feature_code":"PPL",
    "gn:name":"Xiaobantian",
    "gn:population":0,
    "gn:timezone":"Asia/Shanghai",
    "iso:country":"CN",
    "name:zho_x_preferred":[
        "\u5c0f\u677f\u7530"
    ],
    "wof:name":"Xiaobantian",
    "wof:placetype":"locality"
},
  "geometry": {"coordinates":[105.09099999999999,24.1332],"type":"Point"}
}