{
  "type": "Feature",
  "properties": {
    "gn:admin1_code":"30",
    "gn:asciiname":"Ma'an",
    "gn:country_code":"CN",
    "gn:dem":12,
    "gn:feature_class":"P",
    "gn:feature_code":"PPL",
    "gn:name":"Ma\u2019an",
    "gn:population":0,
    "gn:timezone":"Asia/Shanghai",
    "iso:country":"CN",
    "name:und_x_variant":[
        "Ma\u2019an"
    ],
    "name:zho_x_preferred":[
        "\u99ac\u5b89"
    ],
    "wof:name":"Ma'an",
    "wof:placetype":"locality"
},
  "geometry": {"coordinates":[112.38345,22.9787],"type":"Point"}
}