{
  "type": "Feature",
  "properties": {
    "gn:admin1_code":"15.0",
    "gn:asciiname":"Xinglinbu",
    "gn:country_code":"CN",
    "gn:dem":1724,
    "gn:feature_class":"P",
    "gn:feature_code":"PPL",
    "gn:name":"Xinglinbu",
    "gn:population":0,
    "gn:timezone":"Asia/Shanghai",
    "iso:country":"CN",
    "name:zho_x_preferred":[
        "\u674f\u6797\u5821"
    ],
    "wof:name":"Xinglinbu",
    "wof:placetype":"locality"
},
  "geometry": {"coordinates":[106.066,34.9159],"type":"Point"}
}