{
  "type": "Feature",
  "properties": {
    "gn:admin1_code":"14.0",
    "gn:asciiname":"Yigong Nongchang",
    "gn:country_code":"CN",
    "gn:dem":2149,
    "gn:feature_class":"P",
    "gn:feature_code":"PPLF",
    "gn:name":"Yigong Nongchang",
    "gn:population":0,
    "gn:timezone":"Asia/Shanghai",
    "iso:country":"CN",
    "name:bod_x_preferred":[
        "Yi\u2019ong Nongchang"
    ],
    "name:und_x_variant":[
        "Baicun"
    ],
    "name:zho_x_preferred":[
        "Yi\u2019ong Nongchang"
    ],
    "name:zho_x_variant":[
        "Yigong Nongchang",
        "\u6613\u8d21\u519c\u573a",
        "\u67cf\u6751"
    ],
    "wof:name":"Yigong Nongchang",
    "wof:placetype":"locality"
},
  "geometry": {"coordinates":[94.96666999999999,30.16667],"type":"Point"}
}