{
  "type": "Feature",
  "properties": {
    "gn:admin1_code":"11",
    "gn:asciiname":"Wangshijiu",
    "gn:country_code":"CN",
    "gn:dem":152,
    "gn:feature_class":"P",
    "gn:feature_code":"PPL",
    "gn:name":"Wangshijiu",
    "gn:population":0,
    "gn:timezone":"Asia/Shanghai",
    "iso:country":"CN",
    "name:zho_x_preferred":[
        "\u738b\u5341\u4e5d"
    ],
    "wof:name":"Wangshijiu",
    "wof:placetype":"locality"
},
  "geometry": {"coordinates":[111.71244,28.35746],"type":"Point"}
}