{
  "type": "Feature",
  "properties": {
    "gn:admin1_code":"14.0",
    "gn:asciiname":"Geyika",
    "gn:country_code":"CN",
    "gn:dem":4327,
    "gn:feature_class":"P",
    "gn:feature_code":"PPL",
    "gn:name":"Geyika",
    "gn:population":0,
    "gn:timezone":"Asia/Urumqi",
    "iso:country":"CN",
    "name:zho_x_preferred":[
        "\u5404\u8863\u5361"
    ],
    "wof:name":"Geyika",
    "wof:placetype":"locality"
},
  "geometry": {"coordinates":[94.59133,31.53112],"type":"Point"}
}