{
  "type": "Feature",
  "properties": {
    "iso:country":"CN",
    "name:ara_x_preferred":[
        "\u0645\u0637\u0627\u0631 \u062c\u064a\u0646\u064a\u0646\u063a \u0643\u0648\u0641\u0648"
    ],
    "name:ceb_x_preferred":[
        "Jining Qufu Airport"
    ],
    "name:eng_x_preferred":[
        "Jining Qufu Airport"
    ],
    "name:eng_x_variant":[
        "JNG",
        "ZSJG"
    ],
    "name:eus_x_preferred":[
        "Jining aireportua"
    ],
    "name:fas_x_preferred":[
        "\u0641\u0631\u0648\u062f\u06af\u0627\u0647 \u062c\u06cc\u0646\u06cc\u0646\u06af \u06a9\u0648\u0641\u0648"
    ],
    "name:fra_x_preferred":[
        "A\u00e9roport de Jining Qufu"
    ],
    "name:jpn_x_preferred":[
        "\u6e08\u5be7\u66f2\u961c\u7a7a\u6e2f"
    ],
    "name:nld_x_preferred":[
        "Jining Qufu Airport"
    ],
    "name:ron_x_preferred":[
        "Aeroportul Jining Qufu"
    ],
    "name:swe_x_preferred":[
        "Jining Qufu Airport"
    ],
    "name:tgk_x_preferred":[
        "\u0424\u0443\u0440\u0443\u0434\u0433\u043e\u04b3\u0438 \u04b7\u0438\u043d\u0438\u043d\u0433 \u043a\u0443\u0444\u0443"
    ],
    "name:vie_x_preferred":[
        "S\u00e2n bay Kh\u00fac Ph\u1ee5 T\u1ebf Ninh"
    ],
    "name:zho_x_preferred":[
        "\u6d4e\u5b81\u66f2\u961c\u673a\u573a"
    ],
    "oa:elevation_ft":"134",
    "oa:type":"medium_airport",
    "wd:wordcount":36,
    "woe:hierarchy":{
        "country_id":23424781,
        "county_id":26198300,
        "localadmin_id":12687077,
        "planet_id":1,
        "state_id":12578014
    },
    "wof:name":"Jining Airport",
    "wof:placetype":"campus"
},
  "geometry": {"coordinates":[116.346667,35.292778],"type":"Point"}
}