{
  "type": "Feature",
  "properties": {
    "gn:admin1_code":"1.0",
    "gn:asciiname":"Huangpencun",
    "gn:country_code":"CN",
    "gn:dem":20,
    "gn:feature_class":"P",
    "gn:feature_code":"PPL",
    "gn:name":"Huangpencun",
    "gn:population":0,
    "gn:timezone":"Asia/Shanghai",
    "iso:country":"CN",
    "name:zho_x_preferred":[
        "\u9ec4\u76c6\u6751"
    ],
    "wof:name":"Huangpencun",
    "wof:placetype":"locality"
},
  "geometry": {"coordinates":[117.01758,30.86162],"type":"Point"}
}