{
  "type": "Feature",
  "properties": {
    "gn:admin1_code":"03",
    "gn:asciiname":"Lizhai",
    "gn:country_code":"CN",
    "gn:dem":93,
    "gn:feature_class":"P",
    "gn:feature_code":"PPLA4",
    "gn:name":"Lizhai",
    "gn:population":0,
    "gn:timezone":"Asia/Shanghai",
    "iso:country":"CN",
    "name:und_x_variant":[
        "Li-chai",
        "Lizhai",
        "\u674e\u5b85",
        "Lizhai Xiang",
        "\u674e\u5b85\u4e61"
    ],
    "wof:name":"Lizhai",
    "wof:placetype":"locality"
},
  "geometry": {"coordinates":[117.91891,29.00843],"type":"Point"}
}