{
  "type": "Feature",
  "properties": {
    "gn:admin1_code":"8.0",
    "gn:asciiname":"Sanhetun",
    "gn:country_code":"CN",
    "gn:dem":97,
    "gn:feature_class":"P",
    "gn:feature_code":"PPL",
    "gn:name":"Sanhetun",
    "gn:population":0,
    "gn:timezone":"Asia/Shanghai",
    "iso:country":"CN",
    "name:zho_x_preferred":[
        "\u4e09\u6cb3\u5c6f"
    ],
    "wof:name":"Sanhetun",
    "wof:placetype":"locality"
},
  "geometry": {"coordinates":[132.25753,45.69864000000001],"type":"Point"}
}