{
  "type": "Feature",
  "properties": {
    "gn:admin1_code":"30.0",
    "gn:asciiname":"Gaocheba",
    "gn:country_code":"CN",
    "gn:dem":119,
    "gn:feature_class":"P",
    "gn:feature_code":"PPL",
    "gn:name":"Gaocheba",
    "gn:population":0,
    "gn:timezone":"Asia/Shanghai",
    "iso:country":"CN",
    "name:zho_x_preferred":[
        "Gaocheba"
    ],
    "name:zho_x_variant":[
        "\u9ad8\u8f66\u575d"
    ],
    "wof:name":"Gaocheba",
    "wof:placetype":"locality"
},
  "geometry": {"coordinates":[114.03006999999999,24.27784],"type":"Point"}
}