{
  "type": "Feature",
  "properties": {
    "gn:admin1_code":"19.0",
    "gn:asciiname":"Yujiagou",
    "gn:country_code":"CN",
    "gn:dem":513,
    "gn:feature_class":"P",
    "gn:feature_code":"PPL",
    "gn:name":"Yujiagou",
    "gn:population":0,
    "gn:timezone":"Asia/Shanghai",
    "iso:country":"CN",
    "name:und_x_variant":[
        "\u4e8e\u5bb6\u6c9f"
    ],
    "wof:name":"Yujiagou",
    "wof:placetype":"locality"
},
  "geometry": {"coordinates":[124.62218,41.88892],"type":"Point"}
}