{
  "type": "Feature",
  "properties": {
    "gn:admin1_code":"30.0",
    "gn:asciiname":"Shiliuhua",
    "gn:country_code":"CN",
    "gn:dem":179,
    "gn:feature_class":"P",
    "gn:feature_code":"PPL",
    "gn:name":"Shiliuhua",
    "gn:population":0,
    "gn:timezone":"Asia/Shanghai",
    "iso:country":"CN",
    "name:zho_x_preferred":[
        "Shiliuhua"
    ],
    "name:zho_x_variant":[
        "\u77f3\u69b4\u82b1"
    ],
    "wof:name":"Shiliuhua",
    "wof:placetype":"locality"
},
  "geometry": {"coordinates":[114.09792,24.52252],"type":"Point"}
}