{
  "type": "Feature",
  "properties": {
    "gn:admin1_code":"16.0",
    "gn:asciiname":"Yanlou",
    "gn:country_code":"CN",
    "gn:dem":11,
    "gn:feature_class":"P",
    "gn:feature_code":"PPL",
    "gn:name":"Yanlou",
    "gn:population":0,
    "gn:timezone":"Asia/Shanghai",
    "iso:country":"CN",
    "name:ceb_x_preferred":[
        "Yanlou"
    ],
    "name:zho_x_preferred":[
        "\u70df\u697c"
    ],
    "name:zho_x_variant":[
        "\u960e\u697c\u9547"
    ],
    "wof:name":"Yanlou",
    "wof:placetype":"locality"
},
  "geometry": {"coordinates":[109.164,21.5802],"type":"Point"}
}