{
  "type": "Feature",
  "properties": {
    "gn:admin1_code":"15.0",
    "gn:asciiname":"Lijiamao",
    "gn:country_code":"CN",
    "gn:dem":1326,
    "gn:feature_class":"P",
    "gn:feature_code":"PPL",
    "gn:name":"Lijiamao",
    "gn:population":0,
    "gn:timezone":"Asia/Shanghai",
    "iso:country":"CN",
    "name:zho_x_preferred":[
        "\u674e\u5bb6\u5cc1"
    ],
    "wof:name":"Lijiamao",
    "wof:placetype":"locality"
},
  "geometry": {"coordinates":[107.74299999999999,35.9497],"type":"Point"}
}