{
  "type": "Feature",
  "properties": {
    "gn:admin1_code":"15.0",
    "gn:asciiname":"Chashuigou",
    "gn:country_code":"CN",
    "gn:dem":1528,
    "gn:feature_class":"P",
    "gn:feature_code":"PPL",
    "gn:name":"Chashuigou",
    "gn:population":0,
    "gn:timezone":"Asia/Shanghai",
    "iso:country":"CN",
    "name:zho_x_preferred":[
        "\u8336\u6c34\u6c9f"
    ],
    "wof:name":"Chashuigou",
    "wof:placetype":"locality"
},
  "geometry": {"coordinates":[104.922,32.693],"type":"Point"}
}