{
  "type": "Feature",
  "properties": {
    "gn:admin1_code":"29.0",
    "gn:asciiname":"Meilan",
    "gn:country_code":"CN",
    "gn:dem":1340,
    "gn:feature_class":"P",
    "gn:feature_code":"PPL",
    "gn:name":"Meilan",
    "gn:population":0,
    "gn:timezone":"Asia/Shanghai",
    "iso:country":"CN",
    "name:zho_x_preferred":[
        "\u6885\u5170"
    ],
    "wof:name":"Meilan",
    "wof:placetype":"locality"
},
  "geometry": {"coordinates":[100.991,22.7697],"type":"Point"}
}