{
  "type": "Feature",
  "properties": {
    "gn:admin1_code":"26.0",
    "gn:asciiname":"Wanxingcun",
    "gn:country_code":"CN",
    "gn:dem":747,
    "gn:feature_class":"P",
    "gn:feature_code":"PPL",
    "gn:name":"Wanxingcun",
    "gn:population":0,
    "gn:timezone":"Asia/Shanghai",
    "iso:country":"CN",
    "name:zho_x_preferred":[
        "\u4e07\u5174\u6751"
    ],
    "wof:name":"Wanxingcun",
    "wof:placetype":"locality"
},
  "geometry": {"coordinates":[108.28009,32.44732],"type":"Point"}
}