{
  "type": "Feature",
  "properties": {
    "gn:admin1_code":"33.0",
    "gn:asciiname":"Tiewu",
    "gn:country_code":"CN",
    "gn:dem":1046,
    "gn:feature_class":"P",
    "gn:feature_code":"PPL",
    "gn:name":"Tiewu",
    "gn:population":0,
    "gn:timezone":"Asia/Shanghai",
    "iso:country":"CN",
    "name:zho_x_preferred":[
        "\u94c1\u5c4b"
    ],
    "wof:name":"Tiewu",
    "wof:placetype":"locality"
},
  "geometry": {"coordinates":[109.05676,31.17278],"type":"Point"}
}