{
  "type": "Feature",
  "properties": {
    "gn:admin1_code":"32.0",
    "gn:asciiname":"Zhuanjiezi",
    "gn:country_code":"CN",
    "gn:dem":558,
    "gn:feature_class":"P",
    "gn:feature_code":"PPL",
    "gn:name":"Zhuanjiezi",
    "gn:population":0,
    "gn:timezone":"Asia/Shanghai",
    "iso:country":"CN",
    "name:zho_x_preferred":[
        "\u7816\u8857\u5b50"
    ],
    "wof:name":"Zhuanjiezi",
    "wof:placetype":"locality"
},
  "geometry": {"coordinates":[103.50960000000001,30.2786],"type":"Point"}
}