{
  "type": "Feature",
  "properties": {
    "gn:admin1_code":"3.0",
    "gn:asciiname":"Hamazui",
    "gn:country_code":"CN",
    "gn:dem":36,
    "gn:feature_class":"P",
    "gn:feature_code":"PPL",
    "gn:name":"Hamazui",
    "gn:population":0,
    "gn:timezone":"Asia/Shanghai",
    "iso:country":"CN",
    "name:und_x_variant":[
        "\u86e4\u87c6\u5480"
    ],
    "wof:name":"Hamazui",
    "wof:placetype":"locality"
},
  "geometry": {"coordinates":[116.41857,29.43403],"type":"Point"}
}