{
  "type": "Feature",
  "properties": {
    "gn:admin1_code":"28",
    "gn:asciiname":"Dabeijiangu",
    "gn:cc2":"CN",
    "gn:country_code":"CN",
    "gn:dem":4,
    "gn:feature_class":"P",
    "gn:feature_code":"PPL",
    "gn:name":"Dabeijiangu",
    "gn:population":0,
    "gn:timezone":"Asia/Shanghai",
    "iso:country":"CN",
    "name:und_x_variant":[
        "Pei-chien-ku",
        "Beijiangu",
        "Pei-chien-k\u2019ou",
        "Dabeijiangu"
    ],
    "wof:name":"Dabeijiangu",
    "wof:placetype":"locality"
},
  "geometry": {"coordinates":[117.73639,39.33778],"type":"Point"}
}