{
  "type": "Feature",
  "properties": {
    "gn:admin1_code":"26.0",
    "gn:asciiname":"Mayinping",
    "gn:country_code":"CN",
    "gn:dem":584,
    "gn:feature_class":"P",
    "gn:feature_code":"PPL",
    "gn:name":"Mayinping",
    "gn:population":0,
    "gn:timezone":"Asia/Shanghai",
    "iso:country":"CN",
    "name:zho_x_preferred":[
        "\u9ebb\u9634\u576a"
    ],
    "wof:name":"Mayinping",
    "wof:placetype":"locality"
},
  "geometry": {"coordinates":[108.86314,32.415],"type":"Point"}
}