{
  "type": "Feature",
  "properties": {
    "gn:admin1_code":"5.0",
    "gn:asciiname":"Xikulicun",
    "gn:country_code":"CN",
    "gn:dem":141,
    "gn:feature_class":"P",
    "gn:feature_code":"PPL",
    "gn:name":"Xikulicun",
    "gn:population":0,
    "gn:timezone":"Asia/Shanghai",
    "iso:country":"CN",
    "name:zho_x_preferred":[
        "\u897f\u5e93\u91cc\u6751"
    ],
    "wof:name":"Xikulicun",
    "wof:placetype":"locality"
},
  "geometry": {"coordinates":[124.49102999999999,45.33902],"type":"Point"}
}