{
  "type": "Feature",
  "properties": {
    "gn:admin1_code":"30.0",
    "gn:asciiname":"Wenzhong",
    "gn:country_code":"CN",
    "gn:dem":433,
    "gn:feature_class":"P",
    "gn:feature_code":"PPL",
    "gn:name":"Wenzhong",
    "gn:population":0,
    "gn:timezone":"Asia/Shanghai",
    "iso:country":"CN",
    "name:zho_x_preferred":[
        "Wenzhong"
    ],
    "name:zho_x_variant":[
        "\u6587\u4e2d"
    ],
    "wof:name":"Wenzhong",
    "wof:placetype":"locality"
},
  "geometry": {"coordinates":[112.005,24.23111],"type":"Point"}
}