{
  "type": "Feature",
  "properties": {
    "gn:admin1_code":"24",
    "gn:asciiname":"Gaohua",
    "gn:country_code":"CN",
    "gn:dem":761,
    "gn:feature_class":"P",
    "gn:feature_code":"PPL",
    "gn:name":"Gaohua",
    "gn:population":0,
    "gn:timezone":"Asia/Shanghai",
    "iso:country":"CN",
    "name:und_x_variant":[
        "Kao-hua",
        "Kao-hua-ts\u2019un",
        "Gaohua"
    ],
    "name:zho_x_preferred":[
        "\u9ad8\u82b1"
    ],
    "wof:name":"Gaohua",
    "wof:placetype":"locality"
},
  "geometry": {"coordinates":[112.45820000000001,37.52184000000001],"type":"Point"}
}