{
  "type": "Feature",
  "properties": {
    "gn:admin1_code":"9.0",
    "gn:asciiname":"Donggou",
    "gn:country_code":"CN",
    "gn:dem":521,
    "gn:feature_class":"P",
    "gn:feature_code":"PPL",
    "gn:name":"Donggou",
    "gn:population":0,
    "gn:timezone":"Asia/Shanghai",
    "iso:country":"CN",
    "name:und_x_variant":[
        "\u6d1e\u6c9f",
        "Donggou"
    ],
    "wof:name":"Donggou",
    "wof:placetype":"locality"
},
  "geometry": {"coordinates":[112.49684000000001,33.90359],"type":"Point"}
}