{
  "type": "Feature",
  "properties": {
    "gn:admin1_code":"24.0",
    "gn:asciiname":"Guandaodi",
    "gn:country_code":"CN",
    "gn:dem":1457,
    "gn:feature_class":"P",
    "gn:feature_code":"PPL",
    "gn:name":"Guandaodi",
    "gn:population":0,
    "gn:timezone":"Asia/Shanghai",
    "iso:country":"CN",
    "name:zho_x_preferred":[
        "\u5b98\u9053\u5e95"
    ],
    "wof:name":"Guandaodi",
    "wof:placetype":"locality"
},
  "geometry": {"coordinates":[111.36454000000001,38.79527],"type":"Point"}
}