{
  "type": "Feature",
  "properties": {
    "gn:admin1_code":"14.0",
    "gn:asciiname":"Danaji",
    "gn:country_code":"CN",
    "gn:dem":4187,
    "gn:feature_class":"P",
    "gn:feature_code":"PPL",
    "gn:name":"Danaji",
    "gn:population":0,
    "gn:timezone":"Asia/Urumqi",
    "iso:country":"CN",
    "name:zho_x_preferred":[
        "\u6253\u90a3\u7ed9"
    ],
    "wof:name":"Danaji",
    "wof:placetype":"locality"
},
  "geometry": {"coordinates":[96.98737,30.92102],"type":"Point"}
}