{
  "type": "Feature",
  "properties": {
    "gn:admin1_code":"30",
    "gn:asciiname":"Erlongxu",
    "gn:country_code":"CN",
    "gn:dem":49,
    "gn:feature_class":"P",
    "gn:feature_code":"PPL",
    "gn:name":"Erlongxu",
    "gn:population":0,
    "gn:timezone":"Asia/Shanghai",
    "iso:country":"CN",
    "name:zho_x_preferred":[
        "\u4e8c\u9f99\u5729"
    ],
    "wof:name":"Erlongxu",
    "wof:placetype":"locality"
},
  "geometry": {"coordinates":[113.73618,23.3915],"type":"Point"}
}