{
  "type": "Feature",
  "properties": {
    "gn:admin1_code":"18.0",
    "gn:asciiname":"Tufushan",
    "gn:country_code":"CN",
    "gn:dem":649,
    "gn:feature_class":"P",
    "gn:feature_code":"PPL",
    "gn:name":"Tufushan",
    "gn:population":0,
    "gn:timezone":"Asia/Shanghai",
    "iso:country":"CN",
    "name:zho_x_preferred":[
        "\u5c60\u4ed8\u5c71"
    ],
    "wof:name":"Tufushan",
    "wof:placetype":"locality"
},
  "geometry": {"coordinates":[108.41500000000001,26.8645],"type":"Point"}
}