{
  "type": "Feature",
  "properties": {
    "gn:admin1_code":"14.0",
    "gn:asciiname":"Chaomabu",
    "gn:country_code":"CN",
    "gn:dem":5006,
    "gn:feature_class":"P",
    "gn:feature_code":"PPL",
    "gn:name":"Chaomabu",
    "gn:population":0,
    "gn:timezone":"Asia/Shanghai",
    "iso:country":"CN",
    "name:und_x_variant":[
        "Chaomabucun",
        "Chaomabu"
    ],
    "name:zho_x_preferred":[
        "\u671d\u739b\u5e03\u6751"
    ],
    "name:zho_x_variant":[
        "\u671d\u739b\u5e03"
    ],
    "wof:name":"Chaomabu",
    "wof:placetype":"locality"
},
  "geometry": {"coordinates":[82.5018,31.7365],"type":"Point"}
}