{
  "type": "Feature",
  "properties": {
    "gn:admin1_code":"9.0",
    "gn:asciiname":"Fangzhuang",
    "gn:country_code":"CN",
    "gn:dem":55,
    "gn:feature_class":"P",
    "gn:feature_code":"PPL",
    "gn:name":"Fangzhuang",
    "gn:population":0,
    "gn:timezone":"Asia/Shanghai",
    "iso:country":"CN",
    "name:zho_x_preferred":[
        "\u65b9\u5e84"
    ],
    "name:zho_x_variant":[
        "\u65b9\u5e84\u5730\u533a"
    ],
    "wof:name":"Fangzhuang",
    "wof:placetype":"locality"
},
  "geometry": {"coordinates":[114.62832,32.36594],"type":"Point"}
}