{
  "type": "Feature",
  "properties": {
    "gn:admin1_code":"4.0",
    "gn:asciiname":"Dongsha",
    "gn:country_code":"CN",
    "gn:dem":19,
    "gn:feature_class":"P",
    "gn:feature_code":"PPL",
    "gn:name":"Dongsha",
    "gn:population":0,
    "gn:timezone":"Asia/Shanghai",
    "iso:country":"CN",
    "name:zho_x_preferred":[
        "Dongsha"
    ],
    "name:zho_x_variant":[
        "\u4e1c\u6c99"
    ],
    "wof:name":"Dongsha",
    "wof:placetype":"locality"
},
  "geometry": {"coordinates":[119.25503999999999,34.59674],"type":"Point"}
}