{
  "type": "Feature",
  "properties": {
    "gn:admin1_code":"30.0",
    "gn:asciiname":"Zhanglu",
    "gn:country_code":"CN",
    "gn:dem":38,
    "gn:feature_class":"P",
    "gn:feature_code":"PPL",
    "gn:name":"Zhanglu",
    "gn:population":0,
    "gn:timezone":"Asia/Shanghai",
    "iso:country":"CN",
    "name:zho_x_preferred":[
        "\u6a1f\u8def"
    ],
    "name:zho_x_variant":[
        "\u5f20\u9c81\u9547"
    ],
    "wof:name":"Zhanglu",
    "wof:placetype":"locality"
},
  "geometry": {"coordinates":[112.22318,23.14811],"type":"Point"}
}