{
  "type": "Feature",
  "properties": {
    "gn:admin1_code":"19.0",
    "gn:asciiname":"Shengjiatun",
    "gn:country_code":"CN",
    "gn:dem":22,
    "gn:feature_class":"P",
    "gn:feature_code":"PPL",
    "gn:name":"Shengjiatun",
    "gn:population":0,
    "gn:timezone":"Asia/Shanghai",
    "iso:country":"CN",
    "name:und_x_variant":[
        "\u76db\u5bb6\u5c6f"
    ],
    "name:zho_x_preferred":[
        "\u76db\u5bb6\u5c6f"
    ],
    "wof:name":"Shengjiatun",
    "wof:placetype":"locality"
},
  "geometry": {"coordinates":[121.992,39.2683],"type":"Point"}
}