{
  "type": "Feature",
  "properties": {
    "gn:admin1_code":"11.0",
    "gn:asciiname":"Wangshatang",
    "gn:country_code":"CN",
    "gn:dem":49,
    "gn:feature_class":"P",
    "gn:feature_code":"PPL",
    "gn:name":"Wangshatang",
    "gn:population":0,
    "gn:timezone":"Asia/Shanghai",
    "iso:country":"CN",
    "name:zho_x_preferred":[
        "\u738b\u6c99\u5802"
    ],
    "wof:name":"Wangshatang",
    "wof:placetype":"locality"
},
  "geometry": {"coordinates":[113.14816,29.12426],"type":"Point"}
}