{
  "type": "Feature",
  "properties": {
    "gn:admin1_code":"2.0",
    "gn:asciiname":"Qianjiang",
    "gn:country_code":"CN",
    "gn:dem":4,
    "gn:feature_class":"P",
    "gn:feature_code":"PPL",
    "gn:name":"Qianjiang",
    "gn:population":0,
    "gn:timezone":"Asia/Shanghai",
    "iso:country":"CN",
    "name:und_x_variant":[
        "Ch\u2019ien-chiang",
        "Qianjiang"
    ],
    "name:zho_x_preferred":[
        "\u524d\u6c5f"
    ],
    "wof:name":"Qianjiang",
    "wof:placetype":"locality"
},
  "geometry": {"coordinates":[121.42789999999999,29.73397000000001],"type":"Point"}
}