{
  "type": "Feature",
  "properties": {
    "gn:admin1_code":"2.0",
    "gn:asciiname":"Qianjiang",
    "gn:country_code":"CN",
    "gn:dem":4,
    "gn:feature_class":"P",
    "gn:feature_code":"PPL",
    "gn:name":"Qianjiang",
    "gn:population":0,
    "gn:timezone":"Asia/Shanghai",
    "iso:country":"CN",
    "name:ceb_x_preferred":[
        "Qianjiang"
    ],
    "name:ces_x_preferred":[
        "\u010cchien-\u0165iang"
    ],
    "name:deu_x_preferred":[
        "Qianjiang"
    ],
    "name:fra_x_preferred":[
        "Qianjiang"
    ],
    "name:mlg_x_preferred":[
        "Qianjiang"
    ],
    "name:nld_x_preferred":[
        "Qianjiang"
    ],
    "name:nor_x_preferred":[
        "Qianjiang"
    ],
    "name:rus_x_preferred":[
        "\u0426\u044f\u043d\u044c\u0446\u0437\u044f\u043d"
    ],
    "name:swe_x_preferred":[
        "Qianjiang"
    ],
    "name:und_x_variant":[
        "Ch\u2019ien-chiang",
        "Qianjiang"
    ],
    "name:urd_x_preferred":[
        "\u0686\u06cc\u0627\u0646\u062c\u06cc\u0627\u0646\u06af"
    ],
    "name:zho_x_preferred":[
        "\u524d\u6c5f"
    ],
    "wof:name":"Qianjiang",
    "wof:placetype":"locality"
},
  "geometry": {"coordinates":[121.42789999999999,29.73397000000001],"type":"Point"}
}