{
  "type": "Feature",
  "properties": {
    "gn:admin1_code":"15.0",
    "gn:asciiname":"Moba",
    "gn:country_code":"CN",
    "gn:dem":1336,
    "gn:feature_class":"P",
    "gn:feature_code":"PPL",
    "gn:name":"Moba",
    "gn:population":0,
    "gn:timezone":"Asia/Shanghai",
    "iso:country":"CN",
    "name:ceb_x_preferred":[
        "Moba"
    ],
    "name:deu_x_preferred":[
        "Moba"
    ],
    "name:fra_x_preferred":[
        "Moba"
    ],
    "name:ita_x_preferred":[
        "Moba"
    ],
    "name:nld_x_preferred":[
        "Moba"
    ],
    "name:ron_x_preferred":[
        "Moba"
    ],
    "name:rus_x_preferred":[
        "MOBA"
    ],
    "name:swe_x_preferred":[
        "Moba"
    ],
    "name:zho_x_preferred":[
        "\u78e8\u575d"
    ],
    "wof:name":"Moba",
    "wof:placetype":"locality"
},
  "geometry": {"coordinates":[106.06399999999999,34.212],"type":"Point"}
}