{
  "type": "Feature",
  "properties": {
    "gn:admin1_code":"18",
    "gn:asciiname":"Mahuanggou",
    "gn:country_code":"CN",
    "gn:dem":1251,
    "gn:feature_class":"P",
    "gn:feature_code":"PPL",
    "gn:name":"Mahuanggou",
    "gn:population":0,
    "gn:timezone":"Asia/Shanghai",
    "iso:country":"CN",
    "name:zho_x_preferred":[
        "\u8682\u87e5\u6c9f"
    ],
    "wof:name":"Mahuanggou",
    "wof:placetype":"locality"
},
  "geometry": {"coordinates":[106.646,27.7927],"type":"Point"}
}