{
  "type": "Feature",
  "properties": {
    "gn:admin1_code":"19.0",
    "gn:asciiname":"Qianqing Yangbu",
    "gn:country_code":"CN",
    "gn:dem":153,
    "gn:feature_class":"P",
    "gn:feature_code":"PPL",
    "gn:name":"Qianqing Yangbu",
    "gn:population":0,
    "gn:timezone":"Asia/Shanghai",
    "iso:country":"CN",
    "name:und_x_variant":[
        "Qianqingyangbao",
        "\u524d\u9752\u6768\u5821",
        "Qianqing Yangpu",
        "Qianqing Yangbu"
    ],
    "name:zho_x_preferred":[
        "\u524d\u9752\u6768\u5821"
    ],
    "wof:name":"Qianqing Yangbu",
    "wof:placetype":"locality"
},
  "geometry": {"coordinates":[123.51806999999999,40.6203],"type":"Point"}
}