{
  "type": "Feature",
  "properties": {
    "gn:admin1_code":"25.0",
    "gn:asciiname":"Dongchemenkuang",
    "gn:country_code":"CN",
    "gn:dem":34,
    "gn:feature_class":"P",
    "gn:feature_code":"PPL",
    "gn:name":"Dongchemenkuang",
    "gn:population":0,
    "gn:timezone":"Asia/Shanghai",
    "iso:country":"CN",
    "name:zho_x_preferred":[
        "\u4e1c\u8f66\u95e8\u593c"
    ],
    "wof:name":"Dongchemenkuang",
    "wof:placetype":"locality"
},
  "geometry": {"coordinates":[121.90505,37.39203],"type":"Point"}
}