{
  "type": "Feature",
  "properties": {
    "gn:admin1_code":"30",
    "gn:asciiname":"Zhenwutang",
    "gn:country_code":"CN",
    "gn:dem":15,
    "gn:feature_class":"P",
    "gn:feature_code":"PPL",
    "gn:name":"Zhenwutang",
    "gn:population":0,
    "gn:timezone":"Asia/Urumqi",
    "iso:country":"CN",
    "name:zho_x_preferred":[
        "\u9547\u6b66\u5858"
    ],
    "wof:name":"Zhenwutang",
    "wof:placetype":"locality"
},
  "geometry": {"coordinates":[109.86425,21.33659],"type":"Point"}
}