{
  "type": "Feature",
  "properties": {
    "gn:admin1_code":"20.0",
    "gn:asciiname":"Dijiagebu",
    "gn:country_code":"CN",
    "gn:dem":1559,
    "gn:feature_class":"P",
    "gn:feature_code":"PPL",
    "gn:name":"Dijiagebu",
    "gn:population":0,
    "gn:timezone":"Asia/Shanghai",
    "iso:country":"CN",
    "name:und_x_variant":[
        "\u5e95\u5bb6\u572a\u535c"
    ],
    "wof:name":"Dijiagebu",
    "wof:placetype":"locality"
},
  "geometry": {"coordinates":[110.08973,41.36832],"type":"Point"}
}