{
  "type": "Feature",
  "properties": {
    "gn:admin1_code":"29.0",
    "gn:asciiname":"Zhanmagulang",
    "gn:country_code":"CN",
    "gn:dem":1494,
    "gn:feature_class":"P",
    "gn:feature_code":"PPL",
    "gn:name":"Zhanmagulang",
    "gn:population":0,
    "gn:timezone":"Asia/Shanghai",
    "iso:country":"CN",
    "name:zho_x_preferred":[
        "\u6218\u9a6c\u53e4\u90ce"
    ],
    "wof:name":"Zhanmagulang",
    "wof:placetype":"locality"
},
  "geometry": {"coordinates":[99.95229999999999,25.2463],"type":"Point"}
}