{
  "type": "Feature",
  "properties": {
    "gn:admin1_code":"25",
    "gn:asciiname":"Guansi Houcun",
    "gn:country_code":"CN",
    "gn:dem":169,
    "gn:feature_class":"P",
    "gn:feature_code":"PPL",
    "gn:name":"Guansi Houcun",
    "gn:population":0,
    "gn:timezone":"Asia/Shanghai",
    "iso:country":"CN",
    "name:zho_x_preferred":[
        "\u5173\u53f8\u540e\u6751"
    ],
    "wof:name":"Guansi Houcun",
    "wof:placetype":"locality"
},
  "geometry": {"coordinates":[117.675,35.1795],"type":"Point"}
}