{
  "type": "Feature",
  "properties": {
    "gn:admin1_code":"7.0",
    "gn:asciiname":"Yuanqiu",
    "gn:country_code":"CN",
    "gn:dem":533,
    "gn:feature_class":"P",
    "gn:feature_code":"PPL",
    "gn:name":"Yuanqiu",
    "gn:population":0,
    "gn:timezone":"Asia/Shanghai",
    "iso:country":"CN",
    "name:zho_x_preferred":[
        "\u8fdc\u4e18"
    ],
    "wof:name":"Yuanqiu",
    "wof:placetype":"locality"
},
  "geometry": {"coordinates":[118.86749,26.87054],"type":"Point"}
}