{
  "type": "Feature",
  "properties": {
    "gn:admin1_code":"12.0",
    "gn:asciiname":"Huangxiekou",
    "gn:country_code":"CN",
    "gn:dem":30,
    "gn:feature_class":"P",
    "gn:feature_code":"PPLA4",
    "gn:name":"Huangxiekou",
    "gn:population":0,
    "gn:timezone":"Asia/Shanghai",
    "iso:country":"CN",
    "name:und_x_variant":[
        "Huangxiekou Zhen",
        "Huangxiekou",
        "\u9ec4\u6b47\u53e3"
    ],
    "name:zho_x_preferred":[
        "\u9ec4\u6b47\u53e3\u9547"
    ],
    "wof:name":"Huangxiekou",
    "wof:placetype":"locality"
},
  "geometry": {"coordinates":[112.85256,30.03299],"type":"Point"}
}