{
  "type": "Feature",
  "properties": {
    "gn:admin1_code":"15.0",
    "gn:asciiname":"Xiabian Muchang",
    "gn:country_code":"CN",
    "gn:dem":2836,
    "gn:feature_class":"P",
    "gn:feature_code":"PPLF",
    "gn:name":"Xiabian Muchang",
    "gn:population":0,
    "gn:timezone":"Asia/Shanghai",
    "iso:country":"CN",
    "name:und_x_variant":[
        "\u4e0b\u533e\u7267\u573a"
    ],
    "wof:name":"Xiabian Muchang",
    "wof:placetype":"locality"
},
  "geometry": {"coordinates":[104.03838,34.21557],"type":"Point"}
}