{
  "type": "Feature",
  "properties": {
    "gn:admin1_code":"19.0",
    "gn:asciiname":"Jiangnancun",
    "gn:country_code":"CN",
    "gn:dem":401,
    "gn:feature_class":"P",
    "gn:feature_code":"PPL",
    "gn:name":"Jiangnancun",
    "gn:population":0,
    "gn:timezone":"Asia/Shanghai",
    "iso:country":"CN",
    "name:zho_x_preferred":[
        "\u6c5f\u5357\u6751"
    ],
    "wof:name":"Jiangnancun",
    "wof:placetype":"locality"
},
  "geometry": {"coordinates":[125.30887,41.65347],"type":"Point"}
}