{
  "type": "Feature",
  "properties": {
    "gn:admin1_code":"18.0",
    "gn:asciiname":"Luma",
    "gn:country_code":"CN",
    "gn:dem":310,
    "gn:feature_class":"P",
    "gn:feature_code":"PPL",
    "gn:name":"L\u00fcma",
    "gn:population":0,
    "gn:timezone":"Asia/Shanghai",
    "iso:country":"CN",
    "name:ceb_x_preferred":[
        "Luma"
    ],
    "name:deu_x_preferred":[
        "Luma"
    ],
    "name:fin_x_preferred":[
        "Luma"
    ],
    "name:fra_x_preferred":[
        "Luma"
    ],
    "name:mar_x_preferred":[
        "\u0906\u0930\u094d\u092e\u0947\u0928\u093f\u092f\u0928 \u0932\u0941\u092e\u093e"
    ],
    "name:por_x_preferred":[
        "Luma"
    ],
    "name:rus_x_preferred":[
        "\u041b\u0443\u043c\u0430"
    ],
    "name:spa_x_preferred":[
        "Luma"
    ],
    "name:swe_x_preferred":[
        "Luma"
    ],
    "name:und_x_variant":[
        "L\u00fcma"
    ],
    "name:zho_x_preferred":[
        "\u5415\u5b56"
    ],
    "wof:name":"Luma",
    "wof:placetype":"locality"
},
  "geometry": {"coordinates":[108.863,25.9891],"type":"Point"}
}