{
  "type": "Feature",
  "properties": {
    "gn:admin1_code":"3.0",
    "gn:asciiname":"Tubei",
    "gn:country_code":"CN",
    "gn:dem":50,
    "gn:feature_class":"P",
    "gn:feature_code":"PPL",
    "gn:name":"Tubei",
    "gn:population":0,
    "gn:timezone":"Asia/Shanghai",
    "iso:country":"CN",
    "name:und_x_variant":[
        "\u56fe\u9642"
    ],
    "wof:name":"Tubei",
    "wof:placetype":"locality"
},
  "geometry": {"coordinates":[115.06083,28.05533],"type":"Point"}
}