{
  "type": "Feature",
  "properties": {
    "gn:admin1_code":"14",
    "gn:asciiname":"Sozhug",
    "gn:country_code":"CN",
    "gn:dem":3765,
    "gn:feature_class":"P",
    "gn:feature_code":"PPL",
    "gn:name":"Sozhug",
    "gn:population":0,
    "gn:timezone":"Asia/Urumqi",
    "iso:country":"CN",
    "name:bod_x_preferred":[
        "\u0f66\u0f7c\u0f0b\u0f51\u0fb2\u0f74\u0f42"
    ],
    "name:und_x_variant":[
        "Suozhu"
    ],
    "name:zho_x_preferred":[
        "\u7d22\u73e0"
    ],
    "wof:name":"Sozhug",
    "wof:placetype":"locality"
},
  "geometry": {"coordinates":[91.86004,29.42674],"type":"Point"}
}