{
  "type": "Feature",
  "properties": {
    "gn:admin1_code":"30",
    "gn:asciiname":"Shiliting",
    "gn:country_code":"CN",
    "gn:dem":148,
    "gn:feature_class":"P",
    "gn:feature_code":"PPLA4",
    "gn:name":"Shiliting",
    "gn:population":0,
    "gn:timezone":"Asia/Shanghai",
    "iso:country":"CN",
    "name:und_x_variant":[
        "\u5341\u91cc\u4ead",
        "Shiliting Zhen"
    ],
    "name:zho_x_preferred":[
        "\u5341\u91cc\u4ead\u9547"
    ],
    "wof:name":"Shiliting",
    "wof:placetype":"locality"
},
  "geometry": {"coordinates":[113.565,24.84778],"type":"Point"}
}