{
  "type": "Feature",
  "properties": {
    "gn:admin1_code":"8.0",
    "gn:asciiname":"Longzhan",
    "gn:country_code":"CN",
    "gn:dem":238,
    "gn:feature_class":"P",
    "gn:feature_code":"PPL",
    "gn:name":"Longzhan",
    "gn:population":0,
    "gn:timezone":"Asia/Shanghai",
    "iso:country":"CN",
    "name:zho_x_preferred":[
        "\u9f99\u7ad9"
    ],
    "wof:name":"Longzhan",
    "wof:placetype":"locality"
},
  "geometry": {"coordinates":[125.68317,52.85275],"type":"Point"}
}