{
  "type": "Feature",
  "properties": {
    "gn:admin1_code":"15.0",
    "gn:asciiname":"Yinjiaji",
    "gn:country_code":"CN",
    "gn:dem":1369,
    "gn:feature_class":"P",
    "gn:feature_code":"PPL",
    "gn:name":"Yinjiaji",
    "gn:population":0,
    "gn:timezone":"Asia/Shanghai",
    "iso:country":"CN",
    "name:zho_x_preferred":[
        "\u5c39\u5bb6\u96c6"
    ],
    "wof:name":"Yinjiaji",
    "wof:placetype":"locality"
},
  "geometry": {"coordinates":[108.291,35.9921],"type":"Point"}
}