{
  "type": "Feature",
  "properties": {
    "gn:admin1_code":"04",
    "gn:asciiname":"Shatanggang",
    "gn:country_code":"CN",
    "gn:dem":5,
    "gn:feature_class":"P",
    "gn:feature_code":"PPL",
    "gn:name":"Shatanggang",
    "gn:population":0,
    "gn:timezone":"Asia/Shanghai",
    "iso:country":"CN",
    "name:und_x_variant":[
        "Sha-t\u2019ang-hsiang",
        "Sha-t\u2019ang-chiang",
        "Sha-t\u2019ang-kang",
        "Shatangxiang",
        "Shatanggang",
        "\u6c99\u5858\u6e2f"
    ],
    "wof:name":"Shatanggang",
    "wof:placetype":"locality"
},
  "geometry": {"coordinates":[120.00913,31.42003],"type":"Point"}
}