{
  "type": "Feature",
  "properties": {
    "gn:admin1_code":"10",
    "gn:asciiname":"Shuiquangou",
    "gn:country_code":"CN",
    "gn:dem":1431,
    "gn:feature_class":"P",
    "gn:feature_code":"PPL",
    "gn:name":"Shuiquangou",
    "gn:population":0,
    "gn:timezone":"Asia/Shanghai",
    "iso:country":"CN",
    "name:zho_x_preferred":[
        "\u6c34\u6cc9\u6c9f"
    ],
    "wof:name":"Shuiquangou",
    "wof:placetype":"locality"
},
  "geometry": {"coordinates":[115.08049,40.93491],"type":"Point"}
}