{
  "type": "Feature",
  "properties": {
    "gn:admin1_code":"4.0",
    "gn:asciiname":"Jinsigang",
    "gn:country_code":"CN",
    "gn:dem":21,
    "gn:feature_class":"P",
    "gn:feature_code":"PPL",
    "gn:name":"Jinsigang",
    "gn:population":0,
    "gn:timezone":"Asia/Shanghai",
    "iso:country":"CN",
    "name:zho_x_preferred":[
        "\u91d1\u4e1d\u5c97"
    ],
    "wof:name":"Jinsigang",
    "wof:placetype":"locality"
},
  "geometry": {"coordinates":[118.93876000000002,32.07373],"type":"Point"}
}