{
  "type": "Feature",
  "properties": {
    "gn:admin1_code":"02",
    "gn:asciiname":"Hengdaiqiao",
    "gn:cc2":"CN",
    "gn:country_code":"CN",
    "gn:dem":7,
    "gn:feature_class":"P",
    "gn:feature_code":"PPL",
    "gn:name":"Hengdaiqiao",
    "gn:population":0,
    "gn:timezone":"Asia/Shanghai",
    "iso:country":"CN",
    "name:zho_x_preferred":[
        "Huang-ta-ch\u2019iao"
    ],
    "wof:name":"Hengdaiqiao",
    "wof:placetype":"locality"
},
  "geometry": {"coordinates":[120.88249999999999,28.03889],"type":"Point"}
}