{
  "type": "Feature",
  "properties": {
    "gn:admin1_code":"7",
    "gn:asciiname":"Wenling",
    "gn:country_code":"CN",
    "gn:dem":7,
    "gn:feature_class":"P",
    "gn:feature_code":"PPLA4",
    "gn:name":"Wenling",
    "gn:population":0,
    "gn:timezone":"Asia/Shanghai",
    "iso:country":"CN",
    "name:ara_x_preferred":[
        "\u0646\u0644\u064a\u0646\u063a"
    ],
    "name:ceb_x_preferred":[
        "Wenling"
    ],
    "name:deu_x_preferred":[
        "Wenling"
    ],
    "name:fra_x_preferred":[
        "Wenling"
    ],
    "name:ita_x_preferred":[
        "Wenling"
    ],
    "name:jpn_x_preferred":[
        "\u6e29\u5dba\u5e02"
    ],
    "name:kik_x_preferred":[
        "Wenling"
    ],
    "name:kor_x_preferred":[
        "\uc6d0\ub9c1\uc2dc"
    ],
    "name:mlg_x_preferred":[
        "Wenling"
    ],
    "name:nld_x_preferred":[
        "Wenling"
    ],
    "name:nor_x_preferred":[
        "Wenling"
    ],
    "name:swe_x_preferred":[
        "Wenling"
    ],
    "name:tgl_x_preferred":[
        "Wenling"
    ],
    "name:und_x_variant":[
        "Wenling Zhen"
    ],
    "name:urd_x_preferred":[
        "\u0648\u06cc\u0646\u0644\u06cc\u0646\u06af"
    ],
    "name:vie_x_preferred":[
        "\u00d4n L\u0129nh"
    ],
    "name:war_x_preferred":[
        "Wenling"
    ],
    "name:wuu_x_preferred":[
        "\u6e29\u5cad\u5e02"
    ],
    "name:zho_x_preferred":[
        "\u6587\u5cad"
    ],
    "name:zho_x_variant":[
        "\u6587\u5cad\u9547",
        "\u6e29\u5cad\u5e02"
    ],
    "wof:name":"Wenling",
    "wof:placetype":"locality"
},
  "geometry": {"coordinates":[119.64973999999999,25.99662],"type":"Point"}
}