{
  "type": "Feature",
  "properties": {
    "gn:admin1_code":"7",
    "gn:asciiname":"Wenling",
    "gn:country_code":"CN",
    "gn:dem":7,
    "gn:feature_class":"P",
    "gn:feature_code":"PPLA4",
    "gn:name":"Wenling",
    "gn:population":0,
    "gn:timezone":"Asia/Shanghai",
    "iso:country":"CN",
    "name:und_x_variant":[
        "Wenling Zhen"
    ],
    "name:zho_x_preferred":[
        "\u6587\u5cad"
    ],
    "name:zho_x_variant":[
        "\u6587\u5cad\u9547"
    ],
    "wof:name":"Wenling",
    "wof:placetype":"locality"
},
  "geometry": {"coordinates":[119.64973999999999,25.99662],"type":"Point"}
}