{
  "type": "Feature",
  "properties": {
    "gn:admin1_code":"3.0",
    "gn:asciiname":"Yingzhukeng",
    "gn:country_code":"CN",
    "gn:dem":468,
    "gn:feature_class":"P",
    "gn:feature_code":"PPL",
    "gn:name":"Yingzhukeng",
    "gn:population":0,
    "gn:timezone":"Asia/Shanghai",
    "iso:country":"CN",
    "name:und_x_variant":[
        "\u5e94\u7af9\u5751"
    ],
    "wof:name":"Yingzhukeng",
    "wof:placetype":"locality"
},
  "geometry": {"coordinates":[115.67546000000002,26.81019],"type":"Point"}
}