{
  "type": "Feature",
  "properties": {
    "gn:admin1_code":"25.0",
    "gn:asciiname":"Gengdiancun",
    "gn:country_code":"CN",
    "gn:dem":39,
    "gn:feature_class":"P",
    "gn:feature_code":"PPL",
    "gn:name":"Gengdiancun",
    "gn:population":0,
    "gn:timezone":"Asia/Shanghai",
    "iso:country":"CN",
    "name:zho_x_preferred":[
        "\u803f\u5e97\u6751"
    ],
    "wof:name":"Gengdiancun",
    "wof:placetype":"locality"
},
  "geometry": {"coordinates":[115.95855,36.66116],"type":"Point"}
}