{
  "type": "Feature",
  "properties": {
    "gn:admin1_code":"11.0",
    "gn:asciiname":"Huaixiantang",
    "gn:country_code":"CN",
    "gn:dem":127,
    "gn:feature_class":"P",
    "gn:feature_code":"PPL",
    "gn:name":"Huaixiantang",
    "gn:population":0,
    "gn:timezone":"Asia/Shanghai",
    "iso:country":"CN",
    "name:zho_x_preferred":[
        "\u6000\u4ed9\u5802"
    ],
    "wof:name":"Huaixiantang",
    "wof:placetype":"locality"
},
  "geometry": {"coordinates":[112.36358,27.21265],"type":"Point"}
}