{
  "type": "Feature",
  "properties": {
    "gn:admin1_code":"18",
    "gn:asciiname":"Xiajiapo",
    "gn:country_code":"CN",
    "gn:dem":750,
    "gn:feature_class":"P",
    "gn:feature_code":"PPL",
    "gn:name":"Xiajiapo",
    "gn:population":0,
    "gn:timezone":"Asia/Shanghai",
    "iso:country":"CN",
    "name:zho_x_preferred":[
        "\u590f\u5bb6\u5761"
    ],
    "wof:name":"Xiajiapo",
    "wof:placetype":"locality"
},
  "geometry": {"coordinates":[108.035,27.6167],"type":"Point"}
}