{
  "type": "Feature",
  "properties": {
    "gn:admin1_code":"30.0",
    "gn:asciiname":"Baidai",
    "gn:country_code":"CN",
    "gn:dem":705,
    "gn:feature_class":"P",
    "gn:feature_code":"PPL",
    "gn:name":"Baidai",
    "gn:population":0,
    "gn:timezone":"Asia/Shanghai",
    "iso:country":"CN",
    "name:zho_x_preferred":[
        "Baidai"
    ],
    "name:zho_x_variant":[
        "\u767d\u5e26"
    ],
    "wof:name":"Baidai",
    "wof:placetype":"locality"
},
  "geometry": {"coordinates":[112.58972,23.97639],"type":"Point"}
}