{
  "type": "Feature",
  "properties": {
    "gn:admin1_code":"3.0",
    "gn:asciiname":"Xuzhuang",
    "gn:country_code":"CN",
    "gn:dem":434,
    "gn:feature_class":"P",
    "gn:feature_code":"PPL",
    "gn:name":"Xuzhuang",
    "gn:population":0,
    "gn:timezone":"Asia/Shanghai",
    "iso:country":"CN",
    "name:und_x_variant":[
        "\u5f90\u5e84"
    ],
    "wof:name":"Xuzhuang",
    "wof:placetype":"locality"
},
  "geometry": {"coordinates":[115.96839,27.07203],"type":"Point"}
}