{
  "type": "Feature",
  "properties": {
    "gn:admin1_code":"29.0",
    "gn:asciiname":"Bawang",
    "gn:country_code":"CN",
    "gn:dem":996,
    "gn:feature_class":"P",
    "gn:feature_code":"PPL",
    "gn:name":"Bawang",
    "gn:population":0,
    "gn:timezone":"Asia/Shanghai",
    "iso:country":"CN",
    "name:zho_x_preferred":[
        "\u53ed\u5f80"
    ],
    "wof:name":"Bawang",
    "wof:placetype":"locality"
},
  "geometry": {"coordinates":[100.563,21.5338],"type":"Point"}
}