{
  "type": "Feature",
  "properties": {
    "gn:admin1_code":"7",
    "gn:asciiname":"Xiyang",
    "gn:country_code":"CN",
    "gn:dem":53,
    "gn:feature_class":"P",
    "gn:feature_code":"PPL",
    "gn:name":"Xiyang",
    "gn:population":0,
    "gn:timezone":"Asia/Shanghai",
    "iso:country":"CN",
    "name:und_x_variant":[
        "\u831c\u6d0b"
    ],
    "wof:name":"Xiyang",
    "wof:placetype":"locality"
},
  "geometry": {"coordinates":[119.7775,27.01667],"type":"Point"}
}