{
  "type": "Feature",
  "properties": {
    "gn:admin1_code":"29.0",
    "gn:asciiname":"Guanzhongtian",
    "gn:country_code":"CN",
    "gn:dem":1209,
    "gn:feature_class":"P",
    "gn:feature_code":"PPL",
    "gn:name":"Guanzhongtian",
    "gn:population":0,
    "gn:timezone":"Asia/Shanghai",
    "iso:country":"CN",
    "name:zho_x_preferred":[
        "\u7ba1\u79cd\u7530"
    ],
    "wof:name":"Guanzhongtian",
    "wof:placetype":"locality"
},
  "geometry": {"coordinates":[101.009,23.1526],"type":"Point"}
}