{
  "type": "Feature",
  "properties": {
    "gn:admin1_code":"11.0",
    "gn:asciiname":"Juntianwan",
    "gn:country_code":"CN",
    "gn:dem":330,
    "gn:feature_class":"P",
    "gn:feature_code":"PPL",
    "gn:name":"Juntianwan",
    "gn:population":0,
    "gn:timezone":"Asia/Shanghai",
    "iso:country":"CN",
    "name:zho_x_preferred":[
        "\u519b\u7530\u6e7e"
    ],
    "wof:name":"Juntianwan",
    "wof:placetype":"locality"
},
  "geometry": {"coordinates":[110.51246999999999,27.77837],"type":"Point"}
}