{
  "type": "Feature",
  "properties": {
    "gn:admin1_code":"13.0",
    "gn:asciiname":"Nuo'airike",
    "gn:country_code":"CN",
    "gn:dem":1341,
    "gn:feature_class":"P",
    "gn:feature_code":"PPL",
    "gn:name":"Nuo\u2019airike",
    "gn:population":0,
    "gn:timezone":"Asia/Shanghai",
    "iso:country":"CN",
    "name:und_x_variant":[
        "Nuo\u2019airike"
    ],
    "name:zho_x_preferred":[
        "\u8bfa\u827e\u65e5\u514b"
    ],
    "wof:name":"Nuo'airike",
    "wof:placetype":"locality"
},
  "geometry": {"coordinates":[79.89749999999999,37.15302],"type":"Point"}
}