{
  "type": "Feature",
  "properties": {
    "gn:admin1_code":"19.0",
    "gn:asciiname":"Donggangzi",
    "gn:country_code":"CN",
    "gn:dem":14,
    "gn:feature_class":"P",
    "gn:feature_code":"PPL",
    "gn:name":"Donggangzi",
    "gn:population":0,
    "gn:timezone":"Asia/Shanghai",
    "iso:country":"CN",
    "name:zho_x_preferred":[
        "\u4e1c\u5c97\u5b50"
    ],
    "wof:name":"Donggangzi",
    "wof:placetype":"locality"
},
  "geometry": {"coordinates":[121.761,39.475],"type":"Point"}
}