{
  "type": "Feature",
  "properties": {
    "gn:admin1_code":"12",
    "gn:asciiname":"Chenxiang",
    "gn:country_code":"CN",
    "gn:dem":74,
    "gn:feature_class":"P",
    "gn:feature_code":"PPLA4",
    "gn:name":"Chenxiang",
    "gn:population":0,
    "gn:timezone":"Asia/Shanghai",
    "iso:country":"CN",
    "name:und_x_variant":[
        "Ch\u2019en-chia-hsiang",
        "Chenxiang",
        "\u9648\u5df7",
        "Chenxiang Zhen",
        "\u9648\u5df7\u9547"
    ],
    "wof:name":"Chenxiang",
    "wof:placetype":"locality"
},
  "geometry": {"coordinates":[113.76743999999999,31.47981],"type":"Point"}
}