{
  "type": "Feature",
  "properties": {
    "gn:admin1_code":"18",
    "gn:asciiname":"Chuandong",
    "gn:country_code":"CN",
    "gn:dem":1826,
    "gn:feature_class":"P",
    "gn:feature_code":"PPL",
    "gn:name":"Chuandong",
    "gn:population":0,
    "gn:timezone":"Asia/Shanghai",
    "iso:country":"CN",
    "name:zho_x_preferred":[
        "\u7a7f\u6d1e"
    ],
    "wof:name":"Chuandong",
    "wof:placetype":"locality"
},
  "geometry": {"coordinates":[105.456,26.6077],"type":"Point"}
}