{
  "type": "Feature",
  "properties": {
    "gn:admin1_code":"25",
    "gn:asciiname":"Luomizhuang Yicun",
    "gn:country_code":"CN",
    "gn:dem":133,
    "gn:feature_class":"P",
    "gn:feature_code":"PPL",
    "gn:name":"Luomizhuang Yicun",
    "gn:population":0,
    "gn:timezone":"Asia/Shanghai",
    "iso:country":"CN",
    "name:zho_x_preferred":[
        "\u7f57\u7c73\u5e84\u4e00\u6751"
    ],
    "wof:name":"Luomizhuang Yicun",
    "wof:placetype":"locality"
},
  "geometry": {"coordinates":[118.83,35.7139],"type":"Point"}
}