{
  "type": "Feature",
  "properties": {
    "gn:admin1_code":"32.0",
    "gn:asciiname":"Chushuiwan",
    "gn:country_code":"CN",
    "gn:dem":621,
    "gn:feature_class":"P",
    "gn:feature_code":"PPL",
    "gn:name":"Chushuiwan",
    "gn:population":0,
    "gn:timezone":"Asia/Shanghai",
    "iso:country":"CN",
    "name:zho_x_preferred":[
        "\u51fa\u6c34\u6e7e"
    ],
    "wof:name":"Chushuiwan",
    "wof:placetype":"locality"
},
  "geometry": {"coordinates":[104.456,28.6966],"type":"Point"}
}