{
  "type": "Feature",
  "properties": {
    "gn:admin1_code":"26.0",
    "gn:asciiname":"Dongbucun",
    "gn:country_code":"CN",
    "gn:dem":530,
    "gn:feature_class":"P",
    "gn:feature_code":"PPL",
    "gn:name":"Dongbucun",
    "gn:population":0,
    "gn:timezone":"Asia/Shanghai",
    "iso:country":"CN",
    "name:zho_x_preferred":[
        "\u8463\u5821\u6751"
    ],
    "wof:name":"Dongbucun",
    "wof:placetype":"locality"
},
  "geometry": {"coordinates":[108.05347999999999,34.40657],"type":"Point"}
}