{
  "type": "Feature",
  "properties": {
    "gn:admin1_code":"16.0",
    "gn:asciiname":"Jiaomei",
    "gn:country_code":"CN",
    "gn:dem":290,
    "gn:feature_class":"P",
    "gn:feature_code":"PPL",
    "gn:name":"Jiaomei",
    "gn:population":0,
    "gn:timezone":"Asia/Shanghai",
    "iso:country":"CN",
    "name:zho_x_preferred":[
        "\u6559\u7f8e"
    ],
    "name:zho_x_variant":[
        "\u89d2\u7f8e\u9547"
    ],
    "wof:name":"Jiaomei",
    "wof:placetype":"locality"
},
  "geometry": {"coordinates":[107.666,23.5832],"type":"Point"}
}