{
  "type": "Feature",
  "properties": {
    "gn:admin1_code":"26.0",
    "gn:asciiname":"Wuguanhekou",
    "gn:country_code":"CN",
    "gn:dem":401,
    "gn:feature_class":"P",
    "gn:feature_code":"PPL",
    "gn:name":"Wuguanhekou",
    "gn:population":0,
    "gn:timezone":"Asia/Shanghai",
    "iso:country":"CN",
    "name:zho_x_preferred":[
        "\u6b66\u5173\u6cb3\u53e3"
    ],
    "wof:name":"Wuguanhekou",
    "wof:placetype":"locality"
},
  "geometry": {"coordinates":[110.63433999999999,33.44802],"type":"Point"}
}