{
  "type": "Feature",
  "properties": {
    "gn:admin1_code":"26.0",
    "gn:asciiname":"Zhenhuaweicun",
    "gn:country_code":"CN",
    "gn:dem":404,
    "gn:feature_class":"P",
    "gn:feature_code":"PPL",
    "gn:name":"Zhenhuaweicun",
    "gn:population":0,
    "gn:timezone":"Asia/Shanghai",
    "iso:country":"CN",
    "name:zho_x_preferred":[
        "\u771f\u82b1\u7859\u6751"
    ],
    "wof:name":"Zhenhuaweicun",
    "wof:placetype":"locality"
},
  "geometry": {"coordinates":[108.66892,34.17052],"type":"Point"}
}