{
  "type": "Feature",
  "properties": {
    "gn:admin1_code":"10",
    "gn:asciiname":"Xidukouyi",
    "gn:country_code":"CN",
    "gn:dem":33,
    "gn:feature_class":"P",
    "gn:feature_code":"PPL",
    "gn:name":"Xidukouyi",
    "gn:population":0,
    "gn:timezone":"Asia/Shanghai",
    "iso:country":"CN",
    "name:zho_x_preferred":[
        "\u897f\u6e21\u53e3\u9a7f"
    ],
    "wof:name":"Xidukouyi",
    "wof:placetype":"locality"
},
  "geometry": {"coordinates":[115.831,37.0578],"type":"Point"}
}