{
  "type": "Feature",
  "properties": {
    "gn:admin1_code":"15.0",
    "gn:asciiname":"Shangheyu",
    "gn:country_code":"CN",
    "gn:dem":2128,
    "gn:feature_class":"P",
    "gn:feature_code":"PPL",
    "gn:name":"Shangheyu",
    "gn:population":0,
    "gn:timezone":"Asia/Shanghai",
    "iso:country":"CN",
    "name:und_x_variant":[
        "\u4e0a\u6cb3\u5cea"
    ],
    "wof:name":"Shangheyu",
    "wof:placetype":"locality"
},
  "geometry": {"coordinates":[104.87257,34.54881],"type":"Point"}
}