{
  "type": "Feature",
  "properties": {
    "gn:admin1_code":"16.0",
    "gn:asciiname":"Yili",
    "gn:country_code":"CN",
    "gn:dem":159,
    "gn:feature_class":"P",
    "gn:feature_code":"PPL",
    "gn:name":"Yili",
    "gn:population":0,
    "gn:timezone":"Asia/Shanghai",
    "iso:country":"CN",
    "name:ceb_x_preferred":[
        "Yili"
    ],
    "name:deu_x_preferred":[
        "Yili"
    ],
    "name:fra_x_preferred":[
        "Yili"
    ],
    "name:swe_x_preferred":[
        "Yili"
    ],
    "name:zho_x_preferred":[
        "\u76ca\u7281"
    ],
    "wof:name":"Yili",
    "wof:placetype":"locality"
},
  "geometry": {"coordinates":[108.08,23.9953],"type":"Point"}
}