{
  "type": "Feature",
  "properties": {
    "gn:admin1_code":"4.0",
    "gn:asciiname":"Xiayanqian",
    "gn:country_code":"CN",
    "gn:dem":4,
    "gn:feature_class":"P",
    "gn:feature_code":"PPL",
    "gn:name":"Xiayanqian",
    "gn:population":0,
    "gn:timezone":"Asia/Shanghai",
    "iso:country":"CN",
    "name:zho_x_preferred":[
        "\u4e0b\u5830\u524d"
    ],
    "wof:name":"Xiayanqian",
    "wof:placetype":"locality"
},
  "geometry": {"coordinates":[119.34287999999999,31.40562000000001],"type":"Point"}
}