{
  "type": "Feature",
  "properties": {
    "gn:admin1_code":"29.0",
    "gn:asciiname":"Siyong",
    "gn:country_code":"CN",
    "gn:dem":2078,
    "gn:feature_class":"P",
    "gn:feature_code":"PPL",
    "gn:name":"Siyong",
    "gn:population":0,
    "gn:timezone":"Asia/Shanghai",
    "iso:country":"CN",
    "name:zho_x_preferred":[
        "\u65af\u6d8c"
    ],
    "wof:name":"Siyong",
    "wof:placetype":"locality"
},
  "geometry": {"coordinates":[98.32080000000001,28.1227],"type":"Point"}
}