{
  "type": "Feature",
  "properties": {
    "gn:admin1_code":"1.0",
    "gn:asciiname":"Xiaochengcun",
    "gn:country_code":"CN",
    "gn:dem":24,
    "gn:feature_class":"P",
    "gn:feature_code":"PPL",
    "gn:name":"Xiaochengcun",
    "gn:population":0,
    "gn:timezone":"Asia/Shanghai",
    "iso:country":"CN",
    "name:zho_x_preferred":[
        "\u5c0f\u7a0b\u6751"
    ],
    "wof:name":"Xiaochengcun",
    "wof:placetype":"locality"
},
  "geometry": {"coordinates":[117.56426999999999,33.31463],"type":"Point"}
}