{
  "type": "Feature",
  "properties": {
    "gn:admin1_code":"11",
    "gn:asciiname":"Morong",
    "gn:country_code":"CN",
    "gn:dem":282,
    "gn:feature_class":"P",
    "gn:feature_code":"PPLA4",
    "gn:name":"Morong",
    "gn:population":0,
    "gn:timezone":"Asia/Shanghai",
    "iso:country":"CN",
    "name:und_x_variant":[
        "Morong Zhen"
    ],
    "name:zho_x_preferred":[
        "\u9ed8\u620e"
    ],
    "name:zho_x_variant":[
        "\u9ed8\u620e\u9547"
    ],
    "wof:name":"Morong",
    "wof:placetype":"locality"
},
  "geometry": {"coordinates":[109.84757,28.48878],"type":"Point"}
}