{
  "type": "Feature",
  "properties": {
    "gn:admin1_code":"10",
    "gn:asciiname":"Xingzhou",
    "gn:country_code":"CN",
    "gn:dem":475,
    "gn:feature_class":"P",
    "gn:feature_code":"PPL",
    "gn:name":"Xingzhou",
    "gn:population":0,
    "gn:timezone":"Asia/Shanghai",
    "iso:country":"CN",
    "name:fra_x_preferred":[
        "Xingzhou"
    ],
    "name:und_x_variant":[
        "Hsing-chou",
        "Xingzhou"
    ],
    "name:zho_x_preferred":[
        "\u5174\u6d32"
    ],
    "name:zho_x_variant":[
        "\u5174\u5dde"
    ],
    "wof:name":"Xingzhou",
    "wof:placetype":"locality"
},
  "geometry": {"coordinates":[117.3665,41.00681],"type":"Point"}
}