{
  "type": "Feature",
  "properties": {
    "gn:admin1_code":"26",
    "gn:asciiname":"Tieluzicun",
    "gn:country_code":"CN",
    "gn:dem":1091,
    "gn:feature_class":"P",
    "gn:feature_code":"PPL",
    "gn:name":"Tieluzicun",
    "gn:population":0,
    "gn:timezone":"Asia/Shanghai",
    "iso:country":"CN",
    "name:und_x_variant":[
        "T\u2019ieh-lu",
        "T\u2019ieh-lu-chen",
        "T\u2019ien-lu-chen",
        "\u94c1\u7089\u5b50",
        "Tieluzi",
        "Tieluzicun"
    ],
    "name:zho_x_preferred":[
        "\u94c1\u7089\u5b50\u6751"
    ],
    "wof:name":"Tieluzicun",
    "wof:placetype":"locality"
},
  "geometry": {"coordinates":[109.68116000000001,34.05522],"type":"Point"}
}