{
  "type": "Feature",
  "properties": {
    "gn:admin1_code":"4.0",
    "gn:asciiname":"Qiaotou",
    "gn:country_code":"CN",
    "gn:dem":5,
    "gn:feature_class":"P",
    "gn:feature_code":"PPLA4",
    "gn:name":"Qiaotou",
    "gn:population":0,
    "gn:timezone":"Asia/Shanghai",
    "iso:country":"CN",
    "name:ceb_x_preferred":[
        "Qiaotou"
    ],
    "name:deu_x_preferred":[
        "Qiaotou"
    ],
    "name:swe_x_preferred":[
        "Qiaotou"
    ],
    "name:und_x_variant":[
        "\u6865\u5934",
        "Qiaotou Zhen"
    ],
    "name:zho_x_preferred":[
        "\u6865\u5934\u9547"
    ],
    "wof:name":"Qiaotou",
    "wof:placetype":"locality"
},
  "geometry": {"coordinates":[120.06944,32.55],"type":"Point"}
}