{
  "type": "Feature",
  "properties": {
    "gn:admin1_code":"10",
    "gn:asciiname":"Sandaozhangzi",
    "gn:country_code":"CN",
    "gn:dem":811,
    "gn:feature_class":"P",
    "gn:feature_code":"PPL",
    "gn:name":"Sandaozhangzi",
    "gn:population":0,
    "gn:timezone":"Asia/Shanghai",
    "iso:country":"CN",
    "name:zho_x_preferred":[
        "\u4e09\u9053\u6756\u5b50"
    ],
    "wof:name":"Sandaozhangzi",
    "wof:placetype":"locality"
},
  "geometry": {"coordinates":[118.50385,41.07181],"type":"Point"}
}