{
  "type": "Feature",
  "properties": {
    "gn:admin1_code":"16",
    "gn:asciiname":"Liantang",
    "gn:cc2":"CN",
    "gn:country_code":"CN",
    "gn:dem":79,
    "gn:feature_class":"P",
    "gn:feature_code":"PPL",
    "gn:name":"Liantang",
    "gn:population":0,
    "gn:timezone":"Asia/Shanghai",
    "iso:country":"CN",
    "name:und_x_variant":[
        "Lien-t\u2019ang",
        "Lien-t\u2019ang-hs\u00fc",
        "Liantang"
    ],
    "wof:name":"Liantang",
    "wof:placetype":"locality"
},
  "geometry": {"coordinates":[109.14833,22.71083],"type":"Point"}
}