{
  "type": "Feature",
  "properties": {
    "gn:admin1_code":"10",
    "gn:asciiname":"Dabeigou",
    "gn:country_code":"CN",
    "gn:dem":1304,
    "gn:feature_class":"P",
    "gn:feature_code":"PPL",
    "gn:name":"Dabeigou",
    "gn:population":0,
    "gn:timezone":"Asia/Shanghai",
    "iso:country":"CN",
    "name:zho_x_preferred":[
        "\u5927\u5317\u6c9f"
    ],
    "wof:name":"Dabeigou",
    "wof:placetype":"locality"
},
  "geometry": {"coordinates":[115.10677,41.01627],"type":"Point"}
}