{
  "type": "Feature",
  "properties": {
    "gn:admin1_code":"29.0",
    "gn:asciiname":"Nameihanizhai",
    "gn:country_code":"CN",
    "gn:dem":1485,
    "gn:feature_class":"P",
    "gn:feature_code":"PPL",
    "gn:name":"Nameihanizhai",
    "gn:population":0,
    "gn:timezone":"Asia/Shanghai",
    "iso:country":"CN",
    "name:zho_x_preferred":[
        "\u90a3\u7f8e\u54c8\u5c3c\u5be8"
    ],
    "wof:name":"Nameihanizhai",
    "wof:placetype":"locality"
},
  "geometry": {"coordinates":[100.259,22.3155],"type":"Point"}
}