{
  "type": "Feature",
  "properties": {
    "gn:admin1_code":"24.0",
    "gn:asciiname":"Mahecun",
    "gn:country_code":"CN",
    "gn:dem":1345,
    "gn:feature_class":"P",
    "gn:feature_code":"PPL",
    "gn:name":"Mahecun",
    "gn:population":0,
    "gn:timezone":"Asia/Shanghai",
    "iso:country":"CN",
    "name:zho_x_preferred":[
        "\u9a6c\u6cb3\u6751"
    ],
    "wof:name":"Mahecun",
    "wof:placetype":"locality"
},
  "geometry": {"coordinates":[113.44438,40.28963],"type":"Point"}
}