{
  "type": "Feature",
  "properties": {
    "gn:admin1_code":"14.0",
    "gn:asciiname":"Seweile",
    "gn:country_code":"CN",
    "gn:dem":4572,
    "gn:feature_class":"P",
    "gn:feature_code":"PPL",
    "gn:name":"Seweile",
    "gn:population":0,
    "gn:timezone":"Asia/Urumqi",
    "iso:country":"CN",
    "name:zho_x_preferred":[
        "\u8272\u536b\u52d2"
    ],
    "wof:name":"Seweile",
    "wof:placetype":"locality"
},
  "geometry": {"coordinates":[90.04836,29.45315],"type":"Point"}
}