{
  "type": "Feature",
  "properties": {
    "gn:admin1_code":"14",
    "gn:asciiname":"Kageriga",
    "gn:country_code":"CN",
    "gn:dem":3882,
    "gn:feature_class":"P",
    "gn:feature_code":"PPL",
    "gn:name":"Kageriga",
    "gn:population":0,
    "gn:timezone":"Asia/Urumqi",
    "iso:country":"CN",
    "name:zho_x_preferred":[
        "\u5361\u6208\u65e5\u560e"
    ],
    "wof:name":"Kageriga",
    "wof:placetype":"locality"
},
  "geometry": {"coordinates":[89.2551,29.3145],"type":"Point"}
}