{
  "type": "Feature",
  "properties": {
    "gn:admin1_code":"13.0",
    "gn:asciiname":"Huojialeike Houyila",
    "gn:country_code":"CN",
    "gn:dem":1375,
    "gn:feature_class":"P",
    "gn:feature_code":"PPL",
    "gn:name":"Huojialeike Houyila",
    "gn:population":0,
    "gn:timezone":"Asia/Shanghai",
    "iso:country":"CN",
    "name:und_x_variant":[
        "\u970d\u52a0\u52d2\u514b\u970d\u4f0a\u62c9"
    ],
    "wof:name":"Huojialeike Houyila",
    "wof:placetype":"locality"
},
  "geometry": {"coordinates":[76.08781999999999,38.85918],"type":"Point"}
}