{
  "type": "Feature",
  "properties": {
    "gn:admin1_code":"14.0",
    "gn:asciiname":"Gunye",
    "gn:country_code":"CN",
    "gn:dem":4008,
    "gn:feature_class":"P",
    "gn:feature_code":"PPL",
    "gn:name":"Gunye",
    "gn:population":0,
    "gn:timezone":"Asia/Urumqi",
    "iso:country":"CN",
    "name:zho_x_preferred":[
        "\u6eda\u4e5f"
    ],
    "wof:name":"Gunye",
    "wof:placetype":"locality"
},
  "geometry": {"coordinates":[95.15994000000001,31.17547],"type":"Point"}
}