{
  "type": "Feature",
  "properties": {
    "gn:admin1_code":"5.0",
    "gn:asciiname":"Fumincun",
    "gn:country_code":"CN",
    "gn:dem":341,
    "gn:feature_class":"P",
    "gn:feature_code":"PPL",
    "gn:name":"Fumincun",
    "gn:population":0,
    "gn:timezone":"Asia/Shanghai",
    "iso:country":"CN",
    "name:zho_x_preferred":[
        "\u798f\u6c11\u6751"
    ],
    "wof:name":"Fumincun",
    "wof:placetype":"locality"
},
  "geometry": {"coordinates":[125.26975,42.74907],"type":"Point"}
}