{
  "type": "Feature",
  "properties": {
    "gn:admin1_code":"32.0",
    "gn:asciiname":"Dabaishan",
    "gn:country_code":"CN",
    "gn:dem":409,
    "gn:feature_class":"P",
    "gn:feature_code":"PPL",
    "gn:name":"Dabaishan",
    "gn:population":0,
    "gn:timezone":"Asia/Shanghai",
    "iso:country":"CN",
    "name:zho_x_preferred":[
        "\u5927\u767d\u5c71"
    ],
    "wof:name":"Dabaishan",
    "wof:placetype":"locality"
},
  "geometry": {"coordinates":[104.925,30.5911],"type":"Point"}
}