{
  "type": "Feature",
  "properties": {
    "gn:admin1_code":"15.0",
    "gn:asciiname":"Aihaoping",
    "gn:country_code":"CN",
    "gn:dem":1739,
    "gn:feature_class":"P",
    "gn:feature_code":"PPL",
    "gn:name":"Aihaoping",
    "gn:population":0,
    "gn:timezone":"Asia/Shanghai",
    "iso:country":"CN",
    "name:und_x_variant":[
        "\u827e\u84bf\u576a"
    ],
    "wof:name":"Aihaoping",
    "wof:placetype":"locality"
},
  "geometry": {"coordinates":[105.29634,33.13132],"type":"Point"}
}