{
  "type": "Feature",
  "properties": {
    "gn:admin1_code":"32.0",
    "gn:asciiname":"Niuchangpo",
    "gn:country_code":"CN",
    "gn:dem":2480,
    "gn:feature_class":"P",
    "gn:feature_code":"PPL",
    "gn:name":"Niuchangpo",
    "gn:population":0,
    "gn:timezone":"Asia/Shanghai",
    "iso:country":"CN",
    "name:zho_x_preferred":[
        "\u725b\u5382\u5761"
    ],
    "wof:name":"Niuchangpo",
    "wof:placetype":"locality"
},
  "geometry": {"coordinates":[102.955,31.4088],"type":"Point"}
}