{
  "type": "Feature",
  "properties": {
    "gn:admin1_code":"15.0",
    "gn:asciiname":"Youjiangpu",
    "gn:country_code":"CN",
    "gn:dem":1866,
    "gn:feature_class":"P",
    "gn:feature_code":"PPL",
    "gn:name":"Youjiangpu",
    "gn:population":0,
    "gn:timezone":"Asia/Shanghai",
    "iso:country":"CN",
    "name:und_x_variant":[
        "\u60a0\u6c5f\u94fa"
    ],
    "wof:name":"Youjiangpu",
    "wof:placetype":"locality"
},
  "geometry": {"coordinates":[105.25931,35.41365],"type":"Point"}
}