{
  "type": "Feature",
  "properties": {
    "gn:admin1_code":"5.0",
    "gn:asciiname":"Huamu Dixia",
    "gn:country_code":"CN",
    "gn:dem":290,
    "gn:feature_class":"P",
    "gn:feature_code":"PPL",
    "gn:name":"Huamu Dixia",
    "gn:population":0,
    "gn:timezone":"Asia/Shanghai",
    "iso:country":"CN",
    "name:zho_x_preferred":[
        "\u534e\u6728\u5e95\u4e0b"
    ],
    "wof:name":"Huamu Dixia",
    "wof:placetype":"locality"
},
  "geometry": {"coordinates":[126.09838000000001,44.14048],"type":"Point"}
}