{
  "type": "Feature",
  "properties": {
    "gn:admin1_code":"9.0",
    "gn:asciiname":"Xiaodougou",
    "gn:country_code":"CN",
    "gn:dem":653,
    "gn:feature_class":"P",
    "gn:feature_code":"PPL",
    "gn:name":"Xiaodougou",
    "gn:population":0,
    "gn:timezone":"Asia/Shanghai",
    "iso:country":"CN",
    "name:und_x_variant":[
        "\u5c0f\u8c46\u6c9f",
        "Xiaodougou"
    ],
    "wof:name":"Xiaodougou",
    "wof:placetype":"locality"
},
  "geometry": {"coordinates":[112.13718,33.837],"type":"Point"}
}