{
  "type": "Feature",
  "properties": {
    "gn:admin1_code":"10",
    "gn:asciiname":"Xiangtian",
    "gn:cc2":"CN",
    "gn:country_code":"CN",
    "gn:dem":848,
    "gn:feature_class":"P",
    "gn:feature_code":"PPL",
    "gn:name":"Xiangtian",
    "gn:population":0,
    "gn:timezone":"Asia/Shanghai",
    "iso:country":"CN",
    "name:und_x_variant":[
        "Hsiang-t\u2019ien",
        "Xiangtian"
    ],
    "wof:name":"Xiangtian",
    "wof:placetype":"locality"
},
  "geometry": {"coordinates":[115.95,40.81667],"type":"Point"}
}