{
  "type": "Feature",
  "properties": {
    "gn:admin1_code":"29.0",
    "gn:asciiname":"Mashuihe",
    "gn:country_code":"CN",
    "gn:dem":2238,
    "gn:feature_class":"P",
    "gn:feature_code":"PPL",
    "gn:name":"Mashuihe",
    "gn:population":0,
    "gn:timezone":"Asia/Shanghai",
    "iso:country":"CN",
    "name:zho_x_preferred":[
        "\u9a6c\u6c34\u6cb3"
    ],
    "wof:name":"Mashuihe",
    "wof:placetype":"locality"
},
  "geometry": {"coordinates":[102.48699999999999,25.059],"type":"Point"}
}