{
  "type": "Feature",
  "properties": {
    "gn:admin1_code":"18",
    "gn:asciiname":"Dayuantou",
    "gn:country_code":"CN",
    "gn:dem":1754,
    "gn:feature_class":"P",
    "gn:feature_code":"PPL",
    "gn:name":"Dayuantou",
    "gn:population":0,
    "gn:timezone":"Asia/Shanghai",
    "iso:country":"CN",
    "name:zho_x_preferred":[
        "\u5927\u56ed\u5934"
    ],
    "wof:name":"Dayuantou",
    "wof:placetype":"locality"
},
  "geometry": {"coordinates":[105.65600000000001,26.6264],"type":"Point"}
}