{
  "type": "Feature",
  "properties": {
    "gn:admin1_code":"7.0",
    "gn:asciiname":"Xiliang",
    "gn:country_code":"CN",
    "gn:dem":6,
    "gn:feature_class":"P",
    "gn:feature_code":"PPL",
    "gn:name":"Xiliang",
    "gn:population":0,
    "gn:timezone":"Asia/Shanghai",
    "iso:country":"CN",
    "name:zho_x_preferred":[
        "\u897f\u826f"
    ],
    "wof:name":"Xiliang",
    "wof:placetype":"locality"
},
  "geometry": {"coordinates":[117.81887999999999,24.45764],"type":"Point"}
}