{
  "type": "Feature",
  "properties": {
    "gn:admin1_code":"31",
    "gn:asciiname":"Hanmo",
    "gn:country_code":"CN",
    "gn:dem":102,
    "gn:feature_class":"P",
    "gn:feature_code":"PPL",
    "gn:name":"Hanmo",
    "gn:population":0,
    "gn:timezone":"Asia/Shanghai",
    "iso:country":"CN",
    "name:und_x_variant":[
        "\u7ff0\u58a8",
        "Dunmu"
    ],
    "wof:name":"Hanmo",
    "wof:placetype":"locality"
},
  "geometry": {"coordinates":[109.68425000000001,19.65371],"type":"Point"}
}