{
  "type": "Feature",
  "properties": {
    "gn:admin1_code":"24.0",
    "gn:asciiname":"Gedao",
    "gn:country_code":"CN",
    "gn:dem":1434,
    "gn:feature_class":"P",
    "gn:feature_code":"PPL",
    "gn:name":"Gedao",
    "gn:population":0,
    "gn:timezone":"Asia/Shanghai",
    "iso:country":"CN",
    "name:und_x_variant":[
        "\u6208\u9053"
    ],
    "wof:name":"Gedao",
    "wof:placetype":"locality"
},
  "geometry": {"coordinates":[112.81577,39.76079],"type":"Point"}
}