{
  "type": "Feature",
  "properties": {
    "gn:admin1_code":"19.0",
    "gn:asciiname":"Nandiaohuangzicun",
    "gn:country_code":"CN",
    "gn:dem":250,
    "gn:feature_class":"P",
    "gn:feature_code":"PPL",
    "gn:name":"Nandiaohuangzicun",
    "gn:population":0,
    "gn:timezone":"Asia/Shanghai",
    "iso:country":"CN",
    "name:zho_x_preferred":[
        "\u5357\u540a\u5e4c\u5b50\u6751"
    ],
    "wof:name":"Nandiaohuangzicun",
    "wof:placetype":"locality"
},
  "geometry": {"coordinates":[125.08499999999999,40.7952],"type":"Point"}
}