{
  "type": "Feature",
  "properties": {
    "gn:admin1_code":"19.0",
    "gn:asciiname":"Yuanbaoshan",
    "gn:country_code":"CN",
    "gn:dem":230,
    "gn:feature_class":"P",
    "gn:feature_code":"PPL",
    "gn:name":"Yuanbaoshan",
    "gn:population":0,
    "gn:timezone":"Asia/Shanghai",
    "iso:country":"CN",
    "name:zho_x_preferred":[
        "\u5143\u5b9d\u5c71"
    ],
    "wof:name":"Yuanbaoshan",
    "wof:placetype":"locality"
},
  "geometry": {"coordinates":[121.86035,42.03397],"type":"Point"}
}