{
  "type": "Feature",
  "properties": {
    "gn:admin1_code":"15.0",
    "gn:asciiname":"Longfantou",
    "gn:country_code":"CN",
    "gn:dem":1252,
    "gn:feature_class":"P",
    "gn:feature_code":"PPL",
    "gn:name":"Longfantou",
    "gn:population":0,
    "gn:timezone":"Asia/Shanghai",
    "iso:country":"CN",
    "name:zho_x_preferred":[
        "\u9f99\u7ffb\u5934"
    ],
    "wof:name":"Longfantou",
    "wof:placetype":"locality"
},
  "geometry": {"coordinates":[107.627,35.1575],"type":"Point"}
}