{
  "type": "Feature",
  "properties": {
    "gn:admin1_code":"21.0",
    "gn:asciiname":"Tongnan Sandui",
    "gn:country_code":"CN",
    "gn:dem":1110,
    "gn:feature_class":"P",
    "gn:feature_code":"PPLF",
    "gn:name":"Tongnan Sandui",
    "gn:population":0,
    "gn:timezone":"Asia/Shanghai",
    "iso:country":"CN",
    "name:zho_x_preferred":[
        "\u901a\u5357\u4e09\u961f"
    ],
    "wof:name":"Tongnan Sandui",
    "wof:placetype":"locality"
},
  "geometry": {"coordinates":[106.458,38.4571],"type":"Point"}
}