{
  "type": "Feature",
  "properties": {
    "gn:admin1_code":"30.0",
    "gn:asciiname":"Waheliao",
    "gn:country_code":"CN",
    "gn:dem":37,
    "gn:feature_class":"P",
    "gn:feature_code":"PPL",
    "gn:name":"Waheliao",
    "gn:population":0,
    "gn:timezone":"Asia/Shanghai",
    "iso:country":"CN",
    "name:zho_x_preferred":[
        "\u74e6\u79be\u5bee"
    ],
    "wof:name":"Waheliao",
    "wof:placetype":"locality"
},
  "geometry": {"coordinates":[114.6972,23.06787000000001],"type":"Point"}
}