{
  "type": "Feature",
  "properties": {
    "gn:admin1_code":"4.0",
    "gn:asciiname":"Qiuyancun",
    "gn:country_code":"CN",
    "gn:dem":53,
    "gn:feature_class":"P",
    "gn:feature_code":"PPL",
    "gn:name":"Qiuyancun",
    "gn:population":0,
    "gn:timezone":"Asia/Shanghai",
    "iso:country":"CN",
    "name:zho_x_preferred":[
        "\u79cb\u71d5\u6751"
    ],
    "wof:name":"Qiuyancun",
    "wof:placetype":"locality"
},
  "geometry": {"coordinates":[118.67100000000001,32.87333],"type":"Point"}
}