{
  "type": "Feature",
  "properties": {
    "gn:admin1_code":"14.0",
    "gn:asciiname":"Nachacun",
    "gn:country_code":"CN",
    "gn:dem":4762,
    "gn:feature_class":"P",
    "gn:feature_code":"PPL",
    "gn:name":"Nachacun",
    "gn:population":0,
    "gn:timezone":"Asia/Urumqi",
    "iso:country":"CN",
    "name:zho_x_preferred":[
        "\u90a3\u67e5\u6751"
    ],
    "wof:name":"Nachacun",
    "wof:placetype":"locality"
},
  "geometry": {"coordinates":[92.38311,30.69126],"type":"Point"}
}