{
  "type": "Feature",
  "properties": {
    "gn:admin1_code":"32.0",
    "gn:asciiname":"Sandouzhong",
    "gn:country_code":"CN",
    "gn:dem":674,
    "gn:feature_class":"P",
    "gn:feature_code":"PPL",
    "gn:name":"Sandouzhong",
    "gn:population":0,
    "gn:timezone":"Asia/Shanghai",
    "iso:country":"CN",
    "name:zho_x_preferred":[
        "\u4e09\u6597\u79cd"
    ],
    "wof:name":"Sandouzhong",
    "wof:placetype":"locality"
},
  "geometry": {"coordinates":[103.4712,29.30121],"type":"Point"}
}