{
  "type": "Feature",
  "properties": {
    "gn:admin1_code":"4.0",
    "gn:asciiname":"Sanjiawang",
    "gn:country_code":"CN",
    "gn:dem":4,
    "gn:feature_class":"P",
    "gn:feature_code":"PPL",
    "gn:name":"Sanjiawang",
    "gn:population":0,
    "gn:timezone":"Asia/Shanghai",
    "iso:country":"CN",
    "name:zho_x_preferred":[
        "Sanjiawang"
    ],
    "name:zho_x_variant":[
        "\u4e09\u5bb6\u738b"
    ],
    "wof:name":"Sanjiawang",
    "wof:placetype":"locality"
},
  "geometry": {"coordinates":[119.15985999999999,33.18028],"type":"Point"}
}