{
  "type": "Feature",
  "properties": {
    "gn:admin1_code":"4.0",
    "gn:asciiname":"Bailu",
    "gn:country_code":"CN",
    "gn:dem":14,
    "gn:feature_class":"P",
    "gn:feature_code":"PPL",
    "gn:name":"Bailu",
    "gn:population":0,
    "gn:timezone":"Asia/Shanghai",
    "iso:country":"CN",
    "name:deu_x_preferred":[
        "Bailu"
    ],
    "name:swe_x_preferred":[
        "Bailu"
    ],
    "name:zho_x_preferred":[
        "\u767d\u9732"
    ],
    "wof:name":"Bailu",
    "wof:placetype":"locality"
},
  "geometry": {"coordinates":[119.46149,32.10222],"type":"Point"}
}