{
  "type": "Feature",
  "properties": {
    "gn:admin1_code":"30.0",
    "gn:asciiname":"Boxia",
    "gn:country_code":"CN",
    "gn:dem":98,
    "gn:feature_class":"P",
    "gn:feature_code":"PPL",
    "gn:name":"Boxia",
    "gn:population":0,
    "gn:timezone":"Asia/Shanghai",
    "iso:country":"CN",
    "name:zho_x_preferred":[
        "\u535a\u4e0b"
    ],
    "wof:name":"Boxia",
    "wof:placetype":"locality"
},
  "geometry": {"coordinates":[113.81471999999999,24.32083],"type":"Point"}
}