{
  "type": "Feature",
  "properties": {
    "gn:admin1_code":"3.0",
    "gn:asciiname":"Shangxiaoshui",
    "gn:country_code":"CN",
    "gn:dem":129,
    "gn:feature_class":"P",
    "gn:feature_code":"PPL",
    "gn:name":"Shangxiaoshui",
    "gn:population":0,
    "gn:timezone":"Asia/Shanghai",
    "iso:country":"CN",
    "name:zho_x_preferred":[
        "\u4e0a\u5c0f\u6c34"
    ],
    "wof:name":"Shangxiaoshui",
    "wof:placetype":"locality"
},
  "geometry": {"coordinates":[113.738,27.8997],"type":"Point"}
}