{
  "type": "Feature",
  "properties": {
    "gn:admin1_code":"21.0",
    "gn:asciiname":"Lingyang",
    "gn:country_code":"CN",
    "gn:dem":1210,
    "gn:feature_class":"P",
    "gn:feature_code":"PPL",
    "gn:name":"Lingyang",
    "gn:population":0,
    "gn:timezone":"Asia/Shanghai",
    "iso:country":"CN",
    "name:deu_x_preferred":[
        "Lingyang"
    ],
    "name:zho_x_preferred":[
        "\u7f9a\u7f8a"
    ],
    "wof:name":"Lingyang",
    "wof:placetype":"locality"
},
  "geometry": {"coordinates":[105.396,37.4696],"type":"Point"}
}