{
  "type": "Feature",
  "properties": {
    "gn:admin1_code":"07",
    "gn:asciiname":"Jiao'an",
    "gn:country_code":"CN",
    "gn:dem":912,
    "gn:feature_class":"P",
    "gn:feature_code":"PPL",
    "gn:name":"Jiao\u2019an",
    "gn:population":0,
    "gn:timezone":"Asia/Shanghai",
    "iso:country":"CN",
    "name:und_x_variant":[
        "Jiao\u2019an"
    ],
    "name:zho_x_preferred":[
        "\u89d2\u57b5"
    ],
    "wof:name":"Jiao'an",
    "wof:placetype":"locality"
},
  "geometry": {"coordinates":[117.80098,25.29923],"type":"Point"}
}