{
  "type": "Feature",
  "properties": {
    "gn:admin1_code":"16.0",
    "gn:asciiname":"Maogongshan",
    "gn:country_code":"CN",
    "gn:dem":98,
    "gn:feature_class":"P",
    "gn:feature_code":"PPL",
    "gn:name":"Maogongshan",
    "gn:population":0,
    "gn:timezone":"Asia/Shanghai",
    "iso:country":"CN",
    "name:zho_x_preferred":[
        "\u732b\u516c\u5c71"
    ],
    "wof:name":"Maogongshan",
    "wof:placetype":"locality"
},
  "geometry": {"coordinates":[109.398,24.2237],"type":"Point"}
}