{
  "type": "Feature",
  "properties": {
    "gn:admin1_code":"26",
    "gn:asciiname":"Dama",
    "gn:country_code":"CN",
    "gn:dem":572,
    "gn:feature_class":"P",
    "gn:feature_code":"PPL",
    "gn:name":"Dama",
    "gn:population":0,
    "gn:timezone":"Asia/Shanghai",
    "iso:country":"CN",
    "name:und_x_variant":[
        "\u5927\u9a6c"
    ],
    "name:zho_x_preferred":[
        "\u5927\u9a6c"
    ],
    "wof:name":"Dama",
    "wof:placetype":"locality"
},
  "geometry": {"coordinates":[108.31222,34.40306],"type":"Point"}
}