{
  "type": "Feature",
  "properties": {
    "gn:admin1_code":"7.0",
    "gn:asciiname":"Shuizhuyang",
    "gn:country_code":"CN",
    "gn:dem":1088,
    "gn:feature_class":"P",
    "gn:feature_code":"PPL",
    "gn:name":"Shuizhuyang",
    "gn:population":0,
    "gn:timezone":"Asia/Shanghai",
    "iso:country":"CN",
    "name:zho_x_preferred":[
        "\u6c34\u7af9\u6d0b"
    ],
    "wof:name":"Shuizhuyang",
    "wof:placetype":"locality"
},
  "geometry": {"coordinates":[119.09263,27.00235],"type":"Point"}
}