{
  "type": "Feature",
  "properties": {
    "gn:admin1_code":"25",
    "gn:asciiname":"Yuanhuangyu",
    "gn:country_code":"CN",
    "gn:dem":58,
    "gn:feature_class":"P",
    "gn:feature_code":"PPL",
    "gn:name":"Yuanhuangyu",
    "gn:population":0,
    "gn:timezone":"Asia/Shanghai",
    "iso:country":"CN",
    "name:zho_x_preferred":[
        "\u8881\u9ec4\u5cea"
    ],
    "wof:name":"Yuanhuangyu",
    "wof:placetype":"locality"
},
  "geometry": {"coordinates":[118.806,34.9255],"type":"Point"}
}