{
  "type": "Feature",
  "properties": {
    "gn:admin1_code":"15.0",
    "gn:asciiname":"Honghezi",
    "gn:country_code":"CN",
    "gn:dem":2084,
    "gn:feature_class":"P",
    "gn:feature_code":"PPL",
    "gn:name":"Honghezi",
    "gn:population":0,
    "gn:timezone":"Asia/Shanghai",
    "iso:country":"CN",
    "name:zho_x_preferred":[
        "\u7ea2\u6cb3\u5b50"
    ],
    "wof:name":"Honghezi",
    "wof:placetype":"locality"
},
  "geometry": {"coordinates":[104.402,35.4812],"type":"Point"}
}