{
  "type": "Feature",
  "properties": {
    "gn:admin1_code":"24",
    "gn:asciiname":"Zhoushizhuang",
    "gn:country_code":"CN",
    "gn:dem":1132,
    "gn:feature_class":"P",
    "gn:feature_code":"PPLA4",
    "gn:name":"Zhoushizhuang",
    "gn:population":0,
    "gn:timezone":"Asia/Shanghai",
    "iso:country":"CN",
    "name:und_x_variant":[
        "Chou-shih-chuang",
        "Zhoushizhuang",
        "\u5468\u58eb\u5e84",
        "Zhoushizhuang Zhen",
        "\u5468\u58eb\u5e84\u9547"
    ],
    "wof:name":"Zhoushizhuang",
    "wof:placetype":"locality"
},
  "geometry": {"coordinates":[113.46611,40.11389000000001],"type":"Point"}
}