{
  "type": "Feature",
  "properties": {
    "gn:admin1_code":"15.0",
    "gn:asciiname":"Mami",
    "gn:country_code":"CN",
    "gn:dem":2542,
    "gn:feature_class":"P",
    "gn:feature_code":"PPL",
    "gn:name":"Mami",
    "gn:population":0,
    "gn:timezone":"Asia/Shanghai",
    "iso:country":"CN",
    "name:ceb_x_preferred":[
        "Mami"
    ],
    "name:deu_x_preferred":[
        "Mami"
    ],
    "name:eus_x_preferred":[
        "Mami"
    ],
    "name:fas_x_preferred":[
        "\u0645\u0645\u06cc"
    ],
    "name:fra_x_preferred":[
        "Mami"
    ],
    "name:hun_x_preferred":[
        "Mami"
    ],
    "name:por_x_preferred":[
        "Mami"
    ],
    "name:swe_x_preferred":[
        "Mami"
    ],
    "name:tur_x_preferred":[
        "Mami"
    ],
    "name:und_x_variant":[
        "\u561b\u54aa"
    ],
    "wof:name":"Mami",
    "wof:placetype":"locality"
},
  "geometry": {"coordinates":[104.40761999999999,34.65916],"type":"Point"}
}