{
  "type": "Feature",
  "properties": {
    "gn:admin1_code":"32.0",
    "gn:asciiname":"Xiabatang",
    "gn:country_code":"CN",
    "gn:dem":1163,
    "gn:feature_class":"P",
    "gn:feature_code":"PPL",
    "gn:name":"Xiabatang",
    "gn:population":0,
    "gn:timezone":"Asia/Shanghai",
    "iso:country":"CN",
    "name:zho_x_preferred":[
        "\u4e0b\u575d\u5858"
    ],
    "wof:name":"Xiabatang",
    "wof:placetype":"locality"
},
  "geometry": {"coordinates":[101.86072,26.61461],"type":"Point"}
}