{
  "type": "Feature",
  "properties": {
    "gn:admin1_code":"32.0",
    "gn:asciiname":"Mingjuesi",
    "gn:country_code":"CN",
    "gn:dem":335,
    "gn:feature_class":"P",
    "gn:feature_code":"PPL",
    "gn:name":"Mingjuesi",
    "gn:population":0,
    "gn:timezone":"Asia/Shanghai",
    "iso:country":"CN",
    "name:zho_x_preferred":[
        "\u660e\u89c9\u5bfa"
    ],
    "wof:name":"Mingjuesi",
    "wof:placetype":"locality"
},
  "geometry": {"coordinates":[105.38612999999999,30.39375],"type":"Point"}
}