{
  "type": "Feature",
  "properties": {
    "gn:admin1_code":"9",
    "gn:asciiname":"Liugudui",
    "gn:country_code":"CN",
    "gn:dem":59,
    "gn:feature_class":"P",
    "gn:feature_code":"PPL",
    "gn:name":"Liugudui",
    "gn:population":0,
    "gn:timezone":"Asia/Shanghai",
    "iso:country":"CN",
    "name:zho_x_preferred":[
        "\u5218\u580c\u5806"
    ],
    "wof:name":"Liugudui",
    "wof:placetype":"locality"
},
  "geometry": {"coordinates":[115.13827999999999,35.54697],"type":"Point"}
}