{
  "type": "Feature",
  "properties": {
    "gn:admin1_code":"7.0",
    "gn:asciiname":"Da'nanqi",
    "gn:country_code":"CN",
    "gn:dem":579,
    "gn:feature_class":"P",
    "gn:feature_code":"PPL",
    "gn:name":"Da\u2019nanqi",
    "gn:population":0,
    "gn:timezone":"Asia/Shanghai",
    "iso:country":"CN",
    "name:zho_x_preferred":[
        "\u5927\u96be\u5898"
    ],
    "name:zho_x_variant":[
        "Da\u2019nanqi"
    ],
    "wof:name":"Da'nanqi",
    "wof:placetype":"locality"
},
  "geometry": {"coordinates":[117.9104,27.72238],"type":"Point"}
}