{
  "type": "Feature",
  "properties": {
    "gn:admin1_code":"18",
    "gn:asciiname":"Tangchi",
    "gn:country_code":"CN",
    "gn:dem":816,
    "gn:feature_class":"P",
    "gn:feature_code":"PPL",
    "gn:name":"Tangchi",
    "gn:population":0,
    "gn:timezone":"Asia/Shanghai",
    "iso:country":"CN",
    "name:zho_x_preferred":[
        "\u5858\u6c60"
    ],
    "wof:name":"Tangchi",
    "wof:placetype":"locality"
},
  "geometry": {"coordinates":[107.97799999999999,27.7842],"type":"Point"}
}