{
  "type": "Feature",
  "properties": {
    "gn:admin1_code":"20",
    "gn:asciiname":"Narin Nur",
    "gn:cc2":"CN",
    "gn:country_code":"CN",
    "gn:dem":1365,
    "gn:feature_class":"P",
    "gn:feature_code":"PPL",
    "gn:name":"Narin Nur",
    "gn:population":0,
    "gn:timezone":"Asia/Shanghai",
    "iso:country":"CN",
    "name:und_x_variant":[
        "Na-lin-nao",
        "Narin Nur"
    ],
    "wof:name":"Narin Nur",
    "wof:placetype":"locality"
},
  "geometry": {"coordinates":[108.26472,39.39556],"type":"Point"}
}