{
  "type": "Feature",
  "properties": {
    "gn:admin1_code":"9.0",
    "gn:asciiname":"Zhongwei",
    "gn:country_code":"CN",
    "gn:dem":804,
    "gn:feature_class":"P",
    "gn:feature_code":"PPL",
    "gn:name":"Zhongwei",
    "gn:population":0,
    "gn:timezone":"Asia/Shanghai",
    "iso:country":"CN",
    "name:zho_x_preferred":[
        "\u4e2d\u56f4"
    ],
    "wof:name":"Zhongwei",
    "wof:placetype":"locality"
},
  "geometry": {"coordinates":[113.16947,35.32449000000001],"type":"Point"}
}