{
  "type": "Feature",
  "properties": {
    "gn:admin1_code":"9.0",
    "gn:asciiname":"Zhongwei",
    "gn:country_code":"CN",
    "gn:dem":804,
    "gn:feature_class":"P",
    "gn:feature_code":"PPL",
    "gn:name":"Zhongwei",
    "gn:population":0,
    "gn:timezone":"Asia/Shanghai",
    "iso:country":"CN",
    "name:ara_x_preferred":[
        "\u062a\u0634\u0648\u0646\u063a \u0648\u0649"
    ],
    "name:cdo_x_preferred":[
        "D\u1e73\u0306ng-\u00f4i"
    ],
    "name:ces_x_preferred":[
        "\u010cung-wej"
    ],
    "name:dan_x_preferred":[
        "Zhongwei"
    ],
    "name:deu_x_preferred":[
        "Zhongwei"
    ],
    "name:eus_x_preferred":[
        "Zhongwei"
    ],
    "name:fas_x_preferred":[
        "\u0698\u0627\u0646\u06af\u0648\u06cc"
    ],
    "name:fin_x_preferred":[
        "Zhongwei"
    ],
    "name:fra_x_preferred":[
        "Zhongwei"
    ],
    "name:ita_x_preferred":[
        "Zhongwei"
    ],
    "name:jpn_x_preferred":[
        "\u4e2d\u885b\u5e02"
    ],
    "name:kik_x_preferred":[
        "Zhongwei"
    ],
    "name:kor_x_preferred":[
        "\uc911\uc6e8\uc774\uc2dc"
    ],
    "name:nld_x_preferred":[
        "Zhongwei"
    ],
    "name:nor_x_preferred":[
        "Zhongwei"
    ],
    "name:pol_x_preferred":[
        "Zhongwei"
    ],
    "name:por_x_preferred":[
        "Zhongwei"
    ],
    "name:rus_x_preferred":[
        "\u0427\u0436\u0443\u043d\u0432\u044d\u0439"
    ],
    "name:spa_x_preferred":[
        "Zhongwei"
    ],
    "name:swe_x_preferred":[
        "Zhongwei"
    ],
    "name:tur_x_preferred":[
        "Zhongwei"
    ],
    "name:urd_x_preferred":[
        "\u0698\u0648\u0646\u06af\u0648\u0626\u06cc"
    ],
    "name:vie_x_preferred":[
        "Trung V\u1ec7"
    ],
    "name:zho_x_preferred":[
        "\u4e2d\u56f4"
    ],
    "name:zho_x_variant":[
        "\u4e2d\u536b\u5e02"
    ],
    "wof:name":"Zhongwei",
    "wof:placetype":"locality"
},
  "geometry": {"coordinates":[113.16947,35.32449000000001],"type":"Point"}
}