{
  "type": "Feature",
  "properties": {
    "gn:admin1_code":"32.0",
    "gn:asciiname":"Yaquewo",
    "gn:country_code":"CN",
    "gn:dem":1147,
    "gn:feature_class":"P",
    "gn:feature_code":"PPL",
    "gn:name":"Yaquewo",
    "gn:population":0,
    "gn:timezone":"Asia/Shanghai",
    "iso:country":"CN",
    "name:zho_x_preferred":[
        "\u96c5\u96c0\u7a9d"
    ],
    "wof:name":"Yaquewo",
    "wof:placetype":"locality"
},
  "geometry": {"coordinates":[103.3683,28.8242],"type":"Point"}
}