{
  "type": "Feature",
  "properties": {
    "gn:admin1_code":"19.0",
    "gn:asciiname":"Lishu Dixia",
    "gn:country_code":"CN",
    "gn:dem":152,
    "gn:feature_class":"P",
    "gn:feature_code":"PPL",
    "gn:name":"Lishu Dixia",
    "gn:population":0,
    "gn:timezone":"Asia/Shanghai",
    "iso:country":"CN",
    "name:zho_x_preferred":[
        "\u68a8\u6811\u5e95\u4e0b"
    ],
    "wof:name":"Lishu Dixia",
    "wof:placetype":"locality"
},
  "geometry": {"coordinates":[123.13822,40.34832],"type":"Point"}
}