{
  "type": "Feature",
  "properties": {
    "gn:admin1_code":"9.0",
    "gn:asciiname":"Huilongmiao",
    "gn:country_code":"CN",
    "gn:dem":297,
    "gn:feature_class":"P",
    "gn:feature_code":"PPL",
    "gn:name":"Huilongmiao",
    "gn:population":0,
    "gn:timezone":"Asia/Shanghai",
    "iso:country":"CN",
    "name:und_x_variant":[
        "\u56de\u9f99\u5e99",
        "Huilongmiao"
    ],
    "wof:name":"Huilongmiao",
    "wof:placetype":"locality"
},
  "geometry": {"coordinates":[112.81088,33.98534],"type":"Point"}
}