{
  "type": "Feature",
  "properties": {
    "gn:admin1_code":"25",
    "gn:asciiname":"Poshiqiao",
    "gn:country_code":"CN",
    "gn:dem":58,
    "gn:feature_class":"P",
    "gn:feature_code":"PPL",
    "gn:name":"Poshiqiao",
    "gn:population":0,
    "gn:timezone":"Asia/Shanghai",
    "iso:country":"CN",
    "name:zho_x_preferred":[
        "\u5761\u77f3\u6865"
    ],
    "wof:name":"Poshiqiao",
    "wof:placetype":"locality"
},
  "geometry": {"coordinates":[118.70699999999999,34.8428],"type":"Point"}
}