{
  "type": "Feature",
  "properties": {
    "gn:admin1_code":"19",
    "gn:asciiname":"Ankang",
    "gn:cc2":"CN",
    "gn:country_code":"CN",
    "gn:dem":8,
    "gn:feature_class":"P",
    "gn:feature_code":"PPL",
    "gn:name":"Ankang",
    "gn:population":0,
    "gn:timezone":"Asia/Shanghai",
    "iso:country":"CN",
    "name:und_x_variant":[
        "Dadonggang",
        "Chao-shih-kou",
        "Ankang"
    ],
    "wof:name":"Ankang",
    "wof:placetype":"locality"
},
  "geometry": {"coordinates":[124.20667,39.88833],"type":"Point"}
}