{
  "type": "Feature",
  "properties": {
    "gn:admin1_code":"29.0",
    "gn:asciiname":"Xiaowa",
    "gn:country_code":"CN",
    "gn:dem":1643,
    "gn:feature_class":"P",
    "gn:feature_code":"PPL",
    "gn:name":"Xiaowa",
    "gn:population":0,
    "gn:timezone":"Asia/Shanghai",
    "iso:country":"CN",
    "name:zho_x_preferred":[
        "\u5c0f\u6d3c"
    ],
    "wof:name":"Xiaowa",
    "wof:placetype":"locality"
},
  "geometry": {"coordinates":[102.104,25.0332],"type":"Point"}
}