{
  "type": "Feature",
  "properties": {
    "gn:admin1_code":"10",
    "gn:asciiname":"Zhangjinggou",
    "gn:country_code":"CN",
    "gn:dem":559,
    "gn:feature_class":"P",
    "gn:feature_code":"PPL",
    "gn:name":"Zhangjinggou",
    "gn:population":0,
    "gn:timezone":"Asia/Shanghai",
    "iso:country":"CN",
    "name:zho_x_preferred":[
        "\u5f20\u4e95\u6c9f"
    ],
    "wof:name":"Zhangjinggou",
    "wof:placetype":"locality"
},
  "geometry": {"coordinates":[113.98699999999999,37.9339],"type":"Point"}
}