{
  "type": "Feature",
  "properties": {
    "gn:admin1_code":"30.0",
    "gn:asciiname":"Zengjiangbu",
    "gn:country_code":"CN",
    "gn:dem":308,
    "gn:feature_class":"P",
    "gn:feature_code":"PPL",
    "gn:name":"Zengjiangbu",
    "gn:population":0,
    "gn:timezone":"Asia/Shanghai",
    "iso:country":"CN",
    "name:zho_x_preferred":[
        "\u589e\u6c5f\u5e03"
    ],
    "wof:name":"Zengjiangbu",
    "wof:placetype":"locality"
},
  "geometry": {"coordinates":[115.3389,23.9096],"type":"Point"}
}