{
  "type": "Feature",
  "properties": {
    "gn:admin1_code":"25.0",
    "gn:asciiname":"Chenzhuang",
    "gn:country_code":"CN",
    "gn:dem":12,
    "gn:feature_class":"P",
    "gn:feature_code":"PPL",
    "gn:name":"Chenzhuang",
    "gn:population":0,
    "gn:timezone":"Asia/Shanghai",
    "iso:country":"CN",
    "name:zho_x_preferred":[
        "\u9648\u5e84"
    ],
    "wof:name":"Chenzhuang",
    "wof:placetype":"locality"
},
  "geometry": {"coordinates":[119.61966,36.43993],"type":"Point"}
}