{
  "type": "Feature",
  "properties": {
    "gn:admin1_code":"30",
    "gn:asciiname":"Tukeng",
    "gn:country_code":"CN",
    "gn:dem":32,
    "gn:feature_class":"P",
    "gn:feature_code":"PPL",
    "gn:name":"Tukeng",
    "gn:population":0,
    "gn:timezone":"Asia/Shanghai",
    "iso:country":"CN",
    "name:zho_x_preferred":[
        "\u6d82\u5751"
    ],
    "wof:name":"Tukeng",
    "wof:placetype":"locality"
},
  "geometry": {"coordinates":[116.2045,23.24518],"type":"Point"}
}