{
  "type": "Feature",
  "properties": {
    "gn:admin1_code":"29.0",
    "gn:asciiname":"Yunlong",
    "gn:cc2":"CN",
    "gn:country_code":"CN",
    "gn:dem":2009,
    "gn:feature_class":"P",
    "gn:feature_code":"PPL",
    "gn:name":"Yunlong",
    "gn:population":0,
    "gn:timezone":"Asia/Shanghai",
    "iso:country":"CN",
    "name:und_x_variant":[
        "Mo-ch\u2019u",
        "Y\u00fcn-lung",
        "Shwangpo",
        "Y\u00fcn-lung-chen",
        "Shuang-pei",
        "Shuang-pai",
        "Shuang-po",
        "Shuang-pai-hsien",
        "Shwangpak-hsien",
        "Yunlong"
    ],
    "wof:name":"Yunlong",
    "wof:placetype":"locality"
},
  "geometry": {"coordinates":[101.59999999999999,24.83333],"type":"Point"}
}