{
  "type": "Feature",
  "properties": {
    "gn:admin1_code":"25",
    "gn:asciiname":"Nanhumen",
    "gn:country_code":"CN",
    "gn:dem":227,
    "gn:feature_class":"P",
    "gn:feature_code":"PPL",
    "gn:name":"Nanhumen",
    "gn:population":0,
    "gn:timezone":"Asia/Shanghai",
    "iso:country":"CN",
    "name:zho_x_preferred":[
        "\u5357\u864e\u95e8"
    ],
    "wof:name":"Nanhumen",
    "wof:placetype":"locality"
},
  "geometry": {"coordinates":[116.73099999999999,36.1012],"type":"Point"}
}