{
  "type": "Feature",
  "properties": {
    "gn:admin1_code":"2.0",
    "gn:asciiname":"Dacaikou",
    "gn:country_code":"CN",
    "gn:dem":367,
    "gn:feature_class":"P",
    "gn:feature_code":"PPL",
    "gn:name":"Dacaikou",
    "gn:population":0,
    "gn:timezone":"Asia/Shanghai",
    "iso:country":"CN",
    "name:zho_x_preferred":[
        "\u5927\u83dc\u53e3"
    ],
    "wof:name":"Dacaikou",
    "wof:placetype":"locality"
},
  "geometry": {"coordinates":[119.72230999999999,28.78288],"type":"Point"}
}