{
  "type": "Feature",
  "properties": {
    "gn:admin1_code":"29.0",
    "gn:asciiname":"Chunshutang",
    "gn:country_code":"CN",
    "gn:dem":2134,
    "gn:feature_class":"P",
    "gn:feature_code":"PPL",
    "gn:name":"Chunshutang",
    "gn:population":0,
    "gn:timezone":"Asia/Shanghai",
    "iso:country":"CN",
    "name:zho_x_preferred":[
        "\u693f\u6811\u5858"
    ],
    "wof:name":"Chunshutang",
    "wof:placetype":"locality"
},
  "geometry": {"coordinates":[102.67100000000001,25.3283],"type":"Point"}
}