{
  "type": "Feature",
  "properties": {
    "gn:admin1_code":"19.0",
    "gn:asciiname":"Shanggunufen",
    "gn:country_code":"CN",
    "gn:dem":223,
    "gn:feature_class":"P",
    "gn:feature_code":"PPL",
    "gn:name":"Shanggun\u00fcfen",
    "gn:population":0,
    "gn:timezone":"Asia/Shanghai",
    "iso:country":"CN",
    "name:zho_x_preferred":[
        "\u4e0a\u5b64\u5973\u575f"
    ],
    "name:zho_x_variant":[
        "Shanggun\u00fcfen"
    ],
    "wof:name":"Shanggunufen",
    "wof:placetype":"locality"
},
  "geometry": {"coordinates":[120.34520000000001,40.86541],"type":"Point"}
}