{
  "type": "Feature",
  "properties": {
    "gn:admin1_code":"18",
    "gn:asciiname":"Shiliuchong",
    "gn:country_code":"CN",
    "gn:dem":1257,
    "gn:feature_class":"P",
    "gn:feature_code":"PPL",
    "gn:name":"Shiliuchong",
    "gn:population":0,
    "gn:timezone":"Asia/Shanghai",
    "iso:country":"CN",
    "name:zho_x_preferred":[
        "\u77f3\u69b4\u51b2"
    ],
    "wof:name":"Shiliuchong",
    "wof:placetype":"locality"
},
  "geometry": {"coordinates":[106.61,25.9131],"type":"Point"}
}