{
  "type": "Feature",
  "properties": {
    "gn:admin1_code":"16",
    "gn:asciiname":"Xiongdan",
    "gn:country_code":"CN",
    "gn:dem":150,
    "gn:feature_class":"P",
    "gn:feature_code":"PPL",
    "gn:name":"Xiongdan",
    "gn:population":0,
    "gn:timezone":"Asia/Shanghai",
    "iso:country":"CN",
    "name:zho_x_preferred":[
        "\u718a\u80c6"
    ],
    "wof:name":"Xiongdan",
    "wof:placetype":"locality"
},
  "geometry": {"coordinates":[110.71299999999999,22.6503],"type":"Point"}
}