{
  "type": "Feature",
  "properties": {
    "gn:admin1_code":"15.0",
    "gn:asciiname":"Gezigou",
    "gn:country_code":"CN",
    "gn:dem":1894,
    "gn:feature_class":"P",
    "gn:feature_code":"PPL",
    "gn:name":"Gezigou",
    "gn:population":0,
    "gn:timezone":"Asia/Shanghai",
    "iso:country":"CN",
    "name:und_x_variant":[
        "\u683c\u5b50\u6c9f"
    ],
    "name:zho_x_preferred":[
        "\u683c\u5b50\u6c9f"
    ],
    "wof:name":"Gezigou",
    "wof:placetype":"locality"
},
  "geometry": {"coordinates":[104.92353,34.01779000000001],"type":"Point"}
}