{
  "type": "Feature",
  "properties": {
    "gn:admin1_code":"04",
    "gn:asciiname":"Laohuzhuang",
    "gn:cc2":"CN",
    "gn:country_code":"CN",
    "gn:dem":3,
    "gn:feature_class":"P",
    "gn:feature_code":"PPL",
    "gn:name":"Laohuzhuang",
    "gn:population":0,
    "gn:timezone":"Asia/Shanghai",
    "iso:country":"CN",
    "name:und_x_variant":[
        "Ta-hu-chuang",
        "Lao-hu-chuang",
        "Dahuzhuang",
        "Laohuzhuang",
        "\u8001\u6237\u5e84"
    ],
    "wof:name":"Laohuzhuang",
    "wof:placetype":"locality"
},
  "geometry": {"coordinates":[120.51667,32.25],"type":"Point"}
}