{
  "type": "Feature",
  "properties": {
    "gn:admin1_code":"32.0",
    "gn:asciiname":"Kuangchang",
    "gn:country_code":"CN",
    "gn:dem":335,
    "gn:feature_class":"P",
    "gn:feature_code":"PPL",
    "gn:name":"Kuangchang",
    "gn:population":0,
    "gn:timezone":"Asia/Shanghai",
    "iso:country":"CN",
    "name:zho_x_preferred":[
        "\u51b5\u573a"
    ],
    "wof:name":"Kuangchang",
    "wof:placetype":"locality"
},
  "geometry": {"coordinates":[105.30605,28.86278],"type":"Point"}
}