{
  "type": "Feature",
  "properties": {
    "gn:admin1_code":"7",
    "gn:asciiname":"Che'an",
    "gn:country_code":"CN",
    "gn:dem":14,
    "gn:feature_class":"P",
    "gn:feature_code":"PPL",
    "gn:name":"Che\u2019an",
    "gn:population":0,
    "gn:timezone":"Asia/Shanghai",
    "iso:country":"CN",
    "name:zho_x_preferred":[
        "\u8f66\u57b5"
    ],
    "name:zho_x_variant":[
        "Che\u2019an"
    ],
    "wof:name":"Che'an",
    "wof:placetype":"locality"
},
  "geometry": {"coordinates":[118.67363,24.87606],"type":"Point"}
}