{
  "type": "Feature",
  "properties": {
    "gn:admin1_code":"18",
    "gn:asciiname":"Jinjia Wanzi",
    "gn:country_code":"CN",
    "gn:dem":1714,
    "gn:feature_class":"P",
    "gn:feature_code":"PPL",
    "gn:name":"Jinjia Wanzi",
    "gn:population":0,
    "gn:timezone":"Asia/Shanghai",
    "iso:country":"CN",
    "name:zho_x_preferred":[
        "\u91d1\u5bb6\u5f2f\u5b50"
    ],
    "wof:name":"Jinjia Wanzi",
    "wof:placetype":"locality"
},
  "geometry": {"coordinates":[103.968,27.2498],"type":"Point"}
}