{
  "type": "Feature",
  "properties": {
    "gn:admin1_code":"1.0",
    "gn:asciiname":"Piliancun",
    "gn:country_code":"CN",
    "gn:dem":43,
    "gn:feature_class":"P",
    "gn:feature_code":"PPL",
    "gn:name":"Piliancun",
    "gn:population":0,
    "gn:timezone":"Asia/Shanghai",
    "iso:country":"CN",
    "name:zho_x_preferred":[
        "\u6de0\u8054\u6751"
    ],
    "wof:name":"Piliancun",
    "wof:placetype":"locality"
},
  "geometry": {"coordinates":[116.37101,31.73525],"type":"Point"}
}