{
  "type": "Feature",
  "properties": {
    "gn:admin1_code":"32.0",
    "gn:asciiname":"Dongxihe",
    "gn:country_code":"CN",
    "gn:dem":639,
    "gn:feature_class":"P",
    "gn:feature_code":"PPL",
    "gn:name":"Dongxihe",
    "gn:population":0,
    "gn:timezone":"Asia/Shanghai",
    "iso:country":"CN",
    "name:zho_x_preferred":[
        "\u4e1c\u6eaa\u6cb3"
    ],
    "wof:name":"Dongxihe",
    "wof:placetype":"locality"
},
  "geometry": {"coordinates":[105.76222,32.65752],"type":"Point"}
}