{
  "type": "Feature",
  "properties": {
    "gn:admin1_code":"32.0",
    "gn:asciiname":"Yan'erping",
    "gn:country_code":"CN",
    "gn:dem":1323,
    "gn:feature_class":"P",
    "gn:feature_code":"PPL",
    "gn:name":"Yan\u2019erping",
    "gn:population":0,
    "gn:timezone":"Asia/Shanghai",
    "iso:country":"CN",
    "name:zho_x_preferred":[
        "\u5ca9\u54a1\u576a"
    ],
    "name:zho_x_variant":[
        "Yan\u2019erping"
    ],
    "wof:name":"Yan'erping",
    "wof:placetype":"locality"
},
  "geometry": {"coordinates":[103.32552,29.45996],"type":"Point"}
}