{
  "type": "Feature",
  "properties": {
    "gn:admin1_code":"19.0",
    "gn:asciiname":"Hetaochuan",
    "gn:country_code":"CN",
    "gn:dem":177,
    "gn:feature_class":"P",
    "gn:feature_code":"PPL",
    "gn:name":"Hetaochuan",
    "gn:population":0,
    "gn:timezone":"Asia/Shanghai",
    "iso:country":"CN",
    "name:zho_x_preferred":[
        "\u6838\u6843\u5ddd"
    ],
    "wof:name":"Hetaochuan",
    "wof:placetype":"locality"
},
  "geometry": {"coordinates":[124.57917,40.86316],"type":"Point"}
}