{
  "type": "Feature",
  "properties": {
    "gn:admin1_code":"03",
    "gn:asciiname":"Changtang",
    "gn:country_code":"CN",
    "gn:dem":81,
    "gn:feature_class":"P",
    "gn:feature_code":"PPLA4",
    "gn:name":"Changtang",
    "gn:population":0,
    "gn:timezone":"Asia/Shanghai",
    "iso:country":"CN",
    "name:und_x_variant":[
        "\u957f\u5858",
        "Changtang Zhen",
        "\u957f\u5858\u9547"
    ],
    "wof:name":"Changtang",
    "wof:placetype":"locality"
},
  "geometry": {"coordinates":[114.96811,27.19188],"type":"Point"}
}