{
  "type": "Feature",
  "properties": {
    "gn:admin1_code":"12.0",
    "gn:asciiname":"Fujiaping",
    "gn:country_code":"CN",
    "gn:dem":510,
    "gn:feature_class":"P",
    "gn:feature_code":"PPL",
    "gn:name":"Fujiaping",
    "gn:population":0,
    "gn:timezone":"Asia/Shanghai",
    "iso:country":"CN",
    "name:zho_x_preferred":[
        "\u7b26\u5bb6\u576a"
    ],
    "wof:name":"Fujiaping",
    "wof:placetype":"locality"
},
  "geometry": {"coordinates":[111.21731,31.13406],"type":"Point"}
}