{
  "type": "Feature",
  "properties": {
    "gn:admin1_code":"15.0",
    "gn:asciiname":"Qingshuiling",
    "gn:country_code":"CN",
    "gn:dem":1592,
    "gn:feature_class":"P",
    "gn:feature_code":"PPL",
    "gn:name":"Qingshuiling",
    "gn:population":0,
    "gn:timezone":"Asia/Shanghai",
    "iso:country":"CN",
    "name:zho_x_preferred":[
        "\u6e05\u6c34\u5cad"
    ],
    "wof:name":"Qingshuiling",
    "wof:placetype":"locality"
},
  "geometry": {"coordinates":[106.762,35.4052],"type":"Point"}
}