{
  "type": "Feature",
  "properties": {
    "gn:admin1_code":"2.0",
    "gn:asciiname":"Shantangwan",
    "gn:country_code":"CN",
    "gn:dem":240,
    "gn:feature_class":"P",
    "gn:feature_code":"PPL",
    "gn:name":"Shantangwan",
    "gn:population":0,
    "gn:timezone":"Asia/Shanghai",
    "iso:country":"CN",
    "name:zho_x_preferred":[
        "\u5c71\u5858\u5846"
    ],
    "wof:name":"Shantangwan",
    "wof:placetype":"locality"
},
  "geometry": {"coordinates":[119.46613000000001,28.15942],"type":"Point"}
}