{
  "type": "Feature",
  "properties": {
    "gn:admin1_code":"22.0",
    "gn:asciiname":"Mayufangcun",
    "gn:country_code":"CN",
    "gn:dem":228,
    "gn:feature_class":"P",
    "gn:feature_code":"PPL",
    "gn:name":"Mayufangcun",
    "gn:population":0,
    "gn:timezone":"Asia/Shanghai",
    "iso:country":"CN",
    "name:zho_x_preferred":[
        "\u9ebb\u5cea\u623f\u6751"
    ],
    "wof:name":"Mayufangcun",
    "wof:placetype":"locality"
},
  "geometry": {"coordinates":[116.19477000000001,40.33509],"type":"Point"}
}