{
  "type": "Feature",
  "properties": {
    "gn:admin1_code":"8.0",
    "gn:asciiname":"Erpaozi",
    "gn:country_code":"CN",
    "gn:dem":208,
    "gn:feature_class":"P",
    "gn:feature_code":"PPL",
    "gn:name":"Erpaozi",
    "gn:population":0,
    "gn:timezone":"Asia/Shanghai",
    "iso:country":"CN",
    "name:zho_x_preferred":[
        "\u4e8c\u6ce1\u5b50"
    ],
    "wof:name":"Erpaozi",
    "wof:placetype":"locality"
},
  "geometry": {"coordinates":[123.94344,48.31154],"type":"Point"}
}