{
  "type": "Feature",
  "properties": {
    "gn:admin1_code":"12.0",
    "gn:asciiname":"Xigou",
    "gn:country_code":"CN",
    "gn:dem":963,
    "gn:feature_class":"P",
    "gn:feature_code":"PPL",
    "gn:name":"Xigou",
    "gn:population":0,
    "gn:timezone":"Asia/Shanghai",
    "iso:country":"CN",
    "name:zho_x_preferred":[
        "\u897f\u6c9f"
    ],
    "wof:name":"Xigou",
    "wof:placetype":"locality"
},
  "geometry": {"coordinates":[109.92834999999999,32.97579],"type":"Point"}
}