{
  "type": "Feature",
  "properties": {
    "gn:admin1_code":"11.0",
    "gn:asciiname":"Chajiapu",
    "gn:country_code":"CN",
    "gn:dem":72,
    "gn:feature_class":"P",
    "gn:feature_code":"PPL",
    "gn:name":"Chajiapu",
    "gn:population":0,
    "gn:timezone":"Asia/Shanghai",
    "iso:country":"CN",
    "name:zho_x_preferred":[
        "Chajiapu"
    ],
    "name:zho_x_variant":[
        "\u5bdf\u5bb6\u94fa"
    ],
    "wof:name":"Chajiapu",
    "wof:placetype":"locality"
},
  "geometry": {"coordinates":[111.47230999999999,29.46133],"type":"Point"}
}