{
  "type": "Feature",
  "properties": {
    "gn:admin1_code":"18",
    "gn:asciiname":"Fantianjing",
    "gn:country_code":"CN",
    "gn:dem":1124,
    "gn:feature_class":"P",
    "gn:feature_code":"PPL",
    "gn:name":"Fantianjing",
    "gn:population":0,
    "gn:timezone":"Asia/Shanghai",
    "iso:country":"CN",
    "name:zho_x_preferred":[
        "\u8303\u5929\u4e95"
    ],
    "wof:name":"Fantianjing",
    "wof:placetype":"locality"
},
  "geometry": {"coordinates":[107.467,28.9851],"type":"Point"}
}