{
  "type": "Feature",
  "properties": {
    "gn:admin1_code":"18.0",
    "gn:asciiname":"Tuanzhai",
    "gn:country_code":"CN",
    "gn:dem":526,
    "gn:feature_class":"P",
    "gn:feature_code":"PPL",
    "gn:name":"Tuanzhai",
    "gn:population":0,
    "gn:timezone":"Asia/Shanghai",
    "iso:country":"CN",
    "name:zho_x_preferred":[
        "\u56e2\u5be8"
    ],
    "wof:name":"Tuanzhai",
    "wof:placetype":"locality"
},
  "geometry": {"coordinates":[109.17400000000001,27.9607],"type":"Point"}
}