{
  "type": "Feature",
  "properties": {
    "gn:admin1_code":"14.0",
    "gn:asciiname":"Jiulangcang",
    "gn:country_code":"CN",
    "gn:dem":4882,
    "gn:feature_class":"P",
    "gn:feature_code":"PPL",
    "gn:name":"Jiulangcang",
    "gn:population":0,
    "gn:timezone":"Asia/Urumqi",
    "iso:country":"CN",
    "name:zho_x_preferred":[
        "\u4e45\u6717\u4ed3"
    ],
    "wof:name":"Jiulangcang",
    "wof:placetype":"locality"
},
  "geometry": {"coordinates":[90.12891,30.85571],"type":"Point"}
}