{
  "type": "Feature",
  "properties": {
    "gn:admin1_code":"8.0",
    "gn:asciiname":"Qianluluba Yingzi",
    "gn:country_code":"CN",
    "gn:dem":142,
    "gn:feature_class":"P",
    "gn:feature_code":"PPL",
    "gn:name":"Qianluluba Yingzi",
    "gn:population":0,
    "gn:timezone":"Asia/Shanghai",
    "iso:country":"CN",
    "name:zho_x_preferred":[
        "\u524d\u8f98\u8f73\u628a\u8425\u5b50"
    ],
    "wof:name":"Qianluluba Yingzi",
    "wof:placetype":"locality"
},
  "geometry": {"coordinates":[127.03431999999999,46.25145],"type":"Point"}
}