{
  "type": "Feature",
  "properties": {
    "gn:admin1_code":"33.0",
    "gn:asciiname":"Shunping",
    "gn:country_code":"CN",
    "gn:dem":1093,
    "gn:feature_class":"P",
    "gn:feature_code":"PPL",
    "gn:name":"Shunping",
    "gn:population":0,
    "gn:timezone":"Asia/Shanghai",
    "iso:country":"CN",
    "name:zho_x_preferred":[
        "\u987a\u5e73"
    ],
    "wof:name":"Shunping",
    "wof:placetype":"locality"
},
  "geometry": {"coordinates":[108.72001000000002,31.41577],"type":"Point"}
}