{
  "type": "Feature",
  "properties": {
    "gn:admin1_code":"24.0",
    "gn:asciiname":"Hutouzhuang",
    "gn:country_code":"CN",
    "gn:dem":751,
    "gn:feature_class":"P",
    "gn:feature_code":"PPL",
    "gn:name":"Hutouzhuang",
    "gn:population":0,
    "gn:timezone":"Asia/Shanghai",
    "iso:country":"CN",
    "name:und_x_variant":[
        "\u6237\u5934\u5e84"
    ],
    "wof:name":"Hutouzhuang",
    "wof:placetype":"locality"
},
  "geometry": {"coordinates":[111.15644,35.42434],"type":"Point"}
}