{
  "type": "Feature",
  "properties": {
    "gn:admin1_code":"3.0",
    "gn:asciiname":"Ankengkou",
    "gn:country_code":"CN",
    "gn:dem":259,
    "gn:feature_class":"P",
    "gn:feature_code":"PPL",
    "gn:name":"Ankengkou",
    "gn:population":0,
    "gn:timezone":"Asia/Shanghai",
    "iso:country":"CN",
    "name:zho_x_preferred":[
        "\u6697\u5751\u53e3"
    ],
    "wof:name":"Ankengkou",
    "wof:placetype":"locality"
},
  "geometry": {"coordinates":[114.449,29.2092],"type":"Point"}
}