{
  "type": "Feature",
  "properties": {
    "gn:admin1_code":"19.0",
    "gn:asciiname":"Liujia Gangzi",
    "gn:country_code":"CN",
    "gn:dem":39,
    "gn:feature_class":"P",
    "gn:feature_code":"PPL",
    "gn:name":"Liujia Gangzi",
    "gn:population":0,
    "gn:timezone":"Asia/Shanghai",
    "iso:country":"CN",
    "name:zho_x_preferred":[
        "\u5218\u5bb6\u5c97\u5b50"
    ],
    "wof:name":"Liujia Gangzi",
    "wof:placetype":"locality"
},
  "geometry": {"coordinates":[122.512,41.963],"type":"Point"}
}