{
  "type": "Feature",
  "properties": {
    "gn:admin1_code":"04",
    "gn:asciiname":"Kongqiao",
    "gn:country_code":"CN",
    "gn:dem":8,
    "gn:feature_class":"P",
    "gn:feature_code":"PPL",
    "gn:name":"Kongqiao",
    "gn:population":0,
    "gn:timezone":"Asia/Shanghai",
    "iso:country":"CN",
    "name:und_x_variant":[
        "K\u2019ung-chia-ch\u2019iao",
        "Kongjiaqiao",
        "\u5b54\u5bb6\u6865",
        "Kongqiao"
    ],
    "name:zho_x_preferred":[
        "\u5b54\u6865"
    ],
    "wof:name":"Kongqiao",
    "wof:placetype":"locality"
},
  "geometry": {"coordinates":[119.96289,32.32225],"type":"Point"}
}