{
  "type": "Feature",
  "properties": {
    "gn:admin1_code":"28",
    "gn:asciiname":"Xiaogaozhuang",
    "gn:country_code":"CN",
    "gn:dem":4,
    "gn:feature_class":"P",
    "gn:feature_code":"PPL",
    "gn:name":"Xiaogaozhuang",
    "gn:population":0,
    "gn:timezone":"Asia/Shanghai",
    "iso:country":"CN",
    "name:zho_x_preferred":[
        "\u5c0f\u9ad8\u5e84"
    ],
    "wof:name":"Xiaogaozhuang",
    "wof:placetype":"locality"
},
  "geometry": {"coordinates":[117.49278,38.97917],"type":"Point"}
}