{
  "type": "Feature",
  "properties": {
    "gn:admin1_code":"26.0",
    "gn:asciiname":"Zhuojiacun",
    "gn:country_code":"CN",
    "gn:dem":1042,
    "gn:feature_class":"P",
    "gn:feature_code":"PPL",
    "gn:name":"Zhuojiacun",
    "gn:population":0,
    "gn:timezone":"Asia/Shanghai",
    "iso:country":"CN",
    "name:zho_x_preferred":[
        "\u5353\u5bb6\u6751"
    ],
    "wof:name":"Zhuojiacun",
    "wof:placetype":"locality"
},
  "geometry": {"coordinates":[110.25132000000001,36.13273],"type":"Point"}
}