{
  "type": "Feature",
  "properties": {
    "gn:admin1_code":"25.0",
    "gn:asciiname":"Tanjiazhuangcun",
    "gn:country_code":"CN",
    "gn:dem":39,
    "gn:feature_class":"P",
    "gn:feature_code":"PPL",
    "gn:name":"Tanjiazhuangcun",
    "gn:population":0,
    "gn:timezone":"Asia/Shanghai",
    "iso:country":"CN",
    "name:zho_x_preferred":[
        "\u8c2d\u5bb6\u5e84\u6751"
    ],
    "wof:name":"Tanjiazhuangcun",
    "wof:placetype":"locality"
},
  "geometry": {"coordinates":[121.29219000000001,37.32019],"type":"Point"}
}