{
  "type": "Feature",
  "properties": {
    "gn:admin1_code":"15.0",
    "gn:asciiname":"Quanhuagou",
    "gn:country_code":"CN",
    "gn:dem":1927,
    "gn:feature_class":"P",
    "gn:feature_code":"PPL",
    "gn:name":"Quanhuagou",
    "gn:population":0,
    "gn:timezone":"Asia/Shanghai",
    "iso:country":"CN",
    "name:zho_x_preferred":[
        "\u5168\u5316\u6c9f"
    ],
    "wof:name":"Quanhuagou",
    "wof:placetype":"locality"
},
  "geometry": {"coordinates":[104.733,36.0035],"type":"Point"}
}