{
  "type": "Feature",
  "properties": {
    "gn:admin1_code":"18",
    "gn:asciiname":"Shiyuan",
    "gn:country_code":"CN",
    "gn:dem":1225,
    "gn:feature_class":"P",
    "gn:feature_code":"PPL",
    "gn:name":"Shiyuan",
    "gn:population":0,
    "gn:timezone":"Asia/Shanghai",
    "iso:country":"CN",
    "name:fra_x_preferred":[
        "Shiyuan"
    ],
    "name:zho_x_preferred":[
        "\u77f3\u9662"
    ],
    "wof:name":"Shiyuan",
    "wof:placetype":"locality"
},
  "geometry": {"coordinates":[107.023,28.5954],"type":"Point"}
}