{
  "type": "Feature",
  "properties": {
    "gn:admin1_code":"14.0",
    "gn:asciiname":"Yumco",
    "gn:country_code":"CN",
    "gn:dem":4751,
    "gn:feature_class":"P",
    "gn:feature_code":"PPLF",
    "gn:name":"Yumco",
    "gn:population":0,
    "gn:timezone":"Asia/Urumqi",
    "iso:country":"CN",
    "name:bod_x_preferred":[
        "Yumco"
    ],
    "name:msa_x_preferred":[
        "Yumco"
    ],
    "name:zho_x_preferred":[
        "Yongcuo"
    ],
    "name:zho_x_variant":[
        "\u6c38\u63aa",
        "Taibuguoni",
        "\u53f0\u5e03\u679c\u5c3c"
    ],
    "wof:name":"Yumco",
    "wof:placetype":"locality"
},
  "geometry": {"coordinates":[84.61667,31.83333],"type":"Point"}
}