{
  "type": "Feature",
  "properties": {
    "gn:admin1_code":"14.0",
    "gn:asciiname":"Qutaiwoma",
    "gn:country_code":"CN",
    "gn:dem":4288,
    "gn:feature_class":"P",
    "gn:feature_code":"PPL",
    "gn:name":"Qutaiwoma",
    "gn:population":0,
    "gn:timezone":"Asia/Urumqi",
    "iso:country":"CN",
    "name:zho_x_preferred":[
        "\u66f2\u592a\u6c83\u739b"
    ],
    "wof:name":"Qutaiwoma",
    "wof:placetype":"locality"
},
  "geometry": {"coordinates":[92.8165,31.66309],"type":"Point"}
}