{
  "type": "Feature",
  "properties": {
    "gn:admin1_code":"8.0",
    "gn:asciiname":"Lihuatun",
    "gn:country_code":"CN",
    "gn:dem":167,
    "gn:feature_class":"P",
    "gn:feature_code":"PPL",
    "gn:name":"Lihuatun",
    "gn:population":0,
    "gn:timezone":"Asia/Shanghai",
    "iso:country":"CN",
    "name:zho_x_preferred":[
        "\u674e\u82b1\u5c6f"
    ],
    "wof:name":"Lihuatun",
    "wof:placetype":"locality"
},
  "geometry": {"coordinates":[127.32813,45.82163],"type":"Point"}
}