{
  "type": "Feature",
  "properties": {
    "gn:admin1_code":"11.0",
    "gn:asciiname":"Xin'ansi",
    "gn:country_code":"CN",
    "gn:dem":67,
    "gn:feature_class":"P",
    "gn:feature_code":"PPL",
    "gn:name":"Xin\u2019ansi",
    "gn:population":0,
    "gn:timezone":"Asia/Shanghai",
    "iso:country":"CN",
    "name:und_x_variant":[
        "Xin\u2019ansi",
        "Xin\u2019an"
    ],
    "name:zho_x_preferred":[
        "\u65b0\u5b89\u5bfa"
    ],
    "wof:name":"Xin'ansi",
    "wof:placetype":"locality"
},
  "geometry": {"coordinates":[112.63685,26.9856],"type":"Point"}
}