{
  "type": "Feature",
  "properties": {
    "gn:admin1_code":"12.0",
    "gn:asciiname":"Xizhaochang",
    "gn:country_code":"CN",
    "gn:dem":32,
    "gn:feature_class":"P",
    "gn:feature_code":"PPL",
    "gn:name":"Xizhaochang",
    "gn:population":0,
    "gn:timezone":"Asia/Shanghai",
    "iso:country":"CN",
    "name:zho_x_preferred":[
        "\u897f\u8d75\u573a"
    ],
    "wof:name":"Xizhaochang",
    "wof:placetype":"locality"
},
  "geometry": {"coordinates":[113.29425000000001,30.87642],"type":"Point"}
}