{
  "type": "Feature",
  "properties": {
    "gn:admin1_code":"4.0",
    "gn:asciiname":"Chouji Yizu",
    "gn:country_code":"CN",
    "gn:dem":2,
    "gn:feature_class":"P",
    "gn:feature_code":"PPL",
    "gn:name":"Chouji Yizu",
    "gn:population":0,
    "gn:timezone":"Asia/Shanghai",
    "iso:country":"CN",
    "name:zho_x_preferred":[
        "Chouji Yizu"
    ],
    "name:zho_x_variant":[
        "\u4ec7\u5409\u4e00\u7ec4"
    ],
    "wof:name":"Chouji Yizu",
    "wof:placetype":"locality"
},
  "geometry": {"coordinates":[119.98477,33.31787],"type":"Point"}
}