{
  "type": "Feature",
  "properties": {
    "gn:admin1_code":"15",
    "gn:asciiname":"Heqiao",
    "gn:cc2":"CN",
    "gn:country_code":"CN",
    "gn:dem":1905,
    "gn:feature_class":"P",
    "gn:feature_code":"PPL",
    "gn:name":"Heqiao",
    "gn:population":0,
    "gn:timezone":"Asia/Shanghai",
    "iso:country":"CN",
    "name:und_x_variant":[
        "Wuchiaping",
        "Ta-t\u2019ung-chen",
        "Ho-ch\u2019iao",
        "Ho-ch\u2019iao-i",
        "Heqiaoyi",
        "Heqiao"
    ],
    "wof:name":"Heqiao",
    "wof:placetype":"locality"
},
  "geometry": {"coordinates":[102.85417,36.49583],"type":"Point"}
}