{
  "type": "Feature",
  "properties": {
    "gn:admin1_code":"32.0",
    "gn:asciiname":"Yushi",
    "gn:country_code":"CN",
    "gn:dem":321,
    "gn:feature_class":"P",
    "gn:feature_code":"PPL",
    "gn:name":"Yushi",
    "gn:population":0,
    "gn:timezone":"Asia/Shanghai",
    "iso:country":"CN",
    "name:zho_x_preferred":[
        "\u5fa1\u53f2"
    ],
    "wof:name":"Yushi",
    "wof:placetype":"locality"
},
  "geometry": {"coordinates":[106.29644999999999,30.86386],"type":"Point"}
}