{
  "type": "Feature",
  "properties": {
    "gn:admin1_code":"8.0",
    "gn:asciiname":"Xixiaojiatun",
    "gn:country_code":"CN",
    "gn:dem":230,
    "gn:feature_class":"P",
    "gn:feature_code":"PPL",
    "gn:name":"Xixiaojiatun",
    "gn:population":0,
    "gn:timezone":"Asia/Shanghai",
    "iso:country":"CN",
    "name:zho_x_preferred":[
        "\u897f\u8096\u5bb6\u5c6f"
    ],
    "wof:name":"Xixiaojiatun",
    "wof:placetype":"locality"
},
  "geometry": {"coordinates":[125.88853,47.40764],"type":"Point"}
}