{
  "type": "Feature",
  "properties": {
    "gn:admin1_code":"4.0",
    "gn:asciiname":"Qixiaolou",
    "gn:country_code":"CN",
    "gn:dem":43,
    "gn:feature_class":"P",
    "gn:feature_code":"PPL",
    "gn:name":"Qixiaolou",
    "gn:population":0,
    "gn:timezone":"Asia/Shanghai",
    "iso:country":"CN",
    "name:zho_x_preferred":[
        "\u9f50\u5c0f\u697c"
    ],
    "wof:name":"Qixiaolou",
    "wof:placetype":"locality"
},
  "geometry": {"coordinates":[116.45099999999999,34.7304],"type":"Point"}
}