{
  "type": "Feature",
  "properties": {
    "gn:admin1_code":"25.0",
    "gn:asciiname":"Shagou Majia",
    "gn:country_code":"CN",
    "gn:dem":32,
    "gn:feature_class":"P",
    "gn:feature_code":"PPL",
    "gn:name":"Shagou Majia",
    "gn:population":0,
    "gn:timezone":"Asia/Shanghai",
    "iso:country":"CN",
    "name:zho_x_preferred":[
        "\u6c99\u6c9f\u9a6c\u5bb6"
    ],
    "wof:name":"Shagou Majia",
    "wof:placetype":"locality"
},
  "geometry": {"coordinates":[120.33096999999999,37.48064],"type":"Point"}
}