{
  "type": "Feature",
  "properties": {
    "gn:admin1_code":"32.0",
    "gn:asciiname":"Egu",
    "gn:country_code":"CN",
    "gn:dem":3182,
    "gn:feature_class":"P",
    "gn:feature_code":"PPL",
    "gn:name":"Egu",
    "gn:population":0,
    "gn:timezone":"Asia/Shanghai",
    "iso:country":"CN",
    "name:zho_x_preferred":[
        "\u4fc4\u53e4"
    ],
    "wof:name":"Egu",
    "wof:placetype":"locality"
},
  "geometry": {"coordinates":[101.17855,31.80756],"type":"Point"}
}