{
  "type": "Feature",
  "properties": {
    "gn:admin1_code":"1.0",
    "gn:asciiname":"Zhailingcun",
    "gn:country_code":"CN",
    "gn:dem":26,
    "gn:feature_class":"P",
    "gn:feature_code":"PPL",
    "gn:name":"Zhailingcun",
    "gn:population":0,
    "gn:timezone":"Asia/Shanghai",
    "iso:country":"CN",
    "name:zho_x_preferred":[
        "\u5be8\u5cad\u6751"
    ],
    "wof:name":"Zhailingcun",
    "wof:placetype":"locality"
},
  "geometry": {"coordinates":[116.49482999999999,30.20764],"type":"Point"}
}