{
  "type": "Feature",
  "properties": {
    "gn:admin1_code":"29",
    "gn:asciiname":"Lisuda",
    "gn:country_code":"CN",
    "gn:dem":1840,
    "gn:feature_class":"P",
    "gn:feature_code":"PPL",
    "gn:name":"Lisuda",
    "gn:population":0,
    "gn:timezone":"Asia/Shanghai",
    "iso:country":"CN",
    "name:zho_x_preferred":[
        "\u5229\u82cf\u6253"
    ],
    "wof:name":"Lisuda",
    "wof:placetype":"locality"
},
  "geometry": {"coordinates":[101.157,24.6627],"type":"Point"}
}