{
  "type": "Feature",
  "properties": {
    "gn:admin1_code":"7",
    "gn:asciiname":"Chencun",
    "gn:country_code":"CN",
    "gn:dem":893,
    "gn:feature_class":"P",
    "gn:feature_code":"PPL",
    "gn:name":"Chencun",
    "gn:population":0,
    "gn:timezone":"Asia/Shanghai",
    "iso:country":"CN",
    "name:zho_x_preferred":[
        "\u9648\u6751"
    ],
    "wof:name":"Chencun",
    "wof:placetype":"locality"
},
  "geometry": {"coordinates":[117.37884,24.99754],"type":"Point"}
}