{
  "type": "Feature",
  "properties": {
    "gn:admin1_code":"32.0",
    "gn:asciiname":"Muguyimo",
    "gn:country_code":"CN",
    "gn:dem":2541,
    "gn:feature_class":"P",
    "gn:feature_code":"PPL",
    "gn:name":"Muguyimo",
    "gn:population":0,
    "gn:timezone":"Asia/Shanghai",
    "iso:country":"CN",
    "name:zho_x_preferred":[
        "\u6728\u53e4\u5b9c\u83ab"
    ],
    "wof:name":"Muguyimo",
    "wof:placetype":"locality"
},
  "geometry": {"coordinates":[102.477,28.0638],"type":"Point"}
}