{
  "type": "Feature",
  "properties": {
    "gn:admin1_code":"12.0",
    "gn:asciiname":"Hongshan",
    "gn:country_code":"CN",
    "gn:dem":40,
    "gn:feature_class":"P",
    "gn:feature_code":"PPL",
    "gn:name":"Hongshan",
    "gn:population":0,
    "gn:timezone":"Asia/Shanghai",
    "iso:country":"CN",
    "name:zho_x_preferred":[
        "Hongshan"
    ],
    "name:zho_x_variant":[
        "\u6d2a\u5c71"
    ],
    "wof:name":"Hongshan",
    "wof:placetype":"locality"
},
  "geometry": {"coordinates":[111.94817,30.46833],"type":"Point"}
}