{
  "type": "Feature",
  "properties": {
    "gn:admin1_code":"24.0",
    "gn:asciiname":"Zhupuzhang",
    "gn:country_code":"CN",
    "gn:dem":907,
    "gn:feature_class":"P",
    "gn:feature_code":"PPL",
    "gn:name":"Zhupuzhang",
    "gn:population":0,
    "gn:timezone":"Asia/Shanghai",
    "iso:country":"CN",
    "name:zho_x_preferred":[
        "\u4e3b\u94fa\u638c"
    ],
    "wof:name":"Zhupuzhang",
    "wof:placetype":"locality"
},
  "geometry": {"coordinates":[113.79783,38.08676],"type":"Point"}
}