{
  "type": "Feature",
  "properties": {
    "gn:admin1_code":"12.0",
    "gn:asciiname":"Guojiachong",
    "gn:country_code":"CN",
    "gn:dem":247,
    "gn:feature_class":"P",
    "gn:feature_code":"PPL",
    "gn:name":"Guojiachong",
    "gn:population":0,
    "gn:timezone":"Asia/Shanghai",
    "iso:country":"CN",
    "name:zho_x_preferred":[
        "Guojiachong"
    ],
    "name:zho_x_variant":[
        "\u90ed\u5bb6\u51b2"
    ],
    "wof:name":"Guojiachong",
    "wof:placetype":"locality"
},
  "geometry": {"coordinates":[111.51364,30.1516],"type":"Point"}
}