{
  "type": "Feature",
  "properties": {
    "gn:admin1_code":"29.0",
    "gn:asciiname":"Xiaoyangyi",
    "gn:country_code":"CN",
    "gn:dem":1892,
    "gn:feature_class":"P",
    "gn:feature_code":"PPL",
    "gn:name":"Xiaoyangyi",
    "gn:population":0,
    "gn:timezone":"Asia/Shanghai",
    "iso:country":"CN",
    "name:zho_x_preferred":[
        "\u5c0f\u7f8a\u9091"
    ],
    "wof:name":"Xiaoyangyi",
    "wof:placetype":"locality"
},
  "geometry": {"coordinates":[99.26349999999999,24.9108],"type":"Point"}
}