{
  "type": "Feature",
  "properties": {
    "gn:admin1_code":"4.0",
    "gn:asciiname":"Chenduncun",
    "gn:country_code":"CN",
    "gn:dem":16,
    "gn:feature_class":"P",
    "gn:feature_code":"PPL",
    "gn:name":"Chenduncun",
    "gn:population":0,
    "gn:timezone":"Asia/Shanghai",
    "iso:country":"CN",
    "name:zho_x_preferred":[
        "\u9648\u58a9\u6751"
    ],
    "wof:name":"Chenduncun",
    "wof:placetype":"locality"
},
  "geometry": {"coordinates":[118.47852,33.98309],"type":"Point"}
}