{
  "type": "Feature",
  "properties": {
    "gn:admin1_code":"24.0",
    "gn:asciiname":"Xiaoxiangzhai",
    "gn:country_code":"CN",
    "gn:dem":865,
    "gn:feature_class":"P",
    "gn:feature_code":"PPL",
    "gn:name":"Xiaoxiangzhai",
    "gn:population":0,
    "gn:timezone":"Asia/Shanghai",
    "iso:country":"CN",
    "name:zho_x_preferred":[
        "\u5c0f\u76f8\u5be8"
    ],
    "wof:name":"Xiaoxiangzhai",
    "wof:placetype":"locality"
},
  "geometry": {"coordinates":[111.86306999999999,37.36268],"type":"Point"}
}