{
  "type": "Feature",
  "properties": {
    "gn:admin1_code":"32.0",
    "gn:asciiname":"Zhuqing",
    "gn:country_code":"CN",
    "gn:dem":3938,
    "gn:feature_class":"P",
    "gn:feature_code":"PPL",
    "gn:name":"Zhuqing",
    "gn:population":0,
    "gn:timezone":"Asia/Shanghai",
    "iso:country":"CN",
    "name:und_x_variant":[
        "Chu-ch\u2019ing",
        "Dzogchen-gompa",
        "Zogq\u00ean",
        "Zhuqing"
    ],
    "name:zho_x_preferred":[
        "\u7af9\u5e86"
    ],
    "wof:name":"Zhuqing",
    "wof:placetype":"locality"
},
  "geometry": {"coordinates":[98.85919,32.12739000000001],"type":"Point"}
}