{
  "type": "Feature",
  "properties": {
    "gn:admin1_code":"32.0",
    "gn:asciiname":"Guanyindong",
    "gn:country_code":"CN",
    "gn:dem":683,
    "gn:feature_class":"P",
    "gn:feature_code":"PPL",
    "gn:name":"Guanyindong",
    "gn:population":0,
    "gn:timezone":"Asia/Shanghai",
    "iso:country":"CN",
    "name:deu_x_preferred":[
        "Guanyindong"
    ],
    "name:und_x_variant":[
        "\u89c2\u97f3\u6d1e"
    ],
    "wof:name":"Guanyindong",
    "wof:placetype":"locality"
},
  "geometry": {"coordinates":[106.86027,32.1727],"type":"Point"}
}