{
  "type": "Feature",
  "properties": {
    "gn:admin1_code":"19.0",
    "gn:asciiname":"Qujiadian",
    "gn:country_code":"CN",
    "gn:dem":207,
    "gn:feature_class":"P",
    "gn:feature_code":"PPL",
    "gn:name":"Qujiadian",
    "gn:population":0,
    "gn:timezone":"Asia/Shanghai",
    "iso:country":"CN",
    "name:und_x_variant":[
        "\u66f2\u5bb6\u5e97"
    ],
    "wof:name":"Qujiadian",
    "wof:placetype":"locality"
},
  "geometry": {"coordinates":[123.86597999999999,40.46348],"type":"Point"}
}