{
  "type": "Feature",
  "properties": {
    "gn:admin1_code":"16",
    "gn:asciiname":"Zimuchong",
    "gn:country_code":"CN",
    "gn:dem":901,
    "gn:feature_class":"P",
    "gn:feature_code":"PPL",
    "gn:name":"Zimuchong",
    "gn:population":0,
    "gn:timezone":"Asia/Shanghai",
    "iso:country":"CN",
    "name:zho_x_preferred":[
        "\u6893\u6728\u51b2"
    ],
    "wof:name":"Zimuchong",
    "wof:placetype":"locality"
},
  "geometry": {"coordinates":[110.62,26.2879],"type":"Point"}
}