{
  "type": "Feature",
  "properties": {
    "gn:admin1_code":"33",
    "gn:asciiname":"Shuangjiang",
    "gn:country_code":"CN",
    "gn:dem":263,
    "gn:feature_class":"P",
    "gn:feature_code":"PPLA4",
    "gn:name":"Shuangjiang",
    "gn:population":0,
    "gn:timezone":"Asia/Shanghai",
    "iso:country":"CN",
    "name:und_x_variant":[
        "Shuang-chiang-chen",
        "Shuantszyanchzhen\u2019",
        "Shuang-chiang",
        "Shuangjiang",
        "Shuangjiang Zhen",
        "Xiangjiaba"
    ],
    "name:zho_x_preferred":[
        "\u53cc\u6c5f"
    ],
    "name:zho_x_variant":[
        "\u53cc\u6c5f\u9547",
        "\u5411\u5bb6\u575d"
    ],
    "wof:name":"Shuangjiang",
    "wof:placetype":"locality"
},
  "geometry": {"coordinates":[105.7452,30.21754],"type":"Point"}
}