{
  "type": "Feature",
  "properties": {
    "gn:admin1_code":"12.0",
    "gn:asciiname":"Shijiazhai",
    "gn:country_code":"CN",
    "gn:dem":257,
    "gn:feature_class":"P",
    "gn:feature_code":"PPL",
    "gn:name":"Shijiazhai",
    "gn:population":0,
    "gn:timezone":"Asia/Shanghai",
    "iso:country":"CN",
    "name:zho_x_preferred":[
        "\u77f3\u5bb6\u5be8"
    ],
    "wof:name":"Shijiazhai",
    "wof:placetype":"locality"
},
  "geometry": {"coordinates":[115.23,31.12237],"type":"Point"}
}