{
  "type": "Feature",
  "properties": {
    "gn:admin1_code":"11.0",
    "gn:asciiname":"Tangjia Dawu",
    "gn:country_code":"CN",
    "gn:dem":104,
    "gn:feature_class":"P",
    "gn:feature_code":"PPL",
    "gn:name":"Tangjia Dawu",
    "gn:population":0,
    "gn:timezone":"Asia/Shanghai",
    "iso:country":"CN",
    "name:zho_x_preferred":[
        "\u6c64\u5bb6\u5927\u5c4b"
    ],
    "wof:name":"Tangjia Dawu",
    "wof:placetype":"locality"
},
  "geometry": {"coordinates":[112.58551,26.42135],"type":"Point"}
}