{
  "type": "Feature",
  "properties": {
    "gn:admin1_code":"11.0",
    "gn:asciiname":"Huangguchong",
    "gn:country_code":"CN",
    "gn:dem":101,
    "gn:feature_class":"P",
    "gn:feature_code":"PPL",
    "gn:name":"Huangguchong",
    "gn:population":0,
    "gn:timezone":"Asia/Shanghai",
    "iso:country":"CN",
    "name:zho_x_preferred":[
        "\u9ec4\u987e\u51b2"
    ],
    "wof:name":"Huangguchong",
    "wof:placetype":"locality"
},
  "geometry": {"coordinates":[111.38702000000001,28.72588],"type":"Point"}
}