{
  "type": "Feature",
  "properties": {
    "gn:admin1_code":"7.0",
    "gn:asciiname":"Yangligang",
    "gn:country_code":"CN",
    "gn:dem":768,
    "gn:feature_class":"P",
    "gn:feature_code":"PPL",
    "gn:name":"Yangligang",
    "gn:population":0,
    "gn:timezone":"Asia/Shanghai",
    "iso:country":"CN",
    "name:zho_x_preferred":[
        "\u6d0b\u91cc\u5188"
    ],
    "wof:name":"Yangligang",
    "wof:placetype":"locality"
},
  "geometry": {"coordinates":[119.49703999999998,26.96849000000001],"type":"Point"}
}