{
  "type": "Feature",
  "properties": {
    "gn:admin1_code":"25.0",
    "gn:asciiname":"Shicunjicun",
    "gn:country_code":"CN",
    "gn:dem":48,
    "gn:feature_class":"P",
    "gn:feature_code":"PPL",
    "gn:name":"Shicunjicun",
    "gn:population":0,
    "gn:timezone":"Asia/Shanghai",
    "iso:country":"CN",
    "name:zho_x_preferred":[
        "\u77f3\u6751\u96c6\u6751"
    ],
    "wof:name":"Shicunjicun",
    "wof:placetype":"locality"
},
  "geometry": {"coordinates":[116.31946000000001,34.65474],"type":"Point"}
}