{
  "type": "Feature",
  "properties": {
    "gn:admin1_code":"25.0",
    "gn:asciiname":"Zhenwumiaocun",
    "gn:country_code":"CN",
    "gn:dem":40,
    "gn:feature_class":"P",
    "gn:feature_code":"PPL",
    "gn:name":"Zhenwumiaocun",
    "gn:population":0,
    "gn:timezone":"Asia/Shanghai",
    "iso:country":"CN",
    "name:zho_x_preferred":[
        "\u771f\u6b66\u5e99\u6751"
    ],
    "wof:name":"Zhenwumiaocun",
    "wof:placetype":"locality"
},
  "geometry": {"coordinates":[115.96963999999998,36.17561],"type":"Point"}
}