{
  "type": "Feature",
  "properties": {
    "gn:admin1_code":"26.0",
    "gn:asciiname":"Hualiwan",
    "gn:country_code":"CN",
    "gn:dem":1139,
    "gn:feature_class":"P",
    "gn:feature_code":"PPL",
    "gn:name":"Hualiwan",
    "gn:population":0,
    "gn:timezone":"Asia/Shanghai",
    "iso:country":"CN",
    "name:und_x_variant":[
        "\u6866\u91cc\u6e7e"
    ],
    "wof:name":"Hualiwan",
    "wof:placetype":"locality"
},
  "geometry": {"coordinates":[106.67449999999999,34.03345],"type":"Point"}
}