{
  "type": "Feature",
  "properties": {
    "gn:admin1_code":"10.0",
    "gn:asciiname":"Xilingxiao",
    "gn:country_code":"CN",
    "gn:dem":25,
    "gn:feature_class":"P",
    "gn:feature_code":"PPL",
    "gn:name":"Xilingxiao",
    "gn:population":0,
    "gn:timezone":"Asia/Shanghai",
    "iso:country":"CN",
    "name:zho_x_preferred":[
        "\u897f\u51cc\u6d88"
    ],
    "wof:name":"Xilingxiao",
    "wof:placetype":"locality"
},
  "geometry": {"coordinates":[115.73699999999999,38.0892],"type":"Point"}
}