{
  "type": "Feature",
  "properties": {
    "gn:country":"CN",
    "gn:fcode":"ADM3",
    "gn:pop":0,
    "iso:country":"CN",
    "name:unk_x_variant":[
        "Chiang-pei Hsien"
    ],
    "name:zho_x_preferred":[
        "\u6c5f\u5317\u533a"
    ],
    "name:zho_x_variant":[
        "\u6c5f\u5317"
    ],
    "qs:name":"Jiangbei Qu",
    "qs:photos_9r":0,
    "qs:photos_sr":0,
    "qs:pop_sr":"0",
    "wd:wordcount":157,
    "wof:name":"Jiangbei Qu",
    "wof:placetype":"localadmin",
    "wof:population":0
},
  "geometry": {"coordinates":[106.71207,29.62056],"type":"Point"}
}