{
  "type": "Feature",
  "properties": {
    "gn:country":"CN",
    "gn:fcode":"ADM3",
    "gn:pop":0,
    "iso:country":"CN",
    "name:cym_x_preferred":[
        "Ardal Jiangbei"
    ],
    "name:deu_x_preferred":[
        "Jiangbei"
    ],
    "name:eng_x_preferred":[
        "Jiangbei District"
    ],
    "name:eus_x_preferred":[
        "Jiangbei barrutia"
    ],
    "name:gan_x_preferred":[
        "\u6c5f\u5317\u533a"
    ],
    "name:jpn_x_preferred":[
        "\u6c5f\u5317\u533a"
    ],
    "name:kor_x_preferred":[
        "\uc7a5\ubca0\uc774\uad6c"
    ],
    "name:mwl_x_preferred":[
        "Jiangbei"
    ],
    "name:nan_x_preferred":[
        "Kang-pak-khu"
    ],
    "name:nld_x_preferred":[
        "Jiangbei District"
    ],
    "name:nob_x_preferred":[
        "Jiangbei"
    ],
    "name:rus_x_preferred":[
        "\u0426\u0437\u044f\u043d\u0431\u044d\u0439"
    ],
    "name:spa_x_preferred":[
        "Jiangbei"
    ],
    "name:swe_x_preferred":[
        "Jiangbei"
    ],
    "name:unk_x_variant":[
        "Chiang-pei Hsien"
    ],
    "name:vie_x_preferred":[
        "Giang B\u1eafc"
    ],
    "name:wuu_x_preferred":[
        "\u6c5f\u5317\u533a"
    ],
    "name:yue_x_preferred":[
        "\u6c5f\u5317"
    ],
    "name:zho_x_preferred":[
        "\u6c5f\u5317\u533a"
    ],
    "name:zho_x_variant":[
        "\u6c5f\u5317",
        "\u6c5f\u5317\u5340"
    ],
    "qs:name":"Jiangbei Qu",
    "qs:photos_9r":0,
    "qs:photos_sr":0,
    "qs:pop_sr":"0",
    "wd:wordcount":157,
    "wof:name":"Jiangbei Qu",
    "wof:placetype":"localadmin",
    "wof:population":0
},
  "geometry": {"coordinates":[106.71207,29.62056],"type":"Point"}
}