{
  "type": "Feature",
  "properties": {
    "gn:admin1_code":"32.0",
    "gn:asciiname":"Luoba Xicun",
    "gn:country_code":"CN",
    "gn:dem":3504,
    "gn:feature_class":"P",
    "gn:feature_code":"PPL",
    "gn:name":"Luoba Xicun",
    "gn:population":0,
    "gn:timezone":"Asia/Shanghai",
    "iso:country":"CN",
    "name:zho_x_preferred":[
        "\u6d1b\u5df4\u897f\u6751"
    ],
    "wof:name":"Luoba Xicun",
    "wof:placetype":"locality"
},
  "geometry": {"coordinates":[99.3801,31.4963],"type":"Point"}
}