{
  "type": "Feature",
  "properties": {
    "gn:admin1_code":"26.0",
    "gn:asciiname":"Haodigou",
    "gn:country_code":"CN",
    "gn:dem":1229,
    "gn:feature_class":"P",
    "gn:feature_code":"PPL",
    "gn:name":"Haodigou",
    "gn:population":0,
    "gn:timezone":"Asia/Shanghai",
    "iso:country":"CN",
    "name:zho_x_preferred":[
        "\u84bf\u5730\u6c9f"
    ],
    "wof:name":"Haodigou",
    "wof:placetype":"locality"
},
  "geometry": {"coordinates":[108.75136999999999,35.8684],"type":"Point"}
}