{
  "type": "Feature",
  "properties": {
    "gn:admin1_code":"11.0",
    "gn:asciiname":"Shihuichong",
    "gn:country_code":"CN",
    "gn:dem":250,
    "gn:feature_class":"P",
    "gn:feature_code":"PPL",
    "gn:name":"Shihuichong",
    "gn:population":0,
    "gn:timezone":"Asia/Shanghai",
    "iso:country":"CN",
    "name:zho_x_preferred":[
        "\u77f3\u7070\u51b2"
    ],
    "wof:name":"Shihuichong",
    "wof:placetype":"locality"
},
  "geometry": {"coordinates":[111.68026,28.23287],"type":"Point"}
}