{
  "type": "Feature",
  "properties": {
    "gn:admin1_code":"23.0",
    "gn:asciiname":"Nanhang",
    "gn:country_code":"CN",
    "gn:dem":5,
    "gn:feature_class":"P",
    "gn:feature_code":"PPL",
    "gn:name":"Nanhang",
    "gn:population":0,
    "gn:timezone":"Asia/Shanghai",
    "iso:country":"CN",
    "name:und_x_variant":[
        "\u5357\u884c"
    ],
    "wof:name":"Nanhang",
    "wof:placetype":"locality"
},
  "geometry": {"coordinates":[121.51300999999999,30.96501],"type":"Point"}
}