{
  "type": "Feature",
  "properties": {
    "gn:admin1_code":"15.0",
    "gn:asciiname":"Hongshi",
    "gn:country_code":"CN",
    "gn:dem":2633,
    "gn:feature_class":"P",
    "gn:feature_code":"PPL",
    "gn:name":"Hongshi",
    "gn:population":0,
    "gn:timezone":"Asia/Shanghai",
    "iso:country":"CN",
    "name:tha_x_preferred":[
        "\u0e2b\u0e07\u0e09\u0e37\u0e2d"
    ],
    "name:vie_x_preferred":[
        "Ho\u1eb1ng Th\u1eddi"
    ],
    "name:zho_x_preferred":[
        "\u7ea2\u77f3"
    ],
    "wof:name":"Hongshi",
    "wof:placetype":"locality"
},
  "geometry": {"coordinates":[103.44,36.9242],"type":"Point"}
}