{
  "type": "Feature",
  "properties": {
    "gn:admin1_code":"29.0",
    "gn:asciiname":"Baocangshan",
    "gn:country_code":"CN",
    "gn:dem":2153,
    "gn:feature_class":"P",
    "gn:feature_code":"PPL",
    "gn:name":"Baocangshan",
    "gn:population":0,
    "gn:timezone":"Asia/Shanghai",
    "iso:country":"CN",
    "name:zho_x_preferred":[
        "\u5b9d\u4ed3\u5c71"
    ],
    "wof:name":"Baocangshan",
    "wof:placetype":"locality"
},
  "geometry": {"coordinates":[100.655,24.0043],"type":"Point"}
}