{
  "type": "Feature",
  "properties": {
    "gn:admin1_code":"32.0",
    "gn:asciiname":"Xianading",
    "gn:country_code":"CN",
    "gn:dem":2526,
    "gn:feature_class":"P",
    "gn:feature_code":"PPL",
    "gn:name":"Xianading",
    "gn:population":0,
    "gn:timezone":"Asia/Shanghai",
    "iso:country":"CN",
    "name:zho_x_preferred":[
        "\u4e0b\u7eb3\u9876"
    ],
    "wof:name":"Xianading",
    "wof:placetype":"locality"
},
  "geometry": {"coordinates":[101.935,30.9268],"type":"Point"}
}