{
  "type": "Feature",
  "properties": {
    "gn:admin1_code":"2.0",
    "gn:asciiname":"Xuetan",
    "gn:country_code":"CN",
    "gn:dem":106,
    "gn:feature_class":"P",
    "gn:feature_code":"PPL",
    "gn:name":"Xuetan",
    "gn:population":0,
    "gn:timezone":"Asia/Shanghai",
    "iso:country":"CN",
    "name:zho_x_preferred":[
        "\u5b66\u5766"
    ],
    "wof:name":"Xuetan",
    "wof:placetype":"locality"
},
  "geometry": {"coordinates":[118.5823,28.66445],"type":"Point"}
}