{
  "type": "Feature",
  "properties": {
    "gn:admin1_code":"29.0",
    "gn:asciiname":"Wangan",
    "gn:country_code":"CN",
    "gn:dem":1270,
    "gn:feature_class":"P",
    "gn:feature_code":"PPL",
    "gn:name":"Wangan",
    "gn:population":0,
    "gn:timezone":"Asia/Shanghai",
    "iso:country":"CN",
    "name:ceb_x_preferred":[
        "Wangan"
    ],
    "name:jpn_x_preferred":[
        "\u6e7e\u5cb8\u7dda"
    ],
    "name:zho_x_preferred":[
        "\u5f2f\u5e72"
    ],
    "name:zho_x_variant":[
        "\u7063\u5cb8\u7dda"
    ],
    "wof:name":"Wangan",
    "wof:placetype":"locality"
},
  "geometry": {"coordinates":[101.33799999999999,22.4624],"type":"Point"}
}