{
  "type": "Feature",
  "properties": {
    "gn:admin1_code":"29.0",
    "gn:asciiname":"Dahuangtian",
    "gn:country_code":"CN",
    "gn:dem":915,
    "gn:feature_class":"P",
    "gn:feature_code":"PPL",
    "gn:name":"Dahuangtian",
    "gn:population":0,
    "gn:timezone":"Asia/Shanghai",
    "iso:country":"CN",
    "name:zho_x_preferred":[
        "\u5927\u8352\u7530"
    ],
    "wof:name":"Dahuangtian",
    "wof:placetype":"locality"
},
  "geometry": {"coordinates":[101.937,22.4658],"type":"Point"}
}