{
  "type": "Feature",
  "properties": {
    "gn:admin1_code":"33.0",
    "gn:asciiname":"Conglin",
    "gn:country_code":"CN",
    "gn:dem":619,
    "gn:feature_class":"P",
    "gn:feature_code":"PPL",
    "gn:name":"Conglin",
    "gn:population":0,
    "gn:timezone":"Asia/Shanghai",
    "iso:country":"CN",
    "name:por_x_preferred":[
        "Conglin"
    ],
    "name:zho_x_preferred":[
        "\u4e1b\u6797"
    ],
    "wof:name":"Conglin",
    "wof:placetype":"locality"
},
  "geometry": {"coordinates":[108.11958,30.55534],"type":"Point"}
}