{
  "type": "Feature",
  "properties": {
    "gn:admin1_code":"14.0",
    "gn:asciiname":"Nimi",
    "gn:country_code":"CN",
    "gn:dem":3562,
    "gn:feature_class":"P",
    "gn:feature_code":"PPL",
    "gn:name":"Nimi",
    "gn:population":0,
    "gn:timezone":"Asia/Urumqi",
    "iso:country":"CN",
    "name:ceb_x_preferred":[
        "Nimi"
    ],
    "name:swe_x_preferred":[
        "Nimi"
    ],
    "name:zho_x_preferred":[
        "\u6ce5\u54aa"
    ],
    "wof:name":"Nimi",
    "wof:placetype":"locality"
},
  "geometry": {"coordinates":[95.89393,30.9367],"type":"Point"}
}