{
  "type": "Feature",
  "properties": {
    "gn:admin1_code":"16.0",
    "gn:asciiname":"Longshuidong",
    "gn:country_code":"CN",
    "gn:dem":562,
    "gn:feature_class":"P",
    "gn:feature_code":"PPL",
    "gn:name":"Longshuidong",
    "gn:population":0,
    "gn:timezone":"Asia/Shanghai",
    "iso:country":"CN",
    "name:zho_x_preferred":[
        "\u9f99\u6c34\u578c"
    ],
    "wof:name":"Longshuidong",
    "wof:placetype":"locality"
},
  "geometry": {"coordinates":[111.23999999999999,23.8731],"type":"Point"}
}