{
  "type": "Feature",
  "properties": {
    "gn:admin1_code":"26.0",
    "gn:asciiname":"Xichuan",
    "gn:country_code":"CN",
    "gn:dem":1453,
    "gn:feature_class":"P",
    "gn:feature_code":"PPL",
    "gn:name":"Xichuan",
    "gn:population":0,
    "gn:timezone":"Asia/Shanghai",
    "iso:country":"CN",
    "name:und_x_variant":[
        "\u897f\u5ddd"
    ],
    "wof:name":"Xichuan",
    "wof:placetype":"locality"
},
  "geometry": {"coordinates":[107.54992,34.79828],"type":"Point"}
}