{
  "type": "Feature",
  "properties": {
    "gn:admin1_code":"4.0",
    "gn:asciiname":"Anle Yizu",
    "gn:country_code":"CN",
    "gn:dem":5,
    "gn:feature_class":"P",
    "gn:feature_code":"PPL",
    "gn:name":"Anle Yizu",
    "gn:population":0,
    "gn:timezone":"Asia/Shanghai",
    "iso:country":"CN",
    "name:und_x_variant":[
        "\u5b89\u4e50\u4e00\u7ec4"
    ],
    "name:zho_x_preferred":[
        "\u5b89\u4e50\u4e00\u7ec4"
    ],
    "wof:name":"Anle Yizu",
    "wof:placetype":"locality"
},
  "geometry": {"coordinates":[120.58284,32.69325],"type":"Point"}
}