{
  "type": "Feature",
  "properties": {
    "gn:admin1_code":"14.0",
    "gn:asciiname":"Xiaji",
    "gn:country_code":"CN",
    "gn:dem":4795,
    "gn:feature_class":"P",
    "gn:feature_code":"PPL",
    "gn:name":"Xiaji",
    "gn:population":0,
    "gn:timezone":"Asia/Urumqi",
    "iso:country":"CN",
    "name:zho_x_preferred":[
        "\u590f\u5409"
    ],
    "wof:name":"Xiaji",
    "wof:placetype":"locality"
},
  "geometry": {"coordinates":[83.5489,31.3015],"type":"Point"}
}