{
  "type": "Feature",
  "properties": {
    "gn:admin1_code":"7",
    "gn:asciiname":"Kanxia",
    "gn:country_code":"CN",
    "gn:dem":316,
    "gn:feature_class":"P",
    "gn:feature_code":"PPL",
    "gn:name":"Kanxia",
    "gn:population":0,
    "gn:timezone":"Asia/Shanghai",
    "iso:country":"CN",
    "name:zho_x_preferred":[
        "\u574e\u4e0b"
    ],
    "wof:name":"Kanxia",
    "wof:placetype":"locality"
},
  "geometry": {"coordinates":[117.28556,24.20778],"type":"Point"}
}