{
  "type": "Feature",
  "properties": {
    "gn:admin1_code":"33.0",
    "gn:asciiname":"Longmenzhai",
    "gn:country_code":"CN",
    "gn:dem":381,
    "gn:feature_class":"P",
    "gn:feature_code":"PPL",
    "gn:name":"Longmenzhai",
    "gn:population":0,
    "gn:timezone":"Asia/Shanghai",
    "iso:country":"CN",
    "name:zho_x_preferred":[
        "\u9f99\u95e8\u5be8"
    ],
    "wof:name":"Longmenzhai",
    "wof:placetype":"locality"
},
  "geometry": {"coordinates":[107.42082000000001,30.2659],"type":"Point"}
}