{
  "type": "Feature",
  "properties": {
    "gn:admin1_code":"10",
    "gn:asciiname":"Beisanwang",
    "gn:country_code":"CN",
    "gn:dem":6,
    "gn:feature_class":"P",
    "gn:feature_code":"PPL",
    "gn:name":"Beisanwang",
    "gn:population":0,
    "gn:timezone":"Asia/Shanghai",
    "iso:country":"CN",
    "name:zho_x_preferred":[
        "\u5317\u4e09\u738b"
    ],
    "wof:name":"Beisanwang",
    "wof:placetype":"locality"
},
  "geometry": {"coordinates":[116.547,38.7681],"type":"Point"}
}