{
  "type": "Feature",
  "properties": {
    "gn:admin1_code":"7.0",
    "gn:asciiname":"Luodi",
    "gn:country_code":"CN",
    "gn:dem":308,
    "gn:feature_class":"P",
    "gn:feature_code":"PPL",
    "gn:name":"Luodi",
    "gn:population":0,
    "gn:timezone":"Asia/Shanghai",
    "iso:country":"CN",
    "name:und_x_variant":[
        "\u7f57\u5730"
    ],
    "name:zho_x_preferred":[
        "\u7f57\u5730"
    ],
    "wof:name":"Luodi",
    "wof:placetype":"locality"
},
  "geometry": {"coordinates":[116.4216,25.62432],"type":"Point"}
}