{
  "type": "Feature",
  "properties": {
    "gn:admin1_code":"11.0",
    "gn:asciiname":"Fengmushan",
    "gn:country_code":"CN",
    "gn:dem":303,
    "gn:feature_class":"P",
    "gn:feature_code":"PPL",
    "gn:name":"Fengmushan",
    "gn:population":0,
    "gn:timezone":"Asia/Shanghai",
    "iso:country":"CN",
    "name:zho_x_preferred":[
        "\u67ab\u6728\u5c71"
    ],
    "wof:name":"Fengmushan",
    "wof:placetype":"locality"
},
  "geometry": {"coordinates":[110.70296,27.13475],"type":"Point"}
}