{
  "type": "Feature",
  "properties": {
    "gn:admin1_code":"02",
    "gn:asciiname":"Dahongcun",
    "gn:country_code":"CN",
    "gn:dem":120,
    "gn:feature_class":"P",
    "gn:feature_code":"PPL",
    "gn:name":"Dahongcun",
    "gn:population":0,
    "gn:timezone":"Asia/Shanghai",
    "iso:country":"CN",
    "name:und_x_variant":[
        "Ta-hung",
        "Dahong",
        "Dahongcun"
    ],
    "name:zho_x_preferred":[
        "\u5927\u6d2a"
    ],
    "name:zho_x_variant":[
        "\u5927\u6d2a\u6751"
    ],
    "wof:name":"Dahongcun",
    "wof:placetype":"locality"
},
  "geometry": {"coordinates":[120.7953,28.71807],"type":"Point"}
}