{
  "type": "Feature",
  "properties": {
    "gn:admin1_code":"03",
    "gn:asciiname":"Hugongtang",
    "gn:country_code":"CN",
    "gn:dem":305,
    "gn:feature_class":"P",
    "gn:feature_code":"PPL",
    "gn:name":"Hugongtang",
    "gn:population":0,
    "gn:timezone":"Asia/Shanghai",
    "iso:country":"CN",
    "name:zho_x_preferred":[
        "\u6e56\u516c\u5858"
    ],
    "wof:name":"Hugongtang",
    "wof:placetype":"locality"
},
  "geometry": {"coordinates":[115.5757,24.85516],"type":"Point"}
}