{
  "type": "Feature",
  "properties": {
    "gn:admin1_code":"25",
    "gn:asciiname":"Nanhuakuang",
    "gn:country_code":"CN",
    "gn:dem":227,
    "gn:feature_class":"P",
    "gn:feature_code":"PPL",
    "gn:name":"Nanhuakuang",
    "gn:population":0,
    "gn:timezone":"Asia/Shanghai",
    "iso:country":"CN",
    "name:zho_x_preferred":[
        "\u5357\u82b1\u593c"
    ],
    "wof:name":"Nanhuakuang",
    "wof:placetype":"locality"
},
  "geometry": {"coordinates":[120.73099999999999,37.5093],"type":"Point"}
}