{
  "type": "Feature",
  "properties": {
    "gn:admin1_code":"26.0",
    "gn:asciiname":"Jishan",
    "gn:country_code":"CN",
    "gn:dem":1283,
    "gn:feature_class":"P",
    "gn:feature_code":"PPL",
    "gn:name":"Jishan",
    "gn:population":0,
    "gn:timezone":"Asia/Shanghai",
    "iso:country":"CN",
    "name:deu_x_preferred":[
        "Jishan"
    ],
    "name:zho_x_preferred":[
        "\u9e21\u5c71"
    ],
    "wof:name":"Jishan",
    "wof:placetype":"locality"
},
  "geometry": {"coordinates":[109.50351000000001,37.73168],"type":"Point"}
}