{
  "type": "Feature",
  "properties": {
    "gn:admin1_code":"16",
    "gn:asciiname":"Suxu",
    "gn:cc2":"CN",
    "gn:country_code":"CN",
    "gn:dem":140,
    "gn:feature_class":"P",
    "gn:feature_code":"PPL",
    "gn:name":"Suxu",
    "gn:population":0,
    "gn:timezone":"Asia/Shanghai",
    "iso:country":"CN",
    "name:und_x_variant":[
        "Ssu-hs\u00fc",
        "Su-hs\u00fc",
        "Su-ts\u2019un",
        "Suxu"
    ],
    "wof:name":"Suxu",
    "wof:placetype":"locality"
},
  "geometry": {"coordinates":[108.09999999999999,22.55],"type":"Point"}
}