{
  "type": "Feature",
  "properties": {
    "gn:admin1_code":"12.0",
    "gn:asciiname":"Zhaojiachang",
    "gn:country_code":"CN",
    "gn:dem":35,
    "gn:feature_class":"P",
    "gn:feature_code":"PPL",
    "gn:name":"Zhaojiachang",
    "gn:population":0,
    "gn:timezone":"Asia/Shanghai",
    "iso:country":"CN",
    "name:zho_x_preferred":[
        "Zhaojiachang"
    ],
    "name:zho_x_variant":[
        "\u8d75\u5bb6\u573a"
    ],
    "wof:name":"Zhaojiachang",
    "wof:placetype":"locality"
},
  "geometry": {"coordinates":[112.93778,30.66321],"type":"Point"}
}