{
  "type": "Feature",
  "properties": {
    "gn:admin1_code":"24.0",
    "gn:asciiname":"Ximingde",
    "gn:country_code":"CN",
    "gn:dem":483,
    "gn:feature_class":"P",
    "gn:feature_code":"PPL",
    "gn:name":"Ximingde",
    "gn:population":0,
    "gn:timezone":"Asia/Shanghai",
    "iso:country":"CN",
    "name:und_x_variant":[
        "\u897f\u660e\u5fb7"
    ],
    "wof:name":"Ximingde",
    "wof:placetype":"locality"
},
  "geometry": {"coordinates":[111.52903999999999,35.59362],"type":"Point"}
}