{
  "type": "Feature",
  "properties": {
    "gn:admin1_code":"18",
    "gn:asciiname":"Chalinbian",
    "gn:country_code":"CN",
    "gn:dem":857,
    "gn:feature_class":"P",
    "gn:feature_code":"PPL",
    "gn:name":"Chalinbian",
    "gn:population":0,
    "gn:timezone":"Asia/Shanghai",
    "iso:country":"CN",
    "name:zho_x_preferred":[
        "\u8336\u6797\u8fb9"
    ],
    "wof:name":"Chalinbian",
    "wof:placetype":"locality"
},
  "geometry": {"coordinates":[108.071,27.2657],"type":"Point"}
}