{
  "type": "Feature",
  "properties": {
    "gn:admin1_code":"4.0",
    "gn:asciiname":"Beiwuzhuang",
    "gn:country_code":"CN",
    "gn:dem":1,
    "gn:feature_class":"P",
    "gn:feature_code":"PPL",
    "gn:name":"Beiwuzhuang",
    "gn:population":0,
    "gn:timezone":"Asia/Shanghai",
    "iso:country":"CN",
    "name:zho_x_preferred":[
        "\u5317\u5434\u5e84"
    ],
    "wof:name":"Beiwuzhuang",
    "wof:placetype":"locality"
},
  "geometry": {"coordinates":[119.63639000000001,32.75018],"type":"Point"}
}