{
  "type": "Feature",
  "properties": {
    "gn:admin1_code":"26.0",
    "gn:asciiname":"Changhedi",
    "gn:country_code":"CN",
    "gn:dem":974,
    "gn:feature_class":"P",
    "gn:feature_code":"PPL",
    "gn:name":"Changhedi",
    "gn:population":0,
    "gn:timezone":"Asia/Shanghai",
    "iso:country":"CN",
    "name:zho_x_preferred":[
        "\u957f\u6cb3\u5730"
    ],
    "wof:name":"Changhedi",
    "wof:placetype":"locality"
},
  "geometry": {"coordinates":[107.79675,32.68427],"type":"Point"}
}