{
  "type": "Feature",
  "properties": {
    "gn:admin1_code":"14.0",
    "gn:asciiname":"Langmucuo",
    "gn:country_code":"CN",
    "gn:dem":4845,
    "gn:feature_class":"P",
    "gn:feature_code":"PPL",
    "gn:name":"Langmucuo",
    "gn:population":0,
    "gn:timezone":"Asia/Urumqi",
    "iso:country":"CN",
    "name:zho_x_preferred":[
        "\u6717\u6728\u63aa"
    ],
    "wof:name":"Langmucuo",
    "wof:placetype":"locality"
},
  "geometry": {"coordinates":[84.5765,30.905],"type":"Point"}
}