{
  "type": "Feature",
  "properties": {
    "gn:admin1_code":"15.0",
    "gn:asciiname":"Manchenjia",
    "gn:country_code":"CN",
    "gn:dem":2003,
    "gn:feature_class":"P",
    "gn:feature_code":"PPL",
    "gn:name":"Manchenjia",
    "gn:population":0,
    "gn:timezone":"Asia/Shanghai",
    "iso:country":"CN",
    "name:zho_x_preferred":[
        "\u6ee1\u9648\u5bb6"
    ],
    "wof:name":"Manchenjia",
    "wof:placetype":"locality"
},
  "geometry": {"coordinates":[103.00700000000001,35.6821],"type":"Point"}
}