{
  "type": "Feature",
  "properties": {
    "gn:admin1_code":"18.0",
    "gn:asciiname":"Xiaokezhai",
    "gn:country_code":"CN",
    "gn:dem":576,
    "gn:feature_class":"P",
    "gn:feature_code":"PPL",
    "gn:name":"Xiaokezhai",
    "gn:population":0,
    "gn:timezone":"Asia/Shanghai",
    "iso:country":"CN",
    "name:zho_x_preferred":[
        "\u5c0f\u514b\u5be8"
    ],
    "wof:name":"Xiaokezhai",
    "wof:placetype":"locality"
},
  "geometry": {"coordinates":[109.16200000000001,27.4322],"type":"Point"}
}