{
  "type": "Feature",
  "properties": {
    "gn:admin1_code":"26.0",
    "gn:asciiname":"Tudiya",
    "gn:country_code":"CN",
    "gn:dem":1062,
    "gn:feature_class":"P",
    "gn:feature_code":"PPL",
    "gn:name":"Tudiya",
    "gn:population":0,
    "gn:timezone":"Asia/Shanghai",
    "iso:country":"CN",
    "name:und_x_variant":[
        "\u571f\u5730\u57ad"
    ],
    "wof:name":"Tudiya",
    "wof:placetype":"locality"
},
  "geometry": {"coordinates":[106.62683,32.94515999999999],"type":"Point"}
}