{
  "type": "Feature",
  "properties": {
    "gn:admin1_code":"22",
    "gn:asciiname":"Yangfang",
    "gn:country_code":"CN",
    "gn:dem":66,
    "gn:feature_class":"P",
    "gn:feature_code":"PPLA4",
    "gn:name":"Yangfang",
    "gn:population":0,
    "gn:timezone":"Asia/Shanghai",
    "iso:country":"CN",
    "name:und_x_variant":[
        "Yanfan",
        "Yang-fang-chen",
        "Yangfang",
        "Yangfang Zhen"
    ],
    "name:zho_x_preferred":[
        "\u9633\u574a"
    ],
    "name:zho_x_variant":[
        "\u9633\u574a\u9547"
    ],
    "wof:name":"Yangfang",
    "wof:placetype":"locality"
},
  "geometry": {"coordinates":[116.12855999999999,40.13857],"type":"Point"}
}