{
  "type": "Feature",
  "properties": {
    "gn:admin1_code":"26.0",
    "gn:asciiname":"Kuyazi",
    "gn:country_code":"CN",
    "gn:dem":1337,
    "gn:feature_class":"P",
    "gn:feature_code":"PPL",
    "gn:name":"Kuyazi",
    "gn:population":0,
    "gn:timezone":"Asia/Shanghai",
    "iso:country":"CN",
    "name:zho_x_preferred":[
        "\u82e6\u5d16\u5b50"
    ],
    "wof:name":"Kuyazi",
    "wof:placetype":"locality"
},
  "geometry": {"coordinates":[109.21216,35.25473],"type":"Point"}
}