{
  "type": "Feature",
  "properties": {
    "gn:admin1_code":"12.0",
    "gn:asciiname":"Wuguibei",
    "gn:country_code":"CN",
    "gn:dem":1101,
    "gn:feature_class":"P",
    "gn:feature_code":"PPL",
    "gn:name":"Wuguibei",
    "gn:population":0,
    "gn:timezone":"Asia/Shanghai",
    "iso:country":"CN",
    "name:zho_x_preferred":[
        "\u4e4c\u9f9f\u7891"
    ],
    "wof:name":"Wuguibei",
    "wof:placetype":"locality"
},
  "geometry": {"coordinates":[110.31610999999999,30.59733],"type":"Point"}
}