{
  "type": "Feature",
  "properties": {
    "gn:admin1_code":"1.0",
    "gn:asciiname":"Gongjin",
    "gn:country_code":"CN",
    "gn:dem":9,
    "gn:feature_class":"P",
    "gn:feature_code":"PPL",
    "gn:name":"Gongjin",
    "gn:population":0,
    "gn:timezone":"Asia/Shanghai",
    "iso:country":"CN",
    "name:zho_x_preferred":[
        "\u5bab\u9526"
    ],
    "wof:name":"Gongjin",
    "wof:placetype":"locality"
},
  "geometry": {"coordinates":[118.42409000000001,31.66247000000001],"type":"Point"}
}