{
  "type": "Feature",
  "properties": {
    "gn:admin1_code":"26.0",
    "gn:asciiname":"Tianjiacun",
    "gn:country_code":"CN",
    "gn:dem":1076,
    "gn:feature_class":"P",
    "gn:feature_code":"PPL",
    "gn:name":"Tianjiacun",
    "gn:population":0,
    "gn:timezone":"Asia/Shanghai",
    "iso:country":"CN",
    "name:zho_x_preferred":[
        "\u7530\u5bb6\u6751"
    ],
    "wof:name":"Tianjiacun",
    "wof:placetype":"locality"
},
  "geometry": {"coordinates":[110.11103,34.21523],"type":"Point"}
}