{
  "type": "Feature",
  "properties": {
    "gn:admin1_code":"25",
    "gn:asciiname":"Beitaiping",
    "gn:country_code":"CN",
    "gn:dem":179,
    "gn:feature_class":"P",
    "gn:feature_code":"PPL",
    "gn:name":"Beitaiping",
    "gn:population":0,
    "gn:timezone":"Asia/Shanghai",
    "iso:country":"CN",
    "name:zho_x_preferred":[
        "\u5317\u592a\u5e73"
    ],
    "wof:name":"Beitaiping",
    "wof:placetype":"locality"
},
  "geometry": {"coordinates":[118.06100000000001,35.6255],"type":"Point"}
}