{
  "type": "Feature",
  "properties": {
    "gn:admin1_code":"5.0",
    "gn:asciiname":"Yingwucun",
    "gn:country_code":"CN",
    "gn:dem":304,
    "gn:feature_class":"P",
    "gn:feature_code":"PPL",
    "gn:name":"Yingwucun",
    "gn:population":0,
    "gn:timezone":"Asia/Shanghai",
    "iso:country":"CN",
    "name:zho_x_preferred":[
        "\u82f1\u6b66\u6751"
    ],
    "wof:name":"Yingwucun",
    "wof:placetype":"locality"
},
  "geometry": {"coordinates":[125.42455,42.89768],"type":"Point"}
}