{
  "type": "Feature",
  "properties": {
    "gn:admin1_code":"33.0",
    "gn:asciiname":"Yuquanwan",
    "gn:country_code":"CN",
    "gn:dem":145,
    "gn:feature_class":"P",
    "gn:feature_code":"PPL",
    "gn:name":"Yuquanwan",
    "gn:population":0,
    "gn:timezone":"Asia/Shanghai",
    "iso:country":"CN",
    "name:zho_x_preferred":[
        "\u9c7c\u6cc9\u6e7e"
    ],
    "wof:name":"Yuquanwan",
    "wof:placetype":"locality"
},
  "geometry": {"coordinates":[109.92184,31.14286],"type":"Point"}
}