{
  "type": "Feature",
  "properties": {
    "gn:admin1_code":"10",
    "gn:asciiname":"Sizhuang",
    "gn:cc2":"CN",
    "gn:country_code":"CN",
    "gn:dem":21,
    "gn:feature_class":"P",
    "gn:feature_code":"PPL",
    "gn:name":"Sizhuang",
    "gn:population":0,
    "gn:timezone":"Asia/Shanghai",
    "iso:country":"CN",
    "name:und_x_variant":[
        "Ssu-chuang-chen",
        "Ssu-chuang",
        "Sizhuang"
    ],
    "wof:name":"Sizhuang",
    "wof:placetype":"locality"
},
  "geometry": {"coordinates":[116.03610999999999,39.17278],"type":"Point"}
}