{
  "type": "Feature",
  "properties": {
    "gn:admin1_code":"29.0",
    "gn:asciiname":"Jianggan",
    "gn:country_code":"CN",
    "gn:dem":2056,
    "gn:feature_class":"P",
    "gn:feature_code":"PPL",
    "gn:name":"Jianggan",
    "gn:population":0,
    "gn:timezone":"Asia/Shanghai",
    "iso:country":"CN",
    "name:zho_x_preferred":[
        "\u6c5f\u5e72"
    ],
    "wof:name":"Jianggan",
    "wof:placetype":"locality"
},
  "geometry": {"coordinates":[99.9499,26.1242],"type":"Point"}
}