{
  "type": "Feature",
  "properties": {
    "gn:admin1_code":"32.0",
    "gn:asciiname":"Suoba",
    "gn:country_code":"CN",
    "gn:dem":3786,
    "gn:feature_class":"P",
    "gn:feature_code":"PPL",
    "gn:name":"Suoba",
    "gn:population":0,
    "gn:timezone":"Asia/Shanghai",
    "iso:country":"CN",
    "name:zho_x_preferred":[
        "\u6240\u5df4"
    ],
    "wof:name":"Suoba",
    "wof:placetype":"locality"
},
  "geometry": {"coordinates":[99.02769000000001,32.36669000000001],"type":"Point"}
}