{
  "type": "Feature",
  "properties": {
    "gn:admin1_code":"10",
    "gn:asciiname":"Sujigou",
    "gn:country_code":"CN",
    "gn:dem":1472,
    "gn:feature_class":"P",
    "gn:feature_code":"PPL",
    "gn:name":"Sujigou",
    "gn:population":0,
    "gn:timezone":"Asia/Shanghai",
    "iso:country":"CN",
    "name:zho_x_preferred":[
        "\u82cf\u8ba1\u6c9f"
    ],
    "wof:name":"Sujigou",
    "wof:placetype":"locality"
},
  "geometry": {"coordinates":[114.84755,42.02063],"type":"Point"}
}