{
  "type": "Feature",
  "properties": {
    "gn:admin1_code":"3.0",
    "gn:asciiname":"Nuanhu",
    "gn:country_code":"CN",
    "gn:dem":30,
    "gn:feature_class":"P",
    "gn:feature_code":"PPL",
    "gn:name":"Nuanhu",
    "gn:population":0,
    "gn:timezone":"Asia/Shanghai",
    "iso:country":"CN",
    "name:und_x_variant":[
        "\u6696\u6e56"
    ],
    "wof:name":"Nuanhu",
    "wof:placetype":"locality"
},
  "geometry": {"coordinates":[116.57633,29.30381],"type":"Point"}
}