{
  "type": "Feature",
  "properties": {
    "gn:admin1_code":"14",
    "gn:asciiname":"Kule",
    "gn:country_code":"CN",
    "gn:dem":3938,
    "gn:feature_class":"P",
    "gn:feature_code":"PPL",
    "gn:name":"Kule",
    "gn:population":0,
    "gn:timezone":"Asia/Urumqi",
    "iso:country":"CN",
    "name:fra_x_preferred":[
        "Kule"
    ],
    "name:ita_x_preferred":[
        "Kule"
    ],
    "name:mlg_x_preferred":[
        "Kule"
    ],
    "name:nld_x_preferred":[
        "Kule"
    ],
    "name:pol_x_preferred":[
        "Kule"
    ],
    "name:swa_x_preferred":[
        "Kule"
    ],
    "name:swe_x_preferred":[
        "Kule"
    ],
    "name:tsn_x_preferred":[
        "Kule"
    ],
    "name:zho_x_preferred":[
        "\u82e6\u4e50"
    ],
    "wof:name":"Kule",
    "wof:placetype":"locality"
},
  "geometry": {"coordinates":[89.435,29.0704],"type":"Point"}
}