{
  "type": "Feature",
  "properties": {
    "gn:admin1_code":"19",
    "gn:asciiname":"Beijingzi",
    "gn:cc2":"CN",
    "gn:country_code":"CN",
    "gn:dem":4,
    "gn:feature_class":"P",
    "gn:feature_code":"PPL",
    "gn:name":"Beijingzi",
    "gn:population":0,
    "gn:timezone":"Asia/Shanghai",
    "iso:country":"CN",
    "name:und_x_variant":[
        "Pei-ching-tzu",
        "Beijing",
        "Beijingzi"
    ],
    "wof:name":"Beijingzi",
    "wof:placetype":"locality"
},
  "geometry": {"coordinates":[123.91194,39.8825],"type":"Point"}
}