{
  "type": "Feature",
  "properties": {
    "gn:admin1_code":"12.0",
    "gn:asciiname":"Xintianbang",
    "gn:country_code":"CN",
    "gn:dem":838,
    "gn:feature_class":"P",
    "gn:feature_code":"PPL",
    "gn:name":"Xintianbang",
    "gn:population":0,
    "gn:timezone":"Asia/Shanghai",
    "iso:country":"CN",
    "name:zho_x_preferred":[
        "\u65b0\u7530\u585d"
    ],
    "wof:name":"Xintianbang",
    "wof:placetype":"locality"
},
  "geometry": {"coordinates":[108.46930999999999,29.7482],"type":"Point"}
}