{
  "type": "Feature",
  "properties": {
    "gn:admin1_code":"29",
    "gn:asciiname":"Niubei",
    "gn:country_code":"CN",
    "gn:dem":1428,
    "gn:feature_class":"P",
    "gn:feature_code":"PPL",
    "gn:name":"Niubei",
    "gn:population":0,
    "gn:timezone":"Asia/Shanghai",
    "iso:country":"CN",
    "name:zho_x_preferred":[
        "\u725b\u80cc"
    ],
    "wof:name":"Niubei",
    "wof:placetype":"locality"
},
  "geometry": {"coordinates":[103.43600000000001,24.4406],"type":"Point"}
}