{
  "type": "Feature",
  "properties": {
    "gn:admin1_code":"32.0",
    "gn:asciiname":"Nongxing",
    "gn:country_code":"CN",
    "gn:dem":319,
    "gn:feature_class":"P",
    "gn:feature_code":"PPL",
    "gn:name":"Nongxing",
    "gn:population":0,
    "gn:timezone":"Asia/Shanghai",
    "iso:country":"CN",
    "name:zho_x_preferred":[
        "\u519c\u5174"
    ],
    "wof:name":"Nongxing",
    "wof:placetype":"locality"
},
  "geometry": {"coordinates":[105.95008,30.47647000000001],"type":"Point"}
}