{
  "type": "Feature",
  "properties": {
    "gn:admin1_code":"3.0",
    "gn:asciiname":"Banjia'ao",
    "gn:country_code":"CN",
    "gn:dem":473,
    "gn:feature_class":"P",
    "gn:feature_code":"PPL",
    "gn:name":"Banjia\u2019ao",
    "gn:population":0,
    "gn:timezone":"Asia/Shanghai",
    "iso:country":"CN",
    "name:und_x_variant":[
        "Banjia\u2019ao",
        "\u677f\u5bb6\u5773"
    ],
    "wof:name":"Banjia'ao",
    "wof:placetype":"locality"
},
  "geometry": {"coordinates":[115.46889,29.15436],"type":"Point"}
}