{
  "type": "Feature",
  "properties": {
    "gn:admin1_code":"4.0",
    "gn:asciiname":"Qianhu",
    "gn:country_code":"CN",
    "gn:dem":3,
    "gn:feature_class":"P",
    "gn:feature_code":"PPL",
    "gn:name":"Qianhu",
    "gn:population":0,
    "gn:timezone":"Asia/Shanghai",
    "iso:country":"CN",
    "name:und_x_variant":[
        "\u5343\u6237"
    ],
    "name:zho_x_preferred":[
        "\u5343\u6237"
    ],
    "wof:name":"Qianhu",
    "wof:placetype":"locality"
},
  "geometry": {"coordinates":[120.11463999999999,32.76444],"type":"Point"}
}