{
  "type": "Feature",
  "properties": {
    "gn:admin1_code":"29.0",
    "gn:asciiname":"Xiaojianshan",
    "gn:country_code":"CN",
    "gn:dem":1531,
    "gn:feature_class":"P",
    "gn:feature_code":"PPL",
    "gn:name":"Xiaojianshan",
    "gn:population":0,
    "gn:timezone":"Asia/Shanghai",
    "iso:country":"CN",
    "name:zho_x_preferred":[
        "\u5c0f\u5c16\u5c71"
    ],
    "wof:name":"Xiaojianshan",
    "wof:placetype":"locality"
},
  "geometry": {"coordinates":[103.79600000000001,23.8523],"type":"Point"}
}