{
  "type": "Feature",
  "properties": {
    "gn:admin1_code":"26.0",
    "gn:asciiname":"Duguishili",
    "gn:country_code":"CN",
    "gn:dem":1224,
    "gn:feature_class":"P",
    "gn:feature_code":"PPL",
    "gn:name":"Duguishili",
    "gn:population":0,
    "gn:timezone":"Asia/Shanghai",
    "iso:country":"CN",
    "name:zho_x_preferred":[
        "\u90fd\u8d35\u4ec0\u91cc"
    ],
    "wof:name":"Duguishili",
    "wof:placetype":"locality"
},
  "geometry": {"coordinates":[110.17804,39.39108],"type":"Point"}
}