{
  "type": "Feature",
  "properties": {
    "gn:admin1_code":"12.0",
    "gn:asciiname":"Chiba",
    "gn:country_code":"CN",
    "gn:dem":31,
    "gn:feature_class":"P",
    "gn:feature_code":"PPLA4",
    "gn:name":"Chiba",
    "gn:population":0,
    "gn:timezone":"Asia/Shanghai",
    "iso:country":"CN",
    "name:und_x_variant":[
        "Chiba Zhen"
    ],
    "name:zho_x_preferred":[
        "\u5c3a\u516b"
    ],
    "name:zho_x_variant":[
        "\u5c3a\u516b\u9547"
    ],
    "wof:name":"Chiba",
    "wof:placetype":"locality"
},
  "geometry": {"coordinates":[113.01197000000001,29.59004],"type":"Point"}
}