{
  "type": "Feature",
  "properties": {
    "gn:admin1_code":"12.0",
    "gn:asciiname":"Chiba",
    "gn:country_code":"CN",
    "gn:dem":31,
    "gn:feature_class":"P",
    "gn:feature_code":"PPLA4",
    "gn:name":"Chiba",
    "gn:population":0,
    "gn:timezone":"Asia/Shanghai",
    "iso:country":"CN",
    "name:ast_x_preferred":[
        "Chiba"
    ],
    "name:cat_x_preferred":[
        "Chiba"
    ],
    "name:ceb_x_preferred":[
        "Chiba"
    ],
    "name:deu_x_preferred":[
        "Chiba"
    ],
    "name:epo_x_preferred":[
        "\u0108iba"
    ],
    "name:fas_x_preferred":[
        "\u0686\u06cc\u0628\u0627"
    ],
    "name:fra_x_preferred":[
        "Chiba"
    ],
    "name:ita_x_preferred":[
        "Chiba"
    ],
    "name:mlg_x_preferred":[
        "Chiba"
    ],
    "name:nld_x_preferred":[
        "Chiba"
    ],
    "name:nor_x_preferred":[
        "Chiba"
    ],
    "name:pol_x_preferred":[
        "Chiba"
    ],
    "name:rus_x_preferred":[
        "\u0422\u0438\u0431\u0430"
    ],
    "name:sco_x_preferred":[
        "Chiba"
    ],
    "name:slk_x_preferred":[
        "\u010ciba"
    ],
    "name:spa_x_preferred":[
        "Chiba"
    ],
    "name:srp_x_preferred":[
        "\u0427\u0438\u0431\u0430"
    ],
    "name:swa_x_preferred":[
        "Chiba"
    ],
    "name:swe_x_preferred":[
        "Chiba"
    ],
    "name:tha_x_preferred":[
        "\u0e0a\u0e34\u0e1a\u0e30"
    ],
    "name:tur_x_preferred":[
        "Chiba"
    ],
    "name:ukr_x_preferred":[
        "\u0422\u0456\u0431\u0430"
    ],
    "name:und_x_variant":[
        "Chiba Zhen"
    ],
    "name:zho_x_preferred":[
        "\u5c3a\u516b"
    ],
    "name:zho_x_variant":[
        "\u5c3a\u516b\u9547"
    ],
    "wof:name":"Chiba",
    "wof:placetype":"locality"
},
  "geometry": {"coordinates":[113.01197000000001,29.59004],"type":"Point"}
}