{
  "type": "Feature",
  "properties": {
    "gn:admin1_code":"12.0",
    "gn:asciiname":"Yaocai",
    "gn:country_code":"CN",
    "gn:dem":1422,
    "gn:feature_class":"P",
    "gn:feature_code":"PPL",
    "gn:name":"Yaocai",
    "gn:population":0,
    "gn:timezone":"Asia/Shanghai",
    "iso:country":"CN",
    "name:zho_x_preferred":[
        "\u836f\u6750"
    ],
    "wof:name":"Yaocai",
    "wof:placetype":"locality"
},
  "geometry": {"coordinates":[108.71492000000001,30.47704],"type":"Point"}
}