{
  "type": "Feature",
  "properties": {
    "gn:admin1_code":"6.0",
    "gn:asciiname":"Lazhawo Mada",
    "gn:country_code":"CN",
    "gn:dem":4187,
    "gn:feature_class":"P",
    "gn:feature_code":"PPL",
    "gn:name":"Lazhawo Mada",
    "gn:population":0,
    "gn:timezone":"Asia/Urumqi",
    "iso:country":"CN",
    "name:zho_x_preferred":[
        "\u62c9\u624e\u7a9d\u739b\u8fbe"
    ],
    "wof:name":"Lazhawo Mada",
    "wof:placetype":"locality"
},
  "geometry": {"coordinates":[96.81010999999999,33.73671],"type":"Point"}
}