{
  "type": "Feature",
  "properties": {
    "gn:admin1_code":"14.0",
    "gn:asciiname":"Xuedacun",
    "gn:country_code":"CN",
    "gn:dem":4129,
    "gn:feature_class":"P",
    "gn:feature_code":"PPL",
    "gn:name":"Xuedacun",
    "gn:population":0,
    "gn:timezone":"Asia/Urumqi",
    "iso:country":"CN",
    "name:zho_x_preferred":[
        "\u5b66\u8fbe\u6751"
    ],
    "wof:name":"Xuedacun",
    "wof:placetype":"locality"
},
  "geometry": {"coordinates":[97.73107,30.26982000000001],"type":"Point"}
}