{
  "type": "Feature",
  "properties": {
    "gn:admin1_code":"24.0",
    "gn:asciiname":"Shandongzhuangcun",
    "gn:country_code":"CN",
    "gn:dem":384,
    "gn:feature_class":"P",
    "gn:feature_code":"PPL",
    "gn:name":"Shandongzhuangcun",
    "gn:population":0,
    "gn:timezone":"Asia/Shanghai",
    "iso:country":"CN",
    "name:zho_x_preferred":[
        "\u5c71\u4e1c\u5e84\u6751"
    ],
    "wof:name":"Shandongzhuangcun",
    "wof:placetype":"locality"
},
  "geometry": {"coordinates":[110.50745999999999,35.01855],"type":"Point"}
}