{
  "type": "Feature",
  "properties": {
    "gn:admin1_code":"2.0",
    "gn:asciiname":"Danwu",
    "gn:country_code":"CN",
    "gn:dem":96,
    "gn:feature_class":"P",
    "gn:feature_code":"PPL",
    "gn:name":"Danwu",
    "gn:population":0,
    "gn:timezone":"Asia/Shanghai",
    "iso:country":"CN",
    "name:und_x_variant":[
        "\u6de1\u575e"
    ],
    "wof:name":"Danwu",
    "wof:placetype":"locality"
},
  "geometry": {"coordinates":[119.88688999999999,30.46881],"type":"Point"}
}