{
  "type": "Feature",
  "properties": {
    "gn:admin1_code":"18",
    "gn:asciiname":"Zuojiga",
    "gn:country_code":"CN",
    "gn:dem":1371,
    "gn:feature_class":"P",
    "gn:feature_code":"PPL",
    "gn:name":"Zuojiga",
    "gn:population":0,
    "gn:timezone":"Asia/Shanghai",
    "iso:country":"CN",
    "name:zho_x_preferred":[
        "\u5750\u57fa\u560e"
    ],
    "wof:name":"Zuojiga",
    "wof:placetype":"locality"
},
  "geometry": {"coordinates":[105.67100000000001,26.9625],"type":"Point"}
}