{
  "type": "Feature",
  "properties": {
    "gn:admin1_code":"4.0",
    "gn:asciiname":"Guoyuan'er Gongqucun",
    "gn:country_code":"CN",
    "gn:dem":29,
    "gn:feature_class":"P",
    "gn:feature_code":"PPLF",
    "gn:name":"Guoyuan\u2019er Gongqucun",
    "gn:population":0,
    "gn:timezone":"Asia/Shanghai",
    "iso:country":"CN",
    "name:und_x_variant":[
        "Guoyuan\u2019er Gongqucun"
    ],
    "name:zho_x_preferred":[
        "\u679c\u56ed\u4e8c\u5de5\u533a\u6751"
    ],
    "wof:name":"Guoyuan'er Gongqucun",
    "wof:placetype":"locality"
},
  "geometry": {"coordinates":[118.04148000000001,34.38376],"type":"Point"}
}