{
  "type": "Feature",
  "properties": {
    "gn:admin1_code":"18",
    "gn:asciiname":"Hongjiaodi",
    "gn:country_code":"CN",
    "gn:dem":1135,
    "gn:feature_class":"P",
    "gn:feature_code":"PPL",
    "gn:name":"Hongjiaodi",
    "gn:population":0,
    "gn:timezone":"Asia/Shanghai",
    "iso:country":"CN",
    "name:zho_x_preferred":[
        "\u7ea2\u811a\u5730"
    ],
    "wof:name":"Hongjiaodi",
    "wof:placetype":"locality"
},
  "geometry": {"coordinates":[107.483,27.8238],"type":"Point"}
}