{
  "type": "Feature",
  "properties": {
    "gn:admin1_code":"29.0",
    "gn:asciiname":"Pojiao",
    "gn:country_code":"CN",
    "gn:dem":2223,
    "gn:feature_class":"P",
    "gn:feature_code":"PPL",
    "gn:name":"Pojiao",
    "gn:population":0,
    "gn:timezone":"Asia/Shanghai",
    "iso:country":"CN",
    "name:und_x_variant":[
        "\u5761\u811a"
    ],
    "wof:name":"Pojiao",
    "wof:placetype":"locality"
},
  "geometry": {"coordinates":[103.57389000000001,27.08935],"type":"Point"}
}