{
  "type": "Feature",
  "properties": {
    "gn:admin1_code":"12.0",
    "gn:asciiname":"Wuziya",
    "gn:country_code":"CN",
    "gn:dem":1108,
    "gn:feature_class":"P",
    "gn:feature_code":"PPL",
    "gn:name":"Wuziya",
    "gn:population":0,
    "gn:timezone":"Asia/Shanghai",
    "iso:country":"CN",
    "name:zho_x_preferred":[
        "\u620a\u5b50\u57ad"
    ],
    "wof:name":"Wuziya",
    "wof:placetype":"locality"
},
  "geometry": {"coordinates":[110.23276,31.32274],"type":"Point"}
}