{
  "type": "Feature",
  "properties": {
    "gn:admin1_code":"32.0",
    "gn:asciiname":"Baiyangdong",
    "gn:country_code":"CN",
    "gn:dem":815,
    "gn:feature_class":"P",
    "gn:feature_code":"PPL",
    "gn:name":"Baiyangdong",
    "gn:population":0,
    "gn:timezone":"Asia/Shanghai",
    "iso:country":"CN",
    "name:zho_x_preferred":[
        "\u767d\u9633\u6d1e"
    ],
    "wof:name":"Baiyangdong",
    "wof:placetype":"locality"
},
  "geometry": {"coordinates":[104.96802,32.07452],"type":"Point"}
}