{
  "type": "Feature",
  "properties": {
    "gn:admin1_code":"29.0",
    "gn:asciiname":"Xialiangtai",
    "gn:country_code":"CN",
    "gn:dem":1746,
    "gn:feature_class":"P",
    "gn:feature_code":"PPL",
    "gn:name":"Xialiangtai",
    "gn:population":0,
    "gn:timezone":"Asia/Shanghai",
    "iso:country":"CN",
    "name:zho_x_preferred":[
        "\u4e0b\u6881\u53f0"
    ],
    "wof:name":"Xialiangtai",
    "wof:placetype":"locality"
},
  "geometry": {"coordinates":[99.0437,27.4616],"type":"Point"}
}