{
  "type": "Feature",
  "properties": {
    "gn:admin1_code":"29",
    "gn:asciiname":"Weigeng",
    "gn:country_code":"CN",
    "gn:dem":1872,
    "gn:feature_class":"P",
    "gn:feature_code":"PPL",
    "gn:name":"Weigeng",
    "gn:population":0,
    "gn:timezone":"Asia/Shanghai",
    "iso:country":"CN",
    "name:zho_x_preferred":[
        "\u56f4\u57c2"
    ],
    "wof:name":"Weigeng",
    "wof:placetype":"locality"
},
  "geometry": {"coordinates":[102.63800000000001,24.3739],"type":"Point"}
}