{
  "type": "Feature",
  "properties": {
    "gn:admin1_code":"9",
    "gn:asciiname":"Qingshigun",
    "gn:country_code":"CN",
    "gn:dem":52,
    "gn:feature_class":"P",
    "gn:feature_code":"PPL",
    "gn:name":"Qingshigun",
    "gn:population":0,
    "gn:timezone":"Asia/Shanghai",
    "iso:country":"CN",
    "name:zho_x_preferred":[
        "\u9752\u77f3\u6eda"
    ],
    "wof:name":"Qingshigun",
    "wof:placetype":"locality"
},
  "geometry": {"coordinates":[115.09354999999999,36.03193],"type":"Point"}
}