{
  "type": "Feature",
  "properties": {
    "gn:admin1_code":"19.0",
    "gn:asciiname":"Gongjia Wobu",
    "gn:country_code":"CN",
    "gn:dem":187,
    "gn:feature_class":"P",
    "gn:feature_code":"PPL",
    "gn:name":"Gongjia Wobu",
    "gn:population":0,
    "gn:timezone":"Asia/Shanghai",
    "iso:country":"CN",
    "name:und_x_variant":[
        "Gongjiawobao",
        "Gongjia Wobu"
    ],
    "name:zho_x_preferred":[
        "\u516c\u5bb6\u7a9d\u5821"
    ],
    "wof:name":"Gongjia Wobu",
    "wof:placetype":"locality"
},
  "geometry": {"coordinates":[122.66624,42.68657],"type":"Point"}
}