{
  "type": "Feature",
  "properties": {
    "gn:admin1_code":"33.0",
    "gn:asciiname":"Changlong",
    "gn:country_code":"CN",
    "gn:dem":736,
    "gn:feature_class":"P",
    "gn:feature_code":"PPL",
    "gn:name":"Changlong",
    "gn:population":0,
    "gn:timezone":"Asia/Shanghai",
    "iso:country":"CN",
    "name:zho_x_preferred":[
        "\u957f\u9f99"
    ],
    "wof:name":"Changlong",
    "wof:placetype":"locality"
},
  "geometry": {"coordinates":[109.41307,31.34015],"type":"Point"}
}