{
  "type": "Feature",
  "properties": {
    "gn:admin1_code":"3.0",
    "gn:asciiname":"Xiayucun",
    "gn:country_code":"CN",
    "gn:dem":26,
    "gn:feature_class":"P",
    "gn:feature_code":"PPL",
    "gn:name":"Xiayucun",
    "gn:population":0,
    "gn:timezone":"Asia/Shanghai",
    "iso:country":"CN",
    "name:und_x_variant":[
        "\u590f\u5b87\u6751"
    ],
    "wof:name":"Xiayucun",
    "wof:placetype":"locality"
},
  "geometry": {"coordinates":[115.72768000000001,28.54036],"type":"Point"}
}