{
  "type": "Feature",
  "properties": {
    "gn:admin1_code":"30.0",
    "gn:asciiname":"Kengweicun",
    "gn:country_code":"CN",
    "gn:dem":348,
    "gn:feature_class":"P",
    "gn:feature_code":"PPL",
    "gn:name":"Kengweicun",
    "gn:population":0,
    "gn:timezone":"Asia/Shanghai",
    "iso:country":"CN",
    "name:zho_x_preferred":[
        "\u5751\u5c3e\u6751"
    ],
    "wof:name":"Kengweicun",
    "wof:placetype":"locality"
},
  "geometry": {"coordinates":[116.44431000000002,24.38257],"type":"Point"}
}