{
  "type": "Feature",
  "properties": {
    "gn:admin1_code":"4.0",
    "gn:asciiname":"Shangnong Shibadui",
    "gn:country_code":"CN",
    "gn:dem":-1,
    "gn:feature_class":"P",
    "gn:feature_code":"PPLF",
    "gn:name":"Shangnong Shibadui",
    "gn:population":0,
    "gn:timezone":"Asia/Shanghai",
    "iso:country":"CN",
    "name:und_x_variant":[
        "\u4e0a\u519c\u5341\u516b\u961f"
    ],
    "wof:name":"Shangnong Shibadui",
    "wof:placetype":"locality"
},
  "geometry": {"coordinates":[120.58487,33.35146],"type":"Point"}
}