{
  "type": "Feature",
  "properties": {
    "gn:admin1_code":"31",
    "gn:asciiname":"Liren",
    "gn:country_code":"CN",
    "gn:dem":13,
    "gn:feature_class":"P",
    "gn:feature_code":"PPL",
    "gn:name":"Liren",
    "gn:population":0,
    "gn:timezone":"Asia/Shanghai",
    "iso:country":"CN",
    "name:und_x_variant":[
        "\u91cc\u4ec1"
    ],
    "wof:name":"Liren",
    "wof:placetype":"locality"
},
  "geometry": {"coordinates":[109.38800000000001,19.7238],"type":"Point"}
}