{
  "type": "Feature",
  "properties": {
    "gn:admin1_code":"8.0",
    "gn:asciiname":"Fumincun",
    "gn:country_code":"CN",
    "gn:dem":208,
    "gn:feature_class":"P",
    "gn:feature_code":"PPL",
    "gn:name":"Fumincun",
    "gn:population":0,
    "gn:timezone":"Asia/Shanghai",
    "iso:country":"CN",
    "name:zho_x_preferred":[
        "\u5bcc\u6c11\u6751"
    ],
    "wof:name":"Fumincun",
    "wof:placetype":"locality"
},
  "geometry": {"coordinates":[131.11168999999998,45.19873],"type":"Point"}
}