{
  "type": "Feature",
  "properties": {
    "gn:admin1_code":"8.0",
    "gn:asciiname":"Daguitun",
    "gn:country_code":"CN",
    "gn:dem":259,
    "gn:feature_class":"P",
    "gn:feature_code":"PPL",
    "gn:name":"Daguitun",
    "gn:population":0,
    "gn:timezone":"Asia/Shanghai",
    "iso:country":"CN",
    "name:zho_x_preferred":[
        "\u5927\u8d35\u5c6f"
    ],
    "wof:name":"Daguitun",
    "wof:placetype":"locality"
},
  "geometry": {"coordinates":[125.8712,48.47983],"type":"Point"}
}