{
  "type": "Feature",
  "properties": {
    "gn:admin1_code":"32.0",
    "gn:asciiname":"Hongyanzi",
    "gn:country_code":"CN",
    "gn:dem":756,
    "gn:feature_class":"P",
    "gn:feature_code":"PPL",
    "gn:name":"Hongyanzi",
    "gn:population":0,
    "gn:timezone":"Asia/Shanghai",
    "iso:country":"CN",
    "name:zho_x_preferred":[
        "\u7ea2\u5ca9\u5b50"
    ],
    "wof:name":"Hongyanzi",
    "wof:placetype":"locality"
},
  "geometry": {"coordinates":[105.866,32.302],"type":"Point"}
}