{
  "type": "Feature",
  "properties": {
    "gn:admin1_code":"13",
    "gn:asciiname":"Jingerquan",
    "gn:country_code":"CN",
    "gn:dem":1346,
    "gn:feature_class":"P",
    "gn:feature_code":"PPL",
    "gn:name":"Jingerquan",
    "gn:population":0,
    "gn:timezone":"Asia/Urumqi",
    "iso:country":"CN",
    "name:zho_x_preferred":[
        "\u955c\u513f\u6cc9"
    ],
    "wof:name":"Jingerquan",
    "wof:placetype":"locality"
},
  "geometry": {"coordinates":[95.63686,42.5032],"type":"Point"}
}