{
  "type": "Feature",
  "properties": {
    "gn:admin1_code":"7.0",
    "gn:asciiname":"Xiaquyang",
    "gn:country_code":"CN",
    "gn:dem":490,
    "gn:feature_class":"P",
    "gn:feature_code":"PPL",
    "gn:name":"Xiaquyang",
    "gn:population":0,
    "gn:timezone":"Asia/Shanghai",
    "iso:country":"CN",
    "name:und_x_variant":[
        "\u4e0b\u66f2\u6d0b"
    ],
    "name:zho_x_preferred":[
        "\u4e0b\u66f2\u6d0b"
    ],
    "wof:name":"Xiaquyang",
    "wof:placetype":"locality"
},
  "geometry": {"coordinates":[117.00118999999999,25.74287],"type":"Point"}
}