{
  "type": "Feature",
  "properties": {
    "gn:admin1_code":"12.0",
    "gn:asciiname":"Changgengdi",
    "gn:country_code":"CN",
    "gn:dem":36,
    "gn:feature_class":"P",
    "gn:feature_code":"PPL",
    "gn:name":"Changgengdi",
    "gn:population":0,
    "gn:timezone":"Asia/Shanghai",
    "iso:country":"CN",
    "name:zho_x_preferred":[
        "Changgengdi"
    ],
    "name:zho_x_variant":[
        "\u957f\u57c2\u5824"
    ],
    "wof:name":"Changgengdi",
    "wof:placetype":"locality"
},
  "geometry": {"coordinates":[111.93798,30.1211],"type":"Point"}
}