{
  "type": "Feature",
  "properties": {
    "gn:admin1_code":"32.0",
    "gn:asciiname":"Laolinpan",
    "gn:country_code":"CN",
    "gn:dem":488,
    "gn:feature_class":"P",
    "gn:feature_code":"PPL",
    "gn:name":"Laolinpan",
    "gn:population":0,
    "gn:timezone":"Asia/Shanghai",
    "iso:country":"CN",
    "name:zho_x_preferred":[
        "\u8001\u6797\u76d8"
    ],
    "wof:name":"Laolinpan",
    "wof:placetype":"locality"
},
  "geometry": {"coordinates":[104.22033999999999,30.67466],"type":"Point"}
}