{
  "type": "Feature",
  "properties": {
    "gn:admin1_code":"8.0",
    "gn:asciiname":"Shidacaofang",
    "gn:country_code":"CN",
    "gn:dem":145,
    "gn:feature_class":"P",
    "gn:feature_code":"PPL",
    "gn:name":"Shidacaofang",
    "gn:population":0,
    "gn:timezone":"Asia/Shanghai",
    "iso:country":"CN",
    "name:zho_x_preferred":[
        "\u77f3\u5927\u8349\u623f"
    ],
    "wof:name":"Shidacaofang",
    "wof:placetype":"locality"
},
  "geometry": {"coordinates":[125.23367,46.38634],"type":"Point"}
}