{
  "type": "Feature",
  "properties": {
    "gn:admin1_code":"30.0",
    "gn:asciiname":"Xinjing",
    "gn:country_code":"CN",
    "gn:dem":163,
    "gn:feature_class":"P",
    "gn:feature_code":"PPL",
    "gn:name":"Xinjing",
    "gn:population":0,
    "gn:timezone":"Asia/Shanghai",
    "iso:country":"CN",
    "name:deu_x_preferred":[
        "Xinjing"
    ],
    "name:zho_x_preferred":[
        "\u65b0\u8ff3"
    ],
    "wof:name":"Xinjing",
    "wof:placetype":"locality"
},
  "geometry": {"coordinates":[114.398,25.21263],"type":"Point"}
}