{
  "type": "Feature",
  "properties": {
    "gn:admin1_code":"29.0",
    "gn:asciiname":"Shimenkan",
    "gn:country_code":"CN",
    "gn:dem":2200,
    "gn:feature_class":"P",
    "gn:feature_code":"PPL",
    "gn:name":"Shimenkan",
    "gn:population":0,
    "gn:timezone":"Asia/Shanghai",
    "iso:country":"CN",
    "name:zho_x_preferred":[
        "\u77f3\u95e8\u574e"
    ],
    "wof:name":"Shimenkan",
    "wof:placetype":"locality"
},
  "geometry": {"coordinates":[100.479,26.2605],"type":"Point"}
}