{
  "type": "Feature",
  "properties": {
    "gn:admin1_code":"30",
    "gn:asciiname":"Juntun",
    "gn:country_code":"CN",
    "gn:dem":35,
    "gn:feature_class":"P",
    "gn:feature_code":"PPL",
    "gn:name":"Juntun",
    "gn:population":0,
    "gn:timezone":"Asia/Urumqi",
    "iso:country":"CN",
    "name:zho_x_preferred":[
        "\u519b\u5c6f"
    ],
    "wof:name":"Juntun",
    "wof:placetype":"locality"
},
  "geometry": {"coordinates":[111.11058,21.74748],"type":"Point"}
}