{
  "type": "Feature",
  "properties": {
    "gn:admin1_code":"26.0",
    "gn:asciiname":"Xiangdanghekoucun",
    "gn:country_code":"CN",
    "gn:dem":428,
    "gn:feature_class":"P",
    "gn:feature_code":"PPL",
    "gn:name":"Xiangdanghekoucun",
    "gn:population":0,
    "gn:timezone":"Asia/Shanghai",
    "iso:country":"CN",
    "name:zho_x_preferred":[
        "\u54cd\u5f53\u6cb3\u53e3\u6751"
    ],
    "wof:name":"Xiangdanghekoucun",
    "wof:placetype":"locality"
},
  "geometry": {"coordinates":[109.30825,32.42952],"type":"Point"}
}