{
  "type": "Feature",
  "properties": {
    "gn:admin1_code":"7.0",
    "gn:asciiname":"Zhuotian",
    "gn:country_code":"CN",
    "gn:dem":274,
    "gn:feature_class":"P",
    "gn:feature_code":"PPLA4",
    "gn:name":"Zhuotian",
    "gn:population":0,
    "gn:timezone":"Asia/Shanghai",
    "iso:country":"CN",
    "name:und_x_variant":[
        "Cho-t\u2019ien",
        "Zhuotian",
        "\u6fef\u7530",
        "Zhuotian Zhen",
        "\u6fef\u7530\u9547"
    ],
    "wof:name":"Zhuotian",
    "wof:placetype":"locality"
},
  "geometry": {"coordinates":[116.27567999999999,25.55823],"type":"Point"}
}