{
  "type": "Feature",
  "properties": {
    "gn:admin1_code":"31",
    "gn:asciiname":"Lanyangcun",
    "gn:country_code":"CN",
    "gn:dem":168,
    "gn:feature_class":"P",
    "gn:feature_code":"PPL",
    "gn:name":"Lanyangcun",
    "gn:population":0,
    "gn:timezone":"Asia/Shanghai",
    "iso:country":"CN",
    "name:und_x_variant":[
        "\u5170\u6d0b\u6751"
    ],
    "wof:name":"Lanyangcun",
    "wof:placetype":"locality"
},
  "geometry": {"coordinates":[109.67180999999999,19.43726],"type":"Point"}
}