{
  "type": "Feature",
  "properties": {
    "gn:admin1_code":"29.0",
    "gn:asciiname":"Yongbei",
    "gn:country_code":"CN",
    "gn:dem":2537,
    "gn:feature_class":"P",
    "gn:feature_code":"PPLA3",
    "gn:name":"Yongbei",
    "gn:population":0,
    "gn:timezone":"Asia/Shanghai",
    "iso:country":"CN",
    "name:und_x_variant":[
        "Yungpeh",
        "Yung-sheng",
        "Yung-sheng-hsien",
        "Yung-sheng-chen",
        "Yongsheng",
        "Yung-shen",
        "Yung-pei",
        "Yungpeh-hsien",
        "Yongbei"
    ],
    "name:zho_x_preferred":[
        "\u6c38\u5317"
    ],
    "wof:name":"Yongbei",
    "wof:placetype":"locality"
},
  "geometry": {"coordinates":[100.78073000000001,26.64623],"type":"Point"}
}