{
  "type": "Feature",
  "properties": {
    "gn:admin1_code":"14.0",
    "gn:asciiname":"Lasuocun",
    "gn:country_code":"CN",
    "gn:dem":3669,
    "gn:feature_class":"P",
    "gn:feature_code":"PPL",
    "gn:name":"Lasuocun",
    "gn:population":0,
    "gn:timezone":"Asia/Urumqi",
    "iso:country":"CN",
    "name:zho_x_preferred":[
        "\u62c9\u7d22\u6751"
    ],
    "wof:name":"Lasuocun",
    "wof:placetype":"locality"
},
  "geometry": {"coordinates":[92.40615,29.05714],"type":"Point"}
}