{
  "type": "Feature",
  "properties": {
    "gn:admin1_code":"1.0",
    "gn:asciiname":"Magushan Linchang",
    "gn:country_code":"CN",
    "gn:dem":92,
    "gn:feature_class":"P",
    "gn:feature_code":"PPLF",
    "gn:name":"Magushan Linchang",
    "gn:population":0,
    "gn:timezone":"Asia/Shanghai",
    "iso:country":"CN",
    "wof:name":"Magushan Linchang",
    "wof:placetype":"locality"
},
  "geometry": {"coordinates":[118.91667,30.96667],"type":"Point"}
}