{
  "type": "Feature",
  "properties": {
    "gn:admin1_code":"32.0",
    "gn:asciiname":"Youfanggeng",
    "gn:country_code":"CN",
    "gn:dem":1063,
    "gn:feature_class":"P",
    "gn:feature_code":"PPL",
    "gn:name":"Youfanggeng",
    "gn:population":0,
    "gn:timezone":"Asia/Shanghai",
    "iso:country":"CN",
    "name:zho_x_preferred":[
        "\u6cb9\u623f\u57c2"
    ],
    "wof:name":"Youfanggeng",
    "wof:placetype":"locality"
},
  "geometry": {"coordinates":[103.57705,28.66733],"type":"Point"}
}