{
  "type": "Feature",
  "properties": {
    "gn:admin1_code":"12.0",
    "gn:asciiname":"Wenjiachong",
    "gn:country_code":"CN",
    "gn:dem":334,
    "gn:feature_class":"P",
    "gn:feature_code":"PPL",
    "gn:name":"Wenjiachong",
    "gn:population":0,
    "gn:timezone":"Asia/Shanghai",
    "iso:country":"CN",
    "name:zho_x_preferred":[
        "\u6587\u5bb6\u51b2"
    ],
    "wof:name":"Wenjiachong",
    "wof:placetype":"locality"
},
  "geometry": {"coordinates":[111.77213,31.82709],"type":"Point"}
}