{
  "type": "Feature",
  "properties": {
    "gn:admin1_code":"12.0",
    "gn:asciiname":"Zhifanggou",
    "gn:country_code":"CN",
    "gn:dem":992,
    "gn:feature_class":"P",
    "gn:feature_code":"PPL",
    "gn:name":"Zhifanggou",
    "gn:population":0,
    "gn:timezone":"Asia/Shanghai",
    "iso:country":"CN",
    "name:zho_x_preferred":[
        "\u7eb8\u574a\u6c9f"
    ],
    "wof:name":"Zhifanggou",
    "wof:placetype":"locality"
},
  "geometry": {"coordinates":[109.74601,31.87724],"type":"Point"}
}