{
  "type": "Feature",
  "properties": {
    "gn:country":"CN",
    "gn:fcode":"PPL",
    "gn:pop":93666,
    "iso:country":"CN",
    "name:unk_x_variant":[
        "Chengkiatun"
    ],
    "qs:name":"Zhengjiatun",
    "qs:photos_9r":0,
    "qs:photos_sr":0,
    "qs:pop_sr":"8",
    "wof:name":"Zhengjiatun",
    "wof:placetype":"locality",
    "wof:population":93666
},
  "geometry": {"coordinates":[123.50639,43.50639],"type":"Point"}
}