{
  "type": "Feature",
  "properties": {
    "gn:admin1_code":"30.0",
    "gn:asciiname":"Nandouchang",
    "gn:country_code":"CN",
    "gn:dem":16,
    "gn:feature_class":"P",
    "gn:feature_code":"PPL",
    "gn:name":"Nandouchang",
    "gn:population":0,
    "gn:timezone":"Asia/Shanghai",
    "iso:country":"CN",
    "name:zho_x_preferred":[
        "\u5357\u6597\u5382"
    ],
    "wof:name":"Nandouchang",
    "wof:placetype":"locality"
},
  "geometry": {"coordinates":[113.33293999999999,23.75345],"type":"Point"}
}