{
  "type": "Feature",
  "properties": {
    "gn:admin1_code":"29.0",
    "gn:asciiname":"Yejishan",
    "gn:country_code":"CN",
    "gn:dem":672,
    "gn:feature_class":"P",
    "gn:feature_code":"PPL",
    "gn:name":"Yejishan",
    "gn:population":0,
    "gn:timezone":"Asia/Shanghai",
    "iso:country":"CN",
    "name:zho_x_preferred":[
        "\u91ce\u9e21\u5c71"
    ],
    "wof:name":"Yejishan",
    "wof:placetype":"locality"
},
  "geometry": {"coordinates":[104.396,27.9272],"type":"Point"}
}