{
  "type": "Feature",
  "properties": {
    "gn:admin1_code":"7.0",
    "gn:asciiname":"Wenfeng",
    "gn:country_code":"CN",
    "gn:dem":353,
    "gn:feature_class":"P",
    "gn:feature_code":"PPL",
    "gn:name":"Wenfeng",
    "gn:population":0,
    "gn:timezone":"Asia/Shanghai",
    "iso:country":"CN",
    "name:zho_x_preferred":[
        "\u6587\u5cf0"
    ],
    "wof:name":"Wenfeng",
    "wof:placetype":"locality"
},
  "geometry": {"coordinates":[116.74921000000001,25.78664],"type":"Point"}
}