{
  "type": "Feature",
  "properties": {
    "gn:admin1_code":"32.0",
    "gn:asciiname":"Feihong",
    "gn:country_code":"CN",
    "gn:dem":1628,
    "gn:feature_class":"P",
    "gn:feature_code":"PPL",
    "gn:name":"Feihong",
    "gn:population":0,
    "gn:timezone":"Asia/Shanghai",
    "iso:country":"CN",
    "name:zho_x_preferred":[
        "\u98de\u8679"
    ],
    "wof:name":"Feihong",
    "wof:placetype":"locality"
},
  "geometry": {"coordinates":[103.73627999999999,31.79625],"type":"Point"}
}