{
  "type": "Feature",
  "properties": {
    "gn:admin1_code":"13.0",
    "gn:asciiname":"Yushikalasu",
    "gn:country_code":"CN",
    "gn:dem":700,
    "gn:feature_class":"P",
    "gn:feature_code":"PPLA4",
    "gn:name":"Yushikalasu",
    "gn:population":0,
    "gn:timezone":"Asia/Urumqi",
    "iso:country":"CN",
    "name:und_x_variant":[
        "\u00dcq Karasu Xiang",
        "\u00dcq Karasu",
        "Yushikalasu",
        "Yushikalasu Xiang"
    ],
    "name:zho_x_preferred":[
        "\u7389\u4ec0\u5580\u62c9\u82cf"
    ],
    "name:zho_x_variant":[
        "\u7389\u4ec0\u5580\u62c9\u82cf\u4e61"
    ],
    "wof:name":"Yushikalasu",
    "wof:placetype":"locality"
},
  "geometry": {"coordinates":[84.04501999999999,46.70969],"type":"Point"}
}