{
  "type": "Feature",
  "properties": {
    "gn:admin1_code":"5.0",
    "gn:asciiname":"Qianshisi",
    "gn:country_code":"CN",
    "gn:dem":172,
    "gn:feature_class":"P",
    "gn:feature_code":"PPL",
    "gn:name":"Qianshisi",
    "gn:population":0,
    "gn:timezone":"Asia/Shanghai",
    "iso:country":"CN",
    "name:zho_x_preferred":[
        "\u524d\u5341\u56db"
    ],
    "wof:name":"Qianshisi",
    "wof:placetype":"locality"
},
  "geometry": {"coordinates":[123.82980999999999,44.33811],"type":"Point"}
}