{
  "type": "Feature",
  "properties": {
    "gn:admin1_code":"32.0",
    "gn:asciiname":"Gaqiong",
    "gn:country_code":"CN",
    "gn:dem":3432,
    "gn:feature_class":"P",
    "gn:feature_code":"PPL",
    "gn:name":"Gaqiong",
    "gn:population":0,
    "gn:timezone":"Asia/Shanghai",
    "iso:country":"CN",
    "name:zho_x_preferred":[
        "\u560e\u7a77"
    ],
    "wof:name":"Gaqiong",
    "wof:placetype":"locality"
},
  "geometry": {"coordinates":[102.342,33.7075],"type":"Point"}
}