{
  "type": "Feature",
  "properties": {
    "gn:admin1_code":"04",
    "gn:asciiname":"Pailoucun",
    "gn:country_code":"CN",
    "gn:dem":2,
    "gn:feature_class":"P",
    "gn:feature_code":"PPL",
    "gn:name":"Pailoucun",
    "gn:population":0,
    "gn:timezone":"Asia/Shanghai",
    "iso:country":"CN",
    "name:und_x_variant":[
        "P\u2019ai-lou-shih",
        "Pailou",
        "\u724c\u697c",
        "Pailoucun"
    ],
    "name:zho_x_preferred":[
        "\u724c\u697c\u6751"
    ],
    "wof:name":"Pailoucun",
    "wof:placetype":"locality"
},
  "geometry": {"coordinates":[121.19311999999999,31.56171],"type":"Point"}
}