{
  "type": "Feature",
  "properties": {
    "gn:admin1_code":"9.0",
    "gn:asciiname":"Dakuaidi",
    "gn:country_code":"CN",
    "gn:dem":321,
    "gn:feature_class":"P",
    "gn:feature_code":"PPL",
    "gn:name":"Dakuaidi",
    "gn:population":0,
    "gn:timezone":"Asia/Shanghai",
    "iso:country":"CN",
    "name:zho_x_preferred":[
        "\u5927\u5757\u5730"
    ],
    "wof:name":"Dakuaidi",
    "wof:placetype":"locality"
},
  "geometry": {"coordinates":[111.56295,33.32918],"type":"Point"}
}