{
  "type": "Feature",
  "properties": {
    "gn:admin1_code":"31.0",
    "gn:asciiname":"Fuxiong",
    "gn:country_code":"CN",
    "gn:dem":88,
    "gn:feature_class":"P",
    "gn:feature_code":"PPL",
    "gn:name":"Fuxiong",
    "gn:population":0,
    "gn:timezone":"Asia/Shanghai",
    "iso:country":"CN",
    "name:zho_x_preferred":[
        "\u5bcc\u96c4"
    ],
    "wof:name":"Fuxiong",
    "wof:placetype":"locality"
},
  "geometry": {"coordinates":[109.86518999999998,19.81886],"type":"Point"}
}