{
  "type": "Feature",
  "properties": {
    "gn:admin1_code":"12.0",
    "gn:asciiname":"Longwangzui Nongchang",
    "gn:country_code":"CN",
    "gn:dem":29,
    "gn:feature_class":"P",
    "gn:feature_code":"PPLF",
    "gn:name":"Longwangzui Nongchang",
    "gn:population":0,
    "gn:timezone":"Asia/Shanghai",
    "iso:country":"CN",
    "name:und_x_variant":[
        "\u9f99\u738b\u5634\u519c\u573a"
    ],
    "wof:name":"Longwangzui Nongchang",
    "wof:placetype":"locality"
},
  "geometry": {"coordinates":[114.66086,30.59728],"type":"Point"}
}