{
  "type": "Feature",
  "properties": {
    "gn:admin1_code":"18",
    "gn:asciiname":"Wangjiaping",
    "gn:country_code":"CN",
    "gn:dem":1389,
    "gn:feature_class":"P",
    "gn:feature_code":"PPL",
    "gn:name":"Wangjiaping",
    "gn:population":0,
    "gn:timezone":"Asia/Shanghai",
    "iso:country":"CN",
    "name:zho_x_preferred":[
        "\u738b\u5bb6\u576a"
    ],
    "wof:name":"Wangjiaping",
    "wof:placetype":"locality"
},
  "geometry": {"coordinates":[106.52800000000001,28.5936],"type":"Point"}
}