{
  "type": "Feature",
  "properties": {
    "gn:admin1_code":"9.0",
    "gn:asciiname":"Xizhuang",
    "gn:country_code":"CN",
    "gn:dem":594,
    "gn:feature_class":"P",
    "gn:feature_code":"PPL",
    "gn:name":"Xizhuang",
    "gn:population":0,
    "gn:timezone":"Asia/Shanghai",
    "iso:country":"CN",
    "name:und_x_variant":[
        "\u897f\u5e84",
        "Xizhuang"
    ],
    "wof:name":"Xizhuang",
    "wof:placetype":"locality"
},
  "geometry": {"coordinates":[112.64499000000001,33.59968],"type":"Point"}
}