{
  "type": "Feature",
  "properties": {
    "gn:admin1_code":"5.0",
    "gn:asciiname":"Xiahuanxiling",
    "gn:country_code":"CN",
    "gn:dem":455,
    "gn:feature_class":"P",
    "gn:feature_code":"PPL",
    "gn:name":"Xiahuanxiling",
    "gn:population":0,
    "gn:timezone":"Asia/Shanghai",
    "iso:country":"CN",
    "name:und_x_variant":[
        "\u4e0b\u6b22\u559c\u5cad"
    ],
    "wof:name":"Xiahuanxiling",
    "wof:placetype":"locality"
},
  "geometry": {"coordinates":[125.42249,41.74807],"type":"Point"}
}