{
  "type": "Feature",
  "properties": {
    "gn:admin1_code":"1.0",
    "gn:asciiname":"Wuheng",
    "gn:country_code":"CN",
    "gn:dem":53,
    "gn:feature_class":"P",
    "gn:feature_code":"PPL",
    "gn:name":"Wuheng",
    "gn:population":0,
    "gn:timezone":"Asia/Shanghai",
    "iso:country":"CN",
    "name:und_x_variant":[
        "Wuheng Xiang"
    ],
    "name:zho_x_preferred":[
        "\u4e94\u6a2a"
    ],
    "name:zho_x_variant":[
        "\u4e94\u6a2a\u4e61"
    ],
    "wof:name":"Wuheng",
    "wof:placetype":"locality"
},
  "geometry": {"coordinates":[116.97888,30.6853],"type":"Point"}
}