{
  "type": "Feature",
  "properties": {
    "gn:admin1_code":"25",
    "gn:asciiname":"Baowangzhuang",
    "gn:country_code":"CN",
    "gn:dem":10,
    "gn:feature_class":"P",
    "gn:feature_code":"PPL",
    "gn:name":"Baowangzhuang",
    "gn:population":0,
    "gn:timezone":"Asia/Shanghai",
    "iso:country":"CN",
    "name:zho_x_preferred":[
        "\u9c8d\u738b\u5e84"
    ],
    "wof:name":"Baowangzhuang",
    "wof:placetype":"locality"
},
  "geometry": {"coordinates":[118.36008,37.63597],"type":"Point"}
}