{
  "type": "Feature",
  "properties": {
    "gn:admin1_code":"19.0",
    "gn:asciiname":"Dapozi",
    "gn:country_code":"CN",
    "gn:dem":197,
    "gn:feature_class":"P",
    "gn:feature_code":"PPL",
    "gn:name":"Dapozi",
    "gn:population":0,
    "gn:timezone":"Asia/Shanghai",
    "iso:country":"CN",
    "name:zho_x_preferred":[
        "\u5927\u8feb\u5b50"
    ],
    "wof:name":"Dapozi",
    "wof:placetype":"locality"
},
  "geometry": {"coordinates":[124.456,42.2873],"type":"Point"}
}