{
  "type": "Feature",
  "properties": {
    "gn:admin1_code":"15.0",
    "gn:asciiname":"Jinjiacha",
    "gn:country_code":"CN",
    "gn:dem":1970,
    "gn:feature_class":"P",
    "gn:feature_code":"PPL",
    "gn:name":"Jinjiacha",
    "gn:population":0,
    "gn:timezone":"Asia/Shanghai",
    "iso:country":"CN",
    "name:zho_x_preferred":[
        "\u91d1\u5bb6\u5c94"
    ],
    "wof:name":"Jinjiacha",
    "wof:placetype":"locality"
},
  "geometry": {"coordinates":[104.816,35.1556],"type":"Point"}
}