{
  "type": "Feature",
  "properties": {
    "gn:admin1_code":"32.0",
    "gn:asciiname":"Taiyuan",
    "gn:country_code":"CN",
    "gn:dem":350,
    "gn:feature_class":"P",
    "gn:feature_code":"PPL",
    "gn:name":"Taiyuan",
    "gn:population":0,
    "gn:timezone":"Asia/Shanghai",
    "iso:country":"CN",
    "name:zho_x_preferred":[
        "\u592a\u539f"
    ],
    "wof:name":"Taiyuan",
    "wof:placetype":"locality"
},
  "geometry": {"coordinates":[107.639,31.1432],"type":"Point"}
}