{
  "type": "Feature",
  "properties": {
    "gn:admin1_code":"26.0",
    "gn:asciiname":"Wazhaling",
    "gn:country_code":"CN",
    "gn:dem":1423,
    "gn:feature_class":"P",
    "gn:feature_code":"PPL",
    "gn:name":"Wazhaling",
    "gn:population":0,
    "gn:timezone":"Asia/Shanghai",
    "iso:country":"CN",
    "name:zho_x_preferred":[
        "\u74e6\u6e23\u5cad"
    ],
    "wof:name":"Wazhaling",
    "wof:placetype":"locality"
},
  "geometry": {"coordinates":[109.21208,35.26831],"type":"Point"}
}