{
  "type": "Feature",
  "properties": {
    "gn:admin1_code":"4.0",
    "gn:asciiname":"Dasuncun",
    "gn:country_code":"CN",
    "gn:dem":4,
    "gn:feature_class":"P",
    "gn:feature_code":"PPL",
    "gn:name":"Dasuncun",
    "gn:population":0,
    "gn:timezone":"Asia/Shanghai",
    "iso:country":"CN",
    "name:zho_x_preferred":[
        "\u5927\u5b59\u6751"
    ],
    "wof:name":"Dasuncun",
    "wof:placetype":"locality"
},
  "geometry": {"coordinates":[119.20831,34.39752],"type":"Point"}
}