{
  "type": "Feature",
  "properties": {
    "gn:admin1_code":"14.0",
    "gn:asciiname":"Beimei",
    "gn:country_code":"CN",
    "gn:dem":4182,
    "gn:feature_class":"P",
    "gn:feature_code":"PPL",
    "gn:name":"Beimei",
    "gn:population":0,
    "gn:timezone":"Asia/Urumqi",
    "iso:country":"CN",
    "name:zho_x_preferred":[
        "\u5317\u7f8e"
    ],
    "wof:name":"Beimei",
    "wof:placetype":"locality"
},
  "geometry": {"coordinates":[97.35473,30.62952],"type":"Point"}
}