{
  "type": "Feature",
  "properties": {
    "gn:admin1_code":"30.0",
    "gn:asciiname":"Xia'ao",
    "gn:country_code":"CN",
    "gn:dem":418,
    "gn:feature_class":"P",
    "gn:feature_code":"PPL",
    "gn:name":"Xia\u2019ao",
    "gn:population":0,
    "gn:timezone":"Asia/Shanghai",
    "iso:country":"CN",
    "name:zho_x_preferred":[
        "Xia\u2019ao"
    ],
    "name:zho_x_variant":[
        "\u4e0b\u5773"
    ],
    "wof:name":"Xia'ao",
    "wof:placetype":"locality"
},
  "geometry": {"coordinates":[113.23472,25.50639],"type":"Point"}
}