{
  "type": "Feature",
  "properties": {
    "gn:admin1_code":"15.0",
    "gn:asciiname":"Hualing",
    "gn:country_code":"CN",
    "gn:dem":1668,
    "gn:feature_class":"P",
    "gn:feature_code":"PPL",
    "gn:name":"Hualing",
    "gn:population":0,
    "gn:timezone":"Asia/Shanghai",
    "iso:country":"CN",
    "name:zho_x_preferred":[
        "\u5316\u5cad"
    ],
    "wof:name":"Hualing",
    "wof:placetype":"locality"
},
  "geometry": {"coordinates":[105.97799999999999,34.8235],"type":"Point"}
}