{
  "type": "Feature",
  "properties": {
    "gn:admin1_code":"18",
    "gn:asciiname":"Taojiang",
    "gn:cc2":"CN",
    "gn:country_code":"CN",
    "gn:dem":1229,
    "gn:feature_class":"P",
    "gn:feature_code":"PPL",
    "gn:name":"Taojiang",
    "gn:population":0,
    "gn:timezone":"Asia/Shanghai",
    "iso:country":"CN",
    "name:und_x_variant":[
        "T\u2019ao-chiang",
        "Taojiang"
    ],
    "wof:name":"Taojiang",
    "wof:placetype":"locality"
},
  "geometry": {"coordinates":[108.13333,26.28333],"type":"Point"}
}