{
  "type": "Feature",
  "properties": {
    "gn:admin1_code":"16",
    "gn:asciiname":"Sanwang",
    "gn:cc2":"CN",
    "gn:country_code":"CN",
    "gn:dem":599,
    "gn:feature_class":"P",
    "gn:feature_code":"PPL",
    "gn:name":"Sanwang",
    "gn:population":0,
    "gn:timezone":"Asia/Shanghai",
    "iso:country":"CN",
    "name:und_x_variant":[
        "San-wang-hs\u00fc",
        "Sanwang"
    ],
    "wof:name":"Sanwang",
    "wof:placetype":"locality"
},
  "geometry": {"coordinates":[107.63333,24.63333],"type":"Point"}
}