{
  "type": "Feature",
  "properties": {
    "gn:admin1_code":"22.0",
    "gn:asciiname":"Fangezhuangcun",
    "gn:country_code":"CN",
    "gn:dem":45,
    "gn:feature_class":"P",
    "gn:feature_code":"PPL",
    "gn:name":"Fangezhuangcun",
    "gn:population":0,
    "gn:timezone":"Asia/Shanghai",
    "iso:country":"CN",
    "name:zho_x_preferred":[
        "\u6a0a\u5404\u5e84\u6751"
    ],
    "wof:name":"Fangezhuangcun",
    "wof:placetype":"locality"
},
  "geometry": {"coordinates":[116.96033,40.19079],"type":"Point"}
}