{
  "type": "Feature",
  "properties": {
    "gn:admin1_code":"7.0",
    "gn:asciiname":"Daqian",
    "gn:country_code":"CN",
    "gn:dem":452,
    "gn:feature_class":"P",
    "gn:feature_code":"PPL",
    "gn:name":"Daqian",
    "gn:population":0,
    "gn:timezone":"Asia/Shanghai",
    "iso:country":"CN",
    "name:zho_x_preferred":[
        "\u5927\u5898"
    ],
    "wof:name":"Daqian",
    "wof:placetype":"locality"
},
  "geometry": {"coordinates":[118.60563,26.0113],"type":"Point"}
}