{
  "type": "Feature",
  "properties": {
    "gn:admin1_code":"18",
    "gn:asciiname":"Puche Pingzi",
    "gn:country_code":"CN",
    "gn:dem":1864,
    "gn:feature_class":"P",
    "gn:feature_code":"PPL",
    "gn:name":"Puche Pingzi",
    "gn:population":0,
    "gn:timezone":"Asia/Shanghai",
    "iso:country":"CN",
    "name:zho_x_preferred":[
        "\u666e\u8f66\u576a\u5b50"
    ],
    "wof:name":"Puche Pingzi",
    "wof:placetype":"locality"
},
  "geometry": {"coordinates":[104.107,27.3052],"type":"Point"}
}