{
  "type": "Feature",
  "properties": {
    "gn:admin1_code":"29.0",
    "gn:asciiname":"Xiameizishu",
    "gn:country_code":"CN",
    "gn:dem":1953,
    "gn:feature_class":"P",
    "gn:feature_code":"PPL",
    "gn:name":"Xiameizishu",
    "gn:population":0,
    "gn:timezone":"Asia/Shanghai",
    "iso:country":"CN",
    "name:zho_x_preferred":[
        "\u4e0b\u6885\u5b50\u6811"
    ],
    "wof:name":"Xiameizishu",
    "wof:placetype":"locality"
},
  "geometry": {"coordinates":[101.102,25.0749],"type":"Point"}
}