{
  "type": "Feature",
  "properties": {
    "gn:admin1_code":"16.0",
    "gn:asciiname":"Shou'an",
    "gn:country_code":"CN",
    "gn:dem":297,
    "gn:feature_class":"P",
    "gn:feature_code":"PPL",
    "gn:name":"Shou\u2019an",
    "gn:population":0,
    "gn:timezone":"Asia/Shanghai",
    "iso:country":"CN",
    "name:und_x_variant":[
        "Shou\u2019an"
    ],
    "name:zho_x_preferred":[
        "\u5bff\u5b89"
    ],
    "wof:name":"Shou'an",
    "wof:placetype":"locality"
},
  "geometry": {"coordinates":[107.43000000000001,23.7956],"type":"Point"}
}