{
  "type": "Feature",
  "properties": {
    "gn:admin1_code":"18.0",
    "gn:asciiname":"Dabang",
    "gn:country_code":"CN",
    "gn:dem":881,
    "gn:feature_class":"P",
    "gn:feature_code":"PPL",
    "gn:name":"Dabang",
    "gn:population":0,
    "gn:timezone":"Asia/Shanghai",
    "iso:country":"CN",
    "name:por_x_preferred":[
        "Dabang"
    ],
    "wof:name":"Dabang",
    "wof:placetype":"locality"
},
  "geometry": {"coordinates":[105.97083000000001,25.63333],"type":"Point"}
}