{
  "type": "Feature",
  "properties": {
    "gn:admin1_code":"11",
    "gn:asciiname":"Huilongmiao",
    "gn:country_code":"CN",
    "gn:dem":527,
    "gn:feature_class":"P",
    "gn:feature_code":"PPL",
    "gn:name":"Huilongmiao",
    "gn:population":0,
    "gn:timezone":"Asia/Shanghai",
    "iso:country":"CN",
    "name:zho_x_preferred":[
        "\u56de\u9f99\u5e99"
    ],
    "wof:name":"Huilongmiao",
    "wof:placetype":"locality"
},
  "geometry": {"coordinates":[111.69907000000001,25.212],"type":"Point"}
}