{
  "type": "Feature",
  "properties": {
    "gn:admin1_code":"30",
    "gn:asciiname":"Shanweitian",
    "gn:country_code":"CN",
    "gn:dem":25,
    "gn:feature_class":"P",
    "gn:feature_code":"PPL",
    "gn:name":"Shanweitian",
    "gn:population":0,
    "gn:timezone":"Asia/Urumqi",
    "iso:country":"CN",
    "name:zho_x_preferred":[
        "\u5c71\u5c3e\u7530"
    ],
    "wof:name":"Shanweitian",
    "wof:placetype":"locality"
},
  "geometry": {"coordinates":[110.12056,21.3458],"type":"Point"}
}