{
  "type": "Feature",
  "properties": {
    "gn:admin1_code":"11.0",
    "gn:asciiname":"Fengxianggang",
    "gn:country_code":"CN",
    "gn:dem":186,
    "gn:feature_class":"P",
    "gn:feature_code":"PPLA4",
    "gn:name":"Fengxianggang",
    "gn:population":0,
    "gn:timezone":"Asia/Shanghai",
    "iso:country":"CN",
    "name:und_x_variant":[
        "Fengxianggang Xiang",
        "Fengxianggang"
    ],
    "name:zho_x_preferred":[
        "\u67ab\u9999\u5c97"
    ],
    "name:zho_x_variant":[
        "\u67ab\u9999\u5c97\u4e61"
    ],
    "wof:name":"Fengxianggang",
    "wof:placetype":"locality"
},
  "geometry": {"coordinates":[110.39388,29.11007],"type":"Point"}
}