{
  "type": "Feature",
  "properties": {
    "gn:admin1_code":"10",
    "gn:asciiname":"Longtoushan",
    "gn:country_code":"CN",
    "gn:dem":951,
    "gn:feature_class":"P",
    "gn:feature_code":"PPL",
    "gn:name":"Longtoushan",
    "gn:population":0,
    "gn:timezone":"Asia/Shanghai",
    "iso:country":"CN",
    "wof:name":"Longtoushan",
    "wof:placetype":"locality"
},
  "geometry": {"coordinates":[117.66667,41.98333],"type":"Point"}
}