{
  "type": "Feature",
  "properties": {
    "gn:admin1_code":"1.0",
    "gn:asciiname":"Baxicun",
    "gn:country_code":"CN",
    "gn:dem":34,
    "gn:feature_class":"P",
    "gn:feature_code":"PPL",
    "gn:name":"Baxicun",
    "gn:population":0,
    "gn:timezone":"Asia/Shanghai",
    "iso:country":"CN",
    "name:zho_x_preferred":[
        "\u575d\u897f\u6751"
    ],
    "wof:name":"Baxicun",
    "wof:placetype":"locality"
},
  "geometry": {"coordinates":[118.49236999999999,32.43238],"type":"Point"}
}