{
  "type": "Feature",
  "properties": {
    "gn:admin1_code":"23.0",
    "gn:asciiname":"Lianercun",
    "gn:country_code":"CN",
    "gn:dem":5,
    "gn:feature_class":"P",
    "gn:feature_code":"PPL",
    "gn:name":"Lianercun",
    "gn:population":0,
    "gn:timezone":"Asia/Shanghai",
    "iso:country":"CN",
    "name:zho_x_preferred":[
        "\u8054\u4e8c\u6751"
    ],
    "wof:name":"Lianercun",
    "wof:placetype":"locality"
},
  "geometry": {"coordinates":[121.28352,31.48711],"type":"Point"}
}