{
  "type": "Feature",
  "properties": {
    "gn:admin1_code":"15.0",
    "gn:asciiname":"Liangzigou",
    "gn:country_code":"CN",
    "gn:dem":1466,
    "gn:feature_class":"P",
    "gn:feature_code":"PPL",
    "gn:name":"Liangzigou",
    "gn:population":0,
    "gn:timezone":"Asia/Shanghai",
    "iso:country":"CN",
    "name:zho_x_preferred":[
        "\u6881\u5b50\u6c9f"
    ],
    "wof:name":"Liangzigou",
    "wof:placetype":"locality"
},
  "geometry": {"coordinates":[97.01349999999999,40.3455],"type":"Point"}
}