{
  "type": "Feature",
  "properties": {
    "gn:admin1_code":"3",
    "gn:asciiname":"Tangnan",
    "gn:country_code":"CN",
    "gn:dem":276,
    "gn:feature_class":"P",
    "gn:feature_code":"PPL",
    "gn:name":"Tangnan",
    "gn:population":0,
    "gn:timezone":"Asia/Shanghai",
    "iso:country":"CN",
    "name:zho_x_preferred":[
        "\u5858\u5357"
    ],
    "wof:name":"Tangnan",
    "wof:placetype":"locality"
},
  "geometry": {"coordinates":[114.12881000000002,26.72036],"type":"Point"}
}