{
  "type": "Feature",
  "properties": {
    "gn:admin1_code":"32.0",
    "gn:asciiname":"Ejiu",
    "gn:country_code":"CN",
    "gn:dem":2762,
    "gn:feature_class":"P",
    "gn:feature_code":"PPL",
    "gn:name":"Ejiu",
    "gn:population":0,
    "gn:timezone":"Asia/Shanghai",
    "iso:country":"CN",
    "name:zho_x_preferred":[
        "\u4fc4\u4e45"
    ],
    "wof:name":"Ejiu",
    "wof:placetype":"locality"
},
  "geometry": {"coordinates":[102.822,27.471],"type":"Point"}
}