{
  "type": "Feature",
  "properties": {
    "gn:admin1_code":"15.0",
    "gn:asciiname":"Hejiashan",
    "gn:country_code":"CN",
    "gn:dem":1635,
    "gn:feature_class":"P",
    "gn:feature_code":"PPL",
    "gn:name":"Hejiashan",
    "gn:population":0,
    "gn:timezone":"Asia/Shanghai",
    "iso:country":"CN",
    "name:und_x_variant":[
        "\u4f55\u5bb6\u5c71"
    ],
    "wof:name":"Hejiashan",
    "wof:placetype":"locality"
},
  "geometry": {"coordinates":[105.39946999999999,33.75617],"type":"Point"}
}