{
  "type": "Feature",
  "properties": {
    "gn:admin1_code":"26.0",
    "gn:asciiname":"Fengjiayuan",
    "gn:country_code":"CN",
    "gn:dem":586,
    "gn:feature_class":"P",
    "gn:feature_code":"PPL",
    "gn:name":"Fengjiayuan",
    "gn:population":0,
    "gn:timezone":"Asia/Shanghai",
    "iso:country":"CN",
    "name:und_x_variant":[
        "\u51af\u5bb6\u9662"
    ],
    "wof:name":"Fengjiayuan",
    "wof:placetype":"locality"
},
  "geometry": {"coordinates":[106.7603,33.1051],"type":"Point"}
}