{
  "type": "Feature",
  "properties": {
    "gn:admin1_code":"1.0",
    "gn:asciiname":"Shaoyuancun",
    "gn:country_code":"CN",
    "gn:dem":25,
    "gn:feature_class":"P",
    "gn:feature_code":"PPL",
    "gn:name":"Shaoyuancun",
    "gn:population":0,
    "gn:timezone":"Asia/Shanghai",
    "iso:country":"CN",
    "name:zho_x_preferred":[
        "\u90b5\u9662\u6751"
    ],
    "wof:name":"Shaoyuancun",
    "wof:placetype":"locality"
},
  "geometry": {"coordinates":[116.78888000000001,33.16528],"type":"Point"}
}