{
  "type": "Feature",
  "properties": {
    "gn:admin1_code":"24",
    "gn:asciiname":"Yuejiazhuang",
    "gn:country_code":"CN",
    "gn:dem":1882,
    "gn:feature_class":"P",
    "gn:feature_code":"PPL",
    "gn:name":"Yuejiazhuang",
    "gn:population":0,
    "gn:timezone":"Asia/Shanghai",
    "iso:country":"CN",
    "wof:name":"Yuejiazhuang",
    "wof:placetype":"locality"
},
  "geometry": {"coordinates":[111.565,37.53694],"type":"Point"}
}