{
  "type": "Feature",
  "properties": {
    "gn:admin1_code":"7",
    "gn:asciiname":"Longgang",
    "gn:country_code":"CN",
    "gn:dem":384,
    "gn:feature_class":"P",
    "gn:feature_code":"PPL",
    "gn:name":"Longgang",
    "gn:population":0,
    "gn:timezone":"Asia/Shanghai",
    "iso:country":"CN",
    "name:und_x_variant":[
        "\u9f99\u5c97"
    ],
    "wof:name":"Longgang",
    "wof:placetype":"locality"
},
  "geometry": {"coordinates":[116.73784999999999,25.64525],"type":"Point"}
}