{
  "type": "Feature",
  "properties": {
    "gn:admin1_code":"7.0",
    "gn:asciiname":"Huangkengli",
    "gn:country_code":"CN",
    "gn:dem":443,
    "gn:feature_class":"P",
    "gn:feature_code":"PPL",
    "gn:name":"Huangkengli",
    "gn:population":0,
    "gn:timezone":"Asia/Shanghai",
    "iso:country":"CN",
    "name:zho_x_preferred":[
        "\u9ec4\u5751\u91cc"
    ],
    "wof:name":"Huangkengli",
    "wof:placetype":"locality"
},
  "geometry": {"coordinates":[115.8866,25.13852],"type":"Point"}
}