{
  "type": "Feature",
  "properties": {
    "gn:admin1_code":"30",
    "gn:asciiname":"Aijigang",
    "gn:country_code":"CN",
    "gn:dem":221,
    "gn:feature_class":"P",
    "gn:feature_code":"PPL",
    "gn:name":"Aijigang",
    "gn:population":0,
    "gn:timezone":"Asia/Shanghai",
    "iso:country":"CN",
    "name:zho_x_preferred":[
        "\u77ee\u5c8c\u5c97"
    ],
    "wof:name":"Aijigang",
    "wof:placetype":"locality"
},
  "geometry": {"coordinates":[116.67494000000001,24.38394],"type":"Point"}
}