{
  "type": "Feature",
  "properties": {
    "gn:admin1_code":"11.0",
    "gn:asciiname":"Yanshouxu",
    "gn:cc2":"CN",
    "gn:country_code":"CN",
    "gn:dem":596,
    "gn:feature_class":"P",
    "gn:feature_code":"PPL",
    "gn:name":"Yanshouxu",
    "gn:population":0,
    "gn:timezone":"Asia/Shanghai",
    "iso:country":"CN",
    "name:und_x_variant":[
        "Yanshou",
        "Yen-shou",
        "Yanshouxu"
    ],
    "wof:name":"Yanshouxu",
    "wof:placetype":"locality"
},
  "geometry": {"coordinates":[113.51361,25.44389],"type":"Point"}
}