{
  "type": "Feature",
  "properties": {
    "gn:admin1_code":"9.0",
    "gn:asciiname":"Yinjiagou",
    "gn:country_code":"CN",
    "gn:dem":935,
    "gn:feature_class":"P",
    "gn:feature_code":"PPL",
    "gn:name":"Yinjiagou",
    "gn:population":0,
    "gn:timezone":"Asia/Shanghai",
    "iso:country":"CN",
    "name:zho_x_preferred":[
        "\u9634\u5bb6\u6c9f"
    ],
    "wof:name":"Yinjiagou",
    "wof:placetype":"locality"
},
  "geometry": {"coordinates":[111.02196000000001,34.31726],"type":"Point"}
}