{
  "type": "Feature",
  "properties": {
    "gn:admin1_code":"5.0",
    "gn:asciiname":"Nanmocun",
    "gn:country_code":"CN",
    "gn:dem":141,
    "gn:feature_class":"P",
    "gn:feature_code":"PPL",
    "gn:name":"Nanmocun",
    "gn:population":0,
    "gn:timezone":"Asia/Shanghai",
    "iso:country":"CN",
    "name:zho_x_preferred":[
        "\u5357\u83ab\u6751"
    ],
    "wof:name":"Nanmocun",
    "wof:placetype":"locality"
},
  "geometry": {"coordinates":[123.84629,45.77813],"type":"Point"}
}