{
  "type": "Feature",
  "properties": {
    "gn:admin1_code":"3",
    "gn:asciiname":"Liangtan",
    "gn:country_code":"CN",
    "gn:dem":341,
    "gn:feature_class":"P",
    "gn:feature_code":"PPL",
    "gn:name":"Liangtan",
    "gn:population":0,
    "gn:timezone":"Asia/Shanghai",
    "iso:country":"CN",
    "name:zho_x_preferred":[
        "\u51c9\u6ee9"
    ],
    "wof:name":"Liangtan",
    "wof:placetype":"locality"
},
  "geometry": {"coordinates":[113.977,25.6179],"type":"Point"}
}