{
  "type": "Feature",
  "properties": {
    "gn:admin1_code":"20.0",
    "gn:asciiname":"Shisan Gongli",
    "gn:country_code":"CN",
    "gn:dem":957,
    "gn:feature_class":"P",
    "gn:feature_code":"PPL",
    "gn:name":"Shisan Gongli",
    "gn:population":0,
    "gn:timezone":"Asia/Shanghai",
    "iso:country":"CN",
    "name:zho_x_preferred":[
        "\u5341\u4e09\u516c\u91cc"
    ],
    "wof:name":"Shisan Gongli",
    "wof:placetype":"locality"
},
  "geometry": {"coordinates":[121.44693999999998,49.80147],"type":"Point"}
}