{
  "type": "Feature",
  "properties": {
    "gn:admin1_code":"30",
    "gn:asciiname":"Huachengxu",
    "gn:country_code":"CN",
    "gn:dem":38,
    "gn:feature_class":"P",
    "gn:feature_code":"PPL",
    "gn:name":"Huachengxu",
    "gn:population":0,
    "gn:timezone":"Asia/Shanghai",
    "iso:country":"CN",
    "name:und_x_variant":[
        "Fahsien",
        "Hua",
        "Chiu-hua-hsien",
        "Hua-hsien",
        "\u82b1\u57ce\u5729",
        "Huachengxu",
        "Huacheng"
    ],
    "name:zho_x_preferred":[
        "\u82b1\u57ce\u5729"
    ],
    "wof:name":"Huachengxu",
    "wof:placetype":"locality"
},
  "geometry": {"coordinates":[113.28639,23.49826],"type":"Point"}
}