{
  "type": "Feature",
  "properties": {
    "gn:admin1_code":"31.0",
    "gn:asciiname":"Maozu",
    "gn:country_code":"CN",
    "gn:dem":215,
    "gn:feature_class":"P",
    "gn:feature_code":"PPL",
    "gn:name":"Maozu",
    "gn:population":0,
    "gn:timezone":"Asia/Shanghai",
    "iso:country":"CN",
    "name:und_x_variant":[
        "\u6bdb\u7ec4"
    ],
    "wof:name":"Maozu",
    "wof:placetype":"locality"
},
  "geometry": {"coordinates":[109.40904,18.88755],"type":"Point"}
}