{
  "type": "Feature",
  "properties": {
    "gn:admin1_code":"18",
    "gn:asciiname":"Qiaoxihe",
    "gn:country_code":"CN",
    "gn:dem":602,
    "gn:feature_class":"P",
    "gn:feature_code":"PPL",
    "gn:name":"Qiaoxihe",
    "gn:population":0,
    "gn:timezone":"Asia/Shanghai",
    "iso:country":"CN",
    "name:zho_x_preferred":[
        "\u6865\u6eaa\u6cb3"
    ],
    "wof:name":"Qiaoxihe",
    "wof:placetype":"locality"
},
  "geometry": {"coordinates":[107.432,28.5928],"type":"Point"}
}