{
  "type": "Feature",
  "properties": {
    "gn:admin1_code":"18",
    "gn:asciiname":"Shiliya",
    "gn:country_code":"CN",
    "gn:dem":667,
    "gn:feature_class":"P",
    "gn:feature_code":"PPL",
    "gn:name":"Shiliya",
    "gn:population":0,
    "gn:timezone":"Asia/Shanghai",
    "iso:country":"CN",
    "name:zho_x_preferred":[
        "\u72ee\u68a8\u57ad"
    ],
    "wof:name":"Shiliya",
    "wof:placetype":"locality"
},
  "geometry": {"coordinates":[107.40300000000001,28.6058],"type":"Point"}
}