{
  "type": "Feature",
  "properties": {
    "gn:admin1_code":"25.0",
    "gn:asciiname":"Fengwangxincun",
    "gn:country_code":"CN",
    "gn:dem":38,
    "gn:feature_class":"P",
    "gn:feature_code":"PPL",
    "gn:name":"Fengwangxincun",
    "gn:population":0,
    "gn:timezone":"Asia/Shanghai",
    "iso:country":"CN",
    "name:zho_x_preferred":[
        "\u9022\u738b\u65b0\u6751"
    ],
    "wof:name":"Fengwangxincun",
    "wof:placetype":"locality"
},
  "geometry": {"coordinates":[119.31399999999999,36.50786],"type":"Point"}
}