{
  "type": "Feature",
  "properties": {
    "gn:admin1_code":"33.0",
    "gn:asciiname":"Wujiancang",
    "gn:country_code":"CN",
    "gn:dem":370,
    "gn:feature_class":"P",
    "gn:feature_code":"PPL",
    "gn:name":"Wujiancang",
    "gn:population":0,
    "gn:timezone":"Asia/Shanghai",
    "iso:country":"CN",
    "name:zho_x_preferred":[
        "\u4e94\u95f4\u4ed3"
    ],
    "wof:name":"Wujiancang",
    "wof:placetype":"locality"
},
  "geometry": {"coordinates":[105.50357,29.46069],"type":"Point"}
}