{
  "type": "Feature",
  "properties": {
    "gn:admin1_code":"26.0",
    "gn:asciiname":"Shiyuancun",
    "gn:country_code":"CN",
    "gn:dem":480,
    "gn:feature_class":"P",
    "gn:feature_code":"PPL",
    "gn:name":"Shiyuancun",
    "gn:population":0,
    "gn:timezone":"Asia/Shanghai",
    "iso:country":"CN",
    "name:zho_x_preferred":[
        "\u67ff\u56ed\u6751"
    ],
    "wof:name":"Shiyuancun",
    "wof:placetype":"locality"
},
  "geometry": {"coordinates":[108.61259,34.03495],"type":"Point"}
}