{
  "type": "Feature",
  "properties": {
    "gn:admin1_code":"15.0",
    "gn:asciiname":"Zhangjia Cigouliang",
    "gn:country_code":"CN",
    "gn:dem":1446,
    "gn:feature_class":"P",
    "gn:feature_code":"PPL",
    "gn:name":"Zhangjia Cigouliang",
    "gn:population":0,
    "gn:timezone":"Asia/Shanghai",
    "iso:country":"CN",
    "name:zho_x_preferred":[
        "\u5f20\u5bb6\u523a\u6c9f\u6881"
    ],
    "wof:name":"Zhangjia Cigouliang",
    "wof:placetype":"locality"
},
  "geometry": {"coordinates":[98.79049999999999,39.5983],"type":"Point"}
}