{
  "type": "Feature",
  "properties": {
    "gn:admin1_code":"24.0",
    "gn:asciiname":"Getayingcun",
    "gn:country_code":"CN",
    "gn:dem":348,
    "gn:feature_class":"P",
    "gn:feature_code":"PPL",
    "gn:name":"Getayingcun",
    "gn:population":0,
    "gn:timezone":"Asia/Shanghai",
    "iso:country":"CN",
    "name:zho_x_preferred":[
        "\u572a\u5854\u8425\u6751"
    ],
    "wof:name":"Getayingcun",
    "wof:placetype":"locality"
},
  "geometry": {"coordinates":[110.73605000000001,34.92009],"type":"Point"}
}