{
  "type": "Feature",
  "properties": {
    "gn:admin1_code":"29.0",
    "gn:asciiname":"Laozhai",
    "gn:country_code":"CN",
    "gn:dem":2125,
    "gn:feature_class":"P",
    "gn:feature_code":"PPL",
    "gn:name":"Laozhai",
    "gn:population":0,
    "gn:timezone":"Asia/Shanghai",
    "iso:country":"CN",
    "name:zho_x_preferred":[
        "\u8001\u5be8"
    ],
    "wof:name":"Laozhai",
    "wof:placetype":"locality"
},
  "geometry": {"coordinates":[103.405,26.987],"type":"Point"}
}