{
  "type": "Feature",
  "properties": {
    "gn:admin1_code":"8.0",
    "gn:asciiname":"Xiaohoucun",
    "gn:country_code":"CN",
    "gn:dem":88,
    "gn:feature_class":"P",
    "gn:feature_code":"PPL",
    "gn:name":"Xiaohoucun",
    "gn:population":0,
    "gn:timezone":"Asia/Shanghai",
    "iso:country":"CN",
    "name:zho_x_preferred":[
        "\u5c0f\u540e\u6751"
    ],
    "wof:name":"Xiaohoucun",
    "wof:placetype":"locality"
},
  "geometry": {"coordinates":[132.47547,47.30484000000001],"type":"Point"}
}