{
  "type": "Feature",
  "properties": {
    "gn:admin1_code":"3.0",
    "gn:asciiname":"Zaokeng",
    "gn:country_code":"CN",
    "gn:dem":55,
    "gn:feature_class":"P",
    "gn:feature_code":"PPL",
    "gn:name":"Zaokeng",
    "gn:population":0,
    "gn:timezone":"Asia/Shanghai",
    "iso:country":"CN",
    "name:und_x_variant":[
        "\u65e9\u5751"
    ],
    "wof:name":"Zaokeng",
    "wof:placetype":"locality"
},
  "geometry": {"coordinates":[117.30638999999999,29.24425],"type":"Point"}
}