{
  "type": "Feature",
  "properties": {
    "gn:admin1_code":"8.0",
    "gn:asciiname":"Gongpingcun",
    "gn:country_code":"CN",
    "gn:dem":209,
    "gn:feature_class":"P",
    "gn:feature_code":"PPL",
    "gn:name":"Gongpingcun",
    "gn:population":0,
    "gn:timezone":"Asia/Shanghai",
    "iso:country":"CN",
    "name:zho_x_preferred":[
        "\u516c\u5e73\u6751"
    ],
    "wof:name":"Gongpingcun",
    "wof:placetype":"locality"
},
  "geometry": {"coordinates":[125.37783,47.47629000000001],"type":"Point"}
}