{
  "type": "Feature",
  "properties": {
    "gn:admin1_code":"4.0",
    "gn:asciiname":"Wangbuling",
    "gn:country_code":"CN",
    "gn:dem":56,
    "gn:feature_class":"P",
    "gn:feature_code":"PPL",
    "gn:name":"Wangbuling",
    "gn:population":0,
    "gn:timezone":"Asia/Shanghai",
    "iso:country":"CN",
    "name:zho_x_preferred":[
        "\u738b\u57e0\u5cad"
    ],
    "wof:name":"Wangbuling",
    "wof:placetype":"locality"
},
  "geometry": {"coordinates":[117.35599999999999,34.4579],"type":"Point"}
}