{
  "type": "Feature",
  "properties": {
    "gn:admin1_code":"19.0",
    "gn:asciiname":"Mazhangpao",
    "gn:country_code":"CN",
    "gn:dem":7,
    "gn:feature_class":"P",
    "gn:feature_code":"PPL",
    "gn:name":"Mazhangpao",
    "gn:population":0,
    "gn:timezone":"Asia/Shanghai",
    "iso:country":"CN",
    "name:zho_x_preferred":[
        "\u9a6c\u4ed7\u6ce1"
    ],
    "wof:name":"Mazhangpao",
    "wof:placetype":"locality"
},
  "geometry": {"coordinates":[122.25679,41.38279],"type":"Point"}
}