{
  "type": "Feature",
  "properties": {
    "gn:admin1_code":"21.0",
    "gn:asciiname":"Xiaohonggou",
    "gn:country_code":"CN",
    "gn:dem":1394,
    "gn:feature_class":"P",
    "gn:feature_code":"PPL",
    "gn:name":"Xiaohonggou",
    "gn:population":0,
    "gn:timezone":"Asia/Shanghai",
    "iso:country":"CN",
    "name:zho_x_preferred":[
        "\u5c0f\u6d2a\u6c9f"
    ],
    "wof:name":"Xiaohonggou",
    "wof:placetype":"locality"
},
  "geometry": {"coordinates":[105.67700000000001,37.1883],"type":"Point"}
}