{
  "type": "Feature",
  "properties": {
    "gn:admin1_code":"24.0",
    "gn:asciiname":"Shuangjiazhai",
    "gn:country_code":"CN",
    "gn:dem":1259,
    "gn:feature_class":"P",
    "gn:feature_code":"PPL",
    "gn:name":"Shuangjiazhai",
    "gn:population":0,
    "gn:timezone":"Asia/Shanghai",
    "iso:country":"CN",
    "name:zho_x_preferred":[
        "\u53cc\u5bb6\u5be8"
    ],
    "wof:name":"Shuangjiazhai",
    "wof:placetype":"locality"
},
  "geometry": {"coordinates":[111.63933,37.67111],"type":"Point"}
}