{
  "type": "Feature",
  "properties": {
    "gn:admin1_code":"25",
    "gn:asciiname":"Fanguitun",
    "gn:country_code":"CN",
    "gn:dem":60,
    "gn:feature_class":"P",
    "gn:feature_code":"PPL",
    "gn:name":"Fanguitun",
    "gn:population":0,
    "gn:timezone":"Asia/Shanghai",
    "iso:country":"CN",
    "name:zho_x_preferred":[
        "\u6a0a\u8d35\u5c6f"
    ],
    "wof:name":"Fanguitun",
    "wof:placetype":"locality"
},
  "geometry": {"coordinates":[115.152,35.1985],"type":"Point"}
}