{
  "type": "Feature",
  "properties": {
    "gn:admin1_code":"25",
    "gn:asciiname":"Dayuzhu",
    "gn:country_code":"CN",
    "gn:dem":49,
    "gn:feature_class":"P",
    "gn:feature_code":"PPL",
    "gn:name":"Dayuzhu",
    "gn:population":0,
    "gn:timezone":"Asia/Shanghai",
    "iso:country":"CN",
    "name:zho_x_preferred":[
        "\u5927\u96e8\u4f4f"
    ],
    "wof:name":"Dayuzhu",
    "wof:placetype":"locality"
},
  "geometry": {"coordinates":[116.813,35.5017],"type":"Point"}
}