{
  "type": "Feature",
  "properties": {
    "gn:admin1_code":"29.0",
    "gn:asciiname":"Longchi",
    "gn:country_code":"CN",
    "gn:dem":1846,
    "gn:feature_class":"P",
    "gn:feature_code":"PPL",
    "gn:name":"Longchi",
    "gn:population":0,
    "gn:timezone":"Asia/Shanghai",
    "iso:country":"CN",
    "name:zho_x_preferred":[
        "\u9f99\u75f4"
    ],
    "wof:name":"Longchi",
    "wof:placetype":"locality"
},
  "geometry": {"coordinates":[103.41500000000001,23.2385],"type":"Point"}
}