{
  "type": "Feature",
  "properties": {
    "gn:admin1_code":"29.0",
    "gn:asciiname":"Daijiadi",
    "gn:country_code":"CN",
    "gn:dem":1954,
    "gn:feature_class":"P",
    "gn:feature_code":"PPL",
    "gn:name":"Daijiadi",
    "gn:population":0,
    "gn:timezone":"Asia/Shanghai",
    "iso:country":"CN",
    "name:zho_x_preferred":[
        "\u4ee3\u5bb6\u5e95"
    ],
    "wof:name":"Daijiadi",
    "wof:placetype":"locality"
},
  "geometry": {"coordinates":[103.526,25.0731],"type":"Point"}
}