{
  "type": "Feature",
  "properties": {
    "gn:admin1_code":"9.0",
    "gn:asciiname":"Lingjia",
    "gn:country_code":"CN",
    "gn:dem":291,
    "gn:feature_class":"P",
    "gn:feature_code":"PPL",
    "gn:name":"Lingjia",
    "gn:population":0,
    "gn:timezone":"Asia/Shanghai",
    "iso:country":"CN",
    "name:zho_x_preferred":[
        "\u51cc\u5bb6"
    ],
    "wof:name":"Lingjia",
    "wof:placetype":"locality"
},
  "geometry": {"coordinates":[111.41655,33.03053],"type":"Point"}
}