{
  "type": "Feature",
  "properties": {
    "gn:admin1_code":"1.0",
    "gn:asciiname":"Baoshancun",
    "gn:country_code":"CN",
    "gn:dem":25,
    "gn:feature_class":"P",
    "gn:feature_code":"PPL",
    "gn:name":"Baoshancun",
    "gn:population":0,
    "gn:timezone":"Asia/Shanghai",
    "iso:country":"CN",
    "name:zho_x_preferred":[
        "\u8912\u5c71\u6751"
    ],
    "wof:name":"Baoshancun",
    "wof:placetype":"locality"
},
  "geometry": {"coordinates":[118.13928,31.77631],"type":"Point"}
}