{
  "type": "Feature",
  "properties": {
    "iso:country":"CN",
    "name:eng_x_preferred":[
        "Qianshan"
    ],
    "name:zho_x_preferred":[
        "\u524d\u5c71\u9547"
    ],
    "qs:name":"\u524d\u5c71\u9547",
    "qs:name_adm0":"\u4e2d\u570b",
    "qs:name_adm1":"\u5e7f\u4e1c\u7701",
    "qs:photos":63,
    "qs:photos_1k":13,
    "qs:photos_9k":1,
    "qs:photos_9r":2,
    "qs:photos_all":63,
    "qs:photos_sr":2,
    "qs:placetype":"Town",
    "qs:pop_sr":"0",
    "wof:name":"Qianshan",
    "wof:placetype":"locality"
},
  "geometry": {"coordinates":[113.523101,22.240166],"type":"Point"}
}