{
  "type": "Feature",
  "properties": {
    "gn:admin1_code":"02",
    "gn:asciiname":"Maoyangcun",
    "gn:country_code":"CN",
    "gn:dem":17,
    "gn:feature_class":"P",
    "gn:feature_code":"PPL",
    "gn:name":"Maoyangcun",
    "gn:population":0,
    "gn:timezone":"Asia/Shanghai",
    "iso:country":"CN",
    "name:und_x_variant":[
        "Mao-yang-ts\u2019un",
        "Maoyangcun"
    ],
    "name:zho_x_preferred":[
        "\u8305\u579f\u6751"
    ],
    "wof:name":"Maoyangcun",
    "wof:placetype":"locality"
},
  "geometry": {"coordinates":[120.99486,28.24165],"type":"Point"}
}