{
  "type": "Feature",
  "properties": {
    "gn:admin1_code":"26.0",
    "gn:asciiname":"Duiwo",
    "gn:country_code":"CN",
    "gn:dem":1233,
    "gn:feature_class":"P",
    "gn:feature_code":"PPL",
    "gn:name":"Duiwo",
    "gn:population":0,
    "gn:timezone":"Asia/Shanghai",
    "iso:country":"CN",
    "name:zho_x_preferred":[
        "\u5bf9\u7a9d"
    ],
    "wof:name":"Duiwo",
    "wof:placetype":"locality"
},
  "geometry": {"coordinates":[109.14196,35.39203],"type":"Point"}
}