{
  "type": "Feature",
  "properties": {
    "gn:admin1_code":"18.0",
    "gn:asciiname":"Wujiao",
    "gn:country_code":"CN",
    "gn:dem":1077,
    "gn:feature_class":"P",
    "gn:feature_code":"PPL",
    "gn:name":"Wujiao",
    "gn:population":0,
    "gn:timezone":"Asia/Shanghai",
    "iso:country":"CN",
    "name:zho_x_preferred":[
        "\u5c4b\u89d2"
    ],
    "wof:name":"Wujiao",
    "wof:placetype":"locality"
},
  "geometry": {"coordinates":[108.277,26.3207],"type":"Point"}
}