{
  "type": "Feature",
  "properties": {
    "gn:admin1_code":"16",
    "gn:asciiname":"Hongqiaoting",
    "gn:country_code":"CN",
    "gn:dem":498,
    "gn:feature_class":"P",
    "gn:feature_code":"PPL",
    "gn:name":"Hongqiaoting",
    "gn:population":0,
    "gn:timezone":"Asia/Shanghai",
    "iso:country":"CN",
    "name:zho_x_preferred":[
        "\u7ea2\u6865\u4ead"
    ],
    "wof:name":"Hongqiaoting",
    "wof:placetype":"locality"
},
  "geometry": {"coordinates":[110.61,25.8456],"type":"Point"}
}