{
  "type": "Feature",
  "properties": {
    "gn:admin1_code":"9.0",
    "gn:asciiname":"Huweizi",
    "gn:country_code":"CN",
    "gn:dem":58,
    "gn:feature_class":"P",
    "gn:feature_code":"PPL",
    "gn:name":"Huweizi",
    "gn:population":0,
    "gn:timezone":"Asia/Shanghai",
    "iso:country":"CN",
    "name:zho_x_preferred":[
        "\u80e1\u56f4\u5b5c"
    ],
    "wof:name":"Huweizi",
    "wof:placetype":"locality"
},
  "geometry": {"coordinates":[114.6784,32.46524],"type":"Point"}
}