{
  "type": "Feature",
  "properties": {
    "gn:admin1_code":"9.0",
    "gn:asciiname":"Jingshanling",
    "gn:country_code":"CN",
    "gn:dem":203,
    "gn:feature_class":"P",
    "gn:feature_code":"PPL",
    "gn:name":"Jingshanling",
    "gn:population":0,
    "gn:timezone":"Asia/Shanghai",
    "iso:country":"CN",
    "name:zho_x_preferred":[
        "\u8346\u5c71\u5cad"
    ],
    "wof:name":"Jingshanling",
    "wof:placetype":"locality"
},
  "geometry": {"coordinates":[113.31435999999999,34.28874],"type":"Point"}
}