{
  "type": "Feature",
  "properties": {
    "gn:admin1_code":"1.0",
    "gn:asciiname":"Sanfenchang",
    "gn:country_code":"CN",
    "gn:dem":18,
    "gn:feature_class":"P",
    "gn:feature_code":"PPLF",
    "gn:name":"Sanfenchang",
    "gn:population":0,
    "gn:timezone":"Asia/Shanghai",
    "iso:country":"CN",
    "name:und_x_variant":[
        "\u4e09\u5206\u573a"
    ],
    "wof:name":"Sanfenchang",
    "wof:placetype":"locality"
},
  "geometry": {"coordinates":[116.38453,29.94352],"type":"Point"}
}