{
  "type": "Feature",
  "properties": {
    "gn:admin1_code":"2.0",
    "gn:asciiname":"Mukanshan",
    "gn:country_code":"CN",
    "gn:dem":350,
    "gn:feature_class":"P",
    "gn:feature_code":"PPL",
    "gn:name":"Mukanshan",
    "gn:population":0,
    "gn:timezone":"Asia/Shanghai",
    "iso:country":"CN",
    "name:zho_x_preferred":[
        "\u6728\u574e\u5c71"
    ],
    "wof:name":"Mukanshan",
    "wof:placetype":"locality"
},
  "geometry": {"coordinates":[121.26036999999999,29.13236],"type":"Point"}
}