{
  "type": "Feature",
  "properties": {
    "gn:admin1_code":"24.0",
    "gn:asciiname":"Xiaoxiashan",
    "gn:country_code":"CN",
    "gn:dem":956,
    "gn:feature_class":"P",
    "gn:feature_code":"PPL",
    "gn:name":"Xiaoxiashan",
    "gn:population":0,
    "gn:timezone":"Asia/Shanghai",
    "iso:country":"CN",
    "name:zho_x_preferred":[
        "\u5c0f\u4e0b\u5c71"
    ],
    "wof:name":"Xiaoxiashan",
    "wof:placetype":"locality"
},
  "geometry": {"coordinates":[110.60618999999998,37.11016],"type":"Point"}
}