{
  "type": "Feature",
  "properties": {
    "gn:admin1_code":"29.0",
    "gn:asciiname":"Xinmangyang",
    "gn:country_code":"CN",
    "gn:dem":945,
    "gn:feature_class":"P",
    "gn:feature_code":"PPL",
    "gn:name":"Xinmangyang",
    "gn:population":0,
    "gn:timezone":"Asia/Shanghai",
    "iso:country":"CN",
    "name:zho_x_preferred":[
        "\u65b0\u8292\u6837"
    ],
    "wof:name":"Xinmangyang",
    "wof:placetype":"locality"
},
  "geometry": {"coordinates":[99.8489,23.0812],"type":"Point"}
}