{
  "type": "Feature",
  "properties": {
    "gn:admin1_code":"26",
    "gn:asciiname":"Juji'ao",
    "gn:country_code":"CN",
    "gn:dem":1052,
    "gn:feature_class":"P",
    "gn:feature_code":"PPL",
    "gn:name":"Juji\u2019ao",
    "gn:population":0,
    "gn:timezone":"Asia/Shanghai",
    "iso:country":"CN",
    "name:und_x_variant":[
        "\u5c40\u96c6\u5773"
    ],
    "name:zho_x_preferred":[
        "Juji\u2019ao"
    ],
    "name:zho_x_variant":[
        "\u5c40\u96c6\u5773"
    ],
    "wof:name":"Juji'ao",
    "wof:placetype":"locality"
},
  "geometry": {"coordinates":[108.52139,34.83333],"type":"Point"}
}