{
  "type": "Feature",
  "properties": {
    "gn:admin1_code":"9",
    "gn:asciiname":"Hanwangfen",
    "gn:country_code":"CN",
    "gn:dem":1298,
    "gn:feature_class":"P",
    "gn:feature_code":"PPL",
    "gn:name":"Hanwangfen",
    "gn:population":0,
    "gn:timezone":"Asia/Shanghai",
    "iso:country":"CN",
    "name:zho_x_preferred":[
        "\u6c49\u738b\u575f"
    ],
    "wof:name":"Hanwangfen",
    "wof:placetype":"locality"
},
  "geometry": {"coordinates":[111.81838,34.26388],"type":"Point"}
}