{
  "type": "Feature",
  "properties": {
    "gn:admin1_code":"30.0",
    "gn:asciiname":"Yapolei",
    "gn:country_code":"CN",
    "gn:dem":214,
    "gn:feature_class":"P",
    "gn:feature_code":"PPL",
    "gn:name":"Yapolei",
    "gn:population":0,
    "gn:timezone":"Asia/Shanghai",
    "iso:country":"CN",
    "name:zho_x_preferred":[
        "Yapolei"
    ],
    "name:zho_x_variant":[
        "\u9e2d\u5a46\u78ca"
    ],
    "wof:name":"Yapolei",
    "wof:placetype":"locality"
},
  "geometry": {"coordinates":[112.64833,25.02472],"type":"Point"}
}