{
  "type": "Feature",
  "properties": {
    "gn:admin1_code":"11.0",
    "gn:asciiname":"Lianhuachong",
    "gn:country_code":"CN",
    "gn:dem":82,
    "gn:feature_class":"P",
    "gn:feature_code":"PPL",
    "gn:name":"Lianhuachong",
    "gn:population":0,
    "gn:timezone":"Asia/Shanghai",
    "iso:country":"CN",
    "name:zho_x_preferred":[
        "\u83b2\u82b1\u51b2"
    ],
    "wof:name":"Lianhuachong",
    "wof:placetype":"locality"
},
  "geometry": {"coordinates":[113.59819,27.61966],"type":"Point"}
}