{
  "type": "Feature",
  "properties": {
    "gn:admin1_code":"30.0",
    "gn:asciiname":"Suansunshan",
    "gn:country_code":"CN",
    "gn:dem":548,
    "gn:feature_class":"P",
    "gn:feature_code":"PPL",
    "gn:name":"Suansunshan",
    "gn:population":0,
    "gn:timezone":"Asia/Shanghai",
    "iso:country":"CN",
    "name:zho_x_preferred":[
        "\u9178\u7b0b\u5c71"
    ],
    "wof:name":"Suansunshan",
    "wof:placetype":"locality"
},
  "geometry": {"coordinates":[112.23155,24.22409],"type":"Point"}
}