{
  "type": "Feature",
  "properties": {
    "gn:admin1_code":"13.0",
    "gn:asciiname":"Araltopakuduk",
    "gn:country_code":"CN",
    "gn:dem":970,
    "gn:feature_class":"P",
    "gn:feature_code":"PPL",
    "gn:name":"Araltopakuduk",
    "gn:population":0,
    "gn:timezone":"Asia/Urumqi",
    "iso:country":"CN",
    "name:uig_x_preferred":[
        "Aralt\u0275p\u0259k\u0329uduk\u0329"
    ],
    "name:uig_x_variant":[
        "Aralt\u00f6pequduq",
        "\u0626\u0627\u0631\u0627\u0644\u062a\u06c6\u067e\u06d5\u0642\u06c7\u062f\u06c7\u0642",
        "\u0410\u0440\u0430\u043b\u0442\u04e9\u043f\u04d9\u049b\u0443\u0434\u0443\u049b"
    ],
    "wof:name":"Araltopakuduk",
    "wof:placetype":"locality"
},
  "geometry": {"coordinates":[89.40000000000001,45.96667],"type":"Point"}
}