{
  "type": "Feature",
  "properties": {
    "gn:admin1_code":"9.0",
    "gn:asciiname":"Luziyuan",
    "gn:country_code":"CN",
    "gn:dem":970,
    "gn:feature_class":"P",
    "gn:feature_code":"PPL",
    "gn:name":"Luziyuan",
    "gn:population":0,
    "gn:timezone":"Asia/Shanghai",
    "iso:country":"CN",
    "name:zho_x_preferred":[
        "\u82a6\u5b50\u57a3"
    ],
    "wof:name":"Luziyuan",
    "wof:placetype":"locality"
},
  "geometry": {"coordinates":[110.71502,34.38997],"type":"Point"}
}