{
  "type": "Feature",
  "properties": {
    "gn:admin1_code":"9.0",
    "gn:asciiname":"Lijia Dawan",
    "gn:country_code":"CN",
    "gn:dem":119,
    "gn:feature_class":"P",
    "gn:feature_code":"PPL",
    "gn:name":"Lijia Dawan",
    "gn:population":0,
    "gn:timezone":"Asia/Shanghai",
    "iso:country":"CN",
    "name:zho_x_preferred":[
        "\u9ece\u5bb6\u5927\u6e7e"
    ],
    "wof:name":"Lijia Dawan",
    "wof:placetype":"locality"
},
  "geometry": {"coordinates":[114.28122999999999,31.80113],"type":"Point"}
}