{
  "type": "Feature",
  "properties": {
    "gn:admin1_code":"11.0",
    "gn:asciiname":"Gangshi",
    "gn:country_code":"CN",
    "gn:dem":40,
    "gn:feature_class":"P",
    "gn:feature_code":"PPL",
    "gn:name":"Gangshi",
    "gn:population":0,
    "gn:timezone":"Asia/Shanghai",
    "iso:country":"CN",
    "name:zho_x_preferred":[
        "Gangshi"
    ],
    "name:zho_x_variant":[
        "\u5c97\u5e02"
    ],
    "wof:name":"Gangshi",
    "wof:placetype":"locality"
},
  "geometry": {"coordinates":[111.61521999999999,29.09764],"type":"Point"}
}