{
  "type": "Feature",
  "properties": {
    "gn:admin1_code":"20.0",
    "gn:asciiname":"Yili",
    "gn:country_code":"CN",
    "gn:dem":307,
    "gn:feature_class":"P",
    "gn:feature_code":"PPLA4",
    "gn:name":"Yili",
    "gn:population":0,
    "gn:timezone":"Asia/Shanghai",
    "iso:country":"CN",
    "name:und_x_variant":[
        "Yili Zhen"
    ],
    "name:zho_x_preferred":[
        "\u5b9c\u91cc"
    ],
    "name:zho_x_variant":[
        "\u5b9c\u91cc\u9547"
    ],
    "wof:name":"Yili",
    "wof:placetype":"locality"
},
  "geometry": {"coordinates":[124.20944,49.56033],"type":"Point"}
}