{
  "type": "Feature",
  "properties": {
    "gn:admin1_code":"1.0",
    "gn:asciiname":"Daxiezhuangcun",
    "gn:country_code":"CN",
    "gn:dem":41,
    "gn:feature_class":"P",
    "gn:feature_code":"PPL",
    "gn:name":"Daxiezhuangcun",
    "gn:population":0,
    "gn:timezone":"Asia/Shanghai",
    "iso:country":"CN",
    "name:zho_x_preferred":[
        "\u5927\u8c22\u5e84\u6751"
    ],
    "wof:name":"Daxiezhuangcun",
    "wof:placetype":"locality"
},
  "geometry": {"coordinates":[115.20349,32.70728],"type":"Point"}
}