{
  "type": "Feature",
  "properties": {
    "gn:admin1_code":"32.0",
    "gn:asciiname":"Feijiawan",
    "gn:country_code":"CN",
    "gn:dem":1143,
    "gn:feature_class":"P",
    "gn:feature_code":"PPL",
    "gn:name":"Feijiawan",
    "gn:population":0,
    "gn:timezone":"Asia/Shanghai",
    "iso:country":"CN",
    "name:zho_x_preferred":[
        "\u8d39\u5bb6\u6e7e"
    ],
    "wof:name":"Feijiawan",
    "wof:placetype":"locality"
},
  "geometry": {"coordinates":[107.92348,31.51545],"type":"Point"}
}