{
  "type": "Feature",
  "properties": {
    "gn:admin1_code":"5.0",
    "gn:asciiname":"Anchengcun",
    "gn:country_code":"CN",
    "gn:dem":386,
    "gn:feature_class":"P",
    "gn:feature_code":"PPL",
    "gn:name":"Anchengcun",
    "gn:population":0,
    "gn:timezone":"Asia/Shanghai",
    "iso:country":"CN",
    "name:zho_x_preferred":[
        "\u5b89\u57ce\u6751"
    ],
    "wof:name":"Anchengcun",
    "wof:placetype":"locality"
},
  "geometry": {"coordinates":[125.48126999999999,42.92166],"type":"Point"}
}