{
  "type": "Feature",
  "properties": {
    "gn:admin1_code":"12.0",
    "gn:asciiname":"Jutouwei",
    "gn:country_code":"CN",
    "gn:dem":25,
    "gn:feature_class":"P",
    "gn:feature_code":"PPL",
    "gn:name":"Jutouwei",
    "gn:population":0,
    "gn:timezone":"Asia/Shanghai",
    "iso:country":"CN",
    "name:zho_x_preferred":[
        "\u8392\u5934\u5c3e"
    ],
    "wof:name":"Jutouwei",
    "wof:placetype":"locality"
},
  "geometry": {"coordinates":[113.61277,29.94312],"type":"Point"}
}