{
  "type": "Feature",
  "properties": {
    "gn:admin1_code":"26.0",
    "gn:asciiname":"Liujia Yuancun",
    "gn:country_code":"CN",
    "gn:dem":1219,
    "gn:feature_class":"P",
    "gn:feature_code":"PPL",
    "gn:name":"Liujia Yuancun",
    "gn:population":0,
    "gn:timezone":"Asia/Shanghai",
    "iso:country":"CN",
    "name:zho_x_preferred":[
        "\u5218\u5bb6\u586c\u6751"
    ],
    "wof:name":"Liujia Yuancun",
    "wof:placetype":"locality"
},
  "geometry": {"coordinates":[109.964,37.404],"type":"Point"}
}