{
  "type": "Feature",
  "properties": {
    "gn:admin1_code":"10.0",
    "gn:asciiname":"Zhangjia Taizi",
    "gn:country_code":"CN",
    "gn:dem":1018,
    "gn:feature_class":"P",
    "gn:feature_code":"PPL",
    "gn:name":"Zhangjia Taizi",
    "gn:population":0,
    "gn:timezone":"Asia/Shanghai",
    "iso:country":"CN",
    "name:zho_x_preferred":[
        "\u5f20\u5bb6\u53f0\u5b50"
    ],
    "wof:name":"Zhangjia Taizi",
    "wof:placetype":"locality"
},
  "geometry": {"coordinates":[114.48595,40.49117],"type":"Point"}
}