{
  "type": "Feature",
  "properties": {
    "gn:admin1_code":"12.0",
    "gn:asciiname":"Xiwangjiashan",
    "gn:country_code":"CN",
    "gn:dem":565,
    "gn:feature_class":"P",
    "gn:feature_code":"PPL",
    "gn:name":"Xiwangjiashan",
    "gn:population":0,
    "gn:timezone":"Asia/Shanghai",
    "iso:country":"CN",
    "name:zho_x_preferred":[
        "\u7ec6\u738b\u5bb6\u5c71"
    ],
    "wof:name":"Xiwangjiashan",
    "wof:placetype":"locality"
},
  "geometry": {"coordinates":[115.20551,31.46127000000001],"type":"Point"}
}