{
  "type": "Feature",
  "properties": {
    "gn:admin1_code":"29.0",
    "gn:asciiname":"Zhengdu",
    "gn:country_code":"CN",
    "gn:dem":2990,
    "gn:feature_class":"P",
    "gn:feature_code":"PPL",
    "gn:name":"Zhengdu",
    "gn:population":0,
    "gn:timezone":"Asia/Shanghai",
    "iso:country":"CN",
    "name:zho_x_preferred":[
        "\u4e89\u90fd"
    ],
    "wof:name":"Zhengdu",
    "wof:placetype":"locality"
},
  "geometry": {"coordinates":[100.221,26.771],"type":"Point"}
}