{
  "type": "Feature",
  "properties": {
    "gn:admin1_code":"26",
    "gn:asciiname":"Sangshupingzhen",
    "gn:country_code":"CN",
    "gn:dem":461,
    "gn:feature_class":"P",
    "gn:feature_code":"PPL",
    "gn:name":"Sangshupingzhen",
    "gn:population":0,
    "gn:timezone":"Asia/Shanghai",
    "iso:country":"CN",
    "wof:name":"Sangshupingzhen",
    "wof:placetype":"locality"
},
  "geometry": {"coordinates":[110.54694000000001,35.68167000000001],"type":"Point"}
}