{
  "type": "Feature",
  "properties": {
    "gn:admin1_code":"5",
    "gn:asciiname":"Nanxiaojiaohe",
    "gn:country_code":"CN",
    "gn:dem":266,
    "gn:feature_class":"P",
    "gn:feature_code":"PPL",
    "gn:name":"Nanxiaojiaohe",
    "gn:population":0,
    "gn:timezone":"Asia/Shanghai",
    "iso:country":"CN",
    "name:zho_x_preferred":[
        "\u5357\u5c0f\u86df\u6cb3"
    ],
    "wof:name":"Nanxiaojiaohe",
    "wof:placetype":"locality"
},
  "geometry": {"coordinates":[127.30500000000001,43.6894],"type":"Point"}
}