{
  "type": "Feature",
  "properties": {
    "gn:admin1_code":"29.0",
    "gn:asciiname":"Tuanbu",
    "gn:country_code":"CN",
    "gn:dem":2508,
    "gn:feature_class":"P",
    "gn:feature_code":"PPL",
    "gn:name":"Tuanbu",
    "gn:population":0,
    "gn:timezone":"Asia/Shanghai",
    "iso:country":"CN",
    "name:und_x_variant":[
        "\u56e2\u5821"
    ],
    "wof:name":"Tuanbu",
    "wof:placetype":"locality"
},
  "geometry": {"coordinates":[103.01002,27.10175],"type":"Point"}
}