{
  "type": "Feature",
  "properties": {
    "gn:admin1_code":"02",
    "gn:asciiname":"Zhongtang",
    "gn:cc2":"CN",
    "gn:country_code":"CN",
    "gn:dem":16,
    "gn:feature_class":"P",
    "gn:feature_code":"PPL",
    "gn:name":"Zhongtang",
    "gn:population":0,
    "gn:timezone":"Asia/Shanghai",
    "iso:country":"CN",
    "name:und_x_variant":[
        "Chung-t\u2019ang-ts\u2019un",
        "Zhongtang"
    ],
    "wof:name":"Zhongtang",
    "wof:placetype":"locality"
},
  "geometry": {"coordinates":[120.65528,28.14306],"type":"Point"}
}