{
  "type": "Feature",
  "properties": {
    "gn:admin1_code":"11.0",
    "gn:asciiname":"Daopingli",
    "gn:country_code":"CN",
    "gn:dem":516,
    "gn:feature_class":"P",
    "gn:feature_code":"PPL",
    "gn:name":"Daopingli",
    "gn:population":0,
    "gn:timezone":"Asia/Shanghai",
    "iso:country":"CN",
    "name:zho_x_preferred":[
        "\u5012\u576a\u91cc"
    ],
    "wof:name":"Daopingli",
    "wof:placetype":"locality"
},
  "geometry": {"coordinates":[111.95372999999999,28.16275],"type":"Point"}
}