{
  "type": "Feature",
  "properties": {
    "gn:admin1_code":"8.0",
    "gn:asciiname":"Weitang",
    "gn:country_code":"CN",
    "gn:dem":198,
    "gn:feature_class":"P",
    "gn:feature_code":"PPL",
    "gn:name":"Weitang",
    "gn:population":0,
    "gn:timezone":"Asia/Shanghai",
    "iso:country":"CN",
    "name:zho_x_preferred":[
        "\u82c7\u5858"
    ],
    "wof:name":"Weitang",
    "wof:placetype":"locality"
},
  "geometry": {"coordinates":[127.93104,45.30236],"type":"Point"}
}