{
  "type": "Feature",
  "properties": {
    "gn:admin1_code":"25",
    "gn:asciiname":"Dabuyang",
    "gn:country_code":"CN",
    "gn:dem":13,
    "gn:feature_class":"P",
    "gn:feature_code":"PPL",
    "gn:name":"Dabuyang",
    "gn:population":0,
    "gn:timezone":"Asia/Shanghai",
    "iso:country":"CN",
    "name:zho_x_preferred":[
        "\u5927\u535c\u6768"
    ],
    "wof:name":"Dabuyang",
    "wof:placetype":"locality"
},
  "geometry": {"coordinates":[117.31699999999999,37.6057],"type":"Point"}
}