{
  "type": "Feature",
  "properties": {
    "gn:admin1_code":"14.0",
    "gn:asciiname":"Zhasa",
    "gn:country_code":"CN",
    "gn:dem":4942,
    "gn:feature_class":"P",
    "gn:feature_code":"PPLF",
    "gn:name":"Zhasa",
    "gn:population":0,
    "gn:timezone":"Asia/Urumqi",
    "iso:country":"CN",
    "name:bod_x_preferred":[
        "Zhasa"
    ],
    "name:msa_x_preferred":[
        "Zhasa"
    ],
    "name:und_x_variant":[
        "Paggarama"
    ],
    "name:zho_x_preferred":[
        "\u624e\u8428"
    ],
    "name:zho_x_variant":[
        "Pagarema",
        "\u5e15\u560e\u60f9\u739b"
    ],
    "wof:name":"Zhasa",
    "wof:placetype":"locality"
},
  "geometry": {"coordinates":[91.40000000000001,32.88333],"type":"Point"}
}