{
  "type": "Feature",
  "properties": {
    "gn:admin1_code":"18",
    "gn:asciiname":"Shangfaka",
    "gn:country_code":"CN",
    "gn:dem":1525,
    "gn:feature_class":"P",
    "gn:feature_code":"PPL",
    "gn:name":"Shangfaka",
    "gn:population":0,
    "gn:timezone":"Asia/Shanghai",
    "iso:country":"CN",
    "name:zho_x_preferred":[
        "\u4e0a\u6cd5\u5361"
    ],
    "wof:name":"Shangfaka",
    "wof:placetype":"locality"
},
  "geometry": {"coordinates":[105.486,25.9964],"type":"Point"}
}