{
  "type": "Feature",
  "properties": {
    "gn:admin1_code":"16.0",
    "gn:asciiname":"Nonglou",
    "gn:country_code":"CN",
    "gn:dem":119,
    "gn:feature_class":"P",
    "gn:feature_code":"PPL",
    "gn:name":"Nonglou",
    "gn:population":0,
    "gn:timezone":"Asia/Shanghai",
    "iso:country":"CN",
    "name:zho_x_preferred":[
        "\u5f04\u697c"
    ],
    "wof:name":"Nonglou",
    "wof:placetype":"locality"
},
  "geometry": {"coordinates":[107.80800000000001,22.7712],"type":"Point"}
}