{
  "type": "Feature",
  "properties": {
    "gn:admin1_code":"7",
    "gn:asciiname":"Qiantuan",
    "gn:country_code":"CN",
    "gn:dem":174,
    "gn:feature_class":"P",
    "gn:feature_code":"PPL",
    "gn:name":"Qiantuan",
    "gn:population":0,
    "gn:timezone":"Asia/Shanghai",
    "iso:country":"CN",
    "name:und_x_variant":[
        "\u94b1\u56e2"
    ],
    "wof:name":"Qiantuan",
    "wof:placetype":"locality"
},
  "geometry": {"coordinates":[118.76555999999999,27.15556],"type":"Point"}
}