{
  "type": "Feature",
  "properties": {
    "gn:admin1_code":"32.0",
    "gn:asciiname":"Yejiagou",
    "gn:country_code":"CN",
    "gn:dem":1473,
    "gn:feature_class":"P",
    "gn:feature_code":"PPL",
    "gn:name":"Yejiagou",
    "gn:population":0,
    "gn:timezone":"Asia/Shanghai",
    "iso:country":"CN",
    "name:zho_x_preferred":[
        "\u53f6\u5bb6\u6c9f"
    ],
    "wof:name":"Yejiagou",
    "wof:placetype":"locality"
},
  "geometry": {"coordinates":[102.25288,29.47022],"type":"Point"}
}