{
  "type": "Feature",
  "properties": {
    "gn:admin1_code":"16.0",
    "gn:asciiname":"Laowoji",
    "gn:country_code":"CN",
    "gn:dem":1060,
    "gn:feature_class":"P",
    "gn:feature_code":"PPL",
    "gn:name":"Laowoji",
    "gn:population":0,
    "gn:timezone":"Asia/Shanghai",
    "iso:country":"CN",
    "name:zho_x_preferred":[
        "\u8001\u6e25\u57fa"
    ],
    "wof:name":"Laowoji",
    "wof:placetype":"locality"
},
  "geometry": {"coordinates":[107.03,25.4662],"type":"Point"}
}