{
  "type": "Feature",
  "properties": {
    "gn:admin1_code":"16.0",
    "gn:asciiname":"Rongmutang",
    "gn:country_code":"CN",
    "gn:dem":95,
    "gn:feature_class":"P",
    "gn:feature_code":"PPL",
    "gn:name":"Rongmutang",
    "gn:population":0,
    "gn:timezone":"Asia/Shanghai",
    "iso:country":"CN",
    "name:zho_x_preferred":[
        "\u6995\u6728\u5858"
    ],
    "wof:name":"Rongmutang",
    "wof:placetype":"locality"
},
  "geometry": {"coordinates":[109.986,22.4298],"type":"Point"}
}