{
  "type": "Feature",
  "properties": {
    "gn:admin1_code":"16.0",
    "gn:asciiname":"Jiaoluo",
    "gn:country_code":"CN",
    "gn:dem":1173,
    "gn:feature_class":"P",
    "gn:feature_code":"PPL",
    "gn:name":"Jiaoluo",
    "gn:population":0,
    "gn:timezone":"Asia/Shanghai",
    "iso:country":"CN",
    "name:zho_x_preferred":[
        "\u89d2\u843d"
    ],
    "wof:name":"Jiaoluo",
    "wof:placetype":"locality"
},
  "geometry": {"coordinates":[105.28700000000001,24.1597],"type":"Point"}
}