{
  "type": "Feature",
  "properties": {
    "gn:admin1_code":"8.0",
    "gn:asciiname":"Chang'anjia",
    "gn:country_code":"CN",
    "gn:dem":273,
    "gn:feature_class":"P",
    "gn:feature_code":"PPL",
    "gn:name":"Chang\u2019anjia",
    "gn:population":0,
    "gn:timezone":"Asia/Shanghai",
    "iso:country":"CN",
    "name:und_x_variant":[
        "Chang\u2019anjia"
    ],
    "name:zho_x_preferred":[
        "\u957f\u5b89\u7532"
    ],
    "wof:name":"Chang'anjia",
    "wof:placetype":"locality"
},
  "geometry": {"coordinates":[127.52358999999998,44.48542],"type":"Point"}
}