{
  "type": "Feature",
  "properties": {
    "gn:admin1_code":"10.0",
    "gn:asciiname":"Xiaodi",
    "gn:country_code":"CN",
    "gn:dem":27,
    "gn:feature_class":"P",
    "gn:feature_code":"PPL",
    "gn:name":"Xiaodi",
    "gn:population":0,
    "gn:timezone":"Asia/Shanghai",
    "iso:country":"CN",
    "name:und_x_variant":[
        "Hsiao-ti",
        "Hsiao-ti-chen",
        "Xiaodi"
    ],
    "name:zho_x_preferred":[
        "\u5c0f\u5824"
    ],
    "wof:name":"Xiaodi",
    "wof:placetype":"locality"
},
  "geometry": {"coordinates":[115.645,38.1191],"type":"Point"}
}