{
  "type": "Feature",
  "properties": {
    "gn:admin1_code":"9.0",
    "gn:asciiname":"Majiazhuang",
    "gn:country_code":"CN",
    "gn:dem":709,
    "gn:feature_class":"P",
    "gn:feature_code":"PPL",
    "gn:name":"Majiazhuang",
    "gn:population":0,
    "gn:timezone":"Asia/Shanghai",
    "iso:country":"CN",
    "name:und_x_variant":[
        "\u9a6c\u5bb6\u5e84",
        "Majiazhuang"
    ],
    "wof:name":"Majiazhuang",
    "wof:placetype":"locality"
},
  "geometry": {"coordinates":[112.17098,33.29716],"type":"Point"}
}