{
  "type": "Feature",
  "properties": {
    "gn:admin1_code":"5.0",
    "gn:asciiname":"Sanjia Majia",
    "gn:country_code":"CN",
    "gn:dem":127,
    "gn:feature_class":"P",
    "gn:feature_code":"PPL",
    "gn:name":"Sanjia Majia",
    "gn:population":0,
    "gn:timezone":"Asia/Shanghai",
    "iso:country":"CN",
    "name:zho_x_preferred":[
        "\u4e09\u5bb6\u9a6c\u67b6"
    ],
    "wof:name":"Sanjia Majia",
    "wof:placetype":"locality"
},
  "geometry": {"coordinates":[124.00078999999999,43.67733],"type":"Point"}
}