{
  "type": "Feature",
  "properties": {
    "gn:admin1_code":"01",
    "gn:asciiname":"Tangjia",
    "gn:cc2":"CN",
    "gn:country_code":"CN",
    "gn:dem":218,
    "gn:feature_class":"P",
    "gn:feature_code":"PPL",
    "gn:name":"Tangjia",
    "gn:population":0,
    "gn:timezone":"Asia/Shanghai",
    "iso:country":"CN",
    "name:und_x_variant":[
        "T\u2019ang-chia",
        "Tangjia"
    ],
    "wof:name":"Tangjia",
    "wof:placetype":"locality"
},
  "geometry": {"coordinates":[117.58333,29.95],"type":"Point"}
}