{
  "type": "Feature",
  "properties": {
    "gn:admin1_code":"25",
    "gn:asciiname":"Qinglongzhuang",
    "gn:country_code":"CN",
    "gn:dem":190,
    "gn:feature_class":"P",
    "gn:feature_code":"PPL",
    "gn:name":"Qinglongzhuang",
    "gn:population":0,
    "gn:timezone":"Asia/Shanghai",
    "iso:country":"CN",
    "name:zho_x_preferred":[
        "\u9752\u9f99\u5e84"
    ],
    "wof:name":"Qinglongzhuang",
    "wof:placetype":"locality"
},
  "geometry": {"coordinates":[117.52500000000001,35.6631],"type":"Point"}
}