{
  "type": "Feature",
  "properties": {
    "gn:admin1_code":"25",
    "gn:asciiname":"Liangzhuang",
    "gn:country_code":"CN",
    "gn:dem":42,
    "gn:feature_class":"P",
    "gn:feature_code":"PPL",
    "gn:name":"Liangzhuang",
    "gn:population":0,
    "gn:timezone":"Asia/Shanghai",
    "iso:country":"CN",
    "name:zho_x_preferred":[
        "\u6881\u5e84"
    ],
    "wof:name":"Liangzhuang",
    "wof:placetype":"locality"
},
  "geometry": {"coordinates":[116.35599999999999,35.5694],"type":"Point"}
}