{
  "type": "Feature",
  "properties": {
    "gn:admin1_code":"1.0",
    "gn:asciiname":"Nanzhongcun",
    "gn:country_code":"CN",
    "gn:dem":55,
    "gn:feature_class":"P",
    "gn:feature_code":"PPL",
    "gn:name":"Nanzhongcun",
    "gn:population":0,
    "gn:timezone":"Asia/Shanghai",
    "iso:country":"CN",
    "name:zho_x_preferred":[
        "\u5357\u949f\u6751"
    ],
    "wof:name":"Nanzhongcun",
    "wof:placetype":"locality"
},
  "geometry": {"coordinates":[117.67043,32.15163],"type":"Point"}
}