{
  "type": "Feature",
  "properties": {
    "gn:admin1_code":"23.0",
    "gn:asciiname":"Yujiajing",
    "gn:country_code":"CN",
    "gn:dem":8,
    "gn:feature_class":"P",
    "gn:feature_code":"PPL",
    "gn:name":"Yujiajing",
    "gn:population":0,
    "gn:timezone":"Asia/Shanghai",
    "iso:country":"CN",
    "name:zho_x_preferred":[
        "Yujiajing"
    ],
    "name:zho_x_variant":[
        "\u90c1\u5bb6\u6cfe"
    ],
    "wof:name":"Yujiajing",
    "wof:placetype":"locality"
},
  "geometry": {"coordinates":[121.12044,31.12683],"type":"Point"}
}