{
  "type": "Feature",
  "properties": {
    "gn:admin1_code":"18",
    "gn:asciiname":"Qikeba",
    "gn:country_code":"CN",
    "gn:dem":1037,
    "gn:feature_class":"P",
    "gn:feature_code":"PPL",
    "gn:name":"Qikeba",
    "gn:population":0,
    "gn:timezone":"Asia/Shanghai",
    "iso:country":"CN",
    "name:zho_x_preferred":[
        "\u4e03\u67ef\u575d"
    ],
    "wof:name":"Qikeba",
    "wof:placetype":"locality"
},
  "geometry": {"coordinates":[108.185,28.7009],"type":"Point"}
}