{
  "type": "Feature",
  "properties": {
    "gn:admin1_code":"10",
    "gn:asciiname":"Chaicheng",
    "gn:country_code":"CN",
    "gn:dem":33,
    "gn:feature_class":"P",
    "gn:feature_code":"PPL",
    "gn:name":"Chaicheng",
    "gn:population":0,
    "gn:timezone":"Asia/Shanghai",
    "iso:country":"CN",
    "name:zho_x_preferred":[
        "\u67f4\u57ce"
    ],
    "wof:name":"Chaicheng",
    "wof:placetype":"locality"
},
  "geometry": {"coordinates":[115.11199999999999,37.3276],"type":"Point"}
}