{
  "type": "Feature",
  "properties": {
    "gn:admin1_code":"33.0",
    "gn:asciiname":"Liannong",
    "gn:country_code":"CN",
    "gn:dem":446,
    "gn:feature_class":"P",
    "gn:feature_code":"PPL",
    "gn:name":"Liannong",
    "gn:population":0,
    "gn:timezone":"Asia/Shanghai",
    "iso:country":"CN",
    "name:zho_x_preferred":[
        "\u8054\u519c"
    ],
    "wof:name":"Liannong",
    "wof:placetype":"locality"
},
  "geometry": {"coordinates":[107.48765,29.58289000000001],"type":"Point"}
}