{
  "type": "Feature",
  "properties": {
    "gn:admin1_code":"16.0",
    "gn:asciiname":"Bangna",
    "gn:country_code":"CN",
    "gn:dem":875,
    "gn:feature_class":"P",
    "gn:feature_code":"PPL",
    "gn:name":"Bangna",
    "gn:population":0,
    "gn:timezone":"Asia/Shanghai",
    "iso:country":"CN",
    "name:zho_x_preferred":[
        "\u699c\u7eb3"
    ],
    "wof:name":"Bangna",
    "wof:placetype":"locality"
},
  "geometry": {"coordinates":[105.53400000000001,24.7208],"type":"Point"}
}