{
  "type": "Feature",
  "properties": {
    "gn:admin1_code":"32.0",
    "gn:asciiname":"Weilejue",
    "gn:country_code":"CN",
    "gn:dem":2726,
    "gn:feature_class":"P",
    "gn:feature_code":"PPL",
    "gn:name":"Weilejue",
    "gn:population":0,
    "gn:timezone":"Asia/Shanghai",
    "iso:country":"CN",
    "name:zho_x_preferred":[
        "\u7ef4\u52d2\u89c9"
    ],
    "wof:name":"Weilejue",
    "wof:placetype":"locality"
},
  "geometry": {"coordinates":[103.116,28.234],"type":"Point"}
}