{
  "type": "Feature",
  "properties": {
    "gn:admin1_code":"9.0",
    "gn:asciiname":"Biandanli",
    "gn:country_code":"CN",
    "gn:dem":89,
    "gn:feature_class":"P",
    "gn:feature_code":"PPL",
    "gn:name":"Biandanli",
    "gn:population":0,
    "gn:timezone":"Asia/Shanghai",
    "iso:country":"CN",
    "name:zho_x_preferred":[
        "\u6241\u62c5\u674e"
    ],
    "wof:name":"Biandanli",
    "wof:placetype":"locality"
},
  "geometry": {"coordinates":[113.42346000000001,33.51938],"type":"Point"}
}