{
  "type": "Feature",
  "properties": {
    "gn:admin1_code":"16.0",
    "gn:asciiname":"Naneicun",
    "gn:country_code":"CN",
    "gn:dem":318,
    "gn:feature_class":"P",
    "gn:feature_code":"PPL",
    "gn:name":"Naneicun",
    "gn:population":0,
    "gn:timezone":"Asia/Shanghai",
    "iso:country":"CN",
    "name:zho_x_preferred":[
        "\u90a3\u5185\u6751"
    ],
    "wof:name":"Naneicun",
    "wof:placetype":"locality"
},
  "geometry": {"coordinates":[107.608,22.8382],"type":"Point"}
}