{
  "type": "Feature",
  "properties": {
    "gn:admin1_code":"12.0",
    "gn:asciiname":"Dawujin",
    "gn:country_code":"CN",
    "gn:dem":38,
    "gn:feature_class":"P",
    "gn:feature_code":"PPL",
    "gn:name":"Dawujin",
    "gn:population":0,
    "gn:timezone":"Asia/Shanghai",
    "iso:country":"CN",
    "name:und_x_variant":[
        "\u5927\u5c4b\u91d1"
    ],
    "wof:name":"Dawujin",
    "wof:placetype":"locality"
},
  "geometry": {"coordinates":[114.32276,30.12411],"type":"Point"}
}