{
  "type": "Feature",
  "properties": {
    "gn:admin1_code":"03",
    "gn:asciiname":"Zixiao",
    "gn:country_code":"CN",
    "gn:dem":142,
    "gn:feature_class":"P",
    "gn:feature_code":"PPLA4",
    "gn:name":"Zixiao",
    "gn:population":0,
    "gn:timezone":"Asia/Shanghai",
    "iso:country":"CN",
    "name:und_x_variant":[
        "Ch\u2019ia-ts\u2019un",
        "Qiacun",
        "\u7d2b\u9704",
        "\u7d2b\u9704\u9547",
        "Zixiao Zhen",
        "\u6d3d\u6751"
    ],
    "name:zho_x_preferred":[
        "Zixiao"
    ],
    "wof:name":"Zixiao",
    "wof:placetype":"locality"
},
  "geometry": {"coordinates":[116.28251000000002,27.01759],"type":"Point"}
}