{
  "type": "Feature",
  "properties": {
    "gn:admin1_code":"26.0",
    "gn:asciiname":"Guojia Huochangcun",
    "gn:country_code":"CN",
    "gn:dem":1113,
    "gn:feature_class":"P",
    "gn:feature_code":"PPL",
    "gn:name":"Guojia Huochangcun",
    "gn:population":0,
    "gn:timezone":"Asia/Shanghai",
    "iso:country":"CN",
    "name:zho_x_preferred":[
        "\u90ed\u5bb6\u4f19\u573a\u6751"
    ],
    "wof:name":"Guojia Huochangcun",
    "wof:placetype":"locality"
},
  "geometry": {"coordinates":[109.703,38.4265],"type":"Point"}
}