{
  "type": "Feature",
  "properties": {
    "gn:admin1_code":"5.0",
    "gn:asciiname":"Telicun",
    "gn:country_code":"CN",
    "gn:dem":134,
    "gn:feature_class":"P",
    "gn:feature_code":"PPL",
    "gn:name":"Telicun",
    "gn:population":0,
    "gn:timezone":"Asia/Shanghai",
    "iso:country":"CN",
    "name:zho_x_preferred":[
        "\u7279\u529b\u6751"
    ],
    "wof:name":"Telicun",
    "wof:placetype":"locality"
},
  "geometry": {"coordinates":[123.49721,46.20423],"type":"Point"}
}