{
  "type": "Feature",
  "properties": {
    "gn:admin1_code":"9.0",
    "gn:asciiname":"Xia'an",
    "gn:country_code":"CN",
    "gn:dem":151,
    "gn:feature_class":"P",
    "gn:feature_code":"PPL",
    "gn:name":"Xia\u2019an",
    "gn:population":0,
    "gn:timezone":"Asia/Shanghai",
    "iso:country":"CN",
    "name:zho_x_preferred":[
        "\u4e0b\u5b89"
    ],
    "name:zho_x_variant":[
        "Xia\u2019an"
    ],
    "wof:name":"Xia'an",
    "wof:placetype":"locality"
},
  "geometry": {"coordinates":[113.38509000000001,33.15167],"type":"Point"}
}