{
  "type": "Feature",
  "properties": {
    "gn:admin1_code":"30",
    "gn:asciiname":"Aozai",
    "gn:country_code":"CN",
    "gn:dem":85,
    "gn:feature_class":"P",
    "gn:feature_code":"PPLA4",
    "gn:name":"Aozai",
    "gn:population":0,
    "gn:timezone":"Asia/Shanghai",
    "iso:country":"CN",
    "name:und_x_variant":[
        "Ao-tsai",
        "Aozai",
        "Aozai Zhen",
        "\u5773\u4ed4\u9547"
    ],
    "name:zho_x_preferred":[
        "\u5773\u4ed4"
    ],
    "wof:name":"Aozai",
    "wof:placetype":"locality"
},
  "geometry": {"coordinates":[112.30495999999999,23.79268],"type":"Point"}
}