{
  "type": "Feature",
  "properties": {
    "gn:admin1_code":"02",
    "gn:asciiname":"Wurongcun",
    "gn:country_code":"CN",
    "gn:dem":12,
    "gn:feature_class":"P",
    "gn:feature_code":"PPL",
    "gn:name":"Wurongcun",
    "gn:population":0,
    "gn:timezone":"Asia/Shanghai",
    "iso:country":"CN",
    "name:und_x_variant":[
        "Wurong",
        "\u5434\u878d",
        "Wu-jung",
        "Wurongcun"
    ],
    "name:zho_x_preferred":[
        "\u5434\u878d\u6751"
    ],
    "wof:name":"Wurongcun",
    "wof:placetype":"locality"
},
  "geometry": {"coordinates":[120.6919,30.0683],"type":"Point"}
}