{
  "type": "Feature",
  "properties": {
    "gn:admin1_code":"11.0",
    "gn:asciiname":"Chang'anyuan",
    "gn:country_code":"CN",
    "gn:dem":34,
    "gn:feature_class":"P",
    "gn:feature_code":"PPL",
    "gn:name":"Chang\u2019anyuan",
    "gn:population":0,
    "gn:timezone":"Asia/Shanghai",
    "iso:country":"CN",
    "name:und_x_variant":[
        "Chang\u2019anyuan"
    ],
    "name:zho_x_preferred":[
        "\u957f\u5b89\u57b8"
    ],
    "wof:name":"Chang'anyuan",
    "wof:placetype":"locality"
},
  "geometry": {"coordinates":[112.24433999999999,29.53614],"type":"Point"}
}