{
  "type": "Feature",
  "properties": {
    "gn:admin1_code":"32.0",
    "gn:asciiname":"Baihewan",
    "gn:country_code":"CN",
    "gn:dem":349,
    "gn:feature_class":"P",
    "gn:feature_code":"PPL",
    "gn:name":"Baihewan",
    "gn:population":0,
    "gn:timezone":"Asia/Shanghai",
    "iso:country":"CN",
    "name:zho_x_preferred":[
        "\u767d\u6cb3\u6e7e"
    ],
    "wof:name":"Baihewan",
    "wof:placetype":"locality"
},
  "geometry": {"coordinates":[104.628,29.5219],"type":"Point"}
}