{
  "type": "Feature",
  "properties": {
    "gn:admin1_code":"10.0",
    "gn:asciiname":"Xizhaotong",
    "gn:country_code":"CN",
    "gn:dem":70,
    "gn:feature_class":"P",
    "gn:feature_code":"PPLA4",
    "gn:name":"Xizhaotong",
    "gn:population":0,
    "gn:timezone":"Asia/Shanghai",
    "iso:country":"CN",
    "name:und_x_variant":[
        "\u897f\u5146\u901a",
        "Xizhaotong Zhen",
        "\u897f\u5146\u901a\u9547"
    ],
    "wof:name":"Xizhaotong",
    "wof:placetype":"locality"
},
  "geometry": {"coordinates":[114.59675,38.07161],"type":"Point"}
}