{
  "type": "Feature",
  "properties": {
    "gn:admin1_code":"25.0",
    "gn:asciiname":"Xizhuanqucun",
    "gn:country_code":"CN",
    "gn:dem":30,
    "gn:feature_class":"P",
    "gn:feature_code":"PPL",
    "gn:name":"Xizhuanqucun",
    "gn:population":0,
    "gn:timezone":"Asia/Shanghai",
    "iso:country":"CN",
    "name:zho_x_preferred":[
        "\u897f\u8f6c\u6e20\u6751"
    ],
    "wof:name":"Xizhuanqucun",
    "wof:placetype":"locality"
},
  "geometry": {"coordinates":[120.40482,37.61316],"type":"Point"}
}