{
  "type": "Feature",
  "properties": {
    "gn:admin1_code":"3.0",
    "gn:asciiname":"Huangjiakan",
    "gn:country_code":"CN",
    "gn:dem":43,
    "gn:feature_class":"P",
    "gn:feature_code":"PPL",
    "gn:name":"Huangjiakan",
    "gn:population":0,
    "gn:timezone":"Asia/Shanghai",
    "iso:country":"CN",
    "name:und_x_variant":[
        "\u9ec4\u5bb6\u574e"
    ],
    "wof:name":"Huangjiakan",
    "wof:placetype":"locality"
},
  "geometry": {"coordinates":[115.87007,29.55823],"type":"Point"}
}