{
  "type": "Feature",
  "properties": {
    "gn:admin1_code":"15.0",
    "gn:asciiname":"Xiawangjia",
    "gn:country_code":"CN",
    "gn:dem":1777,
    "gn:feature_class":"P",
    "gn:feature_code":"PPL",
    "gn:name":"Xiawangjia",
    "gn:population":0,
    "gn:timezone":"Asia/Shanghai",
    "iso:country":"CN",
    "name:zho_x_preferred":[
        "\u4e0b\u738b\u5bb6"
    ],
    "wof:name":"Xiawangjia",
    "wof:placetype":"locality"
},
  "geometry": {"coordinates":[104.66,36.2303],"type":"Point"}
}