{
  "type": "Feature",
  "properties": {
    "gn:admin1_code":"29.0",
    "gn:asciiname":"Shangyanwacun",
    "gn:country_code":"CN",
    "gn:dem":1795,
    "gn:feature_class":"P",
    "gn:feature_code":"PPL",
    "gn:name":"Shangyanwacun",
    "gn:population":0,
    "gn:timezone":"Asia/Shanghai",
    "iso:country":"CN",
    "name:zho_x_preferred":[
        "\u4e0a\u781a\u74e6\u6751"
    ],
    "wof:name":"Shangyanwacun",
    "wof:placetype":"locality"
},
  "geometry": {"coordinates":[102.503,25.5695],"type":"Point"}
}