{
  "type": "Feature",
  "properties": {
    "gn:admin1_code":"29.0",
    "gn:asciiname":"Zhonghe Laozhai",
    "gn:country_code":"CN",
    "gn:dem":1918,
    "gn:feature_class":"P",
    "gn:feature_code":"PPL",
    "gn:name":"Zhonghe Laozhai",
    "gn:population":0,
    "gn:timezone":"Asia/Shanghai",
    "iso:country":"CN",
    "name:zho_x_preferred":[
        "\u4e2d\u548c\u8001\u5be8"
    ],
    "wof:name":"Zhonghe Laozhai",
    "wof:placetype":"locality"
},
  "geometry": {"coordinates":[104.21899999999999,24.8102],"type":"Point"}
}