{
  "type": "Feature",
  "properties": {
    "gn:admin1_code":"30",
    "gn:asciiname":"Chetianwei",
    "gn:country_code":"CN",
    "gn:dem":27,
    "gn:feature_class":"P",
    "gn:feature_code":"PPL",
    "gn:name":"Chetianwei",
    "gn:population":0,
    "gn:timezone":"Asia/Urumqi",
    "iso:country":"CN",
    "name:zho_x_preferred":[
        "\u8f66\u7530\u5c3e"
    ],
    "wof:name":"Chetianwei",
    "wof:placetype":"locality"
},
  "geometry": {"coordinates":[110.75214,21.8687],"type":"Point"}
}