{
  "type": "Feature",
  "properties": {
    "gn:admin1_code":"29.0",
    "gn:asciiname":"Duoyi",
    "gn:country_code":"CN",
    "gn:dem":1381,
    "gn:feature_class":"P",
    "gn:feature_code":"PPL",
    "gn:name":"Duoyi",
    "gn:population":0,
    "gn:timezone":"Asia/Shanghai",
    "iso:country":"CN",
    "name:zho_x_preferred":[
        "\u591a\u8863"
    ],
    "wof:name":"Duoyi",
    "wof:placetype":"locality"
},
  "geometry": {"coordinates":[103.562,23.1192],"type":"Point"}
}