{
  "type": "Feature",
  "properties": {
    "gn:admin1_code":"18",
    "gn:asciiname":"Pingzhai",
    "gn:country_code":"CN",
    "gn:dem":786,
    "gn:feature_class":"P",
    "gn:feature_code":"PPL",
    "gn:name":"Pingzhai",
    "gn:population":0,
    "gn:timezone":"Asia/Shanghai",
    "iso:country":"CN",
    "name:zho_x_preferred":[
        "\u5e73\u5be8"
    ],
    "wof:name":"Pingzhai",
    "wof:placetype":"locality"
},
  "geometry": {"coordinates":[106.405,25.4444],"type":"Point"}
}