{
  "type": "Feature",
  "properties": {
    "gn:admin1_code":"33.0",
    "gn:asciiname":"Baishuihe",
    "gn:country_code":"CN",
    "gn:dem":245,
    "gn:feature_class":"P",
    "gn:feature_code":"PPL",
    "gn:name":"Baishuihe",
    "gn:population":0,
    "gn:timezone":"Asia/Shanghai",
    "iso:country":"CN",
    "name:zho_x_preferred":[
        "\u767d\u6c34\u6cb3"
    ],
    "wof:name":"Baishuihe",
    "wof:placetype":"locality"
},
  "geometry": {"coordinates":[109.90206000000001,31.12017],"type":"Point"}
}