{
  "type": "Feature",
  "properties": {
    "gn:admin1_code":"12.0",
    "gn:asciiname":"Dacaijia'ao",
    "gn:country_code":"CN",
    "gn:dem":1219,
    "gn:feature_class":"P",
    "gn:feature_code":"PPL",
    "gn:name":"Dacaijia\u2019ao",
    "gn:population":0,
    "gn:timezone":"Asia/Shanghai",
    "iso:country":"CN",
    "name:und_x_variant":[
        "Dacaijia\u2019ao"
    ],
    "name:zho_x_preferred":[
        "\u5927\u8521\u5bb6\u51f9"
    ],
    "wof:name":"Dacaijia'ao",
    "wof:placetype":"locality"
},
  "geometry": {"coordinates":[110.03102,32.53740999999999],"type":"Point"}
}