{
  "type": "Feature",
  "properties": {
    "gn:admin1_code":"9.0",
    "gn:asciiname":"Yeqiaohe",
    "gn:country_code":"CN",
    "gn:dem":939,
    "gn:feature_class":"P",
    "gn:feature_code":"PPL",
    "gn:name":"Yeqiaohe",
    "gn:population":0,
    "gn:timezone":"Asia/Shanghai",
    "iso:country":"CN",
    "name:zho_x_preferred":[
        "\u91ce\u4e54\u6cb3"
    ],
    "wof:name":"Yeqiaohe",
    "wof:placetype":"locality"
},
  "geometry": {"coordinates":[111.28547,34.52585],"type":"Point"}
}