{
  "type": "Feature",
  "properties": {
    "gn:admin1_code":"3.0",
    "gn:asciiname":"Lianjiatan",
    "gn:country_code":"CN",
    "gn:dem":113,
    "gn:feature_class":"P",
    "gn:feature_code":"PPL",
    "gn:name":"Lianjiatan",
    "gn:population":0,
    "gn:timezone":"Asia/Shanghai",
    "iso:country":"CN",
    "name:und_x_variant":[
        "\u8fde\u5bb6\u6ee9"
    ],
    "wof:name":"Lianjiatan",
    "wof:placetype":"locality"
},
  "geometry": {"coordinates":[116.38432,26.97513],"type":"Point"}
}