{
  "type": "Feature",
  "properties": {
    "gn:admin1_code":"14.0",
    "gn:asciiname":"Walaicun",
    "gn:country_code":"CN",
    "gn:dem":3068,
    "gn:feature_class":"P",
    "gn:feature_code":"PPL",
    "gn:name":"Walaicun",
    "gn:population":0,
    "gn:timezone":"Asia/Urumqi",
    "iso:country":"CN",
    "name:zho_x_preferred":[
        "\u74e6\u6765\u6751"
    ],
    "wof:name":"Walaicun",
    "wof:placetype":"locality"
},
  "geometry": {"coordinates":[97.05645,30.015],"type":"Point"}
}