{
  "type": "Feature",
  "properties": {
    "gn:admin1_code":"26.0",
    "gn:asciiname":"Heitaoyuan",
    "gn:country_code":"CN",
    "gn:dem":1049,
    "gn:feature_class":"P",
    "gn:feature_code":"PPL",
    "gn:name":"Heitaoyuan",
    "gn:population":0,
    "gn:timezone":"Asia/Shanghai",
    "iso:country":"CN",
    "name:zho_x_preferred":[
        "\u9ed1\u6843\u56ed"
    ],
    "wof:name":"Heitaoyuan",
    "wof:placetype":"locality"
},
  "geometry": {"coordinates":[108.9914,32.35405],"type":"Point"}
}