{
  "type": "Feature",
  "properties": {
    "gn:admin1_code":"16.0",
    "gn:asciiname":"Liudong",
    "gn:country_code":"CN",
    "gn:dem":277,
    "gn:feature_class":"P",
    "gn:feature_code":"PPL",
    "gn:name":"Liudong",
    "gn:population":0,
    "gn:timezone":"Asia/Shanghai",
    "iso:country":"CN",
    "name:zho_x_preferred":[
        "\u6d41\u5cd2"
    ],
    "wof:name":"Liudong",
    "wof:placetype":"locality"
},
  "geometry": {"coordinates":[108.48699999999999,24.9322],"type":"Point"}
}