{
  "type": "Feature",
  "properties": {
    "gn:admin1_code":"25",
    "gn:asciiname":"Yuantuanguojia",
    "gn:country_code":"CN",
    "gn:dem":52,
    "gn:feature_class":"P",
    "gn:feature_code":"PPL",
    "gn:name":"Yuantuanguojia",
    "gn:population":0,
    "gn:timezone":"Asia/Shanghai",
    "iso:country":"CN",
    "name:zho_x_preferred":[
        "\u539f\u7583\u90ed\u5bb6"
    ],
    "wof:name":"Yuantuanguojia",
    "wof:placetype":"locality"
},
  "geometry": {"coordinates":[120.337,37.4264],"type":"Point"}
}