{
  "type": "Feature",
  "properties": {
    "gn:admin1_code":"2.0",
    "gn:asciiname":"Dameikou",
    "gn:country_code":"CN",
    "gn:dem":351,
    "gn:feature_class":"P",
    "gn:feature_code":"PPL",
    "gn:name":"Dameikou",
    "gn:population":0,
    "gn:timezone":"Asia/Shanghai",
    "iso:country":"CN",
    "name:und_x_variant":[
        "\u5927\u6885\u53e3"
    ],
    "wof:name":"Dameikou",
    "wof:placetype":"locality"
},
  "geometry": {"coordinates":[118.97472,27.8502],"type":"Point"}
}