{
  "type": "Feature",
  "properties": {
    "gn:admin1_code":"26",
    "gn:asciiname":"Chishui",
    "gn:country_code":"CN",
    "gn:dem":346,
    "gn:feature_class":"P",
    "gn:feature_code":"PPLA4",
    "gn:name":"Chishui",
    "gn:population":0,
    "gn:timezone":"Asia/Shanghai",
    "iso:country":"CN",
    "name:deu_x_preferred":[
        "Chishui"
    ],
    "name:nor_x_preferred":[
        "Chishui"
    ],
    "name:pam_x_preferred":[
        "Chishui"
    ],
    "name:und_x_variant":[
        "Ch\u2019ih-shui",
        "Ch\u2019ih-shui-chen",
        "\u8d64\u6c34",
        "Chishui Zhen"
    ],
    "wof:name":"Chishui",
    "wof:placetype":"locality"
},
  "geometry": {"coordinates":[109.64243999999999,34.50723],"type":"Point"}
}