{
  "type": "Feature",
  "properties": {
    "gn:admin1_code":"32.0",
    "gn:asciiname":"Akulewu",
    "gn:country_code":"CN",
    "gn:dem":1981,
    "gn:feature_class":"P",
    "gn:feature_code":"PPL",
    "gn:name":"Akulewu",
    "gn:population":0,
    "gn:timezone":"Asia/Shanghai",
    "iso:country":"CN",
    "name:zho_x_preferred":[
        "\u963f\u5e93\u4e50\u4e4c"
    ],
    "wof:name":"Akulewu",
    "wof:placetype":"locality"
},
  "geometry": {"coordinates":[103.006,27.8187],"type":"Point"}
}