{
  "type": "Feature",
  "properties": {
    "gn:admin1_code":"4.0",
    "gn:asciiname":"Dong'erxudai",
    "gn:country_code":"CN",
    "gn:dem":2,
    "gn:feature_class":"P",
    "gn:feature_code":"PPL",
    "gn:name":"Dong\u2019erxudai",
    "gn:population":0,
    "gn:timezone":"Asia/Shanghai",
    "iso:country":"CN",
    "name:und_x_variant":[
        "Dong\u2019erxudai"
    ],
    "name:zho_x_preferred":[
        "\u4e1c\u4e8c\u5729\u5788"
    ],
    "wof:name":"Dong'erxudai",
    "wof:placetype":"locality"
},
  "geometry": {"coordinates":[120.08531000000001,32.04960999999999],"type":"Point"}
}