{
  "type": "Feature",
  "properties": {
    "gn:admin1_code":"9.0",
    "gn:asciiname":"Quxicun",
    "gn:country_code":"CN",
    "gn:dem":100,
    "gn:feature_class":"P",
    "gn:feature_code":"PPL",
    "gn:name":"Quxicun",
    "gn:population":0,
    "gn:timezone":"Asia/Shanghai",
    "iso:country":"CN",
    "name:zho_x_preferred":[
        "\u6e20\u897f\u6751"
    ],
    "wof:name":"Quxicun",
    "wof:placetype":"locality"
},
  "geometry": {"coordinates":[112.53298999999998,32.64162],"type":"Point"}
}