{
  "type": "Feature",
  "properties": {
    "gn:admin1_code":"14.0",
    "gn:asciiname":"Bairecun",
    "gn:country_code":"CN",
    "gn:dem":3318,
    "gn:feature_class":"P",
    "gn:feature_code":"PPL",
    "gn:name":"Bairecun",
    "gn:population":0,
    "gn:timezone":"Asia/Urumqi",
    "iso:country":"CN",
    "name:zho_x_preferred":[
        "\u767d\u70ed\u6751"
    ],
    "wof:name":"Bairecun",
    "wof:placetype":"locality"
},
  "geometry": {"coordinates":[93.03583999999999,29.03773],"type":"Point"}
}