{
  "type": "Feature",
  "properties": {
    "gn:admin1_code":"3.0",
    "gn:asciiname":"Shaliwang",
    "gn:country_code":"CN",
    "gn:dem":33,
    "gn:feature_class":"P",
    "gn:feature_code":"PPL",
    "gn:name":"Shaliwang",
    "gn:population":0,
    "gn:timezone":"Asia/Shanghai",
    "iso:country":"CN",
    "name:und_x_variant":[
        "\u6c99\u91cc\u738b"
    ],
    "wof:name":"Shaliwang",
    "wof:placetype":"locality"
},
  "geometry": {"coordinates":[116.13736000000002,29.65306],"type":"Point"}
}