{
  "type": "Feature",
  "properties": {
    "gn:admin1_code":"13.0",
    "gn:asciiname":"Rokiya",
    "gn:country_code":"CN",
    "gn:dem":1410,
    "gn:feature_class":"P",
    "gn:feature_code":"PPLA4",
    "gn:name":"Rokiya",
    "gn:population":0,
    "gn:timezone":"Asia/Urumqi",
    "iso:country":"CN",
    "name:uig_x_preferred":[
        "Rok\u0329iy\u0259"
    ],
    "name:uig_x_variant":[
        "Roqiye",
        "\u0631\u0648\u0642\u0649\u064a\u06d5",
        "\u0420\u043e\u049b\u044b\u044f"
    ],
    "name:und_x_variant":[
        "Rokiya Xiang",
        "Rokiya",
        "Ruokeya",
        "Ruokeya Xiang"
    ],
    "name:zho_x_preferred":[
        "\u82e5\u514b\u96c5"
    ],
    "name:zho_x_variant":[
        "\u82e5\u514b\u96c5\u4e61"
    ],
    "wof:name":"Rokiya",
    "wof:placetype":"locality"
},
  "geometry": {"coordinates":[82.81528,37.07861],"type":"Point"}
}