{
  "type": "Feature",
  "properties": {
    "gn:admin1_code":"8.0",
    "gn:asciiname":"Hongwei",
    "gn:country_code":"CN",
    "gn:dem":112,
    "gn:feature_class":"P",
    "gn:feature_code":"PPL",
    "gn:name":"Hongwei",
    "gn:population":0,
    "gn:timezone":"Asia/Shanghai",
    "iso:country":"CN",
    "name:zho_x_preferred":[
        "\u5b8f\u4f1f"
    ],
    "wof:name":"Hongwei",
    "wof:placetype":"locality"
},
  "geometry": {"coordinates":[128.68106,49.46511],"type":"Point"}
}