{
  "type": "Feature",
  "properties": {
    "gn:admin1_code":"15.0",
    "gn:asciiname":"Dujiashan",
    "gn:country_code":"CN",
    "gn:dem":1701,
    "gn:feature_class":"P",
    "gn:feature_code":"PPL",
    "gn:name":"Dujiashan",
    "gn:population":0,
    "gn:timezone":"Asia/Shanghai",
    "iso:country":"CN",
    "name:zho_x_preferred":[
        "\u675c\u5bb6\u5c71"
    ],
    "wof:name":"Dujiashan",
    "wof:placetype":"locality"
},
  "geometry": {"coordinates":[105.795,34.2894],"type":"Point"}
}