{
  "type": "Feature",
  "properties": {
    "gn:admin1_code":"25",
    "gn:asciiname":"Xiliujia Zhuangzi",
    "gn:country_code":"CN",
    "gn:dem":110,
    "gn:feature_class":"P",
    "gn:feature_code":"PPL",
    "gn:name":"Xiliujia Zhuangzi",
    "gn:population":0,
    "gn:timezone":"Asia/Shanghai",
    "iso:country":"CN",
    "name:zho_x_preferred":[
        "\u897f\u5218\u5bb6\u5e84\u5b50"
    ],
    "wof:name":"Xiliujia Zhuangzi",
    "wof:placetype":"locality"
},
  "geometry": {"coordinates":[119.07599999999999,36.1394],"type":"Point"}
}