{
  "type": "Feature",
  "properties": {
    "gn:admin1_code":"8.0",
    "gn:asciiname":"Xinhuacun",
    "gn:country_code":"CN",
    "gn:dem":278,
    "gn:feature_class":"P",
    "gn:feature_code":"PPL",
    "gn:name":"Xinhuacun",
    "gn:population":0,
    "gn:timezone":"Asia/Shanghai",
    "iso:country":"CN",
    "name:zho_x_preferred":[
        "\u65b0\u534e\u6751"
    ],
    "wof:name":"Xinhuacun",
    "wof:placetype":"locality"
},
  "geometry": {"coordinates":[122.52876000000001,47.25945],"type":"Point"}
}