{
  "type": "Feature",
  "properties": {
    "gn:admin1_code":"25",
    "gn:asciiname":"Beizhai",
    "gn:country_code":"CN",
    "gn:dem":90,
    "gn:feature_class":"P",
    "gn:feature_code":"PPL",
    "gn:name":"Beizhai",
    "gn:population":0,
    "gn:timezone":"Asia/Shanghai",
    "iso:country":"CN",
    "name:und_x_variant":[
        "Beizhai Jiedao"
    ],
    "name:zho_x_preferred":[
        "\u5317\u5b85"
    ],
    "name:zho_x_variant":[
        "\u5317\u5b85\u8857\u9053"
    ],
    "wof:name":"Beizhai",
    "wof:placetype":"locality"
},
  "geometry": {"coordinates":[120.52967,36.21944000000001],"type":"Point"}
}