{
  "type": "Feature",
  "properties": {
    "gn:admin1_code":"24",
    "gn:asciiname":"Dahua",
    "gn:country_code":"CN",
    "gn:dem":1314,
    "gn:feature_class":"P",
    "gn:feature_code":"PPL",
    "gn:name":"Dahua",
    "gn:population":0,
    "gn:timezone":"Asia/Shanghai",
    "iso:country":"CN",
    "name:und_x_variant":[
        "Ta-hua",
        "Ta-hua-ts\u2019un",
        "Dahua"
    ],
    "name:zho_x_preferred":[
        "\u5927\u5316"
    ],
    "wof:name":"Dahua",
    "wof:placetype":"locality"
},
  "geometry": {"coordinates":[111.31992,38.8372],"type":"Point"}
}