{
  "type": "Feature",
  "properties": {
    "gn:admin1_code":"1.0",
    "gn:asciiname":"Shutancun",
    "gn:country_code":"CN",
    "gn:dem":551,
    "gn:feature_class":"P",
    "gn:feature_code":"PPL",
    "gn:name":"Shutancun",
    "gn:population":0,
    "gn:timezone":"Asia/Shanghai",
    "iso:country":"CN",
    "name:zho_x_preferred":[
        "\u8212\u6f6d\u6751"
    ],
    "wof:name":"Shutancun",
    "wof:placetype":"locality"
},
  "geometry": {"coordinates":[116.46262,30.88092],"type":"Point"}
}