{
  "type": "Feature",
  "properties": {
    "gn:admin1_code":"15.0",
    "gn:asciiname":"Qiangquanzi",
    "gn:country_code":"CN",
    "gn:dem":1999,
    "gn:feature_class":"P",
    "gn:feature_code":"PPL",
    "gn:name":"Qiangquanzi",
    "gn:population":0,
    "gn:timezone":"Asia/Shanghai",
    "iso:country":"CN",
    "name:zho_x_preferred":[
        "\u5899\u5708\u5b50"
    ],
    "wof:name":"Qiangquanzi",
    "wof:placetype":"locality"
},
  "geometry": {"coordinates":[104.131,36.6455],"type":"Point"}
}