{
  "type": "Feature",
  "properties": {
    "gn:admin1_code":"19.0",
    "gn:asciiname":"Wofosi",
    "gn:country_code":"CN",
    "gn:dem":47,
    "gn:feature_class":"P",
    "gn:feature_code":"PPL",
    "gn:name":"Wofosi",
    "gn:population":0,
    "gn:timezone":"Asia/Shanghai",
    "iso:country":"CN",
    "name:zho_x_preferred":[
        "\u5367\u4f5b\u5bfa"
    ],
    "wof:name":"Wofosi",
    "wof:placetype":"locality"
},
  "geometry": {"coordinates":[120.90322999999999,41.03532],"type":"Point"}
}