{
  "type": "Feature",
  "properties": {
    "gn:admin1_code":"1.0",
    "gn:asciiname":"Baishawan",
    "gn:country_code":"CN",
    "gn:dem":372,
    "gn:feature_class":"P",
    "gn:feature_code":"PPL",
    "gn:name":"Baishawan",
    "gn:population":0,
    "gn:timezone":"Asia/Shanghai",
    "iso:country":"CN",
    "name:und_x_variant":[
        "\u767d\u6c99\u6e7e",
        "Baishawan"
    ],
    "wof:name":"Baishawan",
    "wof:placetype":"locality"
},
  "geometry": {"coordinates":[118.59659000000001,29.71671],"type":"Point"}
}