{
  "type": "Feature",
  "properties": {
    "gn:admin1_code":"3.0",
    "gn:asciiname":"Pailou",
    "gn:country_code":"CN",
    "gn:dem":29,
    "gn:feature_class":"P",
    "gn:feature_code":"PPL",
    "gn:name":"Pailou",
    "gn:population":0,
    "gn:timezone":"Asia/Shanghai",
    "iso:country":"CN",
    "name:ceb_x_preferred":[
        "Pailou"
    ],
    "name:pol_x_preferred":[
        "Pailou"
    ],
    "name:swe_x_preferred":[
        "Pailou"
    ],
    "name:und_x_variant":[
        "\u724c\u697c"
    ],
    "wof:name":"Pailou",
    "wof:placetype":"locality"
},
  "geometry": {"coordinates":[116.24173999999999,29.59165],"type":"Point"}
}