{
  "type": "Feature",
  "properties": {
    "gn:admin1_code":"4.0",
    "gn:asciiname":"Changjing",
    "gn:country_code":"CN",
    "gn:dem":4,
    "gn:feature_class":"P",
    "gn:feature_code":"PPLA4",
    "gn:name":"Changjing",
    "gn:population":0,
    "gn:timezone":"Asia/Shanghai",
    "iso:country":"CN",
    "name:und_x_variant":[
        "Ch\u2019ang-ching",
        "Ch\u2019ang-ching-chen",
        "Changjing",
        "\u957f\u6cfe",
        "Changjing Zhen"
    ],
    "name:zho_x_preferred":[
        "\u957f\u6cfe\u9547"
    ],
    "wof:name":"Changjing",
    "wof:placetype":"locality"
},
  "geometry": {"coordinates":[120.47781999999999,31.75507],"type":"Point"}
}