{
  "type": "Feature",
  "properties": {
    "gn:admin1_code":"24.0",
    "gn:asciiname":"Nansangquan",
    "gn:country_code":"CN",
    "gn:dem":1418,
    "gn:feature_class":"P",
    "gn:feature_code":"PPL",
    "gn:name":"Nansangquan",
    "gn:population":0,
    "gn:timezone":"Asia/Shanghai",
    "iso:country":"CN",
    "name:zho_x_preferred":[
        "\u5357\u6851\u6cc9"
    ],
    "wof:name":"Nansangquan",
    "wof:placetype":"locality"
},
  "geometry": {"coordinates":[113.35720999999999,38.6814],"type":"Point"}
}