{
  "type": "Feature",
  "properties": {
    "gn:admin1_code":"30.0",
    "gn:asciiname":"Meilongxia",
    "gn:country_code":"CN",
    "gn:dem":136,
    "gn:feature_class":"P",
    "gn:feature_code":"PPL",
    "gn:name":"Meilongxia",
    "gn:population":0,
    "gn:timezone":"Asia/Shanghai",
    "iso:country":"CN",
    "name:zho_x_preferred":[
        "Meilongxia"
    ],
    "name:zho_x_variant":[
        "\u7164\u9f99\u4e0b"
    ],
    "wof:name":"Meilongxia",
    "wof:placetype":"locality"
},
  "geometry": {"coordinates":[113.42083999999998,25.01607000000001],"type":"Point"}
}