{
  "type": "Feature",
  "properties": {
    "gn:admin1_code":"14",
    "gn:asciiname":"Kongkangsar",
    "gn:country_code":"CN",
    "gn:dem":4473,
    "gn:feature_class":"P",
    "gn:feature_code":"PPL",
    "gn:name":"Kongkangsar",
    "gn:population":0,
    "gn:timezone":"Asia/Urumqi",
    "iso:country":"CN",
    "name:bod_x_preferred":[
        "\u0f42\u0f7c\u0f44\u0f0b\u0f41\u0f44\u0f0b\u0f42\u0f66\u0f62"
    ],
    "name:und_x_variant":[
        "Gongkangsha",
        "Gongkangsa"
    ],
    "name:zho_x_preferred":[
        "\u8d21\u5eb7\u6c99"
    ],
    "name:zho_x_variant":[
        "\u8d21\u5eb7\u8428"
    ],
    "wof:name":"Kongkangsar",
    "wof:placetype":"locality"
},
  "geometry": {"coordinates":[92.20619000000001,29.14601],"type":"Point"}
}