{
  "type": "Feature",
  "properties": {
    "gn:admin1_code":"33.0",
    "gn:asciiname":"Xiaolingmiao",
    "gn:country_code":"CN",
    "gn:dem":306,
    "gn:feature_class":"P",
    "gn:feature_code":"PPL",
    "gn:name":"Xiaolingmiao",
    "gn:population":0,
    "gn:timezone":"Asia/Shanghai",
    "iso:country":"CN",
    "name:zho_x_preferred":[
        "\u5c0f\u7075\u5e99"
    ],
    "wof:name":"Xiaolingmiao",
    "wof:placetype":"locality"
},
  "geometry": {"coordinates":[105.79492,30.41532],"type":"Point"}
}