{
  "type": "Feature",
  "properties": {
    "gn:admin1_code":"4.0",
    "gn:asciiname":"Wujia",
    "gn:country_code":"CN",
    "gn:dem":44,
    "gn:feature_class":"P",
    "gn:feature_code":"PPL",
    "gn:name":"Wujia",
    "gn:population":0,
    "gn:timezone":"Asia/Shanghai",
    "iso:country":"CN",
    "name:zho_x_preferred":[
        "\u5434\u5bb6"
    ],
    "wof:name":"Wujia",
    "wof:placetype":"locality"
},
  "geometry": {"coordinates":[119.64855,32.09589],"type":"Point"}
}