{
  "type": "Feature",
  "properties": {
    "gn:admin1_code":"29.0",
    "gn:asciiname":"Shangsazuo",
    "gn:country_code":"CN",
    "gn:dem":2184,
    "gn:feature_class":"P",
    "gn:feature_code":"PPL",
    "gn:name":"Shangsazuo",
    "gn:population":0,
    "gn:timezone":"Asia/Shanghai",
    "iso:country":"CN",
    "name:zho_x_preferred":[
        "\u4e0a\u6d12\u4f50"
    ],
    "wof:name":"Shangsazuo",
    "wof:placetype":"locality"
},
  "geometry": {"coordinates":[104.432,25.2155],"type":"Point"}
}