{
  "type": "Feature",
  "properties": {
    "gn:admin1_code":"12.0",
    "gn:asciiname":"Yujiawan",
    "gn:country_code":"CN",
    "gn:dem":94,
    "gn:feature_class":"P",
    "gn:feature_code":"PPL",
    "gn:name":"Yujiawan",
    "gn:population":0,
    "gn:timezone":"Asia/Shanghai",
    "iso:country":"CN",
    "name:zho_x_preferred":[
        "Yujiawan"
    ],
    "name:zho_x_variant":[
        "\u55bb\u5bb6\u6e7e"
    ],
    "wof:name":"Yujiawan",
    "wof:placetype":"locality"
},
  "geometry": {"coordinates":[114.39183,29.8659],"type":"Point"}
}