{
  "type": "Feature",
  "properties": {
    "gn:admin1_code":"16",
    "gn:asciiname":"Qiaoli",
    "gn:cc2":"CN",
    "gn:country_code":"CN",
    "gn:dem":192,
    "gn:feature_class":"P",
    "gn:feature_code":"PPL",
    "gn:name":"Qiaoli",
    "gn:population":0,
    "gn:timezone":"Asia/Shanghai",
    "iso:country":"CN",
    "name:und_x_variant":[
        "Ch\u2019iao-li-ts\u2019un",
        "Ch\u2019iao-li",
        "Ch\u2019iao-hs\u00fc",
        "Ch\u2019iao-li-hs\u00fc",
        "Qiaoli"
    ],
    "wof:name":"Qiaoli",
    "wof:placetype":"locality"
},
  "geometry": {"coordinates":[108.10611000000002,23.63722000000001],"type":"Point"}
}