{
  "type": "Feature",
  "properties": {
    "gn:admin1_code":"26",
    "gn:asciiname":"Tuo'erxiang",
    "gn:country_code":"CN",
    "gn:dem":977,
    "gn:feature_class":"P",
    "gn:feature_code":"PPL",
    "gn:name":"Tuo\u2019erxiang",
    "gn:population":0,
    "gn:timezone":"Asia/Shanghai",
    "iso:country":"CN",
    "name:und_x_variant":[
        "T\u2019o-erh-hsiang",
        "Tuo\u2019erxiang"
    ],
    "wof:name":"Tuo'erxiang",
    "wof:placetype":"locality"
},
  "geometry": {"coordinates":[109.91694,37.52194],"type":"Point"}
}