{
  "type": "Feature",
  "properties": {
    "gn:admin1_code":"8.0",
    "gn:asciiname":"Fucuncun",
    "gn:country_code":"CN",
    "gn:dem":67,
    "gn:feature_class":"P",
    "gn:feature_code":"PPL",
    "gn:name":"Fucuncun",
    "gn:population":0,
    "gn:timezone":"Asia/Shanghai",
    "iso:country":"CN",
    "name:zho_x_preferred":[
        "\u5bcc\u6751\u6751"
    ],
    "wof:name":"Fucuncun",
    "wof:placetype":"locality"
},
  "geometry": {"coordinates":[133.02445,45.91308],"type":"Point"}
}