{
  "type": "Feature",
  "properties": {
    "gn:admin1_code":"9",
    "gn:asciiname":"Guocaolou",
    "gn:country_code":"CN",
    "gn:dem":48,
    "gn:feature_class":"P",
    "gn:feature_code":"PPL",
    "gn:name":"Guocaolou",
    "gn:population":0,
    "gn:timezone":"Asia/Shanghai",
    "iso:country":"CN",
    "name:zho_x_preferred":[
        "\u90ed\u8349\u697c"
    ],
    "wof:name":"Guocaolou",
    "wof:placetype":"locality"
},
  "geometry": {"coordinates":[115.41500000000001,33.995],"type":"Point"}
}