{
  "type": "Feature",
  "properties": {
    "gn:admin1_code":"15.0",
    "gn:asciiname":"Liufanggou",
    "gn:country_code":"CN",
    "gn:dem":1784,
    "gn:feature_class":"P",
    "gn:feature_code":"PPL",
    "gn:name":"Liufanggou",
    "gn:population":0,
    "gn:timezone":"Asia/Shanghai",
    "iso:country":"CN",
    "name:und_x_variant":[
        "\u516d\u623f\u6c9f"
    ],
    "wof:name":"Liufanggou",
    "wof:placetype":"locality"
},
  "geometry": {"coordinates":[105.17480999999999,33.15701],"type":"Point"}
}