{
  "type": "Feature",
  "properties": {
    "gn:admin1_code":"12.0",
    "gn:asciiname":"Liangshuiquan",
    "gn:country_code":"CN",
    "gn:dem":402,
    "gn:feature_class":"P",
    "gn:feature_code":"PPL",
    "gn:name":"Liangshuiquan",
    "gn:population":0,
    "gn:timezone":"Asia/Shanghai",
    "iso:country":"CN",
    "name:zho_x_preferred":[
        "\u51c9\u6c34\u6cc9"
    ],
    "wof:name":"Liangshuiquan",
    "wof:placetype":"locality"
},
  "geometry": {"coordinates":[110.33107,32.68965],"type":"Point"}
}