{
  "type": "Feature",
  "properties": {
    "gn:admin1_code":"26.0",
    "gn:asciiname":"Zaolinzicun",
    "gn:country_code":"CN",
    "gn:dem":1076,
    "gn:feature_class":"P",
    "gn:feature_code":"PPL",
    "gn:name":"Zaolinzicun",
    "gn:population":0,
    "gn:timezone":"Asia/Shanghai",
    "iso:country":"CN",
    "name:zho_x_preferred":[
        "\u67a3\u6797\u5b50\u6751"
    ],
    "wof:name":"Zaolinzicun",
    "wof:placetype":"locality"
},
  "geometry": {"coordinates":[108.25766000000002,35.00549],"type":"Point"}
}