{
  "type": "Feature",
  "properties": {
    "gn:admin1_code":"2.0",
    "gn:asciiname":"Bogongkeng",
    "gn:country_code":"CN",
    "gn:dem":486,
    "gn:feature_class":"P",
    "gn:feature_code":"PPL",
    "gn:name":"Bogongkeng",
    "gn:population":0,
    "gn:timezone":"Asia/Shanghai",
    "iso:country":"CN",
    "name:zho_x_preferred":[
        "\u6cca\u516c\u5751"
    ],
    "wof:name":"Bogongkeng",
    "wof:placetype":"locality"
},
  "geometry": {"coordinates":[120.42306000000001,28.86979],"type":"Point"}
}