{
  "type": "Feature",
  "properties": {
    "gn:admin1_code":"26",
    "gn:asciiname":"Luozhencun",
    "gn:country_code":"CN",
    "gn:dem":493,
    "gn:feature_class":"P",
    "gn:feature_code":"PPL",
    "gn:name":"Luozhencun",
    "gn:population":0,
    "gn:timezone":"Asia/Shanghai",
    "iso:country":"CN",
    "name:und_x_variant":[
        "Lo-chen-pa",
        "Luozhenba",
        "Luozhen",
        "Luozhencun"
    ],
    "name:zho_x_preferred":[
        "\u7f57\u9547\u6751"
    ],
    "name:zho_x_variant":[
        "\u9a86\u9547\u6751"
    ],
    "wof:name":"Luozhencun",
    "wof:placetype":"locality"
},
  "geometry": {"coordinates":[107.8218,32.88563],"type":"Point"}
}