{
  "type": "Feature",
  "properties": {
    "gn:admin1_code":"15.0",
    "gn:asciiname":"Zhuanpinggou",
    "gn:country_code":"CN",
    "gn:dem":1246,
    "gn:feature_class":"P",
    "gn:feature_code":"PPL",
    "gn:name":"Zhuanpinggou",
    "gn:population":0,
    "gn:timezone":"Asia/Shanghai",
    "iso:country":"CN",
    "name:zho_x_preferred":[
        "\u7816\u576a\u6c9f"
    ],
    "wof:name":"Zhuanpinggou",
    "wof:placetype":"locality"
},
  "geometry": {"coordinates":[105.387,32.7257],"type":"Point"}
}