{
  "type": "Feature",
  "properties": {
    "gn:admin1_code":"4.0",
    "gn:asciiname":"Limiaocun",
    "gn:country_code":"CN",
    "gn:dem":21,
    "gn:feature_class":"P",
    "gn:feature_code":"PPL",
    "gn:name":"Limiaocun",
    "gn:population":0,
    "gn:timezone":"Asia/Shanghai",
    "iso:country":"CN",
    "name:zho_x_preferred":[
        "\u674e\u5e99\u6751"
    ],
    "wof:name":"Limiaocun",
    "wof:placetype":"locality"
},
  "geometry": {"coordinates":[118.33947999999999,33.40088],"type":"Point"}
}