{
  "type": "Feature",
  "properties": {
    "gn:admin1_code":"8.0",
    "gn:asciiname":"Xin'er Qiancun",
    "gn:country_code":"CN",
    "gn:dem":195,
    "gn:feature_class":"P",
    "gn:feature_code":"PPL",
    "gn:name":"Xin\u2019er Qiancun",
    "gn:population":0,
    "gn:timezone":"Asia/Shanghai",
    "iso:country":"CN",
    "name:und_x_variant":[
        "Xin\u2019er Qiancun"
    ],
    "name:zho_x_preferred":[
        "\u4fe1\u4e8c\u524d\u6751"
    ],
    "wof:name":"Xin'er Qiancun",
    "wof:placetype":"locality"
},
  "geometry": {"coordinates":[126.74554000000001,46.77869000000001],"type":"Point"}
}