{
  "type": "Feature",
  "properties": {
    "gn:admin1_code":"2.0",
    "gn:asciiname":"Hutangxia",
    "gn:country_code":"CN",
    "gn:dem":3,
    "gn:feature_class":"P",
    "gn:feature_code":"PPL",
    "gn:name":"Hutangxia",
    "gn:population":0,
    "gn:timezone":"Asia/Shanghai",
    "iso:country":"CN",
    "name:zho_x_preferred":[
        "\u6e56\u5858\u4e0b"
    ],
    "wof:name":"Hutangxia",
    "wof:placetype":"locality"
},
  "geometry": {"coordinates":[121.39032,30.1274],"type":"Point"}
}