{
  "type": "Feature",
  "properties": {
    "gn:admin1_code":"8.0",
    "gn:asciiname":"Xinshengcun",
    "gn:country_code":"CN",
    "gn:dem":184,
    "gn:feature_class":"P",
    "gn:feature_code":"PPL",
    "gn:name":"Xinshengcun",
    "gn:population":0,
    "gn:timezone":"Asia/Shanghai",
    "iso:country":"CN",
    "name:zho_x_preferred":[
        "\u65b0\u80dc\u6751"
    ],
    "wof:name":"Xinshengcun",
    "wof:placetype":"locality"
},
  "geometry": {"coordinates":[127.18573000000001,46.54776],"type":"Point"}
}