{
  "type": "Feature",
  "properties": {
    "gn:admin1_code":"9.0",
    "gn:asciiname":"Duntaili",
    "gn:country_code":"CN",
    "gn:dem":63,
    "gn:feature_class":"P",
    "gn:feature_code":"PPL",
    "gn:name":"Duntaili",
    "gn:population":0,
    "gn:timezone":"Asia/Shanghai",
    "iso:country":"CN",
    "name:zho_x_preferred":[
        "\u58a9\u53f0\u674e"
    ],
    "wof:name":"Duntaili",
    "wof:placetype":"locality"
},
  "geometry": {"coordinates":[114.02811,33.84544],"type":"Point"}
}