{
  "type": "Feature",
  "properties": {
    "gn:admin1_code":"26.0",
    "gn:asciiname":"Daleijiagou",
    "gn:country_code":"CN",
    "gn:dem":1009,
    "gn:feature_class":"P",
    "gn:feature_code":"PPL",
    "gn:name":"Daleijiagou",
    "gn:population":0,
    "gn:timezone":"Asia/Shanghai",
    "iso:country":"CN",
    "name:zho_x_preferred":[
        "\u5927\u96f7\u5bb6\u6c9f"
    ],
    "wof:name":"Daleijiagou",
    "wof:placetype":"locality"
},
  "geometry": {"coordinates":[109.80568999999998,33.54863],"type":"Point"}
}