{
  "type": "Feature",
  "properties": {
    "gn:admin1_code":"7.0",
    "gn:asciiname":"Baishicun",
    "gn:country_code":"CN",
    "gn:dem":374,
    "gn:feature_class":"P",
    "gn:feature_code":"PPL",
    "gn:name":"Baishicun",
    "gn:population":0,
    "gn:timezone":"Asia/Shanghai",
    "iso:country":"CN",
    "name:und_x_variant":[
        "\u767d\u77f3\u6751"
    ],
    "name:zho_x_preferred":[
        "\u767d\u77f3\u6751"
    ],
    "wof:name":"Baishicun",
    "wof:placetype":"locality"
},
  "geometry": {"coordinates":[117.53403,26.99787],"type":"Point"}
}