{
  "type": "Feature",
  "properties": {
    "gn:admin1_code":"15.0",
    "gn:asciiname":"Chenggou",
    "gn:country_code":"CN",
    "gn:dem":1652,
    "gn:feature_class":"P",
    "gn:feature_code":"PPL",
    "gn:name":"Chenggou",
    "gn:population":0,
    "gn:timezone":"Asia/Shanghai",
    "iso:country":"CN",
    "name:und_x_variant":[
        "\u7a0b\u6c9f"
    ],
    "wof:name":"Chenggou",
    "wof:placetype":"locality"
},
  "geometry": {"coordinates":[105.71871000000002,34.99791],"type":"Point"}
}