{
  "type": "Feature",
  "properties": {
    "gn:admin1_code":"1.0",
    "gn:asciiname":"Yitai",
    "gn:country_code":"CN",
    "gn:dem":12,
    "gn:feature_class":"P",
    "gn:feature_code":"PPLA4",
    "gn:name":"Yitai",
    "gn:population":0,
    "gn:timezone":"Asia/Shanghai",
    "iso:country":"CN",
    "name:und_x_variant":[
        "Yitai Zhen",
        "Duangang"
    ],
    "name:zho_x_preferred":[
        "\u6613\u592a"
    ],
    "name:zho_x_variant":[
        "\u6613\u592a\u9547",
        "\u6bb5\u6e2f"
    ],
    "wof:name":"Yitai",
    "wof:placetype":"locality"
},
  "geometry": {"coordinates":[118.48589,31.27607],"type":"Point"}
}