{
  "type": "Feature",
  "properties": {
    "gn:admin1_code":"3",
    "gn:asciiname":"Shiweiping",
    "gn:country_code":"CN",
    "gn:dem":670,
    "gn:feature_class":"P",
    "gn:feature_code":"PPL",
    "gn:name":"Shiweiping",
    "gn:population":0,
    "gn:timezone":"Asia/Shanghai",
    "iso:country":"CN",
    "name:zho_x_preferred":[
        "\u77f3\u56f4\u576a"
    ],
    "wof:name":"Shiweiping",
    "wof:placetype":"locality"
},
  "geometry": {"coordinates":[114.208,26.8005],"type":"Point"}
}