{
  "type": "Feature",
  "properties": {
    "gn:admin1_code":"3.0",
    "gn:asciiname":"Huangguan",
    "gn:country_code":"CN",
    "gn:dem":424,
    "gn:feature_class":"P",
    "gn:feature_code":"PPL",
    "gn:name":"Huangguan",
    "gn:population":0,
    "gn:timezone":"Asia/Shanghai",
    "iso:country":"CN",
    "name:zho_x_preferred":[
        "\u9ec4\u5173"
    ],
    "wof:name":"Huangguan",
    "wof:placetype":"locality"
},
  "geometry": {"coordinates":[118.392,28.3239],"type":"Point"}
}