{
  "type": "Feature",
  "properties": {
    "gn:admin1_code":"30",
    "gn:asciiname":"Dashuibang",
    "gn:country_code":"CN",
    "gn:dem":76,
    "gn:feature_class":"P",
    "gn:feature_code":"PPL",
    "gn:name":"Dashuibang",
    "gn:population":0,
    "gn:timezone":"Asia/Shanghai",
    "iso:country":"CN",
    "name:und_x_variant":[
        "\u5927\u6c34\u585d"
    ],
    "wof:name":"Dashuibang",
    "wof:placetype":"locality"
},
  "geometry": {"coordinates":[112.74917000000001,24.07833],"type":"Point"}
}