{
  "type": "Feature",
  "properties": {
    "gn:admin1_code":"8.0",
    "gn:asciiname":"Lianfa Yidui",
    "gn:country_code":"CN",
    "gn:dem":349,
    "gn:feature_class":"P",
    "gn:feature_code":"PPLF",
    "gn:name":"Lianfa Yidui",
    "gn:population":0,
    "gn:timezone":"Asia/Shanghai",
    "iso:country":"CN",
    "name:zho_x_preferred":[
        "\u8054\u53d1\u4e00\u961f"
    ],
    "wof:name":"Lianfa Yidui",
    "wof:placetype":"locality"
},
  "geometry": {"coordinates":[125.68889,48.25687],"type":"Point"}
}