{
  "type": "Feature",
  "properties": {
    "gn:admin1_code":"16.0",
    "gn:asciiname":"Nongtuan",
    "gn:country_code":"CN",
    "gn:dem":436,
    "gn:feature_class":"P",
    "gn:feature_code":"PPL",
    "gn:name":"Nongtuan",
    "gn:population":0,
    "gn:timezone":"Asia/Shanghai",
    "iso:country":"CN",
    "name:zho_x_preferred":[
        "\u5f04\u56e2"
    ],
    "wof:name":"Nongtuan",
    "wof:placetype":"locality"
},
  "geometry": {"coordinates":[108.10899999999999,24.0978],"type":"Point"}
}