{
  "type": "Feature",
  "properties": {
    "gn:admin1_code":"18.0",
    "gn:asciiname":"Paozhai",
    "gn:country_code":"CN",
    "gn:dem":1039,
    "gn:feature_class":"P",
    "gn:feature_code":"PPL",
    "gn:name":"Paozhai",
    "gn:population":0,
    "gn:timezone":"Asia/Shanghai",
    "iso:country":"CN",
    "name:zho_x_preferred":[
        "\u888d\u5be8"
    ],
    "wof:name":"Paozhai",
    "wof:placetype":"locality"
},
  "geometry": {"coordinates":[107.527,25.585],"type":"Point"}
}