{
  "type": "Feature",
  "properties": {
    "gn:admin1_code":"7",
    "gn:asciiname":"Fengjiaping",
    "gn:country_code":"CN",
    "gn:dem":871,
    "gn:feature_class":"P",
    "gn:feature_code":"PPL",
    "gn:name":"Fengjiaping",
    "gn:population":0,
    "gn:timezone":"Asia/Shanghai",
    "iso:country":"CN",
    "name:und_x_variant":[
        "\u51af\u5bb6\u576a",
        "Fengjiaping"
    ],
    "wof:name":"Fengjiaping",
    "wof:placetype":"locality"
},
  "geometry": {"coordinates":[119.58363,27.60345],"type":"Point"}
}