{
  "type": "Feature",
  "properties": {
    "gn:admin1_code":"01",
    "gn:asciiname":"Dasi",
    "gn:cc2":"CN",
    "gn:country_code":"CN",
    "gn:dem":35,
    "gn:feature_class":"P",
    "gn:feature_code":"PPL",
    "gn:name":"Dasi",
    "gn:population":0,
    "gn:timezone":"Asia/Shanghai",
    "iso:country":"CN",
    "name:und_x_variant":[
        "Ta-ssu-chi",
        "Dasi Zhen",
        "Dasiji",
        "Dasi"
    ],
    "wof:name":"Dasi",
    "wof:placetype":"locality"
},
  "geometry": {"coordinates":[115.88333,33.78667],"type":"Point"}
}