{
  "type": "Feature",
  "properties": {
    "gn:admin1_code":"11.0",
    "gn:asciiname":"Xiaojiechongtou",
    "gn:country_code":"CN",
    "gn:dem":550,
    "gn:feature_class":"P",
    "gn:feature_code":"PPL",
    "gn:name":"Xiaojiechongtou",
    "gn:population":0,
    "gn:timezone":"Asia/Shanghai",
    "iso:country":"CN",
    "name:zho_x_preferred":[
        "\u5c0f\u754c\u51b2\u5934"
    ],
    "wof:name":"Xiaojiechongtou",
    "wof:placetype":"locality"
},
  "geometry": {"coordinates":[109.57792000000001,26.85417],"type":"Point"}
}