{
  "type": "Feature",
  "properties": {
    "gn:admin1_code":"12.0",
    "gn:asciiname":"Taipingqiao",
    "gn:country_code":"CN",
    "gn:dem":275,
    "gn:feature_class":"P",
    "gn:feature_code":"PPL",
    "gn:name":"Taipingqiao",
    "gn:population":0,
    "gn:timezone":"Asia/Shanghai",
    "iso:country":"CN",
    "name:zho_x_preferred":[
        "Taipingqiao"
    ],
    "name:zho_x_variant":[
        "\u592a\u5e73\u6865"
    ],
    "wof:name":"Taipingqiao",
    "wof:placetype":"locality"
},
  "geometry": {"coordinates":[111.27155999999999,30.1968],"type":"Point"}
}