{
  "type": "Feature",
  "properties": {
    "gn:admin1_code":"9.0",
    "gn:asciiname":"Wangliuzhuang",
    "gn:country_code":"CN",
    "gn:dem":123,
    "gn:feature_class":"P",
    "gn:feature_code":"PPL",
    "gn:name":"Wangliuzhuang",
    "gn:population":0,
    "gn:timezone":"Asia/Shanghai",
    "iso:country":"CN",
    "name:zho_x_preferred":[
        "\u738b\u5218\u5e84"
    ],
    "wof:name":"Wangliuzhuang",
    "wof:placetype":"locality"
},
  "geometry": {"coordinates":[113.678,34.41685],"type":"Point"}
}