{
  "type": "Feature",
  "properties": {
    "gn:admin1_code":"1.0",
    "gn:asciiname":"Jiusheng",
    "gn:country_code":"CN",
    "gn:dem":95,
    "gn:feature_class":"P",
    "gn:feature_code":"PPL",
    "gn:name":"Jiusheng",
    "gn:population":0,
    "gn:timezone":"Asia/Shanghai",
    "iso:country":"CN",
    "name:zho_x_preferred":[
        "\u4e45\u80dc"
    ],
    "wof:name":"Jiusheng",
    "wof:placetype":"locality"
},
  "geometry": {"coordinates":[118.13141,30.83849],"type":"Point"}
}