{
  "type": "Feature",
  "properties": {
    "gn:admin1_code":"4.0",
    "gn:asciiname":"Zhujiazao",
    "gn:country_code":"CN",
    "gn:dem":1,
    "gn:feature_class":"P",
    "gn:feature_code":"PPL",
    "gn:name":"Zhujiazao",
    "gn:population":0,
    "gn:timezone":"Asia/Shanghai",
    "iso:country":"CN",
    "name:und_x_variant":[
        "Chu-chia-tun",
        "Chu-chia-tsao",
        "Zhujiadun",
        "Zhujiazao"
    ],
    "name:zho_x_preferred":[
        "\u795d\u5bb6\u7076"
    ],
    "wof:name":"Zhujiazao",
    "wof:placetype":"locality"
},
  "geometry": {"coordinates":[120.56667,32.85],"type":"Point"}
}