{
  "type": "Feature",
  "properties": {
    "gn:admin1_code":"32.0",
    "gn:asciiname":"Chazigou",
    "gn:country_code":"CN",
    "gn:dem":360,
    "gn:feature_class":"P",
    "gn:feature_code":"PPL",
    "gn:name":"Chazigou",
    "gn:population":0,
    "gn:timezone":"Asia/Shanghai",
    "iso:country":"CN",
    "name:zho_x_preferred":[
        "\u8336\u5b50\u6c9f"
    ],
    "wof:name":"Chazigou",
    "wof:placetype":"locality"
},
  "geometry": {"coordinates":[104.63,29.023],"type":"Point"}
}