{
  "type": "Feature",
  "properties": {
    "gn:admin1_code":"19.0",
    "gn:asciiname":"Housanjiazicun",
    "gn:country_code":"CN",
    "gn:dem":57,
    "gn:feature_class":"P",
    "gn:feature_code":"PPL",
    "gn:name":"Housanjiazicun",
    "gn:population":0,
    "gn:timezone":"Asia/Shanghai",
    "iso:country":"CN",
    "name:zho_x_preferred":[
        "\u4faf\u4e09\u5bb6\u5b50\u6751"
    ],
    "wof:name":"Housanjiazicun",
    "wof:placetype":"locality"
},
  "geometry": {"coordinates":[123.152,42.36],"type":"Point"}
}