{
  "type": "Feature",
  "properties": {
    "gn:admin1_code":"5.0",
    "gn:asciiname":"Ajiajie",
    "gn:country_code":"CN",
    "gn:dem":370,
    "gn:feature_class":"P",
    "gn:feature_code":"PPL",
    "gn:name":"Ajiajie",
    "gn:population":0,
    "gn:timezone":"Asia/Shanghai",
    "iso:country":"CN",
    "name:zho_x_preferred":[
        "\u77ee\u5bb6\u8857"
    ],
    "wof:name":"Ajiajie",
    "wof:placetype":"locality"
},
  "geometry": {"coordinates":[125.34723,42.60726],"type":"Point"}
}