{
  "type": "Feature",
  "properties": {
    "gn:admin1_code":"9.0",
    "gn:asciiname":"Tudiya",
    "gn:country_code":"CN",
    "gn:dem":1211,
    "gn:feature_class":"P",
    "gn:feature_code":"PPL",
    "gn:name":"Tudiya",
    "gn:population":0,
    "gn:timezone":"Asia/Shanghai",
    "iso:country":"CN",
    "name:afr_x_preferred":[
        "Tudia"
    ],
    "name:amh_x_preferred":[
        "\u1271\u12f2\u12eb"
    ],
    "name:ara_x_preferred":[
        "\u062a\u0648\u062f\u064a\u0627"
    ],
    "name:bul_x_preferred":[
        "\u0422\u0443\u0434\u0438\u044f"
    ],
    "name:cat_x_preferred":[
        "Tudiya"
    ],
    "name:deu_x_preferred":[
        "T\u016bd\u012bja"
    ],
    "name:ell_x_preferred":[
        "\u03a4\u03bf\u03c5\u03bd\u03c4\u03af\u03b3\u03b9\u03b1"
    ],
    "name:fin_x_preferred":[
        "Tudiya"
    ],
    "name:ind_x_preferred":[
        "Tudiya"
    ],
    "name:nld_x_preferred":[
        "Tudiya"
    ],
    "name:ron_x_preferred":[
        "Tudia"
    ],
    "name:spa_x_preferred":[
        "Tudia"
    ],
    "name:srp_x_preferred":[
        "\u0422\u0443\u0434\u0438\u0458\u0430"
    ],
    "name:tur_x_preferred":[
        "Tudiya"
    ],
    "name:zho_x_preferred":[
        "\u571f\u5730\u57ad"
    ],
    "name:zho_x_variant":[
        "\u56fe\u8fea\u4e9a"
    ],
    "wof:name":"Tudiya",
    "wof:placetype":"locality"
},
  "geometry": {"coordinates":[111.40576,33.79563],"type":"Point"}
}