{
  "type": "Feature",
  "properties": {
    "gn:admin1_code":"19.0",
    "gn:asciiname":"Miaozigou",
    "gn:country_code":"CN",
    "gn:dem":278,
    "gn:feature_class":"P",
    "gn:feature_code":"PPL",
    "gn:name":"Miaozigou",
    "gn:population":0,
    "gn:timezone":"Asia/Shanghai",
    "iso:country":"CN",
    "name:und_x_variant":[
        "\u5e99\u5b50\u6c9f"
    ],
    "wof:name":"Miaozigou",
    "wof:placetype":"locality"
},
  "geometry": {"coordinates":[123.07084,40.731],"type":"Point"}
}