{
  "type": "Feature",
  "properties": {
    "gn:admin1_code":"11.0",
    "gn:asciiname":"Laotianchong",
    "gn:country_code":"CN",
    "gn:dem":419,
    "gn:feature_class":"P",
    "gn:feature_code":"PPL",
    "gn:name":"Laotianchong",
    "gn:population":0,
    "gn:timezone":"Asia/Shanghai",
    "iso:country":"CN",
    "name:zho_x_preferred":[
        "\u8001\u7530\u51b2"
    ],
    "wof:name":"Laotianchong",
    "wof:placetype":"locality"
},
  "geometry": {"coordinates":[109.48846,27.95413],"type":"Point"}
}