{
  "type": "Feature",
  "properties": {
    "gn:admin1_code":"16.0",
    "gn:asciiname":"Fulu",
    "gn:country_code":"CN",
    "gn:dem":619,
    "gn:feature_class":"P",
    "gn:feature_code":"PPL",
    "gn:name":"Fulu",
    "gn:population":0,
    "gn:timezone":"Asia/Shanghai",
    "iso:country":"CN",
    "name:deu_x_preferred":[
        "Fulu"
    ],
    "name:fra_x_preferred":[
        "Talisman"
    ],
    "name:nld_x_preferred":[
        "Fulu"
    ],
    "name:rus_x_preferred":[
        "\u0424\u0443\u043b\u0443"
    ],
    "name:ukr_x_preferred":[
        "\u0424\u0443\u043b\u0443"
    ],
    "name:zho_x_preferred":[
        "\u752b\u7f15"
    ],
    "wof:name":"Fulu",
    "wof:placetype":"locality"
},
  "geometry": {"coordinates":[106.904,23.9773],"type":"Point"}
}