{
  "type": "Feature",
  "properties": {
    "gn:admin1_code":"30.0",
    "gn:asciiname":"Langjin",
    "gn:country_code":"CN",
    "gn:dem":15,
    "gn:feature_class":"P",
    "gn:feature_code":"PPL",
    "gn:name":"Langjin",
    "gn:population":0,
    "gn:timezone":"Asia/Shanghai",
    "iso:country":"CN",
    "name:zho_x_preferred":[
        "\u6717\u9526"
    ],
    "wof:name":"Langjin",
    "wof:placetype":"locality"
},
  "geometry": {"coordinates":[112.59273,22.85431],"type":"Point"}
}