{
  "type": "Feature",
  "properties": {
    "gn:admin1_code":"3.0",
    "gn:asciiname":"Gongtang",
    "gn:country_code":"CN",
    "gn:dem":81,
    "gn:feature_class":"P",
    "gn:feature_code":"PPL",
    "gn:name":"Gongtang",
    "gn:population":0,
    "gn:timezone":"Asia/Shanghai",
    "iso:country":"CN",
    "name:und_x_variant":[
        "\u9f9a\u5858"
    ],
    "wof:name":"Gongtang",
    "wof:placetype":"locality"
},
  "geometry": {"coordinates":[114.84139,27.63457],"type":"Point"}
}