{
  "type": "Feature",
  "properties": {
    "gn:admin1_code":"14.0",
    "gn:asciiname":"Godog",
    "gn:country_code":"CN",
    "gn:dem":4462,
    "gn:feature_class":"P",
    "gn:feature_code":"PPL",
    "gn:name":"Godog",
    "gn:population":0,
    "gn:timezone":"Asia/Urumqi",
    "iso:country":"CN",
    "name:bod_x_preferred":[
        "Godog"
    ],
    "name:zho_x_preferred":[
        "Guoduo"
    ],
    "name:zho_x_variant":[
        "\u679c\u591a"
    ],
    "wof:name":"Godog",
    "wof:placetype":"locality"
},
  "geometry": {"coordinates":[97.10299999999999,31.503],"type":"Point"}
}