{
  "type": "Feature",
  "properties": {
    "gn:admin1_code":"32.0",
    "gn:asciiname":"Tiba",
    "gn:country_code":"CN",
    "gn:dem":3270,
    "gn:feature_class":"P",
    "gn:feature_code":"PPL",
    "gn:name":"Tiba",
    "gn:population":0,
    "gn:timezone":"Asia/Shanghai",
    "iso:country":"CN",
    "name:ceb_x_preferred":[
        "Tiba"
    ],
    "name:deu_x_preferred":[
        "Tiba"
    ],
    "name:swe_x_preferred":[
        "Tiba"
    ],
    "name:zho_x_preferred":[
        "\u63d0\u575d"
    ],
    "wof:name":"Tiba",
    "wof:placetype":"locality"
},
  "geometry": {"coordinates":[100.18008,30.87989],"type":"Point"}
}