{
  "type": "Feature",
  "properties": {
    "gn:admin1_code":"29.0",
    "gn:asciiname":"Gangouzhai",
    "gn:country_code":"CN",
    "gn:dem":2099,
    "gn:feature_class":"P",
    "gn:feature_code":"PPL",
    "gn:name":"Gangouzhai",
    "gn:population":0,
    "gn:timezone":"Asia/Shanghai",
    "iso:country":"CN",
    "name:zho_x_preferred":[
        "\u5e72\u6c9f\u5be8"
    ],
    "wof:name":"Gangouzhai",
    "wof:placetype":"locality"
},
  "geometry": {"coordinates":[99.8043,24.2429],"type":"Point"}
}