{
  "type": "Feature",
  "properties": {
    "gn:admin1_code":"10",
    "gn:asciiname":"Nanxintou",
    "gn:country_code":"CN",
    "gn:dem":45,
    "gn:feature_class":"P",
    "gn:feature_code":"PPL",
    "gn:name":"Nanxintou",
    "gn:population":0,
    "gn:timezone":"Asia/Shanghai",
    "iso:country":"CN",
    "name:und_x_variant":[
        "Nan-hsin-chuang",
        "Nanxinzhuang",
        "Nanxintou"
    ],
    "name:zho_x_preferred":[
        "\u5357\u8f9b\u5934"
    ],
    "wof:name":"Nanxintou",
    "wof:placetype":"locality"
},
  "geometry": {"coordinates":[115.2037,36.63136],"type":"Point"}
}