{
  "type": "Feature",
  "properties": {
    "gn:admin1_code":"15.0",
    "gn:asciiname":"Leitan",
    "gn:country_code":"CN",
    "gn:dem":2067,
    "gn:feature_class":"P",
    "gn:feature_code":"PPL",
    "gn:name":"Leitan",
    "gn:population":0,
    "gn:timezone":"Asia/Shanghai",
    "iso:country":"CN",
    "name:und_x_variant":[
        "\u78ca\u6ee9"
    ],
    "wof:name":"Leitan",
    "wof:placetype":"locality"
},
  "geometry": {"coordinates":[103.78547,35.00158],"type":"Point"}
}