{
  "type": "Feature",
  "properties": {
    "gn:admin1_code":"30.0",
    "gn:asciiname":"Dalingjiao",
    "gn:country_code":"CN",
    "gn:dem":268,
    "gn:feature_class":"P",
    "gn:feature_code":"PPL",
    "gn:name":"Dalingjiao",
    "gn:population":0,
    "gn:timezone":"Asia/Urumqi",
    "iso:country":"CN",
    "name:zho_x_preferred":[
        "\u5927\u5cad\u811a"
    ],
    "wof:name":"Dalingjiao",
    "wof:placetype":"locality"
},
  "geometry": {"coordinates":[111.00228,22.44753],"type":"Point"}
}