{
  "type": "Feature",
  "properties": {
    "gn:admin1_code":"18.0",
    "gn:asciiname":"Dahe",
    "gn:country_code":"CN",
    "gn:dem":931,
    "gn:feature_class":"P",
    "gn:feature_code":"PPL",
    "gn:name":"Dahe",
    "gn:population":0,
    "gn:timezone":"Asia/Shanghai",
    "iso:country":"CN",
    "name:ceb_x_preferred":[
        "Dahe"
    ],
    "name:deu_x_preferred":[
        "Dahe"
    ],
    "name:swe_x_preferred":[
        "Dahe"
    ],
    "name:zho_x_preferred":[
        "\u6253\u6cb3"
    ],
    "wof:name":"Dahe",
    "wof:placetype":"locality"
},
  "geometry": {"coordinates":[107.554,26.3859],"type":"Point"}
}