{
  "type": "Feature",
  "properties": {
    "gn:admin1_code":"33.0",
    "gn:asciiname":"Tanshu",
    "gn:country_code":"CN",
    "gn:dem":525,
    "gn:feature_class":"P",
    "gn:feature_code":"PPL",
    "gn:name":"Tanshu",
    "gn:population":0,
    "gn:timezone":"Asia/Shanghai",
    "iso:country":"CN",
    "name:zho_x_preferred":[
        "\u6a80\u6811"
    ],
    "wof:name":"Tanshu",
    "wof:placetype":"locality"
},
  "geometry": {"coordinates":[107.94593999999999,30.75927],"type":"Point"}
}