{
  "type": "Feature",
  "properties": {
    "gn:admin1_code":"14",
    "gn:asciiname":"Chega",
    "gn:country_code":"CN",
    "gn:dem":3985,
    "gn:feature_class":"P",
    "gn:feature_code":"PPL",
    "gn:name":"Chega",
    "gn:population":0,
    "gn:timezone":"Asia/Urumqi",
    "iso:country":"CN",
    "name:fas_x_preferred":[
        "\u0686\u06af\u0627"
    ],
    "name:msa_x_preferred":[
        "Chega"
    ],
    "name:zho_x_preferred":[
        "\u8f66\u560e"
    ],
    "wof:name":"Chega",
    "wof:placetype":"locality"
},
  "geometry": {"coordinates":[89.5331,28.9684],"type":"Point"}
}