{
  "type": "Feature",
  "properties": {
    "gn:admin1_code":"16.0",
    "gn:asciiname":"Nei'en",
    "gn:country_code":"CN",
    "gn:dem":246,
    "gn:feature_class":"P",
    "gn:feature_code":"PPL",
    "gn:name":"Nei\u2019en",
    "gn:population":0,
    "gn:timezone":"Asia/Shanghai",
    "iso:country":"CN",
    "name:und_x_variant":[
        "Nei\u2019en"
    ],
    "name:zho_x_preferred":[
        "\u5185\u6069"
    ],
    "wof:name":"Nei'en",
    "wof:placetype":"locality"
},
  "geometry": {"coordinates":[108.288,23.6603],"type":"Point"}
}