{
  "type": "Feature",
  "properties": {
    "gn:admin1_code":"25.0",
    "gn:asciiname":"Gaoguozhuang",
    "gn:country_code":"CN",
    "gn:dem":81,
    "gn:feature_class":"P",
    "gn:feature_code":"PPL",
    "gn:name":"Gaoguozhuang",
    "gn:population":0,
    "gn:timezone":"Asia/Shanghai",
    "iso:country":"CN",
    "name:zho_x_preferred":[
        "\u9ad8\u90ed\u5e84"
    ],
    "wof:name":"Gaoguozhuang",
    "wof:placetype":"locality"
},
  "geometry": {"coordinates":[120.05821,37.21317],"type":"Point"}
}