{
  "type": "Feature",
  "properties": {
    "gn:admin1_code":"11.0",
    "gn:asciiname":"Jingjiachong",
    "gn:country_code":"CN",
    "gn:dem":257,
    "gn:feature_class":"P",
    "gn:feature_code":"PPL",
    "gn:name":"Jingjiachong",
    "gn:population":0,
    "gn:timezone":"Asia/Shanghai",
    "iso:country":"CN",
    "name:zho_x_preferred":[
        "\u4e95\u5bb6\u51b2"
    ],
    "wof:name":"Jingjiachong",
    "wof:placetype":"locality"
},
  "geometry": {"coordinates":[111.67766,27.32096],"type":"Point"}
}