{
  "type": "Feature",
  "properties": {
    "gn:admin1_code":"4.0",
    "gn:asciiname":"Sunjiadun",
    "gn:country_code":"CN",
    "gn:dem":0,
    "gn:feature_class":"P",
    "gn:feature_code":"PPL",
    "gn:name":"Sunjiadun",
    "gn:population":0,
    "gn:timezone":"Asia/Shanghai",
    "iso:country":"CN",
    "name:zho_x_preferred":[
        "Sunjiadun"
    ],
    "name:zho_x_variant":[
        "\u5b59\u5bb6\u58a9"
    ],
    "wof:name":"Sunjiadun",
    "wof:placetype":"locality"
},
  "geometry": {"coordinates":[119.86503999999999,33.54482],"type":"Point"}
}