{
  "type": "Feature",
  "properties": {
    "gn:admin1_code":"12.0",
    "gn:asciiname":"Ruanjiapailou",
    "gn:country_code":"CN",
    "gn:dem":23,
    "gn:feature_class":"P",
    "gn:feature_code":"PPL",
    "gn:name":"Ruanjiapailou",
    "gn:population":0,
    "gn:timezone":"Asia/Shanghai",
    "iso:country":"CN",
    "name:zho_x_preferred":[
        "\u962e\u5bb6\u724c\u697c"
    ],
    "wof:name":"Ruanjiapailou",
    "wof:placetype":"locality"
},
  "geometry": {"coordinates":[114.41831000000001,30.82264],"type":"Point"}
}