{
  "type": "Feature",
  "properties": {
    "gn:admin1_code":"8.0",
    "gn:asciiname":"Goujiadian",
    "gn:country_code":"CN",
    "gn:dem":250,
    "gn:feature_class":"P",
    "gn:feature_code":"PPL",
    "gn:name":"Goujiadian",
    "gn:population":0,
    "gn:timezone":"Asia/Shanghai",
    "iso:country":"CN",
    "name:zho_x_preferred":[
        "\u52fe\u5bb6\u5e97"
    ],
    "wof:name":"Goujiadian",
    "wof:placetype":"locality"
},
  "geometry": {"coordinates":[127.38873,47.59574],"type":"Point"}
}