{
  "type": "Feature",
  "properties": {
    "gn:admin1_code":"2.0",
    "gn:asciiname":"Qiandaodi",
    "gn:country_code":"CN",
    "gn:dem":102,
    "gn:feature_class":"P",
    "gn:feature_code":"PPL",
    "gn:name":"Qiandaodi",
    "gn:population":0,
    "gn:timezone":"Asia/Shanghai",
    "iso:country":"CN",
    "name:zho_x_preferred":[
        "\u524d\u9053\u5730"
    ],
    "wof:name":"Qiandaodi",
    "wof:placetype":"locality"
},
  "geometry": {"coordinates":[120.06032999999999,29.66447],"type":"Point"}
}