{
  "type": "Feature",
  "properties": {
    "gn:admin1_code":"8.0",
    "gn:asciiname":"Gelidian",
    "gn:country_code":"CN",
    "gn:dem":143,
    "gn:feature_class":"P",
    "gn:feature_code":"PPL",
    "gn:name":"Gelidian",
    "gn:population":0,
    "gn:timezone":"Asia/Shanghai",
    "iso:country":"CN",
    "name:zho_x_preferred":[
        "\u9694\u79bb\u70b9"
    ],
    "wof:name":"Gelidian",
    "wof:placetype":"locality"
},
  "geometry": {"coordinates":[124.54893,46.67735],"type":"Point"}
}