{
  "type": "Feature",
  "properties": {
    "gn:admin1_code":"4.0",
    "gn:asciiname":"Shannan",
    "gn:country_code":"CN",
    "gn:dem":11,
    "gn:feature_class":"P",
    "gn:feature_code":"PPL",
    "gn:name":"Shannan",
    "gn:population":0,
    "gn:timezone":"Asia/Shanghai",
    "iso:country":"CN",
    "name:kor_x_preferred":[
        "\uc0b0\ub09c"
    ],
    "name:und_x_variant":[
        "\u5c71\u5357"
    ],
    "wof:name":"Shannan",
    "wof:placetype":"locality"
},
  "geometry": {"coordinates":[118.95004,32.07335],"type":"Point"}
}