{
  "type": "Feature",
  "properties": {
    "gn:admin1_code":"2",
    "gn:asciiname":"Dashuxia",
    "gn:country_code":"CN",
    "gn:dem":46,
    "gn:feature_class":"P",
    "gn:feature_code":"PPL",
    "gn:name":"Dashuxia",
    "gn:population":0,
    "gn:timezone":"Asia/Shanghai",
    "iso:country":"CN",
    "name:und_x_variant":[
        "\u5927\u6811\u4e0b",
        "Dashuxia"
    ],
    "wof:name":"Dashuxia",
    "wof:placetype":"locality"
},
  "geometry": {"coordinates":[119.84935,29.98832],"type":"Point"}
}