{
  "type": "Feature",
  "properties": {
    "gn:admin1_code":"1.0",
    "gn:asciiname":"Jiangzhuang",
    "gn:country_code":"CN",
    "gn:dem":223,
    "gn:feature_class":"P",
    "gn:feature_code":"PPL",
    "gn:name":"Jiangzhuang",
    "gn:population":0,
    "gn:timezone":"Asia/Shanghai",
    "iso:country":"CN",
    "wof:name":"Jiangzhuang",
    "wof:placetype":"locality"
},
  "geometry": {"coordinates":[116.65000000000001,30.84444],"type":"Point"}
}