{
  "type": "Feature",
  "properties": {
    "gn:admin1_code":"15.0",
    "gn:asciiname":"Xujiabu",
    "gn:country_code":"CN",
    "gn:dem":2051,
    "gn:feature_class":"P",
    "gn:feature_code":"PPL",
    "gn:name":"Xujiabu",
    "gn:population":0,
    "gn:timezone":"Asia/Shanghai",
    "iso:country":"CN",
    "name:zho_x_preferred":[
        "\u5f90\u5bb6\u5821"
    ],
    "wof:name":"Xujiabu",
    "wof:placetype":"locality"
},
  "geometry": {"coordinates":[104.34399999999999,35.071],"type":"Point"}
}