{
  "type": "Feature",
  "properties": {
    "gn:admin1_code":"2.0",
    "gn:asciiname":"Yeshan",
    "gn:country_code":"CN",
    "gn:dem":464,
    "gn:feature_class":"P",
    "gn:feature_code":"PPL",
    "gn:name":"Yeshan",
    "gn:population":0,
    "gn:timezone":"Asia/Shanghai",
    "iso:country":"CN",
    "name:und_x_variant":[
        "\u53f6\u5c71",
        "Yeshan"
    ],
    "wof:name":"Yeshan",
    "wof:placetype":"locality"
},
  "geometry": {"coordinates":[119.88547,27.75829],"type":"Point"}
}