{
  "type": "Feature",
  "properties": {
    "gn:admin1_code":"29",
    "gn:asciiname":"Bainike",
    "gn:country_code":"CN",
    "gn:dem":1259,
    "gn:feature_class":"P",
    "gn:feature_code":"PPL",
    "gn:name":"Bainike",
    "gn:population":0,
    "gn:timezone":"Asia/Shanghai",
    "iso:country":"CN",
    "name:zho_x_preferred":[
        "\u767d\u5c3c\u514b"
    ],
    "wof:name":"Bainike",
    "wof:placetype":"locality"
},
  "geometry": {"coordinates":[101.84,23.9671],"type":"Point"}
}