{
  "type": "Feature",
  "properties": {
    "gn:admin1_code":"29.0",
    "gn:asciiname":"Mang'e",
    "gn:country_code":"CN",
    "gn:dem":1689,
    "gn:feature_class":"P",
    "gn:feature_code":"PPL",
    "gn:name":"Mang\u2019e",
    "gn:population":0,
    "gn:timezone":"Asia/Shanghai",
    "iso:country":"CN",
    "name:und_x_variant":[
        "Mang\u2019e"
    ],
    "name:zho_x_preferred":[
        "\u5fd9\u5ce8"
    ],
    "wof:name":"Mang'e",
    "wof:placetype":"locality"
},
  "geometry": {"coordinates":[99.9693,24.0994],"type":"Point"}
}