{
  "type": "Feature",
  "properties": {
    "gn:admin1_code":"29",
    "gn:asciiname":"Baoliangjie",
    "gn:country_code":"CN",
    "gn:dem":1154,
    "gn:feature_class":"P",
    "gn:feature_code":"PPL",
    "gn:name":"Baoliangjie",
    "gn:population":0,
    "gn:timezone":"Asia/Shanghai",
    "iso:country":"CN",
    "name:zho_x_preferred":[
        "\u4fdd\u6881\u8857"
    ],
    "wof:name":"Baoliangjie",
    "wof:placetype":"locality"
},
  "geometry": {"coordinates":[104.617,22.8729],"type":"Point"}
}