{
  "type": "Feature",
  "properties": {
    "gn:admin1_code":"19.0",
    "gn:asciiname":"Wanpu",
    "gn:country_code":"CN",
    "gn:dem":454,
    "gn:feature_class":"P",
    "gn:feature_code":"PPL",
    "gn:name":"Wanpu",
    "gn:population":0,
    "gn:timezone":"Asia/Shanghai",
    "iso:country":"CN",
    "name:und_x_variant":[
        "\u7897\u94fa"
    ],
    "name:zho_x_preferred":[
        "\u7897\u94fa"
    ],
    "wof:name":"Wanpu",
    "wof:placetype":"locality"
},
  "geometry": {"coordinates":[124.92373000000001,41.53247],"type":"Point"}
}