{
  "type": "Feature",
  "properties": {
    "gn:admin1_code":"13.0",
    "gn:asciiname":"Segezi Wenku'er",
    "gn:country_code":"CN",
    "gn:dem":2005,
    "gn:feature_class":"P",
    "gn:feature_code":"PPL",
    "gn:name":"Segezi Wenku\u2019er",
    "gn:population":0,
    "gn:timezone":"Asia/Shanghai",
    "iso:country":"CN",
    "name:und_x_variant":[
        "Segezi Wenku\u2019er"
    ],
    "name:zho_x_preferred":[
        "\u8272\u683c\u5b50\u6e29\u5e93\u5c14"
    ],
    "wof:name":"Segezi Wenku'er",
    "wof:placetype":"locality"
},
  "geometry": {"coordinates":[81.70938000000002,36.44789],"type":"Point"}
}