{
  "type": "Feature",
  "properties": {
    "gn:admin1_code":"11.0",
    "gn:asciiname":"Taohua",
    "gn:country_code":"CN",
    "gn:dem":67,
    "gn:feature_class":"P",
    "gn:feature_code":"PPL",
    "gn:name":"Taohua",
    "gn:population":0,
    "gn:timezone":"Asia/Shanghai",
    "iso:country":"CN",
    "name:ceb_x_preferred":[
        "Taohua"
    ],
    "name:swe_x_preferred":[
        "Taohua"
    ],
    "name:zho_x_preferred":[
        "\u6843\u82b1"
    ],
    "name:zho_x_variant":[
        "\u6843\u82b1\u9547"
    ],
    "wof:name":"Taohua",
    "wof:placetype":"locality"
},
  "geometry": {"coordinates":[113.01779999999999,28.09413],"type":"Point"}
}