{
  "type": "Feature",
  "properties": {
    "gn:admin1_code":"9.0",
    "gn:asciiname":"Tongjiawa",
    "gn:country_code":"CN",
    "gn:dem":368,
    "gn:feature_class":"P",
    "gn:feature_code":"PPL",
    "gn:name":"Tongjiawa",
    "gn:population":0,
    "gn:timezone":"Asia/Shanghai",
    "iso:country":"CN",
    "name:und_x_variant":[
        "\u4edd\u5bb6\u6d3c",
        "Tongjiawa"
    ],
    "wof:name":"Tongjiawa",
    "wof:placetype":"locality"
},
  "geometry": {"coordinates":[112.20701,33.12826],"type":"Point"}
}