{
  "type": "Feature",
  "properties": {
    "gn:admin1_code":"25",
    "gn:asciiname":"Zhizhuang",
    "gn:country_code":"CN",
    "gn:dem":58,
    "gn:feature_class":"P",
    "gn:feature_code":"PPL",
    "gn:name":"Zhizhuang",
    "gn:population":0,
    "gn:timezone":"Asia/Shanghai",
    "iso:country":"CN",
    "name:zho_x_preferred":[
        "\u90c5\u5e84"
    ],
    "wof:name":"Zhizhuang",
    "wof:placetype":"locality"
},
  "geometry": {"coordinates":[115.35299999999999,35.4086],"type":"Point"}
}