{
  "type": "Feature",
  "properties": {
    "gn:admin1_code":"9.0",
    "gn:asciiname":"Shiziling",
    "gn:country_code":"CN",
    "gn:dem":457,
    "gn:feature_class":"P",
    "gn:feature_code":"PPL",
    "gn:name":"Shiziling",
    "gn:population":0,
    "gn:timezone":"Asia/Shanghai",
    "iso:country":"CN",
    "name:zho_x_preferred":[
        "\u5341\u5b57\u5cad"
    ],
    "wof:name":"Shiziling",
    "wof:placetype":"locality"
},
  "geometry": {"coordinates":[112.14055999999999,34.41605999999999],"type":"Point"}
}