{
  "type": "Feature",
  "properties": {
    "gn:admin1_code":"26.0",
    "gn:asciiname":"Yuziwan",
    "gn:country_code":"CN",
    "gn:dem":1266,
    "gn:feature_class":"P",
    "gn:feature_code":"PPL",
    "gn:name":"Yuziwan",
    "gn:population":0,
    "gn:timezone":"Asia/Shanghai",
    "iso:country":"CN",
    "name:zho_x_preferred":[
        "\u828b\u5b50\u6e7e"
    ],
    "wof:name":"Yuziwan",
    "wof:placetype":"locality"
},
  "geometry": {"coordinates":[108.9676,36.49851],"type":"Point"}
}