{
  "type": "Feature",
  "properties": {
    "gn:admin1_code":"2",
    "gn:asciiname":"Banshanyuan",
    "gn:country_code":"CN",
    "gn:dem":822,
    "gn:feature_class":"P",
    "gn:feature_code":"PPL",
    "gn:name":"Banshanyuan",
    "gn:population":0,
    "gn:timezone":"Asia/Shanghai",
    "iso:country":"CN",
    "name:zho_x_preferred":[
        "\u534a\u5c71\u6e90"
    ],
    "wof:name":"Banshanyuan",
    "wof:placetype":"locality"
},
  "geometry": {"coordinates":[119.24611000000002,27.70417],"type":"Point"}
}