{
  "type": "Feature",
  "properties": {
    "gn:admin1_code":"8.0",
    "gn:asciiname":"Shangsanyangcun",
    "gn:country_code":"CN",
    "gn:dem":329,
    "gn:feature_class":"P",
    "gn:feature_code":"PPL",
    "gn:name":"Shangsanyangcun",
    "gn:population":0,
    "gn:timezone":"Asia/Shanghai",
    "iso:country":"CN",
    "name:zho_x_preferred":[
        "\u4e0a\u4e09\u9633\u6751"
    ],
    "wof:name":"Shangsanyangcun",
    "wof:placetype":"locality"
},
  "geometry": {"coordinates":[130.29023000000001,45.15181],"type":"Point"}
}