{
  "type": "Feature",
  "properties": {
    "gn:admin1_code":"24.0",
    "gn:asciiname":"Yuanjiazhuangcun",
    "gn:country_code":"CN",
    "gn:dem":381,
    "gn:feature_class":"P",
    "gn:feature_code":"PPL",
    "gn:name":"Yuanjiazhuangcun",
    "gn:population":0,
    "gn:timezone":"Asia/Shanghai",
    "iso:country":"CN",
    "name:zho_x_preferred":[
        "\u8881\u5bb6\u5e84\u6751"
    ],
    "wof:name":"Yuanjiazhuangcun",
    "wof:placetype":"locality"
},
  "geometry": {"coordinates":[110.87835,35.02709],"type":"Point"}
}