{
  "type": "Feature",
  "properties": {
    "gn:admin1_code":"2.0",
    "gn:asciiname":"Fengshuikeng",
    "gn:country_code":"CN",
    "gn:dem":162,
    "gn:feature_class":"P",
    "gn:feature_code":"PPL",
    "gn:name":"Fengshuikeng",
    "gn:population":0,
    "gn:timezone":"Asia/Shanghai",
    "iso:country":"CN",
    "name:zho_x_preferred":[
        "\u67ab\u6c34\u5751"
    ],
    "wof:name":"Fengshuikeng",
    "wof:placetype":"locality"
},
  "geometry": {"coordinates":[121.19983000000001,28.13085],"type":"Point"}
}