{
  "type": "Feature",
  "properties": {
    "gn:admin1_code":"15.0",
    "gn:asciiname":"Manping",
    "gn:country_code":"CN",
    "gn:dem":1288,
    "gn:feature_class":"P",
    "gn:feature_code":"PPL",
    "gn:name":"Manping",
    "gn:population":0,
    "gn:timezone":"Asia/Shanghai",
    "iso:country":"CN",
    "name:und_x_variant":[
        "\u5881\u576a"
    ],
    "wof:name":"Manping",
    "wof:placetype":"locality"
},
  "geometry": {"coordinates":[105.87333999999998,33.72264000000001],"type":"Point"}
}