{
  "type": "Feature",
  "properties": {
    "gn:admin1_code":"5.0",
    "gn:asciiname":"Changcai",
    "gn:country_code":"CN",
    "gn:dem":363,
    "gn:feature_class":"P",
    "gn:feature_code":"PPL",
    "gn:name":"Changcai",
    "gn:population":0,
    "gn:timezone":"Asia/Shanghai",
    "iso:country":"CN",
    "name:und_x_variant":[
        "\u957f\u8d22"
    ],
    "wof:name":"Changcai",
    "wof:placetype":"locality"
},
  "geometry": {"coordinates":[129.52833999999999,42.67967],"type":"Point"}
}