{
  "type": "Feature",
  "properties": {
    "gn:admin1_code":"4.0",
    "gn:asciiname":"Zhuanqiang",
    "gn:country_code":"CN",
    "gn:dem":8,
    "gn:feature_class":"P",
    "gn:feature_code":"PPLA4",
    "gn:name":"Zhuanqiang",
    "gn:population":0,
    "gn:timezone":"Asia/Shanghai",
    "iso:country":"CN",
    "name:und_x_variant":[
        "Chuan-ch\u2019iang",
        "Zhuanqiang Zhen",
        "\u7816\u5899\u9547",
        "Zhuanqiang"
    ],
    "name:zho_x_preferred":[
        "\u7816\u5899"
    ],
    "wof:name":"Zhuanqiang",
    "wof:placetype":"locality"
},
  "geometry": {"coordinates":[118.81762999999999,31.26317],"type":"Point"}
}