{
  "type": "Feature",
  "properties": {
    "gn:admin1_code":"18.0",
    "gn:asciiname":"Daijiazhai",
    "gn:country_code":"CN",
    "gn:dem":802,
    "gn:feature_class":"P",
    "gn:feature_code":"PPL",
    "gn:name":"Daijiazhai",
    "gn:population":0,
    "gn:timezone":"Asia/Shanghai",
    "iso:country":"CN",
    "name:zho_x_preferred":[
        "\u6234\u5bb6\u5be8"
    ],
    "wof:name":"Daijiazhai",
    "wof:placetype":"locality"
},
  "geometry": {"coordinates":[108.46899999999999,27.5184],"type":"Point"}
}