{
  "type": "Feature",
  "properties": {
    "gn:admin1_code":"16.0",
    "gn:asciiname":"Zi'e",
    "gn:country_code":"CN",
    "gn:dem":178,
    "gn:feature_class":"P",
    "gn:feature_code":"PPL",
    "gn:name":"Zi\u2019e",
    "gn:population":0,
    "gn:timezone":"Asia/Shanghai",
    "iso:country":"CN",
    "name:und_x_variant":[
        "Zi\u2019e"
    ],
    "name:zho_x_preferred":[
        "\u81ea\u989d"
    ],
    "wof:name":"Zi'e",
    "wof:placetype":"locality"
},
  "geometry": {"coordinates":[109.613,25.3084],"type":"Point"}
}