{
  "type": "Feature",
  "properties": {
    "gn:admin1_code":"33.0",
    "gn:asciiname":"Tangjiazui",
    "gn:country_code":"CN",
    "gn:dem":592,
    "gn:feature_class":"P",
    "gn:feature_code":"PPL",
    "gn:name":"Tangjiazui",
    "gn:population":0,
    "gn:timezone":"Asia/Shanghai",
    "iso:country":"CN",
    "name:zho_x_preferred":[
        "\u6c64\u5bb6\u5480"
    ],
    "wof:name":"Tangjiazui",
    "wof:placetype":"locality"
},
  "geometry": {"coordinates":[106.42655000000001,28.86055],"type":"Point"}
}