{
  "type": "Feature",
  "properties": {
    "gn:admin1_code":"15.0",
    "gn:asciiname":"Zhenzhu",
    "gn:country_code":"CN",
    "gn:dem":1668,
    "gn:feature_class":"P",
    "gn:feature_code":"PPL",
    "gn:name":"Zhenzhu",
    "gn:population":0,
    "gn:timezone":"Asia/Shanghai",
    "iso:country":"CN",
    "name:zho_x_preferred":[
        "\u73cd\u73e0"
    ],
    "wof:name":"Zhenzhu",
    "wof:placetype":"locality"
},
  "geometry": {"coordinates":[105.637,34.1422],"type":"Point"}
}