{
  "type": "Feature",
  "properties": {
    "gn:admin1_code":"25",
    "gn:asciiname":"Huduoluo",
    "gn:country_code":"CN",
    "gn:dem":412,
    "gn:feature_class":"P",
    "gn:feature_code":"PPL",
    "gn:name":"Huduoluo",
    "gn:population":0,
    "gn:timezone":"Asia/Shanghai",
    "iso:country":"CN",
    "name:zho_x_preferred":[
        "\u80e1\u591a\u7f57"
    ],
    "wof:name":"Huduoluo",
    "wof:placetype":"locality"
},
  "geometry": {"coordinates":[117.48399999999999,36.4853],"type":"Point"}
}