{
  "type": "Feature",
  "properties": {
    "gn:admin1_code":"7.0",
    "gn:asciiname":"Jingtong",
    "gn:country_code":"CN",
    "gn:dem":255,
    "gn:feature_class":"P",
    "gn:feature_code":"PPL",
    "gn:name":"Jingtong",
    "gn:population":0,
    "gn:timezone":"Asia/Shanghai",
    "iso:country":"CN",
    "name:ita_x_preferred":[
        "Jingtong"
    ],
    "name:und_x_variant":[
        "\u7ecf\u901a"
    ],
    "name:zho_x_preferred":[
        "\u7ecf\u901a"
    ],
    "wof:name":"Jingtong",
    "wof:placetype":"locality"
},
  "geometry": {"coordinates":[118.22508999999999,26.24043],"type":"Point"}
}