{
  "type": "Feature",
  "properties": {
    "gn:admin1_code":"3.0",
    "gn:asciiname":"Jiangbachang",
    "gn:country_code":"CN",
    "gn:dem":404,
    "gn:feature_class":"P",
    "gn:feature_code":"PPL",
    "gn:name":"Jiangbachang",
    "gn:population":0,
    "gn:timezone":"Asia/Shanghai",
    "iso:country":"CN",
    "name:und_x_variant":[
        "\u6c5f\u575d\u573a"
    ],
    "wof:name":"Jiangbachang",
    "wof:placetype":"locality"
},
  "geometry": {"coordinates":[116.28731000000001,26.60411],"type":"Point"}
}