{
  "type": "Feature",
  "properties": {
    "gn:admin1_code":"16.0",
    "gn:asciiname":"Dayuanjin",
    "gn:country_code":"CN",
    "gn:dem":623,
    "gn:feature_class":"P",
    "gn:feature_code":"PPL",
    "gn:name":"Dayuanjin",
    "gn:population":0,
    "gn:timezone":"Asia/Shanghai",
    "iso:country":"CN",
    "name:zho_x_preferred":[
        "\u5927\u5143\u91d1"
    ],
    "wof:name":"Dayuanjin",
    "wof:placetype":"locality"
},
  "geometry": {"coordinates":[111.83199999999999,24.7651],"type":"Point"}
}