{
  "type": "Feature",
  "properties": {
    "gn:admin1_code":"8.0",
    "gn:asciiname":"Xinyingcun",
    "gn:country_code":"CN",
    "gn:dem":178,
    "gn:feature_class":"P",
    "gn:feature_code":"PPL",
    "gn:name":"Xinyingcun",
    "gn:population":0,
    "gn:timezone":"Asia/Shanghai",
    "iso:country":"CN",
    "name:zho_x_preferred":[
        "\u65b0\u82f1\u6751"
    ],
    "wof:name":"Xinyingcun",
    "wof:placetype":"locality"
},
  "geometry": {"coordinates":[126.46459,45.49942],"type":"Point"}
}