{
  "type": "Feature",
  "properties": {
    "gn:admin1_code":"31",
    "gn:asciiname":"Dantang",
    "gn:country_code":"CN",
    "gn:dem":27,
    "gn:feature_class":"P",
    "gn:feature_code":"PPL",
    "gn:name":"Dantang",
    "gn:population":0,
    "gn:timezone":"Asia/Shanghai",
    "iso:country":"CN",
    "name:und_x_variant":[
        "\u4e39\u5858"
    ],
    "wof:name":"Dantang",
    "wof:placetype":"locality"
},
  "geometry": {"coordinates":[110.94499999999999,19.9601],"type":"Point"}
}