{
  "type": "Feature",
  "properties": {
    "gn:admin1_code":"15.0",
    "gn:asciiname":"Wujiatai",
    "gn:country_code":"CN",
    "gn:dem":1413,
    "gn:feature_class":"P",
    "gn:feature_code":"PPL",
    "gn:name":"Wujiatai",
    "gn:population":0,
    "gn:timezone":"Asia/Shanghai",
    "iso:country":"CN",
    "name:und_x_variant":[
        "\u6b66\u5bb6\u53f0"
    ],
    "wof:name":"Wujiatai",
    "wof:placetype":"locality"
},
  "geometry": {"coordinates":[107.6784,36.54749],"type":"Point"}
}