{
  "type": "Feature",
  "properties": {
    "gn:admin1_code":"11",
    "gn:asciiname":"Chuanyan",
    "gn:cc2":"CN",
    "gn:country_code":"CN",
    "gn:dem":214,
    "gn:feature_class":"P",
    "gn:feature_code":"PPL",
    "gn:name":"Chuanyan",
    "gn:population":0,
    "gn:timezone":"Asia/Shanghai",
    "iso:country":"CN",
    "name:und_x_variant":[
        "Heshi",
        "Chuanyan"
    ],
    "wof:name":"Chuanyan",
    "wof:placetype":"locality"
},
  "geometry": {"coordinates":[111.34472,26.44694],"type":"Point"}
}