{
  "type": "Feature",
  "properties": {
    "gn:admin1_code":"11.0",
    "gn:asciiname":"Dingpengwan",
    "gn:country_code":"CN",
    "gn:dem":566,
    "gn:feature_class":"P",
    "gn:feature_code":"PPL",
    "gn:name":"Dingpengwan",
    "gn:population":0,
    "gn:timezone":"Asia/Shanghai",
    "iso:country":"CN",
    "name:zho_x_preferred":[
        "\u815a\u68da\u6e7e"
    ],
    "wof:name":"Dingpengwan",
    "wof:placetype":"locality"
},
  "geometry": {"coordinates":[109.81292000000001,29.51364],"type":"Point"}
}