{
  "type": "Feature",
  "properties": {
    "gn:admin1_code":"11.0",
    "gn:asciiname":"Jinzhushi",
    "gn:country_code":"CN",
    "gn:dem":420,
    "gn:feature_class":"P",
    "gn:feature_code":"PPL",
    "gn:name":"Jinzhushi",
    "gn:population":0,
    "gn:timezone":"Asia/Shanghai",
    "iso:country":"CN",
    "name:zho_x_preferred":[
        "\u91d1\u73e0\u77f3"
    ],
    "wof:name":"Jinzhushi",
    "wof:placetype":"locality"
},
  "geometry": {"coordinates":[111.44711,27.07705],"type":"Point"}
}