{
  "type": "Feature",
  "properties": {
    "gn:admin1_code":"32.0",
    "gn:asciiname":"Yulong",
    "gn:country_code":"CN",
    "gn:dem":1500,
    "gn:feature_class":"P",
    "gn:feature_code":"PPL",
    "gn:name":"Yulong",
    "gn:population":0,
    "gn:timezone":"Asia/Shanghai",
    "iso:country":"CN",
    "name:ceb_x_preferred":[
        "Yulong"
    ],
    "name:deu_x_preferred":[
        "Yulong"
    ],
    "name:ita_x_preferred":[
        "Yulong"
    ],
    "name:nld_x_preferred":[
        "Yulong"
    ],
    "name:vie_x_preferred":[
        "Yulong"
    ],
    "name:zho_x_preferred":[
        "\u88d5\u9686"
    ],
    "wof:name":"Yulong",
    "wof:placetype":"locality"
},
  "geometry": {"coordinates":[102.16858999999999,27.83785],"type":"Point"}
}