{
  "type": "Feature",
  "properties": {
    "gn:admin1_code":"4.0",
    "gn:asciiname":"Damaozhuang",
    "gn:country_code":"CN",
    "gn:dem":2,
    "gn:feature_class":"P",
    "gn:feature_code":"PPL",
    "gn:name":"Damaozhuang",
    "gn:population":0,
    "gn:timezone":"Asia/Shanghai",
    "iso:country":"CN",
    "name:zho_x_preferred":[
        "Damaozhuang"
    ],
    "name:zho_x_variant":[
        "\u5927\u8306\u5e84"
    ],
    "wof:name":"Damaozhuang",
    "wof:placetype":"locality"
},
  "geometry": {"coordinates":[119.19711,34.4436],"type":"Point"}
}