{
  "type": "Feature",
  "properties": {
    "gn:country":"CN",
    "gn:fcode":"PPLA3",
    "gn:pop":0,
    "iso:country":"CN",
    "name:unk_x_variant":[
        "Fufyn"
    ],
    "qs:name":"\u6276\u98ce\u53bf",
    "qs:name_adm0":"\u4e2d\u570b",
    "qs:name_adm1":"\u965d\u897f\u7701",
    "qs:photos":29,
    "qs:photos_1k":6,
    "qs:photos_9k":1,
    "qs:photos_9r":2,
    "qs:photos_all":29,
    "qs:photos_sr":2,
    "qs:placetype":"LocalAdmin",
    "qs:pop_sr":"5",
    "wd:wordcount":96,
    "wof:name":"\u6276\u98ce\u53bf",
    "wof:placetype":"localadmin",
    "wof:population":0
},
  "geometry": {"coordinates":[107.87348,34.3605],"type":"Point"}
}