{
  "type": "Feature",
  "properties": {
    "gn:country":"CN",
    "gn:fcode":"PPLA3",
    "gn:pop":0,
    "iso:country":"CN",
    "name:ara_x_preferred":[
        "\u0645\u0642\u0627\u0637\u0639\u0629 \u0641\u0648\u0641\u0646\u063a"
    ],
    "name:ben_x_preferred":[
        "\u09ab\u09c1\u09ab\u09c7\u0982 \u0995\u09be\u0989\u09a8\u09cd\u099f\u09bf"
    ],
    "name:ceb_x_preferred":[
        "Fufeng Xian"
    ],
    "name:dan_x_preferred":[
        "Fufeng County"
    ],
    "name:deu_x_preferred":[
        "Fufeng"
    ],
    "name:ell_x_preferred":[
        "\u03a6\u03bf\u03c5\u03c6\u03ad\u03bd\u03b3\u03ba"
    ],
    "name:eng_x_preferred":[
        "Fufeng County"
    ],
    "name:fas_x_preferred":[
        "\u0634\u0647\u0631\u0633\u062a\u0627\u0646 \u0641\u0648\u0641\u0646\u06af"
    ],
    "name:fin_x_preferred":[
        "Fufengin kunta"
    ],
    "name:gan_x_preferred":[
        "\u6276\u98ce\u53bf"
    ],
    "name:guj_x_preferred":[
        "\u0aab\u0ac1\u0aab\u0ac7\u0a82\u0a97 \u0a95\u0abe\u0a89\u0aa8\u0acd\u0a9f\u0ac0"
    ],
    "name:hin_x_preferred":[
        "\u092b\u094d\u092f\u0942\u092b\u0947\u0902\u0917 \u0915\u093e\u0909\u0902\u091f\u0940"
    ],
    "name:hye_x_preferred":[
        "\u0556\u0578\u0582\u0586\u0565\u0576"
    ],
    "name:ind_x_preferred":[
        "Fufeng County"
    ],
    "name:jpn_x_preferred":[
        "\u6276\u98a8\u770c"
    ],
    "name:kan_x_preferred":[
        "\u0cab\u0cc1\u0cab\u0cc6\u0c82\u0c97\u0ccd \u0c95\u0ccc\u0c82\u0c9f\u0cbf"
    ],
    "name:kor_x_preferred":[
        "\ud478\ud391\ud604"
    ],
    "name:lav_x_preferred":[
        "Fufenga"
    ],
    "name:lit_x_preferred":[
        "Fufengas"
    ],
    "name:mar_x_preferred":[
        "\u092b\u0942\u092b\u0947\u0902\u0917 \u0915\u093e\u0909\u0902\u091f\u0940"
    ],
    "name:msa_x_preferred":[
        "Fufeng County"
    ],
    "name:nan_x_preferred":[
        "H\u00fb-hong-ko\u0101n"
    ],
    "name:nld_x_preferred":[
        "Fufeng"
    ],
    "name:nob_x_preferred":[
        "Fufeng"
    ],
    "name:pol_x_preferred":[
        "Powiat Fufeng"
    ],
    "name:rus_x_preferred":[
        "\u0424\u0443\u0444\u044d\u043d"
    ],
    "name:swe_x_preferred":[
        "Fufeng"
    ],
    "name:tel_x_preferred":[
        "\u0c2b\u0c4d\u0c2f\u0c42\u0c2b\u0c46\u0c02\u0c17\u0c4d \u0c15\u0c4c\u0c02\u0c1f\u0c40"
    ],
    "name:tha_x_preferred":[
        "\u0e1d\u0e39\u0e40\u0e1f\u0e34\u0e07 \u0e04\u0e31\u0e19\u0e17\u0e23\u0e35\u0e48"
    ],
    "name:tur_x_preferred":[
        "Fufengy Country"
    ],
    "name:ukr_x_preferred":[
        "\u0424\u0443\u0444\u0435\u043d"
    ],
    "name:unk_x_variant":[
        "Fufyn"
    ],
    "name:urd_x_preferred":[
        "\u0641\u0648\u0641\u06cc\u0646\u062c \u06a9\u0627\u0624\u0646\u0679\u06cc"
    ],
    "name:vie_x_preferred":[
        "Ph\u00f9 Phong"
    ],
    "name:wuu_x_preferred":[
        "\u6276\u98ce\u53bf"
    ],
    "name:yue_x_preferred":[
        "\u6276\u98a8"
    ],
    "name:zho_x_preferred":[
        "\u6276\u98ce\u53bf"
    ],
    "qs:name":"\u6276\u98ce\u53bf",
    "qs:name_adm0":"\u4e2d\u570b",
    "qs:name_adm1":"\u965d\u897f\u7701",
    "qs:photos":29,
    "qs:photos_1k":6,
    "qs:photos_9k":1,
    "qs:photos_9r":2,
    "qs:photos_all":29,
    "qs:photos_sr":2,
    "qs:placetype":"LocalAdmin",
    "qs:pop_sr":"5",
    "wd:wordcount":96,
    "wof:name":"\u6276\u98ce\u53bf",
    "wof:placetype":"localadmin",
    "wof:population":0
},
  "geometry": {"coordinates":[107.87348,34.3605],"type":"Point"}
}