{
  "type": "Feature",
  "properties": {
    "gn:admin1_code":"26.0",
    "gn:asciiname":"Tangligou",
    "gn:country_code":"CN",
    "gn:dem":867,
    "gn:feature_class":"P",
    "gn:feature_code":"PPL",
    "gn:name":"Tangligou",
    "gn:population":0,
    "gn:timezone":"Asia/Shanghai",
    "iso:country":"CN",
    "name:und_x_variant":[
        "\u5510\u7281\u6c9f"
    ],
    "wof:name":"Tangligou",
    "wof:placetype":"locality"
},
  "geometry": {"coordinates":[107.88623,33.23441],"type":"Point"}
}