{
  "type": "Feature",
  "properties": {
    "gn:admin1_code":"18",
    "gn:asciiname":"Hejiawan",
    "gn:country_code":"CN",
    "gn:dem":861,
    "gn:feature_class":"P",
    "gn:feature_code":"PPL",
    "gn:name":"Hejiawan",
    "gn:population":0,
    "gn:timezone":"Asia/Shanghai",
    "iso:country":"CN",
    "name:zho_x_preferred":[
        "\u8d3a\u5bb6\u6e7e"
    ],
    "wof:name":"Hejiawan",
    "wof:placetype":"locality"
},
  "geometry": {"coordinates":[106.752,27.5405],"type":"Point"}
}