{
  "type": "Feature",
  "properties": {
    "gn:admin1_code":"26.0",
    "gn:asciiname":"Zhaojiahe",
    "gn:country_code":"CN",
    "gn:dem":1031,
    "gn:feature_class":"P",
    "gn:feature_code":"PPL",
    "gn:name":"Zhaojiahe",
    "gn:population":0,
    "gn:timezone":"Asia/Shanghai",
    "iso:country":"CN",
    "name:und_x_variant":[
        "\u8d75\u5bb6\u6cb3"
    ],
    "wof:name":"Zhaojiahe",
    "wof:placetype":"locality"
},
  "geometry": {"coordinates":[107.92243000000001,34.71148],"type":"Point"}
}