{
  "type": "Feature",
  "properties": {
    "gn:admin1_code":"15.0",
    "gn:asciiname":"Wangjia Taizi",
    "gn:country_code":"CN",
    "gn:dem":1997,
    "gn:feature_class":"P",
    "gn:feature_code":"PPL",
    "gn:name":"Wangjia Taizi",
    "gn:population":0,
    "gn:timezone":"Asia/Shanghai",
    "iso:country":"CN",
    "name:zho_x_preferred":[
        "\u738b\u5bb6\u53f0\u5b50"
    ],
    "wof:name":"Wangjia Taizi",
    "wof:placetype":"locality"
},
  "geometry": {"coordinates":[101.259,38.5895],"type":"Point"}
}