{
  "type": "Feature",
  "properties": {
    "gn:admin1_code":"15.0",
    "gn:asciiname":"Shangou",
    "gn:country_code":"CN",
    "gn:dem":2660,
    "gn:feature_class":"P",
    "gn:feature_code":"PPL",
    "gn:name":"Shangou",
    "gn:population":0,
    "gn:timezone":"Asia/Shanghai",
    "iso:country":"CN",
    "name:und_x_variant":[
        "\u5c71\u6c9f"
    ],
    "wof:name":"Shangou",
    "wof:placetype":"locality"
},
  "geometry": {"coordinates":[104.22356000000001,34.41833],"type":"Point"}
}