{
  "type": "Feature",
  "properties": {
    "gn:admin1_code":"1.0",
    "gn:asciiname":"Qianjunling",
    "gn:country_code":"CN",
    "gn:dem":26,
    "gn:feature_class":"P",
    "gn:feature_code":"PPL",
    "gn:name":"Qianjunling",
    "gn:population":0,
    "gn:timezone":"Asia/Shanghai",
    "iso:country":"CN",
    "name:zho_x_preferred":[
        "\u5343\u519b\u5cad"
    ],
    "wof:name":"Qianjunling",
    "wof:placetype":"locality"
},
  "geometry": {"coordinates":[118.27656,31.09057],"type":"Point"}
}