{
  "type": "Feature",
  "properties": {
    "gn:admin1_code":"5.0",
    "gn:asciiname":"Wenzicun",
    "gn:country_code":"CN",
    "gn:dem":612,
    "gn:feature_class":"P",
    "gn:feature_code":"PPL",
    "gn:name":"Wenzicun",
    "gn:population":0,
    "gn:timezone":"Asia/Shanghai",
    "iso:country":"CN",
    "name:zho_x_preferred":[
        "\u6587\u5b57\u6751"
    ],
    "wof:name":"Wenzicun",
    "wof:placetype":"locality"
},
  "geometry": {"coordinates":[126.03646000000001,41.35112],"type":"Point"}
}