{
  "type": "Feature",
  "properties": {
    "gn:admin1_code":"32.0",
    "gn:asciiname":"Liumacao",
    "gn:country_code":"CN",
    "gn:dem":1578,
    "gn:feature_class":"P",
    "gn:feature_code":"PPL",
    "gn:name":"Liumacao",
    "gn:population":0,
    "gn:timezone":"Asia/Shanghai",
    "iso:country":"CN",
    "name:zho_x_preferred":[
        "\u6e9c\u9a6c\u69fd"
    ],
    "wof:name":"Liumacao",
    "wof:placetype":"locality"
},
  "geometry": {"coordinates":[103.08,28.9188],"type":"Point"}
}