{
  "type": "Feature",
  "properties": {
    "gn:admin1_code":"14.0",
    "gn:asciiname":"Sajia",
    "gn:country_code":"CN",
    "gn:dem":4643,
    "gn:feature_class":"P",
    "gn:feature_code":"PPLA3",
    "gn:name":"Sajia",
    "gn:population":0,
    "gn:timezone":"Asia/Urumqi",
    "iso:country":"CN",
    "name:bod_x_preferred":[
        "Sa\u2019gya"
    ],
    "name:und_x_variant":[
        "Sa\u2019gya",
        "Sakya G\u00f6mpa",
        "Sakya Gomba",
        "Sakya",
        "Sayka Gompa",
        "Sa-chia",
        "Sa-chia-tsung",
        "Sa\u2019gyaxoi"
    ],
    "name:zho_x_preferred":[
        "Sajia"
    ],
    "name:zho_x_variant":[
        "\u8428\u8fe6"
    ],
    "wof:name":"Sajia",
    "wof:placetype":"locality"
},
  "geometry": {"coordinates":[88.05,28.91667],"type":"Point"}
}