{
  "type": "Feature",
  "properties": {
    "gn:admin1_code":"14.0",
    "gn:asciiname":"Sajia",
    "gn:country_code":"CN",
    "gn:dem":4643,
    "gn:feature_class":"P",
    "gn:feature_code":"PPLA3",
    "gn:name":"Sajia",
    "gn:population":0,
    "gn:timezone":"Asia/Urumqi",
    "iso:country":"CN",
    "name:ara_x_preferred":[
        "\u062f\u064a\u0631 \u0633\u0627\u0643\u064a\u0627"
    ],
    "name:bod_x_preferred":[
        "Sa\u2019gya"
    ],
    "name:bod_x_variant":[
        "\u0f66\u0f0b\u0f66\u0f90\u0fb1\u0f0b\u0f51\u0f42\u0f7c\u0f53\u0f0d"
    ],
    "name:ces_x_preferred":[
        "Kl\u00e1\u0161ter Sakja"
    ],
    "name:deu_x_preferred":[
        "Sakya-Kloster"
    ],
    "name:hun_x_preferred":[
        "Szakja kolostor"
    ],
    "name:jpn_x_preferred":[
        "\u30b5\u30ad\u30e3\u5bfa"
    ],
    "name:nld_x_preferred":[
        "Sakya"
    ],
    "name:pol_x_preferred":[
        "Sakja"
    ],
    "name:por_x_preferred":[
        "Mosteiro Sakya"
    ],
    "name:rus_x_preferred":[
        "\u0421\u0430\u043a\u044c\u044f"
    ],
    "name:und_x_variant":[
        "Sakya G\u00f6mpa",
        "Sakya Gomba",
        "Sayka Gompa",
        "Sa-chia",
        "Sa-chia-tsung",
        "Sa\u2019gyaxoi"
    ],
    "name:zho_x_preferred":[
        "Sajia"
    ],
    "name:zho_x_variant":[
        "\u8428\u8fe6",
        "\u8428\u8fe6\u5bfa"
    ],
    "wof:name":"Sajia",
    "wof:placetype":"locality"
},
  "geometry": {"coordinates":[88.05,28.91667],"type":"Point"}
}