{
  "type": "Feature",
  "properties": {
    "gn:admin1_code":"14.0",
    "gn:asciiname":"Jiggyur",
    "gn:country_code":"CN",
    "gn:dem":5279,
    "gn:feature_class":"P",
    "gn:feature_code":"PPLF",
    "gn:name":"Jiggyur",
    "gn:population":0,
    "gn:timezone":"Asia/Urumqi",
    "iso:country":"CN",
    "name:bod_x_preferred":[
        "Jiggyur"
    ],
    "name:und_x_variant":[
        "Tongyicun"
    ],
    "name:zho_x_preferred":[
        "\u7edf\u4e00\u6751"
    ],
    "name:zho_x_variant":[
        "Longsang",
        "\u9f99\u6851"
    ],
    "wof:name":"Jiggyur",
    "wof:placetype":"locality"
},
  "geometry": {"coordinates":[89.40100000000002,30.601],"type":"Point"}
}