{
  "type": "Feature",
  "properties": {
    "gn:admin1_code":"32.0",
    "gn:asciiname":"Shihe",
    "gn:country_code":"CN",
    "gn:dem":647,
    "gn:feature_class":"P",
    "gn:feature_code":"PPL",
    "gn:name":"Shihe",
    "gn:population":0,
    "gn:timezone":"Asia/Shanghai",
    "iso:country":"CN",
    "name:zho_x_preferred":[
        "\u4e16\u548c"
    ],
    "wof:name":"Shihe",
    "wof:placetype":"locality"
},
  "geometry": {"coordinates":[104.74223000000001,28.63253],"type":"Point"}
}