{
  "type": "Feature",
  "properties": {
    "gn:admin1_code":"29.0",
    "gn:asciiname":"Weiwang",
    "gn:country_code":"CN",
    "gn:dem":1288,
    "gn:feature_class":"P",
    "gn:feature_code":"PPL",
    "gn:name":"Weiwang",
    "gn:population":0,
    "gn:timezone":"Asia/Shanghai",
    "iso:country":"CN",
    "name:zho_x_preferred":[
        "\u672a\u6c6a"
    ],
    "wof:name":"Weiwang",
    "wof:placetype":"locality"
},
  "geometry": {"coordinates":[104.199,24.5619],"type":"Point"}
}