{
  "type": "Feature",
  "properties": {
    "gn:admin1_code":"32.0",
    "gn:asciiname":"Puti",
    "gn:country_code":"CN",
    "gn:dem":2068,
    "gn:feature_class":"P",
    "gn:feature_code":"PPL",
    "gn:name":"Puti",
    "gn:population":0,
    "gn:timezone":"Asia/Shanghai",
    "iso:country":"CN",
    "name:zho_x_preferred":[
        "\u666e\u63d0"
    ],
    "wof:name":"Puti",
    "wof:placetype":"locality"
},
  "geometry": {"coordinates":[102.866,28.0419],"type":"Point"}
}