{
  "type": "Feature",
  "properties": {
    "gn:admin1_code":"26.0",
    "gn:asciiname":"Mianxiyao",
    "gn:country_code":"CN",
    "gn:dem":1642,
    "gn:feature_class":"P",
    "gn:feature_code":"PPL",
    "gn:name":"Mianxiyao",
    "gn:population":0,
    "gn:timezone":"Asia/Shanghai",
    "iso:country":"CN",
    "name:und_x_variant":[
        "\u9762\u897f\u7a91"
    ],
    "wof:name":"Mianxiyao",
    "wof:placetype":"locality"
},
  "geometry": {"coordinates":[107.92055000000001,34.02179],"type":"Point"}
}