{
  "type": "Feature",
  "properties": {
    "gn:admin1_code":"3.0",
    "gn:asciiname":"Maguping",
    "gn:country_code":"CN",
    "gn:dem":453,
    "gn:feature_class":"P",
    "gn:feature_code":"PPL",
    "gn:name":"Maguping",
    "gn:population":0,
    "gn:timezone":"Asia/Shanghai",
    "iso:country":"CN",
    "name:und_x_variant":[
        "\u9a6c\u726f\u576a"
    ],
    "wof:name":"Maguping",
    "wof:placetype":"locality"
},
  "geometry": {"coordinates":[115.24113,25.68443],"type":"Point"}
}