{
  "type": "Feature",
  "properties": {
    "gn:admin1_code":"25.0",
    "gn:asciiname":"Dahebei",
    "gn:country_code":"CN",
    "gn:dem":171,
    "gn:feature_class":"P",
    "gn:feature_code":"PPL",
    "gn:name":"Dahebei",
    "gn:population":0,
    "gn:timezone":"Asia/Shanghai",
    "iso:country":"CN",
    "name:zho_x_preferred":[
        "\u5927\u6cb3\u5317"
    ],
    "wof:name":"Dahebei",
    "wof:placetype":"locality"
},
  "geometry": {"coordinates":[120.82185,37.25471],"type":"Point"}
}