{
  "type": "Feature",
  "properties": {
    "gn:admin1_code":"2.0",
    "gn:asciiname":"Shangtangku",
    "gn:country_code":"CN",
    "gn:dem":1097,
    "gn:feature_class":"P",
    "gn:feature_code":"PPL",
    "gn:name":"Shangtangku",
    "gn:population":0,
    "gn:timezone":"Asia/Shanghai",
    "iso:country":"CN",
    "name:zho_x_preferred":[
        "\u4e0a\u5858\u5800"
    ],
    "wof:name":"Shangtangku",
    "wof:placetype":"locality"
},
  "geometry": {"coordinates":[119.30669,27.94873],"type":"Point"}
}