{
  "type": "Feature",
  "properties": {
    "gn:admin1_code":"32.0",
    "gn:asciiname":"Liyuan",
    "gn:country_code":"CN",
    "gn:dem":544,
    "gn:feature_class":"P",
    "gn:feature_code":"PPL",
    "gn:name":"Liyuan",
    "gn:population":0,
    "gn:timezone":"Asia/Shanghai",
    "iso:country":"CN",
    "name:ceb_x_preferred":[
        "Liyuan"
    ],
    "name:swe_x_preferred":[
        "Liyuan"
    ],
    "name:zho_x_preferred":[
        "\u68a8\u56ed"
    ],
    "wof:name":"Liyuan",
    "wof:placetype":"locality"
},
  "geometry": {"coordinates":[105.14100000000001,31.7532],"type":"Point"}
}