{
  "type": "Feature",
  "properties": {
    "gn:admin1_code":"29",
    "gn:asciiname":"Sachang",
    "gn:country_code":"CN",
    "gn:dem":1424,
    "gn:feature_class":"P",
    "gn:feature_code":"PPL",
    "gn:name":"Sachang",
    "gn:population":0,
    "gn:timezone":"Asia/Shanghai",
    "iso:country":"CN",
    "name:zho_x_preferred":[
        "\u6d12\u5382"
    ],
    "wof:name":"Sachang",
    "wof:placetype":"locality"
},
  "geometry": {"coordinates":[102.506,23.7259],"type":"Point"}
}